{
  "type": "Feature",
  "properties": {
    "iso:country":"DE",
    "sg:address":"Rommersdorfer Str. 61",
    "sg:city":"Bad Honnef",
    "sg:phone":"+49 2224/94800",
    "sg:postcode":"53604",
    "sg:province":"Nordrhein-Westfalen",
    "wof:name":"Harald Stich Steuerberatungs Gmbh",
    "wof:placetype":"venue"
},
  "geometry": {"coordinates":[7.2261991501,50.6495552063],"type":"Point"}
}