{
  "type": "Feature",
  "properties": {
    "iso:country":"DE",
    "sg:address":"An der Eiche 17",
    "sg:city":"Krumbach",
    "sg:phone":"+49 8282/61562",
    "sg:postcode":"86381",
    "sg:province":"Bayern",
    "wof:name":"Biohof Rupert Goldstein",
    "wof:placetype":"venue"
},
  "geometry": {"coordinates":[10.364784,48.272366],"type":"Point"}
}