{
  "type": "Feature",
  "properties": {
    "iso:country":"DE",
    "sg:address":"Hammerbrookstr. 83-90",
    "sg:city":"Hamburg",
    "sg:postcode":"20097",
    "sg:province":"Hamburg",
    "wof:name":"Vitaser Handels Gmbh",
    "wof:placetype":"venue"
},
  "geometry": {"coordinates":[10.0248832703,53.5455551147],"type":"Point"}
}