{
  "type": "Feature",
  "properties": {
    "iso:country":"DE",
    "sg:address":"Ottersrieder Str. 3",
    "sg:city":"Rohrbach",
    "sg:phone":"+49 8442/8534",
    "sg:postcode":"85296",
    "sg:province":"Bayern",
    "wof:name":"Johann Sch\u00f6nauer",
    "wof:placetype":"venue"
},
  "geometry": {"coordinates":[11.560858,48.613945],"type":"Point"}
}