{
  "type": "Feature",
  "properties": {
    "iso:country":"DE",
    "sg:address":"Ostring 42",
    "sg:city":"Gro\u00dfostheim",
    "sg:phone":"+49 6026/4768",
    "sg:postcode":"63762",
    "sg:province":"Bayern",
    "wof:name":"Loeffler & Co.",
    "wof:placetype":"venue"
},
  "geometry": {"coordinates":[9.0388069153,49.9380722046],"type":"Point"}
}