{
  "type": "Feature",
  "properties": {
    "iso:country":"DE",
    "sg:address":"Am Neuerhof 31",
    "sg:city":"Krefeld",
    "sg:phone":"+49 2151/71510",
    "sg:postcode":"47804",
    "sg:province":"Nordrhein-Westfalen",
    "wof:name":"Felten & Guilleaume Ag",
    "wof:placetype":"venue"
},
  "geometry": {"coordinates":[6.5425162315,51.3272323608],"type":"Point"}
}