{
  "type": "Feature",
  "properties": {
    "iso:country":"DE",
    "sg:address":"Liboristr 11-13",
    "sg:city":"M\u00fcnster",
    "sg:phone":"+49 251/661055",
    "sg:postcode":"48155",
    "sg:province":"Nordrhein-Westfalen",
    "wof:name":"G\u00fcnther Dieckmann Gmbh & Co",
    "wof:placetype":"venue"
},
  "geometry": {"coordinates":[7.65406,51.954323],"type":"Point"}
}