{
  "type": "Feature",
  "properties": {
    "iso:country":"DE",
    "sg:address":"Valleystr. 28",
    "sg:city":"M\u00fcnchen",
    "sg:phone":"+49 89/7212224",
    "sg:postcode":"81371",
    "sg:province":"Bayern",
    "wof:name":"P. Varbanova",
    "wof:placetype":"venue"
},
  "geometry": {"coordinates":[11.5479831696,48.117603302],"type":"Point"}
}