{
  "type": "Feature",
  "properties": {
    "iso:country":"DE",
    "sg:address":"D\u00fcsternbrooker Weg 20",
    "sg:city":"Kiel",
    "sg:phone":"+49 431/5973927",
    "sg:postcode":"24105",
    "sg:province":"Schleswig-Holstein",
    "wof:name":"Aquarium Kiel",
    "wof:placetype":"venue"
},
  "geometry": {"coordinates":[10.147822,54.329723],"type":"Point"}
}