{
  "type": "Feature",
  "properties": {
    "iso:country":"DE",
    "sg:address":"Georgswerder Bogen 13",
    "sg:city":"Hamburg",
    "sg:phone":"+49 40/75492577",
    "sg:postcode":"21109",
    "sg:province":"Hamburg",
    "wof:name":"We-ge Technische Handelsgesellschaft Mbh",
    "wof:placetype":"venue"
},
  "geometry": {"coordinates":[10.022804,53.519367],"type":"Point"}
}