{
  "type": "Feature",
  "properties": {
    "iso:country":"DE",
    "sg:address":"Poststr. 2",
    "sg:city":"Espelkamp",
    "sg:phone":"+49 5743/1386",
    "sg:postcode":"32339",
    "sg:province":"Nordrhein-Westfalen",
    "wof:name":"Karl-heinz Finke",
    "wof:placetype":"venue"
},
  "geometry": {"coordinates":[8.643215,52.348316],"type":"Point"}
}