{
  "type": "Feature",
  "properties": {
    "iso:country":"DE",
    "sg:address":"An der Fichte 3",
    "sg:city":"Eisenberg",
    "sg:phone":"+49 36691/51125",
    "sg:postcode":"07607",
    "sg:province":"Th\u00fcringen",
    "wof:name":"H. Ziegler Ingenieur",
    "wof:placetype":"venue"
},
  "geometry": {"coordinates":[11.9030818939,50.9613265991],"type":"Point"}
}