{
  "type": "Feature",
  "properties": {
    "iso:country":"DE",
    "sg:address":"Hausener Str. 5",
    "sg:city":"Munderkingen",
    "sg:phone":"+49 7393/917222",
    "sg:postcode":"89597",
    "sg:province":"Baden-W\u00fcrttemberg",
    "wof:name":"Max Grab E. Kfm.",
    "wof:placetype":"venue"
},
  "geometry": {"coordinates":[9.642731,48.230507],"type":"Point"}
}