{
  "type": "Feature",
  "properties": {
    "iso:country":"DE",
    "sg:address":"R\u00e4hnitzgasse 8",
    "sg:city":"Dresden",
    "sg:phone":"+49 351/8041456",
    "sg:postcode":"01097",
    "sg:province":"Sachsen",
    "wof:name":"Galerie R\u00e4hnitzgasse Der Landeshauptstadt Dresden",
    "wof:placetype":"venue"
},
  "geometry": {"coordinates":[13.740907,51.059174],"type":"Point"}
}