{
  "type": "Feature",
  "properties": {
    "iso:country":"DE",
    "sg:address":"St\u00fcrmleslochweg 6",
    "sg:city":"Bad Wildbad",
    "sg:phone":"+49 7081/8879",
    "sg:postcode":"75323",
    "sg:province":"Baden-W\u00fcrttemberg",
    "wof:name":"H. Rapp",
    "wof:placetype":"venue"
},
  "geometry": {"coordinates":[8.5413579941,48.7330474854],"type":"Point"}
}