{
  "type": "Feature",
  "properties": {
    "iso:country":"DE",
    "sg:address":"Wasserfallstr. 13",
    "sg:city":"Rodgau",
    "sg:phone":"+49 6106/3770",
    "sg:postcode":"63110",
    "sg:province":"Hessen",
    "wof:name":"Willi Corinth",
    "wof:placetype":"venue"
},
  "geometry": {"coordinates":[8.8871507645,50.0331916809],"type":"Point"}
}