{
  "type": "Feature",
  "properties": {
    "iso:country":"DE",
    "sg:address":"Fabrikstr. 11a",
    "sg:city":"Sch\u00f6ningen",
    "sg:phone":"+49 5352/2691",
    "sg:postcode":"38364",
    "sg:province":"Niedersachsen",
    "wof:name":"Andreas H\u00e4nel",
    "wof:placetype":"venue"
},
  "geometry": {"coordinates":[10.978469,52.137016],"type":"Point"}
}