{
  "type": "Feature",
  "properties": {
    "iso:country":"DE",
    "sg:address":"Ludwigshafener Str. 10",
    "sg:city":"Mutterstadt",
    "sg:phone":"+49 6234/7565",
    "sg:postcode":"67112",
    "sg:province":"Rheinland-Pfalz",
    "wof:name":"Kronen-apotheke",
    "wof:placetype":"venue"
},
  "geometry": {"coordinates":[8.356178,49.442665],"type":"Point"}
}