{
  "type": "Feature",
  "properties": {
    "iso:country":"DE",
    "sg:address":"Farrenbracken 3",
    "sg:city":"Remscheid",
    "sg:phone":"+49 2191/22406",
    "sg:postcode":"42855",
    "sg:province":"Nordrhein-Westfalen",
    "wof:name":"Wegerhoff",
    "wof:placetype":"venue"
},
  "geometry": {"coordinates":[7.199244,51.202076],"type":"Point"}
}