{
  "type": "Feature",
  "properties": {
    "iso:country":"DE",
    "sg:address":"Friedr-Wilh-Weber-Str 32",
    "sg:city":"Schwandorf",
    "sg:phone":"+49 9431/20555",
    "sg:postcode":"92421",
    "sg:province":"Bayern",
    "wof:name":"Hans Liepelt",
    "wof:placetype":"venue"
},
  "geometry": {"coordinates":[12.115367,49.322124],"type":"Point"}
}