{
  "type": "Feature",
  "properties": {
    "iso:country":"DE",
    "sg:address":"Steinweg 38",
    "sg:city":"Montabaur",
    "sg:phone":"+49 2602/12978",
    "sg:postcode":"56410",
    "sg:province":"Rheinland-Pfalz",
    "wof:name":"Stein-apotheke Inh. Dr. Massud Nayeri",
    "wof:placetype":"venue"
},
  "geometry": {"coordinates":[7.828431,50.436226],"type":"Point"}
}