{
  "type": "Feature",
  "properties": {
    "iso:country":"DE",
    "sg:address":"Borgfelder Str. 32-34",
    "sg:city":"Hamburg",
    "sg:phone":"+49 40/372202",
    "sg:postcode":"20537",
    "sg:province":"Hamburg",
    "wof:name":"Dpolg-service- Und Betriebs Gmbh",
    "wof:placetype":"venue"
},
  "geometry": {"coordinates":[10.0312614441,53.554233551],"type":"Point"}
}