{
  "type": "Feature",
  "properties": {
    "iso:country":"DE",
    "sg:address":"Auf der Papagei 2",
    "sg:city":"Siegburg",
    "sg:phone":"+49 2241/55644",
    "sg:postcode":"53721",
    "sg:province":"Nordrhein-Westfalen",
    "wof:name":"Kastanienhof",
    "wof:placetype":"venue"
},
  "geometry": {"coordinates":[7.2180399895,50.7981452942],"type":"Point"}
}