{
  "type": "Feature",
  "properties": {
    "iso:country":"DE",
    "sg:address":"Langgasse 7",
    "sg:city":"Bad Wimpfen",
    "sg:phone":"+49 7063/970028",
    "sg:postcode":"74206",
    "sg:province":"Baden-W\u00fcrttemberg",
    "wof:name":"Aes \u00c4rzteservice Schwaben Gmbh",
    "wof:placetype":"venue"
},
  "geometry": {"coordinates":[9.161683,49.229172],"type":"Point"}
}