{
  "type": "Feature",
  "properties": {
    "iso:country":"DE",
    "sg:address":"Bauernsteinstr. 58",
    "sg:city":"Bornstedt",
    "sg:phone":"+49 3475/638869",
    "sg:postcode":"06295",
    "sg:province":"Sachsen-Anhalt",
    "wof:name":"Gerhard Volkland",
    "wof:placetype":"venue"
},
  "geometry": {"coordinates":[11.482545,51.480179],"type":"Point"}
}