{
  "type": "Feature",
  "properties": {
    "iso:country":"DE",
    "sg:address":"Ludwigstr. 33",
    "sg:city":"Kaufbeuren",
    "sg:phone":"+49 8341/2691",
    "sg:postcode":"87600",
    "sg:province":"Bayern",
    "wof:name":"Michael Merk",
    "wof:placetype":"venue"
},
  "geometry": {"coordinates":[10.6209716797,47.8786239624],"type":"Point"}
}