{
  "type": "Feature",
  "properties": {
    "iso:country":"DE",
    "sg:address":"Turmstr. 1",
    "sg:city":"Neudenau",
    "sg:phone":"+49 6264/573",
    "sg:postcode":"74861",
    "sg:province":"Baden-W\u00fcrttemberg",
    "wof:name":"Josef Scheuermann Ingenieur",
    "wof:placetype":"venue"
},
  "geometry": {"coordinates":[9.2719078064,49.2933120728],"type":"Point"}
}