{
  "type": "Feature",
  "properties": {
    "iso:country":"DE",
    "sg:address":"Weinstr. 13",
    "sg:city":"Bad D\u00fcrkheim",
    "sg:phone":"+49 6322/66848",
    "sg:postcode":"67098",
    "sg:province":"Rheinland-Pfalz",
    "wof:name":"Peter Wagner",
    "wof:placetype":"venue"
},
  "geometry": {"coordinates":[8.1768665314,49.4766273499],"type":"Point"}
}