{
  "type": "Feature",
  "properties": {
    "iso:country":"DE",
    "sg:address":"Melanchthonstr. 45",
    "sg:city":"Gro\u00dfr\u00f6hrsdorf",
    "sg:phone":"+49 35952/48650",
    "sg:postcode":"01900",
    "sg:province":"Sachsen",
    "wof:name":"Berger Band Gmbh & Co.",
    "wof:placetype":"venue"
},
  "geometry": {"coordinates":[14.021899,51.1423],"type":"Point"}
}