{
  "type": "Feature",
  "properties": {
    "iso:country":"DE",
    "sg:address":"Postfach 101240",
    "sg:city":"Bremerhaven",
    "sg:phone":"+49 471/3920",
    "sg:postcode":"27512",
    "sg:province":"Bremen",
    "wof:name":"Schichau Seebeckwerft Ag",
    "wof:placetype":"venue"
},
  "geometry": {"coordinates":[8.5781202316,53.5418586731],"type":"Point"}
}