{
  "type": "Feature",
  "properties": {
    "iso:country":"DE",
    "sg:address":"Transitstr. 8 a",
    "sg:city":"M\u00f6nchhagen",
    "sg:postcode":"18182",
    "sg:province":"Mecklenburg-Vorpommern",
    "wof:name":"W & K Wohn-und Industrie- Holzbau Gmbh",
    "wof:placetype":"venue"
},
  "geometry": {"coordinates":[12.2274932861,54.1480789185],"type":"Point"}
}