{
  "type": "Feature",
  "properties": {
    "iso:country":"DE",
    "sg:address":"Wasbeker Str. 324",
    "sg:city":"Neum\u00fcnster",
    "sg:phone":"+49 4321/60124",
    "sg:postcode":"24537",
    "sg:province":"Schleswig-Holstein",
    "wof:name":"Lebensmittelinstitut Kin E. V.",
    "wof:placetype":"venue"
},
  "geometry": {"coordinates":[9.9428443909,54.0692901611],"type":"Point"}
}