{
  "type": "Feature",
  "properties": {
    "iso:country":"DE",
    "sg:address":"Homberger Strasse 115",
    "sg:city":"Moers",
    "sg:phone":"+49 2841/50116",
    "sg:postcode":"47441",
    "sg:province":"Nordrhein-Westfalen",
    "wof:name":"Kr\u00fcger Und Leiss Gmbh",
    "wof:placetype":"venue"
},
  "geometry": {"coordinates":[6.653393,51.442829],"type":"Point"}
}