{
  "type": "Feature",
  "properties": {
    "iso:country":"DE",
    "sg:address":"Robert-Blum-Str. 17",
    "sg:city":"Dresden",
    "sg:phone":"+49 351/8042803",
    "sg:postcode":"01097",
    "sg:province":"Sachsen",
    "wof:name":"K. Ay",
    "wof:placetype":"venue"
},
  "geometry": {"coordinates":[13.7372,51.062538],"type":"Point"}
}