{
  "type": "Feature",
  "properties": {
    "iso:country":"DE",
    "sg:address":"Hohenzollernstr. 37",
    "sg:city":"Ludwigshafen",
    "sg:phone":"+49 621/525373",
    "sg:postcode":"67063",
    "sg:province":"Rheinland-Pfalz",
    "wof:name":"Pizzeria D Antonio",
    "wof:placetype":"venue"
},
  "geometry": {"coordinates":[8.423116684,49.4899711609],"type":"Point"}
}