{
  "type": "Feature",
  "properties": {
    "iso:country":"DE",
    "sg:address":"Am Gro\u00dfen Kampe 12",
    "sg:city":"Damme",
    "sg:phone":"+49 5491/7670",
    "sg:postcode":"49401",
    "sg:province":"Niedersachsen",
    "wof:name":"Gastst\u00e4tte Frank Deters",
    "wof:placetype":"venue"
},
  "geometry": {"coordinates":[8.2812757492,52.568359375],"type":"Point"}
}