{
  "type": "Feature",
  "properties": {
    "iso:country":"DE",
    "sg:address":"Konrad-Adenauer-Str. 40",
    "sg:city":"Rheinbach",
    "sg:phone":"+49 2225/3639",
    "sg:postcode":"53359",
    "sg:province":"Nordrhein-Westfalen",
    "wof:name":"Restaurant Dorfschenke",
    "wof:placetype":"venue"
},
  "geometry": {"coordinates":[6.987912178,50.647731781],"type":"Point"}
}