{
  "type": "Feature",
  "properties": {
    "iso:country":"DE",
    "sg:address":"Dobritzer Str. 12",
    "sg:city":"Nedlitz",
    "sg:phone":"+49 39243/7023",
    "sg:postcode":"39264",
    "sg:province":"Sachsen-Anhalt",
    "wof:name":"Capra Beteiligungs Gmbh",
    "wof:placetype":"venue"
},
  "geometry": {"coordinates":[12.243597,52.07505],"type":"Point"}
}