{
  "type": "Feature",
  "properties": {
    "iso:country":"DE",
    "sg:address":"Brunnenstr. 4",
    "sg:city":"Ihringen",
    "sg:phone":"+49 7668/7257",
    "sg:postcode":"79241",
    "sg:province":"Baden-W\u00fcrttemberg",
    "wof:name":"J. Mattm\u00fcller",
    "wof:placetype":"venue"
},
  "geometry": {"coordinates":[7.6465139389,48.0460472107],"type":"Point"}
}