{
  "type": "Feature",
  "properties": {
    "iso:country":"DE",
    "sg:address":"Im Weidig 4",
    "sg:city":"Obernburg",
    "sg:phone":"+49 6022/5030",
    "sg:postcode":"63785",
    "sg:province":"Bayern",
    "wof:name":"Verwaltungsgesellschaft Walter Reis Gmbh",
    "wof:placetype":"venue"
},
  "geometry": {"coordinates":[9.130053,49.832165],"type":"Point"}
}