{
  "type": "Feature",
  "properties": {
    "iso:country":"DE",
    "sg:address":"Finstere Gasse 3",
    "sg:city":"Markgr\u00f6ningen",
    "sg:phone":"+49 7145/13276",
    "sg:postcode":"71706",
    "sg:province":"Baden-W\u00fcrttemberg",
    "wof:name":"Stadtarchiv",
    "wof:placetype":"venue"
},
  "geometry": {"coordinates":[9.080086,48.9048],"type":"Point"}
}