{
  "type": "Feature",
  "properties": {
    "iso:country":"DE",
    "sg:address":"An der Dohlm\u00fchle",
    "sg:city":"Flonheim",
    "sg:phone":"+49 6734/941041",
    "sg:postcode":"55237",
    "sg:province":"Rheinland-Pfalz",
    "wof:name":"Klaus-dieter St\u00fctz",
    "wof:placetype":"venue"
},
  "geometry": {"coordinates":[8.0428495407,49.7897148132],"type":"Point"}
}