{
  "type": "Feature",
  "properties": {
    "iso:country":"DE",
    "sg:address":"Hasenfleet 3",
    "sg:city":"Oberndorf",
    "sg:phone":"+49 4772/296",
    "sg:postcode":"21787",
    "sg:province":"Niedersachsen",
    "wof:name":"Molkerei Hasenfleth Eg",
    "wof:placetype":"venue"
},
  "geometry": {"coordinates":[9.187210083,53.7631721497],"type":"Point"}
}