{
  "type": "Feature",
  "properties": {
    "iso:country":"DE",
    "sg:address":"Im Br\u00f6ltal 103",
    "sg:city":"Hennef",
    "sg:phone":"+49 2242/6919",
    "sg:postcode":"53773",
    "sg:province":"Nordrhein-Westfalen",
    "wof:name":"Wilfried Knott",
    "wof:placetype":"venue"
},
  "geometry": {"coordinates":[7.327235,50.790771],"type":"Point"}
}