{
  "type": "Feature",
  "properties": {
    "iso:country":"DE",
    "sg:address":"Walchenseeplatz 5",
    "sg:city":"M\u00fcnchen",
    "sg:phone":"+49 89/6929127",
    "sg:postcode":"81539",
    "sg:province":"Bayern",
    "wof:name":"A. Angermayr Steinmetz",
    "wof:placetype":"venue"
},
  "geometry": {"coordinates":[11.5846939087,48.1126976013],"type":"Point"}
}