{
  "type": "Feature",
  "properties": {
    "iso:country":"DE",
    "sg:address":"Mittelstr. 19",
    "sg:city":"Dahlem",
    "sg:phone":"+49 2447/1469",
    "sg:postcode":"53949",
    "sg:province":"Nordrhein-Westfalen",
    "wof:name":"Siegbert Klinkhammer",
    "wof:placetype":"venue"
},
  "geometry": {"coordinates":[6.559853,50.414711],"type":"Point"}
}