{
  "type": "Feature",
  "properties": {
    "iso:country":"DE",
    "sg:address":"Ludwig-Erhardt-Str 1",
    "sg:city":"Wertheim",
    "sg:phone":"+49 9342/8880",
    "sg:postcode":"97877",
    "sg:province":"Baden-W\u00fcrttemberg",
    "wof:name":"Profiltec Gmbh",
    "wof:placetype":"venue"
},
  "geometry": {"coordinates":[9.491646,49.758911],"type":"Point"}
}