{
  "type": "Feature",
  "properties": {
    "iso:country":"DE",
    "sg:address":"Alte Pforzheimer Str. 4",
    "sg:city":"Wurmberg",
    "sg:phone":"+49 7044/940800",
    "sg:postcode":"75449",
    "sg:province":"Baden-W\u00fcrttemberg",
    "wof:name":"Michael Britsch Gmbh",
    "wof:placetype":"venue"
},
  "geometry": {"coordinates":[8.809213,48.872852],"type":"Point"}
}