{
  "type": "Feature",
  "properties": {
    "iso:country":"DE",
    "sg:address":"Hamannplatz 28",
    "sg:city":"M\u00fcnster",
    "sg:phone":"+49 251/246948",
    "sg:postcode":"48157",
    "sg:province":"Nordrhein-Westfalen",
    "wof:name":"A. Aschhoff",
    "wof:placetype":"venue"
},
  "geometry": {"coordinates":[7.648458004,51.9932594299],"type":"Point"}
}