{
  "type": "Feature",
  "properties": {
    "iso:country":"DE",
    "sg:address":"Fasanenweg 13",
    "sg:city":"Starnberg",
    "sg:postcode":"82319",
    "sg:province":"Bayern",
    "wof:name":"E. Vetter",
    "wof:placetype":"venue"
},
  "geometry": {"coordinates":[11.3525133133,48.0154075623],"type":"Point"}
}