{
  "type": "Feature",
  "properties": {
    "iso:country":"DE",
    "sg:address":"Stra\u00dfen 85",
    "sg:city":"Bergisch Gladbach",
    "sg:phone":"+49 2204/82908",
    "sg:postcode":"51429",
    "sg:province":"Nordrhein-Westfalen",
    "wof:name":"Katharina C\u00fcrten",
    "wof:placetype":"venue"
},
  "geometry": {"coordinates":[7.1927552223,50.987071991],"type":"Point"}
}