{
  "type": "Feature",
  "properties": {
    "iso:country":"DE",
    "sg:address":"T\u00f6nisheider Str. 19",
    "sg:city":"W\u00fclfrath",
    "sg:phone":"+49 2058/4050",
    "sg:postcode":"42489",
    "sg:province":"Nordrhein-Westfalen",
    "wof:name":"Rilusolar Gmbh",
    "wof:placetype":"venue"
},
  "geometry": {"coordinates":[7.043627,51.286541],"type":"Point"}
}