{
  "type": "Feature",
  "properties": {
    "iso:country":"DE",
    "sg:address":"Heinrich-Wassermann-Str. 14",
    "sg:city":"B\u00fcddenstedt",
    "sg:phone":"+49 5352/6810",
    "sg:postcode":"38372",
    "sg:province":"Niedersachsen",
    "wof:name":"Bruno Eckert",
    "wof:placetype":"venue"
},
  "geometry": {"coordinates":[11.016408,52.172226],"type":"Point"}
}