{
  "type": "Feature",
  "properties": {
    "iso:country":"DE",
    "sg:address":"Heuweiler Weg 16",
    "sg:city":"Gundelfingen",
    "sg:phone":"+49 761/500669",
    "sg:postcode":"79194",
    "sg:province":"Baden-W\u00fcrttemberg",
    "wof:name":"Alfred Unm\u00fc\u00dfig Architekt",
    "wof:placetype":"venue"
},
  "geometry": {"coordinates":[7.879123,48.034004],"type":"Point"}
}