{
  "type": "Feature",
  "properties": {
    "iso:country":"DE",
    "sg:address":"Hauptstr. 107",
    "sg:city":"Berlin",
    "sg:phone":"+49 30/7812033",
    "sg:postcode":"10827",
    "sg:province":"Berlin",
    "wof:name":"Petra Schlossarczyk Rechtsanw\u00e4ltin",
    "wof:placetype":"venue"
},
  "geometry": {"coordinates":[13.3474693298,52.4808578491],"type":"Point"}
}