{
  "type": "Feature",
  "properties": {
    "iso:country":"DE",
    "sg:address":"Lademannbogen 27",
    "sg:city":"Hamburg",
    "sg:postcode":"22339",
    "sg:province":"Hamburg",
    "wof:name":"Prv Planradiatoren Vertriebsges. Mbh",
    "wof:placetype":"venue"
},
  "geometry": {"coordinates":[10.0352220535,53.6454391479],"type":"Point"}
}