{
  "type": "Feature",
  "properties": {
    "iso:country":"DE",
    "sg:address":"Bickenstr. 11",
    "sg:city":"Villingen-Schwenningen",
    "sg:phone":"+49 7721/53053",
    "sg:postcode":"78050",
    "sg:province":"Baden-W\u00fcrttemberg",
    "wof:name":"Hock-vogt Kg",
    "wof:placetype":"venue"
},
  "geometry": {"coordinates":[8.4604730606,48.0598335266],"type":"Point"}
}