{
  "type": "Feature",
  "properties": {
    "iso:country":"DE",
    "sg:address":"Wagnerstr. 34",
    "sg:city":"M\u00f6glingen",
    "sg:phone":"+49 7141/48081",
    "sg:postcode":"71696",
    "sg:province":"Baden-W\u00fcrttemberg",
    "wof:name":"Berthold Potz Steuerberater",
    "wof:placetype":"venue"
},
  "geometry": {"coordinates":[9.1256933212,48.8850059509],"type":"Point"}
}