{
  "type": "Feature",
  "properties": {
    "iso:country":"DE",
    "sg:address":"Rumohrtalstr. 87",
    "sg:city":"Holzminden",
    "sg:phone":"+49 5531/4813",
    "sg:postcode":"37603",
    "sg:province":"Niedersachsen",
    "wof:name":"Walter Kumlehn",
    "wof:placetype":"venue"
},
  "geometry": {"coordinates":[9.472905,51.812363],"type":"Point"}
}