{
  "type": "Feature",
  "properties": {
    "iso:country":"DE",
    "sg:address":"Bosselmannstr. 8",
    "sg:city":"Schwerin",
    "sg:phone":"+49 385/3260751",
    "sg:postcode":"19063",
    "sg:province":"Mecklenburg-Vorpommern",
    "wof:name":"Egon Kluth",
    "wof:placetype":"venue"
},
  "geometry": {"coordinates":[11.44879,53.59906],"type":"Point"}
}