{
  "type": "Feature",
  "properties": {
    "iso:country":"DE",
    "sg:address":"Hauptstr. 48",
    "sg:city":"M\u00f6mlingen",
    "sg:postcode":"63853",
    "sg:province":"Bayern",
    "wof:name":"Anton Schlecker",
    "wof:placetype":"venue"
},
  "geometry": {"coordinates":[9.085552,49.857422],"type":"Point"}
}