{
  "type": "Feature",
  "properties": {
    "iso:country":"DE",
    "sg:address":"Merschwiese 32",
    "sg:city":"Senden",
    "sg:phone":"+49 2597/98333",
    "sg:postcode":"48308",
    "sg:province":"Nordrhein-Westfalen",
    "wof:name":"Werbemittel, Streuartikel, Werbegeschenke",
    "wof:placetype":"venue"
},
  "geometry": {"coordinates":[7.491115,51.866219],"type":"Point"}
}