{
  "type": "Feature",
  "properties": {
    "iso:country":"DE",
    "sg:address":"Bahnhofstr. 1",
    "sg:city":"Garmisch-Partenkirchen",
    "sg:phone":"+49 8821/3042",
    "sg:postcode":"82467",
    "sg:province":"Bayern",
    "wof:name":"Agnes H\u00e4nsler",
    "wof:placetype":"venue"
},
  "geometry": {"coordinates":[11.1042718887,47.4934501648],"type":"Point"}
}