{
  "type": "Feature",
  "properties": {
    "iso:country":"DE",
    "sg:address":"L\u00f6nsweg 38",
    "sg:city":"Kirchlengern",
    "sg:postcode":"32278",
    "sg:province":"Nordrhein-Westfalen",
    "wof:name":"Icr Unternehmensberatung Gmbh",
    "wof:placetype":"venue"
},
  "geometry": {"coordinates":[8.647989,52.197025],"type":"Point"}
}