{
  "type": "Feature",
  "properties": {
    "iso:country":"DE",
    "sg:address":"Steinstr. 8",
    "sg:city":"Aurachtal",
    "sg:phone":"+49 9132/8752",
    "sg:postcode":"91086",
    "sg:province":"Bayern",
    "wof:name":"Sixtus Maier",
    "wof:placetype":"venue"
},
  "geometry": {"coordinates":[10.820435524,49.577091217],"type":"Point"}
}