{
  "type": "Feature",
  "properties": {
    "iso:country":"DE",
    "sg:address":"Bl\u00f6daustr. 15",
    "sg:city":"Nordhausen",
    "sg:phone":"+49 3631/896850",
    "sg:postcode":"99734",
    "sg:province":"Th\u00fcringen",
    "wof:name":"Gerhard Rische",
    "wof:placetype":"venue"
},
  "geometry": {"coordinates":[10.8036241531,51.5013542175],"type":"Point"}
}