{
  "type": "Feature",
  "properties": {
    "iso:country":"DE",
    "sg:address":"Isamaninger Str. 105",
    "sg:city":"M\u00fcnchen",
    "sg:phone":"+49 89/92590",
    "sg:postcode":"81675",
    "sg:province":"Bayern",
    "wof:name":"Togal Ag",
    "wof:placetype":"venue"
},
  "geometry": {"coordinates":[11.605064,48.148071],"type":"Point"}
}