{
  "type": "Feature",
  "properties": {
    "iso:country":"DE",
    "sg:address":"Suhlawiesen 23",
    "sg:city":"Landolfshausen",
    "sg:phone":"+49 5507/2652",
    "sg:postcode":"37136",
    "sg:province":"Niedersachsen",
    "wof:name":"B & L Sanit\u00e4r-heizung- Und Baubedarf Gross- Und Einzel-",
    "wof:placetype":"venue"
},
  "geometry": {"coordinates":[10.1023330688,51.536945343],"type":"Point"}
}