{
  "type": "Feature",
  "properties": {
    "iso:country":"DE",
    "sg:address":"Liegnitzer Str 15",
    "sg:city":"Berlin",
    "sg:phone":"+49 30/6188845",
    "sg:postcode":"10999",
    "sg:province":"Berlin",
    "wof:name":"World Precision Instruments Harry Fein",
    "wof:placetype":"venue"
},
  "geometry": {"coordinates":[13.434479,52.493599],"type":"Point"}
}