{
  "type": "Feature",
  "properties": {
    "iso:country":"DE",
    "sg:address":"Margaretenstr. 31 c",
    "sg:city":"Solingen",
    "sg:phone":"+49 212/546254",
    "sg:postcode":"42651",
    "sg:province":"Nordrhein-Westfalen",
    "wof:name":"Runkel Gmbh Planungs- Und Ingenieurb\u00fcro",
    "wof:placetype":"venue"
},
  "geometry": {"coordinates":[7.0955858231,51.181427002],"type":"Point"}
}