{
  "type": "Feature",
  "properties": {
    "iso:country":"DE",
    "sg:address":"Luitpoldstr. 4",
    "sg:city":"Kitzingen",
    "sg:phone":"+49 9321/23600",
    "sg:postcode":"97318",
    "sg:province":"Bayern",
    "wof:name":"Frankonia Augenoptik Gerald Z\u00f6rner",
    "wof:placetype":"venue"
},
  "geometry": {"coordinates":[10.1602926254,49.7373046875],"type":"Point"}
}