{
  "type": "Feature",
  "properties": {
    "iso:country":"DE",
    "sg:address":"Knesebeckstr. 8a",
    "sg:city":"Berlin",
    "sg:phone":"+49 30/8325008",
    "sg:postcode":"12205",
    "sg:province":"Berlin",
    "wof:name":"Eckard Lullies Rechtsanwalt",
    "wof:placetype":"venue"
},
  "geometry": {"coordinates":[13.2926721573,52.4444465637],"type":"Point"}
}