{
  "type": "Feature",
  "properties": {
    "iso:country":"DE",
    "sg:address":"Weinstr. 22",
    "sg:city":"Sulzburg",
    "sg:phone":"+49 7634/8954",
    "sg:postcode":"79295",
    "sg:province":"Baden-W\u00fcrttemberg",
    "wof:name":"Fritz Engler-f\u00fcsslin Weinanbau",
    "wof:placetype":"venue"
},
  "geometry": {"coordinates":[7.6837148666,47.8423080444],"type":"Point"}
}