{
  "type": "Feature",
  "properties": {
    "iso:country":"DE",
    "sg:address":"Stadtmauer 37",
    "sg:city":"Friedberg",
    "sg:phone":"+49 821/6089926",
    "sg:postcode":"86316",
    "sg:province":"Bayern",
    "wof:name":"Novaimages",
    "wof:placetype":"venue"
},
  "geometry": {"coordinates":[10.976975,48.355457],"type":"Point"}
}