{
  "type": "Feature",
  "properties": {
    "iso:country":"DE",
    "sg:address":"Immermannstr. 11",
    "sg:city":"Witten",
    "sg:phone":"+49 2302/61878",
    "sg:postcode":"58453",
    "sg:province":"Nordrhein-Westfalen",
    "wof:name":"Margot Helfenbein",
    "wof:placetype":"venue"
},
  "geometry": {"coordinates":[7.370262146,51.4479064941],"type":"Point"}
}