{
  "type": "Feature",
  "properties": {
    "iso:country":"DE",
    "sg:address":"Sonsbecker Str. 2",
    "sg:city":"Uedem",
    "sg:phone":"+49 2825/1673",
    "sg:postcode":"47589",
    "sg:province":"Nordrhein-Westfalen",
    "wof:name":"Karl-heinz Greeven",
    "wof:placetype":"venue"
},
  "geometry": {"coordinates":[6.327976,51.64666],"type":"Point"}
}