{
  "type": "Feature",
  "properties": {
    "iso:country":"DE",
    "sg:address":"Eickhoffweg 5",
    "sg:city":"Hamburg",
    "sg:phone":"+49 40/6564667",
    "sg:postcode":"22041",
    "sg:province":"Hamburg",
    "wof:name":"Benno Krause Architekt",
    "wof:placetype":"venue"
},
  "geometry": {"coordinates":[10.092956,53.577744],"type":"Point"}
}