{
  "type": "Feature",
  "properties": {
    "iso:country":"DE",
    "sg:address":"Auf den Steinen 18",
    "sg:city":"Ense",
    "sg:phone":"+49 2938/97770",
    "sg:postcode":"59469",
    "sg:province":"Nordrhein-Westfalen",
    "wof:name":"Rms Ruhr-m\u00f6hne- Stahlhandel Gmbh",
    "wof:placetype":"venue"
},
  "geometry": {"coordinates":[8.001959,51.490913],"type":"Point"}
}