{
  "type": "Feature",
  "properties": {
    "iso:country":"DE",
    "sg:address":"Friedrichstr. 4",
    "sg:city":"Viernheim",
    "sg:phone":"+49 6204/2136",
    "sg:postcode":"68519",
    "sg:province":"Hessen",
    "wof:name":"Heinrich Herschel",
    "wof:placetype":"venue"
},
  "geometry": {"coordinates":[8.578199,49.542408],"type":"Point"}
}