{
  "type": "Feature",
  "properties": {
    "iso:country":"DE",
    "sg:address":"Bildstr. 42",
    "sg:city":"Collenberg",
    "sg:phone":"+49 9376/1460",
    "sg:postcode":"97903",
    "sg:province":"Bayern",
    "wof:name":"Babyland Liliput Die Gro\u00dfe Welt Der Kleinen",
    "wof:placetype":"venue"
},
  "geometry": {"coordinates":[9.3282194138,49.7717323303],"type":"Point"}
}