{
  "type": "Feature",
  "properties": {
    "iso:country":"DE",
    "sg:address":"Heinsestr. 2-4",
    "sg:city":"Aschaffenburg",
    "sg:phone":"+49 6021/22591",
    "sg:postcode":"63739",
    "sg:province":"Bayern",
    "wof:name":"Ludit-textil Gmbh",
    "wof:placetype":"venue"
},
  "geometry": {"coordinates":[9.1488685608,49.9776191711],"type":"Point"}
}