{
  "type": "Feature",
  "properties": {
    "iso:country":"DE",
    "sg:address":"Lissinger Str. 41",
    "sg:city":"Gerolstein",
    "sg:phone":"+49 6591/4246",
    "sg:postcode":"54568",
    "sg:province":"Rheinland-Pfalz",
    "wof:name":"Alois Bures",
    "wof:placetype":"venue"
},
  "geometry": {"coordinates":[6.6516828537,50.2180595398],"type":"Point"}
}