{
  "type": "Feature",
  "properties": {
    "iso:country":"DE",
    "sg:address":"Pfarrstr. 9",
    "sg:city":"Stuttgart",
    "sg:phone":"+49 711/242187",
    "sg:postcode":"70182",
    "sg:province":"Baden-W\u00fcrttemberg",
    "wof:name":"Insel",
    "wof:placetype":"venue"
},
  "geometry": {"coordinates":[9.181807,48.773453],"type":"Point"}
}