{
  "type": "Feature",
  "properties": {
    "iso:country":"DE",
    "sg:address":"J\u00fcbergstr. 13 a",
    "sg:city":"Hemer",
    "sg:phone":"+49 2372/10327",
    "sg:postcode":"58675",
    "sg:province":"Nordrhein-Westfalen",
    "wof:name":"K. Andreas Stahl- Und Schneidwaren",
    "wof:placetype":"venue"
},
  "geometry": {"coordinates":[7.7714080811,51.3847808838],"type":"Point"}
}