{
  "type": "Feature",
  "properties": {
    "iso:country":"DE",
    "sg:address":"Oderstr. 74-76",
    "sg:city":"Teltow",
    "sg:postcode":"14513",
    "sg:province":"Brandenburg",
    "wof:name":"Grw-arbeitsf\u00f6rderungs- Gesellschaft Mbh",
    "wof:placetype":"venue"
},
  "geometry": {"coordinates":[13.235159,52.396896],"type":"Point"}
}