{
  "type": "Feature",
  "properties": {
    "iso:country":"DE",
    "sg:address":"Neusch\u00f6nau",
    "sg:city":"Neusch\u00f6nau",
    "sg:phone":"+49 2131/9701",
    "sg:postcode":"94556",
    "sg:province":"Bayern",
    "wof:name":"Sparkasse Neuss",
    "wof:placetype":"venue"
},
  "geometry": {"coordinates":[6.693772,51.197083],"type":"Point"}
}