{
  "type": "Feature",
  "properties": {
    "iso:country":"DE",
    "sg:address":"Am Bl\u00fctenring 62",
    "sg:city":"M\u00fcnchen",
    "sg:phone":"+49 89/3232619",
    "sg:postcode":"80939",
    "sg:province":"Bayern",
    "wof:name":"Pvr Pressevertrieb Monika R\u00fcger",
    "wof:placetype":"venue"
},
  "geometry": {"coordinates":[11.631189,48.19553],"type":"Point"}
}