{
  "type": "Feature",
  "properties": {
    "iso:country":"DE",
    "sg:address":"Josef-Seliger-Str. 2",
    "sg:city":"Ottobrunn",
    "sg:phone":"+49 89/603431",
    "sg:postcode":"85521",
    "sg:province":"Bayern",
    "wof:name":"Heimat",
    "wof:placetype":"venue"
},
  "geometry": {"coordinates":[11.6730632782,48.0681648254],"type":"Point"}
}