{
  "type": "Feature",
  "properties": {
    "iso:country":"DE",
    "sg:address":"Birkenbergstr. 26",
    "sg:city":"Leverkusen",
    "sg:phone":"+49 2171/1369",
    "sg:postcode":"51379",
    "sg:province":"Nordrhein-Westfalen",
    "wof:name":"Peter Rosenstock & Sohn",
    "wof:placetype":"venue"
},
  "geometry": {"coordinates":[7.0013360977,51.0653305054],"type":"Point"}
}