{
  "type": "Feature",
  "properties": {
    "iso:country":"DE",
    "sg:address":"Schlesierstr. 117",
    "sg:city":"N\u00fcrtingen",
    "sg:phone":"+49 7022/94212",
    "sg:postcode":"72622",
    "sg:province":"Baden-W\u00fcrttemberg",
    "wof:name":"H. Hagenlocher",
    "wof:placetype":"venue"
},
  "geometry": {"coordinates":[9.3246793747,48.6102294922],"type":"Point"}
}