{
  "type": "Feature",
  "properties": {
    "iso:country":"DE",
    "sg:address":"Rosenstr. 10",
    "sg:city":"Traben-Trarbach",
    "sg:phone":"+49 6541/6412",
    "sg:postcode":"56841",
    "sg:province":"Rheinland-Pfalz",
    "wof:name":"Paul Jakoby",
    "wof:placetype":"venue"
},
  "geometry": {"coordinates":[7.102640152,49.9779129028],"type":"Point"}
}