{
  "type": "Feature",
  "properties": {
    "iso:country":"DE",
    "sg:address":"Gnesener Str. 1",
    "sg:city":"M\u00fcnchen",
    "sg:phone":"+49 89/934800",
    "sg:postcode":"81929",
    "sg:province":"Bayern",
    "wof:name":"Accedo Verlags Gmbh",
    "wof:placetype":"venue"
},
  "geometry": {"coordinates":[11.6474542618,48.1489219666],"type":"Point"}
}