{
  "type": "Feature",
  "properties": {
    "iso:country":"DE",
    "sg:address":"Dittenheim",
    "sg:city":"Dittenheim",
    "sg:phone":"+49 9834/464",
    "sg:postcode":"91723",
    "sg:province":"Bayern",
    "wof:name":"Raiffeisenbank Dittenheim Eg",
    "wof:placetype":"venue"
},
  "geometry": {"coordinates":[10.790375,49.05711],"type":"Point"}
}