{
  "type": "Feature",
  "properties": {
    "iso:country":"DE",
    "sg:address":"Erich-Weinert-Str. 6",
    "sg:city":"Suhl",
    "sg:phone":"+49 3681/723362",
    "sg:postcode":"98527",
    "sg:province":"Th\u00fcringen",
    "wof:name":"Dr. Med. Britta Trenkmann \u00c4rztin F\u00fcr Allgemeinmedizin",
    "wof:placetype":"venue"
},
  "geometry": {"coordinates":[10.7046709061,50.6128425598],"type":"Point"}
}