{
  "type": "Feature",
  "properties": {
    "iso:country":"DE",
    "sg:address":"Erbsengasse 3a",
    "sg:city":"Aschaffenburg",
    "sg:phone":"+49 6021/39970",
    "sg:postcode":"63739",
    "sg:province":"Bayern",
    "wof:name":"O. Pfaff & Sohn Inh. Pfaff & Daniel",
    "wof:placetype":"venue"
},
  "geometry": {"coordinates":[9.1491270065,49.9740524292],"type":"Point"}
}