{
  "type": "Feature",
  "properties": {
    "iso:country":"DE",
    "sg:address":"F\u00f6hrenweg 8",
    "sg:city":"Pentling",
    "sg:postcode":"93080",
    "sg:province":"Bayern",
    "wof:name":"Christoph Schickner",
    "wof:placetype":"venue"
},
  "geometry": {"coordinates":[12.0593833923,48.986995697],"type":"Point"}
}