{
  "type": "Feature",
  "properties": {
    "iso:country":"DE",
    "sg:address":"Obernburger Str. 14",
    "sg:city":"Laudenbach",
    "sg:phone":"+49 9372/2301",
    "sg:postcode":"63925",
    "sg:province":"Bayern",
    "wof:name":"Werner Breitenbach Bauschlosserei",
    "wof:placetype":"venue"
},
  "geometry": {"coordinates":[9.176199,49.74585],"type":"Point"}
}