{
  "type": "Feature",
  "properties": {
    "iso:country":"DE",
    "sg:address":"Altenburger Str. 56",
    "sg:city":"Groitzsch",
    "sg:phone":"+49 34296/42012",
    "sg:postcode":"04539",
    "sg:province":"Sachsen",
    "wof:name":"Peter Fr\u00f6hlich",
    "wof:placetype":"venue"
},
  "geometry": {"coordinates":[12.2854881287,51.1512527466],"type":"Point"}
}