{
  "type": "Feature",
  "properties": {
    "iso:country":"DE",
    "sg:address":"Grabenstr. 11",
    "sg:city":"Seesen",
    "sg:phone":"+49 5381/46823",
    "sg:postcode":"38723",
    "sg:province":"Niedersachsen",
    "wof:name":"Herbert Baxmann",
    "wof:placetype":"venue"
},
  "geometry": {"coordinates":[10.152731,51.916367],"type":"Point"}
}