{
  "type": "Feature",
  "properties": {
    "iso:country":"DE",
    "sg:address":"Neusser Str. 27-29",
    "sg:city":"K\u00f6ln",
    "sg:phone":"+49 221/9730400",
    "sg:postcode":"50670",
    "sg:province":"Nordrhein-Westfalen",
    "wof:name":"Prof. Dr. Peter Kulka Architekt",
    "wof:placetype":"venue"
},
  "geometry": {"coordinates":[6.956927,50.952213],"type":"Point"}
}