{
  "type": "Feature",
  "properties": {
    "iso:country":"DE",
    "sg:address":"Gerstenweg 4",
    "sg:city":"M\u00f6hrendorf",
    "sg:phone":"+49 9131/43860",
    "sg:postcode":"91096",
    "sg:province":"Bayern",
    "wof:name":"Anna-maria Haidacher",
    "wof:placetype":"venue"
},
  "geometry": {"coordinates":[11.0026159286,49.6430702209],"type":"Point"}
}