{
  "type": "Feature",
  "properties": {
    "iso:country":"DE",
    "sg:address":"Peterstr.",
    "sg:city":"Langewiesen",
    "sg:phone":"+49 3677/814469",
    "sg:postcode":"98704",
    "sg:province":"Th\u00fcringen",
    "wof:name":"Th\u00fcringer Hof",
    "wof:placetype":"venue"
},
  "geometry": {"coordinates":[10.9751558304,50.6708297729],"type":"Point"}
}