{
  "type": "Feature",
  "properties": {
    "iso:country":"DE",
    "sg:address":"Breite Str. 9",
    "sg:city":"Seelow",
    "sg:phone":"+49 3346/8246",
    "sg:postcode":"15306",
    "sg:province":"Brandenburg",
    "wof:name":"Dieter Liebenow",
    "wof:placetype":"venue"
},
  "geometry": {"coordinates":[14.3803796768,52.5321655273],"type":"Point"}
}