{
  "type": "Feature",
  "properties": {
    "iso:country":"DE",
    "sg:address":"Burgstr. 4",
    "sg:city":"Detern",
    "sg:phone":"+49 4957/363",
    "sg:postcode":"26847",
    "sg:province":"Niedersachsen",
    "wof:name":"Wiard W\u00fcbbena Pension",
    "wof:placetype":"venue"
},
  "geometry": {"coordinates":[7.639029,53.22102],"type":"Point"}
}