{
  "type": "Feature",
  "properties": {
    "iso:country":"DE",
    "sg:address":"Karl-Halle-Str. 58",
    "sg:city":"Hagen",
    "sg:phone":"+49 2331/587887",
    "sg:postcode":"58097",
    "sg:province":"Nordrhein-Westfalen",
    "wof:name":"Berthold Feldhaus Gmbh",
    "wof:placetype":"venue"
},
  "geometry": {"coordinates":[7.486587,51.370434],"type":"Point"}
}