{
  "type": "Feature",
  "properties": {
    "iso:country":"DE",
    "sg:address":"K\u00f6nigstr. 17",
    "sg:city":"Stuttgart",
    "sg:phone":"+49 711/2262801",
    "sg:postcode":"70173",
    "sg:province":"Baden-W\u00fcrttemberg",
    "wof:name":"Orsay",
    "wof:placetype":"venue"
},
  "geometry": {"coordinates":[9.177314,48.777195],"type":"Point"}
}