{
  "type": "Feature",
  "properties": {
    "iso:country":"DE",
    "sg:address":"Buchenweg 16",
    "sg:city":"Idstein",
    "sg:phone":"+49 6126/4161",
    "sg:postcode":"65510",
    "sg:province":"Hessen",
    "wof:name":"G\u00fcnter Sch\u00e4fer Architekt",
    "wof:placetype":"venue"
},
  "geometry": {"coordinates":[8.259763,50.212177],"type":"Point"}
}