{
  "type": "Feature",
  "properties": {
    "iso:country":"DE",
    "sg:address":"Walburgastr. 16",
    "sg:city":"Ruderatshofen",
    "sg:phone":"+49 8342/7671",
    "sg:postcode":"87674",
    "sg:province":"Bayern",
    "wof:name":"Johann Neth",
    "wof:placetype":"venue"
},
  "geometry": {"coordinates":[10.586333,47.805412],"type":"Point"}
}