{
  "type": "Feature",
  "properties": {
    "iso:country":"DE",
    "sg:address":"Borsigstr. 6",
    "sg:city":"L\u00fcneburg",
    "sg:phone":"+49 4131/36560",
    "sg:postcode":"21339",
    "sg:province":"Niedersachsen",
    "wof:name":"Hans Eckert Inh. Annegret Eckert",
    "wof:placetype":"venue"
},
  "geometry": {"coordinates":[10.411163,53.273861],"type":"Point"}
}