{
  "type": "Feature",
  "properties": {
    "iso:country":"DE",
    "sg:address":"Br\u00f6ckweg 12",
    "sg:city":"Rheinbach",
    "sg:phone":"+49 2226/15591",
    "sg:postcode":"53359",
    "sg:province":"Nordrhein-Westfalen",
    "wof:name":"Willi Breuer",
    "wof:placetype":"venue"
},
  "geometry": {"coordinates":[6.929835,50.5886],"type":"Point"}
}