{
  "type": "Feature",
  "properties": {
    "iso:country":"DE",
    "sg:address":"Hauptstr. 103",
    "sg:city":"Gaggenau",
    "sg:phone":"+49 7225/2666",
    "sg:postcode":"76571",
    "sg:province":"Baden-W\u00fcrttemberg",
    "wof:name":"Peter Evers Und D. Freiherr Von L\u00f6ffelholz",
    "wof:placetype":"venue"
},
  "geometry": {"coordinates":[8.3222112656,48.8006477356],"type":"Point"}
}