{
  "type": "Feature",
  "properties": {
    "iso:country":"DE",
    "sg:address":"Sefferweg 19",
    "sg:city":"Neidenbach",
    "sg:phone":"+49 6563/2535",
    "sg:postcode":"54657",
    "sg:province":"Rheinland-Pfalz",
    "wof:name":"R. Schon",
    "wof:placetype":"venue"
},
  "geometry": {"coordinates":[6.546795,50.088894],"type":"Point"}
}