{
  "type": "Feature",
  "properties": {
    "iso:country":"DE",
    "sg:address":"Kalenberger Graben 11",
    "sg:city":"Hildesheim",
    "sg:phone":"+49 5121/34201",
    "sg:postcode":"31134",
    "sg:province":"Niedersachsen",
    "wof:name":"B\u00f6ger Und Partner Planungsgesellschaft Mbh",
    "wof:placetype":"venue"
},
  "geometry": {"coordinates":[9.9460554123,52.1455574036],"type":"Point"}
}