{
  "type": "Feature",
  "properties": {
    "iso:country":"DE",
    "sg:address":"Wilhelmstr. 21",
    "sg:city":"Erkelenz",
    "sg:phone":"+49 2431/2011",
    "sg:postcode":"41812",
    "sg:province":"Nordrhein-Westfalen",
    "wof:name":"Backes Kuhlen Und Nagel Rechtsanw\u00e4lte",
    "wof:placetype":"venue"
},
  "geometry": {"coordinates":[6.3120698929,51.0775794983],"type":"Point"}
}