{
  "type": "Feature",
  "properties": {
    "iso:country":"DE",
    "sg:address":"Stembergstr. 31",
    "sg:city":"Arnsberg",
    "sg:phone":"+49 2932/9850",
    "sg:postcode":"59755",
    "sg:province":"Nordrhein-Westfalen",
    "wof:name":"Elektro-fachmarkt Berlet Gmbh & Co.",
    "wof:placetype":"venue"
},
  "geometry": {"coordinates":[7.969017,51.446079],"type":"Point"}
}