{
  "type": "Feature",
  "properties": {
    "iso:country":"DE",
    "sg:address":"Hohe Str. 5",
    "sg:city":"Wetzlar",
    "sg:phone":"+49 6441/51708",
    "sg:postcode":"35576",
    "sg:province":"Hessen",
    "wof:name":"W. Eckhardt",
    "wof:placetype":"venue"
},
  "geometry": {"coordinates":[8.477151,50.564922],"type":"Point"}
}