{
  "type": "Feature",
  "properties": {
    "iso:country":"DE",
    "sg:address":"Friedrich-Ebert-Str. 78",
    "sg:city":"M\u00fcnster",
    "sg:phone":"+49 6071/32222",
    "sg:postcode":"64839",
    "sg:province":"Hessen",
    "wof:name":"Discothek Tropical",
    "wof:placetype":"venue"
},
  "geometry": {"coordinates":[8.87208,49.925503],"type":"Point"}
}