{
  "type": "Feature",
  "properties": {
    "iso:country":"DE",
    "sg:address":"Boddenweg",
    "sg:city":"Rappin",
    "sg:phone":"+49 3838/31248",
    "sg:postcode":"18528",
    "sg:province":"Mecklenburg-Vorpommern",
    "wof:name":"Camping Gro\u00df Banzelvitz",
    "wof:placetype":"venue"
},
  "geometry": {"coordinates":[13.40489,54.497276],"type":"Point"}
}