{
  "type": "Feature",
  "properties": {
    "iso:country":"DE",
    "sg:address":"Weikamp 25",
    "sg:city":"H\u00f6rstel",
    "sg:phone":"+49 5978/430",
    "sg:postcode":"48477",
    "sg:province":"Nordrhein-Westfalen",
    "wof:name":"Alfons Sasse",
    "wof:placetype":"venue"
},
  "geometry": {"coordinates":[7.5092787743,52.3275642395],"type":"Point"}
}