{
  "type": "Feature",
  "properties": {
    "iso:country":"DE",
    "sg:address":"Steinstr. 6",
    "sg:city":"Werne",
    "sg:phone":"+49 2389/5021",
    "sg:postcode":"59368",
    "sg:province":"Nordrhein-Westfalen",
    "wof:name":"B\u00fcroorganisation Brauch Inh. Carsten Brauch",
    "wof:placetype":"venue"
},
  "geometry": {"coordinates":[7.6151437759,51.6647720337],"type":"Point"}
}