{
  "type": "Feature",
  "properties": {
    "iso:country":"DE",
    "sg:address":"Am Kleinen Dahlen 20",
    "sg:city":"Hamburg",
    "sg:phone":"+49 40/7603372",
    "sg:postcode":"21077",
    "sg:province":"Hamburg",
    "wof:name":"Siegfried M\u00fcller Inh. Inge M\u00fcller",
    "wof:placetype":"venue"
},
  "geometry": {"coordinates":[9.9673318863,53.4482574463],"type":"Point"}
}