{
  "type": "Feature",
  "properties": {
    "iso:country":"DE",
    "sg:address":"Leipziger Str. 26",
    "sg:city":"Artern",
    "sg:phone":"+49 3466/322471",
    "sg:postcode":"06556",
    "sg:province":"Th\u00fcringen",
    "wof:name":"S. Renno Immobilienmakler",
    "wof:placetype":"venue"
},
  "geometry": {"coordinates":[11.3058452606,51.3918266296],"type":"Point"}
}