{
  "type": "Feature",
  "properties": {
    "iso:country":"DE",
    "sg:address":"Hitzestr. 7",
    "sg:city":"Bocholt",
    "sg:postcode":"46399",
    "sg:province":"Nordrhein-Westfalen",
    "wof:name":"Onlineagentur B. Reinders",
    "wof:placetype":"venue"
},
  "geometry": {"coordinates":[6.5964231491,51.8407897949],"type":"Point"}
}