{
  "type": "Feature",
  "properties": {
    "iso:country":"DE",
    "sg:address":"Harpener Hellweg 16",
    "sg:city":"Bochum",
    "sg:phone":"+49 234/95530",
    "sg:postcode":"44805",
    "sg:province":"Nordrhein-Westfalen",
    "wof:name":"Zimbo Fleischwarenfabrik Verwaltungs Gmbh",
    "wof:placetype":"venue"
},
  "geometry": {"coordinates":[7.28906,51.50071],"type":"Point"}
}