{
  "type": "Feature",
  "properties": {
    "iso:country":"DE",
    "sg:address":"Kauferberg 23",
    "sg:city":"Monschau",
    "sg:phone":"+49 2472/2151",
    "sg:postcode":"52156",
    "sg:province":"Nordrhein-Westfalen",
    "wof:name":"Restaurant Zaunk\u00f6nig",
    "wof:placetype":"venue"
},
  "geometry": {"coordinates":[6.2659339905,50.5246124268],"type":"Point"}
}