{
  "type": "Feature",
  "properties": {
    "iso:country":"DE",
    "sg:address":"Lessingstr. 2 a",
    "sg:city":"R\u00f6tha",
    "sg:phone":"+49 34206/54107",
    "sg:postcode":"04571",
    "sg:province":"Sachsen",
    "wof:name":"Stadt-apotheke Inh. Annett Bigl",
    "wof:placetype":"venue"
},
  "geometry": {"coordinates":[12.416852,51.199417],"type":"Point"}
}