{
  "type": "Feature",
  "properties": {
    "iso:country":"DE",
    "sg:address":"Heinrichstr. 22",
    "sg:city":"Spiesen-Elversberg",
    "sg:phone":"+49 6821/71099",
    "sg:postcode":"66583",
    "sg:province":"Saarland",
    "wof:name":"Karl Conrath Ingenieur",
    "wof:placetype":"venue"
},
  "geometry": {"coordinates":[7.1309690475,49.313949585],"type":"Point"}
}