{
  "type": "Feature",
  "properties": {
    "iso:country":"DE",
    "sg:address":"Kaiserstr. 26",
    "sg:city":"Karlsruhe",
    "sg:phone":"+49 721/374720",
    "sg:postcode":"76133",
    "sg:province":"Baden-W\u00fcrttemberg",
    "wof:name":"Werner A. Hauer Architekt",
    "wof:placetype":"venue"
},
  "geometry": {"coordinates":[8.409006,49.009495],"type":"Point"}
}