{
  "type": "Feature",
  "properties": {
    "iso:country":"DE",
    "sg:address":"Hauptstr. 22",
    "sg:city":"Zeitlofs",
    "sg:phone":"+49 9741/5152",
    "sg:postcode":"97799",
    "sg:province":"Bayern",
    "wof:name":"C. Feulner",
    "wof:placetype":"venue"
},
  "geometry": {"coordinates":[9.71099,50.269222],"type":"Point"}
}