{
  "type": "Feature",
  "properties": {
    "iso:country":"DE",
    "sg:address":"Am Gr\u00fcn 19",
    "sg:city":"Varel",
    "sg:phone":"+49 4451/959860",
    "sg:postcode":"26316",
    "sg:province":"Niedersachsen",
    "wof:name":"Seniorenheim To Huus",
    "wof:placetype":"venue"
},
  "geometry": {"coordinates":[8.148132,53.370136],"type":"Point"}
}