{
  "type": "Feature",
  "properties": {
    "iso:country":"DE",
    "sg:address":"38467",
    "sg:city":"Bergfeld",
    "sg:phone":"+49 5368/748",
    "sg:postcode":"38467",
    "sg:province":"Niedersachsen",
    "wof:name":"Gastst\u00e4tte Zur Post",
    "wof:placetype":"venue"
},
  "geometry": {"coordinates":[10.8456773758,52.5458984375],"type":"Point"}
}