{
  "type": "Feature",
  "properties": {
    "iso:country":"DE",
    "sg:address":"Reisingerstr. 42",
    "sg:city":"Ismaning",
    "sg:phone":"+49 89/969043",
    "sg:postcode":"85737",
    "sg:province":"Bayern",
    "wof:name":"Gabor Petery Architekt",
    "wof:placetype":"venue"
},
  "geometry": {"coordinates":[11.667917,48.21703],"type":"Point"}
}