{
  "type": "Feature",
  "properties": {
    "iso:country":"DE",
    "sg:address":"Traithenstr. 2a",
    "sg:city":"Kiefersfelden",
    "sg:phone":"+49 8033/7930",
    "sg:postcode":"83088",
    "sg:province":"Bayern",
    "wof:name":"M. Wernhardt Heissmangel",
    "wof:placetype":"venue"
},
  "geometry": {"coordinates":[12.1727981567,47.6167297363],"type":"Point"}
}