{
  "type": "Feature",
  "properties": {
    "iso:country":"DE",
    "sg:address":"Implerstr. 12 a",
    "sg:city":"M\u00fcnchen",
    "sg:phone":"+49 89/7470221",
    "sg:postcode":"81371",
    "sg:province":"Bayern",
    "wof:name":"Mathias Rathke",
    "wof:placetype":"venue"
},
  "geometry": {"coordinates":[11.548344,48.122536],"type":"Point"}
}