{
  "type": "Feature",
  "properties": {
    "iso:country":"DE",
    "sg:address":"Webergasse 9",
    "sg:city":"Bad Hersfeld",
    "sg:phone":"+49 6621/74445",
    "sg:postcode":"36251",
    "sg:province":"Hessen",
    "wof:name":"Parkhaus S\u00fcdwest Gmbh & Co. Betriebs Kg",
    "wof:placetype":"venue"
},
  "geometry": {"coordinates":[9.7069396973,50.8663825989],"type":"Point"}
}