{
  "type": "Feature",
  "properties": {
    "iso:country":"DE",
    "sg:address":"Emmerstedter Str. 20",
    "sg:city":"Helmstedt",
    "sg:phone":"+49 5351/55630",
    "sg:postcode":"38350",
    "sg:province":"Niedersachsen",
    "wof:name":"G.schwannecke Baustoffhandlung Zwndl. Der Baubedarf",
    "wof:placetype":"venue"
},
  "geometry": {"coordinates":[10.9947967529,52.2407150269],"type":"Point"}
}