{
  "type": "Feature",
  "properties": {
    "iso:country":"DE",
    "sg:address":"Gartenstr. 14",
    "sg:city":"Freiburg",
    "sg:phone":"+49 761/25239",
    "sg:postcode":"79098",
    "sg:province":"Baden-W\u00fcrttemberg",
    "wof:name":"Dr. Med. Margarete Seume \u00c4rztin F\u00fcr Allgemeinmedizin",
    "wof:placetype":"venue"
},
  "geometry": {"coordinates":[7.8468909264,47.9917182922],"type":"Point"}
}