{
  "type": "Feature",
  "properties": {
    "iso:country":"DE",
    "sg:address":"Hochstr. 31",
    "sg:city":"N\u00fcrnberg",
    "sg:phone":"+49 911/265324",
    "sg:postcode":"90429",
    "sg:province":"Bayern",
    "wof:name":"Brendan Fitzgerald",
    "wof:placetype":"venue"
},
  "geometry": {"coordinates":[11.0608930588,49.4532852173],"type":"Point"}
}