{
  "type": "Feature",
  "properties": {
    "iso:country":"DE",
    "sg:address":"Oberstr. 48-50",
    "sg:city":"Ratingen",
    "sg:phone":"+49 2102/22822",
    "sg:postcode":"40878",
    "sg:province":"Nordrhein-Westfalen",
    "wof:name":"Betten Isenb\u00fcgel",
    "wof:placetype":"venue"
},
  "geometry": {"coordinates":[6.8533248901,51.2983970642],"type":"Point"}
}