{
  "type": "Feature",
  "properties": {
    "iso:country":"DE",
    "sg:address":"Postfach",
    "sg:city":"Schmallenberg",
    "sg:phone":"+49 2974/400",
    "sg:postcode":"57376",
    "sg:province":"Nordrhein-Westfalen",
    "wof:name":"Hallen- Und Freibad Fredeburg",
    "wof:placetype":"venue"
},
  "geometry": {"coordinates":[8.285610199,51.1477890015],"type":"Point"}
}