{
  "type": "Feature",
  "properties": {
    "iso:country":"DE",
    "sg:address":"Burg Hornberg",
    "sg:city":"Neckarzimmern",
    "sg:phone":"+49 6261/5001",
    "sg:postcode":"74865",
    "sg:province":"Baden-W\u00fcrttemberg",
    "wof:name":"Baron Von Gemmingen-hornberg",
    "wof:placetype":"venue"
},
  "geometry": {"coordinates":[9.1460771561,49.3133926392],"type":"Point"}
}