{
  "type": "Feature",
  "properties": {
    "iso:country":"DE",
    "sg:address":"K\u00f6nigsberger Str. 1",
    "sg:city":"Viersen",
    "sg:phone":"+49 2162/33857",
    "sg:postcode":"41748",
    "sg:province":"Nordrhein-Westfalen",
    "wof:name":"Leg Wohnen Gmbh",
    "wof:placetype":"venue"
},
  "geometry": {"coordinates":[6.4183139801,51.2539329529],"type":"Point"}
}