{
  "type": "Feature",
  "properties": {
    "iso:country":"DE",
    "sg:address":"Am Wasserrad 1",
    "sg:city":"Spalt",
    "sg:phone":"+49 9175/626",
    "sg:postcode":"91174",
    "sg:province":"Bayern",
    "wof:name":"Stuhl Regelsysteme Gmbh",
    "wof:placetype":"venue"
},
  "geometry": {"coordinates":[10.9187746048,49.1808586121],"type":"Point"}
}