{
  "type": "Feature",
  "properties": {
    "iso:country":"DE",
    "sg:address":"Poppenlauerer Str. 2",
    "sg:city":"Ma\u00dfbach",
    "sg:phone":"+49 9735/255",
    "sg:postcode":"97711",
    "sg:province":"Bayern",
    "wof:name":"Pizzeria Capri",
    "wof:placetype":"venue"
},
  "geometry": {"coordinates":[10.2748718262,50.1850967407],"type":"Point"}
}