{
  "type": "Feature",
  "properties": {
    "iso:country":"DE",
    "sg:address":"Reichsstr. 5",
    "sg:city":"Berlin",
    "sg:phone":"+49 30/3058094",
    "sg:postcode":"14052",
    "sg:province":"Berlin",
    "wof:name":"Rainer Jurk Rechtsanwalt",
    "wof:placetype":"venue"
},
  "geometry": {"coordinates":[13.2697782516,52.511341095],"type":"Point"}
}