{
  "type": "Feature",
  "properties": {
    "iso:country":"DE",
    "sg:address":"Nieverner Str. 14",
    "sg:city":"Bad Ems",
    "sg:phone":"+49 2603/94100",
    "sg:postcode":"56130",
    "sg:province":"Rheinland-Pfalz",
    "wof:name":"Medsystem Medizinisch Technischer Anlagenbau Gmbh",
    "wof:placetype":"venue"
},
  "geometry": {"coordinates":[7.702407,50.33287],"type":"Point"}
}