{
  "type": "Feature",
  "properties": {
    "iso:country":"DE",
    "sg:address":"S\u00fcdstr. 9",
    "sg:city":"Genderkingen",
    "sg:postcode":"86682",
    "sg:province":"Bayern",
    "wof:name":"Kate Gmbh",
    "wof:placetype":"venue"
},
  "geometry": {"coordinates":[10.873729,48.699413],"type":"Point"}
}