{
  "type": "Feature",
  "properties": {
    "iso:country":"DE",
    "sg:address":"Mathmeckestr. 55",
    "sg:city":"Eslohe",
    "sg:phone":"+49 2973/6721",
    "sg:postcode":"59889",
    "sg:province":"Nordrhein-Westfalen",
    "wof:name":"Alfons Wurm",
    "wof:placetype":"venue"
},
  "geometry": {"coordinates":[8.164325,51.285595],"type":"Point"}
}