{
  "type": "Feature",
  "properties": {
    "iso:country":"DE",
    "sg:address":"Dorfstr. 142",
    "sg:city":"Duisburg",
    "sg:phone":"+49 203/781617",
    "sg:postcode":"47259",
    "sg:province":"Nordrhein-Westfalen",
    "wof:name":"Hermann Blomenkamp",
    "wof:placetype":"venue"
},
  "geometry": {"coordinates":[6.706224,51.348087],"type":"Point"}
}