{
  "type": "Feature",
  "properties": {
    "iso:country":"DE",
    "sg:address":"Kurze Str. 11",
    "sg:city":"Osnabr\u00fcck",
    "sg:phone":"+49 541/82119",
    "sg:postcode":"49080",
    "sg:province":"Niedersachsen",
    "wof:name":"Edith Reinink",
    "wof:placetype":"venue"
},
  "geometry": {"coordinates":[8.0470027924,52.2656288147],"type":"Point"}
}