{
  "type": "Feature",
  "properties": {
    "iso:country":"DE",
    "sg:address":"K\u00f6lner Landstr. 217",
    "sg:city":"D\u00fcren",
    "sg:phone":"+49 2421/38125",
    "sg:postcode":"52351",
    "sg:province":"Nordrhein-Westfalen",
    "wof:name":"Trucker Treff",
    "wof:placetype":"venue"
},
  "geometry": {"coordinates":[6.5058422089,50.8096122742],"type":"Point"}
}