{
  "type": "Feature",
  "properties": {
    "iso:country":"DE",
    "sg:address":"Klosterstra\u00dfe 6",
    "sg:city":"Traunstein",
    "sg:phone":"+49 861/1666136",
    "sg:postcode":"83278",
    "sg:province":"Bayern",
    "wof:name":"Werbung Zum Anziehen Und Aufblasen",
    "wof:placetype":"venue"
},
  "geometry": {"coordinates":[12.647485,47.870922],"type":"Point"}
}