{
  "type": "Feature",
  "properties": {
    "iso:country":"DE",
    "sg:address":"Cranger Str. 35",
    "sg:city":"Gelsenkirchen",
    "sg:phone":"+49 209/30026",
    "sg:postcode":"45894",
    "sg:province":"Nordrhein-Westfalen",
    "wof:name":"Rolf Schr\u00f6der Ingenieur Und Architekt",
    "wof:placetype":"venue"
},
  "geometry": {"coordinates":[7.060757,51.575527],"type":"Point"}
}