{
  "type": "Feature",
  "properties": {
    "iso:country":"DE",
    "sg:address":"Friedrich-Ebert-Str. 37",
    "sg:city":"Weiterstadt",
    "sg:phone":"+49 6150/2632",
    "sg:postcode":"64331",
    "sg:province":"Hessen",
    "wof:name":"Rudolf Morhad",
    "wof:placetype":"venue"
},
  "geometry": {"coordinates":[8.5834264755,49.9035682678],"type":"Point"}
}