{
  "type": "Feature",
  "properties": {
    "iso:country":"DE",
    "sg:address":"Ernst-Th\u00e4lmann Strasse 38",
    "sg:city":"Sagard",
    "sg:phone":"+49 38302/51538",
    "sg:postcode":"18551",
    "sg:province":"Mecklenburg-Vorpommern",
    "wof:name":"Restaurant Zur Brunnenaue",
    "wof:placetype":"venue"
},
  "geometry": {"coordinates":[13.557012,54.524841],"type":"Point"}
}