{
  "type": "Feature",
  "properties": {
    "iso:country":"DE",
    "sg:address":"Elisabethenstr. 28",
    "sg:city":"Darmstadt",
    "sg:phone":"+49 6151/24295",
    "sg:postcode":"64283",
    "sg:province":"Hessen",
    "wof:name":"Karl-august Wilk Ingenieur",
    "wof:placetype":"venue"
},
  "geometry": {"coordinates":[8.6505804062,49.8699684143],"type":"Point"}
}