{
  "type": "Feature",
  "properties": {
    "iso:country":"DE",
    "sg:address":"Hanauer Landstr. 61",
    "sg:city":"Hanau",
    "sg:phone":"+49 4961/8153097",
    "sg:postcode":"63457",
    "sg:province":"Hessen",
    "wof:name":"Karl Riedinger W\u00c4lzlager Gmbh",
    "wof:placetype":"venue"
},
  "geometry": {"coordinates":[8.9369468689,50.1131401062],"type":"Point"}
}