{
  "type": "Feature",
  "properties": {
    "iso:country":"DE",
    "sg:address":"Adolf-Kolping-Str. 32",
    "sg:city":"Gro\u00df-Gerau",
    "sg:phone":"+49 6152/2670",
    "sg:postcode":"64521",
    "sg:province":"Hessen",
    "wof:name":"Walter Schad Architekt",
    "wof:placetype":"venue"
},
  "geometry": {"coordinates":[8.480242,49.925346],"type":"Point"}
}