{
  "type": "Feature",
  "properties": {
    "iso:country":"DE",
    "sg:address":"Herrenstr. 33",
    "sg:city":"Dortmund",
    "sg:phone":"+49 231/486394",
    "sg:postcode":"44287",
    "sg:province":"Nordrhein-Westfalen",
    "wof:name":"Reinhold Wilms Versicherungsvertreter",
    "wof:placetype":"venue"
},
  "geometry": {"coordinates":[7.558909893,51.4709205627],"type":"Point"}
}