{
  "type": "Feature",
  "properties": {
    "iso:country":"DE",
    "sg:address":"Michael-Burgau-Str. 11 a",
    "sg:city":"Regensburg",
    "sg:phone":"+49 941/35547",
    "sg:postcode":"93049",
    "sg:province":"Bayern",
    "wof:name":"Hans Janka Steuerberater",
    "wof:placetype":"venue"
},
  "geometry": {"coordinates":[12.0602931976,49.016746521],"type":"Point"}
}