{
  "type": "Feature",
  "properties": {
    "iso:country":"DE",
    "sg:address":"Hauptstr. 55",
    "sg:city":"Murrhardt",
    "sg:phone":"+49 7192/5220",
    "sg:postcode":"71540",
    "sg:province":"Baden-W\u00fcrttemberg",
    "wof:name":"Sieghard K\u00fcbler",
    "wof:placetype":"venue"
},
  "geometry": {"coordinates":[9.5811166763,48.9784164429],"type":"Point"}
}