{
  "type": "Feature",
  "properties": {
    "iso:country":"DE",
    "sg:address":"Neustadt 56",
    "sg:city":"Husum",
    "sg:phone":"+49 4841/62056",
    "sg:postcode":"25813",
    "sg:province":"Schleswig-Holstein",
    "wof:name":"Adalbert Eggers Herbert J\u00f6ns",
    "wof:placetype":"venue"
},
  "geometry": {"coordinates":[9.0468997955,54.4786186218],"type":"Point"}
}