{
  "type": "Feature",
  "properties": {
    "iso:country":"DE",
    "sg:address":"Heidbergstr. 20",
    "sg:city":"Norderstedt",
    "sg:phone":"+49 40/52110420",
    "sg:postcode":"22846",
    "sg:province":"Schleswig-Holstein",
    "wof:name":"Dan Do Warenhandels Gmbh",
    "wof:placetype":"venue"
},
  "geometry": {"coordinates":[9.9888477325,53.7018165588],"type":"Point"}
}