{
  "type": "Feature",
  "properties": {
    "iso:country":"DE",
    "sg:address":"Herzberger Landstr.",
    "sg:city":"Gieboldehausen",
    "sg:phone":"+49 5528/8806",
    "sg:postcode":"37434",
    "sg:province":"Niedersachsen",
    "wof:name":"Th. W\u00fcrschmidt",
    "wof:placetype":"venue"
},
  "geometry": {"coordinates":[10.2187204361,51.6152915955],"type":"Point"}
}