{
  "type": "Feature",
  "properties": {
    "iso:country":"DE",
    "sg:address":"Herforder Str. 24",
    "sg:city":"Bad Oeynhausen",
    "sg:phone":"+49 5731/28362",
    "sg:postcode":"32545",
    "sg:province":"Nordrhein-Westfalen",
    "wof:name":"Wiltrud P\u00f6hler",
    "wof:placetype":"venue"
},
  "geometry": {"coordinates":[8.787861824,52.2015800476],"type":"Point"}
}