{
  "type": "Feature",
  "properties": {
    "iso:country":"DE",
    "sg:address":"Nibelungenstr. 288",
    "sg:city":"Lautertal",
    "sg:phone":"+49 6254/37379",
    "sg:postcode":"64686",
    "sg:province":"Hessen",
    "wof:name":"Restaurant Brunnenst\u00fcbchen",
    "wof:placetype":"venue"
},
  "geometry": {"coordinates":[8.6939620972,49.71276474],"type":"Point"}
}