{
  "type": "Feature",
  "properties": {
    "iso:country":"DE",
    "sg:address":"Festungstr. 44",
    "sg:city":"T\u00f6nning",
    "sg:phone":"+49 4861/5323",
    "sg:postcode":"25832",
    "sg:province":"Schleswig-Holstein",
    "wof:name":"Gemballa",
    "wof:placetype":"venue"
},
  "geometry": {"coordinates":[8.9439182281,54.3225708008],"type":"Point"}
}