{
  "type": "Feature",
  "properties": {
    "iso:country":"DE",
    "sg:address":"Amselweg 2",
    "sg:city":"Wilhelmshorst",
    "sg:phone":"+49 33205/62626",
    "sg:postcode":"14557",
    "wof:name":"Dorothea M\u00fcller",
    "wof:placetype":"venue"
},
  "geometry": {"coordinates":[13.0535030365,52.3329544067],"type":"Point"}
}