{
  "type": "Feature",
  "properties": {
    "iso:country":"DE",
    "sg:address":"Donauw\u00f6rther Str. 1",
    "sg:city":"Augsburg",
    "sg:phone":"+49 821/418696",
    "sg:postcode":"86154",
    "sg:province":"Bayern",
    "wof:name":"Kulisse",
    "wof:placetype":"venue"
},
  "geometry": {"coordinates":[10.8810310364,48.3794746399],"type":"Point"}
}