{
  "type": "Feature",
  "properties": {
    "iso:country":"DE",
    "sg:address":"Am Hamjebusch 29",
    "sg:city":"Westerstede",
    "sg:postcode":"26655",
    "sg:province":"Niedersachsen",
    "wof:name":"Reise Know-how Verlag Dr. Hans-r. Grundmann Gmbh",
    "wof:placetype":"venue"
},
  "geometry": {"coordinates":[7.9418978691,53.2551231384],"type":"Point"}
}