{
  "type": "Feature",
  "properties": {
    "iso:country":"DE",
    "sg:address":"Eichenweg 12",
    "sg:city":"Roding",
    "sg:phone":"+49 9461/3509",
    "sg:postcode":"93426",
    "sg:province":"Bayern",
    "wof:name":"Philomena Strasser Heilpraktiker",
    "wof:placetype":"venue"
},
  "geometry": {"coordinates":[12.5172042847,49.1864814758],"type":"Point"}
}