{
  "type": "Feature",
  "properties": {
    "iso:country":"DE",
    "sg:address":"Industriestr. 17",
    "sg:city":"Datteln",
    "sg:phone":"+49 2363/4362",
    "sg:postcode":"45711",
    "sg:province":"Nordrhein-Westfalen",
    "wof:name":"Friedhelm Herber",
    "wof:placetype":"venue"
},
  "geometry": {"coordinates":[7.352358,51.667305],"type":"Point"}
}