{
  "type": "Feature",
  "properties": {
    "iso:country":"DE",
    "sg:address":"Bahnhofstr. 10",
    "sg:city":"Ainring",
    "sg:phone":"+49 8654/50903",
    "sg:postcode":"83404",
    "sg:province":"Bayern",
    "wof:name":"Hammerauer Stubn",
    "wof:placetype":"venue"
},
  "geometry": {"coordinates":[12.9454374313,47.7944374084],"type":"Point"}
}