{
  "type": "Feature",
  "properties": {
    "iso:country":"DE",
    "sg:address":"Suderstr. 84",
    "sg:city":"Mainz",
    "sg:phone":"+49 6131/682983",
    "sg:postcode":"55120",
    "sg:province":"Rheinland-Pfalz",
    "wof:name":"Optik Winnecken",
    "wof:placetype":"venue"
},
  "geometry": {"coordinates":[8.2263355255,50.0168685913],"type":"Point"}
}