{
  "type": "Feature",
  "properties": {
    "iso:country":"DE",
    "sg:address":"Hermann-L\u00f6ns-Weg 35",
    "sg:city":"Bretzenheim",
    "sg:phone":"+49 671/42699",
    "sg:postcode":"55559",
    "sg:province":"Rheinland-Pfalz",
    "wof:name":"K.-h. Und K. B\u00f6rner",
    "wof:placetype":"venue"
},
  "geometry": {"coordinates":[7.902716,49.883018],"type":"Point"}
}