{
  "type": "Feature",
  "properties": {
    "iso:country":"DE",
    "sg:address":"Reinhardsbrunner Str. 20",
    "sg:city":"Tabarz",
    "sg:phone":"+49 36259/68411",
    "sg:postcode":"99891",
    "sg:province":"Th\u00fcringen",
    "wof:name":"Hartmut Reske",
    "wof:placetype":"venue"
},
  "geometry": {"coordinates":[10.4800243378,50.8848228455],"type":"Point"}
}