{
  "type": "Feature",
  "properties": {
    "iso:country":"DE",
    "sg:address":"Spenglerg\u00e4\u00dfchen 6",
    "sg:city":"Augsburg",
    "sg:phone":"+49 821/3479880",
    "sg:postcode":"86152",
    "sg:province":"Bayern",
    "wof:name":"Biopoint Gesundheitsberatung Und Vertrieb Gmbh",
    "wof:placetype":"venue"
},
  "geometry": {"coordinates":[10.898112,48.371876],"type":"Point"}
}