{
  "type": "Feature",
  "properties": {
    "iso:country":"DE",
    "sg:address":"Ferdinand-Maria-Str. 26",
    "sg:city":"M\u00fcnchen",
    "sg:phone":"+49 89/177725",
    "sg:postcode":"80639",
    "sg:province":"Bayern",
    "wof:name":"C. Rupp Und T. Merkle Architekten",
    "wof:placetype":"venue"
},
  "geometry": {"coordinates":[11.51682,48.157436],"type":"Point"}
}