{
  "type": "Feature",
  "properties": {
    "iso:country":"DE",
    "sg:address":"Hauptstr. 47",
    "sg:city":"Alsdorf",
    "sg:phone":"+49 2404/24609",
    "sg:postcode":"52477",
    "sg:province":"Nordrhein-Westfalen",
    "wof:name":"Jakob Weinberg",
    "wof:placetype":"venue"
},
  "geometry": {"coordinates":[6.179157,50.876511],"type":"Point"}
}