{
  "type": "Feature",
  "properties": {
    "iso:country":"DE",
    "sg:address":"Mittelstr. 37",
    "sg:city":"Bonn",
    "sg:phone":"+49 228/81010",
    "sg:postcode":"53175",
    "sg:province":"Nordrhein-Westfalen",
    "wof:name":"Evangelische Zentralstelle F\u00fcr Entwicklungshilfe",
    "wof:placetype":"venue"
},
  "geometry": {"coordinates":[7.157566,50.69817],"type":"Point"}
}