{
  "type": "Feature",
  "properties": {
    "iso:country":"DE",
    "sg:address":"Salomon-Idler-Str. 39",
    "sg:city":"Augsburg",
    "sg:phone":"+49 821/577357",
    "sg:postcode":"86159",
    "sg:province":"Bayern",
    "wof:name":"Edmund Epp",
    "wof:placetype":"venue"
},
  "geometry": {"coordinates":[10.9013748169,48.3327102661],"type":"Point"}
}