{
  "type": "Feature",
  "properties": {
    "iso:country":"DE",
    "sg:address":"Friesenstr. 33",
    "sg:city":"Bremen",
    "sg:phone":"+49 421/72116",
    "sg:postcode":"28203",
    "sg:province":"Bremen",
    "wof:name":"Kiek-rin Weinhandel Gmbh",
    "wof:placetype":"venue"
},
  "geometry": {"coordinates":[8.8315544128,53.0725746155],"type":"Point"}
}