{
  "type": "Feature",
  "properties": {
    "iso:country":"DE",
    "sg:address":"Langenbrucker Weg",
    "sg:city":"Reichertshofen",
    "sg:phone":"+49 8453/7092",
    "sg:postcode":"85084",
    "sg:province":"Bayern",
    "wof:name":"Adolf Bartosch",
    "wof:placetype":"venue"
},
  "geometry": {"coordinates":[11.5154266357,48.646446228],"type":"Point"}
}