{
  "type": "Feature",
  "properties": {
    "iso:country":"DE",
    "sg:address":"Franzstr. 59",
    "sg:city":"K\u00f6ln",
    "sg:phone":"+49 221/435065",
    "sg:postcode":"50935",
    "sg:province":"Nordrhein-Westfalen",
    "wof:name":"Disk-spielautomaten Gmbh",
    "wof:placetype":"venue"
},
  "geometry": {"coordinates":[6.9098200798,50.9237632751],"type":"Point"}
}