{
  "type": "Feature",
  "properties": {
    "iso:country":"DE",
    "sg:address":"Poststr. 14",
    "sg:city":"Fallingbostel",
    "sg:phone":"+49 5163/1239",
    "sg:postcode":"29683",
    "sg:province":"Niedersachsen",
    "wof:name":"Deutsche Bahn Ag",
    "wof:placetype":"venue"
},
  "geometry": {"coordinates":[9.7703104019,52.8992614746],"type":"Point"}
}