{
  "type": "Feature",
  "properties": {
    "iso:country":"DE",
    "sg:address":"Handwerkerzentrum 7",
    "sg:city":"Erpel",
    "sg:phone":"+49 2644/981614",
    "sg:postcode":"53579",
    "sg:province":"Rheinland-Pfalz",
    "wof:name":"Gastst\u00e4tte Alt Erpel",
    "wof:placetype":"venue"
},
  "geometry": {"coordinates":[7.2329921722,50.5870780945],"type":"Point"}
}