{
  "type": "Feature",
  "properties": {
    "iso:country":"DE",
    "sg:address":"Maria-Ward-Str. 32",
    "sg:city":"Pfarrkirchen",
    "sg:phone":"+49 8561/1088",
    "sg:postcode":"84347",
    "sg:province":"Bayern",
    "wof:name":"Reinhard Wimmer Krankengymnast",
    "wof:placetype":"venue"
},
  "geometry": {"coordinates":[12.93124,48.439278],"type":"Point"}
}