{
  "type": "Feature",
  "properties": {
    "iso:country":"DE",
    "sg:address":"Schauinslandweg 18",
    "sg:city":"Weinsberg",
    "sg:phone":"+49 7134/8193",
    "sg:postcode":"74189",
    "sg:province":"Baden-W\u00fcrttemberg",
    "wof:name":"Kurt Bendel",
    "wof:placetype":"venue"
},
  "geometry": {"coordinates":[9.2835216522,49.1461982727],"type":"Point"}
}