{
  "type": "Feature",
  "properties": {
    "iso:country":"DE",
    "sg:address":"Friedl\u00e4nder Weg 65-67",
    "sg:city":"G\u00f6ttingen",
    "sg:phone":"+49 551/49580",
    "sg:postcode":"37085",
    "sg:province":"Niedersachsen",
    "wof:name":"Wilh. Lambrecht Unter- St\u00fctzungseinrichtung Gmbh",
    "wof:placetype":"venue"
},
  "geometry": {"coordinates":[9.9470148087,51.5266265869],"type":"Point"}
}