{
  "type": "Feature",
  "properties": {
    "iso:country":"DE",
    "sg:address":"Segelfliegerweg 5",
    "sg:city":"Melle",
    "sg:phone":"+49 5422/41783",
    "sg:postcode":"49324",
    "sg:province":"Niedersachsen",
    "wof:name":"Artemis Handels Gmbh",
    "wof:placetype":"venue"
},
  "geometry": {"coordinates":[8.37487,52.21347],"type":"Point"}
}