{
  "type": "Feature",
  "properties": {
    "iso:country":"DE",
    "sg:address":"Unterlindau 58",
    "sg:city":"Frankfurt",
    "sg:phone":"+49 69/97205488",
    "sg:postcode":"60323",
    "sg:province":"Hessen",
    "wof:name":"At & T Communications Services Deutschland Gmbh",
    "wof:placetype":"venue"
},
  "geometry": {"coordinates":[8.6678667068,50.1204223633],"type":"Point"}
}