{
  "type": "Feature",
  "properties": {
    "iso:country":"DE",
    "sg:address":"Am Torhaus 49",
    "sg:city":"Saarbr\u00fccken",
    "sg:phone":"+49 681/4170772",
    "sg:postcode":"66113",
    "sg:province":"Saarland",
    "wof:name":"Cuwg",
    "wof:placetype":"venue"
},
  "geometry": {"coordinates":[6.9796929359,49.2492141724],"type":"Point"}
}