{
  "type": "Feature",
  "properties": {
    "iso:country":"DE",
    "sg:address":"Heinrich-Rieker-Str. 4",
    "sg:city":"Tuttlingen",
    "sg:phone":"+49 7461/71567",
    "sg:postcode":"78532",
    "sg:province":"Baden-W\u00fcrttemberg",
    "wof:name":"Wolfgang M\u00fcller Rechtsanwalt",
    "wof:placetype":"venue"
},
  "geometry": {"coordinates":[8.8049230576,47.9825248718],"type":"Point"}
}