{
  "type": "Feature",
  "properties": {
    "iso:country":"DE",
    "sg:address":"Wiekhorner Heuweg 88",
    "sg:city":"Delmenhorst",
    "sg:phone":"+49 4221/81635",
    "sg:postcode":"27753",
    "sg:province":"Niedersachsen",
    "wof:name":"Hermann Schnier Rechtsanwalt",
    "wof:placetype":"venue"
},
  "geometry": {"coordinates":[8.6107082367,53.044883728],"type":"Point"}
}