{
  "type": "Feature",
  "properties": {
    "iso:country":"DE",
    "sg:address":"Barellistr. 12",
    "sg:city":"M\u00fcnchen",
    "sg:phone":"+49 89/1785507",
    "sg:postcode":"80638",
    "sg:province":"Bayern",
    "wof:name":"S. Tischer Garten- Und Landschafts-",
    "wof:placetype":"venue"
},
  "geometry": {"coordinates":[11.510655,48.163418],"type":"Point"}
}