{
  "type": "Feature",
  "properties": {
    "iso:country":"DE",
    "sg:address":"Karl-Marx-Platz 6",
    "sg:city":"Berlin",
    "sg:phone":"+49 30/6872277",
    "sg:postcode":"12043",
    "sg:province":"Berlin",
    "wof:name":"Erich Segem\u00fcller",
    "wof:placetype":"venue"
},
  "geometry": {"coordinates":[13.441568,52.473434],"type":"Point"}
}