{
  "type": "Feature",
  "properties": {
    "iso:country":"DE",
    "sg:address":"Am Zauberberg 2 a",
    "sg:city":"Bad Harzburg",
    "sg:phone":"+49 5322/52091",
    "sg:postcode":"38667",
    "sg:province":"Niedersachsen",
    "wof:name":"Exner-werth Recycling Gmbh",
    "wof:placetype":"venue"
},
  "geometry": {"coordinates":[10.5546693802,51.889541626],"type":"Point"}
}