{
  "type": "Feature",
  "properties": {
    "iso:country":"DE",
    "sg:address":"B\u00f6hmerwaldstr. 36",
    "sg:city":"Geretsried",
    "sg:phone":"+49 8171/60371",
    "sg:postcode":"82538",
    "sg:province":"Bayern",
    "wof:name":"Wolfgang Kraus Architekt",
    "wof:placetype":"venue"
},
  "geometry": {"coordinates":[11.4701,47.877953],"type":"Point"}
}