{
  "type": "Feature",
  "properties": {
    "iso:country":"DE",
    "sg:address":"Pilgerstr. 2",
    "sg:city":"Ammerbuch",
    "sg:phone":"+49 7032/71372",
    "sg:postcode":"72119",
    "sg:province":"Baden-W\u00fcrttemberg",
    "wof:name":"Dr. Med. Siegfried Haupt",
    "wof:placetype":"venue"
},
  "geometry": {"coordinates":[8.9027376175,48.5556373596],"type":"Point"}
}