{
  "type": "Feature",
  "properties": {
    "iso:country":"DE",
    "sg:address":"Grabenweg 4",
    "sg:city":"L\u00fcneburg",
    "sg:phone":"+49 4131/606542",
    "sg:postcode":"21339",
    "sg:province":"Niedersachsen",
    "wof:name":"Cerdmann-bilder \u00fcber L\u00fcneburg",
    "wof:placetype":"venue"
},
  "geometry": {"coordinates":[10.401858,53.270885],"type":"Point"}
}