{
  "type": "Feature",
  "properties": {
    "iso:country":"DE",
    "sg:address":"Eichwiese 2",
    "sg:city":"Seesen",
    "sg:phone":"+49 5381/8384",
    "sg:postcode":"38723",
    "sg:province":"Niedersachsen",
    "wof:name":"Lieselotte B\u00f6hm",
    "wof:placetype":"venue"
},
  "geometry": {"coordinates":[10.186852,51.849556],"type":"Point"}
}