{
  "type": "Feature",
  "properties": {
    "iso:country":"DE",
    "sg:address":"Kirchrarbach 26",
    "sg:city":"Schmallenberg",
    "sg:phone":"+49 2971/87231",
    "sg:postcode":"57392",
    "sg:province":"Nordrhein-Westfalen",
    "wof:name":"Lumme",
    "wof:placetype":"venue"
},
  "geometry": {"coordinates":[8.297662,51.253426],"type":"Point"}
}