{
  "type": "Feature",
  "properties": {
    "iso:country":"DE",
    "sg:address":"Niedergasse 4",
    "sg:city":"Weilburg",
    "sg:phone":"+49 6471/2205",
    "sg:postcode":"35781",
    "sg:province":"Hessen",
    "wof:name":"\u00c4nne Goede Inh. Werner Pielen",
    "wof:placetype":"venue"
},
  "geometry": {"coordinates":[8.261231,50.487289],"type":"Point"}
}