{
  "type": "Feature",
  "properties": {
    "iso:country":"DE",
    "sg:address":"Neuwerk 7",
    "sg:city":"Halle",
    "sg:phone":"+49 345/775150",
    "sg:postcode":"06108",
    "sg:province":"Sachsen-Anhalt",
    "wof:name":"Hochschule F\u00fcr Kunst Und Design Halle",
    "wof:placetype":"venue"
},
  "geometry": {"coordinates":[11.957522,51.491287],"type":"Point"}
}