{
  "type": "Feature",
  "properties": {
    "iso:country":"DE",
    "sg:address":"Hauptstr. 4",
    "sg:city":"Kirchheim",
    "sg:phone":"+49 89/9044509",
    "sg:postcode":"85551",
    "sg:province":"Bayern",
    "wof:name":"E. Wenderoth",
    "wof:placetype":"venue"
},
  "geometry": {"coordinates":[9.5753250122,50.8357124329],"type":"Point"}
}