{
  "type": "Feature",
  "properties": {
    "iso:country":"DE",
    "sg:address":"Freiburger Str. 44",
    "sg:city":"Biberach",
    "sg:phone":"+49 7351/5730",
    "sg:postcode":"88400",
    "sg:province":"Baden-W\u00fcrttemberg",
    "wof:name":"Cellofoam Beteiligungs- Gmbh",
    "wof:placetype":"venue"
},
  "geometry": {"coordinates":[9.794052,48.109032],"type":"Point"}
}