{
  "type": "Feature",
  "properties": {
    "iso:country":"DE",
    "sg:address":"Welschseite 21a",
    "sg:city":"Eppelborn",
    "sg:phone":"+49 6881/7913",
    "sg:postcode":"66571",
    "sg:province":"Saarland",
    "wof:name":"M. Mauer",
    "wof:placetype":"venue"
},
  "geometry": {"coordinates":[6.994236,49.388634],"type":"Point"}
}