{
  "type": "Feature",
  "properties": {
    "iso:country":"DE",
    "sg:address":"Wohlwillstr. 50",
    "sg:city":"Hamburg",
    "sg:phone":"+49 40/436343",
    "sg:postcode":"20359",
    "sg:province":"Hamburg",
    "wof:name":"Music-rock-pub Backstage",
    "wof:placetype":"venue"
},
  "geometry": {"coordinates":[9.9628791809,53.5556144714],"type":"Point"}
}