{
  "type": "Feature",
  "properties": {
    "iso:country":"DE",
    "sg:address":"Einsteinstr. 30",
    "sg:city":"Ettlingen",
    "sg:postcode":"76275",
    "sg:province":"Baden-W\u00fcrttemberg",
    "wof:name":"Ipsen Pharma Gmbh",
    "wof:placetype":"venue"
},
  "geometry": {"coordinates":[8.3738613129,48.9411430359],"type":"Point"}
}