{
  "type": "Feature",
  "properties": {
    "iso:country":"DE",
    "sg:address":"Molkereistr. 6",
    "sg:city":"Westerengel",
    "sg:phone":"+49 36379/40231",
    "sg:postcode":"99718",
    "sg:province":"Th\u00fcringen",
    "wof:name":"Norbert Isserstedt Metallbau Gmbh",
    "wof:placetype":"venue"
},
  "geometry": {"coordinates":[10.9045238495,51.2856063843],"type":"Point"}
}