{
  "type": "Feature",
  "properties": {
    "iso:country":"DE",
    "sg:address":"Kampstr. 14",
    "sg:city":"Moers",
    "sg:phone":"+49 2841/41246",
    "sg:postcode":"47445",
    "sg:province":"Nordrhein-Westfalen",
    "wof:name":"Heinrich Stepken",
    "wof:placetype":"venue"
},
  "geometry": {"coordinates":[6.6296038628,51.4706535339],"type":"Point"}
}