{
  "type": "Feature",
  "properties": {
    "iso:country":"DE",
    "sg:address":"Spiegelberg 9",
    "sg:city":"Immenstaad",
    "sg:phone":"+49 7545/521",
    "sg:postcode":"88090",
    "sg:province":"Baden-W\u00fcrttemberg",
    "wof:name":"Schiffsmodellbauclub E. V. Josef Winkhardt",
    "wof:placetype":"venue"
},
  "geometry": {"coordinates":[9.372800827,47.6693267822],"type":"Point"}
}