{
  "type": "Feature",
  "properties": {
    "iso:country":"DE",
    "sg:address":"Bahnhofstr. 12",
    "sg:city":"Walluf",
    "sg:phone":"+49 6123/74849",
    "sg:postcode":"65396",
    "sg:province":"Hessen",
    "wof:name":"Gastst\u00e4tte Zum F\u00e4\u00dfchen",
    "wof:placetype":"venue"
},
  "geometry": {"coordinates":[8.1597013474,50.0365333557],"type":"Point"}
}