{
  "type": "Feature",
  "properties": {
    "iso:country":"DE",
    "sg:address":"Langestr. 32",
    "sg:city":"Schloss Holte",
    "sg:phone":"+49 5207/5634",
    "sg:postcode":"33758",
    "sg:province":"Nordrhein-Westfalen",
    "wof:name":"Kredite Mit Und Ohne Schufa",
    "wof:placetype":"venue"
},
  "geometry": {"coordinates":[8.622383,51.892342],"type":"Point"}
}