{
  "type": "Feature",
  "properties": {
    "iso:country":"DE",
    "sg:address":"Albanstetten 41",
    "sg:city":"Geisenhausen",
    "sg:phone":"+49 8743/549",
    "sg:postcode":"84144",
    "sg:province":"Bayern",
    "wof:name":"Andreas Steckenbiller",
    "wof:placetype":"venue"
},
  "geometry": {"coordinates":[12.234745,48.478596],"type":"Point"}
}