{
  "type": "Feature",
  "properties": {
    "iso:country":"DE",
    "sg:address":"Walther-Rathenau-Str. 30",
    "sg:city":"Wusterwitz",
    "sg:phone":"+49 33839/60284",
    "sg:postcode":"14789",
    "sg:province":"Brandenburg",
    "wof:name":"Versicherungsb\u00fcro Allianz Ronald Schnabel",
    "wof:placetype":"venue"
},
  "geometry": {"coordinates":[12.3758611679,52.3876113892],"type":"Point"}
}