{
  "type": "Feature",
  "properties": {
    "iso:country":"DE",
    "sg:address":"Bahnhofstr. 18",
    "sg:city":"Wiesbaden",
    "sg:phone":"+49 611/9100720",
    "sg:postcode":"65185",
    "sg:province":"Hessen",
    "wof:name":"Piag Beteiligungs- Gmbh",
    "wof:placetype":"venue"
},
  "geometry": {"coordinates":[8.2427244186,50.0775489807],"type":"Point"}
}