{
  "type": "Feature",
  "properties": {
    "iso:country":"DE",
    "sg:address":"Haimbacher Str. 11",
    "sg:city":"Fulda",
    "sg:phone":"+49 661/78538",
    "sg:postcode":"36041",
    "sg:province":"Hessen",
    "wof:name":"Dental Labor Gessner Gmbh",
    "wof:placetype":"venue"
},
  "geometry": {"coordinates":[9.659404,50.55394],"type":"Point"}
}