{
  "type": "Feature",
  "properties": {
    "iso:country":"DE",
    "sg:address":"Bohlenweg 8",
    "sg:city":"Langenhagen",
    "sg:phone":"+49 511/97820160",
    "sg:postcode":"30853",
    "sg:province":"Niedersachsen",
    "wof:name":"Mattischent Spezialbau- Unternehmen F. Bauwerkin-",
    "wof:placetype":"venue"
},
  "geometry": {"coordinates":[9.730632782,52.4469909668],"type":"Point"}
}