{
  "type": "Feature",
  "properties": {
    "iso:country":"DE",
    "sg:address":"Scheibenstr. 49",
    "sg:city":"D\u00fcsseldorf",
    "sg:phone":"+49 211/4920091",
    "sg:postcode":"40479",
    "sg:province":"Nordrhein-Westfalen",
    "wof:name":"Rolf Beeker Rechtsanwalt",
    "wof:placetype":"venue"
},
  "geometry": {"coordinates":[6.7743868828,51.234375],"type":"Point"}
}