{
  "type": "Feature",
  "properties": {
    "iso:country":"DE",
    "sg:address":"Mollnerweg 35",
    "sg:city":"Berlin",
    "sg:phone":"+49 30/6043291",
    "sg:postcode":"12353",
    "sg:province":"Berlin",
    "wof:name":"Mohammed El Khalil",
    "wof:placetype":"venue"
},
  "geometry": {"coordinates":[13.44375,52.41824],"type":"Point"}
}