{
  "type": "Feature",
  "properties": {
    "iso:country":"DE",
    "sg:address":"Marienstr. 36",
    "sg:city":"Rastede",
    "sg:phone":"+49 4402/82024",
    "sg:postcode":"26180",
    "sg:province":"Niedersachsen",
    "wof:name":"Zi-poppinga Dienstleistungs- Gmbh",
    "wof:placetype":"venue"
},
  "geometry": {"coordinates":[8.1981782913,53.2534675598],"type":"Point"}
}