{
  "type": "Feature",
  "properties": {
    "iso:country":"DE",
    "sg:address":"Am Triniusfelsen",
    "sg:city":"Gie\u00df\u00fcbel",
    "sg:phone":"+49 36870/50430",
    "sg:postcode":"98667",
    "sg:province":"Th\u00fcringen",
    "wof:name":"Triniusbaude",
    "wof:placetype":"venue"
},
  "geometry": {"coordinates":[10.8765535355,50.5221061707],"type":"Point"}
}