{
  "type": "Feature",
  "properties": {
    "iso:country":"DE",
    "sg:address":"In der Rehre 22",
    "sg:city":"Hannover",
    "sg:phone":"+49 511/463855",
    "sg:postcode":"30457",
    "sg:province":"Niedersachsen",
    "wof:name":"Gerd Heumann Augenoptiker",
    "wof:placetype":"venue"
},
  "geometry": {"coordinates":[9.6953639984,52.3289489746],"type":"Point"}
}