{
  "type": "Feature",
  "properties": {
    "iso:country":"DE",
    "sg:address":"Rangewiese 10",
    "sg:city":"Warstein",
    "sg:phone":"+49 2902/4818",
    "sg:postcode":"59581",
    "sg:province":"Nordrhein-Westfalen",
    "wof:name":"Franz-josef Hense Architekt",
    "wof:placetype":"venue"
},
  "geometry": {"coordinates":[8.36315,51.444405],"type":"Point"}
}