{
  "type": "Feature",
  "properties": {
    "iso:country":"DE",
    "sg:address":"Kolpingstr. 6",
    "sg:city":"Thuine",
    "sg:postcode":"49832",
    "sg:province":"Niedersachsen",
    "wof:name":"Bit Bau Immobilien Thuine Gmbh",
    "wof:placetype":"venue"
},
  "geometry": {"coordinates":[7.4817318916,52.502281189],"type":"Point"}
}