{
  "type": "Feature",
  "properties": {
    "iso:country":"DE",
    "sg:address":"Untere Bergstr. 32",
    "sg:city":"Lemf\u00f6rde",
    "sg:phone":"+49 5443/1551",
    "sg:postcode":"49448",
    "sg:province":"Niedersachsen",
    "wof:name":"Tankred Menzel Anlageberater",
    "wof:placetype":"venue"
},
  "geometry": {"coordinates":[8.3707466125,52.461063385],"type":"Point"}
}