{
  "type": "Feature",
  "properties": {
    "iso:country":"DE",
    "sg:address":"Zuckerfabriksweg 1 + 3",
    "sg:city":"Sehnde",
    "sg:postcode":"31319",
    "sg:province":"Niedersachsen",
    "wof:name":"Dentika Handelsges. Mbh",
    "wof:placetype":"venue"
},
  "geometry": {"coordinates":[9.969168663,52.3163452148],"type":"Point"}
}