{
  "type": "Feature",
  "properties": {
    "iso:country":"DE",
    "sg:address":"Tulpenstiege 1",
    "sg:city":"Altenberge",
    "sg:phone":"+49 2505/991099",
    "sg:postcode":"48341",
    "sg:province":"Nordrhein-Westfalen",
    "wof:name":"M. Laurenz Gmbh",
    "wof:placetype":"venue"
},
  "geometry": {"coordinates":[7.4753599167,52.0510864258],"type":"Point"}
}