{
  "type": "Feature",
  "properties": {
    "iso:country":"DE",
    "sg:address":"Poststr. 3",
    "sg:city":"L\u00f6ningen",
    "sg:phone":"+49 5432/30245",
    "sg:postcode":"49624",
    "sg:province":"Niedersachsen",
    "wof:name":"Kebab Haus",
    "wof:placetype":"venue"
},
  "geometry": {"coordinates":[7.7580981255,52.7351646423],"type":"Point"}
}