{
  "type": "Feature",
  "properties": {
    "iso:country":"DE",
    "sg:address":"Kupfertwete 7",
    "sg:city":"Braunschweig",
    "sg:phone":"+49 531/45378",
    "sg:postcode":"38100",
    "sg:province":"Niedersachsen",
    "wof:name":"R. Blankenstein",
    "wof:placetype":"venue"
},
  "geometry": {"coordinates":[10.5182609558,52.2680244446],"type":"Point"}
}