{
  "type": "Feature",
  "properties": {
    "iso:country":"DE",
    "sg:address":"Wiesenwinkel 5",
    "sg:city":"Berlin",
    "sg:phone":"+49 30/4853928",
    "sg:postcode":"13158",
    "sg:province":"Berlin",
    "wof:name":"Baucon Beratende Ingenieure Gmbh",
    "wof:placetype":"venue"
},
  "geometry": {"coordinates":[13.3798074722,52.5938987732],"type":"Point"}
}