{
  "type": "Feature",
  "properties": {
    "iso:country":"DE",
    "sg:address":"Nienberger Str. 4",
    "sg:city":"M\u00fcnster",
    "sg:phone":"+49 251/216454",
    "sg:postcode":"48159",
    "sg:province":"Nordrhein-Westfalen",
    "wof:name":"Hansen-koering",
    "wof:placetype":"venue"
},
  "geometry": {"coordinates":[7.5961141586,52.0438041687],"type":"Point"}
}