{
  "type": "Feature",
  "properties": {
    "iso:country":"DE",
    "sg:address":"Kaiserg\u00e4\u00dfchen 9",
    "sg:city":"Kaufbeuren",
    "sg:phone":"+49 8341/16322",
    "sg:postcode":"87600",
    "sg:province":"Bayern",
    "wof:name":"U. Konrad",
    "wof:placetype":"venue"
},
  "geometry": {"coordinates":[10.619581,47.879536],"type":"Point"}
}