{
  "type": "Feature",
  "properties": {
    "iso:country":"DE",
    "sg:address":"Tegernau",
    "sg:city":"Wasserburg",
    "sg:postcode":"83512",
    "sg:province":"Bayern",
    "wof:name":"Bay Wa Bau- Und Gartenmarkt",
    "wof:placetype":"venue"
},
  "geometry": {"coordinates":[12.2207727432,48.0474662781],"type":"Point"}
}