{
  "type": "Feature",
  "properties": {
    "iso:country":"DE",
    "sg:address":"Lindenstr. 30",
    "sg:city":"R\u00fcckmarsdorf",
    "sg:phone":"+49 341/9411400",
    "sg:postcode":"04430",
    "wof:name":"J\u00f6rg Schmidt",
    "wof:placetype":"venue"
},
  "geometry": {"coordinates":[12.2526397705,51.3444786072],"type":"Point"}
}