{
  "type": "Feature",
  "properties": {
    "iso:country":"DE",
    "sg:address":"Hausotterstr. 97",
    "sg:city":"Berlin",
    "sg:phone":"+49 4950/4293000",
    "sg:postcode":"13409",
    "sg:province":"Berlin",
    "wof:name":"Krone Maschinenbau Gmbh",
    "wof:placetype":"venue"
},
  "geometry": {"coordinates":[9.452375,52.192066],"type":"Point"}
}