{
  "type": "Feature",
  "properties": {
    "iso:country":"DE",
    "sg:address":"Graf-Otto-Str. 39",
    "sg:city":"Bergheim",
    "sg:phone":"+49 2271/93630",
    "sg:postcode":"50127",
    "sg:province":"Nordrhein-Westfalen",
    "wof:name":"Peter Bach",
    "wof:placetype":"venue"
},
  "geometry": {"coordinates":[6.6772871017,50.9405822754],"type":"Point"}
}