{
  "type": "Feature",
  "properties": {
    "iso:country":"DE",
    "sg:address":"L\u00f6dingser Str. 5",
    "sg:city":"Hardegsen",
    "sg:phone":"+49 5505/5966",
    "sg:postcode":"37181",
    "sg:province":"Niedersachsen",
    "wof:name":"Holzwerkstatt Hettensen Gmbh",
    "wof:placetype":"venue"
},
  "geometry": {"coordinates":[9.790592,51.616398],"type":"Point"}
}