{
  "type": "Feature",
  "properties": {
    "iso:country":"DE",
    "sg:address":"Nordplatz 11",
    "sg:city":"Altenburg",
    "sg:phone":"+49 3447/82055",
    "sg:postcode":"04600",
    "sg:province":"Th\u00fcringen",
    "wof:name":"Marcusson-apotheke Inh. Steffen Haage",
    "wof:placetype":"venue"
},
  "geometry": {"coordinates":[12.430153,50.988918],"type":"Point"}
}