{
  "type": "Feature",
  "properties": {
    "iso:country":"DE",
    "sg:address":"Geiningen 20",
    "sg:city":"Waldbr\u00f6l",
    "sg:phone":"+49 2291/7756",
    "sg:postcode":"51545",
    "sg:province":"Nordrhein-Westfalen",
    "wof:name":"Gustav M\u00fcller",
    "wof:placetype":"venue"
},
  "geometry": {"coordinates":[7.679479,50.893509],"type":"Point"}
}