{
  "type": "Feature",
  "properties": {
    "iso:country":"DE",
    "sg:address":"Belterstr. 4",
    "sg:city":"Leipzig",
    "sg:postcode":"04347",
    "sg:province":"Sachsen",
    "wof:name":"Klaus Janicke",
    "wof:placetype":"venue"
},
  "geometry": {"coordinates":[12.421485,51.356091],"type":"Point"}
}