{
  "type": "Feature",
  "properties": {
    "iso:country":"DE",
    "sg:address":"Rotenh\u00f6fer Weg 48",
    "sg:city":"Rendsburg",
    "sg:phone":"+49 4331/71205",
    "sg:postcode":"24768",
    "sg:province":"Schleswig-Holstein",
    "wof:name":"Jugendherberge Rendsburg",
    "wof:placetype":"venue"
},
  "geometry": {"coordinates":[9.6369657516,54.3107070923],"type":"Point"}
}