{
  "type": "Feature",
  "properties": {
    "iso:country":"DE",
    "sg:address":"Mariendorfer Damm 185",
    "sg:city":"Berlin",
    "sg:phone":"+49 30/7050229",
    "sg:postcode":"12107",
    "sg:province":"Berlin",
    "wof:name":"Kreativ-boutique Inh. Gisela Vogel",
    "wof:placetype":"venue"
},
  "geometry": {"coordinates":[13.3896751404,52.4354553223],"type":"Point"}
}