{
  "type": "Feature",
  "properties": {
    "iso:country":"DE",
    "sg:address":"Stettenerberg 15",
    "sg:city":"Erkelenz",
    "sg:phone":"+49 2435/3345",
    "sg:postcode":"41812",
    "sg:province":"Nordrhein-Westfalen",
    "wof:name":"Robert Jansen",
    "wof:placetype":"venue"
},
  "geometry": {"coordinates":[6.3198680878,51.0356826782],"type":"Point"}
}