{
  "type": "Feature",
  "properties": {
    "iso:country":"DE",
    "sg:address":"Carl-Zeiss-Str. 14",
    "sg:city":"Offenburg",
    "sg:phone":"+49 781/990000",
    "sg:postcode":"77656",
    "sg:province":"Baden-W\u00fcrttemberg",
    "wof:name":"G. Ruder Gmbh",
    "wof:placetype":"venue"
},
  "geometry": {"coordinates":[7.929364,48.437653],"type":"Point"}
}