{
  "type": "Feature",
  "properties": {
    "iso:country":"DE",
    "sg:address":"Schwanthalerstr. 139",
    "sg:city":"M\u00fcnchen",
    "sg:phone":"+49 89/5029994",
    "sg:postcode":"80339",
    "sg:province":"Bayern",
    "wof:name":"Druckwerk Druckerei Gmbh",
    "wof:placetype":"venue"
},
  "geometry": {"coordinates":[11.543077,48.137661],"type":"Point"}
}