{
  "type": "Feature",
  "properties": {
    "iso:country":"DE",
    "sg:address":"Silcherstr. 5",
    "sg:city":"Dresden",
    "sg:phone":"+49 351/8906034",
    "sg:postcode":"01109",
    "sg:province":"Sachsen",
    "wof:name":"G\u00e4stehaus P. Kotas",
    "wof:placetype":"venue"
},
  "geometry": {"coordinates":[13.7710065842,51.1095962524],"type":"Point"}
}