{
  "type": "Feature",
  "properties": {
    "iso:country":"DE",
    "sg:address":"Industriezubringer 48",
    "sg:city":"Cloppenburg",
    "sg:postcode":"49661",
    "sg:province":"Niedersachsen",
    "wof:name":"Agfo Agrar- Und Forstwirtschaftsbetriebs Gmbh",
    "wof:placetype":"venue"
},
  "geometry": {"coordinates":[8.0838165283,52.8508605957],"type":"Point"}
}