{
  "type": "Feature",
  "properties": {
    "iso:country":"DE",
    "sg:address":"Bahnhofstr. 35",
    "sg:city":"Xanten",
    "sg:phone":"+49 2801/2489",
    "sg:postcode":"46509",
    "sg:province":"Nordrhein-Westfalen",
    "wof:name":"Waldemar Simon",
    "wof:placetype":"venue"
},
  "geometry": {"coordinates":[6.4481048584,51.658946991],"type":"Point"}
}