{
  "type": "Feature",
  "properties": {
    "iso:country":"DE",
    "sg:address":"Hoengener Str. 49",
    "sg:city":"Alsdorf",
    "sg:phone":"+49 2404/25204",
    "sg:postcode":"52477",
    "sg:province":"Nordrhein-Westfalen",
    "wof:name":"Horst M\u00fcller",
    "wof:placetype":"venue"
},
  "geometry": {"coordinates":[6.183111,50.87516],"type":"Point"}
}