{
  "type": "Feature",
  "properties": {
    "iso:country":"DE",
    "sg:address":"Birkendorfer Str 65",
    "sg:city":"Biberach",
    "sg:phone":"+49 6894/9710",
    "sg:postcode":"88400",
    "sg:province":"Baden-W\u00fcrttemberg",
    "wof:name":"Chephasaar Chemisch-pharmazeutische Fabrik Gmbh",
    "wof:placetype":"venue"
},
  "geometry": {"coordinates":[7.1577920914,49.2896461487],"type":"Point"}
}