{
  "type": "Feature",
  "properties": {
    "iso:country":"DE",
    "sg:address":"Tivolistr. 26",
    "sg:city":"D\u00fcren",
    "sg:phone":"+49 2421/44160",
    "sg:postcode":"52349",
    "sg:province":"Nordrhein-Westfalen",
    "wof:name":"Tivoli-apotheke",
    "wof:placetype":"venue"
},
  "geometry": {"coordinates":[6.47637,50.803192],"type":"Point"}
}