{
  "type": "Feature",
  "properties": {
    "iso:country":"DE",
    "sg:address":"Seidenstr. 42",
    "sg:city":"Stuttgart",
    "sg:phone":"+49 4971/1294931",
    "sg:postcode":"70174",
    "sg:province":"Baden-W\u00fcrttemberg",
    "wof:name":"Martin Kugler",
    "wof:placetype":"venue"
},
  "geometry": {"coordinates":[9.1653995514,48.7818946838],"type":"Point"}
}