{
  "type": "Feature",
  "properties": {
    "iso:country":"DE",
    "sg:address":"Solmsstr. 25",
    "sg:city":"Frankfurt",
    "sg:phone":"+49 69/792030",
    "sg:postcode":"60486",
    "sg:province":"Hessen",
    "wof:name":"Omnia Gesellschaft F\u00fcr Verwaltung",
    "wof:placetype":"venue"
},
  "geometry": {"coordinates":[8.634262,50.118416],"type":"Point"}
}