{
  "type": "Feature",
  "properties": {
    "iso:country":"DE",
    "sg:address":"Celsiusstr. 1",
    "sg:city":"Trappenkamp",
    "sg:phone":"+49 4323/2606",
    "sg:postcode":"24610",
    "sg:province":"Schleswig-Holstein",
    "wof:name":"Emil Andresen",
    "wof:placetype":"venue"
},
  "geometry": {"coordinates":[10.2194461823,54.0430107117],"type":"Point"}
}