{
  "type": "Feature",
  "properties": {
    "iso:country":"DE",
    "sg:address":"Bacharacher Str. 59",
    "sg:city":"Rheinb\u00f6llen",
    "sg:phone":"+49 6764/1276",
    "sg:postcode":"55494",
    "sg:province":"Rheinland-Pfalz",
    "wof:name":"Gerhard H\u00f6lz Tankstelle",
    "wof:placetype":"venue"
},
  "geometry": {"coordinates":[7.6746459007,50.010181427],"type":"Point"}
}