{
  "type": "Feature",
  "properties": {
    "iso:country":"DE",
    "sg:address":"Maderbichl 5",
    "sg:city":"Steingaden",
    "sg:postcode":"86989",
    "sg:province":"Bayern",
    "wof:name":"Arp Ger\u00e4te- Und Maschinen- Vertriebs Gmbh",
    "wof:placetype":"venue"
},
  "geometry": {"coordinates":[10.8510694504,47.7202949524],"type":"Point"}
}