{
  "type": "Feature",
  "properties": {
    "iso:country":"DE",
    "sg:address":"Angerstr. 5",
    "sg:city":"F\u00fcrth",
    "sg:phone":"+49 911/776365",
    "sg:postcode":"90762",
    "sg:province":"Bayern",
    "wof:name":"Kurz",
    "wof:placetype":"venue"
},
  "geometry": {"coordinates":[10.986715,49.480289],"type":"Point"}
}