{
  "type": "Feature",
  "properties": {
    "iso:country":"DE",
    "sg:address":"Karolinenstr 6",
    "sg:city":"Hamburg",
    "sg:phone":"+49 40/2840300",
    "sg:postcode":"20357",
    "sg:province":"Hamburg",
    "wof:name":"Contelle",
    "wof:placetype":"venue"
},
  "geometry": {"coordinates":[9.9752693176,53.5575256348],"type":"Point"}
}