{
  "type": "Feature",
  "properties": {
    "iso:country":"DE",
    "sg:address":"Am Nemerberg 2",
    "sg:city":"Taufkirchen",
    "sg:phone":"+49 8638/72846",
    "sg:postcode":"84574",
    "sg:province":"Bayern",
    "wof:name":"Johann H\u00f6lzl",
    "wof:placetype":"venue"
},
  "geometry": {"coordinates":[12.453775,48.147324],"type":"Point"}
}