{
  "type": "Feature",
  "properties": {
    "iso:country":"DE",
    "sg:address":"Hauptstr. 111",
    "sg:city":"Todenb\u00fcttel",
    "sg:phone":"+49 4874/392",
    "sg:postcode":"24819",
    "sg:province":"Schleswig-Holstein",
    "wof:name":"Eduard Sievers Gmbh & Co. Kg",
    "wof:placetype":"venue"
},
  "geometry": {"coordinates":[9.541142,54.122021],"type":"Point"}
}