{
  "type": "Feature",
  "properties": {
    "iso:country":"DE",
    "sg:address":"Alfred-Nobel-Str. 1-5",
    "sg:city":"Frechen",
    "sg:phone":"+49 2234/929282",
    "sg:postcode":"50226",
    "sg:province":"Nordrhein-Westfalen",
    "wof:name":"Hotel Dynamit",
    "wof:placetype":"venue"
},
  "geometry": {"coordinates":[6.8256969452,50.9184570312],"type":"Point"}
}