{
  "type": "Feature",
  "properties": {
    "iso:country":"DE",
    "sg:address":"Sch\u00f6nhauser Allee 44 a",
    "sg:city":"Berlin",
    "sg:phone":"+49 30/4433800",
    "sg:postcode":"10435",
    "sg:province":"Berlin",
    "wof:name":"Leben Vital Gmbh",
    "wof:placetype":"venue"
},
  "geometry": {"coordinates":[13.4125947952,52.5406150818],"type":"Point"}
}