{
  "type": "Feature",
  "properties": {
    "iso:country":"DE",
    "sg:address":"Pilgerpatt 8",
    "sg:city":"Rheda-Wiedenbr\u00fcck",
    "sg:phone":"+49 5242/7048",
    "sg:postcode":"33378",
    "sg:province":"Nordrhein-Westfalen",
    "wof:name":"Hansmeier Gmbh",
    "wof:placetype":"venue"
},
  "geometry": {"coordinates":[8.3203134537,51.8509788513],"type":"Point"}
}