{
  "type": "Feature",
  "properties": {
    "iso:country":"DE",
    "sg:address":"Borngasse 7a",
    "sg:city":"Gro\u00dfkrotzenburg",
    "sg:postcode":"63538",
    "sg:province":"Hessen",
    "wof:name":"Alpha-bau Gmbh",
    "wof:placetype":"venue"
},
  "geometry": {"coordinates":[8.9779758453,50.0803833008],"type":"Point"}
}