{
  "type": "Feature",
  "properties": {
    "iso:country":"DE",
    "sg:address":"Domstr. 6",
    "sg:city":"Verden",
    "sg:phone":"+49 4231/2357",
    "sg:postcode":"27283",
    "sg:province":"Niedersachsen",
    "wof:name":"Hehl Gmbh",
    "wof:placetype":"venue"
},
  "geometry": {"coordinates":[9.2277946472,52.9172325134],"type":"Point"}
}