{
  "type": "Feature",
  "properties": {
    "iso:country":"DE",
    "sg:address":"Kroneng\u00e4ssle 3",
    "sg:city":"Tettnang",
    "sg:postcode":"88069",
    "sg:province":"Baden-W\u00fcrttemberg",
    "wof:name":"Vet-com-pharma Gmbh",
    "wof:placetype":"venue"
},
  "geometry": {"coordinates":[9.588312149,47.6711158752],"type":"Point"}
}