{
  "type": "Feature",
  "properties": {
    "iso:country":"DE",
    "sg:address":"Feldstr. 1",
    "sg:city":"Leese",
    "sg:phone":"+49 5761/92040",
    "sg:postcode":"31633",
    "sg:province":"Niedersachsen",
    "wof:name":"Poppe Fleischhandel Gmbh",
    "wof:placetype":"venue"
},
  "geometry": {"coordinates":[9.1159124374,52.5016822815],"type":"Point"}
}