{
  "type": "Feature",
  "properties": {
    "iso:country":"DE",
    "sg:address":"Gro\u00dfe J\u00fcch 6",
    "sg:city":"Erftstadt",
    "sg:phone":"+49 2235/5657",
    "sg:postcode":"50374",
    "sg:province":"Nordrhein-Westfalen",
    "wof:name":"Moersch Gmbh",
    "wof:placetype":"venue"
},
  "geometry": {"coordinates":[6.757015,50.796829],"type":"Point"}
}