{
  "type": "Feature",
  "properties": {
    "iso:country":"DE",
    "sg:address":"Landstr. 6",
    "sg:city":"Kitzscher",
    "sg:phone":"+49 34345/24193",
    "sg:postcode":"04567",
    "sg:province":"Sachsen",
    "wof:name":"Sportlerheim Inh. F. H\u00fcsken",
    "wof:placetype":"venue"
},
  "geometry": {"coordinates":[12.531457901,51.1695175171],"type":"Point"}
}