{
  "type": "Feature",
  "properties": {
    "iso:country":"DE",
    "sg:address":"Pfarrgasse 22",
    "sg:city":"Pfungstadt",
    "sg:phone":"+49 6157/2502",
    "sg:postcode":"64319",
    "sg:province":"Hessen",
    "wof:name":"Falk-h\u00f6rr",
    "wof:placetype":"venue"
},
  "geometry": {"coordinates":[8.601111,49.803055],"type":"Point"}
}