{
  "type": "Feature",
  "properties": {
    "iso:country":"DE",
    "sg:address":"Am Fuchsberg 2",
    "sg:city":"Wolgast",
    "sg:phone":"+49 3836/202572",
    "sg:postcode":"17438",
    "sg:province":"Mecklenburg-Vorpommern",
    "wof:name":"Dea Tankstelle Gudrun Broneske",
    "wof:placetype":"venue"
},
  "geometry": {"coordinates":[13.7527389526,54.0475769043],"type":"Point"}
}