{
  "type": "Feature",
  "properties": {
    "iso:country":"DE",
    "sg:address":"Ettlinger Str. 27",
    "sg:city":"Karlsruhe",
    "sg:phone":"+49 721/932280",
    "sg:postcode":"76137",
    "sg:province":"Baden-W\u00fcrttemberg",
    "wof:name":"J. Tremml",
    "wof:placetype":"venue"
},
  "geometry": {"coordinates":[8.4038200378,48.9989395142],"type":"Point"}
}