{
  "type": "Feature",
  "properties": {
    "iso:country":"DE",
    "sg:address":"Karl-Unsin-Str. 2",
    "sg:city":"Kolbermoor",
    "sg:phone":"+49 8031/91858",
    "sg:postcode":"83059",
    "sg:province":"Bayern",
    "wof:name":"Leopold Haiberger",
    "wof:placetype":"venue"
},
  "geometry": {"coordinates":[12.0664196014,47.8496208191],"type":"Point"}
}