{
  "type": "Feature",
  "properties": {
    "iso:country":"DE",
    "sg:address":"Werner-Heisenberg-Str. 26",
    "sg:city":"Viernheim",
    "sg:phone":"+49 6204/79045",
    "sg:postcode":"68519",
    "sg:province":"Hessen",
    "wof:name":"Salco Vertriebs Gmbh",
    "wof:placetype":"venue"
},
  "geometry": {"coordinates":[8.5964050293,49.5531616211],"type":"Point"}
}