{
  "type": "Feature",
  "properties": {
    "iso:country":"DE",
    "sg:address":"Aachener Str. 9",
    "sg:city":"Bergheim",
    "sg:phone":"+49 2271/41179",
    "sg:postcode":"50126",
    "sg:province":"Nordrhein-Westfalen",
    "wof:name":"Siegener Nachf. M. Pickel",
    "wof:placetype":"venue"
},
  "geometry": {"coordinates":[6.627335,50.951233],"type":"Point"}
}