{
  "type": "Feature",
  "properties": {
    "iso:country":"DE",
    "sg:address":"Ludenberger Str. 39",
    "sg:city":"D\u00fcsseldorf",
    "sg:phone":"+49 211/682266",
    "sg:postcode":"40629",
    "sg:province":"Nordrhein-Westfalen",
    "wof:name":"Grafenberger Br\u00e4uhaus",
    "wof:placetype":"venue"
},
  "geometry": {"coordinates":[6.8340811729,51.2401161194],"type":"Point"}
}