{
  "type": "Feature",
  "properties": {
    "iso:country":"DE",
    "sg:address":"Reichsbahnstr. 55",
    "sg:city":"Hamburg",
    "sg:phone":"+49 40/57230",
    "sg:postcode":"22525",
    "sg:province":"Hamburg",
    "wof:name":"Berufsbildungswerk Hamburg Gmbh",
    "wof:placetype":"venue"
},
  "geometry": {"coordinates":[9.9060964584,53.6006698608],"type":"Point"}
}