{
  "type": "Feature",
  "properties": {
    "iso:country":"DE",
    "sg:address":"Schleidenstr. 6",
    "sg:city":"Hamburg",
    "sg:phone":"+49 40/2806426",
    "sg:postcode":"22083",
    "sg:province":"Hamburg",
    "wof:name":"Fu\u00dforthop\u00e4die Holger L\u00fctz",
    "wof:placetype":"venue"
},
  "geometry": {"coordinates":[10.0337982178,53.5833053589],"type":"Point"}
}