{
  "type": "Feature",
  "properties": {
    "iso:country":"DE",
    "sg:address":"Paracelsusstr. 49",
    "sg:city":"Leonberg",
    "sg:phone":"+49 7152/49554",
    "sg:postcode":"71229",
    "sg:province":"Baden-W\u00fcrttemberg",
    "wof:name":"Eickhoff & Partner Gmbh",
    "wof:placetype":"venue"
},
  "geometry": {"coordinates":[9.0279445648,48.7906646729],"type":"Point"}
}