{
  "type": "Feature",
  "properties": {
    "iso:country":"DE",
    "sg:address":"Hermann-Bohne-Str. 21",
    "sg:city":"Bramsche",
    "sg:phone":"+49 5461/99590",
    "sg:postcode":"49565",
    "sg:province":"Niedersachsen",
    "wof:name":"Graphischer Betrieb Niemann & G\u00fcnther",
    "wof:placetype":"venue"
},
  "geometry": {"coordinates":[7.97942,52.406696],"type":"Point"}
}