{
  "type": "Feature",
  "properties": {
    "iso:country":"DE",
    "sg:address":"Ludwigstrasse 20",
    "sg:city":"Halle",
    "sg:phone":"+49 345/133550",
    "sg:postcode":"06110",
    "sg:province":"Sachsen-Anhalt",
    "wof:name":"Photovoltaik Solartechnik Von Pusch & Co. Elektro",
    "wof:placetype":"venue"
},
  "geometry": {"coordinates":[11.964276,51.470963],"type":"Point"}
}