{
  "type": "Feature",
  "properties": {
    "iso:country":"DE",
    "sg:address":"Rickertsreute 4",
    "sg:city":"Heiligenberg",
    "sg:phone":"+49 7554/426",
    "sg:postcode":"88633",
    "sg:province":"Baden-W\u00fcrttemberg",
    "wof:name":"H. Ermler",
    "wof:placetype":"venue"
},
  "geometry": {"coordinates":[9.325095,47.858685],"type":"Point"}
}