{
  "type": "Feature",
  "properties": {
    "iso:country":"DE",
    "sg:address":"Von-Flotow-Str. 16a",
    "sg:city":"Schwerin",
    "sg:phone":"+49 385/732014",
    "sg:postcode":"19059",
    "sg:province":"Mecklenburg-Vorpommern",
    "wof:name":"Lundia-vertrieb Wilfried Stech",
    "wof:placetype":"venue"
},
  "geometry": {"coordinates":[11.3901147842,53.6259613037],"type":"Point"}
}