{
  "type": "Feature",
  "properties": {
    "iso:country":"DE",
    "sg:address":"Alte Pforzheimer Str. 44",
    "sg:city":"Wurmberg",
    "sg:phone":"+49 7044/43254",
    "sg:postcode":"75449",
    "sg:province":"Baden-W\u00fcrttemberg",
    "wof:name":"Herbert Binder Gmbh",
    "wof:placetype":"venue"
},
  "geometry": {"coordinates":[8.8127670288,48.8714141846],"type":"Point"}
}