{
  "type": "Feature",
  "properties": {
    "iso:country":"DE",
    "sg:address":"Siegmarstr. 31",
    "sg:city":"Berlin",
    "sg:postcode":"12683",
    "sg:province":"Berlin",
    "wof:name":"Seitz Far East Gmbh",
    "wof:placetype":"venue"
},
  "geometry": {"coordinates":[13.5736541748,52.5307693481],"type":"Point"}
}