{
  "type": "Feature",
  "properties": {
    "iso:country":"DE",
    "sg:address":"Hafeninsel 1",
    "sg:city":"Offenbach",
    "sg:phone":"+49 69/889095",
    "sg:postcode":"63067",
    "sg:province":"Hessen",
    "wof:name":"Progeha Fl\u00fcssiggas Gmbh",
    "wof:placetype":"venue"
},
  "geometry": {"coordinates":[8.745205,50.114037],"type":"Point"}
}