{
  "type": "Feature",
  "properties": {
    "iso:country":"DE",
    "sg:address":"Endenicher Allee 10",
    "sg:city":"Bonn",
    "sg:phone":"+49 228/651507",
    "sg:postcode":"53115",
    "sg:province":"Nordrhein-Westfalen",
    "wof:name":"J. Lengsfeld Rechtsanwalt",
    "wof:placetype":"venue"
},
  "geometry": {"coordinates":[7.0887799263,50.7303314209],"type":"Point"}
}