{
  "type": "Feature",
  "properties": {
    "iso:country":"DE",
    "sg:address":"B\u00f6ddinghauser Weg 89",
    "sg:city":"Plettenberg",
    "sg:phone":"+49 2391/51259",
    "sg:postcode":"58840",
    "sg:province":"Nordrhein-Westfalen",
    "wof:name":"Tripp Gmbh",
    "wof:placetype":"venue"
},
  "geometry": {"coordinates":[7.8554458618,51.2296066284],"type":"Point"}
}