{
  "type": "Feature",
  "properties": {
    "iso:country":"DE",
    "sg:address":"Friedrich-von-Schiller-Str. 10",
    "sg:city":"Duggendorf",
    "sg:postcode":"93182",
    "sg:province":"Bayern",
    "wof:name":"Vakumit Handels Gmbh",
    "wof:placetype":"venue"
},
  "geometry": {"coordinates":[11.9302625656,49.1116065979],"type":"Point"}
}