{
  "type": "Feature",
  "properties": {
    "iso:country":"DE",
    "sg:address":"Bangeltstr. 24",
    "sg:city":"Fridingen",
    "sg:postcode":"78567",
    "sg:province":"Baden-W\u00fcrttemberg",
    "wof:name":"O. Rudolf",
    "wof:placetype":"venue"
},
  "geometry": {"coordinates":[8.937171,48.029057],"type":"Point"}
}