{
  "type": "Feature",
  "properties": {
    "iso:country":"DE",
    "sg:address":"Dahlenwarsleber Str. 5",
    "sg:city":"Hohenwarsleben",
    "sg:phone":"+49 39204/61253",
    "sg:postcode":"39326",
    "sg:province":"Sachsen-Anhalt",
    "wof:name":"Teichanlage B\u00f6sche",
    "wof:placetype":"venue"
},
  "geometry": {"coordinates":[11.501172,52.1786],"type":"Point"}
}