{
  "type": "Feature",
  "properties": {
    "iso:country":"DE",
    "sg:address":"Industriestr. 19",
    "sg:city":"Ennigerloh",
    "sg:phone":"+49 2524/93120",
    "sg:postcode":"59320",
    "sg:province":"Nordrhein-Westfalen",
    "wof:name":"Geba Kunststoffcompounds Gmbh",
    "wof:placetype":"venue"
},
  "geometry": {"coordinates":[8.0259780884,51.8525161743],"type":"Point"}
}