{
  "type": "Feature",
  "properties": {
    "iso:country":"DE",
    "sg:address":"Br\u00fchlstr. 19",
    "sg:city":"Ulm",
    "sg:phone":"+49 731/64081",
    "sg:postcode":"89081",
    "sg:province":"Baden-W\u00fcrttemberg",
    "wof:name":"Karl St\u00e4b",
    "wof:placetype":"venue"
},
  "geometry": {"coordinates":[9.9885883331,48.4458084106],"type":"Point"}
}