{
  "type": "Feature",
  "properties": {
    "iso:country":"DE",
    "sg:address":"Feuergraben 4",
    "sg:city":"Hameln",
    "sg:phone":"+49 5151/7030",
    "sg:postcode":"31785",
    "sg:province":"Niedersachsen",
    "wof:name":"Rolf-r\u00fcdiger Runte Rechtsanwalt Und Notar",
    "wof:placetype":"venue"
},
  "geometry": {"coordinates":[9.3592147827,52.1094207764],"type":"Point"}
}