{
  "type": "Feature",
  "properties": {
    "iso:country":"DE",
    "sg:address":"Heinrich-Nicolaus-Str. 20",
    "sg:city":"Dachau",
    "sg:phone":"+49 8131/87337",
    "sg:postcode":"85221",
    "sg:province":"Bayern",
    "wof:name":"M\u00e4rkl Zimmerei Und Bautr\u00e4ger Gmbh",
    "wof:placetype":"venue"
},
  "geometry": {"coordinates":[11.4343423843,48.2594070435],"type":"Point"}
}