{
  "type": "Feature",
  "properties": {
    "iso:country":"DE",
    "sg:address":"Am Falm 332",
    "sg:city":"Helgoland",
    "sg:phone":"+49 4725/81400",
    "sg:postcode":"27498",
    "sg:province":"Schleswig-Holstein",
    "wof:name":"Hotel Wiesbaden",
    "wof:placetype":"venue"
},
  "geometry": {"coordinates":[7.887116909,54.1828956604],"type":"Point"}
}