{
  "type": "Feature",
  "properties": {
    "iso:country":"DE",
    "sg:address":"Yorckstr. 40",
    "sg:city":"Mittenwalde",
    "sg:phone":"+49 33764/20373",
    "sg:postcode":"15749",
    "sg:province":"Brandenburg",
    "wof:name":"Fritz Schulz",
    "wof:placetype":"venue"
},
  "geometry": {"coordinates":[13.5374794006,52.2626953125],"type":"Point"}
}