{
  "type": "Feature",
  "properties": {
    "iso:country":"DE",
    "sg:address":"Fr\u00f6belstr. 58",
    "sg:city":"Bremen",
    "sg:phone":"+49 421/6520202",
    "sg:postcode":"28755",
    "sg:province":"Bremen",
    "wof:name":"J. Rosenberger",
    "wof:placetype":"venue"
},
  "geometry": {"coordinates":[8.6030502319,53.1760635376],"type":"Point"}
}