{
  "type": "Feature",
  "properties": {
    "iso:country":"DE",
    "sg:address":"Bahnhofstr. 39",
    "sg:city":"Tuttlingen",
    "sg:phone":"+49 7461/3494",
    "sg:postcode":"78532",
    "sg:province":"Baden-W\u00fcrttemberg",
    "wof:name":"Schlecker",
    "wof:placetype":"venue"
},
  "geometry": {"coordinates":[8.8144779205,47.9835166931],"type":"Point"}
}