{
  "type": "Feature",
  "properties": {
    "iso:country":"DE",
    "sg:address":"Hauptstr. 3",
    "sg:city":"Oberau",
    "sg:phone":"+49 8824/335",
    "sg:postcode":"82496",
    "sg:province":"Bayern",
    "wof:name":"Akr Steuerberatungs-gmbh",
    "wof:placetype":"venue"
},
  "geometry": {"coordinates":[11.1374931335,47.5600090027],"type":"Point"}
}