{
  "type": "Feature",
  "properties": {
    "iso:country":"DE",
    "sg:address":"Am Bettelsee 2",
    "sg:city":"Hallstadt",
    "sg:phone":"+49 951/74740",
    "sg:postcode":"96103",
    "sg:province":"Bayern",
    "wof:name":"Brose Verwaltungsges. Mbh",
    "wof:placetype":"venue"
},
  "geometry": {"coordinates":[10.898809,49.926991],"type":"Point"}
}