{
  "type": "Feature",
  "properties": {
    "iso:country":"DE",
    "sg:address":"Bitterfelder Str. 9",
    "sg:city":"Bad D\u00fcben",
    "sg:phone":"+49 34243/24756",
    "sg:postcode":"04849",
    "sg:province":"Sachsen",
    "wof:name":"Bruno Gerlach",
    "wof:placetype":"venue"
},
  "geometry": {"coordinates":[12.5832471848,51.5939865112],"type":"Point"}
}