{
  "type": "Feature",
  "properties": {
    "iso:country":"DE",
    "sg:address":"Xylanderstr. 23",
    "sg:city":"Landau",
    "sg:postcode":"76829",
    "sg:province":"Rheinland-Pfalz",
    "wof:name":"Immobilien Boltz Gmbh",
    "wof:placetype":"venue"
},
  "geometry": {"coordinates":[8.1130237579,49.1926078796],"type":"Point"}
}