{
  "type": "Feature",
  "properties": {
    "iso:country":"DE",
    "sg:address":"Eupener Str. 1",
    "sg:city":"D\u00fcsseldorf",
    "sg:phone":"+49 211/5623243",
    "sg:postcode":"40549",
    "sg:province":"Nordrhein-Westfalen",
    "wof:name":"Weggen Am Handweiser",
    "wof:placetype":"venue"
},
  "geometry": {"coordinates":[6.6980628967,51.2283325195],"type":"Point"}
}