{
  "type": "Feature",
  "properties": {
    "iso:country":"DE",
    "sg:address":"Rosengartenplatz 3-5",
    "sg:city":"Mannheim",
    "sg:postcode":"68161",
    "sg:province":"Baden-W\u00fcrttemberg",
    "wof:name":"Industriedruck Kurpfalz Gmbh",
    "wof:placetype":"venue"
},
  "geometry": {"coordinates":[8.4762592316,49.4850387573],"type":"Point"}
}