{
  "type": "Feature",
  "properties": {
    "iso:country":"DE",
    "sg:address":"Hohensteiner Str. 25",
    "sg:city":"Niederw\u00fcrschnitz",
    "sg:phone":"+49 37296/80716",
    "sg:postcode":"09399",
    "sg:province":"Sachsen",
    "wof:name":"Physiotherapie A. Hahn Gmbh",
    "wof:placetype":"venue"
},
  "geometry": {"coordinates":[12.7537117004,50.7245140076],"type":"Point"}
}