{
  "type": "Feature",
  "properties": {
    "iso:country":"DE",
    "sg:address":"Westernfeld 7",
    "sg:city":"Essen",
    "sg:phone":"+49 201/420664",
    "sg:postcode":"45133",
    "sg:province":"Nordrhein-Westfalen",
    "wof:name":"Wilhelm Janinhoff Rechtsanwalt",
    "wof:placetype":"venue"
},
  "geometry": {"coordinates":[6.9829158783,51.409576416],"type":"Point"}
}