{
  "type": "Feature",
  "properties": {
    "iso:country":"DE",
    "sg:address":"Keldenicher Str. 22",
    "sg:city":"Wesseling",
    "sg:phone":"+49 2236/81292",
    "sg:postcode":"50389",
    "sg:province":"Nordrhein-Westfalen",
    "wof:name":"M. Koch",
    "wof:placetype":"venue"
},
  "geometry": {"coordinates":[6.972096,50.81649],"type":"Point"}
}