{
  "type": "Feature",
  "properties": {
    "iso:country":"DE",
    "sg:address":"Kaiserswerther Str. 128",
    "sg:city":"Krefeld",
    "sg:phone":"+49 2151/571479",
    "sg:postcode":"47809",
    "sg:province":"Nordrhein-Westfalen",
    "wof:name":"Heinz Raven",
    "wof:placetype":"venue"
},
  "geometry": {"coordinates":[6.665109,51.329903],"type":"Point"}
}