{
  "type": "Feature",
  "properties": {
    "iso:country":"DE",
    "sg:address":"Sommergasse 2",
    "sg:city":"Br\u00e4unlingen",
    "sg:phone":"+49 771",
    "sg:postcode":"78199",
    "sg:province":"Baden-W\u00fcrttemberg",
    "wof:name":"Kornelia Bertsche - Freie Malerin Aus Br\u00e4unlingen",
    "wof:placetype":"venue"
},
  "geometry": {"coordinates":[8.449313,47.9305],"type":"Point"}
}