{
  "type": "Feature",
  "properties": {
    "iso:country":"DE",
    "sg:address":"Maria-Schlegel-Str. 1",
    "sg:city":"Ki\u00dflegg",
    "sg:phone":"+49 7563/641",
    "sg:postcode":"88353",
    "sg:province":"Baden-W\u00fcrttemberg",
    "wof:name":"Lamm",
    "wof:placetype":"venue"
},
  "geometry": {"coordinates":[9.8825845718,47.7877159119],"type":"Point"}
}