{
  "type": "Feature",
  "properties": {
    "iso:country":"DE",
    "sg:address":"Westerwaldstr. 1",
    "sg:city":"Oberhausen",
    "sg:phone":"+49 208/669130",
    "sg:postcode":"46145",
    "sg:province":"Nordrhein-Westfalen",
    "wof:name":"H. Leggewie",
    "wof:placetype":"venue"
},
  "geometry": {"coordinates":[6.8630428314,51.5110054016],"type":"Point"}
}