{
  "type": "Feature",
  "properties": {
    "iso:country":"DE",
    "sg:address":"Vorderreihe 30",
    "sg:city":"L\u00fcbeck",
    "sg:phone":"+49 4502/3246",
    "sg:postcode":"23570",
    "sg:province":"Schleswig-Holstein",
    "wof:name":"Somar",
    "wof:placetype":"venue"
},
  "geometry": {"coordinates":[10.86904,53.956867],"type":"Point"}
}