{
  "type": "Feature",
  "properties": {
    "iso:country":"DE",
    "sg:address":"Breiter Weg 22",
    "sg:city":"Westoverledingen",
    "sg:phone":"+49 4955/920130",
    "sg:postcode":"26810",
    "sg:province":"Niedersachsen",
    "wof:name":"Heino Meyer",
    "wof:placetype":"venue"
},
  "geometry": {"coordinates":[7.464792,53.157402],"type":"Point"}
}