{
  "type": "Feature",
  "properties": {
    "iso:country":"DE",
    "sg:address":"Walter-von-Hohenegg-Str. 14",
    "sg:city":"Buchenberg",
    "sg:phone":"+49 8378/441",
    "sg:postcode":"87474",
    "sg:province":"Bayern",
    "wof:name":"Manfred Frey",
    "wof:placetype":"venue"
},
  "geometry": {"coordinates":[10.242835,47.69566],"type":"Point"}
}