{
  "type": "Feature",
  "properties": {
    "iso:country":"DE",
    "sg:address":"Bahnhofstr. 1 - 3",
    "sg:city":"Celle",
    "sg:phone":"+49 4951/419900",
    "sg:postcode":"29221",
    "sg:province":"Niedersachsen",
    "wof:name":"Cellesche Zeitung Schweiger & Pick Verlag Pfingsten Gmbh & Co Kg",
    "wof:placetype":"venue"
},
  "geometry": {"coordinates":[10.076128006,52.6217880249],"type":"Point"}
}