{
  "type": "Feature",
  "properties": {
    "iso:country":"DE",
    "sg:address":"Drakestr. 66",
    "sg:city":"Berlin",
    "sg:phone":"+49 30/8336228",
    "sg:postcode":"12205",
    "sg:province":"Berlin",
    "wof:name":"Kurt Standke Ingenieur",
    "wof:placetype":"venue"
},
  "geometry": {"coordinates":[13.3030595779,52.4370040894],"type":"Point"}
}