{
  "type": "Feature",
  "properties": {
    "iso:country":"DE",
    "sg:address":"Fischerbr\u00e4uwiese 9",
    "sg:city":"Bad Reichenhall",
    "sg:phone":"+49 8651/2972",
    "sg:postcode":"83435",
    "sg:province":"Bayern",
    "wof:name":"Bodo M\u00fcller Architekt-ingenieur",
    "wof:placetype":"venue"
},
  "geometry": {"coordinates":[12.868687,47.724594],"type":"Point"}
}