{
  "type": "Feature",
  "properties": {
    "iso:country":"DE",
    "sg:address":"Fiechtnerstr. 58",
    "sg:city":"Stuttgart",
    "sg:postcode":"70327",
    "sg:province":"Baden-W\u00fcrttemberg",
    "wof:name":"Verein Griechischer Eltern Und Erziehungsberechtigter",
    "wof:placetype":"venue"
},
  "geometry": {"coordinates":[9.248167038,48.7897148132],"type":"Point"}
}