{
  "type": "Feature",
  "properties": {
    "iso:country":"DE",
    "sg:address":"Selztalstra\u00dfe 149",
    "sg:city":"Ingelheim",
    "sg:phone":"+49 6132",
    "sg:postcode":"55218",
    "sg:province":"Rheinland-Pfalz",
    "wof:name":"Unternehmensberatung Dipl.-ing. J\u00fcrgen Peitz",
    "wof:placetype":"venue"
},
  "geometry": {"coordinates":[8.051812,49.970898],"type":"Point"}
}