{
  "type": "Feature",
  "properties": {
    "iso:country":"DE",
    "sg:address":"S\u00fcdstr. 19",
    "sg:city":"Beckum",
    "sg:phone":"+49 2521/93410",
    "sg:postcode":"59269",
    "sg:province":"Nordrhein-Westfalen",
    "wof:name":"Stelma Industrieanlagen Gmbh",
    "wof:placetype":"venue"
},
  "geometry": {"coordinates":[8.038185,51.754333],"type":"Point"}
}