{
  "type": "Feature",
  "properties": {
    "iso:country":"DE",
    "sg:address":"Mainzer Str. 28",
    "sg:city":"Nierstein",
    "sg:phone":"+49 6133/59059",
    "sg:postcode":"55283",
    "sg:province":"Rheinland-Pfalz",
    "wof:name":"Hotel Rheinischer Hof",
    "wof:placetype":"venue"
},
  "geometry": {"coordinates":[8.3419151306,49.8747558594],"type":"Point"}
}