{
  "type": "Feature",
  "properties": {
    "iso:country":"DE",
    "sg:address":"Teichstr. 5a",
    "sg:city":"Gro\u00dftreben-Zwethau",
    "sg:phone":"+49 3421/705216",
    "sg:postcode":"04886",
    "sg:province":"Sachsen",
    "wof:name":"Hausverwaltungs- Und Hausmeisterservice Gmbh",
    "wof:placetype":"venue"
},
  "geometry": {"coordinates":[13.0379724503,51.602432251],"type":"Point"}
}