{
  "type": "Feature",
  "properties": {
    "iso:country":"DE",
    "sg:address":"Gest\u00fctstr. 8",
    "sg:city":"Bad Harzburg",
    "sg:phone":"+49 5322/988096",
    "sg:postcode":"38667",
    "sg:province":"Niedersachsen",
    "wof:name":"Parit\u00e4tischer Goslar Sozialstation Bad Harzburg",
    "wof:placetype":"venue"
},
  "geometry": {"coordinates":[10.546649,51.889095],"type":"Point"}
}