{
  "type": "Feature",
  "properties": {
    "iso:country":"DE",
    "sg:address":"Dorfstr. 56",
    "sg:city":"Meiningen",
    "sg:postcode":"98617",
    "sg:province":"Th\u00fcringen",
    "wof:name":"Dr. Med. Manfred Klettke",
    "wof:placetype":"venue"
},
  "geometry": {"coordinates":[10.405766,50.585442],"type":"Point"}
}