{
  "type": "Feature",
  "properties": {
    "iso:country":"DE",
    "sg:address":"Auf dem Piepenst\u00f6cken 8",
    "sg:city":"Hagen",
    "sg:phone":"+49 2331/45463",
    "sg:postcode":"58135",
    "sg:province":"Nordrhein-Westfalen",
    "wof:name":"Martin Koch Gmbh",
    "wof:placetype":"venue"
},
  "geometry": {"coordinates":[7.4276847839,51.3355827332],"type":"Point"}
}