{
  "type": "Feature",
  "properties": {
    "iso:country":"DE",
    "sg:address":"Agrippastr. 15",
    "sg:city":"Andernach",
    "sg:phone":"+49 2632/441601",
    "sg:postcode":"56626",
    "sg:province":"Rheinland-Pfalz",
    "wof:name":"Sozialberatungsstelle Der Caritas",
    "wof:placetype":"venue"
},
  "geometry": {"coordinates":[7.395374,50.439983],"type":"Point"}
}