{
  "type": "Feature",
  "properties": {
    "iso:country":"DE",
    "sg:address":"Walbecker Str. 1",
    "sg:city":"Hettstedt",
    "sg:phone":"+49 3476/852230",
    "sg:postcode":"06333",
    "sg:province":"Sachsen-Anhalt",
    "wof:name":"Peter Frohberg Heizung & Sanit\u00e4r Gmbh",
    "wof:placetype":"venue"
},
  "geometry": {"coordinates":[11.5134811401,51.6481208801],"type":"Point"}
}