{
  "type": "Feature",
  "properties": {
    "iso:country":"DE",
    "sg:address":"Hauptstr. 58",
    "sg:city":"Monheim",
    "sg:phone":"+49 2173/62807",
    "sg:postcode":"40789",
    "sg:province":"Nordrhein-Westfalen",
    "wof:name":"P. Schlupp",
    "wof:placetype":"venue"
},
  "geometry": {"coordinates":[6.8854980469,51.116771698],"type":"Point"}
}