{
  "type": "Feature",
  "properties": {
    "iso:country":"DE",
    "sg:address":"M\u00fchlenweg 12",
    "sg:city":"Bad Honnef",
    "sg:postcode":"53604",
    "sg:province":"Nordrhein-Westfalen",
    "wof:name":"Bsi Servicegesellschaft Des Bundesverbandes Der Deutschen",
    "wof:placetype":"venue"
},
  "geometry": {"coordinates":[7.2136697769,50.655796051],"type":"Point"}
}