{
  "type": "Feature",
  "properties": {
    "iso:country":"DE",
    "sg:address":"Martin-Luther-Str. 33",
    "sg:city":"Hamm",
    "sg:phone":"+49 2381/23434",
    "sg:postcode":"59065",
    "sg:province":"Nordrhein-Westfalen",
    "wof:name":"Kristall-palast 13",
    "wof:placetype":"venue"
},
  "geometry": {"coordinates":[7.815186,51.679966],"type":"Point"}
}