{
  "type": "Feature",
  "properties": {
    "iso:country":"DE",
    "sg:address":"Clarenbachstr. 1",
    "sg:city":"H\u00fcckeswagen",
    "sg:phone":"+49 2192/916080",
    "sg:postcode":"42499",
    "sg:province":"Nordrhein-Westfalen",
    "wof:name":"Clouth & Kochenrath Beteiligungs Gmbh",
    "wof:placetype":"venue"
},
  "geometry": {"coordinates":[7.291555,51.139446],"type":"Point"}
}