{
  "type": "Feature",
  "properties": {
    "iso:country":"DE",
    "sg:address":"Kampmannbr\u00fccke 37",
    "sg:city":"Essen",
    "sg:postcode":"45257",
    "sg:province":"Nordrhein-Westfalen",
    "wof:name":"Yachtschule Nautico Wolf-d. Reichelt",
    "wof:placetype":"venue"
},
  "geometry": {"coordinates":[7.07971,51.397598],"type":"Point"}
}