{
  "type": "Feature",
  "properties": {
    "iso:country":"DE",
    "sg:address":"Beim Kleinen Tagwerk 27",
    "sg:city":"Bremen",
    "sg:phone":"+49 421/254540",
    "sg:postcode":"28355",
    "sg:province":"Bremen",
    "wof:name":"Wilfried Verwoldt Gmbh",
    "wof:placetype":"venue"
},
  "geometry": {"coordinates":[8.9059715271,53.0956993103],"type":"Point"}
}