{
  "type": "Feature",
  "properties": {
    "iso:country":"DE",
    "sg:address":"Heinrich-Heine-Str. 23",
    "sg:city":"Dessau",
    "sg:phone":"+49 340/215502",
    "sg:postcode":"06844",
    "sg:province":"Sachsen-Anhalt",
    "wof:name":"Dsd Dentalstudio Dessau Gmbh",
    "wof:placetype":"venue"
},
  "geometry": {"coordinates":[12.2502441406,51.8420791626],"type":"Point"}
}