{
  "type": "Feature",
  "properties": {
    "iso:country":"DE",
    "sg:address":"Bahnhofstr. 13 a",
    "sg:city":"H\u00f6hn",
    "sg:phone":"+49 2661/8718",
    "sg:postcode":"56462",
    "sg:province":"Rheinland-Pfalz",
    "wof:name":"Fliesen-jacob Gmbh",
    "wof:placetype":"venue"
},
  "geometry": {"coordinates":[7.9812421799,50.619808197],"type":"Point"}
}