{
  "type": "Feature",
  "properties": {
    "iso:country":"DE",
    "sg:address":"Kreuzstr. 33",
    "sg:city":"Olfen",
    "sg:phone":"+49 2595/1229",
    "sg:postcode":"59399",
    "sg:province":"Nordrhein-Westfalen",
    "wof:name":"Norbert Trogemann",
    "wof:placetype":"venue"
},
  "geometry": {"coordinates":[7.378725,51.712788],"type":"Point"}
}