{
  "type": "Feature",
  "properties": {
    "iso:country":"DE",
    "sg:address":"Luitpoldstra\u00dfe 4-b",
    "sg:city":"Aschaffenburg",
    "sg:phone":"+49 6021",
    "sg:postcode":"63739",
    "sg:province":"Bayern",
    "wof:name":"H\u00f6rger\u00e4te Krainz",
    "wof:placetype":"venue"
},
  "geometry": {"coordinates":[9.144965,49.976387],"type":"Point"}
}