{
  "type": "Feature",
  "properties": {
    "iso:country":"DE",
    "sg:address":"Kupferhammer",
    "sg:city":"Bielefeld",
    "sg:postcode":"33649",
    "sg:province":"Nordrhein-Westfalen",
    "wof:name":"Elastoplast Kunststoff- Technik Gmbh",
    "wof:placetype":"venue"
},
  "geometry": {"coordinates":[8.489285,51.98978],"type":"Point"}
}