{
  "type": "Feature",
  "properties": {
    "iso:country":"DE",
    "sg:address":"Hahnenbachstr. 62",
    "sg:city":"Hahnenbach",
    "sg:phone":"+49 6752/8534",
    "sg:postcode":"55606",
    "sg:province":"Rheinland-Pfalz",
    "wof:name":"Ludwig Bertram",
    "wof:placetype":"venue"
},
  "geometry": {"coordinates":[7.414268,49.810844],"type":"Point"}
}