{
  "type": "Feature",
  "properties": {
    "iso:country":"DE",
    "sg:address":"Lilienthalstr. 8",
    "sg:city":"Schweinfurt",
    "sg:phone":"+49 9721/60638",
    "sg:postcode":"97424",
    "sg:province":"Bayern",
    "wof:name":"N\u00f6th Verwaltungs-gmbh",
    "wof:placetype":"venue"
},
  "geometry": {"coordinates":[10.2400598526,50.0326194763],"type":"Point"}
}