{
  "type": "Feature",
  "properties": {
    "iso:country":"DE",
    "sg:address":"Bahnhofstr. 25",
    "sg:city":"Bogen",
    "sg:phone":"+49 9422/1661",
    "sg:postcode":"94327",
    "sg:province":"Bayern",
    "wof:name":"Holz Pongratz",
    "wof:placetype":"venue"
},
  "geometry": {"coordinates":[12.6876316071,48.9098777771],"type":"Point"}
}