{
  "type": "Feature",
  "properties": {
    "iso:country":"DE",
    "sg:address":"H\u00fclshof 7",
    "sg:city":"L\u00fcnen",
    "sg:phone":"+49 2306/259333",
    "sg:postcode":"44536",
    "sg:province":"Nordrhein-Westfalen",
    "wof:name":"Ricono & Sch\u00e4fers Gbr",
    "wof:placetype":"venue"
},
  "geometry": {"coordinates":[7.502477,51.61145],"type":"Point"}
}