{
  "type": "Feature",
  "properties": {
    "iso:country":"DE",
    "sg:address":"H\u00f6henweg 7",
    "sg:city":"Rimsting",
    "sg:phone":"+49 8051/2063",
    "sg:postcode":"83253",
    "sg:province":"Bayern",
    "wof:name":"Helmut Grie\u00dfl",
    "wof:placetype":"venue"
},
  "geometry": {"coordinates":[12.3354635239,47.8796844482],"type":"Point"}
}