{
  "type": "Feature",
  "properties": {
    "iso:country":"DE",
    "sg:address":"Gausepatt 64",
    "sg:city":"D\u00fclmen",
    "sg:phone":"+49 4925/9499666",
    "sg:postcode":"48249",
    "sg:province":"Nordrhein-Westfalen",
    "wof:name":"Irm Anlagenbau U. Schweisstechnik Gmbh",
    "wof:placetype":"venue"
},
  "geometry": {"coordinates":[7.264012,51.815563],"type":"Point"}
}