{
  "type": "Feature",
  "properties": {
    "iso:country":"DE",
    "sg:address":"Pfortgartenstr. 7",
    "sg:city":"Ranstadt",
    "sg:phone":"+49 6041/6644",
    "sg:postcode":"63691",
    "sg:province":"Hessen",
    "wof:name":"Erwin Herche",
    "wof:placetype":"venue"
},
  "geometry": {"coordinates":[8.9844379425,50.3561515808],"type":"Point"}
}