{
  "type": "Feature",
  "properties": {
    "iso:country":"DE",
    "sg:address":"Innere Br\u00fccke 9",
    "sg:city":"Esslingen",
    "sg:phone":"+49 711/355448",
    "sg:postcode":"73728",
    "sg:province":"Baden-W\u00fcrttemberg",
    "wof:name":"Werner Dohrn Rechtsanwalt",
    "wof:placetype":"venue"
},
  "geometry": {"coordinates":[9.3056240082,48.7399940491],"type":"Point"}
}