{
  "type": "Feature",
  "properties": {
    "iso:country":"DE",
    "sg:address":"Gospoldshofer Str. 5",
    "sg:city":"Bad Wurzach",
    "sg:phone":"+49 7564/3100",
    "sg:postcode":"88410",
    "sg:province":"Baden-W\u00fcrttemberg",
    "wof:name":"Kegelstube Riss",
    "wof:placetype":"venue"
},
  "geometry": {"coordinates":[9.9699726105,47.8910598755],"type":"Point"}
}