{
  "type": "Feature",
  "properties": {
    "iso:country":"DE",
    "sg:address":"Hesb\u00fcller Str.",
    "sg:city":"Neukirchen",
    "sg:phone":"+49 4664/1350",
    "sg:postcode":"25927",
    "sg:province":"Schleswig-Holstein",
    "wof:name":"Ursula Arp",
    "wof:placetype":"venue"
},
  "geometry": {"coordinates":[8.72928,54.863838],"type":"Point"}
}