{
  "type": "Feature",
  "properties": {
    "iso:country":"DE",
    "sg:address":"Wendelsteinstr. 11",
    "sg:city":"M\u00fcnchen",
    "sg:phone":"+49 89/694236",
    "sg:postcode":"81541",
    "sg:province":"Bayern",
    "wof:name":"Dimitri",
    "wof:placetype":"venue"
},
  "geometry": {"coordinates":[11.5820827484,48.1163482666],"type":"Point"}
}