{
  "type": "Feature",
  "properties": {
    "iso:country":"DE",
    "sg:address":"R\u00fcbgrund 24",
    "sg:city":"Griesheim",
    "sg:phone":"+49 4961/5583880",
    "sg:postcode":"64347",
    "sg:province":"Hessen",
    "wof:name":"Nbv + Uga Gmbh",
    "wof:placetype":"venue"
},
  "geometry": {"coordinates":[8.549924,49.866592],"type":"Point"}
}