{
  "type": "Feature",
  "properties": {
    "iso:country":"DE",
    "sg:address":"Heimstr. 2",
    "sg:city":"Baden-Baden",
    "sg:phone":"+49 7221/7030",
    "sg:postcode":"76534",
    "sg:province":"Baden-W\u00fcrttemberg",
    "wof:name":"Schwarzwaldwohnstift Lichtental",
    "wof:placetype":"venue"
},
  "geometry": {"coordinates":[8.25306,48.750004],"type":"Point"}
}