{
  "type": "Feature",
  "properties": {
    "iso:country":"DE",
    "sg:address":"Lange Redder 2",
    "sg:city":"Treia",
    "sg:phone":"+49 4626/370",
    "sg:postcode":"24896",
    "sg:province":"Schleswig-Holstein",
    "wof:name":"H. S\u00f6rensen",
    "wof:placetype":"venue"
},
  "geometry": {"coordinates":[9.3061103821,54.5045509338],"type":"Point"}
}