{
  "type": "Feature",
  "properties": {
    "iso:country":"DE",
    "sg:address":"Haldenweg 1",
    "sg:city":"Bockenheim",
    "sg:phone":"+49 6359/947094",
    "sg:postcode":"67278",
    "sg:province":"Rheinland-Pfalz",
    "wof:name":"Eugen Best Gmbh",
    "wof:placetype":"venue"
},
  "geometry": {"coordinates":[8.180015564,49.6082305908],"type":"Point"}
}