{
  "type": "Feature",
  "properties": {
    "iso:country":"DE",
    "sg:address":"Giselastr. 39",
    "sg:city":"Wuppertal",
    "sg:phone":"+49 202/77815",
    "sg:postcode":"42111",
    "sg:province":"Nordrhein-Westfalen",
    "wof:name":"Harri Sch\u00f6ning Innenarchitekt",
    "wof:placetype":"venue"
},
  "geometry": {"coordinates":[7.165235,51.296753],"type":"Point"}
}