{
  "type": "Feature",
  "properties": {
    "iso:country":"DE",
    "sg:address":"Tiefer Graben 12",
    "sg:city":"Mainleus",
    "sg:phone":"+49 9229/97290",
    "sg:postcode":"95336",
    "sg:province":"Bayern",
    "wof:name":"Gastra Verpackungen Gmbh",
    "wof:placetype":"venue"
},
  "geometry": {"coordinates":[11.3554134369,50.1176986694],"type":"Point"}
}