{
  "type": "Feature",
  "properties": {
    "iso:country":"DE",
    "sg:address":"Saarstr. 32",
    "sg:city":"Leverkusen",
    "sg:phone":"+49 214/53789",
    "sg:postcode":"51375",
    "sg:province":"Nordrhein-Westfalen",
    "wof:name":"Hans K\u00f6hler",
    "wof:placetype":"venue"
},
  "geometry": {"coordinates":[7.0505847931,51.0220375061],"type":"Point"}
}