{
  "type": "Feature",
  "properties": {
    "iso:country":"DE",
    "sg:address":"In der Hau 20",
    "sg:city":"Hohentengen",
    "sg:phone":"+49 7572/3592",
    "sg:postcode":"88367",
    "sg:province":"Baden-W\u00fcrttemberg",
    "wof:name":"Seybold & Co. Maschinenbau Gmbh",
    "wof:placetype":"venue"
},
  "geometry": {"coordinates":[9.371414,48.026146],"type":"Point"}
}