{
  "type": "Feature",
  "properties": {
    "iso:country":"DE",
    "sg:address":"Schaffhauser Str. 12",
    "sg:city":"M\u00fcnchen",
    "sg:phone":"+49 89/751379",
    "sg:postcode":"81476",
    "sg:province":"Bayern",
    "wof:name":"Karl Alfred B\u00e4umler Rechtsanwalt",
    "wof:placetype":"venue"
},
  "geometry": {"coordinates":[11.497127533,48.0978469849],"type":"Point"}
}