{
  "type": "Feature",
  "properties": {
    "iso:country":"DE",
    "sg:address":"Hauptstr. 27",
    "sg:city":"Neuendettelsau",
    "sg:phone":"+49 9874/5350",
    "sg:postcode":"91564",
    "sg:province":"Bayern",
    "wof:name":"Stern",
    "wof:placetype":"venue"
},
  "geometry": {"coordinates":[10.788312912,49.2861404419],"type":"Point"}
}