{
  "type": "Feature",
  "properties": {
    "iso:country":"DE",
    "sg:address":"R\u00f6merstr. 12",
    "sg:city":"Zwickau",
    "sg:phone":"+49 375/2713908",
    "sg:postcode":"08056",
    "sg:province":"Sachsen",
    "wof:name":"Profi-pflasterbau Gmbh",
    "wof:placetype":"venue"
},
  "geometry": {"coordinates":[12.49376297,50.7219848633],"type":"Point"}
}