{
  "type": "Feature",
  "properties": {
    "iso:country":"DE",
    "sg:address":"Engerstra\u00dfe 22",
    "sg:city":"Kempen",
    "sg:phone":"+49 2152/51470",
    "sg:postcode":"47906",
    "sg:province":"Nordrhein-Westfalen",
    "wof:name":"Schmuckgalerie",
    "wof:placetype":"venue"
},
  "geometry": {"coordinates":[6.4227080345,51.3647193909],"type":"Point"}
}