{
  "type": "Feature",
  "properties": {
    "iso:country":"DE",
    "sg:address":"M\u00fchlengasse 4",
    "sg:city":"S\u00f6hlde",
    "sg:postcode":"31185",
    "sg:province":"Niedersachsen",
    "wof:name":"Avatek Inh. Hans-j. Diederich E. K.",
    "wof:placetype":"venue"
},
  "geometry": {"coordinates":[10.158323,52.159489],"type":"Point"}
}