{
  "type": "Feature",
  "properties": {
    "iso:country":"DE",
    "sg:address":"Jakobstr. 11",
    "sg:city":"G\u00f6rlitz",
    "sg:phone":"+49 3581/402227",
    "sg:postcode":"02826",
    "sg:province":"Sachsen",
    "wof:name":"Ingenieurb\u00fcro Ziegert",
    "wof:placetype":"venue"
},
  "geometry": {"coordinates":[14.9834594727,51.1482963562],"type":"Point"}
}