{
  "type": "Feature",
  "properties": {
    "iso:country":"DE",
    "sg:address":"Kurt-SchumacherStr.",
    "sg:city":"Kaiserslautern",
    "sg:phone":"+49 179",
    "sg:postcode":"67663",
    "sg:province":"Rheinland-Pfalz",
    "wof:name":"Brake Webdesign - Ihr Auftritt Im Internet",
    "wof:placetype":"venue"
},
  "geometry": {"coordinates":[7.7442250252,49.4250526428],"type":"Point"}
}