{
  "type": "Feature",
  "properties": {
    "iso:country":"DE",
    "sg:address":"Heidelweg 26",
    "sg:city":"Henstedt-Ulzburg",
    "sg:phone":"+49 4193/78851",
    "sg:postcode":"24558",
    "sg:province":"Schleswig-Holstein",
    "wof:name":"Horst Heidenreich Architekt",
    "wof:placetype":"venue"
},
  "geometry": {"coordinates":[10.011153,53.745731],"type":"Point"}
}