{
  "type": "Feature",
  "properties": {
    "iso:country":"DE",
    "sg:address":"Hauptstr. 78 a",
    "sg:city":"Lichtentanne",
    "sg:phone":"+49 375/241229",
    "sg:postcode":"08115",
    "sg:province":"Sachsen",
    "wof:name":"Bernd Schulze",
    "wof:placetype":"venue"
},
  "geometry": {"coordinates":[12.428451,50.691517],"type":"Point"}
}