{
  "type": "Feature",
  "properties": {
    "iso:country":"DE",
    "sg:address":"Am Sonnenbichl 1",
    "sg:city":"Bad Wiessee",
    "sg:postcode":"83707",
    "sg:province":"Bayern",
    "wof:name":"Am Sonnenbichl Hotel - Restaurant In Bad Wiessee !",
    "wof:placetype":"venue"
},
  "geometry": {"coordinates":[11.7151489258,47.7045783997],"type":"Point"}
}