{
  "type": "Feature",
  "properties": {
    "iso:country":"DE",
    "sg:address":"Obere Str. 5",
    "sg:city":"Coppenbr\u00fcgge",
    "sg:phone":"+49 5159/805",
    "sg:postcode":"31863",
    "sg:province":"Niedersachsen",
    "wof:name":"Friedhelm Thomas",
    "wof:placetype":"venue"
},
  "geometry": {"coordinates":[9.549714,52.117485],"type":"Point"}
}