{
  "type": "Feature",
  "properties": {
    "iso:country":"DE",
    "sg:address":"Wickeder Hellweg 70",
    "sg:city":"Dortmund",
    "sg:phone":"+49 231/210819",
    "sg:postcode":"44319",
    "sg:province":"Nordrhein-Westfalen",
    "wof:name":"Rolf Granseyer",
    "wof:placetype":"venue"
},
  "geometry": {"coordinates":[7.6079258919,51.5320243835],"type":"Point"}
}