{
  "type": "Feature",
  "properties": {
    "iso:country":"DE",
    "sg:address":"Sch\u00f6nleitenstr. 2",
    "sg:city":"Brannenburg",
    "sg:phone":"+49 8034/90650",
    "sg:postcode":"83098",
    "sg:province":"Bayern",
    "wof:name":"Peter Drexler Steuerberater",
    "wof:placetype":"venue"
},
  "geometry": {"coordinates":[12.0958137512,47.7358551025],"type":"Point"}
}