{
  "type": "Feature",
  "properties": {
    "iso:country":"DE",
    "sg:address":"Schlo\u00dfplatz 1",
    "sg:city":"Amorbach",
    "sg:phone":"+49 9373/1287",
    "sg:postcode":"63916",
    "sg:province":"Bayern",
    "wof:name":"Ev. Luth. Pfarramt",
    "wof:placetype":"venue"
},
  "geometry": {"coordinates":[9.21945858,49.6430168152],"type":"Point"}
}