{
  "type": "Feature",
  "properties": {
    "iso:country":"DE",
    "sg:address":"Tempelberger Weg 2",
    "sg:city":"M\u00fcncheberg",
    "sg:phone":"+49 33432/241",
    "sg:postcode":"15374",
    "sg:province":"Brandenburg",
    "wof:name":"Horst Hintze",
    "wof:placetype":"venue"
},
  "geometry": {"coordinates":[14.149467,52.499245],"type":"Point"}
}