{
  "type": "Feature",
  "properties": {
    "iso:country":"DE",
    "sg:address":"Zweibr\u00fccker Str. 23",
    "sg:city":"Neunkirchen",
    "sg:phone":"+49 6821/983284",
    "sg:postcode":"66538",
    "sg:province":"Saarland",
    "wof:name":"Kr\u00e4mers Wirtschaft",
    "wof:placetype":"venue"
},
  "geometry": {"coordinates":[7.1843061447,49.3363952637],"type":"Point"}
}