{
  "type": "Feature",
  "properties": {
    "iso:country":"DE",
    "sg:address":"Am Gather Hof 14",
    "sg:city":"Grevenbroich",
    "sg:phone":"+49 2181/73457",
    "sg:postcode":"41516",
    "sg:province":"Nordrhein-Westfalen",
    "wof:name":"Manfred Becker",
    "wof:placetype":"venue"
},
  "geometry": {"coordinates":[6.625613,51.120838],"type":"Point"}
}