{
  "type": "Feature",
  "properties": {
    "iso:country":"DE",
    "sg:address":"Siemensstr. 7-10",
    "sg:city":"Papenburg",
    "sg:postcode":"26871",
    "sg:province":"Niedersachsen",
    "wof:name":"Ltc Klimablock Papenburg Gmbh",
    "wof:placetype":"venue"
},
  "geometry": {"coordinates":[7.4037089348,53.0925178528],"type":"Point"}
}