{
  "type": "Feature",
  "properties": {
    "iso:country":"DE",
    "sg:address":"Raiherwiesenstr. 32a",
    "sg:city":"Karlsruhe",
    "sg:phone":"+49 721/401871",
    "sg:postcode":"76227",
    "sg:province":"Baden-W\u00fcrttemberg",
    "wof:name":"Laubengastst\u00e4tte",
    "wof:placetype":"venue"
},
  "geometry": {"coordinates":[8.4584264755,48.9975395203],"type":"Point"}
}