{
  "type": "Feature",
  "properties": {
    "iso:country":"DE",
    "sg:address":"Paulinenstr. 17",
    "sg:city":"Albstadt",
    "sg:phone":"+49 7432/98220",
    "sg:postcode":"72459",
    "sg:province":"Baden-W\u00fcrttemberg",
    "wof:name":"Eberhard Didra Architekt",
    "wof:placetype":"venue"
},
  "geometry": {"coordinates":[8.966839,48.256279],"type":"Point"}
}