{
  "type": "Feature",
  "properties": {
    "iso:country":"DE",
    "sg:address":"Dessauer Str. 79",
    "sg:city":"Bitterfeld",
    "sg:phone":"+49 3493/27140",
    "sg:postcode":"06749",
    "sg:province":"Sachsen-Anhalt",
    "wof:name":"Jacob Angelger\u00e4te",
    "wof:placetype":"venue"
},
  "geometry": {"coordinates":[12.32528,51.628254],"type":"Point"}
}