{
  "type": "Feature",
  "properties": {
    "iso:country":"DE",
    "sg:address":"Sophienstr. 53",
    "sg:city":"M\u00fcnster",
    "sg:postcode":"48145",
    "sg:province":"Nordrhein-Westfalen",
    "wof:name":"Institut F\u00fcr Emotionale Bildung",
    "wof:placetype":"venue"
},
  "geometry": {"coordinates":[7.647757,51.956921],"type":"Point"}
}