{
  "type": "Feature",
  "properties": {
    "iso:country":"DE",
    "sg:address":"Hauptstr. 10",
    "sg:city":"Neckarsulm",
    "sg:phone":"+49 7132/42615",
    "sg:postcode":"74172",
    "sg:province":"Baden-W\u00fcrttemberg",
    "wof:name":"Reinhard Ranger",
    "wof:placetype":"venue"
},
  "geometry": {"coordinates":[9.200957,49.196655],"type":"Point"}
}