{
  "type": "Feature",
  "properties": {
    "iso:country":"DE",
    "sg:address":"Marienthaler Str. 19",
    "sg:city":"Zwickau",
    "sg:postcode":"08060",
    "sg:province":"Sachsen",
    "wof:name":"Systempartner Computervertriebs Gmbh",
    "wof:placetype":"venue"
},
  "geometry": {"coordinates":[12.4715070724,50.7202682495],"type":"Point"}
}