{
  "type": "Feature",
  "properties": {
    "iso:country":"DE",
    "sg:address":"Industriestr. 10",
    "sg:city":"Ilsede",
    "sg:phone":"+49 5172/944633",
    "sg:postcode":"31241",
    "sg:province":"Niedersachsen",
    "wof:name":"Holzbau Selle Gmbh",
    "wof:placetype":"venue"
},
  "geometry": {"coordinates":[10.217667,52.275276],"type":"Point"}
}