{
  "type": "Feature",
  "properties": {
    "iso:country":"DE",
    "sg:address":"Schlo\u00dfstr. 63",
    "sg:city":"Dargun",
    "sg:phone":"+49 39959/20298",
    "sg:postcode":"17159",
    "sg:province":"Mecklenburg-Vorpommern",
    "wof:name":"Anke H\u00f6fs Masseurin",
    "wof:placetype":"venue"
},
  "geometry": {"coordinates":[12.855923,53.895813],"type":"Point"}
}