{
  "type": "Feature",
  "properties": {
    "iso:country":"DE",
    "sg:address":"von-Drais-Strasse 9",
    "sg:city":"Ketsch",
    "sg:phone":"+49 6202/692789",
    "sg:postcode":"68775",
    "sg:province":"Baden-W\u00fcrttemberg",
    "wof:name":"Coment Computerloesungen Gmbh",
    "wof:placetype":"venue"
},
  "geometry": {"coordinates":[8.53910923,49.3638114929],"type":"Point"}
}