{
  "type": "Feature",
  "properties": {
    "iso:country":"DE",
    "sg:address":"Ruthstr. 13",
    "sg:city":"Berlin",
    "sg:phone":"+49 30/7726645",
    "sg:postcode":"12247",
    "sg:province":"Berlin",
    "wof:name":"Claus Hennig",
    "wof:placetype":"venue"
},
  "geometry": {"coordinates":[13.3406295776,52.4339447021],"type":"Point"}
}