{
  "type": "Feature",
  "properties": {
    "iso:country":"DE",
    "sg:address":"Bergstr. 2",
    "sg:city":"Marsberg",
    "sg:postcode":"34431",
    "sg:province":"Nordrhein-Westfalen",
    "wof:name":"X-maxx Gmbh",
    "wof:placetype":"venue"
},
  "geometry": {"coordinates":[8.862489,51.457195],"type":"Point"}
}