{
  "type": "Feature",
  "properties": {
    "iso:country":"DE",
    "sg:address":"Amsterdamer Str. 29",
    "sg:city":"Heilbronn",
    "sg:phone":"+49 7131/254928",
    "sg:postcode":"74081",
    "sg:province":"Baden-W\u00fcrttemberg",
    "wof:name":"Paul Neumeister",
    "wof:placetype":"venue"
},
  "geometry": {"coordinates":[9.176678,49.118336],"type":"Point"}
}