{
  "type": "Feature",
  "properties": {
    "iso:country":"DE",
    "sg:address":"Nordlandstr. 70",
    "sg:city":"Gro\u00dfenbrode",
    "sg:phone":"+49 4367/8275",
    "sg:postcode":"23775",
    "sg:province":"Schleswig-Holstein",
    "wof:name":"Werner Hansen",
    "wof:placetype":"venue"
},
  "geometry": {"coordinates":[11.084169,54.370216],"type":"Point"}
}