{
  "type": "Feature",
  "properties": {
    "iso:country":"DE",
    "sg:address":"Wiedenkamper Str. 1",
    "sg:city":"Solingen",
    "sg:phone":"+49 212/310407",
    "sg:postcode":"42719",
    "sg:province":"Nordrhein-Westfalen",
    "wof:name":"Michael Zelmanski",
    "wof:placetype":"venue"
},
  "geometry": {"coordinates":[7.0418071747,51.1821365356],"type":"Point"}
}