{
  "type": "Feature",
  "properties": {
    "iso:country":"DE",
    "sg:address":"Grasweg 8",
    "sg:city":"Hamburg",
    "sg:phone":"+49 40/479199",
    "sg:postcode":"22299",
    "sg:province":"Hamburg",
    "wof:name":"V-studio Einrichtungen Gmbh",
    "wof:placetype":"venue"
},
  "geometry": {"coordinates":[10.0003004074,53.5937194824],"type":"Point"}
}