{
  "type": "Feature",
  "properties": {
    "iso:country":"DE",
    "sg:address":"Markt 38",
    "sg:city":"Waldershof",
    "sg:phone":"+49 9231/7374",
    "sg:postcode":"95679",
    "sg:province":"Bayern",
    "wof:name":"Eiber",
    "wof:placetype":"venue"
},
  "geometry": {"coordinates":[12.0632619858,49.9777030945],"type":"Point"}
}