{
  "type": "Feature",
  "properties": {
    "iso:country":"DE",
    "sg:address":"Liebknechtstr. 38",
    "sg:city":"Erfurt",
    "sg:phone":"+49 361/6439020",
    "sg:postcode":"99086",
    "sg:province":"Th\u00fcringen",
    "wof:name":"Palme",
    "wof:placetype":"venue"
},
  "geometry": {"coordinates":[11.03171,50.986485],"type":"Point"}
}