{
  "type": "Feature",
  "properties": {
    "iso:country":"DE",
    "sg:address":"Am Dechantsberg 9",
    "sg:city":"Karlsruhe",
    "sg:phone":"+49 721/813098",
    "sg:postcode":"76227",
    "sg:province":"Baden-W\u00fcrttemberg",
    "wof:name":"Wieland Agentur F\u00fcr Einrichtungen Gmbh",
    "wof:placetype":"venue"
},
  "geometry": {"coordinates":[8.4768838882,48.9870109558],"type":"Point"}
}