{
  "type": "Feature",
  "properties": {
    "iso:country":"DE",
    "sg:address":"Lortzingstr. 14",
    "sg:city":"M\u00fcnchen",
    "sg:phone":"+49 89/8346252",
    "sg:postcode":"81241",
    "sg:province":"Bayern",
    "wof:name":"Treppen-siebrecht",
    "wof:placetype":"venue"
},
  "geometry": {"coordinates":[11.4546661377,48.148563385],"type":"Point"}
}