{
  "type": "Feature",
  "properties": {
    "iso:country":"DE",
    "sg:address":"Niederkasseler Str. 108",
    "sg:city":"D\u00fcsseldorf",
    "sg:phone":"+49 211/574395",
    "sg:postcode":"40547",
    "sg:province":"Nordrhein-Westfalen",
    "wof:name":"P. Tappe Jun.",
    "wof:placetype":"venue"
},
  "geometry": {"coordinates":[6.7506527901,51.2407531738],"type":"Point"}
}