{
  "type": "Feature",
  "properties": {
    "iso:country":"DE",
    "sg:address":"Schleizer Str. 26",
    "sg:city":"Mehltheuer",
    "sg:phone":"+49 37431/3926",
    "sg:postcode":"08539",
    "sg:province":"Sachsen",
    "wof:name":"Elke Koj",
    "wof:placetype":"venue"
},
  "geometry": {"coordinates":[12.0339899063,50.5453071594],"type":"Point"}
}