{
  "type": "Feature",
  "properties": {
    "iso:country":"DE",
    "sg:address":"Erbstollen 6a",
    "sg:city":"Bochum",
    "sg:phone":"+49 234/9471340",
    "sg:postcode":"44797",
    "sg:province":"Nordrhein-Westfalen",
    "wof:name":"Prof. Feierabend Gmbh",
    "wof:placetype":"venue"
},
  "geometry": {"coordinates":[7.2142920494,51.4393463135],"type":"Point"}
}