{
  "type": "Feature",
  "properties": {
    "iso:country":"DE",
    "sg:address":"Anton-Flettner-Str. 8",
    "sg:city":"Raunheim",
    "sg:phone":"+49 6142/790",
    "sg:postcode":"65479",
    "sg:province":"Hessen",
    "wof:name":"Best Western Wings Hotel",
    "wof:placetype":"venue"
},
  "geometry": {"coordinates":[8.4424943924,50.0115776062],"type":"Point"}
}