{
  "type": "Feature",
  "properties": {
    "iso:country":"DE",
    "sg:address":"Industriestr. 30",
    "sg:city":"Fl\u00f6rsheim",
    "sg:phone":"+49 6145/93120",
    "sg:postcode":"65439",
    "sg:province":"Hessen",
    "wof:name":"Achilles Papierveredelung Fl\u00f6rsheim Gmbh",
    "wof:placetype":"venue"
},
  "geometry": {"coordinates":[8.441186,50.039143],"type":"Point"}
}