{
  "type": "Feature",
  "properties": {
    "iso:country":"DE",
    "sg:address":"Ischenr\u00f6der Str. 2",
    "sg:city":"Gleichen",
    "sg:phone":"+49 5592/1308",
    "sg:postcode":"37130",
    "sg:province":"Niedersachsen",
    "wof:name":"Hubert M\u00fcller Tischlerei",
    "wof:placetype":"venue"
},
  "geometry": {"coordinates":[10.043031,51.445827],"type":"Point"}
}