{
  "type": "Feature",
  "properties": {
    "iso:country":"DE",
    "sg:address":"Lienerstr. 10",
    "sg:city":"Werlte",
    "sg:phone":"+49 5951/5343",
    "sg:postcode":"49757",
    "sg:province":"Niedersachsen",
    "wof:name":"Josef Lamping",
    "wof:placetype":"venue"
},
  "geometry": {"coordinates":[7.6892590523,52.8510704041],"type":"Point"}
}