{
  "type": "Feature",
  "properties": {
    "iso:country":"DE",
    "sg:address":"Friedensstr. 48",
    "sg:city":"Bitterfeld",
    "sg:phone":"+49 3493/43004",
    "sg:postcode":"06749",
    "sg:province":"Sachsen-Anhalt",
    "wof:name":"Elektrobedarf Henze",
    "wof:placetype":"venue"
},
  "geometry": {"coordinates":[12.3384685516,51.6300239563],"type":"Point"}
}