{
  "type": "Feature",
  "properties": {
    "iso:country":"DE",
    "sg:address":"Industriering 3",
    "sg:city":"D\u00f6schwitz",
    "sg:phone":"+49 34425/31015",
    "sg:postcode":"06712",
    "sg:province":"Sachsen-Anhalt",
    "wof:name":"H\u00f6cker Polytechnik Gmbh",
    "wof:placetype":"venue"
},
  "geometry": {"coordinates":[12.0283517838,51.0751533508],"type":"Point"}
}