{
  "type": "Feature",
  "properties": {
    "iso:country":"DE",
    "sg:address":"Amtsstr. 38",
    "sg:city":"Zarrentin",
    "sg:phone":"+49 38851/25405",
    "sg:postcode":"19246",
    "sg:province":"Mecklenburg-Vorpommern",
    "wof:name":"Heinrich Kr\u00fchn",
    "wof:placetype":"venue"
},
  "geometry": {"coordinates":[10.918563,53.548244],"type":"Point"}
}