{
  "type": "Feature",
  "properties": {
    "iso:country":"DE",
    "sg:address":"Mittermaierstr. 17",
    "sg:city":"Heidelberg",
    "sg:phone":"+49 6221/20199",
    "sg:postcode":"69115",
    "sg:province":"Baden-W\u00fcrttemberg",
    "wof:name":"Wohlfahrt & Stegm\u00fcller",
    "wof:placetype":"venue"
},
  "geometry": {"coordinates":[8.677107,49.40691],"type":"Point"}
}