{
  "type": "Feature",
  "properties": {
    "iso:country":"DE",
    "sg:address":"Alte Piccardie 64",
    "sg:city":"Osterwald",
    "sg:phone":"+49 5946/92082",
    "sg:postcode":"49828",
    "sg:province":"Niedersachsen",
    "wof:name":"Was Homepage",
    "wof:placetype":"venue"
},
  "geometry": {"coordinates":[7.07066,52.558521],"type":"Point"}
}