{
  "type": "Feature",
  "properties": {
    "iso:country":"DE",
    "sg:address":"Hauptstr. 5",
    "sg:city":"Dornstadt",
    "sg:phone":"+49 7336/357",
    "sg:postcode":"89160",
    "sg:province":"Baden-W\u00fcrttemberg",
    "wof:name":"Adler",
    "wof:placetype":"venue"
},
  "geometry": {"coordinates":[9.8510341644,48.5115966797],"type":"Point"}
}