{
  "type": "Feature",
  "properties": {
    "iso:country":"DE",
    "sg:address":"Lange Str. 81",
    "sg:city":"F\u00fcrth",
    "sg:phone":"+49 911/785111",
    "sg:postcode":"90762",
    "sg:province":"Bayern",
    "wof:name":"J\u00fcrgen Erdmann",
    "wof:placetype":"venue"
},
  "geometry": {"coordinates":[11.0077009201,49.4681777954],"type":"Point"}
}