{
  "type": "Feature",
  "properties": {
    "iso:country":"DE",
    "sg:address":"Gersdorfer Str. 10a",
    "sg:city":"Kurort Berggie\u00dfh\u00fcbel",
    "sg:postcode":"01819",
    "sg:province":"Sachsen",
    "wof:name":"Gemeindeschwesterstation Ko\u00dferggie\u00dfh\u00fcb",
    "wof:placetype":"venue"
},
  "geometry": {"coordinates":[-82.825073,29.834511],"type":"Point"}
}