{
  "type": "Feature",
  "properties": {
    "iso:country":"DE",
    "sg:address":"Am Sch\u00fctzenhof 25",
    "sg:city":"Kassel",
    "sg:postcode":"34134",
    "sg:province":"Hessen",
    "wof:name":"Red. Vereinsnachrichten Freie Turnerschaft",
    "wof:placetype":"venue"
},
  "geometry": {"coordinates":[9.465637207,51.279510498],"type":"Point"}
}