{
  "type": "Feature",
  "properties": {
    "iso:country":"DE",
    "sg:address":"Oberer Marktplatz 16",
    "sg:city":"Mitterteich",
    "sg:phone":"+49 9633/1238",
    "sg:postcode":"95666",
    "sg:province":"Bayern",
    "wof:name":"Stadt-b\u00e4ckerei Konditorei Inh. Markus Fick",
    "wof:placetype":"venue"
},
  "geometry": {"coordinates":[12.244936,49.951992],"type":"Point"}
}