{
  "type": "Feature",
  "properties": {
    "iso:country":"DE",
    "sg:address":"Holtroper Str. 28",
    "sg:city":"Ihlow",
    "sg:phone":"+49 4943/2471",
    "sg:postcode":"26632",
    "sg:province":"Niedersachsen",
    "wof:name":"M\u00f6belhaus Fr\u00fchling Gmbh",
    "wof:placetype":"venue"
},
  "geometry": {"coordinates":[7.534481,53.423183],"type":"Point"}
}