{
  "type": "Feature",
  "properties": {
    "iso:country":"DE",
    "sg:address":"Ludwig-Jahn-Str. 5",
    "sg:city":"Thalheim",
    "sg:phone":"+49 3721/84631",
    "sg:postcode":"09380",
    "sg:province":"Sachsen",
    "wof:name":"M\u00fcller",
    "wof:placetype":"venue"
},
  "geometry": {"coordinates":[12.846252,50.702415],"type":"Point"}
}