{
  "type": "Feature",
  "properties": {
    "iso:country":"DE",
    "sg:address":"M\u00fchlenstr. 14",
    "sg:city":"Ottersberg",
    "sg:phone":"+49 4205/8455",
    "sg:postcode":"28870",
    "sg:province":"Niedersachsen",
    "wof:name":"Hans-heinrich Maack",
    "wof:placetype":"venue"
},
  "geometry": {"coordinates":[9.150458,53.106297],"type":"Point"}
}