{
  "type": "Feature",
  "properties": {
    "iso:country":"DE",
    "sg:address":"Stadtplatz 9b",
    "sg:city":"Tittmoning",
    "sg:phone":"+49 8683/1834",
    "sg:postcode":"84529",
    "sg:province":"Bayern",
    "wof:name":"Inh. Martin Gl\u00fcck Eisenwaren",
    "wof:placetype":"venue"
},
  "geometry": {"coordinates":[12.7682323456,48.0619239807],"type":"Point"}
}