{
  "type": "Feature",
  "properties": {
    "iso:country":"DE",
    "sg:address":"Berliner Str. 12",
    "sg:city":"Berlin",
    "sg:phone":"+49 30/47598010",
    "sg:postcode":"13127",
    "sg:province":"Berlin",
    "wof:name":"Kasek Auto Teile Gmbh",
    "wof:placetype":"venue"
},
  "geometry": {"coordinates":[13.4331350327,52.598487854],"type":"Point"}
}