{
  "type": "Feature",
  "properties": {
    "iso:country":"DE",
    "sg:address":"Hermann-Hesse-Str. 2a",
    "sg:city":"Erkrath",
    "sg:phone":"+49 2104/138980",
    "sg:postcode":"40699",
    "sg:province":"Nordrhein-Westfalen",
    "wof:name":"Schwarze & Co. Immobilien Kg",
    "wof:placetype":"venue"
},
  "geometry": {"coordinates":[6.9511852264,51.2021636963],"type":"Point"}
}