{
  "type": "Feature",
  "properties": {
    "iso:country":"DE",
    "sg:address":"Im Klosterhof 8",
    "sg:city":"K\u00f6nigsbronn",
    "sg:phone":"+49 7328/6216",
    "sg:postcode":"89551",
    "sg:province":"Baden-W\u00fcrttemberg",
    "wof:name":"Ev. Pfarramt",
    "wof:placetype":"venue"
},
  "geometry": {"coordinates":[10.1156826019,48.7384872437],"type":"Point"}
}