{
  "type": "Feature",
  "properties": {
    "iso:country":"DE",
    "sg:address":"Erlenweg 8",
    "sg:city":"Nahe",
    "sg:phone":"+49 4535/8567",
    "sg:postcode":"23866",
    "sg:province":"Schleswig-Holstein",
    "wof:name":"Erhard Harms Betonwerk Gmbh",
    "wof:placetype":"venue"
},
  "geometry": {"coordinates":[10.143408,53.795414],"type":"Point"}
}