{
  "type": "Feature",
  "properties": {
    "iso:country":"DE",
    "sg:address":"Schmiedeweg 8-10",
    "sg:city":"Oldenburg",
    "sg:phone":"+49 441/20896",
    "sg:postcode":"26135",
    "sg:province":"Niedersachsen",
    "wof:name":"Merkur W\u00e4scherei Gmbh",
    "wof:placetype":"venue"
},
  "geometry": {"coordinates":[8.2625112534,53.1074485779],"type":"Point"}
}