{
  "type": "Feature",
  "properties": {
    "iso:country":"DE",
    "sg:address":"Waldstr. 14",
    "sg:city":"Emskirchen",
    "sg:phone":"+49 9104/860696",
    "sg:postcode":"91448",
    "sg:province":"Bayern",
    "wof:name":"Bf-acryl Bluhm Fr\u00fchwald Ohg",
    "wof:placetype":"venue"
},
  "geometry": {"coordinates":[10.703127,49.554558],"type":"Point"}
}