{
  "type": "Feature",
  "properties": {
    "iso:country":"DE",
    "sg:address":"Hans-Thoma-Str. 5",
    "sg:city":"Remchingen",
    "sg:phone":"+49 6346/1619",
    "sg:postcode":"75196",
    "sg:province":"Baden-W\u00fcrttemberg",
    "wof:name":"Gerhard Berth Architekt",
    "wof:placetype":"venue"
},
  "geometry": {"coordinates":[8.582043,48.945663],"type":"Point"}
}