{
  "type": "Feature",
  "properties": {
    "iso:country":"DE",
    "sg:address":"Residenzstr. 4-6",
    "sg:city":"Waldm\u00fcnchen",
    "sg:postcode":"93449",
    "sg:province":"Bayern",
    "wof:name":"Residenz Wohnpark Cham Gmbh & Co. Kg",
    "wof:placetype":"venue"
},
  "geometry": {"coordinates":[12.704133,49.375336],"type":"Point"}
}