{
  "type": "Feature",
  "properties": {
    "iso:country":"DE",
    "sg:address":"Oberlandstr. 17",
    "sg:city":"Birstein",
    "sg:phone":"+49 6054/498",
    "sg:postcode":"63633",
    "sg:province":"Hessen",
    "wof:name":"Heinrich Kraus",
    "wof:placetype":"venue"
},
  "geometry": {"coordinates":[9.297389,50.386387],"type":"Point"}
}