{
  "type": "Feature",
  "properties": {
    "iso:country":"DE",
    "sg:address":"Ekkehartstr. 14 u. 16",
    "sg:city":"Grasbrunn",
    "sg:postcode":"85630",
    "sg:province":"Bayern",
    "wof:name":"Ihs Immobilien Gmbh",
    "wof:placetype":"venue"
},
  "geometry": {"coordinates":[11.7437229156,48.0789833069],"type":"Point"}
}