{
  "type": "Feature",
  "properties": {
    "iso:country":"DE",
    "sg:address":"Hauptstr. 10",
    "sg:city":"Fa\u00dfberg",
    "sg:phone":"+49 5053/306",
    "sg:postcode":"29328",
    "sg:province":"Niedersachsen",
    "wof:name":"Hans-heinrich Johannes",
    "wof:placetype":"venue"
},
  "geometry": {"coordinates":[10.118009,52.876343],"type":"Point"}
}