{
  "type": "Feature",
  "properties": {
    "iso:country":"DE",
    "sg:address":"Blaugasse 42",
    "sg:city":"K\u00f6ln",
    "sg:phone":"+49 221/5002484",
    "sg:postcode":"50859",
    "sg:province":"Nordrhein-Westfalen",
    "wof:name":"Herbert Enders Schreinerei",
    "wof:placetype":"venue"
},
  "geometry": {"coordinates":[6.829113,50.960785],"type":"Point"}
}