{
  "type": "Feature",
  "properties": {
    "iso:country":"DE",
    "sg:address":"Krefelder Str. 27",
    "sg:city":"Neuss",
    "sg:phone":"+49 2131/222280",
    "sg:postcode":"41460",
    "sg:province":"Nordrhein-Westfalen",
    "wof:name":"Hotel Garni Mara",
    "wof:placetype":"venue"
},
  "geometry": {"coordinates":[6.6849632263,51.2022743225],"type":"Point"}
}