{
  "type": "Feature",
  "properties": {
    "iso:country":"DE",
    "sg:address":"Rautenbreite 4",
    "sg:city":"Magdeburg",
    "sg:postcode":"39116",
    "sg:province":"Sachsen-Anhalt",
    "wof:name":"Magwen Magnetventil-service",
    "wof:placetype":"venue"
},
  "geometry": {"coordinates":[11.5779972076,52.0972442627],"type":"Point"}
}