{
  "type": "Feature",
  "properties": {
    "iso:country":"DE",
    "sg:address":"21614",
    "sg:city":"Buxtehude",
    "sg:phone":"+49 4161/2316",
    "sg:postcode":"21614",
    "sg:province":"Niedersachsen",
    "wof:name":"Bahnhofsgastst\u00e4tte",
    "wof:placetype":"venue"
},
  "geometry": {"coordinates":[9.6906404495,53.4603805542],"type":"Point"}
}