{
  "type": "Feature",
  "properties": {
    "iso:country":"DE",
    "sg:address":"Lohestr. 16",
    "sg:city":"Sulzbach-Rosenberg",
    "sg:phone":"+49 9661/6556",
    "sg:postcode":"92237",
    "sg:province":"Bayern",
    "wof:name":"Erich R\u00f6tzer",
    "wof:placetype":"venue"
},
  "geometry": {"coordinates":[11.7860937119,49.4870414734],"type":"Point"}
}