{
  "type": "Feature",
  "properties": {
    "iso:country":"DE",
    "sg:address":"Auf dem Jakobsberg 10",
    "sg:city":"Elmstein",
    "sg:phone":"+49 6328/989094",
    "sg:postcode":"67471",
    "sg:province":"Rheinland-Pfalz",
    "wof:name":"Rosemarie Kaiser",
    "wof:placetype":"venue"
},
  "geometry": {"coordinates":[7.932349205,49.3471832275],"type":"Point"}
}