{
  "type": "Feature",
  "properties": {
    "iso:country":"DE",
    "sg:address":"Hauptstr. 40",
    "sg:city":"Glattbach",
    "sg:phone":"+49 6021/423411",
    "sg:postcode":"63864",
    "sg:province":"Bayern",
    "wof:name":"Berthold Schuck",
    "wof:placetype":"venue"
},
  "geometry": {"coordinates":[9.153099,50.002449],"type":"Point"}
}