{
  "type": "Feature",
  "properties": {
    "iso:country":"DE",
    "sg:address":"Zollernstr. 83",
    "sg:city":"Sch\u00f6mberg",
    "sg:phone":"+49 7084/6180",
    "sg:postcode":"75328",
    "sg:province":"Baden-W\u00fcrttemberg",
    "wof:name":"G\u00e4stehaus Beck",
    "wof:placetype":"venue"
},
  "geometry": {"coordinates":[8.673743248,48.7819519043],"type":"Point"}
}