{
  "type": "Feature",
  "properties": {
    "iso:country":"DE",
    "sg:address":"Braunstr. 27",
    "sg:city":"Leipzig",
    "sg:postcode":"04347",
    "sg:province":"Sachsen",
    "wof:name":"Gfa-sachsen Ggmbh",
    "wof:placetype":"venue"
},
  "geometry": {"coordinates":[12.430107,51.37011],"type":"Point"}
}