{
  "type": "Feature",
  "properties": {
    "iso:country":"DE",
    "sg:address":"Friedrich-Bergius-Rg. 12",
    "sg:city":"W\u00fcrzburg",
    "sg:phone":"+49 931/279610",
    "sg:postcode":"97076",
    "sg:province":"Bayern",
    "wof:name":"Gasus Dosier-und F\u00d6rdertechnik Gmbh",
    "wof:placetype":"venue"
},
  "geometry": {"coordinates":[9.996992,49.801331],"type":"Point"}
}