{
  "type": "Feature",
  "properties": {
    "iso:country":"DE",
    "sg:address":"Kirchstr. 4",
    "sg:city":"Bischofswerda",
    "sg:phone":"+49 3594/707865",
    "sg:postcode":"01877",
    "sg:province":"Sachsen",
    "wof:name":"Kurt Simke",
    "wof:placetype":"venue"
},
  "geometry": {"coordinates":[14.181146,51.128338],"type":"Point"}
}