{
  "type": "Feature",
  "properties": {
    "iso:country":"DE",
    "sg:address":"Winsener Str. 49",
    "sg:city":"Hamburg",
    "sg:phone":"+49 40/7644966",
    "sg:postcode":"21077",
    "sg:province":"Hamburg",
    "wof:name":"Heinrich Oelkers",
    "wof:placetype":"venue"
},
  "geometry": {"coordinates":[9.989692688,53.4479789734],"type":"Point"}
}