{
  "type": "Feature",
  "properties": {
    "iso:country":"DE",
    "sg:address":"Schlufter 45",
    "sg:city":"Tonna",
    "sg:phone":"+49 36042/74337",
    "sg:postcode":"99958",
    "sg:province":"Th\u00fcringen",
    "wof:name":"Dieter Keil",
    "wof:placetype":"venue"
},
  "geometry": {"coordinates":[10.72095,51.062656],"type":"Point"}
}