{
  "type": "Feature",
  "properties": {
    "iso:country":"DE",
    "sg:address":"Gr\u00fcntalstr. 30",
    "sg:city":"Sailauf",
    "sg:phone":"+49 6093/679",
    "sg:postcode":"63877",
    "sg:province":"Bayern",
    "wof:name":"Walter Rauch",
    "wof:placetype":"venue"
},
  "geometry": {"coordinates":[9.257311821,50.0276870728],"type":"Point"}
}