{
  "type": "Feature",
  "properties": {
    "iso:country":"DE",
    "sg:address":"Briloner Str. 3",
    "sg:city":"Meschede",
    "sg:phone":"+49 291/2848",
    "sg:postcode":"59872",
    "sg:province":"Nordrhein-Westfalen",
    "wof:name":"Embassy",
    "wof:placetype":"venue"
},
  "geometry": {"coordinates":[8.2873878479,51.3456687927],"type":"Point"}
}