{
  "type": "Feature",
  "properties": {
    "iso:country":"DE",
    "sg:address":"Dehlingen",
    "sg:city":"Neresheim",
    "sg:phone":"+49 7326/454",
    "sg:postcode":"73450",
    "sg:province":"Baden-W\u00fcrttemberg",
    "wof:name":"Josef Eckert",
    "wof:placetype":"venue"
},
  "geometry": {"coordinates":[10.3519735336,48.7808532715],"type":"Point"}
}