{
  "type": "Feature",
  "properties": {
    "iso:country":"DE",
    "sg:address":"Bendstich 5",
    "sg:city":"Meisenheim",
    "sg:phone":"+49 6753/2567",
    "sg:postcode":"55590",
    "sg:province":"Rheinland-Pfalz",
    "wof:name":"Hans Fries",
    "wof:placetype":"venue"
},
  "geometry": {"coordinates":[7.6673669815,49.7036857605],"type":"Point"}
}