{
  "type": "Feature",
  "properties": {
    "iso:country":"DE",
    "sg:address":"Bergstr 12",
    "sg:city":"Trierweiler",
    "sg:phone":"+49 651/86286",
    "sg:postcode":"54311",
    "sg:province":"Rheinland-Pfalz",
    "wof:name":"Ch. Bauer",
    "wof:placetype":"venue"
},
  "geometry": {"coordinates":[6.5866298676,49.768913269],"type":"Point"}
}