{
  "type": "Feature",
  "properties": {
    "iso:country":"DE",
    "sg:address":"Lange Str. 51",
    "sg:city":"Uslar",
    "sg:phone":"+49 5571/2457",
    "sg:postcode":"37170",
    "sg:province":"Niedersachsen",
    "wof:name":"Otto Gruhlke",
    "wof:placetype":"venue"
},
  "geometry": {"coordinates":[9.638695,51.659565],"type":"Point"}
}