{
  "type": "Feature",
  "properties": {
    "iso:country":"DE",
    "sg:address":"Am Kreuzgraben 14",
    "sg:city":"Sulzbach",
    "sg:phone":"+49 6897/52544",
    "sg:postcode":"66280",
    "sg:province":"Saarland",
    "wof:name":"Rudolf Zimmer",
    "wof:placetype":"venue"
},
  "geometry": {"coordinates":[7.051252,49.312157],"type":"Point"}
}