{
  "type": "Feature",
  "properties": {
    "iso:country":"DE",
    "sg:address":"Oststr. 40",
    "sg:city":"Hamm",
    "sg:phone":"+49 2381/23520",
    "sg:postcode":"59065",
    "sg:province":"Nordrhein-Westfalen",
    "wof:name":"Zur Theke",
    "wof:placetype":"venue"
},
  "geometry": {"coordinates":[7.8233680725,51.6824684143],"type":"Point"}
}