{
  "type": "Feature",
  "properties": {
    "iso:country":"DE",
    "sg:address":"Platanenweg 51",
    "sg:city":"Markgr\u00f6ningen",
    "sg:phone":"+49 7145/6880",
    "sg:postcode":"71706",
    "sg:province":"Baden-W\u00fcrttemberg",
    "wof:name":"Bauwerk Bautr\u00e4ger Gmbh",
    "wof:placetype":"venue"
},
  "geometry": {"coordinates":[9.075303,48.907192],"type":"Point"}
}