{
  "type": "Feature",
  "properties": {
    "iso:country":"DE",
    "sg:address":"Duvalstr. 1",
    "sg:city":"Duderstadt",
    "sg:phone":"+49 5527/2623",
    "sg:postcode":"37115",
    "sg:province":"Niedersachsen",
    "wof:name":"Malerbetrieb Eckermann Inh. Dietmar Eckermann E. K.",
    "wof:placetype":"venue"
},
  "geometry": {"coordinates":[10.268239975,51.5160140991],"type":"Point"}
}