{
  "type": "Feature",
  "properties": {
    "iso:country":"DE",
    "sg:address":"Untere M\u00e4urichstr. 22",
    "sg:city":"Neuenstadt",
    "sg:phone":"+49 6264/7729",
    "sg:postcode":"74196",
    "sg:province":"Baden-W\u00fcrttemberg",
    "wof:name":"W. Murawski",
    "wof:placetype":"venue"
},
  "geometry": {"coordinates":[9.299339,49.253666],"type":"Point"}
}