{
  "type": "Feature",
  "properties": {
    "iso:country":"DE",
    "sg:address":"Solitudestr. 12",
    "sg:city":"Ditzingen",
    "sg:postcode":"71254",
    "sg:province":"Baden-W\u00fcrttemberg",
    "wof:name":"Sight Max Gmbh",
    "wof:placetype":"venue"
},
  "geometry": {"coordinates":[9.0638980865,48.8227462769],"type":"Point"}
}