{
  "type": "Feature",
  "properties": {
    "iso:country":"DE",
    "sg:address":"Barge 1",
    "sg:city":"Rhede",
    "sg:phone":"+49 2872/3362",
    "sg:postcode":"46414",
    "sg:province":"Nordrhein-Westfalen",
    "wof:name":"Heinrich Bovenkerk",
    "wof:placetype":"venue"
},
  "geometry": {"coordinates":[6.679992,51.828072],"type":"Point"}
}