{
  "type": "Feature",
  "properties": {
    "iso:country":"DE",
    "sg:address":"Am Stapel 16",
    "sg:city":"Altena",
    "sg:postcode":"58762",
    "sg:province":"Nordrhein-Westfalen",
    "wof:name":"Spielautomaten Vertriebs Gmbh",
    "wof:placetype":"venue"
},
  "geometry": {"coordinates":[7.6730380058,51.293888092],"type":"Point"}
}