{
  "type": "Feature",
  "properties": {
    "iso:country":"DE",
    "sg:address":"Heideweg 35",
    "sg:city":"Wegberg",
    "sg:phone":"+49 2436/1315",
    "sg:postcode":"41844",
    "sg:province":"Nordrhein-Westfalen",
    "wof:name":"F. Thies",
    "wof:placetype":"venue"
},
  "geometry": {"coordinates":[6.2891831398,51.1403198242],"type":"Point"}
}