{
  "type": "Feature",
  "properties": {
    "iso:country":"DE",
    "sg:address":"Hauptstr. 2",
    "sg:city":"Aschau",
    "sg:phone":"+49 8638/3488",
    "sg:postcode":"84544",
    "sg:province":"Bayern",
    "wof:name":"Christa Schreyer",
    "wof:placetype":"venue"
},
  "geometry": {"coordinates":[12.350060463,48.1975746155],"type":"Point"}
}