{
  "type": "Feature",
  "properties": {
    "iso:country":"DE",
    "sg:address":"Zimmersgasse 20",
    "sg:city":"Schenklengsfeld",
    "sg:phone":"+49 6629/6211",
    "sg:postcode":"36277",
    "sg:province":"Hessen",
    "wof:name":"K. Ellenberger",
    "wof:placetype":"venue"
},
  "geometry": {"coordinates":[9.78374,50.811169],"type":"Point"}
}