{
  "type": "Feature",
  "properties": {
    "iso:country":"DE",
    "sg:address":"Quellenweg 1",
    "sg:city":"Neuenkirchen-V\u00f6rden",
    "sg:phone":"+49 5493/240",
    "sg:postcode":"49434",
    "sg:province":"Niedersachsen",
    "wof:name":"J\u00fcrgen Kuhlmann Beteiligungs Gmbh",
    "wof:placetype":"venue"
},
  "geometry": {"coordinates":[8.079621,52.50515],"type":"Point"}
}