{
  "type": "Feature",
  "properties": {
    "iso:country":"DE",
    "sg:address":"Max-Lehner-Str.18",
    "sg:city":"Freising",
    "sg:phone":"+49 8161/919550",
    "sg:postcode":"85354",
    "sg:province":"Bayern",
    "wof:name":"Tauchen Tauch-oase Freising",
    "wof:placetype":"venue"
},
  "geometry": {"coordinates":[11.7412099838,48.3945503235],"type":"Point"}
}