{
  "type": "Feature",
  "properties": {
    "iso:country":"DE",
    "sg:address":"Servaisstr. 1a",
    "sg:city":"Trier",
    "sg:phone":"+49 651/64911",
    "sg:postcode":"54293",
    "sg:province":"Rheinland-Pfalz",
    "wof:name":"Lorscheter Gmbh",
    "wof:placetype":"venue"
},
  "geometry": {"coordinates":[6.6853208542,49.8065986633],"type":"Point"}
}