{
  "type": "Feature",
  "properties": {
    "iso:country":"DE",
    "sg:address":"Bungertstr. 41",
    "sg:city":"Essen",
    "sg:phone":"+49 201/354845",
    "sg:postcode":"45239",
    "sg:province":"Nordrhein-Westfalen",
    "wof:name":"Werdener Technik Center Michael Doffing",
    "wof:placetype":"venue"
},
  "geometry": {"coordinates":[7.003264904,51.3872795105],"type":"Point"}
}