{
  "type": "Feature",
  "properties": {
    "iso:country":"DE",
    "sg:address":"Hochstr. 29",
    "sg:city":"Dahlem",
    "sg:phone":"+49 2447/8352",
    "sg:postcode":"53949",
    "sg:province":"Nordrhein-Westfalen",
    "wof:name":"Jakob Thei\u00dfen",
    "wof:placetype":"venue"
},
  "geometry": {"coordinates":[6.556709,50.41243],"type":"Point"}
}