{
  "type": "Feature",
  "properties": {
    "iso:country":"DE",
    "sg:address":"Luitpoldstr. 17",
    "sg:city":"Prichsenstadt",
    "sg:phone":"+49 9383/6884",
    "sg:postcode":"97357",
    "sg:province":"Bayern",
    "wof:name":"M. Und D. Herrenschmidt",
    "wof:placetype":"venue"
},
  "geometry": {"coordinates":[10.3512020111,49.8176727295],"type":"Point"}
}