{
  "type": "Feature",
  "properties": {
    "iso:country":"DE",
    "sg:address":"Westendstr. 51",
    "sg:city":"Kempten",
    "sg:phone":"+49 831/21744",
    "sg:postcode":"87439",
    "sg:province":"Bayern",
    "wof:name":"Gert Frings",
    "wof:placetype":"venue"
},
  "geometry": {"coordinates":[10.3055610657,47.728187561],"type":"Point"}
}