{
  "type": "Feature",
  "properties": {
    "iso:country":"DE",
    "sg:address":"Lohbergenstr 19",
    "sg:city":"Buchholz",
    "sg:phone":"+49 4181/30040",
    "sg:postcode":"21244",
    "sg:province":"Niedersachsen",
    "wof:name":"Pleiger Kunststoff Technik Gmbh & Co Kg",
    "wof:placetype":"venue"
},
  "geometry": {"coordinates":[9.863571,53.286205],"type":"Point"}
}