{
  "type": "Feature",
  "properties": {
    "iso:country":"DE",
    "sg:address":"Gr\u00fcnbacher Str. 33",
    "sg:city":"Hammerbr\u00fccke",
    "sg:phone":"+49 37465/6142",
    "sg:postcode":"08269",
    "sg:province":"Sachsen",
    "wof:name":"Bauernsch\u00e4nke Inh. R. Seifert",
    "wof:placetype":"venue"
},
  "geometry": {"coordinates":[12.4033546448,50.4385070801],"type":"Point"}
}