{
  "type": "Feature",
  "properties": {
    "iso:country":"DE",
    "sg:address":"M\u00fchlenstr. 8",
    "sg:city":"L\u00f6ningen",
    "sg:postcode":"49624",
    "sg:province":"Niedersachsen",
    "wof:name":"Josef Pock Montagedienst Personalleasing Objekt-",
    "wof:placetype":"venue"
},
  "geometry": {"coordinates":[7.7624921799,52.7349128723],"type":"Point"}
}