{
  "type": "Feature",
  "properties": {
    "iso:country":"DE",
    "sg:address":"Marienstr. 18",
    "sg:city":"F\u00fcrth",
    "sg:phone":"+49 911/7498201",
    "sg:postcode":"90762",
    "sg:province":"Bayern",
    "wof:name":"Helene Augustin",
    "wof:placetype":"venue"
},
  "geometry": {"coordinates":[10.98601,49.473331],"type":"Point"}
}