{
  "type": "Feature",
  "properties": {
    "iso:country":"DE",
    "sg:address":"Kaikenrieder Str. 42",
    "sg:city":"Teisnach",
    "sg:phone":"+49 9923/1345",
    "sg:postcode":"94244",
    "sg:province":"Bayern",
    "wof:name":"Hans Kasparbauer Gmbh",
    "wof:placetype":"venue"
},
  "geometry": {"coordinates":[13.0035505295,49.0264472961],"type":"Point"}
}