{
  "type": "Feature",
  "properties": {
    "iso:country":"DE",
    "sg:address":"Kienberg",
    "sg:city":"Kienberg",
    "sg:phone":"+49 8628/256",
    "sg:postcode":"83361",
    "sg:province":"Bayern",
    "wof:name":"Raiffeisenbank Kienberg",
    "wof:placetype":"venue"
},
  "geometry": {"coordinates":[12.46256,48.036152],"type":"Point"}
}