{
  "type": "Feature",
  "properties": {
    "iso:country":"DE",
    "sg:address":"Konrad-Adenauer-Str. 1",
    "sg:city":"Taunusstein",
    "sg:phone":"+49 6128/42506",
    "sg:postcode":"65232",
    "sg:province":"Hessen",
    "wof:name":"Seidel Verm\u00f6gens- Verwaltungs Ohg",
    "wof:placetype":"venue"
},
  "geometry": {"coordinates":[8.1456651688,50.1349983215],"type":"Point"}
}