{
  "type": "Feature",
  "properties": {
    "iso:country":"DE",
    "sg:address":"Fischmarkt",
    "sg:city":"Wetzlar",
    "sg:phone":"+49 6441/34103",
    "sg:postcode":"35578",
    "sg:province":"Hessen",
    "wof:name":"Campingplatz Wetzlar",
    "wof:placetype":"venue"
},
  "geometry": {"coordinates":[8.50143,50.555168],"type":"Point"}
}