{
  "type": "Feature",
  "properties": {
    "iso:country":"DE",
    "sg:address":"Mullstr. 10",
    "sg:city":"Harpstedt",
    "sg:phone":"+49 4244/695",
    "sg:postcode":"27243",
    "sg:province":"Niedersachsen",
    "wof:name":"M. Wessels Heissmangelbetrieb",
    "wof:placetype":"venue"
},
  "geometry": {"coordinates":[8.5855379105,52.9100036621],"type":"Point"}
}