{
  "type": "Feature",
  "properties": {
    "iso:country":"DE",
    "sg:address":"Trautnerstr. 4",
    "sg:city":"Aachen",
    "sg:phone":"+49 241/63091",
    "sg:postcode":"52066",
    "sg:province":"Nordrhein-Westfalen",
    "wof:name":"Altenpflegezentrum Papst-johannes-stift",
    "wof:placetype":"venue"
},
  "geometry": {"coordinates":[6.082898,50.753227],"type":"Point"}
}