{
  "type": "Feature",
  "properties": {
    "iso:country":"DE",
    "sg:address":"Hauptstr. 11",
    "sg:city":"Lemwerder",
    "sg:phone":"+49 421/675454",
    "sg:postcode":"27809",
    "sg:province":"Niedersachsen",
    "wof:name":"Rahder Gmbh",
    "wof:placetype":"venue"
},
  "geometry": {"coordinates":[8.594431,53.140995],"type":"Point"}
}