{
  "type": "Feature",
  "properties": {
    "iso:country":"DE",
    "sg:address":"Rachelstr. 2",
    "sg:city":"Landshut",
    "sg:phone":"+49 871/71958",
    "sg:postcode":"84030",
    "sg:province":"Bayern",
    "wof:name":"Ernst Gramlich Grabdenkm\u00e4ler",
    "wof:placetype":"venue"
},
  "geometry": {"coordinates":[12.1385269165,48.5544509888],"type":"Point"}
}