{
  "type": "Feature",
  "properties": {
    "iso:country":"DE",
    "sg:address":"Viktoriastr. 7",
    "sg:city":"Wiesbaden",
    "sg:phone":"+49 611/301631",
    "sg:postcode":"65189",
    "sg:province":"Hessen",
    "wof:name":"Hotel-restaurant Spitzgrundm\u00fchle Und",
    "wof:placetype":"venue"
},
  "geometry": {"coordinates":[8.249578476,50.0768814087],"type":"Point"}
}