{
  "type": "Feature",
  "properties": {
    "iso:country":"DE",
    "sg:address":"F\u00fcrstenrieder Str. 273",
    "sg:city":"M\u00fcnchen",
    "sg:postcode":"81377",
    "sg:province":"Bayern",
    "wof:name":"Altweger Rechtsanwaltsgesellschaft Mbh",
    "wof:placetype":"venue"
},
  "geometry": {"coordinates":[11.5025405884,48.1094436646],"type":"Point"}
}