{
  "type": "Feature",
  "properties": {
    "iso:country":"DE",
    "sg:address":"Buchenweg 2",
    "sg:city":"Bad Camberg",
    "sg:phone":"+49 6483/5395",
    "sg:postcode":"65520",
    "sg:province":"Hessen",
    "wof:name":"Tilo Cronauge",
    "wof:placetype":"venue"
},
  "geometry": {"coordinates":[8.2438011169,50.3193244934],"type":"Point"}
}