{
  "type": "Feature",
  "properties": {
    "iso:country":"DE",
    "sg:address":"Schubertstr. 16",
    "sg:city":"L\u00fcnen",
    "sg:phone":"+49 4926/616210",
    "sg:postcode":"44534",
    "sg:province":"Nordrhein-Westfalen",
    "wof:name":"Menk Apparatebau Gmbh",
    "wof:placetype":"venue"
},
  "geometry": {"coordinates":[7.94978,50.646461],"type":"Point"}
}