{
  "type": "Feature",
  "properties": {
    "iso:country":"DE",
    "sg:address":"Am Birkenwerder 56",
    "sg:city":"Berlin",
    "sg:phone":"+49 30/89093710",
    "sg:postcode":"12621",
    "sg:province":"Berlin",
    "wof:name":"Anke Eggert",
    "wof:placetype":"venue"
},
  "geometry": {"coordinates":[13.5699892044,52.4846038818],"type":"Point"}
}