{
  "type": "Feature",
  "properties": {
    "iso:country":"DE",
    "sg:address":"Euelerhammerstr. 7",
    "sg:city":"Reichshof",
    "sg:phone":"+49 2296/98130",
    "sg:postcode":"51580",
    "sg:province":"Nordrhein-Westfalen",
    "wof:name":"Sachweh Gmbh",
    "wof:placetype":"venue"
},
  "geometry": {"coordinates":[7.6344718933,50.9285469055],"type":"Point"}
}