{
  "type": "Feature",
  "properties": {
    "iso:country":"DE",
    "sg:address":"Schusterstra\u00dfe 5",
    "sg:city":"W\u00fcrzburg",
    "sg:postcode":"97070",
    "sg:province":"Bayern",
    "wof:name":"Mega-games 24",
    "wof:placetype":"venue"
},
  "geometry": {"coordinates":[9.9293689728,49.7936859131],"type":"Point"}
}