{
  "type": "Feature",
  "properties": {
    "iso:country":"DE",
    "sg:address":"Oberdorf 19",
    "sg:city":"M\u00fcnsingen",
    "sg:phone":"+49 7383/1736",
    "sg:postcode":"72525",
    "sg:province":"Baden-W\u00fcrttemberg",
    "wof:name":"Hermann Und Christina Bentele",
    "wof:placetype":"venue"
},
  "geometry": {"coordinates":[9.485307,48.343822],"type":"Point"}
}