{
  "type": "Feature",
  "properties": {
    "iso:country":"DE",
    "sg:address":"Stockerholzstr. 12",
    "sg:city":"Friedrichshafen",
    "sg:postcode":"88048",
    "sg:province":"Baden-W\u00fcrttemberg",
    "wof:name":"Eurospar",
    "wof:placetype":"venue"
},
  "geometry": {"coordinates":[9.4339742661,47.6638069153],"type":"Point"}
}