{
  "type": "Feature",
  "properties": {
    "iso:country":"DE",
    "sg:address":"Drosselweg 10",
    "sg:city":"Eldingen",
    "sg:phone":"+49 5148/207",
    "sg:postcode":"29351",
    "sg:province":"Niedersachsen",
    "wof:name":"A. K\u00fckem\u00fcck",
    "wof:placetype":"venue"
},
  "geometry": {"coordinates":[10.3412504196,52.6848678589],"type":"Point"}
}