{
  "type": "Feature",
  "properties": {
    "iso:country":"DE",
    "sg:address":"In der R\u00f6th 47",
    "sg:city":"R\u00fcsselsheim",
    "sg:phone":"+49 6142/68217",
    "sg:postcode":"65428",
    "sg:province":"Hessen",
    "wof:name":"Zweithaarstudio Anne-trude - R\u00fcsselsheim",
    "wof:placetype":"venue"
},
  "geometry": {"coordinates":[8.406404,49.983498],"type":"Point"}
}