{
  "type": "Feature",
  "properties": {
    "iso:country":"DE",
    "sg:address":"Nr. 55",
    "sg:city":"Heilingen",
    "sg:postcode":"07407",
    "sg:province":"Th\u00fcringen",
    "wof:name":"Pfeiffer Gdbr",
    "wof:placetype":"venue"
},
  "geometry": {"coordinates":[11.3335895538,50.7327804565],"type":"Point"}
}