{
  "type": "Feature",
  "properties": {
    "iso:country":"DE",
    "sg:address":"Siedlung 2",
    "sg:city":"Sch\u00f6nhausen",
    "sg:postcode":"39524",
    "sg:province":"Sachsen-Anhalt",
    "wof:name":"H. Burkhardt",
    "wof:placetype":"venue"
},
  "geometry": {"coordinates":[12.045545,52.575726],"type":"Point"}
}