{
  "type": "Feature",
  "properties": {
    "iso:country":"DE",
    "sg:address":"Flottmannstr. 57",
    "sg:city":"Bochum",
    "sg:phone":"+49 234/904530",
    "sg:postcode":"44807",
    "sg:province":"Nordrhein-Westfalen",
    "wof:name":"Gsb Group Gmbh",
    "wof:placetype":"venue"
},
  "geometry": {"coordinates":[7.2195291519,51.5174255371],"type":"Point"}
}