{
  "type": "Feature",
  "properties": {
    "iso:country":"DE",
    "sg:address":"Hinter der Kirche 27",
    "sg:city":"Duisburg",
    "sg:postcode":"47058",
    "sg:province":"Nordrhein-Westfalen",
    "wof:name":"Global Linen Exports Gmbh",
    "wof:placetype":"venue"
},
  "geometry": {"coordinates":[6.788242,51.435688],"type":"Point"}
}