{
  "type": "Feature",
  "properties": {
    "iso:country":"DE",
    "sg:address":"Schulweg 1",
    "sg:city":"Nordkirchen",
    "sg:phone":"+49 2596/98910",
    "sg:postcode":"59394",
    "sg:province":"Nordrhein-Westfalen",
    "wof:name":"M\u00fcnsterland-grill",
    "wof:placetype":"venue"
},
  "geometry": {"coordinates":[7.5927519798,51.7320175171],"type":"Point"}
}