{
  "type": "Feature",
  "properties": {
    "iso:country":"DE",
    "sg:address":"Theodor-Heuss-Str. 28",
    "sg:city":"Konstanz",
    "sg:phone":"+49 7531/53529",
    "sg:postcode":"78467",
    "sg:province":"Baden-W\u00fcrttemberg",
    "wof:name":"Meyer & Co. Gmbh",
    "wof:placetype":"venue"
},
  "geometry": {"coordinates":[9.182269,47.66996],"type":"Point"}
}