{
  "type": "Feature",
  "properties": {
    "iso:country":"DE",
    "sg:address":"Weingartstr. 22",
    "sg:city":"Denkendorf",
    "sg:phone":"+49 711/3466028",
    "sg:postcode":"73770",
    "sg:province":"Baden-W\u00fcrttemberg",
    "wof:name":"Cis Gmbh",
    "wof:placetype":"venue"
},
  "geometry": {"coordinates":[9.3122501373,48.6964988708],"type":"Point"}
}