{
  "type": "Feature",
  "properties": {
    "iso:country":"DE",
    "sg:address":"Gockelweg 19",
    "sg:city":"Berlin",
    "sg:phone":"+49 30/6631511",
    "sg:postcode":"12355",
    "sg:province":"Berlin",
    "wof:name":"Lothar K\u00fchne",
    "wof:placetype":"venue"
},
  "geometry": {"coordinates":[13.482485,52.399372],"type":"Point"}
}