{
  "type": "Feature",
  "properties": {
    "iso:country":"DE",
    "sg:address":"Am St\u00fcnzel 7",
    "sg:city":"Schmallenberg",
    "sg:phone":"+49 2972/1361",
    "sg:postcode":"57392",
    "sg:province":"Nordrhein-Westfalen",
    "wof:name":"Pension K. Hennecke",
    "wof:placetype":"venue"
},
  "geometry": {"coordinates":[8.3302650452,51.1422996521],"type":"Point"}
}