{
  "type": "Feature",
  "properties": {
    "iso:country":"DE",
    "sg:address":"Helleter Feldchen 47",
    "sg:city":"W\u00fcrselen",
    "sg:phone":"+49 2405/72497",
    "sg:postcode":"52146",
    "sg:province":"Nordrhein-Westfalen",
    "wof:name":"Dieter Vonhoegen",
    "wof:placetype":"venue"
},
  "geometry": {"coordinates":[6.1608939171,50.823474884],"type":"Point"}
}