{
  "type": "Feature",
  "properties": {
    "iso:country":"DE",
    "sg:address":"Wasserstr. 48",
    "sg:city":"Hornburg",
    "sg:phone":"+49 5334/1531",
    "sg:postcode":"38315",
    "sg:province":"Niedersachsen",
    "wof:name":"Karl-jonas Brandes",
    "wof:placetype":"venue"
},
  "geometry": {"coordinates":[10.606011,52.032574],"type":"Point"}
}