{
  "type": "Feature",
  "properties": {
    "iso:country":"DE",
    "sg:address":"Marktstr. 14",
    "sg:city":"J\u00fclich",
    "sg:phone":"+49 2461/910049",
    "sg:postcode":"52428",
    "sg:province":"Nordrhein-Westfalen",
    "wof:name":"R. Junggeburth",
    "wof:placetype":"venue"
},
  "geometry": {"coordinates":[6.3579931259,50.9208564758],"type":"Point"}
}