{
  "type": "Feature",
  "properties": {
    "iso:country":"DE",
    "sg:address":"Tannenloheweg 3",
    "sg:city":"Wiesau",
    "sg:phone":"+49 9634/3366",
    "sg:postcode":"95676",
    "sg:province":"Bayern",
    "wof:name":"Josef H\u00e4rtl",
    "wof:placetype":"venue"
},
  "geometry": {"coordinates":[12.196083,49.889996],"type":"Point"}
}