{
  "type": "Feature",
  "properties": {
    "iso:country":"DE",
    "sg:address":"Altenburger Str. 16",
    "sg:city":"Gera",
    "sg:phone":"+49 365/200601",
    "sg:postcode":"07546",
    "sg:province":"Th\u00fcringen",
    "wof:name":"Restaurant Trakia Inh. Charlotte Polichronow",
    "wof:placetype":"venue"
},
  "geometry": {"coordinates":[12.0906963348,50.8796920776],"type":"Point"}
}