{
  "type": "Feature",
  "properties": {
    "iso:country":"DE",
    "sg:address":"Hohenlohestr. 13",
    "sg:city":"Forchtenberg",
    "sg:phone":"+49 7947/502",
    "sg:postcode":"74670",
    "sg:province":"Baden-W\u00fcrttemberg",
    "wof:name":"Walter Ludwig",
    "wof:placetype":"venue"
},
  "geometry": {"coordinates":[9.5760602951,49.2635192871],"type":"Point"}
}