{
  "type": "Feature",
  "properties": {
    "iso:country":"DE",
    "sg:address":"Eichhofener Str. 4",
    "sg:city":"Nittendorf",
    "sg:phone":"+49 9404/1907",
    "sg:postcode":"93152",
    "sg:province":"Bayern",
    "wof:name":"Deutsche Bahn Ag",
    "wof:placetype":"venue"
},
  "geometry": {"coordinates":[11.9373121262,49.0274581909],"type":"Point"}
}