{
  "type": "Feature",
  "properties": {
    "iso:country":"DE",
    "sg:address":"Mainzer Str. 119",
    "sg:city":"Bad Kreuznach",
    "sg:phone":"+49 671/68042",
    "sg:postcode":"55545",
    "sg:province":"Rheinland-Pfalz",
    "wof:name":"Helmut Schenk",
    "wof:placetype":"venue"
},
  "geometry": {"coordinates":[7.9137268066,49.8659095764],"type":"Point"}
}