{
  "type": "Feature",
  "properties": {
    "iso:country":"DE",
    "sg:address":"Lockhauser Str. 26",
    "sg:city":"Herford",
    "sg:phone":"+49 5221/759755",
    "sg:postcode":"32052",
    "sg:province":"Nordrhein-Westfalen",
    "wof:name":"Ics Composting Services Gmbh",
    "wof:placetype":"venue"
},
  "geometry": {"coordinates":[8.673193,52.106178],"type":"Point"}
}