{
  "type": "Feature",
  "properties": {
    "iso:country":"DE",
    "sg:address":"Fr\u00fchlinghausen 12",
    "sg:city":"Balve",
    "sg:phone":"+49 2375/91860",
    "sg:postcode":"58802",
    "sg:province":"Nordrhein-Westfalen",
    "wof:name":"Anton Schmoll Schraubenfabrik Gmbh",
    "wof:placetype":"venue"
},
  "geometry": {"coordinates":[7.83463,51.325039],"type":"Point"}
}