{
  "type": "Feature",
  "properties": {
    "iso:country":"DE",
    "sg:address":"Z\u00f6llnertorstr. 5",
    "sg:city":"Schwabach",
    "sg:phone":"+49 9122/2140",
    "sg:postcode":"91126",
    "sg:province":"Bayern",
    "wof:name":"Willi Schmidt",
    "wof:placetype":"venue"
},
  "geometry": {"coordinates":[11.017824173,49.3290557861],"type":"Point"}
}