{
  "type": "Feature",
  "properties": {
    "iso:country":"DE",
    "sg:address":"Rothenburger Str. 29",
    "sg:city":"Oberasbach",
    "sg:phone":"+49 911/692114",
    "sg:postcode":"90522",
    "sg:province":"Bayern",
    "wof:name":"Josef Wieland",
    "wof:placetype":"venue"
},
  "geometry": {"coordinates":[10.9748020172,49.4350585938],"type":"Point"}
}