{
  "type": "Feature",
  "properties": {
    "iso:country":"DE",
    "sg:address":"Kammerer Str. 5",
    "sg:city":"Traunstein",
    "sg:phone":"+49 861/4314",
    "sg:postcode":"83278",
    "sg:province":"Bayern",
    "wof:name":"Knorr",
    "wof:placetype":"venue"
},
  "geometry": {"coordinates":[12.6486558914,47.8721237183],"type":"Point"}
}