{
  "type": "Feature",
  "properties": {
    "iso:country":"DE",
    "sg:address":"Kaiser-Otto-Str. 104",
    "sg:city":"Pulheim",
    "sg:phone":"+49 2234/83303",
    "sg:postcode":"50259",
    "sg:province":"Nordrhein-Westfalen",
    "wof:name":"Manfred Steffens Immobilienmakler",
    "wof:placetype":"venue"
},
  "geometry": {"coordinates":[6.7711439133,50.9595108032],"type":"Point"}
}