{
  "type": "Feature",
  "properties": {
    "iso:country":"DE",
    "sg:address":"Wilhelm-Leuschner-Str 6",
    "sg:city":"Darmstadt",
    "sg:phone":"+49 6151/20277",
    "sg:postcode":"64293",
    "sg:province":"Hessen",
    "wof:name":"J.g. Herbertsche",
    "wof:placetype":"venue"
},
  "geometry": {"coordinates":[8.647324,49.876129],"type":"Point"}
}