{
  "type": "Feature",
  "properties": {
    "iso:country":"DE",
    "sg:address":"Kapellengasse 6",
    "sg:city":"Regensburg",
    "sg:postcode":"93047",
    "sg:province":"Bayern",
    "wof:name":"Johann Bachfischer Handels- Und Verwaltungs-kg",
    "wof:placetype":"venue"
},
  "geometry": {"coordinates":[12.0994176865,49.0179405212],"type":"Point"}
}