{
  "type": "Feature",
  "properties": {
    "iso:country":"DE",
    "sg:address":"Neustrelitzer Str. 7d",
    "sg:city":"Neubrandenburg",
    "sg:phone":"+49 395/5823785",
    "sg:postcode":"17033",
    "sg:province":"Mecklenburg-Vorpommern",
    "wof:name":"Ingrid Ebert",
    "wof:placetype":"venue"
},
  "geometry": {"coordinates":[13.2651357651,53.5496673584],"type":"Point"}
}