{
  "type": "Feature",
  "properties": {
    "iso:country":"DE",
    "sg:address":"Saal\u00e4ckerstr. 2",
    "sg:city":"Kleinostheim",
    "sg:postcode":"63801",
    "sg:province":"Bayern",
    "wof:name":"Pv 5 Solarconcept Gmbh",
    "wof:placetype":"venue"
},
  "geometry": {"coordinates":[9.0707406998,49.9947967529],"type":"Point"}
}