{
  "type": "Feature",
  "properties": {
    "iso:country":"DE",
    "sg:address":"Dietrichstr. 14",
    "sg:city":"Frankfurt",
    "sg:phone":"+49 69/581856",
    "sg:postcode":"60439",
    "sg:province":"Hessen",
    "wof:name":"D. Hering Architekt",
    "wof:placetype":"venue"
},
  "geometry": {"coordinates":[8.624997,50.156395],"type":"Point"}
}