{
  "type": "Feature",
  "properties": {
    "iso:country":"DE",
    "sg:address":"Rehwinkel 12 a",
    "sg:city":"Seelze",
    "sg:phone":"+49 5137/94179",
    "sg:postcode":"30926",
    "sg:province":"Niedersachsen",
    "wof:name":"Egbert Koch",
    "wof:placetype":"venue"
},
  "geometry": {"coordinates":[9.5651597977,52.378074646],"type":"Point"}
}