{
  "type": "Feature",
  "properties": {
    "iso:country":"DE",
    "sg:address":"Parkstr. 60",
    "sg:city":"Berlin",
    "sg:phone":"+49 30/4851604",
    "sg:postcode":"13187",
    "sg:province":"Berlin",
    "wof:name":"Renate Und Reiner Rauer Architekten",
    "wof:placetype":"venue"
},
  "geometry": {"coordinates":[13.406396,52.57346],"type":"Point"}
}