{
  "type": "Feature",
  "properties": {
    "iso:country":"DE",
    "sg:address":"Tunnelstr. 26",
    "sg:city":"Pirmasens",
    "sg:phone":"+49 6331/229016",
    "sg:postcode":"66953",
    "sg:province":"Rheinland-Pfalz",
    "wof:name":"Bw-consulting Informatik Und Kommunikation Gmbh",
    "wof:placetype":"venue"
},
  "geometry": {"coordinates":[7.5977377892,49.2090454102],"type":"Point"}
}