{
  "type": "Feature",
  "properties": {
    "iso:country":"DE",
    "sg:address":"M\u00fcnchener Str. 33c",
    "sg:city":"Roth",
    "sg:phone":"+49 9171/7189",
    "sg:postcode":"91154",
    "sg:province":"Bayern",
    "wof:name":"Wettemann Rad - Sport",
    "wof:placetype":"venue"
},
  "geometry": {"coordinates":[11.090051,49.242924],"type":"Point"}
}