{
  "type": "Feature",
  "properties": {
    "iso:country":"DE",
    "sg:address":"Linden-Kirch-Platz",
    "sg:city":"Dormagen",
    "sg:postcode":"41542",
    "sg:province":"Nordrhein-Westfalen",
    "wof:name":"Kath. Pfarrb\u00fccherei St. Agatha",
    "wof:placetype":"venue"
},
  "geometry": {"coordinates":[6.763096,51.092136],"type":"Point"}
}