{
  "type": "Feature",
  "properties": {
    "iso:country":"DE",
    "sg:address":"Wendelsteinstr. 19 c",
    "sg:city":"Gr\u00e4felfing",
    "sg:postcode":"82166",
    "sg:province":"Bayern",
    "wof:name":"Bau-funktion-physik Biologie Gmbh",
    "wof:placetype":"venue"
},
  "geometry": {"coordinates":[11.4319210052,48.1161231995],"type":"Point"}
}