{
  "type": "Feature",
  "properties": {
    "iso:country":"DE",
    "sg:address":"Berliner Str. 150",
    "sg:city":"Wuppertal",
    "sg:phone":"+49 202/641587",
    "sg:postcode":"42277",
    "sg:province":"Nordrhein-Westfalen",
    "wof:name":"Hosen-k\u00f6nig Harzer Kg Inh. Rosemarie Schulz",
    "wof:placetype":"venue"
},
  "geometry": {"coordinates":[7.2193870544,51.2750091553],"type":"Point"}
}