{
  "type": "Feature",
  "properties": {
    "iso:country":"DE",
    "sg:address":"Bahnhofstr. 151",
    "sg:city":"L\u00f6hne",
    "sg:phone":"+49 5732/2330",
    "sg:postcode":"32584",
    "sg:province":"Nordrhein-Westfalen",
    "wof:name":"Gemeindeb\u00fccherei Schule Obernbeck-nord",
    "wof:placetype":"venue"
},
  "geometry": {"coordinates":[8.689236,52.210114],"type":"Point"}
}