{
  "type": "Feature",
  "properties": {
    "iso:country":"DE",
    "sg:address":"Goethestr. 2",
    "sg:city":"L\u00fcnen",
    "sg:phone":"+49 2306/50754",
    "sg:postcode":"44534",
    "sg:province":"Nordrhein-Westfalen",
    "wof:name":"Helmut Albertz",
    "wof:placetype":"venue"
},
  "geometry": {"coordinates":[7.531678,51.619633],"type":"Point"}
}