{
  "type": "Feature",
  "properties": {
    "iso:country":"DE",
    "sg:address":"Werftstr. 23",
    "sg:city":"Stralsund",
    "sg:phone":"+49 3831/297876",
    "sg:postcode":"18439",
    "sg:province":"Mecklenburg-Vorpommern",
    "wof:name":"Kl.-dieter Weitzel Industrievertretungen",
    "wof:placetype":"venue"
},
  "geometry": {"coordinates":[13.0953235626,54.3017044067],"type":"Point"}
}