{
  "type": "Feature",
  "properties": {
    "iso:country":"DE",
    "sg:address":"Saarstr. 45",
    "sg:city":"Dillingen",
    "sg:phone":"+49 6831/71246",
    "sg:postcode":"66763",
    "sg:province":"Saarland",
    "wof:name":"Kath. \u00d6ffentliche Bibliothek Heiliges Sakrament",
    "wof:placetype":"venue"
},
  "geometry": {"coordinates":[6.726099,49.356186],"type":"Point"}
}