{
  "type": "Feature",
  "properties": {
    "iso:country":"DE",
    "sg:address":"Am Fillerschlo\u00df 45",
    "sg:city":"Georgsmarienh\u00fctte",
    "sg:phone":"+49 5401/2370",
    "sg:postcode":"49124",
    "sg:province":"Niedersachsen",
    "wof:name":"Tiemann Heissmangel",
    "wof:placetype":"venue"
},
  "geometry": {"coordinates":[8.0147390366,52.2043762207],"type":"Point"}
}