{
  "type": "Feature",
  "properties": {
    "iso:country":"DE",
    "sg:address":"Albert-Schweitzer-Str. 4",
    "sg:city":"Marktredwitz",
    "sg:phone":"+49 9231/87339",
    "sg:postcode":"95615",
    "sg:province":"Bayern",
    "wof:name":"E. Oetter",
    "wof:placetype":"venue"
},
  "geometry": {"coordinates":[12.065098,50.000656],"type":"Point"}
}