{
  "type": "Feature",
  "properties": {
    "iso:country":"DE",
    "sg:address":"Vierherren 3",
    "sg:city":"Wolfsburg",
    "sg:phone":"+49 5362/64370",
    "sg:postcode":"38442",
    "sg:province":"Niedersachsen",
    "wof:name":"P. Holweg",
    "wof:placetype":"venue"
},
  "geometry": {"coordinates":[10.69316,52.416306],"type":"Point"}
}