{
  "type": "Feature",
  "properties": {
    "iso:country":"DE",
    "sg:address":"Tegernseer Landstr. 71",
    "sg:city":"M\u00fcnchen",
    "sg:phone":"+49 89/6917077",
    "sg:postcode":"81539",
    "sg:province":"Bayern",
    "wof:name":"Walchensee-apotheke Inh. Ruth Markhauser",
    "wof:placetype":"venue"
},
  "geometry": {"coordinates":[11.579456,48.114857],"type":"Point"}
}