{
  "type": "Feature",
  "properties": {
    "iso:country":"DE",
    "sg:address":"Wasserfuhr 32",
    "sg:city":"Bad Salzuflen",
    "sg:phone":"+49 5222/81485",
    "sg:postcode":"32108",
    "sg:province":"Nordrhein-Westfalen",
    "wof:name":"Eiscafe Rialto",
    "wof:placetype":"venue"
},
  "geometry": {"coordinates":[8.76141,52.075157],"type":"Point"}
}