{
  "type": "Feature",
  "properties": {
    "iso:country":"DE",
    "sg:address":"Untergasse 18",
    "sg:city":"Usingen",
    "sg:phone":"+49 6081/66533",
    "sg:postcode":"61250",
    "sg:province":"Hessen",
    "wof:name":"Alt Usingen",
    "wof:placetype":"venue"
},
  "geometry": {"coordinates":[8.5386161804,50.3330078125],"type":"Point"}
}