{
  "type": "Feature",
  "properties": {
    "iso:country":"DE",
    "sg:address":"Burgfriedstr. 23",
    "sg:city":"Daun",
    "sg:phone":"+49 6592/2192",
    "sg:postcode":"54550",
    "sg:province":"Rheinland-Pfalz",
    "wof:name":"R. Even",
    "wof:placetype":"venue"
},
  "geometry": {"coordinates":[6.830207,50.196899],"type":"Point"}
}