{
  "type": "Feature",
  "properties": {
    "iso:country":"DE",
    "sg:address":"Pfarrer-Kranz-Str. 17",
    "sg:city":"Oberschlei\u00dfheim",
    "sg:phone":"+49 89/3154968",
    "sg:postcode":"85764",
    "sg:province":"Bayern",
    "wof:name":"Peter Kieser Garten-u. Landsch.-architekt",
    "wof:placetype":"venue"
},
  "geometry": {"coordinates":[11.546487,48.252754],"type":"Point"}
}