{
  "type": "Feature",
  "properties": {
    "iso:country":"DE",
    "sg:address":"Opernstr. 13",
    "sg:city":"Kassel",
    "sg:phone":"+49 561/13102",
    "sg:postcode":"34117",
    "sg:province":"Hessen",
    "wof:name":"Wenzel Und Wilk Rechtsanw\u00e4lte Und Notare",
    "wof:placetype":"venue"
},
  "geometry": {"coordinates":[9.4922389984,51.3142318726],"type":"Point"}
}