{
  "type": "Feature",
  "properties": {
    "iso:country":"DE",
    "sg:address":"Burgweg 4",
    "sg:city":"Schmitten",
    "sg:phone":"+49 6082/950600",
    "sg:postcode":"61389",
    "sg:province":"Hessen",
    "wof:name":"Berbott Gmbh",
    "wof:placetype":"venue"
},
  "geometry": {"coordinates":[8.427371,50.244812],"type":"Point"}
}