{
  "type": "Feature",
  "properties": {
    "iso:country":"DE",
    "sg:address":"St.-Apern-Str. 44 -46",
    "sg:city":"K\u00f6ln",
    "sg:phone":"+49 221/2575118",
    "sg:postcode":"50667",
    "sg:province":"Nordrhein-Westfalen",
    "wof:name":"Antik Am Turm Gmbh",
    "wof:placetype":"venue"
},
  "geometry": {"coordinates":[6.946327,50.940052],"type":"Point"}
}