{
  "type": "Feature",
  "properties": {
    "iso:country":"DE",
    "sg:address":"Ruhrstr. 12",
    "sg:city":"Olsberg",
    "sg:phone":"+49 2962/1683",
    "sg:postcode":"59939",
    "sg:province":"Nordrhein-Westfalen",
    "wof:name":"Karl Westhelle & Sohn",
    "wof:placetype":"venue"
},
  "geometry": {"coordinates":[8.487812,51.353298],"type":"Point"}
}