{
  "type": "Feature",
  "properties": {
    "iso:country":"DE",
    "sg:address":"Im Gr\u00fcnen Winkel 16a",
    "sg:city":"Wesel",
    "sg:phone":"+49 281/26331",
    "sg:postcode":"46483",
    "sg:province":"Nordrhein-Westfalen",
    "wof:name":"A.-k. Schlo\u00dfmacher Steuerberater",
    "wof:placetype":"venue"
},
  "geometry": {"coordinates":[6.6200971603,51.6640625],"type":"Point"}
}