{
  "type": "Feature",
  "properties": {
    "iso:country":"DE",
    "sg:address":"Surkenstr. 31",
    "sg:city":"Bochum",
    "sg:phone":"+49 234/797939",
    "sg:postcode":"44797",
    "sg:province":"Nordrhein-Westfalen",
    "wof:name":"Dr. Gerhard Zimmermann Tierarzt",
    "wof:placetype":"venue"
},
  "geometry": {"coordinates":[7.2409200668,51.4312896729],"type":"Point"}
}