{
  "type": "Feature",
  "properties": {
    "iso:country":"DE",
    "sg:address":"Hermann-St\u00f6ber-Str. 1",
    "sg:city":"Helmstedt",
    "sg:phone":"+49 5351/6304",
    "sg:postcode":"38350",
    "sg:province":"Niedersachsen",
    "wof:name":"Christa Ahrens Immobilienmaklerin",
    "wof:placetype":"venue"
},
  "geometry": {"coordinates":[11.004778862,52.2221794128],"type":"Point"}
}