{
  "type": "Feature",
  "properties": {
    "iso:country":"DE",
    "sg:address":"Sch\u00fctzenplatz 9",
    "sg:city":"Schwanewede",
    "sg:phone":"+49 421/661516",
    "sg:postcode":"28790",
    "sg:province":"Niedersachsen",
    "wof:name":"H & Melektrotechnik Gmbh",
    "wof:placetype":"venue"
},
  "geometry": {"coordinates":[8.593943,53.185661],"type":"Point"}
}