{
  "type": "Feature",
  "properties": {
    "iso:country":"DE",
    "sg:address":"Hangweg 10",
    "sg:city":"St. Andreasberg",
    "sg:phone":"+49 5582/613",
    "sg:postcode":"37444",
    "sg:province":"Niedersachsen",
    "wof:name":"Karl-heinrich Weidemeier Architekt",
    "wof:placetype":"venue"
},
  "geometry": {"coordinates":[10.511593,51.713123],"type":"Point"}
}