{
  "type": "Feature",
  "properties": {
    "iso:country":"DE",
    "sg:address":"W\u00fcrthweg 3",
    "sg:city":"Darmstadt",
    "sg:phone":"+49 6151/24724",
    "sg:postcode":"64283",
    "sg:province":"Hessen",
    "wof:name":"Georg Gemmersd\u00f6rfer",
    "wof:placetype":"venue"
},
  "geometry": {"coordinates":[8.6576414108,49.8726425171],"type":"Point"}
}