{
  "type": "Feature",
  "properties": {
    "iso:country":"DE",
    "sg:address":"Ba\u00dfberg 1",
    "sg:city":"Gro\u00dfalmerode",
    "sg:phone":"+49 5604/5261",
    "sg:postcode":"37247",
    "sg:province":"Hessen",
    "wof:name":"Eduard Rappe",
    "wof:placetype":"venue"
},
  "geometry": {"coordinates":[9.782338,51.258099],"type":"Point"}
}