{
  "type": "Feature",
  "properties": {
    "iso:country":"DE",
    "sg:address":"Sympherallee 2",
    "sg:city":"D\u00f6rverden",
    "sg:phone":"+49 4234/699",
    "sg:postcode":"27313",
    "sg:province":"Niedersachsen",
    "wof:name":"Arnold Streek",
    "wof:placetype":"venue"
},
  "geometry": {"coordinates":[9.223769,52.848892],"type":"Point"}
}