{
  "type": "Feature",
  "properties": {
    "iso:country":"DE",
    "sg:address":"Auf der H\u00f6lle 6",
    "sg:city":"Bad Laer",
    "sg:phone":"+49 5403/2296",
    "sg:postcode":"49196",
    "sg:province":"Niedersachsen",
    "wof:name":"Horst Gramsch",
    "wof:placetype":"venue"
},
  "geometry": {"coordinates":[8.038021,52.116711],"type":"Point"}
}