{
  "type": "Feature",
  "properties": {
    "iso:country":"DE",
    "sg:address":"Dietrich-Bonhoeffer-Str. 5",
    "sg:city":"Berlin",
    "sg:phone":"+49 30/42161996",
    "sg:postcode":"10407",
    "sg:province":"Berlin",
    "wof:name":"B & B Fach\u00fcbersetzerges. Mbh",
    "wof:placetype":"venue"
},
  "geometry": {"coordinates":[13.433473,52.534611],"type":"Point"}
}