{
  "type": "Feature",
  "properties": {
    "iso:country":"DE",
    "sg:address":"Venloer Str. 133",
    "sg:city":"Pulheim",
    "sg:phone":"+49 2238/6189",
    "sg:postcode":"50259",
    "sg:province":"Nordrhein-Westfalen",
    "wof:name":"Apotheke Tittelbach Inh. Kurt Tittelbach",
    "wof:placetype":"venue"
},
  "geometry": {"coordinates":[6.799398,50.998772],"type":"Point"}
}