{
  "type": "Feature",
  "properties": {
    "iso:country":"DE",
    "sg:address":"G\u00e4nsberg12",
    "sg:city":"Elfershausen",
    "sg:postcode":"97725",
    "sg:province":"Bayern",
    "wof:name":"Rentenvorsorge",
    "wof:placetype":"venue"
},
  "geometry": {"coordinates":[9.96233,50.146175],"type":"Point"}
}