{
  "type": "Feature",
  "properties": {
    "iso:country":"DE",
    "sg:address":"Pielhof 1",
    "sg:city":"Altenthann",
    "sg:phone":"+49 9408/900",
    "sg:postcode":"93177",
    "sg:province":"Bayern",
    "wof:name":"Josef Obermeier",
    "wof:placetype":"venue"
},
  "geometry": {"coordinates":[12.291175,49.087605],"type":"Point"}
}