{
  "type": "Feature",
  "properties": {
    "iso:country":"DE",
    "sg:address":"Brauweiler Str. 23",
    "sg:city":"K\u00f6ln",
    "sg:phone":"+49 2234",
    "sg:postcode":"50859",
    "sg:province":"Nordrhein-Westfalen",
    "wof:name":"Direct Marketing J\u00fcrgen Sch\u00fcller",
    "wof:placetype":"venue"
},
  "geometry": {"coordinates":[6.8307,50.943893],"type":"Point"}
}