{
  "type": "Feature",
  "properties": {
    "iso:country":"DE",
    "sg:address":"Industriestr. 17",
    "sg:city":"Pfaffenhofen",
    "sg:phone":"+49 4970/4696130",
    "sg:postcode":"74397",
    "sg:province":"Baden-W\u00fcrttemberg",
    "wof:name":"Bico B. Biedermann & H. Conz Gmbh",
    "wof:placetype":"venue"
},
  "geometry": {"coordinates":[8.9752216339,49.0585975647],"type":"Point"}
}