{
  "type": "Feature",
  "properties": {
    "iso:country":"DE",
    "sg:address":"Industriestr. 32",
    "sg:city":"Fl\u00f6rsheim",
    "sg:phone":"+49 6145/30977",
    "sg:postcode":"65439",
    "sg:province":"Hessen",
    "wof:name":"Kilb Gesellschaft Mit Be- Schr\u00e4nkter Haftung -",
    "wof:placetype":"venue"
},
  "geometry": {"coordinates":[8.441687,50.039326],"type":"Point"}
}