{
  "type": "Feature",
  "properties": {
    "iso:country":"DE",
    "sg:address":"Ditmar-Koel-Str. 10",
    "sg:city":"Hamburg",
    "sg:postcode":"20459",
    "sg:province":"Hamburg",
    "wof:name":"Hafen-cafe Takhar Gmbh",
    "wof:placetype":"venue"
},
  "geometry": {"coordinates":[9.9761362076,53.5462112427],"type":"Point"}
}