{
  "type": "Feature",
  "properties": {
    "iso:country":"DE",
    "sg:address":"M\u00e4hringer Weg 6",
    "sg:city":"Ulm",
    "sg:phone":"+49 731/53516",
    "sg:postcode":"89075",
    "sg:province":"Baden-W\u00fcrttemberg",
    "wof:name":"Bruno Blender",
    "wof:placetype":"venue"
},
  "geometry": {"coordinates":[9.973887,48.406624],"type":"Point"}
}