{
  "type": "Feature",
  "properties": {
    "iso:country":"DE",
    "sg:address":"Schozachstr. 48",
    "sg:city":"Abstatt",
    "sg:phone":"+49 7062/62515",
    "sg:postcode":"74232",
    "sg:province":"Baden-W\u00fcrttemberg",
    "wof:name":"Siegfried Graupner",
    "wof:placetype":"venue"
},
  "geometry": {"coordinates":[9.2958812714,49.0670471191],"type":"Point"}
}