{
  "type": "Feature",
  "properties": {
    "iso:country":"DE",
    "sg:address":"K\u00f6lner Str. 64",
    "sg:city":"Remscheid",
    "sg:postcode":"42897",
    "sg:province":"Nordrhein-Westfalen",
    "wof:name":"Rs Krafttraining Gmbh",
    "wof:placetype":"venue"
},
  "geometry": {"coordinates":[7.2560191154,51.1887702942],"type":"Point"}
}