{
  "type": "Feature",
  "properties": {
    "iso:country":"DE",
    "sg:address":"Hirschgraben",
    "sg:city":"Schw\u00e4bisch Hall",
    "sg:phone":"+49 791/751447",
    "sg:postcode":"74523",
    "sg:province":"Baden-W\u00fcrttemberg",
    "wof:name":"Parkhaus",
    "wof:placetype":"venue"
},
  "geometry": {"coordinates":[9.7315196991,49.1111831665],"type":"Point"}
}