{
  "type": "Feature",
  "properties": {
    "iso:country":"DE",
    "sg:address":"Max-Planck-Str. 3",
    "sg:city":"Wennigsen",
    "sg:phone":"+49 5103/925420",
    "sg:postcode":"30974",
    "sg:province":"Niedersachsen",
    "wof:name":"J\u00fcrgen M\u00f6lck Gmbh",
    "wof:placetype":"venue"
},
  "geometry": {"coordinates":[9.580647,52.283066],"type":"Point"}
}