{
  "type": "Feature",
  "properties": {
    "iso:country":"DE",
    "sg:address":"Im Rehwinkel 2a",
    "sg:city":"Hannover",
    "sg:phone":"+49 511/517155",
    "sg:postcode":"30559",
    "sg:province":"Niedersachsen",
    "wof:name":"Wilhelm Aselmann Ingenieur",
    "wof:placetype":"venue"
},
  "geometry": {"coordinates":[9.8387346268,52.3614273071],"type":"Point"}
}