{
  "type": "Feature",
  "properties": {
    "iso:country":"DE",
    "sg:address":"Rieslingweg 3",
    "sg:city":"Stuttgart",
    "sg:phone":"+49 711/323804",
    "sg:postcode":"70329",
    "sg:province":"Baden-W\u00fcrttemberg",
    "wof:name":"H. Wei\u00df",
    "wof:placetype":"venue"
},
  "geometry": {"coordinates":[9.27837,48.778599],"type":"Point"}
}