{
  "type": "Feature",
  "properties": {
    "iso:country":"DE",
    "sg:address":"Flandernstr. 107",
    "sg:city":"Esslingen",
    "sg:phone":"+49 711/372011",
    "sg:postcode":"73732",
    "sg:province":"Baden-W\u00fcrttemberg",
    "wof:name":"Hochschule Esslingen Mensa",
    "wof:placetype":"venue"
},
  "geometry": {"coordinates":[9.324511528,48.743938446],"type":"Point"}
}