{
  "type": "Feature",
  "properties": {
    "iso:country":"DE",
    "sg:address":"B\u00f6ckenheckstr. 42c",
    "sg:city":"Datteln",
    "sg:phone":"+49 2363/62011",
    "sg:postcode":"45711",
    "sg:province":"Nordrhein-Westfalen",
    "wof:name":"Hildegard Gl\u00f6\u00df",
    "wof:placetype":"venue"
},
  "geometry": {"coordinates":[7.32423,51.63438],"type":"Point"}
}