{
  "type": "Feature",
  "properties": {
    "iso:country":"DE",
    "sg:address":"Bonner Str. 3",
    "sg:city":"Kelberg",
    "sg:phone":"+49 2692/383",
    "sg:postcode":"53539",
    "sg:province":"Rheinland-Pfalz",
    "wof:name":"Fleischerei Priwitzer Gmbh",
    "wof:placetype":"venue"
},
  "geometry": {"coordinates":[6.9184851646,50.2868614197],"type":"Point"}
}