{
  "type": "Feature",
  "properties": {
    "iso:country":"DE",
    "sg:address":"Isarleitenweg 4",
    "sg:city":"Bad T\u00f6lz",
    "sg:phone":"+49 8041/41052",
    "sg:postcode":"83646",
    "sg:province":"Bayern",
    "wof:name":"G\u00e4stehaus An Der Isarleiten",
    "wof:placetype":"venue"
},
  "geometry": {"coordinates":[11.5556373596,47.7586479187],"type":"Point"}
}