{
  "type": "Feature",
  "properties": {
    "iso:country":"DE",
    "sg:address":"Bergerstr. 13",
    "sg:city":"Solingen",
    "sg:phone":"+49 212/813065",
    "sg:postcode":"42657",
    "sg:province":"Nordrhein-Westfalen",
    "wof:name":"Ernst Pack & S\u00f6hne",
    "wof:placetype":"venue"
},
  "geometry": {"coordinates":[7.0625009537,51.1515197754],"type":"Point"}
}