{
  "type": "Feature",
  "properties": {
    "iso:country":"DE",
    "sg:address":"Lichstr. 11",
    "sg:city":"Leverkusen",
    "sg:phone":"+49 214/45494",
    "sg:postcode":"51373",
    "sg:province":"Nordrhein-Westfalen",
    "wof:name":"G. Paas Gmbh",
    "wof:placetype":"venue"
},
  "geometry": {"coordinates":[6.98715,51.029652],"type":"Point"}
}