{
  "type": "Feature",
  "properties": {
    "iso:country":"DE",
    "sg:address":"Marktplatz 6",
    "sg:city":"Rottenburg",
    "sg:phone":"+49 7472/3112",
    "sg:postcode":"72108",
    "sg:province":"Baden-W\u00fcrttemberg",
    "wof:name":"O. Joos",
    "wof:placetype":"venue"
},
  "geometry": {"coordinates":[8.933484,48.477112],"type":"Point"}
}