{
  "type": "Feature",
  "properties": {
    "iso:country":"DE",
    "sg:address":"Luttrumer Str. 8",
    "sg:city":"Holle",
    "sg:phone":"+49 5062/8656",
    "sg:postcode":"31188",
    "sg:province":"Niedersachsen",
    "wof:name":"K. Schenk Elektroinstallation",
    "wof:placetype":"venue"
},
  "geometry": {"coordinates":[10.185599,52.125572],"type":"Point"}
}