{
  "type": "Feature",
  "properties": {
    "iso:country":"DE",
    "sg:address":"Hauptstr. 72",
    "sg:city":"Elze",
    "sg:phone":"+49 5068/2324",
    "sg:postcode":"31008",
    "sg:province":"Niedersachsen",
    "wof:name":"Calenberger Hof",
    "wof:placetype":"venue"
},
  "geometry": {"coordinates":[9.7360858917,52.1209983826],"type":"Point"}
}