{
  "type": "Feature",
  "properties": {
    "iso:country":"DE",
    "sg:address":"Beethovenstr. 29",
    "sg:city":"Saarbr\u00fccken",
    "sg:phone":"+49 6898/82411",
    "sg:postcode":"66126",
    "sg:province":"Saarland",
    "wof:name":"Rita Blank",
    "wof:placetype":"venue"
},
  "geometry": {"coordinates":[6.9133501053,49.2503128052],"type":"Point"}
}