{
  "type": "Feature",
  "properties": {
    "iso:country":"DE",
    "sg:address":"Gro\u00dfe Dammstr. 42",
    "sg:city":"Wernigerode",
    "sg:phone":"+49 3943/22427",
    "sg:postcode":"38855",
    "sg:province":"Sachsen-Anhalt",
    "wof:name":"Hildegard Schulze",
    "wof:placetype":"venue"
},
  "geometry": {"coordinates":[10.800974,51.846081],"type":"Point"}
}