{
  "type": "Feature",
  "properties": {
    "iso:country":"DE",
    "sg:address":"Belmsdorfer Str. 26a",
    "sg:city":"Schm\u00f6lln",
    "sg:phone":"+49 3594/703622",
    "sg:postcode":"01877",
    "sg:province":"Sachsen",
    "wof:name":"C. Hanisch",
    "wof:placetype":"venue"
},
  "geometry": {"coordinates":[14.222803,51.119358],"type":"Point"}
}