{
  "type": "Feature",
  "properties": {
    "iso:country":"DE",
    "sg:address":"Landhausstr. 192",
    "sg:city":"Stuttgart",
    "sg:phone":"+49 711/2626755",
    "sg:postcode":"70188",
    "sg:province":"Baden-W\u00fcrttemberg",
    "wof:name":"Hallenbad Leo-vetter-bad",
    "wof:placetype":"venue"
},
  "geometry": {"coordinates":[9.2111406326,48.7848854065],"type":"Point"}
}