{
  "type": "Feature",
  "properties": {
    "iso:country":"DE",
    "sg:address":"Hauptstr. 26",
    "sg:city":"Alfstedt",
    "sg:phone":"+49 4765/485",
    "sg:postcode":"27432",
    "sg:province":"Niedersachsen",
    "wof:name":"Alwin Abert Ingenieur",
    "wof:placetype":"venue"
},
  "geometry": {"coordinates":[9.0694255829,53.5501785278],"type":"Point"}
}