{
  "type": "Feature",
  "properties": {
    "iso:country":"DE",
    "sg:address":"79639",
    "sg:city":"Grenzach-Wyhlen",
    "sg:phone":"+49 7624/5010",
    "sg:postcode":"79639",
    "sg:province":"Baden-W\u00fcrttemberg",
    "wof:name":"Deutsche Bahn Ag",
    "wof:placetype":"venue"
},
  "geometry": {"coordinates":[7.6789298058,47.5538711548],"type":"Point"}
}