{
  "type": "Feature",
  "properties": {
    "iso:country":"DE",
    "sg:address":"Zum Seeteufel 6",
    "sg:city":"Waging",
    "sg:phone":"+49 8681/373",
    "sg:postcode":"83329",
    "sg:province":"Bayern",
    "wof:name":"Mader Gmbh",
    "wof:placetype":"venue"
},
  "geometry": {"coordinates":[12.7413825989,47.9432525635],"type":"Point"}
}