{
  "type": "Feature",
  "properties": {
    "iso:country":"DE",
    "sg:address":"Bahnstr. 14",
    "sg:city":"Baesweiler",
    "sg:phone":"+49 2401/51208",
    "sg:postcode":"52499",
    "sg:province":"Nordrhein-Westfalen",
    "wof:name":"Parkrestaurant",
    "wof:placetype":"venue"
},
  "geometry": {"coordinates":[6.199570179,50.9231414795],"type":"Point"}
}