{
  "type": "Feature",
  "properties": {
    "iso:country":"DE",
    "sg:address":"Erlanger Str. 194",
    "sg:city":"F\u00fcrth",
    "sg:postcode":"90765",
    "sg:province":"Bayern",
    "wof:name":"Aldi Gmbh & Co. Kg",
    "wof:placetype":"venue"
},
  "geometry": {"coordinates":[10.9894542694,49.4931869507],"type":"Point"}
}