{
  "type": "Feature",
  "properties": {
    "iso:country":"DE",
    "sg:address":"Haus Gravener Str. 19",
    "sg:city":"Langenfeld",
    "sg:phone":"+49 2173/978931",
    "sg:postcode":"40764",
    "sg:province":"Nordrhein-Westfalen",
    "wof:name":"Gerhard Randandt",
    "wof:placetype":"venue"
},
  "geometry": {"coordinates":[6.9486131668,51.1315689087],"type":"Point"}
}