{
  "type": "Feature",
  "properties": {
    "iso:country":"DE",
    "sg:address":"Magdeburgstr. 5",
    "sg:city":"Idstein",
    "sg:phone":"+49 6126/3328",
    "sg:postcode":"65510",
    "sg:province":"Hessen",
    "wof:name":"Schlosserei Und Installation Erich Best",
    "wof:placetype":"venue"
},
  "geometry": {"coordinates":[8.265619278,50.2228889465],"type":"Point"}
}