{
  "type": "Feature",
  "properties": {
    "iso:country":"DE",
    "sg:address":"Goebenstr. 19",
    "sg:city":"Hannover",
    "sg:phone":"+49 511/392736",
    "sg:postcode":"30163",
    "sg:province":"Niedersachsen",
    "wof:name":"Klaus Hamelberg",
    "wof:placetype":"venue"
},
  "geometry": {"coordinates":[9.7431020737,52.3930168152],"type":"Point"}
}