{
  "type": "Feature",
  "properties": {
    "iso:country":"DE",
    "sg:address":"Reicker Str. 51",
    "sg:city":"Dresden",
    "sg:phone":"+49 351/4411129",
    "sg:postcode":"01219",
    "sg:province":"Sachsen",
    "wof:name":"Bek Consulting Gmbh",
    "wof:placetype":"venue"
},
  "geometry": {"coordinates":[13.7767820358,51.0215301514],"type":"Point"}
}