{
  "type": "Feature",
  "properties": {
    "iso:country":"DE",
    "sg:address":"Kirchenweg 23 a",
    "sg:city":"Stadtbergen",
    "sg:phone":"+49 821/2431056",
    "sg:postcode":"86391",
    "sg:province":"Bayern",
    "wof:name":"Jutta Cram - Redaktion Und Textgestaltung",
    "wof:placetype":"venue"
},
  "geometry": {"coordinates":[10.8398666382,48.3636512756],"type":"Point"}
}