{
  "type": "Feature",
  "properties": {
    "iso:country":"DE",
    "sg:address":"Lobensteiner Str. 2",
    "sg:city":"Hirschberg",
    "sg:phone":"+49 36644/22204",
    "sg:postcode":"07927",
    "sg:province":"Th\u00fcringen",
    "wof:name":"R. Rockt\u00e4schel Und M. Gei\u00dfler Masseure",
    "wof:placetype":"venue"
},
  "geometry": {"coordinates":[11.815562,50.404873],"type":"Point"}
}