{
  "type": "Feature",
  "properties": {
    "iso:country":"DE",
    "sg:address":"Zum Gro\u00dfen Freien 20",
    "sg:city":"Lehrte",
    "sg:phone":"+49 5132/86940",
    "sg:postcode":"31275",
    "sg:province":"Niedersachsen",
    "wof:name":"Ulrich & Partner Wirtschaftsberatung-",
    "wof:placetype":"venue"
},
  "geometry": {"coordinates":[9.9080696106,52.3769187927],"type":"Point"}
}