{
  "type": "Feature",
  "properties": {
    "iso:country":"DE",
    "sg:address":"Im Keitelsberg 33",
    "sg:city":"Trierweiler",
    "sg:phone":"+49 651/827370",
    "sg:postcode":"54311",
    "sg:province":"Rheinland-Pfalz",
    "wof:name":"Tvs Tabakwaren Handels- Gesellschaft Mbh & Co. Kg",
    "wof:placetype":"venue"
},
  "geometry": {"coordinates":[6.5881462097,49.7719535828],"type":"Point"}
}