{
  "type": "Feature",
  "properties": {
    "iso:country":"DE",
    "sg:address":"Truderinger Str 306",
    "sg:city":"M\u00fcnchen",
    "sg:phone":"+49 89/424402",
    "sg:postcode":"81825",
    "sg:province":"Bayern",
    "wof:name":"Pietzsch & Wimmer",
    "wof:placetype":"venue"
},
  "geometry": {"coordinates":[11.669672,48.121941],"type":"Point"}
}