{
  "type": "Feature",
  "properties": {
    "iso:country":"DE",
    "sg:address":"Vierradener Str. 42",
    "sg:city":"Schwedt",
    "sg:postcode":"16303",
    "sg:province":"Brandenburg",
    "wof:name":"M. R\u00e4hse",
    "wof:placetype":"venue"
},
  "geometry": {"coordinates":[14.285601,53.057667],"type":"Point"}
}