{
  "type": "Feature",
  "properties": {
    "iso:country":"DE",
    "sg:address":"Am R\u00f6merbrunnen 9 a",
    "sg:city":"Frankfurt",
    "sg:postcode":"60437",
    "sg:province":"Hessen",
    "wof:name":"Best Part Verm\u00f6gens Gmbh",
    "wof:placetype":"venue"
},
  "geometry": {"coordinates":[8.7006225586,50.1864471436],"type":"Point"}
}