{
  "type": "Feature",
  "properties": {
    "iso:country":"DE",
    "sg:address":"Am Sweenhof",
    "sg:city":"Seesen",
    "sg:phone":"+49 5381/6663",
    "sg:postcode":"38723",
    "sg:province":"Niedersachsen",
    "wof:name":"Freibad M\u00fcnchehof",
    "wof:placetype":"venue"
},
  "geometry": {"coordinates":[10.1877145767,51.850479126],"type":"Point"}
}