{
  "type": "Feature",
  "properties": {
    "iso:country":"DE",
    "sg:address":"Bergstr 29",
    "sg:city":"Morsbach",
    "sg:phone":"+49 2294/6970",
    "sg:postcode":"51597",
    "sg:province":"Nordrhein-Westfalen",
    "wof:name":"Ibs Brocke Gmbh & Co Kg",
    "wof:placetype":"venue"
},
  "geometry": {"coordinates":[7.7080168724,50.9016227722],"type":"Point"}
}