{
  "type": "Feature",
  "properties": {
    "iso:country":"DE",
    "sg:address":"Bahnhofstr. 14",
    "sg:city":"Vohenstrau\u00df",
    "sg:phone":"+49 9651/2229",
    "sg:postcode":"92648",
    "sg:province":"Bayern",
    "wof:name":"Pension Zur Post",
    "wof:placetype":"venue"
},
  "geometry": {"coordinates":[12.3403320312,49.6258811951],"type":"Point"}
}