{
  "type": "Feature",
  "properties": {
    "iso:country":"DE",
    "sg:address":"Schindelbergstr. 6",
    "sg:city":"\u00d6stringen",
    "sg:phone":"+49 7259/8292",
    "sg:postcode":"76684",
    "sg:province":"Baden-W\u00fcrttemberg",
    "wof:name":"Freibad Odenheim",
    "wof:placetype":"venue"
},
  "geometry": {"coordinates":[8.7137041092,49.2203788757],"type":"Point"}
}