{
  "type": "Feature",
  "properties": {
    "iso:country":"DE",
    "sg:address":"Clara-Zetkin-Str. 18",
    "sg:city":"Demmin",
    "sg:phone":"+49 3998/431675",
    "sg:postcode":"17109",
    "sg:province":"Mecklenburg-Vorpommern",
    "wof:name":"Anke Wagemann Praxis F\u00fcr Physiotherapie",
    "wof:placetype":"venue"
},
  "geometry": {"coordinates":[13.045527,53.905788],"type":"Point"}
}