{
  "type": "Feature",
  "properties": {
    "iso:country":"DE",
    "sg:address":"Rheinberger Str. 262",
    "sg:city":"Moers",
    "sg:phone":"+49 2841/41938",
    "sg:postcode":"47445",
    "sg:province":"Nordrhein-Westfalen",
    "wof:name":"E. W\u00fcllenweber",
    "wof:placetype":"venue"
},
  "geometry": {"coordinates":[6.632445,51.481815],"type":"Point"}
}