{
  "type": "Feature",
  "properties": {
    "iso:country":"DE",
    "sg:address":"Im Neuen Felde 16",
    "sg:city":"Ottersberg",
    "sg:phone":"+49 4293/7522",
    "sg:postcode":"28870",
    "sg:province":"Niedersachsen",
    "wof:name":"Wulf Gr\u00fctzner Architekt",
    "wof:placetype":"venue"
},
  "geometry": {"coordinates":[9.041498,53.118546],"type":"Point"}
}