{
  "type": "Feature",
  "properties": {
    "iso:country":"DE",
    "sg:address":"Lahnstr. 20",
    "sg:city":"Netphen",
    "sg:phone":"+49 2738/8806",
    "sg:postcode":"57250",
    "sg:province":"Nordrhein-Westfalen",
    "wof:name":"S. Bender",
    "wof:placetype":"venue"
},
  "geometry": {"coordinates":[8.1006326675,50.9132881165],"type":"Point"}
}