{
  "type": "Feature",
  "properties": {
    "iso:country":"DE",
    "sg:address":"Im Unterdorf 3",
    "sg:city":"Wirschweiler",
    "sg:phone":"+49 6786/2548",
    "sg:postcode":"55758",
    "sg:province":"Rheinland-Pfalz",
    "wof:name":"Lothar Weis",
    "wof:placetype":"venue"
},
  "geometry": {"coordinates":[7.1714868546,49.7604942322],"type":"Point"}
}