{
  "type": "Feature",
  "properties": {
    "iso:country":"DE",
    "sg:address":"Zur H\u00f6he 16",
    "sg:city":"Hardegsen",
    "sg:phone":"+49 5555/498",
    "sg:postcode":"37181",
    "sg:province":"Niedersachsen",
    "wof:name":"E.-g. Holst",
    "wof:placetype":"venue"
},
  "geometry": {"coordinates":[9.7819833755,51.7011528015],"type":"Point"}
}