{
  "type": "Feature",
  "properties": {
    "iso:country":"DE",
    "sg:address":"Baruther Str. 40",
    "sg:city":"Luckenwalde",
    "sg:phone":"+49 3371/632090",
    "sg:postcode":"14943",
    "sg:province":"Brandenburg",
    "wof:name":"Helga Szlak",
    "wof:placetype":"venue"
},
  "geometry": {"coordinates":[13.176884,52.088661],"type":"Point"}
}