{
  "type": "Feature",
  "properties": {
    "iso:country":"DE",
    "sg:address":"Zollstr. 13",
    "sg:city":"Wittenberge",
    "sg:phone":"+49 3877/403708",
    "sg:postcode":"19322",
    "sg:province":"Brandenburg",
    "wof:name":"D. Lemm",
    "wof:placetype":"venue"
},
  "geometry": {"coordinates":[11.753282547,52.991809845],"type":"Point"}
}