{
  "type": "Feature",
  "properties": {
    "iso:country":"DE",
    "sg:address":"Duisburger Str. 1",
    "sg:city":"D\u00fcsseldorf",
    "sg:postcode":"40477",
    "sg:province":"Nordrhein-Westfalen",
    "wof:name":"Markus Mundrys Handyhaus E. K.",
    "wof:placetype":"venue"
},
  "geometry": {"coordinates":[6.7793068886,51.2370223999],"type":"Point"}
}