{
  "type": "Feature",
  "properties": {
    "iso:country":"DE",
    "sg:address":"\u00c4hrenweg 3a",
    "sg:city":"Neufahrn",
    "sg:phone":"+49 8165/7111",
    "sg:postcode":"85375",
    "sg:province":"Bayern",
    "wof:name":"M. & S. Immobilien",
    "wof:placetype":"venue"
},
  "geometry": {"coordinates":[11.6604290009,48.3110923767],"type":"Point"}
}