{
  "type": "Feature",
  "properties": {
    "iso:country":"DE",
    "sg:address":"St.-Martinus-Str. 8",
    "sg:city":"Erkelenz",
    "sg:phone":"+49 2164/47959",
    "sg:postcode":"41812",
    "sg:province":"Nordrhein-Westfalen",
    "wof:name":"Josef Beeck",
    "wof:placetype":"venue"
},
  "geometry": {"coordinates":[6.433444,51.079815],"type":"Point"}
}