{
  "type": "Feature",
  "properties": {
    "iso:country":"DE",
    "sg:address":"Kaiserstr. 1 - 9",
    "sg:city":"N\u00fcrnberg",
    "sg:phone":"+49 911/224684",
    "sg:postcode":"90403",
    "sg:province":"Bayern",
    "wof:name":"C. M\u00fcller S 18 Gmbh",
    "wof:placetype":"venue"
},
  "geometry": {"coordinates":[11.077512,49.452187],"type":"Point"}
}