{
  "type": "Feature",
  "properties": {
    "iso:country":"DE",
    "sg:address":"Hohenzollernweg 4",
    "sg:city":"Burladingen",
    "sg:phone":"+49 4956/9189750",
    "sg:postcode":"72393",
    "sg:province":"Baden-W\u00fcrttemberg",
    "wof:name":"Karl Illas Gmbh",
    "wof:placetype":"venue"
},
  "geometry": {"coordinates":[9.001646,51.381233],"type":"Point"}
}