{
  "type": "Feature",
  "properties": {
    "iso:country":"DE",
    "sg:address":"Hauptstr. 10",
    "sg:city":"Dietfurt",
    "sg:phone":"+49 8464/8300",
    "sg:postcode":"92345",
    "sg:province":"Bayern",
    "wof:name":"G. Linz",
    "wof:placetype":"venue"
},
  "geometry": {"coordinates":[11.5863256454,49.0353279114],"type":"Point"}
}