{
  "type": "Feature",
  "properties": {
    "iso:country":"DE",
    "sg:address":"Farbm\u00fchle 4",
    "sg:city":"Wuppertal",
    "sg:phone":"+49 202/83218",
    "sg:postcode":"42285",
    "sg:province":"Nordrhein-Westfalen",
    "wof:name":"Piercing/tattoo-studio House Of Pain",
    "wof:placetype":"venue"
},
  "geometry": {"coordinates":[7.179824,51.264069],"type":"Point"}
}