{
  "type": "Feature",
  "properties": {
    "iso:country":"DE",
    "sg:address":"Brusendorferstra\u00dfe 2",
    "sg:city":"Berlin",
    "sg:phone":"+49 4930/8616725",
    "sg:postcode":"12055",
    "sg:province":"Berlin",
    "wof:name":"It-global-networx .. Projektserver",
    "wof:placetype":"venue"
},
  "geometry": {"coordinates":[13.452456,52.474236],"type":"Point"}
}