{
  "type": "Feature",
  "properties": {
    "iso:country":"DE",
    "sg:address":"M\u00fchlenstr. 39",
    "sg:city":"Br\u00fchl",
    "sg:phone":"+49 2232/13210",
    "sg:postcode":"50321",
    "sg:province":"Nordrhein-Westfalen",
    "wof:name":"H. M. Opitz",
    "wof:placetype":"venue"
},
  "geometry": {"coordinates":[6.901819,50.828381],"type":"Point"}
}