{
  "type": "Feature",
  "properties": {
    "iso:country":"DE",
    "sg:address":"Simsonstr. 9",
    "sg:city":"Leipzig",
    "sg:phone":"+49 341/2132584",
    "sg:postcode":"04107",
    "sg:province":"Sachsen",
    "wof:name":"Eveline Franke",
    "wof:placetype":"venue"
},
  "geometry": {"coordinates":[12.3690767288,51.3299102783],"type":"Point"}
}