{
  "type": "Feature",
  "properties": {
    "iso:country":"DE",
    "sg:address":"Adenauerallee 11d",
    "sg:city":"Bonn",
    "sg:phone":"+49 228/225641",
    "sg:postcode":"53111",
    "sg:province":"Nordrhein-Westfalen",
    "wof:name":"Md Data Research Gesellschaft F\u00fcr Informations-",
    "wof:placetype":"venue"
},
  "geometry": {"coordinates":[7.107703,50.733471],"type":"Point"}
}