{
  "type": "Feature",
  "properties": {
    "iso:country":"DE",
    "sg:address":"Gerhard-von-Are-Str. 4",
    "sg:city":"Bonn",
    "sg:phone":"+49 228/650731",
    "sg:postcode":"53111",
    "sg:province":"Nordrhein-Westfalen",
    "wof:name":"Balkan Gastst\u00e4ttenbetriebe Gmbh",
    "wof:placetype":"venue"
},
  "geometry": {"coordinates":[7.0993800163,50.732837677],"type":"Point"}
}