{
  "type": "Feature",
  "properties": {
    "iso:country":"DE",
    "sg:address":"Bruderm\u00fchlstr. 48",
    "sg:city":"M\u00fcnchen",
    "sg:phone":"+49 89/1235255",
    "sg:postcode":"81371",
    "sg:province":"Bayern",
    "wof:name":"Ursus-immobilien Gesellschaft F\u00fcr Grundst\u00fcck",
    "wof:placetype":"venue"
},
  "geometry": {"coordinates":[11.544836998,48.1119804382],"type":"Point"}
}