{
  "type": "Feature",
  "properties": {
    "iso:country":"DE",
    "sg:address":"Stephanstr. 32-34",
    "sg:city":"Lingen",
    "sg:phone":"+49 591/71020",
    "sg:postcode":"49809",
    "sg:province":"Niedersachsen",
    "wof:name":"Kopp & Partner Gmbh",
    "wof:placetype":"venue"
},
  "geometry": {"coordinates":[7.337068,52.521786],"type":"Point"}
}