{
  "type": "Feature",
  "properties": {
    "iso:country":"DE",
    "sg:address":"Bussardstr. 22",
    "sg:city":"F\u00fcrth",
    "sg:phone":"+49 911/7360307",
    "sg:postcode":"90766",
    "sg:province":"Bayern",
    "wof:name":"Friedrich M. Wolf",
    "wof:placetype":"venue"
},
  "geometry": {"coordinates":[10.96118,49.489689],"type":"Point"}
}