{
  "type": "Feature",
  "properties": {
    "iso:country":"DE",
    "sg:address":"Hans-B\u00f6ckler-Stra\u00dfe 2-6",
    "sg:city":"Witten",
    "sg:phone":"+49 2302/580800",
    "sg:postcode":"58455",
    "sg:province":"Nordrhein-Westfalen",
    "wof:name":"W\u00fclbeck Das Kompetente B\u00fcrocentrum",
    "wof:placetype":"venue"
},
  "geometry": {"coordinates":[7.346672,51.448864],"type":"Point"}
}