{
  "type": "Feature",
  "properties": {
    "iso:country":"DE",
    "sg:address":"Im B\u00e4rengarten 9",
    "sg:city":"Frankfurt",
    "sg:phone":"+49 69/652662",
    "sg:postcode":"60599",
    "sg:province":"Hessen",
    "wof:name":"Heinrich Fischer",
    "wof:placetype":"venue"
},
  "geometry": {"coordinates":[8.712768,50.103821],"type":"Point"}
}