{
  "type": "Feature",
  "properties": {
    "iso:country":"DE",
    "sg:address":"Preu\u00dfenstr. 158",
    "sg:city":"Neuss",
    "sg:phone":"+49 2131/222293",
    "sg:postcode":"41464",
    "sg:province":"Nordrhein-Westfalen",
    "wof:name":"Plus-punkt Immobilien Gmbh",
    "wof:placetype":"venue"
},
  "geometry": {"coordinates":[6.668217,51.189064],"type":"Point"}
}