{
  "type": "Feature",
  "properties": {
    "iso:country":"DE",
    "sg:address":"Gerberstr. 50",
    "sg:city":"Villingen-Schwenningen",
    "sg:phone":"+49 7721/25221",
    "sg:postcode":"78050",
    "sg:province":"Baden-W\u00fcrttemberg",
    "wof:name":"Gerhard Paul",
    "wof:placetype":"venue"
},
  "geometry": {"coordinates":[8.4617080688,48.0574798584],"type":"Point"}
}