{
  "type": "Feature",
  "properties": {
    "iso:country":"DE",
    "sg:address":"Finkenhof 12a",
    "sg:city":"Essen",
    "sg:phone":"+49 201/435550",
    "sg:postcode":"45134",
    "sg:province":"Nordrhein-Westfalen",
    "wof:name":"Busse Borchert & Partner Gmbh",
    "wof:placetype":"venue"
},
  "geometry": {"coordinates":[7.027490139,51.4156494141],"type":"Point"}
}