{
  "type": "Feature",
  "properties": {
    "iso:country":"DE",
    "sg:address":"Dorfstr. 24",
    "sg:city":"Hohensaaten",
    "sg:phone":"+49 33368/214",
    "sg:postcode":"16248",
    "sg:province":"Brandenburg",
    "wof:name":"C. Dornfeldt",
    "wof:placetype":"venue"
},
  "geometry": {"coordinates":[14.1430149078,52.87292099],"type":"Point"}
}