{
  "type": "Feature",
  "properties": {
    "iso:country":"DE",
    "sg:address":"Schie\u00dfgartenstr. 14",
    "sg:city":"M\u00fcnster",
    "sg:phone":"+49 6071/31163",
    "sg:postcode":"64839",
    "sg:province":"Hessen",
    "wof:name":"Nikolaus Ulrich & S\u00f6hne Lederwarenfabrikation Ohg",
    "wof:placetype":"venue"
},
  "geometry": {"coordinates":[8.86135,49.925709],"type":"Point"}
}