{
  "type": "Feature",
  "properties": {
    "iso:country":"DE",
    "sg:address":"Langgasse 14",
    "sg:city":"Westerburg",
    "sg:phone":"+49 2663/4580",
    "sg:postcode":"56457",
    "sg:province":"Rheinland-Pfalz",
    "wof:name":"Gastst\u00e4tte D. Otte",
    "wof:placetype":"venue"
},
  "geometry": {"coordinates":[7.9754128456,50.5648727417],"type":"Point"}
}