{
  "type": "Feature",
  "properties": {
    "iso:country":"DE",
    "sg:address":"Im Strickmann 210::",
    "sg:city":"Gottmadingen",
    "sg:postcode":"78244",
    "sg:province":"Baden-W\u00fcrttemberg",
    "wof:name":"Infigate Gmbh",
    "wof:placetype":"venue"
},
  "geometry": {"coordinates":[7.010615,51.451809],"type":"Point"}
}