{
  "type": "Feature",
  "properties": {
    "iso:country":"DE",
    "sg:address":"Cathostr. 7",
    "sg:city":"Essen",
    "sg:phone":"+49 201/673048",
    "sg:postcode":"45356",
    "sg:province":"Nordrhein-Westfalen",
    "wof:name":"David Personalverleih Gmbh",
    "wof:placetype":"venue"
},
  "geometry": {"coordinates":[6.9682297707,51.4839897156],"type":"Point"}
}