{
  "type": "Feature",
  "properties": {
    "iso:country":"DE",
    "sg:address":"Schwarzwaldstr. 80",
    "sg:city":"Freiburg",
    "sg:phone":"+49 761/70370",
    "sg:postcode":"79102",
    "sg:province":"Baden-W\u00fcrttemberg",
    "wof:name":"Messe Freiburg Verwaltungs Gmbh",
    "wof:placetype":"venue"
},
  "geometry": {"coordinates":[7.8727149963,47.9878387451],"type":"Point"}
}