{
  "type": "Feature",
  "properties": {
    "iso:country":"DE",
    "sg:address":"Quagliostr. 6",
    "sg:city":"M\u00fcnchen",
    "sg:phone":"+49 89/659935",
    "sg:postcode":"81543",
    "sg:province":"Bayern",
    "wof:name":"Aikido Dojo M\u00fcnchen",
    "wof:placetype":"venue"
},
  "geometry": {"coordinates":[11.5608911514,48.1051902771],"type":"Point"}
}