{
  "type": "Feature",
  "properties": {
    "iso:country":"DE",
    "sg:address":"Krankenh\u00e4ger Str. 28",
    "sg:city":"Rinteln",
    "sg:phone":"+49 5751/41424",
    "sg:postcode":"31737",
    "sg:province":"Niedersachsen",
    "wof:name":"Post-apotheke",
    "wof:placetype":"venue"
},
  "geometry": {"coordinates":[9.078922,52.18438],"type":"Point"}
}