{
  "type": "Feature",
  "properties": {
    "iso:country":"DE",
    "sg:address":"Brunnengasse 3",
    "sg:city":"Ober-Hilbersheim",
    "sg:phone":"+49 6728/752",
    "sg:postcode":"55437",
    "sg:province":"Rheinland-Pfalz",
    "wof:name":"H. Schmuck",
    "wof:placetype":"venue"
},
  "geometry": {"coordinates":[8.0305995941,49.8994522095],"type":"Point"}
}