{
  "type": "Feature",
  "properties": {
    "iso:country":"DE",
    "sg:address":"Fredeburger Str. 1",
    "sg:city":"Bielefeld",
    "sg:phone":"+49 521/201040",
    "sg:postcode":"33699",
    "sg:province":"Nordrhein-Westfalen",
    "wof:name":"W. Siekmann Inh. Horst Niemann",
    "wof:placetype":"venue"
},
  "geometry": {"coordinates":[8.6043043137,51.9913215637],"type":"Point"}
}