{
  "type": "Feature",
  "properties": {
    "iso:country":"DE",
    "sg:address":"Bernadottestr. 15",
    "sg:city":"N\u00fcrnberg",
    "sg:phone":"+49 911/610157",
    "sg:postcode":"90439",
    "sg:province":"Bayern",
    "wof:name":"Ek - Elektronik E. K.",
    "wof:placetype":"venue"
},
  "geometry": {"coordinates":[11.038295,49.44286],"type":"Point"}
}