{
  "type": "Feature",
  "properties": {
    "iso:country":"DE",
    "sg:address":"Neusser Str. 64",
    "sg:city":"Kaarst",
    "sg:phone":"+49 2131/604262",
    "sg:postcode":"41564",
    "sg:province":"Nordrhein-Westfalen",
    "wof:name":"Schlemmer-grill",
    "wof:placetype":"venue"
},
  "geometry": {"coordinates":[6.6327848434,51.2310333252],"type":"Point"}
}