{
  "type": "Feature",
  "properties": {
    "iso:country":"DE",
    "sg:address":"Zur sch\u00f6nen Aussicht 3",
    "sg:city":"Vettelscho\u00df",
    "sg:phone":"+49 2645/99347",
    "sg:postcode":"53560",
    "sg:province":"Rheinland-Pfalz",
    "wof:name":"Jb-elektrotechnik",
    "wof:placetype":"venue"
},
  "geometry": {"coordinates":[7.349074,50.616962],"type":"Point"}
}