{
  "type": "Feature",
  "properties": {
    "iso:country":"DE",
    "sg:address":"Abendstr. 5 a",
    "sg:city":"Magdeburg",
    "sg:phone":"+49 391/2514721",
    "sg:postcode":"39124",
    "sg:province":"Sachsen-Anhalt",
    "wof:name":"Sch\u00fcrmann",
    "wof:placetype":"venue"
},
  "geometry": {"coordinates":[11.633172,52.15498],"type":"Point"}
}