{
  "type": "Feature",
  "properties": {
    "iso:country":"DE",
    "sg:address":"Hauptstr. 46",
    "sg:city":"Albisheim",
    "sg:phone":"+49 6355/3203",
    "sg:postcode":"67308",
    "sg:province":"Rheinland-Pfalz",
    "wof:name":"Steffen Prohaska Anlageberater",
    "wof:placetype":"venue"
},
  "geometry": {"coordinates":[8.0948486328,49.6494445801],"type":"Point"}
}