{
  "type": "Feature",
  "properties": {
    "iso:country":"DE",
    "sg:address":"Winterbergstr. 20",
    "sg:city":"Olpe",
    "sg:phone":"+49 2761/2153",
    "sg:postcode":"57462",
    "sg:province":"Nordrhein-Westfalen",
    "wof:name":"Alexander Siveri",
    "wof:placetype":"venue"
},
  "geometry": {"coordinates":[7.844463,51.030491],"type":"Point"}
}