{
  "type": "Feature",
  "properties": {
    "iso:country":"DE",
    "sg:address":"Hauptstr. 34",
    "sg:city":"S\u00f6hlde",
    "sg:phone":"+49 5129/521",
    "sg:postcode":"31185",
    "sg:province":"Niedersachsen",
    "wof:name":"Karl H. Himstedt",
    "wof:placetype":"venue"
},
  "geometry": {"coordinates":[10.181789,52.208561],"type":"Point"}
}