{
  "type": "Feature",
  "properties": {
    "iso:country":"DE",
    "sg:address":"Hanauer Landstr. 11",
    "sg:city":"Rodenbach",
    "sg:phone":"+49 6184/50576",
    "sg:postcode":"63517",
    "sg:province":"Hessen",
    "wof:name":"Klaus Weisl",
    "wof:placetype":"venue"
},
  "geometry": {"coordinates":[9.0593385696,50.1375656128],"type":"Point"}
}