{
  "type": "Feature",
  "properties": {
    "iso:country":"DE",
    "sg:address":"Mittelwegring 12",
    "sg:city":"Jockgrim",
    "sg:phone":"+49 7271/950076",
    "sg:postcode":"76751",
    "sg:province":"Rheinland-Pfalz",
    "wof:name":"K\u00f6rber & Sieber Gmbh",
    "wof:placetype":"venue"
},
  "geometry": {"coordinates":[8.2640800476,49.0814590454],"type":"Point"}
}