{
  "type": "Feature",
  "properties": {
    "iso:country":"DE",
    "sg:address":"Hauptstr. 24",
    "sg:city":"Untersteinach",
    "sg:phone":"+49 9225/1353",
    "sg:postcode":"95369",
    "sg:province":"Bayern",
    "wof:name":"Frankenkeller",
    "wof:placetype":"venue"
},
  "geometry": {"coordinates":[11.5295238495,50.1321868896],"type":"Point"}
}