{
  "type": "Feature",
  "properties": {
    "iso:country":"DE",
    "sg:address":"Bahnhofstr. 10",
    "sg:city":"Leutkirch",
    "sg:postcode":"88299",
    "sg:province":"Baden-W\u00fcrttemberg",
    "wof:name":"Leuba-immobilien Verwaltungs-gmbh",
    "wof:placetype":"venue"
},
  "geometry": {"coordinates":[10.019579,47.826515],"type":"Point"}
}