{
  "type": "Feature",
  "properties": {
    "iso:country":"DE",
    "sg:address":"Berliner Str. 33",
    "sg:city":"Berlin",
    "sg:phone":"+49 30",
    "sg:postcode":"13089",
    "sg:province":"Berlin",
    "wof:name":"Karree Automobile",
    "wof:placetype":"venue"
},
  "geometry": {"coordinates":[13.4334611893,52.5598144531],"type":"Point"}
}