{
  "type": "Feature",
  "properties": {
    "iso:country":"DE",
    "sg:address":"Am Hofgarten 5",
    "sg:city":"Bonn",
    "sg:phone":"+49 228/221095",
    "sg:postcode":"53113",
    "sg:province":"Nordrhein-Westfalen",
    "wof:name":"H. Meyer Rechtsanwalt",
    "wof:placetype":"venue"
},
  "geometry": {"coordinates":[7.1036667824,50.7314147949],"type":"Point"}
}