{
  "type": "Feature",
  "properties": {
    "iso:country":"DE",
    "sg:address":"Am Brommerfeld 5",
    "sg:city":"Detmold",
    "sg:phone":"+49 5231/640155",
    "sg:postcode":"32758",
    "sg:province":"Nordrhein-Westfalen",
    "wof:name":"M\u00fcller Enkosa Gmbh",
    "wof:placetype":"venue"
},
  "geometry": {"coordinates":[8.8574609756,51.9499397278],"type":"Point"}
}