{
  "type": "Feature",
  "properties": {
    "iso:country":"DE",
    "sg:address":"Asperger Str 60",
    "sg:city":"Stuttgart",
    "sg:phone":"+49 711/80200",
    "sg:postcode":"70439",
    "sg:province":"Baden-W\u00fcrttemberg",
    "wof:name":"Jva Stuttgart-vaw",
    "wof:placetype":"venue"
},
  "geometry": {"coordinates":[9.155183,48.853329],"type":"Point"}
}