{
  "type": "Feature",
  "properties": {
    "iso:country":"DE",
    "sg:address":"Heinrich Goebel Strasse 4",
    "sg:city":"Grevenbroich",
    "sg:phone":"+49 2181/226540",
    "sg:postcode":"41515",
    "sg:province":"Nordrhein-Westfalen",
    "wof:name":"Ihw-huintjes Gmbh & Co Kg",
    "wof:placetype":"venue"
},
  "geometry": {"coordinates":[6.618745,51.089642],"type":"Point"}
}