{
  "type": "Feature",
  "properties": {
    "iso:country":"DE",
    "sg:address":"Walther-Rathenau-Str. 11",
    "sg:city":"Falkenberg",
    "sg:postcode":"04895",
    "sg:province":"Brandenburg",
    "wof:name":"Mode Live",
    "wof:placetype":"venue"
},
  "geometry": {"coordinates":[13.243448,51.585747],"type":"Point"}
}