{
  "type": "Feature",
  "properties": {
    "iso:country":"DE",
    "sg:address":"Unter den Linden 1",
    "sg:city":"Duderstadt",
    "sg:phone":"+49 5527/6677",
    "sg:postcode":"37115",
    "sg:province":"Niedersachsen",
    "wof:name":"Arbeitsgemeinschaft Nessel- R\u00f6der Vereine Und Verb\u00e4nde",
    "wof:placetype":"venue"
},
  "geometry": {"coordinates":[10.1805028915,51.4914512634],"type":"Point"}
}