{
  "type": "Feature",
  "properties": {
    "iso:country":"DE",
    "sg:address":"Am Graben 9",
    "sg:city":"Lauterbach",
    "sg:phone":"+49 6641/2448",
    "sg:postcode":"36341",
    "sg:province":"Hessen",
    "wof:name":"A. Otterbein Kg",
    "wof:placetype":"venue"
},
  "geometry": {"coordinates":[9.3972902298,50.6364784241],"type":"Point"}
}