{
  "type": "Feature",
  "properties": {
    "iso:country":"DE",
    "sg:address":"Naturbadstr. 79",
    "sg:city":"Erlangen",
    "sg:phone":"+49 9135/1240",
    "sg:postcode":"91056",
    "sg:province":"Bayern",
    "wof:name":"Ristorante-pizzeria Valentino",
    "wof:placetype":"venue"
},
  "geometry": {"coordinates":[10.9543895721,49.6280784607],"type":"Point"}
}