{
  "type": "Feature",
  "properties": {
    "iso:country":"DE",
    "sg:address":"Lessingstr. 24 a",
    "sg:city":"Greven",
    "sg:phone":"+49 2571/55008",
    "sg:postcode":"48268",
    "sg:province":"Nordrhein-Westfalen",
    "wof:name":"Richard Sch\u00fcrmann Garten- Und Landschafts-",
    "wof:placetype":"venue"
},
  "geometry": {"coordinates":[7.58503,52.098717],"type":"Point"}
}