{
  "type": "Feature",
  "properties": {
    "iso:country":"DE",
    "sg:address":"Mittelstr. 13",
    "sg:city":"Lengerich",
    "sg:phone":"+49 5904/92020",
    "sg:postcode":"49838",
    "sg:province":"Niedersachsen",
    "wof:name":"Hirsch-apotheke",
    "wof:placetype":"venue"
},
  "geometry": {"coordinates":[7.53086,52.552269],"type":"Point"}
}