{
  "type": "Feature",
  "properties": {
    "iso:country":"DE",
    "sg:address":"Charlottenstr. 16",
    "sg:city":"Berlin",
    "sg:postcode":"10117",
    "sg:province":"Berlin",
    "wof:name":"Central & Eastern Europe Venture Gmbh",
    "wof:placetype":"venue"
},
  "geometry": {"coordinates":[13.39245,52.508167],"type":"Point"}
}