{
  "type": "Feature",
  "properties": {
    "iso:country":"DE",
    "sg:address":"Bensberger Str. 23",
    "sg:city":"Overath",
    "sg:phone":"+49 2206/2568",
    "sg:postcode":"51491",
    "sg:province":"Nordrhein-Westfalen",
    "wof:name":"Perse & Delling Gmbh",
    "wof:placetype":"venue"
},
  "geometry": {"coordinates":[7.255675,50.938278],"type":"Point"}
}