{
  "type": "Feature",
  "properties": {
    "iso:country":"DE",
    "sg:address":"Hochwaldstr. 60",
    "sg:city":"Morbach",
    "sg:phone":"+49 6533/3776",
    "sg:postcode":"54497",
    "sg:province":"Rheinland-Pfalz",
    "wof:name":"Elid Elektro-informations- Und Datensysteme Gmbh",
    "wof:placetype":"venue"
},
  "geometry": {"coordinates":[7.134472847,49.8033294678],"type":"Point"}
}