{
  "type": "Feature",
  "properties": {
    "iso:country":"DE",
    "sg:address":"Am Neuberg 13",
    "sg:city":"Traben-Trarbach",
    "sg:phone":"+49 6541/5413",
    "sg:postcode":"56841",
    "sg:province":"Rheinland-Pfalz",
    "wof:name":"Jolanta Busch Hebamme",
    "wof:placetype":"venue"
},
  "geometry": {"coordinates":[7.122957,49.957809],"type":"Point"}
}