{
  "type": "Feature",
  "properties": {
    "iso:country":"DE",
    "sg:address":"Kaiserstr. 143",
    "sg:city":"Herten",
    "sg:phone":"+49 2366/32372",
    "sg:postcode":"45699",
    "sg:province":"Nordrhein-Westfalen",
    "wof:name":"Gappa",
    "wof:placetype":"venue"
},
  "geometry": {"coordinates":[7.148660183,51.5994758606],"type":"Point"}
}