{
  "type": "Feature",
  "properties": {
    "iso:country":"DE",
    "sg:address":"Herrenstr. 25",
    "sg:city":"Harsefeld",
    "sg:phone":"+49 4164/8870",
    "sg:postcode":"21698",
    "sg:province":"Niedersachsen",
    "wof:name":"Sozialstation Geest",
    "wof:placetype":"venue"
},
  "geometry": {"coordinates":[9.49893,53.456066],"type":"Point"}
}