{
  "type": "Feature",
  "properties": {
    "iso:country":"DE",
    "sg:address":"Reeser Str. 172",
    "sg:city":"Kalkar",
    "sg:phone":"+49 2824/5731",
    "sg:postcode":"47546",
    "sg:province":"Nordrhein-Westfalen",
    "wof:name":"Neinhuis",
    "wof:placetype":"venue"
},
  "geometry": {"coordinates":[6.350213,51.722107],"type":"Point"}
}