{
  "type": "Feature",
  "properties": {
    "iso:country":"DE",
    "sg:address":"Dechant-Frye-Str. 9",
    "sg:city":"Horstmar",
    "sg:phone":"+49 2558/203",
    "sg:postcode":"48612",
    "sg:province":"Nordrhein-Westfalen",
    "wof:name":"Herbert Laschke",
    "wof:placetype":"venue"
},
  "geometry": {"coordinates":[7.3138852119,52.0799560547],"type":"Point"}
}