{
  "type": "Feature",
  "properties": {
    "iso:country":"DE",
    "sg:address":"L\u00fcbecker Str. 3",
    "sg:city":"Bad Schwartau",
    "sg:phone":"+49 451/21614",
    "sg:postcode":"23611",
    "sg:province":"Schleswig-Holstein",
    "wof:name":"Redaktion L\u00fcbecker Nachrichten",
    "wof:placetype":"venue"
},
  "geometry": {"coordinates":[10.6987762451,53.9187316895],"type":"Point"}
}