{
  "type": "Feature",
  "properties": {
    "iso:country":"DE",
    "sg:address":"Herbecker Weg 26",
    "sg:city":"Hagen",
    "sg:phone":"+49 2331/53907",
    "sg:postcode":"58093",
    "sg:province":"Nordrhein-Westfalen",
    "wof:name":"R. Sch\u00e4fer",
    "wof:placetype":"venue"
},
  "geometry": {"coordinates":[7.5295729637,51.3692398071],"type":"Point"}
}