{
  "type": "Feature",
  "properties": {
    "iso:country":"DE",
    "sg:address":"Samerhofstr. 15 a",
    "sg:city":"M\u00fcnchen",
    "sg:phone":"+49 89/8341072",
    "sg:postcode":"81247",
    "sg:province":"Bayern",
    "wof:name":"Siegfried Wulkow Architekt",
    "wof:placetype":"venue"
},
  "geometry": {"coordinates":[11.45971,48.159523],"type":"Point"}
}