{
  "type": "Feature",
  "properties": {
    "iso:country":"DE",
    "sg:address":"Ebersdorf 4",
    "sg:city":"Neunburg",
    "sg:phone":"+49 9672/613",
    "sg:postcode":"92431",
    "sg:province":"Bayern",
    "wof:name":"A. Winderl",
    "wof:placetype":"venue"
},
  "geometry": {"coordinates":[12.3244819641,49.3378639221],"type":"Point"}
}