{
  "type": "Feature",
  "properties": {
    "iso:country":"DE",
    "sg:address":"Auf der Struth",
    "sg:city":"Bad Sooden-Allendorf",
    "sg:phone":"+49 5652/4159",
    "sg:postcode":"37242",
    "sg:province":"Hessen",
    "wof:name":"Ernst-wilhelm R\u00fchling",
    "wof:placetype":"venue"
},
  "geometry": {"coordinates":[9.957205,51.299503],"type":"Point"}
}