{
  "type": "Feature",
  "properties": {
    "iso:country":"DE",
    "sg:address":"Neuses 14",
    "sg:city":"D\u00fcrrwangen",
    "sg:phone":"+49 9856/242",
    "sg:postcode":"91602",
    "sg:province":"Bayern",
    "wof:name":"H. Hammerl",
    "wof:placetype":"venue"
},
  "geometry": {"coordinates":[10.3514585495,49.1026268005],"type":"Point"}
}