{
  "type": "Feature",
  "properties": {
    "iso:country":"DE",
    "sg:address":"Auf der Wegscheid 27",
    "sg:city":"M\u00fclheim",
    "sg:phone":"+49 208/434763",
    "sg:postcode":"45472",
    "sg:province":"Nordrhein-Westfalen",
    "wof:name":"Friedhelm Fischer",
    "wof:placetype":"venue"
},
  "geometry": {"coordinates":[6.9160881042,51.4325561523],"type":"Point"}
}