{
  "type": "Feature",
  "properties": {
    "iso:country":"DE",
    "sg:address":"Chodowieckistr. 35",
    "sg:city":"Berlin",
    "sg:postcode":"10405",
    "sg:province":"Berlin",
    "wof:name":"B\u00e4rbel Gageik",
    "wof:placetype":"venue"
},
  "geometry": {"coordinates":[13.42925,52.53643],"type":"Point"}
}