{
  "type": "Feature",
  "properties": {
    "iso:country":"DE",
    "sg:address":"Hauptstr. 74",
    "sg:city":"Stadtprozelten",
    "sg:phone":"+49 9392/7265",
    "sg:postcode":"97909",
    "sg:province":"Bayern",
    "wof:name":"Kath. Pfarramt Mari\u00e4 Himmelfahrt",
    "wof:placetype":"venue"
},
  "geometry": {"coordinates":[9.4133844376,49.7858352661],"type":"Point"}
}