{
  "type": "Feature",
  "properties": {
    "iso:country":"DE",
    "sg:address":"Gehlengraben 2",
    "sg:city":"Hamburg",
    "sg:postcode":"22415",
    "sg:province":"Hamburg",
    "wof:name":"Lars Corradi E. K.",
    "wof:placetype":"venue"
},
  "geometry": {"coordinates":[10.0180768967,53.6491928101],"type":"Point"}
}