{
  "type": "Feature",
  "properties": {
    "iso:country":"DE",
    "sg:address":"Sommerburgstr. 165",
    "sg:city":"Essen",
    "sg:phone":"+49 201/714041",
    "sg:postcode":"45149",
    "sg:province":"Nordrhein-Westfalen",
    "wof:name":"Sommerburg-apotheke",
    "wof:placetype":"venue"
},
  "geometry": {"coordinates":[6.975548,51.42532],"type":"Point"}
}