{
  "type": "Feature",
  "properties": {
    "iso:country":"DE",
    "sg:address":"Monschauer Str. 26",
    "sg:city":"D\u00fcren",
    "sg:phone":"+49 2421/968070",
    "sg:postcode":"52355",
    "sg:province":"Nordrhein-Westfalen",
    "wof:name":"Tennishalle Am Ellernbusch Gmbh & Co. Kg",
    "wof:placetype":"venue"
},
  "geometry": {"coordinates":[6.4709911346,50.7938995361],"type":"Point"}
}