{
  "type": "Feature",
  "properties": {
    "iso:country":"DE",
    "sg:address":"Friederikenweg 13",
    "sg:city":"Spiekeroog",
    "sg:phone":"+49 4976/267",
    "sg:postcode":"26474",
    "sg:province":"Niedersachsen",
    "wof:name":"G\u00e4stehaus Fresena Gmbh",
    "wof:placetype":"venue"
},
  "geometry": {"coordinates":[7.7047948837,53.7715873718],"type":"Point"}
}