{
  "type": "Feature",
  "properties": {
    "iso:country":"DE",
    "sg:address":"Rosengasse 10",
    "sg:city":"Bad Reichenhall",
    "sg:phone":"+49 8651/2585",
    "sg:postcode":"83435",
    "sg:province":"Bayern",
    "wof:name":"Enzianst\u00fcberl",
    "wof:placetype":"venue"
},
  "geometry": {"coordinates":[12.878276825,47.7225227356],"type":"Point"}
}