{
  "type": "Feature",
  "properties": {
    "iso:country":"DE",
    "sg:address":"Karlsruher Str. 87",
    "sg:city":"Dresden",
    "sg:phone":"+49 351/4030477",
    "sg:postcode":"01189",
    "sg:province":"Sachsen",
    "wof:name":"Sport & Schuhhaus G\u00f6pfert",
    "wof:placetype":"venue"
},
  "geometry": {"coordinates":[13.693048,51.010658],"type":"Point"}
}