{
  "type": "Feature",
  "properties": {
    "iso:country":"DE",
    "sg:address":"Ahornweg 21",
    "sg:city":"Ebendorf",
    "sg:phone":"+49 39203/62630",
    "sg:postcode":"39179",
    "sg:province":"Sachsen-Anhalt",
    "wof:name":"Musikschule Schuffenhauer",
    "wof:placetype":"venue"
},
  "geometry": {"coordinates":[11.5783004761,52.1900939941],"type":"Point"}
}