{
  "type": "Feature",
  "properties": {
    "iso:country":"DE",
    "sg:address":"Gartenstr. 17",
    "sg:city":"Witzenhausen",
    "sg:phone":"+49 5542/1357",
    "sg:postcode":"37214",
    "sg:province":"Hessen",
    "wof:name":"Vts Aufzug- Und F\u00f6rdertechnik Vertriebs Gmbh",
    "wof:placetype":"venue"
},
  "geometry": {"coordinates":[9.8856096268,51.3462791443],"type":"Point"}
}