{
  "type": "Feature",
  "properties": {
    "iso:country":"DE",
    "sg:address":"Weseler Str. 42",
    "sg:city":"D\u00fclmen",
    "sg:postcode":"48249",
    "sg:province":"Nordrhein-Westfalen",
    "wof:name":"Innoka Gmbh",
    "wof:placetype":"venue"
},
  "geometry": {"coordinates":[7.365136,51.864697],"type":"Point"}
}