{
  "type": "Feature",
  "properties": {
    "iso:country":"DE",
    "sg:address":"Geretsrieder Str. 3A",
    "sg:city":"M\u00fcnchen",
    "sg:phone":"+49 89/78582068",
    "sg:postcode":"81379",
    "sg:province":"Bayern",
    "wof:name":"Deimhard Motorr\u00e4der E. K.",
    "wof:placetype":"venue"
},
  "geometry": {"coordinates":[11.5328149796,48.100479126],"type":"Point"}
}