{
  "type": "Feature",
  "properties": {
    "iso:country":"DE",
    "sg:address":"Elias-Eller-Str. 58",
    "sg:city":"Wuppertal",
    "sg:phone":"+49 202/4698158",
    "sg:postcode":"42369",
    "sg:province":"Nordrhein-Westfalen",
    "wof:name":"Michael Engstfeld",
    "wof:placetype":"venue"
},
  "geometry": {"coordinates":[7.1963481903,51.2307891846],"type":"Point"}
}