{
  "type": "Feature",
  "properties": {
    "iso:country":"DE",
    "sg:address":"Waldstr. 10",
    "sg:city":"Lampertheim",
    "sg:phone":"+49 6256/1544",
    "sg:postcode":"68623",
    "sg:province":"Hessen",
    "wof:name":"A & W Anders Wohnen Gmbh",
    "wof:placetype":"venue"
},
  "geometry": {"coordinates":[8.587263,49.593323],"type":"Point"}
}