{
  "type": "Feature",
  "properties": {
    "iso:country":"DE",
    "sg:address":"K\u00f6penicker Weg 1",
    "sg:city":"Villingen-Schwenningen",
    "sg:phone":"+49 7720/65292",
    "sg:postcode":"78056",
    "sg:province":"Baden-W\u00fcrttemberg",
    "wof:name":"Lux Fluctus Gmbh",
    "wof:placetype":"venue"
},
  "geometry": {"coordinates":[8.551788,48.071602],"type":"Point"}
}