{
  "type": "Feature",
  "properties": {
    "iso:country":"DE",
    "sg:address":"Rathausstr. 4",
    "sg:city":"Saarbr\u00fccken",
    "sg:phone":"+49 6897/72559",
    "sg:postcode":"66125",
    "sg:province":"Saarland",
    "wof:name":"B. Leyendecker",
    "wof:placetype":"venue"
},
  "geometry": {"coordinates":[7.036067009,49.2783355713],"type":"Point"}
}