{
  "type": "Feature",
  "properties": {
    "iso:country":"DE",
    "sg:address":"Neufeldstr. 26",
    "sg:city":"Olching",
    "sg:phone":"+49 8142/488140",
    "sg:postcode":"82140",
    "sg:province":"Bayern",
    "wof:name":"T. Czerlikowski",
    "wof:placetype":"venue"
},
  "geometry": {"coordinates":[11.3469057083,48.2099380493],"type":"Point"}
}