{
  "type": "Feature",
  "properties": {
    "iso:country":"DE",
    "sg:address":"Scharsbergweg 26",
    "sg:city":"M\u00f6nchengladbach",
    "sg:phone":"+49 2166/58239",
    "sg:postcode":"41189",
    "sg:province":"Nordrhein-Westfalen",
    "wof:name":"Irmgard Promsy",
    "wof:placetype":"venue"
},
  "geometry": {"coordinates":[6.3572330475,51.1156616211],"type":"Point"}
}