{
  "type": "Feature",
  "properties": {
    "iso:country":"DE",
    "sg:address":"Dr.-Hermann-Ludewig-Ring 1",
    "sg:city":"Rudolstadt",
    "sg:phone":"+49 3672/52627",
    "sg:postcode":"07407",
    "sg:province":"Th\u00fcringen",
    "wof:name":"Innocycling Ges. Zur Herstellung Und Wiederverwert.",
    "wof:placetype":"venue"
},
  "geometry": {"coordinates":[11.3370065689,50.6924171448],"type":"Point"}
}