{
  "type": "Feature",
  "properties": {
    "iso:country":"DE",
    "sg:address":"Ossietzkystr. 15",
    "sg:city":"Anklam",
    "sg:postcode":"17389",
    "sg:province":"Mecklenburg-Vorpommern",
    "wof:name":"Olbrisch Und Kro\u00df Gmbh",
    "wof:placetype":"venue"
},
  "geometry": {"coordinates":[13.711203,53.848564],"type":"Point"}
}