{
  "type": "Feature",
  "properties": {
    "iso:country":"DE",
    "sg:address":"Gartenstr. 8",
    "sg:city":"Reudelsterz",
    "sg:phone":"+49 2651/71156",
    "sg:postcode":"56727",
    "sg:province":"Rheinland-Pfalz",
    "wof:name":"Helmut Stolz Ingenieur",
    "wof:placetype":"venue"
},
  "geometry": {"coordinates":[7.1520447731,50.3166618347],"type":"Point"}
}