{
  "type": "Feature",
  "properties": {
    "iso:country":"DE",
    "sg:address":"Koblenzer Str. 165-167",
    "sg:city":"Bonn",
    "sg:phone":"+49 228/334621",
    "sg:postcode":"53177",
    "sg:province":"Nordrhein-Westfalen",
    "wof:name":"Mc Donalds",
    "wof:placetype":"venue"
},
  "geometry": {"coordinates":[7.1666908264,50.6784515381],"type":"Point"}
}