{
  "type": "Feature",
  "properties": {
    "iso:country":"DE",
    "sg:address":"Schwarzenbergstr.3",
    "sg:city":"Heitersheim",
    "sg:postcode":"79423",
    "sg:province":"Baden-W\u00fcrttemberg",
    "wof:name":"Telefon Und Mehr Walters-shop",
    "wof:placetype":"venue"
},
  "geometry": {"coordinates":[7.653354,47.877674],"type":"Point"}
}