{
  "type": "Feature",
  "properties": {
    "iso:country":"DE",
    "sg:address":"Hofer Str. 129 a",
    "sg:city":"Oberlungwitz",
    "sg:phone":"+49 3723/45822",
    "sg:postcode":"09353",
    "sg:province":"Sachsen",
    "wof:name":"V. He\u00df",
    "wof:placetype":"venue"
},
  "geometry": {"coordinates":[12.7169513702,50.7847557068],"type":"Point"}
}