{
  "type": "Feature",
  "properties": {
    "iso:country":"DE",
    "sg:address":"Balanstr. 276",
    "sg:city":"M\u00fcnchen",
    "sg:phone":"+49 89/7911962",
    "sg:postcode":"81549",
    "sg:province":"Bayern",
    "wof:name":"Gensler Immobilien Gmbh",
    "wof:placetype":"venue"
},
  "geometry": {"coordinates":[11.6074056625,48.0976905823],"type":"Point"}
}