{
  "type": "Feature",
  "properties": {
    "iso:country":"DE",
    "sg:address":"Leipziger Str. 16",
    "sg:city":"Gr\u00fcndau",
    "sg:phone":"+49 6051/18176",
    "sg:postcode":"63584",
    "sg:province":"Hessen",
    "wof:name":"Salzberger Gmbh",
    "wof:placetype":"venue"
},
  "geometry": {"coordinates":[9.138586,50.206551],"type":"Point"}
}