{
  "type": "Feature",
  "properties": {
    "iso:country":"DE",
    "sg:address":"Am Turm 14",
    "sg:city":"Cottbus",
    "sg:phone":"+49 355/702178",
    "sg:postcode":"03046",
    "sg:province":"Brandenburg",
    "wof:name":"Dr. K. Frey Anlageberater",
    "wof:placetype":"venue"
},
  "geometry": {"coordinates":[14.3323516846,51.7582855225],"type":"Point"}
}