{
  "type": "Feature",
  "properties": {
    "iso:country":"DE",
    "sg:address":"Karl-Marx-Str. 84",
    "sg:city":"Thale",
    "sg:phone":"+49 3947/2757",
    "sg:postcode":"06502",
    "sg:province":"Sachsen-Anhalt",
    "wof:name":"G\u00e4stehaus Forelle",
    "wof:placetype":"venue"
},
  "geometry": {"coordinates":[11.0453691483,51.7536239624],"type":"Point"}
}