{
  "type": "Feature",
  "properties": {
    "iso:country":"DE",
    "sg:address":"Nibelungenweg 62",
    "sg:city":"Bottrop",
    "sg:phone":"+49 2041/93451",
    "sg:postcode":"46240",
    "sg:province":"Nordrhein-Westfalen",
    "wof:name":"Wolfgang Hacke Ingenieur Und Architekt",
    "wof:placetype":"venue"
},
  "geometry": {"coordinates":[6.911324,51.5453],"type":"Point"}
}