{
  "type": "Feature",
  "properties": {
    "iso:country":"DE",
    "sg:address":"Lettenackerstr. 16",
    "sg:city":"Plochingen",
    "sg:phone":"+49 7153/21135",
    "sg:postcode":"73207",
    "sg:province":"Baden-W\u00fcrttemberg",
    "wof:name":"I. Specht",
    "wof:placetype":"venue"
},
  "geometry": {"coordinates":[9.4328737259,48.7077865601],"type":"Point"}
}