{
  "type": "Feature",
  "properties": {
    "iso:country":"DE",
    "sg:address":"Liebensteinstr. 11",
    "sg:city":"Emmendingen",
    "sg:phone":"+49 7641/41970",
    "sg:postcode":"79312",
    "sg:province":"Baden-W\u00fcrttemberg",
    "wof:name":"Psycho-soz. Beratungsstelle D. Ag F. Gef\u00e4hrdetenhilfe",
    "wof:placetype":"venue"
},
  "geometry": {"coordinates":[7.853039,48.115482],"type":"Point"}
}