{
  "type": "Feature",
  "properties": {
    "iso:country":"DE",
    "sg:address":"Neudorfstr. 47 a",
    "sg:city":"Cunewalde",
    "sg:phone":"+49 35877/20010",
    "sg:postcode":"02733",
    "sg:province":"Sachsen",
    "wof:name":"Wagner",
    "wof:placetype":"venue"
},
  "geometry": {"coordinates":[14.5557336807,51.0848007202],"type":"Point"}
}