{
  "type": "Feature",
  "properties": {
    "iso:country":"DE",
    "sg:address":"Karlsruher Str. 91",
    "sg:city":"Heidelberg",
    "sg:phone":"+49 6221/393953",
    "sg:postcode":"69126",
    "sg:province":"Baden-W\u00fcrttemberg",
    "wof:name":"C. Werner Kg",
    "wof:placetype":"venue"
},
  "geometry": {"coordinates":[8.68815,49.380306],"type":"Point"}
}