{
  "type": "Feature",
  "properties": {
    "iso:country":"DE",
    "sg:address":"Hauptstr. 51",
    "sg:city":"Gro\u00dferkmannsdorf",
    "sg:phone":"+49 3528/48190",
    "sg:postcode":"01454",
    "sg:province":"Sachsen",
    "wof:name":"Vorwerk Engineering Gmbh",
    "wof:placetype":"venue"
},
  "geometry": {"coordinates":[13.9284181595,51.0854454041],"type":"Point"}
}