{
  "type": "Feature",
  "properties": {
    "iso:country":"DE",
    "sg:address":"Alt Schwanheim 42",
    "sg:city":"Frankfurt",
    "sg:phone":"+49 69/350476",
    "sg:postcode":"60529",
    "sg:province":"Hessen",
    "wof:name":"Piet\u00e4t H. Dernbach",
    "wof:placetype":"venue"
},
  "geometry": {"coordinates":[8.581044,50.083801],"type":"Point"}
}