{
  "type": "Feature",
  "properties": {
    "iso:country":"DE",
    "sg:address":"Schneeberger Platz 2",
    "sg:city":"L\u00f6\u00dfnitz",
    "sg:phone":"+49 3771/35434",
    "sg:postcode":"08294",
    "sg:province":"Sachsen",
    "wof:name":"S. Wunderlich",
    "wof:placetype":"venue"
},
  "geometry": {"coordinates":[12.728972435,50.6213912964],"type":"Point"}
}