{
  "type": "Feature",
  "properties": {
    "iso:country":"DE",
    "sg:address":"Wilsonstr. 28",
    "sg:city":"Hamburg",
    "sg:phone":"+49 40/663924",
    "sg:postcode":"22045",
    "sg:province":"Hamburg",
    "wof:name":"Robert Puritz",
    "wof:placetype":"venue"
},
  "geometry": {"coordinates":[10.132544,53.586456],"type":"Point"}
}