{
  "type": "Feature",
  "properties": {
    "iso:country":"DE",
    "sg:address":"Blaicherstr. 3",
    "sg:city":"Freudenstadt",
    "sg:phone":"+49 7441/85907",
    "sg:postcode":"72250",
    "sg:province":"Baden-W\u00fcrttemberg",
    "wof:name":"Akdag",
    "wof:placetype":"venue"
},
  "geometry": {"coordinates":[8.4147377014,48.4647483826],"type":"Point"}
}