{
  "type": "Feature",
  "properties": {
    "iso:country":"DE",
    "sg:address":"Burgstr. 37",
    "sg:city":"Lissendorf",
    "sg:phone":"+49 6597/2255",
    "sg:postcode":"54587",
    "sg:province":"Rheinland-Pfalz",
    "wof:name":"Kath. Pfarramt St. Dionysius",
    "wof:placetype":"venue"
},
  "geometry": {"coordinates":[6.6068730354,50.3159217834],"type":"Point"}
}