{
  "type": "Feature",
  "properties": {
    "iso:country":"DE",
    "sg:address":"Poznaner Str. 23",
    "sg:city":"Cottbus",
    "sg:postcode":"03048",
    "sg:province":"Brandenburg",
    "wof:name":"Gwf Mbh",
    "wof:placetype":"venue"
},
  "geometry": {"coordinates":[14.3182277679,51.7325439453],"type":"Point"}
}