{
  "type": "Feature",
  "properties": {
    "iso:country":"DE",
    "sg:address":"Harjesstr. 4-6",
    "sg:city":"Gotha",
    "sg:phone":"+49 3621/713260",
    "sg:postcode":"99867",
    "sg:province":"Th\u00fcringen",
    "wof:name":"Herkules",
    "wof:placetype":"venue"
},
  "geometry": {"coordinates":[10.715133667,50.9275894165],"type":"Point"}
}