{
  "type": "Feature",
  "properties": {
    "iso:country":"DE",
    "sg:address":"Mankhauser Str. 1-3",
    "sg:city":"Solingen",
    "sg:postcode":"42699",
    "sg:province":"Nordrhein-Westfalen",
    "wof:name":"2 Vision Werbeagentur Gmbh",
    "wof:placetype":"venue"
},
  "geometry": {"coordinates":[7.0086808205,51.1600036621],"type":"Point"}
}