{
  "type": "Feature",
  "properties": {
    "iso:country":"DE",
    "sg:address":"Gutenbergstr. 16",
    "sg:city":"Duisburg",
    "sg:phone":"+49 203/21644",
    "sg:postcode":"47051",
    "sg:province":"Nordrhein-Westfalen",
    "wof:name":"City Glas Gmbh",
    "wof:placetype":"venue"
},
  "geometry": {"coordinates":[6.764331,51.435078],"type":"Point"}
}