{
  "type": "Feature",
  "properties": {
    "iso:country":"DE",
    "sg:address":"Gockenholzer Weg 2",
    "sg:city":"Lachendorf",
    "sg:phone":"+49 5145/1743",
    "sg:postcode":"29331",
    "sg:province":"Niedersachsen",
    "wof:name":"W. Schadel Gmbh",
    "wof:placetype":"venue"
},
  "geometry": {"coordinates":[10.242691,52.627201],"type":"Point"}
}