{
  "type": "Feature",
  "properties": {
    "iso:country":"DE",
    "sg:address":"Wiesenstr. 25",
    "sg:city":"Uslar",
    "sg:phone":"+49 5571/4866",
    "sg:postcode":"37170",
    "sg:province":"Niedersachsen",
    "wof:name":"Meeting",
    "wof:placetype":"venue"
},
  "geometry": {"coordinates":[9.6294,51.659855],"type":"Point"}
}