{
  "type": "Feature",
  "properties": {
    "iso:country":"DE",
    "sg:address":"Giengener Str. 19",
    "sg:city":"Giengen",
    "sg:phone":"+49 7324/5577",
    "sg:postcode":"89537",
    "sg:province":"Baden-W\u00fcrttemberg",
    "wof:name":"Felsen",
    "wof:placetype":"venue"
},
  "geometry": {"coordinates":[10.203953743,48.5935783386],"type":"Point"}
}