{
  "type": "Feature",
  "properties": {
    "iso:country":"DE",
    "sg:address":"Bahnhofstr. 2",
    "sg:city":"Dingolfing",
    "sg:phone":"+49 8731/73358",
    "sg:postcode":"84130",
    "sg:province":"Bayern",
    "wof:name":"Restaurant Pizza Italia",
    "wof:placetype":"venue"
},
  "geometry": {"coordinates":[12.4953517914,48.6348800659],"type":"Point"}
}