{
  "type": "Feature",
  "properties": {
    "iso:country":"DE",
    "sg:address":"Uerdinger Str. 101b",
    "sg:city":"Moers",
    "sg:phone":"+49 2841/93830",
    "sg:postcode":"47441",
    "sg:province":"Nordrhein-Westfalen",
    "wof:name":"Sound & Phone",
    "wof:placetype":"venue"
},
  "geometry": {"coordinates":[6.6384449005,51.4433174133],"type":"Point"}
}