{
  "type": "Feature",
  "properties": {
    "iso:country":"DE",
    "sg:address":"Hauptstr. 15",
    "sg:city":"Oberdachstetten",
    "sg:phone":"+49 9845/231",
    "sg:postcode":"91617",
    "sg:province":"Bayern",
    "wof:name":"Richard Eder",
    "wof:placetype":"venue"
},
  "geometry": {"coordinates":[10.422914,49.415428],"type":"Point"}
}