{
  "type": "Feature",
  "properties": {
    "iso:country":"DE",
    "sg:address":"Prambach",
    "sg:city":"Hettenshausen",
    "sg:phone":"+49 8441/2161",
    "sg:postcode":"85276",
    "sg:province":"Bayern",
    "wof:name":"Karlhans Kr\u00f6nauer Wirtschaftspr\u00fcfer Und",
    "wof:placetype":"venue"
},
  "geometry": {"coordinates":[11.5295610428,48.5033950806],"type":"Point"}
}