{
  "type": "Feature",
  "properties": {
    "iso:country":"DE",
    "sg:address":"Fu\u00dfg\u00f6nheimer Str. 24",
    "sg:city":"Ludwigshafen",
    "sg:phone":"+49 6237/7285",
    "sg:postcode":"67071",
    "sg:province":"Rheinland-Pfalz",
    "wof:name":"Klaus Kreiselmaier",
    "wof:placetype":"venue"
},
  "geometry": {"coordinates":[8.325685,49.472008],"type":"Point"}
}