{
  "type": "Feature",
  "properties": {
    "iso:country":"DE",
    "sg:address":"K\u00f6nigsteiner Str. 172",
    "sg:city":"Bad Soden",
    "sg:phone":"+49 6196/29665",
    "sg:postcode":"65812",
    "sg:province":"Hessen",
    "wof:name":"Leukel Gewerbe- Und Immobilien Gmbh & Co. Kg",
    "wof:placetype":"venue"
},
  "geometry": {"coordinates":[8.4914731979,50.1548805237],"type":"Point"}
}