{
  "type": "Feature",
  "properties": {
    "iso:country":"DE",
    "sg:address":"Karlstr. 31",
    "sg:city":"Schmalkalden",
    "sg:postcode":"98574",
    "sg:province":"Th\u00fcringen",
    "wof:name":"R. Kriechling",
    "wof:placetype":"venue"
},
  "geometry": {"coordinates":[10.446203,50.725475],"type":"Point"}
}