{
  "type": "Feature",
  "properties": {
    "iso:country":"DE",
    "sg:address":"N\u00fcrtinger Str. 2",
    "sg:city":"Metzingen",
    "sg:postcode":"72555",
    "sg:province":"Baden-W\u00fcrttemberg",
    "wof:name":"Ubt Unternehmensberatung Und Treuhand Gmbh",
    "wof:placetype":"venue"
},
  "geometry": {"coordinates":[9.2808666229,48.5399932861],"type":"Point"}
}