{
  "type": "Feature",
  "properties": {
    "iso:country":"DE",
    "sg:address":"Ostwall 11",
    "sg:city":"L\u00fcdinghausen",
    "sg:phone":"+49 2591/1699",
    "sg:postcode":"59348",
    "sg:province":"Nordrhein-Westfalen",
    "wof:name":"Wilhelm B\u00fccker Gmbh",
    "wof:placetype":"venue"
},
  "geometry": {"coordinates":[7.4474668503,51.7722663879],"type":"Point"}
}