{
  "type": "Feature",
  "properties": {
    "iso:country":"DE",
    "sg:address":"Blinke 4",
    "sg:city":"Leer",
    "sg:postcode":"26789",
    "sg:province":"Niedersachsen",
    "wof:name":"Ms Ledator Schiffahrts- Verwaltungs Gmbh",
    "wof:placetype":"venue"
},
  "geometry": {"coordinates":[7.445411,53.225979],"type":"Point"}
}