{
  "type": "Feature",
  "properties": {
    "iso:country":"DE",
    "sg:address":"Beim Breitenstein 34",
    "sg:city":"Efringen-Kirchen",
    "sg:phone":"+49 4961/7176088",
    "sg:postcode":"79588",
    "sg:province":"Baden-W\u00fcrttemberg",
    "wof:name":"Krebsm\u00dchle Antiquit\u00c4ten Und Holzbearbeitung Gmbh",
    "wof:placetype":"venue"
},
  "geometry": {"coordinates":[8.6079206467,50.1772346497],"type":"Point"}
}