{
  "type": "Feature",
  "properties": {
    "iso:country":"DE",
    "sg:address":"Kirchstr. 29",
    "sg:city":"Emsdetten",
    "sg:postcode":"48282",
    "sg:province":"Nordrhein-Westfalen",
    "wof:name":"Chronomed Verlag Gesch\u00e4ftsf\u00fchr.ges. F. Wissen-",
    "wof:placetype":"venue"
},
  "geometry": {"coordinates":[7.52611,52.173725],"type":"Point"}
}