{
  "type": "Feature",
  "properties": {
    "iso:country":"DE",
    "sg:address":"Stra\u00dfe der Einheit 28",
    "sg:city":"Blumenthal",
    "sg:phone":"+49 33984/225",
    "sg:postcode":"16928",
    "sg:province":"Brandenburg",
    "wof:name":"Friedrich Immobilienmakler",
    "wof:placetype":"venue"
},
  "geometry": {"coordinates":[12.3357944489,53.0740013123],"type":"Point"}
}