{
  "type": "Feature",
  "properties": {
    "iso:country":"DE",
    "sg:address":"Bahnhofstr.",
    "sg:city":"Gaildorf",
    "sg:phone":"+49 7971/8249",
    "sg:postcode":"74405",
    "sg:province":"Baden-W\u00fcrttemberg",
    "wof:name":"Holzbearbeitung Mauser Ohg",
    "wof:placetype":"venue"
},
  "geometry": {"coordinates":[9.7694101334,49.0003700256],"type":"Point"}
}