{
  "type": "Feature",
  "properties": {
    "iso:country":"DE",
    "sg:address":"Windm\u00fchlenstr. 13",
    "sg:city":"Lauchhammer",
    "sg:phone":"+49 3574/2429",
    "sg:postcode":"01979",
    "sg:province":"Brandenburg",
    "wof:name":"Werner Mlosch",
    "wof:placetype":"venue"
},
  "geometry": {"coordinates":[13.778145,51.489658],"type":"Point"}
}