{
  "type": "Feature",
  "properties": {
    "iso:country":"DE",
    "sg:address":"Medlinger Str. 6",
    "sg:city":"Gundelfingen",
    "sg:phone":"+49 9073/7301",
    "sg:postcode":"89423",
    "sg:province":"Bayern",
    "wof:name":"Kath. Pfarramt St. Peter Und Paul",
    "wof:placetype":"venue"
},
  "geometry": {"coordinates":[10.3672704697,48.5552024841],"type":"Point"}
}