{
  "type": "Feature",
  "properties": {
    "iso:country":"DE",
    "sg:address":"Vossundern 25",
    "sg:city":"Bottrop",
    "sg:postcode":"46244",
    "sg:province":"Nordrhein-Westfalen",
    "wof:name":"C4c Competence For Communication Gmbh",
    "wof:placetype":"venue"
},
  "geometry": {"coordinates":[6.90287,51.569408],"type":"Point"}
}