{
  "type": "Feature",
  "properties": {
    "iso:country":"DE",
    "sg:address":"Boschstr. 11",
    "sg:city":"Herford",
    "sg:phone":"+49 5221/34030",
    "sg:postcode":"32051",
    "sg:province":"Nordrhein-Westfalen",
    "wof:name":"Alsco",
    "wof:placetype":"venue"
},
  "geometry": {"coordinates":[8.624671936,52.100856781],"type":"Point"}
}