{
  "type": "Feature",
  "properties": {
    "iso:country":"DE",
    "sg:address":"M\u00fchlenstr. 8",
    "sg:city":"Neum\u00fcnster",
    "sg:phone":"+49 4321/81565",
    "sg:postcode":"24539",
    "sg:province":"Schleswig-Holstein",
    "wof:name":"Hamanns Gastst\u00e4tte Hans-peter Hamann",
    "wof:placetype":"venue"
},
  "geometry": {"coordinates":[9.9669408798,54.0545005798],"type":"Point"}
}