{
  "type": "Feature",
  "properties": {
    "iso:country":"DE",
    "sg:address":"Oberweg 2",
    "sg:city":"Langewiesen",
    "sg:phone":"+49 3677/80600",
    "sg:postcode":"98704",
    "sg:province":"Th\u00fcringen",
    "wof:name":"Saveway Isolierstoffe Gmbh",
    "wof:placetype":"venue"
},
  "geometry": {"coordinates":[10.9658346176,50.673740387],"type":"Point"}
}