{
  "type": "Feature",
  "properties": {
    "iso:country":"DE",
    "sg:address":"Zum Storchennest 11",
    "sg:city":"Diekhof",
    "sg:phone":"+49 38455/3110",
    "sg:postcode":"18299",
    "sg:province":"Mecklenburg-Vorpommern",
    "wof:name":"Tabeg Tanklagerbetriebs- Gmbh",
    "wof:placetype":"venue"
},
  "geometry": {"coordinates":[12.3613004684,53.8632202148],"type":"Point"}
}