{
  "type": "Feature",
  "properties": {
    "iso:country":"DE",
    "sg:address":"Lindenweg 9",
    "sg:city":"Ducherow",
    "sg:phone":"+49 39726/510",
    "sg:postcode":"17398",
    "sg:province":"Mecklenburg-Vorpommern",
    "wof:name":"H. Chabowski",
    "wof:placetype":"venue"
},
  "geometry": {"coordinates":[13.7737970352,53.7659378052],"type":"Point"}
}