{
  "type": "Feature",
  "properties": {
    "iso:country":"DE",
    "sg:address":"Bramscher Str. 5-7",
    "sg:city":"Bersenbr\u00fcck",
    "sg:phone":"+49 5439/3132",
    "sg:postcode":"49593",
    "sg:province":"Niedersachsen",
    "wof:name":"Foto-ecke",
    "wof:placetype":"venue"
},
  "geometry": {"coordinates":[7.9451160431,52.5352287292],"type":"Point"}
}