{
  "type": "Feature",
  "properties": {
    "iso:country":"DE",
    "sg:address":"Am Reisert 1",
    "sg:city":"We\u00dfling",
    "sg:phone":"+49 8153/1513",
    "sg:postcode":"82234",
    "sg:province":"Bayern",
    "wof:name":"Hubert Krebs Elektronik-service Gmbh",
    "wof:placetype":"venue"
},
  "geometry": {"coordinates":[11.2462320328,48.0703010559],"type":"Point"}
}