{
  "type": "Feature",
  "properties": {
    "iso:country":"DE",
    "sg:address":"Alter Sielweg 19",
    "sg:city":"Esens",
    "sg:phone":"+49 4971/5700",
    "sg:postcode":"26427",
    "sg:province":"Niedersachsen",
    "wof:name":"Pizzeria Palermo",
    "wof:placetype":"venue"
},
  "geometry": {"coordinates":[7.5739240646,53.6744003296],"type":"Point"}
}