{
  "type": "Feature",
  "properties": {
    "iso:country":"DE",
    "sg:address":"Benrather Str. 31",
    "sg:city":"Hilden",
    "sg:phone":"+49 2103/51261",
    "sg:postcode":"40721",
    "sg:province":"Nordrhein-Westfalen",
    "wof:name":"B. Rogall",
    "wof:placetype":"venue"
},
  "geometry": {"coordinates":[6.927658,51.167294],"type":"Point"}
}