{
  "type": "Feature",
  "properties": {
    "iso:country":"DE",
    "sg:address":"In Bisholder 46",
    "sg:city":"Koblenz",
    "sg:phone":"+49 261/94249030",
    "sg:postcode":"56072",
    "sg:province":"Rheinland-Pfalz",
    "wof:name":"Willkommen Auf Den Seiten Der Rb-net",
    "wof:placetype":"venue"
},
  "geometry": {"coordinates":[7.532231,50.333698],"type":"Point"}
}