{
  "type": "Feature",
  "properties": {
    "iso:country":"DE",
    "sg:address":"Gr\u00fcnstr. 49",
    "sg:city":"Meerbusch",
    "sg:phone":"+49 2132/77702",
    "sg:postcode":"40667",
    "sg:province":"Nordrhein-Westfalen",
    "wof:name":"Werner Vogt Ingenieur",
    "wof:placetype":"venue"
},
  "geometry": {"coordinates":[6.7040381432,51.2487792969],"type":"Point"}
}