{
  "type": "Feature",
  "properties": {
    "iso:country":"DE",
    "sg:address":"Krankenhausstr. 1",
    "sg:city":"S\u00fcnching",
    "sg:postcode":"93104",
    "sg:province":"Bayern",
    "wof:name":"Archiv Der Grafen Von Seinsheim",
    "wof:placetype":"venue"
},
  "geometry": {"coordinates":[12.353031,48.878094],"type":"Point"}
}