{
  "type": "Feature",
  "properties": {
    "iso:country":"DE",
    "sg:address":"Jahnstr. 40",
    "sg:city":"Pforzheim",
    "sg:phone":"+49 7231/24126",
    "sg:postcode":"75173",
    "sg:province":"Baden-W\u00fcrttemberg",
    "wof:name":"Helmut Schellhorn Rechtsanwalt",
    "wof:placetype":"venue"
},
  "geometry": {"coordinates":[8.6971502304,48.8866577148],"type":"Point"}
}