{
  "type": "Feature",
  "properties": {
    "iso:country":"DE",
    "sg:address":"Erich-Steinfurth-Str. 32",
    "sg:city":"Eberswalde",
    "sg:phone":"+49 3334/352949",
    "sg:postcode":"16227",
    "sg:province":"Brandenburg",
    "wof:name":"Susanne Hitzel",
    "wof:placetype":"venue"
},
  "geometry": {"coordinates":[13.712562,52.849606],"type":"Point"}
}