{
  "type": "Feature",
  "properties": {
    "iso:country":"DE",
    "sg:address":"Dornr\u00f6schenweg 92",
    "sg:city":"Ibbenb\u00fcren",
    "sg:phone":"+49 5451/84641",
    "sg:postcode":"49479",
    "sg:province":"Nordrhein-Westfalen",
    "wof:name":"Reinhold H\u00f6flich Ingenieur",
    "wof:placetype":"venue"
},
  "geometry": {"coordinates":[7.7848358154,52.2694854736],"type":"Point"}
}