{
  "type": "Feature",
  "properties": {
    "iso:country":"DE",
    "sg:address":"Starkenburger Str. 21",
    "sg:city":"Riedstadt",
    "sg:phone":"+49 6158/5111",
    "sg:postcode":"64560",
    "sg:province":"Hessen",
    "wof:name":"Pizzeria Antonia",
    "wof:placetype":"venue"
},
  "geometry": {"coordinates":[8.5013904572,49.8374710083],"type":"Point"}
}