{
  "type": "Feature",
  "properties": {
    "iso:country":"DE",
    "sg:address":"Kuhlenstr. 57",
    "sg:city":"Westerstede",
    "sg:phone":"+49 4488/73181",
    "sg:postcode":"26655",
    "sg:province":"Niedersachsen",
    "wof:name":"Hans-gerd Becker",
    "wof:placetype":"venue"
},
  "geometry": {"coordinates":[7.9168710709,53.2530288696],"type":"Point"}
}