{
  "type": "Feature",
  "properties": {
    "iso:country":"DE",
    "sg:address":"Breslauer Str. 14",
    "sg:city":"Isernhagen",
    "sg:phone":"+49 5139/3548",
    "sg:postcode":"30916",
    "sg:province":"Niedersachsen",
    "wof:name":"F.-w. Huffnagel",
    "wof:placetype":"venue"
},
  "geometry": {"coordinates":[9.891483,52.46772],"type":"Point"}
}