{
  "type": "Feature",
  "properties": {
    "iso:country":"DE",
    "sg:address":"Bahnstr. 58",
    "sg:city":"Grefrath",
    "sg:phone":"+49 2158/2279",
    "sg:postcode":"47929",
    "sg:province":"Nordrhein-Westfalen",
    "wof:name":"Heinrich T\u00f6nnessen",
    "wof:placetype":"venue"
},
  "geometry": {"coordinates":[6.345325,51.335449],"type":"Point"}
}