{
  "type": "Feature",
  "properties": {
    "iso:country":"DE",
    "sg:address":"Georg-August-Zinn-Weg 7",
    "sg:city":"Neu-Anspach",
    "sg:phone":"+49 6081/42181",
    "sg:postcode":"61267",
    "sg:province":"Hessen",
    "wof:name":"Ulrich Schwinn",
    "wof:placetype":"venue"
},
  "geometry": {"coordinates":[8.5092163086,50.3012161255],"type":"Point"}
}