{
  "type": "Feature",
  "properties": {
    "iso:country":"DE",
    "sg:address":"L\u00fcneburger Landstr. 22",
    "sg:city":"Garlstorf",
    "sg:phone":"+49 4172/215",
    "sg:postcode":"21376",
    "sg:province":"Niedersachsen",
    "wof:name":"G. K\u00f6hler",
    "wof:placetype":"venue"
},
  "geometry": {"coordinates":[10.1094083786,53.2313728333],"type":"Point"}
}