{
  "type": "Feature",
  "properties": {
    "iso:country":"DE",
    "sg:address":"Unter Greut 5",
    "sg:city":"K\u00fcssaberg",
    "sg:phone":"+49 7741/61122",
    "sg:postcode":"79790",
    "sg:province":"Baden-W\u00fcrttemberg",
    "wof:name":"Jordan Bau Gmbh",
    "wof:placetype":"venue"
},
  "geometry": {"coordinates":[8.271701,47.619335],"type":"Point"}
}