{
  "type": "Feature",
  "properties": {
    "iso:country":"DE",
    "sg:address":"Teichweg 1",
    "sg:city":"Stadt Wehlen",
    "sg:phone":"+49 35024/70621",
    "sg:postcode":"01829",
    "sg:province":"Sachsen",
    "wof:name":"Annette Karl",
    "wof:placetype":"venue"
},
  "geometry": {"coordinates":[14.002837,50.961346],"type":"Point"}
}