{
  "type": "Feature",
  "properties": {
    "iso:country":"DE",
    "sg:address":"Adlerstr. 14",
    "sg:city":"Aalen",
    "sg:postcode":"73434",
    "sg:province":"Baden-W\u00fcrttemberg",
    "wof:name":"Bbh Me\u00dftechnik Gmbh",
    "wof:placetype":"venue"
},
  "geometry": {"coordinates":[10.0624542236,48.8301277161],"type":"Point"}
}