{
  "type": "Feature",
  "properties": {
    "iso:country":"DE",
    "sg:address":"Claudiusweg 26",
    "sg:city":"Darmstadt",
    "sg:phone":"+49 6151/48533",
    "sg:postcode":"64285",
    "sg:province":"Hessen",
    "wof:name":"Roland Weimar Tennislehrer",
    "wof:placetype":"venue"
},
  "geometry": {"coordinates":[8.6666955948,49.8550796509],"type":"Point"}
}