{
  "type": "Feature",
  "properties": {
    "iso:country":"DE",
    "sg:address":"Schuhstr. 55",
    "sg:city":"Oldenburg",
    "sg:phone":"+49 4361/2339",
    "sg:postcode":"23758",
    "sg:province":"Schleswig-Holstein",
    "wof:name":"Baby-landschoof Inh. K. Stief",
    "wof:placetype":"venue"
},
  "geometry": {"coordinates":[-85.206237793,39.3398132324],"type":"Point"}
}