{
  "type": "Feature",
  "properties": {
    "iso:country":"DE",
    "sg:address":"Dahlienweg 2",
    "sg:city":"Pentling",
    "sg:postcode":"93080",
    "sg:province":"Bayern",
    "wof:name":"Intakt Wohnbau- Und Verwaltungsges. Mbh & Co.",
    "wof:placetype":"venue"
},
  "geometry": {"coordinates":[12.0568094254,48.9800682068],"type":"Point"}
}