{
  "type": "Feature",
  "properties": {
    "iso:country":"DE",
    "sg:address":"Schwefinger Str. 29",
    "sg:city":"Meppen",
    "sg:phone":"+49 5931/97870",
    "sg:postcode":"49716",
    "sg:province":"Niedersachsen",
    "wof:name":"H & M Automobilhandels- Und Verwaltungs Gmbh",
    "wof:placetype":"venue"
},
  "geometry": {"coordinates":[7.29114,52.68993],"type":"Point"}
}