{
  "type": "Feature",
  "properties": {
    "iso:country":"DE",
    "sg:address":"Adalbert-Stifter-Weg 30",
    "sg:city":"Krumbach",
    "sg:phone":"+49 8282/82240",
    "sg:postcode":"86381",
    "sg:province":"Bayern",
    "wof:name":"Medi-pro E. K.",
    "wof:placetype":"venue"
},
  "geometry": {"coordinates":[10.360208,48.236862],"type":"Point"}
}