{
  "type": "Feature",
  "properties": {
    "iso:country":"DE",
    "sg:address":"Forststr. 76",
    "sg:city":"Breitenbach",
    "sg:phone":"+49 721/15138605",
    "sg:postcode":"06712",
    "sg:province":"Sachsen-Anhalt",
    "wof:name":"Gate-24 - Die Adresse F\u00fcr Ihren Internet Auftritt!",
    "wof:placetype":"venue"
},
  "geometry": {"coordinates":[12.0740003586,51.0038223267],"type":"Point"}
}