{
  "type": "Feature",
  "properties": {
    "iso:country":"DE",
    "sg:address":"Nibelungenstr. 3",
    "sg:city":"Regensburg",
    "sg:phone":"+49 941/90358",
    "sg:postcode":"93051",
    "sg:province":"Bayern",
    "wof:name":"Baugenossenschaft St. Wolfgang Eg",
    "wof:placetype":"venue"
},
  "geometry": {"coordinates":[12.083106,49.004196],"type":"Point"}
}