{
  "type": "Feature",
  "properties": {
    "iso:country":"DE",
    "sg:address":"K\u00f6nigstr. 11",
    "sg:city":"Schwabach",
    "sg:phone":"+49 9122/2130",
    "sg:postcode":"91126",
    "sg:province":"Bayern",
    "wof:name":"Stephan",
    "wof:placetype":"venue"
},
  "geometry": {"coordinates":[11.0191822052,49.3292236328],"type":"Point"}
}