{
  "type": "Feature",
  "properties": {
    "iso:country":"DE",
    "sg:address":"Adlerstr 6",
    "sg:city":"Essen",
    "sg:phone":"+49 201/177660",
    "sg:postcode":"45307",
    "sg:province":"Nordrhein-Westfalen",
    "wof:name":"Afalin Gmbh & Co",
    "wof:placetype":"venue"
},
  "geometry": {"coordinates":[7.101651,51.463272],"type":"Point"}
}