{
  "type": "Feature",
  "properties": {
    "iso:country":"DE",
    "sg:address":"Untermarkt 24",
    "sg:city":"M\u00fchlhausen",
    "sg:phone":"+49 36014/45252",
    "sg:postcode":"99974",
    "sg:province":"Th\u00fcringen",
    "wof:name":"Peter Bellstedt Rechtsanwalt",
    "wof:placetype":"venue"
},
  "geometry": {"coordinates":[10.4603796005,51.2074127197],"type":"Point"}
}