{
  "type": "Feature",
  "properties": {
    "iso:country":"DE",
    "sg:address":"Hatzbacher Str. 18",
    "sg:city":"Stadtallendorf",
    "sg:phone":"+49 6428/1359",
    "sg:postcode":"35260",
    "sg:province":"Hessen",
    "wof:name":"Friedhelm Steinhaus",
    "wof:placetype":"venue"
},
  "geometry": {"coordinates":[9.023859,50.861286],"type":"Point"}
}