{
  "type": "Feature",
  "properties": {
    "iso:country":"DE",
    "sg:address":"An der Vogelrute 38",
    "sg:city":"Ascheberg",
    "sg:phone":"+49 2599/864",
    "sg:postcode":"59387",
    "sg:province":"Nordrhein-Westfalen",
    "wof:name":"S. Scheiter Kunststoffwaren",
    "wof:placetype":"venue"
},
  "geometry": {"coordinates":[7.672209,51.741673],"type":"Point"}
}