{
  "type": "Feature",
  "properties": {
    "iso:country":"DE",
    "sg:address":"Pr\u00e4lat-Pfanzelt-Weg 2",
    "sg:city":"Taufkirchen",
    "sg:postcode":"84416",
    "sg:province":"Bayern",
    "wof:name":"Vimo Dienstleistung Gmbh",
    "wof:placetype":"venue"
},
  "geometry": {"coordinates":[12.17875,48.343449],"type":"Point"}
}