{
  "type": "Feature",
  "properties": {
    "iso:country":"DE",
    "sg:address":"Achterdeck 21 a",
    "sg:city":"L\u00fcbeck",
    "sg:phone":"+49 4502/6013",
    "sg:postcode":"23570",
    "sg:province":"Schleswig-Holstein",
    "wof:name":"Jutta Stute Charteryachten Kg",
    "wof:placetype":"venue"
},
  "geometry": {"coordinates":[10.874573,53.968826],"type":"Point"}
}