{
  "type": "Feature",
  "properties": {
    "iso:country":"DE",
    "sg:address":"Elbuferstr. 162",
    "sg:city":"Marschacht",
    "sg:phone":"+49 4176/1372",
    "sg:postcode":"21436",
    "sg:province":"Niedersachsen",
    "wof:name":"Heinz Fritzenwanker",
    "wof:placetype":"venue"
},
  "geometry": {"coordinates":[10.33641,53.418991],"type":"Point"}
}