{
  "type": "Feature",
  "properties": {
    "iso:country":"DE",
    "sg:address":"Huyssenallee 11",
    "sg:city":"Essen",
    "sg:phone":"+49 201/757300",
    "sg:postcode":"45128",
    "sg:province":"Nordrhein-Westfalen",
    "wof:name":"Pastridor Deutschland Gmbh",
    "wof:placetype":"venue"
},
  "geometry": {"coordinates":[7.0118370056,51.4486312866],"type":"Point"}
}