{
  "type": "Feature",
  "properties": {
    "iso:country":"DE",
    "sg:address":"Forststr. 136 A",
    "sg:city":"Potsdam",
    "sg:postcode":"14471",
    "sg:province":"Brandenburg",
    "wof:name":"Dr. Med. Ingrid B\u00f6hmer",
    "wof:placetype":"venue"
},
  "geometry": {"coordinates":[13.015271,52.381725],"type":"Point"}
}