{
  "type": "Feature",
  "properties": {
    "iso:country":"DE",
    "sg:address":"Finnebachstr. 31",
    "sg:city":"Vlotho",
    "sg:postcode":"32602",
    "sg:province":"Nordrhein-Westfalen",
    "wof:name":"Golfpark Heerhof Gmbh",
    "wof:placetype":"venue"
},
  "geometry": {"coordinates":[8.7357616425,52.118637085],"type":"Point"}
}