{
  "type": "Feature",
  "properties": {
    "iso:country":"DE",
    "sg:address":"G\u00fcchenbacher Weg 7",
    "sg:city":"P\u00fcttlingen",
    "sg:phone":"+49 6806/4184",
    "sg:postcode":"66346",
    "sg:province":"Saarland",
    "wof:name":"Helmut Geschke",
    "wof:placetype":"venue"
},
  "geometry": {"coordinates":[6.9165678024,49.3143043518],"type":"Point"}
}