{
  "type": "Feature",
  "properties": {
    "iso:country":"DE",
    "sg:address":"Werner-Petzold-Str. 6",
    "sg:city":"Gera",
    "sg:phone":"+49 365/7106030",
    "sg:postcode":"07549",
    "sg:province":"Th\u00fcringen",
    "wof:name":"Initiative Hilfe Zur Selbsthilfe E. V.",
    "wof:placetype":"venue"
},
  "geometry": {"coordinates":[12.060583,50.837372],"type":"Point"}
}