{
  "type": "Feature",
  "properties": {
    "iso:country":"DE",
    "sg:address":"Dorfstr. 8",
    "sg:city":"Todtnau",
    "sg:phone":"+49 7674/232",
    "sg:postcode":"79674",
    "sg:province":"Baden-W\u00fcrttemberg",
    "wof:name":"Hotel-restaurant Waldfrieden",
    "wof:placetype":"venue"
},
  "geometry": {"coordinates":[7.9526658058,47.767616272],"type":"Point"}
}