{
  "type": "Feature",
  "properties": {
    "iso:country":"DE",
    "sg:address":"Gr\u00fcnholz 23",
    "sg:city":"Esgrus",
    "sg:phone":"+49 4637/457",
    "sg:postcode":"24402",
    "sg:province":"Schleswig-Holstein",
    "wof:name":"Walter Hinrichsen",
    "wof:placetype":"venue"
},
  "geometry": {"coordinates":[9.778056,54.706051],"type":"Point"}
}