{
  "type": "Feature",
  "properties": {
    "iso:country":"DE",
    "sg:address":"Melanchthonstr. 3a",
    "sg:city":"Lutherstadt Wittenberg",
    "sg:phone":"+49 3491/438284",
    "sg:postcode":"06886",
    "sg:province":"Sachsen-Anhalt",
    "wof:name":"Fachvermittlung F\u00fcr Land- Wirtschaftliche Fachkr\u00e4fte",
    "wof:placetype":"venue"
},
  "geometry": {"coordinates":[12.638206,51.870899],"type":"Point"}
}