{
  "type": "Feature",
  "properties": {
    "iso:country":"DE",
    "sg:address":"K\u00f6nigsberger Str. 14",
    "sg:city":"Hofgeismar",
    "sg:phone":"+49 5671/5547",
    "sg:postcode":"34369",
    "sg:province":"Hessen",
    "wof:name":"Dittmar Aretz",
    "wof:placetype":"venue"
},
  "geometry": {"coordinates":[9.391834259,51.487701416],"type":"Point"}
}