{
  "type": "Feature",
  "properties": {
    "iso:country":"DE",
    "sg:address":"Lindenstr 16",
    "sg:city":"Wittingen",
    "sg:phone":"+49 5834/98890",
    "sg:postcode":"29379",
    "sg:province":"Niedersachsen",
    "wof:name":"Pasemann Transport Gmbh",
    "wof:placetype":"venue"
},
  "geometry": {"coordinates":[10.703523,52.676517],"type":"Point"}
}