{
  "type": "Feature",
  "properties": {
    "iso:country":"DE",
    "sg:address":"Rathausplatz 1",
    "sg:city":"Gr\u00fcnwald",
    "sg:phone":"+49 89/6413573",
    "sg:postcode":"82031",
    "sg:province":"Bayern",
    "wof:name":"Rathaus Apotheke Dr. J\u00fcrgen Dietrich E. K.",
    "wof:placetype":"venue"
},
  "geometry": {"coordinates":[11.521673,48.040649],"type":"Point"}
}