{
  "type": "Feature",
  "properties": {
    "iso:country":"DE",
    "sg:address":"Aschfelder Str. 33",
    "sg:city":"Eu\u00dfenheim",
    "sg:phone":"+49 9350/213",
    "sg:postcode":"97776",
    "sg:province":"Bayern",
    "wof:name":"Engel",
    "wof:placetype":"venue"
},
  "geometry": {"coordinates":[9.8256425858,50.0051307678],"type":"Point"}
}