{
  "type": "Feature",
  "properties": {
    "iso:country":"DE",
    "sg:address":"Luisenstr. 27",
    "sg:city":"Braunschweig",
    "sg:phone":"+49 531/896325",
    "sg:postcode":"38118",
    "sg:province":"Niedersachsen",
    "wof:name":"Hwh Helge Wels Handelsges. Mbh",
    "wof:placetype":"venue"
},
  "geometry": {"coordinates":[10.5093097687,52.2560691833],"type":"Point"}
}