{
  "type": "Feature",
  "properties": {
    "iso:country":"DE",
    "sg:address":"Goltsteinstr. 17",
    "sg:city":"D\u00fcsseldorf",
    "sg:postcode":"40211",
    "sg:province":"Nordrhein-Westfalen",
    "wof:name":"Duskavest Immobilien Frankfurt Gmbh",
    "wof:placetype":"venue"
},
  "geometry": {"coordinates":[6.7848329544,51.2286109924],"type":"Point"}
}