{
  "type": "Feature",
  "properties": {
    "iso:country":"DE",
    "sg:address":"Sonsbecker Str. 24",
    "sg:city":"Xanten",
    "sg:phone":"+49 2801/1476",
    "sg:postcode":"46509",
    "sg:province":"Nordrhein-Westfalen",
    "wof:name":"Franz-josef G\u00f6rtzen Antiquit\u00e4ten",
    "wof:placetype":"venue"
},
  "geometry": {"coordinates":[6.440321,51.655365],"type":"Point"}
}