{
  "type": "Feature",
  "properties": {
    "iso:country":"DE",
    "sg:address":"Schusterstr. 15",
    "sg:city":"D\u00f6mitz",
    "sg:phone":"+49 38758/24369",
    "sg:postcode":"19303",
    "sg:province":"Mecklenburg-Vorpommern",
    "wof:name":"Frank Engelmann",
    "wof:placetype":"venue"
},
  "geometry": {"coordinates":[11.25027,53.140766],"type":"Point"}
}