{
  "type": "Feature",
  "properties": {
    "iso:country":"DE",
    "sg:address":"Hainbuchenweg 7",
    "sg:city":"Villingen-Schwenningen",
    "sg:phone":"+49 7721/21142",
    "sg:postcode":"78052",
    "sg:province":"Baden-W\u00fcrttemberg",
    "wof:name":"Scharting Me\u00dftechnik Gmbh",
    "wof:placetype":"venue"
},
  "geometry": {"coordinates":[8.4528503418,48.0302047729],"type":"Point"}
}