{
  "type": "Feature",
  "properties": {
    "iso:country":"DE",
    "sg:address":"Am Ring 81",
    "sg:city":"Melchow",
    "sg:phone":"+49 3337/41174",
    "sg:postcode":"16230",
    "sg:province":"Brandenburg",
    "wof:name":"Uwe Richter",
    "wof:placetype":"venue"
},
  "geometry": {"coordinates":[13.7084302902,52.7803115845],"type":"Point"}
}