{
  "type": "Feature",
  "properties": {
    "iso:country":"DE",
    "sg:address":"Karl-Marx-Str. 4",
    "sg:city":"Zwickau",
    "sg:postcode":"08066",
    "sg:province":"Sachsen",
    "wof:name":"Nemeth Industriemontagen Gmbh",
    "wof:placetype":"venue"
},
  "geometry": {"coordinates":[12.528673,50.737103],"type":"Point"}
}