{
  "type": "Feature",
  "properties": {
    "iso:country":"DE",
    "sg:address":"M\u00fchlenstr. 4",
    "sg:city":"Marktrodach",
    "sg:phone":"+49 9261/2347",
    "sg:postcode":"96364",
    "sg:province":"Bayern",
    "wof:name":"Hans Zinner Gmbh & Co. Kg",
    "wof:placetype":"venue"
},
  "geometry": {"coordinates":[11.392827034,50.2497215271],"type":"Point"}
}