{
  "type": "Feature",
  "properties": {
    "iso:country":"DE",
    "sg:address":"Werkstr. 523",
    "sg:city":"Schwerin",
    "sg:phone":"+49 385/644690",
    "sg:postcode":"19061",
    "sg:province":"Mecklenburg-Vorpommern",
    "wof:name":"Heinrich Schom\u00e4cker Gmbh",
    "wof:placetype":"venue"
},
  "geometry": {"coordinates":[11.3896312714,53.5739402771],"type":"Point"}
}