{
  "type": "Feature",
  "properties": {
    "iso:country":"DE",
    "sg:address":"Schl\u00fcterstr. 9",
    "sg:city":"Erfurt",
    "sg:phone":"+49 361/210910",
    "sg:postcode":"99089",
    "sg:province":"Th\u00fcringen",
    "wof:name":"Gastst\u00e4tte Rotplombe",
    "wof:placetype":"venue"
},
  "geometry": {"coordinates":[11.0232915878,50.9844398499],"type":"Point"}
}