{
  "type": "Feature",
  "properties": {
    "iso:country":"DE",
    "sg:address":"Goldfasanenweg 28",
    "sg:city":"K\u00f6ln",
    "sg:phone":"+49 221/5801856",
    "sg:postcode":"50829",
    "sg:province":"Nordrhein-Westfalen",
    "wof:name":"Bungarten Gmbh",
    "wof:placetype":"venue"
},
  "geometry": {"coordinates":[6.8876428604,50.9565849304],"type":"Point"}
}