{
  "type": "Feature",
  "properties": {
    "iso:country":"DE",
    "sg:address":"Zwischen den Br\u00fccken 8",
    "sg:city":"Buxtehude",
    "sg:phone":"+49 4161/54807",
    "sg:postcode":"21614",
    "sg:province":"Niedersachsen",
    "wof:name":"Entree Ihr Cafe",
    "wof:placetype":"venue"
},
  "geometry": {"coordinates":[9.6967754364,53.4750938416],"type":"Point"}
}