{
  "type": "Feature",
  "properties": {
    "iso:country":"DE",
    "sg:address":"Am M\u00fchlberg 12",
    "sg:city":"Langg\u00f6ns",
    "sg:phone":"+49 6403/71221",
    "sg:postcode":"35428",
    "sg:province":"Hessen",
    "wof:name":"S. Kober Krankengymnastik",
    "wof:placetype":"venue"
},
  "geometry": {"coordinates":[8.665667,50.496506],"type":"Point"}
}