{
  "type": "Feature",
  "properties": {
    "iso:country":"DE",
    "sg:address":"Hindenburgstr. 27 a",
    "sg:city":"Cadolzburg",
    "sg:phone":"+49 9103/2977",
    "sg:postcode":"90556",
    "sg:province":"Bayern",
    "wof:name":"H. Mayer",
    "wof:placetype":"venue"
},
  "geometry": {"coordinates":[10.8533229828,49.4573783875],"type":"Point"}
}