{
  "type": "Feature",
  "properties": {
    "iso:country":"DE",
    "sg:address":"Wildhagen 88",
    "sg:city":"K\u00fchrstedt",
    "sg:postcode":"27624",
    "sg:province":"Niedersachsen",
    "wof:name":"Schniedewind Holzbau Gmbh",
    "wof:placetype":"venue"
},
  "geometry": {"coordinates":[8.801116,53.577534],"type":"Point"}
}