{
  "type": "Feature",
  "properties": {
    "iso:country":"DE",
    "sg:address":"Karlstr. 32",
    "sg:city":"Ostfildern",
    "sg:phone":"+49 711/4587748",
    "sg:postcode":"73760",
    "sg:province":"Baden-W\u00fcrttemberg",
    "wof:name":"K. Schweizer",
    "wof:placetype":"venue"
},
  "geometry": {"coordinates":[9.2362947464,48.7176322937],"type":"Point"}
}