{
  "type": "Feature",
  "properties": {
    "iso:country":"DE",
    "sg:address":"Emster Str. 91",
    "sg:city":"Hagen",
    "sg:phone":"+49 2331/953411",
    "sg:postcode":"58093",
    "sg:province":"Nordrhein-Westfalen",
    "wof:name":"Emster Apotheke Christiane Gerber E. K.",
    "wof:placetype":"venue"
},
  "geometry": {"coordinates":[7.503723,51.353298],"type":"Point"}
}