{
  "type": "Feature",
  "properties": {
    "iso:country":"DE",
    "sg:address":"Rieslingstr. 20",
    "sg:city":"Erpel",
    "sg:phone":"+49 2644/800343",
    "sg:postcode":"53579",
    "sg:province":"Rheinland-Pfalz",
    "wof:name":"Gln German Local Net Ges. F\u00fcr Internet-kommunikation Mbh",
    "wof:placetype":"venue"
},
  "geometry": {"coordinates":[7.2362961769,50.5890045166],"type":"Point"}
}