{
  "type": "Feature",
  "properties": {
    "iso:country":"DE",
    "sg:address":"Hauptstr 13",
    "sg:city":"Lautersheim",
    "sg:phone":"+49 6351/43718",
    "sg:postcode":"67308",
    "sg:province":"Rheinland-Pfalz",
    "wof:name":"Alberts Tofuhaus",
    "wof:placetype":"venue"
},
  "geometry": {"coordinates":[8.0986375809,49.5868835449],"type":"Point"}
}