{
  "type": "Feature",
  "properties": {
    "iso:country":"DE",
    "sg:address":"Leonrodstr. 31/IV",
    "sg:city":"M\u00fcnchen",
    "sg:postcode":"80636",
    "sg:province":"Bayern",
    "wof:name":"Kovac Gmbh",
    "wof:placetype":"venue"
},
  "geometry": {"coordinates":[11.54088,48.151211],"type":"Point"}
}