{
  "type": "Feature",
  "properties": {
    "iso:country":"DE",
    "sg:address":"Annastr. 13",
    "sg:city":"Magdeburg",
    "sg:phone":"+49 391/7318302",
    "sg:postcode":"39108",
    "sg:province":"Sachsen-Anhalt",
    "wof:name":"Herta Fritz",
    "wof:placetype":"venue"
},
  "geometry": {"coordinates":[11.608259,52.132092],"type":"Point"}
}