{
  "type": "Feature",
  "properties": {
    "iso:country":"DE",
    "sg:address":"Schulstr. 9",
    "sg:city":"Pliening",
    "sg:postcode":"85652",
    "sg:province":"Bayern",
    "wof:name":"Maria Beitinger Gmbh",
    "wof:placetype":"venue"
},
  "geometry": {"coordinates":[11.7730035782,48.1876831055],"type":"Point"}
}