{
  "type": "Feature",
  "properties": {
    "iso:country":"DE",
    "sg:address":"Bruder-Konrad-Weg 7",
    "sg:city":"Bayerbach",
    "sg:phone":"+49 8532/1377",
    "sg:postcode":"94137",
    "sg:province":"Bayern",
    "wof:name":"Kath. \u00d6ffentliche B\u00fccherei Kath. Pfarrhaus",
    "wof:placetype":"venue"
},
  "geometry": {"coordinates":[13.145598,48.409592],"type":"Point"}
}