{
  "type": "Feature",
  "properties": {
    "iso:country":"DE",
    "sg:address":"Wildhagen 104",
    "sg:city":"Bielefeld",
    "sg:phone":"+49 521/103534",
    "sg:postcode":"33619",
    "sg:province":"Nordrhein-Westfalen",
    "wof:name":"Klaus Wellen Gmbh",
    "wof:placetype":"venue"
},
  "geometry": {"coordinates":[8.4740934372,52.0554466248],"type":"Point"}
}