{
  "type": "Feature",
  "properties": {
    "iso:country":"DE",
    "sg:address":"Alte Landstr. 26",
    "sg:city":"D\u00fcsseldorf",
    "sg:phone":"+49 211/403283",
    "sg:postcode":"40489",
    "sg:province":"Nordrhein-Westfalen",
    "wof:name":"T. Homberg",
    "wof:placetype":"venue"
},
  "geometry": {"coordinates":[6.739133,51.289909],"type":"Point"}
}