{
  "type": "Feature",
  "properties": {
    "iso:country":"DE",
    "sg:address":"Grohner Str. 18",
    "sg:city":"Bremen",
    "sg:phone":"+49 421/3808035",
    "sg:postcode":"28217",
    "sg:province":"Bremen",
    "wof:name":"Wiechmann & Co. Kg",
    "wof:placetype":"venue"
},
  "geometry": {"coordinates":[8.7890605927,53.0959281921],"type":"Point"}
}