{
  "type": "Feature",
  "properties": {
    "iso:country":"DE",
    "sg:address":"B\u00e4renreiterweg 2a",
    "sg:city":"Kassel",
    "sg:phone":"+49 561",
    "sg:postcode":"34131",
    "sg:province":"Hessen",
    "wof:name":"Rope-gbr",
    "wof:placetype":"venue"
},
  "geometry": {"coordinates":[9.4314527512,51.3039093018],"type":"Point"}
}