{
  "type": "Feature",
  "properties": {
    "iso:country":"DE",
    "sg:address":"Birkenweg 20",
    "sg:city":"L\u00fcbstorf",
    "sg:phone":"+49 3867/343",
    "sg:postcode":"19069",
    "sg:province":"Mecklenburg-Vorpommern",
    "wof:name":"Uwe Bessin",
    "wof:placetype":"venue"
},
  "geometry": {"coordinates":[11.408290863,53.7260513306],"type":"Point"}
}