{
  "type": "Feature",
  "properties": {
    "iso:country":"DE",
    "sg:address":"Parkallee 25",
    "sg:city":"Hamburg",
    "sg:phone":"+49 40/4103610",
    "sg:postcode":"20144",
    "sg:province":"Hamburg",
    "wof:name":"Otmar Kury Rechtsanwalt",
    "wof:placetype":"venue"
},
  "geometry": {"coordinates":[9.9837141037,53.5753250122],"type":"Point"}
}