{
  "type": "Feature",
  "properties": {
    "iso:country":"DE",
    "sg:address":"Breite Herzogstr. 18",
    "sg:city":"Wolfenb\u00fcttel",
    "sg:phone":"+49 5331/2388",
    "sg:postcode":"38300",
    "sg:province":"Niedersachsen",
    "wof:name":"Kornblume Naturkost Inh. Christine Raedler",
    "wof:placetype":"venue"
},
  "geometry": {"coordinates":[10.5401105881,52.1643218994],"type":"Point"}
}