{
  "type": "Feature",
  "properties": {
    "iso:country":"DE",
    "sg:address":"Stra\u00dfe der Jugend 2",
    "sg:city":"Hermersdorf/Obersdorf",
    "sg:phone":"+49 33432/8734",
    "sg:postcode":"15374",
    "sg:province":"Brandenburg",
    "wof:name":"Jugendherberge M\u00fcnchehofe",
    "wof:placetype":"venue"
},
  "geometry": {"coordinates":[14.1439313889,52.5017471313],"type":"Point"}
}