{
  "type": "Feature",
  "properties": {
    "iso:country":"DE",
    "sg:address":"Von-Beckerath-Platz 4",
    "sg:city":"Krefeld",
    "sg:phone":"+49 2151/58680",
    "sg:postcode":"47799",
    "sg:province":"Nordrhein-Westfalen",
    "wof:name":"Fiducia Verm\u00f6gensverwaltungs Gmbh",
    "wof:placetype":"venue"
},
  "geometry": {"coordinates":[6.574005127,51.336479187],"type":"Point"}
}