{
  "type": "Feature",
  "properties": {
    "iso:country":"DE",
    "sg:address":"Wevelinghover Str. 149",
    "sg:city":"Nettetal",
    "sg:phone":"+49 2153/60196",
    "sg:postcode":"41334",
    "sg:province":"Nordrhein-Westfalen",
    "wof:name":"M. Strentz",
    "wof:placetype":"venue"
},
  "geometry": {"coordinates":[6.2665948868,51.324306488],"type":"Point"}
}