{
  "type": "Feature",
  "properties": {
    "iso:country":"DE",
    "sg:address":"Am Sandforter Bach",
    "sg:city":"Olfen",
    "sg:phone":"+49 2595/961581",
    "sg:postcode":"59399",
    "sg:province":"Nordrhein-Westfalen",
    "wof:name":"Heilpflanzen Haus Sandfort Verwaltung Gmbh",
    "wof:placetype":"venue"
},
  "geometry": {"coordinates":[7.41169,51.700336],"type":"Point"}
}