{
  "type": "Feature",
  "properties": {
    "iso:country":"DE",
    "sg:address":"Hagsche Str. 45",
    "sg:city":"Kleve",
    "sg:phone":"+49 2821/23570",
    "sg:postcode":"47533",
    "sg:province":"Nordrhein-Westfalen",
    "wof:name":"Gardinen Fruhen",
    "wof:placetype":"venue"
},
  "geometry": {"coordinates":[6.135244,51.784462],"type":"Point"}
}