{
  "type": "Feature",
  "properties": {
    "iso:country":"DE",
    "sg:address":"H\u00f6rsterstr. 17",
    "sg:city":"M\u00fcnster",
    "sg:phone":"+49 251/43187",
    "sg:postcode":"48143",
    "sg:province":"Nordrhein-Westfalen",
    "wof:name":"Extraweit - W. Baans E. Kfm.",
    "wof:placetype":"venue"
},
  "geometry": {"coordinates":[7.6310372353,51.9647636414],"type":"Point"}
}