{
  "type": "Feature",
  "properties": {
    "iso:country":"DE",
    "sg:address":"Viersener Str. 23",
    "sg:city":"M\u00f6nchengladbach",
    "sg:phone":"+49 2161/207429",
    "sg:postcode":"41061",
    "sg:province":"Nordrhein-Westfalen",
    "wof:name":"Rainer Wassong Ergotherapie",
    "wof:placetype":"venue"
},
  "geometry": {"coordinates":[6.433014,51.195873],"type":"Point"}
}