{
  "type": "Feature",
  "properties": {
    "iso:country":"DE",
    "sg:address":"Amtsgerichtsstr. 29",
    "sg:city":"Kronach",
    "sg:phone":"+49 9261/3961",
    "sg:postcode":"96317",
    "sg:province":"Bayern",
    "wof:name":"Walter Wicklein",
    "wof:placetype":"venue"
},
  "geometry": {"coordinates":[11.3244686127,50.2421913147],"type":"Point"}
}