{
  "type": "Feature",
  "properties": {
    "iso:country":"DE",
    "sg:address":"Dorfstr. 40",
    "sg:city":"Bargstedt",
    "sg:phone":"+49 4392/89677",
    "sg:postcode":"24793",
    "sg:province":"Schleswig-Holstein",
    "wof:name":"Peters Grill",
    "wof:placetype":"venue"
},
  "geometry": {"coordinates":[9.7666158676,54.1624984741],"type":"Point"}
}