{
  "type": "Feature",
  "properties": {
    "iso:country":"DE",
    "sg:address":"Martin-Luther-Platz 15",
    "sg:city":"Schwabach",
    "sg:phone":"+49 9122/86622",
    "sg:postcode":"91126",
    "sg:province":"Bayern",
    "wof:name":"Pilsstube Wei\u00dfes Ro\u00df",
    "wof:placetype":"venue"
},
  "geometry": {"coordinates":[11.022069931,49.3288497925],"type":"Point"}
}