{
  "type": "Feature",
  "properties": {
    "iso:country":"DE",
    "sg:address":"Hauptstr. 75",
    "sg:city":"Rotta",
    "sg:phone":"+49 34921/20513",
    "sg:postcode":"06773",
    "sg:province":"Sachsen-Anhalt",
    "wof:name":"Realbau Rotta Gmbh",
    "wof:placetype":"venue"
},
  "geometry": {"coordinates":[12.607214,51.762653],"type":"Point"}
}