{
  "type": "Feature",
  "properties": {
    "iso:country":"DE",
    "sg:address":"Rebenweg 1",
    "sg:city":"Barsinghausen",
    "sg:phone":"+49 511/2707370",
    "sg:postcode":"30890",
    "sg:province":"Niedersachsen",
    "wof:name":"Zanox.de - Das Europ\u00e4ische Partnerprogramm",
    "wof:placetype":"venue"
},
  "geometry": {"coordinates":[9.411506,52.327019],"type":"Point"}
}