{
  "type": "Feature",
  "properties": {
    "iso:country":"DE",
    "sg:address":"Osemundstra\u00dfe 27-29",
    "sg:city":"Kierspe",
    "sg:phone":"+49 2359/914050",
    "sg:postcode":"58566",
    "sg:province":"Nordrhein-Westfalen",
    "wof:name":"Walter Goletz Gmbh",
    "wof:placetype":"venue"
},
  "geometry": {"coordinates":[7.5945601463,51.1232757568],"type":"Point"}
}