{
  "type": "Feature",
  "properties": {
    "iso:country":"DE",
    "sg:address":"Badwiesenstr. 16",
    "sg:city":"Rudersberg",
    "sg:phone":"+49 7183/8960",
    "sg:postcode":"73635",
    "sg:province":"Baden-W\u00fcrttemberg",
    "wof:name":"Kurt Abele Architekt",
    "wof:placetype":"venue"
},
  "geometry": {"coordinates":[9.530139,48.888657],"type":"Point"}
}