{
  "type": "Feature",
  "properties": {
    "iso:country":"DE",
    "sg:address":"Hauptstr. 47",
    "sg:city":"Hirschfeld",
    "sg:phone":"+49 37607/5063",
    "sg:postcode":"08144",
    "sg:province":"Sachsen",
    "wof:name":"Hans-joachim Dietz",
    "wof:placetype":"venue"
},
  "geometry": {"coordinates":[12.4569549561,50.6249313354],"type":"Point"}
}