{
  "type": "Feature",
  "properties": {
    "iso:country":"DE",
    "sg:address":"Industriestr. 35",
    "sg:city":"Rheinbach",
    "sg:phone":"+49 2226/4426",
    "sg:postcode":"53359",
    "sg:province":"Nordrhein-Westfalen",
    "wof:name":"F. Hommes",
    "wof:placetype":"venue"
},
  "geometry": {"coordinates":[6.95144701,50.637714386],"type":"Point"}
}