{
  "type": "Feature",
  "properties": {
    "iso:country":"DE",
    "sg:address":"Neuhau\u00dfstr. 6",
    "sg:city":"Frankfurt",
    "sg:phone":"+49 69/551488",
    "sg:postcode":"60322",
    "sg:province":"Hessen",
    "wof:name":"Ausgleichsvereinigung Verlage E. V.",
    "wof:placetype":"venue"
},
  "geometry": {"coordinates":[8.6743602753,50.1303977966],"type":"Point"}
}