{
  "type": "Feature",
  "properties": {
    "iso:country":"DE",
    "sg:address":"Sanderring 22",
    "sg:city":"W\u00fcrzburg",
    "sg:phone":"+49 931/571737",
    "sg:postcode":"97070",
    "sg:province":"Bayern",
    "wof:name":"A. Freienstein Immobiliemakler",
    "wof:placetype":"venue"
},
  "geometry": {"coordinates":[9.9290180206,49.7865409851],"type":"Point"}
}