{
  "type": "Feature",
  "properties": {
    "iso:country":"DE",
    "sg:address":"Bismarckstr. 34",
    "sg:city":"Offenbach",
    "sg:phone":"+49 69/812113",
    "sg:postcode":"63065",
    "sg:province":"Hessen",
    "wof:name":"Frank Hermann",
    "wof:placetype":"venue"
},
  "geometry": {"coordinates":[8.7724666595,50.1017723083],"type":"Point"}
}