{
  "type": "Feature",
  "properties": {
    "iso:country":"DE",
    "sg:address":"Lindenstr. 12",
    "sg:city":"Lorsch",
    "sg:phone":"+49 6251/52400",
    "sg:postcode":"64653",
    "sg:province":"Hessen",
    "wof:name":"M\u00f6belhaus G\u00e4rtner Gmbh",
    "wof:placetype":"venue"
},
  "geometry": {"coordinates":[8.566917,49.658806],"type":"Point"}
}