{
  "type": "Feature",
  "properties": {
    "iso:country":"DE",
    "sg:address":"Schwanenstr. 43",
    "sg:city":"Mannheim",
    "sg:phone":"+49 621/7900820",
    "sg:postcode":"68259",
    "sg:province":"Baden-W\u00fcrttemberg",
    "wof:name":"Lummerland Naturkost",
    "wof:placetype":"venue"
},
  "geometry": {"coordinates":[8.526843071,49.4887886047],"type":"Point"}
}