{
  "type": "Feature",
  "properties": {
    "iso:country":"DE",
    "sg:address":"Busmannstr. 64",
    "sg:city":"Kevelaer",
    "sg:phone":"+49 2832/5010",
    "sg:postcode":"47623",
    "sg:province":"Nordrhein-Westfalen",
    "wof:name":"Volksbank Goch-kevelaer Eg",
    "wof:placetype":"venue"
},
  "geometry": {"coordinates":[6.244899,51.581146],"type":"Point"}
}