{
  "type": "Feature",
  "properties": {
    "iso:country":"DE",
    "sg:address":"Bundesstr. 96",
    "sg:city":"Gundelfingen",
    "sg:phone":"+49 761/585059",
    "sg:postcode":"79194",
    "sg:province":"Baden-W\u00fcrttemberg",
    "wof:name":"Radsport Aktuell K\u00f6rber Gmbh",
    "wof:placetype":"venue"
},
  "geometry": {"coordinates":[7.8704419136,48.0450248718],"type":"Point"}
}