{
  "type": "Feature",
  "properties": {
    "iso:country":"DE",
    "sg:address":"Schlachtstr. 8",
    "sg:city":"Jever",
    "sg:phone":"+49 4461/912255",
    "sg:postcode":"26441",
    "sg:province":"Niedersachsen",
    "wof:name":"Brillen Babatz Gmbh",
    "wof:placetype":"venue"
},
  "geometry": {"coordinates":[7.9033718109,53.5751113892],"type":"Point"}
}