{
  "type": "Feature",
  "properties": {
    "iso:country":"DE",
    "sg:address":"Burgstr. 69",
    "sg:city":"Salzwedel",
    "sg:phone":"+49 3901/83750",
    "sg:postcode":"29410",
    "sg:province":"Sachsen-Anhalt",
    "wof:name":"Wilfried Vick Bernhard Harder Reinhard Eckert",
    "wof:placetype":"venue"
},
  "geometry": {"coordinates":[11.1518917084,52.8502235413],"type":"Point"}
}