{
  "type": "Feature",
  "properties": {
    "iso:country":"DE",
    "sg:address":"Kehrstr. 3",
    "sg:city":"Senheim",
    "sg:phone":"+49 2673/4230",
    "sg:postcode":"56820",
    "sg:province":"Rheinland-Pfalz",
    "wof:name":"T. Zenz",
    "wof:placetype":"venue"
},
  "geometry": {"coordinates":[7.203213,50.08593],"type":"Point"}
}