{
  "type": "Feature",
  "properties": {
    "iso:country":"DE",
    "sg:address":"R\u00f6merstr. 93",
    "sg:city":"Herzogenrath",
    "sg:phone":"+49 2406/63366",
    "sg:postcode":"52134",
    "sg:province":"Nordrhein-Westfalen",
    "wof:name":"W. Schmitz",
    "wof:placetype":"venue"
},
  "geometry": {"coordinates":[6.108853817,50.8839302063],"type":"Point"}
}