{
  "type": "Feature",
  "properties": {
    "iso:country":"DE",
    "sg:address":"Goetheplatz 9",
    "sg:city":"Frankfurt",
    "sg:phone":"+49 69/283699",
    "sg:postcode":"60313",
    "sg:province":"Hessen",
    "wof:name":"Kurt Wiegand Kg",
    "wof:placetype":"venue"
},
  "geometry": {"coordinates":[8.6760864258,50.1133003235],"type":"Point"}
}