{
  "type": "Feature",
  "properties": {
    "iso:country":"DE",
    "sg:address":"Eggenbergstr. 18",
    "sg:city":"Buttenheim",
    "sg:phone":"+49 9545/8219",
    "sg:postcode":"96155",
    "sg:province":"Bayern",
    "wof:name":"Ortwin Gries",
    "wof:placetype":"venue"
},
  "geometry": {"coordinates":[11.030503273,49.8082695007],"type":"Point"}
}