{
  "type": "Feature",
  "properties": {
    "iso:country":"DE",
    "sg:address":"Usedomer Str. 40",
    "sg:city":"Henstedt-Ulzburg",
    "sg:postcode":"24558",
    "sg:province":"Schleswig-Holstein",
    "wof:name":"Conform Unternehmens- Beratung Gmbh",
    "wof:placetype":"venue"
},
  "geometry": {"coordinates":[9.97475,53.78561],"type":"Point"}
}