{
  "type": "Feature",
  "properties": {
    "iso:country":"DE",
    "sg:address":"Ammergaustr. 52-56",
    "sg:city":"Oldenburg",
    "sg:phone":"+49 441/31701",
    "sg:postcode":"26123",
    "sg:province":"Niedersachsen",
    "wof:name":"Blumen Buhr Amalienhof",
    "wof:placetype":"venue"
},
  "geometry": {"coordinates":[8.230226,53.161804],"type":"Point"}
}