{
  "type": "Feature",
  "properties": {
    "iso:country":"DE",
    "sg:address":"Langer Weg 50",
    "sg:city":"Regensburg",
    "sg:phone":"+49 941/949233",
    "sg:postcode":"93055",
    "sg:province":"Bayern",
    "wof:name":"Ciao Ciao",
    "wof:placetype":"venue"
},
  "geometry": {"coordinates":[12.1367368698,48.9846153259],"type":"Point"}
}