{
  "type": "Feature",
  "properties": {
    "iso:country":"DE",
    "sg:address":"Siegbertstr. 8",
    "sg:city":"Speyer",
    "sg:phone":"+49 6232/78557",
    "sg:postcode":"67346",
    "sg:province":"Rheinland-Pfalz",
    "wof:name":"Bader Gmbh",
    "wof:placetype":"venue"
},
  "geometry": {"coordinates":[8.4305753708,49.3250160217],"type":"Point"}
}