{
  "type": "Feature",
  "properties": {
    "iso:country":"DE",
    "sg:address":"K\u00f6lnstr. 38",
    "sg:city":"Sankt Augustin",
    "sg:phone":"+49 2241/923941",
    "sg:postcode":"53757",
    "sg:province":"Nordrhein-Westfalen",
    "wof:name":"Volksf\u00fcrsorge Deutsche Lebensversicherung Ag",
    "wof:placetype":"venue"
},
  "geometry": {"coordinates":[7.1732831001,50.763507843],"type":"Point"}
}