{
  "type": "Feature",
  "properties": {
    "iso:country":"DE",
    "sg:address":"R\u00f6genweg 49",
    "sg:city":"Hamburg",
    "sg:phone":"+49 40/6038699",
    "sg:postcode":"22359",
    "sg:province":"Hamburg",
    "wof:name":"Christina Lindau Hebamme",
    "wof:placetype":"venue"
},
  "geometry": {"coordinates":[10.15167,53.655884],"type":"Point"}
}