{
  "type": "Feature",
  "properties": {
    "iso:country":"DE",
    "sg:address":"Kalkstr. 18",
    "sg:city":"Bitburg",
    "sg:postcode":"54622",
    "sg:province":"Rheinland-Pfalz",
    "wof:name":"Eifel Incoming, Touristik-marketing Und -management",
    "wof:placetype":"venue"
},
  "geometry": {"coordinates":[6.5745239258,49.9959106445],"type":"Point"}
}