{
  "type": "Feature",
  "properties": {
    "iso:country":"DE",
    "sg:address":"Osterend 2",
    "sg:city":"Petershagen",
    "sg:phone":"+49 5702/1027",
    "sg:postcode":"32469",
    "sg:province":"Nordrhein-Westfalen",
    "wof:name":"Heinrich Lange",
    "wof:placetype":"venue"
},
  "geometry": {"coordinates":[9.042674,52.369102],"type":"Point"}
}