{
  "type": "Feature",
  "properties": {
    "iso:country":"DE",
    "sg:address":"Gro\u00dfe Schulgasse 18-19",
    "sg:city":"Magdeburg",
    "sg:phone":"+49 391/6345007",
    "sg:postcode":"39116",
    "sg:province":"Sachsen-Anhalt",
    "wof:name":"Aue Bestattungen",
    "wof:placetype":"venue"
},
  "geometry": {"coordinates":[11.576439,52.086376],"type":"Point"}
}