{
  "type": "Feature",
  "properties": {
    "iso:country":"DE",
    "sg:address":"Hermann-B\u00f6se-Str. 21",
    "sg:city":"Bremen",
    "sg:postcode":"28209",
    "sg:province":"Bremen",
    "wof:name":"Joh. Freese",
    "wof:placetype":"venue"
},
  "geometry": {"coordinates":[8.820571,53.08395],"type":"Point"}
}