{
  "type": "Feature",
  "properties": {
    "iso:country":"DE",
    "sg:address":"Schobserstr. 10",
    "sg:city":"M\u00fcnchen",
    "sg:phone":"+49 89/15703912",
    "sg:postcode":"80638",
    "sg:province":"Bayern",
    "wof:name":"Dr. Klaus Castell Patentanwalt",
    "wof:placetype":"venue"
},
  "geometry": {"coordinates":[11.5163040161,48.1665077209],"type":"Point"}
}