{
  "type": "Feature",
  "properties": {
    "iso:country":"DE",
    "sg:address":"Moorenstr. 23",
    "sg:city":"Essen",
    "sg:phone":"+49 201/778159",
    "sg:postcode":"45131",
    "sg:province":"Nordrhein-Westfalen",
    "wof:name":"B. S. G. Buchmacher- Service Gmbh",
    "wof:placetype":"venue"
},
  "geometry": {"coordinates":[7.000138,51.433273],"type":"Point"}
}