{
  "type": "Feature",
  "properties": {
    "iso:country":"DE",
    "sg:address":"Englerstr. 28",
    "sg:city":"Heidelberg",
    "sg:phone":"+49 6221/451448",
    "sg:postcode":"69126",
    "sg:province":"Baden-W\u00fcrttemberg",
    "wof:name":"Ceos Corrected Electron",
    "wof:placetype":"venue"
},
  "geometry": {"coordinates":[8.6774682999,49.3669281006],"type":"Point"}
}