{
  "type": "Feature",
  "properties": {
    "iso:country":"DE",
    "sg:address":"Zum Wasserwerk 29",
    "sg:city":"D\u00f6lzig",
    "sg:phone":"+49 34205/87942",
    "sg:postcode":"04430",
    "wof:name":"Konsum-verkaufsstelle",
    "wof:placetype":"venue"
},
  "geometry": {"coordinates":[12.2096595764,51.3538589478],"type":"Point"}
}