{
  "type": "Feature",
  "properties": {
    "iso:country":"DE",
    "sg:address":"Wingertstr. 3",
    "sg:city":"Dreieich",
    "sg:phone":"+49 6103/65980",
    "sg:postcode":"63303",
    "sg:province":"Hessen",
    "wof:name":"Gz Fliesen Gmbh",
    "wof:placetype":"venue"
},
  "geometry": {"coordinates":[8.694188118,50.0185852051],"type":"Point"}
}