{
  "type": "Feature",
  "properties": {
    "iso:country":"DE",
    "sg:address":"Hollerweg 4",
    "sg:city":"Brunnthal",
    "sg:postcode":"85649",
    "sg:province":"Bayern",
    "wof:name":"Escon Management Gmbh",
    "wof:placetype":"venue"
},
  "geometry": {"coordinates":[11.7151470184,47.987197876],"type":"Point"}
}