{
  "type": "Feature",
  "properties": {
    "iso:country":"DE",
    "sg:address":"Lerchenstr. 44",
    "sg:city":"Greven",
    "sg:postcode":"48268",
    "sg:province":"Nordrhein-Westfalen",
    "wof:name":"Kalinowski Dienstleistungen Ohg",
    "wof:placetype":"venue"
},
  "geometry": {"coordinates":[7.632796,52.086452],"type":"Point"}
}