{
  "type": "Feature",
  "properties": {
    "iso:country":"DE",
    "sg:address":"Rotlaym\u00fchle",
    "sg:city":"Bad Kreuznach",
    "sg:postcode":"55545",
    "sg:province":"Rheinland-Pfalz",
    "wof:name":"Allit Ag",
    "wof:placetype":"venue"
},
  "geometry": {"coordinates":[7.874645,49.860184],"type":"Point"}
}