{
  "type": "Feature",
  "properties": {
    "iso:country":"DE",
    "sg:address":"Hammer Str. 371",
    "sg:city":"M\u00fcnster",
    "sg:phone":"+49 251/7636040",
    "sg:postcode":"48153",
    "sg:province":"Nordrhein-Westfalen",
    "wof:name":"Fre\u00dfnapf Tiernahrung M\u00fcnster Ralf Schnitker",
    "wof:placetype":"venue"
},
  "geometry": {"coordinates":[7.628816,51.927673],"type":"Point"}
}