{
  "type": "Feature",
  "properties": {
    "iso:country":"DE",
    "sg:address":"Im Johannesberg 8",
    "sg:city":"Mainz",
    "sg:phone":"+49 6131/883687",
    "sg:postcode":"55130",
    "sg:province":"Rheinland-Pfalz",
    "wof:name":"W & W Edv-service Gmbh",
    "wof:placetype":"venue"
},
  "geometry": {"coordinates":[8.3046369553,49.9585494995],"type":"Point"}
}