{
  "type": "Feature",
  "properties": {
    "iso:country":"DE",
    "sg:address":"Hirtel 19",
    "sg:city":"Kappelrodeck",
    "sg:phone":"+49 7842/2126",
    "sg:postcode":"77876",
    "sg:province":"Baden-W\u00fcrttemberg",
    "wof:name":"Rudolf Kohler Obstanbau",
    "wof:placetype":"venue"
},
  "geometry": {"coordinates":[8.1142072678,48.5995063782],"type":"Point"}
}