{
  "type": "Feature",
  "properties": {
    "iso:country":"DE",
    "sg:address":"Fritz-Triddelfitz-Weg 2",
    "sg:city":"Rostock",
    "sg:phone":"+49 381/80880",
    "sg:postcode":"18069",
    "sg:province":"Mecklenburg-Vorpommern",
    "wof:name":"Hotel-restaurant Elbotel",
    "wof:placetype":"venue"
},
  "geometry": {"coordinates":[12.0874214172,54.1036376953],"type":"Point"}
}