{
  "type": "Feature",
  "properties": {
    "iso:country":"DE",
    "sg:address":"Justus-von-Liebig-Str. 6",
    "sg:city":"Bruckm\u00fchl",
    "sg:phone":"+49 8061/2420",
    "sg:postcode":"83052",
    "sg:province":"Bayern",
    "wof:name":"Katholisches Pfarramt St. Korbinian",
    "wof:placetype":"venue"
},
  "geometry": {"coordinates":[11.9686260223,47.8735084534],"type":"Point"}
}