{
  "type": "Feature",
  "properties": {
    "iso:country":"DE",
    "sg:address":"Tiroler Str. 6",
    "sg:city":"Dortmund",
    "sg:phone":"+49 231/737744",
    "sg:postcode":"44229",
    "sg:province":"Nordrhein-Westfalen",
    "wof:name":"Michael Br\u00fchmann & Wrenger",
    "wof:placetype":"venue"
},
  "geometry": {"coordinates":[7.460767,51.461327],"type":"Point"}
}