{
  "type": "Feature",
  "properties": {
    "iso:country":"DE",
    "sg:address":"Lange Str. 92",
    "sg:city":"Effelder",
    "sg:phone":"+49 36075/54386",
    "sg:postcode":"37359",
    "sg:province":"Th\u00fcringen",
    "wof:name":"Eberhard Beau Gmbh",
    "wof:placetype":"venue"
},
  "geometry": {"coordinates":[10.25045,51.242611],"type":"Point"}
}