{
  "type": "Feature",
  "properties": {
    "iso:country":"DE",
    "sg:address":"Am Brambusch 2",
    "sg:city":"L\u00fcnen",
    "sg:phone":"+49 231/877787",
    "sg:postcode":"44536",
    "sg:province":"Nordrhein-Westfalen",
    "wof:name":"Klaus Peter Appel Gmbh",
    "wof:placetype":"venue"
},
  "geometry": {"coordinates":[7.4570431709,51.6032791138],"type":"Point"}
}