{
  "type": "Feature",
  "properties": {
    "iso:country":"DE",
    "sg:address":"B\u00fcrgerhaus",
    "sg:city":"Schlitz",
    "sg:postcode":"36110",
    "sg:province":"Hessen",
    "wof:name":"Stadtb\u00fccherei",
    "wof:placetype":"venue"
},
  "geometry": {"coordinates":[9.562918,50.673199],"type":"Point"}
}