{
  "type": "Feature",
  "properties": {
    "iso:country":"DE",
    "sg:address":"Hasselbeckstr. 57",
    "sg:city":"D\u00fcsseldorf",
    "sg:phone":"+49 211/287781",
    "sg:postcode":"40625",
    "sg:province":"Nordrhein-Westfalen",
    "wof:name":"Gerd Macholz Schaufenstergestaltung",
    "wof:placetype":"venue"
},
  "geometry": {"coordinates":[6.8548750877,51.2393913269],"type":"Point"}
}