{
  "type": "Feature",
  "properties": {
    "iso:country":"DE",
    "sg:address":"Gewerbestr. 5",
    "sg:city":"Haag",
    "sg:phone":"+49 8072/91980",
    "sg:postcode":"83527",
    "sg:province":"Bayern",
    "wof:name":"Richard Kohlert Gmbh",
    "wof:placetype":"venue"
},
  "geometry": {"coordinates":[12.143406868,48.1700363159],"type":"Point"}
}