{
  "type": "Feature",
  "properties": {
    "iso:country":"DE",
    "sg:address":"Daimlerstr. 5",
    "sg:city":"Enger",
    "sg:phone":"+49 5224/790502",
    "sg:postcode":"32130",
    "sg:province":"Nordrhein-Westfalen",
    "wof:name":"Schuf N\u00e4htechnik Gmbh",
    "wof:placetype":"venue"
},
  "geometry": {"coordinates":[8.566108,52.148438],"type":"Point"}
}