{
  "type": "Feature",
  "properties": {
    "iso:country":"DE",
    "sg:address":"Hauptstr. 52",
    "sg:city":"Lilienthal",
    "sg:postcode":"28865",
    "sg:province":"Niedersachsen",
    "wof:name":"Erika Georg",
    "wof:placetype":"venue"
},
  "geometry": {"coordinates":[8.9059000015,53.1402740479],"type":"Point"}
}