{
  "type": "Feature",
  "properties": {
    "iso:country":"DE",
    "sg:address":"Hallwanger Str. 53",
    "sg:city":"Prien",
    "sg:phone":"+49 8051/2336",
    "sg:postcode":"83209",
    "sg:province":"Bayern",
    "wof:name":"Metzgerei Moritz Gmbh",
    "wof:placetype":"venue"
},
  "geometry": {"coordinates":[12.3467140198,47.8640174866],"type":"Point"}
}