{
  "type": "Feature",
  "properties": {
    "iso:country":"DE",
    "sg:address":"Steinstr. 32",
    "sg:city":"Pattensen",
    "sg:phone":"+49 5101/84787",
    "sg:postcode":"30982",
    "sg:province":"Niedersachsen",
    "wof:name":"Physio-care Medical Vertrieb Gmbh",
    "wof:placetype":"venue"
},
  "geometry": {"coordinates":[9.7619161606,52.263217926],"type":"Point"}
}