{
  "type": "Feature",
  "properties": {
    "iso:country":"DE",
    "sg:address":"Marktplatz 15",
    "sg:city":"Untergriesbach",
    "sg:phone":"+49 8593/275",
    "sg:postcode":"94107",
    "sg:province":"Bayern",
    "wof:name":"Anna Seibold",
    "wof:placetype":"venue"
},
  "geometry": {"coordinates":[13.6671028137,48.5733261108],"type":"Point"}
}