{
  "type": "Feature",
  "properties": {
    "iso:country":"DE",
    "sg:address":"Bahnhofstr. 28",
    "sg:city":"Mainburg",
    "sg:phone":"+49 8751/1408",
    "sg:postcode":"84048",
    "sg:province":"Bayern",
    "wof:name":"H. Amberger",
    "wof:placetype":"venue"
},
  "geometry": {"coordinates":[11.7802028656,48.6412658691],"type":"Point"}
}