{
  "type": "Feature",
  "properties": {
    "iso:country":"DE",
    "sg:address":"Westenhellweg 22",
    "sg:city":"Dortmund",
    "sg:phone":"+49 231/9142477",
    "sg:postcode":"44137",
    "sg:province":"Nordrhein-Westfalen",
    "wof:name":"Biba & Pariscop Daub Gmbh",
    "wof:placetype":"venue"
},
  "geometry": {"coordinates":[7.465221,51.51421],"type":"Point"}
}