{
  "type": "Feature",
  "properties": {
    "iso:country":"DE",
    "sg:address":"Rothenbaumchaussee 80",
    "sg:city":"Hamburg",
    "sg:phone":"+49 40/417102",
    "sg:postcode":"20148",
    "sg:province":"Hamburg",
    "wof:name":"Aldebaran Meeresforschungs- Und Medienproduktions Gmbh",
    "wof:placetype":"venue"
},
  "geometry": {"coordinates":[9.989107132,53.5720329285],"type":"Point"}
}