{
  "type": "Feature",
  "properties": {
    "iso:country":"DE",
    "sg:address":"Erbprinzenstr. 18",
    "sg:city":"Freiburg",
    "sg:phone":"+49 761/30837",
    "sg:postcode":"79098",
    "sg:province":"Baden-W\u00fcrttemberg",
    "wof:name":"Konto Wirtschafts- Und Beratungsdienste Steuer-",
    "wof:placetype":"venue"
},
  "geometry": {"coordinates":[7.8445730209,47.9920349121],"type":"Point"}
}