{
  "type": "Feature",
  "properties": {
    "iso:country":"DE",
    "sg:address":"Alte Landstr. 51a",
    "sg:city":"Bargteheide",
    "sg:phone":"+49 4532/6237",
    "sg:postcode":"22941",
    "sg:province":"Schleswig-Holstein",
    "wof:name":"G\u00fcnter Hubert",
    "wof:placetype":"venue"
},
  "geometry": {"coordinates":[10.256378,53.728588],"type":"Point"}
}