{
  "type": "Feature",
  "properties": {
    "iso:country":"DE",
    "sg:address":"Ravensberger Str. 8",
    "sg:city":"Vechta",
    "sg:phone":"+49 4441/2601",
    "sg:postcode":"49377",
    "sg:province":"Niedersachsen",
    "wof:name":"Franz Gerhards",
    "wof:placetype":"venue"
},
  "geometry": {"coordinates":[8.2940073013,52.7301292419],"type":"Point"}
}