{
  "type": "Feature",
  "properties": {
    "iso:country":"DE",
    "sg:address":"Hochstr. 35 - 37",
    "sg:city":"Gelsenkirchen",
    "sg:phone":"+49 209/37471",
    "sg:postcode":"45894",
    "sg:province":"Nordrhein-Westfalen",
    "wof:name":"Fischer Am Dom Gmbh & Co. Kg",
    "wof:placetype":"venue"
},
  "geometry": {"coordinates":[7.0520157814,51.5802345276],"type":"Point"}
}