{
  "type": "Feature",
  "properties": {
    "iso:country":"DE",
    "sg:address":"Markt 18",
    "sg:city":"Frankenberg",
    "sg:postcode":"09669",
    "sg:province":"Sachsen",
    "wof:name":"Gerhard Puchta",
    "wof:placetype":"venue"
},
  "geometry": {"coordinates":[13.0325098038,50.9119033813],"type":"Point"}
}