{
  "type": "Feature",
  "properties": {
    "iso:country":"DE",
    "sg:address":"Am Osterberg 17",
    "sg:city":"Seevetal",
    "sg:phone":"+49 4185/2284",
    "sg:postcode":"21220",
    "sg:province":"Niedersachsen",
    "wof:name":"A. Steffen Innenarchitekt",
    "wof:placetype":"venue"
},
  "geometry": {"coordinates":[10.042119,53.341362],"type":"Point"}
}