{
  "type": "Feature",
  "properties": {
    "iso:country":"DE",
    "sg:address":"Rabensteig 9",
    "sg:city":"Wittenberge",
    "sg:phone":"+49 3877/60237",
    "sg:postcode":"19322",
    "sg:province":"Brandenburg",
    "wof:name":"Goedel & Partner Immobilien",
    "wof:placetype":"venue"
},
  "geometry": {"coordinates":[11.7342071533,53.0007400513],"type":"Point"}
}