{
  "type": "Feature",
  "properties": {
    "iso:country":"DE",
    "sg:address":"Wittelsbacherstr. 4 a",
    "sg:city":"Schwabach",
    "sg:phone":"+49 9122/5101",
    "sg:postcode":"91126",
    "sg:province":"Bayern",
    "wof:name":"Friedrich-boeckh-haus Sch\u00fcler- Und Lehrlingsheim",
    "wof:placetype":"venue"
},
  "geometry": {"coordinates":[11.0171480179,49.3274345398],"type":"Point"}
}