{
  "type": "Feature",
  "properties": {
    "iso:country":"DE",
    "sg:address":"Winkelhof 1",
    "sg:city":"Niedereschach",
    "sg:phone":"+49 7728/1872",
    "sg:postcode":"78078",
    "sg:province":"Baden-W\u00fcrttemberg",
    "wof:name":"Sperrholz Guth Holzwerkstoff",
    "wof:placetype":"venue"
},
  "geometry": {"coordinates":[8.483355,48.118492],"type":"Point"}
}