{
  "type": "Feature",
  "properties": {
    "iso:country":"DE",
    "sg:address":"Herweghstr. 1",
    "sg:city":"Stuttgart",
    "sg:postcode":"70197",
    "sg:province":"Baden-W\u00fcrttemberg",
    "wof:name":"Werkhaus Verwaltungs- Gmbh",
    "wof:placetype":"venue"
},
  "geometry": {"coordinates":[9.1526498795,48.7724685669],"type":"Point"}
}