{
  "type": "Feature",
  "properties": {
    "iso:country":"DE",
    "sg:address":"Kniggestr. 20",
    "sg:city":"M\u00fcnchen",
    "sg:phone":"+49 89/6609130",
    "sg:postcode":"81739",
    "sg:province":"Bayern",
    "wof:name":"M. J. Scholz Und Schaller Steuerberater",
    "wof:placetype":"venue"
},
  "geometry": {"coordinates":[11.6740922928,48.0820045471],"type":"Point"}
}