{
  "type": "Feature",
  "properties": {
    "iso:country":"DE",
    "sg:address":"Berghauser Str. 40",
    "sg:city":"Remscheid",
    "sg:postcode":"42859",
    "sg:province":"Nordrhein-Westfalen",
    "wof:name":"Berghauser Industrie- Beteiligungen Gmbh",
    "wof:placetype":"venue"
},
  "geometry": {"coordinates":[7.21163,51.170769],"type":"Point"}
}