{
  "type": "Feature",
  "properties": {
    "iso:country":"DE",
    "sg:address":"Hanns-Martin-Schleyer-Str. 20",
    "sg:city":"Willich",
    "sg:postcode":"47877",
    "sg:province":"Nordrhein-Westfalen",
    "wof:name":"Strauch Gmbh & Co. Kg",
    "wof:placetype":"venue"
},
  "geometry": {"coordinates":[6.517621,51.277023],"type":"Point"}
}