{
  "type": "Feature",
  "properties": {
    "iso:country":"DE",
    "sg:address":"Coswiger Landstr. 4",
    "sg:city":"Lutherstadt Wittenberg",
    "sg:phone":"+49 3491/610341",
    "sg:postcode":"06886",
    "sg:province":"Sachsen-Anhalt",
    "wof:name":"Wittenberger Fliesenhandel Gmbh",
    "wof:placetype":"venue"
},
  "geometry": {"coordinates":[12.6421127319,51.8666687012],"type":"Point"}
}