{
  "type": "Feature",
  "properties": {
    "iso:country":"DE",
    "sg:address":"Babel 7",
    "sg:city":"Preu\u00dfisch Oldendorf",
    "sg:phone":"+49 5742/1400",
    "sg:postcode":"32361",
    "sg:province":"Nordrhein-Westfalen",
    "wof:name":"Claus-hermann Meier Rechtsanwalt",
    "wof:placetype":"venue"
},
  "geometry": {"coordinates":[8.5279817581,52.2871932983],"type":"Point"}
}