{
  "type": "Feature",
  "properties": {
    "iso:country":"DE",
    "sg:address":"Implerstr. 71",
    "sg:city":"M\u00fcnchen",
    "sg:phone":"+49 89/763016",
    "sg:postcode":"81371",
    "sg:province":"Bayern",
    "wof:name":"Herbert Wetekamp Inh. Hannelore Schmidt",
    "wof:placetype":"venue"
},
  "geometry": {"coordinates":[11.5485897064,48.1165428162],"type":"Point"}
}