{
  "type": "Feature",
  "properties": {
    "iso:country":"DE",
    "sg:address":"Postfach 100350",
    "sg:city":"Heiligenhaus",
    "sg:phone":"+49 2056/20781",
    "sg:postcode":"42568",
    "sg:province":"Nordrhein-Westfalen",
    "wof:name":"Initiative F\u00fcr V\u00f6lker- Verst\u00e4ndigung E. V.",
    "wof:placetype":"venue"
},
  "geometry": {"coordinates":[6.9717202187,51.3265304565],"type":"Point"}
}