{
  "type": "Feature",
  "properties": {
    "iso:country":"DE",
    "sg:address":"Stuttgarter Str. 13",
    "sg:city":"Eislingen",
    "sg:phone":"+49 7161/821988",
    "sg:postcode":"73054",
    "sg:province":"Baden-W\u00fcrttemberg",
    "wof:name":"Bei Jasna",
    "wof:placetype":"venue"
},
  "geometry": {"coordinates":[9.704492569,48.6942329407],"type":"Point"}
}