{
  "type": "Feature",
  "properties": {
    "iso:country":"DE",
    "sg:address":"Lenbachplatz 27",
    "sg:city":"Schrobenhausen",
    "sg:phone":"+49 8252/81710",
    "sg:postcode":"86529",
    "sg:province":"Bayern",
    "wof:name":"Eiscafe Europa",
    "wof:placetype":"venue"
},
  "geometry": {"coordinates":[11.265028,48.560581],"type":"Point"}
}