{
  "type": "Feature",
  "properties": {
    "iso:country":"DE",
    "sg:address":"Zeitblomstr. 20",
    "sg:city":"Ulm",
    "sg:phone":"+49 731/9679810",
    "sg:postcode":"89073",
    "sg:province":"Baden-W\u00fcrttemberg",
    "wof:name":"Lux Gmbh",
    "wof:placetype":"venue"
},
  "geometry": {"coordinates":[9.9870166779,48.4024009705],"type":"Point"}
}