{
  "type": "Feature",
  "properties": {
    "iso:country":"DE",
    "sg:address":"Am B\u00fclten 1",
    "sg:city":"Braunschweig",
    "sg:phone":"+49 531/335489",
    "sg:postcode":"38106",
    "sg:province":"Niedersachsen",
    "wof:name":"Rolf Salomon Anlageberater",
    "wof:placetype":"venue"
},
  "geometry": {"coordinates":[10.5376749039,52.28074646],"type":"Point"}
}