{
  "type": "Feature",
  "properties": {
    "iso:country":"DE",
    "sg:address":"Stra\u00dfe der Jugend 10",
    "sg:city":"Oppach",
    "sg:phone":"+49 35872/38036",
    "sg:postcode":"02736",
    "sg:province":"Sachsen",
    "wof:name":"Tischlerei Loschke Gmbh",
    "wof:placetype":"venue"
},
  "geometry": {"coordinates":[14.50265,51.060905],"type":"Point"}
}