{
  "type": "Feature",
  "properties": {
    "iso:country":"DE",
    "sg:address":"Am Wasserturm 28",
    "sg:city":"Hungen",
    "sg:phone":"+49 6402/9018",
    "sg:postcode":"35410",
    "sg:province":"Hessen",
    "wof:name":"Uwe Hartmann Architekt",
    "wof:placetype":"venue"
},
  "geometry": {"coordinates":[8.888307,50.472054],"type":"Point"}
}