{
  "type": "Feature",
  "properties": {
    "iso:country":"DE",
    "sg:address":"Binger Str. 12",
    "sg:city":"Berlin",
    "sg:phone":"+49 30/8236846",
    "sg:postcode":"14197",
    "sg:province":"Berlin",
    "wof:name":"Klaus Jung",
    "wof:placetype":"venue"
},
  "geometry": {"coordinates":[13.3093738556,52.4753608704],"type":"Point"}
}