{
  "type": "Feature",
  "properties": {
    "iso:country":"DE",
    "sg:address":"Unterkamp 3",
    "sg:city":"Marl",
    "sg:phone":"+49 2365/7667",
    "sg:postcode":"45768",
    "sg:province":"Nordrhein-Westfalen",
    "wof:name":"Paul K. Heidemann",
    "wof:placetype":"venue"
},
  "geometry": {"coordinates":[7.0459218025,51.6247406006],"type":"Point"}
}