{
  "type": "Feature",
  "properties": {
    "iso:country":"DE",
    "sg:address":"Rieden 40",
    "sg:city":"Vechta",
    "sg:phone":"+49 4441/852695",
    "sg:postcode":"49377",
    "sg:province":"Niedersachsen",
    "wof:name":"Spedition Harting Beteiligungs Gmbh",
    "wof:placetype":"venue"
},
  "geometry": {"coordinates":[8.273544,52.743885],"type":"Point"}
}