{
  "type": "Feature",
  "properties": {
    "iso:country":"DE",
    "sg:address":"Hauptstr. 64",
    "sg:city":"Pforzheim",
    "sg:phone":"+49 7231/50236",
    "sg:postcode":"75181",
    "sg:province":"Baden-W\u00fcrttemberg",
    "wof:name":"Hans Ungerer",
    "wof:placetype":"venue"
},
  "geometry": {"coordinates":[8.742672,48.907921],"type":"Point"}
}