{
  "type": "Feature",
  "properties": {
    "iso:country":"DE",
    "sg:address":"Sch\u00fctzengraben 33",
    "sg:city":"Eschwege",
    "sg:phone":"+49 5651/20134",
    "sg:postcode":"37269",
    "sg:province":"Hessen",
    "wof:name":"Montech Karl-heinz Freudenreich",
    "wof:placetype":"venue"
},
  "geometry": {"coordinates":[10.037619,51.187252],"type":"Point"}
}