{
  "type": "Feature",
  "properties": {
    "iso:country":"DE",
    "sg:address":"Carolinengang",
    "sg:city":"Aurich",
    "sg:phone":"+49 4941/4943",
    "sg:postcode":"26603",
    "sg:province":"Niedersachsen",
    "wof:name":"Eduscho Gmbh",
    "wof:placetype":"venue"
},
  "geometry": {"coordinates":[7.4822602272,53.4687957764],"type":"Point"}
}