{
  "type": "Feature",
  "properties": {
    "iso:country":"DE",
    "sg:address":"Karl-Joos-Str. 31",
    "sg:city":"Kornwestheim",
    "sg:phone":"+49 7154/3338",
    "sg:postcode":"70806",
    "sg:province":"Baden-W\u00fcrttemberg",
    "wof:name":"Karin M\u00fcller",
    "wof:placetype":"venue"
},
  "geometry": {"coordinates":[9.183754921,48.8590431213],"type":"Point"}
}