{
  "type": "Feature",
  "properties": {
    "iso:country":"DE",
    "sg:address":"Marktstr. 13",
    "sg:city":"Siegen",
    "sg:phone":"+49 271/82938",
    "sg:postcode":"57078",
    "sg:province":"Nordrhein-Westfalen",
    "wof:name":"Martin L\u00fcck E. K.",
    "wof:placetype":"venue"
},
  "geometry": {"coordinates":[8.0109376907,50.9152145386],"type":"Point"}
}