{
  "type": "Feature",
  "properties": {
    "iso:country":"DE",
    "sg:address":"Bucher Str. 1",
    "sg:city":"Kipfenberg",
    "sg:phone":"+49 8465/276",
    "sg:postcode":"85110",
    "sg:province":"Bayern",
    "wof:name":"Edgar Haderer",
    "wof:placetype":"venue"
},
  "geometry": {"coordinates":[11.396637,48.951908],"type":"Point"}
}