{
  "type": "Feature",
  "properties": {
    "iso:country":"DE",
    "sg:address":"Hans-Sachs-Str. 1",
    "sg:city":"K\u00f6ln",
    "sg:phone":"+49 221/401916",
    "sg:postcode":"50931",
    "sg:province":"Nordrhein-Westfalen",
    "wof:name":"Haus Sachs",
    "wof:placetype":"venue"
},
  "geometry": {"coordinates":[6.9208750725,50.930431366],"type":"Point"}
}