{
  "type": "Feature",
  "properties": {
    "iso:country":"DE",
    "sg:address":"Wormser Landstr. 75",
    "sg:city":"Worms",
    "sg:phone":"+49 6241/33953",
    "sg:postcode":"67551",
    "sg:province":"Rheinland-Pfalz",
    "wof:name":"Restaurant Deutsches Haus",
    "wof:placetype":"venue"
},
  "geometry": {"coordinates":[8.2698049545,49.606010437],"type":"Point"}
}