{
  "type": "Feature",
  "properties": {
    "iso:country":"DE",
    "sg:address":"Karolinenstr. 18",
    "sg:city":"Sulzbach-Rosenberg",
    "sg:phone":"+49 9661/54362",
    "sg:postcode":"92237",
    "sg:province":"Bayern",
    "wof:name":"H\u00fcttenverein Gl\u00fcckauf Heinz J\u00e4ger",
    "wof:placetype":"venue"
},
  "geometry": {"coordinates":[11.7459506989,49.5089187622],"type":"Point"}
}