{
  "type": "Feature",
  "properties": {
    "iso:country":"DE",
    "sg:address":"Haneberg 46",
    "sg:city":"Bippen",
    "sg:phone":"+49 5909/246",
    "sg:postcode":"49626",
    "sg:province":"Niedersachsen",
    "wof:name":"Erich Brands",
    "wof:placetype":"venue"
},
  "geometry": {"coordinates":[7.6484780312,52.5744476318],"type":"Point"}
}