{
  "type": "Feature",
  "properties": {
    "iso:country":"DE",
    "sg:address":"Rottendorfer Str. 22",
    "sg:city":"W\u00fcrzburg",
    "sg:phone":"+49 931/64010",
    "sg:postcode":"97074",
    "sg:province":"Bayern",
    "wof:name":"Bdps Ingenieurges. Mbh",
    "wof:placetype":"venue"
},
  "geometry": {"coordinates":[9.9520168304,49.7912864685],"type":"Point"}
}