{
  "type": "Feature",
  "properties": {
    "iso:country":"DE",
    "sg:address":"Uwe-Johnson-Str.",
    "sg:city":"Ganzlin",
    "sg:phone":"+49 38737/20132",
    "sg:postcode":"19395",
    "sg:province":"Mecklenburg-Vorpommern",
    "wof:name":"Ganzliner Fenster- Und T\u00fcrenbau Gmbh",
    "wof:placetype":"venue"
},
  "geometry": {"coordinates":[12.24574,53.37981],"type":"Point"}
}