{
  "type": "Feature",
  "properties": {
    "iso:country":"DE",
    "sg:address":"Freudenst\u00e4dter Str. 25",
    "sg:city":"Horb",
    "sg:phone":"+49 7451/8804",
    "sg:postcode":"72160",
    "sg:province":"Baden-W\u00fcrttemberg",
    "wof:name":"B. Brenner",
    "wof:placetype":"venue"
},
  "geometry": {"coordinates":[8.6478042603,48.4402656555],"type":"Point"}
}