{
  "type": "Feature",
  "properties": {
    "iso:country":"DE",
    "sg:address":"Knorrstr. 19",
    "sg:city":"Neustadt",
    "sg:phone":"+49 9602/7385",
    "sg:postcode":"92660",
    "sg:province":"Bayern",
    "wof:name":"Lutz Zettler",
    "wof:placetype":"venue"
},
  "geometry": {"coordinates":[12.1741132736,49.7316856384],"type":"Point"}
}