{
  "type": "Feature",
  "properties": {
    "iso:country":"DE",
    "sg:address":"G\u00f6renweg 10",
    "sg:city":"Bitburg",
    "sg:phone":"+49 6561/96400",
    "sg:postcode":"54634",
    "sg:province":"Rheinland-Pfalz",
    "wof:name":"Matthias Just-leuschen",
    "wof:placetype":"venue"
},
  "geometry": {"coordinates":[6.520702,49.975559],"type":"Point"}
}