{
  "type": "Feature",
  "properties": {
    "iso:country":"DE",
    "sg:address":"Kirchrather Str.",
    "sg:city":"Herzogenrath",
    "sg:phone":"+49 2406/65079",
    "sg:postcode":"52134",
    "sg:province":"Nordrhein-Westfalen",
    "wof:name":"Josef Zentis",
    "wof:placetype":"venue"
},
  "geometry": {"coordinates":[6.11293,50.886913],"type":"Point"}
}