{
  "type": "Feature",
  "properties": {
    "iso:country":"DE",
    "sg:address":"Sangen 6",
    "sg:city":"Krokau",
    "sg:phone":"+49 4344/8038",
    "sg:postcode":"24217",
    "sg:province":"Schleswig-Holstein",
    "wof:name":"Rolf Gehrmann",
    "wof:placetype":"venue"
},
  "geometry": {"coordinates":[10.346481,54.400959],"type":"Point"}
}