{
  "type": "Feature",
  "properties": {
    "iso:country":"DE",
    "sg:address":"Wullener Feld 53",
    "sg:city":"Witten",
    "sg:phone":"+49 2302/57408",
    "sg:postcode":"58454",
    "sg:province":"Nordrhein-Westfalen",
    "wof:name":"Friedel Sauer Maschinenbau Gmbh",
    "wof:placetype":"venue"
},
  "geometry": {"coordinates":[7.364845,51.4576],"type":"Point"}
}