{
  "type": "Feature",
  "properties": {
    "iso:country":"DE",
    "sg:address":"Osterstr. 76",
    "sg:city":"Hamburg",
    "sg:phone":"+49 40/405247",
    "sg:postcode":"20259",
    "sg:province":"Hamburg",
    "wof:name":"Osteria",
    "wof:placetype":"venue"
},
  "geometry": {"coordinates":[9.954834938,53.5756530762],"type":"Point"}
}