{
  "type": "Feature",
  "properties": {
    "iso:country":"DE",
    "sg:address":"Gro\u00dfe Str. 47",
    "sg:city":"Helvesiek",
    "sg:phone":"+49 4267/1037",
    "sg:postcode":"27389",
    "sg:province":"Niedersachsen",
    "wof:name":"G. M\u00f6ller",
    "wof:placetype":"venue"
},
  "geometry": {"coordinates":[9.4835863113,53.220085144],"type":"Point"}
}