{
  "type": "Feature",
  "properties": {
    "iso:country":"DE",
    "sg:address":"Forchheimer Str. 7",
    "sg:city":"Neunkirchen",
    "sg:phone":"+49 9134/259",
    "sg:postcode":"91077",
    "sg:province":"Bayern",
    "wof:name":"Gastst\u00e4tte Josef Lausmann",
    "wof:placetype":"venue"
},
  "geometry": {"coordinates":[11.1273040771,49.6151733398],"type":"Point"}
}