{
  "type": "Feature",
  "properties": {
    "iso:country":"DE",
    "sg:address":"Ringstr. 118",
    "sg:city":"Eberswalde",
    "sg:phone":"+49 3334/353511",
    "sg:postcode":"16227",
    "sg:province":"Brandenburg",
    "wof:name":"D. Witthuhn",
    "wof:placetype":"venue"
},
  "geometry": {"coordinates":[13.745297,52.835915],"type":"Point"}
}