{
  "type": "Feature",
  "properties": {
    "iso:country":"DE",
    "sg:address":"Emscherstr. 38",
    "sg:city":"Gelsenkirchen",
    "sg:phone":"+49 4920/9970750",
    "sg:postcode":"45891",
    "sg:province":"Nordrhein-Westfalen",
    "wof:name":"Friedrich Gustav Theis Kaltwalzwerke Gmbh",
    "wof:placetype":"venue"
},
  "geometry": {"coordinates":[7.0806641579,51.5460586548],"type":"Point"}
}