{
  "type": "Feature",
  "properties": {
    "iso:country":"DE",
    "sg:address":"Obere Dorfstr. 5",
    "sg:city":"Braunschweig",
    "sg:phone":"+49 531/875714",
    "sg:postcode":"38122",
    "sg:province":"Niedersachsen",
    "wof:name":"Kurt Helmholz",
    "wof:placetype":"venue"
},
  "geometry": {"coordinates":[10.456087,52.225826],"type":"Point"}
}