{
  "type": "Feature",
  "properties": {
    "iso:country":"DE",
    "sg:address":"Gro\u00dfe Pranke 3",
    "sg:city":"Hannover",
    "sg:phone":"+49 511/791643",
    "sg:postcode":"30419",
    "sg:province":"Niedersachsen",
    "wof:name":"Albrecht Haller",
    "wof:placetype":"venue"
},
  "geometry": {"coordinates":[9.618555069,52.4052391052],"type":"Point"}
}