{
  "type": "Feature",
  "properties": {
    "iso:country":"DE",
    "sg:address":"Sepp-Herberger-Weg 2",
    "sg:city":"Karlsruhe",
    "sg:phone":"+49 721/409040",
    "sg:postcode":"76227",
    "sg:province":"Baden-W\u00fcrttemberg",
    "wof:name":"Sportschule Sch\u00f6neck",
    "wof:placetype":"venue"
},
  "geometry": {"coordinates":[8.4872121811,48.9973182678],"type":"Point"}
}