{
  "type": "Feature",
  "properties": {
    "iso:country":"DE",
    "sg:address":"Marienstr. 16a",
    "sg:city":"Werder",
    "sg:phone":"+49 3327/732187",
    "sg:postcode":"14542",
    "sg:province":"Brandenburg",
    "wof:name":"Gartengestaltung Undwegebau E.k.",
    "wof:placetype":"venue"
},
  "geometry": {"coordinates":[12.922988,52.385029],"type":"Point"}
}