{
  "type": "Feature",
  "properties": {
    "iso:country":"DE",
    "sg:address":"Lauterenstr. 10",
    "sg:city":"Mainz",
    "sg:phone":"+49 6131/225682",
    "sg:postcode":"55116",
    "sg:province":"Rheinland-Pfalz",
    "wof:name":"Heinrich Hilsenbeck",
    "wof:placetype":"venue"
},
  "geometry": {"coordinates":[8.279927,49.997307],"type":"Point"}
}