{
  "type": "Feature",
  "properties": {
    "iso:country":"DE",
    "sg:address":"Am B\u00e4ckerbrink 9",
    "sg:city":"Harsum",
    "sg:phone":"+49 5127/6375",
    "sg:postcode":"31177",
    "sg:province":"Niedersachsen",
    "wof:name":"Heinrich Leinemann",
    "wof:placetype":"venue"
},
  "geometry": {"coordinates":[10.010741,52.205353],"type":"Point"}
}