{
  "type": "Feature",
  "properties": {
    "iso:country":"DE",
    "sg:address":"Postfach 1380:: 34460 Wolfhagen:: Germany.^^Burgstr 28-30::",
    "sg:city":"Wolfhagen",
    "sg:phone":"+49 5692/6010",
    "sg:postcode":"34466",
    "sg:province":"Hessen",
    "wof:name":"Raiffeisenbank Wolfhagen Eg",
    "wof:placetype":"venue"
},
  "geometry": {"coordinates":[9.17242,51.327991],"type":"Point"}
}