{
  "type": "Feature",
  "properties": {
    "iso:country":"DE",
    "sg:address":"Kreutzerstr. 9",
    "sg:city":"W\u00f6rth",
    "sg:phone":"+49 7271/6641",
    "sg:postcode":"76744",
    "sg:province":"Rheinland-Pfalz",
    "wof:name":"Wolfgang Schneck",
    "wof:placetype":"venue"
},
  "geometry": {"coordinates":[8.069955,49.064083],"type":"Point"}
}