{
  "type": "Feature",
  "properties": {
    "iso:country":"DE",
    "sg:address":"Leininger Ring 67",
    "sg:city":"Bockenheim",
    "sg:phone":"+49 6359/4278",
    "sg:postcode":"67278",
    "sg:province":"Rheinland-Pfalz",
    "wof:name":"Rudi Heiser Weinanbau",
    "wof:placetype":"venue"
},
  "geometry": {"coordinates":[8.1874608994,49.6071472168],"type":"Point"}
}