{
  "type": "Feature",
  "properties": {
    "iso:country":"DE",
    "sg:address":"Am Wirtsberg 36",
    "sg:city":"Waldsassen",
    "sg:phone":"+49 9632/5694",
    "sg:postcode":"95652",
    "sg:province":"Bayern",
    "wof:name":"Zeolith In Deutschland Ek",
    "wof:placetype":"venue"
},
  "geometry": {"coordinates":[12.3160648346,49.9886322021],"type":"Point"}
}