{
  "type": "Feature",
  "properties": {
    "iso:country":"DE",
    "sg:address":"Stadtweg 5",
    "sg:city":"Stade",
    "sg:phone":"+49 4941/4163991",
    "sg:postcode":"21684",
    "sg:province":"Niedersachsen",
    "wof:name":"Gottfried Paschilke",
    "wof:placetype":"venue"
},
  "geometry": {"coordinates":[9.4569959641,53.5512313843],"type":"Point"}
}