{
  "type": "Feature",
  "properties": {
    "iso:country":"DE",
    "sg:address":"Ohmstr. 10",
    "sg:city":"Maintal",
    "sg:phone":"+49 6181/497329",
    "sg:postcode":"63477",
    "sg:province":"Hessen",
    "wof:name":"Helmut Fritz Gmbh",
    "wof:placetype":"venue"
},
  "geometry": {"coordinates":[8.8329496384,50.1432418823],"type":"Point"}
}