{
  "type": "Feature",
  "properties": {
    "iso:country":"DE",
    "sg:address":"Suderwicher Str. 111",
    "sg:city":"Castrop-Rauxel",
    "sg:phone":"+49 2367/8446",
    "sg:postcode":"44581",
    "sg:province":"Nordrhein-Westfalen",
    "wof:name":"Gastst\u00e4tte H. Olfmann",
    "wof:placetype":"venue"
},
  "geometry": {"coordinates":[7.3097658157,51.6074905396],"type":"Point"}
}