{
  "type": "Feature",
  "properties": {
    "iso:country":"DE",
    "sg:address":"Am Eichelgarten 14",
    "sg:city":"Pyrbaum",
    "sg:phone":"+49 9180/2694",
    "sg:postcode":"90602",
    "sg:province":"Bayern",
    "wof:name":"Siegfried Diebel",
    "wof:placetype":"venue"
},
  "geometry": {"coordinates":[11.2928924561,49.2969017029],"type":"Point"}
}