{
  "type": "Feature",
  "properties": {
    "iso:country":"DE",
    "sg:address":"Seilerweg 2",
    "sg:city":"Tengen",
    "sg:phone":"+49 7736/424",
    "sg:postcode":"78250",
    "sg:province":"Baden-W\u00fcrttemberg",
    "wof:name":"J\u00fcrgen Zimmermann",
    "wof:placetype":"venue"
},
  "geometry": {"coordinates":[8.684094429,47.7910957336],"type":"Point"}
}