{
  "type": "Feature",
  "properties": {
    "iso:country":"DE",
    "sg:address":"Lenhartzstr. 9",
    "sg:city":"Hamburg",
    "sg:phone":"+49 40/4803964",
    "sg:postcode":"20249",
    "sg:province":"Hamburg",
    "wof:name":"J. Werle",
    "wof:placetype":"venue"
},
  "geometry": {"coordinates":[9.9817781448,53.5864143372],"type":"Point"}
}