{
  "type": "Feature",
  "properties": {
    "iso:country":"DE",
    "sg:address":"Helenenstra\u00dfe 37-39",
    "sg:city":"Limbach-Oberfrohna",
    "sg:phone":"+49 3722",
    "sg:postcode":"09212",
    "sg:province":"Sachsen",
    "wof:name":"Pamec Papp Gmbh - Nl Chemnitz",
    "wof:placetype":"venue"
},
  "geometry": {"coordinates":[12.7572174072,50.8584213257],"type":"Point"}
}