{
  "type": "Feature",
  "properties": {
    "iso:country":"DE",
    "sg:address":"Waxensteinstr. 1",
    "sg:city":"Starnberg",
    "sg:phone":"+49 8151/2205",
    "sg:postcode":"82319",
    "sg:province":"Bayern",
    "wof:name":"Schaffhuber Gmbh & Co. Kg",
    "wof:placetype":"venue"
},
  "geometry": {"coordinates":[11.321472,48.007217],"type":"Point"}
}