{
  "type": "Feature",
  "properties": {
    "iso:country":"DE",
    "sg:address":"Friederikenstr. 36",
    "sg:city":"Coswig",
    "sg:postcode":"06869",
    "sg:province":"Sachsen-Anhalt",
    "wof:name":"Albert Croswig Kg",
    "wof:placetype":"venue"
},
  "geometry": {"coordinates":[12.456958,51.883881],"type":"Point"}
}