{
  "type": "Feature",
  "properties": {
    "iso:country":"DE",
    "sg:address":"Bahnhofstr. 6",
    "sg:city":"Kehl",
    "sg:phone":"+49 7851/3346",
    "sg:postcode":"77694",
    "sg:province":"Baden-W\u00fcrttemberg",
    "wof:name":"Dieter Koch E. K.",
    "wof:placetype":"venue"
},
  "geometry": {"coordinates":[7.8099942207,48.5770454407],"type":"Point"}
}