{
  "type": "Feature",
  "properties": {
    "iso:country":"DE",
    "sg:address":"Brentanostr 9",
    "sg:city":"Alzenau",
    "sg:phone":"+49 6023/1683",
    "sg:postcode":"63755",
    "sg:province":"Bayern",
    "wof:name":"Uni Filter Gro\u00dfhandels Gmbh",
    "wof:placetype":"venue"
},
  "geometry": {"coordinates":[9.0586414337,50.0907211304],"type":"Point"}
}