{
  "type": "Feature",
  "properties": {
    "iso:country":"DE",
    "sg:address":"Stra\u00dflacher Str. 2",
    "sg:city":"M\u00fcnchen",
    "sg:postcode":"81479",
    "sg:province":"Bayern",
    "wof:name":"Eagle W\u00e4rmetauscher Service Gmbh",
    "wof:placetype":"venue"
},
  "geometry": {"coordinates":[11.530265,48.08498],"type":"Point"}
}