{
  "type": "Feature",
  "properties": {
    "iso:country":"DE",
    "sg:address":"Ins Untere Heufeld",
    "sg:city":"Bad Aibling",
    "sg:phone":"+49 8061/1265",
    "sg:postcode":"83043",
    "sg:province":"Bayern",
    "wof:name":"W. Und I. Bierd\u00fcmpfl",
    "wof:placetype":"venue"
},
  "geometry": {"coordinates":[11.985084,47.865585],"type":"Point"}
}