{
  "type": "Feature",
  "properties": {
    "iso:country":"DE",
    "sg:address":"Teutonenweg 3",
    "sg:city":"Dietzenbach",
    "sg:postcode":"63128",
    "sg:province":"Hessen",
    "wof:name":"Gid Gesellschaft F\u00fcr Ingenieur- Und Dienst-",
    "wof:placetype":"venue"
},
  "geometry": {"coordinates":[8.7823638916,50.0266876221],"type":"Point"}
}