{
  "type": "Feature",
  "properties": {
    "iso:country":"DE",
    "sg:address":"Karlsruher Str. 7",
    "sg:city":"Leipzig",
    "sg:postcode":"04209",
    "sg:province":"Sachsen",
    "wof:name":"Gerhard Friedrich",
    "wof:placetype":"venue"
},
  "geometry": {"coordinates":[12.282817,51.31332],"type":"Point"}
}