{
  "type": "Feature",
  "properties": {
    "iso:country":"DE",
    "sg:address":"Grabenstr. 60",
    "sg:city":"Gau-Algesheim",
    "sg:phone":"+49 6725/2832",
    "sg:postcode":"55435",
    "sg:province":"Rheinland-Pfalz",
    "wof:name":"N. Fritzen",
    "wof:placetype":"venue"
},
  "geometry": {"coordinates":[8.014863,49.955566],"type":"Point"}
}