{
  "type": "Feature",
  "properties": {
    "iso:country":"DE",
    "sg:address":"Hansestr. 31a",
    "sg:city":"M\u00fcnster",
    "sg:phone":"+49 2501/28116",
    "sg:postcode":"48165",
    "sg:province":"Nordrhein-Westfalen",
    "wof:name":"Anton Schulz Kg",
    "wof:placetype":"venue"
},
  "geometry": {"coordinates":[7.626871109,51.8935050964],"type":"Point"}
}