{
  "type": "Feature",
  "properties": {
    "iso:country":"DE",
    "sg:address":"Waldmeisterstr. 9",
    "sg:city":"Sassnitz",
    "sg:phone":"+49 38392/50872",
    "sg:postcode":"18546",
    "sg:province":"Mecklenburg-Vorpommern",
    "wof:name":"E. Heinze",
    "wof:placetype":"venue"
},
  "geometry": {"coordinates":[13.6355981827,54.5163536072],"type":"Point"}
}