{
  "type": "Feature",
  "properties": {
    "iso:country":"DE",
    "sg:address":"Jahnstr. 77",
    "sg:city":"Kaiserslautern",
    "sg:phone":"+49 6301/9655",
    "sg:postcode":"67659",
    "sg:province":"Rheinland-Pfalz",
    "wof:name":"Ober & Ober Gmbh",
    "wof:placetype":"venue"
},
  "geometry": {"coordinates":[7.714692,49.475025],"type":"Point"}
}