{
  "type": "Feature",
  "properties": {
    "iso:country":"DE",
    "sg:address":"Margarethenstr 18",
    "sg:city":"Fulda",
    "sg:phone":"+49 661/902580",
    "sg:postcode":"36039",
    "sg:province":"Hessen",
    "wof:name":"Aic Gmbh",
    "wof:placetype":"venue"
},
  "geometry": {"coordinates":[9.6721496582,50.5572929382],"type":"Point"}
}