{
  "type": "Feature",
  "properties": {
    "iso:country":"DE",
    "sg:address":"Stettiner Str. 6a",
    "sg:city":"Marl",
    "sg:postcode":"45770",
    "sg:province":"Nordrhein-Westfalen",
    "wof:name":"Mexita Gastro-enter- Tainment Gmbh",
    "wof:placetype":"venue"
},
  "geometry": {"coordinates":[7.095286,51.645367],"type":"Point"}
}