{
  "type": "Feature",
  "properties": {
    "iso:country":"DE",
    "sg:address":"Br\u00fcckenstr. 2",
    "sg:city":"Spangenberg",
    "sg:phone":"+49 5663/5020",
    "sg:postcode":"34286",
    "sg:province":"Hessen",
    "wof:name":"Spangropharm Gmbh & Co.",
    "wof:placetype":"venue"
},
  "geometry": {"coordinates":[9.656547,51.11977],"type":"Point"}
}