{
  "type": "Feature",
  "properties": {
    "iso:country":"DE",
    "sg:address":"Maichinger Str. 15",
    "sg:city":"Sindelfingen",
    "sg:phone":"+49 7031/875001",
    "sg:postcode":"71063",
    "sg:province":"Baden-W\u00fcrttemberg",
    "wof:name":"Wilhelm Weiss",
    "wof:placetype":"venue"
},
  "geometry": {"coordinates":[8.9981641769,48.7117271423],"type":"Point"}
}