{
  "type": "Feature",
  "properties": {
    "iso:country":"DE",
    "sg:address":"Gartenstr. 41",
    "sg:city":"Albstadt",
    "sg:phone":"+49 7431/3801",
    "sg:postcode":"72458",
    "sg:province":"Baden-W\u00fcrttemberg",
    "wof:name":"Nachbarschaftshilfe",
    "wof:placetype":"venue"
},
  "geometry": {"coordinates":[9.0257,48.211571],"type":"Point"}
}