{
  "type": "Feature",
  "properties": {
    "iso:country":"DE",
    "sg:address":"Konrad-Zuse-Str. 5",
    "sg:city":"Konstanz",
    "sg:phone":"+49 7531/55517",
    "sg:postcode":"78467",
    "sg:province":"Baden-W\u00fcrttemberg",
    "wof:name":"Is-natursteine Gmbh",
    "wof:placetype":"venue"
},
  "geometry": {"coordinates":[9.1618556976,47.6762123108],"type":"Point"}
}