{
  "type": "Feature",
  "properties": {
    "iso:country":"DE",
    "sg:address":"Am Neuen Angerbach 28",
    "sg:city":"Duisburg",
    "sg:phone":"+49 203/750485",
    "sg:postcode":"47259",
    "sg:province":"Nordrhein-Westfalen",
    "wof:name":"Restaurant L. Schneider",
    "wof:placetype":"venue"
},
  "geometry": {"coordinates":[6.7397899628,51.3665428162],"type":"Point"}
}