{
  "type": "Feature",
  "properties": {
    "iso:country":"DE",
    "sg:address":"Prien",
    "sg:city":"Prien",
    "sg:phone":"+49 8051/6040",
    "sg:postcode":"83209",
    "sg:province":"Bayern",
    "wof:name":"Volksbank Prien Eg",
    "wof:placetype":"venue"
},
  "geometry": {"coordinates":[12.32852,47.849091],"type":"Point"}
}