{
  "type": "Feature",
  "properties": {
    "iso:country":"DE",
    "sg:address":"Rappstr. 12",
    "sg:city":"Hamburg",
    "sg:phone":"+49 40/41356999",
    "sg:postcode":"20146",
    "sg:province":"Hamburg",
    "wof:name":"Hilfe Und Pflege Pro Vita Ohg",
    "wof:placetype":"venue"
},
  "geometry": {"coordinates":[9.981657,53.569942],"type":"Point"}
}