{
  "type": "Feature",
  "properties": {
    "iso:country":"DE",
    "sg:address":"Kirchstr. 23",
    "sg:city":"Lahr",
    "sg:phone":"+49 7821/23919",
    "sg:postcode":"77933",
    "sg:province":"Baden-W\u00fcrttemberg",
    "wof:name":"A. Meier",
    "wof:placetype":"venue"
},
  "geometry": {"coordinates":[7.8734960556,48.3397026062],"type":"Point"}
}