{
  "type": "Feature",
  "properties": {
    "iso:country":"DE",
    "sg:address":"Rathausstr. 15",
    "sg:city":"Troisdorf",
    "sg:phone":"+49 2241/44556",
    "sg:postcode":"53844",
    "sg:province":"Nordrhein-Westfalen",
    "wof:name":"La Finezza",
    "wof:placetype":"venue"
},
  "geometry": {"coordinates":[7.1184201241,50.8018684387],"type":"Point"}
}