{
  "type": "Feature",
  "properties": {
    "iso:country":"DE",
    "sg:address":"Eutsch\u00fctzer Str. 12",
    "sg:city":"Dresden",
    "sg:phone":"+49 351/4724264",
    "sg:postcode":"01217",
    "sg:province":"Sachsen",
    "wof:name":"S. Franzky",
    "wof:placetype":"venue"
},
  "geometry": {"coordinates":[13.7533874512,51.0144195557],"type":"Point"}
}