{
  "type": "Feature",
  "properties": {
    "iso:country":"DE",
    "sg:address":"Wirteltorplatz 6",
    "sg:city":"D\u00fcren",
    "sg:phone":"+49 2421/15303",
    "sg:postcode":"52349",
    "sg:province":"Nordrhein-Westfalen",
    "wof:name":"Stepetex Gmbh",
    "wof:placetype":"venue"
},
  "geometry": {"coordinates":[6.483785,50.804989],"type":"Point"}
}