{
  "type": "Feature",
  "properties": {
    "iso:country":"DE",
    "sg:address":"Pl\u00f6\u00dfberg",
    "sg:city":"Immenreuth",
    "sg:phone":"+49 9642/1245",
    "sg:postcode":"95505",
    "sg:province":"Bayern",
    "wof:name":"A. U. M. M\u00fcller",
    "wof:placetype":"venue"
},
  "geometry": {"coordinates":[11.868074,49.921387],"type":"Point"}
}