{
  "type": "Feature",
  "properties": {
    "iso:country":"DE",
    "sg:address":"Wettersteinstr. 2- 4",
    "sg:city":"Peiting",
    "sg:postcode":"86971",
    "sg:province":"Bayern",
    "wof:name":"Die Tafelrunde Creat. Services Werbeagentur Gmbh",
    "wof:placetype":"venue"
},
  "geometry": {"coordinates":[10.9321508408,47.7888145447],"type":"Point"}
}