{
  "type": "Feature",
  "properties": {
    "iso:country":"DE",
    "sg:address":"Tiegelstr. 2",
    "sg:city":"Hagen",
    "sg:phone":"+49 2331/35810",
    "sg:postcode":"58093",
    "sg:province":"Nordrhein-Westfalen",
    "wof:name":"H\u00e4rtetechnik Hagen Gmbh",
    "wof:placetype":"venue"
},
  "geometry": {"coordinates":[7.5171308517,51.3877716064],"type":"Point"}
}