{
  "type": "Feature",
  "properties": {
    "iso:country":"DE",
    "sg:address":"Alte Rabenstra\u00dfe 22",
    "sg:city":"Hamburg",
    "sg:phone":"+49 40/4147940",
    "sg:postcode":"20148",
    "sg:province":"Hamburg",
    "wof:name":"Steuerberater Vo\u00df Und Richter",
    "wof:placetype":"venue"
},
  "geometry": {"coordinates":[9.997399,53.567074],"type":"Point"}
}