{
  "type": "Feature",
  "properties": {
    "iso:country":"DE",
    "sg:address":"Hamelner Str. 5",
    "sg:city":"Barntrup",
    "sg:phone":"+49 5263/2533",
    "sg:postcode":"32683",
    "sg:province":"Nordrhein-Westfalen",
    "wof:name":"Ostertor-apotheke P\u00e4chter Manfred Schreiter E.k.",
    "wof:placetype":"venue"
},
  "geometry": {"coordinates":[9.117772,51.990479],"type":"Point"}
}