{
  "type": "Feature",
  "properties": {
    "iso:country":"DE",
    "sg:address":"Anecampstr. 64",
    "sg:city":"Hannover",
    "sg:phone":"+49 511/520910",
    "sg:postcode":"30539",
    "sg:province":"Niedersachsen",
    "wof:name":"Helmut K\u00f6nig Steuerberater",
    "wof:placetype":"venue"
},
  "geometry": {"coordinates":[9.8344802856,52.3533668518],"type":"Point"}
}