{
  "type": "Feature",
  "properties": {
    "iso:country":"DE",
    "sg:address":"Manchinger Str. 70",
    "sg:city":"Ingolstadt",
    "sg:phone":"+49 841/68410",
    "sg:postcode":"85053",
    "sg:province":"Bayern",
    "wof:name":"Esso Deutschland Gmbh",
    "wof:placetype":"venue"
},
  "geometry": {"coordinates":[11.4485740662,48.7546424866],"type":"Point"}
}