{
  "type": "Feature",
  "properties": {
    "iso:country":"DE",
    "sg:address":"Von-Gablenz-Str. 2-6",
    "sg:city":"K\u00f6ln",
    "sg:phone":"+49 221/8260",
    "sg:postcode":"50679",
    "sg:province":"Nordrhein-Westfalen",
    "wof:name":"Lufthansa Commercial Holding Gmbh",
    "wof:placetype":"venue"
},
  "geometry": {"coordinates":[6.969985,50.935558],"type":"Point"}
}