{
  "type": "Feature",
  "properties": {
    "iso:country":"DE",
    "sg:address":"Macherstr. 52",
    "sg:city":"Kamenz",
    "sg:phone":"+49 35783/00125",
    "sg:postcode":"01917",
    "sg:province":"Sachsen",
    "wof:name":"Simone Neumann E. K.",
    "wof:placetype":"venue"
},
  "geometry": {"coordinates":[14.106095314,51.2813491821],"type":"Point"}
}