{
  "type": "Feature",
  "properties": {
    "iso:country":"DE",
    "sg:address":"Brunnenstr. 9a-10",
    "sg:city":"Eberswalde",
    "sg:phone":"+49 3334/2500",
    "sg:postcode":"16225",
    "sg:province":"Brandenburg",
    "wof:name":"Altenpflegeheim Freudenquell Ggmbh",
    "wof:placetype":"venue"
},
  "geometry": {"coordinates":[13.810976,52.828632],"type":"Point"}
}