{
  "type": "Feature",
  "properties": {
    "iso:country":"DE",
    "sg:address":"Kattberg 1",
    "sg:city":"Grundhof",
    "sg:phone":"+49 4634/9013",
    "sg:postcode":"24977",
    "sg:province":"Schleswig-Holstein",
    "wof:name":"Bernd Petersen",
    "wof:placetype":"venue"
},
  "geometry": {"coordinates":[9.624651,54.779518],"type":"Point"}
}