{
  "type": "Feature",
  "properties": {
    "iso:country":"DE",
    "sg:address":"Harzburger Str. 17 a",
    "sg:city":"Wolfenb\u00fcttel",
    "sg:phone":"+49 5331/61451",
    "sg:postcode":"38304",
    "sg:province":"Niedersachsen",
    "wof:name":"G\u00fcnter Lampe",
    "wof:placetype":"venue"
},
  "geometry": {"coordinates":[10.549055,52.141479],"type":"Point"}
}