{
  "type": "Feature",
  "properties": {
    "iso:country":"DE",
    "sg:address":"Kreuztaler Str. 7",
    "sg:city":"Netphen",
    "sg:postcode":"57250",
    "sg:province":"Nordrhein-Westfalen",
    "wof:name":"Lomexx Beteiligungs- Gesellschaft Mbh",
    "wof:placetype":"venue"
},
  "geometry": {"coordinates":[8.060523,50.916912],"type":"Point"}
}