{
  "type": "Feature",
  "properties": {
    "iso:country":"DE",
    "sg:address":"Deile 16",
    "sg:city":"Essen",
    "sg:phone":"+49 201/485875",
    "sg:postcode":"45257",
    "sg:province":"Nordrhein-Westfalen",
    "wof:name":"Gebr. Brems & Co. Gmbh",
    "wof:placetype":"venue"
},
  "geometry": {"coordinates":[7.10497,51.389042],"type":"Point"}
}