{
  "type": "Feature",
  "properties": {
    "iso:country":"DE",
    "sg:address":"Lindauer Str. 16",
    "sg:city":"Buchenberg",
    "sg:postcode":"87474",
    "sg:province":"Bayern",
    "wof:name":"Magnus Apotheke Apothekerin Sabine Mach E. K.",
    "wof:placetype":"venue"
},
  "geometry": {"coordinates":[10.23971,47.69598],"type":"Point"}
}