{
  "type": "Feature",
  "properties": {
    "iso:country":"DE",
    "sg:address":"Eschweilerstr. 53",
    "sg:city":"Stolberg",
    "sg:phone":"+49 2402/87335",
    "sg:postcode":"52222",
    "sg:province":"Nordrhein-Westfalen",
    "wof:name":"Plotec Werbung Joachim Nagelschmidt E. K.",
    "wof:placetype":"venue"
},
  "geometry": {"coordinates":[6.223992,50.780254],"type":"Point"}
}