{
  "type": "Feature",
  "properties": {
    "iso:country":"DE",
    "sg:address":"Leipziger Str. 374",
    "sg:city":"Kassel",
    "sg:phone":"+49 4956/1511401",
    "sg:postcode":"34123",
    "sg:province":"Hessen",
    "wof:name":"Ponndorf Maschinenfabrik Gmbh",
    "wof:placetype":"venue"
},
  "geometry": {"coordinates":[9.5321903229,51.3033485413],"type":"Point"}
}