{
  "type": "Feature",
  "properties": {
    "iso:country":"DE",
    "sg:address":"Am Hochacker 5",
    "sg:city":"Grasbrunn",
    "sg:phone":"+49 89/46100404",
    "sg:postcode":"85630",
    "sg:province":"Bayern",
    "wof:name":"Sportzentrum Martinsried Ag",
    "wof:placetype":"venue"
},
  "geometry": {"coordinates":[11.763107,48.101097],"type":"Point"}
}