{
  "type": "Feature",
  "properties": {
    "iso:country":"DE",
    "sg:address":"Hochbaumstr. 78",
    "sg:city":"Berlin",
    "sg:phone":"+49 30/8174088",
    "sg:postcode":"14167",
    "sg:province":"Berlin",
    "wof:name":"Ev. Pfarramt Stephanus-gemeinde",
    "wof:placetype":"venue"
},
  "geometry": {"coordinates":[13.2759094238,52.4305763245],"type":"Point"}
}