{
  "type": "Feature",
  "properties": {
    "iso:country":"DE",
    "sg:address":"Hochholdinger Str. 7",
    "sg:city":"Massing",
    "sg:phone":"+49 8724/338",
    "sg:postcode":"84323",
    "sg:province":"Bayern",
    "wof:name":"Maria Lohmaier",
    "wof:placetype":"venue"
},
  "geometry": {"coordinates":[12.616671,48.392639],"type":"Point"}
}