{
  "type": "Feature",
  "properties": {
    "iso:country":"DE",
    "sg:address":"Gewerbepark 10",
    "sg:city":"Radibor",
    "sg:phone":"+49 4935/9352820",
    "sg:postcode":"02627",
    "sg:province":"Sachsen",
    "wof:name":"Fahrzeugservice Schwarzadler Gmbh",
    "wof:placetype":"venue"
},
  "geometry": {"coordinates":[14.5417833328,51.1927566528],"type":"Point"}
}