{
  "type": "Feature",
  "properties": {
    "iso:country":"DE",
    "sg:address":"Schlo\u00dfmacherstr. 3",
    "sg:city":"Radevormwald",
    "sg:phone":"+49 2195/30262",
    "sg:postcode":"42477",
    "sg:province":"Nordrhein-Westfalen",
    "wof:name":"City-immobilien-verwaltungs Gmbh & Co. Betreuungs-kg",
    "wof:placetype":"venue"
},
  "geometry": {"coordinates":[7.3594517708,51.2019119263],"type":"Point"}
}