{
  "type": "Feature",
  "properties": {
    "iso:country":"DE",
    "sg:address":"Aussiger Platz 2",
    "sg:city":"N\u00fcrnberg",
    "sg:phone":"+49 911/4010880",
    "sg:postcode":"90480",
    "sg:province":"Bayern",
    "wof:name":"Norma Lebensmittel- Filial Gmbh & Co. Kg",
    "wof:placetype":"venue"
},
  "geometry": {"coordinates":[11.1241846085,49.4438400269],"type":"Point"}
}