{
  "type": "Feature",
  "properties": {
    "iso:country":"DE",
    "sg:address":"Nauklerstr. 20",
    "sg:city":"Sindelfingen",
    "sg:phone":"+49 7031/874174",
    "sg:postcode":"71065",
    "sg:province":"Baden-W\u00fcrttemberg",
    "wof:name":"Hans Lang",
    "wof:placetype":"venue"
},
  "geometry": {"coordinates":[9.010344,48.696861],"type":"Point"}
}