{
  "type": "Feature",
  "properties": {
    "iso:country":"DE",
    "sg:address":"Waldemarstr. 5",
    "sg:city":"Dresden",
    "sg:postcode":"01139",
    "sg:province":"Sachsen",
    "wof:name":"Baugesch\u00e4ft Hausservice M\u00fctze & Stix Gmbh",
    "wof:placetype":"venue"
},
  "geometry": {"coordinates":[13.702198,51.087112],"type":"Point"}
}