{
  "type": "Feature",
  "properties": {
    "iso:country":"DE",
    "sg:address":"Bautzner Str. 67",
    "sg:city":"Kamenz",
    "sg:phone":"+49 35783/02979",
    "sg:postcode":"01917",
    "sg:province":"Sachsen",
    "wof:name":"Drahtfach Verschleisstechnik",
    "wof:placetype":"venue"
},
  "geometry": {"coordinates":[14.10076,51.271458],"type":"Point"}
}