{
  "type": "Feature",
  "properties": {
    "iso:country":"DE",
    "sg:address":"Thusneldastr. 13",
    "sg:city":"Dortmund",
    "sg:phone":"+49 231/178564",
    "sg:postcode":"44149",
    "sg:province":"Nordrhein-Westfalen",
    "wof:name":"Gastst\u00e4tte Zum Kronenwirt",
    "wof:placetype":"venue"
},
  "geometry": {"coordinates":[7.4252038002,51.5139083862],"type":"Point"}
}