{
  "type": "Feature",
  "properties": {
    "iso:country":"DE",
    "sg:address":"Pillnitzer Landstr. 34 a",
    "sg:city":"Dresden",
    "sg:phone":"+49 351/2666800",
    "sg:postcode":"01326",
    "sg:province":"Sachsen",
    "wof:name":"Elbonia Sports Gmbh",
    "wof:placetype":"venue"
},
  "geometry": {"coordinates":[13.819113,51.05143],"type":"Point"}
}