{
  "type": "Feature",
  "properties": {
    "iso:country":"DE",
    "sg:address":"Sinninger Str. 77",
    "sg:city":"Rheine",
    "sg:phone":"+49 5975/7910",
    "sg:postcode":"48432",
    "sg:province":"Nordrhein-Westfalen",
    "wof:name":"Biamed Gmbh",
    "wof:placetype":"venue"
},
  "geometry": {"coordinates":[7.579638958,52.2367553711],"type":"Point"}
}