{
  "type": "Feature",
  "properties": {
    "iso:country":"DE",
    "sg:address":"Gablonzer Str. 11a",
    "sg:city":"Germaringen",
    "sg:phone":"+49 8341/65312",
    "sg:postcode":"87656",
    "sg:province":"Bayern",
    "wof:name":"H. Wabersich",
    "wof:placetype":"venue"
},
  "geometry": {"coordinates":[10.6661758423,47.9218330383],"type":"Point"}
}