{
  "type": "Feature",
  "properties": {
    "iso:country":"DE",
    "sg:address":"Plan 8",
    "sg:city":"Hamburg",
    "sg:phone":"+49 40/330867",
    "sg:postcode":"20095",
    "sg:province":"Hamburg",
    "wof:name":"Hajo G. Eilers Inh. Gisela Helling",
    "wof:placetype":"venue"
},
  "geometry": {"coordinates":[9.993761,53.551373],"type":"Point"}
}