{
  "type": "Feature",
  "properties": {
    "iso:country":"DE",
    "sg:address":"Semmelstr. 21",
    "sg:city":"K\u00fcrnach",
    "sg:phone":"+49 9367/3377",
    "sg:postcode":"97273",
    "sg:province":"Bayern",
    "wof:name":"Heinz Peks",
    "wof:placetype":"venue"
},
  "geometry": {"coordinates":[10.0374059677,49.845249176],"type":"Point"}
}