{
  "type": "Feature",
  "properties": {
    "iso:country":"DE",
    "sg:address":"Pastoratshof 7",
    "sg:city":"Grefrath",
    "sg:phone":"+49 2158/2230",
    "sg:postcode":"47929",
    "sg:province":"Nordrhein-Westfalen",
    "wof:name":"K\u00f6hnen Kg",
    "wof:placetype":"venue"
},
  "geometry": {"coordinates":[6.3446760178,51.3318748474],"type":"Point"}
}