{
  "type": "Feature",
  "properties": {
    "iso:country":"DE",
    "sg:address":"09468",
    "sg:city":"Tannenberg",
    "sg:phone":"+49 3733/52839",
    "sg:postcode":"09468",
    "sg:province":"Sachsen",
    "wof:name":"Freibad",
    "wof:placetype":"venue"
},
  "geometry": {"coordinates":[12.9470596313,50.6049385071],"type":"Point"}
}