{
  "type": "Feature",
  "properties": {
    "iso:country":"DE",
    "sg:address":"Westendorf 14",
    "sg:city":"Halberstadt",
    "sg:phone":"+49 3941/605191",
    "sg:postcode":"38820",
    "sg:province":"Sachsen-Anhalt",
    "wof:name":"Heckendorf Gmbh",
    "wof:placetype":"venue"
},
  "geometry": {"coordinates":[11.0434627533,51.8944740295],"type":"Point"}
}