{
  "type": "Feature",
  "properties": {
    "iso:country":"DE",
    "sg:address":"Bruchstr. 4",
    "sg:city":"Korschenbroich",
    "sg:phone":"+49 2161/641815",
    "sg:postcode":"41352",
    "sg:province":"Nordrhein-Westfalen",
    "wof:name":"Karl Baues Elektroinstallation",
    "wof:placetype":"venue"
},
  "geometry": {"coordinates":[6.490864,51.179375],"type":"Point"}
}