{
  "type": "Feature",
  "properties": {
    "iso:country":"DE",
    "sg:address":"Zum Seebach 3",
    "sg:city":"Remchingen",
    "sg:phone":"+49 7232/71620",
    "sg:postcode":"75196",
    "sg:province":"Baden-W\u00fcrttemberg",
    "wof:name":"Albert Denning",
    "wof:placetype":"venue"
},
  "geometry": {"coordinates":[8.572518,48.944393],"type":"Point"}
}