{
  "type": "Feature",
  "properties": {
    "iso:country":"DE",
    "sg:address":"Keltenstr. 14",
    "sg:city":"Osterhofen",
    "sg:phone":"+49 8547/96160",
    "sg:postcode":"94486",
    "sg:province":"Bayern",
    "wof:name":"Meiko-konservenfabrik Gergweiss",
    "wof:placetype":"venue"
},
  "geometry": {"coordinates":[12.9815578461,48.6216011047],"type":"Point"}
}