{
  "type": "Feature",
  "properties": {
    "iso:country":"DE",
    "sg:address":"Schlo\u00dfstr. 12",
    "sg:city":"Schwabstedt",
    "sg:phone":"+49 4884/688",
    "sg:postcode":"25876",
    "sg:province":"Schleswig-Holstein",
    "wof:name":"Einhorn-apotheke Vormals B. Heidel-hansen, Fortgef\u00fchrt V.",
    "wof:placetype":"venue"
},
  "geometry": {"coordinates":[9.18284,54.397038],"type":"Point"}
}