{
  "type": "Feature",
  "properties": {
    "iso:country":"DE",
    "sg:address":"Steinbr\u00fccke 18",
    "sg:city":"Quedlinburg",
    "sg:phone":"+49 3946/705301",
    "sg:postcode":"06484",
    "sg:province":"Sachsen-Anhalt",
    "wof:name":"Fielmann Ag & Co.",
    "wof:placetype":"venue"
},
  "geometry": {"coordinates":[11.1497545242,51.7903366089],"type":"Point"}
}