{
  "type": "Feature",
  "properties": {
    "iso:country":"DE",
    "sg:address":"K\u00f6nigsteiner Str. 61 A",
    "sg:city":"Frankfurt",
    "sg:phone":"+49 69/311737",
    "sg:postcode":"65929",
    "sg:province":"Hessen",
    "wof:name":"Z. Udovc Und R. J\u00fcrgens Masseure",
    "wof:placetype":"venue"
},
  "geometry": {"coordinates":[8.54296,50.106464],"type":"Point"}
}