{
  "type": "Feature",
  "properties": {
    "iso:country":"DE",
    "sg:address":"Rottenburger Str. 1",
    "sg:city":"Herrngiersdorf",
    "sg:phone":"+49 9452/93030",
    "sg:postcode":"84097",
    "sg:province":"Bayern",
    "wof:name":"Georg Pritsch Gmbh & Co. Kg",
    "wof:placetype":"venue"
},
  "geometry": {"coordinates":[12.0452432632,48.8152389526],"type":"Point"}
}