{
  "type": "Feature",
  "properties": {
    "iso:country":"DE",
    "sg:address":"unbekannt",
    "sg:city":"M\u00fcnchen",
    "sg:phone":"+49 173 3771850",
    "sg:postcode":"80993",
    "sg:province":"Bayern",
    "wof:name":"The Unifier - Siemens Ic35",
    "wof:placetype":"venue"
},
  "geometry": {"coordinates":[11.52076,48.187229],"type":"Point"}
}