{
  "type": "Feature",
  "properties": {
    "iso:country":"DE",
    "sg:address":"Heinrich-Witzenmann-Str. 5",
    "sg:city":"Pforzheim",
    "sg:phone":"+49 7231/441199",
    "sg:postcode":"75179",
    "sg:province":"Baden-W\u00fcrttemberg",
    "wof:name":"Debitel Plus C-shop",
    "wof:placetype":"venue"
},
  "geometry": {"coordinates":[8.6616220474,48.8845252991],"type":"Point"}
}