{
  "type": "Feature",
  "properties": {
    "iso:country":"DE",
    "sg:address":"Gr\u00fcne M\u00fchle 18 a",
    "sg:city":"H\u00f6xter",
    "sg:phone":"+49 5271/8517",
    "sg:postcode":"37671",
    "sg:province":"Nordrhein-Westfalen",
    "wof:name":"Pension Karl-heinz Bitterberg",
    "wof:placetype":"venue"
},
  "geometry": {"coordinates":[9.3717842102,51.7865562439],"type":"Point"}
}