{
  "type": "Feature",
  "properties": {
    "iso:country":"DE",
    "sg:address":"Reichenberger Str. 8",
    "sg:city":"G\u00fcnzburg",
    "sg:phone":"+49 8221/4734",
    "sg:postcode":"89312",
    "sg:province":"Bayern",
    "wof:name":"Ev.-luth. Pfarramt Ii",
    "wof:placetype":"venue"
},
  "geometry": {"coordinates":[10.2690572739,48.4490356445],"type":"Point"}
}