{
  "type": "Feature",
  "properties": {
    "iso:country":"DE",
    "sg:address":"Am Schulacker 18",
    "sg:city":"Lahr",
    "sg:phone":"+49 7821/43900",
    "sg:postcode":"77933",
    "sg:province":"Baden-W\u00fcrttemberg",
    "wof:name":"Helga G\u00f6ttlicher",
    "wof:placetype":"venue"
},
  "geometry": {"coordinates":[7.8392682076,48.3255081177],"type":"Point"}
}