{
  "type": "Feature",
  "properties": {
    "iso:country":"DE",
    "sg:address":"Am Hirtenbach 1",
    "sg:city":"Ronnenberg",
    "sg:phone":"+49 5109/1325",
    "sg:postcode":"30952",
    "sg:province":"Niedersachsen",
    "wof:name":"Pipoh & Partner Gmbh",
    "wof:placetype":"venue"
},
  "geometry": {"coordinates":[9.648765564,52.3215179443],"type":"Point"}
}