{
  "type": "Feature",
  "properties": {
    "iso:country":"DE",
    "sg:address":"Kirchstr. 3",
    "sg:city":"Birkweiler",
    "sg:phone":"+49 6345/5385",
    "sg:postcode":"76831",
    "sg:province":"Rheinland-Pfalz",
    "wof:name":"Julius Wolf",
    "wof:placetype":"venue"
},
  "geometry": {"coordinates":[8.0354166031,49.2042922974],"type":"Point"}
}