{
  "type": "Feature",
  "properties": {
    "iso:country":"DE",
    "sg:address":"Werner-Petzold-Str. 1",
    "sg:city":"Gera",
    "sg:postcode":"07549",
    "sg:province":"Th\u00fcringen",
    "wof:name":"Kerstin Linke E. K.",
    "wof:placetype":"venue"
},
  "geometry": {"coordinates":[12.0615415573,50.8377380371],"type":"Point"}
}