{
  "type": "Feature",
  "properties": {
    "iso:country":"DE",
    "sg:address":"An der Eisenbahn 4",
    "sg:city":"Achim",
    "sg:phone":"+49 4202/9955",
    "sg:postcode":"28832",
    "sg:province":"Niedersachsen",
    "wof:name":"Preussag Imbema Klug Gmbh",
    "wof:placetype":"venue"
},
  "geometry": {"coordinates":[9.038917,53.015015],"type":"Point"}
}