{
  "type": "Feature",
  "properties": {
    "iso:country":"DE",
    "sg:address":"Kleine Lieth 1",
    "sg:city":"Hann. M\u00fcnden",
    "sg:phone":"+49 5541/2260",
    "sg:postcode":"34346",
    "sg:province":"Niedersachsen",
    "wof:name":"Georg G\u00f6bel",
    "wof:placetype":"venue"
},
  "geometry": {"coordinates":[9.726121,51.414913],"type":"Point"}
}