{
  "type": "Feature",
  "properties": {
    "iso:country":"DE",
    "sg:address":"Holler Landstr. 108",
    "sg:city":"Hude",
    "sg:phone":"+49 4484/290",
    "sg:postcode":"27798",
    "sg:province":"Niedersachsen",
    "wof:name":"Hans Cassebohm",
    "wof:placetype":"venue"
},
  "geometry": {"coordinates":[8.382552,53.156189],"type":"Point"}
}