{
  "type": "Feature",
  "properties": {
    "iso:country":"DE",
    "sg:address":"Saalstr. 14",
    "sg:city":"Saalfeld",
    "sg:phone":"+49 3671/513473",
    "sg:postcode":"07318",
    "sg:province":"Th\u00fcringen",
    "wof:name":"Landte",
    "wof:placetype":"venue"
},
  "geometry": {"coordinates":[11.3621759415,50.6485786438],"type":"Point"}
}