{
  "type": "Feature",
  "properties": {
    "iso:country":"DE",
    "sg:address":"Auestr. 1",
    "sg:city":"Dietzenbach",
    "sg:phone":"+49 6074/42379",
    "sg:postcode":"63128",
    "sg:province":"Hessen",
    "wof:name":"Schmitt",
    "wof:placetype":"venue"
},
  "geometry": {"coordinates":[8.7771511078,50.0121383667],"type":"Point"}
}