{
  "type": "Feature",
  "properties": {
    "iso:country":"DE",
    "sg:address":"Kardinal-von-Galen-Str. 27",
    "sg:city":"Schermbeck",
    "sg:postcode":"46514",
    "sg:province":"Nordrhein-Westfalen",
    "wof:name":"Primo Food Ohg",
    "wof:placetype":"venue"
},
  "geometry": {"coordinates":[6.8761749268,51.6921958923],"type":"Point"}
}