{
  "type": "Feature",
  "properties": {
    "iso:country":"DE",
    "sg:address":"Amselstieg 2",
    "sg:city":"Bad Bevensen",
    "sg:phone":"+49 5821/1249",
    "sg:postcode":"29549",
    "sg:province":"Niedersachsen",
    "wof:name":"G\u00fcnther Held Wiege- Und F\u00f6rdertechnik",
    "wof:placetype":"venue"
},
  "geometry": {"coordinates":[10.5957803726,53.0862503052],"type":"Point"}
}