{
  "type": "Feature",
  "properties": {
    "iso:country":"DE",
    "sg:address":"Weg beim J\u00e4ger 224/226",
    "sg:city":"Hamburg",
    "sg:postcode":"22335",
    "sg:province":"Hamburg",
    "wof:name":"Ab 00 87 Verm\u00f6gens- Verwaltungs Ag",
    "wof:placetype":"venue"
},
  "geometry": {"coordinates":[10.00967,53.623608],"type":"Point"}
}