{
  "type": "Feature",
  "properties": {
    "iso:country":"DE",
    "sg:address":"Dorfstr. 22",
    "sg:city":"Grebs",
    "sg:phone":"+49 3382/703506",
    "sg:postcode":"14797",
    "sg:province":"Brandenburg",
    "wof:name":"Hertha-bau Gmbh",
    "wof:placetype":"venue"
},
  "geometry": {"coordinates":[12.743825,52.318409],"type":"Point"}
}