{
  "type": "Feature",
  "properties": {
    "iso:country":"DE",
    "sg:address":"Zur Hasenheide 3",
    "sg:city":"Langenbernsdorf",
    "sg:postcode":"08428",
    "sg:province":"Sachsen",
    "wof:name":"Ingenieurb\u00fcro F\u00fcr Tragwerksplanung Ibt",
    "wof:placetype":"venue"
},
  "geometry": {"coordinates":[12.2865657806,50.7404556274],"type":"Point"}
}