{
  "type": "Feature",
  "properties": {
    "iso:country":"DE",
    "sg:address":"Zollh\u00fcttengasse 3",
    "sg:city":"Schw\u00e4bisch Hall",
    "sg:phone":"+49 791/9780841",
    "sg:postcode":"74523",
    "sg:province":"Baden-W\u00fcrttemberg",
    "wof:name":"Minat",
    "wof:placetype":"venue"
},
  "geometry": {"coordinates":[9.7336187363,49.1097946167],"type":"Point"}
}