{
  "type": "Feature",
  "properties": {
    "iso:country":"DE",
    "sg:address":"Bernhard-May-Str. 20 a-24",
    "sg:city":"Wiesbaden",
    "sg:postcode":"65203",
    "sg:province":"Hessen",
    "wof:name":"Blumen Peter Gl\u00f6ckler E. K.",
    "wof:placetype":"venue"
},
  "geometry": {"coordinates":[8.247554,50.047676],"type":"Point"}
}