{
  "type": "Feature",
  "properties": {
    "iso:country":"DE",
    "sg:address":"Hagenstr. 6",
    "sg:city":"Winterberg",
    "sg:phone":"+49 2981/81108",
    "sg:postcode":"59955",
    "sg:province":"Nordrhein-Westfalen",
    "wof:name":"K.-d. Wahle",
    "wof:placetype":"venue"
},
  "geometry": {"coordinates":[8.534004,51.194069],"type":"Point"}
}