{
  "type": "Feature",
  "properties": {
    "iso:country":"DE",
    "sg:address":"Neptunstr 5",
    "sg:city":"Bremen",
    "sg:phone":"+49 421/382061",
    "sg:postcode":"28217",
    "sg:province":"Bremen",
    "wof:name":"Lts Speditions-gmbh",
    "wof:placetype":"venue"
},
  "geometry": {"coordinates":[8.7851409912,53.0869216919],"type":"Point"}
}