{
  "type": "Feature",
  "properties": {
    "iso:country":"DE",
    "sg:address":"Alfershausen 228",
    "sg:city":"Thalm\u00e4ssing",
    "sg:phone":"+49 9173",
    "sg:postcode":"91177",
    "sg:province":"Bayern",
    "wof:name":"Creativteam Melmak",
    "wof:placetype":"venue"
},
  "geometry": {"coordinates":[11.185808,49.105068],"type":"Point"}
}