{
  "type": "Feature",
  "properties": {
    "iso:country":"DE",
    "sg:address":"Badfeldweg 3",
    "sg:city":"Maxh\u00fctte-Haidhof",
    "sg:phone":"+49 9471/4430",
    "sg:postcode":"93142",
    "sg:province":"Bayern",
    "wof:name":"Leonberger Schmankerlstuben",
    "wof:placetype":"venue"
},
  "geometry": {"coordinates":[12.1135282516,49.1843795776],"type":"Point"}
}