{
  "type": "Feature",
  "properties": {
    "iso:country":"DE",
    "sg:address":"G\u00e4blerstr. 16",
    "sg:city":"Berlin",
    "sg:phone":"+49 30/9262449",
    "sg:postcode":"13086",
    "sg:province":"Berlin",
    "wof:name":"M\u00f6belrestaurierungswerkstatt Inh. Manfred B\u00e4r",
    "wof:placetype":"venue"
},
  "geometry": {"coordinates":[13.4483442307,52.5544891357],"type":"Point"}
}