{
  "type": "Feature",
  "properties": {
    "iso:country":"DE",
    "sg:address":"Dresdener Str. 64",
    "sg:city":"Kaiserslautern",
    "sg:phone":"+49 631/3507311",
    "sg:postcode":"67663",
    "sg:province":"Rheinland-Pfalz",
    "wof:name":"Transkom Kommunikationsnetzwerke Gmbh",
    "wof:placetype":"venue"
},
  "geometry": {"coordinates":[7.7222771645,49.4329376221],"type":"Point"}
}