{
  "type": "Feature",
  "properties": {
    "iso:country":"DE",
    "sg:address":"Maternusstr. 40",
    "sg:city":"K\u00f6ln",
    "sg:phone":"+49 221/352041",
    "sg:postcode":"50678",
    "sg:province":"Nordrhein-Westfalen",
    "wof:name":"Dr. Ulrich Prutsch Rechtsanwalt",
    "wof:placetype":"venue"
},
  "geometry": {"coordinates":[6.9658799171,50.9207305908],"type":"Point"}
}