{
  "type": "Feature",
  "properties": {
    "iso:country":"DE",
    "sg:address":"Hindenburgstr.4b",
    "sg:city":"Teningen",
    "sg:phone":"+49 7641/573688",
    "sg:postcode":"79331",
    "sg:province":"Baden-W\u00fcrttemberg",
    "wof:name":"Vutura Gmbh",
    "wof:placetype":"venue"
},
  "geometry": {"coordinates":[7.808351,48.125389],"type":"Point"}
}