{
  "type": "Feature",
  "properties": {
    "iso:country":"DE",
    "sg:address":"Hauptstr. 22",
    "sg:city":"M\u00f6lln",
    "sg:phone":"+49 4542/2951",
    "sg:postcode":"23879",
    "sg:province":"Schleswig-Holstein",
    "wof:name":"Andrea Christ Steuerberaterin",
    "wof:placetype":"venue"
},
  "geometry": {"coordinates":[10.685128212,53.626411438],"type":"Point"}
}