{
  "type": "Feature",
  "properties": {
    "iso:country":"DE",
    "sg:address":"Schmaler Weg 7",
    "sg:city":"Enger",
    "sg:phone":"+49 5224/3435",
    "sg:postcode":"32130",
    "sg:province":"Nordrhein-Westfalen",
    "wof:name":"Fight X Back - The Hardcore Fanzine",
    "wof:placetype":"venue"
},
  "geometry": {"coordinates":[8.510005,52.142601],"type":"Point"}
}