{
  "type": "Feature",
  "properties": {
    "iso:country":"DE",
    "sg:city":"Dormagen",
    "sg:phone":"+49 2133/90575",
    "sg:postcode":"41542",
    "sg:province":"Nordrhein-Westfalen",
    "wof:name":"Hypotheken-beratung Wolfgang Berger",
    "wof:placetype":"venue"
},
  "geometry": {"coordinates":[6.77159,51.114738],"type":"Point"}
}