{
  "type": "Feature",
  "properties": {
    "iso:country":"DE",
    "sg:address":"Zweibr\u00fccker Str. 1",
    "sg:city":"Pirmasens",
    "sg:phone":"+49 6331/12626",
    "sg:postcode":"66953",
    "sg:province":"Rheinland-Pfalz",
    "wof:name":"Parkplatz",
    "wof:placetype":"venue"
},
  "geometry": {"coordinates":[7.6040730476,49.2049942017],"type":"Point"}
}