{
  "type": "Feature",
  "properties": {
    "iso:country":"DE",
    "sg:address":"Seckenrain 7a",
    "sg:city":"Wald-Michelbach",
    "sg:phone":"+49 6207/7129",
    "sg:postcode":"69483",
    "sg:province":"Hessen",
    "wof:name":"Gert Veit Steuerberater",
    "wof:placetype":"venue"
},
  "geometry": {"coordinates":[8.8416728973,49.5519065857],"type":"Point"}
}