{
  "type": "Feature",
  "properties": {
    "iso:country":"DE",
    "sg:address":"Keltenstr. 6",
    "sg:city":"K\u00f6nigsbrunn",
    "sg:phone":"+49 8231/2084",
    "sg:postcode":"86343",
    "sg:province":"Bayern",
    "wof:name":"M\u00fcller Werkst\u00e4tte Schreinerei-innenausbau Gmbh",
    "wof:placetype":"venue"
},
  "geometry": {"coordinates":[10.891336441,48.2885437012],"type":"Point"}
}