{
  "type": "Feature",
  "properties": {
    "iso:country":"DE",
    "sg:address":"Alte Crivitzer Landstr.",
    "sg:city":"Schwerin",
    "sg:postcode":"19063",
    "sg:province":"Mecklenburg-Vorpommern",
    "wof:name":"Immobilien- Und Grundst\u00fccks- Verwaltungsges. D. Schweriner",
    "wof:placetype":"venue"
},
  "geometry": {"coordinates":[11.482254982,53.6000938416],"type":"Point"}
}