{
  "type": "Feature",
  "properties": {
    "iso:country":"DE",
    "sg:address":"Alte Bergstr. 11",
    "sg:city":"Mansfeld",
    "sg:phone":"+49 34782/20796",
    "sg:postcode":"06343",
    "sg:province":"Sachsen-Anhalt",
    "wof:name":"D. Neukirchner",
    "wof:placetype":"venue"
},
  "geometry": {"coordinates":[11.459805,51.600849],"type":"Point"}
}