{
  "type": "Feature",
  "properties": {
    "iso:country":"DE",
    "sg:address":"Hauptstr. 95",
    "sg:city":"Bendorf",
    "sg:phone":"+49 2622/4353",
    "sg:postcode":"56170",
    "sg:province":"Rheinland-Pfalz",
    "wof:name":"Pizza Am Park",
    "wof:placetype":"venue"
},
  "geometry": {"coordinates":[7.5749559402,50.4235534668],"type":"Point"}
}