{
  "type": "Feature",
  "properties": {
    "iso:country":"DE",
    "sg:address":"Regensburger Str. 21",
    "sg:city":"Holzheim",
    "sg:phone":"+49 9473/332",
    "sg:postcode":"93183",
    "sg:province":"Bayern",
    "wof:name":"Holzheim",
    "wof:placetype":"venue"
},
  "geometry": {"coordinates":[11.9617052078,49.1620635986],"type":"Point"}
}