{
  "type": "Feature",
  "properties": {
    "iso:country":"DE",
    "sg:address":"Vo\u00dfkuhle 37",
    "sg:city":"Brilon",
    "sg:phone":"+49 2961/8438",
    "sg:postcode":"59929",
    "sg:province":"Nordrhein-Westfalen",
    "wof:name":"Karlheinz Schreckenberg",
    "wof:placetype":"venue"
},
  "geometry": {"coordinates":[8.56389,51.384369],"type":"Point"}
}