{
  "type": "Feature",
  "properties": {
    "iso:country":"DE",
    "sg:address":"Michaelstr. 18",
    "sg:city":"Vettwei\u00df",
    "sg:phone":"+49 2424/7587",
    "sg:postcode":"52391",
    "sg:province":"Nordrhein-Westfalen",
    "wof:name":"Johannes Freidel",
    "wof:placetype":"venue"
},
  "geometry": {"coordinates":[6.597339,50.766563],"type":"Point"}
}