{
  "type": "Feature",
  "properties": {
    "iso:country":"DE",
    "sg:address":"Wolfgang-Heinze-Str. 20",
    "sg:city":"Leipzig",
    "sg:phone":"+49 341/3012280",
    "sg:postcode":"04277",
    "sg:province":"Sachsen",
    "wof:name":"Albert Staske",
    "wof:placetype":"venue"
},
  "geometry": {"coordinates":[12.3729658127,51.3084487915],"type":"Point"}
}