{
  "type": "Feature",
  "properties": {
    "iso:country":"DE",
    "sg:address":"Sedanplatz 4",
    "sg:city":"Lehrte",
    "sg:phone":"+49 5132/55222",
    "sg:postcode":"31275",
    "sg:province":"Niedersachsen",
    "wof:name":"Budack Und Karp Architekten",
    "wof:placetype":"venue"
},
  "geometry": {"coordinates":[9.978536,52.37347],"type":"Point"}
}