{
  "type": "Feature",
  "properties": {
    "iso:country":"DE",
    "sg:address":"Flurweg 3",
    "sg:city":"Altom\u00fcnster",
    "sg:postcode":"85250",
    "sg:province":"Bayern",
    "wof:name":"Fmg Fugenmontage F\u00fcr Fassaden- Und Innenausbau Gmbh",
    "wof:placetype":"venue"
},
  "geometry": {"coordinates":[11.2592868805,48.3941383362],"type":"Point"}
}