{
  "type": "Feature",
  "properties": {
    "iso:country":"DE",
    "sg:address":"Wilhelmstr. 12",
    "sg:city":"Ahlen",
    "sg:phone":"+49 2382/805869",
    "sg:postcode":"59227",
    "sg:province":"Nordrhein-Westfalen",
    "wof:name":"Heimatmuseum Ahlen",
    "wof:placetype":"venue"
},
  "geometry": {"coordinates":[7.889204,51.761681],"type":"Point"}
}