{
  "type": "Feature",
  "properties": {
    "iso:country":"DE",
    "sg:address":"Mittelstr. 2",
    "sg:city":"Tr\u00f6glitz",
    "sg:phone":"+49 3441/533020",
    "sg:postcode":"06729",
    "sg:province":"Sachsen-Anhalt",
    "wof:name":"Rollis Treff",
    "wof:placetype":"venue"
},
  "geometry": {"coordinates":[12.178319931,51.0569992065],"type":"Point"}
}