{
  "type": "Feature",
  "properties": {
    "iso:country":"DE",
    "sg:address":"Bilker Str. 3",
    "sg:city":"Wettringen",
    "sg:phone":"+49 2557/520",
    "sg:postcode":"48493",
    "sg:province":"Nordrhein-Westfalen",
    "wof:name":"Clemens Gering",
    "wof:placetype":"venue"
},
  "geometry": {"coordinates":[7.318545,52.213737],"type":"Point"}
}