{
  "type": "Feature",
  "properties": {
    "iso:country":"DE",
    "sg:address":"Heidestr. 80",
    "sg:city":"Herten",
    "sg:phone":"+49 209/358005",
    "sg:postcode":"45701",
    "sg:province":"Nordrhein-Westfalen",
    "wof:name":"Beg Bio Energie Gmbh",
    "wof:placetype":"venue"
},
  "geometry": {"coordinates":[7.084935,51.613747],"type":"Point"}
}