{
  "type": "Feature",
  "properties": {
    "iso:country":"DE",
    "sg:address":"Am Bismarckturm 17",
    "sg:city":"Stuttgart",
    "sg:postcode":"70192",
    "sg:province":"Baden-W\u00fcrttemberg",
    "wof:name":"Dr. Peter Theile Gmbh",
    "wof:placetype":"venue"
},
  "geometry": {"coordinates":[9.1604223251,48.7937850952],"type":"Point"}
}