{
  "type": "Feature",
  "properties": {
    "iso:country":"DE",
    "sg:address":"Kumpfm\u00fchler Str. 34",
    "sg:city":"Regensburg",
    "sg:phone":"+49 941/53393",
    "sg:postcode":"93051",
    "sg:province":"Bayern",
    "wof:name":"Helmut H\u00f6flmaier Und Gerhard Oreskovich",
    "wof:placetype":"venue"
},
  "geometry": {"coordinates":[12.087477684,49.0096473694],"type":"Point"}
}