{
  "type": "Feature",
  "properties": {
    "iso:country":"DE",
    "sg:address":"Kennedydamm 10::",
    "sg:city":"Hildesheim",
    "sg:phone":"+49 4951/21166",
    "sg:postcode":"31134",
    "sg:province":"Niedersachsen",
    "wof:name":"Volksbank Hildesheim Eg",
    "wof:placetype":"venue"
},
  "geometry": {"coordinates":[9.958536,52.155697],"type":"Point"}
}