{
  "type": "Feature",
  "properties": {
    "iso:country":"DE",
    "sg:address":"Alt Bonames 14",
    "sg:city":"Frankfurt",
    "sg:phone":"+49 69/501876",
    "sg:postcode":"60437",
    "sg:province":"Hessen",
    "wof:name":"Gastst\u00e4tte A. Euler",
    "wof:placetype":"venue"
},
  "geometry": {"coordinates":[8.6647577286,50.1817588806],"type":"Point"}
}