{
  "type": "Feature",
  "properties": {
    "iso:country":"DE",
    "sg:address":"Bredowstr. 18",
    "sg:city":"Hamburg",
    "sg:phone":"+49 40/733420",
    "sg:postcode":"22113",
    "sg:province":"Schleswig-Holstein",
    "wof:name":"Fruchtunion Hamburg Gmbh",
    "wof:placetype":"venue"
},
  "geometry": {"coordinates":[10.087127,53.522808],"type":"Point"}
}