{
  "type": "Feature",
  "properties": {
    "iso:country":"DE",
    "sg:address":"Mozartstr. 5",
    "sg:city":"Gladenbach",
    "sg:phone":"+49 6462/2627",
    "sg:postcode":"35075",
    "sg:province":"Hessen",
    "wof:name":"Jutta Ulrich Rechtsanwalt",
    "wof:placetype":"venue"
},
  "geometry": {"coordinates":[8.5769529343,50.7677726746],"type":"Point"}
}