{
  "type": "Feature",
  "properties": {
    "iso:country":"DE",
    "sg:address":"Mannheimer Str. 58",
    "sg:city":"Edingen-Neckarhausen",
    "sg:phone":"+49 6203/892513",
    "sg:postcode":"68535",
    "sg:province":"Baden-W\u00fcrttemberg",
    "wof:name":"Complete Interline Kommsionier- Und Distributions",
    "wof:placetype":"venue"
},
  "geometry": {"coordinates":[8.596476,49.453037],"type":"Point"}
}