{
  "type": "Feature",
  "properties": {
    "iso:country":"DE",
    "sg:address":"Hinsbergstr. 19",
    "sg:city":"Wuppertal",
    "sg:phone":"+49 202/599426",
    "sg:postcode":"42287",
    "sg:province":"Nordrhein-Westfalen",
    "wof:name":"Fairsicherungsladen Holger Haselhorst",
    "wof:placetype":"venue"
},
  "geometry": {"coordinates":[7.1863250732,51.2604904175],"type":"Point"}
}