{
  "type": "Feature",
  "properties": {
    "iso:country":"DE",
    "sg:address":"Alte Eisenstr. 1",
    "sg:city":"Bad Laasphe",
    "sg:phone":"+49 2752/5413",
    "sg:postcode":"57334",
    "sg:province":"Nordrhein-Westfalen",
    "wof:name":"Erich Rau",
    "wof:placetype":"venue"
},
  "geometry": {"coordinates":[8.353581,50.873669],"type":"Point"}
}