{
  "type": "Feature",
  "properties": {
    "iso:country":"DE",
    "sg:address":"Obere Hof\u00e4ckerstr. 4",
    "sg:city":"Hafenlohr",
    "sg:phone":"+49 9391/6445",
    "sg:postcode":"97840",
    "sg:province":"Bayern",
    "wof:name":"Fritz Schwab",
    "wof:placetype":"venue"
},
  "geometry": {"coordinates":[9.598577,49.862072],"type":"Point"}
}