{
  "type": "Feature",
  "properties": {
    "iso:country":"DE",
    "sg:address":"Wegern 19",
    "sg:city":"Hunderdorf",
    "sg:phone":"+49 9961/497",
    "sg:postcode":"94336",
    "sg:province":"Bayern",
    "wof:name":"Johann Feldmeier",
    "wof:placetype":"venue"
},
  "geometry": {"coordinates":[12.7409477234,48.9587898254],"type":"Point"}
}