{
  "type": "Feature",
  "properties": {
    "iso:country":"DE",
    "sg:address":"Heideweg 24",
    "sg:city":"Oerlinghausen",
    "sg:phone":"+49 5202/7512",
    "sg:postcode":"33813",
    "sg:province":"Nordrhein-Westfalen",
    "wof:name":"H. Und H. Linnenbr\u00fcgger Gmbh",
    "wof:placetype":"venue"
},
  "geometry": {"coordinates":[8.643092,51.932137],"type":"Point"}
}