{
  "type": "Feature",
  "properties": {
    "iso:country":"DE",
    "sg:address":"Talstr.",
    "sg:city":"Eschweiler",
    "sg:postcode":"52249",
    "sg:province":"Nordrhein-Westfalen",
    "wof:name":"Kaisers Markt",
    "wof:placetype":"venue"
},
  "geometry": {"coordinates":[6.2644348145,50.8140144348],"type":"Point"}
}