{
  "type": "Feature",
  "properties": {
    "iso:country":"DE",
    "sg:address":"Bahnhofstr. 6",
    "sg:city":"Breddorf",
    "sg:phone":"+49 4285/247",
    "sg:postcode":"27412",
    "sg:province":"Niedersachsen",
    "wof:name":"Cord Drewes",
    "wof:placetype":"venue"
},
  "geometry": {"coordinates":[9.086335,53.287315],"type":"Point"}
}