{
  "type": "Feature",
  "properties": {
    "iso:country":"DE",
    "sg:address":"Middelicher Str. 12",
    "sg:city":"Gelsenkirchen",
    "sg:phone":"+49 209/785442",
    "sg:postcode":"45891",
    "sg:province":"Nordrhein-Westfalen",
    "wof:name":"Rudolf Leuschner",
    "wof:placetype":"venue"
},
  "geometry": {"coordinates":[7.081843853,51.5695381165],"type":"Point"}
}