{
  "type": "Feature",
  "properties": {
    "iso:country":"DE",
    "sg:address":"Kantstr. 24",
    "sg:city":"Unna",
    "sg:phone":"+49 2303/13199",
    "sg:postcode":"59425",
    "sg:province":"Nordrhein-Westfalen",
    "wof:name":"Architekturb\u00fcro Dipl.-ing. Horst Sickmann",
    "wof:placetype":"venue"
},
  "geometry": {"coordinates":[7.6871881485,51.5394935608],"type":"Point"}
}