{
  "type": "Feature",
  "properties": {
    "iso:country":"DE",
    "sg:address":"Teichstr. 2 a",
    "sg:city":"Ottendorf-Okrilla",
    "sg:phone":"+49 35205/71807",
    "sg:postcode":"01458",
    "sg:province":"Sachsen",
    "wof:name":"Sven Stemmildt Rechtsanwalt",
    "wof:placetype":"venue"
},
  "geometry": {"coordinates":[13.8463964462,51.1831054688],"type":"Point"}
}