{
  "type": "Feature",
  "properties": {
    "iso:country":"DE",
    "sg:address":"Im Heubruch 23 b",
    "sg:city":"Seevetal",
    "sg:phone":"+49 4105/51530",
    "sg:postcode":"21218",
    "sg:province":"Niedersachsen",
    "wof:name":"Johannes Friese B\u00fcrobedarf",
    "wof:placetype":"venue"
},
  "geometry": {"coordinates":[9.997198,53.389881],"type":"Point"}
}