{
  "type": "Feature",
  "properties": {
    "iso:country":"DE",
    "sg:address":"St.-Bruno-Str. 7",
    "sg:city":"Estenfeld",
    "sg:phone":"+49 9305/565",
    "sg:postcode":"97230",
    "sg:province":"Bayern",
    "wof:name":"Hans R\u00f6der",
    "wof:placetype":"venue"
},
  "geometry": {"coordinates":[10.00218,49.824291],"type":"Point"}
}