{
  "type": "Feature",
  "properties": {
    "iso:country":"DE",
    "sg:address":"W\u00fcrzburger Str. 499",
    "sg:city":"F\u00fcrth",
    "sg:phone":"+49 911/754776",
    "sg:postcode":"90768",
    "sg:province":"Bayern",
    "wof:name":"Gerhard Gr\u00e4f",
    "wof:placetype":"venue"
},
  "geometry": {"coordinates":[10.94466,49.484905],"type":"Point"}
}