{
  "type": "Feature",
  "properties": {
    "iso:country":"DE",
    "sg:address":"Martin-Luther-Str. 5 a",
    "sg:city":"Templin",
    "sg:phone":"+49 3987/409011",
    "sg:postcode":"17268",
    "sg:province":"Brandenburg",
    "wof:name":"Pizza Profis",
    "wof:placetype":"venue"
},
  "geometry": {"coordinates":[13.4985599518,53.1202354431],"type":"Point"}
}