{
  "type": "Feature",
  "properties": {
    "iso:country":"DE",
    "sg:address":"W\u00f6lfelstr. 20",
    "sg:city":"Bayreuth",
    "sg:phone":"+49 921/65979",
    "sg:postcode":"95444",
    "sg:province":"Bayern",
    "wof:name":"Pizzeria-restaurant Quetschn",
    "wof:placetype":"venue"
},
  "geometry": {"coordinates":[11.5794019699,49.9454917908],"type":"Point"}
}