{
  "type": "Feature",
  "properties": {
    "iso:country":"DE",
    "sg:address":"M\u00e4rkerweg 75",
    "sg:city":"Hamburg",
    "sg:phone":"+49 40/5526969",
    "sg:postcode":"22455",
    "sg:province":"Hamburg",
    "wof:name":"Albrecht & Birkefeld Gmbh & Co.",
    "wof:placetype":"venue"
},
  "geometry": {"coordinates":[9.9560289383,53.6420326233],"type":"Point"}
}