{
  "type": "Feature",
  "properties": {
    "iso:country":"DE",
    "sg:address":"Hehnkamp 8",
    "sg:city":"Jevenstedt",
    "sg:phone":"+49 4337/1074",
    "sg:postcode":"24808",
    "sg:province":"Schleswig-Holstein",
    "wof:name":"Hans-j\u00fcrgen Struve Ingenieur",
    "wof:placetype":"venue"
},
  "geometry": {"coordinates":[9.6712493896,54.2324371338],"type":"Point"}
}