{
  "type": "Feature",
  "properties": {
    "iso:country":"DE",
    "sg:address":"Parkstr. 3",
    "sg:city":"Ehlscheid",
    "sg:phone":"+49 2634/6560",
    "sg:postcode":"56581",
    "sg:province":"Rheinland-Pfalz",
    "wof:name":"Hotel Haus Westerwald",
    "wof:placetype":"venue"
},
  "geometry": {"coordinates":[7.4701609612,50.5159072876],"type":"Point"}
}