{
  "type": "Feature",
  "properties": {
    "iso:country":"DE",
    "sg:address":"Katzenl\u00fcckstr. 12",
    "sg:city":"Hofheim",
    "sg:phone":"+49 6192/7992",
    "sg:postcode":"65719",
    "sg:province":"Hessen",
    "wof:name":"Kurt Kreutzer Architekt",
    "wof:placetype":"venue"
},
  "geometry": {"coordinates":[8.398439,50.109257],"type":"Point"}
}