{
  "type": "Feature",
  "properties": {
    "iso:country":"DE",
    "sg:address":"Maelostr. 2",
    "sg:city":"Gelsenkirchen",
    "sg:phone":"+49 209/37321",
    "sg:postcode":"45894",
    "sg:province":"Nordrhein-Westfalen",
    "wof:name":"Detlev Posdziech Steuerberater",
    "wof:placetype":"venue"
},
  "geometry": {"coordinates":[7.0530920029,51.5763435364],"type":"Point"}
}