{
  "type": "Feature",
  "properties": {
    "iso:country":"DE",
    "sg:address":"Kaiser-Karl-Str. 2",
    "sg:city":"Pressig",
    "sg:phone":"+49 9265/1081",
    "sg:postcode":"96332",
    "sg:province":"Bayern",
    "wof:name":"E. Suffa",
    "wof:placetype":"venue"
},
  "geometry": {"coordinates":[11.317603,50.363068],"type":"Point"}
}