{
  "type": "Feature",
  "properties": {
    "iso:country":"DE",
    "sg:address":"Neue ABC-Str. 10",
    "sg:city":"Hamburg",
    "sg:phone":"+49 40/353636",
    "sg:postcode":"20354",
    "sg:province":"Hamburg",
    "wof:name":"Yorks Beim G\u00e4nsemarkt Lederwaren York Brecht",
    "wof:placetype":"venue"
},
  "geometry": {"coordinates":[9.986325,53.555367],"type":"Point"}
}