{
  "type": "Feature",
  "properties": {
    "iso:country":"DE",
    "sg:address":"Schillerstr. 75",
    "sg:city":"Gerlingen",
    "sg:phone":"+49 7156/43030",
    "sg:postcode":"70839",
    "sg:province":"Baden-W\u00fcrttemberg",
    "wof:name":"B\u00fchr Lufttechnik Gmbh",
    "wof:placetype":"venue"
},
  "geometry": {"coordinates":[9.07045,48.80389],"type":"Point"}
}