{
  "type": "Feature",
  "properties": {
    "iso:country":"DE",
    "sg:address":"Am Kr\u00e4henberg 10",
    "sg:city":"Fa\u00dfberg",
    "sg:phone":"+49 5053/1246",
    "sg:postcode":"29328",
    "sg:province":"Niedersachsen",
    "wof:name":"Edmund Vollbrecht",
    "wof:placetype":"venue"
},
  "geometry": {"coordinates":[10.119898,52.868637],"type":"Point"}
}