{
  "type": "Feature",
  "properties": {
    "iso:country":"DE",
    "sg:address":"Schafweidstr. 37",
    "sg:city":"Augsburg",
    "sg:phone":"+49 821/8030",
    "sg:postcode":"86179",
    "sg:province":"Bayern",
    "wof:name":"Wafa Kunststofftechnik Gmbh",
    "wof:placetype":"venue"
},
  "geometry": {"coordinates":[10.898458,48.320889],"type":"Point"}
}