{
  "type": "Feature",
  "properties": {
    "iso:country":"DE",
    "sg:address":"Adolf-Theis-Str. 4-8",
    "sg:city":"Gladenbach",
    "sg:phone":"+49 6462/912308",
    "sg:postcode":"35075",
    "sg:province":"Hessen",
    "wof:name":"G. Schaub",
    "wof:placetype":"venue"
},
  "geometry": {"coordinates":[8.585152626,50.7694168091],"type":"Point"}
}