{
  "type": "Feature",
  "properties": {
    "iso:country":"DE",
    "sg:address":"Hauptstr. 144",
    "sg:city":"Heiligenhaus",
    "sg:phone":"+49 2056/6647",
    "sg:postcode":"42579",
    "sg:province":"Nordrhein-Westfalen",
    "wof:name":"Restaurant Ratskeller",
    "wof:placetype":"venue"
},
  "geometry": {"coordinates":[6.9714899063,51.3264350891],"type":"Point"}
}