{
  "type": "Feature",
  "properties": {
    "iso:country":"DE",
    "sg:address":"Hauptstr. 42",
    "sg:city":"Markt Wald",
    "sg:phone":"+49 8262/1763",
    "sg:postcode":"86865",
    "sg:province":"Bayern",
    "wof:name":"Dachdeckerei Sandow Gmbh",
    "wof:placetype":"venue"
},
  "geometry": {"coordinates":[10.583202,48.138527],"type":"Point"}
}