{
  "type": "Feature",
  "properties": {
    "iso:country":"DE",
    "sg:address":"Regensburger Str. 57 a",
    "sg:city":"Teublitz",
    "sg:phone":"+49 9471/991044",
    "sg:postcode":"93158",
    "sg:province":"Bayern",
    "wof:name":"Pizza-blitz",
    "wof:placetype":"venue"
},
  "geometry": {"coordinates":[12.0858631134,49.2216453552],"type":"Point"}
}