{
  "type": "Feature",
  "properties": {
    "iso:country":"DE",
    "sg:address":"Im Langenbroich 20",
    "sg:city":"J\u00fclich",
    "sg:phone":"+49 2461/93520",
    "sg:postcode":"52428",
    "sg:province":"Nordrhein-Westfalen",
    "wof:name":"Mateck Gmbh",
    "wof:placetype":"venue"
},
  "geometry": {"coordinates":[6.38278,50.912621],"type":"Point"}
}