{
  "type": "Feature",
  "properties": {
    "iso:country":"DE",
    "sg:address":"Von-Bodelschwingh-Stra\u00dfe 4",
    "sg:city":"Soltau",
    "sg:phone":"+49 5191",
    "sg:postcode":"29614",
    "sg:province":"Niedersachsen",
    "wof:name":"Sprengel Gmbh, Markennamenentwicklung",
    "wof:placetype":"venue"
},
  "geometry": {"coordinates":[9.849882,52.987579],"type":"Point"}
}