{
  "type": "Feature",
  "properties": {
    "iso:country":"DE",
    "sg:address":"B\u00f6singer Str. 32",
    "sg:city":"B\u00f6singen",
    "sg:phone":"+49 7404/91350",
    "sg:postcode":"78662",
    "sg:province":"Baden-W\u00fcrttemberg",
    "wof:name":"G. Kobel",
    "wof:placetype":"venue"
},
  "geometry": {"coordinates":[8.574182,48.224659],"type":"Point"}
}