{
  "type": "Feature",
  "properties": {
    "iso:country":"DE",
    "sg:address":"Hebelstr. 21",
    "sg:city":"Bad Sch\u00f6nborn",
    "sg:phone":"+49 7253/33033",
    "sg:postcode":"76669",
    "sg:province":"Baden-W\u00fcrttemberg",
    "wof:name":"Hans-reinhard Dissert Anlageberater",
    "wof:placetype":"venue"
},
  "geometry": {"coordinates":[8.648021698,49.2212600708],"type":"Point"}
}