{
  "type": "Feature",
  "properties": {
    "iso:country":"DE",
    "sg:address":"Tiefes Moor 14",
    "sg:city":"Garbsen",
    "sg:phone":"+49 5137/89920",
    "sg:postcode":"30823",
    "sg:province":"Niedersachsen",
    "wof:name":"Rudolf Hofmann",
    "wof:placetype":"venue"
},
  "geometry": {"coordinates":[9.5976953506,52.4156684875],"type":"Point"}
}