{
  "type": "Feature",
  "properties": {
    "iso:country":"DE",
    "sg:address":"Wolfinger Str. 5",
    "sg:city":"Pocking",
    "sg:phone":"+49 8531/4091",
    "sg:postcode":"94060",
    "sg:province":"Bayern",
    "wof:name":"Stadtb\u00fccherei",
    "wof:placetype":"venue"
},
  "geometry": {"coordinates":[13.312138,48.400295],"type":"Point"}
}