{
  "type": "Feature",
  "properties": {
    "iso:country":"DE",
    "sg:address":"Marienstr. 12",
    "sg:city":"\u00dcbach-Palenberg",
    "sg:phone":"+49 2451/41032",
    "sg:postcode":"52531",
    "sg:province":"Nordrhein-Westfalen",
    "wof:name":"Michael Reinartz",
    "wof:placetype":"venue"
},
  "geometry": {"coordinates":[6.0941400528,50.9256744385],"type":"Point"}
}