{
  "type": "Feature",
  "properties": {
    "iso:country":"DE",
    "sg:address":"K\u00fcppelsteiner Str. 10",
    "sg:city":"Remscheid",
    "sg:phone":"+49 2191/71269",
    "sg:postcode":"42857",
    "sg:province":"Nordrhein-Westfalen",
    "wof:name":"Geldsetzer Gmbh",
    "wof:placetype":"venue"
},
  "geometry": {"coordinates":[7.1524200439,51.1611938477],"type":"Point"}
}