{
  "type": "Feature",
  "properties": {
    "iso:country":"DE",
    "sg:address":"Koblenzer Str 120",
    "sg:city":"Neuss",
    "sg:phone":"+49 2131/9370",
    "sg:postcode":"41468",
    "sg:province":"Nordrhein-Westfalen",
    "wof:name":"Aluminium Norf Gmbh",
    "wof:placetype":"venue"
},
  "geometry": {"coordinates":[6.7816,51.155369],"type":"Point"}
}