{
  "type": "Feature",
  "properties": {
    "iso:country":"DE",
    "sg:address":"Pfarrer-Byns-Str. 1",
    "sg:city":"Bonn",
    "sg:phone":"+49 228/5220",
    "sg:postcode":"53121",
    "sg:province":"Nordrhein-Westfalen",
    "wof:name":"Huk-coburg-allgemeine Versicherungs-ag",
    "wof:placetype":"venue"
},
  "geometry": {"coordinates":[7.0648488998,50.7238769531],"type":"Point"}
}