{
  "type": "Feature",
  "properties": {
    "iso:country":"DE",
    "sg:address":"Schreinerweg 1",
    "sg:city":"M\u00f6ssingen",
    "sg:phone":"+49 7473/4634",
    "sg:postcode":"72116",
    "sg:province":"Baden-W\u00fcrttemberg",
    "wof:name":"K. Maier",
    "wof:placetype":"venue"
},
  "geometry": {"coordinates":[9.0671977997,48.4111022949],"type":"Point"}
}