{
  "type": "Feature",
  "properties": {
    "iso:country":"DE",
    "sg:address":"Alte Ziegelei 9",
    "sg:city":"Solingen",
    "sg:phone":"+49 212/592533",
    "sg:postcode":"42653",
    "sg:province":"Nordrhein-Westfalen",
    "wof:name":"Fachhandel F\u00fcr Schleif- U. Polierwerzeuge",
    "wof:placetype":"venue"
},
  "geometry": {"coordinates":[7.0773758888,51.1992912292],"type":"Point"}
}