{
  "type": "Feature",
  "properties": {
    "iso:country":"DE",
    "sg:address":"Hanferstr. 5",
    "sg:city":"Freiburg",
    "sg:phone":"+49 761/16405",
    "sg:postcode":"79108",
    "sg:province":"Baden-W\u00fcrttemberg",
    "wof:name":"Bembe Parkett",
    "wof:placetype":"venue"
},
  "geometry": {"coordinates":[7.8173718452,48.0390853882],"type":"Point"}
}