{
  "type": "Feature",
  "properties": {
    "iso:country":"DE",
    "sg:address":"Kleiner Kornweg 43",
    "sg:city":"Kelsterbach",
    "sg:postcode":"65451",
    "sg:province":"Hessen",
    "wof:name":"Hille Betriebs- Und Verwaltungsgesellschaft Mbh",
    "wof:placetype":"venue"
},
  "geometry": {"coordinates":[8.52647,50.055031],"type":"Point"}
}