{
  "type": "Feature",
  "properties": {
    "iso:country":"DE",
    "sg:address":"Schie\u00dfst\u00e4ttstrasse 28",
    "sg:city":"M\u00fcnchen",
    "sg:phone":"+49 89/5004205",
    "sg:postcode":"80339",
    "sg:province":"Bayern",
    "wof:name":"Triangle",
    "wof:placetype":"venue"
},
  "geometry": {"coordinates":[11.54529953,48.1353759766],"type":"Point"}
}