{
  "type": "Feature",
  "properties": {
    "iso:country":"DE",
    "sg:address":"Kauerndorfer Allee",
    "sg:city":"Altenburg",
    "sg:phone":"+49 3447/834344",
    "sg:postcode":"04600",
    "sg:province":"Th\u00fcringen",
    "wof:name":"Schilling-reisen",
    "wof:placetype":"venue"
},
  "geometry": {"coordinates":[12.4248523712,50.9965057373],"type":"Point"}
}