{
  "type": "Feature",
  "properties": {
    "iso:country":"DE",
    "sg:address":"Ettalstr. 40",
    "sg:city":"M\u00fcnchen",
    "sg:phone":"+49 89/7194751",
    "sg:postcode":"81377",
    "sg:province":"Bayern",
    "wof:name":"Manfred Adelberg Anlageberater",
    "wof:placetype":"venue"
},
  "geometry": {"coordinates":[11.514500618,48.1171188354],"type":"Point"}
}