{
  "type": "Feature",
  "properties": {
    "iso:country":"DE",
    "sg:address":"Lindwurmstr. 41 - 43",
    "sg:city":"M\u00fcnchen",
    "sg:phone":"+49 89/535040",
    "sg:postcode":"80337",
    "sg:province":"Bayern",
    "wof:name":"Eduard Plazotta Gmbh",
    "wof:placetype":"venue"
},
  "geometry": {"coordinates":[11.5614318848,48.1307411194],"type":"Point"}
}