{
  "type": "Feature",
  "properties": {
    "iso:country":"DE",
    "sg:address":"Marzellenstr. 50",
    "sg:city":"K\u00f6ln",
    "sg:phone":"+49 221/137322",
    "sg:postcode":"50668",
    "sg:province":"Nordrhein-Westfalen",
    "wof:name":"Restaurant Jaipur",
    "wof:placetype":"venue"
},
  "geometry": {"coordinates":[6.9561109543,50.9440803528],"type":"Point"}
}