{
  "type": "Feature",
  "properties": {
    "iso:country":"DE",
    "sg:address":"Karlstr. 8",
    "sg:city":"Blaubeuren",
    "sg:phone":"+49 7344/5027",
    "sg:postcode":"89143",
    "sg:province":"Baden-W\u00fcrttemberg",
    "wof:name":"Hotel Adler",
    "wof:placetype":"venue"
},
  "geometry": {"coordinates":[9.7843408585,48.4120368958],"type":"Point"}
}