{
  "type": "Feature",
  "properties": {
    "iso:country":"DE",
    "sg:address":"K\u00f6nigstr. 7",
    "sg:city":"Telgte",
    "sg:phone":"+49 2504/1709",
    "sg:postcode":"48291",
    "sg:province":"Nordrhein-Westfalen",
    "wof:name":"Heinz Rickhoff",
    "wof:placetype":"venue"
},
  "geometry": {"coordinates":[7.783216,51.984573],"type":"Point"}
}