{
  "type": "Feature",
  "properties": {
    "iso:country":"DE",
    "sg:address":"Rotenburger Str. 122A",
    "sg:city":"Osnabr\u00fcck",
    "sg:postcode":"49084",
    "sg:province":"Niedersachsen",
    "wof:name":"Ikos-service Kg",
    "wof:placetype":"venue"
},
  "geometry": {"coordinates":[8.067389,52.274559],"type":"Point"}
}