{
  "type": "Feature",
  "properties": {
    "iso:country":"DE",
    "sg:address":"Forsthausstr. 20",
    "sg:city":"B\u00fcrstadt",
    "sg:phone":"+49 6206/7283",
    "sg:postcode":"68642",
    "sg:province":"Hessen",
    "wof:name":"Zoohaus B\u00fcrstadt Helmut Ofenloch Gmbh & Co. Kg",
    "wof:placetype":"venue"
},
  "geometry": {"coordinates":[8.470354,49.648281],"type":"Point"}
}