{
  "type": "Feature",
  "properties": {
    "iso:country":"DE",
    "sg:address":"Weberhofstr. 10",
    "sg:city":"Gr\u00e4felfing",
    "sg:phone":"+49 89/8542426",
    "sg:postcode":"82166",
    "sg:province":"Bayern",
    "wof:name":"Hans Werdich Bauunternehmung Gmbh",
    "wof:placetype":"venue"
},
  "geometry": {"coordinates":[11.435544,48.111847],"type":"Point"}
}