{
  "type": "Feature",
  "properties": {
    "iso:country":"DE",
    "sg:address":"In der Fleute 143",
    "sg:city":"Wuppertal",
    "sg:phone":"+49 202/260960",
    "sg:postcode":"42389",
    "sg:province":"Nordrhein-Westfalen",
    "wof:name":"R\u00fclke & Schmidt Internationale Speditions-gmbh",
    "wof:placetype":"venue"
},
  "geometry": {"coordinates":[7.260665,51.279274],"type":"Point"}
}