{
  "type": "Feature",
  "properties": {
    "iso:country":"DE",
    "sg:address":"Kantstr. 4",
    "sg:city":"Monheim",
    "sg:phone":"+49 2173/65691",
    "sg:postcode":"40789",
    "sg:province":"Nordrhein-Westfalen",
    "wof:name":"Helmut Kl\u00f6s",
    "wof:placetype":"venue"
},
  "geometry": {"coordinates":[6.8916020393,51.1193351746],"type":"Point"}
}