{
  "type": "Feature",
  "properties": {
    "iso:country":"DE",
    "sg:address":"Ippendorfer Allee 14b",
    "sg:city":"Bonn",
    "sg:phone":"+49 228/285011",
    "sg:postcode":"53127",
    "sg:province":"Nordrhein-Westfalen",
    "wof:name":"Bda-stiftung",
    "wof:placetype":"venue"
},
  "geometry": {"coordinates":[7.0845937729,50.7100067139],"type":"Point"}
}