{
  "type": "Feature",
  "properties": {
    "iso:country":"DE",
    "sg:address":"Obersaurenbach 22",
    "sg:city":"Ruppichteroth",
    "sg:phone":"+49 2295/902214",
    "sg:postcode":"53809",
    "sg:province":"Nordrhein-Westfalen",
    "wof:name":"Island-pullover",
    "wof:placetype":"venue"
},
  "geometry": {"coordinates":[7.477575,50.850849],"type":"Point"}
}