{
  "type": "Feature",
  "properties": {
    "iso:country":"DE",
    "sg:address":"Hilchenbacher Str. 9a",
    "sg:city":"Krostitz",
    "sg:phone":"+49 34295/7440",
    "sg:postcode":"04509",
    "sg:province":"Sachsen",
    "wof:name":"B\u00e4ko Leipzig B\u00e4cker- Und Konditorengenossenschaft Eg",
    "wof:placetype":"venue"
},
  "geometry": {"coordinates":[12.452761,51.472637],"type":"Point"}
}