{
  "type": "Feature",
  "properties": {
    "iso:country":"DE",
    "sg:address":"Gartenstr. 82",
    "sg:city":"Langen",
    "sg:phone":"+49 6103/21178",
    "sg:postcode":"63225",
    "sg:province":"Hessen",
    "wof:name":"Garten-apotheke Dr. Friedrich Brunisch",
    "wof:placetype":"venue"
},
  "geometry": {"coordinates":[8.663578,49.991917],"type":"Point"}
}