{
  "type": "Feature",
  "properties": {
    "iso:country":"DE",
    "sg:address":"Kannenb\u00e4ckerstr. 20",
    "sg:city":"Rheinbach",
    "sg:postcode":"53359",
    "sg:province":"Nordrhein-Westfalen",
    "wof:name":"Astc Advanced Sensor And Telematic Components Gmbh",
    "wof:placetype":"venue"
},
  "geometry": {"coordinates":[6.986907959,50.605140686],"type":"Point"}
}