{
  "type": "Feature",
  "properties": {
    "iso:country":"DE",
    "sg:address":"Kirchstr. 25",
    "sg:city":"Berlin",
    "sg:phone":"+49 30/4045503",
    "sg:postcode":"10557",
    "sg:province":"Berlin",
    "wof:name":"A. Plappert",
    "wof:placetype":"venue"
},
  "geometry": {"coordinates":[13.349623,52.524185],"type":"Point"}
}