{
  "type": "Feature",
  "properties": {
    "iso:country":"DE",
    "sg:address":"Kreuzstr. 29",
    "sg:city":"Gransee",
    "sg:postcode":"16775",
    "sg:province":"Brandenburg",
    "wof:name":"Domaine Gransee Landwirtschaftsges. Mbh",
    "wof:placetype":"venue"
},
  "geometry": {"coordinates":[13.16137,53.008045],"type":"Point"}
}