{
  "type": "Feature",
  "properties": {
    "iso:country":"DE",
    "sg:address":"Schmiedstr. 7",
    "sg:city":"Haldenwang",
    "sg:phone":"+49 8222/2369",
    "sg:postcode":"89356",
    "sg:province":"Bayern",
    "wof:name":"K. Schedel",
    "wof:placetype":"venue"
},
  "geometry": {"coordinates":[10.432867,48.44902],"type":"Point"}
}