{
  "type": "Feature",
  "properties": {
    "iso:country":"DE",
    "sg:address":"Ostring 4",
    "sg:city":"Karlsruhe",
    "sg:phone":"+49 721/617384",
    "sg:postcode":"76131",
    "sg:province":"Baden-W\u00fcrttemberg",
    "wof:name":"Fahrrad Sb Markt Gmbh",
    "wof:placetype":"venue"
},
  "geometry": {"coordinates":[8.438695,49.011116],"type":"Point"}
}