{
  "type": "Feature",
  "properties": {
    "iso:country":"DE",
    "sg:address":"Hauptstr. 62",
    "sg:city":"Marxen",
    "sg:phone":"+49 4185/4377",
    "sg:postcode":"21439",
    "sg:province":"Niedersachsen",
    "wof:name":"Hinrich Rave Kg",
    "wof:placetype":"venue"
},
  "geometry": {"coordinates":[10.0094451904,53.3147392273],"type":"Point"}
}