{
  "type": "Feature",
  "properties": {
    "iso:country":"DE",
    "sg:address":"R\u00fcdesheimer Str. 5",
    "sg:city":"M\u00fcnchen",
    "sg:phone":"+49 89/574094",
    "sg:postcode":"80686",
    "sg:province":"Bayern",
    "wof:name":"Weiland Und Kollegen Rechtsanw\u00e4lte",
    "wof:placetype":"venue"
},
  "geometry": {"coordinates":[11.5235452652,48.1326408386],"type":"Point"}
}