{
  "type": "Feature",
  "properties": {
    "iso:country":"DE",
    "sg:address":"Kleiner Moorweg 16",
    "sg:city":"Tornesch",
    "sg:phone":"+49 4122/51597",
    "sg:postcode":"25436",
    "sg:province":"Schleswig-Holstein",
    "wof:name":"H\u00fcckel Maschinen- Und Niro-apparatebau Gmbh",
    "wof:placetype":"venue"
},
  "geometry": {"coordinates":[9.7279310226,53.6929893494],"type":"Point"}
}