{
  "type": "Feature",
  "properties": {
    "iso:country":"DE",
    "sg:address":"Br\u00fcckenstr. 3",
    "sg:city":"F\u00fcrth",
    "sg:phone":"+49 911/7659351",
    "sg:postcode":"90768",
    "sg:province":"Bayern",
    "wof:name":"Birgit Plack",
    "wof:placetype":"venue"
},
  "geometry": {"coordinates":[10.9678001404,49.5268859863],"type":"Point"}
}