{
  "type": "Feature",
  "properties": {
    "iso:country":"DE",
    "sg:address":"Im Furt 1",
    "sg:city":"Kreuzwertheim",
    "sg:phone":"+49 9342/1023",
    "sg:postcode":"97892",
    "sg:province":"Bayern",
    "wof:name":"Behringer Bauunternehmen Gmbh",
    "wof:placetype":"venue"
},
  "geometry": {"coordinates":[9.515685,49.766335],"type":"Point"}
}