{
  "type": "Feature",
  "properties": {
    "iso:country":"DE",
    "sg:address":"Wangener Str. 21",
    "sg:city":"Schorndorf",
    "sg:phone":"+49 7181/3093",
    "sg:postcode":"73614",
    "sg:province":"Baden-W\u00fcrttemberg",
    "wof:name":"Walter Dannenhauer",
    "wof:placetype":"venue"
},
  "geometry": {"coordinates":[9.552833,48.777611],"type":"Point"}
}