{
  "type": "Feature",
  "properties": {
    "iso:country":"DE",
    "sg:address":"R\u00f6merstr. 17",
    "sg:city":"Metzingen",
    "sg:phone":"+49 7123/9630",
    "sg:postcode":"72555",
    "sg:province":"Baden-W\u00fcrttemberg",
    "wof:name":"Brodbeck Bau- Und Verwaltungs-gmbh",
    "wof:placetype":"venue"
},
  "geometry": {"coordinates":[9.286395,48.532913],"type":"Point"}
}