{
  "type": "Feature",
  "properties": {
    "iso:country":"DE",
    "sg:address":"Breitscheidstr. 32",
    "sg:city":"N\u00fcrnberg",
    "sg:phone":"+49 911/442902",
    "sg:postcode":"90459",
    "sg:province":"Bayern",
    "wof:name":"F. M. Lohrey",
    "wof:placetype":"venue"
},
  "geometry": {"coordinates":[11.084014,49.44146],"type":"Point"}
}