{
  "type": "Feature",
  "properties": {
    "iso:country":"DE",
    "sg:address":"Kirchstr. 53",
    "sg:city":"Hambr\u00fccken",
    "sg:phone":"+49 7255/9627",
    "sg:postcode":"76707",
    "sg:province":"Baden-W\u00fcrttemberg",
    "wof:name":"Monika Weider",
    "wof:placetype":"venue"
},
  "geometry": {"coordinates":[8.5385370255,49.185256958],"type":"Point"}
}