{
  "type": "Feature",
  "properties": {
    "iso:country":"DE",
    "sg:address":"Zum Dammfelde 18",
    "sg:city":"K\u00f6ln",
    "sg:phone":"+49 221/493862",
    "sg:postcode":"50859",
    "sg:province":"Nordrhein-Westfalen",
    "wof:name":"Hans Kaltenbach",
    "wof:placetype":"venue"
},
  "geometry": {"coordinates":[6.8296937943,50.9464302063],"type":"Point"}
}