{
  "type": "Feature",
  "properties": {
    "iso:country":"DE",
    "sg:address":"Rottweiler Str. 8 c",
    "sg:city":"Berlin",
    "sg:phone":"+49 30/7746616",
    "sg:postcode":"12247",
    "sg:province":"Berlin",
    "wof:name":"Peter Troester Holzbildhauer",
    "wof:placetype":"venue"
},
  "geometry": {"coordinates":[13.358773,52.443596],"type":"Point"}
}