{
  "type": "Feature",
  "properties": {
    "iso:country":"DE",
    "sg:address":"Aschaffstr. 2",
    "sg:city":"Waldaschaff",
    "sg:phone":"+49 6095/8742",
    "sg:postcode":"63857",
    "sg:province":"Bayern",
    "wof:name":"Metzgerei Heinz Jung Gmbh",
    "wof:placetype":"venue"
},
  "geometry": {"coordinates":[9.3007488251,49.9723243713],"type":"Point"}
}