{
  "type": "Feature",
  "properties": {
    "iso:country":"DE",
    "sg:address":"Langenwischstr. 33",
    "sg:city":"Delmenhorst",
    "sg:phone":"+49 4221/70711",
    "sg:postcode":"27751",
    "sg:province":"Niedersachsen",
    "wof:name":"I. Brune Heissmangel",
    "wof:placetype":"venue"
},
  "geometry": {"coordinates":[8.6778736115,53.052406311],"type":"Point"}
}