{
  "type": "Feature",
  "properties": {
    "iso:country":"DE",
    "sg:address":"Birkenweg 6",
    "sg:city":"Gerwisch",
    "sg:phone":"+49 39292/26988",
    "sg:postcode":"39175",
    "sg:province":"Sachsen-Anhalt",
    "wof:name":"Burkhard Wolf",
    "wof:placetype":"venue"
},
  "geometry": {"coordinates":[11.7462835312,52.1761207581],"type":"Point"}
}