{
  "type": "Feature",
  "properties": {
    "iso:country":"DE",
    "sg:address":"Matthias-Claudius-Str. 7",
    "sg:city":"Gehrden",
    "sg:phone":"+49 5108/927885",
    "sg:postcode":"30989",
    "sg:province":"Niedersachsen",
    "wof:name":"Kurt Kettemann Immobilienmakler",
    "wof:placetype":"venue"
},
  "geometry": {"coordinates":[9.5915775299,52.3138237],"type":"Point"}
}