{
  "type": "Feature",
  "properties": {
    "iso:country":"DE",
    "sg:address":"Rosenweg 3a",
    "sg:city":"Elchingen",
    "sg:phone":"+49 7308/7694",
    "sg:postcode":"89275",
    "sg:province":"Bayern",
    "wof:name":"Heinz Groner",
    "wof:placetype":"venue"
},
  "geometry": {"coordinates":[10.078368,48.447868],"type":"Point"}
}