{
  "type": "Feature",
  "properties": {
    "iso:country":"DE",
    "sg:address":"Ohmstr. 12",
    "sg:city":"M\u00fcnchen",
    "sg:phone":"+49 89/348286",
    "sg:postcode":"80802",
    "sg:province":"Bayern",
    "wof:name":"Dieter Praske Antiquit\u00e4ten",
    "wof:placetype":"venue"
},
  "geometry": {"coordinates":[11.584699,48.153847],"type":"Point"}
}