{
  "type": "Feature",
  "properties": {
    "iso:country":"DE",
    "sg:address":"Okerweg 25",
    "sg:city":"Kissenbr\u00fcck",
    "sg:phone":"+49 5337/925640",
    "sg:postcode":"38324",
    "sg:province":"Niedersachsen",
    "wof:name":"Drw Spandene Bearbeitung",
    "wof:placetype":"venue"
},
  "geometry": {"coordinates":[10.57174,52.11211],"type":"Point"}
}