{
  "type": "Feature",
  "properties": {
    "iso:country":"DE",
    "sg:address":"Wilhelmstr. 98",
    "sg:city":"Braunschweig",
    "sg:phone":"+49 531/2403891",
    "sg:postcode":"38100",
    "sg:province":"Niedersachsen",
    "wof:name":"Fitnessland Gmbh",
    "wof:placetype":"venue"
},
  "geometry": {"coordinates":[10.5280342102,52.266456604],"type":"Point"}
}