{
  "type": "Feature",
  "properties": {
    "iso:country":"DE",
    "sg:address":"Alfelder Str. 51 A",
    "sg:city":"Hildesheim",
    "sg:phone":"+49 5121/46051",
    "sg:postcode":"31139",
    "sg:province":"Niedersachsen",
    "wof:name":"Brigitte Tute Masseurin",
    "wof:placetype":"venue"
},
  "geometry": {"coordinates":[9.940076,52.140549],"type":"Point"}
}