{
  "type": "Feature",
  "properties": {
    "iso:country":"DE",
    "sg:address":"Baustr. 17",
    "sg:city":"Hameln",
    "sg:phone":"+49 5151/26625",
    "sg:postcode":"31785",
    "sg:province":"Niedersachsen",
    "wof:name":"China-imbi\u00df Hamy",
    "wof:placetype":"venue"
},
  "geometry": {"coordinates":[9.3588352203,52.1061286926],"type":"Point"}
}