{
  "type": "Feature",
  "properties": {
    "iso:country":"DE",
    "sg:address":"Odeonstr. 2",
    "sg:city":"Hannover",
    "sg:phone":"+49 4951/118664",
    "sg:postcode":"30159",
    "sg:province":"Niedersachsen",
    "wof:name":"Odeon Zwo Werbeagentur Gmbh",
    "wof:placetype":"venue"
},
  "geometry": {"coordinates":[9.734532,52.376991],"type":"Point"}
}