{
  "type": "Feature",
  "properties": {
    "iso:country":"DE",
    "sg:address":"Wiesentalstr. 79",
    "sg:city":"L\u00f6rrach",
    "sg:phone":"+49 7621/43603",
    "sg:postcode":"79539",
    "sg:province":"Baden-W\u00fcrttemberg",
    "wof:name":"Anna Parac",
    "wof:placetype":"venue"
},
  "geometry": {"coordinates":[7.6557049751,47.6226654053],"type":"Point"}
}