{
  "type": "Feature",
  "properties": {
    "iso:country":"DE",
    "sg:address":"Eilendorfer Weg 23",
    "sg:city":"Buxtehude",
    "sg:phone":"+49 4161/84636",
    "sg:postcode":"21614",
    "sg:province":"Niedersachsen",
    "wof:name":"W. Soost Ingenieur",
    "wof:placetype":"venue"
},
  "geometry": {"coordinates":[9.6969394684,53.4526138306],"type":"Point"}
}