{
  "type": "Feature",
  "properties": {
    "iso:country":"DE",
    "sg:address":"Waibelweg 16",
    "sg:city":"Memmingen",
    "sg:phone":"+49 8331/86813",
    "sg:postcode":"87700",
    "sg:province":"Bayern",
    "wof:name":"Schlaraffia Bey Den Sieben Schwaben E. V.",
    "wof:placetype":"venue"
},
  "geometry": {"coordinates":[10.1796455383,48.0070114136],"type":"Point"}
}