{
  "type": "Feature",
  "properties": {
    "iso:country":"DE",
    "sg:address":"Sudammsbreite 32",
    "sg:city":"Wolfsburg",
    "sg:phone":"+49 5363/7651",
    "sg:postcode":"38448",
    "sg:province":"Niedersachsen",
    "wof:name":"Natursteinwerk Vorsfelde Gmbh",
    "wof:placetype":"venue"
},
  "geometry": {"coordinates":[10.8580570221,52.4368515015],"type":"Point"}
}