{
  "type": "Feature",
  "properties": {
    "iso:country":"DE",
    "sg:address":"Leonhard-Kraus-Str. 11a",
    "sg:city":"Bad Honnef",
    "sg:phone":"+49 2224/820799",
    "sg:postcode":"53604",
    "sg:province":"Nordrhein-Westfalen",
    "wof:name":"Rechtsanwalt N. Koch",
    "wof:placetype":"venue"
},
  "geometry": {"coordinates":[7.3015379906,50.6676139832],"type":"Point"}
}