{
  "type": "Feature",
  "properties": {
    "iso:country":"DE",
    "sg:address":"St.-Peter-Weg 1",
    "sg:city":"Schwerte",
    "sg:phone":"+49 2304/963170",
    "sg:postcode":"58239",
    "sg:province":"Nordrhein-Westfalen",
    "wof:name":"S. Barthel Steuerberater",
    "wof:placetype":"venue"
},
  "geometry": {"coordinates":[7.5318579674,51.4250946045],"type":"Point"}
}