{
  "type": "Feature",
  "properties": {
    "iso:country":"DE",
    "sg:address":"L\u00e4ngenauer Str. 92",
    "sg:city":"Selb",
    "sg:postcode":"95100",
    "sg:province":"Bayern",
    "wof:name":"Kaufenstein-porzellan Inh. Stefan Kaufenstein",
    "wof:placetype":"venue"
},
  "geometry": {"coordinates":[12.1549949646,50.172039032],"type":"Point"}
}