{
  "type": "Feature",
  "properties": {
    "iso:country":"DE",
    "sg:address":"Raiffeisenstr. 9",
    "sg:city":"Bechtheim",
    "sg:phone":"+49 6242/2160",
    "sg:postcode":"67595",
    "sg:province":"Rheinland-Pfalz",
    "wof:name":"E. Orlemann Weinanbau",
    "wof:placetype":"venue"
},
  "geometry": {"coordinates":[8.2925224304,49.725025177],"type":"Point"}
}