{
  "type": "Feature",
  "properties": {
    "iso:country":"DE",
    "sg:address":"Bismarckstr. 67",
    "sg:city":"Duisburg",
    "sg:phone":"+49 203/3780950",
    "sg:postcode":"47057",
    "sg:province":"Nordrhein-Westfalen",
    "wof:name":"Amira - Ges. F\u00fcr Angewandte Mikroelektronik Regelungs-",
    "wof:placetype":"venue"
},
  "geometry": {"coordinates":[6.784786,51.427605],"type":"Point"}
}