{
  "type": "Feature",
  "properties": {
    "iso:country":"DE",
    "sg:address":"Von-Palm-Str. 18",
    "sg:city":"Schw\u00e4bisch Hall",
    "sg:phone":"+49 791/71592",
    "sg:postcode":"74523",
    "sg:province":"Baden-W\u00fcrttemberg",
    "wof:name":"Ev. Pfarramt Johannes-brenz- Kirche Ii",
    "wof:placetype":"venue"
},
  "geometry": {"coordinates":[9.7210464478,49.1111755371],"type":"Point"}
}