{
  "type": "Feature",
  "properties": {
    "iso:country":"DE",
    "sg:address":"Edisonstr. 5",
    "sg:city":"Hainburg",
    "sg:phone":"+49 6182/4630",
    "sg:postcode":"63512",
    "sg:province":"Hessen",
    "wof:name":"Hildebert Kolb",
    "wof:placetype":"venue"
},
  "geometry": {"coordinates":[8.9638729095,50.068397522],"type":"Point"}
}