{
  "type": "Feature",
  "properties": {
    "iso:country":"DE",
    "sg:address":"Stra\u00dfe der DSF 10 c",
    "sg:city":"G\u00fcsen",
    "sg:phone":"+49 39344/258",
    "sg:postcode":"39317",
    "sg:province":"Sachsen-Anhalt",
    "wof:name":"Johanniter Unfall-hilfe E. V.",
    "wof:placetype":"venue"
},
  "geometry": {"coordinates":[11.977005,52.342037],"type":"Point"}
}