{
  "type": "Feature",
  "properties": {
    "iso:country":"DE",
    "sg:address":"Steller Str. 54",
    "sg:city":"Twistringen",
    "sg:phone":"+49 4243/2469",
    "sg:postcode":"27239",
    "sg:province":"Niedersachsen",
    "wof:name":"Hubert Sch\u00fctte Ingenieur",
    "wof:placetype":"venue"
},
  "geometry": {"coordinates":[8.6483669281,52.7999801636],"type":"Point"}
}