{
  "type": "Feature",
  "properties": {
    "iso:country":"DE",
    "sg:address":"38642",
    "sg:city":"Goslar-Oker",
    "sg:postcode":"38642",
    "sg:province":"Niedersachsen",
    "wof:name":"Volksbank Oker Eg",
    "wof:placetype":"venue"
},
  "geometry": {"coordinates":[10.48563,51.899078],"type":"Point"}
}