{
  "type": "Feature",
  "properties": {
    "iso:country":"DE",
    "sg:address":"Dorfstr. 30",
    "sg:city":"Lehesten",
    "sg:phone":"+49 3641/449076",
    "sg:postcode":"07778",
    "sg:province":"Th\u00fcringen",
    "wof:name":"Franz Donner Rechtsanwalt",
    "wof:placetype":"venue"
},
  "geometry": {"coordinates":[11.5804233551,50.981880188],"type":"Point"}
}