{
  "type": "Feature",
  "properties": {
    "iso:country":"DE",
    "sg:address":"Heimeranstr. 61",
    "sg:city":"M\u00fcnchen",
    "sg:phone":"+49 89/507694",
    "sg:postcode":"80339",
    "sg:province":"Bayern",
    "wof:name":"Xenia Marz",
    "wof:placetype":"venue"
},
  "geometry": {"coordinates":[11.5351362228,48.1335411072],"type":"Point"}
}