{
  "type": "Feature",
  "properties": {
    "iso:country":"DE",
    "sg:address":"Tattersallstr. 19",
    "sg:city":"Mannheim",
    "sg:phone":"+49 621/105277",
    "sg:postcode":"68165",
    "sg:province":"Baden-W\u00fcrttemberg",
    "wof:name":"Hotel-weinstube Goldene Gans",
    "wof:placetype":"venue"
},
  "geometry": {"coordinates":[8.4726676941,49.4810714722],"type":"Point"}
}