{
  "type": "Feature",
  "properties": {
    "iso:country":"DE",
    "sg:address":"Auf Dem Hahnenberg 16",
    "sg:city":"M\u00fclheim-K\u00e4rlich",
    "sg:phone":"+49 4926/3094540",
    "sg:postcode":"56218",
    "sg:province":"Rheinland-Pfalz",
    "wof:name":"Sr Industrieservice U Technische Handelsgmbh",
    "wof:placetype":"venue"
},
  "geometry": {"coordinates":[7.517895,50.394279],"type":"Point"}
}