{
  "type": "Feature",
  "properties": {
    "iso:country":"DE",
    "sg:address":"Vogelsanger Weg 49",
    "sg:city":"D\u00fcsseldorf",
    "sg:phone":"+49 211/63920",
    "sg:postcode":"40470",
    "sg:province":"Nordrhein-Westfalen",
    "wof:name":"Dkv-beteiligungs Gmbh",
    "wof:placetype":"venue"
},
  "geometry": {"coordinates":[6.800672,51.257095],"type":"Point"}
}