{
  "type": "Feature",
  "properties": {
    "iso:country":"DE",
    "sg:address":"Haus Uhlenkotten 32",
    "sg:city":"M\u00fcnster",
    "sg:phone":"+49 251/924330",
    "sg:postcode":"48159",
    "sg:province":"Nordrhein-Westfalen",
    "wof:name":"Aquaconsult Bew\u00e4sserungs- Und Springbrunnentechnik Gmbh",
    "wof:placetype":"venue"
},
  "geometry": {"coordinates":[7.5695381165,51.9900817871],"type":"Point"}
}