{
  "type": "Feature",
  "properties": {
    "iso:country":"DE",
    "sg:address":"Im Gewerbegebiet 27",
    "sg:city":"Lichtenau",
    "sg:phone":"+49 7227/2405",
    "sg:postcode":"77839",
    "sg:province":"Baden-W\u00fcrttemberg",
    "wof:name":"Metallbau Giner Gmbh",
    "wof:placetype":"venue"
},
  "geometry": {"coordinates":[7.998422,48.719971],"type":"Point"}
}