{
  "type": "Feature",
  "properties": {
    "iso:country":"DE",
    "sg:address":"Rheinstr. 114",
    "sg:city":"Krefeld",
    "sg:phone":"+49 2151/6266690",
    "sg:postcode":"47798",
    "sg:province":"Nordrhein-Westfalen",
    "wof:name":"Lechner & Hayn",
    "wof:placetype":"venue"
},
  "geometry": {"coordinates":[6.563049,51.333076],"type":"Point"}
}