{
  "type": "Feature",
  "properties": {
    "iso:country":"DE",
    "sg:address":"Hauptstr. 42",
    "sg:city":"Roetgen",
    "sg:phone":"+49 2471/2630",
    "sg:postcode":"52159",
    "sg:province":"Nordrhein-Westfalen",
    "wof:name":"F\u00fcllhorn Zum Metzgermeister",
    "wof:placetype":"venue"
},
  "geometry": {"coordinates":[6.1947751045,50.6452064514],"type":"Point"}
}