{
  "type": "Feature",
  "properties": {
    "iso:country":"DE",
    "sg:address":"Wormser Str. 35",
    "sg:city":"Frankenthal",
    "sg:phone":"+49 6233/25210",
    "sg:postcode":"67227",
    "sg:province":"Rheinland-Pfalz",
    "wof:name":"Apotheke Am Wormser Tor",
    "wof:placetype":"venue"
},
  "geometry": {"coordinates":[8.35366,49.537796],"type":"Point"}
}