{
  "type": "Feature",
  "properties": {
    "iso:country":"DE",
    "sg:address":"Schumannstr. 158",
    "sg:city":"Offenbach",
    "sg:phone":"+49 69/833083",
    "sg:postcode":"63069",
    "sg:province":"Hessen",
    "wof:name":"Karosseriebau Offenbach Gmbh",
    "wof:placetype":"venue"
},
  "geometry": {"coordinates":[8.74704,50.081928],"type":"Point"}
}