{
  "type": "Feature",
  "properties": {
    "iso:country":"DE",
    "sg:address":"Bahnhofstr. 47",
    "sg:city":"Groitzsch",
    "sg:phone":"+49 34296/41633",
    "sg:postcode":"04539",
    "sg:province":"Sachsen",
    "wof:name":"S. Gutsch & C. Scharf",
    "wof:placetype":"venue"
},
  "geometry": {"coordinates":[12.2857294083,51.1561393738],"type":"Point"}
}