{
  "type": "Feature",
  "properties": {
    "iso:country":"DE",
    "sg:address":"Ludwigsplatz 42",
    "sg:city":"Straubing",
    "sg:phone":"+49 9421/80030",
    "sg:postcode":"94315",
    "sg:province":"Bayern",
    "wof:name":"Ludwig Hafner Gmbh",
    "wof:placetype":"venue"
},
  "geometry": {"coordinates":[12.5698947906,48.881729126],"type":"Point"}
}