{
  "type": "Feature",
  "properties": {
    "iso:country":"DE",
    "sg:city":"Flieden-R\u00fcckers",
    "sg:phone":"+49 700 7397 8325",
    "sg:postcode":"36103",
    "sg:province":"Hessen",
    "wof:name":"Drk Spielmanns- Und Fanfarenzug R\u00fcckers E.v.",
    "wof:placetype":"venue"
},
  "geometry": {"coordinates":[9.566972,50.423405],"type":"Point"}
}