{
  "type": "Feature",
  "properties": {
    "iso:country":"DE",
    "sg:address":"Morsstiege 33",
    "sg:city":"Nordhorn",
    "sg:phone":"+49 5921/36140",
    "sg:postcode":"48529",
    "sg:province":"Niedersachsen",
    "wof:name":"Bernhard Esders",
    "wof:placetype":"venue"
},
  "geometry": {"coordinates":[7.075985,52.436115],"type":"Point"}
}