{
  "type": "Feature",
  "properties": {
    "iso:country":"DE",
    "sg:address":"Heidelerchenweg 12",
    "sg:city":"Hamburg",
    "sg:phone":"+49 40/6020617",
    "sg:postcode":"22399",
    "sg:province":"Hamburg",
    "wof:name":"Herbert Vossberg",
    "wof:placetype":"venue"
},
  "geometry": {"coordinates":[10.060561,53.666977],"type":"Point"}
}