{
  "type": "Feature",
  "properties": {
    "iso:country":"DE",
    "sg:address":"Hauptstr. 55",
    "sg:city":"Sulzburg",
    "sg:phone":"+49 7634/592111",
    "sg:postcode":"79295",
    "sg:province":"Baden-W\u00fcrttemberg",
    "wof:name":"Venocare Med Gmbh",
    "wof:placetype":"venue"
},
  "geometry": {"coordinates":[7.707973,47.841022],"type":"Point"}
}