{
  "type": "Feature",
  "properties": {
    "iso:country":"DE",
    "sg:address":"Marienkirchplatz 26",
    "sg:city":"Neuss",
    "sg:phone":"+49 2131/21256",
    "sg:postcode":"41460",
    "sg:province":"Nordrhein-Westfalen",
    "wof:name":"Kath. Pfarramt St. Marien",
    "wof:placetype":"venue"
},
  "geometry": {"coordinates":[6.6859102249,51.2031898499],"type":"Point"}
}