{
  "type": "Feature",
  "properties": {
    "iso:country":"DE",
    "sg:address":"Rothstr. 3",
    "sg:city":"R\u00f6hrmoos",
    "sg:phone":"+49 8139/7729",
    "sg:postcode":"85244",
    "sg:province":"Bayern",
    "wof:name":"B\u00fcrgergastst\u00e4tte",
    "wof:placetype":"venue"
},
  "geometry": {"coordinates":[11.4129257202,48.3226356506],"type":"Point"}
}