{
  "type": "Feature",
  "properties": {
    "iso:country":"DE",
    "sg:address":"Lange Str. 65",
    "sg:city":"Hessisch Oldendorf",
    "sg:postcode":"31840",
    "sg:province":"Niedersachsen",
    "wof:name":"Artemis Spielhallen Gmbh",
    "wof:placetype":"venue"
},
  "geometry": {"coordinates":[9.2488269806,52.1687278748],"type":"Point"}
}