{
  "type": "Feature",
  "properties": {
    "iso:country":"DE",
    "sg:address":"Logestr. 8",
    "sg:city":"Beverstedt",
    "sg:phone":"+49 4747/256",
    "sg:postcode":"27616",
    "sg:province":"Niedersachsen",
    "wof:name":"Hotel Zum Biber",
    "wof:placetype":"venue"
},
  "geometry": {"coordinates":[8.8202123642,53.4341278076],"type":"Point"}
}