{
  "type": "Feature",
  "properties": {
    "iso:country":"DE",
    "sg:address":"Weidmannsweg 11",
    "sg:city":"Aue",
    "sg:phone":"+49 3771/26704",
    "sg:postcode":"08280",
    "sg:province":"Sachsen",
    "wof:name":"Richard Ullmann",
    "wof:placetype":"venue"
},
  "geometry": {"coordinates":[12.698381424,50.5757598877],"type":"Point"}
}