{
  "type": "Feature",
  "properties": {
    "iso:country":"DE",
    "sg:address":"S\u00e4gm\u00fchle 2",
    "sg:city":"Hemmingen",
    "sg:phone":"+49 7150/6224",
    "sg:postcode":"71282",
    "sg:province":"Baden-W\u00fcrttemberg",
    "wof:name":"S\u00e4gewerk Arnold Gmbh",
    "wof:placetype":"venue"
},
  "geometry": {"coordinates":[9.0520648956,48.8584671021],"type":"Point"}
}