{
  "type": "Feature",
  "properties": {
    "iso:country":"DE",
    "sg:address":"Herzogin-Anna-Str. 24",
    "sg:city":"H\u00f6chst\u00e4dt",
    "sg:postcode":"89420",
    "sg:province":"Bayern",
    "wof:name":"Wkw 2k Web - Design Und It-systeme E. K.",
    "wof:placetype":"venue"
},
  "geometry": {"coordinates":[10.570184,48.610939],"type":"Point"}
}