{
  "type": "Feature",
  "properties": {
    "iso:country":"DE",
    "sg:address":"Taunusstr. 25",
    "sg:city":"Wiesbaden",
    "sg:phone":"+49 611/527578",
    "sg:postcode":"65183",
    "sg:province":"Hessen",
    "wof:name":"La Belle",
    "wof:placetype":"venue"
},
  "geometry": {"coordinates":[8.2416791916,50.0878448486],"type":"Point"}
}