{
  "type": "Feature",
  "properties": {
    "iso:country":"DE",
    "sg:address":"Walkersbrunn 64",
    "sg:city":"Gr\u00e4fenberg",
    "sg:phone":"+49 9192/263",
    "sg:postcode":"91322",
    "sg:province":"Bayern",
    "wof:name":"Manfred Schmidt",
    "wof:placetype":"venue"
},
  "geometry": {"coordinates":[11.20743,49.651787],"type":"Point"}
}