{
  "type": "Feature",
  "properties": {
    "iso:country":"DE",
    "sg:address":"Gartenstr. 30",
    "sg:city":"Oldenburg",
    "sg:phone":"+49 441/501055",
    "sg:postcode":"26122",
    "sg:province":"Niedersachsen",
    "wof:name":"Adolf Garlichs Kg",
    "wof:placetype":"venue"
},
  "geometry": {"coordinates":[8.205205,53.133892],"type":"Point"}
}