{
  "type": "Feature",
  "properties": {
    "iso:country":"DE",
    "sg:address":"Neues Land 3A",
    "sg:city":"Celle",
    "sg:phone":"+49 5141/881962",
    "sg:postcode":"29227",
    "sg:province":"Niedersachsen",
    "wof:name":"Borkowski",
    "wof:placetype":"venue"
},
  "geometry": {"coordinates":[10.0599679947,52.5981254578],"type":"Point"}
}