{
  "type": "Feature",
  "properties": {
    "iso:country":"DE",
    "sg:address":"Eichenweg 11",
    "sg:city":"Leer",
    "sg:phone":"+49 491/61585",
    "sg:postcode":"26789",
    "sg:province":"Niedersachsen",
    "wof:name":"M. Thiele",
    "wof:placetype":"venue"
},
  "geometry": {"coordinates":[7.461692,53.261692],"type":"Point"}
}