{
  "type": "Feature",
  "properties": {
    "iso:country":"DE",
    "sg:address":"Hauptstr. 103",
    "sg:city":"Neustadt",
    "sg:phone":"+49 3596/2624",
    "sg:postcode":"01844",
    "sg:province":"Sachsen",
    "wof:name":"Seifert",
    "wof:placetype":"venue"
},
  "geometry": {"coordinates":[14.190278,50.984879],"type":"Point"}
}