{
  "type": "Feature",
  "properties": {
    "iso:country":"DE",
    "sg:address":"Schweriner Str.",
    "sg:city":"Wismar",
    "sg:phone":"+49 3841/704705",
    "sg:postcode":"23970",
    "sg:province":"Mecklenburg-Vorpommern",
    "wof:name":"Loba Auto-serv Ohg",
    "wof:placetype":"venue"
},
  "geometry": {"coordinates":[11.46254,53.887081],"type":"Point"}
}