{
  "type": "Feature",
  "properties": {
    "iso:country":"DE",
    "sg:address":"Im Reis 56",
    "sg:city":"R\u00fcsselsheim",
    "sg:phone":"+49 6142/33433",
    "sg:postcode":"65428",
    "sg:province":"Hessen",
    "wof:name":"Siegfried Skala Fotodesigner",
    "wof:placetype":"venue"
},
  "geometry": {"coordinates":[8.4571685791,49.963848114],"type":"Point"}
}