{
  "type": "Feature",
  "properties": {
    "iso:country":"DE",
    "sg:address":"Schlo\u00dfm\u00fchlendamm 19",
    "sg:city":"Hamburg",
    "sg:phone":"+49 40/76752983",
    "sg:postcode":"21073",
    "sg:province":"Hamburg",
    "wof:name":"Glowa Und Wendt Rechtsanw\u00e4lte",
    "wof:placetype":"venue"
},
  "geometry": {"coordinates":[9.9814662933,53.4628601074],"type":"Point"}
}