{
  "type": "Feature",
  "properties": {
    "iso:country":"DE",
    "sg:address":"Volmestr. 161",
    "sg:city":"Kierspe",
    "sg:phone":"+49 2359/6690",
    "sg:postcode":"58566",
    "sg:province":"Nordrhein-Westfalen",
    "wof:name":"Bender & Wirth Gmbh & Co.",
    "wof:placetype":"venue"
},
  "geometry": {"coordinates":[7.617357,51.129662],"type":"Point"}
}