{
  "type": "Feature",
  "properties": {
    "iso:country":"DE",
    "sg:address":"F\u00fchrichstr. 39",
    "sg:city":"M\u00fcnchen",
    "sg:phone":"+49 89/405858",
    "sg:postcode":"81671",
    "sg:province":"Bayern",
    "wof:name":"A. Sch\u00f6ftenhuber",
    "wof:placetype":"venue"
},
  "geometry": {"coordinates":[11.614481926,48.1179924011],"type":"Point"}
}