{
  "type": "Feature",
  "properties": {
    "iso:country":"DE",
    "sg:address":"Werderstr. 34",
    "sg:city":"Karlsruhe",
    "sg:phone":"+49 721/7800020",
    "sg:postcode":"76137",
    "sg:province":"Baden-W\u00fcrttemberg",
    "wof:name":"Dieter Lucas Gmbh",
    "wof:placetype":"venue"
},
  "geometry": {"coordinates":[8.406356,49.001305],"type":"Point"}
}