{
  "type": "Feature",
  "properties": {
    "iso:country":"DE",
    "sg:address":"Steinkamp 23",
    "sg:city":"Hamburg",
    "sg:phone":"+49 40/7219915",
    "sg:postcode":"21029",
    "sg:province":"Hamburg",
    "wof:name":"J\u00fcrgen H\u00e4rtel",
    "wof:placetype":"venue"
},
  "geometry": {"coordinates":[10.2223644257,53.4947242737],"type":"Point"}
}