{
  "type": "Feature",
  "properties": {
    "iso:country":"DE",
    "sg:address":"Chausseestr. 13 a",
    "sg:city":"Berlin",
    "sg:phone":"+49 30/8051736",
    "sg:postcode":"14109",
    "sg:province":"Berlin",
    "wof:name":"Klaus H\u00f6now Architekt",
    "wof:placetype":"venue"
},
  "geometry": {"coordinates":[13.145607,52.41568],"type":"Point"}
}