{
  "type": "Feature",
  "properties": {
    "iso:country":"DE",
    "sg:address":"Karmelitenstr. 17",
    "sg:city":"W\u00fcrzburg",
    "sg:phone":"+49 931/14191",
    "sg:postcode":"97070",
    "sg:province":"Bayern",
    "wof:name":"Clou-boutique Edmar Fella",
    "wof:placetype":"venue"
},
  "geometry": {"coordinates":[9.927337,49.794086],"type":"Point"}
}