{
  "type": "Feature",
  "properties": {
    "iso:country":"DE",
    "sg:address":"W\u00f6rheider Weg 1-5",
    "sg:city":"Bielefeld",
    "sg:phone":"+49 5206/3324",
    "sg:postcode":"33739",
    "sg:province":"Nordrhein-Westfalen",
    "wof:name":"Gustav Siekmann",
    "wof:placetype":"venue"
},
  "geometry": {"coordinates":[8.524939537,52.0846977234],"type":"Point"}
}