{
  "type": "Feature",
  "properties": {
    "iso:country":"DE",
    "sg:address":"Stadtpromenade 4",
    "sg:city":"Hoyerswerda",
    "sg:phone":"+49 3571/406242",
    "sg:postcode":"02977",
    "sg:province":"Sachsen",
    "wof:name":"Pinte",
    "wof:placetype":"venue"
},
  "geometry": {"coordinates":[14.2610149384,51.4370422363],"type":"Point"}
}