{
  "type": "Feature",
  "properties": {
    "iso:country":"DE",
    "sg:address":"Sonnenstr. 27",
    "sg:city":"Kaufbeuren",
    "sg:phone":"+49 8341/62169",
    "sg:postcode":"87600",
    "sg:province":"Bayern",
    "wof:name":"Friedrich Wei\u00dfbarth & Sohn Gmbh & Co. Kg",
    "wof:placetype":"venue"
},
  "geometry": {"coordinates":[10.639176,47.911533],"type":"Point"}
}