{
  "type": "Feature",
  "properties": {
    "iso:country":"DE",
    "sg:address":"Am Ostbahnhof 4",
    "sg:city":"Dannenberg",
    "sg:phone":"+49 5861/1207",
    "sg:postcode":"29451",
    "sg:province":"Niedersachsen",
    "wof:name":"Bauernstube",
    "wof:placetype":"venue"
},
  "geometry": {"coordinates":[11.1181678772,53.1034011841],"type":"Point"}
}