{
  "type": "Feature",
  "properties": {
    "iso:country":"DE",
    "sg:address":"Neudorf",
    "sg:city":"Pappenheim",
    "sg:postcode":"91788",
    "sg:province":"Bayern",
    "wof:name":"Ev. Luth. Pfarramt Neudorf-suffersheim",
    "wof:placetype":"venue"
},
  "geometry": {"coordinates":[11.0132398605,48.9659042358],"type":"Point"}
}