{
  "type": "Feature",
  "properties": {
    "iso:country":"DE",
    "sg:address":"Angerstr. 6",
    "sg:city":"Hannover",
    "sg:phone":"+49 511/319927",
    "sg:postcode":"30161",
    "sg:province":"Niedersachsen",
    "wof:name":"H. Kehe",
    "wof:placetype":"venue"
},
  "geometry": {"coordinates":[9.741362,52.381996],"type":"Point"}
}