{
  "type": "Feature",
  "properties": {
    "iso:country":"DE",
    "sg:address":"Zum Hochfels 6",
    "sg:city":"Stadlern",
    "sg:phone":"+49 9674/370",
    "sg:postcode":"92549",
    "sg:province":"Bayern",
    "wof:name":"Reinhold Vogl",
    "wof:placetype":"venue"
},
  "geometry": {"coordinates":[12.6150684357,49.5074920654],"type":"Point"}
}