{
  "type": "Feature",
  "properties": {
    "iso:country":"DE",
    "sg:address":"Blaulstr. 34",
    "sg:city":"Speyer",
    "sg:phone":"+49 6232/79946",
    "sg:postcode":"67346",
    "sg:province":"Rheinland-Pfalz",
    "wof:name":"Hammel Gmbh",
    "wof:placetype":"venue"
},
  "geometry": {"coordinates":[8.423208,49.323296],"type":"Point"}
}