{
  "type": "Feature",
  "properties": {
    "iso:country":"DE",
    "sg:address":"Sauerl\u00e4nder Str. 29",
    "sg:city":"Dortmund",
    "sg:phone":"+49 231/462030",
    "sg:postcode":"44265",
    "sg:province":"Nordrhein-Westfalen",
    "wof:name":"August Dinsing Inh. Dirk Dinsing",
    "wof:placetype":"venue"
},
  "geometry": {"coordinates":[7.4909210205,51.4579238892],"type":"Point"}
}