{
  "type": "Feature",
  "properties": {
    "iso:country":"DE",
    "sg:address":"Feldstr. 12",
    "sg:city":"Prenzlau",
    "sg:phone":"+49 3984/4069",
    "sg:postcode":"17291",
    "sg:province":"Brandenburg",
    "wof:name":"Claus Lindner",
    "wof:placetype":"venue"
},
  "geometry": {"coordinates":[13.881482,53.326668],"type":"Point"}
}