{
  "type": "Feature",
  "properties": {
    "iso:country":"DE",
    "sg:address":"Harthauser Str. 19",
    "sg:city":"M\u00fcnchen",
    "sg:phone":"+49 89/646201",
    "sg:postcode":"81545",
    "sg:province":"Bayern",
    "wof:name":"Maximilian Buchmiller Rechtsanwalt",
    "wof:placetype":"venue"
},
  "geometry": {"coordinates":[11.55189991,48.0886688232],"type":"Point"}
}