{
  "type": "Feature",
  "properties": {
    "iso:country":"DE",
    "sg:address":"B\u00fcrgerm.-Aichele-Weg 4",
    "sg:city":"Oberstaufen",
    "sg:phone":"+49 8386/93020",
    "sg:postcode":"87534",
    "sg:province":"Bayern",
    "wof:name":"Kurhotel Bergkranz",
    "wof:placetype":"venue"
},
  "geometry": {"coordinates":[10.0164012909,47.5551757812],"type":"Point"}
}