{
  "type": "Feature",
  "properties": {
    "iso:country":"DE",
    "sg:address":"Herrenberger Str. 23",
    "sg:city":"T\u00fcbingen",
    "sg:phone":"+49 7071/940648",
    "sg:postcode":"72070",
    "sg:province":"Baden-W\u00fcrttemberg",
    "wof:name":"Psychotherapeutischer Arbeitskreis E. V.",
    "wof:placetype":"venue"
},
  "geometry": {"coordinates":[9.048634,48.523701],"type":"Point"}
}