{
  "type": "Feature",
  "properties": {
    "iso:country":"DE",
    "sg:address":"Stadtplatz 12",
    "sg:city":"Neustadt",
    "sg:postcode":"92660",
    "sg:province":"Bayern",
    "wof:name":"Pfarrb\u00fccherei",
    "wof:placetype":"venue"
},
  "geometry": {"coordinates":[12.171327,49.730614],"type":"Point"}
}