{
  "type": "Feature",
  "properties": {
    "iso:country":"DE",
    "sg:address":"Rheinstr. 5",
    "sg:city":"Karlsruhe",
    "sg:phone":"+49 721/551993",
    "sg:postcode":"76185",
    "sg:province":"Baden-W\u00fcrttemberg",
    "wof:name":"Rolf Sprauer Architekt",
    "wof:placetype":"venue"
},
  "geometry": {"coordinates":[8.36491,49.011192],"type":"Point"}
}