{
  "type": "Feature",
  "properties": {
    "iso:country":"DE",
    "sg:address":"Ohlendorffstr 29",
    "sg:city":"Krefeld",
    "sg:phone":"+49 2151/5790",
    "sg:postcode":"47809",
    "sg:province":"Nordrhein-Westfalen",
    "wof:name":"Compo Gmbh & Co Kg",
    "wof:placetype":"venue"
},
  "geometry": {"coordinates":[6.6708078384,51.3362617493],"type":"Point"}
}