{
  "type": "Feature",
  "properties": {
    "iso:country":"DE",
    "sg:address":"Sandweg 8",
    "sg:city":"Schauenburg",
    "sg:phone":"+49 5601/925674",
    "sg:postcode":"34270",
    "sg:province":"Hessen",
    "wof:name":"Th Multimedia Service Computer And More",
    "wof:placetype":"venue"
},
  "geometry": {"coordinates":[9.386061,51.272137],"type":"Point"}
}