{
  "type": "Feature",
  "properties": {
    "iso:country":"DE",
    "sg:address":"Am Hockstein 6",
    "sg:city":"Hohnstein",
    "sg:phone":"+49 35975/81442",
    "sg:postcode":"01848",
    "sg:province":"Sachsen",
    "wof:name":"Franz Winter",
    "wof:placetype":"venue"
},
  "geometry": {"coordinates":[14.089388,50.983513],"type":"Point"}
}