{
  "type": "Feature",
  "properties": {
    "iso:country":"DE",
    "sg:address":"Lindenstr. 56a",
    "sg:city":"Wadgassen",
    "sg:phone":"+49 6834/41854",
    "sg:postcode":"66787",
    "sg:province":"Saarland",
    "wof:name":"Papeterie Fuchs Gmbh",
    "wof:placetype":"venue"
},
  "geometry": {"coordinates":[6.7953028679,49.2674102783],"type":"Point"}
}