{
  "type": "Feature",
  "properties": {
    "iso:country":"DE",
    "sg:address":"Hauptstr. 20",
    "sg:city":"Langenfeld",
    "sg:phone":"+49 2173/10322",
    "sg:postcode":"40764",
    "sg:province":"Nordrhein-Westfalen",
    "wof:name":"Waffen Wurmann",
    "wof:placetype":"venue"
},
  "geometry": {"coordinates":[10.514005661,49.6133842468],"type":"Point"}
}