{
  "type": "Feature",
  "properties": {
    "iso:country":"DE",
    "sg:address":"Troppauplatz 1f",
    "sg:city":"Bamberg",
    "sg:phone":"+49 951/37773",
    "sg:postcode":"96052",
    "sg:province":"Bayern",
    "wof:name":"Elke Meysami-wenzel",
    "wof:placetype":"venue"
},
  "geometry": {"coordinates":[10.9075746536,49.9069061279],"type":"Point"}
}