{
  "type": "Feature",
  "properties": {
    "iso:country":"DE",
    "sg:address":"An der Steige 17",
    "sg:city":"Schramberg",
    "sg:phone":"+49 7422/21161",
    "sg:postcode":"78713",
    "sg:province":"Baden-W\u00fcrttemberg",
    "wof:name":"Modetruhe Moosmann Gmbh",
    "wof:placetype":"venue"
},
  "geometry": {"coordinates":[8.3864936829,48.2276763916],"type":"Point"}
}