{
  "type": "Feature",
  "properties": {
    "iso:country":"DE",
    "sg:address":"Marienburger Str. 35",
    "sg:city":"Goslar",
    "sg:phone":"+49 5321/81240",
    "sg:postcode":"38642",
    "sg:province":"Niedersachsen",
    "wof:name":"Kath. Pfarramt St. Benno",
    "wof:placetype":"venue"
},
  "geometry": {"coordinates":[10.4357995987,51.927154541],"type":"Point"}
}