{
  "type": "Feature",
  "properties": {
    "iso:country":"DE",
    "sg:address":"Bachstr. 60",
    "sg:city":"Hagen",
    "sg:phone":"+49 2331/331697",
    "sg:postcode":"58089",
    "sg:province":"Nordrhein-Westfalen",
    "wof:name":"Kaufmann & Partner Gmbh",
    "wof:placetype":"venue"
},
  "geometry": {"coordinates":[7.459934,51.35181],"type":"Point"}
}