{
  "type": "Feature",
  "properties": {
    "iso:country":"DE",
    "sg:address":"Schulweg 51",
    "sg:city":"Hatten",
    "sg:phone":"+49 4481/98580",
    "sg:postcode":"26209",
    "sg:province":"Niedersachsen",
    "wof:name":"Sanders Verwaltungs Gmbh",
    "wof:placetype":"venue"
},
  "geometry": {"coordinates":[8.278713,53.066402],"type":"Point"}
}