{
  "type": "Feature",
  "properties": {
    "iso:country":"DE",
    "sg:address":"Stargarder Str. 20",
    "sg:city":"Overath",
    "sg:phone":"+49 2206/82469",
    "sg:postcode":"51491",
    "sg:province":"Nordrhein-Westfalen",
    "wof:name":"Th. Schmitz Ingenieur",
    "wof:placetype":"venue"
},
  "geometry": {"coordinates":[7.286026001,50.9360313416],"type":"Point"}
}