{
  "type": "Feature",
  "properties": {
    "iso:country":"DE",
    "sg:address":"Steigweg 8",
    "sg:city":"Leutkirch",
    "sg:phone":"+49 7561/6681",
    "sg:postcode":"88299",
    "sg:province":"Baden-W\u00fcrttemberg",
    "wof:name":"Dr. Leonhard Willburger Tierarzt",
    "wof:placetype":"venue"
},
  "geometry": {"coordinates":[10.0054092407,47.8656349182],"type":"Point"}
}