{
  "type": "Feature",
  "properties": {
    "iso:country":"DE",
    "sg:address":"Frankenstr. 11",
    "sg:city":"Westerngrund",
    "sg:phone":"+49 6024/5560",
    "sg:postcode":"63825",
    "sg:province":"Bayern",
    "wof:name":"Kraft Gmbh",
    "wof:placetype":"venue"
},
  "geometry": {"coordinates":[9.244736,50.104923],"type":"Point"}
}