{
  "type": "Feature",
  "properties": {
    "iso:country":"DE",
    "sg:address":"Siemensstr. 9",
    "sg:city":"Osterholz-Scharmbeck",
    "sg:phone":"+49 4791/5400",
    "sg:postcode":"27711",
    "sg:province":"Niedersachsen",
    "wof:name":"Hammer Gmbh",
    "wof:placetype":"venue"
},
  "geometry": {"coordinates":[8.8123950958,53.2502288818],"type":"Point"}
}