{
  "type": "Feature",
  "properties": {
    "iso:country":"DE",
    "sg:address":"Bahnhofplatz 2",
    "sg:city":"Mainz",
    "sg:phone":"+49 6131/231303",
    "sg:postcode":"55116",
    "sg:province":"Rheinland-Pfalz",
    "wof:name":"Rhein-apotheke Inh. Peter Neubronner E. K.",
    "wof:placetype":"venue"
},
  "geometry": {"coordinates":[8.260208,50.001232],"type":"Point"}
}