{
  "type": "Feature",
  "properties": {
    "iso:country":"DE",
    "sg:address":"Sandleithe 41a",
    "sg:city":"F\u00fcrth",
    "sg:phone":"+49 911/767217",
    "sg:postcode":"90768",
    "sg:province":"Bayern",
    "wof:name":"A. Piotrowsky-rochefort \u00dcbersetzerin U. Dolmetscherin",
    "wof:placetype":"venue"
},
  "geometry": {"coordinates":[10.963292,49.517414],"type":"Point"}
}