{
  "type": "Feature",
  "properties": {
    "iso:country":"DE",
    "sg:address":"Tennenbacher Str. 51",
    "sg:city":"Freiburg",
    "sg:phone":"+49 761/273344",
    "sg:postcode":"79106",
    "sg:province":"Baden-W\u00fcrttemberg",
    "wof:name":"Bestattungs-institut Inh. Liselotte Hauser",
    "wof:placetype":"venue"
},
  "geometry": {"coordinates":[7.846024,48.006985],"type":"Point"}
}