{
  "type": "Feature",
  "properties": {
    "iso:country":"DE",
    "sg:address":"Sandgasse 4",
    "sg:city":"Aschaffenburg",
    "sg:phone":"+49 6021/22819",
    "sg:postcode":"63739",
    "sg:province":"Bayern",
    "wof:name":"Fritz D\u00f6rh\u00f6fer Gmbh",
    "wof:placetype":"venue"
},
  "geometry": {"coordinates":[9.1470098495,49.974407196],"type":"Point"}
}