{
  "type": "Feature",
  "properties": {
    "iso:country":"DE",
    "sg:address":"Lange Str. 30",
    "sg:city":"Greifswald",
    "sg:phone":"+49 3834/897219",
    "sg:postcode":"17489",
    "sg:province":"Mecklenburg-Vorpommern",
    "wof:name":"St. -jacobi-apotheke",
    "wof:placetype":"venue"
},
  "geometry": {"coordinates":[13.374539,54.096054],"type":"Point"}
}