{
  "type": "Feature",
  "properties": {
    "iso:country":"DE",
    "sg:address":"P\u00f6tzschker Weg 4",
    "sg:city":"Leipzig",
    "sg:postcode":"04179",
    "sg:province":"Sachsen",
    "wof:name":"M\u00f6bel-center Daffner Gmbh",
    "wof:placetype":"venue"
},
  "geometry": {"coordinates":[12.309435,51.326992],"type":"Point"}
}