{
  "type": "Feature",
  "properties": {
    "iso:country":"DE",
    "sg:address":"Fr\u00f6belstr. 5",
    "sg:city":"Neugersdorf",
    "sg:phone":"+49 3586/701046",
    "sg:postcode":"02727",
    "sg:province":"Sachsen",
    "wof:name":"Sanit\u00e4tshaus Muhl Gmbh",
    "wof:placetype":"venue"
},
  "geometry": {"coordinates":[14.6061878204,50.9793624878],"type":"Point"}
}