{
  "type": "Feature",
  "properties": {
    "iso:country":"DE",
    "sg:address":"Bahnhofstr. 24",
    "sg:city":"Schortens",
    "sg:phone":"+49 4461/80681",
    "sg:postcode":"26419",
    "sg:province":"Niedersachsen",
    "wof:name":"G\u00fcnther Friedrichs",
    "wof:placetype":"venue"
},
  "geometry": {"coordinates":[7.952156,53.544918],"type":"Point"}
}