{
  "type": "Feature",
  "properties": {
    "iso:country":"DE",
    "sg:address":"Francstr. 5",
    "sg:city":"Frankfurt",
    "sg:phone":"+49 69/561074",
    "sg:postcode":"60320",
    "sg:province":"Hessen",
    "wof:name":"Heinz Deichert Kg",
    "wof:placetype":"venue"
},
  "geometry": {"coordinates":[8.6815166473,50.1372528076],"type":"Point"}
}