{
  "type": "Feature",
  "properties": {
    "iso:country":"DE",
    "sg:address":"Schulstr. 34",
    "sg:city":"Busdorf",
    "sg:phone":"+49 4621/93900",
    "sg:postcode":"24866",
    "sg:province":"Schleswig-Holstein",
    "wof:name":"Nord-ostsee Automobile Verwaltungsgesellschaft Mbh",
    "wof:placetype":"venue"
},
  "geometry": {"coordinates":[9.5545272827,54.4898300171],"type":"Point"}
}