{
  "type": "Feature",
  "properties": {
    "iso:country":"DE",
    "sg:address":"Pfingstweide 47",
    "sg:city":"Friedberg",
    "sg:postcode":"61169",
    "sg:province":"Hessen",
    "wof:name":"Aldi Gmbh & Co. Kg",
    "wof:placetype":"venue"
},
  "geometry": {"coordinates":[8.7588949203,50.3167495728],"type":"Point"}
}