{
  "type": "Feature",
  "properties": {
    "iso:country":"DE",
    "sg:address":"Hauptstr. 58a",
    "sg:city":"Saarbr\u00fccken",
    "sg:phone":"+49 6898/32240",
    "sg:postcode":"66127",
    "sg:province":"Saarland",
    "wof:name":"Manfred Wilhelm",
    "wof:placetype":"venue"
},
  "geometry": {"coordinates":[6.896868,49.23003],"type":"Point"}
}