{
  "type": "Feature",
  "properties": {
    "iso:country":"DE",
    "sg:address":"K\u00f6sserner Str. 3",
    "sg:city":"Gro\u00dfbothen",
    "sg:phone":"+49 34384/71245",
    "sg:postcode":"04668",
    "sg:province":"Sachsen",
    "wof:name":"Materiell-tech. Versorgung Der Landwirtschaft",
    "wof:placetype":"venue"
},
  "geometry": {"coordinates":[12.73623,51.219872],"type":"Point"}
}