{
  "type": "Feature",
  "properties": {
    "iso:country":"DE",
    "sg:address":"Linslerhof 1",
    "sg:city":"\u00dcberherrn",
    "sg:postcode":"66802",
    "sg:province":"Saarland",
    "wof:name":"Brigitte Von Boch Living Gmbh",
    "wof:placetype":"venue"
},
  "geometry": {"coordinates":[6.7298049927,49.2527656555],"type":"Point"}
}