{
  "type": "Feature",
  "properties": {
    "iso:country":"DE",
    "sg:address":"Am Verkehrskreuz 7",
    "sg:city":"Wiehl",
    "sg:phone":"+49 2261/77879",
    "sg:postcode":"51674",
    "sg:province":"Nordrhein-Westfalen",
    "wof:name":"Scholz Verwaltungs Gmbh",
    "wof:placetype":"venue"
},
  "geometry": {"coordinates":[7.5248131752,50.9684181213],"type":"Point"}
}