{
  "type": "Feature",
  "properties": {
    "iso:country":"DE",
    "sg:address":"Im Eickelkamp 111",
    "sg:city":"Duisburg",
    "sg:phone":"+49 203/592134",
    "sg:postcode":"47169",
    "sg:province":"Nordrhein-Westfalen",
    "wof:name":"Ludwig & Roeckerath Immobilien Gmbh",
    "wof:placetype":"venue"
},
  "geometry": {"coordinates":[6.772922039,51.5250091553],"type":"Point"}
}