{
  "type": "Feature",
  "properties": {
    "iso:country":"DE",
    "sg:address":"Am Borsigturm 2",
    "sg:city":"Berlin",
    "sg:phone":"+49 30/43035047",
    "sg:postcode":"13507",
    "sg:province":"Berlin",
    "wof:name":"Der Zoo Shop In Den Hallen Am Borsigturm",
    "wof:placetype":"venue"
},
  "geometry": {"coordinates":[13.288305,52.58411],"type":"Point"}
}