{
  "type": "Feature",
  "properties": {
    "iso:country":"DE",
    "sg:address":"Bernried 2",
    "sg:city":"Neukirch",
    "sg:postcode":"88099",
    "sg:province":"Baden-W\u00fcrttemberg",
    "wof:name":"Mbz Zirn & Pfeffer Ohg",
    "wof:placetype":"venue"
},
  "geometry": {"coordinates":[9.685351,47.657349],"type":"Point"}
}