{
  "type": "Feature",
  "properties": {
    "iso:country":"DE",
    "sg:address":"Lochhamer Schlag 13",
    "sg:city":"Gr\u00e4felfing",
    "sg:phone":"+49 89/8981330",
    "sg:postcode":"82166",
    "sg:province":"Bayern",
    "wof:name":"Friedrich Neeb Gmbh",
    "wof:placetype":"venue"
},
  "geometry": {"coordinates":[11.4512929916,48.1223335266],"type":"Point"}
}