{
  "type": "Feature",
  "properties": {
    "iso:country":"DE",
    "sg:address":"Leutkircher Str. 19",
    "sg:city":"Ulm",
    "sg:phone":"+49 731/44880",
    "sg:postcode":"89079",
    "sg:province":"Baden-W\u00fcrttemberg",
    "wof:name":"G\u00fcnter Ladenburger Architekt",
    "wof:placetype":"venue"
},
  "geometry": {"coordinates":[9.971708,48.347317],"type":"Point"}
}