{
  "type": "Feature",
  "properties": {
    "iso:country":"DE",
    "sg:address":"Semnonenweg 1",
    "sg:city":"Hamburg",
    "sg:postcode":"22455",
    "sg:province":"Hamburg",
    "wof:name":"Kommanditgesellschaft Denali Sechsundsechzigste Verwal-",
    "wof:placetype":"venue"
},
  "geometry": {"coordinates":[9.963045,53.633896],"type":"Point"}
}