{
  "type": "Feature",
  "properties": {
    "iso:country":"DE",
    "sg:address":"Emmericher Str. 139",
    "sg:city":"Kleve",
    "sg:phone":"+49 2821/9501",
    "sg:postcode":"47533",
    "sg:province":"Nordrhein-Westfalen",
    "wof:name":"Ralf Kirchner",
    "wof:placetype":"venue"
},
  "geometry": {"coordinates":[6.15967,51.79937],"type":"Point"}
}