{
  "type": "Feature",
  "properties": {
    "iso:country":"DE",
    "sg:address":"Zietenstr. 33",
    "sg:city":"Chemnitz",
    "sg:phone":"+49 371/4029536",
    "sg:postcode":"09130",
    "sg:province":"Sachsen",
    "wof:name":"A. Liebig Anlageberater",
    "wof:placetype":"venue"
},
  "geometry": {"coordinates":[12.9393358231,50.8343658447],"type":"Point"}
}