{
  "type": "Feature",
  "properties": {
    "iso:country":"DE",
    "sg:address":"Gro\u00df-Gerauer-Str. 25",
    "sg:city":"Riedstadt",
    "sg:phone":"+49 6158/71041",
    "sg:postcode":"64560",
    "sg:province":"Hessen",
    "wof:name":"J\u00fcrgen Sch\u00e4fer",
    "wof:placetype":"venue"
},
  "geometry": {"coordinates":[8.497268,49.854893],"type":"Point"}
}