{
  "type": "Feature",
  "properties": {
    "iso:country":"DE",
    "sg:address":"Industriestr. 60",
    "sg:city":"Meckesheim",
    "sg:phone":"+49 6226/2551",
    "sg:postcode":"74909",
    "sg:province":"Baden-W\u00fcrttemberg",
    "wof:name":"Minimal",
    "wof:placetype":"venue"
},
  "geometry": {"coordinates":[8.8068990707,49.3265838623],"type":"Point"}
}