{
  "type": "Feature",
  "properties": {
    "iso:country":"DE",
    "sg:address":"Lohmannstr. 4",
    "sg:city":"Sassenberg",
    "sg:phone":"+49 5426/2267",
    "sg:postcode":"48336",
    "sg:province":"Nordrhein-Westfalen",
    "wof:name":"Leonhard Hermeler Inh. Thomas Hermler",
    "wof:placetype":"venue"
},
  "geometry": {"coordinates":[8.029786,52.04533],"type":"Point"}
}