{
  "type": "Feature",
  "properties": {
    "iso:country":"DE",
    "sg:address":"Ludwig-Erhard-Allee 15",
    "sg:city":"D\u00fcsseldorf",
    "sg:phone":"+49 211/97720",
    "sg:postcode":"40227",
    "sg:province":"Nordrhein-Westfalen",
    "wof:name":"Bausparkasse Schw\u00e4bisch Hall Ag",
    "wof:placetype":"venue"
},
  "geometry": {"coordinates":[6.796648,51.21954],"type":"Point"}
}