{
  "type": "Feature",
  "properties": {
    "iso:country":"DE",
    "sg:address":"Werderstr. 57",
    "sg:city":"Karlsruhe",
    "sg:phone":"+49 721/607001",
    "sg:postcode":"76137",
    "sg:province":"Baden-W\u00fcrttemberg",
    "wof:name":"Beratungsstelle F\u00fcr Jugendliche Zuwanderer",
    "wof:placetype":"venue"
},
  "geometry": {"coordinates":[8.4087,49.001644],"type":"Point"}
}