{
  "type": "Feature",
  "properties": {
    "iso:country":"DE",
    "sg:address":"Muskatstr. 5a",
    "sg:city":"Stuttgart",
    "sg:phone":"+49 711/446874",
    "sg:postcode":"70619",
    "sg:province":"Baden-W\u00fcrttemberg",
    "wof:name":"Ferdinand Class",
    "wof:placetype":"venue"
},
  "geometry": {"coordinates":[9.234901,48.746059],"type":"Point"}
}