{
  "type": "Feature",
  "properties": {
    "iso:country":"DE",
    "sg:address":"Uenzer Dorfstr. 49",
    "sg:city":"S\u00fcstedt",
    "sg:phone":"+49 4252/636",
    "sg:postcode":"27305",
    "sg:province":"Niedersachsen",
    "wof:name":"W. Napierski",
    "wof:placetype":"venue"
},
  "geometry": {"coordinates":[8.953212,52.843761],"type":"Point"}
}