{
  "type": "Feature",
  "properties": {
    "iso:country":"DE",
    "sg:address":"Birkenweg 1",
    "sg:city":"Schlat",
    "sg:phone":"+49 7161/814738",
    "sg:postcode":"73114",
    "sg:province":"Baden-W\u00fcrttemberg",
    "wof:name":"M. Granzer",
    "wof:placetype":"venue"
},
  "geometry": {"coordinates":[9.7128820419,48.65366745],"type":"Point"}
}