{
  "type": "Feature",
  "properties": {
    "iso:country":"DE",
    "sg:address":"Postfach",
    "sg:city":"Wegberg",
    "sg:postcode":"41837",
    "sg:province":"Nordrhein-Westfalen",
    "wof:name":"Stadtverwaltung Wegberg Jugendheim Wildenrath",
    "wof:placetype":"venue"
},
  "geometry": {"coordinates":[6.27878,51.14304],"type":"Point"}
}