{
  "type": "Feature",
  "properties": {
    "iso:country":"DE",
    "sg:address":"Welrichsweg 2",
    "sg:city":"Bonn",
    "sg:phone":"+49 228/655649",
    "sg:postcode":"53111",
    "sg:province":"Nordrhein-Westfalen",
    "wof:name":"A. Lhotzky Rechtsanwalt",
    "wof:placetype":"venue"
},
  "geometry": {"coordinates":[7.1023049355,50.7443580627],"type":"Point"}
}