{
  "type": "Feature",
  "properties": {
    "iso:country":"DE",
    "sg:address":"Markt 3",
    "sg:city":"Gro\u00dfenkneten",
    "sg:phone":"+49 4435/6000",
    "sg:postcode":"26197",
    "sg:province":"Niedersachsen",
    "wof:name":"Gemeindeb\u00fccherei",
    "wof:placetype":"venue"
},
  "geometry": {"coordinates":[8.257865,52.944157],"type":"Point"}
}