{
  "type": "Feature",
  "properties": {
    "iso:country":"DE",
    "sg:address":"Gebkenweg 52",
    "sg:city":"Oldenburg",
    "sg:phone":"+49 441/301176",
    "sg:postcode":"26127",
    "sg:province":"Niedersachsen",
    "wof:name":"Rudolf Kieper",
    "wof:placetype":"venue"
},
  "geometry": {"coordinates":[8.2286186218,53.1728439331],"type":"Point"}
}