{
  "type": "Feature",
  "properties": {
    "iso:country":"DE",
    "sg:address":"Hausg\u00e4rten 33",
    "sg:city":"Waiblingen",
    "sg:phone":"+49 7151/55206",
    "sg:postcode":"71332",
    "sg:province":"Baden-W\u00fcrttemberg",
    "wof:name":"Global-bau Gmbh",
    "wof:placetype":"venue"
},
  "geometry": {"coordinates":[9.312367,48.835415],"type":"Point"}
}