{
  "type": "Feature",
  "properties": {
    "iso:country":"DE",
    "sg:address":"Traunstorfer Str. 25",
    "sg:city":"Traunstein",
    "sg:phone":"+49 861/64042",
    "sg:postcode":"83278",
    "sg:province":"Bayern",
    "wof:name":"Hm Plan Gmbh",
    "wof:placetype":"venue"
},
  "geometry": {"coordinates":[12.628238678,47.8712692261],"type":"Point"}
}