{
  "type": "Feature",
  "properties": {
    "iso:country":"DE",
    "sg:address":"Ro\u00dfbergstr. 51",
    "sg:city":"Leinfelden-Echterdingen",
    "sg:phone":"+49 711/7560649",
    "sg:postcode":"70771",
    "sg:province":"Baden-W\u00fcrttemberg",
    "wof:name":"Kraner Und Partner",
    "wof:placetype":"venue"
},
  "geometry": {"coordinates":[9.1419591904,48.6900634766],"type":"Point"}
}