{
  "type": "Feature",
  "properties": {
    "iso:country":"DE",
    "sg:address":"Hauptstr. 28",
    "sg:city":"Postm\u00fcnster",
    "sg:phone":"+49 8561/1774",
    "sg:postcode":"84389",
    "sg:province":"Bayern",
    "wof:name":"Ludwig Kainzlsperger",
    "wof:placetype":"venue"
},
  "geometry": {"coordinates":[12.9057655334,48.4177513123],"type":"Point"}
}