{
  "type": "Feature",
  "properties": {
    "iso:country":"DE",
    "sg:address":"Weberstr. 8",
    "sg:city":"Dipperz",
    "sg:phone":"+49 6657/421",
    "sg:postcode":"36160",
    "sg:province":"Hessen",
    "wof:name":"Otto Bethmann",
    "wof:placetype":"venue"
},
  "geometry": {"coordinates":[9.794897,50.541691],"type":"Point"}
}