{
  "type": "Feature",
  "properties": {
    "iso:country":"DE",
    "sg:address":"Vacher Str. 124",
    "sg:city":"F\u00fcrth",
    "sg:phone":"+49 911/7593506",
    "sg:postcode":"90766",
    "sg:province":"Bayern",
    "wof:name":"Herbert Volk Heilpraktiker",
    "wof:placetype":"venue"
},
  "geometry": {"coordinates":[10.9780311584,49.4914474487],"type":"Point"}
}