{
  "type": "Feature",
  "properties": {
    "iso:country":"DE",
    "sg:address":"Kirchsteig 1",
    "sg:city":"Unterw\u00fcrschnitz",
    "sg:phone":"+49 37421/27505",
    "sg:postcode":"08626",
    "sg:province":"Sachsen",
    "wof:name":"Trockenbau Elstertal Gmbh",
    "wof:placetype":"venue"
},
  "geometry": {"coordinates":[12.222236,50.376411],"type":"Point"}
}