{
  "type": "Feature",
  "properties": {
    "iso:country":"DE",
    "sg:address":"Herzog-Adolph-Str. 11",
    "sg:city":"K\u00f6nigstein",
    "sg:phone":"+49 6174/21595",
    "sg:postcode":"61462",
    "sg:province":"Hessen",
    "wof:name":"Alexander Pfaff Gmbh & Co. Bauunternehmung Kg",
    "wof:placetype":"venue"
},
  "geometry": {"coordinates":[8.465431,50.185017],"type":"Point"}
}