{
  "type": "Feature",
  "properties": {
    "iso:country":"DE",
    "sg:address":"Sudetenstr. 2b",
    "sg:city":"W\u00f6llstadt",
    "sg:phone":"+49 6034/914565",
    "sg:postcode":"61206",
    "sg:province":"Hessen",
    "wof:name":"Intservice",
    "wof:placetype":"venue"
},
  "geometry": {"coordinates":[8.7509155273,50.2960700989],"type":"Point"}
}