{
  "type": "Feature",
  "properties": {
    "iso:country":"DE",
    "sg:address":"Sinsheimer Str. 15",
    "sg:city":"Dielheim",
    "sg:phone":"+49 6222/770577",
    "sg:postcode":"69234",
    "sg:province":"Baden-W\u00fcrttemberg",
    "wof:name":"Kucher Gmbh",
    "wof:placetype":"venue"
},
  "geometry": {"coordinates":[8.7906141281,49.2698707581],"type":"Point"}
}