{
  "type": "Feature",
  "properties": {
    "iso:country":"DE",
    "sg:address":"H\u00fcsgenstr. 35",
    "sg:city":"Aldenhoven",
    "sg:phone":"+49 2464/6932",
    "sg:postcode":"52457",
    "sg:province":"Nordrhein-Westfalen",
    "wof:name":"Hans-gerd Johnen",
    "wof:placetype":"venue"
},
  "geometry": {"coordinates":[6.253969,50.925247],"type":"Point"}
}