{
  "type": "Feature",
  "properties": {
    "iso:country":"DE",
    "sg:address":"Flamschen",
    "sg:city":"Coesfeld",
    "sg:postcode":"48653",
    "sg:province":"Nordrhein-Westfalen",
    "wof:name":"Tischlerei Hageb\u00f6ck Gbr",
    "wof:placetype":"venue"
},
  "geometry": {"coordinates":[7.138614,51.908905],"type":"Point"}
}