{
  "type": "Feature",
  "properties": {
    "iso:country":"DE",
    "sg:address":"Birkenfelder Str. 9",
    "sg:city":"Remlingen",
    "sg:phone":"+49 9369/433",
    "sg:postcode":"97280",
    "sg:province":"Bayern",
    "wof:name":"Werner Wehr",
    "wof:placetype":"venue"
},
  "geometry": {"coordinates":[9.698438,49.807827],"type":"Point"}
}