{
  "type": "Feature",
  "properties": {
    "iso:country":"DE",
    "sg:address":"Rudolf-Breitscheid-Str. 71-72",
    "sg:city":"Potsdam",
    "sg:phone":"+49 331/7481777",
    "sg:postcode":"14482",
    "sg:province":"Brandenburg",
    "wof:name":"Brun & B\u00f6hm Baustoffe Gmbh",
    "wof:placetype":"venue"
},
  "geometry": {"coordinates":[13.100614,52.392323],"type":"Point"}
}