{
  "type": "Feature",
  "properties": {
    "iso:country":"DE",
    "sg:address":"Am Stockfeld 69",
    "sg:city":"Neunkirchen",
    "sg:phone":"+49 6821/932111",
    "sg:postcode":"66539",
    "sg:province":"Saarland",
    "wof:name":"B\u00fcroorganisation S. Schmitt",
    "wof:placetype":"venue"
},
  "geometry": {"coordinates":[7.2401061058,49.3273124695],"type":"Point"}
}