{
  "type": "Feature",
  "properties": {
    "iso:country":"DE",
    "sg:address":"Ponholz 17",
    "sg:city":"Michelsneukirchen",
    "sg:phone":"+49 9467/926",
    "sg:postcode":"93185",
    "sg:province":"Bayern",
    "wof:name":"Gasthaus Max Gro\u00df",
    "wof:placetype":"venue"
},
  "geometry": {"coordinates":[12.5848398209,49.1309585571],"type":"Point"}
}