{
  "type": "Feature",
  "properties": {
    "iso:country":"DE",
    "sg:city":"Gudow",
    "sg:phone":"+49 4547/768",
    "sg:postcode":"23899",
    "sg:province":"Schleswig-Holstein",
    "wof:name":"Campingplatz Gudow",
    "wof:placetype":"venue"
},
  "geometry": {"coordinates":[10.77264,53.555237],"type":"Point"}
}