{
  "type": "Feature",
  "properties": {
    "iso:country":"DE",
    "sg:address":"Schillerstr. 40",
    "sg:city":"Elsterwerda",
    "sg:phone":"+49 3533/2170",
    "sg:postcode":"04910",
    "sg:province":"Brandenburg",
    "wof:name":"Gerd Bergmann",
    "wof:placetype":"venue"
},
  "geometry": {"coordinates":[13.5259304047,51.4641952515],"type":"Point"}
}