{
  "type": "Feature",
  "properties": {
    "iso:country":"DE",
    "sg:address":"Rollefstr. 14b",
    "sg:city":"Aachen",
    "sg:phone":"+49 241/526498",
    "sg:postcode":"52078",
    "sg:province":"Nordrhein-Westfalen",
    "wof:name":"D. Grund",
    "wof:placetype":"venue"
},
  "geometry": {"coordinates":[6.1667571068,50.746219635],"type":"Point"}
}