{
  "type": "Feature",
  "properties": {
    "iso:country":"DE",
    "sg:address":"Max-Planck-Str. 7/9",
    "sg:city":"W\u00fcrzburg",
    "sg:phone":"+49 931/4182907",
    "sg:postcode":"97064",
    "sg:province":"Bayern",
    "wof:name":"Mm-b\u00f6rse - Gebrauchtmaschinen Von A-z",
    "wof:placetype":"venue"
},
  "geometry": {"coordinates":[9.9008693695,49.7966842651],"type":"Point"}
}