{
  "type": "Feature",
  "properties": {
    "iso:country":"DE",
    "sg:address":"Reichhelmstr. 7",
    "sg:city":"Hannover",
    "sg:phone":"+49 511/9845603",
    "sg:postcode":"30519",
    "sg:province":"Niedersachsen",
    "wof:name":"Frank Nowak Gmbh",
    "wof:placetype":"venue"
},
  "geometry": {"coordinates":[9.7599840164,52.3367080688],"type":"Point"}
}