{
  "type": "Feature",
  "properties": {
    "iso:country":"DE",
    "sg:address":"Scheveninger Str. 20",
    "sg:city":"Berlin",
    "sg:postcode":"12359",
    "sg:province":"Berlin",
    "wof:name":"Texan Bau Gmbh",
    "wof:placetype":"venue"
},
  "geometry": {"coordinates":[13.45078,52.455948],"type":"Point"}
}