{
  "type": "Feature",
  "properties": {
    "iso:country":"DE",
    "sg:address":"Sprakensehler Str. 1",
    "sg:city":"Sprakensehl",
    "sg:phone":"+49 5837/1274",
    "sg:postcode":"29365",
    "sg:province":"Niedersachsen",
    "wof:name":"Pension Meyer",
    "wof:placetype":"venue"
},
  "geometry": {"coordinates":[10.459230423,52.7698936462],"type":"Point"}
}