{
  "type": "Feature",
  "properties": {
    "iso:country":"DE",
    "sg:address":"Ludwigstr. 33",
    "sg:city":"M\u00fcnchen",
    "sg:phone":"+49 89/21801",
    "sg:postcode":"80539",
    "sg:province":"Bayern",
    "wof:name":"Seminar F\u00fcr \u00d6konometrie Und Statistik",
    "wof:placetype":"venue"
},
  "geometry": {"coordinates":[11.581608,48.152061],"type":"Point"}
}