{
  "type": "Feature",
  "properties": {
    "iso:country":"DE",
    "sg:address":"Schongauer Str. 5",
    "sg:city":"Mauerstetten",
    "sg:phone":"+49 8341/15764",
    "sg:postcode":"87665",
    "sg:province":"Bayern",
    "wof:name":"Reisach Grundst\u00fccksverwertung Verwaltung Gmbh",
    "wof:placetype":"venue"
},
  "geometry": {"coordinates":[10.671125412,47.8926315308],"type":"Point"}
}