{
  "type": "Feature",
  "properties": {
    "iso:country":"DE",
    "sg:address":"Fabrikstr. 8",
    "sg:city":"Achern",
    "sg:phone":"+49 7841/1591",
    "sg:postcode":"77855",
    "sg:province":"Baden-W\u00fcrttemberg",
    "wof:name":"Huber Spezialtransporte Und Spedition Gmbh",
    "wof:placetype":"venue"
},
  "geometry": {"coordinates":[8.0877628326,48.6073570251],"type":"Point"}
}