{
  "type": "Feature",
  "properties": {
    "iso:country":"DE",
    "sg:address":"Klaswipper 43d",
    "sg:city":"Wipperf\u00fcrth",
    "sg:phone":"+49 2269/7283",
    "sg:postcode":"51688",
    "sg:province":"Nordrhein-Westfalen",
    "wof:name":"Nieto Iglesias Bau Gmbh",
    "wof:placetype":"venue"
},
  "geometry": {"coordinates":[7.471113,51.113766],"type":"Point"}
}