{
  "type": "Feature",
  "properties": {
    "iso:country":"DE",
    "sg:address":"Carl-Benz-Str. 5",
    "sg:city":"Pei\u00dfenberg",
    "sg:phone":"+49 8803/5820",
    "sg:postcode":"82380",
    "sg:province":"Bayern",
    "wof:name":"Weckerle Maschinenbau Gmbh",
    "wof:placetype":"venue"
},
  "geometry": {"coordinates":[11.05183,47.78318],"type":"Point"}
}