{
  "type": "Feature",
  "properties": {
    "iso:country":"DE",
    "sg:address":"Bussardweg 54",
    "sg:city":"Wedemark",
    "sg:phone":"+49 5130/7421",
    "sg:postcode":"30900",
    "sg:province":"Niedersachsen",
    "wof:name":"Georg Kemmler",
    "wof:placetype":"venue"
},
  "geometry": {"coordinates":[9.79407,52.514488],"type":"Point"}
}