{
  "type": "Feature",
  "properties": {
    "iso:country":"DE",
    "sg:address":"Bahnhofstr. 2",
    "sg:city":"Vilshofen",
    "sg:phone":"+49 8541/913000",
    "sg:postcode":"94474",
    "sg:province":"Bayern",
    "wof:name":"Apotheke Am Bahnhof Inh. Sabine Jacobs E. K.",
    "wof:placetype":"venue"
},
  "geometry": {"coordinates":[11.949706,49.296684],"type":"Point"}
}