{
  "type": "Feature",
  "properties": {
    "iso:country":"DE",
    "sg:address":"Am L\u00fcckefeld 8-10",
    "sg:city":"Mahlow",
    "sg:phone":"+49 4933/7920260",
    "sg:postcode":"15831",
    "sg:province":"Brandenburg",
    "wof:name":"Gebr. Becker Sport- Und Freizeitanlagen Gmbh",
    "wof:placetype":"venue"
},
  "geometry": {"coordinates":[13.433291,52.358982],"type":"Point"}
}