{
  "type": "Feature",
  "properties": {
    "iso:country":"DE",
    "sg:address":"Dorfstr. 22",
    "sg:city":"Ohlsbach",
    "sg:phone":"+49 7803/600515",
    "sg:postcode":"77797",
    "sg:province":"Baden-W\u00fcrttemberg",
    "wof:name":"Dierking & Lienert",
    "wof:placetype":"venue"
},
  "geometry": {"coordinates":[7.998018,48.433018],"type":"Point"}
}