{
  "type": "Feature",
  "properties": {
    "iso:country":"DE",
    "sg:address":"Kaiserin-Augusta-Allee 92",
    "sg:city":"Berlin",
    "sg:phone":"+49 30/3441362",
    "sg:postcode":"10589",
    "sg:province":"Berlin",
    "wof:name":"Gastst\u00e4tte Ljubisa Radosavljevic",
    "wof:placetype":"venue"
},
  "geometry": {"coordinates":[13.3113555908,52.5256195068],"type":"Point"}
}