{
  "type": "Feature",
  "properties": {
    "iso:country":"DE",
    "sg:address":"Deisenhofener Str. 55",
    "sg:city":"M\u00fcnchen",
    "sg:phone":"+49 89/696928",
    "sg:postcode":"81539",
    "sg:province":"Bayern",
    "wof:name":"Gabi Lauerer Und Barbara Z\u00f6bisch-robert",
    "wof:placetype":"venue"
},
  "geometry": {"coordinates":[11.5872650146,48.1127738953],"type":"Point"}
}