{
  "type": "Feature",
  "properties": {
    "iso:country":"DE",
    "sg:address":"Frankfurter Str. 5",
    "sg:city":"Neuhof",
    "sg:phone":"+49 6655/2305",
    "sg:postcode":"36119",
    "sg:province":"Hessen",
    "wof:name":"H. Rothmann",
    "wof:placetype":"venue"
},
  "geometry": {"coordinates":[9.616161,50.452168],"type":"Point"}
}