{
  "type": "Feature",
  "properties": {
    "iso:country":"DE",
    "sg:address":"Hauptstr. 87b",
    "sg:city":"Renchen",
    "sg:phone":"+49 7843/7970",
    "sg:postcode":"77871",
    "sg:province":"Baden-W\u00fcrttemberg",
    "wof:name":"Cortina Eiscafe",
    "wof:placetype":"venue"
},
  "geometry": {"coordinates":[8.009206,48.585419],"type":"Point"}
}