{
  "type": "Feature",
  "properties": {
    "iso:country":"DE",
    "sg:address":"Tr\u00f6delmarkt 15-19",
    "sg:city":"N\u00fcrnberg",
    "sg:phone":"+49 911/224832",
    "sg:postcode":"90403",
    "sg:province":"Bayern",
    "wof:name":"Die Spielzeugkiste Inh. Ursula Motsch E. Kfr.",
    "wof:placetype":"venue"
},
  "geometry": {"coordinates":[11.0741949081,49.4530677795],"type":"Point"}
}