{
  "type": "Feature",
  "properties": {
    "iso:country":"DE",
    "sg:address":"Hauptstr. 5",
    "sg:city":"Bodenw\u00f6hr",
    "sg:phone":"+49 9434/3731",
    "sg:postcode":"92439",
    "sg:province":"Bayern",
    "wof:name":"Pizzeria La Fattoria",
    "wof:placetype":"venue"
},
  "geometry": {"coordinates":[12.3036718369,49.2695617676],"type":"Point"}
}