{
  "type": "Feature",
  "properties": {
    "iso:country":"DE",
    "sg:address":"Frankfurter Str. 7-11",
    "sg:city":"Eschborn",
    "sg:postcode":"65760",
    "sg:province":"Hessen",
    "wof:name":"Schiffbauerdamm Beteiligungsges. Mbh",
    "wof:placetype":"venue"
},
  "geometry": {"coordinates":[8.5659627914,50.1322860718],"type":"Point"}
}