{
  "type": "Feature",
  "properties": {
    "iso:country":"DE",
    "sg:address":"Hohentwielstr. 41",
    "sg:city":"Stuttgart",
    "sg:phone":"+49 711/964190",
    "sg:postcode":"70199",
    "sg:province":"Baden-W\u00fcrttemberg",
    "wof:name":"Hpp Laage & Partner Planungsgesellschaft Mbh",
    "wof:placetype":"venue"
},
  "geometry": {"coordinates":[9.153665,48.763596],"type":"Point"}
}