{
  "type": "Feature",
  "properties": {
    "iso:country":"DE",
    "sg:address":"Gottlieber Str. 25",
    "sg:city":"Konstanz",
    "sg:phone":"+49 7531/51554",
    "sg:postcode":"78462",
    "sg:province":"Baden-W\u00fcrttemberg",
    "wof:name":"Dr. Med. Elke Vogel",
    "wof:placetype":"venue"
},
  "geometry": {"coordinates":[9.1669549942,47.6620864868],"type":"Point"}
}