{
  "type": "Feature",
  "properties": {
    "iso:country":"DE",
    "sg:address":"Lindenstr. 227",
    "sg:city":"Heinsberg",
    "sg:phone":"+49 2452/89298",
    "sg:postcode":"52525",
    "sg:province":"Nordrhein-Westfalen",
    "wof:name":"W. Th\u00f6nnissen Und R. Mahn",
    "wof:placetype":"venue"
},
  "geometry": {"coordinates":[6.0666060448,51.0791053772],"type":"Point"}
}