{
  "type": "Feature",
  "properties": {
    "iso:country":"DE",
    "sg:address":"Brunnenstrasse 24",
    "sg:city":"Berlin",
    "sg:phone":"+49 30",
    "sg:postcode":"10119",
    "sg:province":"Berlin",
    "wof:name":"Beschaffung Nach Ma\u00df",
    "wof:placetype":"venue"
},
  "geometry": {"coordinates":[13.398727,52.533691],"type":"Point"}
}