{
  "type": "Feature",
  "properties": {
    "iso:country":"DE",
    "sg:address":"Maigasse 11",
    "sg:city":"Gie\u00dfen",
    "sg:phone":"+49 641/72981",
    "sg:postcode":"35390",
    "sg:province":"Hessen",
    "wof:name":"Artur Tr\u00e4nkner Gmbh",
    "wof:placetype":"venue"
},
  "geometry": {"coordinates":[8.674025,50.584427],"type":"Point"}
}