{
  "type": "Feature",
  "properties": {
    "iso:country":"DE",
    "sg:address":"Innere Plauensche Str. 2",
    "sg:city":"Zwickau",
    "sg:phone":"+49 375/2304978",
    "sg:postcode":"08056",
    "sg:province":"Sachsen",
    "wof:name":"Tefefone Ipsnet Jan K\u00f6hler",
    "wof:placetype":"venue"
},
  "geometry": {"coordinates":[12.4946527481,50.7186393738],"type":"Point"}
}