{
  "type": "Feature",
  "properties": {
    "iso:country":"DE",
    "sg:address":"Herforder Str. 78",
    "sg:city":"Bad Oeynhausen",
    "sg:phone":"+49 5731/23646",
    "sg:postcode":"32545",
    "sg:province":"Nordrhein-Westfalen",
    "wof:name":"Bistro Costa Rica",
    "wof:placetype":"venue"
},
  "geometry": {"coordinates":[8.7958517075,52.204498291],"type":"Point"}
}