{
  "type": "Feature",
  "properties": {
    "iso:country":"DE",
    "sg:address":"Bischofskamp 2",
    "sg:city":"Hildesheim",
    "sg:phone":"+49 5121/52234",
    "sg:postcode":"31137",
    "sg:province":"Niedersachsen",
    "wof:name":"Hermann J\u00e4ger",
    "wof:placetype":"venue"
},
  "geometry": {"coordinates":[9.9473314285,52.1608695984],"type":"Point"}
}