{
  "type": "Feature",
  "properties": {
    "iso:country":"DE",
    "sg:address":"Max-Egon-Str. 13",
    "sg:city":"Donaueschingen",
    "sg:phone":"+49 771/4764",
    "sg:postcode":"78166",
    "sg:province":"Baden-W\u00fcrttemberg",
    "wof:name":"B. Amort",
    "wof:placetype":"venue"
},
  "geometry": {"coordinates":[8.4972047806,47.9516868591],"type":"Point"}
}