{
  "type": "Feature",
  "properties": {
    "iso:country":"DE",
    "sg:address":"Weihalden 1",
    "sg:city":"Altusried",
    "sg:phone":"+49 8373/7062",
    "sg:postcode":"87452",
    "sg:province":"Bayern",
    "wof:name":"Manfred Porr",
    "wof:placetype":"venue"
},
  "geometry": {"coordinates":[10.2051801682,47.8015823364],"type":"Point"}
}