{
  "type": "Feature",
  "properties": {
    "iso:country":"DE",
    "sg:address":"Martinstr. 60",
    "sg:city":"Achern",
    "sg:phone":"+49 7841/3362",
    "sg:postcode":"77855",
    "sg:province":"Baden-W\u00fcrttemberg",
    "wof:name":"Fridolin Zink Ingenieur",
    "wof:placetype":"venue"
},
  "geometry": {"coordinates":[8.0831546783,48.6294937134],"type":"Point"}
}