{
  "type": "Feature",
  "properties": {
    "iso:country":"DE",
    "sg:address":"Adenauerallee 90",
    "sg:city":"Bonn",
    "sg:phone":"+49 228",
    "sg:postcode":"53113",
    "sg:province":"Nordrhein-Westfalen",
    "wof:name":"Wiesbadener Vereinigung",
    "wof:placetype":"venue"
},
  "geometry": {"coordinates":[7.110465,50.726883],"type":"Point"}
}