{
  "type": "Feature",
  "properties": {
    "iso:country":"DE",
    "sg:address":"Waldsiedlung 6",
    "sg:city":"Torgelow",
    "sg:phone":"+49 3976/433165",
    "sg:postcode":"17358",
    "sg:province":"Mecklenburg-Vorpommern",
    "wof:name":"Kursana Gemeinn\u00fctzige Ges. F\u00fcr Sozialeinrichtungen Mbh",
    "wof:placetype":"venue"
},
  "geometry": {"coordinates":[13.996126,53.629883],"type":"Point"}
}