{
  "type": "Feature",
  "properties": {
    "iso:country":"DE",
    "sg:address":"Crostauer Str. 25 a",
    "sg:city":"Crostau",
    "sg:phone":"+49 3592/34414",
    "sg:postcode":"02681",
    "sg:province":"Sachsen",
    "wof:name":"Ccd City Courier Deutschland Service Betriebs-gmbh",
    "wof:placetype":"venue"
},
  "geometry": {"coordinates":[14.4752511978,51.0804595947],"type":"Point"}
}