{
  "type": "Feature",
  "properties": {
    "iso:country":"DE",
    "sg:address":"Neustadter Ring 26",
    "sg:city":"Ludwigshafen",
    "sg:phone":"+49 621/553147",
    "sg:postcode":"67067",
    "sg:province":"Rheinland-Pfalz",
    "wof:name":"Elektro Kr\u00fcger Gmbh",
    "wof:placetype":"venue"
},
  "geometry": {"coordinates":[8.379613,49.452599],"type":"Point"}
}