{
  "type": "Feature",
  "properties": {
    "iso:country":"DE",
    "sg:address":"Hohe Str. 16",
    "sg:city":"B\u00f6blingen",
    "sg:phone":"+49 7735/2917",
    "sg:postcode":"71032",
    "sg:province":"Baden-W\u00fcrttemberg",
    "wof:name":"E. Fischer Architekt",
    "wof:placetype":"venue"
},
  "geometry": {"coordinates":[9.017098,48.681202],"type":"Point"}
}