{
  "type": "Feature",
  "properties": {
    "iso:country":"DE",
    "sg:address":"Expopark 19",
    "sg:city":"Jacobsdorf",
    "sg:postcode":"15236",
    "sg:province":"Brandenburg",
    "wof:name":"Hanse Hafen Und Logistik Gmbh",
    "wof:placetype":"venue"
},
  "geometry": {"coordinates":[14.3509,52.324909],"type":"Point"}
}