{
  "type": "Feature",
  "properties": {
    "iso:country":"DE",
    "sg:address":"Steller Str. 1",
    "sg:city":"Seevetal",
    "sg:phone":"+49 4185/3146",
    "sg:postcode":"21220",
    "sg:province":"Niedersachsen",
    "wof:name":"Gastst\u00e4tte Romaris Gmbh",
    "wof:placetype":"venue"
},
  "geometry": {"coordinates":[10.0776262283,53.3325309753],"type":"Point"}
}