{
  "type": "Feature",
  "properties": {
    "iso:country":"DE",
    "sg:address":"Dachsberg 9c",
    "sg:city":"Hamburg",
    "sg:phone":"+49 40/5502200",
    "sg:postcode":"22459",
    "sg:province":"Hamburg",
    "wof:name":"Mare Immobilienentwicklung Und -verwaltung Gmbh",
    "wof:placetype":"venue"
},
  "geometry": {"coordinates":[9.9262170792,53.626335144],"type":"Point"}
}