{
  "type": "Feature",
  "properties": {
    "iso:country":"DE",
    "sg:address":"Bamberger Str. 4",
    "sg:city":"Breiteng\u00fc\u00dfbach",
    "sg:phone":"+49 9544/376",
    "sg:postcode":"96149",
    "sg:province":"Bayern",
    "wof:name":"Kreissparkasse Bamberg",
    "wof:placetype":"venue"
},
  "geometry": {"coordinates":[10.885535,49.971188],"type":"Point"}
}