{
  "type": "Feature",
  "properties": {
    "iso:country":"DE",
    "sg:address":"Ahlde 43",
    "sg:city":"Emsb\u00fcren",
    "sg:phone":"+49 5903/524",
    "sg:postcode":"48488",
    "sg:province":"Niedersachsen",
    "wof:name":"Hans F\u00fchner",
    "wof:placetype":"venue"
},
  "geometry": {"coordinates":[7.314696,52.361141],"type":"Point"}
}