{
  "type": "Feature",
  "properties": {
    "iso:country":"DE",
    "sg:address":"Kaspar-Siemers-Stieg 12",
    "sg:city":"Hamburg",
    "sg:phone":"+49 40/7128932",
    "sg:postcode":"22117",
    "sg:province":"Hamburg",
    "wof:name":"Sk-f\u00f6rdertechnik Gmbh",
    "wof:placetype":"venue"
},
  "geometry": {"coordinates":[10.117329,53.539288],"type":"Point"}
}