{
  "type": "Feature",
  "properties": {
    "iso:country":"DE",
    "sg:address":"Ludwigstr. 10",
    "sg:city":"Gummersbach",
    "sg:phone":"+49 2261/23196",
    "sg:postcode":"51643",
    "sg:province":"Nordrhein-Westfalen",
    "wof:name":"Richard Heidgen",
    "wof:placetype":"venue"
},
  "geometry": {"coordinates":[7.555888,51.027023],"type":"Point"}
}