{
  "type": "Feature",
  "properties": {
    "iso:country":"DE",
    "sg:address":"Guardinistr. 59",
    "sg:city":"M\u00fcnchen",
    "sg:phone":"+49 89/712388",
    "sg:postcode":"81375",
    "sg:province":"Bayern",
    "wof:name":"Heinz R\u00f6der Architekt",
    "wof:placetype":"venue"
},
  "geometry": {"coordinates":[11.49343,48.117821],"type":"Point"}
}