{
  "type": "Feature",
  "properties": {
    "iso:country":"DE",
    "sg:address":"Rehrener Str. 8",
    "sg:city":"Auetal",
    "sg:phone":"+49 5752/1521",
    "sg:postcode":"31749",
    "sg:province":"Niedersachsen",
    "wof:name":"F. Hoffmann",
    "wof:placetype":"venue"
},
  "geometry": {"coordinates":[9.236538887,52.2327384949],"type":"Point"}
}