{
  "type": "Feature",
  "properties": {
    "iso:country":"DE",
    "sg:address":"Hemmerder Dorfstr. 30",
    "sg:city":"Unna",
    "sg:phone":"+49 2308/2576",
    "sg:postcode":"59427",
    "sg:province":"Nordrhein-Westfalen",
    "wof:name":"Heinz Schr\u00f6er",
    "wof:placetype":"venue"
},
  "geometry": {"coordinates":[7.808693,51.550034],"type":"Point"}
}