{
  "type": "Feature",
  "properties": {
    "iso:country":"DE",
    "sg:address":"Glockenstr. 9",
    "sg:city":"Lichtenau",
    "sg:phone":"+49 5295/1088",
    "sg:postcode":"33165",
    "sg:province":"Nordrhein-Westfalen",
    "wof:name":"A. Kurte",
    "wof:placetype":"venue"
},
  "geometry": {"coordinates":[8.8960771561,51.6161384583],"type":"Point"}
}