{
  "type": "Feature",
  "properties": {
    "iso:country":"DE",
    "sg:address":"Promenade 3",
    "sg:city":"Ro\u00dfla",
    "sg:postcode":"06536",
    "sg:province":"Sachsen-Anhalt",
    "wof:name":"Katholisches Pfarramt Ro\u00dfla",
    "wof:placetype":"venue"
},
  "geometry": {"coordinates":[11.0778141022,51.4624252319],"type":"Point"}
}