{
  "type": "Feature",
  "properties": {
    "iso:country":"DE",
    "sg:address":"Anklamer Str. 17",
    "sg:city":"Friedland",
    "sg:phone":"+49 39601/26367",
    "sg:postcode":"17098",
    "sg:province":"Mecklenburg-Vorpommern",
    "wof:name":"Friedl\u00e4nder Dachdecker Eg",
    "wof:placetype":"venue"
},
  "geometry": {"coordinates":[13.563123,53.676979],"type":"Point"}
}