{
  "type": "Feature",
  "properties": {
    "iso:country":"DE",
    "sg:address":"Bohnitzscher Str. 4",
    "sg:city":"Mei\u00dfen",
    "sg:phone":"+49 3521/731100",
    "sg:postcode":"01662",
    "sg:province":"Sachsen",
    "wof:name":"Ingo Barthel",
    "wof:placetype":"venue"
},
  "geometry": {"coordinates":[13.4966306686,51.1775741577],"type":"Point"}
}