{
  "type": "Feature",
  "properties": {
    "iso:country":"DE",
    "sg:address":"Lange Str. 18",
    "sg:city":"Bielefeld",
    "sg:phone":"+49 521/888959",
    "sg:postcode":"33613",
    "sg:province":"Nordrhein-Westfalen",
    "wof:name":"P. Und P. G. Landwehr Inh. P. Und P.-g. Landwehr",
    "wof:placetype":"venue"
},
  "geometry": {"coordinates":[8.524725,52.045506],"type":"Point"}
}