{
  "type": "Feature",
  "properties": {
    "iso:country":"DE",
    "sg:address":"Oha 5",
    "sg:city":"Ellerhoop",
    "sg:phone":"+49 4120/1358",
    "sg:postcode":"25373",
    "sg:province":"Schleswig-Holstein",
    "wof:name":"Oft-oberfl\u00e4chentechnische Anlagenbau Gmbh",
    "wof:placetype":"venue"
},
  "geometry": {"coordinates":[9.7617,53.720524],"type":"Point"}
}