{
  "type": "Feature",
  "properties": {
    "iso:country":"DE",
    "sg:address":"Mainzer Str. 7",
    "sg:city":"Saulheim",
    "sg:phone":"+49 6732/5025",
    "sg:postcode":"55291",
    "sg:province":"Rheinland-Pfalz",
    "wof:name":"G\u00fcnter Sch\u00e4fer",
    "wof:placetype":"venue"
},
  "geometry": {"coordinates":[8.1516637802,49.8746833801],"type":"Point"}
}