{
  "type": "Feature",
  "properties": {
    "iso:country":"DE",
    "sg:address":"J\u00fcdenstr.",
    "sg:city":"Berlin",
    "sg:phone":"+49 30/4014791",
    "sg:postcode":"10178",
    "sg:province":"Berlin",
    "wof:name":"Luftbr\u00fcckendank Stiftung",
    "wof:placetype":"venue"
},
  "geometry": {"coordinates":[13.4091300964,52.5186767578],"type":"Point"}
}