{
  "type": "Feature",
  "properties": {
    "iso:country":"DE",
    "sg:address":"Rutesheimer Str. 24",
    "sg:city":"Stuttgart",
    "sg:phone":"+49 711/139770",
    "sg:postcode":"70499",
    "sg:province":"Baden-W\u00fcrttemberg",
    "wof:name":"Gischarowski Gmbh",
    "wof:placetype":"venue"
},
  "geometry": {"coordinates":[9.098403,48.821438],"type":"Point"}
}