{
  "type": "Feature",
  "properties": {
    "iso:country":"DE",
    "sg:address":"Lothringer Str. 3",
    "sg:city":"K\u00f6ln",
    "sg:phone":"+49 221/324433",
    "sg:postcode":"50677",
    "sg:province":"Nordrhein-Westfalen",
    "wof:name":"Wir F\u00fcr Euch H\u00e4usliche Krankenpflege Gmbh",
    "wof:placetype":"venue"
},
  "geometry": {"coordinates":[6.954482,50.921654],"type":"Point"}
}