{
  "type": "Feature",
  "properties": {
    "iso:country":"DE",
    "sg:address":"Semmelstr. 65",
    "sg:city":"W\u00fcrzburg",
    "sg:phone":"+49 931/3534490",
    "sg:postcode":"97070",
    "sg:province":"Bayern",
    "wof:name":"Reiseb\u00fcro Z. T. T\u00fcrkish Airlines Agentur",
    "wof:placetype":"venue"
},
  "geometry": {"coordinates":[9.9381723404,49.7977714539],"type":"Point"}
}