{
  "type": "Feature",
  "properties": {
    "iso:country":"DE",
    "sg:address":"Dorfstr. 14",
    "sg:city":"Sankt Peter-Ording",
    "sg:phone":"+49 4863/3973",
    "sg:postcode":"25826",
    "sg:province":"Schleswig-Holstein",
    "wof:name":"G\u00e4stehaus Frieda Ruhnau",
    "wof:placetype":"venue"
},
  "geometry": {"coordinates":[8.6388196945,54.3029403687],"type":"Point"}
}