{
  "type": "Feature",
  "properties": {
    "iso:country":"DE",
    "sg:address":"Hoster 5",
    "sg:city":"Nast\u00e4tten",
    "sg:phone":"+49 6772/49900",
    "sg:postcode":"56355",
    "sg:province":"Rheinland-Pfalz",
    "wof:name":"Sportwelt Finsterseifer E. K.",
    "wof:placetype":"venue"
},
  "geometry": {"coordinates":[7.856894,50.198406],"type":"Point"}
}