{
  "type": "Feature",
  "properties": {
    "iso:country":"DE",
    "sg:address":"K\u00f6nigsberger Str. 13",
    "sg:city":"Heppenheim",
    "sg:phone":"+49 6252/77116",
    "sg:postcode":"64646",
    "sg:province":"Hessen",
    "wof:name":"Franz Christ",
    "wof:placetype":"venue"
},
  "geometry": {"coordinates":[8.637033,49.647068],"type":"Point"}
}