{
  "type": "Feature",
  "properties": {
    "iso:country":"DE",
    "sg:address":"Georg-Wilhelm-Str. 25",
    "sg:city":"Hamburg",
    "sg:phone":"+49 40/758988",
    "sg:postcode":"21107",
    "sg:province":"Hamburg",
    "wof:name":"Kurbad Wilhelmsburg Hans-j\u00fcrgen Kreutz",
    "wof:placetype":"venue"
},
  "geometry": {"coordinates":[9.99291,53.514282],"type":"Point"}
}