{
  "type": "Feature",
  "properties": {
    "iso:country":"DE",
    "sg:address":"Bocksgasse 28",
    "sg:city":"Schw\u00e4bisch Gm\u00fcnd",
    "sg:phone":"+49 7171/927220",
    "sg:postcode":"73525",
    "sg:province":"Baden-W\u00fcrttemberg",
    "wof:name":"Optik M\u00fcller Ohg",
    "wof:placetype":"venue"
},
  "geometry": {"coordinates":[9.7934799194,48.7986297607],"type":"Point"}
}