{
  "type": "Feature",
  "properties": {
    "iso:country":"DE",
    "sg:address":"Stuttgarter Str. 38",
    "sg:city":"G\u00f6ppingen",
    "sg:phone":"+49 7161/27277",
    "sg:postcode":"73033",
    "sg:province":"Baden-W\u00fcrttemberg",
    "wof:name":"C. Behnke-blickle",
    "wof:placetype":"venue"
},
  "geometry": {"coordinates":[9.64165,48.706059],"type":"Point"}
}