{
  "type": "Feature",
  "properties": {
    "iso:country":"DE",
    "sg:address":"Hannoversche Str. 1",
    "sg:city":"Seelze",
    "sg:phone":"+49 5137/3271",
    "sg:postcode":"30926",
    "sg:province":"Niedersachsen",
    "wof:name":"Kreuz-apotheke",
    "wof:placetype":"venue"
},
  "geometry": {"coordinates":[9.591296,52.396881],"type":"Point"}
}