{
  "type": "Feature",
  "properties": {
    "iso:country":"DE",
    "sg:address":"Dorfstr. 11",
    "sg:city":"Uetze",
    "sg:phone":"+49 5173/332",
    "sg:postcode":"31311",
    "sg:province":"Niedersachsen",
    "wof:name":"Heinrich Santelmann",
    "wof:placetype":"venue"
},
  "geometry": {"coordinates":[10.167969,52.436436],"type":"Point"}
}