{
  "type": "Feature",
  "properties": {
    "iso:country":"DE",
    "sg:address":"Wittelsbacherallee 117",
    "sg:city":"Frankfurt am Main",
    "sg:phone":"+49 69",
    "sg:postcode":"60385",
    "sg:province":"Hessen",
    "wof:name":"Videoshop24.net, Gebrauchte Video- Und Dvd-filme",
    "wof:placetype":"venue"
},
  "geometry": {"coordinates":[8.709864,50.122326],"type":"Point"}
}