{
  "type": "Feature",
  "properties": {
    "iso:country":"DE",
    "sg:address":"Muggenthaler Str. 48",
    "sg:city":"Altmannstein",
    "sg:phone":"+49 9446/312",
    "sg:postcode":"93336",
    "sg:province":"Bayern",
    "wof:name":"Josef Wagner",
    "wof:placetype":"venue"
},
  "geometry": {"coordinates":[11.6284103394,48.9047813416],"type":"Point"}
}