{
  "type": "Feature",
  "properties": {
    "iso:country":"DE",
    "sg:address":"S\u00fclsen 16",
    "sg:city":"Olfen",
    "sg:phone":"+49 2595/1223",
    "sg:postcode":"59399",
    "sg:province":"Nordrhein-Westfalen",
    "wof:name":"Norbert Scholbrock",
    "wof:placetype":"venue"
},
  "geometry": {"coordinates":[7.377516,51.682957],"type":"Point"}
}