{
  "type": "Feature",
  "properties": {
    "iso:country":"DE",
    "sg:address":"Greu\u00dfener Str. 30",
    "sg:city":"Greu\u00dfen",
    "sg:phone":"+49 3636/701240",
    "sg:postcode":"99718",
    "sg:province":"Th\u00fcringen",
    "wof:name":"Gastst\u00e4tte Dorfkrug Inh. Renate Cotta",
    "wof:placetype":"venue"
},
  "geometry": {"coordinates":[10.9713859558,51.2296104431],"type":"Point"}
}