{
  "type": "Feature",
  "properties": {
    "iso:country":"DE",
    "sg:address":"K\u00f6llig 15",
    "sg:city":"Nittel",
    "sg:phone":"+49 6584/334",
    "sg:postcode":"54453",
    "sg:province":"Rheinland-Pfalz",
    "wof:name":"Matthias Lautem Weinanbau",
    "wof:placetype":"venue"
},
  "geometry": {"coordinates":[6.4513940811,49.6521492004],"type":"Point"}
}