{
  "type": "Feature",
  "properties": {
    "iso:country":"DE",
    "sg:address":"Koblenzer Str. 6",
    "sg:city":"Hillesheim",
    "sg:phone":"+49 6593/322",
    "sg:postcode":"54576",
    "sg:province":"Rheinland-Pfalz",
    "wof:name":"Anneliese Menrath",
    "wof:placetype":"venue"
},
  "geometry": {"coordinates":[6.6728200912,50.290435791],"type":"Point"}
}