{
  "type": "Feature",
  "properties": {
    "iso:country":"DE",
    "sg:address":"Kronacher Str. 41",
    "sg:city":"Bamberg",
    "sg:postcode":"96052",
    "sg:province":"Bayern",
    "wof:name":"Magnor Bauelemente Gmbh",
    "wof:placetype":"venue"
},
  "geometry": {"coordinates":[10.8986530304,49.9169769287],"type":"Point"}
}