{
  "type": "Feature",
  "properties": {
    "iso:country":"DE",
    "sg:address":"Gertrudenthaler Str. 12",
    "sg:city":"Burg",
    "sg:postcode":"23769",
    "sg:province":"Schleswig-Holstein",
    "wof:name":"Meereszentrum Fehmarn Gmbh",
    "wof:placetype":"venue"
},
  "geometry": {"coordinates":[11.1809520721,54.4456787109],"type":"Point"}
}