{
  "type": "Feature",
  "properties": {
    "iso:country":"DE",
    "sg:address":"Odenwaldstr. 56 a",
    "sg:city":"K\u00f6ln",
    "sg:phone":"+49 221/831923",
    "sg:postcode":"51105",
    "sg:province":"Nordrhein-Westfalen",
    "wof:name":"Gastst\u00e4tte H. B\u00fcscher",
    "wof:placetype":"venue"
},
  "geometry": {"coordinates":[6.9999771118,50.9303817749],"type":"Point"}
}