{
  "type": "Feature",
  "properties": {
    "iso:country":"DE",
    "sg:address":"Farchanter Str. 15",
    "sg:city":"M\u00fcnchen",
    "sg:phone":"+49 89/712034",
    "sg:postcode":"81377",
    "sg:province":"Bayern",
    "wof:name":"Data Conzept Gmbh",
    "wof:placetype":"venue"
},
  "geometry": {"coordinates":[11.5125198364,48.115032196],"type":"Point"}
}