{
  "type": "Feature",
  "properties": {
    "iso:country":"DE",
    "sg:address":"Dreiborner Str. 27",
    "sg:city":"Schleiden",
    "sg:phone":"+49 2444/2317",
    "sg:postcode":"53937",
    "sg:province":"Nordrhein-Westfalen",
    "wof:name":"A. Breuer",
    "wof:placetype":"venue"
},
  "geometry": {"coordinates":[6.4983139038,50.5732307434],"type":"Point"}
}