{
  "type": "Feature",
  "properties": {
    "iso:country":"DE",
    "sg:address":"K\u00f6rnerstr. 34-35",
    "sg:city":"Petershagen",
    "sg:postcode":"15370",
    "sg:province":"Brandenburg",
    "wof:name":"Transport Und Erdbau Gmbh",
    "wof:placetype":"venue"
},
  "geometry": {"coordinates":[13.7847995758,52.5395431519],"type":"Point"}
}