{
  "type": "Feature",
  "properties": {
    "iso:country":"DE",
    "sg:address":"Fischweg 4",
    "sg:city":"Trier",
    "sg:phone":"+49 651/52296",
    "sg:postcode":"54292",
    "sg:province":"Rheinland-Pfalz",
    "wof:name":"A. Von Der Lahr",
    "wof:placetype":"venue"
},
  "geometry": {"coordinates":[6.708378,49.782459],"type":"Point"}
}