{
  "type": "Feature",
  "properties": {
    "iso:country":"DE",
    "sg:address":"Krohnskamp 72",
    "sg:city":"Hamburg",
    "sg:phone":"+49 40/2790684",
    "sg:postcode":"22301",
    "sg:province":"Hamburg",
    "wof:name":"Dirk Henning Krapp",
    "wof:placetype":"venue"
},
  "geometry": {"coordinates":[10.0124864578,53.5895118713],"type":"Point"}
}