{
  "type": "Feature",
  "properties": {
    "iso:country":"DE",
    "sg:address":"Sch\u00f6nheider Str. 1",
    "sg:city":"Morgenr\u00f6the-Rautenkranz",
    "sg:postcode":"08262",
    "sg:province":"Sachsen",
    "wof:name":"Raumfahrtpark Vogtland Gmbh",
    "wof:placetype":"venue"
},
  "geometry": {"coordinates":[12.487529,50.457706],"type":"Point"}
}