{
  "type": "Feature",
  "properties": {
    "iso:country":"DE",
    "sg:address":"Holzau 1",
    "sg:city":"Tann",
    "sg:phone":"+49 8572/91144",
    "sg:postcode":"84367",
    "sg:province":"Bayern",
    "wof:name":"Westner Holzbau Gmbh",
    "wof:placetype":"venue"
},
  "geometry": {"coordinates":[12.930238,48.33799],"type":"Point"}
}