{
  "type": "Feature",
  "properties": {
    "iso:country":"DE",
    "sg:address":"Bitscher Str. 14",
    "sg:city":"H\u00f6hein\u00f6d",
    "sg:postcode":"66989",
    "sg:province":"Rheinland-Pfalz",
    "wof:name":"Galigolf E. K.",
    "wof:placetype":"venue"
},
  "geometry": {"coordinates":[7.612565,49.288288],"type":"Point"}
}