{
  "type": "Feature",
  "properties": {
    "iso:country":"DE",
    "sg:address":"M\u00f6nchsrother Str. 9",
    "sg:city":"Dinkelsb\u00fchl",
    "sg:phone":"+49 9851/7629",
    "sg:postcode":"91550",
    "sg:province":"Bayern",
    "wof:name":"Oswald Hofmann",
    "wof:placetype":"venue"
},
  "geometry": {"coordinates":[10.32652,49.064243],"type":"Point"}
}