{
  "type": "Feature",
  "properties": {
    "iso:country":"DE",
    "sg:address":"Wackenbrucher Str. 132",
    "sg:city":"Wesel",
    "sg:phone":"+49 281/50914",
    "sg:postcode":"46485",
    "sg:province":"Nordrhein-Westfalen",
    "wof:name":"E. Gilhaus",
    "wof:placetype":"venue"
},
  "geometry": {"coordinates":[6.6422719955,51.6557121277],"type":"Point"}
}