{
  "type": "Feature",
  "properties": {
    "iso:country":"DE",
    "sg:address":"Hauptstr. 30",
    "sg:city":"Seeth",
    "sg:phone":"+49 4881/876100",
    "sg:postcode":"25878",
    "sg:province":"Schleswig-Holstein",
    "wof:name":"Reinhardt G\u00f6rtzen",
    "wof:placetype":"venue"
},
  "geometry": {"coordinates":[9.168835,54.365974],"type":"Point"}
}