{
  "type": "Feature",
  "properties": {
    "iso:country":"DE",
    "sg:address":"Von-Ketteler-Str. 16",
    "sg:city":"Hamm",
    "sg:phone":"+49 2381/73666",
    "sg:postcode":"59075",
    "sg:province":"Nordrhein-Westfalen",
    "wof:name":"Ernst Streit",
    "wof:placetype":"venue"
},
  "geometry": {"coordinates":[7.7375268936,51.6948852539],"type":"Point"}
}