{
  "type": "Feature",
  "properties": {
    "iso:country":"DE",
    "sg:address":"Ackerstr. 16",
    "sg:city":"Bad Sooden-Allendorf",
    "sg:phone":"+49 5652/6517",
    "sg:postcode":"37242",
    "sg:province":"Hessen",
    "wof:name":"Aloys Werner Ingenieur",
    "wof:placetype":"venue"
},
  "geometry": {"coordinates":[9.9760026932,51.2727050781],"type":"Point"}
}