{
  "type": "Feature",
  "properties": {
    "iso:country":"DE",
    "sg:address":"K\u00e4lbersch\u00fcttstr. 4 A",
    "sg:city":"Ingolstadt",
    "sg:phone":"+49 841/965600",
    "sg:postcode":"85053",
    "sg:province":"Bayern",
    "wof:name":"Pritschet Gmbh",
    "wof:placetype":"venue"
},
  "geometry": {"coordinates":[11.476134,48.751186],"type":"Point"}
}