{
  "type": "Feature",
  "properties": {
    "iso:country":"DE",
    "sg:address":"Bruckstr. 24",
    "sg:city":"Rottenacker",
    "sg:phone":"+49 7393/1089",
    "sg:postcode":"89616",
    "sg:province":"Baden-W\u00fcrttemberg",
    "wof:name":"Friedrich Klai\u00df",
    "wof:placetype":"venue"
},
  "geometry": {"coordinates":[9.6905126572,48.2338562012],"type":"Point"}
}