{
  "type": "Feature",
  "properties": {
    "iso:country":"DE",
    "sg:address":"Germersheimer Landstr. 4",
    "sg:city":"Philippsburg",
    "sg:phone":"+49 7256/6011",
    "sg:postcode":"76661",
    "sg:province":"Baden-W\u00fcrttemberg",
    "wof:name":"Adolf Schneider Betonwerk Gmbh & Co. Kg",
    "wof:placetype":"venue"
},
  "geometry": {"coordinates":[8.4520111084,49.2016563416],"type":"Point"}
}