{
  "type": "Feature",
  "properties": {
    "iso:country":"DE",
    "sg:address":"Rennershofstr. 26",
    "sg:city":"Mannheim",
    "sg:phone":"+49 621/833840",
    "sg:postcode":"68163",
    "sg:province":"Baden-W\u00fcrttemberg",
    "wof:name":"Robert Schott Immobilienmakler",
    "wof:placetype":"venue"
},
  "geometry": {"coordinates":[8.4646902084,49.4752388],"type":"Point"}
}