{
  "type": "Feature",
  "properties": {
    "iso:country":"DE",
    "sg:address":"Moritzburger Str. 74",
    "sg:city":"Coswig",
    "sg:phone":"+49 3523/62762",
    "sg:postcode":"01640",
    "sg:province":"Sachsen",
    "wof:name":"Spitzgrund-apotheke",
    "wof:placetype":"venue"
},
  "geometry": {"coordinates":[13.589695,51.138317],"type":"Point"}
}