{
  "type": "Feature",
  "properties": {
    "iso:country":"DE",
    "sg:address":"Kolonatstr. 22",
    "sg:city":"Bad Bentheim",
    "sg:phone":"+49 5922/2261",
    "sg:postcode":"48455",
    "sg:province":"Niedersachsen",
    "wof:name":"Rosemarie Moddemann",
    "wof:placetype":"venue"
},
  "geometry": {"coordinates":[7.1724848747,52.289440155],"type":"Point"}
}