{
  "type": "Feature",
  "properties": {
    "iso:country":"DE",
    "sg:address":"Bahnhofstr. 160",
    "sg:city":"Ebnath",
    "sg:phone":"+49 9234/6642",
    "sg:postcode":"95683",
    "sg:province":"Bayern",
    "wof:name":"Karl Kr\u00e4mer",
    "wof:placetype":"venue"
},
  "geometry": {"coordinates":[11.93835,49.956909],"type":"Point"}
}