{
  "type": "Feature",
  "properties": {
    "iso:country":"DE",
    "sg:address":"Siegburger Str. 115 - 119",
    "sg:city":"K\u00f6ln",
    "sg:phone":"+49 221",
    "sg:postcode":"50679",
    "sg:province":"Nordrhein-Westfalen",
    "wof:name":"Bob G. Baus",
    "wof:placetype":"venue"
},
  "geometry": {"coordinates":[6.9711890221,50.9324798584],"type":"Point"}
}