{
  "type": "Feature",
  "properties": {
    "iso:country":"DE",
    "sg:address":"Heinrich-Rau-Str. 14 a",
    "sg:city":"Neuruppin",
    "sg:phone":"+49 3391/504552",
    "sg:postcode":"16816",
    "sg:province":"Brandenburg",
    "wof:name":"Sonnen-apotheke Inh. Dietmar Berger",
    "wof:placetype":"venue"
},
  "geometry": {"coordinates":[12.7932,52.914513],"type":"Point"}
}