{
  "type": "Feature",
  "properties": {
    "iso:country":"DE",
    "sg:address":"Bertholdstra\u00dfe 9",
    "sg:city":"B\u00fcren",
    "sg:postcode":"33142",
    "sg:province":"Nordrhein-Westfalen",
    "wof:name":"Hotel-restaurant Ackfeld, 33142 B\u00fcren",
    "wof:placetype":"venue"
},
  "geometry": {"coordinates":[8.560924,51.554874],"type":"Point"}
}