{
  "type": "Feature",
  "properties": {
    "iso:country":"DE",
    "sg:address":"Poststr. 39",
    "sg:city":"Hamburg",
    "sg:phone":"+49 40/343268",
    "sg:postcode":"20354",
    "sg:province":"Hamburg",
    "wof:name":"Antonio Arnan",
    "wof:placetype":"venue"
},
  "geometry": {"coordinates":[9.9885959625,53.5540504456],"type":"Point"}
}