{
  "type": "Feature",
  "properties": {
    "iso:country":"DE",
    "sg:address":"K\u00f6lner Str. 230",
    "sg:city":"Krefeld",
    "sg:phone":"+49 2151/311416",
    "sg:postcode":"47805",
    "sg:province":"Nordrhein-Westfalen",
    "wof:name":"Bowling-center Peter Bode",
    "wof:placetype":"venue"
},
  "geometry": {"coordinates":[6.575991,51.316944],"type":"Point"}
}