{
  "type": "Feature",
  "properties": {
    "iso:country":"DE",
    "sg:address":"Osthofener Str. 15",
    "sg:city":"Westhofen",
    "sg:phone":"+49 6244/697",
    "sg:postcode":"67593",
    "sg:province":"Rheinland-Pfalz",
    "wof:name":"Karl Graf",
    "wof:placetype":"venue"
},
  "geometry": {"coordinates":[8.2497701645,49.7037696838],"type":"Point"}
}