{
  "type": "Feature",
  "properties": {
    "iso:country":"DE",
    "sg:address":"Schlo\u00dfstr. 1",
    "sg:city":"K\u00f6nigs Wusterhausen",
    "sg:postcode":"15711",
    "sg:province":"Brandenburg",
    "wof:name":"Nova Biophyton Arzneimittelvertrieb",
    "wof:placetype":"venue"
},
  "geometry": {"coordinates":[13.6242313385,52.2990989685],"type":"Point"}
}