{
  "type": "Feature",
  "properties": {
    "iso:country":"DE",
    "sg:address":"Stuttgarter Str. 53",
    "sg:city":"Vaihingen",
    "sg:phone":"+49 7042/5031",
    "sg:postcode":"71665",
    "sg:province":"Baden-W\u00fcrttemberg",
    "wof:name":"Walter Fuchs Rechtsanwalt",
    "wof:placetype":"venue"
},
  "geometry": {"coordinates":[8.9604787827,48.9299659729],"type":"Point"}
}