{
  "type": "Feature",
  "properties": {
    "iso:country":"DE",
    "sg:address":"G\u00f6kerstr. 67",
    "sg:city":"Wilhelmshaven",
    "sg:phone":"+49 4421/365885",
    "sg:postcode":"26384",
    "sg:province":"Niedersachsen",
    "wof:name":"Prestige Finanzierungs- Und Immobilien-vermittlungs Gmbh",
    "wof:placetype":"venue"
},
  "geometry": {"coordinates":[8.1262283325,53.5295372009],"type":"Point"}
}