{
  "type": "Feature",
  "properties": {
    "iso:country":"DE",
    "sg:address":"Rathausstr. 10",
    "sg:city":"Alpirsbach",
    "sg:phone":"+49 7444/2581",
    "sg:postcode":"72275",
    "sg:province":"Baden-W\u00fcrttemberg",
    "wof:name":"Ev. Pfarramt Peterzell",
    "wof:placetype":"venue"
},
  "geometry": {"coordinates":[8.462635994,48.325592041],"type":"Point"}
}