{
  "type": "Feature",
  "properties": {
    "iso:country":"DE",
    "sg:address":"Auf Der Komm 1-3",
    "sg:city":"Aldenhoven",
    "sg:phone":"+49 4924/6499060",
    "sg:postcode":"52457",
    "sg:province":"Nordrhein-Westfalen",
    "wof:name":"Oellers-immex Produktions- U. Vertriebs Gmbh & Co. Kg",
    "wof:placetype":"venue"
},
  "geometry": {"coordinates":[6.283864,50.893059],"type":"Point"}
}