{
  "type": "Feature",
  "properties": {
    "iso:country":"DE",
    "sg:address":"Orionstr. 36",
    "sg:city":"Gilching",
    "sg:phone":"+49 8105/23401",
    "sg:postcode":"82205",
    "sg:province":"Bayern",
    "wof:name":"Robert Seidemann",
    "wof:placetype":"venue"
},
  "geometry": {"coordinates":[11.290625,48.105457],"type":"Point"}
}