{
  "type": "Feature",
  "properties": {
    "iso:country":"DE",
    "sg:address":"Malplaquetstr. 8",
    "sg:city":"Berlin",
    "sg:phone":"+49 30/4565117",
    "sg:postcode":"13347",
    "sg:province":"Berlin",
    "wof:name":"Susanne Kuderna",
    "wof:placetype":"venue"
},
  "geometry": {"coordinates":[13.36057,52.55032],"type":"Point"}
}