{
  "type": "Feature",
  "properties": {
    "iso:country":"DE",
    "sg:address":"Sennfelder Weg 14",
    "sg:city":"Birkenfeld",
    "sg:phone":"+49 9398/868",
    "sg:postcode":"97834",
    "sg:province":"Bayern",
    "wof:name":"Nat\u00fcrlich Frisch Vom Bauernhof E. K.",
    "wof:placetype":"venue"
},
  "geometry": {"coordinates":[9.7239675522,49.873336792],"type":"Point"}
}