{
  "type": "Feature",
  "properties": {
    "iso:country":"DE",
    "sg:address":"Kamener Str. 49",
    "sg:city":"B\u00f6nen",
    "sg:phone":"+49 2383/2582",
    "sg:postcode":"59199",
    "sg:province":"Nordrhein-Westfalen",
    "wof:name":"Haus B\u00f6inghoff",
    "wof:placetype":"venue"
},
  "geometry": {"coordinates":[7.7959737778,51.5874786377],"type":"Point"}
}