{
  "type": "Feature",
  "properties": {
    "iso:country":"DE",
    "sg:address":"K\u00f6nig-Karl-Str.",
    "sg:city":"Stuttgart",
    "sg:phone":"+49 711/566422",
    "sg:postcode":"70372",
    "sg:province":"Baden-W\u00fcrttemberg",
    "wof:name":"R. Geywitz",
    "wof:placetype":"venue"
},
  "geometry": {"coordinates":[9.22101,48.806885],"type":"Point"}
}