{
  "type": "Feature",
  "properties": {
    "iso:country":"DE",
    "sg:address":"Holland 31",
    "sg:city":"Herford",
    "sg:phone":"+49 5221/589903",
    "sg:postcode":"32052",
    "sg:province":"Nordrhein-Westfalen",
    "wof:name":"Beckmann Decken Und Volkmar Rechtsanw\u00e4lte",
    "wof:placetype":"venue"
},
  "geometry": {"coordinates":[8.6738376617,52.1177978516],"type":"Point"}
}