{
  "type": "Feature",
  "properties": {
    "iso:country":"DE",
    "sg:address":"Gutenbergstr. 7",
    "sg:city":"Gaimersheim",
    "sg:phone":"+49 8458/32950",
    "sg:postcode":"85080",
    "sg:province":"Bayern",
    "wof:name":"Pruskil Druck Gmbh",
    "wof:placetype":"venue"
},
  "geometry": {"coordinates":[11.3771600723,48.7831306458],"type":"Point"}
}