{
  "type": "Feature",
  "properties": {
    "iso:country":"DE",
    "sg:address":"Bischof-Tenhumberg-Str. 200",
    "sg:city":"Vreden",
    "sg:phone":"+49 2567/3056",
    "sg:postcode":"48691",
    "sg:province":"Nordrhein-Westfalen",
    "wof:name":"Wilhelm Kramer",
    "wof:placetype":"venue"
},
  "geometry": {"coordinates":[6.821105,52.032845],"type":"Point"}
}