{
  "type": "Feature",
  "properties": {
    "iso:country":"DE",
    "sg:address":"Raiffeisenstrasse 4",
    "sg:city":"Donaueschingen",
    "sg:postcode":"78166",
    "sg:province":"Baden-W\u00fcrttemberg",
    "wof:name":"Massivhaus Schl\u00fcsselfertig Oder Als Ausbauhaus",
    "wof:placetype":"venue"
},
  "geometry": {"coordinates":[8.5111312866,47.9592208862],"type":"Point"}
}