{
  "type": "Feature",
  "properties": {
    "iso:country":"DE",
    "sg:address":"Am Eichenrain 9",
    "sg:city":"Schw\u00e4bisch Gm\u00fcnd",
    "sg:phone":"+49 7171/75760",
    "sg:postcode":"73527",
    "sg:province":"Baden-W\u00fcrttemberg",
    "wof:name":"Wido Werner Gmbh",
    "wof:placetype":"venue"
},
  "geometry": {"coordinates":[9.821644,48.831402],"type":"Point"}
}