{
  "type": "Feature",
  "properties": {
    "iso:country":"DE",
    "sg:address":"Waldstr. 259",
    "sg:city":"Offenbach",
    "sg:phone":"+49 69/833460",
    "sg:postcode":"63071",
    "sg:province":"Hessen",
    "wof:name":"Katholisches Pfarramt St. Konrad",
    "wof:placetype":"venue"
},
  "geometry": {"coordinates":[8.7761650085,50.0822677612],"type":"Point"}
}