{
  "type": "Feature",
  "properties": {
    "iso:country":"DE",
    "sg:address":"Ehlbeek 16",
    "sg:city":"Burgwedel",
    "sg:phone":"+49 5139/89740",
    "sg:postcode":"30938",
    "sg:province":"Niedersachsen",
    "wof:name":"Hildegard Braukmann Kosmetik Gmbh & Co. Kg",
    "wof:placetype":"venue"
},
  "geometry": {"coordinates":[9.8450145721,52.4877471924],"type":"Point"}
}