{
  "type": "Feature",
  "properties": {
    "iso:country":"DE",
    "sg:address":"Pr\u00e4lat-Zimmermann-Str. 2",
    "sg:city":"Bad Driburg",
    "sg:phone":"+49 5253/2301",
    "sg:postcode":"33014",
    "sg:province":"Nordrhein-Westfalen",
    "wof:name":"Ferdinand Ibers",
    "wof:placetype":"venue"
},
  "geometry": {"coordinates":[9.0198907852,51.7359924316],"type":"Point"}
}