{
  "type": "Feature",
  "properties": {
    "iso:country":"DE",
    "sg:address":"Hainstr. 11",
    "sg:city":"Bamberg",
    "sg:phone":"+49 951/200240",
    "sg:postcode":"96047",
    "sg:province":"Bayern",
    "wof:name":"Isb-handel",
    "wof:placetype":"venue"
},
  "geometry": {"coordinates":[10.8937768936,49.8895454407],"type":"Point"}
}