{
  "type": "Feature",
  "properties": {
    "iso:country":"DE",
    "sg:address":"Dorfstr. 23",
    "sg:city":"D\u00e4nischenhagen",
    "sg:phone":"+49 4349/1245",
    "sg:postcode":"24229",
    "sg:province":"Schleswig-Holstein",
    "wof:name":"Rolf Kalinka",
    "wof:placetype":"venue"
},
  "geometry": {"coordinates":[10.129827,54.426285],"type":"Point"}
}