{
  "type": "Feature",
  "properties": {
    "iso:country":"DE",
    "sg:address":"Holzdamm 46",
    "sg:city":"Bremen",
    "sg:phone":"+49 421/832103",
    "sg:postcode":"28279",
    "sg:province":"Bremen",
    "wof:name":"Angela K\u00fcstner",
    "wof:placetype":"venue"
},
  "geometry": {"coordinates":[8.845667,53.055462],"type":"Point"}
}