{
  "type": "Feature",
  "properties": {
    "iso:country":"DE",
    "sg:address":"Bergstr. 105",
    "sg:city":"Zwickau",
    "sg:phone":"+49 375/786385",
    "sg:postcode":"08064",
    "sg:province":"Sachsen",
    "wof:name":"Dr. Med. Johanna Sch\u00fcttauf",
    "wof:placetype":"venue"
},
  "geometry": {"coordinates":[12.477141,50.668171],"type":"Point"}
}