{
  "type": "Feature",
  "properties": {
    "iso:country":"DE",
    "sg:address":"M\u00fchlenstr. 1",
    "sg:city":"Raubling",
    "sg:postcode":"83064",
    "sg:province":"Bayern",
    "wof:name":"Chrom Bios Gmbh",
    "wof:placetype":"venue"
},
  "geometry": {"coordinates":[12.1020364761,47.7741737366],"type":"Point"}
}