{
  "type": "Feature",
  "properties": {
    "iso:country":"DE",
    "sg:address":"Rotthof 6",
    "sg:city":"Warburg",
    "sg:phone":"+49 5641/5266",
    "sg:postcode":"34414",
    "sg:province":"Nordrhein-Westfalen",
    "wof:name":"Ute Einsfelder",
    "wof:placetype":"venue"
},
  "geometry": {"coordinates":[9.145142,51.488232],"type":"Point"}
}