{
  "type": "Feature",
  "properties": {
    "iso:country":"DE",
    "sg:address":"Maximilian-Philipp-Str. 15",
    "sg:city":"T\u00fcrkheim",
    "sg:phone":"+49 8245/1316",
    "sg:postcode":"86842",
    "sg:province":"Bayern",
    "wof:name":"Krone",
    "wof:placetype":"venue"
},
  "geometry": {"coordinates":[10.6402301788,48.061378479],"type":"Point"}
}