{
  "type": "Feature",
  "properties": {
    "iso:country":"DE",
    "sg:address":"Steinhauerstr. 6",
    "sg:city":"Kehl",
    "sg:phone":"+49 7853/1047",
    "sg:postcode":"77694",
    "sg:province":"Baden-W\u00fcrttemberg",
    "wof:name":"Tenne",
    "wof:placetype":"venue"
},
  "geometry": {"coordinates":[7.86876297,48.5879669189],"type":"Point"}
}