{
  "type": "Feature",
  "properties": {
    "iso:country":"DE",
    "sg:address":"Lange Reihe 5",
    "sg:city":"Kiel",
    "sg:phone":"+49 4943/199790",
    "sg:postcode":"24103",
    "sg:province":"Schleswig-Holstein",
    "wof:name":"Muhls Hotel",
    "wof:placetype":"venue"
},
  "geometry": {"coordinates":[10.132955,54.31971],"type":"Point"}
}