{
  "type": "Feature",
  "properties": {
    "iso:country":"DE",
    "sg:address":"Georg-Weidner-Str. 18",
    "sg:city":"Neumarkt",
    "sg:phone":"+49 9181/479843",
    "sg:postcode":"92318",
    "sg:province":"Bayern",
    "wof:name":"Helga Volkmann Steuerberater",
    "wof:placetype":"venue"
},
  "geometry": {"coordinates":[11.4455461502,49.2893028259],"type":"Point"}
}