{
  "type": "Feature",
  "properties": {
    "iso:country":"DE",
    "sg:address":"Neerdar 1",
    "sg:city":"Willingen",
    "sg:phone":"+49 5632/5117",
    "sg:postcode":"34508",
    "sg:province":"Hessen",
    "wof:name":"Karl-heinz R\u00fcddenklau",
    "wof:placetype":"venue"
},
  "geometry": {"coordinates":[8.757131,51.285088],"type":"Point"}
}