{
  "type": "Feature",
  "properties": {
    "iso:country":"DE",
    "sg:address":"Heilmannstr. 8",
    "sg:city":"M\u00fcnchen",
    "sg:phone":"+49 89/799081",
    "sg:postcode":"81479",
    "sg:province":"Bayern",
    "wof:name":"Ekkehard Fahr Architekt",
    "wof:placetype":"venue"
},
  "geometry": {"coordinates":[11.535788,48.080894],"type":"Point"}
}