{
  "type": "Feature",
  "properties": {
    "iso:country":"DE",
    "sg:address":"\u00dcberseering 45",
    "sg:city":"Hamburg",
    "sg:postcode":"22297",
    "sg:province":"Hamburg",
    "wof:name":"Beteiligung Hmm Hamburg- Mannheimer Zweite B\u00fcrogeb\u00e4ude",
    "wof:placetype":"venue"
},
  "geometry": {"coordinates":[10.0177869797,53.6008987427],"type":"Point"}
}