{
  "type": "Feature",
  "properties": {
    "iso:country":"DE",
    "sg:address":"Bischofsweg 1",
    "sg:city":"Glandorf",
    "sg:phone":"+49 5426/5260",
    "sg:postcode":"49219",
    "sg:province":"Niedersachsen",
    "wof:name":"Paul Bischof",
    "wof:placetype":"venue"
},
  "geometry": {"coordinates":[7.993527,52.080982],"type":"Point"}
}