{
  "type": "Feature",
  "properties": {
    "iso:country":"DE",
    "sg:address":"Karl-Marx-Str. 27",
    "sg:city":"Milow",
    "sg:phone":"+49 3386/280723",
    "sg:postcode":"14715",
    "sg:province":"Brandenburg",
    "wof:name":"M. P\u00fcschel",
    "wof:placetype":"venue"
},
  "geometry": {"coordinates":[12.310256958,52.5130844116],"type":"Point"}
}