{
  "type": "Feature",
  "properties": {
    "iso:country":"DE",
    "sg:address":"Ringstr. 1",
    "sg:city":"Hessisch Lichtenau",
    "sg:phone":"+49 5602/2950",
    "sg:postcode":"37235",
    "sg:province":"Hessen",
    "wof:name":"Heinrich Appel",
    "wof:placetype":"venue"
},
  "geometry": {"coordinates":[9.7970275879,51.2136421204],"type":"Point"}
}