{
  "type": "Feature",
  "properties": {
    "iso:country":"DE",
    "sg:address":"Johannisstr. 136-137",
    "sg:city":"Osnabr\u00fcck",
    "sg:phone":"+49 541/2026660",
    "sg:postcode":"49074",
    "sg:province":"Niedersachsen",
    "wof:name":"Pferdeszene K. & U. Pferdesportartikel Gmbh",
    "wof:placetype":"venue"
},
  "geometry": {"coordinates":[8.0539989471,52.2659759521],"type":"Point"}
}