{
  "type": "Feature",
  "properties": {
    "iso:country":"DE",
    "sg:address":"Alter Kirchweg 1",
    "sg:city":"Bad Hersfeld",
    "sg:phone":"+49 6621/2466",
    "sg:postcode":"36251",
    "sg:province":"Hessen",
    "wof:name":"Helmut Kraushaar",
    "wof:placetype":"venue"
},
  "geometry": {"coordinates":[9.7029953003,50.8711128235],"type":"Point"}
}