{
  "type": "Feature",
  "properties": {
    "iso:country":"DE",
    "sg:address":"Maternusstr. 16",
    "sg:city":"K\u00f6ln",
    "sg:phone":"+49 221/312276",
    "sg:postcode":"50678",
    "sg:province":"Nordrhein-Westfalen",
    "wof:name":"G. Wallus",
    "wof:placetype":"venue"
},
  "geometry": {"coordinates":[6.963583,50.920692],"type":"Point"}
}