{
  "type": "Feature",
  "properties": {
    "iso:country":"DE",
    "sg:address":"Osnabr\u00fccker Str. 69",
    "sg:city":"Bad Rothenfelde",
    "sg:phone":"+49 5424/4826",
    "sg:postcode":"49214",
    "sg:province":"Niedersachsen",
    "wof:name":"Vita Nova",
    "wof:placetype":"venue"
},
  "geometry": {"coordinates":[8.1643924713,52.1190071106],"type":"Point"}
}