{
  "type": "Feature",
  "properties": {
    "iso:country":"DE",
    "sg:address":"Billhorner Kanalstr. 1",
    "sg:city":"Hamburg",
    "sg:phone":"+49 40/781917",
    "sg:postcode":"20539",
    "sg:province":"Hamburg",
    "wof:name":"Transportunernehmen Klaus Lohmann Gmbh",
    "wof:placetype":"venue"
},
  "geometry": {"coordinates":[10.0337495804,53.5386428833],"type":"Point"}
}