{
  "type": "Feature",
  "properties": {
    "iso:country":"DE",
    "sg:address":"Kirchgasse 143",
    "sg:city":"Borsch",
    "sg:postcode":"36419",
    "sg:province":"Th\u00fcringen",
    "wof:name":"Katholisches Pfarramt Borsch",
    "wof:placetype":"venue"
},
  "geometry": {"coordinates":[9.9651098251,50.733379364],"type":"Point"}
}