{
  "type": "Feature",
  "properties": {
    "iso:country":"DE",
    "sg:address":"Sachsendamm 65",
    "sg:city":"Berlin",
    "sg:phone":"+49 30/7818984",
    "sg:postcode":"10829",
    "sg:province":"Berlin",
    "wof:name":"A. Erdogan Hundezucht",
    "wof:placetype":"venue"
},
  "geometry": {"coordinates":[13.3598470688,52.4756164551],"type":"Point"}
}