{
  "type": "Feature",
  "properties": {
    "iso:country":"DE",
    "sg:address":"N\u00f6renbergstr 45",
    "sg:city":"Bochum",
    "sg:phone":"+49 234/232282",
    "sg:postcode":"44894",
    "sg:province":"Nordrhein-Westfalen",
    "wof:name":"Gesto Tiernahrungsvertrieb Gmbh",
    "wof:placetype":"venue"
},
  "geometry": {"coordinates":[7.30569,51.499271],"type":"Point"}
}