{
  "type": "Feature",
  "properties": {
    "iso:country":"DE",
    "sg:address":"Lettenstr. 33",
    "sg:city":"Auggen",
    "sg:phone":"+49 7631/16352",
    "sg:postcode":"79424",
    "sg:province":"Baden-W\u00fcrttemberg",
    "wof:name":"T. Sahner",
    "wof:placetype":"venue"
},
  "geometry": {"coordinates":[7.596334,47.792355],"type":"Point"}
}