{
  "type": "Feature",
  "properties": {
    "iso:country":"DE",
    "sg:address":"Hofaue 55",
    "sg:city":"Wuppertal",
    "sg:phone":"+49 202/4598980",
    "sg:postcode":"42103",
    "sg:province":"Nordrhein-Westfalen",
    "wof:name":"M.d. Media Plus Design Gmbh",
    "wof:placetype":"venue"
},
  "geometry": {"coordinates":[7.152449131,51.2573814392],"type":"Point"}
}