{
  "type": "Feature",
  "properties": {
    "iso:country":"DE",
    "sg:address":"Heinz-Kettler-Str.",
    "sg:city":"Kleinblittersdorf",
    "sg:phone":"+49 6805/60080",
    "sg:postcode":"66271",
    "sg:province":"Saarland",
    "wof:name":"Heinz Kettler Gmbh & Co. Kg",
    "wof:placetype":"venue"
},
  "geometry": {"coordinates":[7.055972,49.119442],"type":"Point"}
}