{
  "type": "Feature",
  "properties": {
    "iso:country":"DE",
    "sg:address":"Adelheidstr. 103",
    "sg:city":"Wiesbaden",
    "sg:phone":"+49 611/375170",
    "sg:postcode":"65185",
    "sg:province":"Hessen",
    "wof:name":"R\u00fcdiger Scherbaum Rechtsanwalt",
    "wof:placetype":"venue"
},
  "geometry": {"coordinates":[8.2313013077,50.0757675171],"type":"Point"}
}