{
  "type": "Feature",
  "properties": {
    "iso:country":"DE",
    "sg:address":"Stra\u00dfe des Friedens 122",
    "sg:city":"Gera",
    "sg:postcode":"07548",
    "sg:province":"Th\u00fcringen",
    "wof:name":"Wkg-investitions- Und Verwaltungs Gmbh",
    "wof:placetype":"venue"
},
  "geometry": {"coordinates":[12.0596971512,50.8669204712],"type":"Point"}
}