{
  "type": "Feature",
  "properties": {
    "iso:country":"DE",
    "sg:address":"Fleischstr. 33",
    "sg:city":"Trier",
    "sg:phone":"+49 651/73732",
    "sg:postcode":"54290",
    "sg:province":"Rheinland-Pfalz",
    "wof:name":"Schuhhaus Hammes Gmbh",
    "wof:placetype":"venue"
},
  "geometry": {"coordinates":[6.6372518539,49.7544403076],"type":"Point"}
}