{
  "type": "Feature",
  "properties": {
    "iso:country":"DE",
    "sg:address":"Max-Planck-Str. 7",
    "sg:city":"Illertissen",
    "sg:phone":"+49 7303/42484",
    "sg:postcode":"89257",
    "sg:province":"Bayern",
    "wof:name":"Wolfgang Pfeuffer Ingenieur",
    "wof:placetype":"venue"
},
  "geometry": {"coordinates":[10.1033143997,48.2272567749],"type":"Point"}
}