{
  "type": "Feature",
  "properties": {
    "iso:country":"DE",
    "sg:address":"Bergstr. 52",
    "sg:city":"Pritzwalk",
    "sg:phone":"+49 3395/302291",
    "sg:postcode":"16928",
    "sg:province":"Brandenburg",
    "wof:name":"Comtech Nord Gmbh",
    "wof:placetype":"venue"
},
  "geometry": {"coordinates":[12.182674408,53.1502227783],"type":"Point"}
}