{
  "type": "Feature",
  "properties": {
    "iso:country":"DE",
    "sg:address":"Bennstr. 33",
    "sg:city":"Deidesheim",
    "sg:phone":"+49 6326/8705",
    "sg:postcode":"67146",
    "sg:province":"Rheinland-Pfalz",
    "wof:name":"Helmut F\u00fcrst",
    "wof:placetype":"venue"
},
  "geometry": {"coordinates":[8.1837387085,49.4086418152],"type":"Point"}
}