{
  "type": "Feature",
  "properties": {
    "iso:country":"DE",
    "sg:address":"Bruchsaler Str. 6",
    "sg:city":"Gondelsheim",
    "sg:phone":"+49 7252/974390",
    "sg:postcode":"75053",
    "sg:province":"Baden-W\u00fcrttemberg",
    "wof:name":"Eis U. Pizzaria La Sardegna",
    "wof:placetype":"venue"
},
  "geometry": {"coordinates":[8.657937,49.059315],"type":"Point"}
}