{
  "type": "Feature",
  "properties": {
    "iso:country":"DE",
    "sg:address":"H\u00e4gewiesen 117 A",
    "sg:city":"Hannover",
    "sg:phone":"+49 511/908971",
    "sg:postcode":"30657",
    "sg:province":"Niedersachsen",
    "wof:name":"Ev. Pfarramt Epiphaniaskirche",
    "wof:placetype":"venue"
},
  "geometry": {"coordinates":[9.7728948593,52.4154701233],"type":"Point"}
}