{
  "type": "Feature",
  "properties": {
    "iso:country":"DE",
    "sg:address":"Anton-B\u00f6hlen-Str 28",
    "sg:city":"Warburg",
    "sg:phone":"+49 5641/3012",
    "sg:postcode":"34414",
    "sg:province":"Nordrhein-Westfalen",
    "wof:name":"Dr. Sarabhai Gmbh Medical Systems",
    "wof:placetype":"venue"
},
  "geometry": {"coordinates":[9.16234,51.498806],"type":"Point"}
}