{
  "type": "Feature",
  "properties": {
    "iso:country":"DE",
    "sg:address":"Bahnhofstr. 1",
    "sg:city":"Elmstein",
    "sg:phone":"+49 6328/1737",
    "sg:postcode":"67471",
    "sg:province":"Rheinland-Pfalz",
    "wof:name":"Zum Dorfbrunnen",
    "wof:placetype":"venue"
},
  "geometry": {"coordinates":[7.9356088638,49.3515930176],"type":"Point"}
}