{
  "type": "Feature",
  "properties": {
    "iso:country":"DE",
    "sg:address":"K\u00f6nigstr. 49",
    "sg:city":"F\u00fcrth",
    "sg:phone":"+49 911/774624",
    "sg:postcode":"90762",
    "sg:province":"Bayern",
    "wof:name":"K\u00f6nigsst\u00fcberl",
    "wof:placetype":"venue"
},
  "geometry": {"coordinates":[10.987039566,49.4790077209],"type":"Point"}
}