{
  "type": "Feature",
  "properties": {
    "iso:country":"DE",
    "sg:address":"Heldmanstr. 139",
    "sg:city":"Bad Salzuflen",
    "sg:phone":"+49 5222/81776",
    "sg:postcode":"32108",
    "sg:province":"Nordrhein-Westfalen",
    "wof:name":"Reit- U. Fahrverein Bad Salzuflen E.v.",
    "wof:placetype":"venue"
},
  "geometry": {"coordinates":[8.7830553055,52.0774497986],"type":"Point"}
}