{
  "type": "Feature",
  "properties": {
    "iso:country":"DE",
    "sg:address":"Im Hag 29",
    "sg:city":"Eschweiler",
    "sg:phone":"+49 2403/4592",
    "sg:postcode":"52249",
    "sg:province":"Nordrhein-Westfalen",
    "wof:name":"Josef Hollmann Ingenieur",
    "wof:placetype":"venue"
},
  "geometry": {"coordinates":[6.2567491531,50.8060379028],"type":"Point"}
}