{
  "type": "Feature",
  "properties": {
    "iso:country":"DE",
    "sg:address":"Nordstr. 60",
    "sg:city":"Beckum",
    "sg:phone":"+49 2521/3608",
    "sg:postcode":"59269",
    "sg:province":"Nordrhein-Westfalen",
    "wof:name":"Osterhoff Reiseb\u00fcro Inh. I. Pohl-ringkamp",
    "wof:placetype":"venue"
},
  "geometry": {"coordinates":[8.0419254303,51.7588500977],"type":"Point"}
}