{
  "type": "Feature",
  "properties": {
    "iso:country":"DE",
    "sg:address":"Chausseestr. 4",
    "sg:city":"Joachimsthal",
    "sg:phone":"+49 33361/431",
    "sg:postcode":"16247",
    "sg:province":"Brandenburg",
    "wof:name":"Minol Gmbh",
    "wof:placetype":"venue"
},
  "geometry": {"coordinates":[13.7488470078,52.9698944092],"type":"Point"}
}