{
  "type": "Feature",
  "properties": {
    "iso:country":"DE",
    "sg:address":"Virchowstr. 14",
    "sg:city":"W\u00fcrselen",
    "sg:phone":"+49 2405/9742",
    "sg:postcode":"52146",
    "sg:province":"Nordrhein-Westfalen",
    "wof:name":"Dieter Eichelmann Architekt",
    "wof:placetype":"venue"
},
  "geometry": {"coordinates":[6.139322,50.814617],"type":"Point"}
}