{
  "type": "Feature",
  "properties": {
    "iso:country":"DE",
    "sg:address":"Am Landhagen 96-98",
    "sg:city":"Oelde",
    "sg:phone":"+49 4962/8140400",
    "sg:postcode":"59302",
    "sg:province":"Nordrhein-Westfalen",
    "wof:name":"Odenw\u00c4lder Kunststoffwerke Geh\u00c4usesysteme Gmbh",
    "wof:placetype":"venue"
},
  "geometry": {"coordinates":[9.3350391388,49.5238342285],"type":"Point"}
}