{
  "type": "Feature",
  "properties": {
    "iso:country":"DE",
    "sg:address":"Lilienweg 7",
    "sg:city":"Lollar",
    "sg:phone":"+49 6406/1581",
    "sg:postcode":"35457",
    "sg:province":"Hessen",
    "wof:name":"Elfriede Becker",
    "wof:placetype":"venue"
},
  "geometry": {"coordinates":[8.708645,50.662388],"type":"Point"}
}