{
  "type": "Feature",
  "properties": {
    "iso:country":"DE",
    "sg:address":"Gerhart-Hauptmann-Ring 11",
    "sg:city":"M\u00fcnchen",
    "sg:phone":"+49 89/6373490",
    "sg:postcode":"81737",
    "sg:province":"Bayern",
    "wof:name":"Johann Huber Gmbh",
    "wof:placetype":"venue"
},
  "geometry": {"coordinates":[11.650593,48.100697],"type":"Point"}
}