{
  "type": "Feature",
  "properties": {
    "iso:country":"DE",
    "sg:address":"Allendestr.",
    "sg:city":"Schmalkalden",
    "sg:phone":"+49 3683/780631",
    "sg:postcode":"98574",
    "sg:province":"Th\u00fcringen",
    "wof:name":"Barbara Gebhardt",
    "wof:placetype":"venue"
},
  "geometry": {"coordinates":[10.4715747833,50.7229003906],"type":"Point"}
}