{
  "type": "Feature",
  "properties": {
    "iso:country":"DE",
    "sg:address":"Halderstr. 27",
    "sg:city":"Augsburg",
    "sg:phone":"+49 821/502020",
    "sg:postcode":"86150",
    "sg:province":"Bayern",
    "wof:name":"Universal-leasing- Gmbh",
    "wof:placetype":"venue"
},
  "geometry": {"coordinates":[10.889724,48.365025],"type":"Point"}
}