{
  "type": "Feature",
  "properties": {
    "iso:country":"DE",
    "sg:address":"Fraum\u00fcnsterstr. 48",
    "sg:city":"Fritzlar",
    "sg:phone":"+49 5622/3828",
    "sg:postcode":"34560",
    "sg:province":"Hessen",
    "wof:name":"Gerhard Schmidt",
    "wof:placetype":"venue"
},
  "geometry": {"coordinates":[9.282265,51.130238],"type":"Point"}
}