{
  "type": "Feature",
  "properties": {
    "iso:country":"DE",
    "sg:address":"Hauptstra\u00dfe 15",
    "sg:city":"Kirchlinteln",
    "sg:phone":"+49 4236/210",
    "sg:postcode":"27308",
    "sg:province":"Niedersachsen",
    "wof:name":"Autohaus Bomn\u00fcter",
    "wof:placetype":"venue"
},
  "geometry": {"coordinates":[9.3209629059,52.9409103394],"type":"Point"}
}