{
  "type": "Feature",
  "properties": {
    "iso:country":"DE",
    "sg:city":"Rieden",
    "sg:phone":"+49 2655/3719",
    "sg:postcode":"56745",
    "sg:province":"Rheinland-Pfalz",
    "wof:name":"U. Fiola",
    "wof:placetype":"venue"
},
  "geometry": {"coordinates":[7.177323,50.395039],"type":"Point"}
}