{
  "type": "Feature",
  "properties": {
    "iso:country":"DE",
    "sg:address":"Bahnhofstr. 33",
    "sg:city":"Alt Duvenstedt",
    "sg:phone":"+49 4338/99780",
    "sg:postcode":"24791",
    "sg:province":"Schleswig-Holstein",
    "wof:name":"Praxis Lawrenz",
    "wof:placetype":"venue"
},
  "geometry": {"coordinates":[9.6356468201,54.3585968018],"type":"Point"}
}