{
  "type": "Feature",
  "properties": {
    "iso:country":"DE",
    "sg:address":"Hasensteig 22",
    "sg:city":"Meerane",
    "sg:phone":"+49 3764/3858",
    "sg:postcode":"08393",
    "sg:province":"Sachsen",
    "wof:name":"Volkmar Hecht",
    "wof:placetype":"venue"
},
  "geometry": {"coordinates":[12.4597654343,50.840637207],"type":"Point"}
}