{
  "type": "Feature",
  "properties": {
    "iso:country":"DE",
    "sg:address":"Bachstr. 18",
    "sg:city":"March",
    "sg:phone":"+49 7665/2510",
    "sg:postcode":"79232",
    "sg:province":"Baden-W\u00fcrttemberg",
    "wof:name":"Maier Schwimmbadbau Gmbh",
    "wof:placetype":"venue"
},
  "geometry": {"coordinates":[7.801999,48.072681],"type":"Point"}
}