{
  "type": "Feature",
  "properties": {
    "iso:country":"DE",
    "sg:address":"Nordstr. 124a",
    "sg:city":"D\u00fcren",
    "sg:phone":"+49 2421/83444",
    "sg:postcode":"52353",
    "sg:province":"Nordrhein-Westfalen",
    "wof:name":"Helmut Schmidt",
    "wof:placetype":"venue"
},
  "geometry": {"coordinates":[6.4576530457,50.8317718506],"type":"Point"}
}