{
  "type": "Feature",
  "properties": {
    "iso:country":"DE",
    "sg:address":"Gartenstr. 17",
    "sg:city":"Gaildorf",
    "sg:phone":"+49 7971/5403",
    "sg:postcode":"74405",
    "sg:province":"Baden-W\u00fcrttemberg",
    "wof:name":"U. Schaupp-munz",
    "wof:placetype":"venue"
},
  "geometry": {"coordinates":[9.766182,48.997959],"type":"Point"}
}