{
  "type": "Feature",
  "properties": {
    "iso:country":"DE",
    "sg:address":"Merchinger Str. 53",
    "sg:city":"Merzig",
    "sg:phone":"+49 6861/2393",
    "sg:postcode":"66663",
    "sg:province":"Saarland",
    "wof:name":"Alois Mutschler Architekt",
    "wof:placetype":"venue"
},
  "geometry": {"coordinates":[6.65427,49.441654],"type":"Point"}
}