{
  "type": "Feature",
  "properties": {
    "iso:country":"DE",
    "sg:address":"Gewerbering 9",
    "sg:city":"Ruderting",
    "sg:phone":"+49 8509/93140",
    "sg:postcode":"94161",
    "sg:province":"Bayern",
    "wof:name":"Kunstglaserei Johann Winter",
    "wof:placetype":"venue"
},
  "geometry": {"coordinates":[13.4276390076,48.6523857117],"type":"Point"}
}