{
  "type": "Feature",
  "properties": {
    "iso:country":"DE",
    "sg:address":"Theodor-Heuss-Anlage 2",
    "sg:city":"Mannheim",
    "sg:postcode":"68165",
    "sg:province":"Baden-W\u00fcrttemberg",
    "wof:name":"Grundst\u00fccksverwaltungs- Gesellschaft Rheinbrohl Mbh",
    "wof:placetype":"venue"
},
  "geometry": {"coordinates":[8.4956483841,49.4787254333],"type":"Point"}
}