{
  "type": "Feature",
  "properties": {
    "iso:country":"DE",
    "sg:address":"Kirchplatz 14",
    "sg:city":"Oberstaufen",
    "sg:postcode":"87534",
    "sg:province":"Bayern",
    "wof:name":"Sigrit Warschkow",
    "wof:placetype":"venue"
},
  "geometry": {"coordinates":[10.022158,47.55389],"type":"Point"}
}