{
  "type": "Feature",
  "properties": {
    "iso:country":"DE",
    "sg:address":"Schillerstr. 62",
    "sg:city":"Erfurt",
    "sg:phone":"+49 361/3461021",
    "sg:postcode":"99096",
    "sg:province":"Th\u00fcringen",
    "wof:name":"K\u00fcchenagentur Erfurt",
    "wof:placetype":"venue"
},
  "geometry": {"coordinates":[11.0242977142,50.9664955139],"type":"Point"}
}