{
  "type": "Feature",
  "properties": {
    "iso:country":"DE",
    "sg:address":"Schwalbenweg 14",
    "sg:city":"Klempau",
    "sg:phone":"+49 4508/7142",
    "sg:postcode":"23628",
    "sg:province":"Schleswig-Holstein",
    "wof:name":"G\u00fcnter Kanowski",
    "wof:placetype":"venue"
},
  "geometry": {"coordinates":[10.6621608734,53.761554718],"type":"Point"}
}