{
  "type": "Feature",
  "properties": {
    "iso:country":"DE",
    "sg:address":"Meichelbeckstr. 38",
    "sg:city":"Marktoberdorf",
    "sg:phone":"+49 8342/95559",
    "sg:postcode":"87616",
    "sg:province":"Bayern",
    "wof:name":"Pizza-service",
    "wof:placetype":"venue"
},
  "geometry": {"coordinates":[10.6163988113,47.7741355896],"type":"Point"}
}