{
  "type": "Feature",
  "properties": {
    "iso:country":"DE",
    "sg:address":"In der Wanne 9",
    "sg:city":"Altheim",
    "sg:phone":"+49 7340/333",
    "sg:postcode":"89174",
    "sg:province":"Baden-W\u00fcrttemberg",
    "wof:name":"R\u00f6sch Bauunternehmen Gmbh",
    "wof:placetype":"venue"
},
  "geometry": {"coordinates":[10.029005,48.58477],"type":"Point"}
}