{
  "type": "Feature",
  "properties": {
    "iso:country":"DE",
    "sg:address":"Einsteinstr. 28",
    "sg:city":"Ettlingen",
    "sg:postcode":"76275",
    "sg:province":"Baden-W\u00fcrttemberg",
    "wof:name":"Sit Steuerungstechnik Gmbh",
    "wof:placetype":"venue"
},
  "geometry": {"coordinates":[8.3742685318,48.9411506653],"type":"Point"}
}