{
  "type": "Feature",
  "properties": {
    "iso:country":"DE",
    "sg:address":"M\u00fcnchhof",
    "sg:city":"Lohmar",
    "sg:phone":"+49 2206/5364",
    "sg:postcode":"53797",
    "sg:province":"Nordrhein-Westfalen",
    "wof:name":"H. Koch Rechtsanwalt",
    "wof:placetype":"venue"
},
  "geometry": {"coordinates":[7.2631750107,50.8833236694],"type":"Point"}
}