{
  "type": "Feature",
  "properties": {
    "iso:country":"DE",
    "sg:address":"Nikolausstr. 33",
    "sg:city":"Heldenstein",
    "sg:phone":"+49 8636/6264",
    "sg:postcode":"84431",
    "sg:province":"Bayern",
    "wof:name":"M. Und I. M\u00fcller Gmbh",
    "wof:placetype":"venue"
},
  "geometry": {"coordinates":[12.3798236847,48.2486801147],"type":"Point"}
}