{
  "type": "Feature",
  "properties": {
    "iso:country":"DE",
    "sg:address":"Hauptstr. 318",
    "sg:city":"Gaienhofen",
    "sg:phone":"+49 7735/2035",
    "sg:postcode":"78343",
    "sg:province":"Baden-W\u00fcrttemberg",
    "wof:name":"Hotel Landgasthaus Kellhof",
    "wof:placetype":"venue"
},
  "geometry": {"coordinates":[8.9753704071,47.6786613464],"type":"Point"}
}