{
  "type": "Feature",
  "properties": {
    "iso:country":"DE",
    "sg:address":"Hofackerstr. 9",
    "sg:city":"Kirchhain",
    "sg:phone":"+49 6422/1494",
    "sg:postcode":"35274",
    "sg:province":"Hessen",
    "wof:name":"Wolfgang G\u00fchlich",
    "wof:placetype":"venue"
},
  "geometry": {"coordinates":[8.921747,50.82206],"type":"Point"}
}