{
  "type": "Feature",
  "properties": {
    "iso:country":"DE",
    "sg:address":"Wachsbleiche 7/12",
    "sg:city":"Bonn",
    "sg:postcode":"53111",
    "sg:province":"Nordrhein-Westfalen",
    "wof:name":"Canini Verwaltungs-gmbh",
    "wof:placetype":"venue"
},
  "geometry": {"coordinates":[7.1007199287,50.7407798767],"type":"Point"}
}