{
  "type": "Feature",
  "properties": {
    "iso:country":"DE",
    "sg:address":"Nigglstr. 5a",
    "sg:city":"M\u00fcnchen",
    "sg:phone":"+49 89/8127007",
    "sg:postcode":"80999",
    "sg:province":"Bayern",
    "wof:name":"Christoph Kubuschok Architekt",
    "wof:placetype":"venue"
},
  "geometry": {"coordinates":[11.459153,48.188469],"type":"Point"}
}