{
  "type": "Feature",
  "properties": {
    "iso:country":"DE",
    "sg:address":"Adalbert-Stifter-Weg 8",
    "sg:city":"N\u00fcrtingen",
    "sg:phone":"+49 7022/949395",
    "sg:postcode":"72622",
    "sg:province":"Baden-W\u00fcrttemberg",
    "wof:name":"H. Handel",
    "wof:placetype":"venue"
},
  "geometry": {"coordinates":[9.3584709167,48.6118736267],"type":"Point"}
}