{
  "type": "Feature",
  "properties": {
    "iso:country":"DE",
    "sg:address":"Rossertstr. 18",
    "sg:city":"K\u00f6nigstein",
    "sg:phone":"+49 6174/7443",
    "sg:postcode":"61462",
    "sg:province":"Hessen",
    "wof:name":"G\u00fcnter Lemke Gmbh",
    "wof:placetype":"venue"
},
  "geometry": {"coordinates":[8.446939,50.173714],"type":"Point"}
}