{
  "type": "Feature",
  "properties": {
    "iso:country":"DE",
    "sg:address":"Kastanienweg 5",
    "sg:city":"Gr\u00f6benzell",
    "sg:phone":"+49 8142/590594",
    "sg:postcode":"82194",
    "sg:province":"Bayern",
    "wof:name":"Angelika Seyferth",
    "wof:placetype":"venue"
},
  "geometry": {"coordinates":[11.3690690994,48.2023468018],"type":"Point"}
}