{
  "type": "Feature",
  "properties": {
    "iso:country":"DE",
    "sg:address":"Hauptstr. 17",
    "sg:city":"M\u00fchlheim",
    "sg:phone":"+49 6108/74129",
    "sg:postcode":"63165",
    "sg:province":"Hessen",
    "wof:name":"Traum Tours Fuentes-perry Kg",
    "wof:placetype":"venue"
},
  "geometry": {"coordinates":[8.8571405411,50.1234588623],"type":"Point"}
}