{
  "type": "Feature",
  "properties": {
    "iso:country":"DE",
    "sg:address":"Gl\u00fcck-Auf-Str. 36",
    "sg:city":"Hilchenbach",
    "sg:phone":"+49 2733/2820",
    "sg:postcode":"57271",
    "sg:province":"Nordrhein-Westfalen",
    "wof:name":"Friedrich Wenz Gmbh & Co. Kg",
    "wof:placetype":"venue"
},
  "geometry": {"coordinates":[8.044159,50.987747],"type":"Point"}
}