{
  "type": "Feature",
  "properties": {
    "iso:country":"DE",
    "sg:address":"Heinrich-Lindner-Str. 18",
    "sg:city":"Fichtelberg",
    "sg:phone":"+49 9272/96219",
    "sg:postcode":"95686",
    "sg:province":"Bayern",
    "wof:name":"Kups Edv-gmbh",
    "wof:placetype":"venue"
},
  "geometry": {"coordinates":[11.8520841599,50.0064353943],"type":"Point"}
}