{
  "type": "Feature",
  "properties": {
    "iso:country":"DE",
    "sg:address":"Unterdorfstr. 39 A",
    "sg:city":"Beuren",
    "sg:postcode":"56825",
    "sg:province":"Rheinland-Pfalz",
    "wof:name":"Amchro Gmbh",
    "wof:placetype":"venue"
},
  "geometry": {"coordinates":[7.0794701576,50.0927200317],"type":"Point"}
}