{
  "type": "Feature",
  "properties": {
    "iso:country":"DE",
    "sg:address":"Mannheimer Str. 41",
    "sg:city":"K\u00f6ln",
    "sg:phone":"+49 221/895338",
    "sg:postcode":"51107",
    "sg:province":"Nordrhein-Westfalen",
    "wof:name":"Hans Heck Architekt",
    "wof:placetype":"venue"
},
  "geometry": {"coordinates":[7.038832,50.928989],"type":"Point"}
}