{
  "type": "Feature",
  "properties": {
    "iso:country":"DE",
    "sg:address":"Frankensteiner Str. 1",
    "sg:city":"Weiterstadt",
    "sg:phone":"+49 6150/2667",
    "sg:postcode":"64331",
    "sg:province":"Hessen",
    "wof:name":"Karlheinz Schaubeck E. K.",
    "wof:placetype":"venue"
},
  "geometry": {"coordinates":[8.58469,49.900562],"type":"Point"}
}