{
  "type": "Feature",
  "properties": {
    "iso:country":"DE",
    "sg:address":"Von-Helfensteingasse 426",
    "sg:city":"Landsberg",
    "sg:phone":"+49 8191/128266",
    "sg:postcode":"86899",
    "sg:province":"Bayern",
    "wof:name":"Neues Stadtmuseum",
    "wof:placetype":"venue"
},
  "geometry": {"coordinates":[10.879355,48.049637],"type":"Point"}
}