{
  "type": "Feature",
  "properties": {
    "iso:country":"DE",
    "sg:address":"Borriesstr. 24",
    "sg:city":"B\u00fcnde",
    "sg:phone":"+49 5223/4771",
    "sg:postcode":"32257",
    "sg:province":"Nordrhein-Westfalen",
    "wof:name":"Malermeister Tiemann Gmbh",
    "wof:placetype":"venue"
},
  "geometry": {"coordinates":[8.57232,52.203674],"type":"Point"}
}