{
  "type": "Feature",
  "properties": {
    "iso:country":"DE",
    "sg:address":"Osterstr. 1",
    "sg:city":"Elbe",
    "sg:phone":"+49 5345/351",
    "sg:postcode":"38274",
    "sg:province":"Niedersachsen",
    "wof:name":"T. Und U. Lohse",
    "wof:placetype":"venue"
},
  "geometry": {"coordinates":[10.308277,52.092381],"type":"Point"}
}