{
  "type": "Feature",
  "properties": {
    "iso:country":"DE",
    "sg:address":"Luitpoldstr. 25-27",
    "sg:city":"Zweibr\u00fccken",
    "sg:phone":"+49 6332/17587",
    "sg:postcode":"66482",
    "sg:province":"Rheinland-Pfalz",
    "wof:name":"Jakob Seibert Kg",
    "wof:placetype":"venue"
},
  "geometry": {"coordinates":[7.3591189384,49.2467956543],"type":"Point"}
}