{
  "type": "Feature",
  "properties": {
    "iso:country":"DE",
    "sg:address":"Theodor-Heuss-Allee 106",
    "sg:city":"Frankfurt",
    "sg:postcode":"60486",
    "sg:province":"Hessen",
    "wof:name":"Kreditwesen Service Buchhandel Und Marketing Gmbh",
    "wof:placetype":"venue"
},
  "geometry": {"coordinates":[8.6340923309,50.1152153015],"type":"Point"}
}