{
  "type": "Feature",
  "properties": {
    "iso:country":"DE",
    "sg:address":"Kantstr. 28",
    "sg:city":"Espelkamp",
    "sg:phone":"+49 5772/3484",
    "sg:postcode":"32339",
    "sg:province":"Nordrhein-Westfalen",
    "wof:name":"Restaurant Sudetenland",
    "wof:placetype":"venue"
},
  "geometry": {"coordinates":[8.6304674149,52.3788528442],"type":"Point"}
}