{
  "type": "Feature",
  "properties": {
    "iso:country":"DE",
    "sg:address":"Eschersheimer Landstr. 55",
    "sg:city":"Frankfurt",
    "sg:phone":"+49 69/905540",
    "sg:postcode":"60322",
    "sg:province":"Hessen",
    "wof:name":"Metromedia Germany Holding Gmbh",
    "wof:placetype":"venue"
},
  "geometry": {"coordinates":[8.675438,50.121628],"type":"Point"}
}