{
  "type": "Feature",
  "properties": {
    "iso:country":"DE",
    "sg:address":"Kreuzstr. 19 a",
    "sg:city":"Willich",
    "sg:phone":"+49 2154/412624",
    "sg:postcode":"47877",
    "sg:province":"Nordrhein-Westfalen",
    "wof:name":"U. H\u00fcsgen Architekt",
    "wof:placetype":"venue"
},
  "geometry": {"coordinates":[6.550544,51.262325],"type":"Point"}
}