{
  "type": "Feature",
  "properties": {
    "iso:country":"DE",
    "sg:address":"Gro\u00dfe Str. 49",
    "sg:city":"Dissen",
    "sg:phone":"+49 5421/2661",
    "sg:postcode":"49201",
    "sg:province":"Niedersachsen",
    "wof:name":"Biedendieck",
    "wof:placetype":"venue"
},
  "geometry": {"coordinates":[8.200873,52.114719],"type":"Point"}
}