{
  "type": "Feature",
  "properties": {
    "iso:country":"DE",
    "sg:address":"Untere M\u00fchlstr. 14",
    "sg:city":"M\u00fchlhausen",
    "sg:phone":"+49 6222/63252",
    "sg:postcode":"69242",
    "sg:province":"Baden-W\u00fcrttemberg",
    "wof:name":"Kath. Pfarramt St. C\u00e4cilia",
    "wof:placetype":"venue"
},
  "geometry": {"coordinates":[8.726723671,49.249835968],"type":"Point"}
}