{
  "type": "Feature",
  "properties": {
    "iso:country":"DE",
    "sg:address":"Grabenstr. 11",
    "sg:city":"Isny",
    "sg:phone":"+49 7562/8568",
    "sg:postcode":"88316",
    "sg:province":"Baden-W\u00fcrttemberg",
    "wof:name":"Peter Gutmair",
    "wof:placetype":"venue"
},
  "geometry": {"coordinates":[10.040927,47.690727],"type":"Point"}
}