{
  "type": "Feature",
  "properties": {
    "iso:country":"DE",
    "sg:address":"Immergr\u00fcnstr. 23",
    "sg:city":"M\u00fcnchen",
    "sg:phone":"+49 89/6903434",
    "sg:postcode":"81547",
    "sg:province":"Bayern",
    "wof:name":"Maria Bader",
    "wof:placetype":"venue"
},
  "geometry": {"coordinates":[11.579413,48.099613],"type":"Point"}
}