{
  "type": "Feature",
  "properties": {
    "iso:country":"DE",
    "sg:address":"Mainzer Str. 12",
    "sg:city":"Heilbronn",
    "sg:phone":"+49 7066/901711",
    "sg:postcode":"74078",
    "sg:province":"Baden-W\u00fcrttemberg",
    "wof:name":"R. Hofmann",
    "wof:placetype":"venue"
},
  "geometry": {"coordinates":[9.113697052,49.1791305542],"type":"Point"}
}