{
  "type": "Feature",
  "properties": {
    "iso:country":"DE",
    "sg:address":"Postfach 1164",
    "sg:city":"Bad Reichenhall",
    "sg:phone":"+49 8651/5011",
    "sg:postcode":"83421",
    "sg:province":"Bayern",
    "wof:name":"Stadtbauamt",
    "wof:placetype":"venue"
},
  "geometry": {"coordinates":[12.8782901764,47.7277908325],"type":"Point"}
}