{
  "type": "Feature",
  "properties": {
    "iso:country":"DE",
    "sg:address":"Beckhausstr. 64",
    "sg:city":"Bielefeld",
    "sg:postcode":"33611",
    "sg:province":"Nordrhein-Westfalen",
    "wof:name":"Aldi Gmbh & Co. Kg",
    "wof:placetype":"venue"
},
  "geometry": {"coordinates":[8.5439443588,52.0399131775],"type":"Point"}
}