{
  "type": "Feature",
  "properties": {
    "iso:country":"DE",
    "sg:address":"Plieningerstra\u00dfe 53",
    "sg:city":"Stuttgart",
    "sg:phone":"+49 711/7285937",
    "sg:postcode":"70567",
    "sg:province":"Baden-W\u00fcrttemberg",
    "wof:name":"Diamant",
    "wof:placetype":"venue"
},
  "geometry": {"coordinates":[9.16026,48.723221],"type":"Point"}
}