{
  "type": "Feature",
  "properties": {
    "iso:country":"DE",
    "sg:address":"Bielstr. 12",
    "sg:city":"Zwickau",
    "sg:phone":"+49 4937/5795205",
    "sg:postcode":"08062",
    "sg:province":"Sachsen",
    "wof:name":"W\u00c4rmesysteme Bachmann-beyerl Blei Gbr.",
    "wof:placetype":"venue"
},
  "geometry": {"coordinates":[12.46981,50.692322],"type":"Point"}
}