{
  "type": "Feature",
  "properties": {
    "iso:country":"DE",
    "sg:address":"Wolkersdorfer Str. 20",
    "sg:city":"Traunstein",
    "sg:phone":"+49 861/4718",
    "sg:postcode":"83278",
    "sg:province":"Bayern",
    "wof:name":"Margareta Singer Krankengymnastin",
    "wof:placetype":"venue"
},
  "geometry": {"coordinates":[12.631732,47.876019],"type":"Point"}
}