{
  "type": "Feature",
  "properties": {
    "iso:country":"DE",
    "sg:address":"Wilhelmstr.5 a",
    "sg:city":"Troisdorf",
    "sg:phone":"+49 2241/77021",
    "sg:postcode":"53840",
    "sg:province":"Nordrhein-Westfalen",
    "wof:name":"Dresdner Bank",
    "wof:placetype":"venue"
},
  "geometry": {"coordinates":[7.154196,50.815239],"type":"Point"}
}