{
  "type": "Feature",
  "properties": {
    "iso:country":"DE",
    "sg:address":"Wallensteinstr. 97",
    "sg:city":"N\u00fcrnberg",
    "sg:phone":"+49 911/616916",
    "sg:postcode":"90431",
    "sg:province":"Bayern",
    "wof:name":"Wilfried Hawich",
    "wof:placetype":"venue"
},
  "geometry": {"coordinates":[11.028448,49.436501],"type":"Point"}
}