{
  "type": "Feature",
  "properties": {
    "iso:country":"DE",
    "sg:address":"Langenberger Weg 32",
    "sg:city":"Seesen",
    "sg:phone":"+49 5381/93790",
    "sg:postcode":"38723",
    "sg:province":"Niedersachsen",
    "wof:name":"Dieter Pietzonke",
    "wof:placetype":"venue"
},
  "geometry": {"coordinates":[10.1618,51.923962],"type":"Point"}
}