{
  "type": "Feature",
  "properties": {
    "iso:country":"DE",
    "sg:address":"Duesbergweg",
    "sg:city":"Mainz",
    "sg:phone":"+49 6131/395959",
    "sg:postcode":"55128",
    "sg:province":"Rheinland-Pfalz",
    "wof:name":"Universit\u00e4tsarchiv Der Johannes Gutenberg-universit\u00e4t",
    "wof:placetype":"venue"
},
  "geometry": {"coordinates":[8.230659,49.992279],"type":"Point"}
}