{
  "type": "Feature",
  "properties": {
    "iso:country":"DE",
    "sg:address":"Bahnhofstr. 18",
    "sg:city":"Ortenberg",
    "sg:phone":"+49 6041/6307",
    "sg:postcode":"63683",
    "sg:province":"Hessen",
    "wof:name":"Hartmut Hil\u00df",
    "wof:placetype":"venue"
},
  "geometry": {"coordinates":[9.04924,50.325653],"type":"Point"}
}