{
  "type": "Feature",
  "properties": {
    "iso:country":"DE",
    "sg:address":"Leibnizstr. 4",
    "sg:city":"H\u00f6chberg",
    "sg:phone":"+49 931/497060",
    "sg:postcode":"97204",
    "sg:province":"Bayern",
    "wof:name":"Multi Office Team",
    "wof:placetype":"venue"
},
  "geometry": {"coordinates":[9.8677616119,49.7714805603],"type":"Point"}
}