{
  "type": "Feature",
  "properties": {
    "iso:country":"DE",
    "sg:address":"Am Esch 8",
    "sg:city":"Westerstede",
    "sg:phone":"+49 4488/71283",
    "sg:postcode":"26655",
    "sg:province":"Niedersachsen",
    "wof:name":"Frahmann Ingenieur",
    "wof:placetype":"venue"
},
  "geometry": {"coordinates":[7.9315648079,53.2617645264],"type":"Point"}
}