{
  "type": "Feature",
  "properties": {
    "iso:country":"DE",
    "sg:address":"Apfeltrang",
    "sg:city":"Ruderatshofen",
    "sg:phone":"+49 8341/81976",
    "sg:postcode":"87674",
    "sg:province":"Bayern",
    "wof:name":"Hubertus",
    "wof:placetype":"venue"
},
  "geometry": {"coordinates":[10.5947303772,47.8431396484],"type":"Point"}
}