{
  "type": "Feature",
  "properties": {
    "iso:country":"DE",
    "sg:address":"Hinter den H\u00f6fen 4 D",
    "sg:city":"Isernhagen",
    "sg:postcode":"30916",
    "sg:province":"Niedersachsen",
    "wof:name":"Enrico Schulz Fahrzeug- \u00fcberf\u00fchrungen Gmbh",
    "wof:placetype":"venue"
},
  "geometry": {"coordinates":[9.889168,52.465195],"type":"Point"}
}