{
  "type": "Feature",
  "properties": {
    "iso:country":"DE",
    "sg:address":"Aachener Str. 1040::",
    "sg:city":"Koeln",
    "sg:phone":"+49 4922/14893",
    "sg:postcode":"50858",
    "sg:province":"Nordrhein-Westfalen",
    "wof:name":"Gvv-kommunalversicherung, Versicherungsverein Auf Gegenseitigkeit",
    "wof:placetype":"venue"
},
  "geometry": {"coordinates":[6.857081,50.938305],"type":"Point"}
}