{
  "type": "Feature",
  "properties": {
    "iso:country":"DE",
    "sg:address":"Brunnwiese 12",
    "sg:city":"Traunstein",
    "sg:phone":"+49 861/8367",
    "sg:postcode":"83278",
    "sg:province":"Bayern",
    "wof:name":"Hundskugel",
    "wof:placetype":"venue"
},
  "geometry": {"coordinates":[12.6476621628,47.872592926],"type":"Point"}
}