{
  "type": "Feature",
  "properties": {
    "iso:country":"DE",
    "sg:address":"An der Lieth 7",
    "sg:city":"Bremen",
    "sg:phone":"+49 421/438303",
    "sg:postcode":"28307",
    "sg:province":"Bremen",
    "wof:name":"Hans Gerken Steuerberater",
    "wof:placetype":"venue"
},
  "geometry": {"coordinates":[8.9442367554,53.0357437134],"type":"Point"}
}