{
  "type": "Feature",
  "properties": {
    "iso:country":"DE",
    "sg:address":"Werster Str. 142",
    "sg:city":"Bad Oeynhausen",
    "sg:phone":"+49 5731/41756",
    "sg:postcode":"32549",
    "sg:province":"Nordrhein-Westfalen",
    "wof:name":"Ralf Brinkmann",
    "wof:placetype":"venue"
},
  "geometry": {"coordinates":[8.7753772736,52.2155532837],"type":"Point"}
}