{
  "type": "Feature",
  "properties": {
    "iso:country":"DE",
    "sg:address":"Koopstr. 14",
    "sg:city":"Hamburg",
    "sg:phone":"+49 40/452769",
    "sg:postcode":"20144",
    "sg:province":"Hamburg",
    "wof:name":"Franz Epping",
    "wof:placetype":"venue"
},
  "geometry": {"coordinates":[9.974029541,53.5704956055],"type":"Point"}
}