{
  "type": "Feature",
  "properties": {
    "iso:country":"DE",
    "sg:address":"Hauptstr. 266",
    "sg:city":"Herne",
    "sg:phone":"+49 2325/77035",
    "sg:postcode":"44649",
    "sg:province":"Nordrhein-Westfalen",
    "wof:name":"Baumbach Und Sauerland Gmbh",
    "wof:placetype":"venue"
},
  "geometry": {"coordinates":[7.157971859,51.5332107544],"type":"Point"}
}