{
  "type": "Feature",
  "properties": {
    "iso:country":"DE",
    "sg:address":"Oderberger Str. 2",
    "sg:city":"Angerm\u00fcnde",
    "sg:phone":"+49 3331/23713",
    "sg:postcode":"16278",
    "sg:province":"Brandenburg",
    "wof:name":"Bier- Und Cafestube",
    "wof:placetype":"venue"
},
  "geometry": {"coordinates":[13.9985818863,53.0142402649],"type":"Point"}
}