{
  "type": "Feature",
  "properties": {
    "iso:country":"DE",
    "sg:address":"Westenwall 4",
    "sg:city":"Hamm",
    "sg:postcode":"59065",
    "sg:province":"Nordrhein-Westfalen",
    "wof:name":"Aldi Gmbh & Co. Kg",
    "wof:placetype":"venue"
},
  "geometry": {"coordinates":[7.8137102127,51.6814346313],"type":"Point"}
}