{
  "type": "Feature",
  "properties": {
    "iso:country":"DE",
    "sg:address":"Wilder-Mann-Str. 30",
    "sg:city":"Dresden",
    "sg:phone":"+49 351/8492115",
    "sg:postcode":"01129",
    "sg:province":"Sachsen",
    "wof:name":"Thomas Hirsch Ingenieur",
    "wof:placetype":"venue"
},
  "geometry": {"coordinates":[13.716129303,51.0909957886],"type":"Point"}
}