{
  "type": "Feature",
  "properties": {
    "iso:country":"DE",
    "sg:address":"Auf der Flur 37",
    "sg:city":"Castrop-Rauxel",
    "sg:postcode":"44581",
    "sg:province":"Nordrhein-Westfalen",
    "wof:name":"Gfn Gesellschaft F\u00fcr Naturheilverfahren Information",
    "wof:placetype":"venue"
},
  "geometry": {"coordinates":[7.3033618927,51.6067771912],"type":"Point"}
}