{
  "type": "Feature",
  "properties": {
    "iso:country":"DE",
    "sg:address":"Neuh\u00e4user Str. 18",
    "sg:city":"F\u00fcrstenberg",
    "sg:phone":"+49 5271/4490",
    "sg:postcode":"37699",
    "sg:province":"Niedersachsen",
    "wof:name":"Christiane Schmidt Masseurin",
    "wof:placetype":"venue"
},
  "geometry": {"coordinates":[9.403722,51.72794],"type":"Point"}
}