{
  "type": "Feature",
  "properties": {
    "iso:country":"DE",
    "sg:address":"Simmersh\u00e4user Str. 41",
    "sg:city":"Vellmar",
    "sg:phone":"+49 561/828864",
    "sg:postcode":"34246",
    "sg:province":"Hessen",
    "wof:name":"Atr Trans Transporte Gmbh",
    "wof:placetype":"venue"
},
  "geometry": {"coordinates":[9.48234272,51.3676376343],"type":"Point"}
}