{
  "type": "Feature",
  "properties": {
    "iso:country":"DE",
    "sg:address":"Obertorstr. 61",
    "sg:city":"Esslingen",
    "sg:phone":"+49 711/3180767",
    "sg:postcode":"73728",
    "sg:province":"Baden-W\u00fcrttemberg",
    "wof:name":"Charlotten-stube",
    "wof:placetype":"venue"
},
  "geometry": {"coordinates":[9.3157291412,48.737247467],"type":"Point"}
}