{
  "type": "Feature",
  "properties": {
    "iso:country":"DE",
    "sg:address":"Erlenweg 9",
    "sg:city":"Germering",
    "sg:phone":"+49 89/844663",
    "sg:postcode":"82110",
    "sg:province":"Bayern",
    "wof:name":"Erasmus Kleinhans Rechtsanwalt",
    "wof:placetype":"venue"
},
  "geometry": {"coordinates":[11.3610811234,48.1382064819],"type":"Point"}
}