{
  "type": "Feature",
  "properties": {
    "iso:country":"DE",
    "sg:address":"Weissenburgerstra\u00dfe 89",
    "sg:city":"Gunzenhausen",
    "sg:phone":"+49 9831",
    "sg:postcode":"91710",
    "sg:province":"Bayern",
    "wof:name":"Heinzmann Autotechnik Kg",
    "wof:placetype":"venue"
},
  "geometry": {"coordinates":[10.7623052597,49.105796814],"type":"Point"}
}