{
  "type": "Feature",
  "properties": {
    "iso:country":"DE",
    "sg:address":"Kampstr. 111",
    "sg:city":"Haan",
    "sg:phone":"+49 212/92054",
    "sg:postcode":"42781",
    "sg:province":"Nordrhein-Westfalen",
    "wof:name":"Reiseagentur Dr. Amels Gmbh",
    "wof:placetype":"venue"
},
  "geometry": {"coordinates":[7.0289888382,51.1983642578],"type":"Point"}
}