{
  "type": "Feature",
  "properties": {
    "iso:country":"DE",
    "sg:address":"Georgstr. 1",
    "sg:city":"Themar",
    "sg:phone":"+49 36873/60835",
    "sg:postcode":"98660",
    "sg:province":"Th\u00fcringen",
    "wof:name":"Brigittes St\u00fcbchen",
    "wof:placetype":"venue"
},
  "geometry": {"coordinates":[10.6151742935,50.5027809143],"type":"Point"}
}