{
  "type": "Feature",
  "properties": {
    "iso:country":"DE",
    "sg:address":"Krummredder 58",
    "sg:city":"Neum\u00fcnster",
    "sg:phone":"+49 4321/77363",
    "sg:postcode":"24539",
    "sg:province":"Schleswig-Holstein",
    "wof:name":"Artur Lenczewski Gmbh",
    "wof:placetype":"venue"
},
  "geometry": {"coordinates":[10.01425,54.044765],"type":"Point"}
}