{
  "type": "Feature",
  "properties": {
    "iso:country":"DE",
    "sg:address":"Silberburgstr. 70 A",
    "sg:city":"Stuttgart",
    "sg:phone":"+49 711/638101",
    "sg:postcode":"70176",
    "sg:province":"Baden-W\u00fcrttemberg",
    "wof:name":"Polysport & Elaku Sportbaustoffe Gmbh",
    "wof:placetype":"venue"
},
  "geometry": {"coordinates":[9.161431,48.780754],"type":"Point"}
}