{
  "type": "Feature",
  "properties": {
    "iso:country":"DE",
    "sg:address":"Frankfurter Str. 3",
    "sg:city":"Borken",
    "sg:phone":"+49 5682/9650",
    "sg:postcode":"34582",
    "sg:province":"Hessen",
    "wof:name":"Neumeier Gmbh",
    "wof:placetype":"venue"
},
  "geometry": {"coordinates":[9.2181549072,51.0637168884],"type":"Point"}
}