{
  "type": "Feature",
  "properties": {
    "iso:country":"DE",
    "sg:address":"Neckartalstr. 25",
    "sg:city":"Ludwigsburg",
    "sg:phone":"+49 7141/25410",
    "sg:postcode":"71642",
    "sg:province":"Baden-W\u00fcrttemberg",
    "wof:name":"Leder-wolf Gmbh",
    "wof:placetype":"venue"
},
  "geometry": {"coordinates":[9.23306,48.907841],"type":"Point"}
}