{
  "type": "Feature",
  "properties": {
    "iso:country":"DE",
    "sg:address":"Uhlandstr. 17",
    "sg:city":"Bonn",
    "sg:phone":"+49 228/830050",
    "sg:postcode":"53173",
    "sg:province":"Nordrhein-Westfalen",
    "wof:name":"Dobelmann & Kroke Gmbh",
    "wof:placetype":"venue"
},
  "geometry": {"coordinates":[7.1622571945,50.6910743713],"type":"Point"}
}