{
  "type": "Feature",
  "properties": {
    "iso:country":"DE",
    "sg:address":"Parkstra\u00dfe 20",
    "sg:city":"Leonberg",
    "sg:phone":"+49 7152/394590",
    "sg:postcode":"71229",
    "sg:province":"Baden-W\u00fcrttemberg",
    "wof:name":"R2d2r2",
    "wof:placetype":"venue"
},
  "geometry": {"coordinates":[9.004379,48.791557],"type":"Point"}
}