{
  "type": "Feature",
  "properties": {
    "iso:country":"DE",
    "sg:address":"Am Heiddiek 21",
    "sg:city":"Cuxhaven",
    "sg:phone":"+49 4721/29844",
    "sg:postcode":"27476",
    "sg:province":"Niedersachsen",
    "wof:name":"Dr. Lutz Nieper Tierarzt",
    "wof:placetype":"venue"
},
  "geometry": {"coordinates":[8.6319103241,53.8630409241],"type":"Point"}
}