{
  "type": "Feature",
  "properties": {
    "iso:country":"DE",
    "sg:address":"Hofer Str. 35",
    "sg:city":"Regensburg",
    "sg:phone":"+49 941/696740",
    "sg:postcode":"93057",
    "sg:province":"Bayern",
    "wof:name":"Gabler Gmbh",
    "wof:placetype":"venue"
},
  "geometry": {"coordinates":[12.1373386383,49.0648727417],"type":"Point"}
}