{
  "type": "Feature",
  "properties": {
    "iso:country":"DE",
    "sg:address":"Herzogstr. 88",
    "sg:city":"M\u00fcnchen",
    "sg:postcode":"80796",
    "sg:province":"Bayern",
    "wof:name":"Naked Eye Filmproduction Verwaltungs Gmbh",
    "wof:placetype":"venue"
},
  "geometry": {"coordinates":[11.5718822479,48.1629447937],"type":"Point"}
}