{
  "type": "Feature",
  "properties": {
    "iso:country":"DE",
    "sg:address":"Niederstadt 27",
    "sg:city":"Waldheim",
    "sg:phone":"+49 34327/93714",
    "sg:postcode":"04736",
    "sg:province":"Sachsen",
    "wof:name":"Spielwaren Hofmann",
    "wof:placetype":"venue"
},
  "geometry": {"coordinates":[13.0282077789,51.0761108398],"type":"Point"}
}