{
  "type": "Feature",
  "properties": {
    "iso:country":"DE",
    "sg:address":"In Den Hofwiesen 13 Kueckelheim",
    "sg:city":"Plettenberg",
    "sg:phone":"+49 4923/918140",
    "sg:postcode":"58840",
    "sg:province":"Nordrhein-Westfalen",
    "wof:name":"Brockhaus S\u00d6hne Gmbh",
    "wof:placetype":"venue"
},
  "geometry": {"coordinates":[7.8731150627,51.2163162231],"type":"Point"}
}