{
  "type": "Feature",
  "properties": {
    "iso:country":"DE",
    "sg:address":"Duisburger Str. 236",
    "sg:city":"Duisburg",
    "sg:phone":"+49 203/547536",
    "sg:postcode":"47166",
    "sg:province":"Nordrhein-Westfalen",
    "wof:name":"Mcdonalds",
    "wof:placetype":"venue"
},
  "geometry": {"coordinates":[6.7696042061,51.496055603],"type":"Point"}
}