{
  "type": "Feature",
  "properties": {
    "iso:country":"DE",
    "sg:address":"Gottfried-Herder-Str. 12",
    "sg:city":"Essen",
    "sg:phone":"+49 2054/3268",
    "sg:postcode":"45219",
    "sg:province":"Nordrhein-Westfalen",
    "wof:name":"H. G. P\u00fchl Ingenieur",
    "wof:placetype":"venue"
},
  "geometry": {"coordinates":[6.9439578056,51.3717765808],"type":"Point"}
}