{
  "type": "Feature",
  "properties": {
    "iso:country":"DE",
    "sg:address":"Im Ermlisgrund 10",
    "sg:city":"Waldbronn",
    "sg:phone":"+49 7243/56900",
    "sg:postcode":"76337",
    "sg:province":"Baden-W\u00fcrttemberg",
    "wof:name":"Siffermann Bautr\u00e4ger Gmbh",
    "wof:placetype":"venue"
},
  "geometry": {"coordinates":[8.479517,48.934429],"type":"Point"}
}