{
  "type": "Feature",
  "properties": {
    "iso:country":"DE",
    "sg:address":"Wiegenstr. 5 a",
    "sg:city":"Neuenrade",
    "sg:phone":"+49 2394/707",
    "sg:postcode":"58809",
    "sg:province":"Nordrhein-Westfalen",
    "wof:name":"Sbs Verklinkerung Brinkmann Gmbh",
    "wof:placetype":"venue"
},
  "geometry": {"coordinates":[7.873328,51.274822],"type":"Point"}
}