{
  "type": "Feature",
  "properties": {
    "iso:country":"DE",
    "sg:address":"G\u00e4rtnerstr. 57",
    "sg:city":"Mannheim",
    "sg:phone":"+49 621/315071",
    "sg:postcode":"68169",
    "sg:province":"Baden-W\u00fcrttemberg",
    "wof:name":"Bernd Beisel",
    "wof:placetype":"venue"
},
  "geometry": {"coordinates":[8.46701,49.502567],"type":"Point"}
}