{
  "type": "Feature",
  "properties": {
    "iso:country":"DE",
    "sg:address":"Uppe H\u00f6chte 67",
    "sg:city":"Bremen",
    "sg:phone":"+49 421/682247",
    "sg:postcode":"28777",
    "sg:province":"Bremen",
    "wof:name":"Inge Czichon",
    "wof:placetype":"venue"
},
  "geometry": {"coordinates":[8.530638,53.200825],"type":"Point"}
}