{
  "type": "Feature",
  "properties": {
    "iso:country":"DE",
    "sg:address":"Karl-Mantel-Str. 59",
    "sg:city":"Krumbach",
    "sg:phone":"+49 8282/89760",
    "sg:postcode":"86381",
    "sg:province":"Bayern",
    "wof:name":"Rampp Und Kling Architekten",
    "wof:placetype":"venue"
},
  "geometry": {"coordinates":[10.366535,48.245232],"type":"Point"}
}