{
  "type": "Feature",
  "properties": {
    "iso:country":"DE",
    "sg:address":"Danziger Str. 40 II",
    "sg:city":"Hamburg",
    "sg:phone":"+49 40/243523",
    "sg:postcode":"20099",
    "sg:province":"Hamburg",
    "wof:name":"Klaus Runge",
    "wof:placetype":"venue"
},
  "geometry": {"coordinates":[10.01559,53.555054],"type":"Point"}
}