{
  "type": "Feature",
  "properties": {
    "iso:country":"DE",
    "sg:address":"Kampstr. 7",
    "sg:city":"Hamminkeln",
    "sg:phone":"+49 2852/96230",
    "sg:postcode":"46499",
    "sg:province":"Nordrhein-Westfalen",
    "wof:name":"Viktor Dobnig Gmbh",
    "wof:placetype":"venue"
},
  "geometry": {"coordinates":[6.6072797775,51.7627372742],"type":"Point"}
}