{
  "type": "Feature",
  "properties": {
    "iso:country":"DE",
    "sg:address":"Bismarckstr. 21",
    "sg:city":"Bad Friedrichshall",
    "sg:phone":"+49 7136/22670",
    "sg:postcode":"74177",
    "sg:province":"Baden-W\u00fcrttemberg",
    "wof:name":"Helmut Schmitt Wach- Und Sicherheits-untern.",
    "wof:placetype":"venue"
},
  "geometry": {"coordinates":[9.2128267288,49.2177581787],"type":"Point"}
}