{
  "type": "Feature",
  "properties": {
    "iso:country":"DE",
    "sg:address":"Lindenstr. 50",
    "sg:city":"Niendorf",
    "sg:phone":"+49 38750/20335",
    "sg:postcode":"19294",
    "sg:province":"Mecklenburg-Vorpommern",
    "wof:name":"Niendorfer Landerzeuger- Gesellschaft Mbh",
    "wof:placetype":"venue"
},
  "geometry": {"coordinates":[11.051751,52.445801],"type":"Point"}
}