{
  "type": "Feature",
  "properties": {
    "iso:country":"DE",
    "sg:address":"Schillerstr. 2",
    "sg:city":"Passau",
    "sg:phone":"+49 851/53884",
    "sg:postcode":"94032",
    "sg:province":"Bayern",
    "wof:name":"China-restaurant Mandarin",
    "wof:placetype":"venue"
},
  "geometry": {"coordinates":[13.4520015717,48.5728874207],"type":"Point"}
}