{
  "type": "Feature",
  "properties": {
    "iso:country":"DE",
    "sg:address":"Klosterstr. 6",
    "sg:city":"Bruttig-Fankel",
    "sg:phone":"+49 2671/915150",
    "sg:postcode":"56814",
    "sg:province":"Rheinland-Pfalz",
    "wof:name":"Edm-tec Ohg",
    "wof:placetype":"venue"
},
  "geometry": {"coordinates":[7.23313,50.133591],"type":"Point"}
}