{
  "type": "Feature",
  "properties": {
    "iso:country":"DE",
    "sg:address":"J\u00e4gerstr. 24",
    "sg:city":"Hamburg",
    "sg:phone":"+49 40/7632140",
    "sg:postcode":"21079",
    "sg:province":"Hamburg",
    "wof:name":"Malereibetrieb Kramm Rudolf Kramm Gmbh",
    "wof:placetype":"venue"
},
  "geometry": {"coordinates":[9.994086,53.443764],"type":"Point"}
}