{
  "type": "Feature",
  "properties": {
    "iso:country":"DE",
    "sg:address":"Webergasse 15",
    "sg:city":"Homberg",
    "sg:phone":"+49 5681/2057",
    "sg:postcode":"34576",
    "sg:province":"Hessen",
    "wof:name":"Hanskurt Thiele Elektroinstallation",
    "wof:placetype":"venue"
},
  "geometry": {"coordinates":[9.407131,51.032589],"type":"Point"}
}