{
  "type": "Feature",
  "properties": {
    "iso:country":"DE",
    "sg:address":"Vorwerk 15",
    "sg:city":"Lassan",
    "sg:phone":"+49 38374/80286",
    "sg:postcode":"17440",
    "sg:province":"Mecklenburg-Vorpommern",
    "wof:name":"L. Bethke",
    "wof:placetype":"venue"
},
  "geometry": {"coordinates":[13.8431682587,53.9518966675],"type":"Point"}
}