{
  "type": "Feature",
  "properties": {
    "iso:country":"DE",
    "sg:address":"Wilhelm-Schaudig-Str. 3",
    "sg:city":"Feuchtwangen",
    "sg:phone":"+49 9852/67620",
    "sg:postcode":"91555",
    "sg:province":"Bayern",
    "wof:name":"Kreisaltenheim Feuchtwangen",
    "wof:placetype":"venue"
},
  "geometry": {"coordinates":[10.328883,49.172779],"type":"Point"}
}