{
  "type": "Feature",
  "properties": {
    "iso:country":"DE",
    "sg:address":"Bahnhofstr. 55",
    "sg:city":"Borken",
    "sg:phone":"+49 5682/1234",
    "sg:postcode":"34582",
    "sg:province":"Hessen",
    "wof:name":"Mike Thomas",
    "wof:placetype":"venue"
},
  "geometry": {"coordinates":[9.28221035,51.0464744568],"type":"Point"}
}