{
  "type": "Feature",
  "properties": {
    "iso:country":"DE",
    "sg:address":"Reisstr. 5",
    "sg:city":"Konstanz",
    "sg:phone":"+49 7531/62666",
    "sg:postcode":"78467",
    "sg:province":"Baden-W\u00fcrttemberg",
    "wof:name":"Lang Photodesign",
    "wof:placetype":"venue"
},
  "geometry": {"coordinates":[9.1549348831,47.6763458252],"type":"Point"}
}