{
  "type": "Feature",
  "properties": {
    "iso:country":"DE",
    "sg:address":"Kirschenweg 8",
    "sg:city":"Salzgitter",
    "sg:phone":"+49 5341/43517",
    "sg:postcode":"38229",
    "sg:province":"Niedersachsen",
    "wof:name":"Maria Meinert Hebamme",
    "wof:placetype":"venue"
},
  "geometry": {"coordinates":[10.382867,52.155018],"type":"Point"}
}