{
  "type": "Feature",
  "properties": {
    "iso:country":"DE",
    "sg:address":"Markelstr. 56",
    "sg:city":"Berlin",
    "sg:postcode":"12163",
    "sg:province":"Berlin",
    "wof:name":"Li-sec Bau Gmbh",
    "wof:placetype":"venue"
},
  "geometry": {"coordinates":[13.324606,52.463985],"type":"Point"}
}