{
  "type": "Feature",
  "properties": {
    "iso:country":"DE",
    "sg:address":"Sch\u00f6ntalstr. 30",
    "sg:city":"Gro\u00dferlach",
    "sg:phone":"+49 7192/909080",
    "sg:postcode":"71577",
    "sg:province":"Baden-W\u00fcrttemberg",
    "wof:name":"J. Sterkel",
    "wof:placetype":"venue"
},
  "geometry": {"coordinates":[9.5751085281,49.0398368835],"type":"Point"}
}