{
  "type": "Feature",
  "properties": {
    "iso:country":"DE",
    "sg:address":"Nesselbergstr. 8",
    "sg:city":"Wuppertal",
    "sg:phone":"+49 202/402277",
    "sg:postcode":"42349",
    "sg:province":"Nordrhein-Westfalen",
    "wof:name":"Lothar Hofmann Kg",
    "wof:placetype":"venue"
},
  "geometry": {"coordinates":[7.1320300102,51.2279090881],"type":"Point"}
}