{
  "type": "Feature",
  "properties": {
    "iso:country":"DE",
    "sg:address":"Rufacher Weg 18",
    "sg:city":"Berlin",
    "sg:phone":"+49 30/6041827",
    "sg:postcode":"12349",
    "sg:province":"Berlin",
    "wof:name":"Hans-w. Preis Ingenieur",
    "wof:placetype":"venue"
},
  "geometry": {"coordinates":[13.4319953918,52.4244918823],"type":"Point"}
}