{
  "type": "Feature",
  "properties": {
    "iso:country":"DE",
    "sg:address":"Rheinstr. 61a",
    "sg:city":"Rheinfelden",
    "sg:phone":"+49 7623/4587",
    "sg:postcode":"79618",
    "sg:province":"Baden-W\u00fcrttemberg",
    "wof:name":"Ralf L\u00e4mmlin Ingenieur",
    "wof:placetype":"venue"
},
  "geometry": {"coordinates":[7.7437701225,47.5509796143],"type":"Point"}
}