{
  "type": "Feature",
  "properties": {
    "iso:country":"DE",
    "sg:address":"Gartenstr. 29",
    "sg:city":"Gardelegen",
    "sg:phone":"+49 3907/711131",
    "sg:postcode":"39638",
    "sg:province":"Sachsen-Anhalt",
    "wof:name":"Fehse Und Nowak Steuerberater",
    "wof:placetype":"venue"
},
  "geometry": {"coordinates":[11.4036178589,52.5221061707],"type":"Point"}
}