{
  "type": "Feature",
  "properties": {
    "iso:country":"DE",
    "sg:address":"F\u00e4hrstr. 6",
    "sg:city":"Bremerhaven",
    "sg:phone":"+49 471/411415",
    "sg:postcode":"27568",
    "sg:province":"Bremen",
    "wof:name":"Blinkturm",
    "wof:placetype":"venue"
},
  "geometry": {"coordinates":[8.5831823349,53.5411529541],"type":"Point"}
}