{
  "type": "Feature",
  "properties": {
    "iso:country":"DE",
    "sg:address":"Rappstr. 2::",
    "sg:city":"Hamburg",
    "sg:phone":"+49 40/4103151",
    "sg:postcode":"20146",
    "sg:province":"Hamburg",
    "wof:name":"Philippine Trade Uinvestment Ctr",
    "wof:placetype":"venue"
},
  "geometry": {"coordinates":[9.980577,53.570248],"type":"Point"}
}