{
  "type": "Feature",
  "properties": {
    "iso:country":"DE",
    "sg:address":"Engelstr. 17",
    "sg:city":"Erlangen",
    "sg:phone":"+49 9131/24967",
    "sg:postcode":"91054",
    "sg:province":"Bayern",
    "wof:name":"Trautners American Bar",
    "wof:placetype":"venue"
},
  "geometry": {"coordinates":[11.003314,49.600349],"type":"Point"}
}