{
  "type": "Feature",
  "properties": {
    "iso:country":"DE",
    "sg:address":"Georg-Schumann-Str. 50",
    "sg:city":"Leipzig",
    "sg:phone":"+49 341/5648237",
    "sg:postcode":"04155",
    "sg:province":"Sachsen",
    "wof:name":"Art Und Design K\u00fcchen",
    "wof:placetype":"venue"
},
  "geometry": {"coordinates":[12.3704090118,51.3615837097],"type":"Point"}
}