{
  "type": "Feature",
  "properties": {
    "iso:country":"DE",
    "sg:address":"M\u00fcdener Weg 21",
    "sg:city":"Fa\u00dfberg",
    "sg:postcode":"29328",
    "sg:province":"Niedersachsen",
    "wof:name":"Aldi Gmbh & Co. Kg",
    "wof:placetype":"venue"
},
  "geometry": {"coordinates":[10.1583652496,52.8943367004],"type":"Point"}
}