{
  "type": "Feature",
  "properties": {
    "iso:country":"DE",
    "sg:address":"Triftstr. 2",
    "sg:city":"\u00dcckeritz",
    "sg:phone":"+49 38375/20939",
    "sg:postcode":"17459",
    "sg:province":"Mecklenburg-Vorpommern",
    "wof:name":"E. Pantermehl",
    "wof:placetype":"venue"
},
  "geometry": {"coordinates":[14.050354,54.011833],"type":"Point"}
}