{
  "type": "Feature",
  "properties": {
    "iso:country":"DE",
    "sg:address":"Ludwigkirchstr. 10a",
    "sg:city":"Berlin",
    "sg:postcode":"10719",
    "sg:province":"Berlin",
    "wof:name":"Liegenschaftsgesellschaft S. G. Mbh",
    "wof:placetype":"venue"
},
  "geometry": {"coordinates":[13.3249254227,52.4978485107],"type":"Point"}
}