{
  "type": "Feature",
  "properties": {
    "iso:country":"DE",
    "sg:address":"Karlsbader Str. 21",
    "sg:city":"Schneeberg",
    "sg:phone":"+49 3772/20771",
    "sg:postcode":"08289",
    "sg:province":"Sachsen",
    "wof:name":"Kindermann & Partner",
    "wof:placetype":"venue"
},
  "geometry": {"coordinates":[12.6358709335,50.5857048035],"type":"Point"}
}