{
  "type": "Feature",
  "properties": {
    "iso:country":"DE",
    "sg:address":"Hoher Wallgraben 45",
    "sg:city":"Berlin",
    "sg:phone":"+49 30/5099847",
    "sg:postcode":"10318",
    "sg:province":"Berlin",
    "wof:name":"Giesela B\u00f6bel Patentanw\u00e4ltin",
    "wof:placetype":"venue"
},
  "geometry": {"coordinates":[13.5168933868,52.4763450623],"type":"Point"}
}