{
  "type": "Feature",
  "properties": {
    "iso:country":"DE",
    "sg:address":"Werkring 5",
    "sg:city":"Berlin",
    "sg:phone":"+49 30/82710020",
    "sg:postcode":"13597",
    "sg:province":"Berlin",
    "wof:name":"Gfa Gmbh",
    "wof:placetype":"venue"
},
  "geometry": {"coordinates":[13.236775,52.531174],"type":"Point"}
}