{
  "type": "Feature",
  "properties": {
    "iso:country":"DE",
    "sg:address":"Schillingsrotter Str. 27",
    "sg:city":"K\u00f6ln",
    "sg:phone":"+49 221/391985",
    "sg:postcode":"50996",
    "sg:province":"Nordrhein-Westfalen",
    "wof:name":"Echanges Marktforschung Gmbh",
    "wof:placetype":"venue"
},
  "geometry": {"coordinates":[6.9897928238,50.8820915222],"type":"Point"}
}