{
  "type": "Feature",
  "properties": {
    "iso:country":"DE",
    "sg:address":"K\u00e4figgasse 4",
    "sg:city":"Alzey",
    "sg:phone":"+49 6731/7933",
    "sg:postcode":"55232",
    "sg:province":"Rheinland-Pfalz",
    "wof:name":"Bauernsch\u00e4nke",
    "wof:placetype":"venue"
},
  "geometry": {"coordinates":[8.1143045425,49.7443580627],"type":"Point"}
}