{
  "type": "Feature",
  "properties": {
    "iso:country":"DE",
    "sg:address":"Eichenweg 27",
    "sg:city":"Hamberge",
    "sg:phone":"+49 451/892832",
    "sg:postcode":"23619",
    "sg:province":"Schleswig-Holstein",
    "wof:name":"E. Oymanns",
    "wof:placetype":"venue"
},
  "geometry": {"coordinates":[10.5839090347,53.8396835327],"type":"Point"}
}