{
  "type": "Feature",
  "properties": {
    "iso:country":"DE",
    "sg:address":"Markt 8",
    "sg:city":"Emsb\u00fcren",
    "sg:phone":"+49 5903/205",
    "sg:postcode":"48488",
    "sg:province":"Niedersachsen",
    "wof:name":"B. Fangmeyer",
    "wof:placetype":"venue"
},
  "geometry": {"coordinates":[7.293965,52.391891],"type":"Point"}
}