{
  "type": "Feature",
  "properties": {
    "iso:country":"DE",
    "sg:address":"Rosseeweg 7",
    "sg:city":"Neustadt",
    "sg:phone":"+49 5072/1519",
    "sg:postcode":"31535",
    "sg:province":"Niedersachsen",
    "wof:name":"I. Skaletz Immobilienmakler",
    "wof:placetype":"venue"
},
  "geometry": {"coordinates":[9.5768127441,52.6070747375],"type":"Point"}
}