{
  "type": "Feature",
  "properties": {
    "iso:country":"DE",
    "sg:address":"Talstr. 47 a",
    "sg:city":"Berghaupten",
    "sg:phone":"+49 7803/5845",
    "sg:postcode":"77791",
    "sg:province":"Baden-W\u00fcrttemberg",
    "wof:name":"Reinhard Benz",
    "wof:placetype":"venue"
},
  "geometry": {"coordinates":[7.980713,48.399902],"type":"Point"}
}