{
  "type": "Feature",
  "properties": {
    "iso:country":"DE",
    "sg:address":"Stuhlbergerstr. 28",
    "sg:city":"Pocking",
    "sg:postcode":"94060",
    "sg:province":"Bayern",
    "wof:name":"Sch\u00fcler Verwaltungs Gmbh",
    "wof:placetype":"venue"
},
  "geometry": {"coordinates":[13.3226985931,48.4056510925],"type":"Point"}
}