{
  "type": "Feature",
  "properties": {
    "iso:country":"DE",
    "sg:address":"Industriestr. 7",
    "sg:city":"Ascha",
    "sg:phone":"+49 9961/295",
    "sg:postcode":"94347",
    "sg:province":"Bayern",
    "wof:name":"Gebr. Purr Verkehrsleiteinrichtungs Gmbh",
    "wof:placetype":"venue"
},
  "geometry": {"coordinates":[12.636986,49.000191],"type":"Point"}
}