{
  "type": "Feature",
  "properties": {
    "iso:country":"DE",
    "sg:address":"Rhinstr. 123",
    "sg:city":"Berlin",
    "sg:phone":"+49 30/5499510",
    "sg:postcode":"10315",
    "sg:province":"Berlin",
    "wof:name":"Pfi Planungsb. Freier Ing.- Kommunik.-u.computertech.gmbh",
    "wof:placetype":"venue"
},
  "geometry": {"coordinates":[13.517378,52.529377],"type":"Point"}
}