{
  "type": "Feature",
  "properties": {
    "iso:country":"DE",
    "sg:address":"NEUER MARKT 09",
    "sg:city":"EMDEN",
    "sg:phone":"+49 4921/979540",
    "sg:postcode":"26721",
    "sg:province":"Niedersachsen",
    "wof:name":"Compuna Gbr",
    "wof:placetype":"venue"
},
  "geometry": {"coordinates":[7.2034988403,53.3677253723],"type":"Point"}
}