{
  "type": "Feature",
  "properties": {
    "iso:country":"DE",
    "sg:address":"Schillerstr. 3",
    "sg:city":"Herford",
    "sg:phone":"+49 5221/16680",
    "sg:postcode":"32052",
    "sg:province":"Nordrhein-Westfalen",
    "wof:name":"Wollny Wunram-l\u00f6we Und Meyer Zu Bexten",
    "wof:placetype":"venue"
},
  "geometry": {"coordinates":[8.668964386,52.1192893982],"type":"Point"}
}