{
  "type": "Feature",
  "properties": {
    "iso:country":"DE",
    "sg:address":"Saarstr. 131",
    "sg:city":"Hoppst\u00e4dten-Weiersbach",
    "sg:phone":"+49 6782/2387",
    "sg:postcode":"55768",
    "sg:province":"Rheinland-Pfalz",
    "wof:name":"Heribert Decker",
    "wof:placetype":"venue"
},
  "geometry": {"coordinates":[7.1917619705,49.6149024963],"type":"Point"}
}