{
  "type": "Feature",
  "properties": {
    "iso:country":"DE",
    "sg:address":"K\u00f6nigstr. 34",
    "sg:city":"Stuttgart",
    "sg:phone":"+49 711/2255393",
    "sg:postcode":"70173",
    "sg:province":"Baden-W\u00fcrttemberg",
    "wof:name":"Steffen Gassmann Rechtsanwalt",
    "wof:placetype":"venue"
},
  "geometry": {"coordinates":[9.1772098541,48.77759552],"type":"Point"}
}