{
  "type": "Feature",
  "properties": {
    "iso:country":"DE",
    "sg:address":"Bismarckstr. 25",
    "sg:city":"Bad Sassendorf",
    "sg:phone":"+49 2921/96160",
    "sg:postcode":"59505",
    "sg:province":"Nordrhein-Westfalen",
    "wof:name":"G\u00e4stehaus Brinks",
    "wof:placetype":"venue"
},
  "geometry": {"coordinates":[8.1662683487,51.5888328552],"type":"Point"}
}