{
  "type": "Feature",
  "properties": {
    "iso:country":"DE",
    "sg:address":"Glockenturmstr. 23-25",
    "sg:city":"Berlin",
    "sg:phone":"+49 30/34306878",
    "sg:postcode":"14055",
    "sg:province":"Berlin",
    "wof:name":"Kindertagesst\u00e4tte",
    "wof:placetype":"venue"
},
  "geometry": {"coordinates":[13.2231359482,52.5117149353],"type":"Point"}
}