{
  "type": "Feature",
  "properties": {
    "iso:country":"DE",
    "sg:address":"Harburger Str. 185",
    "sg:city":"Stade",
    "sg:postcode":"21680",
    "sg:province":"Niedersachsen",
    "wof:name":"H & P Stadtzentrum Zeven Verm\u00f6gensverwaltungs-",
    "wof:placetype":"venue"
},
  "geometry": {"coordinates":[9.4994525909,53.5831489563],"type":"Point"}
}