{
  "type": "Feature",
  "properties": {
    "iso:country":"DE",
    "sg:address":"Archenholdstr. 19-21",
    "sg:city":"Berlin",
    "sg:phone":"+49 30/5252100",
    "sg:postcode":"10315",
    "sg:province":"Berlin",
    "wof:name":"Feuerst\u00e4tten Berlin-lichtenberg Gmbh",
    "wof:placetype":"venue"
},
  "geometry": {"coordinates":[13.504117012,52.5076560974],"type":"Point"}
}