{
  "type": "Feature",
  "properties": {
    "iso:country":"DE",
    "sg:address":"Gebind 03",
    "sg:city":"W\u00fcnschendorf",
    "sg:phone":"+49 36603/88220",
    "sg:postcode":"07570",
    "sg:province":"Th\u00fcringen",
    "wof:name":"Hubert Fleischmann",
    "wof:placetype":"venue"
},
  "geometry": {"coordinates":[12.093245,50.794941],"type":"Point"}
}