{
  "type": "Feature",
  "properties": {
    "iso:country":"DE",
    "sg:address":"Schlehdornstr. 2",
    "sg:city":"Gr\u00fcnwald",
    "sg:postcode":"82031",
    "sg:province":"Bayern",
    "wof:name":"Hollystars Gmbh",
    "wof:placetype":"venue"
},
  "geometry": {"coordinates":[11.5333108902,48.0449562073],"type":"Point"}
}