{
  "type": "Feature",
  "properties": {
    "iso:country":"DE",
    "sg:address":"H\u00f6herweg 301",
    "sg:city":"D\u00fcsseldorf",
    "sg:phone":"+49 211/7333030",
    "sg:postcode":"40231",
    "sg:province":"Nordrhein-Westfalen",
    "wof:name":"Hans Schmitt Gmbh",
    "wof:placetype":"venue"
},
  "geometry": {"coordinates":[6.832165,51.220787],"type":"Point"}
}