{
  "type": "Feature",
  "properties": {
    "iso:country":"DE",
    "sg:address":"Oberer Markt 24",
    "sg:city":"Eging",
    "sg:phone":"+49 8544/8441",
    "sg:postcode":"94535",
    "sg:province":"Bayern",
    "wof:name":"F. Berger",
    "wof:placetype":"venue"
},
  "geometry": {"coordinates":[13.267103,48.7127],"type":"Point"}
}