{
  "type": "Feature",
  "properties": {
    "iso:country":"DE",
    "sg:address":"Zum Eisenhammer 1b",
    "sg:city":"Oberhausen",
    "sg:phone":"+49 4920/8857766",
    "sg:postcode":"46049",
    "sg:province":"Nordrhein-Westfalen",
    "wof:name":"Technik-rat & Hilfe Gmbh",
    "wof:placetype":"venue"
},
  "geometry": {"coordinates":[6.843877,51.48254],"type":"Point"}
}