{
  "type": "Feature",
  "properties": {
    "iso:country":"DE",
    "sg:address":"Gartenstr. 8",
    "sg:city":"Sch\u00f6ningen",
    "sg:phone":"+49 5352/2723",
    "sg:postcode":"38364",
    "sg:province":"Niedersachsen",
    "wof:name":"Ev. Pfarrei Twieflingen",
    "wof:placetype":"venue"
},
  "geometry": {"coordinates":[10.9464006424,52.1288337708],"type":"Point"}
}