{
  "type": "Feature",
  "properties": {
    "iso:country":"DE",
    "sg:address":"Kaiserstra\u00dfe 39",
    "sg:city":"Frankfurt/Main",
    "sg:phone":"+49 69",
    "sg:postcode":"60329",
    "sg:province":"Hessen",
    "wof:name":"Rm - Busreisen Rudolf Maier",
    "wof:placetype":"venue"
},
  "geometry": {"coordinates":[8.670884,50.108898],"type":"Point"}
}