{
  "type": "Feature",
  "properties": {
    "iso:country":"DE",
    "sg:address":"Taunusstr. 12",
    "sg:city":"Bruchk\u00f6bel",
    "sg:phone":"+49 6181/76749",
    "sg:postcode":"63486",
    "sg:province":"Hessen",
    "wof:name":"Maison Lanz Weinhandels Gmbh",
    "wof:placetype":"venue"
},
  "geometry": {"coordinates":[8.9304742813,50.195186615],"type":"Point"}
}