{
  "type": "Feature",
  "properties": {
    "iso:country":"DE",
    "sg:address":"Bellmannstr. 20",
    "sg:city":"Hamburg",
    "sg:postcode":"22607",
    "sg:province":"Hamburg",
    "wof:name":"Jens Mumme Gmbh",
    "wof:placetype":"venue"
},
  "geometry": {"coordinates":[9.882633,53.560612],"type":"Point"}
}