{
  "type": "Feature",
  "properties": {
    "iso:country":"DE",
    "sg:address":"Rastdorfer Str.",
    "sg:city":"Werlte",
    "sg:phone":"+49 5951/833",
    "sg:postcode":"49757",
    "sg:province":"Niedersachsen",
    "wof:name":"Wasserbeschaffungsverband H\u00fcmmling",
    "wof:placetype":"venue"
},
  "geometry": {"coordinates":[7.6850199699,52.860458374],"type":"Point"}
}