{
  "type": "Feature",
  "properties": {
    "iso:country":"DE",
    "sg:address":"Neustr. 19",
    "sg:city":"Bad H\u00f6nningen",
    "sg:phone":"+49 2635/2450",
    "sg:postcode":"53557",
    "sg:province":"Rheinland-Pfalz",
    "wof:name":"G\u00fcnther Thiermann",
    "wof:placetype":"venue"
},
  "geometry": {"coordinates":[7.308275,50.515305],"type":"Point"}
}