{
  "type": "Feature",
  "properties": {
    "iso:country":"DE",
    "sg:address":"Wiesbadener Str. 9",
    "sg:city":"Emden",
    "sg:phone":"+49 4921/42870",
    "sg:postcode":"26721",
    "sg:province":"Niedersachsen",
    "wof:name":"Helmut Ebel Ingenieur",
    "wof:placetype":"venue"
},
  "geometry": {"coordinates":[7.1996188164,53.3806991577],"type":"Point"}
}