{
  "type": "Feature",
  "properties": {
    "iso:country":"DE",
    "sg:address":"Vor dem Kaiserdom 1",
    "sg:city":"K\u00f6nigslutter",
    "sg:phone":"+49 5353/2247",
    "sg:postcode":"38154",
    "sg:province":"Niedersachsen",
    "wof:name":"Ev. Pfarramt K\u00f6nigslutter",
    "wof:placetype":"venue"
},
  "geometry": {"coordinates":[10.8162384033,52.2452392578],"type":"Point"}
}