{
  "type": "Feature",
  "properties": {
    "iso:country":"DE",
    "sg:address":"Schulstr. 4",
    "sg:city":"Walsheim",
    "sg:phone":"+49 6341/61560",
    "sg:postcode":"76833",
    "sg:province":"Rheinland-Pfalz",
    "wof:name":"Karl Vogt",
    "wof:placetype":"venue"
},
  "geometry": {"coordinates":[8.1261224747,49.2370414734],"type":"Point"}
}