{
  "type": "Feature",
  "properties": {
    "iso:country":"DE",
    "sg:address":"Dr.-Max-Hofmann-Str. 3",
    "sg:city":"Kolbermoor",
    "sg:phone":"+49 8031/29350",
    "sg:postcode":"83059",
    "sg:province":"Bayern",
    "wof:name":"Schrempf & Lahm",
    "wof:placetype":"venue"
},
  "geometry": {"coordinates":[12.063949,47.845253],"type":"Point"}
}