{
  "type": "Feature",
  "properties": {
    "iso:country":"DE",
    "sg:address":"Neutorstr. 135-137",
    "sg:city":"Emden",
    "sg:phone":"+49 4921/24288",
    "sg:postcode":"26721",
    "sg:province":"Niedersachsen",
    "wof:name":"Heinrich Kleefmann Grabdenkm\u00e4ler",
    "wof:placetype":"venue"
},
  "geometry": {"coordinates":[7.2065601349,53.3728218079],"type":"Point"}
}