{
  "type": "Feature",
  "properties": {
    "iso:country":"DE",
    "sg:address":"Mensteder Weg 2",
    "sg:city":"Gro\u00dfheide",
    "sg:phone":"+49 4936/1774",
    "sg:postcode":"26532",
    "sg:province":"Niedersachsen",
    "wof:name":"R. Rosenboom",
    "wof:placetype":"venue"
},
  "geometry": {"coordinates":[7.392677784,53.6074371338],"type":"Point"}
}