{
  "type": "Feature",
  "properties": {
    "iso:country":"DE",
    "sg:address":"Am Weiher 8",
    "sg:city":"Langenselbold",
    "sg:postcode":"63505",
    "sg:province":"Hessen",
    "wof:name":"Cado Logistic Gmbh",
    "wof:placetype":"venue"
},
  "geometry": {"coordinates":[9.0533800125,50.1610107422],"type":"Point"}
}