{
  "type": "Feature",
  "properties": {
    "iso:country":"DE",
    "sg:address":"Fabrikstr. 1",
    "sg:city":"Gro\u00df Rosenburg",
    "sg:phone":"+49 39294/20351",
    "sg:postcode":"39240",
    "sg:province":"Sachsen-Anhalt",
    "wof:name":"Helmut Knauth",
    "wof:placetype":"venue"
},
  "geometry": {"coordinates":[11.895654,51.91608],"type":"Point"}
}