{
  "type": "Feature",
  "properties": {
    "iso:country":"DE",
    "sg:address":"D\u00f6rnbergstr. 38",
    "sg:city":"Fuldatal",
    "sg:phone":"+49 561/814526",
    "sg:postcode":"34233",
    "sg:province":"Hessen",
    "wof:name":"Evers Fahrzeugdesign",
    "wof:placetype":"venue"
},
  "geometry": {"coordinates":[9.513929,51.349903],"type":"Point"}
}