{
  "type": "Feature",
  "properties": {
    "iso:country":"DE",
    "sg:address":"M\u00fclheimer Str. 128",
    "sg:city":"Oberhausen",
    "sg:phone":"+49 208/874345",
    "sg:postcode":"46045",
    "sg:province":"Nordrhein-Westfalen",
    "wof:name":"B. Salowski",
    "wof:placetype":"venue"
},
  "geometry": {"coordinates":[6.8639822006,51.4743309021],"type":"Point"}
}