{
  "type": "Feature",
  "properties": {
    "iso:country":"DE",
    "sg:address":"Brunnenstr. 5",
    "sg:city":"Riesb\u00fcrg",
    "sg:phone":"+49 9081/3476",
    "sg:postcode":"73469",
    "sg:province":"Baden-W\u00fcrttemberg",
    "wof:name":"Adler",
    "wof:placetype":"venue"
},
  "geometry": {"coordinates":[10.4392547607,48.8296432495],"type":"Point"}
}