{
  "type": "Feature",
  "properties": {
    "iso:country":"DE",
    "sg:address":"Pfauenstr. 8",
    "sg:city":"Riedlingen",
    "sg:phone":"+49 7371/2674",
    "sg:postcode":"88499",
    "sg:province":"Baden-W\u00fcrttemberg",
    "wof:name":"Pizzeria",
    "wof:placetype":"venue"
},
  "geometry": {"coordinates":[9.4752750397,48.1541938782],"type":"Point"}
}