{
  "type": "Feature",
  "properties": {
    "iso:country":"DE",
    "sg:address":"R\u00e4bke",
    "sg:city":"R\u00e4bke",
    "sg:phone":"+49 5355/368",
    "sg:postcode":"38375",
    "sg:province":"Niedersachsen",
    "wof:name":"Genossenschaftsbank Eg",
    "wof:placetype":"venue"
},
  "geometry": {"coordinates":[10.8614,52.196758],"type":"Point"}
}