{
  "type": "Feature",
  "properties": {
    "iso:country":"DE",
    "sg:address":"Rotenberger Str. 43",
    "sg:city":"Rauenberg",
    "sg:phone":"+49 6222/62430",
    "sg:postcode":"69231",
    "sg:province":"Baden-W\u00fcrttemberg",
    "wof:name":"J. Huber",
    "wof:placetype":"venue"
},
  "geometry": {"coordinates":[8.7068300247,49.263923645],"type":"Point"}
}