{
  "type": "Feature",
  "properties": {
    "iso:country":"DE",
    "sg:address":"Bierstr. 2",
    "sg:city":"Osnabr\u00fcck",
    "sg:phone":"+49 541/25251",
    "sg:postcode":"49074",
    "sg:province":"Niedersachsen",
    "wof:name":"Pizzeria Bei Tano",
    "wof:placetype":"venue"
},
  "geometry": {"coordinates":[8.0388898849,52.2787246704],"type":"Point"}
}