{
  "type": "Feature",
  "properties": {
    "iso:country":"DE",
    "sg:address":"Hauptstr. 17 a",
    "sg:city":"Anger",
    "sg:phone":"+49 8656/1472",
    "sg:postcode":"83454",
    "sg:province":"Bayern",
    "wof:name":"Johann Unterreiner",
    "wof:placetype":"venue"
},
  "geometry": {"coordinates":[12.87189,47.790501],"type":"Point"}
}