{
  "type": "Feature",
  "properties": {
    "iso:country":"DE",
    "sg:address":"Torweg 8",
    "sg:city":"Partenstein",
    "sg:phone":"+49 9355/589",
    "sg:postcode":"97846",
    "sg:province":"Bayern",
    "wof:name":"Erhard Mehrlich",
    "wof:placetype":"venue"
},
  "geometry": {"coordinates":[9.5197992325,50.0418815613],"type":"Point"}
}