{
  "type": "Feature",
  "properties": {
    "iso:country":"DE",
    "sg:address":"Ringstr.",
    "sg:city":"Marnitz",
    "sg:postcode":"19376",
    "sg:province":"Mecklenburg-Vorpommern",
    "wof:name":"Ev.-lutherische Kirche",
    "wof:placetype":"venue"
},
  "geometry": {"coordinates":[11.9316596985,53.3165245056],"type":"Point"}
}