{
  "type": "Feature",
  "properties": {
    "iso:country":"DE",
    "sg:address":"Karl-Lindner-Str. 3",
    "sg:city":"Friedberg",
    "sg:phone":"+49 821/601881",
    "sg:postcode":"86316",
    "sg:province":"Bayern",
    "wof:name":"Josef Fendt",
    "wof:placetype":"venue"
},
  "geometry": {"coordinates":[10.982045,48.349514],"type":"Point"}
}