{
  "type": "Feature",
  "properties": {
    "iso:country":"DE",
    "sg:address":"Berliner Str. 11",
    "sg:city":"Salzgitter",
    "sg:phone":"+49 5341/84810",
    "sg:postcode":"38226",
    "sg:province":"Niedersachsen",
    "wof:name":"Gerlind Und Ottokar Meyer Rechtsanw\u00e4lte Und Notarin",
    "wof:placetype":"venue"
},
  "geometry": {"coordinates":[10.3329820633,52.153503418],"type":"Point"}
}