{
  "type": "Feature",
  "properties": {
    "iso:country":"DE",
    "sg:address":"Kaiserstr. 2 A",
    "sg:city":"Heidelberg",
    "sg:phone":"+49 6221/600002",
    "sg:postcode":"69115",
    "sg:province":"Baden-W\u00fcrttemberg",
    "wof:name":"Dr. W. Berner",
    "wof:placetype":"venue"
},
  "geometry": {"coordinates":[8.6914758682,49.4032745361],"type":"Point"}
}