{
  "type": "Feature",
  "properties": {
    "iso:country":"DE",
    "sg:address":"Ringstr. 38",
    "sg:city":"Langenau",
    "sg:postcode":"89129",
    "sg:province":"Baden-W\u00fcrttemberg",
    "wof:name":"Ralf Kirsten",
    "wof:placetype":"venue"
},
  "geometry": {"coordinates":[10.0621166229,48.4859275818],"type":"Point"}
}