{
  "type": "Feature",
  "properties": {
    "iso:country":"DE",
    "sg:address":"Klosterstr. 6",
    "sg:city":"Eurasburg",
    "sg:phone":"+49 8179/398",
    "sg:postcode":"82547",
    "sg:province":"Bayern",
    "wof:name":"Kath. Pfarramt St. Peter Und Paul",
    "wof:placetype":"venue"
},
  "geometry": {"coordinates":[11.4114208221,47.8289375305],"type":"Point"}
}