{
  "type": "Feature",
  "properties": {
    "iso:country":"DE",
    "sg:address":"Salzburger Str. 70",
    "sg:city":"Stephanskirchen",
    "sg:phone":"+49 8031/276250",
    "sg:postcode":"83071",
    "sg:province":"Bayern",
    "wof:name":"Dr. Griehl Drescher & Partner Anwalts- Und",
    "wof:placetype":"venue"
},
  "geometry": {"coordinates":[12.1557893753,47.8606071472],"type":"Point"}
}