{
  "type": "Feature",
  "properties": {
    "iso:country":"DE",
    "sg:address":"Bahnhofstr. 26",
    "sg:city":"Lorsch",
    "sg:phone":"+49 4962/515015",
    "sg:postcode":"64653",
    "sg:province":"Hessen",
    "wof:name":"Bohrer Gmbh & Co.",
    "wof:placetype":"venue"
},
  "geometry": {"coordinates":[8.5677127838,49.6561012268],"type":"Point"}
}