{
  "type": "Feature",
  "properties": {
    "iso:country":"DE",
    "sg:address":"Zwieselbergsiedlung 40",
    "sg:city":"Zwiesel",
    "sg:postcode":"94227",
    "sg:province":"Bayern",
    "wof:name":"Karl Ernst Bayerwald-graniterzeugnisse",
    "wof:placetype":"venue"
},
  "geometry": {"coordinates":[13.2199964523,49.0042304993],"type":"Point"}
}