{
  "type": "Feature",
  "properties": {
    "iso:country":"DE",
    "sg:address":"Bundesallee 212",
    "sg:city":"Berlin",
    "sg:postcode":"10719",
    "sg:province":"Berlin",
    "wof:name":"Wow World Of Wellness Gmbh",
    "wof:placetype":"venue"
},
  "geometry": {"coordinates":[13.3310661316,52.4968032837],"type":"Point"}
}