{
  "type": "Feature",
  "properties": {
    "iso:country":"DE",
    "sg:address":"Uhlandstr. 50",
    "sg:city":"M\u00f6nchengladbach",
    "sg:phone":"+49 2166/850332",
    "sg:postcode":"41238",
    "sg:province":"Nordrhein-Westfalen",
    "wof:name":"Marcus M\u00fcschen",
    "wof:placetype":"venue"
},
  "geometry": {"coordinates":[6.4842982292,51.1541671753],"type":"Point"}
}