{
  "type": "Feature",
  "properties": {
    "iso:country":"DE",
    "sg:address":"Bebelstr. 58",
    "sg:city":"Stuttgart",
    "sg:phone":"+49 711/632806",
    "sg:postcode":"70193",
    "sg:province":"Baden-W\u00fcrttemberg",
    "wof:name":"Adolf Hofgesang",
    "wof:placetype":"venue"
},
  "geometry": {"coordinates":[9.1496610641,48.7749977112],"type":"Point"}
}