{
  "type": "Feature",
  "properties": {
    "iso:country":"DE",
    "sg:address":"Harburger Str. 2",
    "sg:city":"Schee\u00dfel",
    "sg:postcode":"27383",
    "sg:province":"Niedersachsen",
    "wof:name":"Beeke-apotheke Hans-erik Meyer E. K.",
    "wof:placetype":"venue"
},
  "geometry": {"coordinates":[9.486346,53.169067],"type":"Point"}
}