{
  "type": "Feature",
  "properties": {
    "iso:country":"DE",
    "sg:address":"Sanderstr. 142",
    "sg:city":"Wuppertal",
    "sg:phone":"+49 202/83515",
    "sg:postcode":"42283",
    "sg:province":"Nordrhein-Westfalen",
    "wof:name":"Wuppertaler Bau- Und Sparverein Eg",
    "wof:placetype":"venue"
},
  "geometry": {"coordinates":[7.1693181992,51.2727355957],"type":"Point"}
}