{
  "type": "Feature",
  "properties": {
    "iso:country":"DE",
    "sg:address":"Im Kr\u00fcmpel 11",
    "sg:city":"Bielefeld",
    "sg:phone":"+49 521/100454",
    "sg:postcode":"33619",
    "sg:province":"Nordrhein-Westfalen",
    "wof:name":"Heinz Westerheide",
    "wof:placetype":"venue"
},
  "geometry": {"coordinates":[8.476618,52.059399],"type":"Point"}
}