{
  "type": "Feature",
  "properties": {
    "iso:country":"DE",
    "sg:address":"Hauptstr. 74",
    "sg:city":"Wehr",
    "sg:phone":"+49 2636/7455",
    "sg:postcode":"56653",
    "sg:province":"Rheinland-Pfalz",
    "wof:name":"B\u00e4ckerei Genn Gmbh",
    "wof:placetype":"venue"
},
  "geometry": {"coordinates":[7.212219,50.421474],"type":"Point"}
}