{
  "type": "Feature",
  "properties": {
    "iso:country":"DE",
    "sg:address":"Recker Str. 2",
    "sg:city":"Mettingen",
    "sg:phone":"+49 5452/2330",
    "sg:postcode":"49497",
    "sg:province":"Nordrhein-Westfalen",
    "wof:name":"Hermann Agternkamp",
    "wof:placetype":"venue"
},
  "geometry": {"coordinates":[7.778084,52.318863],"type":"Point"}
}