{
  "type": "Feature",
  "properties": {
    "iso:country":"DE",
    "sg:address":"Heusteigstr. 54",
    "sg:city":"Stuttgart",
    "sg:postcode":"70180",
    "sg:province":"Baden-W\u00fcrttemberg",
    "wof:name":"Pompa D Aria 1994 E. V.",
    "wof:placetype":"venue"
},
  "geometry": {"coordinates":[9.1768980026,48.7689743042],"type":"Point"}
}