{
  "type": "Feature",
  "properties": {
    "iso:country":"DE",
    "sg:address":"R\u00f6merstr. 2",
    "sg:city":"W\u00f6lfersheim",
    "sg:phone":"+49 6036/5077",
    "sg:postcode":"61200",
    "sg:province":"Hessen",
    "wof:name":"I. Ulrich",
    "wof:placetype":"venue"
},
  "geometry": {"coordinates":[8.7935,50.39875],"type":"Point"}
}