{
  "type": "Feature",
  "properties": {
    "iso:country":"DE",
    "sg:address":"Von-der-Heydt-Str. 6",
    "sg:city":"P\u00fcttlingen",
    "sg:phone":"+49 6898/689779",
    "sg:postcode":"66346",
    "sg:province":"Saarland",
    "wof:name":"Kirsch Gmbh",
    "wof:placetype":"venue"
},
  "geometry": {"coordinates":[6.9148421288,49.2809944153],"type":"Point"}
}