{
  "type": "Feature",
  "properties": {
    "iso:country":"DE",
    "sg:address":"Amberger Str. 39",
    "sg:city":"Altdorf",
    "sg:phone":"+49 9187/902753",
    "sg:postcode":"90518",
    "sg:province":"Bayern",
    "wof:name":"Erologika Computer Gmbh",
    "wof:placetype":"venue"
},
  "geometry": {"coordinates":[11.3711824417,49.3826446533],"type":"Point"}
}