{
  "type": "Feature",
  "properties": {
    "iso:country":"DE",
    "sg:address":"Hauptstr. 128",
    "sg:city":"Glowe",
    "sg:postcode":"18551",
    "sg:province":"Mecklenburg-Vorpommern",
    "wof:name":"W\u00fcstenberg Immobilien Gmbh",
    "wof:placetype":"venue"
},
  "geometry": {"coordinates":[13.4579696655,54.5687789917],"type":"Point"}
}