{
  "type": "Feature",
  "properties": {
    "iso:country":"DE",
    "sg:address":"Markenbildchenweg 15",
    "sg:city":"Koblenz",
    "sg:phone":"+49 261/15096",
    "sg:postcode":"56068",
    "sg:province":"Rheinland-Pfalz",
    "wof:name":"Mieterbund Neuwied-koblenz Und Umgebung E. V.",
    "wof:placetype":"venue"
},
  "geometry": {"coordinates":[7.5942840576,50.3499298096],"type":"Point"}
}