{
  "type": "Feature",
  "properties": {
    "iso:country":"DE",
    "sg:address":"M\u00fchlenstr. 17",
    "sg:city":"L\u00f6ningen",
    "sg:phone":"+49 5432/3656",
    "sg:postcode":"49624",
    "sg:province":"Niedersachsen",
    "wof:name":"Peter Wietstock",
    "wof:placetype":"venue"
},
  "geometry": {"coordinates":[7.761627,52.733849],"type":"Point"}
}