{
  "type": "Feature",
  "properties": {
    "iso:country":"DE",
    "sg:address":"Hugenweg 42",
    "sg:city":"Rheinfelden",
    "sg:phone":"+49 7623/59226",
    "sg:postcode":"79618",
    "sg:province":"Baden-W\u00fcrttemberg",
    "wof:name":"Uwe Dittus Sportmarketing Gmbh",
    "wof:placetype":"venue"
},
  "geometry": {"coordinates":[7.7909560204,47.6019020081],"type":"Point"}
}