{
  "type": "Feature",
  "properties": {
    "iso:country":"DE",
    "sg:address":"Walter-Dodde-Str. 29",
    "sg:city":"Solingen",
    "sg:phone":"+49 212/2471962",
    "sg:postcode":"42657",
    "sg:province":"Nordrhein-Westfalen",
    "wof:name":"T. Bertrams Architekt",
    "wof:placetype":"venue"
},
  "geometry": {"coordinates":[7.072939,51.161678],"type":"Point"}
}