{
  "type": "Feature",
  "properties": {
    "iso:country":"DE",
    "sg:address":"Markt 10",
    "sg:city":"K\u00f6ln",
    "sg:postcode":"51103",
    "sg:province":"Nordrhein-Westfalen",
    "wof:name":"Hypnose Zur Lebenshilfe",
    "wof:placetype":"venue"
},
  "geometry": {"coordinates":[7.005341,50.940285],"type":"Point"}
}