{
  "type": "Feature",
  "properties": {
    "iso:country":"DE",
    "sg:address":"Werler Str. 113",
    "sg:city":"Hamm",
    "sg:phone":"+49 2381/59409",
    "sg:postcode":"59063",
    "sg:province":"Nordrhein-Westfalen",
    "wof:name":"Dr. Michael Von Glahn Und Wiltrud Von Glahn",
    "wof:placetype":"venue"
},
  "geometry": {"coordinates":[7.8281798363,51.6702919006],"type":"Point"}
}