{
  "type": "Feature",
  "properties": {
    "iso:country":"DE",
    "sg:address":"F\u00e4hrer Flur 60",
    "sg:city":"Bremen",
    "sg:phone":"+49 421/655557",
    "sg:postcode":"28755",
    "sg:province":"Bremen",
    "wof:name":"E. Heer",
    "wof:placetype":"venue"
},
  "geometry": {"coordinates":[8.612282753,53.1801986694],"type":"Point"}
}