{
  "type": "Feature",
  "properties": {
    "iso:country":"DE",
    "sg:address":"Schneeberger Str. 2",
    "sg:city":"Wilkau-Ha\u00dflau",
    "sg:phone":"+49 375/671310",
    "sg:postcode":"08112",
    "sg:province":"Sachsen",
    "wof:name":"Lutz Ungeth\u00fcm",
    "wof:placetype":"venue"
},
  "geometry": {"coordinates":[12.5133619308,50.6766738892],"type":"Point"}
}