{
  "type": "Feature",
  "properties": {
    "iso:country":"DE",
    "sg:address":"Eichendorffstr. 11",
    "sg:city":"Saalfeld",
    "sg:postcode":"07318",
    "sg:province":"Th\u00fcringen",
    "wof:name":"Dr. Med. Birgit Buschner",
    "wof:placetype":"venue"
},
  "geometry": {"coordinates":[11.351954,50.643276],"type":"Point"}
}