{
  "type": "Feature",
  "properties": {
    "iso:country":"DE",
    "sg:address":"Schlo\u00dfplatz 1",
    "sg:city":"Meiningen",
    "sg:phone":"+49 3693/454197",
    "sg:postcode":"98617",
    "sg:province":"Th\u00fcringen",
    "wof:name":"Stadtarchiv",
    "wof:placetype":"venue"
},
  "geometry": {"coordinates":[10.41352,50.570175],"type":"Point"}
}