{
  "type": "Feature",
  "properties": {
    "iso:country":"DE",
    "sg:address":"Gro\u00dfpartstr. 2 C",
    "sg:city":"Ludwigshafen",
    "sg:postcode":"67071",
    "sg:province":"Rheinland-Pfalz",
    "wof:name":"Ares Armee- Und Freizeitbekleidung Gmbh",
    "wof:placetype":"venue"
},
  "geometry": {"coordinates":[8.381665,49.496021],"type":"Point"}
}