{
  "type": "Feature",
  "properties": {
    "iso:country":"DE",
    "sg:address":"B\u00f6ttnerstr. 42",
    "sg:city":"Berlin",
    "sg:phone":"+49 30/94380553",
    "sg:postcode":"13125",
    "sg:province":"Berlin",
    "wof:name":"Kts Transporte Klaus Scholz",
    "wof:placetype":"venue"
},
  "geometry": {"coordinates":[13.4575643539,52.6102600098],"type":"Point"}
}