{
  "type": "Feature",
  "properties": {
    "iso:country":"DE",
    "sg:address":"Helpensteiner Kirchweg 55",
    "sg:city":"Neuss",
    "sg:phone":"+49 2137/76767",
    "sg:postcode":"41469",
    "sg:province":"Nordrhein-Westfalen",
    "wof:name":"Aco Technob\u00fcro Gmbh",
    "wof:placetype":"venue"
},
  "geometry": {"coordinates":[6.6840848923,51.1432418823],"type":"Point"}
}