{
  "type": "Feature",
  "properties": {
    "iso:country":"DE",
    "sg:address":"Berliner Platz 5",
    "sg:city":"Biberach",
    "sg:phone":"+49 7351/21051",
    "sg:postcode":"88400",
    "sg:province":"Baden-W\u00fcrttemberg",
    "wof:name":"Hotel Berliner Hof Gmbh",
    "wof:placetype":"venue"
},
  "geometry": {"coordinates":[9.787021637,48.085647583],"type":"Point"}
}