{
  "type": "Feature",
  "properties": {
    "iso:country":"DE",
    "sg:address":"Bahnhofstr.",
    "sg:city":"Bochum",
    "sg:phone":"+49 234/680535",
    "sg:postcode":"44866",
    "sg:province":"Nordrhein-Westfalen",
    "wof:name":"Geber Intertabaco Gmbh",
    "wof:placetype":"venue"
},
  "geometry": {"coordinates":[7.1382799149,51.4781532288],"type":"Point"}
}