{
  "type": "Feature",
  "properties": {
    "iso:country":"DE",
    "sg:address":"Ringstr. 6",
    "sg:city":"Wiesloch",
    "sg:phone":"+49 6222/8097",
    "sg:postcode":"69168",
    "sg:province":"Baden-W\u00fcrttemberg",
    "wof:name":"I & V Immobilien Und Vermietungs Gmbh",
    "wof:placetype":"venue"
},
  "geometry": {"coordinates":[8.7020111084,49.2944831848],"type":"Point"}
}