{
  "type": "Feature",
  "properties": {
    "iso:country":"DE",
    "sg:address":"Burgstr. 2",
    "sg:city":"Lingen",
    "sg:phone":"+49 591/2210",
    "sg:postcode":"49808",
    "sg:province":"Niedersachsen",
    "wof:name":"B. Wim",
    "wof:placetype":"venue"
},
  "geometry": {"coordinates":[7.317262,52.522141],"type":"Point"}
}