{
  "type": "Feature",
  "properties": {
    "iso:country":"DE",
    "sg:address":"Wangener Marktplatz 4",
    "sg:city":"Stuttgart",
    "sg:postcode":"70327",
    "sg:province":"Baden-W\u00fcrttemberg",
    "wof:name":"Stuttgarter Sonder-posten- Markt Heiko Franke E. Kfm.",
    "wof:placetype":"venue"
},
  "geometry": {"coordinates":[9.2454528809,48.7720031738],"type":"Point"}
}