{
  "type": "Feature",
  "properties": {
    "iso:country":"DE",
    "sg:address":"Mittelstr. 16",
    "sg:city":"Bad W\u00fcnnenberg",
    "sg:phone":"+49 2953/8191",
    "sg:postcode":"33181",
    "sg:province":"Nordrhein-Westfalen",
    "wof:name":"Heinz-josef Daniel",
    "wof:placetype":"venue"
},
  "geometry": {"coordinates":[8.700301,51.521275],"type":"Point"}
}