{
  "type": "Feature",
  "properties": {
    "iso:country":"DE",
    "sg:address":"Hauptstr. 39",
    "sg:city":"Gerolfingen",
    "sg:phone":"+49 9854/293",
    "sg:postcode":"91726",
    "sg:province":"Bayern",
    "wof:name":"Sparkasse Wassertr\u00fcdingen",
    "wof:placetype":"venue"
},
  "geometry": {"coordinates":[10.506995,49.053959],"type":"Point"}
}