{
  "type": "Feature",
  "properties": {
    "iso:country":"DE",
    "sg:address":"Kalterweg 95",
    "sg:city":"Stadtlohn",
    "sg:phone":"+49 2563/3179",
    "sg:postcode":"48703",
    "sg:province":"Nordrhein-Westfalen",
    "wof:name":"Zur Kalter",
    "wof:placetype":"venue"
},
  "geometry": {"coordinates":[6.9333200455,51.9992752075],"type":"Point"}
}