{
  "type": "Feature",
  "properties": {
    "iso:country":"DE",
    "sg:address":"Bugdahnstr. 5",
    "sg:city":"Hamburg",
    "sg:phone":"+49 40/3069270",
    "sg:postcode":"22767",
    "sg:province":"Hamburg",
    "wof:name":"Hermann Jaeger Export Gmbh",
    "wof:placetype":"venue"
},
  "geometry": {"coordinates":[9.937371,53.550892],"type":"Point"}
}