{
  "type": "Feature",
  "properties": {
    "iso:country":"DE",
    "sg:address":"Bergham 15",
    "sg:city":"Marktl",
    "sg:phone":"+49 8678/340",
    "sg:postcode":"84533",
    "sg:province":"Bayern",
    "wof:name":"Josef Edhofer",
    "wof:placetype":"venue"
},
  "geometry": {"coordinates":[12.8426389694,48.2461662292],"type":"Point"}
}