{
  "type": "Feature",
  "properties": {
    "iso:country":"DE",
    "sg:address":"Am Rabensoll 89",
    "sg:city":"Parchim",
    "sg:phone":"+49 3874/47330",
    "sg:postcode":"19370",
    "sg:province":"Mecklenburg-Vorpommern",
    "wof:name":"Wedi Wannenbauelemente Gmbh",
    "wof:placetype":"venue"
},
  "geometry": {"coordinates":[11.87076,53.434128],"type":"Point"}
}