{
  "type": "Feature",
  "properties": {
    "iso:country":"DE",
    "sg:address":"Klaus-Conrad-Str. 13",
    "sg:city":"Wernberg-K\u00f6blitz",
    "sg:postcode":"92533",
    "sg:province":"Bayern",
    "wof:name":"Doll Verwaltungs- Gmbh",
    "wof:placetype":"venue"
},
  "geometry": {"coordinates":[12.139336586,49.5300254822],"type":"Point"}
}