{
  "type": "Feature",
  "properties": {
    "iso:country":"DE",
    "sg:address":"Am Brunnenacker 4",
    "sg:city":"Weidenberg",
    "sg:phone":"+49 9209/16367",
    "sg:postcode":"95466",
    "sg:province":"Bayern",
    "wof:name":"Msd Auto- U. Sportzubeh\u00f6r Gmbh",
    "wof:placetype":"venue"
},
  "geometry": {"coordinates":[11.6657381058,49.919506073],"type":"Point"}
}