{
  "type": "Feature",
  "properties": {
    "iso:country":"DE",
    "sg:address":"Berliner Str. 1",
    "sg:city":"Ro\u00dflau",
    "sg:phone":"+49 34901/84135",
    "sg:postcode":"06862",
    "sg:province":"Sachsen-Anhalt",
    "wof:name":"Zum Waldhorn",
    "wof:placetype":"venue"
},
  "geometry": {"coordinates":[12.2580652237,51.8885116577],"type":"Point"}
}