{
  "type": "Feature",
  "properties": {
    "iso:country":"DE",
    "sg:address":"H\u00f6lderlinstr 1",
    "sg:city":"Leipzig",
    "sg:phone":"+49 341/4800808",
    "sg:postcode":"04157",
    "sg:province":"Sachsen",
    "wof:name":"Goldeck S\u00fc\u00dfwaren Gmbh",
    "wof:placetype":"venue"
},
  "geometry": {"coordinates":[12.364987,51.371151],"type":"Point"}
}