{
  "type": "Feature",
  "properties": {
    "iso:country":"DE",
    "sg:address":"Rotdornstr. 94",
    "sg:city":"Albstadt",
    "sg:phone":"+49 7432/8127",
    "sg:postcode":"72461",
    "sg:province":"Baden-W\u00fcrttemberg",
    "wof:name":"K.-h. Gl\u00f6ckner",
    "wof:placetype":"venue"
},
  "geometry": {"coordinates":[9.0234422684,48.2461624146],"type":"Point"}
}