{
  "type": "Feature",
  "properties": {
    "iso:country":"DE",
    "sg:address":"Anger 30",
    "sg:city":"Bad Frankenhausen",
    "sg:phone":"+49 34671/2114",
    "sg:postcode":"06567",
    "sg:province":"Th\u00fcringen",
    "wof:name":"Kreissparkasse Artern",
    "wof:placetype":"venue"
},
  "geometry": {"coordinates":[11.177272,51.349445],"type":"Point"}
}