{
  "type": "Feature",
  "properties": {
    "iso:country":"DE",
    "sg:address":"Berliner Str. 48",
    "sg:city":"Hennigsdorf",
    "sg:postcode":"16761",
    "sg:province":"Brandenburg",
    "wof:name":"E.-w. Wimmer",
    "wof:placetype":"venue"
},
  "geometry": {"coordinates":[13.2092,52.639015],"type":"Point"}
}