{
  "type": "Feature",
  "properties": {
    "iso:country":"DE",
    "sg:address":"Blondelstr. 18",
    "sg:city":"Aachen",
    "sg:phone":"+49 241/32423",
    "sg:postcode":"52062",
    "sg:province":"Nordrhein-Westfalen",
    "wof:name":"Schl\u00fcssel-fix Peter Nacken Inh. Peter Haupt",
    "wof:placetype":"venue"
},
  "geometry": {"coordinates":[6.0906529427,50.7758903503],"type":"Point"}
}