{
  "type": "Feature",
  "properties": {
    "iso:country":"DE",
    "sg:address":"Hemerter Weg 3",
    "sg:city":"Holzheim",
    "sg:phone":"+49 8276/322",
    "sg:postcode":"86684",
    "sg:province":"Bayern",
    "wof:name":"Josef M\u00fcller",
    "wof:placetype":"venue"
},
  "geometry": {"coordinates":[10.946833,48.612122],"type":"Point"}
}