{
  "type": "Feature",
  "properties": {
    "iso:country":"DE",
    "sg:address":"Tr\u00fcbnerstr. 28",
    "sg:city":"Heidelberg",
    "sg:postcode":"69121",
    "sg:province":"Baden-W\u00fcrttemberg",
    "wof:name":"Achim Knapp Gmbh",
    "wof:placetype":"venue"
},
  "geometry": {"coordinates":[8.679441,49.432411],"type":"Point"}
}