{
  "type": "Feature",
  "properties": {
    "iso:country":"DE",
    "sg:address":"Pfarrgasse 1",
    "sg:city":"B\u00e4rnau",
    "sg:phone":"+49 9635/320",
    "sg:postcode":"95671",
    "sg:province":"Bayern",
    "wof:name":"Gebr\u00fcder H\u00f6pfl",
    "wof:placetype":"venue"
},
  "geometry": {"coordinates":[12.43109,49.811729],"type":"Point"}
}