{
  "type": "Feature",
  "properties": {
    "iso:country":"DE",
    "sg:address":"Wormser Str. 35",
    "sg:city":"Frankenthal",
    "sg:phone":"+49 6233/26414",
    "sg:postcode":"67227",
    "sg:province":"Rheinland-Pfalz",
    "wof:name":"G. L. Soneck Heilpraktiker",
    "wof:placetype":"venue"
},
  "geometry": {"coordinates":[8.3536596298,49.5377960205],"type":"Point"}
}