{
  "type": "Feature",
  "properties": {
    "iso:country":"DE",
    "sg:address":"C\u00e4cilienstra\u00dfe 8",
    "sg:city":"Hamburg",
    "sg:postcode":"22301",
    "sg:province":"Hamburg",
    "wof:name":"Uwe`s Homepage",
    "wof:placetype":"venue"
},
  "geometry": {"coordinates":[10.004872,53.5868],"type":"Point"}
}