{
  "type": "Feature",
  "properties": {
    "iso:country":"DE",
    "sg:address":"Feldbachacker",
    "sg:city":"Dortmund",
    "sg:postcode":"44149",
    "sg:province":"Nordrhein-Westfalen",
    "wof:name":"Midrahtec Drahtwaren Verwaltungs Gmbh",
    "wof:placetype":"venue"
},
  "geometry": {"coordinates":[7.3607711792,51.4920845032],"type":"Point"}
}