{
  "type": "Feature",
  "properties": {
    "iso:country":"DE",
    "sg:address":"Rudolf-Breitscheid-Str. 24",
    "sg:city":"Parey",
    "sg:postcode":"39317",
    "sg:province":"Sachsen-Anhalt",
    "wof:name":"M.w. Beratungsges. Mbh",
    "wof:placetype":"venue"
},
  "geometry": {"coordinates":[11.9874134064,52.384967804],"type":"Point"}
}