{
  "type": "Feature",
  "properties": {
    "iso:country":"DE",
    "sg:address":"Nienoverer Weg",
    "sg:city":"Bodenfelde",
    "sg:phone":"+49 5572/551",
    "sg:postcode":"37194",
    "sg:province":"Hessen",
    "wof:name":"F\u00f6rderverein Freibad E. V.",
    "wof:placetype":"venue"
},
  "geometry": {"coordinates":[9.5597429276,51.6434669495],"type":"Point"}
}