{
  "type": "Feature",
  "properties": {
    "iso:country":"DE",
    "sg:address":"Dorfstr. 30",
    "sg:city":"Domsdorf",
    "sg:phone":"+49 35341/94283",
    "sg:postcode":"04924",
    "sg:province":"Brandenburg",
    "wof:name":"Heinz Schn\u00fcrpel",
    "wof:placetype":"venue"
},
  "geometry": {"coordinates":[13.406887,51.575333],"type":"Point"}
}