{
  "type": "Feature",
  "properties": {
    "iso:country":"DE",
    "sg:address":"Grandweg 15",
    "sg:city":"Ludwigslust",
    "sg:phone":"+49 3874/42410",
    "sg:postcode":"19288",
    "sg:province":"Mecklenburg-Vorpommern",
    "wof:name":"Fahrzeugfedern Gmbh",
    "wof:placetype":"venue"
},
  "geometry": {"coordinates":[11.5023412704,53.3367919922],"type":"Point"}
}