{
  "type": "Feature",
  "properties": {
    "iso:country":"DE",
    "sg:address":"Mittelbacher Str. 13",
    "sg:city":"Jahnsdorf",
    "sg:phone":"+49 371/212214",
    "sg:postcode":"09387",
    "sg:province":"Sachsen",
    "wof:name":"Rainer Drechsler",
    "wof:placetype":"venue"
},
  "geometry": {"coordinates":[12.804309845,50.7795829773],"type":"Point"}
}