{
  "type": "Feature",
  "properties": {
    "iso:country":"DE",
    "sg:address":"Langenrainstr. 16",
    "sg:city":"Obrigheim",
    "sg:phone":"+49 6261/7132",
    "sg:postcode":"74847",
    "sg:province":"Baden-W\u00fcrttemberg",
    "wof:name":"P. Rothenburger",
    "wof:placetype":"venue"
},
  "geometry": {"coordinates":[9.0909690857,49.3548851013],"type":"Point"}
}