{
  "type": "Feature",
  "properties": {
    "iso:country":"DE",
    "sg:address":"Gr\u00e4fin-Theda-Str. 5",
    "sg:city":"Juist",
    "sg:phone":"+49 4935/352",
    "sg:postcode":"26571",
    "sg:province":"Niedersachsen",
    "wof:name":"Pension Haus Hasela",
    "wof:placetype":"venue"
},
  "geometry": {"coordinates":[6.9945859909,53.6788101196],"type":"Point"}
}