{
  "type": "Feature",
  "properties": {
    "iso:country":"DE",
    "sg:address":"Hauptstr. 76",
    "sg:city":"Salach",
    "sg:phone":"+49 7162/42992",
    "sg:postcode":"73084",
    "sg:province":"Baden-W\u00fcrttemberg",
    "wof:name":"Ernst B\u00fchler",
    "wof:placetype":"venue"
},
  "geometry": {"coordinates":[9.7398548126,48.6919326782],"type":"Point"}
}