{
  "type": "Feature",
  "properties": {
    "iso:country":"DE",
    "sg:address":"Immendorf 17",
    "sg:city":"P\u00f6ttmes",
    "sg:phone":"+49 8253/539",
    "sg:postcode":"86554",
    "sg:province":"Bayern",
    "wof:name":"Alois Moser",
    "wof:placetype":"venue"
},
  "geometry": {"coordinates":[11.0840797424,48.5685081482],"type":"Point"}
}