{
  "type": "Feature",
  "properties": {
    "iso:country":"DE",
    "sg:address":"Albrecht-D\u00fcrer-Str. 11",
    "sg:city":"Bautzen",
    "sg:phone":"+49 3591/306604",
    "sg:postcode":"02625",
    "sg:province":"Sachsen",
    "wof:name":"Christian Scholze",
    "wof:placetype":"venue"
},
  "geometry": {"coordinates":[14.417912,51.180607],"type":"Point"}
}