{
  "type": "Feature",
  "properties": {
    "iso:country":"DE",
    "sg:address":"Sch\u00fctzeberger Stra\u00dfe",
    "sg:city":"Wolfhagen",
    "sg:postcode":"34466",
    "sg:province":"Hessen",
    "wof:name":"Sch\u00fctzeberg-apotheke, Peter Blau",
    "wof:placetype":"venue"
},
  "geometry": {"coordinates":[9.180311,51.332184],"type":"Point"}
}