{
  "type": "Feature",
  "properties": {
    "iso:country":"DE",
    "sg:address":"Am S\u00fcrkenstein 7",
    "sg:city":"Balve",
    "sg:phone":"+49 2375/2153",
    "sg:postcode":"58802",
    "sg:province":"Nordrhein-Westfalen",
    "wof:name":"Hans-dieter Berens",
    "wof:placetype":"venue"
},
  "geometry": {"coordinates":[7.8905911446,51.3535995483],"type":"Point"}
}