{
  "type": "Feature",
  "properties": {
    "iso:country":"DE",
    "sg:address":"Hahlgartenstr. 10",
    "sg:city":"Griesheim",
    "sg:phone":"+49 6155/2838",
    "sg:postcode":"64347",
    "sg:province":"Hessen",
    "wof:name":"R. Kr\u00fcger",
    "wof:placetype":"venue"
},
  "geometry": {"coordinates":[8.558895,49.859364],"type":"Point"}
}