{
  "type": "Feature",
  "properties": {
    "iso:country":"DE",
    "sg:address":"Eglseer Weg 30 a",
    "sg:city":"Straubing",
    "sg:phone":"+49 9421/33705",
    "sg:postcode":"94315",
    "sg:province":"Bayern",
    "wof:name":"Georg Spanner",
    "wof:placetype":"venue"
},
  "geometry": {"coordinates":[12.593142,48.869846],"type":"Point"}
}