{
  "type": "Feature",
  "properties": {
    "iso:country":"DE",
    "sg:address":"Taunusweg 4",
    "sg:city":"Fuldabr\u00fcck",
    "sg:phone":"+49 561/583458",
    "sg:postcode":"34277",
    "sg:province":"Hessen",
    "wof:name":"Wilhelm Gross",
    "wof:placetype":"venue"
},
  "geometry": {"coordinates":[9.495747,51.269264],"type":"Point"}
}