{
  "type": "Feature",
  "properties": {
    "iso:country":"DE",
    "sg:address":"Herrnschachtstr. 14",
    "sg:city":"N\u00fcrnberg",
    "sg:postcode":"90453",
    "sg:province":"Bayern",
    "wof:name":"Lebende Gl\u00fcckw\u00fcnsche E. K.",
    "wof:placetype":"venue"
},
  "geometry": {"coordinates":[11.0303096771,49.3784790039],"type":"Point"}
}