{
  "type": "Feature",
  "properties": {
    "iso:country":"DE",
    "sg:address":"Rosenbuschstr. 25",
    "sg:city":"Sinzing",
    "sg:phone":"+49 9404/961056",
    "sg:postcode":"93161",
    "sg:province":"Bayern",
    "wof:name":"Kurt John Werbung",
    "wof:placetype":"venue"
},
  "geometry": {"coordinates":[11.9595403671,48.9773368835],"type":"Point"}
}