{
  "type": "Feature",
  "properties": {
    "iso:country":"DE",
    "sg:address":"Weinstr. 73",
    "sg:city":"Hainfeld",
    "sg:phone":"+49 6323/81314",
    "sg:postcode":"76835",
    "sg:province":"Rheinland-Pfalz",
    "wof:name":"Ernst Oehl Weinanbau",
    "wof:placetype":"venue"
},
  "geometry": {"coordinates":[8.1001806259,49.2583732605],"type":"Point"}
}