{
  "type": "Feature",
  "properties": {
    "iso:country":"DE",
    "sg:address":"Franz-Lenze-Platz 43",
    "sg:city":"Duisburg",
    "sg:phone":"+49 203/474044",
    "sg:postcode":"47178",
    "sg:province":"Nordrhein-Westfalen",
    "wof:name":"Eiscaf\u00e9 Tiziano",
    "wof:placetype":"venue"
},
  "geometry": {"coordinates":[6.721932,51.538063],"type":"Point"}
}