{
  "type": "Feature",
  "properties": {
    "iso:country":"DE",
    "sg:address":"Dorfstr. 18",
    "sg:city":"Zetel",
    "sg:phone":"+49 4453/6615",
    "sg:postcode":"26340",
    "sg:province":"Niedersachsen",
    "wof:name":"Fre\u00dfnapf",
    "wof:placetype":"venue"
},
  "geometry": {"coordinates":[8.002494,53.423031],"type":"Point"}
}