{
  "type": "Feature",
  "properties": {
    "iso:country":"DE",
    "sg:address":"Stauferring 58",
    "sg:city":"Fulda",
    "sg:phone":"+49 661/47227",
    "sg:postcode":"36043",
    "sg:province":"Hessen",
    "wof:name":"Fingernagelstudio Perfect Nails Mobil",
    "wof:placetype":"venue"
},
  "geometry": {"coordinates":[9.695721,50.530773],"type":"Point"}
}