{
  "type": "Feature",
  "properties": {
    "iso:country":"DE",
    "sg:address":"Mainzer Str. 169",
    "sg:city":"Saarbr\u00fccken",
    "sg:phone":"+49 681/62828",
    "sg:postcode":"66121",
    "sg:province":"Saarland",
    "wof:name":"Ais Com For Car Gmbh",
    "wof:placetype":"venue"
},
  "geometry": {"coordinates":[7.0173821449,49.2279548645],"type":"Point"}
}