{
  "type": "Feature",
  "properties": {
    "iso:country":"DE",
    "sg:address":"Charlottenstr. 17",
    "sg:city":"Friedrichshafen",
    "sg:phone":"+49 7541/370173",
    "sg:postcode":"88045",
    "sg:province":"Baden-W\u00fcrttemberg",
    "wof:name":"Sch\u00f6llhorn Wohnbau Gmbh",
    "wof:placetype":"venue"
},
  "geometry": {"coordinates":[9.4777669907,47.6544723511],"type":"Point"}
}