{
  "type": "Feature",
  "properties": {
    "iso:country":"DE",
    "sg:address":"Stadtweg 12",
    "sg:city":"Weinbergen",
    "sg:phone":"+49 36014/40884",
    "sg:postcode":"99998",
    "sg:province":"Th\u00fcringen",
    "wof:name":"R. Thiele",
    "wof:placetype":"venue"
},
  "geometry": {"coordinates":[10.5119848251,51.1680755615],"type":"Point"}
}