{
  "type": "Feature",
  "properties": {
    "iso:country":"DE",
    "sg:address":"\u00dcberseering 29",
    "sg:city":"Hamburg",
    "sg:postcode":"22297",
    "sg:province":"Hamburg",
    "wof:name":"Dr. Sch\u00fcnemann & Ullmer Holding Gmbh",
    "wof:placetype":"venue"
},
  "geometry": {"coordinates":[10.0246648788,53.6052093506],"type":"Point"}
}