{
  "type": "Feature",
  "properties": {
    "iso:country":"DE",
    "sg:address":"Marktplatz 1",
    "sg:city":"Hengersberg",
    "sg:phone":"+49 9901/2658",
    "sg:postcode":"94491",
    "sg:province":"Bayern",
    "wof:name":"Restaurant Thessaloniki",
    "wof:placetype":"venue"
},
  "geometry": {"coordinates":[13.0511045456,48.7736968994],"type":"Point"}
}