{
  "type": "Feature",
  "properties": {
    "iso:country":"DE",
    "sg:address":"Hohner Heide 8",
    "sg:city":"Lengerich",
    "sg:phone":"+49 5481/6947",
    "sg:postcode":"49525",
    "sg:province":"Nordrhein-Westfalen",
    "wof:name":"Hallerdei & Lotz Nachf. Uwe Lotz",
    "wof:placetype":"venue"
},
  "geometry": {"coordinates":[7.8728160858,52.1502876282],"type":"Point"}
}