{
  "type": "Feature",
  "properties": {
    "iso:country":"DE",
    "sg:address":"Bahnhofstr. 12",
    "sg:city":"Freinsheim",
    "sg:postcode":"67251",
    "sg:province":"Rheinland-Pfalz",
    "wof:name":"Stadt Feinsheim Sanierungstr\u00e4ger Gmbh",
    "wof:placetype":"venue"
},
  "geometry": {"coordinates":[8.207459,49.505733],"type":"Point"}
}