{
  "type": "Feature",
  "properties": {
    "iso:country":"DE",
    "sg:address":"Schillerstr. 36",
    "sg:city":"Neunkirchen",
    "sg:phone":"+49 6821/952109",
    "sg:postcode":"66540",
    "sg:province":"Saarland",
    "wof:name":"Frantra Speditions- Und Transport Gmbh",
    "wof:placetype":"venue"
},
  "geometry": {"coordinates":[7.1829929352,49.3661231995],"type":"Point"}
}