{
  "type": "Feature",
  "properties": {
    "iso:country":"DE",
    "sg:address":"Ostbahnstr. 18",
    "sg:city":"Landau",
    "sg:phone":"+49 6341/87162",
    "sg:postcode":"76829",
    "sg:province":"Rheinland-Pfalz",
    "wof:name":"Bahnhof-apotheke",
    "wof:placetype":"venue"
},
  "geometry": {"coordinates":[8.119933,49.197613],"type":"Point"}
}