{
  "type": "Feature",
  "properties": {
    "iso:country":"DE",
    "sg:address":"Sandmoorweg",
    "sg:city":"Hamburg",
    "sg:phone":"+49 40/814792",
    "sg:postcode":"22559",
    "sg:province":"Hamburg",
    "wof:name":"Kleine Waldsch\u00e4nke Am Wildgehege",
    "wof:placetype":"venue"
},
  "geometry": {"coordinates":[9.7464046478,53.5950546265],"type":"Point"}
}