{
  "type": "Feature",
  "properties": {
    "iso:country":"DE",
    "sg:address":"Viktualienmarkt 3",
    "sg:city":"Straubing",
    "sg:phone":"+49 9421/99050",
    "sg:postcode":"94315",
    "sg:province":"Bayern",
    "wof:name":"G\u00fcnter Emnet Notar",
    "wof:placetype":"venue"
},
  "geometry": {"coordinates":[12.5734586716,48.8807525635],"type":"Point"}
}