{
  "type": "Feature",
  "properties": {
    "iso:country":"DE",
    "sg:address":"Hauptstr. 27",
    "sg:city":"Enkenbach-Alsenborn",
    "sg:phone":"+49 6303/983344",
    "sg:postcode":"67677",
    "sg:province":"Rheinland-Pfalz",
    "wof:name":"Praxis Dr. Med. Diehl Und Dr. Thielen",
    "wof:placetype":"venue"
},
  "geometry": {"coordinates":[7.8969368935,49.4869766235],"type":"Point"}
}