{
  "type": "Feature",
  "properties": {
    "iso:country":"DE",
    "sg:address":"Am Brabrinke 14",
    "sg:city":"Hannover",
    "sg:postcode":"30519",
    "sg:province":"Niedersachsen",
    "wof:name":"Fertigungscenter F\u00fcr Elektrische Anlagen",
    "wof:placetype":"venue"
},
  "geometry": {"coordinates":[9.785582,52.323639],"type":"Point"}
}