{
  "type": "Feature",
  "properties": {
    "iso:country":"DE",
    "sg:address":"Oberd\u00f6rfer Str. 7",
    "sg:city":"Brombachtal",
    "sg:phone":"+49 6063/2204",
    "sg:postcode":"64753",
    "sg:province":"Hessen",
    "wof:name":"Heinz Vetter Eisen- Und Haushaltsger\u00e4te",
    "wof:placetype":"venue"
},
  "geometry": {"coordinates":[8.949826,49.722012],"type":"Point"}
}