{
  "type": "Feature",
  "properties": {
    "iso:country":"DE",
    "sg:address":"Inselstr. 8",
    "sg:city":"Braunsbach",
    "sg:phone":"+49 7906/8274",
    "sg:postcode":"74542",
    "sg:province":"Baden-W\u00fcrttemberg",
    "wof:name":"Sonne",
    "wof:placetype":"venue"
},
  "geometry": {"coordinates":[9.7909755707,49.1985473633],"type":"Point"}
}