{
  "type": "Feature",
  "properties": {
    "iso:country":"DE",
    "sg:address":"Alter Kirchdeich 3",
    "sg:city":"Hamburg",
    "sg:phone":"+49 40/7373561",
    "sg:postcode":"21037",
    "sg:province":"Hamburg",
    "wof:name":"Itzehoer Versicherung Olaf Graf",
    "wof:placetype":"venue"
},
  "geometry": {"coordinates":[10.0845775604,53.4758148193],"type":"Point"}
}