{
  "type": "Feature",
  "properties": {
    "iso:country":"DE",
    "sg:address":"Kellergasse 9",
    "sg:city":"Emskirchen",
    "sg:phone":"+49 9104/938",
    "sg:postcode":"91448",
    "sg:province":"Bayern",
    "wof:name":"Ernst Dimpel",
    "wof:placetype":"venue"
},
  "geometry": {"coordinates":[10.719673,49.550476],"type":"Point"}
}