{
  "type": "Feature",
  "properties": {
    "iso:country":"DE",
    "sg:address":"Nr. 86",
    "sg:city":"Warmsen",
    "sg:phone":"+49 5767/223",
    "sg:postcode":"31606",
    "sg:province":"Niedersachsen",
    "wof:name":"Ev. Pfarramt",
    "wof:placetype":"venue"
},
  "geometry": {"coordinates":[8.8493309021,52.456073761],"type":"Point"}
}