{
  "type": "Feature",
  "properties": {
    "iso:country":"DE",
    "sg:address":"Kastanienweg 1",
    "sg:city":"Bad Honnef",
    "sg:phone":"+49 2224/4899",
    "sg:postcode":"53604",
    "sg:province":"Nordrhein-Westfalen",
    "wof:name":"Edith Blome-k\u00f6nig",
    "wof:placetype":"venue"
},
  "geometry": {"coordinates":[7.225589,50.637028],"type":"Point"}
}