{
  "type": "Feature",
  "properties": {
    "iso:country":"DE",
    "sg:address":"Wenger Str. 13",
    "sg:city":"Hameln",
    "sg:phone":"+49 5151/964716",
    "sg:postcode":"31787",
    "sg:province":"Niedersachsen",
    "wof:name":"Burghard Papendick Rechtsanwalt",
    "wof:placetype":"venue"
},
  "geometry": {"coordinates":[9.3418121338,52.1068191528],"type":"Point"}
}