{
  "type": "Feature",
  "properties": {
    "iso:country":"DE",
    "sg:address":"Hanftalstr. 111",
    "sg:city":"Hennef",
    "sg:phone":"+49 2242/82890",
    "sg:postcode":"53773",
    "sg:province":"Nordrhein-Westfalen",
    "wof:name":"Tschiersky Immobilienmakler",
    "wof:placetype":"venue"
},
  "geometry": {"coordinates":[7.3073382378,50.7625694275],"type":"Point"}
}