{
  "type": "Feature",
  "properties": {
    "iso:country":"DE",
    "sg:address":"Waar 1",
    "sg:city":"Radevormwald",
    "sg:phone":"+49 2195/932121",
    "sg:postcode":"42477",
    "sg:province":"Nordrhein-Westfalen",
    "wof:name":"Transporte Krause Kg",
    "wof:placetype":"venue"
},
  "geometry": {"coordinates":[7.4133071899,51.2135162354],"type":"Point"}
}