{
  "type": "Feature",
  "properties": {
    "iso:country":"DE",
    "sg:address":"Vogging 1",
    "sg:city":"Ampfing",
    "sg:phone":"+49 8636/66386",
    "sg:postcode":"84539",
    "sg:province":"Bayern",
    "wof:name":"Restaurant Reiterst\u00fcberl",
    "wof:placetype":"venue"
},
  "geometry": {"coordinates":[12.366437912,48.290309906],"type":"Point"}
}