{
  "type": "Feature",
  "properties": {
    "iso:country":"DE",
    "sg:address":"Th\u00fcngersheimer Str. 127 a",
    "sg:city":"Veitsh\u00f6chheim",
    "sg:phone":"+49 931/98321",
    "sg:postcode":"97209",
    "sg:province":"Bayern",
    "wof:name":"Dr. Herbert Konrad Tierarzt",
    "wof:placetype":"venue"
},
  "geometry": {"coordinates":[9.8704805374,49.8408164978],"type":"Point"}
}