{
  "type": "Feature",
  "properties": {
    "iso:country":"DE",
    "sg:address":"Bahnhofstr. 2",
    "sg:city":"Willebadessen",
    "sg:postcode":"34439",
    "sg:province":"Nordrhein-Westfalen",
    "wof:name":"Bau-werk-stadt Gmbh",
    "wof:placetype":"venue"
},
  "geometry": {"coordinates":[9.0313138962,51.6254425049],"type":"Point"}
}