{
  "type": "Feature",
  "properties": {
    "iso:country":"DE",
    "sg:address":"Werfelstr. 20",
    "sg:city":"Osthofen",
    "sg:phone":"+49 6242/99728",
    "sg:postcode":"67574",
    "sg:province":"Rheinland-Pfalz",
    "wof:name":"Lorenz Ragus",
    "wof:placetype":"venue"
},
  "geometry": {"coordinates":[8.32421875,49.6962165833],"type":"Point"}
}