{
  "type": "Feature",
  "properties": {
    "iso:country":"DE",
    "sg:address":"Burgstr. 33",
    "sg:city":"K\u00f6nnern",
    "sg:phone":"+49 34691/28973",
    "sg:postcode":"06420",
    "sg:province":"Sachsen-Anhalt",
    "wof:name":"Siegfried Kalinowski",
    "wof:placetype":"venue"
},
  "geometry": {"coordinates":[11.7618188858,51.670665741],"type":"Point"}
}