{
  "type": "Feature",
  "properties": {
    "iso:country":"DE",
    "sg:address":"Hauptstr. 73",
    "sg:city":"Schopfheim",
    "sg:phone":"+49 7622/8481",
    "sg:postcode":"79650",
    "sg:province":"Baden-W\u00fcrttemberg",
    "wof:name":"G\u00fcnter Imbery",
    "wof:placetype":"venue"
},
  "geometry": {"coordinates":[7.823102951,47.6511192322],"type":"Point"}
}