{
  "type": "Feature",
  "properties": {
    "iso:country":"DE",
    "sg:address":"Lindenstr. 5",
    "sg:city":"Steinigtwolmsdorf",
    "sg:phone":"+49 35951/32238",
    "sg:postcode":"01904",
    "sg:province":"Sachsen",
    "wof:name":"Heinz Schulze",
    "wof:placetype":"venue"
},
  "geometry": {"coordinates":[14.34275,51.070023],"type":"Point"}
}