{
  "type": "Feature",
  "properties": {
    "iso:country":"DE",
    "sg:address":"Mergenthalerstr. 2",
    "sg:city":"Frankfurt",
    "sg:phone":"+49 69/422001",
    "sg:postcode":"60388",
    "sg:province":"Hessen",
    "wof:name":"Klaus E. H. Zapf Transporte Frankfurt Gmbh",
    "wof:placetype":"venue"
},
  "geometry": {"coordinates":[8.7390642166,50.1332473755],"type":"Point"}
}