{
  "type": "Feature",
  "properties": {
    "iso:country":"DE",
    "sg:address":"Haubachstr. 12",
    "sg:city":"Dortmund",
    "sg:phone":"+49 231/7273763",
    "sg:postcode":"44229",
    "sg:province":"Nordrhein-Westfalen",
    "wof:name":"Weinhandel H. H\u00fcrlimann",
    "wof:placetype":"venue"
},
  "geometry": {"coordinates":[7.4520249367,51.4530563354],"type":"Point"}
}