{
  "type": "Feature",
  "properties": {
    "iso:country":"DE",
    "sg:address":"J\u00e4germ\u00fchle 8",
    "sg:city":"Unterthingau",
    "sg:phone":"+49 8377/227",
    "sg:postcode":"87647",
    "sg:province":"Bayern",
    "wof:name":"Krippner-bogen Baufertigteile Gmbh",
    "wof:placetype":"venue"
},
  "geometry": {"coordinates":[10.4826231003,47.7766876221],"type":"Point"}
}