{
  "type": "Feature",
  "properties": {
    "iso:country":"DE",
    "sg:address":"Erlenweg 4c",
    "sg:city":"Schwarzenbruck",
    "sg:phone":"+49 9183/4939",
    "sg:postcode":"90592",
    "sg:province":"Bayern",
    "wof:name":"A. Miklis",
    "wof:placetype":"venue"
},
  "geometry": {"coordinates":[11.2956895828,49.3383598328],"type":"Point"}
}