{
  "type": "Feature",
  "properties": {
    "iso:country":"DE",
    "sg:address":"Kr\u00fcgerstr. 5",
    "sg:city":"Mannheim",
    "sg:phone":"+49 621/874827",
    "sg:postcode":"68219",
    "sg:province":"Baden-W\u00fcrttemberg",
    "wof:name":"Dammeyer & Selzer Gerhard Weber",
    "wof:placetype":"venue"
},
  "geometry": {"coordinates":[8.51614,49.452885],"type":"Point"}
}