{
  "type": "Feature",
  "properties": {
    "iso:country":"DE",
    "sg:address":"Paul-Keller-Str. 18",
    "sg:city":"Stockdorf",
    "sg:phone":"+49 89/8561033",
    "sg:postcode":"82131",
    "sg:province":"Bayern",
    "wof:name":"Diskmaster Gesellschaft F\u00fcr Daten-",
    "wof:placetype":"venue"
},
  "geometry": {"coordinates":[11.4016542435,48.0822982788],"type":"Point"}
}