{
  "type": "Feature",
  "properties": {
    "iso:country":"DE",
    "sg:address":"Niederbexbacher Str. 15",
    "sg:city":"Kirkel",
    "sg:phone":"+49 6841/982164",
    "sg:postcode":"66459",
    "sg:province":"Saarland",
    "wof:name":"Ecker",
    "wof:placetype":"venue"
},
  "geometry": {"coordinates":[7.2641568184,49.315158844],"type":"Point"}
}