{
  "type": "Feature",
  "properties": {
    "iso:country":"DE",
    "sg:address":"Paul-Lincke-Ufer 39-40",
    "sg:city":"Berlin",
    "sg:phone":"+49 30/6124841",
    "sg:postcode":"10999",
    "sg:province":"Berlin",
    "wof:name":"Otto Wonneberger Nachf.",
    "wof:placetype":"venue"
},
  "geometry": {"coordinates":[13.422312,52.496071],"type":"Point"}
}