{
  "type": "Feature",
  "properties": {
    "iso:country":"DE",
    "sg:address":"Siegersbusch 34",
    "sg:city":"Wuppertal",
    "sg:phone":"+49 202/784794",
    "sg:postcode":"42327",
    "sg:province":"Nordrhein-Westfalen",
    "wof:name":"Gerhard Kohl",
    "wof:placetype":"venue"
},
  "geometry": {"coordinates":[7.065847,51.238945],"type":"Point"}
}