{
  "type": "Feature",
  "properties": {
    "iso:country":"DE",
    "sg:address":"L\u00e4rchenweg 11",
    "sg:city":"Sengenthal",
    "sg:phone":"+49 9181/21577",
    "sg:postcode":"92369",
    "sg:province":"Bayern",
    "wof:name":"Sch\u00fctt Vermessungs-gmbh",
    "wof:placetype":"venue"
},
  "geometry": {"coordinates":[11.4403762817,49.2429580688],"type":"Point"}
}