{
  "type": "Feature",
  "properties": {
    "iso:country":"DE",
    "sg:address":"Tannenbergstr 60",
    "sg:city":"Oberhausen",
    "sg:phone":"+49 208/859770",
    "sg:postcode":"46045",
    "sg:province":"Nordrhein-Westfalen",
    "wof:name":"L\u00f6sche Gmbh & Co",
    "wof:placetype":"venue"
},
  "geometry": {"coordinates":[6.860259,51.479321],"type":"Point"}
}