{
  "type": "Feature",
  "properties": {
    "iso:country":"DE",
    "sg:address":"Wilhelmsaue 34",
    "sg:city":"Berlin",
    "sg:phone":"+49 30/8213015",
    "sg:postcode":"10713",
    "sg:province":"Berlin",
    "wof:name":"Johannes Tabbert Jalousien Gmbh",
    "wof:placetype":"venue"
},
  "geometry": {"coordinates":[13.3182630539,52.4854202271],"type":"Point"}
}