{
  "type": "Feature",
  "properties": {
    "iso:country":"DE",
    "sg:address":"Hauptstr. 1",
    "sg:city":"B\u00f6nnigheim",
    "sg:postcode":"74357",
    "sg:province":"Baden-W\u00fcrttemberg",
    "wof:name":"Industrie-flug Ott Verwaltungs- Und",
    "wof:placetype":"venue"
},
  "geometry": {"coordinates":[9.093925,49.038998],"type":"Point"}
}