{
  "type": "Feature",
  "properties": {
    "iso:country":"DE",
    "sg:address":"Wallersheimer Weg 27",
    "sg:city":"Koblenz",
    "sg:phone":"+49 261/800428",
    "sg:postcode":"56070",
    "sg:province":"Rheinland-Pfalz",
    "wof:name":"Its Medizin Technik Systeme Gmbh",
    "wof:placetype":"venue"
},
  "geometry": {"coordinates":[7.596634,50.371113],"type":"Point"}
}