{
  "type": "Feature",
  "properties": {
    "iso:country":"DE",
    "sg:address":"Theodor-Storm-Weg 100",
    "sg:city":"Solingen",
    "sg:postcode":"42697",
    "sg:province":"Nordrhein-Westfalen",
    "wof:name":"M. Schmidt",
    "wof:placetype":"venue"
},
  "geometry": {"coordinates":[6.966598,51.165245],"type":"Point"}
}