{
  "type": "Feature",
  "properties": {
    "iso:country":"DE",
    "sg:address":"Molkereistr. 8",
    "sg:city":"Dortmund",
    "sg:phone":"+49 231/333438",
    "sg:postcode":"44359",
    "sg:province":"Nordrhein-Westfalen",
    "wof:name":"Textilpflegebetrieb Heinrich Klein",
    "wof:placetype":"venue"
},
  "geometry": {"coordinates":[7.3767318726,51.5705795288],"type":"Point"}
}