{
  "type": "Feature",
  "properties": {
    "iso:country":"DE",
    "sg:address":"Dinkelsb\u00fchler Str. 5",
    "sg:city":"Dentlein",
    "sg:phone":"+49 9855/9520",
    "sg:postcode":"91599",
    "sg:province":"Bayern",
    "wof:name":"Hauf Br\u00e4u Ohg",
    "wof:placetype":"venue"
},
  "geometry": {"coordinates":[10.422629,49.147366],"type":"Point"}
}