{
  "type": "Feature",
  "properties": {
    "iso:country":"DE",
    "sg:address":"Puschkinstr. 71",
    "sg:city":"Schwerin",
    "sg:phone":"+49 385/565956",
    "sg:postcode":"19055",
    "sg:province":"Mecklenburg-Vorpommern",
    "wof:name":"Althen & Claussen",
    "wof:placetype":"venue"
},
  "geometry": {"coordinates":[11.4148797989,53.6279716492],"type":"Point"}
}