{
  "type": "Feature",
  "properties": {
    "iso:country":"DE",
    "sg:address":"Eulenbergstr. 60",
    "sg:city":"Ellhofen",
    "sg:phone":"+49 7134/18505",
    "sg:postcode":"74248",
    "sg:province":"Baden-W\u00fcrttemberg",
    "wof:name":"Vereinsgastst\u00e4tte Tsv",
    "wof:placetype":"venue"
},
  "geometry": {"coordinates":[9.3290243149,49.1444282532],"type":"Point"}
}