{
  "type": "Feature",
  "properties": {
    "iso:country":"DE",
    "sg:address":"Am Heiligen Kreuz 20",
    "sg:city":"Celle",
    "sg:phone":"+49 5141/24080",
    "sg:postcode":"29221",
    "sg:province":"Niedersachsen",
    "wof:name":"R. Junke Vergn\u00fcgungsst\u00e4tte",
    "wof:placetype":"venue"
},
  "geometry": {"coordinates":[10.0858,52.624161],"type":"Point"}
}