{
  "type": "Feature",
  "properties": {
    "iso:country":"DE",
    "sg:address":"Wehldorfer Str. 13",
    "sg:city":"Beverstedt",
    "sg:phone":"+49 4747/8024",
    "sg:postcode":"27616",
    "sg:province":"Niedersachsen",
    "wof:name":"Senioren- Und Pflegeheim Christine Ehlen Gmbh",
    "wof:placetype":"venue"
},
  "geometry": {"coordinates":[8.822872,53.441582],"type":"Point"}
}