{
  "type": "Feature",
  "properties": {
    "iso:country":"DE",
    "sg:address":"Gustav-Throm-Str. 4",
    "sg:city":"Leimen",
    "sg:phone":"+49 8061/49990",
    "sg:postcode":"69181",
    "sg:province":"Baden-W\u00fcrttemberg",
    "wof:name":"Kneifel Werkzeugbau Gmbh",
    "wof:placetype":"venue"
},
  "geometry": {"coordinates":[11.992889,47.880116],"type":"Point"}
}