{
  "type": "Feature",
  "properties": {
    "iso:country":"DE",
    "sg:address":"Karlstr. 4",
    "sg:city":"Dillenburg",
    "sg:phone":"+49 2771/266220",
    "sg:postcode":"35683",
    "sg:province":"Hessen",
    "wof:name":"Electronic Service Gbrmbh",
    "wof:placetype":"venue"
},
  "geometry": {"coordinates":[8.2852554321,50.740940094],"type":"Point"}
}