{
  "type": "Feature",
  "properties": {
    "iso:country":"DE",
    "sg:address":"Karl-Liebknecht-Str. 35",
    "sg:city":"Jena",
    "sg:phone":"+49 3641/443989",
    "sg:postcode":"07749",
    "sg:province":"Th\u00fcringen",
    "wof:name":"Waffen Peters Gmbh",
    "wof:placetype":"venue"
},
  "geometry": {"coordinates":[11.601912,50.930164],"type":"Point"}
}