{
  "type": "Feature",
  "properties": {
    "iso:country":"DE",
    "sg:address":"B\u00f6blinger Str. 9",
    "sg:city":"Holzgerlingen",
    "sg:phone":"+49 7031/742500",
    "sg:postcode":"71088",
    "sg:province":"Baden-W\u00fcrttemberg",
    "wof:name":"Sch\u00f6nbuch-apotheke",
    "wof:placetype":"venue"
},
  "geometry": {"coordinates":[9.011471,48.640198],"type":"Point"}
}