{
  "type": "Feature",
  "properties": {
    "iso:country":"DE",
    "sg:address":"Weidenweg 29",
    "sg:city":"Esslingen",
    "sg:phone":"+49 711/375284",
    "sg:postcode":"73733",
    "sg:province":"Baden-W\u00fcrttemberg",
    "wof:name":"J\u00fcrgen Sindlinger Steuerberater",
    "wof:placetype":"venue"
},
  "geometry": {"coordinates":[9.2988023758,48.7585296631],"type":"Point"}
}