{
  "type": "Feature",
  "properties": {
    "iso:country":"DE",
    "sg:address":"Vossekuhlsweg 19",
    "sg:city":"Xanten",
    "sg:phone":"+49 2801/4811",
    "sg:postcode":"46509",
    "sg:province":"Nordrhein-Westfalen",
    "wof:name":"H\u00fclsken & Co.",
    "wof:placetype":"venue"
},
  "geometry": {"coordinates":[6.4456868172,51.6872062683],"type":"Point"}
}