{
  "type": "Feature",
  "properties": {
    "iso:country":"DE",
    "sg:address":"Gr\u00fcnepleistr. 73",
    "sg:city":"Roetgen",
    "sg:phone":"+49 2471/8386",
    "sg:postcode":"52159",
    "sg:province":"Nordrhein-Westfalen",
    "wof:name":"M. Dohlen",
    "wof:placetype":"venue"
},
  "geometry": {"coordinates":[6.2176828384,50.6428184509],"type":"Point"}
}