{
  "type": "Feature",
  "properties": {
    "iso:country":"DE",
    "sg:address":"Steinthalstr. 9",
    "sg:city":"N\u00fcrnberg",
    "sg:phone":"+49 911/884273",
    "sg:postcode":"90455",
    "sg:province":"Bayern",
    "wof:name":"Gisbert Neisser Architekt",
    "wof:placetype":"venue"
},
  "geometry": {"coordinates":[11.077955,49.374722],"type":"Point"}
}