{
  "type": "Feature",
  "properties": {
    "iso:country":"DE",
    "sg:address":"Lerchenstr. 72",
    "sg:city":"Stuttgart",
    "sg:phone":"+49 711/221392",
    "sg:postcode":"70176",
    "sg:province":"Baden-W\u00fcrttemberg",
    "wof:name":"Transportverleih Korn",
    "wof:placetype":"venue"
},
  "geometry": {"coordinates":[9.158346,48.780529],"type":"Point"}
}