{
  "type": "Feature",
  "properties": {
    "iso:country":"DE",
    "sg:address":"Friedrich-Ebert-Str. 51",
    "sg:city":"Markkleeberg",
    "sg:phone":"+49 341/3581294",
    "sg:postcode":"04416",
    "sg:province":"Sachsen",
    "wof:name":"Smi Softmark Informationstechnologien Gmbh",
    "wof:placetype":"venue"
},
  "geometry": {"coordinates":[12.371295929,51.2805480957],"type":"Point"}
}