{
  "type": "Feature",
  "properties": {
    "iso:country":"DE",
    "sg:address":"Hilker\u00f6der Str. 37",
    "sg:city":"Duderstadt",
    "sg:phone":"+49 5529/736",
    "sg:postcode":"37115",
    "sg:province":"Niedersachsen",
    "wof:name":"Franz-josef Henkel",
    "wof:placetype":"venue"
},
  "geometry": {"coordinates":[10.3106012344,51.5605049133],"type":"Point"}
}