{
  "type": "Feature",
  "properties": {
    "iso:country":"DE",
    "sg:address":"Lessingstr. 7",
    "sg:city":"Erkrath",
    "sg:phone":"+49 2104/40148",
    "sg:postcode":"40699",
    "sg:province":"Nordrhein-Westfalen",
    "wof:name":"Hans-peter Josting Steuerbevollm\u00e4chtigter",
    "wof:placetype":"venue"
},
  "geometry": {"coordinates":[6.9657931328,51.2032928467],"type":"Point"}
}