{
  "type": "Feature",
  "properties": {
    "iso:country":"DE",
    "sg:address":"L\u00fcbecker Str. 18",
    "sg:city":"Anklam",
    "sg:phone":"+49 3971/40345",
    "sg:postcode":"17389",
    "sg:province":"Mecklenburg-Vorpommern",
    "wof:name":"Hamburg Eggert Mineral\u00f6l- Handels Gmbh",
    "wof:placetype":"venue"
},
  "geometry": {"coordinates":[13.6829500198,53.8456115723],"type":"Point"}
}