{
  "type": "Feature",
  "properties": {
    "iso:country":"DE",
    "sg:address":"Steinstr. 2",
    "sg:city":"Boppard",
    "sg:phone":"+49 6742/1200",
    "sg:postcode":"56154",
    "sg:province":"Rheinland-Pfalz",
    "wof:name":"Joy-pob",
    "wof:placetype":"venue"
},
  "geometry": {"coordinates":[7.5938048363,50.2315597534],"type":"Point"}
}