{
  "type": "Feature",
  "properties": {
    "iso:country":"DE",
    "sg:address":"Dorfstr. 16",
    "sg:city":"Vissum",
    "sg:phone":"+49 39034/9649",
    "sg:postcode":"29416",
    "sg:province":"Sachsen-Anhalt",
    "wof:name":"Bernd Neumann",
    "wof:placetype":"venue"
},
  "geometry": {"coordinates":[11.356732,52.820415],"type":"Point"}
}