{
  "type": "Feature",
  "properties": {
    "iso:country":"DE",
    "sg:address":"Bachstr. 2",
    "sg:city":"Igling",
    "sg:phone":"+49 8241/4671",
    "sg:postcode":"86859",
    "sg:province":"Bayern",
    "wof:name":"Trautwein-verkehrs- Unternehmen- Gmbh",
    "wof:placetype":"venue"
},
  "geometry": {"coordinates":[10.780043602,48.0469551086],"type":"Point"}
}