{
  "type": "Feature",
  "properties": {
    "iso:country":"DE",
    "sg:address":"Ferdinand-Porsche-Str. 17",
    "sg:city":"K\u00f6ln",
    "sg:phone":"+49 2203/301992",
    "sg:postcode":"51149",
    "sg:province":"Nordrhein-Westfalen",
    "wof:name":"Knoll Gmbh & Co. Kg Heumar-beton",
    "wof:placetype":"venue"
},
  "geometry": {"coordinates":[7.0689277649,50.9032287598],"type":"Point"}
}