{
  "type": "Feature",
  "properties": {
    "iso:country":"DE",
    "sg:address":"Kettenstr. 3",
    "sg:city":"Erfurt",
    "sg:phone":"+49 361/5667954",
    "sg:postcode":"99084",
    "sg:province":"Th\u00fcringen",
    "wof:name":"Institut F\u00fcr Moderne Kosmetik Gmbh",
    "wof:placetype":"venue"
},
  "geometry": {"coordinates":[11.025695,50.976471],"type":"Point"}
}