{
  "type": "Feature",
  "properties": {
    "iso:country":"DE",
    "sg:address":"Robert-Blum-Str. 14",
    "sg:city":"Neubrandenburg",
    "sg:phone":"+49 395/5666108",
    "sg:postcode":"17033",
    "sg:province":"Mecklenburg-Vorpommern",
    "wof:name":"Schefferski & Wiese Antiquit\u00e4ten-restaurierung",
    "wof:placetype":"venue"
},
  "geometry": {"coordinates":[13.252053,53.561611],"type":"Point"}
}