{
  "type": "Feature",
  "properties": {
    "iso:country":"DE",
    "sg:address":"Weidenweg 06",
    "sg:city":"Salzwedel",
    "sg:phone":"+49 3901/472339",
    "sg:postcode":"29410",
    "sg:province":"Sachsen-Anhalt",
    "wof:name":"Cash - Informationsdienst",
    "wof:placetype":"venue"
},
  "geometry": {"coordinates":[11.177569,52.842556],"type":"Point"}
}