{
  "type": "Feature",
  "properties": {
    "iso:country":"DE",
    "sg:address":"An der Packhalle IX 40",
    "sg:city":"Bremerhaven",
    "sg:postcode":"27572",
    "sg:province":"Bremen",
    "wof:name":"Abs Fischexpress Gmbh",
    "wof:placetype":"venue"
},
  "geometry": {"coordinates":[8.5879268646,53.5165061951],"type":"Point"}
}