{
  "type": "Feature",
  "properties": {
    "iso:country":"DE",
    "sg:address":"Eibseestr. 18",
    "sg:city":"Augsburg",
    "sg:phone":"+49 821/64041",
    "sg:postcode":"86163",
    "sg:province":"Bayern",
    "wof:name":"Traugott Geyer Architekt",
    "wof:placetype":"venue"
},
  "geometry": {"coordinates":[10.941502,48.363548],"type":"Point"}
}