{
  "type": "Feature",
  "properties": {
    "iso:country":"DE",
    "sg:address":"Neuenkirchener Str. 10",
    "sg:city":"Spenge",
    "sg:phone":"+49 5225/3387",
    "sg:postcode":"32139",
    "sg:province":"Nordrhein-Westfalen",
    "wof:name":"W. Gorges",
    "wof:placetype":"venue"
},
  "geometry": {"coordinates":[8.4834,52.149361],"type":"Point"}
}