{
  "type": "Feature",
  "properties": {
    "iso:country":"DE",
    "sg:address":"Kupferdreher Markt 2",
    "sg:city":"Essen",
    "sg:phone":"+49 201/483616",
    "sg:postcode":"45257",
    "sg:province":"Nordrhein-Westfalen",
    "wof:name":"R. A. Stratmann",
    "wof:placetype":"venue"
},
  "geometry": {"coordinates":[7.08191,51.391151],"type":"Point"}
}