{
  "type": "Feature",
  "properties": {
    "iso:country":"DE",
    "sg:address":"Oeslauer Str. 2",
    "sg:city":"R\u00f6dental",
    "sg:phone":"+49 9563/9060",
    "sg:postcode":"96472",
    "sg:province":"Bayern",
    "wof:name":"M\u00f6bel Hofmann Einrichtungshaus Gmbh",
    "wof:placetype":"venue"
},
  "geometry": {"coordinates":[11.044210434,50.2940292358],"type":"Point"}
}