{
  "type": "Feature",
  "properties": {
    "iso:country":"DE",
    "sg:address":"Zum M\u00fchlenbruch 11",
    "sg:city":"Hermannsburg",
    "sg:phone":"+49 5052/2221",
    "sg:postcode":"29320",
    "sg:province":"Niedersachsen",
    "wof:name":"Ernst Lange",
    "wof:placetype":"venue"
},
  "geometry": {"coordinates":[10.133881,52.836555],"type":"Point"}
}