{
  "type": "Feature",
  "properties": {
    "iso:country":"DE",
    "sg:address":"Hamburger Allee 39",
    "sg:city":"Frankfurt",
    "sg:phone":"+49 69/7078687",
    "sg:postcode":"60486",
    "sg:province":"Hessen",
    "wof:name":"Multivisio Kommunikations- Gmbh",
    "wof:placetype":"venue"
},
  "geometry": {"coordinates":[8.6456441879,50.1158103943],"type":"Point"}
}