{
  "type": "Feature",
  "properties": {
    "iso:country":"DE",
    "sg:address":"Konstantinstr. 14",
    "sg:city":"Bonn",
    "sg:phone":"+49 228/362569",
    "sg:postcode":"53179",
    "sg:province":"Nordrhein-Westfalen",
    "wof:name":"Arenz Und Pfister",
    "wof:placetype":"venue"
},
  "geometry": {"coordinates":[7.1696968079,50.6834831238],"type":"Point"}
}