{
  "type": "Feature",
  "properties": {
    "iso:country":"DE",
    "sg:address":"Aspastr. 19",
    "sg:city":"Nordkirchen",
    "sg:phone":"+49 4925/9697090",
    "sg:postcode":"59394",
    "sg:province":"Nordrhein-Westfalen",
    "wof:name":"Walter Laarmann Gmbh",
    "wof:placetype":"venue"
},
  "geometry": {"coordinates":[7.5150980949,51.7400627136],"type":"Point"}
}