{
  "type": "Feature",
  "properties": {
    "iso:country":"DE",
    "sg:address":"Gewerbegrund 7",
    "sg:city":"Harrislee",
    "sg:phone":"+49 461/72072",
    "sg:postcode":"24955",
    "sg:province":"Schleswig-Holstein",
    "wof:name":"Kompan Gmbh",
    "wof:placetype":"venue"
},
  "geometry": {"coordinates":[9.3742704391,54.8031349182],"type":"Point"}
}