{
  "type": "Feature",
  "properties": {
    "iso:country":"DE",
    "sg:address":"Gallberger Weg 38",
    "sg:city":"Hamm",
    "sg:phone":"+49 2381/953105",
    "sg:postcode":"59063",
    "sg:province":"Nordrhein-Westfalen",
    "wof:name":"A. H. G. Allgemeine Handelsge- Sellschaft F\u00fcr Haushalts-",
    "wof:placetype":"venue"
},
  "geometry": {"coordinates":[7.8124408722,51.6632919312],"type":"Point"}
}