{
  "type": "Feature",
  "properties": {
    "iso:country":"DE",
    "sg:address":"Moislinger Allee 99",
    "sg:city":"L\u00fcbeck",
    "sg:postcode":"23558",
    "sg:province":"Schleswig-Holstein",
    "wof:name":"G\u00fcltepe Baustahlarmierung Zwndl. Deutschland Der G\u00fcltepe",
    "wof:placetype":"venue"
},
  "geometry": {"coordinates":[10.6592330933,53.8510818481],"type":"Point"}
}