{
  "type": "Feature",
  "properties": {
    "iso:country":"DE",
    "sg:address":"Finkenweg 1",
    "sg:city":"Langen",
    "sg:phone":"+49 6103/976865",
    "sg:postcode":"63225",
    "sg:province":"Hessen",
    "wof:name":"G\u00fcnter Dietzig",
    "wof:placetype":"venue"
},
  "geometry": {"coordinates":[8.5938749313,53.6114234924],"type":"Point"}
}