{
  "type": "Feature",
  "properties": {
    "iso:country":"DE",
    "sg:city":"Monsheim",
    "sg:phone":"+49 6243/905510",
    "sg:postcode":"67590",
    "sg:province":"Rheinland-Pfalz",
    "wof:name":"Cyberface",
    "wof:placetype":"venue"
},
  "geometry": {"coordinates":[8.204541,49.636501],"type":"Point"}
}