{
  "type": "Feature",
  "properties": {
    "iso:country":"DE",
    "sg:address":"Alexanderstr. 63a",
    "sg:city":"Stuttgart",
    "sg:phone":"+49 711/246736",
    "sg:postcode":"70182",
    "sg:province":"Baden-W\u00fcrttemberg",
    "wof:name":"Gerold K\u00fcster Rechtsanwalt",
    "wof:placetype":"venue"
},
  "geometry": {"coordinates":[9.1850175858,48.7722206116],"type":"Point"}
}