{
  "type": "Feature",
  "properties": {
    "iso:country":"DE",
    "sg:address":"Heideweg 4",
    "sg:city":"Braunschweig",
    "sg:phone":"+49 531/860083",
    "sg:postcode":"38120",
    "sg:province":"Niedersachsen",
    "wof:name":"Milko Guschmann Versicherungen",
    "wof:placetype":"venue"
},
  "geometry": {"coordinates":[10.4473419189,52.2395515442],"type":"Point"}
}