{
  "type": "Feature",
  "properties": {
    "iso:country":"DE",
    "sg:address":"Dorfstr. 6",
    "sg:city":"Sch\u00f6nefeld",
    "sg:phone":"+49 30/6332425",
    "sg:postcode":"12529",
    "sg:province":"Brandenburg",
    "wof:name":"Ulf Dunkel",
    "wof:placetype":"venue"
},
  "geometry": {"coordinates":[13.46122,52.373821],"type":"Point"}
}