{
  "type": "Feature",
  "properties": {
    "iso:country":"DE",
    "sg:address":"Kohlplattenstr. 28",
    "sg:city":"Walzbachtal",
    "sg:phone":"+49 7203/7447",
    "sg:postcode":"75045",
    "sg:province":"Baden-W\u00fcrttemberg",
    "wof:name":"H. Bayha Gmbh",
    "wof:placetype":"venue"
},
  "geometry": {"coordinates":[8.6126260757,49.0041122437],"type":"Point"}
}