{
  "type": "Feature",
  "properties": {
    "iso:country":"DE",
    "sg:address":"Kaiserstr. 29",
    "sg:city":"Bad Sassendorf",
    "sg:phone":"+49 2921/5836",
    "sg:postcode":"59505",
    "sg:province":"Nordrhein-Westfalen",
    "wof:name":"Gudio Rehkemper",
    "wof:placetype":"venue"
},
  "geometry": {"coordinates":[8.1658182144,51.5875854492],"type":"Point"}
}