{
  "type": "Feature",
  "properties": {
    "iso:country":"DE",
    "sg:address":"Neubourgstr. 2",
    "sg:city":"Stade",
    "sg:phone":"+49 4141/3757",
    "sg:postcode":"21682",
    "sg:province":"Niedersachsen",
    "wof:name":"Heidrun Ziehm-kossatz",
    "wof:placetype":"venue"
},
  "geometry": {"coordinates":[9.4744510651,53.5977401733],"type":"Point"}
}