{
  "type": "Feature",
  "properties": {
    "iso:country":"DE",
    "sg:address":"Schwenninger Str. 45",
    "sg:city":"Stetten",
    "sg:phone":"+49 7573/2681",
    "sg:postcode":"72510",
    "sg:province":"Baden-W\u00fcrttemberg",
    "wof:name":"Haus Silberdistel",
    "wof:placetype":"venue"
},
  "geometry": {"coordinates":[9.071291,48.120407],"type":"Point"}
}