{
  "type": "Feature",
  "properties": {
    "iso:country":"DE",
    "sg:address":"Floriansweg 3",
    "sg:city":"Elchingen",
    "sg:postcode":"89275",
    "sg:province":"Bayern",
    "wof:name":"Bautec-bautechnischer Fachgro\u00dfhandel Gmbh",
    "wof:placetype":"venue"
},
  "geometry": {"coordinates":[10.0855445862,48.4488067627],"type":"Point"}
}