{
  "type": "Feature",
  "properties": {
    "iso:country":"DE",
    "sg:address":"S\u00fcdermarren 45",
    "sg:city":"Nordholz",
    "sg:phone":"+49 4741/1474",
    "sg:postcode":"27637",
    "sg:province":"Niedersachsen",
    "wof:name":"Albert Bothe",
    "wof:placetype":"venue"
},
  "geometry": {"coordinates":[8.599281,53.744736],"type":"Point"}
}