{
  "type": "Feature",
  "properties": {
    "iso:country":"DE",
    "sg:address":"Hauptstr. 13",
    "sg:city":"Nohen",
    "sg:phone":"+49 6789/841",
    "sg:postcode":"55767",
    "sg:province":"Rheinland-Pfalz",
    "wof:name":"Bahnhof",
    "wof:placetype":"venue"
},
  "geometry": {"coordinates":[7.2423648834,49.6395568848],"type":"Point"}
}