{
  "type": "Feature",
  "properties": {
    "iso:country":"DE",
    "sg:address":"Rumfordstr. 47",
    "sg:city":"M\u00fcnchen",
    "sg:phone":"+49 89/2606333",
    "sg:postcode":"80469",
    "sg:province":"Bayern",
    "wof:name":"Abg Finanz- Und Versicherungs- Makler Gmbh",
    "wof:placetype":"venue"
},
  "geometry": {"coordinates":[11.581317,48.133915],"type":"Point"}
}