{
  "type": "Feature",
  "properties": {
    "iso:country":"DE",
    "sg:address":"Arzbergweg 1",
    "sg:city":"Hersbruck",
    "sg:phone":"+49 9151/2284",
    "sg:postcode":"91217",
    "sg:province":"Bayern",
    "wof:name":"Pizzeria Zucca-barucca",
    "wof:placetype":"venue"
},
  "geometry": {"coordinates":[11.4387407303,49.5010643005],"type":"Point"}
}