{
  "type": "Feature",
  "properties": {
    "iso:country":"DE",
    "sg:address":"Im Lindental 26",
    "sg:city":"Hagen",
    "sg:phone":"+49 4923/3148140",
    "sg:postcode":"58135",
    "sg:province":"Nordrhein-Westfalen",
    "wof:name":"Hfs Hagener Feinblech Service Gmbh",
    "wof:placetype":"venue"
},
  "geometry": {"coordinates":[7.425259,51.353348],"type":"Point"}
}