{
  "type": "Feature",
  "properties": {
    "iso:country":"DE",
    "sg:address":"Hagenstr. 40",
    "sg:city":"Worms",
    "sg:phone":"+49 6241/925830",
    "sg:postcode":"67547",
    "sg:province":"Rheinland-Pfalz",
    "wof:name":"Friedrich Scheubeck",
    "wof:placetype":"venue"
},
  "geometry": {"coordinates":[8.365557,49.628334],"type":"Point"}
}