{
  "type": "Feature",
  "properties": {
    "iso:country":"DE",
    "sg:address":"Stocken",
    "sg:city":"Vogt",
    "sg:phone":"+49 7506/268",
    "sg:postcode":"88267",
    "sg:province":"Baden-W\u00fcrttemberg",
    "wof:name":"Gastst\u00e4tte Anton Sch\u00fcle",
    "wof:placetype":"venue"
},
  "geometry": {"coordinates":[9.7919902802,47.7704811096],"type":"Point"}
}