{
  "type": "Feature",
  "properties": {
    "iso:country":"DE",
    "sg:address":"Ammerlandallee 4",
    "sg:city":"Westerstede",
    "sg:phone":"+49 4488/52920",
    "sg:postcode":"26655",
    "sg:province":"Niedersachsen",
    "wof:name":"Thomas Wolkenhauer Verm\u00f6gensverwaltungs",
    "wof:placetype":"venue"
},
  "geometry": {"coordinates":[7.937497139,53.259147644],"type":"Point"}
}