{
  "type": "Feature",
  "properties": {
    "iso:country":"DE",
    "sg:address":"Hauptstr. 1",
    "sg:city":"Epfenbach",
    "sg:phone":"+49 7263/5373",
    "sg:postcode":"74925",
    "sg:province":"Baden-W\u00fcrttemberg",
    "wof:name":"Friedrich Ernst",
    "wof:placetype":"venue"
},
  "geometry": {"coordinates":[8.913383,49.337509],"type":"Point"}
}