{
  "type": "Feature",
  "properties": {
    "iso:country":"DE",
    "sg:address":"Beuditzstr. 57",
    "sg:city":"Wei\u00dfenfels",
    "sg:phone":"+49 3443/305243",
    "sg:postcode":"06667",
    "sg:province":"Sachsen-Anhalt",
    "wof:name":"J\u00fcrgen Gloser",
    "wof:placetype":"venue"
},
  "geometry": {"coordinates":[11.9585866928,51.1999702454],"type":"Point"}
}