{
  "type": "Feature",
  "properties": {
    "iso:country":"DE",
    "sg:address":"Osterweide 8",
    "sg:city":"L\u00fcbeck",
    "sg:postcode":"23562",
    "sg:province":"Schleswig-Holstein",
    "wof:name":"Ulrich Biemann Verm\u00f6gensverwaltungs-gmbh",
    "wof:placetype":"venue"
},
  "geometry": {"coordinates":[10.7107906342,53.8404541016],"type":"Point"}
}