{
  "type": "Feature",
  "properties": {
    "iso:country":"DE",
    "sg:address":"R\u00f6merstr. 18",
    "sg:city":"Bad Kreuznach",
    "sg:phone":"+49 671/45206",
    "sg:postcode":"55543",
    "sg:province":"Rheinland-Pfalz",
    "wof:name":"Borchmeyer",
    "wof:placetype":"venue"
},
  "geometry": {"coordinates":[7.861609,49.843399],"type":"Point"}
}