{
  "type": "Feature",
  "properties": {
    "iso:country":"DE",
    "sg:address":"Carl-Zeiss-Str. 80",
    "sg:city":"Aalen",
    "sg:phone":"+49 7361/948071",
    "sg:postcode":"73431",
    "sg:province":"Baden-W\u00fcrttemberg",
    "wof:name":"Rossaro Kanaltechnik Gmbh & Co. Kg",
    "wof:placetype":"venue"
},
  "geometry": {"coordinates":[10.0609769821,48.8241386414],"type":"Point"}
}