{
  "type": "Feature",
  "properties": {
    "iso:country":"DE",
    "sg:address":"Hans-Sailer-Str. 81",
    "sg:city":"Erfurt",
    "sg:phone":"+49 361/7360289",
    "sg:postcode":"99089",
    "sg:province":"Th\u00fcringen",
    "wof:name":"Prokommunal Baugrund Und Projekt Gmbh",
    "wof:placetype":"venue"
},
  "geometry": {"coordinates":[11.023785,50.995804],"type":"Point"}
}