{
  "type": "Feature",
  "properties": {
    "iso:country":"DE",
    "sg:address":"Ferdinandstr. 2",
    "sg:city":"Ennigerloh",
    "sg:phone":"+49 2524/4003",
    "sg:postcode":"59320",
    "sg:province":"Nordrhein-Westfalen",
    "wof:name":"A. L\u00fcck",
    "wof:placetype":"venue"
},
  "geometry": {"coordinates":[8.0403699875,51.8464927673],"type":"Point"}
}