{
  "type": "Feature",
  "properties": {
    "iso:country":"DE",
    "sg:address":"Westring 34",
    "sg:city":"Eschwege",
    "sg:phone":"+49 5651/13910",
    "sg:postcode":"37269",
    "sg:province":"Hessen",
    "wof:name":"Signaplast Inh. Walter Sandner",
    "wof:placetype":"venue"
},
  "geometry": {"coordinates":[10.033696,51.18985],"type":"Point"}
}