{
  "type": "Feature",
  "properties": {
    "iso:country":"DE",
    "sg:address":"Harrasallee 20",
    "sg:city":"Niederwiesa",
    "sg:postcode":"09577",
    "sg:province":"Sachsen",
    "wof:name":"F1gaming-zone",
    "wof:placetype":"venue"
},
  "geometry": {"coordinates":[13.014941,50.88081],"type":"Point"}
}