{
  "type": "Feature",
  "properties": {
    "iso:country":"DE",
    "sg:address":"Nehringstr. 7",
    "sg:city":"Bad Homburg",
    "sg:phone":"+49 6172/100482",
    "sg:postcode":"61352",
    "sg:province":"Hessen",
    "wof:name":"Stadtreinigungsamt",
    "wof:placetype":"venue"
},
  "geometry": {"coordinates":[8.6179943085,50.2157859802],"type":"Point"}
}