{
  "type": "Feature",
  "properties": {
    "iso:country":"DE",
    "sg:address":"Niederrheinstr. 12",
    "sg:city":"D\u00fcsseldorf",
    "sg:postcode":"40474",
    "sg:province":"Nordrhein-Westfalen",
    "wof:name":"Tthu Technologietransfer Heinr. Heine Universit\u00e4t Gmbh",
    "wof:placetype":"venue"
},
  "geometry": {"coordinates":[6.748371,51.268566],"type":"Point"}
}