{
  "type": "Feature",
  "properties": {
    "iso:country":"DE",
    "sg:address":"Dilsberger Str. 2",
    "sg:city":"Neckargem\u00fcnd",
    "sg:phone":"+49 6223/80471",
    "sg:postcode":"69151",
    "sg:province":"Baden-W\u00fcrttemberg",
    "wof:name":"Stadtwerke Neckargem\u00fcnd",
    "wof:placetype":"venue"
},
  "geometry": {"coordinates":[8.801656,49.393471],"type":"Point"}
}