{
  "type": "Feature",
  "properties": {
    "iso:country":"DE",
    "sg:address":"Gartenstr. 28",
    "sg:city":"Kirchheim",
    "sg:phone":"+49 7021/957833",
    "sg:postcode":"73230",
    "sg:province":"Baden-W\u00fcrttemberg",
    "wof:name":"M. Fehrle",
    "wof:placetype":"venue"
},
  "geometry": {"coordinates":[9.4838123322,48.6144981384],"type":"Point"}
}