{
  "type": "Feature",
  "properties": {
    "iso:country":"DE",
    "sg:address":"Kettelerstr. 46",
    "sg:city":"Insheim",
    "sg:phone":"+49 6341/88143",
    "sg:postcode":"76865",
    "sg:province":"Rheinland-Pfalz",
    "wof:name":"Willi Paul",
    "wof:placetype":"venue"
},
  "geometry": {"coordinates":[8.13812,49.155048],"type":"Point"}
}