{
  "type": "Feature",
  "properties": {
    "iso:country":"DE",
    "sg:address":"Mainzer Str. 92",
    "sg:city":"Gau-Odernheim",
    "sg:phone":"+49 6733/6957",
    "sg:postcode":"55239",
    "sg:province":"Rheinland-Pfalz",
    "wof:name":"Dr. Med. Hellmuth Kneip Arzt F\u00fcr Arbeitsmedizin",
    "wof:placetype":"venue"
},
  "geometry": {"coordinates":[8.1853046417,49.7871055603],"type":"Point"}
}