{
  "type": "Feature",
  "properties": {
    "iso:country":"DE",
    "sg:address":"Obere Wiesen",
    "sg:city":"Spaichingen",
    "sg:postcode":"78549",
    "sg:province":"Baden-W\u00fcrttemberg",
    "wof:name":"Grosso",
    "wof:placetype":"venue"
},
  "geometry": {"coordinates":[8.7500238419,48.068195343],"type":"Point"}
}