{
  "type": "Feature",
  "properties": {
    "iso:country":"DE",
    "sg:address":"Otto-Wels-Str. 1a",
    "sg:city":"Hanau",
    "sg:phone":"+49 6181/13081",
    "sg:postcode":"63452",
    "sg:province":"Hessen",
    "wof:name":"Texscan Gmbh",
    "wof:placetype":"venue"
},
  "geometry": {"coordinates":[8.9248857498,50.1401443481],"type":"Point"}
}