{
  "type": "Feature",
  "properties": {
    "iso:country":"DE",
    "sg:city":"Pinache",
    "sg:phone":"+49 4970/4143666",
    "sg:postcode":"75446",
    "sg:province":"Baden-W\u00fcrttemberg",
    "wof:name":"Sparkasse Pforzheim",
    "wof:placetype":"venue"
},
  "geometry": {"coordinates":[8.848645,48.909439],"type":"Point"}
}