{
  "type": "Feature",
  "properties": {
    "iso:country":"DE",
    "sg:address":"K\u00f6thener Str. 27",
    "sg:city":"Aken",
    "sg:postcode":"06385",
    "sg:province":"Sachsen-Anhalt",
    "wof:name":"W. Lurch",
    "wof:placetype":"venue"
},
  "geometry": {"coordinates":[12.0442228317,51.8536491394],"type":"Point"}
}