{
  "type": "Feature",
  "properties": {
    "iso:country":"DE",
    "sg:address":"Bendenweg 39",
    "sg:city":"Bonn",
    "sg:phone":"+49 228/264189",
    "sg:postcode":"53121",
    "sg:province":"Nordrhein-Westfalen",
    "wof:name":"S. Soeding Rechtsanwalt",
    "wof:placetype":"venue"
},
  "geometry": {"coordinates":[7.0512747765,50.7377357483],"type":"Point"}
}