{
  "type": "Feature",
  "properties": {
    "iso:country":"DE",
    "sg:address":"Hauptstr. 8",
    "sg:city":"Langwedel",
    "sg:phone":"+49 4232/1506",
    "sg:postcode":"27299",
    "sg:province":"Niedersachsen",
    "wof:name":"Jochen Zersin Rechtsanwalt",
    "wof:placetype":"venue"
},
  "geometry": {"coordinates":[9.1827774048,52.9769172668],"type":"Point"}
}