{
  "type": "Feature",
  "properties": {
    "iso:country":"DE",
    "sg:address":"Am Dorfteich 15",
    "sg:city":"Fiefbergen",
    "sg:postcode":"24217",
    "sg:province":"Schleswig-Holstein",
    "wof:name":"H. W. Baugesellschaft Mbh & Co.",
    "wof:placetype":"venue"
},
  "geometry": {"coordinates":[10.342023,54.379845],"type":"Point"}
}