{
  "type": "Feature",
  "properties": {
    "iso:country":"DE",
    "sg:address":"Bakkerstr",
    "sg:city":"Borkum",
    "sg:phone":"+49 4922/1010",
    "sg:postcode":"26757",
    "sg:province":"Niedersachsen",
    "wof:name":"Borkum Urlaub - Hotel",
    "wof:placetype":"venue"
},
  "geometry": {"coordinates":[6.6743278503,53.5939102173],"type":"Point"}
}