{
  "type": "Feature",
  "properties": {
    "iso:country":"DE",
    "sg:address":"An der Schmiede 17",
    "sg:city":"Quickborn",
    "sg:phone":"+49 4106/773654",
    "sg:postcode":"25451",
    "sg:province":"Schleswig-Holstein",
    "wof:name":"Peter Zinke",
    "wof:placetype":"venue"
},
  "geometry": {"coordinates":[9.93318,53.74958],"type":"Point"}
}