{
  "type": "Feature",
  "properties": {
    "iso:country":"DE",
    "sg:address":"Am Schafgraben 29",
    "sg:city":"Gera",
    "sg:phone":"+49 365/35971",
    "sg:postcode":"07551",
    "sg:province":"Th\u00fcringen",
    "wof:name":"W. Pickl",
    "wof:placetype":"venue"
},
  "geometry": {"coordinates":[12.0942640305,50.8452453613],"type":"Point"}
}