{
  "type": "Feature",
  "properties": {
    "iso:country":"DE",
    "sg:address":"Fichtenweg 22",
    "sg:city":"Hufschlag",
    "sg:postcode":"83359",
    "wof:name":"Bk Projekt Gmbh",
    "wof:placetype":"venue"
},
  "geometry": {"coordinates":[12.667413,47.874722],"type":"Point"}
}