{
  "type": "Feature",
  "properties": {
    "iso:country":"DE",
    "sg:address":"Bahnhofstr. 49",
    "sg:city":"Fl\u00f6rsheim",
    "sg:phone":"+49 6145/6130",
    "sg:postcode":"65439",
    "sg:province":"Hessen",
    "wof:name":"Willi Habeth",
    "wof:placetype":"venue"
},
  "geometry": {"coordinates":[8.4321537018,50.017616272],"type":"Point"}
}