{
  "type": "Feature",
  "properties": {
    "iso:country":"DE",
    "sg:address":"Anholter Str.",
    "sg:city":"Isselburg",
    "sg:phone":"+49 2874/2038",
    "sg:postcode":"46419",
    "sg:province":"Nordrhein-Westfalen",
    "wof:name":"Schweizerhaus",
    "wof:placetype":"venue"
},
  "geometry": {"coordinates":[6.4236149788,51.8320541382],"type":"Point"}
}