{
  "type": "Feature",
  "properties": {
    "iso:country":"DE",
    "sg:city":"Schuttertal",
    "sg:phone":"+49 4978/232585",
    "sg:postcode":"77978",
    "sg:province":"Baden-W\u00fcrttemberg",
    "wof:name":"Sparkasse Lahr-ettenheim",
    "wof:placetype":"venue"
},
  "geometry": {"coordinates":[7.955626,48.270874],"type":"Point"}
}