{
  "type": "Feature",
  "properties": {
    "iso:country":"DE",
    "sg:address":"Hannoversche Str. 6",
    "sg:city":"Seelze",
    "sg:phone":"+49 5137/3409",
    "sg:postcode":"30926",
    "sg:province":"Niedersachsen",
    "wof:name":"P. Lemcke",
    "wof:placetype":"venue"
},
  "geometry": {"coordinates":[9.591449,52.396584],"type":"Point"}
}