{
  "type": "Feature",
  "properties": {
    "iso:country":"DE",
    "sg:address":"Ranntalstr. 8",
    "sg:city":"Remchingen",
    "sg:phone":"+49 7232/79118",
    "sg:postcode":"75196",
    "sg:province":"Baden-W\u00fcrttemberg",
    "wof:name":"Elisabeth Sch\u00e4fer",
    "wof:placetype":"venue"
},
  "geometry": {"coordinates":[8.5740089417,48.9292564392],"type":"Point"}
}