{
  "type": "Feature",
  "properties": {
    "iso:country":"DE",
    "sg:address":"H\u00f6chberger Str. 1",
    "sg:city":"Waldb\u00fcttelbrunn",
    "sg:phone":"+49 931/409001",
    "sg:postcode":"97297",
    "sg:province":"Bayern",
    "wof:name":"Kreissparkasse W\u00fcrzburg",
    "wof:placetype":"venue"
},
  "geometry": {"coordinates":[9.843357,49.788036],"type":"Point"}
}