{
  "type": "Feature",
  "properties": {
    "iso:country":"DE",
    "sg:address":"Industriestr 5",
    "sg:city":"Gummersbach",
    "sg:phone":"+49 2261/29080",
    "sg:postcode":"51643",
    "sg:province":"Nordrhein-Westfalen",
    "wof:name":"Rothstein Sondermaschinen Gmbh",
    "wof:placetype":"venue"
},
  "geometry": {"coordinates":[7.572677,51.021618],"type":"Point"}
}