{
  "type": "Feature",
  "properties": {
    "iso:country":"DE",
    "sg:address":"Eglseestr. 1",
    "sg:city":"Pinzberg",
    "sg:phone":"+49 9191/60578",
    "sg:postcode":"91361",
    "sg:province":"Bayern",
    "wof:name":"Lorenz Heilmann",
    "wof:placetype":"venue"
},
  "geometry": {"coordinates":[11.100581,49.690506],"type":"Point"}
}