{
  "type": "Feature",
  "properties": {
    "iso:country":"DE",
    "sg:address":"Am Markt 4",
    "sg:city":"Schwanewede",
    "sg:phone":"+49 4209/5516",
    "sg:postcode":"28790",
    "sg:province":"Niedersachsen",
    "wof:name":"Martina Stelter Masseurin",
    "wof:placetype":"venue"
},
  "geometry": {"coordinates":[8.595972,53.222958],"type":"Point"}
}