{
  "type": "Feature",
  "properties": {
    "iso:country":"DE",
    "sg:address":"Hegelstr. 20 POSTFACH 1554",
    "sg:city":"Kirchheim",
    "sg:phone":"+49 4970/215080",
    "sg:postcode":"73223",
    "sg:province":"Bayern",
    "wof:name":"Siemens Ag",
    "wof:placetype":"venue"
},
  "geometry": {"coordinates":[9.46548,48.646412],"type":"Point"}
}