{
  "type": "Feature",
  "properties": {
    "iso:country":"DE",
    "sg:address":"Hohensteiner Str. 1",
    "sg:city":"Stollberg",
    "sg:phone":"+49 37296/4110",
    "sg:postcode":"09366",
    "sg:province":"Sachsen",
    "wof:name":"Stumpf Und Partner Rechtanw\u00e4lte",
    "wof:placetype":"venue"
},
  "geometry": {"coordinates":[12.7782516479,50.7086296082],"type":"Point"}
}