{
  "type": "Feature",
  "properties": {
    "iso:country":"DE",
    "sg:address":"Ziegenhorn 1",
    "sg:city":"Karow",
    "sg:phone":"+49 38738/70292",
    "sg:postcode":"19395",
    "sg:province":"Mecklenburg-Vorpommern",
    "wof:name":"Naturpark Nossentiner- Schwinzer Heide",
    "wof:placetype":"venue"
},
  "geometry": {"coordinates":[12.282623,53.529713],"type":"Point"}
}