{
  "type": "Feature",
  "properties": {
    "iso:country":"DE",
    "sg:address":"Sonnenleite 3",
    "sg:city":"Rottenburg",
    "sg:phone":"+49 8781/1233",
    "sg:postcode":"84056",
    "sg:province":"Bayern",
    "wof:name":"J. Limmer",
    "wof:placetype":"venue"
},
  "geometry": {"coordinates":[12.081240654,48.7412796021],"type":"Point"}
}