{
  "type": "Feature",
  "properties": {
    "iso:country":"DE",
    "sg:address":"Brandbruchstr. 36",
    "sg:city":"Dortmund",
    "sg:phone":"+49 231/47127",
    "sg:postcode":"44265",
    "sg:province":"Nordrhein-Westfalen",
    "wof:name":"Wassweiler Und Partner Gmbh",
    "wof:placetype":"venue"
},
  "geometry": {"coordinates":[7.492834,51.446377],"type":"Point"}
}