{
  "type": "Feature",
  "properties": {
    "iso:country":"DE",
    "sg:address":"Rittnertstr. 45",
    "sg:city":"Pfinztal",
    "sg:phone":"+49 7240/942420",
    "sg:postcode":"76327",
    "sg:province":"Baden-W\u00fcrttemberg",
    "wof:name":"D. Mall Immobilienmakler",
    "wof:placetype":"venue"
},
  "geometry": {"coordinates":[8.5404100418,48.9825172424],"type":"Point"}
}