{
  "type": "Feature",
  "properties": {
    "iso:country":"DE",
    "sg:city":"Harsefeld",
    "sg:phone":"+49 4164/1344",
    "sg:postcode":"21698",
    "sg:province":"Niedersachsen",
    "wof:name":"Rainer Marciniak B\u00e4ckerei",
    "wof:placetype":"venue"
},
  "geometry": {"coordinates":[9.50225,53.452637],"type":"Point"}
}