{
  "type": "Feature",
  "properties": {
    "iso:country":"DE",
    "sg:address":"Gartenstr. 4",
    "sg:city":"Damme",
    "sg:phone":"+49 5491/4033",
    "sg:postcode":"49401",
    "sg:province":"Niedersachsen",
    "wof:name":"Bildungswerk Damme E. V.",
    "wof:placetype":"venue"
},
  "geometry": {"coordinates":[8.1981229782,52.5213127136],"type":"Point"}
}