{
  "type": "Feature",
  "properties": {
    "iso:country":"DE",
    "sg:address":"Kurt-Hein-Str. 23",
    "sg:city":"Mei\u00dfen",
    "sg:phone":"+49 3521/731619",
    "sg:postcode":"01662",
    "sg:province":"Sachsen",
    "wof:name":"Heike Odparlik Heilpraktikerin",
    "wof:placetype":"venue"
},
  "geometry": {"coordinates":[13.4869432449,51.1619148254],"type":"Point"}
}