{
  "type": "Feature",
  "properties": {
    "iso:country":"DE",
    "sg:address":"Gewerbestr. 1a",
    "sg:city":"Gundelfingen",
    "sg:phone":"+49 761/580305",
    "sg:postcode":"79194",
    "sg:province":"Baden-W\u00fcrttemberg",
    "wof:name":"Polster Richter",
    "wof:placetype":"venue"
},
  "geometry": {"coordinates":[7.861287117,48.0377731323],"type":"Point"}
}