{
  "type": "Feature",
  "properties": {
    "iso:country":"DE",
    "sg:address":"Messingstr. 16",
    "sg:city":"Verl",
    "sg:phone":"+49 5246/9650",
    "sg:postcode":"33415",
    "sg:province":"Nordrhein-Westfalen",
    "wof:name":"Alulux Internationale Beteiligungs Gmbh",
    "wof:placetype":"venue"
},
  "geometry": {"coordinates":[8.461885,51.874222],"type":"Point"}
}