{
  "type": "Feature",
  "properties": {
    "iso:country":"DE",
    "sg:address":"Fuhrenkamp 7",
    "sg:city":"Wrestedt",
    "sg:phone":"+49 5802/987920",
    "sg:postcode":"29559",
    "sg:province":"Niedersachsen",
    "wof:name":"Biscova-arzneimittel Vertrieb Pharmazeutische Pr\u00e4parate",
    "wof:placetype":"venue"
},
  "geometry": {"coordinates":[10.5985298157,52.9072914124],"type":"Point"}
}