{
  "type": "Feature",
  "properties": {
    "iso:country":"DE",
    "sg:address":"Nr. 61 e",
    "sg:city":"Guttau",
    "sg:phone":"+49 35932/30580",
    "sg:postcode":"02694",
    "sg:province":"Sachsen",
    "wof:name":"Claus Richter Transporte Gmbh",
    "wof:placetype":"venue"
},
  "geometry": {"coordinates":[14.5265750885,51.2525520325],"type":"Point"}
}