{
  "type": "Feature",
  "properties": {
    "iso:country":"DE",
    "sg:address":"Lessingstr. 22",
    "sg:city":"Karlsruhe",
    "sg:phone":"+49 721/854435",
    "sg:postcode":"76135",
    "sg:province":"Baden-W\u00fcrttemberg",
    "wof:name":"Marianne Seidl-hickstein",
    "wof:placetype":"venue"
},
  "geometry": {"coordinates":[8.38514,49.008991],"type":"Point"}
}