{
  "type": "Feature",
  "properties": {
    "iso:country":"DE",
    "sg:address":"Kreuzstr. 18-20",
    "sg:city":"Freiburg",
    "sg:phone":"+49 761/275851",
    "sg:postcode":"79106",
    "sg:province":"Baden-W\u00fcrttemberg",
    "wof:name":"Neukauf",
    "wof:placetype":"venue"
},
  "geometry": {"coordinates":[7.8428850174,48.0015068054],"type":"Point"}
}