{
  "type": "Feature",
  "properties": {
    "iso:country":"DE",
    "sg:address":"Auf Taubent\u00e4lchen 30",
    "sg:city":"Beckingen",
    "sg:phone":"+49 6832/91200",
    "sg:postcode":"66701",
    "sg:province":"Saarland",
    "wof:name":"Saturn Logistics E. K.",
    "wof:placetype":"venue"
},
  "geometry": {"coordinates":[6.7337799072,49.4520530701],"type":"Point"}
}