{
  "type": "Feature",
  "properties": {
    "iso:country":"DE",
    "sg:address":"Kirchplatz 1 a",
    "sg:city":"Triebes",
    "sg:phone":"+49 36622/51307",
    "sg:postcode":"07950",
    "sg:province":"Th\u00fcringen",
    "wof:name":"Paul Schubert",
    "wof:placetype":"venue"
},
  "geometry": {"coordinates":[12.0182647705,50.6830329895],"type":"Point"}
}