{
  "type": "Feature",
  "properties": {
    "iso:country":"DE",
    "sg:address":"R\u00f6dder 108",
    "sg:city":"D\u00fclmen",
    "sg:phone":"+49 2590/833",
    "sg:postcode":"48249",
    "sg:province":"Nordrhein-Westfalen",
    "wof:name":"Elkosta - Vertretung West E.k.",
    "wof:placetype":"venue"
},
  "geometry": {"coordinates":[7.321377,51.833618],"type":"Point"}
}