{
  "type": "Feature",
  "properties": {
    "iso:country":"DE",
    "sg:address":"Am Lohberg 16",
    "sg:city":"M\u00fcden-Flettmar",
    "sg:phone":"+49 5375/1757",
    "sg:postcode":"38539",
    "sg:province":"Niedersachsen",
    "wof:name":"Feuerwehr, Sch\u00fctzenverein, Sportverein, Landfrauen",
    "wof:placetype":"venue"
},
  "geometry": {"coordinates":[10.3105316162,52.5319900513],"type":"Point"}
}