{
  "type": "Feature",
  "properties": {
    "iso:country":"DE",
    "sg:address":"Blaufeldener Str. 45",
    "sg:city":"Schrozberg",
    "sg:phone":"+49 7935/508",
    "sg:postcode":"74575",
    "sg:province":"Baden-W\u00fcrttemberg",
    "wof:name":"Alfred Hauke",
    "wof:placetype":"venue"
},
  "geometry": {"coordinates":[9.9796733856,49.340965271],"type":"Point"}
}