{
  "type": "Feature",
  "properties": {
    "iso:country":"DE",
    "sg:address":"Mozartstr. 24",
    "sg:city":"Weil im Sch\u00f6nbuch",
    "sg:phone":"+49 7031/226821",
    "sg:postcode":"71093",
    "sg:province":"Baden-W\u00fcrttemberg",
    "wof:name":"Sparadiso M\u00f6belhandel Gmbh",
    "wof:placetype":"venue"
},
  "geometry": {"coordinates":[9.060247,48.642891],"type":"Point"}
}