{
  "type": "Feature",
  "properties": {
    "iso:country":"DE",
    "sg:address":"Friedrich-Seele-Strasse 3a::",
    "sg:city":"Braunschweig",
    "sg:phone":"+49 7033/537630",
    "sg:postcode":"38122",
    "sg:province":"Niedersachsen",
    "wof:name":"Albert Maier Gmbh",
    "wof:placetype":"venue"
},
  "geometry": {"coordinates":[8.873285,48.751926],"type":"Point"}
}