{
  "type": "Feature",
  "properties": {
    "iso:country":"DE",
    "sg:address":"Hookstr. 3",
    "sg:city":"Spelle",
    "sg:phone":"+49 5977/253",
    "sg:postcode":"48480",
    "sg:province":"Niedersachsen",
    "wof:name":"G. B\u00fcltel",
    "wof:placetype":"venue"
},
  "geometry": {"coordinates":[7.444556,52.358135],"type":"Point"}
}