{
  "type": "Feature",
  "properties": {
    "iso:country":"DE",
    "sg:address":"Wei\u00dfenburgstr. 2",
    "sg:city":"Hannover",
    "sg:postcode":"30161",
    "sg:province":"Niedersachsen",
    "wof:name":"Tm T-shirts N More Gmbh",
    "wof:placetype":"venue"
},
  "geometry": {"coordinates":[9.7383966446,52.3868103027],"type":"Point"}
}