{
  "type": "Feature",
  "properties": {
    "iso:country":"DE",
    "sg:address":"Hinter dem Turme 25",
    "sg:city":"Braunschweig",
    "sg:phone":"+49 531/576660",
    "sg:postcode":"38114",
    "sg:province":"Niedersachsen",
    "wof:name":"Gs Ingenieurgesellschaft Gebhardt Und Schenkewitz",
    "wof:placetype":"venue"
},
  "geometry": {"coordinates":[10.4921016693,52.2868652344],"type":"Point"}
}