{
  "type": "Feature",
  "properties": {
    "iso:country":"DE",
    "sg:city":"Mauth",
    "sg:phone":"+49 8557/608",
    "sg:postcode":"94151",
    "sg:province":"Bayern",
    "wof:name":"M. Stockinger",
    "wof:placetype":"venue"
},
  "geometry": {"coordinates":[13.584931,48.889877],"type":"Point"}
}