{
  "type": "Feature",
  "properties": {
    "iso:country":"DE",
    "sg:address":"Loreleystr. 8",
    "sg:city":"Urbar",
    "sg:postcode":"55430",
    "sg:province":"Rheinland-Pfalz",
    "wof:name":"Kath. \u00d6ffentliche Bibliothek",
    "wof:placetype":"venue"
},
  "geometry": {"coordinates":[7.720033,50.132381],"type":"Point"}
}