{
  "type": "Feature",
  "properties": {
    "iso:country":"DE",
    "sg:address":"Vorm H\u00f6ldchen 12",
    "sg:city":"Georgsmarienh\u00fctte",
    "sg:phone":"+49 5401/44180",
    "sg:postcode":"49124",
    "sg:province":"Niedersachsen",
    "wof:name":"F. Kramer Immobilienmakler",
    "wof:placetype":"venue"
},
  "geometry": {"coordinates":[8.0846681595,52.211605072],"type":"Point"}
}