{
  "type": "Feature",
  "properties": {
    "iso:country":"DE",
    "sg:address":"Rathausallee 14",
    "sg:city":"Wallenhorst",
    "sg:phone":"+49 5407/39184",
    "sg:postcode":"49134",
    "sg:province":"Niedersachsen",
    "wof:name":"Ekso Gmbh",
    "wof:placetype":"venue"
},
  "geometry": {"coordinates":[8.01277,52.350674],"type":"Point"}
}