{
  "type": "Feature",
  "properties": {
    "iso:country":"DE",
    "sg:address":"Leopoldstr. 204::",
    "sg:city":"M\u00fcnchen",
    "sg:phone":"+49 89/36060",
    "sg:postcode":"80804",
    "sg:province":"Bayern",
    "wof:name":"Winterthur Schweizerische Versicherungs-ag",
    "wof:placetype":"venue"
},
  "geometry": {"coordinates":[11.585861,48.175159],"type":"Point"}
}