{
  "type": "Feature",
  "properties": {
    "iso:country":"DE",
    "sg:address":"Pusbackweg 6",
    "sg:city":"Hamburg",
    "sg:phone":"+49 40/6781464",
    "sg:postcode":"22145",
    "sg:province":"Hamburg",
    "wof:name":"Jorunn Merks \u00dcbersetzer",
    "wof:placetype":"venue"
},
  "geometry": {"coordinates":[10.166539,53.634392],"type":"Point"}
}