{
  "type": "Feature",
  "properties": {
    "iso:country":"DE",
    "sg:address":"Vorm Burgtor 18",
    "sg:city":"D\u00fclmen",
    "sg:phone":"+49 2594/991883",
    "sg:postcode":"48249",
    "sg:province":"Nordrhein-Westfalen",
    "wof:name":"Holzweissig Dachtechnik Gmbh",
    "wof:placetype":"venue"
},
  "geometry": {"coordinates":[7.275514,51.824982],"type":"Point"}
}