{
  "type": "Feature",
  "properties": {
    "iso:country":"DE",
    "sg:address":"Am Heerdter Hof 18",
    "sg:city":"D\u00fcsseldorf",
    "sg:phone":"+49 211/5654960",
    "sg:postcode":"40549",
    "sg:province":"Nordrhein-Westfalen",
    "wof:name":"Vangenhassend Gmbh",
    "wof:placetype":"venue"
},
  "geometry": {"coordinates":[6.7221422195,51.2332611084],"type":"Point"}
}