{
  "type": "Feature",
  "properties": {
    "iso:country":"DE",
    "sg:address":"Walsroder Str. 3a",
    "sg:city":"Wedemark",
    "sg:phone":"+49 5130/2995",
    "sg:postcode":"30900",
    "sg:province":"Niedersachsen",
    "wof:name":"Kuhstall",
    "wof:placetype":"venue"
},
  "geometry": {"coordinates":[9.7282800674,52.5803604126],"type":"Point"}
}