{
  "type": "Feature",
  "properties": {
    "iso:country":"DE",
    "sg:address":"Lange Gasse 20",
    "sg:city":"N\u00fcrnberg",
    "sg:phone":"+49 911",
    "sg:postcode":"90403",
    "sg:province":"Bayern",
    "wof:name":"Lehrstuhl F\u00fcr Volkswirtschaftslehre Prof. Dr. Harbrecht",
    "wof:placetype":"venue"
},
  "geometry": {"coordinates":[11.083943,49.458473],"type":"Point"}
}