{
  "type": "Feature",
  "properties": {
    "iso:country":"DE",
    "sg:address":"Maurerstr. 46",
    "sg:city":"Alsdorf",
    "sg:phone":"+49 2404/93091",
    "sg:postcode":"52477",
    "sg:province":"Nordrhein-Westfalen",
    "wof:name":"Pro K\u00fchlsole Gmbh",
    "wof:placetype":"venue"
},
  "geometry": {"coordinates":[6.189068,50.879654],"type":"Point"}
}