{
  "type": "Feature",
  "properties": {
    "iso:country":"DE",
    "sg:address":"Schulstr. 14",
    "sg:city":"Bad Berleburg",
    "sg:phone":"+49 2751/7046",
    "sg:postcode":"57319",
    "sg:province":"Nordrhein-Westfalen",
    "wof:name":"D. N\u00f6lling Porzellan- Und Haushaltswaren",
    "wof:placetype":"venue"
},
  "geometry": {"coordinates":[8.3925218582,51.0481071472],"type":"Point"}
}