{
  "type": "Feature",
  "properties": {
    "iso:country":"DE",
    "sg:address":"Metzinger Str. 66",
    "sg:city":"Filderstadt-Bonlanden",
    "sg:phone":"+49 711/7738025",
    "sg:postcode":"70794",
    "sg:province":"Baden-W\u00fcrttemberg",
    "wof:name":"Sikon Gmbh",
    "wof:placetype":"venue"
},
  "geometry": {"coordinates":[9.223535,48.650539],"type":"Point"}
}