{
  "type": "Feature",
  "properties": {
    "iso:country":"DE",
    "sg:address":"Feldstr. 23",
    "sg:city":"Leverkusen",
    "sg:phone":"+49 2171/764630",
    "sg:postcode":"51381",
    "sg:province":"Nordrhein-Westfalen",
    "wof:name":"Indialog - Ihr Handelsvertreter Per Internet Mit Kostenloser",
    "wof:placetype":"venue"
},
  "geometry": {"coordinates":[7.0216608047,51.0659446716],"type":"Point"}
}