{
  "type": "Feature",
  "properties": {
    "iso:country":"DE",
    "sg:address":"Zwickauer Str. 519",
    "sg:city":"Chemnitz",
    "sg:phone":"+49 371/8448144",
    "sg:postcode":"09117",
    "sg:province":"Sachsen",
    "wof:name":"Gottfried H\u00f6rtzsch",
    "wof:placetype":"venue"
},
  "geometry": {"coordinates":[12.8238811493,50.8087348938],"type":"Point"}
}