{
  "type": "Feature",
  "properties": {
    "iso:country":"DE",
    "sg:address":"Teutonenstr. 4",
    "sg:city":"Hamm",
    "sg:phone":"+49 2381/940420",
    "sg:postcode":"59067",
    "sg:province":"Nordrhein-Westfalen",
    "wof:name":"H. -hugo Brenschede Gmbh",
    "wof:placetype":"venue"
},
  "geometry": {"coordinates":[7.778361,51.673996],"type":"Point"}
}