{
  "type": "Feature",
  "properties": {
    "iso:country":"DE",
    "sg:address":"Ringweg 1",
    "sg:city":"Gersdorf-M\u00f6hrsdorf",
    "sg:phone":"+49 35787/1348",
    "sg:postcode":"01920",
    "sg:province":"Sachsen",
    "wof:name":"Hertelt",
    "wof:placetype":"venue"
},
  "geometry": {"coordinates":[14.1320667267,51.2650375366],"type":"Point"}
}