{
  "type": "Feature",
  "properties": {
    "iso:country":"DE",
    "sg:address":"Blumenthaler Str. 1",
    "sg:city":"Torgelow",
    "sg:phone":"+49 3976/432817",
    "sg:postcode":"17358",
    "sg:province":"Mecklenburg-Vorpommern",
    "wof:name":"Instandhaltungsbetrieb F\u00fcr Verkehrsleiteinrichtungen Und",
    "wof:placetype":"venue"
},
  "geometry": {"coordinates":[14.008994,53.636768],"type":"Point"}
}