{
  "type": "Feature",
  "properties": {
    "iso:country":"DE",
    "sg:address":"In den Bruchwiesen 24",
    "sg:city":"Annweiler",
    "sg:phone":"+49 6346/2246",
    "sg:postcode":"76855",
    "sg:province":"Rheinland-Pfalz",
    "wof:name":"Ackerl Gmbh",
    "wof:placetype":"venue"
},
  "geometry": {"coordinates":[7.9861111641,49.2151603699],"type":"Point"}
}