{
  "type": "Feature",
  "properties": {
    "iso:country":"DE",
    "sg:address":"Weichselstr. 12",
    "sg:city":"Berlin",
    "sg:phone":"+49 30/6245419",
    "sg:postcode":"12045",
    "sg:province":"Berlin",
    "wof:name":"Radsport Arlt",
    "wof:placetype":"venue"
},
  "geometry": {"coordinates":[13.434419,52.485153],"type":"Point"}
}