{
  "type": "Feature",
  "properties": {
    "iso:country":"DE",
    "sg:address":"Bensdorpstr. 12",
    "sg:city":"Kleve",
    "sg:phone":"+49 2821/58401",
    "sg:postcode":"47533",
    "sg:province":"Nordrhein-Westfalen",
    "wof:name":"Lva Rheinprovinz",
    "wof:placetype":"venue"
},
  "geometry": {"coordinates":[6.1426501274,51.7906188965],"type":"Point"}
}