{
  "type": "Feature",
  "properties": {
    "iso:country":"DE",
    "sg:address":"R\u00f6ntgenstr. 2",
    "sg:city":"Erkrath",
    "sg:postcode":"40699",
    "sg:province":"Nordrhein-Westfalen",
    "wof:name":"Netsystem Netzwerk- Und Systemtechnik- Gmbh",
    "wof:placetype":"venue"
},
  "geometry": {"coordinates":[6.9427108765,51.2151603699],"type":"Point"}
}