{
  "type": "Feature",
  "properties": {
    "iso:country":"DE",
    "sg:address":"Sagarder Weg 1",
    "sg:city":"Dresden",
    "sg:postcode":"01109",
    "sg:province":"Sachsen",
    "wof:name":"Aldi Gmbh & Co. Kg",
    "wof:placetype":"venue"
},
  "geometry": {"coordinates":[13.7831678391,51.1233062744],"type":"Point"}
}