{
  "type": "Feature",
  "properties": {
    "iso:country":"DE",
    "sg:address":"Manhagener Allee 30",
    "sg:city":"Ahrensburg",
    "sg:postcode":"22926",
    "sg:province":"Schleswig-Holstein",
    "wof:name":"Hgk Hamburger Grundst\u00fcckskontor Gmbh",
    "wof:placetype":"venue"
},
  "geometry": {"coordinates":[10.2416467667,53.6705627441],"type":"Point"}
}