{
  "type": "Feature",
  "properties": {
    "iso:country":"DE",
    "sg:address":"Josef-Geldreich-Str. 16",
    "sg:city":"Oberkirch",
    "sg:phone":"+49 7802/92570",
    "sg:postcode":"77704",
    "sg:province":"Baden-W\u00fcrttemberg",
    "wof:name":"K. Leins & S\u00f6hne Gmbh",
    "wof:placetype":"venue"
},
  "geometry": {"coordinates":[8.079407,48.528683],"type":"Point"}
}