{
  "type": "Feature",
  "properties": {
    "iso:country":"DE",
    "sg:address":"K\u00f6lner Str. 39",
    "sg:city":"Lennestadt",
    "sg:phone":"+49 2721/10141",
    "sg:postcode":"57368",
    "sg:province":"Nordrhein-Westfalen",
    "wof:name":"Marita Dicke",
    "wof:placetype":"venue"
},
  "geometry": {"coordinates":[8.013794899,51.1332092285],"type":"Point"}
}