{
  "type": "Feature",
  "properties": {
    "iso:country":"DE",
    "sg:address":"Hohensteiner Str. 37",
    "sg:city":"Limbach-Oberfrohna",
    "sg:phone":"+49 3722/95887",
    "sg:postcode":"09212",
    "sg:province":"Sachsen",
    "wof:name":"Gisela Wevers",
    "wof:placetype":"venue"
},
  "geometry": {"coordinates":[12.7757520676,50.8559532166],"type":"Point"}
}