{
  "type": "Feature",
  "properties": {
    "iso:country":"DE",
    "sg:address":"Wielandstr. 24",
    "sg:city":"Berlin",
    "sg:phone":"+49 30/8812268",
    "sg:postcode":"10707",
    "sg:province":"Berlin",
    "wof:name":"Von Kloeden Kg",
    "wof:placetype":"venue"
},
  "geometry": {"coordinates":[13.3146810532,52.5000457764],"type":"Point"}
}