{
  "type": "Feature",
  "properties": {
    "iso:country":"DE",
    "sg:address":"Handschuhsheimer Landstr. 38",
    "sg:city":"Heidelberg",
    "sg:phone":"+49 6221/471361",
    "sg:postcode":"69120",
    "sg:province":"Baden-W\u00fcrttemberg",
    "wof:name":"G\u00fcnter Mall Fotograf-u. Fotoatelierbetr.",
    "wof:placetype":"venue"
},
  "geometry": {"coordinates":[8.6895294189,49.4211616516],"type":"Point"}
}