{
  "type": "Feature",
  "properties": {
    "iso:country":"DE",
    "sg:address":"Reeperbahn 117",
    "sg:city":"Hamburg",
    "sg:phone":"+49 40/310808",
    "sg:postcode":"20359",
    "sg:province":"Hamburg",
    "wof:name":"Martin G\u00f6tz",
    "wof:placetype":"venue"
},
  "geometry": {"coordinates":[9.960351944,53.5492401123],"type":"Point"}
}