{
  "type": "Feature",
  "properties": {
    "iso:country":"DE",
    "sg:address":"Friedrichstr. 41",
    "sg:city":"Wiesbaden",
    "sg:phone":"+49 611/306642",
    "sg:postcode":"65185",
    "sg:province":"Hessen",
    "wof:name":"Pizza Hut",
    "wof:placetype":"venue"
},
  "geometry": {"coordinates":[8.2391090393,50.0804595947],"type":"Point"}
}