{
  "type": "Feature",
  "properties": {
    "iso:country":"DE",
    "sg:address":"Angelstr. 9",
    "sg:city":"Vaihingen",
    "sg:phone":"+49 7042/92720",
    "sg:postcode":"71665",
    "sg:province":"Baden-W\u00fcrttemberg",
    "wof:name":"M. Lutz",
    "wof:placetype":"venue"
},
  "geometry": {"coordinates":[8.9602956772,48.9311828613],"type":"Point"}
}