{
  "type": "Feature",
  "properties": {
    "iso:country":"DE",
    "sg:address":"Merseburger Str. 165",
    "sg:city":"Halle",
    "sg:phone":"+49 345/1327381",
    "sg:postcode":"06112",
    "sg:province":"Sachsen-Anhalt",
    "wof:name":"Dr. Med. Sylvia R\u00f6der",
    "wof:placetype":"venue"
},
  "geometry": {"coordinates":[11.9842739105,51.4606513977],"type":"Point"}
}