{
  "type": "Feature",
  "properties": {
    "iso:country":"DE",
    "sg:address":"Nordstr. 2",
    "sg:city":"Gro\u00dfr\u00f6hrsdorf",
    "sg:phone":"+49 35952/58838",
    "sg:postcode":"01900",
    "sg:province":"Sachsen",
    "wof:name":"Haucke Krawatten Und Schleifen Gmbh",
    "wof:placetype":"venue"
},
  "geometry": {"coordinates":[14.04253,51.143311],"type":"Point"}
}