{
  "type": "Feature",
  "properties": {
    "iso:country":"DE",
    "sg:address":"Blutenburgstr. 92",
    "sg:city":"M\u00fcnchen",
    "sg:phone":"+49 89/183700",
    "sg:postcode":"80636",
    "sg:province":"Bayern",
    "wof:name":"Carla Wezyk",
    "wof:placetype":"venue"
},
  "geometry": {"coordinates":[11.5402698517,48.1500244141],"type":"Point"}
}