{
  "type": "Feature",
  "properties": {
    "iso:country":"DE",
    "sg:address":"Ostertoft 19",
    "sg:city":"Dollerup",
    "sg:phone":"+49 4636/8135",
    "sg:postcode":"24989",
    "sg:province":"Schleswig-Holstein",
    "wof:name":"Klaus Lawrenz",
    "wof:placetype":"venue"
},
  "geometry": {"coordinates":[9.680324,54.778381],"type":"Point"}
}