{
  "type": "Feature",
  "properties": {
    "iso:country":"DE",
    "sg:address":"Seestr. 16",
    "sg:city":"Simmerath",
    "sg:phone":"+49 2473/3869",
    "sg:postcode":"52152",
    "sg:province":"Nordrhein-Westfalen",
    "wof:name":"Werner Lutterbach Architekt",
    "wof:placetype":"venue"
},
  "geometry": {"coordinates":[6.388967,50.626389],"type":"Point"}
}