{
  "type": "Feature",
  "properties": {
    "iso:country":"DE",
    "sg:address":"Hauptstr. 10",
    "sg:city":"Waldshut-Tiengen",
    "sg:phone":"+49 7741/62284",
    "sg:postcode":"79761",
    "sg:province":"Baden-W\u00fcrttemberg",
    "wof:name":"D. Wegmann",
    "wof:placetype":"venue"
},
  "geometry": {"coordinates":[8.2737960815,47.6337051392],"type":"Point"}
}