{
  "type": "Feature",
  "properties": {
    "iso:country":"DE",
    "sg:address":"Friedrich-Barnewitz-Str 5",
    "sg:city":"Rostock",
    "sg:phone":"+49 381/5196345",
    "sg:postcode":"18119",
    "sg:province":"Mecklenburg-Vorpommern",
    "wof:name":"Ripka",
    "wof:placetype":"venue"
},
  "geometry": {"coordinates":[12.077271,54.172539],"type":"Point"}
}