{
  "type": "Feature",
  "properties": {
    "iso:country":"DE",
    "sg:address":"Lilienstr. 1",
    "sg:city":"Uslar",
    "sg:phone":"+49 5571/4495",
    "sg:postcode":"37170",
    "sg:province":"Niedersachsen",
    "wof:name":"Heinz-dieter Gutreise",
    "wof:placetype":"venue"
},
  "geometry": {"coordinates":[9.63215,51.665466],"type":"Point"}
}