{
  "type": "Feature",
  "properties": {
    "iso:country":"DE",
    "sg:address":"Oderfelder Str. 42",
    "sg:city":"Hamburg",
    "sg:phone":"+49 40/6065356",
    "sg:postcode":"20149",
    "sg:province":"Hamburg",
    "wof:name":"Dr. Wolfgang Hegels Rechtsanwalt",
    "wof:placetype":"venue"
},
  "geometry": {"coordinates":[9.9885482788,53.5846138],"type":"Point"}
}