{
  "type": "Feature",
  "properties": {
    "iso:country":"DE",
    "sg:address":"Barlachstr. 1",
    "sg:city":"B\u00fcnde",
    "sg:phone":"+49 5223/62622",
    "sg:postcode":"32257",
    "sg:province":"Nordrhein-Westfalen",
    "wof:name":"Sanitos Joachim H\u00fcttemann",
    "wof:placetype":"venue"
},
  "geometry": {"coordinates":[8.55224,52.207127],"type":"Point"}
}