{
  "type": "Feature",
  "properties": {
    "iso:country":"DE",
    "sg:address":"Steinstr. 13",
    "sg:city":"Elbe",
    "sg:phone":"+49 5345/4840",
    "sg:postcode":"38274",
    "sg:province":"Niedersachsen",
    "wof:name":"Holzwerkstatt Schygulla Und Ziegenfu\u00df",
    "wof:placetype":"venue"
},
  "geometry": {"coordinates":[10.265329,52.090931],"type":"Point"}
}