{
  "type": "Feature",
  "properties": {
    "iso:country":"DE",
    "sg:address":"Beffendorfer Str. 15",
    "sg:city":"B\u00f6singen",
    "sg:phone":"+49 7404/502",
    "sg:postcode":"78662",
    "sg:province":"Baden-W\u00fcrttemberg",
    "wof:name":"Alfons Bantle",
    "wof:placetype":"venue"
},
  "geometry": {"coordinates":[8.5535211563,48.2396888733],"type":"Point"}
}