{
  "type": "Feature",
  "properties": {
    "iso:country":"DE",
    "sg:address":"Hauptstr. 329",
    "sg:city":"Idar-Oberstein",
    "sg:phone":"+49 6781/219040",
    "sg:postcode":"55743",
    "sg:province":"Rheinland-Pfalz",
    "wof:name":"Vereinte Versicherungen Marc D\u00fcpre",
    "wof:placetype":"venue"
},
  "geometry": {"coordinates":[7.3203730583,49.7032394409],"type":"Point"}
}