{
  "type": "Feature",
  "properties": {
    "iso:country":"DE",
    "sg:address":"Marienstr. 13",
    "sg:city":"Tutzing",
    "sg:phone":"+49 8158/7430",
    "sg:postcode":"82327",
    "sg:province":"Bayern",
    "wof:name":"Johann M\u00fcller Fisch- Und Forellenz\u00fcchterei",
    "wof:placetype":"venue"
},
  "geometry": {"coordinates":[11.2820329666,47.9104156494],"type":"Point"}
}