{
  "type": "Feature",
  "properties": {
    "iso:country":"DE",
    "sg:address":"Kottmeierstr. 75",
    "sg:city":"Berlin",
    "sg:phone":"+49 30/5354020",
    "sg:postcode":"12459",
    "sg:province":"Berlin",
    "wof:name":"Huschke & Partner Gmbh",
    "wof:placetype":"venue"
},
  "geometry": {"coordinates":[13.53045,52.460602],"type":"Point"}
}