{
  "type": "Feature",
  "properties": {
    "iso:country":"DE",
    "sg:address":"Bahnhofstr. 4",
    "sg:city":"Gro\u00dfkarolinenfeld",
    "sg:phone":"+49 8031/5673",
    "sg:postcode":"83109",
    "sg:province":"Bayern",
    "wof:name":"H. Hildebrand Gmbh",
    "wof:placetype":"venue"
},
  "geometry": {"coordinates":[12.0809593201,47.8904571533],"type":"Point"}
}