{
  "type": "Feature",
  "properties": {
    "iso:country":"DE",
    "sg:address":"Dionysiusstr. 18",
    "sg:city":"H\u00fcckelhoven",
    "sg:phone":"+49 2433/7368",
    "sg:postcode":"41836",
    "sg:province":"Nordrhein-Westfalen",
    "wof:name":"Heinz Bollenberg",
    "wof:placetype":"venue"
},
  "geometry": {"coordinates":[6.24781,51.052303],"type":"Point"}
}