{
  "type": "Feature",
  "properties": {
    "iso:country":"DE",
    "sg:address":"Am Rennplatz 10",
    "sg:city":"Nettetal",
    "sg:phone":"+49 2157/3666",
    "sg:postcode":"41334",
    "sg:province":"Nordrhein-Westfalen",
    "wof:name":"Thieltges Transport Gmbh",
    "wof:placetype":"venue"
},
  "geometry": {"coordinates":[6.2034349442,51.3406181335],"type":"Point"}
}