{
  "type": "Feature",
  "properties": {
    "iso:country":"DE",
    "sg:address":"Europastr. 65",
    "sg:city":"Lahr",
    "sg:postcode":"77933",
    "sg:province":"Baden-W\u00fcrttemberg",
    "wof:name":"Sundwig-kohler Gmbh",
    "wof:placetype":"venue"
},
  "geometry": {"coordinates":[7.82599,48.349628],"type":"Point"}
}