{
  "type": "Feature",
  "properties": {
    "iso:country":"DE",
    "sg:address":"Professor-Drexel-Str. 21",
    "sg:city":"Bad Birnbach",
    "sg:phone":"+49 8563/91384",
    "sg:postcode":"84364",
    "sg:province":"Bayern",
    "wof:name":"Bruno Baier Masseur",
    "wof:placetype":"venue"
},
  "geometry": {"coordinates":[13.086105,48.441341],"type":"Point"}
}