{
  "type": "Feature",
  "properties": {
    "iso:country":"DE",
    "sg:address":"Gottesackerweg 1",
    "sg:city":"Kempten",
    "sg:phone":"+49 831/5218110",
    "sg:postcode":"87439",
    "sg:province":"Bayern",
    "wof:name":"Florian Hiedl",
    "wof:placetype":"venue"
},
  "geometry": {"coordinates":[10.3105096817,47.734172821],"type":"Point"}
}