{
  "type": "Feature",
  "properties": {
    "iso:country":"DE",
    "sg:address":"Kurt-Schumacher-Str. 56",
    "sg:city":"Ludwigshafen",
    "sg:phone":"+49 621/651501",
    "sg:postcode":"67069",
    "sg:province":"Rheinland-Pfalz",
    "wof:name":"Karl Dudenh\u00f6ffer",
    "wof:placetype":"venue"
},
  "geometry": {"coordinates":[8.398673,49.522717],"type":"Point"}
}