{
  "type": "Feature",
  "properties": {
    "iso:country":"DE",
    "sg:address":"Kielwg. 100",
    "sg:city":"Diepholz",
    "sg:phone":"+49 4954/4159280",
    "sg:postcode":"49356",
    "sg:province":"Niedersachsen",
    "wof:name":"Carl Stolte Gmbh & Co Kg",
    "wof:placetype":"venue"
},
  "geometry": {"coordinates":[8.350302,52.606056],"type":"Point"}
}