{
  "type": "Feature",
  "properties": {
    "iso:country":"DE",
    "sg:address":"Vordere Gasse 14",
    "sg:city":"Rosenfeld",
    "sg:phone":"+49 7428/93030",
    "sg:postcode":"72348",
    "sg:province":"Baden-W\u00fcrttemberg",
    "wof:name":"Iso-maschinenbau Gmbh",
    "wof:placetype":"venue"
},
  "geometry": {"coordinates":[8.706891,48.265709],"type":"Point"}
}