{
  "type": "Feature",
  "properties": {
    "iso:country":"DE",
    "sg:address":"Talstr. 2",
    "sg:city":"Altleiningen",
    "sg:postcode":"67317",
    "sg:province":"Rheinland-Pfalz",
    "wof:name":"Drahtzug Holding Gmbh & Co. Kg",
    "wof:placetype":"venue"
},
  "geometry": {"coordinates":[8.09987,49.520046],"type":"Point"}
}