{
  "type": "Feature",
  "properties": {
    "iso:country":"DE",
    "sg:address":"Bergstr. 10",
    "sg:city":"Attendorn",
    "sg:postcode":"57439",
    "sg:province":"Nordrhein-Westfalen",
    "wof:name":"Tct Technologie-training Ohg",
    "wof:placetype":"venue"
},
  "geometry": {"coordinates":[7.893078,51.128803],"type":"Point"}
}