{
  "type": "Feature",
  "properties": {
    "iso:country":"DE",
    "sg:address":"R\u00f6mhilder Str. 27",
    "sg:city":"Hildburghausen",
    "sg:phone":"+49 3685/709500",
    "sg:postcode":"98646",
    "sg:province":"Th\u00fcringen",
    "wof:name":"Hildburgh\u00e4user Baugesellschaft Mbh",
    "wof:placetype":"venue"
},
  "geometry": {"coordinates":[10.7083044052,50.4205513],"type":"Point"}
}