{
  "type": "Feature",
  "properties": {
    "iso:country":"DE",
    "sg:address":"Auf der Teufelsinsel 3",
    "sg:city":"St. Ingbert",
    "sg:phone":"+49 6894/888960",
    "sg:postcode":"66386",
    "sg:province":"Saarland",
    "wof:name":"Michael Pfestorf Rechtsanwalt",
    "wof:placetype":"venue"
},
  "geometry": {"coordinates":[7.1227879524,49.2741279602],"type":"Point"}
}