{
  "type": "Feature",
  "properties": {
    "iso:country":"DE",
    "sg:address":"Im Oberdorf 41",
    "sg:city":"Neufra",
    "sg:phone":"+49 7574/91053",
    "sg:postcode":"72419",
    "sg:province":"Baden-W\u00fcrttemberg",
    "wof:name":"Cpl Medizintechnik Gmbh",
    "wof:placetype":"venue"
},
  "geometry": {"coordinates":[9.1810951233,48.248008728],"type":"Point"}
}