{
  "type": "Feature",
  "properties": {
    "iso:country":"DE",
    "sg:address":"Hofstetter Str. 11",
    "sg:city":"Kleinwallstadt",
    "sg:phone":"+49 6022/21116",
    "sg:postcode":"63839",
    "sg:province":"Bayern",
    "wof:name":"Manfred Hartig",
    "wof:placetype":"venue"
},
  "geometry": {"coordinates":[9.1705684662,49.8701286316],"type":"Point"}
}