{
  "type": "Feature",
  "properties": {
    "iso:country":"DE",
    "sg:address":"K\u00e4the-Kollwitz-Str. 30",
    "sg:city":"Halle",
    "sg:phone":"+49 345/5602751",
    "sg:postcode":"06116",
    "sg:province":"Sachsen-Anhalt",
    "wof:name":"Hartmut Gr\u00fctzmacher",
    "wof:placetype":"venue"
},
  "geometry": {"coordinates":[12.029818,51.475296],"type":"Point"}
}