{
  "type": "Feature",
  "properties": {
    "iso:country":"DE",
    "sg:address":"Staufenstr. 32",
    "sg:city":"Niederstotzingen",
    "sg:phone":"+49 7325/3454",
    "sg:postcode":"89168",
    "sg:province":"Baden-W\u00fcrttemberg",
    "wof:name":"D. Trenner Ingenieur",
    "wof:placetype":"venue"
},
  "geometry": {"coordinates":[10.2410917282,48.5405044556],"type":"Point"}
}