{
  "type": "Feature",
  "properties": {
    "iso:country":"DE",
    "sg:address":"Lindenstr. 8",
    "sg:city":"Feucht",
    "sg:phone":"+49 9128/16086",
    "sg:postcode":"90537",
    "sg:province":"Bayern",
    "wof:name":"Lengerer",
    "wof:placetype":"venue"
},
  "geometry": {"coordinates":[11.214264,49.368008],"type":"Point"}
}