{
  "type": "Feature",
  "properties": {
    "iso:country":"DE",
    "sg:address":"Schneiderstr. 11",
    "sg:city":"Wadern",
    "sg:phone":"+49 6871/4346",
    "sg:postcode":"66687",
    "sg:province":"Saarland",
    "wof:name":"Barth - Keramik Gmbh",
    "wof:placetype":"venue"
},
  "geometry": {"coordinates":[6.8936052322,49.5831832886],"type":"Point"}
}