{
  "type": "Feature",
  "properties": {
    "iso:country":"DE",
    "sg:address":"Hauptstr. 187",
    "sg:city":"\u00d6stringen",
    "sg:phone":"+49 7253/21720",
    "sg:postcode":"76684",
    "sg:province":"Baden-W\u00fcrttemberg",
    "wof:name":"Eugen F\u00f6rderer",
    "wof:placetype":"venue"
},
  "geometry": {"coordinates":[8.7170143127,49.2212677002],"type":"Point"}
}