{
  "type": "Feature",
  "properties": {
    "iso:country":"DE",
    "sg:address":"Hintergasse 39",
    "sg:city":"W\u00f6lfersheim",
    "sg:phone":"+49 6036/2434",
    "sg:postcode":"61200",
    "sg:province":"Hessen",
    "wof:name":"Gerlinde Emmel",
    "wof:placetype":"venue"
},
  "geometry": {"coordinates":[8.830055,50.430519],"type":"Point"}
}