{
  "type": "Feature",
  "properties": {
    "iso:country":"DE",
    "sg:address":"Kohlenstr. 33",
    "sg:city":"Bochum",
    "sg:phone":"+49 234/943730",
    "sg:postcode":"44795",
    "sg:province":"Nordrhein-Westfalen",
    "wof:name":"Wirichs Gmbh & Co",
    "wof:placetype":"venue"
},
  "geometry": {"coordinates":[7.1962270737,51.4637680054],"type":"Point"}
}