{
  "type": "Feature",
  "properties": {
    "iso:country":"DE",
    "sg:address":"Rimbacher Str. 1",
    "sg:city":"Weng",
    "sg:phone":"+49 8702/2725",
    "sg:postcode":"84187",
    "sg:province":"Bayern",
    "wof:name":"Gastwirtschaft Johann Sturm",
    "wof:placetype":"venue"
},
  "geometry": {"coordinates":[12.3693304062,48.6563796997],"type":"Point"}
}