{
  "type": "Feature",
  "properties": {
    "iso:country":"DE",
    "sg:address":"M\u00f6nichhusen 42",
    "sg:city":"Bad Oeynhausen",
    "sg:phone":"+49 5731/53070",
    "sg:postcode":"32549",
    "sg:province":"Nordrhein-Westfalen",
    "wof:name":"Gneuss Kunststofftechnik Gmbh",
    "wof:placetype":"venue"
},
  "geometry": {"coordinates":[8.809521,52.23251],"type":"Point"}
}