{
  "type": "Feature",
  "properties": {
    "iso:country":"DE",
    "sg:address":"Am G\u00fcterbahnhof 12",
    "sg:city":"Friedrichsthal",
    "sg:phone":"+49 6897/85650",
    "sg:postcode":"66299",
    "sg:province":"Saarland",
    "wof:name":"Biesterfeld Chemiedistribution Gmbh & Co. Kg",
    "wof:placetype":"venue"
},
  "geometry": {"coordinates":[7.08734,49.317333],"type":"Point"}
}