{
  "type": "Feature",
  "properties": {
    "iso:country":"DE",
    "sg:address":"Viatisstr. 160",
    "sg:city":"N\u00fcrnberg",
    "sg:phone":"+49 911/405950",
    "sg:postcode":"90480",
    "sg:province":"Bayern",
    "wof:name":"Herbert Von Heynitz",
    "wof:placetype":"venue"
},
  "geometry": {"coordinates":[11.1244459152,49.4365348816],"type":"Point"}
}