{
  "type": "Feature",
  "properties": {
    "iso:country":"DE",
    "sg:address":"Neusser Str. 180",
    "sg:city":"K\u00f6ln",
    "sg:phone":"+49 221/730065",
    "sg:postcode":"50733",
    "sg:province":"Nordrhein-Westfalen",
    "wof:name":"Reiseb\u00fcro Dahmen",
    "wof:placetype":"venue"
},
  "geometry": {"coordinates":[6.9546370506,50.9598731995],"type":"Point"}
}