{
  "type": "Feature",
  "properties": {
    "iso:country":"DE",
    "sg:address":"Ollenhauerstr. 13",
    "sg:city":"Berlin",
    "sg:phone":"+49 30/4952822",
    "sg:postcode":"13403",
    "sg:province":"Berlin",
    "wof:name":"Eric M\u00fcller Rechtsanwalt",
    "wof:placetype":"venue"
},
  "geometry": {"coordinates":[13.329249382,52.5663986206],"type":"Point"}
}