{
  "type": "Feature",
  "properties": {
    "iso:country":"DE",
    "sg:address":"Schl\u00fcterstr. 16",
    "sg:city":"Berlin",
    "sg:phone":"+49 30/3135965",
    "sg:postcode":"10625",
    "sg:province":"Berlin",
    "wof:name":"Karin Prinz-dunst",
    "wof:placetype":"venue"
},
  "geometry": {"coordinates":[13.317586,52.507862],"type":"Point"}
}