{
  "type": "Feature",
  "properties": {
    "iso:country":"DE",
    "sg:address":"Wettstettener Str. 17",
    "sg:city":"Lenting",
    "sg:phone":"+49 8456/3239",
    "sg:postcode":"85101",
    "sg:province":"Bayern",
    "wof:name":"Johann Kraus",
    "wof:placetype":"venue"
},
  "geometry": {"coordinates":[11.4561853409,48.8061027527],"type":"Point"}
}