{
  "type": "Feature",
  "properties": {
    "iso:country":"DE",
    "sg:address":"Sulzbacher Str. 47",
    "sg:city":"R\u00f6thenbach",
    "sg:phone":"+49 911",
    "sg:postcode":"90552",
    "sg:province":"Bayern",
    "wof:name":"Insituform: Generalunternehmer F\u00fcr Kanalsanierung",
    "wof:placetype":"venue"
},
  "geometry": {"coordinates":[11.250398,49.49062],"type":"Point"}
}