{
  "type": "Feature",
  "properties": {
    "iso:country":"DE",
    "sg:address":"Im Obrock 153",
    "sg:city":"Kirchlengern",
    "sg:phone":"+49 5223/78003",
    "sg:postcode":"32278",
    "sg:province":"Nordrhein-Westfalen",
    "wof:name":"Kley Heizung-sanit\u00e4r- Klempnerei Verwaltungs Gmbh",
    "wof:placetype":"venue"
},
  "geometry": {"coordinates":[8.6208753586,52.2017021179],"type":"Point"}
}