{
  "type": "Feature",
  "properties": {
    "iso:country":"DE",
    "sg:address":"Br\u00fcckenstr. 1",
    "sg:city":"Kirchheim",
    "sg:phone":"+49 6625/1265",
    "sg:postcode":"36275",
    "sg:province":"Hessen",
    "wof:name":"Georg Ickler",
    "wof:placetype":"venue"
},
  "geometry": {"coordinates":[9.594634,50.861225],"type":"Point"}
}