{
  "type": "Feature",
  "properties": {
    "iso:country":"DE",
    "sg:address":"Heinrich-Heine-Str. 3",
    "sg:city":"Peine",
    "sg:phone":"+49 5171/6170",
    "sg:postcode":"31224",
    "sg:province":"Niedersachsen",
    "wof:name":"Redaktion Mit Einem Blick Sportblick Verlag",
    "wof:placetype":"venue"
},
  "geometry": {"coordinates":[10.235203743,52.3247184753],"type":"Point"}
}