{
  "type": "Feature",
  "properties": {
    "iso:country":"DE",
    "sg:address":"Pommersche Str. 11",
    "sg:city":"Torgelow",
    "sg:phone":"+49 3976/202107",
    "sg:postcode":"17358",
    "sg:province":"Mecklenburg-Vorpommern",
    "wof:name":"Klaus-peter Bresina",
    "wof:placetype":"venue"
},
  "geometry": {"coordinates":[14.0107793808,53.6296730042],"type":"Point"}
}