{
  "type": "Feature",
  "properties": {
    "iso:country":"DE",
    "sg:address":"Rosengasse 5",
    "sg:city":"Lam",
    "sg:phone":"+49 9943/1368",
    "sg:postcode":"93462",
    "sg:province":"Bayern",
    "wof:name":"Siegfried Schwarz",
    "wof:placetype":"venue"
},
  "geometry": {"coordinates":[13.0506515503,49.1974601746],"type":"Point"}
}