{
  "type": "Feature",
  "properties": {
    "iso:country":"DE",
    "sg:address":"Bl\u00fccherstr. 63",
    "sg:city":"Rostock",
    "sg:postcode":"18057",
    "sg:province":"Mecklenburg-Vorpommern",
    "wof:name":"Werkstatt F\u00fcr Historische Tasteninstrumente",
    "wof:placetype":"venue"
},
  "geometry": {"coordinates":[12.1422548294,54.0785598755],"type":"Point"}
}