{
  "type": "Feature",
  "properties": {
    "iso:country":"DE",
    "sg:address":"Gro\u00dfheider Str. 33",
    "sg:city":"Gro\u00dfheide",
    "sg:phone":"+49 4936/7107",
    "sg:postcode":"26532",
    "sg:province":"Niedersachsen",
    "wof:name":"Siegfried Deneke",
    "wof:placetype":"venue"
},
  "geometry": {"coordinates":[7.34354,53.592327],"type":"Point"}
}