{
  "type": "Feature",
  "properties": {
    "iso:country":"DE",
    "sg:address":"Mittelstr. 3",
    "sg:city":"Bad Liebenwerda",
    "sg:phone":"+49 35341/12251",
    "sg:postcode":"04924",
    "sg:province":"Brandenburg",
    "wof:name":"K. Schaffner",
    "wof:placetype":"venue"
},
  "geometry": {"coordinates":[13.3917665482,51.5155258179],"type":"Point"}
}