{
  "type": "Feature",
  "properties": {
    "iso:country":"DE",
    "sg:address":"Am Seitenweg 24",
    "sg:city":"Marienberg",
    "sg:phone":"+49 3735/24101",
    "sg:postcode":"09496",
    "sg:province":"Sachsen",
    "wof:name":"Udo Haunstein",
    "wof:placetype":"venue"
},
  "geometry": {"coordinates":[13.168347,50.680054],"type":"Point"}
}