{
  "type": "Feature",
  "properties": {
    "iso:country":"DE",
    "sg:address":"Luisenstr. 6",
    "sg:city":"Karben",
    "sg:phone":"+49 6039/42842",
    "sg:postcode":"61184",
    "sg:province":"Hessen",
    "wof:name":"D. He\u00dfler",
    "wof:placetype":"venue"
},
  "geometry": {"coordinates":[8.776909,50.224552],"type":"Point"}
}