{
  "type": "Feature",
  "properties": {
    "iso:country":"DE",
    "sg:address":"Vorsetzen 34",
    "sg:city":"Hamburg",
    "sg:phone":"+49 40/378399",
    "sg:postcode":"20459",
    "sg:province":"Hamburg",
    "wof:name":"Ernst Erdmann",
    "wof:placetype":"venue"
},
  "geometry": {"coordinates":[9.978494,53.544411],"type":"Point"}
}