{
  "type": "Feature",
  "properties": {
    "iso:country":"DE",
    "sg:address":"Max-von-Laue-Str. 8",
    "sg:city":"W\u00fcrzburg",
    "sg:phone":"+49 931/93049",
    "sg:postcode":"97080",
    "sg:province":"Bayern",
    "wof:name":"Horst Grimm Gmbh",
    "wof:placetype":"venue"
},
  "geometry": {"coordinates":[9.8913908005,49.8101425171],"type":"Point"}
}