{
  "type": "Feature",
  "properties": {
    "iso:country":"DE",
    "sg:address":"Hauptstr. 23",
    "sg:city":"Waldshut-Tiengen",
    "sg:phone":"+49 7741/4574",
    "sg:postcode":"79761",
    "sg:province":"Baden-W\u00fcrttemberg",
    "wof:name":"Eberhard Stegen Drogerie",
    "wof:placetype":"venue"
},
  "geometry": {"coordinates":[8.273766,47.634068],"type":"Point"}
}