{
  "type": "Feature",
  "properties": {
    "iso:country":"DE",
    "sg:address":"Gewerbestr. 2",
    "sg:city":"Vohenstrau\u00df",
    "sg:phone":"+49 9651/1490",
    "sg:postcode":"92648",
    "sg:province":"Bayern",
    "wof:name":"Karl Zeitler",
    "wof:placetype":"venue"
},
  "geometry": {"coordinates":[12.3515281677,49.618019104],"type":"Point"}
}