{
  "type": "Feature",
  "properties": {
    "iso:country":"DE",
    "sg:city":"Bornh\u00f6ved",
    "sg:phone":"+49 4323/96573",
    "sg:postcode":"24619",
    "sg:province":"Schleswig-Holstein",
    "wof:name":"Rainer Und Anne B\u00e4ppler Architekten",
    "wof:placetype":"venue"
},
  "geometry": {"coordinates":[10.22752,54.070522],"type":"Point"}
}