{
  "type": "Feature",
  "properties": {
    "iso:country":"DE",
    "sg:address":"Georg-Sandmann-Str. 9",
    "sg:city":"Br\u00fchl",
    "sg:phone":"+49 2232/49960",
    "sg:postcode":"50321",
    "sg:province":"Nordrhein-Westfalen",
    "wof:name":"Norbert Esser Architekt",
    "wof:placetype":"venue"
},
  "geometry": {"coordinates":[6.896664,50.82542],"type":"Point"}
}