{
  "type": "Feature",
  "properties": {
    "iso:country":"DE",
    "sg:address":"Adolfstr. 59",
    "sg:city":"Braunschweig",
    "sg:phone":"+49 531/799111",
    "sg:postcode":"38102",
    "sg:province":"Niedersachsen",
    "wof:name":"Gfs-immobilien",
    "wof:placetype":"venue"
},
  "geometry": {"coordinates":[10.5346193314,52.2610549927],"type":"Point"}
}