{
  "type": "Feature",
  "properties": {
    "iso:country":"DE",
    "sg:address":"Schwarzfeldweg 8",
    "sg:city":"Schernfeld",
    "sg:postcode":"85132",
    "sg:province":"Bayern",
    "wof:name":"H\u00fcttinger Gmbh",
    "wof:placetype":"venue"
},
  "geometry": {"coordinates":[11.11774,48.922092],"type":"Point"}
}