{
  "type": "Feature",
  "properties": {
    "iso:country":"DE",
    "sg:address":"Fattinger Str. 38",
    "sg:city":"Passau",
    "sg:phone":"+49 851/5019780",
    "sg:postcode":"94034",
    "sg:province":"Bayern",
    "wof:name":"David Pharma Gmbh",
    "wof:placetype":"venue"
},
  "geometry": {"coordinates":[13.414905,48.604652],"type":"Point"}
}