{
  "type": "Feature",
  "properties": {
    "iso:country":"DE",
    "sg:address":"Breslauer Str. 29",
    "sg:city":"Axstedt",
    "sg:phone":"+49 4793/2714",
    "sg:postcode":"27729",
    "sg:province":"Niedersachsen",
    "wof:name":"Manfred Sprengler",
    "wof:placetype":"venue"
},
  "geometry": {"coordinates":[8.7732419968,53.3519821167],"type":"Point"}
}