{
  "type": "Feature",
  "properties": {
    "iso:country":"DE",
    "sg:address":"Talstr. 12",
    "sg:city":"Dunzweiler",
    "sg:phone":"+49 6373/4514",
    "sg:postcode":"66916",
    "sg:province":"Rheinland-Pfalz",
    "wof:name":"Mp-bau Gmbh",
    "wof:placetype":"venue"
},
  "geometry": {"coordinates":[7.312017,49.414406],"type":"Point"}
}