{
  "type": "Feature",
  "properties": {
    "iso:country":"DE",
    "sg:address":"Passauer Str. 2",
    "sg:city":"Tittling",
    "sg:phone":"+49 8504/2074",
    "sg:postcode":"94104",
    "sg:province":"Bayern",
    "wof:name":"Raiffeisenbank Dreiburgenland Eg",
    "wof:placetype":"venue"
},
  "geometry": {"coordinates":[13.380499,48.726986],"type":"Point"}
}