{
  "type": "Feature",
  "properties": {
    "iso:country":"DE",
    "sg:address":"Halle-Kasseler-Str. 5a",
    "sg:city":"Arenshausen",
    "sg:postcode":"37318",
    "sg:province":"Th\u00fcringen",
    "wof:name":"H. Pedziwiatr",
    "wof:placetype":"venue"
},
  "geometry": {"coordinates":[9.973299,51.37738],"type":"Point"}
}