{
  "type": "Feature",
  "properties": {
    "iso:country":"DE",
    "sg:address":"Im St\u00e4dtle 122",
    "sg:city":"Veringenstadt",
    "sg:phone":"+49 7577/7326",
    "sg:postcode":"72519",
    "sg:province":"Baden-W\u00fcrttemberg",
    "wof:name":"Hof-apotheke",
    "wof:placetype":"venue"
},
  "geometry": {"coordinates":[9.213042,48.178528],"type":"Point"}
}