{
  "type": "Feature",
  "properties": {
    "iso:country":"DE",
    "sg:address":"An der Wabeck 40",
    "sg:city":"Witten",
    "sg:phone":"+49 2302/71600",
    "sg:postcode":"58456",
    "sg:province":"Nordrhein-Westfalen",
    "wof:name":"J\u00fcst-werkzeuge J\u00fcrgen Stelmaszyk Gmbh",
    "wof:placetype":"venue"
},
  "geometry": {"coordinates":[7.2825632095,51.4160499573],"type":"Point"}
}