{
  "type": "Feature",
  "properties": {
    "iso:country":"DE",
    "sg:address":"Heidestr. 152 b",
    "sg:city":"Frankfurt",
    "sg:phone":"+49 69/453294",
    "sg:postcode":"60385",
    "sg:province":"Hessen",
    "wof:name":"Zur Stra\u00dfenbahn",
    "wof:placetype":"venue"
},
  "geometry": {"coordinates":[8.7087306976,50.1274642944],"type":"Point"}
}