{
  "type": "Feature",
  "properties": {
    "iso:country":"DE",
    "sg:address":"Hebelstr. 7",
    "sg:city":"Ispringen",
    "sg:phone":"+49 7231/89698",
    "sg:postcode":"75228",
    "sg:province":"Baden-W\u00fcrttemberg",
    "wof:name":"Gerd Sch\u00e4fer Finanzberater",
    "wof:placetype":"venue"
},
  "geometry": {"coordinates":[8.6690654755,48.9109802246],"type":"Point"}
}