{
  "type": "Feature",
  "properties": {
    "iso:country":"DE",
    "sg:address":"Bruder-Georg-Weg 13",
    "sg:city":"Pfronten",
    "sg:phone":"+49 8363/94042",
    "sg:postcode":"87459",
    "sg:province":"Bayern",
    "wof:name":"I. Und W. Schmucker",
    "wof:placetype":"venue"
},
  "geometry": {"coordinates":[10.5667695999,47.597076416],"type":"Point"}
}