{
  "type": "Feature",
  "properties": {
    "iso:country":"DE",
    "sg:address":"Aivoglweg 30",
    "sg:city":"F\u00fcrstenzell",
    "sg:phone":"+49 8502/1791",
    "sg:postcode":"94081",
    "sg:province":"Bayern",
    "wof:name":"Josef Spr\u00f6dhuber",
    "wof:placetype":"venue"
},
  "geometry": {"coordinates":[13.313317,48.529987],"type":"Point"}
}