{
  "type": "Feature",
  "properties": {
    "iso:country":"DE",
    "sg:address":"Boschgotthardsh\u00fctte 46",
    "sg:city":"Siegen",
    "sg:phone":"+49 271/70940",
    "sg:postcode":"57076",
    "sg:province":"Nordrhein-Westfalen",
    "wof:name":"Stabo Stahlbau Boschgotthardsh\u00fctte Gmbh",
    "wof:placetype":"venue"
},
  "geometry": {"coordinates":[8.0205335617,50.9015083313],"type":"Point"}
}