{
  "type": "Feature",
  "properties": {
    "iso:country":"DE",
    "sg:address":"Weisendorfer Str. 2 a",
    "sg:city":"Erlangen",
    "sg:phone":"+49 9135/544",
    "sg:postcode":"91056",
    "sg:province":"Bayern",
    "wof:name":"Aral Ag",
    "wof:placetype":"venue"
},
  "geometry": {"coordinates":[10.9381437302,49.6265563965],"type":"Point"}
}