{
  "type": "Feature",
  "properties": {
    "iso:country":"DE",
    "sg:address":"Stader Str. 27",
    "sg:city":"Oyten",
    "sg:phone":"+49 4207/5613",
    "sg:postcode":"28876",
    "sg:province":"Niedersachsen",
    "wof:name":"A. Br\u00fcckner",
    "wof:placetype":"venue"
},
  "geometry": {"coordinates":[9.0118331909,53.0632476807],"type":"Point"}
}