{
  "type": "Feature",
  "properties": {
    "iso:country":"DE",
    "sg:address":"Lange Str. 5",
    "sg:city":"Drakenburg",
    "sg:phone":"+49 5024/269",
    "sg:postcode":"31623",
    "sg:province":"Niedersachsen",
    "wof:name":"Friedrich Th\u00f6lke",
    "wof:placetype":"venue"
},
  "geometry": {"coordinates":[9.209314,52.687897],"type":"Point"}
}