{
  "type": "Feature",
  "properties": {
    "iso:country":"DE",
    "sg:address":"Wichernstr. 2",
    "sg:city":"Aachen",
    "sg:phone":"+49 241/73915",
    "sg:postcode":"52064",
    "sg:province":"Nordrhein-Westfalen",
    "wof:name":"Verein F\u00fcr Diakonie E. V.",
    "wof:placetype":"venue"
},
  "geometry": {"coordinates":[6.075691,50.76656],"type":"Point"}
}