{
  "type": "Feature",
  "properties": {
    "iso:country":"DE",
    "sg:address":"Wyhlertalstr. 9",
    "sg:city":"Wyhl",
    "sg:phone":"+49 7642/3362",
    "sg:postcode":"79369",
    "sg:province":"Baden-W\u00fcrttemberg",
    "wof:name":"Markus K\u00f6bele",
    "wof:placetype":"venue"
},
  "geometry": {"coordinates":[7.650744915,48.1614265442],"type":"Point"}
}