{
  "type": "Feature",
  "properties": {
    "iso:country":"DE",
    "sg:address":"Hauptstr. 200",
    "sg:city":"Himmelstadt",
    "sg:phone":"+49 9364/2328",
    "sg:postcode":"97267",
    "sg:province":"Bayern",
    "wof:name":"Karl Mehling",
    "wof:placetype":"venue"
},
  "geometry": {"coordinates":[9.80104,49.928757],"type":"Point"}
}