{
  "type": "Feature",
  "properties": {
    "iso:country":"DE",
    "sg:address":"Pfarrkirchner Str. 3",
    "sg:city":"Simbach",
    "sg:phone":"+49 8571/60570",
    "sg:postcode":"84359",
    "sg:province":"Bayern",
    "wof:name":"Passauer Neue Presse",
    "wof:placetype":"venue"
},
  "geometry": {"coordinates":[13.0268859863,48.267780304],"type":"Point"}
}