{
  "type": "Feature",
  "properties": {
    "iso:country":"DE",
    "sg:address":"Gro\u00dfe Gosenstr. 41",
    "sg:city":"Halle",
    "sg:phone":"+49 345/520890",
    "sg:postcode":"06114",
    "sg:province":"Sachsen-Anhalt",
    "wof:name":"Pension Am Volkspark",
    "wof:placetype":"venue"
},
  "geometry": {"coordinates":[11.9650096893,51.4992599487],"type":"Point"}
}