{
  "type": "Feature",
  "properties": {
    "iso:country":"DE",
    "sg:address":"R\u00f6merh\u00fcgel 7",
    "sg:city":"Mayen",
    "sg:phone":"+49 2651/947133",
    "sg:postcode":"56727",
    "sg:province":"Rheinland-Pfalz",
    "wof:name":"Werner Frowitter",
    "wof:placetype":"venue"
},
  "geometry": {"coordinates":[7.2250828743,50.3330574036],"type":"Point"}
}