{
  "type": "Feature",
  "properties": {
    "iso:country":"DE",
    "sg:address":"Sitter 25",
    "sg:city":"Visbek",
    "sg:phone":"+49 4445/412",
    "sg:postcode":"49429",
    "sg:province":"Niedersachsen",
    "wof:name":"Josef Busse",
    "wof:placetype":"venue"
},
  "geometry": {"coordinates":[8.303276062,52.8299255371],"type":"Point"}
}