{
  "type": "Feature",
  "properties": {
    "iso:country":"DE",
    "sg:address":"Tegeler Str. 38",
    "sg:city":"Berlin",
    "sg:phone":"+49 30/45084756",
    "sg:postcode":"13353",
    "sg:province":"Berlin",
    "wof:name":"Asba Tiefbau Gmbh",
    "wof:placetype":"venue"
},
  "geometry": {"coordinates":[13.3573532104,52.5412063599],"type":"Point"}
}