{
  "type": "Feature",
  "properties": {
    "iso:country":"DE",
    "sg:address":"Burgherrenstr. 89",
    "sg:city":"Stuttgart",
    "sg:phone":"+49 711/815733",
    "sg:postcode":"70469",
    "sg:province":"Baden-W\u00fcrttemberg",
    "wof:name":"Dr. Hermann Rettenmaier Rechtsanwalt",
    "wof:placetype":"venue"
},
  "geometry": {"coordinates":[9.1572580338,48.8015365601],"type":"Point"}
}