{
  "type": "Feature",
  "properties": {
    "iso:country":"DE",
    "sg:address":"Landwehrs Brede 9",
    "sg:city":"Steinhagen",
    "sg:phone":"+49 5204/3587",
    "sg:postcode":"33803",
    "sg:province":"Nordrhein-Westfalen",
    "wof:name":"Wilhelm Landwehr Steuerberater",
    "wof:placetype":"venue"
},
  "geometry": {"coordinates":[8.4264812469,52.0223770142],"type":"Point"}
}