{
  "type": "Feature",
  "properties": {
    "iso:country":"DE",
    "sg:address":"Leipziger Str. 30",
    "sg:city":"Fulda",
    "sg:phone":"+49 661/68380",
    "sg:postcode":"36037",
    "sg:province":"Hessen",
    "wof:name":"Rhodos",
    "wof:placetype":"venue"
},
  "geometry": {"coordinates":[9.6802206039,50.5596580505],"type":"Point"}
}