{
  "type": "Feature",
  "properties": {
    "iso:country":"DE",
    "sg:address":"Sinning 1",
    "sg:city":"Rohrdorf",
    "sg:postcode":"83101",
    "sg:province":"Bayern",
    "wof:name":"Zb Ziegelwerke Verwaltung Gmbh",
    "wof:placetype":"venue"
},
  "geometry": {"coordinates":[12.185586,47.79306],"type":"Point"}
}