{
  "type": "Feature",
  "properties": {
    "iso:country":"DE",
    "sg:address":"Basler Str. 83",
    "sg:city":"L\u00f6rrach",
    "sg:phone":"+49 7621/2080",
    "sg:postcode":"79540",
    "sg:province":"Baden-W\u00fcrttemberg",
    "wof:name":"Otal-kunststofftechnik Veit B\u00fcrkle",
    "wof:placetype":"venue"
},
  "geometry": {"coordinates":[7.659077,47.604588],"type":"Point"}
}