{
  "type": "Feature",
  "properties": {
    "iso:country":"DE",
    "sg:address":"Erlanger Str. 4",
    "sg:city":"Uttenreuth",
    "sg:phone":"+49 9131/50019",
    "sg:postcode":"91080",
    "sg:province":"Bayern",
    "wof:name":"Pfaff Ingenieurb\u00fcro",
    "wof:placetype":"venue"
},
  "geometry": {"coordinates":[11.0720682144,49.5968818665],"type":"Point"}
}