{
  "type": "Feature",
  "properties": {
    "iso:country":"DE",
    "sg:address":"Gersteinstr. 7",
    "sg:city":"Ahlen",
    "sg:phone":"+49 4923/826611",
    "sg:postcode":"59227",
    "sg:province":"Nordrhein-Westfalen",
    "wof:name":"Landmaschinenvertrieb Katharina Schmuecker-geringhoff Gmbh",
    "wof:placetype":"venue"
},
  "geometry": {"coordinates":[7.929031,51.775471],"type":"Point"}
}