{
  "type": "Feature",
  "properties": {
    "iso:country":"DE",
    "sg:address":"Postfach 1454:: 26851 Papenburg:: Germany.^^Hauptkanal links 60-63::",
    "sg:city":"Papenburg",
    "sg:phone":"+49 4961/9870",
    "sg:postcode":"26871",
    "sg:province":"Niedersachsen",
    "wof:name":"Sparkasse Emsland",
    "wof:placetype":"venue"
},
  "geometry": {"coordinates":[7.42354,53.072861],"type":"Point"}
}