{
  "type": "Feature",
  "properties": {
    "iso:country":"DE",
    "sg:address":"Schwanenmarkt 4",
    "sg:city":"Bochum",
    "sg:phone":"+49 234/14882",
    "sg:postcode":"44787",
    "sg:province":"Nordrhein-Westfalen",
    "wof:name":"H. D. Kronberg",
    "wof:placetype":"venue"
},
  "geometry": {"coordinates":[7.2226080894,51.4832267761],"type":"Point"}
}