{
  "type": "Feature",
  "properties": {
    "iso:country":"DE",
    "sg:address":"Albrecht-Thaer-Str.",
    "sg:city":"L\u00fcchow",
    "sg:postcode":"29439",
    "sg:province":"Niedersachsen",
    "wof:name":"Fricke Transporte Ohg",
    "wof:placetype":"venue"
},
  "geometry": {"coordinates":[11.1658468246,52.9845199585],"type":"Point"}
}