{
  "type": "Feature",
  "properties": {
    "iso:country":"DE",
    "sg:address":"Hornbergstr. 101",
    "sg:city":"Stuttgart",
    "sg:postcode":"70188",
    "sg:province":"Baden-W\u00fcrttemberg",
    "wof:name":"Ev. \u00d6ffentliche Bibliothek Gaisburg",
    "wof:placetype":"venue"
},
  "geometry": {"coordinates":[9.216735,48.782375],"type":"Point"}
}