{
  "type": "Feature",
  "properties": {
    "iso:country":"DE",
    "sg:address":"Wernher-von-Braun-Str. 3",
    "sg:city":"Ampfing",
    "sg:phone":"+49 8636/988219",
    "sg:postcode":"84539",
    "sg:province":"Bayern",
    "wof:name":"Surfcat Verm\u00f6gens- Verwaltungs Gmbh",
    "wof:placetype":"venue"
},
  "geometry": {"coordinates":[12.409526825,48.2489547729],"type":"Point"}
}