{
  "type": "Feature",
  "properties": {
    "iso:country":"DE",
    "sg:address":"Munzinger Str. 1",
    "sg:city":"Freiburg",
    "sg:phone":"+49 761/207780",
    "sg:postcode":"79111",
    "sg:province":"Baden-W\u00fcrttemberg",
    "wof:name":"Crossair Ag",
    "wof:placetype":"venue"
},
  "geometry": {"coordinates":[7.796002,47.988823],"type":"Point"}
}