{
  "type": "Feature",
  "properties": {
    "iso:country":"DE",
    "sg:address":"Am Zeughaus 5",
    "sg:city":"Schweinfurt",
    "sg:phone":"+49 9721/24427",
    "sg:postcode":"97421",
    "sg:province":"Bayern",
    "wof:name":"B\u00fcrgerbr\u00e4u Trinkstube",
    "wof:placetype":"venue"
},
  "geometry": {"coordinates":[10.2298021317,50.0455741882],"type":"Point"}
}