{
  "type": "Feature",
  "properties": {
    "iso:country":"DE",
    "sg:address":"Widdersteinstr. 6-8",
    "sg:city":"Stuttgart",
    "sg:phone":"+49 711/330437",
    "sg:postcode":"70327",
    "sg:province":"Baden-W\u00fcrttemberg",
    "wof:name":"L. Und E. Zaiss Inh. Eberhard Bauer",
    "wof:placetype":"venue"
},
  "geometry": {"coordinates":[9.252074,48.780163],"type":"Point"}
}