{
  "type": "Feature",
  "properties": {
    "iso:country":"DE",
    "sg:address":"Am Stadtgraben 12",
    "sg:city":"Abensberg",
    "sg:phone":"+49 9443/5646",
    "sg:postcode":"93326",
    "sg:province":"Bayern",
    "wof:name":"Lohr Wettannahme",
    "wof:placetype":"venue"
},
  "geometry": {"coordinates":[11.846084,48.817078],"type":"Point"}
}