{
  "type": "Feature",
  "properties": {
    "iso:country":"DE",
    "sg:address":"Denickestr. 92",
    "sg:city":"Hamburg",
    "sg:phone":"+49 40/7903904",
    "sg:postcode":"21075",
    "sg:province":"Hamburg",
    "wof:name":"Ulrich Walliser",
    "wof:placetype":"venue"
},
  "geometry": {"coordinates":[9.957608223,53.4597434998],"type":"Point"}
}