{
  "type": "Feature",
  "properties": {
    "iso:country":"DE",
    "sg:address":"Hauptstr. 27",
    "sg:city":"Brombachtal",
    "sg:phone":"+49 6063/1255",
    "sg:postcode":"64753",
    "sg:province":"Hessen",
    "wof:name":"Zur Traube",
    "wof:placetype":"venue"
},
  "geometry": {"coordinates":[8.9590091705,49.7307014465],"type":"Point"}
}