{
  "type": "Feature",
  "properties": {
    "iso:country":"DE",
    "sg:address":"Isernhagener Str. 56",
    "sg:city":"Hannover",
    "sg:phone":"+49 511/666807",
    "sg:postcode":"30163",
    "sg:province":"Niedersachsen",
    "wof:name":"Heinz Sperling Architekt",
    "wof:placetype":"venue"
},
  "geometry": {"coordinates":[9.740366,52.392483],"type":"Point"}
}