{
  "type": "Feature",
  "properties": {
    "iso:country":"DE",
    "sg:address":"Hofheimer Str. 57",
    "sg:city":"Hofheim",
    "sg:phone":"+49 6192/6270",
    "sg:postcode":"65719",
    "sg:province":"Hessen",
    "wof:name":"R\u00fchl",
    "wof:placetype":"venue"
},
  "geometry": {"coordinates":[8.426255,50.112423],"type":"Point"}
}