{
  "type": "Feature",
  "properties": {
    "iso:country":"DE",
    "sg:address":"Warendorfer Str. 120",
    "sg:city":"Ahlen",
    "sg:phone":"+49 2382/89000",
    "sg:postcode":"59227",
    "sg:province":"Nordrhein-Westfalen",
    "wof:name":"Global Warenvertriebsges. Zindel Mbh & Co.",
    "wof:placetype":"venue"
},
  "geometry": {"coordinates":[7.897481,51.77544],"type":"Point"}
}