{
  "type": "Feature",
  "properties": {
    "iso:country":"DE",
    "sg:address":"Burgstr. 6",
    "sg:city":"Mannheim",
    "sg:phone":"+49 621/442170",
    "sg:postcode":"68165",
    "sg:province":"Baden-W\u00fcrttemberg",
    "wof:name":"H. Bordne Und R. Schmied",
    "wof:placetype":"venue"
},
  "geometry": {"coordinates":[8.482487,49.474712],"type":"Point"}
}