{
  "type": "Feature",
  "properties": {
    "iso:country":"DE",
    "sg:address":"Geiststr. 15",
    "sg:city":"Lippstadt",
    "sg:phone":"+49 2941/58410",
    "sg:postcode":"59555",
    "sg:province":"Nordrhein-Westfalen",
    "wof:name":"Udo Epping",
    "wof:placetype":"venue"
},
  "geometry": {"coordinates":[8.3485479355,51.6754646301],"type":"Point"}
}