{
  "type": "Feature",
  "properties": {
    "iso:country":"DE",
    "sg:address":"Marktstr 31",
    "sg:city":"Remchingen",
    "sg:phone":"+49 7232/734070",
    "sg:postcode":"75196",
    "sg:province":"Baden-W\u00fcrttemberg",
    "wof:name":"Ultratec",
    "wof:placetype":"venue"
},
  "geometry": {"coordinates":[8.566705,48.957722],"type":"Point"}
}