{
  "type": "Feature",
  "properties": {
    "iso:country":"DE",
    "sg:address":"Freudenthaler Str. 8",
    "sg:city":"Taunusstein",
    "sg:phone":"+49 6128/86699",
    "sg:postcode":"65232",
    "sg:province":"Hessen",
    "wof:name":"Dr. Med. Frank A. Huttel Arzt F\u00fcr Psychotherapie",
    "wof:placetype":"venue"
},
  "geometry": {"coordinates":[8.1979455948,50.1535224915],"type":"Point"}
}