{
  "type": "Feature",
  "properties": {
    "iso:country":"DE",
    "sg:address":"Hauptstr. 1",
    "sg:city":"Stockach",
    "sg:phone":"+49 7771/4424",
    "sg:postcode":"78333",
    "sg:province":"Baden-W\u00fcrttemberg",
    "wof:name":"W. Feyel",
    "wof:placetype":"venue"
},
  "geometry": {"coordinates":[9.0116930008,47.8519058228],"type":"Point"}
}