{
  "type": "Feature",
  "properties": {
    "iso:country":"DE",
    "sg:address":"Licher Str. 5",
    "sg:city":"Pohlheim",
    "sg:phone":"+49 6404/4791",
    "sg:postcode":"35415",
    "sg:province":"Hessen",
    "wof:name":"Bernd Bopp",
    "wof:placetype":"venue"
},
  "geometry": {"coordinates":[8.74978,50.537624],"type":"Point"}
}