{
  "type": "Feature",
  "properties": {
    "iso:country":"DE",
    "sg:address":"Im Schlop 11",
    "sg:city":"Kranenburg",
    "sg:phone":"+49 2826/90400",
    "sg:postcode":"47559",
    "sg:province":"Nordrhein-Westfalen",
    "wof:name":"H.s.h. H\u00e4rterei-service Hoenselaer Gmbh",
    "wof:placetype":"venue"
},
  "geometry": {"coordinates":[6.0553817749,51.7843170166],"type":"Point"}
}