{
  "type": "Feature",
  "properties": {
    "iso:country":"DE",
    "sg:address":"Bamberger Str. 8",
    "sg:city":"Neustadt",
    "sg:phone":"+49 9161/60406",
    "sg:postcode":"91413",
    "sg:province":"Bayern",
    "wof:name":"Brillen Herch Gmbh",
    "wof:placetype":"venue"
},
  "geometry": {"coordinates":[10.6093330383,49.5805358887],"type":"Point"}
}