{
  "type": "Feature",
  "properties": {
    "iso:country":"DE",
    "sg:address":"Goethestr. 2",
    "sg:city":"M\u00fchlberg",
    "sg:postcode":"99869",
    "sg:province":"Th\u00fcringen",
    "wof:name":"Ev.-luth. Kirche Muehlberg",
    "wof:placetype":"venue"
},
  "geometry": {"coordinates":[10.8230867386,50.8671302795],"type":"Point"}
}