{
  "type": "Feature",
  "properties": {
    "iso:country":"DE",
    "sg:address":"St.-Getreu-Str. 19",
    "sg:city":"Bamberg",
    "sg:phone":"+49 951/58330",
    "sg:postcode":"96049",
    "sg:province":"Bayern",
    "wof:name":"Klaus Heinle Ingenieur",
    "wof:placetype":"venue"
},
  "geometry": {"coordinates":[10.8691911697,49.8908119202],"type":"Point"}
}