{
  "type": "Feature",
  "properties": {
    "iso:country":"DE",
    "sg:address":"Dobbheide 48",
    "sg:city":"Bremen",
    "sg:phone":"+49 421/6582576",
    "sg:postcode":"28755",
    "sg:province":"Bremen",
    "wof:name":"L Incontro",
    "wof:placetype":"venue"
},
  "geometry": {"coordinates":[8.6290187836,53.1880378723],"type":"Point"}
}