{
  "type": "Feature",
  "properties": {
    "iso:country":"DE",
    "sg:address":"Wollhausstr. 60-62",
    "sg:city":"Heilbronn",
    "sg:phone":"+49 7131/8860",
    "sg:postcode":"74072",
    "sg:province":"Baden-W\u00fcrttemberg",
    "wof:name":"Brunnen Papier Gmbh",
    "wof:placetype":"venue"
},
  "geometry": {"coordinates":[9.227881,49.138699],"type":"Point"}
}