{
  "type": "Feature",
  "properties": {
    "iso:country":"DE",
    "sg:address":"Goethestr. 9a",
    "sg:city":"Contwig",
    "sg:phone":"+49 3731/399920",
    "sg:postcode":"66497",
    "sg:province":"Rheinland-Pfalz",
    "wof:name":"P. Sch\u00f6nenberger",
    "wof:placetype":"venue"
},
  "geometry": {"coordinates":[7.4226307869,49.2541313171],"type":"Point"}
}