{
  "type": "Feature",
  "properties": {
    "iso:country":"DE",
    "sg:address":"Goethestr. 18",
    "sg:city":"Waldkirch",
    "sg:phone":"+49 7681/5209",
    "sg:postcode":"79183",
    "sg:province":"Baden-W\u00fcrttemberg",
    "wof:name":"Schwimmbad",
    "wof:placetype":"venue"
},
  "geometry": {"coordinates":[7.9586601257,48.0895500183],"type":"Point"}
}