{
  "type": "Feature",
  "properties": {
    "iso:country":"DE",
    "sg:address":"Gebhartgasse 18",
    "sg:city":"Lenggries",
    "sg:phone":"+49 8042/2832",
    "sg:postcode":"83661",
    "sg:province":"Bayern",
    "wof:name":"Fremdenheim N. Danner",
    "wof:placetype":"venue"
},
  "geometry": {"coordinates":[11.5784330368,47.6831665039],"type":"Point"}
}