{
  "type": "Feature",
  "properties": {
    "iso:country":"DE",
    "sg:address":"Baukampstr. 25",
    "sg:city":"Duisburg",
    "sg:phone":"+49 203/311142",
    "sg:postcode":"47059",
    "sg:province":"Nordrhein-Westfalen",
    "wof:name":"M. Gasser-westenberger Steuerberater",
    "wof:placetype":"venue"
},
  "geometry": {"coordinates":[6.7507810593,51.4396781921],"type":"Point"}
}