{
  "type": "Feature",
  "properties": {
    "iso:country":"DE",
    "sg:address":"Hauptstr. 5",
    "sg:city":"Bubenreuth",
    "sg:phone":"+49 9131/898886",
    "sg:postcode":"91088",
    "sg:province":"Bayern",
    "wof:name":"Gerd Schmidt Rechtsanwalt",
    "wof:placetype":"venue"
},
  "geometry": {"coordinates":[11.0165891647,49.6278419495],"type":"Point"}
}