{
  "type": "Feature",
  "properties": {
    "iso:country":"DE",
    "sg:address":"Auf der Langweid",
    "sg:city":"Stadecken-Elsheim",
    "sg:phone":"+49 6136/3349",
    "sg:postcode":"55271",
    "sg:province":"Rheinland-Pfalz",
    "wof:name":"Hl Markt",
    "wof:placetype":"venue"
},
  "geometry": {"coordinates":[8.1287746429,49.9125442505],"type":"Point"}
}