{
  "type": "Feature",
  "properties": {
    "iso:country":"DE",
    "sg:address":"Hunsr\u00fcckstr. 16",
    "sg:city":"Bochum",
    "sg:phone":"+49 234/865309",
    "sg:postcode":"44805",
    "sg:province":"Nordrhein-Westfalen",
    "wof:name":"Alfred Wolf",
    "wof:placetype":"venue"
},
  "geometry": {"coordinates":[7.248129,51.51075],"type":"Point"}
}