{
  "type": "Feature",
  "properties": {
    "iso:country":"DE",
    "sg:address":"Erzbischof-Anno-Str. 25",
    "sg:city":"Alpen",
    "sg:phone":"+49 2802/1733",
    "sg:postcode":"46519",
    "sg:province":"Nordrhein-Westfalen",
    "wof:name":"Elektro Tekolf Gmbh",
    "wof:placetype":"venue"
},
  "geometry": {"coordinates":[6.521106,51.576191],"type":"Point"}
}