{
  "type": "Feature",
  "properties": {
    "iso:country":"DE",
    "sg:address":"Meierfeld 12",
    "sg:city":"Rinteln",
    "sg:phone":"+49 5751/3853",
    "sg:postcode":"31737",
    "sg:province":"Niedersachsen",
    "wof:name":"Siegward Melcher",
    "wof:placetype":"venue"
},
  "geometry": {"coordinates":[9.0828552246,52.1554107666],"type":"Point"}
}