{
  "type": "Feature",
  "properties": {
    "iso:country":"DE",
    "sg:address":"Ratsallee 8",
    "sg:city":"Viersen",
    "sg:phone":"+49 2162/67030",
    "sg:postcode":"41749",
    "sg:province":"Nordrhein-Westfalen",
    "wof:name":"Heinz-bernd Rath",
    "wof:placetype":"venue"
},
  "geometry": {"coordinates":[6.37059,51.290741],"type":"Point"}
}