{
  "type": "Feature",
  "properties": {
    "iso:country":"DE",
    "sg:address":"97816",
    "sg:city":"Lohr",
    "sg:postcode":"97816",
    "sg:province":"Bayern",
    "wof:name":"Campingplatz",
    "wof:placetype":"venue"
},
  "geometry": {"coordinates":[9.57905,50.02301],"type":"Point"}
}