{
  "type": "Feature",
  "properties": {
    "iso:country":"DE",
    "sg:address":"Am L\u00fclingsbusch 11",
    "sg:city":"Geseke",
    "sg:phone":"+49 2942/8154",
    "sg:postcode":"59590",
    "sg:province":"Nordrhein-Westfalen",
    "wof:name":"Wresche Elektrotechnik Verwaltungs Gmbh",
    "wof:placetype":"venue"
},
  "geometry": {"coordinates":[8.5083761215,51.6280212402],"type":"Point"}
}