{
  "type": "Feature",
  "properties": {
    "iso:country":"DE",
    "sg:address":"Stadtweg 48",
    "sg:city":"Schleswig",
    "sg:phone":"+49 4621/96210",
    "sg:postcode":"24837",
    "sg:province":"Schleswig-Holstein",
    "wof:name":"Abc-apotheke W. Meinhardt Inh. Angela Meinhardt",
    "wof:placetype":"venue"
},
  "geometry": {"coordinates":[9.56228,54.516563],"type":"Point"}
}