{
  "type": "Feature",
  "properties": {
    "iso:country":"DE",
    "sg:address":"Kaiser-Friedrich-Str. 39",
    "sg:city":"Duisburg",
    "sg:phone":"+49 203/402655",
    "sg:postcode":"47169",
    "sg:province":"Nordrhein-Westfalen",
    "wof:name":"Hans-joachim Schmitz Augenoptiker",
    "wof:placetype":"venue"
},
  "geometry": {"coordinates":[6.761329174,51.5045585632],"type":"Point"}
}