{
  "type": "Feature",
  "properties": {
    "iso:country":"DE",
    "sg:address":"\u00dcberaucher Str. 18",
    "sg:city":"Villingen-Schwenningen",
    "sg:phone":"+49 7705/5454",
    "sg:postcode":"78052",
    "sg:province":"Baden-W\u00fcrttemberg",
    "wof:name":"H. Schlenker Holzbildhauer",
    "wof:placetype":"venue"
},
  "geometry": {"coordinates":[8.418239,47.999851],"type":"Point"}
}