{
  "type": "Feature",
  "properties": {
    "iso:country":"DE",
    "sg:address":"Melanchthonstr. 23",
    "sg:city":"T\u00fcbingen",
    "sg:phone":"+49 7071/52634",
    "sg:postcode":"72074",
    "sg:province":"Baden-W\u00fcrttemberg",
    "wof:name":"Goeckel Und Schulz Rechtsanw\u00e4lte",
    "wof:placetype":"venue"
},
  "geometry": {"coordinates":[9.061457634,48.5279045105],"type":"Point"}
}