{
  "type": "Feature",
  "properties": {
    "iso:country":"DE",
    "sg:address":"Lingener Str. 11",
    "sg:city":"Rheine",
    "sg:phone":"+49 5971/862360",
    "sg:postcode":"48429",
    "sg:province":"Nordrhein-Westfalen",
    "wof:name":"Caritasverband F\u00dcr Stadt & Dekanat Rheine",
    "wof:placetype":"venue"
},
  "geometry": {"coordinates":[7.442725,52.280827],"type":"Point"}
}