{
  "type": "Feature",
  "properties": {
    "iso:country":"DE",
    "sg:address":"Brechtener Str. 148",
    "sg:city":"L\u00fcnen",
    "sg:phone":"+49 231/870855",
    "sg:postcode":"44536",
    "sg:province":"Nordrhein-Westfalen",
    "wof:name":"Arthur Hoffmann",
    "wof:placetype":"venue"
},
  "geometry": {"coordinates":[7.4468917847,51.5852622986],"type":"Point"}
}