{
  "type": "Feature",
  "properties": {
    "iso:country":"DE",
    "sg:address":"Paul-Sch\u00fctz-Str. 1",
    "sg:city":"Krefeld",
    "sg:phone":"+49 177 7725350",
    "sg:postcode":"47800",
    "sg:province":"Nordrhein-Westfalen",
    "wof:name":"A & M Jansen Messebau Gmbh",
    "wof:placetype":"venue"
},
  "geometry": {"coordinates":[6.5847029686,51.3406448364],"type":"Point"}
}