{
  "type": "Feature",
  "properties": {
    "iso:country":"DE",
    "sg:city":"Castrop-Rauxel",
    "sg:phone":"+49 2305/360660",
    "sg:postcode":"44577",
    "sg:province":"Nordrhein-Westfalen",
    "wof:name":"0190 / 0900 Service Provider Bi-pro",
    "wof:placetype":"venue"
},
  "geometry": {"coordinates":[7.322055,51.52726],"type":"Point"}
}