{
  "type": "Feature",
  "properties": {
    "iso:country":"DE",
    "sg:address":"Stockshausstr. 11",
    "sg:city":"Hilden",
    "sg:phone":"+49 2103/45858",
    "sg:postcode":"40721",
    "sg:province":"Nordrhein-Westfalen",
    "wof:name":"Jung Pumpen Gmbh & Co.",
    "wof:placetype":"venue"
},
  "geometry": {"coordinates":[6.924655,51.177277],"type":"Point"}
}