{
  "type": "Feature",
  "properties": {
    "iso:country":"DE",
    "sg:address":"Franz-Wunner-Str. 15",
    "sg:city":"Mindelheim",
    "sg:phone":"+49 8261/4551",
    "sg:postcode":"87719",
    "sg:province":"Bayern",
    "wof:name":"J. Mussack",
    "wof:placetype":"venue"
},
  "geometry": {"coordinates":[10.5105733871,48.0806617737],"type":"Point"}
}