{
  "type": "Feature",
  "properties": {
    "iso:country":"DE",
    "sg:address":"Scheffelstr. 3",
    "sg:city":"Neuenb\u00fcrg",
    "sg:phone":"+49 7082/3374",
    "sg:postcode":"75305",
    "sg:province":"Baden-W\u00fcrttemberg",
    "wof:name":"Ludwig Ellerkamp",
    "wof:placetype":"venue"
},
  "geometry": {"coordinates":[8.582277,48.848923],"type":"Point"}
}