{
  "type": "Feature",
  "properties": {
    "iso:country":"DE",
    "sg:address":"Bahnhofsplatz 2",
    "sg:city":"Ebersberg",
    "sg:phone":"+49 8092/22380",
    "sg:postcode":"85560",
    "sg:province":"Bayern",
    "wof:name":"Dr. Klaus Bischoff Zahnarzt",
    "wof:placetype":"venue"
},
  "geometry": {"coordinates":[11.970859,48.075432],"type":"Point"}
}