{
  "type": "Feature",
  "properties": {
    "iso:country":"DE",
    "sg:address":"Weberstr. 30",
    "sg:city":"Konradsreuth",
    "sg:phone":"+49 9292/6699",
    "sg:postcode":"95176",
    "sg:province":"Bayern",
    "wof:name":"D. Eckhardt Werbeberater",
    "wof:placetype":"venue"
},
  "geometry": {"coordinates":[11.8435897827,50.2666625977],"type":"Point"}
}