{
  "type": "Feature",
  "properties": {
    "iso:country":"DE",
    "sg:address":"Sterkrader Str. 266",
    "sg:city":"Dinslaken",
    "sg:phone":"+49 2064/90963",
    "sg:postcode":"46539",
    "sg:province":"Nordrhein-Westfalen",
    "wof:name":"D. M\u00f6lleken",
    "wof:placetype":"venue"
},
  "geometry": {"coordinates":[6.7646369934,51.5620079041],"type":"Point"}
}