{
  "type": "Feature",
  "properties": {
    "iso:country":"DE",
    "sg:address":"Amselweg 9",
    "sg:city":"Eckental",
    "sg:phone":"+49 9126/286240",
    "sg:postcode":"90542",
    "sg:province":"Bayern",
    "wof:name":"B. Vogel",
    "wof:placetype":"venue"
},
  "geometry": {"coordinates":[11.2200555801,49.5785446167],"type":"Point"}
}