{
  "type": "Feature",
  "properties": {
    "iso:country":"DE",
    "sg:address":"Lange Str. 19",
    "sg:city":"G\u00f6ppingen",
    "sg:phone":"+49 7161/77291",
    "sg:postcode":"73033",
    "sg:province":"Baden-W\u00fcrttemberg",
    "wof:name":"Siegfried H\u00f6ppel",
    "wof:placetype":"venue"
},
  "geometry": {"coordinates":[9.652658,48.703083],"type":"Point"}
}