{
  "type": "Feature",
  "properties": {
    "iso:country":"DE",
    "sg:address":"Hauptstr. 38",
    "sg:city":"Riegel",
    "sg:postcode":"79359",
    "sg:province":"Baden-W\u00fcrttemberg",
    "wof:name":"Ziser Leonhardt Erste Immobilien Kg",
    "wof:placetype":"venue"
},
  "geometry": {"coordinates":[7.7487468719,48.1516876221],"type":"Point"}
}