{
  "type": "Feature",
  "properties": {
    "iso:country":"DE",
    "sg:address":"Strogenstr. 59",
    "sg:city":"Wartenberg",
    "sg:phone":"+49 8762/721206",
    "sg:postcode":"85456",
    "sg:province":"Bayern",
    "wof:name":"Hl-markt Warenhandels Gmbh",
    "wof:placetype":"venue"
},
  "geometry": {"coordinates":[11.9849071503,48.4081039429],"type":"Point"}
}