{
  "type": "Feature",
  "properties": {
    "iso:country":"DE",
    "sg:address":"Tunnelstr. 1",
    "sg:city":"Bayreuth",
    "sg:phone":"+49 921/2208156",
    "sg:postcode":"95448",
    "sg:province":"Bayern",
    "wof:name":"Gastst\u00e4tte Lila Das Original",
    "wof:placetype":"venue"
},
  "geometry": {"coordinates":[11.5787820816,49.9485664368],"type":"Point"}
}