{
  "type": "Feature",
  "properties": {
    "iso:country":"DE",
    "sg:address":"Burgstr. 21",
    "sg:city":"Amstetten",
    "sg:phone":"+49 7336/373",
    "sg:postcode":"73340",
    "sg:province":"Baden-W\u00fcrttemberg",
    "wof:name":"Georg St\u00f6ckle",
    "wof:placetype":"venue"
},
  "geometry": {"coordinates":[9.915928,48.582748],"type":"Point"}
}