{
  "type": "Feature",
  "properties": {
    "iso:country":"DE",
    "sg:address":"M\u00fcnchner Str. 116",
    "sg:city":"Karlsfeld",
    "sg:phone":"+49 8131/91188",
    "sg:postcode":"85757",
    "sg:province":"Bayern",
    "wof:name":"Peter Bechtler Gmbh",
    "wof:placetype":"venue"
},
  "geometry": {"coordinates":[11.4608459473,48.2296981812],"type":"Point"}
}