{
  "type": "Feature",
  "properties": {
    "iso:country":"DE",
    "sg:address":"Neuessener Str. 35",
    "sg:city":"Essen",
    "sg:phone":"+49 201/343274",
    "sg:postcode":"45329",
    "sg:province":"Nordrhein-Westfalen",
    "wof:name":"H. Hochstein",
    "wof:placetype":"venue"
},
  "geometry": {"coordinates":[7.003081,51.504139],"type":"Point"}
}