{
  "type": "Feature",
  "properties": {
    "iso:country":"DE",
    "sg:address":"Ernst-Moritz-Arndt-Str. 96 a",
    "sg:city":"Velbert",
    "sg:phone":"+49 2051/96300",
    "sg:postcode":"42549",
    "sg:province":"Nordrhein-Westfalen",
    "wof:name":"Ingenieurbau A. Grimmert Gmbh",
    "wof:placetype":"venue"
},
  "geometry": {"coordinates":[7.020842,51.334732],"type":"Point"}
}