{
  "type": "Feature",
  "properties": {
    "iso:country":"DE",
    "sg:address":"Hintere Str. 17",
    "sg:city":"Fellbach",
    "sg:phone":"+49 711/586618",
    "sg:postcode":"70734",
    "sg:province":"Baden-W\u00fcrttemberg",
    "wof:name":"W. Schuch",
    "wof:placetype":"venue"
},
  "geometry": {"coordinates":[9.2760972977,48.8076934814],"type":"Point"}
}