{
  "type": "Feature",
  "properties": {
    "iso:country":"DE",
    "sg:address":"M\u00fchlenstr. 12",
    "sg:city":"Gro\u00df Sch\u00f6nebeck",
    "sg:phone":"+49 33393/453",
    "sg:postcode":"16348",
    "sg:province":"Brandenburg",
    "wof:name":"Werner Kr\u00e4uter",
    "wof:placetype":"venue"
},
  "geometry": {"coordinates":[13.472614,52.755035],"type":"Point"}
}