{
  "type": "Feature",
  "properties": {
    "iso:country":"DE",
    "sg:address":"Dorfstr. 3",
    "sg:city":"Hellwege",
    "sg:phone":"+49 4264/700",
    "sg:postcode":"27367",
    "sg:province":"Niedersachsen",
    "wof:name":"F. Pr\u00fcser",
    "wof:placetype":"venue"
},
  "geometry": {"coordinates":[9.231337,53.076443],"type":"Point"}
}