{
  "type": "Feature",
  "properties": {
    "iso:country":"DE",
    "sg:address":"Fehmarnstr. 14",
    "sg:city":"B\u00fcdelsdorf",
    "sg:postcode":"24782",
    "sg:province":"Schleswig-Holstein",
    "wof:name":"Mtr Hansen Pinske Gmbh & Co. Kg",
    "wof:placetype":"venue"
},
  "geometry": {"coordinates":[9.699842453,54.3222808838],"type":"Point"}
}