{
  "type": "Feature",
  "properties": {
    "iso:country":"DE",
    "sg:address":"Tulpenstr. 4",
    "sg:city":"Eckental",
    "sg:phone":"+49 9126/9360",
    "sg:postcode":"90542",
    "sg:province":"Bayern",
    "wof:name":"Udo Vogel",
    "wof:placetype":"venue"
},
  "geometry": {"coordinates":[11.1885099411,49.57629776],"type":"Point"}
}