{
  "type": "Feature",
  "properties": {
    "iso:country":"DE",
    "sg:address":"Im Haferacker 28",
    "sg:city":"Ellern",
    "sg:phone":"+49 6764/960056",
    "sg:postcode":"55497",
    "sg:province":"Rheinland-Pfalz",
    "wof:name":"Gega Gesellschaft F\u00fcr Energie- Einsparung Und Geb\u00e4ude-",
    "wof:placetype":"venue"
},
  "geometry": {"coordinates":[7.610989,49.991123],"type":"Point"}
}