{
  "type": "Feature",
  "properties": {
    "iso:country":"DE",
    "sg:address":"Schanzenstr. 111",
    "sg:city":"Hamburg",
    "sg:phone":"+49 40/4390040",
    "sg:postcode":"20357",
    "sg:province":"Hamburg",
    "wof:name":"Fulladu",
    "wof:placetype":"venue"
},
  "geometry": {"coordinates":[9.965387,53.564682],"type":"Point"}
}