{
  "type": "Feature",
  "properties": {
    "iso:country":"DE",
    "sg:address":"Barmstedter Str. 34",
    "sg:city":"Ellerhoop",
    "sg:phone":"+49 4120/803",
    "sg:postcode":"25373",
    "sg:province":"Schleswig-Holstein",
    "wof:name":"Walter Hansen",
    "wof:placetype":"venue"
},
  "geometry": {"coordinates":[9.768046,53.726257],"type":"Point"}
}