{
  "type": "Feature",
  "properties": {
    "iso:country":"DE",
    "sg:address":"Kirchstr. 3",
    "sg:city":"Unteregg",
    "sg:phone":"+49 8269/657",
    "sg:postcode":"87782",
    "sg:province":"Bayern",
    "wof:name":"Josef Fr\u00f6hlich",
    "wof:placetype":"venue"
},
  "geometry": {"coordinates":[10.465774,47.963512],"type":"Point"}
}