{
  "type": "Feature",
  "properties": {
    "iso:country":"DE",
    "sg:address":"Brasselsbergstr. 4",
    "sg:city":"Kassel",
    "sg:phone":"+49 561/401016",
    "sg:postcode":"34132",
    "sg:province":"Hessen",
    "wof:name":"Justus Hoffmann Kg",
    "wof:placetype":"venue"
},
  "geometry": {"coordinates":[9.4111728668,51.2947540283],"type":"Point"}
}