{
  "type": "Feature",
  "properties": {
    "iso:country":"DE",
    "sg:address":"Fr\u00fchlingstr. 107",
    "sg:city":"Bad Reichenhall",
    "sg:phone":"+49 8651/78741",
    "sg:postcode":"83435",
    "sg:province":"Bayern",
    "wof:name":"Fliesen Rehm Gmbh",
    "wof:placetype":"venue"
},
  "geometry": {"coordinates":[12.8939390182,47.7417755127],"type":"Point"}
}