{
  "type": "Feature",
  "properties": {
    "iso:country":"DE",
    "sg:address":"Karlstr. 27",
    "sg:city":"Hameln",
    "sg:phone":"+49 5151/13587",
    "sg:postcode":"31785",
    "sg:province":"Niedersachsen",
    "wof:name":"J\u00fcrgen Danielsen",
    "wof:placetype":"venue"
},
  "geometry": {"coordinates":[9.372581,52.10603],"type":"Point"}
}