{
  "type": "Feature",
  "properties": {
    "iso:country":"DE",
    "sg:address":"Deppeweg 2",
    "sg:city":"Detmold",
    "sg:postcode":"32758",
    "sg:province":"Nordrhein-Westfalen",
    "wof:name":"Roses And Leaves",
    "wof:placetype":"venue"
},
  "geometry": {"coordinates":[8.793193,51.95171],"type":"Point"}
}