{
  "type": "Feature",
  "properties": {
    "iso:country":"DE",
    "sg:address":"August-Krogmann-Str. 100",
    "sg:city":"Hamburg",
    "sg:phone":"+49 40/645821",
    "sg:postcode":"22159",
    "sg:province":"Hamburg",
    "wof:name":"Hambg. \u00d6ffentl.b\u00fccherhallen Ausgabestelle Pflegeh. Farmsen",
    "wof:placetype":"venue"
},
  "geometry": {"coordinates":[10.115047,53.613846],"type":"Point"}
}