{
  "type": "Feature",
  "properties": {
    "iso:country":"DE",
    "sg:address":"Hohenstaufenring 43-45",
    "sg:city":"K\u00f6ln",
    "sg:postcode":"50674",
    "sg:province":"Nordrhein-Westfalen",
    "wof:name":"Ditges Und Partner Architekten Stadtplaner",
    "wof:placetype":"venue"
},
  "geometry": {"coordinates":[6.939899,50.932209],"type":"Point"}
}