{
  "type": "Feature",
  "properties": {
    "iso:country":"DE",
    "sg:address":"Jeddeloher Damm 58",
    "sg:city":"Edewecht",
    "sg:phone":"+49 4486/1227",
    "sg:postcode":"26188",
    "sg:province":"Niedersachsen",
    "wof:name":"Erich Kelling",
    "wof:placetype":"venue"
},
  "geometry": {"coordinates":[8.043517,53.122658],"type":"Point"}
}