{
  "type": "Feature",
  "properties": {
    "iso:country":"DE",
    "sg:address":"Plankentalstr. 12",
    "sg:city":"Bad Buchau",
    "sg:phone":"+49 7582/8812",
    "sg:postcode":"88422",
    "sg:province":"Baden-W\u00fcrttemberg",
    "wof:name":"August Jaudas",
    "wof:placetype":"venue"
},
  "geometry": {"coordinates":[9.6041688919,48.0550041199],"type":"Point"}
}