{
  "type": "Feature",
  "properties": {
    "iso:country":"DE",
    "sg:address":"Jungbuschstr. 23",
    "sg:city":"Mannheim",
    "sg:phone":"+49 621/24260",
    "sg:postcode":"68159",
    "sg:province":"Baden-W\u00fcrttemberg",
    "wof:name":"Kapit\u00e4n",
    "wof:placetype":"venue"
},
  "geometry": {"coordinates":[8.4579534531,49.4937553406],"type":"Point"}
}