{
  "type": "Feature",
  "properties": {
    "iso:country":"DE",
    "sg:address":"St.-Peter-Str. 20",
    "sg:city":"M\u00f6nchengladbach",
    "sg:phone":"+49 2161/580162",
    "sg:postcode":"41179",
    "sg:province":"Nordrhein-Westfalen",
    "wof:name":"M. Prinzen Heissmangel",
    "wof:placetype":"venue"
},
  "geometry": {"coordinates":[6.3637061119,51.1466636658],"type":"Point"}
}