{
  "type": "Feature",
  "properties": {
    "iso:country":"DE",
    "sg:address":"Im Breul 14",
    "sg:city":"Bruchk\u00f6bel",
    "sg:phone":"+49 6183/6225",
    "sg:postcode":"63486",
    "sg:province":"Hessen",
    "wof:name":"Norbert K\u00f6hler",
    "wof:placetype":"venue"
},
  "geometry": {"coordinates":[8.9500656128,50.1975212097],"type":"Point"}
}