{
  "type": "Feature",
  "properties": {
    "iso:country":"DE",
    "sg:address":"Waldseeweg 56",
    "sg:city":"Berlin",
    "sg:postcode":"13467",
    "sg:province":"Berlin",
    "wof:name":"Studio M\u00f6belhandelsges. Mbh",
    "wof:placetype":"venue"
},
  "geometry": {"coordinates":[13.3172025681,52.6221160889],"type":"Point"}
}