{
  "type": "Feature",
  "properties": {
    "iso:country":"DE",
    "sg:address":"Sand 2",
    "sg:city":"Prebitz",
    "sg:phone":"+49 9270/354",
    "sg:postcode":"95473",
    "sg:province":"Bayern",
    "wof:name":"A. B\u00e4r",
    "wof:placetype":"venue"
},
  "geometry": {"coordinates":[11.645178,49.809841],"type":"Point"}
}