{
  "type": "Feature",
  "properties": {
    "iso:country":"DE",
    "sg:address":"Viehofer Platz 9",
    "sg:city":"Essen",
    "sg:phone":"+49 201/224476",
    "sg:postcode":"45127",
    "sg:province":"Nordrhein-Westfalen",
    "wof:name":"Kreuz-apotheke",
    "wof:placetype":"venue"
},
  "geometry": {"coordinates":[7.013232,51.462223],"type":"Point"}
}