{
  "type": "Feature",
  "properties": {
    "iso:country":"DE",
    "sg:address":"M\u00f6llingstr. 6",
    "sg:city":"Kiel",
    "sg:phone":"+49 431/9877300",
    "sg:postcode":"24103",
    "sg:province":"Schleswig-Holstein",
    "wof:name":"Christoph Sommermeyer Rechtsanwalt",
    "wof:placetype":"venue"
},
  "geometry": {"coordinates":[10.1262083054,54.3225364685],"type":"Point"}
}