{
  "type": "Feature",
  "properties": {
    "iso:country":"DE",
    "sg:address":"maragarethenstr. 24",
    "sg:city":"oldenburg",
    "sg:phone":"+49 173 9146164",
    "sg:postcode":"26121",
    "sg:province":"Niedersachsen",
    "wof:name":"Warner",
    "wof:placetype":"venue"
},
  "geometry": {"coordinates":[8.20832,53.152889],"type":"Point"}
}