{
  "type": "Feature",
  "properties": {
    "iso:country":"DE",
    "sg:address":"Bad Meinberger Str. 50",
    "sg:city":"Detmold",
    "sg:phone":"+49 5231/58140",
    "sg:postcode":"32760",
    "sg:province":"Nordrhein-Westfalen",
    "wof:name":"Friedrich Br\u00f6ker",
    "wof:placetype":"venue"
},
  "geometry": {"coordinates":[8.944335,51.929039],"type":"Point"}
}