{
  "type": "Feature",
  "properties": {
    "iso:country":"DE",
    "sg:address":"Hauptstr. 59",
    "sg:city":"Sulzfeld",
    "sg:phone":"+49 7269/253",
    "sg:postcode":"75056",
    "sg:province":"Baden-W\u00fcrttemberg",
    "wof:name":"Albrecht Sauter",
    "wof:placetype":"venue"
},
  "geometry": {"coordinates":[8.8566293716,49.1037483215],"type":"Point"}
}