{
  "type": "Feature",
  "properties": {
    "iso:country":"DE",
    "sg:address":"Moos 45",
    "sg:city":"Waldkraiburg",
    "sg:phone":"+49 8638/94140",
    "sg:postcode":"84478",
    "sg:province":"Bayern",
    "wof:name":"Global Immobilien Vermietungs- Und Verwaltungs Gmbh",
    "wof:placetype":"venue"
},
  "geometry": {"coordinates":[12.3969593048,48.1898040771],"type":"Point"}
}