{
  "type": "Feature",
  "properties": {
    "iso:country":"DE",
    "sg:address":"Parkstrasse 34",
    "sg:city":"Wiesbaden",
    "sg:phone":"+49 611/9544121",
    "sg:postcode":"65189",
    "sg:province":"Hessen",
    "wof:name":"Cargo Immobilien Am Flughafen Frankfurt / Main",
    "wof:placetype":"venue"
},
  "geometry": {"coordinates":[8.2576818466,50.0854301453],"type":"Point"}
}