{
  "type": "Feature",
  "properties": {
    "iso:country":"DE",
    "sg:address":"Moritzstr. 27",
    "sg:city":"Bad Gandersheim",
    "sg:phone":"+49 4953/827080",
    "sg:postcode":"37581",
    "sg:province":"Niedersachsen",
    "wof:name":"Gandersheimer Volksbank Eg",
    "wof:placetype":"venue"
},
  "geometry": {"coordinates":[10.0241,51.868317],"type":"Point"}
}