{
  "type": "Feature",
  "properties": {
    "iso:country":"DE",
    "sg:address":"Kiefernweg 4",
    "sg:city":"Wallenhorst",
    "sg:phone":"+49 5407/9223",
    "sg:postcode":"49134",
    "sg:province":"Niedersachsen",
    "wof:name":"Fritz Romann Architekt",
    "wof:placetype":"venue"
},
  "geometry": {"coordinates":[7.999848,52.347363],"type":"Point"}
}