{
  "type": "Feature",
  "properties": {
    "iso:country":"DE",
    "sg:address":"Piepenbrocks Kamp 10",
    "sg:city":"Gronau",
    "sg:phone":"+49 2562/3719",
    "sg:postcode":"48599",
    "sg:province":"Nordrhein-Westfalen",
    "wof:name":"J. Hemming",
    "wof:placetype":"venue"
},
  "geometry": {"coordinates":[7.036485,52.214989],"type":"Point"}
}