{
  "type": "Feature",
  "properties": {
    "iso:country":"DE",
    "sg:address":"Ravensburger Str. 4",
    "sg:city":"Weingarten",
    "sg:phone":"+49 751/560000",
    "sg:postcode":"88250",
    "sg:province":"Baden-W\u00fcrttemberg",
    "wof:name":"Rolf B\u00fcrhaus Architekt",
    "wof:placetype":"venue"
},
  "geometry": {"coordinates":[9.635494,47.803543],"type":"Point"}
}