{
  "type": "Feature",
  "properties": {
    "iso:country":"DE",
    "sg:address":"Langerfelder Str. 150",
    "sg:city":"Wuppertal",
    "sg:phone":"+49 202/602912",
    "sg:postcode":"42389",
    "sg:province":"Nordrhein-Westfalen",
    "wof:name":"R. Stalmann",
    "wof:placetype":"venue"
},
  "geometry": {"coordinates":[7.243262,51.274048],"type":"Point"}
}