{
  "type": "Feature",
  "properties": {
    "iso:country":"DE",
    "sg:address":"Vorsterhauser Weg 46",
    "sg:city":"Hamm",
    "sg:phone":"+49 2381/4220",
    "sg:postcode":"59007",
    "sg:province":"Nordrhein-Westfalen",
    "wof:name":"Altenburger Maschinen J\u00e4ckering Gmbh",
    "wof:placetype":"venue"
},
  "geometry": {"coordinates":[7.7905158997,51.6694641113],"type":"Point"}
}