{
  "type": "Feature",
  "properties": {
    "iso:country":"DE",
    "sg:address":"Ackerstr. 2a",
    "sg:city":"Magdeburg",
    "sg:phone":"+49 391/42890",
    "sg:postcode":"39112",
    "sg:province":"Sachsen-Anhalt",
    "wof:name":"Jahns Verwaltungs Kg",
    "wof:placetype":"venue"
},
  "geometry": {"coordinates":[11.61858,52.114845],"type":"Point"}
}