{
  "type": "Feature",
  "properties": {
    "iso:country":"DE",
    "sg:address":"Zeppelinstr. 12",
    "sg:city":"Gosheim",
    "sg:phone":"+49 4974/2696280",
    "sg:postcode":"78559",
    "sg:province":"Baden-W\u00fcrttemberg",
    "wof:name":"Gosmawerkzeugfabrik Und Metallveredlung Weber Gmbh",
    "wof:placetype":"venue"
},
  "geometry": {"coordinates":[8.763785,48.141151],"type":"Point"}
}