{
  "type": "Feature",
  "properties": {
    "iso:country":"DE",
    "sg:address":"Kampenwandstr. 4",
    "sg:city":"Bergen",
    "sg:phone":"+49 8662/8440",
    "sg:postcode":"83346",
    "sg:province":"Bayern",
    "wof:name":"Hans Rolle Steuerberater Und",
    "wof:placetype":"venue"
},
  "geometry": {"coordinates":[12.5846223831,47.8080863953],"type":"Point"}
}