{
  "type": "Feature",
  "properties": {
    "iso:country":"DE",
    "sg:address":"Fuggerstr. 16",
    "sg:city":"Augsburg",
    "sg:phone":"+49 821/346690",
    "sg:postcode":"86150",
    "sg:province":"Bayern",
    "wof:name":"Herrmann Dr. Wiesner Und Decker",
    "wof:placetype":"venue"
},
  "geometry": {"coordinates":[10.8933095932,48.3688812256],"type":"Point"}
}