{
  "type": "Feature",
  "properties": {
    "iso:country":"DE",
    "sg:address":"Gartenstr. 2a",
    "sg:city":"Bretten",
    "sg:phone":"+49 7252/87543",
    "sg:postcode":"75015",
    "sg:province":"Baden-W\u00fcrttemberg",
    "wof:name":"Liebenzeller Gemeinschaftsverband E. V.",
    "wof:placetype":"venue"
},
  "geometry": {"coordinates":[8.703502,49.038105],"type":"Point"}
}