{
  "type": "Feature",
  "properties": {
    "iso:country":"DE",
    "sg:address":"Courbierestr. 2",
    "sg:city":"Emden",
    "sg:phone":"+49 4921/20017",
    "sg:postcode":"26725",
    "sg:province":"Niedersachsen",
    "wof:name":"Abbo R\u00fcst",
    "wof:placetype":"venue"
},
  "geometry": {"coordinates":[7.2155799866,53.3636703491],"type":"Point"}
}