{
  "type": "Feature",
  "properties": {
    "iso:country":"DE",
    "sg:address":"Auf der Fuchskaul 19b",
    "sg:city":"Essen",
    "sg:phone":"+49 201/711975",
    "sg:postcode":"45149",
    "sg:province":"Nordrhein-Westfalen",
    "wof:name":"Gynescan Laborservice Gmbh",
    "wof:placetype":"venue"
},
  "geometry": {"coordinates":[6.965167,51.419571],"type":"Point"}
}