{
  "type": "Feature",
  "properties": {
    "iso:country":"DE",
    "sg:address":"Brandenburg 41",
    "sg:city":"Zell",
    "sg:phone":"+49 6542/5066",
    "sg:postcode":"56856",
    "sg:province":"Rheinland-Pfalz",
    "wof:name":"Jean Korn",
    "wof:placetype":"venue"
},
  "geometry": {"coordinates":[7.1824479103,50.0203208923],"type":"Point"}
}