{
  "type": "Feature",
  "properties": {
    "iso:country":"DE",
    "sg:address":"Schurwaldstr. 17",
    "sg:city":"Altbach",
    "sg:phone":"+49 7153/76530",
    "sg:postcode":"73776",
    "sg:province":"Baden-W\u00fcrttemberg",
    "wof:name":"Claus Mayer",
    "wof:placetype":"venue"
},
  "geometry": {"coordinates":[9.3867588043,48.7246932983],"type":"Point"}
}