{
  "type": "Feature",
  "properties": {
    "iso:country":"DE",
    "sg:address":"Grabenteichweg 25",
    "sg:city":"K\u00fcnzelsau",
    "sg:phone":"+49 7940/4996",
    "sg:postcode":"74653",
    "sg:province":"Baden-W\u00fcrttemberg",
    "wof:name":"Vereinsgastst\u00e4tte Sportclub Amrichshausen E. V.",
    "wof:placetype":"venue"
},
  "geometry": {"coordinates":[9.7354001999,49.2837257385],"type":"Point"}
}