{
  "type": "Feature",
  "properties": {
    "iso:country":"DE",
    "sg:address":"Bahnhofstr. 9",
    "sg:city":"Gie\u00dfen",
    "sg:phone":"+49 641/74335",
    "sg:postcode":"35390",
    "sg:province":"Hessen",
    "wof:name":"Horten Ag",
    "wof:placetype":"venue"
},
  "geometry": {"coordinates":[8.672225,50.585072],"type":"Point"}
}