{
  "type": "Feature",
  "properties": {
    "iso:country":"DE",
    "sg:address":"Melanchthonstr. 32",
    "sg:city":"Saalfeld",
    "sg:phone":"+49 3671/513221",
    "sg:postcode":"07318",
    "sg:province":"Th\u00fcringen",
    "wof:name":"A. Fischer Und Andrea Braqutt Masseure",
    "wof:placetype":"venue"
},
  "geometry": {"coordinates":[11.350286,50.644402],"type":"Point"}
}