{
  "type": "Feature",
  "properties": {
    "iso:country":"DE",
    "sg:address":"Untere Marktstr. 58",
    "sg:city":"Sonneberg",
    "sg:phone":"+49 3675/702325",
    "sg:postcode":"96515",
    "sg:province":"Th\u00fcringen",
    "wof:name":"Optimal Gmbh",
    "wof:placetype":"venue"
},
  "geometry": {"coordinates":[11.1751823425,50.365688324],"type":"Point"}
}