{
  "type": "Feature",
  "properties": {
    "iso:country":"DE",
    "sg:address":"Schnieglinger Str. 156",
    "sg:city":"N\u00fcrnberg",
    "sg:phone":"+49 911/372780",
    "sg:postcode":"90425",
    "sg:province":"Bayern",
    "wof:name":"Fuchs Dea Schmierstoffe Gmbh & Co. Kg",
    "wof:placetype":"venue"
},
  "geometry": {"coordinates":[11.0397262573,49.4668617249],"type":"Point"}
}