{
  "type": "Feature",
  "properties": {
    "iso:country":"DE",
    "sg:address":"Niedersedlitzer Str 37",
    "sg:city":"Dresden",
    "sg:phone":"+49 351/286930",
    "sg:postcode":"01239",
    "sg:province":"Sachsen",
    "wof:name":"Sw Montage Gmbh",
    "wof:placetype":"venue"
},
  "geometry": {"coordinates":[13.805134,51.008194],"type":"Point"}
}