{
  "type": "Feature",
  "properties": {
    "iso:country":"DE",
    "sg:address":"Am Rheindorfer Bach 15",
    "sg:city":"Br\u00fchl",
    "sg:phone":"+49 2232/31223",
    "sg:postcode":"50321",
    "sg:province":"Nordrhein-Westfalen",
    "wof:name":"Georg Ingensiep Architekt",
    "wof:placetype":"venue"
},
  "geometry": {"coordinates":[6.91157,50.803848],"type":"Point"}
}