{
  "type": "Feature",
  "properties": {
    "iso:country":"DE",
    "sg:address":"Ismaninger Str.",
    "sg:city":"M\u00fcnchen",
    "sg:postcode":"81675",
    "sg:province":"Bayern",
    "wof:name":"Eskiocak Lar Import-export Gmbh",
    "wof:placetype":"venue"
},
  "geometry": {"coordinates":[11.6064376831,48.1490592957],"type":"Point"}
}