{
  "type": "Feature",
  "properties": {
    "iso:country":"DE",
    "sg:address":"Hauptstr. 20",
    "sg:city":"Syke",
    "sg:phone":"+49 4242/2420",
    "sg:postcode":"28857",
    "sg:province":"Niedersachsen",
    "wof:name":"Landes Bausparkasse",
    "wof:placetype":"venue"
},
  "geometry": {"coordinates":[8.822802,52.913574],"type":"Point"}
}