{
  "type": "Feature",
  "properties": {
    "iso:country":"DE",
    "sg:address":"Otto-Fielitz-Str. 2",
    "sg:city":"Flensburg",
    "sg:postcode":"24939",
    "sg:province":"Schleswig-Holstein",
    "wof:name":"Scc Sindram Competence Center Ag",
    "wof:placetype":"venue"
},
  "geometry": {"coordinates":[9.410135,54.802399],"type":"Point"}
}