{
  "type": "Feature",
  "properties": {
    "iso:country":"DE",
    "sg:address":"Gr\u00e4felfinger Str. 100 A",
    "sg:city":"M\u00fcnchen",
    "sg:phone":"+49 89/6890640",
    "sg:postcode":"81375",
    "sg:province":"Bayern",
    "wof:name":"Buycentral Gmbh",
    "wof:placetype":"venue"
},
  "geometry": {"coordinates":[11.482004,48.116722],"type":"Point"}
}