{
  "type": "Feature",
  "properties": {
    "iso:country":"DE",
    "sg:address":"Lieserstr. 14",
    "sg:city":"Platten",
    "sg:phone":"+49 6535/275",
    "sg:postcode":"54518",
    "sg:province":"Rheinland-Pfalz",
    "wof:name":"Richard Mirbach",
    "wof:placetype":"venue"
},
  "geometry": {"coordinates":[6.954442,49.954296],"type":"Point"}
}