{
  "type": "Feature",
  "properties": {
    "iso:country":"DE",
    "sg:address":"Kuckucksberg 6",
    "sg:city":"L\u00fctjensee",
    "sg:phone":"+49 4154/7393",
    "sg:postcode":"22952",
    "sg:province":"Schleswig-Holstein",
    "wof:name":"Heim Und Bau Peter Weichert Gmbh",
    "wof:placetype":"venue"
},
  "geometry": {"coordinates":[10.364727,53.642368],"type":"Point"}
}