{
  "type": "Feature",
  "properties": {
    "iso:country":"DE",
    "sg:address":"Buschweg 18",
    "sg:city":"Hennef",
    "sg:phone":"+49 228/420701",
    "sg:postcode":"53773",
    "sg:province":"Nordrhein-Westfalen",
    "wof:name":"Mario K\u00f6hler",
    "wof:placetype":"venue"
},
  "geometry": {"coordinates":[7.3985538483,50.7246055603],"type":"Point"}
}