{
  "type": "Feature",
  "properties": {
    "iso:country":"DE",
    "sg:address":"Am Steingarten 11",
    "sg:city":"Erlenbach",
    "sg:phone":"+49 9372/944770",
    "sg:postcode":"63906",
    "sg:province":"Bayern",
    "wof:name":"Peter K\u00f6hlich",
    "wof:placetype":"venue"
},
  "geometry": {"coordinates":[9.2131433487,49.8106460571],"type":"Point"}
}