{
  "type": "Feature",
  "properties": {
    "iso:country":"DE",
    "sg:address":"Westerjork 31",
    "sg:city":"Jork",
    "sg:phone":"+49 4162/349",
    "sg:postcode":"21635",
    "sg:province":"Niedersachsen",
    "wof:name":"Gr\u00e4fen-apotheke",
    "wof:placetype":"venue"
},
  "geometry": {"coordinates":[9.679716,53.532997],"type":"Point"}
}