{
  "type": "Feature",
  "properties": {
    "iso:country":"DE",
    "sg:address":"Schneidm\u00fchlweg 16",
    "sg:city":"K\u00fclsheim",
    "sg:phone":"+49 9345/1465",
    "sg:postcode":"97900",
    "sg:province":"Baden-W\u00fcrttemberg",
    "wof:name":"Zum M\u00fchltal",
    "wof:placetype":"venue"
},
  "geometry": {"coordinates":[9.5171098709,49.6680488586],"type":"Point"}
}