{
  "type": "Feature",
  "properties": {
    "iso:country":"DE",
    "sg:address":"Goethering 5",
    "sg:city":"Stein",
    "sg:phone":"+49 911/681272",
    "sg:postcode":"90547",
    "sg:province":"Bayern",
    "wof:name":"Bsb Malerteam Gmbh",
    "wof:placetype":"venue"
},
  "geometry": {"coordinates":[11.015493,49.401253],"type":"Point"}
}