{
  "type": "Feature",
  "properties": {
    "iso:country":"DE",
    "sg:address":"Friedrich-Ebert-Str. 6",
    "sg:city":"Niederwerrn",
    "sg:phone":"+49 9721/40178",
    "sg:postcode":"97464",
    "sg:province":"Bayern",
    "wof:name":"Planungsb\u00fcro Konrad",
    "wof:placetype":"venue"
},
  "geometry": {"coordinates":[10.1867542267,50.0594024658],"type":"Point"}
}