{
  "type": "Feature",
  "properties": {
    "iso:country":"DE",
    "sg:address":"Steinbreede 18",
    "sg:city":"Mettingen",
    "sg:phone":"+49 5452/98289",
    "sg:postcode":"49497",
    "sg:province":"Nordrhein-Westfalen",
    "wof:name":"Kls Klima- Und L\u00fcftungsservice Gmbh",
    "wof:placetype":"venue"
},
  "geometry": {"coordinates":[7.7927880287,52.317527771],"type":"Point"}
}