{
  "type": "Feature",
  "properties": {
    "iso:country":"DE",
    "sg:address":"Ringstr. 11",
    "sg:city":"Beilngries",
    "sg:phone":"+49 8461/1206",
    "sg:postcode":"92339",
    "sg:province":"Bayern",
    "wof:name":"Buchdruckerei M. W. Bauer Vertretung F\u00fcr Das Amtliche",
    "wof:placetype":"venue"
},
  "geometry": {"coordinates":[11.4721603394,49.0333557129],"type":"Point"}
}