{
  "type": "Feature",
  "properties": {
    "iso:country":"DE",
    "sg:address":"Sagberg 2",
    "sg:city":"Frasdorf",
    "sg:phone":"+49 8052/620",
    "sg:postcode":"83112",
    "sg:province":"Bayern",
    "wof:name":"Sagberg",
    "wof:placetype":"venue"
},
  "geometry": {"coordinates":[12.2874593735,47.7886161804],"type":"Point"}
}