{
  "type": "Feature",
  "properties": {
    "iso:country":"DE",
    "sg:address":"Ringstr. 15",
    "sg:city":"Waldershof",
    "sg:phone":"+49 9231/7363",
    "sg:postcode":"95679",
    "sg:province":"Bayern",
    "wof:name":"Erwin Zimmerer",
    "wof:placetype":"venue"
},
  "geometry": {"coordinates":[12.059873,49.981297],"type":"Point"}
}