{
  "type": "Feature",
  "properties": {
    "iso:country":"DE",
    "sg:address":"Hebramsdorf 5",
    "sg:city":"Neufahrn",
    "sg:phone":"+49 8785/340",
    "sg:postcode":"84088",
    "sg:province":"Bayern",
    "wof:name":"Otto Berleb",
    "wof:placetype":"venue"
},
  "geometry": {"coordinates":[12.1265602112,48.7207260132],"type":"Point"}
}