{
  "type": "Feature",
  "properties": {
    "iso:country":"DE",
    "sg:address":"Isebekstr. 14 a",
    "sg:city":"Hamburg",
    "sg:phone":"+49 40/857241",
    "sg:postcode":"22769",
    "sg:province":"Hamburg",
    "wof:name":"Pelzschlo\u00df Dmoch",
    "wof:placetype":"venue"
},
  "geometry": {"coordinates":[9.9358911514,53.5680274963],"type":"Point"}
}