{
  "type": "Feature",
  "properties": {
    "iso:country":"DE",
    "sg:address":"Prefagstr. 4",
    "sg:city":"Walzbachtal",
    "sg:postcode":"75045",
    "sg:province":"Baden-W\u00fcrttemberg",
    "wof:name":"Schultz-beteiligungs Kg",
    "wof:placetype":"venue"
},
  "geometry": {"coordinates":[8.609467,49.007702],"type":"Point"}
}