{
  "type": "Feature",
  "properties": {
    "iso:country":"DE",
    "sg:address":"Marktplatz 5",
    "sg:city":"Eisfeld",
    "sg:postcode":"98673",
    "sg:province":"Th\u00fcringen",
    "wof:name":"300288 Und B\u00fcrobedarfszentrum Inh. Klemens Otto",
    "wof:placetype":"venue"
},
  "geometry": {"coordinates":[10.907959,50.427444],"type":"Point"}
}