{
  "type": "Feature",
  "properties": {
    "iso:country":"DE",
    "sg:address":"Gie\u00dfereistr. 43",
    "sg:city":"Rosenheim",
    "sg:phone":"+49 8031/80660",
    "sg:postcode":"83022",
    "sg:province":"Bayern",
    "wof:name":"Tele Dialog Ges. Mbh Zwgl. Rosenheim",
    "wof:placetype":"venue"
},
  "geometry": {"coordinates":[12.121852,47.8498],"type":"Point"}
}