{
  "type": "Feature",
  "properties": {
    "iso:country":"DE",
    "sg:address":"Ursulastr. 42",
    "sg:city":"Neustadt",
    "sg:phone":"+49 6321/30942",
    "sg:postcode":"67434",
    "sg:province":"Rheinland-Pfalz",
    "wof:name":"Rudi Gutting Weinanbau",
    "wof:placetype":"venue"
},
  "geometry": {"coordinates":[8.1412744522,49.3230514526],"type":"Point"}
}