{
  "type": "Feature",
  "properties": {
    "iso:country":"DE",
    "sg:address":"Zur Mergelkuhle 1",
    "sg:city":"Bergkamen",
    "sg:phone":"+49 2307/828208",
    "sg:postcode":"59192",
    "sg:province":"Nordrhein-Westfalen",
    "wof:name":"Frank Elsbeck",
    "wof:placetype":"venue"
},
  "geometry": {"coordinates":[7.6533727646,51.6261329651],"type":"Point"}
}