{
  "type": "Feature",
  "properties": {
    "iso:country":"DE",
    "sg:address":"Bichelweg 1",
    "sg:city":"Obermaiselstein",
    "sg:phone":"+49 8326/7472",
    "sg:postcode":"87538",
    "sg:province":"Bayern",
    "wof:name":"G\u00e4stehaus Helmut Eller",
    "wof:placetype":"venue"
},
  "geometry": {"coordinates":[10.2396478653,47.4473724365],"type":"Point"}
}