{
  "type": "Feature",
  "properties": {
    "iso:country":"DE",
    "sg:address":"Neuer Weg 12",
    "sg:city":"Bensheim",
    "sg:phone":"+49 6251/74759",
    "sg:postcode":"64625",
    "sg:province":"Hessen",
    "wof:name":"S. Arikan",
    "wof:placetype":"venue"
},
  "geometry": {"coordinates":[8.6213521957,49.7025794983],"type":"Point"}
}