{
  "type": "Feature",
  "properties": {
    "iso:country":"DE",
    "sg:address":"Sommerweg 17",
    "sg:city":"Ederm\u00fcnde",
    "sg:phone":"+49 5603/1675",
    "sg:postcode":"34295",
    "sg:province":"Hessen",
    "wof:name":"Rkt Regel Gmbh",
    "wof:placetype":"venue"
},
  "geometry": {"coordinates":[9.386797,51.227406],"type":"Point"}
}