{
  "type": "Feature",
  "properties": {
    "iso:country":"DE",
    "sg:address":"Postfach 1227",
    "sg:city":"Bergen / Chiemgau",
    "sg:phone":"+49 8662/48800",
    "sg:postcode":"83344",
    "wof:name":"Aag Sportversicherungen",
    "wof:placetype":"venue"
},
  "geometry": {"coordinates":[12.5938301086,47.8804206848],"type":"Point"}
}