{
  "type": "Feature",
  "properties": {
    "iso:country":"DE",
    "sg:address":"Gutenbergstr. 5",
    "sg:city":"Bingen",
    "sg:phone":"+49 6721/36598",
    "sg:postcode":"55411",
    "sg:province":"Rheinland-Pfalz",
    "wof:name":"Kath. Vereinshaus",
    "wof:placetype":"venue"
},
  "geometry": {"coordinates":[7.8868818283,49.9650840759],"type":"Point"}
}