{
  "type": "Feature",
  "properties": {
    "iso:country":"DE",
    "sg:address":"Gutsstr. 2",
    "sg:city":"Nentershausen",
    "sg:phone":"+49 6627/225",
    "sg:postcode":"36214",
    "sg:province":"Hessen",
    "wof:name":"Markt-apotheke Rainer Kr\u00fcger E. K.",
    "wof:placetype":"venue"
},
  "geometry": {"coordinates":[9.934411,51.013657],"type":"Point"}
}