{
  "type": "Feature",
  "properties": {
    "iso:country":"DE",
    "sg:address":"Julius-Mosen-Platz 4",
    "sg:city":"Oldenburg",
    "sg:phone":"+49 441/7780166",
    "sg:postcode":"26122",
    "sg:province":"Niedersachsen",
    "wof:name":"Love.de Gbr",
    "wof:placetype":"venue"
},
  "geometry": {"coordinates":[8.2093219757,53.1409873962],"type":"Point"}
}