{
  "type": "Feature",
  "properties": {
    "iso:country":"DE",
    "sg:address":"Bauer Landstr 27",
    "sg:city":"Flensburg",
    "sg:phone":"+49 461/42221",
    "sg:postcode":"24939",
    "sg:province":"Schleswig-Holstein",
    "wof:name":"Dan Dryer N. Saaby J\u00f6rgensen Gmbh",
    "wof:placetype":"venue"
},
  "geometry": {"coordinates":[9.421343,54.801754],"type":"Point"}
}