{
  "type": "Feature",
  "properties": {
    "iso:country":"DE",
    "sg:address":"Hindenburgstr. 50",
    "sg:city":"Diepholz",
    "sg:phone":"+49 4954/419970",
    "sg:postcode":"49356",
    "sg:province":"Niedersachsen",
    "wof:name":"Sch\u00d6ma Christoph Sch\u00d6ttler Maschinenfabrik Gmbh",
    "wof:placetype":"venue"
},
  "geometry": {"coordinates":[8.3796482086,52.6100387573],"type":"Point"}
}