{
  "type": "Feature",
  "properties": {
    "iso:country":"DE",
    "sg:address":"Vogelsanger Str. 427",
    "sg:city":"K\u00f6ln",
    "sg:phone":"+49 221/585440",
    "sg:postcode":"50829",
    "sg:province":"Nordrhein-Westfalen",
    "wof:name":"Pizzeria La Laterna",
    "wof:placetype":"venue"
},
  "geometry": {"coordinates":[6.8856768608,50.9553985596],"type":"Point"}
}