{
  "type": "Feature",
  "properties": {
    "iso:country":"DE",
    "sg:address":"Vogelsang 8",
    "sg:city":"Braunschweig",
    "sg:phone":"+49 531/52671",
    "sg:postcode":"38118",
    "sg:province":"Niedersachsen",
    "wof:name":"Arno Busse",
    "wof:placetype":"venue"
},
  "geometry": {"coordinates":[10.490527,52.267185],"type":"Point"}
}