{
  "type": "Feature",
  "properties": {
    "iso:country":"DE",
    "sg:address":"Dickerstr. 149",
    "sg:city":"Dinslaken",
    "sg:phone":"+49 2064/93951",
    "sg:postcode":"46539",
    "sg:province":"Nordrhein-Westfalen",
    "wof:name":"Peter Schumann",
    "wof:placetype":"venue"
},
  "geometry": {"coordinates":[6.7821230888,51.5778083801],"type":"Point"}
}