{
  "type": "Feature",
  "properties": {
    "iso:country":"DE",
    "sg:address":"Maximilianstr. 16",
    "sg:city":"Regensburg",
    "sg:phone":"+49 941/51636",
    "sg:postcode":"93047",
    "sg:province":"Bayern",
    "wof:name":"Werner K\u00f6hler Immobilienmakler",
    "wof:placetype":"venue"
},
  "geometry": {"coordinates":[12.1001720428,49.016330719],"type":"Point"}
}