{
  "type": "Feature",
  "properties": {
    "iso:country":"DE",
    "sg:address":"Wasserkr\u00fcger Weg 33",
    "sg:city":"M\u00f6lln",
    "sg:phone":"+49 4542/88941",
    "sg:postcode":"23879",
    "sg:province":"Schleswig-Holstein",
    "wof:name":"Christa Paulsen Altenheim",
    "wof:placetype":"venue"
},
  "geometry": {"coordinates":[10.686486,53.624626],"type":"Point"}
}