{
  "type": "Feature",
  "properties": {
    "iso:country":"DE",
    "sg:address":"Zelterstr. 5",
    "sg:city":"Grevenbroich",
    "sg:phone":"+49 2182/3598",
    "sg:postcode":"41516",
    "sg:province":"Nordrhein-Westfalen",
    "wof:name":"Bernhard Elbe",
    "wof:placetype":"venue"
},
  "geometry": {"coordinates":[6.5923857689,51.1281776428],"type":"Point"}
}