{
  "type": "Feature",
  "properties": {
    "iso:country":"DE",
    "sg:address":"Piesberger Str. 10",
    "sg:city":"Osnabr\u00fcck",
    "sg:phone":"+49 541/131195",
    "sg:postcode":"49090",
    "sg:province":"Niedersachsen",
    "wof:name":"Marikas Kosmetikstudio",
    "wof:placetype":"venue"
},
  "geometry": {"coordinates":[8.013962,52.295254],"type":"Point"}
}