{
  "type": "Feature",
  "properties": {
    "iso:country":"DE",
    "sg:address":"Doberaner Str. 40-47",
    "sg:city":"Rostock",
    "sg:phone":"+49 381/208720",
    "sg:postcode":"18057",
    "sg:province":"Mecklenburg-Vorpommern",
    "wof:name":"Gfg Gesellschaft F\u00fcr Gesundheitsfachberufe Ggmbh",
    "wof:placetype":"venue"
},
  "geometry": {"coordinates":[12.1160802841,54.090637207],"type":"Point"}
}