{
  "type": "Feature",
  "properties": {
    "iso:country":"DE",
    "sg:address":"Im Schwarzw\u00e4ldele 15",
    "sg:city":"Offenburg",
    "sg:phone":"+49 781/36605",
    "sg:postcode":"77654",
    "sg:province":"Baden-W\u00fcrttemberg",
    "wof:name":"Horst Becker Architekt",
    "wof:placetype":"venue"
},
  "geometry": {"coordinates":[7.975484,48.467533],"type":"Point"}
}