{
  "type": "Feature",
  "properties": {
    "iso:country":"DE",
    "sg:address":"Magdeburger Str. 23 c",
    "sg:city":"Schneidlingen",
    "sg:phone":"+49 39267/81907",
    "sg:postcode":"39435",
    "sg:province":"Sachsen-Anhalt",
    "wof:name":"Restaurant Zum Nebelhorn",
    "wof:placetype":"venue"
},
  "geometry": {"coordinates":[11.4456605911,51.8888092041],"type":"Point"}
}