{
  "type": "Feature",
  "properties": {
    "iso:country":"DE",
    "sg:address":"Dresdner Str. 3",
    "sg:city":"Zittau",
    "sg:phone":"+49 3583/705928",
    "sg:postcode":"02763",
    "sg:province":"Sachsen",
    "wof:name":"M. Eichenberg Anlageberater",
    "wof:placetype":"venue"
},
  "geometry": {"coordinates":[14.7999668121,50.8988800049],"type":"Point"}
}