{
  "type": "Feature",
  "properties": {
    "iso:country":"DE",
    "sg:address":"Buttermarkt 4",
    "sg:city":"Kempen",
    "sg:phone":"+49 2152/13273",
    "sg:postcode":"47906",
    "sg:province":"Nordrhein-Westfalen",
    "wof:name":"Stadtb\u00fccherei",
    "wof:placetype":"venue"
},
  "geometry": {"coordinates":[6.418667,51.364315],"type":"Point"}
}