{
  "type": "Feature",
  "properties": {
    "iso:country":"DE",
    "sg:address":"Albert-Einstein-Str. 129",
    "sg:city":"Aachen",
    "sg:phone":"+49 2408/7503",
    "sg:postcode":"52076",
    "sg:province":"Nordrhein-Westfalen",
    "wof:name":"Joh. Und Ingo Grabdenkm\u00e4ler",
    "wof:placetype":"venue"
},
  "geometry": {"coordinates":[6.1835417747,50.7128105164],"type":"Point"}
}