{
  "type": "Feature",
  "properties": {
    "iso:country":"DE",
    "sg:address":"Lippst\u00e4dter Str. 1",
    "sg:city":"Langenberg",
    "sg:phone":"+49 5248/7092",
    "sg:postcode":"33449",
    "sg:province":"Nordrhein-Westfalen",
    "wof:name":"Heinrich Baumhus",
    "wof:placetype":"venue"
},
  "geometry": {"coordinates":[8.323182106,51.7757377625],"type":"Point"}
}