{
  "type": "Feature",
  "properties": {
    "iso:country":"DE",
    "sg:address":"Selstener Str. 76",
    "sg:city":"Waldfeucht",
    "sg:phone":"+49 2452/5590",
    "sg:postcode":"52525",
    "sg:province":"Nordrhein-Westfalen",
    "wof:name":"Franz W. Nolten",
    "wof:placetype":"venue"
},
  "geometry": {"coordinates":[6.038632,51.043861],"type":"Point"}
}