{
  "type": "Feature",
  "properties": {
    "iso:country":"DE",
    "sg:address":"Spielmannstr. 26",
    "sg:city":"Frankfurt",
    "sg:phone":"+49 69/39047500",
    "sg:postcode":"65934",
    "sg:province":"Hessen",
    "wof:name":"Restaurant Holzkopp",
    "wof:placetype":"venue"
},
  "geometry": {"coordinates":[8.5682754517,50.09998703],"type":"Point"}
}