{
  "type": "Feature",
  "properties": {
    "iso:country":"DE",
    "sg:address":"Lange Str. 43",
    "sg:city":"Pl\u00f6n",
    "sg:phone":"+49 4522/2706",
    "sg:postcode":"24306",
    "sg:province":"Schleswig-Holstein",
    "wof:name":"Thomsen",
    "wof:placetype":"venue"
},
  "geometry": {"coordinates":[10.4149122238,54.15782547],"type":"Point"}
}