{
  "type": "Feature",
  "properties": {
    "iso:country":"DE",
    "sg:address":"Wentorfer Str. 14",
    "sg:city":"Hamburg",
    "sg:phone":"+49 40/7212053",
    "sg:postcode":"21029",
    "sg:province":"Hamburg",
    "wof:name":"Hahn & Laue Ges. F\u00fcr Bau- Planung Und Baustatistik Mbh",
    "wof:placetype":"venue"
},
  "geometry": {"coordinates":[10.217874,53.486885],"type":"Point"}
}