{
  "type": "Feature",
  "properties": {
    "iso:country":"DE",
    "sg:address":"Bangertstr. 7",
    "sg:city":"Hanau",
    "sg:phone":"+49 6181/24231",
    "sg:postcode":"63450",
    "sg:province":"Hessen",
    "wof:name":"Murad Karakas",
    "wof:placetype":"venue"
},
  "geometry": {"coordinates":[8.9161481857,50.1357688904],"type":"Point"}
}