{
  "type": "Feature",
  "properties": {
    "iso:country":"DE",
    "sg:address":"Isnyer Str. 5",
    "sg:city":"Ulm",
    "sg:phone":"+49 731/41923",
    "sg:postcode":"89079",
    "sg:province":"Baden-W\u00fcrttemberg",
    "wof:name":"Siegfried Wiesner Innenarchitekt",
    "wof:placetype":"venue"
},
  "geometry": {"coordinates":[9.970257,48.347237],"type":"Point"}
}