{
  "type": "Feature",
  "properties": {
    "iso:country":"DE",
    "sg:address":"Wiffertshauser Str. 35",
    "sg:city":"Friedberg",
    "sg:phone":"+49 821/268920",
    "sg:postcode":"86316",
    "sg:province":"Bayern",
    "wof:name":"Ist Informations- Und Systemtechnik C. H\u00f6lzl Gmbh",
    "wof:placetype":"venue"
},
  "geometry": {"coordinates":[10.988724,48.355717],"type":"Point"}
}