{
  "type": "Feature",
  "properties": {
    "iso:country":"DE",
    "sg:address":"Breslauer Str. 1",
    "sg:city":"Allendorf",
    "sg:phone":"+49 6452/1489",
    "sg:postcode":"35108",
    "sg:province":"Hessen",
    "wof:name":"Karl-heinz Monzner",
    "wof:placetype":"venue"
},
  "geometry": {"coordinates":[8.6922178268,51.0235061646],"type":"Point"}
}