{
  "type": "Feature",
  "properties": {
    "iso:country":"DE",
    "sg:address":"Zur Reith 15",
    "sg:city":"Visselh\u00f6vede",
    "sg:phone":"+49 4262/2217",
    "sg:postcode":"27374",
    "sg:province":"Niedersachsen",
    "wof:name":"St\u00f6ckmann",
    "wof:placetype":"venue"
},
  "geometry": {"coordinates":[9.548696,52.977757],"type":"Point"}
}