{
  "type": "Feature",
  "properties": {
    "iso:country":"DE",
    "sg:address":"Uhlandstr. 8",
    "sg:city":"Grenzach-Wyhlen",
    "sg:phone":"+49 7624/6747",
    "sg:postcode":"79639",
    "sg:province":"Baden-W\u00fcrttemberg",
    "wof:name":"Ig Nergerd\u00f6rfle E. V. Wyhlen",
    "wof:placetype":"venue"
},
  "geometry": {"coordinates":[7.6641101837,47.5511283875],"type":"Point"}
}