{
  "type": "Feature",
  "properties": {
    "iso:country":"DE",
    "sg:address":"Beethovenstr. 48",
    "sg:city":"Crailsheim",
    "sg:postcode":"74564",
    "sg:province":"Baden-W\u00fcrttemberg",
    "wof:name":"H & B Engineering Gmbh",
    "wof:placetype":"venue"
},
  "geometry": {"coordinates":[10.0447978973,49.1429481506],"type":"Point"}
}