{
  "type": "Feature",
  "properties": {
    "iso:country":"DE",
    "sg:address":"Zur Glockenkuhle 3",
    "sg:city":"Bippen",
    "sg:phone":"+49 5435/844",
    "sg:postcode":"49626",
    "sg:province":"Niedersachsen",
    "wof:name":"Ella Uphaus Hebamme",
    "wof:placetype":"venue"
},
  "geometry": {"coordinates":[7.736817,52.579369],"type":"Point"}
}