{
  "type": "Feature",
  "properties": {
    "iso:country":"DE",
    "sg:address":"Weserstr. 20",
    "sg:city":"Emmerthal",
    "sg:phone":"+49 5155/97060",
    "sg:postcode":"31860",
    "sg:province":"Niedersachsen",
    "wof:name":"Hans-ulrich Uibeleisen",
    "wof:placetype":"venue"
},
  "geometry": {"coordinates":[9.422758,52.018776],"type":"Point"}
}