{
  "type": "Feature",
  "properties": {
    "iso:country":"DE",
    "sg:address":"Dieselstr. 27",
    "sg:city":"Leingarten",
    "sg:phone":"+49 7131/40630",
    "sg:postcode":"74211",
    "sg:province":"Baden-W\u00fcrttemberg",
    "wof:name":"Thomas Gessmann Gmbh & Co.",
    "wof:placetype":"venue"
},
  "geometry": {"coordinates":[9.123585,49.147064],"type":"Point"}
}