{
  "type": "Feature",
  "properties": {
    "iso:country":"DE",
    "sg:address":"Burgh\u00e4ldeweg 1",
    "sg:city":"Sinsheim",
    "sg:phone":"+49 7261/13085",
    "sg:postcode":"74889",
    "sg:province":"Baden-W\u00fcrttemberg",
    "wof:name":"Martin Kuhmann",
    "wof:placetype":"venue"
},
  "geometry": {"coordinates":[8.8715543747,49.2505645752],"type":"Point"}
}