{
  "type": "Feature",
  "properties": {
    "iso:country":"DE",
    "sg:address":"Gerhardstr. 4c",
    "sg:city":"Saarbr\u00fccken",
    "sg:phone":"+49 6898/81831",
    "sg:postcode":"66126",
    "sg:province":"Saarland",
    "wof:name":"Rudolf Bettinger Gmbh",
    "wof:placetype":"venue"
},
  "geometry": {"coordinates":[6.916644,49.262062],"type":"Point"}
}