{
  "type": "Feature",
  "properties": {
    "iso:country":"DE",
    "sg:address":"Industriestr. 4-8",
    "sg:city":"Emsb\u00fcren",
    "sg:postcode":"48488",
    "sg:province":"Niedersachsen",
    "wof:name":"Mitrah Middendorp- Transport Und Handelsges. Mbh",
    "wof:placetype":"venue"
},
  "geometry": {"coordinates":[7.311332,52.379101],"type":"Point"}
}