{
  "type": "Feature",
  "properties": {
    "iso:country":"DE",
    "sg:address":"Daniel-Weil-Str. 4",
    "sg:city":"Blaubeuren",
    "sg:phone":"+49 7344/6009",
    "sg:postcode":"89143",
    "sg:province":"Baden-W\u00fcrttemberg",
    "wof:name":"Karl Burger Maschinenbau Gmbh & Co.",
    "wof:placetype":"venue"
},
  "geometry": {"coordinates":[9.7794780731,48.4019393921],"type":"Point"}
}