{
  "type": "Feature",
  "properties": {
    "iso:country":"DE",
    "sg:address":"Aubachstr. 2",
    "sg:city":"Kirchseeon",
    "sg:phone":"+49 8091/2078",
    "sg:postcode":"85614",
    "sg:province":"Bayern",
    "wof:name":"Theodor Drax",
    "wof:placetype":"venue"
},
  "geometry": {"coordinates":[11.910686,48.071423],"type":"Point"}
}