{
  "type": "Feature",
  "properties": {
    "iso:country":"DE",
    "sg:address":"Am Steinigt 19",
    "sg:city":"Dresden",
    "sg:phone":"+49 351/4273027",
    "sg:postcode":"01157",
    "sg:province":"Sachsen",
    "wof:name":"Martin K\u00fchne",
    "wof:placetype":"venue"
},
  "geometry": {"coordinates":[13.648212,51.058666],"type":"Point"}
}