{
  "type": "Feature",
  "properties": {
    "iso:country":"DE",
    "sg:address":"Orbinstr. 22",
    "sg:city":"Bruchsal",
    "sg:phone":"+49 7251/303831",
    "sg:postcode":"76646",
    "sg:province":"Baden-W\u00fcrttemberg",
    "wof:name":"Schilder-jahn Gmbh",
    "wof:placetype":"venue"
},
  "geometry": {"coordinates":[8.59274,49.123325],"type":"Point"}
}