{
  "type": "Feature",
  "properties": {
    "iso:country":"DE",
    "sg:address":"Sprendlinger Landstr. 109",
    "sg:city":"Offenbach",
    "sg:phone":"+49 69/846492",
    "sg:postcode":"63069",
    "sg:province":"Hessen",
    "wof:name":"T. Barnicke Makler",
    "wof:placetype":"venue"
},
  "geometry": {"coordinates":[8.7498950958,50.0904273987],"type":"Point"}
}