{
  "type": "Feature",
  "properties": {
    "iso:country":"DE",
    "sg:address":"Heidehofweg 60",
    "sg:city":"Tangstedt",
    "sg:phone":"+49 4101/207605",
    "sg:postcode":"25499",
    "sg:province":"Schleswig-Holstein",
    "wof:name":"J\u00f6rg U. Christian Kemmer",
    "wof:placetype":"venue"
},
  "geometry": {"coordinates":[9.849137,53.667347],"type":"Point"}
}