{
  "type": "Feature",
  "properties": {
    "iso:country":"DE",
    "sg:address":"Marktplatz 17",
    "sg:city":"Waldm\u00fcnchen",
    "sg:phone":"+49 9972/206",
    "sg:postcode":"93449",
    "sg:province":"Bayern",
    "wof:name":"Schmidt Bank",
    "wof:placetype":"venue"
},
  "geometry": {"coordinates":[12.706698,49.377907],"type":"Point"}
}