{
  "type": "Feature",
  "properties": {
    "iso:country":"DE",
    "sg:address":"Frauenstr. 22",
    "sg:city":"Ahaus",
    "sg:phone":"+49 2561/3473",
    "sg:postcode":"48683",
    "sg:province":"Nordrhein-Westfalen",
    "wof:name":"Reinhold Woltering",
    "wof:placetype":"venue"
},
  "geometry": {"coordinates":[7.003704071,52.074420929],"type":"Point"}
}