{
  "type": "Feature",
  "properties": {
    "iso:country":"DE",
    "sg:address":"R\u00fcttenscheider Str. 194-196",
    "sg:city":"Essen",
    "sg:phone":"+49 201/8419400",
    "sg:postcode":"45131",
    "sg:province":"Nordrhein-Westfalen",
    "wof:name":"Haverkohn Verkaufsf\u00d6rderung Gmbh",
    "wof:placetype":"venue"
},
  "geometry": {"coordinates":[7.00262,51.427372],"type":"Point"}
}