{
  "type": "Feature",
  "properties": {
    "iso:country":"DE",
    "sg:address":"Hauptstr. 27",
    "sg:city":"Hambuch",
    "sg:phone":"+49 2653/7367",
    "sg:postcode":"56761",
    "sg:province":"Rheinland-Pfalz",
    "wof:name":"Renate Simonis",
    "wof:placetype":"venue"
},
  "geometry": {"coordinates":[7.1826047897,50.2258872986],"type":"Point"}
}