{
  "type": "Feature",
  "properties": {
    "iso:country":"DE",
    "sg:address":"Kirchplatz 1",
    "sg:city":"Kaufungen",
    "sg:phone":"+49 5605/2709",
    "sg:postcode":"34260",
    "sg:province":"Hessen",
    "wof:name":"Sigrid Braut- Und Abendmoden",
    "wof:placetype":"venue"
},
  "geometry": {"coordinates":[9.602016,51.2855],"type":"Point"}
}