{
  "type": "Feature",
  "properties": {
    "iso:country":"DE",
    "sg:address":"Tunnelstr. 44",
    "sg:city":"Augsburg",
    "sg:phone":"+49 821/406443",
    "sg:postcode":"86156",
    "sg:province":"Bayern",
    "wof:name":"Bauderer Musikhaus",
    "wof:placetype":"venue"
},
  "geometry": {"coordinates":[10.8649511337,48.3815994263],"type":"Point"}
}