{
  "type": "Feature",
  "properties": {
    "iso:country":"DE",
    "sg:address":"Br\u00fcckenstr. 17-19",
    "sg:city":"Erbach",
    "sg:phone":"+49 6062/2066",
    "sg:postcode":"64711",
    "sg:province":"Hessen",
    "wof:name":"Heinrich Brand Kg",
    "wof:placetype":"venue"
},
  "geometry": {"coordinates":[8.9914865494,49.6582679749],"type":"Point"}
}