{
  "type": "Feature",
  "properties": {
    "iso:country":"DE",
    "sg:address":"Bruchtannenstr. 15",
    "sg:city":"Kleinostheim",
    "sg:phone":"+49 6027/4799120",
    "sg:postcode":"63801",
    "sg:province":"Bayern",
    "wof:name":"Fitness Park Kahl Gmbh",
    "wof:placetype":"venue"
},
  "geometry": {"coordinates":[9.0604896545,50.0135421753],"type":"Point"}
}