{
  "type": "Feature",
  "properties": {
    "iso:country":"DE",
    "sg:address":"Eichhalde 44",
    "sg:city":"Freiburg",
    "sg:phone":"+49 761/551187",
    "sg:postcode":"79104",
    "sg:province":"Baden-W\u00fcrttemberg",
    "wof:name":"Dr. Paul Zimmermann Rechtsanwalt",
    "wof:placetype":"venue"
},
  "geometry": {"coordinates":[7.8700118065,48.0117721558],"type":"Point"}
}