{
  "type": "Feature",
  "properties": {
    "iso:country":"DE",
    "sg:address":"Am See",
    "sg:city":"Altenhof",
    "sg:postcode":"16244",
    "sg:province":"Brandenburg",
    "wof:name":"Binnenfischerei",
    "wof:placetype":"venue"
},
  "geometry": {"coordinates":[13.7076597214,52.9130096436],"type":"Point"}
}