{
  "type": "Feature",
  "properties": {
    "iso:country":"DE",
    "sg:address":"Senkingstr. 5",
    "sg:city":"Hildesheim",
    "sg:phone":"+49 5121/52308",
    "sg:postcode":"31137",
    "sg:province":"Niedersachsen",
    "wof:name":"Richard Fischer & Co.",
    "wof:placetype":"venue"
},
  "geometry": {"coordinates":[9.9435710907,52.1593093872],"type":"Point"}
}