{
  "type": "Feature",
  "properties": {
    "iso:country":"DE",
    "sg:address":"Deltastr. 8",
    "sg:city":"Ritterhude",
    "sg:phone":"+49 4292/3807",
    "sg:postcode":"27721",
    "sg:province":"Niedersachsen",
    "wof:name":"Diem & Neumann",
    "wof:placetype":"venue"
},
  "geometry": {"coordinates":[8.757875,53.189487],"type":"Point"}
}