{
  "type": "Feature",
  "properties": {
    "iso:country":"DE",
    "sg:address":"Robert-Bosch-Str. 10",
    "sg:city":"Bietigheim-Bissingen",
    "sg:phone":"+49 4971/425000",
    "sg:postcode":"74321",
    "sg:province":"Baden-W\u00fcrttemberg",
    "wof:name":"Karl Berrang Gmbh",
    "wof:placetype":"venue"
},
  "geometry": {"coordinates":[9.133914,48.940186],"type":"Point"}
}