{
  "type": "Feature",
  "properties": {
    "iso:country":"DE",
    "sg:address":"Wildenburger Str. 18",
    "sg:city":"Wenden",
    "sg:phone":"+49 2762/7245",
    "sg:postcode":"57482",
    "sg:province":"Nordrhein-Westfalen",
    "wof:name":"Johann Buchen",
    "wof:placetype":"venue"
},
  "geometry": {"coordinates":[7.815173,50.95055],"type":"Point"}
}