{
  "type": "Feature",
  "properties": {
    "iso:country":"DE",
    "sg:address":"Kampweg 15",
    "sg:city":"J\u00f6rl",
    "sg:phone":"+49 4607/93030",
    "sg:postcode":"24992",
    "sg:province":"Schleswig-Holstein",
    "wof:name":"Erwin Jessen Gmbh",
    "wof:placetype":"venue"
},
  "geometry": {"coordinates":[9.315546,54.602345],"type":"Point"}
}