{
  "type": "Feature",
  "properties": {
    "iso:country":"DE",
    "sg:address":"Bieseler Feld 68",
    "sg:city":"M\u00f6nchengladbach",
    "sg:phone":"+49 2166/89201",
    "sg:postcode":"41238",
    "sg:province":"Nordrhein-Westfalen",
    "wof:name":"Restaurant Giesenkirchener Hof",
    "wof:placetype":"venue"
},
  "geometry": {"coordinates":[6.4809150696,51.1641464233],"type":"Point"}
}