{
  "type": "Feature",
  "properties": {
    "iso:country":"DE",
    "sg:address":"Kirchgasse 33",
    "sg:city":"Mainz",
    "sg:phone":"+49 6131/40261",
    "sg:postcode":"55126",
    "sg:province":"Rheinland-Pfalz",
    "wof:name":"Friedel Pfannebecker",
    "wof:placetype":"venue"
},
  "geometry": {"coordinates":[8.1728410721,49.9861717224],"type":"Point"}
}