{
  "type": "Feature",
  "properties": {
    "iso:country":"DE",
    "sg:address":"Sandwall 8",
    "sg:city":"Wyk",
    "sg:phone":"+49 4681/3295",
    "sg:postcode":"25938",
    "sg:province":"Schleswig-Holstein",
    "wof:name":"Modenhaus Ehlers Inh. Ursula Weber",
    "wof:placetype":"venue"
},
  "geometry": {"coordinates":[8.567777,54.691833],"type":"Point"}
}