{
  "type": "Feature",
  "properties": {
    "iso:country":"DE",
    "sg:address":"Ernst-Mey-Str. 8",
    "sg:city":"Leinfelden-Echterdingen",
    "sg:phone":"+49 711/75940",
    "sg:postcode":"70771",
    "sg:province":"Baden-W\u00fcrttemberg",
    "wof:name":"Redaktion Der Augenoptiker Willy Schrickel",
    "wof:placetype":"venue"
},
  "geometry": {"coordinates":[9.1460447311,48.696395874],"type":"Point"}
}