{
  "type": "Feature",
  "properties": {
    "iso:country":"DE",
    "sg:address":"Adlerplatz 3",
    "sg:city":"Hinterzarten",
    "sg:phone":"+49 7652/5550",
    "sg:postcode":"79856",
    "sg:province":"Baden-W\u00fcrttemberg",
    "wof:name":"Evelyn Schuster",
    "wof:placetype":"venue"
},
  "geometry": {"coordinates":[8.1070566177,47.9027175903],"type":"Point"}
}