{
  "type": "Feature",
  "properties": {
    "iso:country":"DE",
    "sg:address":"Zum Schreiberthal 1",
    "sg:city":"Kallm\u00fcnz",
    "sg:phone":"+49 9473/402",
    "sg:postcode":"93183",
    "sg:province":"Bayern",
    "wof:name":"Braun Gmbh",
    "wof:placetype":"venue"
},
  "geometry": {"coordinates":[11.9330053329,49.1831092834],"type":"Point"}
}