{
  "type": "Feature",
  "properties": {
    "iso:country":"DE",
    "sg:address":"Hauptstr. 9",
    "sg:city":"Engelthal",
    "sg:phone":"+49 9158/262",
    "sg:postcode":"91238",
    "sg:province":"Bayern",
    "wof:name":"Restaurant Gr\u00fcner Baum",
    "wof:placetype":"venue"
},
  "geometry": {"coordinates":[11.3959627151,49.4719734192],"type":"Point"}
}