{
  "type": "Feature",
  "properties": {
    "iso:country":"DE",
    "sg:address":"Marktstr. 46",
    "sg:city":"Burgdorf",
    "sg:phone":"+49 5136/85005",
    "sg:postcode":"31303",
    "sg:province":"Niedersachsen",
    "wof:name":"Trend Optik Gmbh",
    "wof:placetype":"venue"
},
  "geometry": {"coordinates":[10.008873,52.446907],"type":"Point"}
}