{
  "type": "Feature",
  "properties": {
    "iso:country":"DE",
    "sg:address":"Schiltachstr. 42",
    "sg:city":"Schramberg",
    "sg:phone":"+49 7422/23280",
    "sg:postcode":"78713",
    "sg:province":"Baden-W\u00fcrttemberg",
    "wof:name":"Marc Bornschein",
    "wof:placetype":"venue"
},
  "geometry": {"coordinates":[8.38222,48.230587],"type":"Point"}
}