{
  "type": "Feature",
  "properties": {
    "iso:country":"DE",
    "sg:address":"Heimgartenstr. 7",
    "sg:city":"Olching",
    "sg:phone":"+49 8142/16935",
    "sg:postcode":"82140",
    "sg:province":"Bayern",
    "wof:name":"Ulrich Hoffmann",
    "wof:placetype":"venue"
},
  "geometry": {"coordinates":[11.323982,48.196358],"type":"Point"}
}