{
  "type": "Feature",
  "properties": {
    "iso:country":"DE",
    "sg:address":"Hochstr 11",
    "sg:city":"Taufkirchen",
    "sg:phone":"+49 89/6127600",
    "sg:postcode":"82024",
    "sg:province":"Bayern",
    "wof:name":"Reiser",
    "wof:placetype":"venue"
},
  "geometry": {"coordinates":[11.620315,48.039463],"type":"Point"}
}