{
  "type": "Feature",
  "properties": {
    "iso:country":"DE",
    "sg:address":"Myslowitzer Str. 27-29",
    "sg:city":"Berlin",
    "sg:postcode":"12621",
    "sg:province":"Berlin",
    "wof:name":"Guenter Kreisel",
    "wof:placetype":"venue"
},
  "geometry": {"coordinates":[13.5931196213,52.5089187622],"type":"Point"}
}