{
  "type": "Feature",
  "properties": {
    "iso:country":"DE",
    "sg:address":"An der Uentroper Kirche 6",
    "sg:city":"Hamm",
    "sg:phone":"+49 2388/2354",
    "sg:postcode":"59071",
    "sg:province":"Nordrhein-Westfalen",
    "wof:name":"Ev. Pfarramt Uentrop",
    "wof:placetype":"venue"
},
  "geometry": {"coordinates":[7.9479470253,51.6933364868],"type":"Point"}
}