{
  "type": "Feature",
  "properties": {
    "iso:country":"DE",
    "sg:address":"Innerer Markt 15",
    "sg:city":"Leuchtenberg",
    "sg:phone":"+49 9659/92182",
    "sg:postcode":"92705",
    "sg:province":"Bayern",
    "wof:name":"Otto Pr\u00f6ls",
    "wof:placetype":"venue"
},
  "geometry": {"coordinates":[12.25612,49.597134],"type":"Point"}
}