{
  "type": "Feature",
  "properties": {
    "iso:country":"DE",
    "sg:address":"B\u00fclowstr. 11",
    "sg:city":"Wilhelmshaven",
    "sg:phone":"+49 4421/31077",
    "sg:postcode":"26384",
    "sg:province":"Niedersachsen",
    "wof:name":"Norbert Fundis Baustoffe Gmbh",
    "wof:placetype":"venue"
},
  "geometry": {"coordinates":[8.11957,53.528343],"type":"Point"}
}