{
  "type": "Feature",
  "properties": {
    "iso:country":"DE",
    "sg:address":"Lateingasse 3",
    "sg:city":"Illingen",
    "sg:phone":"+49 6825/42538",
    "sg:postcode":"66557",
    "sg:province":"Saarland",
    "wof:name":"Irene Cerwinski",
    "wof:placetype":"venue"
},
  "geometry": {"coordinates":[7.04997015,49.3775367737],"type":"Point"}
}