{
  "type": "Feature",
  "properties": {
    "iso:country":"DE",
    "sg:address":"F\u00fcrstenbergstr. 14",
    "sg:city":"M\u00fcnchen",
    "sg:phone":"+49 89/35654087",
    "sg:postcode":"80809",
    "sg:province":"Bayern",
    "wof:name":"Heinrich Grubmiller Gmbh",
    "wof:placetype":"venue"
},
  "geometry": {"coordinates":[11.562889,48.173386],"type":"Point"}
}