{
  "type": "Feature",
  "properties": {
    "iso:country":"DE",
    "sg:address":"Walkenrieder Str. 8",
    "sg:city":"Ellrich",
    "sg:postcode":"99755",
    "sg:province":"Th\u00fcringen",
    "wof:name":"Penny-markt",
    "wof:placetype":"venue"
},
  "geometry": {"coordinates":[10.6571998596,51.5867881775],"type":"Point"}
}