{
  "type": "Feature",
  "properties": {
    "iso:country":"DE",
    "sg:address":"Alemannenstr. 11",
    "sg:city":"Neuss",
    "sg:phone":"+49 2131/568320",
    "sg:postcode":"41462",
    "sg:province":"Nordrhein-Westfalen",
    "wof:name":"Walfried B\u00e4hr Ohg",
    "wof:placetype":"venue"
},
  "geometry": {"coordinates":[6.6761097908,51.2066459656],"type":"Point"}
}