{
  "type": "Feature",
  "properties": {
    "iso:country":"DE",
    "sg:address":"Industriestr 1",
    "sg:city":"Ehingen",
    "sg:phone":"+49 9835/97110",
    "sg:postcode":"91725",
    "sg:province":"Bayern",
    "wof:name":"Rehart Gmbh",
    "wof:placetype":"venue"
},
  "geometry": {"coordinates":[10.548055,49.085339],"type":"Point"}
}