{
  "type": "Feature",
  "properties": {
    "iso:country":"DE",
    "sg:address":"Wiemelhauser Str. 187",
    "sg:city":"Bochum",
    "sg:phone":"+49 234/313462",
    "sg:postcode":"44799",
    "sg:province":"Nordrhein-Westfalen",
    "wof:name":"R. Wicherek",
    "wof:placetype":"venue"
},
  "geometry": {"coordinates":[7.2279071808,51.4647712708],"type":"Point"}
}