{
  "type": "Feature",
  "properties": {
    "iso:country":"DE",
    "sg:address":"Lehrter Str. 69a",
    "sg:city":"Berlin",
    "sg:phone":"+49 30/39052532",
    "sg:postcode":"10557",
    "sg:province":"Berlin",
    "wof:name":"Seniorenwohnhaus",
    "wof:placetype":"venue"
},
  "geometry": {"coordinates":[13.364313,52.526604],"type":"Point"}
}