{
  "type": "Feature",
  "properties": {
    "iso:country":"DE",
    "sg:address":"Glogauer Str 13",
    "sg:city":"Kelkheim",
    "sg:phone":"+49 6195/724101",
    "sg:postcode":"65779",
    "sg:province":"Hessen",
    "wof:name":"Agentur F\u00fcr Online-services",
    "wof:placetype":"venue"
},
  "geometry": {"coordinates":[8.4607772827,50.1298713684],"type":"Point"}
}