{
  "type": "Feature",
  "properties": {
    "iso:country":"DE",
    "sg:address":"Benno-Strau\u00df-Str. 39",
    "sg:city":"F\u00fcrth",
    "sg:phone":"+49 911/65850",
    "sg:postcode":"90763",
    "sg:province":"Bayern",
    "wof:name":"Ringfoto Beteiligungsges. Mbh",
    "wof:placetype":"venue"
},
  "geometry": {"coordinates":[10.993987,49.444752],"type":"Point"}
}