{
  "type": "Feature",
  "properties": {
    "iso:country":"DE",
    "sg:address":"Merseburger Str.",
    "sg:city":"Burghausen",
    "sg:phone":"+49 341/4771896",
    "sg:postcode":"04430",
    "sg:province":"Bayern",
    "wof:name":"Lidl Gmbh & Co. Kg",
    "wof:placetype":"venue"
},
  "geometry": {"coordinates":[12.2660198212,51.3559989929],"type":"Point"}
}