{
  "type": "Feature",
  "properties": {
    "iso:country":"DE",
    "sg:address":"Bessemerstr. 16",
    "sg:city":"L\u00fcneburg",
    "sg:phone":"+49 4131/30270",
    "sg:postcode":"21339",
    "sg:province":"Niedersachsen",
    "wof:name":"Eisenvater L\u00fcneburg Kg",
    "wof:placetype":"venue"
},
  "geometry": {"coordinates":[10.4097681046,53.2731170654],"type":"Point"}
}