{
  "type": "Feature",
  "properties": {
    "iso:country":"DE",
    "sg:address":"Bismarckstr. 28",
    "sg:city":"Marburg",
    "sg:phone":"+49 6421/12327",
    "sg:postcode":"35037",
    "sg:province":"Hessen",
    "wof:name":"Alfred Lerch Steuerberater",
    "wof:placetype":"venue"
},
  "geometry": {"coordinates":[8.7637367249,50.8038101196],"type":"Point"}
}