{
  "type": "Feature",
  "properties": {
    "iso:country":"DE",
    "sg:address":"Dolomitenstr. 2",
    "sg:city":"Regensburg",
    "sg:phone":"+49 941/696870",
    "sg:postcode":"93057",
    "sg:province":"Bayern",
    "wof:name":"Sonnen-apotheke",
    "wof:placetype":"venue"
},
  "geometry": {"coordinates":[12.123944,49.042355],"type":"Point"}
}