{
  "type": "Feature",
  "properties": {
    "iso:country":"DE",
    "sg:address":"Freudenthalstr.6",
    "sg:city":"Buchholz",
    "sg:phone":"+49 4181",
    "sg:postcode":"21244",
    "sg:province":"Niedersachsen",
    "wof:name":"Cornelia Klee Immobilien/reinke Partner Immobilien",
    "wof:placetype":"venue"
},
  "geometry": {"coordinates":[9.8787508011,53.3392791748],"type":"Point"}
}