{
  "type": "Feature",
  "properties": {
    "iso:country":"DE",
    "sg:address":"Eisenacher Str. 22",
    "sg:city":"Tann",
    "sg:phone":"+49 6682/8088",
    "sg:postcode":"36142",
    "sg:province":"Hessen",
    "wof:name":"Dietzel & Sohn Ohg",
    "wof:placetype":"venue"
},
  "geometry": {"coordinates":[10.00858,50.623402],"type":"Point"}
}