{
  "type": "Feature",
  "properties": {
    "iso:country":"DE",
    "sg:address":"Friedrich-Ebert-Str. 12",
    "sg:city":"Bad Blankenburg",
    "sg:phone":"+49 36741/2532",
    "sg:postcode":"07422",
    "sg:province":"Th\u00fcringen",
    "wof:name":"Helmut Kr\u00e4mer",
    "wof:placetype":"venue"
},
  "geometry": {"coordinates":[11.26097,50.683788],"type":"Point"}
}