{
  "type": "Feature",
  "properties": {
    "iso:country":"DE",
    "sg:address":"S\u00e4gm\u00fchle 1-3",
    "sg:city":"Vorderweidenthal",
    "sg:phone":"+49 6343/939690",
    "sg:postcode":"76889",
    "sg:province":"Rheinland-Pfalz",
    "wof:name":"Arnold Technologiehandels Und Verwaltungs Gmbh",
    "wof:placetype":"venue"
},
  "geometry": {"coordinates":[7.9580597878,49.0538902283],"type":"Point"}
}