{
  "type": "Feature",
  "properties": {
    "iso:country":"DE",
    "sg:address":"Ermsstr. 25",
    "sg:city":"Metzingen",
    "sg:phone":"+49 7123/96870",
    "sg:postcode":"72555",
    "sg:province":"Baden-W\u00fcrttemberg",
    "wof:name":"O. & P. Melchinger Kg",
    "wof:placetype":"venue"
},
  "geometry": {"coordinates":[9.296836,48.532406],"type":"Point"}
}