{
  "type": "Feature",
  "properties": {
    "iso:country":"DE",
    "sg:address":"Hauptstr. 21",
    "sg:city":"K\u00fcnzelsau",
    "sg:phone":"+49 7940/2442",
    "sg:postcode":"74653",
    "sg:province":"Baden-W\u00fcrttemberg",
    "wof:name":"Mayflower",
    "wof:placetype":"venue"
},
  "geometry": {"coordinates":[9.6888647079,49.2784919739],"type":"Point"}
}