{
  "type": "Feature",
  "properties": {
    "iso:country":"DE",
    "sg:address":"Lindgesfeld 26",
    "sg:city":"Solingen",
    "sg:phone":"+49 212/38270",
    "sg:postcode":"42653",
    "sg:province":"Nordrhein-Westfalen",
    "wof:name":"Cd-design Gmbh",
    "wof:placetype":"venue"
},
  "geometry": {"coordinates":[7.08271,51.204819],"type":"Point"}
}