{
  "type": "Feature",
  "properties": {
    "iso:country":"DE",
    "sg:address":"Schulstr. 19",
    "sg:city":"Benningen",
    "sg:phone":"+49 7144/97813",
    "sg:postcode":"71726",
    "sg:province":"Baden-W\u00fcrttemberg",
    "wof:name":"Eva-maria Wiesenauer Krankengymnastin",
    "wof:placetype":"venue"
},
  "geometry": {"coordinates":[9.243363,48.946327],"type":"Point"}
}