{
  "type": "Feature",
  "properties": {
    "iso:country":"DE",
    "sg:address":"Wutzm\u00fchlstr. 37",
    "sg:city":"Furth im Wald",
    "sg:phone":"+49 9973/1351",
    "sg:postcode":"93437",
    "sg:province":"Bayern",
    "wof:name":"Josef Sp\u00e4th",
    "wof:placetype":"venue"
},
  "geometry": {"coordinates":[12.838432312,49.3030700684],"type":"Point"}
}