{
  "type": "Feature",
  "properties": {
    "iso:country":"DE",
    "sg:address":"Spitalstr. 17",
    "sg:city":"Edenkoben",
    "sg:phone":"+49 6323/2056",
    "sg:postcode":"67480",
    "sg:province":"Rheinland-Pfalz",
    "wof:name":"Dr. Med. Ingo Bittmann",
    "wof:placetype":"venue"
},
  "geometry": {"coordinates":[8.1238183975,49.2820739746],"type":"Point"}
}