{
  "type": "Feature",
  "properties": {
    "iso:country":"DE",
    "sg:address":"Gartenstr. 3",
    "sg:city":"Baldham",
    "sg:phone":"+49 8106/7620",
    "sg:postcode":"85598",
    "sg:province":"Bayern",
    "wof:name":"Jehle Immobilienmakler",
    "wof:placetype":"venue"
},
  "geometry": {"coordinates":[11.7876033783,48.0960731506],"type":"Point"}
}