{
  "type": "Feature",
  "properties": {
    "iso:country":"DE",
    "sg:address":"Vaihinger Str. 13",
    "sg:city":"Sachsenheim",
    "sg:phone":"+49 7147/6758",
    "sg:postcode":"74343",
    "sg:province":"Baden-W\u00fcrttemberg",
    "wof:name":"G. Ulmer Automation Gmbh",
    "wof:placetype":"venue"
},
  "geometry": {"coordinates":[9.0218753815,48.9979896545],"type":"Point"}
}