{
  "type": "Feature",
  "properties": {
    "iso:country":"DE",
    "sg:address":"W\u00fcrzburger Str. 54",
    "sg:city":"Aschaffenburg",
    "sg:phone":"+49 6021/23080",
    "sg:postcode":"63739",
    "sg:province":"Bayern",
    "wof:name":"Dr. Med. Maximilian H\u00f6pfl",
    "wof:placetype":"venue"
},
  "geometry": {"coordinates":[9.1565532684,49.9729652405],"type":"Point"}
}