{
  "type": "Feature",
  "properties": {
    "iso:country":"DE",
    "sg:address":"Osnabr\u00fccker Str. 21",
    "sg:city":"Bad Rothenfelde",
    "sg:phone":"+49 5424/4426",
    "sg:postcode":"49214",
    "sg:province":"Niedersachsen",
    "wof:name":"Westfalen Tankstelle",
    "wof:placetype":"venue"
},
  "geometry": {"coordinates":[8.1621713638,52.1131973267],"type":"Point"}
}