{
  "type": "Feature",
  "properties": {
    "iso:country":"DE",
    "sg:address":"I. Enge Str. 2 3",
    "sg:city":"Schwerin",
    "sg:phone":"+49 385/562912",
    "sg:postcode":"19055",
    "sg:province":"Mecklenburg-Vorpommern",
    "wof:name":"Schweriner Antiquariat",
    "wof:placetype":"venue"
},
  "geometry": {"coordinates":[11.4137554169,53.6284675598],"type":"Point"}
}