{
  "type": "Feature",
  "properties": {
    "iso:country":"DE",
    "sg:address":"Reichenbachtal 81",
    "sg:city":"Gengenbach",
    "sg:phone":"+49 7803/2442",
    "sg:postcode":"77723",
    "sg:province":"Baden-W\u00fcrttemberg",
    "wof:name":"Holzplatzstube",
    "wof:placetype":"venue"
},
  "geometry": {"coordinates":[8.0198707581,48.4306793213],"type":"Point"}
}