{
  "type": "Feature",
  "properties": {
    "iso:country":"DE",
    "sg:address":"Schaffneiweg 5",
    "sg:city":"Mosbach",
    "sg:phone":"+49 6261/4728",
    "sg:postcode":"74821",
    "sg:province":"Baden-W\u00fcrttemberg",
    "wof:name":"Kleintierzuchtverein Dallau Herbert Sander",
    "wof:placetype":"venue"
},
  "geometry": {"coordinates":[9.1484203339,49.3499794006],"type":"Point"}
}