{
  "type": "Feature",
  "properties": {
    "iso:country":"DE",
    "sg:address":"Raffaelweg 1",
    "sg:city":"Hilden",
    "sg:phone":"+49 2103/21217",
    "sg:postcode":"40724",
    "sg:province":"Nordrhein-Westfalen",
    "wof:name":"Ost-alarm In Dresden Gesellschaft F\u00fcr Alarm-",
    "wof:placetype":"venue"
},
  "geometry": {"coordinates":[6.9786520004,51.1697692871],"type":"Point"}
}