{
  "type": "Feature",
  "properties": {
    "iso:country":"DE",
    "sg:city":"Ennepetal",
    "sg:phone":"+49 4923/334102",
    "sg:postcode":"58256",
    "sg:province":"Nordrhein-Westfalen",
    "wof:name":"Deutsche Bank Ag",
    "wof:placetype":"venue"
},
  "geometry": {"coordinates":[7.369048,51.296734],"type":"Point"}
}