{
  "type": "Feature",
  "properties": {
    "iso:country":"DE",
    "sg:address":"Kiefernweg 1",
    "sg:city":"Eschborn",
    "sg:phone":"+49 6173/61047",
    "sg:postcode":"65760",
    "sg:province":"Hessen",
    "wof:name":"Werner W. Hess Gmbh",
    "wof:placetype":"venue"
},
  "geometry": {"coordinates":[8.5485639572,50.1685714722],"type":"Point"}
}