{
  "type": "Feature",
  "properties": {
    "iso:country":"DE",
    "sg:address":"Schlosserstr. 39",
    "sg:city":"Jever",
    "sg:phone":"+49 4461/71619",
    "sg:postcode":"26441",
    "sg:province":"Niedersachsen",
    "wof:name":"Sir Drake Pub",
    "wof:placetype":"venue"
},
  "geometry": {"coordinates":[7.8939647675,53.5694961548],"type":"Point"}
}