{
  "type": "Feature",
  "properties": {
    "iso:country":"DE",
    "sg:address":"Erich-Schlesinger-Str 21",
    "sg:city":"Rostock",
    "sg:phone":"+49 381/448132",
    "sg:postcode":"18059",
    "sg:province":"Mecklenburg-Vorpommern",
    "wof:name":"Druckerei F. Seiboth",
    "wof:placetype":"venue"
},
  "geometry": {"coordinates":[12.1152658463,54.0799102783],"type":"Point"}
}