{
  "type": "Feature",
  "properties": {
    "iso:country":"DE",
    "sg:address":"Schmiedestr. 4",
    "sg:city":"Gelsenkirchen",
    "sg:phone":"+49 209/941330",
    "sg:postcode":"45881",
    "sg:province":"Nordrhein-Westfalen",
    "wof:name":"Hsa Handelsgesellschaft F\u00fcr Schrott Und Altmetalle Mbh",
    "wof:placetype":"venue"
},
  "geometry": {"coordinates":[7.0797262192,51.5148277283],"type":"Point"}
}