{
  "type": "Feature",
  "properties": {
    "iso:country":"DE",
    "sg:address":"Sootb\u00f6rn 15",
    "sg:city":"Hamburg",
    "sg:phone":"+49 40/584286",
    "sg:postcode":"22453",
    "sg:province":"Hamburg",
    "wof:name":"Blumenhaus Huch Ohg",
    "wof:placetype":"venue"
},
  "geometry": {"coordinates":[9.955268,53.615993],"type":"Point"}
}