{
  "type": "Feature",
  "properties": {
    "iso:country":"DE",
    "sg:address":"Ringstr. 8",
    "sg:city":"Allendorf",
    "sg:postcode":"35108",
    "sg:province":"Hessen",
    "wof:name":"Polsterbetten Und Teppichwelt Klaus-rainer Hudyma",
    "wof:placetype":"venue"
},
  "geometry": {"coordinates":[8.6659679413,51.0201797485],"type":"Point"}
}