{
  "type": "Feature",
  "properties": {
    "iso:country":"DE",
    "sg:address":"Frankfurter Str. 587",
    "sg:city":"K\u00f6ln",
    "sg:phone":"+49 2203/307035",
    "sg:postcode":"51107",
    "sg:province":"Nordrhein-Westfalen",
    "wof:name":"Neckura Versicherung",
    "wof:placetype":"venue"
},
  "geometry": {"coordinates":[7.0359039307,50.9357643127],"type":"Point"}
}