{
  "type": "Feature",
  "properties": {
    "iso:country":"DE",
    "sg:address":"Benediktenwandstr. 26",
    "sg:city":"M\u00fcnchen",
    "sg:phone":"+49 89/6427890",
    "sg:postcode":"81545",
    "sg:province":"Bayern",
    "wof:name":"Karin Ragaller Inh. Werner Schmidt",
    "wof:placetype":"venue"
},
  "geometry": {"coordinates":[11.546246,48.077972],"type":"Point"}
}