{
  "type": "Feature",
  "properties": {
    "iso:country":"DE",
    "sg:address":"Dreizehnmorgenweg 6",
    "sg:city":"Bonn",
    "sg:postcode":"53175",
    "sg:province":"Nordrhein-Westfalen",
    "wof:name":"Care Deutschland E.v.",
    "wof:placetype":"venue"
},
  "geometry": {"coordinates":[7.1354417801,50.7011833191],"type":"Point"}
}