{
  "type": "Feature",
  "properties": {
    "iso:country":"DE",
    "sg:address":"Pfarrstr. 4",
    "sg:city":"Offenburg",
    "sg:phone":"+49 781/23816",
    "sg:postcode":"77652",
    "sg:province":"Baden-W\u00fcrttemberg",
    "wof:name":"Kath. \u00d6ffentliche Bibliothek Heilig Kreuz",
    "wof:placetype":"venue"
},
  "geometry": {"coordinates":[7.941628,48.471256],"type":"Point"}
}