{
  "type": "Feature",
  "properties": {
    "iso:country":"DE",
    "sg:address":"Sch\u00fctzenstr. 12",
    "sg:city":"Bergisch Gladbach",
    "sg:phone":"+49 2202/33467",
    "sg:postcode":"51465",
    "sg:province":"Nordrhein-Westfalen",
    "wof:name":"Josef Bl\u00e4sius & S\u00f6hne Dach- Wand- Und",
    "wof:placetype":"venue"
},
  "geometry": {"coordinates":[7.14192,50.989292],"type":"Point"}
}