{
  "type": "Feature",
  "properties": {
    "iso:country":"DE",
    "sg:address":"Fronstr. 2",
    "sg:city":"Worms",
    "sg:phone":"+49 6242/3261",
    "sg:postcode":"67550",
    "sg:province":"Rheinland-Pfalz",
    "wof:name":"Klausenberg-apotheke",
    "wof:placetype":"venue"
},
  "geometry": {"coordinates":[8.280806,49.677223],"type":"Point"}
}