{
  "type": "Feature",
  "properties": {
    "iso:country":"DE",
    "sg:address":"Weinbergstr. 2",
    "sg:city":"Darmstadt",
    "sg:phone":"+49 6151/62682",
    "sg:postcode":"64285",
    "sg:province":"Hessen",
    "wof:name":"Heinz H. Dillmann",
    "wof:placetype":"venue"
},
  "geometry": {"coordinates":[8.651061,49.855759],"type":"Point"}
}