{
  "type": "Feature",
  "properties": {
    "iso:country":"DE",
    "sg:address":"Otto-Perutz-Str. 6",
    "sg:city":"Bruckm\u00fchl",
    "sg:phone":"+49 8061/342222",
    "sg:postcode":"83052",
    "sg:province":"Bayern",
    "wof:name":"Rudolfo Malerbetrieb Gmbh",
    "wof:placetype":"venue"
},
  "geometry": {"coordinates":[11.968724,47.874771],"type":"Point"}
}