{
  "type": "Feature",
  "properties": {
    "iso:country":"DE",
    "sg:address":"Am R\u00f6merweg 3",
    "sg:city":"Schifferstadt",
    "sg:phone":"+49 6235/81139",
    "sg:postcode":"67105",
    "sg:province":"Rheinland-Pfalz",
    "wof:name":"E. Wentz Immobilienmakler",
    "wof:placetype":"venue"
},
  "geometry": {"coordinates":[8.3742256165,49.394744873],"type":"Point"}
}