{
  "type": "Feature",
  "properties": {
    "iso:country":"DE",
    "sg:address":"Heiligenbergerstr.11",
    "sg:city":"Ostrach",
    "sg:phone":"+49 7585",
    "sg:postcode":"88356",
    "sg:province":"Baden-W\u00fcrttemberg",
    "wof:name":"Jung Polykontakt Gmbh",
    "wof:placetype":"venue"
},
  "geometry": {"coordinates":[9.3772640228,47.945854187],"type":"Point"}
}