{
  "type": "Feature",
  "properties": {
    "iso:country":"DE",
    "sg:address":"B\u00fcttnergasse 1",
    "sg:city":"Karlstadt",
    "sg:phone":"+49 9353/228",
    "sg:postcode":"97753",
    "sg:province":"Bayern",
    "wof:name":"Kath. Pfarramt Mari\u00e4 Himmelfahrt",
    "wof:placetype":"venue"
},
  "geometry": {"coordinates":[9.6809892654,49.9923973083],"type":"Point"}
}