{
  "type": "Feature",
  "properties": {
    "iso:country":"DE",
    "sg:address":"Rottscheidter Str. 35",
    "sg:city":"Wuppertal",
    "sg:phone":"+49 202/781161",
    "sg:postcode":"42329",
    "sg:province":"Nordrhein-Westfalen",
    "wof:name":"Axel H\u00f6rster",
    "wof:placetype":"venue"
},
  "geometry": {"coordinates":[7.072724,51.23008],"type":"Point"}
}