{
  "type": "Feature",
  "properties": {
    "iso:country":"DE",
    "sg:address":"Bonsweiherer Str. 2",
    "sg:city":"M\u00f6rlenbach",
    "sg:phone":"+49 6209/4210",
    "sg:postcode":"69509",
    "sg:province":"Hessen",
    "wof:name":"Hermann Knapp",
    "wof:placetype":"venue"
},
  "geometry": {"coordinates":[8.736145,49.597534],"type":"Point"}
}