{
  "type": "Feature",
  "properties": {
    "iso:country":"DE",
    "sg:address":"Pippinger Str. 163",
    "sg:city":"M\u00fcnchen",
    "sg:phone":"+49 89/8116246",
    "sg:postcode":"81247",
    "sg:province":"Bayern",
    "wof:name":"Ferdinand Kornberger",
    "wof:placetype":"venue"
},
  "geometry": {"coordinates":[11.454297,48.173126],"type":"Point"}
}