{
  "type": "Feature",
  "properties": {
    "iso:country":"DE",
    "sg:address":"Seu\u00dfener Str.",
    "sg:city":"Arzberg",
    "sg:phone":"+49 9233/8877",
    "sg:postcode":"95659",
    "sg:province":"Bayern",
    "wof:name":"Adolf Seifert",
    "wof:placetype":"venue"
},
  "geometry": {"coordinates":[12.164475441,50.055229187],"type":"Point"}
}