{
  "type": "Feature",
  "properties": {
    "iso:country":"DE",
    "sg:address":"Rosenweg 62 a",
    "sg:city":"Geretsried",
    "sg:phone":"+49 8171/60589",
    "sg:postcode":"82538",
    "sg:province":"Bayern",
    "wof:name":"Siegfried Pfaff Architekt",
    "wof:placetype":"venue"
},
  "geometry": {"coordinates":[11.471761,47.885868],"type":"Point"}
}