{
  "type": "Feature",
  "properties": {
    "iso:country":"DE",
    "sg:address":"Birkbuschstr. 12",
    "sg:city":"Berlin",
    "sg:phone":"+49 30/8349011",
    "sg:postcode":"12167",
    "sg:province":"Berlin",
    "wof:name":"Sixt Budget",
    "wof:placetype":"venue"
},
  "geometry": {"coordinates":[13.321427,52.451061],"type":"Point"}
}