{
  "type": "Feature",
  "properties": {
    "iso:country":"DE",
    "sg:address":"Osterweder Str. 46b",
    "sg:city":"Worpswede",
    "sg:postcode":"27726",
    "sg:province":"Niedersachsen",
    "wof:name":"Mc Gellan Gmbh",
    "wof:placetype":"venue"
},
  "geometry": {"coordinates":[8.9391689301,53.2294921875],"type":"Point"}
}