{
  "type": "Feature",
  "properties": {
    "iso:country":"DE",
    "sg:address":"Holsteiner Str. 35",
    "sg:city":"Marl",
    "sg:phone":"+49 2365/395090",
    "sg:postcode":"45770",
    "sg:province":"Nordrhein-Westfalen",
    "wof:name":"Goldbergshof",
    "wof:placetype":"venue"
},
  "geometry": {"coordinates":[7.1853151321,51.6650810242],"type":"Point"}
}