{
  "type": "Feature",
  "properties": {
    "iso:country":"DE",
    "sg:address":"Niedermayerstr. 8",
    "sg:city":"Landshut",
    "sg:phone":"+49 871/2063",
    "sg:postcode":"84028",
    "sg:province":"Bayern",
    "wof:name":"Eller Wohnbau Gmbh",
    "wof:placetype":"venue"
},
  "geometry": {"coordinates":[12.165432,48.541405],"type":"Point"}
}