{
  "type": "Feature",
  "properties": {
    "iso:country":"DE",
    "sg:address":"Am Lintel 33",
    "sg:city":"Bremerv\u00f6rde",
    "sg:phone":"+49 4761/5299",
    "sg:postcode":"27432",
    "sg:province":"Niedersachsen",
    "wof:name":"Korken Weinladen",
    "wof:placetype":"venue"
},
  "geometry": {"coordinates":[9.1371526718,53.5286521912],"type":"Point"}
}