{
  "type": "Feature",
  "properties": {
    "iso:country":"DE",
    "sg:address":"Schulstr. 33",
    "sg:city":"Wilhelmshaven",
    "sg:phone":"+49 4421/365146",
    "sg:postcode":"26384",
    "sg:province":"Niedersachsen",
    "wof:name":"J. Erkelens",
    "wof:placetype":"venue"
},
  "geometry": {"coordinates":[8.124323,53.531101],"type":"Point"}
}