{
  "type": "Feature",
  "properties": {
    "iso:country":"DE",
    "sg:address":"Brokeloher Hauptstr. 37",
    "sg:city":"Landesbergen",
    "sg:phone":"+49 5027/1566",
    "sg:postcode":"31628",
    "sg:province":"Niedersachsen",
    "wof:name":"Heidelbeeranbauer L\u00fcneburger Heide E. V.",
    "wof:placetype":"venue"
},
  "geometry": {"coordinates":[9.2137384415,52.5511550903],"type":"Point"}
}