{
  "type": "Feature",
  "properties": {
    "iso:country":"DE",
    "sg:address":"Karlstr. 12",
    "sg:city":"Sigmaringen",
    "sg:phone":"+49 7571/50858",
    "sg:postcode":"72488",
    "sg:province":"Baden-W\u00fcrttemberg",
    "wof:name":"Kath. Sozialstation Thomas Geiselhart E. V.",
    "wof:placetype":"venue"
},
  "geometry": {"coordinates":[9.219623,48.085732],"type":"Point"}
}