{
  "type": "Feature",
  "properties": {
    "iso:country":"DE",
    "sg:address":"Mittelstr. 19 a",
    "sg:city":"Roth",
    "sg:phone":"+49 2742/2941",
    "sg:postcode":"57539",
    "sg:province":"Rheinland-Pfalz",
    "wof:name":"Werner Paulus",
    "wof:placetype":"venue"
},
  "geometry": {"coordinates":[7.7135071754,50.7663383484],"type":"Point"}
}