{
  "type": "Feature",
  "properties": {
    "iso:country":"DE",
    "sg:address":"R\u00f6merstr. 7",
    "sg:city":"Meerbusch",
    "sg:phone":"+49 2132/8271",
    "sg:postcode":"40667",
    "sg:province":"Nordrhein-Westfalen",
    "wof:name":"Pella Grill",
    "wof:placetype":"venue"
},
  "geometry": {"coordinates":[6.6974458694,51.2429847717],"type":"Point"}
}