{
  "type": "Feature",
  "properties": {
    "iso:country":"DE",
    "sg:address":"Ottlarer Str. 11",
    "sg:city":"Willingen",
    "sg:phone":"+49 5632/5309",
    "sg:postcode":"34508",
    "sg:province":"Hessen",
    "wof:name":"Ernst Grebe",
    "wof:placetype":"venue"
},
  "geometry": {"coordinates":[8.651276,51.31134],"type":"Point"}
}