{
  "type": "Feature",
  "properties": {
    "iso:country":"DE",
    "sg:address":"Fraunhoferstr 19",
    "sg:city":"Memmingen",
    "sg:phone":"+49 8331/92770",
    "sg:postcode":"87700",
    "sg:province":"Bayern",
    "wof:name":"Memminger Mediencentrum Druckerei Und Verlagshaus Ag",
    "wof:placetype":"venue"
},
  "geometry": {"coordinates":[10.1649980545,48.0024147034],"type":"Point"}
}