{
  "type": "Feature",
  "properties": {
    "iso:country":"DE",
    "sg:address":"Treeneblick 1",
    "sg:city":"Langstedt",
    "sg:phone":"+49 4609/663",
    "sg:postcode":"24852",
    "sg:province":"Schleswig-Holstein",
    "wof:name":"J. Andresen",
    "wof:placetype":"venue"
},
  "geometry": {"coordinates":[9.388176,54.619816],"type":"Point"}
}