{
  "type": "Feature",
  "properties": {
    "iso:country":"DE",
    "sg:address":"Pr\u00e4sident-Herwig-Str 61-64",
    "sg:city":"Cuxhaven",
    "sg:phone":"+49 6101/545110",
    "sg:postcode":"27472",
    "sg:province":"Niedersachsen",
    "wof:name":"Ahrens & Bergh\u00f6fer Gmbh",
    "wof:placetype":"venue"
},
  "geometry": {"coordinates":[8.72199,50.190804],"type":"Point"}
}