{
  "type": "Feature",
  "properties": {
    "iso:country":"DE",
    "sg:address":"Osterfelderstr.117",
    "sg:city":"Bottrop",
    "sg:phone":"+49 2041",
    "sg:postcode":"46236",
    "sg:province":"Nordrhein-Westfalen",
    "wof:name":"Schlie\u00df-und Sicherheitstechnik Maas",
    "wof:placetype":"venue"
},
  "geometry": {"coordinates":[6.910503,51.518372],"type":"Point"}
}