{
  "type": "Feature",
  "properties": {
    "iso:country":"DE",
    "sg:address":"Oberlinstr. 30",
    "sg:city":"Siegen",
    "sg:phone":"+49 271/62535",
    "sg:postcode":"57074",
    "sg:province":"Nordrhein-Westfalen",
    "wof:name":"Wolfgang Sonntag Ingenieur",
    "wof:placetype":"venue"
},
  "geometry": {"coordinates":[8.0395889282,50.8762626648],"type":"Point"}
}