{
  "type": "Feature",
  "properties": {
    "iso:country":"DE",
    "sg:address":"Kreuzstr. 8",
    "sg:city":"Dortmund",
    "sg:phone":"+49 231/122423",
    "sg:postcode":"44139",
    "sg:province":"Nordrhein-Westfalen",
    "wof:name":"Stendel Gmbh",
    "wof:placetype":"venue"
},
  "geometry": {"coordinates":[7.457587,51.503895],"type":"Point"}
}