{
  "type": "Feature",
  "properties": {
    "iso:country":"DE",
    "sg:address":"Am Anger 19",
    "sg:city":"Sankt Englmar",
    "sg:phone":"+49 9965/1618",
    "sg:postcode":"94379",
    "sg:province":"Bayern",
    "wof:name":"Werner Oltmann",
    "wof:placetype":"venue"
},
  "geometry": {"coordinates":[12.8298139572,49.0016899109],"type":"Point"}
}