{
  "type": "Feature",
  "properties": {
    "iso:country":"DE",
    "sg:address":"Pillnitzer Str. 71",
    "sg:city":"Radeberg",
    "sg:phone":"+49 3528/43970",
    "sg:postcode":"01454",
    "sg:province":"Sachsen",
    "wof:name":"Taubblindendienst Storchennest E. V.",
    "wof:placetype":"venue"
},
  "geometry": {"coordinates":[13.9222297668,51.1051063538],"type":"Point"}
}