{
  "type": "Feature",
  "properties": {
    "iso:country":"DE",
    "sg:address":"Hamburger Str. 33",
    "sg:city":"Schwarzenbek",
    "sg:phone":"+49 4151/2005",
    "sg:postcode":"21493",
    "sg:province":"Schleswig-Holstein",
    "wof:name":"Paulsen Optiker",
    "wof:placetype":"venue"
},
  "geometry": {"coordinates":[10.4703025818,53.5011787415],"type":"Point"}
}