{
  "type": "Feature",
  "properties": {
    "iso:country":"DE",
    "sg:address":"Aufkirchner Str. 10 C",
    "sg:city":"Maisach",
    "sg:phone":"+49 8141/90409",
    "sg:postcode":"82216",
    "sg:province":"Bayern",
    "wof:name":"Johann Vierthaler",
    "wof:placetype":"venue"
},
  "geometry": {"coordinates":[11.2565097809,48.2155265808],"type":"Point"}
}