{
  "type": "Feature",
  "properties": {
    "iso:country":"DE",
    "sg:address":"Ritzefeldstr. 2",
    "sg:city":"Stolberg",
    "sg:phone":"+49 2402/29310",
    "sg:postcode":"52222",
    "sg:province":"Nordrhein-Westfalen",
    "wof:name":"Hans Hartmann",
    "wof:placetype":"venue"
},
  "geometry": {"coordinates":[6.230363,50.772953],"type":"Point"}
}