{
  "type": "Feature",
  "properties": {
    "iso:country":"DE",
    "sg:address":"la rose",
    "sg:city":"marseille",
    "sg:phone":"+49 491/670721",
    "sg:postcode":"13014",
    "wof:name":"Taxi.service",
    "wof:placetype":"venue"
},
  "geometry": {"coordinates":[5.382571,43.334103],"type":"Point"}
}