{
  "type": "Feature",
  "properties": {
    "iso:country":"DE",
    "sg:address":"Goethestr. 57",
    "sg:city":"Gladbeck",
    "sg:phone":"+49 2043/92000",
    "sg:postcode":"45964",
    "sg:province":"Nordrhein-Westfalen",
    "wof:name":"Schuh Gro\u00dfe-kreul Kg",
    "wof:placetype":"venue"
},
  "geometry": {"coordinates":[6.9916300774,51.5727539062],"type":"Point"}
}