{
  "type": "Feature",
  "properties": {
    "iso:country":"DE",
    "sg:address":"Parkstr. 53",
    "sg:city":"D\u00fcsseldorf",
    "sg:phone":"+49 211/482121",
    "sg:postcode":"40477",
    "sg:province":"Nordrhein-Westfalen",
    "wof:name":"Reimer Mohr",
    "wof:placetype":"venue"
},
  "geometry": {"coordinates":[6.7848639488,51.2379722595],"type":"Point"}
}