{
  "type": "Feature",
  "properties": {
    "iso:country":"DE",
    "sg:address":"Riederm\u00fchler Str. 4",
    "sg:city":"Ilmm\u00fcnster",
    "sg:phone":"+49 8441/2209",
    "sg:postcode":"85304",
    "sg:province":"Bayern",
    "wof:name":"R. Gegger",
    "wof:placetype":"venue"
},
  "geometry": {"coordinates":[11.501433,48.486176],"type":"Point"}
}