{
  "type": "Feature",
  "properties": {
    "iso:country":"DE",
    "sg:address":"\u00d6lm\u00fchle 1",
    "sg:city":"Herbertingen",
    "sg:phone":"+49 7586/1866",
    "sg:postcode":"88518",
    "sg:province":"Baden-W\u00fcrttemberg",
    "wof:name":"Ullwer Immobilien Franchise Gmbh",
    "wof:placetype":"venue"
},
  "geometry": {"coordinates":[9.4619550705,48.0653533936],"type":"Point"}
}