{
  "type": "Feature",
  "properties": {
    "iso:country":"DE",
    "sg:address":"R\u00f6merstr. 18",
    "sg:city":"Schriesheim",
    "sg:phone":"+49 6203/65436",
    "sg:postcode":"69198",
    "sg:province":"Baden-W\u00fcrttemberg",
    "wof:name":"Hella Richter Heilpraktikerin",
    "wof:placetype":"venue"
},
  "geometry": {"coordinates":[8.6611328125,49.4742965698],"type":"Point"}
}