{
  "type": "Feature",
  "properties": {
    "iso:country":"DE",
    "sg:address":"Ginsterweg 1",
    "sg:city":"Barth",
    "sg:phone":"+49 38231/2501",
    "sg:postcode":"18356",
    "sg:province":"Mecklenburg-Vorpommern",
    "wof:name":"Eggert Gmbh",
    "wof:placetype":"venue"
},
  "geometry": {"coordinates":[12.67776,54.36692],"type":"Point"}
}