{
  "type": "Feature",
  "properties": {
    "iso:country":"DE",
    "sg:address":"Bajuwarenrg.3",
    "sg:city":"Oberhaching",
    "sg:phone":"+49 89/9590950",
    "sg:postcode":"82041",
    "sg:province":"Bayern",
    "wof:name":"Eurofactor Gmbh",
    "wof:placetype":"venue"
},
  "geometry": {"coordinates":[11.580915,48.030693],"type":"Point"}
}