{
  "type": "Feature",
  "properties": {
    "iso:country":"DE",
    "sg:address":"Brunsb\u00fctteler Damm 57",
    "sg:city":"Berlin",
    "sg:phone":"+49 30/3325937",
    "sg:postcode":"13581",
    "sg:province":"Berlin",
    "wof:name":"Brutzelpfanne",
    "wof:placetype":"venue"
},
  "geometry": {"coordinates":[13.189786911,52.5342597961],"type":"Point"}
}