{
  "type": "Feature",
  "properties": {
    "iso:country":"DE",
    "sg:address":"Preu\u00dfenstr. 36 a",
    "sg:city":"L\u00fcnen",
    "sg:phone":"+49 2306/40266",
    "sg:postcode":"44532",
    "sg:province":"Nordrhein-Westfalen",
    "wof:name":"Kant-apotheke Stefanie Kalinowski E. K.",
    "wof:placetype":"venue"
},
  "geometry": {"coordinates":[7.543085,51.589722],"type":"Point"}
}