{
  "type": "Feature",
  "properties": {
    "iso:country":"DE",
    "sg:address":"Hauptstr. 9",
    "sg:city":"M\u00fchlhausen-Ehingen",
    "sg:postcode":"78259",
    "sg:province":"Baden-W\u00fcrttemberg",
    "wof:name":"Src E. K.",
    "wof:placetype":"venue"
},
  "geometry": {"coordinates":[8.809444,47.827824],"type":"Point"}
}