{
  "type": "Feature",
  "properties": {
    "iso:country":"DE",
    "sg:address":"Hannoversche Heerstr. 119",
    "sg:city":"Celle",
    "sg:phone":"+49 5141/81848",
    "sg:postcode":"29227",
    "sg:province":"Niedersachsen",
    "wof:name":"Elektro-busche",
    "wof:placetype":"venue"
},
  "geometry": {"coordinates":[10.070283,52.597969],"type":"Point"}
}