{
  "type": "Feature",
  "properties": {
    "iso:country":"DE",
    "sg:address":"Hardtsteige 18",
    "sg:city":"Lauchheim",
    "sg:phone":"+49 7363/7171",
    "sg:postcode":"73466",
    "sg:province":"Baden-W\u00fcrttemberg",
    "wof:name":"Tgl Maschinenmarkt",
    "wof:placetype":"venue"
},
  "geometry": {"coordinates":[10.251218,48.869934],"type":"Point"}
}