{
  "type": "Feature",
  "properties": {
    "iso:country":"DE",
    "sg:address":"Glasmoorstr. 65",
    "sg:city":"Norderstedt",
    "sg:phone":"+49 40/5246312",
    "sg:postcode":"22851",
    "sg:province":"Schleswig-Holstein",
    "wof:name":"Bernd Reiher Gmbh",
    "wof:placetype":"venue"
},
  "geometry": {"coordinates":[10.034741,53.700069],"type":"Point"}
}