{
  "type": "Feature",
  "properties": {
    "iso:country":"DE",
    "sg:address":"Bahnhofstr. 48",
    "sg:city":"Freudenberg",
    "sg:phone":"+49 2734/8106",
    "sg:postcode":"57258",
    "sg:province":"Nordrhein-Westfalen",
    "wof:name":"Ludwig K\u00f6hler",
    "wof:placetype":"venue"
},
  "geometry": {"coordinates":[7.8764910698,50.8971290588],"type":"Point"}
}