{
  "type": "Feature",
  "properties": {
    "iso:country":"DE",
    "sg:address":"Am Moor 33",
    "sg:city":"Engelschoff",
    "sg:phone":"+49 4775/8193",
    "sg:postcode":"21710",
    "sg:province":"Niedersachsen",
    "wof:name":"J\u00fcrgen Winter",
    "wof:placetype":"venue"
},
  "geometry": {"coordinates":[9.334624,53.672165],"type":"Point"}
}