{
  "type": "Feature",
  "properties": {
    "iso:country":"DE",
    "sg:address":"Bahnhofstr. 6",
    "sg:city":"Emsb\u00fcren",
    "sg:phone":"+49 5903/1878",
    "sg:postcode":"48488",
    "sg:province":"Niedersachsen",
    "wof:name":"T. L\u00fchle",
    "wof:placetype":"venue"
},
  "geometry": {"coordinates":[7.29371,52.393078],"type":"Point"}
}