{
  "type": "Feature",
  "properties": {
    "iso:country":"DE",
    "sg:address":"Lorettostr. 8",
    "sg:city":"Oberstdorf",
    "sg:phone":"+49 8322/96140",
    "sg:postcode":"87561",
    "sg:province":"Bayern",
    "wof:name":"G\u00e4stehaus Zur F\u00e4rbe",
    "wof:placetype":"venue"
},
  "geometry": {"coordinates":[10.2806282043,47.4049720764],"type":"Point"}
}