{
  "type": "Feature",
  "properties": {
    "iso:country":"DE",
    "sg:address":"Bahnhofstr. 15",
    "sg:city":"St. Wendel",
    "sg:phone":"+49 6851/81800",
    "sg:postcode":"66606",
    "sg:province":"Saarland",
    "wof:name":"Foto Express Demmer & Co. Gmbh",
    "wof:placetype":"venue"
},
  "geometry": {"coordinates":[7.1684441566,49.4666786194],"type":"Point"}
}