{
  "type": "Feature",
  "properties": {
    "iso:country":"DE",
    "sg:address":"Lindenallee 17",
    "sg:city":"G\u00fcstrow",
    "sg:phone":"+49 3843/211111",
    "sg:postcode":"18273",
    "sg:province":"Mecklenburg-Vorpommern",
    "wof:name":"Restaurant China Haus",
    "wof:placetype":"venue"
},
  "geometry": {"coordinates":[12.1893701553,53.8084602356],"type":"Point"}
}