{
  "type": "Feature",
  "properties": {
    "iso:country":"DE",
    "sg:address":"F\u00fcchteler Str. 14",
    "sg:city":"Vechta",
    "sg:phone":"+49 4441/2380",
    "sg:postcode":"49377",
    "sg:province":"Niedersachsen",
    "wof:name":"Heinrich Engelmann",
    "wof:placetype":"venue"
},
  "geometry": {"coordinates":[8.292633,52.730942],"type":"Point"}
}