{
  "type": "Feature",
  "properties": {
    "iso:country":"DE",
    "sg:address":"Obergasse 23",
    "sg:city":"Wahlheim",
    "sg:phone":"+49 6731/43323",
    "sg:postcode":"55234",
    "sg:province":"Rheinland-Pfalz",
    "wof:name":"Thomas Burkhard",
    "wof:placetype":"venue"
},
  "geometry": {"coordinates":[8.1062364578,49.7177238464],"type":"Point"}
}