{
  "type": "Feature",
  "properties": {
    "iso:country":"DE",
    "sg:address":"Asbeckstr 40",
    "sg:city":"Essen",
    "sg:phone":"+49 6434/7025",
    "sg:postcode":"45356",
    "sg:province":"Nordrhein-Westfalen",
    "wof:name":"Heinz Sch\u00fctz Gmbh",
    "wof:placetype":"venue"
},
  "geometry": {"coordinates":[8.260367,50.297684],"type":"Point"}
}