{
  "type": "Feature",
  "properties": {
    "iso:country":"DE",
    "sg:address":"Obernstr. 2-12",
    "sg:city":"Bremen",
    "sg:phone":"+49 421/328086",
    "sg:postcode":"28195",
    "sg:province":"Bremen",
    "wof:name":"Bwb Wertpapier- Dienstleistung Gmbh",
    "wof:placetype":"venue"
},
  "geometry": {"coordinates":[8.8065052032,53.0764198303],"type":"Point"}
}