{
  "type": "Feature",
  "properties": {
    "iso:country":"DE",
    "sg:address":"Herbertzstr. 116",
    "sg:city":"Krefeld",
    "sg:phone":"+49 2151/540343",
    "sg:postcode":"47809",
    "sg:province":"Nordrhein-Westfalen",
    "wof:name":"I. Friesen Wettannahme",
    "wof:placetype":"venue"
},
  "geometry": {"coordinates":[6.598032,51.325729],"type":"Point"}
}