{
  "type": "Feature",
  "properties": {
    "iso:country":"DE",
    "sg:address":"Moritzstr. 1",
    "sg:city":"Ingolstadt",
    "sg:phone":"+49 841/935510",
    "sg:postcode":"85049",
    "sg:province":"Bayern",
    "wof:name":"W\u00fcrttembergische Versicherung Ag",
    "wof:placetype":"venue"
},
  "geometry": {"coordinates":[11.4241962433,48.7640609741],"type":"Point"}
}