{
  "type": "Feature",
  "properties": {
    "iso:country":"DE",
    "sg:address":"Feigenberg 16",
    "sg:city":"Hatzenb\u00fchl",
    "sg:postcode":"76770",
    "sg:province":"Rheinland-Pfalz",
    "wof:name":"Gemeindeb\u00fccherei",
    "wof:placetype":"venue"
},
  "geometry": {"coordinates":[8.242152,49.109295],"type":"Point"}
}