{
  "type": "Feature",
  "properties": {
    "iso:country":"DE",
    "sg:address":"Mennonitenstr. 20",
    "sg:city":"Hamburg",
    "sg:phone":"+49 40/857112",
    "sg:postcode":"22769",
    "sg:province":"Hamburg",
    "wof:name":"Mennonitengemeinde Zu Hamburg Und Altona",
    "wof:placetype":"venue"
},
  "geometry": {"coordinates":[9.948583,53.567738],"type":"Point"}
}