{
  "type": "Feature",
  "properties": {
    "iso:country":"DE",
    "sg:address":"Tecklenburger Str. 7",
    "sg:city":"Lengerich",
    "sg:phone":"+49 5481/94360",
    "sg:postcode":"49525",
    "sg:province":"Nordrhein-Westfalen",
    "wof:name":"Heinrich Howe",
    "wof:placetype":"venue"
},
  "geometry": {"coordinates":[7.8470621109,52.1912460327],"type":"Point"}
}