{
  "type": "Feature",
  "properties": {
    "iso:country":"DE",
    "sg:address":"Gro\u00df 6",
    "sg:city":"Hindelang",
    "sg:phone":"+49 8324/2365",
    "sg:postcode":"87541",
    "sg:province":"Bayern",
    "wof:name":"Elektro Lipp Gmbh",
    "wof:placetype":"venue"
},
  "geometry": {"coordinates":[10.327692,47.50106],"type":"Point"}
}