{
  "type": "Feature",
  "properties": {
    "iso:country":"DE",
    "sg:address":"Zum Niederberg 8",
    "sg:city":"Lieser",
    "sg:phone":"+49 6531/8380",
    "sg:postcode":"54470",
    "sg:province":"Rheinland-Pfalz",
    "wof:name":"L. Genetsch-zirbes Weinbau",
    "wof:placetype":"venue"
},
  "geometry": {"coordinates":[7.0246510506,49.9169425964],"type":"Point"}
}