{
  "type": "Feature",
  "properties": {
    "iso:country":"DE",
    "sg:address":"Grunbacher Str. 14",
    "sg:city":"Unterreichenbach",
    "sg:phone":"+49 7235/7698",
    "sg:postcode":"75399",
    "sg:province":"Baden-W\u00fcrttemberg",
    "wof:name":"Karen Moestue Masseur",
    "wof:placetype":"venue"
},
  "geometry": {"coordinates":[8.708537,48.82729],"type":"Point"}
}