{
  "type": "Feature",
  "properties": {
    "iso:country":"DE",
    "sg:address":"S\u00fcdstr. 11",
    "sg:city":"St. Ingbert",
    "sg:phone":"+49 6894/6065",
    "sg:postcode":"66386",
    "sg:province":"Saarland",
    "wof:name":"Trim-line",
    "wof:placetype":"venue"
},
  "geometry": {"coordinates":[7.120472,49.267094],"type":"Point"}
}