{
  "type": "Feature",
  "properties": {
    "iso:country":"DE",
    "sg:address":"Ernsdorfstr. 10-12",
    "sg:city":"Kreuztal",
    "sg:phone":"+49 2732/1354",
    "sg:postcode":"57223",
    "sg:province":"Nordrhein-Westfalen",
    "wof:name":"Beerdigungsinstitut Giesler Inh. Otto Henrik Giesler",
    "wof:placetype":"venue"
},
  "geometry": {"coordinates":[7.999635,50.962589],"type":"Point"}
}