{
  "type": "Feature",
  "properties": {
    "iso:country":"DE",
    "sg:address":"Hauptstr. 42",
    "sg:city":"Maxdorf",
    "sg:phone":"+49 6237/920554",
    "sg:postcode":"67133",
    "sg:province":"Rheinland-Pfalz",
    "wof:name":"Tsr Industrieconsulting Gmbh",
    "wof:placetype":"venue"
},
  "geometry": {"coordinates":[8.2970695496,49.4826087952],"type":"Point"}
}