{
  "type": "Feature",
  "properties": {
    "iso:country":"DE",
    "sg:address":"Listrupweg 33",
    "sg:city":"Rheine",
    "sg:phone":"+49 5971/85735",
    "sg:postcode":"48429",
    "sg:province":"Nordrhein-Westfalen",
    "wof:name":"Roelof Hofma",
    "wof:placetype":"venue"
},
  "geometry": {"coordinates":[7.437671,52.288227],"type":"Point"}
}