{
  "type": "Feature",
  "properties": {
    "iso:country":"DE",
    "sg:address":"R\u00f6ntgenstr. 18",
    "sg:city":"Bergisch Gladbach",
    "sg:phone":"+49 2202/59198",
    "sg:postcode":"51465",
    "sg:province":"Nordrhein-Westfalen",
    "wof:name":"Grabmale Schumacher E. K. Inh. Michael Drescher",
    "wof:placetype":"venue"
},
  "geometry": {"coordinates":[7.1271400452,50.9941215515],"type":"Point"}
}