{
  "type": "Feature",
  "properties": {
    "iso:country":"DE",
    "sg:address":"Am Baumgarten 3",
    "sg:city":"Dietersheim",
    "sg:phone":"+49 9161/88750",
    "sg:postcode":"91463",
    "sg:province":"Bayern",
    "wof:name":"Auto Zeilinger Gmbh",
    "wof:placetype":"venue"
},
  "geometry": {"coordinates":[10.5424280167,49.5593032837],"type":"Point"}
}