{
  "type": "Feature",
  "properties": {
    "iso:country":"DE",
    "sg:address":"Von-Ketteler-Str. 65",
    "sg:city":"Paderborn",
    "sg:phone":"+49 5254/953228",
    "sg:postcode":"33106",
    "sg:province":"Nordrhein-Westfalen",
    "wof:name":"Edeka-markt Auster",
    "wof:placetype":"venue"
},
  "geometry": {"coordinates":[8.6824007034,51.734828949],"type":"Point"}
}