{
  "type": "Feature",
  "properties": {
    "iso:country":"DE",
    "sg:address":"Uckerather Str. 66",
    "sg:city":"Hennef",
    "sg:phone":"+49 2248/2442",
    "sg:postcode":"53773",
    "sg:province":"Nordrhein-Westfalen",
    "wof:name":"Gertrud Reuter",
    "wof:placetype":"venue"
},
  "geometry": {"coordinates":[7.337696,50.741539],"type":"Point"}
}