{
  "type": "Feature",
  "properties": {
    "iso:country":"DE",
    "sg:address":"Wagnerstr. 10",
    "sg:city":"D\u00fcsseldorf",
    "sg:phone":"+49 211/3694701",
    "sg:postcode":"40212",
    "sg:province":"Nordrhein-Westfalen",
    "wof:name":"Decocenter Rita Lutat",
    "wof:placetype":"venue"
},
  "geometry": {"coordinates":[6.7851548195,51.2263793945],"type":"Point"}
}