{
  "type": "Feature",
  "properties": {
    "iso:country":"DE",
    "sg:address":"Zwieselstr. 4",
    "sg:city":"Ainring",
    "sg:phone":"+49 8654/5640",
    "sg:postcode":"83404",
    "sg:province":"Bayern",
    "wof:name":"Werner Homm",
    "wof:placetype":"venue"
},
  "geometry": {"coordinates":[12.956605,47.813091],"type":"Point"}
}