{
  "type": "Feature",
  "properties": {
    "iso:country":"DE",
    "sg:address":"G\u00f6belstr. 4",
    "sg:city":"Barsinghausen",
    "sg:phone":"+49 5105/4011",
    "sg:postcode":"30890",
    "sg:province":"Niedersachsen",
    "wof:name":"Dau Bus Gmbh",
    "wof:placetype":"venue"
},
  "geometry": {"coordinates":[9.4848871231,52.3018875122],"type":"Point"}
}