{
  "type": "Feature",
  "properties": {
    "iso:country":"DE",
    "sg:address":"Lendringser Str. 31",
    "sg:city":"M\u00f6hnesee",
    "sg:phone":"+49 2924/5149",
    "sg:postcode":"59519",
    "sg:province":"Nordrhein-Westfalen",
    "wof:name":"Haus Wulf-wegener",
    "wof:placetype":"venue"
},
  "geometry": {"coordinates":[8.133313179,51.516910553],"type":"Point"}
}