{
  "type": "Feature",
  "properties": {
    "iso:country":"DE",
    "sg:address":"Aegidienstr. 7-13",
    "sg:city":"L\u00fcbeck",
    "sg:phone":"+49 451/7063820",
    "sg:postcode":"23552",
    "sg:province":"Schleswig-Holstein",
    "wof:name":"Traum-station",
    "wof:placetype":"venue"
},
  "geometry": {"coordinates":[10.6859121323,53.8647003174],"type":"Point"}
}