{
  "type": "Feature",
  "properties": {
    "iso:country":"DE",
    "sg:address":"Am Wehberg",
    "sg:city":"Dorf Mecklenburg",
    "sg:postcode":"23972",
    "sg:province":"Mecklenburg-Vorpommern",
    "wof:name":"Heinz Grunzel Lebensmittel Gmbh",
    "wof:placetype":"venue"
},
  "geometry": {"coordinates":[11.4666175842,53.8439903259],"type":"Point"}
}