{
  "type": "Feature",
  "properties": {
    "iso:country":"DE",
    "sg:address":"Steinstr. 3",
    "sg:city":"Herford",
    "sg:phone":"+49 5221/58105",
    "sg:postcode":"32052",
    "sg:province":"Nordrhein-Westfalen",
    "wof:name":"Siggis Fr\u00fchst\u00fccksstube",
    "wof:placetype":"venue"
},
  "geometry": {"coordinates":[8.6644496918,52.1165771484],"type":"Point"}
}