{
  "type": "Feature",
  "properties": {
    "iso:country":"DE",
    "sg:address":"Brachwitzer Str. 50",
    "sg:city":"Halle",
    "sg:postcode":"06118",
    "sg:province":"Sachsen-Anhalt",
    "wof:name":"Tuwer-siebdruck Halle",
    "wof:placetype":"venue"
},
  "geometry": {"coordinates":[11.931049,51.528553],"type":"Point"}
}