{
  "type": "Feature",
  "properties": {
    "iso:country":"DE",
    "sg:address":"Langenbergstr. 35",
    "sg:city":"Bocholt",
    "sg:phone":"+49 2871/6956",
    "sg:postcode":"46397",
    "sg:province":"Nordrhein-Westfalen",
    "wof:name":"Asia",
    "wof:placetype":"venue"
},
  "geometry": {"coordinates":[6.6189570427,51.8392448425],"type":"Point"}
}