{
  "type": "Feature",
  "properties": {
    "iso:country":"DE",
    "sg:address":"Bahnhofstr. 16",
    "sg:city":"Regen",
    "sg:phone":"+49 9921/970030",
    "sg:postcode":"94209",
    "sg:province":"Bayern",
    "wof:name":"Netcom Informationssysteme E. K.",
    "wof:placetype":"venue"
},
  "geometry": {"coordinates":[13.132718,48.970108],"type":"Point"}
}