{
  "type": "Feature",
  "properties": {
    "iso:country":"DE",
    "sg:address":"Kemptener Str. 4",
    "sg:city":"Wildpoldsried",
    "sg:phone":"+49 8304/304",
    "sg:postcode":"87499",
    "sg:province":"Bayern",
    "wof:name":"Adolf H\u00e4upl",
    "wof:placetype":"venue"
},
  "geometry": {"coordinates":[10.401762,47.766464],"type":"Point"}
}