{
  "type": "Feature",
  "properties": {
    "iso:country":"DE",
    "sg:address":"Rathausgasse 4",
    "sg:city":"Schwabach",
    "sg:postcode":"91126",
    "sg:province":"Bayern",
    "wof:name":"Argento-martini - Silberschmuck - Uhren - Piercing",
    "wof:placetype":"venue"
},
  "geometry": {"coordinates":[11.0213661194,49.32837677],"type":"Point"}
}