{
  "type": "Feature",
  "properties": {
    "iso:country":"DE",
    "sg:address":"In der Hauschlade 5",
    "sg:city":"Balve",
    "sg:phone":"+49 2375/2675",
    "sg:postcode":"58802",
    "sg:province":"Nordrhein-Westfalen",
    "wof:name":"Hedwig Skowranek Metzgerei",
    "wof:placetype":"venue"
},
  "geometry": {"coordinates":[7.8605332375,51.3289031982],"type":"Point"}
}