{
  "type": "Feature",
  "properties": {
    "iso:country":"DE",
    "sg:address":"Spremberger Str 42",
    "sg:city":"Sellessen",
    "sg:phone":"+49 3563/95344",
    "sg:postcode":"03130",
    "sg:province":"Brandenburg",
    "wof:name":"Hilla Alu-bau Gmbh",
    "wof:placetype":"venue"
},
  "geometry": {"coordinates":[14.40118,51.604195],"type":"Point"}
}