{
  "type": "Feature",
  "properties": {
    "iso:country":"DE",
    "sg:address":"P\u00e4pser Kirchweg 123",
    "sg:city":"Siedenburg",
    "sg:phone":"+49 4272/235",
    "sg:postcode":"27254",
    "sg:province":"Niedersachsen",
    "wof:name":"Erich Metzlaff",
    "wof:placetype":"venue"
},
  "geometry": {"coordinates":[8.943652,52.7052],"type":"Point"}
}