{
  "type": "Feature",
  "properties": {
    "iso:country":"DE",
    "sg:address":"Bruckertal 9",
    "sg:city":"Lorch",
    "sg:phone":"+49 7172/6277",
    "sg:postcode":"73547",
    "sg:province":"Baden-W\u00fcrttemberg",
    "wof:name":"Pension Hubertusklause",
    "wof:placetype":"venue"
},
  "geometry": {"coordinates":[9.7044372559,48.8160667419],"type":"Point"}
}