{
  "type": "Feature",
  "properties": {
    "iso:country":"DE",
    "sg:address":"An der Strusbek 27",
    "sg:city":"Ahrensburg",
    "sg:phone":"+49 4102/42911",
    "sg:postcode":"22926",
    "sg:province":"Schleswig-Holstein",
    "wof:name":"Norbert D\u00fcnger Ma\u00dfm\u00f6bel Gmbh",
    "wof:placetype":"venue"
},
  "geometry": {"coordinates":[10.266364,53.687862],"type":"Point"}
}