{
  "type": "Feature",
  "properties": {
    "iso:country":"DE",
    "sg:address":"Am Bahnhof 66",
    "sg:city":"Gro\u00dfschwabhausen",
    "sg:phone":"+49 36454/51323",
    "sg:postcode":"99441",
    "sg:province":"Th\u00fcringen",
    "wof:name":"Andreas Kirscht",
    "wof:placetype":"venue"
},
  "geometry": {"coordinates":[11.47987,50.936111],"type":"Point"}
}