{
  "type": "Feature",
  "properties": {
    "iso:country":"DE",
    "sg:address":"Coloniastrasse 24",
    "sg:city":"Bochum",
    "sg:phone":"+49 234/280077",
    "sg:postcode":"44892",
    "sg:province":"Nordrhein-Westfalen",
    "wof:name":"Ritter Apparatebau Gmbh",
    "wof:placetype":"venue"
},
  "geometry": {"coordinates":[7.2986,51.477596],"type":"Point"}
}