{
  "type": "Feature",
  "properties": {
    "iso:country":"DE",
    "sg:address":"Pellergasse 11",
    "sg:city":"N\u00fcrnberg",
    "sg:phone":"+49 911/831280",
    "sg:postcode":"90475",
    "sg:province":"Bayern",
    "wof:name":"Horst Kr\u00fcger",
    "wof:placetype":"venue"
},
  "geometry": {"coordinates":[11.192259,49.422256],"type":"Point"}
}