{
  "type": "Feature",
  "properties": {
    "iso:country":"DE",
    "sg:address":"F\u00fcrth am Berg",
    "sg:city":"Neustadt",
    "sg:phone":"+49 9568/7871",
    "sg:postcode":"96465",
    "sg:province":"Bayern",
    "wof:name":"Gorlecht",
    "wof:placetype":"venue"
},
  "geometry": {"coordinates":[11.1600704193,50.2780990601],"type":"Point"}
}