{
  "type": "Feature",
  "properties": {
    "iso:country":"DE",
    "sg:address":"Feldweg 23",
    "sg:city":"Coesfeld",
    "sg:phone":"+49 2541/3254",
    "sg:postcode":"48653",
    "sg:province":"Nordrhein-Westfalen",
    "wof:name":"Karl Elkemann",
    "wof:placetype":"venue"
},
  "geometry": {"coordinates":[7.160181,51.950607],"type":"Point"}
}