{
  "type": "Feature",
  "properties": {
    "iso:country":"DE",
    "sg:address":"B\u00fcchsenschinken 30",
    "sg:city":"Reinbek",
    "sg:phone":"+49 4104/5364",
    "sg:postcode":"21465",
    "sg:province":"Schleswig-Holstein",
    "wof:name":"S & S Ingeniergesellschaft W. Und M. Schlichting Gmbh",
    "wof:placetype":"venue"
},
  "geometry": {"coordinates":[10.289978981,53.5607566833],"type":"Point"}
}