{
  "type": "Feature",
  "properties": {
    "iso:country":"DE",
    "sg:address":"Efeustr. 17-19",
    "sg:city":"Bad Segeberg",
    "sg:postcode":"23795",
    "sg:province":"Schleswig-Holstein",
    "wof:name":"European Event Und Medien-technik Gmbh",
    "wof:placetype":"venue"
},
  "geometry": {"coordinates":[10.3101272583,53.9266815186],"type":"Point"}
}