{
  "type": "Feature",
  "properties": {
    "iso:country":"DE",
    "sg:address":"Oberhafenstr. 1",
    "sg:city":"Hamburg",
    "sg:postcode":"20097",
    "sg:province":"Hamburg",
    "wof:name":"Euronut Gmbh",
    "wof:placetype":"venue"
},
  "geometry": {"coordinates":[10.0079069138,53.5459098816],"type":"Point"}
}