{
  "type": "Feature",
  "properties": {
    "iso:country":"DE",
    "sg:address":"Lohweg 16",
    "sg:city":"Hersbruck",
    "sg:phone":"+49 9151/72254",
    "sg:postcode":"91217",
    "sg:province":"Bayern",
    "wof:name":"Cb Unternehmensberatung Gmbh",
    "wof:placetype":"venue"
},
  "geometry": {"coordinates":[11.426651001,49.5079154968],"type":"Point"}
}