{
  "type": "Feature",
  "properties": {
    "iso:country":"DE",
    "sg:address":"Upstallstr 2a",
    "sg:city":"Brandenburg",
    "sg:phone":"+49 3381/522521",
    "sg:postcode":"14772",
    "sg:province":"Brandenburg",
    "wof:name":"Trend Werbung Bernd M\u00e4ttig",
    "wof:placetype":"venue"
},
  "geometry": {"coordinates":[12.5391530991,52.4305152893],"type":"Point"}
}