{
  "type": "Feature",
  "properties": {
    "iso:country":"DE",
    "sg:address":"Zeughausstr. 9",
    "sg:city":"K\u00f6ln",
    "sg:phone":"+49 221/2580833",
    "sg:postcode":"50667",
    "sg:province":"Nordrhein-Westfalen",
    "wof:name":"Einrichtungshaus W. May Kg",
    "wof:placetype":"venue"
},
  "geometry": {"coordinates":[6.946567,50.940853],"type":"Point"}
}