{
  "type": "Feature",
  "properties": {
    "iso:country":"DE",
    "sg:address":"Industriestr.",
    "sg:city":"R\u00fcdesheim",
    "sg:phone":"+49 671/31827",
    "sg:postcode":"55593",
    "sg:province":"Rheinland-Pfalz",
    "wof:name":"Erbes-beteiligungs Gmbh",
    "wof:placetype":"venue"
},
  "geometry": {"coordinates":[7.819693,49.848766],"type":"Point"}
}