{
  "type": "Feature",
  "properties": {
    "iso:country":"DE",
    "sg:address":"Am Maienb\u00fchl 2",
    "sg:city":"Inzlingen",
    "sg:phone":"+49 7621/89491",
    "sg:postcode":"79594",
    "sg:province":"Baden-W\u00fcrttemberg",
    "wof:name":"Kr Wohnbau Immobilien",
    "wof:placetype":"venue"
},
  "geometry": {"coordinates":[7.6819,47.588547],"type":"Point"}
}