{
  "type": "Feature",
  "properties": {
    "iso:country":"DE",
    "sg:address":"Musterbahn 19",
    "sg:city":"L\u00fcbeck",
    "sg:postcode":"23552",
    "sg:province":"Schleswig-Holstein",
    "wof:name":"Khk Handelskontor Gmbh",
    "wof:placetype":"venue"
},
  "geometry": {"coordinates":[10.685742,53.86002],"type":"Point"}
}