{
  "type": "Feature",
  "properties": {
    "iso:country":"DE",
    "sg:address":"Coerder Liekweg 76 b",
    "sg:city":"M\u00fcnster",
    "sg:phone":"+49 251/249977",
    "sg:postcode":"48157",
    "sg:province":"Nordrhein-Westfalen",
    "wof:name":"Reiling-ms-recycling- Gmbh",
    "wof:placetype":"venue"
},
  "geometry": {"coordinates":[7.6393198967,52.0087203979],"type":"Point"}
}