{
  "type": "Feature",
  "properties": {
    "iso:country":"DE",
    "sg:address":"Klosterstr. 12",
    "sg:city":"Nettersheim",
    "sg:phone":"+49 2486/95050",
    "sg:postcode":"53947",
    "sg:province":"Nordrhein-Westfalen",
    "wof:name":"Altenheim Haus Tannenblick",
    "wof:placetype":"venue"
},
  "geometry": {"coordinates":[6.635033,50.495251],"type":"Point"}
}