{
  "type": "Feature",
  "properties": {
    "iso:country":"DE",
    "sg:address":"Filderhauptstr. 43",
    "sg:city":"Stuttgart",
    "sg:phone":"+49 711/4567422",
    "sg:postcode":"70599",
    "sg:province":"Baden-W\u00fcrttemberg",
    "wof:name":"Atelier Ariane",
    "wof:placetype":"venue"
},
  "geometry": {"coordinates":[9.1799850464,48.7216300964],"type":"Point"}
}