{
  "type": "Feature",
  "properties": {
    "iso:country":"DE",
    "sg:address":"Bruckenackerhof 2",
    "sg:city":"Filderstadt",
    "sg:phone":"+49 711/702864",
    "sg:postcode":"70794",
    "sg:province":"Baden-W\u00fcrttemberg",
    "wof:name":"Briem Feldgem\u00fcse Gmbh",
    "wof:placetype":"venue"
},
  "geometry": {"coordinates":[9.224945,48.68409],"type":"Point"}
}