{
  "type": "Feature",
  "properties": {
    "iso:country":"DE",
    "sg:address":"Schillerstr. 1",
    "sg:city":"Weiden",
    "sg:phone":"+49 961/32029",
    "sg:postcode":"92637",
    "sg:province":"Bayern",
    "wof:name":"Bayerische Beamten Lebensversicherung Ag",
    "wof:placetype":"venue"
},
  "geometry": {"coordinates":[12.1580791473,49.6771736145],"type":"Point"}
}