{
  "type": "Feature",
  "properties": {
    "iso:country":"DE",
    "sg:address":"Hedelfinger Str. 47",
    "sg:city":"Stuttgart",
    "sg:phone":"+49 711/4090901",
    "sg:postcode":"70327",
    "sg:province":"Baden-W\u00fcrttemberg",
    "wof:name":"Marie-luise Gaukler",
    "wof:placetype":"venue"
},
  "geometry": {"coordinates":[9.248249054,48.7683677673],"type":"Point"}
}