{
  "type": "Feature",
  "properties": {
    "iso:country":"DE",
    "sg:address":"Breite Stra\u00dfe 55",
    "sg:city":"L\u00fcbeck",
    "sg:phone":"+49 451/74547",
    "sg:postcode":"23552",
    "sg:province":"Schleswig-Holstein",
    "wof:name":"Kalevala Schmuck",
    "wof:placetype":"venue"
},
  "geometry": {"coordinates":[10.6866188049,53.8682594299],"type":"Point"}
}