{
  "type": "Feature",
  "properties": {
    "iso:country":"DE",
    "sg:address":"K\u00f6nigstr. 78",
    "sg:city":"Duisburg",
    "sg:phone":"+49 203/21438",
    "sg:postcode":"47051",
    "sg:province":"Nordrhein-Westfalen",
    "wof:name":"Restaurant G. Heinrichs",
    "wof:placetype":"venue"
},
  "geometry": {"coordinates":[6.7725701332,51.4319839478],"type":"Point"}
}