{
  "type": "Feature",
  "properties": {
    "iso:country":"DE",
    "sg:address":"Hofstr. 50b",
    "sg:city":"M\u00fcnster",
    "sg:phone":"+49 2506/85432",
    "sg:postcode":"48167",
    "sg:province":"Nordrhein-Westfalen",
    "wof:name":"Johannes Hellmann",
    "wof:placetype":"venue"
},
  "geometry": {"coordinates":[7.733321,51.916538],"type":"Point"}
}