{
  "type": "Feature",
  "properties": {
    "iso:country":"DE",
    "sg:address":"Marlowring 21",
    "sg:city":"Hamburg",
    "sg:phone":"+49 40/8515080",
    "sg:postcode":"22525",
    "sg:province":"Hamburg",
    "wof:name":"Thermo- Trans Internationale Spedition Gmbh",
    "wof:placetype":"venue"
},
  "geometry": {"coordinates":[9.9274930954,53.5729904175],"type":"Point"}
}