{
  "type": "Feature",
  "properties": {
    "iso:country":"DE",
    "sg:address":"Neue Str. 27",
    "sg:city":"Brakel",
    "sg:phone":"+49 5272/601232",
    "sg:postcode":"33034",
    "sg:province":"Nordrhein-Westfalen",
    "wof:name":"Beta Plast Thomas Sagel",
    "wof:placetype":"venue"
},
  "geometry": {"coordinates":[9.180223,51.715378],"type":"Point"}
}