{
  "type": "Feature",
  "properties": {
    "iso:country":"DE",
    "sg:address":"Untersachsen 15",
    "sg:city":"Diespeck",
    "sg:phone":"+49 9161/3805",
    "sg:postcode":"91456",
    "sg:province":"Bayern",
    "wof:name":"Bj\u00f6rn Lehnert Architekt",
    "wof:placetype":"venue"
},
  "geometry": {"coordinates":[10.657231,49.583885],"type":"Point"}
}