{
  "type": "Feature",
  "properties": {
    "iso:country":"DE",
    "sg:address":"Am Brennh\u00e4usle 4",
    "sg:city":"Hardheim",
    "sg:phone":"+49 6283/22340",
    "sg:postcode":"74736",
    "sg:province":"Baden-W\u00fcrttemberg",
    "wof:name":"Albrecht Herbst",
    "wof:placetype":"venue"
},
  "geometry": {"coordinates":[9.478727,49.611382],"type":"Point"}
}