{
  "type": "Feature",
  "properties": {
    "iso:country":"DE",
    "sg:address":"P\u00f6lbitzer Str. 20",
    "sg:city":"Zwickau",
    "sg:phone":"+49 375/3531494",
    "sg:postcode":"08058",
    "sg:province":"Sachsen",
    "wof:name":"Sd Gmbh",
    "wof:placetype":"venue"
},
  "geometry": {"coordinates":[12.488627,50.737904],"type":"Point"}
}