{
  "type": "Feature",
  "properties": {
    "iso:country":"DE",
    "sg:address":"Rabensteinstr. 14",
    "sg:city":"Siegsdorf",
    "sg:phone":"+49 8662/9387",
    "sg:postcode":"83313",
    "sg:province":"Bayern",
    "wof:name":"Oskar Poss",
    "wof:placetype":"venue"
},
  "geometry": {"coordinates":[12.6415996552,47.7928886414],"type":"Point"}
}