{
  "type": "Feature",
  "properties": {
    "iso:country":"DE",
    "sg:address":"Bachstr. 10",
    "sg:city":"Berg-Weiler",
    "sg:phone":"+49 4975/0294070",
    "sg:postcode":"88276",
    "sg:province":"Baden-W\u00fcrttemberg",
    "wof:name":"Weerth-handling Systeme Gmbh",
    "wof:placetype":"venue"
},
  "geometry": {"coordinates":[9.595434,47.814533],"type":"Point"}
}