{
  "type": "Feature",
  "properties": {
    "iso:country":"DE",
    "sg:address":"Unterfeldstr. 34",
    "sg:city":"Karlsruhe",
    "sg:phone":"+49 721/706738",
    "sg:postcode":"76149",
    "sg:province":"Baden-W\u00fcrttemberg",
    "wof:name":"Wolfgang Nagel",
    "wof:placetype":"venue"
},
  "geometry": {"coordinates":[8.383539,49.049522],"type":"Point"}
}