{
  "type": "Feature",
  "properties": {
    "iso:country":"DE",
    "sg:address":"Sunderlandstr. 1",
    "sg:city":"Essen",
    "sg:phone":"+49 201/283939",
    "sg:postcode":"45138",
    "sg:province":"Nordrhein-Westfalen",
    "wof:name":"Johann Brandl",
    "wof:placetype":"venue"
},
  "geometry": {"coordinates":[7.056344,51.448017],"type":"Point"}
}