{
  "type": "Feature",
  "properties": {
    "iso:country":"DE",
    "sg:address":"Arnoldshainer Str. 16 a",
    "sg:city":"Frankfurt",
    "sg:phone":"+49 69/780955",
    "sg:postcode":"60489",
    "sg:province":"Hessen",
    "wof:name":"Hotel Aurelia",
    "wof:placetype":"venue"
},
  "geometry": {"coordinates":[8.6073627472,50.1271133423],"type":"Point"}
}