{
  "type": "Feature",
  "properties": {
    "iso:country":"DE",
    "sg:address":"Lerchenstr. 1a",
    "sg:city":"Heusenstamm",
    "sg:phone":"+49 6104/3052",
    "sg:postcode":"63150",
    "sg:province":"Hessen",
    "wof:name":"Viola B\u00e4ckerei Konditorei Gmbh",
    "wof:placetype":"venue"
},
  "geometry": {"coordinates":[8.783553,50.059895],"type":"Point"}
}