{
  "type": "Feature",
  "properties": {
    "iso:country":"DE",
    "sg:address":"Th\u00fcngersheimer Str. 57",
    "sg:city":"G\u00fcntersleben",
    "sg:phone":"+49 9365/9284",
    "sg:postcode":"97261",
    "sg:province":"Bayern",
    "wof:name":"Kurt \u00d6hrlein",
    "wof:placetype":"venue"
},
  "geometry": {"coordinates":[9.898834,49.87151],"type":"Point"}
}