{
  "type": "Feature",
  "properties": {
    "iso:country":"DE",
    "sg:address":"Heinrich-Feurstein-Str 10",
    "sg:city":"Donaueschingen",
    "sg:phone":"+49 771/13500",
    "sg:postcode":"78166",
    "sg:province":"Baden-W\u00fcrttemberg",
    "wof:name":"Richard Romeyko Rechtsanwalt",
    "wof:placetype":"venue"
},
  "geometry": {"coordinates":[8.5028533936,47.9539680481],"type":"Point"}
}