{
  "type": "Feature",
  "properties": {
    "iso:country":"DE",
    "sg:address":"Gneisenaustr. 109",
    "sg:city":"Berlin",
    "sg:phone":"+49 30/6151354",
    "sg:postcode":"10961",
    "sg:province":"Berlin",
    "wof:name":"Ortwin Rau",
    "wof:placetype":"venue"
},
  "geometry": {"coordinates":[13.389623642,52.4928398132],"type":"Point"}
}