{
  "type": "Feature",
  "properties": {
    "iso:country":"DE",
    "sg:address":"Kiefholzstr. 13",
    "sg:city":"Haldensleben",
    "sg:postcode":"39340",
    "sg:province":"Sachsen-Anhalt",
    "wof:name":"Dr. Med. Gisela Kondrasjuk",
    "wof:placetype":"venue"
},
  "geometry": {"coordinates":[11.37176,52.284801],"type":"Point"}
}