{
  "type": "Feature",
  "properties": {
    "iso:country":"DE",
    "sg:address":"Kirchstr. 3",
    "sg:city":"Essen",
    "sg:postcode":"45289",
    "sg:province":"Nordrhein-Westfalen",
    "wof:name":"Ingenieurb\u00fcro Wagner Gmbh",
    "wof:placetype":"venue"
},
  "geometry": {"coordinates":[7.1142148972,51.4147071838],"type":"Point"}
}