{
  "type": "Feature",
  "properties": {
    "iso:country":"DE",
    "sg:address":"Lyoner Str. 26",
    "sg:city":"Frankfurt",
    "sg:phone":"+49 69/66040",
    "sg:postcode":"60528",
    "sg:province":"Hessen",
    "wof:name":"Ims Institut F\u00fcr Medizinische Statistik",
    "wof:placetype":"venue"
},
  "geometry": {"coordinates":[8.6237478256,50.080821991],"type":"Point"}
}