{
  "type": "Feature",
  "properties": {
    "iso:country":"DE",
    "sg:address":"Friedrich-Bergius-Str 7",
    "sg:city":"Grevenbroich",
    "sg:phone":"+49 2181/270670",
    "sg:postcode":"41516",
    "sg:province":"Nordrhein-Westfalen",
    "wof:name":"Siwan Datennetze Und Internet-dienste Gmbh & Co Kg",
    "wof:placetype":"venue"
},
  "geometry": {"coordinates":[6.632681,51.110199],"type":"Point"}
}