{
  "type": "Feature",
  "properties": {
    "iso:country":"DE",
    "sg:address":"Markgrafenstr. 27",
    "sg:city":"Bad Alexandersbad",
    "sg:phone":"+49 9232/700334",
    "sg:postcode":"95680",
    "sg:province":"Bayern",
    "wof:name":"Mtn Medizinisch - Technischer Notdienst A. G\u00fcnther E. K.",
    "wof:placetype":"venue"
},
  "geometry": {"coordinates":[12.017279,50.017708],"type":"Point"}
}