{
  "type": "Feature",
  "properties": {
    "iso:country":"DE",
    "sg:address":"Lindenallee 3",
    "sg:city":"Delitzsch",
    "sg:postcode":"04509",
    "sg:province":"Sachsen",
    "wof:name":"G.m.u. Unternehmensberatung F. Den Mittelstand Beteil. Gmbh",
    "wof:placetype":"venue"
},
  "geometry": {"coordinates":[12.3399715424,51.5257034302],"type":"Point"}
}