{
  "type": "Feature",
  "properties": {
    "iso:country":"DE",
    "sg:address":"Marktstr. 12 a",
    "sg:city":"Neustadt",
    "sg:phone":"+49 5032/65249",
    "sg:postcode":"31535",
    "sg:province":"Niedersachsen",
    "wof:name":"Amadeus - Renate Werner Und Frank Brandst\u00e4dter Ohg",
    "wof:placetype":"venue"
},
  "geometry": {"coordinates":[9.034851,49.817154],"type":"Point"}
}