{
  "type": "Feature",
  "properties": {
    "iso:country":"DE",
    "sg:address":"Tannenberg 91",
    "sg:city":"Burggen",
    "sg:phone":"+49 8860/294",
    "sg:postcode":"86977",
    "sg:province":"Bayern",
    "wof:name":"Bair Baggerbetrieb Und Fuhrunternehmen Gmbh",
    "wof:placetype":"venue"
},
  "geometry": {"coordinates":[10.783406,47.781937],"type":"Point"}
}