{
  "type": "Feature",
  "properties": {
    "iso:country":"DE",
    "sg:address":"H\u00fcttenstr. 10",
    "sg:city":"Wiesbaden",
    "sg:phone":"+49 611/27000",
    "sg:postcode":"65201",
    "sg:province":"Hessen",
    "wof:name":"Saint-gobain Quartz Gmbh",
    "wof:placetype":"venue"
},
  "geometry": {"coordinates":[8.2094841003,50.0494384766],"type":"Point"}
}