{
  "type": "Feature",
  "properties": {
    "iso:country":"DE",
    "sg:address":"\u00dcderseestr. 4",
    "sg:city":"Berlin",
    "sg:phone":"+49 30/5098154",
    "sg:postcode":"10318",
    "sg:province":"Berlin",
    "wof:name":"Hans-j\u00fcrgen M\u00f6hle Ingenieur",
    "wof:placetype":"venue"
},
  "geometry": {"coordinates":[13.5191612244,52.4824104309],"type":"Point"}
}