{
  "type": "Feature",
  "properties": {
    "iso:country":"DE",
    "sg:address":"Klingenbergplatz 1",
    "sg:city":"Oldenburg",
    "sg:phone":"+49 4944/14010",
    "sg:postcode":"26133",
    "sg:province":"Niedersachsen",
    "wof:name":"Fhp Mortors Gmbh",
    "wof:placetype":"venue"
},
  "geometry": {"coordinates":[8.209708,53.10907],"type":"Point"}
}