{
  "type": "Feature",
  "properties": {
    "iso:country":"DE",
    "sg:address":"Siegmund-Hiepe-Str. 35",
    "sg:city":"Wetzlar",
    "sg:phone":"+49 6441/23032",
    "sg:postcode":"35578",
    "sg:province":"Hessen",
    "wof:name":"Hermann Fritz Sanit\u00e4r- Fachhandel Gmbh & Co. Kg",
    "wof:placetype":"venue"
},
  "geometry": {"coordinates":[8.4746580124,50.5514831543],"type":"Point"}
}