{
  "type": "Feature",
  "properties": {
    "iso:country":"DE",
    "sg:address":"Hauptstr. 46",
    "sg:city":"Schwelm",
    "sg:phone":"+49 2336/830167",
    "sg:postcode":"58332",
    "sg:province":"Nordrhein-Westfalen",
    "wof:name":"Vanity Modevertrieb Gmbh & Co.",
    "wof:placetype":"venue"
},
  "geometry": {"coordinates":[7.293333,51.284229],"type":"Point"}
}