{
  "type": "Feature",
  "properties": {
    "iso:country":"DE",
    "sg:address":"Wiesenredder 10",
    "sg:city":"B\u00f6neb\u00fcttel",
    "sg:phone":"+49 4321/29933",
    "sg:postcode":"24620",
    "sg:province":"Schleswig-Holstein",
    "wof:name":"Bsb Baukontor Gmbh",
    "wof:placetype":"venue"
},
  "geometry": {"coordinates":[10.04017,54.068981],"type":"Point"}
}