{
  "type": "Feature",
  "properties": {
    "iso:country":"DE",
    "sg:address":"Am Sonnenhang 5",
    "sg:city":"Wiesbaden",
    "sg:phone":"+49 611/541139",
    "sg:postcode":"65207",
    "sg:province":"Hessen",
    "wof:name":"Stan Glogow Gala Band",
    "wof:placetype":"venue"
},
  "geometry": {"coordinates":[8.2726354599,50.1178359985],"type":"Point"}
}