{
  "type": "Feature",
  "properties": {
    "iso:country":"DE",
    "sg:address":"Altenhof 14",
    "sg:city":"Ebersburg",
    "sg:postcode":"36157",
    "sg:province":"Hessen",
    "wof:name":"Www.fairfinanz24.de Mehr Als Finanzen!",
    "wof:placetype":"venue"
},
  "geometry": {"coordinates":[9.767616,50.429989],"type":"Point"}
}