{
  "type": "Feature",
  "properties": {
    "iso:country":"DE",
    "sg:address":"Bahnhofstr. 17",
    "sg:city":"L\u00fctjensee",
    "sg:phone":"+49 4534/450",
    "sg:postcode":"22952",
    "sg:province":"Schleswig-Holstein",
    "wof:name":"Klaus Hamann",
    "wof:placetype":"venue"
},
  "geometry": {"coordinates":[10.385631,53.665451],"type":"Point"}
}