{
  "type": "Feature",
  "properties": {
    "iso:country":"DE",
    "sg:address":"Katharinenstr. 8",
    "sg:city":"Lichtenau",
    "sg:phone":"+49 7227/768",
    "sg:postcode":"77839",
    "sg:province":"Baden-W\u00fcrttemberg",
    "wof:name":"Ebla Gmbh",
    "wof:placetype":"venue"
},
  "geometry": {"coordinates":[8.0050382614,48.7284545898],"type":"Point"}
}