{
  "type": "Feature",
  "properties": {
    "iso:country":"DE",
    "sg:address":"Schlehenweg 42",
    "sg:city":"Henstedt-Ulzburg",
    "sg:phone":"+49 4193/968181",
    "sg:postcode":"24558",
    "sg:province":"Schleswig-Holstein",
    "wof:name":"Dieter Winter",
    "wof:placetype":"venue"
},
  "geometry": {"coordinates":[9.983795166,53.7796516418],"type":"Point"}
}