{
  "type": "Feature",
  "properties": {
    "iso:country":"DE",
    "sg:address":"Neckarstr. 25",
    "sg:city":"Obertshausen",
    "sg:phone":"+49 6104/799720",
    "sg:postcode":"63179",
    "sg:province":"Hessen",
    "wof:name":"Nf Friedrich & Partner Versicherungs-makler Gmbh",
    "wof:placetype":"venue"
},
  "geometry": {"coordinates":[8.867436409,50.0718803406],"type":"Point"}
}