{
  "type": "Feature",
  "properties": {
    "iso:country":"DE",
    "sg:address":"Marienthaler Str. 145",
    "sg:city":"Hamburg",
    "sg:postcode":"20535",
    "sg:province":"Hamburg",
    "wof:name":"Eurospar",
    "wof:placetype":"venue"
},
  "geometry": {"coordinates":[10.0559015274,53.5640716553],"type":"Point"}
}