{
  "type": "Feature",
  "properties": {
    "iso:country":"DE",
    "sg:address":"L\u00f6wenberger Str. 50",
    "sg:city":"N\u00fcrnberg",
    "sg:phone":"+49 911/8370214",
    "sg:postcode":"90475",
    "sg:province":"Bayern",
    "wof:name":"Comet",
    "wof:placetype":"venue"
},
  "geometry": {"coordinates":[11.1730012894,49.4120788574],"type":"Point"}
}