{
  "type": "Feature",
  "properties": {
    "iso:country":"DE",
    "sg:address":"Langer Weg 10",
    "sg:city":"Zimmern",
    "sg:phone":"+49 7403/7613",
    "sg:postcode":"78658",
    "sg:province":"Baden-W\u00fcrttemberg",
    "wof:name":"Gerhard Storz",
    "wof:placetype":"venue"
},
  "geometry": {"coordinates":[8.528279,48.164818],"type":"Point"}
}