{
  "type": "Feature",
  "properties": {
    "iso:country":"DE",
    "sg:address":"Dobsch\u00fctzstr. 29 k",
    "sg:city":"Lutherstadt Wittenberg",
    "sg:phone":"+49 3491/611086",
    "sg:postcode":"06886",
    "sg:province":"Sachsen-Anhalt",
    "wof:name":"Enatec Elektroanlagenbau Gmbh",
    "wof:placetype":"venue"
},
  "geometry": {"coordinates":[12.63187,51.878578],"type":"Point"}
}