{
  "type": "Feature",
  "properties": {
    "iso:country":"DE",
    "sg:address":"Eddesser Str. 3",
    "sg:city":"Uetze",
    "sg:phone":"+49 5173/1296",
    "sg:postcode":"31311",
    "sg:province":"Niedersachsen",
    "wof:name":"Gerhard Schaper",
    "wof:placetype":"venue"
},
  "geometry": {"coordinates":[10.226486,52.431694],"type":"Point"}
}