{
  "type": "Feature",
  "properties": {
    "iso:country":"DE",
    "sg:address":"M\u00fchlenstr. 17",
    "sg:city":"Hofgeismar",
    "sg:phone":"+49 5671/6799",
    "sg:postcode":"34369",
    "sg:province":"Hessen",
    "wof:name":"Bhw Bausparkasse Ag",
    "wof:placetype":"venue"
},
  "geometry": {"coordinates":[9.38567,51.492626],"type":"Point"}
}