{
  "type": "Feature",
  "properties": {
    "iso:country":"DE",
    "sg:address":"Parkstr. 16",
    "sg:city":"B\u00f6blingen",
    "sg:phone":"+49 7031/24986",
    "sg:postcode":"71034",
    "sg:province":"Baden-W\u00fcrttemberg",
    "wof:name":"Dieter Stobisnki Schilder Und Lichtreklame",
    "wof:placetype":"venue"
},
  "geometry": {"coordinates":[9.009888,48.68259],"type":"Point"}
}