{
  "type": "Feature",
  "properties": {
    "iso:country":"DE",
    "sg:address":"Theodor-Heuss-Str. 1",
    "sg:city":"Neu-Isenburg",
    "sg:phone":"+49 6102/25708",
    "sg:postcode":"63263",
    "sg:province":"Hessen",
    "wof:name":"Erwin Wehrheim",
    "wof:placetype":"venue"
},
  "geometry": {"coordinates":[8.669855,50.055096],"type":"Point"}
}