{
  "type": "Feature",
  "properties": {
    "iso:country":"DE",
    "sg:address":"Am \u00d6lberg 50",
    "sg:city":"Holdorf",
    "sg:phone":"+49 5494/1518",
    "sg:postcode":"49451",
    "sg:province":"Niedersachsen",
    "wof:name":"Tennis-center Heidesee",
    "wof:placetype":"venue"
},
  "geometry": {"coordinates":[8.1154003143,52.5796394348],"type":"Point"}
}