{
  "type": "Feature",
  "properties": {
    "iso:country":"DE",
    "sg:address":"Am Handelshof 2",
    "sg:city":"W\u00fcrzburg",
    "sg:phone":"+49 931/27925",
    "sg:postcode":"97076",
    "sg:province":"Bayern",
    "wof:name":"Media Markt Tv-hifi-elektro Gmbh",
    "wof:placetype":"venue"
},
  "geometry": {"coordinates":[9.9804296494,49.8151931763],"type":"Point"}
}