{
  "type": "Feature",
  "properties": {
    "iso:country":"DE",
    "sg:address":"Wittgensteinstr. 29 a",
    "sg:city":"K\u00f6ln",
    "sg:phone":"+49 221/9402583",
    "sg:postcode":"50931",
    "sg:province":"Nordrhein-Westfalen",
    "wof:name":"Service-center S. Froitzheim Gmbh",
    "wof:placetype":"venue"
},
  "geometry": {"coordinates":[6.9121541977,50.928478241],"type":"Point"}
}