{
  "type": "Feature",
  "properties": {
    "iso:country":"DE",
    "sg:address":"Zum Stadtbad 32",
    "sg:city":"Langenfeld",
    "sg:phone":"+49 2173/76986",
    "sg:postcode":"40764",
    "sg:province":"Nordrhein-Westfalen",
    "wof:name":"Redaktion Di\u00e4t Und Informationen",
    "wof:placetype":"venue"
},
  "geometry": {"coordinates":[6.9401960373,51.1173400879],"type":"Point"}
}