{
  "type": "Feature",
  "properties": {
    "iso:country":"DE",
    "sg:address":"Bahnhofstr. 45",
    "sg:city":"S\u00f6rup",
    "sg:phone":"+49 4635/1648",
    "sg:postcode":"24966",
    "sg:province":"Schleswig-Holstein",
    "wof:name":"Sh-zert Zwertifizierung Und Umweltguta. Partnerschaftsges.",
    "wof:placetype":"venue"
},
  "geometry": {"coordinates":[9.677025795,54.7194442749],"type":"Point"}
}