{
  "type": "Feature",
  "properties": {
    "iso:country":"DE",
    "sg:address":"Im Meienthun 15",
    "sg:city":"Hamburg",
    "sg:phone":"+49 40/6035457",
    "sg:postcode":"22359",
    "sg:province":"Hamburg",
    "wof:name":"Redaktion Musiker Studio Report",
    "wof:placetype":"venue"
},
  "geometry": {"coordinates":[10.1908569336,53.6429710388],"type":"Point"}
}