{
  "type": "Feature",
  "properties": {
    "iso:country":"DE",
    "sg:address":"Scharnhorststr. 7",
    "sg:city":"D\u00fcsseldorf",
    "sg:phone":"+49 211/776979",
    "sg:postcode":"40477",
    "sg:province":"Nordrhein-Westfalen",
    "wof:name":"C. P. R. Copy-print Und Retusche Gmbh",
    "wof:placetype":"venue"
},
  "geometry": {"coordinates":[6.78491,51.241894],"type":"Point"}
}