{
  "type": "Feature",
  "properties": {
    "iso:country":"DE",
    "sg:address":"Stra\u00dfe des Friedens 7",
    "sg:city":"Leinefelde",
    "sg:postcode":"37327",
    "sg:province":"Th\u00fcringen",
    "wof:name":"Kinderbibliothek",
    "wof:placetype":"venue"
},
  "geometry": {"coordinates":[10.322152,51.387672],"type":"Point"}
}