{
  "type": "Feature",
  "properties": {
    "iso:country":"DE",
    "sg:address":"Chiemseestr. 3",
    "sg:city":"Reit im Winkl",
    "sg:phone":"+49 8640/98850",
    "sg:postcode":"83242",
    "sg:province":"Bayern",
    "wof:name":"Pension Haus Pankratius",
    "wof:placetype":"venue"
},
  "geometry": {"coordinates":[12.4817304611,47.6763191223],"type":"Point"}
}