{
  "type": "Feature",
  "properties": {
    "iso:country":"DE",
    "sg:address":"H\u00e4lden 11",
    "sg:city":"Bretzfeld",
    "sg:phone":"+49 7946/418",
    "sg:postcode":"74626",
    "sg:province":"Baden-W\u00fcrttemberg",
    "wof:name":"Alten- Und Pflegeheim Mylius",
    "wof:placetype":"venue"
},
  "geometry": {"coordinates":[9.480811,49.154701],"type":"Point"}
}