{
  "type": "Feature",
  "properties": {
    "iso:country":"DE",
    "sg:address":"Hauptstr. 18",
    "sg:city":"Moorenweis",
    "sg:phone":"+49 8146/253",
    "sg:postcode":"82272",
    "sg:province":"Bayern",
    "wof:name":"Gastst\u00e4tte Georg Pfeil",
    "wof:placetype":"venue"
},
  "geometry": {"coordinates":[11.0862627029,48.1875343323],"type":"Point"}
}