{
  "type": "Feature",
  "properties": {
    "iso:country":"DE",
    "sg:address":"Alte Stroth 2",
    "sg:city":"Weitefeld",
    "sg:phone":"+49 2743/6165",
    "sg:postcode":"57586",
    "sg:province":"Rheinland-Pfalz",
    "wof:name":"Contrans Containertransporte Und-montagen Gmbh",
    "wof:placetype":"venue"
},
  "geometry": {"coordinates":[7.9335341454,50.7218170166],"type":"Point"}
}