{
  "type": "Feature",
  "properties": {
    "iso:country":"DE",
    "sg:address":"Servatiusstr. 71",
    "sg:city":"K\u00f6ln",
    "sg:postcode":"51109",
    "sg:province":"Nordrhein-Westfalen",
    "wof:name":"Ingo Bongartz Handelsvertreter F\u00fcr Chem.-techn. Produkte E.k.",
    "wof:placetype":"venue"
},
  "geometry": {"coordinates":[7.043451,50.937904],"type":"Point"}
}