{
  "type": "Feature",
  "properties": {
    "iso:country":"DE",
    "sg:address":"Lerchenweg 4",
    "sg:city":"Neukirchen",
    "sg:phone":"+49 6694/1510",
    "sg:postcode":"34626",
    "sg:province":"Hessen",
    "wof:name":"Heinz Hellbach",
    "wof:placetype":"venue"
},
  "geometry": {"coordinates":[9.3527421951,50.8640937805],"type":"Point"}
}