{
  "type": "Feature",
  "properties": {
    "iso:country":"DE",
    "sg:address":"Schmalgasse 9 a",
    "sg:city":"Hartheim",
    "sg:phone":"+49 7633/4433",
    "sg:postcode":"79258",
    "sg:province":"Baden-W\u00fcrttemberg",
    "wof:name":"Rampf Grundst\u00fccksver- Waltungs- Gmbh",
    "wof:placetype":"venue"
},
  "geometry": {"coordinates":[7.6241102219,47.9156417847],"type":"Point"}
}