{
  "type": "Feature",
  "properties": {
    "iso:country":"DE",
    "sg:address":"Bahnhofstr 19",
    "sg:city":"Langelsheim",
    "sg:phone":"+49 5326/85164",
    "sg:postcode":"38685",
    "sg:province":"Niedersachsen",
    "wof:name":"Galm Maschinenbau Dreh-fr\u00e4stechnik Gmbh",
    "wof:placetype":"venue"
},
  "geometry": {"coordinates":[10.339539,51.932819],"type":"Point"}
}