{
  "type": "Feature",
  "properties": {
    "iso:country":"DE",
    "sg:address":"Rimberger Str.",
    "sg:city":"Breitenbach",
    "sg:phone":"+49 6675/92020",
    "sg:postcode":"36287",
    "sg:province":"Hessen",
    "wof:name":"H. Sohl",
    "wof:placetype":"venue"
},
  "geometry": {"coordinates":[9.4757413864,50.7806167603],"type":"Point"}
}