{
  "type": "Feature",
  "properties": {
    "iso:country":"DE",
    "sg:address":"Boschweg 4",
    "sg:city":"Geislingen",
    "sg:phone":"+49 7433/15489",
    "sg:postcode":"72351",
    "sg:province":"Baden-W\u00fcrttemberg",
    "wof:name":"P. Schmid",
    "wof:placetype":"venue"
},
  "geometry": {"coordinates":[8.8099403381,48.2953910828],"type":"Point"}
}