{
  "type": "Feature",
  "properties": {
    "iso:country":"DE",
    "sg:address":"Mauerstr. 41",
    "sg:city":"D\u00fcsseldorf",
    "sg:postcode":"40476",
    "sg:province":"Nordrhein-Westfalen",
    "wof:name":"J\u00fcdische Nationalfonds E. V.",
    "wof:placetype":"venue"
},
  "geometry": {"coordinates":[6.778475,51.243134],"type":"Point"}
}