{
  "type": "Feature",
  "properties": {
    "iso:country":"DE",
    "sg:address":"Senator-B\u00f6mers-Str. 44-46",
    "sg:city":"Bremen",
    "sg:phone":"+49 421/5287810",
    "sg:postcode":"28197",
    "sg:province":"Bremen",
    "wof:name":"Forster Feinmechanik Gmbh",
    "wof:placetype":"venue"
},
  "geometry": {"coordinates":[8.754404,53.077293],"type":"Point"}
}