{
  "type": "Feature",
  "properties": {
    "iso:country":"DE",
    "sg:address":"Bahnhofstr. 21",
    "sg:city":"Harra",
    "sg:phone":"+49 36642/22273",
    "sg:postcode":"07366",
    "sg:province":"Th\u00fcringen",
    "wof:name":"Dr. Werner S\u00fc\u00dfenguth Tierarzt",
    "wof:placetype":"venue"
},
  "geometry": {"coordinates":[11.686784,50.417858],"type":"Point"}
}