{
  "type": "Feature",
  "properties": {
    "iso:country":"DE",
    "sg:address":"Kleinwiehe",
    "sg:city":"Lindewitt",
    "sg:phone":"+49 4604/581",
    "sg:postcode":"24969",
    "sg:province":"Schleswig-Holstein",
    "wof:name":"Hans-heinrich Green",
    "wof:placetype":"venue"
},
  "geometry": {"coordinates":[9.2194900513,54.7194900513],"type":"Point"}
}