{
  "type": "Feature",
  "properties": {
    "iso:country":"DE",
    "sg:address":"Heinrich-Maurer-Str. 10",
    "sg:city":"Emmendingen",
    "sg:postcode":"79312",
    "sg:province":"Baden-W\u00fcrttemberg",
    "wof:name":"Ursula Rossol",
    "wof:placetype":"venue"
},
  "geometry": {"coordinates":[7.861069,48.10516],"type":"Point"}
}