{
  "type": "Feature",
  "properties": {
    "iso:country":"DE",
    "sg:address":"Oststr. 5",
    "sg:city":"Schmallenberg",
    "sg:phone":"+49 4929/727991",
    "sg:postcode":"57392",
    "sg:province":"Nordrhein-Westfalen",
    "wof:name":"Falke Kg",
    "wof:placetype":"venue"
},
  "geometry": {"coordinates":[8.284336,51.151909],"type":"Point"}
}