{
  "type": "Feature",
  "properties": {
    "iso:country":"DE",
    "sg:address":"Industriestr. 10",
    "sg:city":"Emmerich",
    "sg:phone":"+49 4928/22740",
    "sg:postcode":"46446",
    "sg:province":"Nordrhein-Westfalen",
    "wof:name":"Akzo Nobel Chemicals Gmbh",
    "wof:placetype":"venue"
},
  "geometry": {"coordinates":[6.2573652267,51.8314208984],"type":"Point"}
}