{
  "type": "Feature",
  "properties": {
    "iso:country":"DE",
    "sg:address":"Auf dem Dieke 12",
    "sg:city":"Essen",
    "sg:phone":"+49 5434/1042",
    "sg:postcode":"49632",
    "sg:province":"Niedersachsen",
    "wof:name":"Hugo Macke",
    "wof:placetype":"venue"
},
  "geometry": {"coordinates":[8.001573,52.717636],"type":"Point"}
}