{
  "type": "Feature",
  "properties": {
    "iso:country":"DE",
    "sg:address":"Flughafenstr. 50",
    "sg:city":"Dortmund",
    "sg:phone":"+49 231/255880",
    "sg:postcode":"44309",
    "sg:province":"Nordrhein-Westfalen",
    "wof:name":"Katholisches Pfarramt St. Clemens",
    "wof:placetype":"venue"
},
  "geometry": {"coordinates":[7.5390629768,51.5388679504],"type":"Point"}
}