{
  "type": "Feature",
  "properties": {
    "iso:country":"DE",
    "sg:address":"Bismarckplatz 8",
    "sg:city":"Landshut",
    "sg:phone":"+49 871/89292",
    "sg:postcode":"84034",
    "sg:province":"Bayern",
    "wof:name":"Pizza-stube",
    "wof:placetype":"venue"
},
  "geometry": {"coordinates":[12.1490573883,48.541633606],"type":"Point"}
}