{
  "type": "Feature",
  "properties": {
    "iso:country":"DE",
    "sg:address":"Untere Marktstr. 4",
    "sg:city":"Ludwigsburg",
    "sg:phone":"+49 7141/904709",
    "sg:postcode":"71634",
    "sg:province":"Baden-W\u00fcrttemberg",
    "wof:name":"Roy Fischer",
    "wof:placetype":"venue"
},
  "geometry": {"coordinates":[9.19166,48.898197],"type":"Point"}
}