{
  "type": "Feature",
  "properties": {
    "iso:country":"DE",
    "sg:address":"Marienstr. 11",
    "sg:city":"Wesel",
    "sg:postcode":"46487",
    "sg:province":"Nordrhein-Westfalen",
    "wof:name":"Janssen Brennstoffe Inh. Peter Christians E. K.",
    "wof:placetype":"venue"
},
  "geometry": {"coordinates":[6.54182,51.641983],"type":"Point"}
}