{
  "type": "Feature",
  "properties": {
    "iso:country":"DE",
    "sg:address":"Grebbener Str. 16b",
    "sg:city":"Heinsberg",
    "sg:phone":"+49 2452/64407",
    "sg:postcode":"52525",
    "sg:province":"Nordrhein-Westfalen",
    "wof:name":"Reise-shop Sk Gmbh",
    "wof:placetype":"venue"
},
  "geometry": {"coordinates":[6.1367588043,51.053817749],"type":"Point"}
}