{
  "type": "Feature",
  "properties": {
    "iso:country":"DE",
    "sg:address":"Mindelheimer Str. 8",
    "sg:city":"Bad W\u00f6rishofen",
    "sg:phone":"+49 8247/2497",
    "sg:postcode":"86825",
    "sg:province":"Bayern",
    "wof:name":"Cafe Hamburg",
    "wof:placetype":"venue"
},
  "geometry": {"coordinates":[10.586675,48.006378],"type":"Point"}
}