{
  "type": "Feature",
  "properties": {
    "iso:country":"DE",
    "sg:address":"Oststr. 51",
    "sg:city":"Gotha",
    "sg:phone":"+49 3621/403734",
    "sg:postcode":"99867",
    "sg:province":"Th\u00fcringen",
    "wof:name":"H\u00e4usliche Kranken- Und Seniorenpflege Gmbh",
    "wof:placetype":"venue"
},
  "geometry": {"coordinates":[10.714825,50.952793],"type":"Point"}
}