{
  "type": "Feature",
  "properties": {
    "iso:country":"DE",
    "sg:address":"Parkstr. 1",
    "sg:city":"Stendal",
    "sg:postcode":"39576",
    "sg:province":"Sachsen-Anhalt",
    "wof:name":"Viehmann Verwaltungsgesellschaft Mbh",
    "wof:placetype":"venue"
},
  "geometry": {"coordinates":[11.8622016907,52.6059608459],"type":"Point"}
}