{
  "type": "Feature",
  "properties": {
    "iso:country":"DE",
    "sg:address":"Stadionweg 14",
    "sg:city":"Aalen",
    "sg:phone":"+49 7361/42545",
    "sg:postcode":"73430",
    "sg:province":"Baden-W\u00fcrttemberg",
    "wof:name":"Vereinsgastst\u00e4tte Ssv Aalen E. V.",
    "wof:placetype":"venue"
},
  "geometry": {"coordinates":[10.0754299164,48.843421936],"type":"Point"}
}