{
  "type": "Feature",
  "properties": {
    "iso:country":"DE",
    "sg:address":"Uferstr. 22",
    "sg:city":"Gingen",
    "sg:phone":"+49 7162/939833",
    "sg:postcode":"73333",
    "sg:province":"Baden-W\u00fcrttemberg",
    "wof:name":"Angelika M\u00fchlh\u00e4user Masseurin",
    "wof:placetype":"venue"
},
  "geometry": {"coordinates":[9.781513,48.655926],"type":"Point"}
}