{
  "type": "Feature",
  "properties": {
    "iso:country":"DE",
    "sg:address":"H\u00fcthumer Str. 115",
    "sg:city":"Emmerich",
    "sg:phone":"+49 2822/3413",
    "sg:postcode":"46446",
    "sg:province":"Nordrhein-Westfalen",
    "wof:name":"Clemens L\u00f6rcks",
    "wof:placetype":"venue"
},
  "geometry": {"coordinates":[6.225475,51.85849],"type":"Point"}
}