{
  "type": "Feature",
  "properties": {
    "iso:country":"DE",
    "sg:address":"Irisweg 16",
    "sg:city":"N\u00fcrnberg",
    "sg:phone":"+49 911/345150",
    "sg:postcode":"90427",
    "sg:province":"Bayern",
    "wof:name":"Peter Kohl Industrievertretungen Gmbh",
    "wof:placetype":"venue"
},
  "geometry": {"coordinates":[11.0459442139,49.5201187134],"type":"Point"}
}