{
  "type": "Feature",
  "properties": {
    "iso:country":"DE",
    "sg:address":"Iburger Str. 226",
    "sg:city":"Osnabr\u00fcck",
    "sg:phone":"+49 541/951000",
    "sg:postcode":"49082",
    "sg:province":"Niedersachsen",
    "wof:name":"Beteiligungsges. Hans Disselkamp Mbh",
    "wof:placetype":"venue"
},
  "geometry": {"coordinates":[8.061572,52.246777],"type":"Point"}
}