{
  "type": "Feature",
  "properties": {
    "iso:country":"DE",
    "sg:address":"Heinrich-Nordhoff-Str. 59",
    "sg:city":"Wolfsburg",
    "sg:phone":"+49 5361/81410",
    "sg:postcode":"38440",
    "sg:province":"Niedersachsen",
    "wof:name":"Norbert Batzdorfer Steuerberater",
    "wof:placetype":"venue"
},
  "geometry": {"coordinates":[10.785615921,52.4278526306],"type":"Point"}
}