{
  "type": "Feature",
  "properties": {
    "iso:country":"DE",
    "sg:address":"Stettiner Str. 63",
    "sg:city":"G\u00f6ttingen",
    "sg:phone":"+49 551/703811",
    "sg:postcode":"37083",
    "sg:province":"Niedersachsen",
    "wof:name":"Schlemmer-grill",
    "wof:placetype":"venue"
},
  "geometry": {"coordinates":[9.9411802292,51.4902114868],"type":"Point"}
}