{
  "type": "Feature",
  "properties": {
    "iso:country":"DE",
    "sg:address":"Domhof 18",
    "sg:city":"Greven",
    "sg:phone":"+49 2571/2067",
    "sg:postcode":"48268",
    "sg:province":"Nordrhein-Westfalen",
    "wof:name":"Katholisches Pfarramt Hl. Schutzengel",
    "wof:placetype":"venue"
},
  "geometry": {"coordinates":[7.6095671654,52.0919494629],"type":"Point"}
}