{
  "type": "Feature",
  "properties": {
    "iso:country":"DE",
    "sg:address":"Franckstr. 40",
    "sg:city":"Vaihingen",
    "sg:phone":"+49 7042/5660",
    "sg:postcode":"71665",
    "sg:province":"Baden-W\u00fcrttemberg",
    "wof:name":"Grabdenkm\u00e4ler Morlock",
    "wof:placetype":"venue"
},
  "geometry": {"coordinates":[8.9609642029,48.9351272583],"type":"Point"}
}