{
  "type": "Feature",
  "properties": {
    "iso:country":"DE",
    "sg:address":"Prielmayrstr. 16",
    "sg:city":"Poing",
    "sg:phone":"+49 8121/82061",
    "sg:postcode":"85586",
    "sg:province":"Bayern",
    "wof:name":"G\u00fcnther Blieninger",
    "wof:placetype":"venue"
},
  "geometry": {"coordinates":[11.819006,48.167877],"type":"Point"}
}