{
  "type": "Feature",
  "properties": {
    "iso:country":"DE",
    "sg:address":"Martin-Luther-Str. 3",
    "sg:city":"Bad Kissingen",
    "sg:phone":"+49 971/2247",
    "sg:postcode":"97688",
    "sg:province":"Bayern",
    "wof:name":"Ditzel Moden Gmbh",
    "wof:placetype":"venue"
},
  "geometry": {"coordinates":[10.078314,50.198135],"type":"Point"}
}