{
  "type": "Feature",
  "properties": {
    "iso:country":"DE",
    "sg:address":"Richard-Matthaei-Platz 1",
    "sg:city":"Hamm",
    "sg:phone":"+49 2381/926880",
    "sg:postcode":"59065",
    "sg:province":"Nordrhein-Westfalen",
    "wof:name":"Werdin Gmbh & Co. Kg",
    "wof:placetype":"venue"
},
  "geometry": {"coordinates":[7.81183,51.681389],"type":"Point"}
}