{
  "type": "Feature",
  "properties": {
    "iso:country":"DE",
    "sg:address":"Albert-Schweitzer-Str. 11",
    "sg:city":"Kleinostheim",
    "sg:phone":"+49 6027/8567",
    "sg:postcode":"63801",
    "sg:province":"Bayern",
    "wof:name":"Georg Schinas",
    "wof:placetype":"venue"
},
  "geometry": {"coordinates":[9.0658607483,50.0009155273],"type":"Point"}
}