{
  "type": "Feature",
  "properties": {
    "iso:country":"DE",
    "sg:address":"Amselstr. 10",
    "sg:city":"Mannheim",
    "sg:phone":"+49 621/786001",
    "sg:postcode":"68307",
    "sg:province":"Baden-W\u00fcrttemberg",
    "wof:name":"Schwarzwaldstube K. H\u00f6rth",
    "wof:placetype":"venue"
},
  "geometry": {"coordinates":[8.4573030472,49.5493431091],"type":"Point"}
}