{
  "type": "Feature",
  "properties": {
    "iso:country":"DE",
    "sg:address":"Talstr. 31",
    "sg:city":"Leverkusen",
    "sg:phone":"+49 2171/3920",
    "sg:postcode":"51379",
    "sg:province":"Nordrhein-Westfalen",
    "wof:name":"Altenheim St. Albertus",
    "wof:placetype":"venue"
},
  "geometry": {"coordinates":[7.015198,51.07103],"type":"Point"}
}