{
  "type": "Feature",
  "properties": {
    "iso:country":"DE",
    "sg:address":"Industriestr. 34",
    "sg:city":"B\u00f6sel",
    "sg:phone":"+49 4494/1711",
    "sg:postcode":"26219",
    "sg:province":"Niedersachsen",
    "wof:name":"Tonenjes & Meichsner Bau Gmbh",
    "wof:placetype":"venue"
},
  "geometry": {"coordinates":[7.944624,52.998005],"type":"Point"}
}