{
  "type": "Feature",
  "properties": {
    "iso:country":"DE",
    "sg:address":"Laizer Str.",
    "sg:city":"Sigmaringen",
    "sg:postcode":"72488",
    "sg:province":"Baden-W\u00fcrttemberg",
    "wof:name":"Baresel Gmbh & Co. Kg",
    "wof:placetype":"venue"
},
  "geometry": {"coordinates":[9.2033472061,48.0843009949],"type":"Point"}
}