{
  "type": "Feature",
  "properties": {
    "iso:country":"DE",
    "sg:address":"Gei\u00dfelhardter Str. 49",
    "sg:city":"Pfedelbach",
    "sg:phone":"+49 7949/463",
    "sg:postcode":"74629",
    "sg:province":"Baden-W\u00fcrttemberg",
    "wof:name":"Gasthaus Karl K\u00f6hler",
    "wof:placetype":"venue"
},
  "geometry": {"coordinates":[9.5267095566,49.1352386475],"type":"Point"}
}