{
  "type": "Feature",
  "properties": {
    "iso:country":"DE",
    "sg:address":"Theodor-Heuss-Str. 31",
    "sg:city":"Bad Vilbel",
    "sg:phone":"+49 6101/98490",
    "sg:postcode":"61118",
    "sg:province":"Hessen",
    "wof:name":"Wamtek Information Systems Gmbh",
    "wof:placetype":"venue"
},
  "geometry": {"coordinates":[8.7371549606,50.2110786438],"type":"Point"}
}