{
  "type": "Feature",
  "properties": {
    "iso:country":"DE",
    "sg:address":"Holter Str. 4",
    "sg:city":"H\u00f6velhof",
    "sg:phone":"+49 5207/5611",
    "sg:postcode":"33161",
    "sg:province":"Nordrhein-Westfalen",
    "wof:name":"K. Schiermeyer",
    "wof:placetype":"venue"
},
  "geometry": {"coordinates":[8.6373224258,51.8671531677],"type":"Point"}
}