{
  "type": "Feature",
  "properties": {
    "iso:country":"DE",
    "sg:address":"Rheinstr. 53",
    "sg:city":"Mainz",
    "sg:phone":"+49 6131/227261",
    "sg:postcode":"55116",
    "sg:province":"Rheinland-Pfalz",
    "wof:name":"Piano On The Rocks",
    "wof:placetype":"venue"
},
  "geometry": {"coordinates":[8.275976181,50.0006065369],"type":"Point"}
}