{
  "type": "Feature",
  "properties": {
    "iso:country":"DE",
    "sg:address":"Kattowitzer Str. 145",
    "sg:city":"Salzgitter",
    "sg:phone":"+49 5341/15050",
    "sg:postcode":"38226",
    "sg:province":"Niedersachsen",
    "wof:name":"R\u00f6merbad Salzgitter Peter Schachtschneider",
    "wof:placetype":"venue"
},
  "geometry": {"coordinates":[10.3211011887,52.1511306763],"type":"Point"}
}