{
  "type": "Feature",
  "properties": {
    "iso:country":"DE",
    "sg:address":"Daimlerstr. 7",
    "sg:city":"S\u00fc\u00dfen",
    "sg:phone":"+49 7162/44266",
    "sg:postcode":"73079",
    "sg:province":"Baden-W\u00fcrttemberg",
    "wof:name":"We.come Gmbh",
    "wof:placetype":"venue"
},
  "geometry": {"coordinates":[9.746473,48.679474],"type":"Point"}
}