{
  "type": "Feature",
  "properties": {
    "iso:country":"DE",
    "sg:address":"Breslauer Stra\u00dfe 31",
    "sg:city":"Melle",
    "sg:postcode":"49324",
    "sg:province":"Niedersachsen",
    "wof:name":"Mgb-chat",
    "wof:placetype":"venue"
},
  "geometry": {"coordinates":[8.3417549133,52.1978759766],"type":"Point"}
}