{
  "type": "Feature",
  "properties": {
    "iso:country":"DE",
    "sg:address":"Alerdsweg 1",
    "sg:city":"Braunschweig",
    "sg:phone":"+49 531/577922",
    "sg:postcode":"38118",
    "sg:province":"Niedersachsen",
    "wof:name":"Sock Automaten",
    "wof:placetype":"venue"
},
  "geometry": {"coordinates":[10.5034189224,52.2647781372],"type":"Point"}
}