{
  "type": "Feature",
  "properties": {
    "iso:country":"DE",
    "sg:address":"Am Flugfeld 9",
    "sg:city":"D\u00fcsseldorf",
    "sg:phone":"+49 211/403247",
    "sg:postcode":"40489",
    "sg:province":"Nordrhein-Westfalen",
    "wof:name":"G. N\u00fcsser Immobilien R D M",
    "wof:placetype":"venue"
},
  "geometry": {"coordinates":[6.7553358078,51.2968711853],"type":"Point"}
}