{
  "type": "Feature",
  "properties": {
    "iso:country":"DE",
    "sg:address":"Markt 19",
    "sg:city":"Finsterwalde",
    "sg:phone":"+49 3531/3309",
    "sg:postcode":"03238",
    "sg:province":"Brandenburg",
    "wof:name":"U. Lampe",
    "wof:placetype":"venue"
},
  "geometry": {"coordinates":[13.7081241608,51.6297531128],"type":"Point"}
}