{
  "type": "Feature",
  "properties": {
    "iso:country":"DE",
    "sg:address":"Flurstr. 48",
    "sg:city":"Simmersfeld",
    "sg:phone":"+49 7453/7530",
    "sg:postcode":"72226",
    "sg:province":"Baden-W\u00fcrttemberg",
    "wof:name":"G\u00e4stehaus K. Und H. Seeger",
    "wof:placetype":"venue"
},
  "geometry": {"coordinates":[8.5390958786,48.593536377],"type":"Point"}
}