{
  "type": "Feature",
  "properties": {
    "iso:country":"DE",
    "sg:address":"Bahnhofstr. 1",
    "sg:city":"Buttenwiesen",
    "sg:phone":"+49 8274/691410",
    "sg:postcode":"86647",
    "sg:province":"Bayern",
    "wof:name":"Rudolf Fottner Gmbh",
    "wof:placetype":"venue"
},
  "geometry": {"coordinates":[10.74329,48.625912],"type":"Point"}
}