{
  "type": "Feature",
  "properties": {
    "iso:country":"DE",
    "sg:address":"Fontanestr. 1",
    "sg:city":"Letschin",
    "sg:phone":"+49 33475/233",
    "sg:postcode":"15324",
    "sg:province":"Brandenburg",
    "wof:name":"Eiscafe Hartmut Philipp",
    "wof:placetype":"venue"
},
  "geometry": {"coordinates":[14.359797,52.647129],"type":"Point"}
}