{
  "type": "Feature",
  "properties": {
    "iso:country":"DE",
    "sg:address":"Bahnhofstr. 3",
    "sg:city":"Naila",
    "sg:phone":"+49 9282/96210",
    "sg:postcode":"95119",
    "sg:province":"Bayern",
    "wof:name":"Axel Adrian Notar",
    "wof:placetype":"venue"
},
  "geometry": {"coordinates":[11.7103967667,50.3291664124],"type":"Point"}
}