{
  "type": "Feature",
  "properties": {
    "iso:country":"DE",
    "sg:address":"Bloher Pad 8",
    "sg:city":"Bad Zwischenahn",
    "sg:phone":"+49 441/69491",
    "sg:postcode":"26160",
    "sg:province":"Niedersachsen",
    "wof:name":"Dirk Borchers Grundst\u00fccks- Handels- Und Beteilig.- Gmbh",
    "wof:placetype":"venue"
},
  "geometry": {"coordinates":[8.14918,53.168079],"type":"Point"}
}