{
  "type": "Feature",
  "properties": {
    "iso:country":"DE",
    "sg:address":"Horemansstr. 28",
    "sg:city":"M\u00fcnchen",
    "sg:phone":"+49 89/1234888",
    "sg:postcode":"80636",
    "sg:province":"Bayern",
    "wof:name":"Prof. Michael G\u00e4n\u00dfler Architekt",
    "wof:placetype":"venue"
},
  "geometry": {"coordinates":[11.540445,48.154171],"type":"Point"}
}