{
  "type": "Feature",
  "properties": {
    "iso:country":"DE",
    "sg:address":"M\u00fchlenweg 22",
    "sg:city":"L\u00f6ningen",
    "sg:phone":"+49 5432/2719",
    "sg:postcode":"49624",
    "sg:province":"Niedersachsen",
    "wof:name":"Seel Gmbh",
    "wof:placetype":"venue"
},
  "geometry": {"coordinates":[7.796148,52.772041],"type":"Point"}
}