{
  "type": "Feature",
  "properties": {
    "iso:country":"DE",
    "sg:address":"Haleb\u00fcller Weg 6",
    "sg:city":"Schob\u00fcll",
    "sg:phone":"+49 4846/1622",
    "sg:postcode":"25875",
    "wof:name":"J. Albertsen",
    "wof:placetype":"venue"
},
  "geometry": {"coordinates":[9.002025,54.512394],"type":"Point"}
}