{
  "type": "Feature",
  "properties": {
    "iso:country":"DE",
    "sg:address":"Brachtstr. 1",
    "sg:city":"Plettenberg",
    "sg:phone":"+49 2391/3051",
    "sg:postcode":"58840",
    "sg:province":"Nordrhein-Westfalen",
    "wof:name":"H.-j. Arnold & Nahrgang",
    "wof:placetype":"venue"
},
  "geometry": {"coordinates":[7.8761987686,51.2130661011],"type":"Point"}
}