{
  "type": "Feature",
  "properties": {
    "iso:country":"DE",
    "sg:address":"Luitpoldst. 52",
    "sg:city":"Landshut",
    "sg:phone":"+49 871/82370",
    "sg:postcode":"84034",
    "sg:province":"Bayern",
    "wof:name":"Volksbank-raiffeisenbank Eg",
    "wof:placetype":"venue"
},
  "geometry": {"coordinates":[12.140757,48.541306],"type":"Point"}
}