{
  "type": "Feature",
  "properties": {
    "iso:country":"DE",
    "sg:address":"Beim Haagensteg 5",
    "sg:city":"L\u00f6rrach",
    "sg:phone":"+49 7621/954110",
    "sg:postcode":"79541",
    "sg:province":"Baden-W\u00fcrttemberg",
    "wof:name":"Sporthotel Impulsiv",
    "wof:placetype":"venue"
},
  "geometry": {"coordinates":[7.6785430908,47.6311645508],"type":"Point"}
}