{
  "type": "Feature",
  "properties": {
    "iso:country":"DE",
    "sg:address":"Schr\u00f6derstr. 20",
    "sg:city":"Schneverdingen",
    "sg:postcode":"29640",
    "sg:province":"Niedersachsen",
    "wof:name":"Lauer & Co.",
    "wof:placetype":"venue"
},
  "geometry": {"coordinates":[9.7963781357,53.1101608276],"type":"Point"}
}