{
  "type": "Feature",
  "properties": {
    "iso:country":"DE",
    "sg:address":"Gr\u00fcttweg 15",
    "sg:city":"L\u00f6rrach",
    "sg:phone":"+49 7621/2542",
    "sg:postcode":"79539",
    "sg:province":"Baden-W\u00fcrttemberg",
    "wof:name":"Restaurant Rot-wei\u00df",
    "wof:placetype":"venue"
},
  "geometry": {"coordinates":[7.6606378555,47.6260757446],"type":"Point"}
}