{
  "type": "Feature",
  "properties": {
    "iso:country":"DE",
    "sg:address":"Am Vosseberg 58",
    "sg:city":"Papenburg",
    "sg:postcode":"26871",
    "sg:province":"Niedersachsen",
    "wof:name":"Lantis-software-l\u00f6sungen F\u00fcr Die Bauwirtschaft Gmbh",
    "wof:placetype":"venue"
},
  "geometry": {"coordinates":[7.4259781837,53.0757369995],"type":"Point"}
}