{
  "type": "Feature",
  "properties": {
    "iso:country":"DE",
    "sg:address":"Burgstr. 5",
    "sg:city":"Wolgast",
    "sg:phone":"+49 3836/602055",
    "sg:postcode":"17438",
    "sg:province":"Mecklenburg-Vorpommern",
    "wof:name":"Dietmar Debniak",
    "wof:placetype":"venue"
},
  "geometry": {"coordinates":[13.7788352966,54.0534934998],"type":"Point"}
}