{
  "type": "Feature",
  "properties": {
    "iso:country":"DE",
    "sg:address":"Vilniuser Str. 6",
    "sg:city":"Erfurt",
    "sg:postcode":"99089",
    "sg:province":"Th\u00fcringen",
    "wof:name":"Dr. Med. Siegfried B\u00f6hm",
    "wof:placetype":"venue"
},
  "geometry": {"coordinates":[11.013678,51.006969],"type":"Point"}
}