{
  "type": "Feature",
  "properties": {
    "iso:country":"DE",
    "sg:address":"Auf der Heide 22",
    "sg:city":"Twistetal",
    "sg:phone":"+49 5695/355",
    "sg:postcode":"34477",
    "sg:province":"Hessen",
    "wof:name":"Anita Heinemann",
    "wof:placetype":"venue"
},
  "geometry": {"coordinates":[8.96589,51.336826],"type":"Point"}
}