{
  "type": "Feature",
  "properties": {
    "iso:country":"DE",
    "sg:address":"Rheydter Str. 278",
    "sg:city":"M\u00f6nchengladbach",
    "sg:phone":"+49 2161/13424",
    "sg:postcode":"41065",
    "sg:province":"Nordrhein-Westfalen",
    "wof:name":"Mbe Medizinische Bedarfs- Und Einrichtungsgesellschaft Mbh",
    "wof:placetype":"venue"
},
  "geometry": {"coordinates":[6.439252,51.178856],"type":"Point"}
}