{
  "type": "Feature",
  "properties": {
    "iso:country":"DE",
    "sg:address":"F\u00fcrstenberg 11",
    "sg:city":"S\u00fcdlohn",
    "sg:phone":"+49 2862/7339",
    "sg:postcode":"46354",
    "sg:province":"Nordrhein-Westfalen",
    "wof:name":"Paul Nienhaus",
    "wof:placetype":"venue"
},
  "geometry": {"coordinates":[6.863241,51.943565],"type":"Point"}
}