{
  "type": "Feature",
  "properties": {
    "iso:country":"DE",
    "sg:address":"Ederweg 2",
    "sg:city":"Calden",
    "sg:postcode":"34379",
    "sg:province":"Hessen",
    "wof:name":"Central Air Flugcharter Gmbh",
    "wof:placetype":"venue"
},
  "geometry": {"coordinates":[9.400781,51.396587],"type":"Point"}
}