{
  "type": "Feature",
  "properties": {
    "iso:country":"DE",
    "sg:address":"Denkmalstr. 25",
    "sg:city":"Harsum",
    "sg:postcode":"31177",
    "sg:province":"Niedersachsen",
    "wof:name":"Arbeitsgemeinschaft Borsumer Vereine",
    "wof:placetype":"venue"
},
  "geometry": {"coordinates":[10.0038280487,52.2077102661],"type":"Point"}
}