{
  "type": "Feature",
  "properties": {
    "iso:country":"DE",
    "sg:address":"Varbrook 84",
    "sg:city":"Niederkr\u00fcchten",
    "sg:phone":"+49 2163/45640",
    "sg:postcode":"41372",
    "sg:province":"Nordrhein-Westfalen",
    "wof:name":"Wilhelm Wolfs",
    "wof:placetype":"venue"
},
  "geometry": {"coordinates":[6.225007,51.178089],"type":"Point"}
}