{
  "type": "Feature",
  "properties": {
    "iso:country":"DE",
    "sg:address":"Gernsheimer Str. 42",
    "sg:city":"Alsbach-H\u00e4hnlein",
    "sg:phone":"+49 6257/62120",
    "sg:postcode":"64665",
    "sg:province":"Hessen",
    "wof:name":"Marktsch\u00e4nke",
    "wof:placetype":"venue"
},
  "geometry": {"coordinates":[8.5733127594,49.7360115051],"type":"Point"}
}