{
  "type": "Feature",
  "properties": {
    "iso:country":"DE",
    "sg:address":"Gerberstr. 43",
    "sg:city":"Kempten",
    "sg:phone":"+49 831/23530",
    "sg:postcode":"87435",
    "sg:province":"Bayern",
    "wof:name":"Andreas Martin Stahl- Und Schneidwaren",
    "wof:placetype":"venue"
},
  "geometry": {"coordinates":[10.3148384094,47.7274856567],"type":"Point"}
}