{
  "type": "Feature",
  "properties": {
    "iso:country":"DE",
    "sg:address":"Schulstr. 1",
    "sg:city":"Gr\u00e4venwiesbach",
    "sg:phone":"+49 6086/457",
    "sg:postcode":"61279",
    "sg:province":"Hessen",
    "wof:name":"A. Lauth",
    "wof:placetype":"venue"
},
  "geometry": {"coordinates":[8.457044,50.388039],"type":"Point"}
}