{
  "type": "Feature",
  "properties": {
    "iso:country":"DE",
    "sg:address":"Siemensstr. 5",
    "sg:city":"Haan",
    "sg:phone":"+49 4921/2994500",
    "sg:postcode":"42781",
    "sg:province":"Nordrhein-Westfalen",
    "wof:name":"Ernst J\u00c4ger Kunststoffverpackung Gmbh",
    "wof:placetype":"venue"
},
  "geometry": {"coordinates":[6.996356,51.183201],"type":"Point"}
}