{
  "type": "Feature",
  "properties": {
    "iso:country":"DE",
    "sg:address":"Gildestr. 72",
    "sg:city":"Ibbenb\u00fcren",
    "sg:phone":"+49 5451/2034",
    "sg:postcode":"49479",
    "sg:province":"Nordrhein-Westfalen",
    "wof:name":"H. Gube Gmbh",
    "wof:placetype":"venue"
},
  "geometry": {"coordinates":[7.747804,52.2714],"type":"Point"}
}