{
  "type": "Feature",
  "properties": {
    "iso:country":"DE",
    "sg:address":"Pirolweg 3",
    "sg:city":"L\u00fcneburg",
    "sg:phone":"+49 4131/51595",
    "sg:postcode":"21337",
    "sg:province":"Niedersachsen",
    "wof:name":"Nils Pusch",
    "wof:placetype":"venue"
},
  "geometry": {"coordinates":[10.42114,53.23671],"type":"Point"}
}