{
  "type": "Feature",
  "properties": {
    "iso:country":"DE",
    "sg:address":"Hindenburgdamm 56",
    "sg:city":"Berlin",
    "sg:phone":"+49 30/8344641",
    "sg:postcode":"12203",
    "sg:province":"Berlin",
    "wof:name":"Wolfgang Klau\u00dfnitzer",
    "wof:placetype":"venue"
},
  "geometry": {"coordinates":[13.3157329559,52.4457931519],"type":"Point"}
}