{
  "type": "Feature",
  "properties": {
    "iso:country":"DE",
    "sg:address":"Eichendorffstr. 42",
    "sg:city":"Ottobrunn",
    "sg:phone":"+49 89/6090767",
    "sg:postcode":"85521",
    "sg:province":"Bayern",
    "wof:name":"P. Sanewytsch Immobilienmakler",
    "wof:placetype":"venue"
},
  "geometry": {"coordinates":[11.6751270294,48.0630722046],"type":"Point"}
}