{
  "type": "Feature",
  "properties": {
    "iso:country":"DE",
    "sg:address":"Am Sandtorkai 2",
    "sg:city":"Hamburg",
    "sg:postcode":"20457",
    "sg:province":"Hamburg",
    "wof:name":"Wertform Gmbh",
    "wof:placetype":"venue"
},
  "geometry": {"coordinates":[9.9959201813,53.5439567566],"type":"Point"}
}