{
  "type": "Feature",
  "properties": {
    "iso:country":"DE",
    "sg:address":"Ro\u00dfplatz 13",
    "sg:city":"Leipzig",
    "sg:phone":"+49 341/9611931",
    "sg:postcode":"04103",
    "sg:province":"Sachsen",
    "wof:name":"Dr. Med. Uwe Tischer Arzt F\u00fcr Allgemeinmedizin",
    "wof:placetype":"venue"
},
  "geometry": {"coordinates":[12.3790168762,51.3357925415],"type":"Point"}
}