{
  "type": "Feature",
  "properties": {
    "iso:country":"DE",
    "sg:address":"Schlankreye 73",
    "sg:city":"Hamburg",
    "sg:phone":"+49 40/4226022",
    "sg:postcode":"20144",
    "sg:province":"Hamburg",
    "wof:name":"Bergsportzentrale Hamburg",
    "wof:placetype":"venue"
},
  "geometry": {"coordinates":[9.977044,53.577381],"type":"Point"}
}