{
  "type": "Feature",
  "properties": {
    "iso:country":"DE",
    "sg:address":"Katharinenstr. 10",
    "sg:city":"Unterhaching",
    "sg:phone":"+49 89/61079057",
    "sg:postcode":"82008",
    "sg:province":"Bayern",
    "wof:name":"Dr. Paul M. Kr\u00e4mer Rechtsanwalt",
    "wof:placetype":"venue"
},
  "geometry": {"coordinates":[11.6129112244,48.0633850098],"type":"Point"}
}