{
  "type": "Feature",
  "properties": {
    "iso:country":"DE",
    "sg:address":"Augustinessenstr. 5",
    "sg:city":"Recklinghausen",
    "sg:phone":"+49 2361/10510",
    "sg:postcode":"45657",
    "sg:province":"Nordrhein-Westfalen",
    "wof:name":"Grollmann Kirste Wallbaum Und Partner",
    "wof:placetype":"venue"
},
  "geometry": {"coordinates":[7.1951751709,51.6154251099],"type":"Point"}
}