{
  "type": "Feature",
  "properties": {
    "iso:country":"DE",
    "sg:address":"Merseburger Str. 52",
    "sg:city":"Leipzig",
    "sg:phone":"+49 341/472816",
    "sg:postcode":"04177",
    "sg:province":"Sachsen",
    "wof:name":"M. Maier",
    "wof:placetype":"venue"
},
  "geometry": {"coordinates":[12.3324661255,51.3333625793],"type":"Point"}
}