{
  "type": "Feature",
  "properties": {
    "iso:country":"DE",
    "sg:address":"Richard-Strauss-Str. 47",
    "sg:city":"M\u00fcnchen",
    "sg:phone":"+49 89/99720947",
    "sg:postcode":"81677",
    "sg:province":"Bayern",
    "wof:name":"Parit\u00e4tische Familien- Bildungsst\u00e4tte M\u00fcnchner",
    "wof:placetype":"venue"
},
  "geometry": {"coordinates":[11.6152105331,48.1433753967],"type":"Point"}
}