{
  "type": "Feature",
  "properties": {
    "iso:country":"DE",
    "sg:address":"Vitusstr. 27",
    "sg:city":"Lathen",
    "sg:phone":"+49 5933/375",
    "sg:postcode":"49762",
    "sg:province":"Niedersachsen",
    "wof:name":"Katholisches Pfarramt St. Antonius",
    "wof:placetype":"venue"
},
  "geometry": {"coordinates":[7.3206300735,52.8628807068],"type":"Point"}
}