{
  "type": "Feature",
  "properties": {
    "iso:country":"DE",
    "sg:address":"Hammer Deich 70b",
    "sg:city":"Hamburg",
    "sg:phone":"+49 40/42910000",
    "sg:postcode":"20537",
    "sg:province":"Hamburg",
    "wof:name":"Ubs Bar Support Gmbh",
    "wof:placetype":"venue"
},
  "geometry": {"coordinates":[10.04515,53.546318],"type":"Point"}
}