{
  "type": "Feature",
  "properties": {
    "iso:country":"DE",
    "sg:address":"Am Rain 5",
    "sg:city":"Hechingen",
    "sg:phone":"+49 7471/2408",
    "sg:postcode":"72379",
    "sg:province":"Baden-W\u00fcrttemberg",
    "wof:name":"Strobel Am Markt Inh. Dieter Strobel E. K.",
    "wof:placetype":"venue"
},
  "geometry": {"coordinates":[8.9638223648,48.3528213501],"type":"Point"}
}