{
  "type": "Feature",
  "properties": {
    "iso:country":"DE",
    "sg:address":"Solidarit\u00e4tsstr. 13",
    "sg:city":"Seeburg",
    "sg:phone":"+49 34774/28279",
    "sg:postcode":"06317",
    "sg:province":"Sachsen-Anhalt",
    "wof:name":"Sauna-dom Gmbh",
    "wof:placetype":"venue"
},
  "geometry": {"coordinates":[11.702957,51.489777],"type":"Point"}
}