{
  "type": "Feature",
  "properties": {
    "iso:country":"DE",
    "sg:address":"Heideweg 31",
    "sg:city":"Sulingen",
    "sg:phone":"+49 4271/2265",
    "sg:postcode":"27232",
    "sg:province":"Niedersachsen",
    "wof:name":"Fritz Wiedemann",
    "wof:placetype":"venue"
},
  "geometry": {"coordinates":[8.7967061996,52.6770248413],"type":"Point"}
}