{
  "type": "Feature",
  "properties": {
    "iso:country":"DE",
    "sg:address":"Elsterstr. 11",
    "sg:city":"Sch\u00f6nwald",
    "sg:phone":"+49 7722/5519",
    "sg:postcode":"78141",
    "sg:province":"Baden-W\u00fcrttemberg",
    "wof:name":"B. Allgaier",
    "wof:placetype":"venue"
},
  "geometry": {"coordinates":[8.2021303177,48.1042289734],"type":"Point"}
}