{
  "type": "Feature",
  "properties": {
    "iso:country":"DE",
    "sg:address":"M\u00f6rser Str. 60",
    "sg:city":"Wolfsburg",
    "sg:phone":"+49 5362/2468",
    "sg:postcode":"38442",
    "sg:province":"Niedersachsen",
    "wof:name":"Detlef Kuhn",
    "wof:placetype":"venue"
},
  "geometry": {"coordinates":[10.707738,52.39455],"type":"Point"}
}