{
  "type": "Feature",
  "properties": {
    "iso:country":"DE",
    "sg:address":"Sierichstr. 75",
    "sg:city":"Hamburg",
    "sg:phone":"+49 40/27878163",
    "sg:postcode":"22301",
    "sg:province":"Hamburg",
    "wof:name":"Achim Schulz-althoff Architekt",
    "wof:placetype":"venue"
},
  "geometry": {"coordinates":[10.00468,53.584133],"type":"Point"}
}