{
  "type": "Feature",
  "properties": {
    "iso:country":"DE",
    "sg:address":"Sportlerweg 15",
    "sg:city":"Chemnitz",
    "sg:phone":"+49 371/584970",
    "sg:postcode":"09125",
    "sg:province":"Sachsen",
    "wof:name":"Sportlerheim Erfenschlag",
    "wof:placetype":"venue"
},
  "geometry": {"coordinates":[12.955491066,50.7890853882],"type":"Point"}
}