{
  "type": "Feature",
  "properties": {
    "iso:country":"DE",
    "sg:address":"Marktstr. 10",
    "sg:city":"K\u00f6nigsbach-Stein",
    "sg:phone":"+49 7232/49059",
    "sg:postcode":"75203",
    "sg:province":"Baden-W\u00fcrttemberg",
    "wof:name":"H. F.",
    "wof:placetype":"venue"
},
  "geometry": {"coordinates":[8.6120262146,48.9657211304],"type":"Point"}
}