{
  "type": "Feature",
  "properties": {
    "iso:country":"DE",
    "sg:address":"Dresdener Str. 76",
    "sg:city":"Wurzen",
    "sg:phone":"+49 3425/8500",
    "sg:postcode":"04808",
    "sg:province":"Sachsen",
    "wof:name":"Elbo Bau Ag Niederlassung Wurzen",
    "wof:placetype":"venue"
},
  "geometry": {"coordinates":[12.759316,51.361412],"type":"Point"}
}