{
  "type": "Feature",
  "properties": {
    "iso:country":"DE",
    "sg:address":"Hoelemannpromenade 9",
    "sg:city":"Osterode",
    "sg:phone":"+49 5522/72200",
    "sg:postcode":"37520",
    "sg:province":"Niedersachsen",
    "wof:name":"Wentscher Und Riban Rechtsanw\u00e4lte Und Notar",
    "wof:placetype":"venue"
},
  "geometry": {"coordinates":[10.2564058304,51.7271728516],"type":"Point"}
}