{
  "type": "Feature",
  "properties": {
    "iso:country":"DE",
    "sg:address":"Johann-Gutenberg-Str. 5",
    "sg:city":"Wehrheim",
    "sg:phone":"+49 6081/56066",
    "sg:postcode":"61273",
    "sg:province":"Hessen",
    "wof:name":"Technopipe Gmbh",
    "wof:placetype":"venue"
},
  "geometry": {"coordinates":[8.563076973,50.3111228943],"type":"Point"}
}