{
  "type": "Feature",
  "properties": {
    "iso:country":"DE",
    "sg:address":"Professor-Ansch\u00fctz-Str. 58",
    "sg:city":"Kiel",
    "sg:phone":"+49 431/87645",
    "sg:postcode":"24118",
    "sg:province":"Schleswig-Holstein",
    "wof:name":"Charlotte Henke Inh. Dorothea Pries",
    "wof:placetype":"venue"
},
  "geometry": {"coordinates":[10.1268396378,54.3386421204],"type":"Point"}
}