{
  "type": "Feature",
  "properties": {
    "iso:country":"DE",
    "sg:address":"Lafontainestr. 32",
    "sg:city":"Halle",
    "sg:phone":"+49 345/8070655",
    "sg:postcode":"06114",
    "sg:province":"Sachsen-Anhalt",
    "wof:name":"Wisl Wirtschafts- Und Softwarel\u00f6sungen Gmbh",
    "wof:placetype":"venue"
},
  "geometry": {"coordinates":[11.9624176025,51.4961700439],"type":"Point"}
}