{
  "type": "Feature",
  "properties": {
    "iso:country":"DE",
    "sg:address":"Klenzestr 1-3",
    "sg:city":"Ismaning",
    "sg:phone":"+49 89/96245611",
    "sg:postcode":"85737",
    "sg:province":"Bayern",
    "wof:name":"Seicom Comunication Systems Gmbh",
    "wof:placetype":"venue"
},
  "geometry": {"coordinates":[11.66360569,48.2186584473],"type":"Point"}
}