{
  "type": "Feature",
  "properties": {
    "iso:country":"DE",
    "sg:address":"Hauptstr. 2",
    "sg:city":"Kalenborn-Scheuern",
    "sg:phone":"+49 6591/95200",
    "sg:postcode":"54570",
    "sg:province":"Rheinland-Pfalz",
    "wof:name":"Joleka Fenster- Und Bau- Elemente Verwaltungs Gmbh",
    "wof:placetype":"venue"
},
  "geometry": {"coordinates":[6.74421,50.226849],"type":"Point"}
}