{
  "type": "Feature",
  "properties": {
    "iso:country":"DE",
    "sg:address":"Th\u00fcnen 48",
    "sg:city":"Werne",
    "sg:phone":"+49 2389",
    "sg:postcode":"59368",
    "sg:province":"Nordrhein-Westfalen",
    "wof:name":"Ehmg Elektro Handels U. Montage Gesellschaft Mbh",
    "wof:placetype":"venue"
},
  "geometry": {"coordinates":[7.6445918083,51.6661071777],"type":"Point"}
}