{
  "type": "Feature",
  "properties": {
    "iso:country":"DE",
    "sg:address":"Zimmermannstr 15",
    "sg:city":"Stuttgart",
    "sg:phone":"+49 711/490900",
    "sg:postcode":"70182",
    "sg:province":"Baden-W\u00fcrttemberg",
    "wof:name":"Gtc Gutacker Telecommunication Gmbh",
    "wof:placetype":"venue"
},
  "geometry": {"coordinates":[9.182785,48.770817],"type":"Point"}
}