{
  "type": "Feature",
  "properties": {
    "iso:country":"DE",
    "sg:address":"Beim Engg\u00e4\u00dfle 1",
    "sg:city":"Villingen-Schwenningen",
    "sg:phone":"+49 7721/55122",
    "sg:postcode":"78050",
    "sg:province":"Baden-W\u00fcrttemberg",
    "wof:name":"Friedrich Ebert Gartenbau Und Blumengesch\u00e4ft",
    "wof:placetype":"venue"
},
  "geometry": {"coordinates":[8.435101,48.058826],"type":"Point"}
}