{
  "type": "Feature",
  "properties": {
    "iso:country":"DE",
    "sg:address":"Werlter Str. 23",
    "sg:city":"Lindern",
    "sg:phone":"+49 5957/1247",
    "sg:postcode":"49699",
    "sg:province":"Niedersachsen",
    "wof:name":"Indor Betriebshygiene-verkauf- Dienstleistungsges. Mbh",
    "wof:placetype":"venue"
},
  "geometry": {"coordinates":[7.772304,52.844994],"type":"Point"}
}