{
  "type": "Feature",
  "properties": {
    "iso:country":"DE",
    "sg:address":"Naturfreundestr. 11",
    "sg:city":"Hausham",
    "sg:phone":"+49 8026/8216",
    "sg:postcode":"83734",
    "sg:province":"Bayern",
    "wof:name":"Christl Jung",
    "wof:placetype":"venue"
},
  "geometry": {"coordinates":[11.83946,47.746368],"type":"Point"}
}