{
  "type": "Feature",
  "properties": {
    "iso:country":"DE",
    "sg:address":"Zum H\u00e4meler Wald",
    "sg:city":"Lehrte",
    "sg:phone":"+49 5175/7204",
    "sg:postcode":"31275",
    "sg:province":"Niedersachsen",
    "wof:name":"Mini Mal Markt",
    "wof:placetype":"venue"
},
  "geometry": {"coordinates":[10.1038150787,52.3729095459],"type":"Point"}
}