{
  "type": "Feature",
  "properties": {
    "iso:country":"DE",
    "sg:address":"Hermannstr. 39",
    "sg:city":"Dortmund",
    "sg:phone":"+49 231/432209",
    "sg:postcode":"44263",
    "sg:province":"Nordrhein-Westfalen",
    "wof:name":"Damian-apotheke",
    "wof:placetype":"venue"
},
  "geometry": {"coordinates":[7.500643,51.489216],"type":"Point"}
}