{
  "type": "Feature",
  "properties": {
    "iso:country":"DE",
    "sg:address":"Grubenstr. 11",
    "sg:city":"Aglasterhausen",
    "sg:phone":"+49 6262/1287",
    "sg:postcode":"74858",
    "sg:province":"Baden-W\u00fcrttemberg",
    "wof:name":"B\u00fcrgerst\u00fcble",
    "wof:placetype":"venue"
},
  "geometry": {"coordinates":[8.9859457016,49.3581008911],"type":"Point"}
}