{
  "type": "Feature",
  "properties": {
    "iso:country":"DE",
    "sg:address":"Stettiner Str. 2",
    "sg:city":"Rheinfelden",
    "sg:phone":"+49 7623/1830",
    "sg:postcode":"79618",
    "sg:province":"Baden-W\u00fcrttemberg",
    "wof:name":"Ev. Pfarramt Pauluspfarrei",
    "wof:placetype":"venue"
},
  "geometry": {"coordinates":[7.7862920761,47.5684394836],"type":"Point"}
}