{
  "type": "Feature",
  "properties": {
    "iso:country":"DE",
    "sg:address":"L\u00f6hstr. 18",
    "sg:city":"Viersen",
    "sg:phone":"+49 2162/31391",
    "sg:postcode":"41747",
    "sg:province":"Nordrhein-Westfalen",
    "wof:name":"Gamma Automatenaufstellungs- Und Vertriebs-gmbh",
    "wof:placetype":"venue"
},
  "geometry": {"coordinates":[6.3858108521,51.2572822571],"type":"Point"}
}