{
  "type": "Feature",
  "properties": {
    "iso:country":"DE",
    "sg:address":"Fr\u00f6lingstr. 15-31",
    "sg:city":"Bad Homburg",
    "sg:phone":"+49 6172/8800",
    "sg:postcode":"61352",
    "sg:province":"Hessen",
    "wof:name":"Dolaypsilon Grundst\u00fccks Verwaltungs Gmbh",
    "wof:placetype":"venue"
},
  "geometry": {"coordinates":[8.6208095551,50.2211952209],"type":"Point"}
}