{
  "type": "Feature",
  "properties": {
    "iso:country":"DE",
    "sg:address":"Zum Gewerbepark 8",
    "sg:city":"Quitzow",
    "sg:postcode":"19348",
    "sg:province":"Brandenburg",
    "wof:name":"Schmitz Lasertechnik Edelstahl- Und Blechverarbei-",
    "wof:placetype":"venue"
},
  "geometry": {"coordinates":[11.861985,53.076126],"type":"Point"}
}