{
  "type": "Feature",
  "properties": {
    "iso:country":"DE",
    "sg:address":"Klompstr. 42-44",
    "sg:city":"Bedburg-Hau",
    "sg:phone":"+49 4928/2189850",
    "sg:postcode":"47551",
    "sg:province":"Nordrhein-Westfalen",
    "wof:name":"Verfers Elektromontagen Gmbh",
    "wof:placetype":"venue"
},
  "geometry": {"coordinates":[6.199593,51.784939],"type":"Point"}
}