{
  "type": "Feature",
  "properties": {
    "iso:country":"DE",
    "sg:address":"Am Buursood 16",
    "sg:city":"Bleckede",
    "sg:phone":"+49 5854/1241",
    "sg:postcode":"21354",
    "sg:province":"Niedersachsen",
    "wof:name":"Heinrich Burmester",
    "wof:placetype":"venue"
},
  "geometry": {"coordinates":[10.78164,53.24194],"type":"Point"}
}