{
  "type": "Feature",
  "properties": {
    "iso:country":"DE",
    "sg:address":"Obere Hilgenstock 32",
    "sg:city":"Warburg",
    "sg:phone":"+49 5641/2161",
    "sg:postcode":"34414",
    "sg:province":"Nordrhein-Westfalen",
    "wof:name":"Alfred Leonard",
    "wof:placetype":"venue"
},
  "geometry": {"coordinates":[9.14857,51.49855],"type":"Point"}
}