{
  "type": "Feature",
  "properties": {
    "iso:country":"DE",
    "sg:address":"An der Neuweide 31",
    "sg:city":"Rheinberg",
    "sg:phone":"+49 2843/860868",
    "sg:postcode":"47495",
    "sg:province":"Nordrhein-Westfalen",
    "wof:name":"I. & E. M\u00f6bel Gottwald Gmbh",
    "wof:placetype":"venue"
},
  "geometry": {"coordinates":[6.6490402222,51.5135688782],"type":"Point"}
}