{
  "type": "Feature",
  "properties": {
    "iso:country":"DE",
    "sg:address":"Brebacher Landstr. 8",
    "sg:city":"Saarbr\u00fccken",
    "sg:phone":"+49 681/63346",
    "sg:postcode":"66121",
    "sg:province":"Saarland",
    "wof:name":"Haus Arabella",
    "wof:placetype":"venue"
},
  "geometry": {"coordinates":[7.0258288383,49.2237663269],"type":"Point"}
}