{
  "type": "Feature",
  "properties": {
    "iso:country":"DE",
    "sg:address":"Meersburger Str. 1",
    "sg:city":"Uhldingen-M\u00fchlhofen",
    "sg:phone":"+49 7556/6528",
    "sg:postcode":"88690",
    "sg:province":"Baden-W\u00fcrttemberg",
    "wof:name":"Stefan Sulger",
    "wof:placetype":"venue"
},
  "geometry": {"coordinates":[9.2345981598,47.7237510681],"type":"Point"}
}