{
  "type": "Feature",
  "properties": {
    "iso:country":"DE",
    "sg:address":"Hornh\u00e4user Str. 93",
    "sg:city":"Oschersleben",
    "sg:phone":"+49 3949/99494",
    "sg:postcode":"39387",
    "sg:province":"Sachsen-Anhalt",
    "wof:name":"Andrea Reinicke",
    "wof:placetype":"venue"
},
  "geometry": {"coordinates":[11.226344,52.027039],"type":"Point"}
}