{
  "type": "Feature",
  "properties": {
    "iso:country":"DE",
    "sg:address":"Dorfstr. 11",
    "sg:city":"Dettelbach",
    "sg:phone":"+49 9324/3615",
    "sg:postcode":"97337",
    "sg:province":"Bayern",
    "wof:name":"R. Und A. R\u00f6der",
    "wof:placetype":"venue"
},
  "geometry": {"coordinates":[10.1751279831,49.8262710571],"type":"Point"}
}