{
  "type": "Feature",
  "properties": {
    "iso:country":"DE",
    "sg:address":"Neue Reihe 32",
    "sg:city":"Voigtstedt",
    "sg:postcode":"06556",
    "sg:province":"Th\u00fcringen",
    "wof:name":"Lohnsteuerhilfeverein Ludwigshafen E.v.",
    "wof:placetype":"venue"
},
  "geometry": {"coordinates":[11.3122692108,51.389503479],"type":"Point"}
}