{
  "type": "Feature",
  "properties": {
    "iso:country":"DE",
    "sg:address":"Hugo-Viehoff-Str. 6",
    "sg:city":"D\u00fcsseldorf",
    "sg:phone":"+49 211/4350097",
    "sg:postcode":"40468",
    "sg:province":"Nordrhein-Westfalen",
    "wof:name":"Joh. Rittmeyer Werkst\u00e4tte F\u00fcr Grabschmuck Und Architektur",
    "wof:placetype":"venue"
},
  "geometry": {"coordinates":[6.7736539841,51.2544250488],"type":"Point"}
}