{
  "type": "Feature",
  "properties": {
    "iso:country":"DE",
    "sg:address":"Schubertstr. 5",
    "sg:city":"Edenkoben",
    "sg:phone":"+49 6323/5238",
    "sg:postcode":"67480",
    "sg:province":"Rheinland-Pfalz",
    "wof:name":"Horst Weilacher Architekt",
    "wof:placetype":"venue"
},
  "geometry": {"coordinates":[8.137517,49.280983],"type":"Point"}
}