{
  "type": "Feature",
  "properties": {
    "iso:country":"DE",
    "sg:address":"Bothenb\u00e4umchen 80",
    "sg:city":"M\u00f6nchengladbach",
    "sg:phone":"+49 2161/557447",
    "sg:postcode":"41169",
    "sg:province":"Nordrhein-Westfalen",
    "wof:name":"Walter Otto",
    "wof:placetype":"venue"
},
  "geometry": {"coordinates":[6.343834877,51.2004165649],"type":"Point"}
}