{
  "type": "Feature",
  "properties": {
    "iso:country":"DE",
    "sg:address":"Franz-Haniel-Stra\u00dfe 16a",
    "sg:city":"Moers",
    "sg:phone":"+49 2841/54001",
    "sg:postcode":"47443",
    "sg:province":"Nordrhein-Westfalen",
    "wof:name":"I.a.i. Deutschland Gmbh",
    "wof:placetype":"venue"
},
  "geometry": {"coordinates":[6.6629390717,51.454498291],"type":"Point"}
}