{
  "type": "Feature",
  "properties": {
    "iso:country":"DE",
    "sg:address":"Carl-Benz-Str. 44",
    "sg:city":"Bietigheim-Bissingen",
    "sg:phone":"+49 7142/989160",
    "sg:postcode":"74321",
    "sg:province":"Baden-W\u00fcrttemberg",
    "wof:name":"Schorr Modell- Und Formenbau Gmbh",
    "wof:placetype":"venue"
},
  "geometry": {"coordinates":[9.12632,48.935459],"type":"Point"}
}