{
  "type": "Feature",
  "properties": {
    "iso:country":"DE",
    "sg:address":"Clemensstr. 7",
    "sg:city":"K\u00f6ln",
    "sg:phone":"+49 221/233257",
    "sg:postcode":"50676",
    "sg:province":"Nordrhein-Westfalen",
    "wof:name":"Dr. Hans Henrici Notar",
    "wof:placetype":"venue"
},
  "geometry": {"coordinates":[6.9455699921,50.9339294434],"type":"Point"}
}