{
  "type": "Feature",
  "properties": {
    "iso:country":"DE",
    "sg:address":"Am Viereck 1",
    "sg:city":"K\u00f6ln",
    "sg:phone":"+49 221/864311",
    "sg:postcode":"51107",
    "sg:province":"Nordrhein-Westfalen",
    "wof:name":"Peter Kurscheid Gmbh",
    "wof:placetype":"venue"
},
  "geometry": {"coordinates":[7.07342,50.922329],"type":"Point"}
}