{
  "type": "Feature",
  "properties": {
    "iso:country":"DE",
    "sg:address":"Schoolpad 7",
    "sg:city":"Aurich",
    "sg:phone":"+49 4941/2456",
    "sg:postcode":"26605",
    "sg:province":"Niedersachsen",
    "wof:name":"F. Ditzfeld",
    "wof:placetype":"venue"
},
  "geometry": {"coordinates":[7.52059412,53.466506958],"type":"Point"}
}