{
  "type": "Feature",
  "properties": {
    "iso:country":"DE",
    "sg:address":"Heinrich-Heine-Str. 2",
    "sg:city":"J\u00f6\u00dfnitz",
    "sg:phone":"+49 3741/521348",
    "sg:postcode":"08547",
    "sg:province":"Sachsen",
    "wof:name":"Friedhold Kuhn",
    "wof:placetype":"venue"
},
  "geometry": {"coordinates":[12.1330575943,50.5374488831],"type":"Point"}
}