{
  "type": "Feature",
  "properties": {
    "iso:country":"DE",
    "sg:address":"Wurzener Str. 6",
    "sg:city":"Hohburg",
    "sg:phone":"+49 34263/41356",
    "sg:postcode":"04808",
    "sg:province":"Sachsen",
    "wof:name":"Pension-gastst\u00e4tte Zum Sportheim",
    "wof:placetype":"venue"
},
  "geometry": {"coordinates":[12.7716856003,51.3922195435],"type":"Point"}
}