{
  "type": "Feature",
  "properties": {
    "iso:country":"DE",
    "sg:address":"Dahlienstr. 1",
    "sg:city":"Aurich",
    "sg:phone":"+49 4941/2178",
    "sg:postcode":"26603",
    "sg:province":"Niedersachsen",
    "wof:name":"H. Schr\u00f6der",
    "wof:placetype":"venue"
},
  "geometry": {"coordinates":[7.489452,53.47707],"type":"Point"}
}