{
  "type": "Feature",
  "properties": {
    "iso:country":"DE",
    "sg:address":"Pfarrstr. 11",
    "sg:city":"Chemnitz",
    "sg:phone":"+49 371/517374",
    "sg:postcode":"09126",
    "sg:province":"Sachsen",
    "wof:name":"Abb Bautenschutz- Und Bautr\u00e4ger Gmbh",
    "wof:placetype":"venue"
},
  "geometry": {"coordinates":[12.953424,50.829758],"type":"Point"}
}