{
  "type": "Feature",
  "properties": {
    "iso:country":"DE",
    "sg:address":"B\u00fcnderies 7",
    "sg:city":"Saustrup",
    "sg:phone":"+49 4641/2388",
    "sg:postcode":"24392",
    "sg:province":"Schleswig-Holstein",
    "wof:name":"Theodor Schmidt",
    "wof:placetype":"venue"
},
  "geometry": {"coordinates":[9.759435,54.660095],"type":"Point"}
}