{
  "type": "Feature",
  "properties": {
    "iso:country":"DE",
    "sg:address":"Windloh 2b",
    "sg:city":"Hamburg",
    "sg:phone":"+49 40/8701122",
    "sg:postcode":"22589",
    "sg:province":"Hamburg",
    "wof:name":"U. Michael",
    "wof:placetype":"venue"
},
  "geometry": {"coordinates":[9.826815,53.578972],"type":"Point"}
}