{
  "type": "Feature",
  "properties": {
    "iso:country":"DE",
    "sg:address":"Lichtenbergplatz 5",
    "sg:city":"Hannover",
    "sg:phone":"+49 511/444048",
    "sg:postcode":"30449",
    "sg:province":"Niedersachsen",
    "wof:name":"Lindener Baukontor",
    "wof:placetype":"venue"
},
  "geometry": {"coordinates":[9.712236,52.369106],"type":"Point"}
}