{
  "type": "Feature",
  "properties": {
    "iso:country":"DE",
    "sg:address":"Oberm\u00fchlhausen",
    "sg:city":"Die\u00dfen",
    "sg:phone":"+49 8196/813",
    "sg:postcode":"86911",
    "sg:province":"Bayern",
    "wof:name":"Ernesto Avendano",
    "wof:placetype":"venue"
},
  "geometry": {"coordinates":[10.9966249466,47.9823379517],"type":"Point"}
}