{
  "type": "Feature",
  "properties": {
    "iso:country":"DE",
    "sg:address":"Langenbochumer Str. 370",
    "sg:city":"Herten",
    "sg:phone":"+49 2366/55609",
    "sg:postcode":"45701",
    "sg:province":"Nordrhein-Westfalen",
    "wof:name":"Hugo Averdung",
    "wof:placetype":"venue"
},
  "geometry": {"coordinates":[7.100642,51.607117],"type":"Point"}
}