{
  "type": "Feature",
  "properties": {
    "iso:country":"DE",
    "sg:address":"Postfach 1352",
    "sg:city":"D\u00fclmen",
    "sg:phone":"+49 2594/4021",
    "sg:postcode":"48234",
    "sg:province":"Nordrhein-Westfalen",
    "wof:name":"Strickwarenfabrik Haltern Gmbh",
    "wof:placetype":"venue"
},
  "geometry": {"coordinates":[7.27784,51.828579],"type":"Point"}
}