{
  "type": "Feature",
  "properties": {
    "iso:country":"DE",
    "sg:address":"Gro\u00dfer Hillen 4",
    "sg:city":"Hannover",
    "sg:phone":"+49 511/512590",
    "sg:postcode":"30559",
    "sg:province":"Niedersachsen",
    "wof:name":"Kosmetikstudio Borchert",
    "wof:placetype":"venue"
},
  "geometry": {"coordinates":[9.826787,52.36121],"type":"Point"}
}