{
  "type": "Feature",
  "properties": {
    "iso:country":"DE",
    "sg:address":"Th\u00fcringer Str. 14",
    "sg:city":"Freiburg",
    "sg:phone":"+49 761/64168",
    "sg:postcode":"79117",
    "sg:province":"Baden-W\u00fcrttemberg",
    "wof:name":"Heinrich Venter Architekt Gmbh",
    "wof:placetype":"venue"
},
  "geometry": {"coordinates":[7.901818,47.97868],"type":"Point"}
}