{
  "type": "Feature",
  "properties": {
    "iso:country":"DE",
    "sg:address":"Im Pfl\u00e4sterle 59",
    "sg:city":"Sindelfingen",
    "sg:phone":"+49 7031/33966",
    "sg:postcode":"71069",
    "sg:province":"Baden-W\u00fcrttemberg",
    "wof:name":"Kissling Sondertechnik Gmbh",
    "wof:placetype":"venue"
},
  "geometry": {"coordinates":[8.9861440659,48.7308540344],"type":"Point"}
}