{
  "type": "Feature",
  "properties": {
    "iso:country":"DE",
    "sg:address":"Zum Schienerberg 3",
    "sg:city":"\u00d6hningen",
    "sg:postcode":"78337",
    "sg:province":"Baden-W\u00fcrttemberg",
    "wof:name":"Kr\u00e4uterhexle Productions E. K.",
    "wof:placetype":"venue"
},
  "geometry": {"coordinates":[8.931019,47.660362],"type":"Point"}
}