{
  "type": "Feature",
  "properties": {
    "iso:country":"DE",
    "sg:address":"Am Sch\u00e4ferstein 6 a",
    "sg:city":"G\u00f6ttingen",
    "sg:phone":"+49 551/505990",
    "sg:postcode":"37079",
    "sg:province":"Niedersachsen",
    "wof:name":"G. Und M. Nowak",
    "wof:placetype":"venue"
},
  "geometry": {"coordinates":[9.8702745438,51.5486755371],"type":"Point"}
}