{
  "type": "Feature",
  "properties": {
    "iso:country":"DE",
    "sg:address":"Ihmeplatz 7",
    "sg:city":"Hannover",
    "sg:postcode":"30449",
    "sg:province":"Niedersachsen",
    "wof:name":"Aldi Gmbh & Co. Kg",
    "wof:placetype":"venue"
},
  "geometry": {"coordinates":[9.7167129517,52.3719749451],"type":"Point"}
}