{
  "type": "Feature",
  "properties": {
    "iso:country":"DE",
    "sg:address":"Krankenhausstr. 12",
    "sg:city":"Dachau",
    "sg:phone":"+49 8131/79849",
    "sg:postcode":"85221",
    "sg:province":"Bayern",
    "wof:name":"Wurftauben-club Dachau E. V. Peter Zinstag",
    "wof:placetype":"venue"
},
  "geometry": {"coordinates":[11.431429863,48.2642326355],"type":"Point"}
}