{
  "type": "Feature",
  "properties": {
    "iso:country":"DE",
    "sg:address":"Schmiedestr. 1",
    "sg:city":"Bad Wildungen",
    "sg:phone":"+49 5621/2488",
    "sg:postcode":"34537",
    "sg:province":"Hessen",
    "wof:name":"Jochen Oschmann",
    "wof:placetype":"venue"
},
  "geometry": {"coordinates":[9.126368,51.120678],"type":"Point"}
}