{
  "type": "Feature",
  "properties": {
    "iso:country":"DE",
    "sg:address":"Lindenfeld 15",
    "sg:city":"Melle",
    "sg:phone":"+49 5422/6442",
    "sg:postcode":"49328",
    "sg:province":"Niedersachsen",
    "wof:name":"Helmut Niermann",
    "wof:placetype":"venue"
},
  "geometry": {"coordinates":[8.40259,52.179283],"type":"Point"}
}