{
  "type": "Feature",
  "properties": {
    "iso:country":"DE",
    "sg:address":"Holbeinstr. 16",
    "sg:city":"Bremen",
    "sg:phone":"+49 421/76355",
    "sg:postcode":"28209",
    "sg:province":"Bremen",
    "wof:name":"Zundel Und Schwenke Ergotherapeutische Praxis",
    "wof:placetype":"venue"
},
  "geometry": {"coordinates":[8.833213,53.085003],"type":"Point"}
}