{
  "type": "Feature",
  "properties": {
    "iso:country":"DE",
    "sg:address":"Ernst-Ludwig-Str. 3",
    "sg:city":"Darmstadt",
    "sg:phone":"+49 6151/293397",
    "sg:postcode":"64283",
    "sg:province":"Hessen",
    "wof:name":"Jansen-kindermoden Gmbh",
    "wof:placetype":"venue"
},
  "geometry": {"coordinates":[8.653512,49.872574],"type":"Point"}
}