{
  "type": "Feature",
  "properties": {
    "iso:country":"DE",
    "sg:address":"Alter Postweg 101",
    "sg:city":"Augsburg",
    "sg:phone":"+49 821/590010",
    "sg:postcode":"86159",
    "sg:province":"Bayern",
    "wof:name":"Bsa Garne Br\u00fcder Schaefer Gmbh",
    "wof:placetype":"venue"
},
  "geometry": {"coordinates":[10.8992872238,48.3380432129],"type":"Point"}
}