{
  "type": "Feature",
  "properties": {
    "iso:country":"DE",
    "sg:address":"Hansastr. 18",
    "sg:city":"Ahlen",
    "sg:phone":"+49 2382/701505",
    "sg:postcode":"59229",
    "sg:province":"Nordrhein-Westfalen",
    "wof:name":"A. Yavuz",
    "wof:placetype":"venue"
},
  "geometry": {"coordinates":[7.9084591866,51.7582244873],"type":"Point"}
}