{
  "type": "Feature",
  "properties": {
    "iso:country":"DE",
    "sg:address":"R\u00fcbker Str. 9",
    "sg:city":"Buxtehude",
    "sg:phone":"+49 4161/641585",
    "sg:postcode":"21614",
    "sg:province":"Niedersachsen",
    "wof:name":"Ulrich Felgentreu",
    "wof:placetype":"venue"
},
  "geometry": {"coordinates":[9.7169799805,53.4742088318],"type":"Point"}
}