{
  "type": "Feature",
  "properties": {
    "iso:country":"DE",
    "sg:address":"Salinstr. 10 B",
    "sg:city":"Rosenheim",
    "sg:postcode":"83022",
    "sg:province":"Bayern",
    "wof:name":"Mlp Finanzdienstleistungen Ag",
    "wof:placetype":"venue"
},
  "geometry": {"coordinates":[12.1232271194,47.8523101807],"type":"Point"}
}