{
  "type": "Feature",
  "properties": {
    "iso:country":"DE",
    "sg:address":"Berghofstr. 1",
    "sg:city":"Bovenden",
    "sg:phone":"+49 5593/8626",
    "sg:postcode":"37120",
    "sg:province":"Niedersachsen",
    "wof:name":"Hans-ulrich H\u00fcbner Ingenieur",
    "wof:placetype":"venue"
},
  "geometry": {"coordinates":[9.8303,51.582069],"type":"Point"}
}