{
  "type": "Feature",
  "properties": {
    "iso:country":"DE",
    "sg:address":"Bahnhofstr. 21",
    "sg:city":"Saulheim",
    "sg:phone":"+49 6732/1084",
    "sg:postcode":"55291",
    "sg:province":"Rheinland-Pfalz",
    "wof:name":"Institut F\u00fcr Handelsmarketing Dr. Walldorf Gmbh",
    "wof:placetype":"venue"
},
  "geometry": {"coordinates":[8.1520872116,49.8735580444],"type":"Point"}
}