{
  "type": "Feature",
  "properties": {
    "iso:country":"DE",
    "sg:address":"Wiesengrund 2",
    "sg:city":"Meine",
    "sg:postcode":"38527",
    "sg:province":"Niedersachsen",
    "wof:name":"Pourelle",
    "wof:placetype":"venue"
},
  "geometry": {"coordinates":[10.5882940292,52.3810462952],"type":"Point"}
}