{
  "type": "Feature",
  "properties": {
    "iso:country":"DE",
    "sg:address":"Konrad-Zuse-Str. 1",
    "sg:city":"Roggentin",
    "sg:phone":"+49 4938/125240",
    "sg:postcode":"18184",
    "sg:province":"Mecklenburg-Vorpommern",
    "wof:name":"Service F\u00dcr Informationsverarbeitung Ag (siv)",
    "wof:placetype":"venue"
},
  "geometry": {"coordinates":[12.1967983246,54.0763168335],"type":"Point"}
}