{
  "type": "Feature",
  "properties": {
    "iso:country":"DE",
    "sg:address":"Am Neumarkt 30",
    "sg:city":"Hamburg",
    "sg:postcode":"22041",
    "sg:province":"Hamburg",
    "wof:name":"Upcd Europe Gmbh",
    "wof:placetype":"venue"
},
  "geometry": {"coordinates":[10.0893268585,53.5751266479],"type":"Point"}
}