{
  "type": "Feature",
  "properties": {
    "iso:country":"DE",
    "sg:address":"Virchowstr. 9",
    "sg:city":"Essen",
    "sg:phone":"+49 201/8745414",
    "sg:postcode":"45147",
    "sg:province":"Nordrhein-Westfalen",
    "wof:name":"Arbeitsgemeinschaft Flughafen Und \u00d6kologie Essen",
    "wof:placetype":"venue"
},
  "geometry": {"coordinates":[6.9953241348,51.4390716553],"type":"Point"}
}