{
  "type": "Feature",
  "properties": {
    "iso:country":"DE",
    "sg:address":"Lonetalstr. 6",
    "sg:city":"Breitingen",
    "sg:phone":"+49 7340/476",
    "sg:postcode":"89183",
    "sg:province":"Baden-W\u00fcrttemberg",
    "wof:name":"Michael H\u00e4ge",
    "wof:placetype":"venue"
},
  "geometry": {"coordinates":[9.992564,48.516575],"type":"Point"}
}