{
  "type": "Feature",
  "properties": {
    "iso:country":"DE",
    "sg:address":"Werwolf 3",
    "sg:city":"Solingen",
    "sg:phone":"+49 212/17004",
    "sg:postcode":"42651",
    "sg:province":"Nordrhein-Westfalen",
    "wof:name":"C. Wittebrock-rauh",
    "wof:placetype":"venue"
},
  "geometry": {"coordinates":[7.086648,51.168594],"type":"Point"}
}