{
  "type": "Feature",
  "properties": {
    "iso:country":"DE",
    "sg:address":"N\u00fcrnberger Str. 106",
    "sg:city":"Kassel",
    "sg:phone":"+49 561/570250",
    "sg:postcode":"34123",
    "sg:province":"Hessen",
    "wof:name":"Hotel Froschk\u00f6nig",
    "wof:placetype":"venue"
},
  "geometry": {"coordinates":[9.5121097565,51.2943687439],"type":"Point"}
}