{
  "type": "Feature",
  "properties": {
    "iso:country":"DE",
    "sg:address":"Pfarrweg 12",
    "sg:city":"Brand",
    "sg:phone":"+49 9236/267",
    "sg:postcode":"95682",
    "sg:province":"Bayern",
    "wof:name":"Kath. Pfarramt Herz Jesu",
    "wof:placetype":"venue"
},
  "geometry": {"coordinates":[11.9094829559,49.9607658386],"type":"Point"}
}