{
  "type": "Feature",
  "properties": {
    "iso:country":"DE",
    "sg:address":"Wormser Str. 16",
    "sg:city":"Dresden",
    "sg:phone":"+49 351/3360412",
    "sg:postcode":"01309",
    "sg:province":"Sachsen",
    "wof:name":"Dr. Med. Gabriele Kr\u00fcger \u00c4rztin F\u00fcr Allgemeinmedizin",
    "wof:placetype":"venue"
},
  "geometry": {"coordinates":[13.7787971497,51.0492324829],"type":"Point"}
}