{
  "type": "Feature",
  "properties": {
    "iso:country":"DE",
    "sg:address":"Glasmeisterstr. 26",
    "sg:city":"Potsdam",
    "sg:phone":"+49 331/707710",
    "sg:postcode":"14482",
    "sg:province":"Brandenburg",
    "wof:name":"Horst Winter",
    "wof:placetype":"venue"
},
  "geometry": {"coordinates":[13.0885696411,52.3926887512],"type":"Point"}
}