{
  "type": "Feature",
  "properties": {
    "iso:country":"DE",
    "sg:address":"Ludwigstr. 113",
    "sg:city":"Neu\u00f6tting",
    "sg:phone":"+49 8671/979186",
    "sg:postcode":"84524",
    "sg:province":"Bayern",
    "wof:name":"Eiscafe Veneto",
    "wof:placetype":"venue"
},
  "geometry": {"coordinates":[12.688742,48.240307],"type":"Point"}
}