{
  "type": "Feature",
  "properties": {
    "iso:country":"DE",
    "sg:address":"Chrysanthemenstr. 3",
    "sg:city":"Berlin",
    "sg:phone":"+49 30/4212867",
    "sg:postcode":"10407",
    "sg:province":"Berlin",
    "wof:name":"Arbeiterwohlfahrt Landesverband Berlin E. V.",
    "wof:placetype":"venue"
},
  "geometry": {"coordinates":[13.460217,52.53096],"type":"Point"}
}