{
  "type": "Feature",
  "properties": {
    "iso:country":"DE",
    "sg:address":"Berliner Str. 4 a",
    "sg:city":"Hohen Neuendorf",
    "sg:phone":"+49 3303/409639",
    "sg:postcode":"16540",
    "sg:province":"Brandenburg",
    "wof:name":"Ubicom Gesellschaft F\u00fcr Telekommunikation Mbh",
    "wof:placetype":"venue"
},
  "geometry": {"coordinates":[13.281979,52.668358],"type":"Point"}
}