{
  "type": "Feature",
  "properties": {
    "iso:country":"DE",
    "sg:address":"Dietzgenstr. 58",
    "sg:city":"Berlin",
    "sg:phone":"+49 30/4764613",
    "sg:postcode":"13156",
    "sg:province":"Berlin",
    "wof:name":"Horst Haseloff",
    "wof:placetype":"venue"
},
  "geometry": {"coordinates":[13.402759552,52.5859375],"type":"Point"}
}