{
  "type": "Feature",
  "properties": {
    "iso:country":"DE",
    "sg:address":"Osterstr. 33",
    "sg:city":"Hildesheim",
    "sg:phone":"+49 5121/17060",
    "sg:postcode":"31134",
    "sg:province":"Niedersachsen",
    "wof:name":"Schirmer Verlag Ohg",
    "wof:placetype":"venue"
},
  "geometry": {"coordinates":[9.954242,52.155991],"type":"Point"}
}