{
  "type": "Feature",
  "properties": {
    "iso:country":"DE",
    "sg:city":"Oberaudorf",
    "sg:phone":"+49 8033/2386",
    "sg:postcode":"83080",
    "sg:province":"Bayern",
    "wof:name":"Camping Luegsteinsee",
    "wof:placetype":"venue"
},
  "geometry": {"coordinates":[12.17211,47.648014],"type":"Point"}
}