{
  "type": "Feature",
  "properties": {
    "iso:country":"DE",
    "sg:address":"Am Flugplatz 12",
    "sg:city":"Worms",
    "sg:phone":"+49 6241/207333",
    "sg:postcode":"67547",
    "sg:province":"Rheinland-Pfalz",
    "wof:name":"Asw Aero-service Worms Gmbh",
    "wof:placetype":"venue"
},
  "geometry": {"coordinates":[8.3664503098,49.6051101685],"type":"Point"}
}