{
  "type": "Feature",
  "properties": {
    "iso:country":"DE",
    "sg:address":"M\u00fcnsterplatz 11",
    "sg:city":"Freiburg",
    "sg:phone":"+49 761/32565",
    "sg:postcode":"79098",
    "sg:province":"Baden-W\u00fcrttemberg",
    "wof:name":"Kornhaus Cafe",
    "wof:placetype":"venue"
},
  "geometry": {"coordinates":[7.852549,47.996117],"type":"Point"}
}