{
  "type": "Feature",
  "properties": {
    "iso:country":"DE",
    "sg:address":"Fr\u00f6belstr. 7",
    "sg:city":"Troisdorf",
    "sg:phone":"+49 2241/946677",
    "sg:postcode":"53842",
    "sg:province":"Nordrhein-Westfalen",
    "wof:name":"Reinhold Becker Steuerberater",
    "wof:placetype":"venue"
},
  "geometry": {"coordinates":[7.1354589462,50.8131370544],"type":"Point"}
}