{
  "type": "Feature",
  "properties": {
    "iso:country":"DE",
    "sg:address":"Brahmsstr. 1",
    "sg:city":"Bremen",
    "sg:phone":"+49 421/3491770",
    "sg:postcode":"28209",
    "sg:province":"Bremen",
    "wof:name":"M. Bamberger Immobilienmakler",
    "wof:placetype":"venue"
},
  "geometry": {"coordinates":[8.8327932358,53.0842247009],"type":"Point"}
}