{
  "type": "Feature",
  "properties": {
    "iso:country":"DE",
    "sg:address":"Im Teller 7",
    "sg:city":"Frankfurt",
    "sg:phone":"+49 69/652505",
    "sg:postcode":"60599",
    "sg:province":"Hessen",
    "wof:name":"Otto Gatzke",
    "wof:placetype":"venue"
},
  "geometry": {"coordinates":[8.737463,50.09444],"type":"Point"}
}