{
  "type": "Feature",
  "properties": {
    "iso:country":"DE",
    "sg:address":"Saarburger Str. 24a",
    "sg:city":"Trassem",
    "sg:phone":"+49 6581/3640",
    "sg:postcode":"54441",
    "sg:province":"Rheinland-Pfalz",
    "wof:name":"Udo Baumann Ingenieur",
    "wof:placetype":"venue"
},
  "geometry": {"coordinates":[6.526561,49.580345],"type":"Point"}
}