{
  "type": "Feature",
  "properties": {
    "iso:country":"DE",
    "sg:address":"Mattentwiete 1",
    "sg:city":"Hamburg",
    "sg:postcode":"20457",
    "sg:province":"Hamburg",
    "wof:name":"Asni Gmbh",
    "wof:placetype":"venue"
},
  "geometry": {"coordinates":[9.989534,53.545883],"type":"Point"}
}