{
  "type": "Feature",
  "properties": {
    "iso:country":"DE",
    "sg:address":"Herderstr. 6",
    "sg:city":"Metzingen",
    "sg:phone":"+49 7123/4417",
    "sg:postcode":"72555",
    "sg:province":"Baden-W\u00fcrttemberg",
    "wof:name":"Otto Voelter",
    "wof:placetype":"venue"
},
  "geometry": {"coordinates":[9.2968921661,48.5349884033],"type":"Point"}
}