{
  "type": "Feature",
  "properties": {
    "iso:country":"DE",
    "sg:address":"Bahnhofstr. 6",
    "sg:city":"Flacht",
    "sg:phone":"+49 6432/6624",
    "sg:postcode":"65558",
    "sg:province":"Rheinland-Pfalz",
    "wof:name":"Fleischhandel Kowalke Gmbh",
    "wof:placetype":"venue"
},
  "geometry": {"coordinates":[8.0508060455,50.343334198],"type":"Point"}
}