{
  "type": "Feature",
  "properties": {
    "iso:country":"DE",
    "sg:address":"Frankfurter Str.",
    "sg:city":"Kronberg",
    "sg:phone":"+49 6173/7050",
    "sg:postcode":"61476",
    "sg:province":"Hessen",
    "wof:name":"Jaguar Deutschland Gmbh",
    "wof:placetype":"venue"
},
  "geometry": {"coordinates":[8.5233869553,50.1741828918],"type":"Point"}
}