{
  "type": "Feature",
  "properties": {
    "iso:country":"DE",
    "sg:address":"Georgenstr. 50",
    "sg:city":"Amberg",
    "sg:phone":"+49 9621/496568",
    "sg:postcode":"92224",
    "sg:province":"Bayern",
    "wof:name":"Sgo-system-balkon Gmbh",
    "wof:placetype":"venue"
},
  "geometry": {"coordinates":[11.853398,49.444321],"type":"Point"}
}