{
  "type": "Feature",
  "properties": {
    "iso:country":"DE",
    "sg:address":"Rheinallee 41",
    "sg:city":"Mainz",
    "sg:postcode":"55118",
    "sg:province":"Rheinland-Pfalz",
    "wof:name":"Wfm Wasserforschung Mainz Gmbh",
    "wof:placetype":"venue"
},
  "geometry": {"coordinates":[8.2640094757,50.0106582642],"type":"Point"}
}