{
  "type": "Feature",
  "properties": {
    "iso:country":"DE",
    "sg:address":"Kasseler Weg 5",
    "sg:city":"Michelstadt",
    "sg:phone":"+49 6061/73313",
    "sg:postcode":"64720",
    "sg:province":"Hessen",
    "wof:name":"M. Kredel Gmbh",
    "wof:placetype":"venue"
},
  "geometry": {"coordinates":[9.0109872818,49.6665115356],"type":"Point"}
}