{
  "type": "Feature",
  "properties": {
    "iso:country":"DE",
    "sg:address":"Nikolaistr. 44",
    "sg:city":"Wei\u00dfenfels",
    "sg:postcode":"06667",
    "sg:province":"Sachsen-Anhalt",
    "wof:name":"Kommunikations- Und Computertechnik",
    "wof:placetype":"venue"
},
  "geometry": {"coordinates":[11.9677047729,51.1986045837],"type":"Point"}
}