{
  "type": "Feature",
  "properties": {
    "iso:country":"DE",
    "sg:address":"In der Grobach 22",
    "sg:city":"Florstadt",
    "sg:phone":"+49 6041/9680",
    "sg:postcode":"61197",
    "sg:province":"Hessen",
    "wof:name":"Cos Memory Ag",
    "wof:placetype":"venue"
},
  "geometry": {"coordinates":[8.930970192,50.3296508789],"type":"Point"}
}