{
  "type": "Feature",
  "properties": {
    "iso:country":"DE",
    "sg:address":"Jahnweg 3",
    "sg:city":"Leipzig",
    "sg:phone":"+49 341/2511947",
    "sg:postcode":"04319",
    "sg:province":"Sachsen",
    "wof:name":"Baumann Kranverleih Gmbh",
    "wof:placetype":"venue"
},
  "geometry": {"coordinates":[12.4989147186,51.3453636169],"type":"Point"}
}