{
  "type": "Feature",
  "properties": {
    "iso:country":"DE",
    "sg:address":"Engelfanger Str. 19",
    "sg:city":"P\u00fcttlingen",
    "sg:phone":"+49 6806/994900",
    "sg:postcode":"66346",
    "sg:province":"Saarland",
    "wof:name":"Rainer Kiefer Informatik Gmbh",
    "wof:placetype":"venue"
},
  "geometry": {"coordinates":[6.898332119,49.2971687317],"type":"Point"}
}