{
  "type": "Feature",
  "properties": {
    "iso:country":"DE",
    "sg:address":"Bleistr. 33",
    "sg:city":"Erftstadt",
    "sg:phone":"+49 2235/71250",
    "sg:postcode":"50374",
    "sg:province":"Nordrhein-Westfalen",
    "wof:name":"Heinrich Zens",
    "wof:placetype":"venue"
},
  "geometry": {"coordinates":[6.767604,50.733639],"type":"Point"}
}