{
  "type": "Feature",
  "properties": {
    "iso:country":"DE",
    "sg:address":"Hans-Sachs-Str. 3",
    "sg:city":"M\u00fcnchen",
    "sg:phone":"+49 89/266521",
    "sg:postcode":"80469",
    "sg:province":"Bayern",
    "wof:name":"Pavao Zlodi",
    "wof:placetype":"venue"
},
  "geometry": {"coordinates":[11.570359,48.130466],"type":"Point"}
}