{
  "type": "Feature",
  "properties": {
    "iso:country":"DE",
    "sg:address":"St.-Georgen-Str. 39",
    "sg:city":"Pforzheim",
    "sg:phone":"+49 7231/61883",
    "sg:postcode":"75175",
    "sg:province":"Baden-W\u00fcrttemberg",
    "wof:name":"J. Binder Vergn\u00fcgungsst\u00e4tte",
    "wof:placetype":"venue"
},
  "geometry": {"coordinates":[8.709972,48.886402],"type":"Point"}
}