{
  "type": "Feature",
  "properties": {
    "iso:country":"DE",
    "sg:address":"Am Rei\u00dfturm 15",
    "sg:city":"N\u00f6rdlingen",
    "sg:phone":"+49 9081/87855",
    "sg:postcode":"86720",
    "sg:province":"Bayern",
    "wof:name":"Maria Sch\u00f6nbrodt Krankengymnastin",
    "wof:placetype":"venue"
},
  "geometry": {"coordinates":[10.495171,48.851372],"type":"Point"}
}