{
  "type": "Feature",
  "properties": {
    "iso:country":"DE",
    "sg:address":"Gewerbestr. 9",
    "sg:city":"Ilsede",
    "sg:postcode":"31241",
    "sg:province":"Niedersachsen",
    "wof:name":"Media Complex Gmbh",
    "wof:placetype":"venue"
},
  "geometry": {"coordinates":[10.219281,52.273083],"type":"Point"}
}