{
  "type": "Feature",
  "properties": {
    "iso:country":"DE",
    "sg:address":"Im Kolk 3",
    "sg:city":"Gescher",
    "sg:phone":"+49 2542/98833",
    "sg:postcode":"48712",
    "sg:province":"Nordrhein-Westfalen",
    "wof:name":"Studio_s Mediengestaltung",
    "wof:placetype":"venue"
},
  "geometry": {"coordinates":[7.014743,51.952274],"type":"Point"}
}