{
  "type": "Feature",
  "properties": {
    "iso:country":"DE",
    "sg:address":"Norderstedter Str. 17 a",
    "sg:city":"Henstedt-Ulzburg",
    "sg:postcode":"24558",
    "sg:province":"Schleswig-Holstein",
    "wof:name":"Verwaltungsgesellschaft Esc Edv-service U. Consulting Gmbh",
    "wof:placetype":"venue"
},
  "geometry": {"coordinates":[9.9961919785,53.7544898987],"type":"Point"}
}