{
  "type": "Feature",
  "properties": {
    "iso:country":"DE",
    "sg:address":"Paulusheim",
    "sg:city":"Schw\u00e4bisch Gm\u00fcnd",
    "sg:phone":"+49 7175/5711",
    "sg:postcode":"73527",
    "sg:province":"Baden-W\u00fcrttemberg",
    "wof:name":"Fehrle",
    "wof:placetype":"venue"
},
  "geometry": {"coordinates":[9.84056,48.848721],"type":"Point"}
}