{
  "type": "Feature",
  "properties": {
    "iso:country":"DE",
    "sg:address":"Weidenweg 90",
    "sg:city":"Kalkar",
    "sg:postcode":"47546",
    "sg:province":"Nordrhein-Westfalen",
    "wof:name":"Reitteam Mith\u00f6fer",
    "wof:placetype":"venue"
},
  "geometry": {"coordinates":[6.270728,51.802372],"type":"Point"}
}