{
  "type": "Feature",
  "properties": {
    "iso:country":"DE",
    "sg:address":"Rodheimer Str. 15",
    "sg:city":"Rosbach",
    "sg:phone":"+49 6003/8033",
    "sg:postcode":"61191",
    "sg:province":"Hessen",
    "wof:name":"Hans Fischer",
    "wof:placetype":"venue"
},
  "geometry": {"coordinates":[8.698261,50.298771],"type":"Point"}
}