{
  "type": "Feature",
  "properties": {
    "iso:country":"DE",
    "sg:address":"Rheinstr. 3",
    "sg:city":"Walluf",
    "sg:phone":"+49 6123/71077",
    "sg:postcode":"65396",
    "sg:province":"Hessen",
    "wof:name":"Hotel Zum Neuen Schwan Hannelore Becker-otte",
    "wof:placetype":"venue"
},
  "geometry": {"coordinates":[8.1606578827,50.034034729],"type":"Point"}
}