{
  "type": "Feature",
  "properties": {
    "iso:country":"DE",
    "sg:city":"Hemau",
    "sg:postcode":"93155",
    "sg:province":"Bayern",
    "wof:name":"Datentechnik H\u00f6llriegl",
    "wof:placetype":"venue"
},
  "geometry": {"coordinates":[11.782335,49.052094],"type":"Point"}
}