{
  "type": "Feature",
  "properties": {
    "iso:country":"DE",
    "sg:address":"S\u00fcdstrand",
    "sg:city":"Gro\u00dfenbrode",
    "sg:phone":"+49 4367/8044",
    "sg:postcode":"23775",
    "sg:province":"Schleswig-Holstein",
    "wof:name":"Strandhotel Dorina",
    "wof:placetype":"venue"
},
  "geometry": {"coordinates":[11.0853176117,54.3561706543],"type":"Point"}
}