{
  "type": "Feature",
  "properties": {
    "iso:country":"DE",
    "sg:address":"Markomannenstr. 11",
    "sg:city":"Leinfelden-Echterdingen",
    "sg:phone":"+49 711/755054",
    "sg:postcode":"70771",
    "sg:province":"Baden-W\u00fcrttemberg",
    "wof:name":"Combauplan Ges. F\u00fcr Computer- Unterst\u00fctzte Bauplanung Und",
    "wof:placetype":"venue"
},
  "geometry": {"coordinates":[9.145622,48.692562],"type":"Point"}
}