{
  "type": "Feature",
  "properties": {
    "iso:country":"DE",
    "sg:address":"Hermann-Oberth-Str. 2",
    "sg:city":"Herdecke",
    "sg:phone":"+49 2330/2632",
    "sg:postcode":"58313",
    "sg:province":"Nordrhein-Westfalen",
    "wof:name":"Anneliese Klauke Steuerberater",
    "wof:placetype":"venue"
},
  "geometry": {"coordinates":[7.440721035,51.4029884338],"type":"Point"}
}