{
  "type": "Feature",
  "properties": {
    "iso:country":"DE",
    "sg:city":"Goldscheuer",
    "sg:phone":"+49 4978/54307",
    "sg:postcode":"77694",
    "sg:province":"Baden-W\u00fcrttemberg",
    "wof:name":"Sparkasse Hanauerland",
    "wof:placetype":"venue"
},
  "geometry": {"coordinates":[7.819111,48.513088],"type":"Point"}
}