{
  "type": "Feature",
  "properties": {
    "iso:country":"DE",
    "sg:address":"Dorfstr. 14",
    "sg:city":"Dahlum",
    "sg:phone":"+49 5332/98940",
    "sg:postcode":"38170",
    "sg:province":"Niedersachsen",
    "wof:name":"Ramblas Gmbh",
    "wof:placetype":"venue"
},
  "geometry": {"coordinates":[10.8435211182,52.1227111816],"type":"Point"}
}