{
  "type": "Feature",
  "properties": {
    "iso:country":"DE",
    "sg:address":"Alt H\u00fcsten 32",
    "sg:city":"Arnsberg",
    "sg:phone":"+49 2932/32221",
    "sg:postcode":"59759",
    "sg:province":"Nordrhein-Westfalen",
    "wof:name":"Hans Esser",
    "wof:placetype":"venue"
},
  "geometry": {"coordinates":[7.992099762,51.4233512878],"type":"Point"}
}