{
  "type": "Feature",
  "properties": {
    "iso:country":"DE",
    "sg:address":"Unterhainstr. 15",
    "sg:city":"Bad Br\u00fcckenau",
    "sg:phone":"+49 9741/2452",
    "sg:postcode":"97769",
    "sg:province":"Bayern",
    "wof:name":"Hotel-restaurant Sonne",
    "wof:placetype":"venue"
},
  "geometry": {"coordinates":[9.7909345627,50.3095397949],"type":"Point"}
}