{
  "type": "Feature",
  "properties": {
    "iso:country":"DE",
    "sg:address":"Hochstr. 107",
    "sg:city":"Heinsberg",
    "sg:phone":"+49 2452/21046",
    "sg:postcode":"52525",
    "sg:province":"Nordrhein-Westfalen",
    "wof:name":"Marien-apotheke",
    "wof:placetype":"venue"
},
  "geometry": {"coordinates":[6.095212,51.062431],"type":"Point"}
}