{
  "type": "Feature",
  "properties": {
    "iso:country":"DE",
    "sg:address":"Lindenstr. 18",
    "sg:city":"Seevetal",
    "sg:phone":"+49 4105/3467",
    "sg:postcode":"21218",
    "sg:province":"Niedersachsen",
    "wof:name":"Restaurant Heidbergklause",
    "wof:placetype":"venue"
},
  "geometry": {"coordinates":[9.960943222,53.4094963074],"type":"Point"}
}