{
  "type": "Feature",
  "properties": {
    "iso:country":"DE",
    "sg:address":"Dorfstr. 22b",
    "sg:city":"Schwerte",
    "sg:phone":"+49 2304/941100",
    "sg:postcode":"58239",
    "sg:province":"Nordrhein-Westfalen",
    "wof:name":"Schafst\u00e4dt Gmbh",
    "wof:placetype":"venue"
},
  "geometry": {"coordinates":[7.609936,51.452957],"type":"Point"}
}