{
  "type": "Feature",
  "properties": {
    "iso:country":"DE",
    "sg:address":"R\u00f6merstr. 38a",
    "sg:city":"Duisburg",
    "sg:phone":"+49 203/700345",
    "sg:postcode":"47249",
    "sg:province":"Nordrhein-Westfalen",
    "wof:name":"Friedrich Hartfil",
    "wof:placetype":"venue"
},
  "geometry": {"coordinates":[6.7542991638,51.3870048523],"type":"Point"}
}