{
  "type": "Feature",
  "properties": {
    "iso:country":"DE",
    "sg:address":"Gustav-Adolf-Str. 48",
    "sg:city":"Stralsund",
    "sg:phone":"+49 3831/394094",
    "sg:postcode":"18435",
    "sg:province":"Mecklenburg-Vorpommern",
    "wof:name":"Dr. Med. Elisabeth Stangel",
    "wof:placetype":"venue"
},
  "geometry": {"coordinates":[13.073496,54.319893],"type":"Point"}
}