{
  "type": "Feature",
  "properties": {
    "iso:country":"DE",
    "sg:address":"Jagdsteig 17",
    "sg:city":"Mei\u00dfen",
    "sg:phone":"+49 3521/733638",
    "sg:postcode":"01662",
    "sg:province":"Sachsen",
    "wof:name":"Peter Nitzschner",
    "wof:placetype":"venue"
},
  "geometry": {"coordinates":[13.502546,51.150707],"type":"Point"}
}