{
  "type": "Feature",
  "properties": {
    "iso:country":"DE",
    "sg:address":"Hechtgasse 2",
    "sg:city":"Tuttlingen",
    "sg:phone":"+49 7462/6527",
    "sg:postcode":"78532",
    "sg:province":"Baden-W\u00fcrttemberg",
    "wof:name":"R. Mayer Heissmangel",
    "wof:placetype":"venue"
},
  "geometry": {"coordinates":[8.7649374008,47.95936203],"type":"Point"}
}