{
  "type": "Feature",
  "properties": {
    "iso:country":"DE",
    "sg:address":"Harthauser Str. 101",
    "sg:city":"M\u00fcnchen",
    "sg:phone":"+49 89/64209561",
    "sg:postcode":"81545",
    "sg:province":"Bayern",
    "wof:name":"Christine Ostwald Rechtsanw\u00e4ltin",
    "wof:placetype":"venue"
},
  "geometry": {"coordinates":[11.5466156006,48.0810813904],"type":"Point"}
}