{
  "type": "Feature",
  "properties": {
    "iso:country":"DE",
    "sg:address":"Dorfstr. 13",
    "sg:city":"D\u00f6bern",
    "sg:phone":"+49 35600/6461",
    "sg:postcode":"03159",
    "sg:province":"Brandenburg",
    "wof:name":"Lindenhof",
    "wof:placetype":"venue"
},
  "geometry": {"coordinates":[14.6172132492,51.6038780212],"type":"Point"}
}