{
  "type": "Feature",
  "properties": {
    "iso:country":"DE",
    "sg:address":"K\u00e4the-Kollwitz-Str. 1",
    "sg:city":"Bernburg",
    "sg:phone":"+49 3471/373358",
    "sg:postcode":"06406",
    "sg:province":"Sachsen-Anhalt",
    "wof:name":"U. Eggert",
    "wof:placetype":"venue"
},
  "geometry": {"coordinates":[11.740112,51.794827],"type":"Point"}
}