{
  "type": "Feature",
  "properties": {
    "iso:country":"DE",
    "sg:address":"Hauptstr. 34",
    "sg:city":"Bad Wimpfen",
    "sg:phone":"+49 7063/303",
    "sg:postcode":"74206",
    "sg:province":"Baden-W\u00fcrttemberg",
    "wof:name":"Hohenstaufenpfalz",
    "wof:placetype":"venue"
},
  "geometry": {"coordinates":[9.1632442474,49.2295761108],"type":"Point"}
}