{
  "type": "Feature",
  "properties": {
    "iso:country":"DE",
    "sg:address":"Schuhstr. 1",
    "sg:city":"Kirchheim",
    "sg:phone":"+49 7021/44559",
    "sg:postcode":"73230",
    "sg:province":"Baden-W\u00fcrttemberg",
    "wof:name":"Klaus Moosmann",
    "wof:placetype":"venue"
},
  "geometry": {"coordinates":[9.4526357651,48.6481285095],"type":"Point"}
}