{
  "type": "Feature",
  "properties": {
    "iso:country":"DE",
    "sg:address":"Ettlinger Str. 5a",
    "sg:city":"Karlsruhe",
    "sg:phone":"+49 721/931010",
    "sg:postcode":"76137",
    "sg:province":"Baden-W\u00fcrttemberg",
    "wof:name":"Volksf\u00fcrsorge Deutsche Lebensversicherung Ag",
    "wof:placetype":"venue"
},
  "geometry": {"coordinates":[8.403499,49.002663],"type":"Point"}
}