{
  "type": "Feature",
  "properties": {
    "iso:country":"DE",
    "sg:address":"Bahnhofstr. 83",
    "sg:city":"N\u00fcrnberg",
    "sg:phone":"+49 911/472458",
    "sg:postcode":"90402",
    "sg:province":"Bayern",
    "wof:name":"Rosemarie Rosenthal-weber Heilpraktikerin",
    "wof:placetype":"venue"
},
  "geometry": {"coordinates":[11.0952396393,49.4486274719],"type":"Point"}
}