{
  "type": "Feature",
  "properties": {
    "iso:country":"DE",
    "sg:address":"Vogelh\u00fcttendeich 51",
    "sg:city":"Hamburg",
    "sg:phone":"+49 40/758361",
    "sg:postcode":"21107",
    "sg:province":"Hamburg",
    "wof:name":"Radio Simon Gmbh",
    "wof:placetype":"venue"
},
  "geometry": {"coordinates":[9.9872980118,53.5174980164],"type":"Point"}
}