{
  "type": "Feature",
  "properties": {
    "iso:country":"DE",
    "sg:address":"Voerder Str. 2a",
    "sg:city":"Hagen",
    "sg:phone":"+49 2331/41951",
    "sg:postcode":"58135",
    "sg:province":"Nordrhein-Westfalen",
    "wof:name":"Alstadt-apotheke",
    "wof:placetype":"venue"
},
  "geometry": {"coordinates":[7.423958,51.346786],"type":"Point"}
}