{
  "type": "Feature",
  "properties": {
    "iso:country":"DE",
    "sg:address":"Eschenauer Hauptstr. 14",
    "sg:city":"Eckental",
    "sg:phone":"+49 9126/278811",
    "sg:postcode":"90542",
    "sg:province":"Bayern",
    "wof:name":"Parf\u00fcmerie-drogerie Endre\u00df Ohg",
    "wof:placetype":"venue"
},
  "geometry": {"coordinates":[11.195947,49.574257],"type":"Point"}
}