{
  "type": "Feature",
  "properties": {
    "iso:country":"DE",
    "sg:address":"Friedrichstr. 15",
    "sg:city":"Kellinghusen",
    "sg:phone":"+49 4822/97000",
    "sg:postcode":"25548",
    "sg:province":"Schleswig-Holstein",
    "wof:name":"R. Und F. Schmalfeldt Gmbh",
    "wof:placetype":"venue"
},
  "geometry": {"coordinates":[9.728969,53.9464],"type":"Point"}
}