{
  "type": "Feature",
  "properties": {
    "iso:country":"DE",
    "sg:address":"Kaiserstr. 21",
    "sg:city":"W\u00fcrzburg",
    "sg:phone":"+49 931/14071",
    "sg:postcode":"97070",
    "sg:province":"Bayern",
    "wof:name":"Bayerische Vereinsbank Ag",
    "wof:placetype":"venue"
},
  "geometry": {"coordinates":[9.934177,49.79932],"type":"Point"}
}