{
  "type": "Feature",
  "properties": {
    "iso:country":"DE",
    "sg:address":"Am Hagelkreuz 54 a",
    "sg:city":"Erkelenz",
    "sg:phone":"+49 2431/6287",
    "sg:postcode":"41812",
    "sg:province":"Nordrhein-Westfalen",
    "wof:name":"Flachsklause",
    "wof:placetype":"venue"
},
  "geometry": {"coordinates":[6.3092718124,51.0735054016],"type":"Point"}
}