{
  "type": "Feature",
  "properties": {
    "iso:country":"DE",
    "sg:address":"Werner-V.-Siemens-Str. 3",
    "sg:city":"Schwarzenbruck",
    "sg:phone":"+49 9128/6090",
    "sg:postcode":"90592",
    "sg:province":"Bayern",
    "wof:name":"Brach + Moll K\u00c4lte- U. Klimatechnik Gmbh",
    "wof:placetype":"venue"
},
  "geometry": {"coordinates":[11.250372,49.360847],"type":"Point"}
}