{
  "type": "Feature",
  "properties": {
    "iso:country":"DE",
    "sg:address":"Bismarckstr. 77",
    "sg:city":"Wilhelmshaven",
    "sg:phone":"+49 4421/993353",
    "sg:postcode":"26384",
    "sg:province":"Niedersachsen",
    "wof:name":"A. Kallee",
    "wof:placetype":"venue"
},
  "geometry": {"coordinates":[8.126188,53.526421],"type":"Point"}
}