{
  "type": "Feature",
  "properties": {
    "iso:country":"DE",
    "sg:address":"Hauptstr. 358",
    "sg:city":"Idar-Oberstein",
    "sg:phone":"+49 6781/24127",
    "sg:postcode":"55743",
    "sg:province":"Rheinland-Pfalz",
    "wof:name":"Rosen-apotheke",
    "wof:placetype":"venue"
},
  "geometry": {"coordinates":[7.324168,49.702797],"type":"Point"}
}