{
  "type": "Feature",
  "properties": {
    "iso:country":"DE",
    "sg:address":"Freistuhl 3",
    "sg:city":"Dortmund",
    "sg:phone":"+49 231/182050",
    "sg:postcode":"44137",
    "sg:province":"Nordrhein-Westfalen",
    "wof:name":"Ergo Versicherungsgruppe Ag",
    "wof:placetype":"venue"
},
  "geometry": {"coordinates":[7.4621210098,51.5155677795],"type":"Point"}
}