{
  "type": "Feature",
  "properties": {
    "iso:country":"DE",
    "sg:address":"D\u00f6llinger Str. 38",
    "sg:city":"Hohenleipisch",
    "sg:phone":"+49 3533/164790",
    "sg:postcode":"04934",
    "sg:province":"Brandenburg",
    "wof:name":"Werbung Wunderlich",
    "wof:placetype":"venue"
},
  "geometry": {"coordinates":[13.562869,51.493301],"type":"Point"}
}