{
  "type": "Feature",
  "properties": {
    "iso:country":"DE",
    "sg:address":"Schulstr. 17",
    "sg:city":"Despetal",
    "sg:phone":"+49 5182/3241",
    "sg:postcode":"31035",
    "sg:province":"Niedersachsen",
    "wof:name":"Walter Kaune",
    "wof:placetype":"venue"
},
  "geometry": {"coordinates":[9.826903,52.090908],"type":"Point"}
}