{
  "type": "Feature",
  "properties": {
    "iso:country":"DE",
    "sg:address":"Amperstr. 2",
    "sg:city":"Grafrath",
    "sg:phone":"+49 8144/235",
    "sg:postcode":"82284",
    "sg:province":"Bayern",
    "wof:name":"Katholisches Pfarramt Mari\u00e4 Himmelfahrt",
    "wof:placetype":"venue"
},
  "geometry": {"coordinates":[11.160867691,48.1195869446],"type":"Point"}
}