{
  "type": "Feature",
  "properties": {
    "iso:country":"DE",
    "sg:address":"Am Kirchgarten",
    "sg:city":"Alzey",
    "sg:phone":"+49 6731/6286",
    "sg:postcode":"55232",
    "sg:province":"Rheinland-Pfalz",
    "wof:name":"R. M\u00fcller",
    "wof:placetype":"venue"
},
  "geometry": {"coordinates":[8.0841503143,49.7629470825],"type":"Point"}
}