{
  "type": "Feature",
  "properties": {
    "iso:country":"DE",
    "sg:address":"Westring 10",
    "sg:city":"Ennigerloh",
    "sg:phone":"+49 2524/930750",
    "sg:postcode":"59320",
    "sg:province":"Nordrhein-Westfalen",
    "wof:name":"Kompostwerk Warendorf Gmbh",
    "wof:placetype":"venue"
},
  "geometry": {"coordinates":[8.0165023804,51.8346328735],"type":"Point"}
}