{
  "type": "Feature",
  "properties": {
    "iso:country":"DE",
    "sg:address":"Waiblinger Str. 20",
    "sg:city":"Stuttgart",
    "sg:phone":"+49 711/552025",
    "sg:postcode":"70372",
    "sg:province":"Baden-W\u00fcrttemberg",
    "wof:name":"Reiseb\u00fcro A. Und R. Lais Kg",
    "wof:placetype":"venue"
},
  "geometry": {"coordinates":[9.2198982239,48.8035812378],"type":"Point"}
}