{
  "type": "Feature",
  "properties": {
    "iso:country":"DE",
    "sg:address":"Weidenstr. 20",
    "sg:city":"Oer-Erkenschwick",
    "sg:phone":"+49 2368/6381",
    "sg:postcode":"45739",
    "sg:province":"Nordrhein-Westfalen",
    "wof:name":"Tus 1909 Erkenschwick E. V. Klaus Skodell",
    "wof:placetype":"venue"
},
  "geometry": {"coordinates":[7.2597961426,51.6506004333],"type":"Point"}
}