{
  "type": "Feature",
  "properties": {
    "iso:country":"DE",
    "sg:address":"Bolongarostr. 117",
    "sg:city":"Frankfurt",
    "sg:phone":"+49 69/316117",
    "sg:postcode":"65929",
    "sg:province":"Hessen",
    "wof:name":"Monika Heeg Verkauf-agentur",
    "wof:placetype":"venue"
},
  "geometry": {"coordinates":[8.550983429,50.100643158],"type":"Point"}
}