{
  "type": "Feature",
  "properties": {
    "iso:country":"DE",
    "sg:address":"Steinweg 6",
    "sg:city":"Quedlinburg",
    "sg:phone":"+49 3946/96140",
    "sg:postcode":"06484",
    "sg:province":"Sachsen-Anhalt",
    "wof:name":"Reiseb\u00fcro Findeisen",
    "wof:placetype":"venue"
},
  "geometry": {"coordinates":[11.1475572586,51.7903594971],"type":"Point"}
}