{
  "type": "Feature",
  "properties": {
    "iso:country":"DE",
    "sg:address":"Wellseedamm 21",
    "sg:city":"Kiel",
    "sg:phone":"+49 431/714036",
    "sg:postcode":"24145",
    "sg:province":"Schleswig-Holstein",
    "wof:name":"Carsten Lohse",
    "wof:placetype":"venue"
},
  "geometry": {"coordinates":[10.148681,54.285652],"type":"Point"}
}