{
  "type": "Feature",
  "properties": {
    "iso:country":"DE",
    "sg:address":"Siedlung 5",
    "sg:city":"Bindfelde",
    "sg:phone":"+49 3931/210137",
    "sg:postcode":"39590",
    "sg:province":"Sachsen-Anhalt",
    "wof:name":"Heinz Thiedke",
    "wof:placetype":"venue"
},
  "geometry": {"coordinates":[11.9003305435,52.5900993347],"type":"Point"}
}