{
  "type": "Feature",
  "properties": {
    "iso:country":"DE",
    "sg:address":"Hauptstr.170",
    "sg:city":"Heiligenhaus",
    "sg:phone":"+49 2056/5148",
    "sg:postcode":"51491",
    "sg:province":"Nordrhein-Westfalen",
    "wof:name":"Dresdner Bank",
    "wof:placetype":"venue"
},
  "geometry": {"coordinates":[6.968986,51.325752],"type":"Point"}
}