{
  "type": "Feature",
  "properties": {
    "iso:country":"DE",
    "sg:address":"Pfarrstr. 13",
    "sg:city":"Bebra",
    "sg:phone":"+49 6622/44160",
    "sg:postcode":"36179",
    "sg:province":"Hessen",
    "wof:name":"Klaus Wittich Rechtsanwalt Und Notar",
    "wof:placetype":"venue"
},
  "geometry": {"coordinates":[9.7906904221,50.9704933167],"type":"Point"}
}