{
  "type": "Feature",
  "properties": {
    "iso:country":"DE",
    "sg:address":"Ro\u00dftrappenstr. 99",
    "sg:city":"Thale",
    "sg:phone":"+49 3947/2475",
    "sg:postcode":"06502",
    "sg:province":"Sachsen-Anhalt",
    "wof:name":"Hans Jahn",
    "wof:placetype":"venue"
},
  "geometry": {"coordinates":[11.0414619446,51.7550621033],"type":"Point"}
}