{
  "type": "Feature",
  "properties": {
    "iso:country":"DE",
    "sg:address":"Stirnstr. 1",
    "sg:city":"H\u00fcnfeld",
    "sg:phone":"+49 6652/4552",
    "sg:postcode":"36088",
    "sg:province":"Hessen",
    "wof:name":"Karl Seng",
    "wof:placetype":"venue"
},
  "geometry": {"coordinates":[9.761936,50.659187],"type":"Point"}
}