{
  "type": "Feature",
  "properties": {
    "iso:country":"DE",
    "sg:address":"Hinterm Hofe 4",
    "sg:city":"Gl\u00fcckstadt",
    "sg:phone":"+49 4124/2081",
    "sg:postcode":"25348",
    "sg:province":"Schleswig-Holstein",
    "wof:name":"Welack",
    "wof:placetype":"venue"
},
  "geometry": {"coordinates":[9.4361553192,53.7765388489],"type":"Point"}
}