{
  "type": "Feature",
  "properties": {
    "iso:country":"DE",
    "sg:address":"Brunnenstr 26",
    "sg:city":"Schotten",
    "sg:phone":"+49 6044/96090",
    "sg:postcode":"63679",
    "sg:province":"Hessen",
    "wof:name":"Herbert Betz Gmbh & Co Kg",
    "wof:placetype":"venue"
},
  "geometry": {"coordinates":[9.160134,50.479565],"type":"Point"}
}