{
  "type": "Feature",
  "properties": {
    "iso:country":"DE",
    "sg:address":"Bahnstr. 7",
    "sg:city":"Erlenbach",
    "sg:phone":"+49 9372/8792",
    "sg:postcode":"63906",
    "sg:province":"Bayern",
    "wof:name":"Eggen Gmbh",
    "wof:placetype":"venue"
},
  "geometry": {"coordinates":[9.159405,49.802231],"type":"Point"}
}