{
  "type": "Feature",
  "properties": {
    "iso:country":"DE",
    "sg:address":"Oberrimbach 59",
    "sg:city":"Creglingen",
    "sg:phone":"+49 7939/1335",
    "sg:postcode":"97993",
    "sg:province":"Baden-W\u00fcrttemberg",
    "wof:name":"Matthias Frie\u00df",
    "wof:placetype":"venue"
},
  "geometry": {"coordinates":[10.059461,49.40929],"type":"Point"}
}