{
  "type": "Feature",
  "properties": {
    "iso:country":"DE",
    "sg:address":"Kaiser-Friedrich-Str. 2",
    "sg:city":"Neuss",
    "sg:phone":"+49 2131/102539",
    "sg:postcode":"41460",
    "sg:province":"Nordrhein-Westfalen",
    "wof:name":"Hv Hotelbetriebsges. Mbh",
    "wof:placetype":"venue"
},
  "geometry": {"coordinates":[6.6807551384,51.1956100464],"type":"Point"}
}