{
  "type": "Feature",
  "properties": {
    "iso:country":"DE",
    "sg:address":"Am Neutor 4",
    "sg:city":"Werne",
    "sg:phone":"+49 2389/7091",
    "sg:postcode":"59368",
    "sg:province":"Nordrhein-Westfalen",
    "wof:name":"Wilhelm Hagen Immobilienmakler",
    "wof:placetype":"venue"
},
  "geometry": {"coordinates":[7.6368398666,51.6625404358],"type":"Point"}
}