{
  "type": "Feature",
  "properties": {
    "iso:country":"DE",
    "sg:address":"Erchenstr. 70",
    "sg:city":"Heidenheim",
    "sg:phone":"+49 7321/95900",
    "sg:postcode":"89522",
    "sg:province":"Baden-W\u00fcrttemberg",
    "wof:name":"Reich Gmbh",
    "wof:placetype":"venue"
},
  "geometry": {"coordinates":[10.1494579315,48.6678123474],"type":"Point"}
}