{
  "type": "Feature",
  "properties": {
    "iso:country":"DE",
    "sg:address":"Helgol\u00e4nder Str. 8",
    "sg:city":"Eschwege",
    "sg:phone":"+49 5651/96080",
    "sg:postcode":"37269",
    "sg:province":"Hessen",
    "wof:name":"Bch B\u00fcropartner Handels Gmbh",
    "wof:placetype":"venue"
},
  "geometry": {"coordinates":[10.019636,51.199223],"type":"Point"}
}