{
  "type": "Feature",
  "properties": {
    "iso:country":"DE",
    "sg:address":"Otto-Hahn-Str. 3",
    "sg:city":"Wallenhorst",
    "sg:phone":"+49 5407/59914",
    "sg:postcode":"49134",
    "sg:province":"Niedersachsen",
    "wof:name":"Holstein & Notthoff Bauunternehmen Gmbh",
    "wof:placetype":"venue"
},
  "geometry": {"coordinates":[7.97143,52.35228],"type":"Point"}
}