{
  "type": "Feature",
  "properties": {
    "iso:country":"DE",
    "sg:address":"Alpenstr. 6",
    "sg:city":"Stetten",
    "sg:phone":"+49 8261/1807",
    "sg:postcode":"87778",
    "sg:province":"Bayern",
    "wof:name":"Neugebauer Gmbh",
    "wof:placetype":"venue"
},
  "geometry": {"coordinates":[10.4475440979,48.0242080688],"type":"Point"}
}