{
  "type": "Feature",
  "properties": {
    "iso:country":"DE",
    "sg:address":"Fabrikstr. 21",
    "sg:city":"B\u00f6hlitz-Ehrenberg",
    "sg:phone":"+49 341/4418970",
    "sg:postcode":"04430",
    "wof:name":"S & S Systeme Gmbh",
    "wof:placetype":"venue"
},
  "geometry": {"coordinates":[12.2930469513,51.3515892029],"type":"Point"}
}