{
  "type": "Feature",
  "properties": {
    "iso:country":"DE",
    "sg:address":"Auenfeldweg 2",
    "sg:city":"Epfach",
    "sg:phone":"+49 8869/93216",
    "sg:postcode":"86920",
    "sg:province":"Bayern",
    "wof:name":"G. Haberstock-haunstein Architektin",
    "wof:placetype":"venue"
},
  "geometry": {"coordinates":[10.91055,47.912182],"type":"Point"}
}