{
  "type": "Feature",
  "properties": {
    "iso:country":"DE",
    "sg:address":"Am Buchenhang 1 a",
    "sg:city":"Bonn",
    "sg:phone":"+49 228/923830",
    "sg:postcode":"53115",
    "sg:province":"Nordrhein-Westfalen",
    "wof:name":"Habelt Verwaltungs Gmbh",
    "wof:placetype":"venue"
},
  "geometry": {"coordinates":[7.1023259163,50.7138175964],"type":"Point"}
}