{
  "type": "Feature",
  "properties": {
    "iso:country":"DE",
    "sg:address":"Marktstr. 2",
    "sg:city":"Buttenheim",
    "sg:phone":"+49 9545/7217",
    "sg:postcode":"96155",
    "sg:province":"Bayern",
    "wof:name":"Fit Like Gmbh",
    "wof:placetype":"venue"
},
  "geometry": {"coordinates":[11.030714,49.801495],"type":"Point"}
}