{
  "type": "Feature",
  "properties": {
    "iso:country":"DE",
    "sg:address":"Zum Stausee 9",
    "sg:city":"Olsberg",
    "sg:phone":"+49 2962/2947",
    "sg:postcode":"59939",
    "sg:province":"Nordrhein-Westfalen",
    "wof:name":"Wilhelm Vollmer",
    "wof:placetype":"venue"
},
  "geometry": {"coordinates":[8.4871931076,51.349521637],"type":"Point"}
}