{
  "type": "Feature",
  "properties": {
    "iso:country":"DE",
    "sg:address":"Falgerstr. 13",
    "sg:city":"M\u00fcnster",
    "sg:phone":"+49 251/25201",
    "sg:postcode":"48147",
    "sg:province":"Nordrhein-Westfalen",
    "wof:name":"Dr. Paul-eduard H\u00fcffer Rechtsanwalt Und Notar",
    "wof:placetype":"venue"
},
  "geometry": {"coordinates":[7.6301541328,51.976398468],"type":"Point"}
}