{
  "type": "Feature",
  "properties": {
    "iso:country":"DE",
    "sg:address":"Gelnh\u00e4user Str. 3",
    "sg:city":"Langenselbold",
    "sg:phone":"+49 6184/921021",
    "sg:postcode":"63505",
    "sg:province":"Hessen",
    "wof:name":"Berthold Reith",
    "wof:placetype":"venue"
},
  "geometry": {"coordinates":[9.0420026779,50.1757469177],"type":"Point"}
}