{
  "type": "Feature",
  "properties": {
    "iso:country":"DE",
    "sg:address":"Stra\u00dfe der Jugend 6a",
    "sg:city":"Burkau",
    "sg:phone":"+49 35953/5209",
    "sg:postcode":"01906",
    "sg:province":"Sachsen",
    "wof:name":"Otto Winter Betonwerk Burkau Gmbh",
    "wof:placetype":"venue"
},
  "geometry": {"coordinates":[14.1803913116,51.1728515625],"type":"Point"}
}