{
  "type": "Feature",
  "properties": {
    "iso:country":"DE",
    "sg:address":"Rosenheimer Str. 65",
    "sg:city":"Kolbermoor",
    "sg:postcode":"83059",
    "sg:province":"Bayern",
    "wof:name":"Imisys Integrierte Management Informationssysteme Software",
    "wof:placetype":"venue"
},
  "geometry": {"coordinates":[12.0786724091,47.8493652344],"type":"Point"}
}