{
  "type": "Feature",
  "properties": {
    "iso:country":"DE",
    "sg:address":"Sandstra\u00dfe 11",
    "sg:city":"Hamburg",
    "sg:phone":"+49 40/64553838",
    "sg:postcode":"22175",
    "sg:province":"Hamburg",
    "wof:name":"Die Sch\u00e4dlingsbek\u00e4mpfungs Gmbh Peth",
    "wof:placetype":"venue"
},
  "geometry": {"coordinates":[10.0983972549,53.6186599731],"type":"Point"}
}