{
  "type": "Feature",
  "properties": {
    "iso:country":"DE",
    "sg:address":"Fu\u00dfbach 12",
    "sg:city":"Gengenbach",
    "sg:phone":"+49 7803/6411",
    "sg:postcode":"77723",
    "sg:province":"Baden-W\u00fcrttemberg",
    "wof:name":"Konrad Schilli",
    "wof:placetype":"venue"
},
  "geometry": {"coordinates":[8.00627,48.365269],"type":"Point"}
}