{
  "type": "Feature",
  "properties": {
    "iso:country":"DE",
    "sg:address":"Haitzinger Str. 67",
    "sg:city":"Passau",
    "sg:phone":"+49 851/956320",
    "sg:postcode":"94036",
    "sg:province":"Bayern",
    "wof:name":"Fritz Kurduletsch Gmbh",
    "wof:placetype":"venue"
},
  "geometry": {"coordinates":[13.424412,48.5718],"type":"Point"}
}