{
  "type": "Feature",
  "properties": {
    "iso:country":"DE",
    "sg:address":"S\u00fcdstr. 28",
    "sg:city":"Wuppertal",
    "sg:phone":"+49 202/306183",
    "sg:postcode":"42103",
    "sg:province":"Nordrhein-Westfalen",
    "wof:name":"Karl H. Brandau Bauschlosserei",
    "wof:placetype":"venue"
},
  "geometry": {"coordinates":[7.1404490471,51.2522201538],"type":"Point"}
}