{
  "type": "Feature",
  "properties": {
    "iso:country":"DE",
    "sg:address":"Prinzenallee 51",
    "sg:city":"Berlin",
    "sg:phone":"+49 30/49771181",
    "sg:postcode":"13359",
    "sg:province":"Berlin",
    "wof:name":"Heinrich-zille-apotheke",
    "wof:placetype":"venue"
},
  "geometry": {"coordinates":[13.386514,52.559338],"type":"Point"}
}