{
  "type": "Feature",
  "properties": {
    "iso:country":"DE",
    "sg:address":"Bergstr. 13-14",
    "sg:city":"Gondershausen",
    "sg:phone":"+49 4967/45326",
    "sg:postcode":"56283",
    "sg:province":"Rheinland-Pfalz",
    "wof:name":"Ewald & Kl\u00c4ser Strickwaren Gmbh",
    "wof:placetype":"venue"
},
  "geometry": {"coordinates":[7.486636,50.159374],"type":"Point"}
}