{
  "type": "Feature",
  "properties": {
    "iso:country":"DE",
    "sg:address":"Weiherfeldstr. 21",
    "sg:city":"Hauzenberg",
    "sg:phone":"+49 8586/1410",
    "sg:postcode":"94051",
    "sg:province":"Bayern",
    "wof:name":"A. Sonnleitner",
    "wof:placetype":"venue"
},
  "geometry": {"coordinates":[13.6085929871,48.648147583],"type":"Point"}
}