{
  "type": "Feature",
  "properties": {
    "iso:country":"DE",
    "sg:address":"Hanauer Str. 33",
    "sg:city":"Sch\u00f6neck",
    "sg:phone":"+49 6187/5066",
    "sg:postcode":"61137",
    "sg:province":"Hessen",
    "wof:name":"Mag Mikroelektronik Und Apparatebau Gmbh",
    "wof:placetype":"venue"
},
  "geometry": {"coordinates":[8.8595657349,50.1984825134],"type":"Point"}
}