{
  "type": "Feature",
  "properties": {
    "iso:country":"DE",
    "sg:address":"Hauptstr. 15",
    "sg:city":"Bad Nenndorf",
    "sg:phone":"+49 5723/2047",
    "sg:postcode":"31542",
    "sg:province":"Niedersachsen",
    "wof:name":"Brandes B\u00f6ttcher Und Fedler Rechtsanw\u00e4lte Und Notare",
    "wof:placetype":"venue"
},
  "geometry": {"coordinates":[9.378578186,52.3358688354],"type":"Point"}
}