{
  "type": "Feature",
  "properties": {
    "iso:country":"DE",
    "sg:address":"Gro\u00dfe Bleichen 30",
    "sg:city":"Hamburg",
    "sg:phone":"+49 40/3509550",
    "sg:postcode":"20354",
    "sg:province":"Hamburg",
    "wof:name":"Modehaus H & M Hennes & Mauritz Gmbh",
    "wof:placetype":"venue"
},
  "geometry": {"coordinates":[9.989549,53.553158],"type":"Point"}
}