{
  "type": "Feature",
  "properties": {
    "iso:country":"DE",
    "sg:address":"Am Markt 1",
    "sg:city":"Luckau",
    "sg:phone":"+49 3544/12688",
    "sg:postcode":"15926",
    "sg:province":"Brandenburg",
    "wof:name":"Lvm-versicherungsb\u00fcro Navrath-stolpe",
    "wof:placetype":"venue"
},
  "geometry": {"coordinates":[13.7157363892,51.852935791],"type":"Point"}
}