{
  "type": "Feature",
  "properties": {
    "iso:country":"DE",
    "sg:address":"Busenberger Str 26",
    "sg:city":"Schindhard",
    "sg:phone":"+49 6391/3000",
    "sg:postcode":"66996",
    "sg:province":"Rheinland-Pfalz",
    "wof:name":"Breitsch Baufertigteile Und Tiefbau Gmbh",
    "wof:placetype":"venue"
},
  "geometry": {"coordinates":[7.82276,49.138672],"type":"Point"}
}