{
  "type": "Feature",
  "properties": {
    "iso:country":"DE",
    "sg:address":"Wertheimer Str. 6",
    "sg:city":"Hardheim",
    "sg:phone":"+49 6283/6281",
    "sg:postcode":"74736",
    "sg:province":"Baden-W\u00fcrttemberg",
    "wof:name":"Robert Leiblein",
    "wof:placetype":"venue"
},
  "geometry": {"coordinates":[9.473394,49.608528],"type":"Point"}
}