{
  "type": "Feature",
  "properties": {
    "iso:country":"DE",
    "sg:address":"Rheinauhafen 6",
    "sg:city":"K\u00f6ln",
    "sg:phone":"+49 221/323449",
    "sg:postcode":"50678",
    "sg:province":"Nordrhein-Westfalen",
    "wof:name":"Drehbr\u00fccke Gmbh",
    "wof:placetype":"venue"
},
  "geometry": {"coordinates":[6.965284,50.929508],"type":"Point"}
}