{
  "type": "Feature",
  "properties": {
    "iso:country":"DE",
    "sg:address":"Heidenkampsweg 54",
    "sg:city":"Hamburg",
    "sg:phone":"+49 40/233438",
    "sg:postcode":"20097",
    "sg:province":"Hamburg",
    "wof:name":"Kommanditges. Lkw-vermietung Mand Gmbh & Co.",
    "wof:placetype":"venue"
},
  "geometry": {"coordinates":[10.0276584625,53.5484619141],"type":"Point"}
}