{
  "type": "Feature",
  "properties": {
    "iso:country":"DE",
    "sg:address":"Forellenweg 15",
    "sg:city":"Ellwangen",
    "sg:postcode":"73479",
    "sg:province":"Baden-W\u00fcrttemberg",
    "wof:name":"Mt & Ms M\u00f6beltransport & Montageservice Subunter-",
    "wof:placetype":"venue"
},
  "geometry": {"coordinates":[10.0909328461,48.9740333557],"type":"Point"}
}