{
  "type": "Feature",
  "properties": {
    "iso:country":"DE",
    "sg:address":"Walkm\u00f6hle 25",
    "sg:city":"Sereetz",
    "sg:phone":"+49 451/391180",
    "sg:postcode":"23611",
    "sg:province":"Schleswig-Holstein",
    "wof:name":"Dr. H.j. Brehm Tierarzt",
    "wof:placetype":"venue"
},
  "geometry": {"coordinates":[10.7278413773,53.92370224],"type":"Point"}
}