{
  "type": "Feature",
  "properties": {
    "iso:country":"DE",
    "sg:address":"Keplerstr. 6",
    "sg:city":"Neu-Ulm",
    "sg:phone":"+49 731/73939",
    "sg:postcode":"89231",
    "sg:province":"Bayern",
    "wof:name":"Keplerst\u00fcble",
    "wof:placetype":"venue"
},
  "geometry": {"coordinates":[10.0050497055,48.3948974609],"type":"Point"}
}