{
  "type": "Feature",
  "properties": {
    "iso:country":"DE",
    "sg:address":"Oberf\u00f6hringer Str. 155",
    "sg:city":"M\u00fcnchen",
    "sg:phone":"+49 89/95939880",
    "sg:postcode":"81925",
    "sg:province":"Bayern",
    "wof:name":"Tomaxx Gmbh",
    "wof:placetype":"venue"
},
  "geometry": {"coordinates":[11.625698,48.171612],"type":"Point"}
}