{
  "type": "Feature",
  "properties": {
    "iso:country":"DE",
    "sg:address":"Friedrich-Ebert-Ring 33",
    "sg:city":"Koblenz",
    "sg:phone":"+49 261/398130",
    "sg:postcode":"56068",
    "sg:province":"Rheinland-Pfalz",
    "wof:name":"Messe Am Rhein Handwerksmesse Koblenz Gmbh",
    "wof:placetype":"venue"
},
  "geometry": {"coordinates":[7.59465,50.354691],"type":"Point"}
}