{
  "type": "Feature",
  "properties": {
    "iso:country":"DE",
    "sg:address":"Relenbergstr. 90",
    "sg:city":"Stuttgart",
    "sg:phone":"+49 4971/120220",
    "sg:postcode":"70174",
    "sg:province":"Baden-W\u00fcrttemberg",
    "wof:name":"W\u00dcrtt Schwesternschaft Vom Roten Kreuz Ev",
    "wof:placetype":"venue"
},
  "geometry": {"coordinates":[9.162394,48.787117],"type":"Point"}
}