{
  "type": "Feature",
  "properties": {
    "iso:country":"DE",
    "sg:address":"St.-Ingberter-Str. 128",
    "sg:city":"Mandelbachtal",
    "sg:phone":"+49 6803/2939",
    "sg:postcode":"66399",
    "sg:province":"Saarland",
    "wof:name":"Werner Schneider Steuerberater",
    "wof:placetype":"venue"
},
  "geometry": {"coordinates":[7.1449460983,49.1968536377],"type":"Point"}
}