{
  "type": "Feature",
  "properties": {
    "iso:country":"DE",
    "sg:address":"Stadtrodaer Str. 46",
    "sg:city":"Gera",
    "sg:phone":"+49 365/827260",
    "sg:postcode":"07548",
    "sg:province":"Th\u00fcringen",
    "wof:name":"Posers-transporte",
    "wof:placetype":"venue"
},
  "geometry": {"coordinates":[12.015630722,50.8631286621],"type":"Point"}
}