{
  "type": "Feature",
  "properties": {
    "iso:country":"DE",
    "sg:address":"Bahnstr. 9",
    "sg:city":"T\u00f6nisvorst",
    "sg:phone":"+49 2151/790205",
    "sg:postcode":"47918",
    "sg:province":"Nordrhein-Westfalen",
    "wof:name":"Franz-josef Knodt",
    "wof:placetype":"venue"
},
  "geometry": {"coordinates":[6.496437,51.320255],"type":"Point"}
}