{
  "type": "Feature",
  "properties": {
    "iso:country":"DE",
    "sg:address":"Am Hofacker 1",
    "sg:city":"Weilerbach",
    "sg:phone":"+49 6374/995752",
    "sg:postcode":"67685",
    "sg:province":"Rheinland-Pfalz",
    "wof:name":"Compufix Gmbh",
    "wof:placetype":"venue"
},
  "geometry": {"coordinates":[7.6316580772,49.4816207886],"type":"Point"}
}