{
  "type": "Feature",
  "properties": {
    "iso:country":"DE",
    "sg:address":"Virchowstr. 10",
    "sg:city":"Oberhausen",
    "sg:phone":"+49 208/864602",
    "sg:postcode":"46047",
    "sg:province":"Nordrhein-Westfalen",
    "wof:name":"Melisa Grill",
    "wof:placetype":"venue"
},
  "geometry": {"coordinates":[6.8646712303,51.4739837646],"type":"Point"}
}