{
  "type": "Feature",
  "properties": {
    "iso:country":"DE",
    "sg:address":"Merchinger Str. 26",
    "sg:city":"Merzig",
    "sg:phone":"+49 6861/4750",
    "sg:postcode":"66663",
    "sg:province":"Saarland",
    "wof:name":"Marlene Thiesen",
    "wof:placetype":"venue"
},
  "geometry": {"coordinates":[6.6524238586,49.4425773621],"type":"Point"}
}