{
  "type": "Feature",
  "properties": {
    "iso:country":"DE",
    "sg:address":"Burganger 4",
    "sg:city":"Alfeld",
    "sg:postcode":"31061",
    "sg:province":"Niedersachsen",
    "wof:name":"Metropol Sportartikel Gmbh",
    "wof:placetype":"venue"
},
  "geometry": {"coordinates":[9.8502006531,51.9556159973],"type":"Point"}
}