{
  "type": "Feature",
  "properties": {
    "iso:country":"DE",
    "sg:address":"Boeler Str. 185",
    "sg:city":"Hagen",
    "sg:phone":"+49 2331/98940",
    "sg:postcode":"58097",
    "sg:province":"Nordrhein-Westfalen",
    "wof:name":"Dietmar Ewerdwalbesloh Steuerberater",
    "wof:placetype":"venue"
},
  "geometry": {"coordinates":[7.4783668518,51.3810043335],"type":"Point"}
}