{
  "type": "Feature",
  "properties": {
    "iso:country":"DE",
    "sg:address":"Rodewaldstr. 1",
    "sg:city":"Hannover",
    "sg:phone":"+49 511/537691",
    "sg:postcode":"30625",
    "sg:province":"Niedersachsen",
    "wof:name":"Timm Fisch & Feinkost Inh. Peter Sch\u00e4fer",
    "wof:placetype":"venue"
},
  "geometry": {"coordinates":[9.7904672623,52.3750114441],"type":"Point"}
}