{
  "type": "Feature",
  "properties": {
    "iso:country":"DE",
    "sg:address":"K\u00f6nigstr. 7",
    "sg:city":"Torgelow",
    "sg:phone":"+49 3976/201900",
    "sg:postcode":"17358",
    "sg:province":"Mecklenburg-Vorpommern",
    "wof:name":"Reinhard Wagner Anlageberater",
    "wof:placetype":"venue"
},
  "geometry": {"coordinates":[14.0069704056,53.6321487427],"type":"Point"}
}