{
  "type": "Feature",
  "properties": {
    "iso:country":"DE",
    "sg:address":"Busmannstr. 18",
    "sg:city":"Kevelaer",
    "sg:phone":"+49 2832/50027",
    "sg:postcode":"47623",
    "sg:province":"Nordrhein-Westfalen",
    "wof:name":"Angelika Klein",
    "wof:placetype":"venue"
},
  "geometry": {"coordinates":[6.2431941032,51.5828857422],"type":"Point"}
}