{
  "type": "Feature",
  "properties": {
    "iso:country":"DE",
    "sg:address":"Baustr. 47",
    "sg:city":"Hilden",
    "sg:phone":"+49 2103/87795",
    "sg:postcode":"40723",
    "sg:province":"Nordrhein-Westfalen",
    "wof:name":"Rudolf Suckow Gmbh",
    "wof:placetype":"venue"
},
  "geometry": {"coordinates":[6.943086,51.163361],"type":"Point"}
}