{
  "type": "Feature",
  "properties": {
    "iso:country":"DE",
    "sg:address":"T\u00fcrkenstr. 92",
    "sg:city":"M\u00fcnchen",
    "sg:phone":"+49 89/282832",
    "sg:postcode":"80799",
    "sg:province":"Bayern",
    "wof:name":"Charivari",
    "wof:placetype":"venue"
},
  "geometry": {"coordinates":[11.5773820877,48.1521682739],"type":"Point"}
}