{
  "type": "Feature",
  "properties": {
    "iso:country":"DE",
    "sg:address":"Holzh\u00e4user Str. 74",
    "sg:city":"Leipzig",
    "sg:phone":"+49 341/80380",
    "sg:postcode":"04299",
    "sg:province":"Sachsen",
    "wof:name":"Hsgo Heizungs- Und Sanit\u00e4r- Gro\u00dfhandel Ost",
    "wof:placetype":"venue"
},
  "geometry": {"coordinates":[12.4189682007,51.319103241],"type":"Point"}
}