{
  "type": "Feature",
  "properties": {
    "iso:country":"DE",
    "sg:address":"Trenkelbachstr. 1",
    "sg:city":"Sulzbach",
    "sg:phone":"+49 6897/4472",
    "sg:postcode":"66280",
    "sg:province":"Saarland",
    "wof:name":"Horst Meynle",
    "wof:placetype":"venue"
},
  "geometry": {"coordinates":[7.05998,49.310452],"type":"Point"}
}