{
  "type": "Feature",
  "properties": {
    "iso:country":"DE",
    "sg:address":"K\u00f6lner Str. 56",
    "sg:city":"Leverkusen",
    "sg:phone":"+49 2171/49557",
    "sg:postcode":"51379",
    "sg:province":"Nordrhein-Westfalen",
    "wof:name":"Ochsenbruch Kg",
    "wof:placetype":"venue"
},
  "geometry": {"coordinates":[7.003482,51.063828],"type":"Point"}
}