{
  "type": "Feature",
  "properties": {
    "iso:country":"DE",
    "sg:address":"Zur K\u00f6hlerh\u00fctte 11",
    "sg:city":"Haiger",
    "sg:phone":"+49 2773/3498",
    "sg:postcode":"35708",
    "sg:province":"Hessen",
    "wof:name":"Michael Kreft",
    "wof:placetype":"venue"
},
  "geometry": {"coordinates":[8.1839933395,50.7805519104],"type":"Point"}
}