{
  "type": "Feature",
  "properties": {
    "iso:country":"DE",
    "sg:address":"Gartenstr. 69",
    "sg:city":"Berlin",
    "sg:phone":"+49 30/6516616",
    "sg:postcode":"12557",
    "sg:province":"Berlin",
    "wof:name":"Ulrich Peikert Architekt",
    "wof:placetype":"venue"
},
  "geometry": {"coordinates":[13.577623,52.439632],"type":"Point"}
}