{
  "type": "Feature",
  "properties": {
    "iso:country":"DE",
    "sg:address":"Schulstr. 15",
    "sg:city":"Sonnefeld",
    "sg:phone":"+49 9266/1244",
    "sg:postcode":"96242",
    "sg:province":"Bayern",
    "wof:name":"Heinz Liebermann Gmbh",
    "wof:placetype":"venue"
},
  "geometry": {"coordinates":[11.174318,50.238327],"type":"Point"}
}