{
  "type": "Feature",
  "properties": {
    "iso:country":"DE",
    "sg:address":"Landgrafenstr. 8",
    "sg:city":"Hessisch Lichtenau",
    "sg:phone":"+49 5602/1212",
    "sg:postcode":"37235",
    "sg:province":"Hessen",
    "wof:name":"Herbert Eckhardt",
    "wof:placetype":"venue"
},
  "geometry": {"coordinates":[9.7219648361,51.1984558105],"type":"Point"}
}