{
  "type": "Feature",
  "properties": {
    "iso:country":"DE",
    "sg:address":"Haag 4",
    "sg:city":"Treuchtlingen",
    "sg:phone":"+49 9142/1817",
    "sg:postcode":"91757",
    "sg:province":"Bayern",
    "wof:name":"H. Schmidt Finanzberater",
    "wof:placetype":"venue"
},
  "geometry": {"coordinates":[10.9095649719,48.919883728],"type":"Point"}
}