{
  "type": "Feature",
  "properties": {
    "iso:country":"DE",
    "sg:address":"Hofstr. 64",
    "sg:city":"Hilden",
    "sg:phone":"+49 2103/62894",
    "sg:postcode":"40723",
    "sg:province":"Nordrhein-Westfalen",
    "wof:name":"Norbert Hannig",
    "wof:placetype":"venue"
},
  "geometry": {"coordinates":[6.930943,51.161144],"type":"Point"}
}