{
  "type": "Feature",
  "properties": {
    "iso:country":"DE",
    "sg:address":"Arnoldstr. 13",
    "sg:city":"Hamburg",
    "sg:phone":"+49 40/394495",
    "sg:postcode":"22765",
    "sg:province":"Hamburg",
    "wof:name":"Eleonore Riechelmann Steuerberaterin",
    "wof:placetype":"venue"
},
  "geometry": {"coordinates":[9.9291982651,53.5493850708],"type":"Point"}
}