{
  "type": "Feature",
  "properties": {
    "iso:country":"DE",
    "sg:address":"St.-Martin-Str. 33",
    "sg:city":"Piesport",
    "sg:phone":"+49 6507/2422",
    "sg:postcode":"54498",
    "sg:province":"Rheinland-Pfalz",
    "wof:name":"Erich Kettern",
    "wof:placetype":"venue"
},
  "geometry": {"coordinates":[6.9256701469,49.8786888123],"type":"Point"}
}