{
  "type": "Feature",
  "properties": {
    "iso:country":"DE",
    "sg:address":"Herberge 12",
    "sg:city":"Schalksm\u00fchle",
    "sg:phone":"+49 2355/908950",
    "sg:postcode":"58579",
    "sg:province":"Nordrhein-Westfalen",
    "wof:name":"Ernst Rittinghaus Gmbh",
    "wof:placetype":"venue"
},
  "geometry": {"coordinates":[7.51258,51.22628],"type":"Point"}
}