{
  "type": "Feature",
  "properties": {
    "iso:country":"DE",
    "sg:address":"J\u00e4gerstr. 35",
    "sg:city":"Potsdam",
    "sg:phone":"+49 331/296070",
    "sg:postcode":"14467",
    "sg:province":"Brandenburg",
    "wof:name":"Klaus Hasselberg",
    "wof:placetype":"venue"
},
  "geometry": {"coordinates":[13.055782,52.401871],"type":"Point"}
}