{
  "type": "Feature",
  "properties": {
    "iso:country":"DE",
    "sg:address":"Benesisstr. 29",
    "sg:city":"K\u00f6ln",
    "sg:phone":"+49 221/2573451",
    "sg:postcode":"50672",
    "sg:province":"Nordrhein-Westfalen",
    "wof:name":"Mr. Smith And Mrs. Miller",
    "wof:placetype":"venue"
},
  "geometry": {"coordinates":[6.94216,50.936996],"type":"Point"}
}