{
  "type": "Feature",
  "properties": {
    "iso:country":"DE",
    "sg:address":"Johannesstr. 94",
    "sg:city":"Bergisch Gladbach",
    "sg:phone":"+49 2202/932984",
    "sg:postcode":"51465",
    "sg:province":"Nordrhein-Westfalen",
    "wof:name":"H. & U. Remmel Steuerbevollm\u00e4chtigte",
    "wof:placetype":"venue"
},
  "geometry": {"coordinates":[7.1346898079,50.9988098145],"type":"Point"}
}