{
  "type": "Feature",
  "properties": {
    "iso:country":"DE",
    "sg:address":"Wirtembergstr. 88",
    "sg:city":"Fellbach",
    "sg:phone":"+49 711/515520",
    "sg:postcode":"70736",
    "sg:province":"Baden-W\u00fcrttemberg",
    "wof:name":"Heinrich Koch",
    "wof:placetype":"venue"
},
  "geometry": {"coordinates":[9.262998,48.82983],"type":"Point"}
}