{
  "type": "Feature",
  "properties": {
    "iso:country":"DE",
    "sg:address":"In den Langen St\u00fccken 1",
    "sg:city":"Halberstadt",
    "sg:phone":"+49 3941/69960",
    "sg:postcode":"38820",
    "sg:province":"Sachsen-Anhalt",
    "wof:name":"Azh Automobil - Zentrum Halberstadt Gmbh",
    "wof:placetype":"venue"
},
  "geometry": {"coordinates":[11.080048,51.901802],"type":"Point"}
}