{
  "type": "Feature",
  "properties": {
    "iso:country":"DE",
    "sg:address":"Boppstr. 4",
    "sg:city":"Berlin",
    "sg:phone":"+49 30/6917958",
    "sg:postcode":"10967",
    "sg:province":"Berlin",
    "wof:name":"Almanya T\u00fcrk Televizyonu Fernseh- Und Videoproduktions-",
    "wof:placetype":"venue"
},
  "geometry": {"coordinates":[13.421404,52.490829],"type":"Point"}
}