{
  "type": "Feature",
  "properties": {
    "iso:country":"DE",
    "sg:address":"Heinestr. 32",
    "sg:city":"R\u00f6tha",
    "sg:phone":"+49 34206/54677",
    "sg:postcode":"04571",
    "sg:province":"Sachsen",
    "wof:name":"A. Flach",
    "wof:placetype":"venue"
},
  "geometry": {"coordinates":[12.4107942581,51.2025032043],"type":"Point"}
}