{
  "type": "Feature",
  "properties": {
    "iso:country":"DE",
    "sg:address":"Vo\u00dfstr. 42",
    "sg:city":"Geislingen",
    "sg:postcode":"73312",
    "sg:province":"Baden-W\u00fcrttemberg",
    "wof:name":"Cm-chemometall Beteiligungs- Und Vertriebs-gmbh",
    "wof:placetype":"venue"
},
  "geometry": {"coordinates":[9.8291196823,48.6244392395],"type":"Point"}
}