{
  "type": "Feature",
  "properties": {
    "iso:country":"DE",
    "sg:address":"Gewerbehofstr. 11",
    "sg:city":"Essen",
    "sg:phone":"+49 201/221011",
    "sg:postcode":"45145",
    "sg:province":"Nordrhein-Westfalen",
    "wof:name":"Mrs Messen-regeln-steuern Technischer Service Gmbh",
    "wof:placetype":"venue"
},
  "geometry": {"coordinates":[6.9946570396,51.4469070435],"type":"Point"}
}