{
  "type": "Feature",
  "properties": {
    "iso:country":"DE",
    "sg:address":"Industriestr. 1",
    "sg:city":"Leipzig",
    "sg:phone":"+49 341/4790270",
    "sg:postcode":"04229",
    "sg:province":"Sachsen",
    "wof:name":"Kai Lippke Rechtsanwalt",
    "wof:placetype":"venue"
},
  "geometry": {"coordinates":[12.3452386856,51.3234367371],"type":"Point"}
}