{
  "type": "Feature",
  "properties": {
    "iso:country":"DE",
    "sg:address":"Hechingerweg 40",
    "sg:city":"Remseck",
    "sg:phone":"+49 7146/8950",
    "sg:postcode":"71686",
    "sg:province":"Baden-W\u00fcrttemberg",
    "wof:name":"Fa. Fentek",
    "wof:placetype":"venue"
},
  "geometry": {"coordinates":[9.2568292618,48.8725700378],"type":"Point"}
}