{
  "type": "Feature",
  "properties": {
    "iso:country":"DE",
    "sg:address":"Waldemar Petersen Str. 45",
    "sg:city":"Kassel",
    "sg:phone":"+49 561/577844",
    "sg:postcode":"34123",
    "sg:province":"Hessen",
    "wof:name":"Moni\u00b4s Tierparadies",
    "wof:placetype":"venue"
},
  "geometry": {"coordinates":[9.522901535,51.2891082764],"type":"Point"}
}