{
  "type": "Feature",
  "properties": {
    "iso:country":"DE",
    "sg:address":"Pfarrgasse 1",
    "sg:city":"Oettingen",
    "sg:phone":"+49 9082/2236",
    "sg:postcode":"86732",
    "sg:province":"Bayern",
    "wof:name":"Ev. Luth. Pfarramt",
    "wof:placetype":"venue"
},
  "geometry": {"coordinates":[10.6055841446,48.9543037415],"type":"Point"}
}