{
  "type": "Feature",
  "properties": {
    "iso:country":"DE",
    "sg:address":"Habichtstr. 41::",
    "sg:city":"Hamburg",
    "sg:phone":"+49 40/6117000",
    "sg:postcode":"22305",
    "sg:province":"Hamburg",
    "wof:name":"Buergschaftsgemeinschaft Hamburg Gmbh",
    "wof:placetype":"venue"
},
  "geometry": {"coordinates":[10.056303,53.591076],"type":"Point"}
}