{
  "type": "Feature",
  "properties": {
    "iso:country":"DE",
    "sg:address":"Max-Scheiff-Str. 23",
    "sg:city":"Ratingen",
    "sg:postcode":"40882",
    "sg:province":"Nordrhein-Westfalen",
    "wof:name":"F & F Gmbh",
    "wof:placetype":"venue"
},
  "geometry": {"coordinates":[6.8680300713,51.2996520996],"type":"Point"}
}