{
  "type": "Feature",
  "properties": {
    "iso:country":"DE",
    "sg:address":"Im Burggarten 5",
    "sg:city":"Schleiden",
    "sg:phone":"+49 2445/8422",
    "sg:postcode":"53937",
    "sg:province":"Nordrhein-Westfalen",
    "wof:name":"Cafe Bistro",
    "wof:placetype":"venue"
},
  "geometry": {"coordinates":[6.4735441208,50.5273895264],"type":"Point"}
}