{
  "type": "Feature",
  "properties": {
    "iso:country":"DE",
    "sg:address":"Stresemannallee",
    "sg:city":"Hamburg",
    "sg:postcode":"22529",
    "sg:province":"Hamburg",
    "wof:name":"Hew Contract Betriebsges. Lokstedt Mbh",
    "wof:placetype":"venue"
},
  "geometry": {"coordinates":[9.95965,53.591206],"type":"Point"}
}