{
  "type": "Feature",
  "properties": {
    "iso:country":"DE",
    "sg:address":"Rudolf-Diesel-Str. 27",
    "sg:city":"Vechta",
    "sg:phone":"+49 4441/99970",
    "sg:postcode":"49377",
    "sg:province":"Niedersachsen",
    "wof:name":"Gramoflor Verwaltungsgesellschaft Mbh",
    "wof:placetype":"venue"
},
  "geometry": {"coordinates":[8.273973465,52.7507667542],"type":"Point"}
}