{
  "type": "Feature",
  "properties": {
    "iso:country":"DE",
    "sg:address":"Berliner Ring 53",
    "sg:city":"Harsewinkel",
    "sg:phone":"+49 5247/92310",
    "sg:postcode":"33428",
    "sg:province":"Nordrhein-Westfalen",
    "wof:name":"Heinrich Br\u00f6skamp",
    "wof:placetype":"venue"
},
  "geometry": {"coordinates":[8.2428245544,51.9673423767],"type":"Point"}
}