{
  "type": "Feature",
  "properties": {
    "iso:country":"DE",
    "sg:address":"Lerchenfeld 48",
    "sg:city":"Hamburg",
    "sg:phone":"+49 40/2299055",
    "sg:postcode":"22081",
    "sg:province":"Hamburg",
    "wof:name":"Baris",
    "wof:placetype":"venue"
},
  "geometry": {"coordinates":[10.0279064178,53.5700302124],"type":"Point"}
}