{
  "type": "Feature",
  "properties": {
    "iso:country":"DE",
    "sg:address":"Wallstr. 8",
    "sg:city":"Kleinwallstadt",
    "sg:phone":"+49 6022/654473",
    "sg:postcode":"63839",
    "sg:province":"Bayern",
    "wof:name":"Teleshop-kleinwallstadt",
    "wof:placetype":"venue"
},
  "geometry": {"coordinates":[9.1670246124,49.8737754822],"type":"Point"}
}