{
  "type": "Feature",
  "properties": {
    "iso:country":"DE",
    "sg:address":"Lehrer-Hangl-Str. 8",
    "sg:city":"Bruckm\u00fchl",
    "sg:phone":"+49 8062/2157",
    "sg:postcode":"83052",
    "sg:province":"Bayern",
    "wof:name":"Bau-gmbh Hochwind Und Rechenauer",
    "wof:placetype":"venue"
},
  "geometry": {"coordinates":[11.9151687622,47.8826522827],"type":"Point"}
}