{
  "type": "Feature",
  "properties": {
    "iso:country":"DE",
    "sg:address":"Hauptstr. 27",
    "sg:city":"Landstuhl",
    "sg:phone":"+49 6371/62970",
    "sg:postcode":"66849",
    "sg:province":"Rheinland-Pfalz",
    "wof:name":"Burg-apotheke",
    "wof:placetype":"venue"
},
  "geometry": {"coordinates":[7.570036,49.410038],"type":"Point"}
}