{
  "type": "Feature",
  "properties": {
    "iso:country":"DE",
    "sg:address":"Daimlerstr. 11",
    "sg:city":"Lichtenstein",
    "sg:phone":"+49 4968/9435059",
    "sg:postcode":"72805",
    "sg:province":"Baden-W\u00fcrttemberg",
    "wof:name":"Hans-joachim Wolter Gmbh Fernmeldeanlagen U. -geraete",
    "wof:placetype":"venue"
},
  "geometry": {"coordinates":[7.0992588997,49.2786178589],"type":"Point"}
}