{
  "type": "Feature",
  "properties": {
    "iso:country":"DE",
    "sg:address":"Wilhelm-Busch-Str. 1",
    "sg:city":"Bad Eilsen",
    "sg:postcode":"31707",
    "sg:province":"Niedersachsen",
    "wof:name":"Format-bau Gmbh",
    "wof:placetype":"venue"
},
  "geometry": {"coordinates":[9.108048439,52.2424468994],"type":"Point"}
}