{
  "type": "Feature",
  "properties": {
    "iso:country":"DE",
    "sg:address":"Clarholzer Str. 54",
    "sg:city":"Herzebrock-Clarholz",
    "sg:phone":"+49 5245/2250",
    "sg:postcode":"33442",
    "sg:province":"Nordrhein-Westfalen",
    "wof:name":"Pizzeria Calabria",
    "wof:placetype":"venue"
},
  "geometry": {"coordinates":[8.2357387543,51.8816833496],"type":"Point"}
}