{
  "type": "Feature",
  "properties": {
    "iso:country":"DE",
    "sg:address":"Am Bubach 10",
    "sg:city":"Mamming",
    "sg:phone":"+49 9955/1656",
    "sg:postcode":"94437",
    "sg:province":"Bayern",
    "wof:name":"A. Seidl",
    "wof:placetype":"venue"
},
  "geometry": {"coordinates":[12.6226730347,48.6371650696],"type":"Point"}
}