{
  "type": "Feature",
  "properties": {
    "iso:country":"DE",
    "sg:address":"Am Eichholz 7",
    "sg:city":"Remscheid",
    "sg:phone":"+49 2191/609280",
    "sg:postcode":"42897",
    "sg:province":"Nordrhein-Westfalen",
    "wof:name":"Pacplast Thermoform Gmbh",
    "wof:placetype":"venue"
},
  "geometry": {"coordinates":[7.2674050331,51.1512718201],"type":"Point"}
}