{
  "type": "Feature",
  "properties": {
    "iso:country":"DE",
    "sg:address":"Saarwiesenweg 2",
    "sg:city":"V\u00f6lklingen",
    "sg:phone":"+49 6898/27286",
    "sg:postcode":"66333",
    "sg:province":"Saarland",
    "wof:name":"Entsorgungsfachbetrieb Harry Ruf Gmbh",
    "wof:placetype":"venue"
},
  "geometry": {"coordinates":[6.865473,49.247368],"type":"Point"}
}