{
  "type": "Feature",
  "properties": {
    "iso:country":"DE",
    "sg:address":"P\u00fcllenweg 2",
    "sg:city":"Korschenbroich",
    "sg:phone":"+49 2161/679617",
    "sg:postcode":"41352",
    "sg:province":"Nordrhein-Westfalen",
    "wof:name":"Achternbosch",
    "wof:placetype":"venue"
},
  "geometry": {"coordinates":[6.551786,51.197121],"type":"Point"}
}