{
  "type": "Feature",
  "properties": {
    "iso:country":"DE",
    "sg:address":"Platter Str. 52",
    "sg:city":"Wiesbaden",
    "sg:phone":"+49 611/523988",
    "sg:postcode":"65193",
    "sg:province":"Hessen",
    "wof:name":"Elektro Diefenbach",
    "wof:placetype":"venue"
},
  "geometry": {"coordinates":[8.231303,50.087322],"type":"Point"}
}