{
  "type": "Feature",
  "properties": {
    "iso:country":"DE",
    "sg:city":"Hannover",
    "sg:phone":"+49 511",
    "sg:postcode":"30161",
    "sg:province":"Niedersachsen",
    "wof:name":"Multi-service-claa\u00dfen",
    "wof:placetype":"venue"
},
  "geometry": {"coordinates":[9.745335,52.382221],"type":"Point"}
}