{
  "type": "Feature",
  "properties": {
    "iso:country":"DE",
    "sg:address":"Stargarder Weg 6",
    "sg:city":"Reinbek",
    "sg:phone":"+49 40/7221263",
    "sg:postcode":"21465",
    "sg:province":"Schleswig-Holstein",
    "wof:name":"Klaus-d. W\u00f6hrmann",
    "wof:placetype":"venue"
},
  "geometry": {"coordinates":[10.2525072098,53.5194625854],"type":"Point"}
}