{
  "type": "Feature",
  "properties": {
    "iso:country":"DE",
    "sg:address":"Sch\u00f6nblick 5",
    "sg:city":"Reichertshofen",
    "sg:phone":"+49 8453/1504",
    "sg:postcode":"85084",
    "sg:province":"Bayern",
    "wof:name":"W. Losch",
    "wof:placetype":"venue"
},
  "geometry": {"coordinates":[11.510652,48.635941],"type":"Point"}
}