{
  "type": "Feature",
  "properties": {
    "iso:country":"DE",
    "sg:address":"Im Tiegel 9",
    "sg:city":"Wartenberg",
    "sg:postcode":"36367",
    "sg:province":"Hessen",
    "wof:name":"Thiesen Hardware- Und Software-design Gmbh",
    "wof:placetype":"venue"
},
  "geometry": {"coordinates":[9.4563856125,50.6235542297],"type":"Point"}
}