{
  "type": "Feature",
  "properties": {
    "iso:country":"DE",
    "sg:city":"Jessern",
    "sg:phone":"+49 35478/608",
    "sg:postcode":"15913",
    "sg:province":"Brandenburg",
    "wof:name":"Camping Jessern",
    "wof:placetype":"venue"
},
  "geometry": {"coordinates":[14.194228,52.02457],"type":"Point"}
}