{
  "type": "Feature",
  "properties": {
    "iso:country":"DE",
    "sg:address":"Neust\u00e4dter Str. 54",
    "sg:city":"Muchow",
    "sg:phone":"+49 38752/80701",
    "sg:postcode":"19300",
    "sg:province":"Mecklenburg-Vorpommern",
    "wof:name":"Balow & M\u00d6llenbecker Landerzeugerges. Mbh",
    "wof:placetype":"venue"
},
  "geometry": {"coordinates":[11.6862430573,53.3145065308],"type":"Point"}
}