{
  "type": "Feature",
  "properties": {
    "iso:country":"DE",
    "sg:address":"Galvanistr. 12",
    "sg:city":"Berlin",
    "sg:phone":"+49 30/3423094",
    "sg:postcode":"10587",
    "sg:province":"Berlin",
    "wof:name":"Gastst\u00e4tte Moustache",
    "wof:placetype":"venue"
},
  "geometry": {"coordinates":[13.3184223175,52.5192298889],"type":"Point"}
}