{
  "type": "Feature",
  "properties": {
    "iso:country":"DE",
    "sg:address":"Margarethenstr. 5",
    "sg:city":"Hochheim",
    "sg:phone":"+49 6146/835979",
    "sg:postcode":"65239",
    "sg:province":"Hessen",
    "wof:name":"Quink-klein Weinanbau",
    "wof:placetype":"venue"
},
  "geometry": {"coordinates":[8.3528900146,50.0131912231],"type":"Point"}
}