{
  "type": "Feature",
  "properties": {
    "iso:country":"DE",
    "sg:address":"Schulstr. 2a",
    "sg:city":"Klein Nordende",
    "sg:phone":"+49 4121/91253",
    "sg:postcode":"25336",
    "sg:province":"Schleswig-Holstein",
    "wof:name":"Kreissparkasse Pinneberg",
    "wof:placetype":"venue"
},
  "geometry": {"coordinates":[9.66259,53.726875],"type":"Point"}
}