{
  "type": "Feature",
  "properties": {
    "iso:country":"DE",
    "sg:address":"Weiherplatz 8",
    "sg:city":"Neuwied",
    "sg:phone":"+49 2631/71930",
    "sg:postcode":"56567",
    "sg:province":"Rheinland-Pfalz",
    "wof:name":"Rathaus-apotheke",
    "wof:placetype":"venue"
},
  "geometry": {"coordinates":[7.443428,50.442383],"type":"Point"}
}