{
  "type": "Feature",
  "properties": {
    "iso:country":"DE",
    "sg:address":"H\u00fcttruper Heide 71",
    "sg:city":"Greven",
    "sg:phone":"+49 2571/91027",
    "sg:postcode":"48268",
    "sg:province":"Nordrhein-Westfalen",
    "wof:name":"Its Gmbh",
    "wof:placetype":"venue"
},
  "geometry": {"coordinates":[7.6916542053,52.1301193237],"type":"Point"}
}