{
  "type": "Feature",
  "properties": {
    "iso:country":"DE",
    "sg:address":"Wallstr. 29",
    "sg:city":"Itzehoe",
    "sg:phone":"+49 4821/3975",
    "sg:postcode":"25524",
    "sg:province":"Schleswig-Holstein",
    "wof:name":"Klaus Kunert Architekt",
    "wof:placetype":"venue"
},
  "geometry": {"coordinates":[9.51455,53.921265],"type":"Point"}
}