{
  "type": "Feature",
  "properties": {
    "iso:country":"DE",
    "sg:address":"Arendseer Str. 44",
    "sg:city":"Seehausen",
    "sg:phone":"+49 39386/54731",
    "sg:postcode":"39615",
    "sg:province":"Sachsen-Anhalt",
    "wof:name":"Kg Behn Und Behn Gro\u00dfhandel Gmbh & Co.",
    "wof:placetype":"venue"
},
  "geometry": {"coordinates":[11.753484726,52.8939094543],"type":"Point"}
}