{
  "type": "Feature",
  "properties": {
    "iso:country":"DE",
    "sg:address":"Borkumer Weg 2c",
    "sg:city":"Leipzig",
    "sg:phone":"+49 341/9126107",
    "sg:postcode":"04157",
    "sg:province":"Sachsen",
    "wof:name":"Andreas Siwoda",
    "wof:placetype":"venue"
},
  "geometry": {"coordinates":[12.36427,51.377106],"type":"Point"}
}