{
  "type": "Feature",
  "properties": {
    "iso:country":"DE",
    "sg:address":"Plauener Weg 14",
    "sg:city":"Murrhardt",
    "sg:phone":"+49 7192/7518",
    "sg:postcode":"71540",
    "sg:province":"Baden-W\u00fcrttemberg",
    "wof:name":"Erwin Lindheimer",
    "wof:placetype":"venue"
},
  "geometry": {"coordinates":[9.555393,48.983044],"type":"Point"}
}