{
  "type": "Feature",
  "properties": {
    "iso:country":"DE",
    "sg:address":"Bahnhofsplatz 1",
    "sg:city":"Wernigerode",
    "sg:phone":"+49 3943/632618",
    "sg:postcode":"38855",
    "sg:province":"Sachsen-Anhalt",
    "wof:name":"Pizza-treff",
    "wof:placetype":"venue"
},
  "geometry": {"coordinates":[10.789465,51.840099],"type":"Point"}
}