{
  "type": "Feature",
  "properties": {
    "iso:country":"DE",
    "sg:address":"Bahnhofstr. 16",
    "sg:city":"Hassendorf",
    "sg:phone":"+49 4264/2906",
    "sg:postcode":"27367",
    "sg:province":"Niedersachsen",
    "wof:name":"Hans H. Behrens",
    "wof:placetype":"venue"
},
  "geometry": {"coordinates":[9.267946,53.112442],"type":"Point"}
}