{
  "type": "Feature",
  "properties": {
    "iso:country":"DE",
    "sg:address":"Schulstr. 9",
    "sg:city":"Reutlingen",
    "sg:phone":"+49 7121/31280",
    "sg:postcode":"72764",
    "sg:province":"Baden-W\u00fcrttemberg",
    "wof:name":"Lobitz Gmbh",
    "wof:placetype":"venue"
},
  "geometry": {"coordinates":[9.2137994766,48.4940490723],"type":"Point"}
}