{
  "type": "Feature",
  "properties": {
    "iso:country":"DE",
    "sg:address":"Burgweg 25",
    "sg:city":"Seehausen",
    "sg:phone":"+49 8841/2480",
    "sg:postcode":"82418",
    "sg:province":"Bayern",
    "wof:name":"Klaus Lindner Architekt",
    "wof:placetype":"venue"
},
  "geometry": {"coordinates":[11.200964,47.676182],"type":"Point"}
}