{
  "type": "Feature",
  "properties": {
    "iso:country":"DE",
    "sg:address":"Triftser Weg 10",
    "sg:city":"Wangen",
    "sg:phone":"+49 7522/29173",
    "sg:postcode":"88239",
    "sg:province":"Baden-W\u00fcrttemberg",
    "wof:name":"A. Und M. Martinec",
    "wof:placetype":"venue"
},
  "geometry": {"coordinates":[9.8195152283,47.7089347839],"type":"Point"}
}