{
  "type": "Feature",
  "properties": {
    "iso:country":"DE",
    "sg:address":"Kirchhaslacher Str 30",
    "sg:city":"Breitenbrunn",
    "sg:phone":"+49 8263/511",
    "sg:postcode":"87739",
    "sg:province":"Bayern",
    "wof:name":"August Ritter Gmbh",
    "wof:placetype":"venue"
},
  "geometry": {"coordinates":[10.398178,48.137539],"type":"Point"}
}