{
  "type": "Feature",
  "properties": {
    "iso:country":"DE",
    "sg:address":"Zizenhausen 3",
    "sg:city":"Bad Saulgau",
    "sg:phone":"+49 7581/2184",
    "sg:postcode":"88348",
    "sg:province":"Baden-W\u00fcrttemberg",
    "wof:name":"Club Wagenhausen Gastst\u00e4tte",
    "wof:placetype":"venue"
},
  "geometry": {"coordinates":[9.4973373413,48.0160484314],"type":"Point"}
}