{
  "type": "Feature",
  "properties": {
    "iso:country":"DE",
    "sg:address":"K\u00f6lner Landstr. 271",
    "sg:city":"D\u00fcsseldorf",
    "sg:postcode":"40589",
    "sg:province":"Nordrhein-Westfalen",
    "wof:name":"Krimpex Gmbh",
    "wof:placetype":"venue"
},
  "geometry": {"coordinates":[6.8213429451,51.1836280823],"type":"Point"}
}