{
  "type": "Feature",
  "properties": {
    "iso:country":"DE",
    "sg:address":"Wesostr. 180",
    "sg:city":"Pfinztal",
    "sg:phone":"+49 7240/1403",
    "sg:postcode":"76327",
    "sg:province":"Baden-W\u00fcrttemberg",
    "wof:name":"Emil Kohler",
    "wof:placetype":"venue"
},
  "geometry": {"coordinates":[8.559137,49.00732],"type":"Point"}
}