{
  "type": "Feature",
  "properties": {
    "iso:country":"DE",
    "sg:city":"Bebra",
    "sg:postcode":"36179",
    "sg:province":"Hessen",
    "wof:name":"Fit & Fun Fitnessclub Bebra",
    "wof:placetype":"venue"
},
  "geometry": {"coordinates":[9.794343,50.970985],"type":"Point"}
}