{
  "type": "Feature",
  "properties": {
    "iso:country":"DE",
    "sg:address":"Striegauer Str. 1",
    "sg:city":"Bielefeld",
    "sg:phone":"+49 521/207272",
    "sg:postcode":"33719",
    "sg:province":"Nordrhein-Westfalen",
    "wof:name":"Honorarkonsulat Von \u00d6sterreich",
    "wof:placetype":"venue"
},
  "geometry": {"coordinates":[8.5927667618,52.0123558044],"type":"Point"}
}