{
  "type": "Feature",
  "properties": {
    "iso:country":"DE",
    "sg:address":"Bei der Schleifm\u00fchle 34",
    "sg:city":"Ingolstadt",
    "sg:phone":"+49 841/1369",
    "sg:postcode":"85049",
    "sg:province":"Bayern",
    "wof:name":"Heino Mark Steuerberater",
    "wof:placetype":"venue"
},
  "geometry": {"coordinates":[11.4223775864,48.7615661621],"type":"Point"}
}