{
  "type": "Feature",
  "properties": {
    "iso:country":"DE",
    "sg:address":"Kalefelder Str. 26",
    "sg:city":"Northeim",
    "sg:phone":"+49 5551/53524",
    "sg:postcode":"37154",
    "sg:province":"Niedersachsen",
    "wof:name":"Horst Pflugmacher",
    "wof:placetype":"venue"
},
  "geometry": {"coordinates":[9.974474,51.753716],"type":"Point"}
}