{
  "type": "Feature",
  "properties": {
    "iso:country":"DE",
    "sg:address":"Abigstr. 9",
    "sg:city":"\u00dcberlingen",
    "sg:phone":"+49 7551",
    "sg:postcode":"88662",
    "sg:province":"Baden-W\u00fcrttemberg",
    "wof:name":"Orgelbau Raffin Gmbh",
    "wof:placetype":"venue"
},
  "geometry": {"coordinates":[9.187662,47.773842],"type":"Point"}
}