{
  "type": "Feature",
  "properties": {
    "iso:country":"DE",
    "sg:address":"Bismarckstr. 52",
    "sg:city":"H\u00f6chst",
    "sg:phone":"+49 6163/9420",
    "sg:postcode":"64739",
    "sg:province":"Hessen",
    "wof:name":"Hallenbad Der Ernst-g\u00f6bel-schule",
    "wof:placetype":"venue"
},
  "geometry": {"coordinates":[8.991522789,49.7937202454],"type":"Point"}
}