{
  "type": "Feature",
  "properties": {
    "iso:country":"DE",
    "sg:address":"Lehenweg 21",
    "sg:city":"Giengen",
    "sg:phone":"+49 7322/7371",
    "sg:postcode":"89537",
    "sg:province":"Baden-W\u00fcrttemberg",
    "wof:name":"B\u00fchlerh\u00f6he",
    "wof:placetype":"venue"
},
  "geometry": {"coordinates":[10.2262411118,48.6186485291],"type":"Point"}
}