{
  "type": "Feature",
  "properties": {
    "iso:country":"DE",
    "sg:address":"Interspar",
    "sg:city":"Rosenheim",
    "sg:phone":"+49 8031/69530",
    "sg:postcode":"83026",
    "sg:province":"Bayern",
    "wof:name":"S. Lanzl",
    "wof:placetype":"venue"
},
  "geometry": {"coordinates":[12.094669,47.825439],"type":"Point"}
}