{
  "type": "Feature",
  "properties": {
    "iso:country":"DE",
    "sg:address":"Orkestr. 8",
    "sg:city":"Winterberg",
    "sg:phone":"+49 2981/1204",
    "sg:postcode":"59955",
    "sg:province":"Nordrhein-Westfalen",
    "wof:name":"Pension Lorenz Sommer",
    "wof:placetype":"venue"
},
  "geometry": {"coordinates":[8.5347223282,51.2004928589],"type":"Point"}
}