{
  "type": "Feature",
  "properties": {
    "iso:country":"DE",
    "sg:address":"Gerichtsweg 3",
    "sg:city":"Hermannsburg",
    "sg:phone":"+49 5052/6054",
    "sg:postcode":"29320",
    "sg:province":"Niedersachsen",
    "wof:name":"Bonito Inh. Peter Walter",
    "wof:placetype":"venue"
},
  "geometry": {"coordinates":[10.0903625488,52.8310470581],"type":"Point"}
}