{
  "type": "Feature",
  "properties": {
    "iso:country":"DE",
    "sg:address":"Pl\u00f6ner Landstr. 36",
    "sg:city":"Schellhorn",
    "sg:phone":"+49 4342/889760",
    "sg:postcode":"24211",
    "sg:province":"Schleswig-Holstein",
    "wof:name":"Aas-autorisierte Allgemeine Steuerberatungs Gmbh",
    "wof:placetype":"venue"
},
  "geometry": {"coordinates":[10.297504425,54.228427887],"type":"Point"}
}