{
  "type": "Feature",
  "properties": {
    "iso:country":"DE",
    "sg:address":"F\u00f6hrenweg 18",
    "sg:city":"Forchheim",
    "sg:phone":"+49 9191/4458",
    "sg:postcode":"91301",
    "sg:province":"Bayern",
    "wof:name":"Rich. Endres Fliesenlegerei",
    "wof:placetype":"venue"
},
  "geometry": {"coordinates":[11.049990654,49.7245521545],"type":"Point"}
}