{
  "type": "Feature",
  "properties": {
    "iso:country":"DE",
    "sg:address":"Holzmarkt 6",
    "sg:city":"Arnstadt",
    "sg:phone":"+49 3628/602595",
    "sg:postcode":"99310",
    "sg:province":"Th\u00fcringen",
    "wof:name":"Harald Fischer",
    "wof:placetype":"venue"
},
  "geometry": {"coordinates":[10.947669,50.833698],"type":"Point"}
}