{
  "type": "Feature",
  "properties": {
    "iso:country":"DE",
    "sg:address":"Neue M\u00fchle 16",
    "sg:city":"Legden",
    "sg:phone":"+49 2566/1295",
    "sg:postcode":"48739",
    "sg:province":"Nordrhein-Westfalen",
    "wof:name":"Rudde Gmbh",
    "wof:placetype":"venue"
},
  "geometry": {"coordinates":[7.0908398628,52.0405082703],"type":"Point"}
}