{
  "type": "Feature",
  "properties": {
    "iso:country":"DE",
    "sg:address":"Nordstra\u00dfe 8",
    "sg:city":"Mogendorf",
    "sg:phone":"+49 2623",
    "sg:postcode":"56424",
    "sg:province":"Rheinland-Pfalz",
    "wof:name":"Dc-music Veranstaltungstechnik",
    "wof:placetype":"venue"
},
  "geometry": {"coordinates":[7.756178,50.491402],"type":"Point"}
}