{
  "type": "Feature",
  "properties": {
    "iso:country":"DE",
    "sg:address":"Marktplatz 4",
    "sg:city":"Niederwerrn",
    "sg:phone":"+49 9721/48825",
    "sg:postcode":"97464",
    "sg:province":"Bayern",
    "wof:name":"Pizzeria Italo",
    "wof:placetype":"venue"
},
  "geometry": {"coordinates":[10.1834621429,50.0604743958],"type":"Point"}
}