{
  "type": "Feature",
  "properties": {
    "iso:country":"DE",
    "sg:address":"Geulenstr. 16",
    "sg:city":"Neuss",
    "sg:phone":"+49 2131/547219",
    "sg:postcode":"41462",
    "sg:province":"Nordrhein-Westfalen",
    "wof:name":"Wolfgang Ponzelar",
    "wof:placetype":"venue"
},
  "geometry": {"coordinates":[6.6631631851,51.2151260376],"type":"Point"}
}