{
  "type": "Feature",
  "properties": {
    "iso:country":"DE",
    "sg:address":"Lange Str. 34 a",
    "sg:city":"Ostseebad Prerow",
    "sg:postcode":"18375",
    "sg:province":"Mecklenburg-Vorpommern",
    "wof:name":"Th. Linke",
    "wof:placetype":"venue"
},
  "geometry": {"coordinates":[12.573331,54.446537],"type":"Point"}
}