{
  "type": "Feature",
  "properties": {
    "iso:country":"DE",
    "sg:address":"Crimmitschauer Stra\u00dfe 36",
    "sg:city":"Werdau",
    "sg:phone":"+49 4937/6118240",
    "sg:postcode":"08412",
    "sg:province":"Sachsen",
    "wof:name":"Schlenker Gmbh Aircondition And Refrigeratiom",
    "wof:placetype":"venue"
},
  "geometry": {"coordinates":[12.3736505508,50.7450065613],"type":"Point"}
}