{
  "type": "Feature",
  "properties": {
    "iso:country":"DE",
    "sg:address":"Auf dem Emmerberge 24",
    "sg:city":"Hannover",
    "sg:phone":"+49 511/803034",
    "sg:postcode":"30169",
    "sg:province":"Niedersachsen",
    "wof:name":"Walter Buero\u00dfe Architekt",
    "wof:placetype":"venue"
},
  "geometry": {"coordinates":[9.741749,52.362877],"type":"Point"}
}