{
  "type": "Feature",
  "properties": {
    "iso:country":"DE",
    "sg:address":"Barbarastr. 9",
    "sg:city":"Friedberg",
    "sg:phone":"+49 6031/12676",
    "sg:postcode":"61169",
    "sg:province":"Hessen",
    "wof:name":"Atelier Rau",
    "wof:placetype":"venue"
},
  "geometry": {"coordinates":[8.759098053,50.3373641968],"type":"Point"}
}