{
  "type": "Feature",
  "properties": {
    "iso:country":"DE",
    "sg:address":"Daimlerstrasse 29",
    "sg:city":"Stuttgart-Bad Cannstatt",
    "sg:phone":"+49 711/569467",
    "sg:postcode":"70372",
    "sg:province":"Baden-W\u00fcrttemberg",
    "wof:name":"Kunst:: Ulrich Zeh: Zeitgen\u00f6ssische Malerei",
    "wof:placetype":"venue"
},
  "geometry": {"coordinates":[9.219416,48.804752],"type":"Point"}
}