{
  "type": "Feature",
  "properties": {
    "iso:country":"DE",
    "sg:address":"In der Schiffheide 46",
    "sg:city":"Rheda-Wiedenbr\u00fcck",
    "sg:phone":"+49 5242/404005",
    "sg:postcode":"33378",
    "sg:province":"Nordrhein-Westfalen",
    "wof:name":"Restaurant Heidekrug",
    "wof:placetype":"venue"
},
  "geometry": {"coordinates":[8.3139820099,51.8562049866],"type":"Point"}
}