{
  "type": "Feature",
  "properties": {
    "iso:country":"DE",
    "sg:address":"Friedenstr. 3",
    "sg:city":"Bayreuth",
    "sg:phone":"+49 921/65229",
    "sg:postcode":"95447",
    "sg:province":"Bayern",
    "wof:name":"Ev. Luth. Pfarramt",
    "wof:placetype":"venue"
},
  "geometry": {"coordinates":[11.5779943466,49.9301223755],"type":"Point"}
}