{
  "type": "Feature",
  "properties": {
    "iso:country":"DE",
    "sg:address":"Hauptstr. 17-19",
    "sg:city":"Schramberg",
    "sg:phone":"+49 7422/20835",
    "sg:postcode":"78713",
    "sg:province":"Baden-W\u00fcrttemberg",
    "wof:name":"Kr\u00f6n E. K.",
    "wof:placetype":"venue"
},
  "geometry": {"coordinates":[8.384915,48.226261],"type":"Point"}
}