{
  "type": "Feature",
  "properties": {
    "iso:country":"DE",
    "sg:address":"Birkenweg 15",
    "sg:city":"Staig",
    "sg:phone":"+49 7346/450",
    "sg:postcode":"89195",
    "sg:province":"Baden-W\u00fcrttemberg",
    "wof:name":"Rampf Planen-bauen Gmbh",
    "wof:placetype":"venue"
},
  "geometry": {"coordinates":[9.985672,48.302589],"type":"Point"}
}