{
  "type": "Feature",
  "properties": {
    "iso:country":"DE",
    "sg:address":"Hakenort 65",
    "sg:city":"Bielefeld",
    "sg:postcode":"33609",
    "sg:province":"Nordrhein-Westfalen",
    "wof:name":"K & K Reinigungskomponenten Handelsgesellschaft Mbh",
    "wof:placetype":"venue"
},
  "geometry": {"coordinates":[8.5553474426,52.0308876038],"type":"Point"}
}