{
  "type": "Feature",
  "properties": {
    "iso:country":"DE",
    "sg:address":"Hauptstr. 84",
    "sg:city":"Mosbach",
    "sg:phone":"+49 4962/612975",
    "sg:postcode":"74821",
    "sg:province":"Baden-W\u00fcrttemberg",
    "wof:name":"Badische Beamtenbank Eg",
    "wof:placetype":"venue"
},
  "geometry": {"coordinates":[9.147026,49.353237],"type":"Point"}
}