{
  "type": "Feature",
  "properties": {
    "iso:country":"DE",
    "sg:address":"August-Bebel-Str. 11",
    "sg:city":"Borsdorf",
    "sg:phone":"+49 34291/86727",
    "sg:postcode":"04451",
    "sg:province":"Sachsen",
    "wof:name":"G. Gruhle Inh. E. Hanke",
    "wof:placetype":"venue"
},
  "geometry": {"coordinates":[12.537402153,51.3471221924],"type":"Point"}
}