{
  "type": "Feature",
  "properties": {
    "iso:country":"DE",
    "sg:address":"Franz-Darpe-Str. 19",
    "sg:city":"Warendorf",
    "sg:phone":"+49 2581/634863",
    "sg:postcode":"48231",
    "sg:province":"Nordrhein-Westfalen",
    "wof:name":"Omt Gmbh",
    "wof:placetype":"venue"
},
  "geometry": {"coordinates":[7.9975800514,51.9430084229],"type":"Point"}
}