{
  "type": "Feature",
  "properties": {
    "iso:country":"DE",
    "sg:address":"B\u00f6cklinstr. 2",
    "sg:city":"M\u00fcnchen",
    "sg:phone":"+49 89/155677",
    "sg:postcode":"80638",
    "sg:province":"Bayern",
    "wof:name":"Prof. Karin Maurer Architektin",
    "wof:placetype":"venue"
},
  "geometry": {"coordinates":[11.527222,48.159538],"type":"Point"}
}