{
  "type": "Feature",
  "properties": {
    "iso:country":"DE",
    "sg:address":"Alexanderstr. 24",
    "sg:city":"Hamburg",
    "sg:phone":"+49 40/2802315",
    "sg:postcode":"20099",
    "sg:province":"Hamburg",
    "wof:name":"Buck Sanit\u00e4rtechnik",
    "wof:placetype":"venue"
},
  "geometry": {"coordinates":[10.0198459625,53.5553474426],"type":"Point"}
}