{
  "type": "Feature",
  "properties": {
    "iso:country":"DE",
    "sg:address":"Bahnhofstr. 13",
    "sg:city":"Frankenberg",
    "sg:phone":"+49 6451/3178",
    "sg:postcode":"35066",
    "sg:province":"Hessen",
    "wof:name":"Ele Moden Inh. Elfriede Stremme E. Kfr.",
    "wof:placetype":"venue"
},
  "geometry": {"coordinates":[8.7933015823,51.0564193726],"type":"Point"}
}