{
  "type": "Feature",
  "properties": {
    "iso:country":"DE",
    "sg:address":"Bachstr. 26",
    "sg:city":"H\u00fcrth",
    "sg:phone":"+49 2233/64734",
    "sg:postcode":"50354",
    "sg:province":"Nordrhein-Westfalen",
    "wof:name":"Haus Burgpark",
    "wof:placetype":"venue"
},
  "geometry": {"coordinates":[6.895277977,50.8945426941],"type":"Point"}
}