{
  "type": "Feature",
  "properties": {
    "iso:country":"DE",
    "sg:address":"Am Camps 7",
    "sg:city":"Havelberg",
    "sg:phone":"+49 39387/21606",
    "sg:postcode":"39539",
    "sg:province":"Sachsen-Anhalt",
    "wof:name":"I. Hass",
    "wof:placetype":"venue"
},
  "geometry": {"coordinates":[12.07392,52.82848],"type":"Point"}
}