{
  "type": "Feature",
  "properties": {
    "iso:country":"DE",
    "sg:address":"Oststr. 1",
    "sg:city":"Halver",
    "sg:phone":"+49 2353/91810",
    "sg:postcode":"58553",
    "sg:province":"Nordrhein-Westfalen",
    "wof:name":"Kirchhoff Gmbh & Co. Kg",
    "wof:placetype":"venue"
},
  "geometry": {"coordinates":[7.503703,51.197186],"type":"Point"}
}