{
  "type": "Feature",
  "properties": {
    "iso:country":"DE",
    "sg:address":"Lindenall. 27",
    "sg:city":"Wuppertal",
    "sg:phone":"+49 4920/247910",
    "sg:postcode":"42349",
    "sg:province":"Nordrhein-Westfalen",
    "wof:name":"Eduard Wille Gmbh & Co Kg",
    "wof:placetype":"venue"
},
  "geometry": {"coordinates":[7.134003,51.205536],"type":"Point"}
}