{
  "type": "Feature",
  "properties": {
    "iso:country":"DE",
    "sg:address":"Ockenheimer Chaussee 18",
    "sg:city":"Bingen",
    "sg:phone":"+49 6721/45695",
    "sg:postcode":"55411",
    "sg:province":"Rheinland-Pfalz",
    "wof:name":"Woog Gmbh",
    "wof:placetype":"venue"
},
  "geometry": {"coordinates":[7.922026,49.947571],"type":"Point"}
}