{
  "type": "Feature",
  "properties": {
    "iso:country":"DE",
    "sg:address":"Damm\u00fchlenweg 23",
    "sg:city":"Haldensleben",
    "sg:phone":"+49 3904/41939",
    "sg:postcode":"39340",
    "sg:province":"Sachsen-Anhalt",
    "wof:name":"J. Und P. Mittendorf",
    "wof:placetype":"venue"
},
  "geometry": {"coordinates":[11.424764,52.267704],"type":"Point"}
}