{
  "type": "Feature",
  "properties": {
    "iso:country":"DE",
    "sg:address":"Ludwig-Weisser-Str. 3",
    "sg:city":"St. Georgen",
    "sg:phone":"+49 7724/7105",
    "sg:postcode":"78112",
    "sg:province":"Baden-W\u00fcrttemberg",
    "wof:name":"Ruemo-modellbau Walter R\u00fcck",
    "wof:placetype":"venue"
},
  "geometry": {"coordinates":[8.341121,48.129906],"type":"Point"}
}