{
  "type": "Feature",
  "properties": {
    "iso:country":"DE",
    "sg:address":"Bredowstr. 23",
    "sg:city":"Hamburg",
    "sg:phone":"+49 40/7336040",
    "sg:postcode":"22113",
    "sg:province":"Schleswig-Holstein",
    "wof:name":"Arno Rosenl\u00f6cher Gmbh & Co.",
    "wof:placetype":"venue"
},
  "geometry": {"coordinates":[10.087484,53.522995],"type":"Point"}
}