{
  "type": "Feature",
  "properties": {
    "iso:country":"DE",
    "sg:address":"Bismarckstr. 26",
    "sg:city":"Delitzsch",
    "sg:phone":"+49 34202/63537",
    "sg:postcode":"04509",
    "sg:province":"Sachsen",
    "wof:name":"Heinz Kunze",
    "wof:placetype":"venue"
},
  "geometry": {"coordinates":[12.3399057388,51.5221290588],"type":"Point"}
}