{
  "type": "Feature",
  "properties": {
    "iso:country":"DE",
    "sg:address":"Fritzenberg",
    "sg:city":"Groitzsch",
    "sg:phone":"+49 34296/42358",
    "sg:postcode":"04539",
    "sg:province":"Sachsen",
    "wof:name":"Rudolf Schumann",
    "wof:placetype":"venue"
},
  "geometry": {"coordinates":[12.271605,51.150349],"type":"Point"}
}