{
  "type": "Feature",
  "properties": {
    "iso:country":"DE",
    "sg:address":"Mendelstr. 11",
    "sg:city":"M\u00fcnster",
    "sg:postcode":"48149",
    "sg:province":"Nordrhein-Westfalen",
    "wof:name":"Beatge Rating-network Gmbh",
    "wof:placetype":"venue"
},
  "geometry": {"coordinates":[7.592248,51.970245],"type":"Point"}
}