{
  "type": "Feature",
  "properties": {
    "iso:country":"DE",
    "sg:address":"B\u00f6rsenplatz",
    "sg:city":"Frankfurt",
    "sg:phone":"+49 4969/6960",
    "sg:postcode":"60313",
    "sg:province":"Hessen",
    "wof:name":"Deutsche Lufthansa Ag",
    "wof:placetype":"venue"
},
  "geometry": {"coordinates":[6.9700160027,50.9355506897],"type":"Point"}
}