{
  "type": "Feature",
  "properties": {
    "iso:country":"DE",
    "sg:address":"Untere Hauptstr. 37",
    "sg:city":"M\u00fchlau",
    "sg:phone":"+49 3722/93410",
    "sg:postcode":"09241",
    "sg:province":"Sachsen",
    "wof:name":"Rolf Berthold",
    "wof:placetype":"venue"
},
  "geometry": {"coordinates":[12.7620716095,50.9033851624],"type":"Point"}
}