{
  "type": "Feature",
  "properties": {
    "iso:country":"DE",
    "sg:address":"Im Kl\u00e4uerchen 8",
    "sg:city":"Oppenheim",
    "sg:postcode":"55276",
    "sg:province":"Rheinland-Pfalz",
    "wof:name":"Humancapital M. D. Beteiligungsgesellschaft Mbh",
    "wof:placetype":"venue"
},
  "geometry": {"coordinates":[8.367355,49.851002],"type":"Point"}
}