{
  "type": "Feature",
  "properties": {
    "iso:country":"DE",
    "sg:address":"Spittastr. 10",
    "sg:city":"Wittingen",
    "sg:phone":"+49 5831/8442",
    "sg:postcode":"29378",
    "sg:province":"Niedersachsen",
    "wof:name":"Hans Preu\u00dfe Rechtsanwalt",
    "wof:placetype":"venue"
},
  "geometry": {"coordinates":[10.735042572,52.7270774841],"type":"Point"}
}