{
  "type": "Feature",
  "properties": {
    "iso:country":"DE",
    "sg:address":"Markusstr. 1",
    "sg:city":"Welschbillig",
    "sg:phone":"+49 6506/219",
    "sg:postcode":"54298",
    "sg:province":"Rheinland-Pfalz",
    "wof:name":"Kath. Pfarramt St. Petrus",
    "wof:placetype":"venue"
},
  "geometry": {"coordinates":[6.6237721443,49.8674430847],"type":"Point"}
}