{
  "type": "Feature",
  "properties": {
    "iso:country":"DE",
    "sg:address":"Philipp-Reis-Str. 5 POSTFACH 1101",
    "sg:city":"Laubach",
    "sg:phone":"+49 6405/505800",
    "sg:postcode":"35316",
    "sg:province":"Hessen",
    "wof:name":"Schwa-medico Medizinischeapparate Vertriebs Gmbh",
    "wof:placetype":"venue"
},
  "geometry": {"coordinates":[8.978282,50.544006],"type":"Point"}
}