{
  "type": "Feature",
  "properties": {
    "iso:country":"DE",
    "sg:address":"S\u00fcd-Nord-Str. 14",
    "sg:city":"Geeste",
    "sg:phone":"+49 5925/392",
    "sg:postcode":"49744",
    "sg:province":"Niedersachsen",
    "wof:name":"Franz Paul",
    "wof:placetype":"venue"
},
  "geometry": {"coordinates":[7.177861,52.564632],"type":"Point"}
}