{
  "type": "Feature",
  "properties": {
    "iso:country":"DE",
    "sg:address":"Bilsteiner Str. 3",
    "sg:city":"K\u00f6ln",
    "sg:phone":"+49 221/896209",
    "sg:postcode":"51109",
    "sg:province":"Nordrhein-Westfalen",
    "wof:name":"Em Heidest\u00fcffge",
    "wof:placetype":"venue"
},
  "geometry": {"coordinates":[7.03748703,50.9412612915],"type":"Point"}
}