{
  "type": "Feature",
  "properties": {
    "iso:country":"DE",
    "sg:address":"Klubgartenstr. 1",
    "sg:city":"Goslar",
    "sg:postcode":"38640",
    "sg:province":"Niedersachsen",
    "wof:name":"Nieders\u00e4chsischer Hof Betriebsgesellschaft Mbh",
    "wof:placetype":"venue"
},
  "geometry": {"coordinates":[10.423874855,51.9104003906],"type":"Point"}
}