{
  "type": "Feature",
  "properties": {
    "iso:country":"DE",
    "sg:address":"Bahnhofstr. 55",
    "sg:city":"Sch\u00f6nenberg-K\u00fcbelberg",
    "sg:phone":"+49 6373/4770",
    "sg:postcode":"66901",
    "sg:province":"Rheinland-Pfalz",
    "wof:name":"Wewoba Westricher Wohnungsbau Gmbh",
    "wof:placetype":"venue"
},
  "geometry": {"coordinates":[7.3763618469,49.4062385559],"type":"Point"}
}