{
  "type": "Feature",
  "properties": {
    "iso:country":"DE",
    "sg:address":"Elsterwerdaer Str. 52",
    "sg:city":"Lauchhammer",
    "sg:phone":"+49 3574/7156",
    "sg:postcode":"01979",
    "sg:province":"Brandenburg",
    "wof:name":"H. Wiedemann",
    "wof:placetype":"venue"
},
  "geometry": {"coordinates":[13.728412,51.474445],"type":"Point"}
}