{
  "type": "Feature",
  "properties": {
    "iso:country":"DE",
    "sg:address":"Rosenstr. 9",
    "sg:city":"Marienhafe",
    "sg:phone":"+49 4934/4025",
    "sg:postcode":"26529",
    "sg:province":"Niedersachsen",
    "wof:name":"Cornelia Strau\u00df",
    "wof:placetype":"venue"
},
  "geometry": {"coordinates":[7.2738518715,53.5221366882],"type":"Point"}
}