{
  "type": "Feature",
  "properties": {
    "iso:country":"DE",
    "sg:address":"Kalverbenden 73",
    "sg:city":"Aachen",
    "sg:phone":"+49 241/500069",
    "sg:postcode":"52066",
    "sg:province":"Nordrhein-Westfalen",
    "wof:name":"Karl-heinz Romme Architekt",
    "wof:placetype":"venue"
},
  "geometry": {"coordinates":[6.098861,50.75647],"type":"Point"}
}