{
  "type": "Feature",
  "properties": {
    "iso:country":"DE",
    "sg:address":"Morier Str. 35B",
    "sg:city":"Stockelsdorf",
    "sg:phone":"+49 451/21168",
    "sg:postcode":"23617",
    "sg:province":"Schleswig-Holstein",
    "wof:name":"J.-p. M\u00fcggenburg",
    "wof:placetype":"venue"
},
  "geometry": {"coordinates":[10.6381883621,53.883266449],"type":"Point"}
}