{
  "type": "Feature",
  "properties": {
    "iso:country":"DE",
    "sg:address":"H\u00e4nselweg 6",
    "sg:city":"Neunkirchen-Seelscheid",
    "sg:postcode":"53819",
    "sg:province":"Nordrhein-Westfalen",
    "wof:name":"Koop K\u00fcchen",
    "wof:placetype":"venue"
},
  "geometry": {"coordinates":[7.3851599693,50.8524513245],"type":"Point"}
}