{
  "type": "Feature",
  "properties": {
    "iso:country":"DE",
    "sg:address":"Tannenweg 12",
    "sg:city":"Spangenberg",
    "sg:phone":"+49 5663/403",
    "sg:postcode":"34286",
    "sg:province":"Hessen",
    "wof:name":"Tischlerei Ackermann Gmbh",
    "wof:placetype":"venue"
},
  "geometry": {"coordinates":[9.720089,51.090195],"type":"Point"}
}