{
  "type": "Feature",
  "properties": {
    "iso:country":"DE",
    "sg:address":"J-Friedr-B\u00f6ttger-Str 1",
    "sg:city":"Ilmenau",
    "sg:phone":"+49 3677/61241",
    "sg:postcode":"98693",
    "sg:province":"Th\u00fcringen",
    "wof:name":"Bier- Und Weinstube Am Stollen",
    "wof:placetype":"venue"
},
  "geometry": {"coordinates":[10.9223575592,50.6773109436],"type":"Point"}
}