{
  "type": "Feature",
  "properties": {
    "iso:country":"DE",
    "sg:address":"Erich-Weinert-Str. 1",
    "sg:city":"Bad Klosterlausnitz",
    "sg:phone":"+49 36601/42014",
    "sg:postcode":"07639",
    "sg:province":"Th\u00fcringen",
    "wof:name":"Rudolf Sacher Ingenieur",
    "wof:placetype":"venue"
},
  "geometry": {"coordinates":[11.8615608215,50.9149055481],"type":"Point"}
}