{
  "type": "Feature",
  "properties": {
    "iso:country":"DE",
    "sg:address":"Leipziger Str. 47",
    "sg:city":"Taucha",
    "sg:phone":"+49 34298/68084",
    "sg:postcode":"04425",
    "sg:province":"Sachsen",
    "wof:name":"Adolf Kutter",
    "wof:placetype":"venue"
},
  "geometry": {"coordinates":[12.491354,51.378815],"type":"Point"}
}