{
  "type": "Feature",
  "properties": {
    "iso:country":"DE",
    "sg:address":"Dreim\u00e4nnerweg 2a",
    "sg:city":"Niesky",
    "sg:phone":"+49 3588/200302",
    "sg:postcode":"02906",
    "sg:province":"Sachsen",
    "wof:name":"H. Meichelb\u00f6ck Gmbh",
    "wof:placetype":"venue"
},
  "geometry": {"coordinates":[14.841331,51.288422],"type":"Point"}
}