{
  "type": "Feature",
  "properties": {
    "iso:country":"DE",
    "sg:address":"K\u00f6nigsallee 243",
    "sg:city":"G\u00f6ttingen",
    "sg:phone":"+49 551/504820",
    "sg:postcode":"37079",
    "sg:province":"Niedersachsen",
    "wof:name":"Sb M\u00f6bel Boss Gmbh & Co. Kg",
    "wof:placetype":"venue"
},
  "geometry": {"coordinates":[9.909203,51.54874],"type":"Point"}
}