{
  "type": "Feature",
  "properties": {
    "iso:country":"DE",
    "sg:address":"Schiffenborn 3",
    "sg:city":"Monschau",
    "sg:phone":"+49 4924/723185",
    "sg:postcode":"52156",
    "sg:province":"Nordrhein-Westfalen",
    "wof:name":"Roder Heizungsbau- & Sanit\u00c4rinstallation Gmbh & Co Kg",
    "wof:placetype":"venue"
},
  "geometry": {"coordinates":[6.2194547653,50.5687980652],"type":"Point"}
}