{
  "type": "Feature",
  "properties": {
    "iso:country":"DE",
    "sg:address":"Alter Postweg 45",
    "sg:city":"M\u00fcnster",
    "sg:phone":"+49 2581/8039",
    "sg:postcode":"48155",
    "sg:province":"Nordrhein-Westfalen",
    "wof:name":"Eine Charismatische Gemeinde In M\u00fcnster",
    "wof:placetype":"venue"
},
  "geometry": {"coordinates":[7.707606,51.927002],"type":"Point"}
}