{
  "type": "Feature",
  "properties": {
    "iso:country":"DE",
    "sg:address":"Taunusstr. 7",
    "sg:city":"Berlin",
    "sg:phone":"+49 30/8514071",
    "sg:postcode":"12161",
    "sg:province":"Berlin",
    "wof:name":"Gastst\u00e4tte Taunus-klause",
    "wof:placetype":"venue"
},
  "geometry": {"coordinates":[13.3247060776,52.4736328125],"type":"Point"}
}