{
  "type": "Feature",
  "properties": {
    "iso:country":"DE",
    "sg:address":"An der Sch\u00fcttenh\u00f6he 1",
    "sg:city":"Gummersbach",
    "sg:postcode":"51643",
    "sg:province":"Nordrhein-Westfalen",
    "wof:name":"Rundfunk-holding Rhein-bergoberberg Gmbh",
    "wof:placetype":"venue"
},
  "geometry": {"coordinates":[7.573435,51.019596],"type":"Point"}
}