{
  "type": "Feature",
  "properties": {
    "iso:country":"DE",
    "sg:address":"Holzhofstr. 34",
    "sg:city":"Mainz",
    "sg:phone":"+49 6131/225697",
    "sg:postcode":"55116",
    "sg:province":"Rheinland-Pfalz",
    "wof:name":"H. Herrmann",
    "wof:placetype":"venue"
},
  "geometry": {"coordinates":[8.274626,49.995495],"type":"Point"}
}