{
  "type": "Feature",
  "properties": {
    "iso:country":"DE",
    "sg:address":"Brookstr. 1 a",
    "sg:city":"Itzehoe",
    "sg:phone":"+49 4821/65491",
    "sg:postcode":"25524",
    "sg:province":"Schleswig-Holstein",
    "wof:name":"Jaenisch & Dammann Gmbh",
    "wof:placetype":"venue"
},
  "geometry": {"coordinates":[9.5141592026,53.9247245789],"type":"Point"}
}