{
  "type": "Feature",
  "properties": {
    "iso:country":"DE",
    "sg:address":"Franz-Mehring-Str. 40",
    "sg:city":"Schwerin",
    "sg:phone":"+49 385/713090",
    "sg:postcode":"19053",
    "sg:province":"Mecklenburg-Vorpommern",
    "wof:name":"Gastst\u00e4tte Einstein",
    "wof:placetype":"venue"
},
  "geometry": {"coordinates":[11.405957222,53.6322860718],"type":"Point"}
}