{
  "type": "Feature",
  "properties": {
    "iso:country":"DE",
    "sg:address":"In der Lacke 7",
    "sg:city":"Werdohl",
    "sg:phone":"+49 2392/5040",
    "sg:postcode":"58791",
    "sg:province":"Nordrhein-Westfalen",
    "wof:name":"Stahlschmidt & Maiworm Beteiligungsverwaltungs Gmbh",
    "wof:placetype":"venue"
},
  "geometry": {"coordinates":[7.715167,51.275112],"type":"Point"}
}