{
  "type": "Feature",
  "properties": {
    "iso:country":"DE",
    "sg:address":"Moselweinstr. 34",
    "sg:city":"Ediger-Eller",
    "sg:phone":"+49 2675/356",
    "sg:postcode":"56814",
    "sg:province":"Rheinland-Pfalz",
    "wof:name":"Winfried Andre",
    "wof:placetype":"venue"
},
  "geometry": {"coordinates":[7.1393890381,50.1024017334],"type":"Point"}
}