{
  "type": "Feature",
  "properties": {
    "iso:country":"DE",
    "sg:address":"L\u00f6hestr. 32",
    "sg:city":"Hennef",
    "sg:phone":"+49 2242/92120",
    "sg:postcode":"53773",
    "sg:province":"Nordrhein-Westfalen",
    "wof:name":"Jansen Verwaltungs Gmbh",
    "wof:placetype":"venue"
},
  "geometry": {"coordinates":[7.2592830658,50.7844390869],"type":"Point"}
}