{
  "type": "Feature",
  "properties": {
    "iso:country":"DE",
    "sg:address":"Am Wolfsgraben 18",
    "sg:city":"Braunfels",
    "sg:postcode":"35619",
    "sg:province":"Hessen",
    "wof:name":"J. A. Consulting Gmbh",
    "wof:placetype":"venue"
},
  "geometry": {"coordinates":[8.4403152466,50.4840583801],"type":"Point"}
}