{
  "type": "Feature",
  "properties": {
    "iso:country":"DE",
    "sg:address":"M\u00fchlstr. 11",
    "sg:city":"Bad K\u00f6nig",
    "sg:phone":"+49 6063/913133",
    "sg:postcode":"64732",
    "sg:province":"Hessen",
    "wof:name":"Restaurant Die Scheune",
    "wof:placetype":"venue"
},
  "geometry": {"coordinates":[9.0082921982,49.7416343689],"type":"Point"}
}