{
  "type": "Feature",
  "properties": {
    "iso:country":"DE",
    "sg:address":"Im Schleusenteich 3",
    "sg:city":"Peine",
    "sg:postcode":"31224",
    "sg:province":"Niedersachsen",
    "wof:name":"M-computer E. K.",
    "wof:placetype":"venue"
},
  "geometry": {"coordinates":[10.239019,52.321251],"type":"Point"}
}