{
  "type": "Feature",
  "properties": {
    "iso:country":"DE",
    "sg:address":"Steglitzer Str. 4",
    "sg:city":"Bad Bentheim",
    "sg:phone":"+49 5922/3528",
    "sg:postcode":"48455",
    "sg:province":"Niedersachsen",
    "wof:name":"Grafik Design Ingo Arndt",
    "wof:placetype":"venue"
},
  "geometry": {"coordinates":[7.156517,52.296928],"type":"Point"}
}