{
  "type": "Feature",
  "properties": {
    "iso:country":"DE",
    "sg:address":"Fetscherstr. 48",
    "sg:city":"Dresden",
    "sg:phone":"+49 351/334308",
    "sg:postcode":"01307",
    "sg:province":"Sachsen",
    "wof:name":"Zoohandlung Aquaristik Inh. J\u00fcrgen J\u00e4nichen",
    "wof:placetype":"venue"
},
  "geometry": {"coordinates":[13.774519,51.04937],"type":"Point"}
}