{
  "type": "Feature",
  "properties": {
    "iso:country":"DE",
    "sg:address":"Hanauer Landstra\u00dfe 344-346",
    "sg:city":"Frankfurt am Main",
    "sg:phone":"+49 69/40800765",
    "sg:postcode":"60314",
    "sg:province":"Hessen",
    "wof:name":"Das Neue Betreuungskonzept Der Firma Gena",
    "wof:placetype":"venue"
},
  "geometry": {"coordinates":[8.745386,50.124352],"type":"Point"}
}