{
  "type": "Feature",
  "properties": {
    "iso:country":"DE",
    "sg:address":"Cordobastr. 1",
    "sg:city":"D\u00fcsseldorf",
    "sg:phone":"+49 211/4983364",
    "sg:postcode":"40477",
    "sg:province":"Nordrhein-Westfalen",
    "wof:name":"Prorising Gmbh",
    "wof:placetype":"venue"
},
  "geometry": {"coordinates":[6.775858,51.238625],"type":"Point"}
}