{
  "type": "Feature",
  "properties": {
    "iso:country":"DE",
    "sg:address":"Heidestr. 39",
    "sg:city":"Radeberg",
    "sg:phone":"+49 3528/442398",
    "sg:postcode":"01454",
    "sg:province":"Sachsen",
    "wof:name":"Sv Einheit Radeberg E. V.",
    "wof:placetype":"venue"
},
  "geometry": {"coordinates":[13.9006299973,51.1146011353],"type":"Point"}
}