{
  "type": "Feature",
  "properties": {
    "iso:country":"DE",
    "sg:address":"Dalmerweg 5",
    "sg:city":"Beckum",
    "sg:phone":"+49 2521/4479",
    "sg:postcode":"59269",
    "sg:province":"Nordrhein-Westfalen",
    "wof:name":"Heinz Wienstr\u00f6r",
    "wof:placetype":"venue"
},
  "geometry": {"coordinates":[8.0419216156,51.7321586609],"type":"Point"}
}