{
  "type": "Feature",
  "properties": {
    "iso:country":"DE",
    "sg:address":"Kohlentwiete 18",
    "sg:city":"Hamburg",
    "sg:phone":"+49 40/853470",
    "sg:postcode":"22761",
    "sg:province":"Hamburg",
    "wof:name":"Fegro",
    "wof:placetype":"venue"
},
  "geometry": {"coordinates":[9.9310932159,53.5618972778],"type":"Point"}
}