{
  "type": "Feature",
  "properties": {
    "iso:country":"DE",
    "sg:address":"Kohlh\u00e4user Str. 118",
    "sg:city":"Fulda",
    "sg:phone":"+49 661/41226",
    "sg:postcode":"36043",
    "sg:province":"Hessen",
    "wof:name":"Kramm Gmbh & Co. Handel Mit Landwirtschaftlichen",
    "wof:placetype":"venue"
},
  "geometry": {"coordinates":[9.682013,50.529442],"type":"Point"}
}