{
  "type": "Feature",
  "properties": {
    "iso:country":"DE",
    "sg:address":"Kritenbarg 21",
    "sg:city":"Hamburg",
    "sg:phone":"+49 40/6065530",
    "sg:postcode":"22391",
    "sg:province":"Hamburg",
    "wof:name":"Kabert Gmbh",
    "wof:placetype":"venue"
},
  "geometry": {"coordinates":[10.0893096924,53.6526527405],"type":"Point"}
}