{
  "type": "Feature",
  "properties": {
    "iso:country":"DE",
    "sg:address":"Weidenweg 18",
    "sg:city":"Bissendorf",
    "sg:phone":"+49 5402/3332",
    "sg:postcode":"49143",
    "sg:province":"Niedersachsen",
    "wof:name":"Erika Strakerjahn",
    "wof:placetype":"venue"
},
  "geometry": {"coordinates":[8.1785116196,52.23387146],"type":"Point"}
}