{
  "type": "Feature",
  "properties": {
    "iso:country":"DE",
    "sg:address":"Hermann-Litzendorf-Str. 8",
    "sg:city":"Dassow",
    "sg:phone":"+49 38826/80648",
    "sg:postcode":"23942",
    "sg:province":"Mecklenburg-Vorpommern",
    "wof:name":"Uwe Westphal",
    "wof:placetype":"venue"
},
  "geometry": {"coordinates":[10.975025177,53.907169342],"type":"Point"}
}