{
  "type": "Feature",
  "properties": {
    "iso:country":"DE",
    "sg:address":"Rilkeweg 3",
    "sg:city":"M\u00fcnster",
    "sg:postcode":"48165",
    "sg:province":"Nordrhein-Westfalen",
    "wof:name":"Abak Maler Gmbh",
    "wof:placetype":"venue"
},
  "geometry": {"coordinates":[7.6264519691,51.9012374878],"type":"Point"}
}