{
  "type": "Feature",
  "properties": {
    "iso:country":"DE",
    "sg:address":"Am Wiesengarten 6",
    "sg:city":"Weimar",
    "sg:phone":"+49 6426/333",
    "sg:postcode":"35096",
    "sg:province":"Hessen",
    "wof:name":"Ev. Pfarramt Niederwalgern",
    "wof:placetype":"venue"
},
  "geometry": {"coordinates":[8.7005596161,50.7340927124],"type":"Point"}
}