{
  "type": "Feature",
  "properties": {
    "iso:country":"DE",
    "sg:address":"Gehrener Str. 7",
    "sg:city":"M\u00f6hrenbach",
    "sg:postcode":"98708",
    "sg:province":"Th\u00fcringen",
    "wof:name":"Heinemannsche Familienstiftung",
    "wof:placetype":"venue"
},
  "geometry": {"coordinates":[10.9949951172,50.6240615845],"type":"Point"}
}