{
  "type": "Feature",
  "properties": {
    "iso:country":"DE",
    "sg:address":"Ostlandstr. 2",
    "sg:city":"Fritzlar",
    "sg:phone":"+49 5622/6774",
    "sg:postcode":"34560",
    "sg:province":"Hessen",
    "wof:name":"Ces Chemieanlagen Engineering Und Service",
    "wof:placetype":"venue"
},
  "geometry": {"coordinates":[9.283634,51.133408],"type":"Point"}
}