{
  "type": "Feature",
  "properties": {
    "iso:country":"DE",
    "sg:address":"Robert-Bosch-Str. 4a",
    "sg:city":"Gie\u00dfen",
    "sg:phone":"+49 6403/779958",
    "sg:postcode":"35398",
    "sg:province":"Hessen",
    "wof:name":"Welsch Und Fa\u00dfbender Rechtsanw\u00e4lte",
    "wof:placetype":"venue"
},
  "geometry": {"coordinates":[8.6470365524,50.5821495056],"type":"Point"}
}