{
  "type": "Feature",
  "properties": {
    "iso:country":"DE",
    "sg:address":"Kelterstr. 10",
    "sg:city":"Lorch",
    "sg:phone":"+49 7172/7055",
    "sg:postcode":"73547",
    "sg:province":"Baden-W\u00fcrttemberg",
    "wof:name":"Plan-team-lohoff-s\u00fcd",
    "wof:placetype":"venue"
},
  "geometry": {"coordinates":[9.636558,48.784988],"type":"Point"}
}