{
  "type": "Feature",
  "properties": {
    "iso:country":"DE",
    "sg:address":"D\u00fcsseldorfer Str. 26",
    "sg:city":"Mettmann",
    "sg:phone":"+49 2104/990",
    "sg:postcode":"40822",
    "sg:province":"Nordrhein-Westfalen",
    "wof:name":"Kreisverkehrsgesell- Schaft Mettmann Mbh",
    "wof:placetype":"venue"
},
  "geometry": {"coordinates":[6.971934,51.252354],"type":"Point"}
}