{
  "type": "Feature",
  "properties": {
    "iso:country":"DE",
    "sg:address":"Feldbergstr. 5",
    "sg:city":"Schmitten",
    "sg:phone":"+49 6082/688",
    "sg:postcode":"61389",
    "sg:province":"Hessen",
    "wof:name":"Verlag Norbert Ruecker",
    "wof:placetype":"venue"
},
  "geometry": {"coordinates":[8.4345636368,50.2424507141],"type":"Point"}
}