{
  "type": "Feature",
  "properties": {
    "iso:country":"DE",
    "sg:address":"Postfach 21:: 72117 Ammerbuch:: Germany.^^Herrenberger Str 1::",
    "sg:city":"Ammerbuch",
    "sg:phone":"+49 7073/3040",
    "sg:postcode":"72119",
    "sg:province":"Baden-W\u00fcrttemberg",
    "wof:name":"Volksbank Ammerbuch Eg -ammertalbank-",
    "wof:placetype":"venue"
},
  "geometry": {"coordinates":[8.965502,48.554535],"type":"Point"}
}