{
  "type": "Feature",
  "properties": {
    "iso:country":"DE",
    "sg:address":"Paul-Gerhardt-Str. 5",
    "sg:city":"Bietigheim-Bissingen",
    "sg:phone":"+49 7142/57745",
    "sg:postcode":"74321",
    "sg:province":"Baden-W\u00fcrttemberg",
    "wof:name":"Flammia",
    "wof:placetype":"venue"
},
  "geometry": {"coordinates":[9.122902,48.944054],"type":"Point"}
}