{
  "type": "Feature",
  "properties": {
    "iso:country":"DE",
    "sg:address":"Hasselkamp 1",
    "sg:city":"Kronshagen",
    "sg:phone":"+49 431/589181",
    "sg:postcode":"24119",
    "sg:province":"Schleswig-Holstein",
    "wof:name":"Ev. Pfarramt Christusgemeinde",
    "wof:placetype":"venue"
},
  "geometry": {"coordinates":[10.0861377716,54.3330688477],"type":"Point"}
}