{
  "type": "Feature",
  "properties": {
    "iso:country":"DE",
    "sg:address":"Karl-Arnold-Str 2",
    "sg:city":"Espelkamp",
    "sg:phone":"+49 5772/97740",
    "sg:postcode":"32339",
    "sg:province":"Nordrhein-Westfalen",
    "wof:name":"Demotronic Gmbh",
    "wof:placetype":"venue"
},
  "geometry": {"coordinates":[8.6163101196,52.3927688599],"type":"Point"}
}