{
  "type": "Feature",
  "properties": {
    "iso:country":"DE",
    "sg:address":"Goethestr. 6",
    "sg:city":"Wernau",
    "sg:phone":"+49 7153/39344",
    "sg:postcode":"73249",
    "sg:province":"Baden-W\u00fcrttemberg",
    "wof:name":"Josef Horn Ingenieur",
    "wof:placetype":"venue"
},
  "geometry": {"coordinates":[9.4165391922,48.6926727295],"type":"Point"}
}