{
  "type": "Feature",
  "properties": {
    "iso:country":"DE",
    "sg:address":"H\u00f6rnleweg 12",
    "sg:city":"Pforzheim",
    "sg:phone":"+49 7231/50186",
    "sg:postcode":"75181",
    "sg:province":"Baden-W\u00fcrttemberg",
    "wof:name":"Wolfgang Kurz",
    "wof:placetype":"venue"
},
  "geometry": {"coordinates":[8.7577972412,48.91771698],"type":"Point"}
}