{
  "type": "Feature",
  "properties": {
    "iso:country":"DE",
    "sg:address":"Mittelstr. 1",
    "sg:city":"Lindwedel",
    "sg:phone":"+49 5073/1725",
    "sg:postcode":"29690",
    "sg:province":"Niedersachsen",
    "wof:name":"Rudolf Lissner",
    "wof:placetype":"venue"
},
  "geometry": {"coordinates":[9.6884651184,52.6125717163],"type":"Point"}
}