{
  "type": "Feature",
  "properties": {
    "iso:country":"DE",
    "sg:address":"Bonner Str. 5 a",
    "sg:city":"Bornheim",
    "sg:phone":"+49 2222/2153",
    "sg:postcode":"53332",
    "sg:province":"Nordrhein-Westfalen",
    "wof:name":"Kurt Ewert",
    "wof:placetype":"venue"
},
  "geometry": {"coordinates":[7.0166,50.751789],"type":"Point"}
}