{
  "type": "Feature",
  "properties": {
    "iso:country":"DE",
    "sg:address":"Ostmarkstr. 30",
    "sg:city":"Oberhausen",
    "sg:phone":"+49 208/896363",
    "sg:postcode":"46117",
    "sg:province":"Nordrhein-Westfalen",
    "wof:name":"M. Okur",
    "wof:placetype":"venue"
},
  "geometry": {"coordinates":[6.884565,51.508667],"type":"Point"}
}