{
  "type": "Feature",
  "properties": {
    "iso:country":"DE",
    "sg:address":"Hornauer Str. 7",
    "sg:city":"Kelkheim",
    "sg:phone":"+49 6195/4848",
    "sg:postcode":"65779",
    "sg:province":"Hessen",
    "wof:name":"K.p. Zimmermann",
    "wof:placetype":"venue"
},
  "geometry": {"coordinates":[8.4507017136,50.1385498047],"type":"Point"}
}