{
  "type": "Feature",
  "properties": {
    "iso:country":"DE",
    "sg:address":"Hennener Str. 31",
    "sg:city":"Iserlohn",
    "sg:phone":"+49 4923/0450840",
    "sg:postcode":"58640",
    "sg:province":"Nordrhein-Westfalen",
    "wof:name":"Austmann Blumen",
    "wof:placetype":"venue"
},
  "geometry": {"coordinates":[7.64928,51.444893],"type":"Point"}
}