{
  "type": "Feature",
  "properties": {
    "iso:country":"DE",
    "sg:address":"Lehmkuhlenweg 8",
    "sg:city":"Wittmund",
    "sg:phone":"+49 4462/7127",
    "sg:postcode":"26409",
    "sg:province":"Niedersachsen",
    "wof:name":"Gert Wolken",
    "wof:placetype":"venue"
},
  "geometry": {"coordinates":[7.758291,53.559895],"type":"Point"}
}