{
  "type": "Feature",
  "properties": {
    "iso:country":"DE",
    "sg:address":"Amrichsh\u00e4user Str. 10",
    "sg:city":"K\u00fcnzelsau",
    "sg:phone":"+49 7940/2496",
    "sg:postcode":"74653",
    "sg:province":"Baden-W\u00fcrttemberg",
    "wof:name":"Botsch-frenz Gmbh",
    "wof:placetype":"venue"
},
  "geometry": {"coordinates":[9.693939,49.281151],"type":"Point"}
}