{
  "type": "Feature",
  "properties": {
    "iso:country":"DE",
    "sg:address":"Im Dorf 2",
    "sg:city":"Braak",
    "sg:phone":"+49 40/6771254",
    "sg:postcode":"22145",
    "sg:province":"Hamburg",
    "wof:name":"Magda Burmeister",
    "wof:placetype":"venue"
},
  "geometry": {"coordinates":[-79.0160751343,38.9223251343],"type":"Point"}
}