{
  "type": "Feature",
  "properties": {
    "iso:country":"DE",
    "sg:address":"\u00c4u\u00dfere M\u00fcnchener Str. 101",
    "sg:city":"Rosenheim",
    "sg:phone":"+49 8031/42041",
    "sg:postcode":"83026",
    "sg:province":"Bayern",
    "wof:name":"Hotel-restaurant Schwaiger Hof",
    "wof:placetype":"venue"
},
  "geometry": {"coordinates":[12.0821943283,47.8427276611],"type":"Point"}
}