{
  "type": "Feature",
  "properties": {
    "iso:country":"DE",
    "sg:address":"Ihringsh\u00e4user Str. 97a",
    "sg:city":"Kassel",
    "sg:phone":"+49 561/814138",
    "sg:postcode":"34125",
    "sg:province":"Hessen",
    "wof:name":"B & E Videothek Gmbh",
    "wof:placetype":"venue"
},
  "geometry": {"coordinates":[9.5132436752,51.3355445862],"type":"Point"}
}