{
  "type": "Feature",
  "properties": {
    "iso:country":"DE",
    "sg:address":"Erikastr. 67",
    "sg:city":"Hamburg",
    "sg:phone":"+49 40/4800350",
    "sg:postcode":"20251",
    "sg:province":"Hamburg",
    "wof:name":"Weinland Ariane Abayan Verwaltungsgesellschaft Mbh",
    "wof:placetype":"venue"
},
  "geometry": {"coordinates":[9.9870672226,53.5947685242],"type":"Point"}
}