{
  "type": "Feature",
  "properties": {
    "iso:country":"DE",
    "sg:address":"Pickhuben 7",
    "sg:city":"Hamburg",
    "sg:phone":"+49 40/365534",
    "sg:postcode":"20457",
    "sg:province":"Hamburg",
    "wof:name":"H\u00fcls & Cons. Gmbh & Co. Kg",
    "wof:placetype":"venue"
},
  "geometry": {"coordinates":[9.993567,53.544106],"type":"Point"}
}