{
  "type": "Feature",
  "properties": {
    "iso:country":"DE",
    "sg:address":"Hauptstr. 93",
    "sg:city":"Lottstetten",
    "sg:phone":"+49 7745/7313",
    "sg:postcode":"79807",
    "sg:province":"Baden-W\u00fcrttemberg",
    "wof:name":"Ernst Brand",
    "wof:placetype":"venue"
},
  "geometry": {"coordinates":[8.569363,47.625366],"type":"Point"}
}