{
  "type": "Feature",
  "properties": {
    "iso:country":"DE",
    "sg:address":"Burgstr. 3",
    "sg:city":"Rhede",
    "sg:phone":"+49 4964/553",
    "sg:postcode":"26899",
    "sg:province":"Niedersachsen",
    "wof:name":"Hans Abeln E. K.",
    "wof:placetype":"venue"
},
  "geometry": {"coordinates":[7.2733998299,53.0604782104],"type":"Point"}
}