{
  "type": "Feature",
  "properties": {
    "iso:country":"DE",
    "sg:address":"Fichtenweg 1",
    "sg:city":"Ruppichteroth",
    "sg:phone":"+49 2295/5707",
    "sg:postcode":"53809",
    "sg:province":"Nordrhein-Westfalen",
    "wof:name":"Rms Regalmontageservice Gmbh",
    "wof:placetype":"venue"
},
  "geometry": {"coordinates":[7.457697,50.837532],"type":"Point"}
}