{
  "type": "Feature",
  "properties": {
    "iso:country":"DE",
    "sg:address":"Franz-Ludwig-Str. 18",
    "sg:city":"Bamberg",
    "sg:phone":"+49 951/2999660",
    "sg:postcode":"96047",
    "sg:province":"Bayern",
    "wof:name":"R\u00fcdiger Bamberger Rechtsanwalt",
    "wof:placetype":"venue"
},
  "geometry": {"coordinates":[10.893995285,49.8927383423],"type":"Point"}
}