{
  "type": "Feature",
  "properties": {
    "iso:country":"DE",
    "sg:address":"Elsastr. 46",
    "sg:city":"Hamburg",
    "sg:postcode":"22083",
    "sg:province":"Hamburg",
    "wof:name":"Kath. \u00d6ffentliche Bibliothek",
    "wof:placetype":"venue"
},
  "geometry": {"coordinates":[10.034368,53.57935],"type":"Point"}
}