{
  "type": "Feature",
  "properties": {
    "iso:country":"DE",
    "sg:address":"Evinger Str. 599",
    "sg:city":"Dortmund",
    "sg:phone":"+49 231/803934",
    "sg:postcode":"44339",
    "sg:province":"Nordrhein-Westfalen",
    "wof:name":"Gras",
    "wof:placetype":"venue"
},
  "geometry": {"coordinates":[7.4632158279,51.5803718567],"type":"Point"}
}