{
  "type": "Feature",
  "properties": {
    "iso:country":"DE",
    "sg:address":"Bismarckstr. 24",
    "sg:city":"Hamburg",
    "sg:postcode":"20259",
    "sg:province":"Hamburg",
    "wof:name":"Aldi Gmbh & Co. Kg",
    "wof:placetype":"venue"
},
  "geometry": {"coordinates":[9.9621295929,53.5731201172],"type":"Point"}
}