{
  "type": "Feature",
  "properties": {
    "iso:country":"DE",
    "sg:address":"Alandsgrund 7",
    "sg:city":"Randersacker",
    "sg:phone":"+49 931/75198",
    "sg:postcode":"97236",
    "sg:province":"Bayern",
    "wof:name":"H. Snop",
    "wof:placetype":"venue"
},
  "geometry": {"coordinates":[9.960965,49.769703],"type":"Point"}
}