{
  "type": "Feature",
  "properties": {
    "iso:country":"DE",
    "sg:address":"Hauptstr. 11",
    "sg:city":"Alpirsbach",
    "sg:phone":"+49 4974/442366",
    "sg:postcode":"72275",
    "sg:province":"Baden-W\u00fcrttemberg",
    "wof:name":"Bessler Druck Inh. Reinhard Junge",
    "wof:placetype":"venue"
},
  "geometry": {"coordinates":[8.4021968842,48.344909668],"type":"Point"}
}