{
  "type": "Feature",
  "properties": {
    "iso:country":"DE",
    "sg:address":"Hauptstr. 1",
    "sg:city":"Kissing",
    "sg:phone":"+49 8233/5676",
    "sg:postcode":"86438",
    "sg:province":"Bayern",
    "wof:name":"Josef Asam Gmbh",
    "wof:placetype":"venue"
},
  "geometry": {"coordinates":[10.988227,48.295902],"type":"Point"}
}