{
  "type": "Feature",
  "properties": {
    "iso:country":"DE",
    "sg:address":"Austr. 2",
    "sg:city":"Dautphetal",
    "sg:phone":"+49 6468/363",
    "sg:postcode":"35232",
    "sg:province":"Hessen",
    "wof:name":"Heinr. Beimborn",
    "wof:placetype":"venue"
},
  "geometry": {"coordinates":[8.5570192337,50.8251914978],"type":"Point"}
}