{
  "type": "Feature",
  "properties": {
    "iso:country":"DE",
    "sg:address":"Erzberger Str. 11",
    "sg:city":"Unterhaching",
    "sg:phone":"+49 89/266104",
    "sg:postcode":"82008",
    "sg:province":"Bayern",
    "wof:name":"Hvm Handels Und Vertriebs Gmbh",
    "wof:placetype":"venue"
},
  "geometry": {"coordinates":[11.6113138199,48.0688285828],"type":"Point"}
}