{
  "type": "Feature",
  "properties": {
    "iso:country":"DE",
    "sg:address":"Paulinenstr. 21a",
    "sg:city":"Detmold",
    "sg:phone":"+49 5231",
    "sg:postcode":"32756",
    "sg:province":"Nordrhein-Westfalen",
    "wof:name":"Global Reach Internationles Onlinemarketing U. Webpromotion",
    "wof:placetype":"venue"
},
  "geometry": {"coordinates":[8.8740787506,51.9355583191],"type":"Point"}
}