{
  "type": "Feature",
  "properties": {
    "iso:country":"DE",
    "sg:address":"Vilstalstr. 6",
    "sg:city":"Pfronten",
    "sg:phone":"+49 8363/5155",
    "sg:postcode":"87459",
    "sg:province":"Bayern",
    "wof:name":"Kees Tv Hifi",
    "wof:placetype":"venue"
},
  "geometry": {"coordinates":[10.5566205978,47.5814666748],"type":"Point"}
}