{
  "type": "Feature",
  "properties": {
    "iso:country":"DE",
    "sg:address":"Oelkinghauser Str. 22",
    "sg:city":"Ennepetal",
    "sg:phone":"+49 2333/70070",
    "sg:postcode":"58256",
    "sg:province":"Nordrhein-Westfalen",
    "wof:name":"Brigitte K\u00f6nen",
    "wof:placetype":"venue"
},
  "geometry": {"coordinates":[7.3266677856,51.2851715088],"type":"Point"}
}