{
  "type": "Feature",
  "properties": {
    "iso:country":"DE",
    "sg:address":"Am J\u00e4gerheim 3",
    "sg:city":"Rheda-Wiedenbr\u00fcck",
    "sg:phone":"+49 5242/7627",
    "sg:postcode":"33378",
    "sg:province":"Nordrhein-Westfalen",
    "wof:name":"Otto Klasmeier Verwaltungs-gmbh",
    "wof:placetype":"venue"
},
  "geometry": {"coordinates":[8.339541,51.832645],"type":"Point"}
}