{
  "type": "Feature",
  "properties": {
    "iso:country":"DE",
    "sg:address":"Goppertsweiler 22",
    "sg:city":"Neukirch",
    "sg:phone":"+49 7528/1866",
    "sg:postcode":"88099",
    "sg:province":"Baden-W\u00fcrttemberg",
    "wof:name":"Broger & Rief",
    "wof:placetype":"venue"
},
  "geometry": {"coordinates":[9.7303466797,47.6556015015],"type":"Point"}
}