{
  "type": "Feature",
  "properties": {
    "iso:country":"DE",
    "sg:address":"Postfach 290130",
    "sg:city":"Bremerhaven",
    "sg:phone":"+49 471/72324",
    "sg:postcode":"27531",
    "sg:province":"Bremen",
    "wof:name":"Nordwestdeutsche Fisch- Versandhallen Fr. Drunagel",
    "wof:placetype":"venue"
},
  "geometry": {"coordinates":[8.5781202316,53.5418586731],"type":"Point"}
}