{
  "type": "Feature",
  "properties": {
    "iso:country":"DE",
    "sg:address":"Kronenstr. 23",
    "sg:city":"Friesenheim",
    "sg:phone":"+49 7821/62002",
    "sg:postcode":"77948",
    "sg:province":"Baden-W\u00fcrttemberg",
    "wof:name":"Martin Ziegler",
    "wof:placetype":"venue"
},
  "geometry": {"coordinates":[7.8750739098,48.3761291504],"type":"Point"}
}