{
  "type": "Feature",
  "properties": {
    "iso:country":"DE",
    "sg:address":"Adam-Ries-Str. 1",
    "sg:city":"Annaberg-Buchholz",
    "sg:phone":"+49 3733/18020",
    "sg:postcode":"09456",
    "sg:province":"Sachsen",
    "wof:name":"D\u00e4nisches Bettenlager Gmbh & Co. Kg",
    "wof:placetype":"venue"
},
  "geometry": {"coordinates":[13.0077943802,50.5825309753],"type":"Point"}
}