{
  "type": "Feature",
  "properties": {
    "iso:country":"DE",
    "sg:address":"Holsteiner Chaussee 7",
    "sg:city":"Hamburg",
    "sg:phone":"+49 40/5706905",
    "sg:postcode":"22523",
    "sg:province":"Hamburg",
    "wof:name":"Johann Ramcke Und Harald Johann Gr\u00fcnberg",
    "wof:placetype":"venue"
},
  "geometry": {"coordinates":[9.9045257568,53.609500885],"type":"Point"}
}