{
  "type": "Feature",
  "properties": {
    "iso:country":"DE",
    "sg:address":"Tannenbergsthaler Str. 3",
    "sg:city":"Hammerbr\u00fccke",
    "sg:phone":"+49 37465/6203",
    "sg:postcode":"08269",
    "sg:province":"Sachsen",
    "wof:name":"E. Gl\u00f6ckl",
    "wof:placetype":"venue"
},
  "geometry": {"coordinates":[12.4150056839,50.4354896545],"type":"Point"}
}