{
  "type": "Feature",
  "properties": {
    "iso:country":"DE",
    "sg:address":"Senefelder Stra\u00dfe 8",
    "sg:city":"Obersulm",
    "sg:phone":"+49 7134/986610",
    "sg:postcode":"74182",
    "sg:province":"Baden-W\u00fcrttemberg",
    "wof:name":"Stiegele Gmbh Stromerzeuger",
    "wof:placetype":"venue"
},
  "geometry": {"coordinates":[9.3633852005,49.1301689148],"type":"Point"}
}