{
  "type": "Feature",
  "properties": {
    "iso:country":"DE",
    "sg:address":"Chopinstr. 18",
    "sg:city":"Leipzig",
    "sg:phone":"+49 341/964370",
    "sg:postcode":"04103",
    "sg:province":"Sachsen",
    "wof:name":"Quester Und Partner",
    "wof:placetype":"venue"
},
  "geometry": {"coordinates":[12.390327,51.343227],"type":"Point"}
}