{
  "type": "Feature",
  "properties": {
    "iso:country":"DE",
    "sg:address":"T\u00fcbinger Str. 102",
    "sg:city":"Tamm",
    "sg:phone":"+49 7141/602082",
    "sg:postcode":"71732",
    "sg:province":"Baden-W\u00fcrttemberg",
    "wof:name":"Gerhart Schneewei\u00df Ingenieur",
    "wof:placetype":"venue"
},
  "geometry": {"coordinates":[9.141752243,48.9237480164],"type":"Point"}
}