{
  "type": "Feature",
  "properties": {
    "iso:country":"DE",
    "sg:address":"Schulstr. 71",
    "sg:city":"Norden",
    "sg:phone":"+49 4931/957966",
    "sg:postcode":"26506",
    "sg:province":"Niedersachsen",
    "wof:name":"Lammert Frerichs",
    "wof:placetype":"venue"
},
  "geometry": {"coordinates":[7.204818,53.599773],"type":"Point"}
}