{
  "type": "Feature",
  "properties": {
    "iso:country":"DE",
    "sg:address":"Saalburgstr 31A",
    "sg:city":"Neu-Anspach",
    "sg:phone":"+49 6081/41710",
    "sg:postcode":"61267",
    "sg:province":"Hessen",
    "wof:name":"Holzbau Langhammer Gmbh",
    "wof:placetype":"venue"
},
  "geometry": {"coordinates":[8.5132369995,50.2901649475],"type":"Point"}
}