{
  "type": "Feature",
  "properties": {
    "iso:country":"DE",
    "sg:address":"Tuchmacherweg 20",
    "sg:city":"Burgdorf",
    "sg:phone":"+49 5136/85051",
    "sg:postcode":"31303",
    "sg:province":"Niedersachsen",
    "wof:name":"Sporting-hotel Concorde",
    "wof:placetype":"venue"
},
  "geometry": {"coordinates":[10.0444850922,52.4492683411],"type":"Point"}
}