{
  "type": "Feature",
  "properties": {
    "iso:country":"DE",
    "sg:address":"Hauptstr. 96",
    "sg:city":"Neunkirchen-Seelscheid",
    "sg:phone":"+49 2247/4688",
    "sg:postcode":"53819",
    "sg:province":"Nordrhein-Westfalen",
    "wof:name":"Jobst W\u00f6lfer",
    "wof:placetype":"venue"
},
  "geometry": {"coordinates":[7.3385148048,50.844909668],"type":"Point"}
}