{
  "type": "Feature",
  "properties": {
    "iso:country":"DE",
    "sg:address":"Zum Bassin 22",
    "sg:city":"Mettlach",
    "sg:phone":"+49 6865/318",
    "sg:postcode":"66693",
    "sg:province":"Saarland",
    "wof:name":"W. Spanier Grabdenkm\u00e4ler",
    "wof:placetype":"venue"
},
  "geometry": {"coordinates":[6.5261998177,49.5088195801],"type":"Point"}
}