{
  "type": "Feature",
  "properties": {
    "iso:country":"DE",
    "sg:address":"Alter Postweg 107a",
    "sg:city":"Seevetal",
    "sg:postcode":"21220",
    "sg:province":"Niedersachsen",
    "wof:name":"Celia Holtz B\u00fcroeinrichtungen",
    "wof:placetype":"venue"
},
  "geometry": {"coordinates":[10.0371398926,53.375995636],"type":"Point"}
}