{
  "type": "Feature",
  "properties": {
    "iso:country":"DE",
    "sg:address":"Erfurter Str. 54",
    "sg:city":"Weimar",
    "sg:phone":"+49 3643/512514",
    "sg:postcode":"99423",
    "sg:province":"Th\u00fcringen",
    "wof:name":"Oppel",
    "wof:placetype":"venue"
},
  "geometry": {"coordinates":[11.3142700195,50.981048584],"type":"Point"}
}