{
  "type": "Feature",
  "properties": {
    "iso:country":"DE",
    "sg:address":"Potsdamer Str. 138",
    "sg:city":"Berlin",
    "sg:phone":"+49 30/2617835",
    "sg:postcode":"10783",
    "sg:province":"Berlin",
    "wof:name":"Potsdamer Stange",
    "wof:placetype":"venue"
},
  "geometry": {"coordinates":[13.3620014191,52.498374939],"type":"Point"}
}