{
  "type": "Feature",
  "properties": {
    "iso:country":"DE",
    "sg:address":"Lessingstr. 33a",
    "sg:city":"Thalheim",
    "sg:phone":"+49 3721/85628",
    "sg:postcode":"09380",
    "sg:province":"Sachsen",
    "wof:name":"S. Karsch",
    "wof:placetype":"venue"
},
  "geometry": {"coordinates":[12.83866,50.700424],"type":"Point"}
}