{
  "type": "Feature",
  "properties": {
    "iso:country":"DE",
    "sg:address":"Martin-Niem\u00f6ller-Str.",
    "sg:city":"Erfurt",
    "sg:phone":"+49 361/7313688",
    "sg:postcode":"99086",
    "sg:province":"Th\u00fcringen",
    "wof:name":"Th\u00fcringer Bauernstube",
    "wof:placetype":"venue"
},
  "geometry": {"coordinates":[11.0275354385,50.9943656921],"type":"Point"}
}