{
  "type": "Feature",
  "properties": {
    "iso:country":"DE",
    "sg:address":"Glimmerweg 49",
    "sg:city":"Berlin",
    "sg:phone":"+49 30/2139070",
    "sg:postcode":"12349",
    "sg:province":"Berlin",
    "wof:name":"Jupiter Bau Gmbh",
    "wof:placetype":"venue"
},
  "geometry": {"coordinates":[13.41466,52.418861],"type":"Point"}
}