{
  "type": "Feature",
  "properties": {
    "iso:country":"DE",
    "sg:address":"M\u00f6nchsberg",
    "sg:city":"Baudenbach",
    "sg:phone":"+49 9166/519",
    "sg:postcode":"91460",
    "sg:province":"Bayern",
    "wof:name":"I. Proschko Und H. B\u00e4rthlein",
    "wof:placetype":"venue"
},
  "geometry": {"coordinates":[10.5682706833,49.6470870972],"type":"Point"}
}