{
  "type": "Feature",
  "properties": {
    "iso:country":"DE",
    "sg:address":"Am Neufeld 41",
    "sg:city":"Frankfurt",
    "sg:phone":"+49 69/383113",
    "sg:postcode":"65933",
    "sg:province":"Hessen",
    "wof:name":"J. Wahba \u00dcbersetzer",
    "wof:placetype":"venue"
},
  "geometry": {"coordinates":[8.595915,50.113354],"type":"Point"}
}