{
  "type": "Feature",
  "properties": {
    "iso:country":"DE",
    "sg:address":"Brambauerstr. 257",
    "sg:city":"L\u00fcnen",
    "sg:phone":"+49 231/8770873",
    "sg:postcode":"44536",
    "sg:province":"Nordrhein-Westfalen",
    "wof:name":"China Restaurant Lotus",
    "wof:placetype":"venue"
},
  "geometry": {"coordinates":[7.4733510017,51.6044273376],"type":"Point"}
}