{
  "type": "Feature",
  "properties": {
    "iso:country":"DE",
    "sg:address":"Mittelseestr. 48",
    "sg:city":"Offenbach",
    "sg:phone":"+49 69/8001701",
    "sg:postcode":"63065",
    "sg:province":"Hessen",
    "wof:name":"Arthur Naujok Rechtsanwalt",
    "wof:placetype":"venue"
},
  "geometry": {"coordinates":[8.761756897,50.1027336121],"type":"Point"}
}