{
  "type": "Feature",
  "properties": {
    "iso:country":"DE",
    "sg:address":"Graseggerstr. 67",
    "sg:city":"K\u00f6ln",
    "sg:phone":"+49 221/9742032",
    "sg:postcode":"50737",
    "sg:province":"Nordrhein-Westfalen",
    "wof:name":"Bohemia Beh\u00e4ltertechnik Gmbh",
    "wof:placetype":"venue"
},
  "geometry": {"coordinates":[6.92534,50.99263],"type":"Point"}
}