{
  "type": "Feature",
  "properties": {
    "iso:country":"DE",
    "sg:address":"Lahrer Weg 40",
    "sg:city":"Hasel\u00fcnne",
    "sg:phone":"+49 5961/4555",
    "sg:postcode":"49740",
    "sg:province":"Niedersachsen",
    "wof:name":"G\u00f6sling Immobilien An- Und Verkauf Gmbh",
    "wof:placetype":"venue"
},
  "geometry": {"coordinates":[7.4491529465,52.6800956726],"type":"Point"}
}