{
  "type": "Feature",
  "properties": {
    "iso:country":"DE",
    "sg:address":"Bismarckstr. 95",
    "sg:city":"Gelsenkirchen",
    "sg:phone":"+49 209/819135",
    "sg:postcode":"45881",
    "sg:province":"Nordrhein-Westfalen",
    "wof:name":"Neckura Versicherungen",
    "wof:placetype":"venue"
},
  "geometry": {"coordinates":[7.1032090187,51.5183792114],"type":"Point"}
}