{
  "type": "Feature",
  "properties": {
    "iso:country":"DE",
    "sg:address":"Marktplatz 4",
    "sg:city":"Bad Neuenahr-Ahrweiler",
    "sg:phone":"+49 2641/36361",
    "sg:postcode":"53474",
    "sg:province":"Rheinland-Pfalz",
    "wof:name":"Gastst\u00e4tte M. Caspers",
    "wof:placetype":"venue"
},
  "geometry": {"coordinates":[7.0950541496,50.5422706604],"type":"Point"}
}