{
  "type": "Feature",
  "properties": {
    "iso:country":"DE",
    "sg:address":"Max-Eyth-Str. 2",
    "sg:city":"Steinenbronn",
    "sg:phone":"+49 7157/72880",
    "sg:postcode":"71144",
    "sg:province":"Baden-W\u00fcrttemberg",
    "wof:name":"Vas Weinmann Gmbh",
    "wof:placetype":"venue"
},
  "geometry": {"coordinates":[9.128247261,48.6658935547],"type":"Point"}
}