{
  "type": "Feature",
  "properties": {
    "iso:country":"DE",
    "sg:address":"Kleiner Schratweg 55",
    "sg:city":"Lemgo",
    "sg:phone":"+49 5261/970804",
    "sg:postcode":"32657",
    "sg:province":"Nordrhein-Westfalen",
    "wof:name":"Wolfgang Wollbrink",
    "wof:placetype":"venue"
},
  "geometry": {"coordinates":[8.881538,52.013908],"type":"Point"}
}