{
  "type": "Feature",
  "properties": {
    "iso:country":"DE",
    "sg:address":"Offenbacher Str. 2",
    "sg:city":"Dreieich",
    "sg:phone":"+49 4961/03950",
    "sg:postcode":"63303",
    "sg:province":"Hessen",
    "wof:name":"Volksbank Dreieich Eg",
    "wof:placetype":"venue"
},
  "geometry": {"coordinates":[8.695766,50.019222],"type":"Point"}
}