{
  "type": "Feature",
  "properties": {
    "iso:country":"DE",
    "sg:address":"Marbachweg 319",
    "sg:city":"Frankfurt",
    "sg:phone":"+49 69/95636570",
    "sg:postcode":"60320",
    "sg:province":"Hessen",
    "wof:name":"Iqmc It And Quality Management Consulting Gmbh",
    "wof:placetype":"venue"
},
  "geometry": {"coordinates":[8.67466259,50.1397132874],"type":"Point"}
}