{
  "type": "Feature",
  "properties": {
    "iso:country":"DE",
    "sg:address":"Alpenblickstr. 6",
    "sg:city":"Dettighofen",
    "sg:phone":"+49 7742/5484",
    "sg:postcode":"79802",
    "sg:province":"Baden-W\u00fcrttemberg",
    "wof:name":"W. Neitzel",
    "wof:placetype":"venue"
},
  "geometry": {"coordinates":[8.487793,47.623219],"type":"Point"}
}