{
  "type": "Feature",
  "properties": {
    "iso:country":"DE",
    "sg:address":"Gerkenstr. 6-8",
    "sg:city":"Wickede",
    "sg:phone":"+49 4923/7791465",
    "sg:postcode":"58739",
    "sg:province":"Nordrhein-Westfalen",
    "wof:name":"Frikowerk Fritz K\u00d6rdt Metallwarenfabrik Gmbh & Co. Kg",
    "wof:placetype":"venue"
},
  "geometry": {"coordinates":[7.863277,51.498421],"type":"Point"}
}