{
  "type": "Feature",
  "properties": {
    "iso:country":"DE",
    "sg:address":"Wilflingen",
    "sg:city":"Langenenslingen",
    "sg:phone":"+49 7376/712",
    "sg:postcode":"88515",
    "sg:province":"Baden-W\u00fcrttemberg",
    "wof:name":"E. K\u00e4ppeler",
    "wof:placetype":"venue"
},
  "geometry": {"coordinates":[9.3588552475,48.1385955811],"type":"Point"}
}