{
  "type": "Feature",
  "properties": {
    "iso:country":"DE",
    "sg:address":"Hirschlachufer 7",
    "sg:city":"Erfurt",
    "sg:postcode":"99084",
    "sg:province":"Th\u00fcringen",
    "wof:name":"Grekuns Baguetterie Gmbh",
    "wof:placetype":"venue"
},
  "geometry": {"coordinates":[11.033172,50.974365],"type":"Point"}
}