{
  "type": "Feature",
  "properties": {
    "iso:country":"DE",
    "sg:address":"Weslarner Weg 36",
    "sg:city":"Soest",
    "sg:phone":"+49 2921/80006",
    "sg:postcode":"59494",
    "sg:province":"Nordrhein-Westfalen",
    "wof:name":"Karl Pankauke",
    "wof:placetype":"venue"
},
  "geometry": {"coordinates":[8.115679,51.582653],"type":"Point"}
}