{
  "type": "Feature",
  "properties": {
    "iso:country":"DE",
    "sg:address":"Lange Str. 120",
    "sg:city":"Brake",
    "sg:phone":"+49 4401/71175",
    "sg:postcode":"26919",
    "sg:province":"Niedersachsen",
    "wof:name":"Gerhard W\u00f6lfer Garten- Und",
    "wof:placetype":"venue"
},
  "geometry": {"coordinates":[8.47855,53.326321],"type":"Point"}
}