{
  "type": "Feature",
  "properties": {
    "iso:country":"DE",
    "sg:address":"Badekower Str. 14",
    "sg:city":"Gresse",
    "sg:phone":"+49 38842/21212",
    "sg:postcode":"19258",
    "sg:province":"Mecklenburg-Vorpommern",
    "wof:name":"Stahlbau Und Geb\u00e4udetechnik Gresse Gmbh",
    "wof:placetype":"venue"
},
  "geometry": {"coordinates":[10.762975,53.4231],"type":"Point"}
}