{
  "type": "Feature",
  "properties": {
    "iso:country":"DE",
    "sg:address":"Zaunwiesenweg 38",
    "sg:city":"N\u00fcrnberg",
    "sg:phone":"+49 911/59808",
    "sg:postcode":"90482",
    "sg:province":"Bayern",
    "wof:name":"Lambda Beteiligungs-gmbh",
    "wof:placetype":"venue"
},
  "geometry": {"coordinates":[11.156599,49.461529],"type":"Point"}
}