{
  "type": "Feature",
  "properties": {
    "iso:country":"DE",
    "sg:address":"Ahornweg 16",
    "sg:city":"Schl\u00fcchtern",
    "sg:phone":"+49 6661/730012",
    "sg:postcode":"36381",
    "sg:province":"Hessen",
    "wof:name":"Albert H\u00e4ussermann Steuerberater",
    "wof:placetype":"venue"
},
  "geometry": {"coordinates":[9.5107145309,50.3306388855],"type":"Point"}
}