{
  "type": "Feature",
  "properties": {
    "iso:country":"DE",
    "sg:address":"Bernhardtstr. 1",
    "sg:city":"Gie\u00dfen",
    "sg:phone":"+49 641/24741",
    "sg:postcode":"35398",
    "sg:province":"Hessen",
    "wof:name":"Monika Happel Rechtsanw\u00e4ltin",
    "wof:placetype":"venue"
},
  "geometry": {"coordinates":[8.6518602371,50.5643882751],"type":"Point"}
}