{
  "type": "Feature",
  "properties": {
    "iso:country":"DE",
    "sg:address":"Vor dem Bahnhaus 1",
    "sg:city":"Bexbach",
    "sg:phone":"+49 6826/50758",
    "sg:postcode":"66450",
    "sg:province":"Saarland",
    "wof:name":"G. Regin",
    "wof:placetype":"venue"
},
  "geometry": {"coordinates":[7.2795939445,49.3441238403],"type":"Point"}
}