{
  "type": "Feature",
  "properties": {
    "iso:country":"DE",
    "sg:address":"Schramberger Str. 76",
    "sg:city":"Lauterbach",
    "sg:phone":"+49 7422/4236",
    "sg:postcode":"78730",
    "sg:province":"Baden-W\u00fcrttemberg",
    "wof:name":"Edgar Emter",
    "wof:placetype":"venue"
},
  "geometry": {"coordinates":[8.3586654663,48.2248764038],"type":"Point"}
}