{
  "type": "Feature",
  "properties": {
    "iso:country":"DE",
    "sg:address":"Fritz-Schweizer-Str. 34-36",
    "sg:city":"Murrhardt",
    "sg:postcode":"71540",
    "sg:province":"Baden-W\u00fcrttemberg",
    "wof:name":"Franke Gmbh",
    "wof:placetype":"venue"
},
  "geometry": {"coordinates":[9.5829496384,48.9802017212],"type":"Point"}
}