{
  "type": "Feature",
  "properties": {
    "iso:country":"DE",
    "sg:address":"Angelsteg 5",
    "sg:city":"Dresden",
    "sg:phone":"+49 351/3108565",
    "sg:postcode":"01309",
    "sg:province":"Sachsen",
    "wof:name":"Schirm Dunger Inh. Christina Seipt",
    "wof:placetype":"venue"
},
  "geometry": {"coordinates":[13.8062620163,51.0524482727],"type":"Point"}
}