{
  "type": "Feature",
  "properties": {
    "iso:country":"DE",
    "sg:address":"Sutthauser Str. 30A",
    "sg:city":"Georgsmarienh\u00fctte",
    "sg:phone":"+49 5401/345580",
    "sg:postcode":"49124",
    "sg:province":"Niedersachsen",
    "wof:name":"Victoria Versicherungsb\u00fcro",
    "wof:placetype":"venue"
},
  "geometry": {"coordinates":[7.9974050522,52.2130508423],"type":"Point"}
}