{
  "type": "Feature",
  "properties": {
    "iso:country":"DE",
    "sg:address":"Rheinstr. 227",
    "sg:city":"Ingelheim",
    "sg:phone":"+49 6132/84712",
    "sg:postcode":"55218",
    "sg:province":"Rheinland-Pfalz",
    "wof:name":"Horst Kittner",
    "wof:placetype":"venue"
},
  "geometry": {"coordinates":[8.024091,49.990383],"type":"Point"}
}