{
  "type": "Feature",
  "properties": {
    "iso:country":"DE",
    "sg:address":"B\u00f6ckinger Str. 26/1",
    "sg:city":"Stuttgart",
    "sg:phone":"+49 711/8401861",
    "sg:postcode":"70437",
    "sg:province":"Baden-W\u00fcrttemberg",
    "wof:name":"Horst Filippi Laborbedarf",
    "wof:placetype":"venue"
},
  "geometry": {"coordinates":[9.196287,48.83617],"type":"Point"}
}