{
  "type": "Feature",
  "properties": {
    "iso:country":"DE",
    "sg:address":"Freudentaler Str. 27",
    "sg:city":"L\u00f6chgau",
    "sg:phone":"+49 7143/24461",
    "sg:postcode":"74369",
    "sg:province":"Baden-W\u00fcrttemberg",
    "wof:name":"Gerhard Weigel",
    "wof:placetype":"venue"
},
  "geometry": {"coordinates":[9.101360321,49.0025672913],"type":"Point"}
}