{
  "type": "Feature",
  "properties": {
    "iso:country":"DE",
    "sg:address":"Nordstr. 1",
    "sg:city":"Rimsting",
    "sg:phone":"+49 8051/68880",
    "sg:postcode":"83253",
    "sg:province":"Bayern",
    "wof:name":"Koch Membranen Beteiligungs- Gmbh",
    "wof:placetype":"venue"
},
  "geometry": {"coordinates":[12.334902,47.884472],"type":"Point"}
}