{
  "type": "Feature",
  "properties": {
    "iso:country":"DE",
    "sg:address":"Harzstr. 2",
    "sg:city":"Heudeber",
    "sg:phone":"+49 39458/5511",
    "sg:postcode":"38855",
    "sg:province":"Sachsen-Anhalt",
    "wof:name":"Recycling-park Gmbh",
    "wof:placetype":"venue"
},
  "geometry": {"coordinates":[10.8397340775,51.9022789001],"type":"Point"}
}