{
  "type": "Feature",
  "properties": {
    "iso:country":"DE",
    "sg:address":"Dr.-Schanz-Str. 20",
    "sg:city":"Olbernhau",
    "sg:phone":"+49 37360/72895",
    "sg:postcode":"09526",
    "sg:province":"Sachsen",
    "wof:name":"Mack & Partner Gmbh",
    "wof:placetype":"venue"
},
  "geometry": {"coordinates":[13.3556079865,50.6544265747],"type":"Point"}
}