{
  "type": "Feature",
  "properties": {
    "iso:country":"DE",
    "sg:address":"Schlagbaumweg 15",
    "sg:city":"Oldenburg",
    "sg:phone":"+49 441/505816",
    "sg:postcode":"26131",
    "sg:province":"Niedersachsen",
    "wof:name":"Kantholz Zimmerei Gmbh",
    "wof:placetype":"venue"
},
  "geometry": {"coordinates":[8.1885614395,53.114364624],"type":"Point"}
}