{
  "type": "Feature",
  "properties": {
    "iso:country":"DE",
    "sg:address":"Breslauer Str.",
    "sg:city":"Eberbach",
    "sg:phone":"+49 6271/3253",
    "sg:postcode":"69412",
    "sg:province":"Baden-W\u00fcrttemberg",
    "wof:name":"Haus Brandenburg",
    "wof:placetype":"venue"
},
  "geometry": {"coordinates":[8.9876823425,49.4760742188],"type":"Point"}
}