{
  "type": "Feature",
  "properties": {
    "iso:country":"DE",
    "sg:address":"Unterblissenbach 7",
    "sg:city":"K\u00fcrten",
    "sg:phone":"+49 2207/7895",
    "sg:postcode":"51515",
    "sg:province":"Nordrhein-Westfalen",
    "wof:name":"Gerd L\u00f6h Natursteinbearbeitung Gmbh",
    "wof:placetype":"venue"
},
  "geometry": {"coordinates":[7.2084407806,51.0181388855],"type":"Point"}
}