{
  "type": "Feature",
  "properties": {
    "iso:country":"DE",
    "sg:address":"M\u00fcnchener Str. 112",
    "sg:city":"Roth",
    "sg:phone":"+49 9171/892349",
    "sg:postcode":"91154",
    "sg:province":"Bayern",
    "wof:name":"Hermann Langenberger",
    "wof:placetype":"venue"
},
  "geometry": {"coordinates":[11.086506,49.233086],"type":"Point"}
}