{
  "type": "Feature",
  "properties": {
    "iso:country":"DE",
    "sg:address":"Hohe Str. 99",
    "sg:city":"Ditzingen",
    "sg:phone":"+49 7156/31608",
    "sg:postcode":"71254",
    "sg:province":"Baden-W\u00fcrttemberg",
    "wof:name":"P. Stilianidis",
    "wof:placetype":"venue"
},
  "geometry": {"coordinates":[9.0418701172,48.8392105103],"type":"Point"}
}