{
  "type": "Feature",
  "properties": {
    "iso:country":"DE",
    "sg:address":"Georg-Hartmann-Str. 6",
    "sg:city":"Jossgrund",
    "sg:phone":"+49 6059/308",
    "sg:postcode":"63637",
    "sg:province":"Hessen",
    "wof:name":"Pension Burgschenke",
    "wof:placetype":"venue"
},
  "geometry": {"coordinates":[9.4802694321,50.205493927],"type":"Point"}
}