{
  "type": "Feature",
  "properties": {
    "iso:country":"DE",
    "sg:address":"Am Fleckenberg 9a",
    "sg:city":"Limburg",
    "sg:phone":"+49 6431/98770",
    "sg:postcode":"65549",
    "sg:province":"Hessen",
    "wof:name":"I-center Elektrogro\u00dfhandel Gmbh & Co.",
    "wof:placetype":"venue"
},
  "geometry": {"coordinates":[8.0592288971,50.4044761658],"type":"Point"}
}