{
  "type": "Feature",
  "properties": {
    "iso:country":"DE",
    "sg:address":"Gartenstr. 5",
    "sg:city":"St. Georgen",
    "sg:phone":"+49 7724/6590",
    "sg:postcode":"78112",
    "sg:province":"Baden-W\u00fcrttemberg",
    "wof:name":"L. Schultheiss",
    "wof:placetype":"venue"
},
  "geometry": {"coordinates":[8.3213176727,48.1265602112],"type":"Point"}
}