{
  "type": "Feature",
  "properties": {
    "iso:country":"DE",
    "sg:address":"Daverdener Str. 39",
    "sg:city":"Langwedel",
    "sg:phone":"+49 4235/546",
    "sg:postcode":"27299",
    "sg:province":"Niedersachsen",
    "wof:name":"Kr\u00fcger-druck",
    "wof:placetype":"venue"
},
  "geometry": {"coordinates":[9.15223,52.988621],"type":"Point"}
}