{
  "type": "Feature",
  "properties": {
    "iso:country":"DE",
    "sg:address":"Spitalfeldstr. 14",
    "sg:city":"Landsberg",
    "sg:phone":"+49 8191/1494",
    "sg:postcode":"86899",
    "sg:province":"Bayern",
    "wof:name":"Schneider-reisen Gmbh",
    "wof:placetype":"venue"
},
  "geometry": {"coordinates":[10.8856992722,48.0508155823],"type":"Point"}
}