{
  "type": "Feature",
  "properties": {
    "iso:country":"DE",
    "sg:address":"Kaltenmoserstr. 7",
    "sg:city":"Weilheim",
    "sg:phone":"+49 881/2236",
    "sg:postcode":"82362",
    "sg:province":"Bayern",
    "wof:name":"Helmut Fischer Foto",
    "wof:placetype":"venue"
},
  "geometry": {"coordinates":[11.1501188278,47.8438835144],"type":"Point"}
}