{
  "type": "Feature",
  "properties": {
    "iso:country":"DE",
    "sg:address":"Hamburger Str. 50",
    "sg:city":"Dortmund",
    "sg:phone":"+49 231/527923",
    "sg:postcode":"44135",
    "sg:province":"Nordrhein-Westfalen",
    "wof:name":"Immobilien Schneider Kg",
    "wof:placetype":"venue"
},
  "geometry": {"coordinates":[7.4800782204,51.5144691467],"type":"Point"}
}