{
  "type": "Feature",
  "properties": {
    "iso:country":"DE",
    "sg:address":"Berliner Promenade 10",
    "sg:city":"Saarbr\u00fccken",
    "sg:postcode":"66111",
    "sg:province":"Saarland",
    "wof:name":"Intradex Grundst\u00fccks- Vermittlungs- Und Beratungs-",
    "wof:placetype":"venue"
},
  "geometry": {"coordinates":[6.9923858643,49.2360115051],"type":"Point"}
}