{
  "type": "Feature",
  "properties": {
    "iso:country":"DE",
    "sg:address":"Hintergasse 8",
    "sg:city":"Dierdorf",
    "sg:phone":"+49 2689/7350",
    "sg:postcode":"56269",
    "sg:province":"Rheinland-Pfalz",
    "wof:name":"Rolf Scheyer",
    "wof:placetype":"venue"
},
  "geometry": {"coordinates":[7.659428,50.537266],"type":"Point"}
}