{
  "type": "Feature",
  "properties": {
    "iso:country":"DE",
    "sg:address":"Am Weinh\u00fcgel 6",
    "sg:city":"F\u00fcrstenzell",
    "sg:phone":"+49 8502/612",
    "sg:postcode":"94081",
    "sg:province":"Bayern",
    "wof:name":"Dreifl\u00fcssige Wohnbau Gmbh",
    "wof:placetype":"venue"
},
  "geometry": {"coordinates":[13.320245,48.525093],"type":"Point"}
}