{
  "type": "Feature",
  "properties": {
    "iso:country":"DE",
    "sg:address":"Ahornstr. 26",
    "sg:city":"Bodnegg",
    "sg:phone":"+49 4975/202157",
    "sg:postcode":"88285",
    "sg:province":"Baden-W\u00fcrttemberg",
    "wof:name":"Krauss Gmbh",
    "wof:placetype":"venue"
},
  "geometry": {"coordinates":[9.698715,47.728634],"type":"Point"}
}