{
  "type": "Feature",
  "properties": {
    "iso:country":"DE",
    "sg:address":"Fischeln 10",
    "sg:city":"Schwalmtal",
    "sg:phone":"+49 2163/31078",
    "sg:postcode":"41366",
    "sg:province":"Nordrhein-Westfalen",
    "wof:name":"A. Conrad Bauunternehmung Gmbh",
    "wof:placetype":"venue"
},
  "geometry": {"coordinates":[6.3123931885,51.1951789856],"type":"Point"}
}