{
  "type": "Feature",
  "properties": {
    "iso:country":"DE",
    "sg:address":"Turkuer Str. 10",
    "sg:city":"Rostock",
    "sg:phone":"+49 381/718446",
    "sg:postcode":"18107",
    "sg:province":"Mecklenburg-Vorpommern",
    "wof:name":"Gerhard Dugel",
    "wof:placetype":"venue"
},
  "geometry": {"coordinates":[12.0519418716,54.1404685974],"type":"Point"}
}