{
  "type": "Feature",
  "properties": {
    "iso:country":"DE",
    "sg:address":"Nu\u00dfdorfer Str. 38g",
    "sg:city":"\u00dcberlingen",
    "sg:phone":"+49 7551/918640",
    "sg:postcode":"88662",
    "sg:province":"Baden-W\u00fcrttemberg",
    "wof:name":"Target Computersysteme Haller Pfaff & Niedermann Ohg",
    "wof:placetype":"venue"
},
  "geometry": {"coordinates":[9.176492691,47.7608680725],"type":"Point"}
}