{
  "type": "Feature",
  "properties": {
    "iso:country":"DE",
    "sg:address":"Krantorstr. 8",
    "sg:city":"Neum\u00fcnster",
    "sg:phone":"+49 4321/528262",
    "sg:postcode":"24536",
    "sg:province":"Schleswig-Holstein",
    "wof:name":"Klaus Schorlepp",
    "wof:placetype":"venue"
},
  "geometry": {"coordinates":[9.9850912094,54.1207618713],"type":"Point"}
}