{
  "type": "Feature",
  "properties": {
    "iso:country":"DE",
    "sg:address":"Anzinger Str. 1",
    "sg:city":"M\u00fcnchen",
    "sg:phone":"+49 89/492023",
    "sg:postcode":"81671",
    "sg:province":"Bayern",
    "wof:name":"Bayerische Vereinsbank Ag",
    "wof:placetype":"venue"
},
  "geometry": {"coordinates":[11.606401,48.12096],"type":"Point"}
}