{
  "type": "Feature",
  "properties": {
    "iso:country":"DE",
    "sg:address":"Abelhorster Weg 2",
    "sg:city":"Beverstedt",
    "sg:phone":"+49 4749/540",
    "sg:postcode":"27616",
    "sg:province":"Niedersachsen",
    "wof:name":"I. Niemeyer",
    "wof:placetype":"venue"
},
  "geometry": {"coordinates":[8.865885,53.476997],"type":"Point"}
}