{
  "type": "Feature",
  "properties": {
    "iso:country":"DE",
    "sg:address":"F\u00fcrstenwall 200",
    "sg:city":"D\u00fcsseldorf",
    "sg:phone":"+49 211/371111",
    "sg:postcode":"40215",
    "sg:province":"Nordrhein-Westfalen",
    "wof:name":"Huvo Druck Gmbh",
    "wof:placetype":"venue"
},
  "geometry": {"coordinates":[6.781168,51.214069],"type":"Point"}
}