{
  "type": "Feature",
  "properties": {
    "iso:country":"DE",
    "sg:address":"Tuchbleiche 2",
    "sg:city":"Haina",
    "sg:phone":"+49 6456/747",
    "sg:postcode":"35114",
    "sg:province":"Hessen",
    "wof:name":"Dieter Webelhuth",
    "wof:placetype":"venue"
},
  "geometry": {"coordinates":[9.050105,51.011929],"type":"Point"}
}