{
  "type": "Feature",
  "properties": {
    "iso:country":"DE",
    "sg:address":"Am Wendehammer 6",
    "sg:city":"Glandorf",
    "sg:phone":"+49 5426/3818",
    "sg:postcode":"49219",
    "sg:province":"Niedersachsen",
    "wof:name":"Rolf Schiermeyer",
    "wof:placetype":"venue"
},
  "geometry": {"coordinates":[8.0374107361,52.0858268738],"type":"Point"}
}