{
  "type": "Feature",
  "properties": {
    "iso:country":"DE",
    "sg:address":"Industriestra\u00dfe 7",
    "sg:city":"Bischofsheim/Rh\u00f6n",
    "sg:phone":"+49 9772",
    "sg:postcode":"97653",
    "sg:province":"Bayern",
    "wof:name":"Maschinenfabrik Berner - Richtpressen,maschinenbau",
    "wof:placetype":"venue"
},
  "geometry": {"coordinates":[10.0066432953,50.4111785889],"type":"Point"}
}