{
  "type": "Feature",
  "properties": {
    "iso:country":"DE",
    "sg:address":"Neuffener Str. 34",
    "sg:city":"Dettingen",
    "sg:phone":"+49 7123/71779",
    "sg:postcode":"72581",
    "sg:province":"Baden-W\u00fcrttemberg",
    "wof:name":"K.-h. Krohmer",
    "wof:placetype":"venue"
},
  "geometry": {"coordinates":[9.34649086,48.5317306519],"type":"Point"}
}