{
  "type": "Feature",
  "properties": {
    "iso:country":"DE",
    "sg:address":"Am Regensbusch 13",
    "sg:city":"Vettwei\u00df",
    "sg:phone":"+49 2424/1808",
    "sg:postcode":"52391",
    "sg:province":"Nordrhein-Westfalen",
    "wof:name":"B. M\u00fcnchhalfen",
    "wof:placetype":"venue"
},
  "geometry": {"coordinates":[6.666453,50.751106],"type":"Point"}
}