{
  "type": "Feature",
  "properties": {
    "iso:country":"DE",
    "sg:address":"Greulingstr. 24",
    "sg:city":"Remscheid",
    "sg:phone":"+49 2191/30769",
    "sg:postcode":"42859",
    "sg:province":"Nordrhein-Westfalen",
    "wof:name":"Gastst\u00e4tte Rudolf Quast",
    "wof:placetype":"venue"
},
  "geometry": {"coordinates":[7.2098407745,51.1749153137],"type":"Point"}
}