{
  "type": "Feature",
  "properties": {
    "iso:country":"DE",
    "sg:address":"\u00d6rtelplatz 5",
    "sg:city":"Zittau",
    "sg:phone":"+49 3583/684084",
    "sg:postcode":"02763",
    "sg:province":"Sachsen",
    "wof:name":"Heinz Apelt Gmbh",
    "wof:placetype":"venue"
},
  "geometry": {"coordinates":[14.8081359863,50.8824958801],"type":"Point"}
}