{
  "type": "Feature",
  "properties": {
    "iso:country":"DE",
    "sg:address":"Schneidergasse 1",
    "sg:city":"Manching",
    "sg:phone":"+49 8459/30868",
    "sg:postcode":"85077",
    "sg:province":"Bayern",
    "wof:name":"Anton Bauer",
    "wof:placetype":"venue"
},
  "geometry": {"coordinates":[11.454896,48.713139],"type":"Point"}
}