{
  "type": "Feature",
  "properties": {
    "iso:country":"DE",
    "sg:address":"K\u00f6lner Str. 69-73",
    "sg:city":"J\u00fcchen",
    "sg:phone":"+49 2165/911328",
    "sg:postcode":"41363",
    "sg:province":"Nordrhein-Westfalen",
    "wof:name":"Troika Brandl\u00f6sch- Und Industrieanlagenbau Gmbh",
    "wof:placetype":"venue"
},
  "geometry": {"coordinates":[6.5145602226,51.0972366333],"type":"Point"}
}