{
  "type": "Feature",
  "properties": {
    "iso:country":"DE",
    "sg:address":"Emser Str. 23",
    "sg:city":"Koblenz",
    "sg:phone":"+49 261/9722030",
    "sg:postcode":"56076",
    "sg:province":"Rheinland-Pfalz",
    "wof:name":"Evangelische Kirchengemeinde Koblenz-pfaffendorf",
    "wof:placetype":"venue"
},
  "geometry": {"coordinates":[7.6087989807,50.3532333374],"type":"Point"}
}