{
  "type": "Feature",
  "properties": {
    "iso:country":"DE",
    "sg:address":"Handtalstr. 6",
    "sg:city":"Jossgrund",
    "sg:phone":"+49 6059/230",
    "sg:postcode":"63637",
    "sg:province":"Hessen",
    "wof:name":"Alfred Els\u00e4sser",
    "wof:placetype":"venue"
},
  "geometry": {"coordinates":[9.4740333557,50.1669616699],"type":"Point"}
}