{
  "type": "Feature",
  "properties": {
    "iso:country":"DE",
    "sg:address":"Engellaustr. 2",
    "sg:city":"Castrop-Rauxel",
    "sg:phone":"+49 2305/21293",
    "sg:postcode":"44575",
    "sg:province":"Nordrhein-Westfalen",
    "wof:name":"Heinrich Schlechter",
    "wof:placetype":"venue"
},
  "geometry": {"coordinates":[7.2958698273,51.5547409058],"type":"Point"}
}