{
  "type": "Feature",
  "properties": {
    "iso:country":"DE",
    "sg:address":"Industriestr 26",
    "sg:city":"Mettmann",
    "sg:phone":"+49 2104/917970",
    "sg:postcode":"40822",
    "sg:province":"Nordrhein-Westfalen",
    "wof:name":"Aluminium Hardenberg Handels-gmbh",
    "wof:placetype":"venue"
},
  "geometry": {"coordinates":[7.011983,51.250652],"type":"Point"}
}