{
  "type": "Feature",
  "properties": {
    "iso:country":"DE",
    "sg:address":"Birkenweg 7",
    "sg:city":"Willich",
    "sg:phone":"+49 2154/7888",
    "sg:postcode":"47877",
    "sg:province":"Nordrhein-Westfalen",
    "wof:name":"Uwe Paulsen",
    "wof:placetype":"venue"
},
  "geometry": {"coordinates":[6.5480389595,51.2386817932],"type":"Point"}
}