{
  "type": "Feature",
  "properties": {
    "iso:country":"DE",
    "sg:address":"Auf dem Graskamp 77A",
    "sg:city":"Gelsenkirchen",
    "sg:phone":"+49 209/201008",
    "sg:postcode":"45888",
    "sg:province":"Nordrhein-Westfalen",
    "wof:name":"Grotec Gro\u00dfk\u00fcchenservice Und Vertriebsgesellschaft Mbh",
    "wof:placetype":"venue"
},
  "geometry": {"coordinates":[7.109555,51.512844],"type":"Point"}
}