{
  "type": "Feature",
  "properties": {
    "iso:country":"DE",
    "sg:address":"Holtzendorffstr. 20",
    "sg:city":"Berlin",
    "sg:phone":"+49 30/3275669",
    "sg:postcode":"14057",
    "sg:province":"Berlin",
    "wof:name":"Taverna Mylos",
    "wof:placetype":"venue"
},
  "geometry": {"coordinates":[13.2960138321,52.5063056946],"type":"Point"}
}