{
  "type": "Feature",
  "properties": {
    "iso:country":"DE",
    "sg:address":"Burbacher Str. 29",
    "sg:city":"Saarbr\u00fccken",
    "sg:phone":"+49 681/776600",
    "sg:postcode":"66115",
    "sg:province":"Saarland",
    "wof:name":"Pizzeria Bella Roma",
    "wof:placetype":"venue"
},
  "geometry": {"coordinates":[6.9448428154,49.2392692566],"type":"Point"}
}