{
  "type": "Feature",
  "properties": {
    "iso:country":"DE",
    "sg:address":"Ortsstr.",
    "sg:city":"Stein\u00e4chle",
    "sg:phone":"+49 7195/64753",
    "sg:postcode":"71364",
    "sg:province":"Baden-W\u00fcrttemberg",
    "wof:name":"Eugen Jung",
    "wof:placetype":"venue"
},
  "geometry": {"coordinates":[9.395121,48.876076],"type":"Point"}
}