{
  "type": "Feature",
  "properties": {
    "iso:country":"DE",
    "sg:address":"Robert-Koch-Str. 10",
    "sg:city":"M\u00fchlheim",
    "sg:phone":"+49 6108/69397",
    "sg:postcode":"63165",
    "sg:province":"Hessen",
    "wof:name":"Eghalanda Gmoiz Offenbach A. M.",
    "wof:placetype":"venue"
},
  "geometry": {"coordinates":[8.8536682129,50.1020317078],"type":"Point"}
}