{
  "type": "Feature",
  "properties": {
    "iso:country":"DE",
    "sg:address":"Ackerstr. 124",
    "sg:city":"D\u00fcsseldorf",
    "sg:postcode":"40233",
    "sg:province":"Nordrhein-Westfalen",
    "wof:name":"As Hydroplant Gmbh",
    "wof:placetype":"venue"
},
  "geometry": {"coordinates":[6.805065,51.229313],"type":"Point"}
}