{
  "type": "Feature",
  "properties": {
    "iso:country":"DE",
    "sg:address":"Amalienburgstr. 25",
    "sg:city":"M\u00fcnchen",
    "sg:phone":"+49 89/8119292",
    "sg:postcode":"81247",
    "sg:province":"Bayern",
    "wof:name":"Sixt Ag",
    "wof:placetype":"venue"
},
  "geometry": {"coordinates":[11.487881,48.163784],"type":"Point"}
}