{
  "type": "Feature",
  "properties": {
    "iso:country":"DE",
    "sg:address":"Hauptstr. 38",
    "sg:city":"Kressbronn",
    "sg:phone":"+49 7543/7609",
    "sg:postcode":"88079",
    "sg:province":"Baden-W\u00fcrttemberg",
    "wof:name":"Schreinerei Binzler Gmbh",
    "wof:placetype":"venue"
},
  "geometry": {"coordinates":[9.600199,47.595177],"type":"Point"}
}