{
  "type": "Feature",
  "properties": {
    "iso:country":"DE",
    "sg:address":"Hauptstr. 1",
    "sg:city":"Dingdorf",
    "sg:phone":"+49 6553/1881",
    "sg:postcode":"54614",
    "sg:province":"Rheinland-Pfalz",
    "wof:name":"Stefan Pinten",
    "wof:placetype":"venue"
},
  "geometry": {"coordinates":[6.435611,50.152523],"type":"Point"}
}