{
  "type": "Feature",
  "properties": {
    "iso:country":"DE",
    "sg:address":"Grabenstr. 3 Hof",
    "sg:city":"Duisburg",
    "sg:phone":"+49 4920/3992580",
    "sg:postcode":"47057",
    "sg:province":"Nordrhein-Westfalen",
    "wof:name":"C-faktory Gesellschaft Kommunikation Mbh",
    "wof:placetype":"venue"
},
  "geometry": {"coordinates":[6.78134,51.430237],"type":"Point"}
}