{
  "type": "Feature",
  "properties": {
    "iso:country":"DE",
    "sg:address":"Sollingstr. 21",
    "sg:city":"Holzminden",
    "sg:phone":"+49 5531/7190",
    "sg:postcode":"37603",
    "sg:province":"Niedersachsen",
    "wof:name":"Sander & Sprenger",
    "wof:placetype":"venue"
},
  "geometry": {"coordinates":[9.475238,51.827446],"type":"Point"}
}