{
  "type": "Feature",
  "properties": {
    "iso:country":"DE",
    "sg:address":"Pfalzburger Str. 10A",
    "sg:city":"Berlin",
    "sg:postcode":"10719",
    "sg:province":"Berlin",
    "wof:name":"Kucheleck Gmbh",
    "wof:placetype":"venue"
},
  "geometry": {"coordinates":[13.3224458694,52.4981422424],"type":"Point"}
}