{
  "type": "Feature",
  "properties": {
    "iso:country":"DE",
    "sg:address":"Kirchstr. 6",
    "sg:city":"Allersberg",
    "sg:phone":"+49 9176/365",
    "sg:postcode":"90584",
    "sg:province":"Bayern",
    "wof:name":"Josef Maurer",
    "wof:placetype":"venue"
},
  "geometry": {"coordinates":[11.234957695,49.2507247925],"type":"Point"}
}