{
  "type": "Feature",
  "properties": {
    "iso:country":"DE",
    "sg:address":"Sandstr. 40",
    "sg:city":"Berlin",
    "sg:phone":"+49 30/3613794",
    "sg:postcode":"13593",
    "sg:province":"Berlin",
    "wof:name":"Hans-joachim Und \u00c4nne Meier",
    "wof:placetype":"venue"
},
  "geometry": {"coordinates":[13.168087,52.516579],"type":"Point"}
}