{
  "type": "Feature",
  "properties": {
    "iso:country":"DE",
    "sg:address":"Kreuzholzstr. 3",
    "sg:city":"Ludwigshafen",
    "sg:phone":"+49 621/6688513",
    "sg:postcode":"67069",
    "sg:province":"Rheinland-Pfalz",
    "wof:name":"Buchen Umweltservice Gmbh",
    "wof:placetype":"venue"
},
  "geometry": {"coordinates":[8.40755,49.540894],"type":"Point"}
}