{
  "type": "Feature",
  "properties": {
    "iso:country":"DE",
    "sg:address":"Eichenplatz 17",
    "sg:city":"Bad D\u00fcrkheim",
    "sg:phone":"+49 6322/620810",
    "sg:postcode":"67098",
    "sg:province":"Rheinland-Pfalz",
    "wof:name":"Michael Hack",
    "wof:placetype":"venue"
},
  "geometry": {"coordinates":[8.1370849609,49.4596557617],"type":"Point"}
}