{
  "type": "Feature",
  "properties": {
    "iso:country":"DE",
    "sg:address":"Industriestr. 18",
    "sg:city":"D\u00f6rentrup",
    "sg:phone":"+49 4952/658282",
    "sg:postcode":"32694",
    "sg:province":"Nordrhein-Westfalen",
    "wof:name":"Olaf T\u00dcnker Polsterm\u00d6bel",
    "wof:placetype":"venue"
},
  "geometry": {"coordinates":[9.0398645401,52.0273284912],"type":"Point"}
}