{
  "type": "Feature",
  "properties": {
    "iso:country":"DE",
    "sg:address":"Gr\u00fcnthaler Str. 30",
    "sg:city":"Olbernhau",
    "sg:phone":"+49 37360/7450",
    "sg:postcode":"09526",
    "sg:province":"Sachsen",
    "wof:name":"Wohnungsbaugesellschaft Olbernhau Mbh",
    "wof:placetype":"venue"
},
  "geometry": {"coordinates":[13.3405990601,50.6591567993],"type":"Point"}
}