{
  "type": "Feature",
  "properties": {
    "iso:country":"DE",
    "sg:address":"Heinrich-Behr-Str. 5b",
    "sg:city":"Lobenstein",
    "sg:phone":"+49 36651/3641",
    "sg:postcode":"07356",
    "sg:province":"Th\u00fcringen",
    "wof:name":"Tbs Beratung Und Service Gmbh",
    "wof:placetype":"venue"
},
  "geometry": {"coordinates":[11.6396789551,50.4527587891],"type":"Point"}
}