{
  "type": "Feature",
  "properties": {
    "iso:country":"DE",
    "sg:address":"Bergstr. 16",
    "sg:city":"Krailling",
    "sg:postcode":"82152",
    "sg:province":"Bayern",
    "wof:name":"Zietenstra\u00dfe 81 Sebastian-bach-stra\u00dfe 13",
    "wof:placetype":"venue"
},
  "geometry": {"coordinates":[11.412668,48.102005],"type":"Point"}
}