{
  "type": "Feature",
  "properties": {
    "iso:country":"DE",
    "sg:address":"Installstr. 10",
    "sg:city":"B\u00fcnde",
    "sg:phone":"+49 5223/4810",
    "sg:postcode":"32257",
    "sg:province":"Nordrhein-Westfalen",
    "wof:name":"Imperial-werke Verwaltungs Gmbh",
    "wof:placetype":"venue"
},
  "geometry": {"coordinates":[8.5742502213,52.2027931213],"type":"Point"}
}