{
  "type": "Feature",
  "properties": {
    "iso:country":"DE",
    "sg:address":"Adolfstr. 99",
    "sg:city":"Bad Schwalbach",
    "sg:phone":"+49 6124/2781",
    "sg:postcode":"65307",
    "sg:province":"Hessen",
    "wof:name":"Hellas",
    "wof:placetype":"venue"
},
  "geometry": {"coordinates":[8.0739088058,50.1437187195],"type":"Point"}
}