{
  "type": "Feature",
  "properties": {
    "iso:country":"DE",
    "sg:address":"Aachener Str. 77",
    "sg:city":"M\u00f6nchengladbach",
    "sg:postcode":"41061",
    "sg:province":"Nordrhein-Westfalen",
    "wof:name":"Hob Gmbh",
    "wof:placetype":"venue"
},
  "geometry": {"coordinates":[6.425613,51.194649],"type":"Point"}
}