{
  "type": "Feature",
  "properties": {
    "iso:country":"DE",
    "sg:address":"Rudolf-Diesel-Str 9",
    "sg:city":"Meerbusch",
    "sg:phone":"+49 2159/69990",
    "sg:postcode":"40670",
    "sg:province":"Nordrhein-Westfalen",
    "wof:name":"Ton- Und Studiotechnik Gmbh",
    "wof:placetype":"venue"
},
  "geometry": {"coordinates":[6.6157717705,51.2751350403],"type":"Point"}
}