{
  "type": "Feature",
  "properties": {
    "iso:country":"DE",
    "sg:address":"Cranestr. 10",
    "sg:city":"Geseke",
    "sg:phone":"+49 2942/78501",
    "sg:postcode":"59590",
    "sg:province":"Nordrhein-Westfalen",
    "wof:name":"Horst Dieter Tiemann",
    "wof:placetype":"venue"
},
  "geometry": {"coordinates":[8.5075302124,51.6395797729],"type":"Point"}
}