{
  "type": "Feature",
  "properties": {
    "iso:country":"DE",
    "sg:address":"Langer Steinweg 12",
    "sg:city":"Blomberg",
    "sg:phone":"+49 5235/96020",
    "sg:postcode":"32825",
    "sg:province":"Nordrhein-Westfalen",
    "wof:name":"Dachdeckermeister Thomas Zastrow Gmbh",
    "wof:placetype":"venue"
},
  "geometry": {"coordinates":[9.09134,51.942596],"type":"Point"}
}