{
  "type": "Feature",
  "properties": {
    "iso:country":"DE",
    "sg:address":"Potsdamer Str. 10",
    "sg:city":"Teltow",
    "sg:postcode":"14513",
    "sg:province":"Brandenburg",
    "wof:name":"Werbetechnik Teltow Gmbh",
    "wof:placetype":"venue"
},
  "geometry": {"coordinates":[13.244591,52.397659],"type":"Point"}
}