{
  "type": "Feature",
  "properties": {
    "iso:country":"DE",
    "sg:address":"Lortzingstr. 15",
    "sg:city":"Bad Pyrmont",
    "sg:phone":"+49 5281/17771",
    "sg:postcode":"31812",
    "sg:province":"Niedersachsen",
    "wof:name":"Lortzing-apotheke",
    "wof:placetype":"venue"
},
  "geometry": {"coordinates":[9.262801,51.985512],"type":"Point"}
}