{
  "type": "Feature",
  "properties": {
    "iso:country":"DE",
    "sg:address":"Ruhrau 45",
    "sg:city":"Essen",
    "sg:phone":"+49 201/54918",
    "sg:postcode":"45279",
    "sg:province":"Nordrhein-Westfalen",
    "wof:name":"W. Kr\u00fcger Einbauk\u00fcchen",
    "wof:placetype":"venue"
},
  "geometry": {"coordinates":[7.088435173,51.4400482178],"type":"Point"}
}