{
  "type": "Feature",
  "properties": {
    "iso:country":"DE",
    "sg:address":"Maiweg 16",
    "sg:city":"Siegen",
    "sg:phone":"+49 271/353134",
    "sg:postcode":"57080",
    "sg:province":"Nordrhein-Westfalen",
    "wof:name":"F-trade Beteiligungs- Und Verwaltungs-gmbh",
    "wof:placetype":"venue"
},
  "geometry": {"coordinates":[7.9562091827,50.858505249],"type":"Point"}
}