{
  "type": "Feature",
  "properties": {
    "iso:country":"DE",
    "sg:address":"Wixh\u00e4user Str. 19",
    "sg:city":"Weiterstadt",
    "sg:phone":"+49 6150/52664",
    "sg:postcode":"64331",
    "sg:province":"Hessen",
    "wof:name":"Kaufeld Ingenieur",
    "wof:placetype":"venue"
},
  "geometry": {"coordinates":[8.606754303,49.9312858582],"type":"Point"}
}