{
  "type": "Feature",
  "properties": {
    "iso:country":"DE",
    "sg:address":"Seeweg 4",
    "sg:city":"Eisfeld",
    "sg:phone":"+49 4936/863620",
    "sg:postcode":"98673",
    "sg:province":"Th\u00fcringen",
    "wof:name":"Feintechnik Gmbh",
    "wof:placetype":"venue"
},
  "geometry": {"coordinates":[10.909722,50.417732],"type":"Point"}
}