{
  "type": "Feature",
  "properties": {
    "iso:country":"DE",
    "sg:address":"Am Zollhaus 16",
    "sg:city":"Fulda",
    "sg:phone":"+49 661/45932",
    "sg:postcode":"36043",
    "sg:province":"Hessen",
    "wof:name":"T. M\u00fcller",
    "wof:placetype":"venue"
},
  "geometry": {"coordinates":[9.6807546616,50.5261116028],"type":"Point"}
}