{
  "type": "Feature",
  "properties": {
    "iso:country":"DE",
    "sg:address":"Schusterstr. 11",
    "sg:city":"Bad Aibling",
    "sg:phone":"+49 8061/2038",
    "sg:postcode":"83043",
    "sg:province":"Bayern",
    "wof:name":"Mo-car Technik Gmbh",
    "wof:placetype":"venue"
},
  "geometry": {"coordinates":[11.986464,47.857262],"type":"Point"}
}