{
  "type": "Feature",
  "properties": {
    "iso:country":"DE",
    "sg:address":"Primsstr. 16",
    "sg:city":"Nalbach",
    "sg:phone":"+49 6838/2156",
    "sg:postcode":"66809",
    "sg:province":"Saarland",
    "wof:name":"Robert Weisgerber",
    "wof:placetype":"venue"
},
  "geometry": {"coordinates":[6.7831788063,49.3765106201],"type":"Point"}
}