{
  "type": "Feature",
  "properties": {
    "iso:country":"DE",
    "sg:address":"Sonnenburg",
    "sg:city":"Bad Freienwalde",
    "sg:phone":"+49 3344/330902",
    "sg:postcode":"16259",
    "sg:province":"Brandenburg",
    "wof:name":"Waldschenke Am Baa-see",
    "wof:placetype":"venue"
},
  "geometry": {"coordinates":[14.0403547287,52.7463378906],"type":"Point"}
}