{
  "type": "Feature",
  "properties": {
    "iso:country":"DE",
    "sg:address":"Marktplatz 20",
    "sg:city":"Gunzenhausen",
    "sg:phone":"+49 9831/67890",
    "sg:postcode":"91710",
    "sg:province":"Bayern",
    "wof:name":"Markt-apotheke Martin Weigel",
    "wof:placetype":"venue"
},
  "geometry": {"coordinates":[10.753857,49.114826],"type":"Point"}
}