{
  "type": "Feature",
  "properties": {
    "iso:country":"DE",
    "sg:address":"Dicke Steinstr. 9",
    "sg:city":"Rieder",
    "sg:phone":"+49 39485/60042",
    "sg:postcode":"06507",
    "sg:province":"Sachsen-Anhalt",
    "wof:name":"Klaus Meyer",
    "wof:placetype":"venue"
},
  "geometry": {"coordinates":[11.17139,51.735191],"type":"Point"}
}