{
  "type": "Feature",
  "properties": {
    "iso:country":"DE",
    "sg:address":"Carl-Maria-von-Weber-Str. 1",
    "sg:city":"Bischofswerda",
    "sg:phone":"+49 3594/704381",
    "sg:postcode":"01877",
    "sg:province":"Sachsen",
    "wof:name":"Imbi\u00dfst\u00fcbel",
    "wof:placetype":"venue"
},
  "geometry": {"coordinates":[14.1815509796,51.1375427246],"type":"Point"}
}