{
  "type": "Feature",
  "properties": {
    "iso:country":"DE",
    "sg:address":"Walderbacher Str. 6",
    "sg:city":"Walderbach",
    "sg:phone":"+49 9464/519",
    "sg:postcode":"93194",
    "sg:province":"Bayern",
    "wof:name":"G. Wallaschek",
    "wof:placetype":"venue"
},
  "geometry": {"coordinates":[12.380493,49.18502],"type":"Point"}
}