{
  "type": "Feature",
  "properties": {
    "iso:country":"DE",
    "sg:address":"Waldstr. 44",
    "sg:city":"Gleichen",
    "sg:phone":"+49 5592/210",
    "sg:postcode":"37130",
    "sg:province":"Niedersachsen",
    "wof:name":"Manfred G\u00fcnther",
    "wof:placetype":"venue"
},
  "geometry": {"coordinates":[9.990539,51.467476],"type":"Point"}
}