{
  "type": "Feature",
  "properties": {
    "iso:country":"DE",
    "sg:address":"Wenkenstr. 114",
    "sg:city":"Bad Salzuflen",
    "sg:phone":"+49 5222/91490",
    "sg:postcode":"32105",
    "sg:province":"Nordrhein-Westfalen",
    "wof:name":"Cafe Schulte",
    "wof:placetype":"venue"
},
  "geometry": {"coordinates":[8.76096,52.092663],"type":"Point"}
}