{
  "type": "Feature",
  "properties": {
    "iso:country":"DE",
    "sg:address":"Obere K\u00f6nigsstr. 11",
    "sg:city":"Kassel",
    "sg:phone":"+49 561/17642",
    "sg:postcode":"34117",
    "sg:province":"Hessen",
    "wof:name":"Schuh-hansa Gmbh & Co. Kg",
    "wof:placetype":"venue"
},
  "geometry": {"coordinates":[9.4920921326,51.3124542236],"type":"Point"}
}