{
  "type": "Feature",
  "properties": {
    "iso:country":"DE",
    "sg:address":"Koblenzer Str. 65",
    "sg:city":"Bonn",
    "sg:phone":"+49 228/353382",
    "sg:postcode":"53173",
    "sg:province":"Nordrhein-Westfalen",
    "wof:name":"Breuer Inh. E. Kautz",
    "wof:placetype":"venue"
},
  "geometry": {"coordinates":[7.155955,50.683601],"type":"Point"}
}