{
  "type": "Feature",
  "properties": {
    "iso:country":"DE",
    "sg:address":"Karl-Liebknecht-Str. 15",
    "sg:city":"Mainhausen",
    "sg:postcode":"63533",
    "sg:province":"Hessen",
    "wof:name":"Studio Ffm Rundfunkprogramm - Anbietergesellschaft Mbh",
    "wof:placetype":"venue"
},
  "geometry": {"coordinates":[9.0244598389,50.0281562805],"type":"Point"}
}