{
  "type": "Feature",
  "properties": {
    "iso:country":"DE",
    "sg:address":"Kirchhofallee 52",
    "sg:city":"Kiel",
    "sg:phone":"+49 431/61684",
    "sg:postcode":"24114",
    "sg:province":"Schleswig-Holstein",
    "wof:name":"Wei\u00dfe Rose",
    "wof:placetype":"venue"
},
  "geometry": {"coordinates":[10.121478,54.316631],"type":"Point"}
}