{
  "type": "Feature",
  "properties": {
    "iso:country":"DE",
    "sg:address":"Kuhlenkamp 7",
    "sg:city":"Bad Bentheim",
    "sg:phone":"+49 5924/6148",
    "sg:postcode":"48455",
    "sg:province":"Niedersachsen",
    "wof:name":"Helmut H\u00f6hne",
    "wof:placetype":"venue"
},
  "geometry": {"coordinates":[7.0961642265,52.2951431274],"type":"Point"}
}