{
  "type": "Feature",
  "properties": {
    "iso:country":"DE",
    "sg:address":"Burendamm 2",
    "sg:city":"Friesoythe",
    "sg:phone":"+49 4496/463",
    "sg:postcode":"26169",
    "sg:province":"Niedersachsen",
    "wof:name":"Clemens Sch\u00f6ning",
    "wof:placetype":"venue"
},
  "geometry": {"coordinates":[7.828995,52.975491],"type":"Point"}
}