{
  "type": "Feature",
  "properties": {
    "iso:country":"DE",
    "sg:address":"Siegener Str 27",
    "sg:city":"Plauen",
    "sg:phone":"+49 3741/423360",
    "sg:postcode":"08523",
    "sg:province":"Sachsen",
    "wof:name":"Altherma Schwimmbad- Und Wellnessanlagen E.k.",
    "wof:placetype":"venue"
},
  "geometry": {"coordinates":[12.1233797073,50.492401123],"type":"Point"}
}