{
  "type": "Feature",
  "properties": {
    "iso:country":"DE",
    "sg:address":"Friedrich-Ebert-Str. 105",
    "sg:city":"Detmold",
    "sg:phone":"+49 5231/8315",
    "sg:postcode":"32760",
    "sg:province":"Nordrhein-Westfalen",
    "wof:name":"Hans-heinrich Drewes",
    "wof:placetype":"venue"
},
  "geometry": {"coordinates":[8.841364,51.924397],"type":"Point"}
}