{
  "type": "Feature",
  "properties": {
    "iso:country":"DE",
    "sg:address":"Haselweg 5",
    "sg:city":"Bad Abbach",
    "sg:phone":"+49 9405/1726",
    "sg:postcode":"93077",
    "sg:province":"Bayern",
    "wof:name":"P. Joscheck",
    "wof:placetype":"venue"
},
  "geometry": {"coordinates":[12.0554065704,48.9221420288],"type":"Point"}
}