{
  "type": "Feature",
  "properties": {
    "iso:country":"DE",
    "sg:address":"Reinhard-Freericks-Str. 4",
    "sg:city":"Haltern",
    "sg:phone":"+49 2364/4791",
    "sg:postcode":"45721",
    "sg:province":"Nordrhein-Westfalen",
    "wof:name":"M. Klassert",
    "wof:placetype":"venue"
},
  "geometry": {"coordinates":[7.18189,51.745731],"type":"Point"}
}