{
  "type": "Feature",
  "properties": {
    "iso:country":"DE",
    "sg:address":"Frettchenweg 12",
    "sg:city":"Leipzig",
    "sg:postcode":"04249",
    "sg:province":"Sachsen",
    "wof:name":"Ddj Montieren Und Ablesen Und Handel Mit",
    "wof:placetype":"venue"
},
  "geometry": {"coordinates":[12.3065481186,51.285785675],"type":"Point"}
}