{
  "type": "Feature",
  "properties": {
    "iso:country":"DE",
    "sg:address":"Am Herrnberg 10",
    "sg:city":"Lappersdorf",
    "sg:phone":"+49 941/893000",
    "sg:postcode":"93138",
    "sg:province":"Bayern",
    "wof:name":"Bernd Wilfahrt",
    "wof:placetype":"venue"
},
  "geometry": {"coordinates":[12.090534,49.045815],"type":"Point"}
}