{
  "type": "Feature",
  "properties": {
    "iso:country":"DE",
    "sg:address":"Preintinger Str. 8",
    "sg:city":"Eging",
    "sg:phone":"+49 8544/8093",
    "sg:postcode":"94535",
    "sg:province":"Bayern",
    "wof:name":"Stieberitz Gmbh",
    "wof:placetype":"venue"
},
  "geometry": {"coordinates":[13.2781438828,48.7171173096],"type":"Point"}
}