{
  "type": "Feature",
  "properties": {
    "iso:country":"DE",
    "sg:address":"Johannes-Bieg-Str. 6",
    "sg:city":"Erligheim",
    "sg:phone":"+49 7143/883820",
    "sg:postcode":"74391",
    "sg:province":"Baden-W\u00fcrttemberg",
    "wof:name":"Vibro Block Ostertag Maschinen Vertriebs Gmbh",
    "wof:placetype":"venue"
},
  "geometry": {"coordinates":[9.092646,49.022633],"type":"Point"}
}