{
  "type": "Feature",
  "properties": {
    "iso:country":"DE",
    "sg:address":"Bahnhofstr. 19",
    "sg:city":"Brand-Erbisdorf",
    "sg:phone":"+49 37322/2283",
    "sg:postcode":"09618",
    "sg:province":"Sachsen",
    "wof:name":"Eiscafe",
    "wof:placetype":"venue"
},
  "geometry": {"coordinates":[13.325267,50.86948],"type":"Point"}
}