{
  "type": "Feature",
  "properties": {
    "iso:country":"DE",
    "sg:address":"K\u00f6hlerstr. 6",
    "sg:city":"Massenhausen",
    "sg:phone":"+49 8165/8516",
    "sg:postcode":"85376",
    "sg:province":"Bayern",
    "wof:name":"Ernst Flassak Fliesenlegermeister",
    "wof:placetype":"venue"
},
  "geometry": {"coordinates":[11.6316814423,48.3483009338],"type":"Point"}
}