{
  "type": "Feature",
  "properties": {
    "iso:country":"DE",
    "sg:address":"Obertor 19",
    "sg:city":"Wasungen",
    "sg:phone":"+49 36941/71331",
    "sg:postcode":"98634",
    "sg:province":"Th\u00fcringen",
    "wof:name":"Adolf Weibrecht",
    "wof:placetype":"venue"
},
  "geometry": {"coordinates":[10.368229,50.661816],"type":"Point"}
}