{
  "type": "Feature",
  "properties": {
    "iso:country":"DE",
    "sg:address":"Leesterstr. 50",
    "sg:city":"Weyhe",
    "sg:phone":"+49 421/895854",
    "sg:postcode":"28844",
    "sg:province":"Niedersachsen",
    "wof:name":"Commerzbank Ag",
    "wof:placetype":"venue"
},
  "geometry": {"coordinates":[8.834843,52.983372],"type":"Point"}
}