{
  "type": "Feature",
  "properties": {
    "iso:country":"DE",
    "sg:address":"Hauptstr. 61",
    "sg:city":"Altmittweida",
    "sg:phone":"+49 3727/3025",
    "sg:postcode":"09648",
    "sg:province":"Sachsen",
    "wof:name":"G\u00fcnter Wiedemann",
    "wof:placetype":"venue"
},
  "geometry": {"coordinates":[12.955624,50.967167],"type":"Point"}
}