{
  "type": "Feature",
  "properties": {
    "iso:country":"DE",
    "sg:address":"Gartenstr. 57",
    "sg:city":"Filderstadt",
    "sg:phone":"+49 711/704285",
    "sg:postcode":"70794",
    "sg:province":"Baden-W\u00fcrttemberg",
    "wof:name":"F. Und C. Trautwein",
    "wof:placetype":"venue"
},
  "geometry": {"coordinates":[9.220753,48.68187],"type":"Point"}
}