{
  "type": "Feature",
  "properties": {
    "iso:country":"DE",
    "sg:address":"Hellweg",
    "sg:city":"Unna",
    "sg:phone":"+49 2303/238495",
    "sg:postcode":"59423",
    "sg:province":"Nordrhein-Westfalen",
    "wof:name":"Klaus Herzog Industriebedarf Gmbh",
    "wof:placetype":"venue"
},
  "geometry": {"coordinates":[7.6981201172,51.5377998352],"type":"Point"}
}