{
  "type": "Feature",
  "properties": {
    "iso:country":"DE",
    "sg:address":"Pasteurstr. 36",
    "sg:city":"Berlin",
    "sg:phone":"+49 30/4250009",
    "sg:postcode":"10407",
    "sg:province":"Berlin",
    "wof:name":"Atax Treuhand-steuer- Beratungs Gmbh",
    "wof:placetype":"venue"
},
  "geometry": {"coordinates":[13.4362773895,52.5320701599],"type":"Point"}
}