{
  "type": "Feature",
  "properties": {
    "iso:country":"DE",
    "sg:address":"Am Schwanhof 34",
    "sg:city":"Marburg",
    "sg:phone":"+49 6421/26175",
    "sg:postcode":"35037",
    "sg:province":"Hessen",
    "wof:name":"Wolfgang Gabrian Kunstmaler",
    "wof:placetype":"venue"
},
  "geometry": {"coordinates":[8.75901,50.799366],"type":"Point"}
}