{
  "type": "Feature",
  "properties": {
    "iso:country":"DE",
    "sg:address":"K\u00e4the-Niederkirchner-Str. 22",
    "sg:city":"Zeitz",
    "sg:phone":"+49 3441/310259",
    "sg:postcode":"06712",
    "sg:province":"Sachsen-Anhalt",
    "wof:name":"Dr. Heinz Lorenz Tierarzt",
    "wof:placetype":"venue"
},
  "geometry": {"coordinates":[12.1436290741,51.0424995422],"type":"Point"}
}