{
  "type": "Feature",
  "properties": {
    "iso:country":"DE",
    "sg:address":"Peter-Henlein-Str. 30",
    "sg:city":"Bremen",
    "sg:phone":"+49 421/2070000",
    "sg:postcode":"28357",
    "sg:province":"Bremen",
    "wof:name":"Aug. Wilkens & Jahns Gmbh",
    "wof:placetype":"venue"
},
  "geometry": {"coordinates":[8.8931837082,53.1130332947],"type":"Point"}
}