{
  "type": "Feature",
  "properties": {
    "iso:country":"DE",
    "sg:address":"Claudiusstr. 21",
    "sg:city":"Walsrode",
    "sg:phone":"+49 5161/3798",
    "sg:postcode":"29664",
    "sg:province":"Niedersachsen",
    "wof:name":"Afw \u00c4rztebedarf Gmbh",
    "wof:placetype":"venue"
},
  "geometry": {"coordinates":[9.5744438171,52.8664894104],"type":"Point"}
}