{
  "type": "Feature",
  "properties": {
    "iso:country":"DE",
    "sg:address":"Fuldenriede 1",
    "sg:city":"Syke",
    "sg:phone":"+49 4248/366",
    "sg:postcode":"28857",
    "sg:province":"Niedersachsen",
    "wof:name":"Wilhelm Meyer",
    "wof:placetype":"venue"
},
  "geometry": {"coordinates":[8.848755,52.853397],"type":"Point"}
}