{
  "type": "Feature",
  "properties": {
    "iso:country":"DE",
    "sg:address":"Cuxhavener Str. 124",
    "sg:city":"Buxtehude",
    "sg:phone":"+49 4161/82575",
    "sg:postcode":"21614",
    "sg:province":"Niedersachsen",
    "wof:name":"Ev. Pfarramt St. Marien Neukloster",
    "wof:placetype":"venue"
},
  "geometry": {"coordinates":[9.6340694427,53.4823226929],"type":"Point"}
}