{
  "type": "Feature",
  "properties": {
    "iso:country":"DE",
    "sg:address":"Dorfstr. 42 b",
    "sg:city":"Tecklenburg",
    "sg:phone":"+49 5455/7155",
    "sg:postcode":"49545",
    "sg:province":"Nordrhein-Westfalen",
    "wof:name":"Rudolf Dodenh\u00f6ft Architekt",
    "wof:placetype":"venue"
},
  "geometry": {"coordinates":[7.750402,52.226048],"type":"Point"}
}