{
  "type": "Feature",
  "properties": {
    "iso:country":"DE",
    "sg:address":"Olenmoorweg 19",
    "sg:city":"Halstenbek",
    "sg:phone":"+49 4101/41223",
    "sg:postcode":"25469",
    "sg:province":"Schleswig-Holstein",
    "wof:name":"Beatrix Und Michael Jacobsen Rechtsanw\u00e4lte",
    "wof:placetype":"venue"
},
  "geometry": {"coordinates":[9.8235301971,53.6134986877],"type":"Point"}
}