{
  "type": "Feature",
  "properties": {
    "iso:country":"DE",
    "sg:address":"Otto-Hahn-Str. 5",
    "sg:city":"Eppingen",
    "sg:phone":"+49 4972/6291740",
    "sg:postcode":"75031",
    "sg:province":"Baden-W\u00fcrttemberg",
    "wof:name":"Hans Hagemann Gmbh",
    "wof:placetype":"venue"
},
  "geometry": {"coordinates":[8.9210128784,49.1357040405],"type":"Point"}
}