{
  "type": "Feature",
  "properties": {
    "iso:country":"DE",
    "sg:address":"Sch\u00e4ferweg 181",
    "sg:city":"B\u00fcnde",
    "sg:phone":"+49 5226/989813",
    "sg:postcode":"32257",
    "sg:province":"Nordrhein-Westfalen",
    "wof:name":"H. Dreyer",
    "wof:placetype":"venue"
},
  "geometry": {"coordinates":[8.483973,52.200718],"type":"Point"}
}