{
  "type": "Feature",
  "properties": {
    "iso:country":"DE",
    "sg:address":"Verler Str. 334",
    "sg:city":"G\u00fctersloh",
    "sg:phone":"+49 5241/46906",
    "sg:postcode":"33334",
    "sg:province":"Nordrhein-Westfalen",
    "wof:name":"A. Jost",
    "wof:placetype":"venue"
},
  "geometry": {"coordinates":[8.4106559753,51.9460525513],"type":"Point"}
}