{
  "type": "Feature",
  "properties": {
    "iso:country":"DE",
    "sg:address":"Bachstr. 15-20",
    "sg:city":"Borchen",
    "sg:phone":"+49 5251/38052",
    "sg:postcode":"33178",
    "sg:province":"Nordrhein-Westfalen",
    "wof:name":"Glas Sander Gmbh",
    "wof:placetype":"venue"
},
  "geometry": {"coordinates":[8.7301521301,51.6596488953],"type":"Point"}
}