{
  "type": "Feature",
  "properties": {
    "iso:country":"DE",
    "sg:address":"Bismarckstr. 13",
    "sg:city":"Diez",
    "sg:phone":"+49 6432/2640",
    "sg:postcode":"65582",
    "sg:province":"Rheinland-Pfalz",
    "wof:name":"Gastst\u00e4tte Die Zwiebel",
    "wof:placetype":"venue"
},
  "geometry": {"coordinates":[8.0168991089,50.3683547974],"type":"Point"}
}