{
  "type": "Feature",
  "properties": {
    "iso:country":"DE",
    "sg:address":"Peterstaler Str. 133",
    "sg:city":"Heidelberg",
    "sg:phone":"+49 6221/809057",
    "sg:postcode":"69118",
    "sg:province":"Baden-W\u00fcrttemberg",
    "wof:name":"J\u00fcrgen Heinlein",
    "wof:placetype":"venue"
},
  "geometry": {"coordinates":[8.7496385574,49.4274749756],"type":"Point"}
}