{
  "type": "Feature",
  "properties": {
    "iso:country":"DE",
    "sg:address":"Mollenbachstr. 23",
    "sg:city":"Leonberg",
    "sg:phone":"+49 7152/979960",
    "sg:postcode":"71229",
    "sg:province":"Baden-W\u00fcrttemberg",
    "wof:name":"Punkt Verlag Und Werbeagentur E. K.",
    "wof:placetype":"venue"
},
  "geometry": {"coordinates":[9.0010995865,48.784866333],"type":"Point"}
}