{
  "type": "Feature",
  "properties": {
    "iso:country":"DE",
    "sg:address":"Wiesenstr. 23",
    "sg:city":"Winnenden",
    "sg:phone":"+49 7195/174288",
    "sg:postcode":"71364",
    "sg:province":"Baden-W\u00fcrttemberg",
    "wof:name":"Josef Mayer",
    "wof:placetype":"venue"
},
  "geometry": {"coordinates":[9.403563,48.876518],"type":"Point"}
}