{
  "type": "Feature",
  "properties": {
    "iso:country":"DE",
    "sg:address":"Sch\u00e4ferberg 20",
    "sg:city":"Weferlingen",
    "sg:phone":"+49 39061/2547",
    "sg:postcode":"39356",
    "sg:province":"Sachsen-Anhalt",
    "wof:name":"Antje Heideck",
    "wof:placetype":"venue"
},
  "geometry": {"coordinates":[11.0633010864,52.3110160828],"type":"Point"}
}