{
  "type": "Feature",
  "properties": {
    "iso:country":"DE",
    "sg:address":"Oberbozen 8",
    "sg:city":"Ritten",
    "sg:phone":"+39 0347 569 3682",
    "sg:postcode":"39059",
    "wof:name":"Gashaus Lobishof",
    "wof:placetype":"venue"
},
  "geometry": {"coordinates":[11.4088726044,46.5293426514],"type":"Point"}
}