{
  "type": "Feature",
  "properties": {
    "iso:country":"DE",
    "sg:address":"Daimlerstr. 15",
    "sg:city":"M\u00f6ckm\u00fchl",
    "sg:phone":"+49 6298/7052",
    "sg:postcode":"74219",
    "sg:province":"Baden-W\u00fcrttemberg",
    "wof:name":"Autohaus F. Hau\u00dfecker Beteiligungs-gmbh",
    "wof:placetype":"venue"
},
  "geometry": {"coordinates":[9.363119,49.317825],"type":"Point"}
}