{
  "type": "Feature",
  "properties": {
    "iso:country":"DE",
    "sg:address":"Bauermannskulle 41",
    "sg:city":"Solingen",
    "sg:phone":"+49 212/3838000",
    "sg:postcode":"42657",
    "sg:province":"Nordrhein-Westfalen",
    "wof:name":"Planquadrat X Gmbh",
    "wof:placetype":"venue"
},
  "geometry": {"coordinates":[7.049478,51.148041],"type":"Point"}
}