{
  "type": "Feature",
  "properties": {
    "iso:country":"DE",
    "sg:address":"Adolf-Staperfeld-Str. 65a",
    "sg:city":"Osnabr\u00fcck",
    "sg:phone":"+49 541/596599",
    "sg:postcode":"49082",
    "sg:province":"Niedersachsen",
    "wof:name":"Ibv-immobilienvermittlungs- Gesellschaft Mbh",
    "wof:placetype":"venue"
},
  "geometry": {"coordinates":[8.0213956833,52.2444343567],"type":"Point"}
}