{
  "type": "Feature",
  "properties": {
    "iso:country":"DE",
    "sg:address":"Demminer Str. 42",
    "sg:city":"Jarmen",
    "sg:phone":"+49 39997/10283",
    "sg:postcode":"17126",
    "sg:province":"Mecklenburg-Vorpommern",
    "wof:name":"Hotel Zum Brunnen",
    "wof:placetype":"venue"
},
  "geometry": {"coordinates":[13.3323640823,53.923248291],"type":"Point"}
}