{
  "type": "Feature",
  "properties": {
    "iso:country":"DE",
    "sg:address":"Zum Zimmergrund 46",
    "sg:city":"Albrechts",
    "sg:postcode":"98529",
    "sg:province":"Th\u00fcringen",
    "wof:name":"Albrechtser Bau - Service E.k.",
    "wof:placetype":"venue"
},
  "geometry": {"coordinates":[10.642914,50.620564],"type":"Point"}
}