{
  "type": "Feature",
  "properties": {
    "iso:country":"DE",
    "sg:address":"Ro\u00dfmarkt 14",
    "sg:city":"Frankfurt",
    "sg:phone":"+49 69/92007201",
    "sg:postcode":"60311",
    "sg:province":"Hessen",
    "wof:name":"Pramex Ges. Zur F\u00f6rderung Von Aus-",
    "wof:placetype":"venue"
},
  "geometry": {"coordinates":[8.677072525,50.1121406555],"type":"Point"}
}