{
  "type": "Feature",
  "properties": {
    "iso:country":"DE",
    "sg:address":"Pl\u00f6ner Str. 18",
    "sg:city":"Ahrensb\u00f6k",
    "sg:postcode":"23623",
    "sg:province":"Schleswig-Holstein",
    "wof:name":"Deutsche Verm\u00f6gensberatung Ag J\u00f6rg Demsat",
    "wof:placetype":"venue"
},
  "geometry": {"coordinates":[10.5720796585,54.0162506104],"type":"Point"}
}