{
  "type": "Feature",
  "properties": {
    "iso:country":"DE",
    "sg:address":"Theodor-Heuss-Ring 23",
    "sg:city":"Bocholt",
    "sg:phone":"+49 2871/181222",
    "sg:postcode":"46395",
    "sg:province":"Nordrhein-Westfalen",
    "wof:name":"Phone-land",
    "wof:placetype":"venue"
},
  "geometry": {"coordinates":[6.6209611893,51.8355636597],"type":"Point"}
}