{
  "type": "Feature",
  "properties": {
    "iso:country":"DE",
    "sg:address":"Bonhoefferstr. 1",
    "sg:city":"Heidelberg",
    "sg:postcode":"69123",
    "sg:province":"Baden-W\u00fcrttemberg",
    "wof:name":"Hcg Consulting Group Ag",
    "wof:placetype":"venue"
},
  "geometry": {"coordinates":[8.6526699066,49.4127311707],"type":"Point"}
}