{
  "type": "Feature",
  "properties": {
    "iso:country":"DE",
    "sg:address":"Am Entenmoos 2",
    "sg:city":"Sonthofen",
    "sg:phone":"+49 8321/26327",
    "sg:postcode":"87527",
    "sg:province":"Bayern",
    "wof:name":"Stefanel",
    "wof:placetype":"venue"
},
  "geometry": {"coordinates":[10.275306,47.510098],"type":"Point"}
}