{
  "type": "Feature",
  "properties": {
    "iso:country":"DE",
    "sg:address":"Obere Gartenstr.3",
    "sg:city":"Sulzbach-Rosenheim",
    "sg:phone":"+49 9661",
    "sg:postcode":"92237",
    "sg:province":"Bayern",
    "wof:name":"Dw Haustechnik",
    "wof:placetype":"venue"
},
  "geometry": {"coordinates":[11.7469,49.503811],"type":"Point"}
}