{
  "type": "Feature",
  "properties": {
    "iso:country":"DE",
    "sg:address":"Auf dem Brauke 7",
    "sg:city":"Gleichen",
    "sg:phone":"+49 5508/8820",
    "sg:postcode":"37130",
    "sg:province":"Niedersachsen",
    "wof:name":"Atrader Kurier J\u00fcrgen T\u00f6lke",
    "wof:placetype":"venue"
},
  "geometry": {"coordinates":[10.0554046631,51.4738960266],"type":"Point"}
}