{
  "type": "Feature",
  "properties": {
    "iso:country":"DE",
    "sg:address":"Am Rheintor 5",
    "sg:city":"Krefeld",
    "sg:phone":"+49 2151/46341",
    "sg:postcode":"47829",
    "sg:province":"Nordrhein-Westfalen",
    "wof:name":"Johann Weyen",
    "wof:placetype":"venue"
},
  "geometry": {"coordinates":[6.6515469551,51.3540649414],"type":"Point"}
}