{
  "type": "Feature",
  "properties": {
    "iso:country":"DE",
    "sg:address":"Clinicumsgasse 10",
    "sg:city":"T\u00fcbingen",
    "sg:phone":"+49 7071/22910",
    "sg:postcode":"72070",
    "sg:province":"Baden-W\u00fcrttemberg",
    "wof:name":"Gottfried Sorgius",
    "wof:placetype":"venue"
},
  "geometry": {"coordinates":[9.054393,48.519444],"type":"Point"}
}