{
  "type": "Feature",
  "properties": {
    "iso:country":"DE",
    "sg:address":"Am Rathberg 2",
    "sg:city":"Winsen",
    "sg:postcode":"29308",
    "sg:province":"Niedersachsen",
    "wof:name":"Bds Bau-daten-service Gmbh",
    "wof:placetype":"venue"
},
  "geometry": {"coordinates":[9.9091672897,52.6800193787],"type":"Point"}
}