{
  "type": "Feature",
  "properties": {
    "iso:country":"DE",
    "sg:address":"Pferdebachstr. 27",
    "sg:city":"Witten",
    "sg:phone":"+49 2302/1750",
    "sg:postcode":"58455",
    "sg:province":"Nordrhein-Westfalen",
    "wof:name":"Evangelisches Krankenhaus",
    "wof:placetype":"venue"
},
  "geometry": {"coordinates":[7.34403,51.445019],"type":"Point"}
}