{
  "type": "Feature",
  "properties": {
    "iso:country":"DE",
    "sg:address":"Hauptstr. 44",
    "sg:city":"Altenstadt",
    "sg:phone":"+49 6047/96450",
    "sg:postcode":"63674",
    "sg:province":"Hessen",
    "wof:name":"Softkom Gmbh",
    "wof:placetype":"venue"
},
  "geometry": {"coordinates":[8.9403028488,50.2758255005],"type":"Point"}
}