{
  "type": "Feature",
  "properties": {
    "iso:country":"DE",
    "sg:address":"Weidenbornstr. 8a",
    "sg:city":"Wiesbaden",
    "sg:phone":"+49 611/79010",
    "sg:postcode":"65189",
    "sg:province":"Hessen",
    "wof:name":"Bsc B\u00fcroservice-enter Gmbh",
    "wof:placetype":"venue"
},
  "geometry": {"coordinates":[8.2559080124,50.0627861023],"type":"Point"}
}