{
  "type": "Feature",
  "properties": {
    "iso:country":"DE",
    "sg:address":"Weserm\u00fcnder Str.",
    "sg:city":"Bremerv\u00f6rde",
    "sg:phone":"+49 4761/3205",
    "sg:postcode":"27432",
    "sg:province":"Niedersachsen",
    "wof:name":"Hans Klaus Oetjen Bw-kaserne",
    "wof:placetype":"venue"
},
  "geometry": {"coordinates":[9.1367950439,53.4898757935],"type":"Point"}
}