{
  "type": "Feature",
  "properties": {
    "iso:country":"DE",
    "sg:address":"Schaumbergstr. 10",
    "sg:city":"Hof",
    "sg:phone":"+49 9281/738250",
    "sg:postcode":"95032",
    "sg:province":"Bayern",
    "wof:name":"Ulrike Kettern",
    "wof:placetype":"venue"
},
  "geometry": {"coordinates":[11.9200267792,50.2862358093],"type":"Point"}
}