{
  "type": "Feature",
  "properties": {
    "iso:country":"DE",
    "sg:city":"Tolk",
    "sg:phone":"+49 4622/503",
    "sg:postcode":"24894",
    "sg:province":"Schleswig-Holstein",
    "wof:name":"Richard Miklitz",
    "wof:placetype":"venue"
},
  "geometry": {"coordinates":[9.63955,54.579475],"type":"Point"}
}