{
  "type": "Feature",
  "properties": {
    "iso:country":"DE",
    "sg:address":"Industriestr. 1",
    "sg:city":"Marne",
    "sg:phone":"+49 4851/2226",
    "sg:postcode":"25709",
    "sg:province":"Schleswig-Holstein",
    "wof:name":"Autohaus Hagge Gmbh",
    "wof:placetype":"venue"
},
  "geometry": {"coordinates":[9.0163469315,53.9566345215],"type":"Point"}
}