{
  "type": "Feature",
  "properties": {
    "iso:country":"DE",
    "sg:address":"An der Lank 12",
    "sg:city":"D\u00fcsseldorf",
    "sg:phone":"+49 211/419141",
    "sg:postcode":"40472",
    "sg:province":"Nordrhein-Westfalen",
    "wof:name":"Herbert Schmitz",
    "wof:placetype":"venue"
},
  "geometry": {"coordinates":[6.79219,51.285889],"type":"Point"}
}