{
  "type": "Feature",
  "properties": {
    "iso:country":"DE",
    "sg:address":"Fuhsestr. 12",
    "sg:city":"Uetze",
    "sg:phone":"+49 5177/1346",
    "sg:postcode":"31311",
    "sg:province":"Niedersachsen",
    "wof:name":"Erich Hennigs",
    "wof:placetype":"venue"
},
  "geometry": {"coordinates":[10.180687,52.408417],"type":"Point"}
}