{
  "type": "Feature",
  "properties": {
    "iso:country":"DE",
    "sg:address":"Sanktjohanserstr. 84",
    "sg:city":"Bad Wiessee",
    "sg:phone":"+49 8022/85300",
    "sg:postcode":"83707",
    "sg:province":"Bayern",
    "wof:name":"Restaurant Arkadenhof",
    "wof:placetype":"venue"
},
  "geometry": {"coordinates":[11.7274494171,47.7016029358],"type":"Point"}
}