{
  "type": "Feature",
  "properties": {
    "iso:country":"DE",
    "sg:address":"Niederstr. 140",
    "sg:city":"Trier",
    "sg:phone":"+49 651/62943",
    "sg:postcode":"54293",
    "sg:province":"Rheinland-Pfalz",
    "wof:name":"Karl Eisenach",
    "wof:placetype":"venue"
},
  "geometry": {"coordinates":[6.686724,49.810467],"type":"Point"}
}