{
  "type": "Feature",
  "properties": {
    "iso:country":"DE",
    "sg:address":"Galileistr. 3",
    "sg:city":"Zwickau",
    "sg:phone":"+49 375/213331",
    "sg:postcode":"08056",
    "sg:province":"Sachsen",
    "wof:name":"Bernd Reimann",
    "wof:placetype":"venue"
},
  "geometry": {"coordinates":[12.475639,50.726624],"type":"Point"}
}