{
  "type": "Feature",
  "properties": {
    "iso:country":"DE",
    "sg:address":"Hauptstr. 10",
    "sg:city":"Sch\u00f6nau v d Walde",
    "sg:phone":"+49 36253/3160",
    "sg:postcode":"99894",
    "sg:province":"Th\u00fcringen",
    "wof:name":"Megalith Bausteinwerk Beteiligungen Gmbh",
    "wof:placetype":"venue"
},
  "geometry": {"coordinates":[10.639202,50.856255],"type":"Point"}
}