{
  "type": "Feature",
  "properties": {
    "iso:country":"DE",
    "sg:address":"Kirchberger Str. 15",
    "sg:city":"Immenstaad",
    "sg:phone":"+49 7545/6510",
    "sg:postcode":"88090",
    "sg:province":"Baden-W\u00fcrttemberg",
    "wof:name":"Cafe Museum Zum Puppenhaus",
    "wof:placetype":"venue"
},
  "geometry": {"coordinates":[9.350585,47.67308],"type":"Point"}
}