{
  "type": "Feature",
  "properties": {
    "iso:country":"DE",
    "sg:address":"Feldstr. 9",
    "sg:city":"Wachtendonk",
    "sg:phone":"+49 2836/7233",
    "sg:postcode":"47669",
    "sg:province":"Nordrhein-Westfalen",
    "wof:name":"Helmut Neffgen",
    "wof:placetype":"venue"
},
  "geometry": {"coordinates":[6.336289,51.408161],"type":"Point"}
}