{
  "type": "Feature",
  "properties": {
    "iso:country":"DE",
    "sg:address":"Reiterstr. 9",
    "sg:city":"Landau",
    "sg:phone":"+49 6341/4265",
    "sg:postcode":"76829",
    "sg:province":"Rheinland-Pfalz",
    "wof:name":"E. Stein",
    "wof:placetype":"venue"
},
  "geometry": {"coordinates":[8.112793,49.195065],"type":"Point"}
}