{
  "type": "Feature",
  "properties": {
    "iso:country":"DE",
    "sg:address":"Am Sulzbogen 20",
    "sg:city":"F\u00fcrstenfeldbruck",
    "sg:phone":"+49 8141/23171",
    "sg:postcode":"82256",
    "sg:province":"Bayern",
    "wof:name":"O. Blum",
    "wof:placetype":"venue"
},
  "geometry": {"coordinates":[11.229144,48.166729],"type":"Point"}
}