{
  "type": "Feature",
  "properties": {
    "iso:country":"DE",
    "sg:address":"Rul\u00e4nderallee 12",
    "sg:city":"Freiburg",
    "sg:phone":"+49 7664/400231",
    "sg:postcode":"79112",
    "sg:province":"Baden-W\u00fcrttemberg",
    "wof:name":"A. G\u00fcther & D. Wenger",
    "wof:placetype":"venue"
},
  "geometry": {"coordinates":[7.7100300789,48.0006484985],"type":"Point"}
}