{
  "type": "Feature",
  "properties": {
    "iso:country":"DE",
    "sg:address":"Eggenfeldener Str. 121",
    "sg:city":"M\u00fcnchen",
    "sg:phone":"+49 89/93938670",
    "sg:postcode":"81929",
    "sg:province":"Bayern",
    "wof:name":"Kronos Titan Gmbh & Co. Ohg",
    "wof:placetype":"venue"
},
  "geometry": {"coordinates":[11.645378,48.140072],"type":"Point"}
}