{
  "type": "Feature",
  "properties": {
    "iso:country":"DE",
    "sg:address":"K\u00f6nig-Karl-Str. 47",
    "sg:city":"Bad Wildbad",
    "sg:phone":"+49 7081/8550",
    "sg:postcode":"75323",
    "sg:province":"Baden-W\u00fcrttemberg",
    "wof:name":"I. Weser",
    "wof:placetype":"venue"
},
  "geometry": {"coordinates":[8.548683,48.751705],"type":"Point"}
}