{
  "type": "Feature",
  "properties": {
    "iso:country":"DE",
    "sg:address":"Am G\u00f6tzenberg 13",
    "sg:city":"Heidelberg",
    "sg:phone":"+49 6221/383813",
    "sg:postcode":"69126",
    "sg:province":"Baden-W\u00fcrttemberg",
    "wof:name":"Aral Ag",
    "wof:placetype":"venue"
},
  "geometry": {"coordinates":[8.7005968094,49.3706741333],"type":"Point"}
}