{
  "type": "Feature",
  "properties": {
    "iso:country":"DE",
    "sg:address":"Spiekweg 1",
    "sg:city":"Haren",
    "sg:phone":"+49 5932/4604",
    "sg:postcode":"49733",
    "sg:province":"Niedersachsen",
    "wof:name":"Hermann Specken",
    "wof:placetype":"venue"
},
  "geometry": {"coordinates":[7.245213,52.762814],"type":"Point"}
}