{
  "type": "Feature",
  "properties": {
    "iso:country":"DE",
    "sg:address":"Reetputt 6",
    "sg:city":"Hamburg",
    "sg:phone":"+49 40/7426753",
    "sg:postcode":"21129",
    "sg:province":"Hamburg",
    "wof:name":"Johannes Stehr",
    "wof:placetype":"venue"
},
  "geometry": {"coordinates":[9.8550052643,53.5362586975],"type":"Point"}
}