{
  "type": "Feature",
  "properties": {
    "iso:country":"DE",
    "sg:address":"Karlstr. 17",
    "sg:city":"Unna",
    "sg:postcode":"59427",
    "sg:province":"Nordrhein-Westfalen",
    "wof:name":"Medical Physio Point Gmbh",
    "wof:placetype":"venue"
},
  "geometry": {"coordinates":[7.650398,51.527939],"type":"Point"}
}