{
  "type": "Feature",
  "properties": {
    "iso:country":"DE",
    "sg:address":"Frankfurter Str. 26",
    "sg:city":"Ober-M\u00f6rlen",
    "sg:phone":"+49 6002/1615",
    "sg:postcode":"61239",
    "sg:province":"Hessen",
    "wof:name":"M. Nadler",
    "wof:placetype":"venue"
},
  "geometry": {"coordinates":[8.693258,50.374397],"type":"Point"}
}