{
  "type": "Feature",
  "properties": {
    "iso:country":"DE",
    "sg:address":"F\u00fcrstenk\u00e4mpe 3 A",
    "sg:city":"Ahaus",
    "sg:phone":"+49 2561/5483",
    "sg:postcode":"48683",
    "sg:province":"Nordrhein-Westfalen",
    "wof:name":"Hartwig Kriege",
    "wof:placetype":"venue"
},
  "geometry": {"coordinates":[7.0144371986,52.0905685425],"type":"Point"}
}