{
  "type": "Feature",
  "properties": {
    "iso:country":"DE",
    "sg:address":"Borstadels 34",
    "sg:city":"Kempten",
    "sg:phone":"+49 8370/558",
    "sg:postcode":"87439",
    "sg:province":"Bayern",
    "wof:name":"Fritz Haggenmiller",
    "wof:placetype":"venue"
},
  "geometry": {"coordinates":[10.249814,47.756721],"type":"Point"}
}