{
  "type": "Feature",
  "properties": {
    "iso:country":"DE",
    "sg:address":"Eppendorfer Str. 3",
    "sg:city":"Borstendorf",
    "sg:phone":"+49 37294/1492",
    "sg:postcode":"09579",
    "sg:province":"Sachsen",
    "wof:name":"Oehmes",
    "wof:placetype":"venue"
},
  "geometry": {"coordinates":[13.1874265671,50.770160675],"type":"Point"}
}