{
  "type": "Feature",
  "properties": {
    "iso:country":"DE",
    "sg:address":"Mittelstr. 4",
    "sg:city":"Sonnewalde",
    "sg:phone":"+49 35323/230",
    "sg:postcode":"03249",
    "sg:province":"Brandenburg",
    "wof:name":"Clemenz Hoffedank",
    "wof:placetype":"venue"
},
  "geometry": {"coordinates":[13.647319,51.695637],"type":"Point"}
}