{
  "type": "Feature",
  "properties": {
    "iso:country":"DE",
    "sg:address":"Bruchwiesenstr. 25",
    "sg:city":"Landstuhl",
    "sg:phone":"+49 6371/64552",
    "sg:postcode":"66849",
    "sg:province":"Rheinland-Pfalz",
    "wof:name":"Witalia Gmbh",
    "wof:placetype":"venue"
},
  "geometry": {"coordinates":[7.5684518814,49.41847229],"type":"Point"}
}