{
  "type": "Feature",
  "properties": {
    "iso:country":"DE",
    "sg:address":"Augsburger Str. 33-35",
    "sg:city":"Dachau",
    "sg:postcode":"85221",
    "sg:province":"Bayern",
    "wof:name":"Volksbank Raiffeisenbank Dachau Eg",
    "wof:placetype":"venue"
},
  "geometry": {"coordinates":[11.4319782257,48.2608566284],"type":"Point"}
}