{
  "type": "Feature",
  "properties": {
    "iso:country":"DE",
    "sg:address":"Kirchenplatz 4",
    "sg:city":"Leutershausen",
    "sg:phone":"+49 9823/213",
    "sg:postcode":"91578",
    "sg:province":"Bayern",
    "wof:name":"Anton Hermanutz Massagepraxis",
    "wof:placetype":"venue"
},
  "geometry": {"coordinates":[10.406684,49.299187],"type":"Point"}
}