{
  "type": "Feature",
  "properties": {
    "iso:country":"DE",
    "sg:address":"Auf dem Kampe 9",
    "sg:city":"Sundern",
    "sg:phone":"+49 2393/1318",
    "sg:postcode":"59846",
    "sg:province":"Nordrhein-Westfalen",
    "wof:name":"Mila Anstrichtechnik Gmbh",
    "wof:placetype":"venue"
},
  "geometry": {"coordinates":[7.958069,51.260952],"type":"Point"}
}