{
  "type": "Feature",
  "properties": {
    "iso:country":"DE",
    "sg:address":"Frankenstr. 40",
    "sg:city":"M\u00f6hrendorf",
    "sg:phone":"+49 9131/41965",
    "sg:postcode":"91096",
    "sg:province":"Bayern",
    "wof:name":"Erwin Sch\u00fctz Gmbh",
    "wof:placetype":"venue"
},
  "geometry": {"coordinates":[10.9969,49.63921],"type":"Point"}
}