{
  "type": "Feature",
  "properties": {
    "iso:country":"DE",
    "sg:address":"Westring 21b",
    "sg:city":"Pirmasens",
    "sg:phone":"+49 6331/228478",
    "sg:postcode":"66954",
    "sg:province":"Rheinland-Pfalz",
    "wof:name":"Mtcl1996",
    "wof:placetype":"venue"
},
  "geometry": {"coordinates":[7.558426,49.20562],"type":"Point"}
}