{
  "type": "Feature",
  "properties": {
    "iso:country":"DE",
    "sg:address":"Frankfurter Str. 107",
    "sg:city":"Dietzenbach",
    "sg:phone":"+49 6074/33644",
    "sg:postcode":"63128",
    "sg:province":"Hessen",
    "wof:name":"Heinz Stegmann",
    "wof:placetype":"venue"
},
  "geometry": {"coordinates":[8.772924,50.01685],"type":"Point"}
}