{
  "type": "Feature",
  "properties": {
    "iso:country":"DE",
    "sg:address":"Donnerschweer Str. 57",
    "sg:city":"Oldenburg",
    "sg:phone":"+49 441/885413",
    "sg:postcode":"26123",
    "sg:province":"Niedersachsen",
    "wof:name":"Grenzenlos Der Reiseladen",
    "wof:placetype":"venue"
},
  "geometry": {"coordinates":[8.2205495834,53.1472053528],"type":"Point"}
}