{
  "type": "Feature",
  "properties": {
    "iso:country":"DE",
    "sg:address":"Wilhelm-Leuschner-Str. 1",
    "sg:city":"Butzbach",
    "sg:phone":"+49 6033/2111",
    "sg:postcode":"35510",
    "sg:province":"Hessen",
    "wof:name":"Kluck Und Frisch Rechtsanw\u00e4lte Und Notare",
    "wof:placetype":"venue"
},
  "geometry": {"coordinates":[8.6729106903,50.4315605164],"type":"Point"}
}