{
  "type": "Feature",
  "properties": {
    "iso:country":"DE",
    "sg:address":"Gartenstr. 8",
    "sg:city":"Heckelberg",
    "sg:postcode":"16259",
    "sg:province":"Brandenburg",
    "wof:name":"Evangelisches Pfarramt",
    "wof:placetype":"venue"
},
  "geometry": {"coordinates":[13.8396129608,52.7401390076],"type":"Point"}
}