{
  "type": "Feature",
  "properties": {
    "iso:country":"DE",
    "sg:address":"Sch\u00f6ngeisinger Str. 27",
    "sg:city":"F\u00fcrstenfeldbruck",
    "sg:postcode":"82256",
    "sg:province":"Bayern",
    "wof:name":"X Page Dtp-service Gmbh",
    "wof:placetype":"venue"
},
  "geometry": {"coordinates":[11.2520656586,48.176574707],"type":"Point"}
}