{
  "type": "Feature",
  "properties": {
    "iso:country":"DE",
    "sg:address":"Lilienstr. 51",
    "sg:city":"Vaterstetten",
    "sg:phone":"+49 8106/1626",
    "sg:postcode":"85591",
    "sg:province":"Bayern",
    "wof:name":"Irene Blum Architektin",
    "wof:placetype":"venue"
},
  "geometry": {"coordinates":[11.770746,48.101807],"type":"Point"}
}