{
  "type": "Feature",
  "properties": {
    "iso:country":"DE",
    "sg:address":"Rosenstra\u00dfe 16",
    "sg:city":"Obernholz",
    "sg:phone":"+49 5832/98980",
    "sg:postcode":"29386",
    "sg:province":"Niedersachsen",
    "wof:name":"Kallweit-busreisen",
    "wof:placetype":"venue"
},
  "geometry": {"coordinates":[10.600548,52.747948],"type":"Point"}
}