{
  "type": "Feature",
  "properties": {
    "iso:country":"DE",
    "sg:address":"Gro\u00dfe Bleichen 19",
    "sg:city":"Hamburg",
    "sg:phone":"+49 40/3020701",
    "sg:postcode":"20354",
    "sg:province":"Hamburg",
    "wof:name":"Thalia-buchhandlung Erich K\u00f6nnecke Gmbh & Co.",
    "wof:placetype":"venue"
},
  "geometry": {"coordinates":[9.9897422791,53.5529098511],"type":"Point"}
}