{
  "type": "Feature",
  "properties": {
    "iso:country":"DE",
    "sg:address":"Schwanheimer Str. 140",
    "sg:city":"Bensheim",
    "sg:phone":"+49 6251/2350",
    "sg:postcode":"64625",
    "sg:province":"Hessen",
    "wof:name":"Peter Kuhn Gmbh",
    "wof:placetype":"venue"
},
  "geometry": {"coordinates":[8.594364,49.684002],"type":"Point"}
}