{
  "type": "Feature",
  "properties": {
    "iso:country":"DE",
    "sg:address":"M\u00fcllerstr. 9",
    "sg:city":"Aschaffenburg",
    "sg:phone":"+49 6021/20123",
    "sg:postcode":"63741",
    "sg:province":"Bayern",
    "wof:name":"Birgit Schwind Friseur-creativ Gmbh",
    "wof:placetype":"venue"
},
  "geometry": {"coordinates":[9.1349191666,49.9816246033],"type":"Point"}
}