{
  "type": "Feature",
  "properties": {
    "iso:country":"DE",
    "sg:address":"Clemensstr. 105",
    "sg:city":"M\u00fcnchen",
    "sg:phone":"+49 89/3088095",
    "sg:postcode":"80796",
    "sg:province":"Bayern",
    "wof:name":"Seidl Und Schuster Steuerberater Gmbh",
    "wof:placetype":"venue"
},
  "geometry": {"coordinates":[11.5680427551,48.1641426086],"type":"Point"}
}