{
  "type": "Feature",
  "properties": {
    "iso:country":"DE",
    "sg:address":"Augsburger Str. 14",
    "sg:city":"Aichach",
    "sg:phone":"+49 8251/89870",
    "sg:postcode":"86551",
    "sg:province":"Bayern",
    "wof:name":"Helmut Grimm Steuerberater",
    "wof:placetype":"venue"
},
  "geometry": {"coordinates":[11.1277093887,48.4554519653],"type":"Point"}
}