{
  "type": "Feature",
  "properties": {
    "iso:country":"DE",
    "sg:address":"Okerweg 17",
    "sg:city":"Kissenbr\u00fcck",
    "sg:phone":"+49 5337/1038",
    "sg:postcode":"38324",
    "sg:province":"Niedersachsen",
    "wof:name":"Gudrun Henschel Masseurin",
    "wof:placetype":"venue"
},
  "geometry": {"coordinates":[10.571249,52.113789],"type":"Point"}
}