{
  "type": "Feature",
  "properties": {
    "iso:country":"DE",
    "sg:address":"Biberacher Str. 5",
    "sg:city":"Ummendorf",
    "sg:phone":"+49 7351/24453",
    "sg:postcode":"88444",
    "sg:province":"Baden-W\u00fcrttemberg",
    "wof:name":"Kath. Pfarramt St. Johannes",
    "wof:placetype":"venue"
},
  "geometry": {"coordinates":[9.830537796,48.0625457764],"type":"Point"}
}