{
  "type": "Feature",
  "properties": {
    "iso:country":"DE",
    "sg:address":"B\u00e4derstr. 34",
    "sg:city":"Bad Bertrich",
    "sg:phone":"+49 2674/1626",
    "sg:postcode":"56864",
    "sg:province":"Rheinland-Pfalz",
    "wof:name":"Pizzeria Italia Altomonte",
    "wof:placetype":"venue"
},
  "geometry": {"coordinates":[7.036921978,50.0718688965],"type":"Point"}
}