{
  "type": "Feature",
  "properties": {
    "iso:country":"DE",
    "sg:address":"Steinergraben 53",
    "sg:city":"Werl",
    "sg:phone":"+49 2922/6755",
    "sg:postcode":"59457",
    "sg:province":"Nordrhein-Westfalen",
    "wof:name":"Dcv Druck Gmbh",
    "wof:placetype":"venue"
},
  "geometry": {"coordinates":[7.90501,51.54813],"type":"Point"}
}