{
  "type": "Feature",
  "properties": {
    "iso:country":"DE",
    "sg:address":"Am Wei\u00dfen Stein 7 c",
    "sg:city":"Wesel",
    "sg:phone":"+49 2803/1632",
    "sg:postcode":"46487",
    "sg:province":"Nordrhein-Westfalen",
    "wof:name":"Johannes Biesen",
    "wof:placetype":"venue"
},
  "geometry": {"coordinates":[6.585494,51.630962],"type":"Point"}
}