{
  "type": "Feature",
  "properties": {
    "iso:country":"DE",
    "sg:address":"Daisendorfer Str. 10",
    "sg:city":"Meersburg",
    "sg:phone":"+49 7251/770",
    "sg:postcode":"88709",
    "sg:province":"Baden-W\u00fcrttemberg",
    "wof:name":"Sparkasse Kraichgau Bruchsal-bretten-sinsheim",
    "wof:placetype":"venue"
},
  "geometry": {"coordinates":[8.601023,49.123772],"type":"Point"}
}