{
  "type": "Feature",
  "properties": {
    "iso:country":"DE",
    "sg:address":"Ziegenmarkt 11",
    "sg:city":"Parchim",
    "sg:phone":"+49 3871/81362",
    "sg:postcode":"19370",
    "sg:province":"Mecklenburg-Vorpommern",
    "wof:name":"Victoria Versicherung",
    "wof:placetype":"venue"
},
  "geometry": {"coordinates":[11.8478956223,53.4258842468],"type":"Point"}
}