{
  "type": "Feature",
  "properties": {
    "iso:country":"DE",
    "sg:address":"Julian-Marchlewski-Str. 58",
    "sg:city":"Leipzig",
    "sg:phone":"+49 341/2313731",
    "sg:postcode":"04347",
    "sg:province":"Sachsen",
    "wof:name":"M. Bock",
    "wof:placetype":"venue"
},
  "geometry": {"coordinates":[12.4271841049,51.3566207886],"type":"Point"}
}