{
  "type": "Feature",
  "properties": {
    "iso:country":"DE",
    "sg:address":"Amalienstra\u00dfe 6",
    "sg:city":"oldenburg",
    "sg:postcode":"26135",
    "sg:province":"Niedersachsen",
    "wof:name":"Wohnen Im Alter - Aktivr Lebenabend !",
    "wof:placetype":"venue"
},
  "geometry": {"coordinates":[8.219643,53.138885],"type":"Point"}
}