{
  "type": "Feature",
  "properties": {
    "iso:country":"DE",
    "sg:address":"Obere Haardt 2 a",
    "sg:city":"Langenaltheim",
    "sg:phone":"+49 9145/1634",
    "sg:postcode":"91799",
    "sg:province":"Bayern",
    "wof:name":"Gemeindeb\u00fccherei L. Opitsch",
    "wof:placetype":"venue"
},
  "geometry": {"coordinates":[10.948185,48.893536],"type":"Point"}
}