{
  "type": "Feature",
  "properties": {
    "iso:country":"DE",
    "sg:address":"Bieringer Str. 30",
    "sg:city":"Rottenburg",
    "sg:postcode":"72108",
    "sg:province":"Baden-W\u00fcrttemberg",
    "wof:name":"L\u00f6wensprudel Beteiligungsges. Mbh",
    "wof:placetype":"venue"
},
  "geometry": {"coordinates":[8.938245,48.475811],"type":"Point"}
}