{
  "type": "Feature",
  "properties": {
    "iso:country":"DE",
    "sg:address":"Nollenpad 68",
    "sg:city":"Gelsenkirchen",
    "sg:phone":"+49 209/32566",
    "sg:postcode":"45894",
    "sg:province":"Nordrhein-Westfalen",
    "wof:name":"Werner Terlunen",
    "wof:placetype":"venue"
},
  "geometry": {"coordinates":[7.0394902229,51.576713562],"type":"Point"}
}