{
  "type": "Feature",
  "properties": {
    "iso:country":"DE",
    "sg:address":"K\u00f6nigstr. 44",
    "sg:city":"Stuttgart",
    "sg:phone":"+49 711/228130",
    "sg:postcode":"70173",
    "sg:province":"Baden-W\u00fcrttemberg",
    "wof:name":"Schwarzw\u00e4lder Bote Gmbh & Co. Kg",
    "wof:placetype":"venue"
},
  "geometry": {"coordinates":[9.1763019562,48.7766304016],"type":"Point"}
}