{
  "type": "Feature",
  "properties": {
    "iso:country":"DE",
    "sg:address":"Sudstr. 19-21",
    "sg:city":"Saarbr\u00fccken",
    "sg:phone":"+49 6897/78548",
    "sg:postcode":"66125",
    "sg:province":"Saarland",
    "wof:name":"Geib & Schott",
    "wof:placetype":"venue"
},
  "geometry": {"coordinates":[7.0364809036,49.280330658],"type":"Point"}
}