{
  "type": "Feature",
  "properties": {
    "iso:country":"DE",
    "sg:address":"Lindenstr. 63",
    "sg:city":"Gundelfingen",
    "sg:phone":"+49 761/592040",
    "sg:postcode":"79194",
    "sg:province":"Baden-W\u00fcrttemberg",
    "wof:name":"Handelsvertretungen Lorenz Kimmig Marketing Agent.",
    "wof:placetype":"venue"
},
  "geometry": {"coordinates":[7.867661953,48.0480728149],"type":"Point"}
}