{
  "type": "Feature",
  "properties": {
    "iso:country":"DE",
    "sg:address":"Griesstr. 1",
    "sg:city":"Marktl",
    "sg:phone":"+49 8678/74890",
    "sg:postcode":"84533",
    "sg:province":"Bayern",
    "wof:name":"Obhainzinger Gmbh",
    "wof:placetype":"venue"
},
  "geometry": {"coordinates":[12.841840744,48.2512931824],"type":"Point"}
}