{
  "type": "Feature",
  "properties": {
    "iso:country":"DE",
    "sg:address":"Irlacher Str. 14",
    "sg:city":"Halfing",
    "sg:phone":"+49 8055/9260",
    "sg:postcode":"83128",
    "sg:province":"Bayern",
    "wof:name":"Huber Rohrleitungsbau Gmbh",
    "wof:placetype":"venue"
},
  "geometry": {"coordinates":[12.2745275497,47.949596405],"type":"Point"}
}