{
  "type": "Feature",
  "properties": {
    "iso:country":"DE",
    "sg:address":"Talstr. 7",
    "sg:city":"Singhofen",
    "sg:phone":"+49 2604/5783",
    "sg:postcode":"56379",
    "sg:province":"Rheinland-Pfalz",
    "wof:name":"B. Mollenhauer",
    "wof:placetype":"venue"
},
  "geometry": {"coordinates":[7.829405,50.273174],"type":"Point"}
}