{
  "type": "Feature",
  "properties": {
    "iso:country":"DE",
    "sg:address":"Frankfurter Str. 50",
    "sg:city":"Kelkheim",
    "sg:phone":"+49 6195/5469",
    "sg:postcode":"65779",
    "sg:province":"Hessen",
    "wof:name":"A. Pabst Ohg",
    "wof:placetype":"venue"
},
  "geometry": {"coordinates":[8.452426,50.133045],"type":"Point"}
}