{
  "type": "Feature",
  "properties": {
    "iso:country":"DE",
    "sg:address":"B\u00fcchel 7",
    "sg:city":"Tettnang",
    "sg:phone":"+49 7542/7692",
    "sg:postcode":"88069",
    "sg:province":"Baden-W\u00fcrttemberg",
    "wof:name":"Pension Karl B\u00fcsser",
    "wof:placetype":"venue"
},
  "geometry": {"coordinates":[9.6118774414,47.6710968018],"type":"Point"}
}