{
  "type": "Feature",
  "properties": {
    "iso:country":"DE",
    "sg:address":"Marktpl. 12",
    "sg:city":"Stuttgart",
    "sg:phone":"+49 711/1640900",
    "sg:postcode":"70173",
    "sg:province":"Baden-W\u00fcrttemberg",
    "wof:name":"Proverb Ohg",
    "wof:placetype":"venue"
},
  "geometry": {"coordinates":[9.178626,48.775517],"type":"Point"}
}