{
  "type": "Feature",
  "properties": {
    "iso:country":"DE",
    "sg:address":"K\u00f6lner Str. 9",
    "sg:city":"K\u00f6ln",
    "sg:phone":"+49 2234/77548",
    "sg:postcode":"50859",
    "sg:province":"Nordrhein-Westfalen",
    "wof:name":"Karl Engel",
    "wof:placetype":"venue"
},
  "geometry": {"coordinates":[6.8313369751,50.9461326599],"type":"Point"}
}