{
  "type": "Feature",
  "properties": {
    "iso:country":"DE",
    "sg:address":"Dorfstr. 9",
    "sg:city":"Dannewerk",
    "sg:phone":"+49 4621/818118",
    "sg:postcode":"24867",
    "sg:province":"Schleswig-Holstein",
    "wof:name":"Gr\u00f6bitz & Partner Gmbh",
    "wof:placetype":"venue"
},
  "geometry": {"coordinates":[9.513463974,54.4864044189],"type":"Point"}
}