{
  "type": "Feature",
  "properties": {
    "iso:country":"DE",
    "sg:address":"J\u00fcdenstr. 15",
    "sg:city":"Wei\u00dfenfels",
    "sg:phone":"+49 3443/303313",
    "sg:postcode":"06667",
    "sg:province":"Sachsen-Anhalt",
    "wof:name":"Otto Bauer",
    "wof:placetype":"venue"
},
  "geometry": {"coordinates":[11.9703102112,51.2012863159],"type":"Point"}
}