{
  "type": "Feature",
  "properties": {
    "iso:country":"DE",
    "sg:address":"Obere Dorfstr. 14",
    "sg:city":"Marktsteft",
    "sg:phone":"+49 9332/3795",
    "sg:postcode":"97342",
    "sg:province":"Bayern",
    "wof:name":"Hans Stumpf",
    "wof:placetype":"venue"
},
  "geometry": {"coordinates":[10.176811,49.697433],"type":"Point"}
}