{
  "type": "Feature",
  "properties": {
    "iso:country":"DE",
    "sg:address":"Hauptstr. 13",
    "sg:city":"Winterrieden",
    "sg:phone":"+49 8333/8498",
    "sg:postcode":"87785",
    "sg:province":"Bayern",
    "wof:name":"Raiffeisenbank Babenhausen-osterb., Eg",
    "wof:placetype":"venue"
},
  "geometry": {"coordinates":[10.226155,48.120605],"type":"Point"}
}