{
  "type": "Feature",
  "properties": {
    "iso:country":"DE",
    "sg:address":"Dompfaffweg 5a",
    "sg:city":"N\u00fcrnberg",
    "sg:phone":"+49 911/882201",
    "sg:postcode":"90455",
    "sg:province":"Bayern",
    "wof:name":"Meister Automaten \u00fcberzeugen",
    "wof:placetype":"venue"
},
  "geometry": {"coordinates":[11.071406,49.37748],"type":"Point"}
}