{
  "type": "Feature",
  "properties": {
    "iso:country":"DE",
    "sg:address":"Hinterm Berg 24",
    "sg:city":"Worpswede",
    "sg:phone":"+49 4792/1273",
    "sg:postcode":"27726",
    "sg:province":"Niedersachsen",
    "wof:name":"Bonners Garni",
    "wof:placetype":"venue"
},
  "geometry": {"coordinates":[8.9164924622,53.2104682922],"type":"Point"}
}