{
  "type": "Feature",
  "properties": {
    "iso:country":"DE",
    "sg:address":"Am Tief 10",
    "sg:city":"Jemgum",
    "sg:phone":"+49 4958/237",
    "sg:postcode":"26844",
    "sg:province":"Niedersachsen",
    "wof:name":"A. Bruhns",
    "wof:placetype":"venue"
},
  "geometry": {"coordinates":[7.280755043,53.3150482178],"type":"Point"}
}