{
  "type": "Feature",
  "properties": {
    "iso:country":"DE",
    "sg:address":"Schwarzer Weg",
    "sg:city":"Walbeck",
    "sg:phone":"+49 39061/2713",
    "sg:postcode":"39356",
    "sg:province":"Sachsen-Anhalt",
    "wof:name":"Sig Maschinenbau Gmbh",
    "wof:placetype":"venue"
},
  "geometry": {"coordinates":[11.05143,52.290966],"type":"Point"}
}