{
  "type": "Feature",
  "properties": {
    "iso:country":"DE",
    "sg:address":"Burgstr. 2",
    "sg:city":"Sankt Augustin",
    "sg:phone":"+49 2241/926973",
    "sg:postcode":"53757",
    "sg:province":"Nordrhein-Westfalen",
    "wof:name":"Axel Ranke",
    "wof:placetype":"venue"
},
  "geometry": {"coordinates":[7.1654071808,50.789981842],"type":"Point"}
}