{
  "type": "Feature",
  "properties": {
    "iso:country":"DE",
    "sg:address":"J\u00fclicher Str. 24",
    "sg:city":"Eschweiler",
    "sg:phone":"+49 2403/26391",
    "sg:postcode":"52249",
    "sg:province":"Nordrhein-Westfalen",
    "wof:name":"Bz Baufachbetrieb Gmbh",
    "wof:placetype":"venue"
},
  "geometry": {"coordinates":[6.267979,50.822491],"type":"Point"}
}