{
  "type": "Feature",
  "properties": {
    "iso:country":"DE",
    "sg:address":"Schorndorfer Str. 1",
    "sg:city":"G\u00f6ppingen",
    "sg:phone":"+49 7161/929550",
    "sg:postcode":"73035",
    "sg:province":"Baden-W\u00fcrttemberg",
    "wof:name":"K. Berg",
    "wof:placetype":"venue"
},
  "geometry": {"coordinates":[9.60896,48.716011],"type":"Point"}
}