{
  "type": "Feature",
  "properties": {
    "iso:country":"DE",
    "sg:address":"Marktplatz 8",
    "sg:city":"Kirchenlamitz",
    "sg:phone":"+49 9285/1579",
    "sg:postcode":"95158",
    "sg:province":"Bayern",
    "wof:name":"Arno Burger",
    "wof:placetype":"venue"
},
  "geometry": {"coordinates":[11.9501247406,50.1515045166],"type":"Point"}
}