{
  "type": "Feature",
  "properties": {
    "iso:country":"DE",
    "sg:address":"Lindenplatz 4",
    "sg:city":"Bad Wiessee",
    "sg:phone":"+49 8022/82874",
    "sg:postcode":"83707",
    "sg:province":"Bayern",
    "wof:name":"Friedl Mandl Inh. Margit R\u00f6sler",
    "wof:placetype":"venue"
},
  "geometry": {"coordinates":[11.725733,47.712223],"type":"Point"}
}