{
  "type": "Feature",
  "properties": {
    "iso:country":"DE",
    "sg:address":"Ittlinger Hauptstr. 62",
    "sg:city":"Straubing",
    "sg:phone":"+49 9421/61304",
    "sg:postcode":"94315",
    "sg:province":"Bayern",
    "wof:name":"Franz Hiendlmayer",
    "wof:placetype":"venue"
},
  "geometry": {"coordinates":[12.6388158798,48.8891220093],"type":"Point"}
}