{
  "type": "Feature",
  "properties": {
    "iso:country":"DE",
    "sg:address":"Ehinger Str. 65",
    "sg:city":"M\u00fcnsingen",
    "sg:postcode":"72525",
    "sg:province":"Baden-W\u00fcrttemberg",
    "wof:name":"G. Schenz",
    "wof:placetype":"venue"
},
  "geometry": {"coordinates":[9.541998,48.34153],"type":"Point"}
}