{
  "type": "Feature",
  "properties": {
    "iso:country":"DE",
    "sg:address":"B\u00e4ckerstr. 8",
    "sg:city":"Perleberg",
    "sg:phone":"+49 3876/612608",
    "sg:postcode":"19348",
    "sg:province":"Brandenburg",
    "wof:name":"Hans Heinrichsr\u00fcscher Rechtsanwalt",
    "wof:placetype":"venue"
},
  "geometry": {"coordinates":[11.8635692596,53.0757217407],"type":"Point"}
}