{
  "type": "Feature",
  "properties": {
    "iso:country":"DE",
    "sg:address":"Hohe Eiche 21",
    "sg:city":"Schwalmstadt",
    "sg:postcode":"34613",
    "sg:province":"Hessen",
    "wof:name":"Com Bautr\u00e4gerges. F\u00fcr Gewerbebauten Mbh & Co. Kg",
    "wof:placetype":"venue"
},
  "geometry": {"coordinates":[9.2599811554,50.9167480469],"type":"Point"}
}