{
  "type": "Feature",
  "properties": {
    "iso:country":"DE",
    "sg:address":"Auf der Beune 65",
    "sg:city":"M\u00fcnster",
    "sg:postcode":"64839",
    "sg:province":"Hessen",
    "wof:name":"Metallbaugesellschaft Schmidt Mbh",
    "wof:placetype":"venue"
},
  "geometry": {"coordinates":[8.8692779541,49.9277267456],"type":"Point"}
}