{
  "type": "Feature",
  "properties": {
    "iso:country":"DE",
    "sg:address":"B\u00fcchelk\u00fchner Str. 11",
    "sg:city":"Schwandorf",
    "sg:phone":"+49 9431/7330",
    "sg:postcode":"92421",
    "sg:province":"Bayern",
    "wof:name":"Langasthof-hotel Grabinger",
    "wof:placetype":"venue"
},
  "geometry": {"coordinates":[12.0834283829,49.2870941162],"type":"Point"}
}