{
  "type": "Feature",
  "properties": {
    "iso:country":"DE",
    "sg:address":"Niegripper Chaussee 25",
    "sg:city":"Burg",
    "sg:postcode":"39288",
    "sg:province":"Sachsen-Anhalt",
    "wof:name":"We Bau B\u00f6ttge Heimtextilien Gmbh",
    "wof:placetype":"venue"
},
  "geometry": {"coordinates":[11.8303279877,52.2742195129],"type":"Point"}
}