{
  "type": "Feature",
  "properties": {
    "iso:country":"DE",
    "sg:address":"Industriestr. 4",
    "sg:city":"H\u00f6sbach",
    "sg:phone":"+49 6021/58960",
    "sg:postcode":"63768",
    "sg:province":"Bayern",
    "wof:name":"Motoren-sauer Instandsetzungs Gmbh",
    "wof:placetype":"venue"
},
  "geometry": {"coordinates":[9.2220191956,50.007358551],"type":"Point"}
}