{
  "type": "Feature",
  "properties": {
    "iso:country":"DE",
    "sg:address":"Heinrichsallee 43",
    "sg:city":"Aachen",
    "sg:phone":"+49 241/408363",
    "sg:postcode":"52062",
    "sg:province":"Nordrhein-Westfalen",
    "wof:name":"Cycle Elmar Pitow",
    "wof:placetype":"venue"
},
  "geometry": {"coordinates":[6.094396,50.777187],"type":"Point"}
}