{
  "type": "Feature",
  "properties": {
    "iso:country":"DE",
    "sg:address":"Zum Bergwerk 5",
    "sg:city":"Frankfurt",
    "sg:phone":"+49 69/503226",
    "sg:postcode":"60437",
    "sg:province":"Hessen",
    "wof:name":"Hermann Cornel",
    "wof:placetype":"venue"
},
  "geometry": {"coordinates":[8.634565,50.189827],"type":"Point"}
}