{
  "type": "Feature",
  "properties": {
    "iso:country":"DE",
    "sg:address":"Akazienstr. 21",
    "sg:city":"Oberursel",
    "sg:phone":"+49 6171/72989",
    "sg:postcode":"61440",
    "sg:province":"Hessen",
    "wof:name":"Paul Gerecht",
    "wof:placetype":"venue"
},
  "geometry": {"coordinates":[8.581157,50.184803],"type":"Point"}
}