{
  "type": "Feature",
  "properties": {
    "iso:country":"DE",
    "sg:address":"Freiheitstr. 26",
    "sg:city":"Altena",
    "sg:phone":"+49 2352/22507",
    "sg:postcode":"58762",
    "sg:province":"Nordrhein-Westfalen",
    "wof:name":"Taverne Mythos",
    "wof:placetype":"venue"
},
  "geometry": {"coordinates":[7.6729078293,51.2928199768],"type":"Point"}
}