{
  "type": "Feature",
  "properties": {
    "iso:country":"DE",
    "sg:address":"Sonnenb\u00fchl 6",
    "sg:city":"Lauben",
    "sg:postcode":"87493",
    "sg:province":"Bayern",
    "wof:name":"Dvline Gmbh",
    "wof:placetype":"venue"
},
  "geometry": {"coordinates":[10.316163063,47.7765388489],"type":"Point"}
}