{
  "type": "Feature",
  "properties": {
    "iso:country":"DE",
    "sg:address":"Elsteraue",
    "sg:city":"Bad K\u00f6stritz",
    "sg:phone":"+49 36605/8890",
    "sg:postcode":"07586",
    "sg:province":"Th\u00fcringen",
    "wof:name":"Sch\u00e4fer",
    "wof:placetype":"venue"
},
  "geometry": {"coordinates":[12.02274,50.927914],"type":"Point"}
}