{
  "type": "Feature",
  "properties": {
    "iso:country":"DE",
    "sg:address":"Marschnerstr. 16",
    "sg:city":"D\u00fcsseldorf",
    "sg:phone":"+49 211/7185270",
    "sg:postcode":"40593",
    "sg:province":"Nordrhein-Westfalen",
    "wof:name":"Casa Trade Bauregie Gmbh",
    "wof:placetype":"venue"
},
  "geometry": {"coordinates":[6.8812432289,51.1558914185],"type":"Point"}
}