{
  "type": "Feature",
  "properties": {
    "iso:country":"DE",
    "sg:address":"Bopparder Str. 13",
    "sg:city":"Boppard",
    "sg:phone":"+49 6742/6260",
    "sg:postcode":"56154",
    "sg:province":"Rheinland-Pfalz",
    "wof:name":"Hotel Schwan",
    "wof:placetype":"venue"
},
  "geometry": {"coordinates":[7.6325340271,50.2065734863],"type":"Point"}
}