{
  "type": "Feature",
  "properties": {
    "iso:country":"DE",
    "sg:address":"Anton-Saefkow-Platz 14",
    "sg:city":"Berlin",
    "sg:postcode":"10369",
    "sg:province":"Berlin",
    "wof:name":"Stadtbezirksbibliothek Berlin-lichtenberg",
    "wof:placetype":"venue"
},
  "geometry": {"coordinates":[13.470541,52.530556],"type":"Point"}
}