{
  "type": "Feature",
  "properties": {
    "iso:country":"DE",
    "sg:address":"Birkerstr. 5",
    "sg:city":"M\u00fcnchen",
    "sg:postcode":"80636",
    "sg:province":"Bayern",
    "wof:name":"Synux Gmbh",
    "wof:placetype":"venue"
},
  "geometry": {"coordinates":[11.5417175293,48.1491851807],"type":"Point"}
}