{
  "type": "Feature",
  "properties": {
    "iso:country":"DE",
    "sg:address":"Ehinger Str. 28",
    "sg:city":"Schelklingen",
    "sg:phone":"+49 7394/2420",
    "sg:postcode":"89601",
    "sg:province":"Baden-W\u00fcrttemberg",
    "wof:name":"Cooper-standard Automotive Deutschland Gmbh",
    "wof:placetype":"venue"
},
  "geometry": {"coordinates":[9.7292232513,48.368560791],"type":"Point"}
}