{
  "type": "Feature",
  "properties": {
    "iso:country":"DE",
    "sg:address":"Sangerh\u00e4user Str. 1-3",
    "sg:city":"Lutherstadt Eisleben",
    "sg:postcode":"06295",
    "sg:province":"Sachsen-Anhalt",
    "wof:name":"Holzhandelskontor Sibir Ohg",
    "wof:placetype":"venue"
},
  "geometry": {"coordinates":[11.5680103302,51.5131797791],"type":"Point"}
}