{
  "type": "Feature",
  "properties": {
    "iso:country":"DE",
    "sg:address":"Am Markt 20",
    "sg:city":"Leutershausen",
    "sg:phone":"+49 9823/91199",
    "sg:postcode":"91578",
    "sg:province":"Bayern",
    "wof:name":"Friedrich Samhammer Inh. Helga Barth E. K.",
    "wof:placetype":"venue"
},
  "geometry": {"coordinates":[10.4093790054,49.2995300293],"type":"Point"}
}