{
  "type": "Feature",
  "properties": {
    "iso:country":"DE",
    "sg:address":"Am Heilbrunnen 136-138",
    "sg:city":"Reutlingen",
    "sg:phone":"+49 4971/2114940",
    "sg:postcode":"72766",
    "sg:province":"Baden-W\u00fcrttemberg",
    "wof:name":"Vita Gmbh",
    "wof:placetype":"venue"
},
  "geometry": {"coordinates":[9.222485,48.507633],"type":"Point"}
}