{
  "type": "Feature",
  "properties": {
    "iso:country":"DE",
    "sg:address":"Druselplatz 3",
    "sg:city":"Kassel",
    "sg:postcode":"34117",
    "sg:province":"Hessen",
    "wof:name":"Filia Hess Optic Gmbh",
    "wof:placetype":"venue"
},
  "geometry": {"coordinates":[9.5000190735,51.3162841797],"type":"Point"}
}