{
  "type": "Feature",
  "properties": {
    "iso:country":"DE",
    "sg:address":"Gro\u00dfe G\u00e4nseweide 12",
    "sg:city":"Winsen",
    "sg:phone":"+49 4171/61030",
    "sg:postcode":"21423",
    "sg:province":"Niedersachsen",
    "wof:name":"H. Beckerling U. R. Kaschwich",
    "wof:placetype":"venue"
},
  "geometry": {"coordinates":[10.2127017975,53.3614997864],"type":"Point"}
}