{
  "type": "Feature",
  "properties": {
    "iso:country":"DE",
    "sg:address":"Steinweg 28",
    "sg:city":"Rotenburg",
    "sg:phone":"+49 6623/2066",
    "sg:postcode":"36199",
    "sg:province":"Hessen",
    "wof:name":"Gerhard A. Albrecht Rechtsanwalt",
    "wof:placetype":"venue"
},
  "geometry": {"coordinates":[9.7308349609,50.9975509644],"type":"Point"}
}