{
  "type": "Feature",
  "properties": {
    "iso:country":"DE",
    "sg:address":"Altenburger Str. 59",
    "sg:city":"G\u00f6\u00dfnitz",
    "sg:phone":"+49 34493/21525",
    "sg:postcode":"04639",
    "sg:province":"Th\u00fcringen",
    "wof:name":"Lindner & Partner Gbr",
    "wof:placetype":"venue"
},
  "geometry": {"coordinates":[12.4339332581,50.8941230774],"type":"Point"}
}