{
  "type": "Feature",
  "properties": {
    "iso:country":"DE",
    "sg:address":"Uferstr. 28",
    "sg:city":"Langsur",
    "sg:phone":"+49 6501/12596",
    "sg:postcode":"54308",
    "sg:province":"Rheinland-Pfalz",
    "wof:name":"B. Marbach",
    "wof:placetype":"venue"
},
  "geometry": {"coordinates":[6.502056,49.751949],"type":"Point"}
}