{
  "type": "Feature",
  "properties": {
    "iso:country":"DE",
    "sg:address":"Sachsenstr. 15",
    "sg:city":"Wiesbaden",
    "sg:phone":"+49 6122/51314",
    "sg:postcode":"65205",
    "sg:province":"Hessen",
    "wof:name":"Carneval Und Brauchtumverein Nordenstadt 1975",
    "wof:placetype":"venue"
},
  "geometry": {"coordinates":[8.338353,50.067112],"type":"Point"}
}