{
  "type": "Feature",
  "properties": {
    "iso:country":"DE",
    "sg:address":"Gustavstr. 26",
    "sg:city":"L\u00fcdenscheid",
    "sg:phone":"+49 2351/41261",
    "sg:postcode":"58511",
    "sg:province":"Nordrhein-Westfalen",
    "wof:name":"Sema-men\u00fc-service Gmbh",
    "wof:placetype":"venue"
},
  "geometry": {"coordinates":[7.6524000168,51.2111053467],"type":"Point"}
}