{
  "type": "Feature",
  "properties": {
    "iso:country":"DE",
    "sg:address":"Max-Planck-Str. 49",
    "sg:city":"Meckenheim",
    "sg:phone":"+49 2225/92300",
    "sg:postcode":"53340",
    "sg:province":"Nordrhein-Westfalen",
    "wof:name":"Wolfgang Fehlberg",
    "wof:placetype":"venue"
},
  "geometry": {"coordinates":[7.048493,50.627899],"type":"Point"}
}