{
  "type": "Feature",
  "properties": {
    "iso:country":"DE",
    "sg:address":"Konstantinstr. 110",
    "sg:city":"Bonn",
    "sg:phone":"+49 228/84910",
    "sg:postcode":"53179",
    "sg:province":"Nordrhein-Westfalen",
    "wof:name":"Bundesforschungsanstalt F\u00fcr Naturschutz Und",
    "wof:placetype":"venue"
},
  "geometry": {"coordinates":[7.1759958267,50.675655365],"type":"Point"}
}