{
  "type": "Feature",
  "properties": {
    "iso:country":"DE",
    "sg:address":"Ehrenberger Str. 37",
    "sg:city":"Wuppertal",
    "sg:phone":"+49 202/6070291",
    "sg:postcode":"42389",
    "sg:province":"Nordrhein-Westfalen",
    "wof:name":"Horst Koch Gmbh",
    "wof:placetype":"venue"
},
  "geometry": {"coordinates":[7.255215,51.274315],"type":"Point"}
}