{
  "type": "Feature",
  "properties": {
    "iso:country":"DE",
    "sg:address":"Sanderrothstr. 15",
    "sg:city":"W\u00fcrzburg",
    "sg:phone":"+49 931/7840813",
    "sg:postcode":"97074",
    "sg:province":"Bayern",
    "wof:name":"R. Miekautsch Immobilienmakler",
    "wof:placetype":"venue"
},
  "geometry": {"coordinates":[9.9542245865,49.7770805359],"type":"Point"}
}