{
  "type": "Feature",
  "properties": {
    "iso:country":"DE",
    "sg:address":"Dillinger Str. 1",
    "sg:city":"H\u00f6chst\u00e4dt",
    "sg:phone":"+49 9074/4838",
    "sg:postcode":"89420",
    "sg:province":"Bayern",
    "wof:name":"Alfred Nerlinger",
    "wof:placetype":"venue"
},
  "geometry": {"coordinates":[10.566461,48.610867],"type":"Point"}
}