{
  "type": "Feature",
  "properties": {
    "iso:country":"DE",
    "sg:address":"Bergstr. 79",
    "sg:city":"B\u00f6tzingen",
    "sg:phone":"+49 7663/6523",
    "sg:postcode":"79268",
    "sg:province":"Baden-W\u00fcrttemberg",
    "wof:name":"Fritz Sommer",
    "wof:placetype":"venue"
},
  "geometry": {"coordinates":[7.712101,48.073898],"type":"Point"}
}