{
  "type": "Feature",
  "properties": {
    "iso:country":"DE",
    "sg:address":"Postfach 1101",
    "sg:city":"Ebermannstadt",
    "sg:phone":"+49 9194/794541",
    "sg:postcode":"91316",
    "sg:province":"Bayern",
    "wof:name":"Dampfbahn Fr\u00e4nkische Schweiz E.v.",
    "wof:placetype":"venue"
},
  "geometry": {"coordinates":[11.1859798431,49.7781791687],"type":"Point"}
}