{
  "type": "Feature",
  "properties": {
    "iso:country":"DE",
    "sg:address":"Olgastr. 9",
    "sg:city":"Weilheim",
    "sg:postcode":"73235",
    "sg:province":"Baden-W\u00fcrttemberg",
    "wof:name":"S. Schulz",
    "wof:placetype":"venue"
},
  "geometry": {"coordinates":[9.523968,48.623371],"type":"Point"}
}