{
  "type": "Feature",
  "properties": {
    "iso:country":"DE",
    "sg:address":"Bunsenstr. 2a",
    "sg:city":"Kiel",
    "sg:phone":"+49 431/717950",
    "sg:postcode":"24145",
    "sg:province":"Schleswig-Holstein",
    "wof:name":"Adolf Richter Stahl- Metall- Und",
    "wof:placetype":"venue"
},
  "geometry": {"coordinates":[10.1599559784,54.2761383057],"type":"Point"}
}