{
  "type": "Feature",
  "properties": {
    "iso:country":"DE",
    "sg:address":"Waxensteinstr. 5",
    "sg:city":"Starnberg",
    "sg:phone":"+49 8151/6715",
    "sg:postcode":"82319",
    "sg:province":"Bayern",
    "wof:name":"Eugen J. Kovacs Fotograf",
    "wof:placetype":"venue"
},
  "geometry": {"coordinates":[11.320684433,48.0078926086],"type":"Point"}
}