{
  "type": "Feature",
  "properties": {
    "iso:country":"DE",
    "sg:address":"Bahnhofstr. 9",
    "sg:city":"Kittlitz",
    "sg:postcode":"03222",
    "sg:province":"Brandenburg",
    "wof:name":"H & P Windkraft Verwaltungs Gmbh",
    "wof:placetype":"venue"
},
  "geometry": {"coordinates":[13.9409198761,51.8595085144],"type":"Point"}
}