{
  "type": "Feature",
  "properties": {
    "iso:country":"DE",
    "sg:address":"Forstenrieder Allee 70 -72",
    "sg:city":"M\u00fcnchen",
    "sg:phone":"+49 89/41149100",
    "sg:postcode":"81476",
    "sg:province":"Bayern",
    "wof:name":"Dis Deutscher Industrie Service Ag",
    "wof:placetype":"venue"
},
  "geometry": {"coordinates":[11.497922,48.095627],"type":"Point"}
}