{
  "type": "Feature",
  "properties": {
    "iso:country":"DE",
    "sg:address":"Am Stadtpark 8",
    "sg:city":"Kempten",
    "sg:phone":"+49 831/83532",
    "sg:postcode":"87435",
    "sg:province":"Bayern",
    "wof:name":"Johann B. Lederle Rechtsanwalt",
    "wof:placetype":"venue"
},
  "geometry": {"coordinates":[10.3107786179,47.7268829346],"type":"Point"}
}