{
  "type": "Feature",
  "properties": {
    "iso:country":"DE",
    "sg:address":"Stettiner Str. 11",
    "sg:city":"Syke",
    "sg:phone":"+49 4242/70653",
    "sg:postcode":"28857",
    "sg:province":"Niedersachsen",
    "wof:name":"Regber",
    "wof:placetype":"venue"
},
  "geometry": {"coordinates":[8.846658,52.952179],"type":"Point"}
}