{
  "type": "Feature",
  "properties": {
    "iso:country":"DE",
    "sg:address":"Pieskower Weg 54",
    "sg:city":"Berlin",
    "sg:phone":"+49 30/93491602",
    "sg:postcode":"10409",
    "sg:province":"Berlin",
    "wof:name":"Graviton Gmbh",
    "wof:placetype":"venue"
},
  "geometry": {"coordinates":[13.4472980499,52.5411071777],"type":"Point"}
}