{
  "type": "Feature",
  "properties": {
    "iso:country":"DE",
    "sg:address":"Herrengraben 12",
    "sg:city":"T\u00f6nning",
    "sg:phone":"+49 4861/387",
    "sg:postcode":"25832",
    "sg:province":"Schleswig-Holstein",
    "wof:name":"Bruno Wischnewski",
    "wof:placetype":"venue"
},
  "geometry": {"coordinates":[8.940565,54.315002],"type":"Point"}
}