{
  "type": "Feature",
  "properties": {
    "iso:country":"DE",
    "sg:address":"Billstr. 98",
    "sg:city":"Hamburg",
    "sg:phone":"+49 40/787431",
    "sg:postcode":"20539",
    "sg:province":"Hamburg",
    "wof:name":"Heinr. Hagendorf Nachf. Gmbh & Co.",
    "wof:placetype":"venue"
},
  "geometry": {"coordinates":[10.0458965302,53.5392951965],"type":"Point"}
}