{
  "type": "Feature",
  "properties": {
    "iso:country":"DE",
    "sg:address":"Albert-Koch-Str. 2",
    "sg:city":"Sch\u00f6nberg",
    "sg:phone":"+49 4344/1666",
    "sg:postcode":"24217",
    "sg:province":"Schleswig-Holstein",
    "wof:name":"Hartmut Keller",
    "wof:placetype":"venue"
},
  "geometry": {"coordinates":[10.3725557327,54.3943710327],"type":"Point"}
}