{
  "type": "Feature",
  "properties": {
    "iso:country":"DE",
    "sg:address":"Alte Bergstr. 145",
    "sg:city":"Landshut",
    "sg:phone":"+49 871/26243",
    "sg:postcode":"84028",
    "sg:province":"Bayern",
    "wof:name":"Discopub Landshut",
    "wof:placetype":"venue"
},
  "geometry": {"coordinates":[12.149258,48.531708],"type":"Point"}
}