{
  "type": "Feature",
  "properties": {
    "iso:country":"DE",
    "sg:address":"Justus-Liebig-Str. 9",
    "sg:city":"Bayreuth",
    "sg:phone":"+49 921/51630",
    "sg:postcode":"95447",
    "sg:province":"Bayern",
    "wof:name":"Dostler Kg",
    "wof:placetype":"venue"
},
  "geometry": {"coordinates":[11.5667552948,49.9318962097],"type":"Point"}
}