{
  "type": "Feature",
  "properties": {
    "iso:country":"DE",
    "sg:address":"Speyerer Str. 28",
    "sg:city":"Frankenthal",
    "sg:phone":"+49 6233/26890",
    "sg:postcode":"67227",
    "sg:province":"Rheinland-Pfalz",
    "wof:name":"Franz Ruf",
    "wof:placetype":"venue"
},
  "geometry": {"coordinates":[8.353709,49.533901],"type":"Point"}
}