{
  "type": "Feature",
  "properties": {
    "iso:country":"DE",
    "sg:address":"Burgwallstr. 23",
    "sg:city":"Panschwitz-Kuckau",
    "sg:phone":"+49 35796/96331",
    "sg:postcode":"01920",
    "sg:province":"Sachsen",
    "wof:name":"Cornelius Schramm",
    "wof:placetype":"venue"
},
  "geometry": {"coordinates":[14.1925010681,51.2174034119],"type":"Point"}
}