{
  "type": "Feature",
  "properties": {
    "iso:country":"DE",
    "sg:address":"Unterl\u00e4nder Str. 70",
    "sg:city":"Stuttgart",
    "sg:phone":"+49 711/8790318",
    "sg:postcode":"70435",
    "sg:province":"Baden-W\u00fcrttemberg",
    "wof:name":"A. Von Th\u00fclen Masseur",
    "wof:placetype":"venue"
},
  "geometry": {"coordinates":[9.168283,48.832455],"type":"Point"}
}