{
  "type": "Feature",
  "properties": {
    "iso:country":"DE",
    "sg:address":"Steinhoffstr. 5",
    "sg:city":"Gerbstedt",
    "sg:phone":"+49 34783/30477",
    "sg:postcode":"06347",
    "sg:province":"Sachsen-Anhalt",
    "wof:name":"Peter Bensing",
    "wof:placetype":"venue"
},
  "geometry": {"coordinates":[11.619685,51.626987],"type":"Point"}
}