{
  "type": "Feature",
  "properties": {
    "iso:country":"DE",
    "sg:address":"Triftstr. 1b",
    "sg:city":"Bad Marienberg",
    "sg:phone":"+49 2661/3830",
    "sg:postcode":"56470",
    "sg:province":"Rheinland-Pfalz",
    "wof:name":"Claudia Roth Krankengymnastin",
    "wof:placetype":"venue"
},
  "geometry": {"coordinates":[7.950378,50.652107],"type":"Point"}
}