{
  "type": "Feature",
  "properties": {
    "iso:country":"DE",
    "sg:address":"Ortsstr. 7",
    "sg:city":"Langenorla",
    "sg:phone":"+49 3647/422545",
    "sg:postcode":"07381",
    "sg:province":"Th\u00fcringen",
    "wof:name":"W. Und H. Lerner",
    "wof:placetype":"venue"
},
  "geometry": {"coordinates":[11.5727071762,50.7413482666],"type":"Point"}
}