{
  "type": "Feature",
  "properties": {
    "iso:country":"DE",
    "sg:address":"Stumpengasse 9",
    "sg:city":"Appenweier",
    "sg:phone":"+49 7805/5106",
    "sg:postcode":"77767",
    "sg:province":"Baden-W\u00fcrttemberg",
    "wof:name":"Restaurant Zum Guede Nochber",
    "wof:placetype":"venue"
},
  "geometry": {"coordinates":[7.981107235,48.5375137329],"type":"Point"}
}