{
  "type": "Feature",
  "properties": {
    "iso:country":"DE",
    "sg:address":"Lengfeldstr. 5",
    "sg:city":"R\u00fcsselsheim",
    "sg:phone":"+49 6142/72141",
    "sg:postcode":"65428",
    "sg:province":"Hessen",
    "wof:name":"Josef Solms",
    "wof:placetype":"venue"
},
  "geometry": {"coordinates":[8.3808689117,49.9601402283],"type":"Point"}
}