{
  "type": "Feature",
  "properties": {
    "iso:country":"DE",
    "sg:address":"Ensdorfer Str. 16",
    "sg:city":"Schwalbach",
    "sg:phone":"+49 6834/51492",
    "sg:postcode":"66773",
    "sg:province":"Saarland",
    "wof:name":"Redoute",
    "wof:placetype":"venue"
},
  "geometry": {"coordinates":[6.8083629608,49.3021125793],"type":"Point"}
}