{
  "type": "Feature",
  "properties": {
    "iso:country":"DE",
    "sg:address":"In den Bonng\u00e4rten 10",
    "sg:city":"Kirtorf",
    "sg:phone":"+49 6635/229",
    "sg:postcode":"36320",
    "sg:province":"Hessen",
    "wof:name":"Ernst Sprankel",
    "wof:placetype":"venue"
},
  "geometry": {"coordinates":[9.100316,50.767159],"type":"Point"}
}