{
  "type": "Feature",
  "properties": {
    "iso:country":"DE",
    "sg:address":"Julius-Wolff-Str. 1",
    "sg:city":"Hameln",
    "sg:phone":"+49 5151/22169",
    "sg:postcode":"31785",
    "sg:province":"Niedersachsen",
    "wof:name":"Renate Olbrich Und Hildegard Fichtner",
    "wof:placetype":"venue"
},
  "geometry": {"coordinates":[9.368315,52.101521],"type":"Point"}
}