{
  "type": "Feature",
  "properties": {
    "iso:country":"DE",
    "sg:address":"Kraillinger Weg 21",
    "sg:city":"Neuried",
    "sg:phone":"+49 89/753069",
    "sg:postcode":"82061",
    "sg:province":"Bayern",
    "wof:name":"Josef Huber Steuerberater",
    "wof:placetype":"venue"
},
  "geometry": {"coordinates":[11.459561348,48.0920410156],"type":"Point"}
}