{
  "type": "Feature",
  "properties": {
    "iso:country":"DE",
    "sg:address":"Oststr. 41",
    "sg:city":"M\u00f6nchengladbach",
    "sg:phone":"+49 2161/45203",
    "sg:postcode":"41065",
    "sg:province":"Nordrhein-Westfalen",
    "wof:name":"S. Smeets",
    "wof:placetype":"venue"
},
  "geometry": {"coordinates":[6.44848,51.189232],"type":"Point"}
}