{
  "type": "Feature",
  "properties": {
    "iso:country":"DE",
    "sg:address":"Denninger Str. 15",
    "sg:city":"M\u00fcnchen",
    "sg:postcode":"81679",
    "sg:province":"Bayern",
    "wof:name":"Virtual Chip Exchange Europe Gmbh",
    "wof:placetype":"venue"
},
  "geometry": {"coordinates":[11.615824,48.149055],"type":"Point"}
}