{
  "type": "Feature",
  "properties": {
    "iso:country":"DE",
    "sg:address":"Heegerstr. 20",
    "sg:city":"Velbert-Langenberg",
    "sg:phone":"+49 2052/604280",
    "sg:postcode":"42555",
    "sg:province":"Nordrhein-Westfalen",
    "wof:name":"Artfleur Hoffmann Gmbh",
    "wof:placetype":"venue"
},
  "geometry": {"coordinates":[7.104816,51.349648],"type":"Point"}
}