{
  "type": "Feature",
  "properties": {
    "iso:country":"DE",
    "sg:address":"Wilhelminenstr. 120",
    "sg:city":"Gelsenkirchen",
    "sg:postcode":"45881",
    "sg:province":"Nordrhein-Westfalen",
    "wof:name":"Gl\u00fcckauf Beteiligungs Gmbh",
    "wof:placetype":"venue"
},
  "geometry": {"coordinates":[7.076599,51.515633],"type":"Point"}
}