{
  "type": "Feature",
  "properties": {
    "iso:country":"DE",
    "sg:address":"Klostertor 7",
    "sg:city":"L\u00fcgde",
    "sg:phone":"+49 5283/1500",
    "sg:postcode":"32676",
    "sg:province":"Nordrhein-Westfalen",
    "wof:name":"Kachelofen- Und Luft- Heizungsbau Harald L\u00f6hr",
    "wof:placetype":"venue"
},
  "geometry": {"coordinates":[9.280805,51.882061],"type":"Point"}
}