{
  "type": "Feature",
  "properties": {
    "iso:country":"DE",
    "sg:address":"Irlham 10",
    "sg:city":"Triftern",
    "sg:phone":"+49 8562/2650",
    "sg:postcode":"84371",
    "sg:province":"Bayern",
    "wof:name":"Wema Hard- Und Software Gmbh",
    "wof:placetype":"venue"
},
  "geometry": {"coordinates":[12.9720201492,48.3861885071],"type":"Point"}
}