{
  "type": "Feature",
  "properties": {
    "iso:country":"DE",
    "sg:address":"Matth\u00e4userstr. 67",
    "sg:city":"B\u00fchlertal",
    "sg:phone":"+49 7223/971876",
    "sg:postcode":"77830",
    "sg:province":"Baden-W\u00fcrttemberg",
    "wof:name":"Peter Golle",
    "wof:placetype":"venue"
},
  "geometry": {"coordinates":[8.1709890366,48.6886863708],"type":"Point"}
}