{
  "type": "Feature",
  "properties": {
    "iso:country":"DE",
    "sg:address":"Niedersachsenstr. 50",
    "sg:city":"H\u00fcde",
    "sg:phone":"+49 5443/628",
    "sg:postcode":"49448",
    "sg:province":"Niedersachsen",
    "wof:name":"Hotel H\u00fcder Hof",
    "wof:placetype":"venue"
},
  "geometry": {"coordinates":[8.3583984375,52.4955406189],"type":"Point"}
}