{
  "type": "Feature",
  "properties": {
    "iso:country":"DE",
    "sg:address":"Blankenburger Str. 1",
    "sg:city":"Altenbrak",
    "sg:phone":"+49 39456/915",
    "sg:postcode":"38889",
    "sg:province":"Sachsen-Anhalt",
    "wof:name":"Restaurant Und Cafe Zur Bode",
    "wof:placetype":"venue"
},
  "geometry": {"coordinates":[10.9224309921,51.7417030334],"type":"Point"}
}