{
  "type": "Feature",
  "properties": {
    "iso:country":"DE",
    "sg:address":"Hans-Kudlich-Platz 5",
    "sg:city":"Bietigheim-Bissingen",
    "sg:phone":"+49 7142/6902",
    "sg:postcode":"74321",
    "sg:province":"Baden-W\u00fcrttemberg",
    "wof:name":"H. Rohn Immobilienmakler",
    "wof:placetype":"venue"
},
  "geometry": {"coordinates":[9.1492500305,48.94688797],"type":"Point"}
}