{
  "type": "Feature",
  "properties": {
    "iso:country":"DE",
    "sg:address":"Hauptstr. 55",
    "sg:city":"Friedeburg",
    "sg:phone":"+49 4465/8817",
    "sg:postcode":"26446",
    "sg:province":"Niedersachsen",
    "wof:name":"Pizzeria Harlekin",
    "wof:placetype":"venue"
},
  "geometry": {"coordinates":[7.861533165,53.4269180298],"type":"Point"}
}