{
  "type": "Feature",
  "properties": {
    "iso:country":"DE",
    "sg:address":"Jahnstr. 33",
    "sg:city":"Lage",
    "sg:phone":"+49 5232/951060",
    "sg:postcode":"32791",
    "sg:province":"Nordrhein-Westfalen",
    "wof:name":"Ingenieur-b\u00fcro Schlegel Gmbh",
    "wof:placetype":"venue"
},
  "geometry": {"coordinates":[8.7926187515,51.9949226379],"type":"Point"}
}