{
  "type": "Feature",
  "properties": {
    "iso:country":"DE",
    "sg:address":"Neue Grube",
    "sg:city":"Strauch",
    "sg:postcode":"01561",
    "sg:province":"Sachsen",
    "wof:name":"Skr Sand-kies-recycling Gmbh",
    "wof:placetype":"venue"
},
  "geometry": {"coordinates":[13.6318492889,51.2894973755],"type":"Point"}
}