{
  "type": "Feature",
  "properties": {
    "iso:country":"DE",
    "sg:address":"Lilienthaler Str. 40",
    "sg:city":"Ottersberg",
    "sg:phone":"+49 4293/7699",
    "sg:postcode":"28870",
    "sg:province":"Niedersachsen",
    "wof:name":"Raiffeisen- Warengenossenschaft Eg",
    "wof:placetype":"venue"
},
  "geometry": {"coordinates":[9.053272,53.125938],"type":"Point"}
}