{
  "type": "Feature",
  "properties": {
    "iso:country":"DE",
    "sg:address":"Zehntsteinweg 18",
    "sg:city":"Freiburg",
    "sg:phone":"+49 761/82331",
    "sg:postcode":"79110",
    "sg:province":"Baden-W\u00fcrttemberg",
    "wof:name":"Rainer Hoffmann",
    "wof:placetype":"venue"
},
  "geometry": {"coordinates":[7.8251948357,48.0047187805],"type":"Point"}
}