{
  "type": "Feature",
  "properties": {
    "iso:country":"DE",
    "sg:address":"Carl-Benz-Str. 6",
    "sg:city":"Hemsbach",
    "sg:phone":"+49 6201/49830",
    "sg:postcode":"69502",
    "sg:province":"Baden-W\u00fcrttemberg",
    "wof:name":"Wolfgang Maiwald & El. K\u00f6belin",
    "wof:placetype":"venue"
},
  "geometry": {"coordinates":[8.6469135284,49.5852203369],"type":"Point"}
}