{
  "type": "Feature",
  "properties": {
    "iso:country":"DE",
    "sg:address":"Harzweg 19",
    "sg:city":"Quedlinburg",
    "sg:phone":"+49 3946/701128",
    "sg:postcode":"06484",
    "sg:province":"Sachsen-Anhalt",
    "wof:name":"Aral-center Andreas Siebold",
    "wof:placetype":"venue"
},
  "geometry": {"coordinates":[11.1457710266,51.7825775146],"type":"Point"}
}