{
  "type": "Feature",
  "properties": {
    "iso:country":"DE",
    "sg:address":"Demianiplatz 27/28",
    "sg:city":"Goerlitz",
    "sg:phone":"+49 3581/66655",
    "sg:postcode":"02826",
    "sg:province":"Sachsen",
    "wof:name":"Global Language Training",
    "wof:placetype":"venue"
},
  "geometry": {"coordinates":[14.985847,51.15324],"type":"Point"}
}