{
  "type": "Feature",
  "properties": {
    "iso:country":"DE",
    "sg:address":"Ostpreu\u00dfenstr. 6",
    "sg:city":"Usingen",
    "sg:phone":"+49 6081/2458",
    "sg:postcode":"61250",
    "sg:province":"Hessen",
    "wof:name":"W. Baumgartl Gmbh",
    "wof:placetype":"venue"
},
  "geometry": {"coordinates":[8.5333070755,50.3302612305],"type":"Point"}
}