{
  "type": "Feature",
  "properties": {
    "iso:country":"DE",
    "sg:address":"L\u00f6cknitzer Str. 22",
    "sg:city":"Boock",
    "sg:phone":"+49 39754/20888",
    "sg:postcode":"17322",
    "sg:province":"Mecklenburg-Vorpommern",
    "wof:name":"R. Gerhard",
    "wof:placetype":"venue"
},
  "geometry": {"coordinates":[14.240247,53.48782],"type":"Point"}
}