{
  "type": "Feature",
  "properties": {
    "iso:country":"DE",
    "sg:address":"H\u00e4nflingstr. 21 - 23",
    "sg:city":"M\u00fclheim",
    "sg:phone":"+49 208/431711",
    "sg:postcode":"45472",
    "sg:province":"Nordrhein-Westfalen",
    "wof:name":"M\u00fclheimer Asphalt Gmbh",
    "wof:placetype":"venue"
},
  "geometry": {"coordinates":[6.9177670479,51.4399528503],"type":"Point"}
}