{
  "type": "Feature",
  "properties": {
    "iso:country":"DE",
    "sg:address":"Obere Dorfstr. 21",
    "sg:city":"Lottstetten",
    "sg:phone":"+49 7745/5492",
    "sg:postcode":"79807",
    "sg:province":"Baden-W\u00fcrttemberg",
    "wof:name":"Friedrich Clau\u00df",
    "wof:placetype":"venue"
},
  "geometry": {"coordinates":[8.5759353638,47.6071662903],"type":"Point"}
}