{
  "type": "Feature",
  "properties": {
    "iso:country":"DE",
    "sg:address":"K\u00f6lner Str. 60",
    "sg:city":"Mechernich",
    "sg:phone":"+49 2443/5440",
    "sg:postcode":"53894",
    "sg:province":"Nordrhein-Westfalen",
    "wof:name":"E. Quasten",
    "wof:placetype":"venue"
},
  "geometry": {"coordinates":[6.648754,50.61306],"type":"Point"}
}