{
  "type": "Feature",
  "properties": {
    "iso:country":"DE",
    "sg:address":"Stroher Damm 7",
    "sg:city":"Vechta",
    "sg:phone":"+49 4447/783",
    "sg:postcode":"49377",
    "sg:province":"Niedersachsen",
    "wof:name":"Heinrich M\u00e4hlmann",
    "wof:placetype":"venue"
},
  "geometry": {"coordinates":[8.217794,52.779602],"type":"Point"}
}