{
  "type": "Feature",
  "properties": {
    "iso:country":"DE",
    "sg:address":"Siemensstr. 10",
    "sg:city":"Schwalmtal",
    "sg:phone":"+49 2163/923050",
    "sg:postcode":"41366",
    "sg:province":"Nordrhein-Westfalen",
    "wof:name":"Uri Arnon",
    "wof:placetype":"venue"
},
  "geometry": {"coordinates":[6.2487869263,51.2384338379],"type":"Point"}
}