{
  "type": "Feature",
  "properties": {
    "iso:country":"DE",
    "sg:address":"Bahnhofstr. 13",
    "sg:city":"S\u00f6rup",
    "sg:postcode":"24966",
    "sg:province":"Schleswig-Holstein",
    "wof:name":"Webincubators Gmbh",
    "wof:placetype":"venue"
},
  "geometry": {"coordinates":[9.67152,54.717518],"type":"Point"}
}