{
  "type": "Feature",
  "properties": {
    "iso:country":"DE",
    "sg:address":"Villastr. 8",
    "sg:city":"Stuttgart",
    "sg:phone":"+49 711/2868455",
    "sg:postcode":"70190",
    "sg:province":"Baden-W\u00fcrttemberg",
    "wof:name":"R. Krause Gmbh",
    "wof:placetype":"venue"
},
  "geometry": {"coordinates":[9.202734,48.794373],"type":"Point"}
}