{
  "type": "Feature",
  "properties": {
    "iso:country":"DE",
    "sg:address":"Hauptstr. 24",
    "sg:city":"Heusenstamm",
    "sg:phone":"+49 6106/5311",
    "sg:postcode":"63150",
    "sg:province":"Hessen",
    "wof:name":"Oswald Graf",
    "wof:placetype":"venue"
},
  "geometry": {"coordinates":[8.8519220352,50.045173645],"type":"Point"}
}