{
  "type": "Feature",
  "properties": {
    "iso:country":"DE",
    "sg:address":"Bayerwaldring 11",
    "sg:city":"Landau",
    "sg:phone":"+49 9951/90130",
    "sg:postcode":"94405",
    "sg:province":"Bayern",
    "wof:name":"Spyros Papadopoulos Ingenieur",
    "wof:placetype":"venue"
},
  "geometry": {"coordinates":[12.7049608231,48.6640968323],"type":"Point"}
}