{
  "type": "Feature",
  "properties": {
    "iso:country":"DE",
    "sg:address":"\u00dcberkinger Weg 6",
    "sg:city":"Leonberg",
    "sg:phone":"+49 7152/44701",
    "sg:postcode":"71229",
    "sg:province":"Baden-W\u00fcrttemberg",
    "wof:name":"Schott Gmbh",
    "wof:placetype":"venue"
},
  "geometry": {"coordinates":[8.995822,48.790024],"type":"Point"}
}