{
  "type": "Feature",
  "properties": {
    "iso:country":"DE",
    "sg:address":"Berthelsdorfer Weg 11",
    "sg:city":"Dresden",
    "sg:phone":"+49 351/2517562",
    "sg:postcode":"01279",
    "sg:province":"Sachsen",
    "wof:name":"Michael Jochim",
    "wof:placetype":"venue"
},
  "geometry": {"coordinates":[13.8112869263,51.0311775208],"type":"Point"}
}