{
  "type": "Feature",
  "properties": {
    "iso:country":"DE",
    "sg:address":"Dorfstr. 3",
    "sg:city":"Penkow",
    "sg:postcode":"17213",
    "sg:province":"Mecklenburg-Vorpommern",
    "wof:name":"Agrar - Gmbh",
    "wof:placetype":"venue"
},
  "geometry": {"coordinates":[12.478397,53.461872],"type":"Point"}
}