{
  "type": "Feature",
  "properties": {
    "iso:country":"DE",
    "sg:address":"Str\u00fcmpfelbacher Str. 29",
    "sg:city":"Weinstadt",
    "sg:phone":"+49 7151/609005",
    "sg:postcode":"71384",
    "sg:province":"Baden-W\u00fcrttemberg",
    "wof:name":"Spiesssche-apotheke",
    "wof:placetype":"venue"
},
  "geometry": {"coordinates":[9.364911,48.812374],"type":"Point"}
}