{
  "type": "Feature",
  "properties": {
    "iso:country":"DE",
    "sg:address":"Wernarzer Str. 62",
    "sg:city":"Bad Br\u00fcckenau",
    "sg:phone":"+49 9741/2160",
    "sg:postcode":"97769",
    "sg:province":"Bayern",
    "wof:name":"Kath. Pfarramt St. Josef Br\u00e4utigam Mariens",
    "wof:placetype":"venue"
},
  "geometry": {"coordinates":[9.7875852585,50.3092041016],"type":"Point"}
}