{
  "type": "Feature",
  "properties": {
    "iso:country":"DE",
    "sg:address":"Wesenberger Chaussee",
    "sg:city":"Mirow",
    "sg:postcode":"17252",
    "sg:province":"Mecklenburg-Vorpommern",
    "wof:name":"Aldi Gmbh & Co. Kg",
    "wof:placetype":"venue"
},
  "geometry": {"coordinates":[12.8212985992,53.2727394104],"type":"Point"}
}