{
  "type": "Feature",
  "properties": {
    "iso:country":"DE",
    "sg:address":"Forestastr. 13",
    "sg:city":"Wuppertal",
    "sg:phone":"+49 202/621900",
    "sg:postcode":"42289",
    "sg:province":"Nordrhein-Westfalen",
    "wof:name":"Joachim Heber Ingenieur",
    "wof:placetype":"venue"
},
  "geometry": {"coordinates":[7.2178602219,51.2632675171],"type":"Point"}
}