{
  "type": "Feature",
  "properties": {
    "iso:country":"DE",
    "sg:address":"Rosa-Luxemburg-Str. 8",
    "sg:city":"Tangerh\u00fctte",
    "sg:phone":"+49 3935/28213",
    "sg:postcode":"39517",
    "sg:province":"Sachsen-Anhalt",
    "wof:name":"Renate Wiebach",
    "wof:placetype":"venue"
},
  "geometry": {"coordinates":[11.804771,52.434708],"type":"Point"}
}