{
  "type": "Feature",
  "properties": {
    "iso:country":"DE",
    "sg:address":"Bielweg 23",
    "sg:city":"Idar-Oberstein",
    "sg:phone":"+49 6781/44321",
    "sg:postcode":"55743",
    "sg:province":"Rheinland-Pfalz",
    "wof:name":"Irene Br\u00e4cher",
    "wof:placetype":"venue"
},
  "geometry": {"coordinates":[7.2865891457,49.7116470337],"type":"Point"}
}