{
  "type": "Feature",
  "properties": {
    "iso:country":"DE",
    "sg:address":"Auberlenstr. 12",
    "sg:city":"Fellbach",
    "sg:phone":"+49 711/589455",
    "sg:postcode":"70736",
    "sg:province":"Baden-W\u00fcrttemberg",
    "wof:name":"Franz Eisgruber Gmbh & Co. Kg",
    "wof:placetype":"venue"
},
  "geometry": {"coordinates":[9.267457962,48.8175163269],"type":"Point"}
}