{
  "type": "Feature",
  "properties": {
    "iso:country":"DE",
    "sg:address":"Hackenheimer Str. 21",
    "sg:city":"Bad Kreuznach",
    "sg:phone":"+49 671/62157",
    "sg:postcode":"55545",
    "sg:province":"Rheinland-Pfalz",
    "wof:name":"Klaus Mees",
    "wof:placetype":"venue"
},
  "geometry": {"coordinates":[7.9143967628,49.8437232971],"type":"Point"}
}