{
  "type": "Feature",
  "properties": {
    "iso:country":"DE",
    "sg:address":"Schweizerstr. 56",
    "sg:city":"Sennfeld",
    "sg:phone":"+49 9721/68006",
    "sg:postcode":"97526",
    "sg:province":"Bayern",
    "wof:name":"Alfred Bandorf",
    "wof:placetype":"venue"
},
  "geometry": {"coordinates":[10.2573099136,50.0432395935],"type":"Point"}
}