{
  "type": "Feature",
  "properties": {
    "iso:country":"DE",
    "sg:address":"Industriestr. 21",
    "sg:city":"M\u00fclheim-K\u00e4rlich",
    "sg:phone":"+49 261/2022",
    "sg:postcode":"56218",
    "sg:province":"Rheinland-Pfalz",
    "wof:name":"Alno-einbauk\u00fcchen G. S\u00e4nger",
    "wof:placetype":"venue"
},
  "geometry": {"coordinates":[7.526766777,50.3950881958],"type":"Point"}
}