{
  "type": "Feature",
  "properties": {
    "iso:country":"DE",
    "sg:address":"Soestweg 18",
    "sg:city":"Welver",
    "sg:phone":"+49 2921/60632",
    "sg:postcode":"59514",
    "sg:province":"Nordrhein-Westfalen",
    "wof:name":"H. Antepoth",
    "wof:placetype":"venue"
},
  "geometry": {"coordinates":[8.034202,51.581295],"type":"Point"}
}