{
  "type": "Feature",
  "properties": {
    "iso:country":"DE",
    "sg:address":"Schreinerstr. 1",
    "sg:city":"Pf\u00f6rring",
    "sg:phone":"+49 8403/92790",
    "sg:postcode":"85104",
    "sg:province":"Bayern",
    "wof:name":"Leo Weese Gmbh",
    "wof:placetype":"venue"
},
  "geometry": {"coordinates":[11.692653,48.815563],"type":"Point"}
}