{
  "type": "Feature",
  "properties": {
    "iso:country":"DE",
    "sg:address":"Torstr. 1",
    "sg:city":"T\u00fcbingen",
    "sg:phone":"+49 7071/791369",
    "sg:postcode":"72070",
    "sg:province":"Baden-W\u00fcrttemberg",
    "wof:name":"Adolf Schnitzler",
    "wof:placetype":"venue"
},
  "geometry": {"coordinates":[9.000431,48.501205],"type":"Point"}
}