{
  "type": "Feature",
  "properties": {
    "iso:country":"DE",
    "sg:address":"Br\u00fcckener Str. 4",
    "sg:city":"Birkenfeld",
    "sg:phone":"+49 6782/2524",
    "sg:postcode":"55765",
    "sg:province":"Rheinland-Pfalz",
    "wof:name":"M\u00f6bel Decker",
    "wof:placetype":"venue"
},
  "geometry": {"coordinates":[7.159365,49.648335],"type":"Point"}
}