{
  "type": "Feature",
  "properties": {
    "iso:country":"DE",
    "sg:address":"Hornstr. 5",
    "sg:city":"Ebstorf",
    "sg:phone":"+49 5822/1295",
    "sg:postcode":"29574",
    "sg:province":"Niedersachsen",
    "wof:name":"Albert Dierksen",
    "wof:placetype":"venue"
},
  "geometry": {"coordinates":[10.4166927338,53.0296173096],"type":"Point"}
}