{
  "type": "Feature",
  "properties": {
    "iso:country":"DE",
    "sg:address":"Gro\u00dfe Str. 8",
    "sg:city":"F\u00fcrstenau",
    "sg:phone":"+49 5901/3502",
    "sg:postcode":"49584",
    "sg:province":"Niedersachsen",
    "wof:name":"Hotel A. Wilken",
    "wof:placetype":"venue"
},
  "geometry": {"coordinates":[7.6754188538,52.5167312622],"type":"Point"}
}