{
  "type": "Feature",
  "properties": {
    "iso:country":"DE",
    "sg:address":"Meiling 5",
    "sg:city":"Rott",
    "sg:postcode":"83543",
    "sg:province":"Bayern",
    "wof:name":"J.g. Grundst\u00fccksverwaltung Gmbh & Co. Kg",
    "wof:placetype":"venue"
},
  "geometry": {"coordinates":[12.12464,47.991734],"type":"Point"}
}