{
  "type": "Feature",
  "properties": {
    "iso:country":"DE",
    "sg:address":"Alte Landstr. 28",
    "sg:city":"Rastorf",
    "sg:phone":"+49 4384/479",
    "sg:postcode":"24211",
    "sg:province":"Schleswig-Holstein",
    "wof:name":"G\u00fcnter Dudda",
    "wof:placetype":"venue"
},
  "geometry": {"coordinates":[10.33536,54.283051],"type":"Point"}
}