{
  "type": "Feature",
  "properties": {
    "iso:country":"DE",
    "sg:address":"Sch\u00f6fferstr 8",
    "sg:city":"Darmstadt",
    "sg:phone":"+49 6151/165427",
    "sg:postcode":"64295",
    "sg:province":"Hessen",
    "wof:name":"Patentinformationszentrum Der Hessischen Landes- Und Hochschulbibliothek",
    "wof:placetype":"venue"
},
  "geometry": {"coordinates":[8.639875412,49.8663253784],"type":"Point"}
}