{
  "type": "Feature",
  "properties": {
    "iso:country":"DE",
    "sg:address":"Schl\u00fcterstr. 77 a",
    "sg:city":"Hamburg",
    "sg:postcode":"20146",
    "sg:province":"Hamburg",
    "wof:name":"M & V Treuhand Gmbh",
    "wof:placetype":"venue"
},
  "geometry": {"coordinates":[9.9859304428,53.5705718994],"type":"Point"}
}