{
  "type": "Feature",
  "properties": {
    "iso:country":"DE",
    "sg:address":"Pfarrer-Fuhs-Str. 12",
    "sg:city":"Selfkant",
    "sg:phone":"+49 2456/1397",
    "sg:postcode":"52538",
    "sg:province":"Nordrhein-Westfalen",
    "wof:name":"Jhb Holzbau Gmbh",
    "wof:placetype":"venue"
},
  "geometry": {"coordinates":[5.902263,51.010193],"type":"Point"}
}