{
  "type": "Feature",
  "properties": {
    "iso:country":"DE",
    "sg:address":"Klever Str. 42",
    "sg:city":"D\u00fcsseldorf",
    "sg:phone":"+49 211/4921675",
    "sg:postcode":"40477",
    "sg:province":"Nordrhein-Westfalen",
    "wof:name":"Eduardo Cebrian",
    "wof:placetype":"venue"
},
  "geometry": {"coordinates":[6.7766928673,51.2408485413],"type":"Point"}
}