{
  "type": "Feature",
  "properties": {
    "iso:country":"DE",
    "sg:address":"Bahnhofstr.",
    "sg:city":"Gera",
    "sg:phone":"+49 365/8323423",
    "sg:postcode":"07545",
    "sg:province":"Th\u00fcringen",
    "wof:name":"Flug- Und Reiseservice Air Voyage",
    "wof:placetype":"venue"
},
  "geometry": {"coordinates":[12.077408,50.881954],"type":"Point"}
}