{
  "type": "Feature",
  "properties": {
    "iso:country":"DE",
    "sg:address":"Seidenstr. 34",
    "sg:city":"Stuttgart",
    "sg:phone":"+49 711/9420",
    "sg:postcode":"70174",
    "sg:province":"Baden-W\u00fcrttemberg",
    "wof:name":"Maritim Gastronomie Kultur- Und Kongre\u00dfzentrum",
    "wof:placetype":"venue"
},
  "geometry": {"coordinates":[9.1661701202,48.7807884216],"type":"Point"}
}