{
  "type": "Feature",
  "properties": {
    "iso:country":"DE",
    "sg:address":"Grundstr. 6",
    "sg:city":"Ro\u00dfwein",
    "sg:phone":"+49 34322/42210",
    "sg:postcode":"04741",
    "sg:province":"Sachsen",
    "wof:name":"Wohnungsgenossenschaft-s\u00fcd Ro\u00dfwein Eg",
    "wof:placetype":"venue"
},
  "geometry": {"coordinates":[13.1866607666,51.056388855],"type":"Point"}
}