{
  "type": "Feature",
  "properties": {
    "iso:country":"DE",
    "sg:address":"Carsten-Heeschen-Str. 22",
    "sg:city":"Neum\u00fcnster",
    "sg:phone":"+49 4321/528434",
    "sg:postcode":"24536",
    "sg:province":"Schleswig-Holstein",
    "wof:name":"Detlef Petersen",
    "wof:placetype":"venue"
},
  "geometry": {"coordinates":[9.9924840927,54.1287155151],"type":"Point"}
}