{
  "type": "Feature",
  "properties": {
    "iso:country":"DE",
    "sg:address":"Im Gewerbegebiet 31",
    "sg:city":"Lichtenau",
    "sg:phone":"+49 7227/953510",
    "sg:postcode":"77839",
    "sg:province":"Baden-W\u00fcrttemberg",
    "wof:name":"L&s Radio Communications",
    "wof:placetype":"venue"
},
  "geometry": {"coordinates":[7.997168,48.719219],"type":"Point"}
}