{
  "type": "Feature",
  "properties": {
    "iso:country":"DE",
    "sg:address":"Liegnitzer Str. 29",
    "sg:city":"Bad Oeynhausen",
    "sg:phone":"+49 5731/105859",
    "sg:postcode":"32549",
    "sg:province":"Nordrhein-Westfalen",
    "wof:name":"Sandra Westerwelle Architektin",
    "wof:placetype":"venue"
},
  "geometry": {"coordinates":[8.796083,52.209732],"type":"Point"}
}