{
  "type": "Feature",
  "properties": {
    "iso:country":"DE",
    "sg:address":"Hauptstr. 107",
    "sg:city":"Karlshuld",
    "sg:phone":"+49 8454/467",
    "sg:postcode":"86668",
    "sg:province":"Bayern",
    "wof:name":"Albert Dittenhauser",
    "wof:placetype":"venue"
},
  "geometry": {"coordinates":[11.302582,48.671741],"type":"Point"}
}