{
  "type": "Feature",
  "properties": {
    "iso:country":"DE",
    "sg:city":"Niederbreitbach",
    "sg:phone":"+49 2638/6154",
    "sg:postcode":"56589",
    "sg:province":"Rheinland-Pfalz",
    "wof:name":"Bauregie-service Gmbh",
    "wof:placetype":"venue"
},
  "geometry": {"coordinates":[7.417283,50.530685],"type":"Point"}
}