{
  "type": "Feature",
  "properties": {
    "iso:country":"DE",
    "sg:address":"Wolschinkaweg 3 a",
    "sg:city":"Lauchhammer",
    "sg:phone":"+49 3574/2460",
    "sg:postcode":"01979",
    "sg:province":"Brandenburg",
    "wof:name":"Eckhard Zedler",
    "wof:placetype":"venue"
},
  "geometry": {"coordinates":[13.776822,51.492653],"type":"Point"}
}