{
  "type": "Feature",
  "properties": {
    "iso:country":"DE",
    "sg:address":"Talring 58",
    "sg:city":"Krefeld",
    "sg:phone":"+49 2151/74980",
    "sg:postcode":"47802",
    "sg:province":"Nordrhein-Westfalen",
    "wof:name":"Ehl Gmbh",
    "wof:placetype":"venue"
},
  "geometry": {"coordinates":[6.530578,51.393833],"type":"Point"}
}