{
  "type": "Feature",
  "properties": {
    "iso:country":"DE",
    "sg:address":"Am Feldrain 10",
    "sg:city":"K\u00f6ln",
    "sg:phone":"+49 221/663662",
    "sg:postcode":"51061",
    "sg:province":"Nordrhein-Westfalen",
    "wof:name":"Rheinische Schule F\u00fcr Sprachbehinderte",
    "wof:placetype":"venue"
},
  "geometry": {"coordinates":[6.9785780907,50.9980545044],"type":"Point"}
}