{
  "type": "Feature",
  "properties": {
    "iso:country":"DE",
    "sg:address":"Am Anger 29",
    "sg:city":"Bernau",
    "sg:phone":"+49 8051/2935",
    "sg:postcode":"83233",
    "sg:province":"Bayern",
    "wof:name":"L. Mehnert",
    "wof:placetype":"venue"
},
  "geometry": {"coordinates":[12.3726,47.807671],"type":"Point"}
}