{
  "type": "Feature",
  "properties": {
    "iso:country":"DE",
    "sg:address":"An den Eichen 3a",
    "sg:city":"Rockenhausen",
    "sg:phone":"+49 6361/8037",
    "sg:postcode":"67806",
    "sg:province":"Rheinland-Pfalz",
    "wof:name":"Sib Trend-immobilien Vermittlungs Gmbh",
    "wof:placetype":"venue"
},
  "geometry": {"coordinates":[7.8257460594,49.6254234314],"type":"Point"}
}