{
  "type": "Feature",
  "properties": {
    "iso:country":"DE",
    "sg:address":"B\u00f6tticherstr. 3",
    "sg:city":"Westerland",
    "sg:phone":"+49 4651/21191",
    "sg:postcode":"25980",
    "sg:province":"Schleswig-Holstein",
    "wof:name":"Beach Club",
    "wof:placetype":"venue"
},
  "geometry": {"coordinates":[8.3042802811,54.9061088562],"type":"Point"}
}