{
  "type": "Feature",
  "properties": {
    "iso:country":"DE",
    "sg:address":"Solferinostr. 24",
    "sg:city":"Br\u00fcggen",
    "sg:phone":"+49 2157/14120",
    "sg:postcode":"41379",
    "sg:province":"Nordrhein-Westfalen",
    "wof:name":"Terstappen- Verwaltungsgesellschaft Mbh",
    "wof:placetype":"venue"
},
  "geometry": {"coordinates":[6.188537,51.277756],"type":"Point"}
}