{
  "type": "Feature",
  "properties": {
    "iso:country":"DE",
    "sg:address":"Hindenburgplatz 1",
    "sg:city":"N\u00f6rten-Hardenberg",
    "sg:phone":"+49 5503/999832",
    "sg:postcode":"37176",
    "sg:province":"Niedersachsen",
    "wof:name":"Let-l\u00f6wer & Co. Gmbh",
    "wof:placetype":"venue"
},
  "geometry": {"coordinates":[9.9370412827,51.6311073303],"type":"Point"}
}