{
  "type": "Feature",
  "properties": {
    "iso:country":"DE",
    "sg:address":"Vahrenwalder Str. 55",
    "sg:city":"Hannover",
    "sg:phone":"+49 511/3501501",
    "sg:postcode":"30165",
    "sg:province":"Niedersachsen",
    "wof:name":"Zoohaus Bergmann",
    "wof:placetype":"venue"
},
  "geometry": {"coordinates":[9.734273,52.39032],"type":"Point"}
}