{
  "type": "Feature",
  "properties": {
    "iso:country":"DE",
    "sg:address":"Hamburger Chaussee 32-36",
    "sg:city":"Kiel",
    "sg:phone":"+49 431/682611",
    "sg:postcode":"24113",
    "sg:province":"Schleswig-Holstein",
    "wof:name":"Paul Erkes Verwaltungs- Und Beteiligungs-gmbh",
    "wof:placetype":"venue"
},
  "geometry": {"coordinates":[10.09878,54.292171],"type":"Point"}
}