{
  "type": "Feature",
  "properties": {
    "iso:country":"DE",
    "sg:address":"Altenberger Str. 4",
    "sg:city":"Dippoldiswalde",
    "sg:phone":"+49 3504/613660",
    "sg:postcode":"01744",
    "sg:province":"Sachsen",
    "wof:name":"Achim Zeiske",
    "wof:placetype":"venue"
},
  "geometry": {"coordinates":[13.66792202,50.8947372437],"type":"Point"}
}