{
  "type": "Feature",
  "properties": {
    "iso:country":"DE",
    "sg:address":"Bahnhofstr. 4",
    "sg:city":"Kell",
    "sg:phone":"+49 6589/7103",
    "sg:postcode":"54427",
    "sg:province":"Rheinland-Pfalz",
    "wof:name":"J\u00fcrgen Klose B\u00e4ckerei",
    "wof:placetype":"venue"
},
  "geometry": {"coordinates":[6.822679,49.634068],"type":"Point"}
}