{
  "type": "Feature",
  "properties": {
    "iso:country":"DE",
    "sg:address":"Merseburger Chaussee 5",
    "sg:city":"D\u00f6lzig",
    "sg:phone":"+49 341/4615456",
    "sg:postcode":"04430",
    "wof:name":"Erdbeerland B\u00f6hlitz-ehrenberg Gmbh",
    "wof:placetype":"venue"
},
  "geometry": {"coordinates":[12.2192363739,51.3503952026],"type":"Point"}
}