{
  "type": "Feature",
  "properties": {
    "iso:country":"DE",
    "sg:address":"Tappenhof 16",
    "sg:city":"Bottrop",
    "sg:phone":"+49 2045/410450",
    "sg:postcode":"46244",
    "sg:province":"Nordrhein-Westfalen",
    "wof:name":"Ambulante Alten- Und Krankenpflege",
    "wof:placetype":"venue"
},
  "geometry": {"coordinates":[6.94303,51.596062],"type":"Point"}
}