{
  "type": "Feature",
  "properties": {
    "iso:country":"DE",
    "sg:address":"Doggerbankstr. 7",
    "sg:city":"Bremerhaven",
    "sg:phone":"+49 471/303363",
    "sg:postcode":"27570",
    "sg:province":"Bremen",
    "wof:name":"Hans D\u00fcring Elektroinstallation",
    "wof:placetype":"venue"
},
  "geometry": {"coordinates":[8.593196,53.521313],"type":"Point"}
}