{
  "type": "Feature",
  "properties": {
    "iso:country":"DE",
    "sg:address":"Minna-Bollmann-Str. 62",
    "sg:city":"Halberstadt",
    "sg:phone":"+49 3941/441315",
    "sg:postcode":"38820",
    "sg:province":"Sachsen-Anhalt",
    "wof:name":"G\u00fcnter Denecke",
    "wof:placetype":"venue"
},
  "geometry": {"coordinates":[11.0534286499,51.8869171143],"type":"Point"}
}