{
  "type": "Feature",
  "properties": {
    "iso:country":"DE",
    "sg:address":"Rinnelberg 10",
    "sg:city":"Plauen",
    "sg:phone":"+49 3741/472098",
    "sg:postcode":"08527",
    "sg:province":"Sachsen",
    "wof:name":"Wesumat Fahrzeug- Waschanlagen Gmbh",
    "wof:placetype":"venue"
},
  "geometry": {"coordinates":[12.142719,50.489563],"type":"Point"}
}