{
  "type": "Feature",
  "properties": {
    "iso:country":"DE",
    "sg:address":"An den Lehmkuhlen 9",
    "sg:city":"Benneckenstein",
    "sg:phone":"+49 39457/40800",
    "sg:postcode":"38877",
    "sg:province":"Sachsen-Anhalt",
    "wof:name":"Ziesenhenne Holzbau Und Holzhandel Gmbh",
    "wof:placetype":"venue"
},
  "geometry": {"coordinates":[10.7273950577,51.6703987122],"type":"Point"}
}