{
  "type": "Feature",
  "properties": {
    "iso:country":"DE",
    "sg:address":"Geschwister-Scholl-Str. 1",
    "sg:city":"Sch\u00f6neck",
    "sg:postcode":"08261",
    "sg:province":"Sachsen",
    "wof:name":"Thomas Lorenz",
    "wof:placetype":"venue"
},
  "geometry": {"coordinates":[12.32753,50.390308],"type":"Point"}
}