{
  "type": "Feature",
  "properties": {
    "iso:country":"DE",
    "sg:address":"Fellersborn 6",
    "sg:city":"L\u00f6hnberg",
    "sg:phone":"+49 6471/8220",
    "sg:postcode":"35792",
    "sg:province":"Hessen",
    "wof:name":"G. Erbe",
    "wof:placetype":"venue"
},
  "geometry": {"coordinates":[8.2726078033,50.514541626],"type":"Point"}
}