{
  "type": "Feature",
  "properties": {
    "iso:country":"DE",
    "sg:address":"M\u00fchlthal 124",
    "sg:city":"Starnberg",
    "sg:phone":"+49 8151/36090",
    "sg:postcode":"82319",
    "sg:province":"Bayern",
    "wof:name":"Forsthaus M\u00fchltal An Der W\u00fcrm",
    "wof:placetype":"venue"
},
  "geometry": {"coordinates":[11.3589134216,48.035282135],"type":"Point"}
}