{
  "type": "Feature",
  "properties": {
    "iso:country":"DE",
    "sg:address":"Am Kreuzberg 16",
    "sg:city":"Medlingen",
    "sg:phone":"+49 9073/7743",
    "sg:postcode":"89441",
    "sg:province":"Bayern",
    "wof:name":"Hansj\u00f6rg Gerold",
    "wof:placetype":"venue"
},
  "geometry": {"coordinates":[10.318397,48.572163],"type":"Point"}
}