{
  "type": "Feature",
  "properties": {
    "iso:country":"DE",
    "sg:address":"D\u00fclmener Str. 155",
    "sg:city":"Coesfeld",
    "sg:phone":"+49 2541/94000",
    "sg:postcode":"48653",
    "sg:province":"Nordrhein-Westfalen",
    "wof:name":"Bautreff Voss",
    "wof:placetype":"venue"
},
  "geometry": {"coordinates":[7.1728291512,51.9233551025],"type":"Point"}
}