{
  "type": "Feature",
  "properties": {
    "iso:country":"DE",
    "sg:address":"Vrasselt 26",
    "sg:city":"Issum",
    "sg:phone":"+49 2835/2133",
    "sg:postcode":"47661",
    "sg:province":"Nordrhein-Westfalen",
    "wof:name":"Heinrich Ripkens Landwirtschaft.",
    "wof:placetype":"venue"
},
  "geometry": {"coordinates":[6.406085,51.523968],"type":"Point"}
}