{
  "type": "Feature",
  "properties": {
    "iso:country":"DE",
    "sg:address":"Limesweg 8",
    "sg:city":"Ehingen",
    "sg:phone":"+49 7392/7602",
    "sg:postcode":"89584",
    "sg:province":"Baden-W\u00fcrttemberg",
    "wof:name":"Thomas Braig",
    "wof:placetype":"venue"
},
  "geometry": {"coordinates":[9.830945015,48.2693328857],"type":"Point"}
}