{
  "type": "Feature",
  "properties": {
    "iso:country":"DE",
    "sg:address":"Vogteistr. 1",
    "sg:city":"L\u00f6hne",
    "sg:phone":"+49 5731/40888",
    "sg:postcode":"32584",
    "sg:province":"Nordrhein-Westfalen",
    "wof:name":"Wien",
    "wof:placetype":"venue"
},
  "geometry": {"coordinates":[8.760466,52.206913],"type":"Point"}
}