{
  "type": "Feature",
  "properties": {
    "iso:country":"DE",
    "sg:address":"Wehrstr. 14 a",
    "sg:city":"Glauchau",
    "sg:postcode":"08371",
    "sg:province":"Sachsen",
    "wof:name":"Mario Reichelt",
    "wof:placetype":"venue"
},
  "geometry": {"coordinates":[12.5294713974,50.8163146973],"type":"Point"}
}