{
  "type": "Feature",
  "properties": {
    "iso:country":"DE",
    "sg:address":"Neusser Str. 422",
    "sg:city":"K\u00f6ln",
    "sg:phone":"+49 221/7608358",
    "sg:postcode":"50733",
    "sg:province":"Nordrhein-Westfalen",
    "wof:name":"Spielkauf Karl-heinz Oerder E. K.",
    "wof:placetype":"venue"
},
  "geometry": {"coordinates":[6.9520292282,50.9713516235],"type":"Point"}
}