{
  "type": "Feature",
  "properties": {
    "iso:country":"DE",
    "sg:address":"Adolf-Vaeltl-Str. 23",
    "sg:city":"Neuburg",
    "sg:phone":"+49 8507/267",
    "sg:postcode":"94127",
    "sg:province":"Bayern",
    "wof:name":"Klaus Oberl\u00e4nder Ingenieur",
    "wof:placetype":"venue"
},
  "geometry": {"coordinates":[13.4494695663,48.509059906],"type":"Point"}
}