{
  "type": "Feature",
  "properties": {
    "iso:country":"DE",
    "sg:address":"Heerwasenstr. 27-1",
    "sg:city":"Gosheim",
    "sg:postcode":"78559",
    "sg:province":"Baden-W\u00fcrttemberg",
    "wof:name":"Weber Pr\u00e4zisionstechnik Gmbh",
    "wof:placetype":"venue"
},
  "geometry": {"coordinates":[8.761629,48.13279],"type":"Point"}
}