{
  "type": "Feature",
  "properties": {
    "iso:country":"DE",
    "sg:address":"Blaik 8",
    "sg:city":"Kiefersfelden",
    "sg:phone":"+49 8033/2598",
    "sg:postcode":"83088",
    "sg:province":"Bayern",
    "wof:name":"Sebastian Danner",
    "wof:placetype":"venue"
},
  "geometry": {"coordinates":[12.179716,47.6301],"type":"Point"}
}