{
  "type": "Feature",
  "properties": {
    "iso:country":"DE",
    "sg:address":"K\u00f6nigseggwalder Str. 98",
    "sg:city":"Ho\u00dfkirch",
    "sg:phone":"+49 7587/462",
    "sg:postcode":"88374",
    "sg:province":"Baden-W\u00fcrttemberg",
    "wof:name":"U. Sourisseau",
    "wof:placetype":"venue"
},
  "geometry": {"coordinates":[9.4377737045,47.939201355],"type":"Point"}
}