{
  "type": "Feature",
  "properties": {
    "iso:country":"DE",
    "sg:address":"Trappenpfad 7",
    "sg:city":"Berlin",
    "sg:phone":"+49 30/6012747",
    "sg:postcode":"12351",
    "sg:province":"Berlin",
    "wof:name":"Elsat Elektro-sanit\u00e4r Installationsgesellschaft",
    "wof:placetype":"venue"
},
  "geometry": {"coordinates":[13.464415,52.441917],"type":"Point"}
}