{
  "type": "Feature",
  "properties": {
    "iso:country":"DE",
    "sg:address":"Schwalbengarten 3",
    "sg:city":"Bonn",
    "sg:phone":"+49 228/3869253",
    "sg:postcode":"53175",
    "sg:province":"Nordrhein-Westfalen",
    "wof:name":"Dlt-dienst-leistung- Textil Gmbh",
    "wof:placetype":"venue"
},
  "geometry": {"coordinates":[7.1220860481,50.6987762451],"type":"Point"}
}