{
  "type": "Feature",
  "properties": {
    "iso:country":"DE",
    "sg:address":"B\u00fcntefeldstr. 2",
    "sg:city":"Ronnenberg",
    "sg:phone":"+49 511/468429",
    "sg:postcode":"30952",
    "sg:province":"Niedersachsen",
    "wof:name":"Bernd Pallas Architekt",
    "wof:placetype":"venue"
},
  "geometry": {"coordinates":[9.662176,52.345657],"type":"Point"}
}