{
  "type": "Feature",
  "properties": {
    "iso:country":"DE",
    "sg:address":"Freier Blick 10",
    "sg:city":"Helbra",
    "sg:phone":"+49 34772/28359",
    "sg:postcode":"06311",
    "sg:province":"Sachsen-Anhalt",
    "wof:name":"Bernd Haberkorn",
    "wof:placetype":"venue"
},
  "geometry": {"coordinates":[11.4736852646,51.55991745],"type":"Point"}
}