{
  "type": "Feature",
  "properties": {
    "iso:country":"DE",
    "sg:address":"Winzerstr. 6",
    "sg:city":"Glottertal",
    "sg:phone":"+49 7684/310",
    "sg:postcode":"79286",
    "sg:province":"Baden-W\u00fcrttemberg",
    "wof:name":"Glotter-grill",
    "wof:placetype":"venue"
},
  "geometry": {"coordinates":[7.9477038383,48.0479125977],"type":"Point"}
}