{
  "type": "Feature",
  "properties": {
    "iso:country":"DE",
    "sg:address":"D\u00fcrerstr. 2-4",
    "sg:city":"Hattersheim",
    "sg:phone":"+49 6190/2777",
    "sg:postcode":"65795",
    "sg:province":"Hessen",
    "wof:name":"Reinhard Kehl Werkzeug- Und Apparatebau Kg",
    "wof:placetype":"venue"
},
  "geometry": {"coordinates":[8.479936,50.062904],"type":"Point"}
}