{
  "type": "Feature",
  "properties": {
    "iso:country":"DE",
    "sg:address":"Edekastr. 10",
    "sg:city":"Heddesheim",
    "sg:postcode":"68542",
    "sg:province":"Baden-W\u00fcrttemberg",
    "wof:name":"B & E Feinkost Produktion Gmbh",
    "wof:placetype":"venue"
},
  "geometry": {"coordinates":[8.6274356842,49.5059394836],"type":"Point"}
}