{
  "type": "Feature",
  "properties": {
    "iso:country":"DE",
    "sg:address":"Alex-Kirchhof-Weg 2",
    "sg:city":"Cuxhaven",
    "sg:postcode":"27478",
    "sg:province":"Niedersachsen",
    "wof:name":"Cux-parkett Inh. G. Meyer-sakrenz E. Kfm.",
    "wof:placetype":"venue"
},
  "geometry": {"coordinates":[8.6646165848,53.8039283752],"type":"Point"}
}