{
  "type": "Feature",
  "properties": {
    "iso:country":"DE",
    "sg:address":"Schmidtstr. 18",
    "sg:city":"R\u00fcdesheim am Rhein",
    "sg:phone":"+49 6722/3545",
    "sg:postcode":"65385",
    "sg:province":"Hessen",
    "wof:name":"C. Siegfried Weinanbau",
    "wof:placetype":"venue"
},
  "geometry": {"coordinates":[7.92456007,49.9798736572],"type":"Point"}
}