{
  "type": "Feature",
  "properties": {
    "iso:country":"DE",
    "sg:address":"Birkenstr. 88",
    "sg:city":"D\u00fcsseldorf",
    "sg:postcode":"40233",
    "sg:province":"Nordrhein-Westfalen",
    "wof:name":"American Sports",
    "wof:placetype":"venue"
},
  "geometry": {"coordinates":[6.8071727753,51.2271156311],"type":"Point"}
}