{
  "type": "Feature",
  "properties": {
    "iso:country":"DE",
    "sg:address":"Ewaldstr. 25",
    "sg:city":"Remscheid",
    "sg:phone":"+49 2191/35229",
    "sg:postcode":"42859",
    "sg:province":"Nordrhein-Westfalen",
    "wof:name":"Klaus K\u00fcster",
    "wof:placetype":"venue"
},
  "geometry": {"coordinates":[7.205976963,51.1727523804],"type":"Point"}
}