{
  "type": "Feature",
  "properties": {
    "iso:country":"DE",
    "sg:address":"D\u00fcendorfer Weg 2 B",
    "sg:city":"Wunstorf",
    "sg:phone":"+49 5031/67031",
    "sg:postcode":"31515",
    "sg:province":"Niedersachsen",
    "wof:name":"Lvm",
    "wof:placetype":"venue"
},
  "geometry": {"coordinates":[9.4312887192,52.4222145081],"type":"Point"}
}