{
  "type": "Feature",
  "properties": {
    "iso:country":"DE",
    "sg:address":"Greizer Str. 74",
    "sg:city":"Gera",
    "sg:phone":"+49 365/53143",
    "sg:postcode":"07545",
    "sg:province":"Th\u00fcringen",
    "wof:name":"Connys Container",
    "wof:placetype":"venue"
},
  "geometry": {"coordinates":[12.086639,50.872952],"type":"Point"}
}