{
  "type": "Feature",
  "properties": {
    "iso:country":"DE",
    "sg:address":"Versbacher Str. 128",
    "sg:city":"W\u00fcrzburg",
    "sg:phone":"+49 931/250810",
    "sg:postcode":"97078",
    "sg:province":"Bayern",
    "wof:name":"Richard Denk Gmbh & Co. Kg",
    "wof:placetype":"venue"
},
  "geometry": {"coordinates":[9.9559583664,49.8332099915],"type":"Point"}
}