{
  "type": "Feature",
  "properties": {
    "iso:country":"DE",
    "sg:city":"Zusamaltheim",
    "sg:phone":"+49 8272/6378",
    "sg:postcode":"89449",
    "sg:province":"Bayern",
    "wof:name":"E. Tatarczyk",
    "wof:placetype":"venue"
},
  "geometry": {"coordinates":[10.63578,48.53043],"type":"Point"}
}