{
  "type": "Feature",
  "properties": {
    "iso:country":"DE",
    "sg:address":"Linsenhofer Str. 149",
    "sg:city":"Suhl",
    "sg:postcode":"98529",
    "sg:province":"Th\u00fcringen",
    "wof:name":"G\u00fcnter Schwarz",
    "wof:placetype":"venue"
},
  "geometry": {"coordinates":[10.663905,50.615807],"type":"Point"}
}