{
  "type": "Feature",
  "properties": {
    "iso:country":"DE",
    "sg:address":"Dom\u00e4nenweg 11",
    "sg:city":"Sonnefeld",
    "sg:postcode":"96242",
    "sg:province":"Bayern",
    "wof:name":"Orthop\u00e4die-schuhtechnik Erich Engelhardt E. K.",
    "wof:placetype":"venue"
},
  "geometry": {"coordinates":[11.1340293884,50.2234687805],"type":"Point"}
}