{
  "type": "Feature",
  "properties": {
    "iso:country":"DE",
    "sg:address":"Berliner Str. 7",
    "sg:city":"Ro\u00dflau",
    "sg:phone":"+49 34901/83936",
    "sg:postcode":"06862",
    "sg:province":"Sachsen-Anhalt",
    "wof:name":"Uwe Kuehne Tischlerei Und Trockenbau Gmbh",
    "wof:placetype":"venue"
},
  "geometry": {"coordinates":[12.25836,51.889011],"type":"Point"}
}