{
  "type": "Feature",
  "properties": {
    "iso:country":"DE",
    "sg:address":"Am Bruckweg 28a",
    "sg:city":"Bogen",
    "sg:phone":"+49 9422/5736",
    "sg:postcode":"94327",
    "sg:province":"Bayern",
    "wof:name":"Echzeit Computer- Und Programmsysteme Gmbh",
    "wof:placetype":"venue"
},
  "geometry": {"coordinates":[12.7037763596,48.9166297913],"type":"Point"}
}