{
  "type": "Feature",
  "properties": {
    "iso:country":"DE",
    "sg:address":"Sienhardtstr. 29",
    "sg:city":"Gummersbach",
    "sg:phone":"+49 2261/52962",
    "sg:postcode":"51645",
    "sg:province":"Nordrhein-Westfalen",
    "wof:name":"Ludwig Witt",
    "wof:placetype":"venue"
},
  "geometry": {"coordinates":[7.6169462204,51.0157814026],"type":"Point"}
}