{
  "type": "Feature",
  "properties": {
    "iso:country":"DE",
    "sg:address":"Rosalienberg 6",
    "sg:city":"Karlsruhe",
    "sg:phone":"+49 721/482323",
    "sg:postcode":"76229",
    "sg:province":"Baden-W\u00fcrttemberg",
    "wof:name":"Hansj\u00f6rg Stemmle",
    "wof:placetype":"venue"
},
  "geometry": {"coordinates":[8.498407,49.008736],"type":"Point"}
}