{
  "type": "Feature",
  "properties": {
    "iso:country":"DE",
    "sg:address":"Robert-Koch-Stra\u00dfe 2",
    "sg:city":"Plaidt",
    "sg:postcode":"56637",
    "sg:province":"Rheinland-Pfalz",
    "wof:name":"Ferienweingut Richard Deis And Bernd Deis Senheim",
    "wof:placetype":"venue"
},
  "geometry": {"coordinates":[7.403354,50.394321],"type":"Point"}
}