{
  "type": "Feature",
  "properties": {
    "iso:country":"DE",
    "sg:address":"Gablonzer Str. 19",
    "sg:city":"Oberursel",
    "sg:phone":"+49 6171/630141",
    "sg:postcode":"61440",
    "sg:province":"Hessen",
    "wof:name":"Audiovision Vertriebs- Und Beratungsgesellschaft Mbh",
    "wof:placetype":"venue"
},
  "geometry": {"coordinates":[8.5877218246,50.1945457458],"type":"Point"}
}