{
  "type": "Feature",
  "properties": {
    "iso:country":"DE",
    "sg:address":"B 4 5",
    "sg:city":"Mannheim",
    "sg:phone":"+49 621/14513",
    "sg:postcode":"68159",
    "sg:province":"Baden-W\u00fcrttemberg",
    "wof:name":"Michaela Thum Rechtsanw\u00e4ltin",
    "wof:placetype":"venue"
},
  "geometry": {"coordinates":[8.4538297653,49.4963607788],"type":"Point"}
}