{
  "type": "Feature",
  "properties": {
    "iso:country":"DE",
    "sg:address":"An der Kleinbahn 5",
    "sg:city":"Winsen",
    "sg:phone":"+49 4171/71961",
    "sg:postcode":"21423",
    "sg:province":"Niedersachsen",
    "wof:name":"Ernst-j. Klippel",
    "wof:placetype":"venue"
},
  "geometry": {"coordinates":[10.2091026306,53.3541107178],"type":"Point"}
}