{
  "type": "Feature",
  "properties": {
    "iso:country":"DE",
    "sg:address":"Soestenstr. 24",
    "sg:city":"Cloppenburg",
    "sg:phone":"+49 4471/2320",
    "sg:postcode":"49661",
    "sg:province":"Niedersachsen",
    "wof:name":"Willi Emken",
    "wof:placetype":"venue"
},
  "geometry": {"coordinates":[8.0371904373,52.8486366272],"type":"Point"}
}