{
  "type": "Feature",
  "properties": {
    "iso:country":"DE",
    "sg:address":"Werkst\u00e4ttenstr. 31",
    "sg:city":"Leipzig",
    "sg:phone":"+49 341/6510535",
    "sg:postcode":"04319",
    "sg:province":"Sachsen",
    "wof:name":"Ddf Tino Hemmann-steffen Vieck Gbr",
    "wof:placetype":"venue"
},
  "geometry": {"coordinates":[12.4699583054,51.3353500366],"type":"Point"}
}