{
  "type": "Feature",
  "properties": {
    "iso:country":"DE",
    "sg:address":"Koppel 55",
    "sg:city":"Hamburg",
    "sg:phone":"+49 40/338651",
    "sg:postcode":"20099",
    "sg:province":"Hamburg",
    "wof:name":"Miplas Gesellschaft F\u00fcr Modulare Informations- Und",
    "wof:placetype":"venue"
},
  "geometry": {"coordinates":[10.0107326508,53.558506012],"type":"Point"}
}