{
  "type": "Feature",
  "properties": {
    "iso:country":"DE",
    "sg:address":"Gallusstr. 89",
    "sg:city":"Bonn",
    "sg:phone":"+49 228/442131",
    "sg:postcode":"53227",
    "sg:province":"Nordrhein-Westfalen",
    "wof:name":"Peter Schmitz",
    "wof:placetype":"venue"
},
  "geometry": {"coordinates":[7.153579,50.726212],"type":"Point"}
}