{
  "type": "Feature",
  "properties": {
    "iso:country":"DE",
    "sg:address":"Grambeker Weg 22",
    "sg:city":"M\u00f6lln",
    "sg:phone":"+49 4542/89252",
    "sg:postcode":"23879",
    "sg:province":"Schleswig-Holstein",
    "wof:name":"Jochen Muth",
    "wof:placetype":"venue"
},
  "geometry": {"coordinates":[10.6829071045,53.622718811],"type":"Point"}
}