{
  "type": "Feature",
  "properties": {
    "iso:country":"DE",
    "sg:address":"Welserstr. 4",
    "sg:city":"K\u00f6ln",
    "sg:phone":"+49 2203/93980",
    "sg:postcode":"51149",
    "sg:province":"Nordrhein-Westfalen",
    "wof:name":"B\u00fcro Direkt",
    "wof:placetype":"venue"
},
  "geometry": {"coordinates":[7.0590047836,50.9117279053],"type":"Point"}
}