{
  "type": "Feature",
  "properties": {
    "iso:country":"DE",
    "sg:address":"Lessingstr. 12",
    "sg:city":"Bitburg",
    "sg:phone":"+49 6561/3807",
    "sg:postcode":"54634",
    "sg:province":"Rheinland-Pfalz",
    "wof:name":"Hydronic Gesellschaft F\u00fcr Me\u00dftechnik Mbh",
    "wof:placetype":"venue"
},
  "geometry": {"coordinates":[6.5151619911,49.96717453],"type":"Point"}
}