{
  "type": "Feature",
  "properties": {
    "iso:country":"DE",
    "sg:address":"Hermannstr. 91 a",
    "sg:city":"Dortmund",
    "sg:postcode":"44263",
    "sg:province":"Nordrhein-Westfalen",
    "wof:name":"Kemper Gmbh",
    "wof:placetype":"venue"
},
  "geometry": {"coordinates":[7.507743,51.488129],"type":"Point"}
}