{
  "type": "Feature",
  "properties": {
    "iso:country":"DE",
    "sg:address":"Steinbach an der Heide 18",
    "sg:city":"Ludwigsstadt",
    "sg:phone":"+49 9263/308",
    "sg:postcode":"96337",
    "sg:province":"Bayern",
    "wof:name":"Ev. Pfarramt Gem. Steinbach",
    "wof:placetype":"venue"
},
  "geometry": {"coordinates":[11.4178447723,50.5071716309],"type":"Point"}
}