{
  "type": "Feature",
  "properties": {
    "iso:country":"DE",
    "sg:address":"Am Burgweiher 50",
    "sg:city":"Bonn",
    "sg:phone":"+49 228/520010",
    "sg:postcode":"53123",
    "sg:province":"Nordrhein-Westfalen",
    "wof:name":"Anite Deutschland Holding Gmbh",
    "wof:placetype":"venue"
},
  "geometry": {"coordinates":[7.0464820862,50.7154922485],"type":"Point"}
}