{
  "type": "Feature",
  "properties": {
    "iso:country":"DE",
    "sg:address":"Jannes-Ohling-Str. 8",
    "sg:city":"Krummh\u00f6rn",
    "sg:phone":"+49 4923/990130",
    "sg:postcode":"26736",
    "sg:province":"Niedersachsen",
    "wof:name":"Steuerberater Hinrich Poppinga",
    "wof:placetype":"venue"
},
  "geometry": {"coordinates":[7.0984601974,53.4336853027],"type":"Point"}
}