{
  "type": "Feature",
  "properties": {
    "iso:country":"DE",
    "sg:address":"Bonnstr. 31",
    "sg:city":"Frechen",
    "sg:phone":"+49 2234/957210",
    "sg:postcode":"50226",
    "sg:province":"Nordrhein-Westfalen",
    "wof:name":"Igefa Fachgro\u00dfhandlung F\u00fcr Artikel Der Sauberkeit Und",
    "wof:placetype":"venue"
},
  "geometry": {"coordinates":[6.827141,50.91618],"type":"Point"}
}