{
  "type": "Feature",
  "properties": {
    "iso:country":"DE",
    "sg:address":"Am Stenn 9",
    "sg:city":"Schmallenberg",
    "sg:postcode":"57392",
    "sg:province":"Nordrhein-Westfalen",
    "wof:name":"Franz-peter Falke Verm\u00f6gensverwaltungs-gmbh",
    "wof:placetype":"venue"
},
  "geometry": {"coordinates":[8.2877960205,51.1445960999],"type":"Point"}
}