{
  "type": "Feature",
  "properties": {
    "iso:country":"DE",
    "sg:address":"Simonshofer Str. 7",
    "sg:city":"Lauf",
    "sg:phone":"+49 9123/4313",
    "sg:postcode":"91207",
    "sg:province":"Bayern",
    "wof:name":"Gr\u00f6schel Immobilien Gmbh",
    "wof:placetype":"venue"
},
  "geometry": {"coordinates":[11.2829704285,49.5141792297],"type":"Point"}
}