{
  "type": "Feature",
  "properties": {
    "iso:country":"DE",
    "sg:address":"H\u00fcttenstr. 13",
    "sg:city":"Brilon",
    "sg:phone":"+49 2961/3938",
    "sg:postcode":"59929",
    "sg:province":"Nordrhein-Westfalen",
    "wof:name":"H.-d. Kropff Heilpraktiker",
    "wof:placetype":"venue"
},
  "geometry": {"coordinates":[8.5061159134,51.3847846985],"type":"Point"}
}