{
  "type": "Feature",
  "properties": {
    "iso:country":"DE",
    "sg:address":"Grambkermoorer Landstr.",
    "sg:city":"Bremen",
    "sg:phone":"+49 421/453109",
    "sg:postcode":"28719",
    "sg:province":"Bremen",
    "wof:name":"Herbert Trost",
    "wof:placetype":"venue"
},
  "geometry": {"coordinates":[8.72266,53.159618],"type":"Point"}
}