{
  "type": "Feature",
  "properties": {
    "iso:country":"DE",
    "sg:address":"Schlo\u00dfstr. 5-7",
    "sg:city":"Eutin",
    "sg:phone":"+49 4945/217790",
    "sg:postcode":"23701",
    "sg:province":"Schleswig-Holstein",
    "wof:name":"Struves Buchdruckerei & Verlag Gmbh & Co Kg",
    "wof:placetype":"venue"
},
  "geometry": {"coordinates":[10.6168069839,54.1376533508],"type":"Point"}
}