{
  "type": "Feature",
  "properties": {
    "iso:country":"DE",
    "sg:address":"Isabellastr. 40",
    "sg:city":"M\u00fcnchen",
    "sg:phone":"+49 89/2719163",
    "sg:postcode":"80796",
    "sg:province":"Bayern",
    "wof:name":"Smolana",
    "wof:placetype":"venue"
},
  "geometry": {"coordinates":[11.5730285645,48.1596679688],"type":"Point"}
}