{
  "type": "Feature",
  "properties": {
    "iso:country":"DE",
    "sg:address":"Westerallee 139",
    "sg:city":"Flensburg",
    "sg:phone":"+49 461/55588",
    "sg:postcode":"24941",
    "sg:province":"Schleswig-Holstein",
    "wof:name":"Peter Johannsen Joha Park Gmbh",
    "wof:placetype":"venue"
},
  "geometry": {"coordinates":[9.3989133835,54.7813644409],"type":"Point"}
}