{
  "type": "Feature",
  "properties": {
    "iso:country":"DE",
    "sg:address":"Zur Tr\u00e4nke 2",
    "sg:city":"Tiefenbronn",
    "sg:phone":"+49 7234/1419",
    "sg:postcode":"75233",
    "sg:province":"Baden-W\u00fcrttemberg",
    "wof:name":"Krankenpflegeverein Tiefenbronn E. V.",
    "wof:placetype":"venue"
},
  "geometry": {"coordinates":[8.803299,48.825211],"type":"Point"}
}