{
  "type": "Feature",
  "properties": {
    "iso:country":"DE",
    "sg:address":"Kastanienallee 2",
    "sg:city":"Braunschweig",
    "sg:postcode":"38102",
    "sg:province":"Niedersachsen",
    "wof:name":"Gesellschaft Zur F\u00f6rderung Kirchenmusikalischen Arbeit Am",
    "wof:placetype":"venue"
},
  "geometry": {"coordinates":[10.5389232635,52.2624702454],"type":"Point"}
}