{
  "type": "Feature",
  "properties": {
    "iso:country":"DE",
    "sg:address":"Filstalstr. 60",
    "sg:city":"Schw\u00e4bisch Gm\u00fcnd",
    "sg:phone":"+49 7332/96960",
    "sg:postcode":"73529",
    "sg:province":"Baden-W\u00fcrttemberg",
    "wof:name":"Annemarie Fuchs-alasafi Steuerberaterin",
    "wof:placetype":"venue"
},
  "geometry": {"coordinates":[9.8840265274,48.7239227295],"type":"Point"}
}