{
  "type": "Feature",
  "properties": {
    "iso:country":"DE",
    "sg:address":"T\u00fcrkenstr. 19",
    "sg:city":"Saarbr\u00fccken",
    "sg:phone":"+49 681/34791",
    "sg:postcode":"66111",
    "sg:province":"Saarland",
    "wof:name":"Altstadtsalon",
    "wof:placetype":"venue"
},
  "geometry": {"coordinates":[6.9988121986,49.2329673767],"type":"Point"}
}