{
  "type": "Feature",
  "properties": {
    "iso:country":"DE",
    "sg:address":"R\u00f6merrast 10",
    "sg:city":"Hamminkeln",
    "sg:phone":"+49 2852/4326",
    "sg:postcode":"46499",
    "sg:province":"Nordrhein-Westfalen",
    "wof:name":"Johann Overkamp",
    "wof:placetype":"venue"
},
  "geometry": {"coordinates":[6.582072,51.760147],"type":"Point"}
}