{
  "type": "Feature",
  "properties": {
    "iso:country":"DE",
    "sg:address":"Industriestr. 1",
    "sg:city":"W\u00f6lfersheim",
    "sg:phone":"+49 6036/888",
    "sg:postcode":"61200",
    "sg:province":"Hessen",
    "wof:name":"Richard Schulze Gesellschaft F\u00fcr Heft- Und Nageltechnik Mbh",
    "wof:placetype":"venue"
},
  "geometry": {"coordinates":[8.8546590805,50.4252204895],"type":"Point"}
}