{
  "type": "Feature",
  "properties": {
    "iso:country":"DE",
    "sg:address":"Am Kinsingwald 1-2",
    "sg:city":"Salzweg",
    "sg:phone":"+49 851/949610",
    "sg:postcode":"94121",
    "sg:province":"Bayern",
    "wof:name":"Fetter & Spiritini Gastro-service Gmbh",
    "wof:placetype":"venue"
},
  "geometry": {"coordinates":[13.4732494354,48.60912323],"type":"Point"}
}