{
  "type": "Feature",
  "properties": {
    "iso:country":"DE",
    "sg:address":"Roggensteiner Allee 180",
    "sg:city":"Eichenau",
    "sg:phone":"+49 8141/80634",
    "sg:postcode":"82223",
    "sg:province":"Bayern",
    "wof:name":"Robert Und Elisabeth Leib",
    "wof:placetype":"venue"
},
  "geometry": {"coordinates":[11.3182840347,48.1619148254],"type":"Point"}
}