{
  "type": "Feature",
  "properties": {
    "iso:country":"DE",
    "sg:address":"Alfelder Str. 38",
    "sg:city":"Diekholzen",
    "sg:phone":"+49 5121/261721",
    "sg:postcode":"31199",
    "sg:province":"Niedersachsen",
    "wof:name":"Michel Prevel",
    "wof:placetype":"venue"
},
  "geometry": {"coordinates":[9.9156455994,52.0937156677],"type":"Point"}
}