{
  "type": "Feature",
  "properties": {
    "iso:country":"DE",
    "sg:address":"Schlossgartenstra\u00dfe 10",
    "sg:city":"Bernburg",
    "sg:phone":"+49 3471/347990",
    "sg:postcode":"06406",
    "sg:province":"Sachsen-Anhalt",
    "wof:name":"Dom\u00e4ne Bobbe",
    "wof:placetype":"venue"
},
  "geometry": {"coordinates":[11.736101,51.795345],"type":"Point"}
}