{
  "type": "Feature",
  "properties": {
    "iso:country":"DE",
    "sg:address":"Eschenallee 74",
    "sg:city":"Hamm",
    "sg:phone":"+49 2381/50522",
    "sg:postcode":"59063",
    "sg:province":"Nordrhein-Westfalen",
    "wof:name":"Haus Heitkemper",
    "wof:placetype":"venue"
},
  "geometry": {"coordinates":[7.8402380943,51.669921875],"type":"Point"}
}