{
  "type": "Feature",
  "properties": {
    "iso:country":"DE",
    "sg:address":"Liliencronstr. 5",
    "sg:city":"Berlin",
    "sg:phone":"+49 30/7954068",
    "sg:postcode":"12167",
    "sg:province":"Berlin",
    "wof:name":"Prof. G. Br\u00f6mme Ingenieur",
    "wof:placetype":"venue"
},
  "geometry": {"coordinates":[13.341301918,52.448677063],"type":"Point"}
}