{
  "type": "Feature",
  "properties": {
    "iso:country":"DE",
    "sg:address":"Gertenbachstr. 21",
    "sg:city":"Remscheid",
    "sg:phone":"+49 2191/50783",
    "sg:postcode":"42899",
    "sg:province":"Nordrhein-Westfalen",
    "wof:name":"Paul Scharw\u00e4chter",
    "wof:placetype":"venue"
},
  "geometry": {"coordinates":[7.2373228073,51.2092323303],"type":"Point"}
}