{
  "type": "Feature",
  "properties": {
    "iso:country":"DE",
    "sg:address":"Augsburger Str. 89",
    "sg:city":"Dresden",
    "sg:phone":"+49 351/3114953",
    "sg:postcode":"01277",
    "sg:province":"Sachsen",
    "wof:name":"U. W. B. Urbaner Wohnungsbau Baubetreuung Gmbh",
    "wof:placetype":"venue"
},
  "geometry": {"coordinates":[13.8011894226,51.0443191528],"type":"Point"}
}