{
  "type": "Feature",
  "properties": {
    "iso:country":"DE",
    "sg:address":"Barloer Str. 51",
    "sg:city":"Rhede",
    "sg:phone":"+49 4928/727075",
    "sg:postcode":"46414",
    "sg:province":"Nordrhein-Westfalen",
    "wof:name":"Steva Gmbh",
    "wof:placetype":"venue"
},
  "geometry": {"coordinates":[6.692555,51.854462],"type":"Point"}
}