{
  "type": "Feature",
  "properties": {
    "iso:country":"DE",
    "sg:address":"Tulpenstr. 4",
    "sg:city":"Wiesentheid",
    "sg:phone":"+49 9383/6542",
    "sg:postcode":"97353",
    "sg:province":"Bayern",
    "wof:name":"Alfred Freund Elektroinstallation",
    "wof:placetype":"venue"
},
  "geometry": {"coordinates":[10.346962,49.798473],"type":"Point"}
}