{
  "type": "Feature",
  "properties": {
    "iso:country":"DE",
    "sg:address":"In der Au 3",
    "sg:city":"Urbar",
    "sg:phone":"+49 261/61582",
    "sg:postcode":"56182",
    "sg:province":"Rheinland-Pfalz",
    "wof:name":"W. Dasting Ingenieur",
    "wof:placetype":"venue"
},
  "geometry": {"coordinates":[7.6227498055,50.3813209534],"type":"Point"}
}