{
  "type": "Feature",
  "properties": {
    "iso:country":"DE",
    "sg:address":"Langer Markt 9",
    "sg:city":"Hermeskeil",
    "sg:phone":"+49 6503/1213",
    "sg:postcode":"54411",
    "sg:province":"Rheinland-Pfalz",
    "wof:name":"Adler-apotheke Michael Kn\u00fcttel",
    "wof:placetype":"venue"
},
  "geometry": {"coordinates":[6.946738,49.655354],"type":"Point"}
}