{
  "type": "Feature",
  "properties": {
    "iso:country":"DE",
    "sg:address":"Tarunstr. 23",
    "sg:city":"Mosbach",
    "sg:phone":"+49 6261/893131",
    "sg:postcode":"74821",
    "sg:province":"Baden-W\u00fcrttemberg",
    "wof:name":"Dr. Hans Karl Hach Patentanwalt",
    "wof:placetype":"venue"
},
  "geometry": {"coordinates":[9.141412735,49.3705368042],"type":"Point"}
}