{
  "type": "Feature",
  "properties": {
    "iso:country":"DE",
    "sg:address":"Worringer Platz 11",
    "sg:city":"D\u00fcsseldorf",
    "sg:phone":"+49 211/356435",
    "sg:postcode":"40210",
    "sg:province":"Nordrhein-Westfalen",
    "wof:name":"Punkt-apotheke",
    "wof:placetype":"venue"
},
  "geometry": {"coordinates":[6.795311,51.223579],"type":"Point"}
}