{
  "type": "Feature",
  "properties": {
    "iso:country":"DE",
    "sg:address":"Kalzhofer Str. 30",
    "sg:city":"Oberstaufen",
    "sg:phone":"+49 8386/93290",
    "sg:postcode":"87534",
    "sg:province":"Bayern",
    "wof:name":"Riedle Verwaltungs Gmbh",
    "wof:placetype":"venue"
},
  "geometry": {"coordinates":[10.028244,47.558662],"type":"Point"}
}