{
  "type": "Feature",
  "properties": {
    "iso:country":"DE",
    "sg:address":"Am Nordbahnhof 13",
    "sg:city":"Schwalmstadt",
    "sg:phone":"+49 6691/94600",
    "sg:postcode":"34613",
    "sg:province":"Hessen",
    "wof:name":"Druck Service Ordermann & Reuter Gmbh",
    "wof:placetype":"venue"
},
  "geometry": {"coordinates":[9.2300424576,50.9243392944],"type":"Point"}
}