{
  "type": "Feature",
  "properties": {
    "iso:country":"DE",
    "sg:address":"Fritz-Hornschuch-Str.2",
    "sg:city":"Kulmbach",
    "sg:phone":"+49 9221/2048",
    "sg:postcode":"95326",
    "sg:province":"Bayern",
    "wof:name":"Dresdner Bank",
    "wof:placetype":"venue"
},
  "geometry": {"coordinates":[11.45291,50.10762],"type":"Point"}
}