{
  "type": "Feature",
  "properties": {
    "iso:country":"DE",
    "sg:address":"Eckenbachstr. 1 A",
    "sg:city":"Eckental",
    "sg:phone":"+49 9126/1001",
    "sg:postcode":"90542",
    "sg:province":"Bayern",
    "wof:name":"Rorich Collection Inh. Dieter Rorich",
    "wof:placetype":"venue"
},
  "geometry": {"coordinates":[11.2116451263,49.5781936646],"type":"Point"}
}