{
  "type": "Feature",
  "properties": {
    "iso:country":"DE",
    "sg:address":"Am Bahnhof 7",
    "sg:city":"Bad Soden",
    "sg:phone":"+49 6196/61004",
    "sg:postcode":"65812",
    "sg:province":"Hessen",
    "wof:name":"Sedes Immobilienvermietung Gmbh",
    "wof:placetype":"venue"
},
  "geometry": {"coordinates":[8.5032501221,50.1441802979],"type":"Point"}
}