{
  "type": "Feature",
  "properties": {
    "iso:country":"DE",
    "sg:address":"Leibnizstr. 14",
    "sg:city":"H\u00f6chberg",
    "sg:phone":"+49 931/48786",
    "sg:postcode":"97204",
    "sg:province":"Bayern",
    "wof:name":"Pritzl Reinigung Gmbh & Co. Kg",
    "wof:placetype":"venue"
},
  "geometry": {"coordinates":[9.86514,49.769531],"type":"Point"}
}