{
  "type": "Feature",
  "properties": {
    "iso:country":"DE",
    "sg:address":"Rehlinger Str. 19",
    "sg:city":"Beckingen",
    "sg:phone":"+49 6835/92310",
    "sg:postcode":"66701",
    "sg:province":"Saarland",
    "wof:name":"G\u00fcnther Kaiser Holz-u. Betonfertigteile Gmbh",
    "wof:placetype":"venue"
},
  "geometry": {"coordinates":[6.693325,49.385876],"type":"Point"}
}