{
  "type": "Feature",
  "properties": {
    "iso:country":"DE",
    "sg:address":"Samuel - Schmidt - Str.6",
    "sg:city":"Coburg",
    "sg:phone":"+49 9563",
    "sg:postcode":"96450",
    "sg:province":"Bayern",
    "wof:name":"Die Internetplattform Fuer Kuenstler Und Musiker",
    "wof:placetype":"venue"
},
  "geometry": {"coordinates":[10.960587,50.246948],"type":"Point"}
}