{
  "type": "Feature",
  "properties": {
    "iso:country":"DE",
    "sg:address":"Amalienstr. 7",
    "sg:city":"Hamburg",
    "sg:phone":"+49 40/778197",
    "sg:postcode":"21073",
    "sg:province":"Hamburg",
    "wof:name":"Hans Fischer",
    "wof:placetype":"venue"
},
  "geometry": {"coordinates":[9.984194,53.458817],"type":"Point"}
}