{
  "type": "Feature",
  "properties": {
    "iso:country":"DE",
    "sg:address":"Markt 17",
    "sg:city":"Naumburg",
    "sg:phone":"+49 3445/208688",
    "sg:postcode":"06618",
    "sg:province":"Sachsen-Anhalt",
    "wof:name":"Zeitungsverlag Naumburg Nebra Gmbh & Co. Kg",
    "wof:placetype":"venue"
},
  "geometry": {"coordinates":[11.8092517853,51.1529197693],"type":"Point"}
}