{
  "type": "Feature",
  "properties": {
    "iso:country":"DE",
    "sg:address":"Kandelstr. 65",
    "sg:city":"Emmendingen",
    "sg:phone":"+49 7641/5097",
    "sg:postcode":"79312",
    "sg:province":"Baden-W\u00fcrttemberg",
    "wof:name":"Martin B\u00e4r Rechtsanwalt",
    "wof:placetype":"venue"
},
  "geometry": {"coordinates":[7.859164238,48.1189727783],"type":"Point"}
}