{
  "type": "Feature",
  "properties": {
    "iso:country":"DE",
    "sg:address":"Bayreuther Str. 106",
    "sg:city":"Forchheim",
    "sg:phone":"+49 9191/13847",
    "sg:postcode":"91301",
    "sg:province":"Bayern",
    "wof:name":"Peter Schneider Tennislehrer",
    "wof:placetype":"venue"
},
  "geometry": {"coordinates":[11.0931100845,49.7149124146],"type":"Point"}
}