{
  "type": "Feature",
  "properties": {
    "iso:country":"DE",
    "sg:address":"Boschstr. 19",
    "sg:city":"Kleve",
    "sg:phone":"+49 2821/13071",
    "sg:postcode":"47533",
    "sg:province":"Nordrhein-Westfalen",
    "wof:name":"Elektroboehmer Gmbh Zweigniederlassung Kleve",
    "wof:placetype":"venue"
},
  "geometry": {"coordinates":[6.1431398392,51.8066215515],"type":"Point"}
}