{
  "type": "Feature",
  "properties": {
    "iso:country":"DE",
    "sg:address":"Hespertal 11",
    "sg:city":"Essen",
    "sg:phone":"+49 201/6159100",
    "sg:postcode":"45239",
    "sg:province":"Nordrhein-Westfalen",
    "wof:name":"Eventage Gmbh",
    "wof:placetype":"venue"
},
  "geometry": {"coordinates":[7.03844,51.38142],"type":"Point"}
}