{
  "type": "Feature",
  "properties": {
    "iso:country":"DE",
    "sg:address":"F\u00f6hrenweg 34",
    "sg:city":"Forchheim",
    "sg:phone":"+49 9191/4774",
    "sg:postcode":"91301",
    "sg:province":"Bayern",
    "wof:name":"West-apotheke Apotheker Wolfram Bleile",
    "wof:placetype":"venue"
},
  "geometry": {"coordinates":[11.049556,49.724606],"type":"Point"}
}