{
  "type": "Feature",
  "properties": {
    "iso:country":"DE",
    "sg:address":"Hildener Str. 11",
    "sg:city":"Erkrath",
    "sg:phone":"+49 2104/31423",
    "sg:postcode":"40699",
    "sg:province":"Nordrhein-Westfalen",
    "wof:name":"H. Conradi",
    "wof:placetype":"venue"
},
  "geometry": {"coordinates":[6.944056,51.217934],"type":"Point"}
}