{
  "type": "Feature",
  "properties": {
    "iso:country":"DE",
    "sg:address":"Sittarder Str. 89",
    "sg:city":"Viersen",
    "sg:phone":"+49 2162/14271",
    "sg:postcode":"41748",
    "sg:province":"Nordrhein-Westfalen",
    "wof:name":"L. Schattenkerk",
    "wof:placetype":"venue"
},
  "geometry": {"coordinates":[6.399596,51.268108],"type":"Point"}
}