{
  "type": "Feature",
  "properties": {
    "iso:country":"DE",
    "sg:address":"An der Autobahn 6",
    "sg:city":"Frankenberg",
    "sg:phone":"+49 37206/770",
    "sg:postcode":"09669",
    "sg:province":"Sachsen",
    "wof:name":"Schelle Gmbh",
    "wof:placetype":"venue"
},
  "geometry": {"coordinates":[13.0399446487,50.9184913635],"type":"Point"}
}