{
  "type": "Feature",
  "properties": {
    "iso:country":"DE",
    "sg:address":"Ludwig-Reinheimer-Str. 30",
    "sg:city":"Frankfurt",
    "sg:phone":"+49 69/505148",
    "sg:postcode":"60439",
    "sg:province":"Hessen",
    "wof:name":"Comtext Gmbh",
    "wof:placetype":"venue"
},
  "geometry": {"coordinates":[8.6384811401,50.1650466919],"type":"Point"}
}