{
  "type": "Feature",
  "properties": {
    "iso:country":"DE",
    "sg:address":"Schaezlerstr. 17",
    "sg:city":"Augsburg",
    "sg:phone":"+49 821/33400",
    "sg:postcode":"86150",
    "sg:province":"Bayern",
    "wof:name":"Gl\u00fcck Und Lutzenberger Rechtsanw\u00e4lte",
    "wof:placetype":"venue"
},
  "geometry": {"coordinates":[10.8917713165,48.3685913086],"type":"Point"}
}