{
  "type": "Feature",
  "properties": {
    "iso:country":"DE",
    "sg:address":"Bahnhofstr. 7",
    "sg:city":"Meudt",
    "sg:phone":"+49 6435/8138",
    "sg:postcode":"56414",
    "sg:province":"Rheinland-Pfalz",
    "wof:name":"Mehrzweckhalle Meudt",
    "wof:placetype":"venue"
},
  "geometry": {"coordinates":[7.897997,50.491692],"type":"Point"}
}