{
  "type": "Feature",
  "properties": {
    "iso:country":"DE",
    "sg:address":"Dr.-Konrad-Adenauer Str. 1",
    "sg:city":"Walld\u00fcrn",
    "sg:phone":"+49 4962/8292270",
    "sg:postcode":"74731",
    "sg:province":"Baden-W\u00fcrttemberg",
    "wof:name":"Quasar Microcomputer Hard- U. Software Gmbh",
    "wof:placetype":"venue"
},
  "geometry": {"coordinates":[9.3709030151,49.5899238586],"type":"Point"}
}