{
  "type": "Feature",
  "properties": {
    "iso:country":"DE",
    "sg:address":"Zur Aue 79",
    "sg:city":"Pohlheim",
    "sg:phone":"+49 6403/67264",
    "sg:postcode":"35415",
    "sg:province":"Hessen",
    "wof:name":"Hartmut Kolmer Ingenieur",
    "wof:placetype":"venue"
},
  "geometry": {"coordinates":[8.7105197906,50.5363578796],"type":"Point"}
}