{
  "type": "Feature",
  "properties": {
    "iso:country":"DE",
    "sg:address":"S\u00f6mmerringstr. 7",
    "sg:city":"Frankfurt",
    "sg:phone":"+49 69/5978731",
    "sg:postcode":"60322",
    "sg:province":"Hessen",
    "wof:name":"H. Walter Ingenieur",
    "wof:placetype":"venue"
},
  "geometry": {"coordinates":[8.6806373596,50.1233940125],"type":"Point"}
}