{
  "type": "Feature",
  "properties": {
    "iso:country":"DE",
    "sg:address":"Rosentalstr. 7",
    "sg:city":"Minden",
    "sg:phone":"+49 571/26747",
    "sg:postcode":"32423",
    "sg:province":"Nordrhein-Westfalen",
    "wof:name":"Wilhlem Schnelle Gmbh & Co. Kg",
    "wof:placetype":"venue"
},
  "geometry": {"coordinates":[8.917574,52.294437],"type":"Point"}
}