{
  "type": "Feature",
  "properties": {
    "iso:country":"DE",
    "sg:address":"Hamburger Str. 116",
    "sg:city":"Ammersbek",
    "sg:phone":"+49 40/6048119",
    "sg:postcode":"22949",
    "sg:province":"Schleswig-Holstein",
    "wof:name":"Wolfgang Kothe",
    "wof:placetype":"venue"
},
  "geometry": {"coordinates":[10.142561,53.676704],"type":"Point"}
}