{
  "type": "Feature",
  "properties": {
    "iso:country":"DE",
    "sg:address":"Polsumer Str. 88",
    "sg:city":"Marl",
    "sg:phone":"+49 2365/15292",
    "sg:postcode":"45768",
    "sg:province":"Nordrhein-Westfalen",
    "wof:name":"Kupferkrug",
    "wof:placetype":"venue"
},
  "geometry": {"coordinates":[7.0662298203,51.6369094849],"type":"Point"}
}