{
  "type": "Feature",
  "properties": {
    "iso:country":"DE",
    "sg:address":"Wustermarker Stra\u00dfe 1",
    "sg:city":"Brieselang",
    "sg:phone":"+49 33232/36045",
    "sg:postcode":"14656",
    "sg:province":"Brandenburg",
    "wof:name":"Dr. Sattler & Partner Gmbh",
    "wof:placetype":"venue"
},
  "geometry": {"coordinates":[13.0011034012,52.5821456909],"type":"Point"}
}