{
  "type": "Feature",
  "properties": {
    "iso:country":"DE",
    "sg:address":"Monplaisirstr. 33",
    "sg:city":"Barby",
    "sg:postcode":"39249",
    "sg:province":"Sachsen-Anhalt",
    "wof:name":"Overbeck Termintransport Kg",
    "wof:placetype":"venue"
},
  "geometry": {"coordinates":[11.8733892441,51.9882011414],"type":"Point"}
}