{
  "type": "Feature",
  "properties": {
    "iso:country":"DE",
    "sg:address":"Berliner Str. 13",
    "sg:city":"Schortens",
    "sg:phone":"+49 4423/7382",
    "sg:postcode":"26419",
    "sg:province":"Niedersachsen",
    "wof:name":"Sylke Trommershausen",
    "wof:placetype":"venue"
},
  "geometry": {"coordinates":[7.9866991043,53.5546188354],"type":"Point"}
}