{
  "type": "Feature",
  "properties": {
    "iso:country":"DE",
    "sg:address":"Taunusstr.34",
    "sg:city":"Offenbach",
    "sg:phone":"+49 69",
    "sg:postcode":"63067",
    "sg:province":"Hessen",
    "wof:name":"Walter Grafik Design",
    "wof:placetype":"venue"
},
  "geometry": {"coordinates":[8.753553,50.109062],"type":"Point"}
}