{
  "type": "Feature",
  "properties": {
    "iso:country":"DE",
    "sg:address":"Dammsteinstr 6",
    "sg:city":"Reichenbach",
    "sg:phone":"+49 3765/559080",
    "sg:postcode":"08468",
    "sg:province":"Sachsen",
    "wof:name":"Schlosserei- Und Metallgestaltung",
    "wof:placetype":"venue"
},
  "geometry": {"coordinates":[12.287517,50.626587],"type":"Point"}
}