{
  "type": "Feature",
  "properties": {
    "iso:country":"DE",
    "sg:address":"Dorfstr 16",
    "sg:city":"Vaterstetten",
    "sg:phone":"+49 8106/36300",
    "sg:postcode":"85591",
    "sg:province":"Bayern",
    "wof:name":"Schweitzer & P\u00f6ltl Gmbh",
    "wof:placetype":"venue"
},
  "geometry": {"coordinates":[11.7728786469,48.111164093],"type":"Point"}
}