{
  "type": "Feature",
  "properties": {
    "iso:country":"DE",
    "sg:address":"Salzwedeler Str. 1",
    "sg:city":"Brome",
    "sg:phone":"+49 5833/285",
    "sg:postcode":"38465",
    "sg:province":"Niedersachsen",
    "wof:name":"Adolf M\u00fcller",
    "wof:placetype":"venue"
},
  "geometry": {"coordinates":[10.9441862106,52.6044464111],"type":"Point"}
}