{
  "type": "Feature",
  "properties": {
    "iso:country":"DE",
    "sg:address":"Dorfstr. 42",
    "sg:city":"Glienecke",
    "sg:phone":"+49 33830/60080",
    "sg:postcode":"14793",
    "sg:province":"Brandenburg",
    "wof:name":"Steffis",
    "wof:placetype":"venue"
},
  "geometry": {"coordinates":[12.378651619,52.277469635],"type":"Point"}
}