{
  "type": "Feature",
  "properties": {
    "iso:country":"DE",
    "sg:address":"\u00dcberseering 5-9",
    "sg:city":"Hamburg",
    "sg:phone":"+49 40/6305001",
    "sg:postcode":"22297",
    "sg:province":"Hamburg",
    "wof:name":"T\u00f6dt Rundfunk- Und Fernsehtechnik Gmbh",
    "wof:placetype":"venue"
},
  "geometry": {"coordinates":[10.0248203278,53.6029472351],"type":"Point"}
}