{
  "type": "Feature",
  "properties": {
    "iso:country":"DE",
    "sg:address":"Daimlerstr. 75 a",
    "sg:city":"Hamburg",
    "sg:phone":"+49 40/8100081",
    "sg:postcode":"22761",
    "sg:province":"Hamburg",
    "wof:name":"Ottmar Muss",
    "wof:placetype":"venue"
},
  "geometry": {"coordinates":[9.9198141098,53.5623207092],"type":"Point"}
}