{
  "type": "Feature",
  "properties": {
    "iso:country":"DE",
    "sg:address":"Steigerwaldstr. 8",
    "sg:city":"Uehlfeld",
    "sg:phone":"+49 9163/8900",
    "sg:postcode":"91486",
    "sg:province":"Bayern",
    "wof:name":"Heinritz & Lechner Gmbh",
    "wof:placetype":"venue"
},
  "geometry": {"coordinates":[10.715988,49.667313],"type":"Point"}
}