{
  "type": "Feature",
  "properties": {
    "iso:country":"DE",
    "sg:address":"Georgstr. 17",
    "sg:city":"Gro\u00df-Gerau",
    "sg:phone":"+49 6152/57941",
    "sg:postcode":"64521",
    "sg:province":"Hessen",
    "wof:name":"W. Metzger",
    "wof:placetype":"venue"
},
  "geometry": {"coordinates":[8.481332,49.927937],"type":"Point"}
}