{
  "type": "Feature",
  "properties": {
    "iso:country":"DE",
    "sg:address":"Postfach 1454",
    "sg:city":"Tettnang",
    "sg:postcode":"88063",
    "sg:province":"Baden-W\u00fcrttemberg",
    "wof:name":"Wlz Obstgro\u00dfmarkt",
    "wof:placetype":"venue"
},
  "geometry": {"coordinates":[9.5860738754,47.6704788208],"type":"Point"}
}