{
  "type": "Feature",
  "properties": {
    "iso:country":"DE",
    "sg:address":"Lange Br\u00fcckstr. 1",
    "sg:city":"Preetz",
    "sg:phone":"+49 4342/2939",
    "sg:postcode":"24211",
    "sg:province":"Schleswig-Holstein",
    "wof:name":"Wohnboutique Am Markt Gmbh",
    "wof:placetype":"venue"
},
  "geometry": {"coordinates":[10.2820148468,54.2353210449],"type":"Point"}
}