{
  "type": "Feature",
  "properties": {
    "iso:country":"DE",
    "sg:address":"Oskar-Mayer Str.12",
    "sg:city":"Noerdlingen",
    "sg:phone":"+49 9081/4428",
    "sg:postcode":"86720",
    "sg:province":"Bayern",
    "wof:name":"Allianz-schreil",
    "wof:placetype":"venue"
},
  "geometry": {"coordinates":[10.4928426743,48.8468856812],"type":"Point"}
}