{
  "type": "Feature",
  "properties": {
    "iso:country":"DE",
    "sg:address":"Gro\u00dfe Elbstr. 279",
    "sg:city":"Hamburg",
    "sg:postcode":"22767",
    "sg:province":"Hamburg",
    "wof:name":"Verwaltungsges. Vitamin E Events Und Emotion Mbh",
    "wof:placetype":"venue"
},
  "geometry": {"coordinates":[9.926387,53.544304],"type":"Point"}
}