{
  "type": "Feature",
  "properties": {
    "iso:country":"DE",
    "sg:address":"G\u00e4rtnerplatz 2",
    "sg:city":"M\u00fcnchen",
    "sg:phone":"+49 89/2016050",
    "sg:postcode":"80469",
    "sg:province":"Bayern",
    "wof:name":"Classic",
    "wof:placetype":"venue"
},
  "geometry": {"coordinates":[11.5765390396,48.131565094],"type":"Point"}
}