{
  "type": "Feature",
  "properties": {
    "iso:country":"DE",
    "sg:address":"Hauptstr. 44",
    "sg:city":"M\u00f6nchengladbach",
    "sg:phone":"+49 2166/41170",
    "sg:postcode":"41236",
    "sg:province":"Nordrhein-Westfalen",
    "wof:name":"Reformhaus Goll Gmbh",
    "wof:placetype":"venue"
},
  "geometry": {"coordinates":[6.4438619614,51.1680145264],"type":"Point"}
}