{
  "type": "Feature",
  "properties": {
    "iso:country":"DE",
    "sg:address":"Fritz-Henkel-Str. 52",
    "sg:city":"Biedenkopf",
    "sg:phone":"+49 6461/98500",
    "sg:postcode":"35216",
    "sg:province":"Hessen",
    "wof:name":"Krause Und Thomas",
    "wof:placetype":"venue"
},
  "geometry": {"coordinates":[8.4790468216,50.9288368225],"type":"Point"}
}