{
  "type": "Feature",
  "properties": {
    "iso:country":"DE",
    "sg:address":"Max-Planck-Str. 20",
    "sg:city":"Helmbrechts",
    "sg:phone":"+49 9252/99120",
    "sg:postcode":"95233",
    "sg:province":"Bayern",
    "wof:name":"Maschinenbau Herzog Gmbh",
    "wof:placetype":"venue"
},
  "geometry": {"coordinates":[11.721022,50.231594],"type":"Point"}
}