{
  "type": "Feature",
  "properties": {
    "iso:country":"DE",
    "sg:address":"Dr.-Wilhelm-K\u00fclz-Str. 1",
    "sg:city":"Zella-Mehlis",
    "sg:phone":"+49 3682/482334",
    "sg:postcode":"98544",
    "sg:province":"Th\u00fcringen",
    "wof:name":"Wolf-dieter Reinhardt",
    "wof:placetype":"venue"
},
  "geometry": {"coordinates":[10.6724872589,50.6547012329],"type":"Point"}
}