{
  "type": "Feature",
  "properties": {
    "iso:country":"DE",
    "sg:address":"Am Bahnhof 1",
    "sg:city":"Pulsnitz",
    "sg:phone":"+49 35955/72433",
    "sg:postcode":"01896",
    "sg:province":"Sachsen",
    "wof:name":"Bahnhofsgastst\u00e4tte",
    "wof:placetype":"venue"
},
  "geometry": {"coordinates":[14.0138196945,51.1874008179],"type":"Point"}
}