{
  "type": "Feature",
  "properties": {
    "iso:country":"DE",
    "sg:address":"Hauptstr. 34",
    "sg:city":"Oberried",
    "sg:phone":"+49 7661/5024",
    "sg:postcode":"79254",
    "sg:province":"Baden-W\u00fcrttemberg",
    "wof:name":"Heinz K\u00fcst",
    "wof:placetype":"venue"
},
  "geometry": {"coordinates":[7.952922,47.934235],"type":"Point"}
}