{
  "type": "Feature",
  "properties": {
    "iso:country":"DE",
    "sg:address":"Kaiser-Friedrich-Str. 266",
    "sg:city":"Duisburg",
    "sg:phone":"+49 203/591905",
    "sg:postcode":"47167",
    "sg:province":"Nordrhein-Westfalen",
    "wof:name":"R\u00fchl",
    "wof:placetype":"venue"
},
  "geometry": {"coordinates":[6.790515,51.509045],"type":"Point"}
}