{
  "type": "Feature",
  "properties": {
    "iso:country":"DE",
    "sg:address":"Forststr. 37",
    "sg:city":"Hilden",
    "sg:phone":"+49 2103/58860",
    "sg:postcode":"40721",
    "sg:province":"Nordrhein-Westfalen",
    "wof:name":"Nord-alarm Nordrhein-westfalen Gesellschaft F\u00fcr Alarm- Und",
    "wof:placetype":"venue"
},
  "geometry": {"coordinates":[6.902878,51.168236],"type":"Point"}
}