{
  "type": "Feature",
  "properties": {
    "iso:country":"DE",
    "sg:address":"Schwarzer Weg 102",
    "sg:city":"Borken",
    "sg:phone":"+49 2862/1467",
    "sg:postcode":"46325",
    "sg:province":"Nordrhein-Westfalen",
    "wof:name":"Franz Kemper Architekt",
    "wof:placetype":"venue"
},
  "geometry": {"coordinates":[6.817187,51.892002],"type":"Point"}
}