{
  "type": "Feature",
  "properties": {
    "iso:country":"DE",
    "sg:address":"Im Dorfe 12",
    "sg:city":"Rohrbach",
    "sg:phone":"+49 36451/494",
    "sg:postcode":"99439",
    "sg:province":"Th\u00fcringen",
    "wof:name":"H. Schmidt",
    "wof:placetype":"venue"
},
  "geometry": {"coordinates":[11.398632,51.066612],"type":"Point"}
}