{
  "type": "Feature",
  "properties": {
    "iso:country":"DE",
    "sg:address":"Bergstr. 24",
    "sg:city":"Selfkant",
    "sg:phone":"+49 2456/2548",
    "sg:postcode":"52538",
    "sg:province":"Nordrhein-Westfalen",
    "wof:name":"P. Und C. Kleuters",
    "wof:placetype":"venue"
},
  "geometry": {"coordinates":[5.9158420563,50.981300354],"type":"Point"}
}