{
  "type": "Feature",
  "properties": {
    "iso:country":"DE",
    "sg:address":"Gr\u00fcndleinsstr. 5",
    "sg:city":"Volkach",
    "sg:phone":"+49 9381/9714",
    "sg:postcode":"97332",
    "sg:province":"Bayern",
    "wof:name":"Karl Englert",
    "wof:placetype":"venue"
},
  "geometry": {"coordinates":[10.254240036,49.8725700378],"type":"Point"}
}