{
  "type": "Feature",
  "properties": {
    "iso:country":"DE",
    "sg:address":"Kohlenstr. 213",
    "sg:city":"Bochum",
    "sg:phone":"+49 234/18265",
    "sg:postcode":"44793",
    "sg:province":"Nordrhein-Westfalen",
    "wof:name":"Mustafa Akbas",
    "wof:placetype":"venue"
},
  "geometry": {"coordinates":[7.1921319962,51.4770011902],"type":"Point"}
}