{
  "type": "Feature",
  "properties": {
    "iso:country":"DE",
    "sg:address":"Friedrich-Reinhardt-Str. 4",
    "sg:city":"Fichtenberg",
    "sg:phone":"+49 7971/7096",
    "sg:postcode":"74427",
    "sg:province":"Baden-W\u00fcrttemberg",
    "wof:name":"Keppeler-technische Entwicklung Gmbh",
    "wof:placetype":"venue"
},
  "geometry": {"coordinates":[9.7057504654,48.9882774353],"type":"Point"}
}