{
  "type": "Feature",
  "properties": {
    "iso:country":"DE",
    "sg:address":"Kronsforder Allee 16",
    "sg:city":"L\u00fcbeck",
    "sg:phone":"+49 451/702740",
    "sg:postcode":"23560",
    "sg:province":"Schleswig-Holstein",
    "wof:name":"Dalloz Safety Gmbh",
    "wof:placetype":"venue"
},
  "geometry": {"coordinates":[10.6881980896,53.8540725708],"type":"Point"}
}