{
  "type": "Feature",
  "properties": {
    "iso:country":"DE",
    "sg:address":"Am Stein 4",
    "sg:city":"Poppenhausen",
    "sg:phone":"+49 6658/353",
    "sg:postcode":"36163",
    "sg:province":"Hessen",
    "wof:name":"Siegfried Molter",
    "wof:placetype":"venue"
},
  "geometry": {"coordinates":[9.864373,50.489517],"type":"Point"}
}