{
  "type": "Feature",
  "properties": {
    "iso:country":"DE",
    "sg:address":"Riegerplatz 3",
    "sg:city":"Darmstadt",
    "sg:phone":"+49 6151/781897",
    "sg:postcode":"64289",
    "sg:province":"Hessen",
    "wof:name":"Restaurant Baiyok Thai",
    "wof:placetype":"venue"
},
  "geometry": {"coordinates":[8.6614589691,49.8805389404],"type":"Point"}
}