{
  "type": "Feature",
  "properties": {
    "iso:country":"DE",
    "sg:address":"Friedrich-Ebert-Str. 144",
    "sg:city":"Duisburg",
    "sg:phone":"+49 203/401443",
    "sg:postcode":"47179",
    "sg:province":"Nordrhein-Westfalen",
    "wof:name":"Reisegalerie Reisevermittlungs Gmbh & Co.",
    "wof:placetype":"venue"
},
  "geometry": {"coordinates":[6.7429389954,51.5261573792],"type":"Point"}
}