{
  "type": "Feature",
  "properties": {
    "iso:country":"DE",
    "sg:address":"Torgauer Str. 59-61",
    "sg:city":"Annaburg",
    "sg:phone":"+49 35385/7090",
    "sg:postcode":"06925",
    "sg:province":"Sachsen-Anhalt",
    "wof:name":"Annaburger Nutzfahrzeug Gmbh",
    "wof:placetype":"venue"
},
  "geometry": {"coordinates":[13.035612,51.724651],"type":"Point"}
}