{
  "type": "Feature",
  "properties": {
    "iso:country":"DE",
    "sg:address":"Wenceslaigasse 40",
    "sg:city":"Wurzen",
    "sg:phone":"+49 3425/815537",
    "sg:postcode":"04808",
    "sg:province":"Sachsen",
    "wof:name":"Hans-georg Schimkus",
    "wof:placetype":"venue"
},
  "geometry": {"coordinates":[12.734413,51.367226],"type":"Point"}
}