{
  "type": "Feature",
  "properties": {
    "iso:country":"DE",
    "sg:address":"Ludwigstr. 77",
    "sg:city":"Bensheim",
    "sg:phone":"+49 6251/70930",
    "sg:postcode":"64625",
    "sg:province":"Hessen",
    "wof:name":"Hans-werner Labitzky Steuerberater",
    "wof:placetype":"venue"
},
  "geometry": {"coordinates":[8.6234703064,49.6957511902],"type":"Point"}
}