{
  "type": "Feature",
  "properties": {
    "iso:country":"DE",
    "sg:address":"Falkenhagener Str. 1",
    "sg:city":"Berlin",
    "sg:phone":"+49 30/3354081",
    "sg:postcode":"13585",
    "sg:province":"Berlin",
    "wof:name":"Pizzeria Pescara",
    "wof:placetype":"venue"
},
  "geometry": {"coordinates":[13.2040987015,52.54429245],"type":"Point"}
}