{
  "type": "Feature",
  "properties": {
    "iso:country":"DE",
    "sg:address":"Am Weingarten 11",
    "sg:city":"Leverkusen",
    "sg:phone":"+49 214/26210",
    "sg:postcode":"51371",
    "sg:province":"Nordrhein-Westfalen",
    "wof:name":"Wilhelm Baur Heissmangel",
    "wof:placetype":"venue"
},
  "geometry": {"coordinates":[6.9509291649,51.0511054993],"type":"Point"}
}