{
  "type": "Feature",
  "properties": {
    "iso:country":"DE",
    "sg:address":"Vluyner Platz 19",
    "sg:city":"Neukirchen-Vluyn",
    "sg:phone":"+49 2845/2040",
    "sg:postcode":"47506",
    "sg:province":"Nordrhein-Westfalen",
    "wof:name":"Provinzial Feuerversicherungs- Anstalt Der Rheinprovinz",
    "wof:placetype":"venue"
},
  "geometry": {"coordinates":[6.5309939384,51.4366722107],"type":"Point"}
}