{
  "type": "Feature",
  "properties": {
    "iso:country":"DE",
    "sg:address":"Lausitzer Strasse 1-7",
    "sg:city":"Cottbus",
    "sg:phone":"+49 355/3551225",
    "sg:postcode":"03046",
    "sg:province":"Brandenburg",
    "wof:name":"Lausitznet",
    "wof:placetype":"venue"
},
  "geometry": {"coordinates":[14.3208780289,51.7602767944],"type":"Point"}
}