{
  "type": "Feature",
  "properties": {
    "iso:country":"DE",
    "sg:address":"Palzstr. 54",
    "sg:city":"Fr\u00f6ndenberg",
    "sg:phone":"+49 2378/2293",
    "sg:postcode":"58730",
    "sg:province":"Nordrhein-Westfalen",
    "wof:name":"Ev. Pfarramt Bausenhagen",
    "wof:placetype":"venue"
},
  "geometry": {"coordinates":[7.8028640747,51.5059661865],"type":"Point"}
}