{
  "type": "Feature",
  "properties": {
    "iso:country":"DE",
    "sg:address":"Ringstr. 21",
    "sg:city":"Wemding",
    "sg:phone":"+49 9092/1585",
    "sg:postcode":"86650",
    "sg:province":"Bayern",
    "wof:name":"Erwin Fischer",
    "wof:placetype":"venue"
},
  "geometry": {"coordinates":[10.694542,48.88765],"type":"Point"}
}