{
  "type": "Feature",
  "properties": {
    "iso:country":"DE",
    "sg:address":"Dorfstr. 23",
    "sg:city":"Titting",
    "sg:phone":"+49 8423/324",
    "sg:postcode":"85135",
    "sg:province":"Bayern",
    "wof:name":"Gastst\u00e4tte Martin Kirschner",
    "wof:placetype":"venue"
},
  "geometry": {"coordinates":[11.1798591614,48.9908256531],"type":"Point"}
}