{
  "type": "Feature",
  "properties": {
    "iso:country":"DE",
    "sg:address":"Rheinstr. 28",
    "sg:city":"Maintal",
    "sg:phone":"+49 6181/441088",
    "sg:postcode":"63477",
    "sg:province":"Hessen",
    "wof:name":"Heinrich Ackermann Industrievertriebs Kg",
    "wof:placetype":"venue"
},
  "geometry": {"coordinates":[8.8454265594,50.1379318237],"type":"Point"}
}