{
  "type": "Feature",
  "properties": {
    "iso:country":"DE",
    "sg:address":"Jasminweg 9 a",
    "sg:city":"Geeste",
    "sg:postcode":"49744",
    "sg:province":"Niedersachsen",
    "wof:name":"Annemarie Klo\u00dfe Architektin",
    "wof:placetype":"venue"
},
  "geometry": {"coordinates":[7.224852,52.587788],"type":"Point"}
}