{
  "type": "Feature",
  "properties": {
    "iso:country":"DE",
    "sg:address":"Lange Str. 57",
    "sg:city":"Frankfurt",
    "sg:phone":"+49 69/590227",
    "sg:postcode":"60311",
    "sg:province":"Hessen",
    "wof:name":"Htb Hotel-treuhand- Und Beratungs-gmbh",
    "wof:placetype":"venue"
},
  "geometry": {"coordinates":[8.68342,50.112041],"type":"Point"}
}