{
  "type": "Feature",
  "properties": {
    "iso:country":"DE",
    "sg:address":"Zum Lindenrondell 10",
    "sg:city":"Calden",
    "sg:phone":"+49 5674/1338",
    "sg:postcode":"34379",
    "sg:province":"Hessen",
    "wof:name":"G\u00e4stehaus L\u00fcke",
    "wof:placetype":"venue"
},
  "geometry": {"coordinates":[9.3998346329,51.3960571289],"type":"Point"}
}