{
  "type": "Feature",
  "properties": {
    "iso:country":"DE",
    "sg:address":"Fr\u00fchlingstr. 39",
    "sg:city":"Germering",
    "sg:phone":"+49 89/848041",
    "sg:postcode":"82110",
    "sg:province":"Bayern",
    "wof:name":"Gemeinde-anzeiger",
    "wof:placetype":"venue"
},
  "geometry": {"coordinates":[11.3585186005,48.1270675659],"type":"Point"}
}