{
  "type": "Feature",
  "properties": {
    "iso:country":"DE",
    "sg:address":"Zum Mentruper Hof 4",
    "sg:city":"Hagen",
    "sg:phone":"+49 5401/98292",
    "sg:postcode":"49170",
    "sg:province":"Niedersachsen",
    "wof:name":"Frank Runde",
    "wof:placetype":"venue"
},
  "geometry": {"coordinates":[7.984622,52.19315],"type":"Point"}
}