{
  "type": "Feature",
  "properties": {
    "iso:country":"DE",
    "sg:address":"Auf Der Aue 1",
    "sg:city":"Unterellen",
    "sg:phone":"+49 4936/9279520",
    "sg:postcode":"99819",
    "sg:province":"Th\u00fcringen",
    "wof:name":"Bernhard Sch\u00c4fer Gmbh",
    "wof:placetype":"venue"
},
  "geometry": {"coordinates":[10.202863,50.912926],"type":"Point"}
}