{
  "type": "Feature",
  "properties": {
    "iso:country":"DE",
    "sg:address":"M\u00fchlbachstr. 11",
    "sg:city":"Bodman-Ludwigshafen",
    "sg:phone":"+49 7773/920030",
    "sg:postcode":"78351",
    "sg:province":"Baden-W\u00fcrttemberg",
    "wof:name":"Sinner Holzbau",
    "wof:placetype":"venue"
},
  "geometry": {"coordinates":[9.0564889908,47.8189697266],"type":"Point"}
}