{
  "type": "Feature",
  "properties": {
    "iso:country":"DE",
    "sg:address":"Stublacher Platz 15",
    "sg:city":"Gera",
    "sg:phone":"+49 365/4204244",
    "sg:postcode":"07552",
    "sg:province":"Th\u00fcringen",
    "wof:name":"Ehrlich-baumschulen-gmbh",
    "wof:placetype":"venue"
},
  "geometry": {"coordinates":[12.041866,50.919964],"type":"Point"}
}