{
  "type": "Feature",
  "properties": {
    "iso:country":"DE",
    "sg:address":"Lange Str. 162",
    "sg:city":"Langenau",
    "sg:phone":"+49 7345/5279",
    "sg:postcode":"89129",
    "sg:province":"Baden-W\u00fcrttemberg",
    "wof:name":"Erwin Unseld",
    "wof:placetype":"venue"
},
  "geometry": {"coordinates":[10.135083,48.503555],"type":"Point"}
}