{
  "type": "Feature",
  "properties": {
    "iso:country":"DE",
    "sg:address":"Marsbruchstr. 133",
    "sg:city":"Dortmund",
    "sg:postcode":"44287",
    "sg:province":"Nordrhein-Westfalen",
    "wof:name":"Dms Projektmanagement Gmbh",
    "wof:placetype":"venue"
},
  "geometry": {"coordinates":[7.55051,51.501423],"type":"Point"}
}