{
  "type": "Feature",
  "properties": {
    "iso:country":"DE",
    "sg:address":"Herzogsgasse 3",
    "sg:city":"Waiblingen",
    "sg:phone":"+49 7146/43808",
    "sg:postcode":"71336",
    "sg:province":"Baden-W\u00fcrttemberg",
    "wof:name":"K.-h. Bok",
    "wof:placetype":"venue"
},
  "geometry": {"coordinates":[9.3162374496,48.890460968],"type":"Point"}
}