{
  "type": "Feature",
  "properties": {
    "iso:country":"DE",
    "sg:address":"Monikastr. 103",
    "sg:city":"Euskirchen",
    "sg:phone":"+49 2251/782097",
    "sg:postcode":"53881",
    "sg:province":"Nordrhein-Westfalen",
    "wof:name":"Agnes Schuler Heilpraktikerin",
    "wof:placetype":"venue"
},
  "geometry": {"coordinates":[6.8589978218,50.6328430176],"type":"Point"}
}