{
  "type": "Feature",
  "properties": {
    "iso:country":"DE",
    "sg:address":"Pfarrgasse 1",
    "sg:city":"Waging",
    "sg:phone":"+49 8681/256",
    "sg:postcode":"83329",
    "sg:province":"Bayern",
    "wof:name":"Kath. Pfarramt St. Stephanus",
    "wof:placetype":"venue"
},
  "geometry": {"coordinates":[12.7361698151,47.9324531555],"type":"Point"}
}