{
  "type": "Feature",
  "properties": {
    "iso:country":"DE",
    "sg:address":"Alsterkrugchaussee 132",
    "sg:city":"Hamburg",
    "sg:phone":"+49 40/5111511",
    "sg:postcode":"22297",
    "sg:province":"Hamburg",
    "wof:name":"Commerzia Commercial Agency Coma Gmbh",
    "wof:placetype":"venue"
},
  "geometry": {"coordinates":[9.9898805618,53.605594635],"type":"Point"}
}