{
  "type": "Feature",
  "properties": {
    "iso:country":"DE",
    "sg:address":"Osnabr\u00fccker Str.",
    "sg:city":"Neuenkirchen-V\u00f6rden",
    "sg:phone":"+49 5495/381",
    "sg:postcode":"49434",
    "sg:province":"Niedersachsen",
    "wof:name":"Gastst\u00e4tte H. M\u00fcller",
    "wof:placetype":"venue"
},
  "geometry": {"coordinates":[8.0844898224,52.4747047424],"type":"Point"}
}