{
  "type": "Feature",
  "properties": {
    "iso:country":"DE",
    "sg:address":"Marienplatz 11/ I. Stock",
    "sg:city":"M\u00fcnchen",
    "sg:phone":"+49 89/223703",
    "sg:postcode":"80331",
    "sg:province":"Bayern",
    "wof:name":"Abr-amtliches Bayrisches Reiseb\u00fcro Gmbh & Co. Kg",
    "wof:placetype":"venue"
},
  "geometry": {"coordinates":[11.5775260925,48.1364173889],"type":"Point"}
}