{
  "type": "Feature",
  "properties": {
    "iso:country":"DE",
    "sg:address":"Amselweg 8",
    "sg:city":"M\u00fchlheim am main",
    "sg:phone":"+49 6108/68089",
    "sg:postcode":"63165",
    "sg:province":"Hessen",
    "wof:name":"Ali Feinste Miniaturb\u00e4rchen",
    "wof:placetype":"venue"
},
  "geometry": {"coordinates":[8.8527412415,50.0925445557],"type":"Point"}
}