{
  "type": "Feature",
  "properties": {
    "iso:country":"DE",
    "sg:address":"Schnieglinger Str. 228",
    "sg:city":"N\u00fcrnberg",
    "sg:phone":"+49 911/313512",
    "sg:postcode":"90427",
    "sg:province":"Bayern",
    "wof:name":"Bub",
    "wof:placetype":"venue"
},
  "geometry": {"coordinates":[11.029876709,49.4675483704],"type":"Point"}
}