{
  "type": "Feature",
  "properties": {
    "iso:country":"DE",
    "sg:address":"Benrather Schlo\u00dfallee 89",
    "sg:city":"D\u00fcsseldorf",
    "sg:phone":"+49 211/7182858",
    "sg:postcode":"40597",
    "sg:province":"Nordrhein-Westfalen",
    "wof:name":"Ttcom Gesellschaft F\u00fcr Kommunikation Mbh",
    "wof:placetype":"venue"
},
  "geometry": {"coordinates":[6.866104126,51.1623916626],"type":"Point"}
}