{
  "type": "Feature",
  "properties": {
    "iso:country":"DE",
    "sg:address":"Erftwerkstr. 93",
    "sg:city":"Grevenbroich",
    "sg:phone":"+49 2181/1040",
    "sg:postcode":"41515",
    "sg:province":"Nordrhein-Westfalen",
    "wof:name":"Gerda Swart",
    "wof:placetype":"venue"
},
  "geometry": {"coordinates":[6.608799,51.084297],"type":"Point"}
}