{
  "type": "Feature",
  "properties": {
    "iso:country":"DE",
    "sg:address":"Bismarckstr. 6",
    "sg:city":"Reichenbach",
    "sg:phone":"+49 7153/51117",
    "sg:postcode":"73262",
    "sg:province":"Baden-W\u00fcrttemberg",
    "wof:name":"E. Schmidt Induktions-h\u00e4rterei",
    "wof:placetype":"venue"
},
  "geometry": {"coordinates":[9.464597702,48.7098617554],"type":"Point"}
}