{
  "type": "Feature",
  "properties": {
    "iso:country":"DE",
    "sg:address":"Endenicher Str. 95",
    "sg:city":"Bonn",
    "sg:phone":"+49 228/696996",
    "sg:postcode":"53115",
    "sg:province":"Nordrhein-Westfalen",
    "wof:name":"Anne K\u00f6nig",
    "wof:placetype":"venue"
},
  "geometry": {"coordinates":[7.0847392082,50.7329978943],"type":"Point"}
}