{
  "type": "Feature",
  "properties": {
    "iso:country":"DE",
    "sg:address":"Breiten\u00e4ckerweg 10",
    "sg:city":"Haiterbach",
    "sg:phone":"+49 7456/224",
    "sg:postcode":"72221",
    "sg:province":"Baden-W\u00fcrttemberg",
    "wof:name":"H. Und K. Killinger",
    "wof:placetype":"venue"
},
  "geometry": {"coordinates":[8.643997,48.519012],"type":"Point"}
}