{
  "type": "Feature",
  "properties": {
    "iso:country":"DE",
    "sg:address":"Am Sandkasten 80",
    "sg:city":"Leezdorf",
    "sg:phone":"+49 4934/1485",
    "sg:postcode":"26529",
    "sg:province":"Niedersachsen",
    "wof:name":"Leezdorfer Hof",
    "wof:placetype":"venue"
},
  "geometry": {"coordinates":[7.294344902,53.5497894287],"type":"Point"}
}