{
  "type": "Feature",
  "properties": {
    "iso:country":"DE",
    "sg:address":"Klosterstr. 19",
    "sg:city":"Titz",
    "sg:phone":"+49 2463/5816",
    "sg:postcode":"52445",
    "sg:province":"Nordrhein-Westfalen",
    "wof:name":"Norbert Becker",
    "wof:placetype":"venue"
},
  "geometry": {"coordinates":[6.459646,50.967304],"type":"Point"}
}