{
  "type": "Feature",
  "properties": {
    "iso:country":"DE",
    "sg:address":"Dorfstra\u00dfe 31",
    "sg:city":"Klein D\u00fcben",
    "sg:phone":"+49 35600/7030",
    "sg:postcode":"03130",
    "sg:province":"Brandenburg",
    "wof:name":"Foba - Glas Und Design",
    "wof:placetype":"venue"
},
  "geometry": {"coordinates":[14.619484,51.562885],"type":"Point"}
}