{
  "type": "Feature",
  "properties": {
    "iso:country":"DE",
    "sg:address":"Wendorfer Str. 6 A",
    "sg:city":"Garz",
    "sg:phone":"+49 38304/450",
    "sg:postcode":"18574",
    "sg:province":"Mecklenburg-Vorpommern",
    "wof:name":"A. Subklew",
    "wof:placetype":"venue"
},
  "geometry": {"coordinates":[13.2749252319,54.2978363037],"type":"Point"}
}