{
  "type": "Feature",
  "properties": {
    "iso:country":"DE",
    "sg:address":"Steinstr. 7",
    "sg:city":"Bonn",
    "sg:phone":"+49 228/364505",
    "sg:postcode":"53175",
    "sg:province":"Nordrhein-Westfalen",
    "wof:name":"Jakob Ring",
    "wof:placetype":"venue"
},
  "geometry": {"coordinates":[7.16413,50.698071],"type":"Point"}
}