{
  "type": "Feature",
  "properties": {
    "iso:country":"DE",
    "sg:address":"Am Waldeck 14",
    "sg:city":"Offenbach am Main",
    "sg:phone":"+49 69/89909090",
    "sg:postcode":"63073",
    "sg:province":"Hessen",
    "wof:name":"Master Immobiliengesellschaft Mbh",
    "wof:placetype":"venue"
},
  "geometry": {"coordinates":[8.7946023941,50.0832366943],"type":"Point"}
}