{
  "type": "Feature",
  "properties": {
    "iso:country":"DE",
    "sg:address":"Akazienweg 7",
    "sg:city":"Duisburg",
    "sg:phone":"+49 2151/940366",
    "sg:postcode":"47239",
    "sg:province":"Nordrhein-Westfalen",
    "wof:name":"Trafavi Gmbh",
    "wof:placetype":"venue"
},
  "geometry": {"coordinates":[6.6543221474,51.3924827576],"type":"Point"}
}