{
  "type": "Feature",
  "properties": {
    "iso:country":"DE",
    "sg:address":"Nassauer Str. 19",
    "sg:city":"Frankfurt",
    "sg:phone":"+49 69/573316",
    "sg:postcode":"60439",
    "sg:province":"Hessen",
    "wof:name":"Solber-eck",
    "wof:placetype":"venue"
},
  "geometry": {"coordinates":[8.647983551,50.161365509],"type":"Point"}
}