{
  "type": "Feature",
  "properties": {
    "iso:country":"DE",
    "sg:address":"Poststr. 2",
    "sg:city":"Metzingen",
    "sg:phone":"+49 7071/38182",
    "sg:postcode":"72555",
    "sg:province":"Baden-W\u00fcrttemberg",
    "wof:name":"A. R\u00fcmmelin",
    "wof:placetype":"venue"
},
  "geometry": {"coordinates":[9.3080329895,48.5309104919],"type":"Point"}
}