{
  "type": "Feature",
  "properties": {
    "iso:country":"DE",
    "sg:address":"Verbr\u00fcderungsring 4d",
    "sg:city":"Schwarzenbek",
    "sg:phone":"+49 4151/3455",
    "sg:postcode":"21493",
    "sg:province":"Schleswig-Holstein",
    "wof:name":"Inge Richter",
    "wof:placetype":"venue"
},
  "geometry": {"coordinates":[10.495614,53.511017],"type":"Point"}
}