{
  "type": "Feature",
  "properties": {
    "iso:country":"DE",
    "sg:address":"Kirchnerstr. 6",
    "sg:city":"Frankfurt",
    "sg:phone":"+49 69/9210950",
    "sg:postcode":"60311",
    "sg:province":"Hessen",
    "wof:name":"Ltu Reservierung",
    "wof:placetype":"venue"
},
  "geometry": {"coordinates":[8.675242424,50.1112518311],"type":"Point"}
}