{
  "type": "Feature",
  "properties": {
    "iso:country":"DE",
    "sg:address":"Im Sundern 21",
    "sg:city":"L\u00fcnen",
    "sg:phone":"+49 2306/40678",
    "sg:postcode":"44532",
    "sg:province":"Nordrhein-Westfalen",
    "wof:name":"Walter Gabelmann",
    "wof:placetype":"venue"
},
  "geometry": {"coordinates":[7.56171,51.590851],"type":"Point"}
}