{
  "type": "Feature",
  "properties": {
    "iso:country":"DE",
    "sg:address":"Hebbelstr. 24",
    "sg:city":"Straubing",
    "sg:phone":"+49 9421/3571",
    "sg:postcode":"94315",
    "sg:province":"Bayern",
    "wof:name":"Amtslader-vereinigung Krebs Meyer & Co. Gmbh",
    "wof:placetype":"venue"
},
  "geometry": {"coordinates":[12.5774621964,48.875957489],"type":"Point"}
}