{
  "type": "Feature",
  "properties": {
    "iso:country":"DE",
    "sg:address":"B\u00e4ukerweg 24",
    "sg:city":"Korbach",
    "sg:phone":"+49 5631/8537",
    "sg:postcode":"34497",
    "sg:province":"Hessen",
    "wof:name":"B. Schlichtherle",
    "wof:placetype":"venue"
},
  "geometry": {"coordinates":[8.74488,51.248779],"type":"Point"}
}