{
  "type": "Feature",
  "properties": {
    "iso:country":"DE",
    "sg:address":"Fritz-Golsen-Str. 7",
    "sg:city":"Zellertal",
    "sg:phone":"+49 6355/433",
    "sg:postcode":"67308",
    "sg:province":"Rheinland-Pfalz",
    "wof:name":"Clemens M\u00fcller",
    "wof:placetype":"venue"
},
  "geometry": {"coordinates":[8.1409063339,49.6494598389],"type":"Point"}
}