{
  "type": "Feature",
  "properties": {
    "iso:country":"DE",
    "sg:address":"Hainhaus 20",
    "sg:city":"Langenhagen",
    "sg:phone":"+49 511/775568",
    "sg:postcode":"30855",
    "sg:province":"Niedersachsen",
    "wof:name":"Friedrich-wilhelm Meyer Immobilien Verwaltungs",
    "wof:placetype":"venue"
},
  "geometry": {"coordinates":[9.7652492523,52.4861373901],"type":"Point"}
}