{
  "type": "Feature",
  "properties": {
    "iso:country":"DE",
    "sg:address":"Meyenburger Damm 1",
    "sg:city":"Schwanewede",
    "sg:phone":"+49 4209/1327",
    "sg:postcode":"28790",
    "sg:province":"Niedersachsen",
    "wof:name":"Adolf Lessner Inh. Kurt Hellmann",
    "wof:placetype":"venue"
},
  "geometry": {"coordinates":[8.5962333679,53.2718505859],"type":"Point"}
}