{
  "type": "Feature",
  "properties": {
    "iso:country":"DE",
    "sg:address":"Hochstr. 7",
    "sg:city":"Diespeck",
    "sg:phone":"+49 9161/3517",
    "sg:postcode":"91456",
    "sg:province":"Bayern",
    "wof:name":"Richard Holzberger",
    "wof:placetype":"venue"
},
  "geometry": {"coordinates":[10.6295,49.590702],"type":"Point"}
}