{
  "type": "Feature",
  "properties": {
    "iso:country":"DE",
    "sg:address":"Auf der Bierau",
    "sg:city":"Wiesbaden",
    "sg:phone":"+49 6122/95670",
    "sg:postcode":"65205",
    "sg:province":"Hessen",
    "wof:name":"Hans A. Rotter Gmbh",
    "wof:placetype":"venue"
},
  "geometry": {"coordinates":[8.354729,50.053711],"type":"Point"}
}