{
  "type": "Feature",
  "properties": {
    "iso:country":"DE",
    "sg:address":"S\u00fclmerstr. 68",
    "sg:city":"Heilbronn",
    "sg:phone":"+49 7131/80844",
    "sg:postcode":"74072",
    "sg:province":"Baden-W\u00fcrttemberg",
    "wof:name":"T. Rembold",
    "wof:placetype":"venue"
},
  "geometry": {"coordinates":[9.2210073471,49.1447143555],"type":"Point"}
}