{
  "type": "Feature",
  "properties": {
    "iso:country":"DE",
    "sg:address":"Bahnhofstr. 1",
    "sg:city":"Lengenfeld",
    "sg:phone":"+49 37606/2383",
    "sg:postcode":"08485",
    "sg:province":"Sachsen",
    "wof:name":"A & C Grillbar",
    "wof:placetype":"venue"
},
  "geometry": {"coordinates":[12.3670101166,50.5696296692],"type":"Point"}
}