{
  "type": "Feature",
  "properties": {
    "iso:country":"DE",
    "sg:address":"Toschlag 33",
    "sg:city":"K\u00f6lln-Reisiek",
    "sg:phone":"+49 4121/71939",
    "sg:postcode":"25337",
    "sg:province":"Schleswig-Holstein",
    "wof:name":"H. W\u00fcnsch Ingenieur",
    "wof:placetype":"venue"
},
  "geometry": {"coordinates":[9.6925210953,53.7601928711],"type":"Point"}
}