{
  "type": "Feature",
  "properties": {
    "iso:country":"DE",
    "sg:address":"Mollerbachstr. 32",
    "sg:city":"Oberursel",
    "sg:postcode":"61440",
    "sg:province":"Hessen",
    "wof:name":"Fr. Schr\u00f6ppel Stiftung Ggmbh",
    "wof:placetype":"venue"
},
  "geometry": {"coordinates":[8.6003112793,50.2007751465],"type":"Point"}
}