{
  "type": "Feature",
  "properties": {
    "iso:country":"DE",
    "sg:address":"Webereistr. 26",
    "sg:city":"Mannheim",
    "sg:phone":"+49 621/786034",
    "sg:postcode":"68307",
    "sg:province":"Baden-W\u00fcrttemberg",
    "wof:name":"Pizzeria Bei Gino",
    "wof:placetype":"venue"
},
  "geometry": {"coordinates":[8.4516849518,49.5395965576],"type":"Point"}
}