{
  "type": "Feature",
  "properties": {
    "iso:country":"DE",
    "sg:address":"Seehalde 45",
    "sg:city":"Winnenden",
    "sg:phone":"+49 7195/2479",
    "sg:postcode":"71364",
    "sg:province":"Baden-W\u00fcrttemberg",
    "wof:name":"Gerhard Schwegler Ingenieur",
    "wof:placetype":"venue"
},
  "geometry": {"coordinates":[9.4050598145,48.8773040771],"type":"Point"}
}