{
  "type": "Feature",
  "properties": {
    "iso:country":"DE",
    "sg:address":"Herrenwald-Kaserne",
    "sg:city":"Stadtallendorf",
    "sg:phone":"+49 6428/7556",
    "sg:postcode":"35260",
    "sg:province":"Hessen",
    "wof:name":"Christa Wehowski Bw-kantine",
    "wof:placetype":"venue"
},
  "geometry": {"coordinates":[9.0119838715,50.8300247192],"type":"Point"}
}