{
  "type": "Feature",
  "properties": {
    "iso:country":"DE",
    "sg:address":"Obere H\u00f6he 7",
    "sg:city":"Elsenfeld",
    "sg:phone":"+49 9374/7314",
    "sg:postcode":"63820",
    "sg:province":"Bayern",
    "wof:name":"Hd-stahlverbau - Bewehrungen",
    "wof:placetype":"venue"
},
  "geometry": {"coordinates":[9.2358217239,49.8466377258],"type":"Point"}
}