{
  "type": "Feature",
  "properties": {
    "iso:country":"DE",
    "sg:address":"H\u00f6lderlinstr. 11",
    "sg:city":"Delmenhorst",
    "sg:phone":"+49 4221/50214",
    "sg:postcode":"27753",
    "sg:province":"Niedersachsen",
    "wof:name":"W\u00e4rme-k\u00e4lte-schall- Brandschutzisolierung",
    "wof:placetype":"venue"
},
  "geometry": {"coordinates":[8.610995,53.06218],"type":"Point"}
}