{
  "type": "Feature",
  "properties": {
    "iso:country":"DE",
    "sg:address":"Grundsch\u00f6tteler Str. 1",
    "sg:city":"Hagen",
    "sg:postcode":"58135",
    "sg:province":"Nordrhein-Westfalen",
    "wof:name":"Mtw Handelsges. Mbh",
    "wof:placetype":"venue"
},
  "geometry": {"coordinates":[7.408659935,51.3431549072],"type":"Point"}
}