{
  "type": "Feature",
  "properties": {
    "iso:country":"DE",
    "sg:address":"Weserstr. 19",
    "sg:city":"Nienburg",
    "sg:phone":"+49 5021/86363",
    "sg:postcode":"31582",
    "sg:province":"Niedersachsen",
    "wof:name":"Psychol. Beratungsstelle F\u00fcr Kinder Und Jugendliche",
    "wof:placetype":"venue"
},
  "geometry": {"coordinates":[9.203267,52.639591],"type":"Point"}
}