{
  "type": "Feature",
  "properties": {
    "iso:country":"DE",
    "sg:address":"Lothringerstr. 108",
    "sg:city":"Aachen",
    "sg:phone":"+49 241/504709",
    "sg:postcode":"52070",
    "sg:province":"Nordrhein-Westfalen",
    "wof:name":"Winand Dohlen",
    "wof:placetype":"venue"
},
  "geometry": {"coordinates":[6.100113,50.769386],"type":"Point"}
}