{
  "type": "Feature",
  "properties": {
    "iso:country":"DE",
    "sg:address":"Im Bocketal 2",
    "sg:city":"Tecklenburg",
    "sg:phone":"+49 5455/93000",
    "sg:postcode":"49545",
    "sg:province":"Nordrhein-Westfalen",
    "wof:name":"Hotel Teutoburger Wald",
    "wof:placetype":"venue"
},
  "geometry": {"coordinates":[7.7446370125,52.2346611023],"type":"Point"}
}