{
  "type": "Feature",
  "properties": {
    "iso:country":"DE",
    "sg:address":"Eschenauer Hauptstr. 34",
    "sg:city":"Eckental",
    "sg:phone":"+49 9126/5481",
    "sg:postcode":"90542",
    "sg:province":"Bayern",
    "wof:name":"Helmut Rott",
    "wof:placetype":"venue"
},
  "geometry": {"coordinates":[11.2005615234,49.5741081238],"type":"Point"}
}