{
  "type": "Feature",
  "properties": {
    "iso:country":"DE",
    "sg:address":"Konrad-Adenauer-Str.",
    "sg:city":"Kleinblittersdorf",
    "sg:phone":"+49 6805/4571",
    "sg:postcode":"66271",
    "sg:province":"Saarland",
    "wof:name":"Dea-tankstelle",
    "wof:placetype":"venue"
},
  "geometry": {"coordinates":[7.0679988861,49.1167488098],"type":"Point"}
}