{
  "type": "Feature",
  "properties": {
    "iso:country":"DE",
    "sg:address":"Friedhofstr. 2040",
    "sg:city":"V\u00f6lklingen",
    "sg:postcode":"66333",
    "sg:province":"Saarland",
    "wof:name":"Stadtb\u00fccherei",
    "wof:placetype":"venue"
},
  "geometry": {"coordinates":[6.85627,49.251083],"type":"Point"}
}