{
  "type": "Feature",
  "properties": {
    "iso:country":"DE",
    "sg:address":"Bauernvogtei 1-3",
    "sg:city":"Reinbek",
    "sg:phone":"+49 40/7223041",
    "sg:postcode":"21465",
    "sg:province":"Schleswig-Holstein",
    "wof:name":"Treuhandgesellschaft F\u00fcr Ver- M\u00f6gensanlagen In Reinbek Mbh",
    "wof:placetype":"venue"
},
  "geometry": {"coordinates":[10.255001,53.530293],"type":"Point"}
}