{
  "type": "Feature",
  "properties": {
    "iso:country":"DE",
    "sg:address":"Langenburger Str. 19b",
    "sg:city":"Braunsbach",
    "sg:phone":"+49 7906/365",
    "sg:postcode":"74542",
    "sg:province":"Baden-W\u00fcrttemberg",
    "wof:name":"Rolf Beck",
    "wof:placetype":"venue"
},
  "geometry": {"coordinates":[9.7982034683,49.221572876],"type":"Point"}
}