{
  "type": "Feature",
  "properties": {
    "iso:country":"DE",
    "sg:address":"Steinbruchstr. 3",
    "sg:city":"Bad Berneck",
    "sg:phone":"+49 9273/353",
    "sg:postcode":"95460",
    "sg:province":"Bayern",
    "wof:name":"Hartsteinwerk K\u00fcfner Gmbh",
    "wof:placetype":"venue"
},
  "geometry": {"coordinates":[11.7150001526,50.0259017944],"type":"Point"}
}