{
  "type": "Feature",
  "properties": {
    "iso:country":"DE",
    "sg:address":"Am Fuchsberg 26",
    "sg:city":"Wunstorf",
    "sg:phone":"+49 5031/5062",
    "sg:postcode":"31515",
    "sg:province":"Niedersachsen",
    "wof:name":"Werko-k\u00fcchen Inh. Rolf Koch",
    "wof:placetype":"venue"
},
  "geometry": {"coordinates":[9.415545,52.443222],"type":"Point"}
}