{
  "type": "Feature",
  "properties": {
    "iso:country":"DE",
    "sg:address":"Moosstr. 14",
    "sg:city":"Chamerau",
    "sg:phone":"+49 9944/2361",
    "sg:postcode":"93466",
    "sg:province":"Bayern",
    "wof:name":"Altmann-bau E. K.",
    "wof:placetype":"venue"
},
  "geometry": {"coordinates":[12.799835,49.191025],"type":"Point"}
}