{
  "type": "Feature",
  "properties": {
    "iso:country":"DE",
    "sg:address":"V\u00f6rier Str. 2",
    "sg:city":"Ronnenberg",
    "sg:phone":"+49 5109/2402",
    "sg:postcode":"30952",
    "sg:province":"Niedersachsen",
    "wof:name":"Rudolf Engelke",
    "wof:placetype":"venue"
},
  "geometry": {"coordinates":[9.639572,52.290337],"type":"Point"}
}