{
  "type": "Feature",
  "properties": {
    "iso:country":"DE",
    "sg:address":"Troppauer Str. 43",
    "sg:city":"Bad W\u00f6rishofen",
    "sg:phone":"+49 8247/7064",
    "sg:postcode":"86825",
    "sg:province":"Bayern",
    "wof:name":"L. Lindl",
    "wof:placetype":"venue"
},
  "geometry": {"coordinates":[10.6189861298,48.0091514587],"type":"Point"}
}