{
  "type": "Feature",
  "properties": {
    "iso:country":"DE",
    "sg:address":"Memminger Str. 156",
    "sg:city":"Kempten",
    "sg:phone":"+49 831/94420",
    "sg:postcode":"87439",
    "sg:province":"Bayern",
    "wof:name":"Gerhard Schindler Immobilienmakler",
    "wof:placetype":"venue"
},
  "geometry": {"coordinates":[10.2761096954,47.7378005981],"type":"Point"}
}