{
  "type": "Feature",
  "properties": {
    "iso:country":"DE",
    "sg:address":"Bahng\u00e4rten 28",
    "sg:city":"Hamburg",
    "sg:phone":"+49 40/680949",
    "sg:postcode":"22041",
    "sg:province":"Hamburg",
    "wof:name":"Ksv Gastronomie Gmbh",
    "wof:placetype":"venue"
},
  "geometry": {"coordinates":[10.0760622025,53.5699653625],"type":"Point"}
}