{
  "type": "Feature",
  "properties": {
    "iso:country":"DE",
    "sg:address":"Buddestr. 115",
    "sg:city":"Krefeld",
    "sg:phone":"+49 2151/541983",
    "sg:postcode":"47809",
    "sg:province":"Nordrhein-Westfalen",
    "wof:name":"Beerdigungsinstitut Josef H\u00fcckelhoven",
    "wof:placetype":"venue"
},
  "geometry": {"coordinates":[6.611575,51.332523],"type":"Point"}
}