{
  "type": "Feature",
  "properties": {
    "iso:country":"DE",
    "sg:address":"Thomas-Mann-Str. 35",
    "sg:city":"Bonn",
    "sg:phone":"+49 228/604810",
    "sg:postcode":"53111",
    "sg:province":"Nordrhein-Westfalen",
    "wof:name":"R. Neuhaus Rechtsanwalt",
    "wof:placetype":"venue"
},
  "geometry": {"coordinates":[7.0953760147,50.7350616455],"type":"Point"}
}