{
  "type": "Feature",
  "properties": {
    "iso:country":"DE",
    "sg:address":"Industriestr.-West 4",
    "sg:city":"Haibach",
    "sg:phone":"+49 6021/610059",
    "sg:postcode":"63808",
    "sg:province":"Bayern",
    "wof:name":"Karl Heger Gmbh",
    "wof:placetype":"venue"
},
  "geometry": {"coordinates":[9.189082,49.962345],"type":"Point"}
}