{
  "type": "Feature",
  "properties": {
    "iso:country":"DE",
    "sg:address":"Bruno-Taut-Ring 18 b",
    "sg:city":"Berlin",
    "sg:phone":"+49 30/6019536",
    "sg:postcode":"12359",
    "sg:province":"Berlin",
    "wof:name":"Helmut Eckhart",
    "wof:placetype":"venue"
},
  "geometry": {"coordinates":[13.450523,52.438755],"type":"Point"}
}