{
  "type": "Feature",
  "properties": {
    "iso:country":"DE",
    "sg:address":"Friedrich-Ludwig-Jahn-Str. 29",
    "sg:city":"Sarstedt",
    "sg:postcode":"31157",
    "sg:province":"Niedersachsen",
    "wof:name":"Teppich-zentrum- Sarstedt Gmbh",
    "wof:placetype":"venue"
},
  "geometry": {"coordinates":[9.8466615677,52.236743927],"type":"Point"}
}