{
  "type": "Feature",
  "properties": {
    "iso:country":"DE",
    "sg:address":"Ringbahnstr. 14",
    "sg:city":"Berlin",
    "sg:postcode":"10711",
    "sg:province":"Berlin",
    "wof:name":"Ttc The Take Care Immobilien Gmbh & Co. Kg",
    "wof:placetype":"venue"
},
  "geometry": {"coordinates":[13.2889919281,52.4979667664],"type":"Point"}
}