{
  "type": "Feature",
  "properties": {
    "iso:country":"DE",
    "sg:address":"Heinrich-Nordhoff-Str. 53",
    "sg:city":"Wolfsburg",
    "sg:phone":"+49 5361/12055",
    "sg:postcode":"38440",
    "sg:province":"Niedersachsen",
    "wof:name":"Mundstock Zokolowski U. Wulfes Ohg",
    "wof:placetype":"venue"
},
  "geometry": {"coordinates":[10.786989212,52.4276542664],"type":"Point"}
}