{
  "type": "Feature",
  "properties": {
    "iso:country":"DE",
    "sg:address":"Rohrbacher Str. 86",
    "sg:city":"Heidelberg",
    "sg:phone":"+49 6221/182261",
    "sg:postcode":"69115",
    "sg:province":"Baden-W\u00fcrttemberg",
    "wof:name":"Weinstein",
    "wof:placetype":"venue"
},
  "geometry": {"coordinates":[8.690363884,49.3999595642],"type":"Point"}
}