{
  "type": "Feature",
  "properties": {
    "iso:country":"DE",
    "sg:address":"Osterstr. 12",
    "sg:city":"Hameln",
    "sg:phone":"+49 5151/923377",
    "sg:postcode":"31785",
    "sg:province":"Niedersachsen",
    "wof:name":"Steding",
    "wof:placetype":"venue"
},
  "geometry": {"coordinates":[9.3590087891,52.1046295166],"type":"Point"}
}