{
  "type": "Feature",
  "properties": {
    "iso:country":"DE",
    "sg:address":"Ferdinand-Stuttmann-Str. 15",
    "sg:city":"R\u00fcsselsheim",
    "sg:phone":"+49 6142/91700",
    "sg:postcode":"65428",
    "sg:province":"Hessen",
    "wof:name":"Raytheon Technical Services International Company",
    "wof:placetype":"venue"
},
  "geometry": {"coordinates":[8.4140453339,49.9914398193],"type":"Point"}
}