{
  "type": "Feature",
  "properties": {
    "iso:country":"DE",
    "sg:address":"Naheweinstr. 160",
    "sg:city":"Langenlonsheim",
    "sg:phone":"+49 6704/2905",
    "sg:postcode":"55450",
    "sg:province":"Rheinland-Pfalz",
    "wof:name":"Dorothea Zimmer",
    "wof:placetype":"venue"
},
  "geometry": {"coordinates":[7.898445,49.89872],"type":"Point"}
}