{
  "type": "Feature",
  "properties": {
    "iso:country":"DE",
    "sg:address":"Alt-Eglsee 1",
    "sg:city":"Amberg",
    "sg:postcode":"92224",
    "sg:province":"Bayern",
    "wof:name":"Anton Und Rita Scharl Gmbh & Co. Betriebs Kg",
    "wof:placetype":"venue"
},
  "geometry": {"coordinates":[11.830755,49.455696],"type":"Point"}
}