{
  "type": "Feature",
  "properties": {
    "iso:country":"DE",
    "sg:address":"Hans-Bunte-Str 8",
    "sg:city":"Freiburg",
    "sg:phone":"+49 761/510480",
    "sg:postcode":"79108",
    "sg:province":"Baden-W\u00fcrttemberg",
    "wof:name":"Madeira Garne Ulrich + Michael Schmidt & Co Gmbh",
    "wof:placetype":"venue"
},
  "geometry": {"coordinates":[7.8528571129,48.0275382996],"type":"Point"}
}