{
  "type": "Feature",
  "properties": {
    "iso:country":"DE",
    "sg:address":"Kreisstr. 1",
    "sg:city":"Birstein",
    "sg:phone":"+49 6054/368",
    "sg:postcode":"63633",
    "sg:province":"Hessen",
    "wof:name":"Heinrich J\u00e4ger",
    "wof:placetype":"venue"
},
  "geometry": {"coordinates":[9.2841520309,50.401309967],"type":"Point"}
}