{
  "type": "Feature",
  "properties": {
    "iso:country":"DE",
    "sg:address":"Postfach 100363",
    "sg:city":"Bielefeld",
    "sg:phone":"+49 521/554200",
    "sg:postcode":"33503",
    "sg:province":"Nordrhein-Westfalen",
    "wof:name":"Umweltstiftung Der Ostwest- F\u00e4lischen Wirtschaft",
    "wof:placetype":"venue"
},
  "geometry": {"coordinates":[8.5331201553,52.0229911804],"type":"Point"}
}