{
  "type": "Feature",
  "properties": {
    "iso:country":"DE",
    "sg:address":"Luegallee 95",
    "sg:city":"D\u00fcsseldorf",
    "sg:phone":"+49 211/572170",
    "sg:postcode":"40545",
    "sg:province":"Nordrhein-Westfalen",
    "wof:name":"Atlas Reisen Gmbh",
    "wof:placetype":"venue"
},
  "geometry": {"coordinates":[6.750316143,51.2312965393],"type":"Point"}
}