{
  "type": "Feature",
  "properties": {
    "iso:country":"DE",
    "sg:address":"Hortwaldstr. 5",
    "sg:city":"Tholey",
    "sg:phone":"+49 6853/2424",
    "sg:postcode":"66636",
    "sg:province":"Saarland",
    "wof:name":"Rudolf Gilla",
    "wof:placetype":"venue"
},
  "geometry": {"coordinates":[7.0322389603,49.4993247986],"type":"Point"}
}