{
  "type": "Feature",
  "properties": {
    "iso:country":"DE",
    "sg:address":"Poststr. 7",
    "sg:city":"Bad Schandau",
    "sg:phone":"+49 35022/43169",
    "sg:postcode":"01814",
    "sg:province":"Sachsen",
    "wof:name":"Karin Barthold",
    "wof:placetype":"venue"
},
  "geometry": {"coordinates":[14.153477,50.918457],"type":"Point"}
}