{
  "type": "Feature",
  "properties": {
    "iso:country":"DE",
    "sg:address":"Brunhildestr. 10",
    "sg:city":"Mannheim",
    "sg:phone":"+49 621/812920",
    "sg:postcode":"68199",
    "sg:province":"Baden-W\u00fcrttemberg",
    "wof:name":"Dr. Med. Eberhard Vith Arzt F\u00fcr P\u00e4diatrie",
    "wof:placetype":"venue"
},
  "geometry": {"coordinates":[8.4910449982,49.4533538818],"type":"Point"}
}