{
  "type": "Feature",
  "properties": {
    "iso:country":"DE",
    "sg:address":"Schwarzenberger Str. 85",
    "sg:city":"Aue",
    "sg:phone":"+49 3771/24741",
    "sg:postcode":"08280",
    "sg:province":"Sachsen",
    "wof:name":"R. F\u00f6rster",
    "wof:placetype":"venue"
},
  "geometry": {"coordinates":[12.7124423981,50.5805969238],"type":"Point"}
}