{
  "type": "Feature",
  "properties": {
    "iso:country":"DE",
    "sg:address":"Bremachstr. 26",
    "sg:city":"Talheim",
    "sg:phone":"+49 7133/15262",
    "sg:postcode":"74388",
    "sg:province":"Baden-W\u00fcrttemberg",
    "wof:name":"Michael Kasper",
    "wof:placetype":"venue"
},
  "geometry": {"coordinates":[9.1918153763,49.0803642273],"type":"Point"}
}