{
  "type": "Feature",
  "properties": {
    "iso:country":"DE",
    "sg:address":"Brunnenstr. 18",
    "sg:city":"Bad Schwalbach",
    "sg:phone":"+49 6124/2121",
    "sg:postcode":"65307",
    "sg:province":"Hessen",
    "wof:name":"Gerhard Klein",
    "wof:placetype":"venue"
},
  "geometry": {"coordinates":[8.0692529678,50.1387634277],"type":"Point"}
}