{
  "type": "Feature",
  "properties": {
    "iso:country":"DE",
    "sg:address":"W\u00fcrselener Str 6",
    "sg:city":"Stolberg",
    "sg:phone":"+49 2402/12390",
    "sg:postcode":"52222",
    "sg:province":"Nordrhein-Westfalen",
    "wof:name":"Peter Worms Gmbh & Co Kg",
    "wof:placetype":"venue"
},
  "geometry": {"coordinates":[6.2175598145,50.7825889587],"type":"Point"}
}