{
  "type": "Feature",
  "properties": {
    "iso:country":"DE",
    "sg:address":"Richard-Sorge-Str. 3",
    "sg:city":"Wildau",
    "sg:phone":"+49 3375/554391",
    "sg:postcode":"15745",
    "sg:province":"Brandenburg",
    "wof:name":"Cafe Treffpunkt",
    "wof:placetype":"venue"
},
  "geometry": {"coordinates":[13.633084,52.316074],"type":"Point"}
}