{
  "type": "Feature",
  "properties": {
    "iso:country":"DE",
    "sg:address":"Waldstr. 16",
    "sg:city":"Sch\u00f6llnach",
    "sg:phone":"+49 9903/1255",
    "sg:postcode":"94508",
    "sg:province":"Bayern",
    "wof:name":"Alfred Sergl",
    "wof:placetype":"venue"
},
  "geometry": {"coordinates":[13.182127,48.755745],"type":"Point"}
}