{
  "type": "Feature",
  "properties": {
    "iso:country":"DE",
    "sg:address":"Alte G\u00e4rtnerei 2",
    "sg:city":"Mainz",
    "sg:phone":"+49 6131/936360",
    "sg:postcode":"55128",
    "sg:province":"Rheinland-Pfalz",
    "wof:name":"Felix Sch\u00fctz Steuerberater",
    "wof:placetype":"venue"
},
  "geometry": {"coordinates":[8.2366266251,49.9768562317],"type":"Point"}
}