{
  "type": "Feature",
  "properties": {
    "iso:country":"DE",
    "sg:address":"Berzeliusstr. 41",
    "sg:city":"Hamburg",
    "sg:phone":"+49 40/7314423",
    "sg:postcode":"22113",
    "sg:province":"Schleswig-Holstein",
    "wof:name":"Kleemann & Co.",
    "wof:placetype":"venue"
},
  "geometry": {"coordinates":[10.093372345,53.5349769592],"type":"Point"}
}