{
  "type": "Feature",
  "properties": {
    "iso:country":"DE",
    "sg:address":"Portiunkulaweg 2",
    "sg:city":"Viersen",
    "sg:phone":"+49 2162/102542",
    "sg:postcode":"41747",
    "sg:province":"Nordrhein-Westfalen",
    "wof:name":"Theo Stappen Rechtsanwalt",
    "wof:placetype":"venue"
},
  "geometry": {"coordinates":[6.3859100342,51.2555198669],"type":"Point"}
}