{
  "type": "Feature",
  "properties": {
    "iso:country":"DE",
    "sg:address":"Sch\u00f6nbeinstr. 4",
    "sg:city":"Heilbronn",
    "sg:phone":"+49 7131/98610",
    "sg:postcode":"74076",
    "sg:province":"Baden-W\u00fcrttemberg",
    "wof:name":"Sim Stahl-industrie Und Montagebauten Gmbh",
    "wof:placetype":"venue"
},
  "geometry": {"coordinates":[9.22108,49.17041],"type":"Point"}
}