{
  "type": "Feature",
  "properties": {
    "iso:country":"DE",
    "sg:address":"Westring 12-15",
    "sg:city":"Wesseling",
    "sg:phone":"+49 2236/842096",
    "sg:postcode":"50389",
    "sg:province":"Nordrhein-Westfalen",
    "wof:name":"Klabunde Fischfachhandel",
    "wof:placetype":"venue"
},
  "geometry": {"coordinates":[6.9789619446,50.8226661682],"type":"Point"}
}