{
  "type": "Feature",
  "properties": {
    "iso:country":"DE",
    "sg:address":"Georgstr. 9",
    "sg:city":"Hannover",
    "sg:phone":"+49 511/327269",
    "sg:postcode":"30159",
    "sg:province":"Niedersachsen",
    "wof:name":"Dieter Ellenberg Rechtsanwalt Und Notar",
    "wof:placetype":"venue"
},
  "geometry": {"coordinates":[9.7335548401,52.3759040833],"type":"Point"}
}