{
  "type": "Feature",
  "properties": {
    "iso:country":"DE",
    "sg:address":"M\u00fchlenstr. 15",
    "sg:city":"Marl",
    "sg:phone":"+49 2365/84409",
    "sg:postcode":"45770",
    "sg:province":"Nordrhein-Westfalen",
    "wof:name":"Radde & Rabe",
    "wof:placetype":"venue"
},
  "geometry": {"coordinates":[7.194537,51.650936],"type":"Point"}
}