{
  "type": "Feature",
  "properties": {
    "iso:country":"DE",
    "sg:address":"Sudetenstr. 3",
    "sg:city":"R\u00fcdesheim am Rhein",
    "sg:phone":"+49 6722/2897",
    "sg:postcode":"65385",
    "sg:province":"Hessen",
    "wof:name":"Haus Panorama",
    "wof:placetype":"venue"
},
  "geometry": {"coordinates":[7.9337029457,49.9969673157],"type":"Point"}
}