{
  "type": "Feature",
  "properties": {
    "iso:country":"DE",
    "sg:address":"Kirschweiler Br\u00fccke 15",
    "sg:city":"Kirschweiler",
    "sg:phone":"+49 4967/8193750",
    "sg:postcode":"55743",
    "sg:province":"Rheinland-Pfalz",
    "wof:name":"May Lichttechnik Gmbh",
    "wof:placetype":"venue"
},
  "geometry": {"coordinates":[7.263326,49.755119],"type":"Point"}
}