{
  "type": "Feature",
  "properties": {
    "iso:country":"DE",
    "sg:address":"Untere Bahnhofstr. 10",
    "sg:city":"Lahntal",
    "sg:phone":"+49 6420/401",
    "sg:postcode":"35094",
    "sg:province":"Hessen",
    "wof:name":"H. Efiba Gmbh & Co. Kg",
    "wof:placetype":"venue"
},
  "geometry": {"coordinates":[8.70889,50.862019],"type":"Point"}
}