{
  "type": "Feature",
  "properties": {
    "iso:country":"DE",
    "sg:address":"Ein\u00f6de 5",
    "sg:city":"Benningen",
    "sg:phone":"+49 8331/5570",
    "sg:postcode":"87734",
    "sg:province":"Bayern",
    "wof:name":"Armin Wechsel",
    "wof:placetype":"venue"
},
  "geometry": {"coordinates":[10.234581,47.966236],"type":"Point"}
}