{
  "type": "Feature",
  "properties": {
    "iso:country":"DE",
    "sg:address":"\u00c4u\u00dferes Pfaffeng\u00e4\u00dfchen 3",
    "sg:city":"Augsburg",
    "sg:phone":"+49 821/518977",
    "sg:postcode":"86152",
    "sg:province":"Bayern",
    "wof:name":"C. Und R. Wild",
    "wof:placetype":"venue"
},
  "geometry": {"coordinates":[10.89717,48.374298],"type":"Point"}
}