{
  "type": "Feature",
  "properties": {
    "iso:country":"DE",
    "sg:address":"Cloosstr. 2",
    "sg:city":"V\u00f6lklingen",
    "sg:phone":"+49 6898/23692",
    "sg:postcode":"66333",
    "sg:province":"Saarland",
    "wof:name":"Burkhardt Gmbh",
    "wof:placetype":"venue"
},
  "geometry": {"coordinates":[6.8565077782,49.2521438599],"type":"Point"}
}