{
  "type": "Feature",
  "properties": {
    "iso:country":"DE",
    "sg:address":"Gro\u00dfe Langgasse 12",
    "sg:city":"Mainz",
    "sg:phone":"+49 6131/224425",
    "sg:postcode":"55116",
    "sg:province":"Rheinland-Pfalz",
    "wof:name":"Kebabkiste Kurdistan",
    "wof:placetype":"venue"
},
  "geometry": {"coordinates":[8.2677268982,49.9995765686],"type":"Point"}
}