{
  "type": "Feature",
  "properties": {
    "iso:country":"DE",
    "sg:address":"Kirchstr. 2a",
    "sg:city":"Lauf",
    "sg:phone":"+49 7841/24387",
    "sg:postcode":"77886",
    "sg:province":"Baden-W\u00fcrttemberg",
    "wof:name":"L. Dinger",
    "wof:placetype":"venue"
},
  "geometry": {"coordinates":[8.1298780441,48.6483192444],"type":"Point"}
}