{
  "type": "Feature",
  "properties": {
    "iso:country":"DE",
    "sg:address":"Lorbeerstr. 66",
    "sg:city":"Stuttgart",
    "sg:phone":"+49 711/445758",
    "sg:postcode":"70619",
    "sg:province":"Baden-W\u00fcrttemberg",
    "wof:name":"Rolf Weigt Steuerberater",
    "wof:placetype":"venue"
},
  "geometry": {"coordinates":[9.2333984375,48.739654541],"type":"Point"}
}