{
  "type": "Feature",
  "properties": {
    "iso:country":"DE",
    "sg:address":"Herrengasse 15",
    "sg:city":"Eckental",
    "sg:phone":"+49 9126/1043",
    "sg:postcode":"90542",
    "sg:province":"Bayern",
    "wof:name":"Kondate Gesellschaft F\u00fcr Konstruktion Und Technische",
    "wof:placetype":"venue"
},
  "geometry": {"coordinates":[11.1994123459,49.5721588135],"type":"Point"}
}