{
  "type": "Feature",
  "properties": {
    "iso:country":"DE",
    "sg:address":"Memminger Str. 4 1-2",
    "sg:city":"Babenhausen",
    "sg:phone":"+49 8333/8548",
    "sg:postcode":"87727",
    "sg:province":"Bayern",
    "wof:name":"Gertraud St\u00f6ckle",
    "wof:placetype":"venue"
},
  "geometry": {"coordinates":[10.2540359497,48.1437225342],"type":"Point"}
}