{
  "type": "Feature",
  "properties": {
    "iso:country":"DE",
    "sg:address":"Bahnhofstr. 25",
    "sg:city":"Bayreuth",
    "sg:phone":"+49 921/726760",
    "sg:postcode":"95444",
    "sg:province":"Bayern",
    "wof:name":"Telekommunkationszentrum Oberfranken E. V.",
    "wof:placetype":"venue"
},
  "geometry": {"coordinates":[11.5786762238,49.9496231079],"type":"Point"}
}