{
  "type": "Feature",
  "properties": {
    "iso:country":"DE",
    "sg:address":"Schubartstr. 2",
    "sg:city":"Bad Urach",
    "sg:phone":"+49 7125/7933",
    "sg:postcode":"72574",
    "sg:province":"Baden-W\u00fcrttemberg",
    "wof:name":"Lothar Ulbrich Architekt",
    "wof:placetype":"venue"
},
  "geometry": {"coordinates":[9.383218,48.498611],"type":"Point"}
}