{
  "type": "Feature",
  "properties": {
    "iso:country":"DE",
    "sg:address":"Kieler Str. 17",
    "sg:city":"Eckernf\u00f6rde",
    "sg:phone":"+49 4351/3280",
    "sg:postcode":"24340",
    "sg:province":"Schleswig-Holstein",
    "wof:name":"Schuh- Und Sporthaus Simon Inh. Dirk Simon",
    "wof:placetype":"venue"
},
  "geometry": {"coordinates":[9.837099,54.471653],"type":"Point"}
}