{
  "type": "Feature",
  "properties": {
    "iso:country":"DE",
    "sg:address":"Hoffeldstr. 85",
    "sg:city":"D\u00fcsseldorf",
    "sg:phone":"+49 211/6907570",
    "sg:postcode":"40235",
    "sg:province":"Nordrhein-Westfalen",
    "wof:name":"Axair Gmbh Barth Und St\u00f6cklein",
    "wof:placetype":"venue"
},
  "geometry": {"coordinates":[6.8145198822,51.2275085449],"type":"Point"}
}