{
  "type": "Feature",
  "properties": {
    "iso:country":"DE",
    "sg:address":"Jahnallee 36",
    "sg:city":"Arnsberg",
    "sg:phone":"+49 2932/26464",
    "sg:postcode":"59757",
    "sg:province":"Nordrhein-Westfalen",
    "wof:name":"Tennishallen Gbr",
    "wof:placetype":"venue"
},
  "geometry": {"coordinates":[7.9504671097,51.4497642517],"type":"Point"}
}