{
  "type": "Feature",
  "properties": {
    "iso:country":"DE",
    "sg:address":"Kohlenstr. 12",
    "sg:city":"Velbert",
    "sg:phone":"+49 2052/3789",
    "sg:postcode":"42555",
    "sg:province":"Nordrhein-Westfalen",
    "wof:name":"A. Baukrowitz",
    "wof:placetype":"venue"
},
  "geometry": {"coordinates":[7.12946,51.37574],"type":"Point"}
}