{
  "type": "Feature",
  "properties": {
    "iso:country":"DE",
    "sg:address":"Burgstr. 7",
    "sg:city":"Worbis",
    "sg:phone":"+49 36074/30807",
    "sg:postcode":"37339",
    "sg:province":"Th\u00fcringen",
    "wof:name":"K. Gr\u00fcning",
    "wof:placetype":"venue"
},
  "geometry": {"coordinates":[10.3599739075,51.4228553772],"type":"Point"}
}