{
  "type": "Feature",
  "properties": {
    "iso:country":"DE",
    "sg:address":"Die Liene 8",
    "sg:city":"Bocholt",
    "sg:phone":"+49 2874/3181",
    "sg:postcode":"46399",
    "sg:province":"Nordrhein-Westfalen",
    "wof:name":"Th. K\u00f6ching",
    "wof:placetype":"venue"
},
  "geometry": {"coordinates":[6.498814106,51.8591346741],"type":"Point"}
}