{
  "type": "Feature",
  "properties": {
    "iso:country":"DE",
    "sg:address":"Lug ins Land 6",
    "sg:city":"Kirchheim",
    "sg:phone":"+49 8266/86070",
    "sg:postcode":"87757",
    "sg:province":"Bayern",
    "wof:name":"Karl Freisinger",
    "wof:placetype":"venue"
},
  "geometry": {"coordinates":[10.473989,48.175148],"type":"Point"}
}