{
  "type": "Feature",
  "properties": {
    "iso:country":"DE",
    "sg:address":"M\u00e4ttich 12",
    "sg:city":"Sasbach",
    "sg:phone":"+49 7841/69560",
    "sg:postcode":"77880",
    "sg:province":"Baden-W\u00fcrttemberg",
    "wof:name":"Bgur - B\u00fcro F\u00fcr Geowissenschaftlichen Umweltschutz Gmbh",
    "wof:placetype":"venue"
},
  "geometry": {"coordinates":[8.085479,48.647701],"type":"Point"}
}