{
  "type": "Feature",
  "properties": {
    "iso:country":"DE",
    "sg:address":"Georg-Schwarz-Str. 126",
    "sg:city":"Leipzig",
    "sg:postcode":"04179",
    "sg:province":"Sachsen",
    "wof:name":"Wolfgang Heiden",
    "wof:placetype":"venue"
},
  "geometry": {"coordinates":[12.3155927658,51.347038269],"type":"Point"}
}