{
  "type": "Feature",
  "properties": {
    "iso:country":"DE",
    "sg:address":"Schlo\u00dfstr. 18",
    "sg:city":"Laufen",
    "sg:phone":"+49 8682/248",
    "sg:postcode":"83410",
    "sg:province":"Bayern",
    "wof:name":"Jakob Brugger Inh. G\u00fcnter Fixl",
    "wof:placetype":"venue"
},
  "geometry": {"coordinates":[12.935968399,47.9387321472],"type":"Point"}
}