{
  "type": "Feature",
  "properties": {
    "iso:country":"DE",
    "sg:address":"Moritzstr. 33",
    "sg:city":"Erfurt",
    "sg:phone":"+49 361/5623922",
    "sg:postcode":"99084",
    "sg:province":"Th\u00fcringen",
    "wof:name":"Wieland Wellendorf",
    "wof:placetype":"venue"
},
  "geometry": {"coordinates":[11.0254182816,50.9816131592],"type":"Point"}
}