{
  "type": "Feature",
  "properties": {
    "iso:country":"DE",
    "sg:address":"Paradiesgasse 1-1",
    "sg:city":"Villingen-Schwenningen",
    "sg:phone":"+49 7721/26324",
    "sg:postcode":"78050",
    "sg:province":"Baden-W\u00fcrttemberg",
    "wof:name":"Rosemarie Schuhmacher",
    "wof:placetype":"venue"
},
  "geometry": {"coordinates":[8.462391,48.057823],"type":"Point"}
}