{
  "type": "Feature",
  "properties": {
    "iso:country":"DE",
    "sg:address":"Karl-Bertelsmann-Str. 161",
    "sg:city":"G\u00fctersloh",
    "sg:phone":"+49 4952/41800",
    "sg:postcode":"33311",
    "sg:province":"Nordrhein-Westfalen",
    "wof:name":"Arvato Ag",
    "wof:placetype":"venue"
},
  "geometry": {"coordinates":[8.4096975327,51.9061698914],"type":"Point"}
}