{
  "type": "Feature",
  "properties": {
    "iso:country":"DE",
    "sg:address":"Marktstr. 52",
    "sg:city":"Burgdorf",
    "sg:phone":"+49 5136/4453",
    "sg:postcode":"31303",
    "sg:province":"Niedersachsen",
    "wof:name":"Textilhaus Friedrich Obermeyer Inh. Gerd Obermeyer",
    "wof:placetype":"venue"
},
  "geometry": {"coordinates":[10.007971,52.446781],"type":"Point"}
}