{
  "type": "Feature",
  "properties": {
    "iso:country":"DE",
    "sg:address":"Schmerfeldstr. 7",
    "sg:city":"Kassel",
    "sg:phone":"+49 561/64415",
    "sg:postcode":"34130",
    "sg:province":"Hessen",
    "wof:name":"Gerhard Jebens",
    "wof:placetype":"venue"
},
  "geometry": {"coordinates":[9.452827,51.323322],"type":"Point"}
}