{
  "type": "Feature",
  "properties": {
    "iso:country":"DE",
    "sg:address":"Auenberg 15",
    "sg:city":"Dillendorf",
    "sg:phone":"+49 6763/1250",
    "sg:postcode":"55481",
    "sg:province":"Rheinland-Pfalz",
    "wof:name":"Herbert Schwob",
    "wof:placetype":"venue"
},
  "geometry": {"coordinates":[7.377447,49.924347],"type":"Point"}
}