{
  "type": "Feature",
  "properties": {
    "iso:country":"DE",
    "sg:address":"Potsdamer Str. 70",
    "sg:city":"Berlin",
    "sg:phone":"+49 30/2618549",
    "sg:postcode":"10785",
    "sg:province":"Berlin",
    "wof:name":"Lloyd-presse Verlagsges. Mbh",
    "wof:placetype":"venue"
},
  "geometry": {"coordinates":[13.3666801453,52.5044784546],"type":"Point"}
}