{
  "type": "Feature",
  "properties": {
    "iso:country":"DE",
    "sg:address":"Alandstr. 18",
    "sg:city":"Schnackenburg",
    "sg:phone":"+49 5840/236",
    "sg:postcode":"29493",
    "sg:province":"Niedersachsen",
    "wof:name":"Kurt Jafke",
    "wof:placetype":"venue"
},
  "geometry": {"coordinates":[11.565386,53.036137],"type":"Point"}
}