{
  "type": "Feature",
  "properties": {
    "iso:country":"DE",
    "sg:address":"Niederstr. 14 a",
    "sg:city":"Dornburg",
    "sg:phone":"+49 6436/7234",
    "sg:postcode":"65599",
    "sg:province":"Hessen",
    "wof:name":"Walter Zimmermann Und G\u00fcnther H\u00f6rter",
    "wof:placetype":"venue"
},
  "geometry": {"coordinates":[8.0198335648,50.5301895142],"type":"Point"}
}