{
  "type": "Feature",
  "properties": {
    "iso:country":"DE",
    "sg:address":"Eisenbahnstr. 21",
    "sg:city":"Achern",
    "sg:phone":"+49 7841/7080",
    "sg:postcode":"77855",
    "sg:province":"Baden-W\u00fcrttemberg",
    "wof:name":"Theo Naendrup Rechtsanwalt",
    "wof:placetype":"venue"
},
  "geometry": {"coordinates":[8.0676059723,48.6314353943],"type":"Point"}
}