{
  "type": "Feature",
  "properties": {
    "iso:country":"DE",
    "sg:address":"Grevenbroicher Str. 31",
    "sg:city":"Rommerskirchen",
    "sg:phone":"+49 2183/6655",
    "sg:postcode":"41569",
    "sg:province":"Nordrhein-Westfalen",
    "wof:name":"Jordans Weindepot",
    "wof:placetype":"venue"
},
  "geometry": {"coordinates":[6.6626992226,51.0462417603],"type":"Point"}
}