{
  "type": "Feature",
  "properties": {
    "iso:country":"DE",
    "sg:address":"Im Avelertal 27",
    "sg:city":"Trier",
    "sg:phone":"+49 651/24706",
    "sg:postcode":"54295",
    "sg:province":"Rheinland-Pfalz",
    "wof:name":"Kavitationserosion - Vibroakustische Diagnostik",
    "wof:placetype":"venue"
},
  "geometry": {"coordinates":[6.6711688042,49.7613754272],"type":"Point"}
}