{
  "type": "Feature",
  "properties": {
    "iso:country":"DE",
    "sg:address":"Holzm\u00fchler Weg 76",
    "sg:city":"Lollar",
    "sg:postcode":"35457",
    "sg:province":"Hessen",
    "wof:name":"Volks- Und Sch\u00fclerb\u00fccherei",
    "wof:placetype":"venue"
},
  "geometry": {"coordinates":[8.712491,50.648315],"type":"Point"}
}