{
  "type": "Feature",
  "properties": {
    "iso:country":"DE",
    "sg:address":"Ro\u00dfmarkt 5",
    "sg:city":"Limburg",
    "sg:phone":"+49 6431/8317",
    "sg:postcode":"65549",
    "sg:province":"Hessen",
    "wof:name":"E. Profitlich",
    "wof:placetype":"venue"
},
  "geometry": {"coordinates":[8.066947937,50.3877983093],"type":"Point"}
}