{
  "type": "Feature",
  "properties": {
    "iso:country":"DE",
    "sg:address":"Vorhofer Str. 4",
    "sg:city":"L\u00f6wenstein",
    "sg:phone":"+49 7130/6165",
    "sg:postcode":"74245",
    "sg:province":"Baden-W\u00fcrttemberg",
    "wof:name":"Reinhold Zipf",
    "wof:placetype":"venue"
},
  "geometry": {"coordinates":[9.3795814514,49.0925140381],"type":"Point"}
}