{
  "type": "Feature",
  "properties": {
    "iso:country":"DE",
    "sg:address":"Hochstr. 16",
    "sg:city":"Andernach",
    "sg:phone":"+49 2632/48277",
    "sg:postcode":"56626",
    "sg:province":"Rheinland-Pfalz",
    "wof:name":"G\u00fcnter Wagner",
    "wof:placetype":"venue"
},
  "geometry": {"coordinates":[7.397258,50.439991],"type":"Point"}
}