{
  "type": "Feature",
  "properties": {
    "iso:country":"DE",
    "sg:address":"Mommsenstr. 76",
    "sg:city":"K\u00f6ln",
    "sg:phone":"+49 221/446646",
    "sg:postcode":"50935",
    "sg:province":"Nordrhein-Westfalen",
    "wof:name":"H\u00f6k Und Silva-hilleke Rechtsanw\u00e4lte",
    "wof:placetype":"venue"
},
  "geometry": {"coordinates":[6.906774044,50.9221801758],"type":"Point"}
}