{
  "type": "Feature",
  "properties": {
    "iso:country":"DE",
    "sg:address":"Am Schleusenkanal 18-22",
    "sg:city":"Geesthacht",
    "sg:phone":"+49 4152/845035",
    "sg:postcode":"21502",
    "sg:province":"Schleswig-Holstein",
    "wof:name":"Reiseb\u00fcro Oberelbe Gmbh",
    "wof:placetype":"venue"
},
  "geometry": {"coordinates":[10.3457307816,53.431892395],"type":"Point"}
}