{
  "type": "Feature",
  "properties": {
    "iso:country":"DE",
    "sg:address":"Industriestr. 1",
    "sg:city":"Holzkirchen",
    "sg:phone":"+49 8024/7883",
    "sg:postcode":"83607",
    "sg:province":"Bayern",
    "wof:name":"Fah Ges Fahrzeughandels- Gesellschaft Mbh",
    "wof:placetype":"venue"
},
  "geometry": {"coordinates":[11.718041,47.877544],"type":"Point"}
}