{
  "type": "Feature",
  "properties": {
    "iso:country":"DE",
    "sg:address":"Am Wehr 3",
    "sg:city":"Eisenach",
    "sg:phone":"+49 3691/732252",
    "sg:postcode":"99817",
    "sg:province":"Th\u00fcringen",
    "wof:name":"Walter Schuchardt",
    "wof:placetype":"venue"
},
  "geometry": {"coordinates":[10.334221,50.979607],"type":"Point"}
}