{
  "type": "Feature",
  "properties": {
    "iso:country":"DE",
    "sg:address":"Carl-Benz-Str. 2",
    "sg:city":"Kaltenkirchen",
    "sg:phone":"+49 4191/88171",
    "sg:postcode":"24568",
    "sg:province":"Schleswig-Holstein",
    "wof:name":"Kuhrt Fleischveredelungs Gmbh",
    "wof:placetype":"venue"
},
  "geometry": {"coordinates":[9.9696998596,53.8260650635],"type":"Point"}
}