{
  "type": "Feature",
  "properties": {
    "iso:country":"DE",
    "sg:address":"Frenshofer Hauptstr. 2",
    "sg:city":"Sch\u00f6nbrunn",
    "sg:phone":"+49 9549/333",
    "sg:postcode":"96185",
    "sg:province":"Bayern",
    "wof:name":"Willi Volk",
    "wof:placetype":"venue"
},
  "geometry": {"coordinates":[10.7196893692,49.872959137],"type":"Point"}
}