{
  "type": "Feature",
  "properties": {
    "iso:country":"DE",
    "sg:address":"Hindenburgstr. 12",
    "sg:city":"Remscheid",
    "sg:phone":"+49 2191/929957",
    "sg:postcode":"42853",
    "sg:province":"Nordrhein-Westfalen",
    "wof:name":"Evertz Gmbh",
    "wof:placetype":"venue"
},
  "geometry": {"coordinates":[7.1828989983,51.1821937561],"type":"Point"}
}