{
  "type": "Feature",
  "properties": {
    "iso:country":"DE",
    "sg:address":"Ferdinand-Porsche-Str. 4",
    "sg:city":"Nufringen",
    "sg:phone":"+49 7032/8084",
    "sg:postcode":"71154",
    "sg:province":"Baden-W\u00fcrttemberg",
    "wof:name":"Bertele Gmbh",
    "wof:placetype":"venue"
},
  "geometry": {"coordinates":[8.898443,48.628716],"type":"Point"}
}