{
  "type": "Feature",
  "properties": {
    "iso:country":"DE",
    "sg:address":"Marktstr. 27",
    "sg:city":"K\u00f6ln",
    "sg:phone":"+49 2203/81203",
    "sg:postcode":"51143",
    "sg:province":"Nordrhein-Westfalen",
    "wof:name":"Landhaus Z\u00fcndorf",
    "wof:placetype":"venue"
},
  "geometry": {"coordinates":[7.0432457924,50.8694267273],"type":"Point"}
}