{
  "type": "Feature",
  "properties": {
    "iso:country":"DE",
    "sg:address":"Zinngie\u00dferstr. 9",
    "sg:city":"Hameln",
    "sg:phone":"+49 5151/924637",
    "sg:postcode":"31789",
    "sg:province":"Niedersachsen",
    "wof:name":"S\u00f6ko",
    "wof:placetype":"venue"
},
  "geometry": {"coordinates":[9.3400115967,52.0836105347],"type":"Point"}
}