{
  "type": "Feature",
  "properties": {
    "iso:country":"DE",
    "sg:address":"K\u00f6lner Str. 252-354",
    "sg:city":"Krefeld",
    "sg:phone":"+49 2151/371224",
    "sg:postcode":"47807",
    "sg:province":"Nordrhein-Westfalen",
    "wof:name":"Standex International Gmbh",
    "wof:placetype":"venue"
},
  "geometry": {"coordinates":[6.5768117905,51.3161582947],"type":"Point"}
}