{
  "type": "Feature",
  "properties": {
    "iso:country":"DE",
    "sg:address":"Hauptstr. 78",
    "sg:city":"Doberlug-Kirchhain",
    "sg:phone":"+49 35322/2307",
    "sg:postcode":"03253",
    "sg:province":"Brandenburg",
    "wof:name":"Steins Bierstuben",
    "wof:placetype":"venue"
},
  "geometry": {"coordinates":[13.5478343964,51.6106338501],"type":"Point"}
}