{
  "type": "Feature",
  "properties": {
    "iso:country":"DE",
    "sg:address":"Neustr. 2",
    "sg:city":"Stolberg",
    "sg:phone":"+49 2402/36183",
    "sg:postcode":"52223",
    "sg:province":"Nordrhein-Westfalen",
    "wof:name":"C. Thelen",
    "wof:placetype":"venue"
},
  "geometry": {"coordinates":[6.220785141,50.7301673889],"type":"Point"}
}