{
  "type": "Feature",
  "properties": {
    "iso:country":"DE",
    "sg:address":"Brunnenstr. 7",
    "sg:city":"Gerabronn",
    "sg:phone":"+49 7952/489",
    "sg:postcode":"74582",
    "sg:province":"Baden-W\u00fcrttemberg",
    "wof:name":"Friedrich Baumann",
    "wof:placetype":"venue"
},
  "geometry": {"coordinates":[9.96461,49.265984],"type":"Point"}
}