{
  "type": "Feature",
  "properties": {
    "iso:country":"DE",
    "sg:address":"Egerl\u00e4nderstr. 7",
    "sg:city":"Altenstadt",
    "sg:phone":"+49 9602/5770",
    "sg:postcode":"92665",
    "sg:province":"Bayern",
    "wof:name":"Siegfried Zoll Masseur",
    "wof:placetype":"venue"
},
  "geometry": {"coordinates":[12.093077,49.777115],"type":"Point"}
}