{
  "type": "Feature",
  "properties": {
    "iso:country":"DE",
    "sg:address":"Ringstr. 43",
    "sg:city":"Spessart",
    "sg:phone":"+49 2655/1833",
    "sg:postcode":"56746",
    "sg:province":"Rheinland-Pfalz",
    "wof:name":"Vfi Gro\u00df Gmbh",
    "wof:placetype":"venue"
},
  "geometry": {"coordinates":[7.1066727638,50.44190979],"type":"Point"}
}