{
  "type": "Feature",
  "properties": {
    "iso:country":"DE",
    "sg:address":"B\u00fcchelberg 110",
    "sg:city":"Gunzenhausen",
    "sg:phone":"+49 9831/3409",
    "sg:postcode":"91710",
    "sg:province":"Bayern",
    "wof:name":"Eberhard Schimmelschmidt Architekt",
    "wof:placetype":"venue"
},
  "geometry": {"coordinates":[10.75874,49.155598],"type":"Point"}
}