{
  "type": "Feature",
  "properties": {
    "iso:country":"DE",
    "sg:address":"Herminghauser Str. 9",
    "sg:city":"Ennepetal",
    "sg:phone":"+49 2333/75235",
    "sg:postcode":"58256",
    "sg:province":"Nordrhein-Westfalen",
    "wof:name":"Michael Gr\u00fcnwald",
    "wof:placetype":"venue"
},
  "geometry": {"coordinates":[7.383289,51.266125],"type":"Point"}
}