{
  "type": "Feature",
  "properties": {
    "iso:country":"DE",
    "sg:address":"Schmelzerstr. 8",
    "sg:city":"Eisenach",
    "sg:phone":"+49 3691/75107",
    "sg:postcode":"99817",
    "sg:province":"Th\u00fcringen",
    "wof:name":"Stahr Und Platz Notare",
    "wof:placetype":"venue"
},
  "geometry": {"coordinates":[10.3213129044,50.9736175537],"type":"Point"}
}