{
  "type": "Feature",
  "properties": {
    "iso:country":"DE",
    "sg:address":"Torgauer Str. 31",
    "sg:city":"Falkenberg",
    "sg:phone":"+49 35365/2358",
    "sg:postcode":"04895",
    "sg:province":"Brandenburg",
    "wof:name":"H. Schmidt",
    "wof:placetype":"venue"
},
  "geometry": {"coordinates":[13.23061,51.5868],"type":"Point"}
}