{
  "type": "Feature",
  "properties": {
    "iso:country":"DE",
    "sg:address":"Oststr. 2",
    "sg:city":"Hohenstein-Ernstthal",
    "sg:phone":"+49 3723/413443",
    "sg:postcode":"09337",
    "sg:province":"Sachsen",
    "wof:name":"A. M\u00fcller",
    "wof:placetype":"venue"
},
  "geometry": {"coordinates":[12.7223100662,50.8011894226],"type":"Point"}
}