{
  "type": "Feature",
  "properties": {
    "iso:country":"DE",
    "sg:address":"Bahnhofstr. 13",
    "sg:city":"Bad Arolsen",
    "sg:phone":"+49 5691/1054",
    "sg:postcode":"34454",
    "sg:province":"Hessen",
    "wof:name":"Hennig Stracke Augenoptiker",
    "wof:placetype":"venue"
},
  "geometry": {"coordinates":[9.0132932663,51.3804283142],"type":"Point"}
}