{
  "type": "Feature",
  "properties": {
    "iso:country":"DE",
    "sg:address":"P\u00f6hlaer Str. 8a",
    "sg:city":"Schwarzenberg",
    "sg:phone":"+49 3774/81089",
    "sg:postcode":"08340",
    "sg:province":"Sachsen",
    "wof:name":"Dr. Med. Christa Leicht \u00c4rztin F\u00fcr Allgemeinmedizin",
    "wof:placetype":"venue"
},
  "geometry": {"coordinates":[12.8181266785,50.5275306702],"type":"Point"}
}