{
  "type": "Feature",
  "properties": {
    "iso:country":"DE",
    "sg:address":"Werdauer Str. 22a",
    "sg:city":"Fraureuth",
    "sg:phone":"+49 3761/3805",
    "sg:postcode":"08427",
    "sg:province":"Sachsen",
    "wof:name":"Klaus Weber",
    "wof:placetype":"venue"
},
  "geometry": {"coordinates":[12.364839,50.708466],"type":"Point"}
}