{
  "type": "Feature",
  "properties": {
    "iso:country":"DE",
    "sg:address":"Freisch\u00fctzstr. 75",
    "sg:city":"M\u00fcnchen",
    "sg:phone":"+49 89/9570073",
    "sg:postcode":"81927",
    "sg:province":"Bayern",
    "wof:name":"Ppm-vertriebs Gmbh",
    "wof:placetype":"venue"
},
  "geometry": {"coordinates":[11.643791,48.166611],"type":"Point"}
}