{
  "type": "Feature",
  "properties": {
    "iso:country":"DE",
    "sg:address":"Flensburger Str. 69",
    "sg:city":"Dresden",
    "sg:phone":"+49 351/4537002",
    "sg:postcode":"01157",
    "sg:province":"Sachsen",
    "wof:name":"Otfried Mieth",
    "wof:placetype":"venue"
},
  "geometry": {"coordinates":[13.657027,51.084846],"type":"Point"}
}