{
  "type": "Feature",
  "properties": {
    "iso:country":"DE",
    "sg:address":"Talstr. 8",
    "sg:city":"Sch\u00f6nau",
    "sg:phone":"+49 7673/1892",
    "sg:postcode":"79677",
    "sg:province":"Baden-W\u00fcrttemberg",
    "wof:name":"Kismet-choice Modevertrieb Gmbh",
    "wof:placetype":"venue"
},
  "geometry": {"coordinates":[7.883975,47.760303],"type":"Point"}
}