{
  "type": "Feature",
  "properties": {
    "iso:country":"DE",
    "sg:address":"Hauptstr. 22",
    "sg:city":"Eggebek",
    "sg:phone":"+49 4609/233",
    "sg:postcode":"24852",
    "sg:province":"Schleswig-Holstein",
    "wof:name":"Annegret Nonn",
    "wof:placetype":"venue"
},
  "geometry": {"coordinates":[9.375745,54.619846],"type":"Point"}
}