{
  "type": "Feature",
  "properties": {
    "iso:country":"DE",
    "sg:address":"Marktplatz",
    "sg:city":"Biedenkopf",
    "sg:phone":"+49 6461/2194",
    "sg:postcode":"35216",
    "sg:province":"Hessen",
    "wof:name":"Druckerei Unverzagt Gmbh & Co Kg",
    "wof:placetype":"venue"
},
  "geometry": {"coordinates":[8.5306253433,50.9113807678],"type":"Point"}
}