{
  "type": "Feature",
  "properties": {
    "iso:country":"DE",
    "sg:address":"Holzdamm",
    "sg:city":"Erftstadt",
    "sg:phone":"+49 2235/3555",
    "sg:postcode":"50374",
    "sg:province":"Nordrhein-Westfalen",
    "wof:name":"Hallenbad Liblar",
    "wof:placetype":"venue"
},
  "geometry": {"coordinates":[6.8139548302,50.8040466309],"type":"Point"}
}