{
  "type": "Feature",
  "properties": {
    "iso:country":"DE",
    "sg:address":"Hammer Str. 77",
    "sg:city":"Kamen",
    "sg:phone":"+49 2307/10237",
    "sg:postcode":"59174",
    "sg:province":"Nordrhein-Westfalen",
    "wof:name":"Josef Vonnahme",
    "wof:placetype":"venue"
},
  "geometry": {"coordinates":[7.681166,51.606441],"type":"Point"}
}