{
  "type": "Feature",
  "properties": {
    "iso:country":"DE",
    "sg:address":"Schweizer Platz 62",
    "sg:city":"Frankfurt",
    "sg:phone":"+49 69/61990340",
    "sg:postcode":"60594",
    "sg:province":"Hessen",
    "wof:name":"Tengelmann",
    "wof:placetype":"venue"
},
  "geometry": {"coordinates":[8.689994812,50.1044006348],"type":"Point"}
}