{
  "type": "Feature",
  "properties": {
    "iso:country":"DE",
    "sg:address":"Kirschstr. 28c",
    "sg:city":"Karlsruhe",
    "sg:phone":"+49 721/573948",
    "sg:postcode":"76189",
    "sg:province":"Baden-W\u00fcrttemberg",
    "wof:name":"Weick Grundst\u00fccksverwaltungs Gmbh",
    "wof:placetype":"venue"
},
  "geometry": {"coordinates":[8.3343029022,49.0027008057],"type":"Point"}
}