{
  "type": "Feature",
  "properties": {
    "iso:country":"DE",
    "sg:address":"Hochstr. 15",
    "sg:city":"Frankfurt",
    "sg:postcode":"60313",
    "sg:province":"Hessen",
    "wof:name":"The Iron Bed Company Gmbh",
    "wof:placetype":"venue"
},
  "geometry": {"coordinates":[8.678113,50.116554],"type":"Point"}
}