{
  "type": "Feature",
  "properties": {
    "iso:country":"DE",
    "sg:address":"Steiger 3",
    "sg:city":"Bessenbach",
    "sg:phone":"+49 6093/8670",
    "sg:postcode":"63856",
    "sg:province":"Bayern",
    "wof:name":"Fitmess Farm Herwig Gmbh",
    "wof:placetype":"venue"
},
  "geometry": {"coordinates":[9.2653217316,49.9969596863],"type":"Point"}
}