{
  "type": "Feature",
  "properties": {
    "iso:country":"DE",
    "sg:address":"Wettgasse 38",
    "sg:city":"Sch\u00f6naich",
    "sg:phone":"+49 7031/6360",
    "sg:postcode":"71101",
    "sg:province":"Baden-W\u00fcrttemberg",
    "wof:name":"Sch\u00f6nbuch-immobilien Gmbh",
    "wof:placetype":"venue"
},
  "geometry": {"coordinates":[9.0602827072,48.6564407349],"type":"Point"}
}