{
  "type": "Feature",
  "properties": {
    "iso:country":"DE",
    "sg:address":"Drachenburgstr. 29",
    "sg:city":"Bonn",
    "sg:phone":"+49 228/9348960",
    "sg:postcode":"53179",
    "sg:province":"Nordrhein-Westfalen",
    "wof:name":"F\u00fcrstenst\u00fcbchen",
    "wof:placetype":"venue"
},
  "geometry": {"coordinates":[7.1764397621,50.6662330627],"type":"Point"}
}