{
  "type": "Feature",
  "properties": {
    "iso:country":"DE",
    "sg:address":"Nymphenburger Str. 84",
    "sg:city":"M\u00fcnchen",
    "sg:postcode":"80636",
    "sg:province":"Bayern",
    "wof:name":"Lenart M\u00fcnchen Verlag Verwaltungs Gmbh",
    "wof:placetype":"venue"
},
  "geometry": {"coordinates":[11.5463447571,48.1500396729],"type":"Point"}
}