{
  "type": "Feature",
  "properties": {
    "iso:country":"DE",
    "sg:address":"Gerwigstr. 41",
    "sg:city":"Karlsruhe",
    "sg:phone":"+49 721/615631",
    "sg:postcode":"76131",
    "sg:province":"Baden-W\u00fcrttemberg",
    "wof:name":"Heinz B\u00e4\u00dfler",
    "wof:placetype":"venue"
},
  "geometry": {"coordinates":[8.4294509888,49.008682251],"type":"Point"}
}