{
  "type": "Feature",
  "properties": {
    "iso:country":"DE",
    "sg:address":"K\u00f6pperner Str. 100",
    "sg:city":"Wehrheim",
    "sg:phone":"+49 6081/95180",
    "sg:postcode":"61273",
    "sg:province":"Hessen",
    "wof:name":"Zur Sch\u00f6nen Aussicht",
    "wof:placetype":"venue"
},
  "geometry": {"coordinates":[8.5783166885,50.2909049988],"type":"Point"}
}