{
  "type": "Feature",
  "properties": {
    "iso:country":"DE",
    "sg:address":"St.-Martin-Weg 1",
    "sg:city":"H\u00f6hr-Grenzhausen",
    "sg:phone":"+49 2624/3209",
    "sg:postcode":"56203",
    "sg:province":"Rheinland-Pfalz",
    "wof:name":"Manfred Mihm",
    "wof:placetype":"venue"
},
  "geometry": {"coordinates":[7.669826,50.429031],"type":"Point"}
}