{
  "type": "Feature",
  "properties": {
    "iso:country":"DE",
    "sg:address":"Am Exerzierplatz 6",
    "sg:city":"Norderstedt",
    "sg:phone":"+49 40/5255143",
    "sg:postcode":"22844",
    "sg:province":"Schleswig-Holstein",
    "wof:name":"Monika Koch",
    "wof:placetype":"venue"
},
  "geometry": {"coordinates":[10.0071163177,53.7040672302],"type":"Point"}
}