{
  "type": "Feature",
  "properties": {
    "iso:country":"DE",
    "sg:address":"Bliesstr. 80",
    "sg:city":"Neunkirchen",
    "sg:postcode":"66538",
    "sg:province":"Saarland",
    "wof:name":"Hela Baupark",
    "wof:placetype":"venue"
},
  "geometry": {"coordinates":[7.2071919441,49.3515014648],"type":"Point"}
}