{
  "type": "Feature",
  "properties": {
    "iso:country":"DE",
    "sg:address":"Wilhelm-Ostwald-Str. 6",
    "sg:city":"M\u00fcnchen",
    "sg:phone":"+49 89/369953",
    "sg:postcode":"80805",
    "sg:province":"Bayern",
    "wof:name":"Brigitte W\u00fcrtz Kunstmaler",
    "wof:placetype":"venue"
},
  "geometry": {"coordinates":[11.599244,48.166748],"type":"Point"}
}