{
  "type": "Feature",
  "properties": {
    "iso:country":"DE",
    "sg:address":"Kirchstr. 28",
    "sg:city":"Hoya",
    "sg:phone":"+49 4251/2523",
    "sg:postcode":"27318",
    "sg:province":"Niedersachsen",
    "wof:name":"Walter H\u00fcbscher",
    "wof:placetype":"venue"
},
  "geometry": {"coordinates":[9.148679,52.808601],"type":"Point"}
}