{
  "type": "Feature",
  "properties": {
    "iso:country":"DE",
    "sg:address":"Am Markt 14",
    "sg:city":"Gettorf",
    "sg:phone":"+49 4346/36810",
    "sg:postcode":"24214",
    "sg:province":"Schleswig-Holstein",
    "wof:name":"K\u00f6nig Corlei\u00dfen Und Reimers Rechtsanw\u00e4lte Und Notare",
    "wof:placetype":"venue"
},
  "geometry": {"coordinates":[9.9739999771,54.4069519043],"type":"Point"}
}