{
  "type": "Feature",
  "properties": {
    "iso:country":"DE",
    "sg:address":"Amtsgerichtstr. 5",
    "sg:city":"Regen",
    "sg:phone":"+49 9921/94020",
    "sg:postcode":"94209",
    "sg:province":"Bayern",
    "wof:name":"Max Stangl",
    "wof:placetype":"venue"
},
  "geometry": {"coordinates":[13.127169,48.971676],"type":"Point"}
}