{
  "type": "Feature",
  "properties": {
    "iso:country":"DE",
    "sg:address":"Indersdorfer Str. 21",
    "sg:city":"Jetzendorf",
    "sg:phone":"+49 8137/3470",
    "sg:postcode":"85305",
    "sg:province":"Bayern",
    "wof:name":"Josefine Finkenzeller",
    "wof:placetype":"venue"
},
  "geometry": {"coordinates":[11.4184007645,48.4308357239],"type":"Point"}
}