{
  "type": "Feature",
  "properties": {
    "iso:country":"DE",
    "sg:address":"Hubertusweg",
    "sg:city":"Wardenburg",
    "sg:phone":"+49 4407/5932",
    "sg:postcode":"26203",
    "sg:province":"Niedersachsen",
    "wof:name":"Reiterverein H\u00f6ven",
    "wof:placetype":"venue"
},
  "geometry": {"coordinates":[8.2240619659,53.0287666321],"type":"Point"}
}