{
  "type": "Feature",
  "properties": {
    "iso:country":"DE",
    "sg:address":"Im Br\u00fchl 4",
    "sg:city":"Lollar",
    "sg:phone":"+49 6406/2541",
    "sg:postcode":"35457",
    "sg:province":"Hessen",
    "wof:name":"Egon Becker",
    "wof:placetype":"venue"
},
  "geometry": {"coordinates":[8.706360817,50.6727676392],"type":"Point"}
}