{
  "type": "Feature",
  "properties": {
    "iso:country":"DE",
    "sg:address":"Nahestr. 15",
    "sg:city":"Gensingen",
    "sg:phone":"+49 6727/952735",
    "sg:postcode":"55457",
    "sg:province":"Rheinland-Pfalz",
    "wof:name":"Peter Liebelt Zimmerei Und Bedachung Gmbh",
    "wof:placetype":"venue"
},
  "geometry": {"coordinates":[7.917721,49.894573],"type":"Point"}
}