{
  "type": "Feature",
  "properties": {
    "iso:country":"DE",
    "sg:address":"Halsbeker Str. 130",
    "sg:city":"Westerstede",
    "sg:phone":"+49 4488/89955",
    "sg:postcode":"26655",
    "sg:province":"Niedersachsen",
    "wof:name":"Eckstein Architekt",
    "wof:placetype":"venue"
},
  "geometry": {"coordinates":[7.882366,53.325638],"type":"Point"}
}