{
  "type": "Feature",
  "properties": {
    "iso:country":"DE",
    "sg:address":"Marktstr. 32",
    "sg:city":"Winnenden",
    "sg:phone":"+49 7195/920426",
    "sg:postcode":"71364",
    "sg:province":"Baden-W\u00fcrttemberg",
    "wof:name":"Cafe Am Markt",
    "wof:placetype":"venue"
},
  "geometry": {"coordinates":[9.399089,48.876095],"type":"Point"}
}