{
  "type": "Feature",
  "properties": {
    "iso:country":"DE",
    "sg:address":"L\u00fchlingsgasse 5",
    "sg:city":"Unkel",
    "sg:phone":"+49 2224/3315",
    "sg:postcode":"53572",
    "sg:province":"Rheinland-Pfalz",
    "wof:name":"Zur Traube",
    "wof:placetype":"venue"
},
  "geometry": {"coordinates":[7.2154350281,50.6000175476],"type":"Point"}
}