{
  "type": "Feature",
  "properties": {
    "iso:country":"DE",
    "sg:address":"Pappelring 4",
    "sg:city":"Selmsdorf",
    "sg:phone":"+49 38823/21190",
    "sg:postcode":"23923",
    "sg:province":"Mecklenburg-Vorpommern",
    "wof:name":"Bernhard Stoeter Gmbh",
    "wof:placetype":"venue"
},
  "geometry": {"coordinates":[10.840508461,53.8824996948],"type":"Point"}
}