{
  "type": "Feature",
  "properties": {
    "iso:country":"DE",
    "sg:address":"Kardohrstr. 10",
    "sg:city":"Eutin",
    "sg:phone":"+49 4521/2415",
    "sg:postcode":"23701",
    "sg:province":"Schleswig-Holstein",
    "wof:name":"G\u00fcnter Wibberenz",
    "wof:placetype":"venue"
},
  "geometry": {"coordinates":[10.5905,54.130005],"type":"Point"}
}