{
  "type": "Feature",
  "properties": {
    "iso:country":"DE",
    "sg:address":"Kr\u00f6blitz",
    "sg:city":"Neunburg",
    "sg:phone":"+49 9672/859",
    "sg:postcode":"92431",
    "sg:province":"Bayern",
    "wof:name":"Schlo\u00dfbrauerei",
    "wof:placetype":"venue"
},
  "geometry": {"coordinates":[12.400847435,49.364982605],"type":"Point"}
}