{
  "type": "Feature",
  "properties": {
    "iso:country":"DE",
    "sg:address":"Obernburger Str. 123",
    "sg:city":"Stockstadt",
    "sg:phone":"+49 6027/1000",
    "sg:postcode":"63811",
    "sg:province":"Bayern",
    "wof:name":"Michael Kempf Schlosserei",
    "wof:placetype":"venue"
},
  "geometry": {"coordinates":[9.0745267868,49.9665031433],"type":"Point"}
}