{
  "type": "Feature",
  "properties": {
    "iso:country":"DE",
    "sg:address":"Fetscherstr. 74",
    "sg:city":"Dresden",
    "sg:phone":"+49 351/4416382",
    "sg:postcode":"01307",
    "sg:province":"Sachsen",
    "wof:name":"I. Strewe",
    "wof:placetype":"venue"
},
  "geometry": {"coordinates":[13.7779941559,51.054813385],"type":"Point"}
}