{
  "type": "Feature",
  "properties": {
    "iso:country":"DE",
    "sg:address":"Wittenwater 8 a",
    "sg:city":"Schwienau",
    "sg:phone":"+49 5822/9944",
    "sg:postcode":"29593",
    "sg:province":"Niedersachsen",
    "wof:name":"Wms-warenvertrieb Inh. Marc Schr\u00f6der",
    "wof:placetype":"venue"
},
  "geometry": {"coordinates":[10.410613,52.997459],"type":"Point"}
}