{
  "type": "Feature",
  "properties": {
    "iso:country":"DE",
    "sg:address":"Rohrackerstr. 78",
    "sg:city":"Stuttgart",
    "sg:phone":"+49 711/428993",
    "sg:postcode":"70329",
    "sg:province":"Baden-W\u00fcrttemberg",
    "wof:name":"Heinz Claar",
    "wof:placetype":"venue"
},
  "geometry": {"coordinates":[9.24172,48.758041],"type":"Point"}
}