{
  "type": "Feature",
  "properties": {
    "iso:country":"DE",
    "sg:address":"Kindinger Str. 22",
    "sg:city":"Kipfenberg",
    "sg:phone":"+49 8465/3166",
    "sg:postcode":"85110",
    "sg:province":"Bayern",
    "wof:name":"Dr. Med. Winfried Reiner",
    "wof:placetype":"venue"
},
  "geometry": {"coordinates":[11.3966350555,48.9521217346],"type":"Point"}
}