{
  "type": "Feature",
  "properties": {
    "iso:country":"DE",
    "sg:address":"D\u00fcrscheider Str. 13",
    "sg:city":"Burscheid",
    "sg:phone":"+49 2174/61380",
    "sg:postcode":"51399",
    "sg:province":"Nordrhein-Westfalen",
    "wof:name":"Werner Schulz",
    "wof:placetype":"venue"
},
  "geometry": {"coordinates":[7.0850129128,51.0719871521],"type":"Point"}
}