{
  "type": "Feature",
  "properties": {
    "iso:country":"DE",
    "sg:address":"Schmiedeberg 6",
    "sg:city":"Storkau",
    "sg:phone":"+49 3443/802283",
    "sg:postcode":"06667",
    "sg:province":"Sachsen-Anhalt",
    "wof:name":"Storkau",
    "wof:placetype":"venue"
},
  "geometry": {"coordinates":[11.9232997894,51.228313446],"type":"Point"}
}