{
  "type": "Feature",
  "properties": {
    "iso:country":"DE",
    "sg:address":"G\u00f6rlitzer Str 39",
    "sg:city":"G\u00f6rlitz",
    "sg:phone":"+49 3581/700030",
    "sg:postcode":"02827",
    "sg:province":"Sachsen",
    "wof:name":"Fahrzeugbau Schwerdtner",
    "wof:placetype":"venue"
},
  "geometry": {"coordinates":[14.9318189621,51.1471290588],"type":"Point"}
}