{
  "type": "Feature",
  "properties": {
    "iso:country":"DE",
    "sg:address":"Frieslandstr. 17",
    "sg:city":"Friedeburg",
    "sg:phone":"+49 4468/507",
    "sg:postcode":"26446",
    "sg:province":"Niedersachsen",
    "wof:name":"H. Sandomir",
    "wof:placetype":"venue"
},
  "geometry": {"coordinates":[7.85653,53.489601],"type":"Point"}
}