{
  "type": "Feature",
  "properties": {
    "iso:country":"DE",
    "sg:address":"K\u00f6lnische Str. 113",
    "sg:city":"Kassel",
    "sg:phone":"+49 561/18070",
    "sg:postcode":"34119",
    "sg:province":"Hessen",
    "wof:name":"G\u00fcnter D\u00e4hnel",
    "wof:placetype":"venue"
},
  "geometry": {"coordinates":[9.4757022858,51.3174362183],"type":"Point"}
}