{
  "type": "Feature",
  "properties": {
    "iso:country":"DE",
    "sg:address":"Pariser Str. 6",
    "sg:city":"Bochum",
    "sg:phone":"+49 234/14947",
    "sg:postcode":"44787",
    "sg:province":"Nordrhein-Westfalen",
    "wof:name":"Jugendmoden Schneider Kg",
    "wof:placetype":"venue"
},
  "geometry": {"coordinates":[7.219153,51.481682],"type":"Point"}
}