{
  "type": "Feature",
  "properties": {
    "iso:country":"DE",
    "sg:address":"H\u00f6lgesstr. 7",
    "sg:city":"Darmstadt",
    "sg:postcode":"64283",
    "sg:province":"Hessen",
    "wof:name":"Bh Beteiligungs Gmbh",
    "wof:placetype":"venue"
},
  "geometry": {"coordinates":[8.6545324326,49.8688964844],"type":"Point"}
}