{
  "type": "Feature",
  "properties": {
    "iso:country":"DE",
    "sg:address":"In den Seeg\u00e4rten 8",
    "sg:city":"Oftersheim",
    "sg:phone":"+49 6202/59530",
    "sg:postcode":"68723",
    "sg:province":"Baden-W\u00fcrttemberg",
    "wof:name":"Dr. W. Stange Rechtsanwalt",
    "wof:placetype":"venue"
},
  "geometry": {"coordinates":[8.5897006989,49.3717651367],"type":"Point"}
}