{
  "type": "Feature",
  "properties": {
    "iso:country":"DE",
    "sg:address":"Kantstr. 28",
    "sg:city":"Berlin",
    "sg:phone":"+49 30/3157030",
    "sg:postcode":"10623",
    "sg:province":"Berlin",
    "wof:name":"U. Sadowski Und R. Lebioda Architekten",
    "wof:placetype":"venue"
},
  "geometry": {"coordinates":[13.318925,52.50621],"type":"Point"}
}