{
  "type": "Feature",
  "properties": {
    "iso:country":"DE",
    "sg:address":"Dr.-Valentin-Koch-Str. 2",
    "sg:city":"Cham",
    "sg:phone":"+49 9971/30455",
    "sg:postcode":"93413",
    "sg:province":"Bayern",
    "wof:name":"Wilhelm Werner",
    "wof:placetype":"venue"
},
  "geometry": {"coordinates":[12.6294603348,49.2104988098],"type":"Point"}
}