{
  "type": "Feature",
  "properties": {
    "iso:country":"DE",
    "sg:address":"Stahlb\u00fchlstr. 29",
    "sg:city":"Weissach",
    "sg:phone":"+49 7044/3018",
    "sg:postcode":"71287",
    "sg:province":"Baden-W\u00fcrttemberg",
    "wof:name":"Ingo Pochert Ingenieur",
    "wof:placetype":"venue"
},
  "geometry": {"coordinates":[8.9021177292,48.8338088989],"type":"Point"}
}