{
  "type": "Feature",
  "properties": {
    "iso:country":"DE",
    "sg:address":"Industriegebiet-Kreuzwiese 12",
    "sg:city":"Rockenhausen",
    "sg:phone":"+49 4963/611286",
    "sg:postcode":"67806",
    "sg:province":"Rheinland-Pfalz",
    "wof:name":"Leipold & Co. Gmbh",
    "wof:placetype":"venue"
},
  "geometry": {"coordinates":[7.825768,49.63866],"type":"Point"}
}