{
  "type": "Feature",
  "properties": {
    "iso:country":"DE",
    "sg:address":"Freiligrathstr. 352",
    "sg:city":"Wilhelmshaven",
    "sg:phone":"+49 4944/2184527",
    "sg:postcode":"26386",
    "sg:province":"Niedersachsen",
    "wof:name":"Wilhelm J. M\u00dcller",
    "wof:placetype":"venue"
},
  "geometry": {"coordinates":[8.1082,53.551651],"type":"Point"}
}