{
  "type": "Feature",
  "properties": {
    "iso:country":"DE",
    "sg:address":"Am Obstgarten 11",
    "sg:city":"Mainz",
    "sg:phone":"+49 6131/690855",
    "sg:postcode":"55120",
    "sg:province":"Rheinland-Pfalz",
    "wof:name":"\u00d6zak Bau Gmbh",
    "wof:placetype":"venue"
},
  "geometry": {"coordinates":[8.219871,50.014755],"type":"Point"}
}