{
  "type": "Feature",
  "properties": {
    "iso:country":"DE",
    "sg:address":"Hauptstr. 142",
    "sg:city":"Mainaschaff",
    "sg:phone":"+49 6021/74281",
    "sg:postcode":"63814",
    "sg:province":"Bayern",
    "wof:name":"Ephesus",
    "wof:placetype":"venue"
},
  "geometry": {"coordinates":[9.0993566513,49.9796257019],"type":"Point"}
}