{
  "type": "Feature",
  "properties": {
    "iso:country":"DE",
    "sg:address":"Angerstr. 4",
    "sg:city":"Sch\u00f6nheide",
    "sg:phone":"+49 37755/2664",
    "sg:postcode":"08304",
    "sg:province":"Sachsen",
    "wof:name":"Sch\u00f6nheider Wochenblatt",
    "wof:placetype":"venue"
},
  "geometry": {"coordinates":[12.5148391724,50.5036277771],"type":"Point"}
}