{
  "type": "Feature",
  "properties": {
    "iso:country":"DE",
    "sg:address":"Im Vogelsang 6",
    "sg:city":"Birkenwerder",
    "sg:phone":"+49 3303/503903",
    "sg:postcode":"16547",
    "sg:province":"Brandenburg",
    "wof:name":"Dr. J. Herrmann Rechtsanwalt",
    "wof:placetype":"venue"
},
  "geometry": {"coordinates":[13.2983818054,52.6890792847],"type":"Point"}
}