{
  "type": "Feature",
  "properties": {
    "iso:country":"DE",
    "sg:address":"Christian-Lassen-Str. 6",
    "sg:city":"Bonn",
    "sg:phone":"+49 228/9671660",
    "sg:postcode":"53117",
    "sg:province":"Nordrhein-Westfalen",
    "wof:name":"J\u00fcrgen Emmerich",
    "wof:placetype":"venue"
},
  "geometry": {"coordinates":[7.0594081879,50.7522926331],"type":"Point"}
}