{
  "type": "Feature",
  "properties": {
    "iso:country":"DE",
    "sg:address":"Schillerstr. 15",
    "sg:city":"Bergrheinfeld",
    "sg:phone":"+49 9721/90143",
    "sg:postcode":"97493",
    "sg:province":"Bayern",
    "wof:name":"Kestler Bauger\u00e4te Gmbh",
    "wof:placetype":"venue"
},
  "geometry": {"coordinates":[10.185825,50.01247],"type":"Point"}
}