{
  "type": "Feature",
  "properties": {
    "iso:country":"DE",
    "sg:address":"Hasenbergsteige 14",
    "sg:city":"Stuttgart",
    "sg:phone":"+49 711/6155100",
    "sg:postcode":"70178",
    "sg:province":"Baden-W\u00fcrttemberg",
    "wof:name":"Anlagen Vermittlung Schwaben Verwaltungs Gmbh",
    "wof:placetype":"venue"
},
  "geometry": {"coordinates":[9.1613292694,48.7679901123],"type":"Point"}
}