{
  "type": "Feature",
  "properties": {
    "iso:country":"DE",
    "sg:address":"Lessingstr. 6",
    "sg:city":"Weimar",
    "sg:phone":"+49 3643/401464",
    "sg:postcode":"99425",
    "sg:province":"Th\u00fcringen",
    "wof:name":"Wsm Weimarer Spezialmontagen- Und Industrieservice Gmbh",
    "wof:placetype":"venue"
},
  "geometry": {"coordinates":[11.32385,50.964512],"type":"Point"}
}