{
  "type": "Feature",
  "properties": {
    "iso:country":"DE",
    "sg:address":"Benzstr. 1b",
    "sg:city":"Kirchheim",
    "sg:phone":"+49 89/99153015",
    "sg:postcode":"85551",
    "sg:province":"Bayern",
    "wof:name":"Holz-elektronik Gmbh",
    "wof:placetype":"venue"
},
  "geometry": {"coordinates":[11.7669420242,48.1788139343],"type":"Point"}
}