{
  "type": "Feature",
  "properties": {
    "iso:country":"DE",
    "sg:address":"Kronenbergstr. 2",
    "sg:city":"Bietigheim-Bissingen",
    "sg:phone":"+49 7142/770161",
    "sg:postcode":"74321",
    "sg:province":"Baden-W\u00fcrttemberg",
    "wof:name":"Eisdiele Olivier",
    "wof:placetype":"venue"
},
  "geometry": {"coordinates":[9.129901,48.96022],"type":"Point"}
}