{
  "type": "Feature",
  "properties": {
    "iso:country":"DE",
    "sg:address":"Zum Riesbach 21A",
    "sg:city":"Langelsheim",
    "sg:phone":"+49 5325/6218",
    "sg:postcode":"38685",
    "sg:province":"Niedersachsen",
    "wof:name":"Klaus Bertuch",
    "wof:placetype":"venue"
},
  "geometry": {"coordinates":[10.2854223251,51.8831748962],"type":"Point"}
}