{
  "type": "Feature",
  "properties": {
    "iso:country":"DE",
    "sg:address":"Sternstr.46",
    "sg:city":"Dortmund",
    "sg:phone":"+49 231/9143414",
    "sg:postcode":"44137",
    "sg:province":"Nordrhein-Westfalen",
    "wof:name":"Fa. Drei\u00dfig Werbung",
    "wof:placetype":"venue"
},
  "geometry": {"coordinates":[7.441196,51.509865],"type":"Point"}
}