{
  "type": "Feature",
  "properties": {
    "iso:country":"DE",
    "sg:address":"Georgenstr 3",
    "sg:city":"M\u00fcnchen",
    "sg:phone":"+49 35341/6320",
    "sg:postcode":"80799",
    "sg:province":"Bayern",
    "wof:name":"Tecoss Kopier- Und B\u00fcroausstatter Gmbh",
    "wof:placetype":"venue"
},
  "geometry": {"coordinates":[13.3930473328,51.5146102905],"type":"Point"}
}