{
  "type": "Feature",
  "properties": {
    "iso:country":"DE",
    "sg:address":"Marstallstr. 10",
    "sg:city":"Altenburg",
    "sg:phone":"+49 3447/504270",
    "sg:postcode":"04600",
    "sg:province":"Th\u00fcringen",
    "wof:name":"J\u00f6rg Stibi Ingenieur",
    "wof:placetype":"venue"
},
  "geometry": {"coordinates":[12.4423723221,50.9876708984],"type":"Point"}
}