{
  "type": "Feature",
  "properties": {
    "iso:country":"DE",
    "sg:address":"Kernerstr. 11",
    "sg:city":"Stuttgart",
    "sg:phone":"+49 711/2864187",
    "sg:postcode":"70182",
    "sg:province":"Baden-W\u00fcrttemberg",
    "wof:name":"Regina Kuhn Fotodesign",
    "wof:placetype":"venue"
},
  "geometry": {"coordinates":[9.1902923584,48.7848167419],"type":"Point"}
}