{
  "type": "Feature",
  "properties": {
    "iso:country":"DE",
    "sg:address":"Hauptstr. 33",
    "sg:city":"Th\u00f6rnich",
    "sg:phone":"+49 6507/3556",
    "sg:postcode":"54340",
    "sg:province":"Rheinland-Pfalz",
    "wof:name":"Karl-walter Botzet",
    "wof:placetype":"venue"
},
  "geometry": {"coordinates":[6.839703083,49.8311767578],"type":"Point"}
}