{
  "type": "Feature",
  "properties": {
    "iso:country":"DE",
    "sg:address":"Zeche Ernestine 23",
    "sg:city":"Essen",
    "sg:phone":"+49 4920/1294000",
    "sg:postcode":"45141",
    "sg:province":"Nordrhein-Westfalen",
    "wof:name":"Fritz Berger Gmbh",
    "wof:placetype":"venue"
},
  "geometry": {"coordinates":[7.0471692085,51.4717216492],"type":"Point"}
}