{
  "type": "Feature",
  "properties": {
    "iso:country":"DE",
    "sg:address":"Vennekenweg 1",
    "sg:city":"Raesfeld",
    "sg:phone":"+49 2865/95760",
    "sg:postcode":"46348",
    "sg:province":"Nordrhein-Westfalen",
    "wof:name":"B\u00e4uerliche Bezugs- Und Absatzgenossenschaft",
    "wof:placetype":"venue"
},
  "geometry": {"coordinates":[6.8324022293,51.7752723694],"type":"Point"}
}