{
  "type": "Feature",
  "properties": {
    "iso:country":"DE",
    "sg:address":"Zeppelinweg 7",
    "sg:city":"M\u00f6lln",
    "sg:phone":"+49 4542/3030",
    "sg:postcode":"23879",
    "sg:province":"Schleswig-Holstein",
    "wof:name":"Krohn Und Tiedemann Ingenieure",
    "wof:placetype":"venue"
},
  "geometry": {"coordinates":[10.6739597321,53.6053161621],"type":"Point"}
}