{
  "type": "Feature",
  "properties": {
    "iso:country":"DE",
    "sg:address":"M\u00fchlenstr. 19",
    "sg:city":"L\u00fcbeck",
    "sg:phone":"+49 451/76441",
    "sg:postcode":"23552",
    "sg:province":"Schleswig-Holstein",
    "wof:name":"Bei Ulla",
    "wof:placetype":"venue"
},
  "geometry": {"coordinates":[10.6862668991,53.8637428284],"type":"Point"}
}