{
  "type": "Feature",
  "properties": {
    "iso:country":"DE",
    "sg:address":"Jungfernstieg 26-28",
    "sg:city":"Hamburg",
    "sg:postcode":"20354",
    "sg:province":"Hamburg",
    "wof:name":"Petite Poupette Babymoden G. Rather Kg",
    "wof:placetype":"venue"
},
  "geometry": {"coordinates":[9.9913244247,53.5538787842],"type":"Point"}
}