{
  "type": "Feature",
  "properties": {
    "iso:country":"DE",
    "sg:address":"Dachelhofer Str. 75",
    "sg:city":"Schwandorf",
    "sg:phone":"+49 9431/21486",
    "sg:postcode":"92421",
    "sg:province":"Bayern",
    "wof:name":"E. Wiedmann",
    "wof:placetype":"venue"
},
  "geometry": {"coordinates":[12.090242,49.32095],"type":"Point"}
}