{
  "type": "Feature",
  "properties": {
    "iso:country":"DE",
    "sg:address":"Rubensstr. 5",
    "sg:city":"Kassel",
    "sg:phone":"+49 561/285980",
    "sg:postcode":"34121",
    "sg:province":"Hessen",
    "wof:name":"Uwe Kaufhold Agentur F\u00fcr",
    "wof:placetype":"venue"
},
  "geometry": {"coordinates":[9.4813499451,51.3067474365],"type":"Point"}
}