{
  "type": "Feature",
  "properties": {
    "iso:country":"DE",
    "sg:address":"M\u00f6nsheimer Str. 20",
    "sg:city":"Wimsheim",
    "sg:postcode":"71299",
    "sg:province":"Baden-W\u00fcrttemberg",
    "wof:name":"Logopak Vertriebsges. S\u00fcd Mbh",
    "wof:placetype":"venue"
},
  "geometry": {"coordinates":[8.8307390213,48.8519248962],"type":"Point"}
}