{
  "type": "Feature",
  "properties": {
    "iso:country":"DE",
    "sg:address":"Gro\u00dfe Kirchgasse 27",
    "sg:city":"Annaberg-Buchholz",
    "sg:phone":"+49 3733/44186",
    "sg:postcode":"09456",
    "sg:province":"Sachsen",
    "wof:name":"Musikhaus S\u00fc\u00df Inh. Stephan S\u00fc\u00df",
    "wof:placetype":"venue"
},
  "geometry": {"coordinates":[13.0058879852,50.5778579712],"type":"Point"}
}