{
  "type": "Feature",
  "properties": {
    "iso:country":"DE",
    "sg:address":"Kolonnadenstr. 11",
    "sg:city":"Leipzig",
    "sg:phone":"+49 341/9607066",
    "sg:postcode":"04109",
    "sg:province":"Sachsen",
    "wof:name":"Bierstube",
    "wof:placetype":"venue"
},
  "geometry": {"coordinates":[12.3670606613,51.3379096985],"type":"Point"}
}