{
  "type": "Feature",
  "properties": {
    "iso:country":"DE",
    "sg:address":"H\u00f6genauer Weg 8",
    "sg:city":"Berg im Gau",
    "sg:phone":"+49 8433/369",
    "sg:postcode":"86562",
    "sg:province":"Bayern",
    "wof:name":"J. Schie\u00dfl",
    "wof:placetype":"venue"
},
  "geometry": {"coordinates":[11.242222,48.62624],"type":"Point"}
}