{
  "type": "Feature",
  "properties": {
    "iso:country":"DE",
    "sg:address":"Rothenburger Str. 1",
    "sg:city":"Schnelldorf",
    "sg:phone":"+49 7950/667",
    "sg:postcode":"91625",
    "sg:province":"Bayern",
    "wof:name":"Friedrich Weinberger Gmbh & Co. Kg",
    "wof:placetype":"venue"
},
  "geometry": {"coordinates":[10.1776885986,49.1983718872],"type":"Point"}
}