{
  "type": "Feature",
  "properties": {
    "iso:country":"DE",
    "sg:address":"Werderring 5",
    "sg:city":"Freiburg",
    "sg:phone":"+49 761/387010",
    "sg:postcode":"79098",
    "sg:province":"Baden-W\u00fcrttemberg",
    "wof:name":"Ihd Industrie-handwerker- Dienst Personal-leasing Gmbh",
    "wof:placetype":"venue"
},
  "geometry": {"coordinates":[7.8496551514,47.9985389709],"type":"Point"}
}