{
  "type": "Feature",
  "properties": {
    "iso:country":"DE",
    "sg:address":"Rubensstr. 50",
    "sg:city":"M\u00fcnster",
    "sg:phone":"+49 2501/27670",
    "sg:postcode":"48165",
    "sg:province":"Nordrhein-Westfalen",
    "wof:name":"Hartmut Benz Unternehmensberatung Edv",
    "wof:placetype":"venue"
},
  "geometry": {"coordinates":[7.674738884,51.9022102356],"type":"Point"}
}