{
  "type": "Feature",
  "properties": {
    "iso:country":"DE",
    "sg:address":"D\u00fcsseldorfer Str. 540",
    "sg:city":"Duisburg",
    "sg:phone":"+49 203/774158",
    "sg:postcode":"47055",
    "sg:province":"Nordrhein-Westfalen",
    "wof:name":"Horst Abels",
    "wof:placetype":"venue"
},
  "geometry": {"coordinates":[6.76152,51.399529],"type":"Point"}
}