{
  "type": "Feature",
  "properties": {
    "iso:country":"DE",
    "sg:address":"Rathausstr. 99",
    "sg:city":"Berlin",
    "sg:postcode":"12105",
    "sg:province":"Berlin",
    "wof:name":"Univex Bau Gmbh",
    "wof:placetype":"venue"
},
  "geometry": {"coordinates":[13.378833,52.451302],"type":"Point"}
}