{
  "type": "Feature",
  "properties": {
    "iso:country":"DE",
    "sg:address":"Herrenteichsstr 1",
    "sg:city":"Osnabr\u00fcck",
    "sg:phone":"+49 541/350600",
    "sg:postcode":"49074",
    "sg:province":"Niedersachsen",
    "wof:name":"Bundesverband Windenergie Ev",
    "wof:placetype":"venue"
},
  "geometry": {"coordinates":[8.0480079651,52.275932312],"type":"Point"}
}