{
  "type": "Feature",
  "properties": {
    "iso:country":"DE",
    "sg:address":"Am See 3",
    "sg:city":"Wusterwitz",
    "sg:phone":"+49 33839/61488",
    "sg:postcode":"14789",
    "sg:province":"Brandenburg",
    "wof:name":"Pizzeria La Toscana",
    "wof:placetype":"venue"
},
  "geometry": {"coordinates":[12.3946914673,52.3623352051],"type":"Point"}
}