{
  "type": "Feature",
  "properties": {
    "iso:country":"DE",
    "sg:address":"Br\u00fcckenstr. 5a",
    "sg:city":"Berlin",
    "sg:phone":"+49 30/246040",
    "sg:postcode":"10179",
    "sg:province":"Berlin",
    "wof:name":"Deutsche Auto-leasing Gmbh",
    "wof:placetype":"venue"
},
  "geometry": {"coordinates":[13.417564,52.512798],"type":"Point"}
}