{
  "type": "Feature",
  "properties": {
    "iso:country":"DE",
    "sg:address":"Gartenstr. 11",
    "sg:city":"H\u00f6chst",
    "sg:phone":"+49 6163/2298",
    "sg:postcode":"64739",
    "sg:province":"Hessen",
    "wof:name":"Wilhelm Volk Mech. Werkstatt",
    "wof:placetype":"venue"
},
  "geometry": {"coordinates":[9.231185,50.206005],"type":"Point"}
}