{
  "type": "Feature",
  "properties": {
    "iso:country":"DE",
    "sg:address":"Ruppiner Stra\u00dfe 57",
    "sg:city":"Kremmen (Kreis Oberhavel)",
    "sg:phone":"+49 33055",
    "sg:postcode":"16766",
    "sg:province":"Brandenburg",
    "wof:name":"Rsimmobilien Gmbh",
    "wof:placetype":"venue"
},
  "geometry": {"coordinates":[13.0275859833,52.7650337219],"type":"Point"}
}