{
  "type": "Feature",
  "properties": {
    "iso:country":"DE",
    "sg:address":"B\u00fclte 5",
    "sg:city":"Aschendorf",
    "sg:phone":"+49 4962/1358",
    "sg:postcode":"26871",
    "sg:province":"Niedersachsen",
    "wof:name":"Hermann Thesing",
    "wof:placetype":"venue"
},
  "geometry": {"coordinates":[7.42354,53.072861],"type":"Point"}
}