{
  "type": "Feature",
  "properties": {
    "iso:country":"DE",
    "sg:address":"Hauptstr. 145",
    "sg:city":"Herbolzheim",
    "sg:phone":"+49 7643/383",
    "sg:postcode":"79336",
    "sg:province":"Baden-W\u00fcrttemberg",
    "wof:name":"Felsenkeller",
    "wof:placetype":"venue"
},
  "geometry": {"coordinates":[7.7797660828,48.2157974243],"type":"Point"}
}