{
  "type": "Feature",
  "properties": {
    "iso:country":"DE",
    "sg:address":"Plittersdorfer Str. 14",
    "sg:city":"Bonn",
    "sg:phone":"+49 228/9563360",
    "sg:postcode":"53173",
    "sg:province":"Nordrhein-Westfalen",
    "wof:name":"G. Jerga",
    "wof:placetype":"venue"
},
  "geometry": {"coordinates":[7.153719902,50.6871681213],"type":"Point"}
}