{
  "type": "Feature",
  "properties": {
    "iso:country":"DE",
    "sg:address":"Zeppelinstr. 21",
    "sg:city":"Aschau",
    "sg:phone":"+49 8638/3767",
    "sg:postcode":"84544",
    "sg:province":"Bayern",
    "wof:name":"Seb.r. B\u00fccherl Schweissereibedarfshdl.",
    "wof:placetype":"venue"
},
  "geometry": {"coordinates":[12.375998,48.187729],"type":"Point"}
}