{
  "type": "Feature",
  "properties": {
    "iso:country":"DE",
    "sg:address":"Gildenstr. 8",
    "sg:city":"Gladbeck",
    "sg:phone":"+49 2043/21146",
    "sg:postcode":"45964",
    "sg:province":"Nordrhein-Westfalen",
    "wof:name":"Karl Goedecke Steuerberater",
    "wof:placetype":"venue"
},
  "geometry": {"coordinates":[6.9848198891,51.5682449341],"type":"Point"}
}