{
  "type": "Feature",
  "properties": {
    "iso:country":"DE",
    "sg:address":"Verborgstra\u00dfe",
    "sg:city":"Emmerich",
    "sg:phone":"+49 174 6601327",
    "sg:postcode":"46446",
    "sg:province":"Nordrhein-Westfalen",
    "wof:name":"Netzwerkparty Niederrhein",
    "wof:placetype":"venue"
},
  "geometry": {"coordinates":[6.22344,51.848492],"type":"Point"}
}