{
  "type": "Feature",
  "properties": {
    "iso:country":"DE",
    "sg:address":"Atzmannsberg 22",
    "sg:city":"Kemnath",
    "sg:phone":"+49 9642/550",
    "sg:postcode":"95478",
    "sg:province":"Bayern",
    "wof:name":"Josef Birkner",
    "wof:placetype":"venue"
},
  "geometry": {"coordinates":[11.954655,49.84198],"type":"Point"}
}