{
  "type": "Feature",
  "properties": {
    "iso:country":"DE",
    "sg:address":"Bahnhofstr. 24",
    "sg:city":"Oberhausen",
    "sg:phone":"+49 208/6350490",
    "sg:postcode":"46145",
    "sg:province":"Nordrhein-Westfalen",
    "wof:name":"Phoneshop Oberhausen",
    "wof:placetype":"venue"
},
  "geometry": {"coordinates":[6.8455748558,51.5142059326],"type":"Point"}
}