{
  "type": "Feature",
  "properties": {
    "iso:country":"DE",
    "sg:address":"Badstr.",
    "sg:city":"Blaibach",
    "sg:phone":"+49 9941/8844",
    "sg:postcode":"93476",
    "sg:province":"Bayern",
    "wof:name":"Freibad",
    "wof:placetype":"venue"
},
  "geometry": {"coordinates":[12.8094625473,49.1639976501],"type":"Point"}
}