{
  "type": "Feature",
  "properties": {
    "iso:country":"DE",
    "sg:address":"Wilhelm-Pieck-Str. 20",
    "sg:city":"P\u00f6llwitz",
    "sg:postcode":"07937",
    "sg:province":"Th\u00fcringen",
    "wof:name":"Landwirtschaftliche Argrar- Dienste Schulz & Bornhacke",
    "wof:placetype":"venue"
},
  "geometry": {"coordinates":[12.03457,50.622501],"type":"Point"}
}