{
  "type": "Feature",
  "properties": {
    "iso:country":"DE",
    "sg:address":"Gartenstr. 5",
    "sg:city":"Potsdam",
    "sg:phone":"+49 331/7480558",
    "sg:postcode":"14482",
    "sg:province":"Brandenburg",
    "wof:name":"Albert Haagen",
    "wof:placetype":"venue"
},
  "geometry": {"coordinates":[13.103915,52.384239],"type":"Point"}
}