{
  "type": "Feature",
  "properties": {
    "iso:country":"DE",
    "sg:address":"Schulstr. 44",
    "sg:city":"Plau",
    "sg:phone":"+49 38735/44567",
    "sg:postcode":"19395",
    "sg:province":"Mecklenburg-Vorpommern",
    "wof:name":"B. Thees",
    "wof:placetype":"venue"
},
  "geometry": {"coordinates":[12.1918888092,53.3706474304],"type":"Point"}
}