{
  "type": "Feature",
  "properties": {
    "iso:country":"DE",
    "sg:address":"Zieditzer Str. 26 a",
    "sg:city":"Schrobenhausen",
    "sg:postcode":"86529",
    "sg:province":"Bayern",
    "wof:name":"Schrobenhausener Geothermie Gmbh",
    "wof:placetype":"venue"
},
  "geometry": {"coordinates":[11.2714071274,48.5469741821],"type":"Point"}
}