{
  "type": "Feature",
  "properties": {
    "iso:country":"DE",
    "sg:address":"Kreuz\u00e4ckerstr. 35",
    "sg:city":"Heilbronn",
    "sg:phone":"+49 7131/255657",
    "sg:postcode":"74081",
    "sg:province":"Baden-W\u00fcrttemberg",
    "wof:name":"Koos Industrie- Lackierungen Gmbh",
    "wof:placetype":"venue"
},
  "geometry": {"coordinates":[9.203104,49.122101],"type":"Point"}
}