{
  "type": "Feature",
  "properties": {
    "iso:country":"DE",
    "sg:address":"Freiburger Str. 7",
    "sg:city":"Emmendingen",
    "sg:phone":"+49 7641/52676",
    "sg:postcode":"79312",
    "sg:province":"Baden-W\u00fcrttemberg",
    "wof:name":"G. Wolf",
    "wof:placetype":"venue"
},
  "geometry": {"coordinates":[7.853427887,48.1131782532],"type":"Point"}
}