{
  "type": "Feature",
  "properties": {
    "iso:country":"DE",
    "sg:address":"Bahnhofstr. 5",
    "sg:city":"Eberswalde",
    "sg:postcode":"16227",
    "sg:province":"Brandenburg",
    "wof:name":"Katholisches Pfarramt St. Theresia Vom Kinde Jesu",
    "wof:placetype":"venue"
},
  "geometry": {"coordinates":[13.7326879501,52.8352470398],"type":"Point"}
}