{
  "type": "Feature",
  "properties": {
    "iso:country":"DE",
    "sg:address":"Gr\u00fcntenstr. 30",
    "sg:city":"Sonthofen",
    "sg:phone":"+49 8321/2454",
    "sg:postcode":"87527",
    "sg:province":"Bayern",
    "wof:name":"Herbert Herz",
    "wof:placetype":"venue"
},
  "geometry": {"coordinates":[10.2815933228,47.5184364319],"type":"Point"}
}