{
  "type": "Feature",
  "properties": {
    "iso:country":"DE",
    "sg:address":"Berliner Str. 22",
    "sg:city":"Hagen",
    "sg:phone":"+49 2331/43224",
    "sg:postcode":"58135",
    "sg:province":"Nordrhein-Westfalen",
    "wof:name":"Errnst Fernholz Jun. E. K.",
    "wof:placetype":"venue"
},
  "geometry": {"coordinates":[7.4421358109,51.3514404297],"type":"Point"}
}