{
  "type": "Feature",
  "properties": {
    "iso:country":"DE",
    "sg:address":"Friedrich-Ebert-Str. 26",
    "sg:city":"Duisburg",
    "sg:phone":"+49 2065/58983",
    "sg:postcode":"47226",
    "sg:province":"Nordrhein-Westfalen",
    "wof:name":"Vereinsgastst\u00e4tte Kegelzentrum Rheinhausen",
    "wof:placetype":"venue"
},
  "geometry": {"coordinates":[6.7118759155,51.4120407104],"type":"Point"}
}