{
  "type": "Feature",
  "properties": {
    "iso:country":"DE",
    "sg:address":"Donnersbergerstr. 29",
    "sg:city":"M\u00fcnchen",
    "sg:phone":"+49 89/161151",
    "sg:postcode":"80634",
    "sg:province":"Bayern",
    "wof:name":"Norma Lebensmittel- Filialbetrieb Gmbh & Co. Kg",
    "wof:placetype":"venue"
},
  "geometry": {"coordinates":[11.5337848663,48.1492118835],"type":"Point"}
}