{
  "type": "Feature",
  "properties": {
    "iso:country":"DE",
    "sg:address":"D\u00fcsseldorfer Str. 450",
    "sg:city":"Duisburg",
    "sg:phone":"+49 203/777429",
    "sg:postcode":"47055",
    "sg:province":"Nordrhein-Westfalen",
    "wof:name":"Hardtm\u00fchle",
    "wof:placetype":"venue"
},
  "geometry": {"coordinates":[6.7645778656,51.4058494568],"type":"Point"}
}