{
  "type": "Feature",
  "properties": {
    "iso:country":"DE",
    "sg:address":"Untere Rheinstr. 15",
    "sg:city":"Reichenau",
    "sg:phone":"+49 7534/7415",
    "sg:postcode":"78479",
    "sg:province":"Baden-W\u00fcrttemberg",
    "wof:name":"Karl Deggelamnn",
    "wof:placetype":"venue"
},
  "geometry": {"coordinates":[9.056719,47.69273],"type":"Point"}
}