{
  "type": "Feature",
  "properties": {
    "iso:country":"DE",
    "sg:address":"Grietgasse 11",
    "sg:city":"Jena",
    "sg:phone":"+49 3641/53657",
    "sg:postcode":"07743",
    "sg:province":"Th\u00fcringen",
    "wof:name":"Huk-coburg",
    "wof:placetype":"venue"
},
  "geometry": {"coordinates":[11.5882949829,50.9261245728],"type":"Point"}
}