{
  "type": "Feature",
  "properties": {
    "iso:country":"DE",
    "sg:address":"Lachener Weg 200",
    "sg:city":"Ha\u00dfloch",
    "sg:phone":"+49 6324/2234",
    "sg:postcode":"67454",
    "sg:province":"Rheinland-Pfalz",
    "wof:name":"Hubertushof",
    "wof:placetype":"venue"
},
  "geometry": {"coordinates":[8.2467765808,49.3462982178],"type":"Point"}
}