{
  "type": "Feature",
  "properties": {
    "iso:country":"DE",
    "sg:address":"Hauptstr. 292",
    "sg:city":"Herne",
    "sg:phone":"+49 2325/50657",
    "sg:postcode":"44649",
    "sg:province":"Nordrhein-Westfalen",
    "wof:name":"W. K\u00fcpper",
    "wof:placetype":"venue"
},
  "geometry": {"coordinates":[7.1569957733,51.5348968506],"type":"Point"}
}