{
  "type": "Feature",
  "properties": {
    "iso:country":"DE",
    "sg:address":"Markdorfer Str. 76",
    "sg:city":"Friedrichshafen",
    "sg:phone":"+49 7544/71038",
    "sg:postcode":"88048",
    "sg:province":"Baden-W\u00fcrttemberg",
    "wof:name":"Schwaderer Fleischwaren Gmbh",
    "wof:placetype":"venue"
},
  "geometry": {"coordinates":[9.3993301392,47.6943283081],"type":"Point"}
}