{
  "type": "Feature",
  "properties": {
    "iso:country":"DE",
    "sg:address":"Bodestr. 1",
    "sg:city":"Halle",
    "sg:phone":"+49 345/2090348",
    "sg:postcode":"06122",
    "sg:province":"Sachsen-Anhalt",
    "wof:name":"Margarete Siebert",
    "wof:placetype":"venue"
},
  "geometry": {"coordinates":[11.9419488907,51.4832191467],"type":"Point"}
}