{
  "type": "Feature",
  "properties": {
    "iso:country":"DE",
    "sg:address":"Versmolder Str. 59",
    "sg:city":"Halle",
    "sg:phone":"+49 5201/10681",
    "sg:postcode":"33790",
    "sg:province":"Nordrhein-Westfalen",
    "wof:name":"H\u00f6rster-grill",
    "wof:placetype":"venue"
},
  "geometry": {"coordinates":[8.3001289368,52.0445518494],"type":"Point"}
}