{
  "type": "Feature",
  "properties": {
    "iso:country":"DE",
    "sg:address":"Postfach 29",
    "sg:city":"Tuttlingen",
    "sg:phone":"+49 7461/77496",
    "sg:postcode":"78501",
    "sg:province":"Baden-W\u00fcrttemberg",
    "wof:name":"Stiftung Zur F\u00f6rderung Der Arthroskopie",
    "wof:placetype":"venue"
},
  "geometry": {"coordinates":[8.7995796204,47.9894104004],"type":"Point"}
}