{
  "type": "Feature",
  "properties": {
    "iso:country":"DE",
    "sg:address":"Am Urnenfeld 6",
    "sg:city":"Schwarmstedt",
    "sg:phone":"+49 5071/1575",
    "sg:postcode":"29690",
    "sg:province":"Niedersachsen",
    "wof:name":"Ingeborg Kamm Masseurin",
    "wof:placetype":"venue"
},
  "geometry": {"coordinates":[9.619768,52.671593],"type":"Point"}
}