{
  "type": "Feature",
  "properties": {
    "iso:country":"DE",
    "sg:address":"Herrschinger Str. 9",
    "sg:city":"Andechs",
    "sg:phone":"+49 8152/2764",
    "sg:postcode":"82346",
    "sg:province":"Bayern",
    "wof:name":"Christa Und Josef Gro\u00df",
    "wof:placetype":"venue"
},
  "geometry": {"coordinates":[11.1829681396,47.9663696289],"type":"Point"}
}