{
  "type": "Feature",
  "properties": {
    "iso:country":"DE",
    "sg:address":"Neustadtstr. 1",
    "sg:city":"Mihla",
    "sg:phone":"+49 36924/42461",
    "sg:postcode":"99826",
    "sg:province":"Th\u00fcringen",
    "wof:name":"Eckard Scheler",
    "wof:placetype":"venue"
},
  "geometry": {"coordinates":[10.3343267441,51.0778045654],"type":"Point"}
}