{
  "type": "Feature",
  "properties": {
    "iso:country":"DE",
    "sg:address":"Westenfelder Str. 39",
    "sg:city":"Sundern",
    "sg:phone":"+49 2933/4586",
    "sg:postcode":"59846",
    "sg:province":"Nordrhein-Westfalen",
    "wof:name":"Anton Assheuer",
    "wof:placetype":"venue"
},
  "geometry": {"coordinates":[8.049958,51.322994],"type":"Point"}
}