{
  "type": "Feature",
  "properties": {
    "iso:country":"DE",
    "sg:address":"Winfriedstr. 11",
    "sg:city":"Paderborn",
    "sg:phone":"+49 5251/72110",
    "sg:postcode":"33098",
    "sg:province":"Nordrhein-Westfalen",
    "wof:name":"Clemens Bentfeld",
    "wof:placetype":"venue"
},
  "geometry": {"coordinates":[8.7588834763,51.7126998901],"type":"Point"}
}