{
  "type": "Feature",
  "properties": {
    "iso:country":"DE",
    "sg:address":"Gichenbach 75",
    "sg:city":"Gersfeld",
    "sg:phone":"+49 6656/201",
    "sg:postcode":"36129",
    "sg:province":"Hessen",
    "wof:name":"Florian Fr\u00f6hlich",
    "wof:placetype":"venue"
},
  "geometry": {"coordinates":[9.837822,50.435715],"type":"Point"}
}