{
  "type": "Feature",
  "properties": {
    "iso:country":"DE",
    "sg:address":"Leutersdorfer Str. 4",
    "sg:city":"Seifhennersdorf",
    "sg:postcode":"02782",
    "sg:province":"Sachsen",
    "wof:name":"Drogerie Friedl\u00e4nder",
    "wof:placetype":"venue"
},
  "geometry": {"coordinates":[14.618975,50.933392],"type":"Point"}
}