{
  "type": "Feature",
  "properties": {
    "iso:country":"DE",
    "sg:address":"Bauerschaft Voxtrup 59",
    "sg:city":"Osnabr\u00fcck",
    "sg:phone":"+49 541/389613",
    "sg:postcode":"49086",
    "sg:province":"Niedersachsen",
    "wof:name":"Heinrich Eggemann",
    "wof:placetype":"venue"
},
  "geometry": {"coordinates":[8.114156,52.24366],"type":"Point"}
}