{
  "type": "Feature",
  "properties": {
    "iso:country":"DE",
    "sg:address":"Goldene-Horn-Str. 7",
    "sg:city":"Bad Essen",
    "sg:postcode":"49152",
    "sg:province":"Niedersachsen",
    "wof:name":"Gemeindeb\u00fccherei Wimmer",
    "wof:placetype":"venue"
},
  "geometry": {"coordinates":[8.427,52.328266],"type":"Point"}
}