{
  "type": "Feature",
  "properties": {
    "iso:country":"DE",
    "sg:address":"Beethovenstr. 48",
    "sg:city":"Ilvesheim",
    "sg:phone":"+49 621/492001",
    "sg:postcode":"68549",
    "sg:province":"Baden-W\u00fcrttemberg",
    "wof:name":"Wirtschaftsgesellschaft Der Innung Des Kraftfahrzeugg.",
    "wof:placetype":"venue"
},
  "geometry": {"coordinates":[8.5508069992,49.4796295166],"type":"Point"}
}