{
  "type": "Feature",
  "properties": {
    "iso:country":"DE",
    "sg:address":"Auwiese 10 Kredenbach",
    "sg:city":"Kreuztal",
    "sg:phone":"+49 4964/16080",
    "sg:postcode":"57223",
    "sg:province":"Nordrhein-Westfalen",
    "wof:name":"Schunk Kohlenstofftechnik Gmbh",
    "wof:placetype":"venue"
},
  "geometry": {"coordinates":[7.2869777679,51.7356452942],"type":"Point"}
}