{
  "type": "Feature",
  "properties": {
    "iso:country":"DE",
    "sg:address":"Kirchstr. 5",
    "sg:city":"N\u00f6rvenich",
    "sg:phone":"+49 2426/6262",
    "sg:postcode":"52388",
    "sg:province":"Nordrhein-Westfalen",
    "wof:name":"Gertrud P\u00f6nsgen",
    "wof:placetype":"venue"
},
  "geometry": {"coordinates":[6.6442861557,50.8060379028],"type":"Point"}
}