{
  "type": "Feature",
  "properties": {
    "iso:country":"DE",
    "sg:address":"Alexanderstr. 263 a",
    "sg:city":"Oldenburg",
    "sg:phone":"+49 441/67616",
    "sg:postcode":"26127",
    "sg:province":"Niedersachsen",
    "wof:name":"U. Pannenborg",
    "wof:placetype":"venue"
},
  "geometry": {"coordinates":[8.201798,53.1646],"type":"Point"}
}