{
  "type": "Feature",
  "properties": {
    "iso:country":"DE",
    "sg:address":"Klingsorstr. 13",
    "sg:city":"Berlin",
    "sg:phone":"+49 30/7916595",
    "sg:postcode":"12167",
    "sg:province":"Berlin",
    "wof:name":"Rabien Spezialist Baumkuchen",
    "wof:placetype":"venue"
},
  "geometry": {"coordinates":[13.3304109573,52.4518165588],"type":"Point"}
}