{
  "type": "Feature",
  "properties": {
    "iso:country":"DE",
    "sg:address":"Rheindammstr. 25",
    "sg:city":"Mannheim",
    "sg:phone":"+49 621/813223",
    "sg:postcode":"68163",
    "sg:province":"Baden-W\u00fcrttemberg",
    "wof:name":"Coment Computer- L\u00f6sungen Gmbh",
    "wof:placetype":"venue"
},
  "geometry": {"coordinates":[8.4663553238,49.4754295349],"type":"Point"}
}