{
  "type": "Feature",
  "properties": {
    "iso:country":"DE",
    "sg:address":"Oberstocka 1",
    "sg:city":"Zandt",
    "sg:phone":"+49 9944/1321",
    "sg:postcode":"93499",
    "sg:province":"Bayern",
    "wof:name":"Anton Schlaghaufer Jun.",
    "wof:placetype":"venue"
},
  "geometry": {"coordinates":[12.725823,49.16827],"type":"Point"}
}