{
  "type": "Feature",
  "properties": {
    "iso:country":"DE",
    "sg:address":"Schubertstr. 27",
    "sg:city":"Eppelheim",
    "sg:phone":"+49 6221/762919",
    "sg:postcode":"69214",
    "sg:province":"Baden-W\u00fcrttemberg",
    "wof:name":"Ifc Gmbh",
    "wof:placetype":"venue"
},
  "geometry": {"coordinates":[8.632169,49.406124],"type":"Point"}
}