{
  "type": "Feature",
  "properties": {
    "iso:country":"DE",
    "sg:address":"Masurenweg 13",
    "sg:city":"Offenbach",
    "sg:phone":"+49 69/835914",
    "sg:postcode":"63069",
    "sg:province":"Hessen",
    "wof:name":"Kurt Seidel",
    "wof:placetype":"venue"
},
  "geometry": {"coordinates":[8.7710847855,50.0833015442],"type":"Point"}
}