{
  "type": "Feature",
  "properties": {
    "iso:country":"DE",
    "sg:address":"Bahnhofstr. 11",
    "sg:city":"Enkenbach-Alsenborn",
    "sg:phone":"+49 6303/4874",
    "sg:postcode":"67677",
    "sg:province":"Rheinland-Pfalz",
    "wof:name":"Wilfried Emmer Architekt",
    "wof:placetype":"venue"
},
  "geometry": {"coordinates":[7.899704,49.488724],"type":"Point"}
}