{
  "type": "Feature",
  "properties": {
    "iso:country":"DE",
    "sg:address":"K\u00f6lner Str. 38",
    "sg:city":"Bad M\u00fcnstereifel",
    "sg:phone":"+49 2253/4653",
    "sg:postcode":"53902",
    "sg:province":"Nordrhein-Westfalen",
    "wof:name":"Mm Moden Gmbh",
    "wof:placetype":"venue"
},
  "geometry": {"coordinates":[6.76528,50.55883],"type":"Point"}
}