{
  "type": "Feature",
  "properties": {
    "iso:country":"DE",
    "sg:address":"Industriestr. 35",
    "sg:city":"Wedel",
    "sg:phone":"+49 4103/82021",
    "sg:postcode":"22880",
    "sg:province":"Schleswig-Holstein",
    "wof:name":"Beyer & Sohn Gmbh",
    "wof:placetype":"venue"
},
  "geometry": {"coordinates":[9.732641,53.577343],"type":"Point"}
}