{
  "type": "Feature",
  "properties": {
    "iso:country":"DE",
    "sg:address":"B\u00e4ckerbrink 3",
    "sg:city":"Hohenhameln",
    "sg:phone":"+49 5128/387",
    "sg:postcode":"31249",
    "sg:province":"Niedersachsen",
    "wof:name":"Heinrich Ressmeyer",
    "wof:placetype":"venue"
},
  "geometry": {"coordinates":[10.0585193634,52.2427711487],"type":"Point"}
}