{
  "type": "Feature",
  "properties": {
    "iso:country":"DE",
    "sg:address":"Knochstr 14",
    "sg:city":"Saalfeld",
    "sg:phone":"+49 3671/33541",
    "sg:postcode":"07318",
    "sg:province":"Th\u00fcringen",
    "wof:name":"Ofenbaumeister Heinz Enke",
    "wof:placetype":"venue"
},
  "geometry": {"coordinates":[11.361603,50.643284],"type":"Point"}
}