{
  "type": "Feature",
  "properties": {
    "iso:country":"DE",
    "sg:address":"Schenefelder Chaussee 8",
    "sg:city":"Itzehoe",
    "sg:postcode":"25524",
    "sg:province":"Schleswig-Holstein",
    "wof:name":"Euro Play Nr. 30 Gmbh",
    "wof:placetype":"venue"
},
  "geometry": {"coordinates":[9.4940490723,53.9473114014],"type":"Point"}
}