{
  "type": "Feature",
  "properties": {
    "iso:country":"DE",
    "sg:address":"Dorf 23",
    "sg:city":"B\u00fclkau",
    "sg:phone":"+49 4754/739",
    "sg:postcode":"21782",
    "sg:province":"Niedersachsen",
    "wof:name":"Ev. Pfarramt B\u00fclkau",
    "wof:placetype":"venue"
},
  "geometry": {"coordinates":[8.9792585373,53.7485847473],"type":"Point"}
}