{
  "type": "Feature",
  "properties": {
    "iso:country":"DE",
    "sg:address":"Feldbrunnenstr. 58",
    "sg:city":"Hamburg",
    "sg:phone":"+49 40/4480410",
    "sg:postcode":"20148",
    "sg:province":"Hamburg",
    "wof:name":"Unesco Institut F\u00fcr P\u00e4dagogik",
    "wof:placetype":"venue"
},
  "geometry": {"coordinates":[9.9910049438,53.5683555603],"type":"Point"}
}