{
  "type": "Feature",
  "properties": {
    "iso:country":"DE",
    "sg:address":"Gl\u00fcsinger Str. 123",
    "sg:city":"Seevetal",
    "sg:phone":"+49 4105/4583",
    "sg:postcode":"21217",
    "sg:province":"Niedersachsen",
    "wof:name":"Seevetaler Stuben",
    "wof:placetype":"venue"
},
  "geometry": {"coordinates":[10.0163478851,53.4082374573],"type":"Point"}
}