{
  "type": "Feature",
  "properties": {
    "iso:country":"DE",
    "sg:address":"Pastor-L\u00fcpschen-Str. 33",
    "sg:city":"D\u00fcren",
    "sg:phone":"+49 2421/71832",
    "sg:postcode":"52351",
    "sg:province":"Nordrhein-Westfalen",
    "wof:name":"E. Hohl",
    "wof:placetype":"venue"
},
  "geometry": {"coordinates":[6.5059990883,50.7916717529],"type":"Point"}
}