{
  "type": "Feature",
  "properties": {
    "iso:country":"DE",
    "sg:address":"Urbanstr. 122",
    "sg:city":"Berlin",
    "sg:phone":"+49 30/6941123",
    "sg:postcode":"10967",
    "sg:province":"Berlin",
    "wof:name":"Hohlfeld-dichtungs- Und Armaturentechnik Gmbh",
    "wof:placetype":"venue"
},
  "geometry": {"coordinates":[13.417381,52.490864],"type":"Point"}
}