{
  "type": "Feature",
  "properties": {
    "iso:country":"DE",
    "sg:address":"Zeughausstr. 103",
    "sg:city":"Trier",
    "sg:phone":"+49 651/23383",
    "sg:postcode":"54292",
    "sg:province":"Rheinland-Pfalz",
    "wof:name":"Pizzeria La Pergola",
    "wof:placetype":"venue"
},
  "geometry": {"coordinates":[6.6492891312,49.765335083],"type":"Point"}
}