{
  "type": "Feature",
  "properties": {
    "iso:country":"DE",
    "sg:address":"Sieverner Str. 136",
    "sg:city":"Langen",
    "sg:phone":"+49 4743/315",
    "sg:postcode":"27607",
    "sg:province":"Niedersachsen",
    "wof:name":"Gastst\u00e4tte Zum Nordpol",
    "wof:placetype":"venue"
},
  "geometry": {"coordinates":[8.6146354675,53.6495552063],"type":"Point"}
}