{
  "type": "Feature",
  "properties": {
    "iso:country":"DE",
    "sg:address":"Bahnhofstr. 8",
    "sg:city":"Wetter",
    "sg:phone":"+49 2335/4565",
    "sg:postcode":"58300",
    "sg:province":"Nordrhein-Westfalen",
    "wof:name":"Alexa Eberling",
    "wof:placetype":"venue"
},
  "geometry": {"coordinates":[7.388078,51.386047],"type":"Point"}
}