{
  "type": "Feature",
  "properties": {
    "iso:country":"DE",
    "sg:address":"Panoramastr. 53",
    "sg:city":"Rosenfeld",
    "sg:phone":"+49 7428/2540",
    "sg:postcode":"72348",
    "sg:province":"Baden-W\u00fcrttemberg",
    "wof:name":"A. Feldberger",
    "wof:placetype":"venue"
},
  "geometry": {"coordinates":[8.726719,48.291134],"type":"Point"}
}