{
  "type": "Feature",
  "properties": {
    "iso:country":"DE",
    "sg:address":"Staig",
    "sg:city":"Staig",
    "sg:phone":"+49 7346/408",
    "sg:postcode":"89195",
    "sg:province":"Baden-W\u00fcrttemberg",
    "wof:name":"Raiffeisenbank Weihungstal Eg",
    "wof:placetype":"venue"
},
  "geometry": {"coordinates":[9.990341,48.299541],"type":"Point"}
}