{
  "type": "Feature",
  "properties": {
    "iso:country":"DE",
    "sg:address":"Alte Steige 28",
    "sg:city":"Langenau",
    "sg:phone":"+49 7345/7217",
    "sg:postcode":"89129",
    "sg:province":"Baden-W\u00fcrttemberg",
    "wof:name":"Franz Kaltenecker Elektroinstallation",
    "wof:placetype":"venue"
},
  "geometry": {"coordinates":[10.054433,48.482246],"type":"Point"}
}