{
  "type": "Feature",
  "properties": {
    "iso:country":"DE",
    "sg:address":"Nordwohlder Dorfstr. 4",
    "sg:city":"Bassum",
    "sg:phone":"+49 4249/316",
    "sg:postcode":"27211",
    "sg:province":"Niedersachsen",
    "wof:name":"Volksbank Bassum Eg",
    "wof:placetype":"venue"
},
  "geometry": {"coordinates":[8.74222,52.905151],"type":"Point"}
}