{
  "type": "Feature",
  "properties": {
    "iso:country":"DE",
    "sg:address":"Westring 401",
    "sg:city":"Wuppertal",
    "sg:phone":"+49 212/258210",
    "sg:postcode":"42329",
    "sg:province":"Nordrhein-Westfalen",
    "wof:name":"Richartz & Hilger Gmbh",
    "wof:placetype":"venue"
},
  "geometry": {"coordinates":[7.046991,51.209324],"type":"Point"}
}