{
  "type": "Feature",
  "properties": {
    "iso:country":"DE",
    "sg:address":"Poststr. 12",
    "sg:city":"Hauzenberg",
    "sg:phone":"+49 8586/2177",
    "sg:postcode":"94051",
    "sg:province":"Bayern",
    "wof:name":"Adolf Kinadeter",
    "wof:placetype":"venue"
},
  "geometry": {"coordinates":[13.6242265701,48.6487503052],"type":"Point"}
}