{
  "type": "Feature",
  "properties": {
    "iso:country":"DE",
    "sg:address":"Kirchgasse 19",
    "sg:city":"Markt Erlbach",
    "sg:phone":"+49 9106/337",
    "sg:postcode":"91459",
    "sg:province":"Bayern",
    "wof:name":"Walther Engelhardt",
    "wof:placetype":"venue"
},
  "geometry": {"coordinates":[10.654603,49.494251],"type":"Point"}
}