{
  "type": "Feature",
  "properties": {
    "iso:country":"DE",
    "sg:address":"Am Riesenberg 20",
    "sg:city":"Ense",
    "sg:phone":"+49 2938/1286",
    "sg:postcode":"59469",
    "sg:province":"Nordrhein-Westfalen",
    "wof:name":"Bernhard K\u00f6hler",
    "wof:placetype":"venue"
},
  "geometry": {"coordinates":[8.010346,51.499126],"type":"Point"}
}