{
  "type": "Feature",
  "properties": {
    "iso:country":"DE",
    "sg:address":"M\u00fchlgasse 11",
    "sg:city":"Friesenheim",
    "sg:phone":"+49 7821/67413",
    "sg:postcode":"77948",
    "sg:province":"Baden-W\u00fcrttemberg",
    "wof:name":"Antje Loleit-kuhlen",
    "wof:placetype":"venue"
},
  "geometry": {"coordinates":[7.8852391243,48.374168396],"type":"Point"}
}