{
  "type": "Feature",
  "properties": {
    "iso:country":"DE",
    "sg:address":"Saarstr. 183",
    "sg:city":"Kandel",
    "sg:phone":"+49 7275/1469",
    "sg:postcode":"76870",
    "sg:province":"Rheinland-Pfalz",
    "wof:name":"Arno Vollmer",
    "wof:placetype":"venue"
},
  "geometry": {"coordinates":[8.170732,49.074333],"type":"Point"}
}