{
  "type": "Feature",
  "properties": {
    "iso:country":"DE",
    "sg:address":"B\u00fcrgerm.-Kircher-Str. 17",
    "sg:city":"Meisenheim",
    "sg:phone":"+49 6753/94633",
    "sg:postcode":"55590",
    "sg:province":"Rheinland-Pfalz",
    "wof:name":"Christa R\u00e4dler",
    "wof:placetype":"venue"
},
  "geometry": {"coordinates":[7.669315815,49.7010993958],"type":"Point"}
}