{
  "type": "Feature",
  "properties": {
    "iso:country":"DE",
    "sg:address":"Merseburger Str. 45",
    "sg:city":"Querfurt",
    "sg:phone":"+49 34771/24460",
    "sg:postcode":"06268",
    "sg:province":"Sachsen-Anhalt",
    "wof:name":"Andreas Richter",
    "wof:placetype":"venue"
},
  "geometry": {"coordinates":[11.6039619446,51.3813018799],"type":"Point"}
}