{
  "type": "Feature",
  "properties": {
    "iso:country":"DE",
    "sg:address":"Schmitzinger Str. 27",
    "sg:city":"Waldshut-Tiengen",
    "sg:phone":"+49 7751/6754",
    "sg:postcode":"79761",
    "sg:province":"Baden-W\u00fcrttemberg",
    "wof:name":"Jadran Zvonimir Komljenovic",
    "wof:placetype":"venue"
},
  "geometry": {"coordinates":[8.2112026215,47.6308860779],"type":"Point"}
}