{
  "type": "Feature",
  "properties": {
    "iso:country":"DE",
    "sg:address":"Rathausstr. 1",
    "sg:city":"Heidelberg",
    "sg:phone":"+49 6221/332116",
    "sg:postcode":"69126",
    "sg:province":"Baden-W\u00fcrttemberg",
    "wof:name":"Vicente Palencia",
    "wof:placetype":"venue"
},
  "geometry": {"coordinates":[8.6880588531,49.380191803],"type":"Point"}
}