{
  "type": "Feature",
  "properties": {
    "iso:country":"DE",
    "sg:address":"Wolliner Str. 5",
    "sg:city":"Berlin",
    "sg:phone":"+49 30/4496502",
    "sg:postcode":"10435",
    "sg:province":"Berlin",
    "wof:name":"Klaus Schr\u00f6ter",
    "wof:placetype":"venue"
},
  "geometry": {"coordinates":[13.4043312073,52.5365066528],"type":"Point"}
}