{
  "type": "Feature",
  "properties": {
    "iso:country":"DE",
    "sg:address":"Im Hasenwinkel",
    "sg:city":"Barleben",
    "sg:phone":"+49 39203/61348",
    "sg:postcode":"39179",
    "sg:province":"Sachsen-Anhalt",
    "wof:name":"Passavant Werke Ag",
    "wof:placetype":"venue"
},
  "geometry": {"coordinates":[11.6046581268,52.1876754761],"type":"Point"}
}