{
  "type": "Feature",
  "properties": {
    "iso:country":"DE",
    "sg:address":"Oberstr. 50",
    "sg:city":"Niederkassel",
    "sg:phone":"+49 2208/74227",
    "sg:postcode":"53859",
    "sg:province":"Nordrhein-Westfalen",
    "wof:name":"Gerlinde Oepen Rechtsanw\u00e4ltin",
    "wof:placetype":"venue"
},
  "geometry": {"coordinates":[7.0445652008,50.7881546021],"type":"Point"}
}