{
  "type": "Feature",
  "properties": {
    "iso:country":"DE",
    "sg:address":"Dr.-Boecale-Str. 5",
    "sg:city":"Parsberg",
    "sg:phone":"+49 9492/94160",
    "sg:postcode":"92331",
    "sg:province":"Bayern",
    "wof:name":"Paracelsus-apotheke",
    "wof:placetype":"venue"
},
  "geometry": {"coordinates":[11.716376,49.160095],"type":"Point"}
}