{
  "type": "Feature",
  "properties": {
    "iso:country":"DE",
    "sg:address":"B\u00fclker Weg 26",
    "sg:city":"Strande",
    "sg:phone":"+49 4349/269",
    "sg:postcode":"24229",
    "sg:province":"Schleswig-Holstein",
    "wof:name":"Wolfgang Und Barbara Vogt Architekten",
    "wof:placetype":"venue"
},
  "geometry": {"coordinates":[10.177535,54.442009],"type":"Point"}
}