{
  "type": "Feature",
  "properties": {
    "iso:country":"DE",
    "sg:address":"Klosterstr. 2",
    "sg:city":"Rheine",
    "sg:phone":"+49 5971/13100",
    "sg:postcode":"48431",
    "sg:province":"Nordrhein-Westfalen",
    "wof:name":"R\u00fcschenschmidt & Co. Kg",
    "wof:placetype":"venue"
},
  "geometry": {"coordinates":[7.4376168251,52.2786026001],"type":"Point"}
}