{
  "type": "Feature",
  "properties": {
    "iso:country":"DE",
    "sg:address":"H\u00e4ger Str. 21",
    "sg:city":"L\u00f6hne",
    "sg:phone":"+49 5732/5740",
    "sg:postcode":"32584",
    "sg:province":"Nordrhein-Westfalen",
    "wof:name":"Heinrich Held",
    "wof:placetype":"venue"
},
  "geometry": {"coordinates":[8.740129,52.175922],"type":"Point"}
}