{
  "type": "Feature",
  "properties": {
    "iso:country":"DE",
    "sg:address":"Moltkestr. 23",
    "sg:city":"Bad Salzuflen",
    "sg:phone":"+49 5222/13240",
    "sg:postcode":"32105",
    "sg:province":"Nordrhein-Westfalen",
    "wof:name":"Pension Haus Hedwig-elisabeth",
    "wof:placetype":"venue"
},
  "geometry": {"coordinates":[8.7440624237,52.0895614624],"type":"Point"}
}