{
  "type": "Feature",
  "properties": {
    "iso:country":"DE",
    "sg:address":"Bellenbruchstr. 62",
    "sg:city":"Barntrup",
    "sg:phone":"+49 5263/1455",
    "sg:postcode":"32683",
    "sg:province":"Nordrhein-Westfalen",
    "wof:name":"Karl-hermann Hilker",
    "wof:placetype":"venue"
},
  "geometry": {"coordinates":[9.121736,51.997272],"type":"Point"}
}