{
  "type": "Feature",
  "properties": {
    "iso:country":"DE",
    "sg:address":"Winzerleite 4",
    "sg:city":"Passau",
    "sg:phone":"+49 851/88011",
    "sg:postcode":"94036",
    "sg:province":"Bayern",
    "wof:name":"Br\u00dcder Buchner Verm\u00d6gensverwaltung",
    "wof:placetype":"venue"
},
  "geometry": {"coordinates":[13.385545,48.589211],"type":"Point"}
}