{
  "type": "Feature",
  "properties": {
    "iso:country":"DE",
    "sg:address":"Kettelerstr. 3",
    "sg:city":"Rimpar",
    "sg:phone":"+49 9365/80750",
    "sg:postcode":"97222",
    "sg:province":"Bayern",
    "wof:name":"Aston Group Deutschland Gmbh",
    "wof:placetype":"venue"
},
  "geometry": {"coordinates":[9.9654817581,49.849319458],"type":"Point"}
}