{
  "type": "Feature",
  "properties": {
    "iso:country":"DE",
    "sg:address":"Ostende 5",
    "sg:city":"Leipzig",
    "sg:phone":"+49 34297/13445",
    "sg:postcode":"04288",
    "sg:province":"Sachsen",
    "wof:name":"Kleinig",
    "wof:placetype":"venue"
},
  "geometry": {"coordinates":[12.47198,51.285793],"type":"Point"}
}