{
  "type": "Feature",
  "properties": {
    "iso:country":"DE",
    "sg:address":"Marktplatz 4",
    "sg:city":"Steingaden",
    "sg:phone":"+49 8862/320",
    "sg:postcode":"86989",
    "sg:province":"Bayern",
    "wof:name":"Max Hintermair",
    "wof:placetype":"venue"
},
  "geometry": {"coordinates":[10.8609209061,47.7013320923],"type":"Point"}
}