{
  "type": "Feature",
  "properties": {
    "iso:country":"DE",
    "sg:address":"Ochsenzoller Str. 103",
    "sg:city":"Norderstedt",
    "sg:postcode":"22848",
    "sg:province":"Schleswig-Holstein",
    "wof:name":"Z\u00fclfikar-d\u00f6ner-produktion Gmbh",
    "wof:placetype":"venue"
},
  "geometry": {"coordinates":[9.9799661636,53.681804657],"type":"Point"}
}