{
  "type": "Feature",
  "properties": {
    "iso:country":"DE",
    "sg:address":"Kurf\u00fcrstenstr.",
    "sg:city":"Alzey",
    "sg:phone":"+49 6731/8809",
    "sg:postcode":"55232",
    "sg:province":"Rheinland-Pfalz",
    "wof:name":"D. Clauss",
    "wof:placetype":"venue"
},
  "geometry": {"coordinates":[8.1251268387,49.745426178],"type":"Point"}
}