{
  "type": "Feature",
  "properties": {
    "iso:country":"DE",
    "sg:address":"Delitzscher Str. 49a",
    "sg:city":"Halle",
    "sg:postcode":"06112",
    "sg:province":"Sachsen-Anhalt",
    "wof:name":"Hans-j\u00fcrgen Kurek Gmbh",
    "wof:placetype":"venue"
},
  "geometry": {"coordinates":[11.9990577698,51.4789505005],"type":"Point"}
}