{
  "type": "Feature",
  "properties": {
    "iso:country":"DE",
    "sg:address":"Hiltensweiler 18",
    "sg:city":"Tettnang",
    "sg:phone":"+49 7543/8311",
    "sg:postcode":"88069",
    "sg:province":"Baden-W\u00fcrttemberg",
    "wof:name":"Willi Bucher",
    "wof:placetype":"venue"
},
  "geometry": {"coordinates":[9.6579189301,47.6245384216],"type":"Point"}
}