{
  "type": "Feature",
  "properties": {
    "iso:country":"DE",
    "sg:address":"Ernst-Reuter-Allee 12",
    "sg:city":"Magdeburg",
    "sg:phone":"+49 391/5414196",
    "sg:postcode":"39104",
    "sg:province":"Sachsen-Anhalt",
    "wof:name":"D\u00fcnnebeil Umz\u00fcge",
    "wof:placetype":"venue"
},
  "geometry": {"coordinates":[11.6370811462,52.1310844421],"type":"Point"}
}