{
  "type": "Feature",
  "properties": {
    "iso:country":"DE",
    "sg:address":"Cliev 8",
    "sg:city":"K\u00fcrten",
    "sg:phone":"+49 2207/81604",
    "sg:postcode":"51515",
    "sg:province":"Nordrhein-Westfalen",
    "wof:name":"Willi Kimmel Gmbh",
    "wof:placetype":"venue"
},
  "geometry": {"coordinates":[7.199231,51.033123],"type":"Point"}
}