{
  "type": "Feature",
  "properties": {
    "iso:country":"DE",
    "sg:address":"Krainh\u00e4ger Weg 3",
    "sg:city":"Obernkirchen",
    "sg:phone":"+49 5724/2297",
    "sg:postcode":"31683",
    "sg:province":"Niedersachsen",
    "wof:name":"Meier Natursteinbetrieb Gmbh",
    "wof:placetype":"venue"
},
  "geometry": {"coordinates":[9.134789,52.261745],"type":"Point"}
}