{
  "type": "Feature",
  "properties": {
    "iso:country":"DE",
    "sg:address":"Mithoffstr. 17",
    "sg:city":"Rodenberg",
    "sg:postcode":"31552",
    "sg:province":"Niedersachsen",
    "wof:name":"Kristensen & Partner Verwaltungs Bauges. Mbh",
    "wof:placetype":"venue"
},
  "geometry": {"coordinates":[9.347871,52.314297],"type":"Point"}
}