{
  "type": "Feature",
  "properties": {
    "iso:country":"DE",
    "sg:address":"Enzstr. 19",
    "sg:city":"Kornwestheim",
    "sg:phone":"+49 7154/26464",
    "sg:postcode":"70806",
    "sg:province":"Baden-W\u00fcrttemberg",
    "wof:name":"Renner",
    "wof:placetype":"venue"
},
  "geometry": {"coordinates":[9.20802,48.86496],"type":"Point"}
}