{
  "type": "Feature",
  "properties": {
    "iso:country":"DE",
    "sg:address":"Klosterstr. 112",
    "sg:city":"K\u00f6ln",
    "sg:phone":"+49 221/405244",
    "sg:postcode":"50931",
    "sg:province":"Nordrhein-Westfalen",
    "wof:name":"Manfred Kreutzer Architekt",
    "wof:placetype":"venue"
},
  "geometry": {"coordinates":[6.913229,50.935112],"type":"Point"}
}