{
  "type": "Feature",
  "properties": {
    "iso:country":"DE",
    "sg:address":"Traarer Str. 67 a",
    "sg:city":"Duisburg",
    "sg:phone":"+49 2151/940998",
    "sg:postcode":"47239",
    "sg:province":"Nordrhein-Westfalen",
    "wof:name":"Michael Wilde Rechtsanwalt",
    "wof:placetype":"venue"
},
  "geometry": {"coordinates":[6.6446061134,51.3886909485],"type":"Point"}
}