{
  "type": "Feature",
  "properties": {
    "iso:country":"DE",
    "sg:address":"Kurt-Schumacher-Str. 3",
    "sg:city":"Kassel",
    "sg:phone":"+49 561/12823",
    "sg:postcode":"34117",
    "sg:province":"Hessen",
    "wof:name":"Fun Point",
    "wof:placetype":"venue"
},
  "geometry": {"coordinates":[9.498995,51.318604],"type":"Point"}
}