{
  "type": "Feature",
  "properties": {
    "iso:country":"DE",
    "sg:address":"Liststra\u00dfe 18",
    "sg:city":"Karlsruhe",
    "sg:phone":"+49 721/944330",
    "sg:postcode":"76185",
    "sg:province":"Baden-W\u00fcrttemberg",
    "wof:name":"Projekt Eins Karlsruhe Gmbh",
    "wof:placetype":"venue"
},
  "geometry": {"coordinates":[8.358651,49.007282],"type":"Point"}
}