{
  "type": "Feature",
  "properties": {
    "iso:country":"DE",
    "sg:address":"Hingbergstr. 238",
    "sg:city":"M\u00fclheim",
    "sg:phone":"+49 208/432369",
    "sg:postcode":"45472",
    "sg:province":"Nordrhein-Westfalen",
    "wof:name":"Hingberg Gastronomische Betriebe Gmbh",
    "wof:placetype":"venue"
},
  "geometry": {"coordinates":[6.9092102051,51.4335517883],"type":"Point"}
}