{
  "type": "Feature",
  "properties": {
    "iso:country":"DE",
    "sg:address":"Schillerstr. 70",
    "sg:city":"Bensheim",
    "sg:phone":"+49 6251/788822",
    "sg:postcode":"64625",
    "sg:province":"Hessen",
    "wof:name":"Doctor Bike",
    "wof:placetype":"venue"
},
  "geometry": {"coordinates":[8.614509,49.703407],"type":"Point"}
}