{
  "type": "Feature",
  "properties": {
    "iso:country":"DE",
    "sg:address":"Carl-Robert-Str. 13",
    "sg:city":"Halle",
    "sg:postcode":"06114",
    "sg:province":"Sachsen-Anhalt",
    "wof:name":"Dorothea Stemmler",
    "wof:placetype":"venue"
},
  "geometry": {"coordinates":[11.969928,51.502701],"type":"Point"}
}