{
  "type": "Feature",
  "properties": {
    "iso:country":"DE",
    "sg:address":"Kaiserallee 3a",
    "sg:city":"L\u00fcbeck",
    "sg:phone":"+49 4502/73351",
    "sg:postcode":"23570",
    "sg:province":"Schleswig-Holstein",
    "wof:name":"Kur- Apotheke Stefanie Hiller E. K.",
    "wof:placetype":"venue"
},
  "geometry": {"coordinates":[10.87867,53.96524],"type":"Point"}
}