{
  "type": "Feature",
  "properties": {
    "iso:country":"DE",
    "sg:address":"Georgenstr 10",
    "sg:city":"Bamberg",
    "sg:phone":"+49 951/932260",
    "sg:postcode":"96052",
    "sg:province":"Bayern",
    "wof:name":"Irene Steiger",
    "wof:placetype":"venue"
},
  "geometry": {"coordinates":[10.904838562,49.9002990723],"type":"Point"}
}