{
  "type": "Feature",
  "properties": {
    "iso:country":"DE",
    "sg:address":"Wetzlarer Str. 53 a",
    "sg:city":"Wetzlar",
    "sg:phone":"+49 6441/92077",
    "sg:postcode":"35580",
    "sg:province":"Hessen",
    "wof:name":"Arno Viehmann Gmbh Bauunternehmen",
    "wof:placetype":"venue"
},
  "geometry": {"coordinates":[8.4976,50.533222],"type":"Point"}
}