{
  "type": "Feature",
  "properties": {
    "iso:country":"DE",
    "sg:address":"Segeberger Str. 30",
    "sg:city":"Bad Oldesloe",
    "sg:phone":"+49 4531/5820",
    "sg:postcode":"23843",
    "sg:province":"Schleswig-Holstein",
    "wof:name":"Ulrich Fleischfresser Inh. Christian Fleischfresser",
    "wof:placetype":"venue"
},
  "geometry": {"coordinates":[10.376125,53.815578],"type":"Point"}
}