{
  "type": "Feature",
  "properties": {
    "iso:country":"DE",
    "sg:address":"Liegnitzer Str. 43",
    "sg:city":"Stade",
    "sg:phone":"+49 4141/45672",
    "sg:postcode":"21680",
    "sg:province":"Niedersachsen",
    "wof:name":"Irenes Fundgrube E. Kfr.",
    "wof:placetype":"venue"
},
  "geometry": {"coordinates":[9.496653,53.59988],"type":"Point"}
}