{
  "type": "Feature",
  "properties": {
    "iso:country":"DE",
    "sg:address":"Moraltpark 1E",
    "sg:city":"Bad T\u00f6lz",
    "sg:phone":"+49 8041/72310",
    "sg:postcode":"83646",
    "sg:province":"Bayern",
    "wof:name":"Ingrid Manhart Und Partner Masseurin Und Med. Bade-",
    "wof:placetype":"venue"
},
  "geometry": {"coordinates":[11.561107,47.751945],"type":"Point"}
}