{
  "type": "Feature",
  "properties": {
    "iso:country":"DE",
    "sg:address":"Im Quersiefen 12a",
    "sg:city":"Bad M\u00fcnstereifel",
    "sg:phone":"+49 2257/4413",
    "sg:postcode":"53902",
    "sg:province":"Nordrhein-Westfalen",
    "wof:name":"Linden Und Nelles Gmbh",
    "wof:placetype":"venue"
},
  "geometry": {"coordinates":[6.88842,50.540829],"type":"Point"}
}