{
  "type": "Feature",
  "properties": {
    "iso:country":"DE",
    "sg:address":"Am Stadtwald 3 PF 1353",
    "sg:city":"Wickede",
    "sg:phone":"+49 4958/213064",
    "sg:postcode":"58739",
    "sg:province":"Nordrhein-Westfalen",
    "wof:name":"Runggas Maschinen-anlagen-u. Rohrleitungsbau Gmbh",
    "wof:placetype":"venue"
},
  "geometry": {"coordinates":[10.576545,53.081436],"type":"Point"}
}