{
  "type": "Feature",
  "properties": {
    "iso:country":"DE",
    "sg:address":"Ortsstr. 59",
    "sg:city":"Oberhain",
    "sg:phone":"+49 36738/42642",
    "sg:postcode":"07426",
    "sg:province":"Th\u00fcringen",
    "wof:name":"Klein",
    "wof:placetype":"venue"
},
  "geometry": {"coordinates":[11.1358776093,50.6175003052],"type":"Point"}
}