{
  "type": "Feature",
  "properties": {
    "iso:country":"DE",
    "sg:address":"Arracher Weg 14",
    "sg:city":"Falkenstein",
    "sg:phone":"+49 9462/910070",
    "sg:postcode":"93167",
    "sg:province":"Bayern",
    "wof:name":"Planungsb\u00fcro F\u00fcr Elektro- Technik Hallermeier Gmbh",
    "wof:placetype":"venue"
},
  "geometry": {"coordinates":[12.486305,49.093109],"type":"Point"}
}