{
  "type": "Feature",
  "properties": {
    "iso:country":"DE",
    "sg:address":"B\u00fclowstr. 135",
    "sg:city":"Datteln",
    "sg:phone":"+49 2363/34580",
    "sg:postcode":"45711",
    "sg:province":"Nordrhein-Westfalen",
    "wof:name":"G. De Arends Grothe Moran",
    "wof:placetype":"venue"
},
  "geometry": {"coordinates":[7.3468308449,51.6670646667],"type":"Point"}
}