{
  "type": "Feature",
  "properties": {
    "iso:country":"DE",
    "sg:address":"Volgershall",
    "sg:city":"L\u00fcneburg",
    "sg:phone":"+49 4131/64196",
    "sg:postcode":"21339",
    "sg:province":"Niedersachsen",
    "wof:name":"Hausverwaltung Briese",
    "wof:placetype":"venue"
},
  "geometry": {"coordinates":[10.3855581284,53.250415802],"type":"Point"}
}