{
  "type": "Feature",
  "properties": {
    "iso:country":"DE",
    "sg:address":"Oberstr. 97",
    "sg:city":"Neuss",
    "sg:phone":"+49 2131/274144",
    "sg:postcode":"41460",
    "sg:province":"Nordrhein-Westfalen",
    "wof:name":"Zolltor-apotheke",
    "wof:placetype":"venue"
},
  "geometry": {"coordinates":[6.694699,51.196804],"type":"Point"}
}