{
  "type": "Feature",
  "properties": {
    "iso:country":"DE",
    "sg:address":"Hermann-Danz-Str. 76",
    "sg:city":"Hecklingen",
    "sg:phone":"+49 3925/284258",
    "sg:postcode":"39444",
    "sg:province":"Sachsen-Anhalt",
    "wof:name":"Schwan-apotheke",
    "wof:placetype":"venue"
},
  "geometry": {"coordinates":[11.53609,51.848015],"type":"Point"}
}