{
  "type": "Feature",
  "properties": {
    "iso:country":"DE",
    "sg:address":"Eduard-Lingel-Str. 4",
    "sg:city":"K\u00f6nigsberg",
    "sg:phone":"+49 9525/259",
    "sg:postcode":"97486",
    "sg:province":"Bayern",
    "wof:name":"Rudolf Hirt",
    "wof:placetype":"venue"
},
  "geometry": {"coordinates":[10.568555,50.08147],"type":"Point"}
}