{
  "type": "Feature",
  "properties": {
    "iso:country":"DE",
    "sg:address":"Hoddeb\u00fclldeich",
    "sg:city":"Emmelsb\u00fcll-Horsb\u00fcll",
    "sg:phone":"+49 4665/253",
    "sg:postcode":"25924",
    "sg:province":"Schleswig-Holstein",
    "wof:name":"Karl Stapelfeld",
    "wof:placetype":"venue"
},
  "geometry": {"coordinates":[8.707867,54.823956],"type":"Point"}
}