{
  "type": "Feature",
  "properties": {
    "iso:country":"DE",
    "sg:address":"Zeppelinstr. 26",
    "sg:city":"Ravensburg",
    "sg:phone":"+49 751/25686",
    "sg:postcode":"88212",
    "sg:province":"Baden-W\u00fcrttemberg",
    "wof:name":"Wolfgang Hofmann Steuerberater",
    "wof:placetype":"venue"
},
  "geometry": {"coordinates":[9.6202011108,47.7846374512],"type":"Point"}
}