{
  "type": "Feature",
  "properties": {
    "iso:country":"DE",
    "sg:address":"Kanzleistr. 9",
    "sg:city":"Celle",
    "sg:phone":"+49 241/604924",
    "sg:postcode":"29221",
    "sg:province":"Niedersachsen",
    "wof:name":"Deutsche Bank Ag",
    "wof:placetype":"venue"
},
  "geometry": {"coordinates":[6.092286,50.761864],"type":"Point"}
}