{
  "type": "Feature",
  "properties": {
    "iso:country":"DE",
    "sg:address":"Trendelburger Weg 24",
    "sg:city":"Bad Karlshafen",
    "sg:phone":"+49 5672/423",
    "sg:postcode":"34385",
    "sg:province":"Hessen",
    "wof:name":"Ernst Bornemann",
    "wof:placetype":"venue"
},
  "geometry": {"coordinates":[9.45895,51.624142],"type":"Point"}
}