{
  "type": "Feature",
  "properties": {
    "iso:country":"DE",
    "sg:address":"Angerstr. 2",
    "sg:city":"Gr\u00f6benzell",
    "sg:phone":"+49 8142/7213",
    "sg:postcode":"82194",
    "sg:province":"Bayern",
    "wof:name":"Schlei\u00dfheimer Ger\u00e4tebau Gmbh",
    "wof:placetype":"venue"
},
  "geometry": {"coordinates":[11.372913,48.199181],"type":"Point"}
}