{
  "type": "Feature",
  "properties": {
    "iso:country":"DE",
    "sg:address":"Adlerstr. 41",
    "sg:city":"Wiesbaden",
    "sg:phone":"+49 611/529272",
    "sg:postcode":"65183",
    "sg:province":"Hessen",
    "wof:name":"Franz Schuhmacher",
    "wof:placetype":"venue"
},
  "geometry": {"coordinates":[8.2362747192,50.086555481],"type":"Point"}
}