{
  "type": "Feature",
  "properties": {
    "iso:country":"DE",
    "sg:address":"Rul\u00e4nderweg 22",
    "sg:city":"Gau-Bischofsheim",
    "sg:phone":"+49 6135/4348",
    "sg:postcode":"55296",
    "sg:province":"Rheinland-Pfalz",
    "wof:name":"K. Und W. Kerz Steinmetzbetrieb",
    "wof:placetype":"venue"
},
  "geometry": {"coordinates":[8.2749519348,49.9079093933],"type":"Point"}
}