{
  "type": "Feature",
  "properties": {
    "iso:country":"DE",
    "sg:address":"Walstedder Str. 178",
    "sg:city":"Ahlen",
    "sg:phone":"+49 2382/2929",
    "sg:postcode":"59227",
    "sg:province":"Nordrhein-Westfalen",
    "wof:name":"Gastst\u00e4tte Haus Quante Inh. Bernhard Quante",
    "wof:placetype":"venue"
},
  "geometry": {"coordinates":[7.8613228798,51.7589759827],"type":"Point"}
}