{
  "type": "Feature",
  "properties": {
    "iso:country":"DE",
    "sg:address":"Bahnhofstr. 21",
    "sg:city":"Westoverledingen",
    "sg:phone":"+49 4955/4611",
    "sg:postcode":"26810",
    "sg:province":"Niedersachsen",
    "wof:name":"Helga Focken",
    "wof:placetype":"venue"
},
  "geometry": {"coordinates":[7.451329,53.166409],"type":"Point"}
}