{
  "type": "Feature",
  "properties": {
    "iso:country":"DE",
    "sg:address":"Eitelstr. 86",
    "sg:city":"Berlin",
    "sg:postcode":"10317",
    "sg:province":"Berlin",
    "wof:name":"Star Concept Service Team Gmbh",
    "wof:placetype":"venue"
},
  "geometry": {"coordinates":[13.4965801239,52.508808136],"type":"Point"}
}