{
  "type": "Feature",
  "properties": {
    "iso:country":"DE",
    "sg:address":"Fuchsweg 12",
    "sg:city":"Lichtenfels",
    "sg:phone":"+49 9571/3776",
    "sg:postcode":"96215",
    "sg:province":"Bayern",
    "wof:name":"Karl Kr\u00f6ner",
    "wof:placetype":"venue"
},
  "geometry": {"coordinates":[11.1011199951,50.1256523132],"type":"Point"}
}