{
  "type": "Feature",
  "properties": {
    "iso:country":"DE",
    "sg:address":"M\u00fchltalstr. 96",
    "sg:city":"Heidelberg",
    "sg:phone":"+49 6221/413976",
    "sg:postcode":"69121",
    "sg:province":"Baden-W\u00fcrttemberg",
    "wof:name":"Herbert Elfner Obstanbau",
    "wof:placetype":"venue"
},
  "geometry": {"coordinates":[8.6904411316,49.4306221008],"type":"Point"}
}