{
  "type": "Feature",
  "properties": {
    "iso:country":"DE",
    "sg:address":"Saarpfalzstr. 12",
    "sg:city":"Mandelbachtal",
    "sg:phone":"+49 4968/032394",
    "sg:postcode":"66399",
    "sg:province":"Saarland",
    "wof:name":"G\u00dcnter Lang Gmbh",
    "wof:placetype":"venue"
},
  "geometry": {"coordinates":[7.1620659828,49.2186813354],"type":"Point"}
}