{
  "type": "Feature",
  "properties": {
    "iso:country":"DE",
    "sg:city":"Gnarrenburg",
    "sg:phone":"+49 4763/313",
    "sg:postcode":"27442",
    "sg:province":"Niedersachsen",
    "wof:name":"Friedrich Meiners Beteiligungsgesellschaft Mbh",
    "wof:placetype":"venue"
},
  "geometry": {"coordinates":[9.002778,53.382645],"type":"Point"}
}