{
  "type": "Feature",
  "properties": {
    "iso:country":"DE",
    "sg:address":"Breite Str. 87",
    "sg:city":"Stendal",
    "sg:phone":"+49 3931/217323",
    "sg:postcode":"39576",
    "sg:province":"Sachsen-Anhalt",
    "wof:name":"Brandt",
    "wof:placetype":"venue"
},
  "geometry": {"coordinates":[11.863176,52.603401],"type":"Point"}
}