{
  "type": "Feature",
  "properties": {
    "iso:country":"DE",
    "sg:address":"Neckarstr. 98",
    "sg:city":"Stuttgart",
    "sg:phone":"+49 711/261033",
    "sg:postcode":"70190",
    "sg:province":"Baden-W\u00fcrttemberg",
    "wof:name":"Georg Beisswenger",
    "wof:placetype":"venue"
},
  "geometry": {"coordinates":[9.1914958954,48.7867660522],"type":"Point"}
}