{
  "type": "Feature",
  "properties": {
    "iso:country":"DE",
    "sg:address":"Gewerbestr. 2",
    "sg:city":"Neuried",
    "sg:phone":"+49 7807/2327",
    "sg:postcode":"77743",
    "sg:province":"Baden-W\u00fcrttemberg",
    "wof:name":"W. Marx Gmbh",
    "wof:placetype":"venue"
},
  "geometry": {"coordinates":[7.811318,48.460087],"type":"Point"}
}