{
  "type": "Feature",
  "properties": {
    "iso:country":"DE",
    "sg:address":"Stra\u00dfe der Jugend",
    "sg:city":"Hornhausen",
    "sg:phone":"+49 3949/97824",
    "sg:postcode":"39387",
    "sg:province":"Sachsen-Anhalt",
    "wof:name":"Vereinslokal Sport- Und Sch\u00fctzenheim",
    "wof:placetype":"venue"
},
  "geometry": {"coordinates":[11.1732997894,52.051448822],"type":"Point"}
}