{
  "type": "Feature",
  "properties": {
    "iso:country":"DE",
    "sg:address":"Weimarer Str. 6",
    "sg:city":"Steinhagen",
    "sg:phone":"+49 5204/2145",
    "sg:postcode":"33803",
    "sg:province":"Nordrhein-Westfalen",
    "wof:name":"Ingeburg Sandowski",
    "wof:placetype":"venue"
},
  "geometry": {"coordinates":[8.451721,52.008415],"type":"Point"}
}