{
  "type": "Feature",
  "properties": {
    "iso:country":"DE",
    "sg:address":"Schwachhauser Heerstr. 293",
    "sg:city":"Bremen",
    "sg:postcode":"28211",
    "sg:province":"Bremen",
    "wof:name":"Unicards Medien Gmbh",
    "wof:placetype":"venue"
},
  "geometry": {"coordinates":[8.858465,53.089046],"type":"Point"}
}