{
  "type": "Feature",
  "properties": {
    "iso:country":"DE",
    "sg:address":"Untere Schulstr. 10",
    "sg:city":"Riegelsberg",
    "sg:phone":"+49 6806/2545",
    "sg:postcode":"66292",
    "sg:province":"Saarland",
    "wof:name":"Rainer Sch\u00f6nbucher Immobilienmakler",
    "wof:placetype":"venue"
},
  "geometry": {"coordinates":[6.9354739189,49.3010520935],"type":"Point"}
}