{
  "type": "Feature",
  "properties": {
    "iso:country":"DE",
    "sg:address":"Schraudolphstr. 27",
    "sg:city":"M\u00fcnchen",
    "sg:phone":"+49 89/2715066",
    "sg:postcode":"80799",
    "sg:province":"Bayern",
    "wof:name":"Klier Industrie Gmbh",
    "wof:placetype":"venue"
},
  "geometry": {"coordinates":[11.5739850998,48.1550788879],"type":"Point"}
}