{
  "type": "Feature",
  "properties": {
    "iso:country":"DE",
    "sg:address":"Redener Str.",
    "sg:city":"Neunkirchen",
    "sg:phone":"+49 6821/690051",
    "sg:postcode":"66540",
    "sg:province":"Saarland",
    "wof:name":"Praktiker Bau- Und Heimwerkermarkt",
    "wof:placetype":"venue"
},
  "geometry": {"coordinates":[7.1607198715,49.3511199951],"type":"Point"}
}