{
  "type": "Feature",
  "properties": {
    "iso:country":"DE",
    "sg:address":"Birkenwerderstr. 5",
    "sg:city":"Bergfelde",
    "sg:phone":"+49 3303/500863",
    "sg:postcode":"16562",
    "sg:province":"Brandenburg",
    "wof:name":"B. Michalak",
    "wof:placetype":"venue"
},
  "geometry": {"coordinates":[13.316342,52.673885],"type":"Point"}
}