{
  "type": "Feature",
  "properties": {
    "iso:country":"DE",
    "sg:address":"Robert-Bosch-Str. 11",
    "sg:city":"Radevormwald",
    "sg:phone":"+49 2195/931247",
    "sg:postcode":"42477",
    "sg:province":"Nordrhein-Westfalen",
    "wof:name":"Elffering & Schuttkowski",
    "wof:placetype":"venue"
},
  "geometry": {"coordinates":[7.383548,51.200111],"type":"Point"}
}