{
  "type": "Feature",
  "properties": {
    "iso:country":"DE",
    "sg:address":"Grafenwald 5",
    "sg:city":"Loiching",
    "sg:phone":"+49 8744/7264",
    "sg:postcode":"84180",
    "sg:province":"Bayern",
    "wof:name":"Av Elektro Service Gmbh",
    "wof:placetype":"venue"
},
  "geometry": {"coordinates":[12.421343,48.56596],"type":"Point"}
}