{
  "type": "Feature",
  "properties": {
    "iso:country":"DE",
    "sg:address":"Wegscheider Str. 15",
    "sg:city":"Berlin",
    "sg:phone":"+49 30/3352532",
    "sg:postcode":"13587",
    "sg:province":"Berlin",
    "wof:name":"Klaus Noack",
    "wof:placetype":"venue"
},
  "geometry": {"coordinates":[13.206962,52.556644],"type":"Point"}
}