{
  "type": "Feature",
  "properties": {
    "iso:country":"DE",
    "sg:address":"Hauptstra\u00dfe 16",
    "sg:city":"Burgebrach",
    "sg:postcode":"96138",
    "sg:province":"Bayern",
    "wof:name":"Brauerei Und Gasthof Schwan",
    "wof:placetype":"venue"
},
  "geometry": {"coordinates":[10.7411403656,49.8282165527],"type":"Point"}
}