{
  "type": "Feature",
  "properties": {
    "iso:country":"DE",
    "sg:address":"Hauptstr. 4",
    "sg:city":"Forst",
    "sg:phone":"+49 2672/8337",
    "sg:postcode":"56754",
    "sg:province":"Rheinland-Pfalz",
    "wof:name":"Vinzenz Pauly",
    "wof:placetype":"venue"
},
  "geometry": {"coordinates":[7.6840281487,50.8022232056],"type":"Point"}
}