{
  "type": "Feature",
  "properties": {
    "iso:country":"DE",
    "sg:address":"Schiffbeker Weg 96 a",
    "sg:city":"Hamburg",
    "sg:phone":"+49 40/7320155",
    "sg:postcode":"22119",
    "sg:province":"Hamburg",
    "wof:name":"Glaserei J. Retzlaff",
    "wof:placetype":"venue"
},
  "geometry": {"coordinates":[10.108558,53.54884],"type":"Point"}
}