{
  "type": "Feature",
  "properties": {
    "iso:country":"DE",
    "sg:address":"J\u00e4gerstrasse 7",
    "sg:city":"Freital",
    "sg:phone":"+49 351",
    "sg:postcode":"01705",
    "sg:province":"Sachsen",
    "wof:name":"M\u00f6bel Rehn",
    "wof:placetype":"venue"
},
  "geometry": {"coordinates":[13.6478281021,50.9912261963],"type":"Point"}
}