{
  "type": "Feature",
  "properties": {
    "iso:country":"DE",
    "sg:address":"Auf der Plinke 12",
    "sg:city":"Greifenstein",
    "sg:phone":"+49 6478/2381",
    "sg:postcode":"35753",
    "sg:province":"Hessen",
    "wof:name":"Alfred Gaster",
    "wof:placetype":"venue"
},
  "geometry": {"coordinates":[8.2944402695,50.5801353455],"type":"Point"}
}