{
  "type": "Feature",
  "properties": {
    "iso:country":"DE",
    "sg:address":"Ehebachstr. 19",
    "sg:city":"M\u00fcllheim",
    "sg:phone":"+49 7631/2958",
    "sg:postcode":"79379",
    "sg:province":"Baden-W\u00fcrttemberg",
    "wof:name":"Optosol Gmbh",
    "wof:placetype":"venue"
},
  "geometry": {"coordinates":[7.669434,47.82795],"type":"Point"}
}