{
  "type": "Feature",
  "properties": {
    "iso:country":"DE",
    "sg:address":"Uhlandstr. 23",
    "sg:city":"Hamm",
    "sg:phone":"+49 2381/71862",
    "sg:postcode":"59075",
    "sg:province":"Nordrhein-Westfalen",
    "wof:name":"F. Henrichs",
    "wof:placetype":"venue"
},
  "geometry": {"coordinates":[7.7470521927,51.699016571],"type":"Point"}
}