{
  "type": "Feature",
  "properties": {
    "iso:country":"DE",
    "sg:address":"Frankensteinstr. 14",
    "sg:city":"Tiefenort",
    "sg:phone":"+49 3695/824141",
    "sg:postcode":"36469",
    "sg:province":"Th\u00fcringen",
    "wof:name":"Deinzer & Weyland Vertriebs Gmbh",
    "wof:placetype":"venue"
},
  "geometry": {"coordinates":[10.168192,50.841137],"type":"Point"}
}