{
  "type": "Feature",
  "properties": {
    "iso:country":"DE",
    "sg:address":"Valenkamp 20",
    "sg:city":"Duisburg",
    "sg:phone":"+49 203/61109",
    "sg:postcode":"47053",
    "sg:province":"Nordrhein-Westfalen",
    "wof:name":"Hochfelder-st\u00fcbchen",
    "wof:placetype":"venue"
},
  "geometry": {"coordinates":[6.7506818771,51.4211196899],"type":"Point"}
}