{
  "type": "Feature",
  "properties": {
    "iso:country":"DE",
    "sg:address":"Burgweintinger Str. 10",
    "sg:city":"Regensburg",
    "sg:phone":"+49 941/700883",
    "sg:postcode":"93055",
    "sg:province":"Bayern",
    "wof:name":"Franz Rei\u00dfmann",
    "wof:placetype":"venue"
},
  "geometry": {"coordinates":[12.168064,48.987312],"type":"Point"}
}