{
  "type": "Feature",
  "properties": {
    "iso:country":"DE",
    "sg:address":"Oberdorfstr. 5 a",
    "sg:city":"Auggen",
    "sg:phone":"+49 7631/3574",
    "sg:postcode":"79424",
    "sg:province":"Baden-W\u00fcrttemberg",
    "wof:name":"E. Siegwald",
    "wof:placetype":"venue"
},
  "geometry": {"coordinates":[7.5995140076,47.7855300903],"type":"Point"}
}