{
  "type": "Feature",
  "properties": {
    "iso:country":"DE",
    "sg:address":"Oddernskamp 27",
    "sg:city":"Hamburg",
    "sg:postcode":"22529",
    "sg:province":"Hamburg",
    "wof:name":"Werner Doepfert Verm\u00f6gens- Verwaltung Gmbh & Co. Kg",
    "wof:placetype":"venue"
},
  "geometry": {"coordinates":[9.9520282745,53.599445343],"type":"Point"}
}