{
  "type": "Feature",
  "properties": {
    "iso:country":"DE",
    "sg:address":"Wallstr. 11",
    "sg:city":"Neustadt",
    "sg:phone":"+49 5032/4444",
    "sg:postcode":"31535",
    "sg:province":"Niedersachsen",
    "wof:name":"Zettlitz Gmbh & Co. Kg",
    "wof:placetype":"venue"
},
  "geometry": {"coordinates":[9.459654808,52.5064506531],"type":"Point"}
}