{
  "type": "Feature",
  "properties": {
    "iso:country":"DE",
    "sg:address":"Im Ermlisgrund 26",
    "sg:city":"Waldbronn",
    "sg:phone":"+49 7243/56850",
    "sg:postcode":"76337",
    "sg:province":"Baden-W\u00fcrttemberg",
    "wof:name":"Mediadress Datenver- Arbeitungs Gmbh",
    "wof:placetype":"venue"
},
  "geometry": {"coordinates":[8.4775867462,48.9341545105],"type":"Point"}
}