{
  "type": "Feature",
  "properties": {
    "iso:country":"DE",
    "sg:address":"Lindnerstr. 68",
    "sg:city":"Gleichamberg",
    "sg:phone":"+49 36875/69311",
    "sg:postcode":"98646",
    "sg:province":"Th\u00fcringen",
    "wof:name":"Zum Goldenen Lamm",
    "wof:placetype":"venue"
},
  "geometry": {"coordinates":[10.6295671463,50.361415863],"type":"Point"}
}