{
  "type": "Feature",
  "properties": {
    "iso:country":"DE",
    "sg:address":"Bahnstr. 13",
    "sg:city":"Kevelaer",
    "sg:phone":"+49 2832/4200",
    "sg:postcode":"47623",
    "sg:province":"Nordrhein-Westfalen",
    "wof:name":"Bst Brand-sanierungs-team E.k.",
    "wof:placetype":"venue"
},
  "geometry": {"coordinates":[6.249029,51.582676],"type":"Point"}
}