{
  "type": "Feature",
  "properties": {
    "iso:country":"DE",
    "sg:address":"Im Sommerfeld 25",
    "sg:city":"Wolfenb\u00fcttel",
    "sg:phone":"+49 5331/96150",
    "sg:postcode":"38304",
    "sg:province":"Niedersachsen",
    "wof:name":"Fr\u00e4stechnik Wolfenb\u00fcttel Gmbh",
    "wof:placetype":"venue"
},
  "geometry": {"coordinates":[10.5417900085,52.1451148987],"type":"Point"}
}