{
  "type": "Feature",
  "properties": {
    "iso:country":"DE",
    "sg:address":"Hauptstr. 217",
    "sg:city":"Lauterstein",
    "sg:phone":"+49 7332/5377",
    "sg:postcode":"73111",
    "sg:province":"Baden-W\u00fcrttemberg",
    "wof:name":"Adolf Knobel",
    "wof:placetype":"venue"
},
  "geometry": {"coordinates":[9.883732,48.709351],"type":"Point"}
}