{
  "type": "Feature",
  "properties": {
    "iso:country":"DE",
    "sg:address":"Sudetenhof",
    "sg:city":"Steinweiler",
    "sg:phone":"+49 6349/6661",
    "sg:postcode":"76872",
    "sg:province":"Rheinland-Pfalz",
    "wof:name":"P. Stauss",
    "wof:placetype":"venue"
},
  "geometry": {"coordinates":[8.14407,49.11301],"type":"Point"}
}