{
  "type": "Feature",
  "properties": {
    "iso:country":"DE",
    "sg:address":"Eiderstedter Str. 18",
    "sg:city":"T\u00f6nning",
    "sg:phone":"+49 4861/383",
    "sg:postcode":"25832",
    "sg:province":"Schleswig-Holstein",
    "wof:name":"Wilhelm Walter Ohg",
    "wof:placetype":"venue"
},
  "geometry": {"coordinates":[8.952809,54.320045],"type":"Point"}
}