{
  "type": "Feature",
  "properties": {
    "iso:country":"DE",
    "sg:address":"Walter-Freitag-Str. 9",
    "sg:city":"Remscheid",
    "sg:phone":"+49 2191/95640",
    "sg:postcode":"42899",
    "sg:province":"Nordrhein-Westfalen",
    "wof:name":"Dressel & Balthasar Gmbh & Co. Kg",
    "wof:placetype":"venue"
},
  "geometry": {"coordinates":[7.239128,51.21859],"type":"Point"}
}