{
  "type": "Feature",
  "properties": {
    "iso:country":"DE",
    "sg:address":"Filderbahnstr. 29",
    "sg:city":"Stuttgart",
    "sg:phone":"+49 711/2164466",
    "sg:postcode":"70567",
    "sg:province":"Baden-W\u00fcrttemberg",
    "wof:name":"Stadtb\u00fccherei B\u00fccherei Im Spitalhof",
    "wof:placetype":"venue"
},
  "geometry": {"coordinates":[9.146583,48.727875],"type":"Point"}
}