{
  "type": "Feature",
  "properties": {
    "iso:country":"DE",
    "sg:address":"Steig\u00e4ckerstr. 7",
    "sg:city":"Eschach",
    "sg:phone":"+49 4971/75430",
    "sg:postcode":"73569",
    "sg:province":"Baden-W\u00fcrttemberg",
    "wof:name":"Kreissparkasse Ostalb",
    "wof:placetype":"venue"
},
  "geometry": {"coordinates":[9.868912,48.887337],"type":"Point"}
}