{
  "type": "Feature",
  "properties": {
    "iso:country":"DE",
    "sg:address":"Cottbuser Str. 26a",
    "sg:city":"Forst",
    "sg:phone":"+49 3562/6433",
    "sg:postcode":"03149",
    "sg:province":"Brandenburg",
    "wof:name":"Apotheke Cottbuser Stra\u00dfe Dr. Dobbert Und",
    "wof:placetype":"venue"
},
  "geometry": {"coordinates":[14.604105,51.690681],"type":"Point"}
}