{
  "type": "Feature",
  "properties": {
    "iso:country":"DE",
    "sg:address":"J\u00e4gerstr. 5",
    "sg:city":"W\u00fcrzburg",
    "sg:phone":"+49 931/43174",
    "sg:postcode":"97082",
    "sg:province":"Bayern",
    "wof:name":"Josef Unterreiner",
    "wof:placetype":"venue"
},
  "geometry": {"coordinates":[9.916686058,49.7930641174],"type":"Point"}
}