{
  "type": "Feature",
  "properties": {
    "iso:country":"DE",
    "sg:address":"Duisburger Str. 170",
    "sg:city":"Oberhausen",
    "sg:phone":"+49 208/2053650",
    "sg:postcode":"46049",
    "sg:province":"Nordrhein-Westfalen",
    "wof:name":"Leama Import Und Export Gmbh",
    "wof:placetype":"venue"
},
  "geometry": {"coordinates":[6.8450579643,51.4792709351],"type":"Point"}
}