{
  "type": "Feature",
  "properties": {
    "iso:country":"DE",
    "sg:address":"Bannz\u00e4unerweg 40",
    "sg:city":"Bingen",
    "sg:phone":"+49 6721/45935",
    "sg:postcode":"55411",
    "sg:province":"Rheinland-Pfalz",
    "wof:name":"Klaus Schmitt",
    "wof:placetype":"venue"
},
  "geometry": {"coordinates":[7.9174909592,49.9474105835],"type":"Point"}
}