{
  "type": "Feature",
  "properties": {
    "iso:country":"DE",
    "sg:address":"G\u00f6ttendorfer Weg 14",
    "sg:city":"Drensteinfurt",
    "sg:phone":"+49 2538/8101",
    "sg:postcode":"48317",
    "sg:province":"Nordrhein-Westfalen",
    "wof:name":"Heinz Loddenkemper Gmbh",
    "wof:placetype":"venue"
},
  "geometry": {"coordinates":[7.6925702095,51.8386497498],"type":"Point"}
}