{
  "type": "Feature",
  "properties": {
    "iso:country":"DE",
    "sg:address":"Veringstr. 26",
    "sg:city":"Hamburg",
    "sg:phone":"+49 40/751329",
    "sg:postcode":"21107",
    "sg:province":"Hamburg",
    "wof:name":"Dogus",
    "wof:placetype":"venue"
},
  "geometry": {"coordinates":[9.9876251221,53.5161705017],"type":"Point"}
}