{
  "type": "Feature",
  "properties": {
    "iso:country":"DE",
    "sg:address":"M\u00f6nchenwerther Str. 24",
    "sg:city":"D\u00fcsseldorf",
    "sg:phone":"+49 211/551446",
    "sg:postcode":"40547",
    "sg:province":"Nordrhein-Westfalen",
    "wof:name":"Erika Rahmann Heilpraktikerin",
    "wof:placetype":"venue"
},
  "geometry": {"coordinates":[6.7569122314,51.2355384827],"type":"Point"}
}