{
  "type": "Feature",
  "properties": {
    "iso:country":"DE",
    "sg:address":"Theaterstr. 5",
    "sg:city":"F\u00fcrth",
    "sg:phone":"+49 911/777444",
    "sg:postcode":"90762",
    "sg:province":"Bayern",
    "wof:name":"Streng Tanzschule",
    "wof:placetype":"venue"
},
  "geometry": {"coordinates":[10.9854774475,49.4767150879],"type":"Point"}
}