{
  "type": "Feature",
  "properties": {
    "iso:country":"DE",
    "sg:address":"Koblenzer Str. 67",
    "sg:city":"Bonn",
    "sg:postcode":"53177",
    "sg:province":"Nordrhein-Westfalen",
    "wof:name":"Postbank",
    "wof:placetype":"venue"
},
  "geometry": {"coordinates":[7.1564588547,50.6832885742],"type":"Point"}
}