{
  "type": "Feature",
  "properties": {
    "iso:country":"DE",
    "sg:address":"Schmale G. 12a",
    "sg:city":"Bielefeld",
    "sg:phone":"+49 4952/167200",
    "sg:postcode":"33602",
    "sg:province":"Nordrhein-Westfalen",
    "wof:name":"J\u00dcrgen Riedel",
    "wof:placetype":"venue"
},
  "geometry": {"coordinates":[8.531641,52.017181],"type":"Point"}
}