{
  "type": "Feature",
  "properties": {
    "iso:country":"DE",
    "sg:address":"Stuben 4",
    "sg:city":"P\u00f6ttmes",
    "sg:phone":"+49 8253/6292",
    "sg:postcode":"86554",
    "sg:province":"Bayern",
    "wof:name":"R. Brenner",
    "wof:placetype":"venue"
},
  "geometry": {"coordinates":[11.0275917053,48.5631790161],"type":"Point"}
}