{
  "type": "Feature",
  "properties": {
    "iso:country":"DE",
    "sg:address":"B\u00fcltstiege 4",
    "sg:city":"Rheine",
    "sg:phone":"+49 5971/963060",
    "sg:postcode":"48429",
    "sg:province":"Nordrhein-Westfalen",
    "wof:name":"Heckhuis Gmbh",
    "wof:placetype":"venue"
},
  "geometry": {"coordinates":[7.4427790642,52.2799186707],"type":"Point"}
}