{
  "type": "Feature",
  "properties": {
    "iso:country":"DE",
    "sg:address":"K\u00f6nigin-Elisabeth-Str. 2",
    "sg:city":"Berlin",
    "sg:phone":"+49 30/3024396",
    "sg:postcode":"14059",
    "sg:province":"Berlin",
    "wof:name":"Gerda Schimpf",
    "wof:placetype":"venue"
},
  "geometry": {"coordinates":[13.2820415497,52.5103111267],"type":"Point"}
}