{
  "type": "Feature",
  "properties": {
    "iso:country":"DE",
    "sg:address":"Theresienstr. 18",
    "sg:city":"Ingolstadt",
    "sg:phone":"+49 841/35229",
    "sg:postcode":"85049",
    "sg:province":"Bayern",
    "wof:name":"Gebr. Riemer Inh. Wolfgang Riemer",
    "wof:placetype":"venue"
},
  "geometry": {"coordinates":[11.4228229523,48.7638473511],"type":"Point"}
}