{
  "type": "Feature",
  "properties": {
    "iso:country":"DE",
    "sg:address":"Im Leitle 7",
    "sg:city":"Pegnitz",
    "sg:phone":"+49 9241/3462",
    "sg:postcode":"91257",
    "sg:province":"Bayern",
    "wof:name":"Kurt Schiller",
    "wof:placetype":"venue"
},
  "geometry": {"coordinates":[11.5362987518,49.7419891357],"type":"Point"}
}