{
  "type": "Feature",
  "properties": {
    "iso:country":"DE",
    "sg:address":"Am Gebr\u00e4un 33",
    "sg:city":"Eisenach",
    "sg:phone":"+49 3691/872300",
    "sg:postcode":"99817",
    "sg:province":"Th\u00fcringen",
    "wof:name":"Klaus Weber",
    "wof:placetype":"venue"
},
  "geometry": {"coordinates":[10.305166,50.995422],"type":"Point"}
}