{
  "type": "Feature",
  "properties": {
    "iso:country":"DE",
    "sg:address":"Hardhofweg 40",
    "sg:city":"Mosbach",
    "sg:phone":"+49 6261/810",
    "sg:postcode":"74821",
    "sg:province":"Baden-W\u00fcrttemberg",
    "wof:name":"Honeywell Braukamm Unterst\u00fctzungskasse Gmbh",
    "wof:placetype":"venue"
},
  "geometry": {"coordinates":[9.166209,49.346855],"type":"Point"}
}