{
  "type": "Feature",
  "properties": {
    "iso:country":"DE",
    "sg:address":"Casterfeldstr. 91a",
    "sg:city":"Mannheim",
    "sg:phone":"+49 621/851039",
    "sg:postcode":"68199",
    "sg:province":"Baden-W\u00fcrttemberg",
    "wof:name":"Helmut Medici Gmbh",
    "wof:placetype":"venue"
},
  "geometry": {"coordinates":[8.50822258,49.4468917847],"type":"Point"}
}