{
  "type": "Feature",
  "properties": {
    "iso:country":"DE",
    "sg:address":"Marktstr. 3",
    "sg:city":"Namborn",
    "sg:postcode":"66640",
    "sg:province":"Saarland",
    "wof:name":"K.-h. Bosel Immobilienmakler",
    "wof:placetype":"venue"
},
  "geometry": {"coordinates":[7.1404290199,49.5223770142],"type":"Point"}
}