{
  "type": "Feature",
  "properties": {
    "iso:country":"DE",
    "sg:address":"Alter Dyk 2",
    "sg:city":"Stadtlohn",
    "sg:phone":"+49 2563/7713",
    "sg:postcode":"48703",
    "sg:province":"Nordrhein-Westfalen",
    "wof:name":"Gasthaus J\u00f6rg Tombrink",
    "wof:placetype":"venue"
},
  "geometry": {"coordinates":[6.9305491447,51.991443634],"type":"Point"}
}