{
  "type": "Feature",
  "properties": {
    "iso:country":"DE",
    "sg:address":"Daimlerstr 7",
    "sg:city":"Wildeshausen",
    "sg:phone":"+49 4431/73770",
    "sg:postcode":"27793",
    "sg:province":"Niedersachsen",
    "wof:name":"Logiplan Gmbh",
    "wof:placetype":"venue"
},
  "geometry": {"coordinates":[8.414311409,52.8831596375],"type":"Point"}
}