{
  "type": "Feature",
  "properties": {
    "iso:country":"DE",
    "sg:address":"Gutleutstr. 163",
    "sg:city":"Frankfurt",
    "sg:phone":"+49 69/27138890",
    "sg:postcode":"60327",
    "sg:province":"Hessen",
    "wof:name":"Gfm Gesellschaft F\u00fcr Minder- Heitsbeteiligungen Mbh",
    "wof:placetype":"venue"
},
  "geometry": {"coordinates":[8.659413,50.101456],"type":"Point"}
}