{
  "type": "Feature",
  "properties": {
    "iso:country":"DE",
    "sg:address":"M\u00fchlstr. 24",
    "sg:city":"Nidda",
    "sg:phone":"+49 6043/2562",
    "sg:postcode":"63667",
    "sg:province":"Hessen",
    "wof:name":"B. Schneider",
    "wof:placetype":"venue"
},
  "geometry": {"coordinates":[9.00826931,50.4136581421],"type":"Point"}
}