{
  "type": "Feature",
  "properties": {
    "iso:country":"DE",
    "sg:address":"Siegdamm 32",
    "sg:city":"Siegburg",
    "sg:phone":"+49 2241/59920",
    "sg:postcode":"53721",
    "sg:province":"Nordrhein-Westfalen",
    "wof:name":"Interdean Ag",
    "wof:placetype":"venue"
},
  "geometry": {"coordinates":[7.1890888214,50.7964630127],"type":"Point"}
}