{
  "type": "Feature",
  "properties": {
    "iso:country":"DE",
    "sg:address":"Pistoriusstrasse 2",
    "sg:city":"Berlin",
    "sg:phone":"+49 30/96065266",
    "sg:postcode":"13086",
    "sg:province":"Berlin",
    "wof:name":"Holzspielzeug - Spielzeug Versand Vielspiel",
    "wof:placetype":"venue"
},
  "geometry": {"coordinates":[13.458349,52.550495],"type":"Point"}
}