{
  "type": "Feature",
  "properties": {
    "iso:country":"DE",
    "sg:address":"Durchholzer Str. 195",
    "sg:city":"Witten",
    "sg:phone":"+49 2302/73954",
    "sg:postcode":"58456",
    "sg:province":"Nordrhein-Westfalen",
    "wof:name":"Adalbert St\u00f6ter",
    "wof:placetype":"venue"
},
  "geometry": {"coordinates":[7.288323,51.375713],"type":"Point"}
}