{
  "type": "Feature",
  "properties": {
    "iso:country":"DE",
    "sg:address":"Stollwerckhof 9",
    "sg:city":"K\u00f6ln",
    "sg:phone":"+49 221/9320966",
    "sg:postcode":"50678",
    "sg:province":"Nordrhein-Westfalen",
    "wof:name":"Persisch Tubis Mahdokht Tubis",
    "wof:placetype":"venue"
},
  "geometry": {"coordinates":[6.965115,50.92424],"type":"Point"}
}