{
  "type": "Feature",
  "properties": {
    "iso:country":"DE",
    "sg:address":"Sch\u00fctzenstr. 16",
    "sg:city":"Lahn",
    "sg:phone":"+49 5951/665",
    "sg:postcode":"49757",
    "sg:province":"Niedersachsen",
    "wof:name":"Franz Pund",
    "wof:placetype":"venue"
},
  "geometry": {"coordinates":[7.616878,52.819756],"type":"Point"}
}