{
  "type": "Feature",
  "properties": {
    "iso:country":"DE",
    "sg:address":"Raderbroich 141a",
    "sg:city":"Korschenbroich",
    "sg:phone":"+49 2161/641591",
    "sg:postcode":"41352",
    "sg:province":"Nordrhein-Westfalen",
    "wof:name":"K. Hohnen",
    "wof:placetype":"venue"
},
  "geometry": {"coordinates":[6.53702,51.200447],"type":"Point"}
}