{
  "type": "Feature",
  "properties": {
    "iso:country":"DE",
    "sg:address":"Hauptstr. 87",
    "sg:city":"Kesseling",
    "sg:phone":"+49 2647/3467",
    "sg:postcode":"53506",
    "sg:province":"Rheinland-Pfalz",
    "wof:name":"Dietmar Monreal",
    "wof:placetype":"venue"
},
  "geometry": {"coordinates":[7.040924,50.480873],"type":"Point"}
}