{
  "type": "Feature",
  "properties": {
    "iso:country":"DE",
    "sg:address":"Mitterfeldstr. 14",
    "sg:city":"M\u00fcnchen",
    "sg:phone":"+49 89/5801549",
    "sg:postcode":"80689",
    "sg:province":"Bayern",
    "wof:name":"Franz Kollerbaur Gmbh",
    "wof:placetype":"venue"
},
  "geometry": {"coordinates":[11.4822340012,48.1381111145],"type":"Point"}
}