{
  "type": "Feature",
  "properties": {
    "iso:country":"DE",
    "sg:address":"Hildburghausen Sachsenbr.",
    "sg:city":"Eisfeld",
    "sg:phone":"+49 3686/2333",
    "sg:postcode":"98673",
    "sg:province":"Th\u00fcringen",
    "wof:name":"Raiffeisenbank Und Handelsgenossen-, Schaft E. G.",
    "wof:placetype":"venue"
},
  "geometry": {"coordinates":[10.905354,50.426178],"type":"Point"}
}