{
  "type": "Feature",
  "properties": {
    "iso:country":"DE",
    "sg:address":"Andreasberg 5",
    "sg:city":"Fulda",
    "sg:phone":"+49 661/73102",
    "sg:postcode":"36041",
    "sg:province":"Hessen",
    "wof:name":"Kath. Pfarramt St. Andreas",
    "wof:placetype":"venue"
},
  "geometry": {"coordinates":[9.6615839005,50.5525894165],"type":"Point"}
}