{
  "type": "Feature",
  "properties": {
    "iso:country":"DE",
    "sg:address":"Wilhelmstr. 41",
    "sg:city":"Dortmund",
    "sg:phone":"+49 231/143849",
    "sg:postcode":"44137",
    "sg:province":"Nordrhein-Westfalen",
    "wof:name":"Hans-j. Budeit Architekt",
    "wof:placetype":"venue"
},
  "geometry": {"coordinates":[7.453891,51.510811],"type":"Point"}
}