{
  "type": "Feature",
  "properties": {
    "iso:country":"DE",
    "sg:address":"Moorstr. 56",
    "sg:city":"Walsrode",
    "sg:phone":"+49 5161/73134",
    "sg:postcode":"29664",
    "sg:province":"Niedersachsen",
    "wof:name":"Eiscafe Dal-cin",
    "wof:placetype":"venue"
},
  "geometry": {"coordinates":[9.590345,52.862492],"type":"Point"}
}