{
  "type": "Feature",
  "properties": {
    "iso:country":"DE",
    "sg:address":"Regerstr. 39",
    "sg:city":"Mainz",
    "sg:phone":"+49 6131/71463",
    "sg:postcode":"55127",
    "sg:province":"Rheinland-Pfalz",
    "wof:name":"Schinderhannes",
    "wof:placetype":"venue"
},
  "geometry": {"coordinates":[8.1984548569,49.9592819214],"type":"Point"}
}