{
  "type": "Feature",
  "properties": {
    "iso:country":"DE",
    "sg:address":"Hauptstra\u00dfe 77-81",
    "sg:city":"Mengen",
    "sg:phone":"+49 7572/76560",
    "sg:postcode":"88512",
    "sg:province":"Baden-W\u00fcrttemberg",
    "wof:name":"Netpoint Verbund Deutschland",
    "wof:placetype":"venue"
},
  "geometry": {"coordinates":[9.3298482895,48.0489616394],"type":"Point"}
}