{
  "type": "Feature",
  "properties": {
    "iso:country":"DE",
    "sg:address":"Dekan-Karl-Platz 1",
    "sg:city":"Mittenwald",
    "sg:phone":"+49 8823/8282",
    "sg:postcode":"82481",
    "sg:province":"Bayern",
    "wof:name":"P. Werner Trachten- Und Uniformen",
    "wof:placetype":"venue"
},
  "geometry": {"coordinates":[11.2605886459,47.4397201538],"type":"Point"}
}