{
  "type": "Feature",
  "properties": {
    "iso:country":"DE",
    "sg:address":"Rheinberger Str. 81",
    "sg:city":"Kamp-Lintfort",
    "sg:phone":"+49 2842/47892",
    "sg:postcode":"47475",
    "sg:province":"Nordrhein-Westfalen",
    "wof:name":"B. Gie\u00dfler",
    "wof:placetype":"venue"
},
  "geometry": {"coordinates":[6.521505,51.504684],"type":"Point"}
}