{
  "type": "Feature",
  "properties": {
    "iso:country":"DE",
    "sg:address":"Nachtigallenstr. 13",
    "sg:city":"Meiningen",
    "sg:postcode":"98617",
    "sg:province":"Th\u00fcringen",
    "wof:name":"Semilas Optische Systeme Gmbh",
    "wof:placetype":"venue"
},
  "geometry": {"coordinates":[10.4084978104,50.5646133423],"type":"Point"}
}