{
  "type": "Feature",
  "properties": {
    "iso:country":"DE",
    "sg:address":"Im Garbrock 4",
    "sg:city":"Ahaus",
    "sg:phone":"+49 2561/82585",
    "sg:postcode":"48683",
    "sg:province":"Nordrhein-Westfalen",
    "wof:name":"Thesing Baugesch\u00e4ft Gmbh",
    "wof:placetype":"venue"
},
  "geometry": {"coordinates":[6.918476,52.078762],"type":"Point"}
}