{
  "type": "Feature",
  "properties": {
    "iso:country":"DE",
    "sg:address":"Haagstr. 34",
    "sg:city":"Moers",
    "sg:phone":"+49 2841/170544",
    "sg:postcode":"47441",
    "sg:province":"Nordrhein-Westfalen",
    "wof:name":"Wilhelm Harpel",
    "wof:placetype":"venue"
},
  "geometry": {"coordinates":[6.625834,51.450966],"type":"Point"}
}