{
  "type": "Feature",
  "properties": {
    "iso:country":"DE",
    "sg:address":"Tudorfer Str. 2",
    "sg:city":"Borchen",
    "sg:phone":"+49 5251/398390",
    "sg:postcode":"33178",
    "sg:province":"Nordrhein-Westfalen",
    "wof:name":"J\u00fcrgen Nillies",
    "wof:placetype":"venue"
},
  "geometry": {"coordinates":[8.701753,51.651443],"type":"Point"}
}