{
  "type": "Feature",
  "properties": {
    "iso:country":"DE",
    "sg:address":"Lohbr\u00fcgger Weg 1",
    "sg:city":"Hamburg",
    "sg:phone":"+49 40/7399905",
    "sg:postcode":"21031",
    "sg:province":"Hamburg",
    "wof:name":"Stephanie K\u00f6wing",
    "wof:placetype":"venue"
},
  "geometry": {"coordinates":[10.203678,53.498989],"type":"Point"}
}