{
  "type": "Feature",
  "properties": {
    "iso:country":"DE",
    "sg:address":"Falkenberger Chaussee 7c",
    "sg:city":"Berlin",
    "sg:phone":"+49 30/9267411",
    "sg:postcode":"13051",
    "sg:province":"Berlin",
    "wof:name":"Karl-heinz Brauschke",
    "wof:placetype":"venue"
},
  "geometry": {"coordinates":[13.500802,52.562008],"type":"Point"}
}