{
  "type": "Feature",
  "properties": {
    "iso:country":"DE",
    "sg:address":"Ziegelkampstr. 30",
    "sg:city":"Nienburg",
    "sg:postcode":"31582",
    "sg:province":"Niedersachsen",
    "wof:name":"Aldi Gmbh & Co. Kg",
    "wof:placetype":"venue"
},
  "geometry": {"coordinates":[9.2249984741,52.6344795227],"type":"Point"}
}