{
  "type": "Feature",
  "properties": {
    "iso:country":"DE",
    "sg:address":"Laurenzstr. 13",
    "sg:city":"Ochtrup",
    "sg:phone":"+49 2553/977893",
    "sg:postcode":"48607",
    "sg:province":"Nordrhein-Westfalen",
    "wof:name":"Terra Nova E. V.",
    "wof:placetype":"venue"
},
  "geometry": {"coordinates":[7.191606,52.210659],"type":"Point"}
}