{
  "type": "Feature",
  "properties": {
    "iso:country":"DE",
    "sg:address":"G\u00fcterstr. 1",
    "sg:city":"Rheinfelden",
    "sg:phone":"+49 7623/799137",
    "sg:postcode":"79618",
    "sg:province":"Baden-W\u00fcrttemberg",
    "wof:name":"Brogtec Mischtechnik Gmbh",
    "wof:placetype":"venue"
},
  "geometry": {"coordinates":[7.782264,47.5569],"type":"Point"}
}