{
  "type": "Feature",
  "properties": {
    "iso:country":"DE",
    "sg:address":"Am Alten Tor 6",
    "sg:city":"Nordhausen",
    "sg:phone":"+49 172 3619993",
    "sg:postcode":"99734",
    "sg:province":"Th\u00fcringen",
    "wof:name":"Remo Paulitschke Rechtsanwalt",
    "wof:placetype":"venue"
},
  "geometry": {"coordinates":[10.7868471146,51.5079154968],"type":"Point"}
}