{
  "type": "Feature",
  "properties": {
    "iso:country":"DE",
    "sg:address":"Burgweintinger Strasse.30",
    "sg:city":"Regensburg",
    "sg:phone":"+49 941/7060105",
    "sg:postcode":"93055",
    "sg:province":"Bayern",
    "wof:name":"Die L\u00f6sung Gegen Elektrosmog",
    "wof:placetype":"venue"
},
  "geometry": {"coordinates":[12.150872,48.990265],"type":"Point"}
}