{
  "type": "Feature",
  "properties": {
    "iso:country":"DE",
    "sg:address":"Bizetstr. 113",
    "sg:city":"Berlin",
    "sg:phone":"+49 30/9272923",
    "sg:postcode":"13088",
    "sg:province":"Berlin",
    "wof:name":"G. Lange U. J. Stange Gbr",
    "wof:placetype":"venue"
},
  "geometry": {"coordinates":[13.4612789154,52.5495529175],"type":"Point"}
}