{
  "type": "Feature",
  "properties": {
    "iso:country":"DE",
    "sg:address":"Falkenweg 25",
    "sg:city":"Fichtenberg",
    "sg:phone":"+49 7971/8925",
    "sg:postcode":"74427",
    "sg:province":"Baden-W\u00fcrttemberg",
    "wof:name":"Karl Feucht",
    "wof:placetype":"venue"
},
  "geometry": {"coordinates":[9.707356,48.992035],"type":"Point"}
}