{
  "type": "Feature",
  "properties": {
    "iso:country":"DE",
    "sg:address":"Buchberg 23",
    "sg:city":"Hohenau",
    "sg:phone":"+49 8551/4441",
    "sg:postcode":"94545",
    "sg:province":"Bayern",
    "wof:name":"Otto Drexler",
    "wof:placetype":"venue"
},
  "geometry": {"coordinates":[13.509598732,48.8232269287],"type":"Point"}
}