{
  "type": "Feature",
  "properties": {
    "iso:country":"DE",
    "sg:address":"L\u00e4nderweg 5",
    "sg:city":"Frankfurt",
    "sg:phone":"+49 69/624422",
    "sg:postcode":"60599",
    "sg:province":"Hessen",
    "wof:name":"A. Roggow & S\u00f6hne Stra\u00dfen- Und Wegebau",
    "wof:placetype":"venue"
},
  "geometry": {"coordinates":[8.7000770569,50.1030197144],"type":"Point"}
}