{
  "type": "Feature",
  "properties": {
    "iso:country":"DE",
    "sg:address":"Bruchk\u00f6beler Landstr. 104",
    "sg:city":"Hanau",
    "sg:phone":"+49 6181/99310",
    "sg:postcode":"63452",
    "sg:province":"Hessen",
    "wof:name":"Berger Zahntechnik Gmbh",
    "wof:placetype":"venue"
},
  "geometry": {"coordinates":[8.90898,50.148476],"type":"Point"}
}