{
  "type": "Feature",
  "properties": {
    "iso:country":"DE",
    "sg:address":"Hauptstr. 14",
    "sg:city":"Poing",
    "sg:phone":"+49 8121/81702",
    "sg:postcode":"85586",
    "sg:province":"Bayern",
    "wof:name":"Wolfgang Spieth Rechtsanwalt",
    "wof:placetype":"venue"
},
  "geometry": {"coordinates":[11.8155193329,48.1708068848],"type":"Point"}
}