{
  "type": "Feature",
  "properties": {
    "iso:country":"DE",
    "sg:address":"Otto-Hahn-Str. 19",
    "sg:city":"M\u00fchlheim",
    "sg:phone":"+49 6108/79770",
    "sg:postcode":"63165",
    "sg:province":"Hessen",
    "wof:name":"Offset-repro Gmbh",
    "wof:placetype":"venue"
},
  "geometry": {"coordinates":[8.847244,50.112869],"type":"Point"}
}