{
  "type": "Feature",
  "properties": {
    "iso:country":"DE",
    "sg:address":"H\u00fcmmlingweg 16",
    "sg:city":"Bremen",
    "sg:phone":"+49 4942/1451193",
    "sg:postcode":"28309",
    "sg:province":"Bremen",
    "wof:name":"Nomo-zerspannungstechnik Gmbh",
    "wof:placetype":"venue"
},
  "geometry": {"coordinates":[8.90126,53.045406],"type":"Point"}
}