{
  "type": "Feature",
  "properties": {
    "iso:country":"DE",
    "sg:address":"Rathausstr. 14",
    "sg:city":"Altdorf",
    "sg:phone":"+49 7127/33478",
    "sg:postcode":"72655",
    "sg:province":"Baden-W\u00fcrttemberg",
    "wof:name":"Elektro Martin Leitenberger Gmbh & Co. Kg",
    "wof:placetype":"venue"
},
  "geometry": {"coordinates":[9.270794,48.593071],"type":"Point"}
}