{
  "type": "Feature",
  "properties": {
    "iso:country":"DE",
    "sg:address":"Bergstr 8",
    "sg:city":"Hannover",
    "sg:phone":"+49 511/511074",
    "sg:postcode":"30539",
    "sg:province":"Niedersachsen",
    "wof:name":"Aps-industrie-technik Gmbh",
    "wof:placetype":"venue"
},
  "geometry": {"coordinates":[9.8295326233,52.3367462158],"type":"Point"}
}