{
  "type": "Feature",
  "properties": {
    "iso:country":"DE",
    "sg:address":"Ulmenstra\u00dfe 125",
    "sg:city":"D\u00fcsseldorf",
    "sg:phone":"+49 211/3807690",
    "sg:postcode":"40476",
    "sg:province":"Nordrhein-Westfalen",
    "wof:name":"E-plus Mobilfunk Gmbh",
    "wof:placetype":"venue"
},
  "geometry": {"coordinates":[6.781834,51.251202],"type":"Point"}
}