{
  "type": "Feature",
  "properties": {
    "iso:country":"DE",
    "sg:address":"Hauptstr. 6",
    "sg:city":"Vendersheim",
    "sg:phone":"+49 6732/8747",
    "sg:postcode":"55578",
    "sg:province":"Rheinland-Pfalz",
    "wof:name":"Helmut Mohr",
    "wof:placetype":"venue"
},
  "geometry": {"coordinates":[8.0671291351,49.8668136597],"type":"Point"}
}