{
  "type": "Feature",
  "properties": {
    "iso:country":"DE",
    "sg:address":"Lange Str. 36",
    "sg:city":"Wunstorf",
    "sg:phone":"+49 5031/3679",
    "sg:postcode":"31515",
    "sg:province":"Niedersachsen",
    "wof:name":"Wilhelm Herborth",
    "wof:placetype":"venue"
},
  "geometry": {"coordinates":[9.425748,52.425896],"type":"Point"}
}