{
  "type": "Feature",
  "properties": {
    "iso:country":"DE",
    "sg:address":"Gr\u00fcngrabenstr. 10",
    "sg:city":"Albstadt",
    "sg:phone":"+49 7431/9200",
    "sg:postcode":"72458",
    "sg:province":"Baden-W\u00fcrttemberg",
    "wof:name":"C & A",
    "wof:placetype":"venue"
},
  "geometry": {"coordinates":[9.0279655457,48.2129631042],"type":"Point"}
}