{
  "type": "Feature",
  "properties": {
    "iso:country":"DE",
    "sg:address":"T\u00f6pferweg 6",
    "sg:city":"Luckau",
    "sg:phone":"+49 3544/2746",
    "sg:postcode":"15926",
    "sg:province":"Brandenburg",
    "wof:name":"Dr. Harry Zienbold",
    "wof:placetype":"venue"
},
  "geometry": {"coordinates":[13.696969986,51.8456802368],"type":"Point"}
}