{
  "type": "Feature",
  "properties": {
    "iso:country":"DE",
    "sg:address":"Rielasinger Str. 21",
    "sg:city":"Singen",
    "sg:phone":"+49 7731/87210",
    "sg:postcode":"78224",
    "sg:province":"Baden-W\u00fcrttemberg",
    "wof:name":"Ott Und Co.",
    "wof:placetype":"venue"
},
  "geometry": {"coordinates":[8.83882,47.755119],"type":"Point"}
}