{
  "type": "Feature",
  "properties": {
    "iso:country":"DE",
    "sg:address":"Karl-Liebknecht-Str 80",
    "sg:city":"Leipzig",
    "sg:phone":"+49 341/309960",
    "sg:postcode":"04275",
    "sg:province":"Sachsen",
    "wof:name":"Midek\u00ae Gmbh Gesellschaft F\u00fcr Keilriemen- Und Dichtungselemente",
    "wof:placetype":"venue"
},
  "geometry": {"coordinates":[12.373212,51.321426],"type":"Point"}
}