{
  "type": "Feature",
  "properties": {
    "iso:country":"DE",
    "sg:address":"Industriestr. 26",
    "sg:city":"Sinzheim",
    "sg:phone":"+49 7221/98250",
    "sg:postcode":"76547",
    "sg:province":"Baden-W\u00fcrttemberg",
    "wof:name":"Ideal Wohnbaugesellschaft Mbh & Co. Kg",
    "wof:placetype":"venue"
},
  "geometry": {"coordinates":[8.17928,48.777557],"type":"Point"}
}