{
  "type": "Feature",
  "properties": {
    "iso:country":"DE",
    "sg:address":"Ostwennemarstr. 106",
    "sg:city":"Hamm",
    "sg:postcode":"59071",
    "sg:province":"Nordrhein-Westfalen",
    "wof:name":"Rewitax Steuer- Beratungsgesellschaft Mbh",
    "wof:placetype":"venue"
},
  "geometry": {"coordinates":[7.884168148,51.6886520386],"type":"Point"}
}