{
  "type": "Feature",
  "properties": {
    "iso:country":"DE",
    "sg:address":"Dammstr 36a",
    "sg:city":"Werther",
    "sg:phone":"+49 5203/919970",
    "sg:postcode":"33824",
    "sg:province":"Nordrhein-Westfalen",
    "wof:name":"Eugen Theis Gmbh",
    "wof:placetype":"venue"
},
  "geometry": {"coordinates":[8.4049758911,52.0980224609],"type":"Point"}
}