{
  "type": "Feature",
  "properties": {
    "iso:country":"DE",
    "sg:address":"Erlestr. 33",
    "sg:city":"Gelsenkirchen",
    "sg:phone":"+49 209/30967",
    "sg:postcode":"45894",
    "sg:province":"Nordrhein-Westfalen",
    "wof:name":"Rolf L\u00fcmkemann Architekt",
    "wof:placetype":"venue"
},
  "geometry": {"coordinates":[7.062184,51.578529],"type":"Point"}
}