{
  "type": "Feature",
  "properties": {
    "iso:country":"DE",
    "sg:address":"Schwaibacher Str. 29",
    "sg:city":"Anzenkirchen",
    "sg:phone":"+49 8562/2445",
    "sg:postcode":"84371",
    "sg:province":"Bayern",
    "wof:name":"Holzbau Lackner",
    "wof:placetype":"venue"
},
  "geometry": {"coordinates":[13.031512,48.432518],"type":"Point"}
}