{
  "type": "Feature",
  "properties": {
    "iso:country":"DE",
    "sg:address":"Kirchgasse 4",
    "sg:city":"Kirchheim",
    "sg:phone":"+49 7143/92504",
    "sg:postcode":"74366",
    "sg:province":"Baden-W\u00fcrttemberg",
    "wof:name":"Gerhard Langjahr Rechtsanwalt",
    "wof:placetype":"venue"
},
  "geometry": {"coordinates":[9.1464977264,49.0438575745],"type":"Point"}
}