{
  "type": "Feature",
  "properties": {
    "iso:country":"DE",
    "sg:address":"M\u00fcllerstr. 59",
    "sg:city":"Berlin",
    "sg:phone":"+49 30/4510562",
    "sg:postcode":"13349",
    "sg:province":"Berlin",
    "wof:name":"Grill 1",
    "wof:placetype":"venue"
},
  "geometry": {"coordinates":[13.3446836472,52.5548858643],"type":"Point"}
}