{
  "type": "Feature",
  "properties": {
    "iso:country":"DE",
    "sg:address":"Dattelnerstr. 30",
    "sg:city":"Castrop-Rauxel",
    "sg:phone":"+49 172",
    "sg:postcode":"44577",
    "sg:province":"Nordrhein-Westfalen",
    "wof:name":"Weber Automobile",
    "wof:placetype":"venue"
},
  "geometry": {"coordinates":[7.316901207,51.6148300171],"type":"Point"}
}