{
  "type": "Feature",
  "properties": {
    "iso:country":"DE",
    "sg:address":"Jakob-Haspel-Str. 60",
    "sg:city":"Heilbronn",
    "sg:phone":"+49 7131/24677",
    "sg:postcode":"74078",
    "sg:province":"Baden-W\u00fcrttemberg",
    "wof:name":"Obradovic Gmbh",
    "wof:placetype":"venue"
},
  "geometry": {"coordinates":[9.187765,49.16959],"type":"Point"}
}