{
  "type": "Feature",
  "properties": {
    "iso:country":"DE",
    "sg:address":"Eckenerstr. 35",
    "sg:city":"Karlsruhe",
    "sg:phone":"+49 721/575826",
    "sg:postcode":"76185",
    "sg:province":"Baden-W\u00fcrttemberg",
    "wof:name":"Dabb Nei",
    "wof:placetype":"venue"
},
  "geometry": {"coordinates":[8.3454818726,49.0015792847],"type":"Point"}
}