{
  "type": "Feature",
  "properties": {
    "iso:country":"DE",
    "sg:address":"Obere Vorstadtstr. 12",
    "sg:city":"Walld\u00fcrn",
    "sg:phone":"+49 6282/8283",
    "sg:postcode":"74731",
    "sg:province":"Baden-W\u00fcrttemberg",
    "wof:name":"Volpert Gmbh",
    "wof:placetype":"venue"
},
  "geometry": {"coordinates":[9.367374,49.582962],"type":"Point"}
}