{
  "type": "Feature",
  "properties": {
    "iso:country":"DE",
    "sg:address":"Hensenweg 45",
    "sg:city":"M\u00f6nchengladbach",
    "sg:phone":"+49 2161/895600",
    "sg:postcode":"41068",
    "sg:province":"Nordrhein-Westfalen",
    "wof:name":"Heinz D\u00f6lle",
    "wof:placetype":"venue"
},
  "geometry": {"coordinates":[6.407479,51.19857],"type":"Point"}
}