{
  "type": "Feature",
  "properties": {
    "iso:country":"DE",
    "sg:address":"Am Sonnenh\u00fcgel 3",
    "sg:city":"Neuglobsow",
    "sg:phone":"+49 33082/70304",
    "sg:postcode":"16775",
    "sg:province":"Brandenburg",
    "wof:name":"Harry Becker",
    "wof:placetype":"venue"
},
  "geometry": {"coordinates":[13.045176,53.145985],"type":"Point"}
}