{
  "type": "Feature",
  "properties": {
    "iso:country":"DE",
    "sg:address":"Neue S\u00fclze 22",
    "sg:city":"L\u00fcneburg",
    "sg:phone":"+49 4131/760399",
    "sg:postcode":"21335",
    "sg:province":"Niedersachsen",
    "wof:name":"Ollis Musikstore",
    "wof:placetype":"venue"
},
  "geometry": {"coordinates":[10.4048423767,53.2482376099],"type":"Point"}
}