{
  "type": "Feature",
  "properties": {
    "iso:country":"DE",
    "sg:address":"Dr.-Paul-M\u00fcller-Str. 62",
    "sg:city":"Lennestadt",
    "sg:phone":"+49 2721/94160",
    "sg:postcode":"57368",
    "sg:province":"Nordrhein-Westfalen",
    "wof:name":"Sonntag Gmbh",
    "wof:placetype":"venue"
},
  "geometry": {"coordinates":[8.01443,51.118019],"type":"Point"}
}