{
  "type": "Feature",
  "properties": {
    "iso:country":"DE",
    "sg:address":"K\u00f6nigsberger Str. 8",
    "sg:city":"Bebra",
    "sg:phone":"+49 6622/3301",
    "sg:postcode":"36179",
    "sg:province":"Hessen",
    "wof:name":"Norbert Schimke",
    "wof:placetype":"venue"
},
  "geometry": {"coordinates":[9.807674,50.969845],"type":"Point"}
}