{
  "type": "Feature",
  "properties": {
    "iso:country":"DE",
    "sg:address":"Untere Hauptstr. 33",
    "sg:city":"Hockenheim",
    "sg:phone":"+49 6205/7316",
    "sg:postcode":"68766",
    "sg:province":"Baden-W\u00fcrttemberg",
    "wof:name":"Pension Krone",
    "wof:placetype":"venue"
},
  "geometry": {"coordinates":[8.5449485779,49.3207092285],"type":"Point"}
}