{
  "type": "Feature",
  "properties": {
    "iso:country":"DE",
    "sg:address":"Gocher Str. 31",
    "sg:city":"Uedem",
    "sg:phone":"+49 2825/294",
    "sg:postcode":"47589",
    "sg:province":"Nordrhein-Westfalen",
    "wof:name":"Heinr. Haal",
    "wof:placetype":"venue"
},
  "geometry": {"coordinates":[6.265955,51.666138],"type":"Point"}
}