{
  "type": "Feature",
  "properties": {
    "iso:country":"DE",
    "sg:address":"Weingasse 2",
    "sg:city":"Regensburg",
    "sg:phone":"+49 941/5997087",
    "sg:postcode":"93047",
    "sg:province":"Bayern",
    "wof:name":"H.-p. Zierer Fotoatelier",
    "wof:placetype":"venue"
},
  "geometry": {"coordinates":[12.0928058624,49.0206718445],"type":"Point"}
}