{
  "type": "Feature",
  "properties": {
    "iso:country":"DE",
    "sg:address":"Drachhausener Str. 70",
    "sg:city":"Cottbus",
    "sg:postcode":"03044",
    "sg:province":"Brandenburg",
    "wof:name":"Landhotel Am Kappenberg Gmbh",
    "wof:placetype":"venue"
},
  "geometry": {"coordinates":[14.3207759857,51.7815666199],"type":"Point"}
}