{
  "type": "Feature",
  "properties": {
    "iso:country":"DE",
    "sg:address":"Geschwister-Scholl-Str. 1",
    "sg:city":"Rostock",
    "sg:phone":"+49 381/83090",
    "sg:postcode":"18069",
    "sg:province":"Mecklenburg-Vorpommern",
    "wof:name":"Dietrich Timm Garten- Und Landschafts-",
    "wof:placetype":"venue"
},
  "geometry": {"coordinates":[12.078941,54.097687],"type":"Point"}
}