{
  "type": "Feature",
  "properties": {
    "iso:country":"DE",
    "sg:address":"Kaiserstuhlstr. 12-14",
    "sg:city":"Freiburg",
    "sg:phone":"+49 761/281210",
    "sg:postcode":"79106",
    "sg:province":"Baden-W\u00fcrttemberg",
    "wof:name":"Bus Connection Gmbh & Co. Kg",
    "wof:placetype":"venue"
},
  "geometry": {"coordinates":[7.8457489014,48.010345459],"type":"Point"}
}