{
  "type": "Feature",
  "properties": {
    "iso:country":"DE",
    "sg:address":"Neuhauser Str. 12",
    "sg:city":"Konstanz",
    "sg:phone":"+49 7531/56664",
    "sg:postcode":"78464",
    "sg:province":"Baden-W\u00fcrttemberg",
    "wof:name":"Helmut K. Doerfler Bdw",
    "wof:placetype":"venue"
},
  "geometry": {"coordinates":[9.1886386871,47.6685562134],"type":"Point"}
}