{
  "type": "Feature",
  "properties": {
    "iso:country":"DE",
    "sg:address":"Salzstr. 20",
    "sg:city":"Tuttlingen",
    "sg:phone":"+49 7461/76486",
    "sg:postcode":"78532",
    "sg:province":"Baden-W\u00fcrttemberg",
    "wof:name":"A. Dilanc",
    "wof:placetype":"venue"
},
  "geometry": {"coordinates":[8.8173055649,47.9823303223],"type":"Point"}
}