{
  "type": "Feature",
  "properties": {
    "iso:country":"DE",
    "sg:address":"Cranachstr. 42",
    "sg:city":"Berlin",
    "sg:phone":"+49 30/8520045",
    "sg:postcode":"12157",
    "sg:province":"Berlin",
    "wof:name":"Art Software Design Gmbh",
    "wof:placetype":"venue"
},
  "geometry": {"coordinates":[13.3427238464,52.4652290344],"type":"Point"}
}