{
  "type": "Feature",
  "properties": {
    "iso:country":"DE",
    "sg:address":"Thunacker 12",
    "sg:city":"Ibbenb\u00fcren",
    "sg:phone":"+49 5451/8235",
    "sg:postcode":"49479",
    "sg:province":"Nordrhein-Westfalen",
    "wof:name":"Gerd Wroberger",
    "wof:placetype":"venue"
},
  "geometry": {"coordinates":[7.794604,52.254128],"type":"Point"}
}