{
  "type": "Feature",
  "properties": {
    "iso:country":"DE",
    "sg:address":"Dr.-Eckener-Str. 3",
    "sg:city":"Eppelheim",
    "sg:postcode":"69214",
    "sg:province":"Baden-W\u00fcrttemberg",
    "wof:name":"Homogen-bau Gmbh",
    "wof:placetype":"venue"
},
  "geometry": {"coordinates":[8.628857,49.401604],"type":"Point"}
}