{
  "type": "Feature",
  "properties": {
    "iso:country":"DE",
    "sg:address":"Hauptstr. 20",
    "sg:city":"Bretzfeld",
    "sg:phone":"+49 7946/2788",
    "sg:postcode":"74626",
    "sg:province":"Baden-W\u00fcrttemberg",
    "wof:name":"Richard Und Regina Weihbrecht",
    "wof:placetype":"venue"
},
  "geometry": {"coordinates":[9.4038486481,49.1833572388],"type":"Point"}
}