{
  "type": "Feature",
  "properties": {
    "iso:country":"DE",
    "sg:address":"Westentor 3",
    "sg:city":"Hamm",
    "sg:phone":"+49 2381/922110",
    "sg:postcode":"59065",
    "sg:province":"Nordrhein-Westfalen",
    "wof:name":"Forum-apotheke Dr. Frank J. Bialaschik",
    "wof:placetype":"venue"
},
  "geometry": {"coordinates":[7.8137660027,51.6798973083],"type":"Point"}
}