{
  "type": "Feature",
  "properties": {
    "iso:country":"DE",
    "sg:address":"Burgtorgasse 3",
    "sg:city":"Neukirchen",
    "sg:phone":"+49 6694/248",
    "sg:postcode":"34626",
    "sg:province":"Hessen",
    "wof:name":"Bedachungen Mantz Gmbh",
    "wof:placetype":"venue"
},
  "geometry": {"coordinates":[9.345237,50.866756],"type":"Point"}
}