{
  "type": "Feature",
  "properties": {
    "iso:country":"DE",
    "sg:address":"Friedenstr. 6",
    "sg:city":"Pforzheim",
    "sg:phone":"+49 7231/290898",
    "sg:postcode":"75173",
    "sg:province":"Baden-W\u00fcrttemberg",
    "wof:name":"Wenzeslaus Weirich Und Wolfgang F Deschler Uhren Und Juwelenhandelsgese Gmbh",
    "wof:placetype":"venue"
},
  "geometry": {"coordinates":[8.6924905777,48.8847122192],"type":"Point"}
}