{
  "type": "Feature",
  "properties": {
    "iso:country":"DE",
    "sg:address":"Haldenweg 21",
    "sg:city":"Gro\u00dferlach",
    "sg:phone":"+49 7192/6132",
    "sg:postcode":"71577",
    "sg:province":"Baden-W\u00fcrttemberg",
    "wof:name":"Kurt Stradinger",
    "wof:placetype":"venue"
},
  "geometry": {"coordinates":[9.57153,49.024921],"type":"Point"}
}