{
  "type": "Feature",
  "properties": {
    "iso:country":"DE",
    "sg:address":"Rosenstr. 38 a",
    "sg:city":"Diez",
    "sg:phone":"+49 6432/7743",
    "sg:postcode":"65582",
    "sg:province":"Rheinland-Pfalz",
    "wof:name":"H. Schmidt",
    "wof:placetype":"venue"
},
  "geometry": {"coordinates":[8.0067,50.370457],"type":"Point"}
}