{
  "type": "Feature",
  "properties": {
    "iso:country":"DE",
    "sg:address":"Hohensteiner str. 5",
    "sg:city":"Delmenhorst",
    "sg:phone":"+49 4221",
    "sg:postcode":"27751",
    "sg:province":"Niedersachsen",
    "wof:name":"Guido Sander, Bezirksleitung Vereinte Krankenversicherung",
    "wof:placetype":"venue"
},
  "geometry": {"coordinates":[8.6728124619,53.0505828857],"type":"Point"}
}