{
  "type": "Feature",
  "properties": {
    "iso:country":"DE",
    "sg:address":"Trierer Str. 43",
    "sg:city":"Newel",
    "sg:phone":"+49 6505/1374",
    "sg:postcode":"54309",
    "sg:province":"Rheinland-Pfalz",
    "wof:name":"W. Schneider",
    "wof:placetype":"venue"
},
  "geometry": {"coordinates":[6.61504,49.807411],"type":"Point"}
}