{
  "type": "Feature",
  "properties": {
    "iso:country":"DE",
    "sg:address":"Berliner Str.",
    "sg:city":"Rheda-Wiedenbr\u00fcck",
    "sg:phone":"+49 5242/94440",
    "sg:postcode":"33378",
    "sg:province":"Nordrhein-Westfalen",
    "wof:name":"Reiling Gmbh",
    "wof:placetype":"venue"
},
  "geometry": {"coordinates":[8.2914304733,51.8510665894],"type":"Point"}
}