{
  "type": "Feature",
  "properties": {
    "iso:country":"DE",
    "sg:address":"Peter-Gehlen-Str. 11",
    "sg:city":"Erkelenz",
    "sg:phone":"+49 2431/5934",
    "sg:postcode":"41812",
    "sg:province":"Nordrhein-Westfalen",
    "wof:name":"Johann Heid",
    "wof:placetype":"venue"
},
  "geometry": {"coordinates":[6.284208,51.079453],"type":"Point"}
}