{
  "type": "Feature",
  "properties": {
    "iso:country":"DE",
    "sg:address":"Recheweg 1",
    "sg:city":"Kaltenengers",
    "sg:phone":"+49 2630/6811",
    "sg:postcode":"56220",
    "sg:province":"Rheinland-Pfalz",
    "wof:name":"Peter Schuth",
    "wof:placetype":"venue"
},
  "geometry": {"coordinates":[7.540109,50.41737],"type":"Point"}
}