{
  "type": "Feature",
  "properties": {
    "iso:country":"DE",
    "sg:address":"Karlstr. 17",
    "sg:city":"Baden-Baden",
    "sg:phone":"+49 7223/9908430",
    "sg:postcode":"76530",
    "sg:province":"Baden-W\u00fcrttemberg",
    "wof:name":"P.o.s. Media Gmbh",
    "wof:placetype":"venue"
},
  "geometry": {"coordinates":[8.231133461,48.7703971863],"type":"Point"}
}