{
  "type": "Feature",
  "properties": {
    "iso:country":"DE",
    "sg:address":"Pretzfelder Str. 15",
    "sg:city":"N\u00fcrnberg",
    "sg:phone":"+49 911/9347110",
    "sg:postcode":"90425",
    "sg:province":"Bayern",
    "wof:name":"M\u00fcller Adress Und Neue Mediengesellschaft",
    "wof:placetype":"venue"
},
  "geometry": {"coordinates":[11.063049,49.471912],"type":"Point"}
}