{
  "type": "Feature",
  "properties": {
    "iso:country":"DE",
    "sg:address":"Am Weichselgarten 7",
    "sg:city":"Erlangen",
    "sg:phone":"+49 9131/691160",
    "sg:postcode":"91058",
    "sg:province":"Bayern",
    "wof:name":"Opticom Dipl. Ing. M. Keyhl Gmbh",
    "wof:placetype":"venue"
},
  "geometry": {"coordinates":[11.0256357193,49.5429649353],"type":"Point"}
}