{
  "type": "Feature",
  "properties": {
    "iso:country":"DE",
    "sg:address":"Elbchaussee 185",
    "sg:city":"Hamburg",
    "sg:phone":"+49 40/8800587",
    "sg:postcode":"22605",
    "sg:province":"Hamburg",
    "wof:name":"Christel Hudemann-schwartz Kunstmalerin",
    "wof:placetype":"venue"
},
  "geometry": {"coordinates":[9.905197,53.545479],"type":"Point"}
}