{
  "type": "Feature",
  "properties": {
    "iso:country":"DE",
    "sg:address":"Reichenstr. 8",
    "sg:city":"Hemdingen",
    "sg:phone":"+49 4123/3146",
    "sg:postcode":"25485",
    "sg:province":"Schleswig-Holstein",
    "wof:name":"H. Und K. Jensen",
    "wof:placetype":"venue"
},
  "geometry": {"coordinates":[9.8446655273,53.7668190002],"type":"Point"}
}