{
  "type": "Feature",
  "properties": {
    "iso:country":"DE",
    "sg:address":"Brauhausgasse 31",
    "sg:city":"Luckau",
    "sg:phone":"+49 3544/2791",
    "sg:postcode":"15926",
    "sg:province":"Brandenburg",
    "wof:name":"H. Roske",
    "wof:placetype":"venue"
},
  "geometry": {"coordinates":[13.7127809525,51.8515586853],"type":"Point"}
}