{
  "type": "Feature",
  "properties": {
    "iso:country":"DE",
    "sg:address":"Hagenstr. 26",
    "sg:city":"Korbach",
    "sg:phone":"+49 5631/64607",
    "sg:postcode":"34497",
    "sg:province":"Hessen",
    "wof:name":"Karin Schenck Und G. Emde Krankengymnasten",
    "wof:placetype":"venue"
},
  "geometry": {"coordinates":[8.865132,51.277107],"type":"Point"}
}