{
  "type": "Feature",
  "properties": {
    "iso:country":"DE",
    "sg:address":"Europaweg 6",
    "sg:city":"Ostrach",
    "sg:phone":"+49 7585/2405",
    "sg:postcode":"88356",
    "sg:province":"Baden-W\u00fcrttemberg",
    "wof:name":"R. Winkler",
    "wof:placetype":"venue"
},
  "geometry": {"coordinates":[9.384806,47.954144],"type":"Point"}
}