{
  "type": "Feature",
  "properties": {
    "iso:country":"DE",
    "sg:address":"Farnweg 10",
    "sg:city":"Villingen",
    "sg:phone":"+49 7721/94840",
    "sg:postcode":"78048",
    "sg:province":"Baden-W\u00fcrttemberg",
    "wof:name":"Schwarzwald Schwarzwald Villingen Hotel Garland",
    "wof:placetype":"venue"
},
  "geometry": {"coordinates":[8.431666,48.072517],"type":"Point"}
}