{
  "type": "Feature",
  "properties": {
    "iso:country":"DE",
    "sg:address":"Industriestr. 17",
    "sg:city":"Feuchtwangen",
    "sg:phone":"+49 9852/2088",
    "sg:postcode":"91555",
    "sg:province":"Bayern",
    "wof:name":"J\u00f6rg H\u00e4hnlein Architekt",
    "wof:placetype":"venue"
},
  "geometry": {"coordinates":[10.319597,49.164555],"type":"Point"}
}