{
  "type": "Feature",
  "properties": {
    "iso:country":"DE",
    "sg:address":"St.-Johann-Str. 16",
    "sg:city":"Duisburg",
    "sg:phone":"+49 203/662575",
    "sg:postcode":"47053",
    "sg:province":"Nordrhein-Westfalen",
    "wof:name":"Marie-luise Keuser",
    "wof:placetype":"venue"
},
  "geometry": {"coordinates":[6.754996,51.417004],"type":"Point"}
}