{
  "type": "Feature",
  "properties": {
    "iso:country":"DE",
    "sg:address":"Hauptstr. 30",
    "sg:city":"Liesenich",
    "sg:phone":"+49 6545/1843",
    "sg:postcode":"56858",
    "sg:province":"Rheinland-Pfalz",
    "wof:name":"Hotel-restaurant Moselh\u00f6he",
    "wof:placetype":"venue"
},
  "geometry": {"coordinates":[7.2658758163,50.0850486755],"type":"Point"}
}