{
  "type": "Feature",
  "properties": {
    "iso:country":"DE",
    "sg:address":"An der Windm\u00fchle 2",
    "sg:city":"Kamenz",
    "sg:postcode":"01917",
    "sg:province":"Sachsen",
    "wof:name":"Jeans Und Mehr",
    "wof:placetype":"venue"
},
  "geometry": {"coordinates":[14.104683876,51.2742576599],"type":"Point"}
}