{
  "type": "Feature",
  "properties": {
    "iso:country":"DE",
    "sg:address":"Kirschgartenstr. 1",
    "sg:city":"Hofheim",
    "sg:phone":"+49 6192/6201",
    "sg:postcode":"65719",
    "sg:province":"Hessen",
    "wof:name":"Albrecht Faust",
    "wof:placetype":"venue"
},
  "geometry": {"coordinates":[8.4462575912,50.0862464905],"type":"Point"}
}