{
  "type": "Feature",
  "properties": {
    "iso:country":"DE",
    "sg:address":"Ahornweg 17",
    "sg:city":"Seelow",
    "sg:phone":"+49 3346/80925",
    "sg:postcode":"15306",
    "sg:province":"Brandenburg",
    "wof:name":"Renate Rogosch",
    "wof:placetype":"venue"
},
  "geometry": {"coordinates":[14.3822593689,52.5390434265],"type":"Point"}
}