{
  "type": "Feature",
  "properties": {
    "iso:country":"DE",
    "sg:address":"An der Schlade 7",
    "sg:city":"Kassel",
    "sg:phone":"+49 561/523970",
    "sg:postcode":"34123",
    "sg:province":"Hessen",
    "wof:name":"H. Eisenhuth Gmbh",
    "wof:placetype":"venue"
},
  "geometry": {"coordinates":[9.554374,51.30637],"type":"Point"}
}