{
  "type": "Feature",
  "properties": {
    "iso:country":"DE",
    "sg:address":"Neumarkt 7",
    "sg:city":"Bischofswerda",
    "sg:phone":"+49 3594/704533",
    "sg:postcode":"01877",
    "sg:province":"Sachsen",
    "wof:name":"Bestattungshaus Griete",
    "wof:placetype":"venue"
},
  "geometry": {"coordinates":[14.177204,51.127781],"type":"Point"}
}