{
  "type": "Feature",
  "properties": {
    "iso:country":"DE",
    "sg:address":"Wilhelm-Leuschner-Str. 1",
    "sg:city":"Seeheim-Jugenheim",
    "sg:phone":"+49 6257/86414",
    "sg:postcode":"64342",
    "sg:province":"Hessen",
    "wof:name":"La Potiniere",
    "wof:placetype":"venue"
},
  "geometry": {"coordinates":[8.6474761963,49.7684745789],"type":"Point"}
}