{
  "type": "Feature",
  "properties": {
    "iso:country":"DE",
    "sg:address":"Schillerstr. 23",
    "sg:city":"Heidenau",
    "sg:phone":"+49 3529/512312",
    "sg:postcode":"01809",
    "sg:province":"Sachsen",
    "wof:name":"Heidenauer Blech- Bearbeitungs Gmbh",
    "wof:placetype":"venue"
},
  "geometry": {"coordinates":[13.871388,50.969009],"type":"Point"}
}