{
  "type": "Feature",
  "properties": {
    "iso:country":"DE",
    "sg:address":"Aue 23-27",
    "sg:city":"Chemnitz",
    "sg:phone":"+49 371/6512378",
    "sg:postcode":"09112",
    "sg:province":"Sachsen",
    "wof:name":"Rawema Countertrade Handelsgesellschaft Mbh",
    "wof:placetype":"venue"
},
  "geometry": {"coordinates":[12.9182395935,50.8272094727],"type":"Point"}
}