{
  "type": "Feature",
  "properties": {
    "iso:country":"DE",
    "sg:address":"Obere Wank 19",
    "sg:city":"Nesselwang",
    "sg:phone":"+49 8361/1366",
    "sg:postcode":"87484",
    "sg:province":"Bayern",
    "wof:name":"Peter Schlichtling",
    "wof:placetype":"venue"
},
  "geometry": {"coordinates":[10.508878,47.618732],"type":"Point"}
}