{
  "type": "Feature",
  "properties": {
    "iso:country":"DE",
    "sg:address":"Im Mohrenfeld 15",
    "sg:city":"Bonn",
    "sg:phone":"+49 228/9442073",
    "sg:postcode":"53227",
    "sg:province":"Nordrhein-Westfalen",
    "wof:name":"H. Fromm Finanzberater",
    "wof:placetype":"venue"
},
  "geometry": {"coordinates":[7.1725258827,50.7088088989],"type":"Point"}
}