{
  "type": "Feature",
  "properties": {
    "iso:country":"DE",
    "sg:address":"Mauritzstr. 29-32",
    "sg:city":"M\u00fcnster",
    "sg:postcode":"48143",
    "sg:province":"Nordrhein-Westfalen",
    "wof:name":"Rs-m\u00f6bel Gmbh",
    "wof:placetype":"venue"
},
  "geometry": {"coordinates":[7.634136,51.961891],"type":"Point"}
}