{
  "type": "Feature",
  "properties": {
    "iso:country":"DE",
    "sg:address":"Tannenweg 4",
    "sg:city":"Frankfurt",
    "sg:phone":"+49 69/5073740",
    "sg:postcode":"60437",
    "sg:province":"Hessen",
    "wof:name":"Gerhart Friese",
    "wof:placetype":"venue"
},
  "geometry": {"coordinates":[8.6700935364,50.2024116516],"type":"Point"}
}