{
  "type": "Feature",
  "properties": {
    "iso:country":"DE",
    "sg:address":"Zolltenstr. 27",
    "sg:city":"Dettenheim",
    "sg:phone":"+49 7255/4546",
    "sg:postcode":"76706",
    "sg:province":"Baden-W\u00fcrttemberg",
    "wof:name":"Wolfgang Kuhnl Gmbh",
    "wof:placetype":"venue"
},
  "geometry": {"coordinates":[8.422627449,49.186706543],"type":"Point"}
}