{
  "type": "Feature",
  "properties": {
    "iso:country":"DE",
    "sg:address":"Thann 5",
    "sg:city":"Berching",
    "sg:phone":"+49 9184/1698",
    "sg:postcode":"92334",
    "sg:province":"Bayern",
    "wof:name":"Gastst\u00e4tte G\u00fcnther Kn\u00f6r",
    "wof:placetype":"venue"
},
  "geometry": {"coordinates":[11.5314235687,49.1616668701],"type":"Point"}
}