{
  "type": "Feature",
  "properties": {
    "iso:country":"DE",
    "sg:address":"Stra\u00dfe der Stahlwerker 14",
    "sg:city":"Crossen",
    "sg:phone":"+49 36693/4860",
    "sg:postcode":"07613",
    "sg:province":"Th\u00fcringen",
    "wof:name":"Wohnungsgenossenschaft Crossen-hartmannsdorf Eg",
    "wof:placetype":"venue"
},
  "geometry": {"coordinates":[11.9721012115,50.9739952087],"type":"Point"}
}