{
  "type": "Feature",
  "properties": {
    "iso:country":"DE",
    "sg:address":"G\u00e4nsfu\u00dfallee 23",
    "sg:city":"Ludwigsburg",
    "sg:phone":"+49 7141/9100",
    "sg:postcode":"71636",
    "sg:province":"Baden-W\u00fcrttemberg",
    "wof:name":"Stadtwerke Ludwigsburg Gmbh",
    "wof:placetype":"venue"
},
  "geometry": {"coordinates":[9.175419,48.892323],"type":"Point"}
}