{
  "type": "Feature",
  "properties": {
    "iso:country":"DE",
    "sg:address":"Hospitalstr. 17",
    "sg:city":"Reichenbach",
    "sg:phone":"+49 3765/12851",
    "sg:postcode":"08468",
    "sg:province":"Sachsen",
    "wof:name":"Georg Schneider",
    "wof:placetype":"venue"
},
  "geometry": {"coordinates":[12.3076820374,50.6136436462],"type":"Point"}
}