{
  "type": "Feature",
  "properties": {
    "iso:country":"DE",
    "sg:address":"Rielasinger Str. 11",
    "sg:city":"Singen",
    "sg:phone":"+49 7731/63146",
    "sg:postcode":"78224",
    "sg:province":"Baden-W\u00fcrttemberg",
    "wof:name":"A. Bross",
    "wof:placetype":"venue"
},
  "geometry": {"coordinates":[8.837805748,47.756149292],"type":"Point"}
}