{
  "type": "Feature",
  "properties": {
    "iso:country":"DE",
    "sg:address":"Wilhelm-Liebknecht-Str. 1",
    "sg:city":"Merseburg",
    "sg:phone":"+49 3461/440150",
    "sg:postcode":"06217",
    "sg:province":"Sachsen-Anhalt",
    "wof:name":"Historisches Stadtarchiv",
    "wof:placetype":"venue"
},
  "geometry": {"coordinates":[11.988944,51.355156],"type":"Point"}
}