{
  "type": "Feature",
  "properties": {
    "iso:country":"DE",
    "sg:address":"Am Hambuch 17",
    "sg:city":"Meckenheim",
    "sg:postcode":"53340",
    "sg:province":"Nordrhein-Westfalen",
    "wof:name":"Vibra Multimedia Gmbh",
    "wof:placetype":"venue"
},
  "geometry": {"coordinates":[7.0242629051,50.6488113403],"type":"Point"}
}