{
  "type": "Feature",
  "properties": {
    "iso:country":"DE",
    "sg:address":"Am Wall 184",
    "sg:city":"Bremen",
    "sg:phone":"+49 421/325421",
    "sg:postcode":"28195",
    "sg:province":"Bremen",
    "wof:name":"Rupert H\u00f6rnig Verlagsvertreter",
    "wof:placetype":"venue"
},
  "geometry": {"coordinates":[8.812272,53.075832],"type":"Point"}
}