{
  "type": "Feature",
  "properties": {
    "iso:country":"DE",
    "sg:address":"Feuerdornweg 10",
    "sg:city":"Augsburg",
    "sg:postcode":"86169",
    "sg:province":"Bayern",
    "wof:name":"Softwhere-it E. K.",
    "wof:placetype":"venue"
},
  "geometry": {"coordinates":[10.9156856537,48.3980102539],"type":"Point"}
}