{
  "type": "Feature",
  "properties": {
    "iso:country":"DE",
    "sg:address":"Am Hellteich 19",
    "sg:city":"Walsrode",
    "sg:phone":"+49 5161/910707",
    "sg:postcode":"29664",
    "sg:province":"Niedersachsen",
    "wof:name":"Coors Aquaristik Und Zoobedarf Gmbh",
    "wof:placetype":"venue"
},
  "geometry": {"coordinates":[9.604246,52.871078],"type":"Point"}
}