{
  "type": "Feature",
  "properties": {
    "iso:country":"DE",
    "sg:address":"Hirtenweg 54",
    "sg:city":"Rotenburg",
    "sg:phone":"+49 4261/94400",
    "sg:postcode":"27356",
    "sg:province":"Niedersachsen",
    "wof:name":"Spedition Cl\u00fcver Gmbh & Co",
    "wof:placetype":"venue"
},
  "geometry": {"coordinates":[9.4276971817,53.1248321533],"type":"Point"}
}