{
  "type": "Feature",
  "properties": {
    "iso:country":"DE",
    "sg:address":"Br\u00fcder-Grimm-Str. 84",
    "sg:city":"Steinau",
    "sg:phone":"+49 6663/1584",
    "sg:postcode":"36396",
    "sg:province":"Hessen",
    "wof:name":"Nachtcafe Motte",
    "wof:placetype":"venue"
},
  "geometry": {"coordinates":[9.45965,50.312431],"type":"Point"}
}