{
  "type": "Feature",
  "properties": {
    "iso:country":"DE",
    "sg:address":"Hauptstr. 112",
    "sg:city":"P\u00f6lzig",
    "sg:phone":"+49 36695/20980",
    "sg:postcode":"07554",
    "sg:province":"Th\u00fcringen",
    "wof:name":"Pension Zum Alten Bahnhof",
    "wof:placetype":"venue"
},
  "geometry": {"coordinates":[12.1864404678,50.9563598633],"type":"Point"}
}