{
  "type": "Feature",
  "properties": {
    "iso:country":"DE",
    "sg:address":"Erlenstra\u00dfe 5-7",
    "sg:city":"Wertheim",
    "sg:phone":"+49 9342",
    "sg:postcode":"97877",
    "sg:province":"Baden-W\u00fcrttemberg",
    "wof:name":"Lutz-pumpen Gmbh&co.co",
    "wof:placetype":"venue"
},
  "geometry": {"coordinates":[9.5070390701,49.7803726196],"type":"Point"}
}