{
  "type": "Feature",
  "properties": {
    "iso:country":"DE",
    "sg:address":"Am Weiher 6",
    "sg:city":"Marsberg",
    "sg:phone":"+49 2991/200",
    "sg:postcode":"34431",
    "sg:province":"Nordrhein-Westfalen",
    "wof:name":"Diemeltal",
    "wof:placetype":"venue"
},
  "geometry": {"coordinates":[8.73026371,51.3826332092],"type":"Point"}
}