{
  "type": "Feature",
  "properties": {
    "iso:country":"DE",
    "sg:address":"Strindbergweg 11",
    "sg:city":"Hamburg",
    "sg:phone":"+49 40/866164",
    "sg:postcode":"22587",
    "sg:province":"Hamburg",
    "wof:name":"Stiftung Lulu Und Robert Bartolomay",
    "wof:placetype":"venue"
},
  "geometry": {"coordinates":[9.791176796,53.5679512024],"type":"Point"}
}