{
  "type": "Feature",
  "properties": {
    "iso:country":"DE",
    "sg:address":"Narzissenweg 1",
    "sg:city":"Kehl",
    "sg:phone":"+49 7854/7083",
    "sg:postcode":"77694",
    "sg:province":"Baden-W\u00fcrttemberg",
    "wof:name":"Iris-apotheke",
    "wof:placetype":"venue"
},
  "geometry": {"coordinates":[7.822254,48.521118],"type":"Point"}
}