{
  "type": "Feature",
  "properties": {
    "iso:country":"DE",
    "sg:address":"M\u00fcnchener Str. 9",
    "sg:city":"Sauerlach",
    "sg:phone":"+49 8104/1330",
    "sg:postcode":"82054",
    "sg:province":"Bayern",
    "wof:name":"Sophie Bruckner",
    "wof:placetype":"venue"
},
  "geometry": {"coordinates":[11.653633,47.973495],"type":"Point"}
}