{
  "type": "Feature",
  "properties": {
    "iso:country":"DE",
    "sg:address":"Neuenhoefer Allee 49 - 51",
    "sg:city":"K\u00f6ln",
    "sg:phone":"+49 4922/1463091",
    "sg:postcode":"50935",
    "sg:province":"Nordrhein-Westfalen",
    "wof:name":"Nenninger Gmbh",
    "wof:placetype":"venue"
},
  "geometry": {"coordinates":[6.912779808,50.9159088135],"type":"Point"}
}