{
  "type": "Feature",
  "properties": {
    "iso:country":"DE",
    "sg:address":"Zwiesele 86",
    "sg:city":"Heimenkirch",
    "sg:phone":"+49 8385/1784",
    "sg:postcode":"88178",
    "sg:province":"Bayern",
    "wof:name":"Horst Baumann Mechanische Fertigung E. K.",
    "wof:placetype":"venue"
},
  "geometry": {"coordinates":[9.87359,47.639561],"type":"Point"}
}