{
  "type": "Feature",
  "properties": {
    "iso:country":"DE",
    "sg:address":"Bockhorst 6",
    "sg:city":"Versmold",
    "sg:phone":"+49 5423/7738",
    "sg:postcode":"33775",
    "sg:province":"Nordrhein-Westfalen",
    "wof:name":"Otto Peters",
    "wof:placetype":"venue"
},
  "geometry": {"coordinates":[8.20525,52.074551],"type":"Point"}
}