{
  "type": "Feature",
  "properties": {
    "iso:country":"DE",
    "sg:address":"Seligenthaler Str. 48",
    "sg:city":"Landshut",
    "sg:phone":"+49 871/9247910",
    "sg:postcode":"84034",
    "sg:province":"Bayern",
    "wof:name":"Robert Wilborn Gmbh",
    "wof:placetype":"venue"
},
  "geometry": {"coordinates":[12.143244,48.545223],"type":"Point"}
}