{
  "type": "Feature",
  "properties": {
    "iso:country":"DE",
    "sg:address":"Immelmannstr. 12",
    "sg:city":"Landau",
    "sg:phone":"+49 6341/87733",
    "sg:postcode":"76829",
    "sg:province":"Rheinland-Pfalz",
    "wof:name":"Hans Weber Ingenieur",
    "wof:placetype":"venue"
},
  "geometry": {"coordinates":[8.1133136749,49.2043266296],"type":"Point"}
}