{
  "type": "Feature",
  "properties": {
    "iso:country":"DE",
    "sg:address":"Eichenstr. 95",
    "sg:city":"Bondorf",
    "sg:phone":"+49 7457/1494",
    "sg:postcode":"71149",
    "sg:province":"Baden-W\u00fcrttemberg",
    "wof:name":"G\u00fcnter Noll",
    "wof:placetype":"venue"
},
  "geometry": {"coordinates":[8.8309249878,48.5251159668],"type":"Point"}
}