{
  "type": "Feature",
  "properties": {
    "iso:country":"DE",
    "sg:address":"Bahnhofstr. 38a",
    "sg:city":"Kusel",
    "sg:phone":"+49 6381/3440",
    "sg:postcode":"66869",
    "sg:province":"Rheinland-Pfalz",
    "wof:name":"Kurt Schleicher Augenoptiker",
    "wof:placetype":"venue"
},
  "geometry": {"coordinates":[7.4049038887,49.5377998352],"type":"Point"}
}