{
  "type": "Feature",
  "properties": {
    "iso:country":"DE",
    "sg:address":"August-Bebel-Str. 4",
    "sg:city":"Bernburg",
    "sg:phone":"+49 3471/333351",
    "sg:postcode":"06406",
    "sg:province":"Sachsen-Anhalt",
    "wof:name":"R. Jochheim",
    "wof:placetype":"venue"
},
  "geometry": {"coordinates":[11.760594,51.785576],"type":"Point"}
}