{
  "type": "Feature",
  "properties": {
    "iso:country":"DE",
    "sg:address":"Bezirksstr. 36",
    "sg:city":"Blieskastel",
    "sg:phone":"+49 6842/6422",
    "sg:postcode":"66440",
    "sg:province":"Saarland",
    "wof:name":"Ch. Rubert",
    "wof:placetype":"venue"
},
  "geometry": {"coordinates":[7.1923098564,49.2439994812],"type":"Point"}
}