{
  "type": "Feature",
  "properties": {
    "iso:country":"DE",
    "sg:address":"Kamenzer Str. 41",
    "sg:city":"Dresden",
    "sg:phone":"+49 351/8010567",
    "sg:postcode":"01099",
    "sg:province":"Sachsen",
    "wof:name":"Christian Reichelt",
    "wof:placetype":"venue"
},
  "geometry": {"coordinates":[13.7584276199,51.0682563782],"type":"Point"}
}