{
  "type": "Feature",
  "properties": {
    "iso:country":"DE",
    "sg:address":"Lindberghstr 11",
    "sg:city":"Puchheim",
    "sg:phone":"+49 89/8006100",
    "sg:postcode":"82178",
    "sg:province":"Bayern",
    "wof:name":"Hess Medizintechnik Gmbh",
    "wof:placetype":"venue"
},
  "geometry": {"coordinates":[11.338442,48.162144],"type":"Point"}
}