{
  "type": "Feature",
  "properties": {
    "iso:country":"DE",
    "sg:address":"Kurf\u00fcrstenstr. 52",
    "sg:city":"Schwetzingen",
    "sg:phone":"+49 6202/18852",
    "sg:postcode":"68723",
    "sg:province":"Baden-W\u00fcrttemberg",
    "wof:name":"Rebstein Werbung Gesellschaft F\u00fcr",
    "wof:placetype":"venue"
},
  "geometry": {"coordinates":[8.5846586227,49.3860015869],"type":"Point"}
}