{
  "type": "Feature",
  "properties": {
    "iso:country":"DE",
    "sg:address":"Storkower Str. 20",
    "sg:city":"Prieros",
    "sg:phone":"+49 33768/50264",
    "sg:postcode":"15752",
    "wof:name":"A. Mittwede",
    "wof:placetype":"venue"
},
  "geometry": {"coordinates":[13.766495,52.22588],"type":"Point"}
}