{
  "type": "Feature",
  "properties": {
    "iso:country":"DE",
    "sg:address":"Landauer Str. 60",
    "sg:city":"Contwig",
    "sg:phone":"+49 6336/5675",
    "sg:postcode":"66497",
    "sg:province":"Rheinland-Pfalz",
    "wof:name":"Bonaventura",
    "wof:placetype":"venue"
},
  "geometry": {"coordinates":[7.4569039345,49.2411727905],"type":"Point"}
}