{
  "type": "Feature",
  "properties": {
    "iso:country":"DE",
    "sg:address":"Grotegaster Str. 21",
    "sg:city":"Westoverledingen",
    "sg:phone":"+49 4955/1634",
    "sg:postcode":"26810",
    "sg:province":"Niedersachsen",
    "wof:name":"Onno-wiard Feenders",
    "wof:placetype":"venue"
},
  "geometry": {"coordinates":[7.39859,53.173119],"type":"Point"}
}