{
  "type": "Feature",
  "properties": {
    "iso:country":"DE",
    "sg:address":"Hofer Str. 18",
    "sg:city":"Gera",
    "sg:phone":"+49 365/811328",
    "sg:postcode":"07548",
    "sg:province":"Th\u00fcringen",
    "wof:name":"Mcd Staps & Antonic Ohg",
    "wof:placetype":"venue"
},
  "geometry": {"coordinates":[12.0295372009,50.8498802185],"type":"Point"}
}