{
  "type": "Feature",
  "properties": {
    "iso:country":"DE",
    "sg:address":"Gro\u00dfe Str. 91a",
    "sg:city":"Vechta",
    "sg:phone":"+49 4441/81020",
    "sg:postcode":"49377",
    "sg:province":"Niedersachsen",
    "wof:name":"Gallier",
    "wof:placetype":"venue"
},
  "geometry": {"coordinates":[8.2875938416,52.7297973633],"type":"Point"}
}