{
  "type": "Feature",
  "properties": {
    "iso:country":"DE",
    "sg:address":"Aegidienstr. 20",
    "sg:city":"Heilbad Heiligenstadt",
    "sg:phone":"+49 3606/6770",
    "sg:postcode":"37308",
    "sg:province":"Th\u00fcringen",
    "wof:name":"Stadtarchiv",
    "wof:placetype":"venue"
},
  "geometry": {"coordinates":[10.137381,51.377075],"type":"Point"}
}