{
  "type": "Feature",
  "properties": {
    "iso:country":"DE",
    "sg:address":"Gerhart-Hauptmann-Str. 13",
    "sg:city":"Lauchringen",
    "sg:phone":"+49 7741/2595",
    "sg:postcode":"79787",
    "sg:province":"Baden-W\u00fcrttemberg",
    "wof:name":"E. Jehle",
    "wof:placetype":"venue"
},
  "geometry": {"coordinates":[8.303583,47.631668],"type":"Point"}
}