{
  "type": "Feature",
  "properties": {
    "iso:country":"DE",
    "sg:address":"Drescherh\u00e4user 5",
    "sg:city":"Dresden",
    "sg:phone":"+49 351/42320",
    "sg:postcode":"01159",
    "sg:province":"Sachsen",
    "wof:name":"System-haus Dresden Gmbh",
    "wof:placetype":"venue"
},
  "geometry": {"coordinates":[13.701252,51.049141],"type":"Point"}
}