{
  "type": "Feature",
  "properties": {
    "iso:country":"DE",
    "sg:address":"Falterstr. 5",
    "sg:city":"Kitzingen",
    "sg:phone":"+49 9321/24441",
    "sg:postcode":"97318",
    "sg:province":"Bayern",
    "wof:name":"Stephan Kaufold Rechtsanwalt",
    "wof:placetype":"venue"
},
  "geometry": {"coordinates":[10.160654068,49.7365951538],"type":"Point"}
}