{
  "type": "Feature",
  "properties": {
    "iso:country":"DE",
    "sg:address":"Wintersbacher Str.",
    "sg:city":"Dammbach",
    "sg:phone":"+49 4960/92329",
    "sg:postcode":"63874",
    "sg:province":"Bayern",
    "wof:name":"Raiffeisenbank Heimbuchenthal Eg",
    "wof:placetype":"venue"
},
  "geometry": {"coordinates":[9.30481,49.862339],"type":"Point"}
}