{
  "type": "Feature",
  "properties": {
    "iso:country":"DE",
    "sg:address":"Eckstr. 19",
    "sg:city":"Kaiserslautern",
    "sg:phone":"+49 631/56787",
    "sg:postcode":"67661",
    "sg:province":"Rheinland-Pfalz",
    "wof:name":"P. K\u00f6nig",
    "wof:placetype":"venue"
},
  "geometry": {"coordinates":[7.7288889885,49.4064483643],"type":"Point"}
}