{
  "type": "Feature",
  "properties": {
    "iso:country":"DE",
    "sg:address":"Eichendorffstr. 11",
    "sg:city":"Hasbergen",
    "sg:phone":"+49 5405/3874",
    "sg:postcode":"49205",
    "sg:province":"Niedersachsen",
    "wof:name":"Hartmut Kr\u00f6sche Ingenieur",
    "wof:placetype":"venue"
},
  "geometry": {"coordinates":[7.957092762,52.2454109192],"type":"Point"}
}