{
  "type": "Feature",
  "properties": {
    "iso:country":"DE",
    "sg:address":"Phillip-Reis-Str.2",
    "sg:city":"Alzenau",
    "sg:phone":"+49 6023",
    "sg:postcode":"63755",
    "sg:province":"Bayern",
    "wof:name":"Calpeda Pumpen Vertrieb Gmbh Deutschland",
    "wof:placetype":"venue"
},
  "geometry": {"coordinates":[9.0608606339,50.0913543701],"type":"Point"}
}