{
  "type": "Feature",
  "properties": {
    "iso:country":"DE",
    "sg:address":"Kronauer Weg 6",
    "sg:city":"Graben-Neudorf",
    "sg:phone":"+49 7255/71110",
    "sg:postcode":"76676",
    "sg:province":"Baden-W\u00fcrttemberg",
    "wof:name":"Dieter Baumann",
    "wof:placetype":"venue"
},
  "geometry": {"coordinates":[8.496645,49.166016],"type":"Point"}
}