{
  "type": "Feature",
  "properties": {
    "iso:country":"DE",
    "sg:address":"Schlo\u00dfstr. 10",
    "sg:city":"St. Wendel",
    "sg:phone":"+49 6851/85660",
    "sg:postcode":"66606",
    "sg:province":"Saarland",
    "wof:name":"Opticland Die Brille St. Wendel Gmbh",
    "wof:placetype":"venue"
},
  "geometry": {"coordinates":[7.1697030067,49.4677200317],"type":"Point"}
}