{
  "type": "Feature",
  "properties": {
    "iso:country":"DE",
    "sg:address":"Kasseler Str. 12",
    "sg:city":"Ludwigsau",
    "sg:phone":"+49 6621/75382",
    "sg:postcode":"36251",
    "sg:province":"Hessen",
    "wof:name":"Jakob Trinter",
    "wof:placetype":"venue"
},
  "geometry": {"coordinates":[9.746621,50.899925],"type":"Point"}
}