{
  "type": "Feature",
  "properties": {
    "iso:country":"DE",
    "sg:address":"Otto von Guericke Str. 21",
    "sg:city":"Schwerin",
    "sg:phone":"+49 385/2073071",
    "sg:postcode":"19063",
    "sg:province":"Mecklenburg-Vorpommern",
    "wof:name":"Der Billig-fuchs , Software Und Hardwarehandel",
    "wof:placetype":"venue"
},
  "geometry": {"coordinates":[11.471909,53.580902],"type":"Point"}
}