{
  "type": "Feature",
  "properties": {
    "iso:country":"DE",
    "sg:address":"Hirschbrunnenstr. 5",
    "sg:city":"Merzig",
    "sg:phone":"+49 6861/791800",
    "sg:postcode":"66663",
    "sg:province":"Saarland",
    "wof:name":"Elektro Stroh Gmbh",
    "wof:placetype":"venue"
},
  "geometry": {"coordinates":[6.607505,49.439739],"type":"Point"}
}