{
  "type": "Feature",
  "properties": {
    "iso:country":"DE",
    "sg:address":"Zeppelinallee 46",
    "sg:city":"Frankfurt",
    "sg:phone":"+49 69/779301",
    "sg:postcode":"60487",
    "sg:province":"Hessen",
    "wof:name":"Leonhard Meier",
    "wof:placetype":"venue"
},
  "geometry": {"coordinates":[8.65046978,50.1270103455],"type":"Point"}
}