{
  "type": "Feature",
  "properties": {
    "iso:country":"DE",
    "sg:address":"Poststr. 1",
    "sg:city":"Ruhmannsfelden",
    "sg:phone":"+49 9929/90000",
    "sg:postcode":"94239",
    "sg:province":"Bayern",
    "wof:name":"Nkd Vertriebs- Gesellschaft Mbh",
    "wof:placetype":"venue"
},
  "geometry": {"coordinates":[12.986661911,48.9844474792],"type":"Point"}
}