{
  "type": "Feature",
  "properties": {
    "iso:country":"DE",
    "sg:address":"Krickenbeckstr. 21",
    "sg:city":"Krefeld",
    "sg:phone":"+49 2151/710888",
    "sg:postcode":"47804",
    "sg:province":"Nordrhein-Westfalen",
    "wof:name":"U. Und F. Fuchs",
    "wof:placetype":"venue"
},
  "geometry": {"coordinates":[6.538858,51.324825],"type":"Point"}
}