{
  "type": "Feature",
  "properties": {
    "iso:country":"DE",
    "sg:address":"Strandstr. 2",
    "sg:city":"Ostseebad Rerik",
    "sg:phone":"+49 38296/78287",
    "sg:postcode":"18230",
    "sg:province":"Mecklenburg-Vorpommern",
    "wof:name":"Cafe Weinhol",
    "wof:placetype":"venue"
},
  "geometry": {"coordinates":[11.658118,54.135628],"type":"Point"}
}