{
  "type": "Feature",
  "properties": {
    "iso:country":"DE",
    "sg:address":"Vordere Fr\u00f6hnstr. 2",
    "sg:city":"Landstuhl",
    "sg:phone":"+49 6371/2112",
    "sg:postcode":"66849",
    "sg:province":"Rheinland-Pfalz",
    "wof:name":"Lions-club Thomas Ernst",
    "wof:placetype":"venue"
},
  "geometry": {"coordinates":[7.5669288635,49.4112854004],"type":"Point"}
}