{
  "type": "Feature",
  "properties": {
    "iso:country":"DE",
    "sg:address":"Silvesterstr 3::",
    "sg:city":"Raesfeld",
    "sg:phone":"+49 2865/95750",
    "sg:postcode":"46348",
    "sg:province":"Nordrhein-Westfalen",
    "wof:name":"Volksbank Erle Eg",
    "wof:placetype":"venue"
},
  "geometry": {"coordinates":[6.865493,51.746506],"type":"Point"}
}