{
  "type": "Feature",
  "properties": {
    "iso:country":"DE",
    "sg:address":"Lindenallee 15",
    "sg:city":"Oebisfelde",
    "sg:phone":"+49 39002/42960",
    "sg:postcode":"39646",
    "sg:province":"Sachsen-Anhalt",
    "wof:name":"Horst Schrader",
    "wof:placetype":"venue"
},
  "geometry": {"coordinates":[10.984395,52.433395],"type":"Point"}
}