{
  "type": "Feature",
  "properties": {
    "iso:country":"DE",
    "sg:address":"Alois-Wenzel-Str. 18",
    "sg:city":"Haibach",
    "sg:phone":"+49 6021/69715",
    "sg:postcode":"63808",
    "sg:province":"Bayern",
    "wof:name":"A. Und M. Bergmann",
    "wof:placetype":"venue"
},
  "geometry": {"coordinates":[9.198548,49.965309],"type":"Point"}
}