{
  "type": "Feature",
  "properties": {
    "iso:country":"DE",
    "sg:address":"Alte Reutstr. 124",
    "sg:city":"F\u00fcrth",
    "sg:phone":"+49 911/7906641",
    "sg:postcode":"90765",
    "sg:province":"Bayern",
    "wof:name":"Helmut Boelian",
    "wof:placetype":"venue"
},
  "geometry": {"coordinates":[11.006108284,49.4877166748],"type":"Point"}
}