{
  "type": "Feature",
  "properties": {
    "iso:country":"DE",
    "sg:address":"Filchnerstr. 56",
    "sg:city":"Potsdam",
    "sg:postcode":"14482",
    "sg:province":"Brandenburg",
    "wof:name":"Gustke Tiefbau Gmbh",
    "wof:placetype":"venue"
},
  "geometry": {"coordinates":[13.1048002243,52.4013519287],"type":"Point"}
}