{
  "type": "Feature",
  "properties": {
    "iso:country":"DE",
    "sg:address":"Chemnitzer Str. 5",
    "sg:city":"Michelstadt",
    "sg:postcode":"64720",
    "sg:province":"Hessen",
    "wof:name":"J. J. Schlayer Gmbh",
    "wof:placetype":"venue"
},
  "geometry": {"coordinates":[9.0107030869,49.6778030396],"type":"Point"}
}