{
  "type": "Feature",
  "properties": {
    "iso:country":"DE",
    "sg:address":"Herrfurthstr 2",
    "sg:city":"Merseburg",
    "sg:phone":"+49 3461/73190",
    "sg:postcode":"06217",
    "sg:province":"Sachsen-Anhalt",
    "wof:name":"Kontak Gmbh",
    "wof:placetype":"venue"
},
  "geometry": {"coordinates":[11.976425,51.374447],"type":"Point"}
}