{
  "type": "Feature",
  "properties": {
    "iso:country":"DE",
    "sg:address":"Jahnstr. 5",
    "sg:city":"Bad Br\u00fcckenau",
    "sg:postcode":"97769",
    "sg:province":"Bayern",
    "wof:name":"Skyline Film- Und Fernsehgesellschaft Mbh",
    "wof:placetype":"venue"
},
  "geometry": {"coordinates":[9.7918968201,50.3076553345],"type":"Point"}
}