{
  "type": "Feature",
  "properties": {
    "iso:country":"DE",
    "sg:address":"Lessingstr. 1",
    "sg:city":"B\u00f6blingen",
    "sg:phone":"+49 7031/46100",
    "sg:postcode":"71032",
    "sg:province":"Baden-W\u00fcrttemberg",
    "wof:name":"Gall Reisen Gmbh",
    "wof:placetype":"venue"
},
  "geometry": {"coordinates":[9.0239782333,48.6860923767],"type":"Point"}
}