{
  "type": "Feature",
  "properties": {
    "iso:country":"DE",
    "sg:address":"Heinrichsallee 35",
    "sg:city":"Aachen",
    "sg:phone":"+49 241/403100",
    "sg:postcode":"52062",
    "sg:province":"Nordrhein-Westfalen",
    "wof:name":"Schiewald Immobilienmakler",
    "wof:placetype":"venue"
},
  "geometry": {"coordinates":[6.0945110321,50.7769470215],"type":"Point"}
}