{
  "type": "Feature",
  "properties": {
    "iso:country":"DE",
    "sg:address":"Boosstr. 3",
    "sg:city":"Worms",
    "sg:phone":"+49 6241/591093",
    "sg:postcode":"67547",
    "sg:province":"Rheinland-Pfalz",
    "wof:name":"Sozialberatung F. Werdende M\u00fctter-diak. Werk",
    "wof:placetype":"venue"
},
  "geometry": {"coordinates":[8.351116,49.618568],"type":"Point"}
}