{
  "type": "Feature",
  "properties": {
    "iso:country":"DE",
    "sg:address":"Kleine Ulrichstr. 23",
    "sg:city":"Halle",
    "sg:phone":"+49 345/25080",
    "sg:postcode":"06108",
    "sg:province":"Sachsen-Anhalt",
    "wof:name":"Gebr. Wegewitz-bau- Gmbh",
    "wof:placetype":"venue"
},
  "geometry": {"coordinates":[11.966432,51.486366],"type":"Point"}
}