{
  "type": "Feature",
  "properties": {
    "iso:country":"DE",
    "sg:address":"Salierstr. 27",
    "sg:city":"Pforzheim",
    "sg:phone":"+49 7231/351596",
    "sg:postcode":"75177",
    "sg:province":"Baden-W\u00fcrttemberg",
    "wof:name":"T. Leonhardt",
    "wof:placetype":"venue"
},
  "geometry": {"coordinates":[8.700624,48.896191],"type":"Point"}
}