{
  "type": "Feature",
  "properties": {
    "iso:country":"DE",
    "sg:address":"Kaiserpassage 2",
    "sg:city":"Karlsruhe",
    "sg:phone":"+49 721/23971",
    "sg:postcode":"76133",
    "sg:province":"Baden-W\u00fcrttemberg",
    "wof:name":"Tui Reise Center",
    "wof:placetype":"venue"
},
  "geometry": {"coordinates":[8.3966732025,49.0101051331],"type":"Point"}
}