{
  "type": "Feature",
  "properties": {
    "iso:country":"DE",
    "sg:address":"Wasserschwenden 8",
    "sg:city":"Altusried",
    "sg:phone":"+49 8374/25581",
    "sg:postcode":"87452",
    "sg:province":"Bayern",
    "wof:name":"Hiedl Gbr",
    "wof:placetype":"venue"
},
  "geometry": {"coordinates":[10.213572,47.80629],"type":"Point"}
}