{
  "type": "Feature",
  "properties": {
    "iso:country":"DE",
    "sg:address":"H\u00f6nower Str. 83",
    "sg:city":"Berlin",
    "sg:phone":"+49 30/5638575",
    "sg:postcode":"12623",
    "sg:province":"Berlin",
    "wof:name":"R\u00f6wer",
    "wof:placetype":"venue"
},
  "geometry": {"coordinates":[13.611995,52.511951],"type":"Point"}
}