{
  "type": "Feature",
  "properties": {
    "iso:country":"DE",
    "sg:address":"Rosengarten 10",
    "sg:city":"Wedel",
    "sg:phone":"+49 4103/121160",
    "sg:postcode":"22880",
    "sg:province":"Schleswig-Holstein",
    "wof:name":"Lif Gmbh",
    "wof:placetype":"venue"
},
  "geometry": {"coordinates":[10.623107,52.275684],"type":"Point"}
}