{
  "type": "Feature",
  "properties": {
    "iso:country":"DE",
    "sg:address":"Freiberger Str. 4",
    "sg:city":"Pretzschendorf",
    "sg:phone":"+49 35058/41236",
    "sg:postcode":"01774",
    "sg:province":"Sachsen",
    "wof:name":"Volker Sauer",
    "wof:placetype":"venue"
},
  "geometry": {"coordinates":[13.52706,50.873344],"type":"Point"}
}