{
  "type": "Feature",
  "properties": {
    "iso:country":"DE",
    "sg:address":"Grabenstr. 34",
    "sg:city":"Gau-Algesheim",
    "sg:phone":"+49 6725/3220",
    "sg:postcode":"55435",
    "sg:province":"Rheinland-Pfalz",
    "wof:name":"Albert Becker",
    "wof:placetype":"venue"
},
  "geometry": {"coordinates":[8.0136299133,49.9565505981],"type":"Point"}
}