{
  "type": "Feature",
  "properties": {
    "iso:country":"DE",
    "sg:address":"Ortsstra\u00dfe",
    "sg:city":"Wittchenstein",
    "sg:phone":"+49 36482/30199",
    "sg:postcode":"07819",
    "sg:province":"Th\u00fcringen",
    "wof:name":"Ingenieurb\u00fcro Bergner",
    "wof:placetype":"venue"
},
  "geometry": {"coordinates":[11.8404998779,50.7386016846],"type":"Point"}
}