{
  "type": "Feature",
  "properties": {
    "iso:country":"DE",
    "sg:address":"Heider Str. 16",
    "sg:city":"B\u00fcsum",
    "sg:phone":"+49 4834/2317",
    "sg:postcode":"25761",
    "sg:province":"Schleswig-Holstein",
    "wof:name":"Aral-tankstelle",
    "wof:placetype":"venue"
},
  "geometry": {"coordinates":[8.8678941727,54.135055542],"type":"Point"}
}