{
  "type": "Feature",
  "properties": {
    "iso:country":"DE",
    "sg:address":"Sch\u00f6naustr. 34",
    "sg:city":"Wiesbaden",
    "sg:phone":"+49 611/260503",
    "sg:postcode":"65201",
    "sg:province":"Hessen",
    "wof:name":"Kurt Etz",
    "wof:placetype":"venue"
},
  "geometry": {"coordinates":[8.196976,50.052197],"type":"Point"}
}