{
  "type": "Feature",
  "properties": {
    "iso:country":"DE",
    "sg:address":"Ruhe-Christi-Str. 24",
    "sg:city":"Rottweil",
    "sg:phone":"+49 741/23039",
    "sg:postcode":"78628",
    "sg:province":"Baden-W\u00fcrttemberg",
    "wof:name":"Eberle Und Von Herbert Ergotherapeutische Praxis",
    "wof:placetype":"venue"
},
  "geometry": {"coordinates":[8.632136,48.16328],"type":"Point"}
}