{
  "type": "Feature",
  "properties": {
    "iso:country":"DE",
    "sg:address":"Annoplatz 1",
    "sg:city":"Hennef",
    "sg:phone":"+49 2242/3412",
    "sg:postcode":"53773",
    "sg:province":"Nordrhein-Westfalen",
    "wof:name":"Restaurant B\u00fcrgerhof Happerschoss",
    "wof:placetype":"venue"
},
  "geometry": {"coordinates":[7.3021950722,50.7981834412],"type":"Point"}
}