{
  "type": "Feature",
  "properties": {
    "iso:country":"DE",
    "sg:address":"Brauhausstieg 35",
    "sg:city":"Hamburg",
    "sg:phone":"+49 40/6521344",
    "sg:postcode":"22041",
    "sg:province":"Hamburg",
    "wof:name":"Enterprise Dr. Om Prakash Garg",
    "wof:placetype":"venue"
},
  "geometry": {"coordinates":[10.0606822968,53.5720062256],"type":"Point"}
}