{
  "type": "Feature",
  "properties": {
    "iso:country":"DE",
    "sg:address":"Alt-Biesdorf 64",
    "sg:city":"Berlin",
    "sg:phone":"+49 30/5143097",
    "sg:postcode":"12683",
    "sg:province":"Berlin",
    "wof:name":"Klebind B\u00fcroklebe- Und -bindesysteme",
    "wof:placetype":"venue"
},
  "geometry": {"coordinates":[13.552423,52.509483],"type":"Point"}
}