{
  "type": "Feature",
  "properties": {
    "iso:country":"DE",
    "sg:address":"Schandauer Str. 20",
    "sg:city":"Sebnitz",
    "sg:phone":"+49 35971/57787",
    "sg:postcode":"01855",
    "sg:province":"Sachsen",
    "wof:name":"I. Weser",
    "wof:placetype":"venue"
},
  "geometry": {"coordinates":[14.27039814,50.9704170227],"type":"Point"}
}