{
  "type": "Feature",
  "properties": {
    "iso:country":"DE",
    "sg:address":"Bauhausplatz 5",
    "sg:city":"Dessau",
    "sg:phone":"+49 340/612017",
    "sg:postcode":"06846",
    "sg:province":"Sachsen-Anhalt",
    "wof:name":"Immo-invest Petra Ratschke",
    "wof:placetype":"venue"
},
  "geometry": {"coordinates":[12.2255754471,51.838722229],"type":"Point"}
}