{
  "type": "Feature",
  "properties": {
    "iso:country":"DE",
    "sg:address":"Grantschener Str. 10",
    "sg:city":"Weinsberg",
    "sg:phone":"+49 7134/20535",
    "sg:postcode":"74189",
    "sg:province":"Baden-W\u00fcrttemberg",
    "wof:name":"Pizzeria Positano",
    "wof:placetype":"venue"
},
  "geometry": {"coordinates":[9.2942857742,49.1515579224],"type":"Point"}
}