{
  "type": "Feature",
  "properties": {
    "iso:country":"DE",
    "sg:address":"Waldbreitbacher Str. 11",
    "sg:city":"Breitscheid",
    "sg:phone":"+49 2638/5080",
    "sg:postcode":"53547",
    "sg:province":"Rheinland-Pfalz",
    "wof:name":"Josef Br\u00fccken",
    "wof:placetype":"venue"
},
  "geometry": {"coordinates":[7.4463992119,50.5570983887],"type":"Point"}
}