{
  "type": "Feature",
  "properties": {
    "iso:country":"DE",
    "sg:address":"Hafenstr. 29",
    "sg:city":"M\u00fcnster",
    "sg:phone":"+49 251/490120",
    "sg:postcode":"48153",
    "sg:province":"Nordrhein-Westfalen",
    "wof:name":"Dkv Deutsche Krankenversicherung Ag",
    "wof:placetype":"venue"
},
  "geometry": {"coordinates":[7.6301288605,51.9544944763],"type":"Point"}
}