{
  "type": "Feature",
  "properties": {
    "iso:country":"DE",
    "sg:address":"Am Sportplatz 2",
    "sg:city":"Neustadt",
    "sg:phone":"+49 5034/555",
    "sg:postcode":"31535",
    "sg:province":"Niedersachsen",
    "wof:name":"Hirth",
    "wof:placetype":"venue"
},
  "geometry": {"coordinates":[9.1113023758,50.8742141724],"type":"Point"}
}