{
  "type": "Feature",
  "properties": {
    "iso:country":"DE",
    "sg:address":"Hauptstr. 65",
    "sg:city":"Wickede",
    "sg:phone":"+49 2377/2322",
    "sg:postcode":"58739",
    "sg:province":"Nordrhein-Westfalen",
    "wof:name":"Bernhard Kree Kohlenhandlung Und Transportunternehmen",
    "wof:placetype":"venue"
},
  "geometry": {"coordinates":[7.8685097694,51.4925003052],"type":"Point"}
}