{
  "type": "Feature",
  "properties": {
    "iso:country":"DE",
    "sg:address":"Schellenbergstr. 4b",
    "sg:city":"Kempten",
    "sg:phone":"+49 831/511252",
    "sg:postcode":"87435",
    "sg:province":"Bayern",
    "wof:name":"Peter Schmiedt",
    "wof:placetype":"venue"
},
  "geometry": {"coordinates":[10.309589386,47.7161865234],"type":"Point"}
}