{
  "type": "Feature",
  "properties": {
    "iso:country":"DE",
    "sg:address":"Marktstr. 4",
    "sg:city":"Ramstein-Miesenbach",
    "sg:phone":"+49 6371/57988",
    "sg:postcode":"66877",
    "sg:province":"Rheinland-Pfalz",
    "wof:name":"Frank Hussung Immobilienmakler",
    "wof:placetype":"venue"
},
  "geometry": {"coordinates":[7.555961132,49.4453849792],"type":"Point"}
}