{
  "type": "Feature",
  "properties": {
    "iso:country":"DE",
    "sg:address":"Am Bahnhof 10",
    "sg:city":"Suhl",
    "sg:phone":"+49 3681/303528",
    "sg:postcode":"98529",
    "sg:province":"Th\u00fcringen",
    "wof:name":"M. Meusert Immobilienmakler",
    "wof:placetype":"venue"
},
  "geometry": {"coordinates":[10.6833810806,50.6063346863],"type":"Point"}
}