{
  "type": "Feature",
  "properties": {
    "iso:country":"DE",
    "sg:address":"Martin-Luther-King-Str. 14",
    "sg:city":"G\u00f6ppingen",
    "sg:phone":"+49 7161/683823",
    "sg:postcode":"73037",
    "sg:province":"Baden-W\u00fcrttemberg",
    "wof:name":"Sozialberatung B\u00fcrgerh\u00f6lzle",
    "wof:placetype":"venue"
},
  "geometry": {"coordinates":[9.682927,48.714249],"type":"Point"}
}