{
  "type": "Feature",
  "properties": {
    "iso:country":"DE",
    "sg:address":"Grevenbr\u00fccker Str. 7",
    "sg:city":"Lennestadt",
    "sg:phone":"+49 2721/983768",
    "sg:postcode":"57368",
    "sg:province":"Nordrhein-Westfalen",
    "wof:name":"Albrecht Und Berthold Knoche",
    "wof:placetype":"venue"
},
  "geometry": {"coordinates":[8.0297088623,51.1304512024],"type":"Point"}
}