{
  "type": "Feature",
  "properties": {
    "iso:country":"DE",
    "sg:address":"Haid-und-Neu-Str. 6",
    "sg:city":"Karlsruhe",
    "sg:phone":"+49 721/698969",
    "sg:postcode":"76131",
    "sg:province":"Baden-W\u00fcrttemberg",
    "wof:name":"Industrieb\u00fcro Gesenberg Gmbh",
    "wof:placetype":"venue"
},
  "geometry": {"coordinates":[8.4248399734,49.0117759705],"type":"Point"}
}