{
  "type": "Feature",
  "properties": {
    "iso:country":"DE",
    "sg:address":"Stinteck",
    "sg:city":"Westerdeichstrich",
    "sg:phone":"+49 4834/2147",
    "sg:postcode":"25761",
    "sg:province":"Schleswig-Holstein",
    "wof:name":"Wiesengrund",
    "wof:placetype":"venue"
},
  "geometry": {"coordinates":[8.8311834335,54.1576156616],"type":"Point"}
}