{
  "type": "Feature",
  "properties": {
    "iso:country":"DE",
    "sg:address":"Heimbergstr. 1",
    "sg:city":"Langelsheim",
    "sg:postcode":"38685",
    "sg:province":"Niedersachsen",
    "wof:name":"K-catering Gmbh",
    "wof:placetype":"venue"
},
  "geometry": {"coordinates":[10.324068,51.914303],"type":"Point"}
}