{
  "type": "Feature",
  "properties": {
    "iso:country":"DE",
    "sg:address":"Am Kirchplatz 1",
    "sg:city":"Stephanskirchen",
    "sg:phone":"+49 8031/71126",
    "sg:postcode":"83071",
    "sg:province":"Bayern",
    "wof:name":"Katholisches Pfarramt St. Georg",
    "wof:placetype":"venue"
},
  "geometry": {"coordinates":[12.1472482681,47.8572807312],"type":"Point"}
}