{
  "type": "Feature",
  "properties": {
    "iso:country":"DE",
    "sg:address":"F\u00fcstingweg 9",
    "sg:city":"Ratingen",
    "sg:phone":"+49 2102/50110",
    "sg:postcode":"40882",
    "sg:province":"Nordrhein-Westfalen",
    "wof:name":"Raiffeisen-markt",
    "wof:placetype":"venue"
},
  "geometry": {"coordinates":[6.933552,51.299236],"type":"Point"}
}