{
  "type": "Feature",
  "properties": {
    "iso:country":"DE",
    "sg:address":"Beethovenstr. 279",
    "sg:city":"Solingen",
    "sg:phone":"+49 212/223310",
    "sg:postcode":"42655",
    "sg:province":"Nordrhein-Westfalen",
    "wof:name":"Engling Telekommunikation Gmbh",
    "wof:placetype":"venue"
},
  "geometry": {"coordinates":[7.0437412262,51.1726760864],"type":"Point"}
}