{
  "type": "Feature",
  "properties": {
    "iso:country":"DE",
    "sg:address":"Berliner Str. 36",
    "sg:city":"Berlin",
    "sg:postcode":"10715",
    "sg:province":"Berlin",
    "wof:name":"Treuwind Gmbh",
    "wof:placetype":"venue"
},
  "geometry": {"coordinates":[13.32204,52.486759],"type":"Point"}
}