{
  "type": "Feature",
  "properties": {
    "iso:country":"DE",
    "sg:address":"K\u00f6rnerstr. 80",
    "sg:city":"K\u00f6ln",
    "sg:phone":"+49 172 2417600",
    "sg:postcode":"50823",
    "sg:province":"Nordrhein-Westfalen",
    "wof:name":"Schreibb\u00fcro B. Kaufeld",
    "wof:placetype":"venue"
},
  "geometry": {"coordinates":[6.924221,50.950356],"type":"Point"}
}