{
  "type": "Feature",
  "properties": {
    "iso:country":"DE",
    "sg:address":"Ulmergasse 6",
    "sg:city":"Ulm",
    "sg:phone":"+49 731/6020440",
    "sg:postcode":"89073",
    "sg:province":"Baden-W\u00fcrttemberg",
    "wof:name":"City - In",
    "wof:placetype":"venue"
},
  "geometry": {"coordinates":[9.988513,48.39904],"type":"Point"}
}