{
  "type": "Feature",
  "properties": {
    "iso:country":"DE",
    "sg:address":"Elstorf",
    "sg:city":"Neu Wulmstorf",
    "sg:phone":"+49 4168/516",
    "sg:postcode":"21629",
    "sg:province":"Niedersachsen",
    "wof:name":"R. Klindworth",
    "wof:placetype":"venue"
},
  "geometry": {"coordinates":[9.80548,53.440643],"type":"Point"}
}