{
  "type": "Feature",
  "properties": {
    "iso:country":"DE",
    "sg:address":"Achterstr. 37",
    "sg:city":"Wittingen",
    "sg:phone":"+49 5831/1238",
    "sg:postcode":"29378",
    "sg:province":"Niedersachsen",
    "wof:name":"Schramm",
    "wof:placetype":"venue"
},
  "geometry": {"coordinates":[10.7411212921,52.7271347046],"type":"Point"}
}