{
  "type": "Feature",
  "properties": {
    "iso:country":"DE",
    "sg:address":"Langeler Weg 26",
    "sg:city":"K\u00f6ln",
    "sg:phone":"+49 221/784772",
    "sg:postcode":"50769",
    "sg:province":"Nordrhein-Westfalen",
    "wof:name":"Peter Wolff",
    "wof:placetype":"venue"
},
  "geometry": {"coordinates":[6.872049,51.062843],"type":"Point"}
}