{
  "type": "Feature",
  "properties": {
    "iso:country":"DE",
    "sg:address":"Trierer Str. 2",
    "sg:city":"Speicher",
    "sg:phone":"+49 6562/2424",
    "sg:postcode":"54662",
    "sg:province":"Rheinland-Pfalz",
    "wof:name":"Josef Berrens",
    "wof:placetype":"venue"
},
  "geometry": {"coordinates":[6.639525,49.934883],"type":"Point"}
}