{
  "type": "Feature",
  "properties": {
    "iso:country":"DE",
    "sg:address":"Georg-Reism\u00fcller-Str. 1",
    "sg:city":"M\u00fcnchen",
    "sg:postcode":"80999",
    "sg:province":"Bayern",
    "wof:name":"H & H Handelsgesellschaft Mbh",
    "wof:placetype":"venue"
},
  "geometry": {"coordinates":[11.4667596817,48.190788269],"type":"Point"}
}