{
  "type": "Feature",
  "properties": {
    "iso:country":"DE",
    "sg:address":"Am Bahnhof 6",
    "sg:city":"Lebach",
    "sg:phone":"+49 6881/53688",
    "sg:postcode":"66822",
    "sg:province":"Saarland",
    "wof:name":"Foto Fercho Gmbh",
    "wof:placetype":"venue"
},
  "geometry": {"coordinates":[6.908853054,49.4085731506],"type":"Point"}
}