{
  "type": "Feature",
  "properties": {
    "iso:country":"DE",
    "sg:address":"W\u00f6stefeld 10",
    "sg:city":"Osnabr\u00fcck",
    "sg:phone":"+49 541/128334",
    "sg:postcode":"49090",
    "sg:province":"Niedersachsen",
    "wof:name":"Sami Tabbara",
    "wof:placetype":"venue"
},
  "geometry": {"coordinates":[7.9928269386,52.3206558228],"type":"Point"}
}