{
  "type": "Feature",
  "properties": {
    "iso:country":"DE",
    "sg:address":"Landeskronstr. 26",
    "sg:city":"G\u00f6rlitz",
    "sg:phone":"+49 3581/314149",
    "sg:postcode":"02826",
    "sg:province":"Sachsen",
    "wof:name":"Drehscheibe",
    "wof:placetype":"venue"
},
  "geometry": {"coordinates":[14.9712619781,51.1513938904],"type":"Point"}
}