{
  "type": "Feature",
  "properties": {
    "iso:country":"DE",
    "sg:address":"Bettinghausen 45",
    "sg:city":"Engeln",
    "sg:phone":"+49 4247/517",
    "sg:postcode":"27305",
    "sg:province":"Niedersachsen",
    "wof:name":"Friedrich Labbus",
    "wof:placetype":"venue"
},
  "geometry": {"coordinates":[8.942414,52.777161],"type":"Point"}
}