{
  "type": "Feature",
  "properties": {
    "iso:country":"DE",
    "sg:address":"Eichenweg 35",
    "sg:city":"Stahnsdorf",
    "sg:phone":"+49 3329/62084",
    "sg:postcode":"14532",
    "sg:province":"Brandenburg",
    "wof:name":"J. Schenderlein",
    "wof:placetype":"venue"
},
  "geometry": {"coordinates":[13.2024745941,52.3915405273],"type":"Point"}
}