{
  "type": "Feature",
  "properties": {
    "iso:country":"DE",
    "sg:address":"Falkentorstr. 17",
    "sg:city":"Hildrizhausen",
    "sg:phone":"+49 4970/344232",
    "sg:postcode":"71157",
    "sg:province":"Baden-W\u00fcrttemberg",
    "wof:name":"Wilhelm Braun & S\u00d6hne Gmbh & Co.",
    "wof:placetype":"venue"
},
  "geometry": {"coordinates":[8.964302063,48.6250495911],"type":"Point"}
}