{
  "type": "Feature",
  "properties": {
    "iso:country":"DE",
    "sg:address":"Im Gewerbepark 57",
    "sg:city":"Regensburg",
    "sg:postcode":"93059",
    "sg:province":"Bayern",
    "wof:name":"Retrain Ag",
    "wof:placetype":"venue"
},
  "geometry": {"coordinates":[12.131574,49.031658],"type":"Point"}
}