{
  "type": "Feature",
  "properties": {
    "iso:country":"DE",
    "sg:address":"Max-Beckmann-Str. 3",
    "sg:city":"Frankenthal",
    "sg:phone":"+49 6233/42035",
    "sg:postcode":"67227",
    "sg:province":"Rheinland-Pfalz",
    "wof:name":"Heinrich Plomer Architekt",
    "wof:placetype":"venue"
},
  "geometry": {"coordinates":[8.365487,49.52496],"type":"Point"}
}