{
  "type": "Feature",
  "properties": {
    "iso:country":"DE",
    "sg:address":"Wiesenstr. 51",
    "sg:city":"D\u00fcsseldorf",
    "sg:phone":"+49 211/5630900",
    "sg:postcode":"40549",
    "sg:province":"Nordrhein-Westfalen",
    "wof:name":"Pvm Papierverarbeitungs- Maschinen Gmbh",
    "wof:placetype":"venue"
},
  "geometry": {"coordinates":[6.708236,51.227455],"type":"Point"}
}