{
  "type": "Feature",
  "properties": {
    "iso:country":"DE",
    "sg:address":"Langbaurghstrasse 13",
    "sg:city":"Troisdorf",
    "sg:phone":"+49 4922/4191960",
    "sg:postcode":"53842",
    "sg:province":"Nordrhein-Westfalen",
    "wof:name":"Showconcept Veranstaltungstechnik",
    "wof:placetype":"venue"
},
  "geometry": {"coordinates":[7.108628,50.821617],"type":"Point"}
}