{
  "type": "Feature",
  "properties": {
    "iso:country":"DE",
    "sg:address":"Tiefendorfer Str. 87",
    "sg:city":"Hagen",
    "sg:phone":"+49 2334/51214",
    "sg:postcode":"58093",
    "sg:province":"Nordrhein-Westfalen",
    "wof:name":"Bechem Entwicklungs- Und Vertriebs Gmbh",
    "wof:placetype":"venue"
},
  "geometry": {"coordinates":[7.561093,51.393124],"type":"Point"}
}