{
  "type": "Feature",
  "properties": {
    "iso:country":"DE",
    "sg:address":"Ewaldstr. 29",
    "sg:city":"Bocholt",
    "sg:phone":"+49 2871/217990",
    "sg:postcode":"46395",
    "sg:province":"Nordrhein-Westfalen",
    "wof:name":"Menstell-stahl Gmbh",
    "wof:placetype":"venue"
},
  "geometry": {"coordinates":[6.619647,51.831211],"type":"Point"}
}