{
  "type": "Feature",
  "properties": {
    "iso:country":"DE",
    "sg:address":"Hauptstr. 6",
    "sg:city":"Johannesberg",
    "sg:phone":"+49 6021/421769",
    "sg:postcode":"63867",
    "sg:province":"Bayern",
    "wof:name":"Kath. \u00d6ffentliche Bibliothek Kath. Pfarramt",
    "wof:placetype":"venue"
},
  "geometry": {"coordinates":[9.140941,50.029747],"type":"Point"}
}