{
  "type": "Feature",
  "properties": {
    "iso:country":"DE",
    "sg:address":"Luftbadstr. 2",
    "sg:city":"Sellin",
    "sg:phone":"+49 38303/1790",
    "sg:postcode":"18586",
    "sg:province":"Mecklenburg-Vorpommern",
    "wof:name":"Pension E. M\u00fchlbach",
    "wof:placetype":"venue"
},
  "geometry": {"coordinates":[13.6950912476,54.3777809143],"type":"Point"}
}