{
  "type": "Feature",
  "properties": {
    "iso:country":"DE",
    "sg:address":"Wolfsgarten 21",
    "sg:city":"Bovenden",
    "sg:phone":"+49 5594/1007",
    "sg:postcode":"37120",
    "sg:province":"Niedersachsen",
    "wof:name":"Gerhard Oppermann Steuerberater",
    "wof:placetype":"venue"
},
  "geometry": {"coordinates":[9.9616470337,51.595905304],"type":"Point"}
}