{
  "type": "Feature",
  "properties": {
    "iso:country":"DE",
    "sg:address":"Paul-Pieper-Str. 15",
    "sg:city":"D\u00fcsseldorf",
    "sg:phone":"+49 211/287728",
    "sg:postcode":"40625",
    "sg:province":"Nordrhein-Westfalen",
    "wof:name":"Gerhard Heinz Maurer",
    "wof:placetype":"venue"
},
  "geometry": {"coordinates":[6.8484940529,51.2417831421],"type":"Point"}
}