{
  "type": "Feature",
  "properties": {
    "iso:country":"DE",
    "sg:address":"H\u00fcgelstr. 14",
    "sg:city":"Puchheim",
    "sg:phone":"+49 89/808408",
    "sg:postcode":"82178",
    "sg:province":"Bayern",
    "wof:name":"Fischer & Weber Gmbh Elektroinstallation",
    "wof:placetype":"venue"
},
  "geometry": {"coordinates":[11.342178,48.149693],"type":"Point"}
}