{
  "type": "Feature",
  "properties": {
    "iso:country":"DE",
    "sg:address":"Borsigstr. 5",
    "sg:city":"Hildesheim",
    "sg:phone":"+49 5121/511211",
    "sg:postcode":"31135",
    "sg:province":"Niedersachsen",
    "wof:name":"Der Dienstleistungspartner Streit Gmbh",
    "wof:placetype":"venue"
},
  "geometry": {"coordinates":[9.977016,52.168159],"type":"Point"}
}