{
  "type": "Feature",
  "properties": {
    "iso:country":"DE",
    "sg:address":"Flensburger Str. 46-48",
    "sg:city":"Dresden",
    "sg:phone":"+49 351/4539999",
    "sg:postcode":"01157",
    "sg:province":"Sachsen",
    "wof:name":"B\u00fcro Und Computer Schwarz Inh. Ute Schwarz",
    "wof:placetype":"venue"
},
  "geometry": {"coordinates":[13.665679,51.076992],"type":"Point"}
}