{
  "type": "Feature",
  "properties": {
    "iso:country":"DE",
    "sg:address":"Burgstr. 6",
    "sg:city":"Nordhorn",
    "sg:phone":"+49 5921/16338",
    "sg:postcode":"48529",
    "sg:province":"Niedersachsen",
    "wof:name":"Gastst\u00e4tte Domspatz",
    "wof:placetype":"venue"
},
  "geometry": {"coordinates":[7.0694489479,52.4362754822],"type":"Point"}
}