{
  "type": "Feature",
  "properties": {
    "iso:country":"DE",
    "sg:address":"August-Wessing-Damm 22",
    "sg:city":"Warendorf",
    "sg:phone":"+49 2581/93640",
    "sg:postcode":"48231",
    "sg:province":"Nordrhein-Westfalen",
    "wof:name":"K\u00f6ckemann Gmbh",
    "wof:placetype":"venue"
},
  "geometry": {"coordinates":[7.9822001457,51.9523506165],"type":"Point"}
}