{
  "type": "Feature",
  "properties": {
    "iso:country":"DE",
    "sg:address":"An der Drehbank 13",
    "sg:city":"Gevelsberg",
    "sg:phone":"+49 2332/14353",
    "sg:postcode":"58285",
    "sg:province":"Nordrhein-Westfalen",
    "wof:name":"A. W. Verwaltungs- Und Vertriebs Gmbh & Co. Kg",
    "wof:placetype":"venue"
},
  "geometry": {"coordinates":[7.351692,51.326759],"type":"Point"}
}