{
  "type": "Feature",
  "properties": {
    "iso:country":"DE",
    "sg:address":"Stricker Str. 5",
    "sg:city":"Bad Arolsen",
    "sg:phone":"+49 2993/350",
    "sg:postcode":"34454",
    "sg:province":"Hessen",
    "wof:name":"Christian Br\u00fccher",
    "wof:placetype":"venue"
},
  "geometry": {"coordinates":[8.9424877167,51.4347686768],"type":"Point"}
}