{
  "type": "Feature",
  "properties": {
    "iso:country":"DE",
    "sg:address":"Kelheimer Str. 11 a",
    "sg:city":"Berlin",
    "sg:phone":"+49 30/2114036",
    "sg:postcode":"10777",
    "sg:province":"Berlin",
    "wof:name":"Helga Oehler",
    "wof:placetype":"venue"
},
  "geometry": {"coordinates":[13.3373727798,52.4980392456],"type":"Point"}
}