{
  "type": "Feature",
  "properties": {
    "iso:country":"DE",
    "sg:address":"Bergweg 6a",
    "sg:city":"Sierksdorf",
    "sg:phone":"+49 4563/8231",
    "sg:postcode":"23730",
    "sg:province":"Schleswig-Holstein",
    "wof:name":"Kreissparkasse Ostholstein",
    "wof:placetype":"venue"
},
  "geometry": {"coordinates":[10.764984,54.062977],"type":"Point"}
}