{
  "type": "Feature",
  "properties": {
    "iso:country":"DE",
    "sg:address":"Schacht-Kronprinz-Str. 60",
    "sg:city":"Essen",
    "sg:phone":"+49 201/686163",
    "sg:postcode":"45359",
    "sg:province":"Nordrhein-Westfalen",
    "wof:name":"Parkett Scholl Inh. A. Linnberg",
    "wof:placetype":"venue"
},
  "geometry": {"coordinates":[6.9358868599,51.4576644897],"type":"Point"}
}