{
  "type": "Feature",
  "properties": {
    "iso:country":"DE",
    "sg:address":"Kantstr. 54",
    "sg:city":"Berlin",
    "sg:phone":"+49 30/3125047",
    "sg:postcode":"10627",
    "sg:province":"Berlin",
    "wof:name":"Kant-kino",
    "wof:placetype":"venue"
},
  "geometry": {"coordinates":[13.308488,52.506786],"type":"Point"}
}