{
  "type": "Feature",
  "properties": {
    "iso:country":"DE",
    "sg:address":"Hauptstr. 332",
    "sg:city":"Eschborn",
    "sg:phone":"+49 6173/607760",
    "sg:postcode":"65760",
    "sg:province":"Hessen",
    "wof:name":"Mhb Leasing Service Gmbh",
    "wof:placetype":"venue"
},
  "geometry": {"coordinates":[8.55702,50.148102],"type":"Point"}
}