{
  "type": "Feature",
  "properties": {
    "iso:country":"DE",
    "sg:address":"Maxplatz 18",
    "sg:city":"Hof",
    "sg:postcode":"95028",
    "sg:province":"Bayern",
    "wof:name":"Rainer Hopf Raumausstattung E. K.",
    "wof:placetype":"venue"
},
  "geometry": {"coordinates":[11.9205207825,50.3226966858],"type":"Point"}
}