{
  "type": "Feature",
  "properties": {
    "iso:country":"DE",
    "sg:address":"Semperstr. 78",
    "sg:city":"Hamburg",
    "sg:phone":"+49 40/2793850",
    "sg:postcode":"22303",
    "sg:province":"Hamburg",
    "wof:name":"Ristorante Sabatini",
    "wof:placetype":"venue"
},
  "geometry": {"coordinates":[10.0202198029,53.5876350403],"type":"Point"}
}