{
  "type": "Feature",
  "properties": {
    "iso:country":"DE",
    "sg:address":"D\u00fcrerstr. 8",
    "sg:city":"Herne",
    "sg:phone":"+49 2325/77767",
    "sg:postcode":"44652",
    "sg:province":"Nordrhein-Westfalen",
    "wof:name":"Herbert Dirschke",
    "wof:placetype":"venue"
},
  "geometry": {"coordinates":[7.1609449387,51.5251655579],"type":"Point"}
}