{
  "type": "Feature",
  "properties": {
    "iso:country":"DE",
    "sg:address":"Wei\u00dfdornweg 37",
    "sg:city":"Karlsruhe",
    "sg:phone":"+49 721/9712397",
    "sg:postcode":"76149",
    "sg:province":"Baden-W\u00fcrttemberg",
    "wof:name":"Hartmut Reiser",
    "wof:placetype":"venue"
},
  "geometry": {"coordinates":[8.3878993988,49.0353240967],"type":"Point"}
}