{
  "type": "Feature",
  "properties": {
    "iso:country":"DE",
    "sg:address":"Zur Wulfskammer 8",
    "sg:city":"Alfeld",
    "sg:phone":"+49 5181/5815",
    "sg:postcode":"31061",
    "sg:province":"Niedersachsen",
    "wof:name":"Ev. Pfarramt Gerzen",
    "wof:placetype":"venue"
},
  "geometry": {"coordinates":[9.8007602692,51.9672966003],"type":"Point"}
}