{
  "type": "Feature",
  "properties": {
    "iso:country":"DE",
    "sg:address":"Siemensstr. 3-5",
    "sg:city":"Rednitzhembach",
    "sg:postcode":"91126",
    "sg:province":"Bayern",
    "wof:name":"Forschungs- Und Entwicklungszentrum",
    "wof:placetype":"venue"
},
  "geometry": {"coordinates":[11.0485916138,49.3132095337],"type":"Point"}
}