{
  "type": "Feature",
  "properties": {
    "iso:country":"DE",
    "sg:address":"Zollenspieker Hauptdeich 64",
    "sg:city":"Hamburg",
    "sg:phone":"+49 40/7230611",
    "sg:postcode":"21037",
    "sg:province":"Hamburg",
    "wof:name":"G\u00fcnter Wobbe",
    "wof:placetype":"venue"
},
  "geometry": {"coordinates":[10.193833,53.403755],"type":"Point"}
}