{
  "type": "Feature",
  "properties": {
    "iso:country":"DE",
    "sg:address":"Grammendorfer Weg 2a",
    "sg:city":"Tribsees",
    "sg:phone":"+49 38320/66112",
    "sg:postcode":"18465",
    "sg:province":"Mecklenburg-Vorpommern",
    "wof:name":"Metallbau Heizungs- Und Sanit\u00e4rtechnik Tribsees Gmbh",
    "wof:placetype":"venue"
},
  "geometry": {"coordinates":[12.7700271606,54.0867652893],"type":"Point"}
}