{
  "type": "Feature",
  "properties": {
    "iso:country":"DE",
    "sg:address":"Johann-Walter-Str. 7",
    "sg:city":"Lampertheim",
    "sg:phone":"+49 6256/1464",
    "sg:postcode":"68623",
    "sg:province":"Hessen",
    "wof:name":"Paletten-handel Meinolf Klute Gmbh",
    "wof:placetype":"venue"
},
  "geometry": {"coordinates":[8.5839271545,49.5950813293],"type":"Point"}
}