{
  "type": "Feature",
  "properties": {
    "iso:country":"DE",
    "sg:address":"Holtenauer Str. 288",
    "sg:city":"Kiel",
    "sg:phone":"+49 431/30717",
    "sg:postcode":"24106",
    "sg:province":"Schleswig-Holstein",
    "wof:name":"Ragotzky & G\u00e4tje Gmbh",
    "wof:placetype":"venue"
},
  "geometry": {"coordinates":[10.132579,54.351929],"type":"Point"}
}