{
  "type": "Feature",
  "properties": {
    "iso:country":"DE",
    "sg:address":"Eichweg 1",
    "sg:city":"Pforzen",
    "sg:phone":"+49 8346/9777",
    "sg:postcode":"87666",
    "sg:province":"Bayern",
    "wof:name":"W. Zech",
    "wof:placetype":"venue"
},
  "geometry": {"coordinates":[10.6164627075,47.9281730652],"type":"Point"}
}