{
  "type": "Feature",
  "properties": {
    "iso:country":"DE",
    "sg:address":"Markgrafenstr. 67",
    "sg:city":"Berlin",
    "sg:phone":"+49 30/259007210",
    "sg:postcode":"10969",
    "sg:province":"Berlin",
    "wof:name":"Stadtentwicklungsgesellschaft Buch Mbh",
    "wof:placetype":"venue"
},
  "geometry": {"coordinates":[13.394334,52.505901],"type":"Point"}
}