{
  "type": "Feature",
  "properties": {
    "iso:country":"DE",
    "sg:address":"Pfrondorfer Str. 4",
    "sg:city":"T\u00fcbingen",
    "sg:phone":"+49 7071/81104",
    "sg:postcode":"72074",
    "sg:province":"Baden-W\u00fcrttemberg",
    "wof:name":"Redaktion Lexicographika Niemeyer Verlag",
    "wof:placetype":"venue"
},
  "geometry": {"coordinates":[9.0790224075,48.5319366455],"type":"Point"}
}