{
  "type": "Feature",
  "properties": {
    "iso:country":"DE",
    "sg:address":"Weidenpescher Str. 2",
    "sg:city":"K\u00f6ln",
    "sg:phone":"+49 221/7124135",
    "sg:postcode":"50735",
    "sg:province":"Nordrhein-Westfalen",
    "wof:name":"Elektro Junker Gmbh",
    "wof:placetype":"venue"
},
  "geometry": {"coordinates":[6.961381,50.977234],"type":"Point"}
}