{
  "type": "Feature",
  "properties": {
    "iso:country":"DE",
    "sg:address":"Oschatzer Str. 17",
    "sg:city":"Belgern",
    "sg:phone":"+49 34224/40211",
    "sg:postcode":"04874",
    "sg:province":"Sachsen",
    "wof:name":"D\u00f6ner-kebap Inh. Hidir Fener",
    "wof:placetype":"venue"
},
  "geometry": {"coordinates":[13.1231393814,51.4807701111],"type":"Point"}
}