{
  "type": "Feature",
  "properties": {
    "iso:country":"DE",
    "sg:address":"B\u00fcsnauer Str. 28",
    "sg:city":"Stuttgart",
    "sg:phone":"+49 711/682590",
    "sg:postcode":"70563",
    "sg:province":"Baden-W\u00fcrttemberg",
    "wof:name":"Hans Ziehlke Architekt",
    "wof:placetype":"venue"
},
  "geometry": {"coordinates":[9.098865,48.735577],"type":"Point"}
}