{
  "type": "Feature",
  "properties": {
    "iso:country":"DE",
    "sg:address":"M\u00fchlenstr. 16",
    "sg:city":"Wedel",
    "sg:phone":"+49 4103/83066",
    "sg:postcode":"22880",
    "sg:province":"Schleswig-Holstein",
    "wof:name":"Stammbach Und Borek Rechtsanw\u00e4lte",
    "wof:placetype":"venue"
},
  "geometry": {"coordinates":[9.7001314163,53.5829582214],"type":"Point"}
}