{
  "type": "Feature",
  "properties": {
    "iso:country":"DE",
    "sg:address":"Zimmlerstr. 14",
    "sg:city":"Liebstadt",
    "sg:phone":"+49 35025/50732",
    "sg:postcode":"01825",
    "sg:province":"Sachsen",
    "wof:name":"A. Morgenstern",
    "wof:placetype":"venue"
},
  "geometry": {"coordinates":[13.8528347015,50.8624649048],"type":"Point"}
}