{
  "type": "Feature",
  "properties": {
    "iso:country":"DE",
    "sg:address":"Sarweystr. 3",
    "sg:city":"Stuttgart",
    "sg:phone":"+49 711/8995520",
    "sg:postcode":"70191",
    "sg:province":"Baden-W\u00fcrttemberg",
    "wof:name":"Fichtner Solar Gmbh",
    "wof:placetype":"venue"
},
  "geometry": {"coordinates":[9.188278,48.805527],"type":"Point"}
}