{
  "type": "Feature",
  "properties": {
    "iso:country":"DE",
    "sg:address":"Hornberg 1",
    "sg:city":"Schw\u00e4bisch Gm\u00fcnd",
    "sg:phone":"+49 7171/82235",
    "sg:postcode":"73529",
    "sg:province":"Baden-W\u00fcrttemberg",
    "wof:name":"H\u00f6henrestaurant",
    "wof:placetype":"venue"
},
  "geometry": {"coordinates":[9.8598833084,48.7459831238],"type":"Point"}
}