{
  "type": "Feature",
  "properties": {
    "iso:country":"DE",
    "sg:address":"Markt 3",
    "sg:city":"Mei\u00dfen",
    "sg:phone":"+49 3521/41940",
    "sg:postcode":"01662",
    "sg:province":"Sachsen",
    "wof:name":"Tourist-information Mei\u00dfen Gmbh",
    "wof:placetype":"venue"
},
  "geometry": {"coordinates":[13.470870018,51.1631317139],"type":"Point"}
}