{
  "type": "Feature",
  "properties": {
    "iso:country":"DE",
    "sg:address":"Ziegenmarkt 1",
    "sg:city":"L\u00fcbz",
    "sg:postcode":"19386",
    "sg:province":"Mecklenburg-Vorpommern",
    "wof:name":"Rudi Z\u00fchlke Blumen",
    "wof:placetype":"venue"
},
  "geometry": {"coordinates":[12.031315,53.461185],"type":"Point"}
}