{
  "type": "Feature",
  "properties": {
    "iso:country":"DE",
    "sg:address":"Buchenweg 1",
    "sg:city":"Nossen",
    "sg:phone":"+49 35242/4200",
    "sg:postcode":"01683",
    "sg:province":"Sachsen",
    "wof:name":"Vbh Vereinigter Baubeschlag- Handels Gmbh",
    "wof:placetype":"venue"
},
  "geometry": {"coordinates":[13.29338,51.048141],"type":"Point"}
}