{
  "type": "Feature",
  "properties": {
    "iso:country":"DE",
    "sg:address":"Forststr. 30",
    "sg:city":"Bad Schwalbach",
    "sg:phone":"+49 6124/2197",
    "sg:postcode":"65307",
    "sg:province":"Hessen",
    "wof:name":"Ursula Georg Heilpraktikerin",
    "wof:placetype":"venue"
},
  "geometry": {"coordinates":[8.0414066315,50.1334114075],"type":"Point"}
}