{
  "type": "Feature",
  "properties": {
    "iso:country":"DE",
    "sg:address":"Schillerstr. 12",
    "sg:city":"Kehl",
    "sg:phone":"+49 7854/302",
    "sg:postcode":"77694",
    "sg:province":"Baden-W\u00fcrttemberg",
    "wof:name":"F.-j. Becker",
    "wof:placetype":"venue"
},
  "geometry": {"coordinates":[7.82765,48.507832],"type":"Point"}
}