{
  "type": "Feature",
  "properties": {
    "iso:country":"DE",
    "sg:address":"Hauptstr. 12",
    "sg:city":"Pommersfelden",
    "sg:phone":"+49 9548/314",
    "sg:postcode":"96178",
    "sg:province":"Bayern",
    "wof:name":"G. Kirchner",
    "wof:placetype":"venue"
},
  "geometry": {"coordinates":[10.8187446594,49.767326355],"type":"Point"}
}