{
  "type": "Feature",
  "properties": {
    "iso:country":"DE",
    "sg:address":"Griesbr\u00e4ustr. 12",
    "sg:city":"Murnau",
    "sg:phone":"+49 8841/90543",
    "sg:postcode":"82418",
    "sg:province":"Bayern",
    "wof:name":"Dinah Marker Heilpraktikerin",
    "wof:placetype":"venue"
},
  "geometry": {"coordinates":[11.1991176605,47.6798706055],"type":"Point"}
}