{
  "type": "Feature",
  "properties": {
    "iso:country":"DE",
    "sg:address":"Frankensteiner Str. 19",
    "sg:city":"Darmstadt",
    "sg:phone":"+49 6151/54409",
    "sg:postcode":"64297",
    "sg:province":"Hessen",
    "wof:name":"Alfred Koll",
    "wof:placetype":"venue"
},
  "geometry": {"coordinates":[8.6573095322,49.8070106506],"type":"Point"}
}