{
  "type": "Feature",
  "properties": {
    "iso:country":"DE",
    "sg:address":"Adolf-Clarenbach-Str. 21",
    "sg:city":"Solingen",
    "sg:phone":"+49 212/318488",
    "sg:postcode":"42719",
    "sg:province":"Nordrhein-Westfalen",
    "wof:name":"Grill Am Stadion",
    "wof:placetype":"venue"
},
  "geometry": {"coordinates":[7.0347561836,51.1839103699],"type":"Point"}
}