{
  "type": "Feature",
  "properties": {
    "iso:country":"DE",
    "sg:address":"Bremer Str. 7a",
    "sg:city":"Bohmte",
    "sg:phone":"+49 5471/1543",
    "sg:postcode":"49163",
    "sg:province":"Niedersachsen",
    "wof:name":"S. Rothert",
    "wof:placetype":"venue"
},
  "geometry": {"coordinates":[8.3090991974,52.3618392944],"type":"Point"}
}