{
  "type": "Feature",
  "properties": {
    "iso:country":"DE",
    "sg:address":"Ostseeallee 21",
    "sg:city":"K\u00fchlungsborn",
    "sg:postcode":"18225",
    "sg:province":"Mecklenburg-Vorpommern",
    "wof:name":"Beauty Und Wellness Hotel K\u00fchlungsborn Ag",
    "wof:placetype":"venue"
},
  "geometry": {"coordinates":[11.7472667694,54.1527023315],"type":"Point"}
}