{
  "type": "Feature",
  "properties": {
    "iso:country":"DE",
    "sg:address":"Fetscherstr. 62",
    "sg:city":"Dresden",
    "sg:phone":"+49 351/4422222",
    "sg:postcode":"01307",
    "sg:province":"Sachsen",
    "wof:name":"B. Gutte",
    "wof:placetype":"venue"
},
  "geometry": {"coordinates":[13.7764253616,51.0513076782],"type":"Point"}
}