{
  "type": "Feature",
  "properties": {
    "iso:country":"DE",
    "sg:address":"Strombergstr. 14 a",
    "sg:city":"Stuttgart",
    "sg:phone":"+49 711/463818",
    "sg:postcode":"70188",
    "sg:province":"Baden-W\u00fcrttemberg",
    "wof:name":"R. W. Bell",
    "wof:placetype":"venue"
},
  "geometry": {"coordinates":[9.2068052292,48.7825241089],"type":"Point"}
}