{
  "type": "Feature",
  "properties": {
    "iso:country":"DE",
    "sg:address":"Weststr. 38",
    "sg:city":"Chemnitz",
    "sg:postcode":"09112",
    "sg:province":"Sachsen",
    "wof:name":"Actior Trading Center Chemnitz Gmbh",
    "wof:placetype":"venue"
},
  "geometry": {"coordinates":[12.9029073715,50.8324623108],"type":"Point"}
}