{
  "type": "Feature",
  "properties": {
    "iso:country":"DE",
    "sg:address":"Eifelstr. 22",
    "sg:city":"Bad Breisig",
    "sg:phone":"+49 2633/95708",
    "sg:postcode":"53498",
    "sg:province":"Rheinland-Pfalz",
    "wof:name":"Kreissparkasse Ahrweiler",
    "wof:placetype":"venue"
},
  "geometry": {"coordinates":[7.294482,50.506893],"type":"Point"}
}