{
  "type": "Feature",
  "properties": {
    "iso:country":"DE",
    "sg:address":"Aubachstr. 17",
    "sg:city":"Obertraubling",
    "sg:phone":"+49 9401/51152",
    "sg:postcode":"93083",
    "sg:province":"Bayern",
    "wof:name":"Hermelinde Fr\u00f6hler-schlachter Rechtsanw\u00e4ltin",
    "wof:placetype":"venue"
},
  "geometry": {"coordinates":[12.1252288818,48.9595870972],"type":"Point"}
}