{
  "type": "Feature",
  "properties": {
    "iso:country":"DE",
    "sg:address":"Ortsstr. 19",
    "sg:city":"Rudolstadt",
    "sg:phone":"+49 3672/423152",
    "sg:postcode":"07407",
    "sg:province":"Th\u00fcringen",
    "wof:name":"S. Schaube",
    "wof:placetype":"venue"
},
  "geometry": {"coordinates":[11.3266448975,50.7368049622],"type":"Point"}
}