{
  "type": "Feature",
  "properties": {
    "iso:country":"DE",
    "sg:address":"Heddesdorfer Str. 29",
    "sg:city":"Neuwied",
    "sg:phone":"+49 2631/26864",
    "sg:postcode":"56564",
    "sg:province":"Rheinland-Pfalz",
    "wof:name":"Jutta Russo",
    "wof:placetype":"venue"
},
  "geometry": {"coordinates":[7.464459,50.43206],"type":"Point"}
}