{
  "type": "Feature",
  "properties": {
    "iso:country":"DE",
    "sg:address":"Sudetenstr. 5",
    "sg:city":"Herrenberg",
    "sg:phone":"+49 7032/957144",
    "sg:postcode":"71083",
    "sg:province":"Baden-W\u00fcrttemberg",
    "wof:name":"W.h. Voutta",
    "wof:placetype":"venue"
},
  "geometry": {"coordinates":[8.8781194687,48.5793876648],"type":"Point"}
}