{
  "type": "Feature",
  "properties": {
    "iso:country":"DE",
    "sg:address":"Reinboldsm\u00fchle",
    "sg:city":"Buxheim",
    "sg:phone":"+49 8458/8803",
    "sg:postcode":"85114",
    "sg:province":"Bayern",
    "wof:name":"Ernst Z\u00f6pfli",
    "wof:placetype":"venue"
},
  "geometry": {"coordinates":[11.3086929321,48.7916297913],"type":"Point"}
}