{
  "type": "Feature",
  "properties": {
    "iso:country":"DE",
    "sg:address":"Durlacher Allee 32",
    "sg:city":"Karlsruhe",
    "sg:phone":"+49 721/697065",
    "sg:postcode":"76131",
    "sg:province":"Baden-W\u00fcrttemberg",
    "wof:name":"Sanit\u00e4tshaus Krux Inh. Gerhard Willnauer",
    "wof:placetype":"venue"
},
  "geometry": {"coordinates":[8.4213199615,49.0080337524],"type":"Point"}
}