{
  "type": "Feature",
  "properties": {
    "iso:country":"DE",
    "sg:address":"Meinrad-Thoma-Str. 1",
    "sg:city":"Todtnau",
    "sg:phone":"+49 7671/385",
    "sg:postcode":"79674",
    "sg:province":"Baden-W\u00fcrttemberg",
    "wof:name":"Restaurant Sonne",
    "wof:placetype":"venue"
},
  "geometry": {"coordinates":[7.9465928078,47.8303833008],"type":"Point"}
}