{
  "type": "Feature",
  "properties": {
    "iso:country":"DE",
    "sg:address":"Seligenst\u00e4dter Str. 71",
    "sg:city":"R\u00f6dermark",
    "sg:phone":"+49 6074/93364",
    "sg:postcode":"63322",
    "sg:province":"Hessen",
    "wof:name":"F. Cassagne",
    "wof:placetype":"venue"
},
  "geometry": {"coordinates":[8.837092,49.974396],"type":"Point"}
}