{
  "type": "Feature",
  "properties": {
    "iso:country":"DE",
    "sg:address":"Von-Essen-Str. 62",
    "sg:city":"Hamburg",
    "sg:phone":"+49 40/292006",
    "sg:postcode":"22081",
    "sg:province":"Hamburg",
    "wof:name":"Hella D\u00e4hms",
    "wof:placetype":"venue"
},
  "geometry": {"coordinates":[10.0445966721,53.5748710632],"type":"Point"}
}