{
  "type": "Feature",
  "properties": {
    "iso:country":"DE",
    "sg:address":"Mittelstr. 39",
    "sg:city":"Zierenberg",
    "sg:phone":"+49 5606/2211",
    "sg:postcode":"34289",
    "sg:province":"Hessen",
    "wof:name":"Restaurant Andreaskreuz",
    "wof:placetype":"venue"
},
  "geometry": {"coordinates":[9.3004455566,51.3674697876],"type":"Point"}
}