{
  "type": "Feature",
  "properties": {
    "iso:country":"DE",
    "sg:address":"Karlstr. 21",
    "sg:city":"Weingarten",
    "sg:phone":"+49 751/560980",
    "sg:postcode":"88250",
    "sg:province":"Baden-W\u00fcrttemberg",
    "wof:name":"Kaufland",
    "wof:placetype":"venue"
},
  "geometry": {"coordinates":[9.6408624649,47.8068733215],"type":"Point"}
}