{
  "type": "Feature",
  "properties": {
    "iso:country":"DE",
    "sg:address":"du Perche",
    "sg:city":"Landelles",
    "sg:phone":"+49 2372/37598",
    "sg:postcode":"28190",
    "wof:name":"Aiki Jutsu Takeda Ryu Maroto Ha",
    "wof:placetype":"venue"
},
  "geometry": {"coordinates":[1.196565032,48.4679832458],"type":"Point"}
}