{
  "type": "Feature",
  "properties": {
    "iso:country":"DE",
    "sg:address":"Stettiner Str. 57",
    "sg:city":"Eggesin",
    "sg:phone":"+49 39779/20560",
    "sg:postcode":"17367",
    "sg:province":"Mecklenburg-Vorpommern",
    "wof:name":"G. Zimmermann",
    "wof:placetype":"venue"
},
  "geometry": {"coordinates":[14.086692,53.677814],"type":"Point"}
}