{
  "type": "Feature",
  "properties": {
    "iso:country":"DE",
    "sg:address":"Wankelstr. 1",
    "sg:city":"Stadtbergen",
    "sg:phone":"+49 821/440980",
    "sg:postcode":"86391",
    "sg:province":"Bayern",
    "wof:name":"Eger Und Graf Rechtsanw\u00e4lte",
    "wof:placetype":"venue"
},
  "geometry": {"coordinates":[10.842622757,48.3783111572],"type":"Point"}
}