{
  "type": "Feature",
  "properties": {
    "iso:country":"DE",
    "sg:address":"Im Unterdorf 5",
    "sg:city":"Landwehr",
    "sg:phone":"+49 5382/5233",
    "sg:postcode":"31087",
    "sg:province":"Niedersachsen",
    "wof:name":"Werner Bohnsack",
    "wof:placetype":"venue"
},
  "geometry": {"coordinates":[9.99182,51.912289],"type":"Point"}
}