{
  "type": "Feature",
  "properties": {
    "iso:country":"DE",
    "sg:address":"Liblarer See",
    "sg:city":"Erftstadt",
    "sg:phone":"+49 2235/43596",
    "sg:postcode":"50374",
    "sg:province":"Nordrhein-Westfalen",
    "wof:name":"Seeterrasse",
    "wof:placetype":"venue"
},
  "geometry": {"coordinates":[6.7655310631,50.7999420166],"type":"Point"}
}