{
  "type": "Feature",
  "properties": {
    "iso:country":"DE",
    "sg:address":"Regensburger Str. 15",
    "sg:city":"Berlin",
    "sg:phone":"+49 30/2138070",
    "sg:postcode":"10777",
    "sg:province":"Berlin",
    "wof:name":"Gernot Und Stefanie Meyer Rechtsanw\u00e4lte Und Notar",
    "wof:placetype":"venue"
},
  "geometry": {"coordinates":[13.3330059052,52.4960632324],"type":"Point"}
}