{
  "type": "Feature",
  "properties": {
    "iso:country":"DE",
    "sg:address":"Marderweg 25",
    "sg:city":"Jena",
    "sg:phone":"+49 3641/825247",
    "sg:postcode":"07749",
    "sg:province":"Th\u00fcringen",
    "wof:name":"Dr. Med. Werner Ebert",
    "wof:placetype":"venue"
},
  "geometry": {"coordinates":[11.625856,50.929714],"type":"Point"}
}