{
  "type": "Feature",
  "properties": {
    "iso:country":"DE",
    "sg:address":"St.-Antonius-Weg 8",
    "sg:city":"Ravensburg",
    "sg:phone":"+49 751/61284",
    "sg:postcode":"88213",
    "sg:province":"Baden-W\u00fcrttemberg",
    "wof:name":"Kath. Pfarramt St. Antonius V. Padua",
    "wof:placetype":"venue"
},
  "geometry": {"coordinates":[9.5757598877,47.7568702698],"type":"Point"}
}