{
  "type": "Feature",
  "properties": {
    "iso:country":"DE",
    "sg:address":"Mazenodweg 2",
    "sg:city":"Borken",
    "sg:postcode":"46325",
    "sg:province":"Nordrhein-Westfalen",
    "wof:name":"Missions-soforthilfe",
    "wof:placetype":"venue"
},
  "geometry": {"coordinates":[6.8443279266,51.8501243591],"type":"Point"}
}