{
  "type": "Feature",
  "properties": {
    "iso:country":"DE",
    "sg:address":"Hauptstr. 78",
    "sg:city":"Rellingen",
    "sg:phone":"+49 4101/22718",
    "sg:postcode":"25462",
    "sg:province":"Schleswig-Holstein",
    "wof:name":"Dat Rellinger Backhus",
    "wof:placetype":"venue"
},
  "geometry": {"coordinates":[9.829669,53.652973],"type":"Point"}
}