{
  "type": "Feature",
  "properties": {
    "iso:country":"DE",
    "sg:address":"Alter Markt 12",
    "sg:city":"M\u00f6nchengladbach",
    "sg:phone":"+49 2161/175388",
    "sg:postcode":"41061",
    "sg:province":"Nordrhein-Westfalen",
    "wof:name":"Marktsch\u00e4nke",
    "wof:placetype":"venue"
},
  "geometry": {"coordinates":[6.4314332008,51.1943283081],"type":"Point"}
}