{
  "type": "Feature",
  "properties": {
    "iso:country":"DE",
    "sg:address":"Carl-Orff-Str. 6",
    "sg:city":"Donauw\u00f6rth",
    "sg:phone":"+49 906/705720",
    "sg:postcode":"86609",
    "sg:province":"Bayern",
    "wof:name":"Strobel Verwaltungs Gmbh",
    "wof:placetype":"venue"
},
  "geometry": {"coordinates":[10.779971,48.690441],"type":"Point"}
}