{
  "type": "Feature",
  "properties": {
    "iso:country":"DE",
    "sg:address":"Lindleystra\u00dfe 22",
    "sg:city":"Frankfurt/Main",
    "sg:phone":"+49 69/9433170",
    "sg:postcode":"60314",
    "sg:province":"Hessen",
    "wof:name":"Hans Gilles Transport-service Gmbh",
    "wof:placetype":"venue"
},
  "geometry": {"coordinates":[8.72579,50.11459],"type":"Point"}
}