{
  "type": "Feature",
  "properties": {
    "iso:country":"DE",
    "sg:address":"Hallstattweg 11",
    "sg:city":"Linnich",
    "sg:phone":"+49 2462/74116",
    "sg:postcode":"52441",
    "sg:province":"Nordrhein-Westfalen",
    "wof:name":"J\u00f6rg L\u00fchmann Finanzberater",
    "wof:placetype":"venue"
},
  "geometry": {"coordinates":[6.267056942,50.9704017639],"type":"Point"}
}