{
  "type": "Feature",
  "properties": {
    "iso:country":"DE",
    "sg:address":"Friedrichsgaber Str. 19",
    "sg:city":"Quickborn",
    "sg:phone":"+49 4106/71137",
    "sg:postcode":"25451",
    "sg:province":"Schleswig-Holstein",
    "wof:name":"Shell-tankstelle",
    "wof:placetype":"venue"
},
  "geometry": {"coordinates":[9.9347648621,53.7497024536],"type":"Point"}
}