{
  "type": "Feature",
  "properties": {
    "iso:country":"DE",
    "sg:address":"Albert-Schneble-Str. 21",
    "sg:city":"B\u00fchlertal",
    "sg:phone":"+49 7223/74866",
    "sg:postcode":"77830",
    "sg:province":"Baden-W\u00fcrttemberg",
    "wof:name":"Rum\u00e4nienhilfe E. V. Christine Kunsmann",
    "wof:placetype":"venue"
},
  "geometry": {"coordinates":[8.1899299622,48.6683311462],"type":"Point"}
}