{
  "type": "Feature",
  "properties": {
    "iso:country":"DE",
    "sg:address":"Erlenweg 51",
    "sg:city":"M\u00fclheim",
    "sg:phone":"+49 208/489972",
    "sg:postcode":"45481",
    "sg:province":"Nordrhein-Westfalen",
    "wof:name":"P. A. A. M. Import-export Gmbh",
    "wof:placetype":"venue"
},
  "geometry": {"coordinates":[6.8608498573,51.3938293457],"type":"Point"}
}