{
  "type": "Feature",
  "properties": {
    "iso:country":"DE",
    "sg:address":"M\u00f6llner Str. 15",
    "sg:city":"B\u00fcchen",
    "sg:phone":"+49 4155/3989",
    "sg:postcode":"21514",
    "sg:province":"Schleswig-Holstein",
    "wof:name":"Manfred Neetzke",
    "wof:placetype":"venue"
},
  "geometry": {"coordinates":[10.6165761948,53.482509613],"type":"Point"}
}