{
  "type": "Feature",
  "properties": {
    "iso:country":"DE",
    "sg:address":"Eduard-Maurer-Str. 11c",
    "sg:city":"Hennigsdorf",
    "sg:phone":"+49 3302/810295",
    "sg:postcode":"16761",
    "sg:province":"Brandenburg",
    "wof:name":"Bk Wassertechnik Und Rohrleitungsbau Gmbh",
    "wof:placetype":"venue"
},
  "geometry": {"coordinates":[13.2069730759,52.6514015198],"type":"Point"}
}