{
  "type": "Feature",
  "properties": {
    "iso:country":"DE",
    "sg:address":"Seelenbinderstr.44",
    "sg:city":"Berlin-K\u00f6penick",
    "sg:phone":"+49 6526/2089",
    "sg:postcode":"12555",
    "sg:province":"Berlin",
    "wof:name":"Gastro & Delivery",
    "wof:placetype":"venue"
},
  "geometry": {"coordinates":[13.581234,52.45528],"type":"Point"}
}