{
  "type": "Feature",
  "properties": {
    "iso:country":"DE",
    "sg:address":"Mindener Str. 60",
    "sg:city":"Herford",
    "sg:phone":"+49 5221/23222",
    "sg:postcode":"32049",
    "sg:province":"Nordrhein-Westfalen",
    "wof:name":"Bauelemente Kleeschulte Gmbh",
    "wof:placetype":"venue"
},
  "geometry": {"coordinates":[8.682442,52.123363],"type":"Point"}
}