{
  "type": "Feature",
  "properties": {
    "iso:country":"DE",
    "sg:address":"Werkstr. 2",
    "sg:city":"Schwerin",
    "sg:phone":"+49 385/616208",
    "sg:postcode":"19061",
    "sg:province":"Mecklenburg-Vorpommern",
    "wof:name":"Sperlich",
    "wof:placetype":"venue"
},
  "geometry": {"coordinates":[11.38861,53.57132],"type":"Point"}
}