{
  "type": "Feature",
  "properties": {
    "iso:country":"DE",
    "sg:address":"Am Schacht 9",
    "sg:city":"G\u00f6llingen",
    "sg:postcode":"06567",
    "sg:province":"Th\u00fcringen",
    "wof:name":"Noi-meerestechnik Gmbh",
    "wof:placetype":"venue"
},
  "geometry": {"coordinates":[10.9960346222,51.3375778198],"type":"Point"}
}