{
  "type": "Feature",
  "properties": {
    "iso:country":"DE",
    "sg:address":"Max-T\u00fcrpe-Str. 44",
    "sg:city":"Chemnitz",
    "sg:phone":"+49 371/221161",
    "sg:postcode":"09122",
    "sg:province":"Sachsen",
    "wof:name":"Klaus Buchheim",
    "wof:placetype":"venue"
},
  "geometry": {"coordinates":[12.8824863434,50.7915802002],"type":"Point"}
}