{
  "type": "Feature",
  "properties": {
    "iso:country":"DE",
    "sg:address":"Falkstr. 17",
    "sg:city":"Bielefeld",
    "sg:phone":"+49 521/66081",
    "sg:postcode":"33602",
    "sg:province":"Nordrhein-Westfalen",
    "wof:name":"Hans-g\u00fcnther Klussmann Architekt",
    "wof:placetype":"venue"
},
  "geometry": {"coordinates":[8.539259,52.0224],"type":"Point"}
}