{
  "type": "Feature",
  "properties": {
    "iso:country":"DE",
    "sg:address":"Franz-Kruckenberg-Str. 5",
    "sg:city":"Uetersen",
    "sg:phone":"+49 4122/3013",
    "sg:postcode":"25436",
    "sg:province":"Schleswig-Holstein",
    "wof:name":"M. Lottermoser Blumenhandels-gmbh",
    "wof:placetype":"venue"
},
  "geometry": {"coordinates":[9.697699,53.679974],"type":"Point"}
}