{
  "type": "Feature",
  "properties": {
    "iso:country":"DE",
    "sg:address":"W\u00f6rthstr. 33",
    "sg:city":"Reutlingen",
    "sg:phone":"+49 7121/925810",
    "sg:postcode":"72764",
    "sg:province":"Baden-W\u00fcrttemberg",
    "wof:name":"Kost Gmbh",
    "wof:placetype":"venue"
},
  "geometry": {"coordinates":[9.219119072,48.4851112366],"type":"Point"}
}