{
  "type": "Feature",
  "properties": {
    "iso:country":"DE",
    "sg:address":"Scharffstr. 4-6",
    "sg:city":"Remscheid",
    "sg:phone":"+49 2191/442637",
    "sg:postcode":"42853",
    "sg:province":"Nordrhein-Westfalen",
    "wof:name":"Stadtb\u00fccherei",
    "wof:placetype":"venue"
},
  "geometry": {"coordinates":[7.189455,51.181705],"type":"Point"}
}