{
  "type": "Feature",
  "properties": {
    "iso:country":"DE",
    "sg:address":"Nottorstr. 3",
    "sg:city":"Hachenburg",
    "sg:phone":"+49 2662/4218",
    "sg:postcode":"57627",
    "sg:province":"Rheinland-Pfalz",
    "wof:name":"H. Schlaug",
    "wof:placetype":"venue"
},
  "geometry": {"coordinates":[7.8234372139,50.6614303589],"type":"Point"}
}