{
  "type": "Feature",
  "properties": {
    "iso:country":"DE",
    "sg:address":"Weyerstr. 253",
    "sg:city":"Solingen",
    "sg:phone":"+49 212/310742",
    "sg:postcode":"42719",
    "sg:province":"Nordrhein-Westfalen",
    "wof:name":"Weyer Eck",
    "wof:placetype":"venue"
},
  "geometry": {"coordinates":[7.0297589302,51.1775474548],"type":"Point"}
}