{
  "type": "Feature",
  "properties": {
    "iso:country":"DE",
    "sg:address":"Wasserstr. 31",
    "sg:city":"Steinfurt",
    "sg:phone":"+49 2551/5208",
    "sg:postcode":"48565",
    "sg:province":"Nordrhein-Westfalen",
    "wof:name":"Rosemarie Gude",
    "wof:placetype":"venue"
},
  "geometry": {"coordinates":[7.340923,52.149727],"type":"Point"}
}