{
  "type": "Feature",
  "properties": {
    "iso:country":"DE",
    "sg:address":"Hauptstr. 31",
    "sg:city":"Spaatz",
    "sg:phone":"+49 33872/70355",
    "sg:postcode":"14715",
    "sg:province":"Brandenburg",
    "wof:name":"Wilfried Roloff",
    "wof:placetype":"venue"
},
  "geometry": {"coordinates":[12.308015,52.704178],"type":"Point"}
}