{
  "type": "Feature",
  "properties": {
    "iso:country":"DE",
    "sg:address":"Carl-Peschken-Str. 8",
    "sg:city":"Moers",
    "sg:phone":"+49 2841/17910",
    "sg:postcode":"47441",
    "sg:province":"Nordrhein-Westfalen",
    "wof:name":"Sta Silo- Und Tank- Anh\u00e4nger-service Gmbh",
    "wof:placetype":"venue"
},
  "geometry": {"coordinates":[6.595734,51.440334],"type":"Point"}
}