{
  "type": "Feature",
  "properties": {
    "iso:country":"DE",
    "sg:address":"Hauptstr. 30",
    "sg:city":"Nortrup",
    "sg:phone":"+49 5436/1654",
    "sg:postcode":"49638",
    "sg:province":"Niedersachsen",
    "wof:name":"K & L Klima-l\u00fcftungs- Handels-gmbh",
    "wof:placetype":"venue"
},
  "geometry": {"coordinates":[7.8592920303,52.6147727966],"type":"Point"}
}