{
  "type": "Feature",
  "properties": {
    "iso:country":"DE",
    "sg:address":"Eckenerstr. 11",
    "sg:city":"Tamm",
    "sg:phone":"+49 7141/603710",
    "sg:postcode":"71732",
    "sg:province":"Baden-W\u00fcrttemberg",
    "wof:name":"Helmut Zoller",
    "wof:placetype":"venue"
},
  "geometry": {"coordinates":[9.1243696213,48.919834137],"type":"Point"}
}