{
  "type": "Feature",
  "properties": {
    "iso:country":"DE",
    "sg:address":"An Der Kirche 3",
    "sg:city":"Wadern",
    "sg:phone":"+49 4968/712391",
    "sg:postcode":"66687",
    "sg:province":"Saarland",
    "wof:name":"Wderner & Hermeskeiler Druckerei Dochow & Gouvneur",
    "wof:placetype":"venue"
},
  "geometry": {"coordinates":[6.8897399902,49.5387153625],"type":"Point"}
}