{
  "type": "Feature",
  "properties": {
    "iso:country":"DE",
    "sg:address":"Industriepark 206",
    "sg:city":"Gottmadingen",
    "sg:phone":"+49 7731/976739",
    "sg:postcode":"78244",
    "sg:province":"Baden-W\u00fcrttemberg",
    "wof:name":"Rsa Gmbh",
    "wof:placetype":"venue"
},
  "geometry": {"coordinates":[8.787157,47.73756],"type":"Point"}
}