{
  "type": "Feature",
  "properties": {
    "iso:country":"DE",
    "sg:address":"Unterau 42",
    "sg:city":"Amtzell",
    "sg:phone":"+49 7522/8916",
    "sg:postcode":"88279",
    "sg:province":"Baden-W\u00fcrttemberg",
    "wof:name":"Wochner Und Wolf Architekt",
    "wof:placetype":"venue"
},
  "geometry": {"coordinates":[9.77808,47.698421],"type":"Point"}
}