{
  "type": "Feature",
  "properties": {
    "iso:country":"DE",
    "sg:address":"Lagesche Str. 12",
    "sg:city":"Detmold",
    "sg:phone":"+49 5231/26384",
    "sg:postcode":"32756",
    "sg:province":"Nordrhein-Westfalen",
    "wof:name":"Popcorn",
    "wof:placetype":"venue"
},
  "geometry": {"coordinates":[8.8758487701,51.9433937073],"type":"Point"}
}