{
  "type": "Feature",
  "properties": {
    "iso:country":"DE",
    "sg:address":"Am Wehrhahn 1",
    "sg:city":"D\u00fcsseldorf",
    "sg:phone":"+49 211/360531",
    "sg:postcode":"40211",
    "sg:province":"Nordrhein-Westfalen",
    "wof:name":"Atlasreisen Gmbh",
    "wof:placetype":"venue"
},
  "geometry": {"coordinates":[6.7877149582,51.2278022766],"type":"Point"}
}