{
  "type": "Feature",
  "properties": {
    "iso:country":"DE",
    "sg:address":"Auf der Steig 15",
    "sg:city":"Tiefenbronn",
    "sg:phone":"+49 7234/949088",
    "sg:postcode":"75233",
    "sg:province":"Baden-W\u00fcrttemberg",
    "wof:name":"Olze Dienstleistungen Gmbh",
    "wof:placetype":"venue"
},
  "geometry": {"coordinates":[8.819284,48.807823],"type":"Point"}
}