{
  "type": "Feature",
  "properties": {
    "iso:country":"DE",
    "sg:address":"Karolinenstr. 30",
    "sg:city":"Ansbach",
    "sg:phone":"+49 981/12688",
    "sg:postcode":"91522",
    "sg:province":"Bayern",
    "wof:name":"Richard Frank Steuerberater",
    "wof:placetype":"venue"
},
  "geometry": {"coordinates":[10.5769996643,49.299911499],"type":"Point"}
}