{
  "type": "Feature",
  "properties": {
    "iso:country":"DE",
    "sg:address":"Saarstr. 82",
    "sg:city":"K\u00f6ln",
    "sg:phone":"+49 2234/77418",
    "sg:postcode":"50859",
    "sg:province":"Nordrhein-Westfalen",
    "wof:name":"E. Schmidt",
    "wof:placetype":"venue"
},
  "geometry": {"coordinates":[6.8276629448,50.9428405762],"type":"Point"}
}