{
  "type": "Feature",
  "properties": {
    "iso:country":"DE",
    "sg:address":"Dammer Weg 36",
    "sg:city":"Parchim",
    "sg:phone":"+49 3871/66031",
    "sg:postcode":"19370",
    "sg:province":"Mecklenburg-Vorpommern",
    "wof:name":"W. Huth",
    "wof:placetype":"venue"
},
  "geometry": {"coordinates":[11.8265771866,53.4319038391],"type":"Point"}
}