{
  "type": "Feature",
  "properties": {
    "iso:country":"DE",
    "sg:address":"23684",
    "sg:city":"Scharbeutz",
    "sg:postcode":"23684",
    "sg:province":"Schleswig-Holstein",
    "wof:name":"Raiffeisenbank Eg P\u00f6nitz",
    "wof:placetype":"venue"
},
  "geometry": {"coordinates":[10.67164,54.019112],"type":"Point"}
}