{
  "type": "Feature",
  "properties": {
    "iso:country":"DE",
    "sg:address":"Bahnstr. 1",
    "sg:city":"Dinslaken",
    "sg:phone":"+49 2064/4115",
    "sg:postcode":"46535",
    "sg:province":"Nordrhein-Westfalen",
    "wof:name":"Malteser Beauty",
    "wof:placetype":"venue"
},
  "geometry": {"coordinates":[6.739641,51.563457],"type":"Point"}
}