{
  "type": "Feature",
  "properties": {
    "iso:country":"DE",
    "sg:address":"M\u00fchlweg 43",
    "sg:city":"Limburgerhof",
    "sg:phone":"+49 6236/48497",
    "sg:postcode":"67117",
    "sg:province":"Rheinland-Pfalz",
    "wof:name":"Thomas-wohnbau Gmbh",
    "wof:placetype":"venue"
},
  "geometry": {"coordinates":[8.381806,49.422695],"type":"Point"}
}