{
  "type": "Feature",
  "properties": {
    "iso:country":"DE",
    "sg:address":"Br\u00fcckenstr. 7",
    "sg:city":"Biedenkopf",
    "sg:phone":"+49 6461/8287",
    "sg:postcode":"35216",
    "sg:province":"Hessen",
    "wof:name":"H. Und R. Schneider",
    "wof:placetype":"venue"
},
  "geometry": {"coordinates":[8.4620723724,50.9137763977],"type":"Point"}
}