{
  "type": "Feature",
  "properties": {
    "iso:country":"DE",
    "sg:address":"Steinbuck 1 a",
    "sg:city":"Klettgau",
    "sg:phone":"+49 7742/7604",
    "sg:postcode":"79771",
    "sg:province":"Baden-W\u00fcrttemberg",
    "wof:name":"Horst Burghardt Heilpraktikerin",
    "wof:placetype":"venue"
},
  "geometry": {"coordinates":[8.4280910492,47.6588630676],"type":"Point"}
}