{
  "type": "Feature",
  "properties": {
    "iso:country":"DE",
    "sg:address":"Wallgutstr. 39",
    "sg:city":"Konstanz",
    "sg:phone":"+49 7531/21447",
    "sg:postcode":"78462",
    "sg:province":"Baden-W\u00fcrttemberg",
    "wof:name":"Uwe Sch\u00fctt",
    "wof:placetype":"venue"
},
  "geometry": {"coordinates":[9.1670799255,47.6644325256],"type":"Point"}
}