{
  "type": "Feature",
  "properties": {
    "iso:country":"DE",
    "sg:address":"Lilienthalstr. 1",
    "sg:city":"Hamm",
    "sg:phone":"+49 2381/303300",
    "sg:postcode":"59065",
    "sg:province":"Nordrhein-Westfalen",
    "wof:name":"Edv Service-center Pfeiffer W\u00e4lz & Partner Gmbh",
    "wof:placetype":"venue"
},
  "geometry": {"coordinates":[7.8089461327,51.687625885],"type":"Point"}
}