{
  "type": "Feature",
  "properties": {
    "iso:country":"DE",
    "sg:address":"Aachener Str. 698",
    "sg:city":"K\u00f6ln",
    "sg:phone":"+49 221/9472800",
    "sg:postcode":"50933",
    "sg:province":"Nordrhein-Westfalen",
    "wof:name":"Aphrodite",
    "wof:placetype":"venue"
},
  "geometry": {"coordinates":[6.8826341629,50.9379081726],"type":"Point"}
}