{
  "type": "Feature",
  "properties": {
    "iso:country":"DE",
    "sg:address":"Am Welschen Brunnen 81",
    "sg:city":"Crailsheim",
    "sg:phone":"+49 7951/8114",
    "sg:postcode":"74564",
    "sg:province":"Baden-W\u00fcrttemberg",
    "wof:name":"R. Bach",
    "wof:placetype":"venue"
},
  "geometry": {"coordinates":[10.0791034698,49.1251564026],"type":"Point"}
}