{
  "type": "Feature",
  "properties": {
    "iso:country":"DE",
    "sg:address":"Augsburger Str. 59",
    "sg:city":"Mammendorf",
    "sg:phone":"+49 8145/5115",
    "sg:postcode":"82291",
    "sg:province":"Bayern",
    "wof:name":"A. Pollersp\u00f6ck",
    "wof:placetype":"venue"
},
  "geometry": {"coordinates":[11.1543283463,48.2055397034],"type":"Point"}
}