{
  "type": "Feature",
  "properties": {
    "iso:country":"DE",
    "sg:address":"Am Tanzberg 20",
    "sg:city":"Stockheim",
    "sg:postcode":"97640",
    "sg:province":"Bayern",
    "wof:name":"Pfarrb\u00fccherei",
    "wof:placetype":"venue"
},
  "geometry": {"coordinates":[10.270776,50.457413],"type":"Point"}
}