{
  "type": "Feature",
  "properties": {
    "iso:country":"DE",
    "sg:address":"Heisinger Str. 488",
    "sg:city":"Essen",
    "sg:phone":"+49 201/460762",
    "sg:postcode":"45259",
    "sg:province":"Nordrhein-Westfalen",
    "wof:name":"Bruno L\u00fcntz",
    "wof:placetype":"venue"
},
  "geometry": {"coordinates":[7.066146,51.403366],"type":"Point"}
}