{
  "type": "Feature",
  "properties": {
    "iso:country":"DE",
    "sg:address":"Nonnenrain 7",
    "sg:city":"Erfurt",
    "sg:phone":"+49 361/5626661",
    "sg:postcode":"99096",
    "sg:province":"Th\u00fcringen",
    "wof:name":"Stempel Voigt Gmbh",
    "wof:placetype":"venue"
},
  "geometry": {"coordinates":[11.042493,50.971256],"type":"Point"}
}