{
  "type": "Feature",
  "properties": {
    "iso:country":"DE",
    "sg:address":"Freudenst\u00e4dter Str. 9",
    "sg:city":"Baiersbronn",
    "sg:phone":"+49 7442/3798",
    "sg:postcode":"72270",
    "sg:province":"Baden-W\u00fcrttemberg",
    "wof:name":"Herbert Schneider",
    "wof:placetype":"venue"
},
  "geometry": {"coordinates":[8.3707389832,48.5093727112],"type":"Point"}
}