{
  "type": "Feature",
  "properties": {
    "iso:country":"DE",
    "sg:address":"Am Gerhardsweiler -Alt- 12a",
    "sg:city":"J\u00fcchen",
    "sg:phone":"+49 2165/7372",
    "sg:postcode":"41363",
    "sg:province":"Nordrhein-Westfalen",
    "wof:name":"A. Mebs",
    "wof:placetype":"venue"
},
  "geometry": {"coordinates":[6.5154538155,51.1076545715],"type":"Point"}
}