{
  "type": "Feature",
  "properties": {
    "iso:country":"DE",
    "sg:address":"Liiger Wal 3",
    "sg:city":"Sylt-Ost",
    "sg:phone":"+49 4651/890550",
    "sg:postcode":"25980",
    "sg:province":"Schleswig-Holstein",
    "wof:name":"H. Johannsen",
    "wof:placetype":"venue"
},
  "geometry": {"coordinates":[8.423861,54.857754],"type":"Point"}
}