{
  "type": "Feature",
  "properties": {
    "iso:country":"DE",
    "sg:address":"Losheimer Str. 31",
    "sg:city":"Weiskirchen",
    "sg:phone":"+49 6876/801",
    "sg:postcode":"66709",
    "sg:province":"Saarland",
    "wof:name":"Hans Wecker",
    "wof:placetype":"venue"
},
  "geometry": {"coordinates":[6.817784,49.552502],"type":"Point"}
}