{
  "type": "Feature",
  "properties": {
    "iso:country":"DE",
    "sg:address":"Marktstr. 54",
    "sg:city":"Krefeld",
    "sg:phone":"+49 2151/29458",
    "sg:postcode":"47798",
    "sg:province":"Nordrhein-Westfalen",
    "wof:name":"Phildar-wolle",
    "wof:placetype":"venue"
},
  "geometry": {"coordinates":[6.561557,51.330193],"type":"Point"}
}