{
  "type": "Feature",
  "properties": {
    "iso:country":"DE",
    "sg:address":"Uffeln Mitte 14",
    "sg:city":"Ibbenb\u00fcren",
    "sg:phone":"+49 5459/8208",
    "sg:postcode":"49479",
    "sg:province":"Nordrhein-Westfalen",
    "wof:name":"Gastst\u00e4tte Josef Helmer",
    "wof:placetype":"venue"
},
  "geometry": {"coordinates":[7.6302351952,52.3229179382],"type":"Point"}
}