{
  "type": "Feature",
  "properties": {
    "iso:country":"DE",
    "sg:address":"Gudestr. 4",
    "sg:city":"Sinzig",
    "sg:phone":"+49 2642/7781",
    "sg:postcode":"53489",
    "sg:province":"Rheinland-Pfalz",
    "wof:name":"Claudia Hnida",
    "wof:placetype":"venue"
},
  "geometry": {"coordinates":[7.2522277832,50.5443305969],"type":"Point"}
}