{
  "type": "Feature",
  "properties": {
    "iso:country":"DE",
    "sg:address":"Bl\u00fctenstr. 17",
    "sg:city":"Weiden",
    "sg:phone":"+49 961/5675",
    "sg:postcode":"92637",
    "sg:province":"Bayern",
    "wof:name":"Heinz M\u00fcller Gmbh",
    "wof:placetype":"venue"
},
  "geometry": {"coordinates":[12.1398258209,49.6571273804],"type":"Point"}
}