{
  "type": "Feature",
  "properties": {
    "iso:country":"DE",
    "sg:address":"Silberpappelstr. 2",
    "sg:city":"Winnenden",
    "sg:phone":"+49 7195/6930",
    "sg:postcode":"71364",
    "sg:province":"Baden-W\u00fcrttemberg",
    "wof:name":"Jws Nusser Verwaltungs Gmbh",
    "wof:placetype":"venue"
},
  "geometry": {"coordinates":[9.3933582306,48.8750038147],"type":"Point"}
}