{
  "type": "Feature",
  "properties": {
    "iso:country":"DE",
    "sg:address":"Vorhelmer Weg 32",
    "sg:city":"Ahlen",
    "sg:phone":"+49 2382/81001",
    "sg:postcode":"59227",
    "sg:province":"Nordrhein-Westfalen",
    "wof:name":"Michael Schwarte Dipl. -ing.",
    "wof:placetype":"venue"
},
  "geometry": {"coordinates":[7.9017720222,51.7730140686],"type":"Point"}
}