{
  "type": "Feature",
  "properties": {
    "iso:country":"DE",
    "sg:address":"Bayerisches Filmzentrum / Bavariafilmpla",
    "sg:city":"Geiselgasteig",
    "sg:phone":"+49 89/64981136",
    "sg:postcode":"82031",
    "sg:province":"Bayern",
    "wof:name":"Juicy Film And Mental Torture",
    "wof:placetype":"venue"
},
  "geometry": {"coordinates":[11.522715,48.039635],"type":"Point"}
}