{
  "type": "Feature",
  "properties": {
    "iso:country":"DE",
    "sg:address":"Wilhelm-Bergner-Str. 1",
    "sg:city":"Glinde",
    "sg:phone":"+49 40/727404",
    "sg:postcode":"21509",
    "sg:province":"Schleswig-Holstein",
    "wof:name":"De Laval Distribution Center Gmbh",
    "wof:placetype":"venue"
},
  "geometry": {"coordinates":[10.224125,53.529488],"type":"Point"}
}