{
  "type": "Feature",
  "properties": {
    "iso:country":"DE",
    "sg:address":"Friedensstr. 12",
    "sg:city":"Bergen",
    "sg:phone":"+49 3838/209232",
    "sg:postcode":"18528",
    "sg:province":"Mecklenburg-Vorpommern",
    "wof:name":"Thomas Herrmann Architekt",
    "wof:placetype":"venue"
},
  "geometry": {"coordinates":[11.363898,52.111919],"type":"Point"}
}