{
  "type": "Feature",
  "properties": {
    "iso:country":"DE",
    "sg:address":"Falkenstr. 4",
    "sg:city":"Baden-Baden",
    "sg:phone":"+49 7221/36190",
    "sg:postcode":"76530",
    "sg:province":"Baden-W\u00fcrttemberg",
    "wof:name":"Ges. F\u00fcr Stadterneuerung Und Stadtentwicklung",
    "wof:placetype":"venue"
},
  "geometry": {"coordinates":[8.2455644608,48.7524337769],"type":"Point"}
}