{
  "type": "Feature",
  "properties": {
    "iso:country":"DE",
    "sg:address":"Kalk-M\u00fclheimer Str. 157",
    "sg:city":"K\u00f6ln",
    "sg:phone":"+49 221/850775",
    "sg:postcode":"51103",
    "sg:province":"Nordrhein-Westfalen",
    "wof:name":"Deutscher Verkehrs- Verlag Gmbh",
    "wof:placetype":"venue"
},
  "geometry": {"coordinates":[7.0012421608,50.9429244995],"type":"Point"}
}