{
  "type": "Feature",
  "properties": {
    "iso:country":"DE",
    "sg:address":"Weissenseestr. 101",
    "sg:city":"M\u00fcnchen",
    "sg:phone":"+49 89/6518535",
    "sg:postcode":"81539",
    "sg:province":"Bayern",
    "wof:name":"Ambient Recording Gmbh",
    "wof:placetype":"venue"
},
  "geometry": {"coordinates":[11.580005,48.108582],"type":"Point"}
}