{
  "type": "Feature",
  "properties": {
    "iso:country":"DE",
    "sg:address":"Zum Stadion 69",
    "sg:city":"Langenfeld",
    "sg:phone":"+49 2173/80360",
    "sg:postcode":"40764",
    "sg:province":"Nordrhein-Westfalen",
    "wof:name":"Imo Informationssysteme Management- Und",
    "wof:placetype":"venue"
},
  "geometry": {"coordinates":[6.942029953,51.1192817688],"type":"Point"}
}