{
  "type": "Feature",
  "properties": {
    "iso:country":"DE",
    "sg:address":"Geschwister-Scholl-Str. 96",
    "sg:city":"Monheim",
    "sg:postcode":"40789",
    "sg:province":"Nordrhein-Westfalen",
    "wof:name":"Artir Gastronomiebetriebe Gmbh",
    "wof:placetype":"venue"
},
  "geometry": {"coordinates":[6.8934431076,51.1268920898],"type":"Point"}
}