{
  "type": "Feature",
  "properties": {
    "iso:country":"DE",
    "sg:address":"Koogchaussee 28",
    "sg:city":"Lunden",
    "sg:phone":"+49 4882/65010",
    "sg:postcode":"25774",
    "sg:province":"Schleswig-Holstein",
    "wof:name":"Petersen Und Jacobs Gmbh",
    "wof:placetype":"venue"
},
  "geometry": {"coordinates":[9.0221004486,54.3278884888],"type":"Point"}
}