{
  "type": "Feature",
  "properties": {
    "iso:country":"DE",
    "sg:address":"Goethestr. 1",
    "sg:city":"Renningen",
    "sg:phone":"+49 7159/8687",
    "sg:postcode":"71272",
    "sg:province":"Baden-W\u00fcrttemberg",
    "wof:name":"H. F\u00fcnfer",
    "wof:placetype":"venue"
},
  "geometry": {"coordinates":[8.9344120026,48.770816803],"type":"Point"}
}