{
  "type": "Feature",
  "properties": {
    "iso:country":"DE",
    "sg:address":"Kocherstr. 7",
    "sg:city":"Heubach",
    "sg:phone":"+49 7173/5020",
    "sg:postcode":"73540",
    "sg:province":"Baden-W\u00fcrttemberg",
    "wof:name":"Mario Vivaldi",
    "wof:placetype":"venue"
},
  "geometry": {"coordinates":[9.912436,48.79641],"type":"Point"}
}