{
  "type": "Feature",
  "properties": {
    "iso:country":"DE",
    "sg:address":"Birkenweg 21",
    "sg:city":"Tornesch",
    "sg:phone":"+49 4122/952121",
    "sg:postcode":"25436",
    "sg:province":"Schleswig-Holstein",
    "wof:name":"Beldan Gmbh & Co. Kg Trennwandsysteme Und Raumteiler",
    "wof:placetype":"venue"
},
  "geometry": {"coordinates":[9.7155399323,53.7128219604],"type":"Point"}
}