{
  "type": "Feature",
  "properties": {
    "iso:country":"DE",
    "sg:address":"Einsteinstr. 5",
    "sg:city":"Ahlen",
    "sg:phone":"+49 2382/3405",
    "sg:postcode":"59227",
    "sg:province":"Nordrhein-Westfalen",
    "wof:name":"Leg Wohnen Gmbh",
    "wof:placetype":"venue"
},
  "geometry": {"coordinates":[7.8860621452,51.7749786377],"type":"Point"}
}