{
  "type": "Feature",
  "properties": {
    "iso:country":"DE",
    "sg:address":"Am Wiesenhang 7",
    "sg:city":"Wennigsen",
    "sg:phone":"+49 5103/8051",
    "sg:postcode":"30974",
    "sg:province":"Niedersachsen",
    "wof:name":"Cillys Shop Inh. Cilly Hofmann",
    "wof:placetype":"venue"
},
  "geometry": {"coordinates":[9.529214,52.270897],"type":"Point"}
}