{
  "type": "Feature",
  "properties": {
    "iso:country":"DE",
    "sg:address":"Kurf\u00fcrstendamm 206",
    "sg:city":"Berlin",
    "sg:phone":"+49 30/8859110",
    "sg:postcode":"10719",
    "sg:province":"Berlin",
    "wof:name":"Kom\u00f6die Berliner Privattheater Gmbh",
    "wof:placetype":"venue"
},
  "geometry": {"coordinates":[13.3230228424,52.5019493103],"type":"Point"}
}