{
  "type": "Feature",
  "properties": {
    "iso:country":"DE",
    "sg:address":"Johann-G.-Gutenberg-Str. 28",
    "sg:city":"Olching",
    "sg:phone":"+49 8142/40792",
    "sg:postcode":"82140",
    "sg:province":"Bayern",
    "wof:name":"Fliesen Hanff & Scheidecker Verwaltungs Gmbh",
    "wof:placetype":"venue"
},
  "geometry": {"coordinates":[11.325489,48.197918],"type":"Point"}
}