{
  "type": "Feature",
  "properties": {
    "iso:country":"DE",
    "sg:address":"Stollberger Str. 265",
    "sg:city":"Chemnitz",
    "sg:phone":"+49 371/37465",
    "sg:postcode":"09122",
    "sg:province":"Sachsen",
    "wof:name":"G. Lang",
    "wof:placetype":"venue"
},
  "geometry": {"coordinates":[12.882229805,50.7962112427],"type":"Point"}
}