{
  "type": "Feature",
  "properties": {
    "iso:country":"DE",
    "sg:address":"Ru\u00dflandweg 14",
    "sg:city":"Friedeburg",
    "sg:postcode":"26446",
    "sg:province":"Niedersachsen",
    "wof:name":"Fries. Porzellan Manufaktur Heiko Blume",
    "wof:placetype":"venue"
},
  "geometry": {"coordinates":[7.820171833,53.4521522522],"type":"Point"}
}