{
  "type": "Feature",
  "properties": {
    "iso:country":"DE",
    "sg:address":"Holzstr. 100",
    "sg:city":"M\u00fclheim",
    "sg:phone":"+49 208/429733",
    "sg:postcode":"45479",
    "sg:province":"Nordrhein-Westfalen",
    "wof:name":"Arthur Auberg",
    "wof:placetype":"venue"
},
  "geometry": {"coordinates":[6.863718,51.41885],"type":"Point"}
}