{
  "type": "Feature",
  "properties": {
    "iso:country":"DE",
    "sg:address":"Calwer Str. 6",
    "sg:city":"Pforzheim",
    "sg:phone":"+49 7231/62596",
    "sg:postcode":"75175",
    "sg:province":"Baden-W\u00fcrttemberg",
    "wof:name":"Jugenzentrum Schlauch",
    "wof:placetype":"venue"
},
  "geometry": {"coordinates":[8.703423,48.887276],"type":"Point"}
}