{
  "type": "Feature",
  "properties": {
    "iso:country":"DE",
    "sg:address":"Waldhofer Str. 6",
    "sg:city":"Bad Birnbach",
    "sg:phone":"+49 8563/451",
    "sg:postcode":"84364",
    "sg:province":"Bayern",
    "wof:name":"E. Engleder",
    "wof:placetype":"venue"
},
  "geometry": {"coordinates":[13.031693,48.455273],"type":"Point"}
}