{
  "type": "Feature",
  "properties": {
    "iso:country":"DE",
    "sg:address":"Auf dem Sand 23",
    "sg:city":"Mannheim",
    "sg:phone":"+49 621/735723",
    "sg:postcode":"68309",
    "sg:province":"Baden-W\u00fcrttemberg",
    "wof:name":"Bruno Walther",
    "wof:placetype":"venue"
},
  "geometry": {"coordinates":[8.506737709,49.5097312927],"type":"Point"}
}