{
  "type": "Feature",
  "properties": {
    "iso:country":"DE",
    "sg:address":"Industrieweg 1-3",
    "sg:city":"Neustadt",
    "sg:phone":"+49 4561/51630",
    "sg:postcode":"23730",
    "sg:province":"Schleswig-Holstein",
    "wof:name":"Neust\u00e4dter Transport Gmbh",
    "wof:placetype":"venue"
},
  "geometry": {"coordinates":[10.885068,54.134293],"type":"Point"}
}