{
  "type": "Feature",
  "properties": {
    "iso:country":"DE",
    "sg:address":"Niedersachsenstr. 25-27",
    "sg:city":"Tostedt",
    "sg:phone":"+49 4182/28330",
    "sg:postcode":"21255",
    "sg:province":"Niedersachsen",
    "wof:name":"Altenheim Homann Gmbh",
    "wof:placetype":"venue"
},
  "geometry": {"coordinates":[9.73766,53.273151],"type":"Point"}
}