{
  "type": "Feature",
  "properties": {
    "iso:country":"DE",
    "sg:address":"Wildbader Str. 30",
    "sg:city":"Dobel",
    "sg:phone":"+49 7083/8828",
    "sg:postcode":"75335",
    "sg:province":"Baden-W\u00fcrttemberg",
    "wof:name":"Fremdenheim K. U. L. Beck",
    "wof:placetype":"venue"
},
  "geometry": {"coordinates":[8.4961700439,48.7948112488],"type":"Point"}
}