{
  "type": "Feature",
  "properties": {
    "iso:country":"DE",
    "sg:address":"Bundeskanzlerplatz 2-10",
    "sg:city":"Bonn",
    "sg:phone":"+49 49228",
    "sg:postcode":"53113",
    "sg:province":"Nordrhein-Westfalen",
    "wof:name":"Bach Consulting",
    "wof:placetype":"venue"
},
  "geometry": {"coordinates":[7.11666,50.719044],"type":"Point"}
}