{
  "type": "Feature",
  "properties": {
    "iso:country":"DE",
    "sg:address":"Kaiser-Joseph-Str. 231",
    "sg:city":"Freiburg",
    "sg:phone":"+49 761/32529",
    "sg:postcode":"79098",
    "sg:province":"Baden-W\u00fcrttemberg",
    "wof:name":"Laufsteg E. Gimber",
    "wof:placetype":"venue"
},
  "geometry": {"coordinates":[7.8491439819,47.9937782288],"type":"Point"}
}