{
  "type": "Feature",
  "properties": {
    "iso:country":"DE",
    "sg:address":"Im Dorfe 22",
    "sg:city":"Garbsen",
    "sg:phone":"+49 5031/71363",
    "sg:postcode":"30826",
    "sg:province":"Niedersachsen",
    "wof:name":"W. Homeyer",
    "wof:placetype":"venue"
},
  "geometry": {"coordinates":[9.511331,52.429245],"type":"Point"}
}