{
  "type": "Feature",
  "properties": {
    "iso:country":"DE",
    "sg:address":"Amselweg 1",
    "sg:city":"Kleinblittersdorf",
    "sg:phone":"+49 6805/22915",
    "sg:postcode":"66271",
    "sg:province":"Saarland",
    "wof:name":"J. Beisert",
    "wof:placetype":"venue"
},
  "geometry": {"coordinates":[7.088834,49.170082],"type":"Point"}
}