{
  "type": "Feature",
  "properties": {
    "iso:country":"DE",
    "sg:address":"Saggrian 2",
    "sg:city":"K\u00fcsten",
    "sg:postcode":"29482",
    "sg:province":"Niedersachsen",
    "wof:name":"Nan Gesellschaft F\u00fcr Me\u00dftechnik Und",
    "wof:placetype":"venue"
},
  "geometry": {"coordinates":[11.0201339722,53.0198898315],"type":"Point"}
}