{
  "type": "Feature",
  "properties": {
    "iso:country":"DE",
    "sg:address":"Hauptstr. 41",
    "sg:city":"Gelchsheim",
    "sg:phone":"+49 9335/1327",
    "sg:postcode":"97255",
    "sg:province":"Bayern",
    "wof:name":"C. Esslinger",
    "wof:placetype":"venue"
},
  "geometry": {"coordinates":[10.0211648941,49.5730895996],"type":"Point"}
}