{
  "type": "Feature",
  "properties": {
    "iso:country":"DE",
    "sg:address":"Damaschkestr. 53",
    "sg:city":"Lingen",
    "sg:phone":"+49 591/78800",
    "sg:postcode":"49811",
    "sg:province":"Niedersachsen",
    "wof:name":"Alten Tagespflege Herbstzeitlose",
    "wof:placetype":"venue"
},
  "geometry": {"coordinates":[7.355839,52.543358],"type":"Point"}
}