{
  "type": "Feature",
  "properties": {
    "iso:country":"DE",
    "sg:address":"Mecklenburger Str. 73",
    "sg:city":"L\u00fcbeck",
    "sg:phone":"+49 451/690148",
    "sg:postcode":"23568",
    "sg:province":"Schleswig-Holstein",
    "wof:name":"C. Wedderkopp",
    "wof:placetype":"venue"
},
  "geometry": {"coordinates":[10.762602,53.891525],"type":"Point"}
}