{
  "type": "Feature",
  "properties": {
    "iso:country":"DE",
    "sg:address":"Waldstr. 28",
    "sg:city":"Woldegk",
    "sg:phone":"+49 3963/210408",
    "sg:postcode":"17348",
    "sg:province":"Mecklenburg-Vorpommern",
    "wof:name":"Dr. Ekkehard Rathmann Tierarzt",
    "wof:placetype":"venue"
},
  "geometry": {"coordinates":[13.5864009857,53.4645423889],"type":"Point"}
}