{
  "type": "Feature",
  "properties": {
    "iso:country":"DE",
    "sg:address":"Homberger Str. 23 Mosheim",
    "sg:city":"Malsfeld/Mosheim",
    "sg:phone":"+49 4956/6294900",
    "sg:postcode":"34323",
    "sg:province":"Hessen",
    "wof:name":"Hans Heinrich Hain Gmbh",
    "wof:placetype":"venue"
},
  "geometry": {"coordinates":[9.461316,51.084827],"type":"Point"}
}