{
  "type": "Feature",
  "properties": {
    "iso:country":"DE",
    "sg:address":"Gewerbestra\u00dfe 2+4",
    "sg:city":"Freudenberg",
    "sg:phone":"+49 2734/275240",
    "sg:postcode":"57252",
    "sg:province":"Baden-W\u00fcrttemberg",
    "wof:name":"Zerst\u00f6rungsfreie Werkstoffpr\u00fcfung",
    "wof:placetype":"venue"
},
  "geometry": {"coordinates":[7.913653,50.911514],"type":"Point"}
}