{
  "type": "Feature",
  "properties": {
    "iso:country":"DE",
    "sg:address":"Kirchweg 17",
    "sg:city":"Berg",
    "sg:phone":"+49 8151/50041",
    "sg:postcode":"82335",
    "sg:province":"Bayern",
    "wof:name":"Schulze-lackner Gmbh",
    "wof:placetype":"venue"
},
  "geometry": {"coordinates":[11.36734,47.957203],"type":"Point"}
}