{
  "type": "Feature",
  "properties": {
    "iso:country":"DE",
    "sg:address":"Fleischergasse 3",
    "sg:city":"Crimmitschau",
    "sg:phone":"+49 3762/95320",
    "sg:postcode":"08451",
    "sg:province":"Sachsen",
    "wof:name":"Gemeinn\u00fctzige Baugesellschaft Crimmitschau Mbh",
    "wof:placetype":"venue"
},
  "geometry": {"coordinates":[12.3863134384,50.8148078918],"type":"Point"}
}