{
  "type": "Feature",
  "properties": {
    "iso:country":"DE",
    "sg:address":"Gewerbegebiet",
    "sg:city":"Bellheim",
    "sg:phone":"+49 7272/70030",
    "sg:postcode":"76756",
    "sg:province":"Rheinland-Pfalz",
    "wof:name":"Einrichtungshaus Strohmeier & Gilb Gmbh",
    "wof:placetype":"venue"
},
  "geometry": {"coordinates":[8.2805871964,49.1911849976],"type":"Point"}
}