{
  "type": "Feature",
  "properties": {
    "iso:country":"DE",
    "sg:address":"Versbacher Str. 249",
    "sg:city":"W\u00fcrzburg",
    "sg:phone":"+49 931/21432",
    "sg:postcode":"97078",
    "sg:province":"Bayern",
    "wof:name":"A. B\u00e4uml Heissmangel",
    "wof:placetype":"venue"
},
  "geometry": {"coordinates":[9.9567899704,49.8301391602],"type":"Point"}
}