{
  "type": "Feature",
  "properties": {
    "iso:country":"DE",
    "sg:address":"Kastanienweg 18",
    "sg:city":"Salow",
    "sg:postcode":"17099",
    "sg:province":"Mecklenburg-Vorpommern",
    "wof:name":"Tusek-bau Gmbh",
    "wof:placetype":"venue"
},
  "geometry": {"coordinates":[13.495733,53.677631],"type":"Point"}
}