{
  "type": "Feature",
  "properties": {
    "iso:country":"DE",
    "sg:address":"Untereickener Str. 55",
    "sg:city":"M\u00f6nchengladbach",
    "sg:phone":"+49 2161/16957",
    "sg:postcode":"41063",
    "sg:province":"Nordrhein-Westfalen",
    "wof:name":"Haus Klingen",
    "wof:placetype":"venue"
},
  "geometry": {"coordinates":[6.4495267868,51.213684082],"type":"Point"}
}