{
  "type": "Feature",
  "properties": {
    "iso:country":"DE",
    "sg:address":"Bebenh\u00e4userhofstr. 12",
    "sg:city":"Reutlingen",
    "sg:phone":"+49 7121/346762",
    "sg:postcode":"72764",
    "sg:province":"Baden-W\u00fcrttemberg",
    "wof:name":"Novel",
    "wof:placetype":"venue"
},
  "geometry": {"coordinates":[9.2102174759,48.4928627014],"type":"Point"}
}