{
  "type": "Feature",
  "properties": {
    "iso:country":"DE",
    "sg:address":"Wei\u00dfm\u00fchlweg 20",
    "sg:city":"Undenheim",
    "sg:phone":"+49 6737/8982",
    "sg:postcode":"55278",
    "sg:province":"Rheinland-Pfalz",
    "wof:name":"Herburg Hage Krankengymnastin",
    "wof:placetype":"venue"
},
  "geometry": {"coordinates":[8.219458,49.837761],"type":"Point"}
}