{
  "type": "Feature",
  "properties": {
    "iso:country":"DE",
    "sg:address":"Hohe Str. 16",
    "sg:city":"Leipzig",
    "sg:phone":"+49 341/9600597",
    "sg:postcode":"04107",
    "sg:province":"Sachsen",
    "wof:name":"J\u00f6rg Wegmann Rechtsanwalt",
    "wof:placetype":"venue"
},
  "geometry": {"coordinates":[12.3793554306,51.3290977478],"type":"Point"}
}