{
  "type": "Feature",
  "properties": {
    "iso:country":"DE",
    "sg:address":"Gartenstr. 5",
    "sg:city":"Laufen",
    "sg:phone":"+49 8682/7236",
    "sg:postcode":"83410",
    "sg:province":"Bayern",
    "wof:name":"Rud. Spitzauer",
    "wof:placetype":"venue"
},
  "geometry": {"coordinates":[12.8947629929,47.9227027893],"type":"Point"}
}