{
  "type": "Feature",
  "properties": {
    "iso:country":"DE",
    "sg:address":"K\u00f6lner Ring 143",
    "sg:city":"Soest",
    "sg:phone":"+49 2921/60553",
    "sg:postcode":"59494",
    "sg:province":"Nordrhein-Westfalen",
    "wof:name":"Kronen-quell",
    "wof:placetype":"venue"
},
  "geometry": {"coordinates":[8.0912494659,51.5745544434],"type":"Point"}
}