{
  "type": "Feature",
  "properties": {
    "iso:country":"DE",
    "sg:address":"An der Hasel 69",
    "sg:city":"Suhl",
    "sg:phone":"+49 3681/708054",
    "sg:postcode":"98527",
    "sg:province":"Th\u00fcringen",
    "wof:name":"Bartenstein",
    "wof:placetype":"venue"
},
  "geometry": {"coordinates":[10.686223,50.601902],"type":"Point"}
}