{
  "type": "Feature",
  "properties": {
    "iso:country":"DE",
    "sg:address":"Meyerstr. 1",
    "sg:city":"Cuxhaven",
    "sg:postcode":"27472",
    "sg:province":"Niedersachsen",
    "wof:name":"Reederei Frank Dahl Ms Orade Kg",
    "wof:placetype":"venue"
},
  "geometry": {"coordinates":[8.71628,53.853821],"type":"Point"}
}