{
  "type": "Feature",
  "properties": {
    "iso:country":"DE",
    "sg:address":"Erlenweg 4",
    "sg:city":"Hindelang",
    "sg:phone":"+49 8324/7192",
    "sg:postcode":"87541",
    "sg:province":"Bayern",
    "wof:name":"W. Kramer",
    "wof:placetype":"venue"
},
  "geometry": {"coordinates":[10.42747,47.544304],"type":"Point"}
}