{
  "type": "Feature",
  "properties": {
    "iso:country":"DE",
    "sg:address":"An der Palmweide 55",
    "sg:city":"Dortmund",
    "sg:phone":"+49 231/9759747",
    "sg:postcode":"44227",
    "sg:province":"Nordrhein-Westfalen",
    "wof:name":"Webster Messtechnik",
    "wof:placetype":"venue"
},
  "geometry": {"coordinates":[7.4315347672,51.4906730652],"type":"Point"}
}