{
  "type": "Feature",
  "properties": {
    "iso:country":"DE",
    "sg:address":"Sonnenburger Str. 12",
    "sg:city":"Bad Freienwalde",
    "sg:phone":"+49 3344/2521",
    "sg:postcode":"16259",
    "sg:province":"Brandenburg",
    "wof:name":"Pension Wolfgang Schulz",
    "wof:placetype":"venue"
},
  "geometry": {"coordinates":[14.0733194351,52.7651062012],"type":"Point"}
}