{
  "type": "Feature",
  "properties": {
    "iso:country":"DE",
    "sg:address":"Freier-Grund-Str. 73",
    "sg:city":"Burbach",
    "sg:phone":"+49 2736/5452",
    "sg:postcode":"57299",
    "sg:province":"Nordrhein-Westfalen",
    "wof:name":"Athen",
    "wof:placetype":"venue"
},
  "geometry": {"coordinates":[8.0558595657,50.7580413818],"type":"Point"}
}