{
  "type": "Feature",
  "properties": {
    "iso:country":"DE",
    "sg:address":"Schuknechtstr. 1",
    "sg:city":"Darmstadt",
    "sg:postcode":"64289",
    "sg:province":"Hessen",
    "wof:name":"Multifone Communication Gmbh",
    "wof:placetype":"venue"
},
  "geometry": {"coordinates":[8.654991,49.880836],"type":"Point"}
}