{
  "type": "Feature",
  "properties": {
    "iso:country":"DE",
    "sg:address":"Paderborner Str. 60",
    "sg:city":"Borchen",
    "sg:phone":"+49 5251/399828",
    "sg:postcode":"33178",
    "sg:province":"Nordrhein-Westfalen",
    "wof:name":"Eva-maria Bertels Rechtsanw\u00e4ltin",
    "wof:placetype":"venue"
},
  "geometry": {"coordinates":[8.7244997025,51.6718788147],"type":"Point"}
}