{
  "type": "Feature",
  "properties": {
    "iso:country":"DE",
    "sg:address":"Alte Holstenstr. 54",
    "sg:city":"Hamburg",
    "sg:phone":"+49 40/7242380",
    "sg:postcode":"21029",
    "sg:province":"Hamburg",
    "wof:name":"China-restaurant Zum Gl\u00fcckshaus",
    "wof:placetype":"venue"
},
  "geometry": {"coordinates":[10.2084751129,53.49036026],"type":"Point"}
}