{
  "type": "Feature",
  "properties": {
    "iso:country":"DE",
    "sg:address":"Roseggerstr. 7",
    "sg:city":"M\u00fcnchen",
    "sg:postcode":"81245",
    "sg:province":"Bayern",
    "wof:name":"Wolfgang Spanier",
    "wof:placetype":"venue"
},
  "geometry": {"coordinates":[11.4718570709,48.1484947205],"type":"Point"}
}