{
  "type": "Feature",
  "properties": {
    "iso:country":"DE",
    "sg:address":"Bamenohler Str. 58",
    "sg:city":"Finnentrop",
    "sg:postcode":"57413",
    "sg:province":"Nordrhein-Westfalen",
    "wof:name":"N & F Bau Gmbh",
    "wof:placetype":"venue"
},
  "geometry": {"coordinates":[7.9841489792,51.1655654907],"type":"Point"}
}