{
  "type": "Feature",
  "properties": {
    "iso:country":"DE",
    "sg:address":"T\u00fcbinger Str. 102 /1",
    "sg:city":"Reutlingen",
    "sg:phone":"+49 7121/337363",
    "sg:postcode":"72762",
    "sg:province":"Baden-W\u00fcrttemberg",
    "wof:name":"Restaurant Schneckenh\u00e4usle",
    "wof:placetype":"venue"
},
  "geometry": {"coordinates":[9.194601059,48.4951171875],"type":"Point"}
}