{
  "type": "Feature",
  "properties": {
    "iso:country":"DE",
    "sg:address":"Auf Dem Sande 26",
    "sg:city":"Lage",
    "sg:phone":"+49 4952/3295970",
    "sg:postcode":"32791",
    "sg:province":"Nordrhein-Westfalen",
    "wof:name":"Epoca Holzbearbeitung Gmbh & Co.kg",
    "wof:placetype":"venue"
},
  "geometry": {"coordinates":[8.748705864,52.0204467773],"type":"Point"}
}