{
  "type": "Feature",
  "properties": {
    "iso:country":"DE",
    "sg:address":"Frankenstr. 278",
    "sg:city":"Essen",
    "sg:phone":"+49 201/444411",
    "sg:postcode":"45134",
    "sg:province":"Nordrhein-Westfalen",
    "wof:name":"Eiscafe Renzo Betori",
    "wof:placetype":"venue"
},
  "geometry": {"coordinates":[7.024804,51.420479],"type":"Point"}
}