{
  "type": "Feature",
  "properties": {
    "iso:country":"DE",
    "sg:address":"Eckeseyer Str. 101",
    "sg:city":"Hagen",
    "sg:phone":"+49 2331/125850",
    "sg:postcode":"58089",
    "sg:province":"Nordrhein-Westfalen",
    "wof:name":"Gerhard Bultink Gmbh",
    "wof:placetype":"venue"
},
  "geometry": {"coordinates":[7.45548,51.375114],"type":"Point"}
}