{
  "type": "Feature",
  "properties": {
    "iso:country":"DE",
    "sg:address":"Badstr. 35",
    "sg:city":"Waldshut-Tiengen",
    "sg:phone":"+49 7741/63808",
    "sg:postcode":"79761",
    "sg:province":"Baden-W\u00fcrttemberg",
    "wof:name":"Badische Staatsbrauerei Rothaus Ag",
    "wof:placetype":"venue"
},
  "geometry": {"coordinates":[8.260993,47.627964],"type":"Point"}
}