{
  "type": "Feature",
  "properties": {
    "iso:country":"DE",
    "sg:address":"Auf der Gr\u00fcn 30",
    "sg:city":"Miesbach",
    "sg:phone":"+49 8025/3519",
    "sg:postcode":"83714",
    "sg:province":"Bayern",
    "wof:name":"Stefan Lander",
    "wof:placetype":"venue"
},
  "geometry": {"coordinates":[11.823748,47.791912],"type":"Point"}
}