{
  "type": "Feature",
  "properties": {
    "iso:country":"DE",
    "sg:address":"Karlstr. 15",
    "sg:city":"Horb",
    "sg:phone":"+49 7486/9434",
    "sg:postcode":"72160",
    "sg:province":"Baden-W\u00fcrttemberg",
    "wof:name":"Casablanca Filmproduktion",
    "wof:placetype":"venue"
},
  "geometry": {"coordinates":[8.6572179794,48.4880065918],"type":"Point"}
}