{
  "type": "Feature",
  "properties": {
    "iso:country":"DE",
    "sg:address":"Strontianitstr 25",
    "sg:city":"Ahlen",
    "sg:phone":"+49 2528/1818",
    "sg:postcode":"59227",
    "sg:province":"Nordrhein-Westfalen",
    "wof:name":"Wevo L\u00f6sungen Aus Draht",
    "wof:placetype":"venue"
},
  "geometry": {"coordinates":[7.95923,51.791363],"type":"Point"}
}