{
  "type": "Feature",
  "properties": {
    "iso:country":"DE",
    "sg:address":"Arnoldusstr. 5 a",
    "sg:city":"Gilching",
    "sg:postcode":"82205",
    "sg:province":"Bayern",
    "wof:name":"Vishesella - Werbeartikel- Und Verpackungsproduktions Kg",
    "wof:placetype":"venue"
},
  "geometry": {"coordinates":[11.2999076843,48.1078071594],"type":"Point"}
}