{
  "type": "Feature",
  "properties": {
    "iso:country":"DE",
    "sg:address":"Leonhard-Eckel-Siedlung",
    "sg:city":"Edesheim",
    "sg:phone":"+49 6323/2370",
    "sg:postcode":"67483",
    "sg:province":"Rheinland-Pfalz",
    "wof:name":"Poth Metallwaren Gmbh",
    "wof:placetype":"venue"
},
  "geometry": {"coordinates":[8.10886,49.256405],"type":"Point"}
}