{
  "type": "Feature",
  "properties": {
    "iso:country":"DE",
    "sg:address":"Stralauer Allee 23a",
    "sg:city":"Berlin",
    "sg:phone":"+49 30/2917511",
    "sg:postcode":"10245",
    "sg:province":"Berlin",
    "wof:name":"Tobias Morgenstern",
    "wof:placetype":"venue"
},
  "geometry": {"coordinates":[13.4586763382,52.4994506836],"type":"Point"}
}