{
  "type": "Feature",
  "properties": {
    "iso:country":"DE",
    "sg:address":"Opelstr. 12-63",
    "sg:city":"Kaiserslautern",
    "sg:phone":"+49 6301/713910",
    "sg:postcode":"67661",
    "sg:province":"Rheinland-Pfalz",
    "wof:name":"Karom Ges.z.veredelung Von Geruchs- U.geschmack -",
    "wof:placetype":"venue"
},
  "geometry": {"coordinates":[7.6930828094,49.463432312],"type":"Point"}
}