{
  "type": "Feature",
  "properties": {
    "iso:country":"DE",
    "sg:address":"Pfarrstr. 2",
    "sg:city":"Marktl",
    "sg:phone":"+49 8678/236",
    "sg:postcode":"84533",
    "sg:province":"Bayern",
    "wof:name":"F. Alber",
    "wof:placetype":"venue"
},
  "geometry": {"coordinates":[12.8421421051,48.253780365],"type":"Point"}
}