{
  "type": "Feature",
  "properties": {
    "iso:country":"DE",
    "sg:address":"Schule Moos",
    "sg:city":"Moos",
    "sg:postcode":"94554",
    "sg:province":"Bayern",
    "wof:name":"Mehrzweckhalle Kurzenisarhofen",
    "wof:placetype":"venue"
},
  "geometry": {"coordinates":[12.959748,48.74575],"type":"Point"}
}