{
  "type": "Feature",
  "properties": {
    "iso:country":"DE",
    "sg:address":"Bergstr 4-6",
    "sg:city":"Haan",
    "sg:phone":"+49 2104/60236",
    "sg:postcode":"42781",
    "sg:province":"Nordrhein-Westfalen",
    "wof:name":"Plissee-endrix",
    "wof:placetype":"venue"
},
  "geometry": {"coordinates":[7.0121979713,51.2139205933],"type":"Point"}
}