{
  "type": "Feature",
  "properties": {
    "iso:country":"DE",
    "sg:address":"\u00d6sterstr. 11-13",
    "sg:city":"Meldorf",
    "sg:phone":"+49 4832/7071",
    "sg:postcode":"25704",
    "sg:province":"Schleswig-Holstein",
    "wof:name":"Schillhorn Kg",
    "wof:placetype":"venue"
},
  "geometry": {"coordinates":[9.0800285339,54.0890197754],"type":"Point"}
}