{
  "type": "Feature",
  "properties": {
    "iso:country":"DE",
    "sg:address":"Am Waldrand 26",
    "sg:city":"M\u00fcnchen",
    "sg:phone":"+49 89/7191938",
    "sg:postcode":"81377",
    "sg:province":"Bayern",
    "wof:name":"Ms Hausverwaltungs-gmbh",
    "wof:placetype":"venue"
},
  "geometry": {"coordinates":[11.4835567474,48.1068191528],"type":"Point"}
}