{
  "type": "Feature",
  "properties": {
    "iso:country":"DE",
    "sg:address":"Lerchenfeldstr. 15",
    "sg:city":"Halle",
    "sg:phone":"+49 345/2900360",
    "sg:postcode":"06110",
    "sg:province":"Sachsen-Anhalt",
    "wof:name":"Procon M Mietgesellschaft Mbh",
    "wof:placetype":"venue"
},
  "geometry": {"coordinates":[11.9641056061,51.47448349],"type":"Point"}
}