{
  "type": "Feature",
  "properties": {
    "iso:country":"DE",
    "sg:address":"Lindemannstr. 12",
    "sg:city":"Dortmund",
    "sg:phone":"+49 231/7213583",
    "sg:postcode":"44137",
    "sg:province":"Nordrhein-Westfalen",
    "wof:name":"B\u00fcrgermeister Lindemann",
    "wof:placetype":"venue"
},
  "geometry": {"coordinates":[7.4513268471,51.5056266785],"type":"Point"}
}