{
  "type": "Feature",
  "properties": {
    "iso:country":"DE",
    "sg:address":"Neue Str. 12",
    "sg:city":"Lichtenhain",
    "sg:phone":"+49 35971/7490",
    "sg:postcode":"01855",
    "sg:province":"Sachsen",
    "wof:name":"R. Lehmann",
    "wof:placetype":"venue"
},
  "geometry": {"coordinates":[14.2367191315,50.9457168579],"type":"Point"}
}