{
  "type": "Feature",
  "properties": {
    "iso:country":"DE",
    "sg:address":"Adolphstrasse 101a",
    "sg:city":"Gro\u00dfr\u00f6hrsdorf",
    "sg:phone":"+49 35952",
    "sg:postcode":"01900",
    "sg:province":"Sachsen",
    "wof:name":"Tief Und Landschaftsbau Gmbh",
    "wof:placetype":"venue"
},
  "geometry": {"coordinates":[14.029686,51.134556],"type":"Point"}
}