{
  "type": "Feature",
  "properties": {
    "iso:country":"DE",
    "sg:address":"Gro\u00df Orden 1",
    "sg:city":"Quedlinburg",
    "sg:postcode":"06484",
    "sg:province":"Sachsen-Anhalt",
    "wof:name":"Hs Quedlinburg Gmbh",
    "wof:placetype":"venue"
},
  "geometry": {"coordinates":[11.1776399612,51.7952003479],"type":"Point"}
}