{
  "type": "Feature",
  "properties": {
    "iso:country":"DE",
    "sg:address":"Am Mu\u00dfriedegraben 6",
    "sg:city":"Nienburg",
    "sg:phone":"+49 5021/62011",
    "sg:postcode":"31582",
    "sg:province":"Niedersachsen",
    "wof:name":"Siegfried Neumann",
    "wof:placetype":"venue"
},
  "geometry": {"coordinates":[9.2245874405,52.6538619995],"type":"Point"}
}