{
  "type": "Feature",
  "properties": {
    "iso:country":"DE",
    "sg:address":"Luboldtstr. 28",
    "sg:city":"Dresden",
    "sg:phone":"+49 351/2679838",
    "sg:postcode":"01324",
    "sg:province":"Sachsen",
    "wof:name":"Beate Dietrich",
    "wof:placetype":"venue"
},
  "geometry": {"coordinates":[13.8223619461,51.062953949],"type":"Point"}
}