{
  "type": "Feature",
  "properties": {
    "iso:country":"DE",
    "sg:address":"Koppel 78",
    "sg:city":"Hamburg",
    "sg:phone":"+49 40/249836",
    "sg:postcode":"20099",
    "sg:province":"Hamburg",
    "wof:name":"Alex Goergens Und Theel Rechtsanw\u00e4lte",
    "wof:placetype":"venue"
},
  "geometry": {"coordinates":[10.0118188858,53.5588874817],"type":"Point"}
}