{
  "type": "Feature",
  "properties": {
    "iso:country":"DE",
    "sg:address":"D\u00fcrener Str. 57",
    "sg:city":"Eschweiler",
    "sg:phone":"+49 2403/800521",
    "sg:postcode":"52249",
    "sg:province":"Nordrhein-Westfalen",
    "wof:name":"Herzog",
    "wof:placetype":"venue"
},
  "geometry": {"coordinates":[6.2724018097,50.8190917969],"type":"Point"}
}