{
  "type": "Feature",
  "properties": {
    "iso:country":"DE",
    "sg:address":"Maurerstr. 6",
    "sg:city":"Isernhagen",
    "sg:phone":"+49 5136/879440",
    "sg:postcode":"30916",
    "sg:province":"Niedersachsen",
    "wof:name":"Afb Automobilumr\u00dcstungen F\u00dcrbehinderte Gmbh",
    "wof:placetype":"venue"
},
  "geometry": {"coordinates":[9.8798913956,52.4420814514],"type":"Point"}
}