{
  "type": "Feature",
  "properties": {
    "iso:country":"DE",
    "sg:address":"Ballindamm 26",
    "sg:city":"Hamburg",
    "sg:phone":"+49 40/3256240",
    "sg:postcode":"20095",
    "sg:province":"Hamburg",
    "wof:name":"Gbk Beteiligungen Ag",
    "wof:placetype":"venue"
},
  "geometry": {"coordinates":[9.99698,53.552979],"type":"Point"}
}