{
  "type": "Feature",
  "properties": {
    "iso:country":"DE",
    "sg:address":"Mainburger Str. 1",
    "sg:city":"Elsendorf",
    "sg:phone":"+49 8753/245",
    "sg:postcode":"84094",
    "sg:province":"Bayern",
    "wof:name":"Kath. Pfarramt Maria-unbefl. Empf.",
    "wof:placetype":"venue"
},
  "geometry": {"coordinates":[11.8086042404,48.7089042664],"type":"Point"}
}