{
  "type": "Feature",
  "properties": {
    "iso:country":"DE",
    "sg:address":"Bermestr. 73",
    "sg:city":"M\u00fcnster",
    "sg:phone":"+49 2506/2734",
    "sg:postcode":"48167",
    "sg:province":"Nordrhein-Westfalen",
    "wof:name":"Volker Schl\u00fcter Und Peter Dier",
    "wof:placetype":"venue"
},
  "geometry": {"coordinates":[7.716237,51.913754],"type":"Point"}
}