{
  "type": "Feature",
  "properties": {
    "iso:country":"DE",
    "sg:address":"Hauptstra\u00dfe 79",
    "sg:city":"Wingerode",
    "sg:phone":"+49 3605/502609",
    "sg:postcode":"37327",
    "sg:province":"Th\u00fcringen",
    "wof:name":"Cwm Flightcases",
    "wof:placetype":"venue"
},
  "geometry": {"coordinates":[10.23848,51.391624],"type":"Point"}
}