{
  "type": "Feature",
  "properties": {
    "iso:country":"DE",
    "sg:address":"Stra\u00dfe des Friedens 50 b",
    "sg:city":"Zschornewitz",
    "sg:phone":"+49 34953/88578",
    "sg:postcode":"06791",
    "sg:province":"Sachsen-Anhalt",
    "wof:name":"E. Quinque",
    "wof:placetype":"venue"
},
  "geometry": {"coordinates":[12.4059085846,51.7153015137],"type":"Point"}
}