{
  "type": "Feature",
  "properties": {
    "iso:country":"DE",
    "sg:address":"Hundsm\u00fchler Str 161a",
    "sg:city":"Oldenburg",
    "sg:phone":"+49 441/5040011",
    "sg:postcode":"26131",
    "sg:province":"Niedersachsen",
    "wof:name":"Havekost & A\u00dfmann Datensysteme Gmbh",
    "wof:placetype":"venue"
},
  "geometry": {"coordinates":[8.1915416718,53.1169242859],"type":"Point"}
}