{
  "type": "Feature",
  "properties": {
    "iso:country":"DE",
    "sg:address":"Salegaster Chaussee 3",
    "sg:city":"Greppin",
    "sg:postcode":"06803",
    "sg:province":"Sachsen-Anhalt",
    "wof:name":"Kesla Forschung Und Service Kg",
    "wof:placetype":"venue"
},
  "geometry": {"coordinates":[12.2988157272,51.6540641785],"type":"Point"}
}