{
  "type": "Feature",
  "properties": {
    "iso:country":"DE",
    "sg:address":"Wormser Landstr. 129",
    "sg:city":"Worms",
    "sg:phone":"+49 6241/935290",
    "sg:postcode":"67551",
    "sg:province":"Rheinland-Pfalz",
    "wof:name":"Ulrich Gerhardt",
    "wof:placetype":"venue"
},
  "geometry": {"coordinates":[8.275448,49.607887],"type":"Point"}
}