{
  "type": "Feature",
  "properties": {
    "iso:country":"DE",
    "sg:address":"Sch\u00e4ferweg 17",
    "sg:city":"Reinheim",
    "sg:postcode":"64354",
    "sg:province":"Hessen",
    "wof:name":"Meito H\u00e4hnchen Grill Station Gmbh",
    "wof:placetype":"venue"
},
  "geometry": {"coordinates":[8.840026,49.83522],"type":"Point"}
}