{
  "type": "Feature",
  "properties": {
    "iso:country":"DE",
    "sg:address":"Gro\u00dfenhainer Str. 39",
    "sg:city":"Elsterwerda",
    "sg:phone":"+49 3533/4226",
    "sg:postcode":"04910",
    "sg:province":"Brandenburg",
    "wof:name":"A. Fuchs",
    "wof:placetype":"venue"
},
  "geometry": {"coordinates":[13.5207414627,51.4498672485],"type":"Point"}
}