{
  "type": "Feature",
  "properties": {
    "iso:country":"DE",
    "sg:address":"Max-Steenebck-Str. 46",
    "sg:city":"Jena",
    "sg:phone":"+49 3641/617820",
    "sg:postcode":"07745",
    "sg:province":"Th\u00fcringen",
    "wof:name":"Interactiv Webdesign Und Internetmarketing Jena G.b.r.",
    "wof:placetype":"venue"
},
  "geometry": {"coordinates":[11.5776720047,50.9003486633],"type":"Point"}
}