{
  "type": "Feature",
  "properties": {
    "iso:country":"DE",
    "sg:address":"Blumenthalstr. 31",
    "sg:city":"Rieden",
    "sg:phone":"+49 9624/2383",
    "sg:postcode":"92286",
    "sg:province":"Bayern",
    "wof:name":"Paul Albert",
    "wof:placetype":"venue"
},
  "geometry": {"coordinates":[11.9399299622,49.3245201111],"type":"Point"}
}