{
  "type": "Feature",
  "properties": {
    "iso:country":"DE",
    "sg:address":"Weinstr. 4",
    "sg:city":"Bad Hersfeld",
    "sg:postcode":"36251",
    "sg:province":"Hessen",
    "wof:name":"Franz Geist Ihr H\u00f6rger\u00e4te-berater",
    "wof:placetype":"venue"
},
  "geometry": {"coordinates":[9.7067108154,50.8679733276],"type":"Point"}
}