{
  "type": "Feature",
  "properties": {
    "iso:country":"DE",
    "sg:address":"Surenburger Str. 28",
    "sg:city":"H\u00f6rstel 2",
    "sg:phone":"+49 5454/408",
    "sg:postcode":"48477",
    "sg:province":"Nordrhein-Westfalen",
    "wof:name":"Mvm-consulting",
    "wof:placetype":"venue"
},
  "geometry": {"coordinates":[7.61997509,52.2599220276],"type":"Point"}
}