{
  "type": "Feature",
  "properties": {
    "iso:country":"DE",
    "sg:address":"Hauptstr. 66",
    "sg:city":"Warstein",
    "sg:phone":"+49 2902/920200",
    "sg:postcode":"59581",
    "sg:province":"Nordrhein-Westfalen",
    "wof:name":"Budeus Gmbh",
    "wof:placetype":"venue"
},
  "geometry": {"coordinates":[8.3543434143,51.4446334839],"type":"Point"}
}