{
  "type": "Feature",
  "properties": {
    "iso:country":"DE",
    "sg:address":"Tannenhofstr. 71 a",
    "sg:city":"Norderstedt",
    "sg:phone":"+49 40/5235168",
    "sg:postcode":"22848",
    "sg:province":"Schleswig-Holstein",
    "wof:name":"Willi Schmidt",
    "wof:placetype":"venue"
},
  "geometry": {"coordinates":[9.986998,53.677036],"type":"Point"}
}