{
  "type": "Feature",
  "properties": {
    "iso:country":"DE",
    "sg:address":"Bahnhofstr. 5",
    "sg:city":"Bodenw\u00f6hr",
    "sg:phone":"+49 9434/1379",
    "sg:postcode":"92439",
    "sg:province":"Bayern",
    "wof:name":"Blechhammer Am See Campingplatz",
    "wof:placetype":"venue"
},
  "geometry": {"coordinates":[12.328374,49.277061],"type":"Point"}
}