{
  "type": "Feature",
  "properties": {
    "iso:country":"DE",
    "sg:address":"Gr\u00f6perstr. 58",
    "sg:city":"Halberstadt",
    "sg:postcode":"38820",
    "sg:province":"Sachsen-Anhalt",
    "wof:name":"Jutt Computer",
    "wof:placetype":"venue"
},
  "geometry": {"coordinates":[11.0483980179,51.8995170593],"type":"Point"}
}