{
  "type": "Feature",
  "properties": {
    "iso:country":"DE",
    "sg:address":"Dompfaffenstr. 27a",
    "sg:city":"G\u00fctersloh",
    "sg:phone":"+49 5241/701787",
    "sg:postcode":"33335",
    "sg:province":"Nordrhein-Westfalen",
    "wof:name":"Diboa Borgsen Gmbh",
    "wof:placetype":"venue"
},
  "geometry": {"coordinates":[8.4502038956,51.9381027222],"type":"Point"}
}