{
  "type": "Feature",
  "properties": {
    "iso:country":"DE",
    "sg:address":"Bahnhofstr. 37",
    "sg:city":"K\u00f6tzschau",
    "sg:phone":"+49 3462/933327",
    "sg:postcode":"06231",
    "sg:province":"Sachsen-Anhalt",
    "wof:name":"Hotline-full-service Telekommunikation Gmbh",
    "wof:placetype":"venue"
},
  "geometry": {"coordinates":[12.1243200302,51.3093605042],"type":"Point"}
}