{
  "type": "Feature",
  "properties": {
    "iso:country":"DE",
    "sg:address":"Magdeburger Allee 134",
    "sg:city":"Erfurt",
    "sg:phone":"+49 361/6431727",
    "sg:postcode":"99086",
    "sg:province":"Th\u00fcringen",
    "wof:name":"Aib Architektur- Und Ingenieurb\u00fcro Gmbh",
    "wof:placetype":"venue"
},
  "geometry": {"coordinates":[11.026648,50.997452],"type":"Point"}
}