{
  "type": "Feature",
  "properties": {
    "iso:country":"DE",
    "sg:address":"Kohlgruber Str. 26",
    "sg:city":"Murnau",
    "sg:phone":"+49 8841/9178",
    "sg:postcode":"82418",
    "sg:province":"Bayern",
    "wof:name":"Trattoria Italiana",
    "wof:placetype":"venue"
},
  "geometry": {"coordinates":[11.1903829575,47.6759262085],"type":"Point"}
}