{
  "type": "Feature",
  "properties": {
    "iso:country":"DE",
    "sg:city":"Uelzen",
    "sg:phone":"+49 4958/142399",
    "sg:postcode":"29525",
    "sg:province":"Niedersachsen",
    "wof:name":"Volksbank Ostkreis Uelzen Eg",
    "wof:placetype":"venue"
},
  "geometry": {"coordinates":[10.560615,52.965576],"type":"Point"}
}