{
  "type": "Feature",
  "properties": {
    "iso:country":"DE",
    "sg:address":"Am Herrengarten 79",
    "sg:city":"Bonn",
    "sg:postcode":"53229",
    "sg:province":"Nordrhein-Westfalen",
    "wof:name":"Frank Burneleit E. K.",
    "wof:placetype":"venue"
},
  "geometry": {"coordinates":[7.1494250298,50.7523078918],"type":"Point"}
}