{
  "type": "Feature",
  "properties": {
    "iso:country":"DE",
    "sg:address":"Daensstr. 25 a",
    "sg:city":"Stolberg",
    "sg:phone":"+49 2409/1317",
    "sg:postcode":"52224",
    "sg:province":"Nordrhein-Westfalen",
    "wof:name":"Jutta Stiel",
    "wof:placetype":"venue"
},
  "geometry": {"coordinates":[6.28311,50.736809],"type":"Point"}
}