{
  "type": "Feature",
  "properties": {
    "iso:country":"DE",
    "sg:address":"Goethestr. 44",
    "sg:city":"Prenzlau",
    "sg:phone":"+49 3984/4873",
    "sg:postcode":"17291",
    "sg:province":"Brandenburg",
    "wof:name":"Lutz Krasemann Ingenieur",
    "wof:placetype":"venue"
},
  "geometry": {"coordinates":[13.8702936172,53.3029289246],"type":"Point"}
}