{
  "type": "Feature",
  "properties": {
    "iso:country":"DE",
    "sg:address":"Meitzer Str. 15",
    "sg:city":"Wedemark",
    "sg:phone":"+49 5130/40905",
    "sg:postcode":"30900",
    "sg:province":"Niedersachsen",
    "wof:name":"Restaurant Forellenst\u00fcbchen",
    "wof:placetype":"venue"
},
  "geometry": {"coordinates":[9.7981996536,52.564781189],"type":"Point"}
}