{
  "type": "Feature",
  "properties": {
    "iso:country":"DE",
    "sg:address":"H\u00f6rmannshofen",
    "sg:city":"Biessenhofen",
    "sg:phone":"+49 8341/81968",
    "sg:postcode":"87640",
    "sg:province":"Bayern",
    "wof:name":"Traube",
    "wof:placetype":"venue"
},
  "geometry": {"coordinates":[10.6407632828,47.8328170776],"type":"Point"}
}