{
  "type": "Feature",
  "properties": {
    "iso:country":"DE",
    "sg:address":"Bielefelder Str. 29",
    "sg:city":"Borgholzhausen",
    "sg:phone":"+49 5425/5345",
    "sg:postcode":"33829",
    "sg:province":"Nordrhein-Westfalen",
    "wof:name":"Werner Garlich",
    "wof:placetype":"venue"
},
  "geometry": {"coordinates":[8.3080940247,52.1073417664],"type":"Point"}
}