{
  "type": "Feature",
  "properties": {
    "iso:country":"DE",
    "sg:address":"Wittstocker Str. 6",
    "sg:city":"Flecken Zechlin",
    "sg:phone":"+49 33923/201",
    "sg:postcode":"16837",
    "sg:province":"Brandenburg",
    "wof:name":"Kreissparkasse Neuruppin",
    "wof:placetype":"venue"
},
  "geometry": {"coordinates":[12.765669,53.158173],"type":"Point"}
}