{
  "type": "Feature",
  "properties": {
    "iso:country":"DE",
    "sg:address":"Johannisstra\u00dfe 64",
    "sg:city":"Zschopau",
    "sg:phone":"+49 3725/35060",
    "sg:postcode":"09405",
    "sg:province":"Sachsen",
    "wof:name":"Satron Sachsen Gmbh",
    "wof:placetype":"venue"
},
  "geometry": {"coordinates":[13.0686283112,50.7452049255],"type":"Point"}
}