{
  "type": "Feature",
  "properties": {
    "iso:country":"DE",
    "sg:address":"Lotharpassage 10",
    "sg:city":"Mainz",
    "sg:phone":"+49 6131/223598",
    "sg:postcode":"55116",
    "sg:province":"Rheinland-Pfalz",
    "wof:name":"Fischgastst\u00e4tten Brauns & Co.",
    "wof:placetype":"venue"
},
  "geometry": {"coordinates":[8.2672271729,50.0017204285],"type":"Point"}
}