{
  "type": "Feature",
  "properties": {
    "iso:country":"DE",
    "sg:address":"M\u00fchlenstr. 4",
    "sg:city":"Winsen",
    "sg:phone":"+49 4171/62397",
    "sg:postcode":"21423",
    "sg:province":"Niedersachsen",
    "wof:name":"K. Probst",
    "wof:placetype":"venue"
},
  "geometry": {"coordinates":[10.203579,53.363811],"type":"Point"}
}