{
  "type": "Feature",
  "properties": {
    "iso:country":"DE",
    "sg:address":"Obere Wiesener Str. 18",
    "sg:city":"Kirchberg",
    "sg:postcode":"08107",
    "sg:province":"Sachsen",
    "wof:name":"Land- Forst- U. Gartentechnik",
    "wof:placetype":"venue"
},
  "geometry": {"coordinates":[12.5262,50.62846],"type":"Point"}
}