{
  "type": "Feature",
  "properties": {
    "iso:country":"DE",
    "sg:address":"Markt 3",
    "sg:city":"Ro\u00dfwein",
    "sg:phone":"+49 34322/42425",
    "sg:postcode":"04741",
    "sg:province":"Sachsen",
    "wof:name":"Hotel Herkules",
    "wof:placetype":"venue"
},
  "geometry": {"coordinates":[13.1846246719,51.0649337769],"type":"Point"}
}