{
  "type": "Feature",
  "properties": {
    "iso:country":"DE",
    "sg:address":"Wiemelhauser Str. 414",
    "sg:city":"Bochum",
    "sg:phone":"+49 234/72175",
    "sg:postcode":"44799",
    "sg:province":"Nordrhein-Westfalen",
    "wof:name":"Restaurant Don Quijote",
    "wof:placetype":"venue"
},
  "geometry": {"coordinates":[7.2286658287,51.4484214783],"type":"Point"}
}