{
  "type": "Feature",
  "properties": {
    "iso:country":"DE",
    "sg:address":"Am S\u00fcdhang 12",
    "sg:city":"Isterberg",
    "sg:phone":"+49 5922/6866",
    "sg:postcode":"48465",
    "sg:province":"Niedersachsen",
    "wof:name":"Isterberger Waldcafe",
    "wof:placetype":"venue"
},
  "geometry": {"coordinates":[7.146501,52.352757],"type":"Point"}
}