{
  "type": "Feature",
  "properties": {
    "iso:country":"DE",
    "sg:address":"Fredersdorfer Str. 15",
    "sg:city":"Berlin",
    "sg:phone":"+49 30/2961646",
    "sg:postcode":"10243",
    "sg:province":"Berlin",
    "wof:name":"Kerstin Nawroth",
    "wof:placetype":"venue"
},
  "geometry": {"coordinates":[13.443306,52.514717],"type":"Point"}
}