{
  "type": "Feature",
  "properties": {
    "iso:country":"DE",
    "sg:address":"Friedrich-Naumann-Str. 55",
    "sg:city":"Reutlingen",
    "sg:phone":"+49 4971/2126830",
    "sg:postcode":"72762",
    "sg:province":"Baden-W\u00fcrttemberg",
    "wof:name":"Albert Mayer",
    "wof:placetype":"venue"
},
  "geometry": {"coordinates":[9.193441391,48.485824585],"type":"Point"}
}