{
  "type": "Feature",
  "properties": {
    "iso:country":"DE",
    "sg:address":"Gro\u00dfaigner Str.",
    "sg:city":"Eschlkam",
    "sg:phone":"+49 9948/293",
    "sg:postcode":"93458",
    "sg:province":"Bayern",
    "wof:name":"J. Neumeier",
    "wof:placetype":"venue"
},
  "geometry": {"coordinates":[12.9169874191,49.3012199402],"type":"Point"}
}