{
  "type": "Feature",
  "properties": {
    "iso:country":"DE",
    "sg:address":"Heinz-Sommer-Weg 47",
    "sg:city":"Magdeburg",
    "sg:phone":"+49 391/737600",
    "sg:postcode":"39120",
    "sg:province":"Sachsen-Anhalt",
    "wof:name":"Ingenieur-b\u00fcro Klaus Bolle",
    "wof:placetype":"venue"
},
  "geometry": {"coordinates":[11.635028,52.092178],"type":"Point"}
}