{
  "type": "Feature",
  "properties": {
    "iso:country":"DE",
    "sg:address":"Mainzer-Tor-Weg 20",
    "sg:city":"Friedberg",
    "sg:phone":"+49 6032/73207",
    "sg:postcode":"61169",
    "sg:province":"Hessen",
    "wof:name":"Hks Gesellschaft F\u00fcr Arbeitssicherheit Mbh",
    "wof:placetype":"venue"
},
  "geometry": {"coordinates":[8.753503,50.329304],"type":"Point"}
}