{
  "type": "Feature",
  "properties": {
    "iso:country":"DE",
    "sg:address":"Eibischstr. 9",
    "sg:city":"Berlin",
    "sg:phone":"+49 30/6617939",
    "sg:postcode":"12357",
    "sg:province":"Berlin",
    "wof:name":"Schmidt",
    "wof:placetype":"venue"
},
  "geometry": {"coordinates":[13.4977493286,52.4265022278],"type":"Point"}
}