{
  "type": "Feature",
  "properties": {
    "iso:country":"DE",
    "sg:address":"Postfach 2146",
    "sg:city":"M\u00fchlhausen",
    "sg:phone":"+49 6222/63252",
    "sg:postcode":"69240",
    "sg:province":"Baden-W\u00fcrttemberg",
    "wof:name":"Kath. \u00f6ffentl. Bibliothek St. C\u00e4cilia",
    "wof:placetype":"venue"
},
  "geometry": {"coordinates":[8.722712,49.249538],"type":"Point"}
}