{
  "type": "Feature",
  "properties": {
    "iso:country":"DE",
    "sg:address":"Hauptstr. 42",
    "sg:city":"Herbolzheim",
    "sg:phone":"+49 7643/370",
    "sg:postcode":"79336",
    "sg:province":"Baden-W\u00fcrttemberg",
    "wof:name":"Ulmer Inhaber Christoph Ulmer E. K.",
    "wof:placetype":"venue"
},
  "geometry": {"coordinates":[7.777341,48.221741],"type":"Point"}
}