{
  "type": "Feature",
  "properties": {
    "iso:country":"DE",
    "sg:address":"Hauptstr. 25",
    "sg:city":"Mudau",
    "sg:phone":"+49 6284/92110",
    "sg:postcode":"69427",
    "sg:province":"Baden-W\u00fcrttemberg",
    "wof:name":"L\u00f6wen Gastst\u00e4tte",
    "wof:placetype":"venue"
},
  "geometry": {"coordinates":[9.2057743073,49.5335922241],"type":"Point"}
}