{
  "type": "Feature",
  "properties": {
    "iso:country":"DE",
    "sg:address":"Methweg 18",
    "sg:city":"K\u00f6ln",
    "sg:phone":"+49 221/174360",
    "sg:postcode":"50823",
    "sg:province":"Nordrhein-Westfalen",
    "wof:name":"Hanns Stiel",
    "wof:placetype":"venue"
},
  "geometry": {"coordinates":[6.9359941483,50.9586448669],"type":"Point"}
}