{
  "type": "Feature",
  "properties": {
    "iso:country":"DE",
    "sg:address":"Hofackerstr. 3",
    "sg:city":"Baden-Baden",
    "sg:phone":"+49 7221/968640",
    "sg:postcode":"76532",
    "sg:province":"Baden-W\u00fcrttemberg",
    "wof:name":"Areal Concept Eberhard Schmitz E. K.",
    "wof:placetype":"venue"
},
  "geometry": {"coordinates":[8.223503,48.774956],"type":"Point"}
}