{
  "type": "Feature",
  "properties": {
    "iso:country":"DE",
    "sg:address":"Dorfstra\u00dfe 18",
    "sg:city":"Werther",
    "sg:postcode":"99735",
    "sg:province":"Th\u00fcringen",
    "wof:name":"Peter, Friedrich",
    "wof:placetype":"venue"
},
  "geometry": {"coordinates":[10.7458200455,51.4680595398],"type":"Point"}
}