{
  "type": "Feature",
  "properties": {
    "iso:country":"DE",
    "sg:address":"Rudolfstr. 11",
    "sg:city":"Pforzheim",
    "sg:phone":"+49 7231/351475",
    "sg:postcode":"75177",
    "sg:province":"Baden-W\u00fcrttemberg",
    "wof:name":"Hotel Garni Pension Marlock",
    "wof:placetype":"venue"
},
  "geometry": {"coordinates":[8.6989173889,48.8952293396],"type":"Point"}
}