{
  "type": "Feature",
  "properties": {
    "iso:country":"DE",
    "sg:address":"Lange Str. 11",
    "sg:city":"B\u00fcckeburg",
    "sg:phone":"+49 5722/24545",
    "sg:postcode":"31675",
    "sg:province":"Niedersachsen",
    "wof:name":"Knop-wanninger",
    "wof:placetype":"venue"
},
  "geometry": {"coordinates":[9.049926,52.260216],"type":"Point"}
}