{
  "type": "Feature",
  "properties": {
    "iso:country":"DE",
    "sg:address":"Zerbster Str. 20",
    "sg:city":"Dessau",
    "sg:phone":"+49 340/2211996",
    "sg:postcode":"06844",
    "sg:province":"Sachsen-Anhalt",
    "wof:name":"C. Und F. Lehmann",
    "wof:placetype":"venue"
},
  "geometry": {"coordinates":[12.246832,51.836418],"type":"Point"}
}