{
  "type": "Feature",
  "properties": {
    "iso:country":"DE",
    "sg:address":"Robert-Koch-Str. 10",
    "sg:city":"Frankenthal",
    "sg:phone":"+49 6233/68741",
    "sg:postcode":"67227",
    "sg:province":"Rheinland-Pfalz",
    "wof:name":"Erich Oberling",
    "wof:placetype":"venue"
},
  "geometry": {"coordinates":[8.3648433685,49.538974762],"type":"Point"}
}