{
  "type": "Feature",
  "properties": {
    "iso:country":"DE",
    "sg:address":"Hochriesstr. 7",
    "sg:city":"Prien",
    "sg:phone":"+49 8051/5063",
    "sg:postcode":"83209",
    "sg:province":"Bayern",
    "wof:name":"Siemens Nixdorf Informationssysteme Ag",
    "wof:placetype":"venue"
},
  "geometry": {"coordinates":[12.3469467163,47.8535194397],"type":"Point"}
}