{
  "type": "Feature",
  "properties": {
    "iso:country":"DE",
    "sg:address":"Hohlweg 1",
    "sg:city":"Ochtmersleben",
    "sg:phone":"+49 39206/50491",
    "sg:postcode":"39167",
    "sg:province":"Sachsen-Anhalt",
    "wof:name":"Georg Wipperm\u00fcller",
    "wof:placetype":"venue"
},
  "geometry": {"coordinates":[11.41329,52.157845],"type":"Point"}
}