{
  "type": "Feature",
  "properties": {
    "iso:country":"DE",
    "sg:address":"Loorweg 157 a",
    "sg:city":"K\u00f6ln",
    "sg:phone":"+49 2203/81118",
    "sg:postcode":"51143",
    "sg:province":"Nordrhein-Westfalen",
    "wof:name":"Rudolf Spalding",
    "wof:placetype":"venue"
},
  "geometry": {"coordinates":[7.0255498886,50.856338501],"type":"Point"}
}