{
  "type": "Feature",
  "properties": {
    "iso:country":"DE",
    "sg:address":"Industriestr. 3",
    "sg:city":"Kirchhundem",
    "sg:phone":"+49 2764/801",
    "sg:postcode":"57399",
    "sg:province":"Nordrhein-Westfalen",
    "wof:name":"Raiffeisen-warengenossenschaft Kichhundem Eg",
    "wof:placetype":"venue"
},
  "geometry": {"coordinates":[7.994463,51.038143],"type":"Point"}
}