{
  "type": "Feature",
  "properties": {
    "iso:country":"DE",
    "sg:address":"Zuschka 26",
    "sg:city":"Cottbus",
    "sg:phone":"+49 355/823660",
    "sg:postcode":"03044",
    "sg:province":"Brandenburg",
    "wof:name":"Lvm Versicherung",
    "wof:placetype":"venue"
},
  "geometry": {"coordinates":[14.3421010971,51.7849197388],"type":"Point"}
}