{
  "type": "Feature",
  "properties": {
    "iso:country":"DE",
    "sg:address":"Uhlandstr. 55",
    "sg:city":"Aichtal",
    "sg:phone":"+49 7127/50115",
    "sg:postcode":"72631",
    "sg:province":"Baden-W\u00fcrttemberg",
    "wof:name":"Hans Jansen",
    "wof:placetype":"venue"
},
  "geometry": {"coordinates":[9.250408,48.629704],"type":"Point"}
}