{
  "type": "Feature",
  "properties": {
    "iso:country":"DE",
    "sg:address":"Malchiner Str. 88",
    "sg:city":"Teterow",
    "sg:phone":"+49 3996/181890",
    "sg:postcode":"17166",
    "sg:province":"Mecklenburg-Vorpommern",
    "wof:name":"Restaurant Prellbock",
    "wof:placetype":"venue"
},
  "geometry": {"coordinates":[12.583609581,53.7695388794],"type":"Point"}
}