{
  "type": "Feature",
  "properties": {
    "iso:country":"DE",
    "sg:address":"Postfach 31 14 32",
    "sg:city":"Stuttgart",
    "sg:phone":"+49 177 4044245",
    "sg:postcode":"70474",
    "sg:province":"Baden-W\u00fcrttemberg",
    "wof:name":"Gisela\u00b4s Video - Club & Video - Verkauf",
    "wof:placetype":"venue"
},
  "geometry": {"coordinates":[9.180729866,48.7772216797],"type":"Point"}
}