{
  "type": "Feature",
  "properties": {
    "iso:country":"DE",
    "sg:address":"Vor der M\u00fchle 2",
    "sg:city":"Wedemark",
    "sg:postcode":"30900",
    "sg:province":"Niedersachsen",
    "wof:name":"K\u00e4hlig Beteiligungs- Gmbh",
    "wof:placetype":"venue"
},
  "geometry": {"coordinates":[9.68756,52.55751],"type":"Point"}
}