{
  "type": "Feature",
  "properties": {
    "iso:country":"DE",
    "sg:address":"Auerbacher Weg 25",
    "sg:city":"Elztal",
    "sg:phone":"+49 6261/2780",
    "sg:postcode":"74834",
    "sg:province":"Baden-W\u00fcrttemberg",
    "wof:name":"Gerhard Ganz",
    "wof:placetype":"venue"
},
  "geometry": {"coordinates":[9.194859,49.386444],"type":"Point"}
}