{
  "type": "Feature",
  "properties": {
    "iso:country":"DE",
    "sg:address":"Max-Pezold-Str. 2",
    "sg:city":"Frankenberg",
    "sg:phone":"+49 37206/3237",
    "sg:postcode":"09669",
    "sg:province":"Sachsen",
    "wof:name":"M. Bretfeld",
    "wof:placetype":"venue"
},
  "geometry": {"coordinates":[13.039374,50.91227],"type":"Point"}
}