{
  "type": "Feature",
  "properties": {
    "iso:country":"DE",
    "sg:address":"Roh\u00f6fe 37",
    "sg:city":"Achim",
    "sg:postcode":"28832",
    "sg:province":"Niedersachsen",
    "wof:name":"Bremische Ausbildungs- Initiative E. V.",
    "wof:placetype":"venue"
},
  "geometry": {"coordinates":[8.9671602249,53.0238189697],"type":"Point"}
}