{
  "type": "Feature",
  "properties": {
    "iso:country":"DE",
    "sg:address":"Lichtenfelser Str. 41",
    "sg:city":"Burgkunstadt",
    "sg:phone":"+49 9572/3626",
    "sg:postcode":"96224",
    "sg:province":"Bayern",
    "wof:name":"Ernst Sievert Und Dr. Wilhelm Sievert",
    "wof:placetype":"venue"
},
  "geometry": {"coordinates":[11.2433681488,50.1428451538],"type":"Point"}
}