{
  "type": "Feature",
  "properties": {
    "iso:country":"DE",
    "sg:address":"Franz-Schmidt-Str. 58",
    "sg:city":"Schildow",
    "sg:phone":"+49 33056/6160",
    "sg:postcode":"16552",
    "sg:province":"Brandenburg",
    "wof:name":"Havel Bau Gmbh",
    "wof:placetype":"venue"
},
  "geometry": {"coordinates":[13.36756,52.630459],"type":"Point"}
}