{
  "type": "Feature",
  "properties": {
    "iso:country":"DE",
    "sg:address":"Lohweg 1",
    "sg:city":"Bindlach",
    "sg:phone":"+49 9208/222",
    "sg:postcode":"95463",
    "sg:province":"Bayern",
    "wof:name":"Hans K\u00f6gel",
    "wof:placetype":"venue"
},
  "geometry": {"coordinates":[11.639932,49.999344],"type":"Point"}
}