{
  "type": "Feature",
  "properties": {
    "iso:country":"DE",
    "sg:address":"Rosengarten 27",
    "sg:city":"Mahlberg",
    "sg:postcode":"77972",
    "sg:province":"Baden-W\u00fcrttemberg",
    "wof:name":"Two In One Design Gmbh",
    "wof:placetype":"venue"
},
  "geometry": {"coordinates":[7.81404,48.289848],"type":"Point"}
}