{
  "type": "Feature",
  "properties": {
    "iso:country":"DE",
    "sg:address":"S\u00fcrther Hauptstr. 214",
    "sg:city":"K\u00f6ln",
    "sg:phone":"+49 2236/69905",
    "sg:postcode":"50999",
    "sg:province":"Nordrhein-Westfalen",
    "wof:name":"Peter Schielin Architekt",
    "wof:placetype":"venue"
},
  "geometry": {"coordinates":[7.021279,50.869011],"type":"Point"}
}