{
  "type": "Feature",
  "properties": {
    "iso:country":"DE",
    "sg:address":"Gustav-Rau-Str. 20",
    "sg:city":"Bietigheim-Bissingen",
    "sg:phone":"+49 7142/97490",
    "sg:postcode":"74321",
    "sg:province":"Baden-W\u00fcrttemberg",
    "wof:name":"Wagner Gmbh & Co. Kg",
    "wof:placetype":"venue"
},
  "geometry": {"coordinates":[9.148013,48.951271],"type":"Point"}
}