{
  "type": "Feature",
  "properties": {
    "iso:country":"DE",
    "sg:address":"Rebenhof",
    "sg:city":"Weinolsheim",
    "sg:phone":"+49 6249/7624",
    "sg:postcode":"55278",
    "sg:province":"Rheinland-Pfalz",
    "wof:name":"E. Schittler Weinanbau",
    "wof:placetype":"venue"
},
  "geometry": {"coordinates":[8.2649402618,49.8136558533],"type":"Point"}
}