{
  "type": "Feature",
  "properties": {
    "iso:country":"DE",
    "sg:address":"Erdmannh\u00e4user Str. 59",
    "sg:city":"Marbach",
    "sg:phone":"+49 7144/9020",
    "sg:postcode":"71672",
    "sg:province":"Baden-W\u00fcrttemberg",
    "wof:name":"Bbp Kunststoffwerk Marbach Baier Gmbh",
    "wof:placetype":"venue"
},
  "geometry": {"coordinates":[9.275619,48.941921],"type":"Point"}
}