{
  "type": "Feature",
  "properties": {
    "iso:country":"DE",
    "sg:address":"Drosselweg 5",
    "sg:city":"Wernau",
    "sg:phone":"+49 7153/3371",
    "sg:postcode":"73249",
    "sg:province":"Baden-W\u00fcrttemberg",
    "wof:name":"Erhard Waldapfel",
    "wof:placetype":"venue"
},
  "geometry": {"coordinates":[9.4149799347,48.6903686523],"type":"Point"}
}