{
  "type": "Feature",
  "properties": {
    "iso:country":"DE",
    "sg:address":"Philosophenstr. 3",
    "sg:city":"Worms",
    "sg:phone":"+49 6241/25733",
    "sg:postcode":"67547",
    "sg:province":"Rheinland-Pfalz",
    "wof:name":"G\u00fcnter R\u00f6rig Steuerberater",
    "wof:placetype":"venue"
},
  "geometry": {"coordinates":[8.3674669266,49.6266174316],"type":"Point"}
}