{
  "type": "Feature",
  "properties": {
    "iso:country":"DE",
    "sg:address":"Gr\u00fcne Str. 7",
    "sg:city":"Ribnitz-Damgarten",
    "sg:phone":"+49 3821/4332",
    "sg:postcode":"18311",
    "sg:province":"Mecklenburg-Vorpommern",
    "wof:name":"H. Gohr",
    "wof:placetype":"venue"
},
  "geometry": {"coordinates":[12.473831,54.258678],"type":"Point"}
}