{
  "type": "Feature",
  "properties": {
    "iso:country":"DE",
    "sg:address":"Hohe Str. 13",
    "sg:city":"Rhede",
    "sg:phone":"+49 2872/2341",
    "sg:postcode":"46414",
    "sg:province":"Nordrhein-Westfalen",
    "wof:name":"Bernhard Essing",
    "wof:placetype":"venue"
},
  "geometry": {"coordinates":[6.6962771416,51.8394737244],"type":"Point"}
}