{
  "type": "Feature",
  "properties": {
    "iso:country":"DE",
    "sg:address":"Abensberger Str. 13",
    "sg:city":"Mainburg",
    "sg:phone":"+49 8751/7010",
    "sg:postcode":"84048",
    "sg:province":"Bayern",
    "wof:name":"Hallertauer Volksbank Eg",
    "wof:placetype":"venue"
},
  "geometry": {"coordinates":[11.787327,48.642574],"type":"Point"}
}