{
  "type": "Feature",
  "properties": {
    "iso:country":"DE",
    "sg:address":"Triptiser Str 35",
    "sg:city":"Auma",
    "sg:phone":"+49 5208/8026",
    "sg:postcode":"07955",
    "sg:province":"Th\u00fcringen",
    "wof:name":"Reinhard Fromme Kg",
    "wof:placetype":"venue"
},
  "geometry": {"coordinates":[8.6684732437,52.0557518005],"type":"Point"}
}