{
  "type": "Feature",
  "properties": {
    "iso:country":"DE",
    "sg:address":"Marienburger Str. 29",
    "sg:city":"K\u00f6ln",
    "sg:phone":"+49 221/384407",
    "sg:postcode":"50968",
    "sg:province":"Nordrhein-Westfalen",
    "wof:name":"Klaus Moritz",
    "wof:placetype":"venue"
},
  "geometry": {"coordinates":[6.972864151,50.9010162354],"type":"Point"}
}