{
  "type": "Feature",
  "properties": {
    "iso:country":"DE",
    "sg:address":"Obere Maingasse 8",
    "sg:city":"Veitsh\u00f6chheim",
    "sg:phone":"+49 931/91553",
    "sg:postcode":"97209",
    "sg:province":"Bayern",
    "wof:name":"Heinrich Herbert Personenschiffahrt",
    "wof:placetype":"venue"
},
  "geometry": {"coordinates":[9.869768,49.831238],"type":"Point"}
}