{
  "type": "Feature",
  "properties": {
    "iso:country":"DE",
    "sg:address":"Freidrich-Then-Weg 44",
    "sg:city":"Frontenhausen",
    "sg:phone":"+49 8732/930606",
    "sg:postcode":"84160",
    "sg:province":"Bayern",
    "wof:name":"Ingenieurbuero Martin Krey",
    "wof:placetype":"venue"
},
  "geometry": {"coordinates":[12.524885,48.540844],"type":"Point"}
}