{
  "type": "Feature",
  "properties": {
    "iso:country":"DE",
    "sg:address":"Am Heidberg 36",
    "sg:city":"Henstedt-Ulzburg",
    "sg:phone":"+49 4193/77868",
    "sg:postcode":"24558",
    "sg:province":"Schleswig-Holstein",
    "wof:name":"G\u00fcnther Krohn",
    "wof:placetype":"venue"
},
  "geometry": {"coordinates":[9.9875202179,53.7568855286],"type":"Point"}
}