{
  "type": "Feature",
  "properties": {
    "iso:country":"DE",
    "sg:address":"Overather Str.",
    "sg:city":"Engelskirchen",
    "sg:phone":"+49 2263/3717",
    "sg:postcode":"51766",
    "sg:province":"Nordrhein-Westfalen",
    "wof:name":"Hbt H\u00f6lzer Verwaltungs- Und",
    "wof:placetype":"venue"
},
  "geometry": {"coordinates":[7.38228,50.983524],"type":"Point"}
}