{
  "type": "Feature",
  "properties": {
    "iso:country":"DE",
    "sg:address":"Goetheweg 17",
    "sg:city":"Pritzwalk",
    "sg:phone":"+49 3395/302613",
    "sg:postcode":"16928",
    "sg:province":"Brandenburg",
    "wof:name":"Dr. Med. J\u00fcrgen Bohl",
    "wof:placetype":"venue"
},
  "geometry": {"coordinates":[12.182683,53.142757],"type":"Point"}
}