{
  "type": "Feature",
  "properties": {
    "iso:country":"DE",
    "sg:address":"Riehler Strasse 90::",
    "sg:city":"Koeln",
    "sg:phone":"+49 4935/558150",
    "sg:postcode":"50668",
    "sg:province":"Nordrhein-Westfalen",
    "wof:name":"Agro Data Edv & Werbung Gmbh",
    "wof:placetype":"venue"
},
  "geometry": {"coordinates":[14.312657,51.717995],"type":"Point"}
}