{
  "type": "Feature",
  "properties": {
    "iso:country":"DE",
    "sg:address":"Alleestr. 82",
    "sg:city":"Castrop-Rauxel",
    "sg:phone":"+49 2305/32549",
    "sg:postcode":"44579",
    "sg:province":"Nordrhein-Westfalen",
    "wof:name":"Dkv Versicherung Ag Frank Treffts",
    "wof:placetype":"venue"
},
  "geometry": {"coordinates":[7.312953949,51.5739250183],"type":"Point"}
}