{
  "type": "Feature",
  "properties": {
    "iso:country":"DE",
    "sg:address":"Paul-Esch-Str. 55-57",
    "sg:city":"Duisburg",
    "sg:phone":"+49 203/61044",
    "sg:postcode":"47053",
    "sg:province":"Nordrhein-Westfalen",
    "wof:name":"Reifen-center A. Gorski Gmbh",
    "wof:placetype":"venue"
},
  "geometry": {"coordinates":[6.764309,51.412083],"type":"Point"}
}