{
  "type": "Feature",
  "properties": {
    "iso:country":"DE",
    "sg:address":"Sigismundstr. 17",
    "sg:city":"Konstanz",
    "sg:phone":"+49 7531/23952",
    "sg:postcode":"78462",
    "sg:province":"Baden-W\u00fcrttemberg",
    "wof:name":"Kath. Pfarramt Dreifaltigkeit",
    "wof:placetype":"venue"
},
  "geometry": {"coordinates":[9.175444603,47.6586532593],"type":"Point"}
}