{
  "type": "Feature",
  "properties": {
    "iso:country":"DE",
    "sg:address":"Gaisentalstr. 61",
    "sg:city":"Biberach",
    "sg:phone":"+49 7351/6758",
    "sg:postcode":"88400",
    "sg:province":"Baden-W\u00fcrttemberg",
    "wof:name":"Wilhelm Bopp Gmbh",
    "wof:placetype":"venue"
},
  "geometry": {"coordinates":[9.773957,48.099854],"type":"Point"}
}