{
  "type": "Feature",
  "properties": {
    "iso:country":"DE",
    "sg:address":"Daimlerstr. 1k",
    "sg:city":"Dreieich",
    "sg:phone":"+49 6103/80970",
    "sg:postcode":"63303",
    "sg:province":"Hessen",
    "wof:name":"Dsc Dr. St\u00e4rk Computer Gmbh",
    "wof:placetype":"venue"
},
  "geometry": {"coordinates":[8.690943718,50.0057029724],"type":"Point"}
}