{
  "type": "Feature",
  "properties": {
    "iso:country":"DE",
    "sg:address":"Friedrichstr. 16",
    "sg:city":"Kronberg",
    "sg:phone":"+49 6173/68228",
    "sg:postcode":"61476",
    "sg:province":"Hessen",
    "wof:name":"Dieter Kilian",
    "wof:placetype":"venue"
},
  "geometry": {"coordinates":[8.525714,50.182049],"type":"Point"}
}