{
  "type": "Feature",
  "properties": {
    "iso:country":"DE",
    "sg:address":"Bahnhofstr. 9",
    "sg:city":"Dietzenbach",
    "sg:phone":"+49 6074/32763",
    "sg:postcode":"63128",
    "sg:province":"Hessen",
    "wof:name":"Kie\u00dfling & Partner Gmbh",
    "wof:placetype":"venue"
},
  "geometry": {"coordinates":[8.7777414322,50.0087165833],"type":"Point"}
}