{
  "type": "Feature",
  "properties": {
    "iso:country":"DE",
    "sg:address":"Erasmusweg 8",
    "sg:city":"Bretten",
    "sg:phone":"+49 7252/94940",
    "sg:postcode":"75015",
    "sg:province":"Baden-W\u00fcrttemberg",
    "wof:name":"Hans D\u00fcck",
    "wof:placetype":"venue"
},
  "geometry": {"coordinates":[8.717866,49.036976],"type":"Point"}
}