{
  "type": "Feature",
  "properties": {
    "iso:country":"DE",
    "sg:address":"Ghaibrunnenweg 7",
    "sg:city":"Schorndorf",
    "sg:phone":"+49 7181/61088",
    "sg:postcode":"73614",
    "sg:province":"Baden-W\u00fcrttemberg",
    "wof:name":"Rolf Kugler Ingenieur",
    "wof:placetype":"venue"
},
  "geometry": {"coordinates":[9.5509977341,48.833984375],"type":"Point"}
}