{
  "type": "Feature",
  "properties": {
    "iso:country":"DE",
    "sg:address":"Celler Str. 88",
    "sg:city":"Soltau",
    "sg:phone":"+49 5191/18790",
    "sg:postcode":"29614",
    "sg:province":"Niedersachsen",
    "wof:name":"Big Stone",
    "wof:placetype":"venue"
},
  "geometry": {"coordinates":[9.8493442535,52.9755821228],"type":"Point"}
}