{
  "type": "Feature",
  "properties": {
    "iso:country":"DE",
    "sg:address":"An der Schneiderburg 11",
    "sg:city":"Simmern",
    "sg:phone":"+49 6761/2332",
    "sg:postcode":"55469",
    "sg:province":"Rheinland-Pfalz",
    "wof:name":"Friedrich Schmitt",
    "wof:placetype":"venue"
},
  "geometry": {"coordinates":[7.479887,49.974373],"type":"Point"}
}