{
  "type": "Feature",
  "properties": {
    "iso:country":"DE",
    "sg:address":"Saarbr\u00fccker Str. 48",
    "sg:city":"Nohfelden",
    "sg:phone":"+49 6852/7904",
    "sg:postcode":"66625",
    "sg:province":"Saarland",
    "wof:name":"Marys Eiscafe",
    "wof:placetype":"venue"
},
  "geometry": {"coordinates":[7.111597,49.57655],"type":"Point"}
}