{
  "type": "Feature",
  "properties": {
    "iso:country":"DE",
    "sg:address":"Theodor-Heuss-Str. 60 a",
    "sg:city":"Pforzheim",
    "sg:phone":"+49 7231/766304",
    "sg:postcode":"75180",
    "sg:province":"Baden-W\u00fcrttemberg",
    "wof:name":"Klittich Immobilien Gmbh",
    "wof:placetype":"venue"
},
  "geometry": {"coordinates":[8.6651248932,48.8664894104],"type":"Point"}
}