{
  "type": "Feature",
  "properties": {
    "iso:country":"DE",
    "sg:address":"Am Rupenhorn 6",
    "sg:city":"Berlin",
    "sg:phone":"+49 30/2139093",
    "sg:postcode":"14055",
    "sg:province":"Berlin",
    "wof:name":"Promedico Medizinische Ger\u00e4te Gmbh",
    "wof:placetype":"venue"
},
  "geometry": {"coordinates":[13.214108,52.50502],"type":"Point"}
}