{
  "type": "Feature",
  "properties": {
    "iso:country":"DE",
    "sg:address":"W\u00f6rrst\u00e4dter Str. 16",
    "sg:city":"Nierstein",
    "sg:postcode":"55283",
    "sg:province":"Rheinland-Pfalz",
    "wof:name":"A. L. O. Associated Leisure Organizers Gmbh",
    "wof:placetype":"venue"
},
  "geometry": {"coordinates":[8.346969,49.867863],"type":"Point"}
}