{
  "type": "Feature",
  "properties": {
    "iso:country":"DE",
    "sg:address":"Mittelstr 9",
    "sg:city":"Schipkau",
    "sg:phone":"+49 35754/63063",
    "sg:postcode":"01993",
    "sg:province":"Brandenburg",
    "wof:name":"Panorama Entertainment Inh. S\u00f6ren Hannusch",
    "wof:placetype":"venue"
},
  "geometry": {"coordinates":[13.901927948,51.5090026855],"type":"Point"}
}