{
  "type": "Feature",
  "properties": {
    "iso:country":"DE",
    "sg:address":"K\u00f6lner Tor 5",
    "sg:city":"D\u00fcsseldorf",
    "sg:phone":"+49 211/284953",
    "sg:postcode":"40625",
    "sg:province":"Nordrhein-Westfalen",
    "wof:name":"H. Tophofen",
    "wof:placetype":"venue"
},
  "geometry": {"coordinates":[6.861736,51.236706],"type":"Point"}
}