{
  "type": "Feature",
  "properties": {
    "iso:country":"DE",
    "sg:address":"Schramberger Str. 5",
    "sg:city":"Schramberg",
    "sg:phone":"+49 7422/6064",
    "sg:postcode":"78713",
    "sg:province":"Baden-W\u00fcrttemberg",
    "wof:name":"Rauch Und K\u00f6nig Architekten",
    "wof:placetype":"venue"
},
  "geometry": {"coordinates":[8.419035,48.227947],"type":"Point"}
}