{
  "type": "Feature",
  "properties": {
    "iso:country":"DE",
    "sg:address":"Leonberger Str. 5",
    "sg:city":"Rutesheim",
    "sg:phone":"+49 7152/52716",
    "sg:postcode":"71277",
    "sg:province":"Baden-W\u00fcrttemberg",
    "wof:name":"Schnell Und Seidler-schnell Rechtsanw\u00e4lte",
    "wof:placetype":"venue"
},
  "geometry": {"coordinates":[8.9461641312,48.8081626892],"type":"Point"}
}