{
  "type": "Feature",
  "properties": {
    "iso:country":"DE",
    "sg:address":"Hoher Weg 26",
    "sg:city":"Augsburg",
    "sg:phone":"+49 821/518339",
    "sg:postcode":"86152",
    "sg:province":"Bayern",
    "wof:name":"Haus St. Hildegard",
    "wof:placetype":"venue"
},
  "geometry": {"coordinates":[10.8975038528,48.3729782104],"type":"Point"}
}