{
  "type": "Feature",
  "properties": {
    "iso:country":"DE",
    "sg:address":"Steinweg 18",
    "sg:city":"Gifhorn",
    "sg:phone":"+49 5371/4176",
    "sg:postcode":"38518",
    "sg:province":"Niedersachsen",
    "wof:name":"Brokelt Leder",
    "wof:placetype":"venue"
},
  "geometry": {"coordinates":[10.546095,52.487053],"type":"Point"}
}