{
  "type": "Feature",
  "properties": {
    "iso:country":"DE",
    "sg:address":"Ewersbacher Str. 3",
    "sg:city":"Haiger",
    "sg:phone":"+49 2773/5135",
    "sg:postcode":"35708",
    "sg:province":"Hessen",
    "wof:name":"R. Damm",
    "wof:placetype":"venue"
},
  "geometry": {"coordinates":[8.2014493942,50.8055915833],"type":"Point"}
}