{
  "type": "Feature",
  "properties": {
    "iso:country":"DE",
    "sg:address":"Eckacker 14",
    "sg:city":"Freiamt",
    "sg:phone":"+49 7645/625",
    "sg:postcode":"79348",
    "sg:province":"Baden-W\u00fcrttemberg",
    "wof:name":"Friedrich Kern",
    "wof:placetype":"venue"
},
  "geometry": {"coordinates":[7.920503,48.184826],"type":"Point"}
}