{
  "type": "Feature",
  "properties": {
    "iso:country":"DE",
    "sg:address":"Esmarchstra\u00dfe 26",
    "sg:city":"Berlin",
    "sg:phone":"+49 30/4213631",
    "sg:postcode":"10407",
    "sg:province":"Berlin",
    "wof:name":"1 Mehr Event Und Ticket-service",
    "wof:placetype":"venue"
},
  "geometry": {"coordinates":[13.4306116104,52.5315055847],"type":"Point"}
}