{
  "type": "Feature",
  "properties": {
    "iso:country":"DE",
    "sg:address":"M\u00fcnsterstr. 15",
    "sg:city":"Rheine",
    "sg:phone":"+49 5971/50010",
    "sg:postcode":"48431",
    "sg:province":"Nordrhein-Westfalen",
    "wof:name":"Tchibo Frisch-r\u00f6st-kaffee Gmbh",
    "wof:placetype":"venue"
},
  "geometry": {"coordinates":[7.4398012161,52.2783966064],"type":"Point"}
}