{
  "type": "Feature",
  "properties": {
    "iso:country":"DE",
    "sg:address":"Postfach 2220",
    "sg:city":"Borkum",
    "sg:postcode":"26748",
    "sg:province":"Niedersachsen",
    "wof:name":"Kino",
    "wof:placetype":"venue"
},
  "geometry": {"coordinates":[6.6915,53.580921],"type":"Point"}
}