{
  "type": "Feature",
  "properties": {
    "iso:country":"DE",
    "sg:address":"Veghestr. 10",
    "sg:city":"M\u00fcnster",
    "sg:phone":"+49 251/20775",
    "sg:postcode":"48149",
    "sg:province":"Nordrhein-Westfalen",
    "wof:name":"Lietzow-hausbau Gmbh",
    "wof:placetype":"venue"
},
  "geometry": {"coordinates":[7.608812,51.96867],"type":"Point"}
}