{
  "type": "Feature",
  "properties": {
    "iso:country":"DE",
    "sg:address":"Dreilindenstr.21",
    "sg:city":"Leipzig",
    "sg:phone":"+49 341/4806262",
    "sg:postcode":"04177",
    "sg:province":"Sachsen",
    "wof:name":"Welcome To Sex4club.de",
    "wof:placetype":"venue"
},
  "geometry": {"coordinates":[12.338436,51.336372],"type":"Point"}
}