{
  "type": "Feature",
  "properties": {
    "iso:country":"DE",
    "sg:address":"Alter Kirchweg 15",
    "sg:city":"Bad M\u00fcnder",
    "sg:phone":"+49 5042/4250",
    "sg:postcode":"31848",
    "sg:province":"Niedersachsen",
    "wof:name":"Freibad Bakede",
    "wof:placetype":"venue"
},
  "geometry": {"coordinates":[9.3928480148,52.2064933777],"type":"Point"}
}