{
  "type": "Feature",
  "properties": {
    "iso:country":"DE",
    "sg:address":"Eisenacher Str. 42",
    "sg:city":"Wutha-Farnroda",
    "sg:phone":"+49 36921/96409",
    "sg:postcode":"99848",
    "sg:province":"Th\u00fcringen",
    "wof:name":"Wolfgang Leinhos Rechtsanwalt",
    "wof:placetype":"venue"
},
  "geometry": {"coordinates":[10.3903408051,50.9573554993],"type":"Point"}
}