{
  "type": "Feature",
  "properties": {
    "iso:country":"DE",
    "sg:address":"Angerweg 8",
    "sg:city":"Prem",
    "sg:phone":"+49 8862/7474",
    "sg:postcode":"86984",
    "sg:province":"Bayern",
    "wof:name":"Helmut Hei\u00dferer",
    "wof:placetype":"venue"
},
  "geometry": {"coordinates":[10.8060321808,47.6826591492],"type":"Point"}
}