{
  "type": "Feature",
  "properties": {
    "iso:country":"DE",
    "sg:address":"Vierzoner Str. 110",
    "sg:city":"Bitterfeld",
    "sg:phone":"+49 3493/69038",
    "sg:postcode":"06749",
    "sg:province":"Sachsen-Anhalt",
    "wof:name":"Sportstudio Schweiger Gmbh",
    "wof:placetype":"venue"
},
  "geometry": {"coordinates":[12.3286895752,51.6298866272],"type":"Point"}
}