{
  "type": "Feature",
  "properties": {
    "iso:country":"DE",
    "sg:address":"Reuschenlay 34",
    "sg:city":"Kruft",
    "sg:phone":"+49 2652/7200",
    "sg:postcode":"56642",
    "sg:province":"Rheinland-Pfalz",
    "wof:name":"Franz J. Thomas",
    "wof:placetype":"venue"
},
  "geometry": {"coordinates":[7.344892025,50.3761672974],"type":"Point"}
}