{
  "type": "Feature",
  "properties": {
    "iso:country":"DE",
    "sg:address":"Barnackufer 23",
    "sg:city":"Berlin",
    "sg:phone":"+49 30/7724099",
    "sg:postcode":"12207",
    "sg:province":"Berlin",
    "wof:name":"Uniko Raumsysteme- Sicherheitstechnik Gmbh",
    "wof:placetype":"venue"
},
  "geometry": {"coordinates":[13.3118028641,52.4289360046],"type":"Point"}
}