{
  "type": "Feature",
  "properties": {
    "iso:country":"DE",
    "sg:address":"Nikolaus-Otto-Str. 15",
    "sg:city":"Bad Kreuznach",
    "sg:phone":"+49 671/894045",
    "sg:postcode":"55543",
    "sg:province":"Rheinland-Pfalz",
    "wof:name":"Bierther Gmbh",
    "wof:placetype":"venue"
},
  "geometry": {"coordinates":[7.891404,49.852867],"type":"Point"}
}