{
  "type": "Feature",
  "properties": {
    "iso:country":"DE",
    "sg:address":"Bergstr. 37",
    "sg:city":"Holzminden",
    "sg:phone":"+49 5531/6369",
    "sg:postcode":"37603",
    "sg:province":"Niedersachsen",
    "wof:name":"Hans Schneider Architekt",
    "wof:placetype":"venue"
},
  "geometry": {"coordinates":[9.454706,51.836304],"type":"Point"}
}