{
  "type": "Feature",
  "properties": {
    "iso:country":"DE",
    "sg:address":"Puschkinstr. 12 b",
    "sg:city":"Frankfurt",
    "sg:postcode":"15236",
    "sg:province":"Brandenburg",
    "wof:name":"Ihk-projektgesellschaft Mbh",
    "wof:placetype":"venue"
},
  "geometry": {"coordinates":[14.354413,52.339134],"type":"Point"}
}