{
  "type": "Feature",
  "properties": {
    "iso:country":"DE",
    "sg:address":"Reventlowstr. 35",
    "sg:city":"Hamburg",
    "sg:phone":"+49 40/8810833",
    "sg:postcode":"22605",
    "sg:province":"Hamburg",
    "wof:name":"Johannes Struck Architekt",
    "wof:placetype":"venue"
},
  "geometry": {"coordinates":[9.889767,53.556751],"type":"Point"}
}