{
  "type": "Feature",
  "properties": {
    "iso:country":"DE",
    "sg:address":"Raiffeisenstr 1::",
    "sg:city":"Guxhagen",
    "sg:postcode":"34302",
    "sg:province":"Hessen",
    "wof:name":"Raiffeisenbank Guxhagen Eg",
    "wof:placetype":"venue"
},
  "geometry": {"coordinates":[9.48204,51.20406],"type":"Point"}
}