{
  "type": "Feature",
  "properties": {
    "iso:country":"DE",
    "sg:address":"Heudorfer Str.",
    "sg:city":"Scheer",
    "sg:phone":"+49 7572/2189",
    "sg:postcode":"72516",
    "sg:province":"Baden-W\u00fcrttemberg",
    "wof:name":"J. Mannhart",
    "wof:placetype":"venue"
},
  "geometry": {"coordinates":[9.300161,48.074795],"type":"Point"}
}