{
  "type": "Feature",
  "properties": {
    "iso:country":"DE",
    "sg:address":"Hauptstr. 6-8",
    "sg:city":"Lauterecken",
    "sg:postcode":"67742",
    "sg:province":"Rheinland-Pfalz",
    "wof:name":"Julius Schneider Bahnschneider Gmbh",
    "wof:placetype":"venue"
},
  "geometry": {"coordinates":[7.589425,49.651493],"type":"Point"}
}