{
  "type": "Feature",
  "properties": {
    "iso:country":"DE",
    "sg:address":"Carl-Stockhinger-Str 1c",
    "sg:city":"Bremen",
    "sg:phone":"+49 421/521717",
    "sg:postcode":"28197",
    "sg:province":"Bremen",
    "wof:name":"Tol Trans Ocean Logistik Gmbh & Co",
    "wof:placetype":"venue"
},
  "geometry": {"coordinates":[8.7582502365,53.0784187317],"type":"Point"}
}