{
  "type": "Feature",
  "properties": {
    "iso:country":"DE",
    "sg:address":"Averdiekstr. 6",
    "sg:city":"Osnabr\u00fcck",
    "sg:phone":"+49 541/440802",
    "sg:postcode":"49078",
    "sg:province":"Niedersachsen",
    "wof:name":"Osna-handel F. -dieter Neumann",
    "wof:placetype":"venue"
},
  "geometry": {"coordinates":[7.974431,52.267773],"type":"Point"}
}