{
  "type": "Feature",
  "properties": {
    "iso:country":"DE",
    "sg:address":"Mozartring 25 a",
    "sg:city":"G\u00fcnzburg",
    "sg:phone":"+49 8221/36240",
    "sg:postcode":"89312",
    "sg:province":"Bayern",
    "wof:name":"G. Weishaupt-zahntechnik Gmbh",
    "wof:placetype":"venue"
},
  "geometry": {"coordinates":[10.284212,48.457722],"type":"Point"}
}