{
  "type": "Feature",
  "properties": {
    "iso:country":"DE",
    "sg:address":"Bahnhofstr. 3",
    "sg:city":"B\u00fcrstadt",
    "sg:phone":"+49 6206/6449",
    "sg:postcode":"68642",
    "sg:province":"Hessen",
    "wof:name":"Helmut Vonderheid",
    "wof:placetype":"venue"
},
  "geometry": {"coordinates":[8.455751,49.645569],"type":"Point"}
}