{
  "type": "Feature",
  "properties": {
    "iso:country":"DE",
    "sg:address":"Hankerfeld 8",
    "sg:city":"R\u00fcthen",
    "sg:phone":"+49 2952/97200",
    "sg:postcode":"59602",
    "sg:province":"Nordrhein-Westfalen",
    "wof:name":"T\u00fcrenwerk H. Ebbers Gmbh",
    "wof:placetype":"venue"
},
  "geometry": {"coordinates":[8.4445447922,51.4838256836],"type":"Point"}
}