{
  "type": "Feature",
  "properties": {
    "iso:country":"DE",
    "sg:address":"Neustadt 63",
    "sg:city":"Celle",
    "sg:phone":"+49 5141/482880",
    "sg:postcode":"29225",
    "sg:province":"Niedersachsen",
    "wof:name":"Virtuelle Server",
    "wof:placetype":"venue"
},
  "geometry": {"coordinates":[10.057253,52.620464],"type":"Point"}
}