{
  "type": "Feature",
  "properties": {
    "iso:country":"DE",
    "sg:address":"Egelpfuhlstr. 46",
    "sg:city":"Berlin",
    "sg:phone":"+49 30/3318408",
    "sg:postcode":"13581",
    "sg:province":"Berlin",
    "wof:name":"Josef Janowski",
    "wof:placetype":"venue"
},
  "geometry": {"coordinates":[13.169511795,52.5328979492],"type":"Point"}
}