{
  "type": "Feature",
  "properties": {
    "iso:country":"DE",
    "sg:address":"Cranger Str. 286",
    "sg:city":"Gelsenkirchen",
    "sg:phone":"+49 209/778828",
    "sg:postcode":"45891",
    "sg:province":"Nordrhein-Westfalen",
    "wof:name":"Eiscafe A. Alvaro",
    "wof:placetype":"venue"
},
  "geometry": {"coordinates":[7.103924,51.550541],"type":"Point"}
}