{
  "type": "Feature",
  "properties": {
    "iso:country":"DE",
    "sg:address":"Gartenstr. 20",
    "sg:city":"Niedererbach",
    "sg:phone":"+49 6485/1545",
    "sg:postcode":"56412",
    "sg:province":"Rheinland-Pfalz",
    "wof:name":"Meier Verlags Gmbh",
    "wof:placetype":"venue"
},
  "geometry": {"coordinates":[7.971886158,50.425151825],"type":"Point"}
}