{
  "type": "Feature",
  "properties": {
    "iso:country":"DE",
    "sg:address":"Bruchflachweg 36",
    "sg:city":"L\u00fcbbecke",
    "sg:phone":"+49 5742/920592",
    "sg:postcode":"32312",
    "sg:province":"Nordrhein-Westfalen",
    "wof:name":"Friedrich Von Behren",
    "wof:placetype":"venue"
},
  "geometry": {"coordinates":[8.548498,52.316685],"type":"Point"}
}