{
  "type": "Feature",
  "properties": {
    "iso:country":"DE",
    "sg:address":"Brohltalstr. 129",
    "sg:city":"Burgbrohl",
    "sg:phone":"+49 2636/2356",
    "sg:postcode":"56659",
    "sg:province":"Rheinland-Pfalz",
    "wof:name":"Herbert Heinrich",
    "wof:placetype":"venue"
},
  "geometry": {"coordinates":[7.272464,50.45816],"type":"Point"}
}