{
  "type": "Feature",
  "properties": {
    "iso:country":"DE",
    "sg:address":"Gr\u00e4flingsweg 18",
    "sg:city":"Norderstedt",
    "sg:phone":"+49 40/5222348",
    "sg:postcode":"22844",
    "sg:province":"Schleswig-Holstein",
    "wof:name":"Cs Trading Claus-walther Schroeder",
    "wof:placetype":"venue"
},
  "geometry": {"coordinates":[9.99862957,53.7451896667],"type":"Point"}
}