{
  "type": "Feature",
  "properties": {
    "iso:country":"DE",
    "sg:address":"Wickingstr. 34",
    "sg:city":"Beckum",
    "sg:postcode":"59269",
    "sg:province":"Nordrhein-Westfalen",
    "wof:name":"Elgropa Schaltanlagen Gmbh",
    "wof:placetype":"venue"
},
  "geometry": {"coordinates":[8.0137214661,51.7982902527],"type":"Point"}
}