{
  "type": "Feature",
  "properties": {
    "iso:country":"DE",
    "sg:address":"Boldebucker Weg 1",
    "sg:city":"G\u00fcstrow",
    "sg:postcode":"18273",
    "sg:province":"Mecklenburg-Vorpommern",
    "wof:name":"F Und C Forschungstechnik Und Computersysteme Gmbh",
    "wof:placetype":"venue"
},
  "geometry": {"coordinates":[12.1729640961,53.7967720032],"type":"Point"}
}