{
  "type": "Feature",
  "properties": {
    "iso:country":"DE",
    "sg:address":"Lortzingstr. 85-7",
    "sg:city":"Schorndorf",
    "sg:phone":"+49 7181/42845",
    "sg:postcode":"73614",
    "sg:province":"Baden-W\u00fcrttemberg",
    "wof:name":"R. Hoffrichter",
    "wof:placetype":"venue"
},
  "geometry": {"coordinates":[9.51805,48.79977],"type":"Point"}
}