{
  "type": "Feature",
  "properties": {
    "iso:country":"DE",
    "sg:address":"Frauenbrunner Str. 39",
    "sg:city":"Eppingen",
    "sg:phone":"+49 7262/6612",
    "sg:postcode":"75031",
    "sg:province":"Baden-W\u00fcrttemberg",
    "wof:name":"Caracciolo Gmbh",
    "wof:placetype":"venue"
},
  "geometry": {"coordinates":[8.896238327,49.1318702698],"type":"Point"}
}