{
  "type": "Feature",
  "properties": {
    "iso:country":"DE",
    "sg:address":"Wilhelm-R\u00f6ntgen-Str. 28",
    "sg:city":"Maintal",
    "sg:phone":"+49 6181/493007",
    "sg:postcode":"63477",
    "sg:province":"Hessen",
    "wof:name":"Maler Lapp Gmbh",
    "wof:placetype":"venue"
},
  "geometry": {"coordinates":[8.860122,50.130337],"type":"Point"}
}