{
  "type": "Feature",
  "properties": {
    "iso:country":"DE",
    "sg:address":"Rheinstr. 33",
    "sg:city":"Kuppenheim",
    "sg:phone":"+49 7222/949605",
    "sg:postcode":"76456",
    "sg:province":"Baden-W\u00fcrttemberg",
    "wof:name":"Prof. Thomas Grochowiak Museum Recklinghausen",
    "wof:placetype":"venue"
},
  "geometry": {"coordinates":[8.24766922,48.8279266357],"type":"Point"}
}