{
  "type": "Feature",
  "properties": {
    "iso:country":"DE",
    "sg:address":"Barw\u00f6ste 2",
    "sg:city":"Schapen",
    "sg:phone":"+49 5458/1729",
    "sg:postcode":"48480",
    "sg:province":"Niedersachsen",
    "wof:name":"August L\u00f6gers",
    "wof:placetype":"venue"
},
  "geometry": {"coordinates":[7.47308,52.364254],"type":"Point"}
}