{
  "type": "Feature",
  "properties": {
    "iso:country":"DE",
    "sg:address":"Woltorfer Str. 70",
    "sg:city":"Peine",
    "sg:phone":"+49 5171/6526",
    "sg:postcode":"31224",
    "sg:province":"Niedersachsen",
    "wof:name":"Restaurant Belgrad Grill",
    "wof:placetype":"venue"
},
  "geometry": {"coordinates":[10.2430562973,52.3202018738],"type":"Point"}
}