{
  "type": "Feature",
  "properties": {
    "iso:country":"DE",
    "sg:city":"Miltenberg",
    "sg:phone":"+49 9371/2588",
    "sg:postcode":"63897",
    "sg:province":"Bayern",
    "wof:name":"Alfred Schaubhut",
    "wof:placetype":"venue"
},
  "geometry": {"coordinates":[9.256472,49.702221],"type":"Point"}
}