{
  "type": "Feature",
  "properties": {
    "iso:country":"DE",
    "sg:address":"Langfurch 24",
    "sg:city":"Kappelrodeck",
    "sg:phone":"+49 7842/2242",
    "sg:postcode":"77876",
    "sg:province":"Baden-W\u00fcrttemberg",
    "wof:name":"A. Kiemann",
    "wof:placetype":"venue"
},
  "geometry": {"coordinates":[8.112532,48.592266],"type":"Point"}
}