{
  "type": "Feature",
  "properties": {
    "iso:country":"DE",
    "sg:address":"Hellersbergstr. 2 a",
    "sg:city":"Neuss",
    "sg:postcode":"41460",
    "sg:province":"Nordrhein-Westfalen",
    "wof:name":"Xerox Dienstleistungs- Gesellschaft Mbh",
    "wof:placetype":"venue"
},
  "geometry": {"coordinates":[6.709799,51.19569],"type":"Point"}
}