{
  "type": "Feature",
  "properties": {
    "iso:country":"DE",
    "sg:address":"Zipperstr. 9",
    "sg:city":"Bonn",
    "sg:phone":"+49 228/441596",
    "sg:postcode":"53227",
    "sg:province":"Nordrhein-Westfalen",
    "wof:name":"Putzbau-r\u00f6nz Gmbh",
    "wof:placetype":"venue"
},
  "geometry": {"coordinates":[7.1684279442,50.711971283],"type":"Point"}
}