{
  "type": "Feature",
  "properties": {
    "iso:country":"DE",
    "sg:address":"Maximiliansplatz 12 a",
    "sg:city":"M\u00fcnchen",
    "sg:phone":"+49 89/292410",
    "sg:postcode":"80333",
    "sg:province":"Bayern",
    "wof:name":"Margarete Ammon Stiftung Ag",
    "wof:placetype":"venue"
},
  "geometry": {"coordinates":[11.5733747482,48.1424484253],"type":"Point"}
}