{
  "type": "Feature",
  "properties": {
    "iso:country":"DE",
    "sg:city":"Rinow",
    "sg:phone":"+49 33744/60739",
    "sg:postcode":"14913",
    "sg:province":"Brandenburg",
    "wof:name":"Schmidt Solar Heizung Sanit\u00e4r",
    "wof:placetype":"venue"
},
  "geometry": {"coordinates":[13.285949,51.829277],"type":"Point"}
}