{
  "type": "Feature",
  "properties": {
    "iso:country":"DE",
    "sg:address":"Heidelberger Str. 59",
    "sg:city":"Brensbach",
    "sg:phone":"+49 6161/483",
    "sg:postcode":"64395",
    "sg:province":"Hessen",
    "wof:name":"W. Reeg",
    "wof:placetype":"venue"
},
  "geometry": {"coordinates":[8.8800373077,49.7703590393],"type":"Point"}
}