{
  "type": "Feature",
  "properties": {
    "iso:country":"DE",
    "sg:address":"Barlachstr. 9",
    "sg:city":"N\u00fcrnberg",
    "sg:phone":"+49 911/988840",
    "sg:postcode":"90455",
    "sg:province":"Bayern",
    "wof:name":"L\u00f6ckener & Co. Immobilien Gmbh",
    "wof:placetype":"venue"
},
  "geometry": {"coordinates":[11.078401,49.372181],"type":"Point"}
}