{
  "type": "Feature",
  "properties": {
    "iso:country":"DE",
    "sg:address":"Weldener Str. 19",
    "sg:city":"Fuchstal",
    "sg:phone":"+49 8243/2229",
    "sg:postcode":"86925",
    "sg:province":"Bayern",
    "wof:name":"Bergcafe",
    "wof:placetype":"venue"
},
  "geometry": {"coordinates":[10.823012,47.932175],"type":"Point"}
}