{
  "type": "Feature",
  "properties": {
    "iso:country":"DE",
    "sg:address":"Wengertsteige 13",
    "sg:city":"Holzgerlingen",
    "sg:phone":"+49 7031/609695",
    "sg:postcode":"71088",
    "sg:province":"Baden-W\u00fcrttemberg",
    "wof:name":"Rudolf Schneider",
    "wof:placetype":"venue"
},
  "geometry": {"coordinates":[9.030538559,48.6445655823],"type":"Point"}
}