{
  "type": "Feature",
  "properties": {
    "iso:country":"DE",
    "sg:address":"Kastellstr. 57",
    "sg:city":"Heilbronn",
    "sg:phone":"+49 7131/41234",
    "sg:postcode":"74080",
    "sg:province":"Baden-W\u00fcrttemberg",
    "wof:name":"Matthias Fuchs Gmbh",
    "wof:placetype":"venue"
},
  "geometry": {"coordinates":[9.1931247711,49.1342544556],"type":"Point"}
}