{
  "type": "Feature",
  "properties": {
    "iso:country":"DE",
    "sg:address":"G\u00f6rlitzer Str. 28",
    "sg:city":"Bernstadt",
    "sg:phone":"+49 35874/20383",
    "sg:postcode":"02748",
    "sg:province":"Sachsen",
    "wof:name":"Drogerie Fuhrmann",
    "wof:placetype":"venue"
},
  "geometry": {"coordinates":[14.8297,51.048115],"type":"Point"}
}