{
  "type": "Feature",
  "properties": {
    "iso:country":"DE",
    "sg:address":"Maubisstr. 11",
    "sg:city":"Kaarst",
    "sg:phone":"+49 2131/660594",
    "sg:postcode":"41564",
    "sg:province":"Nordrhein-Westfalen",
    "wof:name":"Bistro Centre Ville",
    "wof:placetype":"venue"
},
  "geometry": {"coordinates":[6.6191110611,51.2293434143],"type":"Point"}
}