{
  "type": "Feature",
  "properties": {
    "iso:country":"DE",
    "sg:address":"Richtweg 49",
    "sg:city":"Wendelstein",
    "sg:phone":"+49 9129/279939",
    "sg:postcode":"90530",
    "sg:province":"Bayern",
    "wof:name":"New Garden China Restaurant",
    "wof:placetype":"venue"
},
  "geometry": {"coordinates":[11.1639003754,49.352394104],"type":"Point"}
}