{
  "type": "Feature",
  "properties": {
    "iso:country":"DE",
    "sg:address":"Christophstr. 41",
    "sg:city":"G\u00f6ppingen",
    "sg:phone":"+49 7161/23158",
    "sg:postcode":"73033",
    "sg:province":"Baden-W\u00fcrttemberg",
    "wof:name":"W. Vester Inh. J. Schell",
    "wof:placetype":"venue"
},
  "geometry": {"coordinates":[9.6518278122,48.7080383301],"type":"Point"}
}