{
  "type": "Feature",
  "properties": {
    "iso:country":"DE",
    "sg:address":"Obermarkt 1",
    "sg:city":"Mittenwald",
    "sg:phone":"+49 8823/92700",
    "sg:postcode":"82481",
    "sg:province":"Bayern",
    "wof:name":"Hotel-gasthof Alpenrose",
    "wof:placetype":"venue"
},
  "geometry": {"coordinates":[11.2605237961,47.4418182373],"type":"Point"}
}