{
  "type": "Feature",
  "properties": {
    "iso:country":"DE",
    "sg:address":"Scheffelstr. 33",
    "sg:city":"Kirchzarten",
    "sg:phone":"+49 7661/7009",
    "sg:postcode":"79199",
    "sg:province":"Baden-W\u00fcrttemberg",
    "wof:name":"Karl-martin \u00d6ttinger Rechtsanwalt",
    "wof:placetype":"venue"
},
  "geometry": {"coordinates":[7.9493641853,47.9689788818],"type":"Point"}
}