{
  "type": "Feature",
  "properties": {
    "iso:country":"DE",
    "sg:address":"Martersteigstr. 38",
    "sg:city":"Weimar",
    "sg:phone":"+49 3643/59418",
    "sg:postcode":"99423",
    "sg:province":"Th\u00fcringen",
    "wof:name":"Falk-rainer Metzner",
    "wof:placetype":"venue"
},
  "geometry": {"coordinates":[11.3139038086,50.9774894714],"type":"Point"}
}