{
  "type": "Feature",
  "properties": {
    "iso:country":"DE",
    "sg:address":"Manfredstr. 2",
    "sg:city":"Gelsenkirchen",
    "sg:phone":"+49 4920/974038",
    "sg:postcode":"45891",
    "sg:province":"Nordrhein-Westfalen",
    "wof:name":"Ridderskamp & Hahn Gmbh",
    "wof:placetype":"venue"
},
  "geometry": {"coordinates":[7.0850849152,51.5520744324],"type":"Point"}
}