{
  "type": "Feature",
  "properties": {
    "iso:country":"DE",
    "sg:address":"Sch\u00f6nblickstr. 7",
    "sg:city":"Seefeld",
    "sg:postcode":"82229",
    "sg:province":"Bayern",
    "wof:name":"Oprah Consulting Gmbh",
    "wof:placetype":"venue"
},
  "geometry": {"coordinates":[11.191613,48.036938],"type":"Point"}
}