{
  "type": "Feature",
  "properties": {
    "iso:country":"DE",
    "sg:address":"Ansbacher Str. 6",
    "sg:city":"Uffenheim",
    "sg:phone":"+49 9842/8912",
    "sg:postcode":"97215",
    "sg:province":"Bayern",
    "wof:name":"Europa",
    "wof:placetype":"venue"
},
  "geometry": {"coordinates":[10.2311964035,49.5434188843],"type":"Point"}
}