{
  "type": "Feature",
  "properties": {
    "iso:country":"DE",
    "sg:address":"Talstr. 10",
    "sg:city":"Achstetten",
    "sg:phone":"+49 7392/6881",
    "sg:postcode":"88480",
    "sg:province":"Baden-W\u00fcrttemberg",
    "wof:name":"J\u00fcrgen Wagner",
    "wof:placetype":"venue"
},
  "geometry": {"coordinates":[9.8937997818,48.2669143677],"type":"Point"}
}