{
  "type": "Feature",
  "properties": {
    "iso:country":"DE",
    "sg:address":"Burgstr.",
    "sg:city":"Brohl-L\u00fctzing",
    "sg:postcode":"56656",
    "sg:province":"Rheinland-Pfalz",
    "wof:name":"Alfred Eickhoff",
    "wof:placetype":"venue"
},
  "geometry": {"coordinates":[7.326815,50.484322],"type":"Point"}
}