{
  "type": "Feature",
  "properties": {
    "iso:country":"DE",
    "sg:address":"Raublinger Str. 3",
    "sg:city":"Rosenheim",
    "sg:phone":"+49 8031/66693",
    "sg:postcode":"83026",
    "sg:province":"Bayern",
    "wof:name":"Johanna Eisgruber",
    "wof:placetype":"venue"
},
  "geometry": {"coordinates":[12.1051740646,47.8200531006],"type":"Point"}
}