{
  "type": "Feature",
  "properties": {
    "iso:country":"DE",
    "sg:address":"Wittener Str. 1",
    "sg:city":"Gevelsberg",
    "sg:phone":"+49 2332/2148",
    "sg:postcode":"58285",
    "sg:province":"Nordrhein-Westfalen",
    "wof:name":"Alfred Thiel",
    "wof:placetype":"venue"
},
  "geometry": {"coordinates":[7.3386950493,51.3198394775],"type":"Point"}
}