{
  "type": "Feature",
  "properties": {
    "iso:country":"DE",
    "sg:address":"Keltenweg 1",
    "sg:city":"Heimbach",
    "sg:phone":"+49 2425/7135",
    "sg:postcode":"52396",
    "sg:province":"Nordrhein-Westfalen",
    "wof:name":"Repro Handels-gmbh",
    "wof:placetype":"venue"
},
  "geometry": {"coordinates":[6.5429201126,50.6468391418],"type":"Point"}
}