{
  "type": "Feature",
  "properties": {
    "iso:country":"DE",
    "sg:address":"Bachstr. 8",
    "sg:city":"Plettenberg",
    "sg:phone":"+49 2391/51046",
    "sg:postcode":"58840",
    "sg:province":"Nordrhein-Westfalen",
    "wof:name":"Bistro Big Ben",
    "wof:placetype":"venue"
},
  "geometry": {"coordinates":[7.8718109131,51.2320671082],"type":"Point"}
}