{
  "type": "Feature",
  "properties": {
    "iso:country":"DE",
    "sg:address":"Rahmengasse 26",
    "sg:city":"Heidelberg",
    "sg:phone":"+49 6221/409675",
    "sg:postcode":"69120",
    "sg:province":"Baden-W\u00fcrttemberg",
    "wof:name":"B. L. Leimner & Co.",
    "wof:placetype":"venue"
},
  "geometry": {"coordinates":[8.6910610199,49.415435791],"type":"Point"}
}