{
  "type": "Feature",
  "properties": {
    "iso:country":"DE",
    "sg:address":"Friedhofstr. 3",
    "sg:city":"Gersheim",
    "sg:phone":"+49 6843/220",
    "sg:postcode":"66453",
    "sg:province":"Saarland",
    "wof:name":"G. Koch",
    "wof:placetype":"venue"
},
  "geometry": {"coordinates":[7.206127,49.173832],"type":"Point"}
}