{
  "type": "Feature",
  "properties": {
    "iso:country":"DE",
    "sg:address":"Kniebisstr. 7",
    "sg:city":"Neuenb\u00fcrg",
    "sg:phone":"+49 7082/5493",
    "sg:postcode":"75305",
    "sg:province":"Baden-W\u00fcrttemberg",
    "wof:name":"Preissler",
    "wof:placetype":"venue"
},
  "geometry": {"coordinates":[8.579403,48.846703],"type":"Point"}
}