{
  "type": "Feature",
  "properties": {
    "iso:country":"DE",
    "sg:address":"Hohe Dammgasse 7",
    "sg:city":"B\u00fcdingen",
    "sg:phone":"+49 6042/2575",
    "sg:postcode":"63654",
    "sg:province":"Hessen",
    "wof:name":"H. Wagner Inh. Rolf Wagner",
    "wof:placetype":"venue"
},
  "geometry": {"coordinates":[9.1152334213,50.2938041687],"type":"Point"}
}