{
  "type": "Feature",
  "properties": {
    "iso:country":"DE",
    "sg:address":"Burgstr. 73",
    "sg:city":"Sankt Augustin",
    "sg:phone":"+49 2241/91360",
    "sg:postcode":"53757",
    "sg:province":"Nordrhein-Westfalen",
    "wof:name":"Josef Hupperich Gmbh",
    "wof:placetype":"venue"
},
  "geometry": {"coordinates":[7.1574430466,50.7896614075],"type":"Point"}
}