{
  "type": "Feature",
  "properties": {
    "iso:country":"DE",
    "sg:address":"Eichh\u00f6rnchenweg 42",
    "sg:city":"Neubrandenburg",
    "sg:phone":"+49 395/7781830",
    "sg:postcode":"17036",
    "sg:province":"Mecklenburg-Vorpommern",
    "wof:name":"H. Helm",
    "wof:placetype":"venue"
},
  "geometry": {"coordinates":[13.297418,53.543488],"type":"Point"}
}