{
  "type": "Feature",
  "properties": {
    "iso:country":"DE",
    "sg:address":"Speldrop 7",
    "sg:city":"Rees",
    "sg:phone":"+49 2851/1396",
    "sg:postcode":"46459",
    "sg:province":"Nordrhein-Westfalen",
    "wof:name":"Maria Verhalen",
    "wof:placetype":"venue"
},
  "geometry": {"coordinates":[6.387037,51.780121],"type":"Point"}
}