{
  "type": "Feature",
  "properties": {
    "iso:country":"DE",
    "sg:address":"Gestade 7",
    "sg:city":"Bernkastel-Kues",
    "sg:phone":"+49 6531/95340",
    "sg:postcode":"54470",
    "sg:province":"Rheinland-Pfalz",
    "wof:name":"Jacob Astor Gmbh & Co. Im- Und Export Kg",
    "wof:placetype":"venue"
},
  "geometry": {"coordinates":[7.07482,49.915981],"type":"Point"}
}