{
  "type": "Feature",
  "properties": {
    "iso:country":"DE",
    "sg:address":"Hammergm\u00fcnd",
    "sg:city":"Grafenw\u00f6hr",
    "sg:phone":"+49 9641/2357",
    "sg:postcode":"92655",
    "sg:province":"Bayern",
    "wof:name":"Anton Kraus",
    "wof:placetype":"venue"
},
  "geometry": {"coordinates":[11.9117746353,49.7179718018],"type":"Point"}
}