{
  "type": "Feature",
  "properties": {
    "iso:country":"DE",
    "sg:address":"Schulstr. 19",
    "sg:city":"Unterensingen",
    "sg:phone":"+49 7022/64737",
    "sg:postcode":"72669",
    "sg:province":"Baden-W\u00fcrttemberg",
    "wof:name":"Martino",
    "wof:placetype":"venue"
},
  "geometry": {"coordinates":[9.3537893295,48.6580276489],"type":"Point"}
}