{
  "type": "Feature",
  "properties": {
    "iso:country":"DE",
    "sg:address":"Am Jungbrunnen 7",
    "sg:city":"Dortmund",
    "sg:phone":"+49 231/310841",
    "sg:postcode":"44369",
    "sg:province":"Nordrhein-Westfalen",
    "wof:name":"Borchardt & Partner Plan- Und Wohnungsbau Gmbh",
    "wof:placetype":"venue"
},
  "geometry": {"coordinates":[7.4158701897,51.5324859619],"type":"Point"}
}