{
  "type": "Feature",
  "properties": {
    "iso:country":"DE",
    "sg:address":"Schmahlweg 1",
    "sg:city":"Hamburg",
    "sg:phone":"+49 40/67563322",
    "sg:postcode":"22143",
    "sg:province":"Hamburg",
    "wof:name":"Hpu Manfred Heinemann",
    "wof:placetype":"venue"
},
  "geometry": {"coordinates":[10.1608610153,53.6057090759],"type":"Point"}
}