{
  "type": "Feature",
  "properties": {
    "iso:country":"DE",
    "sg:address":"Lindenstr. 26",
    "sg:city":"Niendorf",
    "sg:phone":"+49 38750/20516",
    "sg:postcode":"19294",
    "sg:province":"Mecklenburg-Vorpommern",
    "wof:name":"J. Margraff",
    "wof:placetype":"venue"
},
  "geometry": {"coordinates":[11.324238,53.240295],"type":"Point"}
}