{
  "type": "Feature",
  "properties": {
    "iso:country":"DE",
    "sg:address":"Spittlertorgraben 13",
    "sg:city":"N\u00fcrnberg",
    "sg:phone":"+49 800 1808800",
    "sg:postcode":"90429",
    "sg:province":"Bayern",
    "wof:name":"Nefkom Telekommunikation Gmbh & Co Kg",
    "wof:placetype":"venue"
},
  "geometry": {"coordinates":[11.0651769638,49.4498291016],"type":"Point"}
}