{
  "type": "Feature",
  "properties": {
    "iso:country":"DE",
    "sg:address":"Marienstr. 3",
    "sg:city":"Naumburg",
    "sg:phone":"+49 3445/200847",
    "sg:postcode":"06618",
    "sg:province":"Sachsen-Anhalt",
    "wof:name":"Lotze",
    "wof:placetype":"venue"
},
  "geometry": {"coordinates":[11.8110265732,51.1526031494],"type":"Point"}
}