{
  "type": "Feature",
  "properties": {
    "iso:country":"DE",
    "sg:address":"Nieder-Ramst\u00fcdter Str. 2",
    "sg:city":"Darmstadt",
    "sg:phone":"+49 4961/5121306",
    "sg:postcode":"64283",
    "sg:province":"Hessen",
    "wof:name":"Ludwig-georgs-gymnasium Darmstadt",
    "wof:placetype":"venue"
},
  "geometry": {"coordinates":[8.657387,49.869568],"type":"Point"}
}