{
  "type": "Feature",
  "properties": {
    "iso:country":"DE",
    "sg:address":"Gro\u00dfer M\u00fchlenweg 41",
    "sg:city":"Kaarst",
    "sg:phone":"+49 2131/666807",
    "sg:postcode":"41564",
    "sg:province":"Nordrhein-Westfalen",
    "wof:name":"Willi Bohr",
    "wof:placetype":"venue"
},
  "geometry": {"coordinates":[6.623837,51.210381],"type":"Point"}
}