{
  "type": "Feature",
  "properties": {
    "iso:country":"DE",
    "sg:address":"Hauffstr. 2",
    "sg:city":"Brackenheim",
    "sg:phone":"+49 7135/2160",
    "sg:postcode":"74336",
    "sg:province":"Baden-W\u00fcrttemberg",
    "wof:name":"B. Hackh",
    "wof:placetype":"venue"
},
  "geometry": {"coordinates":[9.0683689117,49.075920105],"type":"Point"}
}