{
  "type": "Feature",
  "properties": {
    "iso:country":"DE",
    "sg:address":"Johann-Kelberg-Weg 2",
    "sg:city":"Soest",
    "sg:postcode":"59494",
    "sg:province":"Nordrhein-Westfalen",
    "wof:name":"Heck Verm\u00f6gensverwaltungs Gmbh",
    "wof:placetype":"venue"
},
  "geometry": {"coordinates":[8.0956783295,51.571521759],"type":"Point"}
}