{
  "type": "Feature",
  "properties": {
    "iso:country":"DE",
    "sg:address":"Heinrich-Rumpf-Str. 19",
    "sg:city":"Haltern",
    "sg:phone":"+49 2364/169323",
    "sg:postcode":"45721",
    "sg:province":"Nordrhein-Westfalen",
    "wof:name":"Ing.-b\u00fcro Tr\u00e4umner Planungs- Und Handels Gmbh",
    "wof:placetype":"venue"
},
  "geometry": {"coordinates":[7.181181,51.74828],"type":"Point"}
}