{
  "type": "Feature",
  "properties": {
    "iso:country":"DE",
    "sg:address":"Albachinger Str. 11",
    "sg:city":"Edling",
    "sg:postcode":"83533",
    "sg:province":"Bayern",
    "wof:name":"T S Gmbh",
    "wof:placetype":"venue"
},
  "geometry": {"coordinates":[12.166639,48.059547],"type":"Point"}
}