{
  "type": "Feature",
  "properties": {
    "iso:country":"DE",
    "sg:address":"Helbetorstr. 15",
    "sg:city":"Wei\u00dfensee",
    "sg:phone":"+49 36374/20209",
    "sg:postcode":"99631",
    "sg:province":"Th\u00fcringen",
    "wof:name":"Erholung",
    "wof:placetype":"venue"
},
  "geometry": {"coordinates":[11.0626993179,51.2015190125],"type":"Point"}
}