{
  "type": "Feature",
  "properties": {
    "iso:country":"DE",
    "sg:address":"G\u00f6schwitzer Str. 38",
    "sg:city":"Jena",
    "sg:phone":"+49 4936/416290",
    "sg:postcode":"07745",
    "sg:province":"Th\u00fcringen",
    "wof:name":"Jentech Datensysteme Ag",
    "wof:placetype":"venue"
},
  "geometry": {"coordinates":[11.5959701538,50.8873291016],"type":"Point"}
}