{
  "type": "Feature",
  "properties": {
    "iso:country":"DE",
    "sg:address":"Wiesenstr. 7",
    "sg:city":"Dentlein",
    "sg:phone":"+49 9855/1655",
    "sg:postcode":"91599",
    "sg:province":"Bayern",
    "wof:name":"Edeka Aktiv Frischmarkt Gmbh",
    "wof:placetype":"venue"
},
  "geometry": {"coordinates":[10.4402418137,49.1363182068],"type":"Point"}
}