{
  "type": "Feature",
  "properties": {
    "iso:country":"DE",
    "sg:address":"Rodensteiner Str. 13",
    "sg:city":"Fr\u00e4nkisch-Crumbach",
    "sg:phone":"+49 6164/2560",
    "sg:postcode":"64407",
    "sg:province":"Hessen",
    "wof:name":"Restaurant Crumbacher Stuben",
    "wof:placetype":"venue"
},
  "geometry": {"coordinates":[8.8534097672,49.744758606],"type":"Point"}
}