{
  "type": "Feature",
  "properties": {
    "iso:country":"DE",
    "sg:address":"Peiner Str. 28",
    "sg:city":"Wendeburg",
    "sg:phone":"+49 5303/91070",
    "sg:postcode":"38176",
    "sg:province":"Niedersachsen",
    "wof:name":"Kospro Kosmetik- Produktionsges. Mbh",
    "wof:placetype":"venue"
},
  "geometry": {"coordinates":[10.3879365921,52.3266525269],"type":"Point"}
}