{
  "type": "Feature",
  "properties": {
    "iso:country":"DE",
    "sg:address":"Bahnhofplatz 9",
    "sg:city":"Konstanz",
    "sg:phone":"+49 7531/22936",
    "sg:postcode":"78462",
    "sg:province":"Baden-W\u00fcrttemberg",
    "wof:name":"A. Oettinger Inh. Carl Karrer",
    "wof:placetype":"venue"
},
  "geometry": {"coordinates":[9.1772823334,47.65965271],"type":"Point"}
}