{
  "type": "Feature",
  "properties": {
    "iso:country":"DE",
    "sg:address":"Am S\u00e4gewerk 19",
    "sg:city":"Mainz",
    "sg:phone":"+49 6131/41957",
    "sg:postcode":"55124",
    "sg:province":"Rheinland-Pfalz",
    "wof:name":"H. Und D. Becker",
    "wof:placetype":"venue"
},
  "geometry": {"coordinates":[8.215923,49.996353],"type":"Point"}
}