{
  "type": "Feature",
  "properties": {
    "iso:country":"DE",
    "sg:address":"Am Haus Langen 11",
    "sg:city":"Everswinkel",
    "sg:phone":"+49 2582/5692",
    "sg:postcode":"48351",
    "sg:province":"Nordrhein-Westfalen",
    "wof:name":"Klaus Bosenius",
    "wof:placetype":"venue"
},
  "geometry": {"coordinates":[7.8564,51.924747],"type":"Point"}
}