{
  "type": "Feature",
  "properties": {
    "iso:country":"DE",
    "sg:address":"Schulweg 04",
    "sg:city":"Clau\u00dfnitz",
    "sg:phone":"+49 37202/89342",
    "sg:postcode":"09236",
    "sg:province":"Sachsen",
    "wof:name":"Sprachbuero Anglistik",
    "wof:placetype":"venue"
},
  "geometry": {"coordinates":[12.884593,50.936745],"type":"Point"}
}