{
  "type": "Feature",
  "properties": {
    "iso:country":"DE",
    "sg:address":"Bahnhofstr. 28",
    "sg:city":"Langenau",
    "sg:phone":"+49 7345/5288",
    "sg:postcode":"89129",
    "sg:province":"Baden-W\u00fcrttemberg",
    "wof:name":"Armin Dedlmar",
    "wof:placetype":"venue"
},
  "geometry": {"coordinates":[10.123365,48.496258],"type":"Point"}
}