{
  "type": "Feature",
  "properties": {
    "iso:country":"DE",
    "sg:address":"Erasmusstr. 14",
    "sg:city":"Berlin",
    "sg:postcode":"10553",
    "sg:province":"Berlin",
    "wof:name":"Reo Verkaufsf\u00f6rderung Gmbh",
    "wof:placetype":"venue"
},
  "geometry": {"coordinates":[13.3250932693,52.5264511108],"type":"Point"}
}