{
  "type": "Feature",
  "properties": {
    "iso:country":"DE",
    "sg:address":"Dorotheenstr. 168",
    "sg:city":"Bonn",
    "sg:postcode":"53119",
    "sg:province":"Nordrhein-Westfalen",
    "wof:name":"Derman - G. Deniz E. K.",
    "wof:placetype":"venue"
},
  "geometry": {"coordinates":[7.081304,50.742893],"type":"Point"}
}