{
  "type": "Feature",
  "properties": {
    "iso:country":"DE",
    "sg:address":"Schie\u00dfhausstr. 3",
    "sg:city":"Erlangen",
    "sg:phone":"+49 9131/601201",
    "sg:postcode":"91058",
    "sg:province":"Bayern",
    "wof:name":"Sch\u00fctzenheim",
    "wof:placetype":"venue"
},
  "geometry": {"coordinates":[10.9860334396,49.5575027466],"type":"Point"}
}