{
  "type": "Feature",
  "properties": {
    "iso:country":"DE",
    "sg:address":"Gro\u00dfholzhausen",
    "sg:city":"Raubling",
    "sg:phone":"+49 8034/3423",
    "sg:postcode":"83064",
    "sg:province":"Bayern",
    "wof:name":"Johann Antretter",
    "wof:placetype":"venue"
},
  "geometry": {"coordinates":[12.1091814041,47.7878379822],"type":"Point"}
}