{
  "type": "Feature",
  "properties": {
    "iso:country":"DE",
    "sg:address":"Sitzingerstr. 6",
    "sg:city":"Worms",
    "sg:phone":"+49 6241/75937",
    "sg:postcode":"67549",
    "sg:province":"Rheinland-Pfalz",
    "wof:name":"Willi Neiss",
    "wof:placetype":"venue"
},
  "geometry": {"coordinates":[8.3272161484,49.634262085],"type":"Point"}
}