{
  "type": "Feature",
  "properties": {
    "iso:country":"DE",
    "sg:address":"Friedrichstr. 28",
    "sg:city":"Balingen",
    "sg:phone":"+49 7433/7185",
    "sg:postcode":"72336",
    "sg:province":"Baden-W\u00fcrttemberg",
    "wof:name":"Andreas Hengsteler",
    "wof:placetype":"venue"
},
  "geometry": {"coordinates":[8.8511066437,48.274307251],"type":"Point"}
}