{
  "type": "Feature",
  "properties": {
    "iso:country":"DE",
    "sg:address":"Klippe 9",
    "sg:city":"Querfurt",
    "sg:postcode":"06268",
    "sg:province":"Sachsen-Anhalt",
    "wof:name":"Optik Markt S\u00f6lzer",
    "wof:placetype":"venue"
},
  "geometry": {"coordinates":[11.5990381241,51.3794975281],"type":"Point"}
}