{
  "type": "Feature",
  "properties": {
    "iso:country":"DE",
    "sg:address":"Paulinenstr. 6",
    "sg:city":"Dei\u00dflingen",
    "sg:phone":"+49 7420/576",
    "sg:postcode":"78652",
    "sg:province":"Baden-W\u00fcrttemberg",
    "wof:name":"Peter Wei\u00df Steuerberater",
    "wof:placetype":"venue"
},
  "geometry": {"coordinates":[8.6013736725,48.1086120605],"type":"Point"}
}