{
  "type": "Feature",
  "properties": {
    "iso:country":"DE",
    "sg:address":"Steinfurter Str. 3",
    "sg:city":"M\u00fcnster",
    "sg:phone":"+49 251/272259",
    "sg:postcode":"48149",
    "sg:province":"Nordrhein-Westfalen",
    "wof:name":"Spielothek",
    "wof:placetype":"venue"
},
  "geometry": {"coordinates":[7.6140851974,51.967792511],"type":"Point"}
}