{
  "type": "Feature",
  "properties": {
    "iso:country":"DE",
    "sg:address":"Meisenweg 1",
    "sg:city":"Kaiserslautern",
    "sg:phone":"+49 631/59172",
    "sg:postcode":"67663",
    "sg:province":"Rheinland-Pfalz",
    "wof:name":"P. Sachs Gmbh",
    "wof:placetype":"venue"
},
  "geometry": {"coordinates":[7.740904,49.437756],"type":"Point"}
}