{
  "type": "Feature",
  "properties": {
    "iso:country":"DE",
    "sg:address":"B\u00e4ckerstr. 6",
    "sg:city":"Burgheim",
    "sg:phone":"+49 8432/1748",
    "sg:postcode":"86666",
    "sg:province":"Bayern",
    "wof:name":"Josef M\u00fcller",
    "wof:placetype":"venue"
},
  "geometry": {"coordinates":[11.0489206314,48.6755027771],"type":"Point"}
}