{
  "type": "Feature",
  "properties": {
    "iso:country":"DE",
    "sg:address":"Schillerstr. 5",
    "sg:city":"Gnoien",
    "sg:phone":"+49 39971/12184",
    "sg:postcode":"17179",
    "sg:province":"Mecklenburg-Vorpommern",
    "wof:name":"Oehmcke Orthop\u00e4die-schuhtechnik Gmbh",
    "wof:placetype":"venue"
},
  "geometry": {"coordinates":[12.702986,53.966988],"type":"Point"}
}