{
  "type": "Feature",
  "properties": {
    "iso:country":"DE",
    "sg:address":"Schwohenend 19",
    "sg:city":"Korschenbroich",
    "sg:phone":"+49 2182/4328",
    "sg:postcode":"41352",
    "sg:province":"Nordrhein-Westfalen",
    "wof:name":"Karl Schumacher",
    "wof:placetype":"venue"
},
  "geometry": {"coordinates":[6.575558,51.164009],"type":"Point"}
}