{
  "type": "Feature",
  "properties": {
    "iso:country":"DE",
    "sg:address":"Eckstr. 9",
    "sg:city":"Velbert",
    "sg:phone":"+49 2051/53006",
    "sg:postcode":"42551",
    "sg:province":"Nordrhein-Westfalen",
    "wof:name":"Gebr. Brus",
    "wof:placetype":"venue"
},
  "geometry": {"coordinates":[7.0395531654,51.3454742432],"type":"Point"}
}