{
  "type": "Feature",
  "properties": {
    "iso:country":"DE",
    "sg:address":"Bahnhofstr.",
    "sg:city":"Walschleben",
    "sg:phone":"+49 36201/6420",
    "sg:postcode":"99189",
    "sg:province":"Th\u00fcringen",
    "wof:name":"Adam Bauer Bauunternehmen Gmbh & Co. Kg",
    "wof:placetype":"venue"
},
  "geometry": {"coordinates":[10.9465847015,51.0670089722],"type":"Point"}
}