{
  "type": "Feature",
  "properties": {
    "iso:country":"DE",
    "sg:address":"Marktstr. 9",
    "sg:city":"Hindelang",
    "sg:phone":"+49 8324/8920",
    "sg:postcode":"87541",
    "sg:province":"Bayern",
    "wof:name":"Gemeindeb\u00fccherei Rathaus",
    "wof:placetype":"venue"
},
  "geometry": {"coordinates":[10.371346,47.506485],"type":"Point"}
}