{
  "type": "Feature",
  "properties": {
    "iso:country":"DE",
    "sg:address":"Marienweg 18",
    "sg:city":"Stuhr",
    "sg:phone":"+49 4206/9006",
    "sg:postcode":"28816",
    "sg:province":"Niedersachsen",
    "wof:name":"Hackfeld Gmbh & Co.",
    "wof:placetype":"venue"
},
  "geometry": {"coordinates":[8.7027006149,52.9648857117],"type":"Point"}
}