{
  "type": "Feature",
  "properties": {
    "iso:country":"DE",
    "sg:address":"Brennesstr. 9",
    "sg:city":"Bayerisch Eisenstein",
    "sg:phone":"+49 9925/278",
    "sg:postcode":"94252",
    "sg:province":"Bayern",
    "wof:name":"F\u00fcrstl. Hohenzollernsche Arber-bergbahn E. K.",
    "wof:placetype":"venue"
},
  "geometry": {"coordinates":[13.195789,49.125229],"type":"Point"}
}