{
  "type": "Feature",
  "properties": {
    "iso:country":"DE",
    "sg:address":"Wilmannsberg 16",
    "sg:city":"Bremen",
    "sg:phone":"+49 421/662264",
    "sg:postcode":"28757",
    "sg:province":"Bremen",
    "wof:name":"A. Kuhlmann",
    "wof:placetype":"venue"
},
  "geometry": {"coordinates":[8.6246099472,53.1717796326],"type":"Point"}
}