{
  "type": "Feature",
  "properties": {
    "iso:country":"DE",
    "sg:address":"Lindenstr. 9",
    "sg:city":"B\u00e4chingen",
    "sg:phone":"+49 7325/5326",
    "sg:postcode":"89431",
    "sg:province":"Bayern",
    "wof:name":"Wolfgang Bendele",
    "wof:placetype":"venue"
},
  "geometry": {"coordinates":[10.3125801086,48.5474586487],"type":"Point"}
}