{
  "type": "Feature",
  "properties": {
    "iso:country":"DE",
    "sg:address":"Nebelhornstr. 28",
    "sg:city":"Schwabm\u00fcnchen",
    "sg:postcode":"86830",
    "sg:province":"Bayern",
    "wof:name":"A. Bernstein",
    "wof:placetype":"venue"
},
  "geometry": {"coordinates":[10.744714,48.171227],"type":"Point"}
}