{
  "type": "Feature",
  "properties": {
    "iso:country":"DE",
    "sg:address":"Moselstr. 71",
    "sg:city":"Troisdorf",
    "sg:phone":"+49 2241/82233",
    "sg:postcode":"53842",
    "sg:province":"Nordrhein-Westfalen",
    "wof:name":"Gastst\u00e4tte Kleine Taverne",
    "wof:placetype":"venue"
},
  "geometry": {"coordinates":[7.151927948,50.8088874817],"type":"Point"}
}