{
  "type": "Feature",
  "properties": {
    "iso:country":"DE",
    "sg:address":"Hochstr. 76",
    "sg:city":"Lahnstein",
    "sg:phone":"+49 2621/50606",
    "sg:postcode":"56112",
    "sg:province":"Rheinland-Pfalz",
    "wof:name":"Delphi",
    "wof:placetype":"venue"
},
  "geometry": {"coordinates":[7.6065859795,50.2980918884],"type":"Point"}
}