{
  "type": "Feature",
  "properties": {
    "iso:country":"DE",
    "sg:address":"Gartenwiese 16",
    "sg:city":"Alf",
    "sg:phone":"+49 6542/2405",
    "sg:postcode":"56859",
    "sg:province":"Rheinland-Pfalz",
    "wof:name":"Karl B\u00f6mer",
    "wof:placetype":"venue"
},
  "geometry": {"coordinates":[7.12495,50.05584],"type":"Point"}
}