{
  "type": "Feature",
  "properties": {
    "iso:country":"DE",
    "sg:address":"Klosterstr. 19",
    "sg:city":"Br\u00fcggen",
    "sg:phone":"+49 2163/58305",
    "sg:postcode":"41379",
    "sg:province":"Nordrhein-Westfalen",
    "wof:name":"Br\u00fcggener Stuben",
    "wof:placetype":"venue"
},
  "geometry": {"coordinates":[6.1849808693,51.239982605],"type":"Point"}
}