{
  "type": "Feature",
  "properties": {
    "iso:country":"DE",
    "sg:address":"Auf der Scheib",
    "sg:city":"Saarbr\u00fccken",
    "sg:phone":"+49 681/780282",
    "sg:postcode":"66115",
    "sg:province":"Saarland",
    "wof:name":"Gastst\u00e4tte Vereinshaus Kleingartenbauverein",
    "wof:placetype":"venue"
},
  "geometry": {"coordinates":[6.9409999847,49.2476768494],"type":"Point"}
}