{
  "type": "Feature",
  "properties": {
    "iso:country":"DE",
    "sg:address":"Sechs\u00e4cker 22",
    "sg:city":"Vellmar",
    "sg:phone":"+49 561/8201955",
    "sg:postcode":"34246",
    "sg:province":"Hessen",
    "wof:name":"Pro Vidus Finanz- Und Versicherungsmakler",
    "wof:placetype":"venue"
},
  "geometry": {"coordinates":[9.4820156097,51.3595581055],"type":"Point"}
}