{
  "type": "Feature",
  "properties": {
    "iso:country":"DE",
    "sg:address":"Sonnenstr. 37",
    "sg:city":"Waldaschaff",
    "sg:postcode":"63857",
    "sg:province":"Bayern",
    "wof:name":"Claudia Hoberg-welp Krankengymnastin",
    "wof:placetype":"venue"
},
  "geometry": {"coordinates":[9.293659,49.975063],"type":"Point"}
}