{
  "type": "Feature",
  "properties": {
    "iso:country":"DE",
    "sg:address":"H\u00f6fer Br\u00fchlweg 4",
    "sg:city":"Leinfelden-Echterdingen",
    "sg:phone":"+49 711/7942341",
    "sg:postcode":"70771",
    "sg:province":"Baden-W\u00fcrttemberg",
    "wof:name":"Ewald Bloching",
    "wof:placetype":"venue"
},
  "geometry": {"coordinates":[9.1752157211,48.6698608398],"type":"Point"}
}