{
  "type": "Feature",
  "properties": {
    "iso:country":"DE",
    "sg:address":"Nymphenburger Str. 160",
    "sg:city":"M\u00fcnchen",
    "sg:phone":"+49 89/13016460",
    "sg:postcode":"80634",
    "sg:province":"Bayern",
    "wof:name":"Winthir-apotheke",
    "wof:placetype":"venue"
},
  "geometry": {"coordinates":[11.533884,48.152946],"type":"Point"}
}