{
  "type": "Feature",
  "properties": {
    "iso:country":"DE",
    "sg:address":"Hadlichstr.",
    "sg:city":"Berlin",
    "sg:postcode":"13187",
    "sg:province":"Berlin",
    "wof:name":"Kaisers Verbrauchermarkt",
    "wof:placetype":"venue"
},
  "geometry": {"coordinates":[13.4133195877,52.568611145],"type":"Point"}
}