{
  "type": "Feature",
  "properties": {
    "iso:country":"DE",
    "sg:address":"Am Hohen Rain 3",
    "sg:city":"Bubesheim",
    "sg:phone":"+49 8221/4812",
    "sg:postcode":"89347",
    "sg:province":"Bayern",
    "wof:name":"Peter Laub",
    "wof:placetype":"venue"
},
  "geometry": {"coordinates":[10.256863,48.437176],"type":"Point"}
}