{
  "type": "Feature",
  "properties": {
    "iso:country":"DE",
    "sg:address":"Grafenberger Allee 300",
    "sg:city":"D\u00fcsseldorf",
    "sg:phone":"+49 211/6920",
    "sg:postcode":"40237",
    "sg:province":"Nordrhein-Westfalen",
    "wof:name":"Arbeitsamt D\u00fcsseldorf",
    "wof:placetype":"venue"
},
  "geometry": {"coordinates":[6.819901,51.236015],"type":"Point"}
}