{
  "type": "Feature",
  "properties": {
    "iso:country":"DE",
    "sg:address":"Ansbacher Str. 68",
    "sg:city":"Bechhofen",
    "sg:phone":"+49 9822/333",
    "sg:postcode":"91572",
    "sg:province":"Bayern",
    "wof:name":"Ernst Bock & Sohn Ohg",
    "wof:placetype":"venue"
},
  "geometry": {"coordinates":[10.558049202,49.1625366211],"type":"Point"}
}