{
  "type": "Feature",
  "properties": {
    "iso:country":"DE",
    "sg:address":"M\u00f6llner Landstr. 76",
    "sg:city":"Glinde",
    "sg:postcode":"21509",
    "sg:province":"Schleswig-Holstein",
    "wof:name":"Konrad Sill",
    "wof:placetype":"venue"
},
  "geometry": {"coordinates":[10.211631,53.540733],"type":"Point"}
}