{
  "type": "Feature",
  "properties": {
    "iso:country":"DE",
    "sg:address":"Erlenstr. 1",
    "sg:city":"Bochum",
    "sg:phone":"+49 234/313333",
    "sg:postcode":"44795",
    "sg:province":"Nordrhein-Westfalen",
    "wof:name":"Theo Lutter Ingenieur",
    "wof:placetype":"venue"
},
  "geometry": {"coordinates":[7.2072939873,51.4646606445],"type":"Point"}
}