{
  "type": "Feature",
  "properties": {
    "iso:country":"DE",
    "sg:address":"Atterseestr. 18",
    "sg:city":"M\u00fcnchen",
    "sg:phone":"+49 89/8345411",
    "sg:postcode":"81241",
    "sg:province":"Bayern",
    "wof:name":"Ulrich Knoch Architekt",
    "wof:placetype":"venue"
},
  "geometry": {"coordinates":[11.476633,48.144768],"type":"Point"}
}