{
  "type": "Feature",
  "properties": {
    "iso:country":"DE",
    "sg:address":"M\u00f6rikeweg 15",
    "sg:city":"Hagen",
    "sg:phone":"+49 2331/61184",
    "sg:postcode":"58099",
    "sg:province":"Nordrhein-Westfalen",
    "wof:name":"August Brauckmann Gmbh",
    "wof:placetype":"venue"
},
  "geometry": {"coordinates":[7.474656,51.387329],"type":"Point"}
}