{
  "type": "Feature",
  "properties": {
    "iso:country":"DE",
    "sg:address":"Burgstr. 21",
    "sg:city":"Wernigerode",
    "sg:phone":"+49 3943/92350",
    "sg:postcode":"38855",
    "sg:province":"Sachsen-Anhalt",
    "wof:name":"B & S B\u00fcro Und Service Gmbh",
    "wof:placetype":"venue"
},
  "geometry": {"coordinates":[10.788752,51.833038],"type":"Point"}
}