{
  "type": "Feature",
  "properties": {
    "iso:country":"DE",
    "sg:address":"Dorfstr. 25",
    "sg:city":"D\u00fcrrwangen",
    "sg:phone":"+49 9856/4875",
    "sg:postcode":"91602",
    "sg:province":"Bayern",
    "wof:name":"Kadar-industriemontagen Ohg",
    "wof:placetype":"venue"
},
  "geometry": {"coordinates":[10.416279,49.09816],"type":"Point"}
}