{
  "type": "Feature",
  "properties": {
    "iso:country":"DE",
    "sg:address":"Kaiserstr. 1",
    "sg:city":"Rees",
    "sg:phone":"+49 2850/7736",
    "sg:postcode":"46459",
    "sg:province":"Nordrhein-Westfalen",
    "wof:name":"W. Tenhagen",
    "wof:placetype":"venue"
},
  "geometry": {"coordinates":[6.458434,51.775852],"type":"Point"}
}