{
  "type": "Feature",
  "properties": {
    "iso:country":"DE",
    "sg:address":"Hochstr. 29",
    "sg:city":"Ebersburg",
    "sg:phone":"+49 6656/252",
    "sg:postcode":"36157",
    "sg:province":"Hessen",
    "wof:name":"Otto Krug Inh. W. Fuchs",
    "wof:placetype":"venue"
},
  "geometry": {"coordinates":[9.794826,50.483818],"type":"Point"}
}