{
  "type": "Feature",
  "properties": {
    "iso:country":"DE",
    "sg:address":"Niederwall 53",
    "sg:city":"Bielefeld",
    "sg:phone":"+49 521/9675390",
    "sg:postcode":"33602",
    "sg:province":"Nordrhein-Westfalen",
    "wof:name":"Bergler Pr / Presse- Und \u00d6ffentlichkeitsarbeit",
    "wof:placetype":"venue"
},
  "geometry": {"coordinates":[8.533692,52.017502],"type":"Point"}
}