{
  "type": "Feature",
  "properties": {
    "iso:country":"DE",
    "sg:address":"Zum Selsberg 33",
    "sg:city":"Beverungen",
    "sg:phone":"+49 5273/6890",
    "sg:postcode":"37688",
    "sg:province":"Nordrhein-Westfalen",
    "wof:name":"Bernhard Hake Zeltverleih",
    "wof:placetype":"venue"
},
  "geometry": {"coordinates":[9.3685445786,51.6750068665],"type":"Point"}
}