{
  "type": "Feature",
  "properties": {
    "iso:country":"DE",
    "sg:address":"Esslinger Str. 7",
    "sg:city":"Altbach",
    "sg:phone":"+49 7153/22481",
    "sg:postcode":"73776",
    "sg:province":"Baden-W\u00fcrttemberg",
    "wof:name":"Richard Barth",
    "wof:placetype":"venue"
},
  "geometry": {"coordinates":[9.370222,48.724895],"type":"Point"}
}