{
  "type": "Feature",
  "properties": {
    "iso:country":"DE",
    "sg:address":"Bolongarostr. 131",
    "sg:city":"Frankfurt",
    "sg:phone":"+49 69/313493",
    "sg:postcode":"65929",
    "sg:province":"Hessen",
    "wof:name":"Kaysser-apotheke",
    "wof:placetype":"venue"
},
  "geometry": {"coordinates":[8.549887,50.100079],"type":"Point"}
}