{
  "type": "Feature",
  "properties": {
    "iso:country":"DE",
    "sg:address":"Kleine Reichenstr. 1",
    "sg:city":"Hamburg",
    "sg:postcode":"20457",
    "sg:province":"Hamburg",
    "wof:name":"Tascon Verm\u00f6gens Treuhand Gmbh",
    "wof:placetype":"venue"
},
  "geometry": {"coordinates":[9.9983444214,53.5482559204],"type":"Point"}
}