{
  "type": "Feature",
  "properties": {
    "iso:country":"DE",
    "sg:address":"Stahlstr. 5",
    "sg:city":"Velbert",
    "sg:phone":"+49 2051/254927",
    "sg:postcode":"42551",
    "sg:province":"Nordrhein-Westfalen",
    "wof:name":"E. Br\u00fcck",
    "wof:placetype":"venue"
},
  "geometry": {"coordinates":[7.070975,51.348663],"type":"Point"}
}