{
  "type": "Feature",
  "properties": {
    "iso:country":"DE",
    "sg:address":"Magstadter Str 12",
    "sg:city":"Leonberg",
    "sg:phone":"+49 7152/30920",
    "sg:postcode":"71229",
    "sg:province":"Baden-W\u00fcrttemberg",
    "wof:name":"Hebe",
    "wof:placetype":"venue"
},
  "geometry": {"coordinates":[8.989164,48.761955],"type":"Point"}
}