{
  "type": "Feature",
  "properties": {
    "iso:country":"DE",
    "sg:address":"Bachstr. 4",
    "sg:city":"Rosenfeld",
    "sg:phone":"+49 7428/93930",
    "sg:postcode":"72348",
    "sg:province":"Baden-W\u00fcrttemberg",
    "wof:name":"Rosenfelder Knopffabrik Gmbh",
    "wof:placetype":"venue"
},
  "geometry": {"coordinates":[8.730456,48.287853],"type":"Point"}
}