{
  "type": "Feature",
  "properties": {
    "iso:country":"DE",
    "sg:city":"Stuttgart",
    "sg:postcode":"70182",
    "sg:province":"Baden-W\u00fcrttemberg",
    "wof:name":"Strohecker Consulting",
    "wof:placetype":"venue"
},
  "geometry": {"coordinates":[9.18425,48.776718],"type":"Point"}
}