{
  "type": "Feature",
  "properties": {
    "iso:country":"DE",
    "sg:address":"Ludolfstr. 50",
    "sg:city":"Hamburg",
    "sg:phone":"+49 40/473057",
    "sg:postcode":"20249",
    "sg:province":"Hamburg",
    "wof:name":"Sellmer & Co.restaurant Inh. Dieter Pauly",
    "wof:placetype":"venue"
},
  "geometry": {"coordinates":[9.991765976,53.5926895142],"type":"Point"}
}