{
  "type": "Feature",
  "properties": {
    "iso:country":"DE",
    "sg:address":"Lange Str. 28",
    "sg:city":"Oederan",
    "sg:phone":"+49 37292/4250",
    "sg:postcode":"09569",
    "sg:province":"Sachsen",
    "wof:name":"Sabine Ringel",
    "wof:placetype":"venue"
},
  "geometry": {"coordinates":[13.16774,50.858818],"type":"Point"}
}