{
  "type": "Feature",
  "properties": {
    "iso:country":"DE",
    "sg:address":"Lehenb\u00fchlstr. 9",
    "sg:city":"Renningen",
    "sg:phone":"+49 7159/936700",
    "sg:postcode":"71272",
    "sg:province":"Baden-W\u00fcrttemberg",
    "wof:name":"K. P. Mundinger Gmbh",
    "wof:placetype":"venue"
},
  "geometry": {"coordinates":[8.934387,48.773121],"type":"Point"}
}