{
  "type": "Feature",
  "properties": {
    "iso:country":"DE",
    "sg:address":"Im Wiesengrund 1",
    "sg:city":"M\u00f6nchengladbach",
    "sg:phone":"+49 2161/662733",
    "sg:postcode":"41066",
    "sg:province":"Nordrhein-Westfalen",
    "wof:name":"Erich Becker",
    "wof:placetype":"venue"
},
  "geometry": {"coordinates":[6.485233,51.23394],"type":"Point"}
}