{
  "type": "Feature",
  "properties": {
    "iso:country":"DE",
    "sg:address":"Mahlenziener Str. 19",
    "sg:city":"Brandenburg",
    "sg:postcode":"14774",
    "sg:province":"Brandenburg",
    "wof:name":"Kirchm\u00f6seraner Wasserwanderer E. V.",
    "wof:placetype":"venue"
},
  "geometry": {"coordinates":[12.4211349487,52.3774490356],"type":"Point"}
}