{
  "type": "Feature",
  "properties": {
    "iso:country":"DE",
    "sg:address":"Germaniastr. 26",
    "sg:city":"Krefeld",
    "sg:phone":"+49 2151/593583",
    "sg:postcode":"47800",
    "sg:province":"Nordrhein-Westfalen",
    "wof:name":"H. Grubert Ingenieur",
    "wof:placetype":"venue"
},
  "geometry": {"coordinates":[6.5872712135,51.3404083252],"type":"Point"}
}