{
  "type": "Feature",
  "properties": {
    "iso:country":"DE",
    "sg:address":"Walrodstr. 17",
    "sg:city":"Mei\u00dfner",
    "sg:phone":"+49 5657/435",
    "sg:postcode":"37290",
    "sg:province":"Hessen",
    "wof:name":"Heinrich Becker",
    "wof:placetype":"venue"
},
  "geometry": {"coordinates":[9.962745,51.21822],"type":"Point"}
}