{
  "type": "Feature",
  "properties": {
    "iso:country":"DE",
    "sg:address":"Theodor-Heuss-Str. 12a",
    "sg:city":"Waldkirch",
    "sg:phone":"+49 7681/9104",
    "sg:postcode":"79183",
    "sg:province":"Baden-W\u00fcrttemberg",
    "wof:name":"Cego-club Waldkirch Max B\u00fchler",
    "wof:placetype":"venue"
},
  "geometry": {"coordinates":[7.96667099,48.09633255],"type":"Point"}
}