{
  "type": "Feature",
  "properties": {
    "iso:country":"DE",
    "sg:address":"Fischerwinkel 14",
    "sg:city":"Ra\u00dfnitz",
    "sg:phone":"+49 34605/20275",
    "sg:postcode":"06184",
    "sg:province":"Sachsen-Anhalt",
    "wof:name":"C. Voigt",
    "wof:placetype":"venue"
},
  "geometry": {"coordinates":[12.0912475586,51.3909759521],"type":"Point"}
}