{
  "type": "Feature",
  "properties": {
    "iso:country":"DE",
    "sg:address":"Heidsteige 2",
    "sg:city":"Wolpertshausen",
    "sg:phone":"+49 7907/1566",
    "sg:postcode":"74549",
    "sg:province":"Baden-W\u00fcrttemberg",
    "wof:name":"Erich Kern",
    "wof:placetype":"venue"
},
  "geometry": {"coordinates":[9.829796,49.151077],"type":"Point"}
}