{
  "type": "Feature",
  "properties": {
    "iso:country":"DE",
    "sg:address":"Lingener Str. 4",
    "sg:city":"Rheine",
    "sg:phone":"+49 5971/70251",
    "sg:postcode":"48429",
    "sg:province":"Nordrhein-Westfalen",
    "wof:name":"Kannacher",
    "wof:placetype":"venue"
},
  "geometry": {"coordinates":[7.4440951347,52.2802696228],"type":"Point"}
}