{
  "type": "Feature",
  "properties": {
    "iso:country":"DE",
    "sg:address":"Messeplatz 8-10",
    "sg:city":"Florstadt",
    "sg:phone":"+49 6035/5816",
    "sg:postcode":"61197",
    "sg:province":"Hessen",
    "wof:name":"J\u00fcrgen Klein",
    "wof:placetype":"venue"
},
  "geometry": {"coordinates":[8.8607578278,50.3193054199],"type":"Point"}
}