{
  "type": "Feature",
  "properties": {
    "iso:country":"DE",
    "sg:address":"Am Lindenhofe 25",
    "sg:city":"Hannover",
    "sg:phone":"+49 511/841313",
    "sg:postcode":"30519",
    "sg:province":"Niedersachsen",
    "wof:name":"Form Art Grafik U. Design Gmbh",
    "wof:placetype":"venue"
},
  "geometry": {"coordinates":[9.7625370026,52.3344535828],"type":"Point"}
}