{
  "type": "Feature",
  "properties": {
    "iso:country":"DE",
    "sg:address":"\u00c4u\u00dfere Oberaustr. 14",
    "sg:city":"Rosenheim",
    "sg:phone":"+49 8031/41961",
    "sg:postcode":"83026",
    "sg:province":"Bayern",
    "wof:name":"Wilhelm Dreher",
    "wof:placetype":"venue"
},
  "geometry": {"coordinates":[12.0798330307,47.8508796692],"type":"Point"}
}