{
  "type": "Feature",
  "properties": {
    "iso:country":"DE",
    "sg:address":"Im Garthof 53",
    "sg:city":"Bovenden",
    "sg:phone":"+49 5594/8402",
    "sg:postcode":"37120",
    "sg:province":"Niedersachsen",
    "wof:name":"Immoinvesta E. K.",
    "wof:placetype":"venue"
},
  "geometry": {"coordinates":[9.9531841278,51.5963821411],"type":"Point"}
}