{
  "type": "Feature",
  "properties": {
    "iso:country":"DE",
    "sg:address":"Frohe Zukunft 34",
    "sg:city":"Luckenwalde",
    "sg:phone":"+49 3371/614552",
    "sg:postcode":"14943",
    "sg:province":"Brandenburg",
    "wof:name":"Dr. Gunnar George",
    "wof:placetype":"venue"
},
  "geometry": {"coordinates":[13.1592903137,52.1014442444],"type":"Point"}
}