{
  "type": "Feature",
  "properties": {
    "iso:country":"DE",
    "sg:address":"Am Rahmtor 7",
    "sg:city":"Oberursel",
    "sg:phone":"+49 6171/55355",
    "sg:postcode":"61440",
    "sg:province":"Hessen",
    "wof:name":"Leonhard Schumacher",
    "wof:placetype":"venue"
},
  "geometry": {"coordinates":[8.5759983063,50.2018241882],"type":"Point"}
}