{
  "type": "Feature",
  "properties": {
    "iso:country":"DE",
    "sg:address":"Enzer Str. 7",
    "sg:city":"Stadthagen",
    "sg:phone":"+49 5721/79021",
    "sg:postcode":"31655",
    "sg:province":"Niedersachsen",
    "wof:name":"Behnke Und Menke Rechtsanw\u00e4lte",
    "wof:placetype":"venue"
},
  "geometry": {"coordinates":[9.2007541656,52.3235473633],"type":"Point"}
}