{
  "type": "Feature",
  "properties": {
    "iso:country":"DE",
    "sg:address":"Marktplatz",
    "sg:city":"Memmingen",
    "sg:phone":"+49 8331/191",
    "sg:postcode":"87700",
    "sg:province":"Bayern",
    "wof:name":"Erziehungsberatungsstelle Stadtjugendamt",
    "wof:placetype":"venue"
},
  "geometry": {"coordinates":[10.1804304123,47.9866409302],"type":"Point"}
}