{
  "type": "Feature",
  "properties": {
    "iso:country":"DE",
    "sg:address":"Auf der Hohlmauer 2",
    "sg:city":"Kriftel",
    "sg:phone":"+49 6192/42961",
    "sg:postcode":"65830",
    "sg:province":"Hessen",
    "wof:name":"Josef Henrich Obstanbau",
    "wof:placetype":"venue"
},
  "geometry": {"coordinates":[8.4585847855,50.0793609619],"type":"Point"}
}