{
  "type": "Feature",
  "properties": {
    "iso:country":"DE",
    "sg:address":"\u00c4u\u00dfere Heinrichstr. 1",
    "sg:city":"Thalheim",
    "sg:phone":"+49 3721/85289",
    "sg:postcode":"09380",
    "sg:province":"Sachsen",
    "wof:name":"K. Friedrich",
    "wof:placetype":"venue"
},
  "geometry": {"coordinates":[12.8453350067,50.6998748779],"type":"Point"}
}