{
  "type": "Feature",
  "properties": {
    "iso:country":"DE",
    "sg:address":"Loshardt 12",
    "sg:city":"Kall",
    "sg:phone":"+49 2441/5908",
    "sg:postcode":"53925",
    "sg:province":"Nordrhein-Westfalen",
    "wof:name":"Hotel-restaurant Haus Hensch",
    "wof:placetype":"venue"
},
  "geometry": {"coordinates":[6.5506777763,50.5373382568],"type":"Point"}
}