{
  "type": "Feature",
  "properties": {
    "iso:country":"DE",
    "sg:address":"Riemker Str. 13",
    "sg:city":"Bochum",
    "sg:phone":"+49 234/54511",
    "sg:postcode":"44809",
    "sg:province":"Nordrhein-Westfalen",
    "wof:name":"China-imbiss Huynh",
    "wof:placetype":"venue"
},
  "geometry": {"coordinates":[7.1928119659,51.5082130432],"type":"Point"}
}