{
  "type": "Feature",
  "properties": {
    "iso:country":"DE",
    "sg:address":"Schleu\u00dfnerstr. 58 b",
    "sg:city":"Neu-Isenburg",
    "sg:phone":"+49 6102/6600",
    "sg:postcode":"63263",
    "sg:province":"Hessen",
    "wof:name":"Taxi-reibert Gmbh",
    "wof:placetype":"venue"
},
  "geometry": {"coordinates":[8.6822681427,50.0477104187],"type":"Point"}
}