{
  "type": "Feature",
  "properties": {
    "iso:country":"DE",
    "sg:address":"Kehreinstr. 2",
    "sg:city":"Frankfurt",
    "sg:phone":"+49 69/396532",
    "sg:postcode":"65934",
    "sg:province":"Hessen",
    "wof:name":"A. Leeb Textilwaren",
    "wof:placetype":"venue"
},
  "geometry": {"coordinates":[8.5674705505,50.1015396118],"type":"Point"}
}