{
  "type": "Feature",
  "properties": {
    "iso:country":"DE",
    "sg:address":"Billrothstr. 29",
    "sg:city":"Braunschweig",
    "sg:phone":"+49 531/514351",
    "sg:postcode":"38116",
    "sg:province":"Niedersachsen",
    "wof:name":"Rolf Bammel",
    "wof:placetype":"venue"
},
  "geometry": {"coordinates":[10.462155,52.289539],"type":"Point"}
}