{
  "type": "Feature",
  "properties": {
    "iso:country":"DE",
    "sg:address":"Bahnhaus 1",
    "sg:city":"Marburg",
    "sg:phone":"+49 6421/43935",
    "sg:postcode":"35043",
    "sg:province":"Hessen",
    "wof:name":"A. B. I. Aktiv Baumaschinen Und Industriebedarf Gmbh",
    "wof:placetype":"venue"
},
  "geometry": {"coordinates":[8.760887,50.78392],"type":"Point"}
}