{
  "type": "Feature",
  "properties": {
    "iso:country":"DE",
    "sg:address":"Postfach 1204",
    "sg:city":"Isny",
    "sg:phone":"+49 7562/913436",
    "sg:postcode":"88306",
    "wof:name":"Isnet E.v.",
    "wof:placetype":"venue"
},
  "geometry": {"coordinates":[10.0394897461,47.6921691895],"type":"Point"}
}