{
  "type": "Feature",
  "properties": {
    "iso:country":"DE",
    "sg:address":"Rauher Kamp 8",
    "sg:city":"Dortmund",
    "sg:phone":"+49 231/800325",
    "sg:postcode":"44339",
    "sg:province":"Nordrhein-Westfalen",
    "wof:name":"Manfred Schulz",
    "wof:placetype":"venue"
},
  "geometry": {"coordinates":[7.4631490707,51.5847511292],"type":"Point"}
}