{
  "type": "Feature",
  "properties": {
    "iso:country":"DE",
    "sg:address":"Marktplatz 39",
    "sg:city":"Biberach",
    "sg:phone":"+49 7351/12658",
    "sg:postcode":"88400",
    "sg:province":"Baden-W\u00fcrttemberg",
    "wof:name":"Reisch Ohg",
    "wof:placetype":"venue"
},
  "geometry": {"coordinates":[9.786860466,48.0971183777],"type":"Point"}
}