{
  "type": "Feature",
  "properties": {
    "iso:country":"DE",
    "sg:address":"Martinistr. 5",
    "sg:city":"Recklinghausen",
    "sg:phone":"+49 2361/26737",
    "sg:postcode":"45657",
    "sg:province":"Nordrhein-Westfalen",
    "wof:name":"Kunsthaus Schr\u00f6der",
    "wof:placetype":"venue"
},
  "geometry": {"coordinates":[7.200698,51.616226],"type":"Point"}
}