{
  "type": "Feature",
  "properties": {
    "iso:country":"DE",
    "sg:address":"Von-Hasencamp-Str. 14",
    "sg:city":"Harsum",
    "sg:phone":"+49 5127/5166",
    "sg:postcode":"31177",
    "sg:province":"Niedersachsen",
    "wof:name":"Kollakowski",
    "wof:placetype":"venue"
},
  "geometry": {"coordinates":[9.962296,52.204502],"type":"Point"}
}