{
  "type": "Feature",
  "properties": {
    "iso:country":"DE",
    "sg:address":"Comeniusweg 1-3",
    "sg:city":"K\u00f6ln",
    "sg:postcode":"51143",
    "sg:province":"Nordrhein-Westfalen",
    "wof:name":"Mediarent Gesellschaft F\u00fcr Den Vertrieb Und Service Von",
    "wof:placetype":"venue"
},
  "geometry": {"coordinates":[7.0389289856,50.8642349243],"type":"Point"}
}