{
  "type": "Feature",
  "properties": {
    "iso:country":"DE",
    "sg:address":"Am Lohof 35a",
    "sg:city":"Jesteburg",
    "sg:phone":"+49 4183/3424",
    "sg:postcode":"21266",
    "sg:province":"Niedersachsen",
    "wof:name":"Gerhard Werner",
    "wof:placetype":"venue"
},
  "geometry": {"coordinates":[9.963507,53.320629],"type":"Point"}
}