{
  "type": "Feature",
  "properties": {
    "iso:country":"DE",
    "sg:address":"Thomas-Mann-Str. 1",
    "sg:city":"Berlin",
    "sg:phone":"+49 30/42852020",
    "sg:postcode":"10409",
    "sg:province":"Berlin",
    "wof:name":"M\u00fchlenberg Apotheke Inh. Susanne Kluczynski",
    "wof:placetype":"venue"
},
  "geometry": {"coordinates":[13.442133,52.543312],"type":"Point"}
}