{
  "type": "Feature",
  "properties": {
    "iso:country":"DE",
    "sg:address":"Kalker Hauptstr. 216",
    "sg:city":"K\u00f6ln",
    "sg:phone":"+49 221/8701910",
    "sg:postcode":"51103",
    "sg:province":"Nordrhein-Westfalen",
    "wof:name":"Hotel B\u00f6hmer",
    "wof:placetype":"venue"
},
  "geometry": {"coordinates":[7.0078001022,50.9386329651],"type":"Point"}
}