{
  "type": "Feature",
  "properties": {
    "iso:country":"DE",
    "sg:address":"Kohlheckstr. 37",
    "sg:city":"Wiesbaden",
    "sg:phone":"+49 611/468040",
    "sg:postcode":"65199",
    "sg:province":"Hessen",
    "wof:name":"Lorenz-werthmann-haus",
    "wof:placetype":"venue"
},
  "geometry": {"coordinates":[8.192336,50.08173],"type":"Point"}
}