{
  "type": "Feature",
  "properties": {
    "iso:country":"DE",
    "sg:address":"Obergasse 23 - 25",
    "sg:city":"Zwingenberg",
    "sg:phone":"+49 6251/788146",
    "sg:postcode":"64673",
    "sg:province":"Hessen",
    "wof:name":"Fewa Wagner Gmbh",
    "wof:placetype":"venue"
},
  "geometry": {"coordinates":[8.613338,49.723927],"type":"Point"}
}