{
  "type": "Feature",
  "properties": {
    "iso:country":"DE",
    "sg:address":"Neumarkt 20",
    "sg:city":"Schleiz",
    "sg:phone":"+49 3663/428537",
    "sg:postcode":"07907",
    "sg:province":"Th\u00fcringen",
    "wof:name":"Cafe Riedl Inh. Lutz Wagner",
    "wof:placetype":"venue"
},
  "geometry": {"coordinates":[11.8090047836,50.576751709],"type":"Point"}
}