{
  "type": "Feature",
  "properties": {
    "iso:country":"DE",
    "sg:address":"Kleine Str. 14",
    "sg:city":"Heyen",
    "sg:phone":"+49 5533/5443",
    "sg:postcode":"37619",
    "sg:province":"Niedersachsen",
    "wof:name":"Steinbrink",
    "wof:placetype":"venue"
},
  "geometry": {"coordinates":[9.506376,52.012215],"type":"Point"}
}