{
  "type": "Feature",
  "properties": {
    "iso:country":"DE",
    "sg:address":"H\u00f6rlbacher Str. 9",
    "sg:city":"Abensberg",
    "sg:postcode":"93326",
    "sg:province":"Bayern",
    "wof:name":"Far East Trading Agency Gmbh",
    "wof:placetype":"venue"
},
  "geometry": {"coordinates":[11.8641300201,48.8079528809],"type":"Point"}
}