{
  "type": "Feature",
  "properties": {
    "iso:country":"DE",
    "sg:address":"Steinbeisstr. 6",
    "sg:city":"Gammertingen",
    "sg:phone":"+49 7574/4000",
    "sg:postcode":"72501",
    "sg:province":"Baden-W\u00fcrttemberg",
    "wof:name":"Preisser Messtechnik Gmbh & Co. Kg",
    "wof:placetype":"venue"
},
  "geometry": {"coordinates":[9.215059,48.243435],"type":"Point"}
}