{
  "type": "Feature",
  "properties": {
    "iso:country":"DE",
    "sg:city":"Karlsruhe",
    "sg:postcode":"76137",
    "sg:province":"Baden-W\u00fcrttemberg",
    "wof:name":"Rechtsanw\u00e4lte Scholz & Noetzel In Karlsruhe",
    "wof:placetype":"venue"
},
  "geometry": {"coordinates":[8.409202,49.010376],"type":"Point"}
}