{
  "type": "Feature",
  "properties": {
    "iso:country":"DE",
    "sg:address":"Oststr. 130",
    "sg:city":"Niederahr",
    "sg:phone":"+49 6435/8448",
    "sg:postcode":"56414",
    "sg:province":"Rheinland-Pfalz",
    "wof:name":"K. Lauf",
    "wof:placetype":"venue"
},
  "geometry": {"coordinates":[7.86617,50.491291],"type":"Point"}
}