{
  "type": "Feature",
  "properties": {
    "iso:country":"DE",
    "sg:address":"Kaufingerstr. 13",
    "sg:city":"M\u00fcnchen",
    "sg:phone":"+49 89/231930",
    "sg:postcode":"80331",
    "sg:province":"Bayern",
    "wof:name":"C. & A.",
    "wof:placetype":"venue"
},
  "geometry": {"coordinates":[11.5717611313,48.1379547119],"type":"Point"}
}