{
  "type": "Feature",
  "properties": {
    "iso:country":"DE",
    "sg:address":"Glatzer Str. 23",
    "sg:city":"Hamburg",
    "sg:phone":"+49 40/67391120",
    "sg:postcode":"22045",
    "sg:province":"Hamburg",
    "wof:name":"Peter Zschirnt",
    "wof:placetype":"venue"
},
  "geometry": {"coordinates":[10.146062,53.577724],"type":"Point"}
}