{
  "type": "Feature",
  "properties": {
    "iso:country":"DE",
    "sg:address":"Martinistr. 7",
    "sg:city":"Neumarkt",
    "sg:postcode":"92318",
    "sg:province":"Bayern",
    "wof:name":"Vdk Kreisverband",
    "wof:placetype":"venue"
},
  "geometry": {"coordinates":[11.4547891617,49.2769165039],"type":"Point"}
}