{
  "type": "Feature",
  "properties": {
    "iso:country":"DE",
    "sg:address":"Neusalzer Str. 52 d",
    "sg:city":"Offenbach",
    "sg:phone":"+49 69/847008",
    "sg:postcode":"63069",
    "sg:province":"Hessen",
    "wof:name":"Uwe Entelmann Immobilien Janus",
    "wof:placetype":"venue"
},
  "geometry": {"coordinates":[8.7714548111,50.0848007202],"type":"Point"}
}