{
  "type": "Feature",
  "properties": {
    "iso:country":"DE",
    "sg:address":"Wipperf\u00fcrther Str. 117",
    "sg:city":"K\u00fcrten",
    "sg:phone":"+49 2207/4488",
    "sg:postcode":"51515",
    "sg:province":"Nordrhein-Westfalen",
    "wof:name":"U. Roeske",
    "wof:placetype":"venue"
},
  "geometry": {"coordinates":[7.2226901054,51.0119514465],"type":"Point"}
}