{
  "type": "Feature",
  "properties": {
    "iso:country":"DE",
    "sg:address":"Rubensweg 36",
    "sg:city":"Bocholt",
    "sg:phone":"+49 2871/37202",
    "sg:postcode":"46399",
    "sg:province":"Nordrhein-Westfalen",
    "wof:name":"Hans Brauwers Automaten Gmbh",
    "wof:placetype":"venue"
},
  "geometry": {"coordinates":[6.6110692024,51.8501434326],"type":"Point"}
}