{
  "type": "Feature",
  "properties": {
    "iso:country":"DE",
    "sg:address":"Ostring 1",
    "sg:city":"Gro\u00dfostheim",
    "sg:phone":"+49 6026/1736",
    "sg:postcode":"63762",
    "sg:province":"Bayern",
    "wof:name":"Hemberger & Kunze Gmbh",
    "wof:placetype":"venue"
},
  "geometry": {"coordinates":[9.04328,49.931],"type":"Point"}
}