{
  "type": "Feature",
  "properties": {
    "iso:country":"DE",
    "sg:address":"Weinbergstr. 1 a",
    "sg:city":"Eching",
    "sg:postcode":"85386",
    "sg:province":"Bayern",
    "wof:name":"Da Trachtn B\u00e4da Gmbh",
    "wof:placetype":"venue"
},
  "geometry": {"coordinates":[11.600887,48.32114],"type":"Point"}
}