{
  "type": "Feature",
  "properties": {
    "iso:country":"DE",
    "sg:address":"Braunfelser Str. 70",
    "sg:city":"Wetzlar",
    "sg:phone":"+49 6441/90100",
    "sg:postcode":"35578",
    "sg:province":"Hessen",
    "wof:name":"Werner Gimmler Wetzlarer Verkehrsbetriebe",
    "wof:placetype":"venue"
},
  "geometry": {"coordinates":[8.4759082794,50.5504150391],"type":"Point"}
}