{
  "type": "Feature",
  "properties": {
    "iso:country":"DE",
    "sg:address":"Karlstr. 43",
    "sg:city":"Friedrichshafen",
    "sg:phone":"+49 7541/22619",
    "sg:postcode":"88045",
    "sg:province":"Baden-W\u00fcrttemberg",
    "wof:name":"Cafe Soravia",
    "wof:placetype":"venue"
},
  "geometry": {"coordinates":[9.480758,47.649967],"type":"Point"}
}