{
  "type": "Feature",
  "properties": {
    "iso:country":"DE",
    "sg:address":"Hintermeierstr. 28",
    "sg:city":"M\u00fcnchen",
    "sg:phone":"+49 89/8128187",
    "sg:postcode":"80999",
    "sg:province":"Bayern",
    "wof:name":"Velsa Bau Gmbh",
    "wof:placetype":"venue"
},
  "geometry": {"coordinates":[11.467189,48.186577],"type":"Point"}
}