{
  "type": "Feature",
  "properties": {
    "iso:country":"DE",
    "sg:address":"Am Bruchheck 4",
    "sg:city":"Dortmund",
    "sg:phone":"+49 231/431299",
    "sg:postcode":"44263",
    "sg:province":"Nordrhein-Westfalen",
    "wof:name":"Dionysos Grill",
    "wof:placetype":"venue"
},
  "geometry": {"coordinates":[7.5013251305,51.4845924377],"type":"Point"}
}