{
  "type": "Feature",
  "properties": {
    "iso:country":"DE",
    "sg:address":"Lindenstr. 100",
    "sg:city":"Zorneding",
    "sg:phone":"+49 8106/29977",
    "sg:postcode":"85604",
    "sg:province":"Bayern",
    "wof:name":"S. K. Consulting Services Gesellschaft F\u00fcr Informations-",
    "wof:placetype":"venue"
},
  "geometry": {"coordinates":[11.8297748566,48.0843009949],"type":"Point"}
}