{
  "type": "Feature",
  "properties": {
    "iso:country":"DE",
    "sg:address":"Hauptstr. 16",
    "sg:city":"Baumholder",
    "sg:phone":"+49 6783/2719",
    "sg:postcode":"55774",
    "sg:province":"Rheinland-Pfalz",
    "wof:name":"Fritz Licht",
    "wof:placetype":"venue"
},
  "geometry": {"coordinates":[7.338655,49.615185],"type":"Point"}
}