{
  "type": "Feature",
  "properties": {
    "iso:country":"DE",
    "sg:address":"Emerich-Ambros-Ufer 50",
    "sg:city":"Dresden",
    "sg:phone":"+49 351/4220964",
    "sg:postcode":"01159",
    "sg:province":"Sachsen",
    "wof:name":"Ibeu Dresden E. V.",
    "wof:placetype":"venue"
},
  "geometry": {"coordinates":[13.6983203888,51.0526885986],"type":"Point"}
}