{
  "type": "Feature",
  "properties": {
    "iso:country":"DE",
    "sg:address":"Goslarer Str. 29",
    "sg:city":"Vienenburg",
    "sg:phone":"+49 5324/4783",
    "sg:postcode":"38690",
    "sg:province":"Niedersachsen",
    "wof:name":"Der Holl\u00e4nder",
    "wof:placetype":"venue"
},
  "geometry": {"coordinates":[10.556372,51.953423],"type":"Point"}
}