{
  "type": "Feature",
  "properties": {
    "iso:country":"DE",
    "sg:address":"Langestr. 28",
    "sg:city":"Kirchheim",
    "sg:phone":"+49 7362/7111",
    "sg:postcode":"73467",
    "sg:province":"Baden-W\u00fcrttemberg",
    "wof:name":"F. Schnele",
    "wof:placetype":"venue"
},
  "geometry": {"coordinates":[10.3988723755,48.8779602051],"type":"Point"}
}