{
  "type": "Feature",
  "properties": {
    "iso:country":"DE",
    "sg:address":"Kachstedter Weg 63",
    "sg:city":"Sch\u00f6nfeld",
    "sg:phone":"+49 3466/321892",
    "sg:postcode":"06556",
    "sg:province":"Th\u00fcringen",
    "wof:name":"Roy Koppa",
    "wof:placetype":"venue"
},
  "geometry": {"coordinates":[11.2644710541,51.365524292],"type":"Point"}
}