{
  "type": "Feature",
  "properties": {
    "iso:country":"DE",
    "sg:address":"Langewanneweg 43",
    "sg:city":"Hamm",
    "sg:phone":"+49 2381/50584",
    "sg:postcode":"59063",
    "sg:province":"Nordrhein-Westfalen",
    "wof:name":"Gerda W\u00fcnsche",
    "wof:placetype":"venue"
},
  "geometry": {"coordinates":[7.824778,51.669529],"type":"Point"}
}