{
  "type": "Feature",
  "properties": {
    "iso:country":"DE",
    "sg:address":"Klosterstr. 71",
    "sg:city":"Br\u00fcggen",
    "sg:phone":"+49 2163/7747",
    "sg:postcode":"41379",
    "sg:province":"Nordrhein-Westfalen",
    "wof:name":"G\u00fcnter Strick",
    "wof:placetype":"venue"
},
  "geometry": {"coordinates":[6.182351,51.241421],"type":"Point"}
}