{
  "type": "Feature",
  "properties": {
    "iso:country":"DE",
    "sg:address":"Kreuzstr 26",
    "sg:city":"Kreuzwertheim",
    "sg:phone":"+49 9342/9050",
    "sg:postcode":"97892",
    "sg:province":"Bayern",
    "wof:name":"Skt-kunststofftechnik Gmbh",
    "wof:placetype":"venue"
},
  "geometry": {"coordinates":[9.5240182877,49.7709999084],"type":"Point"}
}