{
  "type": "Feature",
  "properties": {
    "iso:country":"DE",
    "sg:address":"Strehlaer Str. 12",
    "sg:city":"Oschatz",
    "sg:phone":"+49 3435/928350",
    "sg:postcode":"04758",
    "sg:province":"Sachsen",
    "wof:name":"Hannelore Puchinger",
    "wof:placetype":"venue"
},
  "geometry": {"coordinates":[13.1101560593,51.2986106873],"type":"Point"}
}