{
  "type": "Feature",
  "properties": {
    "iso:country":"DE",
    "sg:address":"Friedensallee 29",
    "sg:city":"Hamburg",
    "sg:phone":"+49 40/39906508",
    "sg:postcode":"22765",
    "sg:province":"Hamburg",
    "wof:name":"Jens Bulnheim Rechtsanwalt",
    "wof:placetype":"venue"
},
  "geometry": {"coordinates":[9.924328804,53.5554733276],"type":"Point"}
}