{
  "type": "Feature",
  "properties": {
    "iso:country":"DE",
    "sg:address":"Bleicherstr. 23",
    "sg:city":"Bremen",
    "sg:phone":"+49 421/3398939",
    "sg:postcode":"28203",
    "sg:province":"Bremen",
    "wof:name":"Joachim Schulz Architekt",
    "wof:placetype":"venue"
},
  "geometry": {"coordinates":[8.816157,53.070721],"type":"Point"}
}