{
  "type": "Feature",
  "properties": {
    "iso:country":"DE",
    "sg:address":"M\u00fcnchhausenplatz 8",
    "sg:city":"Bodenwerder",
    "sg:phone":"+49 5533/3312",
    "sg:postcode":"37619",
    "sg:province":"Niedersachsen",
    "wof:name":"Oskar G\u00f6rlandt Inh. Thomas Lindenkohl E. K.",
    "wof:placetype":"venue"
},
  "geometry": {"coordinates":[9.5144376755,51.9756088257],"type":"Point"}
}