{
  "type": "Feature",
  "properties": {
    "iso:country":"DE",
    "sg:address":"Weiskircher Weg 9",
    "sg:city":"Heusenstamm",
    "sg:phone":"+49 6104/96050",
    "sg:postcode":"63150",
    "sg:province":"Hessen",
    "wof:name":"Harald Neppe",
    "wof:placetype":"venue"
},
  "geometry": {"coordinates":[8.8128099442,50.0577201843],"type":"Point"}
}