{
  "type": "Feature",
  "properties": {
    "iso:country":"DE",
    "sg:address":"Im Hafen",
    "sg:city":"Bendorf",
    "sg:postcode":"56170",
    "sg:province":"Rheinland-Pfalz",
    "wof:name":"United Parcel Service Deutschland Inc.",
    "wof:placetype":"venue"
},
  "geometry": {"coordinates":[7.5759048462,50.4201393127],"type":"Point"}
}