{
  "type": "Feature",
  "properties": {
    "iso:country":"DE",
    "sg:address":"Kart\u00e4usergasse 28",
    "sg:city":"K\u00f6ln",
    "sg:phone":"+49 221/317788",
    "sg:postcode":"50678",
    "sg:province":"Nordrhein-Westfalen",
    "wof:name":"Brigitte Baader",
    "wof:placetype":"venue"
},
  "geometry": {"coordinates":[6.9546661377,50.9256439209],"type":"Point"}
}