{
  "type": "Feature",
  "properties": {
    "iso:country":"DE",
    "sg:address":"Drahtzieherstr. 4a",
    "sg:city":"N\u00fcrnberg",
    "sg:phone":"+49 911/6312831",
    "sg:postcode":"90453",
    "sg:province":"Bayern",
    "wof:name":"Exart International Executive Art Design & Marketing Gmbh",
    "wof:placetype":"venue"
},
  "geometry": {"coordinates":[11.0235099792,49.3857498169],"type":"Point"}
}