{
  "type": "Feature",
  "properties": {
    "iso:country":"DE",
    "sg:address":"Karlsbergweg 8",
    "sg:city":"Mauerstetten",
    "sg:phone":"+49 8341/65883",
    "sg:postcode":"87665",
    "sg:province":"Bayern",
    "wof:name":"Kassen & Waagen Service Bernd E. K.",
    "wof:placetype":"venue"
},
  "geometry": {"coordinates":[10.666201,47.903667],"type":"Point"}
}