{
  "type": "Feature",
  "properties": {
    "iso:country":"DE",
    "sg:address":"Ridlerstr 31c",
    "sg:city":"M\u00fcnchen",
    "sg:phone":"+49 89/62370",
    "sg:postcode":"80339",
    "sg:province":"Bayern",
    "wof:name":"Kraftanlagen Anlagentechnik M\u00fcnchen Gmbh",
    "wof:placetype":"venue"
},
  "geometry": {"coordinates":[11.535553,48.132164],"type":"Point"}
}