{
  "type": "Feature",
  "properties": {
    "iso:country":"DE",
    "sg:address":"Huntestr. 25",
    "sg:city":"Rheine",
    "sg:phone":"+49 5971/2638",
    "sg:postcode":"48431",
    "sg:province":"Nordrhein-Westfalen",
    "wof:name":"Hans Und Anna M. Quellhorst Garten- Und Landschafts-",
    "wof:placetype":"venue"
},
  "geometry": {"coordinates":[7.409925,52.279587],"type":"Point"}
}