{
  "type": "Feature",
  "properties": {
    "iso:country":"DE",
    "sg:address":"Triererstrasse 4",
    "sg:city":"Bitburg",
    "sg:phone":"+49 6561/96540",
    "sg:postcode":"54634",
    "sg:province":"Rheinland-Pfalz",
    "wof:name":"Reiseb\u00fcro Olk Gmbh",
    "wof:placetype":"venue"
},
  "geometry": {"coordinates":[6.522318,49.968296],"type":"Point"}
}