{
  "type": "Feature",
  "properties": {
    "iso:country":"DE",
    "sg:address":"Pfadgasse 129",
    "sg:city":"Biblis",
    "sg:phone":"+49 6245/8016",
    "sg:postcode":"68647",
    "sg:province":"Hessen",
    "wof:name":"H. D. Wilhelm Mineral\u00f6le Gmbh",
    "wof:placetype":"venue"
},
  "geometry": {"coordinates":[8.462556,49.690594],"type":"Point"}
}