{
  "type": "Feature",
  "properties": {
    "iso:country":"DE",
    "sg:address":"An der Kirche 1",
    "sg:city":"Hannover",
    "sg:phone":"+49 511/463459",
    "sg:postcode":"30457",
    "sg:province":"Niedersachsen",
    "wof:name":"Johannes-apotheke",
    "wof:placetype":"venue"
},
  "geometry": {"coordinates":[9.691522,52.328903],"type":"Point"}
}