{
  "type": "Feature",
  "properties": {
    "iso:country":"DE",
    "sg:address":"Fontanestr. 20",
    "sg:city":"Leipzig",
    "sg:phone":"+49 341/8621958",
    "sg:postcode":"04289",
    "sg:province":"Sachsen",
    "wof:name":"Gudrun Spielmeyer",
    "wof:placetype":"venue"
},
  "geometry": {"coordinates":[12.428242,51.300102],"type":"Point"}
}