{
  "type": "Feature",
  "properties": {
    "iso:country":"DE",
    "sg:address":"Haller Str. 53",
    "sg:city":"K\u00fcnzelsau",
    "sg:phone":"+49 7940/57444",
    "sg:postcode":"74653",
    "sg:province":"Baden-W\u00fcrttemberg",
    "wof:name":"Alte Harmonie",
    "wof:placetype":"venue"
},
  "geometry": {"coordinates":[9.75963,49.263569],"type":"Point"}
}