{
  "type": "Feature",
  "properties": {
    "iso:country":"DE",
    "sg:address":"Hochkreuzallee 39",
    "sg:city":"Bonn",
    "sg:phone":"+49 228/643072",
    "sg:postcode":"53175",
    "sg:province":"Nordrhein-Westfalen",
    "wof:name":"Der Selbst\u00e4ndige Verlags- Gmbh",
    "wof:placetype":"venue"
},
  "geometry": {"coordinates":[7.1375660896,50.6958084106],"type":"Point"}
}