{
  "type": "Feature",
  "properties": {
    "iso:country":"DE",
    "sg:address":"Peter-Hartmann-Allee 1",
    "sg:city":"Bad Lippspringe",
    "sg:phone":"+49 5252/50303",
    "sg:postcode":"33175",
    "sg:province":"Nordrhein-Westfalen",
    "wof:name":"Touristik Und Marketing Gmbh",
    "wof:placetype":"venue"
},
  "geometry": {"coordinates":[8.8112592697,51.7855758667],"type":"Point"}
}