{
  "type": "Feature",
  "properties": {
    "iso:country":"DE",
    "sg:address":"Stra\u00dfburger Str. 32",
    "sg:city":"Alsdorf",
    "sg:phone":"+49 2404/97153",
    "sg:postcode":"52477",
    "sg:province":"Nordrhein-Westfalen",
    "wof:name":"Monika R\u00f6mer",
    "wof:placetype":"venue"
},
  "geometry": {"coordinates":[6.18693,50.862007],"type":"Point"}
}