{
  "type": "Feature",
  "properties": {
    "iso:country":"DE",
    "sg:address":"Brunsb\u00fctteler Damm 248",
    "sg:city":"Berlin",
    "sg:phone":"+49 30/3661948",
    "sg:postcode":"13581",
    "sg:province":"Berlin",
    "wof:name":"Hans-joachim Bauer",
    "wof:placetype":"venue"
},
  "geometry": {"coordinates":[13.160121,52.533386],"type":"Point"}
}