{
  "type": "Feature",
  "properties": {
    "iso:country":"DE",
    "sg:address":"Hallesche Str. 66",
    "sg:city":"K\u00f6then",
    "sg:phone":"+49 3496/557697",
    "sg:postcode":"06366",
    "sg:province":"Sachsen-Anhalt",
    "wof:name":"J\u00f6rg Handt",
    "wof:placetype":"venue"
},
  "geometry": {"coordinates":[11.972318,51.748947],"type":"Point"}
}