{
  "type": "Feature",
  "properties": {
    "iso:country":"DE",
    "sg:address":"Regensburger Str. 34",
    "sg:city":"Burglengenfeld",
    "sg:postcode":"93133",
    "sg:province":"Bayern",
    "wof:name":"Aral Ag",
    "wof:placetype":"venue"
},
  "geometry": {"coordinates":[12.0441522598,49.203868866],"type":"Point"}
}