{
  "type": "Feature",
  "properties": {
    "iso:country":"DE",
    "sg:address":"Boyenstr. 46",
    "sg:city":"Berlin",
    "sg:postcode":"10115",
    "sg:province":"Berlin",
    "wof:name":"Konnex-berlin Ges. F\u00fcr Strategische Finanzplanung Mbh",
    "wof:placetype":"venue"
},
  "geometry": {"coordinates":[13.3731460571,52.5378684998],"type":"Point"}
}