{
  "type": "Feature",
  "properties": {
    "iso:country":"DE",
    "sg:address":"Wiesenstr. 2",
    "sg:city":"Sch\u00f6ffengrund",
    "sg:phone":"+49 6445/7321",
    "sg:postcode":"35641",
    "sg:province":"Hessen",
    "wof:name":"Crass-regalcenter",
    "wof:placetype":"venue"
},
  "geometry": {"coordinates":[8.460417,50.514755],"type":"Point"}
}