{
  "type": "Feature",
  "properties": {
    "iso:country":"DE",
    "sg:address":"Hauptstr. 10",
    "sg:city":"Hitzhusen",
    "sg:phone":"+49 4192/898881",
    "sg:postcode":"24576",
    "sg:province":"Schleswig-Holstein",
    "wof:name":"Metallbau Radbruch Gmbh",
    "wof:placetype":"venue"
},
  "geometry": {"coordinates":[9.8562,53.922318],"type":"Point"}
}