{
  "type": "Feature",
  "properties": {
    "iso:country":"DE",
    "sg:address":"Ziegenhainer Str. 25",
    "sg:city":"Homberg",
    "sg:phone":"+49 5681/98850",
    "sg:postcode":"34576",
    "sg:province":"Hessen",
    "wof:name":"Lbh-steuerberatungsges. Mbh",
    "wof:placetype":"venue"
},
  "geometry": {"coordinates":[9.3999576569,51.0296020508],"type":"Point"}
}