{
  "type": "Feature",
  "properties": {
    "iso:country":"DE",
    "sg:address":"Wickering",
    "sg:city":"Gangkofen",
    "sg:phone":"+49 8722/1640",
    "sg:postcode":"84140",
    "sg:province":"Bayern",
    "wof:name":"W. Haberl",
    "wof:placetype":"venue"
},
  "geometry": {"coordinates":[12.5950098038,48.4215164185],"type":"Point"}
}