{
  "type": "Feature",
  "properties": {
    "iso:country":"DE",
    "sg:address":"Am Haibierl 10",
    "sg:city":"Roding",
    "sg:phone":"+49 9461/910026",
    "sg:postcode":"93426",
    "sg:province":"Bayern",
    "wof:name":"St. Michael Seniorenheim Gschwendner Gmbh",
    "wof:placetype":"venue"
},
  "geometry": {"coordinates":[12.5234,49.196785],"type":"Point"}
}