{
  "type": "Feature",
  "properties": {
    "iso:country":"DE",
    "sg:address":"Hauptstr. 20",
    "sg:city":"Ingersheim",
    "sg:phone":"+49 7142/51514",
    "sg:postcode":"74379",
    "sg:province":"Baden-W\u00fcrttemberg",
    "wof:name":"Manfred Schumacher",
    "wof:placetype":"venue"
},
  "geometry": {"coordinates":[9.199193,48.974274],"type":"Point"}
}