{
  "type": "Feature",
  "properties": {
    "iso:country":"DE",
    "sg:address":"Nibelungenplatz 17",
    "sg:city":"Braunschweig",
    "sg:phone":"+49 531/873287",
    "sg:postcode":"38106",
    "sg:province":"Niedersachsen",
    "wof:name":"Tadayon",
    "wof:placetype":"venue"
},
  "geometry": {"coordinates":[10.5274333954,52.2865257263],"type":"Point"}
}