{
  "type": "Feature",
  "properties": {
    "iso:country":"DE",
    "sg:address":"Bergstr. 11",
    "sg:city":"Egesheim",
    "sg:phone":"+49 7429/1220",
    "sg:postcode":"78592",
    "sg:province":"Baden-W\u00fcrttemberg",
    "wof:name":"Erika Gentner",
    "wof:placetype":"venue"
},
  "geometry": {"coordinates":[8.8557472229,48.1182556152],"type":"Point"}
}