{
  "type": "Feature",
  "properties": {
    "iso:country":"DE",
    "sg:address":"Kanalstr. 25",
    "sg:city":"Dortmund",
    "sg:phone":"+49 4923/19970",
    "sg:postcode":"44147",
    "sg:province":"Nordrhein-Westfalen",
    "wof:name":"Abb Process Industries Gmbh",
    "wof:placetype":"venue"
},
  "geometry": {"coordinates":[7.4526,51.524235],"type":"Point"}
}