{
  "type": "Feature",
  "properties": {
    "iso:country":"DE",
    "sg:address":"Dannenkoppel 5",
    "sg:city":"Hamburg",
    "sg:phone":"+49 40/5365569",
    "sg:postcode":"22391",
    "sg:province":"Hamburg",
    "wof:name":"Susanne Jensen-raschke Rechtsanw\u00e4ltin",
    "wof:placetype":"venue"
},
  "geometry": {"coordinates":[10.0825662613,53.635761261],"type":"Point"}
}