{
  "type": "Feature",
  "properties": {
    "iso:country":"DE",
    "sg:address":"Marktstr. 1",
    "sg:city":"Bad Lippspringe",
    "sg:phone":"+49 5252/973000",
    "sg:postcode":"33175",
    "sg:province":"Nordrhein-Westfalen",
    "wof:name":"H & W",
    "wof:placetype":"venue"
},
  "geometry": {"coordinates":[8.8203077316,51.7829246521],"type":"Point"}
}