{
  "type": "Feature",
  "properties": {
    "iso:country":"DE",
    "sg:address":"Daimlerstr. 104",
    "sg:city":"Stuttgart",
    "sg:postcode":"70372",
    "sg:province":"Baden-W\u00fcrttemberg",
    "wof:name":"Toom-baumarkt",
    "wof:placetype":"venue"
},
  "geometry": {"coordinates":[9.2204399109,48.7988510132],"type":"Point"}
}