{
  "type": "Feature",
  "properties": {
    "iso:country":"DE",
    "sg:address":"Walter-Rathenau-Str. 37",
    "sg:city":"Oelsnitz",
    "sg:phone":"+49 37421/222150",
    "sg:postcode":"08606",
    "sg:province":"Sachsen",
    "wof:name":"Kurt W\u00f6llner",
    "wof:placetype":"venue"
},
  "geometry": {"coordinates":[12.177688,50.417118],"type":"Point"}
}