{
  "type": "Feature",
  "properties": {
    "iso:country":"DE",
    "sg:address":"Leonhardstr. 12a",
    "sg:city":"Mering",
    "sg:phone":"+49 8233/9092",
    "sg:postcode":"86415",
    "sg:province":"Bayern",
    "wof:name":"W. Eberwein",
    "wof:placetype":"venue"
},
  "geometry": {"coordinates":[10.993284,48.261604],"type":"Point"}
}