{
  "type": "Feature",
  "properties": {
    "iso:country":"DE",
    "sg:address":"Praunheimer Weg 34 e",
    "sg:city":"Frankfurt",
    "sg:phone":"+49 69/574018",
    "sg:postcode":"60439",
    "sg:province":"Hessen",
    "wof:name":"Secon-ingenieur Gmbh",
    "wof:placetype":"venue"
},
  "geometry": {"coordinates":[8.64714,50.161766],"type":"Point"}
}