{
  "type": "Feature",
  "properties": {
    "iso:country":"DE",
    "sg:address":"Gewerbestr. 11",
    "sg:city":"Oschatz/Gaunitz",
    "sg:phone":"+49 3435/620045",
    "sg:postcode":"04758",
    "sg:province":"Sachsen",
    "wof:name":"Aquatec-reuter",
    "wof:placetype":"venue"
},
  "geometry": {"coordinates":[13.1191101074,51.3263015747],"type":"Point"}
}