{
  "type": "Feature",
  "properties": {
    "iso:country":"DE",
    "sg:address":"Alte Marktstr. 18",
    "sg:city":"Hameln",
    "sg:phone":"+49 5151/95080",
    "sg:postcode":"31785",
    "sg:province":"Niedersachsen",
    "wof:name":"Hotel Christinenhof",
    "wof:placetype":"venue"
},
  "geometry": {"coordinates":[9.3578701019,52.1020088196],"type":"Point"}
}