{
  "type": "Feature",
  "properties": {
    "iso:country":"DE",
    "sg:address":"Uslarer Str. 7",
    "sg:city":"Bodenfelde",
    "sg:phone":"+49 5572/921527",
    "sg:postcode":"37194",
    "sg:province":"Hessen",
    "wof:name":"Restaurant Bella Italia",
    "wof:placetype":"venue"
},
  "geometry": {"coordinates":[9.5590429306,51.636138916],"type":"Point"}
}