{
  "type": "Feature",
  "properties": {
    "iso:country":"DE",
    "sg:address":"K\u00f6bler Weg 85",
    "sg:city":"Hammersbach",
    "sg:phone":"+49 6185/81990",
    "sg:postcode":"63546",
    "sg:province":"Hessen",
    "wof:name":"Wolff Hartherz Und Weber Rechtsanw\u00e4lte",
    "wof:placetype":"venue"
},
  "geometry": {"coordinates":[8.9982404709,50.2293395996],"type":"Point"}
}