{
  "type": "Feature",
  "properties": {
    "iso:country":"DE",
    "sg:address":"Unterer Grasweg 25",
    "sg:city":"Ludwigshafen",
    "sg:phone":"+49 621/551198",
    "sg:postcode":"67065",
    "sg:province":"Rheinland-Pfalz",
    "wof:name":"Vereinsgastst\u00e4tte Sc Alemania Maudach E. V.",
    "wof:placetype":"venue"
},
  "geometry": {"coordinates":[8.3771409988,49.4496421814],"type":"Point"}
}