{
  "type": "Feature",
  "properties": {
    "iso:country":"DE",
    "sg:address":"Hermann-Krimmer-Weg 9",
    "sg:city":"Backnang",
    "sg:phone":"+49 7191/65864",
    "sg:postcode":"71522",
    "sg:province":"Baden-W\u00fcrttemberg",
    "wof:name":"I. Auer",
    "wof:placetype":"venue"
},
  "geometry": {"coordinates":[9.430331,48.948448],"type":"Point"}
}