{
  "type": "Feature",
  "properties": {
    "iso:country":"DE",
    "sg:address":"Tulpenstr. 16",
    "sg:city":"Pressath",
    "sg:phone":"+49 9644/8097",
    "sg:postcode":"92690",
    "sg:province":"Bayern",
    "wof:name":"Anna Gr\u00fcnberger",
    "wof:placetype":"venue"
},
  "geometry": {"coordinates":[11.935652,49.771572],"type":"Point"}
}