{
  "type": "Feature",
  "properties": {
    "iso:country":"DE",
    "sg:address":"Sch\u00fctzenstr. 19",
    "sg:city":"Landshut",
    "sg:phone":"+49 871/51773",
    "sg:postcode":"84028",
    "sg:province":"Bayern",
    "wof:name":"Andreas Hauptmer Grabdenkm\u00e4ler",
    "wof:placetype":"venue"
},
  "geometry": {"coordinates":[12.1702766418,48.5447158813],"type":"Point"}
}