{
  "type": "Feature",
  "properties": {
    "iso:country":"DE",
    "sg:address":"Altenholte 19",
    "sg:city":"H\u00fcckeswagen",
    "sg:phone":"+49 2192/2519",
    "sg:postcode":"42499",
    "sg:province":"Nordrhein-Westfalen",
    "wof:name":"Wilhelm Marquardt",
    "wof:placetype":"venue"
},
  "geometry": {"coordinates":[7.330104,51.12978],"type":"Point"}
}