{
  "type": "Feature",
  "properties": {
    "iso:country":"DE",
    "sg:address":"K\u00e4rrnerweg",
    "sg:city":"Leipzig",
    "sg:phone":"+49 341/8781342",
    "sg:postcode":"04299",
    "sg:province":"Sachsen",
    "wof:name":"Am K\u00e4rrnerweg",
    "wof:placetype":"venue"
},
  "geometry": {"coordinates":[12.4308958054,51.3205528259],"type":"Point"}
}