{
  "type": "Feature",
  "properties": {
    "iso:country":"DE",
    "sg:address":"Ruhrfelder Str. 39",
    "sg:city":"M\u00f6nchengladbach",
    "sg:phone":"+49 2166/606217",
    "sg:postcode":"41199",
    "sg:province":"Nordrhein-Westfalen",
    "wof:name":"Gernot Laue",
    "wof:placetype":"venue"
},
  "geometry": {"coordinates":[6.4478912354,51.1361923218],"type":"Point"}
}