{
  "type": "Feature",
  "properties": {
    "iso:country":"DE",
    "sg:address":"Bergstr. 4",
    "sg:city":"A\u00dflar",
    "sg:phone":"+49 6440/209",
    "sg:postcode":"35614",
    "sg:province":"Hessen",
    "wof:name":"Henrich Gmbh & Co. Kg",
    "wof:placetype":"venue"
},
  "geometry": {"coordinates":[8.4588317871,50.5936737061],"type":"Point"}
}