{
  "type": "Feature",
  "properties": {
    "iso:country":"DE",
    "sg:address":"Am Freistein 120",
    "sg:city":"Mettmann",
    "sg:phone":"+49 2104/73442",
    "sg:postcode":"40822",
    "sg:province":"Nordrhein-Westfalen",
    "wof:name":"Peter Graf Ingenieur",
    "wof:placetype":"venue"
},
  "geometry": {"coordinates":[6.9706201553,51.2445640564],"type":"Point"}
}