{
  "type": "Feature",
  "properties": {
    "iso:country":"DE",
    "sg:address":"Hubertusallee 7",
    "sg:city":"Berlin",
    "sg:phone":"+49 30/8927271",
    "sg:postcode":"14193",
    "sg:province":"Berlin",
    "wof:name":"Tiesing Gmbh",
    "wof:placetype":"venue"
},
  "geometry": {"coordinates":[13.284865,52.493469],"type":"Point"}
}