{
  "type": "Feature",
  "properties": {
    "iso:country":"DE",
    "sg:address":"Robert-Stolz-Str. 2",
    "sg:city":"Wiesbaden",
    "sg:phone":"+49 6122/92420",
    "sg:postcode":"65205",
    "sg:province":"Hessen",
    "wof:name":"Hotel-restaurant Schmucker Eck",
    "wof:placetype":"venue"
},
  "geometry": {"coordinates":[8.342256546,50.0662117004],"type":"Point"}
}