{
  "type": "Feature",
  "properties": {
    "iso:country":"DE",
    "sg:address":"Gustav-Sch\u00f6ller-Str. 7",
    "sg:city":"M\u00f6ssingen",
    "sg:phone":"+49 7473/22269",
    "sg:postcode":"72116",
    "sg:province":"Baden-W\u00fcrttemberg",
    "wof:name":"Andreas Und Beate Kommerell",
    "wof:placetype":"venue"
},
  "geometry": {"coordinates":[9.114008,48.415287],"type":"Point"}
}