{
  "type": "Feature",
  "properties": {
    "iso:country":"DE",
    "sg:address":"Haagstr. 27",
    "sg:city":"Weener",
    "sg:phone":"+49 4951/4569",
    "sg:postcode":"26826",
    "sg:province":"Niedersachsen",
    "wof:name":"Ali Atia",
    "wof:placetype":"venue"
},
  "geometry": {"coordinates":[7.3502488136,53.1640472412],"type":"Point"}
}