{
  "type": "Feature",
  "properties": {
    "iso:country":"DE",
    "sg:address":"Hoheluftchaussee 108",
    "sg:city":"Hamburg",
    "sg:phone":"+49 40/366469",
    "sg:postcode":"20253",
    "sg:province":"Hamburg",
    "wof:name":"Rudolf Franke",
    "wof:placetype":"venue"
},
  "geometry": {"coordinates":[9.969747,53.584351],"type":"Point"}
}