{
  "type": "Feature",
  "properties": {
    "iso:country":"DE",
    "sg:address":"Stadtplatz 37",
    "sg:city":"Vilsbiburg",
    "sg:phone":"+49 8741/4548",
    "sg:postcode":"84137",
    "sg:province":"Bayern",
    "wof:name":"M. Schmei\u00dfer",
    "wof:placetype":"venue"
},
  "geometry": {"coordinates":[12.3537340164,48.4494018555],"type":"Point"}
}