{
  "type": "Feature",
  "properties": {
    "iso:country":"DE",
    "sg:address":"Bl\u00fccherplatz 6",
    "sg:city":"Spenge",
    "sg:phone":"+49 5225/87920",
    "sg:postcode":"32139",
    "sg:province":"Nordrhein-Westfalen",
    "wof:name":"Hotel Zum Bl\u00fccherplatz",
    "wof:placetype":"venue"
},
  "geometry": {"coordinates":[8.4901037216,52.1407966614],"type":"Point"}
}