{
  "type": "Feature",
  "properties": {
    "iso:country":"DE",
    "sg:address":"Am M\u00fchlenberg 12",
    "sg:city":"Bad Arolsen",
    "sg:phone":"+49 5691/911691",
    "sg:postcode":"34454",
    "sg:province":"Hessen",
    "wof:name":"Hindernisbau Und Reitsport - Ihr Spezialist",
    "wof:placetype":"venue"
},
  "geometry": {"coordinates":[9.0540466309,51.3779373169],"type":"Point"}
}