{
  "type": "Feature",
  "properties": {
    "iso:country":"DE",
    "sg:address":"Aachener Str. 59",
    "sg:city":"Koblenz",
    "sg:phone":"+49 261/9224290",
    "sg:postcode":"56072",
    "sg:province":"Rheinland-Pfalz",
    "wof:name":"Franz-josef Bahl",
    "wof:placetype":"venue"
},
  "geometry": {"coordinates":[7.5226750374,50.3713493347],"type":"Point"}
}