{
  "type": "Feature",
  "properties": {
    "iso:country":"DE",
    "sg:address":"Wiesg\u00e4rten 8",
    "sg:city":"Dielheim",
    "sg:phone":"+49 6222/73057",
    "sg:postcode":"69234",
    "sg:province":"Baden-W\u00fcrttemberg",
    "wof:name":"Ltb Vertriebs- Gmbh",
    "wof:placetype":"venue"
},
  "geometry": {"coordinates":[8.782214,49.278591],"type":"Point"}
}