{
  "type": "Feature",
  "properties": {
    "iso:country":"DE",
    "sg:address":"Alte Freiheit 8",
    "sg:city":"Wuppertal",
    "sg:phone":"+49 202/455340",
    "sg:postcode":"42103",
    "sg:province":"Nordrhein-Westfalen",
    "wof:name":"Hunkem\u00f6ller Deutschland Gmbh",
    "wof:placetype":"venue"
},
  "geometry": {"coordinates":[7.147802,51.256962],"type":"Point"}
}