{
  "type": "Feature",
  "properties": {
    "iso:country":"DE",
    "sg:address":"Steinfurter Str. 37",
    "sg:city":"M\u00fcnster",
    "sg:phone":"+49 251/278794",
    "sg:postcode":"48149",
    "sg:province":"Nordrhein-Westfalen",
    "wof:name":"Restaurant Phoenicia",
    "wof:placetype":"venue"
},
  "geometry": {"coordinates":[7.611166954,51.9699020386],"type":"Point"}
}