{
  "type": "Feature",
  "properties": {
    "iso:country":"DE",
    "sg:address":"Im Grund 12",
    "sg:city":"Hagen",
    "sg:phone":"+49 2337/8468",
    "sg:postcode":"58091",
    "sg:province":"Nordrhein-Westfalen",
    "wof:name":"Hans-werner K\u00e4mper Architekt",
    "wof:placetype":"venue"
},
  "geometry": {"coordinates":[7.53122,51.272308],"type":"Point"}
}