{
  "type": "Feature",
  "properties": {
    "iso:country":"DE",
    "sg:address":"Puschkinstr. 14",
    "sg:city":"L\u00fcbben",
    "sg:postcode":"15907",
    "sg:province":"Brandenburg",
    "wof:name":"Deutsche Telekom T-punkt",
    "wof:placetype":"venue"
},
  "geometry": {"coordinates":[13.8902597427,51.9381408691],"type":"Point"}
}