{
  "type": "Feature",
  "properties": {
    "iso:country":"DE",
    "sg:address":"Quickborner Str. 111",
    "sg:city":"Borstel-Hohenraden",
    "sg:phone":"+49 4101/76775",
    "sg:postcode":"25494",
    "sg:province":"Schleswig-Holstein",
    "wof:name":"E. H. Becker",
    "wof:placetype":"venue"
},
  "geometry": {"coordinates":[9.828285,53.701195],"type":"Point"}
}