{
  "type": "Feature",
  "properties": {
    "iso:country":"DE",
    "sg:address":"Riedstr. 11",
    "sg:city":"Donaueschingen",
    "sg:phone":"+49 771/158278",
    "sg:postcode":"78166",
    "sg:province":"Baden-W\u00fcrttemberg",
    "wof:name":"Gastst\u00e4tte B\u00fcrgerst\u00fcble",
    "wof:placetype":"venue"
},
  "geometry": {"coordinates":[8.5034093857,47.9404602051],"type":"Point"}
}