{
  "type": "Feature",
  "properties": {
    "iso:country":"DE",
    "sg:address":"Industriestr.",
    "sg:city":"\u00d6stringen",
    "sg:phone":"+49 7253/920970",
    "sg:postcode":"76684",
    "sg:province":"Baden-W\u00fcrttemberg",
    "wof:name":"W\u00fcrttembergische Versicherungs Ag",
    "wof:placetype":"venue"
},
  "geometry": {"coordinates":[8.6917896271,49.2126312256],"type":"Point"}
}