{
  "type": "Feature",
  "properties": {
    "iso:country":"DE",
    "sg:address":"Von-Harnack-Str. 3",
    "sg:city":"Merseburg",
    "sg:phone":"+49 3461/201591",
    "sg:postcode":"06217",
    "sg:province":"Sachsen-Anhalt",
    "wof:name":"Hotel Zum Goldenen L\u00f6wen",
    "wof:placetype":"venue"
},
  "geometry": {"coordinates":[11.9878702164,51.3569221497],"type":"Point"}
}