{
  "type": "Feature",
  "properties": {
    "iso:country":"DE",
    "sg:address":"Marktstr. 13",
    "sg:city":"Gerolzhofen",
    "sg:phone":"+49 9382/1457",
    "sg:postcode":"97447",
    "sg:province":"Bayern",
    "wof:name":"Karlheinz Weisensee",
    "wof:placetype":"venue"
},
  "geometry": {"coordinates":[10.3478450775,49.9014930725],"type":"Point"}
}