{
  "type": "Feature",
  "properties": {
    "iso:country":"DE",
    "sg:address":"Dannenwalderweg 72 C",
    "sg:city":"berlin",
    "sg:postcode":"13439",
    "sg:province":"Berlin",
    "wof:name":"Webdesign Erstellung Ihrer Firmen-hompage",
    "wof:placetype":"venue"
},
  "geometry": {"coordinates":[13.346798,52.591305],"type":"Point"}
}