{
  "type": "Feature",
  "properties": {
    "iso:country":"DE",
    "sg:address":"Ben-Gurion-Ring 54",
    "sg:city":"Frankfurt",
    "sg:postcode":"60437",
    "sg:province":"Hessen",
    "wof:name":"\u00e4nderungsschneiderei Und Reinigungsservice Omurtak/frankfurt",
    "wof:placetype":"venue"
},
  "geometry": {"coordinates":[8.6650114059,50.190322876],"type":"Point"}
}