{
  "type": "Feature",
  "properties": {
    "iso:country":"DE",
    "sg:address":"Jungfernm\u00fchle 1",
    "sg:city":"Hamburg",
    "sg:phone":"+49 40/7979906",
    "sg:postcode":"21147",
    "sg:province":"Hamburg",
    "wof:name":"Aykut Karatoprakli",
    "wof:placetype":"venue"
},
  "geometry": {"coordinates":[9.8939390182,53.4752998352],"type":"Point"}
}