{
  "type": "Feature",
  "properties": {
    "iso:country":"DE",
    "sg:address":"Allg\u00e4uer Str. 38",
    "sg:city":"Pfronten",
    "sg:phone":"+49 8363/8182",
    "sg:postcode":"87459",
    "sg:province":"Bayern",
    "wof:name":"Anton Hartmann Steuerberater",
    "wof:placetype":"venue"
},
  "geometry": {"coordinates":[10.5597162247,47.5849647522],"type":"Point"}
}