{
  "type": "Feature",
  "properties": {
    "iso:country":"DE",
    "sg:address":"Reherstr. 375",
    "sg:city":"Wietzen",
    "sg:postcode":"31613",
    "sg:province":"Niedersachsen",
    "wof:name":"Erich Hindahl Bauunternehmen Gmbh",
    "wof:placetype":"venue"
},
  "geometry": {"coordinates":[9.0789804459,52.7121810913],"type":"Point"}
}