{
  "type": "Feature",
  "properties": {
    "iso:country":"DE",
    "sg:address":"Kleinbettlinger Str. 19",
    "sg:city":"Riederich",
    "sg:phone":"+49 7123/32769",
    "sg:postcode":"72585",
    "sg:province":"Baden-W\u00fcrttemberg",
    "wof:name":"G\u00fcnther Schoofs Ingenieur",
    "wof:placetype":"venue"
},
  "geometry": {"coordinates":[9.2708415985,48.56407547],"type":"Point"}
}