{
  "type": "Feature",
  "properties": {
    "iso:country":"DE",
    "sg:address":"Schwanseestr. 10",
    "sg:city":"M\u00fcnchen",
    "sg:phone":"+49 89/696347",
    "sg:postcode":"81539",
    "sg:province":"Bayern",
    "wof:name":"M. Karadag",
    "wof:placetype":"venue"
},
  "geometry": {"coordinates":[11.5947685242,48.1096572876],"type":"Point"}
}