{
  "type": "Feature",
  "properties": {
    "iso:country":"DE",
    "sg:address":"Bergstr. 104",
    "sg:city":"Kamen",
    "sg:phone":"+49 2307/40125",
    "sg:postcode":"59174",
    "sg:province":"Nordrhein-Westfalen",
    "wof:name":"M\u00e4rkische Apotheke Inh. Heike Post",
    "wof:placetype":"venue"
},
  "geometry": {"coordinates":[7.719792,51.581158],"type":"Point"}
}