{
  "type": "Feature",
  "properties": {
    "iso:country":"DE",
    "sg:address":"Nordstr. 109",
    "sg:city":"Osnabr\u00fcck",
    "sg:phone":"+49 541/77535",
    "sg:postcode":"49084",
    "sg:province":"Niedersachsen",
    "wof:name":"Niedersachsenhof Radizio Do Brasil Gmbh",
    "wof:placetype":"venue"
},
  "geometry": {"coordinates":[8.105755806,52.2927093506],"type":"Point"}
}