{
  "type": "Feature",
  "properties": {
    "iso:country":"DE",
    "sg:address":"Burgstr. 30",
    "sg:city":"Oldenburg",
    "sg:phone":"+49 441/13777",
    "sg:postcode":"26122",
    "sg:province":"Niedersachsen",
    "wof:name":"Klaus J. Smid Antiquit\u00e4ten",
    "wof:placetype":"venue"
},
  "geometry": {"coordinates":[8.210825,53.140137],"type":"Point"}
}