{
  "type": "Feature",
  "properties": {
    "iso:country":"DE",
    "sg:address":"Neue Gasse 11",
    "sg:city":"Jahnsdorf",
    "sg:postcode":"09387",
    "sg:province":"Sachsen",
    "wof:name":"W & B Bau Gmbh",
    "wof:placetype":"venue"
},
  "geometry": {"coordinates":[12.809374,50.77219],"type":"Point"}
}