{
  "type": "Feature",
  "properties": {
    "iso:country":"DE",
    "sg:address":"Mainstr. 5",
    "sg:city":"Erlenbach",
    "sg:postcode":"63906",
    "sg:province":"Bayern",
    "wof:name":"Moinos-schiffahrts- Verwaltungs Gmbh",
    "wof:placetype":"venue"
},
  "geometry": {"coordinates":[9.159607,49.804565],"type":"Point"}
}