{
  "type": "Feature",
  "properties": {
    "iso:country":"DE",
    "sg:address":"Dorfstr. 132",
    "sg:city":"Risum-Lindholm",
    "sg:phone":"+49 4661/8293",
    "sg:postcode":"25920",
    "sg:province":"Schleswig-Holstein",
    "wof:name":"K. Brodersen",
    "wof:placetype":"venue"
},
  "geometry": {"coordinates":[8.857579,54.754417],"type":"Point"}
}