{
  "type": "Feature",
  "properties": {
    "iso:country":"DE",
    "sg:address":"F\u00e4hrstr. 2-4",
    "sg:city":"Erden",
    "sg:phone":"+49 6532/4624",
    "sg:postcode":"54492",
    "sg:province":"Rheinland-Pfalz",
    "wof:name":"Alois Kaufmann",
    "wof:placetype":"venue"
},
  "geometry": {"coordinates":[7.0242071152,49.9796104431],"type":"Point"}
}