{
  "type": "Feature",
  "properties": {
    "iso:country":"DE",
    "sg:address":"Friedl\u00e4nder Landstr. 16",
    "sg:city":"Anklam",
    "sg:phone":"+49 3971/831467",
    "sg:postcode":"17389",
    "sg:province":"Mecklenburg-Vorpommern",
    "wof:name":"J\u00e4ger",
    "wof:placetype":"venue"
},
  "geometry": {"coordinates":[13.686622,53.845707],"type":"Point"}
}