{
  "type": "Feature",
  "properties": {
    "iso:country":"DE",
    "sg:address":"Kunstm\u00fchlestr. 16",
    "sg:city":"Pfullingen",
    "sg:postcode":"72793",
    "sg:province":"Baden-W\u00fcrttemberg",
    "wof:name":"Fiedler Beteiligungs-gmbh",
    "wof:placetype":"venue"
},
  "geometry": {"coordinates":[9.225768,48.472851],"type":"Point"}
}