{
  "type": "Feature",
  "properties": {
    "iso:country":"DE",
    "sg:address":"Am Markt 18",
    "sg:city":"Leichlingen",
    "sg:phone":"+49 2174/795014",
    "sg:postcode":"42799",
    "sg:province":"Nordrhein-Westfalen",
    "wof:name":"Jacobs",
    "wof:placetype":"venue"
},
  "geometry": {"coordinates":[7.1108789444,51.1156616211],"type":"Point"}
}