{
  "type": "Feature",
  "properties": {
    "iso:country":"DE",
    "sg:address":"Siegfriedstr. 39",
    "sg:city":"Weinheim",
    "sg:phone":"+49 6201/185586",
    "sg:postcode":"69469",
    "sg:province":"Baden-W\u00fcrttemberg",
    "wof:name":"Steyert Weinkellerei Gmbh Heinrich Nepomuk",
    "wof:placetype":"venue"
},
  "geometry": {"coordinates":[8.6676721573,49.5618476868],"type":"Point"}
}