{
  "type": "Feature",
  "properties": {
    "iso:country":"DE",
    "sg:address":"Friedrich-Engels-Str. 59",
    "sg:city":"Potsdam",
    "sg:postcode":"14482",
    "sg:province":"Brandenburg",
    "wof:name":"S. Janov",
    "wof:placetype":"venue"
},
  "geometry": {"coordinates":[13.0918397903,52.3925132751],"type":"Point"}
}