{
  "type": "Feature",
  "properties": {
    "iso:country":"DE",
    "sg:address":"Bahnhofstr. 91",
    "sg:city":"Saarbr\u00fccken",
    "sg:phone":"+49 681/9382990",
    "sg:postcode":"66111",
    "sg:province":"Saarland",
    "wof:name":"Gerhard Fritz Rechtsanwalt",
    "wof:placetype":"venue"
},
  "geometry": {"coordinates":[6.991587162,49.2374458313],"type":"Point"}
}