{
  "type": "Feature",
  "properties": {
    "iso:country":"DE",
    "sg:address":"Adenauerplatz 22",
    "sg:city":"Hennef",
    "sg:phone":"+49 2242/81630",
    "sg:postcode":"53773",
    "sg:province":"Nordrhein-Westfalen",
    "wof:name":"Buchhandlung Am Markt Gmbh",
    "wof:placetype":"venue"
},
  "geometry": {"coordinates":[7.2845258713,50.7747077942],"type":"Point"}
}