{
  "type": "Feature",
  "properties": {
    "iso:country":"DE",
    "sg:address":"Robert-Bosch-Str 19",
    "sg:city":"Odelzhausen",
    "sg:phone":"+49 8134/55543",
    "sg:postcode":"85235",
    "sg:province":"Bayern",
    "wof:name":"Elf Vertriebs Und Service Gmbh",
    "wof:placetype":"venue"
},
  "geometry": {"coordinates":[11.208846,48.304592],"type":"Point"}
}