{
  "type": "Feature",
  "properties": {
    "iso:country":"DE",
    "sg:address":"Warthestr. 13",
    "sg:city":"Bochum",
    "sg:phone":"+49 234/591542",
    "sg:postcode":"44791",
    "sg:province":"Nordrhein-Westfalen",
    "wof:name":"Antik Am Stadion Gmbh",
    "wof:placetype":"venue"
},
  "geometry": {"coordinates":[7.256726,51.487099],"type":"Point"}
}