{
  "type": "Feature",
  "properties": {
    "iso:country":"DE",
    "sg:address":"Bergstr. 21",
    "sg:city":"Biedenkopf",
    "sg:phone":"+49 6461/2502",
    "sg:postcode":"35216",
    "sg:province":"Hessen",
    "wof:name":"H. Grebe",
    "wof:placetype":"venue"
},
  "geometry": {"coordinates":[8.5610628128,50.8790168762],"type":"Point"}
}