{
  "type": "Feature",
  "properties": {
    "iso:country":"DE",
    "sg:address":"Erzenbachstr. 2",
    "sg:city":"Winden",
    "sg:phone":"+49 7682/8591",
    "sg:postcode":"79297",
    "sg:province":"Baden-W\u00fcrttemberg",
    "wof:name":"Artur Emler Holzbildhauer",
    "wof:placetype":"venue"
},
  "geometry": {"coordinates":[8.045457,48.15155],"type":"Point"}
}