{
  "type": "Feature",
  "properties": {
    "iso:country":"DE",
    "sg:address":"Neue Bergstr. 14",
    "sg:city":"Scharbeutz",
    "sg:phone":"+49 4503/35500",
    "sg:postcode":"23683",
    "sg:province":"Schleswig-Holstein",
    "wof:name":"Dr. Med. Klaus Nagel Arzt F\u00fcr Allgemeinmedizin",
    "wof:placetype":"venue"
},
  "geometry": {"coordinates":[10.7512102127,54.029510498],"type":"Point"}
}