{
  "type": "Feature",
  "properties": {
    "iso:country":"DE",
    "sg:address":"Schnieglinger Str. 128 a",
    "sg:city":"N\u00fcrnberg",
    "sg:phone":"+49 911/390967",
    "sg:postcode":"90425",
    "sg:province":"Bayern",
    "wof:name":"N\u00fctro Hirsch Gmbh & Co.",
    "wof:placetype":"venue"
},
  "geometry": {"coordinates":[11.043082,49.466068],"type":"Point"}
}