{
  "type": "Feature",
  "properties": {
    "iso:country":"DE",
    "sg:city":"D\u00e4geling",
    "sg:phone":"+49 4821/82341",
    "sg:postcode":"25578",
    "sg:province":"Schleswig-Holstein",
    "wof:name":"G. Schwardt",
    "wof:placetype":"venue"
},
  "geometry": {"coordinates":[9.53095,53.876682],"type":"Point"}
}