{
  "type": "Feature",
  "properties": {
    "iso:country":"DE",
    "sg:address":"Fahrstr. 43",
    "sg:city":"Babenhausen",
    "sg:phone":"+49 6073/5550",
    "sg:postcode":"64832",
    "sg:province":"Hessen",
    "wof:name":"Ev. Pfarramt Gem. Babenhausen Ii",
    "wof:placetype":"venue"
},
  "geometry": {"coordinates":[8.9525232315,49.9632644653],"type":"Point"}
}