{
  "type": "Feature",
  "properties": {
    "iso:country":"DE",
    "sg:address":"Wambach",
    "sg:city":"Taufkirchen",
    "sg:phone":"+49 8084/2303",
    "sg:postcode":"84416",
    "sg:province":"Bayern",
    "wof:name":"J. Loipf\u00fchrer",
    "wof:placetype":"venue"
},
  "geometry": {"coordinates":[12.17847,48.388157],"type":"Point"}
}