{
  "type": "Feature",
  "properties": {
    "iso:country":"DE",
    "sg:address":"Lerchenweg 6",
    "sg:city":"Stade",
    "sg:phone":"+49 4141/84450",
    "sg:postcode":"21682",
    "sg:province":"Niedersachsen",
    "wof:name":"Spar-markt Ralf Und Almuth Graack",
    "wof:placetype":"venue"
},
  "geometry": {"coordinates":[9.4324922562,53.5967979431],"type":"Point"}
}