{
  "type": "Feature",
  "properties": {
    "iso:country":"DE",
    "sg:address":"Ivo-Beucker-Stra\u00dfe 43",
    "sg:city":"D\u00fcsseldorf",
    "sg:postcode":"40237",
    "sg:province":"Nordrhein-Westfalen",
    "wof:name":"Industrieverband Klebstoffe E.v.",
    "wof:placetype":"venue"
},
  "geometry": {"coordinates":[6.8203778267,51.2375526428],"type":"Point"}
}