{
  "type": "Feature",
  "properties": {
    "iso:country":"DE",
    "sg:address":"Luxemburger Str. 282 e",
    "sg:city":"K\u00f6ln",
    "sg:postcode":"50937",
    "sg:province":"Nordrhein-Westfalen",
    "wof:name":"Working Capital Asset Management Gmbh",
    "wof:placetype":"venue"
},
  "geometry": {"coordinates":[6.9268598557,50.9161567688],"type":"Point"}
}