{
  "type": "Feature",
  "properties": {
    "iso:country":"DE",
    "sg:address":"Dorenborg 2",
    "sg:city":"Westoverledingen",
    "sg:phone":"+49 4955/1648",
    "sg:postcode":"26810",
    "sg:province":"Niedersachsen",
    "wof:name":"Hermann Nehuis",
    "wof:placetype":"venue"
},
  "geometry": {"coordinates":[7.399294,53.182873],"type":"Point"}
}