{
  "type": "Feature",
  "properties": {
    "iso:country":"DE",
    "sg:address":"Elbdeich 236",
    "sg:city":"Seevetal/HH",
    "sg:phone":"+49 40/7685071",
    "sg:postcode":"21217",
    "sg:province":"Niedersachsen",
    "wof:name":"Rewatec Gmbh",
    "wof:placetype":"venue"
},
  "geometry": {"coordinates":[10.073800087,53.44739151],"type":"Point"}
}