{
  "type": "Feature",
  "properties": {
    "iso:country":"DE",
    "sg:address":"Graf-Adolf-Platz 1-2",
    "sg:city":"D\u00fcsseldorf",
    "sg:phone":"+49 211/9889980",
    "sg:postcode":"40213",
    "sg:province":"Nordrhein-Westfalen",
    "wof:name":"Sibirsky Aluminium Gmbh",
    "wof:placetype":"venue"
},
  "geometry": {"coordinates":[6.7757658958,51.2183036804],"type":"Point"}
}