{
  "type": "Feature",
  "properties": {
    "iso:country":"DE",
    "sg:address":"Liegnitzer Str. 53",
    "sg:city":"Weinheim",
    "sg:phone":"+49 6201/187091",
    "sg:postcode":"69469",
    "sg:province":"Baden-W\u00fcrttemberg",
    "wof:name":"Cyenc. Com Gmbh",
    "wof:placetype":"venue"
},
  "geometry": {"coordinates":[8.638299942,49.5407028198],"type":"Point"}
}