{
  "type": "Feature",
  "properties": {
    "iso:country":"DE",
    "sg:address":"Negenborner Weg 1-7",
    "sg:city":"Einbeck",
    "sg:phone":"+49 5561/5027",
    "sg:postcode":"37574",
    "sg:province":"Niedersachsen",
    "wof:name":"Einbecker Puddingpulver Und N\u00e4hrmittelfabrik",
    "wof:placetype":"venue"
},
  "geometry": {"coordinates":[9.8739299774,51.8206214905],"type":"Point"}
}