{
  "type": "Feature",
  "properties": {
    "iso:country":"DE",
    "sg:address":"Gr\u00fcnauer Allee 57",
    "sg:city":"Unterhaching",
    "sg:phone":"+49 89",
    "sg:postcode":"82008",
    "sg:province":"Bayern",
    "wof:name":"Sportmed-shop",
    "wof:placetype":"venue"
},
  "geometry": {"coordinates":[11.621492,48.061466],"type":"Point"}
}