{
  "type": "Feature",
  "properties": {
    "iso:country":"DE",
    "sg:address":"Friedrich-List-Str 89",
    "sg:city":"Paderborn",
    "sg:phone":"+49 5251/529400",
    "sg:postcode":"33100",
    "sg:province":"Nordrhein-Westfalen",
    "wof:name":"Hks-netzwerksysteme Gmbh & Co Kg",
    "wof:placetype":"venue"
},
  "geometry": {"coordinates":[8.7924365997,51.7269287109],"type":"Point"}
}