{
  "type": "Feature",
  "properties": {
    "iso:country":"DE",
    "sg:address":"Hans-Baldung-Str. 15",
    "sg:city":"Reutlingen",
    "sg:phone":"+49 7121/601554",
    "sg:postcode":"72768",
    "sg:province":"Baden-W\u00fcrttemberg",
    "wof:name":"Jochen Rein Edv-beratung Gmbh",
    "wof:placetype":"venue"
},
  "geometry": {"coordinates":[9.1789102554,48.51770401],"type":"Point"}
}