{
  "type": "Feature",
  "properties": {
    "iso:country":"DE",
    "sg:address":"Schlo\u00dfstra\u00dfe 24",
    "sg:city":"K\u00f6nigsbr\u00fcck",
    "sg:phone":"+49 35795",
    "sg:postcode":"01936",
    "sg:province":"Sachsen",
    "wof:name":"Innovative Haustechnik Gmbh",
    "wof:placetype":"venue"
},
  "geometry": {"coordinates":[13.901115,51.263718],"type":"Point"}
}