{
  "type": "Feature",
  "properties": {
    "iso:country":"DE",
    "sg:address":"'s Heerenberger Str. 400",
    "sg:city":"Emmerich",
    "sg:phone":"+49 2822/687500",
    "sg:postcode":"46446",
    "sg:province":"Nordrhein-Westfalen",
    "wof:name":"Permadental Bv",
    "wof:placetype":"venue"
},
  "geometry": {"coordinates":[6.2477269173,51.8693847656],"type":"Point"}
}