{
  "type": "Feature",
  "properties": {
    "iso:country":"DE",
    "sg:address":"Bein 21",
    "sg:city":"Idar-Oberstein",
    "sg:phone":"+49 6784/342",
    "sg:postcode":"55743",
    "sg:province":"Rheinland-Pfalz",
    "wof:name":"Ev. Pfarramt Weierbach",
    "wof:placetype":"venue"
},
  "geometry": {"coordinates":[7.393078804,49.7219657898],"type":"Point"}
}