{
  "type": "Feature",
  "properties": {
    "iso:country":"DE",
    "sg:address":"Am Igelsbach 6",
    "sg:city":"Rothenburg",
    "sg:phone":"+49 9861/87840",
    "sg:postcode":"91541",
    "sg:province":"Bayern",
    "wof:name":"Alc Autolackiercentrum Rothenburg Verwaltungs Gmbh",
    "wof:placetype":"venue"
},
  "geometry": {"coordinates":[10.200325,49.367046],"type":"Point"}
}