{
  "type": "Feature",
  "properties": {
    "iso:country":"DE",
    "sg:address":"Gro\u00dfer Moorweg 45",
    "sg:city":"Tornesch",
    "sg:phone":"+49 4941/227011",
    "sg:postcode":"25436",
    "sg:province":"Schleswig-Holstein",
    "wof:name":"Hellermann Tyton Gmbh",
    "wof:placetype":"venue"
},
  "geometry": {"coordinates":[9.733092308,53.6975212097],"type":"Point"}
}