{
  "type": "Feature",
  "properties": {
    "iso:country":"DE",
    "sg:address":"Selbelanger Weg 16",
    "sg:city":"Retzow",
    "sg:phone":"+49 33237/88753",
    "sg:postcode":"14641",
    "sg:province":"Brandenburg",
    "wof:name":"Marija Begemann",
    "wof:placetype":"venue"
},
  "geometry": {"coordinates":[12.689044,52.625721],"type":"Point"}
}