{
  "type": "Feature",
  "properties": {
    "iso:country":"DE",
    "sg:address":"Sachsenstrasse 99",
    "sg:city":"Recklinghausen",
    "sg:phone":"+49 2361/98045",
    "sg:postcode":"45665",
    "sg:province":"Nordrhein-Westfalen",
    "wof:name":"Computer Sign & Graphic",
    "wof:placetype":"venue"
},
  "geometry": {"coordinates":[7.267753,51.612263],"type":"Point"}
}