{
  "type": "Feature",
  "properties": {
    "iso:country":"DE",
    "sg:address":"Schreberweg 3",
    "sg:city":"Kronshagen",
    "sg:phone":"+49 4943/1546270",
    "sg:postcode":"24119",
    "sg:province":"Schleswig-Holstein",
    "wof:name":"Horst Theunissen Gmbh",
    "wof:placetype":"venue"
},
  "geometry": {"coordinates":[10.099071,54.338924],"type":"Point"}
}