{
  "type": "Feature",
  "properties": {
    "iso:country":"DE",
    "sg:address":"Wei\u00dfenthurmer Str. 26 a",
    "sg:city":"Kettig",
    "sg:phone":"+49 2637/940147",
    "sg:postcode":"56220",
    "sg:province":"Rheinland-Pfalz",
    "wof:name":"Werner Hillesheim",
    "wof:placetype":"venue"
},
  "geometry": {"coordinates":[7.462302,50.401974],"type":"Point"}
}