{
  "type": "Feature",
  "properties": {
    "iso:country":"DE",
    "sg:address":"Sch\u00fcruferstr. 296",
    "sg:city":"Dortmund",
    "sg:phone":"+49 231/4461871",
    "sg:postcode":"44287",
    "sg:province":"Nordrhein-Westfalen",
    "wof:name":"M & W Autoteile Service Gmbh",
    "wof:placetype":"venue"
},
  "geometry": {"coordinates":[7.5496201515,51.4924201965],"type":"Point"}
}