{
  "type": "Feature",
  "properties": {
    "iso:country":"DE",
    "sg:address":"Hainstr. 8",
    "sg:city":"Bamberg",
    "sg:phone":"+49 951/200033",
    "sg:postcode":"96047",
    "sg:province":"Bayern",
    "wof:name":"Dbv-winterthur Lebensversicherung Ag",
    "wof:placetype":"venue"
},
  "geometry": {"coordinates":[10.89796,49.879395],"type":"Point"}
}