{
  "type": "Feature",
  "properties": {
    "iso:country":"DE",
    "sg:address":"Matthias-Gr\u00fcnewald-Str. 1-3",
    "sg:city":"Bonn",
    "sg:phone":"+49 228",
    "sg:postcode":"53175",
    "sg:province":"Nordrhein-Westfalen",
    "wof:name":"Klimaschutzkongress Nrw",
    "wof:placetype":"venue"
},
  "geometry": {"coordinates":[7.145087,50.699738],"type":"Point"}
}