{
  "type": "Feature",
  "properties": {
    "iso:country":"DE",
    "sg:address":"Hauptstr. 60",
    "sg:city":"Eislingen",
    "sg:phone":"+49 7161/88370",
    "sg:postcode":"73054",
    "sg:province":"Baden-W\u00fcrttemberg",
    "wof:name":"Wilhelm H\u00f6fer",
    "wof:placetype":"venue"
},
  "geometry": {"coordinates":[9.707421,48.69949],"type":"Point"}
}