{
  "type": "Feature",
  "properties": {
    "iso:country":"DE",
    "sg:address":"Schillerstr. 93",
    "sg:city":"Berlin",
    "sg:phone":"+49 30/3120918",
    "sg:postcode":"10625",
    "sg:province":"Berlin",
    "wof:name":"Viktor Kattinger",
    "wof:placetype":"venue"
},
  "geometry": {"coordinates":[13.310472,52.510204],"type":"Point"}
}