{
  "type": "Feature",
  "properties": {
    "iso:country":"DE",
    "sg:address":"Am Sieltief 8",
    "sg:city":"Nordenham",
    "sg:phone":"+49 4731/94210",
    "sg:postcode":"26954",
    "sg:province":"Niedersachsen",
    "wof:name":"Rcg-landtechnik Vertriebs- Und Service Gmbh",
    "wof:placetype":"venue"
},
  "geometry": {"coordinates":[8.47857,53.489529],"type":"Point"}
}