{
  "type": "Feature",
  "properties": {
    "iso:country":"DE",
    "sg:address":"Alfred-Mumb\u00e4cher-Str. 30g",
    "sg:city":"Mainz",
    "sg:phone":"+49 6131/34408",
    "sg:postcode":"55128",
    "sg:province":"Rheinland-Pfalz",
    "wof:name":"P.r. Rentel",
    "wof:placetype":"venue"
},
  "geometry": {"coordinates":[8.2566795349,49.9809761047],"type":"Point"}
}