{
  "type": "Feature",
  "properties": {
    "iso:country":"DE",
    "sg:address":"Kronprinzenstra\u00dfe 31",
    "sg:city":"Bonn",
    "sg:phone":"+49 228/9358341",
    "sg:postcode":"53173",
    "sg:province":"Nordrhein-Westfalen",
    "wof:name":"Ev. Kirchengemeinde Wachtberg",
    "wof:placetype":"venue"
},
  "geometry": {"coordinates":[7.162821,50.688641],"type":"Point"}
}