{
  "type": "Feature",
  "properties": {
    "iso:country":"DE",
    "sg:address":"Reihekamp 28",
    "sg:city":"Barsinghausen",
    "sg:phone":"+49 5105",
    "sg:postcode":"30890",
    "sg:province":"Niedersachsen",
    "wof:name":"Gartenger\u00e4te Und Rasenm\u00e4herzubeh\u00f6r",
    "wof:placetype":"venue"
},
  "geometry": {"coordinates":[9.4899368286,52.3018493652],"type":"Point"}
}