{
  "type": "Feature",
  "properties": {
    "iso:country":"DE",
    "sg:address":"Bahnhofstr. 4",
    "sg:city":"Prien",
    "sg:phone":"+49 8051/6040",
    "sg:postcode":"83209",
    "sg:province":"Bayern",
    "wof:name":"Gfd Ges. F\u00fcr Datenver- Arbeitung Mbh",
    "wof:placetype":"venue"
},
  "geometry": {"coordinates":[12.3453884125,47.8549690247],"type":"Point"}
}