{
  "type": "Feature",
  "properties": {
    "iso:country":"DE",
    "sg:address":"Kellerweg 27",
    "sg:city":"Senden",
    "sg:phone":"+49 7307/929200",
    "sg:postcode":"89250",
    "sg:province":"Bayern",
    "wof:name":"Aquachem Gmbh",
    "wof:placetype":"venue"
},
  "geometry": {"coordinates":[10.0598335266,48.3243408203],"type":"Point"}
}