{
  "type": "Feature",
  "properties": {
    "iso:country":"DE",
    "sg:address":"Lindlarer Str. 25",
    "sg:city":"Overath",
    "sg:phone":"+49 2204/71030",
    "sg:postcode":"51491",
    "sg:province":"Nordrhein-Westfalen",
    "wof:name":"Gr\u00fcnland Naturprodukte Gmbh",
    "wof:placetype":"venue"
},
  "geometry": {"coordinates":[7.2314891815,50.9573364258],"type":"Point"}
}