{
  "type": "Feature",
  "properties": {
    "iso:country":"DE",
    "sg:address":"Dudweiler Landstr.",
    "sg:city":"Saarbr\u00fccken",
    "sg:phone":"+49 681/3081",
    "sg:postcode":"66123",
    "sg:province":"Saarland",
    "wof:name":"Deutsche Bahn Ag",
    "wof:placetype":"venue"
},
  "geometry": {"coordinates":[7.0230498314,49.2484893799],"type":"Point"}
}