{
  "type": "Feature",
  "properties": {
    "iso:country":"DE",
    "sg:address":"Schenkenburgstr. 16",
    "sg:city":"Ecklingerode",
    "sg:phone":"+49 36071/97809",
    "sg:postcode":"37339",
    "sg:province":"Th\u00fcringen",
    "wof:name":"Otto Hoffmeister",
    "wof:placetype":"venue"
},
  "geometry": {"coordinates":[10.3154096603,51.5027770996],"type":"Point"}
}