{
  "type": "Feature",
  "properties": {
    "iso:country":"DE",
    "sg:address":"Karlstr. 49a",
    "sg:city":"Karlsruhe",
    "sg:postcode":"76133",
    "sg:province":"Baden-W\u00fcrttemberg",
    "wof:name":"Eqs Privatinstitut F\u00fcr Evaluation Und Qualit\u00e4tss. Im",
    "wof:placetype":"venue"
},
  "geometry": {"coordinates":[8.3948640823,49.0048332214],"type":"Point"}
}