{
  "type": "Feature",
  "properties": {
    "iso:country":"DE",
    "sg:address":"M\u00fchlenhagen 130",
    "sg:city":"Hamburg",
    "sg:postcode":"20539",
    "sg:province":"Hamburg",
    "wof:name":"Happyware Computer Components Firat G\u00fcnay E. K.",
    "wof:placetype":"venue"
},
  "geometry": {"coordinates":[10.0667076111,53.5374794006],"type":"Point"}
}