{
  "type": "Feature",
  "properties": {
    "iso:country":"DE",
    "sg:address":"Rheinstr. 49",
    "sg:city":"Oppenheim",
    "sg:phone":"+49 6133/4495",
    "sg:postcode":"55276",
    "sg:province":"Rheinland-Pfalz",
    "wof:name":"Laubenheimer Fliesenverlegung Gmbh",
    "wof:placetype":"venue"
},
  "geometry": {"coordinates":[8.3629102707,49.8561058044],"type":"Point"}
}