{
  "type": "Feature",
  "properties": {
    "iso:country":"DE",
    "sg:address":"Obere Weinbergsleithe 3",
    "sg:city":"Strullendorf",
    "sg:phone":"+49 9543/9287",
    "sg:postcode":"96129",
    "sg:province":"Bayern",
    "wof:name":"Herbert Und Hilde Borrmann",
    "wof:placetype":"venue"
},
  "geometry": {"coordinates":[10.99609375,49.8559532166],"type":"Point"}
}