{
  "type": "Feature",
  "properties": {
    "iso:country":"DE",
    "sg:address":"M\u00f6hlenredder 6",
    "sg:city":"Barsb\u00fcttel",
    "sg:phone":"+49 40/6770760",
    "sg:postcode":"22885",
    "sg:province":"Schleswig-Holstein",
    "wof:name":"Hinrich Gotthard",
    "wof:placetype":"venue"
},
  "geometry": {"coordinates":[10.232947,53.590725],"type":"Point"}
}