{
  "type": "Feature",
  "properties": {
    "iso:country":"DE",
    "sg:address":"Industriestr.",
    "sg:city":"Heiligenroth",
    "sg:phone":"+49 2602/4970",
    "sg:postcode":"56412",
    "sg:province":"Rheinland-Pfalz",
    "wof:name":"Pinguin",
    "wof:placetype":"venue"
},
  "geometry": {"coordinates":[7.8479661942,50.44871521],"type":"Point"}
}