{
  "type": "Feature",
  "properties": {
    "iso:country":"DE",
    "sg:address":"Von-R\u00f6ntgen-Str. 3",
    "sg:city":"Ahaus",
    "sg:phone":"+49 2561/69081",
    "sg:postcode":"48683",
    "sg:province":"Nordrhein-Westfalen",
    "wof:name":"Schmeing Verwaltungs Gmbh",
    "wof:placetype":"venue"
},
  "geometry": {"coordinates":[7.0218930244,52.0803222656],"type":"Point"}
}