{
  "type": "Feature",
  "properties": {
    "iso:country":"DE",
    "sg:address":"K\u00f6nigsheide 18",
    "sg:city":"L\u00fcnen",
    "sg:phone":"+49 231/338033",
    "sg:postcode":"44536",
    "sg:province":"Nordrhein-Westfalen",
    "wof:name":"Ulrich Kinzel",
    "wof:placetype":"venue"
},
  "geometry": {"coordinates":[7.4420938492,51.5955467224],"type":"Point"}
}