{
  "type": "Feature",
  "properties": {
    "iso:country":"DE",
    "sg:address":"Kremmener Str. 23",
    "sg:city":"Germendorf",
    "sg:phone":"+49 3301/3363",
    "sg:postcode":"16767",
    "sg:province":"Brandenburg",
    "wof:name":"Eichholz Bautr\u00e4ger Gmbh",
    "wof:placetype":"venue"
},
  "geometry": {"coordinates":[13.1934452057,52.7236938477],"type":"Point"}
}