{
  "type": "Feature",
  "properties": {
    "iso:country":"DE",
    "sg:address":"Robert-Koch-Str. 91",
    "sg:city":"Garbsen",
    "sg:phone":"+49 5131/52531",
    "sg:postcode":"30826",
    "sg:province":"Niedersachsen",
    "wof:name":"Helmut Brandt Architekt",
    "wof:placetype":"venue"
},
  "geometry": {"coordinates":[9.580816,52.454369],"type":"Point"}
}