{
  "type": "Feature",
  "properties": {
    "iso:country":"DE",
    "sg:address":"Untergasse 5",
    "sg:city":"Gedern",
    "sg:phone":"+49 6045/950050",
    "sg:postcode":"63688",
    "sg:province":"Hessen",
    "wof:name":"Kaha- Licht Karl-heinz Hanselmann",
    "wof:placetype":"venue"
},
  "geometry": {"coordinates":[9.1988859177,50.4239463806],"type":"Point"}
}