{
  "type": "Feature",
  "properties": {
    "iso:country":"DE",
    "sg:address":"Herrsteiner Str.",
    "sg:city":"Kempfeld",
    "sg:phone":"+49 6786/7127",
    "sg:postcode":"55758",
    "sg:province":"Rheinland-Pfalz",
    "wof:name":"Horst Albohr",
    "wof:placetype":"venue"
},
  "geometry": {"coordinates":[7.244771,49.790565],"type":"Point"}
}