{
  "type": "Feature",
  "properties": {
    "iso:country":"DE",
    "sg:address":"Haydnstra\u00dfe 2",
    "sg:city":"Hude",
    "sg:phone":"+49 4408/306",
    "sg:postcode":"27798",
    "sg:province":"Niedersachsen",
    "wof:name":"Paul Plambeck -mineral\u00f6lhandel-",
    "wof:placetype":"venue"
},
  "geometry": {"coordinates":[8.45665,53.109169],"type":"Point"}
}