{
  "type": "Feature",
  "properties": {
    "iso:country":"DE",
    "sg:address":"Bevensener Str. 1",
    "sg:city":"Suhlendorf",
    "sg:phone":"+49 5820/316",
    "sg:postcode":"29562",
    "sg:province":"Niedersachsen",
    "wof:name":"Friedrich Prilop",
    "wof:placetype":"venue"
},
  "geometry": {"coordinates":[10.768884,52.927116],"type":"Point"}
}