{
  "type": "Feature",
  "properties": {
    "iso:country":"DE",
    "sg:address":"Ru\u00dfheider Weg 7",
    "sg:city":"Bielefeld",
    "sg:phone":"+49 521/150415",
    "sg:postcode":"33604",
    "sg:province":"Nordrhein-Westfalen",
    "wof:name":"Midas Ag",
    "wof:placetype":"venue"
},
  "geometry": {"coordinates":[8.552238,52.011551],"type":"Point"}
}