{
  "type": "Feature",
  "properties": {
    "iso:country":"DE",
    "sg:address":"Br\u00fcckenstr. 9-11",
    "sg:city":"Schweinfurt",
    "sg:phone":"+49 9721/16040",
    "sg:postcode":"97421",
    "sg:province":"Bayern",
    "wof:name":"Franken Wkv Bank Gmbh",
    "wof:placetype":"venue"
},
  "geometry": {"coordinates":[10.235562,50.044838],"type":"Point"}
}