{
  "type": "Feature",
  "properties": {
    "iso:country":"DE",
    "sg:address":"Westfalenstr. 64",
    "sg:city":"Essen",
    "sg:phone":"+49 201/510282",
    "sg:postcode":"45136",
    "sg:province":"Nordrhein-Westfalen",
    "wof:name":"J. B. H. Jochen Barry Gmbh",
    "wof:placetype":"venue"
},
  "geometry": {"coordinates":[7.059203,51.436302],"type":"Point"}
}