{
  "type": "Feature",
  "properties": {
    "iso:country":"DE",
    "sg:address":"Ringstr. 2",
    "sg:city":"Gem\u00fcnden",
    "sg:phone":"+49 6453/91080",
    "sg:postcode":"35285",
    "sg:province":"Hessen",
    "wof:name":"B. M\u00f6bus Masseur",
    "wof:placetype":"venue"
},
  "geometry": {"coordinates":[8.974908,50.973446],"type":"Point"}
}