{
  "type": "Feature",
  "properties": {
    "iso:country":"DE",
    "sg:address":"Martin-Luther-Str. 26",
    "sg:city":"Viersen",
    "sg:phone":"+49 2162/52157",
    "sg:postcode":"41751",
    "sg:province":"Nordrhein-Westfalen",
    "wof:name":"Rolf R\u00f6ser",
    "wof:placetype":"venue"
},
  "geometry": {"coordinates":[6.3390960693,51.2556915283],"type":"Point"}
}