{
  "type": "Feature",
  "properties": {
    "iso:country":"DE",
    "sg:address":"Ostring 33",
    "sg:city":"Burghaun",
    "sg:phone":"+49 6652/2925",
    "sg:postcode":"36151",
    "sg:province":"Hessen",
    "wof:name":"Helmut Barthel",
    "wof:placetype":"venue"
},
  "geometry": {"coordinates":[9.7251300812,50.7048606873],"type":"Point"}
}