{
  "type": "Feature",
  "properties": {
    "iso:country":"DE",
    "sg:address":"Schenefelder Chaussee 81",
    "sg:city":"Itzehoe",
    "sg:phone":"+49 4821/41174",
    "sg:postcode":"25524",
    "sg:province":"Schleswig-Holstein",
    "wof:name":"Karl-heinz Braasch Gmbh",
    "wof:placetype":"venue"
},
  "geometry": {"coordinates":[9.493926,53.953278],"type":"Point"}
}