{
  "type": "Feature",
  "properties": {
    "iso:country":"DE",
    "sg:address":"Seestr. 15",
    "sg:city":"Rheinsberg",
    "sg:phone":"+49 33931/2221",
    "sg:postcode":"16831",
    "sg:province":"Brandenburg",
    "wof:name":"Auktionshaus Rheinsberg Kg",
    "wof:placetype":"venue"
},
  "geometry": {"coordinates":[12.8905086517,53.1005630493],"type":"Point"}
}