{
  "type": "Feature",
  "properties": {
    "iso:country":"DE",
    "sg:address":"Tellmer Dorfstr. 5",
    "sg:city":"Betzendorf",
    "sg:phone":"+49 4138/1250",
    "sg:postcode":"21386",
    "sg:province":"Niedersachsen",
    "wof:name":"Niesler Dachdeckerbetrieb Gmbh",
    "wof:placetype":"venue"
},
  "geometry": {"coordinates":[10.302386,53.111874],"type":"Point"}
}