{
  "type": "Feature",
  "properties": {
    "iso:country":"DE",
    "sg:address":"Pyramidenweg 20",
    "sg:city":"Untersiemau",
    "sg:phone":"+49 9565/858",
    "sg:postcode":"96253",
    "sg:province":"Bayern",
    "wof:name":"Gehlen Polsterm\u00f6bel Gmbh",
    "wof:placetype":"venue"
},
  "geometry": {"coordinates":[10.969080925,50.1991729736],"type":"Point"}
}