{
  "type": "Feature",
  "properties": {
    "iso:country":"DE",
    "sg:address":"Kornblumenstr. 8",
    "sg:city":"Staufenberg",
    "sg:phone":"+49 6406/3775",
    "sg:postcode":"35460",
    "sg:province":"Hessen",
    "wof:name":"Heimatmuseum",
    "wof:placetype":"venue"
},
  "geometry": {"coordinates":[8.72903,50.660042],"type":"Point"}
}