{
  "type": "Feature",
  "properties": {
    "iso:country":"DE",
    "sg:address":"Otto-Hahn-Ring 20",
    "sg:city":"M\u00fcnchen",
    "sg:phone":"+49 89/12063600",
    "sg:postcode":"81739",
    "sg:province":"Bayern",
    "wof:name":"Daimler Chrysler Bank Gmbh",
    "wof:placetype":"venue"
},
  "geometry": {"coordinates":[11.655457,48.090858],"type":"Point"}
}