{
  "type": "Feature",
  "properties": {
    "iso:country":"DE",
    "sg:address":"Berner Weg 34 a",
    "sg:city":"Hamburg",
    "sg:phone":"+49 40/6018109",
    "sg:postcode":"22393",
    "sg:province":"Hamburg",
    "wof:name":"Werner Wittenburg Gmbh",
    "wof:placetype":"venue"
},
  "geometry": {"coordinates":[10.117492,53.648849],"type":"Point"}
}