{
  "type": "Feature",
  "properties": {
    "iso:country":"DE",
    "sg:address":"Obere Hainstr. 14",
    "sg:city":"Oberursel",
    "sg:phone":"+49 6171/4744",
    "sg:postcode":"61440",
    "sg:province":"Hessen",
    "wof:name":"Alfred Burkard",
    "wof:placetype":"venue"
},
  "geometry": {"coordinates":[8.575868,50.203743],"type":"Point"}
}