{
  "type": "Feature",
  "properties": {
    "iso:country":"DE",
    "sg:address":"Sch\u00fcrener Str. 29",
    "sg:city":"Dortmund",
    "sg:phone":"+49 231/457445",
    "sg:postcode":"44269",
    "sg:province":"Nordrhein-Westfalen",
    "wof:name":"Tomislav Loncar Ingenieur",
    "wof:placetype":"venue"
},
  "geometry": {"coordinates":[7.5366110802,51.4927711487],"type":"Point"}
}