{
  "type": "Feature",
  "properties": {
    "iso:country":"DE",
    "sg:address":"Troppauer Str. 5",
    "sg:city":"H\u00f6chstadt",
    "sg:phone":"+49 9193/7466",
    "sg:postcode":"91315",
    "sg:province":"Bayern",
    "wof:name":"Fotostudio Somieski Gmbh",
    "wof:placetype":"venue"
},
  "geometry": {"coordinates":[10.8131332397,49.6954574585],"type":"Point"}
}