{
  "type": "Feature",
  "properties": {
    "iso:country":"DE",
    "sg:address":"August-Bebel-Str. 56",
    "sg:city":"Pforzheim",
    "sg:phone":"+49 7231/73171",
    "sg:postcode":"75180",
    "sg:province":"Baden-W\u00fcrttemberg",
    "wof:name":"Hans K. Hirn Rechtsanwalt",
    "wof:placetype":"venue"
},
  "geometry": {"coordinates":[8.6684856415,48.8725166321],"type":"Point"}
}