{
  "type": "Feature",
  "properties": {
    "iso:country":"DE",
    "sg:address":"Johannes-Kerer-Str. 1",
    "sg:city":"Wertheim",
    "sg:phone":"+49 9342/5008",
    "sg:postcode":"97877",
    "sg:province":"Baden-W\u00fcrttemberg",
    "wof:name":"Gastst\u00e4tte Zirkelbach",
    "wof:placetype":"venue"
},
  "geometry": {"coordinates":[9.5010557175,49.7829551697],"type":"Point"}
}