{
  "type": "Feature",
  "properties": {
    "iso:country":"DE",
    "sg:address":"Bahnhofstr. 3 a",
    "sg:city":"Sarstedt",
    "sg:phone":"+49 5066/2682",
    "sg:postcode":"31157",
    "sg:province":"Niedersachsen",
    "wof:name":"Ulrich Kindling",
    "wof:placetype":"venue"
},
  "geometry": {"coordinates":[9.8432617188,52.2320556641],"type":"Point"}
}