{
  "type": "Feature",
  "properties": {
    "iso:country":"DE",
    "sg:address":"Ostertorsteinweg 97",
    "sg:city":"Bremen",
    "sg:phone":"+49 421/78112",
    "sg:postcode":"28203",
    "sg:province":"Bremen",
    "wof:name":"Ernst Birkle",
    "wof:placetype":"venue"
},
  "geometry": {"coordinates":[8.821831,53.072765],"type":"Point"}
}