{
  "type": "Feature",
  "properties": {
    "iso:country":"DE",
    "sg:address":"Cheruskerstr. 48",
    "sg:city":"D\u00fcsseldorf",
    "sg:phone":"+49 211/551284",
    "sg:postcode":"40545",
    "sg:province":"Nordrhein-Westfalen",
    "wof:name":"Herbert Wallner Architekt",
    "wof:placetype":"venue"
},
  "geometry": {"coordinates":[6.752439,51.230247],"type":"Point"}
}