{
  "type": "Feature",
  "properties": {
    "iso:country":"DE",
    "sg:address":"Friedrichstr. 15",
    "sg:city":"Schwerin",
    "sg:phone":"+49 385/590130",
    "sg:postcode":"19055",
    "sg:province":"Mecklenburg-Vorpommern",
    "wof:name":"Modehaus Am Dom Gmbh",
    "wof:placetype":"venue"
},
  "geometry": {"coordinates":[11.415523,53.629875],"type":"Point"}
}