{
  "type": "Feature",
  "properties": {
    "iso:country":"DE",
    "sg:address":"Horner Heerstr. 37",
    "sg:city":"Bremen",
    "sg:phone":"+49 421/230112",
    "sg:postcode":"28359",
    "sg:province":"Bremen",
    "wof:name":"Petersen Augenoptiker",
    "wof:placetype":"venue"
},
  "geometry": {"coordinates":[8.8704357147,53.0969314575],"type":"Point"}
}