{
  "type": "Feature",
  "properties": {
    "iso:country":"DE",
    "sg:address":"Weinbergstr. 37",
    "sg:city":"Kassel",
    "sg:postcode":"34117",
    "sg:province":"Hessen",
    "wof:name":"Aschoffs Supermarkt Gmbh",
    "wof:placetype":"venue"
},
  "geometry": {"coordinates":[9.4858779907,51.309261322],"type":"Point"}
}