{
  "type": "Feature",
  "properties": {
    "iso:country":"DE",
    "sg:address":"Schwander Str. 3",
    "sg:city":"Rednitzhembach",
    "sg:phone":"+49 9122/72285",
    "sg:postcode":"91126",
    "sg:province":"Bayern",
    "wof:name":"Helmut Ges\u00e4nger",
    "wof:placetype":"venue"
},
  "geometry": {"coordinates":[11.0829267502,49.2990608215],"type":"Point"}
}