{
  "type": "Feature",
  "properties": {
    "iso:country":"DE",
    "sg:address":"Engelbosteler Damm 24",
    "sg:city":"Hannover",
    "sg:phone":"+49 511/702251",
    "sg:postcode":"30167",
    "sg:province":"Niedersachsen",
    "wof:name":"Hansa-apotheke Eckhardt Schlie E. K.",
    "wof:placetype":"venue"
},
  "geometry": {"coordinates":[9.725444,52.383804],"type":"Point"}
}