{
  "type": "Feature",
  "properties": {
    "iso:country":"DE",
    "sg:address":"Frontenhausener Str. 64",
    "sg:city":"Vilsbiburg",
    "sg:postcode":"84137",
    "sg:province":"Bayern",
    "wof:name":"Dkig Deutsch-kroatische Investitionsgesellschaft Mbh",
    "wof:placetype":"venue"
},
  "geometry": {"coordinates":[12.359117,48.451942],"type":"Point"}
}