{
  "type": "Feature",
  "properties": {
    "iso:country":"DE",
    "sg:address":"Ziegelgasse 12",
    "sg:city":"Amberg",
    "sg:phone":"+49 9621/47250",
    "sg:postcode":"92224",
    "sg:province":"Bayern",
    "wof:name":"Stahler Und Schmidt-wobst Steuerberater",
    "wof:placetype":"venue"
},
  "geometry": {"coordinates":[11.8604984283,49.4471473694],"type":"Point"}
}