{
  "type": "Feature",
  "properties": {
    "iso:country":"DE",
    "sg:address":"Breslauer Str. 13",
    "sg:city":"Neu Wulmstorf",
    "sg:phone":"+49 40/7006828",
    "sg:postcode":"21629",
    "sg:province":"Niedersachsen",
    "wof:name":"Hans-j\u00fcrgen Popp Gmbh",
    "wof:placetype":"venue"
},
  "geometry": {"coordinates":[9.804181,53.460659],"type":"Point"}
}