{
  "type": "Feature",
  "properties": {
    "iso:country":"DE",
    "sg:address":"Marconistr. 15",
    "sg:city":"Mannheim",
    "sg:phone":"+49 4962/1728220",
    "sg:postcode":"68309",
    "sg:province":"Baden-W\u00fcrttemberg",
    "wof:name":"Christoph Bernet Gmbh",
    "wof:placetype":"venue"
},
  "geometry": {"coordinates":[8.506296,49.511444],"type":"Point"}
}