{
  "type": "Feature",
  "properties": {
    "iso:country":"DE",
    "sg:address":"Hohmannstr. 22",
    "sg:city":"Bad Kissingen",
    "sg:phone":"+49 971/3567",
    "sg:postcode":"97688",
    "sg:province":"Bayern",
    "wof:name":"Werner Deppisch",
    "wof:placetype":"venue"
},
  "geometry": {"coordinates":[10.0747041702,50.2111778259],"type":"Point"}
}