{
  "type": "Feature",
  "properties": {
    "iso:country":"DE",
    "sg:address":"Friedrich-Ludwig-Jahn-Str. 1-3",
    "sg:city":"Nienburg",
    "sg:phone":"+49 5021/912712",
    "sg:postcode":"31582",
    "sg:province":"Niedersachsen",
    "wof:name":"Uhrenfachgesch\u00e4ft Wilfried Schnauer",
    "wof:placetype":"venue"
},
  "geometry": {"coordinates":[9.2070922852,52.6410331726],"type":"Point"}
}