{
  "type": "Feature",
  "properties": {
    "iso:country":"DE",
    "sg:address":"Wildparkstr. 7",
    "sg:city":"R\u00f6hrsdorf",
    "sg:postcode":"09247",
    "sg:province":"Sachsen",
    "wof:name":"Arc Auto Rent Chemnitz Gmbh",
    "wof:placetype":"venue"
},
  "geometry": {"coordinates":[12.857005,50.864796],"type":"Point"}
}