{
  "type": "Feature",
  "properties": {
    "iso:country":"DE",
    "sg:address":"Kaiserstr. 6",
    "sg:city":"K\u00f6ln",
    "sg:phone":"+49 2203/21122",
    "sg:postcode":"51145",
    "sg:province":"Nordrhein-Westfalen",
    "wof:name":"Eiscafe Arcobaleno",
    "wof:placetype":"venue"
},
  "geometry": {"coordinates":[7.081811,50.881599],"type":"Point"}
}