{
  "type": "Feature",
  "properties": {
    "iso:country":"DE",
    "sg:address":"Burghauser Str. 2",
    "sg:city":"Alt\u00f6tting",
    "sg:phone":"+49 8671/6560",
    "sg:postcode":"84503",
    "sg:province":"Bayern",
    "wof:name":"Udo Siebzehnr\u00fcbl",
    "wof:placetype":"venue"
},
  "geometry": {"coordinates":[12.677654,48.224533],"type":"Point"}
}