{
  "type": "Feature",
  "properties": {
    "iso:country":"DE",
    "sg:address":"Wassertr\u00fcdinger Str. 10",
    "sg:city":"Dinkelsb\u00fchl",
    "sg:phone":"+49 9851/553997",
    "sg:postcode":"91550",
    "sg:province":"Bayern",
    "wof:name":"Richard Splett Grundst\u00fccks Gmbh & Co. Kg",
    "wof:placetype":"venue"
},
  "geometry": {"coordinates":[10.3341531754,49.0660400391],"type":"Point"}
}