{
  "type": "Feature",
  "properties": {
    "iso:country":"DE",
    "sg:address":"Tummelburg 2",
    "sg:city":"Bad Gandersheim",
    "sg:phone":"+49 5382/930743",
    "sg:postcode":"37581",
    "sg:province":"Niedersachsen",
    "wof:name":"Eiscafe Venecia",
    "wof:placetype":"venue"
},
  "geometry": {"coordinates":[10.028051,51.870258],"type":"Point"}
}