{
  "type": "Feature",
  "properties": {
    "iso:country":"DE",
    "sg:address":"Brunckstr. 55",
    "sg:city":"Maxdorf",
    "sg:phone":"+49 6237/3514",
    "sg:postcode":"67133",
    "sg:province":"Rheinland-Pfalz",
    "wof:name":"Rudi Laber",
    "wof:placetype":"venue"
},
  "geometry": {"coordinates":[8.2851991653,49.4785194397],"type":"Point"}
}