{
  "type": "Feature",
  "properties": {
    "iso:country":"DE",
    "sg:address":"Carl-Meyer-Str. 6",
    "sg:city":"B\u00f6hlitz-Ehrenberg",
    "sg:phone":"+49 341/4512655",
    "sg:postcode":"04430",
    "wof:name":"Helmut Barras",
    "wof:placetype":"venue"
},
  "geometry": {"coordinates":[12.2923898697,51.3594207764],"type":"Point"}
}