{
  "type": "Feature",
  "properties": {
    "iso:country":"DE",
    "sg:address":"Bismarckstr. 7",
    "sg:city":"Friedberg",
    "sg:phone":"+49 6031/69060",
    "sg:postcode":"61169",
    "sg:province":"Hessen",
    "wof:name":"Gottfried G. Roskoni Und H. Br\u00fcckmann",
    "wof:placetype":"venue"
},
  "geometry": {"coordinates":[8.7554397583,50.3348426819],"type":"Point"}
}