{
  "type": "Feature",
  "properties": {
    "iso:country":"DE",
    "sg:address":"Arnhofener Weg 30",
    "sg:city":"Abensberg",
    "sg:phone":"+49 9443/91510",
    "sg:postcode":"93326",
    "sg:province":"Bayern",
    "wof:name":"Heigls Kartoffelveredelungs Gmbh",
    "wof:placetype":"venue"
},
  "geometry": {"coordinates":[11.8612957001,48.8205375671],"type":"Point"}
}