{
  "type": "Feature",
  "properties": {
    "iso:country":"DE",
    "sg:address":"Friedrichstr. 3",
    "sg:city":"Weil am Rhein",
    "sg:phone":"+49 7621/72185",
    "sg:postcode":"79576",
    "sg:province":"Baden-W\u00fcrttemberg",
    "wof:name":"Heinz Klein Binnenfischerei",
    "wof:placetype":"venue"
},
  "geometry": {"coordinates":[7.6141638756,47.5923156738],"type":"Point"}
}