{
  "type": "Feature",
  "properties": {
    "iso:country":"DE",
    "sg:address":"Hochstr. 119",
    "sg:city":"Heinsberg",
    "sg:phone":"+49 2452/22009",
    "sg:postcode":"52525",
    "sg:province":"Nordrhein-Westfalen",
    "wof:name":"B\u00e4cker Dick Kg",
    "wof:placetype":"venue"
},
  "geometry": {"coordinates":[6.095718,51.063141],"type":"Point"}
}