{
  "type": "Feature",
  "properties": {
    "iso:country":"DE",
    "sg:address":"Hainerbergweg 51",
    "sg:city":"K\u00f6nigstein",
    "sg:phone":"+49 6174/4509",
    "sg:postcode":"61462",
    "sg:province":"Hessen",
    "wof:name":"Dr. Hans-peter Reuter Rechtsanwalt",
    "wof:placetype":"venue"
},
  "geometry": {"coordinates":[8.4692468643,50.1728820801],"type":"Point"}
}