{
  "type": "Feature",
  "properties": {
    "iso:country":"DE",
    "sg:address":"Im Wiesengrund 1",
    "sg:city":"Sprakensehl",
    "sg:phone":"+49 5837/373",
    "sg:postcode":"29365",
    "sg:province":"Niedersachsen",
    "wof:name":"Helmut Schulenburg",
    "wof:placetype":"venue"
},
  "geometry": {"coordinates":[10.545386,52.809547],"type":"Point"}
}