{
  "type": "Feature",
  "properties": {
    "iso:country":"DE",
    "sg:address":"Hoppenberg 6",
    "sg:city":"Boffzen",
    "sg:phone":"+49 5271/5257",
    "sg:postcode":"37691",
    "sg:province":"Niedersachsen",
    "wof:name":"M\u00fcller Asphaltbau Und Bedachungen",
    "wof:placetype":"venue"
},
  "geometry": {"coordinates":[9.403842,51.749634],"type":"Point"}
}