{
  "type": "Feature",
  "properties": {
    "iso:country":"DE",
    "sg:address":"Helfergasse 5",
    "sg:city":"Langenau",
    "sg:phone":"+49 7345/22760",
    "sg:postcode":"89129",
    "sg:province":"Baden-W\u00fcrttemberg",
    "wof:name":"Eugen Pfl\u00fcger",
    "wof:placetype":"venue"
},
  "geometry": {"coordinates":[10.1242637634,48.5009384155],"type":"Point"}
}