{
  "type": "Feature",
  "properties": {
    "iso:country":"DE",
    "sg:address":"Weetfelder Str. 104",
    "sg:city":"Hamm",
    "sg:phone":"+49 2381/400547",
    "sg:postcode":"59077",
    "sg:province":"Nordrhein-Westfalen",
    "wof:name":"Ev. Pfarramt Wiescherh\u00f6fen",
    "wof:placetype":"venue"
},
  "geometry": {"coordinates":[7.7829837799,51.6406097412],"type":"Point"}
}