{
  "type": "Feature",
  "properties": {
    "iso:country":"DE",
    "sg:address":"Parkstr. 45",
    "sg:city":"Neuenhagen",
    "sg:phone":"+49 3342/201326",
    "sg:postcode":"15366",
    "sg:province":"Brandenburg",
    "wof:name":"U. Brenner & R. Klemenz",
    "wof:placetype":"venue"
},
  "geometry": {"coordinates":[13.674704,52.529335],"type":"Point"}
}