{
  "type": "Feature",
  "properties": {
    "iso:country":"DE",
    "sg:address":"Oldesloer Str. 5",
    "sg:city":"Berkenthin",
    "sg:phone":"+49 4544/82388",
    "sg:postcode":"23919",
    "sg:province":"Schleswig-Holstein",
    "wof:name":"Macke",
    "wof:placetype":"venue"
},
  "geometry": {"coordinates":[10.641238,53.734425],"type":"Point"}
}