{
  "type": "Feature",
  "properties": {
    "iso:country":"DE",
    "sg:address":"Alter Weg 23",
    "sg:city":"Cuxhaven",
    "sg:postcode":"27478",
    "sg:province":"Niedersachsen",
    "wof:name":"Umwelt Windprojekt Gmbh & Co. Thyrowberg Kg",
    "wof:placetype":"venue"
},
  "geometry": {"coordinates":[8.767137,53.825413],"type":"Point"}
}