{
  "type": "Feature",
  "properties": {
    "iso:country":"DE",
    "sg:address":"Hosigaustr. 10",
    "sg:city":"M\u00fcnchen",
    "sg:phone":"+49 89/70009230",
    "sg:postcode":"81375",
    "sg:province":"Bayern",
    "wof:name":"Rainer Mahler Verlagsmarketing Gmbh",
    "wof:placetype":"venue"
},
  "geometry": {"coordinates":[11.4751253128,48.1200141907],"type":"Point"}
}