{
  "type": "Feature",
  "properties": {
    "iso:country":"DE",
    "sg:address":"Industriestr. 4",
    "sg:city":"Zella-Mehlis",
    "sg:postcode":"98544",
    "sg:province":"Th\u00fcringen",
    "wof:name":"Media Markt Tv-hifi- Elektro Gmbh",
    "wof:placetype":"venue"
},
  "geometry": {"coordinates":[10.6903495789,50.6443328857],"type":"Point"}
}