{
  "type": "Feature",
  "properties": {
    "iso:country":"DE",
    "sg:address":"Chausseestr. 6",
    "sg:city":"Vierraden",
    "sg:phone":"+49 3332/22579",
    "sg:postcode":"16306",
    "sg:province":"Brandenburg",
    "wof:name":"I. Gerhardt",
    "wof:placetype":"venue"
},
  "geometry": {"coordinates":[14.2109642029,53.210559845],"type":"Point"}
}