{
  "type": "Feature",
  "properties": {
    "iso:country":"DE",
    "sg:address":"Hochstr. 215",
    "sg:city":"Duisburg",
    "sg:phone":"+49 2065/77250",
    "sg:postcode":"47228",
    "sg:province":"Nordrhein-Westfalen",
    "wof:name":"C-dat Computer- Datentechnik Gmbh",
    "wof:placetype":"venue"
},
  "geometry": {"coordinates":[6.6843299866,51.4211006165],"type":"Point"}
}