{
  "type": "Feature",
  "properties": {
    "iso:country":"DE",
    "sg:address":"St. Margareten 12",
    "sg:city":"Brannenburg",
    "sg:phone":"+49 8034/8199",
    "sg:postcode":"83098",
    "sg:province":"Bayern",
    "wof:name":"Berggasthaus Kraxenberger",
    "wof:placetype":"venue"
},
  "geometry": {"coordinates":[12.083236,47.729736],"type":"Point"}
}