{
  "type": "Feature",
  "properties": {
    "iso:country":"DE",
    "sg:address":"Theresienstr. 1",
    "sg:city":"Hof",
    "sg:phone":"+49 9281/84375",
    "sg:postcode":"95028",
    "sg:province":"Bayern",
    "wof:name":"Helmut Eckardt",
    "wof:placetype":"venue"
},
  "geometry": {"coordinates":[11.9149484634,50.3116188049],"type":"Point"}
}