{
  "type": "Feature",
  "properties": {
    "iso:country":"DE",
    "sg:address":"Mannheimer Str. 38",
    "sg:city":"Oftersheim",
    "sg:phone":"+49 4962/0220162",
    "sg:postcode":"68723",
    "sg:province":"Baden-W\u00fcrttemberg",
    "wof:name":"Bezirkssparkasse Schwetzingen",
    "wof:placetype":"venue"
},
  "geometry": {"coordinates":[8.583339,49.369644],"type":"Point"}
}