{
  "type": "Feature",
  "properties": {
    "iso:country":"DE",
    "sg:address":"Aueliede 24",
    "sg:city":"Schmalkalden",
    "sg:phone":"+49 3683/402674",
    "sg:postcode":"98574",
    "sg:province":"Th\u00fcringen",
    "wof:name":"Dr. Gerhard Kuner Tierarzt",
    "wof:placetype":"venue"
},
  "geometry": {"coordinates":[10.470246315,50.7228813171],"type":"Point"}
}