{
  "type": "Feature",
  "properties": {
    "iso:country":"DE",
    "sg:address":"Goethestr. 6",
    "sg:city":"Burgkunstadt",
    "sg:phone":"+49 9572/1266",
    "sg:postcode":"96224",
    "sg:province":"Bayern",
    "wof:name":"Gemeinn. Wohnungsunternehmen Burgkunstadt Und Umgebung Eg",
    "wof:placetype":"venue"
},
  "geometry": {"coordinates":[11.2577962875,50.139541626],"type":"Point"}
}