{
  "type": "Feature",
  "properties": {
    "iso:country":"DE",
    "sg:address":"M\u00fchlbachstr 20",
    "sg:city":"Seefeld",
    "sg:phone":"+49 8152/37200",
    "sg:postcode":"82229",
    "sg:province":"Bayern",
    "wof:name":"Sdt Dr. Seitner Gmbh",
    "wof:placetype":"venue"
},
  "geometry": {"coordinates":[11.216133,48.04073],"type":"Point"}
}