{
  "type": "Feature",
  "properties": {
    "iso:country":"DE",
    "sg:address":"Bahnhofstr. 9",
    "sg:city":"Rothenburg",
    "sg:phone":"+49 35891/35229",
    "sg:postcode":"02929",
    "sg:province":"Sachsen",
    "wof:name":"Hartmut Steinert",
    "wof:placetype":"venue"
},
  "geometry": {"coordinates":[14.967549324,51.3339042664],"type":"Point"}
}