{
  "type": "Feature",
  "properties": {
    "iso:country":"DE",
    "sg:address":"Ernst-Hohner-Str. 37",
    "sg:city":"Trossingen",
    "sg:phone":"+49 7425/31407",
    "sg:postcode":"78647",
    "sg:province":"Baden-W\u00fcrttemberg",
    "wof:name":"Plus Warenhandels- Gmbh & Co.",
    "wof:placetype":"venue"
},
  "geometry": {"coordinates":[8.6369600296,48.0697784424],"type":"Point"}
}