{
  "type": "Feature",
  "properties": {
    "iso:country":"DE",
    "sg:address":"Mohnweg 5",
    "sg:city":"Stuttgart",
    "sg:postcode":"70599",
    "sg:province":"Baden-W\u00fcrttemberg",
    "wof:name":"Reuss Gastroservice Gmbh",
    "wof:placetype":"venue"
},
  "geometry": {"coordinates":[9.197529,48.71526],"type":"Point"}
}