{
  "type": "Feature",
  "properties": {
    "iso:country":"DE",
    "sg:address":"Perrestr. 2",
    "sg:city":"Leipzig",
    "sg:phone":"+49 341/4800438",
    "sg:postcode":"04229",
    "sg:province":"Sachsen",
    "wof:name":"J\u00fcrgen H\u00e4u\u00dfler",
    "wof:placetype":"venue"
},
  "geometry": {"coordinates":[12.3452720642,51.3155784607],"type":"Point"}
}