{
  "type": "Feature",
  "properties": {
    "iso:country":"DE",
    "sg:address":"Baiersdorfer Str. 2",
    "sg:city":"Effeltrich",
    "sg:phone":"+49 9133/3820",
    "sg:postcode":"91090",
    "sg:province":"Bayern",
    "wof:name":"Fischer Gr\u00fcnbau Gmbh",
    "wof:placetype":"venue"
},
  "geometry": {"coordinates":[11.091747,49.660343],"type":"Point"}
}