{
  "type": "Feature",
  "properties": {
    "iso:country":"DE",
    "sg:address":"In den Gr\u00fcben 11",
    "sg:city":"Jockgrim",
    "sg:phone":"+49 7271/5726",
    "sg:postcode":"76751",
    "sg:province":"Rheinland-Pfalz",
    "wof:name":"Siegfried Weigel Stahl- Und Apparatebau Gmbh",
    "wof:placetype":"venue"
},
  "geometry": {"coordinates":[8.273904,49.099247],"type":"Point"}
}