{
  "type": "Feature",
  "properties": {
    "iso:country":"DE",
    "sg:address":"Zur Arche",
    "sg:city":"Menden",
    "sg:postcode":"58706",
    "sg:province":"Nordrhein-Westfalen",
    "wof:name":"Freibad Arche Noah",
    "wof:placetype":"venue"
},
  "geometry": {"coordinates":[7.8191537857,51.4266395569],"type":"Point"}
}