{
  "type": "Feature",
  "properties": {
    "iso:country":"DE",
    "sg:address":"Ringstr. 8",
    "sg:city":"Nettetal",
    "sg:phone":"+49 2157/6123",
    "sg:postcode":"41334",
    "sg:province":"Nordrhein-Westfalen",
    "wof:name":"Alfred Wesch",
    "wof:placetype":"venue"
},
  "geometry": {"coordinates":[6.19046,51.318489],"type":"Point"}
}