{
  "type": "Feature",
  "properties": {
    "iso:country":"DE",
    "sg:address":"Tennenbacher Str. 31",
    "sg:city":"Freiburg",
    "sg:phone":"+49 761/2024743",
    "sg:postcode":"79106",
    "sg:province":"Baden-W\u00fcrttemberg",
    "wof:name":"Dr. Jost-caesar B\u00f6hme Rechtsanwalt",
    "wof:placetype":"venue"
},
  "geometry": {"coordinates":[7.8482069969,48.0054779053],"type":"Point"}
}