{
  "type": "Feature",
  "properties": {
    "iso:country":"DE",
    "sg:address":"Hollentalstr. 11",
    "sg:city":"Steinheim",
    "sg:phone":"+49 5233/1333",
    "sg:postcode":"32839",
    "sg:province":"Nordrhein-Westfalen",
    "wof:name":"R. Buhler",
    "wof:placetype":"venue"
},
  "geometry": {"coordinates":[9.094245,51.867485],"type":"Point"}
}