{
  "type": "Feature",
  "properties": {
    "iso:country":"DE",
    "sg:address":"Innere Wiener Str. 46",
    "sg:city":"M\u00fcnchen",
    "sg:phone":"+49 89/4489580",
    "sg:postcode":"81667",
    "sg:province":"Bayern",
    "wof:name":"H. Hutterer Architekt",
    "wof:placetype":"venue"
},
  "geometry": {"coordinates":[11.596147,48.134056],"type":"Point"}
}