{
  "type": "Feature",
  "properties": {
    "iso:country":"DE",
    "sg:address":"Klosterstr. 43a",
    "sg:city":"Dorsten",
    "sg:phone":"+49 2362/92810",
    "sg:postcode":"46282",
    "sg:province":"Nordrhein-Westfalen",
    "wof:name":"Heinz Und Bernd Huffmann Steuerberater",
    "wof:placetype":"venue"
},
  "geometry": {"coordinates":[6.9554228783,51.6604881287],"type":"Point"}
}