{
  "type": "Feature",
  "properties": {
    "iso:country":"DE",
    "sg:address":"Sch\u00fcttorfer Str. 16",
    "sg:city":"Salzbergen",
    "sg:phone":"+49 5976/9393",
    "sg:postcode":"48499",
    "sg:province":"Niedersachsen",
    "wof:name":"Robers Taxi",
    "wof:placetype":"venue"
},
  "geometry": {"coordinates":[7.339012146,52.3218917847],"type":"Point"}
}