{
  "type": "Feature",
  "properties": {
    "iso:country":"DE",
    "sg:address":"Kirchfeldstr. 14",
    "sg:city":"Essen",
    "sg:phone":"+49 2054/2145",
    "sg:postcode":"45219",
    "sg:province":"Nordrhein-Westfalen",
    "wof:name":"G. Dohr",
    "wof:placetype":"venue"
},
  "geometry": {"coordinates":[6.938487,51.364666],"type":"Point"}
}