{
  "type": "Feature",
  "properties": {
    "iso:country":"DE",
    "sg:address":"Klaus-Herrmann-Str. 20",
    "sg:city":"Guben",
    "sg:phone":"+49 3561/53602",
    "sg:postcode":"03172",
    "sg:province":"Brandenburg",
    "wof:name":"C. Hensel",
    "wof:placetype":"venue"
},
  "geometry": {"coordinates":[14.683171,51.953354],"type":"Point"}
}