{
  "type": "Feature",
  "properties": {
    "iso:country":"DE",
    "sg:address":"Am Lienkamp 11",
    "sg:city":"Langenhagen",
    "sg:phone":"+49 511/744660",
    "sg:postcode":"30855",
    "sg:province":"Niedersachsen",
    "wof:name":"H. Zimmermann Immobilienmakler",
    "wof:placetype":"venue"
},
  "geometry": {"coordinates":[9.6952972412,52.4411582947],"type":"Point"}
}