{
  "type": "Feature",
  "properties": {
    "iso:country":"DE",
    "sg:address":"Syrlinstr. 20",
    "sg:city":"Ulm",
    "sg:phone":"+49 731/63110",
    "sg:postcode":"89073",
    "sg:province":"Baden-W\u00fcrttemberg",
    "wof:name":"Manfred Sch\u00f6tz",
    "wof:placetype":"venue"
},
  "geometry": {"coordinates":[9.990364,48.403973],"type":"Point"}
}