{
  "type": "Feature",
  "properties": {
    "iso:country":"DE",
    "sg:address":"Huisberdener Str. 30",
    "sg:city":"Kleve",
    "sg:postcode":"47533",
    "sg:province":"Nordrhein-Westfalen",
    "wof:name":"M. S. W. Rheinbau Bautr\u00e4ger Gmbh",
    "wof:placetype":"venue"
},
  "geometry": {"coordinates":[6.201132,51.807148],"type":"Point"}
}