{
  "type": "Feature",
  "properties": {
    "iso:country":"DE",
    "sg:address":"Solinger Str. 174",
    "sg:city":"Langenfeld",
    "sg:phone":"+49 212/24479",
    "sg:postcode":"40764",
    "sg:province":"Nordrhein-Westfalen",
    "wof:name":"H. Fa\u00dfbender",
    "wof:placetype":"venue"
},
  "geometry": {"coordinates":[6.9617657661,51.1152610779],"type":"Point"}
}