{
  "type": "Feature",
  "properties": {
    "iso:country":"DE",
    "sg:address":"Wichsenstein",
    "sg:city":"G\u00f6\u00dfweinstein",
    "sg:phone":"+49 9197/509",
    "sg:postcode":"91327",
    "sg:province":"Bayern",
    "wof:name":"Gasthaus Felsennest",
    "wof:placetype":"venue"
},
  "geometry": {"coordinates":[11.2611999512,49.7361068726],"type":"Point"}
}