{
  "type": "Feature",
  "properties": {
    "iso:country":"DE",
    "sg:address":"Muckenreuth",
    "sg:city":"Neudrossenfeld",
    "sg:phone":"+49 9203/272",
    "sg:postcode":"95512",
    "sg:province":"Bayern",
    "wof:name":"Betty Werner",
    "wof:placetype":"venue"
},
  "geometry": {"coordinates":[11.4924602509,50.0049438477],"type":"Point"}
}