{
  "type": "Feature",
  "properties": {
    "iso:country":"DE",
    "sg:address":"Girardetstr. 34",
    "sg:city":"Wuppertal",
    "sg:phone":"+49 202/726780",
    "sg:postcode":"42109",
    "sg:province":"Nordrhein-Westfalen",
    "wof:name":"Joachim Diel Garten- Und",
    "wof:placetype":"venue"
},
  "geometry": {"coordinates":[7.133274,51.278419],"type":"Point"}
}