{
  "type": "Feature",
  "properties": {
    "iso:country":"DE",
    "sg:address":"Hauptstr. 29",
    "sg:city":"Leopoldsh\u00f6he",
    "sg:phone":"+49 5208/1493",
    "sg:postcode":"33818",
    "sg:province":"Nordrhein-Westfalen",
    "wof:name":"Erich Kerker",
    "wof:placetype":"venue"
},
  "geometry": {"coordinates":[8.698399,52.009212],"type":"Point"}
}