{
  "type": "Feature",
  "properties": {
    "iso:country":"DE",
    "sg:address":"Kl\u00f6tzer Str. 20",
    "sg:city":"Kusey",
    "sg:phone":"+49 39005/456",
    "sg:postcode":"38486",
    "sg:province":"Sachsen-Anhalt",
    "wof:name":"Coiffeur Charmant Gmbh",
    "wof:placetype":"venue"
},
  "geometry": {"coordinates":[11.0916824341,52.581703186],"type":"Point"}
}