{
  "type": "Feature",
  "properties": {
    "iso:country":"DE",
    "sg:address":"Friedrich-List-Str. 35",
    "sg:city":"Althen",
    "sg:phone":"+49 34291/86243",
    "sg:postcode":"04451",
    "sg:province":"Sachsen",
    "wof:name":"Johann Lenders",
    "wof:placetype":"venue"
},
  "geometry": {"coordinates":[12.54433,51.34885],"type":"Point"}
}