{
  "type": "Feature",
  "properties": {
    "iso:country":"DE",
    "sg:address":"Pfarrholz 3",
    "sg:city":"Leimbach",
    "sg:postcode":"99735",
    "sg:province":"Th\u00fcringen",
    "wof:name":"Agrargesellschaft Leimbach Mbh",
    "wof:placetype":"venue"
},
  "geometry": {"coordinates":[10.86167,51.500412],"type":"Point"}
}