{
  "type": "Feature",
  "properties": {
    "iso:country":"DE",
    "sg:address":"Dorfstra\u00dfe 102 H",
    "sg:city":"K\u00f6nigshain",
    "sg:phone":"+49 37202",
    "sg:postcode":"09306",
    "sg:province":"Sachsen",
    "wof:name":"Elektro Kluge - K\u00f6nigshain",
    "wof:placetype":"venue"
},
  "geometry": {"coordinates":[12.8266267776,51.0273284912],"type":"Point"}
}