{
  "type": "Feature",
  "properties": {
    "iso:country":"DE",
    "sg:address":"Hauptstr. 38 a",
    "sg:city":"Hanau",
    "sg:phone":"+49 6181/573765",
    "sg:postcode":"63457",
    "sg:province":"Hessen",
    "wof:name":"Inge Schreiber",
    "wof:placetype":"venue"
},
  "geometry": {"coordinates":[8.9430007935,50.1061096191],"type":"Point"}
}