{
  "type": "Feature",
  "properties": {
    "iso:country":"DE",
    "sg:address":"Am H\u00e4userteich 7",
    "sg:city":"Neukyhna",
    "sg:phone":"+49 34202/21040",
    "sg:postcode":"04509",
    "sg:province":"Sachsen",
    "wof:name":"Haberland",
    "wof:placetype":"venue"
},
  "geometry": {"coordinates":[12.227735,51.526089],"type":"Point"}
}