{
  "type": "Feature",
  "properties": {
    "iso:country":"DE",
    "sg:address":"Karwinskistr. 5",
    "sg:city":"M\u00fcnchen",
    "sg:phone":"+49 89/8144112",
    "sg:postcode":"81247",
    "sg:province":"Bayern",
    "wof:name":"A.s.a. Sicheneder Elektroanlagen Gmbh",
    "wof:placetype":"venue"
},
  "geometry": {"coordinates":[11.474324,48.167774],"type":"Point"}
}