{
  "type": "Feature",
  "properties": {
    "iso:country":"DE",
    "sg:address":"Bahndamm 11",
    "sg:city":"Steinhagen",
    "sg:phone":"+49 5204/91490",
    "sg:postcode":"33803",
    "sg:province":"Nordrhein-Westfalen",
    "wof:name":"Kleen Dichtungstechnik Gmbh",
    "wof:placetype":"venue"
},
  "geometry": {"coordinates":[8.439711,52.009071],"type":"Point"}
}