{
  "type": "Feature",
  "properties": {
    "iso:country":"DE",
    "sg:address":"Rabeckbreite 16",
    "sg:city":"Vienenburg",
    "sg:postcode":"38690",
    "sg:province":"Niedersachsen",
    "wof:name":"Schn\u00e4ppchen-diele Braunschweig Gmbh",
    "wof:placetype":"venue"
},
  "geometry": {"coordinates":[10.5515184402,51.9547462463],"type":"Point"}
}