{
  "type": "Feature",
  "properties": {
    "iso:country":"DE",
    "sg:address":"Schalldorfer Str. 2",
    "sg:city":"Emmering",
    "sg:phone":"+49 8039/1200",
    "sg:postcode":"83550",
    "sg:province":"Bayern",
    "wof:name":"Dr. Heinz Schmidt Tierarzt",
    "wof:placetype":"venue"
},
  "geometry": {"coordinates":[12.0564899445,47.9966316223],"type":"Point"}
}