{
  "type": "Feature",
  "properties": {
    "iso:country":"DE",
    "sg:address":"Wiesenweg 1",
    "sg:city":"Willingen",
    "sg:phone":"+49 5632/6462",
    "sg:postcode":"34508",
    "sg:province":"Hessen",
    "wof:name":"Pension Behle",
    "wof:placetype":"venue"
},
  "geometry": {"coordinates":[8.6150894165,51.2915344238],"type":"Point"}
}