{
  "type": "Feature",
  "properties": {
    "iso:country":"DE",
    "sg:address":"Am Rosengarten 14",
    "sg:city":"Barnstorf",
    "sg:phone":"+49 5442/2389",
    "sg:postcode":"49406",
    "sg:province":"Niedersachsen",
    "wof:name":"Kath. Pfarramt St. Barbara",
    "wof:placetype":"venue"
},
  "geometry": {"coordinates":[8.4995546341,52.7067337036],"type":"Point"}
}