{
  "type": "Feature",
  "properties": {
    "iso:country":"DE",
    "sg:address":"M\u00f6rikestr. 8",
    "sg:city":"Simmozheim",
    "sg:phone":"+49 7033/9522",
    "sg:postcode":"75397",
    "sg:province":"Baden-W\u00fcrttemberg",
    "wof:name":"Bernhard Burr Heilpraktiker",
    "wof:placetype":"venue"
},
  "geometry": {"coordinates":[8.8134078979,48.7535057068],"type":"Point"}
}