{
  "type": "Feature",
  "properties": {
    "iso:country":"DE",
    "sg:address":"Dickmannstr. 2",
    "sg:city":"Essen",
    "sg:phone":"+49 201/8701340",
    "sg:postcode":"45143",
    "sg:province":"Nordrhein-Westfalen",
    "wof:name":"Arbeiterpresse Verlags- Und Vertriebs-gmbh",
    "wof:placetype":"venue"
},
  "geometry": {"coordinates":[6.9819879532,51.4607925415],"type":"Point"}
}