{
  "type": "Feature",
  "properties": {
    "iso:country":"DE",
    "sg:address":"Gutenbergstr. 23",
    "sg:city":"Hainburg",
    "sg:phone":"+49 6182/4762",
    "sg:postcode":"63512",
    "sg:province":"Hessen",
    "wof:name":"Erwin Zechmeister",
    "wof:placetype":"venue"
},
  "geometry": {"coordinates":[8.966406,50.071045],"type":"Point"}
}