{
  "type": "Feature",
  "properties": {
    "iso:country":"DE",
    "sg:address":"Tulpenstr. 10",
    "sg:city":"Dortmund",
    "sg:phone":"+49 231/409482",
    "sg:postcode":"44289",
    "sg:province":"Nordrhein-Westfalen",
    "wof:name":"Ingo Sch\u00f6rgenhummer",
    "wof:placetype":"venue"
},
  "geometry": {"coordinates":[7.5912899971,51.4820594788],"type":"Point"}
}