{
  "type": "Feature",
  "properties": {
    "iso:country":"DE",
    "sg:address":"K\u00e4the-Kollwitz-Str. 33",
    "sg:city":"Gro\u00dfenhain",
    "sg:phone":"+49 3522/63054",
    "sg:postcode":"01558",
    "sg:province":"Sachsen",
    "wof:name":"Bernd Wolfframm",
    "wof:placetype":"venue"
},
  "geometry": {"coordinates":[13.5369853973,51.2854728699],"type":"Point"}
}