{
  "type": "Feature",
  "properties": {
    "iso:country":"DE",
    "sg:address":"M\u00fchlenstr.",
    "sg:city":"Steinfeld",
    "sg:phone":"+49 5492/450",
    "sg:postcode":"49439",
    "sg:province":"Niedersachsen",
    "wof:name":"H. Kr\u00f6ger",
    "wof:placetype":"venue"
},
  "geometry": {"coordinates":[8.226219,52.614086],"type":"Point"}
}