{
  "type": "Feature",
  "properties": {
    "iso:country":"DE",
    "sg:address":"Aloys-Mennekes-Str 1",
    "sg:city":"Kirchhundem",
    "sg:phone":"+49 2723/411",
    "sg:postcode":"57399",
    "sg:province":"Nordrhein-Westfalen",
    "wof:name":"Mennekes Elektrotechnik Gmbh & Co Kg",
    "wof:placetype":"venue"
},
  "geometry": {"coordinates":[8.0777168274,51.0913238525],"type":"Point"}
}