{
  "type": "Feature",
  "properties": {
    "iso:country":"DE",
    "sg:address":"Gerst\u00e4ckerweg 34",
    "sg:city":"Berlin",
    "sg:phone":"+49 30/3658753",
    "sg:postcode":"14089",
    "sg:province":"Berlin",
    "wof:name":"Zimmermanns Transport Und Baustoff Gmbh",
    "wof:placetype":"venue"
},
  "geometry": {"coordinates":[13.1288747787,52.4506950378],"type":"Point"}
}