{
  "type": "Feature",
  "properties": {
    "iso:country":"DE",
    "sg:address":"Wurmbergstr. 1",
    "sg:city":"Fladungen",
    "sg:phone":"+49 9778/91220",
    "sg:postcode":"97650",
    "sg:province":"Bayern",
    "wof:name":"Hotel-pension Sonnentau",
    "wof:placetype":"venue"
},
  "geometry": {"coordinates":[10.1524600983,50.52576828],"type":"Point"}
}