{
  "type": "Feature",
  "properties": {
    "iso:country":"DE",
    "sg:address":"Kastanienstr. 7",
    "sg:city":"Detern",
    "sg:phone":"+49 4957/912977",
    "sg:postcode":"26847",
    "sg:province":"Niedersachsen",
    "wof:name":"Malereibetrieb J. Reiners Ohg",
    "wof:placetype":"venue"
},
  "geometry": {"coordinates":[7.660475,53.21344],"type":"Point"}
}