{
  "type": "Feature",
  "properties": {
    "iso:country":"DE",
    "sg:address":"Eichwaldstr. 15",
    "sg:city":"Schmitten",
    "sg:phone":"+49 6082/3107",
    "sg:postcode":"61389",
    "sg:province":"Hessen",
    "wof:name":"Josef Spiess Eisen-und Metallwaren-",
    "wof:placetype":"venue"
},
  "geometry": {"coordinates":[8.425886,50.241764],"type":"Point"}
}