{
  "type": "Feature",
  "properties": {
    "iso:country":"DE",
    "sg:address":"Zollstr. 12",
    "sg:city":"Olbernhau",
    "sg:postcode":"09526",
    "sg:province":"Sachsen",
    "wof:name":"I. Drechsel",
    "wof:placetype":"venue"
},
  "geometry": {"coordinates":[13.379038,50.648922],"type":"Point"}
}