{
  "type": "Feature",
  "properties": {
    "iso:country":"DE",
    "sg:address":"Am Speksel 32",
    "sg:city":"Bielefeld",
    "sg:phone":"+49 521/48314",
    "sg:postcode":"33649",
    "sg:province":"Nordrhein-Westfalen",
    "wof:name":"Klaus Beller Gardinen",
    "wof:placetype":"venue"
},
  "geometry": {"coordinates":[8.4567403793,51.9698448181],"type":"Point"}
}