{
  "type": "Feature",
  "properties": {
    "iso:country":"DE",
    "sg:address":"Florian-Fischer-Str. 1",
    "sg:city":"Bad Birnbach",
    "sg:postcode":"84364",
    "sg:province":"Bayern",
    "wof:name":"Mhs Wirtschaftsberatung Verwaltungs Gmbh",
    "wof:placetype":"venue"
},
  "geometry": {"coordinates":[13.0868997574,48.4475784302],"type":"Point"}
}