{
  "type": "Feature",
  "properties": {
    "iso:country":"DE",
    "sg:address":"Fuldaer Str. 4",
    "sg:city":"Eichenzell",
    "sg:phone":"+49 6659/4603",
    "sg:postcode":"36124",
    "sg:province":"Hessen",
    "wof:name":"E.-m. Krieg",
    "wof:placetype":"venue"
},
  "geometry": {"coordinates":[9.69555,50.49411],"type":"Point"}
}