{
  "type": "Feature",
  "properties": {
    "iso:country":"DE",
    "sg:address":"S\u00fcdstr. 1 a",
    "sg:city":"Eslohe",
    "sg:phone":"+49 2973/6292",
    "sg:postcode":"59889",
    "sg:province":"Nordrhein-Westfalen",
    "wof:name":"Pension Franz Becker",
    "wof:placetype":"venue"
},
  "geometry": {"coordinates":[8.1811199188,51.2448997498],"type":"Point"}
}