{
  "type": "Feature",
  "properties": {
    "iso:country":"DE",
    "sg:address":"Steinerne Furt 65a",
    "sg:city":"Augsburg",
    "sg:phone":"+49 821/703026",
    "sg:postcode":"86167",
    "sg:province":"Bayern",
    "wof:name":"Keller & Hosp Kg",
    "wof:placetype":"venue"
},
  "geometry": {"coordinates":[10.927919,48.394703],"type":"Point"}
}