{
  "type": "Feature",
  "properties": {
    "iso:country":"DE",
    "sg:address":"W\u00f6lckernstr. 52",
    "sg:city":"N\u00fcrnberg",
    "sg:phone":"+49 911/451181",
    "sg:postcode":"90459",
    "sg:province":"Bayern",
    "wof:name":"T\u00fcrkis Tour Travel Gmbh",
    "wof:placetype":"venue"
},
  "geometry": {"coordinates":[11.0862751007,49.4409332275],"type":"Point"}
}