{
  "type": "Feature",
  "properties": {
    "iso:country":"DE",
    "sg:address":"Neue Str. 2",
    "sg:city":"Schemmerhofen",
    "sg:phone":"+49 7356/3851",
    "sg:postcode":"88433",
    "sg:province":"Baden-W\u00fcrttemberg",
    "wof:name":"Eberhard Schmidberger Steuerberater",
    "wof:placetype":"venue"
},
  "geometry": {"coordinates":[9.7843341827,48.1739616394],"type":"Point"}
}