{
  "type": "Feature",
  "properties": {
    "iso:country":"DE",
    "sg:address":"Teichstr. 12",
    "sg:city":"Buxtehude",
    "sg:phone":"+49 4161/721396",
    "sg:postcode":"21614",
    "sg:province":"Niedersachsen",
    "wof:name":"Aacs Gesellschaft F\u00fcr Marketing Und Kommunkation Mbh",
    "wof:placetype":"venue"
},
  "geometry": {"coordinates":[9.6854066849,53.4660644531],"type":"Point"}
}