{
  "type": "Feature",
  "properties": {
    "iso:country":"DE",
    "sg:address":"Bildstockstr. 47",
    "sg:city":"Merchweiler",
    "sg:phone":"+49 6825/2790",
    "sg:postcode":"66589",
    "sg:province":"Saarland",
    "wof:name":"Gro\u00df",
    "wof:placetype":"venue"
},
  "geometry": {"coordinates":[7.08055,49.366459],"type":"Point"}
}