{
  "type": "Feature",
  "properties": {
    "iso:country":"DE",
    "sg:address":"Dechbettener Str. 18",
    "sg:city":"Regensburg",
    "sg:phone":"+49 941/23924",
    "sg:postcode":"93049",
    "sg:province":"Bayern",
    "wof:name":"Marianne Listl",
    "wof:placetype":"venue"
},
  "geometry": {"coordinates":[12.081629,49.016762],"type":"Point"}
}