{
  "type": "Feature",
  "properties": {
    "iso:country":"DE",
    "sg:address":"Kantstr. 11",
    "sg:city":"Trier",
    "sg:phone":"+49 651/85740",
    "sg:postcode":"54294",
    "sg:province":"Rheinland-Pfalz",
    "wof:name":"Ruth Ferring",
    "wof:placetype":"venue"
},
  "geometry": {"coordinates":[6.580269,49.720322],"type":"Point"}
}