{
  "type": "Feature",
  "properties": {
    "iso:country":"DE",
    "sg:address":"Deichweg 16",
    "sg:city":"Kienitz",
    "sg:postcode":"15324",
    "sg:province":"Brandenburg",
    "wof:name":"Wasserstra\u00dfenbetrieb Und- Unterhaltung Eberswalde",
    "wof:placetype":"venue"
},
  "geometry": {"coordinates":[14.440914,52.675304],"type":"Point"}
}