{
  "type": "Feature",
  "properties": {
    "iso:country":"DE",
    "sg:address":"Kornstr. 63",
    "sg:city":"Krefeld",
    "sg:phone":"+49 2151/779338",
    "sg:postcode":"47798",
    "sg:province":"Nordrhein-Westfalen",
    "wof:name":"H. Klinkhammer",
    "wof:placetype":"venue"
},
  "geometry": {"coordinates":[6.5503540039,51.3305435181],"type":"Point"}
}