{
  "type": "Feature",
  "properties": {
    "iso:country":"DE",
    "sg:address":"Z\u00f6llinplatz 6",
    "sg:city":"Badenweiler",
    "sg:phone":"+49 7632/5317",
    "sg:postcode":"79410",
    "sg:province":"Baden-W\u00fcrttemberg",
    "wof:name":"Fritz Gmelin",
    "wof:placetype":"venue"
},
  "geometry": {"coordinates":[7.6776652336,47.8028793335],"type":"Point"}
}