{
  "type": "Feature",
  "properties": {
    "iso:country":"DE",
    "sg:address":"Finkenweg 24",
    "sg:city":"Elsdorf",
    "sg:phone":"+49 2271/55331",
    "sg:postcode":"50189",
    "sg:province":"Nordrhein-Westfalen",
    "wof:name":"B. M\u00fcnstermann Rechtsanwalt",
    "wof:placetype":"venue"
},
  "geometry": {"coordinates":[6.5806341171,50.9379997253],"type":"Point"}
}