{
  "type": "Feature",
  "properties": {
    "iso:country":"DE",
    "sg:address":"Stettiner Str. 87",
    "sg:city":"Mannheim",
    "sg:phone":"+49 621/781703",
    "sg:postcode":"68307",
    "sg:province":"Baden-W\u00fcrttemberg",
    "wof:name":"Ernst Stein",
    "wof:placetype":"venue"
},
  "geometry": {"coordinates":[8.469428,49.544731],"type":"Point"}
}