{
  "type": "Feature",
  "properties": {
    "iso:country":"DE",
    "sg:address":"Auf der Worth 28",
    "sg:city":"Dissen",
    "sg:phone":"+49 5421/94690",
    "sg:postcode":"49201",
    "sg:province":"Niedersachsen",
    "wof:name":"Wolfgang T\u00f6nnies Und Else Friedl",
    "wof:placetype":"venue"
},
  "geometry": {"coordinates":[8.2015237808,52.1105384827],"type":"Point"}
}