{
  "type": "Feature",
  "properties": {
    "iso:country":"DE",
    "sg:address":"Ramskamp 47",
    "sg:city":"Elmshorn",
    "sg:phone":"+49 4121/437445",
    "sg:postcode":"25337",
    "sg:province":"Schleswig-Holstein",
    "wof:name":"Weimann & Steinke Ladenbau Gmbh",
    "wof:placetype":"venue"
},
  "geometry": {"coordinates":[9.6895570755,53.742061615],"type":"Point"}
}