{
  "type": "Feature",
  "properties": {
    "iso:country":"DE",
    "sg:address":"Bahnhofstr. 11",
    "sg:city":"Koblenz",
    "sg:postcode":"56068",
    "sg:province":"Rheinland-Pfalz",
    "wof:name":"Vcm Venture-capital Mittelrhein Unternehmens-",
    "wof:placetype":"venue"
},
  "geometry": {"coordinates":[7.591567,50.354347],"type":"Point"}
}