{
  "type": "Feature",
  "properties": {
    "iso:country":"DE",
    "sg:address":"Budapester Str. 40",
    "sg:city":"Hamburg",
    "sg:phone":"+49 40/31979985",
    "sg:postcode":"20359",
    "sg:province":"Hamburg",
    "wof:name":"Hanno Kreiselmaier Rechtsanwalt",
    "wof:placetype":"venue"
},
  "geometry": {"coordinates":[9.9645462036,53.5545196533],"type":"Point"}
}