{
  "type": "Feature",
  "properties": {
    "iso:country":"DE",
    "sg:address":"Rebgutstr. 80",
    "sg:city":"Lauda-K\u00f6nigshofen",
    "sg:phone":"+49 9343/3193",
    "sg:postcode":"97922",
    "sg:province":"Baden-W\u00fcrttemberg",
    "wof:name":"Staatliches Weingut Lauda Inh. Werner V\u00f6gtlin",
    "wof:placetype":"venue"
},
  "geometry": {"coordinates":[9.6892719269,49.5683708191],"type":"Point"}
}