{
  "type": "Feature",
  "properties": {
    "iso:country":"DE",
    "sg:address":"Dorfstr. 24",
    "sg:city":"Niederdorf",
    "sg:phone":"+49 37296/3386",
    "sg:postcode":"09366",
    "sg:province":"Sachsen",
    "wof:name":"Gottfried Busch",
    "wof:placetype":"venue"
},
  "geometry": {"coordinates":[12.788666,50.725121],"type":"Point"}
}