{
  "type": "Feature",
  "properties": {
    "iso:country":"DE",
    "sg:address":"M\u00fchlenstr. 1",
    "sg:city":"Wassenberg",
    "sg:phone":"+49 2432/2173",
    "sg:postcode":"41849",
    "sg:province":"Nordrhein-Westfalen",
    "wof:name":"Kath. Pfarramt St. Lambertus",
    "wof:placetype":"venue"
},
  "geometry": {"coordinates":[6.1521830559,51.1132888794],"type":"Point"}
}