{
  "type": "Feature",
  "properties": {
    "iso:country":"DE",
    "sg:address":"Heinrich-B\u00f6ll-Str. 42",
    "sg:city":"T\u00f6nisvorst",
    "sg:phone":"+49 2151/794036",
    "sg:postcode":"47918",
    "sg:province":"Nordrhein-Westfalen",
    "wof:name":"Btl Fliesen Gmbh",
    "wof:placetype":"venue"
},
  "geometry": {"coordinates":[6.4758591652,51.3265647888],"type":"Point"}
}