{
  "type": "Feature",
  "properties": {
    "iso:country":"DE",
    "sg:address":"Stresemannstr. 110",
    "sg:city":"Hamburg",
    "sg:phone":"+49 40/4301050",
    "sg:postcode":"22769",
    "sg:province":"Hamburg",
    "wof:name":"Electro Medical Ger\u00e4tebau Gmbh",
    "wof:placetype":"venue"
},
  "geometry": {"coordinates":[9.955655,53.56102],"type":"Point"}
}