{
  "type": "Feature",
  "properties": {
    "iso:country":"DE",
    "sg:address":"Hauptstr. 44",
    "sg:city":"B\u00f6nnigheim",
    "sg:phone":"+49 7143/21010",
    "sg:postcode":"74357",
    "sg:province":"Baden-W\u00fcrttemberg",
    "wof:name":"Fritz Seybold",
    "wof:placetype":"venue"
},
  "geometry": {"coordinates":[9.093457222,49.0410995483],"type":"Point"}
}