{
  "type": "Feature",
  "properties": {
    "iso:country":"DE",
    "sg:address":"Friedrich-Ebert-Damm 160",
    "sg:city":"Hamburg",
    "sg:phone":"+49 40/6961071",
    "sg:postcode":"22047",
    "sg:province":"Hamburg",
    "wof:name":"S. Mi\u00dffeldt Anlageberater",
    "wof:placetype":"venue"
},
  "geometry": {"coordinates":[10.0993623734,53.5888938904],"type":"Point"}
}