{
  "type": "Feature",
  "properties": {
    "iso:country":"DE",
    "sg:address":"Bahnstr. 1a",
    "sg:city":"Wipperf\u00fcrth",
    "sg:phone":"+49 2267/2092",
    "sg:postcode":"51688",
    "sg:province":"Nordrhein-Westfalen",
    "wof:name":"H\u00f6ne & Biedermann",
    "wof:placetype":"venue"
},
  "geometry": {"coordinates":[7.392956,51.116329],"type":"Point"}
}