{
  "type": "Feature",
  "properties": {
    "iso:country":"DE",
    "sg:address":"Am Friedhof 4",
    "sg:city":"Tostedt",
    "sg:phone":"+49 4182/5073",
    "sg:postcode":"21255",
    "sg:province":"Niedersachsen",
    "wof:name":"M.-l. Und H. Senkbeil",
    "wof:placetype":"venue"
},
  "geometry": {"coordinates":[9.70632,53.284145],"type":"Point"}
}