{
  "type": "Feature",
  "properties": {
    "iso:country":"DE",
    "sg:address":"Heideweg 3",
    "sg:city":"Bad Honnef",
    "sg:phone":"+49 2224/97340",
    "sg:postcode":"53604",
    "sg:province":"Nordrhein-Westfalen",
    "wof:name":"Iso-speed Gmbh",
    "wof:placetype":"venue"
},
  "geometry": {"coordinates":[7.32168,50.651421],"type":"Point"}
}