{
  "type": "Feature",
  "properties": {
    "iso:country":"DE",
    "sg:address":"Maximilian-Kolbe-Str. 60",
    "sg:city":"Steinfurt",
    "sg:phone":"+49 2552/98160",
    "sg:postcode":"48565",
    "sg:province":"Nordrhein-Westfalen",
    "wof:name":"Tro Tec",
    "wof:placetype":"venue"
},
  "geometry": {"coordinates":[7.3928132057,52.1146697998],"type":"Point"}
}