{
  "type": "Feature",
  "properties": {
    "iso:country":"DE",
    "sg:address":"Zum Kirchplatz",
    "sg:city":"Rottenburg",
    "sg:phone":"+49 8781/401",
    "sg:postcode":"84056",
    "sg:province":"Bayern",
    "wof:name":"Georg Pritsch Gmbh & Co. Kg",
    "wof:placetype":"venue"
},
  "geometry": {"coordinates":[12.0892734528,48.7416419983],"type":"Point"}
}