{
  "type": "Feature",
  "properties": {
    "iso:country":"DE",
    "sg:address":"Halbergstr. 3",
    "sg:city":"Saarbr\u00fccken",
    "sg:phone":"+49 681/66330",
    "sg:postcode":"66121",
    "sg:province":"Saarland",
    "wof:name":"Ilf Institut F\u00fcr Lehrer- Fort Und Weiterbildung",
    "wof:placetype":"venue"
},
  "geometry": {"coordinates":[7.006425,49.232491],"type":"Point"}
}