{
  "type": "Feature",
  "properties": {
    "iso:country":"DE",
    "sg:address":"Lorenz-Hutschenreuther-Str. 85",
    "sg:city":"Selb",
    "sg:phone":"+49 9287/99530",
    "sg:postcode":"95100",
    "sg:province":"Bayern",
    "wof:name":"Toom-baumarkt",
    "wof:placetype":"venue"
},
  "geometry": {"coordinates":[12.1435098648,50.1688194275],"type":"Point"}
}