{
  "type": "Feature",
  "properties": {
    "iso:country":"DE",
    "sg:address":"Bahnhofstr. 4",
    "sg:city":"M\u00fchlhausen",
    "sg:phone":"+49 36014/47688",
    "sg:postcode":"99974",
    "sg:province":"Th\u00fcringen",
    "wof:name":"G\u00fcnther H\u00fchnermann",
    "wof:placetype":"venue"
},
  "geometry": {"coordinates":[8.730605,49.248093],"type":"Point"}
}