{
  "type": "Feature",
  "properties": {
    "iso:country":"DE",
    "sg:address":"Industriestr 9",
    "sg:city":"R\u00f6ttenbach",
    "sg:phone":"+49 9172/7901",
    "sg:postcode":"91187",
    "sg:province":"Bayern",
    "wof:name":"Balazs",
    "wof:placetype":"venue"
},
  "geometry": {"coordinates":[11.0351867676,49.1565589905],"type":"Point"}
}