{
  "type": "Feature",
  "properties": {
    "iso:country":"DE",
    "sg:address":"B\u00fcrgerm\u00fchlenweg 11",
    "sg:city":"Waiblingen",
    "sg:phone":"+49 7151/956858",
    "sg:postcode":"71332",
    "sg:province":"Baden-W\u00fcrttemberg",
    "wof:name":"Arbeiterwohlfahrt Im Remstal Gmbh",
    "wof:placetype":"venue"
},
  "geometry": {"coordinates":[9.31642,48.83086],"type":"Point"}
}