{
  "type": "Feature",
  "properties": {
    "iso:country":"DE",
    "sg:address":"Zeppelinstr. 1",
    "sg:city":"M\u00fclheim",
    "sg:postcode":"45470",
    "sg:province":"Nordrhein-Westfalen",
    "wof:name":"P.b.k.s. Marion Land E. K.",
    "wof:placetype":"venue"
},
  "geometry": {"coordinates":[6.899678,51.418648],"type":"Point"}
}