{
  "type": "Feature",
  "properties": {
    "iso:country":"DE",
    "sg:address":"Emil-Nolde-Str. 8",
    "sg:city":"Viernheim",
    "sg:phone":"+49 6204/740726",
    "sg:postcode":"68519",
    "sg:province":"Hessen",
    "wof:name":"Martina Bartzsch Rechtsanw\u00e4ltin",
    "wof:placetype":"venue"
},
  "geometry": {"coordinates":[8.5671167374,49.5440177917],"type":"Point"}
}