{
  "type": "Feature",
  "properties": {
    "iso:country":"DE",
    "sg:address":"Kaiserstr. 50",
    "sg:city":"W\u00fcrselen",
    "sg:phone":"+49 2405/2526",
    "sg:postcode":"52146",
    "sg:province":"Nordrhein-Westfalen",
    "wof:name":"Cs Foto Creativ",
    "wof:placetype":"venue"
},
  "geometry": {"coordinates":[6.1309871674,50.8209686279],"type":"Point"}
}