{
  "type": "Feature",
  "properties": {
    "iso:country":"DE",
    "sg:address":"Ahlhorner Str. 80",
    "sg:city":"Wildeshausen",
    "sg:phone":"+49 4431/930341",
    "sg:postcode":"27793",
    "sg:province":"Niedersachsen",
    "wof:name":"Autofit Venzke",
    "wof:placetype":"venue"
},
  "geometry": {"coordinates":[8.4158687592,52.8982009888],"type":"Point"}
}