{
  "type": "Feature",
  "properties": {
    "iso:country":"DE",
    "sg:address":"K\u00f6lner Str. 2 a",
    "sg:city":"J\u00fcchen",
    "sg:phone":"+49 2165/7009",
    "sg:postcode":"41363",
    "sg:province":"Nordrhein-Westfalen",
    "wof:name":"G\u00fcnther Sch\u00fctze Steuerberater",
    "wof:placetype":"venue"
},
  "geometry": {"coordinates":[6.5048480034,51.1010437012],"type":"Point"}
}