{
  "type": "Feature",
  "properties": {
    "iso:country":"DE",
    "sg:address":"Heinrich-Br\u00fcning-Str. 8",
    "sg:city":"M\u00fcnster",
    "sg:phone":"+49 4925/1414660",
    "sg:postcode":"48143",
    "sg:province":"Nordrhein-Westfalen",
    "wof:name":"Skipperservice Yachting Gmbh",
    "wof:placetype":"venue"
},
  "geometry": {"coordinates":[7.6294870377,51.9609718323],"type":"Point"}
}