{
  "type": "Feature",
  "properties": {
    "iso:country":"DE",
    "sg:address":"Schlei\u00dfheimer Str. 121",
    "sg:city":"M\u00fcnchen",
    "sg:phone":"+49 89/30778395",
    "sg:postcode":"80797",
    "sg:province":"Bayern",
    "wof:name":"Taverne Kreta",
    "wof:placetype":"venue"
},
  "geometry": {"coordinates":[11.5633831024,48.1617660522],"type":"Point"}
}