{
  "type": "Feature",
  "properties": {
    "iso:country":"DE",
    "sg:address":"Homberger Str. 18",
    "sg:city":"Moers",
    "sg:phone":"+49 2841/90489",
    "sg:postcode":"47441",
    "sg:province":"Nordrhein-Westfalen",
    "wof:name":"Extra",
    "wof:placetype":"venue"
},
  "geometry": {"coordinates":[6.6309518814,51.4507293701],"type":"Point"}
}