{
  "type": "Feature",
  "properties": {
    "iso:country":"DE",
    "sg:address":"Dr.-Simoneit-Str. 40",
    "sg:city":"M\u00fclheim",
    "sg:phone":"+49 208/71269",
    "sg:postcode":"45473",
    "sg:province":"Nordrhein-Westfalen",
    "wof:name":"Gantenberg",
    "wof:placetype":"venue"
},
  "geometry": {"coordinates":[6.891364,51.450623],"type":"Point"}
}