{
  "type": "Feature",
  "properties": {
    "iso:country":"DE",
    "sg:address":"Max-Joseph-Weg 16",
    "sg:city":"Hallbergmoos",
    "sg:phone":"+49 811/95344",
    "sg:postcode":"85399",
    "sg:province":"Bayern",
    "wof:name":"P. Sp\u00e4th",
    "wof:placetype":"venue"
},
  "geometry": {"coordinates":[11.739906,48.318024],"type":"Point"}
}