{
  "type": "Feature",
  "properties": {
    "iso:country":"DE",
    "sg:address":"Hauptstr. 13",
    "sg:city":"Esch",
    "sg:phone":"+49 6597/1404",
    "sg:postcode":"54585",
    "sg:province":"Rheinland-Pfalz",
    "wof:name":"Bierst\u00fcbchen",
    "wof:placetype":"venue"
},
  "geometry": {"coordinates":[6.6117911339,50.3589057922],"type":"Point"}
}