{
  "type": "Feature",
  "properties": {
    "iso:country":"DE",
    "sg:address":"Hegelstr. 26 Und 28d",
    "sg:city":"Bamberg",
    "sg:phone":"+49 951/935430",
    "sg:postcode":"96052",
    "sg:province":"Bayern",
    "wof:name":"Druckerei U Verlag K Urlaub Gmbh",
    "wof:placetype":"venue"
},
  "geometry": {"coordinates":[10.8873100281,49.9118690491],"type":"Point"}
}