{
  "type": "Feature",
  "properties": {
    "iso:country":"DE",
    "sg:address":"Arnoldstr. 15",
    "sg:city":"M\u00fcnchen",
    "sg:postcode":"80999",
    "sg:province":"Bayern",
    "wof:name":"Empress Verlag-depot Inh. J. R\u00f6ll",
    "wof:placetype":"venue"
},
  "geometry": {"coordinates":[11.4528751373,48.2024154663],"type":"Point"}
}