{
  "type": "Feature",
  "properties": {
    "iso:country":"DE",
    "sg:address":"Obernstr. 13",
    "sg:city":"Stadthagen",
    "sg:phone":"+49 5721/3317",
    "sg:postcode":"31655",
    "sg:province":"Niedersachsen",
    "wof:name":"Kaisers Tengelmann Ag",
    "wof:placetype":"venue"
},
  "geometry": {"coordinates":[9.2052984238,52.3224563599],"type":"Point"}
}