{
  "type": "Feature",
  "properties": {
    "iso:country":"DE",
    "sg:address":"Rappach 56a",
    "sg:city":"M\u00f6mbris",
    "sg:phone":"+49 6029/995702",
    "sg:postcode":"63776",
    "sg:province":"Bayern",
    "wof:name":"Cyra Cosmetics Gmbh",
    "wof:placetype":"venue"
},
  "geometry": {"coordinates":[9.141397,50.065239],"type":"Point"}
}