{
  "type": "Feature",
  "properties": {
    "iso:country":"DE",
    "sg:address":"Ludwig-Erhard-Str 16",
    "sg:city":"Neufahrn",
    "sg:phone":"+49 8165/61710",
    "sg:postcode":"85375",
    "sg:province":"Bayern",
    "wof:name":"Aeromaritime Systembau Gmbh",
    "wof:placetype":"venue"
},
  "geometry": {"coordinates":[11.6476211548,48.3115348816],"type":"Point"}
}