{
  "type": "Feature",
  "properties": {
    "iso:country":"DE",
    "sg:address":"Zur Kaffeeh\u00f6tt 106",
    "sg:city":"Duisburg",
    "sg:phone":"+49 203/762447",
    "sg:postcode":"47269",
    "sg:province":"Nordrhein-Westfalen",
    "wof:name":"Detlef R\u00fcbler",
    "wof:placetype":"venue"
},
  "geometry": {"coordinates":[6.773905,51.34679],"type":"Point"}
}