{
  "type": "Feature",
  "properties": {
    "iso:country":"DE",
    "sg:address":"Rossertstr. 32",
    "sg:city":"Kriftel",
    "sg:phone":"+49 6192/42297",
    "sg:postcode":"65830",
    "sg:province":"Hessen",
    "wof:name":"G. Ziegler",
    "wof:placetype":"venue"
},
  "geometry": {"coordinates":[8.4689350128,50.087097168],"type":"Point"}
}