{
  "type": "Feature",
  "properties": {
    "iso:country":"DE",
    "sg:address":"Leibnizstr. 26",
    "sg:city":"Stuttgart",
    "sg:phone":"+49 711/6366453",
    "sg:postcode":"70193",
    "sg:province":"Baden-W\u00fcrttemberg",
    "wof:name":"Klaus Sommerrock Rechtsanwalt",
    "wof:placetype":"venue"
},
  "geometry": {"coordinates":[9.1459197998,48.7819862366],"type":"Point"}
}