{
  "type": "Feature",
  "properties": {
    "iso:country":"DE",
    "sg:address":"Emdener Str. 42",
    "sg:city":"Berlin",
    "sg:phone":"+49 30/39879151",
    "sg:postcode":"10551",
    "sg:province":"Berlin",
    "wof:name":"Eurasiacom E. K.",
    "wof:placetype":"venue"
},
  "geometry": {"coordinates":[13.3340768814,52.5310974121],"type":"Point"}
}