{
  "type": "Feature",
  "properties": {
    "iso:country":"DE",
    "sg:address":"Hohenhorststr. 1 b",
    "sg:city":"L\u00fcneburg",
    "sg:postcode":"21337",
    "sg:province":"Niedersachsen",
    "wof:name":"Krampitz Tanksystem Gmbh",
    "wof:placetype":"venue"
},
  "geometry": {"coordinates":[10.4756202698,53.2456283569],"type":"Point"}
}