{
  "type": "Feature",
  "properties": {
    "iso:country":"DE",
    "sg:address":"Leipziger Str. 7",
    "sg:city":"Sulingen",
    "sg:phone":"+49 4271/93460",
    "sg:postcode":"27232",
    "sg:province":"Niedersachsen",
    "wof:name":"Biesterfeld Scheibler Linssen Gmbh & Co.",
    "wof:placetype":"venue"
},
  "geometry": {"coordinates":[8.838083,52.686665],"type":"Point"}
}