{
  "type": "Feature",
  "properties": {
    "iso:country":"DE",
    "sg:address":"Otto-Brenner-Str. 112",
    "sg:city":"Bielefeld",
    "sg:phone":"+49 521/299080",
    "sg:postcode":"33607",
    "sg:province":"Nordrhein-Westfalen",
    "wof:name":"Pro Active Computer-service Gmbh",
    "wof:placetype":"venue"
},
  "geometry": {"coordinates":[8.5656480789,52.0148925781],"type":"Point"}
}