{
  "type": "Feature",
  "properties": {
    "iso:country":"DE",
    "sg:address":"Hochstr. 8",
    "sg:city":"Bochum",
    "sg:phone":"+49 2327/10053",
    "sg:postcode":"44866",
    "sg:province":"Nordrhein-Westfalen",
    "wof:name":"Kss Steuerberatungs- Gesellschaft Mbh",
    "wof:placetype":"venue"
},
  "geometry": {"coordinates":[7.1378622055,51.480255127],"type":"Point"}
}