{
  "type": "Feature",
  "properties": {
    "iso:country":"DE",
    "sg:address":"Werkstr. 8",
    "sg:city":"Dortmund",
    "sg:phone":"+49 2304/8422",
    "sg:postcode":"44267",
    "sg:province":"Nordrhein-Westfalen",
    "wof:name":"Rsb Ruhrtal-stahl- Und Beh\u00e4lterbau Erich M\u00fcller Gmbh",
    "wof:placetype":"venue"
},
  "geometry": {"coordinates":[7.534959,51.443863],"type":"Point"}
}