{
  "type": "Feature",
  "properties": {
    "iso:country":"DE",
    "sg:address":"Gr\u00fcner Hof 3",
    "sg:city":"Friesoythe",
    "sg:phone":"+49 4491/718",
    "sg:postcode":"26169",
    "sg:province":"Niedersachsen",
    "wof:name":"Esso Deutschland Gmbh",
    "wof:placetype":"venue"
},
  "geometry": {"coordinates":[7.8596529961,53.0206604004],"type":"Point"}
}