{
  "type": "Feature",
  "properties": {
    "iso:country":"DE",
    "sg:address":"Zeppelinallee 95",
    "sg:city":"Frankfurt",
    "sg:phone":"+49 69/701542",
    "sg:postcode":"60487",
    "sg:province":"Hessen",
    "wof:name":"Hans Kapp Immobilien- Und Verwaltungs Gmbh",
    "wof:placetype":"venue"
},
  "geometry": {"coordinates":[8.6467552185,50.1280555725],"type":"Point"}
}