{
  "type": "Feature",
  "properties": {
    "iso:country":"DE",
    "sg:address":"Berliner Str. 62",
    "sg:city":"Lohfelden",
    "sg:phone":"+49 561/951680",
    "sg:postcode":"34253",
    "sg:province":"Hessen",
    "wof:name":"Schelkmann Pasquay Und Gr\u00fcnder Rechtsanw\u00e4lte Und Notare",
    "wof:placetype":"venue"
},
  "geometry": {"coordinates":[9.5523500443,51.2706871033],"type":"Point"}
}