{
  "type": "Feature",
  "properties": {
    "iso:country":"DE",
    "sg:address":"Selxer Str. 1",
    "sg:city":"Aerzen",
    "sg:phone":"+49 5154/670",
    "sg:postcode":"31855",
    "sg:province":"Niedersachsen",
    "wof:name":"Lvm Versicherung Siever",
    "wof:placetype":"venue"
},
  "geometry": {"coordinates":[9.2867670059,52.0586242676],"type":"Point"}
}