{
  "type": "Feature",
  "properties": {
    "iso:country":"DE",
    "sg:address":"Am Seegraben 20",
    "sg:city":"Gro\u00df Gaglow",
    "sg:postcode":"03058",
    "sg:province":"Brandenburg",
    "wof:name":"Orthop\u00e4die- Und Reha-team Zimmermann Gmbh",
    "wof:placetype":"venue"
},
  "geometry": {"coordinates":[14.315911293,51.7177505493],"type":"Point"}
}