{
  "type": "Feature",
  "properties": {
    "iso:country":"DE",
    "sg:address":"Bahnhofstr. 60",
    "sg:city":"Weyhe",
    "sg:phone":"+49 4203/789315",
    "sg:postcode":"28844",
    "sg:province":"Niedersachsen",
    "wof:name":"Senioren Wohnpark Weser Ggmbh",
    "wof:placetype":"venue"
},
  "geometry": {"coordinates":[8.859717,52.984234],"type":"Point"}
}