{
  "type": "Feature",
  "properties": {
    "iso:country":"DE",
    "sg:address":"Hinter der Kapelle 2",
    "sg:city":"Witterda",
    "sg:phone":"+49 36201/50073",
    "sg:postcode":"99189",
    "sg:province":"Th\u00fcringen",
    "wof:name":"Strumpf-riese Strumpfwarengro\u00dfhandel",
    "wof:placetype":"venue"
},
  "geometry": {"coordinates":[10.8947,51.037842],"type":"Point"}
}