{
  "type": "Feature",
  "properties": {
    "iso:country":"DE",
    "sg:address":"Wendelsteinweg 1",
    "sg:city":"Kissing",
    "sg:phone":"+49 8233/20744",
    "sg:postcode":"86438",
    "sg:province":"Bayern",
    "wof:name":"Rolf Scheibenbogen Masseur",
    "wof:placetype":"venue"
},
  "geometry": {"coordinates":[10.970494,48.298389],"type":"Point"}
}