{
  "type": "Feature",
  "properties": {
    "iso:country":"DE",
    "sg:address":"Alemannenstr. 10",
    "sg:city":"Trier",
    "sg:phone":"+49 651/67154",
    "sg:postcode":"54293",
    "sg:province":"Rheinland-Pfalz",
    "wof:name":"Friedrich Bisplinghof Ingenieur Grad Hochbau",
    "wof:placetype":"venue"
},
  "geometry": {"coordinates":[6.6992211342,49.8163604736],"type":"Point"}
}