{
  "type": "Feature",
  "properties": {
    "iso:country":"DE",
    "sg:address":"Rheinstr. 107",
    "sg:city":"Ettlingen",
    "sg:phone":"+49 7243/30254",
    "sg:postcode":"76275",
    "sg:province":"Baden-W\u00fcrttemberg",
    "wof:name":"A. Strahm",
    "wof:placetype":"venue"
},
  "geometry": {"coordinates":[8.3956861496,48.9461021423],"type":"Point"}
}