{
  "type": "Feature",
  "properties": {
    "iso:country":"DE",
    "sg:address":"Mainauweg 8",
    "sg:city":"Solingen",
    "sg:phone":"+49 212/61655",
    "sg:postcode":"42699",
    "sg:province":"Nordrhein-Westfalen",
    "wof:name":"Alois Jechorek",
    "wof:placetype":"venue"
},
  "geometry": {"coordinates":[6.995077,51.127941],"type":"Point"}
}