{
  "type": "Feature",
  "properties": {
    "iso:country":"DE",
    "sg:address":"Inselstr. 16",
    "sg:city":"Rheinm\u00fcnster",
    "sg:phone":"+49 7227/2413",
    "sg:postcode":"77836",
    "sg:province":"Baden-W\u00fcrttemberg",
    "wof:name":"Alfred Weisbrod",
    "wof:placetype":"venue"
},
  "geometry": {"coordinates":[8.04356,48.745789],"type":"Point"}
}