{
  "type": "Feature",
  "properties": {
    "iso:country":"DE",
    "sg:address":"Okerstr. 7",
    "sg:city":"Wolfenb\u00fcttel",
    "sg:phone":"+49 5331/27802",
    "sg:postcode":"38300",
    "sg:province":"Niedersachsen",
    "wof:name":"Der Weinladen",
    "wof:placetype":"venue"
},
  "geometry": {"coordinates":[10.5386152267,52.1635704041],"type":"Point"}
}