{
  "type": "Feature",
  "properties": {
    "iso:country":"DE",
    "sg:address":"Am Brenschelt 3",
    "sg:city":"Diemelsee",
    "sg:phone":"+49 5633/1059",
    "sg:postcode":"34519",
    "sg:province":"Hessen",
    "wof:name":"Erich Gottschalk",
    "wof:placetype":"venue"
},
  "geometry": {"coordinates":[8.696992,51.332176],"type":"Point"}
}