{
  "type": "Feature",
  "properties": {
    "iso:country":"DE",
    "sg:address":"Ziegelheide 5",
    "sg:city":"Kempen",
    "sg:postcode":"47906",
    "sg:province":"Nordrhein-Westfalen",
    "wof:name":"P. Coenen",
    "wof:placetype":"venue"
},
  "geometry": {"coordinates":[6.403226,51.364067],"type":"Point"}
}