{
  "type": "Feature",
  "properties": {
    "iso:country":"DE",
    "sg:address":"Pirolpfad 5",
    "sg:city":"R\u00f6dermark",
    "sg:phone":"+49 6074/861720",
    "sg:postcode":"63322",
    "sg:province":"Hessen",
    "wof:name":"Ernst-rudolf V\u00f6lger Rechtsanwalt",
    "wof:placetype":"venue"
},
  "geometry": {"coordinates":[8.7861146927,49.9716415405],"type":"Point"}
}