{
  "type": "Feature",
  "properties": {
    "iso:country":"DE",
    "sg:address":"Berthelsdorfer Str.54",
    "sg:city":"Freiberg",
    "sg:postcode":"09599",
    "sg:province":"Sachsen",
    "wof:name":"Complex Cole",
    "wof:placetype":"venue"
},
  "geometry": {"coordinates":[13.349075,50.909508],"type":"Point"}
}