{
  "type": "Feature",
  "properties": {
    "iso:country":"DE",
    "sg:address":"Tempelhofer Damm 119",
    "sg:city":"Berlin",
    "sg:phone":"+49 30/75774680",
    "sg:postcode":"12099",
    "sg:province":"Berlin",
    "wof:name":"Bad Shop - Luxus Bad, Traumbad, Exklusive Badplanung, Design",
    "wof:placetype":"venue"
},
  "geometry": {"coordinates":[13.3859128952,52.4691162109],"type":"Point"}
}