{
  "type": "Feature",
  "properties": {
    "iso:country":"DE",
    "sg:address":"M\u00f6nckebergstr. 10",
    "sg:city":"Hamburg",
    "sg:phone":"+49 40/3256720",
    "sg:postcode":"20095",
    "sg:province":"Hamburg",
    "wof:name":"Ask International Market Research Aski Gmbh",
    "wof:placetype":"venue"
},
  "geometry": {"coordinates":[10.0026826859,53.5515174866],"type":"Point"}
}