{
  "type": "Feature",
  "properties": {
    "iso:country":"DE",
    "sg:address":"Lutherplatz 6",
    "sg:city":"Landsberg",
    "sg:phone":"+49 34602/2890",
    "sg:postcode":"06188",
    "sg:province":"Sachsen-Anhalt",
    "wof:name":"T & L R\u00f6der & Partner Wirtschafts- U. Steuerbera-",
    "wof:placetype":"venue"
},
  "geometry": {"coordinates":[12.1597290039,51.5250930786],"type":"Point"}
}