{
  "type": "Feature",
  "properties": {
    "iso:country":"DE",
    "sg:address":"Mathildenstr. 4",
    "sg:city":"Planegg",
    "sg:phone":"+49 89/8598487",
    "sg:postcode":"82152",
    "sg:province":"Bayern",
    "wof:name":"Gottlieb Gum Gmbh & Co. Bauunternehmung Kg",
    "wof:placetype":"venue"
},
  "geometry": {"coordinates":[11.417807,48.104908],"type":"Point"}
}