{
  "type": "Feature",
  "properties": {
    "iso:country":"DE",
    "sg:address":"Othmarstr. 8 a",
    "sg:city":"Geseke",
    "sg:phone":"+49 2942/8402",
    "sg:postcode":"59590",
    "sg:province":"Nordrhein-Westfalen",
    "wof:name":"Dieter Kl\u00f6ppel",
    "wof:placetype":"venue"
},
  "geometry": {"coordinates":[8.510931015,51.6355171204],"type":"Point"}
}