{
  "type": "Feature",
  "properties": {
    "iso:country":"DE",
    "sg:address":"Lindgesfeld 14",
    "sg:city":"Solingen",
    "sg:phone":"+49 212/262300",
    "sg:postcode":"42653",
    "sg:province":"Nordrhein-Westfalen",
    "wof:name":"Dames Kanttechnik Gmbh",
    "wof:placetype":"venue"
},
  "geometry": {"coordinates":[7.081177,51.203266],"type":"Point"}
}