{
  "type": "Feature",
  "properties": {
    "iso:country":"DE",
    "sg:address":"Seemeweg 28",
    "sg:city":"Sinntal",
    "sg:phone":"+49 6664/6731",
    "sg:postcode":"36391",
    "sg:province":"Hessen",
    "wof:name":"R. Ackmann",
    "wof:placetype":"venue"
},
  "geometry": {"coordinates":[9.6275672913,50.3169250488],"type":"Point"}
}