{
  "type": "Feature",
  "properties": {
    "iso:country":"DE",
    "sg:address":"Hauptstr. 24",
    "sg:city":"Himbergen",
    "sg:phone":"+49 5828/495",
    "sg:postcode":"29584",
    "sg:province":"Niedersachsen",
    "wof:name":"Helmut Schulz Ingenieur",
    "wof:placetype":"venue"
},
  "geometry": {"coordinates":[10.7025327682,53.1245231628],"type":"Point"}
}