{
  "type": "Feature",
  "properties": {
    "iso:country":"DE",
    "sg:address":"Blumenthalstr. 66",
    "sg:city":"Duisburg",
    "sg:phone":"+49 203/330359",
    "sg:postcode":"47058",
    "sg:province":"Nordrhein-Westfalen",
    "wof:name":"Windgassen Gmbh & Co. Kg",
    "wof:placetype":"venue"
},
  "geometry": {"coordinates":[6.78769,51.438614],"type":"Point"}
}