{
  "type": "Feature",
  "properties": {
    "iso:country":"DE",
    "sg:address":"Lortzingstr. 40",
    "sg:city":"Unna",
    "sg:phone":"+49 2303/870540",
    "sg:postcode":"59423",
    "sg:province":"Nordrhein-Westfalen",
    "wof:name":"Ed-elementbau Gmbh",
    "wof:placetype":"venue"
},
  "geometry": {"coordinates":[7.679227829,51.5378227234],"type":"Point"}
}