{
  "type": "Feature",
  "properties": {
    "iso:country":"DE",
    "sg:address":"Hatzberg 2",
    "sg:city":"Hamburg",
    "sg:postcode":"22527",
    "sg:province":"Hamburg",
    "wof:name":"Ggo Grundst\u00fccksges. Ottensen Mbh",
    "wof:placetype":"venue"
},
  "geometry": {"coordinates":[9.9257745743,53.6013755798],"type":"Point"}
}