{
  "type": "Feature",
  "properties": {
    "iso:country":"DE",
    "sg:address":"Mittelm\u00fchlgasse 10",
    "sg:city":"Donzdorf",
    "sg:phone":"+49 7162/29252",
    "sg:postcode":"73072",
    "sg:province":"Baden-W\u00fcrttemberg",
    "wof:name":"Erwin Maier",
    "wof:placetype":"venue"
},
  "geometry": {"coordinates":[9.8091554642,48.6870918274],"type":"Point"}
}