{
  "type": "Feature",
  "properties": {
    "iso:country":"DE",
    "sg:address":"Lohne",
    "sg:city":"Bad Sassendorf",
    "sg:phone":"+49 2921/55660",
    "sg:postcode":"59505",
    "sg:province":"Nordrhein-Westfalen",
    "wof:name":"Erwin Dohle",
    "wof:placetype":"venue"
},
  "geometry": {"coordinates":[8.1770963669,51.5860671997],"type":"Point"}
}