{
  "type": "Feature",
  "properties": {
    "iso:country":"DE",
    "sg:address":"K\u00f6nigstr. 9",
    "sg:city":"Bad Emstal",
    "sg:phone":"+49 5625/819",
    "sg:postcode":"34308",
    "sg:province":"Hessen",
    "wof:name":"Karl Meyer",
    "wof:placetype":"venue"
},
  "geometry": {"coordinates":[9.237303,51.272659],"type":"Point"}
}