{
  "type": "Feature",
  "properties": {
    "iso:country":"DE",
    "sg:address":"Lagerhausstr. 8",
    "sg:city":"Grainau",
    "sg:phone":"+49 8821/81433",
    "sg:postcode":"82491",
    "sg:province":"Bayern",
    "wof:name":"Hans-martin Neuner",
    "wof:placetype":"venue"
},
  "geometry": {"coordinates":[11.024471,47.474197],"type":"Point"}
}