{
  "type": "Feature",
  "properties": {
    "iso:country":"DE",
    "sg:address":"Neue Amberger Str. 16",
    "sg:city":"Schwarzenfeld",
    "sg:phone":"+49 9435/2101",
    "sg:postcode":"92521",
    "sg:province":"Bayern",
    "wof:name":"Josef Simbeck Rechtsanwalt",
    "wof:placetype":"venue"
},
  "geometry": {"coordinates":[12.1384992599,49.3875389099],"type":"Point"}
}