{
  "type": "Feature",
  "properties": {
    "iso:country":"DE",
    "sg:address":"Neugasse 49",
    "sg:city":"Hofheim",
    "sg:postcode":"65719",
    "sg:province":"Hessen",
    "wof:name":"Stern Lines Shipping Gmbh",
    "wof:placetype":"venue"
},
  "geometry": {"coordinates":[8.4538030624,50.0870246887],"type":"Point"}
}