{
  "type": "Feature",
  "properties": {
    "iso:country":"DE",
    "sg:address":"Nollendorfplatz 3",
    "sg:city":"Berlin",
    "sg:phone":"+49 30/2176779",
    "sg:postcode":"10777",
    "sg:province":"Berlin",
    "wof:name":"Hongwan-hanwide Gmbh",
    "wof:placetype":"venue"
},
  "geometry": {"coordinates":[13.3527870178,52.4994049072],"type":"Point"}
}