{
  "type": "Feature",
  "properties": {
    "iso:country":"DE",
    "sg:address":"Karlstr. 29",
    "sg:city":"Planegg",
    "sg:phone":"+49 89/8562052",
    "sg:postcode":"82152",
    "sg:province":"Bayern",
    "wof:name":"S & M Palaisbau Gmbh",
    "wof:placetype":"venue"
},
  "geometry": {"coordinates":[11.416513,48.113937],"type":"Point"}
}