{
  "type": "Feature",
  "properties": {
    "iso:country":"DE",
    "sg:address":"Viktoriastr. 34",
    "sg:city":"M\u00fcnchen",
    "sg:phone":"+49 89/772806",
    "sg:postcode":"80803",
    "sg:province":"Bayern",
    "wof:name":"Michael Bornschlegel Architekt",
    "wof:placetype":"venue"
},
  "geometry": {"coordinates":[11.57929,48.16637],"type":"Point"}
}