{
  "type": "Feature",
  "properties": {
    "iso:country":"DE",
    "sg:address":"Schlachthofstr. 53",
    "sg:city":"Memmingen",
    "sg:phone":"+49 8331/4490",
    "sg:postcode":"87700",
    "sg:province":"Bayern",
    "wof:name":"Bartosch Und Klier",
    "wof:placetype":"venue"
},
  "geometry": {"coordinates":[10.1846132278,47.9948234558],"type":"Point"}
}