{
  "type": "Feature",
  "properties": {
    "iso:country":"DE",
    "sg:address":"Hauptstr. 9",
    "sg:city":"Rheinau",
    "sg:phone":"+49 7844/991650",
    "sg:postcode":"77866",
    "sg:province":"Baden-W\u00fcrttemberg",
    "wof:name":"Wiga Heimtextilien Gmbh",
    "wof:placetype":"venue"
},
  "geometry": {"coordinates":[7.940036,48.664829],"type":"Point"}
}