{
  "type": "Feature",
  "properties": {
    "iso:country":"DE",
    "sg:address":"Thomasiusstr. 2a",
    "sg:city":"Leipzig",
    "sg:postcode":"04109",
    "sg:province":"Sachsen",
    "wof:name":"M\u00e4der Beteiligungs-gmbh",
    "wof:placetype":"venue"
},
  "geometry": {"coordinates":[12.364599,51.342941],"type":"Point"}
}