{
  "type": "Feature",
  "properties": {
    "iso:country":"DE",
    "sg:address":"Kaiser-Ludwig-Ring 7",
    "sg:city":"Amberg",
    "sg:phone":"+49 9621/49050",
    "sg:postcode":"92224",
    "sg:province":"Bayern",
    "wof:name":"Deutsche Bahn Ag",
    "wof:placetype":"venue"
},
  "geometry": {"coordinates":[11.8632097244,49.4464912415],"type":"Point"}
}