{
  "type": "Feature",
  "properties": {
    "iso:country":"DE",
    "sg:address":"Moltkestr. 16",
    "sg:city":"Weinheim",
    "sg:phone":"+49 6201/66406",
    "sg:postcode":"69469",
    "sg:province":"Baden-W\u00fcrttemberg",
    "wof:name":"Eva Wesner Heilpraktikerin",
    "wof:placetype":"venue"
},
  "geometry": {"coordinates":[8.6675071716,49.5493621826],"type":"Point"}
}