{
  "type": "Feature",
  "properties": {
    "iso:country":"DE",
    "sg:address":"Carl-Petersen-Str. 57",
    "sg:city":"Hamburg",
    "sg:phone":"+49 40/2543909",
    "sg:postcode":"20535",
    "sg:province":"Hamburg",
    "wof:name":"Karl-ernst Koch Schlosserei Und Metallbau Gmbh",
    "wof:placetype":"venue"
},
  "geometry": {"coordinates":[10.045858,53.558529],"type":"Point"}
}