{
  "type": "Feature",
  "properties": {
    "iso:country":"DE",
    "sg:address":"Kirchstr. 17",
    "sg:city":"Hoyerswerda",
    "sg:phone":"+49 3571/48310",
    "sg:postcode":"02977",
    "sg:province":"Sachsen",
    "wof:name":"Vvb Verm\u00f6gensaufbau-vorsorge- Beratungsorganisations-",
    "wof:placetype":"venue"
},
  "geometry": {"coordinates":[14.2424039841,51.4382171631],"type":"Point"}
}