{
  "type": "Feature",
  "properties": {
    "iso:country":"DE",
    "sg:address":"Stellbergsweg",
    "sg:city":"Homberg",
    "sg:phone":"+49 5681/4068",
    "sg:postcode":"34576",
    "sg:province":"Hessen",
    "wof:name":"Rewe Mohr",
    "wof:placetype":"venue"
},
  "geometry": {"coordinates":[9.395324707,51.0312843323],"type":"Point"}
}