{
  "type": "Feature",
  "properties": {
    "iso:country":"DE",
    "sg:address":"An der Sch\u00e4ferei 22",
    "sg:city":"Pulsnitz",
    "sg:phone":"+49 35955/45262",
    "sg:postcode":"01896",
    "sg:province":"Sachsen",
    "wof:name":"A. Und Michael Schieblich",
    "wof:placetype":"venue"
},
  "geometry": {"coordinates":[14.01334,51.180908],"type":"Point"}
}