{
  "type": "Feature",
  "properties": {
    "iso:country":"DE",
    "sg:address":"Peterstr. 15",
    "sg:city":"Westerstede",
    "sg:phone":"+49 4488/99800",
    "sg:postcode":"26655",
    "sg:province":"Niedersachsen",
    "wof:name":"Weiss B\u00fcro-service Gmbh",
    "wof:placetype":"venue"
},
  "geometry": {"coordinates":[7.9274530411,53.2554168701],"type":"Point"}
}