{
  "type": "Feature",
  "properties": {
    "iso:country":"DE",
    "sg:address":"Am Gangsteig 17",
    "sg:city":"Kirchheim",
    "sg:phone":"+49 89/9030765",
    "sg:postcode":"85551",
    "sg:province":"Bayern",
    "wof:name":"R. Wagnitz",
    "wof:placetype":"venue"
},
  "geometry": {"coordinates":[11.758054,48.162251],"type":"Point"}
}