{
  "type": "Feature",
  "properties": {
    "iso:country":"DE",
    "sg:address":"Haldener Str. 107",
    "sg:city":"Hagen",
    "sg:phone":"+49 2331/85188",
    "sg:postcode":"58095",
    "sg:province":"Nordrhein-Westfalen",
    "wof:name":"Elisabeth-apotheke",
    "wof:placetype":"venue"
},
  "geometry": {"coordinates":[7.491733,51.36507],"type":"Point"}
}