{
  "type": "Feature",
  "properties": {
    "iso:country":"DE",
    "sg:address":"Oberwarmensteinach 56",
    "sg:city":"Warmensteinach",
    "sg:phone":"+49 9277/1341",
    "sg:postcode":"95485",
    "sg:province":"Bayern",
    "wof:name":"Haus Mausbachtal",
    "wof:placetype":"venue"
},
  "geometry": {"coordinates":[11.7918596268,50.0020599365],"type":"Point"}
}