{
  "type": "Feature",
  "properties": {
    "iso:country":"DE",
    "sg:address":"Kreuzkapelle 65",
    "sg:city":"Much",
    "sg:phone":"+49 2245/650",
    "sg:postcode":"53804",
    "sg:province":"Nordrhein-Westfalen",
    "wof:name":"Dr. Fink-stauf Gmbh & Co. Kg",
    "wof:placetype":"venue"
},
  "geometry": {"coordinates":[7.3887939453,50.8814048767],"type":"Point"}
}