{
  "type": "Feature",
  "properties": {
    "iso:country":"DE",
    "sg:address":"S\u00fc\u00dfmilchstr. 6",
    "sg:city":"Bischofswerda",
    "sg:phone":"+49 3594/704829",
    "sg:postcode":"01877",
    "sg:province":"Sachsen",
    "wof:name":"Portas Fachbetrieb Frank St\u00e4glich",
    "wof:placetype":"venue"
},
  "geometry": {"coordinates":[14.181116,51.124386],"type":"Point"}
}