{
  "type": "Feature",
  "properties": {
    "iso:country":"DE",
    "sg:address":"Kantstr. 23",
    "sg:city":"Gr\u00fcnberg",
    "sg:phone":"+49 6401/7348",
    "sg:postcode":"35305",
    "sg:province":"Hessen",
    "wof:name":"Leonhard Schmidt Architekt",
    "wof:placetype":"venue"
},
  "geometry": {"coordinates":[8.952044,50.591999],"type":"Point"}
}