{
  "type": "Feature",
  "properties": {
    "iso:country":"DE",
    "sg:address":"Gassentor 4",
    "sg:city":"Brackenheim",
    "sg:phone":"+49 7135/5616",
    "sg:postcode":"74336",
    "sg:province":"Baden-W\u00fcrttemberg",
    "wof:name":"Hugo Schilling",
    "wof:placetype":"venue"
},
  "geometry": {"coordinates":[9.078307,49.089199],"type":"Point"}
}