{
  "type": "Feature",
  "properties": {
    "iso:country":"DE",
    "sg:address":"Kreuzweg 23",
    "sg:city":"Bad Salzuflen",
    "sg:phone":"+49 5222/98450",
    "sg:postcode":"32107",
    "sg:province":"Nordrhein-Westfalen",
    "wof:name":"K.r. Meier Gmbh & Co. Kg",
    "wof:placetype":"venue"
},
  "geometry": {"coordinates":[8.7470607758,52.0723762512],"type":"Point"}
}