{
  "type": "Feature",
  "properties": {
    "iso:country":"DE",
    "sg:address":"Bahnhof",
    "sg:city":"Ehingen",
    "sg:phone":"+49 7391/1443",
    "sg:postcode":"89584",
    "sg:province":"Baden-W\u00fcrttemberg",
    "wof:name":"E. Walde",
    "wof:placetype":"venue"
},
  "geometry": {"coordinates":[9.7233810425,48.2850761414],"type":"Point"}
}