{
  "type": "Feature",
  "properties": {
    "iso:country":"DE",
    "sg:address":"Bahnhofstr. 3a",
    "sg:city":"Wolfach",
    "sg:phone":"+49 7834/833890",
    "sg:postcode":"77709",
    "sg:province":"Baden-W\u00fcrttemberg",
    "wof:name":"Raiffeisen-warengenossenschaft Kinzigtal Und Umgebung Eg",
    "wof:placetype":"venue"
},
  "geometry": {"coordinates":[8.221548,48.294594],"type":"Point"}
}