{
  "type": "Feature",
  "properties": {
    "iso:country":"DE",
    "sg:address":"Schl\u00f6rplatz 1 a",
    "sg:city":"Weiden",
    "sg:phone":"+49 961/47470",
    "sg:postcode":"92637",
    "sg:province":"Bayern",
    "wof:name":"Hotel Am Tor",
    "wof:placetype":"venue"
},
  "geometry": {"coordinates":[12.1657896042,49.6768074036],"type":"Point"}
}