{
  "type": "Feature",
  "properties": {
    "iso:country":"DE",
    "sg:address":"Siefersheimer Str. 36",
    "sg:city":"W\u00f6llstein",
    "sg:phone":"+49 6703/1640",
    "sg:postcode":"55597",
    "sg:province":"Rheinland-Pfalz",
    "wof:name":"Holzbrandkunst Van Helden Gmbh",
    "wof:placetype":"venue"
},
  "geometry": {"coordinates":[7.9603219032,49.8093643188],"type":"Point"}
}