{
  "type": "Feature",
  "properties": {
    "iso:country":"DE",
    "sg:address":"Gewerbestr. 31",
    "sg:city":"Hardt",
    "sg:phone":"+49 4974/222770",
    "sg:postcode":"78739",
    "sg:province":"Baden-W\u00fcrttemberg",
    "wof:name":"Uts Pr\u00c4zisionstechnik Gmbh",
    "wof:placetype":"venue"
},
  "geometry": {"coordinates":[8.4157390594,48.1832427979],"type":"Point"}
}