{
  "type": "Feature",
  "properties": {
    "iso:country":"DE",
    "sg:address":"Eichenstr 32",
    "sg:city":"Taufkirchen",
    "sg:phone":"+49 89/6140135",
    "sg:postcode":"82024",
    "sg:province":"Bayern",
    "wof:name":"Kreissparkasse M\u00fcnchen",
    "wof:placetype":"venue"
},
  "geometry": {"coordinates":[11.603864,48.052177],"type":"Point"}
}