{
  "type": "Feature",
  "properties": {
    "iso:country":"DE",
    "sg:address":"Freiligrathstr. 99",
    "sg:city":"Wuppertal",
    "sg:phone":"+49 202/63315",
    "sg:postcode":"42289",
    "sg:province":"Nordrhein-Westfalen",
    "wof:name":"Verlag Holger Deimling - Wissenschaftlicher Buchverlag",
    "wof:placetype":"venue"
},
  "geometry": {"coordinates":[7.218053,51.266232],"type":"Point"}
}