{
  "type": "Feature",
  "properties": {
    "iso:country":"DE",
    "sg:address":"Am Alten Markt 8",
    "sg:city":"Ahrensburg",
    "sg:phone":"+49 4102/1824",
    "sg:postcode":"22926",
    "sg:province":"Schleswig-Holstein",
    "wof:name":"Franz Wucherpfennig Gmbh",
    "wof:placetype":"venue"
},
  "geometry": {"coordinates":[10.239552,53.677559],"type":"Point"}
}