{
  "type": "Feature",
  "properties": {
    "iso:country":"DE",
    "sg:address":"Gewerbestr. 31",
    "sg:city":"D\u00fclmen",
    "sg:phone":"+49 2590/91700",
    "sg:postcode":"48249",
    "sg:province":"Nordrhein-Westfalen",
    "wof:name":"Techno-design Wilmering Gmbh",
    "wof:placetype":"venue"
},
  "geometry": {"coordinates":[7.3852028847,51.8702583313],"type":"Point"}
}