{
  "type": "Feature",
  "properties": {
    "iso:country":"DE",
    "sg:address":"Theodor-Storm-Str. 16",
    "sg:city":"B\u00fcdelsdorf",
    "sg:phone":"+49 4331/669527",
    "sg:postcode":"24782",
    "sg:province":"Schleswig-Holstein",
    "wof:name":"Armin Hefner",
    "wof:placetype":"venue"
},
  "geometry": {"coordinates":[9.681683,54.322109],"type":"Point"}
}