{
  "type": "Feature",
  "properties": {
    "iso:country":"DE",
    "sg:address":"Kettelerstr. 59",
    "sg:city":"B\u00fcrstadt",
    "sg:phone":"+49 6206/6636",
    "sg:postcode":"68642",
    "sg:province":"Hessen",
    "wof:name":"W. Guthier Ingenieur",
    "wof:placetype":"venue"
},
  "geometry": {"coordinates":[8.468957901,49.640411377],"type":"Point"}
}