{
  "type": "Feature",
  "properties": {
    "iso:country":"DE",
    "sg:address":"Eggertstr. 30",
    "sg:city":"Paderborn",
    "sg:phone":"+49 5251/522400",
    "sg:postcode":"33100",
    "sg:province":"Nordrhein-Westfalen",
    "wof:name":"Pdc Westfalia Druck Gmbh",
    "wof:placetype":"venue"
},
  "geometry": {"coordinates":[8.799124,51.725883],"type":"Point"}
}