{
  "type": "Feature",
  "properties": {
    "iso:country":"DE",
    "sg:address":"Unteres Waldtor 1",
    "sg:city":"Waltershausen",
    "sg:phone":"+49 3622/60523",
    "sg:postcode":"99880",
    "sg:province":"Th\u00fcringen",
    "wof:name":"Manfred Meier",
    "wof:placetype":"venue"
},
  "geometry": {"coordinates":[10.553589,50.897537],"type":"Point"}
}