{
  "type": "Feature",
  "properties": {
    "iso:country":"DE",
    "sg:address":"Chemnitzer Str. 4",
    "sg:city":"Hainichen",
    "sg:phone":"+49 37207/3963",
    "sg:postcode":"09661",
    "sg:province":"Sachsen",
    "wof:name":"Andreas Schneider",
    "wof:placetype":"venue"
},
  "geometry": {"coordinates":[13.1315202713,50.9942321777],"type":"Point"}
}