{
  "type": "Feature",
  "properties": {
    "iso:country":"DE",
    "sg:address":"Neue Str. 16",
    "sg:city":"Hohndorf",
    "sg:phone":"+49 37204/5218",
    "sg:postcode":"09394",
    "sg:province":"Sachsen",
    "wof:name":"S. Schnerr",
    "wof:placetype":"venue"
},
  "geometry": {"coordinates":[12.67384,50.743519],"type":"Point"}
}