{
  "type": "Feature",
  "properties": {
    "iso:country":"DE",
    "sg:address":"Am Lokschuppen 6",
    "sg:city":"Neuwied",
    "sg:phone":"+49 4926/2292700",
    "sg:postcode":"56566",
    "sg:province":"Rheinland-Pfalz",
    "wof:name":"Orthop\u00c4dische Werkst\u00c4tten Gmbh",
    "wof:placetype":"venue"
},
  "geometry": {"coordinates":[7.5513849258,50.4242973328],"type":"Point"}
}