{
  "type": "Feature",
  "properties": {
    "iso:country":"DE",
    "sg:address":"Margaretenweg 3",
    "sg:city":"Neustadt",
    "sg:phone":"+49 5032/3143",
    "sg:postcode":"31535",
    "sg:province":"Niedersachsen",
    "wof:name":"Alfons Schendzielarz",
    "wof:placetype":"venue"
},
  "geometry": {"coordinates":[9.434533,52.503876],"type":"Point"}
}