{
  "type": "Feature",
  "properties": {
    "iso:country":"DE",
    "sg:address":"Friedrich-Ebert-Ring 29",
    "sg:city":"W\u00fcrzburg",
    "sg:phone":"+49 931/51914",
    "sg:postcode":"97072",
    "sg:province":"Bayern",
    "wof:name":"Kremling Nicolay Und Morlock Rechtsanw\u00e4lte",
    "wof:placetype":"venue"
},
  "geometry": {"coordinates":[9.9376964569,49.787273407],"type":"Point"}
}