{
  "type": "Feature",
  "properties": {
    "iso:country":"DE",
    "sg:address":"K\u00f6hlstr. 44",
    "sg:city":"Wiesbaden",
    "sg:phone":"+49 611/761635",
    "sg:postcode":"65205",
    "sg:province":"Hessen",
    "wof:name":"Pizzeria Roma",
    "wof:placetype":"venue"
},
  "geometry": {"coordinates":[8.2993659973,50.0563468933],"type":"Point"}
}