{
  "type": "Feature",
  "properties": {
    "iso:country":"DE",
    "sg:address":"Kreudnitzer Str. 4",
    "sg:city":"R\u00f6tha",
    "sg:phone":"+49 34206/64820",
    "sg:postcode":"04571",
    "sg:province":"Sachsen",
    "wof:name":"Agrargenossenschaft P\u00f6tzschau Eg",
    "wof:placetype":"venue"
},
  "geometry": {"coordinates":[12.420319,51.190266],"type":"Point"}
}