{
  "type": "Feature",
  "properties": {
    "iso:country":"DE",
    "sg:address":"Paradiesgasse 11",
    "sg:city":"Schramberg",
    "sg:phone":"+49 7422/3546",
    "sg:postcode":"78713",
    "sg:province":"Baden-W\u00fcrttemberg",
    "wof:name":"Karl Weiss",
    "wof:placetype":"venue"
},
  "geometry": {"coordinates":[8.3861675262,48.2279968262],"type":"Point"}
}