{
  "type": "Feature",
  "properties": {
    "iso:country":"DE",
    "sg:address":"Kirchstr. 14",
    "sg:city":"Quierschied",
    "sg:phone":"+49 6897/65199",
    "sg:postcode":"66287",
    "sg:province":"Saarland",
    "wof:name":"Spieloase Virginia Automatenaufstellungs-",
    "wof:placetype":"venue"
},
  "geometry": {"coordinates":[7.0478730202,49.3213996887],"type":"Point"}
}