{
  "type": "Feature",
  "properties": {
    "iso:country":"DE",
    "sg:address":"Settelweg 16",
    "sg:city":"Halle",
    "sg:phone":"+49 5201/16327",
    "sg:postcode":"33790",
    "sg:province":"Nordrhein-Westfalen",
    "wof:name":"Karl Lakebrink Gmbh",
    "wof:placetype":"venue"
},
  "geometry": {"coordinates":[8.3037462234,52.0051879883],"type":"Point"}
}