{
  "type": "Feature",
  "properties": {
    "iso:country":"DE",
    "sg:address":"Fuhrmannh\u00f6fe 3",
    "sg:city":"Weil der Stadt",
    "sg:phone":"+49 7033/41501",
    "sg:postcode":"71263",
    "sg:province":"Baden-W\u00fcrttemberg",
    "wof:name":"David G\u00f6tz",
    "wof:placetype":"venue"
},
  "geometry": {"coordinates":[8.916555,48.735168],"type":"Point"}
}