{
  "type": "Feature",
  "properties": {
    "iso:country":"DE",
    "sg:address":"Am Knauersbach 13",
    "sg:city":"N\u00fcrnberg",
    "sg:phone":"+49 911/882938",
    "sg:postcode":"90455",
    "sg:province":"Bayern",
    "wof:name":"B\u00fcro- Und Appartmenthaus Villa Freisleben Am Waldpark",
    "wof:placetype":"venue"
},
  "geometry": {"coordinates":[11.0795021057,49.3761825562],"type":"Point"}
}