{
  "type": "Feature",
  "properties": {
    "iso:country":"DE",
    "sg:address":"Bayrische Str. 1",
    "sg:city":"Neundorf",
    "sg:phone":"+49 36651/31301",
    "sg:postcode":"07356",
    "sg:province":"Th\u00fcringen",
    "wof:name":"Gastst\u00e4tte Und Pension",
    "wof:placetype":"venue"
},
  "geometry": {"coordinates":[11.6273288727,50.4547615051],"type":"Point"}
}