{
  "type": "Feature",
  "properties": {
    "iso:country":"DE",
    "sg:address":"Olpener Str. 793-795",
    "sg:city":"K\u00f6ln",
    "sg:phone":"+49 221/844419",
    "sg:postcode":"51109",
    "sg:province":"Nordrhein-Westfalen",
    "wof:name":"Kremer Innenausbau Gmbh",
    "wof:placetype":"venue"
},
  "geometry": {"coordinates":[7.0748910904,50.9454917908],"type":"Point"}
}