{
  "type": "Feature",
  "properties": {
    "iso:country":"DE",
    "sg:address":"M\u00f6rikestr. 62",
    "sg:city":"Filderstadt",
    "sg:phone":"+49 711/775011",
    "sg:postcode":"70794",
    "sg:province":"Baden-W\u00fcrttemberg",
    "wof:name":"Gerd Mayr",
    "wof:placetype":"venue"
},
  "geometry": {"coordinates":[9.2023601532,48.6585960388],"type":"Point"}
}