{
  "type": "Feature",
  "properties": {
    "iso:country":"DE",
    "sg:address":"Griembergweg 1",
    "sg:city":"Berlin",
    "sg:phone":"+49 30/7464451",
    "sg:postcode":"12305",
    "sg:province":"Berlin",
    "wof:name":"Bartel",
    "wof:placetype":"venue"
},
  "geometry": {"coordinates":[13.4065103531,52.4064178467],"type":"Point"}
}