{
  "type": "Feature",
  "properties": {
    "iso:country":"DE",
    "sg:address":"Hengeler 28",
    "sg:city":"Stadtlohn",
    "sg:phone":"+49 2563/5622",
    "sg:postcode":"48703",
    "sg:province":"Nordrhein-Westfalen",
    "wof:name":"Josef Wenning",
    "wof:placetype":"venue"
},
  "geometry": {"coordinates":[6.893402,52.012714],"type":"Point"}
}