{
  "type": "Feature",
  "properties": {
    "iso:country":"DE",
    "sg:address":"Rathausplatz",
    "sg:city":"Ingelheim",
    "sg:phone":"+49 6132/7820",
    "sg:postcode":"55218",
    "sg:province":"Rheinland-Pfalz",
    "wof:name":"Museum Bei Der Kaiserpfalz",
    "wof:placetype":"venue"
},
  "geometry": {"coordinates":[8.070826,49.976685],"type":"Point"}
}