{
  "type": "Feature",
  "properties": {
    "iso:country":"DE",
    "sg:address":"Kyffh\u00e4userstr. 21",
    "sg:city":"K\u00f6ln",
    "sg:phone":"+49 221/216213",
    "sg:postcode":"50674",
    "sg:province":"Nordrhein-Westfalen",
    "wof:name":"Hugo Otto Mauer Gmbh",
    "wof:placetype":"venue"
},
  "geometry": {"coordinates":[6.939343,50.928715],"type":"Point"}
}