{
  "type": "Feature",
  "properties": {
    "iso:country":"DE",
    "sg:address":"Industriestrasse 1",
    "sg:city":"Altendorf",
    "sg:phone":"+49 4909/5454490",
    "sg:postcode":"96146",
    "sg:province":"Bayern",
    "wof:name":"Loesch Verpackungstechnik Gmbh Co Kg",
    "wof:placetype":"venue"
},
  "geometry": {"coordinates":[11.0157976151,49.7964897156],"type":"Point"}
}