{
  "type": "Feature",
  "properties": {
    "iso:country":"DE",
    "sg:address":"Jesenwanger Str. 50",
    "sg:city":"Grafrath",
    "sg:postcode":"82284",
    "sg:province":"Bayern",
    "wof:name":"Tino Cabero Gesellschaft F\u00fcr K\u00e4lte- Und",
    "wof:placetype":"venue"
},
  "geometry": {"coordinates":[11.162934,48.134735],"type":"Point"}
}