{
  "type": "Feature",
  "properties": {
    "iso:country":"DE",
    "sg:address":"Schalaunische Str. 10",
    "sg:city":"K\u00f6then",
    "sg:phone":"+49 3496/213587",
    "sg:postcode":"06366",
    "sg:province":"Sachsen-Anhalt",
    "wof:name":"Petra Schmook",
    "wof:placetype":"venue"
},
  "geometry": {"coordinates":[11.978042,51.751293],"type":"Point"}
}