{
  "type": "Feature",
  "properties": {
    "iso:country":"DE",
    "sg:address":"Hemshofstr.38",
    "sg:city":"Ludwigshafen",
    "sg:phone":"+49 621/5907340",
    "sg:postcode":"67063",
    "sg:province":"Rheinland-Pfalz",
    "wof:name":"Dresdner Bank",
    "wof:placetype":"venue"
},
  "geometry": {"coordinates":[8.435936,49.49144],"type":"Point"}
}