{
  "type": "Feature",
  "properties": {
    "iso:country":"DE",
    "sg:address":"Steinh\u00f6hle 3",
    "sg:city":"Bad Orb",
    "sg:phone":"+49 6052/2125",
    "sg:postcode":"63619",
    "sg:province":"Hessen",
    "wof:name":"Panorama Hotel Und Gastst\u00e4tten Gmbh",
    "wof:placetype":"venue"
},
  "geometry": {"coordinates":[9.3502607346,50.2325935364],"type":"Point"}
}