{
  "type": "Feature",
  "properties": {
    "iso:country":"DE",
    "sg:address":"Auf den Bruchswiesen 6",
    "sg:city":"Gummersbach",
    "sg:phone":"+49 2261/63491",
    "sg:postcode":"51643",
    "sg:province":"Nordrhein-Westfalen",
    "wof:name":"F\u00fcmel Handelsvertretungen U. Grosshandel Gmbh",
    "wof:placetype":"venue"
},
  "geometry": {"coordinates":[7.5415520668,51.0133285522],"type":"Point"}
}