{
  "type": "Feature",
  "properties": {
    "iso:country":"DE",
    "sg:address":"Ebenseestr. 2a",
    "sg:city":"N\u00fcrnberg",
    "sg:phone":"+49 911/5430725",
    "sg:postcode":"90482",
    "sg:province":"Bayern",
    "wof:name":"Axel Linst\u00e4dt Komponist",
    "wof:placetype":"venue"
},
  "geometry": {"coordinates":[11.137140274,49.4671287537],"type":"Point"}
}