{
  "type": "Feature",
  "properties": {
    "iso:country":"DE",
    "sg:address":"Ritterstr. 7",
    "sg:city":"Karlsruhe",
    "sg:postcode":"76133",
    "sg:province":"Baden-W\u00fcrttemberg",
    "wof:name":"In Ex Dentalhandel Gmbh",
    "wof:placetype":"venue"
},
  "geometry": {"coordinates":[8.400894,49.009079],"type":"Point"}
}