{
  "type": "Feature",
  "properties": {
    "iso:country":"DE",
    "sg:address":"Schl\u00fcterstr. 17-19",
    "sg:city":"D\u00fcsseldorf",
    "sg:postcode":"40235",
    "sg:province":"Nordrhein-Westfalen",
    "wof:name":"Metro Asia Holding Gmbh",
    "wof:placetype":"venue"
},
  "geometry": {"coordinates":[6.822308,51.235039],"type":"Point"}
}