{
  "type": "Feature",
  "properties": {
    "iso:country":"DE",
    "sg:address":"Mozartstr. 102",
    "sg:city":"Hochdorf",
    "sg:postcode":"88454",
    "sg:province":"Baden-W\u00fcrttemberg",
    "wof:name":"Xaver Schott Verwaltungs Gmbh",
    "wof:placetype":"venue"
},
  "geometry": {"coordinates":[9.7924404144,48.0250015259],"type":"Point"}
}