{
  "type": "Feature",
  "properties": {
    "iso:country":"DE",
    "sg:address":"Klenzestr. 43",
    "sg:city":"M\u00fcnchen",
    "sg:phone":"+49 89/2016776",
    "sg:postcode":"80469",
    "sg:province":"Bayern",
    "wof:name":"Club Morizz",
    "wof:placetype":"venue"
},
  "geometry": {"coordinates":[11.574535,48.130611],"type":"Point"}
}