{
  "type": "Feature",
  "properties": {
    "iso:country":"DE",
    "sg:address":"Saxbergstr. 22",
    "sg:city":"Sinzing",
    "sg:phone":"+49 9404/4617",
    "sg:postcode":"93161",
    "sg:province":"Bayern",
    "wof:name":"Lundia Regale Susanne Mai",
    "wof:placetype":"venue"
},
  "geometry": {"coordinates":[11.95166,48.967339],"type":"Point"}
}