{
  "type": "Feature",
  "properties": {
    "iso:country":"DE",
    "sg:address":"Heerstr. 13",
    "sg:city":"Meinerzhagen",
    "sg:phone":"+49 2354/91800",
    "sg:postcode":"58540",
    "sg:province":"Nordrhein-Westfalen",
    "wof:name":"Wsm Werkzeugstahl Gmbh",
    "wof:placetype":"venue"
},
  "geometry": {"coordinates":[7.671558,51.096691],"type":"Point"}
}