{
  "type": "Feature",
  "properties": {
    "iso:country":"DE",
    "sg:address":"Damaschkestr. 6",
    "sg:city":"Rudolstadt",
    "sg:phone":"+49 3672/424341",
    "sg:postcode":"07407",
    "sg:province":"Th\u00fcringen",
    "wof:name":"B\u00e4rbel Kalff Architektin",
    "wof:placetype":"venue"
},
  "geometry": {"coordinates":[11.340775,50.711487],"type":"Point"}
}