{
  "type": "Feature",
  "properties": {
    "iso:country":"DE",
    "sg:address":"Ostfrieslandstr. 34",
    "sg:city":"Hamburg",
    "sg:phone":"+49 40/7426113",
    "sg:postcode":"21129",
    "sg:province":"Hamburg",
    "wof:name":"Finkenwerder Imbi\u00df",
    "wof:placetype":"venue"
},
  "geometry": {"coordinates":[9.8786621094,53.5294036865],"type":"Point"}
}