{
  "type": "Feature",
  "properties": {
    "iso:country":"DE",
    "sg:address":"Gro\u00dfe Ulrichstr.",
    "sg:city":"Halle",
    "sg:phone":"+49 345/9772601",
    "sg:postcode":"06108",
    "sg:province":"Sachsen-Anhalt",
    "wof:name":"Catapult Gmbh",
    "wof:placetype":"venue"
},
  "geometry": {"coordinates":[11.9665298462,51.4871902466],"type":"Point"}
}