{
  "type": "Feature",
  "properties": {
    "iso:country":"DE",
    "sg:address":"Altersham 13",
    "sg:city":"Pittenhart",
    "sg:postcode":"83132",
    "sg:province":"Bayern",
    "wof:name":"Termin-express-logistik Gmbh Te",
    "wof:placetype":"venue"
},
  "geometry": {"coordinates":[12.3448677063,47.9811248779],"type":"Point"}
}