{
  "type": "Feature",
  "properties": {
    "iso:country":"DE",
    "sg:address":"Auf'm Kickel 2",
    "sg:city":"Andernach",
    "sg:postcode":"56626",
    "sg:province":"Rheinland-Pfalz",
    "wof:name":"Master Consulting Group Internationale Beteiligungs Ag",
    "wof:placetype":"venue"
},
  "geometry": {"coordinates":[7.394209,50.432976],"type":"Point"}
}