{
  "type": "Feature",
  "properties": {
    "iso:country":"DE",
    "sg:address":"Ellernstr. 8 a",
    "sg:city":"Norderney",
    "sg:phone":"+49 4932/2298",
    "sg:postcode":"26548",
    "sg:province":"Niedersachsen",
    "wof:name":"Bauunternehmung Bodenstab Gmbh & Co. Kg",
    "wof:placetype":"venue"
},
  "geometry": {"coordinates":[7.151251,53.709282],"type":"Point"}
}