{
  "type": "Feature",
  "properties": {
    "iso:country":"DE",
    "sg:address":"Sankt Augustiner Str. 93",
    "sg:city":"Bonn",
    "sg:phone":"+49 228/462255",
    "sg:postcode":"53225",
    "sg:province":"Nordrhein-Westfalen",
    "wof:name":"Ralf S\u00e4dler E. K.",
    "wof:placetype":"venue"
},
  "geometry": {"coordinates":[7.1218748093,50.7432289124],"type":"Point"}
}