{
  "type": "Feature",
  "properties": {
    "iso:country":"DE",
    "sg:address":"\u00d6stringer Weg 156",
    "sg:city":"Osnabr\u00fcck",
    "sg:phone":"+49 541/63581",
    "sg:postcode":"49090",
    "sg:province":"Niedersachsen",
    "wof:name":"Friedrich Hardinghaus",
    "wof:placetype":"venue"
},
  "geometry": {"coordinates":[8.074315,52.31319],"type":"Point"}
}