{
  "type": "Feature",
  "properties": {
    "iso:country":"DE",
    "sg:address":"Adenauerring 9",
    "sg:city":"M\u00fcnchen",
    "sg:phone":"+49 89/63002100",
    "sg:postcode":"81737",
    "sg:province":"Bayern",
    "wof:name":"Accor It Service Gmbh",
    "wof:placetype":"venue"
},
  "geometry": {"coordinates":[11.640819,48.104542],"type":"Point"}
}