{
  "type": "Feature",
  "properties": {
    "iso:country":"DE",
    "sg:address":"Ehlersstr. 17",
    "sg:city":"Falkensee",
    "sg:phone":"+49 3322/203994",
    "sg:postcode":"14612",
    "sg:province":"Brandenburg",
    "wof:name":"Redewo Immobilien Gmbh",
    "wof:placetype":"venue"
},
  "geometry": {"coordinates":[13.0395917892,52.5655021667],"type":"Point"}
}