{
  "type": "Feature",
  "properties": {
    "iso:country":"DE",
    "sg:address":"Hersfelder Str. 26",
    "sg:city":"Bad Hersfeld",
    "sg:phone":"+49 6621/77016",
    "sg:postcode":"36251",
    "sg:province":"Hessen",
    "wof:name":"H. F. L. Frucht-logistik Gmbh",
    "wof:placetype":"venue"
},
  "geometry": {"coordinates":[9.675283432,50.8859634399],"type":"Point"}
}