{
  "type": "Feature",
  "properties": {
    "iso:country":"DE",
    "sg:address":"Bahnhofstr. 40",
    "sg:city":"Redwitz",
    "sg:phone":"+49 9574/650171",
    "sg:postcode":"96257",
    "sg:province":"Bayern",
    "wof:name":"Willy Wagner Gmbh",
    "wof:placetype":"venue"
},
  "geometry": {"coordinates":[11.205641,50.171013],"type":"Point"}
}