{
  "type": "Feature",
  "properties": {
    "iso:country":"DE",
    "sg:address":"Jahnstr. 34",
    "sg:city":"Geesthacht",
    "sg:phone":"+49 4152/71618",
    "sg:postcode":"21502",
    "sg:province":"Schleswig-Holstein",
    "wof:name":"Imbi\u00df Gr\u00fcnhof",
    "wof:placetype":"venue"
},
  "geometry": {"coordinates":[10.43409729,53.41381073],"type":"Point"}
}