{
  "type": "Feature",
  "properties": {
    "iso:country":"DE",
    "sg:address":"Gartenstr. 17",
    "sg:city":"Stelle",
    "sg:postcode":"21435",
    "sg:province":"Niedersachsen",
    "wof:name":"Hermann Ahlers",
    "wof:placetype":"venue"
},
  "geometry": {"coordinates":[10.1455001831,53.3629112244],"type":"Point"}
}