{
  "type": "Feature",
  "properties": {
    "iso:country":"DE",
    "sg:address":"Parkstr. 34",
    "sg:city":"Rostock",
    "sg:phone":"+49 381/5192928",
    "sg:postcode":"18119",
    "sg:province":"Mecklenburg-Vorpommern",
    "wof:name":"Nord-h\u00e4user Baubetreuungsges. Mbh",
    "wof:placetype":"venue"
},
  "geometry": {"coordinates":[12.066577,54.176754],"type":"Point"}
}