{
  "type": "Feature",
  "properties": {
    "iso:country":"DE",
    "sg:address":"Irmengardisstr. 5",
    "sg:city":"Bad Buchau",
    "sg:phone":"+49 7582/2578",
    "sg:postcode":"88422",
    "sg:province":"Baden-W\u00fcrttemberg",
    "wof:name":"C. Haller Hebamme",
    "wof:placetype":"venue"
},
  "geometry": {"coordinates":[9.616705,48.059097],"type":"Point"}
}