{
  "type": "Feature",
  "properties": {
    "iso:country":"DE",
    "sg:address":"W\u00f6rther Str. 1",
    "sg:city":"W\u00f6rth",
    "sg:phone":"+49 8122/3492",
    "sg:postcode":"85457",
    "sg:province":"Bayern",
    "wof:name":"Hans Roth",
    "wof:placetype":"venue"
},
  "geometry": {"coordinates":[11.936375,48.243824],"type":"Point"}
}