{
  "type": "Feature",
  "properties": {
    "iso:country":"DE",
    "sg:address":"Hasselsstr. 120",
    "sg:city":"D\u00fcsseldorf",
    "sg:phone":"+49 211/745705",
    "sg:postcode":"40599",
    "sg:province":"Nordrhein-Westfalen",
    "wof:name":"B\u00fcrgerhaus",
    "wof:placetype":"venue"
},
  "geometry": {"coordinates":[6.8737230301,51.1778717041],"type":"Point"}
}