{
  "type": "Feature",
  "properties": {
    "iso:country":"DE",
    "sg:address":"Lerchenberg 33",
    "sg:city":"Hamburg",
    "sg:phone":"+49 40/6032657",
    "sg:postcode":"22359",
    "sg:province":"Hamburg",
    "wof:name":"G\u00fcnter Schulz Innenausbau Gmbh",
    "wof:placetype":"venue"
},
  "geometry": {"coordinates":[10.167548,53.654137],"type":"Point"}
}