{
  "type": "Feature",
  "properties": {
    "iso:country":"DE",
    "sg:address":"Schaumbergstr. 123",
    "sg:city":"Lebach",
    "sg:phone":"+49 6888/8555",
    "sg:postcode":"66822",
    "sg:province":"Saarland",
    "wof:name":"Gilbert M\u00fcller",
    "wof:placetype":"venue"
},
  "geometry": {"coordinates":[6.9634537697,49.446434021],"type":"Point"}
}