{
  "type": "Feature",
  "properties": {
    "iso:country":"DE",
    "sg:address":"Postfach 1107",
    "sg:city":"Emmerich",
    "sg:postcode":"46421",
    "wof:name":"Alpen- Kreuzer Gebr. Kramer Gmbh",
    "wof:placetype":"venue"
},
  "geometry": {"coordinates":[6.23477,51.846191],"type":"Point"}
}