{
  "type": "Feature",
  "properties": {
    "iso:country":"DE",
    "sg:address":"Laubstiege 19",
    "sg:city":"Gronau",
    "sg:phone":"+49 2562/7170",
    "sg:postcode":"48599",
    "sg:province":"Nordrhein-Westfalen",
    "wof:name":"Zweite Stadtwerke Windkraftanlagen Gmbh & Co. Kg",
    "wof:placetype":"venue"
},
  "geometry": {"coordinates":[7.033241,52.205597],"type":"Point"}
}