{
  "type": "Feature",
  "properties": {
    "iso:country":"DE",
    "sg:address":"Sandweg 8",
    "sg:city":"W\u00fcstenrot",
    "sg:phone":"+49 7945/2568",
    "sg:postcode":"71543",
    "sg:province":"Baden-W\u00fcrttemberg",
    "wof:name":"Heinrich Geist Gmbh",
    "wof:placetype":"venue"
},
  "geometry": {"coordinates":[9.460874,49.078533],"type":"Point"}
}