{
  "type": "Feature",
  "properties": {
    "iso:country":"DE",
    "sg:address":"Schwaiger Str. 36",
    "sg:city":"Dingolfing",
    "sg:phone":"+49 8731/74181",
    "sg:postcode":"84130",
    "sg:province":"Bayern",
    "wof:name":"Sanirail Gleis- Und Tiefbau Gmbh",
    "wof:placetype":"venue"
},
  "geometry": {"coordinates":[12.486735,48.640167],"type":"Point"}
}