{
  "type": "Feature",
  "properties": {
    "iso:country":"DE",
    "sg:address":"Caspar-David-Friedrich-Str. 2",
    "sg:city":"Greifswald",
    "sg:phone":"+49 3834/892903",
    "sg:postcode":"17489",
    "sg:province":"Mecklenburg-Vorpommern",
    "wof:name":"Bernhard Jablonski",
    "wof:placetype":"venue"
},
  "geometry": {"coordinates":[13.376502,54.095509],"type":"Point"}
}