{
  "type": "Feature",
  "properties": {
    "iso:country":"DE",
    "sg:address":"Raiffeisenstr 1",
    "sg:city":"Fluorn-Winzeln",
    "sg:phone":"+49 7402/1384",
    "sg:postcode":"78737",
    "sg:province":"Baden-W\u00fcrttemberg",
    "wof:name":"Rainer Hess",
    "wof:placetype":"venue"
},
  "geometry": {"coordinates":[8.49257,48.295029],"type":"Point"}
}