{
  "type": "Feature",
  "properties": {
    "iso:country":"DE",
    "sg:address":"Demmeltrather Str. 18",
    "sg:city":"Solingen",
    "sg:phone":"+49 212/313315",
    "sg:postcode":"42719",
    "sg:province":"Nordrhein-Westfalen",
    "wof:name":"Tischlerei Raschke Gmbh",
    "wof:placetype":"venue"
},
  "geometry": {"coordinates":[7.056036,51.189987],"type":"Point"}
}