{
  "type": "Feature",
  "properties": {
    "iso:country":"DE",
    "sg:address":"Im Aachtal 1",
    "sg:city":"Aach",
    "sg:phone":"+49 7774/93120",
    "sg:postcode":"78267",
    "sg:province":"Baden-W\u00fcrttemberg",
    "wof:name":"Bardenheuer & Str\u00f6hle Gmbh",
    "wof:placetype":"venue"
},
  "geometry": {"coordinates":[8.865114212,47.8325920105],"type":"Point"}
}