{
  "type": "Feature",
  "properties": {
    "iso:country":"DE",
    "sg:address":"D\u00fcrerstr. 37",
    "sg:city":"Balingen",
    "sg:postcode":"72336",
    "sg:province":"Baden-W\u00fcrttemberg",
    "wof:name":"T\u00dco- Technische \u00dcberwachungs- Organistion F. Abfallwirt.",
    "wof:placetype":"venue"
},
  "geometry": {"coordinates":[8.845548,48.289188],"type":"Point"}
}