{
  "type": "Feature",
  "properties": {
    "iso:country":"DE",
    "sg:address":"Duckterather Busch 16",
    "sg:city":"Bergisch Gladbach",
    "sg:phone":"+49 2202/52390",
    "sg:postcode":"51469",
    "sg:province":"Nordrhein-Westfalen",
    "wof:name":"W. M\u00fcller",
    "wof:placetype":"venue"
},
  "geometry": {"coordinates":[7.0989069939,50.9850921631],"type":"Point"}
}