{
  "type": "Feature",
  "properties": {
    "iso:country":"DE",
    "sg:address":"Colonnaden 3",
    "sg:city":"Hamburg",
    "sg:postcode":"20354",
    "sg:province":"Hamburg",
    "wof:name":"Offtake Vermarktungskonzepte F\u00fcr Den Einzelhandel Gmbh",
    "wof:placetype":"venue"
},
  "geometry": {"coordinates":[9.9905662537,53.5550193787],"type":"Point"}
}