{
  "type": "Feature",
  "properties": {
    "iso:country":"DE",
    "sg:address":"Hauptstr. 18",
    "sg:city":"Leopoldsh\u00f6he",
    "sg:phone":"+49 5208/7651",
    "sg:postcode":"33818",
    "sg:province":"Nordrhein-Westfalen",
    "wof:name":"K. Winkler",
    "wof:placetype":"venue"
},
  "geometry": {"coordinates":[8.698591,52.010906],"type":"Point"}
}