{
  "type": "Feature",
  "properties": {
    "iso:country":"DE",
    "sg:address":"Bergstr. 9",
    "sg:city":"Sachsenkam",
    "sg:phone":"+49 8021/504",
    "sg:postcode":"83679",
    "sg:province":"Bayern",
    "wof:name":"Kath. Pfarramt St. Andreas",
    "wof:placetype":"venue"
},
  "geometry": {"coordinates":[11.6470565796,47.8056716919],"type":"Point"}
}