{
  "type": "Feature",
  "properties": {
    "iso:country":"DE",
    "sg:address":"An der Kreisstr. 4",
    "sg:city":"Ainring",
    "sg:phone":"+49 8654/8440",
    "sg:postcode":"83404",
    "sg:province":"Bayern",
    "wof:name":"Rudolf Keil Steinmetz",
    "wof:placetype":"venue"
},
  "geometry": {"coordinates":[12.9454612732,47.8098678589],"type":"Point"}
}