{
  "type": "Feature",
  "properties": {
    "iso:country":"DE",
    "sg:address":"Markt 9",
    "sg:city":"Mittweida",
    "sg:phone":"+49 3727/3016",
    "sg:postcode":"09648",
    "sg:province":"Sachsen",
    "wof:name":"K. Uhlig",
    "wof:placetype":"venue"
},
  "geometry": {"coordinates":[12.981381,50.985729],"type":"Point"}
}