{
  "type": "Feature",
  "properties": {
    "iso:country":"DE",
    "sg:address":"Basler Str. 63",
    "sg:city":"Freiburg",
    "sg:phone":"+49 761/4098240",
    "sg:postcode":"79100",
    "sg:province":"Baden-W\u00fcrttemberg",
    "wof:name":"Jaso M\u00f6belwerke Gmbh",
    "wof:placetype":"venue"
},
  "geometry": {"coordinates":[7.837059021,47.9865112305],"type":"Point"}
}