{
  "type": "Feature",
  "properties": {
    "iso:country":"DE",
    "sg:address":"Grafengasse 10",
    "sg:city":"Erfurt",
    "sg:phone":"+49 361/598980",
    "sg:postcode":"99084",
    "sg:province":"Th\u00fcringen",
    "wof:name":"Verlag Heinz Heise Gmbh & Co. Kg",
    "wof:placetype":"venue"
},
  "geometry": {"coordinates":[11.031895,50.97578],"type":"Point"}
}