{
  "type": "Feature",
  "properties": {
    "iso:country":"DE",
    "sg:address":"Bauernstr. 12",
    "sg:city":"Erxleben",
    "sg:phone":"+49 39052/253",
    "sg:postcode":"39343",
    "sg:province":"Sachsen-Anhalt",
    "wof:name":"Burkhard Kruschel",
    "wof:placetype":"venue"
},
  "geometry": {"coordinates":[11.236746,52.218533],"type":"Point"}
}