{
  "type": "Feature",
  "properties": {
    "iso:country":"DE",
    "sg:address":"Zollerstr. 7",
    "sg:city":"Aretsried",
    "sg:phone":"+49 8236/999501",
    "sg:postcode":"86850",
    "sg:province":"Bayern",
    "wof:name":"Optipack Gmbh & Co Kg",
    "wof:placetype":"venue"
},
  "geometry": {"coordinates":[10.6539325714,48.3090934753],"type":"Point"}
}