{
  "type": "Feature",
  "properties": {
    "iso:country":"DE",
    "sg:address":"Stelzenhofstr. 26",
    "sg:city":"Hof",
    "sg:phone":"+49 9281/75430",
    "sg:postcode":"95032",
    "sg:province":"Bayern",
    "wof:name":"Bbv Beton- Und Baustoff-vertrieb Eg",
    "wof:placetype":"venue"
},
  "geometry": {"coordinates":[11.917104,50.288853],"type":"Point"}
}