{
  "type": "Feature",
  "properties": {
    "iso:country":"DE",
    "sg:address":"B\u00fcchnerweg 92",
    "sg:city":"Berlin",
    "sg:phone":"+49 30/6770011",
    "sg:postcode":"12489",
    "sg:province":"Berlin",
    "wof:name":"Lutz Nessing",
    "wof:placetype":"venue"
},
  "geometry": {"coordinates":[13.547359,52.43306],"type":"Point"}
}