{
  "type": "Feature",
  "properties": {
    "iso:country":"DE",
    "sg:address":"Ebertstr. 25",
    "sg:city":"Zwenkau",
    "sg:phone":"+49 34203/31763",
    "sg:postcode":"04442",
    "sg:province":"Sachsen",
    "wof:name":"Hrs Projekt- Und Bau Entwicklungsgesellschaft Mbh",
    "wof:placetype":"venue"
},
  "geometry": {"coordinates":[12.33476,51.218323],"type":"Point"}
}