{
  "type": "Feature",
  "properties": {
    "iso:country":"DE",
    "sg:address":"Mannheimer Str. 30",
    "sg:city":"Br\u00fchl",
    "sg:phone":"+49 6202/72675",
    "sg:postcode":"68782",
    "sg:province":"Baden-W\u00fcrttemberg",
    "wof:name":"L. Radler Dachdecker Gmbh",
    "wof:placetype":"venue"
},
  "geometry": {"coordinates":[8.535159,49.397259],"type":"Point"}
}