{
  "type": "Feature",
  "properties": {
    "iso:country":"DE",
    "sg:address":"Dr.-Fuchs-Str. 4",
    "sg:city":"Friedrichsdorf",
    "sg:postcode":"61381",
    "sg:province":"Hessen",
    "wof:name":"Adhoc Kurierdienst Gmbh",
    "wof:placetype":"venue"
},
  "geometry": {"coordinates":[8.638826,50.257118],"type":"Point"}
}