{
  "type": "Feature",
  "properties": {
    "iso:country":"DE",
    "sg:address":"Kimmelg\u00e4\u00dfle 1",
    "sg:city":"Gingen",
    "sg:phone":"+49 7162/45077",
    "sg:postcode":"73333",
    "sg:province":"Baden-W\u00fcrttemberg",
    "wof:name":"W\u00fcrttembergische Versicherung",
    "wof:placetype":"venue"
},
  "geometry": {"coordinates":[9.7798080444,48.6583747864],"type":"Point"}
}