{
  "type": "Feature",
  "properties": {
    "iso:country":"DE",
    "sg:address":"Auf'm Bruch 12",
    "sg:city":"Warstein",
    "sg:phone":"+49 2902/4025",
    "sg:postcode":"59581",
    "sg:province":"Nordrhein-Westfalen",
    "wof:name":"Herrenzentrum Sch\u00fctte",
    "wof:placetype":"venue"
},
  "geometry": {"coordinates":[8.2740602493,51.4832000732],"type":"Point"}
}