{
  "type": "Feature",
  "properties": {
    "iso:country":"DE",
    "sg:address":"St.-Cajetan-Str. 8",
    "sg:city":"M\u00fcnchen",
    "sg:postcode":"81669",
    "sg:province":"Bayern",
    "wof:name":"Dr. Roland Gerstmeier E. K.",
    "wof:placetype":"venue"
},
  "geometry": {"coordinates":[11.6001443863,48.1215896606],"type":"Point"}
}