{
  "type": "Feature",
  "properties": {
    "iso:country":"DE",
    "sg:address":"Altenfurter Str. 68",
    "sg:city":"N\u00fcrnberg",
    "sg:postcode":"90475",
    "sg:province":"Bayern",
    "wof:name":"Feuerschutz Noris Gmbh",
    "wof:placetype":"venue"
},
  "geometry": {"coordinates":[11.176118,49.403133],"type":"Point"}
}