{
  "type": "Feature",
  "properties": {
    "iso:country":"DE",
    "sg:address":"Hohenfelde 2",
    "sg:city":"Harsefeld",
    "sg:phone":"+49 4164/6403",
    "sg:postcode":"21698",
    "sg:province":"Niedersachsen",
    "wof:name":"Gastst\u00e4tte Kithira",
    "wof:placetype":"venue"
},
  "geometry": {"coordinates":[9.5083751678,53.4556045532],"type":"Point"}
}