{
  "type": "Feature",
  "properties": {
    "iso:country":"DE",
    "sg:address":"Obere Eichst\u00e4dtstr. 33",
    "sg:city":"Leipzig",
    "sg:phone":"+49 341/8613730",
    "sg:postcode":"04299",
    "sg:province":"Sachsen",
    "wof:name":"Frank Rosner",
    "wof:placetype":"venue"
},
  "geometry": {"coordinates":[12.41704,51.31868],"type":"Point"}
}