{
  "type": "Feature",
  "properties": {
    "iso:country":"DE",
    "sg:address":"Drankhausen 10",
    "sg:city":"Borgentreich",
    "sg:phone":"+49 5645/9148",
    "sg:postcode":"34434",
    "sg:province":"Nordrhein-Westfalen",
    "wof:name":"Hwo Barbara Oberhoff Gmbh",
    "wof:placetype":"venue"
},
  "geometry": {"coordinates":[9.209042,51.616631],"type":"Point"}
}