{
  "type": "Feature",
  "properties": {
    "iso:country":"DE",
    "sg:address":"Rodigallee 147",
    "sg:city":"Hamburg",
    "sg:postcode":"22043",
    "sg:province":"Hamburg",
    "wof:name":"Shico Direktvertrieb Gmbh",
    "wof:placetype":"venue"
},
  "geometry": {"coordinates":[10.1126680374,53.5711669922],"type":"Point"}
}