{
  "type": "Feature",
  "properties": {
    "iso:country":"DE",
    "sg:address":"Karnaper Str. 124",
    "sg:city":"Essen",
    "sg:phone":"+49 201/8385761",
    "sg:postcode":"45329",
    "sg:province":"Nordrhein-Westfalen",
    "wof:name":"Reibu Spielhallen Gmbh",
    "wof:placetype":"venue"
},
  "geometry": {"coordinates":[7.008478,51.523781],"type":"Point"}
}