{
  "type": "Feature",
  "properties": {
    "iso:country":"DE",
    "sg:address":"Arnemannstr. 1",
    "sg:city":"Hamburg",
    "sg:phone":"+49 40/396852",
    "sg:postcode":"22765",
    "sg:province":"Hamburg",
    "wof:name":"Altonaer Blume Andreas Lappat",
    "wof:placetype":"venue"
},
  "geometry": {"coordinates":[9.931737,53.547928],"type":"Point"}
}