{
  "type": "Feature",
  "properties": {
    "iso:country":"DE",
    "sg:address":"Mumbacher Str. 21",
    "sg:city":"Birkenau",
    "sg:phone":"+49 6209/4285",
    "sg:postcode":"69488",
    "sg:province":"Hessen",
    "wof:name":"Adam Jakob",
    "wof:placetype":"venue"
},
  "geometry": {"coordinates":[8.7217359543,49.5793762207],"type":"Point"}
}