{
  "type": "Feature",
  "properties": {
    "iso:country":"DE",
    "sg:address":"Robert-Bosch-Str. 4",
    "sg:city":"Radevormwald",
    "sg:phone":"+49 2195/7193",
    "sg:postcode":"42477",
    "sg:province":"Nordrhein-Westfalen",
    "wof:name":"Gilbert Freymann",
    "wof:placetype":"venue"
},
  "geometry": {"coordinates":[7.3842449188,51.2023200989],"type":"Point"}
}