{
  "type": "Feature",
  "properties": {
    "iso:country":"DE",
    "sg:address":"Marienplatz 11",
    "sg:city":"Naumburg",
    "sg:phone":"+49 3445/202904",
    "sg:postcode":"06618",
    "sg:province":"Sachsen-Anhalt",
    "wof:name":"H. Schweinoch",
    "wof:placetype":"venue"
},
  "geometry": {"coordinates":[11.81278,51.154621],"type":"Point"}
}