{
  "type": "Feature",
  "properties": {
    "iso:country":"DE",
    "sg:address":"Heerdter Landstr. 227",
    "sg:city":"D\u00fcsseldorf",
    "sg:phone":"+49 4921/1502144",
    "sg:postcode":"40549",
    "sg:province":"Nordrhein-Westfalen",
    "wof:name":"Nirschel & St\u00dcdemann Inh. Harald Lenke",
    "wof:placetype":"venue"
},
  "geometry": {"coordinates":[6.7022609711,51.2292938232],"type":"Point"}
}