{
  "type": "Feature",
  "properties": {
    "iso:country":"DE",
    "sg:address":"Beierfelder Str. 47",
    "sg:city":"Bernsbach",
    "sg:postcode":"08315",
    "sg:province":"Sachsen",
    "wof:name":"Seifert Drucklufttechnik Gmbh",
    "wof:placetype":"venue"
},
  "geometry": {"coordinates":[12.776263,50.570904],"type":"Point"}
}