{
  "type": "Feature",
  "properties": {
    "iso:country":"DE",
    "sg:address":"Uhuweg 1",
    "sg:city":"K\u00f6ln",
    "sg:phone":"+49 2233/280988",
    "sg:postcode":"50997",
    "sg:province":"Nordrhein-Westfalen",
    "wof:name":"Fa Pamukkale Gmbh",
    "wof:placetype":"venue"
},
  "geometry": {"coordinates":[6.9596881866,50.873046875],"type":"Point"}
}