{
  "type": "Feature",
  "properties": {
    "iso:country":"DE",
    "sg:address":"Amalienstr. 45",
    "sg:city":"M\u00fcnchen",
    "sg:phone":"+49 89/5468250",
    "sg:postcode":"80799",
    "sg:province":"Bayern",
    "wof:name":"Seitz & Partner Gmbh",
    "wof:placetype":"venue"
},
  "geometry": {"coordinates":[11.5771951675,48.148765564],"type":"Point"}
}