{
  "type": "Feature",
  "properties": {
    "iso:country":"DE",
    "sg:address":"Siebenmorgen 30",
    "sg:city":"Bergisch Gladbach",
    "sg:phone":"+49 2204/925160",
    "sg:postcode":"51427",
    "sg:province":"Nordrhein-Westfalen",
    "wof:name":"K. Berens",
    "wof:placetype":"venue"
},
  "geometry": {"coordinates":[7.116818,50.95713],"type":"Point"}
}