{
  "type": "Feature",
  "properties": {
    "iso:country":"DE",
    "sg:address":"Sandweg 9",
    "sg:city":"Leck",
    "sg:phone":"+49 4662/4570",
    "sg:postcode":"25917",
    "sg:province":"Schleswig-Holstein",
    "wof:name":"Elmar Ochmann Schweinezucht Kg",
    "wof:placetype":"venue"
},
  "geometry": {"coordinates":[8.9596805573,54.7504348755],"type":"Point"}
}