{
  "type": "Feature",
  "properties": {
    "iso:country":"DE",
    "sg:address":"Alsenzstr. 26",
    "sg:city":"M\u00fcnchweiler",
    "sg:phone":"+49 6302/2232",
    "sg:postcode":"67728",
    "sg:province":"Rheinland-Pfalz",
    "wof:name":"Erwin Engel",
    "wof:placetype":"venue"
},
  "geometry": {"coordinates":[7.886913,49.554653],"type":"Point"}
}