{
  "type": "Feature",
  "properties": {
    "iso:country":"DE",
    "sg:address":"Sebastianusstr. 78",
    "sg:city":"Stolberg",
    "sg:phone":"+49 2402/27402",
    "sg:postcode":"52222",
    "sg:province":"Nordrhein-Westfalen",
    "wof:name":"Leo Stich",
    "wof:placetype":"venue"
},
  "geometry": {"coordinates":[6.208675,50.785404],"type":"Point"}
}