{
  "type": "Feature",
  "properties": {
    "iso:country":"DE",
    "sg:address":"Neumarkt 5",
    "sg:city":"Viersen",
    "sg:phone":"+49 2162/53299",
    "sg:postcode":"41751",
    "sg:province":"Nordrhein-Westfalen",
    "wof:name":"Club Extase",
    "wof:placetype":"venue"
},
  "geometry": {"coordinates":[6.336425,51.25301],"type":"Point"}
}