{
  "type": "Feature",
  "properties": {
    "iso:country":"DE",
    "sg:address":"Neuh\u00e4userstr. 13",
    "sg:city":"Augsburg",
    "sg:phone":"+49 821/411393",
    "sg:postcode":"86154",
    "sg:province":"Bayern",
    "wof:name":"A. Rettenberger",
    "wof:placetype":"venue"
},
  "geometry": {"coordinates":[10.8747911453,48.3826522827],"type":"Point"}
}