{
  "type": "Feature",
  "properties": {
    "iso:country":"DE",
    "sg:address":"Kornmarkt 19",
    "sg:city":"Essen",
    "sg:phone":"+49 201/230070",
    "sg:postcode":"45127",
    "sg:province":"Nordrhein-Westfalen",
    "wof:name":"Its Reisecenter",
    "wof:placetype":"venue"
},
  "geometry": {"coordinates":[7.0110940933,51.4574584961],"type":"Point"}
}