{
  "type": "Feature",
  "properties": {
    "iso:country":"DE",
    "sg:address":"Rotdornweg 7",
    "sg:city":"Hemmingen",
    "sg:phone":"+49 5101/58154",
    "sg:postcode":"30966",
    "sg:province":"Niedersachsen",
    "wof:name":"Dtw Immobilien D. Wei\u00dfschuh",
    "wof:placetype":"venue"
},
  "geometry": {"coordinates":[9.7362480164,52.2949066162],"type":"Point"}
}