{
  "type": "Feature",
  "properties": {
    "iso:country":"DE",
    "sg:address":"Lindenstr. 14",
    "sg:city":"K\u00fchbach",
    "sg:phone":"+49 8251/3772",
    "sg:postcode":"86556",
    "sg:province":"Bayern",
    "wof:name":"Augustin Zimmerei- Und Holzbau Gmbh",
    "wof:placetype":"venue"
},
  "geometry": {"coordinates":[11.1904392242,48.4877929688],"type":"Point"}
}