{
  "type": "Feature",
  "properties": {
    "iso:country":"DE",
    "sg:address":"Schmiedeklint 3",
    "sg:city":"Wolfenb\u00fcttel",
    "sg:phone":"+49 5341/25110",
    "sg:postcode":"38304",
    "sg:province":"Niedersachsen",
    "wof:name":"Helmut Meier",
    "wof:placetype":"venue"
},
  "geometry": {"coordinates":[10.463329,52.143856],"type":"Point"}
}