{
  "type": "Feature",
  "properties": {
    "iso:country":"DE",
    "sg:address":"Heisenbergstr. 3",
    "sg:city":"Heilbronn",
    "sg:phone":"+49 7066/7407",
    "sg:postcode":"74078",
    "sg:province":"Baden-W\u00fcrttemberg",
    "wof:name":"Werner Hess",
    "wof:placetype":"venue"
},
  "geometry": {"coordinates":[9.1476535797,49.1916999817],"type":"Point"}
}