{
  "type": "Feature",
  "properties": {
    "iso:country":"DE",
    "sg:address":"Im Kleinen Feldchen 10",
    "sg:city":"Burgschwalbach",
    "sg:phone":"+49 6430/30018",
    "sg:postcode":"65558",
    "sg:province":"Rheinland-Pfalz",
    "wof:name":"I. Lauschke",
    "wof:placetype":"venue"
},
  "geometry": {"coordinates":[8.0820665359,50.2811775208],"type":"Point"}
}