{
  "type": "Feature",
  "properties": {
    "iso:country":"DE",
    "sg:address":"Kiliansgasse 21",
    "sg:city":"Altdorf",
    "sg:phone":"+49 9187/5948",
    "sg:postcode":"90518",
    "sg:province":"Bayern",
    "wof:name":"Elisabets Haarstudio",
    "wof:placetype":"venue"
},
  "geometry": {"coordinates":[11.3567781448,49.386844635],"type":"Point"}
}