{
  "type": "Feature",
  "properties": {
    "iso:country":"DE",
    "sg:address":"Heistedter Str. 21",
    "sg:city":"Heide",
    "sg:phone":"+49 481/8557003",
    "sg:postcode":"25746",
    "sg:province":"Schleswig-Holstein",
    "wof:name":"Cordshagen Und H\u00f6fler Ergotherapeutische Praxis",
    "wof:placetype":"venue"
},
  "geometry": {"coordinates":[9.096183,54.19846],"type":"Point"}
}