{
  "type": "Feature",
  "properties": {
    "iso:country":"DE",
    "sg:address":"Karpfangerstr. 9",
    "sg:city":"Hamburg",
    "sg:phone":"+49 40/362655",
    "sg:postcode":"20459",
    "sg:province":"Hamburg",
    "wof:name":"I. Franckenberg",
    "wof:placetype":"venue"
},
  "geometry": {"coordinates":[9.97704,53.545212],"type":"Point"}
}