{
  "type": "Feature",
  "properties": {
    "iso:country":"DE",
    "sg:address":"Falkenweg 8",
    "sg:city":"Paderborn",
    "sg:phone":"+49 5254/3467",
    "sg:postcode":"33104",
    "sg:province":"Nordrhein-Westfalen",
    "wof:name":"Dieter Olmer",
    "wof:placetype":"venue"
},
  "geometry": {"coordinates":[8.728335,51.765747],"type":"Point"}
}