{
  "type": "Feature",
  "properties": {
    "iso:country":"DE",
    "sg:address":"Horster Str. 17",
    "sg:city":"Bottrop",
    "sg:phone":"+49 2041/687934",
    "sg:postcode":"46236",
    "sg:province":"Nordrhein-Westfalen",
    "wof:name":"Norbert J\u00e4ger",
    "wof:placetype":"venue"
},
  "geometry": {"coordinates":[6.9285621643,51.5230560303],"type":"Point"}
}