{
  "type": "Feature",
  "properties": {
    "iso:country":"DE",
    "sg:address":"Zur Eisenheld 11",
    "sg:city":"Daun",
    "sg:phone":"+49 6592/985471",
    "sg:postcode":"54550",
    "sg:province":"Rheinland-Pfalz",
    "wof:name":"Bfh Planungsb\u00fcro F\u00fcr Haustechnik Gmbh",
    "wof:placetype":"venue"
},
  "geometry": {"coordinates":[6.8152527809,50.1945304871],"type":"Point"}
}