{
  "type": "Feature",
  "properties": {
    "iso:country":"DE",
    "sg:address":"H\u00f6ssen 3",
    "sg:city":"Kal\u00fcbbe",
    "sg:phone":"+49 4526/417",
    "sg:postcode":"24326",
    "sg:province":"Schleswig-Holstein",
    "wof:name":"Hans-j\u00fcrgen Witt",
    "wof:placetype":"venue"
},
  "geometry": {"coordinates":[10.276897,54.11824],"type":"Point"}
}