{
  "type": "Feature",
  "properties": {
    "iso:country":"DE",
    "sg:address":"Alte Lohmarer Str. 13",
    "sg:city":"Lohmar",
    "sg:phone":"+49 2246/4829",
    "sg:postcode":"53797",
    "sg:province":"Nordrhein-Westfalen",
    "wof:name":"Bergsch\u00e4nke",
    "wof:placetype":"venue"
},
  "geometry": {"coordinates":[7.2094430923,50.8349151611],"type":"Point"}
}