{
  "type": "Feature",
  "properties": {
    "iso:country":"DE",
    "sg:address":"Gutenbergstr. 13",
    "sg:city":"Neus\u00e4\u00df",
    "sg:phone":"+49 821/462097",
    "sg:postcode":"86356",
    "sg:province":"Bayern",
    "wof:name":"August Luigart & Sohn Gmbh & Co. Kg",
    "wof:placetype":"venue"
},
  "geometry": {"coordinates":[10.8282909393,48.3970565796],"type":"Point"}
}