{
  "type": "Feature",
  "properties": {
    "iso:country":"DE",
    "sg:address":"Burgstr. 4",
    "sg:city":"Wernigerode",
    "sg:phone":"+49 3943/905883",
    "sg:postcode":"38855",
    "sg:province":"Sachsen-Anhalt",
    "wof:name":"Keradent-dentaltechnik Gmbh",
    "wof:placetype":"venue"
},
  "geometry": {"coordinates":[10.787996,51.83427],"type":"Point"}
}