{
  "type": "Feature",
  "properties": {
    "iso:country":"DE",
    "sg:address":"Ahornweg 1",
    "sg:city":"Miesbach",
    "sg:phone":"+49 8025/5555",
    "sg:postcode":"83714",
    "sg:province":"Bayern",
    "wof:name":"Clm Langheiter Verlags-gmbh",
    "wof:placetype":"venue"
},
  "geometry": {"coordinates":[11.8358983994,47.7821388245],"type":"Point"}
}