{
  "type": "Feature",
  "properties": {
    "iso:country":"DE",
    "sg:address":"Breite Str. 16",
    "sg:city":"Recklinghausen",
    "sg:phone":"+49 2361/93600",
    "sg:postcode":"45657",
    "sg:province":"Nordrhein-Westfalen",
    "wof:name":"Quelle Ag & Co.",
    "wof:placetype":"venue"
},
  "geometry": {"coordinates":[7.197136,51.612965],"type":"Point"}
}