{
  "type": "Feature",
  "properties": {
    "iso:country":"DE",
    "sg:address":"D\u00fcsseldorfer Str. 40",
    "sg:city":"Viersen",
    "sg:phone":"+49 2162/67551",
    "sg:postcode":"41749",
    "sg:province":"Nordrhein-Westfalen",
    "wof:name":"Sport Von Den Bruck",
    "wof:placetype":"venue"
},
  "geometry": {"coordinates":[6.373201,51.281406],"type":"Point"}
}