{
  "type": "Feature",
  "properties": {
    "iso:country":"DE",
    "sg:address":"Frankfurter Allee 54",
    "sg:city":"Berlin",
    "sg:phone":"+49 30/2912775",
    "sg:postcode":"10247",
    "sg:province":"Berlin",
    "wof:name":"Dr. Med. Horst Lindecke Arzt F\u00fcr Gyn\u00e4kologie",
    "wof:placetype":"venue"
},
  "geometry": {"coordinates":[13.4651918411,52.514465332],"type":"Point"}
}