{
  "type": "Feature",
  "properties": {
    "iso:country":"DE",
    "sg:address":"Raiffeisenstr. 20",
    "sg:city":"Gro\u00dfbardorf",
    "sg:phone":"+49 9766/646",
    "sg:postcode":"97633",
    "sg:province":"Bayern",
    "wof:name":"Peter Dahinten",
    "wof:placetype":"venue"
},
  "geometry": {"coordinates":[10.367645,50.269619],"type":"Point"}
}