{
  "type": "Feature",
  "properties": {
    "iso:country":"DE",
    "sg:address":"Raiffeisenstr. 5",
    "sg:city":"Hirschaid",
    "sg:phone":"+49 9543/3475",
    "sg:postcode":"96114",
    "sg:province":"Bayern",
    "wof:name":"Franz Behr",
    "wof:placetype":"venue"
},
  "geometry": {"coordinates":[10.926109,49.799133],"type":"Point"}
}