{
  "type": "Feature",
  "properties": {
    "iso:country":"DE",
    "sg:address":"Uhlbergstr. 40",
    "sg:city":"Filderstadt",
    "sg:phone":"+49 711/774027",
    "sg:postcode":"70794",
    "sg:province":"Baden-W\u00fcrttemberg",
    "wof:name":"Stauch",
    "wof:placetype":"venue"
},
  "geometry": {"coordinates":[9.1974258423,48.6533927917],"type":"Point"}
}