{
  "type": "Feature",
  "properties": {
    "iso:country":"DE",
    "sg:address":"Senefelderstr. 2",
    "sg:city":"Wiesbaden",
    "sg:phone":"+49 6122/941860",
    "sg:postcode":"65205",
    "sg:province":"Hessen",
    "wof:name":"Bl Br\u00fchl Datensysteme Inh. Roland Br\u00fchl",
    "wof:placetype":"venue"
},
  "geometry": {"coordinates":[8.3450260162,50.0597305298],"type":"Point"}
}