{
  "type": "Feature",
  "properties": {
    "iso:country":"DE",
    "sg:address":"Str d Einheit 40",
    "sg:city":"Uder",
    "sg:phone":"+49 36083/2243",
    "sg:postcode":"37318",
    "sg:province":"Th\u00fcringen",
    "wof:name":"Volksbank Heiligenstadt E.g.",
    "wof:placetype":"venue"
},
  "geometry": {"coordinates":[10.076003,51.362633],"type":"Point"}
}