{
  "type": "Feature",
  "properties": {
    "iso:country":"DE",
    "sg:address":"Annenstr. 136",
    "sg:city":"Witten",
    "sg:phone":"+49 2302/962071",
    "sg:postcode":"58453",
    "sg:province":"Nordrhein-Westfalen",
    "wof:name":"Foto Werner Brinkmann",
    "wof:placetype":"venue"
},
  "geometry": {"coordinates":[7.371282,51.445873],"type":"Point"}
}