{
  "type": "Feature",
  "properties": {
    "iso:country":"DE",
    "sg:address":"Frenser Str. 16",
    "sg:city":"Bergheim",
    "sg:phone":"+49 2271/798500",
    "sg:postcode":"50127",
    "sg:province":"Nordrhein-Westfalen",
    "wof:name":"Lutz Barck & Martin Theil Gbr",
    "wof:placetype":"venue"
},
  "geometry": {"coordinates":[6.6843910217,50.9373855591],"type":"Point"}
}