{
  "type": "Feature",
  "properties": {
    "iso:country":"DE",
    "sg:address":"Wilhelmstr. 75",
    "sg:city":"Wittingen",
    "sg:phone":"+49 5836/308",
    "sg:postcode":"29378",
    "sg:province":"Niedersachsen",
    "wof:name":"Heinrich Otto",
    "wof:placetype":"venue"
},
  "geometry": {"coordinates":[10.86279,52.645821],"type":"Point"}
}