{
  "type": "Feature",
  "properties": {
    "iso:country":"DE",
    "sg:address":"Heustr. 2",
    "sg:city":"Kaiserslautern",
    "sg:phone":"+49 631/73919",
    "sg:postcode":"67659",
    "sg:province":"Rheinland-Pfalz",
    "wof:name":"Peter Wagner",
    "wof:placetype":"venue"
},
  "geometry": {"coordinates":[7.7386870384,49.4409675598],"type":"Point"}
}