{
  "type": "Feature",
  "properties": {
    "iso:country":"DE",
    "sg:address":"Tulpenstr. 3",
    "sg:city":"F\u00fcrstenfeldbruck",
    "sg:phone":"+49 8141/63710",
    "sg:postcode":"82256",
    "sg:province":"Bayern",
    "wof:name":"Richard Mayer",
    "wof:placetype":"venue"
},
  "geometry": {"coordinates":[11.266176,48.174011],"type":"Point"}
}