{
  "type": "Feature",
  "properties": {
    "iso:country":"DE",
    "sg:address":"Uhlendiekstr. 103-107",
    "sg:city":"B\u00fcnde",
    "sg:phone":"+49 4968/949610",
    "sg:postcode":"32257",
    "sg:province":"Nordrhein-Westfalen",
    "wof:name":"Saar Pr\u00c4zision Gmbh",
    "wof:placetype":"venue"
},
  "geometry": {"coordinates":[7.101089,49.272285],"type":"Point"}
}