{
  "type": "Feature",
  "properties": {
    "iso:country":"DE",
    "sg:address":"Bahnhofstr. 16b",
    "sg:city":"Passau",
    "sg:phone":"+49 851/753639",
    "sg:postcode":"94032",
    "sg:province":"Bayern",
    "wof:name":"Smiline Dentallabor Mehlsam Ohg",
    "wof:placetype":"venue"
},
  "geometry": {"coordinates":[13.45267,48.574371],"type":"Point"}
}