{
  "type": "Feature",
  "properties": {
    "iso:country":"DE",
    "sg:address":"Mannheimer Str. 13",
    "sg:city":"Br\u00fchl",
    "sg:phone":"+49 6202/71813",
    "sg:postcode":"68782",
    "sg:province":"Baden-W\u00fcrttemberg",
    "wof:name":"Karl M\u00fcndel Bauschlosserei",
    "wof:placetype":"venue"
},
  "geometry": {"coordinates":[8.53445,49.396202],"type":"Point"}
}