{
  "type": "Feature",
  "properties": {
    "iso:country":"DE",
    "sg:address":"Rosenplatz 23a",
    "sg:city":"Osnabr\u00fcck",
    "sg:phone":"+49 541/82665",
    "sg:postcode":"49074",
    "sg:province":"Niedersachsen",
    "wof:name":"Restaurant Vital",
    "wof:placetype":"venue"
},
  "geometry": {"coordinates":[8.0533027649,52.2657165527],"type":"Point"}
}