{
  "type": "Feature",
  "properties": {
    "iso:country":"DE",
    "sg:address":"Lindenallee 32",
    "sg:city":"Bad Orb",
    "sg:phone":"+49 6052/2468",
    "sg:postcode":"63619",
    "sg:province":"Hessen",
    "wof:name":"Kurpension Specht Raimund Neveling",
    "wof:placetype":"venue"
},
  "geometry": {"coordinates":[9.349981308,50.2180366516],"type":"Point"}
}