{
  "type": "Feature",
  "properties": {
    "iso:country":"DE",
    "sg:address":"Vaderkeborg",
    "sg:city":"Leer",
    "sg:phone":"+49 491/3333",
    "sg:postcode":"26789",
    "sg:province":"Niedersachsen",
    "wof:name":"Kino-center Leer 4 Kinos Delicityroxyurania",
    "wof:placetype":"venue"
},
  "geometry": {"coordinates":[7.460708,53.230553],"type":"Point"}
}