{
  "type": "Feature",
  "properties": {
    "iso:country":"DE",
    "sg:address":"Geraer Str. 6",
    "sg:city":"Stadtroda",
    "sg:phone":"+49 36428/62260",
    "sg:postcode":"07646",
    "sg:province":"Th\u00fcringen",
    "wof:name":"M. St\u00f6ckel",
    "wof:placetype":"venue"
},
  "geometry": {"coordinates":[11.728014946,50.8578605652],"type":"Point"}
}