{
  "type": "Feature",
  "properties": {
    "iso:country":"DE",
    "sg:address":"Otto-Conrad-Str. 1",
    "sg:city":"Rhaunen",
    "sg:phone":"+49 6544/1000",
    "sg:postcode":"55624",
    "sg:province":"Rheinland-Pfalz",
    "wof:name":"Gernot Papzien Rechtsanwalt",
    "wof:placetype":"venue"
},
  "geometry": {"coordinates":[7.3460550308,49.8642120361],"type":"Point"}
}