{
  "type": "Feature",
  "properties": {
    "iso:country":"DE",
    "sg:address":"Frankfurter Str. 2",
    "sg:city":"Schkeuditz",
    "sg:phone":"+49 341/4672011",
    "sg:postcode":"04435",
    "sg:province":"Sachsen",
    "wof:name":"Robert Scharpf Bau-consult Gmbh",
    "wof:placetype":"venue"
},
  "geometry": {"coordinates":[12.198274,51.398632],"type":"Point"}
}