{
  "type": "Feature",
  "properties": {
    "iso:country":"DE",
    "sg:address":"Otto-Br\u00fcgmann-Str. 11",
    "sg:city":"Geesthacht",
    "sg:phone":"+49 4152/2394",
    "sg:postcode":"21502",
    "sg:province":"Schleswig-Holstein",
    "wof:name":"A. H. Gr\u00fcnwaldt Pferdeschlachterei",
    "wof:placetype":"venue"
},
  "geometry": {"coordinates":[10.3782320023,53.4311676025],"type":"Point"}
}