{
  "type": "Feature",
  "properties": {
    "iso:country":"DE",
    "sg:address":"Am Stadion 40",
    "sg:city":"Recklinghausen",
    "sg:phone":"+49 4923/6191920",
    "sg:postcode":"45659",
    "sg:province":"Nordrhein-Westfalen",
    "wof:name":"Cyrus Gmbh",
    "wof:placetype":"venue"
},
  "geometry": {"coordinates":[7.189496,51.5979],"type":"Point"}
}