{
  "type": "Feature",
  "properties": {
    "iso:country":"DE",
    "sg:address":"Neuenwalde 2",
    "sg:city":"Damme",
    "sg:phone":"+49 5491/5101",
    "sg:postcode":"49401",
    "sg:province":"Niedersachsen",
    "wof:name":"H. Klebeck",
    "wof:placetype":"venue"
},
  "geometry": {"coordinates":[8.1531133652,52.5025367737],"type":"Point"}
}