{
  "type": "Feature",
  "properties": {
    "iso:country":"DE",
    "sg:address":"Dieselstr. 6",
    "sg:city":"Reutlingen",
    "sg:postcode":"72770",
    "sg:province":"Baden-W\u00fcrttemberg",
    "wof:name":"Telma Telefon- Und Marketing Service Gmbh",
    "wof:placetype":"venue"
},
  "geometry": {"coordinates":[9.185641,48.500076],"type":"Point"}
}