{
  "type": "Feature",
  "properties": {
    "iso:country":"DE",
    "sg:address":"M\u00fcnsterstr. 165",
    "sg:city":"D\u00fcsseldorf",
    "sg:phone":"+49 211/488278",
    "sg:postcode":"40476",
    "sg:province":"Nordrhein-Westfalen",
    "wof:name":"De Luca",
    "wof:placetype":"venue"
},
  "geometry": {"coordinates":[6.7921280861,51.246257782],"type":"Point"}
}