{
  "type": "Feature",
  "properties": {
    "iso:country":"DE",
    "sg:address":"M\u00fcllritterweg 1 A",
    "sg:city":"Ruhpolding",
    "sg:phone":"+49 8663/883944",
    "sg:postcode":"83324",
    "sg:province":"Bayern",
    "wof:name":"Kaesberg",
    "wof:placetype":"venue"
},
  "geometry": {"coordinates":[12.6467809677,47.7620506287],"type":"Point"}
}