{
  "type": "Feature",
  "properties": {
    "iso:country":"DE",
    "sg:address":"Bergstr. 6",
    "sg:city":"Celle",
    "sg:phone":"+49 5141/22402",
    "sg:postcode":"29221",
    "sg:province":"Niedersachsen",
    "wof:name":"Foto Margraf Inh. Horst Bremer",
    "wof:placetype":"venue"
},
  "geometry": {"coordinates":[10.0836334229,52.6232948303],"type":"Point"}
}