{
  "type": "Feature",
  "properties": {
    "iso:country":"DE",
    "sg:address":"Wilhelmstr. 132",
    "sg:city":"Betzdorf",
    "sg:phone":"+49 2741/22324",
    "sg:postcode":"57518",
    "sg:province":"Rheinland-Pfalz",
    "wof:name":"F. K. Schmidt",
    "wof:placetype":"venue"
},
  "geometry": {"coordinates":[7.8619880676,50.7967987061],"type":"Point"}
}