{
  "type": "Feature",
  "properties": {
    "iso:country":"DE",
    "sg:address":"Haar-Siedlung 12",
    "sg:city":"Haren",
    "sg:phone":"+49 5932/5333",
    "sg:postcode":"49733",
    "sg:province":"Niedersachsen",
    "wof:name":"Eltro Data Gmbh",
    "wof:placetype":"venue"
},
  "geometry": {"coordinates":[7.1396589279,52.7898406982],"type":"Point"}
}