{
  "type": "Feature",
  "properties": {
    "iso:country":"DE",
    "sg:address":"Buigenrainstr. 40",
    "sg:city":"M\u00f6nsheim",
    "sg:phone":"+49 7044/7273",
    "sg:postcode":"71297",
    "sg:province":"Baden-W\u00fcrttemberg",
    "wof:name":"Dieter Wehner",
    "wof:placetype":"venue"
},
  "geometry": {"coordinates":[8.866727829,48.8632965088],"type":"Point"}
}