{
  "type": "Feature",
  "properties": {
    "iso:country":"DE",
    "sg:address":"Raasdorfer Str. 16",
    "sg:city":"Mohlsdorf",
    "sg:phone":"+49 3661/430174",
    "sg:postcode":"07987",
    "sg:province":"Th\u00fcringen",
    "wof:name":"Metallbau Jahn Gmbh",
    "wof:placetype":"venue"
},
  "geometry": {"coordinates":[12.254597,50.67215],"type":"Point"}
}