{
  "type": "Feature",
  "properties": {
    "iso:country":"DE",
    "sg:address":"F\u00fcrstenrieder Str. 262",
    "sg:city":"M\u00fcnchen",
    "sg:phone":"+49 89/74160434",
    "sg:postcode":"81377",
    "sg:province":"Bayern",
    "wof:name":"Walla Rehatechnik Handels Gmbh",
    "wof:placetype":"venue"
},
  "geometry": {"coordinates":[11.502122,48.115921],"type":"Point"}
}