{
  "type": "Feature",
  "properties": {
    "iso:country":"DE",
    "sg:address":"Sudhoferweg 19",
    "sg:city":"Beckum",
    "sg:phone":"+49 2521/6868",
    "sg:postcode":"59269",
    "sg:province":"Nordrhein-Westfalen",
    "wof:name":"Krull Gmbh",
    "wof:placetype":"venue"
},
  "geometry": {"coordinates":[8.059085,51.756603],"type":"Point"}
}