{
  "type": "Feature",
  "properties": {
    "iso:country":"DE",
    "sg:address":"Weimarer Str. 17",
    "sg:city":"Neuss",
    "sg:phone":"+49 2131/745580",
    "sg:postcode":"41472",
    "sg:province":"Nordrhein-Westfalen",
    "wof:name":"Georg Stolz Gesellschaft F\u00fcr Unternehmensberatung Mbh",
    "wof:placetype":"venue"
},
  "geometry": {"coordinates":[6.6711711884,51.1608581543],"type":"Point"}
}