{
  "type": "Feature",
  "properties": {
    "iso:country":"DE",
    "sg:address":"Hekeser Str. 15",
    "sg:city":"Berge",
    "sg:phone":"+49 5435/2044",
    "sg:postcode":"49626",
    "sg:province":"Niedersachsen",
    "wof:name":"H. Wolke",
    "wof:placetype":"venue"
},
  "geometry": {"coordinates":[7.7608342171,52.6068534851],"type":"Point"}
}