{
  "type": "Feature",
  "properties": {
    "iso:country":"DE",
    "sg:address":"Rastenburger Str. 8",
    "sg:city":"Mannheim",
    "sg:phone":"+49 621/782860",
    "sg:postcode":"68307",
    "sg:province":"Baden-W\u00fcrttemberg",
    "wof:name":"U. Neumann",
    "wof:placetype":"venue"
},
  "geometry": {"coordinates":[8.4693508148,49.5507316589],"type":"Point"}
}