{
  "type": "Feature",
  "properties": {
    "iso:country":"DE",
    "sg:address":"Sondernau 18",
    "sg:city":"Oberelsbach",
    "sg:phone":"+49 9774/1219",
    "sg:postcode":"97656",
    "sg:province":"Bayern",
    "wof:name":"G. Hergenhan",
    "wof:placetype":"venue"
},
  "geometry": {"coordinates":[10.1195850372,50.4413909912],"type":"Point"}
}