{
  "type": "Feature",
  "properties": {
    "iso:country":"DE",
    "sg:address":"Friedensring 25",
    "sg:city":"Kerpen",
    "sg:postcode":"50171",
    "sg:province":"Nordrhein-Westfalen",
    "wof:name":"Restaurant J\u00e4gerhof Kerpen E. K.",
    "wof:placetype":"venue"
},
  "geometry": {"coordinates":[6.6958398819,50.8764190674],"type":"Point"}
}