{
  "type": "Feature",
  "properties": {
    "iso:country":"DE",
    "sg:address":"Kriegsstr. 246",
    "sg:city":"Karlsruhe",
    "sg:phone":"+49 721/859521",
    "sg:postcode":"76135",
    "sg:province":"Baden-W\u00fcrttemberg",
    "wof:name":"Eggler Dennig Und Rehm Rechtsanw\u00e4lte",
    "wof:placetype":"venue"
},
  "geometry": {"coordinates":[8.3784418106,49.0057907104],"type":"Point"}
}