{
  "type": "Feature",
  "properties": {
    "iso:country":"DE",
    "sg:address":"Mindener Str. 64",
    "sg:city":"Rehburg-Loccum",
    "sg:phone":"+49 5766/1308",
    "sg:postcode":"31547",
    "sg:province":"Niedersachsen",
    "wof:name":"Christa Schnepel",
    "wof:placetype":"venue"
},
  "geometry": {"coordinates":[9.1233978271,52.4460067749],"type":"Point"}
}