{
  "type": "Feature",
  "properties": {
    "iso:country":"DE",
    "sg:address":"Bonhoefferplatz 7",
    "sg:city":"Dresden",
    "sg:phone":"+49 351/4213531",
    "sg:postcode":"01159",
    "sg:province":"Sachsen",
    "wof:name":"Ernst-g\u00fcnther Sprung",
    "wof:placetype":"venue"
},
  "geometry": {"coordinates":[13.7030391693,51.0386123657],"type":"Point"}
}