{
  "type": "Feature",
  "properties": {
    "iso:country":"DE",
    "sg:address":"\u00c4usserer Stadtmauerweg 4",
    "sg:city":"Neustadt an der Aisch",
    "sg:phone":"+49 9161/8957020",
    "sg:postcode":"91413",
    "sg:province":"Bayern",
    "wof:name":"Pareto Analysen",
    "wof:placetype":"venue"
},
  "geometry": {"coordinates":[10.610197,49.578396],"type":"Point"}
}