{
  "type": "Feature",
  "properties": {
    "iso:country":"DE",
    "sg:address":"Schumannstr. 5",
    "sg:city":"Frankfurt",
    "sg:phone":"+49 69/746092",
    "sg:postcode":"60325",
    "sg:province":"Hessen",
    "wof:name":"Bsi Bau-, Sanierungs- Und Instandhaltungs Gmbh",
    "wof:placetype":"venue"
},
  "geometry": {"coordinates":[8.6545257568,50.1133651733],"type":"Point"}
}