{
  "type": "Feature",
  "properties": {
    "iso:country":"DE",
    "sg:address":"Adlzreiterstr. 12",
    "sg:city":"M\u00fcnchen",
    "sg:phone":"+49 89/774840",
    "sg:postcode":"80337",
    "sg:province":"Bayern",
    "wof:name":"Ivan M\u00fcller",
    "wof:placetype":"venue"
},
  "geometry": {"coordinates":[11.5556602478,48.1271476746],"type":"Point"}
}