{
  "type": "Feature",
  "properties": {
    "iso:country":"DE",
    "sg:address":"Oberschlatzendorf 4",
    "sg:city":"Viechtach",
    "sg:phone":"+49 9942/1449",
    "sg:postcode":"94234",
    "sg:province":"Bayern",
    "wof:name":"Enk\u00dc K\u00dchlm\u00d6belbau Gmbh",
    "wof:placetype":"venue"
},
  "geometry": {"coordinates":[12.88307,49.065987],"type":"Point"}
}