{
  "type": "Feature",
  "properties": {
    "iso:country":"DE",
    "sg:address":"Burger Str. 40",
    "sg:city":"Remscheid",
    "sg:phone":"+49 2191/341116",
    "sg:postcode":"42859",
    "sg:province":"Nordrhein-Westfalen",
    "wof:name":"B. Pohl",
    "wof:placetype":"venue"
},
  "geometry": {"coordinates":[7.2064781189,51.1712036133],"type":"Point"}
}