{
  "type": "Feature",
  "properties": {
    "iso:country":"DE",
    "sg:address":"Nu\u00dfallee 8",
    "sg:city":"H\u00fcrth",
    "sg:phone":"+49 2233/42258",
    "sg:postcode":"50354",
    "sg:province":"Nordrhein-Westfalen",
    "wof:name":"Johannes Nenner Elektroinstallation",
    "wof:placetype":"venue"
},
  "geometry": {"coordinates":[6.887639,50.865177],"type":"Point"}
}