{
  "type": "Feature",
  "properties": {
    "iso:country":"DE",
    "sg:address":"Altkaditz 4",
    "sg:city":"Dresden",
    "sg:phone":"+49 351/8384884",
    "sg:postcode":"01139",
    "sg:province":"Sachsen",
    "wof:name":"Wagert",
    "wof:placetype":"venue"
},
  "geometry": {"coordinates":[13.6738786697,51.0820655823],"type":"Point"}
}