{
  "type": "Feature",
  "properties": {
    "iso:country":"DE",
    "sg:address":"G\u00fcltlinger Str. 21",
    "sg:city":"Calw",
    "sg:phone":"+49 7053/3146",
    "sg:postcode":"75365",
    "sg:province":"Baden-W\u00fcrttemberg",
    "wof:name":"Erwin Meister",
    "wof:placetype":"venue"
},
  "geometry": {"coordinates":[8.7467756271,48.6586151123],"type":"Point"}
}