{
  "type": "Feature",
  "properties": {
    "iso:country":"DE",
    "sg:address":"Am Kellerberg 1",
    "sg:city":"Speinshart",
    "sg:phone":"+49 9645/601990",
    "sg:postcode":"92676",
    "sg:province":"Bayern",
    "wof:name":"Tmg Tremmersdorfer Maschinenbau Gmbh",
    "wof:placetype":"venue"
},
  "geometry": {"coordinates":[11.814133,49.778908],"type":"Point"}
}