{
  "type": "Feature",
  "properties": {
    "iso:country":"DE",
    "sg:address":"Dorfstr. 32",
    "sg:city":"Neugrimnitz",
    "sg:phone":"+49 33361/833",
    "sg:postcode":"16247",
    "sg:province":"Brandenburg",
    "wof:name":"Landwirtschaftsbetrieb Neugrimnitz Gmbh",
    "wof:placetype":"venue"
},
  "geometry": {"coordinates":[13.829286,52.974957],"type":"Point"}
}