{
  "type": "Feature",
  "properties": {
    "iso:country":"DE",
    "sg:address":"Neuhauser Str. 20",
    "sg:city":"Villingen-Schwenningen",
    "sg:phone":"+49 7721/70520",
    "sg:postcode":"78052",
    "sg:province":"Baden-W\u00fcrttemberg",
    "wof:name":"Vera Und Hans Zimmermann",
    "wof:placetype":"venue"
},
  "geometry": {"coordinates":[8.467052,48.107937],"type":"Point"}
}