{
  "type": "Feature",
  "properties": {
    "iso:country":"DE",
    "sg:address":"Kapfweg 16",
    "sg:city":"Schemmerhofen",
    "sg:phone":"+49 7356/665",
    "sg:postcode":"88433",
    "sg:province":"Baden-W\u00fcrttemberg",
    "wof:name":"Bruno Birk Ingenieur",
    "wof:placetype":"venue"
},
  "geometry": {"coordinates":[9.7944192886,48.1849708557],"type":"Point"}
}