{
  "type": "Feature",
  "properties": {
    "iso:country":"DE",
    "sg:address":"Vor dem Dammtor 18",
    "sg:city":"Hornburg",
    "sg:phone":"+49 5334/1430",
    "sg:postcode":"38315",
    "sg:province":"Niedersachsen",
    "wof:name":"Verkehrsbetriebe Bachstein Gmbh",
    "wof:placetype":"venue"
},
  "geometry": {"coordinates":[10.600774765,52.0303497314],"type":"Point"}
}