{
  "type": "Feature",
  "properties": {
    "iso:country":"DE",
    "sg:address":"Kehrstr. 87",
    "sg:city":"Rheinbrohl",
    "sg:phone":"+49 2635/3834",
    "sg:postcode":"56598",
    "sg:province":"Rheinland-Pfalz",
    "wof:name":"Gasthaus Zur Schweiz",
    "wof:placetype":"venue"
},
  "geometry": {"coordinates":[7.334127903,50.4941368103],"type":"Point"}
}