{
  "type": "Feature",
  "properties": {
    "iso:country":"DE",
    "sg:address":"Rabenhorst 23",
    "sg:city":"Nienburg",
    "sg:phone":"+49 5021/926025",
    "sg:postcode":"31582",
    "sg:province":"Niedersachsen",
    "wof:name":"Walter Rochow",
    "wof:placetype":"venue"
},
  "geometry": {"coordinates":[9.205283,52.622356],"type":"Point"}
}