{
  "type": "Feature",
  "properties": {
    "iso:country":"DE",
    "sg:address":"Haltestellenweg 12",
    "sg:city":"Kronach",
    "sg:phone":"+49 9261/2590",
    "sg:postcode":"96317",
    "sg:province":"Bayern",
    "wof:name":"Oskar B\u00e4r",
    "wof:placetype":"venue"
},
  "geometry": {"coordinates":[11.3077630997,50.2151069641],"type":"Point"}
}