{
  "type": "Feature",
  "properties": {
    "iso:country":"DE",
    "sg:address":"Holzweg 2",
    "sg:city":"Oberursel",
    "sg:phone":"+49 6171/52625",
    "sg:postcode":"61440",
    "sg:province":"Hessen",
    "wof:name":"H. Zellmer",
    "wof:placetype":"venue"
},
  "geometry": {"coordinates":[8.581064,50.202026],"type":"Point"}
}