{
  "type": "Feature",
  "properties": {
    "iso:country":"DE",
    "sg:address":"Romanstr. 3",
    "sg:city":"Bayreuth",
    "sg:phone":"+49 921/30832",
    "sg:postcode":"95444",
    "sg:province":"Bayern",
    "wof:name":"Alfred Herath",
    "wof:placetype":"venue"
},
  "geometry": {"coordinates":[11.5824403763,49.9423065186],"type":"Point"}
}