{
  "type": "Feature",
  "properties": {
    "iso:country":"DE",
    "sg:address":"Bahnhofstr. 118",
    "sg:city":"Tuttlingen",
    "sg:phone":"+49 7461/3302",
    "sg:postcode":"78532",
    "sg:province":"Baden-W\u00fcrttemberg",
    "wof:name":"A. Niggel",
    "wof:placetype":"venue"
},
  "geometry": {"coordinates":[8.8033208847,47.9815330505],"type":"Point"}
}