{
  "type": "Feature",
  "properties": {
    "iso:country":"DE",
    "sg:address":"Vogelweideplatz 1",
    "sg:city":"M\u00fcnchen",
    "sg:phone":"+49 89/4708081",
    "sg:postcode":"81677",
    "sg:province":"Bayern",
    "wof:name":"Aliger Reisen Kg",
    "wof:placetype":"venue"
},
  "geometry": {"coordinates":[11.619244,48.137794],"type":"Point"}
}