{
  "type": "Feature",
  "properties": {
    "iso:country":"DE",
    "sg:address":"Neust\u00e4dter Str. 4",
    "sg:city":"Westerkappeln",
    "sg:phone":"+49 5404/2925",
    "sg:postcode":"49492",
    "sg:province":"Nordrhein-Westfalen",
    "wof:name":"Hans Diepen",
    "wof:placetype":"venue"
},
  "geometry": {"coordinates":[7.8785,52.315407],"type":"Point"}
}