{
  "type": "Feature",
  "properties": {
    "iso:country":"DE",
    "sg:address":"Kopenhagener Str. 9",
    "sg:city":"Berlin",
    "sg:phone":"+49 30/44319660",
    "sg:postcode":"10437",
    "sg:province":"Berlin",
    "wof:name":"K. Herb Bau- Und Vertriebs- Betreuung Gmbh & Co. Kg",
    "wof:placetype":"venue"
},
  "geometry": {"coordinates":[13.410776,52.549007],"type":"Point"}
}