{
  "type": "Feature",
  "properties": {
    "iso:country":"DE",
    "sg:address":"Zeughausstr. 8",
    "sg:city":"Meschede",
    "sg:phone":"+49 291/9529810",
    "sg:postcode":"59872",
    "sg:province":"Nordrhein-Westfalen",
    "wof:name":"F. Sauer-schmuck Und Optik Gmbh",
    "wof:placetype":"venue"
},
  "geometry": {"coordinates":[8.2850837708,51.3459663391],"type":"Point"}
}