{
  "type": "Feature",
  "properties": {
    "iso:country":"DE",
    "sg:address":"Haferkuhle 3",
    "sg:city":"Uchte",
    "sg:phone":"+49 5763/96160",
    "sg:postcode":"31600",
    "sg:province":"Niedersachsen",
    "wof:name":"Betonwerk Uchte Gmbh",
    "wof:placetype":"venue"
},
  "geometry": {"coordinates":[8.8989152908,52.4820289612],"type":"Point"}
}