{
  "type": "Feature",
  "properties": {
    "iso:country":"DE",
    "sg:address":"Pr\u00e4sidentenstr. 27",
    "sg:city":"Bergkamen",
    "sg:phone":"+49 2307/83991",
    "sg:postcode":"59192",
    "sg:province":"Nordrhein-Westfalen",
    "wof:name":"Bac",
    "wof:placetype":"venue"
},
  "geometry": {"coordinates":[7.6400060654,51.6184310913],"type":"Point"}
}