{
  "type": "Feature",
  "properties": {
    "iso:country":"DE",
    "sg:address":"Am Sch\u00f6nblick 3",
    "sg:city":"Leonberg",
    "sg:phone":"+49 7152/905991",
    "sg:postcode":"71229",
    "sg:province":"Baden-W\u00fcrttemberg",
    "wof:name":"Hausverwaltung Seifert & Partner Kg",
    "wof:placetype":"venue"
},
  "geometry": {"coordinates":[8.9587812424,48.7916030884],"type":"Point"}
}