{
  "type": "Feature",
  "properties": {
    "iso:country":"DE",
    "sg:address":"Platz an der Schmiede 3",
    "sg:city":"Witten",
    "sg:phone":"+49 2302/760114",
    "sg:postcode":"58456",
    "sg:province":"Nordrhein-Westfalen",
    "wof:name":"Messetermine By Solarconnect",
    "wof:placetype":"venue"
},
  "geometry": {"coordinates":[7.28128,51.423904],"type":"Point"}
}