{
  "type": "Feature",
  "properties": {
    "iso:country":"DE",
    "sg:address":"Lange Str. 45",
    "sg:city":"Dannenberg",
    "sg:phone":"+49 5861/8454",
    "sg:postcode":"29451",
    "sg:province":"Niedersachsen",
    "wof:name":"August L\u00f6ffler Inh. Matthias Hagemann E. K.",
    "wof:placetype":"venue"
},
  "geometry": {"coordinates":[11.0903453827,53.0966796875],"type":"Point"}
}