{
  "type": "Feature",
  "properties": {
    "iso:country":"DE",
    "sg:address":"Meckenheimer Str. 39",
    "sg:city":"Weilerswist",
    "sg:phone":"+49 2254/1350",
    "sg:postcode":"53919",
    "sg:province":"Nordrhein-Westfalen",
    "wof:name":"Zur Schmiede",
    "wof:placetype":"venue"
},
  "geometry": {"coordinates":[6.8888368607,50.736114502],"type":"Point"}
}