{
  "type": "Feature",
  "properties": {
    "iso:country":"DE",
    "sg:address":"Rheinstr. 41",
    "sg:city":"H\u00f6hr-Grenzhausen",
    "sg:phone":"+49 2624/9110",
    "sg:postcode":"56203",
    "sg:province":"Rheinland-Pfalz",
    "wof:name":"Redaktion L\u00f6hnberg-nachrichten Verlag & Druck Wittich",
    "wof:placetype":"venue"
},
  "geometry": {"coordinates":[7.6663928032,50.431968689],"type":"Point"}
}