{
  "type": "Feature",
  "properties": {
    "iso:country":"DE",
    "sg:address":"Am Kotten 11",
    "sg:city":"Gevelsberg",
    "sg:phone":"+49 2332/14756",
    "sg:postcode":"58285",
    "sg:province":"Nordrhein-Westfalen",
    "wof:name":"M. Petig Immobilienmakler",
    "wof:placetype":"venue"
},
  "geometry": {"coordinates":[7.3199081421,51.3150405884],"type":"Point"}
}