{
  "type": "Feature",
  "properties": {
    "iso:country":"DE",
    "sg:address":"Bergstr. 44",
    "sg:city":"Solingen",
    "sg:phone":"+49 4921/2209040",
    "sg:postcode":"42651",
    "sg:province":"Nordrhein-Westfalen",
    "wof:name":"S. Schilling Gbr",
    "wof:placetype":"venue"
},
  "geometry": {"coordinates":[7.078318,51.169502],"type":"Point"}
}