{
  "type": "Feature",
  "properties": {
    "iso:country":"DE",
    "sg:address":"Luitpoldstr. 58",
    "sg:city":"Landshut",
    "sg:phone":"+49 871/61138",
    "sg:postcode":"84034",
    "sg:province":"Bayern",
    "wof:name":"Dr. Ulrich Wesche",
    "wof:placetype":"venue"
},
  "geometry": {"coordinates":[12.1398544312,48.5422782898],"type":"Point"}
}