{
  "type": "Feature",
  "properties": {
    "iso:country":"DE",
    "sg:address":"Lange Str. 91-95",
    "sg:city":"Delmenhorst",
    "sg:phone":"+49 4221/1040",
    "sg:postcode":"27749",
    "sg:province":"Niedersachsen",
    "wof:name":"Karstadt Warenhaus Ag",
    "wof:placetype":"venue"
},
  "geometry": {"coordinates":[8.631709,53.048817],"type":"Point"}
}