{
  "type": "Feature",
  "properties": {
    "iso:country":"DE",
    "sg:address":"Lauterlech 49",
    "sg:city":"Augsburg",
    "sg:postcode":"86152",
    "sg:province":"Bayern",
    "wof:name":"Ev. Method. Pfarramt",
    "wof:placetype":"venue"
},
  "geometry": {"coordinates":[10.9032936096,48.3728103638],"type":"Point"}
}