{
  "type": "Feature",
  "properties": {
    "iso:country":"DE",
    "sg:address":"Meppener Str. 38",
    "sg:city":"Lingen",
    "sg:phone":"+49 591/3658",
    "sg:postcode":"49808",
    "sg:province":"Niedersachsen",
    "wof:name":"Zweirad-klus Wilhelm Klus",
    "wof:placetype":"venue"
},
  "geometry": {"coordinates":[7.311835,52.528316],"type":"Point"}
}