{
  "type": "Feature",
  "properties": {
    "iso:country":"DE",
    "sg:address":"Ingolst\u00e4dter Str. 43",
    "sg:city":"N\u00fcrnberg",
    "sg:phone":"+49 911/4466677",
    "sg:postcode":"90461",
    "sg:province":"Bayern",
    "wof:name":"Zanuso Kugellager Gmbh",
    "wof:placetype":"venue"
},
  "geometry": {"coordinates":[11.097475,49.42831],"type":"Point"}
}