{
  "type": "Feature",
  "properties": {
    "iso:country":"DE",
    "sg:address":"Maximilianstr. 20-22",
    "sg:city":"Lindau",
    "sg:postcode":"88131",
    "sg:province":"Bayern",
    "wof:name":"Kaisers Drugstore",
    "wof:placetype":"venue"
},
  "geometry": {"coordinates":[9.663177,47.572323],"type":"Point"}
}