{
  "type": "Feature",
  "properties": {
    "iso:country":"DE",
    "sg:address":"Danziger Str. 10",
    "sg:city":"Bayreuth",
    "sg:phone":"+49 921/92516",
    "sg:postcode":"95448",
    "sg:province":"Bayern",
    "wof:name":"Harald Klein Architekt",
    "wof:placetype":"venue"
},
  "geometry": {"coordinates":[11.615777,49.958496],"type":"Point"}
}