{
  "type": "Feature",
  "properties": {
    "iso:country":"DE",
    "sg:address":"Johannesplatz 5",
    "sg:city":"Dinslaken",
    "sg:phone":"+49 2064/39017",
    "sg:postcode":"46537",
    "sg:province":"Nordrhein-Westfalen",
    "wof:name":"Kadir Coban",
    "wof:placetype":"venue"
},
  "geometry": {"coordinates":[6.7354469299,51.5808792114],"type":"Point"}
}