{
  "type": "Feature",
  "properties": {
    "iso:country":"DE",
    "sg:address":"Alfred-Neubert-Str. 1",
    "sg:city":"Chemnitz",
    "sg:phone":"+49 371/2604228",
    "sg:postcode":"09123",
    "sg:province":"Sachsen",
    "wof:name":"Gunter Weichelt",
    "wof:placetype":"venue"
},
  "geometry": {"coordinates":[12.896402359,50.7864456177],"type":"Point"}
}