{
  "type": "Feature",
  "properties": {
    "iso:country":"DE",
    "sg:address":"Kochler Str. 70",
    "sg:city":"Iffeldorf",
    "sg:phone":"+49 8856/5593",
    "sg:postcode":"82393",
    "sg:province":"Bayern",
    "wof:name":"Mateyka Malereibetrieb Gmbh",
    "wof:placetype":"venue"
},
  "geometry": {"coordinates":[11.333954,47.775074],"type":"Point"}
}