{
  "type": "Feature",
  "properties": {
    "iso:country":"DE",
    "sg:address":"Am Burggraben 16",
    "sg:city":"Giengen",
    "sg:phone":"+49 7324/980411",
    "sg:postcode":"89537",
    "sg:province":"Baden-W\u00fcrttemberg",
    "wof:name":"Gartenmaier",
    "wof:placetype":"venue"
},
  "geometry": {"coordinates":[10.203049,48.593204],"type":"Point"}
}