{
  "type": "Feature",
  "properties": {
    "iso:country":"DE",
    "sg:address":"Weseler Str. 121",
    "sg:city":"Geldern",
    "sg:phone":"+49 2831/94920",
    "sg:postcode":"47608",
    "sg:province":"Nordrhein-Westfalen",
    "wof:name":"Mc Donalds Restaurant",
    "wof:placetype":"venue"
},
  "geometry": {"coordinates":[6.3462190628,51.522644043],"type":"Point"}
}