{
  "type": "Feature",
  "properties": {
    "iso:country":"DE",
    "sg:address":"Lieserweg 17",
    "sg:city":"\u00dcdersdorf",
    "sg:phone":"+49 6596/411",
    "sg:postcode":"54552",
    "sg:province":"Rheinland-Pfalz",
    "wof:name":"Martha Borsch Hebamme",
    "wof:placetype":"venue"
},
  "geometry": {"coordinates":[6.82034,50.137341],"type":"Point"}
}