{
  "type": "Feature",
  "properties": {
    "iso:country":"DE",
    "sg:address":"Kurze Str. 18",
    "sg:city":"Gr\u00fcnendeich",
    "sg:phone":"+49 4142/2267",
    "sg:postcode":"21720",
    "sg:province":"Niedersachsen",
    "wof:name":"Hans D\u00fcwer Ohg",
    "wof:placetype":"venue"
},
  "geometry": {"coordinates":[9.6118831635,53.5692138672],"type":"Point"}
}