{
  "type": "Feature",
  "properties": {
    "iso:country":"DE",
    "sg:address":"Postfach 2574",
    "sg:city":"Brunsb\u00fcttel",
    "sg:phone":"+49 4852/87073",
    "sg:postcode":"25538",
    "sg:province":"Schleswig-Holstein",
    "wof:name":"Emv Montage F\u00fcr Elektro Und Msr-technik Gmbh",
    "wof:placetype":"venue"
},
  "geometry": {"coordinates":[9.1259698868,53.8956604004],"type":"Point"}
}