{
  "type": "Feature",
  "properties": {
    "iso:country":"DE",
    "sg:address":"Egerer Str. 11",
    "sg:city":"Amberg",
    "sg:postcode":"92224",
    "sg:province":"Bayern",
    "wof:name":"Lutz Bergmann Architekt",
    "wof:placetype":"venue"
},
  "geometry": {"coordinates":[11.886563,49.446499],"type":"Point"}
}