{
  "type": "Feature",
  "properties": {
    "iso:country":"DE",
    "sg:address":"Theodor-Fontane-Str. 5",
    "sg:city":"Dormagen",
    "sg:phone":"+49 2133/41924",
    "sg:postcode":"41541",
    "sg:province":"Nordrhein-Westfalen",
    "wof:name":"H. Peters",
    "wof:placetype":"venue"
},
  "geometry": {"coordinates":[6.841007,51.120636],"type":"Point"}
}