{
  "type": "Feature",
  "properties": {
    "iso:country":"DE",
    "sg:address":"Industriestr. 30",
    "sg:city":"Gr\u00f6benzell",
    "sg:phone":"+49 8142/6618",
    "sg:postcode":"82194",
    "sg:province":"Bayern",
    "wof:name":"Walter Frei Masseur",
    "wof:placetype":"venue"
},
  "geometry": {"coordinates":[11.386704,48.187023],"type":"Point"}
}