{
  "type": "Feature",
  "properties": {
    "iso:country":"DE",
    "sg:address":"Berliner Str. 35",
    "sg:city":"Bad M\u00fcnster-Ebernburg",
    "sg:phone":"+49 6708/3322",
    "sg:postcode":"55583",
    "sg:province":"Rheinland-Pfalz",
    "wof:name":"Felsen-apotheke",
    "wof:placetype":"venue"
},
  "geometry": {"coordinates":[7.847768,49.811882],"type":"Point"}
}