{
  "type": "Feature",
  "properties": {
    "iso:country":"DE",
    "sg:address":"Im Ries 21",
    "sg:city":"N\u00fcrnberg",
    "sg:phone":"+49 911/6427361",
    "sg:postcode":"90451",
    "sg:province":"Bayern",
    "wof:name":"H. Schmeusser",
    "wof:placetype":"venue"
},
  "geometry": {"coordinates":[11.0365686417,49.3979797363],"type":"Point"}
}