{
  "type": "Feature",
  "properties": {
    "iso:country":"DE",
    "sg:address":"Bielefelder Str. 3",
    "sg:city":"Paderborn",
    "sg:postcode":"33104",
    "sg:province":"Nordrhein-Westfalen",
    "wof:name":"Garten- Und Landschaftsplanung Fischer Kg",
    "wof:placetype":"venue"
},
  "geometry": {"coordinates":[8.714087,51.746433],"type":"Point"}
}