{
  "type": "Feature",
  "properties": {
    "iso:country":"DE",
    "sg:address":"Bahnhofstr. 15",
    "sg:city":"Korbach",
    "sg:phone":"+49 5631/2487",
    "sg:postcode":"34497",
    "sg:province":"Hessen",
    "wof:name":"Modehaus Witter Inh. Alfred Witter",
    "wof:placetype":"venue"
},
  "geometry": {"coordinates":[8.872607,51.277641],"type":"Point"}
}