{
  "type": "Feature",
  "properties": {
    "iso:country":"DE",
    "sg:address":"Unterer Steig 2",
    "sg:city":"Ruhstorf",
    "sg:phone":"+49 8534/1387",
    "sg:postcode":"94099",
    "sg:province":"Bayern",
    "wof:name":"Cafe Brotzeitst\u00fcberl",
    "wof:placetype":"venue"
},
  "geometry": {"coordinates":[13.254179,48.477119],"type":"Point"}
}