{
  "type": "Feature",
  "properties": {
    "iso:country":"DE",
    "sg:address":"Buchholzstr. 31",
    "sg:city":"Duisburg",
    "sg:phone":"+49 203/770284",
    "sg:postcode":"47055",
    "sg:province":"Nordrhein-Westfalen",
    "wof:name":"Neon-kuttler Kg",
    "wof:placetype":"venue"
},
  "geometry": {"coordinates":[6.768499,51.404354],"type":"Point"}
}