{
  "type": "Feature",
  "properties": {
    "iso:country":"DE",
    "sg:address":"Neutorstr. 12",
    "sg:city":"Ulm",
    "sg:phone":"+49 731/96470",
    "sg:postcode":"89073",
    "sg:province":"Baden-W\u00fcrttemberg",
    "wof:name":"Hotel Ibis",
    "wof:placetype":"venue"
},
  "geometry": {"coordinates":[9.987443924,48.4013595581],"type":"Point"}
}