{
  "type": "Feature",
  "properties": {
    "iso:country":"DE",
    "sg:address":"Bahnhofstr. 14-16",
    "sg:city":"Konstanz",
    "sg:phone":"+49 7531/23544",
    "sg:postcode":"78462",
    "sg:province":"Baden-W\u00fcrttemberg",
    "wof:name":"Adolf Brunner",
    "wof:placetype":"venue"
},
  "geometry": {"coordinates":[9.175201416,47.6590118408],"type":"Point"}
}