{
  "type": "Feature",
  "properties": {
    "iso:country":"DE",
    "sg:address":"Friedrichstr. 9",
    "sg:city":"Helmstedt",
    "sg:phone":"+49 5351/34809",
    "sg:postcode":"38350",
    "sg:province":"Niedersachsen",
    "wof:name":"Friedrichseck",
    "wof:placetype":"venue"
},
  "geometry": {"coordinates":[11.0034532547,52.2336502075],"type":"Point"}
}