{
  "type": "Feature",
  "properties": {
    "iso:country":"DE",
    "sg:address":"Leibnitzstr 20",
    "sg:city":"Weingarten",
    "sg:phone":"+49 751/561540",
    "sg:postcode":"88250",
    "sg:province":"Baden-W\u00fcrttemberg",
    "wof:name":"Msw Innovative Software Gmbh",
    "wof:placetype":"venue"
},
  "geometry": {"coordinates":[9.654445,47.81358],"type":"Point"}
}