{
  "type": "Feature",
  "properties": {
    "iso:country":"DE",
    "sg:address":"Pivitsheider Str. 45",
    "sg:city":"Augustdorf",
    "sg:phone":"+49 5237/96940",
    "sg:postcode":"32832",
    "sg:province":"Nordrhein-Westfalen",
    "wof:name":"H\u00f6rig Reisestudio",
    "wof:placetype":"venue"
},
  "geometry": {"coordinates":[8.7408618927,51.9092025757],"type":"Point"}
}