{
  "type": "Feature",
  "properties": {
    "iso:country":"DE",
    "sg:address":"Dollweg 4",
    "sg:city":"H\u00fcrtgenwald",
    "sg:postcode":"52393",
    "sg:province":"Nordrhein-Westfalen",
    "wof:name":"Deutsches Internationales Hilfswerk E. V.",
    "wof:placetype":"venue"
},
  "geometry": {"coordinates":[6.4276719093,50.7410011292],"type":"Point"}
}