{
  "type": "Feature",
  "properties": {
    "iso:country":"DE",
    "sg:address":"Blankenburger Str. 30",
    "sg:city":"K\u00f6nigsee",
    "sg:phone":"+49 36738/460",
    "sg:postcode":"07426",
    "sg:province":"Th\u00fcringen",
    "wof:name":"Rexel Mitte Elektrotechnik Gmbh",
    "wof:placetype":"venue"
},
  "geometry": {"coordinates":[11.1024856567,50.6646080017],"type":"Point"}
}