{
  "type": "Feature",
  "properties": {
    "iso:country":"DE",
    "sg:address":"Joseph-Belli-Weg 5",
    "sg:city":"Konstanz",
    "sg:phone":"+49 7531/693722",
    "sg:postcode":"78467",
    "sg:province":"Baden-W\u00fcrttemberg",
    "wof:name":"M. Cole",
    "wof:placetype":"venue"
},
  "geometry": {"coordinates":[9.163264,47.679169],"type":"Point"}
}