{
  "type": "Feature",
  "properties": {
    "iso:country":"DE",
    "sg:address":"B\u00fcrgermeister-Smidt-Str. 178",
    "sg:city":"Bremerhaven",
    "sg:phone":"+49 471/46401",
    "sg:postcode":"27568",
    "sg:province":"Bremen",
    "wof:name":"B\u00fcrgerkrug",
    "wof:placetype":"venue"
},
  "geometry": {"coordinates":[8.5721683502,53.5510673523],"type":"Point"}
}