{
  "type": "Feature",
  "properties": {
    "iso:country":"DE",
    "sg:address":"Bismarckstr. 76-78",
    "sg:city":"M\u00f6nchengladbach",
    "sg:phone":"+49 2161/12219",
    "sg:postcode":"41061",
    "sg:province":"Nordrhein-Westfalen",
    "wof:name":"Eldo Rado Zweirad Dirk Egert",
    "wof:placetype":"venue"
},
  "geometry": {"coordinates":[6.440328,51.197582],"type":"Point"}
}