{
  "type": "Feature",
  "properties": {
    "iso:country":"DE",
    "sg:address":"D\u00fcnenweg 11",
    "sg:city":"Wittd\u00fcn",
    "sg:phone":"+49 4682/612",
    "sg:postcode":"25946",
    "sg:province":"Schleswig-Holstein",
    "wof:name":"Pension Hans Paulsen",
    "wof:placetype":"venue"
},
  "geometry": {"coordinates":[8.3734207153,54.628944397],"type":"Point"}
}