{
  "type": "Feature",
  "properties": {
    "iso:country":"DE",
    "sg:address":"Charles-Darwin-Ring 2",
    "sg:city":"Rostock",
    "sg:phone":"+49 381/405380",
    "sg:postcode":"18059",
    "sg:province":"Mecklenburg-Vorpommern",
    "wof:name":"Montra Gmbh",
    "wof:placetype":"venue"
},
  "geometry": {"coordinates":[12.119459,54.062164],"type":"Point"}
}