{
  "type": "Feature",
  "properties": {
    "iso:country":"DE",
    "sg:address":"Urnenfeldstr. 19",
    "sg:city":"Hamm",
    "sg:phone":"+49 2389/535489",
    "sg:postcode":"59077",
    "sg:province":"Nordrhein-Westfalen",
    "wof:name":"Norbert Mennigmann",
    "wof:placetype":"venue"
},
  "geometry": {"coordinates":[7.686895,51.65876],"type":"Point"}
}