{
  "type": "Feature",
  "properties": {
    "iso:country":"DE",
    "sg:address":"Grade Eiche 51",
    "sg:city":"Titz",
    "sg:phone":"+49 2463/1014",
    "sg:postcode":"52445",
    "sg:province":"Nordrhein-Westfalen",
    "wof:name":"P. Caspars",
    "wof:placetype":"venue"
},
  "geometry": {"coordinates":[6.4623818398,50.963104248],"type":"Point"}
}