{
  "type": "Feature",
  "properties": {
    "iso:country":"DE",
    "sg:address":"Salbeiweg 2",
    "sg:city":"K\u00f6nigsbrunn",
    "sg:phone":"+49 8231/6489",
    "sg:postcode":"86343",
    "sg:province":"Bayern",
    "wof:name":"H. H. M\u00fcller",
    "wof:placetype":"venue"
},
  "geometry": {"coordinates":[10.8902168274,48.2617340088],"type":"Point"}
}