{
  "type": "Feature",
  "properties": {
    "iso:country":"DE",
    "sg:address":"Ginsterweg 5",
    "sg:city":"Borkheide",
    "sg:phone":"+49 33845/40502",
    "sg:postcode":"14822",
    "sg:province":"Brandenburg",
    "wof:name":"Kerker Baustoffe Gmbh",
    "wof:placetype":"venue"
},
  "geometry": {"coordinates":[12.7745351791,52.1990203857],"type":"Point"}
}