{
  "type": "Feature",
  "properties": {
    "iso:country":"DE",
    "sg:address":"Martin-Luther-Str. 1",
    "sg:city":"Bad Salzuflen",
    "sg:phone":"+49 5222/59142",
    "sg:postcode":"32105",
    "sg:province":"Nordrhein-Westfalen",
    "wof:name":"Akropolis",
    "wof:placetype":"venue"
},
  "geometry": {"coordinates":[8.7505264282,52.0834274292],"type":"Point"}
}