{
  "type": "Feature",
  "properties": {
    "iso:country":"DE",
    "sg:address":"Winterfeldtstr. 58",
    "sg:city":"Berlin",
    "sg:phone":"+49 30/2152374",
    "sg:postcode":"10781",
    "sg:province":"Berlin",
    "wof:name":"Gastst\u00e4tte Alexis Sorbas",
    "wof:placetype":"venue"
},
  "geometry": {"coordinates":[13.3511838913,52.4968070984],"type":"Point"}
}