{
  "type": "Feature",
  "properties": {
    "iso:country":"DE",
    "sg:address":"Olympiastr. 2",
    "sg:city":"Garmisch-Partenkirchen",
    "sg:phone":"+49 8821/93200",
    "sg:postcode":"82467",
    "sg:province":"Bayern",
    "wof:name":"I. Von Der Borch",
    "wof:placetype":"venue"
},
  "geometry": {"coordinates":[11.092431,47.494148],"type":"Point"}
}