{
  "type": "Feature",
  "properties": {
    "iso:country":"DE",
    "sg:address":"Wallgasse 45",
    "sg:city":"Neustadt",
    "sg:phone":"+49 6321/31855",
    "sg:postcode":"67433",
    "sg:province":"Rheinland-Pfalz",
    "wof:name":"Pf\u00e4lzer Weinkehlchen Neustadt",
    "wof:placetype":"venue"
},
  "geometry": {"coordinates":[8.1344470978,49.3539276123],"type":"Point"}
}