{
  "type": "Feature",
  "properties": {
    "iso:country":"DE",
    "sg:address":"R\u00f6merstr. 125",
    "sg:city":"Leonberg",
    "sg:phone":"+49 7152/25169",
    "sg:postcode":"71229",
    "sg:province":"Baden-W\u00fcrttemberg",
    "wof:name":"Walter B\u00e4uerle",
    "wof:placetype":"venue"
},
  "geometry": {"coordinates":[9.016076088,48.795879364],"type":"Point"}
}