{
  "type": "Feature",
  "properties": {
    "iso:country":"DE",
    "sg:address":"St.-Magnus-Str. 96",
    "sg:city":"Bremen",
    "sg:postcode":"28217",
    "sg:province":"Bremen",
    "wof:name":"Technologie-transfer-zentrum Des Bremischen Handwerks E. V.",
    "wof:placetype":"venue"
},
  "geometry": {"coordinates":[8.790148735,53.0948410034],"type":"Point"}
}