{
  "type": "Feature",
  "properties": {
    "iso:country":"DE",
    "sg:address":"Breite Str. 21",
    "sg:city":"Grevenbroich",
    "sg:phone":"+49 2181/64764",
    "sg:postcode":"41515",
    "sg:province":"Nordrhein-Westfalen",
    "wof:name":"E. Fenes",
    "wof:placetype":"venue"
},
  "geometry": {"coordinates":[6.588786,51.088978],"type":"Point"}
}