{
  "type": "Feature",
  "properties": {
    "iso:country":"DE",
    "sg:address":"Ortsstr. 2",
    "sg:city":"Syrau",
    "sg:phone":"+49 37431/3673",
    "sg:postcode":"08548",
    "sg:province":"Sachsen",
    "wof:name":"W & S Reinigungs Gmbh",
    "wof:placetype":"venue"
},
  "geometry": {"coordinates":[12.09202,50.567501],"type":"Point"}
}