{
  "type": "Feature",
  "properties": {
    "iso:country":"DE",
    "sg:address":"Uterm\u00f6hlestr. 10",
    "sg:city":"Hildesheim",
    "sg:phone":"+49 4951/2176710",
    "sg:postcode":"31135",
    "sg:province":"Niedersachsen",
    "wof:name":"Gustav Morsch Gmbh",
    "wof:placetype":"venue"
},
  "geometry": {"coordinates":[9.990251,52.169029],"type":"Point"}
}