{
  "type": "Feature",
  "properties": {
    "iso:country":"DE",
    "sg:address":"Hagenpolder I 11",
    "sg:city":"Krummh\u00f6rn",
    "sg:phone":"+49 4920/318",
    "sg:postcode":"26736",
    "sg:province":"Niedersachsen",
    "wof:name":"Versuchs- Und Beratungsring \u00f6kologischer Landbau E. V.",
    "wof:placetype":"venue"
},
  "geometry": {"coordinates":[7.1873559952,53.5151329041],"type":"Point"}
}