{
  "type": "Feature",
  "properties": {
    "iso:country":"DE",
    "sg:address":"Kanderner Str. 6",
    "sg:city":"Schliengen",
    "sg:phone":"+49 7635/2532",
    "sg:postcode":"79418",
    "sg:province":"Baden-W\u00fcrttemberg",
    "wof:name":"M. Und U. Moritz",
    "wof:placetype":"venue"
},
  "geometry": {"coordinates":[7.646736145,47.7559814453],"type":"Point"}
}