{
  "type": "Feature",
  "properties": {
    "iso:country":"DE",
    "sg:address":"Dornberger Str. 270",
    "sg:city":"Bielefeld",
    "sg:phone":"+49 521/911030",
    "sg:postcode":"33619",
    "sg:province":"Nordrhein-Westfalen",
    "wof:name":"W. Westerhold Agentur Gmbh",
    "wof:placetype":"venue"
},
  "geometry": {"coordinates":[8.4822397232,52.0224914551],"type":"Point"}
}