{
  "type": "Feature",
  "properties": {
    "iso:country":"DE",
    "sg:address":"Talstr. 5",
    "sg:city":"Kiedrich",
    "sg:phone":"+49 6123/3365",
    "sg:postcode":"65399",
    "sg:province":"Hessen",
    "wof:name":"Walter Abt",
    "wof:placetype":"venue"
},
  "geometry": {"coordinates":[8.079071,50.047096],"type":"Point"}
}