{
  "type": "Feature",
  "properties": {
    "iso:country":"DE",
    "sg:address":"Lange Str. 6b",
    "sg:city":"Oberursel",
    "sg:phone":"+49 6171/3706",
    "sg:postcode":"61440",
    "sg:province":"Hessen",
    "wof:name":"Thomas Stimpert",
    "wof:placetype":"venue"
},
  "geometry": {"coordinates":[8.583545,50.200981],"type":"Point"}
}