{
  "type": "Feature",
  "properties": {
    "iso:country":"DE",
    "sg:address":"Lichtstr. 72",
    "sg:city":"D\u00fcsseldorf",
    "sg:phone":"+49 211/675931",
    "sg:postcode":"40235",
    "sg:province":"Nordrhein-Westfalen",
    "wof:name":"Rudolf Eiermann",
    "wof:placetype":"venue"
},
  "geometry": {"coordinates":[6.8157639503,51.2291374207],"type":"Point"}
}