{
  "type": "Feature",
  "properties": {
    "iso:country":"DE",
    "sg:address":"Neusser Str. 587",
    "sg:city":"K\u00f6ln",
    "sg:phone":"+49 221/745628",
    "sg:postcode":"50737",
    "sg:province":"Nordrhein-Westfalen",
    "wof:name":"B. M\u00fchlberg",
    "wof:placetype":"venue"
},
  "geometry": {"coordinates":[6.9475970268,50.9821357727],"type":"Point"}
}