{
  "type": "Feature",
  "properties": {
    "iso:country":"DE",
    "sg:address":"Emsdettener Str. 227",
    "sg:city":"Neuenkirchen",
    "sg:phone":"+49 5973/660",
    "sg:postcode":"48485",
    "sg:province":"Nordrhein-Westfalen",
    "wof:name":"Klm K\u00fchl- Und Lagerhaus M\u00fcnsterland Gmbh",
    "wof:placetype":"venue"
},
  "geometry": {"coordinates":[7.402747,52.209099],"type":"Point"}
}