{
  "type": "Feature",
  "properties": {
    "iso:country":"DE",
    "sg:address":"Neue Str. 17",
    "sg:city":"Seebach",
    "sg:phone":"+49 36929/63270",
    "sg:postcode":"99846",
    "sg:province":"Th\u00fcringen",
    "wof:name":"Lothar Griesam",
    "wof:placetype":"venue"
},
  "geometry": {"coordinates":[10.422725,50.913139],"type":"Point"}
}