{
  "type": "Feature",
  "properties": {
    "iso:country":"DE",
    "sg:address":"Sch\u00f6nholzer Weg 3",
    "sg:city":"Berlin",
    "sg:phone":"+49 30/9316752",
    "sg:postcode":"13158",
    "sg:province":"Berlin",
    "wof:name":"Klaus Burkel",
    "wof:placetype":"venue"
},
  "geometry": {"coordinates":[13.3719215393,52.5899353027],"type":"Point"}
}