{
  "type": "Feature",
  "properties": {
    "iso:country":"DE",
    "sg:address":"Lippst\u00e4dter Str. 5",
    "sg:city":"Rietberg",
    "sg:phone":"+49 2944/1442",
    "sg:postcode":"33397",
    "sg:province":"Nordrhein-Westfalen",
    "wof:name":"Restaurant Adelmann",
    "wof:placetype":"venue"
},
  "geometry": {"coordinates":[8.3897438049,51.7564849854],"type":"Point"}
}