{
  "type": "Feature",
  "properties": {
    "iso:country":"DE",
    "sg:address":"Otto-Hahn-Str. 3",
    "sg:city":"Glinde",
    "sg:phone":"+49 40/727580",
    "sg:postcode":"21509",
    "sg:province":"Schleswig-Holstein",
    "wof:name":"Imw Anlagenbau Ingenieure B. Und G. Miehe",
    "wof:placetype":"venue"
},
  "geometry": {"coordinates":[10.234146,53.529709],"type":"Point"}
}