{
  "type": "Feature",
  "properties": {
    "iso:country":"DE",
    "sg:address":"Oberdorf 7",
    "sg:city":"K\u00fcssaberg",
    "sg:phone":"+49 7741/2579",
    "sg:postcode":"79790",
    "sg:province":"Baden-W\u00fcrttemberg",
    "wof:name":"Bruno Wagner",
    "wof:placetype":"venue"
},
  "geometry": {"coordinates":[8.2975206375,47.6077842712],"type":"Point"}
}