{
  "type": "Feature",
  "properties": {
    "iso:country":"DE",
    "sg:address":"Linzinger Str. 2",
    "sg:city":"Osterhofen",
    "sg:phone":"+49 9932/2371",
    "sg:postcode":"94486",
    "sg:province":"Bayern",
    "wof:name":"Max Weinberger",
    "wof:placetype":"venue"
},
  "geometry": {"coordinates":[13.011889,48.690163],"type":"Point"}
}