{
  "type": "Feature",
  "properties": {
    "iso:country":"DE",
    "sg:address":"Bahnhofstr. 58",
    "sg:city":"Petershagen",
    "sg:phone":"+49 5702/9418",
    "sg:postcode":"32469",
    "sg:province":"Nordrhein-Westfalen",
    "wof:name":"Heinrich Becker Inh. Heidi Kuhlmann-becker",
    "wof:placetype":"venue"
},
  "geometry": {"coordinates":[9.004799,52.36768],"type":"Point"}
}