{
  "type": "Feature",
  "properties": {
    "iso:country":"DE",
    "sg:address":"Ulmer Str. 128",
    "sg:city":"Augsburg",
    "sg:phone":"+49 821/299930",
    "sg:postcode":"86156",
    "sg:province":"Bayern",
    "wof:name":"Hermann Schnierle Gmbh",
    "wof:placetype":"venue"
},
  "geometry": {"coordinates":[10.862039566,48.3806800842],"type":"Point"}
}