{
  "type": "Feature",
  "properties": {
    "iso:country":"DE",
    "sg:address":"Gartenstr. 17",
    "sg:city":"Horn-Bad Meinberg",
    "sg:phone":"+49 5234/98103",
    "sg:postcode":"32805",
    "sg:province":"Nordrhein-Westfalen",
    "wof:name":"Pension Haus Ilse",
    "wof:placetype":"venue"
},
  "geometry": {"coordinates":[8.979393959,51.8936805725],"type":"Point"}
}