{
  "type": "Feature",
  "properties": {
    "iso:country":"DE",
    "sg:address":"Bahnhofstr. 23",
    "sg:city":"Reichenberg",
    "sg:phone":"+49 931/69223",
    "sg:postcode":"97234",
    "sg:province":"Bayern",
    "wof:name":"Bauunternehmung Joh. Pfeuffer Gmbh & Co. Kg",
    "wof:placetype":"venue"
},
  "geometry": {"coordinates":[9.9156951904,49.7295455933],"type":"Point"}
}