{
  "type": "Feature",
  "properties": {
    "iso:country":"DE",
    "sg:address":"Breite Str. 73",
    "sg:city":"L\u00fcbeck",
    "sg:phone":"+49 451/75369",
    "sg:postcode":"23552",
    "sg:province":"Schleswig-Holstein",
    "wof:name":"Orsay Gmbh",
    "wof:placetype":"venue"
},
  "geometry": {"coordinates":[10.683006,53.866352],"type":"Point"}
}