{
  "type": "Feature",
  "properties": {
    "iso:country":"DE",
    "sg:address":"Westerbachstr. 23",
    "sg:city":"Kronberg",
    "sg:phone":"+49 6173/79057",
    "sg:postcode":"61476",
    "sg:province":"Hessen",
    "wof:name":"Esca-markt Tierbedarf Timm Heidel",
    "wof:placetype":"venue"
},
  "geometry": {"coordinates":[8.52776,50.172626],"type":"Point"}
}