{
  "type": "Feature",
  "properties": {
    "iso:country":"DE",
    "sg:address":"Alte Str. 6",
    "sg:city":"Walzbachtal",
    "sg:phone":"+49 7203/8569",
    "sg:postcode":"75045",
    "sg:province":"Baden-W\u00fcrttemberg",
    "wof:name":"Berthold St\u00f6ckle Architekt",
    "wof:placetype":"venue"
},
  "geometry": {"coordinates":[8.611424,49.010181],"type":"Point"}
}