{
  "type": "Feature",
  "properties": {
    "iso:country":"DE",
    "sg:address":"Hauptstr. 14",
    "sg:city":"Langlingen",
    "sg:phone":"+49 4950/82245",
    "sg:postcode":"29364",
    "sg:province":"Niedersachsen",
    "wof:name":"Sparkasse Celle",
    "wof:placetype":"venue"
},
  "geometry": {"coordinates":[10.278505,52.557343],"type":"Point"}
}