{
  "type": "Feature",
  "properties": {
    "iso:country":"DE",
    "sg:address":"Elbestr. 18",
    "sg:city":"Frankfurt",
    "sg:phone":"+49 69/234571",
    "sg:postcode":"60329",
    "sg:province":"Hessen",
    "wof:name":"Bierstube",
    "wof:placetype":"venue"
},
  "geometry": {"coordinates":[8.6689453125,50.1078186035],"type":"Point"}
}