{
  "type": "Feature",
  "properties": {
    "iso:country":"DE",
    "sg:address":"Br\u00fcder-Grimm-Str. 52",
    "sg:city":"Offenbach",
    "sg:postcode":"63069",
    "sg:province":"Hessen",
    "wof:name":"Nv-bauprojekt Gmbh",
    "wof:placetype":"venue"
},
  "geometry": {"coordinates":[8.7648611069,50.0914421082],"type":"Point"}
}