{
  "type": "Feature",
  "properties": {
    "iso:country":"DE",
    "sg:address":"Birkenweg 10",
    "sg:city":"Gehrden bei Hannover",
    "sg:phone":"+49 5108/925528",
    "sg:postcode":"30989",
    "sg:province":"Niedersachsen",
    "wof:name":"Aball Internet Netzdienste Gmbh",
    "wof:placetype":"venue"
},
  "geometry": {"coordinates":[9.5953884125,52.3093566895],"type":"Point"}
}