{
  "type": "Feature",
  "properties": {
    "iso:country":"DE",
    "sg:address":"Tafingerstr. 14",
    "sg:city":"Vaihingen",
    "sg:phone":"+49 7042/9560",
    "sg:postcode":"71665",
    "sg:province":"Baden-W\u00fcrttemberg",
    "wof:name":"Unical Kessel Und Apparate Gmbh",
    "wof:placetype":"venue"
},
  "geometry": {"coordinates":[8.9581403732,48.9436607361],"type":"Point"}
}