{
  "type": "Feature",
  "properties": {
    "iso:country":"DE",
    "sg:address":"Temmlerstr. 2",
    "sg:city":"Marburg",
    "sg:phone":"+49 4964/214940",
    "sg:postcode":"35039",
    "sg:province":"Hessen",
    "wof:name":"Temmler Pharma Gmbh",
    "wof:placetype":"venue"
},
  "geometry": {"coordinates":[8.764254,50.789436],"type":"Point"}
}