{
  "type": "Feature",
  "properties": {
    "iso:country":"DE",
    "sg:address":"Sigsfeldstr 5",
    "sg:city":"Aachen",
    "sg:phone":"+49 241/521041",
    "sg:postcode":"52078",
    "sg:province":"Nordrhein-Westfalen",
    "wof:name":"Rolladen Kutsch Heinrich Kutsch Gmbh",
    "wof:placetype":"venue"
},
  "geometry": {"coordinates":[6.167238,50.762241],"type":"Point"}
}