{
  "type": "Feature",
  "properties": {
    "iso:country":"DE",
    "sg:address":"Hans-Delbr\u00fcck-Str. 20",
    "sg:city":"Gera",
    "sg:postcode":"07548",
    "sg:province":"Th\u00fcringen",
    "wof:name":"Gerhard G\u00fcnther",
    "wof:placetype":"venue"
},
  "geometry": {"coordinates":[12.0633935928,50.8916168213],"type":"Point"}
}