{
  "type": "Feature",
  "properties": {
    "iso:country":"DE",
    "sg:address":"Dreschstr. 9",
    "sg:city":"M\u00fcnchen",
    "sg:phone":"+49 89/3615074",
    "sg:postcode":"80805",
    "sg:province":"Bayern",
    "wof:name":"Ludwig Raith Ingenieur",
    "wof:placetype":"venue"
},
  "geometry": {"coordinates":[11.5901508331,48.1682357788],"type":"Point"}
}