{
  "type": "Feature",
  "properties": {
    "iso:country":"DE",
    "sg:address":"Am Schlo\u00df Broich 1-3",
    "sg:city":"M\u00fclheim",
    "sg:postcode":"45479",
    "sg:province":"Nordrhein-Westfalen",
    "wof:name":"Vereinigte Rhein-ruhr-wasser- Wirtschaftsgesellschaft Mbh",
    "wof:placetype":"venue"
},
  "geometry": {"coordinates":[6.874589,51.426708],"type":"Point"}
}