{
  "type": "Feature",
  "properties": {
    "iso:country":"DE",
    "sg:address":"Gennaer Str. 34",
    "sg:city":"Iserlohn",
    "sg:phone":"+49 2374/10373",
    "sg:postcode":"58642",
    "sg:province":"Nordrhein-Westfalen",
    "wof:name":"Ermerts Backstube Gmbh",
    "wof:placetype":"venue"
},
  "geometry": {"coordinates":[7.608945,51.360149],"type":"Point"}
}