{
  "type": "Feature",
  "properties": {
    "iso:country":"DE",
    "sg:address":"Friedhofstr. 3",
    "sg:city":"Ottersheim",
    "sg:phone":"+49 6348/1200",
    "sg:postcode":"76879",
    "sg:province":"Rheinland-Pfalz",
    "wof:name":"A. Glatz",
    "wof:placetype":"venue"
},
  "geometry": {"coordinates":[8.2274188995,49.1900520325],"type":"Point"}
}