{
  "type": "Feature",
  "properties": {
    "iso:country":"DE",
    "sg:address":"Kirchgasse 25",
    "sg:city":"Baesweiler",
    "sg:postcode":"52499",
    "sg:province":"Nordrhein-Westfalen",
    "wof:name":"Holp Gesellschaft F\u00fcr Handel Und Organisation",
    "wof:placetype":"venue"
},
  "geometry": {"coordinates":[6.186770916,50.8963279724],"type":"Point"}
}