{
  "type": "Feature",
  "properties": {
    "iso:country":"DE",
    "sg:address":"Ringstr. 18",
    "sg:city":"Syrgenstein",
    "sg:phone":"+49 9077/1062",
    "sg:postcode":"89428",
    "sg:province":"Bayern",
    "wof:name":"Benedikt Keis",
    "wof:placetype":"venue"
},
  "geometry": {"coordinates":[10.3055896759,48.6435928345],"type":"Point"}
}