{
  "type": "Feature",
  "properties": {
    "iso:country":"DE",
    "sg:address":"Kahrstr. 50",
    "sg:city":"Niederkr\u00fcchten",
    "sg:phone":"+49 2163/82036",
    "sg:postcode":"41372",
    "sg:province":"Nordrhein-Westfalen",
    "wof:name":"H. Classen",
    "wof:placetype":"venue"
},
  "geometry": {"coordinates":[6.219573,51.214428],"type":"Point"}
}