{
  "type": "Feature",
  "properties": {
    "iso:country":"DE",
    "sg:address":"Fischerstr. 2",
    "sg:city":"Kempten",
    "sg:phone":"+49 831/52800",
    "sg:postcode":"87435",
    "sg:province":"Bayern",
    "wof:name":"Kaufhaus Kempten Beteiligungs Gmbh",
    "wof:placetype":"venue"
},
  "geometry": {"coordinates":[10.315891,47.724293],"type":"Point"}
}