{
  "type": "Feature",
  "properties": {
    "iso:country":"DE",
    "sg:address":"Alfred-Reinhardt-Str. 60",
    "sg:city":"Halle",
    "sg:postcode":"06132",
    "sg:province":"Sachsen-Anhalt",
    "wof:name":"Loewe Werbung Gmbh",
    "wof:placetype":"venue"
},
  "geometry": {"coordinates":[11.9992542267,51.4314231873],"type":"Point"}
}