{
  "type": "Feature",
  "properties": {
    "iso:country":"DE",
    "sg:address":"Fritzlarer Str. 8",
    "sg:city":"Melsungen",
    "sg:phone":"+49 5661/51790",
    "sg:postcode":"34212",
    "sg:province":"Hessen",
    "wof:name":"Marianne Fehr",
    "wof:placetype":"venue"
},
  "geometry": {"coordinates":[9.541955,51.130573],"type":"Point"}
}