{
  "type": "Feature",
  "properties": {
    "iso:country":"DE",
    "sg:address":"Spitzwegstr. 42",
    "sg:city":"Ottobrunn",
    "sg:phone":"+49 89/6010122",
    "sg:postcode":"85521",
    "sg:province":"Bayern",
    "wof:name":"Erben & Partner Gmbh",
    "wof:placetype":"venue"
},
  "geometry": {"coordinates":[11.6915073395,48.0670928955],"type":"Point"}
}