{
  "type": "Feature",
  "properties": {
    "iso:country":"DE",
    "sg:address":"Burg-Layer-Str. 16",
    "sg:city":"R\u00fcmmelsheim",
    "sg:phone":"+49 4967/2146512",
    "sg:postcode":"55452",
    "sg:province":"Rheinland-Pfalz",
    "wof:name":"Manfred Pieroth",
    "wof:placetype":"venue"
},
  "geometry": {"coordinates":[7.86445,49.929703],"type":"Point"}
}