{
  "type": "Feature",
  "properties": {
    "iso:country":"DE",
    "sg:address":"Flechtdorfer Str. 3a",
    "sg:city":"Korbach",
    "sg:phone":"+49 5631/4021",
    "sg:postcode":"34497",
    "sg:province":"Hessen",
    "wof:name":"Eisenberg-apotheke",
    "wof:placetype":"venue"
},
  "geometry": {"coordinates":[8.870618,51.277058],"type":"Point"}
}