{
  "type": "Feature",
  "properties": {
    "iso:country":"DE",
    "sg:address":"Hauptstr. 25",
    "sg:city":"Illmensee",
    "sg:phone":"+49 7558/1269",
    "sg:postcode":"88636",
    "sg:province":"Baden-W\u00fcrttemberg",
    "wof:name":"Seest\u00fcble",
    "wof:placetype":"venue"
},
  "geometry": {"coordinates":[9.3748722076,47.8624534607],"type":"Point"}
}