{
  "type": "Feature",
  "properties": {
    "iso:country":"DE",
    "sg:address":"Heckingstr. 12-14",
    "sg:city":"Saarburg",
    "sg:postcode":"54439",
    "sg:province":"Rheinland-Pfalz",
    "wof:name":"Markant",
    "wof:placetype":"venue"
},
  "geometry": {"coordinates":[6.5462708473,49.6070594788],"type":"Point"}
}