{
  "type": "Feature",
  "properties": {
    "iso:country":"DE",
    "sg:address":"Schmellerstr. 21",
    "sg:city":"M\u00fcnchen",
    "sg:phone":"+49 89/779531",
    "sg:postcode":"80337",
    "sg:province":"Bayern",
    "wof:name":"Bauer Und Balogh Rechtsanw\u00e4lte Partnerschaft",
    "wof:placetype":"venue"
},
  "geometry": {"coordinates":[11.5516138077,48.1253585815],"type":"Point"}
}