{
  "type": "Feature",
  "properties": {
    "iso:country":"DE",
    "sg:address":"Kurt-Schumacher-Str. 71",
    "sg:city":"Langen",
    "sg:phone":"+49 6103/52952",
    "sg:postcode":"63225",
    "sg:province":"Hessen",
    "wof:name":"Proinvest-immobilien- Vermittlungs- Gmbh",
    "wof:placetype":"venue"
},
  "geometry": {"coordinates":[8.683767,49.981247],"type":"Point"}
}