{
  "type": "Feature",
  "properties": {
    "iso:country":"DE",
    "sg:address":"Kindergartenstr. 1",
    "sg:city":"Am\u00f6neburg",
    "sg:phone":"+49 6429/7356",
    "sg:postcode":"35287",
    "sg:province":"Hessen",
    "wof:name":"Ewald Schick",
    "wof:placetype":"venue"
},
  "geometry": {"coordinates":[8.913271,50.764572],"type":"Point"}
}