{
  "type": "Feature",
  "properties": {
    "iso:country":"DE",
    "sg:address":"An der Pferdsleite 7",
    "sg:city":"Obertrubach",
    "sg:phone":"+49 9245/367",
    "sg:postcode":"91286",
    "sg:province":"Bayern",
    "wof:name":"Georg Neuner",
    "wof:placetype":"venue"
},
  "geometry": {"coordinates":[11.3435649872,49.6937866211],"type":"Point"}
}