{
  "type": "Feature",
  "properties": {
    "iso:country":"DE",
    "sg:address":"Mainaustr. 6",
    "sg:city":"Konstanz",
    "sg:phone":"+49 7531/65815",
    "sg:postcode":"78464",
    "sg:province":"Baden-W\u00fcrttemberg",
    "wof:name":"Destille",
    "wof:placetype":"venue"
},
  "geometry": {"coordinates":[9.1808986664,47.6680717468],"type":"Point"}
}