{
  "type": "Feature",
  "properties": {
    "iso:country":"DE",
    "sg:address":"Herrengasse 2",
    "sg:city":"Wilgartswiesen",
    "sg:phone":"+49 6392/589",
    "sg:postcode":"76848",
    "sg:province":"Rheinland-Pfalz",
    "wof:name":"Heinz Br\u00f6del",
    "wof:placetype":"venue"
},
  "geometry": {"coordinates":[7.879275,49.209827],"type":"Point"}
}