{
  "type": "Feature",
  "properties": {
    "iso:country":"DE",
    "sg:address":"H\u00f6felstr. 15",
    "sg:city":"Bodelshausen",
    "sg:phone":"+49 7471/73447",
    "sg:postcode":"72411",
    "sg:province":"Baden-W\u00fcrttemberg",
    "wof:name":"Strasser Und B\u00e4chle",
    "wof:placetype":"venue"
},
  "geometry": {"coordinates":[8.96172,48.38393],"type":"Point"}
}