{
  "type": "Feature",
  "properties": {
    "iso:country":"DE",
    "sg:address":"Haeberlinstr.40",
    "sg:city":"Frankfurt",
    "sg:phone":"+49 69",
    "sg:postcode":"60431",
    "sg:province":"Hessen",
    "wof:name":"Evangelisches Jugendwerk Hessen",
    "wof:placetype":"venue"
},
  "geometry": {"coordinates":[8.658381,50.151264],"type":"Point"}
}