{
  "type": "Feature",
  "properties": {
    "iso:country":"DE",
    "sg:address":"Meerstr. 55",
    "sg:city":"Sankt Augustin",
    "sg:phone":"+49 2241/338399",
    "sg:postcode":"53757",
    "sg:province":"Nordrhein-Westfalen",
    "wof:name":"Ingrid Klinger Gmbh",
    "wof:placetype":"venue"
},
  "geometry": {"coordinates":[7.201211,50.784313],"type":"Point"}
}