{
  "type": "Feature",
  "properties": {
    "iso:country":"DE",
    "sg:address":"K\u00f6lner Str. 29 A",
    "sg:city":"Ennepetal",
    "sg:phone":"+49 2333/3534",
    "sg:postcode":"58256",
    "sg:province":"Nordrhein-Westfalen",
    "wof:name":"Peter F\u00fcrstenow",
    "wof:placetype":"venue"
},
  "geometry": {"coordinates":[7.346714,51.307472],"type":"Point"}
}