{
  "type": "Feature",
  "properties": {
    "iso:country":"DE",
    "sg:address":"Zeltendorf Bachh\u00e4user",
    "sg:city":"K\u00f6tzting",
    "sg:phone":"+49 9941/90083",
    "sg:postcode":"93444",
    "sg:province":"Bayern",
    "wof:name":"M Und B. Simstich",
    "wof:placetype":"venue"
},
  "geometry": {"coordinates":[12.8545541763,49.174747467],"type":"Point"}
}