{
  "type": "Feature",
  "properties": {
    "iso:country":"DE",
    "sg:address":"Oberbolheimer Str.",
    "sg:city":"N\u00f6rvenich",
    "sg:phone":"+49 2426/6744",
    "sg:postcode":"52388",
    "sg:province":"Nordrhein-Westfalen",
    "wof:name":"Otto Firchau",
    "wof:placetype":"venue"
},
  "geometry": {"coordinates":[6.6473221779,50.8094825745],"type":"Point"}
}