{
  "type": "Feature",
  "properties": {
    "iso:country":"DE",
    "sg:address":"Sandweg 34",
    "sg:city":"Steinfurt",
    "sg:phone":"+49 2552/3155",
    "sg:postcode":"48565",
    "sg:province":"Nordrhein-Westfalen",
    "wof:name":"Bernhard Herbes",
    "wof:placetype":"venue"
},
  "geometry": {"coordinates":[7.398758,52.108032],"type":"Point"}
}