{
  "type": "Feature",
  "properties": {
    "iso:country":"DE",
    "sg:address":"Curiestr 4",
    "sg:city":"Stuttgart",
    "sg:phone":"+49 711/9019039",
    "sg:postcode":"70563",
    "sg:province":"Baden-W\u00fcrttemberg",
    "wof:name":"B & B Systemhaus Gmbh",
    "wof:placetype":"venue"
},
  "geometry": {"coordinates":[9.113112,48.738274],"type":"Point"}
}