{
  "type": "Feature",
  "properties": {
    "iso:country":"DE",
    "sg:address":"Marthweg 38",
    "sg:city":"N\u00fcrnberg",
    "sg:phone":"+49 911/883827",
    "sg:postcode":"90455",
    "sg:province":"Bayern",
    "wof:name":"Waldgastst\u00e4tte Weiherhaus",
    "wof:placetype":"venue"
},
  "geometry": {"coordinates":[11.0739078522,49.3854103088],"type":"Point"}
}