{
  "type": "Feature",
  "properties": {
    "iso:country":"DE",
    "sg:address":"Im Lohr 49",
    "sg:city":"Mannheim",
    "sg:phone":"+49 621/825040",
    "sg:postcode":"68199",
    "sg:province":"Baden-W\u00fcrttemberg",
    "wof:name":"B. H\u00f6rner Immobilienmakler",
    "wof:placetype":"venue"
},
  "geometry": {"coordinates":[8.4793815613,49.4616088867],"type":"Point"}
}