{
  "type": "Feature",
  "properties": {
    "iso:country":"DE",
    "sg:address":"Leipziger Str. 59",
    "sg:city":"Frankfurt am Main",
    "sg:phone":"+49 69/97070524",
    "sg:postcode":"60487",
    "sg:province":"Hessen",
    "wof:name":"Akte X - Die Akten Sind Noch Nicht Geschlossen",
    "wof:placetype":"venue"
},
  "geometry": {"coordinates":[8.6443767548,50.1228675842],"type":"Point"}
}