{
  "type": "Feature",
  "properties": {
    "iso:country":"DE",
    "sg:address":"Schanzenstr. 48",
    "sg:city":"Hamburg",
    "sg:phone":"+49 40/4313890",
    "sg:postcode":"20357",
    "sg:province":"Hamburg",
    "wof:name":"Netzpiloten Ag",
    "wof:placetype":"venue"
},
  "geometry": {"coordinates":[9.965635,53.561153],"type":"Point"}
}