{
  "type": "Feature",
  "properties": {
    "iso:country":"DE",
    "sg:address":"R\u00f6ntgenstr. 8",
    "sg:city":"Gronau",
    "sg:phone":"+49 2562/96650",
    "sg:postcode":"48599",
    "sg:province":"Nordrhein-Westfalen",
    "wof:name":"Deitmers Kran- Und Stahlbau Gmbh",
    "wof:placetype":"venue"
},
  "geometry": {"coordinates":[7.072728,52.212189],"type":"Point"}
}