{
  "type": "Feature",
  "properties": {
    "iso:country":"DE",
    "sg:address":"Sittenbacher Str. 1",
    "sg:city":"Schnaittach",
    "sg:phone":"+49 9153/7940",
    "sg:postcode":"91220",
    "sg:province":"Bayern",
    "wof:name":"Ignaz Haider",
    "wof:placetype":"venue"
},
  "geometry": {"coordinates":[11.375606,49.553795],"type":"Point"}
}