{
  "type": "Feature",
  "properties": {
    "iso:country":"DE",
    "sg:address":"Schwieringhauser Str. 16",
    "sg:city":"Dortmund",
    "sg:phone":"+49 231/3339498",
    "sg:postcode":"44359",
    "sg:province":"Nordrhein-Westfalen",
    "wof:name":"Spann Fix Gmbh",
    "wof:placetype":"venue"
},
  "geometry": {"coordinates":[7.414904,51.579094],"type":"Point"}
}