{
  "type": "Feature",
  "properties": {
    "iso:country":"DE",
    "sg:address":"Scharnhorststr. 6",
    "sg:city":"Regensburg",
    "sg:phone":"+49 941/35041",
    "sg:postcode":"93049",
    "sg:province":"Bayern",
    "wof:name":"Heerde Und Wimmer Ingenieurb\u00fcro",
    "wof:placetype":"venue"
},
  "geometry": {"coordinates":[12.060634613,49.0138282776],"type":"Point"}
}