{
  "type": "Feature",
  "properties": {
    "iso:country":"DE",
    "sg:address":"Gaggenau",
    "sg:city":"Gaggenau",
    "sg:phone":"+49 7222/140",
    "sg:postcode":"76571",
    "sg:province":"Baden-W\u00fcrttemberg",
    "wof:name":"Volksbank Baden-baden Rastatt Eg",
    "wof:placetype":"venue"
},
  "geometry": {"coordinates":[8.19872,48.862316],"type":"Point"}
}