{
  "type": "Feature",
  "properties": {
    "iso:country":"DE",
    "sg:address":"Riekestr. 10",
    "sg:city":"Greven",
    "sg:phone":"+49 2571/1222",
    "sg:postcode":"48268",
    "sg:province":"Nordrhein-Westfalen",
    "wof:name":"Franz Und Roswitha Vennekamp Masseure",
    "wof:placetype":"venue"
},
  "geometry": {"coordinates":[7.613435,52.095573],"type":"Point"}
}