{
  "type": "Feature",
  "properties": {
    "iso:country":"DE",
    "sg:address":"Genossenschaftsweg 1",
    "sg:city":"Wolmirstedt",
    "sg:phone":"+49 39206/68050",
    "sg:postcode":"39326",
    "sg:province":"Sachsen-Anhalt",
    "wof:name":"Sbr Bautenschutz Gmbh",
    "wof:placetype":"venue"
},
  "geometry": {"coordinates":[11.6234178543,52.2563743591],"type":"Point"}
}