{
  "type": "Feature",
  "properties": {
    "iso:country":"DE",
    "sg:address":"Stra\u00dfe 13",
    "sg:city":"N\u00fcmbrecht",
    "sg:phone":"+49 2295/5307",
    "sg:postcode":"51588",
    "sg:province":"Nordrhein-Westfalen",
    "wof:name":"Mpo Kellerbau Gmbh",
    "wof:placetype":"venue"
},
  "geometry": {"coordinates":[7.493733,50.870289],"type":"Point"}
}