{
  "type": "Feature",
  "properties": {
    "iso:country":"DE",
    "sg:address":"Thielaustr. 5",
    "sg:city":"Dresden",
    "sg:phone":"+49 351/3161837",
    "sg:postcode":"01309",
    "sg:province":"Sachsen",
    "wof:name":"Hans-karl Schmidt",
    "wof:placetype":"venue"
},
  "geometry": {"coordinates":[13.8012542725,51.0492706299],"type":"Point"}
}