{
  "type": "Feature",
  "properties": {
    "iso:country":"DE",
    "sg:address":"Richthofenstr. 19",
    "sg:city":"Billigheim-Ingenheim",
    "sg:phone":"+49 6349/8655",
    "sg:postcode":"76831",
    "sg:province":"Rheinland-Pfalz",
    "wof:name":"Erich Eck Steuerberater",
    "wof:placetype":"venue"
},
  "geometry": {"coordinates":[8.1028814316,49.1362609863],"type":"Point"}
}