{
  "type": "Feature",
  "properties": {
    "iso:country":"DE",
    "sg:address":"Alte Stuttgarter Str. 5",
    "sg:city":"Magstadt",
    "sg:phone":"+49 7159/42457",
    "sg:postcode":"71106",
    "sg:province":"Baden-W\u00fcrttemberg",
    "wof:name":"E. Schmidt",
    "wof:placetype":"venue"
},
  "geometry": {"coordinates":[8.964503,48.742561],"type":"Point"}
}