{
  "type": "Feature",
  "properties": {
    "iso:country":"DE",
    "sg:address":"Max-Planck-Str. 23",
    "sg:city":"Mahlow",
    "sg:phone":"+49 3379/321841",
    "sg:postcode":"15831",
    "sg:province":"Brandenburg",
    "wof:name":"Andreas Vater Immobilienmakler",
    "wof:placetype":"venue"
},
  "geometry": {"coordinates":[13.3909015656,52.3707008362],"type":"Point"}
}