{
  "type": "Feature",
  "properties": {
    "iso:country":"DE",
    "sg:address":"Gr\u00e4fstr. 97",
    "sg:city":"Frankfurt",
    "sg:postcode":"60487",
    "sg:province":"Hessen",
    "wof:name":"Equinet Expansion Stage Capital Fonds Nr. 1",
    "wof:placetype":"venue"
},
  "geometry": {"coordinates":[8.650607,50.121258],"type":"Point"}
}