{
  "type": "Feature",
  "properties": {
    "iso:country":"DE",
    "sg:address":"Passauer Stra\u00dfe 20",
    "sg:city":"Ruderting",
    "sg:phone":"+49 172",
    "sg:postcode":"94161",
    "sg:province":"Bayern",
    "wof:name":"Timo Boll",
    "wof:placetype":"venue"
},
  "geometry": {"coordinates":[13.408778,48.653141],"type":"Point"}
}