{
  "type": "Feature",
  "properties": {
    "iso:country":"DE",
    "sg:address":"Graf-Galen-Str. 6",
    "sg:city":"Beckum",
    "sg:phone":"+49 2525/7969",
    "sg:postcode":"59269",
    "sg:province":"Nordrhein-Westfalen",
    "wof:name":"B. Lillmanst\u00f6ns",
    "wof:placetype":"venue"
},
  "geometry": {"coordinates":[8.0242643356,51.8018074036],"type":"Point"}
}