{
  "type": "Feature",
  "properties": {
    "iso:country":"DE",
    "sg:address":"Lerchenbergstr. 16",
    "sg:city":"Ostfildern",
    "sg:phone":"+49 711/3401620",
    "sg:postcode":"73760",
    "sg:province":"Baden-W\u00fcrttemberg",
    "wof:name":"Muster-straub Gmbh",
    "wof:placetype":"venue"
},
  "geometry": {"coordinates":[9.306314,48.709202],"type":"Point"}
}