{
  "type": "Feature",
  "properties": {
    "iso:country":"DE",
    "sg:address":"Dircksenstr. 52",
    "sg:city":"Berlin",
    "sg:postcode":"10178",
    "sg:province":"Berlin",
    "wof:name":"Fmk Finanzdienstleistung Gmbh",
    "wof:placetype":"venue"
},
  "geometry": {"coordinates":[13.4038496017,52.5233955383],"type":"Point"}
}