{
  "type": "Feature",
  "properties": {
    "iso:country":"DE",
    "sg:address":"Weinbergsblick 9",
    "sg:city":"Weinsheim",
    "sg:phone":"+49 6758/92570",
    "sg:postcode":"55595",
    "sg:province":"Rheinland-Pfalz",
    "wof:name":"Helmut Jost",
    "wof:placetype":"venue"
},
  "geometry": {"coordinates":[7.7665939331,49.8346252441],"type":"Point"}
}