{
  "type": "Feature",
  "properties": {
    "iso:country":"DE",
    "sg:address":"Blenheimstr. 4",
    "sg:city":"Berlin",
    "sg:phone":"+49 30/5437757",
    "sg:postcode":"12685",
    "sg:province":"Berlin",
    "wof:name":"Rei\u00dfmann & Serzisko",
    "wof:placetype":"venue"
},
  "geometry": {"coordinates":[13.553571701,52.541721344],"type":"Point"}
}