{
  "type": "Feature",
  "properties": {
    "iso:country":"DE",
    "sg:address":"Klosterstr. 75",
    "sg:city":"Lobbach",
    "sg:phone":"+49 6226/41187",
    "sg:postcode":"74931",
    "sg:province":"Baden-W\u00fcrttemberg",
    "wof:name":"Carl Personal-leasing",
    "wof:placetype":"venue"
},
  "geometry": {"coordinates":[8.870084,49.35313],"type":"Point"}
}