{
  "type": "Feature",
  "properties": {
    "iso:country":"DE",
    "sg:address":"Stiftsfeldstr. 81",
    "sg:city":"H\u00fcllhorst",
    "sg:phone":"+49 5744/1598",
    "sg:postcode":"32609",
    "sg:province":"Nordrhein-Westfalen",
    "wof:name":"Friedr. P\u00f6rtner",
    "wof:placetype":"venue"
},
  "geometry": {"coordinates":[8.624853,52.262379],"type":"Point"}
}