{
  "type": "Feature",
  "properties": {
    "iso:country":"DE",
    "sg:address":"Ludwigsplatz 3",
    "sg:city":"Apolda",
    "sg:phone":"+49 3644/550702",
    "sg:postcode":"99510",
    "sg:province":"Th\u00fcringen",
    "wof:name":"Hans H\u00e4rter",
    "wof:placetype":"venue"
},
  "geometry": {"coordinates":[11.52095,51.020828],"type":"Point"}
}