{
  "type": "Feature",
  "properties": {
    "iso:country":"DE",
    "sg:address":"Ringau 21",
    "sg:city":"Leinefelde",
    "sg:phone":"+49 3605/512532",
    "sg:postcode":"37327",
    "sg:province":"Th\u00fcringen",
    "wof:name":"Fiedler Trockenbau Gmbh",
    "wof:placetype":"venue"
},
  "geometry": {"coordinates":[10.32004,51.388988],"type":"Point"}
}