{
  "type": "Feature",
  "properties": {
    "iso:country":"DE",
    "sg:address":"Millbergerweg 1",
    "sg:city":"Neuhaus",
    "sg:phone":"+49 8503/90040",
    "sg:postcode":"94152",
    "sg:province":"Bayern",
    "wof:name":"Domizil Hotel & Restaurant Gmbh",
    "wof:placetype":"venue"
},
  "geometry": {"coordinates":[13.4223423004,48.4637451172],"type":"Point"}
}