{
  "type": "Feature",
  "properties": {
    "iso:country":"DE",
    "sg:address":"Dorfstr 1",
    "sg:city":"Schwabhausen",
    "sg:phone":"+49 8138/666012",
    "sg:postcode":"85247",
    "sg:province":"Bayern",
    "wof:name":"Dt - Montage Dach-wand Und Fassaden Systeme Gmbh",
    "wof:placetype":"venue"
},
  "geometry": {"coordinates":[11.371429,48.296696],"type":"Point"}
}