{
  "type": "Feature",
  "properties": {
    "iso:country":"DE",
    "sg:address":"Paradiesstr. 14",
    "sg:city":"D\u00fcren",
    "sg:phone":"+49 2421/44254",
    "sg:postcode":"52349",
    "sg:province":"Nordrhein-Westfalen",
    "wof:name":"Paul Keuth",
    "wof:placetype":"venue"
},
  "geometry": {"coordinates":[6.474588871,50.8046455383],"type":"Point"}
}