{
  "type": "Feature",
  "properties": {
    "iso:country":"DE",
    "sg:address":"Uhinger Str 91",
    "sg:city":"Albershausen",
    "sg:phone":"+49 7161/389960",
    "sg:postcode":"73095",
    "sg:province":"Baden-W\u00fcrttemberg",
    "wof:name":"H-o-t H\u00e4rte- Und Oberfl\u00e4chentechnik Gmbh & Co Kg",
    "wof:placetype":"venue"
},
  "geometry": {"coordinates":[9.5711698532,48.6998329163],"type":"Point"}
}