{
  "type": "Feature",
  "properties": {
    "iso:country":"DE",
    "sg:address":"Max-Planck-Str. 9 a",
    "sg:city":"Friedrichsdorf",
    "sg:phone":"+49 6172/954682",
    "sg:postcode":"61381",
    "sg:province":"Hessen",
    "wof:name":"Dieter Riegelhof",
    "wof:placetype":"venue"
},
  "geometry": {"coordinates":[8.6568889618,50.2588882446],"type":"Point"}
}