{
  "type": "Feature",
  "properties": {
    "iso:country":"DE",
    "sg:address":"Zum Breitmaar 10",
    "sg:city":"Kerpen",
    "sg:phone":"+49 2273/53401",
    "sg:postcode":"50170",
    "sg:province":"Nordrhein-Westfalen",
    "wof:name":"C. Br\u00fchl",
    "wof:placetype":"venue"
},
  "geometry": {"coordinates":[6.6723527908,50.907169342],"type":"Point"}
}