{
  "type": "Feature",
  "properties": {
    "iso:country":"DE",
    "sg:address":"Marktstr 65",
    "sg:city":"Stuttgart",
    "sg:phone":"+49 4971/1560678",
    "sg:postcode":"70178",
    "sg:province":"Baden-W\u00fcrttemberg",
    "wof:name":"Citibank Privatkunden Ag",
    "wof:placetype":"venue"
},
  "geometry": {"coordinates":[9.213304,48.8055],"type":"Point"}
}