{
  "type": "Feature",
  "properties": {
    "iso:country":"DE",
    "sg:address":"Zietenstr. 10",
    "sg:city":"Chemnitz",
    "sg:phone":"+49 371/4025088",
    "sg:postcode":"09130",
    "sg:province":"Sachsen",
    "wof:name":"Bestattungshaus Zietenstra\u00dfe Gmbh",
    "wof:placetype":"venue"
},
  "geometry": {"coordinates":[12.939358,50.831928],"type":"Point"}
}