{
  "type": "Feature",
  "properties": {
    "iso:country":"DE",
    "sg:address":"Effertzgasse 36",
    "sg:city":"D\u00fcren",
    "sg:phone":"+49 2421/981040",
    "sg:postcode":"52353",
    "sg:province":"Nordrhein-Westfalen",
    "wof:name":"A. A. S.- Atlas Ambulanz Service Gmbh",
    "wof:placetype":"venue"
},
  "geometry": {"coordinates":[6.4644417763,50.8228302002],"type":"Point"}
}