{
  "type": "Feature",
  "properties": {
    "iso:country":"DE",
    "sg:address":"Finowstr. 11",
    "sg:city":"Berlin",
    "sg:phone":"+49 30",
    "sg:postcode":"10247",
    "sg:province":"Berlin",
    "wof:name":"Ausstellungssysteme Faltbar & Modular",
    "wof:placetype":"venue"
},
  "geometry": {"coordinates":[13.467584,52.51189],"type":"Point"}
}