{
  "type": "Feature",
  "properties": {
    "iso:country":"DE",
    "sg:address":"Dorf 46",
    "sg:city":"L\u00fcbben",
    "sg:phone":"+49 3546/180902",
    "sg:postcode":"15907",
    "sg:province":"Brandenburg",
    "wof:name":"Torsten Weichert",
    "wof:placetype":"venue"
},
  "geometry": {"coordinates":[13.858425,51.937199],"type":"Point"}
}