{
  "type": "Feature",
  "properties": {
    "iso:country":"DE",
    "sg:address":"Marktplatz 8",
    "sg:city":"Zierenberg",
    "sg:phone":"+49 5606/3600",
    "sg:postcode":"34289",
    "sg:province":"Hessen",
    "wof:name":"Forum",
    "wof:placetype":"venue"
},
  "geometry": {"coordinates":[9.301874,51.36858],"type":"Point"}
}