{
  "type": "Feature",
  "properties": {
    "iso:country":"DE",
    "sg:address":"Dritte Industriestr.",
    "sg:city":"Hockenheim",
    "sg:phone":"+49 6205/270",
    "sg:postcode":"68766",
    "sg:province":"Baden-W\u00fcrttemberg",
    "wof:name":"Joseph V\u00f6gele Ag",
    "wof:placetype":"venue"
},
  "geometry": {"coordinates":[8.536785,49.336826],"type":"Point"}
}