{
  "type": "Feature",
  "properties": {
    "iso:country":"DE",
    "sg:address":"Oststr. 4",
    "sg:city":"Hadamar",
    "sg:phone":"+49 6433/4568",
    "sg:postcode":"65589",
    "sg:province":"Hessen",
    "wof:name":"H\u00f6hler Heizungsbau Gmbh",
    "wof:placetype":"venue"
},
  "geometry": {"coordinates":[8.0659389496,50.4728622437],"type":"Point"}
}