{
  "type": "Feature",
  "properties": {
    "iso:country":"DE",
    "sg:address":"Weinhaldenstr. 12",
    "sg:city":"Wendlingen",
    "sg:postcode":"73240",
    "sg:province":"Baden-W\u00fcrttemberg",
    "wof:name":"Zirn Verm\u00f6gens- Verwaltungs Gmbh",
    "wof:placetype":"venue"
},
  "geometry": {"coordinates":[9.3820285797,48.6794433594],"type":"Point"}
}