{
  "type": "Feature",
  "properties": {
    "iso:country":"DE",
    "sg:address":"Robert-Bosch-Str. 6/1",
    "sg:city":"K\u00fcnzelsau",
    "sg:phone":"+49 7940/92910",
    "sg:postcode":"74653",
    "sg:province":"Baden-W\u00fcrttemberg",
    "wof:name":"Hkr Climatec Gmbh",
    "wof:placetype":"venue"
},
  "geometry": {"coordinates":[9.68507,49.255497],"type":"Point"}
}