{
  "type": "Feature",
  "properties": {
    "iso:country":"DE",
    "sg:address":"Axelbachstr. 15",
    "sg:city":"Wolnzach",
    "sg:phone":"+49 8442/915820",
    "sg:postcode":"85283",
    "sg:province":"Bayern",
    "wof:name":"Vud Prospekt-service Gmbh",
    "wof:placetype":"venue"
},
  "geometry": {"coordinates":[11.641392,48.633137],"type":"Point"}
}