{
  "type": "Feature",
  "properties": {
    "iso:country":"DE",
    "sg:address":"Baderinn 1",
    "sg:city":"Zwiesel",
    "sg:phone":"+49 9922/1442",
    "sg:postcode":"94227",
    "sg:province":"Bayern",
    "wof:name":"Pension Elke S\u00f6ller",
    "wof:placetype":"venue"
},
  "geometry": {"coordinates":[13.2360715866,49.0236740112],"type":"Point"}
}