{
  "type": "Feature",
  "properties": {
    "iso:country":"DE",
    "sg:address":"Marktstr. 40",
    "sg:city":"Nieheim",
    "sg:phone":"+49 5274/952299",
    "sg:postcode":"33039",
    "sg:province":"Nordrhein-Westfalen",
    "wof:name":"City-grill",
    "wof:placetype":"venue"
},
  "geometry": {"coordinates":[9.1091766357,51.8040542603],"type":"Point"}
}