{
  "type": "Feature",
  "properties": {
    "iso:country":"DE",
    "sg:address":"Hahnemannstr. 24",
    "sg:city":"Velbert",
    "sg:phone":"+49 2051/989038",
    "sg:postcode":"42549",
    "sg:province":"Nordrhein-Westfalen",
    "wof:name":"Axo Data Systems Gmbh",
    "wof:placetype":"venue"
},
  "geometry": {"coordinates":[7.0091629028,51.3495826721],"type":"Point"}
}