{
  "type": "Feature",
  "properties": {
    "iso:country":"DE",
    "sg:address":"Am Bahnhof 1",
    "sg:city":"Feldberg",
    "sg:phone":"+49 39831/20260",
    "sg:postcode":"17258",
    "sg:province":"Mecklenburg-Vorpommern",
    "wof:name":"Piccolo Am Bahnhof",
    "wof:placetype":"venue"
},
  "geometry": {"coordinates":[13.4323740005,53.3309135437],"type":"Point"}
}