{
  "type": "Feature",
  "properties": {
    "iso:country":"DE",
    "sg:address":"Nordwalder Str. 61",
    "sg:city":"Greven",
    "sg:phone":"+49 2571/55850",
    "sg:postcode":"48268",
    "sg:province":"Nordrhein-Westfalen",
    "wof:name":"Schulze Gronover Immobilien Verwaltungs- Gmbh",
    "wof:placetype":"venue"
},
  "geometry": {"coordinates":[7.5881748199,52.0936584473],"type":"Point"}
}