{
  "type": "Feature",
  "properties": {
    "iso:country":"DE",
    "sg:address":"Bergstr. 3",
    "sg:city":"Haan",
    "sg:phone":"+49 2104/61424",
    "sg:postcode":"42781",
    "sg:province":"Nordrhein-Westfalen",
    "wof:name":"Uwe Kampf",
    "wof:placetype":"venue"
},
  "geometry": {"coordinates":[7.012413,51.214203],"type":"Point"}
}