{
  "type": "Feature",
  "properties": {
    "iso:country":"DE",
    "sg:address":"Wilhelm-Riehl-Str. 41",
    "sg:city":"M\u00fcnchen",
    "sg:phone":"+49 89/54779215",
    "sg:postcode":"80687",
    "sg:province":"Bayern",
    "wof:name":"Luna Handels Gmbh",
    "wof:placetype":"venue"
},
  "geometry": {"coordinates":[11.5142526627,48.135723114],"type":"Point"}
}