{
  "type": "Feature",
  "properties": {
    "iso:country":"DE",
    "sg:address":"K\u00f6nigswinterer Str. 325",
    "sg:city":"K\u00f6nigswinter",
    "sg:phone":"+49 2223/912244",
    "sg:postcode":"53639",
    "sg:province":"Nordrhein-Westfalen",
    "wof:name":"Vr-immobilien Gmbh",
    "wof:placetype":"venue"
},
  "geometry": {"coordinates":[7.2535691261,50.6775016785],"type":"Point"}
}