{
  "type": "Feature",
  "properties": {
    "iso:country":"DE",
    "sg:address":"Gartenstr. 1",
    "sg:city":"Crinitz",
    "sg:phone":"+49 35324/38200",
    "sg:postcode":"03246",
    "sg:province":"Brandenburg",
    "wof:name":"I. Risse",
    "wof:placetype":"venue"
},
  "geometry": {"coordinates":[13.759885,51.737232],"type":"Point"}
}