{
  "type": "Feature",
  "properties": {
    "iso:country":"DE",
    "sg:address":"Kapellenstr. 2",
    "sg:city":"Mittelneufnach",
    "sg:phone":"+49 8262/623",
    "sg:postcode":"86868",
    "sg:province":"Bayern",
    "wof:name":"Orthop\u00e4die Deutschenbaur Gmbh",
    "wof:placetype":"venue"
},
  "geometry": {"coordinates":[10.5946035385,48.1764259338],"type":"Point"}
}