{
  "type": "Feature",
  "properties": {
    "iso:country":"DE",
    "sg:address":"Heschredder 98",
    "sg:city":"Hamburg",
    "sg:phone":"+49 40/503904",
    "sg:postcode":"22335",
    "sg:province":"Hamburg",
    "wof:name":"Werner Schultz Finanzberater",
    "wof:placetype":"venue"
},
  "geometry": {"coordinates":[10.0159692764,53.6311264038],"type":"Point"}
}