{
  "type": "Feature",
  "properties": {
    "iso:country":"DE",
    "sg:address":"Gro\u00dfe Gartenstr. 47",
    "sg:city":"Brandenburg",
    "sg:phone":"+49 3381/524626",
    "sg:postcode":"14776",
    "sg:province":"Brandenburg",
    "wof:name":"Deutsche Verm\u00f6gensberatung Ag",
    "wof:placetype":"venue"
},
  "geometry": {"coordinates":[12.5619440079,52.4028587341],"type":"Point"}
}