{
  "type": "Feature",
  "properties": {
    "iso:country":"DE",
    "sg:address":"Wolfsh\u00fcgelstr. 22",
    "sg:city":"Dresden",
    "sg:phone":"+49 351/2845595",
    "sg:postcode":"01324",
    "sg:province":"Sachsen",
    "wof:name":"Marktvereinigung Obst Und Gem\u00fcse Sachsen-anhalt E. V.",
    "wof:placetype":"venue"
},
  "geometry": {"coordinates":[13.8189668655,51.0612983704],"type":"Point"}
}