{
  "type": "Feature",
  "properties": {
    "iso:country":"DE",
    "sg:address":"Juliuspromenade 28",
    "sg:city":"W\u00fcrzburg",
    "sg:phone":"+49 931/50845",
    "sg:postcode":"97070",
    "sg:province":"Bayern",
    "wof:name":"Hanseatic Bank",
    "wof:placetype":"venue"
},
  "geometry": {"coordinates":[9.928878,49.796478],"type":"Point"}
}