{
  "type": "Feature",
  "properties": {
    "iso:country":"DE",
    "sg:address":"Postfach 201156:: 08013 Zwickau:: Germany.^^Bahnhofstr 1a::",
    "sg:city":"Zwickau",
    "sg:phone":"+49 375/39110",
    "sg:postcode":"08056",
    "sg:province":"Sachsen",
    "wof:name":"Volksbank Zwickau Eg",
    "wof:placetype":"venue"
},
  "geometry": {"coordinates":[12.49075,50.708969],"type":"Point"}
}