{
  "type": "Feature",
  "properties": {
    "iso:country":"DE",
    "sg:address":"Viehweg 7",
    "sg:city":"Hellwege",
    "sg:phone":"+49 4264/84224",
    "sg:postcode":"27367",
    "sg:province":"Niedersachsen",
    "wof:name":"W. Schloh",
    "wof:placetype":"venue"
},
  "geometry": {"coordinates":[9.2404413223,53.0744895935],"type":"Point"}
}