{
  "type": "Feature",
  "properties": {
    "iso:country":"DE",
    "sg:address":"Hansastr.",
    "sg:city":"Osnabr\u00fcck",
    "sg:postcode":"49090",
    "sg:province":"Niedersachsen",
    "wof:name":"Hellweg Die Profi-baum\u00e4rkte Gmbh",
    "wof:placetype":"venue"
},
  "geometry": {"coordinates":[8.0399398804,52.2850456238],"type":"Point"}
}