{
  "type": "Feature",
  "properties": {
    "iso:country":"DE",
    "sg:address":"Bergstr. 13",
    "sg:city":"Sulzbach-Laufen",
    "sg:phone":"+49 7976/598",
    "sg:postcode":"74429",
    "sg:province":"Baden-W\u00fcrttemberg",
    "wof:name":"Rainer J\u00e4ger Ingenieur",
    "wof:placetype":"venue"
},
  "geometry": {"coordinates":[9.8409957886,48.9655914307],"type":"Point"}
}