{
  "type": "Feature",
  "properties": {
    "iso:country":"DE",
    "sg:address":"Callinstr. 3",
    "sg:city":"Hannover",
    "sg:phone":"+49 511/7625544",
    "sg:postcode":"30167",
    "sg:province":"Niedersachsen",
    "wof:name":"Dr. K\u00dcke Gmbh",
    "wof:placetype":"venue"
},
  "geometry": {"coordinates":[9.717235,52.38599],"type":"Point"}
}