{
  "type": "Feature",
  "properties": {
    "iso:country":"DE",
    "sg:address":"Lerchenweg 2",
    "sg:city":"Coppenbr\u00fcgge",
    "sg:phone":"+49 5156/381",
    "sg:postcode":"31863",
    "sg:province":"Niedersachsen",
    "wof:name":"Ernst-august Feuerhake",
    "wof:placetype":"venue"
},
  "geometry": {"coordinates":[9.5526371002,52.1188850403],"type":"Point"}
}