{
  "type": "Feature",
  "properties": {
    "iso:country":"DE",
    "sg:address":"Immendorfer Str 17",
    "sg:city":"Br\u00fchl",
    "sg:phone":"+49 2232/76300",
    "sg:postcode":"50321",
    "sg:province":"Nordrhein-Westfalen",
    "wof:name":"Dpi Gmbh",
    "wof:placetype":"venue"
},
  "geometry": {"coordinates":[6.920303,50.841652],"type":"Point"}
}