{
  "type": "Feature",
  "properties": {
    "iso:country":"DE",
    "sg:address":"Augasse 16",
    "sg:city":"Niddatal",
    "sg:phone":"+49 6034/2821",
    "sg:postcode":"61194",
    "sg:province":"Hessen",
    "wof:name":"Berger-bau Gmbh",
    "wof:placetype":"venue"
},
  "geometry": {"coordinates":[8.795697,50.280731],"type":"Point"}
}