{
  "type": "Feature",
  "properties": {
    "iso:country":"DE",
    "sg:address":"Westenhellweg 121",
    "sg:city":"Dortmund",
    "sg:phone":"+49 231/140041",
    "sg:postcode":"44137",
    "sg:province":"Nordrhein-Westfalen",
    "wof:name":"Holiday Express Reiseb\u00fcro Inh. Heico Reiseb\u00fcro Gmbh",
    "wof:placetype":"venue"
},
  "geometry": {"coordinates":[7.4564790726,51.5138893127],"type":"Point"}
}