{
  "type": "Feature",
  "properties": {
    "iso:country":"DE",
    "sg:address":"Stresemannstr. 12",
    "sg:city":"Bad Nauheim",
    "sg:phone":"+49 6032/91260",
    "sg:postcode":"61231",
    "sg:province":"Hessen",
    "wof:name":"Central-apotheke",
    "wof:placetype":"venue"
},
  "geometry": {"coordinates":[8.73961,50.364479],"type":"Point"}
}