{
  "type": "Feature",
  "properties": {
    "iso:country":"DE",
    "sg:address":"Grabenkamp 39 d",
    "sg:city":"Bielefeld",
    "sg:phone":"+49 521/411661",
    "sg:postcode":"33649",
    "sg:province":"Nordrhein-Westfalen",
    "wof:name":"Willkommen Bei Steinhudermeer.net",
    "wof:placetype":"venue"
},
  "geometry": {"coordinates":[8.481024,51.984325],"type":"Point"}
}