{
  "type": "Feature",
  "properties": {
    "iso:country":"DE",
    "sg:address":"Carl-Von-Linde-Str. 5",
    "sg:city":"Eberswalde",
    "sg:phone":"+49 4933/3427090",
    "sg:postcode":"16225",
    "sg:province":"Brandenburg",
    "wof:name":"Fensterwelt-metall-u. Kunststoffbau Gmbh",
    "wof:placetype":"venue"
},
  "geometry": {"coordinates":[13.7924423218,52.8587722778],"type":"Point"}
}