{
  "type": "Feature",
  "properties": {
    "iso:country":"DE",
    "sg:address":"Gremmendorfer Weg 5",
    "sg:city":"M\u00fcnster",
    "sg:phone":"+49 251/62336",
    "sg:postcode":"48167",
    "sg:province":"Nordrhein-Westfalen",
    "wof:name":"A. Heynemann",
    "wof:placetype":"venue"
},
  "geometry": {"coordinates":[7.668327,51.928768],"type":"Point"}
}