{
  "type": "Feature",
  "properties": {
    "iso:country":"DE",
    "sg:address":"Merianstr. 18",
    "sg:city":"Bochum",
    "sg:phone":"+49 234/704917",
    "sg:postcode":"44801",
    "sg:province":"Nordrhein-Westfalen",
    "wof:name":"Gerd Schwerdt",
    "wof:placetype":"venue"
},
  "geometry": {"coordinates":[7.264934,51.454155],"type":"Point"}
}