{
  "type": "Feature",
  "properties": {
    "iso:country":"DE",
    "sg:address":"Hessels H\u00f6he 8",
    "sg:city":"Vechta",
    "sg:phone":"+49 4447/1814",
    "sg:postcode":"49377",
    "sg:province":"Niedersachsen",
    "wof:name":"A. W\u00f6rdemann",
    "wof:placetype":"venue"
},
  "geometry": {"coordinates":[8.2346029282,52.7689933777],"type":"Point"}
}