{
  "type": "Feature",
  "properties": {
    "iso:country":"DE",
    "sg:address":"Oberstr. 8",
    "sg:city":"A\u00dflar",
    "sg:phone":"+49 6441/85201",
    "sg:postcode":"35614",
    "sg:province":"Hessen",
    "wof:name":"Gerd Kunzig Augenoptiker",
    "wof:placetype":"venue"
},
  "geometry": {"coordinates":[8.4639720917,50.591003418],"type":"Point"}
}