{
  "type": "Feature",
  "properties": {
    "iso:country":"DE",
    "sg:address":"Sch\u00fctzengasse 8",
    "sg:city":"Weimar",
    "sg:phone":"+49 3643/202439",
    "sg:postcode":"99423",
    "sg:province":"Th\u00fcringen",
    "wof:name":"E. Lehmann",
    "wof:placetype":"venue"
},
  "geometry": {"coordinates":[11.3263978958,50.9782676697],"type":"Point"}
}