{
  "type": "Feature",
  "properties": {
    "iso:country":"DE",
    "sg:address":"Kleinb\u00fcllesheimer Str. 87",
    "sg:city":"Euskirchen",
    "sg:postcode":"53881",
    "sg:province":"Nordrhein-Westfalen",
    "wof:name":"B. T. G. Transporte Ltd. Filiale Euskirchen",
    "wof:placetype":"venue"
},
  "geometry": {"coordinates":[6.8294620514,50.6742248535],"type":"Point"}
}