{
  "type": "Feature",
  "properties": {
    "iso:country":"DE",
    "sg:address":"Am Schwanenbach 119",
    "sg:city":"Osnabr\u00fcck",
    "sg:phone":"+49 541/43526",
    "sg:postcode":"49080",
    "sg:province":"Niedersachsen",
    "wof:name":"Hartwig Peter Zimny Ingenieur",
    "wof:placetype":"venue"
},
  "geometry": {"coordinates":[8.0182514191,52.2631568909],"type":"Point"}
}