{
  "type": "Feature",
  "properties": {
    "iso:country":"DE",
    "sg:address":"Wildshausener Str. 75",
    "sg:city":"Meschede",
    "sg:phone":"+49 2937/7060",
    "sg:postcode":"59872",
    "sg:province":"Nordrhein-Westfalen",
    "wof:name":"Thiessen-papchem Gmbh & Co. Kg Apparate- Und Anlagenbau",
    "wof:placetype":"venue"
},
  "geometry": {"coordinates":[8.16016,51.389404],"type":"Point"}
}