{
  "type": "Feature",
  "properties": {
    "iso:country":"DE",
    "sg:address":"Bahnhofstr. 27a",
    "sg:city":"Bielefeld",
    "sg:phone":"+49 521/49977",
    "sg:postcode":"33602",
    "sg:province":"Nordrhein-Westfalen",
    "wof:name":"Riha- Frottiereinzelhandels Gmbh",
    "wof:placetype":"venue"
},
  "geometry": {"coordinates":[8.531188,52.025326],"type":"Point"}
}