{
  "type": "Feature",
  "properties": {
    "iso:country":"DE",
    "sg:address":"M\u00fchlstr. 1",
    "sg:city":"Biebergem\u00fcnd",
    "sg:phone":"+49 6050/1811",
    "sg:postcode":"63599",
    "sg:province":"Hessen",
    "wof:name":"Gerhard L\u00fcckel",
    "wof:placetype":"venue"
},
  "geometry": {"coordinates":[9.2770986557,50.1780891418],"type":"Point"}
}