{
  "type": "Feature",
  "properties": {
    "iso:country":"DE",
    "sg:address":"Kirschenweg 25",
    "sg:city":"Hilden",
    "sg:phone":"+49 2103/80778",
    "sg:postcode":"40723",
    "sg:province":"Nordrhein-Westfalen",
    "wof:name":"T. Steffens",
    "wof:placetype":"venue"
},
  "geometry": {"coordinates":[6.947127,51.156639],"type":"Point"}
}