{
  "type": "Feature",
  "properties": {
    "iso:country":"DE",
    "sg:address":"Kl\u00f6vensteenweg 112b",
    "sg:city":"Hamburg",
    "sg:phone":"+49 40/815020",
    "sg:postcode":"22559",
    "sg:province":"Hamburg",
    "wof:name":"Compcare Gmbh",
    "wof:placetype":"venue"
},
  "geometry": {"coordinates":[9.763792038,53.5904350281],"type":"Point"}
}