{
  "type": "Feature",
  "properties": {
    "iso:country":"DE",
    "sg:address":"Zweinaundorfer Str. 28",
    "sg:city":"Leipzig",
    "sg:phone":"+49 341/2612383",
    "sg:postcode":"04318",
    "sg:province":"Sachsen",
    "wof:name":"T. H\u00e4nsel",
    "wof:placetype":"venue"
},
  "geometry": {"coordinates":[12.412521,51.334438],"type":"Point"}
}