{
  "type": "Feature",
  "properties": {
    "iso:country":"DE",
    "sg:address":"Marktplatz 2",
    "sg:city":"Bad Vilbel",
    "sg:phone":"+49 6101/500640",
    "sg:postcode":"61118",
    "sg:province":"Hessen",
    "wof:name":"Becker Und Sch\u00e4fer Rechtsanw\u00e4lte",
    "wof:placetype":"venue"
},
  "geometry": {"coordinates":[8.7442703247,50.1832008362],"type":"Point"}
}