{
  "type": "Feature",
  "properties": {
    "iso:country":"DE",
    "sg:address":"Gro\u00dfer Kolonnenweg 3",
    "sg:city":"Hannover",
    "sg:phone":"+49 511/315033",
    "sg:postcode":"30163",
    "sg:province":"Niedersachsen",
    "wof:name":"Georg Sattelmacher & Co.",
    "wof:placetype":"venue"
},
  "geometry": {"coordinates":[9.7363710403,52.4044303894],"type":"Point"}
}