{
  "type": "Feature",
  "properties": {
    "iso:country":"DE",
    "sg:address":"Zum Forellenhof 11",
    "sg:city":"Oberelbert",
    "sg:phone":"+49 4926/081227",
    "sg:postcode":"56412",
    "sg:province":"Rheinland-Pfalz",
    "wof:name":"Achim Schmidt Tief- U. Strassenbau Gmbh",
    "wof:placetype":"venue"
},
  "geometry": {"coordinates":[7.81758,50.388546],"type":"Point"}
}