{
  "type": "Feature",
  "properties": {
    "iso:country":"DE",
    "sg:address":"Zollm\u00fchle 1",
    "sg:city":"Ellingen",
    "sg:phone":"+49 9141/3976",
    "sg:postcode":"91792",
    "sg:province":"Bayern",
    "wof:name":"Golfshop Des Golfclubs Zollm\u00fchle",
    "wof:placetype":"venue"
},
  "geometry": {"coordinates":[10.968065,49.080708],"type":"Point"}
}