{
  "type": "Feature",
  "properties": {
    "iso:country":"DE",
    "sg:address":"Unterer Hammer 4",
    "sg:city":"Finnentrop",
    "sg:phone":"+49 2395/239",
    "sg:postcode":"57413",
    "sg:province":"Nordrhein-Westfalen",
    "wof:name":"Pavel Rozmann",
    "wof:placetype":"venue"
},
  "geometry": {"coordinates":[7.9655079842,51.1738243103],"type":"Point"}
}