{
  "type": "Feature",
  "properties": {
    "iso:country":"DE",
    "sg:address":"Lateinschulgasse 15",
    "sg:city":"Deggendorf",
    "sg:phone":"+49 991/31344",
    "sg:postcode":"94469",
    "sg:province":"Bayern",
    "wof:name":"Hermann Eller",
    "wof:placetype":"venue"
},
  "geometry": {"coordinates":[12.960364,48.831501],"type":"Point"}
}