{
  "type": "Feature",
  "properties": {
    "iso:country":"DE",
    "sg:address":"Kirchheimer Str. 33",
    "sg:city":"Stuttgart",
    "sg:phone":"+49 711/476610",
    "sg:postcode":"70619",
    "sg:province":"Baden-W\u00fcrttemberg",
    "wof:name":"Kurt Bauer & Co. Gmbh",
    "wof:placetype":"venue"
},
  "geometry": {"coordinates":[9.2099552155,48.7466888428],"type":"Point"}
}