{
  "type": "Feature",
  "properties": {
    "iso:country":"DE",
    "sg:address":"Fichtenweg 2",
    "sg:city":"Steinbach",
    "sg:phone":"+49 9269/314",
    "sg:postcode":"96361",
    "sg:province":"Bayern",
    "wof:name":"Bruno Fr\u00f6ba Gmbh & Co. Kg",
    "wof:placetype":"venue"
},
  "geometry": {"coordinates":[11.293478,50.424183],"type":"Point"}
}