{
  "type": "Feature",
  "properties": {
    "iso:country":"DE",
    "sg:address":"Bahnhofstr. 10",
    "sg:city":"Baunach",
    "sg:phone":"+49 9544/4410",
    "sg:postcode":"96148",
    "sg:province":"Bayern",
    "wof:name":"Dietmar Heger",
    "wof:placetype":"venue"
},
  "geometry": {"coordinates":[10.85398,49.988472],"type":"Point"}
}