{
  "type": "Feature",
  "properties": {
    "iso:country":"DE",
    "sg:address":"Schlo\u00dfplatz",
    "sg:city":"Bad Buchau",
    "sg:phone":"+49 7582/8250",
    "sg:postcode":"88422",
    "sg:province":"Baden-W\u00fcrttemberg",
    "wof:name":"Stiftmuseum",
    "wof:placetype":"venue"
},
  "geometry": {"coordinates":[9.610726,48.067024],"type":"Point"}
}