{
  "type": "Feature",
  "properties": {
    "iso:country":"DE",
    "sg:address":"Elbeallee 59",
    "sg:city":"Bielefeld",
    "sg:phone":"+49 5205/4103",
    "sg:postcode":"33689",
    "sg:province":"Nordrhein-Westfalen",
    "wof:name":"Ernst Jantke Inh. Katharina Jantke",
    "wof:placetype":"venue"
},
  "geometry": {"coordinates":[8.5872449875,51.9469528198],"type":"Point"}
}