{
  "type": "Feature",
  "properties": {
    "iso:country":"DE",
    "sg:address":"Theberather Weg 11",
    "sg:city":"Heinsberg",
    "sg:phone":"+49 2452/967481",
    "sg:postcode":"52525",
    "sg:province":"Nordrhein-Westfalen",
    "wof:name":"Asia Purchase Service Aps",
    "wof:placetype":"venue"
},
  "geometry": {"coordinates":[6.098606,51.082638],"type":"Point"}
}