{
  "type": "Feature",
  "properties": {
    "iso:country":"DE",
    "sg:address":"Wilhelmsh\u00e4user Str. 31",
    "sg:city":"Hann. M\u00fcnden",
    "sg:phone":"+49 5541/5773",
    "sg:postcode":"34346",
    "sg:province":"Niedersachsen",
    "wof:name":"Esso Tankstelle",
    "wof:placetype":"venue"
},
  "geometry": {"coordinates":[9.6437997818,51.4118423462],"type":"Point"}
}