{
  "type": "Feature",
  "properties": {
    "iso:country":"DE",
    "sg:address":"Ludwigstr. 39",
    "sg:city":"Neu\u00f6tting",
    "sg:phone":"+49 8671/71319",
    "sg:postcode":"84524",
    "sg:province":"Bayern",
    "wof:name":"Reiseb\u00fcro Margit K\u00f6lbl",
    "wof:placetype":"venue"
},
  "geometry": {"coordinates":[12.6849880219,48.2412643433],"type":"Point"}
}