{
  "type": "Feature",
  "properties": {
    "iso:country":"DE",
    "sg:address":"Karl-Wackenhut-Str. 1",
    "sg:city":"Altensteig-\u00dcberberg",
    "sg:phone":"+49 4974/532770",
    "sg:postcode":"72213",
    "sg:province":"Baden-W\u00fcrttemberg",
    "wof:name":"Wackenhut Gmbh & Co Kg",
    "wof:placetype":"venue"
},
  "geometry": {"coordinates":[8.575340271,48.5982398987],"type":"Point"}
}