{
  "type": "Feature",
  "properties": {
    "iso:country":"DE",
    "sg:address":"Heinstr. 25",
    "sg:city":"Bremen",
    "sg:phone":"+49 421/274248",
    "sg:postcode":"28213",
    "sg:province":"Bremen",
    "wof:name":"Modac Mode U. Accessoires Gmbh",
    "wof:placetype":"venue"
},
  "geometry": {"coordinates":[8.856024,53.093513],"type":"Point"}
}