{
  "type": "Feature",
  "properties": {
    "iso:country":"DE",
    "sg:address":"Neue Rabenstr. 15 - 19",
    "sg:city":"Hamburg",
    "sg:postcode":"20354",
    "sg:province":"Hamburg",
    "wof:name":"Iduna-nova Grundst\u00fccks-gmbh",
    "wof:placetype":"venue"
},
  "geometry": {"coordinates":[9.9931869507,53.5610466003],"type":"Point"}
}