{
  "type": "Feature",
  "properties": {
    "iso:country":"DE",
    "sg:address":"In Berg 35-45",
    "sg:city":"Wegberg",
    "sg:phone":"+49 2434/5051",
    "sg:postcode":"41844",
    "sg:province":"Nordrhein-Westfalen",
    "wof:name":"Formzeug Formen Und Werkzeug-gmbh",
    "wof:placetype":"venue"
},
  "geometry": {"coordinates":[6.277676,51.15395],"type":"Point"}
}