{
  "type": "Feature",
  "properties": {
    "iso:country":"DE",
    "sg:address":"Eigene Scholle 10",
    "sg:city":"Magdeburg",
    "sg:phone":"+49 391/8115982",
    "sg:postcode":"39114",
    "sg:province":"Sachsen-Anhalt",
    "wof:name":"Wilfrid Kilz",
    "wof:placetype":"venue"
},
  "geometry": {"coordinates":[11.680707,52.10825],"type":"Point"}
}