{
  "type": "Feature",
  "properties": {
    "iso:country":"DE",
    "sg:address":"Sch\u00f6nheider Str. 9",
    "sg:city":"Eibenstock",
    "sg:phone":"+49 37752/67890",
    "sg:postcode":"08309",
    "sg:province":"Sachsen",
    "wof:name":"Hotel Ratskeller",
    "wof:placetype":"venue"
},
  "geometry": {"coordinates":[12.5983247757,50.4939155579],"type":"Point"}
}