{
  "type": "Feature",
  "properties": {
    "iso:country":"DE",
    "sg:address":"Lange Br\u00fccke 28",
    "sg:city":"Erfurt",
    "sg:phone":"+49 361/6436021",
    "sg:postcode":"99084",
    "sg:province":"Th\u00fcringen",
    "wof:name":"Japan-restaurant Nagano",
    "wof:placetype":"venue"
},
  "geometry": {"coordinates":[11.027586937,50.974105835],"type":"Point"}
}