{
  "type": "Feature",
  "properties": {
    "iso:country":"DE",
    "sg:address":"Auf dem Daniel 17",
    "sg:city":"Mechernich",
    "sg:phone":"+49 2443/6673",
    "sg:postcode":"53894",
    "sg:province":"Nordrhein-Westfalen",
    "wof:name":"Weko-fertigbau Gmbh",
    "wof:placetype":"venue"
},
  "geometry": {"coordinates":[6.643514,50.611954],"type":"Point"}
}