{
  "type": "Feature",
  "properties": {
    "iso:country":"DE",
    "sg:address":"Br\u00fcckenstr. 20",
    "sg:city":"W\u00f6lfersheim",
    "sg:phone":"+49 6036/2294",
    "sg:postcode":"61200",
    "sg:province":"Hessen",
    "wof:name":"Hartwig Koch",
    "wof:placetype":"venue"
},
  "geometry": {"coordinates":[8.862441,50.426842],"type":"Point"}
}