{
  "type": "Feature",
  "properties": {
    "iso:country":"DE",
    "sg:address":"An der Untertrave 102 a",
    "sg:city":"L\u00fcbeck",
    "sg:phone":"+49 451/75868",
    "sg:postcode":"23552",
    "sg:province":"Schleswig-Holstein",
    "wof:name":"Sabine Zander-meink Ergotherapeutsche Praxis",
    "wof:placetype":"venue"
},
  "geometry": {"coordinates":[10.680762,53.867813],"type":"Point"}
}