{
  "type": "Feature",
  "properties": {
    "iso:country":"DE",
    "sg:address":"Im Riedle 12",
    "sg:city":"Blaufelden",
    "sg:phone":"+49 7953/270",
    "sg:postcode":"74572",
    "sg:province":"Baden-W\u00fcrttemberg",
    "wof:name":"Manfred Schmieg Omnibusverkehr E. K.",
    "wof:placetype":"venue"
},
  "geometry": {"coordinates":[9.9800567627,49.2960357666],"type":"Point"}
}