{
  "type": "Feature",
  "properties": {
    "iso:country":"DE",
    "sg:address":"Binnenhafenstr. 20",
    "sg:city":"Mannheim",
    "sg:phone":"+49 621/150000",
    "sg:postcode":"68159",
    "sg:province":"Baden-W\u00fcrttemberg",
    "wof:name":"L. H. Knubben Speditions Gmbh & Co.",
    "wof:placetype":"venue"
},
  "geometry": {"coordinates":[8.4475917816,49.5010070801],"type":"Point"}
}