{
  "type": "Feature",
  "properties": {
    "iso:country":"DE",
    "sg:address":"Hirschkamp 28",
    "sg:city":"Norderstedt",
    "sg:phone":"+49 40/5221611",
    "sg:postcode":"22846",
    "sg:province":"Schleswig-Holstein",
    "wof:name":"Michael Rueter Gmbh",
    "wof:placetype":"venue"
},
  "geometry": {"coordinates":[9.9980945587,53.715587616],"type":"Point"}
}