{
  "type": "Feature",
  "properties": {
    "iso:country":"DE",
    "sg:address":"Oberdorfweg 12",
    "sg:city":"Horn",
    "sg:phone":"+49 7175/6486",
    "sg:postcode":"73575",
    "sg:province":"Baden-W\u00fcrttemberg",
    "wof:name":"Hermann Sachsenmaier",
    "wof:placetype":"venue"
},
  "geometry": {"coordinates":[-103.439728,42.765663],"type":"Point"}
}