{
  "type": "Feature",
  "properties": {
    "iso:country":"DE",
    "sg:address":"Gronhofweg 1",
    "sg:city":"Bad Salzuflen",
    "sg:phone":"+49 5222/7846",
    "sg:postcode":"32107",
    "sg:province":"Nordrhein-Westfalen",
    "wof:name":"Wilhelm Potthoff",
    "wof:placetype":"venue"
},
  "geometry": {"coordinates":[8.75052,52.040298],"type":"Point"}
}