{
  "type": "Feature",
  "properties": {
    "iso:country":"DE",
    "sg:address":"Ohlsdorfer Str. 5",
    "sg:city":"Hamburg",
    "sg:phone":"+49 40/473183",
    "sg:postcode":"22299",
    "sg:province":"Hamburg",
    "wof:name":"Julius Wieseler",
    "wof:placetype":"venue"
},
  "geometry": {"coordinates":[10.000625,53.595402],"type":"Point"}
}