{
  "type": "Feature",
  "properties": {
    "iso:country":"DE",
    "sg:address":"warmbadweg 4",
    "sg:city":"Langeoog",
    "sg:phone":"+49 4972/1636",
    "sg:postcode":"26465",
    "sg:province":"Niedersachsen",
    "wof:name":"Anselm Atelier Am Meer",
    "wof:placetype":"venue"
},
  "geometry": {"coordinates":[7.479926,53.75201],"type":"Point"}
}