{
  "type": "Feature",
  "properties": {
    "iso:country":"DE",
    "sg:address":"Waldstr. 36",
    "sg:city":"Karlsruhe",
    "sg:phone":"+49 721/22514",
    "sg:postcode":"76133",
    "sg:province":"Baden-W\u00fcrttemberg",
    "wof:name":"Spiegel Verlag Rudolf Augstein Gmbh & Co. Kg",
    "wof:placetype":"venue"
},
  "geometry": {"coordinates":[8.3968677521,49.0097961426],"type":"Point"}
}