{
  "type": "Feature",
  "properties": {
    "iso:country":"DE",
    "sg:address":"An der L\u00f6serm\u00fchle 1",
    "sg:city":"Neuhausen",
    "sg:phone":"+49 37327/9212",
    "sg:postcode":"09544",
    "sg:province":"Sachsen",
    "wof:name":"Erzgebirgsst\u00fcbl L\u00f6serm\u00fchle",
    "wof:placetype":"venue"
},
  "geometry": {"coordinates":[13.4790115356,50.6830406189],"type":"Point"}
}