{
  "type": "Feature",
  "properties": {
    "iso:country":"DE",
    "sg:address":"Dahlienweg 21",
    "sg:city":"Kirchen",
    "sg:phone":"+49 2741/60618",
    "sg:postcode":"57548",
    "sg:province":"Rheinland-Pfalz",
    "wof:name":"Peter Daub Gmbh",
    "wof:placetype":"venue"
},
  "geometry": {"coordinates":[7.895317,50.819202],"type":"Point"}
}