{
  "type": "Feature",
  "properties": {
    "iso:country":"DE",
    "sg:address":"Bremland 42",
    "sg:city":"Fahrdorf",
    "sg:phone":"+49 4621/34926",
    "sg:postcode":"24857",
    "sg:province":"Schleswig-Holstein",
    "wof:name":"Land- Garten- Und Kommunal- Technik Joachim Pahl Gmbh",
    "wof:placetype":"venue"
},
  "geometry": {"coordinates":[9.618553,54.495346],"type":"Point"}
}