{
  "type": "Feature",
  "properties": {
    "iso:country":"DE",
    "sg:address":"Folgenstr. 32",
    "sg:city":"Limbach-Oberfrohna",
    "sg:phone":"+49 3722/95178",
    "sg:postcode":"09212",
    "sg:province":"Sachsen",
    "wof:name":"Manfred Borck",
    "wof:placetype":"venue"
},
  "geometry": {"coordinates":[12.7102947235,50.8492774963],"type":"Point"}
}