{
  "type": "Feature",
  "properties": {
    "iso:country":"DE",
    "sg:address":"Koblenzer Str. 173a",
    "sg:city":"Mayen",
    "sg:phone":"+49 2651/41427",
    "sg:postcode":"56727",
    "sg:province":"Rheinland-Pfalz",
    "wof:name":"Restaurant Rhodos",
    "wof:placetype":"venue"
},
  "geometry": {"coordinates":[7.2403459549,50.3283424377],"type":"Point"}
}