{
  "type": "Feature",
  "properties": {
    "iso:country":"DE",
    "sg:address":"Dettinger Str. 12",
    "sg:city":"Kirchheim",
    "sg:phone":"+49 7021/3349",
    "sg:postcode":"73230",
    "sg:province":"Baden-W\u00fcrttemberg",
    "wof:name":"Gunther Frey Rechtsanwalt",
    "wof:placetype":"venue"
},
  "geometry": {"coordinates":[9.4513578415,48.6452827454],"type":"Point"}
}