{
  "type": "Feature",
  "properties": {
    "iso:country":"DE",
    "sg:address":"F\u00f6hrenstr. 65",
    "sg:city":"Bremen",
    "sg:phone":"+49 421/413613",
    "sg:postcode":"28207",
    "sg:province":"Bremen",
    "wof:name":"Joseph Ten Brink Immobilienmakler",
    "wof:placetype":"venue"
},
  "geometry": {"coordinates":[8.8761262894,53.0628166199],"type":"Point"}
}