{
  "type": "Feature",
  "properties": {
    "iso:country":"DE",
    "sg:address":"Soltauer Str. 22",
    "sg:city":"Uelzen",
    "sg:phone":"+49 581/18764",
    "sg:postcode":"29525",
    "sg:province":"Niedersachsen",
    "wof:name":"Veer\u00dfer Pfanne",
    "wof:placetype":"venue"
},
  "geometry": {"coordinates":[10.545463562,52.9568214417],"type":"Point"}
}