{
  "type": "Feature",
  "properties": {
    "iso:country":"DE",
    "sg:address":"L\u00fctt H\u00f6rpel 8",
    "sg:city":"Eyendorf",
    "sg:phone":"+49 4172/5489",
    "sg:postcode":"21376",
    "sg:province":"Niedersachsen",
    "wof:name":"Heidi Und Otto Zeller",
    "wof:placetype":"venue"
},
  "geometry": {"coordinates":[10.1495046616,53.2000617981],"type":"Point"}
}