{
  "type": "Feature",
  "properties": {
    "iso:country":"DE",
    "sg:address":"Fasanenstr. 24",
    "sg:city":"Berlin",
    "sg:phone":"+49 30/8825210",
    "sg:postcode":"10719",
    "sg:province":"Berlin",
    "wof:name":"K\u00e4the-kollwitz-museum Berlin",
    "wof:placetype":"venue"
},
  "geometry": {"coordinates":[13.327117,52.50211],"type":"Point"}
}