{
  "type": "Feature",
  "properties": {
    "iso:country":"DE",
    "sg:address":"Gutleutstr. 85::",
    "sg:city":"Frankfurt",
    "sg:phone":"+49 4969/310860",
    "sg:postcode":"60329",
    "sg:province":"Hessen",
    "wof:name":"Devif Deutsche Gesellschaft F\u00dcr Investment-fonds Gmbh",
    "wof:placetype":"venue"
},
  "geometry": {"coordinates":[8.666576,50.104591],"type":"Point"}
}