{
  "type": "Feature",
  "properties": {
    "iso:country":"DE",
    "sg:address":"Oberaltenallee 14 a",
    "sg:city":"Hamburg",
    "sg:phone":"+49 40/2207721",
    "sg:postcode":"22081",
    "sg:province":"Hamburg",
    "wof:name":"Krista Beator",
    "wof:placetype":"venue"
},
  "geometry": {"coordinates":[10.0289974213,53.5706939697],"type":"Point"}
}