{
  "type": "Feature",
  "properties": {
    "iso:country":"DE",
    "sg:address":"Gewerberingstr. 20",
    "sg:city":"Kolkwitz",
    "sg:phone":"+49 35604/6160",
    "sg:postcode":"03099",
    "sg:province":"Brandenburg",
    "wof:name":"Asg Asphalt Strassenbau Gmbh",
    "wof:placetype":"venue"
},
  "geometry": {"coordinates":[14.2117671967,51.7508888245],"type":"Point"}
}