{
  "type": "Feature",
  "properties": {
    "iso:country":"DE",
    "sg:address":"Neuer Landweg 27",
    "sg:city":"Garbsen",
    "sg:phone":"+49 5131/93430",
    "sg:postcode":"30827",
    "sg:province":"Niedersachsen",
    "wof:name":"Norbert Glaser",
    "wof:placetype":"venue"
},
  "geometry": {"coordinates":[9.614831,52.442753],"type":"Point"}
}