{
  "type": "Feature",
  "properties": {
    "iso:country":"DE",
    "sg:address":"Briloner Landstr. 87",
    "sg:city":"Korbach",
    "sg:phone":"+49 4956/313046",
    "sg:postcode":"34497",
    "sg:province":"Hessen",
    "wof:name":"Schrinner & Schmidt Gmbh",
    "wof:placetype":"venue"
},
  "geometry": {"coordinates":[8.848573,51.282806],"type":"Point"}
}