{
  "type": "Feature",
  "properties": {
    "iso:country":"DE",
    "sg:address":"Bockumer Str. 378",
    "sg:city":"D\u00fcsseldorf",
    "sg:phone":"+49 203/781979",
    "sg:postcode":"40489",
    "sg:province":"Nordrhein-Westfalen",
    "wof:name":"A. Japcke",
    "wof:placetype":"venue"
},
  "geometry": {"coordinates":[6.7234997749,51.3339385986],"type":"Point"}
}