{
  "type": "Feature",
  "properties": {
    "iso:country":"DE",
    "sg:address":"Brunswiker Str. 50",
    "sg:city":"Kiel",
    "sg:phone":"+49 431/567068",
    "sg:postcode":"24105",
    "sg:province":"Schleswig-Holstein",
    "wof:name":"H\u00f6gelein Und Schr\u00f6der Rechtsanw\u00e4lte",
    "wof:placetype":"venue"
},
  "geometry": {"coordinates":[10.1356391907,54.3288841248],"type":"Point"}
}