{
  "type": "Feature",
  "properties": {
    "iso:country":"DE",
    "sg:address":"Bredowstr. 30",
    "sg:city":"Dortmund",
    "sg:phone":"+49 231/255088",
    "sg:postcode":"44309",
    "sg:province":"Nordrhein-Westfalen",
    "wof:name":"Helmut Matzner",
    "wof:placetype":"venue"
},
  "geometry": {"coordinates":[7.5631661415,51.513420105],"type":"Point"}
}