{
  "type": "Feature",
  "properties": {
    "iso:country":"DE",
    "sg:address":"Steinmattenstr. 5",
    "sg:city":"Heitersheim",
    "sg:phone":"+49 7634/51130",
    "sg:postcode":"79423",
    "sg:province":"Baden-W\u00fcrttemberg",
    "wof:name":"Wassmer Spezialmaschinen Gmbh",
    "wof:placetype":"venue"
},
  "geometry": {"coordinates":[7.647577,47.872204],"type":"Point"}
}