{
  "type": "Feature",
  "properties": {
    "iso:country":"DE",
    "sg:address":"Schustergasse 13",
    "sg:city":"Steinbach b Moritzburg",
    "sg:phone":"+49 35243/36425",
    "sg:postcode":"01471",
    "sg:province":"Sachsen",
    "wof:name":"Artur Betz Gmbh",
    "wof:placetype":"venue"
},
  "geometry": {"coordinates":[-71.57163238530001,42.6084594727],"type":"Point"}
}