{
  "type": "Feature",
  "properties": {
    "iso:country":"DE",
    "sg:address":"B\u00fcrdestr. 14",
    "sg:city":"Nettetal",
    "sg:postcode":"41334",
    "sg:province":"Nordrhein-Westfalen",
    "wof:name":"Aqua United Gmbh",
    "wof:placetype":"venue"
},
  "geometry": {"coordinates":[6.1791739464,51.3201293945],"type":"Point"}
}