{
  "type": "Feature",
  "properties": {
    "iso:country":"DE",
    "sg:address":"Vor den Eichh\u00f6fen 1",
    "sg:city":"Wienhausen",
    "sg:phone":"+49 5149/670",
    "sg:postcode":"29342",
    "sg:province":"Niedersachsen",
    "wof:name":"Siegbert Hotopp Ingenieur",
    "wof:placetype":"venue"
},
  "geometry": {"coordinates":[10.1385269165,52.5706062317],"type":"Point"}
}