{
  "type": "Feature",
  "properties": {
    "iso:country":"DE",
    "sg:address":"Grapengie\u00dferstr. 23",
    "sg:city":"L\u00fcbeck",
    "sg:postcode":"23556",
    "sg:province":"Schleswig-Holstein",
    "wof:name":"Herav Verwaltungs- Und Beteiligungsgesellschaft Mbh",
    "wof:placetype":"venue"
},
  "geometry": {"coordinates":[10.633795,53.861832],"type":"Point"}
}