{
  "type": "Feature",
  "properties": {
    "iso:country":"DE",
    "sg:address":"Gellertstr. 51",
    "sg:city":"Bremen",
    "sg:phone":"+49 421/5360265",
    "sg:postcode":"28201",
    "sg:province":"Bremen",
    "wof:name":"Joachim Sauer Steuerbevollm\u00e4chtigter",
    "wof:placetype":"venue"
},
  "geometry": {"coordinates":[8.8060512543,53.0625991821],"type":"Point"}
}