{
  "type": "Feature",
  "properties": {
    "iso:country":"DE",
    "sg:address":"Max-Planck-Str. 7",
    "sg:city":"H\u00fcrth",
    "sg:phone":"+49 2233/974400",
    "sg:postcode":"50354",
    "sg:province":"Nordrhein-Westfalen",
    "wof:name":"Franken Filtertechnik Kg",
    "wof:placetype":"venue"
},
  "geometry": {"coordinates":[6.900277,50.882858],"type":"Point"}
}