{
  "type": "Feature",
  "properties": {
    "iso:country":"DE",
    "sg:city":"Windeck-Herchen",
    "sg:postcode":"51570",
    "sg:province":"Nordrhein-Westfalen",
    "wof:name":"Bundesverband Ged\u00e4chtnistraining E.v.",
    "wof:placetype":"venue"
},
  "geometry": {"coordinates":[7.51208,50.781239],"type":"Point"}
}