{
  "type": "Feature",
  "properties": {
    "iso:country":"DE",
    "sg:address":"Fliederstr. 23",
    "sg:city":"Ahrensfelde",
    "sg:phone":"+49 30/9339193",
    "sg:postcode":"16356",
    "sg:province":"Brandenburg",
    "wof:name":"Manfred Goldenbogen",
    "wof:placetype":"venue"
},
  "geometry": {"coordinates":[13.57694,52.581509],"type":"Point"}
}