{
  "type": "Feature",
  "properties": {
    "iso:country":"DE",
    "sg:address":"Blochstr 1",
    "sg:city":"Leipzig",
    "sg:phone":"+49 341/2568100",
    "sg:postcode":"04329",
    "sg:province":"Sachsen",
    "wof:name":"D.g.l. Technische Dienstleistungs- Und Service Gmbh",
    "wof:placetype":"venue"
},
  "geometry": {"coordinates":[12.467613,51.365768],"type":"Point"}
}