{
  "type": "Feature",
  "properties": {
    "iso:country":"DE",
    "sg:address":"Nordring 12a",
    "sg:city":"Pleinfeld",
    "sg:phone":"+49 9144/92300",
    "sg:postcode":"91785",
    "sg:province":"Bayern",
    "wof:name":"Udo Wolf \u00d6fen Und Herde",
    "wof:placetype":"venue"
},
  "geometry": {"coordinates":[10.9695034027,49.1043930054],"type":"Point"}
}