{
  "type": "Feature",
  "properties": {
    "iso:country":"DE",
    "sg:address":"Alsenberger Str. 18",
    "sg:city":"Hof",
    "sg:phone":"+49 9281/85333",
    "sg:postcode":"95028",
    "sg:province":"Bayern",
    "wof:name":"Maler Luge",
    "wof:placetype":"venue"
},
  "geometry": {"coordinates":[11.921489,50.312176],"type":"Point"}
}