{
  "type": "Feature",
  "properties": {
    "iso:country":"DE",
    "sg:address":"Bantorfer Str. 6",
    "sg:city":"Bad Nenndorf",
    "sg:phone":"+49 5723/914491",
    "sg:postcode":"31542",
    "sg:province":"Niedersachsen",
    "wof:name":"Ewald Innovationstechnik Gmbh",
    "wof:placetype":"venue"
},
  "geometry": {"coordinates":[9.406814,52.339874],"type":"Point"}
}