{
  "type": "Feature",
  "properties": {
    "iso:country":"DE",
    "sg:address":"Siechenstr. 82",
    "sg:city":"Bamberg",
    "sg:phone":"+49 951/601676",
    "sg:postcode":"96052",
    "sg:province":"Bayern",
    "wof:name":"I. Beck",
    "wof:placetype":"venue"
},
  "geometry": {"coordinates":[10.888522,49.902729],"type":"Point"}
}