{
  "type": "Feature",
  "properties": {
    "iso:country":"DE",
    "sg:address":"Lerchenweg 7",
    "sg:city":"Reichenschwand",
    "sg:phone":"+49 9151/95333",
    "sg:postcode":"91244",
    "sg:province":"Bayern",
    "wof:name":"Heinrich Schmitz Gmbh",
    "wof:placetype":"venue"
},
  "geometry": {"coordinates":[11.3741197586,49.5143508911],"type":"Point"}
}