{
  "type": "Feature",
  "properties": {
    "iso:country":"DE",
    "sg:address":"Provinzialstr. 102",
    "sg:city":"Dortmund",
    "sg:phone":"+49 231/601818",
    "sg:postcode":"44388",
    "sg:province":"Nordrhein-Westfalen",
    "wof:name":"B. Richter",
    "wof:placetype":"venue"
},
  "geometry": {"coordinates":[7.3258361816,51.4979553223],"type":"Point"}
}