{
  "type": "Feature",
  "properties": {
    "iso:country":"DE",
    "sg:address":"Teichstr. 8",
    "sg:city":"Schwerte",
    "sg:phone":"+49 2304/13008",
    "sg:postcode":"58239",
    "sg:province":"Nordrhein-Westfalen",
    "wof:name":"Sporthaus Schwerte Znl Der Sporthaus Werne",
    "wof:placetype":"venue"
},
  "geometry": {"coordinates":[7.56692,51.440201],"type":"Point"}
}