{
  "type": "Feature",
  "properties": {
    "iso:country":"DE",
    "sg:address":"Marktstr. 6",
    "sg:city":"Olbernhau",
    "sg:phone":"+49 37360/74202",
    "sg:postcode":"09526",
    "sg:province":"Sachsen",
    "wof:name":"F. Preu\u00dfler",
    "wof:placetype":"venue"
},
  "geometry": {"coordinates":[13.335912,50.661228],"type":"Point"}
}