{
  "type": "Feature",
  "properties": {
    "iso:country":"DE",
    "sg:address":"Robert-F\u00fcrbringer-Str. 39",
    "sg:city":"Gera",
    "sg:phone":"+49 365/33287",
    "sg:postcode":"07551",
    "sg:province":"Th\u00fcringen",
    "wof:name":"Ingenieurb\u00fcro Ernst Recha",
    "wof:placetype":"venue"
},
  "geometry": {"coordinates":[12.0887298584,50.8488388062],"type":"Point"}
}