{
  "type": "Feature",
  "properties": {
    "iso:country":"DE",
    "sg:address":"Karl-Hau\u00dfmann-Str. 15",
    "sg:city":"Ludwigsburg",
    "sg:phone":"+49 7141/460633",
    "sg:postcode":"71636",
    "sg:province":"Baden-W\u00fcrttemberg",
    "wof:name":"Siegfried Schmid",
    "wof:placetype":"venue"
},
  "geometry": {"coordinates":[9.1651134491,48.8888931274],"type":"Point"}
}