{
  "type": "Feature",
  "properties": {
    "iso:country":"DE",
    "sg:city":"Sulzbach",
    "sg:phone":"+49 4979/76305",
    "sg:postcode":"74429",
    "sg:province":"Baden-W\u00fcrttemberg",
    "wof:name":"Limpurger Bank Eg",
    "wof:placetype":"venue"
},
  "geometry": {"coordinates":[9.845818,48.964474],"type":"Point"}
}