{
  "type": "Feature",
  "properties": {
    "iso:country":"DE",
    "sg:address":"Hinter der Bahn 13",
    "sg:city":"Sch\u00f6ppenstedt",
    "sg:postcode":"38170",
    "sg:province":"Niedersachsen",
    "wof:name":"Aldi Gmbh & Co. Kg",
    "wof:placetype":"venue"
},
  "geometry": {"coordinates":[10.7706708908,52.1397705078],"type":"Point"}
}