{
  "type": "Feature",
  "properties": {
    "iso:country":"DE",
    "sg:address":"Br\u00fcsseler Allee 37",
    "sg:city":"Erkelenz",
    "sg:phone":"+49 2431/945510",
    "sg:postcode":"41812",
    "sg:province":"Nordrhein-Westfalen",
    "wof:name":"Tecon Spezialmaschinen Gmbh",
    "wof:placetype":"venue"
},
  "geometry": {"coordinates":[6.312909,51.062191],"type":"Point"}
}