{
  "type": "Feature",
  "properties": {
    "iso:country":"DE",
    "sg:address":"Breite Str. 20",
    "sg:city":"Goslar",
    "sg:phone":"+49 5321/26148",
    "sg:postcode":"38640",
    "sg:province":"Niedersachsen",
    "wof:name":"Broyhan St\u00fcbchen",
    "wof:placetype":"venue"
},
  "geometry": {"coordinates":[10.4323959351,51.9075164795],"type":"Point"}
}