{
  "type": "Feature",
  "properties": {
    "iso:country":"DE",
    "sg:address":"Ki\u00dflingerstr. 15",
    "sg:city":"Rottach-Egern",
    "sg:phone":"+49 8022/5138",
    "sg:postcode":"83700",
    "sg:province":"Bayern",
    "wof:name":"Heinz Graner Ingenieur",
    "wof:placetype":"venue"
},
  "geometry": {"coordinates":[11.7643594742,47.6913299561],"type":"Point"}
}