{
  "type": "Feature",
  "properties": {
    "iso:country":"DE",
    "sg:address":"Bahnhofstr. 39",
    "sg:city":"Bremen",
    "sg:phone":"+49 421/165890",
    "sg:postcode":"28195",
    "sg:province":"Bremen",
    "wof:name":"Europa-filmpalast",
    "wof:placetype":"venue"
},
  "geometry": {"coordinates":[8.810478,53.080528],"type":"Point"}
}