{
  "type": "Feature",
  "properties": {
    "iso:country":"DE",
    "sg:address":"Hauptstr. 23",
    "sg:city":"Denklingen",
    "sg:phone":"+49 8243/2066",
    "sg:postcode":"86920",
    "sg:province":"Bayern",
    "wof:name":"\u00d6ffentl. Gemeindeb\u00fccherei",
    "wof:placetype":"venue"
},
  "geometry": {"coordinates":[10.849573,47.911896],"type":"Point"}
}