{
  "type": "Feature",
  "properties": {
    "iso:country":"DE",
    "sg:address":"Korngasse 1",
    "sg:city":"Greifenstein",
    "sg:phone":"+49 6478/640",
    "sg:postcode":"35753",
    "sg:province":"Hessen",
    "wof:name":"Kurt B\u00f6lzer",
    "wof:placetype":"venue"
},
  "geometry": {"coordinates":[8.292272,50.573044],"type":"Point"}
}