{
  "type": "Feature",
  "properties": {
    "iso:country":"DE",
    "sg:address":"Bischofsweiherstr. 5",
    "sg:city":"Erlangen",
    "sg:phone":"+49 9135/2733",
    "sg:postcode":"91056",
    "sg:province":"Bayern",
    "wof:name":"Konrad Nendel",
    "wof:placetype":"venue"
},
  "geometry": {"coordinates":[10.939076,49.629295],"type":"Point"}
}