{
  "type": "Feature",
  "properties": {
    "iso:country":"DE",
    "sg:address":"Arenberger Str. 132",
    "sg:city":"Koblenz",
    "sg:phone":"+49 261/68946",
    "sg:postcode":"56077",
    "sg:province":"Rheinland-Pfalz",
    "wof:name":"Pizzeria Lido",
    "wof:placetype":"venue"
},
  "geometry": {"coordinates":[7.6250700951,50.3707504272],"type":"Point"}
}