{
  "type": "Feature",
  "properties": {
    "iso:country":"DE",
    "sg:address":"Markt 20",
    "sg:city":"J\u00fcchen",
    "sg:phone":"+49 2165/1033",
    "sg:postcode":"41363",
    "sg:province":"Nordrhein-Westfalen",
    "wof:name":"Pizzeria Al Capone",
    "wof:placetype":"venue"
},
  "geometry": {"coordinates":[6.5030479431,51.1005058289],"type":"Point"}
}