{
  "type": "Feature",
  "properties": {
    "iso:country":"DE",
    "sg:address":"Gr\u00fcnauer Fenn 12",
    "sg:city":"Rathenow",
    "sg:phone":"+49 3385/516332",
    "sg:postcode":"14712",
    "sg:province":"Brandenburg",
    "wof:name":"Rathenower Feinguss Gmbh",
    "wof:placetype":"venue"
},
  "geometry": {"coordinates":[12.338931,52.576675],"type":"Point"}
}