{
  "type": "Feature",
  "properties": {
    "iso:country":"DE",
    "sg:address":"Lombacher Str. 54",
    "sg:city":"Glatten",
    "sg:phone":"+49 7443/8580",
    "sg:postcode":"72293",
    "sg:province":"Baden-W\u00fcrttemberg",
    "wof:name":"W. Franz K\u00fcferei",
    "wof:placetype":"venue"
},
  "geometry": {"coordinates":[8.51558,48.440723],"type":"Point"}
}