{
  "type": "Feature",
  "properties": {
    "iso:country":"DE",
    "sg:address":"Findorffstr. 85",
    "sg:city":"Bremen",
    "sg:phone":"+49 421/357406",
    "sg:postcode":"28215",
    "sg:province":"Bremen",
    "wof:name":"Bremer Rundfunkmuseum",
    "wof:placetype":"venue"
},
  "geometry": {"coordinates":[8.810124,53.088753],"type":"Point"}
}