{
  "type": "Feature",
  "properties": {
    "iso:country":"DE",
    "sg:address":"Ziegelh\u00fctte 2",
    "sg:city":"Kaufungen",
    "sg:phone":"+49 5605/3239",
    "sg:postcode":"34260",
    "sg:province":"Hessen",
    "wof:name":"Erster Roh\u00f6lz\u00fcnderclub Kaufungen",
    "wof:placetype":"venue"
},
  "geometry": {"coordinates":[9.6172361374,51.277217865],"type":"Point"}
}