{
  "type": "Feature",
  "properties": {
    "iso:country":"DE",
    "sg:address":"Altstr. 3",
    "sg:city":"Neunkirchen",
    "sg:phone":"+49 6858/313",
    "sg:postcode":"66540",
    "sg:province":"Saarland",
    "wof:name":"Alten- Und Pflegeheim Am Berg",
    "wof:placetype":"venue"
},
  "geometry": {"coordinates":[7.240349,49.393875],"type":"Point"}
}