{
  "type": "Feature",
  "properties": {
    "iso:country":"DE",
    "sg:address":"Talstr. 48",
    "sg:city":"Gr\u00fcnebach",
    "sg:phone":"+49 2741/973193",
    "sg:postcode":"57520",
    "sg:province":"Rheinland-Pfalz",
    "wof:name":"Heinz Mader Ingenieur",
    "wof:placetype":"venue"
},
  "geometry": {"coordinates":[7.9093542099,50.7814102173],"type":"Point"}
}