{
  "type": "Feature",
  "properties": {
    "iso:country":"DE",
    "sg:address":"Himmelgeister Str. 11",
    "sg:city":"D\u00fcsseldorf",
    "sg:phone":"+49 211/340835",
    "sg:postcode":"40225",
    "sg:province":"Nordrhein-Westfalen",
    "wof:name":"Pizzeria Due Fratelli",
    "wof:placetype":"venue"
},
  "geometry": {"coordinates":[6.7802357674,51.2034568787],"type":"Point"}
}