{
  "type": "Feature",
  "properties": {
    "iso:country":"DE",
    "sg:address":"Gustav-Heinemann-Str. 66",
    "sg:city":"Frechen",
    "sg:phone":"+49 2234/965980",
    "sg:postcode":"50226",
    "sg:province":"Nordrhein-Westfalen",
    "wof:name":"I. J\u00f6nsson Rechtsanwalt",
    "wof:placetype":"venue"
},
  "geometry": {"coordinates":[6.7816929817,50.9412498474],"type":"Point"}
}