{
  "type": "Feature",
  "properties": {
    "iso:country":"DE",
    "sg:address":"Fr\u00fchlingstr.",
    "sg:city":"Eggst\u00e4tt",
    "sg:phone":"+49 8056/462",
    "sg:postcode":"83125",
    "sg:province":"Bayern",
    "wof:name":"Hartsee Tennisanlagen",
    "wof:placetype":"venue"
},
  "geometry": {"coordinates":[12.3857851028,47.9309997559],"type":"Point"}
}