{
  "type": "Feature",
  "properties": {
    "iso:country":"DE",
    "sg:address":"Maximilianstr. 6",
    "sg:city":"Regensburg",
    "sg:postcode":"93047",
    "sg:province":"Bayern",
    "wof:name":"Ma-pa Textilienvertriebs-gmbh",
    "wof:placetype":"venue"
},
  "geometry": {"coordinates":[12.100345,49.017307],"type":"Point"}
}