{
  "type": "Feature",
  "properties": {
    "iso:country":"DE",
    "sg:address":"Postfach 32 01",
    "sg:city":"N\u00fcrnberg",
    "sg:phone":"+49 9187/903132",
    "sg:postcode":"90015",
    "sg:province":"Bayern",
    "wof:name":"B&n Internet Marketing",
    "wof:placetype":"venue"
},
  "geometry": {"coordinates":[11.0804796219,49.4505195618],"type":"Point"}
}