{
  "type": "Feature",
  "properties": {
    "iso:country":"DE",
    "sg:address":"Taku-Fort-Str. 9",
    "sg:city":"M\u00fcnchen",
    "sg:phone":"+49 89/638100",
    "sg:postcode":"81827",
    "sg:province":"Bayern",
    "wof:name":"K. H. Wille Ingenieur Gmbh",
    "wof:placetype":"venue"
},
  "geometry": {"coordinates":[11.7077550888,48.105632782],"type":"Point"}
}