{
  "type": "Feature",
  "properties": {
    "iso:country":"DE",
    "sg:address":"Zinsgutstr. 31a",
    "sg:city":"Berlin",
    "sg:phone":"+49 30/6702229",
    "sg:postcode":"12489",
    "sg:province":"Berlin",
    "wof:name":"Renate B\u00f6hm",
    "wof:placetype":"venue"
},
  "geometry": {"coordinates":[13.5580911636,52.4389686584],"type":"Point"}
}