{
  "type": "Feature",
  "properties": {
    "iso:country":"DE",
    "sg:address":"Schr\u00f6derstr. 17",
    "sg:city":"Limbach-Oberfrohna",
    "sg:phone":"+49 3722/92384",
    "sg:postcode":"09212",
    "sg:province":"Sachsen",
    "wof:name":"Hermann T\u00e4schner",
    "wof:placetype":"venue"
},
  "geometry": {"coordinates":[12.746606,50.861496],"type":"Point"}
}