{
  "type": "Feature",
  "properties": {
    "iso:country":"DE",
    "sg:address":"S\u00fcdstra\u00dfe 14",
    "sg:city":"Busenberg",
    "sg:phone":"+49 6301/993112",
    "sg:postcode":"76891",
    "sg:province":"Rheinland-Pfalz",
    "wof:name":"Ferienwohnungen Haus Schuhfelsblick, Bruchweiler-b",
    "wof:placetype":"venue"
},
  "geometry": {"coordinates":[7.822534,49.129459],"type":"Point"}
}