{
  "type": "Feature",
  "properties": {
    "iso:country":"DE",
    "sg:address":"Zwickauer Str. 134",
    "sg:city":"Leipzig",
    "sg:phone":"+49 341/3303802",
    "sg:postcode":"04279",
    "sg:province":"Sachsen",
    "wof:name":"Fleming-apotheke Inh. Olaf-dirk Scheibler",
    "wof:placetype":"venue"
},
  "geometry": {"coordinates":[12.395951,51.301628],"type":"Point"}
}