{
  "type": "Feature",
  "properties": {
    "iso:country":"DE",
    "sg:address":"Springemarkt 3",
    "sg:city":"Gelsenkirchen",
    "sg:phone":"+49 209/377773",
    "sg:postcode":"45894",
    "sg:province":"Nordrhein-Westfalen",
    "wof:name":"Heinz Seidel Tanzschule",
    "wof:placetype":"venue"
},
  "geometry": {"coordinates":[7.0548448563,51.5786628723],"type":"Point"}
}