{
  "type": "Feature",
  "properties": {
    "iso:country":"DE",
    "sg:address":"Postfach 6023",
    "sg:city":"Osnabr\u00fcck",
    "sg:postcode":"49093",
    "sg:province":"Niedersachsen",
    "wof:name":"Erto Gmbh",
    "wof:placetype":"venue"
},
  "geometry": {"coordinates":[8.05319,52.267269],"type":"Point"}
}