{
  "type": "Feature",
  "properties": {
    "iso:country":"DE",
    "sg:address":"Auf der H\u00f6he 9",
    "sg:city":"Engen",
    "sg:postcode":"78234",
    "sg:province":"Baden-W\u00fcrttemberg",
    "wof:name":"Armin Br\u00e4uning Finanzkonzepte E. K.",
    "wof:placetype":"venue"
},
  "geometry": {"coordinates":[8.7623605728,47.8473243713],"type":"Point"}
}