{
  "type": "Feature",
  "properties": {
    "iso:country":"DE",
    "sg:address":"Berliner Chaussee 3",
    "sg:city":"Mittenwalde",
    "sg:phone":"+49 33764/830",
    "sg:postcode":"15749",
    "sg:province":"Brandenburg",
    "wof:name":"Viessmann Kessel Und Apparatebau Gmbh & Co.",
    "wof:placetype":"venue"
},
  "geometry": {"coordinates":[13.5366830826,52.2707138062],"type":"Point"}
}