{
  "type": "Feature",
  "properties": {
    "iso:country":"DE",
    "sg:address":"Sparnecker Weg 1",
    "sg:city":"Berlin",
    "sg:postcode":"14089",
    "sg:province":"Berlin",
    "wof:name":"Aldi Gmbh & Co. Kg",
    "wof:placetype":"venue"
},
  "geometry": {"coordinates":[13.1302461624,52.4646377563],"type":"Point"}
}