{
  "type": "Feature",
  "properties": {
    "iso:country":"DE",
    "sg:address":"Preysingstr. 22",
    "sg:city":"Abensberg",
    "sg:phone":"+49 9443/903733",
    "sg:postcode":"93326",
    "sg:province":"Bayern",
    "wof:name":"Karl Ruhstorfer",
    "wof:placetype":"venue"
},
  "geometry": {"coordinates":[11.9034900665,48.8111915588],"type":"Point"}
}