{
  "type": "Feature",
  "properties": {
    "iso:country":"DE",
    "sg:address":"Holdenstedter Str. 27",
    "sg:city":"Uelzen",
    "sg:phone":"+49 581/15682",
    "sg:postcode":"29525",
    "sg:province":"Niedersachsen",
    "wof:name":"Gasthaus Hillmann Inh. Ilse Hinz",
    "wof:placetype":"venue"
},
  "geometry": {"coordinates":[10.5708589554,52.9661865234],"type":"Point"}
}