{
  "type": "Feature",
  "properties": {
    "iso:country":"DE",
    "sg:address":"Ringstr. 59",
    "sg:city":"Aachen",
    "sg:phone":"+49 2253/3506",
    "sg:postcode":"52078",
    "sg:province":"Nordrhein-Westfalen",
    "wof:name":"Reiner Jungbluth",
    "wof:placetype":"venue"
},
  "geometry": {"coordinates":[6.1598820686,50.7484931946],"type":"Point"}
}