{
  "type": "Feature",
  "properties": {
    "iso:country":"DE",
    "sg:address":"Frankfurter Str. 462",
    "sg:city":"K\u00f6ln",
    "sg:phone":"+49 2203/922580",
    "sg:postcode":"51145",
    "sg:province":"Nordrhein-Westfalen",
    "wof:name":"H. P. Gusen Baustoffe Und Entsorgung Gmbh",
    "wof:placetype":"venue"
},
  "geometry": {"coordinates":[7.0833501816,50.8721199036],"type":"Point"}
}