{
  "type": "Feature",
  "properties": {
    "iso:country":"DE",
    "sg:address":"Pfannerstr. 53",
    "sg:city":"Wangen",
    "sg:phone":"+49 7522/20979",
    "sg:postcode":"88239",
    "sg:province":"Baden-W\u00fcrttemberg",
    "wof:name":"Greims Pilsstube",
    "wof:placetype":"venue"
},
  "geometry": {"coordinates":[9.8302536011,47.6938552856],"type":"Point"}
}