{
  "type": "Feature",
  "properties": {
    "iso:country":"DE",
    "sg:address":"Odenwaldstr. 4",
    "sg:city":"Lauterbach",
    "sg:postcode":"36341",
    "sg:province":"Hessen",
    "wof:name":"Marmor Schwing Gmbh & Co. Kg",
    "wof:placetype":"venue"
},
  "geometry": {"coordinates":[9.4092884064,50.6387443542],"type":"Point"}
}