{
  "type": "Feature",
  "properties": {
    "iso:country":"DE",
    "sg:address":"Herrenackerstr. 4",
    "sg:city":"Hechingen",
    "sg:phone":"+49 7471/15429",
    "sg:postcode":"72379",
    "sg:province":"Baden-W\u00fcrttemberg",
    "wof:name":"B. Und A. Ciriello",
    "wof:placetype":"venue"
},
  "geometry": {"coordinates":[8.9671163559,48.3548316956],"type":"Point"}
}