{
  "type": "Feature",
  "properties": {
    "iso:country":"DE",
    "sg:address":"Nordring 14",
    "sg:city":"Gro\u00dfostheim",
    "sg:phone":"+49 6026/3744",
    "sg:postcode":"63762",
    "sg:province":"Bayern",
    "wof:name":"Hein & Co. Stahl- Und Metallbau Gmbh",
    "wof:placetype":"venue"
},
  "geometry": {"coordinates":[9.034342,49.937862],"type":"Point"}
}