{
  "type": "Feature",
  "properties": {
    "iso:country":"DE",
    "sg:address":"Finkenkruger Str. 2",
    "sg:city":"Falkensee",
    "sg:phone":"+49 3322/3071",
    "sg:postcode":"14612",
    "sg:province":"Brandenburg",
    "wof:name":"Dietrich Schulz",
    "wof:placetype":"venue"
},
  "geometry": {"coordinates":[13.0882062912,52.5597038269],"type":"Point"}
}