{
  "type": "Feature",
  "properties": {
    "iso:country":"DE",
    "sg:address":"Olper H\u00f6he 4",
    "sg:city":"Remscheid",
    "sg:postcode":"42899",
    "sg:province":"Nordrhein-Westfalen",
    "wof:name":"Bornewasser E. K.",
    "wof:placetype":"venue"
},
  "geometry": {"coordinates":[7.253166,51.217125],"type":"Point"}
}