{
  "type": "Feature",
  "properties": {
    "iso:country":"DE",
    "sg:address":"Hainh\u00e4user Weg 133",
    "sg:city":"Langenhagen",
    "sg:phone":"+49 511/776291",
    "sg:postcode":"30855",
    "sg:province":"Niedersachsen",
    "wof:name":"Bruno Fahrenholz",
    "wof:placetype":"venue"
},
  "geometry": {"coordinates":[9.751245,52.479198],"type":"Point"}
}