{
  "type": "Feature",
  "properties": {
    "iso:country":"DE",
    "sg:address":"Stegener Weg 10",
    "sg:city":"Kayhude",
    "sg:phone":"+49 4535/8244",
    "sg:postcode":"23863",
    "sg:province":"Schleswig-Holstein",
    "wof:name":"Peitzker Automaten- Betriebs Gmbh",
    "wof:placetype":"venue"
},
  "geometry": {"coordinates":[10.136557579,53.7578392029],"type":"Point"}
}