{
  "type": "Feature",
  "properties": {
    "iso:country":"DE",
    "sg:address":"Gr\u00fcnower Str. 7",
    "sg:city":"Passow",
    "sg:phone":"+49 33336/55741",
    "sg:postcode":"16306",
    "sg:province":"Brandenburg",
    "wof:name":"Ahv Gmbh & Co.kg",
    "wof:placetype":"venue"
},
  "geometry": {"coordinates":[14.107447,53.139862],"type":"Point"}
}