{
  "type": "Feature",
  "properties": {
    "iso:country":"DE",
    "sg:address":"Dinklager Str. 44",
    "sg:city":"Badbergen",
    "sg:phone":"+49 5433/6744",
    "sg:postcode":"49635",
    "sg:province":"Niedersachsen",
    "wof:name":"Klaus-peter Iredi",
    "wof:placetype":"venue"
},
  "geometry": {"coordinates":[7.98853,52.636311],"type":"Point"}
}