{
  "type": "Feature",
  "properties": {
    "iso:country":"DE",
    "sg:address":"Zweifaller Str. 275-287",
    "sg:city":"Stolberg",
    "sg:phone":"+49 4924/02171",
    "sg:postcode":"52224",
    "sg:province":"Nordrhein-Westfalen",
    "wof:name":"Kerpenwerk Gmbh & Co.",
    "wof:placetype":"venue"
},
  "geometry": {"coordinates":[6.28311,50.736809],"type":"Point"}
}