{
  "type": "Feature",
  "properties": {
    "iso:country":"DE",
    "sg:address":"August-Grabbe-Siedlung 22",
    "sg:city":"Hessisch Oldendorf",
    "sg:phone":"+49 5152/2691",
    "sg:postcode":"31840",
    "sg:province":"Niedersachsen",
    "wof:name":"Hans Kalisch",
    "wof:placetype":"venue"
},
  "geometry": {"coordinates":[9.245463,52.150078],"type":"Point"}
}