{
  "type": "Feature",
  "properties": {
    "iso:country":"DE",
    "sg:address":"Zelterstr. 9-10",
    "sg:city":"Zepernick",
    "sg:phone":"+49 30/9442018",
    "sg:postcode":"16341",
    "sg:province":"Brandenburg",
    "wof:name":"Helmut Schulze",
    "wof:placetype":"venue"
},
  "geometry": {"coordinates":[13.54716,52.654541],"type":"Point"}
}