{
  "type": "Feature",
  "properties": {
    "iso:country":"DE",
    "sg:address":"St\u00fchlingerstr. 21",
    "sg:city":"Freiburg",
    "sg:phone":"+49 761/4001129",
    "sg:postcode":"79106",
    "sg:province":"Baden-W\u00fcrttemberg",
    "wof:name":"Bernhard Fl\u00fcgler Rechtsanwalt",
    "wof:placetype":"venue"
},
  "geometry": {"coordinates":[7.8353590965,47.9957275391],"type":"Point"}
}