{
  "type": "Feature",
  "properties": {
    "iso:country":"DE",
    "sg:address":"Johannes-Daur-Str. 3",
    "sg:city":"Korntal-M\u00fcnchingen",
    "sg:phone":"+49 711/833209",
    "sg:postcode":"70825",
    "sg:province":"Baden-W\u00fcrttemberg",
    "wof:name":"Zentral-apotheke",
    "wof:placetype":"venue"
},
  "geometry": {"coordinates":[9.12171,48.830681],"type":"Point"}
}