{
  "type": "Feature",
  "properties": {
    "iso:country":"DE",
    "sg:address":"Baldusstr. 4-6",
    "sg:city":"Duisburg",
    "sg:phone":"+49 203/438362",
    "sg:postcode":"47138",
    "sg:province":"Nordrhein-Westfalen",
    "wof:name":"Aircraft Cabin Maintenance Gmbh",
    "wof:placetype":"venue"
},
  "geometry": {"coordinates":[6.7869000435,51.4547691345],"type":"Point"}
}