{
  "type": "Feature",
  "properties": {
    "iso:country":"DE",
    "sg:address":"M\u00fcrwiker Str. 162",
    "sg:city":"Flensburg",
    "sg:phone":"+49 461/314130",
    "sg:postcode":"24944",
    "sg:province":"Schleswig-Holstein",
    "wof:name":"F\u00f6rde-apotheke",
    "wof:placetype":"venue"
},
  "geometry": {"coordinates":[9.459486,54.806896],"type":"Point"}
}