{
  "type": "Feature",
  "properties": {
    "iso:country":"DE",
    "sg:address":"Pfarrer-Wimberger-Str. 52",
    "sg:city":"Osterhofen",
    "sg:phone":"+49 9938/903905",
    "sg:postcode":"94486",
    "sg:province":"Bayern",
    "wof:name":"Josef Breit Gmbh",
    "wof:placetype":"venue"
},
  "geometry": {"coordinates":[13.0070257187,48.7574691772],"type":"Point"}
}