{
  "type": "Feature",
  "properties": {
    "iso:country":"DE",
    "sg:address":"Kropsbachstr. 12",
    "sg:city":"Neustadt",
    "sg:phone":"+49 6327/1223",
    "sg:postcode":"67435",
    "sg:province":"Rheinland-Pfalz",
    "wof:name":"Roland Maurer Industriemontage Gmbh",
    "wof:placetype":"venue"
},
  "geometry": {"coordinates":[8.2102298737,49.2981834412],"type":"Point"}
}