{
  "type": "Feature",
  "properties": {
    "iso:country":"DE",
    "sg:address":"Carl-Bertelsmann-Str. 41",
    "sg:city":"G\u00fctersloh",
    "sg:phone":"+49 5241/15197",
    "sg:postcode":"33332",
    "sg:province":"Nordrhein-Westfalen",
    "wof:name":"Hugo Miebach Beteiligungs Gmbh",
    "wof:placetype":"venue"
},
  "geometry": {"coordinates":[8.390607,51.90519],"type":"Point"}
}