{
  "type": "Feature",
  "properties": {
    "iso:country":"DE",
    "sg:address":"Hanauer Ring 30",
    "sg:city":"Clausen",
    "sg:phone":"+49 6333/1299",
    "sg:postcode":"66978",
    "sg:province":"Rheinland-Pfalz",
    "wof:name":"Fk 1919 Clausen Fu\u00dfballverein",
    "wof:placetype":"venue"
},
  "geometry": {"coordinates":[7.6789731979,49.2613220215],"type":"Point"}
}