{
  "type": "Feature",
  "properties": {
    "iso:country":"DE",
    "sg:address":"Haferweg 1",
    "sg:city":"Drage/Schwinde",
    "sg:phone":"+49 4176",
    "sg:postcode":"21423",
    "sg:province":"Niedersachsen",
    "wof:name":"Hinsch Und Rindelaub Gbr",
    "wof:placetype":"venue"
},
  "geometry": {"coordinates":[10.207904,53.364349],"type":"Point"}
}