{
  "type": "Feature",
  "properties": {
    "iso:country":"DE",
    "sg:address":"Rosenheimer Str. 145 F",
    "sg:city":"M\u00fcnchen",
    "sg:postcode":"81671",
    "sg:province":"Bayern",
    "wof:name":"H5b5 Digital Gmbh",
    "wof:placetype":"venue"
},
  "geometry": {"coordinates":[11.6115198135,48.1231994629],"type":"Point"}
}