{
  "type": "Feature",
  "properties": {
    "iso:country":"DE",
    "sg:address":"Hauptstr. 48",
    "sg:city":"T\u00f6ging",
    "sg:phone":"+49 8631/91155",
    "sg:postcode":"84513",
    "sg:province":"Bayern",
    "wof:name":"Seniorenheim Toerringhof Verwaltungs- Gmbh",
    "wof:placetype":"venue"
},
  "geometry": {"coordinates":[12.5920705795,48.2559814453],"type":"Point"}
}