{
  "type": "Feature",
  "properties": {
    "iso:country":"DE",
    "sg:address":"Burgstr. 7",
    "sg:city":"Vreden",
    "sg:phone":"+49 2564/1770",
    "sg:postcode":"48691",
    "sg:province":"Nordrhein-Westfalen",
    "wof:name":"C & M Lederdesign",
    "wof:placetype":"venue"
},
  "geometry": {"coordinates":[6.8244137764,52.0373916626],"type":"Point"}
}