{
  "type": "Feature",
  "properties": {
    "iso:country":"DE",
    "sg:address":"Beauner Platz 3",
    "sg:city":"Bensheim",
    "sg:phone":"+49 6251/67182",
    "sg:postcode":"64625",
    "sg:province":"Hessen",
    "wof:name":"Harald Bauer Gmbh",
    "wof:placetype":"venue"
},
  "geometry": {"coordinates":[8.61983,49.681011],"type":"Point"}
}