{
  "type": "Feature",
  "properties": {
    "iso:country":"DE",
    "sg:address":"Margaretenstr. 12",
    "sg:city":"Rostock",
    "sg:phone":"+49 381/2001611",
    "sg:postcode":"18057",
    "sg:province":"Mecklenburg-Vorpommern",
    "wof:name":"H. Dethloff",
    "wof:placetype":"venue"
},
  "geometry": {"coordinates":[12.1159553528,54.0878791809],"type":"Point"}
}