{
  "type": "Feature",
  "properties": {
    "iso:country":"DE",
    "sg:address":"Postfach 1169:: 83261 Traunstein:: Germany.^^Maxplatz 12::",
    "sg:city":"Traunstein",
    "sg:phone":"+49 861/989880",
    "sg:postcode":"83278",
    "sg:province":"Bayern",
    "wof:name":"Raiffeisenbank Traunstein Eg",
    "wof:placetype":"venue"
},
  "geometry": {"coordinates":[12.63995,47.867424],"type":"Point"}
}