{
  "type": "Feature",
  "properties": {
    "iso:country":"DE",
    "sg:address":"Br\u00fcckenstr. 21",
    "sg:city":"Geilenkirchen",
    "sg:phone":"+49 2453/2160",
    "sg:postcode":"52511",
    "sg:province":"Nordrhein-Westfalen",
    "wof:name":"Schreinerei J. Zimmermann Gmbh",
    "wof:placetype":"venue"
},
  "geometry": {"coordinates":[6.188032,50.995049],"type":"Point"}
}