{
  "type": "Feature",
  "properties": {
    "iso:country":"DE",
    "sg:address":"Geranienweg 8",
    "sg:city":"Baldham",
    "sg:phone":"+49 8106/8264",
    "sg:postcode":"85598",
    "sg:province":"Bayern",
    "wof:name":"R. K\u00fcffner Tabakwarenhdl.",
    "wof:placetype":"venue"
},
  "geometry": {"coordinates":[11.7862520218,48.0938682556],"type":"Point"}
}