{
  "type": "Feature",
  "properties": {
    "iso:country":"DE",
    "sg:address":"Auf dem Hohwart 77",
    "sg:city":"Dortmund",
    "sg:phone":"+49 231/590583",
    "sg:postcode":"44143",
    "sg:province":"Nordrhein-Westfalen",
    "wof:name":"Friedhofsg\u00e4rtnerei Dortmund Eg",
    "wof:placetype":"venue"
},
  "geometry": {"coordinates":[7.534055,51.510361],"type":"Point"}
}