{
  "type": "Feature",
  "properties": {
    "iso:country":"DE",
    "sg:address":"Oberstadt 5",
    "sg:city":"Lich",
    "sg:postcode":"35423",
    "sg:province":"Hessen",
    "wof:name":"Coimpa Managementberatung Gmbh",
    "wof:placetype":"venue"
},
  "geometry": {"coordinates":[8.820643425,50.5202865601],"type":"Point"}
}