{
  "type": "Feature",
  "properties": {
    "iso:country":"DE",
    "sg:address":"Hermann-Ehlers-Str. 30",
    "sg:city":"Wilhelmshaven",
    "sg:phone":"+49 4421/82506",
    "sg:postcode":"26386",
    "sg:province":"Niedersachsen",
    "wof:name":"Neog Inh. Harms",
    "wof:placetype":"venue"
},
  "geometry": {"coordinates":[8.0910263062,53.5518760681],"type":"Point"}
}