{
  "type": "Feature",
  "properties": {
    "iso:country":"DE",
    "sg:address":"An der Br\u00fccke 3 a",
    "sg:city":"Dasburg",
    "sg:phone":"+49 6550/1073",
    "sg:postcode":"54689",
    "sg:province":"Rheinland-Pfalz",
    "wof:name":"J\u00fcrgen Relles M\u00fchle Campingplatz",
    "wof:placetype":"venue"
},
  "geometry": {"coordinates":[6.126631,50.050076],"type":"Point"}
}