{
  "type": "Feature",
  "properties": {
    "iso:country":"DE",
    "sg:address":"Platanenweg 10",
    "sg:city":"Dortmund",
    "sg:phone":"+49 231/593505",
    "sg:postcode":"44143",
    "sg:province":"Nordrhein-Westfalen",
    "wof:name":"Gerhard K\u00f6tting",
    "wof:placetype":"venue"
},
  "geometry": {"coordinates":[7.5171041489,51.519733429],"type":"Point"}
}