{
  "type": "Feature",
  "properties": {
    "iso:country":"DE",
    "sg:address":"Kirchring 15",
    "sg:city":"Ederm\u00fcnde",
    "sg:phone":"+49 5665/5737",
    "sg:postcode":"34295",
    "sg:province":"Hessen",
    "wof:name":"Ev. Pfarramt Grift",
    "wof:placetype":"venue"
},
  "geometry": {"coordinates":[9.4436159134,51.2114219666],"type":"Point"}
}