{
  "type": "Feature",
  "properties": {
    "iso:country":"DE",
    "sg:address":"Schulstr 9",
    "sg:city":"Kumhausen",
    "sg:phone":"+49 871/41013",
    "sg:postcode":"84036",
    "sg:province":"Bayern",
    "wof:name":"Ziegel- U. Betonwerke G\u00fcnther Bauer Gmbh & Co Kg",
    "wof:placetype":"venue"
},
  "geometry": {"coordinates":[12.159765,48.507038],"type":"Point"}
}