{
  "type": "Feature",
  "properties": {
    "iso:country":"DE",
    "sg:address":"Hauptstr. 10",
    "sg:city":"Macken",
    "sg:phone":"+49 2605/4513",
    "sg:postcode":"56290",
    "sg:province":"Rheinland-Pfalz",
    "wof:name":"Michael Krautkr\u00e4mer",
    "wof:placetype":"venue"
},
  "geometry": {"coordinates":[7.402928,50.175598],"type":"Point"}
}