{
  "type": "Feature",
  "properties": {
    "iso:country":"DE",
    "sg:address":"Limburger Str. 39",
    "sg:city":"Bad Camberg",
    "sg:phone":"+49 6434/902171",
    "sg:postcode":"65520",
    "sg:province":"Hessen",
    "wof:name":"Telemax Telekommunikation",
    "wof:placetype":"venue"
},
  "geometry": {"coordinates":[8.2627849579,50.3001670837],"type":"Point"}
}