{
  "type": "Feature",
  "properties": {
    "iso:country":"DE",
    "sg:address":"Beckergrube 32",
    "sg:city":"L\u00fcbeck",
    "sg:phone":"+49 451/77008",
    "sg:postcode":"23552",
    "sg:province":"Schleswig-Holstein",
    "wof:name":"Walter Berg Ohg",
    "wof:placetype":"venue"
},
  "geometry": {"coordinates":[10.6851444244,53.8697624207],"type":"Point"}
}