{
  "type": "Feature",
  "properties": {
    "iso:country":"DE",
    "sg:address":"Bergstr. 32",
    "sg:city":"Vollersode",
    "sg:phone":"+49 4793/1696",
    "sg:postcode":"27729",
    "sg:province":"Niedersachsen",
    "wof:name":"R. Schwiderski",
    "wof:placetype":"venue"
},
  "geometry": {"coordinates":[8.902519,53.320873],"type":"Point"}
}