{
  "type": "Feature",
  "properties": {
    "iso:country":"DE",
    "sg:address":"Eisenbahnstr. 6",
    "sg:city":"Homburg",
    "sg:phone":"+49 6841/60503",
    "sg:postcode":"66424",
    "sg:province":"Saarland",
    "wof:name":"Christine Leibrecht",
    "wof:placetype":"venue"
},
  "geometry": {"coordinates":[7.3407249451,49.3223266602],"type":"Point"}
}