{
  "type": "Feature",
  "properties": {
    "iso:country":"DE",
    "sg:address":"Alte Rathausstr. 10",
    "sg:city":"Waldbr\u00f6l",
    "sg:phone":"+49 2291/92460",
    "sg:postcode":"51545",
    "sg:province":"Nordrhein-Westfalen",
    "wof:name":"H. W. Langefeld Und Eberhard Rothstein",
    "wof:placetype":"venue"
},
  "geometry": {"coordinates":[7.6170721054,50.8756561279],"type":"Point"}
}