{
  "type": "Feature",
  "properties": {
    "iso:country":"DE",
    "sg:address":"Hauptstr. 15",
    "sg:city":"Peitz",
    "sg:phone":"+49 35601/23195",
    "sg:postcode":"03185",
    "sg:province":"Brandenburg",
    "wof:name":"Eb\u00fcs Gmbh",
    "wof:placetype":"venue"
},
  "geometry": {"coordinates":[14.410988,51.857723],"type":"Point"}
}