{
  "type": "Feature",
  "properties": {
    "iso:country":"DE",
    "sg:address":"Cloppenburger Str. 27",
    "sg:city":"Oldenburg",
    "sg:phone":"+49 441/14075",
    "sg:postcode":"26135",
    "sg:province":"Niedersachsen",
    "wof:name":"Otto Meyer",
    "wof:placetype":"venue"
},
  "geometry": {"coordinates":[8.221383,53.129723],"type":"Point"}
}