{
  "type": "Feature",
  "properties": {
    "iso:country":"DE",
    "sg:address":"Moritzburgring 6",
    "sg:city":"Halle",
    "sg:phone":"+49 345/3881568",
    "sg:postcode":"06108",
    "sg:province":"Sachsen-Anhalt",
    "wof:name":"Heike Rogge",
    "wof:placetype":"venue"
},
  "geometry": {"coordinates":[11.965243,51.487347],"type":"Point"}
}