{
  "type": "Feature",
  "properties": {
    "iso:country":"DE",
    "sg:address":"Thomas-Mann-Str. 9",
    "sg:city":"Schwedt",
    "sg:postcode":"16303",
    "sg:province":"Brandenburg",
    "wof:name":"Lvm Versicherung",
    "wof:placetype":"venue"
},
  "geometry": {"coordinates":[14.2794713974,53.06457901],"type":"Point"}
}