{
  "type": "Feature",
  "properties": {
    "iso:country":"DE",
    "sg:address":"Rote Erde 2",
    "sg:city":"Steinhagen",
    "sg:phone":"+49 5204/2749",
    "sg:postcode":"33803",
    "sg:province":"Nordrhein-Westfalen",
    "wof:name":"Ottensmann",
    "wof:placetype":"venue"
},
  "geometry": {"coordinates":[8.428416,52.014889],"type":"Point"}
}