{
  "type": "Feature",
  "properties": {
    "iso:country":"DE",
    "sg:address":"Holzkamp 24",
    "sg:city":"Itzehoe",
    "sg:phone":"+49 4821/67500",
    "sg:postcode":"25524",
    "sg:province":"Schleswig-Holstein",
    "wof:name":"Pickert K\u00f6nig Und Rummel Rechtsanw\u00e4lte Und Notare",
    "wof:placetype":"venue"
},
  "geometry": {"coordinates":[9.5225763321,53.92345047],"type":"Point"}
}