{
  "type": "Feature",
  "properties": {
    "iso:country":"DE",
    "sg:address":"Hauptstr. 1",
    "sg:city":"Hanhofen",
    "sg:phone":"+49 6344/5644",
    "sg:postcode":"67374",
    "sg:province":"Rheinland-Pfalz",
    "wof:name":"Georg Gr\u00fcner Schlo\u00dfm\u00fchle",
    "wof:placetype":"venue"
},
  "geometry": {"coordinates":[8.3493900299,49.3171234131],"type":"Point"}
}