{
  "type": "Feature",
  "properties": {
    "iso:country":"DE",
    "sg:address":"Kr\u00fctzpoort 1",
    "sg:city":"Krefeld",
    "sg:phone":"+49 2151/972100",
    "sg:postcode":"47804",
    "sg:province":"Nordrhein-Westfalen",
    "wof:name":"H. Thiel Steuerberater",
    "wof:placetype":"venue"
},
  "geometry": {"coordinates":[6.5292959213,51.3265953064],"type":"Point"}
}