{
  "type": "Feature",
  "properties": {
    "iso:country":"DE",
    "sg:address":"J\u00f6llenbecker Str. 99 a",
    "sg:city":"Bielefeld",
    "sg:phone":"+49 521/171128",
    "sg:postcode":"33613",
    "sg:province":"Nordrhein-Westfalen",
    "wof:name":"Generali Lloyd Versicherung Ag",
    "wof:placetype":"venue"
},
  "geometry": {"coordinates":[8.5238447189,52.0344581604],"type":"Point"}
}