{
  "type": "Feature",
  "properties": {
    "iso:country":"DE",
    "sg:address":"Oldenburger Landstr 2",
    "sg:city":"Osnabr\u00fcck",
    "sg:phone":"+49 541/96460",
    "sg:postcode":"49090",
    "sg:province":"Niedersachsen",
    "wof:name":"Cc Erfrischungsgetr\u00e4nke Teutoburger Wald Gmbh & Co Kg",
    "wof:placetype":"venue"
},
  "geometry": {"coordinates":[8.035646,52.302956],"type":"Point"}
}