{
  "type": "Feature",
  "properties": {
    "iso:country":"DE",
    "sg:address":"Luxemburger Allee 4",
    "sg:city":"M\u00fclheim",
    "sg:postcode":"45481",
    "sg:province":"Nordrhein-Westfalen",
    "wof:name":"Papyrus Versicherungs- Vermittler F\u00fcr Die",
    "wof:placetype":"venue"
},
  "geometry": {"coordinates":[6.8717360497,51.3949584961],"type":"Point"}
}