{
  "type": "Feature",
  "properties": {
    "iso:country":"DE",
    "sg:address":"Milanweg 20",
    "sg:city":"Bielefeld",
    "sg:phone":"+49 521/494806",
    "sg:postcode":"33659",
    "sg:province":"Nordrhein-Westfalen",
    "wof:name":"S. Martin",
    "wof:placetype":"venue"
},
  "geometry": {"coordinates":[8.535514,51.974941],"type":"Point"}
}