{
  "type": "Feature",
  "properties": {
    "iso:country":"DE",
    "sg:address":"Els\u00e4sser Str 35",
    "sg:city":"L\u00fcbeck",
    "sg:phone":"+49 451/6110666",
    "sg:postcode":"23564",
    "sg:province":"Schleswig-Holstein",
    "wof:name":"Suntronic Inh. P. Cruse",
    "wof:placetype":"venue"
},
  "geometry": {"coordinates":[10.7053670883,53.8590202332],"type":"Point"}
}