{
  "type": "Feature",
  "properties": {
    "iso:country":"DE",
    "sg:address":"Ziegeleistr. 55",
    "sg:city":"Hille",
    "sg:phone":"+49 5703/697",
    "sg:postcode":"32479",
    "sg:province":"Nordrhein-Westfalen",
    "wof:name":"H. Niedernolte",
    "wof:placetype":"venue"
},
  "geometry": {"coordinates":[8.774006,52.376663],"type":"Point"}
}