{
  "type": "Feature",
  "properties": {
    "iso:country":"DE",
    "sg:address":"Bremerhavener Str. 24",
    "sg:city":"Gnarrenburg",
    "sg:phone":"+49 4763/7265",
    "sg:postcode":"27442",
    "sg:province":"Niedersachsen",
    "wof:name":"Helmut Fittschen",
    "wof:placetype":"venue"
},
  "geometry": {"coordinates":[8.951515,53.385128],"type":"Point"}
}