{
  "type": "Feature",
  "properties": {
    "iso:country":"DE",
    "sg:address":"Hauswiesen 20",
    "sg:city":"K\u00fcnzelsau",
    "sg:phone":"+49 7944/395",
    "sg:postcode":"74653",
    "sg:province":"Baden-W\u00fcrttemberg",
    "wof:name":"Gastst\u00e4tte Rudolf Krummrein",
    "wof:placetype":"venue"
},
  "geometry": {"coordinates":[9.7086362839,49.2475242615],"type":"Point"}
}