{
  "type": "Feature",
  "properties": {
    "iso:country":"DE",
    "sg:address":"Am Passagierkai 4",
    "sg:city":"Warnem\u00fcnde-Rostock",
    "sg:phone":"+49 4938/151183",
    "sg:postcode":"18119",
    "sg:province":"Mecklenburg-Vorpommern",
    "wof:name":"Scan-mot Schiffstechnik Gmbh",
    "wof:placetype":"venue"
},
  "geometry": {"coordinates":[12.0345153809,54.1690864563],"type":"Point"}
}