{
  "type": "Feature",
  "properties": {
    "iso:country":"DE",
    "sg:address":"Hofer Str. 29",
    "sg:city":"Mittelbach",
    "sg:phone":"+49 371/8200970",
    "sg:postcode":"09224",
    "sg:province":"Sachsen",
    "wof:name":"Eiscafe Heidrun Adner",
    "wof:placetype":"venue"
},
  "geometry": {"coordinates":[12.791245,50.810249],"type":"Point"}
}