{
  "type": "Feature",
  "properties": {
    "iso:country":"DE",
    "sg:address":"Schwabaicherstr. 1",
    "sg:city":"Langerringen",
    "sg:phone":"+49 8248",
    "sg:postcode":"86853",
    "sg:province":"Bayern",
    "wof:name":"Landtechnik Hefele",
    "wof:placetype":"venue"
},
  "geometry": {"coordinates":[10.7686929703,48.1063232422],"type":"Point"}
}