{
  "type": "Feature",
  "properties": {
    "iso:country":"DE",
    "sg:address":"Gustav-Bastert-Str. 8",
    "sg:city":"Bielefeld",
    "sg:phone":"+49 521/3368723",
    "sg:postcode":"33719",
    "sg:province":"Nordrhein-Westfalen",
    "wof:name":"Dr\u00f6ge Kg",
    "wof:placetype":"venue"
},
  "geometry": {"coordinates":[8.610255,52.027779],"type":"Point"}
}