{
  "type": "Feature",
  "properties": {
    "iso:country":"DE",
    "sg:address":"Sauerlacher Str. 10",
    "sg:city":"Egling",
    "sg:phone":"+49 8176/7427",
    "sg:postcode":"82544",
    "sg:province":"Bayern",
    "wof:name":"Hans Sepp",
    "wof:placetype":"venue"
},
  "geometry": {"coordinates":[11.536422,47.925976],"type":"Point"}
}