{
  "type": "Feature",
  "properties": {
    "iso:country":"DE",
    "sg:address":"Am Gewerbepark 22",
    "sg:city":"S\u00fcptitz",
    "sg:phone":"+49 3421/7406",
    "sg:postcode":"04860",
    "sg:province":"Sachsen",
    "wof:name":"Bauunternehmung Ezel Torgau Gmbh",
    "wof:placetype":"venue"
},
  "geometry": {"coordinates":[12.923235,51.560387],"type":"Point"}
}