{
  "type": "Feature",
  "properties": {
    "iso:country":"DE",
    "sg:address":"Borussiastr. 101",
    "sg:city":"Dortmund",
    "sg:phone":"+49 231/96560",
    "sg:postcode":"44149",
    "sg:province":"Nordrhein-Westfalen",
    "wof:name":"Metro Sb-gro\u00dfm\u00e4rkte Verwaltungs Gmbh",
    "wof:placetype":"venue"
},
  "geometry": {"coordinates":[7.3696761131,51.4932022095],"type":"Point"}
}