{
  "type": "Feature",
  "properties": {
    "iso:country":"DE",
    "sg:address":"Am Hohen Baum 2",
    "sg:city":"Neulingen",
    "sg:phone":"+49 7237/1469",
    "sg:postcode":"75245",
    "sg:province":"Baden-W\u00fcrttemberg",
    "wof:name":"Wilhelm Lansche",
    "wof:placetype":"venue"
},
  "geometry": {"coordinates":[8.688714,48.988865],"type":"Point"}
}