{
  "type": "Feature",
  "properties": {
    "iso:country":"DE",
    "sg:address":"Wiener Str. 26 - 32",
    "sg:city":"Bielefeld",
    "sg:postcode":"33649",
    "sg:province":"Nordrhein-Westfalen",
    "wof:name":"Lindhorst Gmbh",
    "wof:placetype":"venue"
},
  "geometry": {"coordinates":[8.474762,51.985359],"type":"Point"}
}