{
  "type": "Feature",
  "properties": {
    "iso:country":"DE",
    "sg:address":"Gartenstr. 31",
    "sg:city":"Kelbra",
    "sg:phone":"+49 34651/98684",
    "sg:postcode":"06537",
    "sg:province":"Sachsen-Anhalt",
    "wof:name":"A. Kundlatsch",
    "wof:placetype":"venue"
},
  "geometry": {"coordinates":[11.039437,51.432907],"type":"Point"}
}