{
  "type": "Feature",
  "properties": {
    "iso:country":"DE",
    "sg:address":"Remstalstr. 43-45",
    "sg:city":"Remseck",
    "sg:phone":"+49 7146/7324",
    "sg:postcode":"71686",
    "sg:province":"Baden-W\u00fcrttemberg",
    "wof:name":"Jochen Zeller",
    "wof:placetype":"venue"
},
  "geometry": {"coordinates":[9.2737550735,48.8706741333],"type":"Point"}
}