{
  "type": "Feature",
  "properties": {
    "iso:country":"DE",
    "sg:address":"M\u00f6nchw\u00f6rthstr. 78a",
    "sg:city":"Mannheim",
    "sg:phone":"+49 621/815180",
    "sg:postcode":"68199",
    "sg:province":"Baden-W\u00fcrttemberg",
    "wof:name":"Michael C. Sternheimer \u00dcbersetzungsgemeinschaft",
    "wof:placetype":"venue"
},
  "geometry": {"coordinates":[8.48691,49.463657],"type":"Point"}
}