{
  "type": "Feature",
  "properties": {
    "iso:country":"DE",
    "sg:address":"Ackerstr. 184",
    "sg:city":"D\u00fcsseldorf",
    "sg:phone":"+49 211/660313",
    "sg:postcode":"40235",
    "sg:province":"Nordrhein-Westfalen",
    "wof:name":"Ingrid Jansen Modevertriebs Gmbh",
    "wof:placetype":"venue"
},
  "geometry": {"coordinates":[6.8099927902,51.2310256958],"type":"Point"}
}