{
  "type": "Feature",
  "properties": {
    "iso:country":"DE",
    "sg:address":"Obere Steinbeisstr. 41",
    "sg:city":"\u00d6lbronn-D\u00fcrrn",
    "sg:phone":"+49 7043/8482",
    "sg:postcode":"75248",
    "sg:province":"Baden-W\u00fcrttemberg",
    "wof:name":"Frank Reichelt",
    "wof:placetype":"venue"
},
  "geometry": {"coordinates":[8.7535581589,48.9808731079],"type":"Point"}
}