{
  "type": "Feature",
  "properties": {
    "iso:country":"DE",
    "sg:address":"Silberstr. 42",
    "sg:city":"Crimmitschau",
    "sg:phone":"+49 3762/2960",
    "sg:postcode":"08451",
    "sg:province":"Sachsen",
    "wof:name":"Ralf Zschiegner",
    "wof:placetype":"venue"
},
  "geometry": {"coordinates":[12.3869495392,50.8140716553],"type":"Point"}
}