{
  "type": "Feature",
  "properties": {
    "iso:country":"DE",
    "sg:address":"Schleiermacherstr. 8",
    "sg:city":"Darmstadt",
    "sg:phone":"+49 6151/25980",
    "sg:postcode":"64283",
    "sg:province":"Hessen",
    "wof:name":"Otto Hoffmann Architekt",
    "wof:placetype":"venue"
},
  "geometry": {"coordinates":[8.651912,49.874405],"type":"Point"}
}