{
  "type": "Feature",
  "properties": {
    "iso:country":"DE",
    "sg:address":"Junkerstr. 5",
    "sg:city":"Oldenburg",
    "sg:phone":"+49 441/81289",
    "sg:postcode":"26123",
    "sg:province":"Niedersachsen",
    "wof:name":"Bernd Rehbock",
    "wof:placetype":"venue"
},
  "geometry": {"coordinates":[8.225986,53.151817],"type":"Point"}
}