{
  "type": "Feature",
  "properties": {
    "iso:country":"DE",
    "sg:address":"Hinter dem Dorf 6",
    "sg:city":"Zernitz",
    "sg:phone":"+49 33973/50210",
    "sg:postcode":"16845",
    "sg:province":"Brandenburg",
    "wof:name":"G\u00fcnter Kopka",
    "wof:placetype":"venue"
},
  "geometry": {"coordinates":[12.374871,52.880989],"type":"Point"}
}