{
  "type": "Feature",
  "properties": {
    "iso:country":"DE",
    "sg:address":"Michael-Bauer-Stra\u00dfe 30",
    "sg:city":"Lappersdorf",
    "sg:phone":"+49 941/81060",
    "sg:postcode":"93138",
    "sg:province":"Bayern",
    "wof:name":"Staatliche Feuerwehrschule Regensburg - Homepage",
    "wof:placetype":"venue"
},
  "geometry": {"coordinates":[12.08674,49.057526],"type":"Point"}
}