{
  "type": "Feature",
  "properties": {
    "iso:country":"DE",
    "sg:address":"Kiesstr. 45",
    "sg:city":"Berlin",
    "sg:phone":"+49 30/7720500",
    "sg:postcode":"12209",
    "sg:province":"Berlin",
    "wof:name":"Kath. Kinderheim St. Monika",
    "wof:placetype":"venue"
},
  "geometry": {"coordinates":[13.337439537,52.4232063293],"type":"Point"}
}