{
  "type": "Feature",
  "properties": {
    "iso:country":"DE",
    "sg:address":"Berliner Str. 6",
    "sg:city":"Rheda-Wiedenbr\u00fcck",
    "sg:phone":"+49 5242/42638",
    "sg:postcode":"33378",
    "sg:province":"Nordrhein-Westfalen",
    "wof:name":"Werner D\u00fcsing",
    "wof:placetype":"venue"
},
  "geometry": {"coordinates":[8.2916517258,51.8509521484],"type":"Point"}
}