{
  "type": "Feature",
  "properties": {
    "iso:country":"DE",
    "sg:address":"Deggendorfer Str. 16",
    "sg:city":"Wallersdorf",
    "sg:phone":"+49 9933/321",
    "sg:postcode":"94522",
    "sg:province":"Bayern",
    "wof:name":"W. Glockshuber & G. Weinzierl",
    "wof:placetype":"venue"
},
  "geometry": {"coordinates":[12.747026,48.739182],"type":"Point"}
}