{
  "type": "Feature",
  "properties": {
    "iso:country":"DE",
    "sg:address":"Dielmannstr. 48",
    "sg:city":"Offenbach",
    "sg:phone":"+49 69/9840210",
    "sg:postcode":"63069",
    "sg:province":"Hessen",
    "wof:name":"Hans-j\u00fcrgen H\u00f6pcker Steuerberater",
    "wof:placetype":"venue"
},
  "geometry": {"coordinates":[8.744140625,50.0894813538],"type":"Point"}
}