{
  "type": "Feature",
  "properties": {
    "iso:country":"DE",
    "sg:address":"Im Flecken 17",
    "sg:city":"Barenburg",
    "sg:phone":"+49 4273/391",
    "sg:postcode":"27245",
    "sg:province":"Niedersachsen",
    "wof:name":"Henry Maschmann",
    "wof:placetype":"venue"
},
  "geometry": {"coordinates":[8.7989902496,52.6196517944],"type":"Point"}
}