{
  "type": "Feature",
  "properties": {
    "iso:country":"DE",
    "sg:address":"Holterkamp 18",
    "sg:city":"Ratingen",
    "sg:phone":"+49 2102/33009",
    "sg:postcode":"40880",
    "sg:province":"Nordrhein-Westfalen",
    "wof:name":"Rino Food Gmbh",
    "wof:placetype":"venue"
},
  "geometry": {"coordinates":[6.8312401772,51.3132514954],"type":"Point"}
}