{
  "type": "Feature",
  "properties": {
    "iso:country":"DE",
    "sg:address":"Aiblinger Str. 1",
    "sg:city":"A\u00dfling",
    "sg:phone":"+49 8092/7187",
    "sg:postcode":"85617",
    "sg:province":"Bayern",
    "wof:name":"Bauer",
    "wof:placetype":"venue"
},
  "geometry": {"coordinates":[11.9729919434,47.9969673157],"type":"Point"}
}