{
  "type": "Feature",
  "properties": {
    "iso:country":"DE",
    "sg:address":"Siebentunnelweg 59",
    "sg:city":"Halstenbek",
    "sg:phone":"+49 4101/42417",
    "sg:postcode":"25469",
    "sg:province":"Schleswig-Holstein",
    "wof:name":"Wolfgang Lenz",
    "wof:placetype":"venue"
},
  "geometry": {"coordinates":[9.863411,53.611443],"type":"Point"}
}