{
  "type": "Feature",
  "properties": {
    "iso:country":"DE",
    "sg:address":"Schubertstr. 41",
    "sg:city":"Dresden",
    "sg:phone":"+49 351/318210",
    "sg:postcode":"01307",
    "sg:province":"Sachsen",
    "wof:name":"Warth & Klein Gmbh",
    "wof:placetype":"venue"
},
  "geometry": {"coordinates":[13.7861270905,51.0600166321],"type":"Point"}
}