{
  "type": "Feature",
  "properties": {
    "iso:country":"DE",
    "sg:address":"Reisstr. 24a",
    "sg:city":"Friedberg",
    "sg:phone":"+49 821/666540",
    "sg:postcode":"86316",
    "sg:province":"Bayern",
    "wof:name":"Paul Loos",
    "wof:placetype":"venue"
},
  "geometry": {"coordinates":[10.9582357407,48.3473320007],"type":"Point"}
}