{
  "type": "Feature",
  "properties": {
    "iso:country":"DE",
    "sg:address":"Schulstr. 1",
    "sg:city":"Dietingen",
    "sg:phone":"+49 7404/427",
    "sg:postcode":"78661",
    "sg:province":"Baden-W\u00fcrttemberg",
    "wof:name":"T. Bachmann",
    "wof:placetype":"venue"
},
  "geometry": {"coordinates":[8.6589279175,48.2478179932],"type":"Point"}
}