{
  "type": "Feature",
  "properties": {
    "iso:country":"DE",
    "sg:address":"Professor-K\u00fcck-Str. 8",
    "sg:city":"Hollenstedt",
    "sg:phone":"+49 4165/8450",
    "sg:postcode":"21279",
    "sg:province":"Niedersachsen",
    "wof:name":"Heinrich B\u00f6hrs",
    "wof:placetype":"venue"
},
  "geometry": {"coordinates":[9.7157077789,53.3660545349],"type":"Point"}
}