{
  "type": "Feature",
  "properties": {
    "iso:country":"DE",
    "sg:address":"Sieversdorf",
    "sg:city":"Malente",
    "sg:phone":"+49 4523/2561",
    "sg:postcode":"23714",
    "sg:province":"Schleswig-Holstein",
    "wof:name":"Vereinigte Kieswerke In Ostholstein Gmbh & Co. Kg",
    "wof:placetype":"venue"
},
  "geometry": {"coordinates":[10.5595903397,54.2030487061],"type":"Point"}
}