{
  "type": "Feature",
  "properties": {
    "iso:country":"DE",
    "sg:address":"Alt-Mahlsdorf 20",
    "sg:city":"Berlin",
    "sg:phone":"+49 30/5677975",
    "sg:postcode":"12623",
    "sg:province":"Berlin",
    "wof:name":"Hotel An Der Weide",
    "wof:placetype":"venue"
},
  "geometry": {"coordinates":[13.605632782,52.5052261353],"type":"Point"}
}