{
  "type": "Feature",
  "properties": {
    "iso:country":"DE",
    "sg:address":"Unterdorf 17",
    "sg:city":"B\u00fcttelborn",
    "sg:phone":"+49 6152/40871",
    "sg:postcode":"64572",
    "sg:province":"Hessen",
    "wof:name":"Werner St\u00fctz",
    "wof:placetype":"venue"
},
  "geometry": {"coordinates":[8.546382,49.928688],"type":"Point"}
}