{
  "type": "Feature",
  "properties": {
    "iso:country":"DE",
    "sg:address":"Kirchbr\u00fcndlstr. 10",
    "sg:city":"Tyrlaching",
    "sg:phone":"+49 8623/1088",
    "sg:postcode":"84558",
    "sg:province":"Bayern",
    "wof:name":"G\u00fcnther Kirchleitner",
    "wof:placetype":"venue"
},
  "geometry": {"coordinates":[12.6710109711,48.0601730347],"type":"Point"}
}