{
  "type": "Feature",
  "properties": {
    "iso:country":"DE",
    "sg:address":"Gartenweg 18",
    "sg:city":"Wasbek",
    "sg:postcode":"24647",
    "sg:province":"Schleswig-Holstein",
    "wof:name":"W. Golland",
    "wof:placetype":"venue"
},
  "geometry": {"coordinates":[9.9274616241,54.067073822],"type":"Point"}
}