{
  "type": "Feature",
  "properties": {
    "iso:country":"DE",
    "sg:address":"Am Plan 7",
    "sg:city":"Koblenz",
    "sg:phone":"+49 261/12216",
    "sg:postcode":"56068",
    "sg:province":"Rheinland-Pfalz",
    "wof:name":"I. K. Mrozek E. K.",
    "wof:placetype":"venue"
},
  "geometry": {"coordinates":[7.5951161385,50.3603897095],"type":"Point"}
}