{
  "type": "Feature",
  "properties": {
    "iso:country":"DE",
    "sg:address":"Schwarzwaldstr. 43",
    "sg:city":"Kelkheim",
    "sg:phone":"+49 6195/61300",
    "sg:postcode":"65779",
    "sg:province":"Hessen",
    "wof:name":"A. Dumke-sch\u00e4fer Und H.schmitt",
    "wof:placetype":"venue"
},
  "geometry": {"coordinates":[8.4332094193,50.1472930908],"type":"Point"}
}