{
  "type": "Feature",
  "properties": {
    "iso:country":"DE",
    "sg:address":"Zeppelinstr. 33",
    "sg:city":"Griesheim",
    "sg:phone":"+49 6155/66283",
    "sg:postcode":"64347",
    "sg:province":"Hessen",
    "wof:name":"Cd Solft Gmbh",
    "wof:placetype":"venue"
},
  "geometry": {"coordinates":[8.5853624344,49.859161377],"type":"Point"}
}