{
  "type": "Feature",
  "properties": {
    "iso:country":"DE",
    "sg:address":"Schlei\u00dfheimer Str. 375",
    "sg:city":"M\u00fcnchen",
    "sg:phone":"+49 89/3510027",
    "sg:postcode":"80935",
    "sg:province":"Bayern",
    "wof:name":"Hometrend Inku Gmbh",
    "wof:placetype":"venue"
},
  "geometry": {"coordinates":[11.5648708344,48.1937255859],"type":"Point"}
}