{
  "type": "Feature",
  "properties": {
    "iso:country":"DE",
    "sg:address":"K\u00f6rpricher Str. 4",
    "sg:city":"Lebach",
    "sg:phone":"+49 6881/2448",
    "sg:postcode":"66822",
    "sg:province":"Saarland",
    "wof:name":"Alfred Ziegler",
    "wof:placetype":"venue"
},
  "geometry": {"coordinates":[6.911285,49.410816],"type":"Point"}
}