{
  "type": "Feature",
  "properties": {
    "iso:country":"DE",
    "sg:address":"Weinsberg 6",
    "sg:city":"Solingen",
    "sg:phone":"+49 212/812805",
    "sg:postcode":"42657",
    "sg:province":"Nordrhein-Westfalen",
    "wof:name":"T. Bachem",
    "wof:placetype":"venue"
},
  "geometry": {"coordinates":[7.081412,51.157406],"type":"Point"}
}