{
  "type": "Feature",
  "properties": {
    "iso:country":"DE",
    "sg:address":"Mehlbeerenstr. 3",
    "sg:city":"Landsberg",
    "sg:phone":"+49 8191/5427",
    "sg:postcode":"86899",
    "sg:province":"Bayern",
    "wof:name":"Fabienne Und Edgar Senkel",
    "wof:placetype":"venue"
},
  "geometry": {"coordinates":[10.8595552444,48.0526924133],"type":"Point"}
}