{
  "type": "Feature",
  "properties": {
    "iso:country":"DE",
    "sg:address":"Dotzheimer Str. 25",
    "sg:city":"Wiesbaden",
    "sg:phone":"+49 611/300455",
    "sg:postcode":"65185",
    "sg:province":"Hessen",
    "wof:name":"Engel Apotheke Martin Heyse E. K.",
    "wof:placetype":"venue"
},
  "geometry": {"coordinates":[8.233152,50.078671],"type":"Point"}
}