{
  "type": "Feature",
  "properties": {
    "iso:country":"DE",
    "sg:address":"Kreuzeichenstr. 2",
    "sg:city":"Neuenstein",
    "sg:phone":"+49 6677/1451",
    "sg:postcode":"36286",
    "sg:province":"Hessen",
    "wof:name":"Wolfgang Gerland",
    "wof:placetype":"venue"
},
  "geometry": {"coordinates":[9.5991230011,50.90366745],"type":"Point"}
}