{
  "type": "Feature",
  "properties": {
    "iso:country":"DE",
    "sg:address":"Ausschl\u00e4ger Billdeich 50",
    "sg:city":"Hamburg",
    "sg:phone":"+49 40/7891660",
    "sg:postcode":"20539",
    "sg:province":"Hamburg",
    "wof:name":"Transo-pharm Produktions Gmbh",
    "wof:placetype":"venue"
},
  "geometry": {"coordinates":[10.050339,53.541458],"type":"Point"}
}