{
  "type": "Feature",
  "properties": {
    "iso:country":"DE",
    "sg:address":"Raiffeisenstr. 8",
    "sg:city":"Bubesheim",
    "sg:phone":"+49 8221/6507",
    "sg:postcode":"89347",
    "sg:province":"Bayern",
    "wof:name":"Ernst Arnold Gmbh Fliesen Und Kachelofenbau",
    "wof:placetype":"venue"
},
  "geometry": {"coordinates":[10.257191658,48.4330291748],"type":"Point"}
}