{
  "type": "Feature",
  "properties": {
    "iso:country":"DE",
    "sg:address":"Unterstr. 10",
    "sg:city":"Harzgerode",
    "sg:phone":"+49 39484/42879",
    "sg:postcode":"06493",
    "sg:province":"Sachsen-Anhalt",
    "wof:name":"U. Pilling",
    "wof:placetype":"venue"
},
  "geometry": {"coordinates":[11.145414,51.641365],"type":"Point"}
}