{
  "type": "Feature",
  "properties": {
    "iso:country":"DE",
    "sg:address":"G\u00f6nnheimer Str. 4",
    "sg:city":"Ellerstadt",
    "sg:phone":"+49 6237/2291",
    "sg:postcode":"67158",
    "sg:province":"Rheinland-Pfalz",
    "wof:name":"Armin Schneider Weinanbau",
    "wof:placetype":"venue"
},
  "geometry": {"coordinates":[8.258433342,49.4613037109],"type":"Point"}
}