{
  "type": "Feature",
  "properties": {
    "iso:country":"DE",
    "sg:address":"Kirchweg 3",
    "sg:city":"Hagnau",
    "sg:phone":"+49 7532/6231",
    "sg:postcode":"88709",
    "sg:province":"Baden-W\u00fcrttemberg",
    "wof:name":"Kath. Pfarramt St. Johann Baphist",
    "wof:placetype":"venue"
},
  "geometry": {"coordinates":[9.3198823929,47.6750488281],"type":"Point"}
}