{
  "type": "Feature",
  "properties": {
    "iso:country":"DE",
    "sg:address":"Meisenweg 35",
    "sg:city":"Neumarkt",
    "sg:phone":"+49 9181/905060",
    "sg:postcode":"92318",
    "sg:province":"Bayern",
    "wof:name":"M. Und A. Altug",
    "wof:placetype":"venue"
},
  "geometry": {"coordinates":[11.460521698,49.2542877197],"type":"Point"}
}