{
  "type": "Feature",
  "properties": {
    "iso:country":"DE",
    "sg:address":"Dorfstr. 93",
    "sg:city":"Schneeberg",
    "sg:phone":"+49 3772/28611",
    "sg:postcode":"08289",
    "sg:province":"Sachsen",
    "wof:name":"Thierfelder Reisen Gmbh",
    "wof:placetype":"venue"
},
  "geometry": {"coordinates":[12.6204948425,50.5882072449],"type":"Point"}
}