{
  "type": "Feature",
  "properties": {
    "iso:country":"DE",
    "sg:address":"Tengstr. 28",
    "sg:city":"M\u00fcnchen",
    "sg:phone":"+49 89/2712287",
    "sg:postcode":"80798",
    "sg:province":"Bayern",
    "wof:name":"E. John Milch Und Molkereiprodukte Eh",
    "wof:placetype":"venue"
},
  "geometry": {"coordinates":[11.5692129135,48.1586456299],"type":"Point"}
}