{
  "type": "Feature",
  "properties": {
    "iso:country":"DE",
    "sg:address":"Efeuweg 8",
    "sg:city":"Bergkamen",
    "sg:phone":"+49 2307/87664",
    "sg:postcode":"59192",
    "sg:province":"Nordrhein-Westfalen",
    "wof:name":"Arendt-transporte Inh. Erika Arendt",
    "wof:placetype":"venue"
},
  "geometry": {"coordinates":[7.6661162376,51.6217155457],"type":"Point"}
}