{
  "type": "Feature",
  "properties": {
    "iso:country":"DE",
    "sg:address":"Ludwig-Feuerbach-Weg 15a",
    "sg:city":"Rostock",
    "sg:phone":"+49 381/681879",
    "sg:postcode":"18146",
    "sg:province":"Mecklenburg-Vorpommern",
    "wof:name":"Dierkower M\u00fchle",
    "wof:placetype":"venue"
},
  "geometry": {"coordinates":[12.1526060104,54.1095809937],"type":"Point"}
}