{
  "type": "Feature",
  "properties": {
    "iso:country":"DE",
    "sg:address":"Unterer Markt 15",
    "sg:city":"Aidenbach",
    "sg:phone":"+49 8543/4954",
    "sg:postcode":"94501",
    "sg:province":"Bayern",
    "wof:name":"Josefine Strenz Masseurin",
    "wof:placetype":"venue"
},
  "geometry": {"coordinates":[13.083957,48.568741],"type":"Point"}
}