{
  "type": "Feature",
  "properties": {
    "iso:country":"DE",
    "sg:address":"Oranienstr. 36",
    "sg:city":"Mainz",
    "sg:phone":"+49 6131/466551",
    "sg:postcode":"55124",
    "sg:province":"Rheinland-Pfalz",
    "wof:name":"Simpex Lebensmittelhandel Gmbh",
    "wof:placetype":"venue"
},
  "geometry": {"coordinates":[8.2101917267,50.0066680908],"type":"Point"}
}