{
  "type": "Feature",
  "properties": {
    "iso:country":"DE",
    "sg:address":"Hetendorf 47",
    "sg:city":"Hermannsburg",
    "sg:phone":"+49 5052/1224",
    "sg:postcode":"29320",
    "sg:province":"Niedersachsen",
    "wof:name":"Hubertus Von Bothmer Architekt",
    "wof:placetype":"venue"
},
  "geometry": {"coordinates":[10.027037,52.866711],"type":"Point"}
}