{
  "type": "Feature",
  "properties": {
    "iso:country":"DE",
    "sg:address":"B\u00fcrgermeister-Smidt-Str. 56",
    "sg:city":"Bremen",
    "sg:postcode":"28195",
    "sg:province":"Bremen",
    "wof:name":"Danitz & Walter Gmbh",
    "wof:placetype":"venue"
},
  "geometry": {"coordinates":[8.806579,53.081451],"type":"Point"}
}