{
  "type": "Feature",
  "properties": {
    "iso:country":"DE",
    "sg:address":"Gottlieb-Schill-Weg 4",
    "sg:city":"Himmelkron",
    "sg:phone":"+49 9227/972125",
    "sg:postcode":"95502",
    "sg:province":"Bayern",
    "wof:name":"Aha-a\u00dfmann Haus Gmbh",
    "wof:placetype":"venue"
},
  "geometry": {"coordinates":[11.581169,50.058418],"type":"Point"}
}