{
  "type": "Feature",
  "properties": {
    "iso:country":"DE",
    "sg:address":"Untergasse 46",
    "sg:city":"Bingen",
    "sg:phone":"+49 6725/2493",
    "sg:postcode":"55411",
    "sg:province":"Rheinland-Pfalz",
    "wof:name":"Maria Weis",
    "wof:placetype":"venue"
},
  "geometry": {"coordinates":[7.9613780975,49.9225158691],"type":"Point"}
}