{
  "type": "Feature",
  "properties": {
    "iso:country":"DE",
    "sg:address":"Eichenweg 10",
    "sg:city":"B\u00f6sel",
    "sg:postcode":"26219",
    "sg:province":"Niedersachsen",
    "wof:name":"Franz Rolfes",
    "wof:placetype":"venue"
},
  "geometry": {"coordinates":[7.952769,53.021286],"type":"Point"}
}