{
  "type": "Feature",
  "properties": {
    "iso:country":"DE",
    "sg:address":"Florian-Geyer-Str. 1",
    "sg:city":"B\u00f6blingen",
    "sg:postcode":"71034",
    "sg:province":"Baden-W\u00fcrttemberg",
    "wof:name":"F Und B Haustechnik Gmbh",
    "wof:placetype":"venue"
},
  "geometry": {"coordinates":[9.002615,48.668076],"type":"Point"}
}