{
  "type": "Feature",
  "properties": {
    "iso:country":"DE",
    "sg:address":"Dr\u00f6nnewitzer Str. 48",
    "sg:city":"Demmin",
    "sg:phone":"+49 3998/27200",
    "sg:postcode":"17109",
    "sg:province":"Mecklenburg-Vorpommern",
    "wof:name":"Htm Baubetrieb Gmbh",
    "wof:placetype":"venue"
},
  "geometry": {"coordinates":[13.009724617,53.9060974121],"type":"Point"}
}