{
  "type": "Feature",
  "properties": {
    "iso:country":"DE",
    "sg:address":"Br\u00fcderstr. 1",
    "sg:city":"Werdau",
    "sg:phone":"+49 3761/2377",
    "sg:postcode":"08412",
    "sg:province":"Sachsen",
    "wof:name":"Friedrich Piehler",
    "wof:placetype":"venue"
},
  "geometry": {"coordinates":[12.376206398,50.7316970825],"type":"Point"}
}