{
  "type": "Feature",
  "properties": {
    "iso:country":"DE",
    "sg:address":"Hauptstr. 41",
    "sg:city":"R\u00fcdenau",
    "sg:phone":"+49 9371/2834",
    "sg:postcode":"63924",
    "sg:province":"Bayern",
    "wof:name":"Stern",
    "wof:placetype":"venue"
},
  "geometry": {"coordinates":[9.1797981262,49.7111625671],"type":"Point"}
}