{
  "type": "Feature",
  "properties": {
    "iso:country":"DE",
    "sg:address":"Yorckstr. 46",
    "sg:city":"Mittenwalde",
    "sg:postcode":"15749",
    "sg:province":"Brandenburg",
    "wof:name":"Polowczyk Und Kollegen Rechtsanw\u00e4lte",
    "wof:placetype":"venue"
},
  "geometry": {"coordinates":[13.5368833542,52.2634468079],"type":"Point"}
}