{
  "type": "Feature",
  "properties": {
    "iso:country":"DE",
    "sg:address":"Sinziger Str. 2",
    "sg:city":"Berlin",
    "sg:phone":"+49 30/5090202",
    "sg:postcode":"10318",
    "sg:province":"Berlin",
    "wof:name":"Uwe Henneberg Immobilienmakler",
    "wof:placetype":"venue"
},
  "geometry": {"coordinates":[13.5287094116,52.4857063293],"type":"Point"}
}