{
  "type": "Feature",
  "properties": {
    "iso:country":"DE",
    "sg:address":"Am Bocksb\u00fchl 21",
    "sg:city":"Argenb\u00fchl",
    "sg:phone":"+49 7566/1757",
    "sg:postcode":"88260",
    "sg:province":"Baden-W\u00fcrttemberg",
    "wof:name":"Kds Gmbh",
    "wof:placetype":"venue"
},
  "geometry": {"coordinates":[9.964292,47.689407],"type":"Point"}
}