{
  "type": "Feature",
  "properties": {
    "iso:country":"DE",
    "sg:address":"Odenwaldstr. 5",
    "sg:city":"Lauterbach",
    "sg:phone":"+49 6641/2686",
    "sg:postcode":"36341",
    "sg:province":"Hessen",
    "wof:name":"Alfred Becker",
    "wof:placetype":"venue"
},
  "geometry": {"coordinates":[9.3926668167,50.6363601685],"type":"Point"}
}