{
  "type": "Feature",
  "properties": {
    "iso:country":"DE",
    "sg:address":"Eisenbahnstr. 15",
    "sg:city":"Eberswalde",
    "sg:phone":"+49 3334/286038",
    "sg:postcode":"16225",
    "sg:province":"Brandenburg",
    "wof:name":"Krane Optik- Und Akustik Gmbh & Co. Betriebs Kg",
    "wof:placetype":"venue"
},
  "geometry": {"coordinates":[13.8126182556,52.8338508606],"type":"Point"}
}