{
  "type": "Feature",
  "properties": {
    "iso:country":"DE",
    "sg:address":"Dainbach",
    "sg:city":"Dainbach",
    "sg:phone":"+49 4979/306140",
    "sg:postcode":"97980",
    "sg:province":"Baden-W\u00fcrttemberg",
    "wof:name":"Volksbank Boxberg Eg",
    "wof:placetype":"venue"
},
  "geometry": {"coordinates":[9.71553,49.49662],"type":"Point"}
}