{
  "type": "Feature",
  "properties": {
    "iso:country":"DE",
    "sg:address":"Oberer M\u00fchlweg 24",
    "sg:city":"Bad Kreuznach",
    "sg:phone":"+49 671/845333",
    "sg:postcode":"55545",
    "sg:province":"Rheinland-Pfalz",
    "wof:name":"Abflu\u00df-sofortdienst Wittlinger",
    "wof:placetype":"venue"
},
  "geometry": {"coordinates":[7.8397741318,49.8463668823],"type":"Point"}
}