{
  "type": "Feature",
  "properties": {
    "iso:country":"DE",
    "sg:address":"Sommerauer Str. 11",
    "sg:city":"St. Georgen",
    "sg:phone":"+49 7724/6480",
    "sg:postcode":"78112",
    "sg:province":"Baden-W\u00fcrttemberg",
    "wof:name":"Berthold Buroh",
    "wof:placetype":"venue"
},
  "geometry": {"coordinates":[8.3377199173,48.1230201721],"type":"Point"}
}