{
  "type": "Feature",
  "properties": {
    "iso:country":"DE",
    "sg:address":"Ruhsteinstr. 16",
    "sg:city":"M\u00f6hrendorf",
    "sg:phone":"+49 9131/44357",
    "sg:postcode":"91096",
    "sg:province":"Bayern",
    "wof:name":"Thiel Gmbh",
    "wof:placetype":"venue"
},
  "geometry": {"coordinates":[10.998185,49.635654],"type":"Point"}
}