{
  "type": "Feature",
  "properties": {
    "iso:country":"DE",
    "sg:address":"Wilhelmstr. 37-39",
    "sg:city":"Ibbenb\u00fcren",
    "sg:phone":"+49 5451/7006",
    "sg:postcode":"49477",
    "sg:province":"Nordrhein-Westfalen",
    "wof:name":"Transporte Brinkmann Gmbh",
    "wof:placetype":"venue"
},
  "geometry": {"coordinates":[7.7245287895,52.2746429443],"type":"Point"}
}