{
  "type": "Feature",
  "properties": {
    "iso:country":"DE",
    "sg:address":"D\u00fcsseldorfer Str. 26",
    "sg:city":"Leverkusen",
    "sg:phone":"+49 2171/27171",
    "sg:postcode":"51379",
    "sg:province":"Nordrhein-Westfalen",
    "wof:name":"Dr. Med. Amir-m. Nazemi Arzt F\u00fcr Innere Medizin",
    "wof:placetype":"venue"
},
  "geometry": {"coordinates":[7.0009269714,51.0696296692],"type":"Point"}
}