{
  "type": "Feature",
  "properties": {
    "iso:country":"DE",
    "sg:address":"Unter der Mauer 7",
    "sg:city":"Waldenbuch",
    "sg:phone":"+49 7157/8688",
    "sg:postcode":"71111",
    "sg:province":"Baden-W\u00fcrttemberg",
    "wof:name":"R. W\u00f6hrle",
    "wof:placetype":"venue"
},
  "geometry": {"coordinates":[9.132894,48.636848],"type":"Point"}
}