{
  "type": "Feature",
  "properties": {
    "iso:country":"DE",
    "sg:address":"Marktplatz 33",
    "sg:city":"Freudenstadt",
    "sg:phone":"+49 7441/2253",
    "sg:postcode":"72250",
    "sg:province":"Baden-W\u00fcrttemberg",
    "wof:name":"Otto Kl\u00e4ger",
    "wof:placetype":"venue"
},
  "geometry": {"coordinates":[8.411529,48.4627],"type":"Point"}
}