{
  "type": "Feature",
  "properties": {
    "iso:country":"DE",
    "sg:address":"Wuhrweg 9",
    "sg:city":"Binzen",
    "sg:phone":"+49 7621/6086",
    "sg:postcode":"79589",
    "sg:province":"Baden-W\u00fcrttemberg",
    "wof:name":"Chs Software Gmbh",
    "wof:placetype":"venue"
},
  "geometry": {"coordinates":[7.619532,47.630013],"type":"Point"}
}