{
  "type": "Feature",
  "properties": {
    "iso:country":"DE",
    "sg:address":"Otto-Raggenbass-Str. 5",
    "sg:city":"Konstanz",
    "sg:phone":"+49 7531/16411",
    "sg:postcode":"78462",
    "sg:province":"Baden-W\u00fcrttemberg",
    "wof:name":"Rolf Stratemann Heilpraktiker",
    "wof:placetype":"venue"
},
  "geometry": {"coordinates":[9.1747293472,47.6562194824],"type":"Point"}
}