{
  "type": "Feature",
  "properties": {
    "iso:country":"DE",
    "sg:address":"Breite Str. 28",
    "sg:city":"Wernigerode",
    "sg:phone":"+49 3943/633034",
    "sg:postcode":"38855",
    "sg:province":"Sachsen-Anhalt",
    "wof:name":"Rossmann Drogeriemarkt",
    "wof:placetype":"venue"
},
  "geometry": {"coordinates":[10.787047,51.834187],"type":"Point"}
}