{
  "type": "Feature",
  "properties": {
    "iso:country":"DE",
    "sg:address":"Schevenh\u00fctter Str. 67",
    "sg:city":"Stolberg",
    "sg:phone":"+49 2409/9263",
    "sg:postcode":"52224",
    "sg:province":"Nordrhein-Westfalen",
    "wof:name":"Wolfgang Uhlig",
    "wof:placetype":"venue"
},
  "geometry": {"coordinates":[6.3067278862,50.7722930908],"type":"Point"}
}