{
  "type": "Feature",
  "properties": {
    "iso:country":"DE",
    "sg:address":"Stolpener Str.",
    "sg:city":"Bischofswerda",
    "sg:phone":"+49 3594/703753",
    "sg:postcode":"01877",
    "sg:province":"Sachsen",
    "wof:name":"Morgensonne",
    "wof:placetype":"venue"
},
  "geometry": {"coordinates":[14.1710605621,51.1204910278],"type":"Point"}
}