{
  "type": "Feature",
  "properties": {
    "iso:country":"DE",
    "sg:address":"Zur Lehmkuhle 32",
    "sg:city":"N\u00f6rten-Hardenberg",
    "sg:phone":"+49 5503/999132",
    "sg:postcode":"37176",
    "sg:province":"Niedersachsen",
    "wof:name":"Till Habermann",
    "wof:placetype":"venue"
},
  "geometry": {"coordinates":[9.87882,51.636761],"type":"Point"}
}