{
  "type": "Feature",
  "properties": {
    "iso:country":"DE",
    "sg:address":"Buchenweg 1a",
    "sg:city":"Dettenheim",
    "sg:phone":"+49 7255/5517",
    "sg:postcode":"76706",
    "sg:province":"Baden-W\u00fcrttemberg",
    "wof:name":"A. Werner Inh. Heinz Werner",
    "wof:placetype":"venue"
},
  "geometry": {"coordinates":[8.427189827,49.1786613464],"type":"Point"}
}