{
  "type": "Feature",
  "properties": {
    "iso:country":"DE",
    "sg:address":"Leuschstr. 2",
    "sg:city":"Neuss",
    "sg:phone":"+49 2131/50268",
    "sg:postcode":"41460",
    "sg:province":"Nordrhein-Westfalen",
    "wof:name":"Holz-frisch Gmbh Inh. Helmut Frisch",
    "wof:placetype":"venue"
},
  "geometry": {"coordinates":[6.6932058334,51.2244644165],"type":"Point"}
}