{
  "type": "Feature",
  "properties": {
    "iso:country":"DE",
    "sg:address":"Bahnhofstr. 136 c",
    "sg:city":"Maintal",
    "sg:phone":"+49 6181/491425",
    "sg:postcode":"63477",
    "sg:province":"Hessen",
    "wof:name":"Reinhardt Heck Steuerberater",
    "wof:placetype":"venue"
},
  "geometry": {"coordinates":[8.8363056183,50.146156311],"type":"Point"}
}