{
  "type": "Feature",
  "properties": {
    "iso:country":"DE",
    "sg:address":"Nord-S\u00fcd-Str. 1",
    "sg:city":"Salzgitter",
    "sg:postcode":"38259",
    "sg:province":"Niedersachsen",
    "wof:name":"Scg Salzgitter Consult Gmbh",
    "wof:placetype":"venue"
},
  "geometry": {"coordinates":[10.3791952133,52.0476226807],"type":"Point"}
}