{
  "type": "Feature",
  "properties": {
    "iso:country":"DE",
    "sg:address":"Dorfstr. 18",
    "sg:city":"Owschlag",
    "sg:phone":"+49 4336/3393",
    "sg:postcode":"24811",
    "sg:province":"Schleswig-Holstein",
    "wof:name":"Klaus-heinrich Rathje",
    "wof:placetype":"venue"
},
  "geometry": {"coordinates":[9.603262,54.393047],"type":"Point"}
}