{
  "type": "Feature",
  "properties": {
    "iso:country":"DE",
    "sg:address":"Eichsfelder Str. 33",
    "sg:city":"Witzenhausen",
    "sg:phone":"+49 5542/2267",
    "sg:postcode":"37213",
    "sg:province":"Hessen",
    "wof:name":"Mechtild Rommel",
    "wof:placetype":"venue"
},
  "geometry": {"coordinates":[9.845605,51.340233],"type":"Point"}
}