{
  "type": "Feature",
  "properties": {
    "iso:country":"DE",
    "sg:address":"L\u00fcbsche Str. 88",
    "sg:city":"Wismar",
    "sg:postcode":"23966",
    "sg:province":"Mecklenburg-Vorpommern",
    "wof:name":"L. Schuldes",
    "wof:placetype":"venue"
},
  "geometry": {"coordinates":[11.4574136734,53.8917770386],"type":"Point"}
}