{
  "type": "Feature",
  "properties": {
    "iso:country":"DE",
    "sg:address":"Marie-Juchacz-Str. 17",
    "sg:city":"Zweibr\u00fccken",
    "sg:phone":"+49 6332/905627",
    "sg:postcode":"66482",
    "sg:province":"Rheinland-Pfalz",
    "wof:name":"Horst Junger",
    "wof:placetype":"venue"
},
  "geometry": {"coordinates":[7.3479428291,49.2358779907],"type":"Point"}
}