{
  "type": "Feature",
  "properties": {
    "iso:country":"DE",
    "sg:address":"Am Gastland 2",
    "sg:city":"Vechta",
    "sg:postcode":"49377",
    "sg:province":"Niedersachsen",
    "wof:name":"Tennispark Am Brahmpark Gmbh & Co. Kg",
    "wof:placetype":"venue"
},
  "geometry": {"coordinates":[8.2587776184,52.7843971252],"type":"Point"}
}