{
  "type": "Feature",
  "properties": {
    "iso:country":"DE",
    "sg:address":"Bahnhofstr. 39",
    "sg:city":"Rehfelde",
    "sg:phone":"+49 33435/297",
    "sg:postcode":"15345",
    "sg:province":"Brandenburg",
    "wof:name":"Franz Pollak",
    "wof:placetype":"venue"
},
  "geometry": {"coordinates":[13.927136,52.530876],"type":"Point"}
}