{
  "type": "Feature",
  "properties": {
    "iso:country":"DE",
    "sg:address":"Im Schubigsfeld 44",
    "sg:city":"D\u00fcren",
    "sg:phone":"+49 2421/84674",
    "sg:postcode":"52353",
    "sg:province":"Nordrhein-Westfalen",
    "wof:name":"Wilfried Fischer Finanzberater",
    "wof:placetype":"venue"
},
  "geometry": {"coordinates":[6.4401679039,50.8178291321],"type":"Point"}
}