{
  "type": "Feature",
  "properties": {
    "iso:country":"DE",
    "sg:address":"Nassauer Str. 7",
    "sg:city":"Oberursel",
    "sg:phone":"+49 6171/55035",
    "sg:postcode":"61440",
    "sg:province":"Hessen",
    "wof:name":"Deutsche Bahn Ag",
    "wof:placetype":"venue"
},
  "geometry": {"coordinates":[8.5891513824,50.2003860474],"type":"Point"}
}