{
  "type": "Feature",
  "properties": {
    "iso:country":"DE",
    "sg:address":"Fliederweg 10",
    "sg:city":"Geilenkirchen",
    "sg:phone":"+49 2451/66151",
    "sg:postcode":"52511",
    "sg:province":"Nordrhein-Westfalen",
    "wof:name":"J. Kouchen",
    "wof:placetype":"venue"
},
  "geometry": {"coordinates":[6.1213078499,50.9729423523],"type":"Point"}
}