{
  "type": "Feature",
  "properties": {
    "iso:country":"DE",
    "sg:address":"Sch\u00f6nholzer Str. 4",
    "sg:city":"Eberswalde",
    "sg:phone":"+49 3334/300800",
    "sg:postcode":"16227",
    "sg:province":"Brandenburg",
    "wof:name":"Johanniter-unfall-hilfe E. V.",
    "wof:placetype":"venue"
},
  "geometry": {"coordinates":[13.7364225388,52.8365783691],"type":"Point"}
}