{
  "type": "Feature",
  "properties": {
    "iso:country":"DE",
    "sg:address":"Babenhauser Str. 157",
    "sg:city":"Bielefeld",
    "sg:postcode":"33619",
    "sg:province":"Nordrhein-Westfalen",
    "wof:name":"Grundschule Babenhausen",
    "wof:placetype":"venue"
},
  "geometry": {"coordinates":[8.48239,52.057652],"type":"Point"}
}