{
  "type": "Feature",
  "properties": {
    "iso:country":"DE",
    "sg:address":"Humboldtstr. 26",
    "sg:city":"Heinsberg",
    "sg:phone":"+49 2452/3849",
    "sg:postcode":"52525",
    "sg:province":"Nordrhein-Westfalen",
    "wof:name":"W. Mennen",
    "wof:placetype":"venue"
},
  "geometry": {"coordinates":[6.1100621223,51.0672836304],"type":"Point"}
}