{
  "type": "Feature",
  "properties": {
    "iso:country":"DE",
    "sg:address":"Wickrather Str. 9",
    "sg:city":"D\u00fcsseldorf",
    "sg:phone":"+49 211/5381228",
    "sg:postcode":"40547",
    "sg:province":"Nordrhein-Westfalen",
    "wof:name":"Sofia Import-export Gmbh",
    "wof:placetype":"venue"
},
  "geometry": {"coordinates":[6.7302742004,51.2433242798],"type":"Point"}
}