{
  "type": "Feature",
  "properties": {
    "iso:country":"DE",
    "sg:address":"Am Gr\u00fcnen Wege 48",
    "sg:city":"Altena",
    "sg:phone":"+49 2352/21416",
    "sg:postcode":"58762",
    "sg:province":"Nordrhein-Westfalen",
    "wof:name":"Peter Mayweg",
    "wof:placetype":"venue"
},
  "geometry": {"coordinates":[7.671104908,51.3040924072],"type":"Point"}
}