{
  "type": "Feature",
  "properties": {
    "iso:country":"DE",
    "sg:address":"Kiebitzweg 12",
    "sg:city":"Braunschweig",
    "sg:phone":"+49 5307/980110",
    "sg:postcode":"38110",
    "sg:province":"Niedersachsen",
    "wof:name":"Dcs Beratungsgesellschaft F\u00fcr Informationsmanagement Mbh",
    "wof:placetype":"venue"
},
  "geometry": {"coordinates":[10.5642547607,52.3269081116],"type":"Point"}
}