{
  "type": "Feature",
  "properties": {
    "iso:country":"DE",
    "sg:address":"Friedrichsstr. 13",
    "sg:city":"Kassel",
    "sg:phone":"+49 561/7395808",
    "sg:postcode":"34117",
    "sg:province":"Hessen",
    "wof:name":"A. Eifert Anlagenberater",
    "wof:placetype":"venue"
},
  "geometry": {"coordinates":[9.4900417328,51.3123016357],"type":"Point"}
}