{
  "type": "Feature",
  "properties": {
    "iso:country":"DE",
    "sg:address":"S\u00fcndernstr. 16a",
    "sg:city":"Hannover",
    "sg:phone":"+49 511/6463388",
    "sg:postcode":"30657",
    "sg:province":"Niedersachsen",
    "wof:name":"Hans Seegers Gmbh",
    "wof:placetype":"venue"
},
  "geometry": {"coordinates":[9.792146,52.412067],"type":"Point"}
}