{
  "type": "Feature",
  "properties": {
    "iso:country":"DE",
    "sg:address":"Alte Bundesstr. 51",
    "sg:city":"Krempel",
    "sg:phone":"+49 4882/1459",
    "sg:postcode":"25774",
    "sg:province":"Schleswig-Holstein",
    "wof:name":"Carsten Godbersen",
    "wof:placetype":"venue"
},
  "geometry": {"coordinates":[9.029354,54.31741],"type":"Point"}
}