{
  "type": "Feature",
  "properties": {
    "iso:country":"DE",
    "sg:address":"Madenburgstr. 11",
    "sg:city":"Birkweiler",
    "sg:phone":"+49 6345/1782",
    "sg:postcode":"76831",
    "sg:province":"Rheinland-Pfalz",
    "wof:name":"Alban L\u00f6hr Weinanbau",
    "wof:placetype":"venue"
},
  "geometry": {"coordinates":[8.0377178192,49.206615448],"type":"Point"}
}