{
  "type": "Feature",
  "properties": {
    "iso:country":"DE",
    "sg:address":"Liebigstr 32-36",
    "sg:city":"Hamburg",
    "sg:phone":"+49 40/7313671",
    "sg:postcode":"22113",
    "sg:province":"Schleswig-Holstein",
    "wof:name":"Technopan Aussenhandel Gmbh",
    "wof:placetype":"venue"
},
  "geometry": {"coordinates":[10.0857601166,53.5341796875],"type":"Point"}
}