{
  "type": "Feature",
  "properties": {
    "iso:country":"DE",
    "sg:address":"Hofmarkstr. 16",
    "sg:city":"Johanniskirchen",
    "sg:phone":"+49 8564/792",
    "sg:postcode":"84381",
    "sg:province":"Bayern",
    "wof:name":"Johann Steindorfer",
    "wof:placetype":"venue"
},
  "geometry": {"coordinates":[12.944296,48.527328],"type":"Point"}
}