{
  "type": "Feature",
  "properties": {
    "iso:country":"DE",
    "sg:address":"Wiesenweg 4",
    "sg:city":"Laucha",
    "sg:phone":"+49 3622/40300",
    "sg:postcode":"99880",
    "sg:province":"Th\u00fcringen",
    "wof:name":"Allcar 24 Autohaus Gmbh",
    "wof:placetype":"venue"
},
  "geometry": {"coordinates":[10.544894,50.924255],"type":"Point"}
}