{
  "type": "Feature",
  "properties": {
    "iso:country":"DE",
    "sg:address":"Apostelweg 21",
    "sg:city":"Hamburg",
    "sg:phone":"+49 40/376450",
    "sg:postcode":"22143",
    "sg:province":"Hamburg",
    "wof:name":"Sw Beteiligungs Gmbh",
    "wof:placetype":"venue"
},
  "geometry": {"coordinates":[10.15162,53.60284],"type":"Point"}
}