{
  "type": "Feature",
  "properties": {
    "iso:country":"DE",
    "sg:address":"Am Alten Markt 13",
    "sg:city":"Bornh\u00f6ved",
    "sg:phone":"+49 4323/6441",
    "sg:postcode":"24619",
    "sg:province":"Schleswig-Holstein",
    "wof:name":"B\u00e4ckerei Renner Gmbh",
    "wof:placetype":"venue"
},
  "geometry": {"coordinates":[10.227235,54.070522],"type":"Point"}
}