{
  "type": "Feature",
  "properties": {
    "iso:country":"DE",
    "sg:address":"Tannenring 128",
    "sg:city":"Wiesbaden",
    "sg:postcode":"65207",
    "sg:province":"Hessen",
    "wof:name":"Team-it Gmbh",
    "wof:placetype":"venue"
},
  "geometry": {"coordinates":[8.3345775604,50.1297798157],"type":"Point"}
}