{
  "type": "Feature",
  "properties": {
    "iso:country":"DE",
    "sg:address":"Schwalbenweg 5",
    "sg:city":"Krailling",
    "sg:phone":"+49 89/8571146",
    "sg:postcode":"82152",
    "sg:province":"Bayern",
    "wof:name":"Gerda Winklhofer Steuerberaterin",
    "wof:placetype":"venue"
},
  "geometry": {"coordinates":[11.4050559998,48.1010513306],"type":"Point"}
}