{
  "type": "Feature",
  "properties": {
    "iso:country":"DE",
    "sg:address":"Viehfeldstr. 27 a",
    "sg:city":"Drensteinfurt",
    "sg:phone":"+49 2508/1603",
    "sg:postcode":"48317",
    "sg:province":"Nordrhein-Westfalen",
    "wof:name":"Andrea Hiller",
    "wof:placetype":"venue"
},
  "geometry": {"coordinates":[7.7346801758,51.7891311646],"type":"Point"}
}