{
  "type": "Feature",
  "properties": {
    "iso:country":"DE",
    "sg:address":"Braubachstr. 10-12",
    "sg:city":"Frankfurt",
    "sg:phone":"+49 69/287733",
    "sg:postcode":"60311",
    "sg:province":"Hessen",
    "wof:name":"Wilhelm M. D\u00f6britz",
    "wof:placetype":"venue"
},
  "geometry": {"coordinates":[8.684276,50.111649],"type":"Point"}
}