{
  "type": "Feature",
  "properties": {
    "iso:country":"DE",
    "sg:address":"Rottersdorf 27",
    "sg:city":"Stephansposching",
    "sg:phone":"+49 9935/386",
    "sg:postcode":"94569",
    "sg:province":"Bayern",
    "wof:name":"Gefl\u00fcgelmast Gmbh",
    "wof:placetype":"venue"
},
  "geometry": {"coordinates":[12.778061,48.797581],"type":"Point"}
}