{
  "type": "Feature",
  "properties": {
    "iso:country":"DE",
    "sg:address":"Karlstr. 5",
    "sg:city":"Ostfildern",
    "sg:phone":"+49 711/4560543",
    "sg:postcode":"73760",
    "sg:province":"Baden-W\u00fcrttemberg",
    "wof:name":"Harald Mergel Rechtsanwalt",
    "wof:placetype":"venue"
},
  "geometry": {"coordinates":[9.2358198166,48.7186317444],"type":"Point"}
}