{
  "type": "Feature",
  "properties": {
    "iso:country":"DE",
    "sg:address":"H\u00fclser Str. 764A",
    "sg:city":"Krefeld",
    "sg:phone":"+49 2151/87990",
    "sg:postcode":"47803",
    "sg:province":"Nordrhein-Westfalen",
    "wof:name":"Mmv Leasing Gmbh",
    "wof:placetype":"venue"
},
  "geometry": {"coordinates":[6.5240149498,51.3601112366],"type":"Point"}
}