{
  "type": "Feature",
  "properties": {
    "iso:country":"DE",
    "sg:address":"Ludwig-Wilhelm-Str. 1",
    "sg:city":"Baden-Baden",
    "sg:phone":"+49 7221/28332",
    "sg:postcode":"76530",
    "sg:province":"Baden-W\u00fcrttemberg",
    "wof:name":"Hans N. G\u00f6tz Rechtsanwalt",
    "wof:placetype":"venue"
},
  "geometry": {"coordinates":[8.24132061,48.756729126],"type":"Point"}
}