{
  "type": "Feature",
  "properties": {
    "iso:country":"DE",
    "sg:address":"Itag-Str. 5-17 POSTFACH 1328",
    "sg:city":"Celle",
    "sg:phone":"+49 4971/633562",
    "sg:postcode":"29203",
    "sg:province":"Niedersachsen",
    "wof:name":"Hermann Zeh",
    "wof:placetype":"venue"
},
  "geometry": {"coordinates":[9.5429296494,48.7096710205],"type":"Point"}
}