{
  "type": "Feature",
  "properties": {
    "iso:country":"DE",
    "sg:address":"Hohwachter Weg 40",
    "sg:city":"Kiel",
    "sg:phone":"+49 431/736881",
    "sg:postcode":"24143",
    "sg:province":"Schleswig-Holstein",
    "wof:name":"Msh-mettenhofer Sanit\u00e4r- Und Heizungsmarkt Gmbh",
    "wof:placetype":"venue"
},
  "geometry": {"coordinates":[10.148166,54.300182],"type":"Point"}
}