{
  "type": "Feature",
  "properties": {
    "iso:country":"DE",
    "sg:address":"Hustedter Weg 4",
    "sg:city":"Celle",
    "sg:phone":"+49 5141/51660",
    "sg:postcode":"29229",
    "sg:province":"Niedersachsen",
    "wof:name":"Tannenl\u00e4ufer Alt- Und Abfallstoffe",
    "wof:placetype":"venue"
},
  "geometry": {"coordinates":[10.057328,52.65715],"type":"Point"}
}