{
  "type": "Feature",
  "properties": {
    "iso:country":"DE",
    "sg:address":"Welchenholzer Str. 7",
    "sg:city":"Wilburgstetten",
    "sg:phone":"+49 9853/627",
    "sg:postcode":"91634",
    "sg:province":"Bayern",
    "wof:name":"Brenner & Haas Kg",
    "wof:placetype":"venue"
},
  "geometry": {"coordinates":[10.3943109512,49.0333938599],"type":"Point"}
}