{
  "type": "Feature",
  "properties": {
    "iso:country":"DE",
    "sg:address":"Badergraben 10",
    "sg:city":"Wurzen",
    "sg:phone":"+49 3425/925852",
    "sg:postcode":"04808",
    "sg:province":"Sachsen",
    "wof:name":"Werner Rost",
    "wof:placetype":"venue"
},
  "geometry": {"coordinates":[12.7367925644,51.3689041138],"type":"Point"}
}