{
  "type": "Feature",
  "properties": {
    "iso:country":"DE",
    "sg:address":"Neustadt 5-9",
    "sg:city":"Gie\u00dfen",
    "sg:phone":"+49 4955/45781",
    "sg:postcode":"35390",
    "sg:province":"Hessen",
    "wof:name":"Edgar Hausmann Gmbh",
    "wof:placetype":"venue"
},
  "geometry": {"coordinates":[9.767669,51.393391],"type":"Point"}
}