{
  "type": "Feature",
  "properties": {
    "iso:country":"DE",
    "sg:address":"Waldfeuchter Str. 247",
    "sg:city":"Heinsberg",
    "sg:phone":"+49 2452/7903",
    "sg:postcode":"52525",
    "sg:province":"Nordrhein-Westfalen",
    "wof:name":"Anita Kretschmann",
    "wof:placetype":"venue"
},
  "geometry": {"coordinates":[6.0694389343,51.0762214661],"type":"Point"}
}