{
  "type": "Feature",
  "properties": {
    "iso:country":"DE",
    "sg:address":"Frankfurter Allee 47",
    "sg:city":"Berlin",
    "sg:phone":"+49 30/42780980",
    "sg:postcode":"10247",
    "sg:province":"Berlin",
    "wof:name":"Peter Eilenstein",
    "wof:placetype":"venue"
},
  "geometry": {"coordinates":[13.4638948441,52.5150222778],"type":"Point"}
}