{
  "type": "Feature",
  "properties": {
    "iso:country":"DE",
    "sg:address":"Ludwigstr. 155",
    "sg:city":"Hanau",
    "sg:phone":"+49 6181/62790",
    "sg:postcode":"63456",
    "sg:province":"Hessen",
    "wof:name":"C. Eckhard Hebamme",
    "wof:placetype":"venue"
},
  "geometry": {"coordinates":[8.914869,50.113918],"type":"Point"}
}