{
  "type": "Feature",
  "properties": {
    "iso:country":"DE",
    "sg:address":"L\u00f6senbacher Landstr. 8",
    "sg:city":"L\u00fcdenscheid",
    "sg:phone":"+49 2351/7273",
    "sg:postcode":"58515",
    "sg:province":"Nordrhein-Westfalen",
    "wof:name":"Battenfeld-elektro- Technik Gmbh",
    "wof:placetype":"venue"
},
  "geometry": {"coordinates":[7.5784,51.213249],"type":"Point"}
}