{
  "type": "Feature",
  "properties": {
    "iso:country":"DE",
    "sg:address":"Oberstr. 2",
    "sg:city":"Girkenroth",
    "sg:phone":"+49 6435/2851",
    "sg:postcode":"56459",
    "sg:province":"Rheinland-Pfalz",
    "wof:name":"Hubert Schlag",
    "wof:placetype":"venue"
},
  "geometry": {"coordinates":[7.970835,50.51976],"type":"Point"}
}