{
  "type": "Feature",
  "properties": {
    "iso:country":"DE",
    "sg:address":"Hauptstr. 58",
    "sg:city":"Ruhpolding",
    "sg:phone":"+49 8663/371",
    "sg:postcode":"83324",
    "sg:province":"Bayern",
    "wof:name":"Raiffeisen-immobilien Gmbh",
    "wof:placetype":"venue"
},
  "geometry": {"coordinates":[12.6480484009,47.7614784241],"type":"Point"}
}