{
  "type": "Feature",
  "properties": {
    "iso:country":"DE",
    "sg:address":"Steinbacher Str. 35",
    "sg:city":"Dresden",
    "sg:postcode":"01157",
    "sg:province":"Sachsen",
    "wof:name":"B & S Wohn- Und Gewerbebau Gmbh",
    "wof:placetype":"venue"
},
  "geometry": {"coordinates":[13.679887,51.052345],"type":"Point"}
}