{
  "type": "Feature",
  "properties": {
    "iso:country":"DE",
    "sg:address":"Obere Str. 12",
    "sg:city":"Reinheim",
    "sg:phone":"+49 6162/4159",
    "sg:postcode":"64354",
    "sg:province":"Hessen",
    "wof:name":"Kurt Renkel",
    "wof:placetype":"venue"
},
  "geometry": {"coordinates":[8.83374,49.83205],"type":"Point"}
}