{
  "type": "Feature",
  "properties": {
    "iso:country":"DE",
    "sg:address":"Im \u00d6kodorf 6",
    "sg:city":"Lilienthal",
    "sg:phone":"+49 4298/467565",
    "sg:postcode":"28865",
    "sg:province":"Niedersachsen",
    "wof:name":"H. Rohde",
    "wof:placetype":"venue"
},
  "geometry": {"coordinates":[8.9158582687,53.1546325684],"type":"Point"}
}