{
  "type": "Feature",
  "properties": {
    "iso:country":"DE",
    "sg:address":"Albert-Schweitzer-Str. 21",
    "sg:city":"Senden",
    "sg:postcode":"89250",
    "sg:province":"Bayern",
    "wof:name":"Fischereiverein Ulm Neu-ulm E. V.",
    "wof:placetype":"venue"
},
  "geometry": {"coordinates":[10.0712842941,48.321849823],"type":"Point"}
}