{
  "type": "Feature",
  "properties": {
    "iso:country":"DE",
    "sg:address":"Ziegelstr. 14",
    "sg:city":"Plettenberg",
    "sg:phone":"+49 2391/10779",
    "sg:postcode":"58840",
    "sg:province":"Nordrhein-Westfalen",
    "wof:name":"Burghard Herbst",
    "wof:placetype":"venue"
},
  "geometry": {"coordinates":[7.871761,51.207134],"type":"Point"}
}