{
  "type": "Feature",
  "properties": {
    "iso:country":"DE",
    "sg:address":"Eisenbacher Weg 1",
    "sg:city":"Rehweiler",
    "sg:phone":"+49 6383/7898",
    "sg:postcode":"66907",
    "sg:province":"Rheinland-Pfalz",
    "wof:name":"Walter Loo\u00df",
    "wof:placetype":"venue"
},
  "geometry": {"coordinates":[7.440169,49.487293],"type":"Point"}
}