{
  "type": "Feature",
  "properties": {
    "iso:country":"DE",
    "sg:address":"Industriestr. 16",
    "sg:city":"M\u00fcnchweiler",
    "sg:phone":"+49 6395/534",
    "sg:postcode":"66981",
    "sg:province":"Rheinland-Pfalz",
    "wof:name":"Dreher Gmbh",
    "wof:placetype":"venue"
},
  "geometry": {"coordinates":[7.6849,49.212204],"type":"Point"}
}