{
  "type": "Feature",
  "properties": {
    "iso:country":"DE",
    "sg:address":"R\u00f6merstr. 70",
    "sg:city":"Gilching",
    "sg:phone":"+49 8105/24260",
    "sg:postcode":"82205",
    "sg:province":"Bayern",
    "wof:name":"Carmen Schlor",
    "wof:placetype":"venue"
},
  "geometry": {"coordinates":[11.2949991226,48.1127052307],"type":"Point"}
}