{
  "type": "Feature",
  "properties": {
    "iso:country":"DE",
    "sg:address":"Hohenlohe Stra\u00dfe 18a",
    "sg:city":"\u00d6hringen",
    "sg:phone":"+49 7941/63876",
    "sg:postcode":"74613",
    "sg:province":"Baden-W\u00fcrttemberg",
    "wof:name":"Manhattan - Die Veranstaltungsagentur",
    "wof:placetype":"venue"
},
  "geometry": {"coordinates":[9.505544,49.20472],"type":"Point"}
}