{
  "type": "Feature",
  "properties": {
    "iso:country":"DE",
    "sg:address":"Querfurter Weg 6",
    "sg:city":"Eggenstein-Leopoldshafen",
    "sg:phone":"+49 721/785051",
    "sg:postcode":"76344",
    "sg:province":"Baden-W\u00fcrttemberg",
    "wof:name":"Joachim M\u00fcller Steuerberater",
    "wof:placetype":"venue"
},
  "geometry": {"coordinates":[8.4035902023,49.0848312378],"type":"Point"}
}