{
  "type": "Feature",
  "properties": {
    "iso:country":"DE",
    "sg:address":"Lortzingstr. 4",
    "sg:city":"Osnabr\u00fcck",
    "sg:postcode":"49074",
    "sg:province":"Niedersachsen",
    "wof:name":"Dirk\u00dfen-h\u00f6ner Outdoorartikel Einzelhandels-",
    "wof:placetype":"venue"
},
  "geometry": {"coordinates":[8.0426149368,52.2763977051],"type":"Point"}
}