{
  "type": "Feature",
  "properties": {
    "iso:country":"DE",
    "sg:address":"B\u00fcrgerm.-Huber-Str. 30",
    "sg:city":"Bruckm\u00fchl",
    "sg:phone":"+49 8062/2875",
    "sg:postcode":"83052",
    "sg:province":"Bayern",
    "wof:name":"Manfred Hoffmann Akustikbau Gmbh",
    "wof:placetype":"venue"
},
  "geometry": {"coordinates":[11.915169,47.882652],"type":"Point"}
}