{
  "type": "Feature",
  "properties": {
    "iso:country":"DE",
    "sg:address":"M\u00fchlbergweg 1",
    "sg:city":"Neustadt",
    "sg:phone":"+49 9602/2208",
    "sg:postcode":"92660",
    "sg:province":"Bayern",
    "wof:name":"P. Winde Steuerberater",
    "wof:placetype":"venue"
},
  "geometry": {"coordinates":[12.167517662,49.7314682007],"type":"Point"}
}