{
  "type": "Feature",
  "properties": {
    "iso:country":"DE",
    "sg:address":"Glinder Weg 77",
    "sg:city":"Moorrege",
    "sg:phone":"+49 4122/82702",
    "sg:postcode":"25436",
    "sg:province":"Schleswig-Holstein",
    "wof:name":"Insha Und Wolfgang Bolt",
    "wof:placetype":"venue"
},
  "geometry": {"coordinates":[9.68097,53.665031],"type":"Point"}
}