{
  "type": "Feature",
  "properties": {
    "iso:country":"DE",
    "sg:address":"Koblenzer Str. 25",
    "sg:city":"Altenkirchen",
    "sg:phone":"+49 2681/3355",
    "sg:postcode":"57610",
    "sg:province":"Rheinland-Pfalz",
    "wof:name":"Institut F\u00fcr Krankengymnastik Und Massage Langenbach Gmbh",
    "wof:placetype":"venue"
},
  "geometry": {"coordinates":[7.64159,50.68272],"type":"Point"}
}