{
  "type": "Feature",
  "properties": {
    "iso:country":"DE",
    "sg:address":"Postweg 11",
    "sg:city":"Teisnach",
    "sg:phone":"+49 9923/1323",
    "sg:postcode":"94244",
    "sg:province":"Bayern",
    "wof:name":"Paul Stadler",
    "wof:placetype":"venue"
},
  "geometry": {"coordinates":[13.0297851562,49.0141944885],"type":"Point"}
}