{
  "type": "Feature",
  "properties": {
    "iso:country":"DE",
    "sg:address":"Sperberweg 27",
    "sg:city":"Villmar",
    "sg:postcode":"65606",
    "sg:province":"Hessen",
    "wof:name":"Ordonez Maler- Meisterbetrieb Gmbh",
    "wof:placetype":"venue"
},
  "geometry": {"coordinates":[8.198249,50.399391],"type":"Point"}
}