{
  "type": "Feature",
  "properties": {
    "iso:country":"DE",
    "sg:address":"Struthstr. 18",
    "sg:city":"Gie\u00dfen",
    "sg:phone":"+49 641/42119",
    "sg:postcode":"35394",
    "sg:province":"Hessen",
    "wof:name":"B. Schmidt",
    "wof:placetype":"venue"
},
  "geometry": {"coordinates":[8.7474727631,50.6005744934],"type":"Point"}
}