{
  "type": "Feature",
  "properties": {
    "iso:country":"DE",
    "sg:address":"Waldstr. 2",
    "sg:city":"L\u00fcbberstorf",
    "sg:phone":"+49 38422/20639",
    "sg:postcode":"23992",
    "sg:province":"Mecklenburg-Vorpommern",
    "wof:name":"H. Mertins",
    "wof:placetype":"venue"
},
  "geometry": {"coordinates":[11.7184085846,53.8613052368],"type":"Point"}
}