{
  "type": "Feature",
  "properties": {
    "iso:country":"DE",
    "sg:address":"Admiral-Rosendahl-Str. 10",
    "sg:city":"Neu-Isenburg",
    "sg:postcode":"63263",
    "sg:province":"Hessen",
    "wof:name":"Carl Geck Gmbh & Co.",
    "wof:placetype":"venue"
},
  "geometry": {"coordinates":[8.6090230942,50.0383071899],"type":"Point"}
}