{
  "type": "Feature",
  "properties": {
    "iso:country":"DE",
    "sg:address":"Waidstr. 7",
    "sg:city":"Bad Sulza",
    "sg:phone":"+49 36461/21640",
    "sg:postcode":"99518",
    "sg:province":"Th\u00fcringen",
    "wof:name":"Christina Benedix",
    "wof:placetype":"venue"
},
  "geometry": {"coordinates":[11.6223697662,51.0867958069],"type":"Point"}
}