{
  "type": "Feature",
  "properties": {
    "iso:country":"DE",
    "sg:address":"Langestr. 127",
    "sg:city":"Bad Driburg",
    "sg:phone":"+49 4952/532036",
    "sg:postcode":"33014",
    "sg:province":"Nordrhein-Westfalen",
    "wof:name":"Commerzbank Ag",
    "wof:placetype":"venue"
},
  "geometry": {"coordinates":[9.02609,51.733616],"type":"Point"}
}