{
  "type": "Feature",
  "properties": {
    "iso:country":"DE",
    "sg:address":"Schmellwitzer Str. 25",
    "sg:city":"Cottbus",
    "sg:phone":"+49 355/871389",
    "sg:postcode":"03044",
    "sg:province":"Brandenburg",
    "wof:name":"A. Neumann",
    "wof:placetype":"venue"
},
  "geometry": {"coordinates":[14.335183,51.778561],"type":"Point"}
}