{
  "type": "Feature",
  "properties": {
    "iso:country":"DE",
    "sg:address":"Ritter-Raschen-Str. 3",
    "sg:city":"Bremen",
    "sg:phone":"+49 421/391127",
    "sg:postcode":"28219",
    "sg:province":"Bremen",
    "wof:name":"Kohl & Co.",
    "wof:placetype":"venue"
},
  "geometry": {"coordinates":[8.781162262,53.1040382385],"type":"Point"}
}