{
  "type": "Feature",
  "properties": {
    "iso:country":"DE",
    "sg:address":"Hauptstr. 196",
    "sg:city":"Weil am Rhein",
    "sg:phone":"+49 7621/76701",
    "sg:postcode":"79576",
    "sg:province":"Baden-W\u00fcrttemberg",
    "wof:name":"Yvonne Heimann",
    "wof:placetype":"venue"
},
  "geometry": {"coordinates":[7.622573,47.593311],"type":"Point"}
}