{
  "type": "Feature",
  "properties": {
    "iso:country":"DE",
    "sg:address":"Schwarzer-Grat-Weg 3-2",
    "sg:city":"Leutkirch",
    "sg:postcode":"88299",
    "sg:province":"Baden-W\u00fcrttemberg",
    "wof:name":"Fleischbearbeitungsbetrieb Der Fleischwirtschaft",
    "wof:placetype":"venue"
},
  "geometry": {"coordinates":[10.0141706467,47.8200073242],"type":"Point"}
}