{
  "type": "Feature",
  "properties": {
    "iso:country":"DE",
    "sg:address":"Ludwig-Wucherer-Str. 13",
    "sg:city":"Halle",
    "sg:phone":"+49 345/219570",
    "sg:postcode":"06108",
    "sg:province":"Sachsen-Anhalt",
    "wof:name":"Dr. Reinhard Reimann & Andere",
    "wof:placetype":"venue"
},
  "geometry": {"coordinates":[11.9739246368,51.4914512634],"type":"Point"}
}