{
  "type": "Feature",
  "properties": {
    "iso:country":"DE",
    "sg:address":"Weinbergstr. 21",
    "sg:city":"Saaldorf-Surheim",
    "sg:postcode":"83416",
    "sg:province":"Bayern",
    "wof:name":"Dr. Erich M\u00fcller Tierarzt",
    "wof:placetype":"venue"
},
  "geometry": {"coordinates":[12.9236097336,47.8509407043],"type":"Point"}
}