{
  "type": "Feature",
  "properties": {
    "iso:country":"DE",
    "sg:address":"H\u00f6fle 2",
    "sg:city":"Ofterdingen",
    "sg:phone":"+49 7473/273841",
    "sg:postcode":"72131",
    "sg:province":"Baden-W\u00fcrttemberg",
    "wof:name":"Martin Sauerbeck E. K.",
    "wof:placetype":"venue"
},
  "geometry": {"coordinates":[9.0341329575,48.42212677],"type":"Point"}
}