{
  "type": "Feature",
  "properties": {
    "iso:country":"DE",
    "sg:address":"Luiter Weg 161",
    "sg:city":"Krefeld",
    "sg:phone":"+49 2151/564777",
    "sg:postcode":"47802",
    "sg:province":"Nordrhein-Westfalen",
    "wof:name":"Peter Nieskens Immobilienmakler",
    "wof:placetype":"venue"
},
  "geometry": {"coordinates":[6.5757708549,51.3836746216],"type":"Point"}
}