{
  "type": "Feature",
  "properties": {
    "iso:country":"DE",
    "sg:address":"Eisenbahnstr. 106",
    "sg:city":"Mutterstadt",
    "sg:phone":"+49 6234/2029",
    "sg:postcode":"67112",
    "sg:province":"Rheinland-Pfalz",
    "wof:name":"Reisert Baubetreuungs-gmbh",
    "wof:placetype":"venue"
},
  "geometry": {"coordinates":[8.3636322021,49.4344100952],"type":"Point"}
}