{
  "type": "Feature",
  "properties": {
    "iso:country":"DE",
    "sg:address":"Neutharder Str. 1",
    "sg:city":"Bruchsal",
    "sg:postcode":"76646",
    "sg:province":"Baden-W\u00fcrttemberg",
    "wof:name":"Hildegard Abele Verwaltungsges. Mbh",
    "wof:placetype":"venue"
},
  "geometry": {"coordinates":[8.529795,49.104904],"type":"Point"}
}