{
  "type": "Feature",
  "properties": {
    "iso:country":"DE",
    "sg:address":"Edisonstr. 3",
    "sg:city":"Dormagen",
    "sg:phone":"+49 2133/77090",
    "sg:postcode":"41542",
    "sg:province":"Nordrhein-Westfalen",
    "wof:name":"Transalkim Internationale Spedition Gmbh",
    "wof:placetype":"venue"
},
  "geometry": {"coordinates":[6.7951750755,51.1335258484],"type":"Point"}
}