{
  "type": "Feature",
  "properties": {
    "iso:country":"DE",
    "sg:address":"Saarstr. 4",
    "sg:city":"Lauf",
    "sg:phone":"+49 9123/75727",
    "sg:postcode":"91207",
    "sg:province":"Bayern",
    "wof:name":"English Pub",
    "wof:placetype":"venue"
},
  "geometry": {"coordinates":[11.2794542313,49.5119285583],"type":"Point"}
}