{
  "type": "Feature",
  "properties": {
    "iso:country":"DE",
    "sg:address":"Friedrichstr. 16",
    "sg:city":"Westerland",
    "sg:phone":"+49 4651/23283",
    "sg:postcode":"25980",
    "sg:province":"Schleswig-Holstein",
    "wof:name":"Lothar Feustel",
    "wof:placetype":"venue"
},
  "geometry": {"coordinates":[8.304086,54.907795],"type":"Point"}
}