{
  "type": "Feature",
  "properties": {
    "iso:country":"DE",
    "sg:address":"Fockestr. 13",
    "sg:city":"Leipzig",
    "sg:phone":"+49 341/3011093",
    "sg:postcode":"04275",
    "sg:province":"Sachsen",
    "wof:name":"Bernd Noack",
    "wof:placetype":"venue"
},
  "geometry": {"coordinates":[12.365715,51.321613],"type":"Point"}
}