{
  "type": "Feature",
  "properties": {
    "iso:country":"DE",
    "sg:address":"Bayreuther Str. 1a",
    "sg:city":"Vilseck",
    "sg:phone":"+49 9662/6025",
    "sg:postcode":"92249",
    "sg:province":"Bayern",
    "wof:name":"A. Str\u00f6ll",
    "wof:placetype":"venue"
},
  "geometry": {"coordinates":[11.7922506332,49.60887146],"type":"Point"}
}