{
  "type": "Feature",
  "properties": {
    "iso:country":"DE",
    "sg:address":"Nordhellenweg 13",
    "sg:city":"Winterberg",
    "sg:phone":"+49 2983/345",
    "sg:postcode":"59955",
    "sg:province":"Nordrhein-Westfalen",
    "wof:name":"Josef Menke",
    "wof:placetype":"venue"
},
  "geometry": {"coordinates":[8.483085,51.233677],"type":"Point"}
}