{
  "type": "Feature",
  "properties": {
    "iso:country":"DE",
    "sg:address":"Wieckhorster Str. 71",
    "sg:city":"Schneverdingen",
    "sg:phone":"+49 5193/1593",
    "sg:postcode":"29640",
    "sg:province":"Niedersachsen",
    "wof:name":"Helmut Vorwerk",
    "wof:placetype":"venue"
},
  "geometry": {"coordinates":[9.791749,53.08147],"type":"Point"}
}