{
  "type": "Feature",
  "properties": {
    "iso:country":"DE",
    "sg:address":"Industriestr. 26 - 28",
    "sg:city":"Greven",
    "sg:phone":"+49 4925/752436",
    "sg:postcode":"48268",
    "sg:province":"Nordrhein-Westfalen",
    "wof:name":"Bleco Apparatebau Gmbh",
    "wof:placetype":"venue"
},
  "geometry": {"coordinates":[7.5530438423,52.1319274902],"type":"Point"}
}