{
  "type": "Feature",
  "properties": {
    "iso:country":"DE",
    "sg:address":"Hindenburgstr. 7",
    "sg:city":"Albertshofen",
    "sg:phone":"+49 9321/31246",
    "sg:postcode":"97320",
    "sg:province":"Bayern",
    "wof:name":"Richard Hofmann",
    "wof:placetype":"venue"
},
  "geometry": {"coordinates":[10.159559,49.771465],"type":"Point"}
}