{
  "type": "Feature",
  "properties": {
    "iso:country":"DE",
    "sg:address":"Untere Schneckenbergstr. 66",
    "sg:city":"Passau",
    "sg:phone":"+49 851/42784",
    "sg:postcode":"94034",
    "sg:province":"Bayern",
    "wof:name":"Franz Koller",
    "wof:placetype":"venue"
},
  "geometry": {"coordinates":[13.493554,48.577148],"type":"Point"}
}