{
  "type": "Feature",
  "properties": {
    "iso:country":"DE",
    "sg:address":"Salzstetter Str. 54",
    "sg:city":"Horb",
    "sg:phone":"+49 7486/1593",
    "sg:postcode":"72160",
    "sg:province":"Baden-W\u00fcrttemberg",
    "wof:name":"Manfred Nafz",
    "wof:placetype":"venue"
},
  "geometry": {"coordinates":[8.6319103241,48.4745292664],"type":"Point"}
}