{
  "type": "Feature",
  "properties": {
    "iso:country":"DE",
    "sg:address":"Sch\u00fctzenhofstr. 113 a",
    "sg:city":"Oldenburg",
    "sg:postcode":"26133",
    "sg:province":"Niedersachsen",
    "wof:name":"Ingbau Ingenieurgesellschaft F\u00fcr Bauplanung Mbh",
    "wof:placetype":"venue"
},
  "geometry": {"coordinates":[8.220685,53.122375],"type":"Point"}
}