{
  "type": "Feature",
  "properties": {
    "iso:country":"DE",
    "sg:address":"Alsheimer Str. 28",
    "sg:city":"Gimbsheim",
    "sg:phone":"+49 6249/6133",
    "sg:postcode":"67578",
    "sg:province":"Rheinland-Pfalz",
    "wof:name":"Tengelmann-markt",
    "wof:placetype":"venue"
},
  "geometry": {"coordinates":[8.3678445816,49.7768974304],"type":"Point"}
}