{
  "type": "Feature",
  "properties": {
    "iso:country":"DE",
    "sg:address":"Franzstr. 21",
    "sg:city":"Bonn",
    "sg:phone":"+49 228/691439",
    "sg:postcode":"53111",
    "sg:province":"Nordrhein-Westfalen",
    "wof:name":"Detlef Nicot Anlageberatung",
    "wof:placetype":"venue"
},
  "geometry": {"coordinates":[7.0918970108,50.7378196716],"type":"Point"}
}