{
  "type": "Feature",
  "properties": {
    "iso:country":"DE",
    "sg:address":"Siemensstr. 19",
    "sg:city":"Bad M\u00fcnstereifel",
    "sg:postcode":"53902",
    "sg:province":"Nordrhein-Westfalen",
    "wof:name":"Frs Fitting-reparatur- Service Gmbh",
    "wof:placetype":"venue"
},
  "geometry": {"coordinates":[6.8027100563,50.598941803],"type":"Point"}
}