{
  "type": "Feature",
  "properties": {
    "iso:country":"DE",
    "sg:address":"Bachstr. 32",
    "sg:city":"Altshausen",
    "sg:phone":"+49 7584/2308",
    "sg:postcode":"88361",
    "sg:province":"Baden-W\u00fcrttemberg",
    "wof:name":"Werner F\u00fcrst",
    "wof:placetype":"venue"
},
  "geometry": {"coordinates":[9.5457897186,47.9314575195],"type":"Point"}
}