{
  "type": "Feature",
  "properties": {
    "iso:country":"DE",
    "sg:address":"Rickerstr. 24",
    "sg:city":"Wagenfeld",
    "sg:phone":"+49 5774/310",
    "sg:postcode":"49419",
    "sg:province":"Niedersachsen",
    "wof:name":"F. Renzelmann",
    "wof:placetype":"venue"
},
  "geometry": {"coordinates":[8.721396,52.523624],"type":"Point"}
}