{
  "type": "Feature",
  "properties": {
    "iso:country":"DE",
    "sg:address":"Baidergasse 11",
    "sg:city":"Rosbach",
    "sg:phone":"+49 6003/3342",
    "sg:postcode":"61191",
    "sg:province":"Hessen",
    "wof:name":"Hannis Weinkontor",
    "wof:placetype":"venue"
},
  "geometry": {"coordinates":[8.6894464493,50.3040313721],"type":"Point"}
}