{
  "type": "Feature",
  "properties": {
    "iso:country":"DE",
    "sg:address":"Koppenstr. 75",
    "sg:city":"Berlin",
    "sg:phone":"+49 30/2964394",
    "sg:postcode":"10243",
    "sg:province":"Berlin",
    "wof:name":"Nowak & Beth Gmbh",
    "wof:placetype":"venue"
},
  "geometry": {"coordinates":[13.4345788956,52.5139274597],"type":"Point"}
}