{
  "type": "Feature",
  "properties": {
    "iso:country":"DE",
    "sg:address":"Eisenbahnstr. 73",
    "sg:city":"Eberswalde",
    "sg:phone":"+49 3334/24267",
    "sg:postcode":"16225",
    "sg:province":"Brandenburg",
    "wof:name":"B. Neuhaus",
    "wof:placetype":"venue"
},
  "geometry": {"coordinates":[13.8062992096,52.8338165283],"type":"Point"}
}