{
  "type": "Feature",
  "properties": {
    "iso:country":"DE",
    "sg:address":"Finkenweg 12",
    "sg:city":"Lingen",
    "sg:phone":"+49 591/65388",
    "sg:postcode":"49808",
    "sg:province":"Niedersachsen",
    "wof:name":"Heinz Kuper",
    "wof:placetype":"venue"
},
  "geometry": {"coordinates":[7.3249750137,52.5382766724],"type":"Point"}
}