{
  "type": "Feature",
  "properties": {
    "iso:country":"DE",
    "sg:address":"Kupferstr. 7",
    "sg:city":"Rheda-Wiedenbr\u00fcck",
    "sg:phone":"+49 5242/902200",
    "sg:postcode":"33378",
    "sg:province":"Nordrhein-Westfalen",
    "wof:name":"Gesicom Gmbh & Co. Kg",
    "wof:placetype":"venue"
},
  "geometry": {"coordinates":[8.35954,51.83263],"type":"Point"}
}