{
  "type": "Feature",
  "properties": {
    "iso:country":"DE",
    "sg:address":"Postfach 17 06",
    "sg:city":"Varel",
    "sg:postcode":"26307",
    "sg:province":"Niedersachsen",
    "wof:name":"Bfo Biofilter- Anlagentechnik Gmbh",
    "wof:placetype":"venue"
},
  "geometry": {"coordinates":[8.13835,53.39782],"type":"Point"}
}