{
  "type": "Feature",
  "properties": {
    "iso:country":"DE",
    "sg:address":"Postfach",
    "sg:city":"Bad Mergentheim",
    "sg:phone":"+49 7931/2310",
    "sg:postcode":"97961",
    "sg:province":"Baden-W\u00fcrttemberg",
    "wof:name":"F. K. Zeiner",
    "wof:placetype":"venue"
},
  "geometry": {"coordinates":[9.77185,49.493328],"type":"Point"}
}