{
  "type": "Feature",
  "properties": {
    "iso:country":"DE",
    "sg:address":"Grundstr. 14",
    "sg:city":"Steinbach b Unkersdorf",
    "sg:phone":"+49 35204/47026",
    "sg:postcode":"01462",
    "wof:name":"G\u00e4rtnereibedarf Sachsen Daniel Olle Kg",
    "wof:placetype":"venue"
},
  "geometry": {"coordinates":[13.5915498734,51.0561790466],"type":"Point"}
}