{
  "type": "Feature",
  "properties": {
    "iso:country":"DE",
    "sg:address":"Kirchstr. 9",
    "sg:city":"Bous",
    "sg:phone":"+49 6834/2300",
    "sg:postcode":"66359",
    "sg:province":"Saarland",
    "wof:name":"Marien-apotheke",
    "wof:placetype":"venue"
},
  "geometry": {"coordinates":[6.796707,49.275543],"type":"Point"}
}