{
  "type": "Feature",
  "properties": {
    "iso:country":"DE",
    "sg:address":"Heinrich-Ehrhardt-Str. 10",
    "sg:city":"Zella-Mehlis",
    "sg:postcode":"98544",
    "sg:province":"Th\u00fcringen",
    "wof:name":"Reise-center Zella-mehlis",
    "wof:placetype":"venue"
},
  "geometry": {"coordinates":[10.6737318039,50.6557807922],"type":"Point"}
}