{
  "type": "Feature",
  "properties": {
    "iso:country":"DE",
    "sg:address":"Jacob-Burckhardt-Str. 5",
    "sg:city":"Grenzach-Wyhlen",
    "sg:phone":"+49 7624/1555",
    "sg:postcode":"79639",
    "sg:province":"Baden-W\u00fcrttemberg",
    "wof:name":"Kismet-choice Modevertrieb Gmbh",
    "wof:placetype":"venue"
},
  "geometry": {"coordinates":[7.661181,47.552147],"type":"Point"}
}