{
  "type": "Feature",
  "properties": {
    "iso:country":"DE",
    "sg:address":"W\u00fcrzburger Str. 197",
    "sg:city":"F\u00fcrth",
    "sg:phone":"+49 911/7592336",
    "sg:postcode":"90766",
    "sg:province":"Bayern",
    "wof:name":"Claudia Wunderling",
    "wof:placetype":"venue"
},
  "geometry": {"coordinates":[10.9564447403,49.4845619202],"type":"Point"}
}