{
  "type": "Feature",
  "properties": {
    "iso:country":"DE",
    "sg:address":"Hauptstr. 43",
    "sg:city":"Gr\u00f6ditz",
    "sg:phone":"+49 35263/60220",
    "sg:postcode":"01609",
    "sg:province":"Sachsen",
    "wof:name":"R. Rauch",
    "wof:placetype":"venue"
},
  "geometry": {"coordinates":[13.4510011673,51.4151191711],"type":"Point"}
}