{
  "type": "Feature",
  "properties": {
    "iso:country":"DE",
    "sg:address":"Harffstr. 43",
    "sg:city":"D\u00fcsseldorf",
    "sg:phone":"+49 211/720076",
    "sg:postcode":"40591",
    "sg:province":"Nordrhein-Westfalen",
    "wof:name":"Innovall Pharma Vertriebs Gmbh & Co. Kg",
    "wof:placetype":"venue"
},
  "geometry": {"coordinates":[6.816336,51.197048],"type":"Point"}
}