{
  "type": "Feature",
  "properties": {
    "iso:country":"DE",
    "sg:address":"Ilmenauer Str. 11",
    "sg:city":"Gr\u00e4fenroda",
    "sg:phone":"+49 36205/76328",
    "sg:postcode":"99330",
    "sg:province":"Th\u00fcringen",
    "wof:name":"Cafe-milchbar Griebel",
    "wof:placetype":"venue"
},
  "geometry": {"coordinates":[10.812662,50.74752],"type":"Point"}
}