{
  "type": "Feature",
  "properties": {
    "iso:country":"DE",
    "sg:address":"Weinstr. 128",
    "sg:city":"Neustadt",
    "sg:phone":"+49 6321/2692",
    "sg:postcode":"67434",
    "sg:province":"Rheinland-Pfalz",
    "wof:name":"Hans Seiberth Weinanbau",
    "wof:placetype":"venue"
},
  "geometry": {"coordinates":[8.1305904388,49.3362236023],"type":"Point"}
}