{
  "type": "Feature",
  "properties": {
    "iso:country":"DE",
    "sg:address":"Blumenkamper Weg 16",
    "sg:city":"Wesel",
    "sg:phone":"+49 281/60220",
    "sg:postcode":"46485",
    "sg:province":"Nordrhein-Westfalen",
    "wof:name":"Verlag Hintermann Gmbh",
    "wof:placetype":"venue"
},
  "geometry": {"coordinates":[6.6155028343,51.6788406372],"type":"Point"}
}