{
  "type": "Feature",
  "properties": {
    "iso:country":"DE",
    "sg:address":"An der Kanzlei 15",
    "sg:city":"Steinbergkirche",
    "sg:phone":"+49 4632/7828",
    "sg:postcode":"24972",
    "sg:province":"Schleswig-Holstein",
    "wof:name":"Gisela Sch\u00f6nleiter",
    "wof:placetype":"venue"
},
  "geometry": {"coordinates":[9.7648382187,54.7585029602],"type":"Point"}
}