{
  "type": "Feature",
  "properties": {
    "iso:country":"DE",
    "sg:address":"Moselweinstr. 22",
    "sg:city":"Valwig",
    "sg:phone":"+49 2671/1767",
    "sg:postcode":"56812",
    "sg:province":"Rheinland-Pfalz",
    "wof:name":"Alois Zenz",
    "wof:placetype":"venue"
},
  "geometry": {"coordinates":[7.2075791359,50.1420593262],"type":"Point"}
}