{
  "type": "Feature",
  "properties": {
    "iso:country":"DE",
    "sg:address":"Tannenstr. 9",
    "sg:city":"K\u00fcrnach",
    "sg:phone":"+49 9367/980741",
    "sg:postcode":"97273",
    "sg:province":"Bayern",
    "wof:name":"Telekommunikations Consulting Volker Grawert",
    "wof:placetype":"venue"
},
  "geometry": {"coordinates":[10.0445241928,49.8491783142],"type":"Point"}
}