{
  "type": "Feature",
  "properties": {
    "iso:country":"DE",
    "sg:address":"Heerweg 54",
    "sg:city":"Karlsbad",
    "sg:phone":"+49 7248/5083",
    "sg:postcode":"76307",
    "sg:province":"Baden-W\u00fcrttemberg",
    "wof:name":"D Und S Funkmietwagen",
    "wof:placetype":"venue"
},
  "geometry": {"coordinates":[8.505734,48.871105],"type":"Point"}
}