{
  "type": "Feature",
  "properties": {
    "iso:country":"DE",
    "sg:address":"Hochwaldstr. 54",
    "sg:city":"Merzig",
    "sg:phone":"+49 6861/5166",
    "sg:postcode":"66663",
    "sg:province":"Saarland",
    "wof:name":"Hawner-2-rad-center",
    "wof:placetype":"venue"
},
  "geometry": {"coordinates":[6.64047,49.442684],"type":"Point"}
}