{
  "type": "Feature",
  "properties": {
    "iso:country":"DE",
    "sg:address":"Hauptstr. 41",
    "sg:city":"Br\u00fchl",
    "sg:phone":"+49 2232/211180",
    "sg:postcode":"50321",
    "sg:province":"Nordrhein-Westfalen",
    "wof:name":"Lengwenat",
    "wof:placetype":"venue"
},
  "geometry": {"coordinates":[6.894698143,50.8442955017],"type":"Point"}
}