{
  "type": "Feature",
  "properties": {
    "iso:country":"DE",
    "sg:address":"Friedhofstr. 42",
    "sg:city":"M\u00fclheim",
    "sg:phone":"+49 208/50672",
    "sg:postcode":"45478",
    "sg:province":"Nordrhein-Westfalen",
    "wof:name":"C. Orzech",
    "wof:placetype":"venue"
},
  "geometry": {"coordinates":[6.8424057961,51.4258766174],"type":"Point"}
}