{
  "type": "Feature",
  "properties": {
    "iso:country":"DE",
    "sg:address":"Uferstr. 14",
    "sg:city":"Kelheim",
    "sg:phone":"+49 9441/7885",
    "sg:postcode":"93309",
    "sg:province":"Bayern",
    "wof:name":"Michael K\u00fcrzl",
    "wof:placetype":"venue"
},
  "geometry": {"coordinates":[11.819605,48.89362],"type":"Point"}
}