{
  "type": "Feature",
  "properties": {
    "iso:country":"DE",
    "sg:address":"Postfach 1367:: 58556 Kierspe:: Germany.^^Friedrich Ebert Str 257/259::",
    "sg:city":"Kierspe",
    "sg:phone":"+49 2359/90690",
    "sg:postcode":"58566",
    "sg:province":"Nordrhein-Westfalen",
    "wof:name":"Volksbank Kierspe Eg",
    "wof:placetype":"venue"
},
  "geometry": {"coordinates":[7.594165,51.12999],"type":"Point"}
}