{
  "type": "Feature",
  "properties": {
    "iso:country":"DE",
    "sg:address":"Ringstr. 24",
    "sg:city":"Coppengrave",
    "sg:phone":"+49 5185/1208",
    "sg:postcode":"31091",
    "sg:province":"Niedersachsen",
    "wof:name":"Horst Hermes",
    "wof:placetype":"venue"
},
  "geometry": {"coordinates":[9.726166,51.985661],"type":"Point"}
}