{
  "type": "Feature",
  "properties": {
    "iso:country":"DE",
    "sg:address":"Pflaumenallee 1",
    "sg:city":"Lubmin",
    "sg:phone":"+49 38354/22949",
    "sg:postcode":"17509",
    "sg:province":"Mecklenburg-Vorpommern",
    "wof:name":"Hanke & Sohn Gmbh",
    "wof:placetype":"venue"
},
  "geometry": {"coordinates":[13.6153011322,54.1318664551],"type":"Point"}
}