{
  "type": "Feature",
  "properties": {
    "iso:country":"DE",
    "sg:address":"Johann-G.-Gutenberg-Str. 19",
    "sg:city":"Olching",
    "sg:postcode":"82140",
    "sg:province":"Bayern",
    "wof:name":"Tierbedarf Peter Plendl",
    "wof:placetype":"venue"
},
  "geometry": {"coordinates":[11.331619,48.197964],"type":"Point"}
}