{
  "type": "Feature",
  "properties": {
    "iso:country":"DE",
    "sg:address":"Alter Lingener Damm 5",
    "sg:city":"Rheine",
    "sg:phone":"+49 5971/82527",
    "sg:postcode":"48429",
    "sg:province":"Nordrhein-Westfalen",
    "wof:name":"Pars 2000 Bahram Kalantar-shahpouri E. K.",
    "wof:placetype":"venue"
},
  "geometry": {"coordinates":[7.44267416,52.2878341675],"type":"Point"}
}