{
  "type": "Feature",
  "properties": {
    "iso:country":"DE",
    "sg:address":"Emser Str. 85",
    "sg:city":"Berlin",
    "sg:postcode":"12051",
    "sg:province":"Berlin",
    "wof:name":"Euro-taxi Etg Gmbh",
    "wof:placetype":"venue"
},
  "geometry": {"coordinates":[13.424439,52.467609],"type":"Point"}
}