{
  "type": "Feature",
  "properties": {
    "iso:country":"DE",
    "sg:address":"Tangstedter Chaussee 1",
    "sg:city":"Rellingen",
    "sg:postcode":"25462",
    "sg:province":"Schleswig-Holstein",
    "wof:name":"Stecar Verwaltungs Gmbh",
    "wof:placetype":"venue"
},
  "geometry": {"coordinates":[9.8295984268,53.6533889771],"type":"Point"}
}