{
  "type": "Feature",
  "properties": {
    "iso:country":"DE",
    "sg:address":"Rittweg 1",
    "sg:city":"Ditzingen",
    "sg:postcode":"71254",
    "sg:province":"Baden-W\u00fcrttemberg",
    "wof:name":"Mobil Baustoffe Gmbh & Co. Kg",
    "wof:placetype":"venue"
},
  "geometry": {"coordinates":[9.004502,48.842102],"type":"Point"}
}