{
  "type": "Feature",
  "properties": {
    "iso:country":"DE",
    "sg:address":"Kurf\u00fcrstenstrasse 20",
    "sg:city":"Wintrich",
    "sg:phone":"+49 6534/8388",
    "sg:postcode":"54487",
    "sg:province":"Rheinland-Pfalz",
    "wof:name":"Moselurlaub Mit Hund",
    "wof:placetype":"venue"
},
  "geometry": {"coordinates":[6.954761982,49.890838623],"type":"Point"}
}