{
  "type": "Feature",
  "properties": {
    "iso:country":"DE",
    "sg:address":"Hauptstr. 60",
    "sg:city":"Bielefeld",
    "sg:phone":"+49 521/443023",
    "sg:postcode":"33647",
    "sg:province":"Nordrhein-Westfalen",
    "wof:name":"Friedrich Humberg",
    "wof:placetype":"venue"
},
  "geometry": {"coordinates":[8.512605,51.989521],"type":"Point"}
}