{
  "type": "Feature",
  "properties": {
    "iso:country":"DE",
    "sg:address":"Mitterhaselbach 4",
    "sg:city":"Mallersdorf-Pfaffenberg",
    "sg:phone":"+49 8772/5401",
    "sg:postcode":"84066",
    "sg:province":"Bayern",
    "wof:name":"Gastst\u00e4tte Anton B\u00fccherl",
    "wof:placetype":"venue"
},
  "geometry": {"coordinates":[12.1748228073,48.7762718201],"type":"Point"}
}