{
  "type": "Feature",
  "properties": {
    "iso:country":"DE",
    "sg:address":"Wellingsb\u00fctteler Landstr. 199",
    "sg:city":"Hamburg",
    "sg:phone":"+49 40/503902",
    "sg:postcode":"22337",
    "sg:province":"Hamburg",
    "wof:name":"Kurt Schmischke",
    "wof:placetype":"venue"
},
  "geometry": {"coordinates":[10.048953,53.634247],"type":"Point"}
}