{
  "type": "Feature",
  "properties": {
    "iso:country":"DE",
    "sg:address":"Heinrich-B\u00f6ll-Str. 3",
    "sg:city":"Bad Bentheim",
    "sg:postcode":"48455",
    "sg:province":"Niedersachsen",
    "wof:name":"Aldi Gmbh & Co. Kg",
    "wof:placetype":"venue"
},
  "geometry": {"coordinates":[7.1684799194,52.3056488037],"type":"Point"}
}