{
  "type": "Feature",
  "properties": {
    "iso:country":"DE",
    "sg:address":"Am Tivoli 3",
    "sg:city":"Aachen",
    "sg:postcode":"52070",
    "sg:province":"Nordrhein-Westfalen",
    "wof:name":"Kloubert Designkonzept",
    "wof:placetype":"venue"
},
  "geometry": {"coordinates":[6.0929389,50.7915077209],"type":"Point"}
}