{
  "type": "Feature",
  "properties": {
    "iso:country":"DE",
    "sg:address":"Industriegebiet 6",
    "sg:city":"Borgentreich",
    "sg:phone":"+49 5645/78070",
    "sg:postcode":"34434",
    "sg:province":"Nordrhein-Westfalen",
    "wof:name":"Koch Transporte & Baustoffe Gmbh & Co. Kg",
    "wof:placetype":"venue"
},
  "geometry": {"coordinates":[9.2395963669,51.6015625],"type":"Point"}
}