{
  "type": "Feature",
  "properties": {
    "iso:country":"DE",
    "sg:address":"Berliner Str. 25",
    "sg:city":"Ravensburg",
    "sg:phone":"+49 751/24556",
    "sg:postcode":"88212",
    "sg:province":"Baden-W\u00fcrttemberg",
    "wof:name":"Dr. Friedrich Knorpp Tierarzt",
    "wof:placetype":"venue"
},
  "geometry": {"coordinates":[9.6244344711,47.7676925659],"type":"Point"}
}