{
  "type": "Feature",
  "properties": {
    "iso:country":"DE",
    "sg:address":"Tunnelhalde 28",
    "sg:city":"Hettingen",
    "sg:phone":"+49 7574/91301",
    "sg:postcode":"72513",
    "sg:province":"Baden-W\u00fcrttemberg",
    "wof:name":"H. Wessner",
    "wof:placetype":"venue"
},
  "geometry": {"coordinates":[9.2333803177,48.2233428955],"type":"Point"}
}