{
  "type": "Feature",
  "properties": {
    "iso:country":"DE",
    "sg:address":"Deutschordenstr. 20",
    "sg:city":"Bad Friedrichshall",
    "sg:phone":"+49 7136/5355",
    "sg:postcode":"74177",
    "sg:province":"Baden-W\u00fcrttemberg",
    "wof:name":"Ihre Textilpflege",
    "wof:placetype":"venue"
},
  "geometry": {"coordinates":[9.192556,49.232792],"type":"Point"}
}