{
  "type": "Feature",
  "properties": {
    "iso:country":"DE",
    "sg:address":"Wedeler Chaussee 113",
    "sg:city":"Moorrege",
    "sg:phone":"+49 4122/83271",
    "sg:postcode":"25436",
    "sg:province":"Schleswig-Holstein",
    "wof:name":"Uwe Olbers",
    "wof:placetype":"venue"
},
  "geometry": {"coordinates":[9.668894,53.660965],"type":"Point"}
}