{
  "type": "Feature",
  "properties": {
    "iso:country":"DE",
    "sg:address":"An der Parthenaue 36",
    "sg:city":"Beucha",
    "sg:postcode":"04824",
    "sg:province":"Sachsen",
    "wof:name":"P. Gey",
    "wof:placetype":"venue"
},
  "geometry": {"coordinates":[12.562126,51.320293],"type":"Point"}
}