{
  "type": "Feature",
  "properties": {
    "iso:country":"DE",
    "sg:address":"St\u00fcckweg 70",
    "sg:city":"Ostseebad Prerow",
    "sg:phone":"+49 38233/447",
    "sg:postcode":"18375",
    "sg:province":"Mecklenburg-Vorpommern",
    "wof:name":"Gerhard Vontra",
    "wof:placetype":"venue"
},
  "geometry": {"coordinates":[12.56659,54.441349],"type":"Point"}
}