{
  "type": "Feature",
  "properties": {
    "iso:country":"DE",
    "sg:address":"Rettchensdorfer Str. 3",
    "sg:city":"Altd\u00f6bern",
    "sg:phone":"+49 35434/237",
    "sg:postcode":"03229",
    "sg:province":"Brandenburg",
    "wof:name":"Merced\u00f6l-feuerungsbau Gmbh",
    "wof:placetype":"venue"
},
  "geometry": {"coordinates":[14.028859,51.666965],"type":"Point"}
}