{
  "type": "Feature",
  "properties": {
    "iso:country":"DE",
    "sg:address":"Rheydter Str. 131a",
    "sg:city":"Grevenbroich",
    "sg:phone":"+49 2181/242666",
    "sg:postcode":"41515",
    "sg:province":"Nordrhein-Westfalen",
    "wof:name":"Mgg Medizinische Gymnastik Grevenbroich Gmbh",
    "wof:placetype":"venue"
},
  "geometry": {"coordinates":[6.57167,51.092072],"type":"Point"}
}