{
  "type": "Feature",
  "properties": {
    "iso:country":"DE",
    "sg:address":"Nassaustr. 26",
    "sg:city":"Hofheim",
    "sg:phone":"+49 6122/4014",
    "sg:postcode":"65719",
    "sg:province":"Hessen",
    "wof:name":"Hille & M\u00fcller Gmbh",
    "wof:placetype":"venue"
},
  "geometry": {"coordinates":[8.385392,50.069695],"type":"Point"}
}