{
  "type": "Feature",
  "properties": {
    "iso:country":"DE",
    "sg:address":"Siemensstr. 7",
    "sg:city":"M\u00f6rfelden-Walldorf",
    "sg:postcode":"64546",
    "sg:province":"Hessen",
    "wof:name":"Fertigungscenter F\u00fcr Elektrische Anlagen",
    "wof:placetype":"venue"
},
  "geometry": {"coordinates":[8.5663042068,49.9656982422],"type":"Point"}
}