{
  "type": "Feature",
  "properties": {
    "iso:country":"DE",
    "sg:address":"An der Seem\u00fchle 15",
    "sg:city":"Wettenberg",
    "sg:phone":"+49 641/982540",
    "sg:postcode":"35435",
    "sg:province":"Hessen",
    "wof:name":"Schleenbecker Gmbh & Co. Kg Gmbh & Co. Kg",
    "wof:placetype":"venue"
},
  "geometry": {"coordinates":[8.64536,50.614658],"type":"Point"}
}