{
  "type": "Feature",
  "properties": {
    "iso:country":"DE",
    "sg:address":"92676",
    "sg:city":"Eschenbach",
    "sg:postcode":"92676",
    "sg:province":"Bayern",
    "wof:name":"Raiffeisenbank Eschenbach-pressath-trabitz Eg",
    "wof:placetype":"venue"
},
  "geometry": {"coordinates":[11.81385,49.776539],"type":"Point"}
}