{
  "type": "Feature",
  "properties": {
    "iso:country":"DE",
    "sg:address":"Huttenheimer Landstr. 2",
    "sg:city":"Graben-Neudorf",
    "sg:phone":"+49 7255/721200",
    "sg:postcode":"76676",
    "sg:province":"Baden-W\u00fcrttemberg",
    "wof:name":"Quattro Natursteine Gmbh",
    "wof:placetype":"venue"
},
  "geometry": {"coordinates":[8.496303,49.173542],"type":"Point"}
}