{
  "type": "Feature",
  "properties": {
    "iso:country":"DE",
    "sg:address":"Neunzigstr. 10",
    "sg:city":"D\u00fcsseldorf",
    "sg:phone":"+49 211/2296060",
    "sg:postcode":"40625",
    "sg:province":"Nordrhein-Westfalen",
    "wof:name":"Brembach Liedgens Und Zmug Rechtsanw\u00e4lte",
    "wof:placetype":"venue"
},
  "geometry": {"coordinates":[6.8599710464,51.2388191223],"type":"Point"}
}