{
  "type": "Feature",
  "properties": {
    "iso:country":"DE",
    "sg:address":"Am Fu\u00dfweg 2",
    "sg:city":"Frankenau",
    "sg:phone":"+49 6455/8705",
    "sg:postcode":"35110",
    "sg:province":"Hessen",
    "wof:name":"Heinrich Berg",
    "wof:placetype":"venue"
},
  "geometry": {"coordinates":[8.900941,51.065361],"type":"Point"}
}