{
  "type": "Feature",
  "properties": {
    "iso:country":"DE",
    "sg:address":"Parcusstr. 1",
    "sg:city":"Mainz",
    "sg:phone":"+49 6131/227655",
    "sg:postcode":"55116",
    "sg:province":"Rheinland-Pfalz",
    "wof:name":"Raugraf Gastst\u00e4tten Gmbh",
    "wof:placetype":"venue"
},
  "geometry": {"coordinates":[8.2605895996,50.0002708435],"type":"Point"}
}