{
  "type": "Feature",
  "properties": {
    "iso:country":"DE",
    "sg:address":"Heinrichstr. 56",
    "sg:city":"Eisenach",
    "sg:phone":"+49 3691/742705",
    "sg:postcode":"99817",
    "sg:province":"Th\u00fcringen",
    "wof:name":"Petersberg-apotheke E. K.",
    "wof:placetype":"venue"
},
  "geometry": {"coordinates":[10.34064,50.979061],"type":"Point"}
}