{
  "type": "Feature",
  "properties": {
    "iso:country":"DE",
    "sg:address":"S\u00fcdberg 111",
    "sg:city":"Ahlen",
    "sg:phone":"+49 2382/60395",
    "sg:postcode":"59229",
    "sg:province":"Nordrhein-Westfalen",
    "wof:name":"Berni Hubbert Heissmangelbetrieb",
    "wof:placetype":"venue"
},
  "geometry": {"coordinates":[7.9073529243,51.7592773438],"type":"Point"}
}