{
  "type": "Feature",
  "properties": {
    "iso:country":"DE",
    "sg:address":"Hertichstr. 34",
    "sg:city":"Leonberg",
    "sg:phone":"+49 7152/76173",
    "sg:postcode":"71229",
    "sg:province":"Baden-W\u00fcrttemberg",
    "wof:name":"Lieb & Pieper Rationa Werkzeuge",
    "wof:placetype":"venue"
},
  "geometry": {"coordinates":[9.003091,48.786636],"type":"Point"}
}