{
  "type": "Feature",
  "properties": {
    "iso:country":"DE",
    "sg:address":"Willy-R\u00fcsch-Str. 11",
    "sg:city":"Kernen",
    "sg:phone":"+49 7151/949310",
    "sg:postcode":"71394",
    "sg:province":"Baden-W\u00fcrttemberg",
    "wof:name":"Omnibus-schlienz Reiseb\u00fcro Gmbh & Co. Kg",
    "wof:placetype":"venue"
},
  "geometry": {"coordinates":[9.3142671585,48.8143920898],"type":"Point"}
}