{
  "type": "Feature",
  "properties": {
    "iso:country":"DE",
    "sg:address":"Dalbergstr. 11",
    "sg:city":"Eichenzell",
    "sg:phone":"+49 6659/919310",
    "sg:postcode":"36124",
    "sg:province":"Hessen",
    "wof:name":"Cs Cad Cam Systeme Gmbh",
    "wof:placetype":"venue"
},
  "geometry": {"coordinates":[9.7034816742,50.4973754883],"type":"Point"}
}