{
  "type": "Feature",
  "properties": {
    "iso:country":"DE",
    "sg:address":"Kirchenstr. 40",
    "sg:city":"Hamburg",
    "sg:phone":"+49 40/3894252",
    "sg:postcode":"22767",
    "sg:province":"Hamburg",
    "wof:name":"Ev. Pfarramt St. Trinitatis Altona",
    "wof:placetype":"venue"
},
  "geometry": {"coordinates":[9.9500055313,53.5484695435],"type":"Point"}
}