{
  "type": "Feature",
  "properties": {
    "iso:country":"DE",
    "sg:address":"Oberer Neuer Weg 64",
    "sg:city":"Obernburg",
    "sg:phone":"+49 6022/72588",
    "sg:postcode":"63785",
    "sg:province":"Bayern",
    "wof:name":"Klaus Fischer",
    "wof:placetype":"venue"
},
  "geometry": {"coordinates":[9.134913,49.843582],"type":"Point"}
}