{
  "type": "Feature",
  "properties": {
    "iso:country":"DE",
    "sg:address":"R\u00fcckertstr. 8",
    "sg:city":"Heidenheim",
    "sg:phone":"+49 7321/941730",
    "sg:postcode":"89518",
    "sg:province":"Baden-W\u00fcrttemberg",
    "wof:name":"Eugen Prietz Architekt",
    "wof:placetype":"venue"
},
  "geometry": {"coordinates":[10.140414,48.681145],"type":"Point"}
}