{
  "type": "Feature",
  "properties": {
    "iso:country":"DE",
    "sg:address":"Lindenstr. 19",
    "sg:city":"Leipzig",
    "sg:phone":"+49 341/4222545",
    "sg:postcode":"04158",
    "sg:province":"Sachsen",
    "wof:name":"Henning Graviat",
    "wof:placetype":"venue"
},
  "geometry": {"coordinates":[12.341365,51.401016],"type":"Point"}
}