{
  "type": "Feature",
  "properties": {
    "iso:country":"DE",
    "sg:address":"J\u00e4gerwirth",
    "sg:city":"F\u00fcrstenzell",
    "sg:phone":"+49 8502/3000",
    "sg:postcode":"94081",
    "sg:province":"Bayern",
    "wof:name":"Elisabeth Voggenreiter Heilpraktiker",
    "wof:placetype":"venue"
},
  "geometry": {"coordinates":[13.3015050888,48.5523986816],"type":"Point"}
}