{
  "type": "Feature",
  "properties": {
    "iso:country":"DE",
    "sg:address":"Alst\u00e4tter Friedhofstr. 8",
    "sg:city":"Ahaus",
    "sg:phone":"+49 2567/214",
    "sg:postcode":"48683",
    "sg:province":"Nordrhein-Westfalen",
    "wof:name":"Theodor Perick",
    "wof:placetype":"venue"
},
  "geometry": {"coordinates":[6.912281,52.128845],"type":"Point"}
}