{
  "type": "Feature",
  "properties": {
    "iso:country":"DE",
    "sg:address":"Herzbachweg 21",
    "sg:city":"Gelnhausen",
    "sg:phone":"+49 6051/92140",
    "sg:postcode":"63571",
    "sg:province":"Hessen",
    "wof:name":"Michael Rack Architekt",
    "wof:placetype":"venue"
},
  "geometry": {"coordinates":[9.18091,50.205784],"type":"Point"}
}