{
  "type": "Feature",
  "properties": {
    "iso:country":"DE",
    "sg:address":"Tr\u00fcmpelberg 16",
    "sg:city":"Querfurt",
    "sg:phone":"+49 34771/24475",
    "sg:postcode":"06268",
    "sg:province":"Sachsen-Anhalt",
    "wof:name":"Hans-j\u00fcrgen Liebau",
    "wof:placetype":"venue"
},
  "geometry": {"coordinates":[11.534617424,51.375705719],"type":"Point"}
}