{
  "type": "Feature",
  "properties": {
    "iso:country":"DE",
    "sg:address":"Kirchstr. 5",
    "sg:city":"D\u00fcrbheim",
    "sg:phone":"+49 7424/3434",
    "sg:postcode":"78589",
    "sg:province":"Baden-W\u00fcrttemberg",
    "wof:name":"Gastst\u00e4tte Bierhalle",
    "wof:placetype":"venue"
},
  "geometry": {"coordinates":[8.7924919128,48.0578079224],"type":"Point"}
}