{
  "type": "Feature",
  "properties": {
    "iso:country":"DE",
    "sg:address":"Winterburger Str. 39",
    "sg:city":"Bockenau",
    "sg:phone":"+49 6758/6656",
    "sg:postcode":"55595",
    "sg:province":"Rheinland-Pfalz",
    "wof:name":"Richard Und Ursula Dockendorff",
    "wof:placetype":"venue"
},
  "geometry": {"coordinates":[7.6750822067,49.837146759],"type":"Point"}
}