{
  "type": "Feature",
  "properties": {
    "iso:country":"DE",
    "sg:address":"Fliederweg 12",
    "sg:city":"Schw\u00e4bisch Hall",
    "sg:phone":"+49 791/932300",
    "sg:postcode":"74523",
    "sg:province":"Baden-W\u00fcrttemberg",
    "wof:name":"Udo Illig",
    "wof:placetype":"venue"
},
  "geometry": {"coordinates":[9.751789093,49.1312446594],"type":"Point"}
}