{
  "type": "Feature",
  "properties": {
    "iso:country":"DE",
    "sg:address":"Am Wirthsfeld 29",
    "sg:city":"Aitrach",
    "sg:phone":"+49 7565/5100",
    "sg:postcode":"88319",
    "sg:province":"Baden-W\u00fcrttemberg",
    "wof:name":"Lemmer Verwaltungs Gmbh",
    "wof:placetype":"venue"
},
  "geometry": {"coordinates":[10.106719,47.935822],"type":"Point"}
}