{
  "type": "Feature",
  "properties": {
    "iso:country":"DE",
    "sg:address":"Kalkstr. 2",
    "sg:city":"Leverkusen",
    "sg:phone":"+49 214/76969",
    "sg:postcode":"51377",
    "sg:province":"Nordrhein-Westfalen",
    "wof:name":"Alt Manfort",
    "wof:placetype":"venue"
},
  "geometry": {"coordinates":[7.0268602371,51.0276107788],"type":"Point"}
}