{
  "type": "Feature",
  "properties": {
    "iso:country":"DE",
    "sg:address":"Hauptstr. 61",
    "sg:city":"Warburg",
    "sg:phone":"+49 5641/8753",
    "sg:postcode":"34414",
    "sg:province":"Nordrhein-Westfalen",
    "wof:name":"Paul Kohlschein Drogerie",
    "wof:placetype":"venue"
},
  "geometry": {"coordinates":[9.147475,51.488895],"type":"Point"}
}