{
  "type": "Feature",
  "properties": {
    "iso:country":"DE",
    "sg:address":"Oberj\u00e4gerweg 16a",
    "sg:city":"Benediktbeuern",
    "sg:phone":"+49 8857/1380",
    "sg:postcode":"83671",
    "sg:province":"Bayern",
    "wof:name":"Lydia Danner",
    "wof:placetype":"venue"
},
  "geometry": {"coordinates":[11.420088,47.707176],"type":"Point"}
}