{
  "type": "Feature",
  "properties": {
    "iso:country":"DE",
    "sg:address":"Mozartstr. 5",
    "sg:city":"Kempten",
    "sg:phone":"+49 831/521380",
    "sg:postcode":"87435",
    "sg:province":"Bayern",
    "wof:name":"Dr. Erwin-maximilian H\u00f6rmann Steuerberater",
    "wof:placetype":"venue"
},
  "geometry": {"coordinates":[10.3125810623,47.7215385437],"type":"Point"}
}