{
  "type": "Feature",
  "properties": {
    "iso:country":"DE",
    "sg:address":"Ringstr. 28",
    "sg:city":"Walld\u00fcrn",
    "sg:phone":"+49 6282/7460",
    "sg:postcode":"74731",
    "sg:province":"Baden-W\u00fcrttemberg",
    "wof:name":"Hilmar Heidinger Architekt",
    "wof:placetype":"venue"
},
  "geometry": {"coordinates":[9.359989,49.579239],"type":"Point"}
}