{
  "type": "Feature",
  "properties": {
    "iso:country":"DE",
    "sg:address":"Kirchhalde 10",
    "sg:city":"T\u00fcbingen",
    "sg:phone":"+49 7073/7550",
    "sg:postcode":"72070",
    "sg:province":"Baden-W\u00fcrttemberg",
    "wof:name":"Isinger Dorfmuseum-alte Kelter",
    "wof:placetype":"venue"
},
  "geometry": {"coordinates":[8.977802,48.527283],"type":"Point"}
}