{
  "type": "Feature",
  "properties": {
    "iso:country":"DE",
    "sg:address":"Niedernstr. 33",
    "sg:city":"Stadthagen",
    "sg:phone":"+49 5721/75739",
    "sg:postcode":"31655",
    "sg:province":"Niedersachsen",
    "wof:name":"Fleischerei G\u00fcnther Gmbh",
    "wof:placetype":"venue"
},
  "geometry": {"coordinates":[9.2055082321,52.3258781433],"type":"Point"}
}