{
  "type": "Feature",
  "properties": {
    "iso:country":"DE",
    "sg:address":"Neu-Ulmer Str. 15",
    "sg:city":"Meiningen",
    "sg:phone":"+49 3693/502711",
    "sg:postcode":"98617",
    "sg:province":"Th\u00fcringen",
    "wof:name":"Druckerei Wehry-druck Inh. Pia Roll",
    "wof:placetype":"venue"
},
  "geometry": {"coordinates":[10.418777,50.567657],"type":"Point"}
}