{
  "type": "Feature",
  "properties": {
    "iso:country":"DE",
    "sg:address":"H\u00f6henweg 35",
    "sg:city":"Wilhelmsfeld",
    "sg:phone":"+49 4962/207017",
    "sg:postcode":"69259",
    "sg:province":"Baden-W\u00fcrttemberg",
    "wof:name":"Besta-technik F\u00dcrchromatographie Gmbh",
    "wof:placetype":"venue"
},
  "geometry": {"coordinates":[8.7594413757,49.4770851135],"type":"Point"}
}