{
  "type": "Feature",
  "properties": {
    "iso:country":"DE",
    "sg:address":"Dominikanerstr. 4",
    "sg:city":"Halberstadt",
    "sg:phone":"+49 3941/447197",
    "sg:postcode":"38820",
    "sg:province":"Sachsen-Anhalt",
    "wof:name":"Dominikanerklause",
    "wof:placetype":"venue"
},
  "geometry": {"coordinates":[11.0486974716,51.8980369568],"type":"Point"}
}