{
  "type": "Feature",
  "properties": {
    "iso:country":"DE",
    "sg:address":"Dachsenbergstr. 23",
    "sg:city":"Weil",
    "sg:phone":"+49 8193/8016",
    "sg:postcode":"86947",
    "sg:province":"Bayern",
    "wof:name":"Dr. Hanna Jakob Tier\u00e4rztin",
    "wof:placetype":"venue"
},
  "geometry": {"coordinates":[10.9838209152,48.1068725586],"type":"Point"}
}