{
  "type": "Feature",
  "properties": {
    "iso:country":"DE",
    "sg:address":"Im Strickmann 202",
    "sg:city":"Gottmadingen",
    "sg:phone":"+49 7731/976611",
    "sg:postcode":"78244",
    "sg:province":"Baden-W\u00fcrttemberg",
    "wof:name":"M. Patulea",
    "wof:placetype":"venue"
},
  "geometry": {"coordinates":[8.7771654129,47.7349853516],"type":"Point"}
}