{
  "type": "Feature",
  "properties": {
    "iso:country":"DE",
    "sg:address":"L\u00fcneburger Str. 34",
    "sg:city":"Bremerhaven",
    "sg:phone":"+49 471/73627",
    "sg:postcode":"27572",
    "sg:province":"Bremen",
    "wof:name":"Georg S\u00f6hl",
    "wof:placetype":"venue"
},
  "geometry": {"coordinates":[8.599035,53.508419],"type":"Point"}
}