{
  "type": "Feature",
  "properties": {
    "iso:country":"DE",
    "sg:address":"Leonhardsberg 6",
    "sg:city":"Augsburg",
    "sg:phone":"+49 821/502100",
    "sg:postcode":"86150",
    "sg:province":"Bayern",
    "wof:name":"Alshut-steuerberatungs Gmbh",
    "wof:placetype":"venue"
},
  "geometry": {"coordinates":[10.8985900879,48.3704833984],"type":"Point"}
}