{
  "type": "Feature",
  "properties": {
    "iso:country":"DE",
    "sg:address":"Butenwall 31",
    "sg:city":"Borken",
    "sg:phone":"+49 2861/8194",
    "sg:postcode":"46325",
    "sg:province":"Nordrhein-Westfalen",
    "wof:name":"Kn\u00fcsting",
    "wof:placetype":"venue"
},
  "geometry": {"coordinates":[6.8556551933,51.8427658081],"type":"Point"}
}