{
  "type": "Feature",
  "properties": {
    "iso:country":"DE",
    "sg:address":"Stephansrieder Str. 7",
    "sg:city":"Ottobeuren",
    "sg:phone":"+49 8332/7039",
    "sg:postcode":"87724",
    "sg:province":"Bayern",
    "wof:name":"Bay Wa Ag",
    "wof:placetype":"venue"
},
  "geometry": {"coordinates":[10.309378,47.946087],"type":"Point"}
}