{
  "type": "Feature",
  "properties": {
    "iso:country":"DE",
    "sg:address":"Lerchenstr. 23",
    "sg:city":"Altensteig",
    "sg:phone":"+49 7453/91116",
    "sg:postcode":"72213",
    "sg:province":"Baden-W\u00fcrttemberg",
    "wof:name":"Gisela K\u00f6nig Steuerberater",
    "wof:placetype":"venue"
},
  "geometry": {"coordinates":[8.6062812805,48.5892753601],"type":"Point"}
}