{
  "type": "Feature",
  "properties": {
    "iso:country":"DE",
    "sg:address":"Heedfelder Str. 18",
    "sg:city":"L\u00fcdenscheid",
    "sg:phone":"+49 2351/22035",
    "sg:postcode":"58509",
    "sg:province":"Nordrhein-Westfalen",
    "wof:name":"B\u00f6hler Ag",
    "wof:placetype":"venue"
},
  "geometry": {"coordinates":[7.620364,51.222736],"type":"Point"}
}