{
  "type": "Feature",
  "properties": {
    "iso:country":"DE",
    "sg:address":"Franz-Beer-Str. 1",
    "sg:city":"Weingarten",
    "sg:phone":"+49 751/41285",
    "sg:postcode":"88250",
    "sg:province":"Baden-W\u00fcrttemberg",
    "wof:name":"Erich Segelbacher",
    "wof:placetype":"venue"
},
  "geometry": {"coordinates":[9.630028,47.803158],"type":"Point"}
}