{
  "type": "Feature",
  "properties": {
    "iso:country":"DE",
    "sg:address":"Am H\u00fcgel 9",
    "sg:city":"Carlsberg",
    "sg:phone":"+49 6356/1619",
    "sg:postcode":"67316",
    "sg:province":"Rheinland-Pfalz",
    "wof:name":"Rainer Sch\u00f6n",
    "wof:placetype":"venue"
},
  "geometry": {"coordinates":[8.0436286926,49.5042152405],"type":"Point"}
}