{
  "type": "Feature",
  "properties": {
    "iso:country":"DE",
    "sg:address":"Stra\u00dfburger Str. 303",
    "sg:city":"Oberhausen",
    "sg:phone":"+49 208/8830708",
    "sg:postcode":"46045",
    "sg:province":"Nordrhein-Westfalen",
    "wof:name":"Henze Bedachungs- Gesellschaft Mbh",
    "wof:placetype":"venue"
},
  "geometry": {"coordinates":[6.866319,51.463154],"type":"Point"}
}