{
  "type": "Feature",
  "properties": {
    "iso:country":"DE",
    "sg:address":"Wagnerstr. 2",
    "sg:city":"Kronau",
    "sg:phone":"+49 7253/3753",
    "sg:postcode":"76709",
    "sg:province":"Baden-W\u00fcrttemberg",
    "wof:name":"Helmut Opluschtil Masseur",
    "wof:placetype":"venue"
},
  "geometry": {"coordinates":[8.626577,49.222504],"type":"Point"}
}