{
  "type": "Feature",
  "properties": {
    "iso:country":"DE",
    "sg:address":"Oberm\u00fchlstr. 38",
    "sg:city":"Offenbach",
    "sg:phone":"+49 69/891774",
    "sg:postcode":"63073",
    "sg:province":"Hessen",
    "wof:name":"Hartmut Titt",
    "wof:placetype":"venue"
},
  "geometry": {"coordinates":[8.806975,50.084599],"type":"Point"}
}