{
  "type": "Feature",
  "properties": {
    "iso:country":"DE",
    "sg:address":"Bahnhofstr. 1",
    "sg:city":"Thum",
    "sg:phone":"+49 37297/2361",
    "sg:postcode":"09419",
    "sg:province":"Sachsen",
    "wof:name":"Vettermann Bau- Verwaltungs-gmbh",
    "wof:placetype":"venue"
},
  "geometry": {"coordinates":[12.9512844086,50.6689758301],"type":"Point"}
}