{
  "type": "Feature",
  "properties": {
    "iso:country":"DE",
    "sg:address":"Bahnhofstr. 6",
    "sg:city":"Neukirchen",
    "sg:phone":"+49 371/2607124",
    "sg:postcode":"09221",
    "sg:province":"Sachsen",
    "wof:name":"Hans-eberhard K\u00f6hler",
    "wof:placetype":"venue"
},
  "geometry": {"coordinates":[12.8816814423,50.7722625732],"type":"Point"}
}