{
  "type": "Feature",
  "properties": {
    "iso:country":"DE",
    "sg:address":"Talstr. 4",
    "sg:city":"Dautphetal",
    "sg:phone":"+49 4964/6891300",
    "sg:postcode":"35232",
    "sg:province":"Hessen",
    "wof:name":"Tecoplast Gmbh",
    "wof:placetype":"venue"
},
  "geometry": {"coordinates":[8.5311326981,50.8155593872],"type":"Point"}
}