{
  "type": "Feature",
  "properties": {
    "iso:country":"DE",
    "sg:address":"R\u00fcsternweg 5",
    "sg:city":"Magdeburg",
    "sg:postcode":"39120",
    "sg:province":"Sachsen-Anhalt",
    "wof:name":"Ute Bodsch",
    "wof:placetype":"venue"
},
  "geometry": {"coordinates":[11.623971,52.092884],"type":"Point"}
}