{
  "type": "Feature",
  "properties": {
    "iso:country":"DE",
    "sg:address":"Unterer Markt 2",
    "sg:city":"K\u00f6nigstein",
    "sg:phone":"+49 9665/953444",
    "sg:postcode":"92281",
    "sg:province":"Bayern",
    "wof:name":"Angies Inn",
    "wof:placetype":"venue"
},
  "geometry": {"coordinates":[11.6336145401,49.6072616577],"type":"Point"}
}