{
  "type": "Feature",
  "properties": {
    "iso:country":"DE",
    "sg:address":"Manhagener Allee 3",
    "sg:city":"Ahrensburg",
    "sg:phone":"+49 4102/50890",
    "sg:postcode":"22926",
    "sg:province":"Schleswig-Holstein",
    "wof:name":"Parf\u00fcmerie Douglas Nord Gmbh & Co. Kg",
    "wof:placetype":"venue"
},
  "geometry": {"coordinates":[10.24,53.672634],"type":"Point"}
}