{
  "type": "Feature",
  "properties": {
    "iso:country":"DE",
    "sg:address":"Gro\u00dfhecken 41b",
    "sg:city":"R\u00f6srath",
    "sg:postcode":"51503",
    "sg:province":"Nordrhein-Westfalen",
    "wof:name":"Malerwerkst\u00e4tten Lenz Gmbh",
    "wof:placetype":"venue"
},
  "geometry": {"coordinates":[7.21835,50.89854],"type":"Point"}
}