{
  "type": "Feature",
  "properties": {
    "iso:country":"DE",
    "sg:address":"Ollenhauerstr. 76",
    "sg:city":"Berlin",
    "sg:phone":"+49 30/34651627",
    "sg:postcode":"13403",
    "sg:province":"Berlin",
    "wof:name":"Mag-zimmerei Gmbh",
    "wof:placetype":"venue"
},
  "geometry": {"coordinates":[13.3323030472,52.5771903992],"type":"Point"}
}