{
  "type": "Feature",
  "properties": {
    "iso:country":"DE",
    "sg:address":"Heidenheimer Str. 17",
    "sg:city":"Leonberg",
    "sg:phone":"+49 7152/76147",
    "sg:postcode":"71229",
    "sg:province":"Baden-W\u00fcrttemberg",
    "wof:name":"Tilly Naturholzplatten Vertriebs Gmbh",
    "wof:placetype":"venue"
},
  "geometry": {"coordinates":[8.997181,48.794273],"type":"Point"}
}