{
  "type": "Feature",
  "properties": {
    "iso:country":"DE",
    "sg:address":"Siemensstr. 4",
    "sg:city":"Essen",
    "sg:phone":"+49 201/620097",
    "sg:postcode":"45143",
    "sg:province":"Nordrhein-Westfalen",
    "wof:name":"Hans Enders Inhaberin Helga Sch\u00fcrhoff",
    "wof:placetype":"venue"
},
  "geometry": {"coordinates":[6.9748101234,51.4612312317],"type":"Point"}
}