{
  "type": "Feature",
  "properties": {
    "iso:country":"DE",
    "sg:address":"Am Stumpf 9",
    "sg:city":"Wermelskirchen",
    "sg:phone":"+49 2193/531448",
    "sg:postcode":"42929",
    "sg:province":"Nordrhein-Westfalen",
    "wof:name":"Frische Fb",
    "wof:placetype":"venue"
},
  "geometry": {"coordinates":[7.216222,51.101643],"type":"Point"}
}