{
  "type": "Feature",
  "properties": {
    "iso:country":"DE",
    "sg:address":"Zeppelinstr. 139",
    "sg:city":"Heidelberg",
    "sg:postcode":"69121",
    "sg:province":"Baden-W\u00fcrttemberg",
    "wof:name":"Obs-dv Gmbh",
    "wof:placetype":"venue"
},
  "geometry": {"coordinates":[8.6813592911,49.4269828796],"type":"Point"}
}