{
  "type": "Feature",
  "properties": {
    "iso:country":"DE",
    "sg:address":"M\u00fcnchgrabenstr. 33",
    "sg:city":"Lambsheim",
    "sg:phone":"+49 6233/50538",
    "sg:postcode":"67245",
    "sg:province":"Rheinland-Pfalz",
    "wof:name":"Josef Reuter",
    "wof:placetype":"venue"
},
  "geometry": {"coordinates":[8.291321,49.517513],"type":"Point"}
}