{
  "type": "Feature",
  "properties": {
    "iso:country":"DE",
    "sg:address":"Muggenhoferstr. 172",
    "sg:city":"N\u00fcrnberg",
    "sg:phone":"+49 911/939045",
    "sg:postcode":"90429",
    "sg:province":"Bayern",
    "wof:name":"Mikron Gmbh",
    "wof:placetype":"venue"
},
  "geometry": {"coordinates":[11.025954,49.462364],"type":"Point"}
}