{
  "type": "Feature",
  "properties": {
    "iso:country":"DE",
    "sg:address":"Backhausfeld 5",
    "sg:city":"Ratingen",
    "sg:phone":"+49 2102/870701",
    "sg:postcode":"40878",
    "sg:province":"Nordrhein-Westfalen",
    "wof:name":"Klaus Brandenstein Steuerberater",
    "wof:placetype":"venue"
},
  "geometry": {"coordinates":[6.8564100266,51.3004264832],"type":"Point"}
}