{
  "type": "Feature",
  "properties": {
    "iso:country":"DE",
    "sg:address":"Silberbergstr. 4",
    "sg:city":"Uelzen",
    "sg:phone":"+49 5804/388",
    "sg:postcode":"29525",
    "sg:province":"Niedersachsen",
    "wof:name":"Werner P\u00fcffel",
    "wof:placetype":"venue"
},
  "geometry": {"coordinates":[10.670931,52.954292],"type":"Point"}
}