{
  "type": "Feature",
  "properties": {
    "iso:country":"DE",
    "sg:address":"Im W\u00f6rtel 41",
    "sg:city":"Mannheim",
    "sg:phone":"+49 621/8544073",
    "sg:postcode":"68199",
    "sg:province":"Baden-W\u00fcrttemberg",
    "wof:name":"Pso Partner F\u00fcr Software Und Organisation",
    "wof:placetype":"venue"
},
  "geometry": {"coordinates":[8.4829111099,49.4520721436],"type":"Point"}
}