{
  "type": "Feature",
  "properties": {
    "iso:country":"DE",
    "sg:address":"Vo\u00dfbarg 65c",
    "sg:city":"Rastede",
    "sg:postcode":"26180",
    "sg:province":"Niedersachsen",
    "wof:name":"Procos Immobilien Gmbh",
    "wof:placetype":"venue"
},
  "geometry": {"coordinates":[8.1815929413,53.2394371033],"type":"Point"}
}