{
  "type": "Feature",
  "properties": {
    "iso:country":"DE",
    "sg:address":"Marktweg 6",
    "sg:city":"Fa\u00dfberg",
    "sg:phone":"+49 5055/8280",
    "sg:postcode":"29328",
    "sg:province":"Niedersachsen",
    "wof:name":"C. Roelofs",
    "wof:placetype":"venue"
},
  "geometry": {"coordinates":[10.1711750031,52.9011039734],"type":"Point"}
}