{
  "type": "Feature",
  "properties": {
    "iso:country":"DE",
    "sg:address":"W\u00fclferoder Str. 38",
    "sg:city":"Hannover",
    "sg:phone":"+49 511/9525995",
    "sg:postcode":"30539",
    "sg:province":"Niedersachsen",
    "wof:name":"Vgh Lutz Michell &",
    "wof:placetype":"venue"
},
  "geometry": {"coordinates":[9.8336439133,52.3379592896],"type":"Point"}
}