{
  "type": "Feature",
  "properties": {
    "iso:country":"DE",
    "sg:address":"Wengertweg 10",
    "sg:city":"G\u00e4rtringen",
    "sg:phone":"+49 7034/992055",
    "sg:postcode":"71116",
    "sg:province":"Baden-W\u00fcrttemberg",
    "wof:name":"E. Blomberg",
    "wof:placetype":"venue"
},
  "geometry": {"coordinates":[8.928228,48.62524],"type":"Point"}
}