{
  "type": "Feature",
  "properties": {
    "iso:country":"DE",
    "sg:address":"Am Bockholt 15",
    "sg:city":"Warstein",
    "sg:phone":"+49 2925/4024",
    "sg:postcode":"59581",
    "sg:province":"Nordrhein-Westfalen",
    "wof:name":"Wolfgang Rusche",
    "wof:placetype":"venue"
},
  "geometry": {"coordinates":[8.259733,51.476494],"type":"Point"}
}