{
  "type": "Feature",
  "properties": {
    "iso:country":"DE",
    "sg:address":"Am Wattenmeer 2",
    "sg:city":"Esens",
    "sg:phone":"+49 4971/4024",
    "sg:postcode":"26427",
    "sg:province":"Niedersachsen",
    "wof:name":"Hotel-pension Nordkap Heinz Und Mena Toben",
    "wof:placetype":"venue"
},
  "geometry": {"coordinates":[7.5807142258,53.6755981445],"type":"Point"}
}