{
  "type": "Feature",
  "properties": {
    "iso:country":"DE",
    "sg:address":"Pohligstra\u00dfe 1",
    "sg:city":"K\u00f6ln",
    "sg:phone":"+49 221/4705369",
    "sg:postcode":"50969",
    "sg:province":"Nordrhein-Westfalen",
    "wof:name":"Qfd Institut Deutschland E. V.",
    "wof:placetype":"venue"
},
  "geometry": {"coordinates":[6.941006,50.917019],"type":"Point"}
}