{
  "type": "Feature",
  "properties": {
    "iso:country":"DE",
    "sg:address":"Belvederer Allee 57a",
    "sg:city":"Weimar",
    "sg:phone":"+49 3643/59938",
    "sg:postcode":"99425",
    "sg:province":"Th\u00fcringen",
    "wof:name":"T. Kneisz",
    "wof:placetype":"venue"
},
  "geometry": {"coordinates":[11.342565,50.958862],"type":"Point"}
}