{
  "type": "Feature",
  "properties": {
    "iso:country":"DE",
    "sg:address":"Barbarastr. 35",
    "sg:city":"Langenfeld",
    "sg:phone":"+49 2173/13101",
    "sg:postcode":"40764",
    "sg:province":"Nordrhein-Westfalen",
    "wof:name":"Werner Nikutowski",
    "wof:placetype":"venue"
},
  "geometry": {"coordinates":[6.972485,51.085617],"type":"Point"}
}