{
  "type": "Feature",
  "properties": {
    "iso:country":"DE",
    "sg:address":"Heesfeld 1",
    "sg:city":"Braunschweig",
    "sg:postcode":"38112",
    "sg:province":"Niedersachsen",
    "wof:name":"Geodienste Gmbh",
    "wof:placetype":"venue"
},
  "geometry": {"coordinates":[10.481332,52.308762],"type":"Point"}
}