{
  "type": "Feature",
  "properties": {
    "iso:country":"DE",
    "sg:address":"Am Wald 48",
    "sg:city":"Gro\u00dfenbrode",
    "sg:phone":"+49 4367/996941",
    "sg:postcode":"23775",
    "sg:province":"Schleswig-Holstein",
    "wof:name":"J\u00f6rg Stehr",
    "wof:placetype":"venue"
},
  "geometry": {"coordinates":[11.0832118988,54.3614730835],"type":"Point"}
}