{
  "type": "Feature",
  "properties": {
    "iso:country":"DE",
    "sg:address":"Appenzeller Str. 2",
    "sg:city":"M\u00fcnchen",
    "sg:postcode":"81475",
    "sg:province":"Bayern",
    "wof:name":"Kath. \u00d6ffentliche Bibliothek St. Matthias",
    "wof:placetype":"venue"
},
  "geometry": {"coordinates":[11.478538,48.090363],"type":"Point"}
}