{
  "type": "Feature",
  "properties": {
    "iso:country":"DE",
    "sg:address":"Jahnstr. 15",
    "sg:city":"Bad Soden",
    "sg:phone":"+49 6196/24804",
    "sg:postcode":"65812",
    "sg:province":"Hessen",
    "wof:name":"G. Baumg\u00e4rtner",
    "wof:placetype":"venue"
},
  "geometry": {"coordinates":[8.508482933,50.1419067383],"type":"Point"}
}