{
  "type": "Feature",
  "properties": {
    "iso:country":"DE",
    "sg:address":"Kleiststr. 15",
    "sg:city":"Solingen",
    "sg:phone":"+49 212/6776660586",
    "sg:postcode":"42699",
    "sg:province":"Nordrhein-Westfalen",
    "wof:name":"Koshorst Malerwerkst\u00e4tten Gmbh",
    "wof:placetype":"venue"
},
  "geometry": {"coordinates":[7.012314,51.152447],"type":"Point"}
}