{
  "type": "Feature",
  "properties": {
    "iso:country":"DE",
    "sg:address":"Am Strand 5",
    "sg:city":"Rangsdorf",
    "sg:phone":"+49 33708/21130",
    "sg:postcode":"15834",
    "sg:province":"Brandenburg",
    "wof:name":"Seesch\u00e4nke",
    "wof:placetype":"venue"
},
  "geometry": {"coordinates":[13.4164323807,52.2902336121],"type":"Point"}
}