{
  "type": "Feature",
  "properties": {
    "iso:country":"DE",
    "sg:address":"Achternstr. 8",
    "sg:city":"Gro\u00dfenkneten",
    "sg:phone":"+49 4487/453",
    "sg:postcode":"26197",
    "sg:province":"Niedersachsen",
    "wof:name":"D\u00f6hler Bauernstuben",
    "wof:placetype":"venue"
},
  "geometry": {"coordinates":[8.2573699951,52.9665718079],"type":"Point"}
}