{
  "type": "Feature",
  "properties": {
    "iso:country":"DE",
    "sg:address":"Deisterstr. 85",
    "sg:city":"Hannover",
    "sg:phone":"+49 511/21978101",
    "sg:postcode":"30449",
    "sg:province":"Niedersachsen",
    "wof:name":"Arbeiterwohlfahrt Jugend- U. Sozialdienste Ggmbh",
    "wof:placetype":"venue"
},
  "geometry": {"coordinates":[9.715171814,52.3614578247],"type":"Point"}
}