{
  "type": "Feature",
  "properties": {
    "iso:country":"DE",
    "sg:address":"Alexanderstr. 30",
    "sg:city":"F\u00fcrth",
    "sg:phone":"+49 911/740500",
    "sg:postcode":"90762",
    "sg:province":"Bayern",
    "wof:name":"Sozialberatungsstelle Caritasverband",
    "wof:placetype":"venue"
},
  "geometry": {"coordinates":[10.991627,49.47401],"type":"Point"}
}