{
  "type": "Feature",
  "properties": {
    "iso:country":"DE",
    "sg:address":"Untere Papierm\u00fchle 1",
    "sg:city":"Wiesentheid",
    "sg:phone":"+49 9325/99971",
    "sg:postcode":"97353",
    "sg:province":"Bayern",
    "wof:name":"Selbstbau-service Haberkamm Kg",
    "wof:placetype":"venue"
},
  "geometry": {"coordinates":[10.299208,49.788021],"type":"Point"}
}