{
  "type": "Feature",
  "properties": {
    "iso:country":"DE",
    "sg:address":"Beethovenstr. 17",
    "sg:city":"Ottobrunn",
    "sg:phone":"+49 89/6090758",
    "sg:postcode":"85521",
    "sg:province":"Bayern",
    "wof:name":"W. Und R. Henning",
    "wof:placetype":"venue"
},
  "geometry": {"coordinates":[11.6676502228,48.0657920837],"type":"Point"}
}