{
  "type": "Feature",
  "properties": {
    "iso:country":"DE",
    "sg:address":"Ostendstr. 198",
    "sg:city":"N\u00fcrnberg",
    "sg:phone":"+49 911/5460774",
    "sg:postcode":"90482",
    "sg:province":"Bayern",
    "wof:name":"Iris-apotheke Inh. Ruth Hoffmann",
    "wof:placetype":"venue"
},
  "geometry": {"coordinates":[11.127499,49.458321],"type":"Point"}
}