{
  "type": "Feature",
  "properties": {
    "iso:country":"DE",
    "sg:address":"Sparnecker Str. 7",
    "sg:city":"M\u00fcnchberg",
    "sg:phone":"+49 9251/94770",
    "sg:postcode":"95213",
    "sg:province":"Bayern",
    "wof:name":"B\u00f6hmer Massivhaus Gmbh",
    "wof:placetype":"venue"
},
  "geometry": {"coordinates":[11.791255,50.184307],"type":"Point"}
}