{
  "type": "Feature",
  "properties": {
    "iso:country":"DE",
    "sg:address":"Heubergstr. 9",
    "sg:city":"M\u00fcnchen",
    "sg:postcode":"81825",
    "sg:province":"Bayern",
    "wof:name":"Indonesia Travel Service Lg Fernreisen Und",
    "wof:placetype":"venue"
},
  "geometry": {"coordinates":[11.6427078247,48.1188201904],"type":"Point"}
}