{
  "type": "Feature",
  "properties": {
    "iso:country":"DE",
    "sg:address":"Heinrich-Strunk-Str. 77",
    "sg:city":"Essen",
    "sg:phone":"+49 201/8020",
    "sg:postcode":"45143",
    "sg:province":"Nordrhein-Westfalen",
    "wof:name":"Noweda Eg",
    "wof:placetype":"venue"
},
  "geometry": {"coordinates":[6.9716339111,51.4589080811],"type":"Point"}
}