{
  "type": "Feature",
  "properties": {
    "iso:country":"DE",
    "sg:address":"Friedhofstra\u00dfe 18",
    "sg:city":"Sassenberg",
    "sg:postcode":"48336",
    "sg:province":"Nordrhein-Westfalen",
    "wof:name":"Andreas Abeck Informationstechnik",
    "wof:placetype":"venue"
},
  "geometry": {"coordinates":[8.034231,51.992447],"type":"Point"}
}