{
  "type": "Feature",
  "properties": {
    "iso:country":"DE",
    "sg:address":"Otto-Hahn-Str. 8",
    "sg:city":"Estenfeld",
    "sg:phone":"+49 9305/1626",
    "sg:postcode":"97230",
    "sg:province":"Bayern",
    "wof:name":"Schw\u00f6rer Haus Gmbh & Co. Kg",
    "wof:placetype":"venue"
},
  "geometry": {"coordinates":[10.011926,49.836033],"type":"Point"}
}