{
  "type": "Feature",
  "properties": {
    "iso:country":"DE",
    "sg:address":"Kreuzgasse 3",
    "sg:city":"Kelheim",
    "sg:phone":"+49 9441/3450",
    "sg:postcode":"93309",
    "sg:province":"Bayern",
    "wof:name":"Kath. Pfarramt Hl. Kreuz",
    "wof:placetype":"venue"
},
  "geometry": {"coordinates":[11.8931522369,48.9060821533],"type":"Point"}
}