{
  "type": "Feature",
  "properties": {
    "iso:country":"DE",
    "sg:address":"Haardt 13",
    "sg:city":"R\u00f6hrsdorf",
    "sg:phone":"+49 3722/621100",
    "sg:postcode":"09247",
    "sg:province":"Sachsen",
    "wof:name":"Smk R\u00f6hrsdorf Gmbh",
    "wof:placetype":"venue"
},
  "geometry": {"coordinates":[12.836716,50.862991],"type":"Point"}
}