{
  "type": "Feature",
  "properties": {
    "iso:country":"DE",
    "sg:address":"Klaus-Groth-Str. 10",
    "sg:city":"Bad Bevensen",
    "sg:phone":"+49 5821/1250",
    "sg:postcode":"29549",
    "sg:province":"Niedersachsen",
    "wof:name":"Hans-walter Ohnesorge",
    "wof:placetype":"venue"
},
  "geometry": {"coordinates":[10.5663528442,53.0817108154],"type":"Point"}
}