{
  "type": "Feature",
  "properties": {
    "iso:country":"DE",
    "sg:address":"Heideweg 1a",
    "sg:city":"Hagen",
    "sg:phone":"+49 4746/725795",
    "sg:postcode":"27628",
    "sg:province":"Niedersachsen",
    "wof:name":"Dachdeckerei Thomas Schumacher Gmbh",
    "wof:placetype":"venue"
},
  "geometry": {"coordinates":[8.630194,53.354473],"type":"Point"}
}