{
  "type": "Feature",
  "properties": {
    "iso:country":"DE",
    "sg:address":"Im Feldchen 2a",
    "sg:city":"Nidderau",
    "sg:phone":"+49 6187/26024",
    "sg:postcode":"61130",
    "sg:province":"Hessen",
    "wof:name":"J. Garcia",
    "wof:placetype":"venue"
},
  "geometry": {"coordinates":[8.87427,50.22102],"type":"Point"}
}