{
  "type": "Feature",
  "properties": {
    "iso:country":"DE",
    "sg:address":"Ladestr. 9",
    "sg:city":"Burbach",
    "sg:phone":"+49 2736/6188",
    "sg:postcode":"57299",
    "sg:province":"Nordrhein-Westfalen",
    "wof:name":"Wolfgang M\u00fcller Spedition E.k.",
    "wof:placetype":"venue"
},
  "geometry": {"coordinates":[8.0784692764,50.7492141724],"type":"Point"}
}