{
  "type": "Feature",
  "properties": {
    "iso:country":"DE",
    "sg:address":"Am Birnbaum 15",
    "sg:city":"Wiesbaden",
    "sg:phone":"+49 611/547147",
    "sg:postcode":"65191",
    "sg:province":"Hessen",
    "wof:name":"M. Nagetusch Immobilienmakler",
    "wof:placetype":"venue"
},
  "geometry": {"coordinates":[8.2716617584,50.101600647],"type":"Point"}
}