{
  "type": "Feature",
  "properties": {
    "iso:country":"DE",
    "sg:address":"Franziskusplatz 2/1",
    "sg:city":"Friedrichshafen",
    "sg:postcode":"88045",
    "sg:province":"Baden-W\u00fcrttemberg",
    "wof:name":"Karl Peterka Architekt",
    "wof:placetype":"venue"
},
  "geometry": {"coordinates":[9.474625,47.654045],"type":"Point"}
}