{
  "type": "Feature",
  "properties": {
    "iso:country":"DE",
    "sg:address":"Frankfurter Str. 25",
    "sg:city":"Gro\u00df-Gerau",
    "sg:phone":"+49 6152/40692",
    "sg:postcode":"64521",
    "sg:province":"Hessen",
    "wof:name":"Tratoria Roma",
    "wof:placetype":"venue"
},
  "geometry": {"coordinates":[8.4820995331,49.9228210449],"type":"Point"}
}