{
  "type": "Feature",
  "properties": {
    "iso:country":"DE",
    "sg:address":"Marienstr. 69",
    "sg:city":"Neuss",
    "sg:postcode":"41462",
    "sg:province":"Nordrhein-Westfalen",
    "wof:name":"Buchholz Wohnungsbau Gmbh",
    "wof:placetype":"venue"
},
  "geometry": {"coordinates":[6.6755,51.204079],"type":"Point"}
}