{
  "type": "Feature",
  "properties": {
    "iso:country":"DE",
    "sg:address":"Kraglinger Str. 14 a",
    "sg:city":"Stephanskirchen",
    "sg:phone":"+49 8036/4470",
    "sg:postcode":"83071",
    "sg:province":"Bayern",
    "wof:name":"Inter - Tec Gmbh",
    "wof:placetype":"venue"
},
  "geometry": {"coordinates":[12.160866,47.863392],"type":"Point"}
}