{
  "type": "Feature",
  "properties": {
    "iso:country":"DE",
    "sg:address":"Seilerstr. 1",
    "sg:city":"Baden-Baden",
    "sg:phone":"+49 7221/23480",
    "sg:postcode":"76530",
    "sg:province":"Baden-W\u00fcrttemberg",
    "wof:name":"Pizzeria Da Pietro",
    "wof:placetype":"venue"
},
  "geometry": {"coordinates":[8.2413415909,48.7585144043],"type":"Point"}
}