{
  "type": "Feature",
  "properties": {
    "iso:country":"DE",
    "sg:address":"Corveystr. 20",
    "sg:city":"Hamburg",
    "sg:phone":"+49 40/495908",
    "sg:postcode":"22529",
    "sg:province":"Hamburg",
    "wof:name":"Jens Henners Sanit\u00e4rtechnik Gmbh",
    "wof:placetype":"venue"
},
  "geometry": {"coordinates":[9.96926,53.597748],"type":"Point"}
}