{
  "type": "Feature",
  "properties": {
    "iso:country":"DE",
    "sg:address":"Brunnenaue 12",
    "sg:city":"Kenz-K\u00fcstrow",
    "sg:postcode":"18314",
    "sg:province":"Mecklenburg-Vorpommern",
    "wof:name":"Ev. Kirche",
    "wof:placetype":"venue"
},
  "geometry": {"coordinates":[12.7355499268,54.3258590698],"type":"Point"}
}