{
  "type": "Feature",
  "properties": {
    "iso:country":"DE",
    "sg:address":"Dresdner Str. 1",
    "sg:city":"Germering",
    "sg:phone":"+49 89/8403741",
    "sg:postcode":"82110",
    "sg:province":"Bayern",
    "wof:name":"Dehner Gmbh & Co. Kg",
    "wof:placetype":"venue"
},
  "geometry": {"coordinates":[11.373253,48.138241],"type":"Point"}
}