{
  "type": "Feature",
  "properties": {
    "iso:country":"DE",
    "sg:address":"Eichenstr. 45",
    "sg:city":"Wittlich",
    "sg:phone":"+49 6571/90250",
    "sg:postcode":"54516",
    "sg:province":"Rheinland-Pfalz",
    "wof:name":"L. Max Und Reihsner",
    "wof:placetype":"venue"
},
  "geometry": {"coordinates":[6.9474720955,50.0004043579],"type":"Point"}
}