{
  "type": "Feature",
  "properties": {
    "iso:country":"DE",
    "sg:address":"Eichenstr. 3",
    "sg:city":"Neustetten",
    "sg:phone":"+49 7457/1775",
    "sg:postcode":"72149",
    "sg:province":"Baden-W\u00fcrttemberg",
    "wof:name":"Krone",
    "wof:placetype":"venue"
},
  "geometry": {"coordinates":[8.8453817368,48.4879341125],"type":"Point"}
}