{
  "type": "Feature",
  "properties": {
    "iso:country":"DE",
    "sg:address":"Dingolfinger Str. 1",
    "sg:city":"Moosthenning",
    "sg:phone":"+49 8731/91828",
    "sg:postcode":"84164",
    "sg:province":"Bayern",
    "wof:name":"Gasthaus Wasserburger",
    "wof:placetype":"venue"
},
  "geometry": {"coordinates":[12.4958114624,48.6766052246],"type":"Point"}
}