{
  "type": "Feature",
  "properties": {
    "iso:country":"DE",
    "sg:address":"G\u00fcnther-Wagner-Allee 17",
    "sg:city":"Hannover",
    "sg:phone":"+49 511/816033",
    "sg:postcode":"30177",
    "sg:province":"Niedersachsen",
    "wof:name":"Csc Ploenzke Consulting Gmbh",
    "wof:placetype":"venue"
},
  "geometry": {"coordinates":[9.7688617706,52.3985290527],"type":"Point"}
}