{
  "type": "Feature",
  "properties": {
    "iso:country":"DE",
    "sg:address":"Walderbacher Str. 15",
    "sg:city":"Roding",
    "sg:phone":"+49 9468/207",
    "sg:postcode":"93426",
    "sg:province":"Bayern",
    "wof:name":"Katholisches Pfarramt Sieben Schmerzen Mariens",
    "wof:placetype":"venue"
},
  "geometry": {"coordinates":[12.517121315,49.1955566406],"type":"Point"}
}