{
  "type": "Feature",
  "properties": {
    "iso:country":"DE",
    "sg:address":"Kirchstr. 38",
    "sg:city":"Lorch",
    "sg:phone":"+49 7172/8135",
    "sg:postcode":"73547",
    "sg:province":"Baden-W\u00fcrttemberg",
    "wof:name":"Karl Kr\u00f6ner Tanzschule",
    "wof:placetype":"venue"
},
  "geometry": {"coordinates":[9.6884918213,48.7978248596],"type":"Point"}
}