{
  "type": "Feature",
  "properties": {
    "iso:country":"DE",
    "sg:address":"Schmallenberger Str. 9",
    "sg:city":"Lennestadt",
    "sg:phone":"+49 2723/8989",
    "sg:postcode":"57368",
    "sg:province":"Nordrhein-Westfalen",
    "wof:name":"Martin Tillmann",
    "wof:placetype":"venue"
},
  "geometry": {"coordinates":[8.098009,51.111485],"type":"Point"}
}