{
  "type": "Feature",
  "properties": {
    "iso:country":"DE",
    "sg:address":"Hindenburgstr. 54 a",
    "sg:city":"Bremen",
    "sg:phone":"+49 421/693490",
    "sg:postcode":"28717",
    "sg:province":"Bremen",
    "wof:name":"Rolf-dieter Geffken Steuerberater",
    "wof:placetype":"venue"
},
  "geometry": {"coordinates":[8.68679142,53.1700592041],"type":"Point"}
}