{
  "type": "Feature",
  "properties": {
    "iso:country":"DE",
    "sg:address":"Tannenstr. 48",
    "sg:city":"Kreuzwertheim",
    "sg:phone":"+49 9342/92890",
    "sg:postcode":"97892",
    "sg:province":"Bayern",
    "wof:name":"G & T Fun Gastronomiebetriebe Beteiligungs Gmbh",
    "wof:placetype":"venue"
},
  "geometry": {"coordinates":[9.5369300842,49.7731208801],"type":"Point"}
}