{
  "type": "Feature",
  "properties": {
    "iso:country":"DE",
    "sg:address":"Klotenstra\u00dfe 9",
    "sg:city":"Issum Sevelen",
    "sg:phone":"+49 2842/41069",
    "sg:postcode":"47661",
    "sg:province":"Nordrhein-Westfalen",
    "wof:name":"Handgearbeitetes Flaschen-regal",
    "wof:placetype":"venue"
},
  "geometry": {"coordinates":[6.473903,51.482822],"type":"Point"}
}