{
  "type": "Feature",
  "properties": {
    "iso:country":"DE",
    "sg:address":"Werkstr. 14a",
    "sg:city":"Hameln",
    "sg:postcode":"31789",
    "sg:province":"Niedersachsen",
    "wof:name":"M. Deppe Gmbh",
    "wof:placetype":"venue"
},
  "geometry": {"coordinates":[9.331041,52.076382],"type":"Point"}
}