{
  "type": "Feature",
  "properties": {
    "iso:country":"DE",
    "sg:address":"Im Wingert 5",
    "sg:city":"Ruppichteroth",
    "sg:postcode":"53809",
    "sg:province":"Nordrhein-Westfalen",
    "wof:name":"Ispm Sport- Promotion Und Management Gmbh",
    "wof:placetype":"venue"
},
  "geometry": {"coordinates":[7.4854660034,50.8443641663],"type":"Point"}
}