{
  "type": "Feature",
  "properties": {
    "iso:country":"DE",
    "sg:address":"Heidegrundweg 92",
    "sg:city":"Bielefeld",
    "sg:phone":"+49 5205/98060",
    "sg:postcode":"33689",
    "sg:province":"Nordrhein-Westfalen",
    "wof:name":"Christoph Rasche-sch\u00fcrmann Architekt",
    "wof:placetype":"venue"
},
  "geometry": {"coordinates":[8.556995,51.937344],"type":"Point"}
}