{
  "type": "Feature",
  "properties": {
    "iso:country":"DE",
    "sg:address":"Am Alten Markt 10",
    "sg:city":"Bornh\u00f6ved",
    "sg:phone":"+49 4323/6292",
    "sg:postcode":"24619",
    "sg:province":"Schleswig-Holstein",
    "wof:name":"G. Hahne",
    "wof:placetype":"venue"
},
  "geometry": {"coordinates":[10.227265,54.070015],"type":"Point"}
}