{
  "type": "Feature",
  "properties": {
    "iso:country":"DE",
    "sg:address":"Hauptstr. 35",
    "sg:city":"Annweiler",
    "sg:phone":"+49 6346/929000",
    "sg:postcode":"76855",
    "sg:province":"Rheinland-Pfalz",
    "wof:name":"Nkd Vertriebsges. Mbh",
    "wof:placetype":"venue"
},
  "geometry": {"coordinates":[7.963385,49.202618],"type":"Point"}
}