{
  "type": "Feature",
  "properties": {
    "iso:country":"DE",
    "sg:address":"L\u00fcttiserbrook 5",
    "sg:city":"Hamburg",
    "sg:phone":"+49 40/876391",
    "sg:postcode":"22589",
    "sg:province":"Hamburg",
    "wof:name":"Hardo Heuer Gmbh",
    "wof:placetype":"venue"
},
  "geometry": {"coordinates":[9.816421,53.578197],"type":"Point"}
}