{
  "type": "Feature",
  "properties": {
    "iso:country":"DE",
    "sg:address":"An der M\u00fchle 6",
    "sg:city":"Greifswald",
    "sg:phone":"+49 3834/840093",
    "sg:postcode":"17493",
    "sg:province":"Mecklenburg-Vorpommern",
    "wof:name":"Gasthaus Zur Wiecker Br\u00fccke",
    "wof:placetype":"venue"
},
  "geometry": {"coordinates":[13.4477348328,54.0926704407],"type":"Point"}
}