{
  "type": "Feature",
  "properties": {
    "iso:country":"DE",
    "sg:address":"Am F\u00e4rberhof 10",
    "sg:city":"Erlangen",
    "sg:phone":"+49 9131/207385",
    "sg:postcode":"91052",
    "sg:province":"Bayern",
    "wof:name":"Evangelisches Siedlungswerk In Bayern Gemeinn\u00fctzige Bau-",
    "wof:placetype":"venue"
},
  "geometry": {"coordinates":[10.9989500046,49.5911750793],"type":"Point"}
}