{
  "type": "Feature",
  "properties": {
    "iso:country":"DE",
    "sg:address":"Pilotystr. 4",
    "sg:city":"M\u00fcnchen",
    "sg:postcode":"80538",
    "sg:province":"Bayern",
    "wof:name":"Mitas Handels Gmbh",
    "wof:placetype":"venue"
},
  "geometry": {"coordinates":[11.583911,48.141861],"type":"Point"}
}