{
  "type": "Feature",
  "properties": {
    "iso:country":"DE",
    "sg:address":"Stollberger Str. 32 a",
    "sg:city":"Jahnsdorf",
    "sg:phone":"+49 3721/3630",
    "sg:postcode":"09387",
    "sg:province":"Sachsen",
    "wof:name":"Dat Pr\u00fcf- Und Sch\u00e4tzungsstelle",
    "wof:placetype":"venue"
},
  "geometry": {"coordinates":[12.842465,50.737293],"type":"Point"}
}