{
  "type": "Feature",
  "properties": {
    "iso:country":"DE",
    "sg:address":"Langgasse 1",
    "sg:city":"Kist",
    "sg:phone":"+49 9306/1304",
    "sg:postcode":"97270",
    "sg:province":"Bayern",
    "wof:name":"Helmut Schmollinger",
    "wof:placetype":"venue"
},
  "geometry": {"coordinates":[9.834949,49.74271],"type":"Point"}
}