{
  "type": "Feature",
  "properties": {
    "iso:country":"DE",
    "sg:address":"Rabenkopfstr. 12",
    "sg:city":"M\u00fcnchen",
    "sg:phone":"+49 89/292929",
    "sg:postcode":"81545",
    "sg:province":"Bayern",
    "wof:name":"Hans Schneckenburger Architekt",
    "wof:placetype":"venue"
},
  "geometry": {"coordinates":[11.548994,48.079952],"type":"Point"}
}