{
  "type": "Feature",
  "properties": {
    "iso:country":"DE",
    "sg:address":"G\u00fcnzburger Str. 2",
    "sg:city":"Gundelfingen",
    "sg:phone":"+49 9073/7371",
    "sg:postcode":"89423",
    "sg:province":"Bayern",
    "wof:name":"Erich Hausmann",
    "wof:placetype":"venue"
},
  "geometry": {"coordinates":[10.365486145,48.5513572693],"type":"Point"}
}