{
  "type": "Feature",
  "properties": {
    "iso:country":"DE",
    "sg:address":"Ober-Roggenstein 1",
    "sg:city":"Roggenstein",
    "sg:postcode":"82223",
    "sg:province":"Bayern",
    "wof:name":"Versuchsstation F\u00fcr Pflanzenproduktion Und",
    "wof:placetype":"venue"
},
  "geometry": {"coordinates":[-104.3104934692,42.1576805115],"type":"Point"}
}