{
  "type": "Feature",
  "properties": {
    "iso:country":"DE",
    "sg:address":"Aumoosstr. 1",
    "sg:city":"Mittelstetten",
    "sg:postcode":"82293",
    "sg:province":"Bayern",
    "wof:name":"Kewo Handels Gmbh",
    "wof:placetype":"venue"
},
  "geometry": {"coordinates":[11.117632,48.264484],"type":"Point"}
}