{
  "type": "Feature",
  "properties": {
    "iso:country":"DE",
    "sg:address":"Gr\u00fcnenbaum 6",
    "sg:city":"Kierspe",
    "sg:postcode":"58566",
    "sg:province":"Nordrhein-Westfalen",
    "wof:name":"G. B. Verwaltungs Gmbh",
    "wof:placetype":"venue"
},
  "geometry": {"coordinates":[7.61906,51.145691],"type":"Point"}
}