{
  "type": "Feature",
  "properties": {
    "iso:country":"DE",
    "sg:address":"Paosostr. 120",
    "sg:city":"M\u00fcnchen",
    "sg:phone":"+49 89/873734",
    "sg:postcode":"81249",
    "sg:province":"Bayern",
    "wof:name":"Deuter Ag",
    "wof:placetype":"venue"
},
  "geometry": {"coordinates":[11.433092,48.137314],"type":"Point"}
}