{
  "type": "Feature",
  "properties": {
    "iso:country":"DE",
    "sg:address":"Katharinenstr. 86-88",
    "sg:city":"Eisenach",
    "sg:phone":"+49 3691/203737",
    "sg:postcode":"99817",
    "sg:province":"Th\u00fcringen",
    "wof:name":"Glock",
    "wof:placetype":"venue"
},
  "geometry": {"coordinates":[10.3090181351,50.9768638611],"type":"Point"}
}