{
  "type": "Feature",
  "properties": {
    "iso:country":"DE",
    "sg:address":"Busestr. 3",
    "sg:city":"Bremen",
    "sg:phone":"+49 421/212592",
    "sg:postcode":"28213",
    "sg:province":"Bremen",
    "wof:name":"Hellmut Rentsch Ingenieur",
    "wof:placetype":"venue"
},
  "geometry": {"coordinates":[8.8357896805,53.0969429016],"type":"Point"}
}