{
  "type": "Feature",
  "properties": {
    "iso:country":"DE",
    "sg:address":"Untere Str. 1",
    "sg:city":"Schorndorf",
    "sg:phone":"+49 7181/3099",
    "sg:postcode":"73614",
    "sg:province":"Baden-W\u00fcrttemberg",
    "wof:name":"Fr\u00f6scher",
    "wof:placetype":"venue"
},
  "geometry": {"coordinates":[9.5559930801,48.7769126892],"type":"Point"}
}