{
  "type": "Feature",
  "properties": {
    "iso:country":"DE",
    "sg:address":"Schulstr. 54",
    "sg:city":"Bernburg",
    "sg:phone":"+49 3471/314090",
    "sg:postcode":"06406",
    "sg:province":"Sachsen-Anhalt",
    "wof:name":"Reinhard Beyer",
    "wof:placetype":"venue"
},
  "geometry": {"coordinates":[11.74893,51.787392],"type":"Point"}
}