{
  "type": "Feature",
  "properties": {
    "iso:country":"DE",
    "sg:address":"Oberbrunnweg 2",
    "sg:city":"Sindelfingen",
    "sg:postcode":"71069",
    "sg:province":"Baden-W\u00fcrttemberg",
    "wof:name":"Tes Technology Und Engineering Service Gmbh",
    "wof:placetype":"venue"
},
  "geometry": {"coordinates":[8.9664211273,48.7179985046],"type":"Point"}
}