{
  "type": "Feature",
  "properties": {
    "iso:country":"DE",
    "sg:address":"Westerdeich 3",
    "sg:city":"Wittmund",
    "sg:phone":"+49 4467/596",
    "sg:postcode":"26409",
    "sg:province":"Niedersachsen",
    "wof:name":"Heiner Spicker",
    "wof:placetype":"venue"
},
  "geometry": {"coordinates":[7.780769,53.642872],"type":"Point"}
}