{
  "type": "Feature",
  "properties": {
    "iso:country":"DE",
    "sg:address":"Schlutuper Kirchstr 13",
    "sg:city":"L\u00fcbeck",
    "sg:phone":"+49 451/690922",
    "sg:postcode":"23568",
    "sg:province":"Schleswig-Holstein",
    "wof:name":"Peter Steffen Gmbh",
    "wof:placetype":"venue"
},
  "geometry": {"coordinates":[10.7997369766,53.8894309998],"type":"Point"}
}