{
  "type": "Feature",
  "properties": {
    "iso:country":"DE",
    "sg:address":"M\u00f6rikeweg 5",
    "sg:city":"Immendingen",
    "sg:phone":"+49 7462/1527",
    "sg:postcode":"78194",
    "sg:province":"Baden-W\u00fcrttemberg",
    "wof:name":"R. Schilling",
    "wof:placetype":"venue"
},
  "geometry": {"coordinates":[8.7291316986,47.9461288452],"type":"Point"}
}