{
  "type": "Feature",
  "properties": {
    "iso:country":"DE",
    "sg:address":"Friedrichstr. 2",
    "sg:city":"Rastatt",
    "sg:phone":"+49 7222/25439",
    "sg:postcode":"76437",
    "sg:province":"Baden-W\u00fcrttemberg",
    "wof:name":"Hans G\u00f6tz",
    "wof:placetype":"venue"
},
  "geometry": {"coordinates":[8.2066316605,48.8530769348],"type":"Point"}
}