{
  "type": "Feature",
  "properties": {
    "iso:country":"DE",
    "sg:address":"Richard-Lehmann-Str. 36",
    "sg:city":"Leipzig",
    "sg:phone":"+49 341/3025518",
    "sg:postcode":"04275",
    "sg:province":"Sachsen",
    "wof:name":"Baugenossenschaft Leipzig",
    "wof:placetype":"venue"
},
  "geometry": {"coordinates":[12.3755893707,51.3146476746],"type":"Point"}
}