{
  "type": "Feature",
  "properties": {
    "iso:country":"DE",
    "sg:address":"Wendenstr. 19",
    "sg:city":"Gro\u00dfbottwar",
    "sg:phone":"+49 7148/923523",
    "sg:postcode":"71723",
    "sg:province":"Baden-W\u00fcrttemberg",
    "wof:name":"Martina Wiedner-elsweier",
    "wof:placetype":"venue"
},
  "geometry": {"coordinates":[9.292282,49.005226],"type":"Point"}
}