{
  "type": "Feature",
  "properties": {
    "iso:country":"DE",
    "sg:address":"Wolfratshauser Str. 288",
    "sg:city":"M\u00fcnchen",
    "sg:phone":"+49 89/798890",
    "sg:postcode":"81479",
    "sg:province":"Bayern",
    "wof:name":"Eckart Pr\u00f6ll Ingenieur",
    "wof:placetype":"venue"
},
  "geometry": {"coordinates":[11.5178976059,48.0699424744],"type":"Point"}
}