{
  "type": "Feature",
  "properties": {
    "iso:country":"DE",
    "sg:address":"Marktstr. 17",
    "sg:city":"Essen",
    "sg:phone":"+49 201/674545",
    "sg:postcode":"45355",
    "sg:province":"Nordrhein-Westfalen",
    "wof:name":"Liliput",
    "wof:placetype":"venue"
},
  "geometry": {"coordinates":[6.9500861168,51.4734840393],"type":"Point"}
}