{
  "type": "Feature",
  "properties": {
    "iso:country":"DE",
    "sg:address":"Neu-Ulmer Str. 24",
    "sg:city":"Meiningen",
    "sg:phone":"+49 3693/471355",
    "sg:postcode":"98617",
    "sg:province":"Th\u00fcringen",
    "wof:name":"Walter Rellig Ingenieur",
    "wof:placetype":"venue"
},
  "geometry": {"coordinates":[10.4167375565,50.5650291443],"type":"Point"}
}