{
  "type": "Feature",
  "properties": {
    "iso:country":"DE",
    "sg:address":"Am Alten Bahnhof 17",
    "sg:city":"H\u00fcckelhoven",
    "sg:phone":"+49 2435/948094",
    "sg:postcode":"41836",
    "sg:province":"Nordrhein-Westfalen",
    "wof:name":"Versicherungsb\u00fcro Michael Cremer E. K.",
    "wof:placetype":"venue"
},
  "geometry": {"coordinates":[6.2850999832,51.0373382568],"type":"Point"}
}