{
  "type": "Feature",
  "properties": {
    "iso:country":"DE",
    "sg:address":"L\u00fcttringhauser Str. 155",
    "sg:city":"Remscheid",
    "sg:phone":"+49 2191/51552",
    "sg:postcode":"42899",
    "sg:province":"Nordrhein-Westfalen",
    "wof:name":"Ad. Fr. Baack Autozubeh\u00f6r",
    "wof:placetype":"venue"
},
  "geometry": {"coordinates":[7.2453708649,51.2055587769],"type":"Point"}
}