{
  "type": "Feature",
  "properties": {
    "iso:country":"DE",
    "sg:address":"Fabrikstr 1",
    "sg:city":"Nerchau",
    "sg:phone":"+49 37291/20448",
    "sg:postcode":"04685",
    "sg:province":"Sachsen",
    "wof:name":"Metallbau - Wasserkraft Onnen Krieger Gmbh & Co Kg",
    "wof:placetype":"venue"
},
  "geometry": {"coordinates":[13.0752773285,50.7873916626],"type":"Point"}
}