{
  "type": "Feature",
  "properties": {
    "iso:country":"DE",
    "sg:address":"Altk\u00f6nigstr. 50",
    "sg:city":"Oberursel",
    "sg:phone":"+49 6171/3522",
    "sg:postcode":"61440",
    "sg:province":"Hessen",
    "wof:name":"Friedel Kern Architekt Vfa",
    "wof:placetype":"venue"
},
  "geometry": {"coordinates":[8.570161,50.20504],"type":"Point"}
}