{
  "type": "Feature",
  "properties": {
    "iso:country":"DE",
    "sg:address":"Gutenbergstr. 1",
    "sg:city":"Garbsen",
    "sg:postcode":"30823",
    "sg:province":"Niedersachsen",
    "wof:name":"Vgv Kinderland Gmbh",
    "wof:placetype":"venue"
},
  "geometry": {"coordinates":[9.5753936768,52.419216156],"type":"Point"}
}