{
  "type": "Feature",
  "properties": {
    "iso:country":"DE",
    "sg:address":"Daimlerstr. 21",
    "sg:city":"Sch\u00f6naich",
    "sg:phone":"+49 7031/75860",
    "sg:postcode":"71101",
    "sg:province":"Baden-W\u00fcrttemberg",
    "wof:name":"Edwin Ulmer Transporte Gmbh",
    "wof:placetype":"venue"
},
  "geometry": {"coordinates":[9.0693101883,48.6685333252],"type":"Point"}
}