{
  "type": "Feature",
  "properties": {
    "iso:country":"DE",
    "sg:address":"Gertrudenstr. 3",
    "sg:city":"Flensburg",
    "sg:phone":"+49 461/53366",
    "sg:postcode":"24939",
    "sg:province":"Schleswig-Holstein",
    "wof:name":"T. Demsch",
    "wof:placetype":"venue"
},
  "geometry": {"coordinates":[9.4209499359,54.7900047302],"type":"Point"}
}