{
  "type": "Feature",
  "properties": {
    "iso:country":"DE",
    "sg:address":"Adelhardsgasse 4",
    "sg:city":"Adelsdorf",
    "sg:phone":"+49 9195/7949",
    "sg:postcode":"91325",
    "sg:province":"Bayern",
    "wof:name":"Albin M\u00f6nius",
    "wof:placetype":"venue"
},
  "geometry": {"coordinates":[10.895411,49.715134],"type":"Point"}
}