{
  "type": "Feature",
  "properties": {
    "iso:country":"DE",
    "sg:address":"B\u00fcrsteler Str. 12",
    "sg:city":"Ganderkesee",
    "sg:phone":"+49 4222/3353",
    "sg:postcode":"27777",
    "sg:province":"Niedersachsen",
    "wof:name":"Seramo Naturprodukte Gmbh",
    "wof:placetype":"venue"
},
  "geometry": {"coordinates":[8.5100622177,53.0133171082],"type":"Point"}
}