{
  "type": "Feature",
  "properties": {
    "iso:country":"DE",
    "sg:address":"Seibelstr. 4",
    "sg:city":"Gr\u00fcndau",
    "sg:phone":"+49 6051/13301",
    "sg:postcode":"63584",
    "sg:province":"Hessen",
    "wof:name":"A. Boos",
    "wof:placetype":"venue"
},
  "geometry": {"coordinates":[9.1244344711,50.1990814209],"type":"Point"}
}