{
  "type": "Feature",
  "properties": {
    "iso:country":"DE",
    "sg:address":"L\u00fcbsche Str. 18",
    "sg:city":"Wismar",
    "sg:phone":"+49 3841/200060",
    "sg:postcode":"23966",
    "sg:province":"Mecklenburg-Vorpommern",
    "wof:name":"Der Schlauch",
    "wof:placetype":"venue"
},
  "geometry": {"coordinates":[11.4633378983,53.8920402527],"type":"Point"}
}