{
  "type": "Feature",
  "properties": {
    "iso:country":"DE",
    "sg:address":"Gutenbergstr. 4",
    "sg:city":"Sarstedt",
    "sg:phone":"+49 5066/70010",
    "sg:postcode":"31157",
    "sg:province":"Niedersachsen",
    "wof:name":"Baude Gmbh & Co. Kg",
    "wof:placetype":"venue"
},
  "geometry": {"coordinates":[9.8582601547,52.2472076416],"type":"Point"}
}