{
  "type": "Feature",
  "properties": {
    "iso:country":"DE",
    "sg:address":"Auf den Dorfwiesen 1-5",
    "sg:city":"Hillscheid",
    "sg:phone":"+49 2624/20810",
    "sg:postcode":"56204",
    "sg:province":"Rheinland-Pfalz",
    "wof:name":"D & M Rolladentechnik Gmbh",
    "wof:placetype":"venue"
},
  "geometry": {"coordinates":[7.6904759407,50.4132652283],"type":"Point"}
}