{
  "type": "Feature",
  "properties": {
    "iso:country":"DE",
    "sg:address":"Portiastr. 14",
    "sg:city":"M\u00fcnchen",
    "sg:phone":"+49 89/640420",
    "sg:postcode":"81545",
    "sg:province":"Bayern",
    "wof:name":"Joseph Ronel Architekt",
    "wof:placetype":"venue"
},
  "geometry": {"coordinates":[11.562799,48.0882],"type":"Point"}
}