{
  "type": "Feature",
  "properties": {
    "iso:country":"DE",
    "sg:address":"Abelbachstr. 2",
    "sg:city":"B\u00fcren",
    "sg:phone":"+49 2951/2937",
    "sg:postcode":"33142",
    "sg:province":"Nordrhein-Westfalen",
    "wof:name":"Wolfgang K\u00f6nig",
    "wof:placetype":"venue"
},
  "geometry": {"coordinates":[8.51716,51.58757],"type":"Point"}
}