{
  "type": "Feature",
  "properties": {
    "iso:country":"DE",
    "sg:address":"Wallfahrtsweg 57",
    "sg:city":"Cloppenburg",
    "sg:phone":"+49 4471/2564",
    "sg:postcode":"49661",
    "sg:province":"Niedersachsen",
    "wof:name":"Katholisches Pfarramt St. Marien",
    "wof:placetype":"venue"
},
  "geometry": {"coordinates":[8.061044693,52.8638916016],"type":"Point"}
}