{
  "type": "Feature",
  "properties": {
    "iso:country":"DE",
    "sg:address":"Wittgensdorfer Str. 17",
    "sg:city":"Burgst\u00e4dt",
    "sg:phone":"+49 3724/2517",
    "sg:postcode":"09217",
    "sg:province":"Sachsen",
    "wof:name":"U. Pohl",
    "wof:placetype":"venue"
},
  "geometry": {"coordinates":[12.82805,50.888351],"type":"Point"}
}