{
  "type": "Feature",
  "properties": {
    "iso:country":"DE",
    "sg:address":"Martin-Empel-Ring 10",
    "sg:city":"M\u00fcnchen",
    "sg:phone":"+49 89/94500555",
    "sg:postcode":"81829",
    "sg:province":"Bayern",
    "wof:name":"Ogv",
    "wof:placetype":"venue"
},
  "geometry": {"coordinates":[11.681414,48.139591],"type":"Point"}
}