{
  "type": "Feature",
  "properties": {
    "iso:country":"DE",
    "sg:address":"Hochstr. 4",
    "sg:city":"Dornburg",
    "sg:phone":"+49 6436/7403",
    "sg:postcode":"65599",
    "sg:province":"Hessen",
    "wof:name":"Edgar Sturm",
    "wof:placetype":"venue"
},
  "geometry": {"coordinates":[8.0188112259,50.5278015137],"type":"Point"}
}