{
  "type": "Feature",
  "properties": {
    "iso:country":"DE",
    "sg:address":"Williges Worth 3",
    "sg:city":"Wedemark",
    "sg:phone":"+49 5130/40284",
    "sg:postcode":"30900",
    "sg:province":"Niedersachsen",
    "wof:name":"Wilhelm Meyer Jun.",
    "wof:placetype":"venue"
},
  "geometry": {"coordinates":[9.732932,52.545246],"type":"Point"}
}