{
  "type": "Feature",
  "properties": {
    "iso:country":"DE",
    "sg:address":"G\u00fcldenstr. 59",
    "sg:city":"Braunschweig",
    "sg:phone":"+49 531/125753",
    "sg:postcode":"38100",
    "sg:province":"Niedersachsen",
    "wof:name":"M. D\u00f6ring",
    "wof:placetype":"venue"
},
  "geometry": {"coordinates":[10.514341,52.262806],"type":"Point"}
}