{
  "type": "Feature",
  "properties": {
    "iso:country":"DE",
    "sg:address":"Sebastianstr. 24",
    "sg:city":"Berlin",
    "sg:phone":"+49 30/2787280",
    "sg:postcode":"10179",
    "sg:province":"Berlin",
    "wof:name":"Wohnungsbaugenossenschaft Berolina Eg",
    "wof:placetype":"venue"
},
  "geometry": {"coordinates":[13.4100694656,52.5070648193],"type":"Point"}
}