{
  "type": "Feature",
  "properties": {
    "iso:country":"DE",
    "sg:address":"Liebigstr. 40",
    "sg:city":"R\u00f6dermark",
    "sg:phone":"+49 6074/8919330",
    "sg:postcode":"63322",
    "sg:province":"Hessen",
    "wof:name":"Hsk Ges. F\u00fcr Kommunikationst. L\u00f6sungen Mbh",
    "wof:placetype":"venue"
},
  "geometry": {"coordinates":[8.7990322113,49.9793052673],"type":"Point"}
}