{
  "type": "Feature",
  "properties": {
    "iso:country":"DE",
    "sg:address":"Hufeisenstr. 11",
    "sg:city":"Hattingen",
    "sg:phone":"+49 2324/21061",
    "sg:postcode":"45525",
    "sg:province":"Nordrhein-Westfalen",
    "wof:name":"Huster Baustoffe Gmbh & Co. Kg",
    "wof:placetype":"venue"
},
  "geometry": {"coordinates":[7.1687641144,51.3966522217],"type":"Point"}
}