{
  "type": "Feature",
  "properties": {
    "iso:country":"DE",
    "sg:address":"Im Eppen 17",
    "sg:city":"H\u00fcttisheim",
    "sg:phone":"+49 7305/6439",
    "sg:postcode":"89185",
    "sg:province":"Baden-W\u00fcrttemberg",
    "wof:name":"Dieter Kalkowski",
    "wof:placetype":"venue"
},
  "geometry": {"coordinates":[9.940236,48.27771],"type":"Point"}
}