{
  "type": "Feature",
  "properties": {
    "iso:country":"DE",
    "sg:address":"Neustadt 51",
    "sg:city":"Flensburg",
    "sg:phone":"+49 461/47427",
    "sg:postcode":"24939",
    "sg:province":"Schleswig-Holstein",
    "wof:name":"Durmaz",
    "wof:placetype":"venue"
},
  "geometry": {"coordinates":[9.4246282578,54.7985916138],"type":"Point"}
}