{
  "type": "Feature",
  "properties": {
    "iso:country":"DE",
    "sg:address":"Regnitzau 12",
    "sg:city":"Forchheim",
    "sg:phone":"+49 9191/31595",
    "sg:postcode":"91301",
    "sg:province":"Bayern",
    "wof:name":"A. Kestler",
    "wof:placetype":"venue"
},
  "geometry": {"coordinates":[11.0555076599,49.7275810242],"type":"Point"}
}