{
  "type": "Feature",
  "properties": {
    "iso:country":"DE",
    "sg:address":"Raumerstr. 14B",
    "sg:city":"Berlin",
    "sg:phone":"+49 30/4419090",
    "sg:postcode":"10437",
    "sg:province":"Berlin",
    "wof:name":"Apotheke Am Helmholtzplatz",
    "wof:placetype":"venue"
},
  "geometry": {"coordinates":[13.419955,52.542049],"type":"Point"}
}