{
  "type": "Feature",
  "properties": {
    "iso:country":"DE",
    "sg:address":"Auf dem Sand 14",
    "sg:city":"Hilden",
    "sg:phone":"+49 2103/9403",
    "sg:postcode":"40721",
    "sg:province":"Nordrhein-Westfalen",
    "wof:name":"Denison Hydraulik Gmbh",
    "wof:placetype":"venue"
},
  "geometry": {"coordinates":[6.9263300896,51.1762123108],"type":"Point"}
}