{
  "type": "Feature",
  "properties": {
    "iso:country":"DE",
    "sg:address":"Lange Str. 10",
    "sg:city":"L\u00fcbesse",
    "sg:postcode":"19077",
    "sg:province":"Mecklenburg-Vorpommern",
    "wof:name":"Chs & L Windpark Gmbh & Co. L\u00fcbesse Betriebs Kg",
    "wof:placetype":"venue"
},
  "geometry": {"coordinates":[11.458707,53.487423],"type":"Point"}
}