{
  "type": "Feature",
  "properties": {
    "iso:country":"DE",
    "sg:address":"Im Grund 1",
    "sg:city":"Burgbernheim",
    "sg:phone":"+49 9843/3080",
    "sg:postcode":"91593",
    "sg:province":"Bayern",
    "wof:name":"Ubb Umformtechnik Gmbh",
    "wof:placetype":"venue"
},
  "geometry": {"coordinates":[10.31419,49.456062],"type":"Point"}
}