{
  "type": "Feature",
  "properties": {
    "iso:country":"DE",
    "sg:address":"Sch\u00f6nblickstr. 67",
    "sg:city":"Engelsbrand",
    "sg:phone":"+49 7235/1839",
    "sg:postcode":"75331",
    "sg:province":"Baden-W\u00fcrttemberg",
    "wof:name":"Gerhard Schwarz",
    "wof:placetype":"venue"
},
  "geometry": {"coordinates":[8.687408,48.830399],"type":"Point"}
}