{
  "type": "Feature",
  "properties": {
    "iso:country":"DE",
    "sg:address":"Kirchheimer Str. 47",
    "sg:city":"Ostfildern",
    "sg:phone":"+49 711/413616",
    "sg:postcode":"73760",
    "sg:province":"Baden-W\u00fcrttemberg",
    "wof:name":"Manfred Reichert Architekt",
    "wof:placetype":"venue"
},
  "geometry": {"coordinates":[9.236751,48.73653],"type":"Point"}
}