{
  "type": "Feature",
  "properties": {
    "iso:country":"DE",
    "sg:address":"Untenende 48",
    "sg:city":"Rhauderfehn",
    "sg:phone":"+49 4952/2700",
    "sg:postcode":"26817",
    "sg:province":"Niedersachsen",
    "wof:name":"Erich Baumann Und Dorothee Schuppert",
    "wof:placetype":"venue"
},
  "geometry": {"coordinates":[7.5875,53.13715],"type":"Point"}
}