{
  "type": "Feature",
  "properties": {
    "iso:country":"DE",
    "sg:address":"Neuer Wall 35",
    "sg:city":"Hamburg",
    "sg:phone":"+49 40",
    "sg:postcode":"20354",
    "sg:province":"Hamburg",
    "wof:name":"Dennso Management Consulting Gmbh",
    "wof:placetype":"venue"
},
  "geometry": {"coordinates":[9.9905843735,53.551486969],"type":"Point"}
}