{
  "type": "Feature",
  "properties": {
    "iso:country":"DE",
    "sg:address":"Windm\u00fchlenstr. 18",
    "sg:city":"Verden",
    "sg:phone":"+49 4231/3170",
    "sg:postcode":"27283",
    "sg:province":"Niedersachsen",
    "wof:name":"L\u00f6ns-apotheke",
    "wof:placetype":"venue"
},
  "geometry": {"coordinates":[9.234646,52.920235],"type":"Point"}
}