{
  "type": "Feature",
  "properties": {
    "iso:country":"DE",
    "sg:address":"Obere Gasse 3",
    "sg:city":"Vaihingen",
    "sg:phone":"+49 7042/34244",
    "sg:postcode":"71665",
    "sg:province":"Baden-W\u00fcrttemberg",
    "wof:name":"Gastst\u00e4tte Engelst\u00fcble",
    "wof:placetype":"venue"
},
  "geometry": {"coordinates":[8.9687099457,48.9522018433],"type":"Point"}
}