{
  "type": "Feature",
  "properties": {
    "iso:country":"DE",
    "sg:address":"Auf den H\u00e4fen 1-2",
    "sg:city":"Bremen",
    "sg:postcode":"28203",
    "sg:province":"Bremen",
    "wof:name":"Orgelmann-orthop\u00e4die- Technik Gmbh",
    "wof:placetype":"venue"
},
  "geometry": {"coordinates":[8.822444,53.075306],"type":"Point"}
}