{
  "type": "Feature",
  "properties": {
    "iso:country":"DE",
    "sg:address":"Ratsgasse 1",
    "sg:city":"Dessau",
    "sg:phone":"+49 340/2205984",
    "sg:postcode":"06844",
    "sg:province":"Sachsen-Anhalt",
    "wof:name":"Geld- Und Werttransport Gmbh",
    "wof:placetype":"venue"
},
  "geometry": {"coordinates":[12.2462310791,51.8343048096],"type":"Point"}
}