{
  "type": "Feature",
  "properties": {
    "iso:country":"DE",
    "sg:address":"Postfach 12 28",
    "sg:city":"Heek",
    "sg:postcode":"48614",
    "sg:province":"Nordrhein-Westfalen",
    "wof:name":"Van Egmond Mechanisch Transport Gmbh",
    "wof:placetype":"venue"
},
  "geometry": {"coordinates":[7.1119351387,52.1164054871],"type":"Point"}
}