{
  "type": "Feature",
  "properties": {
    "iso:country":"DE",
    "sg:address":"Jenaer Str. 2",
    "sg:city":"Kleinromstedt",
    "sg:phone":"+49 3644/5800",
    "sg:postcode":"99510",
    "sg:province":"Th\u00fcringen",
    "wof:name":"Hotel Holiday Inn",
    "wof:placetype":"venue"
},
  "geometry": {"coordinates":[11.5135669708,50.9865608215],"type":"Point"}
}