{
  "type": "Feature",
  "properties": {
    "iso:country":"DE",
    "sg:address":"Glockenkamp 25",
    "sg:city":"Langelsheim",
    "sg:phone":"+49 5326/85061",
    "sg:postcode":"38685",
    "sg:province":"Niedersachsen",
    "wof:name":"Stadt- Und Schulb\u00fccherei Schulzentrum",
    "wof:placetype":"venue"
},
  "geometry": {"coordinates":[10.327024,51.938976],"type":"Point"}
}