{
  "type": "Feature",
  "properties": {
    "iso:country":"DE",
    "sg:address":"Am R\u00f6dchen 10",
    "sg:city":"M\u00fcnchhausen",
    "sg:phone":"+49 6423/1475",
    "sg:postcode":"35117",
    "sg:province":"Hessen",
    "wof:name":"Burgwald-trekking",
    "wof:placetype":"venue"
},
  "geometry": {"coordinates":[8.710128,50.939644],"type":"Point"}
}