{
  "type": "Feature",
  "properties": {
    "iso:country":"DE",
    "sg:address":"Industriering 1",
    "sg:city":"Blieskastel",
    "sg:postcode":"66440",
    "sg:province":"Saarland",
    "wof:name":"Cornelia Welsch Gmbh",
    "wof:placetype":"venue"
},
  "geometry": {"coordinates":[7.2605719566,49.2462806702],"type":"Point"}
}