{
  "type": "Feature",
  "properties": {
    "iso:country":"DE",
    "sg:address":"Kreuzstr. 14",
    "sg:city":"Aurich",
    "sg:phone":"+49 4941/64564",
    "sg:postcode":"26603",
    "sg:province":"Niedersachsen",
    "wof:name":"Tischlerei Pupkes",
    "wof:placetype":"venue"
},
  "geometry": {"coordinates":[7.48734,53.461281],"type":"Point"}
}