{
  "type": "Feature",
  "properties": {
    "iso:country":"DE",
    "sg:address":"Bahnhofstr. 8",
    "sg:city":"Detmold",
    "sg:phone":"+49 5231/92480",
    "sg:postcode":"32756",
    "sg:province":"Nordrhein-Westfalen",
    "wof:name":"Bvo Busverkehr Ostwestfalen Gmbh",
    "wof:placetype":"venue"
},
  "geometry": {"coordinates":[8.8737859726,51.9401321411],"type":"Point"}
}