{
  "type": "Feature",
  "properties": {
    "iso:country":"DE",
    "sg:address":"Ostlandstr. 48",
    "sg:city":"Lotte",
    "sg:phone":"+49 541/120560",
    "sg:postcode":"49504",
    "sg:province":"Nordrhein-Westfalen",
    "wof:name":"Matthias Meyer",
    "wof:placetype":"venue"
},
  "geometry": {"coordinates":[7.9860758781,52.3057975769],"type":"Point"}
}