{
  "type": "Feature",
  "properties": {
    "iso:country":"DE",
    "sg:address":"Bochumer Str. 104",
    "sg:city":"Recklinghausen",
    "sg:phone":"+49 2361/658448",
    "sg:postcode":"45661",
    "sg:province":"Nordrhein-Westfalen",
    "wof:name":"Nachhilfestudio Schlaumeier E. K.",
    "wof:placetype":"venue"
},
  "geometry": {"coordinates":[7.2126750946,51.574798584],"type":"Point"}
}