{
  "type": "Feature",
  "properties": {
    "iso:country":"DE",
    "sg:address":"Hagenauer Str. 42",
    "sg:city":"Wiesbaden",
    "sg:phone":"+49 611/182500",
    "sg:postcode":"65203",
    "sg:province":"Hessen",
    "wof:name":"Raytheon Engineers & Constructors Germany Gmbh",
    "wof:placetype":"venue"
},
  "geometry": {"coordinates":[8.216547,50.048523],"type":"Point"}
}