{
  "type": "Feature",
  "properties": {
    "iso:country":"DE",
    "sg:address":"Daimlerstr. 9",
    "sg:city":"Lemgo",
    "sg:phone":"+49 5261/970437",
    "sg:postcode":"32657",
    "sg:province":"Nordrhein-Westfalen",
    "wof:name":"Elisabeth F\u00fcsting-m\u00fcller Rechtsanw\u00e4ltin",
    "wof:placetype":"venue"
},
  "geometry": {"coordinates":[8.9021396637,52.0150985718],"type":"Point"}
}