{
  "type": "Feature",
  "properties": {
    "iso:country":"DE",
    "sg:address":"Jahnplatz 36",
    "sg:city":"Essen",
    "sg:postcode":"45143",
    "sg:province":"Nordrhein-Westfalen",
    "wof:name":"Team-bau Gmbh",
    "wof:placetype":"venue"
},
  "geometry": {"coordinates":[6.980401,51.467152],"type":"Point"}
}