{
  "type": "Feature",
  "properties": {
    "iso:country":"DE",
    "sg:address":"Am Anger 8 A",
    "sg:city":"Wiehe",
    "sg:postcode":"06571",
    "sg:province":"Th\u00fcringen",
    "wof:name":"Mineral\u00f6lversand Sander",
    "wof:placetype":"venue"
},
  "geometry": {"coordinates":[11.4208269119,51.2621650696],"type":"Point"}
}