{
  "type": "Feature",
  "properties": {
    "iso:country":"DE",
    "sg:address":"Reuterstr. 6",
    "sg:city":"Oerlinghausen",
    "sg:phone":"+49 5202/158185",
    "sg:postcode":"33813",
    "sg:province":"Nordrhein-Westfalen",
    "wof:name":"Hans-peter G\u00f6hn Architekt",
    "wof:placetype":"venue"
},
  "geometry": {"coordinates":[8.66476,51.96122],"type":"Point"}
}