{
  "type": "Feature",
  "properties": {
    "iso:country":"DE",
    "sg:address":"Kampstr. 30",
    "sg:city":"Wetschen",
    "sg:phone":"+49 5446/1581",
    "sg:postcode":"49453",
    "sg:province":"Niedersachsen",
    "wof:name":"Oliver Kaspar",
    "wof:placetype":"venue"
},
  "geometry": {"coordinates":[8.4496793747,52.6098976135],"type":"Point"}
}