{
  "type": "Feature",
  "properties": {
    "iso:country":"DE",
    "sg:address":"Schwerter Str. 209",
    "sg:city":"Dortmund",
    "sg:phone":"+49 231/443905",
    "sg:postcode":"44287",
    "sg:province":"Nordrhein-Westfalen",
    "wof:name":"Zahn Bauunternehmung Gmbh & Co. Kg",
    "wof:placetype":"venue"
},
  "geometry": {"coordinates":[7.5695610046,51.4849853516],"type":"Point"}
}