{
  "type": "Feature",
  "properties": {
    "iso:country":"DE",
    "sg:address":"Hauptstr. 32",
    "sg:city":"Ettringen",
    "sg:phone":"+49 8249/610",
    "sg:postcode":"86833",
    "sg:province":"Bayern",
    "wof:name":"Hubert M\u00fcller",
    "wof:placetype":"venue"
},
  "geometry": {"coordinates":[10.6577043533,48.1060829163],"type":"Point"}
}