{
  "type": "Feature",
  "properties": {
    "iso:country":"DE",
    "sg:address":"Bertoldstr. 9",
    "sg:city":"Regensburg",
    "sg:phone":"+49 941/58997",
    "sg:postcode":"93047",
    "sg:province":"Bayern",
    "wof:name":"St\u00e4dt. Galerie Leerer Beutel",
    "wof:placetype":"venue"
},
  "geometry": {"coordinates":[12.1031141281,49.0183982849],"type":"Point"}
}