{
  "type": "Feature",
  "properties": {
    "iso:country":"DE",
    "sg:address":"Adolfstr. 67",
    "sg:city":"Lahnstein",
    "sg:phone":"+49 2621/5840",
    "sg:postcode":"56112",
    "sg:province":"Rheinland-Pfalz",
    "wof:name":"St.-martin-stube",
    "wof:placetype":"venue"
},
  "geometry": {"coordinates":[7.607006073,50.300994873],"type":"Point"}
}