{
  "type": "Feature",
  "properties": {
    "iso:country":"DE",
    "sg:address":"Fliederstr. 42",
    "sg:city":"Gro\u00dfrinderfeld",
    "sg:phone":"+49 9344/91031",
    "sg:postcode":"97950",
    "sg:province":"Baden-W\u00fcrttemberg",
    "wof:name":"Norbert Emmerling",
    "wof:placetype":"venue"
},
  "geometry": {"coordinates":[9.783253,49.70261],"type":"Point"}
}