{
  "type": "Feature",
  "properties": {
    "iso:country":"DE",
    "sg:address":"Kieler Str. 90",
    "sg:city":"Kronshagen",
    "sg:phone":"+49 431/5842914",
    "sg:postcode":"24119",
    "sg:province":"Schleswig-Holstein",
    "wof:name":"Heike Joost-kr\u00fcger Architektin",
    "wof:placetype":"venue"
},
  "geometry": {"coordinates":[10.08163,54.331894],"type":"Point"}
}