{
  "type": "Feature",
  "properties": {
    "iso:country":"DE",
    "sg:address":"Imental 1",
    "sg:city":"Jettingen",
    "sg:phone":"+49 7452/75339",
    "sg:postcode":"71131",
    "sg:province":"Baden-W\u00fcrttemberg",
    "wof:name":"Erich Niethammer",
    "wof:placetype":"venue"
},
  "geometry": {"coordinates":[8.76621,48.558647],"type":"Point"}
}