{
  "type": "Feature",
  "properties": {
    "iso:country":"DE",
    "sg:address":"Bahnhofstr. 15",
    "sg:city":"St. Ingbert",
    "sg:phone":"+49 6894/5590",
    "sg:postcode":"66386",
    "sg:province":"Saarland",
    "wof:name":"Marlene Unbehend",
    "wof:placetype":"venue"
},
  "geometry": {"coordinates":[7.1145329475,49.2763748169],"type":"Point"}
}