{
  "type": "Feature",
  "properties": {
    "iso:country":"DE",
    "sg:address":"Bahrenfelder Steindamm 6",
    "sg:city":"Hamburg",
    "sg:postcode":"22761",
    "sg:province":"Hamburg",
    "wof:name":"More Bernhard M\u00fcller",
    "wof:placetype":"venue"
},
  "geometry": {"coordinates":[9.927570343,53.559928894],"type":"Point"}
}