{
  "type": "Feature",
  "properties": {
    "iso:country":"DE",
    "sg:address":"Hauptstr. 83",
    "sg:city":"Zella-Mehlis",
    "sg:phone":"+49 3682/482937",
    "sg:postcode":"98544",
    "sg:province":"Th\u00fcringen",
    "wof:name":"Fahrrad-k\u00f6hler Inh. Lutz K\u00f6hler",
    "wof:placetype":"venue"
},
  "geometry": {"coordinates":[10.6687803268,50.655330658],"type":"Point"}
}