{
  "type": "Feature",
  "properties": {
    "iso:country":"DE",
    "sg:address":"Uthleder Berg 74",
    "sg:city":"Uthlede",
    "sg:postcode":"27628",
    "sg:province":"Niedersachsen",
    "wof:name":"Otto Baur",
    "wof:placetype":"venue"
},
  "geometry": {"coordinates":[8.6430625916,53.3554801941],"type":"Point"}
}