{
  "type": "Feature",
  "properties": {
    "iso:country":"DE",
    "sg:address":"Werdauer Str. 7",
    "sg:city":"Fraureuth",
    "sg:phone":"+49 3761/81443",
    "sg:postcode":"08427",
    "sg:province":"Sachsen",
    "wof:name":"Zimmerei Und Treppenbau Gmbh Thomas Bormann",
    "wof:placetype":"venue"
},
  "geometry": {"coordinates":[12.3622045517,50.7069473267],"type":"Point"}
}