{
  "type": "Feature",
  "properties": {
    "iso:country":"DE",
    "sg:address":"Ludwigshafener Str. 48",
    "sg:city":"Mutterstadt",
    "sg:phone":"+49 6234/6334",
    "sg:postcode":"67112",
    "sg:province":"Rheinland-Pfalz",
    "wof:name":"Waggel-stubb",
    "wof:placetype":"venue"
},
  "geometry": {"coordinates":[8.3588094711,49.4457855225],"type":"Point"}
}