{
  "type": "Feature",
  "properties": {
    "iso:country":"DE",
    "sg:address":"M\u00fchlenweg 5 a",
    "sg:city":"Westfehmarn",
    "sg:phone":"+49 4372/314",
    "sg:postcode":"23769",
    "sg:province":"Schleswig-Holstein",
    "wof:name":"Ernst-peter K\u00fchlsen",
    "wof:placetype":"venue"
},
  "geometry": {"coordinates":[11.09954,54.439781],"type":"Point"}
}