{
  "type": "Feature",
  "properties": {
    "iso:country":"DE",
    "sg:address":"Kaiser-Wilhelm-Str. 11b",
    "sg:city":"Bad Kreuznach",
    "sg:phone":"+49 671/46441",
    "sg:postcode":"55543",
    "sg:province":"Rheinland-Pfalz",
    "wof:name":"Manfred Scheib",
    "wof:placetype":"venue"
},
  "geometry": {"coordinates":[7.8552417755,49.8403053284],"type":"Point"}
}