{
  "type": "Feature",
  "properties": {
    "iso:country":"DE",
    "sg:address":"Rheinlandplatz",
    "sg:city":"Neuss",
    "sg:phone":"+49 4921/312900",
    "sg:postcode":"41460",
    "sg:province":"Nordrhein-Westfalen",
    "wof:name":"Rheinland Lebensversicherung Ag",
    "wof:placetype":"venue"
},
  "geometry": {"coordinates":[6.68933,51.205284],"type":"Point"}
}