{
  "type": "Feature",
  "properties": {
    "iso:country":"DE",
    "sg:address":"An Der Garnbleiche 10 - 12",
    "sg:city":"D\u00fcren",
    "sg:phone":"+49 4924/2195340",
    "sg:postcode":"52349",
    "sg:province":"Nordrhein-Westfalen",
    "wof:name":"Holz Leisten Gmbh",
    "wof:placetype":"venue"
},
  "geometry": {"coordinates":[6.4875388145,50.7873001099],"type":"Point"}
}