{
  "type": "Feature",
  "properties": {
    "iso:country":"DE",
    "sg:address":"Pariser Str. 38",
    "sg:city":"Berlin",
    "sg:phone":"+49 30/8816102",
    "sg:postcode":"10707",
    "sg:province":"Berlin",
    "wof:name":"Merkur Investitions- Consulting Gmbh",
    "wof:placetype":"venue"
},
  "geometry": {"coordinates":[13.318045,52.49818],"type":"Point"}
}