{
  "type": "Feature",
  "properties": {
    "iso:country":"DE",
    "sg:address":"Schelderh\u00fctte 1",
    "sg:city":"Dillenburg",
    "sg:phone":"+49 2771/89950",
    "sg:postcode":"35687",
    "sg:province":"Hessen",
    "wof:name":"Metallverarbeitung Klahr Gmbh",
    "wof:placetype":"venue"
},
  "geometry": {"coordinates":[8.3133296967,50.7252693176],"type":"Point"}
}