{
  "type": "Feature",
  "properties": {
    "iso:country":"DE",
    "sg:address":"Raiffeisenstr. 4",
    "sg:city":"Pondorf",
    "sg:phone":"+49 9428/8774",
    "sg:postcode":"94356",
    "sg:province":"Bayern",
    "wof:name":"Raiffeisenbank Straubing Eg",
    "wof:placetype":"venue"
},
  "geometry": {"coordinates":[12.488721,48.965149],"type":"Point"}
}