{
  "type": "Feature",
  "properties": {
    "iso:country":"DE",
    "sg:address":"Bremer Str. 42",
    "sg:city":"Osnabr\u00fcck",
    "sg:postcode":"49084",
    "sg:province":"Niedersachsen",
    "wof:name":"Mtg Magdeburger Hoch- Tief-und Tankstellenbau Gmbh & Co. Kg",
    "wof:placetype":"venue"
},
  "geometry": {"coordinates":[8.073704,52.282936],"type":"Point"}
}