{
  "type": "Feature",
  "properties": {
    "iso:country":"DE",
    "sg:address":"Am Lilienbaum 10 b",
    "sg:city":"Hagen",
    "sg:phone":"+49 2331/42386",
    "sg:postcode":"58135",
    "sg:province":"Nordrhein-Westfalen",
    "wof:name":"Rainer Weber",
    "wof:placetype":"venue"
},
  "geometry": {"coordinates":[7.4202799797,51.3608589172],"type":"Point"}
}