{
  "type": "Feature",
  "properties": {
    "iso:country":"DE",
    "sg:address":"Friedhofsweg 3",
    "sg:city":"H\u00fcttenrode",
    "sg:phone":"+49 3944/352455",
    "sg:postcode":"38889",
    "sg:province":"Sachsen-Anhalt",
    "wof:name":"H. Stein",
    "wof:placetype":"venue"
},
  "geometry": {"coordinates":[10.907318,51.772629],"type":"Point"}
}