{
  "type": "Feature",
  "properties": {
    "iso:country":"DE",
    "sg:address":"Dorfstr. 38",
    "sg:city":"Bad Bayersoien",
    "sg:phone":"+49 8845/1896",
    "sg:postcode":"82435",
    "sg:province":"Bayern",
    "wof:name":"Holderied Gmbh",
    "wof:placetype":"venue"
},
  "geometry": {"coordinates":[10.9942646027,47.6911239624],"type":"Point"}
}