{
  "type": "Feature",
  "properties": {
    "iso:country":"DE",
    "sg:address":"Bahnhofstr. 7",
    "sg:city":"Gernsheim",
    "sg:phone":"+49 6258/902591",
    "sg:postcode":"64579",
    "sg:province":"Hessen",
    "wof:name":"J\u00fcrgen Walter Rechtsanwalt",
    "wof:placetype":"venue"
},
  "geometry": {"coordinates":[8.4889192581,49.7551841736],"type":"Point"}
}