{
  "type": "Feature",
  "properties": {
    "iso:country":"DE",
    "sg:address":"Schwabacher Strasse 30",
    "sg:city":"Feucht",
    "sg:phone":"+49 9128/8580",
    "sg:postcode":"90537",
    "sg:province":"Bayern",
    "wof:name":"Lichtpaus- & Kopier- Service Mentzen",
    "wof:placetype":"venue"
},
  "geometry": {"coordinates":[11.211496,49.37188],"type":"Point"}
}