{
  "type": "Feature",
  "properties": {
    "iso:country":"DE",
    "sg:address":"Kreuzbergstr. 5a",
    "sg:city":"Grabenst\u00e4tt",
    "sg:phone":"+49 861/3101",
    "sg:postcode":"83355",
    "sg:province":"Bayern",
    "wof:name":"Georg Strohmayer",
    "wof:placetype":"venue"
},
  "geometry": {"coordinates":[12.594044,47.874592],"type":"Point"}
}