{
  "type": "Feature",
  "properties": {
    "iso:country":"DE",
    "sg:address":"Oberfrohnaer Str. 111",
    "sg:city":"Chemnitz",
    "sg:phone":"+49 371/851870",
    "sg:postcode":"09117",
    "sg:province":"Sachsen",
    "wof:name":"G. Sch\u00e4fer",
    "wof:placetype":"venue"
},
  "geometry": {"coordinates":[12.82271,50.829929],"type":"Point"}
}