{
  "type": "Feature",
  "properties": {
    "iso:country":"DE",
    "sg:address":"Kapellenstr. 10",
    "sg:city":"Otterstadt",
    "sg:phone":"+49 6232/33130",
    "sg:postcode":"67166",
    "sg:province":"Rheinland-Pfalz",
    "wof:name":"Erwin Spindler",
    "wof:placetype":"venue"
},
  "geometry": {"coordinates":[8.4518671036,49.3715782166],"type":"Point"}
}