{
  "type": "Feature",
  "properties": {
    "iso:country":"DE",
    "sg:address":"L\u00f6wenberger Str. 4",
    "sg:city":"Emmerich",
    "sg:phone":"+49 2822/6751",
    "sg:postcode":"46446",
    "sg:province":"Nordrhein-Westfalen",
    "wof:name":"Castello M\u00f6bel Gmbh",
    "wof:placetype":"venue"
},
  "geometry": {"coordinates":[6.249525,51.835564],"type":"Point"}
}