{
  "type": "Feature",
  "properties": {
    "iso:country":"DE",
    "sg:address":"Anton-Flettner-Str. 7",
    "sg:city":"Raunheim",
    "sg:phone":"+49 6142/42029",
    "sg:postcode":"65479",
    "sg:province":"Hessen",
    "wof:name":"Blumen-risse Gmbh & Co. Kg",
    "wof:placetype":"venue"
},
  "geometry": {"coordinates":[8.440982,50.011307],"type":"Point"}
}