{
  "type": "Feature",
  "properties": {
    "iso:country":"DE",
    "sg:address":"N\u00fcrnberger Str. 16",
    "sg:city":"Forchheim",
    "sg:phone":"+49 9191/67863",
    "sg:postcode":"91301",
    "sg:province":"Bayern",
    "wof:name":"T. Scott",
    "wof:placetype":"venue"
},
  "geometry": {"coordinates":[11.060116,49.716648],"type":"Point"}
}