{
  "type": "Feature",
  "properties": {
    "iso:country":"DE",
    "sg:address":"Oberer Birken 4a",
    "sg:city":"Markdorf",
    "sg:phone":"+49 7544/4543",
    "sg:postcode":"88677",
    "sg:province":"Baden-W\u00fcrttemberg",
    "wof:name":"J. Braun Ingenieur",
    "wof:placetype":"venue"
},
  "geometry": {"coordinates":[9.4174222946,47.7165794373],"type":"Point"}
}