{
  "type": "Feature",
  "properties": {
    "iso:country":"DE",
    "sg:address":"H\u00fcttenbergstr. 28",
    "sg:city":"Neunkirchen",
    "sg:phone":"+49 6821/14634",
    "sg:postcode":"66538",
    "sg:province":"Saarland",
    "wof:name":"Megabike Fahrzeughandel Gmbh",
    "wof:placetype":"venue"
},
  "geometry": {"coordinates":[7.176030159,49.3461380005],"type":"Point"}
}