{
  "type": "Feature",
  "properties": {
    "iso:country":"DE",
    "sg:address":"Am Kleinwald 2 a",
    "sg:city":"Herxheim",
    "sg:phone":"+49 7276/7896",
    "sg:postcode":"76863",
    "sg:province":"Rheinland-Pfalz",
    "wof:name":"Optifit",
    "wof:placetype":"venue"
},
  "geometry": {"coordinates":[8.2226886749,49.1399154663],"type":"Point"}
}