{
  "type": "Feature",
  "properties": {
    "iso:country":"DE",
    "sg:address":"In der Gibitzen 9",
    "sg:city":"Wendelstein",
    "sg:postcode":"90530",
    "sg:province":"Bayern",
    "wof:name":"Idrizi Gmbh",
    "wof:placetype":"venue"
},
  "geometry": {"coordinates":[11.1408472061,49.3559532166],"type":"Point"}
}