{
  "type": "Feature",
  "properties": {
    "iso:country":"DE",
    "sg:address":"St.-Michael-Str. 8",
    "sg:city":"M\u00fcnchen",
    "sg:phone":"+49 89/4310164",
    "sg:postcode":"81673",
    "sg:province":"Bayern",
    "wof:name":"Margarete Patscheider",
    "wof:placetype":"venue"
},
  "geometry": {"coordinates":[11.631493,48.125885],"type":"Point"}
}