{
  "type": "Feature",
  "properties": {
    "iso:country":"DE",
    "sg:address":"Bekenreihe",
    "sg:city":"Kiebitzreihe",
    "sg:phone":"+49 4121/5402",
    "sg:postcode":"25368",
    "sg:province":"Schleswig-Holstein",
    "wof:name":"Werner Kahl",
    "wof:placetype":"venue"
},
  "geometry": {"coordinates":[9.590477,53.790253],"type":"Point"}
}