{
  "type": "Feature",
  "properties": {
    "iso:country":"DE",
    "sg:address":"Schonerstr. 12",
    "sg:city":"N\u00fcrnberg",
    "sg:phone":"+49 911/459306",
    "sg:postcode":"90443",
    "sg:province":"Bayern",
    "wof:name":"Gabriele Neugebauer",
    "wof:placetype":"venue"
},
  "geometry": {"coordinates":[11.0750007629,49.440738678],"type":"Point"}
}