{
  "type": "Feature",
  "properties": {
    "iso:country":"DE",
    "sg:address":"An der Burg 3",
    "sg:city":"Weferlingen",
    "sg:phone":"+49 39061/2822",
    "sg:postcode":"39356",
    "sg:province":"Sachsen-Anhalt",
    "wof:name":"B\u00fcttner Gmbh",
    "wof:placetype":"venue"
},
  "geometry": {"coordinates":[11.056265,52.310722],"type":"Point"}
}