{
  "type": "Feature",
  "properties": {
    "iso:country":"DE",
    "sg:address":"Kappelstr. 51",
    "sg:city":"Burgthann",
    "sg:phone":"+49 9183/791",
    "sg:postcode":"90559",
    "sg:province":"Bayern",
    "wof:name":"D. G\u00fcgel",
    "wof:placetype":"venue"
},
  "geometry": {"coordinates":[11.2764978409,49.355846405],"type":"Point"}
}