{
  "type": "Feature",
  "properties": {
    "iso:country":"DE",
    "sg:address":"Rollhofweg 61",
    "sg:city":"Schw\u00e4bisch Hall",
    "sg:phone":"+49 791/51544",
    "sg:postcode":"74523",
    "sg:province":"Baden-W\u00fcrttemberg",
    "wof:name":"Fritz Reinardt Architekt",
    "wof:placetype":"venue"
},
  "geometry": {"coordinates":[9.719432,49.10648],"type":"Point"}
}