{
  "type": "Feature",
  "properties": {
    "iso:country":"DE",
    "sg:address":"Graf-von-Galen-Ring 10",
    "sg:city":"Hagen",
    "sg:phone":"+49 2331/181114",
    "sg:postcode":"58095",
    "sg:province":"Nordrhein-Westfalen",
    "wof:name":"A. Keser",
    "wof:placetype":"venue"
},
  "geometry": {"coordinates":[7.4634189606,51.3637237549],"type":"Point"}
}