{
  "type": "Feature",
  "properties": {
    "iso:country":"DE",
    "sg:address":"Im Schwarzenfeld 28a",
    "sg:city":"Mittenwald",
    "sg:phone":"+49 8823/93111",
    "sg:postcode":"82481",
    "sg:province":"Bayern",
    "wof:name":"Christian Sprenger",
    "wof:placetype":"venue"
},
  "geometry": {"coordinates":[11.265291214,47.4343185425],"type":"Point"}
}