{
  "type": "Feature",
  "properties": {
    "iso:country":"DE",
    "sg:address":"Bonifatiusstr. 32",
    "sg:city":"Fritzlar",
    "sg:phone":"+49 5622/3875",
    "sg:postcode":"34560",
    "sg:province":"Hessen",
    "wof:name":"Restaurant Heinrich Wagner",
    "wof:placetype":"venue"
},
  "geometry": {"coordinates":[9.2566432953,51.1374015808],"type":"Point"}
}