{
  "type": "Feature",
  "properties": {
    "iso:country":"DE",
    "sg:address":"Eintrachtstr. 90",
    "sg:city":"K\u00f6ln",
    "sg:phone":"+49 221/133427",
    "sg:postcode":"50668",
    "sg:province":"Nordrhein-Westfalen",
    "wof:name":"Horneck",
    "wof:placetype":"venue"
},
  "geometry": {"coordinates":[6.9531059265,50.9465293884],"type":"Point"}
}