{
  "type": "Feature",
  "properties": {
    "iso:country":"DE",
    "sg:address":"Hauptstr. 12",
    "sg:city":"Lohra",
    "sg:phone":"+49 6426/7235",
    "sg:postcode":"35102",
    "sg:province":"Hessen",
    "wof:name":"S. Blicker",
    "wof:placetype":"venue"
},
  "geometry": {"coordinates":[8.602969,50.700211],"type":"Point"}
}