{
  "type": "Feature",
  "properties": {
    "iso:country":"DE",
    "sg:address":"Grafenberger Allee 99",
    "sg:city":"D\u00fcsseldorf",
    "sg:postcode":"40237",
    "sg:province":"Nordrhein-Westfalen",
    "wof:name":"Commerotrade Gmbh Vermittlung Von B\u00f6rsenanlagen",
    "wof:placetype":"venue"
},
  "geometry": {"coordinates":[6.804459095,51.2309112549],"type":"Point"}
}