{
  "type": "Feature",
  "properties": {
    "iso:country":"DE",
    "sg:address":"Christian-Sch\u00e4fer-Str. 4",
    "sg:city":"Euskirchen",
    "sg:phone":"+49 2255/2377",
    "sg:postcode":"53881",
    "sg:province":"Nordrhein-Westfalen",
    "wof:name":"Tolkemit Gesellschaft Mbh",
    "wof:placetype":"venue"
},
  "geometry": {"coordinates":[6.849234,50.62484],"type":"Point"}
}