{
  "type": "Feature",
  "properties": {
    "iso:country":"DE",
    "sg:address":"Hahnenstr. 19",
    "sg:city":"Riegelsberg",
    "sg:phone":"+49 6806/46208",
    "sg:postcode":"66292",
    "sg:province":"Saarland",
    "wof:name":"Klaus-j\u00fcrgen Braun Architekt",
    "wof:placetype":"venue"
},
  "geometry": {"coordinates":[6.951384,49.313198],"type":"Point"}
}