{
  "type": "Feature",
  "properties": {
    "iso:country":"DE",
    "sg:address":"Zollhallenstr 4-14",
    "sg:city":"Freiburg",
    "sg:phone":"+49 761/5130",
    "sg:postcode":"79106",
    "sg:province":"Baden-W\u00fcrttemberg",
    "wof:name":"Schenker Deutschland Ag",
    "wof:placetype":"venue"
},
  "geometry": {"coordinates":[7.8478488922,48.0110054016],"type":"Point"}
}