{
  "type": "Feature",
  "properties": {
    "iso:country":"DE",
    "sg:address":"Industriestr. 2",
    "sg:city":"Heiligenroth",
    "sg:phone":"+49 2602/15890",
    "sg:postcode":"56412",
    "sg:province":"Rheinland-Pfalz",
    "wof:name":"Nick-baubedarf Gmbh & Co. Kg",
    "wof:placetype":"venue"
},
  "geometry": {"coordinates":[7.8487811089,50.4516563416],"type":"Point"}
}