{
  "type": "Feature",
  "properties": {
    "iso:country":"DE",
    "sg:address":"Bahnhofstr. 68",
    "sg:city":"Petershagen",
    "sg:phone":"+49 5702/9637",
    "sg:postcode":"32469",
    "sg:province":"Nordrhein-Westfalen",
    "wof:name":"Peggys Pub",
    "wof:placetype":"venue"
},
  "geometry": {"coordinates":[9.0067958832,52.3672676086],"type":"Point"}
}