{
  "type": "Feature",
  "properties": {
    "iso:country":"DE",
    "sg:address":"Kaiserstr. 1",
    "sg:city":"Heilbronn",
    "sg:phone":"+49 7131/96110",
    "sg:postcode":"74072",
    "sg:province":"Baden-W\u00fcrttemberg",
    "wof:name":"Hypo-immobilien Service Gmbh",
    "wof:placetype":"venue"
},
  "geometry": {"coordinates":[9.2164583206,49.1424446106],"type":"Point"}
}