{
  "type": "Feature",
  "properties": {
    "iso:country":"DE",
    "sg:address":"Gneisenaustr. 56",
    "sg:city":"Bad Schwartau",
    "sg:phone":"+49 451/25557",
    "sg:postcode":"23611",
    "sg:province":"Schleswig-Holstein",
    "wof:name":"P. Brandt Ingenieur",
    "wof:placetype":"venue"
},
  "geometry": {"coordinates":[10.7080030441,53.9185142517],"type":"Point"}
}