{
  "type": "Feature",
  "properties": {
    "iso:country":"DE",
    "sg:address":"Calvinstr. 4",
    "sg:city":"Gera",
    "sg:phone":"+49 365/22157",
    "sg:postcode":"07546",
    "sg:province":"Th\u00fcringen",
    "wof:name":"Blaue Sch\u00fcrze",
    "wof:placetype":"venue"
},
  "geometry": {"coordinates":[12.0924777985,50.8810195923],"type":"Point"}
}