{
  "type": "Feature",
  "properties": {
    "iso:country":"DE",
    "sg:address":"Boelckestr. 40",
    "sg:city":"Regensburg",
    "sg:phone":"+49 941/920110",
    "sg:postcode":"93051",
    "sg:province":"Bayern",
    "wof:name":"Solar Quarter Unterer W\u00f6hrd Gmbh",
    "wof:placetype":"venue"
},
  "geometry": {"coordinates":[12.0723543167,49.0010452271],"type":"Point"}
}