{
  "type": "Feature",
  "properties": {
    "iso:country":"DE",
    "sg:address":"Postfach 1710",
    "sg:city":"R\u00fcsselsheim",
    "sg:phone":"+49 4961/42660",
    "sg:postcode":"65423",
    "sg:province":"Hessen",
    "wof:name":"Adam Opel Ag",
    "wof:placetype":"venue"
},
  "geometry": {"coordinates":[8.4104852676,49.9948043823],"type":"Point"}
}