{
  "type": "Feature",
  "properties": {
    "iso:country":"DE",
    "sg:city":"Hannover",
    "sg:postcode":"30629",
    "sg:province":"Niedersachsen",
    "wof:name":"Internet Riding Shop",
    "wof:placetype":"venue"
},
  "geometry": {"coordinates":[9.853825,52.390343],"type":"Point"}
}