{
  "type": "Feature",
  "properties": {
    "iso:country":"DE",
    "sg:address":"Gahlenfeldstr. 42 a",
    "sg:city":"Herdecke",
    "sg:postcode":"58313",
    "sg:province":"Nordrhein-Westfalen",
    "wof:name":"H\u00f6hler Bauelemente Gmbh",
    "wof:placetype":"venue"
},
  "geometry": {"coordinates":[7.44309,51.419914],"type":"Point"}
}