{
  "type": "Feature",
  "properties": {
    "iso:country":"DE",
    "sg:address":"Kolpingstr. 9",
    "sg:city":"Aschendorf",
    "sg:phone":"+49 4962/810",
    "sg:postcode":"26871",
    "sg:province":"Niedersachsen",
    "wof:name":"Kolpinghaus",
    "wof:placetype":"venue"
},
  "geometry": {"coordinates":[7.3328828812,53.0520057678],"type":"Point"}
}