{
  "type": "Feature",
  "properties": {
    "iso:country":"DE",
    "sg:address":"Heckebaum 16",
    "sg:city":"Saerbeck",
    "sg:phone":"+49 2574/1707",
    "sg:postcode":"48369",
    "sg:province":"Nordrhein-Westfalen",
    "wof:name":"H.-j. Bachmann Ingenieur",
    "wof:placetype":"venue"
},
  "geometry": {"coordinates":[7.6407318115,52.1765289307],"type":"Point"}
}