{
  "type": "Feature",
  "properties": {
    "iso:country":"DE",
    "sg:address":"Gei\u00dfelgasse 1a",
    "sg:city":"Landau",
    "sg:phone":"+49 6341/63532",
    "sg:postcode":"76829",
    "sg:province":"Rheinland-Pfalz",
    "wof:name":"Maria Zangmeister",
    "wof:placetype":"venue"
},
  "geometry": {"coordinates":[8.1100053787,49.2229347229],"type":"Point"}
}