{
  "type": "Feature",
  "properties": {
    "iso:country":"DE",
    "sg:address":"Blumenstr. 2",
    "sg:city":"Schwaikheim",
    "sg:phone":"+49 7195/51101",
    "sg:postcode":"71409",
    "sg:province":"Baden-W\u00fcrttemberg",
    "wof:name":"Hans-peter Eberhardt",
    "wof:placetype":"venue"
},
  "geometry": {"coordinates":[9.352858,48.871555],"type":"Point"}
}