{
  "type": "Feature",
  "properties": {
    "iso:country":"DE",
    "sg:address":"Br\u00fcckenstr. 27",
    "sg:city":"Neumagen-Dhron",
    "sg:phone":"+49 6507/5837",
    "sg:postcode":"54347",
    "sg:province":"Rheinland-Pfalz",
    "wof:name":"L. Hardt",
    "wof:placetype":"venue"
},
  "geometry": {"coordinates":[6.901915,49.8633],"type":"Point"}
}