{
  "type": "Feature",
  "properties": {
    "iso:country":"DE",
    "sg:address":"Marktplatz 61",
    "sg:city":"Ro\u00dftal",
    "sg:phone":"+49 9127/6528",
    "sg:postcode":"90574",
    "sg:province":"Bayern",
    "wof:name":"Hans Wei\u00df",
    "wof:placetype":"venue"
},
  "geometry": {"coordinates":[10.8849172592,49.3977012634],"type":"Point"}
}