{
  "type": "Feature",
  "properties": {
    "iso:country":"DE",
    "sg:address":"Heinrich-Christiansen-Str. 35",
    "sg:city":"Pinneberg",
    "sg:phone":"+49 4101/22280",
    "sg:postcode":"25421",
    "sg:province":"Schleswig-Holstein",
    "wof:name":"Siewertsen Gmbh",
    "wof:placetype":"venue"
},
  "geometry": {"coordinates":[9.789078,53.652824],"type":"Point"}
}