{
  "type": "Feature",
  "properties": {
    "iso:country":"DE",
    "sg:address":"M\u00f6gersbronner Str. 1",
    "sg:city":"Feuchtwangen",
    "sg:phone":"+49 9852/615080",
    "sg:postcode":"91555",
    "sg:province":"Bayern",
    "wof:name":"M\u00fcller Fl\u00fcssiggas Vertriebs Gmbh",
    "wof:placetype":"venue"
},
  "geometry": {"coordinates":[10.3242349625,49.149974823],"type":"Point"}
}