{
  "type": "Feature",
  "properties": {
    "iso:country":"DE",
    "sg:address":"Querfurter Str. 2",
    "sg:city":"Merseburg",
    "sg:phone":"+49 3461/203972",
    "sg:postcode":"06217",
    "sg:province":"Sachsen-Anhalt",
    "wof:name":"C. N\u00f6ckel",
    "wof:placetype":"venue"
},
  "geometry": {"coordinates":[11.98168,51.37109],"type":"Point"}
}