{
  "type": "Feature",
  "properties": {
    "iso:country":"DE",
    "sg:address":"Metzgergasse 2",
    "sg:city":"Wei\u00dfenburg",
    "sg:phone":"+49 9142/8167",
    "sg:postcode":"91781",
    "sg:province":"Bayern",
    "wof:name":"Klaus Kattinger",
    "wof:placetype":"venue"
},
  "geometry": {"coordinates":[10.948273,48.986568],"type":"Point"}
}