{
  "type": "Feature",
  "properties": {
    "iso:country":"DE",
    "sg:address":"Arendsstr. 16",
    "sg:city":"Offenbach",
    "sg:phone":"+49 69/862959",
    "sg:postcode":"63075",
    "sg:province":"Hessen",
    "wof:name":"Marianne Oestreich",
    "wof:placetype":"venue"
},
  "geometry": {"coordinates":[8.785226,50.121071],"type":"Point"}
}