{
  "type": "Feature",
  "properties": {
    "iso:country":"DE",
    "sg:address":"Thiersheimer Str. 3",
    "sg:city":"Arzberg",
    "sg:phone":"+49 9233/77500",
    "sg:postcode":"95659",
    "sg:province":"Bayern",
    "wof:name":"Raiffeisen Service Gmbh",
    "wof:placetype":"venue"
},
  "geometry": {"coordinates":[12.184967041,50.0572547913],"type":"Point"}
}