{
  "type": "Feature",
  "properties": {
    "iso:country":"DE",
    "sg:address":"Altriper Str. 64",
    "sg:city":"Ludwigshafen",
    "sg:phone":"+49 621/576189",
    "sg:postcode":"67065",
    "sg:province":"Rheinland-Pfalz",
    "wof:name":"Werner Wittmann",
    "wof:placetype":"venue"
},
  "geometry": {"coordinates":[8.4324712753,49.4611473083],"type":"Point"}
}