{
  "type": "Feature",
  "properties": {
    "iso:country":"DE",
    "sg:address":"Kaiser-Wilhelm-Str. 53",
    "sg:city":"Hamburg",
    "sg:postcode":"20355",
    "sg:province":"Hamburg",
    "wof:name":"Integragroup Internet Management Gmbh",
    "wof:placetype":"venue"
},
  "geometry": {"coordinates":[9.9829092026,53.5534133911],"type":"Point"}
}