{
  "type": "Feature",
  "properties": {
    "iso:country":"DE",
    "sg:address":"Ammannstr. 15-17",
    "sg:city":"Garbsen",
    "sg:phone":"+49 511/435537",
    "sg:postcode":"30823",
    "sg:province":"Niedersachsen",
    "wof:name":"Fine Food Company Gmbh",
    "wof:placetype":"venue"
},
  "geometry": {"coordinates":[9.5674314499,52.4177284241],"type":"Point"}
}