{
  "type": "Feature",
  "properties": {
    "iso:country":"DE",
    "sg:address":"Neuer Weg 6",
    "sg:city":"Thale",
    "sg:phone":"+49 3947/61811",
    "sg:postcode":"06502",
    "sg:province":"Sachsen-Anhalt",
    "wof:name":"Christiane Breite",
    "wof:placetype":"venue"
},
  "geometry": {"coordinates":[11.0348110199,51.7529983521],"type":"Point"}
}