{
  "type": "Feature",
  "properties": {
    "iso:country":"DE",
    "sg:address":"Gr\u00fcner Weg 2",
    "sg:city":"Lohne",
    "sg:phone":"+49 4442/921133",
    "sg:postcode":"49393",
    "sg:province":"Niedersachsen",
    "wof:name":"Josef Schwerter",
    "wof:placetype":"venue"
},
  "geometry": {"coordinates":[8.2275972366,52.6724891663],"type":"Point"}
}