{
  "type": "Feature",
  "properties": {
    "iso:country":"DE",
    "sg:address":"Karbener Weg 8",
    "sg:city":"Karben",
    "sg:phone":"+49 6039/2506",
    "sg:postcode":"61184",
    "sg:province":"Hessen",
    "wof:name":"Markt-apotheke",
    "wof:placetype":"venue"
},
  "geometry": {"coordinates":[8.773611,50.23127],"type":"Point"}
}