{
  "type": "Feature",
  "properties": {
    "iso:country":"DE",
    "sg:address":"Irisweg 17",
    "sg:city":"Karlsruhe",
    "sg:phone":"+49 721/887931",
    "sg:postcode":"76199",
    "sg:province":"Baden-W\u00fcrttemberg",
    "wof:name":"Claus Brendel Architekt",
    "wof:placetype":"venue"
},
  "geometry": {"coordinates":[8.409535,48.978931],"type":"Point"}
}