{
  "type": "Feature",
  "properties": {
    "iso:country":"DE",
    "sg:address":"Ziegelstr. 4",
    "sg:city":"Drochtersen",
    "sg:phone":"+49 4148/1313",
    "sg:postcode":"21706",
    "sg:province":"Niedersachsen",
    "wof:name":"Klaus Erich Jagemann Seeschiffahrt-unternehmen",
    "wof:placetype":"venue"
},
  "geometry": {"coordinates":[9.445225,53.687408],"type":"Point"}
}