{
  "type": "Feature",
  "properties": {
    "iso:country":"DE",
    "sg:address":"Garstedter Weg 182",
    "sg:city":"Hamburg",
    "sg:postcode":"22455",
    "sg:province":"Hamburg",
    "wof:name":"Chinarestaurant Dynastie",
    "wof:placetype":"venue"
},
  "geometry": {"coordinates":[9.9648361206,53.6328315735],"type":"Point"}
}