{
  "type": "Feature",
  "properties": {
    "iso:country":"DE",
    "sg:address":"Haystr. 28",
    "sg:city":"Bad Sobernheim",
    "sg:phone":"+49 6751/5438",
    "sg:postcode":"55566",
    "sg:province":"Rheinland-Pfalz",
    "wof:name":"D. Stangenberg Autolackiererei",
    "wof:placetype":"venue"
},
  "geometry": {"coordinates":[7.630183,49.787258],"type":"Point"}
}