{
  "type": "Feature",
  "properties": {
    "iso:country":"DE",
    "sg:address":"Heckenweg 5",
    "sg:city":"Vreden",
    "sg:phone":"+49 2564/31117",
    "sg:postcode":"48691",
    "sg:province":"Nordrhein-Westfalen",
    "wof:name":"Wilhelm Schwanekamp",
    "wof:placetype":"venue"
},
  "geometry": {"coordinates":[6.815355,52.040718],"type":"Point"}
}