{
  "type": "Feature",
  "properties": {
    "iso:country":"DE",
    "sg:address":"Kannengie\u00dferstr. 11",
    "sg:city":"Braunschweig",
    "sg:phone":"+49 531/2404997",
    "sg:postcode":"38100",
    "sg:province":"Niedersachsen",
    "wof:name":"Etek Kniebel Gmbh",
    "wof:placetype":"venue"
},
  "geometry": {"coordinates":[10.519102,52.264477],"type":"Point"}
}