{
  "type": "Feature",
  "properties": {
    "iso:country":"DE",
    "sg:address":"Dr.-Kisselmann-Str. 9",
    "sg:city":"Peiting",
    "sg:phone":"+49 8861/66136",
    "sg:postcode":"86971",
    "sg:province":"Bayern",
    "wof:name":"Toni Strau\u00df",
    "wof:placetype":"venue"
},
  "geometry": {"coordinates":[10.937085,47.79443],"type":"Point"}
}