{
  "type": "Feature",
  "properties": {
    "iso:country":"DE",
    "sg:address":"Wilhelm-Leuschner-Str. 54",
    "sg:city":"Nauheim",
    "sg:phone":"+49 6152/6749",
    "sg:postcode":"64569",
    "sg:province":"Hessen",
    "wof:name":"Werner Mischlich",
    "wof:placetype":"venue"
},
  "geometry": {"coordinates":[8.45642,49.943043],"type":"Point"}
}