{
  "type": "Feature",
  "properties": {
    "iso:country":"DE",
    "sg:address":"Sch\u00f6nhausenstr. 15",
    "sg:city":"Bremen",
    "sg:phone":"+49 421/74792",
    "sg:postcode":"28203",
    "sg:province":"Bremen",
    "wof:name":"Bernd Collenbusch Steuerberater",
    "wof:placetype":"venue"
},
  "geometry": {"coordinates":[8.8293199539,53.076965332],"type":"Point"}
}