{
  "type": "Feature",
  "properties": {
    "iso:country":"DE",
    "sg:address":"Haselackstr. 9",
    "sg:city":"Schwerte",
    "sg:phone":"+49 2304/13478",
    "sg:postcode":"58239",
    "sg:province":"Nordrhein-Westfalen",
    "wof:name":"G. D\u00fcnnwald",
    "wof:placetype":"venue"
},
  "geometry": {"coordinates":[7.566404,51.442364],"type":"Point"}
}