{
  "type": "Feature",
  "properties": {
    "iso:country":"DE",
    "sg:address":"Lange Str. 4",
    "sg:city":"G\u00f6ppingen",
    "sg:phone":"+49 7161/70439",
    "sg:postcode":"73033",
    "sg:province":"Baden-W\u00fcrttemberg",
    "wof:name":"A. Freudenreich",
    "wof:placetype":"venue"
},
  "geometry": {"coordinates":[9.654258,48.702354],"type":"Point"}
}