{
  "type": "Feature",
  "properties": {
    "iso:country":"DE",
    "sg:address":"Lindenstr. 16 a",
    "sg:city":"Werneuchen",
    "sg:phone":"+49 33398/7427",
    "sg:postcode":"16356",
    "sg:province":"Brandenburg",
    "wof:name":"Klaus Finkelde",
    "wof:placetype":"venue"
},
  "geometry": {"coordinates":[13.7271881104,52.6378974915],"type":"Point"}
}