{
  "type": "Feature",
  "properties": {
    "iso:country":"DE",
    "sg:address":"Goldschmiedgasse 7",
    "sg:city":"Ellwangen",
    "sg:phone":"+49 7961/2295",
    "sg:postcode":"73479",
    "sg:province":"Baden-W\u00fcrttemberg",
    "wof:name":"Schindler Verwaltungs Gmbh",
    "wof:placetype":"venue"
},
  "geometry": {"coordinates":[10.1333045959,48.9606323242],"type":"Point"}
}