{
  "type": "Feature",
  "properties": {
    "iso:country":"DE",
    "sg:address":"Maierstr. 20",
    "sg:city":"Stuttgart",
    "sg:phone":"+49 711/714842",
    "sg:postcode":"70567",
    "sg:province":"Baden-W\u00fcrttemberg",
    "wof:name":"Albert Haist",
    "wof:placetype":"venue"
},
  "geometry": {"coordinates":[9.145126,48.727417],"type":"Point"}
}