{
  "type": "Feature",
  "properties": {
    "iso:country":"DE",
    "sg:address":"Lerchenweg 14",
    "sg:city":"Schmelz",
    "sg:postcode":"66839",
    "sg:province":"Saarland",
    "wof:name":"Ecologie Systems Ag",
    "wof:placetype":"venue"
},
  "geometry": {"coordinates":[6.857125,49.445583],"type":"Point"}
}