{
  "type": "Feature",
  "properties": {
    "iso:country":"DE",
    "sg:address":"Mittelstr. 73",
    "sg:city":"Lahnstein",
    "sg:phone":"+49 2621/2044",
    "sg:postcode":"56112",
    "sg:province":"Rheinland-Pfalz",
    "wof:name":"Gothaer Versicherungsbank Vvag",
    "wof:placetype":"venue"
},
  "geometry": {"coordinates":[7.6098971367,50.2987670898],"type":"Point"}
}