{
  "type": "Feature",
  "properties": {
    "iso:country":"DE",
    "sg:address":"Genthiner Str. 8",
    "sg:city":"Berlin",
    "sg:phone":"+49 30/21752304",
    "sg:postcode":"10785",
    "sg:province":"Berlin",
    "wof:name":"Berlin Press G\u00f6tz & Zwangsleitner",
    "wof:placetype":"venue"
},
  "geometry": {"coordinates":[13.359912,52.505077],"type":"Point"}
}