{
  "type": "Feature",
  "properties": {
    "iso:country":"DE",
    "sg:address":"T\u00e4ubchenstr. 15",
    "sg:city":"Berlin",
    "sg:phone":"+49 30/8132055",
    "sg:postcode":"14163",
    "sg:province":"Berlin",
    "wof:name":"Helmut Bahle Steuerberater",
    "wof:placetype":"venue"
},
  "geometry": {"coordinates":[13.2356843948,52.4480476379],"type":"Point"}
}