{
  "type": "Feature",
  "properties": {
    "iso:country":"DE",
    "sg:address":"17 Cit\u00e9 Moynet",
    "sg:city":"PARIS",
    "sg:phone":"+49 140049350",
    "sg:postcode":"75012",
    "wof:name":"Paris Trampoline 12",
    "wof:placetype":"venue"
},
  "geometry": {"coordinates":[2.38657,48.843891],"type":"Point"}
}