{
  "type": "Feature",
  "properties": {
    "iso:country":"DE",
    "sg:address":"Schnorrstr. 3b",
    "sg:city":"Leipzig",
    "sg:phone":"+49 341/4805124",
    "sg:postcode":"04229",
    "sg:province":"Sachsen",
    "wof:name":"C. Matthia",
    "wof:placetype":"venue"
},
  "geometry": {"coordinates":[12.3442754745,51.3196525574],"type":"Point"}
}