{
  "type": "Feature",
  "properties": {
    "iso:country":"DE",
    "sg:address":"Niederwall 26",
    "sg:city":"Bielefeld",
    "sg:phone":"+49 521/54701",
    "sg:postcode":"33602",
    "sg:province":"Nordrhein-Westfalen",
    "wof:name":"Westdeutsche Landesbank Girozentrale",
    "wof:placetype":"venue"
},
  "geometry": {"coordinates":[8.5322589874,52.0221977234],"type":"Point"}
}