{
  "type": "Feature",
  "properties": {
    "iso:country":"DE",
    "sg:address":"Am Westring 1a",
    "sg:city":"Saulheim",
    "sg:phone":"+49 6732/8424",
    "sg:postcode":"55291",
    "sg:province":"Rheinland-Pfalz",
    "wof:name":"Grafik . Design . Architektur",
    "wof:placetype":"venue"
},
  "geometry": {"coordinates":[8.1473798752,49.8712348938],"type":"Point"}
}