{
  "type": "Feature",
  "properties": {
    "iso:country":"DE",
    "sg:address":"Leihb\u00fchl 25",
    "sg:city":"Lichtenau",
    "sg:phone":"+49 5295/998080",
    "sg:postcode":"33165",
    "sg:province":"Nordrhein-Westfalen",
    "wof:name":"M\u00d6hring U. Droll Gbr",
    "wof:placetype":"venue"
},
  "geometry": {"coordinates":[8.8856916428,51.6219062805],"type":"Point"}
}