{
  "type": "Feature",
  "properties": {
    "iso:country":"DE",
    "sg:address":"T\u00f6pferstr. 48",
    "sg:city":"Linnich",
    "sg:phone":"+49 2462/8673",
    "sg:postcode":"52441",
    "sg:province":"Nordrhein-Westfalen",
    "wof:name":"J. Meyer",
    "wof:placetype":"venue"
},
  "geometry": {"coordinates":[6.218883,50.957478],"type":"Point"}
}