{
  "type": "Feature",
  "properties": {
    "iso:country":"DE",
    "sg:address":"Rollinstr. 23",
    "sg:city":"Biberach",
    "sg:phone":"+49 7351/28146",
    "sg:postcode":"88400",
    "sg:province":"Baden-W\u00fcrttemberg",
    "wof:name":"Luca Nuic Gmbh",
    "wof:placetype":"venue"
},
  "geometry": {"coordinates":[9.7936677933,48.0932998657],"type":"Point"}
}