{
  "type": "Feature",
  "properties": {
    "iso:country":"DE",
    "sg:address":"D\u00f6rner Str. 5",
    "sg:city":"Wiehl",
    "sg:phone":"+49 2262/93164",
    "sg:postcode":"51674",
    "sg:province":"Nordrhein-Westfalen",
    "wof:name":"Rolf Kluxen Tiefbau Gmbh",
    "wof:placetype":"venue"
},
  "geometry": {"coordinates":[7.5446929932,50.9461250305],"type":"Point"}
}