{
  "type": "Feature",
  "properties": {
    "iso:country":"DE",
    "sg:address":"Obere Remscheider Str. 26",
    "sg:city":"Wermelskirchen",
    "sg:phone":"+49 2196/1611",
    "sg:postcode":"42929",
    "sg:province":"Nordrhein-Westfalen",
    "wof:name":"Jutta Petri Massagepraxis",
    "wof:placetype":"venue"
},
  "geometry": {"coordinates":[7.215515,51.141876],"type":"Point"}
}