{
  "type": "Feature",
  "properties": {
    "iso:country":"DE",
    "sg:address":"August-Pfaltz-Str. 31",
    "sg:city":"Dachau",
    "sg:phone":"+49 8131/368530",
    "sg:postcode":"85221",
    "sg:province":"Bayern",
    "wof:name":"A. Hartmann Steuerberater",
    "wof:placetype":"venue"
},
  "geometry": {"coordinates":[11.4316110611,48.2506446838],"type":"Point"}
}