{
  "type": "Feature",
  "properties": {
    "iso:country":"DE",
    "sg:address":"Schlesienstr. 18",
    "sg:city":"Bad Berleburg",
    "sg:phone":"+49 2751/5958",
    "sg:postcode":"57319",
    "sg:province":"Nordrhein-Westfalen",
    "wof:name":"Friedhelm Limper",
    "wof:placetype":"venue"
},
  "geometry": {"coordinates":[8.3476600647,51.0360984802],"type":"Point"}
}