{
  "type": "Feature",
  "properties": {
    "iso:country":"DE",
    "sg:address":"Merkurweg 11",
    "sg:city":"Schwalmtal",
    "sg:phone":"+49 2163/2337",
    "sg:postcode":"41366",
    "sg:province":"Nordrhein-Westfalen",
    "wof:name":"Erich Hilgers Architekt",
    "wof:placetype":"venue"
},
  "geometry": {"coordinates":[6.242718,51.225925],"type":"Point"}
}