{
  "type": "Feature",
  "properties": {
    "iso:country":"DE",
    "sg:address":"Hermann-Behn-Weg 16",
    "sg:city":"Hamburg",
    "sg:phone":"+49 40/4140140",
    "sg:postcode":"20146",
    "sg:province":"Hamburg",
    "wof:name":"Arno M\u00f6hring Architekt",
    "wof:placetype":"venue"
},
  "geometry": {"coordinates":[9.986588,53.571632],"type":"Point"}
}