{
  "type": "Feature",
  "properties": {
    "iso:country":"DE",
    "sg:address":"Sonnenweg 5",
    "sg:city":"Dierdorf",
    "sg:phone":"+49 2689/3537",
    "sg:postcode":"56269",
    "sg:province":"Rheinland-Pfalz",
    "wof:name":"Harald Pitzen Ingenieur",
    "wof:placetype":"venue"
},
  "geometry": {"coordinates":[7.6643519402,50.549118042],"type":"Point"}
}