{
  "type": "Feature",
  "properties": {
    "iso:country":"DE",
    "sg:address":"Altenbekener Damm 13",
    "sg:city":"Hannover",
    "sg:phone":"+49 511/8091924",
    "sg:postcode":"30173",
    "sg:province":"Niedersachsen",
    "wof:name":"Eiscafe Bunny",
    "wof:placetype":"venue"
},
  "geometry": {"coordinates":[9.765358,52.357269],"type":"Point"}
}