{
  "type": "Feature",
  "properties": {
    "iso:country":"DE",
    "sg:address":"Carl-Bertelsmann-Str. 270",
    "sg:city":"G\u00fctersloh",
    "sg:phone":"+49 5241/800",
    "sg:postcode":"33335",
    "sg:province":"Nordrhein-Westfalen",
    "wof:name":"Adler Immobilien- Verwaltungs Gmbh",
    "wof:placetype":"venue"
},
  "geometry": {"coordinates":[8.4209165573,51.9099578857],"type":"Point"}
}