{
  "type": "Feature",
  "properties": {
    "iso:country":"DE",
    "sg:address":"Altenh\u00e4ger Str. 19",
    "sg:city":"Hagenburg",
    "sg:phone":"+49 5033/7706",
    "sg:postcode":"31558",
    "sg:province":"Niedersachsen",
    "wof:name":"Axel Fl\u00f6gel",
    "wof:placetype":"venue"
},
  "geometry": {"coordinates":[9.3276700974,52.4343185425],"type":"Point"}
}