{
  "type": "Feature",
  "properties": {
    "iso:country":"DE",
    "sg:address":"Rodenkircherwurp",
    "sg:city":"Stadland",
    "sg:phone":"+49 4732/2602",
    "sg:postcode":"26935",
    "sg:province":"Niedersachsen",
    "wof:name":"Am Markt",
    "wof:placetype":"venue"
},
  "geometry": {"coordinates":[8.3732976913,53.4072990417],"type":"Point"}
}