{
  "type": "Feature",
  "properties": {
    "iso:country":"DE",
    "sg:address":"Mainzer Str. 28",
    "sg:city":"Oppenheim",
    "sg:phone":"+49 6133/2259",
    "sg:postcode":"55276",
    "sg:province":"Rheinland-Pfalz",
    "wof:name":"K\u00f6th-kuhn Weinanbau",
    "wof:placetype":"venue"
},
  "geometry": {"coordinates":[8.3568000793,49.8538284302],"type":"Point"}
}