{
  "type": "Feature",
  "properties": {
    "iso:country":"DE",
    "sg:address":"Grabenstr. 13",
    "sg:city":"Heimsheim",
    "sg:phone":"+49 7033/31927",
    "sg:postcode":"71296",
    "sg:province":"Baden-W\u00fcrttemberg",
    "wof:name":"Carpent Gmbh",
    "wof:placetype":"venue"
},
  "geometry": {"coordinates":[8.8643798828,48.8064994812],"type":"Point"}
}