{
  "type": "Feature",
  "properties": {
    "iso:country":"DE",
    "sg:address":"M\u00fchlenweg 42",
    "sg:city":"Buchholz",
    "sg:postcode":"21244",
    "sg:province":"Niedersachsen",
    "wof:name":"Maschinenring Mansfelder Land Dr. Jochen Vehring",
    "wof:placetype":"venue"
},
  "geometry": {"coordinates":[9.8164796829,53.313621521],"type":"Point"}
}