{
  "type": "Feature",
  "properties": {
    "iso:country":"DE",
    "sg:address":"D\u00fcrnkonreuth 11",
    "sg:city":"Pl\u00f6\u00dfberg",
    "sg:phone":"+49 9636/277",
    "sg:postcode":"95703",
    "sg:province":"Bayern",
    "wof:name":"Michael Wolfrum",
    "wof:placetype":"venue"
},
  "geometry": {"coordinates":[12.351823,49.816475],"type":"Point"}
}