{
  "type": "Feature",
  "properties": {
    "iso:country":"DE",
    "sg:address":"Taubenheimstr. 26",
    "sg:city":"Stuttgart",
    "sg:phone":"+49 711/9559140",
    "sg:postcode":"70372",
    "sg:province":"Baden-W\u00fcrttemberg",
    "wof:name":"Promotec Gmbh",
    "wof:placetype":"venue"
},
  "geometry": {"coordinates":[9.2259750366,48.8056106567],"type":"Point"}
}