{
  "type": "Feature",
  "properties": {
    "iso:country":"DE",
    "sg:address":"Im Gei\u00dfengrund 8",
    "sg:city":"Bischofsheim",
    "sg:phone":"+49 9772/1010",
    "sg:postcode":"97653",
    "sg:province":"Bayern",
    "wof:name":"Edmund P\u00e4ckert Immobilienmakler",
    "wof:placetype":"venue"
},
  "geometry": {"coordinates":[9.9937953949,50.3963317871],"type":"Point"}
}