{
  "type": "Feature",
  "properties": {
    "iso:country":"DE",
    "sg:address":"Aberlin-J\u00f6rg-Str. 20",
    "sg:city":"Stuttgart",
    "sg:phone":"+49 711/551677",
    "sg:postcode":"70372",
    "sg:province":"Baden-W\u00fcrttemberg",
    "wof:name":"Safetec It-systeme Vertriebsgesellschaft Mbh",
    "wof:placetype":"venue"
},
  "geometry": {"coordinates":[9.230123,48.80135],"type":"Point"}
}