{
  "type": "Feature",
  "properties": {
    "iso:country":"DE",
    "sg:address":"Garbenpfad 14 a",
    "sg:city":"Berlin",
    "sg:phone":"+49 30/5412601",
    "sg:postcode":"12683",
    "sg:province":"Berlin",
    "wof:name":"Dietrich Pott Ingenieur",
    "wof:placetype":"venue"
},
  "geometry": {"coordinates":[13.5607185364,52.5148544312],"type":"Point"}
}