{
  "type": "Feature",
  "properties": {
    "iso:country":"DE",
    "sg:address":"Podbielskistr. 185",
    "sg:city":"Hannover",
    "sg:phone":"+49 511/6963322",
    "sg:postcode":"30177",
    "sg:province":"Niedersachsen",
    "wof:name":"B\u00fclow",
    "wof:placetype":"venue"
},
  "geometry": {"coordinates":[9.7772083282,52.3992996216],"type":"Point"}
}