{
  "type": "Feature",
  "properties": {
    "iso:country":"DE",
    "sg:address":"Walckerstr. 10",
    "sg:city":"Stuttgart",
    "sg:phone":"+49 711/560024",
    "sg:postcode":"70374",
    "sg:province":"Baden-W\u00fcrttemberg",
    "wof:name":"Volkmar M\u00fcller Ingenieur",
    "wof:placetype":"venue"
},
  "geometry": {"coordinates":[9.2303056717,48.8121185303],"type":"Point"}
}