{
  "type": "Feature",
  "properties": {
    "iso:country":"DE",
    "sg:address":"Alte Dorfstr. 2",
    "sg:city":"Rinteln",
    "sg:phone":"+49 5262/3757",
    "sg:postcode":"31737",
    "sg:province":"Niedersachsen",
    "wof:name":"K. Zacharias",
    "wof:placetype":"venue"
},
  "geometry": {"coordinates":[9.153377533,52.1033821106],"type":"Point"}
}