{
  "type": "Feature",
  "properties": {
    "iso:country":"DE",
    "sg:address":"Nahariyastr. 1",
    "sg:city":"Bielefeld",
    "sg:postcode":"33602",
    "sg:province":"Nordrhein-Westfalen",
    "wof:name":"Deutsche Post Ag",
    "wof:placetype":"venue"
},
  "geometry": {"coordinates":[8.535610199,52.029838562],"type":"Point"}
}