{
  "type": "Feature",
  "properties": {
    "iso:country":"DE",
    "sg:address":"Waldstr. 61",
    "sg:city":"Nauheim",
    "sg:phone":"+49 6152/97400",
    "sg:postcode":"64569",
    "sg:province":"Hessen",
    "wof:name":"Comtek Computer Und Kommunikationssysteme Gmbh",
    "wof:placetype":"venue"
},
  "geometry": {"coordinates":[8.4581546783,49.9517707825],"type":"Point"}
}