{
  "type": "Feature",
  "properties": {
    "iso:country":"DE",
    "sg:address":"Goslarer Str. 101",
    "sg:city":"Stuttgart",
    "sg:postcode":"70499",
    "sg:province":"Baden-W\u00fcrttemberg",
    "wof:name":"Orianda Solutions Ag",
    "wof:placetype":"venue"
},
  "geometry": {"coordinates":[9.1254825592,48.8162727356],"type":"Point"}
}