{
  "type": "Feature",
  "properties": {
    "iso:country":"DE",
    "sg:address":"Neckargasse 12",
    "sg:city":"Benningen",
    "sg:phone":"+49 7144/5785",
    "sg:postcode":"71726",
    "sg:province":"Baden-W\u00fcrttemberg",
    "wof:name":"Christel Scheichenbauer Hebamme",
    "wof:placetype":"venue"
},
  "geometry": {"coordinates":[9.243814,48.947742],"type":"Point"}
}