{
  "type": "Feature",
  "properties": {
    "iso:country":"DE",
    "sg:address":"Hallstadter Str. 5",
    "sg:city":"Kemmern",
    "sg:phone":"+49 9544/7542",
    "sg:postcode":"96164",
    "sg:province":"Bayern",
    "wof:name":"G. Eichhorn",
    "wof:placetype":"venue"
},
  "geometry": {"coordinates":[10.878412,49.952122],"type":"Point"}
}