{
  "type": "Feature",
  "properties": {
    "iso:country":"DE",
    "sg:address":"Bahnhofstr. 113",
    "sg:city":"Neu-Isenburg",
    "sg:phone":"+49 6102/22657",
    "sg:postcode":"63263",
    "sg:province":"Hessen",
    "wof:name":"Annelie Haas",
    "wof:placetype":"venue"
},
  "geometry": {"coordinates":[8.684934,50.053299],"type":"Point"}
}