{
  "type": "Feature",
  "properties": {
    "iso:country":"DE",
    "sg:address":"Wilhelm-Bakker-Str. 21",
    "sg:city":"Borkum",
    "sg:phone":"+49 4922/2193",
    "sg:postcode":"26757",
    "sg:province":"Niedersachsen",
    "wof:name":"Pension Hildegard Akkermann",
    "wof:placetype":"venue"
},
  "geometry": {"coordinates":[6.6685352325,53.5878067017],"type":"Point"}
}