{
  "type": "Feature",
  "properties": {
    "iso:country":"DE",
    "sg:address":"Prinz-Ludwig-Str. 13",
    "sg:city":"Waldsassen",
    "sg:phone":"+49 9632/8571",
    "sg:postcode":"95652",
    "sg:province":"Bayern",
    "wof:name":"Vvb Velhorn Verwaltungs- Und Beteiligungs Gmbh",
    "wof:placetype":"venue"
},
  "geometry": {"coordinates":[12.30422,50.003262],"type":"Point"}
}