{
  "type": "Feature",
  "properties": {
    "iso:country":"DE",
    "sg:address":"Marborner Warte 1",
    "sg:city":"Steinau",
    "sg:phone":"+49 6663/919150",
    "sg:postcode":"36396",
    "sg:province":"Hessen",
    "wof:name":"Km Kinzig-m\u00f6rtel Gmbh",
    "wof:placetype":"venue"
},
  "geometry": {"coordinates":[9.4340219498,50.315448761],"type":"Point"}
}