{
  "type": "Feature",
  "properties": {
    "iso:country":"DE",
    "sg:address":"Ursheim",
    "sg:city":"Polsingen",
    "sg:phone":"+49 9093/256",
    "sg:postcode":"91805",
    "sg:province":"Bayern",
    "wof:name":"Friedrich Heinlein",
    "wof:placetype":"venue"
},
  "geometry": {"coordinates":[10.7168903351,48.9387283325],"type":"Point"}
}