{
  "type": "Feature",
  "properties": {
    "iso:country":"DE",
    "sg:address":"Prinze\u00df-Luise-Str. 36",
    "sg:city":"M\u00fclheim",
    "sg:phone":"+49 208/420931",
    "sg:postcode":"45479",
    "sg:province":"Nordrhein-Westfalen",
    "wof:name":"Heinz Fraune",
    "wof:placetype":"venue"
},
  "geometry": {"coordinates":[6.862195015,51.4246177673],"type":"Point"}
}