{
  "type": "Feature",
  "properties": {
    "iso:country":"DE",
    "sg:address":"Hannoversche Str. 55",
    "sg:city":"G\u00f6ttingen",
    "sg:phone":"+49 551/389080",
    "sg:postcode":"37075",
    "sg:province":"Niedersachsen",
    "wof:name":"Ruhe & Co. Gmbh & Co.",
    "wof:placetype":"venue"
},
  "geometry": {"coordinates":[9.9845619202,51.540599823],"type":"Point"}
}