{
  "type": "Feature",
  "properties": {
    "iso:country":"DE",
    "sg:address":"Langen\u00e4cker 6",
    "sg:city":"Rauenberg",
    "sg:postcode":"69231",
    "sg:province":"Baden-W\u00fcrttemberg",
    "wof:name":"Aldi Gmbh & Co. Kg",
    "wof:placetype":"venue"
},
  "geometry": {"coordinates":[8.7050800323,49.2647895813],"type":"Point"}
}