{
  "type": "Feature",
  "properties": {
    "iso:country":"DE",
    "sg:address":"Grassauer Str. 6",
    "sg:city":"\u00dcbersee",
    "sg:phone":"+49 8642/6826",
    "sg:postcode":"83236",
    "sg:province":"Bayern",
    "wof:name":"Norbert Kubiak Bauingenieur",
    "wof:placetype":"venue"
},
  "geometry": {"coordinates":[12.481127739,47.8196907043],"type":"Point"}
}