{
  "type": "Feature",
  "properties": {
    "iso:country":"DE",
    "sg:address":"Steinst\u00fccke 4a",
    "sg:city":"Syke",
    "sg:postcode":"28857",
    "sg:province":"Niedersachsen",
    "wof:name":"Sascha Lahr Gmbh",
    "wof:placetype":"venue"
},
  "geometry": {"coordinates":[8.869945,52.941151],"type":"Point"}
}