{
  "type": "Feature",
  "properties": {
    "iso:country":"DE",
    "sg:address":"Alte Bundesstr. 5",
    "sg:city":"Burgdorf",
    "sg:phone":"+49 5085/7916",
    "sg:postcode":"31303",
    "sg:province":"Niedersachsen",
    "wof:name":"Gastst\u00e4tte Baloo",
    "wof:placetype":"venue"
},
  "geometry": {"coordinates":[10.0305433273,52.5234565735],"type":"Point"}
}