{
  "type": "Feature",
  "properties": {
    "iso:country":"DE",
    "sg:address":"Schulstr. 32",
    "sg:city":"Einselthum",
    "sg:phone":"+49 6355/3836",
    "sg:postcode":"67308",
    "sg:province":"Rheinland-Pfalz",
    "wof:name":"A. Hofmann",
    "wof:placetype":"venue"
},
  "geometry": {"coordinates":[8.1230487823,49.6495437622],"type":"Point"}
}