{
  "type": "Feature",
  "properties": {
    "iso:country":"DE",
    "sg:address":"Poststr. 19",
    "sg:city":"Kaisersesch",
    "sg:phone":"+49 2653/6926",
    "sg:postcode":"56759",
    "sg:province":"Rheinland-Pfalz",
    "wof:name":"W. G. Thiel",
    "wof:placetype":"venue"
},
  "geometry": {"coordinates":[7.139263,50.230122],"type":"Point"}
}