{
  "type": "Feature",
  "properties": {
    "iso:country":"DE",
    "sg:address":"Friedrich-Engels-Str. 1",
    "sg:city":"Kurort Oybin",
    "sg:phone":"+49 35844/70221",
    "sg:postcode":"02797",
    "sg:province":"Sachsen",
    "wof:name":"Oybintal",
    "wof:placetype":"venue"
},
  "geometry": {"coordinates":[14.7465496063,50.8457298279],"type":"Point"}
}