{
  "type": "Feature",
  "properties": {
    "iso:country":"DE",
    "sg:address":"Gatower Str. 108",
    "sg:city":"Berlin",
    "sg:phone":"+49 30/3519040",
    "sg:postcode":"13595",
    "sg:province":"Berlin",
    "wof:name":"Perform Ges. F. Organisation Software U. Datenverarbeitung",
    "wof:placetype":"venue"
},
  "geometry": {"coordinates":[13.1812000275,52.5108261108],"type":"Point"}
}