{
  "type": "Feature",
  "properties": {
    "iso:country":"DE",
    "sg:address":"Chemnitzer Str. 22",
    "sg:city":"Frankenberg",
    "sg:phone":"+49 37206/75688",
    "sg:postcode":"09669",
    "sg:province":"Sachsen",
    "wof:name":"M. Poser",
    "wof:placetype":"venue"
},
  "geometry": {"coordinates":[13.0307102203,50.910030365],"type":"Point"}
}