{
  "type": "Feature",
  "properties": {
    "iso:country":"DE",
    "sg:address":"Hasenberglstr. 64",
    "sg:city":"M\u00fcnchen",
    "sg:phone":"+49 89/31215770",
    "sg:postcode":"80933",
    "sg:province":"Bayern",
    "wof:name":"Donth Ep Com Gmbh",
    "wof:placetype":"venue"
},
  "geometry": {"coordinates":[11.5604467392,48.2099761963],"type":"Point"}
}