{
  "type": "Feature",
  "properties": {
    "iso:country":"DE",
    "sg:address":"Talblick 23",
    "sg:city":"Zwickau",
    "sg:phone":"+49 375/799446",
    "sg:postcode":"08064",
    "sg:province":"Sachsen",
    "wof:name":"Povenz",
    "wof:placetype":"venue"
},
  "geometry": {"coordinates":[12.476162,50.661964],"type":"Point"}
}