{
  "type": "Feature",
  "properties": {
    "iso:country":"DE",
    "sg:address":"Bitterfelder Str. 6",
    "sg:city":"Leipzig",
    "sg:phone":"+49 341/566640",
    "sg:postcode":"04129",
    "sg:province":"Sachsen",
    "wof:name":"Krankentransport Ost-west Gmbh",
    "wof:placetype":"venue"
},
  "geometry": {"coordinates":[12.390841,51.356918],"type":"Point"}
}