{
  "type": "Feature",
  "properties": {
    "iso:country":"DE",
    "sg:address":"Zu den Ohlwiesen 11",
    "sg:city":"Arnsberg",
    "sg:phone":"+49 2932/39666",
    "sg:postcode":"59755",
    "sg:province":"Nordrhein-Westfalen",
    "wof:name":"Sonntag Datentechnik Gmbh",
    "wof:placetype":"venue"
},
  "geometry": {"coordinates":[7.949488163,51.4634361267],"type":"Point"}
}