{
  "type": "Feature",
  "properties": {
    "iso:country":"DE",
    "sg:address":"Umgehungsstr. 469",
    "sg:city":"Stockstadt",
    "sg:phone":"+49 6027/7416",
    "sg:postcode":"63811",
    "sg:province":"Bayern",
    "wof:name":"Werner H\u00fchnlein",
    "wof:placetype":"venue"
},
  "geometry": {"coordinates":[9.0641546249,49.9795608521],"type":"Point"}
}