{
  "type": "Feature",
  "properties": {
    "iso:country":"DE",
    "sg:address":"Rathausweg 6",
    "sg:city":"Ulm",
    "sg:phone":"+49 731/51552",
    "sg:postcode":"89081",
    "sg:province":"Baden-W\u00fcrttemberg",
    "wof:name":"R\u00f6ssle",
    "wof:placetype":"venue"
},
  "geometry": {"coordinates":[9.9399013519,48.4367141724],"type":"Point"}
}