{
  "type": "Feature",
  "properties": {
    "iso:country":"DE",
    "sg:address":"Antoniusstr. 27",
    "sg:city":"Lingen",
    "sg:phone":"+49 591/47811",
    "sg:postcode":"49811",
    "sg:province":"Niedersachsen",
    "wof:name":"W. Meemann",
    "wof:placetype":"venue"
},
  "geometry": {"coordinates":[7.4062571526,52.5141868591],"type":"Point"}
}