{
  "type": "Feature",
  "properties": {
    "iso:country":"DE",
    "sg:address":"Neum\u00fchlenallee 21",
    "sg:city":"Borken",
    "sg:phone":"+49 2861/91747",
    "sg:postcode":"46325",
    "sg:province":"Nordrhein-Westfalen",
    "wof:name":"Walter Hemsteg",
    "wof:placetype":"venue"
},
  "geometry": {"coordinates":[6.860928,51.860195],"type":"Point"}
}