{
  "type": "Feature",
  "properties": {
    "iso:country":"DE",
    "sg:address":"An der Untertrave 17",
    "sg:city":"L\u00fcbeck",
    "sg:phone":"+49 451/798820",
    "sg:postcode":"23552",
    "sg:province":"Schleswig-Holstein",
    "wof:name":"Tr\u00fcper Gondesen Und Partner Tgp",
    "wof:placetype":"venue"
},
  "geometry": {"coordinates":[10.686506,53.873508],"type":"Point"}
}