{
  "type": "Feature",
  "properties": {
    "iso:country":"DE",
    "sg:address":"Achternstr. 24",
    "sg:city":"Oldenburg",
    "sg:phone":"+49 441/25215",
    "sg:postcode":"26122",
    "sg:province":"Niedersachsen",
    "wof:name":"H. Kock",
    "wof:placetype":"venue"
},
  "geometry": {"coordinates":[8.21143,53.13868],"type":"Point"}
}