{
  "type": "Feature",
  "properties": {
    "iso:country":"DE",
    "sg:address":"Kehrstr. 6",
    "sg:city":"G\u00f6ttingen",
    "sg:phone":"+49 551/793031",
    "sg:postcode":"37085",
    "sg:province":"Niedersachsen",
    "wof:name":"G\u00d6-immobilien Gmbh",
    "wof:placetype":"venue"
},
  "geometry": {"coordinates":[9.9565582275,51.5145111084],"type":"Point"}
}