{
  "type": "Feature",
  "properties": {
    "iso:country":"DE",
    "sg:address":"L\u00fctzner Str. 66",
    "sg:city":"Leipzig",
    "sg:phone":"+49 341/4774524",
    "sg:postcode":"04177",
    "sg:province":"Sachsen",
    "wof:name":"Frankfurter Allgemeine Zeitung Gmbh",
    "wof:placetype":"venue"
},
  "geometry": {"coordinates":[12.3308801651,51.3359489441],"type":"Point"}
}