{
  "type": "Feature",
  "properties": {
    "iso:country":"DE",
    "sg:address":"Wasserweg 2 a",
    "sg:city":"Veltheim",
    "sg:phone":"+49 5305/3495",
    "sg:postcode":"38173",
    "sg:province":"Niedersachsen",
    "wof:name":"U. Ahlswede",
    "wof:placetype":"venue"
},
  "geometry": {"coordinates":[10.687662,52.217411],"type":"Point"}
}