{
  "type": "Feature",
  "properties": {
    "iso:country":"DE",
    "sg:address":"Hermannstr. 46",
    "sg:city":"Bad Lippspringe",
    "sg:phone":"+49 5252/4214",
    "sg:postcode":"33175",
    "sg:province":"Nordrhein-Westfalen",
    "wof:name":"Asb Spielbetriebe Gmbh",
    "wof:placetype":"venue"
},
  "geometry": {"coordinates":[8.8233308792,51.7908668518],"type":"Point"}
}