{
  "type": "Feature",
  "properties": {
    "iso:country":"DE",
    "sg:address":"Im Neuen Felde 3",
    "sg:city":"Langwedel",
    "sg:phone":"+49 4232/7961",
    "sg:postcode":"27299",
    "sg:province":"Niedersachsen",
    "wof:name":"Meinhard Jungenkr\u00fcger",
    "wof:placetype":"venue"
},
  "geometry": {"coordinates":[9.228754,53.001503],"type":"Point"}
}