{
  "type": "Feature",
  "properties": {
    "iso:country":"DE",
    "sg:address":"Rumbachtal 46",
    "sg:city":"M\u00fclheim",
    "sg:phone":"+49 208/370277",
    "sg:postcode":"45470",
    "sg:province":"Nordrhein-Westfalen",
    "wof:name":"W. Hellebrandt",
    "wof:placetype":"venue"
},
  "geometry": {"coordinates":[6.917334,51.424084],"type":"Point"}
}