{
  "type": "Feature",
  "properties": {
    "iso:country":"DE",
    "sg:address":"Julius-Leber-Str. 37",
    "sg:city":"Aalen",
    "sg:phone":"+49 7361/6301",
    "sg:postcode":"73430",
    "sg:province":"Baden-W\u00fcrttemberg",
    "wof:name":"Pinocchio",
    "wof:placetype":"venue"
},
  "geometry": {"coordinates":[10.0904579163,48.8345451355],"type":"Point"}
}