{
  "type": "Feature",
  "properties": {
    "iso:country":"DE",
    "sg:address":"Kohlh\u00f6kerstr. 10",
    "sg:city":"Bremen",
    "sg:postcode":"28203",
    "sg:province":"Bremen",
    "wof:name":"Planungswerkstatt F\u00fcr Stadt- Entwicklung E. V.",
    "wof:placetype":"venue"
},
  "geometry": {"coordinates":[8.8188619614,53.0746650696],"type":"Point"}
}