{
  "type": "Feature",
  "properties": {
    "iso:country":"DE",
    "sg:address":"Dahler Str. 45",
    "sg:city":"Solingen",
    "sg:phone":"+49 212/2541442",
    "sg:postcode":"42653",
    "sg:province":"Nordrhein-Westfalen",
    "wof:name":"Isenburg Immobilienmakler",
    "wof:placetype":"venue"
},
  "geometry": {"coordinates":[7.0717310905,51.1955375671],"type":"Point"}
}