{
  "type": "Feature",
  "properties": {
    "iso:country":"DE",
    "sg:address":"Hessenstr. 1",
    "sg:city":"Langenhagen",
    "sg:phone":"+49 511/786300",
    "sg:postcode":"30855",
    "sg:province":"Niedersachsen",
    "wof:name":"Handelsagentur Lehmann Ohg",
    "wof:placetype":"venue"
},
  "geometry": {"coordinates":[9.7112150192,52.442024231],"type":"Point"}
}