{
  "type": "Feature",
  "properties": {
    "iso:country":"DE",
    "sg:address":"Raiffeisenring 11-13",
    "sg:city":"Bocholt",
    "sg:phone":"+49 2871/9960",
    "sg:postcode":"46395",
    "sg:province":"Nordrhein-Westfalen",
    "wof:name":"Stil-glas Gmbh & Co. Kg",
    "wof:placetype":"venue"
},
  "geometry": {"coordinates":[6.56453,51.814796],"type":"Point"}
}