{
  "type": "Feature",
  "properties": {
    "iso:country":"DE",
    "sg:address":"Hauptstr. 25",
    "sg:city":"Bad Rodach",
    "sg:phone":"+49 9564/1850",
    "sg:postcode":"96476",
    "sg:province":"Bayern",
    "wof:name":"F\u00f6rstersch\u00e4nke",
    "wof:placetype":"venue"
},
  "geometry": {"coordinates":[10.8018093109,50.3566017151],"type":"Point"}
}