{
  "type": "Feature",
  "properties": {
    "iso:country":"DE",
    "sg:address":"N\u00fcrnberger Str. 5",
    "sg:city":"Pegnitz",
    "sg:phone":"+49 9241/8292",
    "sg:postcode":"91257",
    "sg:province":"Bayern",
    "wof:name":"Waltraud Eckert",
    "wof:placetype":"venue"
},
  "geometry": {"coordinates":[11.5372610092,49.7538566589],"type":"Point"}
}