{
  "type": "Feature",
  "properties": {
    "iso:country":"DE",
    "sg:address":"P\u00f6hlenweg 44",
    "sg:city":"D\u00fcsseldorf",
    "sg:postcode":"40629",
    "sg:province":"Nordrhein-Westfalen",
    "wof:name":"Hans-walter Schmitz Architekt",
    "wof:placetype":"venue"
},
  "geometry": {"coordinates":[6.836489,51.238171],"type":"Point"}
}