{
  "type": "Feature",
  "properties": {
    "iso:country":"DE",
    "sg:address":"Alt-Tempelhof 9 a",
    "sg:city":"Berlin",
    "sg:phone":"+49 30/75764455",
    "sg:postcode":"12099",
    "sg:province":"Berlin",
    "wof:name":"Eberhard Brunner Elektro-inst.-meister",
    "wof:placetype":"venue"
},
  "geometry": {"coordinates":[13.387711,52.465618],"type":"Point"}
}