{
  "type": "Feature",
  "properties": {
    "iso:country":"DE",
    "sg:address":"Hohenhorster Str. 33",
    "sg:city":"Bocholt",
    "sg:phone":"+49 2871/5228",
    "sg:postcode":"46397",
    "sg:province":"Nordrhein-Westfalen",
    "wof:name":"Johannes Telohe",
    "wof:placetype":"venue"
},
  "geometry": {"coordinates":[6.648679,51.829254],"type":"Point"}
}