{
  "type": "Feature",
  "properties": {
    "iso:country":"DE",
    "sg:address":"Helvesieker Weg 37",
    "sg:city":"Schee\u00dfel",
    "sg:postcode":"27383",
    "sg:province":"Niedersachsen",
    "wof:name":"Brammerloh Gmbh",
    "wof:placetype":"venue"
},
  "geometry": {"coordinates":[9.482305,53.176647],"type":"Point"}
}