{
  "type": "Feature",
  "properties": {
    "iso:country":"DE",
    "sg:address":"Butzbacher Str. 22",
    "sg:city":"W\u00f6lfersheim",
    "sg:phone":"+49 6036/97180",
    "sg:postcode":"61200",
    "sg:province":"Hessen",
    "wof:name":"Gfc Gesellschaft F\u00fcr Computergrafik Mbh",
    "wof:placetype":"venue"
},
  "geometry": {"coordinates":[8.8593997955,50.4272499084],"type":"Point"}
}