{
  "type": "Feature",
  "properties": {
    "iso:country":"DE",
    "sg:address":"Ichtersh\u00e4user Str. 8",
    "sg:city":"Arnstadt",
    "sg:phone":"+49 3628/600830",
    "sg:postcode":"99310",
    "sg:province":"Th\u00fcringen",
    "wof:name":"Wendl K\u00fcchen E. Kfr.",
    "wof:placetype":"venue"
},
  "geometry": {"coordinates":[10.951516,50.843239],"type":"Point"}
}