{
  "type": "Feature",
  "properties": {
    "iso:country":"DE",
    "sg:address":"Villenstr. 2",
    "sg:city":"Kaiserslautern",
    "sg:phone":"+49 631/61070",
    "sg:postcode":"67657",
    "sg:province":"Rheinland-Pfalz",
    "wof:name":"Prof. Dr. Karl-heinz Fischer Architekt",
    "wof:placetype":"venue"
},
  "geometry": {"coordinates":[7.766165,49.448631],"type":"Point"}
}