{
  "type": "Feature",
  "properties": {
    "iso:country":"DE",
    "sg:address":"Voerder Str. 48",
    "sg:city":"Ennepetal",
    "sg:phone":"+49 2333/974900",
    "sg:postcode":"58256",
    "sg:province":"Nordrhein-Westfalen",
    "wof:name":"B. Arnold",
    "wof:placetype":"venue"
},
  "geometry": {"coordinates":[7.3481612206,51.2991447449],"type":"Point"}
}