{
  "type": "Feature",
  "properties": {
    "iso:country":"DE",
    "sg:address":"Buchtstr. 14",
    "sg:city":"Hamburg",
    "sg:phone":"+49 40/2272020",
    "sg:postcode":"22087",
    "sg:province":"Hamburg",
    "wof:name":"Sphinx Datenverarbeitungs- Systeme Gmbh",
    "wof:placetype":"venue"
},
  "geometry": {"coordinates":[10.0178260803,53.5635566711],"type":"Point"}
}