{
  "type": "Feature",
  "properties": {
    "iso:country":"DE",
    "sg:address":"Stockheimer Ring 18",
    "sg:city":"Michelstadt",
    "sg:phone":"+49 4960/6172377",
    "sg:postcode":"64720",
    "sg:province":"Hessen",
    "wof:name":"Autokrane Schwerlast-montagen-service Gmbh",
    "wof:placetype":"venue"
},
  "geometry": {"coordinates":[9.008392334,49.665725708],"type":"Point"}
}