{
  "type": "Feature",
  "properties": {
    "iso:country":"DE",
    "sg:address":"Bahnhofstra\u00dfe 11",
    "sg:city":"Bad Honnef",
    "sg:phone":"+49 2224",
    "sg:postcode":"53604",
    "sg:province":"Nordrhein-Westfalen",
    "wof:name":"Sahm Gallery",
    "wof:placetype":"venue"
},
  "geometry": {"coordinates":[7.2237467766,50.6436004639],"type":"Point"}
}