{
  "type": "Feature",
  "properties": {
    "iso:country":"DE",
    "sg:address":"Celler Str. 108",
    "sg:city":"Braunschweig",
    "sg:phone":"+49 4953/1509077",
    "sg:postcode":"38114",
    "sg:province":"Niedersachsen",
    "wof:name":"Commerzbank Aktiengesellschaft",
    "wof:placetype":"venue"
},
  "geometry": {"coordinates":[10.508677,52.270557],"type":"Point"}
}