{
  "type": "Feature",
  "properties": {
    "iso:country":"DE",
    "sg:address":"Bl\u00fccherstr. 11",
    "sg:city":"Bacharach",
    "sg:phone":"+49 6743/1313",
    "sg:postcode":"55422",
    "sg:province":"Rheinland-Pfalz",
    "wof:name":"Fritz Kober",
    "wof:placetype":"venue"
},
  "geometry": {"coordinates":[7.7668800354,50.0598678589],"type":"Point"}
}