{
  "type": "Feature",
  "properties": {
    "iso:country":"DE",
    "sg:address":"Schillingsrotter Weg 7",
    "sg:city":"K\u00f6ln",
    "sg:phone":"+49 221/93706150",
    "sg:postcode":"50968",
    "sg:province":"Nordrhein-Westfalen",
    "wof:name":"Empirix.net.online.medien",
    "wof:placetype":"venue"
},
  "geometry": {"coordinates":[6.9738020897,50.894733429],"type":"Point"}
}