{
  "type": "Feature",
  "properties": {
    "iso:country":"DE",
    "sg:address":"N\u00fcrnberger Str. 55",
    "sg:city":"Burgthann",
    "sg:phone":"+49 9183/7286",
    "sg:postcode":"90559",
    "sg:province":"Bayern",
    "wof:name":"Eugen R\u00fcd",
    "wof:placetype":"venue"
},
  "geometry": {"coordinates":[11.32734,49.326591],"type":"Point"}
}