{
  "type": "Feature",
  "properties": {
    "iso:country":"DE",
    "sg:address":"Baisieper Str. 19a",
    "sg:city":"Remscheid",
    "sg:phone":"+49 4921/9136410",
    "sg:postcode":"42859",
    "sg:province":"Nordrhein-Westfalen",
    "wof:name":"Pfaffrath Print & Medien Gmbh",
    "wof:placetype":"venue"
},
  "geometry": {"coordinates":[7.2182130814,51.1740951538],"type":"Point"}
}