{
  "type": "Feature",
  "properties": {
    "iso:country":"DE",
    "sg:address":"Dertmanns Feld 45",
    "sg:city":"Bochum",
    "sg:phone":"+49 234/476353",
    "sg:postcode":"44797",
    "sg:province":"Nordrhein-Westfalen",
    "wof:name":"J\u00fcrgen Hauk Rechtsanwalt",
    "wof:placetype":"venue"
},
  "geometry": {"coordinates":[7.2124462128,51.4357528687],"type":"Point"}
}