{
  "type": "Feature",
  "properties": {
    "iso:country":"DE",
    "sg:address":"Provinzialstr. 33",
    "sg:city":"Waldalgesheim",
    "sg:phone":"+49 6721/35761",
    "sg:postcode":"55425",
    "sg:province":"Rheinland-Pfalz",
    "wof:name":"Gasthaus Jung",
    "wof:placetype":"venue"
},
  "geometry": {"coordinates":[7.8340277672,49.951335907],"type":"Point"}
}