{
  "type": "Feature",
  "properties": {
    "iso:country":"DE",
    "sg:address":"Schlachthofstr. 8-10",
    "sg:city":"Weimar",
    "sg:phone":"+49 3643/54340",
    "sg:postcode":"99423",
    "sg:province":"Th\u00fcringen",
    "wof:name":"Matth\u00e4i Bauunternehmen Gmbh & Co. Kg",
    "wof:placetype":"venue"
},
  "geometry": {"coordinates":[11.334325,50.989574],"type":"Point"}
}