{
  "type": "Feature",
  "properties": {
    "iso:country":"DE",
    "sg:address":"Obere Gewerbestr 2",
    "sg:city":"Berghaupten",
    "sg:phone":"+49 7803/2510",
    "sg:postcode":"77791",
    "sg:province":"Baden-W\u00fcrttemberg",
    "wof:name":"Franz Kr\u00e4mer",
    "wof:placetype":"venue"
},
  "geometry": {"coordinates":[7.999896,48.404308],"type":"Point"}
}