{
  "type": "Feature",
  "properties": {
    "iso:country":"DE",
    "sg:address":"Lobensteiner Str. 1",
    "sg:city":"Wurzbach",
    "sg:postcode":"07343",
    "sg:province":"Th\u00fcringen",
    "wof:name":"Bhg",
    "wof:placetype":"venue"
},
  "geometry": {"coordinates":[11.540266,50.463619],"type":"Point"}
}