{
  "type": "Feature",
  "properties": {
    "iso:country":"DE",
    "sg:address":"H\u00f6fenweg 3a",
    "sg:city":"Quedlinburg",
    "sg:phone":"+49 3946/96510",
    "sg:postcode":"06484",
    "sg:province":"Sachsen-Anhalt",
    "wof:name":"Intec Gmbh",
    "wof:placetype":"venue"
},
  "geometry": {"coordinates":[11.1616153717,51.7910461426],"type":"Point"}
}