{
  "type": "Feature",
  "properties": {
    "iso:country":"DE",
    "sg:address":"Moerser Str. 338-340",
    "sg:city":"Krefeld",
    "sg:postcode":"47803",
    "sg:province":"Nordrhein-Westfalen",
    "wof:name":"General Interest Gmbh",
    "wof:placetype":"venue"
},
  "geometry": {"coordinates":[6.5749931335,51.3496551514],"type":"Point"}
}