{
  "type": "Feature",
  "properties": {
    "iso:country":"DE",
    "sg:address":"Gr\u00f6bitzer Weg 107",
    "sg:city":"Finsterwalde",
    "sg:phone":"+49 3531/61970",
    "sg:postcode":"03238",
    "sg:province":"Brandenburg",
    "wof:name":"Portas",
    "wof:placetype":"venue"
},
  "geometry": {"coordinates":[13.7095098495,51.6431999207],"type":"Point"}
}