{
  "type": "Feature",
  "properties": {
    "iso:country":"DE",
    "sg:address":"Liebigstr. 5",
    "sg:city":"Ansbach",
    "sg:postcode":"91522",
    "sg:province":"Bayern",
    "wof:name":"Rattelmeier Gmbh",
    "wof:placetype":"venue"
},
  "geometry": {"coordinates":[10.5122003555,49.2778587341],"type":"Point"}
}