{
  "type": "Feature",
  "properties": {
    "iso:country":"DE",
    "sg:address":"Hauptstr. 2",
    "sg:city":"Beilngries",
    "sg:phone":"+49 8461/1380",
    "sg:postcode":"92339",
    "sg:province":"Bayern",
    "wof:name":"Bierstube Zur Mauth",
    "wof:placetype":"venue"
},
  "geometry": {"coordinates":[11.4747982025,49.033618927],"type":"Point"}
}