{
  "type": "Feature",
  "properties": {
    "iso:country":"DE",
    "sg:address":"Sedanstr. 14 a",
    "sg:city":"Kiel",
    "sg:phone":"+49 431/16990",
    "sg:postcode":"24116",
    "sg:province":"Schleswig-Holstein",
    "wof:name":"Max Giese Bau Gmbh",
    "wof:placetype":"venue"
},
  "geometry": {"coordinates":[10.1086406708,54.3276977539],"type":"Point"}
}