{
  "type": "Feature",
  "properties": {
    "iso:country":"DE",
    "sg:address":"Marienfelder Chaussee 2",
    "sg:city":"Berlin",
    "sg:phone":"+49 30/76203280",
    "sg:postcode":"12349",
    "sg:province":"Berlin",
    "wof:name":"Heinrich Scheuermann Gmbh & Co. Kg",
    "wof:placetype":"venue"
},
  "geometry": {"coordinates":[13.42623806,52.4207305908],"type":"Point"}
}