{
  "type": "Feature",
  "properties": {
    "iso:country":"DE",
    "sg:address":"Waldeckstr. 6",
    "sg:city":"Wuppertal",
    "sg:phone":"+49 202/625153",
    "sg:postcode":"42289",
    "sg:province":"Nordrhein-Westfalen",
    "wof:name":"Im Landsknecht",
    "wof:placetype":"venue"
},
  "geometry": {"coordinates":[7.2237548828,51.2714080811],"type":"Point"}
}