{
  "type": "Feature",
  "properties": {
    "iso:country":"DE",
    "sg:address":"Hauptstr. 105",
    "sg:city":"Renchen",
    "sg:phone":"+49 7843/323",
    "sg:postcode":"77871",
    "sg:province":"Baden-W\u00fcrttemberg",
    "wof:name":"Deutsche Bahn Ag",
    "wof:placetype":"venue"
},
  "geometry": {"coordinates":[8.0071439743,48.5841827393],"type":"Point"}
}