{
  "type": "Feature",
  "properties": {
    "iso:country":"DE",
    "sg:address":"Jakobsplatz 15",
    "sg:city":"Augsburg",
    "sg:phone":"+49 821/519516",
    "sg:postcode":"86152",
    "sg:province":"Bayern",
    "wof:name":"C. Nickl",
    "wof:placetype":"venue"
},
  "geometry": {"coordinates":[10.9053382874,48.3691291809],"type":"Point"}
}