{
  "type": "Feature",
  "properties": {
    "iso:country":"DE",
    "sg:address":"Schulrat-Hohe-Str. 1",
    "sg:city":"Naila",
    "sg:postcode":"95119",
    "sg:province":"Bayern",
    "wof:name":"K & R Vermietungs- Und Verwaltungsges. Mbh",
    "wof:placetype":"venue"
},
  "geometry": {"coordinates":[11.7128582001,50.323059082],"type":"Point"}
}