{
  "type": "Feature",
  "properties": {
    "iso:country":"DE",
    "sg:address":"Carlstr. 12",
    "sg:city":"Helmstedt",
    "sg:phone":"+49 5351/31119",
    "sg:postcode":"38350",
    "sg:province":"Niedersachsen",
    "wof:name":"L\u00f6hr",
    "wof:placetype":"venue"
},
  "geometry": {"coordinates":[11.004348,52.232758],"type":"Point"}
}