{
  "type": "Feature",
  "properties": {
    "iso:country":"DE",
    "sg:address":"L\u00f6nsstr. 32",
    "sg:city":"K\u00f6ln",
    "sg:phone":"+49 2234/400300",
    "sg:postcode":"50858",
    "sg:province":"Nordrhein-Westfalen",
    "wof:name":"Siegfried Tchorz Architekt",
    "wof:placetype":"venue"
},
  "geometry": {"coordinates":[6.837094,50.938999],"type":"Point"}
}