{
  "type": "Feature",
  "properties": {
    "iso:country":"DE",
    "sg:address":"Gru\u00dfdorfstr. 14",
    "sg:city":"Berlin",
    "sg:phone":"+49 30/4347706",
    "sg:postcode":"13507",
    "sg:province":"Berlin",
    "wof:name":"Heike Sieben Masseurin",
    "wof:placetype":"venue"
},
  "geometry": {"coordinates":[13.285679,52.588577],"type":"Point"}
}