{
  "type": "Feature",
  "properties": {
    "iso:country":"DE",
    "sg:address":"Noldestr. 6",
    "sg:city":"\u00dcbach-Palenberg",
    "sg:phone":"+49 2451/909525",
    "sg:postcode":"52531",
    "sg:province":"Nordrhein-Westfalen",
    "wof:name":"Renald Robioneck Steuerberater",
    "wof:placetype":"venue"
},
  "geometry": {"coordinates":[6.1312599182,50.9121894836],"type":"Point"}
}