{
  "type": "Feature",
  "properties": {
    "iso:country":"DE",
    "sg:address":"Sch\u00f6neberger Str. 1",
    "sg:city":"G\u00f6ttingen",
    "sg:phone":"+49 551/791744",
    "sg:postcode":"37085",
    "sg:province":"Niedersachsen",
    "wof:name":"Mittelberger-apotheke Martina Bulczak E. K.",
    "wof:placetype":"venue"
},
  "geometry": {"coordinates":[9.971025,51.516968],"type":"Point"}
}