{
  "type": "Feature",
  "properties": {
    "iso:country":"DE",
    "sg:address":"Embachstr. 2",
    "sg:city":"Malgersdorf",
    "sg:phone":"+49 9954/7673",
    "sg:postcode":"84333",
    "sg:province":"Bayern",
    "wof:name":"C. Boysen",
    "wof:placetype":"venue"
},
  "geometry": {"coordinates":[12.745652,48.532619],"type":"Point"}
}