{
  "type": "Feature",
  "properties": {
    "iso:country":"DE",
    "sg:address":"Ober-Ramst\u00e4dter-Str. 13",
    "sg:city":"Gro\u00df-Bieberau",
    "sg:phone":"+49 6162/3346",
    "sg:postcode":"64401",
    "sg:province":"Hessen",
    "wof:name":"Georg Krell",
    "wof:placetype":"venue"
},
  "geometry": {"coordinates":[8.820825,49.798637],"type":"Point"}
}