{
  "type": "Feature",
  "properties": {
    "iso:country":"DE",
    "sg:address":"Am Bach 2",
    "sg:city":"Rabenau",
    "sg:phone":"+49 351/6412474",
    "sg:postcode":"01734",
    "sg:province":"Sachsen",
    "wof:name":"Kurt Fleischer",
    "wof:placetype":"venue"
},
  "geometry": {"coordinates":[13.6693649292,50.9451370239],"type":"Point"}
}