{
  "type": "Feature",
  "properties": {
    "iso:country":"DE",
    "sg:address":"An der Oberm\u00fchle 110",
    "sg:city":"Grevenbroich",
    "sg:postcode":"41516",
    "sg:province":"Nordrhein-Westfalen",
    "wof:name":"Peco Transport-gmbh",
    "wof:placetype":"venue"
},
  "geometry": {"coordinates":[6.61662817,51.1039772034],"type":"Point"}
}