{
  "type": "Feature",
  "properties": {
    "iso:country":"DE",
    "sg:address":"Bohlenstr. 3A",
    "sg:city":"Barsinghausen",
    "sg:phone":"+49 5105/82361",
    "sg:postcode":"30890",
    "sg:province":"Niedersachsen",
    "wof:name":"Jens Widdel",
    "wof:placetype":"venue"
},
  "geometry": {"coordinates":[9.537004,52.305233],"type":"Point"}
}