{
  "type": "Feature",
  "properties": {
    "iso:country":"DE",
    "sg:address":"Topfmarkt 15",
    "sg:city":"Frankleben",
    "sg:phone":"+49 34637/50281",
    "sg:postcode":"06259",
    "sg:province":"Sachsen-Anhalt",
    "wof:name":"Joachim Knorn",
    "wof:placetype":"venue"
},
  "geometry": {"coordinates":[11.93075,51.311253],"type":"Point"}
}