{
  "type": "Feature",
  "properties": {
    "iso:country":"DE",
    "sg:address":"Bottroper Str. 1",
    "sg:city":"Bottrop",
    "sg:phone":"+49 2045/6631",
    "sg:postcode":"46244",
    "sg:province":"Nordrhein-Westfalen",
    "wof:name":"Nagel Studio Erika Pentz",
    "wof:placetype":"venue"
},
  "geometry": {"coordinates":[6.913951,51.589294],"type":"Point"}
}