{
  "type": "Feature",
  "properties": {
    "iso:country":"DE",
    "sg:address":"ABC-Str. 19",
    "sg:city":"Wismar",
    "sg:phone":"+49 3841/209020",
    "sg:postcode":"23966",
    "sg:province":"Mecklenburg-Vorpommern",
    "wof:name":"Fidus Bau- Und Handels Gmbh",
    "wof:placetype":"venue"
},
  "geometry": {"coordinates":[11.467384,53.894341],"type":"Point"}
}