{
  "type": "Feature",
  "properties": {
    "iso:country":"DE",
    "sg:address":"Rienecker Str. 4",
    "sg:city":"Burgsinn",
    "sg:phone":"+49 9356/1216",
    "sg:postcode":"97775",
    "sg:province":"Bayern",
    "wof:name":"Spessart-lichtspiele",
    "wof:placetype":"venue"
},
  "geometry": {"coordinates":[9.6496982574,50.1465187073],"type":"Point"}
}