{
  "type": "Feature",
  "properties": {
    "iso:country":"DE",
    "sg:address":"B\u00f6tersteg 1",
    "sg:city":"Ratzeburg",
    "sg:postcode":"23909",
    "sg:province":"Schleswig-Holstein",
    "wof:name":"Alkohol- Und Drogenberatung Im Kreis Herzogtum",
    "wof:placetype":"venue"
},
  "geometry": {"coordinates":[10.771684,53.700256],"type":"Point"}
}