{
  "type": "Feature",
  "properties": {
    "iso:country":"DE",
    "sg:address":"M\u00f6schenfelder Str. 62",
    "sg:city":"Vaterstetten",
    "sg:phone":"+49 8106/899499",
    "sg:postcode":"85591",
    "sg:province":"Bayern",
    "wof:name":"Gerd Fischer Computerhandlungen",
    "wof:placetype":"venue"
},
  "geometry": {"coordinates":[11.7690792084,48.0980796814],"type":"Point"}
}