{
  "type": "Feature",
  "properties": {
    "iso:country":"DE",
    "sg:address":"Georgsplatz 10",
    "sg:city":"Hamburg",
    "sg:postcode":"20099",
    "sg:province":"Hamburg",
    "wof:name":"Act Land- Und Forstwirtschaft Gmbh",
    "wof:placetype":"venue"
},
  "geometry": {"coordinates":[10.002595,53.553703],"type":"Point"}
}