{
  "type": "Feature",
  "properties": {
    "iso:country":"DE",
    "sg:address":"Don-Carlos-Str. 15",
    "sg:city":"Stuttgart",
    "sg:postcode":"70563",
    "sg:province":"Baden-W\u00fcrttemberg",
    "wof:name":"Primo Gmbh",
    "wof:placetype":"venue"
},
  "geometry": {"coordinates":[9.1208076477,48.7366905212],"type":"Point"}
}