{
  "type": "Feature",
  "properties": {
    "iso:country":"DE",
    "sg:address":"Schwerinstr. 34-38",
    "sg:city":"M\u00fclheim",
    "sg:phone":"+49 4920/8402055",
    "sg:postcode":"45476",
    "sg:province":"Nordrhein-Westfalen",
    "wof:name":"Rw Moll & Co Chemische Fabrik Gmbh",
    "wof:placetype":"venue"
},
  "geometry": {"coordinates":[6.855833,51.452255],"type":"Point"}
}