{
  "type": "Feature",
  "properties": {
    "iso:country":"DE",
    "sg:address":"Am Br\u00fchl 7",
    "sg:city":"Sangerhausen",
    "sg:postcode":"06526",
    "sg:province":"Sachsen-Anhalt",
    "wof:name":"Ivt Engineering Gmbh Gummiraupen/rubbercrawler",
    "wof:placetype":"venue"
},
  "geometry": {"coordinates":[11.29479,51.482742],"type":"Point"}
}