{
  "type": "Feature",
  "properties": {
    "iso:country":"DE",
    "sg:address":"Teichstr. 20",
    "sg:city":"Lieskau",
    "sg:phone":"+49 345/5508271",
    "sg:postcode":"06120",
    "sg:province":"Sachsen-Anhalt",
    "wof:name":"Thomas Liesegang",
    "wof:placetype":"venue"
},
  "geometry": {"coordinates":[11.8653612137,51.5023498535],"type":"Point"}
}