{
  "type": "Feature",
  "properties": {
    "iso:country":"DE",
    "sg:address":"St\u00fcvestr. 60",
    "sg:city":"Melle",
    "sg:phone":"+49 5427/342",
    "sg:postcode":"49328",
    "sg:province":"Niedersachsen",
    "wof:name":"Heinrich Elberg Gmbh",
    "wof:placetype":"venue"
},
  "geometry": {"coordinates":[8.4215583801,52.2340278625],"type":"Point"}
}