{
  "type": "Feature",
  "properties": {
    "iso:country":"DE",
    "sg:address":"Ro\u00dfbacher Str. 50",
    "sg:city":"Leidersbach",
    "sg:phone":"+49 6092/6617",
    "sg:postcode":"63849",
    "sg:province":"Bayern",
    "wof:name":"Omnibusbetrieb Armin Mergler Gmbh",
    "wof:placetype":"venue"
},
  "geometry": {"coordinates":[9.2402744293,49.8905448914],"type":"Point"}
}