{
  "type": "Feature",
  "properties": {
    "iso:country":"DE",
    "sg:address":"Bahndamm 20",
    "sg:city":"Rehburg-Loccum",
    "sg:phone":"+49 5037/978250",
    "sg:postcode":"31547",
    "sg:province":"Niedersachsen",
    "wof:name":"Eben Holz Gmbh",
    "wof:placetype":"venue"
},
  "geometry": {"coordinates":[9.219361,52.467571],"type":"Point"}
}