{
  "type": "Feature",
  "properties": {
    "iso:country":"DE",
    "sg:address":"Vorderer Berg 9",
    "sg:city":"G\u00f6ppingen",
    "sg:phone":"+49 7161/43854",
    "sg:postcode":"73035",
    "sg:province":"Baden-W\u00fcrttemberg",
    "wof:name":"Hotel Garni Elisabeth Inh. Elisabeth Kinkel",
    "wof:placetype":"venue"
},
  "geometry": {"coordinates":[9.6286220551,48.6877212524],"type":"Point"}
}