{
  "type": "Feature",
  "properties": {
    "iso:country":"DE",
    "sg:address":"Breite Str. 55",
    "sg:city":"Andernach",
    "sg:phone":"+49 2632/47205",
    "sg:postcode":"56626",
    "sg:province":"Rheinland-Pfalz",
    "wof:name":"Bistro New Wave",
    "wof:placetype":"venue"
},
  "geometry": {"coordinates":[7.4016418457,50.4351730347],"type":"Point"}
}