{
  "type": "Feature",
  "properties": {
    "iso:country":"DE",
    "sg:address":"Tal 34",
    "sg:city":"M\u00fcnchen",
    "sg:phone":"+49 89/2429780",
    "sg:postcode":"80331",
    "sg:province":"Bayern",
    "wof:name":"Raven Pack Ag",
    "wof:placetype":"venue"
},
  "geometry": {"coordinates":[11.580169,48.135605],"type":"Point"}
}