{
  "type": "Feature",
  "properties": {
    "iso:country":"DE",
    "sg:address":"Ettinger Str. 32",
    "sg:city":"Ingolstadt",
    "sg:phone":"+49 841/49070",
    "sg:postcode":"85057",
    "sg:province":"Bayern",
    "wof:name":"Brunnquell Gmbh",
    "wof:placetype":"venue"
},
  "geometry": {"coordinates":[11.416535,48.778141],"type":"Point"}
}