{
  "type": "Feature",
  "properties": {
    "iso:country":"DE",
    "sg:address":"Pariser Str. 127",
    "sg:city":"Nieder-Olm",
    "sg:phone":"+49 6136/3065",
    "sg:postcode":"55268",
    "sg:province":"Rheinland-Pfalz",
    "wof:name":"Emil Tengelmann",
    "wof:placetype":"venue"
},
  "geometry": {"coordinates":[8.1999473572,49.907787323],"type":"Point"}
}