{
  "type": "Feature",
  "properties": {
    "iso:country":"DE",
    "sg:address":"Junkendiek 38",
    "sg:city":"Ibbenb\u00fcren",
    "sg:phone":"+49 5451/45411",
    "sg:postcode":"49479",
    "sg:province":"Nordrhein-Westfalen",
    "wof:name":"Gottfried Grothe",
    "wof:placetype":"venue"
},
  "geometry": {"coordinates":[7.665125,52.277946],"type":"Point"}
}