{
  "type": "Feature",
  "properties": {
    "iso:country":"DE",
    "sg:address":"Olgastr. 2",
    "sg:city":"B\u00f6nnigheim",
    "sg:phone":"+49 7143/22909",
    "sg:postcode":"74357",
    "sg:province":"Baden-W\u00fcrttemberg",
    "wof:name":"Ev. Pfarramt B\u00f6nnigheim Ii",
    "wof:placetype":"venue"
},
  "geometry": {"coordinates":[9.0963973999,49.041633606],"type":"Point"}
}