{
  "type": "Feature",
  "properties": {
    "iso:country":"DE",
    "sg:address":"Ludwigstr. 2",
    "sg:city":"Passau",
    "sg:phone":"+49 851/32092",
    "sg:postcode":"94032",
    "sg:province":"Bayern",
    "wof:name":"Dr. Med. K. K. Kr\u00f6ner-wiedorn \u00c4rztin F\u00fcr Allgemeinmedizin",
    "wof:placetype":"venue"
},
  "geometry": {"coordinates":[13.4601812363,48.5748825073],"type":"Point"}
}