{
  "type": "Feature",
  "properties": {
    "iso:country":"DE",
    "sg:address":"Fichtenstrasse 2",
    "sg:city":"Neuried",
    "sg:phone":"+49 89/74513641",
    "sg:postcode":"82061",
    "sg:province":"Bayern",
    "wof:name":"Kr\u00f6ll Verpackung Tragetaschen Aller Art",
    "wof:placetype":"venue"
},
  "geometry": {"coordinates":[11.458574,48.088776],"type":"Point"}
}