{
  "type": "Feature",
  "properties": {
    "iso:country":"DE",
    "sg:address":"Euregiostr. 4",
    "sg:city":"Bad Bentheim",
    "sg:phone":"+49 5924/6496",
    "sg:postcode":"48455",
    "sg:province":"Niedersachsen",
    "wof:name":"Paus-automobile Gmbh",
    "wof:placetype":"venue"
},
  "geometry": {"coordinates":[7.118039,52.295506],"type":"Point"}
}