{
  "type": "Feature",
  "properties": {
    "iso:country":"DE",
    "sg:address":"Marktstr. 18",
    "sg:city":"Winsen",
    "sg:phone":"+49 4171/2254",
    "sg:postcode":"21423",
    "sg:province":"Niedersachsen",
    "wof:name":"Heinrich Wenck",
    "wof:placetype":"venue"
},
  "geometry": {"coordinates":[10.2061929703,53.3644180298],"type":"Point"}
}