{
  "type": "Feature",
  "properties": {
    "iso:country":"DE",
    "sg:address":"S\u00fcdstr.",
    "sg:city":"Swisttal",
    "sg:phone":"+49 2255/8411",
    "sg:postcode":"53913",
    "sg:province":"Nordrhein-Westfalen",
    "wof:name":"K. Karottki Masseur",
    "wof:placetype":"venue"
},
  "geometry": {"coordinates":[6.873635,50.64893],"type":"Point"}
}