{
  "type": "Feature",
  "properties": {
    "iso:country":"DE",
    "sg:address":"Erlenstr. 12",
    "sg:city":"Kirchroth",
    "sg:phone":"+49 9428/1522",
    "sg:postcode":"94356",
    "sg:province":"Bayern",
    "wof:name":"Riedl",
    "wof:placetype":"venue"
},
  "geometry": {"coordinates":[12.549275,48.950157],"type":"Point"}
}