{
  "type": "Feature",
  "properties": {
    "iso:country":"DE",
    "sg:address":"Hauptstr. 1",
    "sg:city":"Langensteinbach",
    "sg:phone":"+49 34346/60644",
    "sg:postcode":"04657",
    "sg:province":"Sachsen",
    "wof:name":"Bernd Schierak",
    "wof:placetype":"venue"
},
  "geometry": {"coordinates":[8.506362915,48.9165306091],"type":"Point"}
}