{
  "type": "Feature",
  "properties": {
    "iso:country":"DE",
    "sg:address":"Butzbacher Str. 16",
    "sg:city":"Butzbach",
    "sg:phone":"+49 6033/6195",
    "sg:postcode":"35510",
    "sg:province":"Hessen",
    "wof:name":"Z\u00f6rb B\u00e4ckerei Und Konditorei Gmbh",
    "wof:placetype":"venue"
},
  "geometry": {"coordinates":[8.68316,50.420559],"type":"Point"}
}