{
  "type": "Feature",
  "properties": {
    "iso:country":"DE",
    "sg:address":"Haus Gravener Str. 161",
    "sg:city":"Langenfeld",
    "sg:phone":"+49 2173/854340",
    "sg:postcode":"40764",
    "sg:province":"Nordrhein-Westfalen",
    "wof:name":"Classico Winterhagen Gmbh",
    "wof:placetype":"venue"
},
  "geometry": {"coordinates":[6.9649729729,51.1363372803],"type":"Point"}
}