{
  "type": "Feature",
  "properties": {
    "iso:country":"DE",
    "sg:address":"Christinenstr. 11",
    "sg:city":"Ratingen",
    "sg:phone":"+49 2102/94720",
    "sg:postcode":"40880",
    "sg:province":"Nordrhein-Westfalen",
    "wof:name":"Leffler Messe- Und Ausstellungs- Gmbh",
    "wof:placetype":"venue"
},
  "geometry": {"coordinates":[6.8259420395,51.3050804138],"type":"Point"}
}