{
  "type": "Feature",
  "properties": {
    "iso:country":"DE",
    "sg:address":"Marktplatz 1",
    "sg:city":"Auetal",
    "sg:phone":"+49 5752/7128",
    "sg:postcode":"31749",
    "sg:province":"Niedersachsen",
    "wof:name":"E. Weltjen",
    "wof:placetype":"venue"
},
  "geometry": {"coordinates":[9.2358293533,52.2323455811],"type":"Point"}
}