{
  "type": "Feature",
  "properties": {
    "iso:country":"DE",
    "sg:address":"K\u00f6nigsberger Str. 10",
    "sg:city":"Bad Schwalbach",
    "sg:phone":"+49 6124/6495",
    "sg:postcode":"65307",
    "sg:province":"Hessen",
    "wof:name":"Sch\u00fctzengesellschaft Nast\u00e4tten 1954 E. V.",
    "wof:placetype":"venue"
},
  "geometry": {"coordinates":[8.0620994568,50.1403656006],"type":"Point"}
}