{
  "type": "Feature",
  "properties": {
    "iso:country":"DE",
    "sg:address":"Notburgaweg 1",
    "sg:city":"Deggendorf",
    "sg:phone":"+49 991/33964",
    "sg:postcode":"94469",
    "sg:province":"Bayern",
    "wof:name":"W. Hackl",
    "wof:placetype":"venue"
},
  "geometry": {"coordinates":[12.962201,48.831322],"type":"Point"}
}