{
  "type": "Feature",
  "properties": {
    "iso:country":"DE",
    "sg:address":"Ermsstr. 40",
    "sg:city":"Bempflingen",
    "sg:phone":"+49 7123/32833",
    "sg:postcode":"72658",
    "sg:province":"Baden-W\u00fcrttemberg",
    "wof:name":"Eugen Bandle",
    "wof:placetype":"venue"
},
  "geometry": {"coordinates":[9.2626543045,48.5698165894],"type":"Point"}
}