{
  "type": "Feature",
  "properties": {
    "iso:country":"DE",
    "sg:address":"Nordstr. 2",
    "sg:city":"Hamm",
    "sg:phone":"+49 2381/13616",
    "sg:postcode":"59065",
    "sg:province":"Nordrhein-Westfalen",
    "wof:name":"Krane Optik- Und Akustik Gmbh & Co. Betriebs Kg",
    "wof:placetype":"venue"
},
  "geometry": {"coordinates":[7.8171892166,51.6811904907],"type":"Point"}
}