{
  "type": "Feature",
  "properties": {
    "iso:country":"DE",
    "sg:address":"Erdeborner Str. 3",
    "sg:city":"L\u00fcttchendorf",
    "sg:phone":"+49 3475/718398",
    "sg:postcode":"06317",
    "sg:province":"Sachsen-Anhalt",
    "wof:name":"E. Seemann",
    "wof:placetype":"venue"
},
  "geometry": {"coordinates":[11.627498,51.500702],"type":"Point"}
}