{
  "type": "Feature",
  "properties": {
    "iso:country":"DE",
    "sg:address":"Zum Ackerberg 5",
    "sg:city":"Braunschweig",
    "sg:phone":"+49 531/66282",
    "sg:postcode":"38126",
    "sg:province":"Niedersachsen",
    "wof:name":"G\u00fcnter Gerecke",
    "wof:placetype":"venue"
},
  "geometry": {"coordinates":[10.584655,52.241482],"type":"Point"}
}