{
  "type": "Feature",
  "properties": {
    "iso:country":"DE",
    "sg:address":"Heidemannstr. 27",
    "sg:city":"M\u00fcnchen",
    "sg:phone":"+49 89/3162503",
    "sg:postcode":"80939",
    "sg:province":"Bayern",
    "wof:name":"Monika Manghabati Ergotherapiepraxis",
    "wof:placetype":"venue"
},
  "geometry": {"coordinates":[11.589856,48.201496],"type":"Point"}
}