{
  "type": "Feature",
  "properties": {
    "iso:country":"DE",
    "sg:address":"Im Halben Mond 28",
    "sg:city":"Eppelborn",
    "sg:phone":"+49 6881/80270",
    "sg:postcode":"66571",
    "sg:province":"Saarland",
    "wof:name":"F.-j. Lillig",
    "wof:placetype":"venue"
},
  "geometry": {"coordinates":[6.9715819359,49.400592804],"type":"Point"}
}