{
  "type": "Feature",
  "properties": {
    "iso:country":"DE",
    "sg:address":"Buxtrup 5",
    "sg:city":"Nottuln",
    "sg:phone":"+49 2502/23030",
    "sg:postcode":"48301",
    "sg:province":"Nordrhein-Westfalen",
    "wof:name":"Giesker & Laakmann Gmbh",
    "wof:placetype":"venue"
},
  "geometry": {"coordinates":[7.38966,51.906742],"type":"Point"}
}