{
  "type": "Feature",
  "properties": {
    "iso:country":"DE",
    "sg:address":"Marktstr. 5",
    "sg:city":"Siegen",
    "sg:phone":"+49 271/81001",
    "sg:postcode":"57078",
    "sg:province":"Nordrhein-Westfalen",
    "wof:name":"B\u00e4cker Verwaltungs Gmbh",
    "wof:placetype":"venue"
},
  "geometry": {"coordinates":[8.0106372833,50.9146499634],"type":"Point"}
}