{
  "type": "Feature",
  "properties": {
    "iso:country":"DE",
    "sg:address":"Bertholdstr. 6",
    "sg:city":"Schleusingen",
    "sg:phone":"+49 36841/40087",
    "sg:postcode":"98553",
    "sg:province":"Th\u00fcringen",
    "wof:name":"Hans-joachim Scharf",
    "wof:placetype":"venue"
},
  "geometry": {"coordinates":[10.7558870316,50.5108413696],"type":"Point"}
}