{
  "type": "Feature",
  "properties": {
    "iso:country":"DE",
    "sg:address":"Wredestr. 35",
    "sg:city":"Ludwigshafen",
    "sg:phone":"+49 621/591290",
    "sg:postcode":"67059",
    "sg:province":"Rheinland-Pfalz",
    "wof:name":"C & A Mode Kg",
    "wof:placetype":"venue"
},
  "geometry": {"coordinates":[8.448261,49.47961],"type":"Point"}
}