{
  "type": "Feature",
  "properties": {
    "iso:country":"DE",
    "sg:address":"Am Lanzenbusch 3",
    "sg:city":"Ramstein-Miesenbach",
    "sg:phone":"+49 6371/58289",
    "sg:postcode":"66877",
    "sg:province":"Rheinland-Pfalz",
    "wof:name":"Weberst\u00fcbchen",
    "wof:placetype":"venue"
},
  "geometry": {"coordinates":[7.5538768768,49.4390983582],"type":"Point"}
}