{
  "type": "Feature",
  "properties": {
    "iso:country":"DE",
    "sg:address":"Uferstr. 12",
    "sg:city":"Sch\u00f6neck",
    "sg:phone":"+49 6187",
    "sg:postcode":"61137",
    "sg:province":"Hessen",
    "wof:name":"Arno Zeh Heizungsbau",
    "wof:placetype":"venue"
},
  "geometry": {"coordinates":[8.83604,50.203629],"type":"Point"}
}