{
  "type": "Feature",
  "properties": {
    "iso:country":"DE",
    "sg:address":"Dornregt 6",
    "sg:city":"Minden",
    "sg:phone":"+49 571/49351",
    "sg:postcode":"32425",
    "sg:province":"Nordrhein-Westfalen",
    "wof:name":"W. Dombrowa",
    "wof:placetype":"venue"
},
  "geometry": {"coordinates":[8.9085102081,52.3070449829],"type":"Point"}
}