{
  "type": "Feature",
  "properties": {
    "iso:country":"DE",
    "sg:address":"Lungwitzer Str. 77",
    "sg:city":"St. Egidien",
    "sg:postcode":"09356",
    "sg:province":"Sachsen",
    "wof:name":"Heimatstube St. Egidien",
    "wof:placetype":"venue"
},
  "geometry": {"coordinates":[12.622527,50.784176],"type":"Point"}
}