{
  "type": "Feature",
  "properties": {
    "iso:country":"DE",
    "sg:address":"Bruchweg 1",
    "sg:city":"Bad Iburg",
    "sg:phone":"+49 5403/2032",
    "sg:postcode":"49186",
    "sg:province":"Niedersachsen",
    "wof:name":"Hubert Gr\u00fcndker",
    "wof:placetype":"venue"
},
  "geometry": {"coordinates":[8.01905,52.137783],"type":"Point"}
}