{
  "type": "Feature",
  "properties": {
    "iso:country":"DE",
    "sg:address":"F\u00fcrstenbergstr. 92",
    "sg:city":"Konstanz",
    "sg:phone":"+49 7531/77579",
    "sg:postcode":"78467",
    "sg:province":"Baden-W\u00fcrttemberg",
    "wof:name":"Akiss-reinigung Hess Kg",
    "wof:placetype":"venue"
},
  "geometry": {"coordinates":[9.157452,47.683216],"type":"Point"}
}