{
  "type": "Feature",
  "properties": {
    "iso:country":"DE",
    "sg:address":"Eichenlochweg 4",
    "sg:city":"Sinsheim",
    "sg:phone":"+49 7261/62829",
    "sg:postcode":"74889",
    "sg:province":"Baden-W\u00fcrttemberg",
    "wof:name":"Klaus-dieter Speichert Masseur",
    "wof:placetype":"venue"
},
  "geometry": {"coordinates":[8.831071,49.246986],"type":"Point"}
}