{
  "type": "Feature",
  "properties": {
    "iso:country":"DE",
    "sg:address":"Stettiner Str. 70",
    "sg:city":"Eggesin",
    "sg:phone":"+49 39779/27330",
    "sg:postcode":"17367",
    "sg:province":"Mecklenburg-Vorpommern",
    "wof:name":"H. Hintz",
    "wof:placetype":"venue"
},
  "geometry": {"coordinates":[14.082447,53.679764],"type":"Point"}
}