{
  "type": "Feature",
  "properties": {
    "iso:country":"DE",
    "sg:address":"Harderberger Weg 2a",
    "sg:city":"Georgsmarienh\u00fctte",
    "sg:phone":"+49 5401/8000",
    "sg:postcode":"49124",
    "sg:province":"Niedersachsen",
    "wof:name":"St\u00e4dtereinigung Holtmeyer Gmbh & Co.",
    "wof:placetype":"venue"
},
  "geometry": {"coordinates":[8.0390691757,52.2136650085],"type":"Point"}
}