{
  "type": "Feature",
  "properties": {
    "iso:country":"DE",
    "sg:address":"Ro\u00dfbachstr. 2",
    "sg:city":"Ravensburg",
    "sg:phone":"+49 751/16010",
    "sg:postcode":"88212",
    "sg:province":"Baden-W\u00fcrttemberg",
    "wof:name":"Georg Dresely Rechtsanwalt",
    "wof:placetype":"venue"
},
  "geometry": {"coordinates":[9.6156311035,47.781375885],"type":"Point"}
}