{
  "type": "Feature",
  "properties": {
    "iso:country":"DE",
    "sg:address":"Bruno-Baum-Ring 24",
    "sg:city":"Rathenow",
    "sg:postcode":"14712",
    "sg:province":"Brandenburg",
    "wof:name":"Kirscher Kg",
    "wof:placetype":"venue"
},
  "geometry": {"coordinates":[12.363871,52.604172],"type":"Point"}
}