{
  "type": "Feature",
  "properties": {
    "iso:country":"DE",
    "sg:address":"Georg-Schumann-Str. 65",
    "sg:city":"Leipzig",
    "sg:postcode":"04155",
    "sg:province":"Sachsen",
    "wof:name":"Eckhardt",
    "wof:placetype":"venue"
},
  "geometry": {"coordinates":[12.367286,51.361877],"type":"Point"}
}