{
  "type": "Feature",
  "properties": {
    "iso:country":"DE",
    "sg:address":"Honeggerstr. 1",
    "sg:city":"Wiesbaden",
    "sg:phone":"+49 611/522845",
    "sg:postcode":"65193",
    "sg:province":"Hessen",
    "wof:name":"La Perla",
    "wof:placetype":"venue"
},
  "geometry": {"coordinates":[8.2485342026,50.0959815979],"type":"Point"}
}