{
  "type": "Feature",
  "properties": {
    "iso:country":"DE",
    "sg:address":"Eupener Str. 10 c",
    "sg:city":"Hannover",
    "sg:phone":"+49 511/842730",
    "sg:postcode":"30519",
    "sg:province":"Niedersachsen",
    "wof:name":"Fagro Rettberg Gmbh & Co. Kg",
    "wof:placetype":"venue"
},
  "geometry": {"coordinates":[9.784583,52.343796],"type":"Point"}
}