{
  "type": "Feature",
  "properties": {
    "iso:country":"DE",
    "sg:address":"Olympiastr. 4",
    "sg:city":"Spatzenhausen",
    "sg:phone":"+49 8847/6020",
    "sg:postcode":"82447",
    "sg:province":"Bayern",
    "wof:name":"G. Fuchs",
    "wof:placetype":"venue"
},
  "geometry": {"coordinates":[11.20082,47.722183],"type":"Point"}
}