{
  "type": "Feature",
  "properties": {
    "iso:country":"DE",
    "sg:address":"Gaustr. 2",
    "sg:city":"Bechtheim",
    "sg:phone":"+49 6242/7633",
    "sg:postcode":"67595",
    "sg:province":"Rheinland-Pfalz",
    "wof:name":"J\u00fcrgen Spie\u00df",
    "wof:placetype":"venue"
},
  "geometry": {"coordinates":[8.2908248901,49.726650238],"type":"Point"}
}