{
  "type": "Feature",
  "properties": {
    "iso:country":"DE",
    "sg:address":"Landweg 5",
    "sg:city":"Berlin",
    "sg:phone":"+49 30/7121020",
    "sg:postcode":"12207",
    "sg:province":"Berlin",
    "wof:name":"Abc Autolackiererei Gmbh",
    "wof:placetype":"venue"
},
  "geometry": {"coordinates":[13.3204526901,52.4103622437],"type":"Point"}
}