{
  "type": "Feature",
  "properties": {
    "iso:country":"DE",
    "sg:address":"Eisenh\u00fcttenstr. 2",
    "sg:city":"Ratingen",
    "sg:phone":"+49 2102/80640",
    "sg:postcode":"40882",
    "sg:province":"Nordrhein-Westfalen",
    "wof:name":"L\u00f6wen-apotheke",
    "wof:placetype":"venue"
},
  "geometry": {"coordinates":[6.866845,51.296768],"type":"Point"}
}