{
  "type": "Feature",
  "properties": {
    "iso:country":"DE",
    "sg:address":"Br\u00fcsseler Str 5",
    "sg:city":"Georgsmarienh\u00fctte",
    "sg:phone":"+49 5401/866612",
    "sg:postcode":"49124",
    "sg:province":"Niedersachsen",
    "wof:name":"Technische Anlagen Wamhoff Gmbh + Co Kg",
    "wof:placetype":"venue"
},
  "geometry": {"coordinates":[8.0845851898,52.2231445312],"type":"Point"}
}