{
  "type": "Feature",
  "properties": {
    "iso:country":"DE",
    "sg:address":"Blumenheckstrasse. 32",
    "sg:city":"Pforzheim",
    "sg:phone":"+49 7231/290801",
    "sg:postcode":"75177",
    "sg:province":"Baden-W\u00fcrttemberg",
    "wof:name":"Amway Internet Shop Von Heinrich Moor",
    "wof:placetype":"venue"
},
  "geometry": {"coordinates":[8.713549,48.89864],"type":"Point"}
}