{
  "type": "Feature",
  "properties": {
    "iso:country":"DE",
    "sg:address":"Brockengasse 6",
    "sg:city":"Inden",
    "sg:phone":"+49 2465/3214",
    "sg:postcode":"52459",
    "sg:province":"Nordrhein-Westfalen",
    "wof:name":"A. Heesen",
    "wof:placetype":"venue"
},
  "geometry": {"coordinates":[6.3519029617,50.8372383118],"type":"Point"}
}