{
  "type": "Feature",
  "properties": {
    "iso:country":"DE",
    "sg:address":"Tr\u00e4nkeweg 24",
    "sg:city":"F\u00fcrstenwalde",
    "sg:phone":"+49 3361/2668",
    "sg:postcode":"15517",
    "sg:province":"Brandenburg",
    "wof:name":"Ccd Courier Deutschland- Service",
    "wof:placetype":"venue"
},
  "geometry": {"coordinates":[14.087327,52.34903],"type":"Point"}
}