{
  "type": "Feature",
  "properties": {
    "iso:country":"DE",
    "sg:address":"H\u00e4uschensweg 25",
    "sg:city":"K\u00f6ln",
    "sg:postcode":"50827",
    "sg:province":"Nordrhein-Westfalen",
    "wof:name":"Logiksektor Gmbh",
    "wof:placetype":"venue"
},
  "geometry": {"coordinates":[6.8976669312,50.9597129822],"type":"Point"}
}