{
  "type": "Feature",
  "properties": {
    "iso:country":"DE",
    "sg:address":"Kirchstr. 3",
    "sg:city":"Lauenau",
    "sg:phone":"+49 5043/440",
    "sg:postcode":"31867",
    "sg:province":"Niedersachsen",
    "wof:name":"Ev. Pfarramt Pfarrhaus",
    "wof:placetype":"venue"
},
  "geometry": {"coordinates":[9.3679971695,52.273109436],"type":"Point"}
}