{
  "type": "Feature",
  "properties": {
    "iso:country":"DE",
    "sg:address":"R\u00f6hrsdorfer Allee 1",
    "sg:city":"R\u00f6hrsdorf",
    "sg:phone":"+49 3722/6030",
    "sg:postcode":"09247",
    "sg:province":"Sachsen",
    "wof:name":"Metro Sb-grossm\u00e4rkte Gmbh & Co. Kg",
    "wof:placetype":"venue"
},
  "geometry": {"coordinates":[12.8610954285,50.8658370972],"type":"Point"}
}