{
  "type": "Feature",
  "properties": {
    "iso:country":"DE",
    "sg:address":"Nordstr. 8",
    "sg:city":"Pritzwalk",
    "sg:phone":"+49 3395/304223",
    "sg:postcode":"16928",
    "sg:province":"Brandenburg",
    "wof:name":"F. Sch\u00fcgner",
    "wof:placetype":"venue"
},
  "geometry": {"coordinates":[12.1766834259,53.1563453674],"type":"Point"}
}