{
  "type": "Feature",
  "properties": {
    "iso:country":"DE",
    "sg:address":"Reitbahnweg 85",
    "sg:city":"Neubrandenburg",
    "sg:phone":"+49 395/4222423",
    "sg:postcode":"17034",
    "sg:province":"Mecklenburg-Vorpommern",
    "wof:name":"G. Onasch",
    "wof:placetype":"venue"
},
  "geometry": {"coordinates":[13.260429,53.571159],"type":"Point"}
}