{
  "type": "Feature",
  "properties": {
    "iso:country":"DE",
    "sg:address":"Bergfelder Str. 8",
    "sg:city":"V\u00f6hringen",
    "sg:phone":"+49 7454/92563",
    "sg:postcode":"72189",
    "sg:province":"Baden-W\u00fcrttemberg",
    "wof:name":"J\u00fcrgen Hoh",
    "wof:placetype":"venue"
},
  "geometry": {"coordinates":[8.662107,48.337608],"type":"Point"}
}