{
  "type": "Feature",
  "properties": {
    "iso:country":"DE",
    "sg:address":"An der Norderhake 5-7",
    "sg:city":"Eckernf\u00f6rde",
    "sg:phone":"+49 4351/5002",
    "sg:postcode":"24340",
    "sg:province":"Schleswig-Holstein",
    "wof:name":"Cc Gro\u00dfkauf Eckernf\u00f6rde Gmbh",
    "wof:placetype":"venue"
},
  "geometry": {"coordinates":[9.828627,54.472118],"type":"Point"}
}