{
  "type": "Feature",
  "properties": {
    "iso:country":"DE",
    "sg:address":"Brunnenfeldweg 1",
    "sg:city":"Geretsried",
    "sg:phone":"+49 8171/43130",
    "sg:postcode":"82538",
    "sg:province":"Bayern",
    "wof:name":"Nissan Design Europe Gmbh",
    "wof:placetype":"venue"
},
  "geometry": {"coordinates":[11.4386615753,47.8876152039],"type":"Point"}
}