{
  "type": "Feature",
  "properties": {
    "iso:country":"DE",
    "sg:address":"Bruchhagen 38",
    "sg:city":"Steyerberg",
    "sg:phone":"+49 5764/1881",
    "sg:postcode":"31595",
    "sg:province":"Niedersachsen",
    "wof:name":"Fashion Hair By Marita Hinz Gmbh",
    "wof:placetype":"venue"
},
  "geometry": {"coordinates":[8.97736,52.549824],"type":"Point"}
}