{
  "type": "Feature",
  "properties": {
    "iso:country":"DE",
    "sg:address":"Neuengammer Hausdeich 69",
    "sg:city":"Hamburg",
    "sg:phone":"+49 40/7235238",
    "sg:postcode":"21039",
    "sg:province":"Hamburg",
    "wof:name":"Rudolf Wulff",
    "wof:placetype":"venue"
},
  "geometry": {"coordinates":[10.246411,53.428822],"type":"Point"}
}