{
  "type": "Feature",
  "properties": {
    "iso:country":"DE",
    "sg:address":"Lindenstr. 12",
    "sg:city":"Neckarwestheim",
    "sg:phone":"+49 7133/95250",
    "sg:postcode":"74382",
    "sg:province":"Baden-W\u00fcrttemberg",
    "wof:name":"Walter Stahl",
    "wof:placetype":"venue"
},
  "geometry": {"coordinates":[9.1936578751,49.0466690063],"type":"Point"}
}