{
  "type": "Feature",
  "properties": {
    "iso:country":"DE",
    "sg:address":"Am Steg 18",
    "sg:city":"Gie\u00dfen",
    "sg:phone":"+49 641/7023894",
    "sg:postcode":"35392",
    "sg:province":"Hessen",
    "wof:name":"Zentrum F\u00fcr Psychiatrie Zentrum F\u00fcr Neurologie",
    "wof:placetype":"venue"
},
  "geometry": {"coordinates":[8.661939,50.573318],"type":"Point"}
}