{
  "type": "Feature",
  "properties": {
    "iso:country":"DE",
    "sg:address":"Spreestr. 13",
    "sg:city":"L\u00fcbbenau",
    "sg:phone":"+49 3542/41777",
    "sg:postcode":"03222",
    "sg:province":"Brandenburg",
    "wof:name":"Spreewald-idyll",
    "wof:placetype":"venue"
},
  "geometry": {"coordinates":[13.9694318771,51.8688240051],"type":"Point"}
}