{
  "type": "Feature",
  "properties": {
    "iso:country":"DE",
    "sg:address":"Faurndauer Str. 49",
    "sg:city":"Rechberghausen",
    "sg:postcode":"73098",
    "sg:province":"Baden-W\u00fcrttemberg",
    "wof:name":"Rl Spielautomatenbetriebs- Gmbh",
    "wof:placetype":"venue"
},
  "geometry": {"coordinates":[9.6391906738,48.7282333374],"type":"Point"}
}