{
  "type": "Feature",
  "properties": {
    "iso:country":"DE",
    "sg:address":"Glasuritstr. 1",
    "sg:city":"M\u00fcnster",
    "sg:phone":"+49 2501/140",
    "sg:postcode":"48165",
    "sg:province":"Nordrhein-Westfalen",
    "wof:name":"Glasurit Gmbh",
    "wof:placetype":"venue"
},
  "geometry": {"coordinates":[7.651166,51.901703],"type":"Point"}
}