{
  "type": "Feature",
  "properties": {
    "iso:country":"DE",
    "sg:address":"Karlsberger Str. 7",
    "sg:city":"Durach",
    "sg:phone":"+49 831/561120",
    "sg:postcode":"87471",
    "sg:province":"Bayern",
    "wof:name":"Allg\u00c4uer Furnier.-u. Sperr- Holzhandel Gmbh & Co.",
    "wof:placetype":"venue"
},
  "geometry": {"coordinates":[10.3422546387,47.700668335],"type":"Point"}
}