{
  "type": "Feature",
  "properties": {
    "iso:country":"DE",
    "sg:address":"Hansastr. 6",
    "sg:city":"Arnsberg",
    "sg:phone":"+49 2931/52640",
    "sg:postcode":"59821",
    "sg:province":"Nordrhein-Westfalen",
    "wof:name":"Aev-elektrogro\u00dfhandel Gmbh",
    "wof:placetype":"venue"
},
  "geometry": {"coordinates":[8.0646381378,51.4039459229],"type":"Point"}
}