{
  "type": "Feature",
  "properties": {
    "iso:country":"DE",
    "sg:address":"Friedenauer Str. 1b",
    "sg:city":"Hannover",
    "sg:phone":"+49 511/631261",
    "sg:postcode":"30419",
    "sg:province":"Niedersachsen",
    "wof:name":"Fred-bernd Bewernick Textilien Mode",
    "wof:placetype":"venue"
},
  "geometry": {"coordinates":[9.7139759064,52.4149436951],"type":"Point"}
}