{
  "type": "Feature",
  "properties": {
    "iso:country":"DE",
    "sg:address":"Duisburger Str. 80",
    "sg:city":"D\u00fcsseldorf",
    "sg:phone":"+49 211/4982285",
    "sg:postcode":"40479",
    "sg:province":"Nordrhein-Westfalen",
    "wof:name":"Kreta Reisen",
    "wof:placetype":"venue"
},
  "geometry": {"coordinates":[6.7843031883,51.2340698242],"type":"Point"}
}