{
  "type": "Feature",
  "properties": {
    "iso:country":"DE",
    "sg:address":"Im Unterfeld 1a",
    "sg:city":"Neuberg",
    "sg:postcode":"63543",
    "sg:province":"Hessen",
    "wof:name":"Msv M\u00f6bel-sonderposten Und Verwertungs Gmbh",
    "wof:placetype":"venue"
},
  "geometry": {"coordinates":[8.9920186996,50.1833152771],"type":"Point"}
}