{
  "type": "Feature",
  "properties": {
    "iso:country":"DE",
    "sg:address":"Hauptstrasse 1",
    "sg:city":"Budenheim",
    "sg:phone":"+49 5582/999781",
    "sg:postcode":"55257",
    "sg:province":"Rheinland-Pfalz",
    "wof:name":"Tafeu E.k.",
    "wof:placetype":"venue"
},
  "geometry": {"coordinates":[8.1720571518,50.0259284973],"type":"Point"}
}