{
  "type": "Feature",
  "properties": {
    "iso:country":"DE",
    "sg:address":"Karlsruher Str. 51",
    "sg:city":"Pforzheim",
    "sg:phone":"+49 7231/912850",
    "sg:postcode":"75179",
    "sg:province":"Baden-W\u00fcrttemberg",
    "wof:name":"Multi-media Gmbh",
    "wof:placetype":"venue"
},
  "geometry": {"coordinates":[8.664342,48.900909],"type":"Point"}
}