{
  "type": "Feature",
  "properties": {
    "iso:country":"DE",
    "sg:address":"Mariendorfer Damm 50-52",
    "sg:city":"Berlin",
    "sg:phone":"+49 30/7051078",
    "sg:postcode":"12109",
    "sg:province":"Berlin",
    "wof:name":"Steakhouse Becerro",
    "wof:placetype":"venue"
},
  "geometry": {"coordinates":[13.3849563599,52.4483909607],"type":"Point"}
}