{
  "type": "Feature",
  "properties": {
    "iso:country":"DE",
    "sg:address":"Dornberg 108",
    "sg:city":"Ansbach",
    "sg:phone":"+49 981/65786",
    "sg:postcode":"91522",
    "sg:province":"Bayern",
    "wof:name":"A. Mardefeld Anlage-und Finanzberater",
    "wof:placetype":"venue"
},
  "geometry": {"coordinates":[10.498623848,49.3069877625],"type":"Point"}
}