{
  "type": "Feature",
  "properties": {
    "iso:country":"DE",
    "sg:address":"Hilbertstr. 1-3",
    "sg:city":"Dresden",
    "sg:phone":"+49 351/4119625",
    "sg:postcode":"01169",
    "sg:province":"Sachsen",
    "wof:name":"Pulwer & Urlau Ohg",
    "wof:placetype":"venue"
},
  "geometry": {"coordinates":[13.672301,51.040012],"type":"Point"}
}