{
  "type": "Feature",
  "properties": {
    "iso:country":"DE",
    "sg:address":"Sch\u00f6nauergasse 4",
    "sg:city":"Oberwesel",
    "sg:phone":"+49 6744/221",
    "sg:postcode":"55430",
    "sg:province":"Rheinland-Pfalz",
    "wof:name":"Zum Lamm",
    "wof:placetype":"venue"
},
  "geometry": {"coordinates":[7.7281827927,50.1066818237],"type":"Point"}
}