{
  "type": "Feature",
  "properties": {
    "iso:country":"DE",
    "sg:address":"Amtsstr. 7",
    "sg:city":"Moorrege",
    "sg:phone":"+49 4122/967661",
    "sg:postcode":"25436",
    "sg:province":"Schleswig-Holstein",
    "wof:name":"Wolfgang Preck",
    "wof:placetype":"venue"
},
  "geometry": {"coordinates":[9.6739816666,53.6756515503],"type":"Point"}
}