{
  "type": "Feature",
  "properties": {
    "iso:country":"DE",
    "sg:address":"S\u00fcdring 43",
    "sg:city":"Bad Sch\u00f6nborn",
    "sg:phone":"+49 7253/94580",
    "sg:postcode":"76669",
    "sg:province":"Baden-W\u00fcrttemberg",
    "wof:name":"Famila Handels-betriebe Gmbh & Co. Kg",
    "wof:placetype":"venue"
},
  "geometry": {"coordinates":[8.6450090408,49.197303772],"type":"Point"}
}