{
  "type": "Feature",
  "properties": {
    "iso:country":"DE",
    "sg:address":"Budenheimer Weg 31 a",
    "sg:city":"Heidesheim",
    "sg:postcode":"55262",
    "sg:province":"Rheinland-Pfalz",
    "wof:name":"S. T. E. R. N. Schwei\u00dftechnik Und Industrieanlagen Gmbh",
    "wof:placetype":"venue"
},
  "geometry": {"coordinates":[8.1363754272,50.0054664612],"type":"Point"}
}