{
  "type": "Feature",
  "properties": {
    "iso:country":"DE",
    "sg:address":"Gereut 1",
    "sg:city":"Lahr",
    "sg:phone":"+49 7821/77744",
    "sg:postcode":"77933",
    "sg:province":"Baden-W\u00fcrttemberg",
    "wof:name":"Paul Fehrenbacher",
    "wof:placetype":"venue"
},
  "geometry": {"coordinates":[7.948418,48.339321],"type":"Point"}
}