{
  "type": "Feature",
  "properties": {
    "iso:country":"DE",
    "sg:address":"Heerstr. 15",
    "sg:city":"Hodenhagen",
    "sg:phone":"+49 5164/739",
    "sg:postcode":"29693",
    "sg:province":"Niedersachsen",
    "wof:name":"Siegfried K\u00f6rber",
    "wof:placetype":"venue"
},
  "geometry": {"coordinates":[9.586835,52.758179],"type":"Point"}
}