{
  "type": "Feature",
  "properties": {
    "iso:country":"DE",
    "sg:address":"Allmandstra\u00dfe 2",
    "sg:city":"Glatten",
    "sg:phone":"+49 7443/91083",
    "sg:postcode":"72293",
    "sg:province":"Baden-W\u00fcrttemberg",
    "wof:name":"Fertig-gardine.com",
    "wof:placetype":"venue"
},
  "geometry": {"coordinates":[8.5046396255,48.4441108704],"type":"Point"}
}