{
  "type": "Feature",
  "properties": {
    "iso:country":"DE",
    "sg:address":"Sonnenstr. 8",
    "sg:city":"Wallerfangen",
    "sg:phone":"+49 6831/60170",
    "sg:postcode":"66798",
    "sg:province":"Saarland",
    "wof:name":"C. Z\u00f6llner",
    "wof:placetype":"venue"
},
  "geometry": {"coordinates":[6.7147159576,49.3313293457],"type":"Point"}
}