{
  "type": "Feature",
  "properties": {
    "iso:country":"DE",
    "sg:address":"Schwennenbacher Str.",
    "sg:city":"H\u00f6chst\u00e4dt",
    "sg:phone":"+49 9074/706",
    "sg:postcode":"89420",
    "sg:province":"Bayern",
    "wof:name":"Gastst\u00e4tte H. Rothenh\u00e4usler",
    "wof:placetype":"venue"
},
  "geometry": {"coordinates":[10.5782012939,48.6491699219],"type":"Point"}
}