{
  "type": "Feature",
  "properties": {
    "iso:country":"DE",
    "sg:address":"Kaiserstr. 36",
    "sg:city":"Landstuhl",
    "sg:phone":"+49 6371/62256",
    "sg:postcode":"66849",
    "sg:province":"Rheinland-Pfalz",
    "wof:name":"G. Paulus Immobilienmakler",
    "wof:placetype":"venue"
},
  "geometry": {"coordinates":[7.5675349236,49.4128227234],"type":"Point"}
}