{
  "type": "Feature",
  "properties": {
    "iso:country":"DE",
    "sg:address":"Jahnstr. 28",
    "sg:city":"Stiege",
    "sg:phone":"+49 39459/71833",
    "sg:postcode":"38899",
    "sg:province":"Sachsen-Anhalt",
    "wof:name":"Juergen Weissleder",
    "wof:placetype":"venue"
},
  "geometry": {"coordinates":[10.883135,51.663757],"type":"Point"}
}