{
  "type": "Feature",
  "properties": {
    "iso:country":"DE",
    "sg:address":"Augustastr. 15",
    "sg:city":"Hattingen",
    "sg:phone":"+49 2324/202393",
    "sg:postcode":"45525",
    "sg:province":"Nordrhein-Westfalen",
    "wof:name":"Werner R\u00fcdig Rechtsanwalt",
    "wof:placetype":"venue"
},
  "geometry": {"coordinates":[7.184689045,51.3991699219],"type":"Point"}
}