{
  "type": "Feature",
  "properties": {
    "iso:country":"DE",
    "sg:address":"Ahornweg 2",
    "sg:city":"Sankt Augustin",
    "sg:phone":"+49 2241/337957",
    "sg:postcode":"53757",
    "sg:province":"Nordrhein-Westfalen",
    "wof:name":"F-research Forschungs- Und Entwicklungs Gmbh",
    "wof:placetype":"venue"
},
  "geometry": {"coordinates":[7.205535,50.77803],"type":"Point"}
}