{
  "type": "Feature",
  "properties": {
    "iso:country":"DE",
    "sg:address":"Rodderweg 149",
    "sg:city":"Br\u00fchl",
    "sg:phone":"+49 2232/920455",
    "sg:postcode":"50321",
    "sg:province":"Nordrhein-Westfalen",
    "wof:name":"Iwb International Wine Broker Handelsgesellschaft Mbh",
    "wof:placetype":"venue"
},
  "geometry": {"coordinates":[6.8785738945,50.8256721497],"type":"Point"}
}