{
  "type": "Feature",
  "properties": {
    "iso:country":"DE",
    "sg:address":"Kurt-Schumacher-Str. 54",
    "sg:city":"Gelsenkirchen",
    "sg:phone":"+49 209/84079",
    "sg:postcode":"45881",
    "sg:province":"Nordrhein-Westfalen",
    "wof:name":"Manfred Faltin Architekt",
    "wof:placetype":"venue"
},
  "geometry": {"coordinates":[7.091644,51.519009],"type":"Point"}
}