{
  "type": "Feature",
  "properties": {
    "iso:country":"DE",
    "sg:address":"Schulstr. 8",
    "sg:city":"Lug",
    "sg:phone":"+49 6392/2133",
    "sg:postcode":"76848",
    "sg:province":"Rheinland-Pfalz",
    "wof:name":"Treffpunkt",
    "wof:placetype":"venue"
},
  "geometry": {"coordinates":[7.8931221962,49.1816368103],"type":"Point"}
}