{
  "type": "Feature",
  "properties": {
    "iso:country":"DE",
    "sg:address":"Rheinstr. 10a",
    "sg:city":"Teltow",
    "sg:phone":"+49 3328/43050",
    "sg:postcode":"14513",
    "sg:province":"Brandenburg",
    "wof:name":"Kopier Potsdam Gmbh",
    "wof:placetype":"venue"
},
  "geometry": {"coordinates":[13.243608,52.398792],"type":"Point"}
}