{
  "type": "Feature",
  "properties": {
    "iso:country":"DE",
    "sg:address":"Sulterkamp 54 (Am Autokino)",
    "sg:city":"Essen",
    "sg:phone":"+49 201/619070",
    "sg:postcode":"45356",
    "sg:province":"Nordrhein-Westfalen",
    "wof:name":"Leckebusch Gmbh",
    "wof:placetype":"venue"
},
  "geometry": {"coordinates":[6.9717020988,51.4857406616],"type":"Point"}
}