{
  "type": "Feature",
  "properties": {
    "iso:country":"DE",
    "sg:address":"Wiesenstr. 8",
    "sg:city":"Gehrden",
    "sg:phone":"+49 5108/5438",
    "sg:postcode":"30989",
    "sg:province":"Niedersachsen",
    "wof:name":"Dr. H. Prasser Ingenieur",
    "wof:placetype":"venue"
},
  "geometry": {"coordinates":[9.5662899017,52.3013191223],"type":"Point"}
}