{
  "type": "Feature",
  "properties": {
    "iso:country":"DE",
    "sg:address":"Schulstr. 7",
    "sg:city":"Bokel",
    "sg:phone":"+49 4748/1773",
    "sg:postcode":"27616",
    "sg:province":"Niedersachsen",
    "wof:name":"Wilhelm Schmidt",
    "wof:placetype":"venue"
},
  "geometry": {"coordinates":[8.7676267624,53.3940124512],"type":"Point"}
}