{
  "type": "Feature",
  "properties": {
    "iso:country":"DE",
    "sg:address":"Hauptstr. 103",
    "sg:city":"Finowfurt",
    "sg:phone":"+49 3335/7243",
    "sg:postcode":"16244",
    "sg:province":"Brandenburg",
    "wof:name":"Maa\u00df Und Partner",
    "wof:placetype":"venue"
},
  "geometry": {"coordinates":[13.6825370789,52.8439979553],"type":"Point"}
}