{
  "type": "Feature",
  "properties": {
    "iso:country":"DE",
    "sg:address":"Kapellenstr. 7",
    "sg:city":"Frittlingen",
    "sg:phone":"+49 7426/96190",
    "sg:postcode":"78665",
    "sg:province":"Baden-W\u00fcrttemberg",
    "wof:name":"Gastst\u00e4tte Sonnenst\u00fcble",
    "wof:placetype":"venue"
},
  "geometry": {"coordinates":[8.7065429688,48.127822876],"type":"Point"}
}