{
  "type": "Feature",
  "properties": {
    "iso:country":"DE",
    "sg:address":"Styrumer Str. 29",
    "sg:city":"Essen",
    "sg:phone":"+49 201/623481",
    "sg:postcode":"45143",
    "sg:province":"Nordrhein-Westfalen",
    "wof:name":"Samuel Leonbacher",
    "wof:placetype":"venue"
},
  "geometry": {"coordinates":[6.965085,51.464573],"type":"Point"}
}