{
  "type": "Feature",
  "properties": {
    "iso:country":"DE",
    "sg:address":"Am Graben 1",
    "sg:city":"P\u00f6ttmes",
    "sg:phone":"+49 8253/92908",
    "sg:postcode":"86554",
    "sg:province":"Bayern",
    "wof:name":"Helmut Hasenfratz",
    "wof:placetype":"venue"
},
  "geometry": {"coordinates":[11.0900268555,48.5827827454],"type":"Point"}
}