{
  "type": "Feature",
  "properties": {
    "iso:country":"DE",
    "sg:address":"Geilingsgasse 60 a",
    "sg:city":"Tonna",
    "sg:phone":"+49 36042/79738",
    "sg:postcode":"99958",
    "sg:province":"Th\u00fcringen",
    "wof:name":"Giesbert Thiede",
    "wof:placetype":"venue"
},
  "geometry": {"coordinates":[10.72232,51.063622],"type":"Point"}
}