{
  "type": "Feature",
  "properties": {
    "iso:country":"DE",
    "sg:address":"Nibelungenstr. 225",
    "sg:city":"Lautertal",
    "sg:phone":"+49 6254/942120",
    "sg:postcode":"64686",
    "sg:province":"Hessen",
    "wof:name":"Roland M\u00fcller",
    "wof:placetype":"venue"
},
  "geometry": {"coordinates":[8.6905088425,49.7102775574],"type":"Point"}
}