{
  "type": "Feature",
  "properties": {
    "iso:country":"DE",
    "sg:address":"Zum \u00d6sterreich 9",
    "sg:city":"Ostercappeln",
    "sg:phone":"+49 5473/1223",
    "sg:postcode":"49179",
    "sg:province":"Niedersachsen",
    "wof:name":"F. W. Und K. Reller Ohg",
    "wof:placetype":"venue"
},
  "geometry": {"coordinates":[8.2651166916,52.3310470581],"type":"Point"}
}