{
  "type": "Feature",
  "properties": {
    "iso:country":"DE",
    "sg:address":"Carolus-Magnus-Str. 12",
    "sg:city":"Marsberg",
    "sg:phone":"+49 2992/97800",
    "sg:postcode":"34431",
    "sg:province":"Nordrhein-Westfalen",
    "wof:name":"Rec Rehfeldt Edv Consulting Gmbh",
    "wof:placetype":"venue"
},
  "geometry": {"coordinates":[8.8335895538,51.452419281],"type":"Point"}
}