{
  "type": "Feature",
  "properties": {
    "iso:country":"DE",
    "sg:address":"Am Viertelacker 32c",
    "sg:city":"Dresden",
    "sg:postcode":"01259",
    "sg:province":"Sachsen",
    "wof:name":"Autohaus N. 1 Ash Gmbh",
    "wof:placetype":"venue"
},
  "geometry": {"coordinates":[13.8112039566,50.9851951599],"type":"Point"}
}