{
  "type": "Feature",
  "properties": {
    "iso:country":"DE",
    "sg:address":"Am Okerufer 25",
    "sg:city":"Wolfenb\u00fcttel",
    "sg:phone":"+49 5331/75856",
    "sg:postcode":"38302",
    "sg:province":"Niedersachsen",
    "wof:name":"Marie-luise Wilke Heilpraktikerin",
    "wof:placetype":"venue"
},
  "geometry": {"coordinates":[10.5375728607,52.1671981812],"type":"Point"}
}