{
  "type": "Feature",
  "properties": {
    "iso:country":"DE",
    "sg:address":"Goethestr. 3",
    "sg:city":"Riegelsberg",
    "sg:phone":"+49 6806/3167",
    "sg:postcode":"66292",
    "sg:province":"Saarland",
    "wof:name":"Feingoldstube",
    "wof:placetype":"venue"
},
  "geometry": {"coordinates":[6.939699173,49.3192710876],"type":"Point"}
}