{
  "type": "Feature",
  "properties": {
    "iso:country":"DE",
    "sg:address":"T\u00f6lzer Str. 39c",
    "sg:city":"Gr\u00fcnwald",
    "sg:phone":"+49 89/6492295",
    "sg:postcode":"82031",
    "sg:province":"Bayern",
    "wof:name":"Scs Hotels Und Boardinghouses Betriebs Gmbh",
    "wof:placetype":"venue"
},
  "geometry": {"coordinates":[11.5206365585,48.0319290161],"type":"Point"}
}