{
  "type": "Feature",
  "properties": {
    "iso:country":"DE",
    "sg:address":"Kahnstr. 8",
    "sg:city":"Falken",
    "sg:postcode":"99830",
    "sg:province":"Th\u00fcringen",
    "wof:name":"Brennstoff Landhandel-heiz\u00f6l Inh. Heinz-j\u00fcrgen B\u00f6hm",
    "wof:placetype":"venue"
},
  "geometry": {"coordinates":[10.2674303055,51.1191673279],"type":"Point"}
}