{
  "type": "Feature",
  "properties": {
    "iso:country":"DE",
    "sg:address":"Gutenbergstr. 2c",
    "sg:city":"Erlangen",
    "sg:phone":"+49 9131/67273",
    "sg:postcode":"91058",
    "sg:province":"Bayern",
    "wof:name":"Karin Melzer",
    "wof:placetype":"venue"
},
  "geometry": {"coordinates":[11.0035572052,49.5659790039],"type":"Point"}
}