{
  "type": "Feature",
  "properties": {
    "iso:country":"DE",
    "sg:address":"Kirchgasse 5",
    "sg:city":"Moos",
    "sg:phone":"+49 7732/3222",
    "sg:postcode":"78345",
    "sg:province":"Baden-W\u00fcrttemberg",
    "wof:name":"G\u00e4stehaus Albert Jauch",
    "wof:placetype":"venue"
},
  "geometry": {"coordinates":[8.9339084625,47.7250213623],"type":"Point"}
}