{
  "type": "Feature",
  "properties": {
    "iso:country":"DE",
    "sg:address":"Pfarrgasse 2",
    "sg:city":"Schwabach",
    "sg:phone":"+49 9122/85075",
    "sg:postcode":"91126",
    "sg:province":"Bayern",
    "wof:name":"Klein\u00f6der Reiseb\u00fcro",
    "wof:placetype":"venue"
},
  "geometry": {"coordinates":[11.0228204727,49.3293991089],"type":"Point"}
}