{
  "type": "Feature",
  "properties": {
    "iso:country":"DE",
    "sg:address":"Cuxhavener Str. 481",
    "sg:city":"Hamburg",
    "sg:phone":"+49 40/7018026",
    "sg:postcode":"21149",
    "sg:province":"Hamburg",
    "wof:name":"Brigitta Meyer",
    "wof:placetype":"venue"
},
  "geometry": {"coordinates":[9.8213558197,53.4701805115],"type":"Point"}
}