{
  "type": "Feature",
  "properties": {
    "iso:country":"DE",
    "sg:address":"M\u00f6nkhofer Weg 78",
    "sg:city":"L\u00fcbeck",
    "sg:phone":"+49 451/583160",
    "sg:postcode":"23562",
    "sg:province":"Schleswig-Holstein",
    "wof:name":"Apotheke Am M\u00f6nkhofer Weg Eiko Franz",
    "wof:placetype":"venue"
},
  "geometry": {"coordinates":[10.699065,53.844604],"type":"Point"}
}