{
  "type": "Feature",
  "properties": {
    "iso:country":"DE",
    "sg:address":"Karl-Marx-Allee 108",
    "sg:city":"Berlin",
    "sg:phone":"+49 30/2947883",
    "sg:postcode":"10243",
    "sg:province":"Berlin",
    "wof:name":"Fleischerei Neuling",
    "wof:placetype":"venue"
},
  "geometry": {"coordinates":[13.445133,52.516472],"type":"Point"}
}