{
  "type": "Feature",
  "properties": {
    "iso:country":"DE",
    "sg:address":"Rheinstr. 2",
    "sg:city":"Murg",
    "sg:phone":"+49 7763/6060",
    "sg:postcode":"79730",
    "sg:province":"Baden-W\u00fcrttemberg",
    "wof:name":"Manfred Z\u00e4pf",
    "wof:placetype":"venue"
},
  "geometry": {"coordinates":[8.021318,47.553097],"type":"Point"}
}