{
  "type": "Feature",
  "properties": {
    "iso:country":"DE",
    "sg:address":"Dorotheenstr. 64",
    "sg:city":"Hamburg",
    "sg:postcode":"22301",
    "sg:province":"Hamburg",
    "wof:name":"Selangor Verm\u00f6gens- Verwaltungsgesellschaft Mbh",
    "wof:placetype":"venue"
},
  "geometry": {"coordinates":[10.0078134537,53.5836715698],"type":"Point"}
}