{
  "type": "Feature",
  "properties": {
    "iso:country":"DE",
    "sg:address":"B\u00e4rnfels 136",
    "sg:city":"Obertrubach",
    "sg:phone":"+49 9245/1332",
    "sg:postcode":"91286",
    "sg:province":"Bayern",
    "wof:name":"Hubert R\u00f6hrer",
    "wof:placetype":"venue"
},
  "geometry": {"coordinates":[11.33531,49.71283],"type":"Point"}
}