{
  "type": "Feature",
  "properties": {
    "iso:country":"DE",
    "sg:address":"Rehwechsel 7b",
    "sg:city":"Rosengarten",
    "sg:phone":"+49 40/344715",
    "sg:postcode":"21224",
    "sg:province":"Niedersachsen",
    "wof:name":"Doris Benemann Glas- Und Porzellanwaren",
    "wof:placetype":"venue"
},
  "geometry": {"coordinates":[9.8918733597,53.4512138367],"type":"Point"}
}