{
  "type": "Feature",
  "properties": {
    "iso:country":"DE",
    "sg:address":"W\u00fcrttembergstr. 2",
    "sg:city":"Regensburg",
    "sg:phone":"+49 941/22278",
    "sg:postcode":"93049",
    "sg:province":"Bayern",
    "wof:name":"Martha Schier Hebamme",
    "wof:placetype":"venue"
},
  "geometry": {"coordinates":[12.080212,49.023563],"type":"Point"}
}