{
  "type": "Feature",
  "properties": {
    "iso:country":"DE",
    "sg:address":"Talstr. 7",
    "sg:city":"St\u00fchlingen",
    "sg:phone":"+49 7744/5099",
    "sg:postcode":"79780",
    "sg:province":"Baden-W\u00fcrttemberg",
    "wof:name":"E. Stei\u00df Gmbh",
    "wof:placetype":"venue"
},
  "geometry": {"coordinates":[8.427570343,47.778678894],"type":"Point"}
}