{
  "type": "Feature",
  "properties": {
    "iso:country":"DE",
    "sg:address":"Zweibr\u00fccker Str. 209",
    "sg:city":"Pirmasens",
    "sg:postcode":"66954",
    "sg:province":"Rheinland-Pfalz",
    "wof:name":"Gesch\u00e4ftsf\u00fchrungsgesellschaft R. Th. Dully Lederfabrik Mbh",
    "wof:placetype":"venue"
},
  "geometry": {"coordinates":[7.592592,49.222092],"type":"Point"}
}