{
  "type": "Feature",
  "properties": {
    "iso:country":"DE",
    "sg:address":"Damerowsweg 4",
    "sg:city":"Hamburg",
    "sg:postcode":"22081",
    "sg:province":"Hamburg",
    "wof:name":"Evolving Systems Consulting Gmbh",
    "wof:placetype":"venue"
},
  "geometry": {"coordinates":[10.0515956879,53.5801467896],"type":"Point"}
}