{
  "type": "Feature",
  "properties": {
    "iso:country":"DE",
    "sg:address":"Hauptstr. 63",
    "sg:city":"Riegel",
    "sg:phone":"+49 7642/6880",
    "sg:postcode":"79359",
    "sg:province":"Baden-W\u00fcrttemberg",
    "wof:name":"Stiftung Erzbisch\u00f6fliches Kinderheim St. Anton",
    "wof:placetype":"venue"
},
  "geometry": {"coordinates":[7.7479090691,48.1504592896],"type":"Point"}
}