{
  "type": "Feature",
  "properties": {
    "iso:country":"DE",
    "sg:address":"H\u00fclser Str. 9",
    "sg:city":"Kempen",
    "sg:phone":"+49 2152/209550",
    "sg:postcode":"47906",
    "sg:province":"Nordrhein-Westfalen",
    "wof:name":"Appartmenthotel Thomasstadt",
    "wof:placetype":"venue"
},
  "geometry": {"coordinates":[6.4248900414,51.3644294739],"type":"Point"}
}