{
  "type": "Feature",
  "properties": {
    "iso:country":"DE",
    "sg:address":"Silcherstr. 22",
    "sg:city":"H\u00f6chstadt",
    "sg:postcode":"91315",
    "sg:province":"Bayern",
    "wof:name":"Jeans-shop Blue Corner Peter Jerundow",
    "wof:placetype":"venue"
},
  "geometry": {"coordinates":[10.8242197037,49.7132606506],"type":"Point"}
}