{
  "type": "Feature",
  "properties": {
    "iso:country":"DE",
    "sg:address":"Donnerburgstr. 23",
    "sg:city":"Denkte",
    "sg:phone":"+49 5331/68020",
    "sg:postcode":"38321",
    "sg:province":"Niedersachsen",
    "wof:name":"Hermann Heine",
    "wof:placetype":"venue"
},
  "geometry": {"coordinates":[10.58906,52.142506],"type":"Point"}
}