{
  "type": "Feature",
  "properties": {
    "iso:country":"DE",
    "sg:address":"Scheyerner Weg 3",
    "sg:city":"M\u00fcnchen",
    "sg:phone":"+49 89/17809529",
    "sg:postcode":"80638",
    "sg:province":"Bayern",
    "wof:name":"Gateway Logistik Gmbh",
    "wof:placetype":"venue"
},
  "geometry": {"coordinates":[11.51416,48.16621],"type":"Point"}
}