{
  "type": "Feature",
  "properties": {
    "iso:country":"DE",
    "sg:address":"Lotter Str. 19",
    "sg:city":"Osnabr\u00fcck",
    "sg:phone":"+49 541/47790",
    "sg:postcode":"49078",
    "sg:province":"Niedersachsen",
    "wof:name":"Gastst\u00e4tte Journal",
    "wof:placetype":"venue"
},
  "geometry": {"coordinates":[8.034029007,52.2747764587],"type":"Point"}
}