{
  "type": "Feature",
  "properties": {
    "iso:country":"DE",
    "sg:address":"Schulstr. 19",
    "sg:city":"Durbach",
    "sg:phone":"+49 781/42947",
    "sg:postcode":"77770",
    "sg:province":"Baden-W\u00fcrttemberg",
    "wof:name":"Erich Werner",
    "wof:placetype":"venue"
},
  "geometry": {"coordinates":[7.983015,48.504765],"type":"Point"}
}