{
  "type": "Feature",
  "properties": {
    "iso:country":"DE",
    "sg:address":"Georgenstr. 123",
    "sg:city":"M\u00fcnchen",
    "sg:phone":"+49 89/183008",
    "sg:postcode":"80797",
    "sg:province":"Bayern",
    "wof:name":"Verlag Antje Kunstmann",
    "wof:placetype":"venue"
},
  "geometry": {"coordinates":[11.56091,48.157326],"type":"Point"}
}