{
  "type": "Feature",
  "properties": {
    "iso:country":"DE",
    "sg:address":"Bonner Wall 27",
    "sg:city":"K\u00f6ln",
    "sg:phone":"+49 221/9370050",
    "sg:postcode":"50677",
    "sg:province":"Nordrhein-Westfalen",
    "wof:name":"Schmitt Verwaltungs- Gesellschaft Mbh",
    "wof:placetype":"venue"
},
  "geometry": {"coordinates":[6.954708,50.916946],"type":"Point"}
}