{
  "type": "Feature",
  "properties": {
    "iso:country":"DE",
    "sg:address":"Alte Poststr. 49",
    "sg:city":"Elze",
    "sg:phone":"+49 5068/3131",
    "sg:postcode":"31008",
    "sg:province":"Niedersachsen",
    "wof:name":"Reitsport Ebeling",
    "wof:placetype":"venue"
},
  "geometry": {"coordinates":[9.692898,52.113598],"type":"Point"}
}