{
  "type": "Feature",
  "properties": {
    "iso:country":"DE",
    "sg:address":"Str d Opf d Faschismus 30",
    "sg:city":"Gardelegen",
    "sg:postcode":"39638",
    "sg:province":"Sachsen-Anhalt",
    "wof:name":"I. M\u00fcller",
    "wof:placetype":"venue"
},
  "geometry": {"coordinates":[11.4085674286,52.5304450989],"type":"Point"}
}