{
  "type": "Feature",
  "properties": {
    "iso:country":"DE",
    "sg:address":"Am Busch 5",
    "sg:city":"Rheinberg",
    "sg:phone":"+49 2843/3751",
    "sg:postcode":"47495",
    "sg:province":"Nordrhein-Westfalen",
    "wof:name":"Johannes Hunold",
    "wof:placetype":"venue"
},
  "geometry": {"coordinates":[6.635352,51.530704],"type":"Point"}
}