{
  "type": "Feature",
  "properties": {
    "iso:country":"DE",
    "sg:address":"Auf dem Rode 19a",
    "sg:city":"Hagen",
    "sg:phone":"+49 2331/45774",
    "sg:postcode":"58135",
    "sg:province":"Nordrhein-Westfalen",
    "wof:name":"Werner B\u00f6hne Ingenieur",
    "wof:placetype":"venue"
},
  "geometry": {"coordinates":[7.4270467758,51.3578453064],"type":"Point"}
}