{
  "type": "Feature",
  "properties": {
    "iso:country":"DE",
    "sg:address":"Im Riedle 9",
    "sg:city":"Nersingen",
    "sg:phone":"+49 7308/96950",
    "sg:postcode":"89278",
    "sg:province":"Bayern",
    "wof:name":"Ms-parts Gmbh",
    "wof:placetype":"venue"
},
  "geometry": {"coordinates":[10.1151895523,48.4277191162],"type":"Point"}
}