{
  "type": "Feature",
  "properties": {
    "iso:country":"DE",
    "sg:address":"Fr\u00fchlingstr. 16",
    "sg:city":"Lindenberg",
    "sg:phone":"+49 8381/1511",
    "sg:postcode":"88161",
    "sg:province":"Bayern",
    "wof:name":"Kapellenverein Nadenberg E. V. Josef Kraft",
    "wof:placetype":"venue"
},
  "geometry": {"coordinates":[9.8870000839,47.6100616455],"type":"Point"}
}