{
  "type": "Feature",
  "properties": {
    "iso:country":"DE",
    "sg:address":"Am Kindergarten 17",
    "sg:city":"Lingen",
    "sg:phone":"+49 591/7918",
    "sg:postcode":"49811",
    "sg:province":"Niedersachsen",
    "wof:name":"Stoffzentrale Manfred Herzig",
    "wof:placetype":"venue"
},
  "geometry": {"coordinates":[7.362896,52.554508],"type":"Point"}
}