{
  "type": "Feature",
  "properties": {
    "iso:country":"DE",
    "sg:address":"Carl-Maria-von-Weber-Str. 7",
    "sg:city":"Bayreuth",
    "sg:phone":"+49 921/22377",
    "sg:postcode":"95448",
    "sg:province":"Bayern",
    "wof:name":"Kachelofenbau D\u00f6tschel Walter D\u00f6tschel",
    "wof:placetype":"venue"
},
  "geometry": {"coordinates":[11.5875406265,49.9483757019],"type":"Point"}
}