{
  "type": "Feature",
  "properties": {
    "iso:country":"DE",
    "sg:address":"Hermannstr. 6",
    "sg:city":"D\u00fcsseldorf",
    "sg:phone":"+49 211/682278",
    "sg:postcode":"40233",
    "sg:province":"Nordrhein-Westfalen",
    "wof:name":"Dr. Manfred C\u00fcrten Rechtsanwalt",
    "wof:placetype":"venue"
},
  "geometry": {"coordinates":[6.8072252274,51.2311401367],"type":"Point"}
}