{
  "type": "Feature",
  "properties": {
    "iso:country":"DE",
    "sg:address":"Nikolaus-R\u00fcdinger-Str. 17",
    "sg:city":"M\u00fcnchen",
    "sg:phone":"+49 89/8122171",
    "sg:postcode":"80999",
    "sg:province":"Bayern",
    "wof:name":"Allacher Apotheke Sigrid-renate Drasch",
    "wof:placetype":"venue"
},
  "geometry": {"coordinates":[11.462622,48.189457],"type":"Point"}
}