{
  "type": "Feature",
  "properties": {
    "iso:country":"DE",
    "sg:address":"Im Holte 72",
    "sg:city":"Gevelsberg",
    "sg:phone":"+49 2332/10812",
    "sg:postcode":"58285",
    "sg:province":"Nordrhein-Westfalen",
    "wof:name":"P. G. Lindenberg Ingenieur",
    "wof:placetype":"venue"
},
  "geometry": {"coordinates":[7.317138195,51.3131256104],"type":"Point"}
}