{
  "type": "Feature",
  "properties": {
    "iso:country":"DE",
    "sg:address":"Fremersbergstr. 55",
    "sg:city":"Baden-Baden",
    "sg:phone":"+49 7221/64470",
    "sg:postcode":"76530",
    "sg:province":"Baden-W\u00fcrttemberg",
    "wof:name":"Media Consult Buscher Gmbh",
    "wof:placetype":"venue"
},
  "geometry": {"coordinates":[8.2284231186,48.7532043457],"type":"Point"}
}