{
  "type": "Feature",
  "properties": {
    "iso:country":"DE",
    "sg:address":"Braunschweiger Str 20",
    "sg:city":"Eicklingen",
    "sg:phone":"+49 5144/5200",
    "sg:postcode":"29358",
    "sg:province":"Niedersachsen",
    "wof:name":"Atelier Fineline Gbr",
    "wof:placetype":"venue"
},
  "geometry": {"coordinates":[10.1811857224,52.5484008789],"type":"Point"}
}