{
  "type": "Feature",
  "properties": {
    "iso:country":"DE",
    "sg:address":"Friedensstr. 3",
    "sg:city":"Offenbach",
    "sg:postcode":"63071",
    "sg:province":"Hessen",
    "wof:name":"Habag Bau Gmbh",
    "wof:placetype":"venue"
},
  "geometry": {"coordinates":[8.7671146393,50.0979499817],"type":"Point"}
}