{
  "type": "Feature",
  "properties": {
    "iso:country":"DE",
    "sg:address":"Rodheimer Str. 7",
    "sg:city":"Niddatal",
    "sg:postcode":"61194",
    "sg:province":"Hessen",
    "wof:name":"A & D Wohnbau Gmbh",
    "wof:placetype":"venue"
},
  "geometry": {"coordinates":[8.7948246002,50.2815322876],"type":"Point"}
}