{
  "type": "Feature",
  "properties": {
    "iso:country":"DE",
    "sg:address":"W\u00fcrzburger Str. 26",
    "sg:city":"Lohr",
    "sg:phone":"+49 9352/4321",
    "sg:postcode":"97816",
    "sg:province":"Bayern",
    "wof:name":"Martin E. Endres Consult Gmbh",
    "wof:placetype":"venue"
},
  "geometry": {"coordinates":[9.5845441818,49.994304657],"type":"Point"}
}