{
  "type": "Feature",
  "properties": {
    "iso:country":"DE",
    "sg:address":"Wehmkamp 1",
    "sg:city":"Sehnde",
    "sg:phone":"+49 5138/8049",
    "sg:postcode":"31319",
    "sg:province":"Niedersachsen",
    "wof:name":"I. Ude Immobilienmakler",
    "wof:placetype":"venue"
},
  "geometry": {"coordinates":[10.0035533905,52.3180427551],"type":"Point"}
}