{
  "type": "Feature",
  "properties": {
    "iso:country":"DE",
    "sg:address":"Carl-Benz-Str. 8",
    "sg:city":"Lahr",
    "sg:phone":"+49 4978/214966",
    "sg:postcode":"77933",
    "sg:province":"Baden-W\u00fcrttemberg",
    "wof:name":"B\u00dchler Gmbh",
    "wof:placetype":"venue"
},
  "geometry": {"coordinates":[7.826900959,48.3419685364],"type":"Point"}
}