{
  "type": "Feature",
  "properties": {
    "iso:country":"DE",
    "sg:address":"Dorfstr. 25",
    "sg:city":"Mustin",
    "sg:phone":"+49 4546/321",
    "sg:postcode":"23911",
    "sg:province":"Schleswig-Holstein",
    "wof:name":"Alfred Vogel",
    "wof:placetype":"venue"
},
  "geometry": {"coordinates":[10.8854579926,53.6854896545],"type":"Point"}
}