{
  "type": "Feature",
  "properties": {
    "iso:country":"DE",
    "sg:address":"Wallstr. 7",
    "sg:city":"Ockfen",
    "sg:phone":"+49 6581/2120",
    "sg:postcode":"54441",
    "sg:province":"Rheinland-Pfalz",
    "wof:name":"Helmut G\u00f6rgen",
    "wof:placetype":"venue"
},
  "geometry": {"coordinates":[6.5829920769,49.6245231628],"type":"Point"}
}