{
  "type": "Feature",
  "properties": {
    "iso:country":"DE",
    "sg:address":"Eibiswiesenstr. 12",
    "sg:city":"Bad Wildbad",
    "sg:phone":"+49 7081/6278",
    "sg:postcode":"75323",
    "sg:province":"Baden-W\u00fcrttemberg",
    "wof:name":"Oskar Barth",
    "wof:placetype":"venue"
},
  "geometry": {"coordinates":[8.5739307404,48.776386261],"type":"Point"}
}