{
  "type": "Feature",
  "properties": {
    "iso:country":"DE",
    "sg:address":"Grabenstr. 27",
    "sg:city":"Guldental",
    "sg:phone":"+49 6707/670",
    "sg:postcode":"55452",
    "sg:province":"Rheinland-Pfalz",
    "wof:name":"Alfons Und Bernd Lukas",
    "wof:placetype":"venue"
},
  "geometry": {"coordinates":[7.8413529396,49.8918876648],"type":"Point"}
}