{
  "type": "Feature",
  "properties": {
    "iso:country":"DE",
    "sg:address":"Ruppiner Chaussee 37 b",
    "sg:city":"Kremmen",
    "sg:phone":"+49 33055/70321",
    "sg:postcode":"16766",
    "sg:province":"Brandenburg",
    "wof:name":"Hans J\u00fcrgen Knu\u00dfmann",
    "wof:placetype":"venue"
},
  "geometry": {"coordinates":[13.0339298248,52.7666740417],"type":"Point"}
}