{
  "type": "Feature",
  "properties": {
    "iso:country":"DE",
    "sg:address":"Obere Str. 11",
    "sg:city":"Wurmlingen",
    "sg:phone":"+49 7461/5475",
    "sg:postcode":"78573",
    "sg:province":"Baden-W\u00fcrttemberg",
    "wof:name":"Karl Bacher",
    "wof:placetype":"venue"
},
  "geometry": {"coordinates":[8.7782516479,48.0043411255],"type":"Point"}
}