{
  "type": "Feature",
  "properties": {
    "iso:country":"DE",
    "sg:address":"Schlo\u00dfmattenstr. 5",
    "sg:city":"B\u00f6tzingen",
    "sg:phone":"+49 7663/5132",
    "sg:postcode":"79268",
    "sg:province":"Baden-W\u00fcrttemberg",
    "wof:name":"Minimal",
    "wof:placetype":"venue"
},
  "geometry": {"coordinates":[7.7225551605,48.0652656555],"type":"Point"}
}