{
  "type": "Feature",
  "properties": {
    "iso:country":"DE",
    "sg:address":"Breidenbacherstr. 4",
    "sg:city":"Mainz",
    "sg:phone":"+49 6131/229219",
    "sg:postcode":"55116",
    "sg:province":"Rheinland-Pfalz",
    "wof:name":"Hans-horst M\u00f6bes Graphik-designer",
    "wof:placetype":"venue"
},
  "geometry": {"coordinates":[8.267477,49.996712],"type":"Point"}
}