{
  "type": "Feature",
  "properties": {
    "iso:country":"DE",
    "sg:address":"Hohenhorster Kirchweg 26",
    "sg:city":"Isernhagen",
    "sg:phone":"+49 511/776676",
    "sg:postcode":"30916",
    "sg:province":"Niedersachsen",
    "wof:name":"Helga Leyendecker Steuerberaterin",
    "wof:placetype":"venue"
},
  "geometry": {"coordinates":[9.8047761917,52.4733123779],"type":"Point"}
}