{
  "type": "Feature",
  "properties": {
    "iso:country":"DE",
    "sg:address":"Philippstr. 32",
    "sg:city":"Essen",
    "sg:phone":"+49 201/332134",
    "sg:postcode":"45327",
    "sg:province":"Nordrhein-Westfalen",
    "wof:name":"Airboard Airbanner.de Shlomo Weiss E. K.",
    "wof:placetype":"venue"
},
  "geometry": {"coordinates":[7.0236301422,51.4952926636],"type":"Point"}
}