{
  "type": "Feature",
  "properties": {
    "iso:country":"DE",
    "sg:address":"Kettelerstr. 19",
    "sg:city":"Dreieich",
    "sg:phone":"+49 6103/936212",
    "sg:postcode":"63303",
    "sg:province":"Hessen",
    "wof:name":"J. H. Erhard",
    "wof:placetype":"venue"
},
  "geometry": {"coordinates":[8.688368,50.034222],"type":"Point"}
}