{
  "type": "Feature",
  "properties": {
    "iso:country":"DE",
    "sg:address":"Hauptstr. 272 POSTFACH 1210",
    "sg:city":"R\u00f6srath",
    "sg:phone":"+49 4922/0592430",
    "sg:postcode":"51493",
    "sg:province":"Nordrhein-Westfalen",
    "wof:name":"Pilgram Druck U. Dienstleistung Gmbh & Co. Kg",
    "wof:placetype":"venue"
},
  "geometry": {"coordinates":[7.1983160973,50.9156074524],"type":"Point"}
}