{
  "type": "Feature",
  "properties": {
    "iso:country":"DE",
    "sg:address":"Pfingstbornstr. 27",
    "sg:city":"Oberursel",
    "sg:phone":"+49 6171/74126",
    "sg:postcode":"61440",
    "sg:province":"Hessen",
    "wof:name":"Redaktion Vdl Informiert Verband D. Lehrer",
    "wof:placetype":"venue"
},
  "geometry": {"coordinates":[8.5783452988,50.1831893921],"type":"Point"}
}