{
  "type": "Feature",
  "properties": {
    "iso:country":"DE",
    "sg:address":"Vordere Sterngasse 28",
    "sg:city":"N\u00fcrnberg",
    "sg:phone":"+49 911/2059737",
    "sg:postcode":"90402",
    "sg:province":"Bayern",
    "wof:name":"E. Sorg Transport- Und Lagerhausges. Gmbh & Co. Kg",
    "wof:placetype":"venue"
},
  "geometry": {"coordinates":[11.0780506134,49.4474716187],"type":"Point"}
}