{
  "type": "Feature",
  "properties": {
    "iso:country":"DE",
    "sg:address":"In Der Donk 48",
    "sg:city":"D\u00fcsseldorf",
    "sg:postcode":"40599",
    "sg:province":"Nordrhein-Westfalen",
    "wof:name":"Alles Wissenswerte \u00fcber Wein",
    "wof:placetype":"venue"
},
  "geometry": {"coordinates":[6.864558,51.184605],"type":"Point"}
}