{
  "type": "Feature",
  "properties": {
    "iso:country":"DE",
    "sg:address":"Bahnhofstr. 23",
    "sg:city":"Michelstadt",
    "sg:phone":"+49 6061/12402",
    "sg:postcode":"64720",
    "sg:province":"Hessen",
    "wof:name":"Bistro Marmaris",
    "wof:placetype":"venue"
},
  "geometry": {"coordinates":[9.0030698776,49.6810951233],"type":"Point"}
}