{
  "type": "Feature",
  "properties": {
    "iso:country":"DE",
    "sg:address":"Marktstr. 17",
    "sg:city":"Bad Bergzabern",
    "sg:phone":"+49 6343/93780",
    "sg:postcode":"76887",
    "sg:province":"Rheinland-Pfalz",
    "wof:name":"Redaktion Rheinpfalz- Pf\u00e4lzer Tageblatt",
    "wof:placetype":"venue"
},
  "geometry": {"coordinates":[7.9957408905,49.1009216309],"type":"Point"}
}