{
  "type": "Feature",
  "properties": {
    "iso:country":"DE",
    "sg:address":"Theodor-Heuss-Str. 23",
    "sg:city":"Vaihingen",
    "sg:phone":"+49 7042/92696",
    "sg:postcode":"71665",
    "sg:province":"Baden-W\u00fcrttemberg",
    "wof:name":"G. Vogel",
    "wof:placetype":"venue"
},
  "geometry": {"coordinates":[8.976984024,48.9530105591],"type":"Point"}
}