{
  "type": "Feature",
  "properties": {
    "iso:country":"DE",
    "sg:address":"Im Hinninghofen 1",
    "sg:city":"Essen",
    "sg:phone":"+49 2054/5692",
    "sg:postcode":"45219",
    "sg:province":"Nordrhein-Westfalen",
    "wof:name":"Herbert Nitschke",
    "wof:placetype":"venue"
},
  "geometry": {"coordinates":[6.9436779022,51.3659324646],"type":"Point"}
}