{
  "type": "Feature",
  "properties": {
    "iso:country":"DE",
    "sg:address":"Tarpenbekstr. 93G",
    "sg:city":"Hamburg",
    "sg:phone":"+49 40/479812",
    "sg:postcode":"20251",
    "sg:province":"Hamburg",
    "wof:name":"Irmgard Li\u00df",
    "wof:placetype":"venue"
},
  "geometry": {"coordinates":[9.983846,53.597336],"type":"Point"}
}