{
  "type": "Feature",
  "properties": {
    "iso:country":"DE",
    "sg:address":"Alte Str. 9",
    "sg:city":"Markkleeberg",
    "sg:phone":"+49 34299/75790",
    "sg:postcode":"04416",
    "sg:province":"Sachsen",
    "wof:name":"Dieter Schnurpel",
    "wof:placetype":"venue"
},
  "geometry": {"coordinates":[12.377468,51.260666],"type":"Point"}
}