{
  "type": "Feature",
  "properties": {
    "iso:country":"DE",
    "sg:address":"Hirtenweg 4",
    "sg:city":"Pfinztal",
    "sg:phone":"+49 7240/8112",
    "sg:postcode":"76327",
    "sg:province":"Baden-W\u00fcrttemberg",
    "wof:name":"G. M\u00fcller",
    "wof:placetype":"venue"
},
  "geometry": {"coordinates":[8.5464477539,48.9833145142],"type":"Point"}
}