{
  "type": "Feature",
  "properties": {
    "iso:country":"DE",
    "sg:address":"Ganharting 1",
    "sg:city":"Aicha",
    "sg:phone":"+49 831/56180",
    "sg:postcode":"94529",
    "sg:province":"Bayern",
    "wof:name":"Wacker - Chemie Gmbh",
    "wof:placetype":"venue"
},
  "geometry": {"coordinates":[10.33064,47.706547],"type":"Point"}
}