{
  "type": "Feature",
  "properties": {
    "iso:country":"DE",
    "sg:address":"Am Gei\u00dfgraben 2",
    "sg:city":"Gro\u00dfrinderfeld",
    "sg:phone":"+49 9344/238",
    "sg:postcode":"97950",
    "sg:province":"Baden-W\u00fcrttemberg",
    "wof:name":"Franz-josef Karl",
    "wof:placetype":"venue"
},
  "geometry": {"coordinates":[9.787502,49.697914],"type":"Point"}
}