{
  "type": "Feature",
  "properties": {
    "iso:country":"DE",
    "sg:address":"Wenigenjenaer Ufer 1-2",
    "sg:city":"Jena",
    "sg:phone":"+49 3641/489844",
    "sg:postcode":"07749",
    "sg:province":"Th\u00fcringen",
    "wof:name":"Etc Euro-trade-consult Gmbh",
    "wof:placetype":"venue"
},
  "geometry": {"coordinates":[11.5995607376,50.9299850464],"type":"Point"}
}