{
  "type": "Feature",
  "properties": {
    "iso:country":"DE",
    "sg:address":"Wilhelm-Busch-Str. 20",
    "sg:city":"Rastatt",
    "sg:phone":"+49 7222/69244",
    "sg:postcode":"76437",
    "sg:province":"Baden-W\u00fcrttemberg",
    "wof:name":"Patric Geschwender",
    "wof:placetype":"venue"
},
  "geometry": {"coordinates":[8.1902551651,48.8650474548],"type":"Point"}
}