{
  "type": "Feature",
  "properties": {
    "iso:country":"DE",
    "sg:address":"Oldenburger Str. 260",
    "sg:city":"Wardenburg",
    "sg:phone":"+49 4407/922110",
    "sg:postcode":"26203",
    "sg:province":"Niedersachsen",
    "wof:name":"Max Herrmann Gmbh",
    "wof:placetype":"venue"
},
  "geometry": {"coordinates":[8.197229,53.060493],"type":"Point"}
}