{
  "type": "Feature",
  "properties": {
    "iso:country":"DE",
    "sg:address":"Schlagbaum 19",
    "sg:city":"Ennepetal",
    "sg:phone":"+49 2333/973770",
    "sg:postcode":"58256",
    "sg:province":"Nordrhein-Westfalen",
    "wof:name":"St\u00f6neberg Cafe",
    "wof:placetype":"venue"
},
  "geometry": {"coordinates":[7.35472,51.24614],"type":"Point"}
}