{
  "type": "Feature",
  "properties": {
    "iso:country":"DE",
    "sg:address":"Kantstr. 71",
    "sg:city":"Berlin",
    "sg:phone":"+49 30/8147750",
    "sg:postcode":"10627",
    "sg:province":"Berlin",
    "wof:name":"South & Browse Gmbh",
    "wof:placetype":"venue"
},
  "geometry": {"coordinates":[13.300332,52.506989],"type":"Point"}
}