{
  "type": "Feature",
  "properties": {
    "iso:country":"DE",
    "sg:address":"Iparstr. 32-34",
    "sg:city":"N\u00fcrnberg",
    "sg:postcode":"90451",
    "sg:province":"Bayern",
    "wof:name":"Computer Verlag",
    "wof:placetype":"venue"
},
  "geometry": {"coordinates":[11.0375404358,49.4070396423],"type":"Point"}
}