{
  "type": "Feature",
  "properties": {
    "iso:country":"DE",
    "sg:address":"Am Kirchenfeld 12",
    "sg:city":"Michelstadt",
    "sg:phone":"+49 6061/4880",
    "sg:postcode":"64720",
    "sg:province":"Hessen",
    "wof:name":"Hotel Am Kellereiberg Erika Varga Gmbh",
    "wof:placetype":"venue"
},
  "geometry": {"coordinates":[9.0040502548,49.6767082214],"type":"Point"}
}