{
  "type": "Feature",
  "properties": {
    "iso:country":"DE",
    "sg:address":"Mittelstr. 5",
    "sg:city":"Ostrau",
    "sg:phone":"+49 34324/22247",
    "sg:postcode":"04749",
    "sg:province":"Sachsen",
    "wof:name":"Hadrian Innenausbau Gmbh",
    "wof:placetype":"venue"
},
  "geometry": {"coordinates":[13.149394,51.204975],"type":"Point"}
}