{
  "type": "Feature",
  "properties": {
    "iso:country":"DE",
    "sg:address":"Friedrich-Ebert-Str. 61a",
    "sg:city":"Kassel",
    "sg:phone":"+49 561/109690",
    "sg:postcode":"34119",
    "sg:province":"Hessen",
    "wof:name":"R. Koser & T. Landgrebe",
    "wof:placetype":"venue"
},
  "geometry": {"coordinates":[9.4797687531,51.3147964478],"type":"Point"}
}