{
  "type": "Feature",
  "properties": {
    "iso:country":"DE",
    "sg:address":"Hegholt 15",
    "sg:city":"Hamburg",
    "sg:postcode":"22179",
    "sg:province":"Hamburg",
    "wof:name":"Fabon Trading Bonna Onyeke E. K.",
    "wof:placetype":"venue"
},
  "geometry": {"coordinates":[10.078401,53.602112],"type":"Point"}
}