{
  "type": "Feature",
  "properties": {
    "iso:country":"DE",
    "sg:address":"Luegallee 79",
    "sg:city":"D\u00fcsseldorf",
    "sg:phone":"+49 211/588880",
    "sg:postcode":"40545",
    "sg:province":"Nordrhein-Westfalen",
    "wof:name":"Saitta-import Gmbh",
    "wof:placetype":"venue"
},
  "geometry": {"coordinates":[6.7516160011,51.2312850952],"type":"Point"}
}