{
  "type": "Feature",
  "properties": {
    "iso:country":"DE",
    "sg:address":"Ludwig-Jahn-Str. 33",
    "sg:city":"T\u00f6nisvorst",
    "sg:phone":"+49 2151/790646",
    "sg:postcode":"47918",
    "sg:province":"Nordrhein-Westfalen",
    "wof:name":"Helmut Thyssen",
    "wof:placetype":"venue"
},
  "geometry": {"coordinates":[6.4981012344,51.3229484558],"type":"Point"}
}