{
  "type": "Feature",
  "properties": {
    "iso:country":"DE",
    "sg:address":"Raabestr. 23",
    "sg:city":"Bayreuth",
    "sg:phone":"+49 921/65619",
    "sg:postcode":"95444",
    "sg:province":"Bayern",
    "wof:name":"Parkst\u00fcbchen",
    "wof:placetype":"venue"
},
  "geometry": {"coordinates":[11.5792379379,49.938785553],"type":"Point"}
}