{
  "type": "Feature",
  "properties": {
    "iso:country":"DE",
    "sg:address":"Steglitzer Damm 96b",
    "sg:city":"Berlin",
    "sg:phone":"+49 30/7952002",
    "sg:postcode":"12169",
    "sg:province":"Berlin",
    "wof:name":"Claudias Kosmetikpraxis",
    "wof:placetype":"venue"
},
  "geometry": {"coordinates":[13.3539419174,52.448890686],"type":"Point"}
}