{
  "type": "Feature",
  "properties": {
    "iso:country":"DE",
    "sg:address":"Gustav-Werner-Str. 15",
    "sg:city":"Reutlingen",
    "sg:phone":"+49 7121/3811080",
    "sg:postcode":"72762",
    "sg:province":"Baden-W\u00fcrttemberg",
    "wof:name":"Frank Rilling Rechtanwalt",
    "wof:placetype":"venue"
},
  "geometry": {"coordinates":[9.2047157288,48.4922180176],"type":"Point"}
}