{
  "type": "Feature",
  "properties": {
    "iso:country":"DE",
    "sg:address":"Bahnhofstr. 9",
    "sg:city":"Weiden",
    "sg:phone":"+49 961/43457",
    "sg:postcode":"92637",
    "sg:province":"Bayern",
    "wof:name":"Brunner",
    "wof:placetype":"venue"
},
  "geometry": {"coordinates":[12.156227,49.672894],"type":"Point"}
}