{
  "type": "Feature",
  "properties": {
    "iso:country":"DE",
    "sg:address":"Goldgipfel 49",
    "sg:city":"Gr\u00fcndau",
    "sg:phone":"+49 6058/910430",
    "sg:postcode":"63584",
    "sg:province":"Hessen",
    "wof:name":"Gastec Gmbh",
    "wof:placetype":"venue"
},
  "geometry": {"coordinates":[9.1518688202,50.2358970642],"type":"Point"}
}