{
  "type": "Feature",
  "properties": {
    "iso:country":"DE",
    "sg:address":"Bahnstr. 7",
    "sg:city":"Langenselbold",
    "sg:phone":"+49 6184/921290",
    "sg:postcode":"63505",
    "sg:province":"Hessen",
    "wof:name":"Herget Baucenter Gmbh",
    "wof:placetype":"venue"
},
  "geometry": {"coordinates":[9.04289,50.174812],"type":"Point"}
}