{
  "type": "Feature",
  "properties": {
    "iso:country":"DE",
    "sg:address":"Kleine Ulrichstr. 3",
    "sg:city":"Halle",
    "sg:phone":"+49 345/2028584",
    "sg:postcode":"06108",
    "sg:province":"Sachsen-Anhalt",
    "wof:name":"Uwe R\u00e4ttig",
    "wof:placetype":"venue"
},
  "geometry": {"coordinates":[11.966340065,51.4844284058],"type":"Point"}
}