{
  "type": "Feature",
  "properties": {
    "iso:country":"DE",
    "sg:address":"F\u00fcrstenbergstr. 96",
    "sg:city":"Konstanz",
    "sg:phone":"+49 7531/74856",
    "sg:postcode":"78467",
    "sg:province":"Baden-W\u00fcrttemberg",
    "wof:name":"Architekturb\u00fcro P.-m. Klein",
    "wof:placetype":"venue"
},
  "geometry": {"coordinates":[9.157901,47.682766],"type":"Point"}
}