{
  "type": "Feature",
  "properties": {
    "iso:country":"DE",
    "sg:address":"Heideweg 2",
    "sg:city":"R\u00f6derau-Bobersen",
    "sg:phone":"+49 3525/760160",
    "sg:postcode":"01619",
    "sg:province":"Sachsen",
    "wof:name":"Uwe Barth",
    "wof:placetype":"venue"
},
  "geometry": {"coordinates":[13.3197793961,51.3439598083],"type":"Point"}
}