{
  "type": "Feature",
  "properties": {
    "iso:country":"DE",
    "sg:address":"Hauptstr. 38",
    "sg:city":"Gimbsheim",
    "sg:phone":"+49 6249/4944",
    "sg:postcode":"67578",
    "sg:province":"Rheinland-Pfalz",
    "wof:name":"Jakob Und Anita Scheller",
    "wof:placetype":"venue"
},
  "geometry": {"coordinates":[8.376095,49.778721],"type":"Point"}
}