{
  "type": "Feature",
  "properties": {
    "iso:country":"DE",
    "sg:address":"Kasseler Str.",
    "sg:city":"Bad Zwesten",
    "sg:phone":"+49 5626/1419",
    "sg:postcode":"34596",
    "sg:province":"Hessen",
    "wof:name":"Vereinsgastst\u00e4tte Fc Rot-wei\u00df Zwesten E. V.",
    "wof:placetype":"venue"
},
  "geometry": {"coordinates":[9.1761865616,51.0542640686],"type":"Point"}
}