{
  "type": "Feature",
  "properties": {
    "iso:country":"DE",
    "sg:address":"Hauptstr. 43",
    "sg:city":"Gro\u00dfharthau-B\u00fchlau",
    "sg:phone":"+49 35954/50285",
    "sg:postcode":"01909",
    "sg:province":"Sachsen",
    "wof:name":"Maik Hantsch",
    "wof:placetype":"venue"
},
  "geometry": {"coordinates":[14.107004,51.130875],"type":"Point"}
}