{
  "type": "Feature",
  "properties": {
    "iso:country":"DE",
    "sg:address":"B\u00fcrgermeister Smidt Str. 27",
    "sg:city":"Bremen",
    "sg:phone":"+49 4942/1351031",
    "sg:postcode":"28189",
    "sg:province":"Bremen",
    "wof:name":"Dyko-druck",
    "wof:placetype":"venue"
},
  "geometry": {"coordinates":[8.8081407547,53.0829734802],"type":"Point"}
}