{
  "type": "Feature",
  "properties": {
    "iso:country":"DE",
    "sg:address":"Lipper Weg 25",
    "sg:city":"Marl",
    "sg:phone":"+49 2365/933764",
    "sg:postcode":"45770",
    "sg:province":"Nordrhein-Westfalen",
    "wof:name":"Pizzeria Bei Ullah",
    "wof:placetype":"venue"
},
  "geometry": {"coordinates":[7.1208500862,51.6647186279],"type":"Point"}
}