{
  "type": "Feature",
  "properties": {
    "iso:country":"DE",
    "sg:address":"Lindenallee 59",
    "sg:city":"Kleve",
    "sg:phone":"+49 2821/24183",
    "sg:postcode":"47533",
    "sg:province":"Nordrhein-Westfalen",
    "wof:name":"Grasshoff",
    "wof:placetype":"venue"
},
  "geometry": {"coordinates":[6.1293010712,51.7832756042],"type":"Point"}
}