{
  "type": "Feature",
  "properties": {
    "iso:country":"DE",
    "sg:address":"Gutenbergstr. 3 a",
    "sg:city":"Hemmingen",
    "sg:phone":"+49 511/422091",
    "sg:postcode":"30966",
    "sg:province":"Niedersachsen",
    "wof:name":"Momm W\u00e4rmelieferungs- Und Verwaltungs Gmbh",
    "wof:placetype":"venue"
},
  "geometry": {"coordinates":[9.7237529755,52.3222541809],"type":"Point"}
}