{
  "type": "Feature",
  "properties": {
    "iso:country":"DE",
    "sg:address":"Beedenkirchener Str. 60",
    "sg:city":"Lautertal",
    "sg:phone":"+49 6254/7525",
    "sg:postcode":"64686",
    "sg:province":"Hessen",
    "wof:name":"Gefl\u00fcgelzuchtverein Reichenbach",
    "wof:placetype":"venue"
},
  "geometry": {"coordinates":[8.6930809021,49.7163124084],"type":"Point"}
}