{
  "type": "Feature",
  "properties": {
    "iso:country":"DE",
    "sg:address":"Hauptstr. 24",
    "sg:city":"Benshausen",
    "sg:phone":"+49 36843/60254",
    "sg:postcode":"98554",
    "sg:province":"Th\u00fcringen",
    "wof:name":"W. Gan\u00df",
    "wof:placetype":"venue"
},
  "geometry": {"coordinates":[10.5943641663,50.6440429688],"type":"Point"}
}