{
  "type": "Feature",
  "properties": {
    "iso:country":"DE",
    "sg:address":"Schilderstr. 31",
    "sg:city":"Aachen",
    "sg:phone":"+49 241/552186",
    "sg:postcode":"52080",
    "sg:province":"Nordrhein-Westfalen",
    "wof:name":"Eva Maus",
    "wof:placetype":"venue"
},
  "geometry": {"coordinates":[6.163843,50.776875],"type":"Point"}
}