{
  "type": "Feature",
  "properties": {
    "iso:country":"DE",
    "sg:address":"Stuttgarter Str. 14b",
    "sg:city":"Ostelsheim",
    "sg:phone":"+49 7033/41789",
    "sg:postcode":"75395",
    "sg:province":"Baden-W\u00fcrttemberg",
    "wof:name":"Detlev Kuhbandner",
    "wof:placetype":"venue"
},
  "geometry": {"coordinates":[8.8543348312,48.7270088196],"type":"Point"}
}