{
  "type": "Feature",
  "properties": {
    "iso:country":"DE",
    "sg:address":"Habbelrather Str. 6",
    "sg:city":"Kerpen",
    "sg:phone":"+49 2273/1080",
    "sg:postcode":"50169",
    "sg:province":"Nordrhein-Westfalen",
    "wof:name":"Heinen",
    "wof:placetype":"venue"
},
  "geometry": {"coordinates":[6.7264480591,50.9154052734],"type":"Point"}
}