{
  "type": "Feature",
  "properties": {
    "iso:country":"DE",
    "sg:address":"Leiboldstr. 66",
    "sg:city":"Sinzheim",
    "sg:phone":"+49 7223/52552",
    "sg:postcode":"76547",
    "sg:province":"Baden-W\u00fcrttemberg",
    "wof:name":"R\u00f6ssel",
    "wof:placetype":"venue"
},
  "geometry": {"coordinates":[8.1006612778,48.754119873],"type":"Point"}
}