{
  "type": "Feature",
  "properties": {
    "iso:country":"DE",
    "sg:address":"Werftstr. 214-216",
    "sg:city":"Kiel",
    "sg:postcode":"24143",
    "sg:province":"Schleswig-Holstein",
    "wof:name":"P. O. S. Medien Service Gmbh",
    "wof:placetype":"venue"
},
  "geometry": {"coordinates":[10.138009,54.310272],"type":"Point"}
}