{
  "type": "Feature",
  "properties": {
    "iso:country":"DE",
    "sg:address":"Fabianweg 7",
    "sg:city":"Marienberg",
    "sg:phone":"+49 3735/63766",
    "sg:postcode":"09496",
    "sg:province":"Sachsen",
    "wof:name":"Dr. Med. Heinrich Illing",
    "wof:placetype":"venue"
},
  "geometry": {"coordinates":[13.164495,50.654842],"type":"Point"}
}