{
  "type": "Feature",
  "properties": {
    "iso:country":"DE",
    "sg:address":"Nordwalder Str. 87 a",
    "sg:city":"Steinfurt",
    "sg:phone":"+49 2552/4519",
    "sg:postcode":"48565",
    "sg:province":"Nordrhein-Westfalen",
    "wof:name":"D. Bensmann",
    "wof:placetype":"venue"
},
  "geometry": {"coordinates":[7.4165420532,52.1236686707],"type":"Point"}
}