{
  "type": "Feature",
  "properties": {
    "iso:country":"DE",
    "sg:address":"Reichenbacher Str. 18",
    "sg:city":"Warendorf",
    "sg:phone":"+49 2581/7692",
    "sg:postcode":"48231",
    "sg:province":"Nordrhein-Westfalen",
    "wof:name":"Hartmann Versicherungsb\u00fcro Inh. M. Sandjohann",
    "wof:placetype":"venue"
},
  "geometry": {"coordinates":[7.9870319366,51.9429473877],"type":"Point"}
}