{
  "type": "Feature",
  "properties": {
    "iso:country":"DE",
    "sg:address":"Landrat-Schultz-Str. 10",
    "sg:city":"Mettingen",
    "sg:phone":"+49 5452/509243",
    "sg:postcode":"49497",
    "sg:province":"Nordrhein-Westfalen",
    "wof:name":"Bistro Zum Clown",
    "wof:placetype":"venue"
},
  "geometry": {"coordinates":[7.7803239822,52.3145217896],"type":"Point"}
}