{
  "type": "Feature",
  "properties": {
    "iso:country":"DE",
    "sg:address":"Mommsenstr. 65",
    "sg:city":"Berlin",
    "sg:phone":"+49 30/8811248",
    "sg:postcode":"10629",
    "sg:province":"Berlin",
    "wof:name":"Tavga Design",
    "wof:placetype":"venue"
},
  "geometry": {"coordinates":[13.317921,52.502899],"type":"Point"}
}