{
  "type": "Feature",
  "properties": {
    "iso:country":"DE",
    "sg:address":"Handjerystr. 50-51",
    "sg:city":"Berlin",
    "sg:phone":"+49 30/8517633",
    "sg:postcode":"12161",
    "sg:province":"Berlin",
    "wof:name":"Seniorenwohnheim Der Friedenskirche",
    "wof:placetype":"venue"
},
  "geometry": {"coordinates":[13.329819,52.469223],"type":"Point"}
}