{
  "type": "Feature",
  "properties": {
    "iso:country":"DE",
    "sg:address":"Hauptstr. 190",
    "sg:city":"Sundern",
    "sg:phone":"+49 2933/77073",
    "sg:postcode":"59846",
    "sg:province":"Nordrhein-Westfalen",
    "wof:name":"Stadtkrug",
    "wof:placetype":"venue"
},
  "geometry": {"coordinates":[8.0005254745,51.3346061707],"type":"Point"}
}