{
  "type": "Feature",
  "properties": {
    "iso:country":"DE",
    "sg:address":"M\u00fcnsterstr. 96",
    "sg:city":"Rheine",
    "sg:phone":"+49 5971/2912",
    "sg:postcode":"48431",
    "sg:province":"Nordrhein-Westfalen",
    "wof:name":"Franz Velker Gmbh",
    "wof:placetype":"venue"
},
  "geometry": {"coordinates":[7.4429588318,52.2720603943],"type":"Point"}
}