{
  "type": "Feature",
  "properties": {
    "iso:country":"DE",
    "sg:address":"F\u00fcrstabt-Gerold-Str. 38",
    "sg:city":"Horb",
    "sg:phone":"+49 7482/324",
    "sg:postcode":"72160",
    "sg:province":"Baden-W\u00fcrttemberg",
    "wof:name":"Waldschl\u00f6\u00dfle",
    "wof:placetype":"venue"
},
  "geometry": {"coordinates":[8.6256217957,48.4129104614],"type":"Point"}
}