{
  "type": "Feature",
  "properties": {
    "iso:country":"DE",
    "sg:address":"Bergwiese 1",
    "sg:city":"Rotterode",
    "sg:phone":"+49 36847/32356",
    "sg:postcode":"98587",
    "sg:province":"Th\u00fcringen",
    "wof:name":"Matthias Werner",
    "wof:placetype":"venue"
},
  "geometry": {"coordinates":[10.549548,50.71336],"type":"Point"}
}