{
  "type": "Feature",
  "properties": {
    "iso:country":"DE",
    "sg:address":"Waiblinger Str. 11",
    "sg:city":"Weinstadt",
    "sg:phone":"+49 7151/609835",
    "sg:postcode":"71384",
    "sg:province":"Baden-W\u00fcrttemberg",
    "wof:name":"Greiner",
    "wof:placetype":"venue"
},
  "geometry": {"coordinates":[9.362222,48.81311],"type":"Point"}
}