{
  "type": "Feature",
  "properties": {
    "iso:country":"DE",
    "sg:city":"Langweiler",
    "sg:phone":"+49 6788/267",
    "sg:postcode":"67746",
    "sg:province":"Rheinland-Pfalz",
    "wof:name":"Horst Trilling Gartenbau",
    "wof:placetype":"venue"
},
  "geometry": {"coordinates":[7.527014,49.665752],"type":"Point"}
}