{
  "type": "Feature",
  "properties": {
    "iso:country":"DE",
    "sg:address":"Scharfenberger Str. 41",
    "sg:city":"Dresden",
    "sg:postcode":"01139",
    "sg:province":"Sachsen",
    "wof:name":"Dr. Med. Hans-joachim Brause",
    "wof:placetype":"venue"
},
  "geometry": {"coordinates":[13.694189,51.073017],"type":"Point"}
}