{
  "type": "Feature",
  "properties": {
    "iso:country":"DE",
    "sg:address":"Schieferstr. 4",
    "sg:city":"Wettenberg",
    "sg:phone":"+49 641/85987",
    "sg:postcode":"35435",
    "sg:province":"Hessen",
    "wof:name":"Jochen Reinholz Rechtsanwalt",
    "wof:placetype":"venue"
},
  "geometry": {"coordinates":[8.6329746246,50.6223716736],"type":"Point"}
}