{
  "type": "Feature",
  "properties": {
    "iso:country":"DE",
    "sg:address":"Josephsburgstr. 8",
    "sg:city":"M\u00fcnchen",
    "sg:phone":"+49 89/432238",
    "sg:postcode":"81673",
    "sg:province":"Bayern",
    "wof:name":"Berg-bad",
    "wof:placetype":"venue"
},
  "geometry": {"coordinates":[11.626749,48.128468],"type":"Point"}
}