{
  "type": "Feature",
  "properties": {
    "iso:country":"DE",
    "sg:address":"R\u00fcbenkamp 148",
    "sg:city":"Hamburg",
    "sg:phone":"+49 40/63273434",
    "sg:postcode":"22307",
    "sg:province":"Hamburg",
    "wof:name":"Druckkammerzentzrum Hamburg Institut F\u00fcr Hyperbare",
    "wof:placetype":"venue"
},
  "geometry": {"coordinates":[10.035364,53.603428],"type":"Point"}
}