{
  "type": "Feature",
  "properties": {
    "iso:country":"DE",
    "sg:address":"Kressengartenstr. 2",
    "sg:city":"N\u00fcrnberg",
    "sg:phone":"+49 8741/800",
    "sg:postcode":"90402",
    "sg:province":"Bayern",
    "wof:name":"Bulthaup Gmbh & Co. Kg",
    "wof:placetype":"venue"
},
  "geometry": {"coordinates":[12.4054803848,48.4241638184],"type":"Point"}
}