{
  "type": "Feature",
  "properties": {
    "iso:country":"DE",
    "sg:address":"Lehmkuhlenbusch 4",
    "sg:city":"Delmenhorst",
    "sg:phone":"+49 4221/91600",
    "sg:postcode":"27753",
    "sg:province":"Niedersachsen",
    "wof:name":"Hanse-wissenschaftskolleg",
    "wof:placetype":"venue"
},
  "geometry": {"coordinates":[8.5918369293,53.042514801],"type":"Point"}
}