{
  "type": "Feature",
  "properties": {
    "iso:country":"DE",
    "sg:city":"Ruhmannsfelden",
    "sg:phone":"+49 9929/1379",
    "sg:postcode":"94239",
    "sg:province":"Bayern",
    "wof:name":"F. Und A. Rauch",
    "wof:placetype":"venue"
},
  "geometry": {"coordinates":[12.98101,48.9841],"type":"Point"}
}