{
  "type": "Feature",
  "properties": {
    "iso:country":"DE",
    "sg:address":"Richtweg 1",
    "sg:city":"Nonnenhorn",
    "sg:phone":"+49 8382/8463",
    "sg:postcode":"88149",
    "sg:province":"Bayern",
    "wof:name":"Josef Dietrich Obstbau",
    "wof:placetype":"venue"
},
  "geometry": {"coordinates":[9.6132040024,47.5762367249],"type":"Point"}
}