{
  "type": "Feature",
  "properties": {
    "iso:country":"DE",
    "sg:address":"Bonner Str. 37",
    "sg:city":"Bornheim",
    "sg:phone":"+49 2222/60129",
    "sg:postcode":"53332",
    "sg:province":"Nordrhein-Westfalen",
    "wof:name":"W. Kr\u00e4mer",
    "wof:placetype":"venue"
},
  "geometry": {"coordinates":[7.0117049217,50.7542915344],"type":"Point"}
}