{
  "type": "Feature",
  "properties": {
    "iso:country":"DE",
    "sg:address":"Olpener Str. 60",
    "sg:city":"Engelskirchen",
    "sg:phone":"+49 2263/901717",
    "sg:postcode":"51766",
    "sg:province":"Nordrhein-Westfalen",
    "wof:name":"Ursula Hall Natur- Gold- Und Silberschmuck Fabrikat. Und Gh",
    "wof:placetype":"venue"
},
  "geometry": {"coordinates":[7.4227237701,50.9857826233],"type":"Point"}
}