{
  "type": "Feature",
  "properties": {
    "iso:country":"DE",
    "sg:address":"Ernst-Th\u00e4lmann-Str. 10",
    "sg:city":"Neustadt",
    "sg:postcode":"07806",
    "sg:province":"Th\u00fcringen",
    "wof:name":"B. Ludwig",
    "wof:placetype":"venue"
},
  "geometry": {"coordinates":[11.736365,50.724075],"type":"Point"}
}