{
  "type": "Feature",
  "properties": {
    "iso:country":"DE",
    "sg:address":"Rother Kuppe 2",
    "sg:city":"Hausen",
    "sg:phone":"+49 9779/910",
    "sg:postcode":"97647",
    "sg:province":"Bayern",
    "wof:name":"Rh\u00f6n-park-hotel Gmbh & Co. Kg",
    "wof:placetype":"venue"
},
  "geometry": {"coordinates":[10.105340004,50.4797019958],"type":"Point"}
}