{
  "type": "Feature",
  "properties": {
    "iso:country":"DE",
    "sg:address":"Industriestr. 4",
    "sg:city":"Morbach",
    "sg:phone":"+49 6533/95010",
    "sg:postcode":"54497",
    "sg:province":"Rheinland-Pfalz",
    "wof:name":"J. Gottlieb Peiseler Gmbh & Co. Kg",
    "wof:placetype":"venue"
},
  "geometry": {"coordinates":[7.136567,49.811794],"type":"Point"}
}