{
  "type": "Feature",
  "properties": {
    "iso:country":"DE",
    "sg:address":"Berliner Platz 10",
    "sg:city":"Schifferstadt",
    "sg:phone":"+49 6235/7671",
    "sg:postcode":"67105",
    "sg:province":"Rheinland-Pfalz",
    "wof:name":"Busch-l\u00fctzel Hausverwaltung Gmbh",
    "wof:placetype":"venue"
},
  "geometry": {"coordinates":[8.391166687,49.3809356689],"type":"Point"}
}