{
  "type": "Feature",
  "properties": {
    "iso:country":"DE",
    "sg:address":"Hauptstr. 80",
    "sg:city":"Senden",
    "sg:phone":"+49 7307/4594",
    "sg:postcode":"89250",
    "sg:province":"Bayern",
    "wof:name":"R\u00e4uberkr\u00fcgle",
    "wof:placetype":"venue"
},
  "geometry": {"coordinates":[10.0379314423,48.322265625],"type":"Point"}
}