{
  "type": "Feature",
  "properties": {
    "iso:country":"DE",
    "sg:address":"Am Stettberg 10",
    "sg:city":"Niederstotzingen",
    "sg:phone":"+49 7325/3721",
    "sg:postcode":"89168",
    "sg:province":"Baden-W\u00fcrttemberg",
    "wof:name":"H. H. Maurer",
    "wof:placetype":"venue"
},
  "geometry": {"coordinates":[10.20902,48.555859],"type":"Point"}
}