{
  "type": "Feature",
  "properties": {
    "iso:country":"DE",
    "sg:address":"Ravensteynstr. 6",
    "sg:city":"Koblenz",
    "sg:postcode":"56076",
    "sg:province":"Rheinland-Pfalz",
    "wof:name":"B\u00e4sch Einkauf Logistik Gmbh & Co. Kg",
    "wof:placetype":"venue"
},
  "geometry": {"coordinates":[7.603897,50.345303],"type":"Point"}
}