{
  "type": "Feature",
  "properties": {
    "iso:country":"DE",
    "sg:address":"Heidelberger Str. 1",
    "sg:city":"Brensbach",
    "sg:phone":"+49 6161/438",
    "sg:postcode":"64395",
    "sg:province":"Hessen",
    "wof:name":"Metzgerei Lutz Gmbh",
    "wof:placetype":"venue"
},
  "geometry": {"coordinates":[8.8783636093,49.7725219727],"type":"Point"}
}