{
  "type": "Feature",
  "properties": {
    "iso:country":"DE",
    "sg:address":"Bruchstr. 1 a",
    "sg:city":"Coesfeld",
    "sg:phone":"+49 2546/98811",
    "sg:postcode":"48653",
    "sg:province":"Nordrhein-Westfalen",
    "wof:name":"B\u00f6hne",
    "wof:placetype":"venue"
},
  "geometry": {"coordinates":[7.17614,51.892223],"type":"Point"}
}