{
  "type": "Feature",
  "properties": {
    "iso:country":"DE",
    "sg:address":"Lienackern 33",
    "sg:city":"Bremen",
    "sg:phone":"+49 421/832974",
    "sg:postcode":"28279",
    "sg:province":"Bremen",
    "wof:name":"Gate General Aviation Trading & Engineering Gmbh",
    "wof:placetype":"venue"
},
  "geometry": {"coordinates":[8.853683,53.046295],"type":"Point"}
}