{
  "type": "Feature",
  "properties": {
    "iso:country":"DE",
    "sg:address":"Weidestr. 18",
    "sg:city":"Hagen",
    "sg:phone":"+49 2331/371002",
    "sg:postcode":"58089",
    "sg:province":"Nordrhein-Westfalen",
    "wof:name":"Pasa",
    "wof:placetype":"venue"
},
  "geometry": {"coordinates":[7.4545822144,51.3585510254],"type":"Point"}
}