{
  "type": "Feature",
  "properties": {
    "iso:country":"DE",
    "sg:address":"Fraunhoferstr. 10",
    "sg:city":"N\u00fcrnberg",
    "sg:phone":"+49 911/519960",
    "sg:postcode":"90409",
    "sg:province":"Bayern",
    "wof:name":"N\u00fcrnberger Wach- Und Schlie\u00dfgesellschaft Mbh",
    "wof:placetype":"venue"
},
  "geometry": {"coordinates":[11.0978336334,49.4680862427],"type":"Point"}
}