{
  "type": "Feature",
  "properties": {
    "iso:country":"DE",
    "sg:address":"Auf der Kenner Ley 2",
    "sg:city":"Kenn",
    "sg:phone":"+49 6502/4290",
    "sg:postcode":"54344",
    "sg:province":"Rheinland-Pfalz",
    "wof:name":"Michael Friedrich",
    "wof:placetype":"venue"
},
  "geometry": {"coordinates":[6.7079567909,49.7984771729],"type":"Point"}
}