{
  "type": "Feature",
  "properties": {
    "iso:country":"DE",
    "sg:address":"Von-Braun-Str. 70",
    "sg:city":"Ahaus",
    "sg:phone":"+49 2561/93350",
    "sg:postcode":"48683",
    "sg:province":"Nordrhein-Westfalen",
    "wof:name":"Stenau Sonderabfalltransporte Gmbh",
    "wof:placetype":"venue"
},
  "geometry": {"coordinates":[7.0259661674,52.0765457153],"type":"Point"}
}