{
  "type": "Feature",
  "properties": {
    "iso:country":"DE",
    "sg:address":"Pommernstr. 15",
    "sg:city":"Langenlonsheim",
    "sg:postcode":"55450",
    "sg:province":"Rheinland-Pfalz",
    "wof:name":"Lipsis",
    "wof:placetype":"venue"
},
  "geometry": {"coordinates":[7.903751,49.886478],"type":"Point"}
}