{
  "type": "Feature",
  "properties": {
    "iso:country":"DE",
    "sg:address":"Hohenstaufenring 34-40",
    "sg:city":"K\u00f6ln",
    "sg:phone":"+49 221/231447",
    "sg:postcode":"50674",
    "sg:province":"Nordrhein-Westfalen",
    "wof:name":"Klaus Bielenberg",
    "wof:placetype":"venue"
},
  "geometry": {"coordinates":[6.9408531189,50.9316482544],"type":"Point"}
}