{
  "type": "Feature",
  "properties": {
    "iso:country":"DE",
    "sg:address":"Kanalstr. 37",
    "sg:city":"Peine",
    "sg:phone":"+49 5171/55337",
    "sg:postcode":"31226",
    "sg:province":"Niedersachsen",
    "wof:name":"I. Leue",
    "wof:placetype":"venue"
},
  "geometry": {"coordinates":[10.1469163895,52.3119544983],"type":"Point"}
}