{
  "type": "Feature",
  "properties": {
    "iso:country":"DE",
    "sg:address":"Gantweg 26",
    "sg:city":"Billerbeck",
    "sg:phone":"+49 2543/4184",
    "sg:postcode":"48727",
    "sg:province":"Nordrhein-Westfalen",
    "wof:name":"Franz Jeusfeld",
    "wof:placetype":"venue"
},
  "geometry": {"coordinates":[7.291615,51.994781],"type":"Point"}
}