{
  "type": "Feature",
  "properties": {
    "iso:country":"DE",
    "sg:address":"Im Hahn 5",
    "sg:city":"Hinterweiler",
    "sg:phone":"+49 6595/384",
    "sg:postcode":"54570",
    "sg:province":"Rheinland-Pfalz",
    "wof:name":"H. Assion",
    "wof:placetype":"venue"
},
  "geometry": {"coordinates":[6.755871,50.235306],"type":"Point"}
}