{
  "type": "Feature",
  "properties": {
    "iso:country":"DE",
    "sg:address":"Rheinstr. 64",
    "sg:city":"Bornheim",
    "sg:phone":"+49 2222/8940",
    "sg:postcode":"53332",
    "sg:province":"Nordrhein-Westfalen",
    "wof:name":"Hans-j\u00fcrgenpacholke",
    "wof:placetype":"venue"
},
  "geometry": {"coordinates":[7.0505871773,50.7681236267],"type":"Point"}
}