{
  "type": "Feature",
  "properties": {
    "iso:country":"DE",
    "sg:address":"Osterstr. 19",
    "sg:city":"Aurich",
    "sg:phone":"+49 4941/64924",
    "sg:postcode":"26603",
    "sg:province":"Niedersachsen",
    "wof:name":"Ires Inspiration",
    "wof:placetype":"venue"
},
  "geometry": {"coordinates":[7.4841179848,53.4695358276],"type":"Point"}
}