{
  "type": "Feature",
  "properties": {
    "iso:country":"DE",
    "sg:address":"Keltenstr. 6",
    "sg:city":"Singen",
    "sg:postcode":"78224",
    "sg:province":"Baden-W\u00fcrttemberg",
    "wof:name":"Tc-tecconsult Gmbh",
    "wof:placetype":"venue"
},
  "geometry": {"coordinates":[8.5715751648,48.9584770203],"type":"Point"}
}