{
  "type": "Feature",
  "properties": {
    "iso:country":"DE",
    "sg:address":"Dorfstr. 42",
    "sg:city":"Uenze",
    "sg:phone":"+49 38784/60353",
    "sg:postcode":"19348",
    "sg:province":"Brandenburg",
    "wof:name":"Uwe Sch\u00e4ffer",
    "wof:placetype":"venue"
},
  "geometry": {"coordinates":[11.8619852066,53.0761260986],"type":"Point"}
}