{
  "type": "Feature",
  "properties": {
    "iso:country":"DE",
    "sg:address":"Forststr. 19",
    "sg:city":"Friedberg",
    "sg:phone":"+49 821/780780",
    "sg:postcode":"86316",
    "sg:province":"Bayern",
    "wof:name":"Augsburger Kalksand- Stein Gmbh & Co. Kg",
    "wof:placetype":"venue"
},
  "geometry": {"coordinates":[10.975446,48.412086],"type":"Point"}
}