{
  "type": "Feature",
  "properties": {
    "iso:country":"DE",
    "sg:address":"Sandhausener Ring 3",
    "sg:city":"Osterholz-Scharmbeck",
    "sg:phone":"+49 4791/59800",
    "sg:postcode":"27711",
    "sg:province":"Niedersachsen",
    "wof:name":"Reinigung-b\u00fcro-leasing Service Gmbh",
    "wof:placetype":"venue"
},
  "geometry": {"coordinates":[8.8243932724,53.2714080811],"type":"Point"}
}