{
  "type": "Feature",
  "properties": {
    "iso:country":"DE",
    "sg:address":"Rudolf-Breitscheid-Str. 5",
    "sg:city":"Koblenz",
    "sg:phone":"+49 261/9730873",
    "sg:postcode":"56077",
    "sg:province":"Rheinland-Pfalz",
    "wof:name":"Ulrich Adomeit Jazz Orchester",
    "wof:placetype":"venue"
},
  "geometry": {"coordinates":[7.6132922173,50.3500976562],"type":"Point"}
}