{
  "type": "Feature",
  "properties": {
    "iso:country":"DE",
    "sg:address":"Winzererstr. 36",
    "sg:city":"M\u00fcnchen",
    "sg:phone":"+49 89/18999366",
    "sg:postcode":"80797",
    "sg:province":"Bayern",
    "wof:name":"Heilmann Beteiligungs Gmbh",
    "wof:placetype":"venue"
},
  "geometry": {"coordinates":[11.560108,48.155643],"type":"Point"}
}