{
  "type": "Feature",
  "properties": {
    "iso:country":"DE",
    "sg:address":"Industriestr 8",
    "sg:city":"H\u00fcckeswagen",
    "sg:phone":"+49 2192/912110",
    "sg:postcode":"42499",
    "sg:province":"Nordrhein-Westfalen",
    "wof:name":"Luk Automobiltechnik Gmbh & Co Kg",
    "wof:placetype":"venue"
},
  "geometry": {"coordinates":[7.301595211,51.146774292],"type":"Point"}
}