{
  "type": "Feature",
  "properties": {
    "iso:country":"DE",
    "sg:address":"Christian-Jorhan-Str. 24",
    "sg:city":"Langenpreising",
    "sg:phone":"+49 8762/9820",
    "sg:postcode":"85465",
    "sg:province":"Bayern",
    "wof:name":"Max Sellmair",
    "wof:placetype":"venue"
},
  "geometry": {"coordinates":[11.9759120941,48.4282341003],"type":"Point"}
}