{
  "type": "Feature",
  "properties": {
    "iso:country":"DE",
    "sg:address":"Mozartstr. 2 a",
    "sg:city":"Premnitz",
    "sg:phone":"+49 3386/282600",
    "sg:postcode":"14727",
    "sg:province":"Brandenburg",
    "wof:name":"Dr. Med. Heinz-werner Than Arzt F\u00fcr Allgemeinmedizin",
    "wof:placetype":"venue"
},
  "geometry": {"coordinates":[12.3403892517,52.5405807495],"type":"Point"}
}