{
  "type": "Feature",
  "properties": {
    "iso:country":"DE",
    "sg:address":"Hermann-Ehlers-Str. 21",
    "sg:city":"Mainz",
    "sg:phone":"+49 6131/44587",
    "sg:postcode":"55124",
    "sg:province":"Rheinland-Pfalz",
    "wof:name":"Ute Und Michael Uhrig",
    "wof:placetype":"venue"
},
  "geometry": {"coordinates":[8.210385,50.002304],"type":"Point"}
}