{
  "type": "Feature",
  "properties": {
    "iso:country":"DE",
    "sg:address":"G\u00f6hlbachtal 24",
    "sg:city":"Hamburg",
    "sg:phone":"+49 40/7658146",
    "sg:postcode":"21073",
    "sg:province":"Hamburg",
    "wof:name":"K. Schulz Immobilienmakler",
    "wof:placetype":"venue"
},
  "geometry": {"coordinates":[9.966460228,53.4547348022],"type":"Point"}
}