{
  "type": "Feature",
  "properties": {
    "iso:country":"DE",
    "sg:address":"Westf\u00e4lische Str. 66",
    "sg:city":"Olpe",
    "sg:phone":"+49 2761/63201",
    "sg:postcode":"57462",
    "sg:province":"Nordrhein-Westfalen",
    "wof:name":"Olper Schl\u00fcssel-u. Schilder- Dienst",
    "wof:placetype":"venue"
},
  "geometry": {"coordinates":[7.8501648903,51.0325431824],"type":"Point"}
}