{
  "type": "Feature",
  "properties": {
    "iso:country":"DE",
    "sg:address":"Kelterplatz 7",
    "sg:city":"Neckartenzlingen",
    "sg:phone":"+49 7127/31878",
    "sg:postcode":"72654",
    "sg:province":"Baden-W\u00fcrttemberg",
    "wof:name":"C. Gujber",
    "wof:placetype":"venue"
},
  "geometry": {"coordinates":[9.2380409241,48.5895004272],"type":"Point"}
}