{
  "type": "Feature",
  "properties": {
    "iso:country":"DE",
    "sg:address":"Bezirkstr. 82",
    "sg:city":"Merzig",
    "sg:phone":"+49 6861/2000",
    "sg:postcode":"66663",
    "sg:province":"Saarland",
    "wof:name":"Hotel-restaurant Zur Linde",
    "wof:placetype":"venue"
},
  "geometry": {"coordinates":[6.6077370644,49.4741287231],"type":"Point"}
}