{
  "type": "Feature",
  "properties": {
    "iso:country":"DE",
    "sg:address":"L\u00fctten Hop 7",
    "sg:city":"Otterndorf",
    "sg:postcode":"21762",
    "sg:province":"Niedersachsen",
    "wof:name":"R. Pieper",
    "wof:placetype":"venue"
},
  "geometry": {"coordinates":[8.9129152298,53.8107528687],"type":"Point"}
}