{
  "type": "Feature",
  "properties": {
    "iso:country":"DE",
    "sg:address":"Schl\u00f6\u00dflanger 10",
    "sg:city":"M\u00fcnchen",
    "sg:phone":"+49 89/3169370",
    "sg:postcode":"80939",
    "sg:province":"Bayern",
    "wof:name":"Hotel Bock Garni",
    "wof:placetype":"venue"
},
  "geometry": {"coordinates":[11.6107406616,48.2041625977],"type":"Point"}
}