{
  "type": "Feature",
  "properties": {
    "iso:country":"DE",
    "sg:address":"K\u00e4the-Kollwitz-Str. 14",
    "sg:city":"Eibau-Walddorf",
    "sg:phone":"+49 3586/300766",
    "sg:postcode":"02739",
    "sg:province":"Sachsen",
    "wof:name":"Wolfgang Nitzsche",
    "wof:placetype":"venue"
},
  "geometry": {"coordinates":[14.65036,50.988892],"type":"Point"}
}