{
  "type": "Feature",
  "properties": {
    "iso:country":"DE",
    "sg:address":"Friedrich-Heinrich-Platz 32",
    "sg:city":"Munster",
    "sg:phone":"+49 5192/3123",
    "sg:postcode":"29633",
    "sg:province":"Niedersachsen",
    "wof:name":"Hotel L\u00fcneburger Hof",
    "wof:placetype":"venue"
},
  "geometry": {"coordinates":[10.0898809433,52.983795166],"type":"Point"}
}