{
  "type": "Feature",
  "properties": {
    "iso:country":"DE",
    "sg:address":"Bahnhofstr. 2",
    "sg:city":"Neukirchen",
    "sg:phone":"+49 9663/805",
    "sg:postcode":"92259",
    "sg:province":"Bayern",
    "wof:name":"Bahnhofgastst\u00e4tte Sylvia Und J\u00f6rg Reimann",
    "wof:placetype":"venue"
},
  "geometry": {"coordinates":[11.6201133728,49.5245323181],"type":"Point"}
}