{
  "type": "Feature",
  "properties": {
    "iso:country":"DE",
    "sg:address":"Patersbergweg 5",
    "sg:city":"Mainleus",
    "sg:phone":"+49 9229/7670",
    "sg:postcode":"95336",
    "sg:province":"Bayern",
    "wof:name":"Gisela Unger Kg",
    "wof:placetype":"venue"
},
  "geometry": {"coordinates":[11.388507,50.119495],"type":"Point"}
}