{
  "type": "Feature",
  "properties": {
    "iso:country":"DE",
    "sg:address":"Aberlestr. 23",
    "sg:city":"M\u00fcnchen",
    "sg:phone":"+49 89/773435",
    "sg:postcode":"81371",
    "sg:province":"Bayern",
    "wof:name":"Wolfgang Purschke",
    "wof:placetype":"venue"
},
  "geometry": {"coordinates":[11.5455684662,48.120010376],"type":"Point"}
}