{
  "type": "Feature",
  "properties": {
    "iso:country":"DE",
    "sg:address":"Dillstr 4",
    "sg:city":"H\u00fcttenberg",
    "sg:phone":"+49 6403/70090",
    "sg:postcode":"35625",
    "sg:province":"Hessen",
    "wof:name":"Lang Gmbh & Co Kg Graviermaschinen",
    "wof:placetype":"venue"
},
  "geometry": {"coordinates":[8.627794,50.506275],"type":"Point"}
}