{
  "type": "Feature",
  "properties": {
    "iso:country":"DE",
    "sg:address":"Hagenstr. 1",
    "sg:city":"Winterberg",
    "sg:phone":"+49 2981/523",
    "sg:postcode":"59955",
    "sg:province":"Nordrhein-Westfalen",
    "wof:name":"Cafe Kr\u00e4mer",
    "wof:placetype":"venue"
},
  "geometry": {"coordinates":[8.5336055756,51.1938362122],"type":"Point"}
}