{
  "type": "Feature",
  "properties": {
    "iso:country":"DE",
    "sg:address":"Eckegasse 1",
    "sg:city":"B\u00fcdingen",
    "sg:phone":"+49 6049/551",
    "sg:postcode":"63654",
    "sg:province":"Hessen",
    "wof:name":"Lutz Gmbh",
    "wof:placetype":"venue"
},
  "geometry": {"coordinates":[9.188007,50.318249],"type":"Point"}
}