{
  "type": "Feature",
  "properties": {
    "iso:country":"DE",
    "sg:address":"Vogelweideplatz 1",
    "sg:city":"M\u00fcnchen",
    "sg:phone":"+49 89/4706139",
    "sg:postcode":"81677",
    "sg:province":"Bayern",
    "wof:name":"Bachmann Immobilienmakler",
    "wof:placetype":"venue"
},
  "geometry": {"coordinates":[11.6192436218,48.1377944946],"type":"Point"}
}