{
  "type": "Feature",
  "properties": {
    "iso:country":"DE",
    "sg:address":"Lion-Feuchtwanger-Str. 22",
    "sg:city":"Berlin",
    "sg:phone":"+49 30/5633468",
    "sg:postcode":"12619",
    "sg:province":"Berlin",
    "wof:name":"Robinson Apotheke Inh. J\u00f6rg Bartlakowski",
    "wof:placetype":"venue"
},
  "geometry": {"coordinates":[13.582694,52.517414],"type":"Point"}
}