{
  "type": "Feature",
  "properties": {
    "iso:country":"DE",
    "sg:address":"Am Thieleshof 52",
    "sg:city":"Erkrath",
    "sg:phone":"+49 211/201580",
    "sg:postcode":"40699",
    "sg:province":"Nordrhein-Westfalen",
    "wof:name":"Medisin-medizinische Anlagen Gmbh",
    "wof:placetype":"venue"
},
  "geometry": {"coordinates":[6.9289808273,51.1971359253],"type":"Point"}
}