{
  "type": "Feature",
  "properties": {
    "iso:country":"DE",
    "sg:address":"Arheilger Woogstr. 43",
    "sg:city":"Darmstadt",
    "sg:phone":"+49 6151/373183",
    "sg:postcode":"64291",
    "sg:province":"Hessen",
    "wof:name":"Helmut Blumenschein",
    "wof:placetype":"venue"
},
  "geometry": {"coordinates":[8.663143158,49.9093704224],"type":"Point"}
}