{
  "type": "Feature",
  "properties": {
    "iso:country":"DE",
    "sg:address":"Karlsplatz 10",
    "sg:city":"Eisenach",
    "sg:phone":"+49 3691/213400",
    "sg:postcode":"99817",
    "sg:province":"Th\u00fcringen",
    "wof:name":"Cafe Swing",
    "wof:placetype":"venue"
},
  "geometry": {"coordinates":[10.32539,50.975014],"type":"Point"}
}