{
  "type": "Feature",
  "properties": {
    "iso:country":"DE",
    "sg:address":"Marienburgstr. 16",
    "sg:city":"Singen",
    "sg:phone":"+49 7731/29902",
    "sg:postcode":"78224",
    "sg:province":"Baden-W\u00fcrttemberg",
    "wof:name":"L. Lob Gmbh",
    "wof:placetype":"venue"
},
  "geometry": {"coordinates":[8.8573331833,47.7469902039],"type":"Point"}
}