{
  "type": "Feature",
  "properties": {
    "iso:country":"DE",
    "sg:address":"Stuttgarter Str. 90",
    "sg:city":"Geislingen",
    "sg:phone":"+49 7331/66383",
    "sg:postcode":"73312",
    "sg:province":"Baden-W\u00fcrttemberg",
    "wof:name":"Sport Extra Achilles- Pechmann Gmbh",
    "wof:placetype":"venue"
},
  "geometry": {"coordinates":[9.82595,48.625225],"type":"Point"}
}