{
  "type": "Feature",
  "properties": {
    "iso:country":"DE",
    "sg:city":"Bremen",
    "sg:phone":"+49 421",
    "sg:postcode":"28199",
    "sg:province":"Bremen",
    "wof:name":"Drewes & Focke Und J. Herm. Runge, Versicherungen",
    "wof:placetype":"venue"
},
  "geometry": {"coordinates":[8.804667,53.075165],"type":"Point"}
}