{
  "type": "Feature",
  "properties": {
    "iso:country":"DE",
    "sg:address":"H\u00f6henweg 3",
    "sg:city":"Hagen",
    "sg:phone":"+49 5401/90006",
    "sg:postcode":"49170",
    "sg:province":"Niedersachsen",
    "wof:name":"Matec Maschinen- Und Anlagenbau Gmbh",
    "wof:placetype":"venue"
},
  "geometry": {"coordinates":[7.987002,52.197948],"type":"Point"}
}