{
  "type": "Feature",
  "properties": {
    "iso:country":"DE",
    "sg:address":"Schatzbogen 43b",
    "sg:city":"M\u00fcnchen",
    "sg:phone":"+49 89/4510460",
    "sg:postcode":"81829",
    "sg:province":"Bayern",
    "wof:name":"Loehr & Partner Gmbh",
    "wof:placetype":"venue"
},
  "geometry": {"coordinates":[11.662458,48.134083],"type":"Point"}
}