{
  "type": "Feature",
  "properties": {
    "iso:country":"DE",
    "sg:address":"Am Sch\u00f6nblick 41",
    "sg:city":"Bad Breisig",
    "sg:phone":"+49 2633/9300",
    "sg:postcode":"53498",
    "sg:province":"Rheinland-Pfalz",
    "wof:name":"B. Mestermann-henniges Hebamme",
    "wof:placetype":"venue"
},
  "geometry": {"coordinates":[7.284065,50.501225],"type":"Point"}
}