{
  "type": "Feature",
  "properties": {
    "iso:country":"DE",
    "sg:city":"S\u00fcpplingenburg",
    "sg:phone":"+49 4953/55333",
    "sg:postcode":"38376",
    "sg:province":"Niedersachsen",
    "wof:name":"Genossenschaftsbank Eg",
    "wof:placetype":"venue"
},
  "geometry": {"coordinates":[10.912979,52.251186],"type":"Point"}
}