{
  "type": "Feature",
  "properties": {
    "iso:country":"DE",
    "sg:address":"Hohenkampsweg 31a",
    "sg:city":"Bremen",
    "sg:phone":"+49 421/3469719",
    "sg:postcode":"28355",
    "sg:province":"Bremen",
    "wof:name":"Meyer Und Meyer-baumgartner Rechtsanw\u00e4lte",
    "wof:placetype":"venue"
},
  "geometry": {"coordinates":[8.9443969727,53.094417572],"type":"Point"}
}