{
  "type": "Feature",
  "properties": {
    "iso:country":"DE",
    "sg:address":"Andersenstr. 27",
    "sg:city":"L\u00f6hne",
    "sg:phone":"+49 5732/5493",
    "sg:postcode":"32584",
    "sg:province":"Nordrhein-Westfalen",
    "wof:name":"Horst Meier",
    "wof:placetype":"venue"
},
  "geometry": {"coordinates":[8.7011880875,52.2110671997],"type":"Point"}
}