{
  "type": "Feature",
  "properties": {
    "iso:country":"DE",
    "sg:address":"Gr\u00fcnewalder Str. 54a",
    "sg:city":"Solingen",
    "sg:phone":"+49 212/815181",
    "sg:postcode":"42657",
    "sg:province":"Nordrhein-Westfalen",
    "wof:name":"Marion M\u00fcller",
    "wof:placetype":"venue"
},
  "geometry": {"coordinates":[7.076383,51.160385],"type":"Point"}
}