{
  "type": "Feature",
  "properties": {
    "iso:country":"DE",
    "sg:address":"Wehdenweg 25",
    "sg:city":"Kiel",
    "sg:phone":"+49 431/7209230",
    "sg:postcode":"24148",
    "sg:province":"Schleswig-Holstein",
    "wof:name":"Hsi Software Service Und Immobilienverwaltung Gmbh",
    "wof:placetype":"venue"
},
  "geometry": {"coordinates":[10.202902,54.318981],"type":"Point"}
}