{
  "type": "Feature",
  "properties": {
    "iso:country":"DE",
    "sg:address":"Postweg 2",
    "sg:city":"Unterdie\u00dfen",
    "sg:phone":"+49 8243/3175",
    "sg:postcode":"86944",
    "sg:province":"Bayern",
    "wof:name":"Karl Dworski Ingenieur",
    "wof:placetype":"venue"
},
  "geometry": {"coordinates":[10.8298339844,47.9797058105],"type":"Point"}
}