{
  "type": "Feature",
  "properties": {
    "iso:country":"DE",
    "sg:address":"Unter den Eichen 2",
    "sg:city":"Bremen",
    "sg:phone":"+49 421",
    "sg:postcode":"28213",
    "sg:province":"Bremen",
    "wof:name":"Fachpraxis F\u00fcr Proktologie",
    "wof:placetype":"venue"
},
  "geometry": {"coordinates":[8.862936,53.090721],"type":"Point"}
}