{
  "type": "Feature",
  "properties": {
    "iso:country":"DE",
    "sg:address":"S\u00f6hlekamp 42",
    "sg:city":"Salzgitter",
    "sg:phone":"+49 5341/85920",
    "sg:postcode":"38228",
    "sg:province":"Niedersachsen",
    "wof:name":"Gastst\u00e4tte G. Winter",
    "wof:placetype":"venue"
},
  "geometry": {"coordinates":[10.3168077469,52.1394119263],"type":"Point"}
}