{
  "type": "Feature",
  "properties": {
    "iso:country":"DE",
    "sg:address":"Berliner Wall 20",
    "sg:city":"Rheda-Wiedenbr\u00fcck",
    "sg:phone":"+49 5242/2066",
    "sg:postcode":"33378",
    "sg:province":"Nordrhein-Westfalen",
    "wof:name":"G. Eckervogt Ohg",
    "wof:placetype":"venue"
},
  "geometry": {"coordinates":[8.3147878647,51.837638855],"type":"Point"}
}