{
  "type": "Feature",
  "properties": {
    "iso:country":"DE",
    "sg:address":"Ingolst\u00e4dter Str. 105",
    "sg:city":"Karlshuld",
    "sg:phone":"+49 8454/2080",
    "sg:postcode":"86668",
    "sg:province":"Bayern",
    "wof:name":"Dieter Remmele Architekt",
    "wof:placetype":"venue"
},
  "geometry": {"coordinates":[11.300079,48.691162],"type":"Point"}
}