{
  "type": "Feature",
  "properties": {
    "iso:country":"DE",
    "sg:address":"Angelburger Str. 25",
    "sg:city":"Flensburg",
    "sg:phone":"+49 461/27039",
    "sg:postcode":"24937",
    "sg:province":"Schleswig-Holstein",
    "wof:name":"Rainer Groth",
    "wof:placetype":"venue"
},
  "geometry": {"coordinates":[9.438534,54.782818],"type":"Point"}
}