{
  "type": "Feature",
  "properties": {
    "iso:country":"DE",
    "sg:address":"Am Koberg 22",
    "sg:city":"Selters",
    "sg:phone":"+49 6475/912904",
    "sg:postcode":"65618",
    "sg:province":"Hessen",
    "wof:name":"R. Ernet",
    "wof:placetype":"venue"
},
  "geometry": {"coordinates":[8.3171157837,50.3586196899],"type":"Point"}
}