{
  "type": "Feature",
  "properties": {
    "iso:country":"DE",
    "sg:address":"Lippestr. 44",
    "sg:city":"Dorsten",
    "sg:phone":"+49 2362/22866",
    "sg:postcode":"46282",
    "sg:province":"Nordrhein-Westfalen",
    "wof:name":"Multikauf-eichhorn Vertriebs Gmbh",
    "wof:placetype":"venue"
},
  "geometry": {"coordinates":[6.9646167755,51.6626281738],"type":"Point"}
}