{
  "type": "Feature",
  "properties": {
    "iso:country":"DE",
    "sg:address":"Berliner Allee 160",
    "sg:city":"Berlin",
    "sg:phone":"+49 30/92377774",
    "sg:postcode":"13088",
    "sg:province":"Berlin",
    "wof:name":"Opus Vinarium Gmbh",
    "wof:placetype":"venue"
},
  "geometry": {"coordinates":[13.4665498734,52.5522499084],"type":"Point"}
}