{
  "type": "Feature",
  "properties": {
    "iso:country":"DE",
    "sg:address":"Gahlener Weg 15 POSTFACH 1172",
    "sg:city":"Calau",
    "sg:phone":"+49 4935/41840",
    "sg:postcode":"03201",
    "sg:province":"Brandenburg",
    "wof:name":"Caleg Schrank Undgeh\u00c4usebau Gmbh",
    "wof:placetype":"venue"
},
  "geometry": {"coordinates":[13.988559,51.739555],"type":"Point"}
}