{
  "type": "Feature",
  "properties": {
    "iso:country":"DE",
    "sg:address":"L\u00fcneburger Str. 110",
    "sg:city":"Winsen",
    "sg:phone":"+49 4171/75000",
    "sg:postcode":"21423",
    "sg:province":"Niedersachsen",
    "wof:name":"Imbi\u00dfbetrieb Presto",
    "wof:placetype":"venue"
},
  "geometry": {"coordinates":[10.221777916,53.3533477783],"type":"Point"}
}