{
  "type": "Feature",
  "properties": {
    "iso:country":"DE",
    "sg:address":"Vahrenwalder Str. 24",
    "sg:city":"Hannover",
    "sg:phone":"+49 511/3482141",
    "sg:postcode":"30165",
    "sg:province":"Niedersachsen",
    "wof:name":"Restaurant Aristoteles",
    "wof:placetype":"venue"
},
  "geometry": {"coordinates":[9.7346200943,52.3877220154],"type":"Point"}
}