{
  "type": "Feature",
  "properties": {
    "iso:country":"DE",
    "sg:address":"M\u00fchlenbecker Str. 58",
    "sg:city":"Schildow",
    "sg:postcode":"16552",
    "sg:province":"Brandenburg",
    "wof:name":"Grundst\u00fccksgesellschaft Am T\u00f6ppersberg Mbh",
    "wof:placetype":"venue"
},
  "geometry": {"coordinates":[13.376832,52.645569],"type":"Point"}
}