{
  "type": "Feature",
  "properties": {
    "iso:country":"DE",
    "sg:address":"Oberer Eutinger Talhof",
    "sg:city":"Horb",
    "sg:postcode":"72160",
    "sg:province":"Baden-W\u00fcrttemberg",
    "wof:name":"J. Schlotterbeck",
    "wof:placetype":"venue"
},
  "geometry": {"coordinates":[8.691031456,48.445350647],"type":"Point"}
}