{
  "type": "Feature",
  "properties": {
    "iso:country":"DE",
    "sg:address":"Achternweg 1",
    "sg:city":"Delmenhorst",
    "sg:phone":"+49 4221/74535",
    "sg:postcode":"27751",
    "sg:province":"Niedersachsen",
    "wof:name":"Hans-wolfram Heldt Architekt",
    "wof:placetype":"venue"
},
  "geometry": {"coordinates":[8.678397,53.051987],"type":"Point"}
}