{
  "type": "Feature",
  "properties": {
    "iso:country":"DE",
    "sg:address":"Steinweg 1",
    "sg:city":"Vacha",
    "sg:phone":"+49 36962/24358",
    "sg:postcode":"36404",
    "sg:province":"Th\u00fcringen",
    "wof:name":"Gerhard Simon",
    "wof:placetype":"venue"
},
  "geometry": {"coordinates":[10.018753,50.82452],"type":"Point"}
}