{
  "type": "Feature",
  "properties": {
    "iso:country":"DE",
    "sg:address":"Fuhrtsberg 45a",
    "sg:city":"Malchin",
    "sg:phone":"+49 3994/210586",
    "sg:postcode":"17139",
    "sg:province":"Mecklenburg-Vorpommern",
    "wof:name":"Wolf B\u00f6ttcher",
    "wof:placetype":"venue"
},
  "geometry": {"coordinates":[12.7592172623,53.7261161804],"type":"Point"}
}