{
  "type": "Feature",
  "properties": {
    "iso:country":"DE",
    "sg:address":"An der Almert 5",
    "sg:city":"Schmallenberg",
    "sg:phone":"+49 2972/7050",
    "sg:postcode":"57392",
    "sg:province":"Nordrhein-Westfalen",
    "wof:name":"Hubert Droste",
    "wof:placetype":"venue"
},
  "geometry": {"coordinates":[8.3357133865,51.14686203],"type":"Point"}
}