{
  "type": "Feature",
  "properties": {
    "iso:country":"DE",
    "sg:address":"Gl\u00fcckauf-Str. 8",
    "sg:city":"Vienenburg",
    "sg:phone":"+49 5324/1512",
    "sg:postcode":"38690",
    "sg:province":"Niedersachsen",
    "wof:name":"H. St\u00fcbig",
    "wof:placetype":"venue"
},
  "geometry": {"coordinates":[10.538283,51.947609],"type":"Point"}
}