{
  "type": "Feature",
  "properties": {
    "iso:country":"DE",
    "sg:address":"Oberstr. 83",
    "sg:city":"Grevenbroich",
    "sg:phone":"+49 2181/74513",
    "sg:postcode":"41516",
    "sg:province":"Nordrhein-Westfalen",
    "wof:name":"Elsbeth Und G. Kottmann",
    "wof:placetype":"venue"
},
  "geometry": {"coordinates":[6.614458,51.099812],"type":"Point"}
}