{
  "type": "Feature",
  "properties": {
    "iso:country":"DE",
    "sg:address":"Ludwigstr. 17",
    "sg:city":"Edesheim",
    "sg:phone":"+49 6323/1343",
    "sg:postcode":"67483",
    "sg:province":"Rheinland-Pfalz",
    "wof:name":"Josef Mentz Weinanbau",
    "wof:placetype":"venue"
},
  "geometry": {"coordinates":[8.1288785934,49.2604408264],"type":"Point"}
}