{
  "type": "Feature",
  "properties": {
    "iso:country":"DE",
    "sg:address":"Seyfferstr. 103",
    "sg:city":"Stuttgart",
    "sg:phone":"+49 711/612190",
    "sg:postcode":"70193",
    "sg:province":"Baden-W\u00fcrttemberg",
    "wof:name":"I. V.-bau-gmbh",
    "wof:placetype":"venue"
},
  "geometry": {"coordinates":[9.1520576477,48.7756156921],"type":"Point"}
}