{
  "type": "Feature",
  "properties": {
    "iso:country":"DE",
    "sg:address":"Am Hainberg 41",
    "sg:city":"Moringen",
    "sg:phone":"+49 5555/9954003",
    "sg:postcode":"37186",
    "sg:province":"Niedersachsen",
    "wof:name":"Webservice-wohlgemuth",
    "wof:placetype":"venue"
},
  "geometry": {"coordinates":[9.7968149185,51.7376251221],"type":"Point"}
}