{
  "type": "Feature",
  "properties": {
    "iso:country":"DE",
    "sg:address":"Leipheimer Str. 87",
    "sg:city":"Neu-Ulm",
    "sg:phone":"+49 731/711749",
    "sg:postcode":"89233",
    "sg:province":"Bayern",
    "wof:name":"Benno Kling",
    "wof:placetype":"venue"
},
  "geometry": {"coordinates":[10.041844368,48.4064674377],"type":"Point"}
}