{
  "type": "Feature",
  "properties": {
    "iso:country":"DE",
    "sg:address":"Hauptstr. 33",
    "sg:city":"Dresden",
    "sg:phone":"+49 351/2690065",
    "sg:postcode":"01328",
    "sg:province":"Sachsen",
    "wof:name":"Hochland-express Stra\u00dfenverkehrsunternehmen",
    "wof:placetype":"venue"
},
  "geometry": {"coordinates":[13.888221,51.057243],"type":"Point"}
}