{
  "type": "Feature",
  "properties": {
    "iso:country":"DE",
    "sg:address":"Hochwinkel 43",
    "sg:city":"K\u00f6ln",
    "sg:phone":"+49 221/682011",
    "sg:postcode":"51069",
    "sg:province":"Nordrhein-Westfalen",
    "wof:name":"K. Schenk Rechtsanwalt",
    "wof:placetype":"venue"
},
  "geometry": {"coordinates":[7.0646781921,50.9650993347],"type":"Point"}
}