{
  "type": "Feature",
  "properties": {
    "iso:country":"DE",
    "sg:address":"Horremer Str. 7",
    "sg:city":"Neuss",
    "sg:phone":"+49 2137/76000",
    "sg:postcode":"41470",
    "sg:province":"Nordrhein-Westfalen",
    "wof:name":"Hedwig Krause Anlageberaterin",
    "wof:placetype":"venue"
},
  "geometry": {"coordinates":[6.7608442307,51.1263771057],"type":"Point"}
}