{
  "type": "Feature",
  "properties": {
    "iso:country":"DE",
    "sg:address":"Bergstr. 8",
    "sg:city":"Wietmarschen",
    "sg:phone":"+49 591/47633",
    "sg:postcode":"49835",
    "sg:province":"Niedersachsen",
    "wof:name":"\u00d6ko - Windenergie Nordlohne - Gmbh",
    "wof:placetype":"venue"
},
  "geometry": {"coordinates":[7.250076,52.52652],"type":"Point"}
}