{
  "type": "Feature",
  "properties": {
    "iso:country":"DE",
    "sg:address":"Hospitalstr 32",
    "sg:city":"Neunkirchen",
    "sg:phone":"+49 6821/25061",
    "sg:postcode":"66538",
    "sg:province":"Saarland",
    "wof:name":"Hans-joachim Schnell",
    "wof:placetype":"venue"
},
  "geometry": {"coordinates":[7.1818170547,49.348941803],"type":"Point"}
}