{
  "type": "Feature",
  "properties": {
    "iso:country":"DE",
    "sg:address":"Gut Schnellenberg",
    "sg:city":"L\u00fcneburg",
    "sg:phone":"+49 4131/63563",
    "sg:postcode":"21339",
    "sg:province":"Niedersachsen",
    "wof:name":"Wasmuth Von Meding",
    "wof:placetype":"venue"
},
  "geometry": {"coordinates":[10.368882,53.236965],"type":"Point"}
}