{
  "type": "Feature",
  "properties": {
    "iso:country":"DE",
    "sg:address":"H\u00f6henstr. 30",
    "sg:city":"Rabenau",
    "sg:phone":"+49 6407/1259",
    "sg:postcode":"35466",
    "sg:province":"Hessen",
    "wof:name":"Herbert Werner",
    "wof:placetype":"venue"
},
  "geometry": {"coordinates":[8.8875284195,50.664100647],"type":"Point"}
}