{
  "type": "Feature",
  "properties": {
    "iso:country":"DE",
    "sg:address":"Zum Mainholz 4",
    "sg:city":"Lichtenfels",
    "sg:phone":"+49 5636/97950",
    "sg:postcode":"35104",
    "sg:province":"Hessen",
    "wof:name":"Pflegezentrum Lichtenfels Gmbh",
    "wof:placetype":"venue"
},
  "geometry": {"coordinates":[8.794562,51.174541],"type":"Point"}
}