{
  "type": "Feature",
  "properties": {
    "iso:country":"DE",
    "sg:address":"Dreim\u00fchlenstr. 29",
    "sg:city":"M\u00fcnchen",
    "sg:phone":"+49 89/7473330",
    "sg:postcode":"80469",
    "sg:province":"Bayern",
    "wof:name":"Just Travel Gmbh",
    "wof:placetype":"venue"
},
  "geometry": {"coordinates":[11.5595493317,48.1204452515],"type":"Point"}
}