{
  "type": "Feature",
  "properties": {
    "iso:country":"DE",
    "sg:address":"Obere Dammstr. 10",
    "sg:city":"Solingen",
    "sg:phone":"+49 212/58750",
    "sg:postcode":"42653",
    "sg:province":"Nordrhein-Westfalen",
    "wof:name":"Delft Instruments-brd Gmbh",
    "wof:placetype":"venue"
},
  "geometry": {"coordinates":[7.079108,51.181107],"type":"Point"}
}