{
  "type": "Feature",
  "properties": {
    "iso:country":"DE",
    "sg:address":"Grundstr. 19",
    "sg:city":"Villingen-Schwenningen",
    "sg:phone":"+49 7721/71932",
    "sg:postcode":"78052",
    "sg:province":"Baden-W\u00fcrttemberg",
    "wof:name":"Werner Benz",
    "wof:placetype":"venue"
},
  "geometry": {"coordinates":[8.5110826492,48.0963821411],"type":"Point"}
}