{
  "type": "Feature",
  "properties": {
    "iso:country":"DE",
    "sg:address":"Bahnhofstr.",
    "sg:city":"Kastorf",
    "sg:phone":"+49 4501/218",
    "sg:postcode":"23847",
    "sg:province":"Schleswig-Holstein",
    "wof:name":"Herbert Schering",
    "wof:placetype":"venue"
},
  "geometry": {"coordinates":[10.56686,53.747925],"type":"Point"}
}