{
  "type": "Feature",
  "properties": {
    "iso:country":"DE",
    "sg:address":"Menzelstr.",
    "sg:city":"Kassel",
    "sg:postcode":"34121",
    "sg:province":"Hessen",
    "wof:name":"Universit\u00e4t Kassel Mensa",
    "wof:placetype":"venue"
},
  "geometry": {"coordinates":[9.4846878052,51.3021469116],"type":"Point"}
}