{
  "type": "Feature",
  "properties": {
    "iso:country":"DE",
    "sg:address":"N\u00fcrtinger Str. 10",
    "sg:city":"N\u00fcrtingen",
    "sg:phone":"+49 7022/52244",
    "sg:postcode":"72622",
    "sg:province":"Baden-W\u00fcrttemberg",
    "wof:name":"Hirsch",
    "wof:placetype":"venue"
},
  "geometry": {"coordinates":[9.3106632233,48.6179161072],"type":"Point"}
}