{
  "type": "Feature",
  "properties": {
    "iso:country":"DE",
    "sg:address":"Rudi-Arndt-Str. 15",
    "sg:city":"Tangerh\u00fctte",
    "sg:phone":"+49 4939/359400",
    "sg:postcode":"39517",
    "sg:province":"Sachsen-Anhalt",
    "wof:name":"Technoguss Tangerh\u00dctte Gmbh",
    "wof:placetype":"venue"
},
  "geometry": {"coordinates":[11.80866,52.434437],"type":"Point"}
}