{
  "type": "Feature",
  "properties": {
    "iso:country":"DE",
    "sg:address":"Brahmsweg 15",
    "sg:city":"Meerbusch",
    "sg:phone":"+49 2159/1257",
    "sg:postcode":"40670",
    "sg:province":"Nordrhein-Westfalen",
    "wof:name":"J. Pollack Architekt",
    "wof:placetype":"venue"
},
  "geometry": {"coordinates":[6.639647,51.266869],"type":"Point"}
}