{
  "type": "Feature",
  "properties": {
    "iso:country":"DE",
    "sg:address":"Neuengammer Hausdeich 453",
    "sg:city":"Hamburg",
    "sg:phone":"+49 40/7231215",
    "sg:postcode":"21039",
    "sg:province":"Hamburg",
    "wof:name":"Hermann Heitmann",
    "wof:placetype":"venue"
},
  "geometry": {"coordinates":[10.201773,53.460278],"type":"Point"}
}