{
  "type": "Feature",
  "properties": {
    "iso:country":"DE",
    "sg:address":"M\u00f6nchstr. 32",
    "sg:city":"Marsberg",
    "sg:phone":"+49 2992/95099",
    "sg:postcode":"34431",
    "sg:province":"Nordrhein-Westfalen",
    "wof:name":"Telemax-datentechnik Gmbh",
    "wof:placetype":"venue"
},
  "geometry": {"coordinates":[8.857088,51.466621],"type":"Point"}
}