{
  "type": "Feature",
  "properties": {
    "iso:country":"DE",
    "sg:address":"Weilimdorfer Str. 47",
    "sg:city":"Korntal-M\u00fcnchingen",
    "sg:phone":"+49 711/83948480",
    "sg:postcode":"70825",
    "sg:province":"Baden-W\u00fcrttemberg",
    "wof:name":"Mosaiq-media Gmbh",
    "wof:placetype":"venue"
},
  "geometry": {"coordinates":[9.11608,48.825562],"type":"Point"}
}