{
  "type": "Feature",
  "properties": {
    "iso:country":"DE",
    "sg:address":"Hauptstr. 37",
    "sg:city":"K\u00fcllstedt",
    "sg:phone":"+49 36075/64360",
    "sg:postcode":"37359",
    "sg:province":"Th\u00fcringen",
    "wof:name":"Bernhard Mock",
    "wof:placetype":"venue"
},
  "geometry": {"coordinates":[10.276116,51.277237],"type":"Point"}
}