{
  "type": "Feature",
  "properties": {
    "iso:country":"DE",
    "sg:address":"Erichshofer Str. 78",
    "sg:city":"Weyhe",
    "sg:phone":"+49 421/892201",
    "sg:postcode":"28844",
    "sg:province":"Niedersachsen",
    "wof:name":"Trockenbau-heimann-menke Gmbh",
    "wof:placetype":"venue"
},
  "geometry": {"coordinates":[8.790124,52.996849],"type":"Point"}
}