{
  "type": "Feature",
  "properties": {
    "iso:country":"DE",
    "sg:address":"Gladbecker Str. 75",
    "sg:city":"Dorsten",
    "sg:phone":"+49 2362/22999",
    "sg:postcode":"46282",
    "sg:province":"Nordrhein-Westfalen",
    "wof:name":"Robert Kringel",
    "wof:placetype":"venue"
},
  "geometry": {"coordinates":[6.96525,51.649342],"type":"Point"}
}