{
  "type": "Feature",
  "properties": {
    "iso:country":"DE",
    "sg:address":"Nordstr. 108",
    "sg:city":"Remscheid",
    "sg:phone":"+49 2191/28989",
    "sg:postcode":"42853",
    "sg:province":"Nordrhein-Westfalen",
    "wof:name":"B\u00f6cker Bauelemente Gmbh & Co.",
    "wof:placetype":"venue"
},
  "geometry": {"coordinates":[7.190652,51.183788],"type":"Point"}
}