{
  "type": "Feature",
  "properties": {
    "iso:country":"DE",
    "sg:address":"Westmark 1",
    "sg:city":"Vechta",
    "sg:postcode":"49377",
    "sg:province":"Niedersachsen",
    "wof:name":"Zooform Handel Beteiligungs- Gmbh",
    "wof:placetype":"venue"
},
  "geometry": {"coordinates":[8.262979,52.718506],"type":"Point"}
}