{
  "type": "Feature",
  "properties": {
    "iso:country":"DE",
    "sg:address":"Garbenheimer Str. 36-38",
    "sg:city":"Wetzlar",
    "sg:phone":"+49 6441/9050",
    "sg:postcode":"35578",
    "sg:province":"Hessen",
    "wof:name":"Beck Ipc Gmbh",
    "wof:placetype":"venue"
},
  "geometry": {"coordinates":[8.51611,50.565781],"type":"Point"}
}