{
  "type": "Feature",
  "properties": {
    "iso:country":"DE",
    "sg:address":"Hauptstr. 31",
    "sg:city":"Giengen",
    "sg:phone":"+49 7322/7250",
    "sg:postcode":"89537",
    "sg:province":"Baden-W\u00fcrttemberg",
    "wof:name":"Karl F\u00e4rber",
    "wof:placetype":"venue"
},
  "geometry": {"coordinates":[10.2750692368,48.6281013489],"type":"Point"}
}