{
  "type": "Feature",
  "properties": {
    "iso:country":"DE",
    "sg:city":"Freudental",
    "sg:phone":"+49 7143/26693",
    "sg:postcode":"74392",
    "sg:province":"Baden-W\u00fcrttemberg",
    "wof:name":"Diakoniestation",
    "wof:placetype":"venue"
},
  "geometry": {"coordinates":[9.06091,49.009171],"type":"Point"}
}