{
  "type": "Feature",
  "properties": {
    "iso:country":"DE",
    "sg:address":"Poststr. 18",
    "sg:city":"Merzig",
    "sg:postcode":"66663",
    "sg:province":"Saarland",
    "wof:name":"Deutsche Telekom T-punkt",
    "wof:placetype":"venue"
},
  "geometry": {"coordinates":[6.6369519234,49.4427680969],"type":"Point"}
}