{
  "type": "Feature",
  "properties": {
    "iso:country":"DE",
    "sg:address":"Platnerstr. 13",
    "sg:city":"Leipzig",
    "sg:postcode":"04155",
    "sg:province":"Sachsen",
    "wof:name":"Weiss Messebau Gmbh",
    "wof:placetype":"venue"
},
  "geometry": {"coordinates":[12.3601074219,51.3583908081],"type":"Point"}
}