{
  "type": "Feature",
  "properties": {
    "iso:country":"DE",
    "sg:address":"Genrnsheimer Str. 79",
    "sg:city":"Pfungstadt",
    "sg:phone":"+49 4961/573674",
    "sg:postcode":"64319",
    "sg:province":"Hessen",
    "wof:name":"Volksbank Raiffeisen Eg",
    "wof:placetype":"venue"
},
  "geometry": {"coordinates":[8.556117,49.794807],"type":"Point"}
}