{
  "type": "Feature",
  "properties": {
    "iso:country":"DE",
    "sg:address":"Marschtorstr. 45",
    "sg:city":"Dannenberg",
    "sg:phone":"+49 5861/4716",
    "sg:postcode":"29451",
    "sg:province":"Niedersachsen",
    "wof:name":"Apotheke Seepassage",
    "wof:placetype":"venue"
},
  "geometry": {"coordinates":[11.099106,53.100677],"type":"Point"}
}