{
  "type": "Feature",
  "properties": {
    "iso:country":"DE",
    "sg:address":"Ernst-Th\u00e4lmann-Str. 53",
    "sg:city":"Br\u00fcck",
    "sg:phone":"+49 33844/215",
    "sg:postcode":"14822",
    "sg:province":"Brandenburg",
    "wof:name":"K. Fries",
    "wof:placetype":"venue"
},
  "geometry": {"coordinates":[12.760322,52.193195],"type":"Point"}
}