{
  "type": "Feature",
  "properties": {
    "iso:country":"DE",
    "sg:address":"Parsdorferstr.1",
    "sg:city":"Hergolding",
    "sg:postcode":"85599",
    "sg:province":"Bayern",
    "wof:name":"Mazinox Edelstahl Vtb Gmbh",
    "wof:placetype":"venue"
},
  "geometry": {"coordinates":[11.7916250229,48.1234741211],"type":"Point"}
}