{
  "type": "Feature",
  "properties": {
    "iso:country":"DE",
    "sg:address":"Schlichtstr. 8 A",
    "sg:city":"Waldsee",
    "sg:phone":"+49 6236/54322",
    "sg:postcode":"67165",
    "sg:province":"Rheinland-Pfalz",
    "wof:name":"Zur Schlicht",
    "wof:placetype":"venue"
},
  "geometry": {"coordinates":[8.4402837753,49.4048957825],"type":"Point"}
}