{
  "type": "Feature",
  "properties": {
    "iso:country":"DE",
    "sg:address":"K\u00f6lner Str. 226",
    "sg:city":"K\u00f6ln",
    "sg:postcode":"51149",
    "sg:province":"Nordrhein-Westfalen",
    "wof:name":"Iic Iran Informations Center E. K.",
    "wof:placetype":"venue"
},
  "geometry": {"coordinates":[7.0249590874,50.902431488],"type":"Point"}
}