{
  "type": "Feature",
  "properties": {
    "iso:country":"DE",
    "sg:address":"Alter Markt 11",
    "sg:city":"Arnsberg",
    "sg:phone":"+49 2931/22357",
    "sg:postcode":"59821",
    "sg:province":"Nordrhein-Westfalen",
    "wof:name":"Dieter Risse",
    "wof:placetype":"venue"
},
  "geometry": {"coordinates":[8.0639982224,51.3967895508],"type":"Point"}
}