{
  "type": "Feature",
  "properties": {
    "iso:country":"DE",
    "sg:address":"Uhlenbusch 18",
    "sg:city":"Seevetal",
    "sg:phone":"+49 40/7685657",
    "sg:postcode":"21217",
    "sg:province":"Niedersachsen",
    "wof:name":"E. Wolf Steuerberater",
    "wof:placetype":"venue"
},
  "geometry": {"coordinates":[10.0832290649,53.4455833435],"type":"Point"}
}