{
  "type": "Feature",
  "properties": {
    "iso:country":"DE",
    "sg:address":"Friedrichstr. 24",
    "sg:city":"Friedrichshafen",
    "sg:phone":"+49 4975/4170000",
    "sg:postcode":"88045",
    "sg:province":"Baden-W\u00fcrttemberg",
    "wof:name":"Bfg-bank Ag",
    "wof:placetype":"venue"
},
  "geometry": {"coordinates":[9.477404,47.651779],"type":"Point"}
}