{
  "type": "Feature",
  "properties": {
    "iso:country":"DE",
    "sg:address":"Gro\u00dfenbaumer Allee 168-174",
    "sg:city":"Duisburg",
    "sg:phone":"+49 203/2837053",
    "sg:postcode":"47269",
    "sg:province":"Nordrhein-Westfalen",
    "wof:name":"Gesamthochschule S\u00fcd Schulbibliothek",
    "wof:placetype":"venue"
},
  "geometry": {"coordinates":[6.778365,51.365551],"type":"Point"}
}