{
  "type": "Feature",
  "properties": {
    "iso:country":"DE",
    "sg:address":"Brunnenstr. 6",
    "sg:city":"B\u00f6hmenkirch",
    "sg:phone":"+49 7332/6955",
    "sg:postcode":"89558",
    "sg:province":"Baden-W\u00fcrttemberg",
    "wof:name":"Josef Kaiser",
    "wof:placetype":"venue"
},
  "geometry": {"coordinates":[9.878065,48.675381],"type":"Point"}
}