{
  "type": "Feature",
  "properties": {
    "iso:country":"DE",
    "sg:address":"Veldener Str. 27",
    "sg:city":"Vilsbiburg",
    "sg:phone":"+49 8741/96060",
    "sg:postcode":"84137",
    "sg:province":"Bayern",
    "wof:name":"Balk Gmbh & Co. Kg",
    "wof:placetype":"venue"
},
  "geometry": {"coordinates":[12.3544502258,48.4441184998],"type":"Point"}
}