{
  "type": "Feature",
  "properties": {
    "iso:country":"DE",
    "sg:address":"Majoransheide 13",
    "sg:city":"L\u00fcbben",
    "sg:phone":"+49 3546/3073",
    "sg:postcode":"15907",
    "sg:province":"Brandenburg",
    "wof:name":"Einkaufs- Und Liefergenossenschaft",
    "wof:placetype":"venue"
},
  "geometry": {"coordinates":[13.872256,51.941032],"type":"Point"}
}