{
  "type": "Feature",
  "properties": {
    "iso:country":"DE",
    "sg:address":"Gotthelf-Leimbach-Str. 9",
    "sg:city":"G\u00f6ttingen",
    "sg:phone":"+49 551/505480",
    "sg:postcode":"37079",
    "sg:province":"Niedersachsen",
    "wof:name":"G\u00f6ttinger Bedachungsgesch\u00e4ft Josef Engelhardt Gmbh & Co. Kg",
    "wof:placetype":"venue"
},
  "geometry": {"coordinates":[9.891752,51.546455],"type":"Point"}
}