{
  "type": "Feature",
  "properties": {
    "iso:country":"DE",
    "sg:address":"Himmerichweg 10",
    "sg:city":"Bonn",
    "sg:phone":"+49 228/464868",
    "sg:postcode":"53227",
    "sg:province":"Nordrhein-Westfalen",
    "wof:name":"C. Kissener",
    "wof:placetype":"venue"
},
  "geometry": {"coordinates":[7.139113,50.726448],"type":"Point"}
}