{
  "type": "Feature",
  "properties": {
    "iso:country":"DE",
    "sg:address":"Wilhelm-Raabe-Str. 20",
    "sg:city":"Stuttgart",
    "sg:phone":"+49 711/606198",
    "sg:postcode":"70199",
    "sg:province":"Baden-W\u00fcrttemberg",
    "wof:name":"Wilhelm Mathes Architekt",
    "wof:placetype":"venue"
},
  "geometry": {"coordinates":[9.159067,48.758419],"type":"Point"}
}