{
  "type": "Feature",
  "properties": {
    "iso:country":"DE",
    "sg:address":"Am Hohen Berg 22",
    "sg:city":"Usingen",
    "sg:phone":"+49 6081/2895",
    "sg:postcode":"61250",
    "sg:province":"Hessen",
    "wof:name":"Henry Behn Fassadentechnik Gmbh",
    "wof:placetype":"venue"
},
  "geometry": {"coordinates":[8.525508,50.34127],"type":"Point"}
}