{
  "type": "Feature",
  "properties": {
    "iso:country":"DE",
    "sg:address":"Dorfstr. 9",
    "sg:city":"Goldkronach",
    "sg:phone":"+49 9208/379",
    "sg:postcode":"95497",
    "sg:province":"Bayern",
    "wof:name":"Schwarzer Adler",
    "wof:placetype":"venue"
},
  "geometry": {"coordinates":[11.6851978302,49.9942016602],"type":"Point"}
}