{
  "type": "Feature",
  "properties": {
    "iso:country":"DE",
    "sg:address":"35410",
    "sg:city":"Hungen-Inheiden",
    "sg:postcode":"35410",
    "sg:province":"Hessen",
    "wof:name":"Oberhessische Volksbank Hungen Eg",
    "wof:placetype":"venue"
},
  "geometry": {"coordinates":[8.8929,50.458691],"type":"Point"}
}