{
  "type": "Feature",
  "properties": {
    "iso:country":"DE",
    "sg:address":"Nienburger Str. 1a",
    "sg:city":"Sulingen",
    "sg:phone":"+49 4271/4551",
    "sg:postcode":"27232",
    "sg:province":"Niedersachsen",
    "wof:name":"Irene Steiner",
    "wof:placetype":"venue"
},
  "geometry": {"coordinates":[8.8135080338,52.6834449768],"type":"Point"}
}