{
  "type": "Feature",
  "properties": {
    "iso:country":"DE",
    "sg:address":"Ostraallee 20",
    "sg:city":"Dresden",
    "sg:phone":"+49 351/48642601",
    "sg:postcode":"01069",
    "sg:province":"Sachsen",
    "wof:name":"Sz-online | Sachsen Im Netz",
    "wof:placetype":"venue"
},
  "geometry": {"coordinates":[13.728412,51.056957],"type":"Point"}
}