{
  "type": "Feature",
  "properties": {
    "iso:country":"DE",
    "sg:address":"Karl-G\u00f6tz-Str 5",
    "sg:city":"Schweinfurt",
    "sg:phone":"+49 7136/4088",
    "sg:postcode":"97424",
    "sg:province":"Bayern",
    "wof:name":"Alsa-chemie Oberfl\u00e4chentechnik",
    "wof:placetype":"venue"
},
  "geometry": {"coordinates":[9.205973,49.229523],"type":"Point"}
}