{
  "type": "Feature",
  "properties": {
    "iso:country":"DE",
    "sg:address":"Pappelweg 45",
    "sg:city":"Bovenden",
    "sg:phone":"+49 5593/92980",
    "sg:postcode":"37120",
    "sg:province":"Niedersachsen",
    "wof:name":"G\u00f6ttinger Farbfilter Gmbh",
    "wof:placetype":"venue"
},
  "geometry": {"coordinates":[9.87813,51.590012],"type":"Point"}
}