{
  "type": "Feature",
  "properties": {
    "iso:country":"DE",
    "sg:address":"Borker Str. 24 Eing. Ladestr.",
    "sg:city":"L\u00fcnen",
    "sg:postcode":"44534",
    "sg:province":"Nordrhein-Westfalen",
    "wof:name":"Linz & Co. Gmbh",
    "wof:placetype":"venue"
},
  "geometry": {"coordinates":[7.5190501213,51.6128501892],"type":"Point"}
}