{
  "type": "Feature",
  "properties": {
    "iso:country":"DE",
    "sg:address":"Hansestr. 12",
    "sg:city":"Uelzen",
    "sg:phone":"+49 581/970020",
    "sg:postcode":"29525",
    "sg:province":"Niedersachsen",
    "wof:name":"Rollw\u00e4nde- Und Jalousienfabrik C. Behrens Gmbh & Co.",
    "wof:placetype":"venue"
},
  "geometry": {"coordinates":[10.542966,52.990692],"type":"Point"}
}