{
  "type": "Feature",
  "properties": {
    "iso:country":"DE",
    "sg:address":"Altratjensdorf",
    "sg:city":"Riepsdorf",
    "sg:phone":"+49 4366/426",
    "sg:postcode":"23738",
    "sg:province":"Schleswig-Holstein",
    "wof:name":"Hermann Schuldt",
    "wof:placetype":"venue"
},
  "geometry": {"coordinates":[11.00044,54.22681],"type":"Point"}
}