{
  "type": "Feature",
  "properties": {
    "iso:country":"DE",
    "sg:address":"Dorfstr. 16",
    "sg:city":"Lunzenau",
    "sg:phone":"+49 37383/6319",
    "sg:postcode":"09328",
    "sg:province":"Sachsen",
    "wof:name":"A. K\u00e4stner",
    "wof:placetype":"venue"
},
  "geometry": {"coordinates":[12.7772388458,50.9573478699],"type":"Point"}
}