{
  "type": "Feature",
  "properties": {
    "iso:country":"DE",
    "sg:address":"Grimmer Str. 86-88",
    "sg:city":"Greifswald",
    "sg:postcode":"17489",
    "sg:province":"Mecklenburg-Vorpommern",
    "wof:name":"Botanisches Institut",
    "wof:placetype":"venue"
},
  "geometry": {"coordinates":[13.366185,54.094711],"type":"Point"}
}