{
  "type": "Feature",
  "properties": {
    "iso:country":"DE",
    "sg:address":"Wingertstr. 7",
    "sg:city":"Idar-Oberstein",
    "sg:phone":"+49 6781/900829",
    "sg:postcode":"55743",
    "sg:province":"Rheinland-Pfalz",
    "wof:name":"N. M\u00fcller Und S. H\u00fcttner-m\u00fcller",
    "wof:placetype":"venue"
},
  "geometry": {"coordinates":[7.3001489639,49.7226715088],"type":"Point"}
}