{
  "type": "Feature",
  "properties": {
    "iso:country":"DE",
    "sg:address":"Zehnstadel 2",
    "sg:city":"Schalkau",
    "sg:phone":"+49 36766/22833",
    "sg:postcode":"96528",
    "sg:province":"Th\u00fcringen",
    "wof:name":"Ronald Wolf",
    "wof:placetype":"venue"
},
  "geometry": {"coordinates":[11.0061922073,50.3971710205],"type":"Point"}
}