{
  "type": "Feature",
  "properties": {
    "iso:country":"DE",
    "sg:address":"Beifu\u00dfweg 11",
    "sg:city":"Berlin",
    "sg:postcode":"12357",
    "sg:province":"Berlin",
    "wof:name":"Ul-connection Leichtflugzeuge Gmbh",
    "wof:placetype":"venue"
},
  "geometry": {"coordinates":[13.4753656387,52.4375572205],"type":"Point"}
}