{
  "type": "Feature",
  "properties": {
    "iso:country":"DE",
    "sg:address":"Steinbachstr. 22",
    "sg:city":"Passau",
    "sg:postcode":"94036",
    "sg:province":"Bayern",
    "wof:name":"Lindner Gmbh & Co. Kg Objekt M.",
    "wof:placetype":"venue"
},
  "geometry": {"coordinates":[13.4090003967,48.5739097595],"type":"Point"}
}