{
  "type": "Feature",
  "properties": {
    "iso:country":"DE",
    "sg:address":"Gr\u00fcntenstr. 1",
    "sg:city":"Buxheim",
    "sg:postcode":"87740",
    "sg:province":"Bayern",
    "wof:name":"Peters Radsport",
    "wof:placetype":"venue"
},
  "geometry": {"coordinates":[10.143135,47.995045],"type":"Point"}
}