{
  "type": "Feature",
  "properties": {
    "iso:country":"DE",
    "sg:address":"H\u00f6ll 2",
    "sg:city":"Ravensburg",
    "sg:phone":"+49 751/23037",
    "sg:postcode":"88212",
    "sg:province":"Baden-W\u00fcrttemberg",
    "wof:name":"Weinimport Zum Muke Weinkellerei Eric Knoblauch",
    "wof:placetype":"venue"
},
  "geometry": {"coordinates":[9.5909795761,47.7852210999],"type":"Point"}
}