{
  "type": "Feature",
  "properties": {
    "iso:country":"DE",
    "sg:address":"Pfifferling 1",
    "sg:city":"Rottenburg",
    "sg:phone":"+49 8781/1040",
    "sg:postcode":"84056",
    "sg:province":"Bayern",
    "wof:name":"Frimberger Gmbh",
    "wof:placetype":"venue"
},
  "geometry": {"coordinates":[12.07351017,48.6961784363],"type":"Point"}
}