{
  "type": "Feature",
  "properties": {
    "iso:country":"DE",
    "sg:address":"Dresdener Str. 24",
    "sg:city":"Bad Liebenwerda",
    "sg:phone":"+49 35341/12471",
    "sg:postcode":"04924",
    "sg:province":"Brandenburg",
    "wof:name":"Hgb Haus- Und Grundbesitzges. Bad Liebenwerda Mbh",
    "wof:placetype":"venue"
},
  "geometry": {"coordinates":[13.4048757553,51.5149536133],"type":"Point"}
}