{
  "type": "Feature",
  "properties": {
    "iso:country":"DE",
    "sg:address":"Berliner Platz 12",
    "sg:city":"Oer-Erkenschwick",
    "sg:phone":"+49 2368/1774",
    "sg:postcode":"45739",
    "sg:province":"Nordrhein-Westfalen",
    "wof:name":"Betten K\u00e4hning Gmbh",
    "wof:placetype":"venue"
},
  "geometry": {"coordinates":[7.2596001625,51.6398277283],"type":"Point"}
}