{
  "type": "Feature",
  "properties": {
    "iso:country":"DE",
    "sg:address":"Buckhof 1",
    "sg:city":"Freiamt",
    "sg:phone":"+49 4976/45445",
    "sg:postcode":"79348",
    "sg:province":"Baden-W\u00fcrttemberg",
    "wof:name":"Markus Glatz",
    "wof:placetype":"venue"
},
  "geometry": {"coordinates":[7.918613,48.18885],"type":"Point"}
}