{
  "type": "Feature",
  "properties": {
    "iso:country":"DE",
    "sg:address":"Am Teich 78",
    "sg:city":"L\u00fcbeck",
    "sg:phone":"+49 451/690290",
    "sg:postcode":"23568",
    "sg:province":"Schleswig-Holstein",
    "wof:name":"P. Rutkowski",
    "wof:placetype":"venue"
},
  "geometry": {"coordinates":[10.790875,53.885883],"type":"Point"}
}