{
  "type": "Feature",
  "properties": {
    "iso:country":"DE",
    "sg:address":"Bahnhofstr. 4",
    "sg:city":"Waldfischbach-Burgalben",
    "sg:phone":"+49 6333/1516",
    "sg:postcode":"67714",
    "sg:province":"Rheinland-Pfalz",
    "wof:name":"Bahnhofsgastst\u00e4tte",
    "wof:placetype":"venue"
},
  "geometry": {"coordinates":[7.6524610519,49.2882652283],"type":"Point"}
}