{
  "type": "Feature",
  "properties": {
    "iso:country":"DE",
    "sg:address":"Hanweiler Str. 7/1",
    "sg:city":"Korb",
    "sg:phone":"+49 7151/32861",
    "sg:postcode":"71404",
    "sg:province":"Baden-W\u00fcrttemberg",
    "wof:name":"G\u00fcnther Ertel",
    "wof:placetype":"venue"
},
  "geometry": {"coordinates":[9.3699064255,48.8405189514],"type":"Point"}
}