{
  "type": "Feature",
  "properties": {
    "iso:country":"DE",
    "sg:address":"Spandauer Str. 160c",
    "sg:city":"Falkensee",
    "sg:phone":"+49 3322/22813",
    "sg:postcode":"14612",
    "sg:province":"Brandenburg",
    "wof:name":"Wand Und Boden Berlin Gmbh",
    "wof:placetype":"venue"
},
  "geometry": {"coordinates":[13.1342964172,52.5587425232],"type":"Point"}
}