{
  "type": "Feature",
  "properties": {
    "iso:country":"DE",
    "sg:address":"Schwedenweg 1 b",
    "sg:city":"N\u00fcrnberg",
    "sg:phone":"+49 911/882614",
    "sg:postcode":"90455",
    "sg:province":"Bayern",
    "wof:name":"Gerhard Hagelauer",
    "wof:placetype":"venue"
},
  "geometry": {"coordinates":[11.0708780289,49.3720283508],"type":"Point"}
}