{
  "type": "Feature",
  "properties": {
    "iso:country":"DE",
    "sg:address":"Springenweg 13",
    "sg:city":"Neukirchen-Vluyn",
    "sg:phone":"+49 2845/2598",
    "sg:postcode":"47506",
    "sg:province":"Nordrhein-Westfalen",
    "wof:name":"Hans Albert Mei\u00df Gmbh",
    "wof:placetype":"venue"
},
  "geometry": {"coordinates":[6.536205,51.439484],"type":"Point"}
}