{
  "type": "Feature",
  "properties": {
    "iso:country":"DE",
    "sg:address":"Schlo\u00dfstr. 2",
    "sg:city":"Dachau",
    "sg:phone":"+49 8131/4543660",
    "sg:postcode":"85221",
    "sg:province":"Bayern",
    "wof:name":"Caf\u00e9 Restaurant Schlo\u00df Dachau Zn Der Hz Gastronomie-",
    "wof:placetype":"venue"
},
  "geometry": {"coordinates":[11.433011055,48.2583312988],"type":"Point"}
}