{
  "type": "Feature",
  "properties": {
    "iso:country":"DE",
    "sg:address":"Eisenbahnstr. 5a",
    "sg:city":"Bechhofen",
    "sg:phone":"+49 9822/82020",
    "sg:postcode":"91572",
    "sg:province":"Bayern",
    "wof:name":"Kundner Verwaltungs Gmbh",
    "wof:placetype":"venue"
},
  "geometry": {"coordinates":[10.5559177399,49.1619224548],"type":"Point"}
}