{
  "type": "Feature",
  "properties": {
    "iso:country":"DE",
    "sg:address":"Industriestr. 7",
    "sg:city":"Baden-Baden",
    "sg:phone":"+49 7221/61827",
    "sg:postcode":"76532",
    "sg:province":"Baden-W\u00fcrttemberg",
    "wof:name":"E. Ihle",
    "wof:placetype":"venue"
},
  "geometry": {"coordinates":[8.190037,48.785843],"type":"Point"}
}