{
  "type": "Feature",
  "properties": {
    "iso:country":"DE",
    "sg:address":"Otto-Nagel-Str. 123",
    "sg:city":"Berlin",
    "sg:phone":"+49 30/5419123",
    "sg:postcode":"12683",
    "sg:province":"Berlin",
    "wof:name":"Karl-heinz Gennies",
    "wof:placetype":"venue"
},
  "geometry": {"coordinates":[13.551099,52.517052],"type":"Point"}
}