{
  "type": "Feature",
  "properties": {
    "iso:country":"DE",
    "sg:address":"Lenzhalde 1",
    "sg:city":"Leinfelden-Echterdingen",
    "sg:phone":"+49 711/7544638",
    "sg:postcode":"70771",
    "sg:province":"Baden-W\u00fcrttemberg",
    "wof:name":"Reinhold St\u00e4bler",
    "wof:placetype":"venue"
},
  "geometry": {"coordinates":[9.119324,48.691956],"type":"Point"}
}