{
  "type": "Feature",
  "properties": {
    "iso:country":"DE",
    "sg:address":"Bickenaschbacher Torhaus",
    "sg:city":"Zweibr\u00fccken",
    "sg:phone":"+49 6338/547",
    "sg:postcode":"66482",
    "sg:province":"Rheinland-Pfalz",
    "wof:name":"W. Vogt",
    "wof:placetype":"venue"
},
  "geometry": {"coordinates":[7.319999,49.190964],"type":"Point"}
}