{
  "type": "Feature",
  "properties": {
    "iso:country":"DE",
    "sg:address":"Mainstr. 9",
    "sg:city":"Marktheidenfeld",
    "sg:phone":"+49 9391/2558",
    "sg:postcode":"97828",
    "sg:province":"Bayern",
    "wof:name":"G. Scheiner",
    "wof:placetype":"venue"
},
  "geometry": {"coordinates":[9.595513,49.891773],"type":"Point"}
}