{
  "type": "Feature",
  "properties": {
    "iso:country":"DE",
    "sg:address":"Mathildenstr. 10",
    "sg:city":"Saarbr\u00fccken",
    "sg:phone":"+49 681/5898662",
    "sg:postcode":"66119",
    "sg:province":"Saarland",
    "wof:name":"Dr. Med. Marion Kisling",
    "wof:placetype":"venue"
},
  "geometry": {"coordinates":[6.9924449921,49.226978302],"type":"Point"}
}