{
  "type": "Feature",
  "properties": {
    "iso:country":"DE",
    "sg:address":"Auf der Schanze 3",
    "sg:city":"Bielefeld",
    "sg:phone":"+49 521/444637",
    "sg:postcode":"33647",
    "sg:province":"Nordrhein-Westfalen",
    "wof:name":"Beratungsstelle F. Suchtkranke Und Gef\u00e4hrdete Diakonisches",
    "wof:placetype":"venue"
},
  "geometry": {"coordinates":[8.511201,51.983742],"type":"Point"}
}