{
  "type": "Feature",
  "properties": {
    "iso:country":"DE",
    "sg:address":"Hauptstr. 38",
    "sg:city":"Reichartshausen",
    "sg:phone":"+49 6262/6637",
    "sg:postcode":"74934",
    "sg:province":"Baden-W\u00fcrttemberg",
    "wof:name":"Wilhelm Dentz",
    "wof:placetype":"venue"
},
  "geometry": {"coordinates":[8.944166,49.357887],"type":"Point"}
}