{
  "type": "Feature",
  "properties": {
    "iso:country":"DE",
    "sg:address":"Am K\u00f6nigsflo\u00df 20",
    "sg:city":"Mainz-Kastel",
    "sg:phone":"+49 6134/64751",
    "sg:postcode":"55252",
    "sg:province":"Hessen",
    "wof:name":"Siege Gem. Gmbh",
    "wof:placetype":"venue"
},
  "geometry": {"coordinates":[8.2943429947,50.0141143799],"type":"Point"}
}