{
  "type": "Feature",
  "properties": {
    "iso:country":"DE",
    "sg:address":"Neckarstr. 149",
    "sg:city":"Stuttgart",
    "sg:postcode":"70190",
    "sg:province":"Baden-W\u00fcrttemberg",
    "wof:name":"Verein Der Ehemaligen Sch\u00fcler Und Lehrer Des Zeppelin-",
    "wof:placetype":"venue"
},
  "geometry": {"coordinates":[9.1956634521,48.7896499634],"type":"Point"}
}