{
  "type": "Feature",
  "properties": {
    "iso:country":"DE",
    "sg:address":"Gei\u00dfelhardter Str. 1",
    "sg:city":"Mainhardt - Lachweiler",
    "sg:phone":"+49 7903/1020",
    "sg:postcode":"74535",
    "sg:province":"Baden-W\u00fcrttemberg",
    "wof:name":"R\u00d6la-bau Gmbh",
    "wof:placetype":"venue"
},
  "geometry": {"coordinates":[9.5577402115,49.0812606812],"type":"Point"}
}