{
  "type": "Feature",
  "properties": {
    "iso:country":"DE",
    "sg:address":"Museumstr. 50",
    "sg:city":"Neuwied",
    "sg:postcode":"56564",
    "sg:province":"Rheinland-Pfalz",
    "wof:name":"Haas Antiquit\u00e4ten Handels- Gmbh",
    "wof:placetype":"venue"
},
  "geometry": {"coordinates":[7.4719099998,50.4294509888],"type":"Point"}
}