{
  "type": "Feature",
  "properties": {
    "iso:country":"DE",
    "sg:address":"Markt 5",
    "sg:city":"Groitzsch",
    "sg:phone":"+49 34296/41446",
    "sg:postcode":"04539",
    "sg:province":"Sachsen",
    "wof:name":"Restaurant Alexis Sorbas",
    "wof:placetype":"venue"
},
  "geometry": {"coordinates":[12.2786712646,51.1568336487],"type":"Point"}
}