{
  "type": "Feature",
  "properties": {
    "iso:country":"DE",
    "sg:address":"Weberstr. 24",
    "sg:city":"D\u00fcsseldorf",
    "sg:phone":"+49 211/330044",
    "sg:postcode":"40215",
    "sg:province":"Nordrhein-Westfalen",
    "wof:name":"Hermann Joecken & S\u00f6hne Kg",
    "wof:placetype":"venue"
},
  "geometry": {"coordinates":[6.780118,51.209339],"type":"Point"}
}