{
  "type": "Feature",
  "properties": {
    "iso:country":"DE",
    "sg:address":"Volkwardingen 3",
    "sg:city":"Bispingen",
    "sg:phone":"+49 5194/2524",
    "sg:postcode":"29646",
    "sg:province":"Niedersachsen",
    "wof:name":"Cord-otto Wegener",
    "wof:placetype":"venue"
},
  "geometry": {"coordinates":[9.99922,53.12851],"type":"Point"}
}