{
  "type": "Feature",
  "properties": {
    "iso:country":"DE",
    "sg:address":"Fritz-Siemon-Str. 21",
    "sg:city":"Leipzig",
    "sg:phone":"+49 341/2412055",
    "sg:postcode":"04347",
    "sg:province":"Sachsen",
    "wof:name":"Prof. Dr. Werner Knaupe Ingenieur",
    "wof:placetype":"venue"
},
  "geometry": {"coordinates":[12.4188747406,51.3522262573],"type":"Point"}
}