{
  "type": "Feature",
  "properties": {
    "iso:country":"DE",
    "sg:address":"Gerichtsstr. 23",
    "sg:city":"Dortmund",
    "sg:phone":"+49 231/524824",
    "sg:postcode":"44135",
    "sg:province":"Nordrhein-Westfalen",
    "wof:name":"Pilz Gmbh",
    "wof:placetype":"venue"
},
  "geometry": {"coordinates":[7.478706,51.515385],"type":"Point"}
}