{
  "type": "Feature",
  "properties": {
    "iso:country":"DE",
    "sg:address":"Hinter Abend 2",
    "sg:city":"Treis-Karden",
    "sg:phone":"+49 2672/1328",
    "sg:postcode":"56253",
    "sg:province":"Rheinland-Pfalz",
    "wof:name":"Zilles Wetzlar & Co. Gmbh",
    "wof:placetype":"venue"
},
  "geometry": {"coordinates":[7.304648,50.16954],"type":"Point"}
}