{
  "type": "Feature",
  "properties": {
    "iso:country":"DE",
    "sg:address":"Lehmsiek 9",
    "sg:city":"Schwabstedt",
    "sg:postcode":"25876",
    "sg:province":"Schleswig-Holstein",
    "wof:name":"Baugesch\u00e4ft Jans Gmbh",
    "wof:placetype":"venue"
},
  "geometry": {"coordinates":[9.201018,54.410793],"type":"Point"}
}