{
  "type": "Feature",
  "properties": {
    "iso:country":"DE",
    "sg:address":"Steindamm 32",
    "sg:city":"Bremen",
    "sg:phone":"+49 421/643910",
    "sg:postcode":"28719",
    "sg:province":"Bremen",
    "wof:name":"Avtosped Internationale Speditions Gmbh",
    "wof:placetype":"venue"
},
  "geometry": {"coordinates":[8.7076177597,53.1620330811],"type":"Point"}
}