{
  "type": "Feature",
  "properties": {
    "iso:country":"DE",
    "sg:address":"Volkwinsweg 30",
    "sg:city":"Br\u00fchl",
    "sg:phone":"+49 2232/26346",
    "sg:postcode":"50321",
    "sg:province":"Nordrhein-Westfalen",
    "wof:name":"Horst K\u00f6rfgen",
    "wof:placetype":"venue"
},
  "geometry": {"coordinates":[6.893948,50.831421],"type":"Point"}
}