{
  "type": "Feature",
  "properties": {
    "iso:country":"DE",
    "sg:address":"Wilhelmstr. 8",
    "sg:city":"Plettenberg",
    "sg:phone":"+49 2391/3794",
    "sg:postcode":"58840",
    "sg:province":"Nordrhein-Westfalen",
    "wof:name":"Kurt Schadwinkel Lotterieannahme",
    "wof:placetype":"venue"
},
  "geometry": {"coordinates":[7.87418,51.213753],"type":"Point"}
}