{
  "type": "Feature",
  "properties": {
    "iso:country":"DE",
    "sg:address":"Limesstr. 24",
    "sg:city":"Kleinheubach",
    "sg:phone":"+49 9371/80998",
    "sg:postcode":"63924",
    "sg:province":"Bayern",
    "wof:name":"Harald Bayer Frischgefl\u00fcgel Gmbh",
    "wof:placetype":"venue"
},
  "geometry": {"coordinates":[9.2133131027,49.71667099],"type":"Point"}
}