{
  "type": "Feature",
  "properties": {
    "iso:country":"DE",
    "sg:address":"Hauptstr. 25",
    "sg:city":"Heidenheim",
    "sg:phone":"+49 7321/93580",
    "sg:postcode":"89522",
    "sg:province":"Baden-W\u00fcrttemberg",
    "wof:name":"Karl H\u00e4n\u00dfler Gmbh",
    "wof:placetype":"venue"
},
  "geometry": {"coordinates":[10.151921,48.676605],"type":"Point"}
}