{
  "type": "Feature",
  "properties": {
    "iso:country":"DE",
    "sg:address":"Drieschweg 3",
    "sg:city":"Bad Honnef",
    "sg:phone":"+49 2224/940530",
    "sg:postcode":"53604",
    "sg:province":"Nordrhein-Westfalen",
    "wof:name":"B. Schubert",
    "wof:placetype":"venue"
},
  "geometry": {"coordinates":[7.2259149551,50.6290740967],"type":"Point"}
}