{
  "type": "Feature",
  "properties": {
    "iso:country":"DE",
    "sg:address":"Breite Str. 1",
    "sg:city":"Nebra",
    "sg:phone":"+49 34461/24675",
    "sg:postcode":"06642",
    "sg:province":"Sachsen-Anhalt",
    "wof:name":"W. Neubert",
    "wof:placetype":"venue"
},
  "geometry": {"coordinates":[11.545285,51.268059],"type":"Point"}
}