{
  "type": "Feature",
  "properties": {
    "iso:country":"DE",
    "sg:address":"B\u00fcckebergstr. 59",
    "sg:city":"Buchholz",
    "sg:phone":"+49 5751/74334",
    "sg:postcode":"31710",
    "sg:province":"Niedersachsen",
    "wof:name":"F. R\u00f6bke",
    "wof:placetype":"venue"
},
  "geometry": {"coordinates":[9.1285028458,52.2270698547],"type":"Point"}
}