{
  "type": "Feature",
  "properties": {
    "iso:country":"DE",
    "sg:address":"Dorfstr. 28",
    "sg:city":"M\u00f6lln",
    "sg:phone":"+49 39602/20176",
    "sg:postcode":"17091",
    "sg:province":"Mecklenburg-Vorpommern",
    "wof:name":"E. Majora",
    "wof:placetype":"venue"
},
  "geometry": {"coordinates":[13.053204,53.57785],"type":"Point"}
}