{
  "type": "Feature",
  "properties": {
    "iso:country":"DE",
    "sg:address":"Eltener Str. 355",
    "sg:city":"Emmerich",
    "sg:phone":"+49 2822/45343",
    "sg:postcode":"46446",
    "sg:province":"Nordrhein-Westfalen",
    "wof:name":"Fam. Lensing-hebben Ortscher Hof",
    "wof:placetype":"venue"
},
  "geometry": {"coordinates":[6.2075438499,51.8465080261],"type":"Point"}
}