{
  "type": "Feature",
  "properties": {
    "iso:country":"DE",
    "sg:address":"Geisgasse 10",
    "sg:city":"Eberbach",
    "sg:phone":"+49 6271/91060",
    "sg:postcode":"69412",
    "sg:province":"Baden-W\u00fcrttemberg",
    "wof:name":"Ri Verlag F\u00fcr Regionalinformationen Gmbh",
    "wof:placetype":"venue"
},
  "geometry": {"coordinates":[8.9848556519,49.4622001648],"type":"Point"}
}