{
  "type": "Feature",
  "properties": {
    "iso:country":"DE",
    "sg:address":"Kamper Weg 57",
    "sg:city":"D\u00fcsseldorf",
    "sg:phone":"+49 211/278592",
    "sg:postcode":"40627",
    "sg:province":"Nordrhein-Westfalen",
    "wof:name":"Josef Orth",
    "wof:placetype":"venue"
},
  "geometry": {"coordinates":[6.851386,51.207153],"type":"Point"}
}