{
  "type": "Feature",
  "properties": {
    "iso:country":"DE",
    "sg:address":"Claussenstr. 12",
    "sg:city":"Bremerhaven",
    "sg:phone":"+49 471/25685",
    "sg:postcode":"27570",
    "sg:province":"Bremen",
    "wof:name":"J\u00f6rg Denzel Immobilienmakler",
    "wof:placetype":"venue"
},
  "geometry": {"coordinates":[8.5883350372,53.5409164429],"type":"Point"}
}