{
  "type": "Feature",
  "properties": {
    "iso:country":"DE",
    "sg:address":"Bachgasse 10",
    "sg:city":"Lauda-K\u00f6nigshofen",
    "sg:phone":"+49 9343/65618",
    "sg:postcode":"97922",
    "sg:province":"Baden-W\u00fcrttemberg",
    "wof:name":"A. Briscoe",
    "wof:placetype":"venue"
},
  "geometry": {"coordinates":[9.703424,49.570034],"type":"Point"}
}