{
  "type": "Feature",
  "properties": {
    "iso:country":"DE",
    "sg:address":"Leunaer Str. 24",
    "sg:city":"Marl",
    "sg:phone":"+49 2365/62883",
    "sg:postcode":"45772",
    "sg:province":"Nordrhein-Westfalen",
    "wof:name":"Anneliese Berendes Steuerbevollm\u00e4chtigte",
    "wof:placetype":"venue"
},
  "geometry": {"coordinates":[7.1055679321,51.6721496582],"type":"Point"}
}