{
  "type": "Feature",
  "properties": {
    "iso:country":"DE",
    "sg:address":"Schulstr. 8",
    "sg:city":"Havelberg",
    "sg:phone":"+49 39387/79032",
    "sg:postcode":"39539",
    "sg:province":"Sachsen-Anhalt",
    "wof:name":"K. Jannasch",
    "wof:placetype":"venue"
},
  "geometry": {"coordinates":[12.076346,52.825089],"type":"Point"}
}