{
  "type": "Feature",
  "properties": {
    "iso:country":"DE",
    "sg:address":"Spesbacher Str. 54",
    "sg:city":"Ramstein-Miesenbach",
    "sg:phone":"+49 6371/50454",
    "sg:postcode":"66877",
    "sg:province":"Rheinland-Pfalz",
    "wof:name":"Red Roses",
    "wof:placetype":"venue"
},
  "geometry": {"coordinates":[7.5485777855,49.4447631836],"type":"Point"}
}