{
  "type": "Feature",
  "properties": {
    "iso:country":"DE",
    "sg:address":"Philosophenweg",
    "sg:city":"Bad Arolsen",
    "sg:phone":"+49 5691/97960",
    "sg:postcode":"34454",
    "sg:province":"Hessen",
    "wof:name":"Waldecksches Diakonissenhaus",
    "wof:placetype":"venue"
},
  "geometry": {"coordinates":[8.9947786331,51.3655815125],"type":"Point"}
}