{
  "type": "Feature",
  "properties": {
    "iso:country":"DE",
    "sg:address":"Lehmweg 1",
    "sg:city":"Bienenb\u00fcttel",
    "sg:phone":"+49 5823/1794",
    "sg:postcode":"29553",
    "sg:province":"Niedersachsen",
    "wof:name":"Andreas Knobloch",
    "wof:placetype":"venue"
},
  "geometry": {"coordinates":[10.494436,53.116558],"type":"Point"}
}