{
  "type": "Feature",
  "properties": {
    "iso:country":"DE",
    "sg:address":"Postfach",
    "sg:city":"Gelsenkirchen",
    "sg:postcode":"45801",
    "sg:province":"Nordrhein-Westfalen",
    "wof:name":"Stein- Und Metall-bau Gmbh",
    "wof:placetype":"venue"
},
  "geometry": {"coordinates":[7.10538,51.52541],"type":"Point"}
}