{
  "type": "Feature",
  "properties": {
    "iso:country":"DE",
    "sg:address":"Brackeler Hellweg 136",
    "sg:city":"Dortmund",
    "sg:phone":"+49 231/259989",
    "sg:postcode":"44309",
    "sg:province":"Nordrhein-Westfalen",
    "wof:name":"Ratskeller",
    "wof:placetype":"venue"
},
  "geometry": {"coordinates":[7.5462698936,51.5237083435],"type":"Point"}
}