{
  "type": "Feature",
  "properties": {
    "iso:country":"DE",
    "sg:address":"Heidkoppel 1",
    "sg:city":"Bergen",
    "sg:phone":"+49 5054/989300",
    "sg:postcode":"29303",
    "sg:province":"Niedersachsen",
    "wof:name":"Holzwerk Roetenbach Gmbh",
    "wof:placetype":"venue"
},
  "geometry": {"coordinates":[10.0429811478,52.74451828],"type":"Point"}
}