{
  "type": "Feature",
  "properties": {
    "iso:country":"DE",
    "sg:address":"Weschental 20",
    "sg:city":"Horb",
    "sg:phone":"+49 7486/7698",
    "sg:postcode":"72160",
    "sg:province":"Baden-W\u00fcrttemberg",
    "wof:name":"Vereinsgastst\u00e4tte Sportheim",
    "wof:placetype":"venue"
},
  "geometry": {"coordinates":[8.6542835236,48.4856300354],"type":"Point"}
}