{
  "type": "Feature",
  "properties": {
    "iso:country":"DE",
    "sg:address":"Prinz-Karl-Str. 50",
    "sg:city":"Starnberg",
    "sg:postcode":"82319",
    "sg:province":"Bayern",
    "wof:name":"Vip Voelkel Industrie- Produkte Gmbh",
    "wof:placetype":"venue"
},
  "geometry": {"coordinates":[11.334775,48.003998],"type":"Point"}
}