{
  "type": "Feature",
  "properties": {
    "iso:country":"DE",
    "sg:address":"Schwarzwaldstr. 137",
    "sg:city":"Freiburg",
    "sg:phone":"+49 761/22274",
    "sg:postcode":"79102",
    "sg:province":"Baden-W\u00fcrttemberg",
    "wof:name":"Margarete Walter Krankengymnastin",
    "wof:placetype":"venue"
},
  "geometry": {"coordinates":[7.870814,47.988544],"type":"Point"}
}