{
  "type": "Feature",
  "properties": {
    "iso:country":"DE",
    "sg:address":"Greifswalder Str. 68",
    "sg:city":"Hamburg",
    "sg:phone":"+49 40/2802650",
    "sg:postcode":"20099",
    "sg:province":"Hamburg",
    "wof:name":"Rolf Kaiser",
    "wof:placetype":"venue"
},
  "geometry": {"coordinates":[10.0122013092,53.557346344],"type":"Point"}
}