{
  "type": "Feature",
  "properties": {
    "iso:country":"DE",
    "sg:address":"An der Kirche 2",
    "sg:city":"Uetze",
    "sg:phone":"+49 5147/254",
    "sg:postcode":"31311",
    "sg:province":"Niedersachsen",
    "wof:name":"Ev.-luth. Pfarramt Gem. H\u00e4nigsen",
    "wof:placetype":"venue"
},
  "geometry": {"coordinates":[10.0960416794,52.483215332],"type":"Point"}
}