{
  "type": "Feature",
  "properties": {
    "iso:country":"DE",
    "sg:address":"Zur G\u00f6tscher M\u00fchle 12",
    "sg:city":"Langenfeld",
    "sg:phone":"+49 2173/70379",
    "sg:postcode":"40764",
    "sg:province":"Nordrhein-Westfalen",
    "wof:name":"D. Franz",
    "wof:placetype":"venue"
},
  "geometry": {"coordinates":[6.956014,51.140026],"type":"Point"}
}