{
  "type": "Feature",
  "properties": {
    "iso:country":"DE",
    "sg:address":"Vorgangstra\u00dfe 21",
    "sg:city":"H\u00f6sbach",
    "sg:phone":"+49 6021/560721",
    "sg:postcode":"63768",
    "sg:province":"Bayern",
    "wof:name":"Medizinprodukte Jung",
    "wof:placetype":"venue"
},
  "geometry": {"coordinates":[9.1976642609,50.0028572083],"type":"Point"}
}