{
  "type": "Feature",
  "properties": {
    "iso:country":"DE",
    "sg:address":"Hochfeldstr. 2",
    "sg:city":"Augsburg",
    "sg:phone":"+49 821/36391",
    "sg:postcode":"86159",
    "sg:province":"Bayern",
    "wof:name":"R. Langner",
    "wof:placetype":"venue"
},
  "geometry": {"coordinates":[10.8997440338,48.3593635559],"type":"Point"}
}