{
  "type": "Feature",
  "properties": {
    "iso:country":"DE",
    "sg:address":"Ringstr. 5 a",
    "sg:city":"Neu Boltenhagen",
    "sg:phone":"+49 38373/20238",
    "sg:postcode":"17509",
    "sg:province":"Mecklenburg-Vorpommern",
    "wof:name":"Ziesetal Agrar Mbh",
    "wof:placetype":"venue"
},
  "geometry": {"coordinates":[13.610147,54.067108],"type":"Point"}
}