{
  "type": "Feature",
  "properties": {
    "iso:country":"DE",
    "sg:address":"Schmiedestr. 2",
    "sg:city":"Neunkirchen-Seelscheid",
    "sg:phone":"+49 2247/1803",
    "sg:postcode":"53819",
    "sg:province":"Nordrhein-Westfalen",
    "wof:name":"Karl-josef Oberd\u00f6rster",
    "wof:placetype":"venue"
},
  "geometry": {"coordinates":[7.3334350586,50.8404922485],"type":"Point"}
}