{
  "type": "Feature",
  "properties": {
    "iso:country":"DE",
    "sg:address":"Siedlerhof 3",
    "sg:city":"Rheinm\u00fcnster",
    "sg:phone":"+49 7227/2237",
    "sg:postcode":"77836",
    "sg:province":"Baden-W\u00fcrttemberg",
    "wof:name":"Emil Frietsch",
    "wof:placetype":"venue"
},
  "geometry": {"coordinates":[8.061947,48.749363],"type":"Point"}
}