{
  "type": "Feature",
  "properties": {
    "iso:country":"DE",
    "sg:address":"Baderplatz 10",
    "sg:city":"Neukirchen",
    "sg:phone":"+49 9947/1289",
    "sg:postcode":"93453",
    "sg:province":"Bayern",
    "wof:name":"Xaver Altmann",
    "wof:placetype":"venue"
},
  "geometry": {"coordinates":[12.970106,49.257229],"type":"Point"}
}