{
  "type": "Feature",
  "properties": {
    "iso:country":"DE",
    "sg:address":"Postplatz 7",
    "sg:city":"Kirchheim",
    "sg:phone":"+49 7021/46099",
    "sg:postcode":"73230",
    "sg:province":"Baden-W\u00fcrttemberg",
    "wof:name":"K\u00fcstermann Gmbh",
    "wof:placetype":"venue"
},
  "geometry": {"coordinates":[9.447288,48.649494],"type":"Point"}
}