{
  "type": "Feature",
  "properties": {
    "iso:country":"DE",
    "sg:address":"B\u00fcrgerstr. 14",
    "sg:city":"Wittenberge",
    "sg:phone":"+49 3877/60156",
    "sg:postcode":"19322",
    "sg:province":"Brandenburg",
    "wof:name":"Nordwest Dienstleistungs- Und Handels-gmbh",
    "wof:placetype":"venue"
},
  "geometry": {"coordinates":[11.7586593628,52.9956359863],"type":"Point"}
}