{
  "type": "Feature",
  "properties": {
    "iso:country":"DE",
    "sg:address":"Germanenstr. 6",
    "sg:city":"Neunkirchen-Seelscheid",
    "sg:phone":"+49 2247/6138",
    "sg:postcode":"53819",
    "sg:province":"Nordrhein-Westfalen",
    "wof:name":"P. Kuhn",
    "wof:placetype":"venue"
},
  "geometry": {"coordinates":[7.328701,50.869263],"type":"Point"}
}