{
  "type": "Feature",
  "properties": {
    "iso:country":"DE",
    "sg:address":"M\u00fchlstr. 22",
    "sg:city":"Ludwigsburg",
    "sg:phone":"+49 7141/93060",
    "sg:postcode":"71640",
    "sg:province":"Baden-W\u00fcrttemberg",
    "wof:name":"Albert-knapp-heim",
    "wof:placetype":"venue"
},
  "geometry": {"coordinates":[9.201354,48.897751],"type":"Point"}
}