{
  "type": "Feature",
  "properties": {
    "iso:country":"DE",
    "sg:address":"Klingelswiese 4",
    "sg:city":"Andernach",
    "sg:phone":"+49 2632/48113",
    "sg:postcode":"56626",
    "sg:province":"Rheinland-Pfalz",
    "wof:name":"Dental-labor Ulrich Gonsberg Gmbh",
    "wof:placetype":"venue"
},
  "geometry": {"coordinates":[7.3859009743,50.4265708923],"type":"Point"}
}