{
  "type": "Feature",
  "properties": {
    "iso:country":"DE",
    "sg:address":"Viktorstr. 12",
    "sg:city":"Wuppertal",
    "sg:phone":"+49 202/591519",
    "sg:postcode":"42275",
    "sg:province":"Nordrhein-Westfalen",
    "wof:name":"Gerhard Noll Rechtsanwalt",
    "wof:placetype":"venue"
},
  "geometry": {"coordinates":[7.1963877678,51.2725830078],"type":"Point"}
}