{
  "type": "Feature",
  "properties": {
    "iso:country":"DE",
    "sg:address":"Hauptstr. 40",
    "sg:city":"Gro\u00dflangheim",
    "sg:phone":"+49 9325/370",
    "sg:postcode":"97320",
    "sg:province":"Bayern",
    "wof:name":"Kath. Pfarramt St. Jakobus D.\u00c4.",
    "wof:placetype":"venue"
},
  "geometry": {"coordinates":[10.240404129,49.7550086975],"type":"Point"}
}