{
  "type": "Feature",
  "properties": {
    "iso:country":"DE",
    "sg:address":"Im T\u00fcmpfel",
    "sg:city":"P\u00f6\u00dfneck",
    "sg:phone":"+49 3647/423059",
    "sg:postcode":"07381",
    "sg:province":"Th\u00fcringen",
    "wof:name":"G. Haase",
    "wof:placetype":"venue"
},
  "geometry": {"coordinates":[11.605796,50.700428],"type":"Point"}
}