{
  "type": "Feature",
  "properties": {
    "iso:country":"DE",
    "sg:address":"Ob der Steig 28",
    "sg:city":"Erbach",
    "sg:phone":"+49 7305/4321",
    "sg:postcode":"89155",
    "sg:province":"Baden-W\u00fcrttemberg",
    "wof:name":"Dieter V\u00f6lk Architekt",
    "wof:placetype":"venue"
},
  "geometry": {"coordinates":[9.862632,48.31646],"type":"Point"}
}