{
  "type": "Feature",
  "properties": {
    "iso:country":"DE",
    "sg:address":"Fahrenheitstr. 6",
    "sg:city":"Bremen",
    "sg:postcode":"28359",
    "sg:province":"Bremen",
    "wof:name":"Hti Mitteldeutschland Beteiligungs- Und",
    "wof:placetype":"venue"
},
  "geometry": {"coordinates":[8.846287,53.107994],"type":"Point"}
}