{
  "type": "Feature",
  "properties": {
    "iso:country":"DE",
    "sg:address":"Burgstr. 3",
    "sg:city":"Bickendorf",
    "sg:phone":"+49 6569/833",
    "sg:postcode":"54636",
    "sg:province":"Rheinland-Pfalz",
    "wof:name":"Helmut Biewer E. K. Inh. Stefan Schomer",
    "wof:placetype":"venue"
},
  "geometry": {"coordinates":[6.4997358322,50.0340461731],"type":"Point"}
}