{
  "type": "Feature",
  "properties": {
    "iso:country":"DE",
    "sg:address":"An der Tuchbleiche 4",
    "sg:city":"Lampertheim",
    "sg:phone":"+49 6256/810",
    "sg:postcode":"68623",
    "sg:province":"Hessen",
    "wof:name":"Parker Hannifin Gmbh Zweigniederlassung Lampertheim",
    "wof:placetype":"venue"
},
  "geometry": {"coordinates":[8.583754,49.599789],"type":"Point"}
}