{
  "type": "Feature",
  "properties": {
    "iso:country":"DE",
    "sg:address":"Albert-Einstein-Str. 2",
    "sg:city":"Bergkamen",
    "sg:phone":"+49 2307/82401",
    "sg:postcode":"59192",
    "sg:province":"Nordrhein-Westfalen",
    "wof:name":"Seniorenzentrum Haus Am Nordberg",
    "wof:placetype":"venue"
},
  "geometry": {"coordinates":[7.641537,51.62159],"type":"Point"}
}