{
  "type": "Feature",
  "properties": {
    "iso:country":"DE",
    "sg:address":"Hauptstr.",
    "sg:city":"Trebur",
    "sg:phone":"+49 6147/3811",
    "sg:postcode":"65468",
    "sg:province":"Hessen",
    "wof:name":"Kalkst\u00fcbchen",
    "wof:placetype":"venue"
},
  "geometry": {"coordinates":[8.3987550735,49.9253540039],"type":"Point"}
}