{
  "type": "Feature",
  "properties": {
    "iso:country":"DE",
    "sg:address":"Sebastian-Kneipp-Str. 2",
    "sg:city":"St. Blasien",
    "sg:phone":"+49 7672/2066",
    "sg:postcode":"79837",
    "sg:province":"Baden-W\u00fcrttemberg",
    "wof:name":"Sportgastst\u00e4tte",
    "wof:placetype":"venue"
},
  "geometry": {"coordinates":[8.1195440292,47.766834259],"type":"Point"}
}