{
  "type": "Feature",
  "properties": {
    "iso:country":"DE",
    "sg:address":"Planie 7",
    "sg:city":"Reutlingen",
    "sg:phone":"+49 7121/346753",
    "sg:postcode":"72764",
    "sg:province":"Baden-W\u00fcrttemberg",
    "wof:name":"Margarete Knecht Heilpraktikerin",
    "wof:placetype":"venue"
},
  "geometry": {"coordinates":[9.2170972824,48.4923477173],"type":"Point"}
}