{
  "type": "Feature",
  "properties": {
    "iso:country":"DE",
    "sg:address":"Haidweg 45",
    "sg:city":"Varel",
    "sg:phone":"+49 4451/959681",
    "sg:postcode":"26316",
    "sg:province":"Niedersachsen",
    "wof:name":"Hermann Hinrichs Gmbh",
    "wof:placetype":"venue"
},
  "geometry": {"coordinates":[8.110324,53.370827],"type":"Point"}
}