{
  "type": "Feature",
  "properties": {
    "iso:country":"DE",
    "sg:address":"Wilhelmstr. 7",
    "sg:city":"Saarwellingen",
    "sg:phone":"+49 6838/3447",
    "sg:postcode":"66793",
    "sg:province":"Saarland",
    "wof:name":"Festhalle Saarwellingen",
    "wof:placetype":"venue"
},
  "geometry": {"coordinates":[6.807069,49.352119],"type":"Point"}
}