{
  "type": "Feature",
  "properties": {
    "iso:country":"DE",
    "sg:address":"Schlo\u00dfstr. 24",
    "sg:city":"Kalkar",
    "sg:phone":"+49 2824/6433",
    "sg:postcode":"47546",
    "sg:province":"Nordrhein-Westfalen",
    "wof:name":"Theo B\u00fcren K\u00fcchenchef",
    "wof:placetype":"venue"
},
  "geometry": {"coordinates":[6.315385,51.788193],"type":"Point"}
}