{
  "type": "Feature",
  "properties": {
    "iso:country":"DE",
    "sg:address":"B\u00fcckingstr. 1",
    "sg:city":"Bremen",
    "sg:phone":"+49 421/36370",
    "sg:postcode":"28217",
    "sg:province":"Bremen",
    "wof:name":"Nis Industrie- Und Schiffstechnik Gmbh",
    "wof:placetype":"venue"
},
  "geometry": {"coordinates":[8.757405,53.100349],"type":"Point"}
}