{
  "type": "Feature",
  "properties": {
    "iso:country":"DE",
    "sg:address":"Ostlandstr. 12",
    "sg:city":"Wendeburg",
    "sg:phone":"+49 5303/990152",
    "sg:postcode":"38176",
    "sg:province":"Niedersachsen",
    "wof:name":"Hf Bauunternehmung Gmbh",
    "wof:placetype":"venue"
},
  "geometry": {"coordinates":[10.3731012344,52.3271865845],"type":"Point"}
}