{
  "type": "Feature",
  "properties": {
    "iso:country":"DE",
    "sg:address":"Hauptstr. 13",
    "sg:city":"Bopfingen",
    "sg:phone":"+49 7362/7595",
    "sg:postcode":"73441",
    "sg:province":"Baden-W\u00fcrttemberg",
    "wof:name":"H\u00e4gele",
    "wof:placetype":"venue"
},
  "geometry": {"coordinates":[10.3526849747,48.8576507568],"type":"Point"}
}