{
  "type": "Feature",
  "properties": {
    "iso:country":"DE",
    "sg:address":"Heilwigstr. 35",
    "sg:city":"Hamburg",
    "sg:phone":"+49 40/46094450",
    "sg:postcode":"20249",
    "sg:province":"Hamburg",
    "wof:name":"Baroda Grundst\u00fccks- Verwaltung Gmbh",
    "wof:placetype":"venue"
},
  "geometry": {"coordinates":[9.9935407639,53.5840682983],"type":"Point"}
}