{
  "type": "Feature",
  "properties": {
    "iso:country":"DE",
    "sg:address":"Konstantinstr. 4-10",
    "sg:city":"Trier",
    "sg:postcode":"54290",
    "sg:province":"Rheinland-Pfalz",
    "wof:name":"Finower Stahlschutz- Planken Gmbh",
    "wof:placetype":"venue"
},
  "geometry": {"coordinates":[6.6403,49.754559],"type":"Point"}
}