{
  "type": "Feature",
  "properties": {
    "iso:country":"DE",
    "sg:address":"Flemmingen",
    "sg:city":"J\u00fcckelberg",
    "sg:phone":"+49 34497/70015",
    "sg:postcode":"04618",
    "sg:province":"Th\u00fcringen",
    "wof:name":"Tbv Geithain Transporte Bau- Maschinenverleih Gmbh & Co. Kg",
    "wof:placetype":"venue"
},
  "geometry": {"coordinates":[12.621503,50.935963],"type":"Point"}
}