{
  "type": "Feature",
  "properties": {
    "iso:country":"DE",
    "sg:address":"Rohrteichstr. 30",
    "sg:city":"Bielefeld",
    "sg:phone":"+49 4952/162505",
    "sg:postcode":"33602",
    "sg:province":"Nordrhein-Westfalen",
    "wof:name":"D. Rose",
    "wof:placetype":"venue"
},
  "geometry": {"coordinates":[8.5367326736,52.0158309937],"type":"Point"}
}