{
  "type": "Feature",
  "properties": {
    "iso:country":"DE",
    "sg:address":"Im Alten Dorf 3",
    "sg:city":"Dransfeld",
    "sg:phone":"+49 5502/94222",
    "sg:postcode":"37127",
    "sg:province":"Niedersachsen",
    "wof:name":"Ernst Immobilien",
    "wof:placetype":"venue"
},
  "geometry": {"coordinates":[9.7574300766,51.500038147],"type":"Point"}
}