{
  "type": "Feature",
  "properties": {
    "iso:country":"DE",
    "sg:address":"Heideblick 34",
    "sg:city":"Dortmund",
    "sg:phone":"+49 231/731607",
    "sg:postcode":"44229",
    "sg:province":"Nordrhein-Westfalen",
    "wof:name":"Heinz P\u00f6ting Heilpraktiker",
    "wof:placetype":"venue"
},
  "geometry": {"coordinates":[7.4771838188,51.4673881531],"type":"Point"}
}