{
  "type": "Feature",
  "properties": {
    "iso:country":"DE",
    "sg:address":"Industriestr. 6",
    "sg:city":"Satteldorf",
    "sg:phone":"+49 7951/467557",
    "sg:postcode":"74589",
    "sg:province":"Baden-W\u00fcrttemberg",
    "wof:name":"Meco Metallbeschichtung Gmbh",
    "wof:placetype":"venue"
},
  "geometry": {"coordinates":[10.0754346848,49.180141449],"type":"Point"}
}