{
  "type": "Feature",
  "properties": {
    "iso:country":"DE",
    "sg:address":"Im Neuenheimer Feld 234",
    "sg:city":"Heidelberg",
    "sg:phone":"+49 6221/562831",
    "sg:postcode":"69120",
    "sg:province":"Baden-W\u00fcrttemberg",
    "wof:name":"Museum Geologie Pal\u00f6ontologie",
    "wof:placetype":"venue"
},
  "geometry": {"coordinates":[8.674829,49.418575],"type":"Point"}
}