{
  "type": "Feature",
  "properties": {
    "iso:country":"DE",
    "sg:address":"Dingstiege 50",
    "sg:city":"M\u00fcnster",
    "sg:phone":"+49 251/231359",
    "sg:postcode":"48155",
    "sg:province":"Nordrhein-Westfalen",
    "wof:name":"Eberhard Brinkmann",
    "wof:placetype":"venue"
},
  "geometry": {"coordinates":[7.6709799767,51.9793395996],"type":"Point"}
}