{
  "type": "Feature",
  "properties": {
    "iso:country":"DE",
    "sg:address":"Rottalstr. 5",
    "sg:city":"M\u00fcnchen",
    "sg:phone":"+49 89/4313051",
    "sg:postcode":"81673",
    "sg:province":"Bayern",
    "wof:name":"Dr. K. Zwick Steuerberater",
    "wof:placetype":"venue"
},
  "geometry": {"coordinates":[11.6201000214,48.1277122498],"type":"Point"}
}