{
  "type": "Feature",
  "properties": {
    "iso:country":"DE",
    "sg:address":"Steinroder Str. 22",
    "sg:city":"Ebersdorf",
    "sg:phone":"+49 9562/3387",
    "sg:postcode":"96237",
    "sg:province":"Bayern",
    "wof:name":"Motschmann Verwaltungs Gmbh",
    "wof:placetype":"venue"
},
  "geometry": {"coordinates":[11.081436,50.253555],"type":"Point"}
}