{
  "type": "Feature",
  "properties": {
    "iso:country":"DE",
    "sg:address":"Hofgewannstr. 25",
    "sg:city":"Mannheim",
    "sg:phone":"+49 621/783525",
    "sg:postcode":"68307",
    "sg:province":"Baden-W\u00fcrttemberg",
    "wof:name":"Ute Reister Dipl.-\u00dcbersetzerin",
    "wof:placetype":"venue"
},
  "geometry": {"coordinates":[8.4498,49.562099],"type":"Point"}
}