{
  "type": "Feature",
  "properties": {
    "iso:country":"DE",
    "sg:address":"Freckenhorster Str. 18",
    "sg:city":"Warendorf",
    "sg:phone":"+49 2581/3150",
    "sg:postcode":"48231",
    "sg:province":"Nordrhein-Westfalen",
    "wof:name":"M & M Foto Und Ambiente Mlinarzik & Moreno Ohg",
    "wof:placetype":"venue"
},
  "geometry": {"coordinates":[7.9884409904,51.9513244629],"type":"Point"}
}