{
  "type": "Feature",
  "properties": {
    "iso:country":"DE",
    "sg:address":"An den G\u00e4rten 13",
    "sg:city":"Overath",
    "sg:phone":"+49 2206/84224",
    "sg:postcode":"51491",
    "sg:province":"Nordrhein-Westfalen",
    "wof:name":"Marlies Langguth",
    "wof:placetype":"venue"
},
  "geometry": {"coordinates":[7.285907,50.932072],"type":"Point"}
}