{
  "type": "Feature",
  "properties": {
    "iso:country":"DE",
    "sg:address":"Abter\u00f6der Str. 24",
    "sg:city":"Mei\u00dfner",
    "sg:phone":"+49 5657/91200",
    "sg:postcode":"37290",
    "sg:province":"Hessen",
    "wof:name":"Klemke Gmbh",
    "wof:placetype":"venue"
},
  "geometry": {"coordinates":[9.9093847275,51.1986846924],"type":"Point"}
}