{
  "type": "Feature",
  "properties": {
    "iso:country":"DE",
    "sg:address":"Kurt-G\u00fcnther-Str. 2",
    "sg:city":"Leipzig",
    "sg:postcode":"04317",
    "sg:province":"Sachsen",
    "wof:name":"Green Care Sachsen Ges. F\u00fcr Dienstleistungen U. Handel Mit",
    "wof:placetype":"venue"
},
  "geometry": {"coordinates":[12.4053440094,51.3301696777],"type":"Point"}
}