{
  "type": "Feature",
  "properties": {
    "iso:country":"DE",
    "sg:address":"Holzheimer Weg 46-48",
    "sg:city":"Neuss",
    "sg:phone":"+49 2131/44001",
    "sg:postcode":"41464",
    "sg:province":"Nordrhein-Westfalen",
    "wof:name":"Klacer Heimtextilien Gmbh",
    "wof:placetype":"venue"
},
  "geometry": {"coordinates":[6.6859312057,51.1826515198],"type":"Point"}
}