{
  "type": "Feature",
  "properties": {
    "iso:country":"DE",
    "sg:address":"Schellhorner Str. 29",
    "sg:city":"Preetz",
    "sg:phone":"+49 4342/87269",
    "sg:postcode":"24211",
    "sg:province":"Schleswig-Holstein",
    "wof:name":"E. Sonders",
    "wof:placetype":"venue"
},
  "geometry": {"coordinates":[10.2877759933,54.2333641052],"type":"Point"}
}