{
  "type": "Feature",
  "properties": {
    "iso:country":"DE",
    "sg:address":"Cottbuser Str. 20",
    "sg:city":"Forst",
    "sg:phone":"+49 3562/8778",
    "sg:postcode":"03149",
    "sg:province":"Brandenburg",
    "wof:name":"Lehmann",
    "wof:placetype":"venue"
},
  "geometry": {"coordinates":[14.604105,51.690681],"type":"Point"}
}