{
  "type": "Feature",
  "properties": {
    "iso:country":"DE",
    "sg:address":"Kranichstr. 18",
    "sg:city":"Gimbsheim",
    "sg:phone":"+49 6249/4136",
    "sg:postcode":"67578",
    "sg:province":"Rheinland-Pfalz",
    "wof:name":"Armin Schuster",
    "wof:placetype":"venue"
},
  "geometry": {"coordinates":[8.386251,49.780987],"type":"Point"}
}