{
  "type": "Feature",
  "properties": {
    "iso:country":"DE",
    "sg:address":"Hindenburgstr. 3",
    "sg:city":"Sinn",
    "sg:phone":"+49 2772/51511",
    "sg:postcode":"35764",
    "sg:province":"Hessen",
    "wof:name":"Ev. Pfarramt Sinn",
    "wof:placetype":"venue"
},
  "geometry": {"coordinates":[8.3288106918,50.6539382935],"type":"Point"}
}