{
  "type": "Feature",
  "properties": {
    "iso:country":"DE",
    "sg:address":"Dehlinger Weg 24",
    "sg:city":"K\u00f6ln",
    "sg:phone":"+49 221/798986",
    "sg:postcode":"50767",
    "sg:province":"Nordrhein-Westfalen",
    "wof:name":"Heribert Winkel",
    "wof:placetype":"venue"
},
  "geometry": {"coordinates":[6.8879299164,51.0034255981],"type":"Point"}
}