{
  "type": "Feature",
  "properties": {
    "iso:country":"DE",
    "sg:address":"Waldwinkel 2",
    "sg:city":"Nienst\u00e4dt",
    "sg:phone":"+49 5721/3960",
    "sg:postcode":"31688",
    "sg:province":"Niedersachsen",
    "wof:name":"Conzepta Versicherungsmakler E. K.",
    "wof:placetype":"venue"
},
  "geometry": {"coordinates":[9.1558866501,52.311882019],"type":"Point"}
}