{
  "type": "Feature",
  "properties": {
    "iso:country":"DE",
    "sg:address":"Kirchweg 10",
    "sg:city":"Kirchberg i. Wald",
    "sg:postcode":"94259",
    "sg:province":"Bayern",
    "wof:name":"Pulwa Gmbh & Co. Kg",
    "wof:placetype":"venue"
},
  "geometry": {"coordinates":[13.1357593536,48.9067420959],"type":"Point"}
}