{
  "type": "Feature",
  "properties": {
    "iso:country":"DE",
    "sg:address":"Buchholzer Str 55-61",
    "sg:city":"Berlin",
    "sg:phone":"+49 30/40101010",
    "sg:postcode":"13156",
    "sg:province":"Berlin",
    "wof:name":"Iwertec Gmbh",
    "wof:placetype":"venue"
},
  "geometry": {"coordinates":[13.416794,52.590744],"type":"Point"}
}