{
  "type": "Feature",
  "properties": {
    "iso:country":"DE",
    "sg:address":"Vorbecker Landweg 25",
    "sg:city":"Schwaan",
    "sg:phone":"+49 3844/813867",
    "sg:postcode":"18258",
    "sg:province":"Mecklenburg-Vorpommern",
    "wof:name":"Horst Hensel",
    "wof:placetype":"venue"
},
  "geometry": {"coordinates":[12.1013860703,53.9290008545],"type":"Point"}
}