{
  "type": "Feature",
  "properties": {
    "iso:country":"DE",
    "sg:address":"Am Herrenweiher 3",
    "sg:city":"Heideck",
    "sg:phone":"+49 9177/1012",
    "sg:postcode":"91180",
    "sg:province":"Bayern",
    "wof:name":"Karl Beierlein",
    "wof:placetype":"venue"
},
  "geometry": {"coordinates":[11.1324634552,49.1340026855],"type":"Point"}
}