{
  "type": "Feature",
  "properties": {
    "iso:country":"DE",
    "sg:address":"Grasweg 23",
    "sg:city":"Verl",
    "sg:phone":"+49 4952/462169",
    "sg:postcode":"33415",
    "sg:province":"Nordrhein-Westfalen",
    "wof:name":"Elmar Pickert Gmbh",
    "wof:placetype":"venue"
},
  "geometry": {"coordinates":[8.5313310623,51.8795051575],"type":"Point"}
}