{
  "type": "Feature",
  "properties": {
    "iso:country":"DE",
    "sg:address":"Cappelstr. 15",
    "sg:city":"Lippstadt",
    "sg:phone":"+49 2941/3133",
    "sg:postcode":"59555",
    "sg:province":"Nordrhein-Westfalen",
    "wof:name":"Fit-aktiv",
    "wof:placetype":"venue"
},
  "geometry": {"coordinates":[8.3427381516,51.6758079529],"type":"Point"}
}