{
  "type": "Feature",
  "properties": {
    "iso:country":"DE",
    "sg:address":"Am Gewerbering 4",
    "sg:city":"Richtenberg",
    "sg:phone":"+49 38322/5380",
    "sg:postcode":"18461",
    "sg:province":"Mecklenburg-Vorpommern",
    "wof:name":"Rohstoff-recycling Rostock Gmbh & Co Kg",
    "wof:placetype":"venue"
},
  "geometry": {"coordinates":[12.90558815,54.2032432556],"type":"Point"}
}