{
  "type": "Feature",
  "properties": {
    "iso:country":"DE",
    "sg:address":"Sachsenstr. 47",
    "sg:city":"M\u00f6nchengladbach",
    "sg:phone":"+49 2161/208080",
    "sg:postcode":"41063",
    "sg:province":"Nordrhein-Westfalen",
    "wof:name":"Manfred Schulz",
    "wof:placetype":"venue"
},
  "geometry": {"coordinates":[6.4415869713,51.2092971802],"type":"Point"}
}