{
  "type": "Feature",
  "properties": {
    "iso:country":"DE",
    "sg:address":"Feldbrunnenstr. 20",
    "sg:city":"Hamburg",
    "sg:phone":"+49 40/444156",
    "sg:postcode":"20148",
    "sg:province":"Hamburg",
    "wof:name":"J. G\u00fcnther",
    "wof:placetype":"venue"
},
  "geometry": {"coordinates":[9.9911899567,53.565322876],"type":"Point"}
}