{
  "type": "Feature",
  "properties": {
    "iso:country":"DE",
    "sg:address":"Hedwig-Dransfeld-Str. 17",
    "sg:city":"Werl",
    "sg:phone":"+49 2922/4060",
    "sg:postcode":"59457",
    "sg:province":"Nordrhein-Westfalen",
    "wof:name":"Kroll M\u00fchr Und Scheffel Rechtsanw\u00e4lte Und Notare",
    "wof:placetype":"venue"
},
  "geometry": {"coordinates":[7.9179768562,51.553653717],"type":"Point"}
}