{
  "type": "Feature",
  "properties": {
    "iso:country":"DE",
    "sg:address":"B\u00fchrener Kirchweg 20",
    "sg:city":"Cloppenburg",
    "sg:postcode":"49661",
    "sg:province":"Niedersachsen",
    "wof:name":"Rolf Imsieke Antiquit\u00e4ten",
    "wof:placetype":"venue"
},
  "geometry": {"coordinates":[8.032318,52.851826],"type":"Point"}
}