{
  "type": "Feature",
  "properties": {
    "iso:country":"DE",
    "sg:address":"Am Heizkraftwerk 17",
    "sg:city":"Neustrelitz",
    "sg:phone":"+49 3981/443608",
    "sg:postcode":"17235",
    "sg:province":"Mecklenburg-Vorpommern",
    "wof:name":"Kfz-meisterbetrieb Burkhard Gervelis",
    "wof:placetype":"venue"
},
  "geometry": {"coordinates":[13.0855588913,53.3609199524],"type":"Point"}
}