{
  "type": "Feature",
  "properties": {
    "iso:country":"DE",
    "sg:address":"Kantstr. 20",
    "sg:city":"Lehrte",
    "sg:phone":"+49 5175/7578",
    "sg:postcode":"31275",
    "sg:province":"Niedersachsen",
    "wof:name":"Gesellschaft F\u00fcr Betriebs- Und Informationstechnik Mbh",
    "wof:placetype":"venue"
},
  "geometry": {"coordinates":[10.1227817535,52.3690681458],"type":"Point"}
}