{
  "type": "Feature",
  "properties": {
    "iso:country":"DE",
    "sg:address":"Stromstr. 1-2",
    "sg:city":"Berlin",
    "sg:phone":"+49 30/3904930",
    "sg:postcode":"10555",
    "sg:province":"Berlin",
    "wof:name":"Hartung Consult Gmbh",
    "wof:placetype":"venue"
},
  "geometry": {"coordinates":[13.3425388336,52.5237541199],"type":"Point"}
}