{
  "type": "Feature",
  "properties": {
    "iso:country":"DE",
    "sg:address":"Fuhrberger Str. 116",
    "sg:city":"Celle",
    "sg:phone":"+49 5141/47592",
    "sg:postcode":"29225",
    "sg:province":"Niedersachsen",
    "wof:name":"Christiane Und Robert M\u00f6schler",
    "wof:placetype":"venue"
},
  "geometry": {"coordinates":[10.0430803299,52.6137504578],"type":"Point"}
}