{
  "type": "Feature",
  "properties": {
    "iso:country":"DE",
    "sg:address":"Dorfstr. 4",
    "sg:city":"Kr\u00fczen",
    "sg:phone":"+49 4153/4618",
    "sg:postcode":"21483",
    "sg:province":"Schleswig-Holstein",
    "wof:name":"Helmut Brockm\u00fcller",
    "wof:placetype":"venue"
},
  "geometry": {"coordinates":[10.52684,53.398861],"type":"Point"}
}