{
  "type": "Feature",
  "properties": {
    "iso:country":"DE",
    "sg:address":"Kalscheurener Str. 89",
    "sg:city":"H\u00fcrth",
    "sg:phone":"+49 2233/60880",
    "sg:postcode":"50354",
    "sg:province":"Nordrhein-Westfalen",
    "wof:name":"Comeins Computer Und Kommuni- Kations Verwaltungs Gmbh",
    "wof:placetype":"venue"
},
  "geometry": {"coordinates":[6.9066910744,50.8885536194],"type":"Point"}
}