{
  "type": "Feature",
  "properties": {
    "iso:country":"DE",
    "sg:address":"Georgstr. 4",
    "sg:city":"M\u00fclheim",
    "sg:phone":"+49 208/475013",
    "sg:postcode":"45468",
    "sg:province":"Nordrhein-Westfalen",
    "wof:name":"Anonyme Drogenberatungs-st. Arbeiterwohlfahrt",
    "wof:placetype":"venue"
},
  "geometry": {"coordinates":[6.880201,51.432114],"type":"Point"}
}