{
  "type": "Feature",
  "properties": {
    "iso:country":"DE",
    "sg:address":"Harkortstr. 84",
    "sg:city":"Dortmund",
    "sg:phone":"+49 231/779595",
    "sg:postcode":"44225",
    "sg:province":"Nordrhein-Westfalen",
    "wof:name":"Margret Reinecke",
    "wof:placetype":"venue"
},
  "geometry": {"coordinates":[7.436401,51.475468],"type":"Point"}
}