{
  "type": "Feature",
  "properties": {
    "iso:country":"DE",
    "sg:address":"Gerhardstr. 36",
    "sg:city":"Kiel",
    "sg:phone":"+49 431/577044",
    "sg:postcode":"24105",
    "sg:province":"Schleswig-Holstein",
    "wof:name":"P\u00e4diko E. V.",
    "wof:placetype":"venue"
},
  "geometry": {"coordinates":[10.1358299255,54.3345146179],"type":"Point"}
}