{
  "type": "Feature",
  "properties": {
    "iso:country":"DE",
    "sg:address":"Wendlohstr. 37",
    "sg:city":"Hamburg",
    "sg:phone":"+49 40/55584040",
    "sg:postcode":"22459",
    "sg:province":"Hamburg",
    "wof:name":"H + S Heizungsbau Gmbh",
    "wof:placetype":"venue"
},
  "geometry": {"coordinates":[9.946958,53.625313],"type":"Point"}
}