{
  "type": "Feature",
  "properties": {
    "iso:country":"DE",
    "sg:address":"Kathendorfer Str. 2",
    "sg:city":"R\u00e4tzlingen",
    "sg:postcode":"39359",
    "sg:province":"Sachsen-Anhalt",
    "wof:name":"Gifhorn-heicke Verwaltungs Gmbh",
    "wof:placetype":"venue"
},
  "geometry": {"coordinates":[11.115369,52.401218],"type":"Point"}
}