{
  "type": "Feature",
  "properties": {
    "iso:country":"DE",
    "sg:address":"Heidh\u00f6rner Weg 2",
    "sg:city":"Friedeburg",
    "sg:phone":"+49 4465/675",
    "sg:postcode":"26446",
    "sg:province":"Niedersachsen",
    "wof:name":"Hermann Peeks",
    "wof:placetype":"venue"
},
  "geometry": {"coordinates":[7.820568,53.470119],"type":"Point"}
}