{
  "type": "Feature",
  "properties": {
    "iso:country":"DE",
    "sg:address":"Freiherr-vom-Stein-Str. 7 a",
    "sg:city":"Reken",
    "sg:phone":"+49 2864/94210",
    "sg:postcode":"48734",
    "sg:province":"Nordrhein-Westfalen",
    "wof:name":"Cavaletti Barbara Jost-besten",
    "wof:placetype":"venue"
},
  "geometry": {"coordinates":[7.042908,51.796913],"type":"Point"}
}