{
  "type": "Feature",
  "properties": {
    "iso:country":"DE",
    "sg:address":"Gutenbergstr. 108",
    "sg:city":"Schw\u00e4bisch Gm\u00fcnd",
    "sg:phone":"+49 7171/68395",
    "sg:postcode":"73525",
    "sg:province":"Baden-W\u00fcrttemberg",
    "wof:name":"Michael Roll Heissmangel",
    "wof:placetype":"venue"
},
  "geometry": {"coordinates":[9.8106269836,48.7916297913],"type":"Point"}
}