{
  "type": "Feature",
  "properties": {
    "iso:country":"DE",
    "sg:address":"Ferdinand-Rei\u00df-Str. 5",
    "sg:city":"Hausach",
    "sg:postcode":"77756",
    "sg:province":"Baden-W\u00fcrttemberg",
    "wof:name":"Hausacher W\u00e4rmelieferung Verwaltungsgesellschaft Mbh",
    "wof:placetype":"venue"
},
  "geometry": {"coordinates":[8.1429834366,48.2821083069],"type":"Point"}
}