{
  "type": "Feature",
  "properties": {
    "iso:country":"DE",
    "sg:address":"Obergasse 44",
    "sg:city":"Lauterbach",
    "sg:phone":"+49 6641/18462",
    "sg:postcode":"36341",
    "sg:province":"Hessen",
    "wof:name":"Hohhausbibliothek Vereinsbibliothek Des",
    "wof:placetype":"venue"
},
  "geometry": {"coordinates":[9.394111,50.637375],"type":"Point"}
}