{
  "type": "Feature",
  "properties": {
    "iso:country":"DE",
    "sg:address":"Lindenstr. 43",
    "sg:city":"Koblenz",
    "sg:phone":"+49 261/41213",
    "sg:postcode":"56073",
    "sg:province":"Rheinland-Pfalz",
    "wof:name":"K. Rosenbaum Grabdenkm\u00e4ler",
    "wof:placetype":"venue"
},
  "geometry": {"coordinates":[7.5830430984,50.3527908325],"type":"Point"}
}