{
  "type": "Feature",
  "properties": {
    "iso:country":"DE",
    "sg:address":"Vahrenwalder Str. 7",
    "sg:city":"Hannover",
    "sg:postcode":"30165",
    "sg:province":"Niedersachsen",
    "wof:name":"Comte-moderne Analysesysteme Gmbh",
    "wof:placetype":"venue"
},
  "geometry": {"coordinates":[9.733651,52.38628],"type":"Point"}
}