{
  "type": "Feature",
  "properties": {
    "iso:country":"DE",
    "sg:address":"Philipp-Rosenthal-Str. 15",
    "sg:city":"Leipzig",
    "sg:phone":"+49 341/9612960",
    "sg:postcode":"04103",
    "sg:province":"Sachsen",
    "wof:name":"Anneliese Bredow",
    "wof:placetype":"venue"
},
  "geometry": {"coordinates":[12.384815,51.329449],"type":"Point"}
}