{
  "type": "Feature",
  "properties": {
    "iso:country":"DE",
    "sg:address":"F\u00e4hrstr. 12",
    "sg:city":"Eisenh\u00fcttenstadt",
    "sg:phone":"+49 3364/43396",
    "sg:postcode":"15890",
    "sg:province":"Brandenburg",
    "wof:name":"Fotopoint Im Kaufland",
    "wof:placetype":"venue"
},
  "geometry": {"coordinates":[14.6469011307,52.1433944702],"type":"Point"}
}