{
  "type": "Feature",
  "properties": {
    "iso:country":"DE",
    "sg:address":"Dorfstr. 17",
    "sg:city":"Hohenwart",
    "sg:phone":"+49 8446/246",
    "sg:postcode":"86558",
    "sg:province":"Bayern",
    "wof:name":"Katholisches Pfarramt St. Anna",
    "wof:placetype":"venue"
},
  "geometry": {"coordinates":[11.4256696701,48.6008453369],"type":"Point"}
}