{
  "type": "Feature",
  "properties": {
    "iso:country":"DE",
    "sg:address":"R\u00f6llbacher Str. 27",
    "sg:city":"Gro\u00dfheubach",
    "sg:phone":"+49 9371/2716",
    "sg:postcode":"63920",
    "sg:province":"Bayern",
    "wof:name":"Hilmar Oettinger",
    "wof:placetype":"venue"
},
  "geometry": {"coordinates":[9.224138,49.729481],"type":"Point"}
}