{
  "type": "Feature",
  "properties": {
    "iso:country":"DE",
    "sg:address":"Heinrich-Buff-Ring 58",
    "sg:city":"Gie\u00dfen",
    "sg:phone":"+49 641/7023007",
    "sg:postcode":"35392",
    "sg:province":"Hessen",
    "wof:name":"Ludwig-schunk-bibliothek Fb Humanmedizin Stiftungsbibl.",
    "wof:placetype":"venue"
},
  "geometry": {"coordinates":[8.672467,50.571808],"type":"Point"}
}