{
  "type": "Feature",
  "properties": {
    "iso:country":"DE",
    "sg:address":"Steigerwaldstr. 17",
    "sg:city":"Herrenberg",
    "sg:phone":"+49 7032/3077",
    "sg:postcode":"71083",
    "sg:province":"Baden-W\u00fcrttemberg",
    "wof:name":"Arno Burkart Elektronenstrahltechnik Gmbh",
    "wof:placetype":"venue"
},
  "geometry": {"coordinates":[8.8449373245,48.6122016907],"type":"Point"}
}