{
  "type": "Feature",
  "properties": {
    "iso:country":"DE",
    "sg:address":"F\u00e4rberstr. 11",
    "sg:city":"N\u00fcrnberg",
    "sg:phone":"+49 911/208151",
    "sg:postcode":"90402",
    "sg:province":"Bayern",
    "wof:name":"Zoo Schell-bunte Tierwelt Gmbh",
    "wof:placetype":"venue"
},
  "geometry": {"coordinates":[11.072904,49.449585],"type":"Point"}
}