{
  "type": "Feature",
  "properties": {
    "iso:country":"DE",
    "sg:address":"Sch\u00f6nfeldstr. 13",
    "sg:city":"M\u00fcnchen",
    "sg:phone":"+49 89/1292997",
    "sg:postcode":"80539",
    "sg:province":"Bayern",
    "wof:name":"Siegfried Demmel Rechtsanwalt",
    "wof:placetype":"venue"
},
  "geometry": {"coordinates":[11.582324028,48.1457901001],"type":"Point"}
}