{
  "type": "Feature",
  "properties": {
    "iso:country":"DE",
    "sg:address":"Gymnasiumstr. 4",
    "sg:city":"Mainz",
    "sg:phone":"+49 6131/232977",
    "sg:postcode":"55116",
    "sg:province":"Rheinland-Pfalz",
    "wof:name":"Tabotex",
    "wof:placetype":"venue"
},
  "geometry": {"coordinates":[8.2692251205,49.9992103577],"type":"Point"}
}