{
  "type": "Feature",
  "properties": {
    "iso:country":"DE",
    "sg:address":"Kirchweg 2 a",
    "sg:city":"Hagnau",
    "sg:phone":"+49 7532/6261",
    "sg:postcode":"88709",
    "sg:province":"Baden-W\u00fcrttemberg",
    "wof:name":"Hotel Scharfes Eck",
    "wof:placetype":"venue"
},
  "geometry": {"coordinates":[9.3192977905,47.6749420166],"type":"Point"}
}