{
  "type": "Feature",
  "properties": {
    "iso:country":"DE",
    "sg:address":"Steingassen 2",
    "sg:city":"Isen",
    "sg:phone":"+49 8083/53110",
    "sg:postcode":"84424",
    "sg:province":"Bayern",
    "wof:name":"Martin Angermaier Gmbh",
    "wof:placetype":"venue"
},
  "geometry": {"coordinates":[12.05022,48.229286],"type":"Point"}
}