{
  "type": "Feature",
  "properties": {
    "iso:country":"DE",
    "sg:address":"Hauptstr. 39",
    "sg:city":"Sche\u00dflitz",
    "sg:phone":"+49 9542/1564",
    "sg:postcode":"96110",
    "sg:province":"Bayern",
    "wof:name":"Ludwig Lindner",
    "wof:placetype":"venue"
},
  "geometry": {"coordinates":[11.033651,49.976437],"type":"Point"}
}