{
  "type": "Feature",
  "properties": {
    "iso:country":"DE",
    "sg:address":"K\u00f6hler Str 41",
    "sg:city":"Dorsten",
    "sg:phone":"+49 2369/1075",
    "sg:postcode":"46286",
    "sg:province":"Nordrhein-Westfalen",
    "wof:name":"Abf\u00fcllanlagenbau Pwa Gmbh",
    "wof:placetype":"venue"
},
  "geometry": {"coordinates":[7.004294,51.711376],"type":"Point"}
}