{
  "type": "Feature",
  "properties": {
    "iso:country":"DE",
    "sg:address":"Ulrichstr. 43",
    "sg:city":"Albstadt",
    "sg:phone":"+49 4974/312441",
    "sg:postcode":"72458",
    "sg:province":"Baden-W\u00fcrttemberg",
    "wof:name":"Helga Diebold",
    "wof:placetype":"venue"
},
  "geometry": {"coordinates":[9.0189580917,48.2142410278],"type":"Point"}
}