{
  "type": "Feature",
  "properties": {
    "iso:country":"DE",
    "sg:address":"Nistertalstr. 25",
    "sg:city":"Bad Marienberg",
    "sg:phone":"+49 2661/8648",
    "sg:postcode":"56470",
    "sg:province":"Rheinland-Pfalz",
    "wof:name":"Albert Kempf",
    "wof:placetype":"venue"
},
  "geometry": {"coordinates":[7.947057,50.640099],"type":"Point"}
}