{
  "type": "Feature",
  "properties": {
    "iso:country":"DE",
    "sg:address":"Oberrarbach 1",
    "sg:city":"Schmallenberg",
    "sg:phone":"+49 2971/87808",
    "sg:postcode":"57392",
    "sg:province":"Nordrhein-Westfalen",
    "wof:name":"Franz Gierse",
    "wof:placetype":"venue"
},
  "geometry": {"coordinates":[8.322368,51.229256],"type":"Point"}
}