{
  "type": "Feature",
  "properties": {
    "iso:country":"DE",
    "sg:address":"Schiefersteinstr. 16",
    "sg:city":"Wiesbaden",
    "sg:phone":"+49 611/428837",
    "sg:postcode":"65199",
    "sg:province":"Hessen",
    "wof:name":"Klaus Und Andreas Wichmann Malerbetrieb Gmbh",
    "wof:placetype":"venue"
},
  "geometry": {"coordinates":[8.206344,50.066597],"type":"Point"}
}