{
  "type": "Feature",
  "properties": {
    "iso:country":"DE",
    "sg:address":"Elisabethenstr. 8",
    "sg:city":"Landau",
    "sg:phone":"+49 6341/62362",
    "sg:postcode":"76829",
    "sg:province":"Rheinland-Pfalz",
    "wof:name":"O. Winck",
    "wof:placetype":"venue"
},
  "geometry": {"coordinates":[8.0712747574,49.2117576599],"type":"Point"}
}