{
  "type": "Feature",
  "properties": {
    "iso:country":"DE",
    "sg:address":"Wetterkreuz 7",
    "sg:city":"Erlangen",
    "sg:phone":"+49 9131/6080",
    "sg:postcode":"91058",
    "sg:province":"Bayern",
    "wof:name":"Hotel Transmar",
    "wof:placetype":"venue"
},
  "geometry": {"coordinates":[11.0287380219,49.5442428589],"type":"Point"}
}