{
  "type": "Feature",
  "properties": {
    "iso:country":"DE",
    "sg:address":"Bubenheimer Weg 23",
    "sg:city":"Koblenz",
    "sg:phone":"+49 261/2046",
    "sg:postcode":"56072",
    "sg:province":"Rheinland-Pfalz",
    "wof:name":"G\u00f6rlitz Verlags Gmbh",
    "wof:placetype":"venue"
},
  "geometry": {"coordinates":[7.5718989372,50.370880127],"type":"Point"}
}