{
  "type": "Feature",
  "properties": {
    "iso:country":"DE",
    "sg:address":"Oschatzer Str. 5",
    "sg:city":"Dresden",
    "sg:phone":"+49 351/51384",
    "sg:postcode":"01127",
    "sg:province":"Sachsen",
    "wof:name":"Heike Schwarz",
    "wof:placetype":"venue"
},
  "geometry": {"coordinates":[13.72313,51.075172],"type":"Point"}
}