{
  "type": "Feature",
  "properties": {
    "iso:country":"DE",
    "sg:address":"Laventiestr. 10",
    "sg:city":"Iserlohn",
    "sg:phone":"+49 2371/40009",
    "sg:postcode":"58640",
    "sg:province":"Nordrhein-Westfalen",
    "wof:name":"Hermann Niehaves",
    "wof:placetype":"venue"
},
  "geometry": {"coordinates":[7.713047,51.419159],"type":"Point"}
}