{
  "type": "Feature",
  "properties": {
    "iso:country":"DE",
    "sg:address":"Erwin-Seiz-Str. 10",
    "sg:city":"Reutlingen",
    "sg:phone":"+49 4923/7360271",
    "sg:postcode":"72764",
    "sg:province":"Baden-W\u00fcrttemberg",
    "wof:name":"Hermes Fahrzeugbau Ohg",
    "wof:placetype":"venue"
},
  "geometry": {"coordinates":[7.7594752312,51.4383506775],"type":"Point"}
}