{
  "type": "Feature",
  "properties": {
    "iso:country":"DE",
    "sg:address":"Heidhauser Str. 52",
    "sg:city":"Essen",
    "sg:phone":"+49 201/403310",
    "sg:postcode":"45239",
    "sg:province":"Nordrhein-Westfalen",
    "wof:name":"Ingrid Wilke Masseurin",
    "wof:placetype":"venue"
},
  "geometry": {"coordinates":[7.025753,51.385872],"type":"Point"}
}