{
  "type": "Feature",
  "properties": {
    "iso:country":"DE",
    "sg:address":"Ostlandweg 3",
    "sg:city":"Burgkirchen",
    "sg:phone":"+49 8679/6886",
    "sg:postcode":"84508",
    "sg:province":"Bayern",
    "wof:name":"Josef Schmid",
    "wof:placetype":"venue"
},
  "geometry": {"coordinates":[12.6588096619,48.151096344],"type":"Point"}
}