{
  "type": "Feature",
  "properties": {
    "iso:country":"DE",
    "sg:address":"Altenessener Str. 194",
    "sg:city":"Essen",
    "sg:phone":"+49 201/311130",
    "sg:postcode":"45326",
    "sg:province":"Nordrhein-Westfalen",
    "wof:name":"Haus Stachels",
    "wof:placetype":"venue"
},
  "geometry": {"coordinates":[7.0097279549,51.4823608398],"type":"Point"}
}