{
  "type": "Feature",
  "properties": {
    "iso:country":"DE",
    "sg:address":"Arend-Smid-Str. 14",
    "sg:city":"Leer",
    "sg:phone":"+49 491/62087",
    "sg:postcode":"26789",
    "sg:province":"Niedersachsen",
    "wof:name":"Hasso Herrmuth Rechtsanwalt Und Notar",
    "wof:placetype":"venue"
},
  "geometry": {"coordinates":[7.4571118355,53.2346916199],"type":"Point"}
}