{
  "type": "Feature",
  "properties": {
    "iso:country":"DE",
    "sg:address":"Hanns-Martin-Schleyer-Str. 2",
    "sg:city":"Offenburg",
    "sg:postcode":"77656",
    "sg:province":"Baden-W\u00fcrttemberg",
    "wof:name":"Tk-log Tiefk\u00fchllogistik Gmbh",
    "wof:placetype":"venue"
},
  "geometry": {"coordinates":[7.9209461212,48.4821662903],"type":"Point"}
}