{
  "type": "Feature",
  "properties": {
    "iso:country":"DE",
    "sg:address":"Dorfstr. 8",
    "sg:city":"Langwedel",
    "sg:phone":"+49 4235/957550",
    "sg:postcode":"27299",
    "sg:province":"Niedersachsen",
    "wof:name":"Karl-heinz Biene",
    "wof:placetype":"venue"
},
  "geometry": {"coordinates":[9.115188,52.994282],"type":"Point"}
}