{
  "type": "Feature",
  "properties": {
    "iso:country":"DE",
    "sg:address":"Geldernsche Str. 64",
    "sg:city":"Krefeld",
    "sg:phone":"+49 2151/601604",
    "sg:postcode":"47798",
    "sg:province":"Nordrhein-Westfalen",
    "wof:name":"Starfoto Hans Koenen",
    "wof:placetype":"venue"
},
  "geometry": {"coordinates":[6.5569958687,51.339225769],"type":"Point"}
}