{
  "type": "Feature",
  "properties": {
    "iso:country":"DE",
    "sg:address":"Adlerstr. 34",
    "sg:city":"Essen",
    "sg:phone":"+49 201/553544",
    "sg:postcode":"45307",
    "sg:province":"Nordrhein-Westfalen",
    "wof:name":"Elektro Segro Gmbh",
    "wof:placetype":"venue"
},
  "geometry": {"coordinates":[7.1040959358,51.4648017883],"type":"Point"}
}