{
  "type": "Feature",
  "properties": {
    "iso:country":"DE",
    "sg:address":"Eschenweg 16",
    "sg:city":"Osterholz-Scharmbeck",
    "sg:phone":"+49 4795/95147",
    "sg:postcode":"27711",
    "sg:province":"Niedersachsen",
    "wof:name":"Telefonbau Lehmann Fernmeldeanlagenbau",
    "wof:placetype":"venue"
},
  "geometry": {"coordinates":[8.7225542068,53.2722930908],"type":"Point"}
}