{
  "type": "Feature",
  "properties": {
    "iso:country":"DE",
    "sg:address":"Karl-Liebknecht-Str. 62",
    "sg:city":"Gumtow",
    "sg:phone":"+49 33977/50910",
    "sg:postcode":"16866",
    "sg:province":"Brandenburg",
    "wof:name":"H.-p. Dittrich",
    "wof:placetype":"venue"
},
  "geometry": {"coordinates":[12.2580833435,52.9829597473],"type":"Point"}
}