{
  "type": "Feature",
  "properties": {
    "iso:country":"DE",
    "sg:address":"Hof 22",
    "sg:city":"M\u00fcnstertal",
    "sg:phone":"+49 7636/355",
    "sg:postcode":"79244",
    "sg:province":"Baden-W\u00fcrttemberg",
    "wof:name":"Bernhard Schweitzer",
    "wof:placetype":"venue"
},
  "geometry": {"coordinates":[7.7685332298,47.8569908142],"type":"Point"}
}