{
  "type": "Feature",
  "properties": {
    "iso:country":"DE",
    "sg:address":"Rheinwaldstr. 10",
    "sg:city":"Rottweil",
    "sg:phone":"+49 741/18800",
    "sg:postcode":"78628",
    "sg:province":"Baden-W\u00fcrttemberg",
    "wof:name":"K\u00fcchen Art",
    "wof:placetype":"venue"
},
  "geometry": {"coordinates":[8.6415586472,48.1454277039],"type":"Point"}
}