{
  "type": "Feature",
  "properties": {
    "iso:country":"DE",
    "sg:address":"Walld\u00fcrner Str. 2",
    "sg:city":"Buchen",
    "sg:phone":"+49 6281/2356",
    "sg:postcode":"74722",
    "sg:province":"Baden-W\u00fcrttemberg",
    "wof:name":"Sozialberatungsstelle Caritasverband F. D.",
    "wof:placetype":"venue"
},
  "geometry": {"coordinates":[9.321879,49.522869],"type":"Point"}
}