{
  "type": "Feature",
  "properties": {
    "iso:country":"DE",
    "sg:address":"Harthaer Str. 50",
    "sg:city":"Dorfhain",
    "sg:phone":"+49 35055/61301",
    "sg:postcode":"01738",
    "sg:province":"Sachsen",
    "wof:name":"Helfried Tittel",
    "wof:placetype":"venue"
},
  "geometry": {"coordinates":[13.5548,50.937527],"type":"Point"}
}