{
  "type": "Feature",
  "properties": {
    "iso:country":"DE",
    "sg:address":"F\u00f6hrenweg 13",
    "sg:city":"Blomberg",
    "sg:phone":"+49 5235/8053",
    "sg:postcode":"32825",
    "sg:province":"Nordrhein-Westfalen",
    "wof:name":"Wilhelm Henjes",
    "wof:placetype":"venue"
},
  "geometry": {"coordinates":[9.10469,51.955181],"type":"Point"}
}