{
  "type": "Feature",
  "properties": {
    "iso:country":"DE",
    "sg:address":"Westheide 56",
    "sg:city":"Dortmund",
    "sg:phone":"+49 231/332224",
    "sg:postcode":"44357",
    "sg:province":"Nordrhein-Westfalen",
    "wof:name":"Thomas R\u00fctershoff",
    "wof:placetype":"venue"
},
  "geometry": {"coordinates":[7.3515300751,51.5632019043],"type":"Point"}
}