{
  "type": "Feature",
  "properties": {
    "iso:country":"DE",
    "sg:address":"Vorster Str. 94",
    "sg:city":"Kempen",
    "sg:phone":"+49 2152/2321",
    "sg:postcode":"47906",
    "sg:province":"Nordrhein-Westfalen",
    "wof:name":"Heinz Sch\u00fcrmann",
    "wof:placetype":"venue"
},
  "geometry": {"coordinates":[6.422094,51.355717],"type":"Point"}
}