{
  "type": "Feature",
  "properties": {
    "iso:country":"DE",
    "sg:address":"D\u00fcsseldorfer Str. 18",
    "sg:city":"Frankfurt",
    "sg:phone":"+49 4969/252089",
    "sg:postcode":"60329",
    "sg:province":"Hessen",
    "wof:name":"Berlinski Kg",
    "wof:placetype":"venue"
},
  "geometry": {"coordinates":[8.661681,50.109241],"type":"Point"}
}