{
  "type": "Feature",
  "properties": {
    "iso:country":"DE",
    "sg:address":"Am Steinacker 17",
    "sg:city":"Ganderkesee",
    "sg:phone":"+49 4222/93190",
    "sg:postcode":"27777",
    "sg:province":"Niedersachsen",
    "wof:name":"Cpu-ingenieur Gmbh",
    "wof:placetype":"venue"
},
  "geometry": {"coordinates":[8.538259,53.037376],"type":"Point"}
}