{
  "type": "Feature",
  "properties": {
    "iso:country":"DE",
    "sg:address":"Dobritzer Str. 55",
    "sg:city":"Zerbst",
    "sg:phone":"+49 4939/2362931",
    "sg:postcode":"39261",
    "sg:province":"Sachsen-Anhalt",
    "wof:name":"Pension Am Stadtrand",
    "wof:placetype":"venue"
},
  "geometry": {"coordinates":[12.098324,51.976089],"type":"Point"}
}