{
  "type": "Feature",
  "properties": {
    "iso:country":"DE",
    "sg:address":"H\u00fclchrather Str. 21",
    "sg:city":"D\u00fcsseldorf",
    "sg:phone":"+49 211/151074",
    "sg:postcode":"40221",
    "sg:province":"Nordrhein-Westfalen",
    "wof:name":"P.-j. Nicolin",
    "wof:placetype":"venue"
},
  "geometry": {"coordinates":[6.762307,51.196213],"type":"Point"}
}