{
  "type": "Feature",
  "properties": {
    "iso:country":"DE",
    "sg:address":"Cecilienstr. 8",
    "sg:city":"Siegburg",
    "sg:phone":"+49 2241/59620",
    "sg:postcode":"53721",
    "sg:province":"Nordrhein-Westfalen",
    "wof:name":"Inhausen Gmbh",
    "wof:placetype":"venue"
},
  "geometry": {"coordinates":[7.208554,50.79974],"type":"Point"}
}