{
  "type": "Feature",
  "properties": {
    "iso:country":"DE",
    "sg:address":"Talstr. 4",
    "sg:city":"Castrop-Rauxel",
    "sg:phone":"+49 2305/24896",
    "sg:postcode":"44577",
    "sg:province":"Nordrhein-Westfalen",
    "wof:name":"Egon May",
    "wof:placetype":"venue"
},
  "geometry": {"coordinates":[7.349888,51.557228],"type":"Point"}
}