{
  "type": "Feature",
  "properties": {
    "iso:country":"DE",
    "sg:address":"Kronenstr. 22",
    "sg:city":"Stuttgart",
    "sg:phone":"+49 711/2236851",
    "sg:postcode":"70173",
    "sg:province":"Baden-W\u00fcrttemberg",
    "wof:name":"Ronzino-cafe-bar Gmbh",
    "wof:placetype":"venue"
},
  "geometry": {"coordinates":[9.178432,48.782715],"type":"Point"}
}