{
  "type": "Feature",
  "properties": {
    "iso:country":"DE",
    "sg:address":"Zweifaller Str. 120",
    "sg:city":"Stolberg",
    "sg:postcode":"52224",
    "sg:province":"Nordrhein-Westfalen",
    "wof:name":"Win Cosmetic Verwaltungsges. Mbh",
    "wof:placetype":"venue"
},
  "geometry": {"coordinates":[6.2831101418,50.7368087769],"type":"Point"}
}