{
  "type": "Feature",
  "properties": {
    "iso:country":"DE",
    "sg:address":"Stedinger Str. 183",
    "sg:city":"Delmenhorst",
    "sg:phone":"+49 7151/910810",
    "sg:postcode":"27753",
    "sg:province":"Niedersachsen",
    "wof:name":"Gerhard Mogck Gmbh",
    "wof:placetype":"venue"
},
  "geometry": {"coordinates":[9.3219661713,48.8125267029],"type":"Point"}
}