{
  "type": "Feature",
  "properties": {
    "iso:country":"DE",
    "sg:address":"Mundsburger Damm 8",
    "sg:city":"Hamburg",
    "sg:postcode":"22087",
    "sg:province":"Hamburg",
    "wof:name":"Mbw Communication Network Gmbh",
    "wof:placetype":"venue"
},
  "geometry": {"coordinates":[10.0184793472,53.5645523071],"type":"Point"}
}