{
  "type": "Feature",
  "properties": {
    "iso:country":"DE",
    "sg:address":"Hauptstr. 75",
    "sg:city":"Weilerbach",
    "sg:phone":"+49 4963/7491320",
    "sg:postcode":"67685",
    "sg:province":"Rheinland-Pfalz",
    "wof:name":"Sch\u00c4fer-drehteile Gmbh",
    "wof:placetype":"venue"
},
  "geometry": {"coordinates":[7.63748,49.477943],"type":"Point"}
}