{
  "type": "Feature",
  "properties": {
    "iso:country":"DE",
    "sg:address":"Sonnenstr 3",
    "sg:city":"Simmerath",
    "sg:phone":"+49 2473/939210",
    "sg:postcode":"52152",
    "sg:province":"Nordrhein-Westfalen",
    "wof:name":"Wkl Gmbh",
    "wof:placetype":"venue"
},
  "geometry": {"coordinates":[6.3366618156,50.6262207031],"type":"Point"}
}