{
  "type": "Feature",
  "properties": {
    "iso:country":"DE",
    "sg:address":"Am Kirchberg 41",
    "sg:city":"Karlsruhe",
    "sg:phone":"+49 721/468791",
    "sg:postcode":"76229",
    "sg:province":"Baden-W\u00fcrttemberg",
    "wof:name":"Gmf Gesellschaft F\u00fcr Me\u00df- Und Filtertechnik Mbh",
    "wof:placetype":"venue"
},
  "geometry": {"coordinates":[8.501148,49.001488],"type":"Point"}
}