{
  "type": "Feature",
  "properties": {
    "iso:country":"DE",
    "sg:address":"Untere Staufenbergstr. 12",
    "sg:city":"Bonstetten",
    "sg:phone":"+49 8293/262",
    "sg:postcode":"86486",
    "sg:province":"Bayern",
    "wof:name":"Raiffeisenbank Welden Und Umgb. Eg",
    "wof:placetype":"venue"
},
  "geometry": {"coordinates":[10.705143,48.438705],"type":"Point"}
}