{
  "type": "Feature",
  "properties": {
    "iso:country":"DE",
    "sg:address":"Hans-Bredow-Str. 10",
    "sg:city":"Bremen",
    "sg:phone":"+49 421/2462211",
    "sg:postcode":"28307",
    "sg:province":"Bremen",
    "wof:name":"Radio Bremen Werbung Gmbh",
    "wof:placetype":"venue"
},
  "geometry": {"coordinates":[8.963636,53.05669],"type":"Point"}
}