{
  "type": "Feature",
  "properties": {
    "iso:country":"DE",
    "sg:address":"Antoniusweg 16",
    "sg:city":"Schelklingen",
    "sg:phone":"+49 7394/619",
    "sg:postcode":"89601",
    "sg:province":"Baden-W\u00fcrttemberg",
    "wof:name":"Anton Sailer",
    "wof:placetype":"venue"
},
  "geometry": {"coordinates":[9.7394886017,48.3785324097],"type":"Point"}
}