{
  "type": "Feature",
  "properties": {
    "iso:country":"DE",
    "sg:address":"Dorfstr. 20",
    "sg:city":"Z\u00f6llnitz",
    "sg:phone":"+49 3641/394375",
    "sg:postcode":"07751",
    "sg:province":"Th\u00fcringen",
    "wof:name":"Mario H\u00e4drich",
    "wof:placetype":"venue"
},
  "geometry": {"coordinates":[11.643595,50.869183],"type":"Point"}
}