{
  "type": "Feature",
  "properties": {
    "iso:country":"DE",
    "sg:address":"Ahorn\u00f6d",
    "sg:city":"Freyung",
    "sg:phone":"+49 8551/1572",
    "sg:postcode":"94078",
    "sg:province":"Bayern",
    "wof:name":"W. Manzenberger",
    "wof:placetype":"venue"
},
  "geometry": {"coordinates":[13.5332250595,48.821105957],"type":"Point"}
}