{
  "type": "Feature",
  "properties": {
    "iso:country":"DE",
    "sg:address":"Greifswalder Str. 64",
    "sg:city":"Hamburg",
    "sg:phone":"+49 40/240082",
    "sg:postcode":"20099",
    "sg:province":"Hamburg",
    "wof:name":"R. Frank",
    "wof:placetype":"venue"
},
  "geometry": {"coordinates":[10.0120592117,53.5572166443],"type":"Point"}
}