{
  "type": "Feature",
  "properties": {
    "iso:country":"DE",
    "sg:address":"Gr\u00fcnw\u00e4lderstr. 23",
    "sg:city":"Freiburg",
    "sg:postcode":"79098",
    "sg:province":"Baden-W\u00fcrttemberg",
    "wof:name":"Burger King Freiburg Philipp Eiermann",
    "wof:placetype":"venue"
},
  "geometry": {"coordinates":[7.8518509865,47.9940567017],"type":"Point"}
}