{
  "type": "Feature",
  "properties": {
    "iso:country":"DE",
    "sg:address":"Anton-Weck-Str. 4-6",
    "sg:city":"Dresden",
    "sg:postcode":"01159",
    "sg:province":"Sachsen",
    "wof:name":"Fronius Munk Schwei\u00dftechnik Gmbh",
    "wof:placetype":"venue"
},
  "geometry": {"coordinates":[13.703081131,51.0411911011],"type":"Point"}
}