{
  "type": "Feature",
  "properties": {
    "iso:country":"DE",
    "sg:address":"Marktstr. 14",
    "sg:city":"M\u00f6nchengladbach",
    "sg:phone":"+49 2166/613502",
    "sg:postcode":"41236",
    "sg:province":"Nordrhein-Westfalen",
    "wof:name":"Christiane John",
    "wof:placetype":"venue"
},
  "geometry": {"coordinates":[6.4447,51.166828],"type":"Point"}
}