{
  "type": "Feature",
  "properties": {
    "iso:country":"DE",
    "sg:address":"Arnulfstr. 60",
    "sg:city":"M\u00fcnchen",
    "sg:postcode":"80335",
    "sg:province":"Bayern",
    "wof:name":"Gesellschaft Zur Erforschung Der Postgeschichte E. V.",
    "wof:placetype":"venue"
},
  "geometry": {"coordinates":[11.5492486954,48.143661499],"type":"Point"}
}