{
  "type": "Feature",
  "properties": {
    "iso:country":"DE",
    "sg:address":"Stuttgarter Str. 204",
    "sg:city":"Kirchheim",
    "sg:phone":"+49 7021/42750",
    "sg:postcode":"73230",
    "sg:province":"Baden-W\u00fcrttemberg",
    "wof:name":"Werner Frik",
    "wof:placetype":"venue"
},
  "geometry": {"coordinates":[9.4210863113,48.6575317383],"type":"Point"}
}