{
  "type": "Feature",
  "properties": {
    "iso:country":"DE",
    "sg:address":"Stollbergstr 6",
    "sg:city":"M\u00fcnchen",
    "sg:phone":"+49 89/223351",
    "sg:postcode":"80539",
    "sg:province":"Bayern",
    "wof:name":"Perma Consultants Personal & Management Beratung Gmbh",
    "wof:placetype":"venue"
},
  "geometry": {"coordinates":[11.5833454132,48.1365127563],"type":"Point"}
}