{
  "type": "Feature",
  "properties": {
    "iso:country":"DE",
    "sg:address":"Brandenburgische Str. 38",
    "sg:city":"Berlin",
    "sg:postcode":"10707",
    "sg:province":"Berlin",
    "wof:name":"Mendelson-e-commerce Gmbh",
    "wof:placetype":"venue"
},
  "geometry": {"coordinates":[13.3073139191,52.4979133606],"type":"Point"}
}