{
  "type": "Feature",
  "properties": {
    "iso:country":"DE",
    "sg:address":"Adolfstr. 28",
    "sg:city":"Bad Schwalbach",
    "sg:phone":"+49 6124/2298",
    "sg:postcode":"65307",
    "sg:province":"Hessen",
    "wof:name":"Hamm Bestattungen Gmbh",
    "wof:placetype":"venue"
},
  "geometry": {"coordinates":[8.070705,50.140846],"type":"Point"}
}