{
  "type": "Feature",
  "properties": {
    "iso:country":"DE",
    "sg:address":"Vogelsang 47 a",
    "sg:city":"Steinfurt",
    "sg:phone":"+49 2551/81484",
    "sg:postcode":"48565",
    "sg:province":"Nordrhein-Westfalen",
    "wof:name":"K. Rummler",
    "wof:placetype":"venue"
},
  "geometry": {"coordinates":[7.3254079819,52.1489257812],"type":"Point"}
}