{
  "type": "Feature",
  "properties": {
    "iso:country":"DE",
    "sg:address":"Eugen-Bolz-Str. 9",
    "sg:city":"Schw\u00e4bisch Gm\u00fcnd",
    "sg:phone":"+49 7171/66838",
    "sg:postcode":"73525",
    "sg:province":"Baden-W\u00fcrttemberg",
    "wof:name":"Spranger Verwaltungs Gmbh",
    "wof:placetype":"venue"
},
  "geometry": {"coordinates":[9.777604,48.788631],"type":"Point"}
}