{
  "type": "Feature",
  "properties": {
    "iso:country":"DE",
    "sg:city":"Markt Einersheim",
    "sg:phone":"+49 9326/1278",
    "sg:postcode":"97348",
    "sg:province":"Bayern",
    "wof:name":"R. Rabenstein",
    "wof:placetype":"venue"
},
  "geometry": {"coordinates":[10.292738,49.68755],"type":"Point"}
}