{
  "type": "Feature",
  "properties": {
    "iso:country":"DE",
    "sg:address":"Bonhoefferstr. 24 a",
    "sg:city":"Weimar",
    "sg:postcode":"99427",
    "sg:province":"Th\u00fcringen",
    "wof:name":"Tr\u00e4gerwerke Sozieale Dienste Gemeinn\u00fctzige Arbeits- Und",
    "wof:placetype":"venue"
},
  "geometry": {"coordinates":[11.3144950867,50.9953765869],"type":"Point"}
}