{
  "type": "Feature",
  "properties": {
    "iso:country":"DE",
    "sg:address":"Dornhofstr. 71",
    "sg:city":"Neu-Isenburg",
    "sg:phone":"+49 4961/022898",
    "sg:postcode":"63263",
    "sg:province":"Hessen",
    "wof:name":"Dr Kurt R\u00dcger & Josg\u00dcnzel Schmelzfarbenfabrik Gmbh",
    "wof:placetype":"venue"
},
  "geometry": {"coordinates":[8.681514,50.045597],"type":"Point"}
}