{
  "type": "Feature",
  "properties": {
    "iso:country":"DE",
    "sg:address":"Werftstr. 31",
    "sg:city":"Andernach",
    "sg:postcode":"56626",
    "sg:province":"Rheinland-Pfalz",
    "wof:name":"Vermessungsb\u00fcro Schmidt",
    "wof:placetype":"venue"
},
  "geometry": {"coordinates":[7.4134049416,50.437297821],"type":"Point"}
}