{
  "type": "Feature",
  "properties": {
    "iso:country":"DE",
    "sg:address":"Kirchstr. 2",
    "sg:city":"Uhingen",
    "sg:phone":"+49 7161/93800",
    "sg:postcode":"73066",
    "sg:province":"Baden-W\u00fcrttemberg",
    "wof:name":"Redaktion Mitteilungsblatt Der Gemeinde Kuchen",
    "wof:placetype":"venue"
},
  "geometry": {"coordinates":[9.5858383179,48.7046051025],"type":"Point"}
}