{
  "type": "Feature",
  "properties": {
    "iso:country":"DE",
    "sg:address":"Steinergasse 15",
    "sg:city":"Straubing",
    "sg:phone":"+49 9421/12127",
    "sg:postcode":"94315",
    "sg:province":"Bayern",
    "wof:name":"Restaurant Kochl\u00f6ffel Gmbh & Co. Kg",
    "wof:placetype":"venue"
},
  "geometry": {"coordinates":[12.5695457458,48.8812179565],"type":"Point"}
}