{
  "type": "Feature",
  "properties": {
    "iso:country":"DE",
    "sg:address":"Harrendorf 22",
    "sg:city":"Bramstedt",
    "sg:phone":"+49 4746/1562",
    "sg:postcode":"27628",
    "sg:province":"Niedersachsen",
    "wof:name":"Horst Und Karola Werner",
    "wof:placetype":"venue"
},
  "geometry": {"coordinates":[8.7401657104,53.3494911194],"type":"Point"}
}