{
  "type": "Feature",
  "properties": {
    "iso:country":"DE",
    "sg:address":"Hohe Str. 61",
    "sg:city":"Windeck",
    "sg:phone":"+49 2292/5473",
    "sg:postcode":"51570",
    "sg:province":"Nordrhein-Westfalen",
    "wof:name":"Hurster Hof",
    "wof:placetype":"venue"
},
  "geometry": {"coordinates":[7.6409869194,50.7926063538],"type":"Point"}
}