{
  "type": "Feature",
  "properties": {
    "iso:country":"DE",
    "sg:address":"Bergstr. 8",
    "sg:city":"Bad Bodenteich",
    "sg:phone":"+49 5824/3667",
    "sg:postcode":"29389",
    "sg:province":"Niedersachsen",
    "wof:name":"Molly- Chic",
    "wof:placetype":"venue"
},
  "geometry": {"coordinates":[10.675241,52.832809],"type":"Point"}
}