{
  "type": "Feature",
  "properties": {
    "iso:country":"DE",
    "sg:address":"Schmitzb\u00fcchel 36",
    "sg:city":"Overath",
    "sg:phone":"+49 2204/74401",
    "sg:postcode":"51491",
    "sg:province":"Nordrhein-Westfalen",
    "wof:name":"W. Preiss",
    "wof:placetype":"venue"
},
  "geometry": {"coordinates":[7.222714901,50.9573936462],"type":"Point"}
}