{
  "type": "Feature",
  "properties": {
    "iso:country":"DE",
    "sg:address":"Stadionstr. 146",
    "sg:city":"Grefrath",
    "sg:phone":"+49 2158/1745",
    "sg:postcode":"47929",
    "sg:province":"Nordrhein-Westfalen",
    "wof:name":"Pizzeria Da Luigi",
    "wof:placetype":"venue"
},
  "geometry": {"coordinates":[6.3422927856,51.3470153809],"type":"Point"}
}