{
  "type": "Feature",
  "properties": {
    "iso:country":"DE",
    "sg:address":"Lange Str. 71",
    "sg:city":"Diepenau",
    "sg:phone":"+49 5775/277",
    "sg:postcode":"31603",
    "sg:province":"Niedersachsen",
    "wof:name":"Textilhaus Gustav Wehring",
    "wof:placetype":"venue"
},
  "geometry": {"coordinates":[8.770999,52.475391],"type":"Point"}
}