{
  "type": "Feature",
  "properties": {
    "iso:country":"DE",
    "sg:address":"Katternberger Str. 279",
    "sg:city":"Solingen",
    "sg:phone":"+49 4961/724080",
    "sg:postcode":"42655",
    "sg:province":"Nordrhein-Westfalen",
    "wof:name":"Bridgestone Deutschland Gmbh",
    "wof:placetype":"venue"
},
  "geometry": {"coordinates":[8.6586704254,50.2215385437],"type":"Point"}
}