{
  "type": "Feature",
  "properties": {
    "iso:country":"DE",
    "sg:address":"Paul-Gerhardt-Allee 42",
    "sg:city":"M\u00fcnchen",
    "sg:phone":"+49 89/8292650",
    "sg:postcode":"81245",
    "sg:province":"Bayern",
    "wof:name":"Metronomia Gmbh",
    "wof:placetype":"venue"
},
  "geometry": {"coordinates":[11.476896286,48.1533088684],"type":"Point"}
}