{
  "type": "Feature",
  "properties": {
    "iso:country":"DE",
    "sg:address":"Ludwigstr. 36",
    "sg:city":"Gie\u00dfen",
    "sg:phone":"+49 641/72684",
    "sg:postcode":"35390",
    "sg:province":"Hessen",
    "wof:name":"Pizzeria Italienische Nudelstube",
    "wof:placetype":"venue"
},
  "geometry": {"coordinates":[8.6756248474,50.5804023743],"type":"Point"}
}