{
  "type": "Feature",
  "properties": {
    "iso:country":"DE",
    "sg:address":"Marktstr. 17",
    "sg:city":"Bad M\u00fcnder",
    "sg:phone":"+49 5042/6980",
    "sg:postcode":"31848",
    "sg:province":"Niedersachsen",
    "wof:name":"A. Jaschinski",
    "wof:placetype":"venue"
},
  "geometry": {"coordinates":[9.4623250961,52.1974868774],"type":"Point"}
}