{
  "type": "Feature",
  "properties": {
    "iso:country":"DE",
    "sg:address":"Am Maintor 8",
    "sg:city":"Hanau",
    "sg:phone":"+49 6181/670900",
    "sg:postcode":"63456",
    "sg:province":"Hessen",
    "wof:name":"Eido - The Magic Shop",
    "wof:placetype":"venue"
},
  "geometry": {"coordinates":[8.916554,50.107487],"type":"Point"}
}