{
  "type": "Feature",
  "properties": {
    "iso:country":"DE",
    "sg:address":"Weidenkamp 28",
    "sg:city":"Xanten",
    "sg:phone":"+49 2801/3582",
    "sg:postcode":"46509",
    "sg:province":"Nordrhein-Westfalen",
    "wof:name":"Dr. Helmut Zielinski Tierarzt",
    "wof:placetype":"venue"
},
  "geometry": {"coordinates":[6.436519146,51.6503410339],"type":"Point"}
}