{
  "type": "Feature",
  "properties": {
    "iso:country":"DE",
    "sg:address":"Steinheimer Str. 58a",
    "sg:city":"Seligenstadt",
    "sg:phone":"+49 6182/3017",
    "sg:postcode":"63500",
    "sg:province":"Hessen",
    "wof:name":"Immoplan Gmbh",
    "wof:placetype":"venue"
},
  "geometry": {"coordinates":[8.9746856689,50.0491523743],"type":"Point"}
}