{
  "type": "Feature",
  "properties": {
    "iso:country":"DE",
    "sg:address":"Kalkarer Str. 22-26",
    "sg:city":"Goch",
    "sg:phone":"+49 2823/93330",
    "sg:postcode":"47574",
    "sg:province":"Nordrhein-Westfalen",
    "wof:name":"Raab Karcher Baustoffe",
    "wof:placetype":"venue"
},
  "geometry": {"coordinates":[6.16229105,51.6795654297],"type":"Point"}
}