{
  "type": "Feature",
  "properties": {
    "iso:country":"DE",
    "sg:address":"Gotenweg 1",
    "sg:city":"Braunschweig",
    "sg:phone":"+49 531/388090",
    "sg:postcode":"38106",
    "sg:province":"Niedersachsen",
    "wof:name":"Harke & Schulze",
    "wof:placetype":"venue"
},
  "geometry": {"coordinates":[10.5370883942,52.2824783325],"type":"Point"}
}