{
  "type": "Feature",
  "properties": {
    "iso:country":"DE",
    "sg:address":"Auf der Langwies 3",
    "sg:city":"H\u00fcnstetten",
    "sg:phone":"+49 6126/53722",
    "sg:postcode":"65510",
    "sg:province":"Hessen",
    "wof:name":"Gerd Ahlers Gmbh Forst- Und Gartenger\u00e4te",
    "wof:placetype":"venue"
},
  "geometry": {"coordinates":[8.1944742203,50.2485122681],"type":"Point"}
}