{
  "type": "Feature",
  "properties": {
    "iso:country":"DE",
    "sg:address":"Buschweg 7",
    "sg:city":"Aerzen",
    "sg:phone":"+49 5154/2001",
    "sg:postcode":"31855",
    "sg:province":"Niedersachsen",
    "wof:name":"Hotel Landluft-multh\u00f6pen",
    "wof:placetype":"venue"
},
  "geometry": {"coordinates":[9.2428922653,52.0791015625],"type":"Point"}
}