{
  "type": "Feature",
  "properties": {
    "iso:country":"DE",
    "sg:address":"Kopenhagener Str. 65",
    "sg:city":"Berlin",
    "sg:phone":"+49 30/4498287",
    "sg:postcode":"10437",
    "sg:province":"Berlin",
    "wof:name":"G\u00fcnter K\u00f6rner",
    "wof:placetype":"venue"
},
  "geometry": {"coordinates":[13.408438,52.548897],"type":"Point"}
}