{
  "type": "Feature",
  "properties": {
    "iso:country":"DE",
    "sg:address":"M\u00fchlenstr. 22",
    "sg:city":"Weener",
    "sg:phone":"+49 4951/8283",
    "sg:postcode":"26826",
    "sg:province":"Niedersachsen",
    "wof:name":"R. B\u00fcnker-k\u00f6ller & J. K\u00f6ller",
    "wof:placetype":"venue"
},
  "geometry": {"coordinates":[7.3463487625,53.160572052],"type":"Point"}
}