{
  "type": "Feature",
  "properties": {
    "iso:country":"DE",
    "sg:address":"Mont-Cenis-Str. 238",
    "sg:city":"Herne",
    "sg:phone":"+49 2323/96202",
    "sg:postcode":"44627",
    "sg:province":"Nordrhein-Westfalen",
    "wof:name":"Frohne",
    "wof:placetype":"venue"
},
  "geometry": {"coordinates":[7.24488,51.538582],"type":"Point"}
}