{
  "type": "Feature",
  "properties": {
    "iso:country":"DE",
    "sg:address":"Am Breitenstein 4",
    "sg:city":"Heinade",
    "sg:phone":"+49 5532/4589",
    "sg:postcode":"37627",
    "sg:province":"Niedersachsen",
    "wof:name":"K. Niemeyer",
    "wof:placetype":"venue"
},
  "geometry": {"coordinates":[9.6372470856,51.8339347839],"type":"Point"}
}