{
  "type": "Feature",
  "properties": {
    "iso:country":"DE",
    "sg:address":"Am Sportplatz",
    "sg:city":"Eichelhardt",
    "sg:phone":"+49 4927/515280",
    "sg:postcode":"57612",
    "sg:province":"Rheinland-Pfalz",
    "wof:name":"Gebr Stahlschmidt Gmbh & Co Kg",
    "wof:placetype":"venue"
},
  "geometry": {"coordinates":[8.3630237579,51.0347862244],"type":"Point"}
}