{
  "type": "Feature",
  "properties": {
    "iso:country":"DE",
    "sg:address":"Kaiserstr. 75",
    "sg:city":"Saarbr\u00fccken",
    "sg:phone":"+49 681/817706",
    "sg:postcode":"66133",
    "sg:province":"Saarland",
    "wof:name":"Moppels Classic",
    "wof:placetype":"venue"
},
  "geometry": {"coordinates":[7.0588030815,49.2446708679],"type":"Point"}
}