{
  "type": "Feature",
  "properties": {
    "iso:country":"DE",
    "sg:address":"Ludwig-Thoma-Str. 7",
    "sg:city":"Erlangen",
    "sg:phone":"+49 9131/205408",
    "sg:postcode":"91054",
    "sg:province":"Bayern",
    "wof:name":"Horst Lawaczeck-textil- Handelsvertretungen Gmbh",
    "wof:placetype":"venue"
},
  "geometry": {"coordinates":[11.016076088,49.6096801758],"type":"Point"}
}