{
  "type": "Feature",
  "properties": {
    "iso:country":"DE",
    "sg:address":"Geibelstr. 21",
    "sg:city":"Ratingen",
    "sg:phone":"+49 2102/50334",
    "sg:postcode":"40882",
    "sg:province":"Nordrhein-Westfalen",
    "wof:name":"Hans-joachim Bardts Masseur",
    "wof:placetype":"venue"
},
  "geometry": {"coordinates":[6.930469,51.29319],"type":"Point"}
}