{
  "type": "Feature",
  "properties": {
    "iso:country":"DE",
    "sg:address":"Henkelstr. 67",
    "sg:city":"D\u00fcsseldorf",
    "sg:postcode":"40589",
    "sg:province":"Nordrhein-Westfalen",
    "wof:name":"Schwarzkopf & Henkel Production",
    "wof:placetype":"venue"
},
  "geometry": {"coordinates":[6.8415780067,51.175327301],"type":"Point"}
}