{
  "type": "Feature",
  "properties": {
    "iso:country":"DE",
    "sg:address":"Loher Str. 8",
    "sg:city":"Erwitte",
    "sg:phone":"+49 2945/2295",
    "sg:postcode":"59597",
    "sg:province":"Nordrhein-Westfalen",
    "wof:name":"Paul Rienhoff",
    "wof:placetype":"venue"
},
  "geometry": {"coordinates":[8.223528,51.62394],"type":"Point"}
}