{
  "type": "Feature",
  "properties": {
    "iso:country":"DE",
    "sg:address":"Friesenstr. 49",
    "sg:city":"Hannover",
    "sg:phone":"+49 511/311203",
    "sg:postcode":"30161",
    "sg:province":"Niedersachsen",
    "wof:name":"Heiner Kolster",
    "wof:placetype":"venue"
},
  "geometry": {"coordinates":[9.7487068176,52.3817329407],"type":"Point"}
}