{
  "type": "Feature",
  "properties": {
    "iso:country":"DE",
    "sg:address":"Kronenstr. 4",
    "sg:city":"Oberndorf",
    "sg:phone":"+49 7423/4554",
    "sg:postcode":"78727",
    "sg:province":"Baden-W\u00fcrttemberg",
    "wof:name":"Walter Baier Und Hermann Eberhardt",
    "wof:placetype":"venue"
},
  "geometry": {"coordinates":[8.570835,48.291008],"type":"Point"}
}