{
  "type": "Feature",
  "properties": {
    "iso:country":"DE",
    "sg:address":"Schlesische Str. 67",
    "sg:city":"Hennef",
    "sg:phone":"+49 2242/82763",
    "sg:postcode":"53773",
    "sg:province":"Nordrhein-Westfalen",
    "wof:name":"H. Timpen",
    "wof:placetype":"venue"
},
  "geometry": {"coordinates":[7.2531518936,50.7750244141],"type":"Point"}
}