{
  "type": "Feature",
  "properties": {
    "iso:country":"DE",
    "sg:address":"Bruchhausener Str. 27",
    "sg:city":"Arnsberg",
    "sg:phone":"+49 2932/31507",
    "sg:postcode":"59759",
    "sg:province":"Nordrhein-Westfalen",
    "wof:name":"Gastst\u00e4tte Annette K\u00f6rner",
    "wof:placetype":"venue"
},
  "geometry": {"coordinates":[8.0333747864,51.4294548035],"type":"Point"}
}