{
  "type": "Feature",
  "properties": {
    "iso:country":"DE",
    "sg:address":"Schanzenweg 4",
    "sg:city":"Rechenberg-Bienenm\u00fchle",
    "sg:phone":"+49 37327/7489",
    "sg:postcode":"09623",
    "sg:province":"Sachsen",
    "wof:name":"Weises Gastst\u00e4tte",
    "wof:placetype":"venue"
},
  "geometry": {"coordinates":[13.5756750107,50.7356185913],"type":"Point"}
}