{
  "type": "Feature",
  "properties": {
    "iso:country":"DE",
    "sg:address":"Weinstr. 7",
    "sg:city":"Bad Soden-Salm\u00fcnster",
    "sg:phone":"+49 6056/5205",
    "sg:postcode":"63628",
    "sg:province":"Hessen",
    "wof:name":"W. Becker",
    "wof:placetype":"venue"
},
  "geometry": {"coordinates":[9.3681440353,50.2724533081],"type":"Point"}
}