{
  "type": "Feature",
  "properties": {
    "iso:country":"DE",
    "sg:address":"Buckower Strasse 8",
    "sg:city":"Tauche",
    "sg:phone":"+49 33675/219",
    "sg:postcode":"15848",
    "sg:province":"Brandenburg",
    "wof:name":"Beeskower Sch\u00fctzengilde 1424 E.v.",
    "wof:placetype":"venue"
},
  "geometry": {"coordinates":[14.1603794098,52.1586761475],"type":"Point"}
}