{
  "type": "Feature",
  "properties": {
    "iso:country":"DE",
    "sg:address":"Immling",
    "sg:city":"Halfing",
    "sg:postcode":"83128",
    "sg:province":"Bayern",
    "wof:name":"Kunst Und Begegnung Veranstaltungs Gmbh",
    "wof:placetype":"venue"
},
  "geometry": {"coordinates":[12.2641744614,47.9243202209],"type":"Point"}
}