{
  "type": "Feature",
  "properties": {
    "iso:country":"DE",
    "sg:address":"Waldstr. 4",
    "sg:city":"Bad D\u00fcrkheim",
    "sg:phone":"+49 6322/1628",
    "sg:postcode":"67098",
    "sg:province":"Rheinland-Pfalz",
    "wof:name":"K.-p. Schwinn",
    "wof:placetype":"venue"
},
  "geometry": {"coordinates":[8.157324791,49.493057251],"type":"Point"}
}