{
  "type": "Feature",
  "properties": {
    "iso:country":"DE",
    "sg:address":"Waldstr. 15",
    "sg:city":"Heidenrod",
    "sg:phone":"+49 6120/8873",
    "sg:postcode":"65321",
    "sg:province":"Hessen",
    "wof:name":"Franzen Gmbh",
    "wof:placetype":"venue"
},
  "geometry": {"coordinates":[8.0055713654,50.1868057251],"type":"Point"}
}