{
  "type": "Feature",
  "properties": {
    "iso:country":"DE",
    "sg:address":"Dorfstr. 4",
    "sg:city":"Legde",
    "sg:phone":"+49 38791/6235",
    "sg:postcode":"19336",
    "sg:province":"Brandenburg",
    "wof:name":"Eckhard Noack",
    "wof:placetype":"venue"
},
  "geometry": {"coordinates":[12.0019,52.913898],"type":"Point"}
}