{
  "type": "Feature",
  "properties": {
    "iso:country":"DE",
    "sg:address":"Neckarstr. 48",
    "sg:city":"K\u00f6ln",
    "sg:phone":"+49 2203/913277",
    "sg:postcode":"51149",
    "sg:province":"Nordrhein-Westfalen",
    "wof:name":"Hans Frank Ingenieur",
    "wof:placetype":"venue"
},
  "geometry": {"coordinates":[7.0187587738,50.8979911804],"type":"Point"}
}