{
  "type": "Feature",
  "properties": {
    "iso:country":"DE",
    "sg:address":"Tassilostr. 15 a",
    "sg:city":"Neuching",
    "sg:phone":"+49 8123/1603",
    "sg:postcode":"85467",
    "sg:province":"Bayern",
    "wof:name":"R. Isemann",
    "wof:placetype":"venue"
},
  "geometry": {"coordinates":[11.8547477722,48.2387466431],"type":"Point"}
}