{
  "type": "Feature",
  "properties": {
    "iso:country":"DE",
    "sg:address":"Wollanistr. 12",
    "sg:city":"M\u00fcnchen",
    "sg:phone":"+49 89/401947",
    "sg:postcode":"81671",
    "sg:province":"Bayern",
    "wof:name":"Straubinger Bauunternehmung Gmbh",
    "wof:placetype":"venue"
},
  "geometry": {"coordinates":[11.6126241684,48.118057251],"type":"Point"}
}