{
  "type": "Feature",
  "properties": {
    "iso:country":"DE",
    "sg:address":"K\u00f6nigsstr. 19",
    "sg:city":"Oettingen",
    "sg:phone":"+49 9082/3801",
    "sg:postcode":"86732",
    "sg:province":"Bayern",
    "wof:name":"J. Schwarzer Reiseb\u00fcro",
    "wof:placetype":"venue"
},
  "geometry": {"coordinates":[10.602643013,48.9501075745],"type":"Point"}
}