{
  "type": "Feature",
  "properties": {
    "iso:country":"DE",
    "sg:address":"Am Stadtpark",
    "sg:city":"Frankfurt",
    "sg:phone":"+49 69/319416",
    "sg:postcode":"65929",
    "sg:province":"Hessen",
    "wof:name":"Vereinsgastst\u00e4tte Kleingartenverein",
    "wof:placetype":"venue"
},
  "geometry": {"coordinates":[8.5599403381,50.1110038757],"type":"Point"}
}