{
  "type": "Feature",
  "properties": {
    "iso:country":"DE",
    "sg:address":"Badehausallee 43",
    "sg:city":"Cuxhaven",
    "sg:phone":"+49 4721/36643",
    "sg:postcode":"27476",
    "sg:province":"Niedersachsen",
    "wof:name":"Monika Buch",
    "wof:placetype":"venue"
},
  "geometry": {"coordinates":[8.683477,53.875084],"type":"Point"}
}