{
  "type": "Feature",
  "properties": {
    "iso:country":"DE",
    "sg:address":"Wiesenweg 4 + 7",
    "sg:city":"Willingen",
    "sg:phone":"+49 5632/69553",
    "sg:postcode":"34508",
    "sg:province":"Hessen",
    "wof:name":"Kunst-studio Brigitte Marx",
    "wof:placetype":"venue"
},
  "geometry": {"coordinates":[8.61534,51.292091],"type":"Point"}
}