{
  "type": "Feature",
  "properties": {
    "iso:country":"DE",
    "sg:address":"Colonnaden 5",
    "sg:city":"Hamburg",
    "sg:phone":"+49 40/3553360",
    "sg:postcode":"20354",
    "sg:province":"Hamburg",
    "wof:name":"Alpers & Stenger Steuerberatungsges. Mbh",
    "wof:placetype":"venue"
},
  "geometry": {"coordinates":[9.990530014,53.555141449],"type":"Point"}
}