{
  "type": "Feature",
  "properties": {
    "iso:country":"DE",
    "sg:address":"Zum Hohen Felde 6",
    "sg:city":"Kranenburg",
    "sg:phone":"+49 4140/443",
    "sg:postcode":"21726",
    "sg:province":"Niedersachsen",
    "wof:name":"K. Und K. G\u00f6rlach",
    "wof:placetype":"venue"
},
  "geometry": {"coordinates":[9.2062730789,53.6047554016],"type":"Point"}
}