{
  "type": "Feature",
  "properties": {
    "iso:country":"DE",
    "sg:address":"Gr\u00fcner Winkel 3",
    "sg:city":"Reckenfeld",
    "sg:phone":"+49 2575",
    "sg:postcode":"48268",
    "sg:province":"Nordrhein-Westfalen",
    "wof:name":"Cdu Reckenfeld",
    "wof:placetype":"venue"
},
  "geometry": {"coordinates":[7.5554590225,52.129940033],"type":"Point"}
}