{
  "type": "Feature",
  "properties": {
    "iso:country":"DE",
    "sg:address":"Gerabronn",
    "sg:city":"Gerabronn",
    "sg:phone":"+49 7952/6050",
    "sg:postcode":"74582",
    "sg:province":"Baden-W\u00fcrttemberg",
    "wof:name":"Volksbank Gerabronn Eg",
    "wof:placetype":"venue"
},
  "geometry": {"coordinates":[9.92615,49.239471],"type":"Point"}
}