{
  "type": "Feature",
  "properties": {
    "iso:country":"DE",
    "sg:address":"Auf dem Menn 5",
    "sg:city":"Reichshof",
    "sg:phone":"+49 2297/7682",
    "sg:postcode":"51580",
    "sg:province":"Nordrhein-Westfalen",
    "wof:name":"Marita Und Norbert K\u00fchr Immobilienmakler",
    "wof:placetype":"venue"
},
  "geometry": {"coordinates":[7.7667632103,50.969367981],"type":"Point"}
}