{
  "type": "Feature",
  "properties": {
    "iso:country":"DE",
    "sg:address":"Ludwig-Weisser-Str. 46",
    "sg:city":"St. Georgen",
    "sg:phone":"+49 7724/4429",
    "sg:postcode":"78112",
    "sg:province":"Baden-W\u00fcrttemberg",
    "wof:name":"Siegfried B\u00f6singer Masseur",
    "wof:placetype":"venue"
},
  "geometry": {"coordinates":[8.33749,48.13221],"type":"Point"}
}