{
  "type": "Feature",
  "properties": {
    "iso:country":"DE",
    "sg:address":"Hauptstr. 116",
    "sg:city":"H\u00fctschenhausen",
    "sg:phone":"+49 6372/1479",
    "sg:postcode":"66882",
    "sg:province":"Rheinland-Pfalz",
    "wof:name":"Albert Becker",
    "wof:placetype":"venue"
},
  "geometry": {"coordinates":[7.4748,49.419083],"type":"Point"}
}