{
  "type": "Feature",
  "properties": {
    "iso:country":"DE",
    "sg:address":"Dhauner Str. 18 a",
    "sg:city":"Kirn",
    "sg:phone":"+49 6752/4257",
    "sg:postcode":"55606",
    "sg:province":"Rheinland-Pfalz",
    "wof:name":"J\u00f6rg Becker",
    "wof:placetype":"venue"
},
  "geometry": {"coordinates":[7.459843,49.789352],"type":"Point"}
}