{
  "type": "Feature",
  "properties": {
    "iso:country":"DE",
    "sg:address":"Jahnstr. 6",
    "sg:city":"Baienfurt",
    "sg:phone":"+49 751/42308",
    "sg:postcode":"88255",
    "sg:province":"Baden-W\u00fcrttemberg",
    "wof:name":"Hans J\u00f6chle",
    "wof:placetype":"venue"
},
  "geometry": {"coordinates":[9.6501893997,47.8290557861],"type":"Point"}
}