{
  "type": "Feature",
  "properties": {
    "iso:country":"DE",
    "sg:address":"Loikumer Rott 12",
    "sg:city":"Hamminkeln",
    "sg:postcode":"46499",
    "sg:province":"Nordrhein-Westfalen",
    "wof:name":"Stall-profi Gmbh",
    "wof:placetype":"venue"
},
  "geometry": {"coordinates":[6.589103,51.740898],"type":"Point"}
}