{
  "type": "Feature",
  "properties": {
    "iso:country":"DE",
    "sg:address":"Herborner Str 7",
    "sg:city":"Sinn",
    "sg:phone":"+49 2772/571471",
    "sg:postcode":"35764",
    "sg:province":"Hessen",
    "wof:name":"Geruk Gmbh",
    "wof:placetype":"venue"
},
  "geometry": {"coordinates":[8.3259153366,50.6572189331],"type":"Point"}
}