{
  "type": "Feature",
  "properties": {
    "iso:country":"DE",
    "sg:address":"Hauptstr. 119",
    "sg:city":"Osterode",
    "sg:phone":"+49 5522/2637",
    "sg:postcode":"37520",
    "sg:province":"Niedersachsen",
    "wof:name":"E. D\u00f6ring",
    "wof:placetype":"venue"
},
  "geometry": {"coordinates":[10.2628698349,51.7336196899],"type":"Point"}
}