{
  "type": "Feature",
  "properties": {
    "iso:country":"DE",
    "sg:address":"Dorfstr. 14",
    "sg:city":"Eimeldingen",
    "sg:phone":"+49 7621/62584",
    "sg:postcode":"79591",
    "sg:province":"Baden-W\u00fcrttemberg",
    "wof:name":"Ev. Pfarramt Eimeldingen M\u00e4rkt",
    "wof:placetype":"venue"
},
  "geometry": {"coordinates":[7.5967440605,47.6309280396],"type":"Point"}
}