{
  "type": "Feature",
  "properties": {
    "iso:country":"DE",
    "sg:address":"Vor der Prinzenquelle 20a",
    "sg:city":"Kassel",
    "sg:phone":"+49 561/311533",
    "sg:postcode":"34130",
    "sg:province":"Hessen",
    "wof:name":"Dr. Sigurg Luberichs Rechtsanwalt",
    "wof:placetype":"venue"
},
  "geometry": {"coordinates":[9.429394722,51.3231735229],"type":"Point"}
}