{
  "type": "Feature",
  "properties": {
    "iso:country":"DE",
    "sg:address":"Hirtstr. 7",
    "sg:city":"Sch\u00f6llnach",
    "sg:phone":"+49 9903/537",
    "sg:postcode":"94508",
    "sg:province":"Bayern",
    "wof:name":"Alte Herren Sch\u00f6llnach Alois Feilmeier",
    "wof:placetype":"venue"
},
  "geometry": {"coordinates":[13.1852807999,48.7463607788],"type":"Point"}
}