{
  "type": "Feature",
  "properties": {
    "iso:country":"DE",
    "sg:address":"Blumenstr. 12",
    "sg:city":"Bornheim",
    "sg:phone":"+49 2227/2777",
    "sg:postcode":"53332",
    "sg:province":"Nordrhein-Westfalen",
    "wof:name":"R. Schaefer",
    "wof:placetype":"venue"
},
  "geometry": {"coordinates":[6.9510741234,50.7656402588],"type":"Point"}
}