{
  "type": "Feature",
  "properties": {
    "iso:country":"DE",
    "sg:address":"Norderstr. 3",
    "sg:city":"Kronprinzenkoog",
    "sg:phone":"+49 4856/1263",
    "sg:postcode":"25709",
    "sg:province":"Schleswig-Holstein",
    "wof:name":"Rausch",
    "wof:placetype":"venue"
},
  "geometry": {"coordinates":[8.98137,53.948391],"type":"Point"}
}