{
  "type": "Feature",
  "properties": {
    "iso:country":"DE",
    "sg:address":"Landwehrstr. 18",
    "sg:city":"Schweinfurt",
    "sg:phone":"+49 9721/18236",
    "sg:postcode":"97421",
    "sg:province":"Bayern",
    "wof:name":"Jenner & Partner",
    "wof:placetype":"venue"
},
  "geometry": {"coordinates":[10.2206230164,50.0405197144],"type":"Point"}
}