{
  "type": "Feature",
  "properties": {
    "iso:country":"DE",
    "sg:address":"K\u00f6nigstr. 6",
    "sg:city":"Hof",
    "sg:phone":"+49 9281/72820",
    "sg:postcode":"95028",
    "sg:province":"Bayern",
    "wof:name":"Werbeagentur Georg Fickenscher Gmbh",
    "wof:placetype":"venue"
},
  "geometry": {"coordinates":[11.9232320786,50.3091278076],"type":"Point"}
}