{
  "type": "Feature",
  "properties": {
    "iso:country":"DE",
    "sg:address":"Unterachtel 5",
    "sg:city":"Simmelsdorf",
    "sg:phone":"+49 9155/483",
    "sg:postcode":"91245",
    "sg:province":"Bayern",
    "wof:name":"Henrike Sauermann",
    "wof:placetype":"venue"
},
  "geometry": {"coordinates":[11.370347023,49.6156272888],"type":"Point"}
}