{
  "type": "Feature",
  "properties": {
    "iso:country":"DE",
    "sg:address":"Eilveser Hauptstr. 25",
    "sg:city":"Neustadt",
    "sg:phone":"+49 5034/309",
    "sg:postcode":"31535",
    "sg:province":"Niedersachsen",
    "wof:name":"Heinrich Kruse",
    "wof:placetype":"venue"
},
  "geometry": {"coordinates":[9.413951,52.546276],"type":"Point"}
}