{
  "type": "Feature",
  "properties": {
    "iso:country":"DE",
    "sg:address":"Elkanweg 17",
    "sg:city":"Viersen",
    "sg:phone":"+49 4971/258209",
    "sg:postcode":"41748",
    "sg:province":"Nordrhein-Westfalen",
    "wof:name":"Viesel Apparatebau",
    "wof:placetype":"venue"
},
  "geometry": {"coordinates":[9.409218,48.494713],"type":"Point"}
}