{
  "type": "Feature",
  "properties": {
    "iso:country":"DE",
    "sg:address":"B\u00fcschenloh 11",
    "sg:city":"Westerheim",
    "sg:postcode":"72589",
    "sg:province":"Baden-W\u00fcrttemberg",
    "wof:name":"Hans-helmut Kurz Architekt",
    "wof:placetype":"venue"
},
  "geometry": {"coordinates":[9.621602,48.508595],"type":"Point"}
}