{
  "type": "Feature",
  "properties": {
    "iso:country":"DE",
    "sg:address":"Altenessener Str. 311",
    "sg:city":"Essen",
    "sg:phone":"+49 201/357535",
    "sg:postcode":"45326",
    "sg:province":"Nordrhein-Westfalen",
    "wof:name":"Hotel B\u00f6ll Gmbh",
    "wof:placetype":"venue"
},
  "geometry": {"coordinates":[7.0089349747,51.4901657104],"type":"Point"}
}