{
  "type": "Feature",
  "properties": {
    "iso:country":"DE",
    "sg:address":"S\u00fcdring 25 a",
    "sg:city":"Trunkelsberg",
    "sg:phone":"+49 8331/2624",
    "sg:postcode":"87779",
    "sg:province":"Bayern",
    "wof:name":"Peter Linder",
    "wof:placetype":"venue"
},
  "geometry": {"coordinates":[10.217294693,48.0005569458],"type":"Point"}
}