{
  "type": "Feature",
  "properties": {
    "iso:country":"DE",
    "sg:address":"Bahnhofstr. 115",
    "sg:city":"Castrop-Rauxel",
    "sg:phone":"+49 2305/12859",
    "sg:postcode":"44575",
    "sg:province":"Nordrhein-Westfalen",
    "wof:name":"Jet-tankstelle",
    "wof:placetype":"venue"
},
  "geometry": {"coordinates":[7.3096461296,51.5601119995],"type":"Point"}
}