{
  "type": "Feature",
  "properties": {
    "iso:country":"DE",
    "sg:address":"Mainaustr. 33",
    "sg:city":"W\u00fcrzburg",
    "sg:phone":"+49 931/41940",
    "sg:postcode":"97082",
    "sg:province":"Bayern",
    "wof:name":"Bibliothek Der Industrie- Und Handelskammer",
    "wof:placetype":"venue"
},
  "geometry": {"coordinates":[9.909356,49.801472],"type":"Point"}
}