{
  "type": "Feature",
  "properties": {
    "iso:country":"DE",
    "sg:address":"An de Wees 16",
    "sg:city":"Kosel",
    "sg:phone":"+49 4354/98430",
    "sg:postcode":"24354",
    "sg:province":"Schleswig-Holstein",
    "wof:name":"Campingplatz Wees",
    "wof:placetype":"venue"
},
  "geometry": {"coordinates":[9.72313,54.52272],"type":"Point"}
}