{
  "type": "Feature",
  "properties": {
    "iso:country":"DE",
    "sg:address":"Gradh\u00f6he 1",
    "sg:city":"Grebenstein",
    "sg:phone":"+49 5674/6270",
    "sg:postcode":"34393",
    "sg:province":"Hessen",
    "wof:name":"Lothar Trinoga",
    "wof:placetype":"venue"
},
  "geometry": {"coordinates":[9.408064,51.43214],"type":"Point"}
}