{
  "type": "Feature",
  "properties": {
    "iso:country":"DE",
    "sg:address":"Markdorfer Str. 22",
    "sg:city":"Salem",
    "sg:phone":"+49 7553/6565",
    "sg:postcode":"88682",
    "sg:province":"Baden-W\u00fcrttemberg",
    "wof:name":"Klemens Normann Massagepraxis",
    "wof:placetype":"venue"
},
  "geometry": {"coordinates":[9.311409,47.759529],"type":"Point"}
}