{
  "type": "Feature",
  "properties": {
    "iso:country":"DE",
    "sg:address":"Hauptstr. 77",
    "sg:city":"Burscheid",
    "sg:phone":"+49 2174/785796",
    "sg:postcode":"51399",
    "sg:province":"Nordrhein-Westfalen",
    "wof:name":"P. Immobilien Kintscher Gmbh",
    "wof:placetype":"venue"
},
  "geometry": {"coordinates":[7.1128997803,51.0850601196],"type":"Point"}
}