{
  "type": "Feature",
  "properties": {
    "iso:country":"DE",
    "sg:address":"Winnekendonker Str. 12",
    "sg:city":"Kevelaer",
    "sg:phone":"+49 2825/7268",
    "sg:postcode":"47627",
    "sg:province":"Nordrhein-Westfalen",
    "wof:name":"Karl-heinz Kerkenrath",
    "wof:placetype":"venue"
},
  "geometry": {"coordinates":[6.2788739204,51.6296310425],"type":"Point"}
}