{
  "type": "Feature",
  "properties": {
    "iso:country":"DE",
    "sg:address":"Stockhausener Str 2",
    "sg:city":"D\u00f6beln",
    "sg:phone":"+49 3431/66140",
    "sg:postcode":"04720",
    "sg:province":"Sachsen",
    "wof:name":"Rkb-reparatur Und Karosseriebau Gmbh",
    "wof:placetype":"venue"
},
  "geometry": {"coordinates":[13.096527,51.124123],"type":"Point"}
}