{
  "type": "Feature",
  "properties": {
    "iso:country":"DE",
    "sg:address":"Nordhorner Str. 30",
    "sg:city":"Sch\u00fcttorf",
    "sg:phone":"+49 5923/3157",
    "sg:postcode":"48465",
    "sg:province":"Niedersachsen",
    "wof:name":"Gefl\u00fcgelzuchtverein G\u00fcnter K\u00fchlmann",
    "wof:placetype":"venue"
},
  "geometry": {"coordinates":[7.215514183,52.3255958557],"type":"Point"}
}