{
  "type": "Feature",
  "properties": {
    "iso:country":"DE",
    "sg:address":"Sonnenhalde 20",
    "sg:city":"Schw\u00e4bisch Gm\u00fcnd",
    "sg:phone":"+49 7171/987060",
    "sg:postcode":"73529",
    "sg:province":"Baden-W\u00fcrttemberg",
    "wof:name":"Hanisch Formenbau Gmbh",
    "wof:placetype":"venue"
},
  "geometry": {"coordinates":[9.8384666443,48.7884216309],"type":"Point"}
}