{
  "type": "Feature",
  "properties": {
    "iso:country":"DE",
    "sg:address":"Dr.-Eugen-Sch\u00f6n-Str. 31",
    "sg:city":"Volkach",
    "sg:phone":"+49 9381/6589",
    "sg:postcode":"97332",
    "sg:province":"Bayern",
    "wof:name":"Paul Seltsam",
    "wof:placetype":"venue"
},
  "geometry": {"coordinates":[10.232417,49.863426],"type":"Point"}
}