{
  "type": "Feature",
  "properties": {
    "iso:country":"DE",
    "sg:address":"Hans-Schrader-Str. 11",
    "sg:city":"Sondershausen",
    "sg:phone":"+49 3632/750107",
    "sg:postcode":"99706",
    "sg:province":"Th\u00fcringen",
    "wof:name":"Bo-ra-tec Gmbh",
    "wof:placetype":"venue"
},
  "geometry": {"coordinates":[10.8587112427,51.3671417236],"type":"Point"}
}