{
  "type": "Feature",
  "properties": {
    "iso:country":"DE",
    "sg:address":"Marktstr. 43",
    "sg:city":"Neuwied",
    "sg:phone":"+49 2631/32714",
    "sg:postcode":"56564",
    "sg:province":"Rheinland-Pfalz",
    "wof:name":"Dart-treff 501",
    "wof:placetype":"venue"
},
  "geometry": {"coordinates":[7.4614639282,50.4291496277],"type":"Point"}
}