{
  "type": "Feature",
  "properties": {
    "iso:country":"DE",
    "sg:address":"Beendorfer Str. 63",
    "sg:city":"Morsleben",
    "sg:phone":"+49 39050/2297",
    "sg:postcode":"39343",
    "sg:province":"Sachsen-Anhalt",
    "wof:name":"Edmund Kresse",
    "wof:placetype":"venue"
},
  "geometry": {"coordinates":[11.109846,52.220825],"type":"Point"}
}