{
  "type": "Feature",
  "properties": {
    "iso:country":"DE",
    "sg:address":"Pfarrgasse 9",
    "sg:city":"Vohenstrau\u00df",
    "sg:phone":"+49 9651/1503",
    "sg:postcode":"92648",
    "sg:province":"Bayern",
    "wof:name":"Hugo Steininger Architekt",
    "wof:placetype":"venue"
},
  "geometry": {"coordinates":[12.340512,49.622681],"type":"Point"}
}