{
  "type": "Feature",
  "properties": {
    "iso:country":"DE",
    "sg:address":"Bergweg 61",
    "sg:city":"Kassel",
    "sg:phone":"+49 561/8705420",
    "sg:postcode":"34125",
    "sg:province":"Hessen",
    "wof:name":"Avisa Gmbh",
    "wof:placetype":"venue"
},
  "geometry": {"coordinates":[9.5429458618,51.3288230896],"type":"Point"}
}