{
  "type": "Feature",
  "properties": {
    "iso:country":"DE",
    "sg:address":"Lindenstr. 65",
    "sg:city":"Wadgassen",
    "sg:phone":"+49 6834/41342",
    "sg:postcode":"66787",
    "sg:province":"Saarland",
    "wof:name":"D. Egli",
    "wof:placetype":"venue"
},
  "geometry": {"coordinates":[6.79773283,49.2674751282],"type":"Point"}
}