{
  "type": "Feature",
  "properties": {
    "iso:country":"DE",
    "sg:address":"Erlenweg 11",
    "sg:city":"Parsdorf",
    "sg:phone":"+49 89/1403250",
    "sg:postcode":"85599",
    "sg:province":"Bayern",
    "wof:name":"Franz Litzinger Gmbh",
    "wof:placetype":"venue"
},
  "geometry": {"coordinates":[11.7825841904,48.1413612366],"type":"Point"}
}