{
  "type": "Feature",
  "properties": {
    "iso:country":"DE",
    "sg:address":"Obstmarschenweg 73",
    "sg:city":"Stade",
    "sg:phone":"+49 4941/4195440",
    "sg:postcode":"21683",
    "sg:province":"Niedersachsen",
    "wof:name":"Spedition Walter K\u00d6llner Gmbh",
    "wof:placetype":"venue"
},
  "geometry": {"coordinates":[9.4862451553,53.6258087158],"type":"Point"}
}