{
  "type": "Feature",
  "properties": {
    "iso:country":"DE",
    "sg:address":"Rudolf-Breitscheid-Str. 61",
    "sg:city":"Wilkau-Ha\u00dflau",
    "sg:phone":"+49 375",
    "sg:postcode":"08112",
    "sg:province":"Sachsen",
    "wof:name":"Libella Traumhaus",
    "wof:placetype":"venue"
},
  "geometry": {"coordinates":[12.5175600052,50.6693611145],"type":"Point"}
}