{
  "type": "Feature",
  "properties": {
    "iso:country":"DE",
    "sg:address":"Dortmunder Str. 183-187",
    "sg:city":"Hamm",
    "sg:phone":"+49 2381/462046",
    "sg:postcode":"59077",
    "sg:province":"Nordrhein-Westfalen",
    "wof:name":"B\u00fccker Gmbh",
    "wof:placetype":"venue"
},
  "geometry": {"coordinates":[7.755746,51.662312],"type":"Point"}
}