{
  "type": "Feature",
  "properties": {
    "iso:country":"DE",
    "sg:address":"Ohmdener Str. 2",
    "sg:city":"Holzmaden",
    "sg:phone":"+49 7023/900640",
    "sg:postcode":"73271",
    "sg:province":"Baden-W\u00fcrttemberg",
    "wof:name":"Karl Braun Gmbh & Co. Kg",
    "wof:placetype":"venue"
},
  "geometry": {"coordinates":[9.527659,48.636662],"type":"Point"}
}