{
  "type": "Feature",
  "properties": {
    "iso:country":"DE",
    "sg:address":"Langenheckenweg 5",
    "sg:city":"Laubach",
    "sg:phone":"+49 6405/3584",
    "sg:postcode":"35321",
    "sg:province":"Hessen",
    "wof:name":"Corina Reuter",
    "wof:placetype":"venue"
},
  "geometry": {"coordinates":[8.9562292099,50.5175819397],"type":"Point"}
}