{
  "type": "Feature",
  "properties": {
    "iso:country":"DE",
    "sg:address":"Ma\u00dfholder Weg 18",
    "sg:city":"Mihla",
    "sg:phone":"+49 36924/30341",
    "sg:postcode":"99826",
    "sg:province":"Th\u00fcringen",
    "wof:name":"Pension Nr-18",
    "wof:placetype":"venue"
},
  "geometry": {"coordinates":[10.343996,51.074493],"type":"Point"}
}