{
  "type": "Feature",
  "properties": {
    "iso:country":"DE",
    "sg:address":"Schlegelstr. 5",
    "sg:city":"Gotha",
    "sg:postcode":"99867",
    "sg:province":"Th\u00fcringen",
    "wof:name":"Kieswerke Kieser Verwaltungs Gmbh",
    "wof:placetype":"venue"
},
  "geometry": {"coordinates":[10.715966,50.931473],"type":"Point"}
}