{
  "type": "Feature",
  "properties": {
    "iso:country":"DE",
    "sg:address":"Heisfelder Str. 78",
    "sg:city":"Leer",
    "sg:phone":"+49 491/927860",
    "sg:postcode":"26789",
    "sg:province":"Niedersachsen",
    "wof:name":"Sophien-caf\u00e9",
    "wof:placetype":"venue"
},
  "geometry": {"coordinates":[7.455658,53.237892],"type":"Point"}
}