{
  "type": "Feature",
  "properties": {
    "iso:country":"DE",
    "sg:address":"Schwerdtfegerstr. 17",
    "sg:city":"Salzgitter",
    "sg:phone":"+49 5341/62650",
    "sg:postcode":"38239",
    "sg:province":"Niedersachsen",
    "wof:name":"Joachim Jeschke Ingenieur",
    "wof:placetype":"venue"
},
  "geometry": {"coordinates":[10.4060688019,52.1785621643],"type":"Point"}
}