{
  "type": "Feature",
  "properties": {
    "iso:country":"DE",
    "sg:address":"Heckweg 1",
    "sg:city":"K\u00f6ln",
    "sg:phone":"+49 221/5991904",
    "sg:postcode":"50739",
    "sg:province":"Nordrhein-Westfalen",
    "wof:name":"Alfons Irmler",
    "wof:placetype":"venue"
},
  "geometry": {"coordinates":[6.9080867767,50.997341156],"type":"Point"}
}