{
  "type": "Feature",
  "properties": {
    "iso:country":"DE",
    "sg:address":"Sierichstr. 157",
    "sg:city":"Hamburg",
    "sg:phone":"+49 40/477408",
    "sg:postcode":"22299",
    "sg:province":"Hamburg",
    "wof:name":"Krankengymnasten-zentral- Verband Landesverband Hamburg",
    "wof:placetype":"venue"
},
  "geometry": {"coordinates":[9.9983863831,53.5924682617],"type":"Point"}
}