{
  "type": "Feature",
  "properties": {
    "iso:country":"DE",
    "sg:address":"Ostwall 21",
    "sg:city":"Krefeld",
    "sg:phone":"+49 2151/392188",
    "sg:postcode":"47798",
    "sg:province":"Nordrhein-Westfalen",
    "wof:name":"Johannes Bonn",
    "wof:placetype":"venue"
},
  "geometry": {"coordinates":[6.5691971779,51.3273010254],"type":"Point"}
}