{
  "type": "Feature",
  "properties": {
    "iso:country":"DE",
    "sg:address":"Laubenhof 13",
    "sg:city":"Essen",
    "sg:phone":"+49 201/834080",
    "sg:postcode":"45326",
    "sg:province":"Nordrhein-Westfalen",
    "wof:name":"C. H. Zikesch Armaturentechnik Gmbh",
    "wof:placetype":"venue"
},
  "geometry": {"coordinates":[6.992138,51.483635],"type":"Point"}
}