{
  "type": "Feature",
  "properties": {
    "iso:country":"DE",
    "sg:address":"Faberstr. 12",
    "sg:city":"Friedrichshafen",
    "sg:phone":"+49 7541/53008",
    "sg:postcode":"88045",
    "sg:province":"Baden-W\u00fcrttemberg",
    "wof:name":"Dat Pr\u00fcf- Und Sch\u00e4tzungsstelle",
    "wof:placetype":"venue"
},
  "geometry": {"coordinates":[9.475205,47.669556],"type":"Point"}
}