{
  "type": "Feature",
  "properties": {
    "iso:country":"DE",
    "sg:address":"Holunderweg 52",
    "sg:city":"Frankfurt",
    "sg:phone":"+49 69/543104",
    "sg:postcode":"60433",
    "sg:province":"Hessen",
    "wof:name":"Manfred Muth",
    "wof:placetype":"venue"
},
  "geometry": {"coordinates":[8.6735858917,50.1641159058],"type":"Point"}
}