{
  "type": "Feature",
  "properties": {
    "iso:country":"DE",
    "sg:address":"Im Kaltenborn 44",
    "sg:city":"Sundern",
    "sg:phone":"+49 4923/931242",
    "sg:postcode":"59846",
    "sg:province":"Nordrhein-Westfalen",
    "wof:name":"Fs Forsttechnik Sch\u00dcltke",
    "wof:placetype":"venue"
},
  "geometry": {"coordinates":[7.954648,51.301247],"type":"Point"}
}