{
  "type": "Feature",
  "properties": {
    "iso:country":"DE",
    "sg:address":"Birnthoner Weg 4",
    "sg:city":"Feucht",
    "sg:phone":"+49 9128/5656",
    "sg:postcode":"90537",
    "sg:province":"Bayern",
    "wof:name":"Rega Einrichtungs Gmbh",
    "wof:placetype":"venue"
},
  "geometry": {"coordinates":[11.2597513199,49.3948440552],"type":"Point"}
}