{
  "type": "Feature",
  "properties": {
    "iso:country":"DE",
    "sg:address":"Burghaldenstr. 64",
    "sg:city":"Weinstadt",
    "sg:phone":"+49 7151/67103",
    "sg:postcode":"71384",
    "sg:province":"Baden-W\u00fcrttemberg",
    "wof:name":"Weing\u00e4rtnergenossenschaft Beutelsbach E.g.",
    "wof:placetype":"venue"
},
  "geometry": {"coordinates":[9.3981342316,48.8017578125],"type":"Point"}
}