{
  "type": "Feature",
  "properties": {
    "iso:country":"DE",
    "sg:address":"Karlstr. 31",
    "sg:city":"Kornwestheim",
    "sg:phone":"+49 7154/3843",
    "sg:postcode":"70806",
    "sg:province":"Baden-W\u00fcrttemberg",
    "wof:name":"Maler-service Otmar W. Reith",
    "wof:placetype":"venue"
},
  "geometry": {"coordinates":[9.182398,48.863022],"type":"Point"}
}