{
  "type": "Feature",
  "properties": {
    "iso:country":"DE",
    "sg:address":"Brahmsallee 6",
    "sg:city":"Hamburg",
    "sg:phone":"+49 40/45011850",
    "sg:postcode":"20144",
    "sg:province":"Hamburg",
    "wof:name":"Konzertdirektion Dr. Rudolf Goette Gmbh",
    "wof:placetype":"venue"
},
  "geometry": {"coordinates":[9.981947,53.573204],"type":"Point"}
}