{
  "type": "Feature",
  "properties": {
    "iso:country":"DE",
    "sg:address":"Burgsiedlung 1",
    "sg:city":"Friedberg",
    "sg:phone":"+49 6031/60030",
    "sg:postcode":"61169",
    "sg:province":"Hessen",
    "wof:name":"Reifen-seher- Und Fahrzeugtechnik Gmbh",
    "wof:placetype":"venue"
},
  "geometry": {"coordinates":[8.75854,50.344662],"type":"Point"}
}