{
  "type": "Feature",
  "properties": {
    "iso:country":"DE",
    "sg:address":"Ettringer Weg 8a",
    "sg:city":"Amberg",
    "sg:phone":"+49 8241/910204",
    "sg:postcode":"86854",
    "sg:province":"Bayern",
    "wof:name":"Redaktionsb\u00fcro Dr. Weyer",
    "wof:placetype":"venue"
},
  "geometry": {"coordinates":[10.679357,48.066612],"type":"Point"}
}