{
  "type": "Feature",
  "properties": {
    "iso:country":"DE",
    "sg:address":"Gatower Weg 14",
    "sg:city":"Seeburg",
    "sg:phone":"+49 33201/21996",
    "sg:postcode":"14476",
    "sg:province":"Brandenburg",
    "wof:name":"Area Bautr\u00e4gerges. Mbh",
    "wof:placetype":"venue"
},
  "geometry": {"coordinates":[13.126777,52.508095],"type":"Point"}
}