{
  "type": "Feature",
  "properties": {
    "iso:country":"DE",
    "sg:address":"Industriestr. 22::",
    "sg:city":"Saarlouis",
    "sg:phone":"+49 4969/299700",
    "sg:postcode":"66740",
    "sg:province":"Saarland",
    "wof:name":"Helaba Trust",
    "wof:placetype":"venue"
},
  "geometry": {"coordinates":[8.68342,50.112041],"type":"Point"}
}