{
  "type": "Feature",
  "properties": {
    "iso:country":"DE",
    "sg:address":"Stadt-Au 21",
    "sg:city":"Deggendorf",
    "sg:postcode":"94469",
    "sg:province":"Bayern",
    "wof:name":"Conactive Verwaltungs Gmbh",
    "wof:placetype":"venue"
},
  "geometry": {"coordinates":[12.9689264297,48.8329162598],"type":"Point"}
}