{
  "type": "Feature",
  "properties": {
    "iso:country":"DE",
    "sg:address":"Tremskamp 5",
    "sg:city":"Bad Schwartau",
    "sg:phone":"+49 451/20020",
    "sg:postcode":"23611",
    "sg:province":"Schleswig-Holstein",
    "wof:name":"Wolfgang Holst Ingenieur",
    "wof:placetype":"venue"
},
  "geometry": {"coordinates":[10.6908597946,53.9063415527],"type":"Point"}
}