{
  "type": "Feature",
  "properties": {
    "iso:country":"DE",
    "sg:address":"Dieselstr. 5",
    "sg:city":"Forchheim",
    "sg:postcode":"91301",
    "sg:province":"Bayern",
    "wof:name":"Erlwein Verwaltungs Gmbh",
    "wof:placetype":"venue"
},
  "geometry": {"coordinates":[11.0641222,49.7036972046],"type":"Point"}
}