{
  "type": "Feature",
  "properties": {
    "iso:country":"DE",
    "sg:address":"Dorotheenstr. 43",
    "sg:city":"Berlin",
    "sg:phone":"+49 30/20450955",
    "sg:postcode":"10117",
    "sg:province":"Berlin",
    "wof:name":"Botschaft Der Republik Kap Verde",
    "wof:placetype":"venue"
},
  "geometry": {"coordinates":[13.3888673782,52.5186080933],"type":"Point"}
}