{
  "type": "Feature",
  "properties": {
    "iso:country":"DE",
    "sg:address":"Hauptstr. 15",
    "sg:city":"Reichenbach",
    "sg:phone":"+49 7153/51124",
    "sg:postcode":"73262",
    "sg:province":"Baden-W\u00fcrttemberg",
    "wof:name":"Gernot Hess Central Drogerie",
    "wof:placetype":"venue"
},
  "geometry": {"coordinates":[12.346631,49.182774],"type":"Point"}
}