{
  "type": "Feature",
  "properties": {
    "iso:country":"DE",
    "sg:address":"Grabenstr. 24",
    "sg:city":"Heidesheim",
    "sg:phone":"+49 6132/5208",
    "sg:postcode":"55262",
    "sg:province":"Rheinland-Pfalz",
    "wof:name":"G.j. Heiser",
    "wof:placetype":"venue"
},
  "geometry": {"coordinates":[8.1155691147,49.9924430847],"type":"Point"}
}