{
  "type": "Feature",
  "properties": {
    "iso:country":"DE",
    "sg:address":"Memmertweg 28",
    "sg:city":"Bielefeld",
    "sg:phone":"+49 521/761170",
    "sg:postcode":"33729",
    "sg:province":"Nordrhein-Westfalen",
    "wof:name":"Joachim Hoffmann Innenarchitekt",
    "wof:placetype":"venue"
},
  "geometry": {"coordinates":[8.589547,52.069447],"type":"Point"}
}