{
  "type": "Feature",
  "properties": {
    "iso:country":"DE",
    "sg:address":"Frickenh\u00e4user Str. 14",
    "sg:city":"N\u00fcrtingen",
    "sg:phone":"+49 7022/932940",
    "sg:postcode":"72622",
    "sg:province":"Baden-W\u00fcrttemberg",
    "wof:name":"G. Bollermann N\u00fcrtinger Dental Labor",
    "wof:placetype":"venue"
},
  "geometry": {"coordinates":[9.340397,48.625633],"type":"Point"}
}