{
  "type": "Feature",
  "properties": {
    "iso:country":"DE",
    "sg:address":"Am Gro\u00dfmarkt",
    "sg:city":"Maxdorf",
    "sg:phone":"+49 6237/6653",
    "sg:postcode":"67133",
    "sg:province":"Rheinland-Pfalz",
    "wof:name":"Fr. Hofmann",
    "wof:placetype":"venue"
},
  "geometry": {"coordinates":[8.2897100449,49.4852600098],"type":"Point"}
}