{
  "type": "Feature",
  "properties": {
    "iso:country":"DE",
    "sg:address":"Staufer Hauptstr. 22",
    "sg:city":"Neumarkt",
    "sg:phone":"+49 9181/905763",
    "sg:postcode":"92318",
    "sg:province":"Bayern",
    "wof:name":"A. Ingerling",
    "wof:placetype":"venue"
},
  "geometry": {"coordinates":[11.431943,49.261868],"type":"Point"}
}