{
  "type": "Feature",
  "properties": {
    "iso:country":"DE",
    "sg:address":"Kirchkampweg 12",
    "sg:city":"Neuss",
    "sg:phone":"+49 2131/599807",
    "sg:postcode":"41462",
    "sg:province":"Nordrhein-Westfalen",
    "wof:name":"Klaus Becker",
    "wof:placetype":"venue"
},
  "geometry": {"coordinates":[6.6520972252,51.209487915],"type":"Point"}
}