{
  "type": "Feature",
  "properties": {
    "iso:country":"DE",
    "sg:address":"Solplatz 1",
    "sg:city":"Bad Orb",
    "sg:phone":"+49 6052/4543",
    "sg:postcode":"63619",
    "sg:province":"Hessen",
    "wof:name":"K. Koch",
    "wof:placetype":"venue"
},
  "geometry": {"coordinates":[9.348752,50.225536],"type":"Point"}
}