{
  "type": "Feature",
  "properties": {
    "iso:country":"DE",
    "sg:address":"Ernst-L\u00fcck-Platz 1",
    "sg:city":"Lotte",
    "sg:phone":"+49 541/1208410",
    "sg:postcode":"49504",
    "sg:province":"Nordrhein-Westfalen",
    "wof:name":"San Marino Eiscaf\u00e8",
    "wof:placetype":"venue"
},
  "geometry": {"coordinates":[7.989751,52.306931],"type":"Point"}
}