{
  "type": "Feature",
  "properties": {
    "iso:country":"DE",
    "sg:address":"Oberwieser Str. 9",
    "sg:city":"Kriegsfeld",
    "sg:phone":"+49 6358/339",
    "sg:postcode":"67819",
    "sg:province":"Rheinland-Pfalz",
    "wof:name":"G\u00fcnther Stoll",
    "wof:placetype":"venue"
},
  "geometry": {"coordinates":[7.921375,49.708584],"type":"Point"}
}