{
  "type": "Feature",
  "properties": {
    "iso:country":"DE",
    "sg:address":"Bremer Str. 112",
    "sg:city":"Delmenhorst",
    "sg:phone":"+49 4221/150873",
    "sg:postcode":"27751",
    "sg:province":"Niedersachsen",
    "wof:name":"H. Reusner",
    "wof:placetype":"venue"
},
  "geometry": {"coordinates":[8.6515293121,53.0534553528],"type":"Point"}
}