{
  "type": "Feature",
  "properties": {
    "iso:country":"DE",
    "sg:address":"Au\u00dferhienthaler Str. 25",
    "sg:city":"Salching",
    "sg:phone":"+49 9426/360",
    "sg:postcode":"94330",
    "sg:province":"Bayern",
    "wof:name":"Buchner-bau Gmbh",
    "wof:placetype":"venue"
},
  "geometry": {"coordinates":[12.578108,48.798252],"type":"Point"}
}