{
  "type": "Feature",
  "properties": {
    "iso:country":"DE",
    "sg:address":"Oestricher Str. 1",
    "sg:city":"Hofheim",
    "sg:phone":"+49 6122/6686",
    "sg:postcode":"65719",
    "sg:province":"Hessen",
    "wof:name":"Horst Lang",
    "wof:placetype":"venue"
},
  "geometry": {"coordinates":[8.369528,50.063007],"type":"Point"}
}