{
  "type": "Feature",
  "properties": {
    "iso:country":"DE",
    "sg:address":"Beisinger Weg 80",
    "sg:city":"Recklinghausen",
    "sg:phone":"+49 2361/186761",
    "sg:postcode":"45657",
    "sg:province":"Nordrhein-Westfalen",
    "wof:name":"Hansa-catering Gmbh",
    "wof:placetype":"venue"
},
  "geometry": {"coordinates":[7.189311,51.62421],"type":"Point"}
}