{
  "type": "Feature",
  "properties": {
    "iso:country":"DE",
    "sg:address":"Soester Str. 277",
    "sg:city":"Hamm",
    "sg:phone":"+49 2381/880704",
    "sg:postcode":"59071",
    "sg:province":"Nordrhein-Westfalen",
    "wof:name":"Cornelia Kollek",
    "wof:placetype":"venue"
},
  "geometry": {"coordinates":[7.86898,51.672089],"type":"Point"}
}