{
  "type": "Feature",
  "properties": {
    "iso:country":"DE",
    "sg:address":"Stammestr. 5",
    "sg:city":"Hannover",
    "sg:phone":"+49 511/426345",
    "sg:postcode":"30459",
    "sg:province":"Niedersachsen",
    "wof:name":"Hannjo's Angell\u00e4dchen Inh. Erhard Stadler",
    "wof:placetype":"venue"
},
  "geometry": {"coordinates":[9.729208,52.342918],"type":"Point"}
}