{
  "type": "Feature",
  "properties": {
    "iso:country":"DE",
    "sg:address":"Nordring 2",
    "sg:city":"Gro\u00df-Gerau",
    "sg:phone":"+49 6152/86757",
    "sg:postcode":"64521",
    "sg:province":"Hessen",
    "wof:name":"Griebel & Schmidt Gmbh Baumaschinen Gebraucht Und Neu",
    "wof:placetype":"venue"
},
  "geometry": {"coordinates":[8.4848909378,49.9300498962],"type":"Point"}
}