{
  "type": "Feature",
  "properties": {
    "iso:country":"DE",
    "sg:address":"Averhoffstr. 6",
    "sg:city":"Hamburg",
    "sg:phone":"+49 40/222301",
    "sg:postcode":"22085",
    "sg:province":"Hamburg",
    "wof:name":"Dieter Michalski",
    "wof:placetype":"venue"
},
  "geometry": {"coordinates":[10.0178937912,53.5705795288],"type":"Point"}
}