{
  "type": "Feature",
  "properties": {
    "iso:country":"DE",
    "sg:address":"W\u00fcrmstr. 13a",
    "sg:city":"Gr\u00e4felfing",
    "sg:phone":"+49 89/8960710",
    "sg:postcode":"82166",
    "sg:province":"Bayern",
    "wof:name":"Dross Schaffer Und Dr. Kocker Gmbh",
    "wof:placetype":"venue"
},
  "geometry": {"coordinates":[11.438247,48.117905],"type":"Point"}
}