{
  "type": "Feature",
  "properties": {
    "iso:country":"DE",
    "sg:address":"Staufenring 23",
    "sg:city":"Ulm",
    "sg:phone":"+49 731/9213710",
    "sg:postcode":"89073",
    "sg:province":"Baden-W\u00fcrttemberg",
    "wof:name":"Stahl & Berger Sicherheits- Dienste Gmbh",
    "wof:placetype":"venue"
},
  "geometry": {"coordinates":[10.0027542114,48.4053421021],"type":"Point"}
}