{
  "type": "Feature",
  "properties": {
    "iso:country":"DE",
    "sg:address":"Friedrich-von-Teck-Str. 20",
    "sg:city":"H\u00f6chst\u00e4dt",
    "sg:postcode":"89420",
    "sg:province":"Bayern",
    "wof:name":"Bettenreich Waltraud Reichenberger E. K.",
    "wof:placetype":"venue"
},
  "geometry": {"coordinates":[10.5671844482,48.6126594543],"type":"Point"}
}