{
  "type": "Feature",
  "properties": {
    "iso:country":"DE",
    "sg:address":"Kurt-Schumacher-Str.13",
    "sg:city":"Troisdorf",
    "sg:phone":"+49 2241/978320",
    "sg:postcode":"53840",
    "sg:province":"Nordrhein-Westfalen",
    "wof:name":"Lanz&partner Communicationservices (inh.h.lanz)",
    "wof:placetype":"venue"
},
  "geometry": {"coordinates":[7.147921,50.799763],"type":"Point"}
}