{
  "type": "Feature",
  "properties": {
    "iso:country":"DE",
    "sg:address":"Koppersstr. 23",
    "sg:city":"D\u00fcsseldorf",
    "sg:phone":"+49 211/656098",
    "sg:postcode":"40549",
    "sg:province":"Nordrhein-Westfalen",
    "wof:name":"L\u00fcck Floristenbedarf Gmbh",
    "wof:placetype":"venue"
},
  "geometry": {"coordinates":[6.718873,51.233208],"type":"Point"}
}