{
  "type": "Feature",
  "properties": {
    "iso:country":"DE",
    "sg:address":"Innerer Graben 20",
    "sg:city":"W\u00fcrzburg",
    "sg:phone":"+49 931/53273",
    "sg:postcode":"97070",
    "sg:province":"Bayern",
    "wof:name":"Otto H\u00f6hn & S\u00f6hne Nachfolger",
    "wof:placetype":"venue"
},
  "geometry": {"coordinates":[9.929244,49.796314],"type":"Point"}
}