{
  "type": "Feature",
  "properties": {
    "iso:country":"DE",
    "sg:address":"Gewerbering 2",
    "sg:city":"Beilrode",
    "sg:postcode":"04886",
    "sg:province":"Sachsen",
    "wof:name":"Otb Baustoffcentrum Gmbh",
    "wof:placetype":"venue"
},
  "geometry": {"coordinates":[13.069705,51.584431],"type":"Point"}
}