{
  "type": "Feature",
  "properties": {
    "iso:country":"DE",
    "sg:address":"Dr.-C.-Otto-Str. 124",
    "sg:city":"Bochum",
    "sg:phone":"+49 234/496069",
    "sg:postcode":"44879",
    "sg:province":"Nordrhein-Westfalen",
    "wof:name":"Sonneneck",
    "wof:placetype":"venue"
},
  "geometry": {"coordinates":[7.1441907883,51.4266624451],"type":"Point"}
}