{
  "type": "Feature",
  "properties": {
    "iso:country":"DE",
    "sg:address":"M\u00fcllerweg 8",
    "sg:city":"M\u00fchlheim",
    "sg:phone":"+49 6108/705447",
    "sg:postcode":"63165",
    "sg:province":"Hessen",
    "wof:name":"Offenbacher Putzteufel",
    "wof:placetype":"venue"
},
  "geometry": {"coordinates":[8.836795,50.115597],"type":"Point"}
}