{
  "type": "Feature",
  "properties": {
    "iso:country":"DE",
    "sg:address":"Goldene Ringgasse 3",
    "sg:city":"Rothenburg",
    "sg:phone":"+49 9861/7200",
    "sg:postcode":"91541",
    "sg:province":"Bayern",
    "wof:name":"G\u00fcnter Schwarz Gmbh",
    "wof:placetype":"venue"
},
  "geometry": {"coordinates":[10.1810560226,49.3760604858],"type":"Point"}
}