{
  "type": "Feature",
  "properties": {
    "iso:country":"DE",
    "sg:address":"Eichelberg 1",
    "sg:city":"Freising",
    "sg:phone":"+49 8167/1210",
    "sg:postcode":"85354",
    "sg:province":"Bayern",
    "wof:name":"Martin Oberprieler",
    "wof:placetype":"venue"
},
  "geometry": {"coordinates":[11.731505,48.439129],"type":"Point"}
}