{
  "type": "Feature",
  "properties": {
    "iso:country":"DE",
    "sg:address":"Lindenbergstr. 4 A",
    "sg:city":"Altenhausen",
    "sg:phone":"+49 39052/6014",
    "sg:postcode":"39343",
    "sg:province":"Sachsen-Anhalt",
    "wof:name":"Tischlerei Horsika Gmbh",
    "wof:placetype":"venue"
},
  "geometry": {"coordinates":[11.256897,52.25946],"type":"Point"}
}