{
  "type": "Feature",
  "properties": {
    "iso:country":"DE",
    "sg:address":"W\u00f6rthstr. 9",
    "sg:city":"W\u00fcrzburg",
    "sg:phone":"+49 931/42374",
    "sg:postcode":"97082",
    "sg:province":"Bayern",
    "wof:name":"Postbaugenossenschaft W\u00fcrzburg Eg",
    "wof:placetype":"venue"
},
  "geometry": {"coordinates":[9.9162921906,49.7947273254],"type":"Point"}
}