{
  "type": "Feature",
  "properties": {
    "iso:country":"DE",
    "sg:address":"Dorfstr. 6",
    "sg:city":"Westertimke",
    "sg:phone":"+49 4289/236",
    "sg:postcode":"27412",
    "sg:province":"Niedersachsen",
    "wof:name":"Hermann Rugen",
    "wof:placetype":"venue"
},
  "geometry": {"coordinates":[9.131292,53.24131],"type":"Point"}
}