{
  "type": "Feature",
  "properties": {
    "iso:country":"DE",
    "sg:address":"Pelkovenstr. 57",
    "sg:city":"M\u00fcnchen",
    "sg:phone":"+49 89/1413673",
    "sg:postcode":"80992",
    "sg:province":"Bayern",
    "wof:name":"Restaurante Toscano Tre Pini",
    "wof:placetype":"venue"
},
  "geometry": {"coordinates":[11.5168790817,48.1817970276],"type":"Point"}
}