{
  "type": "Feature",
  "properties": {
    "iso:country":"DE",
    "sg:address":"Werkst\u00e4ttenstr. 13",
    "sg:city":"Recklinghausen",
    "sg:phone":"+49 2361/108296",
    "sg:postcode":"45659",
    "sg:province":"Nordrhein-Westfalen",
    "wof:name":"\u00d6ko-software Gmbh",
    "wof:placetype":"venue"
},
  "geometry": {"coordinates":[7.208427906,51.5972557068],"type":"Point"}
}