{
  "type": "Feature",
  "properties": {
    "iso:country":"DE",
    "sg:address":"Oberbenrader Str. 529",
    "sg:city":"Krefeld",
    "sg:phone":"+49 2151/816300",
    "sg:postcode":"47804",
    "sg:province":"Nordrhein-Westfalen",
    "wof:name":"Dos Or Die Recordings Gmbh",
    "wof:placetype":"venue"
},
  "geometry": {"coordinates":[6.516427,51.326965],"type":"Point"}
}