{
  "type": "Feature",
  "properties": {
    "iso:country":"DE",
    "sg:address":"Louis-Pasteur-Str. 1",
    "sg:city":"W\u00fcrzburg",
    "sg:phone":"+49 931/270140",
    "sg:postcode":"97076",
    "sg:province":"Bayern",
    "wof:name":"Milchwerke Mainfranken Eg",
    "wof:placetype":"venue"
},
  "geometry": {"coordinates":[9.997276,49.796284],"type":"Point"}
}