{
  "type": "Feature",
  "properties": {
    "iso:country":"DE",
    "sg:address":"Scheunenweg 1",
    "sg:city":"Mittenwalde",
    "sg:phone":"+49 33764/60905",
    "sg:postcode":"15749",
    "sg:province":"Brandenburg",
    "wof:name":"Pro-pac Ostendorf Plastic Thermoformfolien Und",
    "wof:placetype":"venue"
},
  "geometry": {"coordinates":[13.538611412,52.2706680298],"type":"Point"}
}