{
  "type": "Feature",
  "properties": {
    "iso:country":"DE",
    "sg:address":"Anzinger Str. 3",
    "sg:city":"Poing",
    "sg:phone":"+49 8121/80788",
    "sg:postcode":"85586",
    "sg:province":"Bayern",
    "wof:name":"Hl-markt Warenhandels- Gmbh",
    "wof:placetype":"venue"
},
  "geometry": {"coordinates":[11.8187494278,48.1704673767],"type":"Point"}
}