{
  "type": "Feature",
  "properties": {
    "iso:country":"DE",
    "sg:address":"Bahnhofstr. 18",
    "sg:city":"Burgthann",
    "sg:phone":"+49 9183/950043",
    "sg:postcode":"90559",
    "sg:province":"Bayern",
    "wof:name":"Erika Bruhn Krankengymnastin",
    "wof:placetype":"venue"
},
  "geometry": {"coordinates":[11.310562,49.348888],"type":"Point"}
}