{
  "type": "Feature",
  "properties": {
    "iso:country":"DE",
    "sg:address":"Mozartstr. 6",
    "sg:city":"Kamen",
    "sg:phone":"+49 2307/3489",
    "sg:postcode":"59174",
    "sg:province":"Nordrhein-Westfalen",
    "wof:name":"Cpd-baustoffhandel Und Transporte Gmbh",
    "wof:placetype":"venue"
},
  "geometry": {"coordinates":[7.606227,51.569656],"type":"Point"}
}