{
  "type": "Feature",
  "properties": {
    "iso:country":"DE",
    "sg:address":"Diezstr. 4a",
    "sg:city":"Stuttgart",
    "sg:phone":"+49 711/741061",
    "sg:postcode":"70565",
    "sg:province":"Baden-W\u00fcrttemberg",
    "wof:name":"Europa-sprachclub Gmbh",
    "wof:placetype":"venue"
},
  "geometry": {"coordinates":[9.105093956,48.7161026001],"type":"Point"}
}