{
  "type": "Feature",
  "properties": {
    "iso:country":"DE",
    "sg:address":"Benderstr. 136",
    "sg:city":"D\u00fcsseldorf",
    "sg:phone":"+49 211/287257",
    "sg:postcode":"40625",
    "sg:province":"Nordrhein-Westfalen",
    "wof:name":"Haus Wicharz",
    "wof:placetype":"venue"
},
  "geometry": {"coordinates":[6.8468542099,51.2391967773],"type":"Point"}
}