{
  "type": "Feature",
  "properties": {
    "iso:country":"DE",
    "sg:address":"Am Gro\u00dfen Geeren 42",
    "sg:city":"Ritterhude",
    "sg:phone":"+49 4292/2444",
    "sg:postcode":"27721",
    "sg:province":"Niedersachsen",
    "wof:name":"Kreissparkasse Osterholz",
    "wof:placetype":"venue"
},
  "geometry": {"coordinates":[8.749618,53.187279],"type":"Point"}
}