{
  "type": "Feature",
  "properties": {
    "iso:country":"DE",
    "sg:address":"Oberneulander Heerstr. 80",
    "sg:city":"Bremen",
    "sg:phone":"+49 421/2574775",
    "sg:postcode":"28355",
    "sg:province":"Bremen",
    "wof:name":"Roland Gmbh",
    "wof:placetype":"venue"
},
  "geometry": {"coordinates":[8.907815,53.10157],"type":"Point"}
}