{
  "type": "Feature",
  "properties": {
    "iso:country":"DE",
    "sg:address":"Holzstr 5",
    "sg:city":"M\u00fclheim",
    "sg:phone":"+49 208/997066",
    "sg:postcode":"45479",
    "sg:province":"Nordrhein-Westfalen",
    "wof:name":"Klaus Brenzel Beschallungstechnik Gmbh",
    "wof:placetype":"venue"
},
  "geometry": {"coordinates":[6.8699951172,51.4230155945],"type":"Point"}
}