{
  "type": "Feature",
  "properties": {
    "iso:country":"DE",
    "sg:address":"Zeitlbergstr. 38",
    "sg:city":"Zeitlarn",
    "sg:phone":"+49 941/63304",
    "sg:postcode":"93197",
    "sg:province":"Bayern",
    "wof:name":"Dr. Otto Kronthaler Tierarzt",
    "wof:placetype":"venue"
},
  "geometry": {"coordinates":[12.1061954498,49.0717163086],"type":"Point"}
}