{
  "type": "Feature",
  "properties": {
    "iso:country":"DE",
    "sg:address":"N\u00f6rdlinger Str. 7",
    "sg:city":"Rothenburg",
    "sg:phone":"+49 9861/93939",
    "sg:postcode":"91541",
    "sg:province":"Bayern",
    "wof:name":"Deutsche Shell Ag",
    "wof:placetype":"venue"
},
  "geometry": {"coordinates":[10.1831188202,49.3690605164],"type":"Point"}
}