{
  "type": "Feature",
  "properties": {
    "iso:country":"DE",
    "sg:address":"Parkstr. 123",
    "sg:city":"L\u00fcdenscheid",
    "sg:phone":"+49 2351/21931",
    "sg:postcode":"58509",
    "sg:province":"Nordrhein-Westfalen",
    "wof:name":"Guttempler Bergstadt",
    "wof:placetype":"venue"
},
  "geometry": {"coordinates":[7.6058049202,51.2150344849],"type":"Point"}
}