{
  "type": "Feature",
  "properties": {
    "iso:country":"DE",
    "sg:address":"Christgasse 13",
    "sg:city":"Jagstzell",
    "sg:phone":"+49 7967/6393",
    "sg:postcode":"73489",
    "sg:province":"Baden-W\u00fcrttemberg",
    "wof:name":"Hans Schwarz",
    "wof:placetype":"venue"
},
  "geometry": {"coordinates":[10.0974054337,49.0269126892],"type":"Point"}
}