{
  "type": "Feature",
  "properties": {
    "iso:country":"DE",
    "sg:address":"Xantener Str. 79",
    "sg:city":"Rheinberg",
    "sg:phone":"+49 2843/6153",
    "sg:postcode":"47495",
    "sg:province":"Nordrhein-Westfalen",
    "wof:name":"Jakob Kempken S\u00e4gewerk Holzhandlung",
    "wof:placetype":"venue"
},
  "geometry": {"coordinates":[6.5943851471,51.5526695251],"type":"Point"}
}