{
  "type": "Feature",
  "properties": {
    "iso:country":"DE",
    "sg:address":"Erpftinger Str.",
    "sg:city":"Landsberg",
    "sg:phone":"+49 8191/2507",
    "sg:postcode":"86899",
    "sg:province":"Bayern",
    "wof:name":"L. Moritz",
    "wof:placetype":"venue"
},
  "geometry": {"coordinates":[10.8584899902,48.0379600525],"type":"Point"}
}