{
  "type": "Feature",
  "properties": {
    "iso:country":"DE",
    "sg:address":"Reichspr\u00e4sidentenstr. 21-25",
    "sg:city":"M\u00fclheim",
    "sg:phone":"+49 208/390626",
    "sg:postcode":"45470",
    "sg:province":"Nordrhein-Westfalen",
    "wof:name":"Moveable Gesellschaft F\u00fcr Elektronische",
    "wof:placetype":"venue"
},
  "geometry": {"coordinates":[6.8941907883,51.4176712036],"type":"Point"}
}