{
  "type": "Feature",
  "properties": {
    "iso:country":"DE",
    "sg:address":"Sternstr. 19",
    "sg:city":"Gaimersheim",
    "sg:postcode":"85080",
    "sg:province":"Bayern",
    "wof:name":"Die Website Gmbh",
    "wof:placetype":"venue"
},
  "geometry": {"coordinates":[11.371655,48.78513],"type":"Point"}
}