{
  "type": "Feature",
  "properties": {
    "iso:country":"DE",
    "sg:address":"Wiesenstr. 12",
    "sg:city":"Jena",
    "sg:postcode":"07749",
    "sg:province":"Th\u00fcringen",
    "wof:name":"Sekund\u00e4rrohstofferfassung",
    "wof:placetype":"venue"
},
  "geometry": {"coordinates":[11.595489,50.936253],"type":"Point"}
}