{
  "type": "Feature",
  "properties": {
    "iso:country":"DE",
    "sg:address":"Eichendorffstr. 13",
    "sg:city":"K\u00f6then",
    "sg:phone":"+49 3496/555153",
    "sg:postcode":"06366",
    "sg:province":"Sachsen-Anhalt",
    "wof:name":"R\u00fcdiger Heinol",
    "wof:placetype":"venue"
},
  "geometry": {"coordinates":[11.9634122849,51.7477111816],"type":"Point"}
}