{
  "type": "Feature",
  "properties": {
    "iso:country":"DE",
    "sg:address":"Zur Finkenkuhle 25",
    "sg:city":"Salzgitter",
    "sg:postcode":"38259",
    "sg:province":"Niedersachsen",
    "wof:name":"Bs Beteiligungs Gmbh",
    "wof:placetype":"venue"
},
  "geometry": {"coordinates":[10.361909,52.046616],"type":"Point"}
}