{
  "type": "Feature",
  "properties": {
    "iso:country":"DE",
    "sg:address":"Goseplack 7",
    "sg:city":"Hardegsen",
    "sg:phone":"+49 4955/051305",
    "sg:postcode":"37181",
    "sg:province":"Niedersachsen",
    "wof:name":"Peter Becker Spielger\u00c4te U. Gartenm\u00d6bel",
    "wof:placetype":"venue"
},
  "geometry": {"coordinates":[9.8296251297,51.6505432129],"type":"Point"}
}