{
  "type": "Feature",
  "properties": {
    "iso:country":"DE",
    "sg:address":"Boschstr. 9",
    "sg:city":"L\u00fcbbecke",
    "sg:phone":"+49 5741/12061",
    "sg:postcode":"32312",
    "sg:province":"Nordrhein-Westfalen",
    "wof:name":"Blase Gmbh & Co. Kg",
    "wof:placetype":"venue"
},
  "geometry": {"coordinates":[8.622077,52.329517],"type":"Point"}
}