{
  "type": "Feature",
  "properties": {
    "iso:country":"DE",
    "sg:address":"Bolland 26",
    "sg:city":"Nordkirchen",
    "sg:phone":"+49 2596/98305",
    "sg:postcode":"59394",
    "sg:province":"Nordrhein-Westfalen",
    "wof:name":"Gia Gmbh",
    "wof:placetype":"venue"
},
  "geometry": {"coordinates":[7.5177469254,51.7310371399],"type":"Point"}
}