{
  "type": "Feature",
  "properties": {
    "iso:country":"DE",
    "sg:address":"Wilhelmstr. 27",
    "sg:city":"Ludwigsburg",
    "sg:postcode":"71638",
    "sg:province":"Baden-W\u00fcrttemberg",
    "wof:name":"Werbe-tex E. Simsek E. K.",
    "wof:placetype":"venue"
},
  "geometry": {"coordinates":[9.1872472763,48.8960494995],"type":"Point"}
}