{
  "type": "Feature",
  "properties": {
    "iso:country":"DE",
    "sg:address":"Tegelbergstr. 16",
    "sg:city":"F\u00fcssen",
    "sg:phone":"+49 8362/7339",
    "sg:postcode":"87629",
    "sg:province":"Bayern",
    "wof:name":"Hilde K\u00f6pf",
    "wof:placetype":"venue"
},
  "geometry": {"coordinates":[10.70517,47.573212],"type":"Point"}
}