{
  "type": "Feature",
  "properties": {
    "iso:country":"DE",
    "sg:address":"Ludwigstr. 8",
    "sg:city":"Filderstadt",
    "sg:postcode":"70794",
    "sg:province":"Baden-W\u00fcrttemberg",
    "wof:name":"Agentur Hofmann",
    "wof:placetype":"venue"
},
  "geometry": {"coordinates":[9.2153100967,48.6747741699],"type":"Point"}
}