{
  "type": "Feature",
  "properties": {
    "iso:country":"DE",
    "sg:address":"Ammertalstr. 18",
    "sg:city":"Rottenburg",
    "sg:phone":"+49 7472/24840",
    "sg:postcode":"72108",
    "sg:province":"Baden-W\u00fcrttemberg",
    "wof:name":"Wolfgang H. Storz Wirtschaftspr\u00fcfer",
    "wof:placetype":"venue"
},
  "geometry": {"coordinates":[8.9722223282,48.5091705322],"type":"Point"}
}