{
  "type": "Feature",
  "properties": {
    "iso:country":"DE",
    "sg:address":"An der Garnbleiche 5",
    "sg:city":"D\u00fcren",
    "sg:phone":"+49 2421/54903",
    "sg:postcode":"52349",
    "sg:province":"Nordrhein-Westfalen",
    "wof:name":"Gebr. Rath Schlosserei Metallbau Gmbh",
    "wof:placetype":"venue"
},
  "geometry": {"coordinates":[6.482805,50.804684],"type":"Point"}
}