{
  "type": "Feature",
  "properties": {
    "iso:country":"DE",
    "sg:address":"Erholungspark Nord-Elm",
    "sg:city":"R\u00e4bke",
    "sg:phone":"+49 5355/8352",
    "sg:postcode":"38375",
    "sg:province":"Niedersachsen",
    "wof:name":"Camping Nord-elm",
    "wof:placetype":"venue"
},
  "geometry": {"coordinates":[10.864735,52.194164],"type":"Point"}
}