{
  "type": "Feature",
  "properties": {
    "iso:country":"DE",
    "sg:address":"Breite Str. 4",
    "sg:city":"Peine",
    "sg:phone":"+49 5171/41911",
    "sg:postcode":"31224",
    "sg:province":"Niedersachsen",
    "wof:name":"Arko Gmbh",
    "wof:placetype":"venue"
},
  "geometry": {"coordinates":[10.2260847092,52.3227005005],"type":"Point"}
}