{
  "type": "Feature",
  "properties": {
    "iso:country":"DE",
    "sg:address":"Hauptstr. 25",
    "sg:city":"Tarmstedt",
    "sg:phone":"+49 4283/8806",
    "sg:postcode":"27412",
    "sg:province":"Niedersachsen",
    "wof:name":"Latzke",
    "wof:placetype":"venue"
},
  "geometry": {"coordinates":[9.078598,53.226543],"type":"Point"}
}