{
  "type": "Feature",
  "properties": {
    "iso:country":"DE",
    "sg:address":"In der Flur",
    "sg:city":"Gerstungen",
    "sg:postcode":"99834",
    "sg:province":"Th\u00fcringen",
    "wof:name":"Agrargenossenschaft Gerstungen Eg",
    "wof:placetype":"venue"
},
  "geometry": {"coordinates":[10.07452,50.971554],"type":"Point"}
}