{
  "type": "Feature",
  "properties": {
    "iso:country":"DE",
    "sg:address":"Pariser Str. 101",
    "sg:city":"Nieder-Olm",
    "sg:phone":"+49 6136/95010",
    "sg:postcode":"55268",
    "sg:province":"Rheinland-Pfalz",
    "wof:name":"E. Flashaar-bl\u00f6dorm Inh. Hans-dieter Hauptmann",
    "wof:placetype":"venue"
},
  "geometry": {"coordinates":[8.2024612427,49.9092636108],"type":"Point"}
}