{
  "type": "Feature",
  "properties": {
    "iso:country":"DE",
    "sg:address":"Beurener Str. 49",
    "sg:city":"Pfaffenhofen",
    "sg:phone":"+49 7302/5124",
    "sg:postcode":"89284",
    "sg:province":"Bayern",
    "wof:name":"Georg Bolkart",
    "wof:placetype":"venue"
},
  "geometry": {"coordinates":[10.1892623901,48.3582496643],"type":"Point"}
}