{
  "type": "Feature",
  "properties": {
    "iso:country":"DE",
    "sg:address":"Hackenberger Str. 107",
    "sg:city":"Remscheid",
    "sg:postcode":"42897",
    "sg:province":"Nordrhein-Westfalen",
    "wof:name":"Arbeitsgemeinschaft F\u00fcr Kardiologische Rehabilitation",
    "wof:placetype":"venue"
},
  "geometry": {"coordinates":[7.2766327858,51.1994934082],"type":"Point"}
}