{
  "type": "Feature",
  "properties": {
    "iso:country":"DE",
    "sg:address":"Haagweg 20",
    "sg:city":"\u00d6hringen",
    "sg:postcode":"74613",
    "sg:province":"Baden-W\u00fcrttemberg",
    "wof:name":"Schaller & Riedling Treuhand Gmbh",
    "wof:placetype":"venue"
},
  "geometry": {"coordinates":[9.5045223236,49.2014503479],"type":"Point"}
}