{
  "type": "Feature",
  "properties": {
    "iso:country":"DE",
    "sg:address":"Im Lothringen 4",
    "sg:city":"Losheim",
    "sg:phone":"+49 6872/4352",
    "sg:postcode":"66679",
    "sg:province":"Saarland",
    "wof:name":"Pension Hilde Schramm",
    "wof:placetype":"venue"
},
  "geometry": {"coordinates":[6.7601032257,49.5514564514],"type":"Point"}
}