{
  "type": "Feature",
  "properties": {
    "iso:country":"DE",
    "sg:address":"Adenauerplatz 7",
    "sg:city":"Hennef",
    "sg:phone":"+49 2242/83733",
    "sg:postcode":"53773",
    "sg:province":"Nordrhein-Westfalen",
    "wof:name":"Match 1",
    "wof:placetype":"venue"
},
  "geometry": {"coordinates":[7.2842469215,50.7741012573],"type":"Point"}
}