{
  "type": "Feature",
  "properties": {
    "iso:country":"DE",
    "sg:address":"Bahnhofstr. 9",
    "sg:city":"Oschatz",
    "sg:phone":"+49 3435/622712",
    "sg:postcode":"04758",
    "sg:province":"Sachsen",
    "wof:name":"Marien-apotheke",
    "wof:placetype":"venue"
},
  "geometry": {"coordinates":[13.108028,51.303772],"type":"Point"}
}