{
  "type": "Feature",
  "properties": {
    "iso:country":"DE",
    "sg:address":"Rathausplatz 4-5",
    "sg:city":"Unterw\u00f6ssen",
    "sg:postcode":"83246",
    "sg:province":"Bayern",
    "wof:name":"D\u00f6llerer-verwaltungs-gmbh",
    "wof:placetype":"venue"
},
  "geometry": {"coordinates":[12.4565620422,47.7355384827],"type":"Point"}
}