{
  "type": "Feature",
  "properties": {
    "iso:country":"DE",
    "sg:address":"Untere Haspelstr. 22",
    "sg:city":"Waldshut-Tiengen",
    "sg:phone":"+49 7751/3936",
    "sg:postcode":"79761",
    "sg:province":"Baden-W\u00fcrttemberg",
    "wof:name":"Ev. Freikirchl. Pfarramt",
    "wof:placetype":"venue"
},
  "geometry": {"coordinates":[8.2060785294,47.6241340637],"type":"Point"}
}