{
  "type": "Feature",
  "properties": {
    "iso:country":"DE",
    "sg:address":"Am Layerhof 7",
    "sg:city":"Mayen",
    "sg:phone":"+49 2651/41829",
    "sg:postcode":"56727",
    "sg:province":"Rheinland-Pfalz",
    "wof:name":"Dagmar Nagelsky",
    "wof:placetype":"venue"
},
  "geometry": {"coordinates":[7.242064,50.332001],"type":"Point"}
}