{
  "type": "Feature",
  "properties": {
    "iso:country":"DE",
    "sg:address":"Kiefernallee 20-21",
    "sg:city":"Neuenhagen",
    "sg:phone":"+49 3342/80317",
    "sg:postcode":"15366",
    "sg:province":"Brandenburg",
    "wof:name":"L. K\u00e4mmer",
    "wof:placetype":"venue"
},
  "geometry": {"coordinates":[13.6837253571,52.5092391968],"type":"Point"}
}