{
  "type": "Feature",
  "properties": {
    "iso:country":"DE",
    "sg:address":"Seerau im Drawehn 2",
    "sg:city":"K\u00fcsten",
    "sg:phone":"+49 5841/974780",
    "sg:postcode":"29482",
    "sg:province":"Niedersachsen",
    "wof:name":"Brigitte Paartz",
    "wof:placetype":"venue"
},
  "geometry": {"coordinates":[11.0724554062,52.9599266052],"type":"Point"}
}