{
  "type": "Feature",
  "properties": {
    "iso:country":"DE",
    "sg:address":"Karl-H\u00fcller-Str 25",
    "sg:city":"Ludwigsburg",
    "sg:phone":"+49 7141/41544",
    "sg:postcode":"71636",
    "sg:province":"Baden-W\u00fcrttemberg",
    "wof:name":"Rudolf K\u00f6nig",
    "wof:placetype":"venue"
},
  "geometry": {"coordinates":[9.174707,48.891529],"type":"Point"}
}