{
  "type": "Feature",
  "properties": {
    "iso:country":"DE",
    "sg:address":"Gr\u00fcnkraut",
    "sg:city":"Gr\u00fcnkraut",
    "sg:phone":"+49 4975/16924",
    "sg:postcode":"88287",
    "sg:province":"Baden-W\u00fcrttemberg",
    "wof:name":"Kreissparkasse Bodnegger Str. 2",
    "wof:placetype":"venue"
},
  "geometry": {"coordinates":[9.654682,47.741009],"type":"Point"}
}