{
  "type": "Feature",
  "properties": {
    "iso:country":"DE",
    "sg:address":"Rosenweg 4",
    "sg:city":"B\u00fcchen",
    "sg:phone":"+49 4155/6774",
    "sg:postcode":"21514",
    "sg:province":"Schleswig-Holstein",
    "wof:name":"Jm Hardwarekonzepte Gmbh",
    "wof:placetype":"venue"
},
  "geometry": {"coordinates":[10.6224794388,53.4726104736],"type":"Point"}
}