{
  "type": "Feature",
  "properties": {
    "iso:country":"DE",
    "sg:address":"E 5",
    "sg:city":"Mannheim",
    "sg:postcode":"68159",
    "sg:province":"Baden-W\u00fcrttemberg",
    "wof:name":"Studien-institut Rhein- Neckar Ggmbh",
    "wof:placetype":"venue"
},
  "geometry": {"coordinates":[8.45383,49.496361],"type":"Point"}
}