{
  "type": "Feature",
  "properties": {
    "iso:country":"DE",
    "sg:address":"Im Gosewinkel 15",
    "sg:city":"Hannover",
    "sg:phone":"+49 511/572750",
    "sg:postcode":"30627",
    "sg:province":"Niedersachsen",
    "wof:name":"Horst Becker",
    "wof:placetype":"venue"
},
  "geometry": {"coordinates":[9.822128,52.389534],"type":"Point"}
}