{
  "type": "Feature",
  "properties": {
    "iso:country":"DE",
    "sg:address":"Gro\u00dfbeerenstr. 16",
    "sg:city":"Potsdam",
    "sg:postcode":"14482",
    "sg:province":"Brandenburg",
    "wof:name":"Inter Krankenversicherung",
    "wof:placetype":"venue"
},
  "geometry": {"coordinates":[13.0924854279,52.3894386292],"type":"Point"}
}