{
  "type": "Feature",
  "properties": {
    "iso:country":"DE",
    "sg:address":"Jahnstr. 5",
    "sg:city":"Nordhausen",
    "sg:phone":"+49 3631/89180",
    "sg:postcode":"99734",
    "sg:province":"Th\u00fcringen",
    "wof:name":"Jens Otto Rechtsanwalt",
    "wof:placetype":"venue"
},
  "geometry": {"coordinates":[10.8086700439,51.5042114258],"type":"Point"}
}