{
  "type": "Feature",
  "properties": {
    "iso:country":"DE",
    "sg:address":"Kaiserallee 111",
    "sg:city":"Karlsruhe",
    "sg:phone":"+49 721/985200",
    "sg:postcode":"76185",
    "sg:province":"Baden-W\u00fcrttemberg",
    "wof:name":"Ipg Automotive Engineering Software Und Consulting Gmbh",
    "wof:placetype":"venue"
},
  "geometry": {"coordinates":[8.3690757751,49.0109901428],"type":"Point"}
}