{
  "type": "Feature",
  "properties": {
    "iso:country":"DE",
    "sg:address":"Kaiserstr. 10",
    "sg:city":"K\u00f6nigswinter",
    "sg:phone":"+49 2223/21172",
    "sg:postcode":"53639",
    "sg:province":"Nordrhein-Westfalen",
    "wof:name":"Werner Lemmerz",
    "wof:placetype":"venue"
},
  "geometry": {"coordinates":[7.191914,50.678715],"type":"Point"}
}