{
  "type": "Feature",
  "properties": {
    "iso:country":"DE",
    "sg:address":"Schlosserstr. 42",
    "sg:city":"Alsdorf",
    "sg:phone":"+49 2404/22623",
    "sg:postcode":"52477",
    "sg:province":"Nordrhein-Westfalen",
    "wof:name":"Heinz-josef Errenst",
    "wof:placetype":"venue"
},
  "geometry": {"coordinates":[6.158609,50.879173],"type":"Point"}
}