{
  "type": "Feature",
  "properties": {
    "iso:country":"DE",
    "sg:address":"Kiebitzstr. 33",
    "sg:city":"Herford",
    "sg:phone":"+49 5221/54076",
    "sg:postcode":"32051",
    "sg:province":"Nordrhein-Westfalen",
    "wof:name":"Die Brot-kate",
    "wof:placetype":"venue"
},
  "geometry": {"coordinates":[8.649781,52.128086],"type":"Point"}
}