{
  "type": "Feature",
  "properties": {
    "iso:country":"DE",
    "sg:address":"Weiherstr. 7",
    "sg:city":"Bayreuth",
    "sg:phone":"+49 921/22029",
    "sg:postcode":"95448",
    "sg:province":"Bayern",
    "wof:name":"S\u00fcd-treibstoff Mineral\u00f6lhandelsgesellschaft",
    "wof:placetype":"venue"
},
  "geometry": {"coordinates":[11.5990285873,49.9593772888],"type":"Point"}
}