{
  "type": "Feature",
  "properties": {
    "iso:country":"DE",
    "sg:address":"Immermannstr. 23",
    "sg:city":"D\u00fcsseldorf",
    "sg:postcode":"40210",
    "sg:province":"Nordrhein-Westfalen",
    "wof:name":"Delta Management Holding Gmbh",
    "wof:placetype":"venue"
},
  "geometry": {"coordinates":[6.78729,51.223976],"type":"Point"}
}