{
  "type": "Feature",
  "properties": {
    "iso:country":"DE",
    "sg:address":"Staudenweg 22",
    "sg:city":"Bielefeld",
    "sg:phone":"+49 521/771877",
    "sg:postcode":"33729",
    "sg:province":"Nordrhein-Westfalen",
    "wof:name":"Erich Bartels Elektromstr.",
    "wof:placetype":"venue"
},
  "geometry": {"coordinates":[8.592167,52.076668],"type":"Point"}
}