{
  "type": "Feature",
  "properties": {
    "iso:country":"DE",
    "sg:address":"Dentersstra\u00dfe 1",
    "sg:city":"Biederbach",
    "sg:phone":"+49 4976/82",
    "sg:postcode":"79215",
    "sg:province":"Baden-W\u00fcrttemberg",
    "wof:name":"Rihaplastic Gmbh",
    "wof:placetype":"venue"
},
  "geometry": {"coordinates":[8.0445203781,48.2036247253],"type":"Point"}
}