{
  "type": "Feature",
  "properties": {
    "iso:country":"DE",
    "sg:address":"89605",
    "sg:city":"Altheim",
    "sg:postcode":"89605",
    "sg:province":"Baden-W\u00fcrttemberg",
    "wof:name":"Kath. Pfarramt St. Michael",
    "wof:placetype":"venue"
},
  "geometry": {"coordinates":[9.7693519592,48.32762146],"type":"Point"}
}