{
  "type": "Feature",
  "properties": {
    "iso:country":"DE",
    "sg:address":"Milanweg 42",
    "sg:city":"Oldenburg",
    "sg:phone":"+49 441/3047484",
    "sg:postcode":"26127",
    "sg:province":"Niedersachsen",
    "wof:name":"Kr\u00e4ft Immobilien",
    "wof:placetype":"venue"
},
  "geometry": {"coordinates":[8.2131175995,53.1736755371],"type":"Point"}
}