{
  "type": "Feature",
  "properties": {
    "iso:country":"DE",
    "sg:address":"Franz-Hoffmann-Str. 8",
    "sg:city":"Neuburg an der Donau",
    "sg:phone":"+49 700",
    "sg:postcode":"86633",
    "sg:province":"Bayern",
    "wof:name":"Ah-tech, It Service",
    "wof:placetype":"venue"
},
  "geometry": {"coordinates":[11.193186,48.730015],"type":"Point"}
}