{
  "type": "Feature",
  "properties": {
    "iso:country":"DE",
    "sg:address":"Altvaterstr. 25",
    "sg:city":"Wetzlar",
    "sg:postcode":"35579",
    "sg:province":"Hessen",
    "wof:name":"Hom\u00f6omed Vital Center Gmbh",
    "wof:placetype":"venue"
},
  "geometry": {"coordinates":[8.4523620605,50.5421676636],"type":"Point"}
}