{
  "type": "Feature",
  "properties": {
    "iso:country":"DE",
    "sg:address":"Heubergstr. 5",
    "sg:city":"Bruckm\u00fchl",
    "sg:phone":"+49 8062/4611",
    "sg:postcode":"83052",
    "sg:province":"Bayern",
    "wof:name":"Dori-titus Constantiniuc Architekt",
    "wof:placetype":"venue"
},
  "geometry": {"coordinates":[11.948233,47.865471],"type":"Point"}
}