{
  "type": "Feature",
  "properties": {
    "iso:country":"DE",
    "sg:address":"Nieder-Ramst\u00e4dter Str. 13",
    "sg:city":"Darmstadt",
    "sg:phone":"+49 6151/41448",
    "sg:postcode":"64283",
    "sg:province":"Hessen",
    "wof:name":"Al Caminetto",
    "wof:placetype":"venue"
},
  "geometry": {"coordinates":[8.6580200195,49.8692245483],"type":"Point"}
}