{
  "type": "Feature",
  "properties": {
    "iso:country":"DE",
    "sg:address":"Querstr. 7",
    "sg:city":"L\u00fcbbecke",
    "sg:phone":"+49 5741/6741",
    "sg:postcode":"32312",
    "sg:province":"Nordrhein-Westfalen",
    "wof:name":"R. Ottenberg",
    "wof:placetype":"venue"
},
  "geometry": {"coordinates":[8.6639842987,52.3085212708],"type":"Point"}
}