{
  "type": "Feature",
  "properties": {
    "iso:country":"DE",
    "sg:address":"Birkunger Str.",
    "sg:city":"Dingelst\u00e4dt",
    "sg:postcode":"37351",
    "sg:province":"Th\u00fcringen",
    "wof:name":"Bhg",
    "wof:placetype":"venue"
},
  "geometry": {"coordinates":[10.32194,51.320644],"type":"Point"}
}