{
  "type": "Feature",
  "properties": {
    "iso:country":"DE",
    "sg:address":"Hahnerheide 1",
    "sg:city":"Marburg",
    "sg:phone":"+49 6424/5652",
    "sg:postcode":"35043",
    "sg:province":"Hessen",
    "wof:name":"Heinrich Bohl",
    "wof:placetype":"venue"
},
  "geometry": {"coordinates":[8.806831,50.771675],"type":"Point"}
}