{
  "type": "Feature",
  "properties": {
    "iso:country":"DE",
    "sg:address":"Donaustetter Str. 9/2",
    "sg:city":"Erbach",
    "sg:phone":"+49 7305/919117",
    "sg:postcode":"89155",
    "sg:province":"Baden-W\u00fcrttemberg",
    "wof:name":"G. Hummler",
    "wof:placetype":"venue"
},
  "geometry": {"coordinates":[9.893119812,48.328502655],"type":"Point"}
}