{
  "type": "Feature",
  "properties": {
    "iso:country":"DE",
    "sg:address":"Nordstr. 60",
    "sg:city":"Werther",
    "sg:phone":"+49 5203/7850",
    "sg:postcode":"33824",
    "sg:province":"Nordrhein-Westfalen",
    "wof:name":"Thomas Heidemann",
    "wof:placetype":"venue"
},
  "geometry": {"coordinates":[8.4099779129,52.079120636],"type":"Point"}
}