{
  "type": "Feature",
  "properties": {
    "iso:country":"DE",
    "sg:address":"Alnwicker Ring 2",
    "sg:city":"Voerde",
    "sg:phone":"+49 2855/82079",
    "sg:postcode":"46562",
    "sg:province":"Nordrhein-Westfalen",
    "wof:name":"Alnwicker Hof",
    "wof:placetype":"venue"
},
  "geometry": {"coordinates":[6.6841979027,51.5978851318],"type":"Point"}
}