{
  "type": "Feature",
  "properties": {
    "iso:country":"DE",
    "sg:address":"G\u00f6gginger Str.",
    "sg:city":"Bad F\u00fcssing",
    "sg:phone":"+49 8538/805",
    "sg:postcode":"94072",
    "sg:province":"Bayern",
    "wof:name":"Bradlwirt",
    "wof:placetype":"venue"
},
  "geometry": {"coordinates":[13.3642978668,48.3592605591],"type":"Point"}
}