{
  "type": "Feature",
  "properties": {
    "iso:country":"DE",
    "sg:address":"Sandhofstr.",
    "sg:city":"B\u00fcdingen",
    "sg:phone":"+49 6042/2386",
    "sg:postcode":"63654",
    "sg:province":"Hessen",
    "wof:name":"Gastwirtschaft Fritz Nos",
    "wof:placetype":"venue"
},
  "geometry": {"coordinates":[9.0908050537,50.3100547791],"type":"Point"}
}