{
  "type": "Feature",
  "properties": {
    "iso:country":"DE",
    "sg:address":"Muskauer Str. 74",
    "sg:city":"Wei\u00dfwasser",
    "sg:phone":"+49 3576/208443",
    "sg:postcode":"02943",
    "sg:province":"Sachsen",
    "wof:name":"Fielmann Ag & Co.",
    "wof:placetype":"venue"
},
  "geometry": {"coordinates":[14.642237,51.505356],"type":"Point"}
}