{
  "type": "Feature",
  "properties": {
    "iso:country":"DE",
    "sg:address":"Rabegasse 2",
    "sg:city":"Gr\u00fcnberg",
    "sg:phone":"+49 6401/1444",
    "sg:postcode":"35305",
    "sg:province":"Hessen",
    "wof:name":"Philipp M\u00fcller-hillebrand Steuerberater",
    "wof:placetype":"venue"
},
  "geometry": {"coordinates":[8.9602470398,50.5909919739],"type":"Point"}
}