{
  "type": "Feature",
  "properties": {
    "iso:country":"DE",
    "sg:address":"Bahnhofplatz",
    "sg:city":"Pforzheim",
    "sg:phone":"+49 7231/314732",
    "sg:postcode":"75175",
    "sg:province":"Baden-W\u00fcrttemberg",
    "wof:name":"Handelshaus F\u00fcr Reise Und Verkehr Dr. Eckert & Co.",
    "wof:placetype":"venue"
},
  "geometry": {"coordinates":[8.7032060623,48.8932762146],"type":"Point"}
}