{
  "type": "Feature",
  "properties": {
    "iso:country":"DE",
    "sg:address":"Geibeltstr. 3",
    "sg:city":"Pirna",
    "sg:phone":"+49 3501/445505",
    "sg:postcode":"01796",
    "sg:province":"Sachsen",
    "wof:name":"Bbn Baumaschinen Bauger\u00e4te Und Nutzfahrzeugehandel Gmbh",
    "wof:placetype":"venue"
},
  "geometry": {"coordinates":[13.924837,50.958736],"type":"Point"}
}