{
  "type": "Feature",
  "properties": {
    "iso:country":"DE",
    "sg:address":"Laventiestr. 9",
    "sg:city":"Iserlohn",
    "sg:phone":"+49 2371/42889",
    "sg:postcode":"58640",
    "sg:province":"Nordrhein-Westfalen",
    "wof:name":"Karl-heinz Schr\u00f6der",
    "wof:placetype":"venue"
},
  "geometry": {"coordinates":[7.712418,51.418861],"type":"Point"}
}