{
  "type": "Feature",
  "properties": {
    "iso:country":"DE",
    "sg:address":"Meerwiesenstr. 47",
    "sg:city":"Herzebrock-Clarholz",
    "sg:phone":"+49 5245/4582",
    "sg:postcode":"33442",
    "sg:province":"Nordrhein-Westfalen",
    "wof:name":"Jaekel",
    "wof:placetype":"venue"
},
  "geometry": {"coordinates":[8.235555,51.881615],"type":"Point"}
}