{
  "type": "Feature",
  "properties": {
    "iso:country":"DE",
    "sg:address":"Triftstr. 51",
    "sg:city":"Osnabr\u00fcck",
    "sg:phone":"+49 541/126274",
    "sg:postcode":"49090",
    "sg:province":"Niedersachsen",
    "wof:name":"Webeler Heizung Und Sanit\u00e4r Verwalt.-",
    "wof:placetype":"venue"
},
  "geometry": {"coordinates":[7.994899,52.300304],"type":"Point"}
}