{
  "type": "Feature",
  "properties": {
    "iso:country":"DE",
    "sg:address":"Erfurter Str. 23",
    "sg:city":"Sondershausen",
    "sg:phone":"+49 3632/788588",
    "sg:postcode":"99706",
    "sg:province":"Th\u00fcringen",
    "wof:name":"Aral_tankstelle",
    "wof:placetype":"venue"
},
  "geometry": {"coordinates":[10.8495817184,51.3675880432],"type":"Point"}
}