{
  "type": "Feature",
  "properties": {
    "iso:country":"DE",
    "sg:address":"Riege-Wolfstange 6",
    "sg:city":"Friesoythe",
    "sg:phone":"+49 4491/40704",
    "sg:postcode":"26169",
    "sg:province":"Niedersachsen",
    "wof:name":"Albert Scheper",
    "wof:placetype":"venue"
},
  "geometry": {"coordinates":[7.8871297836,53.0365180969],"type":"Point"}
}