{
  "type": "Feature",
  "properties": {
    "iso:country":"DE",
    "sg:address":"Erzstr. 2",
    "sg:city":"Herdorf",
    "sg:postcode":"57562",
    "sg:province":"Rheinland-Pfalz",
    "wof:name":"Johannes Sch\u00e4fer Gmbh",
    "wof:placetype":"venue"
},
  "geometry": {"coordinates":[7.950491,50.778339],"type":"Point"}
}