{
  "type": "Feature",
  "properties": {
    "iso:country":"DE",
    "sg:address":"An der B 22",
    "sg:city":"T\u00e4nnesberg",
    "sg:phone":"+49 9655/490",
    "sg:postcode":"92723",
    "sg:province":"Bayern",
    "wof:name":"Sonnenhof Cafe",
    "wof:placetype":"venue"
},
  "geometry": {"coordinates":[12.324901,49.531712],"type":"Point"}
}