{
  "type": "Feature",
  "properties": {
    "iso:country":"DE",
    "sg:address":"Kieler Str. 19-21",
    "sg:city":"Eckernf\u00f6rde",
    "sg:phone":"+49 4351/712727",
    "sg:postcode":"24340",
    "sg:province":"Schleswig-Holstein",
    "wof:name":"Rossmann Drogeriemarkt",
    "wof:placetype":"venue"
},
  "geometry": {"coordinates":[9.837127,54.471561],"type":"Point"}
}