{
  "type": "Feature",
  "properties": {
    "iso:country":"DE",
    "sg:address":"Kirchener Str.",
    "sg:city":"Betzdorf",
    "sg:phone":"+49 2741/970921",
    "sg:postcode":"57518",
    "sg:province":"Rheinland-Pfalz",
    "wof:name":"Flora Frisch 3000 Gmbh",
    "wof:placetype":"venue"
},
  "geometry": {"coordinates":[7.878353,50.796749],"type":"Point"}
}