{
  "type": "Feature",
  "properties": {
    "iso:country":"DE",
    "sg:address":"Weg am K\u00f6tterberg 7",
    "sg:city":"Bochum",
    "sg:phone":"+49 234/595068",
    "sg:postcode":"44807",
    "sg:province":"Nordrhein-Westfalen",
    "wof:name":"Rolf Blome",
    "wof:placetype":"venue"
},
  "geometry": {"coordinates":[7.243504,51.504261],"type":"Point"}
}