{
  "type": "Feature",
  "properties": {
    "iso:country":"DE",
    "sg:address":"Kantstr. 33",
    "sg:city":"Bamberg",
    "sg:phone":"+49 951/31287",
    "sg:postcode":"96052",
    "sg:province":"Bayern",
    "wof:name":"S\u00fcdaufbau Wohnungs- Und Aufbau-gmbh",
    "wof:placetype":"venue"
},
  "geometry": {"coordinates":[10.9101438522,49.9095993042],"type":"Point"}
}