{
  "type": "Feature",
  "properties": {
    "iso:country":"DE",
    "sg:address":"Wipsch 1",
    "sg:city":"Bad Ems",
    "sg:phone":"+49 2603/937450",
    "sg:postcode":"56130",
    "sg:province":"Rheinland-Pfalz",
    "wof:name":"Redaktion Rhein-lahn-zeitung",
    "wof:placetype":"venue"
},
  "geometry": {"coordinates":[7.713534832,50.3337631226],"type":"Point"}
}