{
  "type": "Feature",
  "properties": {
    "iso:country":"DE",
    "sg:address":"Fronstr. 2",
    "sg:city":"Winningen",
    "sg:phone":"+49 2606/435",
    "sg:postcode":"56333",
    "sg:province":"Rheinland-Pfalz",
    "wof:name":"Frohnhofstuben",
    "wof:placetype":"venue"
},
  "geometry": {"coordinates":[7.5200600624,50.3125305176],"type":"Point"}
}