{
  "type": "Feature",
  "properties": {
    "iso:country":"DE",
    "sg:address":"Schanzenberg 5",
    "sg:city":"Schlangenbad",
    "sg:phone":"+49 6129/1324",
    "sg:postcode":"65388",
    "sg:province":"Hessen",
    "wof:name":"M. M\u00fcller",
    "wof:placetype":"venue"
},
  "geometry": {"coordinates":[8.0991706848,50.1085243225],"type":"Point"}
}