{
  "type": "Feature",
  "properties": {
    "iso:country":"DE",
    "sg:address":"Hauptstr. 3 a",
    "sg:city":"Thalmassing",
    "sg:phone":"+49 9453/256",
    "sg:postcode":"93107",
    "sg:province":"Bayern",
    "wof:name":"L. Kiendl",
    "wof:placetype":"venue"
},
  "geometry": {"coordinates":[12.1640644073,48.9150047302],"type":"Point"}
}