{
  "type": "Feature",
  "properties": {
    "iso:country":"DE",
    "sg:address":"Leimbachstr. 4",
    "sg:city":"Siegen",
    "sg:postcode":"57074",
    "sg:province":"Nordrhein-Westfalen",
    "wof:name":"Com-es-schallplatten- Und Musikverlagsges. Mbh",
    "wof:placetype":"venue"
},
  "geometry": {"coordinates":[8.0136804581,50.8699378967],"type":"Point"}
}