{
  "type": "Feature",
  "properties": {
    "iso:country":"DE",
    "sg:address":"H\u00f6velmarkt 7",
    "sg:city":"H\u00f6velhof",
    "sg:phone":"+49 5257/1585",
    "sg:postcode":"33161",
    "sg:province":"Nordrhein-Westfalen",
    "wof:name":"Einstein",
    "wof:placetype":"venue"
},
  "geometry": {"coordinates":[8.6596698761,51.8211517334],"type":"Point"}
}