{
  "type": "Feature",
  "properties": {
    "iso:country":"DE",
    "sg:address":"L\u00fcbecker Str. 18",
    "sg:city":"Schwerin",
    "sg:phone":"+49 385/565506",
    "sg:postcode":"19053",
    "sg:province":"Mecklenburg-Vorpommern",
    "wof:name":"U. Ostmann Und M. Vogel Rechtsanw\u00e4lte",
    "wof:placetype":"venue"
},
  "geometry": {"coordinates":[11.4085903168,53.6291046143],"type":"Point"}
}