{
  "type": "Feature",
  "properties": {
    "iso:country":"DE",
    "sg:address":"Am Papierweiher 1",
    "sg:city":"Blieskastel",
    "sg:phone":"+49 6842/92000",
    "sg:postcode":"66440",
    "sg:province":"Saarland",
    "wof:name":"Lautzkirchener Kalksandsteinwerk Gmbh",
    "wof:placetype":"venue"
},
  "geometry": {"coordinates":[7.25234,49.25275],"type":"Point"}
}