{
  "type": "Feature",
  "properties": {
    "iso:country":"DE",
    "sg:address":"Pagendarmweg 9a",
    "sg:city":"Paderborn",
    "sg:phone":"+49 5251/14410",
    "sg:postcode":"33100",
    "sg:province":"Nordrhein-Westfalen",
    "wof:name":"Janson & Even M\u00f6bel Und Design Gmbh",
    "wof:placetype":"venue"
},
  "geometry": {"coordinates":[8.7732744217,51.7364006042],"type":"Point"}
}