{
  "type": "Feature",
  "properties": {
    "iso:country":"DE",
    "sg:address":"Bergstr. 1",
    "sg:city":"Westerburg",
    "sg:phone":"+49 2663/4814",
    "sg:postcode":"56457",
    "sg:province":"Rheinland-Pfalz",
    "wof:name":"Arsenio Garcia",
    "wof:placetype":"venue"
},
  "geometry": {"coordinates":[7.968762,50.561192],"type":"Point"}
}