{
  "type": "Feature",
  "properties": {
    "iso:country":"DE",
    "sg:address":"Worpheimer Str. 15",
    "sg:city":"Worpswede",
    "sg:phone":"+49 4792/2720",
    "sg:postcode":"27726",
    "sg:province":"Niedersachsen",
    "wof:name":"K. D. Fachwerkbau Gmbh",
    "wof:placetype":"venue"
},
  "geometry": {"coordinates":[8.9003734589,53.1964302063],"type":"Point"}
}