{
  "type": "Feature",
  "properties": {
    "iso:country":"DE",
    "sg:address":"Am Dreieck 8",
    "sg:city":"Neuss",
    "sg:phone":"+49 2137/60080",
    "sg:postcode":"41470",
    "sg:province":"Nordrhein-Westfalen",
    "wof:name":"Al-gummi- Und Kunststofftechnik Gmbh",
    "wof:placetype":"venue"
},
  "geometry": {"coordinates":[6.728934,51.123444],"type":"Point"}
}