{
  "type": "Feature",
  "properties": {
    "iso:country":"DE",
    "sg:address":"An der Feldmark 15",
    "sg:city":"Wunstorf",
    "sg:phone":"+49 5031/910000",
    "sg:postcode":"31515",
    "sg:province":"Niedersachsen",
    "wof:name":"Dieter Schaller",
    "wof:placetype":"venue"
},
  "geometry": {"coordinates":[9.4535312653,52.4157981873],"type":"Point"}
}