{
  "type": "Feature",
  "properties": {
    "iso:country":"DE",
    "sg:address":"Altk\u00f6nigstr. 10",
    "sg:city":"K\u00f6nigstein",
    "sg:postcode":"61462",
    "sg:province":"Hessen",
    "wof:name":"Horn Gmbh",
    "wof:placetype":"venue"
},
  "geometry": {"coordinates":[8.467662,50.189137],"type":"Point"}
}