{
  "type": "Feature",
  "properties": {
    "iso:country":"DE",
    "sg:address":"Am Wasen 9",
    "sg:city":"Malsch",
    "sg:phone":"+49 7204/8151",
    "sg:postcode":"76316",
    "sg:province":"Baden-W\u00fcrttemberg",
    "wof:name":"Wink Gmbh",
    "wof:placetype":"venue"
},
  "geometry": {"coordinates":[8.3924417496,48.8645324707],"type":"Point"}
}