{
  "type": "Feature",
  "properties": {
    "iso:country":"DE",
    "sg:address":"Markt 26",
    "sg:city":"Oldenburg",
    "sg:phone":"+49 4361/52198",
    "sg:postcode":"23758",
    "sg:province":"Schleswig-Holstein",
    "wof:name":"Gastst\u00e4tte Fieka Und Johanna",
    "wof:placetype":"venue"
},
  "geometry": {"coordinates":[-85.206237793,39.3398132324],"type":"Point"}
}