{
  "type": "Feature",
  "properties": {
    "iso:country":"DE",
    "sg:address":"Br\u00fcckenstr. 10",
    "sg:city":"Dierdorf",
    "sg:phone":"+49 2689/2051",
    "sg:postcode":"56269",
    "sg:province":"Rheinland-Pfalz",
    "wof:name":"Manfred Ladwein Gmbh",
    "wof:placetype":"venue"
},
  "geometry": {"coordinates":[7.657797,50.545914],"type":"Point"}
}