{
  "type": "Feature",
  "properties": {
    "iso:country":"DE",
    "sg:address":"Wilhelm-Pieck-Str. 18",
    "sg:city":"K\u00f6nigsee",
    "sg:phone":"+49 36738/42371",
    "sg:postcode":"07426",
    "sg:province":"Th\u00fcringen",
    "wof:name":"Rainer Springer",
    "wof:placetype":"venue"
},
  "geometry": {"coordinates":[11.094206,50.660877],"type":"Point"}
}