{
  "type": "Feature",
  "properties": {
    "iso:country":"DE",
    "sg:address":"Am Sauerborn 19",
    "sg:city":"Echzell",
    "sg:phone":"+49 4960/0891110",
    "sg:postcode":"61209",
    "sg:province":"Hessen",
    "wof:name":"Lse Reisemobile Vertriebsgesellschaft Mbh",
    "wof:placetype":"venue"
},
  "geometry": {"coordinates":[8.8918504715,50.3897285461],"type":"Point"}
}