{
  "type": "Feature",
  "properties": {
    "iso:country":"DE",
    "sg:address":"Steeler Str. 125",
    "sg:city":"Essen",
    "sg:phone":"+49 201/285436",
    "sg:postcode":"45138",
    "sg:province":"Nordrhein-Westfalen",
    "wof:name":"Pizzeria Bei Mario",
    "wof:placetype":"venue"
},
  "geometry": {"coordinates":[7.0300331116,51.4514312744],"type":"Point"}
}