{
  "type": "Feature",
  "properties": {
    "iso:country":"DE",
    "sg:address":"Kiem-Pauli-Str. 6",
    "sg:city":"Ingolstadt",
    "sg:phone":"+49 841/38087",
    "sg:postcode":"85055",
    "sg:province":"Bayern",
    "wof:name":"Ernst Ullrich Elektroinstallation",
    "wof:placetype":"venue"
},
  "geometry": {"coordinates":[11.408629,48.802334],"type":"Point"}
}