{
  "type": "Feature",
  "properties": {
    "iso:country":"DE",
    "sg:address":"Willhartsberg 23",
    "sg:city":"Salzweg",
    "sg:phone":"+49 8501/1844",
    "sg:postcode":"94121",
    "sg:province":"Bayern",
    "wof:name":"Josef Juhass",
    "wof:placetype":"venue"
},
  "geometry": {"coordinates":[13.511992,48.631783],"type":"Point"}
}