{
  "type": "Feature",
  "properties": {
    "iso:country":"DE",
    "sg:address":"Eichelgasse 10",
    "sg:city":"L\u00f6bau",
    "sg:phone":"+49 3585/404635",
    "sg:postcode":"02708",
    "sg:province":"Sachsen",
    "wof:name":"Reformhaus Alfred Puschmann Inh. B\u00e4rbel Schneider",
    "wof:placetype":"venue"
},
  "geometry": {"coordinates":[14.6672830582,51.0946578979],"type":"Point"}
}