{
  "type": "Feature",
  "properties": {
    "iso:country":"DE",
    "sg:address":"Hauptstr. 101",
    "sg:city":"Amstetten",
    "sg:phone":"+49 7331/7252",
    "sg:postcode":"73340",
    "sg:province":"Baden-W\u00fcrttemberg",
    "wof:name":"Bendel",
    "wof:placetype":"venue"
},
  "geometry": {"coordinates":[9.87454,48.579159],"type":"Point"}
}