{
  "type": "Feature",
  "properties": {
    "iso:country":"DE",
    "sg:address":"R\u00f6merring 11",
    "sg:city":"Hildesheim",
    "sg:phone":"+49 5121/301612",
    "sg:postcode":"31137",
    "sg:province":"Niedersachsen",
    "wof:name":"Stadt Hildesheim",
    "wof:placetype":"venue"
},
  "geometry": {"coordinates":[9.9359502792,52.1590042114],"type":"Point"}
}