{
  "type": "Feature",
  "properties": {
    "iso:country":"DE",
    "sg:address":"Im Winkel 25",
    "sg:city":"Wedemark",
    "sg:phone":"+49 5130/6117",
    "sg:postcode":"30900",
    "sg:province":"Niedersachsen",
    "wof:name":"K\u00fcchentechnik Lempke",
    "wof:placetype":"venue"
},
  "geometry": {"coordinates":[9.7269277573,52.5250473022],"type":"Point"}
}