{
  "type": "Feature",
  "properties": {
    "iso:country":"DE",
    "sg:address":"Dorfstr. 31",
    "sg:city":"Jonaswalde",
    "sg:postcode":"04626",
    "sg:province":"Th\u00fcringen",
    "wof:name":"Psp Steuer- Beratungsgesellschaft Mbh",
    "wof:placetype":"venue"
},
  "geometry": {"coordinates":[12.2867383957,50.8394050598],"type":"Point"}
}