{
  "type": "Feature",
  "properties": {
    "iso:country":"DE",
    "sg:address":"Werner-Siemens-Str. 76",
    "sg:city":"Pforzheim",
    "sg:phone":"+49 7231/23340",
    "sg:postcode":"75173",
    "sg:province":"Baden-W\u00fcrttemberg",
    "wof:name":"Bohrain",
    "wof:placetype":"venue"
},
  "geometry": {"coordinates":[8.6787338257,48.8859024048],"type":"Point"}
}