{
  "type": "Feature",
  "properties": {
    "iso:country":"DE",
    "sg:address":"M\u00fchlstr. 15",
    "sg:city":"Dietersheim",
    "sg:phone":"+49 9161/3202",
    "sg:postcode":"91463",
    "sg:province":"Bayern",
    "wof:name":"G\u00fcnter Winnerlein",
    "wof:placetype":"venue"
},
  "geometry": {"coordinates":[10.5363483429,49.5574569702],"type":"Point"}
}