{
  "type": "Feature",
  "properties": {
    "iso:country":"DE",
    "sg:address":"Markt 22",
    "sg:city":"Heide",
    "sg:phone":"+49 481/67675",
    "sg:postcode":"25746",
    "sg:province":"Schleswig-Holstein",
    "wof:name":"Foto Am Markt Inh. Reiner Kaun",
    "wof:placetype":"venue"
},
  "geometry": {"coordinates":[9.0933103561,54.1941108704],"type":"Point"}
}