{
  "type": "Feature",
  "properties": {
    "iso:country":"DE",
    "sg:address":"Leipziger Str. 256",
    "sg:city":"Kaufungen",
    "sg:phone":"+49 5605/6419",
    "sg:postcode":"34260",
    "sg:province":"Hessen",
    "wof:name":"Mords Men\u00fc",
    "wof:placetype":"venue"
},
  "geometry": {"coordinates":[9.601348877,51.284324646],"type":"Point"}
}