{
  "type": "Feature",
  "properties": {
    "iso:country":"DE",
    "sg:address":"Bad S\u00fclzer Str. 50",
    "sg:city":"L\u00f6bnitz",
    "sg:phone":"+49 38324/89120",
    "sg:postcode":"18314",
    "sg:province":"Mecklenburg-Vorpommern",
    "wof:name":"Hid Handels-instandsetzungs- Und Dienstleistungs-ges. Mbh",
    "wof:placetype":"venue"
},
  "geometry": {"coordinates":[12.71791,54.288754],"type":"Point"}
}