{
  "type": "Feature",
  "properties": {
    "iso:country":"DE",
    "sg:address":"Achimer Br\u00fcckenstr. 5",
    "sg:city":"Achim",
    "sg:phone":"+49 4202/8084",
    "sg:postcode":"28832",
    "sg:province":"Niedersachsen",
    "wof:name":"Hans-joachim Busch Rechtsanwalt Und Notar",
    "wof:placetype":"venue"
},
  "geometry": {"coordinates":[9.0360975266,53.0129013062],"type":"Point"}
}