{
  "type": "Feature",
  "properties": {
    "iso:country":"DE",
    "sg:address":"Mittelstr. 4",
    "sg:city":"Velbert",
    "sg:phone":"+49 2051/50659",
    "sg:postcode":"42551",
    "sg:province":"Nordrhein-Westfalen",
    "wof:name":"Ali Z. Sivrice",
    "wof:placetype":"venue"
},
  "geometry": {"coordinates":[7.0451431274,51.342300415],"type":"Point"}
}