{
  "type": "Feature",
  "properties": {
    "iso:country":"DE",
    "sg:address":"Burgstr. 29",
    "sg:city":"Neum\u00fcnster",
    "sg:phone":"+49 4321/989298",
    "sg:postcode":"24539",
    "sg:province":"Schleswig-Holstein",
    "wof:name":"K Und K Software Gmbh",
    "wof:placetype":"venue"
},
  "geometry": {"coordinates":[9.961763382,54.0552368164],"type":"Point"}
}