{
  "type": "Feature",
  "properties": {
    "iso:country":"DE",
    "sg:address":"Lindenstr. 27",
    "sg:city":"L\u00fcbben",
    "sg:phone":"+49 3546/4566",
    "sg:postcode":"15907",
    "sg:province":"Brandenburg",
    "wof:name":"Harry Possling",
    "wof:placetype":"venue"
},
  "geometry": {"coordinates":[13.892558,51.939507],"type":"Point"}
}