{
  "type": "Feature",
  "properties": {
    "iso:country":"DE",
    "sg:address":"Hochdahler Markt 15",
    "sg:city":"Erkrath",
    "sg:phone":"+49 2104/43677",
    "sg:postcode":"40699",
    "sg:province":"Nordrhein-Westfalen",
    "wof:name":"Markt-apotheke",
    "wof:placetype":"venue"
},
  "geometry": {"coordinates":[6.956394,51.207657],"type":"Point"}
}