{
  "type": "Feature",
  "properties": {
    "iso:country":"DE",
    "sg:address":"Bredentiner Weg 4a",
    "sg:city":"G\u00fcstrow",
    "sg:phone":"+49 385/64300",
    "sg:postcode":"18273",
    "sg:province":"Mecklenburg-Vorpommern",
    "wof:name":"Nordkorn Saaten Gmbh",
    "wof:placetype":"venue"
},
  "geometry": {"coordinates":[12.177627,53.808655],"type":"Point"}
}