{
  "type": "Feature",
  "properties": {
    "iso:country":"DE",
    "sg:address":"Hauptstr. 2",
    "sg:city":"Kandern",
    "sg:phone":"+49 7626/7563",
    "sg:postcode":"79400",
    "sg:province":"Baden-W\u00fcrttemberg",
    "wof:name":"H. Tanner",
    "wof:placetype":"venue"
},
  "geometry": {"coordinates":[7.6603,47.714169],"type":"Point"}
}