{
  "type": "Feature",
  "properties": {
    "iso:country":"DE",
    "sg:address":"Hindenburgdamm 59A",
    "sg:city":"Berlin",
    "sg:phone":"+49 30/84471100",
    "sg:postcode":"12203",
    "sg:province":"Berlin",
    "wof:name":"Kaisers Kaffee-gesch\u00e4ft",
    "wof:placetype":"venue"
},
  "geometry": {"coordinates":[13.3156480789,52.4482803345],"type":"Point"}
}