{
  "type": "Feature",
  "properties": {
    "iso:country":"DE",
    "sg:address":"Bahnhofstr. 92",
    "sg:city":"Paderborn",
    "sg:phone":"+49 5251/33516",
    "sg:postcode":"33102",
    "sg:province":"Nordrhein-Westfalen",
    "wof:name":"Shell-tankstelle",
    "wof:placetype":"venue"
},
  "geometry": {"coordinates":[8.7315149307,51.7114906311],"type":"Point"}
}