{
  "type": "Feature",
  "properties": {
    "iso:country":"DE",
    "sg:address":"Hauptstr. 29",
    "sg:city":"Pei\u00dfenberg",
    "sg:phone":"+49 8803/2422",
    "sg:postcode":"82380",
    "sg:province":"Bayern",
    "wof:name":"H. D. Schr\u00f6tter",
    "wof:placetype":"venue"
},
  "geometry": {"coordinates":[11.075652,47.801796],"type":"Point"}
}