{
  "type": "Feature",
  "properties": {
    "iso:country":"DE",
    "sg:address":"Scheibenbergstr. 16",
    "sg:city":"Sigmaringen",
    "sg:phone":"+49 7577/932058",
    "sg:postcode":"72488",
    "sg:province":"Baden-W\u00fcrttemberg",
    "wof:name":"Eduard Kn\u00f6r M\u00f6bel- Und Bauschreinerei",
    "wof:placetype":"venue"
},
  "geometry": {"coordinates":[9.210877,48.135715],"type":"Point"}
}