{
  "type": "Feature",
  "properties": {
    "iso:country":"DE",
    "sg:address":"Hauptstr. 5",
    "sg:city":"Gro\u00dfbreitenbach",
    "sg:phone":"+49 36781/40481",
    "sg:postcode":"98701",
    "sg:province":"Th\u00fcringen",
    "wof:name":"Gerlof",
    "wof:placetype":"venue"
},
  "geometry": {"coordinates":[11.004991,50.581074],"type":"Point"}
}