{
  "type": "Feature",
  "properties": {
    "iso:country":"DE",
    "sg:address":"Krayer Str. 24",
    "sg:city":"Essen",
    "sg:phone":"+49 201/501162",
    "sg:postcode":"45276",
    "sg:province":"Nordrhein-Westfalen",
    "wof:name":"Conny Winert",
    "wof:placetype":"venue"
},
  "geometry": {"coordinates":[7.0774259567,51.4519348145],"type":"Point"}
}