{
  "type": "Feature",
  "properties": {
    "iso:country":"DE",
    "sg:address":"Altlandsberger Chaussee 23",
    "sg:city":"Fredersdorf",
    "sg:phone":"+49 33439/59215",
    "sg:postcode":"15370",
    "sg:province":"Brandenburg",
    "wof:name":"Steinmetzbetrieb Axel Schoebel",
    "wof:placetype":"venue"
},
  "geometry": {"coordinates":[13.7553882599,52.5311508179],"type":"Point"}
}