{
  "type": "Feature",
  "properties": {
    "iso:country":"DE",
    "sg:address":"Waltharistrasse 11 a",
    "sg:city":"Berlin",
    "sg:phone":"+49 30/80491299",
    "sg:postcode":"14109",
    "sg:province":"Berlin",
    "wof:name":"H\u00f6gl & Partner",
    "wof:placetype":"venue"
},
  "geometry": {"coordinates":[13.186342,52.421986],"type":"Point"}
}