{
  "type": "Feature",
  "properties": {
    "iso:country":"DE",
    "sg:address":"Twenh\u00f6venweg 22",
    "sg:city":"M\u00fcnster",
    "sg:phone":"+49 2506/1242",
    "sg:postcode":"48167",
    "sg:province":"Nordrhein-Westfalen",
    "wof:name":"Dr. Burghard Schulte-uebbing Tierarzt",
    "wof:placetype":"venue"
},
  "geometry": {"coordinates":[7.7063741684,51.9174842834],"type":"Point"}
}