{
  "type": "Feature",
  "properties": {
    "iso:country":"DE",
    "sg:address":"Quellenweg 2a",
    "sg:city":"Niedernhausen",
    "sg:phone":"+49 6127/7105",
    "sg:postcode":"65527",
    "sg:province":"Hessen",
    "wof:name":"D\u00fcnnemann",
    "wof:placetype":"venue"
},
  "geometry": {"coordinates":[8.3182134628,50.167301178],"type":"Point"}
}