{
  "type": "Feature",
  "properties": {
    "iso:country":"DE",
    "sg:address":"Hessenstr. 14",
    "sg:city":"Finsterwalde",
    "sg:phone":"+49 3531/601254",
    "sg:postcode":"03238",
    "sg:province":"Brandenburg",
    "wof:name":"Peter Eckenigk",
    "wof:placetype":"venue"
},
  "geometry": {"coordinates":[13.71103,51.621109],"type":"Point"}
}