{
  "type": "Feature",
  "properties": {
    "iso:country":"DE",
    "sg:address":"Schulstr. 32",
    "sg:city":"Aichstetten",
    "sg:phone":"+49 7565/1582",
    "sg:postcode":"88317",
    "sg:province":"Baden-W\u00fcrttemberg",
    "wof:name":"Hubert Leonhardt",
    "wof:placetype":"venue"
},
  "geometry": {"coordinates":[10.0805721283,47.8929214478],"type":"Point"}
}