{
  "type": "Feature",
  "properties": {
    "iso:country":"DE",
    "sg:address":"Alleestr. 21",
    "sg:city":"Riesa",
    "sg:phone":"+49 3525/893184",
    "sg:postcode":"01591",
    "sg:province":"Sachsen",
    "wof:name":"S. Franke",
    "wof:placetype":"venue"
},
  "geometry": {"coordinates":[13.2736120224,51.3210105896],"type":"Point"}
}