{
  "type": "Feature",
  "properties": {
    "iso:country":"DE",
    "sg:address":"Meuchefitz",
    "sg:city":"K\u00fcsten",
    "sg:phone":"+49 5841/5977",
    "sg:postcode":"29482",
    "sg:province":"Niedersachsen",
    "wof:name":"Meuchefitzer Gasthof Und Werkst\u00e4tten Gmbh",
    "wof:placetype":"venue"
},
  "geometry": {"coordinates":[11.066313,52.959362],"type":"Point"}
}