{
  "type": "Feature",
  "properties": {
    "iso:country":"DE",
    "sg:address":"Frankfurter Str. 14",
    "sg:city":"Bad K\u00f6nig",
    "sg:phone":"+49 6063/4250",
    "sg:postcode":"64732",
    "sg:province":"Hessen",
    "wof:name":"Eisel Gmbh & Co. Kg",
    "wof:placetype":"venue"
},
  "geometry": {"coordinates":[9.0049610138,49.7431488037],"type":"Point"}
}