{
  "type": "Feature",
  "properties": {
    "iso:country":"DE",
    "sg:address":"Enztalstr. 13",
    "sg:city":"Mettendorf",
    "sg:phone":"+49 6522/209",
    "sg:postcode":"54675",
    "sg:province":"Rheinland-Pfalz",
    "wof:name":"W. Meyer-ludowisy",
    "wof:placetype":"venue"
},
  "geometry": {"coordinates":[6.332426,49.945583],"type":"Point"}
}