{
  "type": "Feature",
  "properties": {
    "iso:country":"DE",
    "sg:address":"Anzinger Str. 29",
    "sg:city":"M\u00fcnchen",
    "sg:phone":"+49 89/404750",
    "sg:postcode":"81671",
    "sg:province":"Bayern",
    "wof:name":"Degi Deutsche Gesellschaft F\u00fcr Immobilienfonds Mbh",
    "wof:placetype":"venue"
},
  "geometry": {"coordinates":[11.6103887558,48.1211929321],"type":"Point"}
}