{
  "type": "Feature",
  "properties": {
    "iso:country":"DE",
    "sg:address":"Kleine K\u00f6nigstr. 55 Embken",
    "sg:city":"Nideggen",
    "sg:phone":"+49 2425/291",
    "sg:postcode":"52385",
    "sg:province":"Nordrhein-Westfalen",
    "wof:name":"Impex Au\u00dfenhandels Gmbh",
    "wof:placetype":"venue"
},
  "geometry": {"coordinates":[6.4841370583,50.6918449402],"type":"Point"}
}