{
  "type": "Feature",
  "properties": {
    "iso:country":"DE",
    "sg:address":"Sch\u00f6nblickstr. 40",
    "sg:city":"Deggingen",
    "sg:phone":"+49 7334/5013",
    "sg:postcode":"73326",
    "sg:province":"Baden-W\u00fcrttemberg",
    "wof:name":"Ivt Ingenieurb\u00fcro F\u00fcr Verpackungstechnik Gmbh",
    "wof:placetype":"venue"
},
  "geometry": {"coordinates":[9.7277441025,48.5956802368],"type":"Point"}
}