{
  "type": "Feature",
  "properties": {
    "iso:country":"DE",
    "sg:address":"Aschaffenburger Str. 18",
    "sg:city":"Seligenstadt",
    "sg:phone":"+49 6182/3830",
    "sg:postcode":"63500",
    "sg:province":"Hessen",
    "wof:name":"I. R\u00f6sch",
    "wof:placetype":"venue"
},
  "geometry": {"coordinates":[8.975998,50.042709],"type":"Point"}
}