{
  "type": "Feature",
  "properties": {
    "iso:country":"DE",
    "sg:address":"Am Bach 4",
    "sg:city":"Leinburg",
    "sg:phone":"+49 9187/1576",
    "sg:postcode":"91227",
    "sg:province":"Bayern",
    "wof:name":"Liebel Bedachungen Gmbh",
    "wof:placetype":"venue"
},
  "geometry": {"coordinates":[11.358839,49.429615],"type":"Point"}
}