{
  "type": "Feature",
  "properties": {
    "iso:country":"DE",
    "sg:address":"M\u00f6rikestr. 3",
    "sg:city":"Wendlingen",
    "sg:phone":"+49 7024/989839",
    "sg:postcode":"73240",
    "sg:province":"Baden-W\u00fcrttemberg",
    "wof:name":"K (punkt) Agentur F\u00fcr Kommunikation Gmbh",
    "wof:placetype":"venue"
},
  "geometry": {"coordinates":[9.3845024109,48.6714172363],"type":"Point"}
}