{
  "type": "Feature",
  "properties": {
    "iso:country":"DE",
    "sg:address":"S\u00fcdstr. 2",
    "sg:city":"Schwanau",
    "sg:phone":"+49 7824/2253",
    "sg:postcode":"77963",
    "sg:province":"Baden-W\u00fcrttemberg",
    "wof:name":"Werner Stolz",
    "wof:placetype":"venue"
},
  "geometry": {"coordinates":[7.754795,48.383118],"type":"Point"}
}