{
  "type": "Feature",
  "properties": {
    "iso:country":"DE",
    "sg:address":"Jahnstr. 42",
    "sg:city":"Bad Orb",
    "sg:phone":"+49 6052/3071",
    "sg:postcode":"63619",
    "sg:province":"Hessen",
    "wof:name":"Haus Belvedere",
    "wof:placetype":"venue"
},
  "geometry": {"coordinates":[9.3541460037,50.2205429077],"type":"Point"}
}