{
  "type": "Feature",
  "properties": {
    "iso:country":"DE",
    "sg:address":"Albertstr. 65",
    "sg:city":"Eschweiler",
    "sg:phone":"+49 2402/29916",
    "sg:postcode":"52249",
    "sg:province":"Nordrhein-Westfalen",
    "wof:name":"Friedhelm He\u00df",
    "wof:placetype":"venue"
},
  "geometry": {"coordinates":[6.281,50.789551],"type":"Point"}
}