{
  "type": "Feature",
  "properties": {
    "iso:country":"DE",
    "sg:address":"An den Kirchen 28",
    "sg:city":"Hamm",
    "sg:phone":"+49 2381/996990",
    "sg:postcode":"59077",
    "sg:province":"Nordrhein-Westfalen",
    "wof:name":"Kranken-transport Herzig Gmbh",
    "wof:placetype":"venue"
},
  "geometry": {"coordinates":[7.7354211807,51.6603126526],"type":"Point"}
}