{
  "type": "Feature",
  "properties": {
    "iso:country":"DE",
    "sg:address":"An der Plantage 3",
    "sg:city":"Altenweddingen",
    "sg:phone":"+49 39205/21298",
    "sg:postcode":"39171",
    "sg:province":"Sachsen-Anhalt",
    "wof:name":"E.-m. Hoffmann",
    "wof:placetype":"venue"
},
  "geometry": {"coordinates":[11.5345716476,52.0035629272],"type":"Point"}
}