{
  "type": "Feature",
  "properties": {
    "iso:country":"DE",
    "sg:address":"N\u00fcrtinger Str. 30",
    "sg:city":"Filderstadt",
    "sg:phone":"+49 711/703789",
    "sg:postcode":"70794",
    "sg:province":"Baden-W\u00fcrttemberg",
    "wof:name":"Erwin Manz",
    "wof:placetype":"venue"
},
  "geometry": {"coordinates":[9.2204360962,48.6785736084],"type":"Point"}
}