{
  "type": "Feature",
  "properties": {
    "iso:country":"DE",
    "sg:address":"Feldmarkweg 20",
    "sg:city":"Hagen",
    "sg:phone":"+49 2331/61150",
    "sg:postcode":"58093",
    "sg:province":"Nordrhein-Westfalen",
    "wof:name":"Josef Sigfanz",
    "wof:placetype":"venue"
},
  "geometry": {"coordinates":[7.503955,51.389248],"type":"Point"}
}