{
  "type": "Feature",
  "properties": {
    "iso:country":"DE",
    "sg:address":"L\u00e4hrer Weg 103 a",
    "sg:city":"Neumarkt",
    "sg:phone":"+49 9181/905967",
    "sg:postcode":"92318",
    "sg:province":"Bayern",
    "wof:name":"Sunny Sport Gmbh",
    "wof:placetype":"venue"
},
  "geometry": {"coordinates":[11.4732027054,49.2678375244],"type":"Point"}
}