{
  "type": "Feature",
  "properties": {
    "iso:country":"DE",
    "sg:address":"Schottstr. 108",
    "sg:city":"Stuttgart",
    "sg:postcode":"70192",
    "sg:province":"Baden-W\u00fcrttemberg",
    "wof:name":"Elterninitiative Kinder- Tagesst\u00e4tte Stuttgart E. V.",
    "wof:placetype":"venue"
},
  "geometry": {"coordinates":[9.1707057953,48.7881584167],"type":"Point"}
}