{
  "type": "Feature",
  "properties": {
    "iso:country":"DE",
    "sg:address":"Eupener Str. 23",
    "sg:city":"Bremerhaven",
    "sg:phone":"+49 471/43833",
    "sg:postcode":"27576",
    "sg:province":"Bremen",
    "wof:name":"Emil Schepp",
    "wof:placetype":"venue"
},
  "geometry": {"coordinates":[8.579592,53.55772],"type":"Point"}
}