{
  "type": "Feature",
  "properties": {
    "iso:country":"DE",
    "sg:address":"Zerndorfer Weg 53",
    "sg:city":"Berlin",
    "sg:phone":"+49 30/4013524",
    "sg:postcode":"13465",
    "sg:province":"Berlin",
    "wof:name":"G\u00fcnther Herbstleb Steuerberater",
    "wof:placetype":"venue"
},
  "geometry": {"coordinates":[13.3015918732,52.6378974915],"type":"Point"}
}