{
  "type": "Feature",
  "properties": {
    "iso:country":"DE",
    "sg:address":"Driburger Str 4a",
    "sg:city":"Bielefeld",
    "sg:phone":"+49 521/431999",
    "sg:postcode":"33647",
    "sg:province":"Nordrhein-Westfalen",
    "wof:name":"Dent-technik-team Labor F\u00fcr Zahnersatz Gmbh",
    "wof:placetype":"venue"
},
  "geometry": {"coordinates":[8.519413,51.980267],"type":"Point"}
}