{
  "type": "Feature",
  "properties": {
    "iso:country":"DE",
    "sg:address":"Am Schlagsbach 11",
    "sg:city":"Dreieich",
    "sg:phone":"+49 6103/310490",
    "sg:postcode":"63303",
    "sg:province":"Hessen",
    "wof:name":"Advanta Ag",
    "wof:placetype":"venue"
},
  "geometry": {"coordinates":[8.7005033493,50.0234985352],"type":"Point"}
}