{
  "type": "Feature",
  "properties": {
    "iso:country":"DE",
    "sg:address":"Br\u00fcckenstr. 5",
    "sg:city":"Trier",
    "sg:phone":"+49 651/74949",
    "sg:postcode":"54290",
    "sg:province":"Rheinland-Pfalz",
    "wof:name":"Johann Schmitt",
    "wof:placetype":"venue"
},
  "geometry": {"coordinates":[6.6362390518,49.7539634705],"type":"Point"}
}