{
  "type": "Feature",
  "properties": {
    "iso:country":"DE",
    "sg:address":"Von-Richthofen-Str. 28",
    "sg:city":"Augsburg",
    "sg:phone":"+49 821/414666",
    "sg:postcode":"86159",
    "sg:province":"Bayern",
    "wof:name":"Nahrungs- Genussmittel Non Food Abholm\u00e4rkte Gam Gmbh",
    "wof:placetype":"venue"
},
  "geometry": {"coordinates":[10.8955316544,48.3465499878],"type":"Point"}
}