{
  "type": "Feature",
  "properties": {
    "iso:country":"DE",
    "sg:address":"M\u00fchlstr. 13",
    "sg:city":"Naila",
    "sg:phone":"+49 9282/7059",
    "sg:postcode":"95119",
    "sg:province":"Bayern",
    "wof:name":"Redaktion Frankenpost",
    "wof:placetype":"venue"
},
  "geometry": {"coordinates":[11.7075300217,50.3278694153],"type":"Point"}
}