{
  "type": "Feature",
  "properties": {
    "iso:country":"DE",
    "sg:address":"Wehrstr 13c",
    "sg:city":"Glauchau",
    "sg:phone":"+49 3763/77740",
    "sg:postcode":"08371",
    "sg:province":"Sachsen",
    "wof:name":"Projekt Medizin Gmbh",
    "wof:placetype":"venue"
},
  "geometry": {"coordinates":[12.529025,50.81599],"type":"Point"}
}