{
  "type": "Feature",
  "properties": {
    "iso:country":"DE",
    "sg:address":"Eichendorffstr. 11",
    "sg:city":"Hamb\u00fchren",
    "sg:phone":"+49 5084/732",
    "sg:postcode":"29313",
    "sg:province":"Niedersachsen",
    "wof:name":"Katholisches Pfarramt Hl. Schutzengel",
    "wof:placetype":"venue"
},
  "geometry": {"coordinates":[9.9637336731,52.6250686646],"type":"Point"}
}