{
  "type": "Feature",
  "properties": {
    "iso:country":"DE",
    "sg:address":"Bettelpfad 62",
    "sg:city":"Mainz",
    "sg:phone":"+49 6131/830870",
    "sg:postcode":"55130",
    "sg:province":"Rheinland-Pfalz",
    "wof:name":"Farbraum Medienservice Gmbh",
    "wof:placetype":"venue"
},
  "geometry": {"coordinates":[8.29397,49.981491],"type":"Point"}
}