{
  "type": "Feature",
  "properties": {
    "iso:country":"DE",
    "sg:address":"Max-Planck-Str 3",
    "sg:city":"Marbach",
    "sg:phone":"+49 7144/831170",
    "sg:postcode":"71672",
    "sg:province":"Baden-W\u00fcrttemberg",
    "wof:name":"Mehrkantschaber",
    "wof:placetype":"venue"
},
  "geometry": {"coordinates":[9.3301134109,48.9609870911],"type":"Point"}
}