{
  "type": "Feature",
  "properties": {
    "iso:country":"DE",
    "sg:address":"Kurpfalzstr. 6",
    "sg:city":"Wiesloch",
    "sg:postcode":"69168",
    "sg:province":"Baden-W\u00fcrttemberg",
    "wof:name":"Ml Immobilien",
    "wof:placetype":"venue"
},
  "geometry": {"coordinates":[8.687303,49.29443],"type":"Point"}
}