{
  "type": "Feature",
  "properties": {
    "iso:country":"DE",
    "sg:address":"Dohnsener Str. 2",
    "sg:city":"Dohnsen",
    "sg:phone":"+49 5533/97250",
    "sg:postcode":"37620",
    "sg:province":"Niedersachsen",
    "wof:name":"Ith Fenster- Und Fassaden- Technik Gmbh",
    "wof:placetype":"venue"
},
  "geometry": {"coordinates":[9.5733957291,52.0048332214],"type":"Point"}
}