{
  "type": "Feature",
  "properties": {
    "iso:country":"DE",
    "sg:address":"Schwalbenstr. 54",
    "sg:city":"Hamburg",
    "sg:phone":"+49 40/6905755",
    "sg:postcode":"22305",
    "sg:province":"Hamburg",
    "wof:name":"Friedrich Ahlers Steuerberater",
    "wof:placetype":"venue"
},
  "geometry": {"coordinates":[10.0470647812,53.5909461975],"type":"Point"}
}