{
  "type": "Feature",
  "properties": {
    "iso:country":"DE",
    "sg:address":"Paderborner Tor 150",
    "sg:city":"Warburg",
    "sg:phone":"+49 5641/3731",
    "sg:postcode":"34414",
    "sg:province":"Nordrhein-Westfalen",
    "wof:name":"Adolf Reineke",
    "wof:placetype":"venue"
},
  "geometry": {"coordinates":[9.132057,51.491718],"type":"Point"}
}