{
  "type": "Feature",
  "properties": {
    "iso:country":"DE",
    "sg:address":"K\u00f6nitzer Str. 60",
    "sg:city":"Kaulsdorf",
    "sg:phone":"+49 36733/21533",
    "sg:postcode":"07338",
    "sg:province":"Th\u00fcringen",
    "wof:name":"Alfred Wolfram",
    "wof:placetype":"venue"
},
  "geometry": {"coordinates":[11.432510376,50.6220703125],"type":"Point"}
}