{
  "type": "Feature",
  "properties": {
    "iso:country":"DE",
    "sg:address":"Rotkreuzstr. 3",
    "sg:city":"Parsberg",
    "sg:phone":"+49 9492/5065",
    "sg:postcode":"92331",
    "sg:province":"Bayern",
    "wof:name":"Vertrauens\u00e4rztlicher-dienst Der Lva Niederb. Oberpfalz",
    "wof:placetype":"venue"
},
  "geometry": {"coordinates":[11.7171802521,49.1586837769],"type":"Point"}
}