{
  "type": "Feature",
  "properties": {
    "iso:country":"DE",
    "sg:address":"Finkenkamp 39",
    "sg:city":"Braunschweig",
    "sg:phone":"+49 531/361400",
    "sg:postcode":"38104",
    "sg:province":"Niedersachsen",
    "wof:name":"Dieter Hartmann Elektroinstallation",
    "wof:placetype":"venue"
},
  "geometry": {"coordinates":[10.585946,52.284031],"type":"Point"}
}