{
  "type": "Feature",
  "properties": {
    "iso:country":"DE",
    "sg:address":"Sandscheider Str. 20",
    "sg:city":"K\u00f6nigswinter",
    "sg:phone":"+49 2244/3713",
    "sg:postcode":"53639",
    "sg:province":"Nordrhein-Westfalen",
    "wof:name":"Hausmann",
    "wof:placetype":"venue"
},
  "geometry": {"coordinates":[7.3049149513,50.7018127441],"type":"Point"}
}