{
  "type": "Feature",
  "properties": {
    "iso:country":"DE",
    "sg:address":"Borussiastr. 83",
    "sg:city":"Dortmund",
    "sg:phone":"+49 231/65352",
    "sg:postcode":"44149",
    "sg:province":"Nordrhein-Westfalen",
    "wof:name":"G\u00fcnther Odenw\u00e4lder Heinz Spiess",
    "wof:placetype":"venue"
},
  "geometry": {"coordinates":[7.375716,51.490215],"type":"Point"}
}