{
  "type": "Feature",
  "properties": {
    "iso:country":"DE",
    "sg:address":"Buchenweg 3",
    "sg:city":"Hinterschmiding",
    "sg:phone":"+49 8551/6000",
    "sg:postcode":"94146",
    "sg:province":"Bayern",
    "wof:name":"Erich Gerstlberger",
    "wof:placetype":"venue"
},
  "geometry": {"coordinates":[13.602563858,48.8027114868],"type":"Point"}
}