{
  "type": "Feature",
  "properties": {
    "iso:country":"DE",
    "sg:address":"Dorfstr. 55",
    "sg:city":"Ostseebad Ahrenshoop",
    "sg:phone":"+49 38220/630",
    "sg:postcode":"18347",
    "sg:province":"Mecklenburg-Vorpommern",
    "wof:name":"Reha-klinik Ahrenshoop Gmbh",
    "wof:placetype":"venue"
},
  "geometry": {"coordinates":[12.3564147949,54.2923431396],"type":"Point"}
}