{
  "type": "Feature",
  "properties": {
    "iso:country":"DE",
    "sg:address":"Makrelenweg 1a",
    "sg:city":"Norden",
    "sg:phone":"+49 4931/8431",
    "sg:postcode":"26506",
    "sg:province":"Niedersachsen",
    "wof:name":"J. Von Der Ohe",
    "wof:placetype":"venue"
},
  "geometry": {"coordinates":[7.1611089706,53.6168861389],"type":"Point"}
}