{
  "type": "Feature",
  "properties": {
    "iso:country":"DE",
    "sg:address":"Becklinger Str. 32",
    "sg:city":"Fallingbostel",
    "sg:phone":"+49 5163/98080",
    "sg:postcode":"29683",
    "sg:province":"Niedersachsen",
    "wof:name":"Sisovit Jan Siemsgl\u00fcss Gmbh",
    "wof:placetype":"venue"
},
  "geometry": {"coordinates":[9.77757,52.897228],"type":"Point"}
}