{
  "type": "Feature",
  "properties": {
    "iso:country":"DE",
    "sg:address":"Hannoversche Str. 112",
    "sg:city":"G\u00f6ttingen",
    "sg:phone":"+49 551/31512",
    "sg:postcode":"37077",
    "sg:province":"Niedersachsen",
    "wof:name":"Restaurant Rolf Gerdes",
    "wof:placetype":"venue"
},
  "geometry": {"coordinates":[9.93222332,51.5612068176],"type":"Point"}
}