{
  "type": "Feature",
  "properties": {
    "iso:country":"DE",
    "sg:address":"Kirchhofsbrink 1",
    "sg:city":"Emmerthal",
    "sg:phone":"+49 5157/213",
    "sg:postcode":"31860",
    "sg:province":"Niedersachsen",
    "wof:name":"Wilhelm Wessel",
    "wof:placetype":"venue"
},
  "geometry": {"coordinates":[9.482416,52.019997],"type":"Point"}
}