{
  "type": "Feature",
  "properties": {
    "iso:country":"DE",
    "sg:address":"Untere Ortsstr. 2",
    "sg:city":"Schiltberg",
    "sg:phone":"+49 8259/1071",
    "sg:postcode":"86576",
    "sg:province":"Bayern",
    "wof:name":"Konrad J\u00e4ger",
    "wof:placetype":"venue"
},
  "geometry": {"coordinates":[11.2487621307,48.4655761719],"type":"Point"}
}