{
  "type": "Feature",
  "properties": {
    "iso:country":"DE",
    "sg:address":"Krempelsdorfer Allee 51 a",
    "sg:city":"L\u00fcbeck",
    "sg:phone":"+49 451/4993994",
    "sg:postcode":"23556",
    "sg:province":"Schleswig-Holstein",
    "wof:name":"Hans-j\u00fcrgen Sch\u00fcttler Steuerberater",
    "wof:placetype":"venue"
},
  "geometry": {"coordinates":[10.6563940048,53.8824462891],"type":"Point"}
}