{
  "type": "Feature",
  "properties": {
    "iso:country":"DE",
    "sg:address":"Gustav-Hertz-Str. 24",
    "sg:city":"Straubing",
    "sg:phone":"+49 9421/63982",
    "sg:postcode":"94315",
    "sg:province":"Bayern",
    "wof:name":"Gruber-folien Inh. Erich Gruber",
    "wof:placetype":"venue"
},
  "geometry": {"coordinates":[12.627624,48.888618],"type":"Point"}
}