{
  "type": "Feature",
  "properties": {
    "iso:country":"DE",
    "sg:address":"Lange Str. 39",
    "sg:city":"Waiblingen",
    "sg:phone":"+49 7151/53222",
    "sg:postcode":"71332",
    "sg:province":"Baden-W\u00fcrttemberg",
    "wof:name":"Eisele Stahlwaren",
    "wof:placetype":"venue"
},
  "geometry": {"coordinates":[9.3162088394,48.8327598572],"type":"Point"}
}