{
  "type": "Feature",
  "properties": {
    "iso:country":"DE",
    "sg:address":"Adolf-Kolping-Str. 10",
    "sg:city":"Ebern",
    "sg:phone":"+49 9531/8319",
    "sg:postcode":"96106",
    "sg:province":"Bayern",
    "wof:name":"Reiner Dehler",
    "wof:placetype":"venue"
},
  "geometry": {"coordinates":[10.801451,50.101501],"type":"Point"}
}