{
  "type": "Feature",
  "properties": {
    "iso:country":"DE",
    "sg:address":"Bechemstr. 22",
    "sg:city":"Duisburg",
    "sg:phone":"+49 203/331888",
    "sg:postcode":"47058",
    "sg:province":"Nordrhein-Westfalen",
    "wof:name":"W. Biller Steuerberater",
    "wof:placetype":"venue"
},
  "geometry": {"coordinates":[6.7838888168,51.4345588684],"type":"Point"}
}