{
  "type": "Feature",
  "properties": {
    "iso:country":"DE",
    "sg:address":"Regensburger Str. 38",
    "sg:city":"Burglengenfeld",
    "sg:phone":"+49 9471/8767",
    "sg:postcode":"93133",
    "sg:province":"Bayern",
    "wof:name":"Apart Kg",
    "wof:placetype":"venue"
},
  "geometry": {"coordinates":[12.046391,49.203499],"type":"Point"}
}