{
  "type": "Feature",
  "properties": {
    "iso:country":"DE",
    "sg:address":"Zehntstr. 5",
    "sg:city":"Mannheim",
    "sg:phone":"+49 621/311800",
    "sg:postcode":"68169",
    "sg:province":"Baden-W\u00fcrttemberg",
    "wof:name":"Wollschl\u00e4ger Gmbh",
    "wof:placetype":"venue"
},
  "geometry": {"coordinates":[8.464748,49.499496],"type":"Point"}
}