{
  "type": "Feature",
  "properties": {
    "iso:country":"DE",
    "sg:address":"Hauptstr. 14",
    "sg:city":"J\u00f6rnstorf",
    "sg:phone":"+49 38294/78228",
    "sg:postcode":"18233",
    "sg:province":"Mecklenburg-Vorpommern",
    "wof:name":"Marianne Kreutzfeldt",
    "wof:placetype":"venue"
},
  "geometry": {"coordinates":[11.672425,54.03154],"type":"Point"}
}