{
  "type": "Feature",
  "properties": {
    "iso:country":"DE",
    "sg:address":"Wallstr. 5",
    "sg:city":"Bayreuth",
    "sg:phone":"+49 921/61206",
    "sg:postcode":"95445",
    "sg:province":"Bayern",
    "wof:name":"G\u00fcnther Kotter",
    "wof:placetype":"venue"
},
  "geometry": {"coordinates":[11.553462,49.937805],"type":"Point"}
}