{
  "type": "Feature",
  "properties": {
    "iso:country":"DE",
    "sg:address":"M\u00fchlenbach 7",
    "sg:city":"K\u00f6ln",
    "sg:phone":"+49 221/232497",
    "sg:postcode":"50676",
    "sg:province":"Nordrhein-Westfalen",
    "wof:name":"Wilhelm L\u00f6venich Inh. Hubertine L\u00f6venich E. K.",
    "wof:placetype":"venue"
},
  "geometry": {"coordinates":[6.956687,50.933071],"type":"Point"}
}