{
  "type": "Feature",
  "properties": {
    "iso:country":"DE",
    "sg:address":"Griesweg 17",
    "sg:city":"M\u00fchlheim",
    "sg:phone":"+49 7463/345",
    "sg:postcode":"78570",
    "sg:province":"Baden-W\u00fcrttemberg",
    "wof:name":"Christian Frick",
    "wof:placetype":"venue"
},
  "geometry": {"coordinates":[8.884174,48.029346],"type":"Point"}
}