{
  "type": "Feature",
  "properties": {
    "iso:country":"DE",
    "sg:address":"H\u00fclsmeyerstr. 48",
    "sg:city":"D\u00fcsseldorf",
    "sg:postcode":"40629",
    "sg:province":"Nordrhein-Westfalen",
    "wof:name":"Teleprint Gmbh",
    "wof:placetype":"venue"
},
  "geometry": {"coordinates":[6.865528,51.258663],"type":"Point"}
}