{
  "type": "Feature",
  "properties": {
    "iso:country":"DE",
    "sg:address":"Albert-Schweitzer-Str. 14",
    "sg:city":"Eppelheim",
    "sg:phone":"+49 6221/767169",
    "sg:postcode":"69214",
    "sg:province":"Baden-W\u00fcrttemberg",
    "wof:name":"Bernhard Beigel Rechtsanwalt",
    "wof:placetype":"venue"
},
  "geometry": {"coordinates":[8.6267471313,49.3941688538],"type":"Point"}
}