{
  "type": "Feature",
  "properties": {
    "iso:country":"DE",
    "sg:address":"Lindenstr. 125",
    "sg:city":"Siegburg",
    "sg:phone":"+49 2241/62918",
    "sg:postcode":"53721",
    "sg:province":"Nordrhein-Westfalen",
    "wof:name":"Industrie-akustik Siegburg Paul Schmitz Gmbh",
    "wof:placetype":"venue"
},
  "geometry": {"coordinates":[7.187888,50.800045],"type":"Point"}
}