{
  "type": "Feature",
  "properties": {
    "iso:country":"DE",
    "sg:address":"Alleestr. 9",
    "sg:city":"B\u00fcsum",
    "sg:phone":"+49 4834/2955",
    "sg:postcode":"25761",
    "sg:province":"Schleswig-Holstein",
    "wof:name":"Detlev Lintz",
    "wof:placetype":"venue"
},
  "geometry": {"coordinates":[8.860566,54.130486],"type":"Point"}
}