{
  "type": "Feature",
  "properties": {
    "iso:country":"DE",
    "sg:address":"Ernst-Th\u00e4lmann-Str. 28",
    "sg:city":"Gl\u00f6the",
    "sg:phone":"+49 39266/51037",
    "sg:postcode":"39240",
    "sg:province":"Sachsen-Anhalt",
    "wof:name":"E. Schleysing",
    "wof:placetype":"venue"
},
  "geometry": {"coordinates":[11.6719446182,51.9085006714],"type":"Point"}
}