{
  "type": "Feature",
  "properties": {
    "iso:country":"DE",
    "sg:address":"Reutleser Str. 57 a",
    "sg:city":"N\u00fcrnberg",
    "sg:phone":"+49 911/304553",
    "sg:postcode":"90427",
    "sg:province":"Bayern",
    "wof:name":"Konrad Kropf Architekt",
    "wof:placetype":"venue"
},
  "geometry": {"coordinates":[11.022142,49.533237],"type":"Point"}
}