{
  "type": "Feature",
  "properties": {
    "iso:country":"DE",
    "sg:address":"Richardstr. 13",
    "sg:city":"Zwickau",
    "sg:postcode":"08064",
    "sg:province":"Sachsen",
    "wof:name":"G. Resch",
    "wof:placetype":"venue"
},
  "geometry": {"coordinates":[12.4753427505,50.6789131165],"type":"Point"}
}