{
  "type": "Feature",
  "properties": {
    "iso:country":"DE",
    "sg:address":"Sennestadtring 15 a",
    "sg:city":"Bielefeld",
    "sg:phone":"+49 5205/2202",
    "sg:postcode":"33689",
    "sg:province":"Nordrhein-Westfalen",
    "wof:name":"Dreams",
    "wof:placetype":"venue"
},
  "geometry": {"coordinates":[8.5827112198,51.9461135864],"type":"Point"}
}