{
  "type": "Feature",
  "properties": {
    "iso:country":"DE",
    "sg:address":"Am Schiffbeker Berg 4",
    "sg:city":"Hamburg",
    "sg:postcode":"22111",
    "sg:province":"Hamburg",
    "wof:name":"Hvg Hanseatische Vertriebs-ges F\u00fcr Elektronische",
    "wof:placetype":"venue"
},
  "geometry": {"coordinates":[10.0924825668,53.542640686],"type":"Point"}
}