{
  "type": "Feature",
  "properties": {
    "iso:country":"DE",
    "sg:address":"Markstiege 2",
    "sg:city":"Borken",
    "sg:phone":"+49 2861/94160",
    "sg:postcode":"46325",
    "sg:province":"Nordrhein-Westfalen",
    "wof:name":"Altenheim Bodelschwingh-haus",
    "wof:placetype":"venue"
},
  "geometry": {"coordinates":[6.86591,51.856766],"type":"Point"}
}