{
  "type": "Feature",
  "properties": {
    "iso:country":"DE",
    "sg:address":"K\u00e4sbachstr. 15",
    "sg:city":"Ammerbuch",
    "sg:phone":"+49 7073/3151",
    "sg:postcode":"72119",
    "sg:province":"Baden-W\u00fcrttemberg",
    "wof:name":"Schlechter-m\u00fcller & Partner Gmbh",
    "wof:placetype":"venue"
},
  "geometry": {"coordinates":[8.9623384476,48.5328025818],"type":"Point"}
}