{
  "type": "Feature",
  "properties": {
    "iso:country":"DE",
    "sg:address":"Fr\u00f6merner Str. 2",
    "sg:city":"Fr\u00f6ndenberg",
    "sg:phone":"+49 2303/4654",
    "sg:postcode":"58730",
    "sg:province":"Nordrhein-Westfalen",
    "wof:name":"Fritz F\u00fclbeck",
    "wof:placetype":"venue"
},
  "geometry": {"coordinates":[7.770545,51.515938],"type":"Point"}
}