{
  "type": "Feature",
  "properties": {
    "iso:country":"DE",
    "sg:address":"Geltendorf",
    "sg:city":"Geltendorf",
    "sg:phone":"+49 8193/8435",
    "sg:postcode":"82269",
    "sg:province":"Bayern",
    "wof:name":"Raiffeisenbank Eresing Eg",
    "wof:placetype":"venue"
},
  "geometry": {"coordinates":[11.02593,48.122639],"type":"Point"}
}