{
  "type": "Feature",
  "properties": {
    "iso:country":"DE",
    "sg:address":"Grundstr. 148",
    "sg:city":"Dresden",
    "sg:phone":"+49 351/269840",
    "sg:postcode":"01324",
    "sg:province":"Sachsen",
    "wof:name":"Ulf Nobe",
    "wof:placetype":"venue"
},
  "geometry": {"coordinates":[13.8436098099,51.0595855713],"type":"Point"}
}