{
  "type": "Feature",
  "properties": {
    "iso:country":"DE",
    "sg:address":"Dorfstr. 31",
    "sg:city":"Gro\u00dftreben-Zwethau",
    "sg:postcode":"04886",
    "sg:province":"Sachsen",
    "wof:name":"Irene Schoechert",
    "wof:placetype":"venue"
},
  "geometry": {"coordinates":[13.0082817078,51.6380271912],"type":"Point"}
}