{
  "type": "Feature",
  "properties": {
    "iso:country":"DE",
    "sg:address":"Alte Neckarelzer Str. 24",
    "sg:city":"Mosbach",
    "sg:phone":"+49 4962/6193970",
    "sg:postcode":"74821",
    "sg:province":"Baden-W\u00fcrttemberg",
    "wof:name":"Cae Weisz Systemtechnik Gmbh",
    "wof:placetype":"venue"
},
  "geometry": {"coordinates":[9.124128,49.342537],"type":"Point"}
}