{
  "type": "Feature",
  "properties": {
    "iso:country":"DE",
    "sg:address":"Brauereistr. 6",
    "sg:city":"Dierdorf",
    "sg:phone":"+49 2689/979402",
    "sg:postcode":"56269",
    "sg:province":"Rheinland-Pfalz",
    "wof:name":"Rita Griesche",
    "wof:placetype":"venue"
},
  "geometry": {"coordinates":[7.6501407623,50.5440673828],"type":"Point"}
}