{
  "type": "Feature",
  "properties": {
    "iso:country":"DE",
    "sg:address":"Hohenzollernstr. 1",
    "sg:city":"Recklinghausen",
    "sg:phone":"+49 2361/102010",
    "sg:postcode":"45659",
    "sg:province":"Nordrhein-Westfalen",
    "wof:name":"Diakoniestation",
    "wof:placetype":"venue"
},
  "geometry": {"coordinates":[7.195617,51.608871],"type":"Point"}
}