{
  "type": "Feature",
  "properties": {
    "iso:country":"DE",
    "sg:address":"Im Interpark",
    "sg:city":"Offenbach",
    "sg:phone":"+49 4963/4898420",
    "sg:postcode":"76877",
    "sg:province":"Rheinland-Pfalz",
    "wof:name":"Rid Gmbh Anlagenbau Metallbau Industriemontage",
    "wof:placetype":"venue"
},
  "geometry": {"coordinates":[8.19031,49.1931],"type":"Point"}
}