{
  "type": "Feature",
  "properties": {
    "iso:country":"DE",
    "sg:address":"Bahnhofstr. 39",
    "sg:city":"Haan",
    "sg:phone":"+49 212/98172",
    "sg:postcode":"42781",
    "sg:province":"Nordrhein-Westfalen",
    "wof:name":"K. Bunk",
    "wof:placetype":"venue"
},
  "geometry": {"coordinates":[7.002188,51.190376],"type":"Point"}
}