{
  "type": "Feature",
  "properties": {
    "iso:country":"DE",
    "sg:address":"Twieh\u00fcserweg 59",
    "sg:city":"Rheda-Wiedenbr\u00fcck",
    "sg:phone":"+49 5242/3110",
    "sg:postcode":"33378",
    "sg:province":"Nordrhein-Westfalen",
    "wof:name":"Hans-dieter Frymark",
    "wof:placetype":"venue"
},
  "geometry": {"coordinates":[8.289731,51.833553],"type":"Point"}
}