{
  "type": "Feature",
  "properties": {
    "iso:country":"DE",
    "sg:address":"Leipziger Str. 18",
    "sg:city":"Altenburg",
    "sg:phone":"+49 3447/4568",
    "sg:postcode":"04600",
    "sg:province":"Th\u00fcringen",
    "wof:name":"Helmut Kirbach",
    "wof:placetype":"venue"
},
  "geometry": {"coordinates":[12.4462995529,50.9944992065],"type":"Point"}
}