{
  "type": "Feature",
  "properties": {
    "iso:country":"DE",
    "sg:address":"B\u00fcckeburger Str. 18",
    "sg:city":"Kamen",
    "sg:phone":"+49 2307/74967",
    "sg:postcode":"59174",
    "sg:province":"Nordrhein-Westfalen",
    "wof:name":"Bauelemente Hartwig",
    "wof:placetype":"venue"
},
  "geometry": {"coordinates":[7.655739,51.574554],"type":"Point"}
}