{
  "type": "Feature",
  "properties": {
    "iso:country":"DE",
    "sg:address":"Securiusstr. 54",
    "sg:city":"Delitzsch",
    "sg:phone":"+49 34202/60155",
    "sg:postcode":"04509",
    "sg:province":"Sachsen",
    "wof:name":"Bernd Oehmichen",
    "wof:placetype":"venue"
},
  "geometry": {"coordinates":[12.326748848,51.5324211121],"type":"Point"}
}