{
  "type": "Feature",
  "properties": {
    "iso:country":"DE",
    "sg:address":"Am Strand 4",
    "sg:city":"Ottenhain",
    "sg:phone":"+49 34341/42716",
    "sg:postcode":"04643",
    "sg:province":"Sachsen",
    "wof:name":"P. Kahl",
    "wof:placetype":"venue"
},
  "geometry": {"coordinates":[12.698162,51.080788],"type":"Point"}
}