{
  "type": "Feature",
  "properties": {
    "iso:country":"DE",
    "sg:address":"Ursulastr. 3",
    "sg:city":"Nordhorn",
    "sg:phone":"+49 5921/7080",
    "sg:postcode":"48529",
    "sg:province":"Niedersachsen",
    "wof:name":"Beton- Und Monierbau Gmbh",
    "wof:placetype":"venue"
},
  "geometry": {"coordinates":[7.0616412163,52.4063186646],"type":"Point"}
}