{
  "type": "Feature",
  "properties": {
    "iso:country":"DE",
    "sg:address":"Taunusstr. 4",
    "sg:city":"Ginsheim-Gustavsburg",
    "sg:phone":"+49 6144/32517",
    "sg:postcode":"65462",
    "sg:province":"Hessen",
    "wof:name":"Kupferkanne",
    "wof:placetype":"venue"
},
  "geometry": {"coordinates":[8.3477268219,49.9723815918],"type":"Point"}
}