{
  "type": "Feature",
  "properties": {
    "iso:country":"DE",
    "sg:address":"Hauptstr. 104",
    "sg:city":"Ubstadt-Weiher",
    "sg:phone":"+49 7251/96960",
    "sg:postcode":"76698",
    "sg:province":"Baden-W\u00fcrttemberg",
    "wof:name":"C. Rosenkranz-hoselt Steuerberater",
    "wof:placetype":"venue"
},
  "geometry": {"coordinates":[8.623167038,49.1795463562],"type":"Point"}
}