{
  "type": "Feature",
  "properties": {
    "iso:country":"DE",
    "sg:address":"Zimmerau 10",
    "sg:city":"Rinchnach",
    "sg:phone":"+49 9922/60166",
    "sg:postcode":"94269",
    "sg:province":"Bayern",
    "wof:name":"Josef Ertl Sen.",
    "wof:placetype":"venue"
},
  "geometry": {"coordinates":[13.2005605698,48.9512481689],"type":"Point"}
}