{
  "type": "Feature",
  "properties": {
    "iso:country":"DE",
    "sg:address":"Adalbertsteinweg 112",
    "sg:city":"Aachen",
    "sg:phone":"+49 241/514450",
    "sg:postcode":"52070",
    "sg:province":"Nordrhein-Westfalen",
    "wof:name":"Dr. Med. W. Neuefeind Arzt F\u00fcr Gyn\u00e4kologie",
    "wof:placetype":"venue"
},
  "geometry": {"coordinates":[6.1027297974,50.7743988037],"type":"Point"}
}