{
  "type": "Feature",
  "properties": {
    "iso:country":"DE",
    "sg:address":"Licht\u00e4cker 46",
    "sg:city":"Ludwigsburg",
    "sg:phone":"+49 7141/35468",
    "sg:postcode":"71634",
    "sg:province":"Baden-W\u00fcrttemberg",
    "wof:name":"G\u00fcnther Wiedmann Rechtsanwalt",
    "wof:placetype":"venue"
},
  "geometry": {"coordinates":[9.1791505814,48.9120826721],"type":"Point"}
}