{
  "type": "Feature",
  "properties": {
    "iso:country":"DE",
    "sg:address":"Stendaler Str. 2",
    "sg:city":"Haldensleben",
    "sg:phone":"+49 3904/40416",
    "sg:postcode":"39340",
    "sg:province":"Sachsen-Anhalt",
    "wof:name":"J\u00f6rg Lange",
    "wof:placetype":"venue"
},
  "geometry": {"coordinates":[11.412406,52.29187],"type":"Point"}
}