{
  "type": "Feature",
  "properties": {
    "iso:country":"DE",
    "sg:address":"Katharinenweg 14 a",
    "sg:city":"Apolda",
    "sg:postcode":"99510",
    "sg:province":"Th\u00fcringen",
    "wof:name":"Erdstoffannahme Katharinenweg Apolda Gmbh & Co. Kg",
    "wof:placetype":"venue"
},
  "geometry": {"coordinates":[11.517063,51.035885],"type":"Point"}
}