{
  "type": "Feature",
  "properties": {
    "iso:country":"DE",
    "sg:address":"Bahnhofsweg 8",
    "sg:city":"Freystadt",
    "sg:phone":"+49 9179/94090",
    "sg:postcode":"92342",
    "sg:province":"Bayern",
    "wof:name":"Holzbau Dess Gmbh",
    "wof:placetype":"venue"
},
  "geometry": {"coordinates":[11.3268451691,49.2000236511],"type":"Point"}
}