{
  "type": "Feature",
  "properties": {
    "iso:country":"DE",
    "sg:address":"Schulzestr. 29",
    "sg:city":"Berlin",
    "sg:phone":"+49 30/4811672",
    "sg:postcode":"13187",
    "sg:province":"Berlin",
    "wof:name":"Schottenschulle Co Peter Schultze",
    "wof:placetype":"venue"
},
  "geometry": {"coordinates":[13.3916053772,52.5665931702],"type":"Point"}
}