{
  "type": "Feature",
  "properties": {
    "iso:country":"DE",
    "sg:address":"Schulstr. 49",
    "sg:city":"Gummersbach",
    "sg:phone":"+49 2261/979321",
    "sg:postcode":"51645",
    "sg:province":"Nordrhein-Westfalen",
    "wof:name":"Sanner Kg Schirmfabrik",
    "wof:placetype":"venue"
},
  "geometry": {"coordinates":[7.5351281166,50.9819641113],"type":"Point"}
}