{
  "type": "Feature",
  "properties": {
    "iso:country":"DE",
    "sg:address":"Frauenhofer Str. 5",
    "sg:city":"Darmstadt",
    "sg:phone":"+49 4961/511550",
    "sg:postcode":"64283",
    "sg:province":"Hessen",
    "wof:name":"Zentrum F\u00dcr Graphische Daten- Verarbeitung E. V.",
    "wof:placetype":"venue"
},
  "geometry": {"coordinates":[8.659315,49.874119],"type":"Point"}
}