{
  "type": "Feature",
  "properties": {
    "iso:country":"DE",
    "sg:address":"Maillingerstr. 32",
    "sg:city":"M\u00fcnchen",
    "sg:phone":"+49 89/1239410",
    "sg:postcode":"80636",
    "sg:province":"Bayern",
    "wof:name":"Mkh Steuerberatungs- Gesellschaft Mbh",
    "wof:placetype":"venue"
},
  "geometry": {"coordinates":[11.5433950424,48.1470794678],"type":"Point"}
}