{
  "type": "Feature",
  "properties": {
    "iso:country":"DE",
    "sg:address":"Alte Heerstr. 91a",
    "sg:city":"Koblenz",
    "sg:phone":"+49 261/53784",
    "sg:postcode":"56076",
    "sg:province":"Rheinland-Pfalz",
    "wof:name":"Hagra Wohnbau Gmbh",
    "wof:placetype":"venue"
},
  "geometry": {"coordinates":[7.6064300537,50.3316497803],"type":"Point"}
}