{
  "type": "Feature",
  "properties": {
    "iso:country":"DE",
    "sg:address":"Rutenbergstr. 25",
    "sg:city":"Harsum",
    "sg:phone":"+49 5128/4687",
    "sg:postcode":"31177",
    "sg:province":"Niedersachsen",
    "wof:name":"Wendler",
    "wof:placetype":"venue"
},
  "geometry": {"coordinates":[10.035693,52.217674],"type":"Point"}
}