{
  "type": "Feature",
  "properties": {
    "iso:country":"DE",
    "sg:address":"Schneewiesenstr. 12",
    "sg:city":"Birkenfeld",
    "sg:phone":"+49 6782/1281",
    "sg:postcode":"55765",
    "sg:province":"Rheinland-Pfalz",
    "wof:name":"Sch\u00e4fer Und Fiedler Rechtsanw\u00e4lte",
    "wof:placetype":"venue"
},
  "geometry": {"coordinates":[7.1670751572,49.6490478516],"type":"Point"}
}