{
  "type": "Feature",
  "properties": {
    "iso:country":"DE",
    "sg:address":"M\u00fchlenstr. 8",
    "sg:city":"Jever",
    "sg:postcode":"26441",
    "sg:province":"Niedersachsen",
    "wof:name":"Goldener Garten Im- Und Export Jever Gmbh",
    "wof:placetype":"venue"
},
  "geometry": {"coordinates":[7.905523777,53.572303772],"type":"Point"}
}