{
  "type": "Feature",
  "properties": {
    "iso:country":"DE",
    "sg:address":"Riemekestr. 160",
    "sg:city":"Paderborn",
    "sg:postcode":"33106",
    "sg:province":"Nordrhein-Westfalen",
    "wof:name":"Service One Facility Management Gmbh",
    "wof:placetype":"venue"
},
  "geometry": {"coordinates":[8.7152938843,51.715423584],"type":"Point"}
}