{
  "type": "Feature",
  "properties": {
    "iso:country":"DE",
    "sg:address":"Kappenzipfel 36",
    "sg:city":"G\u00fcnzburg",
    "sg:phone":"+49 8221/1223",
    "sg:postcode":"89312",
    "sg:province":"Bayern",
    "wof:name":"Klaus Jorga",
    "wof:placetype":"venue"
},
  "geometry": {"coordinates":[10.273448,48.458084],"type":"Point"}
}