{
  "type": "Feature",
  "properties": {
    "iso:country":"DE",
    "sg:address":"Kessenicher Str. 116a",
    "sg:city":"Euskirchen",
    "sg:phone":"+49 2251/56046",
    "sg:postcode":"53879",
    "sg:province":"Nordrhein-Westfalen",
    "wof:name":"Peter Christ Steuerberater",
    "wof:placetype":"venue"
},
  "geometry": {"coordinates":[6.7871980667,50.6678924561],"type":"Point"}
}