{
  "type": "Feature",
  "properties": {
    "iso:country":"DE",
    "sg:address":"Cannabichstr. 36",
    "sg:city":"Mannheim",
    "sg:phone":"+49 621/378811",
    "sg:postcode":"68167",
    "sg:province":"Baden-W\u00fcrttemberg",
    "wof:name":"Franz Baumg\u00e4rtner",
    "wof:placetype":"venue"
},
  "geometry": {"coordinates":[8.4837503433,49.4970054626],"type":"Point"}
}