{
  "type": "Feature",
  "properties": {
    "iso:country":"DE",
    "sg:address":"Lindenstr. 33",
    "sg:city":"Nellingen",
    "sg:phone":"+49 7337/96500",
    "sg:postcode":"89191",
    "sg:province":"Baden-W\u00fcrttemberg",
    "wof:name":"Willi Singerer Steuerberater",
    "wof:placetype":"venue"
},
  "geometry": {"coordinates":[9.7941246033,48.5458717346],"type":"Point"}
}