{
  "type": "Feature",
  "properties": {
    "iso:country":"DE",
    "sg:address":"Leipziger Str. 207",
    "sg:city":"Dresden",
    "sg:phone":"+49 351/8590377",
    "sg:postcode":"01139",
    "sg:province":"Sachsen",
    "wof:name":"J\u00fcno Dachdecker Gmbh",
    "wof:placetype":"venue"
},
  "geometry": {"coordinates":[13.704289,51.086365],"type":"Point"}
}