{
  "type": "Feature",
  "properties": {
    "iso:country":"DE",
    "sg:address":"Bauersweg 10a",
    "sg:city":"Buchholz",
    "sg:postcode":"21244",
    "sg:province":"Niedersachsen",
    "wof:name":"Fidi Gmbh",
    "wof:placetype":"venue"
},
  "geometry": {"coordinates":[9.860295,53.365501],"type":"Point"}
}