{
  "type": "Feature",
  "properties": {
    "iso:country":"DE",
    "sg:address":"Lichtendorfer Str. 5",
    "sg:city":"Schwerte",
    "sg:phone":"+49 2304/40424",
    "sg:postcode":"58239",
    "sg:province":"Nordrhein-Westfalen",
    "wof:name":"Haus Kreinberg",
    "wof:placetype":"venue"
},
  "geometry": {"coordinates":[7.5781607628,51.4544906616],"type":"Point"}
}