{
  "type": "Feature",
  "properties": {
    "iso:country":"DE",
    "sg:address":"Schenkendorfstr. 51",
    "sg:city":"Oberhausen",
    "sg:phone":"+49 208/862706",
    "sg:postcode":"46047",
    "sg:province":"Nordrhein-Westfalen",
    "wof:name":"Horst Lattki",
    "wof:placetype":"venue"
},
  "geometry": {"coordinates":[6.868060112,51.4795837402],"type":"Point"}
}