{
  "type": "Feature",
  "properties": {
    "iso:country":"DE",
    "sg:address":"Nickritzer Str 11",
    "sg:city":"Riesa",
    "sg:phone":"+49 3525/68490",
    "sg:postcode":"01589",
    "sg:province":"Sachsen",
    "wof:name":"Stratos Gmbh Dipl.-ing. Christoph Staroske",
    "wof:placetype":"venue"
},
  "geometry": {"coordinates":[13.290076,51.28672],"type":"Point"}
}