{
  "type": "Feature",
  "properties": {
    "iso:country":"DE",
    "sg:address":"Industriestr. 116",
    "sg:city":"Ludwigsfelde",
    "sg:phone":"+49 3378/804680",
    "sg:postcode":"14974",
    "sg:province":"Brandenburg",
    "wof:name":"Axma Beteiligungs- Und Handels Gmbh",
    "wof:placetype":"venue"
},
  "geometry": {"coordinates":[13.265109,52.317074],"type":"Point"}
}