{
  "type": "Feature",
  "properties": {
    "iso:country":"DE",
    "sg:address":"Hannebacher Str",
    "sg:city":"Kempenich",
    "sg:phone":"+49 2655/95920",
    "sg:postcode":"56746",
    "sg:province":"Rheinland-Pfalz",
    "wof:name":"Fibrolith-d\u00e4mmstoffe",
    "wof:placetype":"venue"
},
  "geometry": {"coordinates":[7.121465,50.42033],"type":"Point"}
}