{
  "type": "Feature",
  "properties": {
    "iso:country":"DE",
    "sg:address":"Jacob-Winter-Platz 1",
    "sg:city":"Dresden",
    "sg:phone":"+49 351/2841185",
    "sg:postcode":"01239",
    "sg:province":"Sachsen",
    "wof:name":"E.-k. Solich",
    "wof:placetype":"venue"
},
  "geometry": {"coordinates":[13.797233,51.004604],"type":"Point"}
}