{
  "type": "Feature",
  "properties": {
    "iso:country":"DE",
    "sg:address":"Am Feldrain 2",
    "sg:city":"Stadtlauringen",
    "sg:phone":"+49 9724/2892",
    "sg:postcode":"97488",
    "sg:province":"Bayern",
    "wof:name":"Klaus-ulrich K\u00f6hler Fotograf",
    "wof:placetype":"venue"
},
  "geometry": {"coordinates":[10.3664522171,50.1601333618],"type":"Point"}
}