{
  "type": "Feature",
  "properties": {
    "iso:country":"DE",
    "sg:address":"Attilastr. 177",
    "sg:city":"Berlin",
    "sg:phone":"+49 30/7512402",
    "sg:postcode":"12105",
    "sg:province":"Berlin",
    "wof:name":"Heinz-j\u00fcrgen Palm Dreherei-maschinenbau",
    "wof:placetype":"venue"
},
  "geometry": {"coordinates":[13.376517,52.455807],"type":"Point"}
}