{
  "type": "Feature",
  "properties": {
    "iso:country":"DE",
    "sg:address":"Hans-Sachs-Str. 10",
    "sg:city":"M\u00fcnchen",
    "sg:phone":"+49 89/2603116",
    "sg:postcode":"80469",
    "sg:province":"Bayern",
    "wof:name":"Thomas Schoeller Restaurator",
    "wof:placetype":"venue"
},
  "geometry": {"coordinates":[11.5696735382,48.1297798157],"type":"Point"}
}