{
  "type": "Feature",
  "properties": {
    "iso:country":"DE",
    "sg:address":"Guntherstr. 4",
    "sg:city":"Wendelstein",
    "sg:postcode":"90530",
    "sg:province":"Bayern",
    "wof:name":"Tks Transport-kombi Service Gmbh",
    "wof:placetype":"venue"
},
  "geometry": {"coordinates":[11.1749992371,49.3665237427],"type":"Point"}
}