{
  "type": "Feature",
  "properties": {
    "iso:country":"DE",
    "sg:address":"Pontstr. 151 a",
    "sg:city":"Aachen",
    "sg:phone":"+49 241/20153",
    "sg:postcode":"52062",
    "sg:province":"Nordrhein-Westfalen",
    "wof:name":"Manfred Bachmann",
    "wof:placetype":"venue"
},
  "geometry": {"coordinates":[6.0789680481,50.780834198],"type":"Point"}
}