{
  "type": "Feature",
  "properties": {
    "iso:country":"DE",
    "sg:address":"Hasslerstrasse",
    "sg:city":"Kolbermoor",
    "sg:phone":"+49 8031/96409",
    "sg:postcode":"83059",
    "sg:province":"Bayern",
    "wof:name":"Energydrinks-magicdrinks-spiritousen-importbiere",
    "wof:placetype":"venue"
},
  "geometry": {"coordinates":[12.062798,47.851555],"type":"Point"}
}