{
  "type": "Feature",
  "properties": {
    "iso:country":"DE",
    "sg:address":"M\u00fcggenkampstr. 43",
    "sg:city":"Hamburg",
    "sg:phone":"+49 40/496680",
    "sg:postcode":"20257",
    "sg:province":"Hamburg",
    "wof:name":"Marius Meyer",
    "wof:placetype":"venue"
},
  "geometry": {"coordinates":[9.9429254532,53.5797843933],"type":"Point"}
}