{
  "type": "Feature",
  "properties": {
    "iso:country":"DE",
    "sg:address":"Paderborner Str. 37",
    "sg:city":"Borchen",
    "sg:phone":"+49 5251/39298",
    "sg:postcode":"33178",
    "sg:province":"Nordrhein-Westfalen",
    "wof:name":"Eduard St\u00fcmpel",
    "wof:placetype":"venue"
},
  "geometry": {"coordinates":[8.724501,51.67252],"type":"Point"}
}