{
  "type": "Feature",
  "properties": {
    "iso:country":"DE",
    "sg:address":"Halmweg 26",
    "sg:city":"Delmenhorst",
    "sg:phone":"+49 4221/43575",
    "sg:postcode":"27751",
    "sg:province":"Niedersachsen",
    "wof:name":"Frank Wieczorek Immobilienmakler",
    "wof:placetype":"venue"
},
  "geometry": {"coordinates":[8.6603078842,53.0595932007],"type":"Point"}
}