{
  "type": "Feature",
  "properties": {
    "iso:country":"DE",
    "sg:address":"Hans-Sachs-Str. 6",
    "sg:city":"H\u00f6chstadt",
    "sg:phone":"+49 9193/1018",
    "sg:postcode":"91315",
    "sg:province":"Bayern",
    "wof:name":"Johann \u00d6ttinger",
    "wof:placetype":"venue"
},
  "geometry": {"coordinates":[10.8154916763,49.7063102722],"type":"Point"}
}