{
  "type": "Feature",
  "properties": {
    "iso:country":"DE",
    "sg:address":"Eichh\u00f6rnchenweg 3",
    "sg:city":"Erkner",
    "sg:phone":"+49 3362/4490",
    "sg:postcode":"15537",
    "sg:province":"Brandenburg",
    "wof:name":"Dirk Gericke",
    "wof:placetype":"venue"
},
  "geometry": {"coordinates":[13.755546,52.417282],"type":"Point"}
}