{
  "type": "Feature",
  "properties": {
    "iso:country":"DE",
    "sg:address":"M\u00f6nkhoffs Busch 1",
    "sg:city":"Essen",
    "sg:phone":"+49 201/582284",
    "sg:postcode":"45277",
    "sg:province":"Nordrhein-Westfalen",
    "wof:name":"Eberhard Ehlert Masseur",
    "wof:placetype":"venue"
},
  "geometry": {"coordinates":[7.089627,51.421371],"type":"Point"}
}