{
  "type": "Feature",
  "properties": {
    "iso:country":"DE",
    "sg:address":"Eberst\u00e4dter Str. 72",
    "sg:city":"Pfungstadt",
    "sg:phone":"+49 6157/2719",
    "sg:postcode":"64319",
    "sg:province":"Hessen",
    "wof:name":"B\u00e4ckerei Peter Kramer Gmbh",
    "wof:placetype":"venue"
},
  "geometry": {"coordinates":[8.602295,49.804527],"type":"Point"}
}