{
  "type": "Feature",
  "properties": {
    "iso:country":"DE",
    "sg:address":"Bahnhofstr. 44",
    "sg:city":"Hann. M\u00fcnden",
    "sg:phone":"+49 5541/2409",
    "sg:postcode":"34346",
    "sg:province":"Niedersachsen",
    "wof:name":"Hans-j\u00fcrgen M\u00f6ller Rechtsanwalt Und Notar",
    "wof:placetype":"venue"
},
  "geometry": {"coordinates":[9.6579351425,51.4136123657],"type":"Point"}
}