{
  "type": "Feature",
  "properties": {
    "iso:country":"DE",
    "sg:address":"Hauptstr. 17",
    "sg:city":"Kr\u00f6ppen",
    "sg:phone":"+49 6335/391",
    "sg:postcode":"66957",
    "sg:province":"Rheinland-Pfalz",
    "wof:name":"A. Und M. Buchheit",
    "wof:placetype":"venue"
},
  "geometry": {"coordinates":[7.526613,49.150002],"type":"Point"}
}