{
  "type": "Feature",
  "properties": {
    "iso:country":"DE",
    "sg:address":"Linsenstr. 12",
    "sg:city":"M\u00fchlhausen",
    "sg:phone":"+49 36013/371",
    "sg:postcode":"99974",
    "sg:province":"Th\u00fcringen",
    "wof:name":"J. Halbeisen Und Sohn",
    "wof:placetype":"venue"
},
  "geometry": {"coordinates":[10.4577407837,51.2077865601],"type":"Point"}
}