{
  "type": "Feature",
  "properties": {
    "iso:country":"DE",
    "sg:address":"Dr.-Peter-Jordan-Str. 28",
    "sg:city":"Bautzen",
    "sg:phone":"+49 3591/605454",
    "sg:postcode":"02625",
    "sg:province":"Sachsen",
    "wof:name":"Schlucknapf",
    "wof:placetype":"venue"
},
  "geometry": {"coordinates":[14.4347267151,51.1707038879],"type":"Point"}
}