{
  "type": "Feature",
  "properties": {
    "iso:country":"DE",
    "sg:address":"Engerstr. 159",
    "sg:city":"Herford",
    "sg:phone":"+49 5221/31555",
    "sg:postcode":"32051",
    "sg:province":"Nordrhein-Westfalen",
    "wof:name":"Stellmacher Gmbh",
    "wof:placetype":"venue"
},
  "geometry": {"coordinates":[8.63831,52.123138],"type":"Point"}
}