{
  "type": "Feature",
  "properties": {
    "iso:country":"DE",
    "sg:address":"Dingelstedterstr. 2",
    "sg:city":"Weimar",
    "sg:phone":"+49 3643/2659",
    "sg:postcode":"99423",
    "sg:province":"Th\u00fcringen",
    "wof:name":"Volksbank Weimar E. G.",
    "wof:placetype":"venue"
},
  "geometry": {"coordinates":[11.325348,50.979332],"type":"Point"}
}