{
  "type": "Feature",
  "properties": {
    "iso:country":"DE",
    "sg:address":"Bremer Str. 1",
    "sg:city":"Drebber",
    "sg:phone":"+49 5445/767",
    "sg:postcode":"49457",
    "sg:province":"Niedersachsen",
    "wof:name":"Rolf Brzezina Mineral\u00f6lhandel Gmbh",
    "wof:placetype":"venue"
},
  "geometry": {"coordinates":[8.422413,52.646496],"type":"Point"}
}