{
  "type": "Feature",
  "properties": {
    "iso:country":"DE",
    "sg:address":"Desmecke 5",
    "sg:city":"Brilon",
    "sg:phone":"+49 2961/8403",
    "sg:postcode":"59929",
    "sg:province":"Nordrhein-Westfalen",
    "wof:name":"Beerdigungsinstitut Elvira Schmitt",
    "wof:placetype":"venue"
},
  "geometry": {"coordinates":[8.507449,51.38105],"type":"Point"}
}