{
  "type": "Feature",
  "properties": {
    "iso:country":"DE",
    "sg:address":"Malsfeldstr. 1",
    "sg:city":"Roth",
    "sg:postcode":"57539",
    "sg:province":"Rheinland-Pfalz",
    "wof:name":"Druckerei M\u00fcller Verwaltungs Gmbh",
    "wof:placetype":"venue"
},
  "geometry": {"coordinates":[7.706195,50.761391],"type":"Point"}
}