{
  "type": "Feature",
  "properties": {
    "iso:country":"DE",
    "sg:address":"Giershagener Str. 1",
    "sg:city":"Diemelsee",
    "sg:phone":"+49 5633/1005",
    "sg:postcode":"34519",
    "sg:province":"Hessen",
    "wof:name":"Heinrich Wilke",
    "wof:placetype":"venue"
},
  "geometry": {"coordinates":[8.8117208481,51.3636436462],"type":"Point"}
}