{
  "type": "Feature",
  "properties": {
    "iso:country":"DE",
    "sg:address":"F\u00f6hrichstr. 30",
    "sg:city":"Stuttgart",
    "sg:phone":"+49 711/853851",
    "sg:postcode":"70469",
    "sg:province":"Baden-W\u00fcrttemberg",
    "wof:name":"Dieter Weber",
    "wof:placetype":"venue"
},
  "geometry": {"coordinates":[9.148226738,48.8107872009],"type":"Point"}
}