{
  "type": "Feature",
  "properties": {
    "iso:country":"DE",
    "sg:address":"Uhlmannstr. 39",
    "sg:city":"Laupheim",
    "sg:phone":"+49 7392/96650",
    "sg:postcode":"88471",
    "sg:province":"Baden-W\u00fcrttemberg",
    "wof:name":"Bucher Fensterbau Gmbh & Co. Kg",
    "wof:placetype":"venue"
},
  "geometry": {"coordinates":[9.872569,48.237206],"type":"Point"}
}