{
  "type": "Feature",
  "properties": {
    "iso:country":"DE",
    "sg:address":"Erzebacher Str. 2",
    "sg:city":"Neuenstein",
    "sg:phone":"+49 6677/340",
    "sg:postcode":"36286",
    "sg:province":"Hessen",
    "wof:name":"Ev. Pfarramt Obergeis",
    "wof:placetype":"venue"
},
  "geometry": {"coordinates":[9.592297554,50.9040107727],"type":"Point"}
}