{
  "type": "Feature",
  "properties": {
    "iso:country":"DE",
    "sg:address":"Am Eichelkamp 213",
    "sg:city":"Hilden",
    "sg:phone":"+49 2103/62697",
    "sg:postcode":"40723",
    "sg:province":"Nordrhein-Westfalen",
    "wof:name":"Helmut Gruber",
    "wof:placetype":"venue"
},
  "geometry": {"coordinates":[6.9525361061,51.1602096558],"type":"Point"}
}