{
  "type": "Feature",
  "properties": {
    "iso:country":"DE",
    "sg:address":"Neckargartacherstr.90",
    "sg:city":"Heilbronn",
    "sg:phone":"+49 7131666782542",
    "sg:postcode":"74080",
    "sg:province":"Baden-W\u00fcrttemberg",
    "wof:name":"Televideo Entertainment",
    "wof:placetype":"venue"
},
  "geometry": {"coordinates":[9.1961755753,49.1469917297],"type":"Point"}
}