{
  "type": "Feature",
  "properties": {
    "iso:country":"DE",
    "sg:address":"Im Hainbruch 28",
    "sg:city":"Gusterath",
    "sg:phone":"+49 6588/7477",
    "sg:postcode":"54317",
    "sg:province":"Rheinland-Pfalz",
    "wof:name":"Koch Fliesen Gmbh",
    "wof:placetype":"venue"
},
  "geometry": {"coordinates":[6.7103328705,49.7001571655],"type":"Point"}
}