{
  "type": "Feature",
  "properties": {
    "iso:country":"DE",
    "sg:address":"Karlstr. 18",
    "sg:city":"Pfalzgrafenweiler",
    "sg:phone":"+49 7445/2396",
    "sg:postcode":"72285",
    "sg:province":"Baden-W\u00fcrttemberg",
    "wof:name":"R. Schmid Transporte Inh. E. Schmid",
    "wof:placetype":"venue"
},
  "geometry": {"coordinates":[8.5659809113,48.5304985046],"type":"Point"}
}