{
  "type": "Feature",
  "properties": {
    "iso:country":"DE",
    "sg:address":"Reinickendorfer Str. 55",
    "sg:city":"Berlin",
    "sg:phone":"+49 30/4572325",
    "sg:postcode":"13347",
    "sg:province":"Berlin",
    "wof:name":"Studiob\u00fchne Berlin",
    "wof:placetype":"venue"
},
  "geometry": {"coordinates":[13.367096,52.552551],"type":"Point"}
}