{
  "type": "Feature",
  "properties": {
    "iso:country":"DE",
    "sg:address":"Sennockstr. 26",
    "sg:city":"Berlin",
    "sg:phone":"+49 30/7522027",
    "sg:postcode":"12103",
    "sg:province":"Berlin",
    "wof:name":"Lechtenb\u00f6hmer Gmbh",
    "wof:placetype":"venue"
},
  "geometry": {"coordinates":[13.3813762665,52.467956543],"type":"Point"}
}