{
  "type": "Feature",
  "properties": {
    "iso:country":"DE",
    "sg:address":"S\u00f6ller Str. 7",
    "sg:city":"Gstadt",
    "sg:phone":"+49 8054/346",
    "sg:postcode":"83257",
    "sg:province":"Bayern",
    "wof:name":"Leonhard Dobler Mech. Werkstatt",
    "wof:placetype":"venue"
},
  "geometry": {"coordinates":[12.436255,47.915737],"type":"Point"}
}