{
  "type": "Feature",
  "properties": {
    "iso:country":"DE",
    "sg:address":"Heidweg 4",
    "sg:city":"Goldenstedt",
    "sg:phone":"+49 4441/4464",
    "sg:postcode":"49424",
    "sg:province":"Niedersachsen",
    "wof:name":"Arnold H\u00f6ne",
    "wof:placetype":"venue"
},
  "geometry": {"coordinates":[8.366002,52.765167],"type":"Point"}
}