{
  "type": "Feature",
  "properties": {
    "iso:country":"DE",
    "sg:address":"Ruhrorter Str.",
    "sg:city":"Duisburg",
    "sg:phone":"+49 203/81604",
    "sg:postcode":"47119",
    "sg:province":"Nordrhein-Westfalen",
    "wof:name":"Aral Ag",
    "wof:placetype":"venue"
},
  "geometry": {"coordinates":[6.7433700562,51.4471054077],"type":"Point"}
}