{
  "type": "Feature",
  "properties": {
    "iso:country":"DE",
    "sg:address":"M\u00f6ckernstr. 65",
    "sg:city":"Berlin",
    "sg:phone":"+49 30/78952633",
    "sg:postcode":"10965",
    "sg:province":"Berlin",
    "wof:name":"Hspg-keller-komplett- Service Und Playpoint Gmbh",
    "wof:placetype":"venue"
},
  "geometry": {"coordinates":[13.379133,52.49054],"type":"Point"}
}