{
  "type": "Feature",
  "properties": {
    "iso:country":"DE",
    "sg:address":"Am Vogelsgesang 15",
    "sg:city":"Einselthum",
    "sg:phone":"+49 6355/1405",
    "sg:postcode":"67308",
    "sg:province":"Rheinland-Pfalz",
    "wof:name":"Fritz Radmacher Ergotherapeutsche Praxis",
    "wof:placetype":"venue"
},
  "geometry": {"coordinates":[8.127574,49.649704],"type":"Point"}
}