{
  "type": "Feature",
  "properties": {
    "iso:country":"DE",
    "sg:address":"Lietzenburger Str. 91",
    "sg:city":"Berlin",
    "sg:phone":"+49 30/88550660",
    "sg:postcode":"10719",
    "sg:province":"Berlin",
    "wof:name":"Jerzy Krolikowski Architekt",
    "wof:placetype":"venue"
},
  "geometry": {"coordinates":[13.321813,52.499702],"type":"Point"}
}