{
  "type": "Feature",
  "properties": {
    "iso:country":"DE",
    "sg:address":"Christophorusstr. 13",
    "sg:city":"Bergisch Gladbach",
    "sg:phone":"+49 2202/932627",
    "sg:postcode":"51469",
    "sg:province":"Nordrhein-Westfalen",
    "wof:name":"Hans Gerd Gro\u00dfbach E. Kfm.",
    "wof:placetype":"venue"
},
  "geometry": {"coordinates":[7.1403570175,50.982585907],"type":"Point"}
}