{
  "type": "Feature",
  "properties": {
    "iso:country":"DE",
    "sg:address":"Hasengartenstr. 42",
    "sg:city":"Wiesbaden",
    "sg:phone":"+49 611/951590",
    "sg:postcode":"65189",
    "sg:province":"Hessen",
    "wof:name":"Lutz Schumann",
    "wof:placetype":"venue"
},
  "geometry": {"coordinates":[8.259513855,50.0600624084],"type":"Point"}
}