{
  "type": "Feature",
  "properties": {
    "iso:country":"DE",
    "sg:address":"Soester Str. 21",
    "sg:city":"Lippetal",
    "sg:phone":"+49 2923/1343",
    "sg:postcode":"59510",
    "sg:province":"Nordrhein-Westfalen",
    "wof:name":"K. R\u00fcther Gmbh",
    "wof:placetype":"venue"
},
  "geometry": {"coordinates":[8.0999126434,51.6300621033],"type":"Point"}
}