{
  "type": "Feature",
  "properties": {
    "iso:country":"DE",
    "sg:address":"Lichtenrader Damm 95",
    "sg:city":"Berlin",
    "sg:phone":"+49 30/7458701",
    "sg:postcode":"12305",
    "sg:province":"Berlin",
    "wof:name":"Ottmann Lichtenrader Damm 95",
    "wof:placetype":"venue"
},
  "geometry": {"coordinates":[13.406761,52.405102],"type":"Point"}
}