{
  "type": "Feature",
  "properties": {
    "iso:country":"DE",
    "sg:address":"Burglehn 1",
    "sg:city":"Bautzen",
    "sg:phone":"+49 3591/490141",
    "sg:postcode":"02625",
    "sg:province":"Sachsen",
    "wof:name":"M\u00f6nchshof",
    "wof:placetype":"venue"
},
  "geometry": {"coordinates":[14.4209060669,51.1816749573],"type":"Point"}
}