{
  "type": "Feature",
  "properties": {
    "iso:country":"DE",
    "sg:address":"Frankenweg 23",
    "sg:city":"Brilon",
    "sg:phone":"+49 2961/2882",
    "sg:postcode":"59929",
    "sg:province":"Nordrhein-Westfalen",
    "wof:name":"H.-h. Kohn",
    "wof:placetype":"venue"
},
  "geometry": {"coordinates":[8.5731010437,51.3870887756],"type":"Point"}
}