{
  "type": "Feature",
  "properties": {
    "iso:country":"DE",
    "sg:address":"\u00c4hrenstr. 7",
    "sg:city":"Duisburg",
    "sg:phone":"+49 203/765588",
    "sg:postcode":"47269",
    "sg:province":"Nordrhein-Westfalen",
    "wof:name":"Hartmut Lofing",
    "wof:placetype":"venue"
},
  "geometry": {"coordinates":[6.7759690285,51.3499946594],"type":"Point"}
}