{
  "type": "Feature",
  "properties": {
    "iso:country":"DE",
    "sg:address":"Rindermarkt 3",
    "sg:city":"Freising",
    "sg:phone":"+49 8161/94015",
    "sg:postcode":"85354",
    "sg:province":"Bayern",
    "wof:name":"Beratungsstelle F\u00fcr Alkoholiker",
    "wof:placetype":"venue"
},
  "geometry": {"coordinates":[11.741986,48.40118],"type":"Point"}
}