{
  "type": "Feature",
  "properties": {
    "iso:country":"DE",
    "sg:address":"Frankfurter Str. 88",
    "sg:city":"Bad Camberg",
    "sg:phone":"+49 6434/7343",
    "sg:postcode":"65520",
    "sg:province":"Hessen",
    "wof:name":"H. Biegel",
    "wof:placetype":"venue"
},
  "geometry": {"coordinates":[8.2725782394,50.2924575806],"type":"Point"}
}