{
  "type": "Feature",
  "properties": {
    "iso:country":"DE",
    "sg:address":"Kreuzstr. 14",
    "sg:city":"Triftern",
    "sg:phone":"+49 8562/96060",
    "sg:postcode":"84371",
    "sg:province":"Bayern",
    "wof:name":"Eduard Wensauer Rottaler Hammerwerk",
    "wof:placetype":"venue"
},
  "geometry": {"coordinates":[13.026869,48.439827],"type":"Point"}
}