{
  "type": "Feature",
  "properties": {
    "iso:country":"DE",
    "sg:address":"Am Roten Acker 2",
    "sg:city":"Rauenberg",
    "sg:phone":"+49 6222/63284",
    "sg:postcode":"69231",
    "sg:province":"Baden-W\u00fcrttemberg",
    "wof:name":"Rudolf Menges Drogerie",
    "wof:placetype":"venue"
},
  "geometry": {"coordinates":[8.698087,49.268539],"type":"Point"}
}