{
  "type": "Feature",
  "properties": {
    "iso:country":"DE",
    "sg:address":"Wastl-Witt-Str. 11",
    "sg:city":"M\u00fcnchen",
    "sg:phone":"+49 89/7696964",
    "sg:postcode":"80689",
    "sg:province":"Bayern",
    "wof:name":"Angelika Franz",
    "wof:placetype":"venue"
},
  "geometry": {"coordinates":[11.4728527069,48.1279792786],"type":"Point"}
}