{
  "type": "Feature",
  "properties": {
    "iso:country":"DE",
    "sg:address":"Postfach 1573:: 59061 Hamm:: Germany.^^Westf J\u00e4gerallee 3-7::",
    "sg:city":"Hamm",
    "sg:phone":"+49 2381/8990",
    "sg:postcode":"59071",
    "sg:province":"Nordrhein-Westfalen",
    "wof:name":"Bag Bankaktiengesellschaft",
    "wof:placetype":"venue"
},
  "geometry": {"coordinates":[7.875578,51.67524],"type":"Point"}
}