{
  "type": "Feature",
  "properties": {
    "iso:country":"DE",
    "sg:address":"Marienstr. 96",
    "sg:city":"Wassenberg",
    "sg:phone":"+49 2432/3074",
    "sg:postcode":"41849",
    "sg:province":"Nordrhein-Westfalen",
    "wof:name":"Hans Jennissen",
    "wof:placetype":"venue"
},
  "geometry": {"coordinates":[6.099727,51.111988],"type":"Point"}
}