{
  "type": "Feature",
  "properties": {
    "iso:country":"DE",
    "sg:address":"Margaretenstr.",
    "sg:city":"K\u00f6ln",
    "sg:phone":"+49 2203/966450",
    "sg:postcode":"51147",
    "sg:province":"Nordrhein-Westfalen",
    "wof:name":"Estelit Baustoffwerk Gmbh",
    "wof:placetype":"venue"
},
  "geometry": {"coordinates":[7.0767707825,50.8401031494],"type":"Point"}
}