{
  "type": "Feature",
  "properties": {
    "iso:country":"DE",
    "sg:address":"Netzerstr. 29",
    "sg:city":"M\u00fcnchen",
    "sg:phone":"+49 89/142134",
    "sg:postcode":"80992",
    "sg:province":"Bayern",
    "wof:name":"Da Alberto",
    "wof:placetype":"venue"
},
  "geometry": {"coordinates":[11.5082349777,48.1720924377],"type":"Point"}
}