{
  "type": "Feature",
  "properties": {
    "iso:country":"DE",
    "sg:address":"Weinstr. 10",
    "sg:city":"L\u00f6chgau",
    "sg:phone":"+49 7143/28842",
    "sg:postcode":"74369",
    "sg:province":"Baden-W\u00fcrttemberg",
    "wof:name":"Luxus Konzertservice Peter Morscheck",
    "wof:placetype":"venue"
},
  "geometry": {"coordinates":[9.1055335999,49.002784729],"type":"Point"}
}