{
  "type": "Feature",
  "properties": {
    "iso:country":"DE",
    "sg:address":"Geraer Str. 40",
    "sg:city":"Weida",
    "sg:phone":"+49 36603/62754",
    "sg:postcode":"07570",
    "sg:province":"Th\u00fcringen",
    "wof:name":"Bachmann Containerdienst Und Rohstoffhandel Gmbh",
    "wof:placetype":"venue"
},
  "geometry": {"coordinates":[12.0621871948,50.7758369446],"type":"Point"}
}