{
  "type": "Feature",
  "properties": {
    "iso:country":"DE",
    "sg:address":"Spiecherg\u00e4ssle 10",
    "sg:city":"Grafenhausen",
    "sg:phone":"+49 7748/5404",
    "sg:postcode":"79865",
    "sg:province":"Baden-W\u00fcrttemberg",
    "wof:name":"M. Kromer",
    "wof:placetype":"venue"
},
  "geometry": {"coordinates":[8.256436,47.773811],"type":"Point"}
}