{
  "type": "Feature",
  "properties": {
    "iso:country":"DE",
    "sg:address":"Baseler Platz 3",
    "sg:city":"Frankfurt",
    "sg:phone":"+49 69/252884",
    "sg:postcode":"60329",
    "sg:province":"Hessen",
    "wof:name":"It Intertouring Rum\u00e4nienreisen Gmbh",
    "wof:placetype":"venue"
},
  "geometry": {"coordinates":[8.664691925,50.1023674011],"type":"Point"}
}