{
  "type": "Feature",
  "properties": {
    "iso:country":"DE",
    "sg:address":"Angerstr. 8",
    "sg:city":"Neuburg",
    "sg:phone":"+49 8431/7856",
    "sg:postcode":"86633",
    "sg:province":"Bayern",
    "wof:name":"Michael Stapf Wohnbau Gmbh",
    "wof:placetype":"venue"
},
  "geometry": {"coordinates":[11.254336,48.715706],"type":"Point"}
}