{
  "type": "Feature",
  "properties": {
    "iso:country":"DE",
    "sg:address":"Wilhelmstr. 26",
    "sg:city":"Lahnstein",
    "sg:phone":"+49 2621/40660",
    "sg:postcode":"56112",
    "sg:province":"Rheinland-Pfalz",
    "wof:name":"Johannes Lauer",
    "wof:placetype":"venue"
},
  "geometry": {"coordinates":[7.607124,50.303497],"type":"Point"}
}