{
  "type": "Feature",
  "properties": {
    "iso:country":"DE",
    "sg:address":"Kossenkamp 153",
    "sg:city":"S\u00f6gel",
    "sg:phone":"+49 5952/631",
    "sg:postcode":"49751",
    "sg:province":"Niedersachsen",
    "wof:name":"Hans Borchers",
    "wof:placetype":"venue"
},
  "geometry": {"coordinates":[7.52737,52.83765],"type":"Point"}
}