{
  "type": "Feature",
  "properties": {
    "iso:country":"DE",
    "sg:address":"Robert-Koch-Str. 9",
    "sg:city":"Stuttgart",
    "sg:phone":"+49 711/7352019",
    "sg:postcode":"70563",
    "sg:province":"Baden-W\u00fcrttemberg",
    "wof:name":"Ambulanto Sozialpsychiatrischer",
    "wof:placetype":"venue"
},
  "geometry": {"coordinates":[9.109949,48.729443],"type":"Point"}
}