{
  "type": "Feature",
  "properties": {
    "iso:country":"DE",
    "sg:address":"Museumstr. 5-9",
    "sg:city":"Albstadt",
    "sg:phone":"+49 7431/4081",
    "sg:postcode":"72458",
    "sg:province":"Baden-W\u00fcrttemberg",
    "wof:name":"W. Fuss Bickelhaupt Verwaltungs Gmbh",
    "wof:placetype":"venue"
},
  "geometry": {"coordinates":[9.0254020691,48.212223053],"type":"Point"}
}