{
  "type": "Feature",
  "properties": {
    "iso:country":"DE",
    "sg:address":"Domgasse 1",
    "sg:city":"F\u00fcrstenwalde",
    "sg:phone":"+49 3361/310038",
    "sg:postcode":"15517",
    "sg:province":"Brandenburg",
    "wof:name":"Athene",
    "wof:placetype":"venue"
},
  "geometry": {"coordinates":[14.0646896362,52.3579902649],"type":"Point"}
}