{
  "type": "Feature",
  "properties": {
    "iso:country":"DE",
    "sg:address":"Sonnenmoosstr. 20",
    "sg:city":"Rottach-Egern",
    "sg:phone":"+49 8022/5812",
    "sg:postcode":"83700",
    "sg:province":"Bayern",
    "wof:name":"Hotel Sonnenhof",
    "wof:placetype":"venue"
},
  "geometry": {"coordinates":[11.7750253677,47.6862602234],"type":"Point"}
}