{
  "type": "Feature",
  "properties": {
    "iso:country":"DE",
    "sg:address":"Wallstr. 10",
    "sg:city":"Freudenstadt",
    "sg:phone":"+49 7441/905626",
    "sg:postcode":"72250",
    "sg:province":"Baden-W\u00fcrttemberg",
    "wof:name":"Signal Iduna-versicherungen",
    "wof:placetype":"venue"
},
  "geometry": {"coordinates":[8.4133872986,48.467086792],"type":"Point"}
}