{
  "type": "Feature",
  "properties": {
    "iso:country":"DE",
    "sg:address":"Rautenbreite 17",
    "sg:city":"Magdeburg",
    "sg:postcode":"39116",
    "sg:province":"Sachsen-Anhalt",
    "wof:name":"Dr. Med. Bernd Rauschenbach",
    "wof:placetype":"venue"
},
  "geometry": {"coordinates":[11.578884,52.097023],"type":"Point"}
}