{
  "type": "Feature",
  "properties": {
    "iso:country":"DE",
    "sg:address":"Kopernikusstr. 54",
    "sg:city":"Offenbach",
    "sg:phone":"+49 69/853387",
    "sg:postcode":"63071",
    "sg:province":"Hessen",
    "wof:name":"Ev. Pfarramt Markusgemeinde Ost",
    "wof:placetype":"venue"
},
  "geometry": {"coordinates":[8.7872190475,50.0955619812],"type":"Point"}
}