{
  "type": "Feature",
  "properties": {
    "iso:country":"DE",
    "sg:address":"Kaiserstr. 104",
    "sg:city":"Siegburg",
    "sg:phone":"+49 2241/65808",
    "sg:postcode":"53721",
    "sg:province":"Nordrhein-Westfalen",
    "wof:name":"Restaurant Goldener Ochse",
    "wof:placetype":"venue"
},
  "geometry": {"coordinates":[7.2053952217,50.8018798828],"type":"Point"}
}