{
  "type": "Feature",
  "properties": {
    "iso:country":"DE",
    "sg:address":"Sirchinger Weg 1",
    "sg:city":"M\u00fcnsingen",
    "sg:phone":"+49 7381/3287",
    "sg:postcode":"72525",
    "sg:province":"Baden-W\u00fcrttemberg",
    "wof:name":"W. Sch\u00f6ll",
    "wof:placetype":"venue"
},
  "geometry": {"coordinates":[9.4423933029,48.4353179932],"type":"Point"}
}