{
  "type": "Feature",
  "properties": {
    "iso:country":"DE",
    "sg:address":"K\u00fchgasse 19",
    "sg:city":"Hindelang",
    "sg:phone":"+49 8324/2249",
    "sg:postcode":"87541",
    "sg:province":"Bayern",
    "wof:name":"W\u00fcrttembergische Versicherung Ag",
    "wof:placetype":"venue"
},
  "geometry": {"coordinates":[10.3871860504,47.5050506592],"type":"Point"}
}