{
  "type": "Feature",
  "properties": {
    "iso:country":"DE",
    "sg:address":"Dornbuscher Str. 42",
    "sg:city":"Drochtersen",
    "sg:phone":"+49 4143/1269",
    "sg:postcode":"21706",
    "sg:province":"Niedersachsen",
    "wof:name":"Reederei Stefan Patjens Beteiligungsgesellschaft Mbh",
    "wof:placetype":"venue"
},
  "geometry": {"coordinates":[9.345357,53.734901],"type":"Point"}
}