{
  "type": "Feature",
  "properties": {
    "iso:country":"DE",
    "sg:address":"Laufenburger Str. 13",
    "sg:city":"Laufenburg",
    "sg:phone":"+49 7763/5109",
    "sg:postcode":"79725",
    "sg:province":"Baden-W\u00fcrttemberg",
    "wof:name":"Paul B\u00f6hler",
    "wof:placetype":"venue"
},
  "geometry": {"coordinates":[8.061584,47.59198],"type":"Point"}
}