{
  "type": "Feature",
  "properties": {
    "iso:country":"DE",
    "sg:address":"Hauptstr. 2",
    "sg:city":"Rohr",
    "sg:phone":"+49 9876/262",
    "sg:postcode":"91189",
    "sg:province":"Bayern",
    "wof:name":"H. Scheuber",
    "wof:placetype":"venue"
},
  "geometry": {"coordinates":[10.89497,49.340195],"type":"Point"}
}