{
  "type": "Feature",
  "properties": {
    "iso:country":"DE",
    "sg:address":"Donaustrasse 13 Backnang-Waldrems",
    "sg:city":"Backnang",
    "sg:phone":"+49 4971/9195660",
    "sg:postcode":"71522",
    "sg:province":"Baden-W\u00fcrttemberg",
    "wof:name":"Kk Elektrotechnik Gmbh",
    "wof:placetype":"venue"
},
  "geometry": {"coordinates":[9.432515,48.948376],"type":"Point"}
}