{
  "type": "Feature",
  "properties": {
    "iso:country":"DE",
    "sg:address":"G\u00fcnzburger Str. 5",
    "sg:city":"Ichenhausen",
    "sg:phone":"+49 8223/409894",
    "sg:postcode":"89335",
    "sg:province":"Bayern",
    "wof:name":"Elektro-volk Gmbh",
    "wof:placetype":"venue"
},
  "geometry": {"coordinates":[10.306067,48.372612],"type":"Point"}
}