{
  "type": "Feature",
  "properties": {
    "iso:country":"DE",
    "sg:address":"Burgweg 52",
    "sg:city":"Ha\u00dfloch",
    "sg:phone":"+49 6324/4036",
    "sg:postcode":"67454",
    "sg:province":"Rheinland-Pfalz",
    "wof:name":"I. Eichmann Heissmangel",
    "wof:placetype":"venue"
},
  "geometry": {"coordinates":[8.2502241135,49.3575325012],"type":"Point"}
}