{
  "type": "Feature",
  "properties": {
    "iso:country":"DE",
    "sg:address":"Steindamm 16",
    "sg:city":"Hamburg",
    "sg:phone":"+49 40/241695",
    "sg:postcode":"20099",
    "sg:province":"Hamburg",
    "wof:name":"New Man Kino- Und Handels-gmbh",
    "wof:placetype":"venue"
},
  "geometry": {"coordinates":[10.0116853714,53.5531959534],"type":"Point"}
}