{
  "type": "Feature",
  "properties": {
    "iso:country":"DE",
    "sg:address":"Kenkhauser Str. 105",
    "sg:city":"Wermelskirchen",
    "sg:phone":"+49 2196/92022",
    "sg:postcode":"42929",
    "sg:province":"Nordrhein-Westfalen",
    "wof:name":"Haus Hochstein",
    "wof:placetype":"venue"
},
  "geometry": {"coordinates":[7.2246761322,51.150352478],"type":"Point"}
}