{
  "type": "Feature",
  "properties": {
    "iso:country":"DE",
    "sg:address":"Bahnhofstr. 44",
    "sg:city":"Stubben",
    "sg:phone":"+49 4748/2224",
    "sg:postcode":"27616",
    "sg:province":"Niedersachsen",
    "wof:name":"B. R\u00f6hricht",
    "wof:placetype":"venue"
},
  "geometry": {"coordinates":[8.7855539322,53.4105415344],"type":"Point"}
}