{
  "type": "Feature",
  "properties": {
    "iso:country":"DE",
    "sg:address":"Schopfheimer Str. 79 a",
    "sg:city":"Wehr",
    "sg:phone":"+49 7762/8588",
    "sg:postcode":"79664",
    "sg:province":"Baden-W\u00fcrttemberg",
    "wof:name":"Richard Berger",
    "wof:placetype":"venue"
},
  "geometry": {"coordinates":[7.896944,47.633434],"type":"Point"}
}