{
  "type": "Feature",
  "properties": {
    "iso:country":"DE",
    "sg:address":"K\u00f6nigin-Luise-Str. 22",
    "sg:city":"Berlin",
    "sg:phone":"+49 30/3147137",
    "sg:postcode":"14195",
    "sg:province":"Berlin",
    "wof:name":"Institut F. \u00d6kologie Fach- Gebiet Zierpflanzenbau",
    "wof:placetype":"venue"
},
  "geometry": {"coordinates":[13.2990560532,52.4576797485],"type":"Point"}
}