{
  "type": "Feature",
  "properties": {
    "iso:country":"DE",
    "sg:address":"Nordenbrocker Str. 4",
    "sg:city":"Cappeln",
    "sg:phone":"+49 4446/961053",
    "sg:postcode":"49692",
    "sg:province":"Niedersachsen",
    "wof:name":"J\u00f6rg Jarmer",
    "wof:placetype":"venue"
},
  "geometry": {"coordinates":[8.185122,52.786499],"type":"Point"}
}