{
  "type": "Feature",
  "properties": {
    "iso:country":"DE",
    "sg:address":"Hauptstr. 62",
    "sg:city":"Markkleeberg",
    "sg:phone":"+49 341/3582458",
    "sg:postcode":"04416",
    "sg:province":"Sachsen",
    "wof:name":"Pelikan-apotheke",
    "wof:placetype":"venue"
},
  "geometry": {"coordinates":[12.374226,51.279427],"type":"Point"}
}