{
  "type": "Feature",
  "properties": {
    "iso:country":"DE",
    "sg:address":"Holtauer Weg 2",
    "sg:city":"Winsen",
    "sg:phone":"+49 5143/6357",
    "sg:postcode":"29308",
    "sg:province":"Niedersachsen",
    "wof:name":"Heinrich Meinheit",
    "wof:placetype":"venue"
},
  "geometry": {"coordinates":[9.961312,52.660191],"type":"Point"}
}