{
  "type": "Feature",
  "properties": {
    "iso:country":"DE",
    "sg:address":"Hauptstr. 57",
    "sg:city":"Sch\u00f6neck",
    "sg:phone":"+49 37464/88755",
    "sg:postcode":"08261",
    "sg:province":"Sachsen",
    "wof:name":"Gabriele Seifert",
    "wof:placetype":"venue"
},
  "geometry": {"coordinates":[12.3338632584,50.3948402405],"type":"Point"}
}