{
  "type": "Feature",
  "properties": {
    "iso:country":"DE",
    "sg:address":"Brunnengasse 9",
    "sg:city":"Reiskirchen",
    "sg:phone":"+49 6408/962626",
    "sg:postcode":"35447",
    "sg:province":"Hessen",
    "wof:name":"Eckel-fiedler Und Kaup-sonntag Rechtsanw\u00e4ltinnen",
    "wof:placetype":"venue"
},
  "geometry": {"coordinates":[8.8169956207,50.5781135559],"type":"Point"}
}