{
  "type": "Feature",
  "properties": {
    "iso:country":"DE",
    "sg:address":"Dorfstr. 82",
    "sg:city":"L\u00fcdelsen",
    "sg:phone":"+49 39003/265",
    "sg:postcode":"38489",
    "sg:province":"Sachsen-Anhalt",
    "wof:name":"Herbert Kruse",
    "wof:placetype":"venue"
},
  "geometry": {"coordinates":[10.94578,52.686787],"type":"Point"}
}