{
  "type": "Feature",
  "properties": {
    "iso:country":"DE",
    "sg:address":"Bahnhofstr. 30",
    "sg:city":"Alfter",
    "sg:phone":"+49 2222/1813",
    "sg:postcode":"53347",
    "sg:province":"Nordrhein-Westfalen",
    "wof:name":"H. Stein",
    "wof:placetype":"venue"
},
  "geometry": {"coordinates":[7.013492,50.740932],"type":"Point"}
}