{
  "type": "Feature",
  "properties": {
    "iso:country":"DE",
    "sg:address":"K\u00f6nigsbergstr. 37",
    "sg:city":"Bayreuth",
    "sg:phone":"+49 921/12135",
    "sg:postcode":"95448",
    "sg:province":"Bayern",
    "wof:name":"Werner Widmann",
    "wof:placetype":"venue"
},
  "geometry": {"coordinates":[11.6009225845,49.9552116394],"type":"Point"}
}