{
  "type": "Feature",
  "properties": {
    "iso:country":"DE",
    "sg:address":"Hauptstr. 7",
    "sg:city":"Gudersleben",
    "sg:phone":"+49 36336/56294",
    "sg:postcode":"99755",
    "sg:province":"Th\u00fcringen",
    "wof:name":"Akk - Landtechnik Gmbh",
    "wof:placetype":"venue"
},
  "geometry": {"coordinates":[10.681152,51.556381],"type":"Point"}
}