{
  "type": "Feature",
  "properties": {
    "iso:country":"DE",
    "sg:address":"Dorfstr 10",
    "sg:city":"Hille",
    "sg:phone":"+49 5703/920888",
    "sg:postcode":"32479",
    "sg:province":"Nordrhein-Westfalen",
    "wof:name":"Volksbank Hille-unterl\u00fcbbe Eg",
    "wof:placetype":"venue"
},
  "geometry": {"coordinates":[8.743986,52.335033],"type":"Point"}
}