{
  "type": "Feature",
  "properties": {
    "iso:country":"DE",
    "sg:address":"Sedlmayrstr. 28",
    "sg:city":"M\u00fcnchen",
    "sg:phone":"+49 89/1688643",
    "sg:postcode":"80634",
    "sg:province":"Bayern",
    "wof:name":"Fellst\u00fcberl",
    "wof:placetype":"venue"
},
  "geometry": {"coordinates":[11.531244278,48.1491851807],"type":"Point"}
}