{
  "type": "Feature",
  "properties": {
    "iso:country":"DE",
    "sg:address":"Ernestusstr. 1",
    "sg:city":"Halle",
    "sg:phone":"+49 345/5231908",
    "sg:postcode":"06114",
    "sg:province":"Sachsen-Anhalt",
    "wof:name":"Berlin Wohnbau Gmbh",
    "wof:placetype":"venue"
},
  "geometry": {"coordinates":[11.961815,51.497669],"type":"Point"}
}