{
  "type": "Feature",
  "properties": {
    "iso:country":"DE",
    "sg:address":"Metzer Stra\u00dfe 3",
    "sg:city":"Saarlouis",
    "sg:phone":"+49 6831/121717",
    "sg:postcode":"66740",
    "sg:province":"Saarland",
    "wof:name":"Teleshop-der-telefonladen",
    "wof:placetype":"venue"
},
  "geometry": {"coordinates":[6.747314,49.309673],"type":"Point"}
}