{
  "type": "Feature",
  "properties": {
    "iso:country":"DE",
    "sg:address":"Bachstr. 20",
    "sg:city":"Aachen",
    "sg:phone":"+49 241/407980",
    "sg:postcode":"52066",
    "sg:province":"Nordrhein-Westfalen",
    "wof:name":"Bvr Busverkehr Rheinland Gmbh",
    "wof:placetype":"venue"
},
  "geometry": {"coordinates":[6.09698,50.767269],"type":"Point"}
}