{
  "type": "Feature",
  "properties": {
    "iso:country":"DE",
    "sg:address":"Frankfurter Str. 6",
    "sg:city":"Bad K\u00f6nig",
    "sg:phone":"+49 6063/50050",
    "sg:postcode":"64732",
    "sg:province":"Hessen",
    "wof:name":"Hotel-restaurant B\u00fcchner",
    "wof:placetype":"venue"
},
  "geometry": {"coordinates":[9.0048093796,49.7425613403],"type":"Point"}
}