{
  "type": "Feature",
  "properties": {
    "iso:country":"DE",
    "sg:address":"Hansaallee 2",
    "sg:city":"D\u00fcsseldorf",
    "sg:phone":"+49 211/5597561",
    "sg:postcode":"40547",
    "sg:province":"Nordrhein-Westfalen",
    "wof:name":"Unis Group Gmbh",
    "wof:placetype":"venue"
},
  "geometry": {"coordinates":[6.7350101471,51.2379989624],"type":"Point"}
}