{
  "type": "Feature",
  "properties": {
    "iso:country":"DE",
    "sg:address":"Fichtenstr. 15",
    "sg:city":"Neuenstein",
    "sg:phone":"+49 7942/8604",
    "sg:postcode":"74632",
    "sg:province":"Baden-W\u00fcrttemberg",
    "wof:name":"I. M. Egger Immobilienmakler",
    "wof:placetype":"venue"
},
  "geometry": {"coordinates":[9.5710668564,49.2089729309],"type":"Point"}
}