{
  "type": "Feature",
  "properties": {
    "iso:country":"DE",
    "sg:address":"Westmarkstr. 118",
    "sg:city":"Karlsruhe",
    "sg:phone":"+49 721/401520",
    "sg:postcode":"76227",
    "sg:province":"Baden-W\u00fcrttemberg",
    "wof:name":"Verein F\u00fcr Hom\u00f6opathie Und Lebenspflege E. V.",
    "wof:placetype":"venue"
},
  "geometry": {"coordinates":[8.456489563,48.9872245789],"type":"Point"}
}