{
  "type": "Feature",
  "properties": {
    "iso:country":"DE",
    "sg:address":"Eisenbahnstr. 41",
    "sg:city":"R\u00f6merberg",
    "sg:phone":"+49 6232/84163",
    "sg:postcode":"67354",
    "sg:province":"Rheinland-Pfalz",
    "wof:name":"Reinhold Brendel",
    "wof:placetype":"venue"
},
  "geometry": {"coordinates":[8.409685,49.294456],"type":"Point"}
}