{
  "type": "Feature",
  "properties": {
    "iso:country":"DE",
    "sg:address":"Gr\u00fcner Weg 43",
    "sg:city":"K\u00f6ln",
    "sg:phone":"+49 2236/380208",
    "sg:postcode":"50999",
    "sg:province":"Nordrhein-Westfalen",
    "wof:name":"Prof. Dr. Alexander Thiemann",
    "wof:placetype":"venue"
},
  "geometry": {"coordinates":[7.0104618073,50.8717880249],"type":"Point"}
}