{
  "type": "Feature",
  "properties": {
    "iso:country":"DE",
    "sg:address":"Amerner Strasse 49",
    "sg:city":"Schwalmtal-Waldniel",
    "sg:phone":"+49 2163/338890",
    "sg:postcode":"41366",
    "sg:province":"Nordrhein-Westfalen",
    "wof:name":"Marcadent Gmbh",
    "wof:placetype":"venue"
},
  "geometry": {"coordinates":[6.269215,51.216557],"type":"Point"}
}