{
  "type": "Feature",
  "properties": {
    "iso:country":"DE",
    "sg:address":"Veilchenweg 4",
    "sg:city":"Kassel",
    "sg:phone":"+49 561/811437",
    "sg:postcode":"34125",
    "sg:province":"Hessen",
    "wof:name":"B. Ronniger",
    "wof:placetype":"venue"
},
  "geometry": {"coordinates":[9.5337467194,51.3329925537],"type":"Point"}
}