{
  "type": "Feature",
  "properties": {
    "iso:country":"DE",
    "sg:address":"Oberer Markt 15",
    "sg:city":"Markneukirchen",
    "sg:phone":"+49 37422/2398",
    "sg:postcode":"08258",
    "sg:province":"Sachsen",
    "wof:name":"Margitta Hamberger",
    "wof:placetype":"venue"
},
  "geometry": {"coordinates":[12.329574585,50.3121414185],"type":"Point"}
}