{
  "type": "Feature",
  "properties": {
    "iso:country":"DE",
    "sg:address":"Mayers G\u00e4rten 4",
    "sg:city":"K\u00f6nigstein",
    "sg:postcode":"61462",
    "sg:province":"Hessen",
    "wof:name":"City-arkaden Grundst\u00fccks-gmbh",
    "wof:placetype":"venue"
},
  "geometry": {"coordinates":[8.4790935516,50.1896095276],"type":"Point"}
}