{
  "type": "Feature",
  "properties": {
    "iso:country":"DE",
    "sg:address":"Alter Schulweg 2",
    "sg:city":"Gl\u00fccksburg",
    "sg:phone":"+49 4631",
    "sg:postcode":"24960",
    "sg:province":"Schleswig-Holstein",
    "wof:name":"Alfred Grages Berufsbekleidung",
    "wof:placetype":"venue"
},
  "geometry": {"coordinates":[9.5872650146,54.8466682434],"type":"Point"}
}