{
  "type": "Feature",
  "properties": {
    "iso:country":"DE",
    "sg:address":"Alt-Treptow 6",
    "sg:city":"Berlin",
    "sg:postcode":"12435",
    "sg:province":"Berlin",
    "wof:name":"Ernst Zinna",
    "wof:placetype":"venue"
},
  "geometry": {"coordinates":[13.4786567688,52.4856758118],"type":"Point"}
}