{
  "type": "Feature",
  "properties": {
    "iso:country":"DE",
    "sg:address":"Heinrichstr. 15",
    "sg:city":"Bergkamen",
    "sg:phone":"+49 2307/828262",
    "sg:postcode":"59192",
    "sg:province":"Nordrhein-Westfalen",
    "wof:name":"F\u00e4\u00dfchen",
    "wof:placetype":"venue"
},
  "geometry": {"coordinates":[7.6443090439,51.6141853333],"type":"Point"}
}