{
  "type": "Feature",
  "properties": {
    "iso:country":"DE",
    "sg:address":"Wierlings Esch 33 b",
    "sg:city":"D\u00fclmen",
    "sg:phone":"+49 2594/786413",
    "sg:postcode":"48249",
    "sg:province":"Nordrhein-Westfalen",
    "wof:name":"Schlingemann Gmbh & Co. Grundst\u00fccks- Und",
    "wof:placetype":"venue"
},
  "geometry": {"coordinates":[7.3090128899,51.8244857788],"type":"Point"}
}