{
  "type": "Feature",
  "properties": {
    "iso:country":"DE",
    "sg:address":"Augsburger Str. 4",
    "sg:city":"Mering",
    "sg:phone":"+49 8233/32153",
    "sg:postcode":"86415",
    "sg:province":"Bayern",
    "wof:name":"Deutsche Woolworth Gmbh & Co. Ohg",
    "wof:placetype":"venue"
},
  "geometry": {"coordinates":[10.986854,48.268433],"type":"Point"}
}