{
  "type": "Feature",
  "properties": {
    "iso:country":"DE",
    "sg:address":"Anbau 13",
    "sg:city":"Tauscha",
    "sg:phone":"+49 35240/72361",
    "sg:postcode":"01561",
    "sg:province":"Sachsen",
    "wof:name":"Thomas Schempp Fleischerei",
    "wof:placetype":"venue"
},
  "geometry": {"coordinates":[13.8027458191,51.2575798035],"type":"Point"}
}