{
  "type": "Feature",
  "properties": {
    "iso:country":"DE",
    "sg:address":"Querallee 13",
    "sg:city":"Kleve",
    "sg:postcode":"47533",
    "sg:province":"Nordrhein-Westfalen",
    "wof:name":"Aldi Gmbh & Co. Kg",
    "wof:placetype":"venue"
},
  "geometry": {"coordinates":[6.117536068,51.7707824707],"type":"Point"}
}