{
  "type": "Feature",
  "properties": {
    "iso:country":"DE",
    "sg:address":"Freiheitstr 185-187",
    "sg:city":"Remscheid",
    "sg:phone":"+49 2191/78280",
    "sg:postcode":"42853",
    "sg:province":"Nordrhein-Westfalen",
    "wof:name":"Jutger",
    "wof:placetype":"venue"
},
  "geometry": {"coordinates":[7.179105,51.179817],"type":"Point"}
}