{
  "type": "Feature",
  "properties": {
    "iso:country":"DE",
    "sg:address":"Hauptstr. 33",
    "sg:city":"Ribbesb\u00fcttel",
    "sg:phone":"+49 5373/1648",
    "sg:postcode":"38551",
    "sg:province":"Niedersachsen",
    "wof:name":"Erich Sch\u00f6ne",
    "wof:placetype":"venue"
},
  "geometry": {"coordinates":[10.485608,52.427876],"type":"Point"}
}