{
  "type": "Feature",
  "properties": {
    "iso:country":"DE",
    "sg:address":"Zollgasse 10",
    "sg:city":"Wertheim",
    "sg:phone":"+49 9342/4862",
    "sg:postcode":"97877",
    "sg:province":"Baden-W\u00fcrttemberg",
    "wof:name":"Restaurant Gr\u00fcnauer Hof",
    "wof:placetype":"venue"
},
  "geometry": {"coordinates":[9.5172405243,49.760799408],"type":"Point"}
}