{
  "type": "Feature",
  "properties": {
    "iso:country":"DE",
    "sg:address":"Sulgauer Str. 11-13",
    "sg:city":"Schramberg",
    "sg:phone":"+49 7422/54683",
    "sg:postcode":"78713",
    "sg:province":"Baden-W\u00fcrttemberg",
    "wof:name":"Optik Storz Gmbh",
    "wof:placetype":"venue"
},
  "geometry": {"coordinates":[8.420715332,48.2251701355],"type":"Point"}
}