{
  "type": "Feature",
  "properties": {
    "iso:country":"DE",
    "sg:address":"Lewickistr. 23",
    "sg:city":"Dresden",
    "sg:phone":"+49 351/2516853",
    "sg:postcode":"01279",
    "sg:province":"Sachsen",
    "wof:name":"Keramikzirkel E. V. Rita Schwarz",
    "wof:placetype":"venue"
},
  "geometry": {"coordinates":[13.8215494156,51.0305709839],"type":"Point"}
}