{
  "type": "Feature",
  "properties": {
    "iso:country":"DE",
    "sg:address":"D\u00fcrener Str. 186",
    "sg:city":"K\u00f6ln",
    "sg:phone":"+49 221/407614",
    "sg:postcode":"50931",
    "sg:province":"Nordrhein-Westfalen",
    "wof:name":"Lindenthaler Reiseb\u00fcro Herbert Reichel Kg",
    "wof:placetype":"venue"
},
  "geometry": {"coordinates":[6.9141960144,50.9298248291],"type":"Point"}
}