{
  "type": "Feature",
  "properties": {
    "iso:country":"DE",
    "sg:address":"Kirchstrasse 57",
    "sg:city":"Baesweiler",
    "sg:phone":"+49 2401/88008",
    "sg:postcode":"52499",
    "sg:province":"Nordrhein-Westfalen",
    "wof:name":"Hilmar Koch Maschinen Und Ger\u00e4te Service",
    "wof:placetype":"venue"
},
  "geometry": {"coordinates":[6.182479,50.907051],"type":"Point"}
}