{
  "type": "Feature",
  "properties": {
    "iso:country":"DE",
    "sg:address":"Dresdner Str. 27",
    "sg:city":"Dresden",
    "sg:phone":"+49 351/4537263",
    "sg:postcode":"01326",
    "sg:province":"Sachsen",
    "wof:name":"Groli Sch\u00e4dlings- Bek\u00e4mpfung Gmbh",
    "wof:placetype":"venue"
},
  "geometry": {"coordinates":[13.855264,51.024708],"type":"Point"}
}