{
  "type": "Feature",
  "properties": {
    "iso:country":"DE",
    "sg:address":"Letterweg 12",
    "sg:city":"Hannover",
    "sg:phone":"+49 511/404142",
    "sg:postcode":"30453",
    "sg:province":"Niedersachsen",
    "wof:name":"Magdalene Clavier",
    "wof:placetype":"venue"
},
  "geometry": {"coordinates":[9.6585264206,52.3864479065],"type":"Point"}
}