{
  "type": "Feature",
  "properties": {
    "iso:country":"DE",
    "sg:address":"Am Rimbach 1",
    "sg:city":"Waldsolms",
    "sg:postcode":"35647",
    "sg:province":"Hessen",
    "wof:name":"Caro Gmbh",
    "wof:placetype":"venue"
},
  "geometry": {"coordinates":[8.497163,50.433365],"type":"Point"}
}