{
  "type": "Feature",
  "properties": {
    "iso:country":"DE",
    "sg:address":"Rohrs\u00e4ngerplatz 5",
    "sg:city":"M\u00fcnchen",
    "sg:phone":"+49 89/8642564",
    "sg:postcode":"81249",
    "sg:province":"Bayern",
    "wof:name":"Herbert Schmied",
    "wof:placetype":"venue"
},
  "geometry": {"coordinates":[11.3980417252,48.1805076599],"type":"Point"}
}