{
  "type": "Feature",
  "properties": {
    "iso:country":"DE",
    "sg:address":"Peterstr. 1",
    "sg:city":"Neum\u00fcnster",
    "sg:phone":"+49 4321/42031",
    "sg:postcode":"24534",
    "sg:province":"Schleswig-Holstein",
    "wof:name":"Brachenfelder Haus- Und Wohnungsverwaltungs-gmbh",
    "wof:placetype":"venue"
},
  "geometry": {"coordinates":[9.99061203,54.0719032288],"type":"Point"}
}