{
  "type": "Feature",
  "properties": {
    "iso:country":"DE",
    "sg:address":"Br\u00fcckstr. 3",
    "sg:city":"Wesel",
    "sg:phone":"+49 281/26165",
    "sg:postcode":"46483",
    "sg:province":"Nordrhein-Westfalen",
    "wof:name":"Louis T\u00f6nnes Inh. H. Henrichs",
    "wof:placetype":"venue"
},
  "geometry": {"coordinates":[6.6149821281,51.6571235657],"type":"Point"}
}