{
  "type": "Feature",
  "properties": {
    "iso:country":"DE",
    "sg:address":"Schlesierweg 1",
    "sg:city":"Homberg",
    "sg:phone":"+49 5681/7095",
    "sg:postcode":"34576",
    "sg:province":"Hessen",
    "wof:name":"Beratungsstelle D. Schwalm-eder-kreises",
    "wof:placetype":"venue"
},
  "geometry": {"coordinates":[9.394369,51.032188],"type":"Point"}
}