{
  "type": "Feature",
  "properties": {
    "iso:country":"DE",
    "sg:address":"Luisenstr. 15",
    "sg:city":"Heilbronn",
    "sg:phone":"+49 7131/888870",
    "sg:postcode":"74072",
    "sg:province":"Baden-W\u00fcrttemberg",
    "wof:name":"Peter Schmid",
    "wof:placetype":"venue"
},
  "geometry": {"coordinates":[9.2176036835,49.1358451843],"type":"Point"}
}