{
  "type": "Feature",
  "properties": {
    "iso:country":"DE",
    "sg:address":"Hauptstr. 81",
    "sg:city":"Reinhardtsgrimma",
    "sg:phone":"+49 35053/47025",
    "sg:postcode":"01768",
    "sg:province":"Sachsen",
    "wof:name":"Gerd Tinius Verm\u00f6gensberatung",
    "wof:placetype":"venue"
},
  "geometry": {"coordinates":[13.7468452454,50.8900604248],"type":"Point"}
}