{
  "type": "Feature",
  "properties": {
    "iso:country":"DE",
    "sg:address":"Hauptstr. 38",
    "sg:city":"Drees",
    "sg:phone":"+49 2691/2451",
    "sg:postcode":"53520",
    "sg:province":"Rheinland-Pfalz",
    "wof:name":"G\u00e4stehaus J. Manheller",
    "wof:placetype":"venue"
},
  "geometry": {"coordinates":[6.995279789,50.3413085938],"type":"Point"}
}