{
  "type": "Feature",
  "properties": {
    "iso:country":"DE",
    "sg:address":"Am Galgenberg 18",
    "sg:city":"Rimbach",
    "sg:postcode":"93485",
    "sg:province":"Bayern",
    "wof:name":"I. N. U. S. Medizin - Marketing Zentral Gmbh",
    "wof:placetype":"venue"
},
  "geometry": {"coordinates":[12.8613843918,49.2334671021],"type":"Point"}
}