{
  "type": "Feature",
  "properties": {
    "iso:country":"DE",
    "sg:address":"Bachstr. 205",
    "sg:city":"Kerpen",
    "sg:phone":"+49 2237/3307",
    "sg:postcode":"50171",
    "sg:province":"Nordrhein-Westfalen",
    "wof:name":"Johann Schumacher",
    "wof:placetype":"venue"
},
  "geometry": {"coordinates":[6.68704319,50.865776062],"type":"Point"}
}