{
  "type": "Feature",
  "properties": {
    "iso:country":"DE",
    "sg:address":"Molkereistr. 5",
    "sg:city":"Memmingerberg",
    "sg:phone":"+49 8331/5151",
    "sg:postcode":"87766",
    "sg:province":"Bayern",
    "wof:name":"J. Hochsteiner",
    "wof:placetype":"venue"
},
  "geometry": {"coordinates":[10.207573,47.988831],"type":"Point"}
}