{
  "type": "Feature",
  "properties": {
    "iso:country":"DE",
    "sg:address":"Sigmundsgr\u00fcn",
    "sg:city":"Rehau",
    "sg:postcode":"95111",
    "sg:province":"Bayern",
    "wof:name":"Hofer Und Wagenknecht Schwei\u00df- Und Rohrleitungsbau Gmbh",
    "wof:placetype":"venue"
},
  "geometry": {"coordinates":[12.118215,50.283745],"type":"Point"}
}