{
  "type": "Feature",
  "properties": {
    "iso:country":"DE",
    "sg:address":"sch\u00fctzenstr.229",
    "sg:city":"solingen",
    "sg:phone":"+49 212",
    "sg:postcode":"42659",
    "sg:province":"Nordrhein-Westfalen",
    "wof:name":"Das Feuerhaus In Solingen",
    "wof:placetype":"venue"
},
  "geometry": {"coordinates":[7.111001,51.162086],"type":"Point"}
}