{
  "type": "Feature",
  "properties": {
    "iso:country":"DE",
    "sg:address":"Arbketal 339",
    "sg:city":"Dingelstedt",
    "sg:phone":"+49 39425/2118",
    "sg:postcode":"38838",
    "sg:province":"Sachsen-Anhalt",
    "wof:name":"Klaus B\u00f6gelsack",
    "wof:placetype":"venue"
},
  "geometry": {"coordinates":[10.978081,51.978088],"type":"Point"}
}