{
  "type": "Feature",
  "properties": {
    "iso:country":"DE",
    "sg:address":"Unterweiden 130",
    "sg:city":"T\u00f6nisvorst",
    "sg:phone":"+49 2152/517757",
    "sg:postcode":"47918",
    "sg:province":"Nordrhein-Westfalen",
    "wof:name":"Gastst\u00e4tte Haus Nellessen",
    "wof:placetype":"venue"
},
  "geometry": {"coordinates":[6.4649958611,51.3422889709],"type":"Point"}
}