{
  "type": "Feature",
  "properties": {
    "iso:country":"DE",
    "sg:address":"Karl-Liebknecht-Str. 32",
    "sg:city":"Berlin",
    "sg:phone":"+49 30/243430",
    "sg:postcode":"10178",
    "sg:province":"Berlin",
    "wof:name":"Tlg Berlin Alexanderplatz Gmbh",
    "wof:placetype":"venue"
},
  "geometry": {"coordinates":[13.4139556885,52.5252799988],"type":"Point"}
}