{
  "type": "Feature",
  "properties": {
    "iso:country":"DE",
    "sg:address":"Ludwig-Lange-Str. 23",
    "sg:city":"Zeitz",
    "sg:phone":"+49 3441/220122",
    "sg:postcode":"06712",
    "sg:province":"Sachsen-Anhalt",
    "wof:name":"Eiscafe Royal",
    "wof:placetype":"venue"
},
  "geometry": {"coordinates":[12.123462,51.0462],"type":"Point"}
}