{
  "type": "Feature",
  "properties": {
    "iso:country":"DE",
    "sg:address":"Florastr. 2b",
    "sg:city":"D\u00fcsseldorf",
    "sg:phone":"+49 211/376235",
    "sg:postcode":"40217",
    "sg:province":"Nordrhein-Westfalen",
    "wof:name":"Ricci Pempelfort",
    "wof:placetype":"venue"
},
  "geometry": {"coordinates":[6.7732658386,51.2154960632],"type":"Point"}
}