{
  "type": "Feature",
  "properties": {
    "iso:country":"DE",
    "sg:address":"Max-Eyth-Str. 17",
    "sg:city":"Dortmund",
    "sg:phone":"+49 231/422136",
    "sg:postcode":"44141",
    "sg:province":"Nordrhein-Westfalen",
    "wof:name":"J\u00f6rg Engelhardt Architekt",
    "wof:placetype":"venue"
},
  "geometry": {"coordinates":[7.514279,51.501335],"type":"Point"}
}