{
  "type": "Feature",
  "properties": {
    "iso:country":"DE",
    "sg:address":"Karlstr.1",
    "sg:city":"Rheinstetten",
    "sg:postcode":"76287",
    "sg:province":"Baden-W\u00fcrttemberg",
    "wof:name":"Jung, Superscharf, Versaut!",
    "wof:placetype":"venue"
},
  "geometry": {"coordinates":[8.309956,48.973427],"type":"Point"}
}