{
  "type": "Feature",
  "properties": {
    "iso:country":"DE",
    "sg:address":"Hauptstr. 35",
    "sg:city":"Westerngrund",
    "sg:phone":"+49 4960/249174",
    "sg:postcode":"63825",
    "sg:province":"Bayern",
    "wof:name":"Raiffeisenbank Sch\u00f6llkrippen U. Um-, Gebung Eg",
    "wof:placetype":"venue"
},
  "geometry": {"coordinates":[9.241687,50.116516],"type":"Point"}
}