{
  "type": "Feature",
  "properties": {
    "iso:country":"DE",
    "sg:address":"Radefelder Weg 2a",
    "sg:city":"Leipzig",
    "sg:phone":"+49 341/4615222",
    "sg:postcode":"04159",
    "sg:province":"Sachsen",
    "wof:name":"Andre H\u00e4ntzschel",
    "wof:placetype":"venue"
},
  "geometry": {"coordinates":[12.28150177,51.3844604492],"type":"Point"}
}