{
  "type": "Feature",
  "properties": {
    "iso:country":"DE",
    "sg:address":"K\u00f6hnstr. 60",
    "sg:city":"N\u00fcrnberg",
    "sg:phone":"+49 911/4624966",
    "sg:postcode":"90478",
    "sg:province":"Bayern",
    "wof:name":"Anette Oberhauser Rechtsanw\u00e4ltin",
    "wof:placetype":"venue"
},
  "geometry": {"coordinates":[11.092300415,49.4451217651],"type":"Point"}
}