{
  "type": "Feature",
  "properties": {
    "iso:country":"DE",
    "sg:address":"Maybachstr. 169",
    "sg:city":"Krefeld",
    "sg:phone":"+49 2151/540705",
    "sg:postcode":"47809",
    "sg:province":"Nordrhein-Westfalen",
    "wof:name":"W. K\u00f6sters",
    "wof:placetype":"venue"
},
  "geometry": {"coordinates":[6.6116919518,51.330619812],"type":"Point"}
}