{
  "type": "Feature",
  "properties": {
    "iso:country":"DE",
    "sg:address":"Gie\u00dferstr. 49",
    "sg:city":"Leipzig",
    "sg:phone":"+49 341/4804070",
    "sg:postcode":"04229",
    "sg:province":"Sachsen",
    "wof:name":"Hedwig Mahnert",
    "wof:placetype":"venue"
},
  "geometry": {"coordinates":[12.326669693,51.3225440979],"type":"Point"}
}