{
  "type": "Feature",
  "properties": {
    "iso:country":"DE",
    "sg:address":"Brauenkamper Str. 31",
    "sg:city":"Delmenhorst",
    "sg:phone":"+49 4221/86046",
    "sg:postcode":"27753",
    "sg:province":"Niedersachsen",
    "wof:name":"Hamburg Mannheimer Versicherungsgesellschaften",
    "wof:placetype":"venue"
},
  "geometry": {"coordinates":[8.6029253006,53.0436973572],"type":"Point"}
}