{
  "type": "Feature",
  "properties": {
    "iso:country":"DE",
    "sg:address":"Stubaier Str. 20",
    "sg:city":"Stuttgart",
    "sg:phone":"+49 711/330704",
    "sg:postcode":"70327",
    "sg:province":"Baden-W\u00fcrttemberg",
    "wof:name":"Rfl Online Services Gmbh",
    "wof:placetype":"venue"
},
  "geometry": {"coordinates":[9.2523860931,48.7816696167],"type":"Point"}
}