{
  "type": "Feature",
  "properties": {
    "iso:country":"DE",
    "sg:address":"Folzbachstr. 4",
    "sg:city":"M\u00f6mbris",
    "sg:phone":"+49 6029/6482",
    "sg:postcode":"63776",
    "sg:province":"Bayern",
    "wof:name":"Otmar Kaiser",
    "wof:placetype":"venue"
},
  "geometry": {"coordinates":[9.1894226074,50.0513496399],"type":"Point"}
}