{
  "type": "Feature",
  "properties": {
    "iso:country":"DE",
    "sg:address":"Wildrosenweg 26",
    "sg:city":"K\u00f6ln",
    "sg:phone":"+49 221/9636105",
    "sg:postcode":"51061",
    "sg:province":"Nordrhein-Westfalen",
    "wof:name":"D & D Glasbau Und Bauelementehandel Gmbh",
    "wof:placetype":"venue"
},
  "geometry": {"coordinates":[7.0314188004,50.9750366211],"type":"Point"}
}