{
  "type": "Feature",
  "properties": {
    "iso:country":"DE",
    "sg:address":"Hauptstr. 1",
    "sg:city":"Hanau",
    "sg:phone":"+49 6181/54251",
    "sg:postcode":"63457",
    "sg:province":"Hessen",
    "wof:name":"Rochus-apotheke",
    "wof:placetype":"venue"
},
  "geometry": {"coordinates":[8.944821,50.103741],"type":"Point"}
}