{
  "type": "Feature",
  "properties": {
    "iso:country":"DE",
    "sg:address":"Dierdorfer Str. 496",
    "sg:city":"Neuwied",
    "sg:phone":"+49 2631/948664",
    "sg:postcode":"56566",
    "sg:province":"Rheinland-Pfalz",
    "wof:name":"Ursula Kudszus-merl Gmbh & Co. Kg",
    "wof:placetype":"venue"
},
  "geometry": {"coordinates":[7.5108470917,50.4653816223],"type":"Point"}
}