{
  "type": "Feature",
  "properties": {
    "iso:country":"DE",
    "sg:address":"Kirchplatz 5",
    "sg:city":"Molschleben",
    "sg:phone":"+49 36258/52352",
    "sg:postcode":"99869",
    "sg:province":"Th\u00fcringen",
    "wof:name":"Dietrich Walter",
    "wof:placetype":"venue"
},
  "geometry": {"coordinates":[10.783559,51.004047],"type":"Point"}
}