{
  "type": "Feature",
  "properties": {
    "iso:country":"DE",
    "sg:address":"Magdeburger Str. 47",
    "sg:city":"Saarbr\u00fccken",
    "sg:phone":"+49 681/814978",
    "sg:postcode":"66121",
    "sg:province":"Saarland",
    "wof:name":"Wilfried Fuchs",
    "wof:placetype":"venue"
},
  "geometry": {"coordinates":[7.0403780937,49.2358283997],"type":"Point"}
}