{
  "type": "Feature",
  "properties": {
    "iso:country":"DE",
    "sg:address":"Wigeystr. 20",
    "sg:city":"Lennestadt",
    "sg:phone":"+49 2723/96680",
    "sg:postcode":"57368",
    "sg:province":"Nordrhein-Westfalen",
    "wof:name":"Marx & Moschner Gmbh",
    "wof:placetype":"venue"
},
  "geometry": {"coordinates":[8.073109,51.108768],"type":"Point"}
}