{
  "type": "Feature",
  "properties": {
    "iso:country":"DE",
    "sg:address":"H\u00e4nselweg 1",
    "sg:city":"Leipzig",
    "sg:phone":"+49 341/8773780",
    "sg:postcode":"04277",
    "sg:province":"Sachsen",
    "wof:name":"Wolfgang Penndorf",
    "wof:placetype":"venue"
},
  "geometry": {"coordinates":[12.39918,51.307865],"type":"Point"}
}