{
  "type": "Feature",
  "properties": {
    "iso:country":"DE",
    "sg:address":"Heiligenst\u00e4dter Str. 13",
    "sg:city":"Gleichen",
    "sg:phone":"+49 5592/1768",
    "sg:postcode":"37130",
    "sg:province":"Niedersachsen",
    "wof:name":"A. M\u00fcller Hebamme",
    "wof:placetype":"venue"
},
  "geometry": {"coordinates":[10.037879,51.450096],"type":"Point"}
}