{
  "type": "Feature",
  "properties": {
    "iso:country":"DE",
    "sg:address":"In der Meile 5",
    "sg:city":"Dortmund",
    "sg:phone":"+49 231/614086",
    "sg:postcode":"44379",
    "sg:province":"Nordrhein-Westfalen",
    "wof:name":"Roman Schwarz",
    "wof:placetype":"venue"
},
  "geometry": {"coordinates":[7.382018,51.50613],"type":"Point"}
}