{
  "type": "Feature",
  "properties": {
    "iso:country":"DE",
    "sg:address":"Unterl\u00e4nder Str. 41",
    "sg:city":"Stuttgart",
    "sg:phone":"+49 711/9879000",
    "sg:postcode":"70435",
    "sg:province":"Baden-W\u00fcrttemberg",
    "wof:name":"Erz Und Kollegen Rechtsanw\u00e4lte",
    "wof:placetype":"venue"
},
  "geometry": {"coordinates":[9.1711845398,48.8320465088],"type":"Point"}
}