{
  "type": "Feature",
  "properties": {
    "iso:country":"DE",
    "sg:address":"Neumarkter Str. 39",
    "sg:city":"Berg",
    "sg:phone":"+49 9189/7434",
    "sg:postcode":"92348",
    "sg:province":"Bayern",
    "wof:name":"Pizzeria Dolce Vita",
    "wof:placetype":"venue"
},
  "geometry": {"coordinates":[11.443564415,49.3261108398],"type":"Point"}
}