{
  "type": "Feature",
  "properties": {
    "iso:country":"DE",
    "sg:address":"Keferstr. 3",
    "sg:city":"M\u00fcnchen",
    "sg:phone":"+49 89/341250",
    "sg:postcode":"80802",
    "sg:province":"Bayern",
    "wof:name":"Dr. Norbert Jan Mayer Komponist",
    "wof:placetype":"venue"
},
  "geometry": {"coordinates":[11.5929355621,48.1610794067],"type":"Point"}
}