{
  "type": "Feature",
  "properties": {
    "iso:country":"DE",
    "sg:address":"Von-Braun-Str. 25a",
    "sg:city":"Geilenkirchen",
    "sg:phone":"+49 2451/1584",
    "sg:postcode":"52511",
    "sg:province":"Nordrhein-Westfalen",
    "wof:name":"M\u00fcller Design",
    "wof:placetype":"venue"
},
  "geometry": {"coordinates":[6.103636,50.980736],"type":"Point"}
}