{
  "type": "Feature",
  "properties": {
    "iso:country":"DE",
    "sg:address":"Katharinenstr. 23",
    "sg:city":"Neubrandenburg",
    "sg:postcode":"17033",
    "sg:province":"Mecklenburg-Vorpommern",
    "wof:name":"Infoherz New Media Gmbh",
    "wof:placetype":"venue"
},
  "geometry": {"coordinates":[13.2724409103,53.5566368103],"type":"Point"}
}