{
  "type": "Feature",
  "properties": {
    "iso:country":"DE",
    "sg:address":"Ahornweg 5",
    "sg:city":"Leutkirch",
    "sg:phone":"+49 7561/4221",
    "sg:postcode":"88299",
    "sg:province":"Baden-W\u00fcrttemberg",
    "wof:name":"Fritz Mendler",
    "wof:placetype":"venue"
},
  "geometry": {"coordinates":[10.0345,47.822456],"type":"Point"}
}