{
  "type": "Feature",
  "properties": {
    "iso:country":"DE",
    "sg:address":"Richard-R\u00f6sch-Str. 24",
    "sg:city":"Dresden",
    "sg:phone":"+49 351/4768115",
    "sg:postcode":"01129",
    "sg:province":"Sachsen",
    "wof:name":"Waimax Gmbh",
    "wof:placetype":"venue"
},
  "geometry": {"coordinates":[13.703535,51.092495],"type":"Point"}
}