{
  "type": "Feature",
  "properties": {
    "iso:country":"DE",
    "sg:address":"Bahnhofplatz 1",
    "sg:city":"Landshut",
    "sg:phone":"+49 871/9637261",
    "sg:postcode":"84032",
    "sg:province":"Bayern",
    "wof:name":"Deutsche Bahn Ag",
    "wof:placetype":"venue"
},
  "geometry": {"coordinates":[12.1354312897,48.5468482971],"type":"Point"}
}