{
  "type": "Feature",
  "properties": {
    "iso:country":"DE",
    "sg:address":"Bahnhofstr. 1",
    "sg:city":"Rheine",
    "sg:phone":"+49 5971/92310",
    "sg:postcode":"48431",
    "sg:province":"Nordrhein-Westfalen",
    "wof:name":"Bahnhof-apotheke",
    "wof:placetype":"venue"
},
  "geometry": {"coordinates":[7.435999,52.277355],"type":"Point"}
}