{
  "type": "Feature",
  "properties": {
    "iso:country":"DE",
    "sg:address":"Am Stadion 8",
    "sg:city":"Recklinghausen",
    "sg:phone":"+49 2361/109208",
    "sg:postcode":"45659",
    "sg:province":"Nordrhein-Westfalen",
    "wof:name":"Tischlerei Detlef Fluchs E. K.",
    "wof:placetype":"venue"
},
  "geometry": {"coordinates":[7.196853,51.597195],"type":"Point"}
}