{
  "type": "Feature",
  "properties": {
    "iso:country":"DE",
    "sg:address":"Im B\u00e4chel 9",
    "sg:city":"Herborn",
    "sg:phone":"+49 2777/6542",
    "sg:postcode":"35745",
    "sg:province":"Hessen",
    "wof:name":"Pension Dorothe",
    "wof:placetype":"venue"
},
  "geometry": {"coordinates":[8.2227859497,50.6711120605],"type":"Point"}
}