{
  "type": "Feature",
  "properties": {
    "iso:country":"DE",
    "sg:address":"Lindenallee 30",
    "sg:city":"Eisenh\u00fcttenstadt",
    "sg:postcode":"15890",
    "sg:province":"Brandenburg",
    "wof:name":"Allianz Versicherungs Ag",
    "wof:placetype":"venue"
},
  "geometry": {"coordinates":[14.6316003799,52.148815155],"type":"Point"}
}