{
  "type": "Feature",
  "properties": {
    "iso:country":"DE",
    "sg:address":"Dingdener Str.",
    "sg:city":"Bocholt",
    "sg:phone":"+49 2871/15041",
    "sg:postcode":"46395",
    "sg:province":"Nordrhein-Westfalen",
    "wof:name":"B. L\u00fcb Gmbh & Co. Kg",
    "wof:placetype":"venue"
},
  "geometry": {"coordinates":[6.613035202,51.8179893494],"type":"Point"}
}