{
  "type": "Feature",
  "properties": {
    "iso:country":"DE",
    "sg:address":"Hebelermeer 17",
    "sg:city":"Twist",
    "sg:phone":"+49 5935/1563",
    "sg:postcode":"49767",
    "sg:province":"Niedersachsen",
    "wof:name":"Franz Schwenen",
    "wof:placetype":"venue"
},
  "geometry": {"coordinates":[7.092934,52.744705],"type":"Point"}
}