{
  "type": "Feature",
  "properties": {
    "iso:country":"DE",
    "sg:address":"Gammertinger Str. 3",
    "sg:city":"Riedlingen",
    "sg:phone":"+49 7371/2008",
    "sg:postcode":"88499",
    "sg:province":"Baden-W\u00fcrttemberg",
    "wof:name":"Pizzeria La Ragosta",
    "wof:placetype":"venue"
},
  "geometry": {"coordinates":[9.4715528488,48.1528320312],"type":"Point"}
}