{
  "type": "Feature",
  "properties": {
    "iso:country":"DE",
    "sg:address":"Bergkamener Str. 56",
    "sg:city":"Kamen",
    "sg:phone":"+49 2307/18274",
    "sg:postcode":"59174",
    "sg:province":"Nordrhein-Westfalen",
    "wof:name":"Haus Kneuper",
    "wof:placetype":"venue"
},
  "geometry": {"coordinates":[7.651881218,51.5979423523],"type":"Point"}
}