{
  "type": "Feature",
  "properties": {
    "iso:country":"DE",
    "sg:address":"Zum Steinbusch 1",
    "sg:city":"N\u00fcsttal",
    "sg:phone":"+49 6684/362",
    "sg:postcode":"36167",
    "sg:province":"Hessen",
    "wof:name":"Ernst V\u00f6gler",
    "wof:placetype":"venue"
},
  "geometry": {"coordinates":[9.8467187881,50.6359062195],"type":"Point"}
}