{
  "type": "Feature",
  "properties": {
    "iso:country":"DE",
    "sg:address":"August-Bebel-Str. 30",
    "sg:city":"Wallwitz",
    "sg:phone":"+49 39221/340",
    "sg:postcode":"39291",
    "sg:province":"Sachsen-Anhalt",
    "wof:name":"G. Ballerstedt",
    "wof:placetype":"venue"
},
  "geometry": {"coordinates":[11.9120483398,52.1188735962],"type":"Point"}
}