{
  "type": "Feature",
  "properties": {
    "iso:country":"DE",
    "sg:address":"Deggendorfer Str. 41",
    "sg:city":"Hengersberg",
    "sg:phone":"+49 9901/7120",
    "sg:postcode":"94491",
    "sg:province":"Bayern",
    "wof:name":"Franz Warta",
    "wof:placetype":"venue"
},
  "geometry": {"coordinates":[13.051229,48.778259],"type":"Point"}
}