{
  "type": "Feature",
  "properties": {
    "iso:country":"DE",
    "sg:address":"Schlehenweg 11",
    "sg:city":"Neuss",
    "sg:postcode":"41468",
    "sg:province":"Nordrhein-Westfalen",
    "wof:name":"Mtt Martin Tigges Gmbh",
    "wof:placetype":"venue"
},
  "geometry": {"coordinates":[6.7227067947,51.1820106506],"type":"Point"}
}