{
  "type": "Feature",
  "properties": {
    "iso:country":"DE",
    "sg:address":"Am Kirchrain 14",
    "sg:city":"Ringgau",
    "sg:phone":"+49 5659/1010",
    "sg:postcode":"37296",
    "sg:province":"Hessen",
    "wof:name":"Ev. Pfarramt Datterode",
    "wof:placetype":"venue"
},
  "geometry": {"coordinates":[10.024772644,51.119884491],"type":"Point"}
}