{
  "type": "Feature",
  "properties": {
    "iso:country":"DE",
    "sg:address":"Neues Land 5",
    "sg:city":"Basdahl",
    "sg:phone":"+49 4766/3075447",
    "sg:postcode":"27432",
    "sg:province":"Niedersachsen",
    "wof:name":"Heino Peters",
    "wof:placetype":"venue"
},
  "geometry": {"coordinates":[8.978637,53.444172],"type":"Point"}
}