{
  "type": "Feature",
  "properties": {
    "iso:country":"DE",
    "sg:address":"Weisachstr. 8",
    "sg:city":"Markt Taschendorf",
    "sg:phone":"+49 9552/920030",
    "sg:postcode":"91480",
    "sg:province":"Bayern",
    "wof:name":"Ewe Edv Dienstleistungs Und Werbe Gmbh",
    "wof:placetype":"venue"
},
  "geometry": {"coordinates":[10.5551795959,49.7015686035],"type":"Point"}
}