{
  "type": "Feature",
  "properties": {
    "iso:country":"DE",
    "sg:address":"Halfinger Str. 30 - 32",
    "sg:city":"M\u00fcnchen",
    "sg:phone":"+49 89/432021",
    "sg:postcode":"81825",
    "sg:province":"Bayern",
    "wof:name":"Hans Hundsberger Gmbh",
    "wof:placetype":"venue"
},
  "geometry": {"coordinates":[11.6533212662,48.1257896423],"type":"Point"}
}