{
  "type": "Feature",
  "properties": {
    "iso:country":"DE",
    "sg:address":"Gl\u00fccksbrunner Str.",
    "sg:city":"Schweina",
    "sg:phone":"+49 36961/72402",
    "sg:postcode":"36448",
    "sg:province":"Th\u00fcringen",
    "wof:name":"Erbe M\u00f6bel",
    "wof:placetype":"venue"
},
  "geometry": {"coordinates":[10.339124,50.825947],"type":"Point"}
}