{
  "type": "Feature",
  "properties": {
    "iso:country":"DE",
    "sg:address":"Gartenstr. 36",
    "sg:city":"Bergisch Gladbach",
    "sg:postcode":"51429",
    "sg:province":"Nordrhein-Westfalen",
    "wof:name":"Ambulanter Krankenpflegedienst Klaus Werner Gmbh",
    "wof:placetype":"venue"
},
  "geometry": {"coordinates":[7.157713,50.962803],"type":"Point"}
}