{
  "type": "Feature",
  "properties": {
    "iso:country":"DE",
    "sg:address":"Keplerstr. 12",
    "sg:city":"Ulm",
    "sg:phone":"+49 731/66022",
    "sg:postcode":"89073",
    "sg:province":"Baden-W\u00fcrttemberg",
    "wof:name":"Bl\u00fcm Klein Und Rumberg Rechtsanw\u00e4lte",
    "wof:placetype":"venue"
},
  "geometry": {"coordinates":[9.9934988022,48.4035263062],"type":"Point"}
}