{
  "type": "Feature",
  "properties": {
    "iso:country":"DE",
    "sg:address":"Montfortweg 5",
    "sg:city":"Oberstaufen",
    "sg:phone":"+49 8386/4531",
    "sg:postcode":"87534",
    "sg:province":"Bayern",
    "wof:name":"Staufen-brennstoffe Gmbh",
    "wof:placetype":"venue"
},
  "geometry": {"coordinates":[10.0183000565,47.5535354614],"type":"Point"}
}