{
  "type": "Feature",
  "properties": {
    "iso:country":"DE",
    "sg:address":"Am R\u00f6ttchen 5",
    "sg:city":"D\u00fcsseldorf",
    "sg:phone":"+49 211/429718",
    "sg:postcode":"40468",
    "sg:province":"Nordrhein-Westfalen",
    "wof:name":"Johann Hoster",
    "wof:placetype":"venue"
},
  "geometry": {"coordinates":[6.7815990448,51.272857666],"type":"Point"}
}