{
  "type": "Feature",
  "properties": {
    "iso:country":"DE",
    "sg:address":"H\u00f6ven 295",
    "sg:city":"Rosendahl",
    "sg:phone":"+49 2541/5593",
    "sg:postcode":"48720",
    "sg:province":"Nordrhein-Westfalen",
    "wof:name":"Franz Holtk\u00f6tter",
    "wof:placetype":"venue"
},
  "geometry": {"coordinates":[7.12949,51.979481],"type":"Point"}
}