{
  "type": "Feature",
  "properties": {
    "iso:country":"DE",
    "sg:address":"Theodor-Lessing Str. 4",
    "sg:city":"Chemnitz",
    "sg:phone":"+49 371",
    "sg:postcode":"09112",
    "sg:province":"Sachsen",
    "wof:name":"Arztpraxis Gisela Will Chemnitz",
    "wof:placetype":"venue"
},
  "geometry": {"coordinates":[12.898733,50.832867],"type":"Point"}
}