{
  "type": "Feature",
  "properties": {
    "iso:country":"DE",
    "sg:address":"Seepromenade 47a",
    "sg:city":"Falkensee",
    "sg:phone":"+49 3322/236796",
    "sg:postcode":"14612",
    "sg:province":"Brandenburg",
    "wof:name":"Frank Amon Rechtsanwalt",
    "wof:placetype":"venue"
},
  "geometry": {"coordinates":[13.1164770126,52.5730476379],"type":"Point"}
}