{
  "type": "Feature",
  "properties": {
    "iso:country":"DE",
    "sg:address":"In den Fischermatten 4",
    "sg:city":"Emmendingen",
    "sg:phone":"+49 7641/5017",
    "sg:postcode":"79312",
    "sg:province":"Baden-W\u00fcrttemberg",
    "wof:name":"Wolfgang G\u00f6ke",
    "wof:placetype":"venue"
},
  "geometry": {"coordinates":[7.8469438553,48.1151657104],"type":"Point"}
}