{
  "type": "Feature",
  "properties": {
    "iso:country":"DE",
    "sg:address":"Sylvanerweg 9",
    "sg:city":"Alzey",
    "sg:postcode":"55232",
    "sg:province":"Rheinland-Pfalz",
    "wof:name":"Conretis-dieberater- Gruppe- Gmbh",
    "wof:placetype":"venue"
},
  "geometry": {"coordinates":[8.065463,49.738636],"type":"Point"}
}