{
  "type": "Feature",
  "properties": {
    "iso:country":"DE",
    "sg:address":"Spessartstr. 13",
    "sg:city":"Lauterbach",
    "sg:phone":"+49 6641/880",
    "sg:postcode":"36341",
    "sg:province":"Hessen",
    "wof:name":"Amalie Balzer",
    "wof:placetype":"venue"
},
  "geometry": {"coordinates":[9.412919,50.63752],"type":"Point"}
}