{
  "type": "Feature",
  "properties": {
    "iso:country":"DE",
    "sg:address":"Am Dunkelschlag 31",
    "sg:city":"Oberhausen",
    "sg:phone":"+49 208/676449",
    "sg:postcode":"46147",
    "sg:province":"Nordrhein-Westfalen",
    "wof:name":"W. B\u00f6ing Ingenieur",
    "wof:placetype":"venue"
},
  "geometry": {"coordinates":[6.8235349655,51.5480194092],"type":"Point"}
}