{
  "type": "Feature",
  "properties": {
    "iso:country":"DE",
    "sg:address":"Kufsteiner Str. 69",
    "sg:city":"Rosenheim",
    "sg:phone":"+49 8031/14228",
    "sg:postcode":"83026",
    "sg:province":"Bayern",
    "wof:name":"F. Kochlik",
    "wof:placetype":"venue"
},
  "geometry": {"coordinates":[12.126187,47.847225],"type":"Point"}
}