{
  "type": "Feature",
  "properties": {
    "iso:country":"DE",
    "sg:address":"Friedrich-Ebert-Str.",
    "sg:city":"Kassel",
    "sg:phone":"+49 561/3010",
    "sg:postcode":"34119",
    "sg:province":"Hessen",
    "wof:name":"K & S Ag",
    "wof:placetype":"venue"
},
  "geometry": {"coordinates":[9.4646320343,51.3163108826],"type":"Point"}
}