{
  "type": "Feature",
  "properties": {
    "iso:country":"DE",
    "sg:address":"Kieler Str. 70",
    "sg:city":"Rendsburg",
    "sg:phone":"+49 4331/24666",
    "sg:postcode":"24768",
    "sg:province":"Schleswig-Holstein",
    "wof:name":"Gert Czech",
    "wof:placetype":"venue"
},
  "geometry": {"coordinates":[9.6875295639,54.3068656921],"type":"Point"}
}