{
  "type": "Feature",
  "properties": {
    "iso:country":"DE",
    "sg:address":"Rosenstr. 5",
    "sg:city":"Cham",
    "sg:phone":"+49 9971/6031",
    "sg:postcode":"93413",
    "sg:province":"Bayern",
    "wof:name":"Arber Reiseb\u00fcro",
    "wof:placetype":"venue"
},
  "geometry": {"coordinates":[12.6642818451,49.2183494568],"type":"Point"}
}