{
  "type": "Feature",
  "properties": {
    "iso:country":"DE",
    "sg:address":"Hans-Sachs-Str. 7-1",
    "sg:city":"\u00d6hringen",
    "sg:phone":"+49 7941/36311",
    "sg:postcode":"74613",
    "sg:province":"Baden-W\u00fcrttemberg",
    "wof:name":"R. Voigt Hebamme",
    "wof:placetype":"venue"
},
  "geometry": {"coordinates":[9.517347,49.206051],"type":"Point"}
}