{
  "type": "Feature",
  "properties": {
    "iso:country":"DE",
    "sg:address":"Industrieweg 9",
    "sg:city":"Zerbst",
    "sg:phone":"+49 4939/2361230",
    "sg:postcode":"39261",
    "sg:province":"Sachsen-Anhalt",
    "wof:name":"Kmb Technologie Ges. F. Rationelle Fertigung Mbh",
    "wof:placetype":"venue"
},
  "geometry": {"coordinates":[12.0965051651,51.9518356323],"type":"Point"}
}