{
  "type": "Feature",
  "properties": {
    "iso:country":"DE",
    "sg:address":"Kirchenstr. 25",
    "sg:city":"Dortmund",
    "sg:phone":"+49 231/822465",
    "sg:postcode":"44147",
    "sg:province":"Nordrhein-Westfalen",
    "wof:name":"Ev. Pfarramt Paulus Gem.",
    "wof:placetype":"venue"
},
  "geometry": {"coordinates":[7.4552907944,51.5205421448],"type":"Point"}
}