{
  "type": "Feature",
  "properties": {
    "iso:country":"DE",
    "sg:address":"Bauvereinstr. 50",
    "sg:city":"Herford",
    "sg:phone":"+49 5221/80109",
    "sg:postcode":"32049",
    "sg:province":"Nordrhein-Westfalen",
    "wof:name":"Gerhard Burgdorf",
    "wof:placetype":"venue"
},
  "geometry": {"coordinates":[8.7007703781,52.105594635],"type":"Point"}
}