{
  "type": "Feature",
  "properties": {
    "iso:country":"DE",
    "sg:address":"L\u00fcttringhauser Str. 9",
    "sg:city":"Remscheid",
    "sg:phone":"+49 2191/966637",
    "sg:postcode":"42897",
    "sg:province":"Nordrhein-Westfalen",
    "wof:name":"Michael Schmidt-modrow Rechtsanwalt",
    "wof:placetype":"venue"
},
  "geometry": {"coordinates":[7.2542328835,51.1946868896],"type":"Point"}
}