{
  "type": "Feature",
  "properties": {
    "iso:country":"DE",
    "sg:address":"Tuchmacherstr.",
    "sg:city":"Finsterwalde",
    "sg:phone":"+49 3531/8325",
    "sg:postcode":"03238",
    "sg:province":"Brandenburg",
    "wof:name":"Schwimmhalle",
    "wof:placetype":"venue"
},
  "geometry": {"coordinates":[13.7023601532,51.6318855286],"type":"Point"}
}