{
  "type": "Feature",
  "properties": {
    "iso:country":"DE",
    "sg:address":"Hauptstr. 1a",
    "sg:city":"Asbach",
    "sg:phone":"+49 2683/4752",
    "sg:postcode":"53567",
    "sg:province":"Rheinland-Pfalz",
    "wof:name":"Folkard Mentzer",
    "wof:placetype":"venue"
},
  "geometry": {"coordinates":[7.42,50.661198],"type":"Point"}
}