{
  "type": "Feature",
  "properties": {
    "iso:country":"DE",
    "sg:address":"Weiherer Str. 34",
    "sg:city":"Kulmbach",
    "sg:phone":"+49 9221/75742",
    "sg:postcode":"95326",
    "sg:province":"Bayern",
    "wof:name":"Spitzweg-apotheke",
    "wof:placetype":"venue"
},
  "geometry": {"coordinates":[11.451094,50.099411],"type":"Point"}
}