{
  "type": "Feature",
  "properties": {
    "iso:country":"DE",
    "sg:address":"Gutenbergstr. 8",
    "sg:city":"Kriftel",
    "sg:phone":"+49 6192/994050",
    "sg:postcode":"65830",
    "sg:province":"Hessen",
    "wof:name":"Wolters Kluwer Wirtschaftsanlage Gmbh",
    "wof:placetype":"venue"
},
  "geometry": {"coordinates":[8.4774160385,50.0794143677],"type":"Point"}
}