{
  "type": "Feature",
  "properties": {
    "iso:country":"DE",
    "sg:address":"Klopstockstr. 57",
    "sg:city":"Stuttgart",
    "sg:phone":"+49 711/634850",
    "sg:postcode":"70193",
    "sg:province":"Baden-W\u00fcrttemberg",
    "wof:name":"C. Grieser Architekt",
    "wof:placetype":"venue"
},
  "geometry": {"coordinates":[9.149149,48.777077],"type":"Point"}
}