{
  "type": "Feature",
  "properties": {
    "iso:country":"DE",
    "sg:address":"W\u00fcrmtalstr. 79",
    "sg:city":"M\u00fcnchen",
    "sg:phone":"+49 89/7146738",
    "sg:postcode":"81375",
    "sg:province":"Bayern",
    "wof:name":"Claus Frhr. Von Thielmann Rechtsanwalt",
    "wof:placetype":"venue"
},
  "geometry": {"coordinates":[11.4836416245,48.114364624],"type":"Point"}
}