{
  "type": "Feature",
  "properties": {
    "iso:country":"DE",
    "sg:address":"Marktstr. 25",
    "sg:city":"Schraplau",
    "sg:phone":"+49 34774/27242",
    "sg:postcode":"06279",
    "sg:province":"Sachsen-Anhalt",
    "wof:name":"Ratskeller",
    "wof:placetype":"venue"
},
  "geometry": {"coordinates":[11.6668901443,51.438419342],"type":"Point"}
}