{
  "type": "Feature",
  "properties": {
    "iso:country":"DE",
    "sg:address":"Stresemannstr. 16",
    "sg:city":"Darmstadt",
    "sg:postcode":"64297",
    "sg:province":"Hessen",
    "wof:name":"Nabicon Export-import Nabil Hegazi",
    "wof:placetype":"venue"
},
  "geometry": {"coordinates":[8.644804,49.804462],"type":"Point"}
}