{
  "type": "Feature",
  "properties": {
    "iso:country":"DE",
    "sg:address":"Freiberger Str. 41",
    "sg:city":"Brand-Erbisdorf",
    "sg:phone":"+49 37322/3380",
    "sg:postcode":"09618",
    "sg:province":"Sachsen",
    "wof:name":"Autohaus Stephan Kaden Gmbh",
    "wof:placetype":"venue"
},
  "geometry": {"coordinates":[13.3254909515,50.8790359497],"type":"Point"}
}