{
  "type": "Feature",
  "properties": {
    "iso:country":"DE",
    "sg:address":"Holtrup 63",
    "sg:city":"Ennigerloh",
    "sg:postcode":"59320",
    "sg:province":"Nordrhein-Westfalen",
    "wof:name":"Hws Profil-kontor Gmbh",
    "wof:placetype":"venue"
},
  "geometry": {"coordinates":[8.025605,51.834187],"type":"Point"}
}