{
  "type": "Feature",
  "properties": {
    "iso:country":"DE",
    "sg:address":"Schellerweg 59",
    "sg:city":"Stolberg",
    "sg:phone":"+49 2402/25759",
    "sg:postcode":"52223",
    "sg:province":"Nordrhein-Westfalen",
    "wof:name":"Ostl\u00e4nder Immobilien Gmbh",
    "wof:placetype":"venue"
},
  "geometry": {"coordinates":[6.2209911346,50.7719612122],"type":"Point"}
}