{
  "type": "Feature",
  "properties": {
    "iso:country":"DE",
    "sg:address":"Alte Dorfstr. 1",
    "sg:city":"Egestorf",
    "sg:phone":"+49 4175/1060",
    "sg:postcode":"21272",
    "sg:province":"Niedersachsen",
    "wof:name":"Linden-apotheke Inh. Silvia Seipold",
    "wof:placetype":"venue"
},
  "geometry": {"coordinates":[10.063424,53.194294],"type":"Point"}
}