{
  "type": "Feature",
  "properties": {
    "iso:country":"DE",
    "sg:address":"Kerstingweg 15",
    "sg:city":"Schlo\u00df Holte-Stukenbrok",
    "sg:phone":"+49 5207/2255",
    "sg:postcode":"33758",
    "sg:province":"Nordrhein-Westfalen",
    "wof:name":"Horst Haake",
    "wof:placetype":"venue"
},
  "geometry": {"coordinates":[-82.8005599976,27.9655990601],"type":"Point"}
}