{
  "type": "Feature",
  "properties": {
    "iso:country":"DE",
    "sg:address":"Land\u00e4ckerstr. 41",
    "sg:city":"Ludwigsburg",
    "sg:phone":"+49 7141/250567",
    "sg:postcode":"71642",
    "sg:province":"Baden-W\u00fcrttemberg",
    "wof:name":"Brigitte Nowak Steuerberaterin",
    "wof:placetype":"venue"
},
  "geometry": {"coordinates":[9.2236814499,48.9153862],"type":"Point"}
}