{
  "type": "Feature",
  "properties": {
    "iso:country":"DE",
    "sg:address":"Weseler Str. 17",
    "sg:city":"Duisburg",
    "sg:phone":"+49 203/402827",
    "sg:postcode":"47169",
    "sg:province":"Nordrhein-Westfalen",
    "wof:name":"S. Neul",
    "wof:placetype":"venue"
},
  "geometry": {"coordinates":[6.756624,51.50222],"type":"Point"}
}