{
  "type": "Feature",
  "properties": {
    "iso:country":"DE",
    "sg:address":"Marktgasse 13",
    "sg:city":"Mei\u00dfen",
    "sg:phone":"+49 3521/458448",
    "sg:postcode":"01662",
    "sg:province":"Sachsen",
    "wof:name":"Blitzsauber Schnell- Reinigung Gmbh",
    "wof:placetype":"venue"
},
  "geometry": {"coordinates":[13.471476,51.162628],"type":"Point"}
}