{
  "type": "Feature",
  "properties": {
    "iso:country":"DE",
    "sg:address":"Peterstr. 16",
    "sg:city":"Elmshorn",
    "sg:phone":"+49 4121/21811",
    "sg:postcode":"25335",
    "sg:province":"Schleswig-Holstein",
    "wof:name":"Restaurant Baalmann",
    "wof:placetype":"venue"
},
  "geometry": {"coordinates":[9.6532258987,53.7550888062],"type":"Point"}
}