{
  "type": "Feature",
  "properties": {
    "iso:country":"DE",
    "sg:address":"Thorwaldsenstr. 17",
    "sg:city":"M\u00fcnchen",
    "sg:phone":"+49 89/12001770",
    "sg:postcode":"80335",
    "sg:province":"Bayern",
    "wof:name":"Pst Gesundheitszentrum M\u00fcchen Gmbh",
    "wof:placetype":"venue"
},
  "geometry": {"coordinates":[11.549094,48.150826],"type":"Point"}
}