{
  "type": "Feature",
  "properties": {
    "iso:country":"DE",
    "sg:address":"Ostpreu\u00dfenweg 6",
    "sg:city":"Hodenhagen",
    "sg:postcode":"29693",
    "sg:province":"Niedersachsen",
    "wof:name":"Ngh Gas- Und Industrie- Rohrbau Gmbh",
    "wof:placetype":"venue"
},
  "geometry": {"coordinates":[9.597114563,52.7677993774],"type":"Point"}
}