{
  "type": "Feature",
  "properties": {
    "iso:country":"DE",
    "sg:address":"Ursulinenstr. 43-45",
    "sg:city":"Saarbr\u00fccken",
    "sg:phone":"+49 681/389850",
    "sg:postcode":"66111",
    "sg:province":"Saarland",
    "wof:name":"Weinhandel Le Rocher Gmbh",
    "wof:placetype":"venue"
},
  "geometry": {"coordinates":[6.9959058762,49.2403945923],"type":"Point"}
}