{
  "type": "Feature",
  "properties": {
    "iso:country":"DE",
    "sg:address":"B\u00e4ckerstr. 35",
    "sg:city":"Obernkirchen",
    "sg:phone":"+49 5724/2138",
    "sg:postcode":"31683",
    "sg:province":"Niedersachsen",
    "wof:name":"Wilhelm Meier",
    "wof:placetype":"venue"
},
  "geometry": {"coordinates":[9.105048,52.271454],"type":"Point"}
}