{
  "type": "Feature",
  "properties": {
    "iso:country":"DE",
    "sg:address":"Gorch-Fock-Str. 71 a",
    "sg:city":"Emden",
    "sg:phone":"+49 4921/42482",
    "sg:postcode":"26721",
    "sg:province":"Niedersachsen",
    "wof:name":"Volker Poelders",
    "wof:placetype":"venue"
},
  "geometry": {"coordinates":[7.218127,53.384338],"type":"Point"}
}