{
  "type": "Feature",
  "properties": {
    "iso:country":"DE",
    "sg:address":"D\u00fcnefehnstr. 4",
    "sg:city":"Lathen",
    "sg:phone":"+49 5933/8817",
    "sg:postcode":"49762",
    "sg:province":"Niedersachsen",
    "wof:name":"Helmut Rolfes Masseur",
    "wof:placetype":"venue"
},
  "geometry": {"coordinates":[7.334245,52.860035],"type":"Point"}
}