{
  "type": "Feature",
  "properties": {
    "iso:country":"DE",
    "sg:address":"Sch\u00f6nbachstr. 65a",
    "sg:city":"Leipzig",
    "sg:phone":"+49 341/8684620",
    "sg:postcode":"04299",
    "sg:province":"Sachsen",
    "wof:name":"G. Weise",
    "wof:placetype":"venue"
},
  "geometry": {"coordinates":[12.4130096436,51.323387146],"type":"Point"}
}