{
  "type": "Feature",
  "properties": {
    "iso:country":"DE",
    "sg:address":"Firlstr. 32",
    "sg:city":"Berlin",
    "sg:phone":"+49 30/64197930",
    "sg:postcode":"12459",
    "sg:province":"Berlin",
    "wof:name":"Schl\u00fcsseldienst Schnell Ohg",
    "wof:placetype":"venue"
},
  "geometry": {"coordinates":[13.521805,52.461704],"type":"Point"}
}