{
  "type": "Feature",
  "properties": {
    "iso:country":"DE",
    "sg:address":"Hagenbreite 9",
    "sg:city":"Ermsleben",
    "sg:phone":"+49 34743/53632",
    "sg:postcode":"06463",
    "sg:province":"Sachsen-Anhalt",
    "wof:name":"Exhibition Und Marketing Wehrstadt Gmbh",
    "wof:placetype":"venue"
},
  "geometry": {"coordinates":[11.3467721939,51.7271270752],"type":"Point"}
}