{
  "type": "Feature",
  "properties": {
    "iso:country":"DE",
    "sg:address":"Puschkinstr. 23 a",
    "sg:city":"Frankfurt",
    "sg:phone":"+49 335/535732",
    "sg:postcode":"15236",
    "sg:province":"Brandenburg",
    "wof:name":"Manfred Dorge",
    "wof:placetype":"venue"
},
  "geometry": {"coordinates":[14.532128334,52.3367538452],"type":"Point"}
}