{
  "type": "Feature",
  "properties": {
    "iso:country":"DE",
    "sg:address":"Hagener Landstr. 21",
    "sg:city":"Uthlede",
    "sg:phone":"+49 4296/330",
    "sg:postcode":"27628",
    "sg:province":"Niedersachsen",
    "wof:name":"Helmut Schnibbe",
    "wof:placetype":"venue"
},
  "geometry": {"coordinates":[8.579457,53.315762],"type":"Point"}
}