{
  "type": "Feature",
  "properties": {
    "iso:country":"DE",
    "sg:address":"Moritzstr. 34 - 35",
    "sg:city":"Bad Gandersheim",
    "sg:phone":"+49 5382/2659",
    "sg:postcode":"37581",
    "sg:province":"Niedersachsen",
    "wof:name":"Leopold Kempe Inh. Wilma Timm",
    "wof:placetype":"venue"
},
  "geometry": {"coordinates":[10.024656,51.86937],"type":"Point"}
}