{
  "type": "Feature",
  "properties": {
    "iso:country":"DE",
    "sg:address":"Fleiner Str. 6",
    "sg:city":"Heilbronn",
    "sg:phone":"+49 4971/3162260",
    "sg:postcode":"74072",
    "sg:province":"Baden-W\u00fcrttemberg",
    "wof:name":"Palm Am Fleiner Tor Gmbh",
    "wof:placetype":"venue"
},
  "geometry": {"coordinates":[9.219083,49.139652],"type":"Point"}
}