{
  "type": "Feature",
  "properties": {
    "iso:country":"DE",
    "sg:address":"J\u00e4gerstieg 34",
    "sg:city":"Gardelegen",
    "sg:phone":"+49 3907/711938",
    "sg:postcode":"39638",
    "sg:province":"Sachsen-Anhalt",
    "wof:name":"P. Schulz",
    "wof:placetype":"venue"
},
  "geometry": {"coordinates":[11.404247,52.522583],"type":"Point"}
}