{
  "type": "Feature",
  "properties": {
    "iso:country":"DE",
    "sg:address":"Schmiedeweg 2",
    "sg:city":"Oldenburg",
    "sg:phone":"+49 4944/1920680",
    "sg:postcode":"26135",
    "sg:province":"Niedersachsen",
    "wof:name":"Novacard Informationssysteme Gmbh",
    "wof:placetype":"venue"
},
  "geometry": {"coordinates":[8.2634658813,53.108001709],"type":"Point"}
}