{
  "type": "Feature",
  "properties": {
    "iso:country":"DE",
    "sg:address":"Augustinerstr. 22",
    "sg:city":"Esslingen",
    "sg:phone":"+49 711/353096",
    "sg:postcode":"73728",
    "sg:province":"Baden-W\u00fcrttemberg",
    "wof:name":"Schlaegel Maier Wolff Rechtsanw\u00e4lte",
    "wof:placetype":"venue"
},
  "geometry": {"coordinates":[9.3083963394,48.7433547974],"type":"Point"}
}