{
  "type": "Feature",
  "properties": {
    "iso:country":"DE",
    "sg:address":"Friedhof",
    "sg:city":"Holzgerlingen",
    "sg:phone":"+49 7031",
    "sg:postcode":"71088",
    "sg:province":"Baden-W\u00fcrttemberg",
    "wof:name":"Holzgerlinger Turner Und Leichtathleten",
    "wof:placetype":"venue"
},
  "geometry": {"coordinates":[9.015832,48.641193],"type":"Point"}
}