{
  "type": "Feature",
  "properties": {
    "iso:country":"DE",
    "sg:address":"Hasenwinkel 14",
    "sg:city":"Schneverdingen",
    "sg:phone":"+49 5193/7452",
    "sg:postcode":"29640",
    "sg:province":"Niedersachsen",
    "wof:name":"Helmut J\u00e4ger",
    "wof:placetype":"venue"
},
  "geometry": {"coordinates":[9.7837638855,53.1292228699],"type":"Point"}
}