{
  "type": "Feature",
  "properties": {
    "iso:country":"DE",
    "sg:address":"Unterer Sch\u00fctzenrain 16",
    "sg:city":"Leonberg",
    "sg:phone":"+49 7152/25851",
    "sg:postcode":"71229",
    "sg:province":"Baden-W\u00fcrttemberg",
    "wof:name":"Textiltechnik Fuchs Erich Fuchs",
    "wof:placetype":"venue"
},
  "geometry": {"coordinates":[9.018976,48.805084],"type":"Point"}
}