{
  "type": "Feature",
  "properties": {
    "iso:country":"DE",
    "sg:address":"Am Handweisergraben 11",
    "sg:city":"Bovenden",
    "sg:phone":"+49 571/798390",
    "sg:postcode":"37120",
    "sg:province":"Niedersachsen",
    "wof:name":"Rubi Rost Gmbh & Co Kg",
    "wof:placetype":"venue"
},
  "geometry": {"coordinates":[8.9177703857,52.2377929688],"type":"Point"}
}