{
  "type": "Feature",
  "properties": {
    "iso:country":"DE",
    "sg:address":"Nistenbergstr. 21",
    "sg:city":"Bergneustadt",
    "sg:phone":"+49 2261/45150",
    "sg:postcode":"51702",
    "sg:province":"Nordrhein-Westfalen",
    "wof:name":"Angelika Wessendorf Krankengymnastin",
    "wof:placetype":"venue"
},
  "geometry": {"coordinates":[7.669347,51.026043],"type":"Point"}
}