{
  "type": "Feature",
  "properties": {
    "iso:country":"DE",
    "sg:address":"Maasstr. 25",
    "sg:city":"D\u00fcsseldorf",
    "sg:phone":"+49 211/51447",
    "sg:postcode":"40547",
    "sg:province":"Nordrhein-Westfalen",
    "wof:name":"Katholisches Pfarramt Christ K\u00f6nig",
    "wof:placetype":"venue"
},
  "geometry": {"coordinates":[6.7377109528,51.2392883301],"type":"Point"}
}