{
  "type": "Feature",
  "properties": {
    "iso:country":"DE",
    "sg:address":"Ostermoorweg 60",
    "sg:city":"B\u00f6nningstedt",
    "sg:phone":"+49 40/5566361",
    "sg:postcode":"25474",
    "sg:province":"Schleswig-Holstein",
    "wof:name":"Jonny Heidorn",
    "wof:placetype":"venue"
},
  "geometry": {"coordinates":[9.910815239,53.6757049561],"type":"Point"}
}