{
  "type": "Feature",
  "properties": {
    "iso:country":"DE",
    "sg:address":"Klaiberweg 14",
    "sg:city":"Gro\u00dfaitingen",
    "sg:phone":"+49 8203/295",
    "sg:postcode":"86845",
    "sg:province":"Bayern",
    "wof:name":"Fritz Nixdorf",
    "wof:placetype":"venue"
},
  "geometry": {"coordinates":[10.775069,48.225544],"type":"Point"}
}