{
  "type": "Feature",
  "properties": {
    "iso:country":"DE",
    "sg:address":"An der Mauer",
    "sg:city":"Memmingen",
    "sg:phone":"+49 8331/5627",
    "sg:postcode":"87700",
    "sg:province":"Bayern",
    "wof:name":"Gustav Greiner",
    "wof:placetype":"venue"
},
  "geometry": {"coordinates":[10.179044,47.983185],"type":"Point"}
}