{
  "type": "Feature",
  "properties": {
    "iso:country":"DE",
    "sg:address":"Franz-Mehring-Str. 24",
    "sg:city":"Gera",
    "sg:phone":"+49 365/855990",
    "sg:postcode":"07545",
    "sg:province":"Th\u00fcringen",
    "wof:name":"Thomas Witt Rechtsanwalt",
    "wof:placetype":"venue"
},
  "geometry": {"coordinates":[12.0813846588,50.8845252991],"type":"Point"}
}