{
  "type": "Feature",
  "properties": {
    "iso:country":"DE",
    "sg:address":"Witschgasse 16",
    "sg:city":"Pulheim",
    "sg:phone":"+49 2238/83270",
    "sg:postcode":"50259",
    "sg:province":"Nordrhein-Westfalen",
    "wof:name":"K. Piuk Architekt",
    "wof:placetype":"venue"
},
  "geometry": {"coordinates":[6.805493,50.998455],"type":"Point"}
}