{
  "type": "Feature",
  "properties": {
    "iso:country":"DE",
    "sg:address":"Georg-Storm-Str. 36a",
    "sg:city":"Weiterstadt",
    "sg:phone":"+49 6150/14919",
    "sg:postcode":"64331",
    "sg:province":"Hessen",
    "wof:name":"Bk-med Gesundheits- Produkte Gmbh",
    "wof:placetype":"venue"
},
  "geometry": {"coordinates":[8.5867757797,49.9048576355],"type":"Point"}
}