{
  "type": "Feature",
  "properties": {
    "iso:country":"DE",
    "sg:address":"Richard-Strauss-Str. 2",
    "sg:city":"Gochsheim",
    "sg:phone":"+49 9721/61946",
    "sg:postcode":"97469",
    "sg:province":"Bayern",
    "wof:name":"Omnibusreisen Schickram Gmbh",
    "wof:placetype":"venue"
},
  "geometry": {"coordinates":[10.2754802704,50.0245399475],"type":"Point"}
}