{
  "type": "Feature",
  "properties": {
    "iso:country":"DE",
    "sg:address":"Auf der H\u00f6he 66",
    "sg:city":"Duisburg",
    "sg:phone":"+49 203/313133",
    "sg:postcode":"47059",
    "sg:province":"Nordrhein-Westfalen",
    "wof:name":"Expo Fair Messen Und Austellungsbau Gmbh",
    "wof:placetype":"venue"
},
  "geometry": {"coordinates":[6.727775,51.432819],"type":"Point"}
}