{
  "type": "Feature",
  "properties": {
    "iso:country":"DE",
    "sg:address":"Aribostr. 7",
    "sg:city":"Rottach-Egern",
    "sg:phone":"+49 8022/92190",
    "sg:postcode":"83700",
    "sg:province":"Bayern",
    "wof:name":"G\u00e4stehaus Liedschreiber",
    "wof:placetype":"venue"
},
  "geometry": {"coordinates":[11.7570457458,47.694683075],"type":"Point"}
}