{
  "type": "Feature",
  "properties": {
    "iso:country":"DE",
    "sg:address":"K\u00f6niginstr. 4",
    "sg:city":"Feldafing",
    "sg:phone":"+49 8157/8200",
    "sg:postcode":"82340",
    "sg:province":"Bayern",
    "wof:name":"Strandbad",
    "wof:placetype":"venue"
},
  "geometry": {"coordinates":[11.3068008423,47.9489784241],"type":"Point"}
}