{
  "type": "Feature",
  "properties": {
    "iso:country":"DE",
    "sg:address":"Im Pferdebrook 18",
    "sg:city":"Bielefeld",
    "sg:phone":"+49 521/105077",
    "sg:postcode":"33619",
    "sg:province":"Nordrhein-Westfalen",
    "wof:name":"Treuhansa Verm\u00f6gensverwaltungs Gmbh",
    "wof:placetype":"venue"
},
  "geometry": {"coordinates":[8.4884939194,52.0267601013],"type":"Point"}
}