{
  "type": "Feature",
  "properties": {
    "iso:country":"DE",
    "sg:address":"Pferdemarkt 16",
    "sg:city":"Stade",
    "sg:phone":"+49 4141/44742",
    "sg:postcode":"21682",
    "sg:province":"Niedersachsen",
    "wof:name":"A. Harms",
    "wof:placetype":"venue"
},
  "geometry": {"coordinates":[9.47545,53.599831],"type":"Point"}
}