{
  "type": "Feature",
  "properties": {
    "iso:country":"DE",
    "sg:address":"Gartenstr. 19",
    "sg:city":"Hilgert",
    "sg:phone":"+49 2624/7548",
    "sg:postcode":"56206",
    "sg:province":"Rheinland-Pfalz",
    "wof:name":"Heinz Z\u00f6ller",
    "wof:placetype":"venue"
},
  "geometry": {"coordinates":[7.691006,50.456276],"type":"Point"}
}