{
  "type": "Feature",
  "properties": {
    "iso:country":"DE",
    "sg:address":"Eugen-Bolz-Str. 44",
    "sg:city":"T\u00fcbingen",
    "sg:phone":"+49 7472/42009",
    "sg:postcode":"72072",
    "sg:province":"Baden-W\u00fcrttemberg",
    "wof:name":"P. Rigger",
    "wof:placetype":"venue"
},
  "geometry": {"coordinates":[9.000848,48.484154],"type":"Point"}
}