{
  "type": "Feature",
  "properties": {
    "iso:country":"DE",
    "sg:address":"Hauptstr. 11",
    "sg:city":"Thallwitz",
    "sg:phone":"+49 3425/923312",
    "sg:postcode":"04808",
    "sg:province":"Sachsen",
    "wof:name":"Rainer Augst",
    "wof:placetype":"venue"
},
  "geometry": {"coordinates":[12.6818323135,51.431350708],"type":"Point"}
}