{
  "type": "Feature",
  "properties": {
    "iso:country":"DE",
    "sg:address":"Augustenstr. 88",
    "sg:city":"Stuttgart",
    "sg:phone":"+49 711/6150421",
    "sg:postcode":"70178",
    "sg:province":"Baden-W\u00fcrttemberg",
    "wof:name":"Delphi",
    "wof:placetype":"venue"
},
  "geometry": {"coordinates":[9.1591863632,48.769443512],"type":"Point"}
}