{
  "type": "Feature",
  "properties": {
    "iso:country":"DE",
    "sg:address":"Holzbr\u00fcnnlstr. 17",
    "sg:city":"Haag",
    "sg:phone":"+49 8167/310",
    "sg:postcode":"85410",
    "sg:province":"Bayern",
    "wof:name":"B. Wolf",
    "wof:placetype":"venue"
},
  "geometry": {"coordinates":[11.823013,48.459911],"type":"Point"}
}