{
  "type": "Feature",
  "properties": {
    "iso:country":"DE",
    "sg:address":"Europaallee 2",
    "sg:city":"Frechen",
    "sg:phone":"+49 2234/2030",
    "sg:postcode":"50226",
    "sg:province":"Nordrhein-Westfalen",
    "wof:name":"Fgm M\u00f6bel Handels Gmbh & Co. Kg",
    "wof:placetype":"venue"
},
  "geometry": {"coordinates":[6.834393,50.915703],"type":"Point"}
}