{
  "type": "Feature",
  "properties": {
    "iso:country":"DE",
    "sg:address":"Falkenweg 1",
    "sg:city":"Eschwege",
    "sg:phone":"+49 5651/754676",
    "sg:postcode":"37269",
    "sg:province":"Hessen",
    "wof:name":"Bernd Gro\u00dfst\u00fcck",
    "wof:placetype":"venue"
},
  "geometry": {"coordinates":[10.078804,51.17057],"type":"Point"}
}