{
  "type": "Feature",
  "properties": {
    "iso:country":"DE",
    "sg:address":"Am Weiher 3",
    "sg:city":"Reichenberg",
    "sg:phone":"+49 351/839850",
    "sg:postcode":"01468",
    "sg:province":"Sachsen",
    "wof:name":"M\u00fchl Product Und Service Mittelsachsen Gmbh",
    "wof:placetype":"venue"
},
  "geometry": {"coordinates":[13.679889679,51.1426086426],"type":"Point"}
}