{
  "type": "Feature",
  "properties": {
    "iso:country":"DE",
    "sg:address":"Friedrich-Ebert-Str. 156",
    "sg:city":"Osthofen",
    "sg:phone":"+49 6242/7764",
    "sg:postcode":"67574",
    "sg:province":"Rheinland-Pfalz",
    "wof:name":"August Stoll Immobilienmakler",
    "wof:placetype":"venue"
},
  "geometry": {"coordinates":[8.3084220886,49.7031364441],"type":"Point"}
}