{
  "type": "Feature",
  "properties": {
    "iso:country":"DE",
    "sg:address":"Kattowitzer Str. 78",
    "sg:city":"M\u00fcnchen",
    "sg:phone":"+49 89/937250",
    "sg:postcode":"81929",
    "sg:province":"Bayern",
    "wof:name":"Adolf Lechner Architekt",
    "wof:placetype":"venue"
},
  "geometry": {"coordinates":[11.655261,48.149868],"type":"Point"}
}