{
  "type": "Feature",
  "properties": {
    "iso:country":"DE",
    "sg:address":"N\u00fcrtinger Str. 1",
    "sg:city":"Filderstadt",
    "sg:phone":"+49 711/701600",
    "sg:postcode":"70794",
    "sg:province":"Baden-W\u00fcrttemberg",
    "wof:name":"B\u00e4ckerhaus Veit Gmbh",
    "wof:placetype":"venue"
},
  "geometry": {"coordinates":[9.218358,48.678581],"type":"Point"}
}