{
  "type": "Feature",
  "properties": {
    "iso:country":"DE",
    "sg:address":"Karlsberg 9",
    "sg:city":"Weinheim",
    "sg:phone":"+49 6201/183354",
    "sg:postcode":"69469",
    "sg:province":"Baden-W\u00fcrttemberg",
    "wof:name":"P. F. Overdevest",
    "wof:placetype":"venue"
},
  "geometry": {"coordinates":[8.671529,49.54945],"type":"Point"}
}