{
  "type": "Feature",
  "properties": {
    "iso:country":"DE",
    "sg:address":"Bahnhofstr. 4",
    "sg:city":"Mei\u00dfen",
    "sg:phone":"+49 3521/732022",
    "sg:postcode":"01662",
    "sg:province":"Sachsen",
    "wof:name":"Volker Scharnagel",
    "wof:placetype":"venue"
},
  "geometry": {"coordinates":[13.4786539078,51.1641235352],"type":"Point"}
}