{
  "type": "Feature",
  "properties": {
    "iso:country":"DE",
    "sg:address":"Saarlandstr. 158",
    "sg:city":"Bingen",
    "sg:phone":"+49 6721/41106",
    "sg:postcode":"55411",
    "sg:province":"Rheinland-Pfalz",
    "wof:name":"Karl Kastell",
    "wof:placetype":"venue"
},
  "geometry": {"coordinates":[7.9102377892,49.9504547119],"type":"Point"}
}