{
  "type": "Feature",
  "properties": {
    "iso:country":"DE",
    "sg:address":"Fabrikstr. 108",
    "sg:city":"Borna",
    "sg:postcode":"04552",
    "sg:province":"Sachsen",
    "wof:name":"Mibrag Vereinigte Mittel- Deutsche Braunkohlenwerke Ag",
    "wof:placetype":"venue"
},
  "geometry": {"coordinates":[12.475619,51.12524],"type":"Point"}
}