{
  "type": "Feature",
  "properties": {
    "iso:country":"DE",
    "sg:address":"Findorffstr. 6",
    "sg:city":"Grasberg",
    "sg:phone":"+49 4208/1377",
    "sg:postcode":"28879",
    "sg:province":"Niedersachsen",
    "wof:name":"Wsg Industrievertretung Und Ingenieurb\u00fcro W. Schwitzing",
    "wof:placetype":"venue"
},
  "geometry": {"coordinates":[8.98788,53.181164],"type":"Point"}
}