{
  "type": "Feature",
  "properties": {
    "iso:country":"DE",
    "sg:address":"Neue Str. 40",
    "sg:city":"Bremerv\u00f6rde",
    "sg:postcode":"27432",
    "sg:province":"Niedersachsen",
    "wof:name":"Stiftung Der Kreissparkasse Bremerv\u00f6rde Zur F\u00f6rderung Von",
    "wof:placetype":"venue"
},
  "geometry": {"coordinates":[9.1444578171,53.4877624512],"type":"Point"}
}