{
  "type": "Feature",
  "properties": {
    "iso:country":"DE",
    "sg:address":"Beusselstr. 50",
    "sg:city":"Berlin",
    "sg:phone":"+49 30/3921391",
    "sg:postcode":"10553",
    "sg:province":"Berlin",
    "wof:name":"Troja Grill",
    "wof:placetype":"venue"
},
  "geometry": {"coordinates":[13.3283061981,52.5317649841],"type":"Point"}
}