{
  "type": "Feature",
  "properties": {
    "iso:country":"DE",
    "sg:address":"Hofmarkstr. 27 b",
    "sg:city":"Planegg",
    "sg:postcode":"82152",
    "sg:province":"Bayern",
    "wof:name":"Richard Toolen Gmbh",
    "wof:placetype":"venue"
},
  "geometry": {"coordinates":[11.419506073,48.109413147],"type":"Point"}
}