{
  "type": "Feature",
  "properties": {
    "iso:country":"DE",
    "sg:address":"Rudolf-Diesel-Str. 10",
    "sg:city":"Buchloe",
    "sg:phone":"+49 8241/5030",
    "sg:postcode":"86807",
    "sg:province":"Bayern",
    "wof:name":"Helmut Kulessa Gmbh & Co. Kg",
    "wof:placetype":"venue"
},
  "geometry": {"coordinates":[10.7159776688,48.0443572998],"type":"Point"}
}