{
  "type": "Feature",
  "properties": {
    "iso:country":"DE",
    "sg:address":"Sudetenstr. 26",
    "sg:city":"Weilm\u00fcnster",
    "sg:phone":"+49 6472/7090",
    "sg:postcode":"35789",
    "sg:province":"Hessen",
    "wof:name":"B\u00e4rbels Frisurenstudio",
    "wof:placetype":"venue"
},
  "geometry": {"coordinates":[8.3831663132,50.4296989441],"type":"Point"}
}