{
  "type": "Feature",
  "properties": {
    "iso:country":"DE",
    "sg:address":"Am Wall 128 -134",
    "sg:city":"Bremen",
    "sg:phone":"+49 4942/130930",
    "sg:postcode":"28195",
    "sg:province":"Bremen",
    "wof:name":"Herm Dauelsberg Gmbh & Co",
    "wof:placetype":"venue"
},
  "geometry": {"coordinates":[8.8066291809,53.0794067383],"type":"Point"}
}