{
  "type": "Feature",
  "properties": {
    "iso:country":"DE",
    "sg:address":"Liebfrauenstr. 3",
    "sg:city":"Hirzenhain",
    "sg:phone":"+49 6045/1888",
    "sg:postcode":"63697",
    "sg:province":"Hessen",
    "wof:name":"Karlheinz Marx",
    "wof:placetype":"venue"
},
  "geometry": {"coordinates":[9.1579093933,50.4005393982],"type":"Point"}
}