{
  "type": "Feature",
  "properties": {
    "iso:country":"DE",
    "sg:address":"Westender Weg 83",
    "sg:city":"Herdecke",
    "sg:phone":"+49 2330/8162",
    "sg:postcode":"58313",
    "sg:province":"Nordrhein-Westfalen",
    "wof:name":"Blumen Kohlstedt",
    "wof:placetype":"venue"
},
  "geometry": {"coordinates":[7.405485,51.41301],"type":"Point"}
}