{
  "type": "Feature",
  "properties": {
    "iso:country":"DE",
    "sg:address":"Bosfelder Weg 25",
    "sg:city":"Rheda-Wiedenbr\u00fcck",
    "sg:phone":"+49 5242/94450",
    "sg:postcode":"33378",
    "sg:province":"Nordrhein-Westfalen",
    "wof:name":"Strunz-happe Familien Beteiligungs Gmbh",
    "wof:placetype":"venue"
},
  "geometry": {"coordinates":[8.274817,51.857143],"type":"Point"}
}