{
  "type": "Feature",
  "properties": {
    "iso:country":"DE",
    "sg:address":"Vierzoner Str.",
    "sg:city":"Bitterfeld",
    "sg:phone":"+49 4934/9360810",
    "sg:postcode":"06749",
    "sg:province":"Sachsen-Anhalt",
    "wof:name":"Handelshof Bitterfeld Gmbh",
    "wof:placetype":"venue"
},
  "geometry": {"coordinates":[12.294004,51.611828],"type":"Point"}
}