{
  "type": "Feature",
  "properties": {
    "iso:country":"DE",
    "sg:address":"Seetalstr. 5",
    "sg:city":"Bad Urach",
    "sg:phone":"+49 7381/3328",
    "sg:postcode":"72574",
    "sg:province":"Baden-W\u00fcrttemberg",
    "wof:name":"M. Oettinger",
    "wof:placetype":"venue"
},
  "geometry": {"coordinates":[9.4560537338,48.445930481],"type":"Point"}
}