{
  "type": "Feature",
  "properties": {
    "iso:country":"DE",
    "sg:address":"Olgastr. 2",
    "sg:city":"Heilbronn",
    "sg:phone":"+49 7131/84033",
    "sg:postcode":"74072",
    "sg:province":"Baden-W\u00fcrttemberg",
    "wof:name":"Schuster Ladenbau Und Einrichtungen Gmbh",
    "wof:placetype":"venue"
},
  "geometry": {"coordinates":[9.21126,49.140442],"type":"Point"}
}