{
  "type": "Feature",
  "properties": {
    "iso:country":"DE",
    "sg:address":"In den Griesen 15",
    "sg:city":"Langenfeld",
    "sg:phone":"+49 2173/97420",
    "sg:postcode":"40764",
    "sg:province":"Nordrhein-Westfalen",
    "wof:name":"Bauverein Langenfeld E.g.",
    "wof:placetype":"venue"
},
  "geometry": {"coordinates":[6.950168,51.115604],"type":"Point"}
}