{
  "type": "Feature",
  "properties": {
    "iso:country":"DE",
    "sg:address":"Akazienallee 6",
    "sg:city":"T\u00f6nisvorst",
    "sg:phone":"+49 2151/790582",
    "sg:postcode":"47918",
    "sg:province":"Nordrhein-Westfalen",
    "wof:name":"Josef Krins Steuerberater",
    "wof:placetype":"venue"
},
  "geometry": {"coordinates":[6.4923439026,51.31407547],"type":"Point"}
}