{
  "type": "Feature",
  "properties": {
    "iso:country":"DE",
    "sg:address":"Winkelstr. 8",
    "sg:city":"Ennepetal",
    "sg:phone":"+49 4923/3372615",
    "sg:postcode":"58256",
    "sg:province":"Nordrhein-Westfalen",
    "wof:name":"Ennepetaler Kistenfabrik Schl\u00c4per Inh Arno Fichtner",
    "wof:placetype":"venue"
},
  "geometry": {"coordinates":[7.3453888893,51.3010177612],"type":"Point"}
}