{
  "type": "Feature",
  "properties": {
    "iso:country":"DE",
    "sg:address":"Im Letsch 25",
    "sg:city":"Bergisch Gladbach",
    "sg:phone":"+49 2204/24658",
    "sg:postcode":"51427",
    "sg:province":"Nordrhein-Westfalen",
    "wof:name":"Josef Trompetter Rechtsanwalt",
    "wof:placetype":"venue"
},
  "geometry": {"coordinates":[7.1090660095,50.9569892883],"type":"Point"}
}