{
  "type": "Feature",
  "properties": {
    "iso:country":"DE",
    "sg:address":"Am Sandbach 23",
    "sg:city":"Trier",
    "sg:phone":"+49 651/34847",
    "sg:postcode":"54294",
    "sg:province":"Rheinland-Pfalz",
    "wof:name":"Heinz Rau",
    "wof:placetype":"venue"
},
  "geometry": {"coordinates":[6.631527,49.727268],"type":"Point"}
}