{
  "type": "Feature",
  "properties": {
    "iso:country":"DE",
    "sg:address":"Friedrich-Ebert-Str. 228",
    "sg:city":"M\u00f6nchengladbach",
    "sg:phone":"+49 2166/2821",
    "sg:postcode":"41236",
    "sg:province":"Nordrhein-Westfalen",
    "wof:name":"G\u00fcnter Dorn",
    "wof:placetype":"venue"
},
  "geometry": {"coordinates":[6.4395217896,51.173828125],"type":"Point"}
}