{
  "type": "Feature",
  "properties": {
    "iso:country":"DE",
    "sg:address":"Burgstr. 23",
    "sg:city":"M\u00fclheim-K\u00e4rlich",
    "sg:phone":"+49 2630/4821",
    "sg:postcode":"56218",
    "sg:province":"Rheinland-Pfalz",
    "wof:name":"Hilde Kindl",
    "wof:placetype":"venue"
},
  "geometry": {"coordinates":[7.486006,50.389561],"type":"Point"}
}