{
  "type": "Feature",
  "properties": {
    "iso:country":"DE",
    "sg:address":"Lindenstr. 72",
    "sg:city":"Miltach",
    "sg:phone":"+49 9944/465",
    "sg:postcode":"93468",
    "sg:province":"Bayern",
    "wof:name":"Robert Huber Heilpraktiker",
    "wof:placetype":"venue"
},
  "geometry": {"coordinates":[12.7649173737,49.1706466675],"type":"Point"}
}