{
  "type": "Feature",
  "properties": {
    "iso:country":"DE",
    "sg:address":"Gartenstr. 4",
    "sg:city":"Neidlingen",
    "sg:phone":"+49 7023/72020",
    "sg:postcode":"73272",
    "sg:province":"Baden-W\u00fcrttemberg",
    "wof:name":"Wlz-raiffeisen Ag",
    "wof:placetype":"venue"
},
  "geometry": {"coordinates":[9.565711,48.576168],"type":"Point"}
}