{
  "type": "Feature",
  "properties": {
    "iso:country":"DE",
    "sg:address":"Arndtstr. 28",
    "sg:city":"Hamburg",
    "sg:phone":"+49 40/2290676",
    "sg:postcode":"22085",
    "sg:province":"Hamburg",
    "wof:name":"Karlheinz W\u00fcst Kameramann",
    "wof:placetype":"venue"
},
  "geometry": {"coordinates":[10.0179595947,53.5749092102],"type":"Point"}
}