{
  "type": "Feature",
  "properties": {
    "iso:country":"DE",
    "sg:address":"Valdorfer stra\u00dfe 7",
    "sg:city":"Bad Oeynhausen",
    "sg:phone":"+49 5731",
    "sg:postcode":"32545",
    "sg:province":"Nordrhein-Westfalen",
    "wof:name":"P\u00f6nnighaus Holzkunst",
    "wof:placetype":"venue"
},
  "geometry": {"coordinates":[8.8074178696,52.1767578125],"type":"Point"}
}