{
  "type": "Feature",
  "properties": {
    "iso:country":"DE",
    "sg:address":"Flandrische Str. 13",
    "sg:city":"K\u00f6ln",
    "sg:phone":"+49 221/1390403",
    "sg:postcode":"50674",
    "sg:province":"Nordrhein-Westfalen",
    "wof:name":"Thomas Hollacher Rechtsanwalt",
    "wof:placetype":"venue"
},
  "geometry": {"coordinates":[6.9380440712,50.9368896484],"type":"Point"}
}