{
  "type": "Feature",
  "properties": {
    "iso:country":"DE",
    "sg:address":"Waldgirmeser Str. 42",
    "sg:city":"Wetzlar",
    "sg:phone":"+49 6441/32049",
    "sg:postcode":"35584",
    "sg:province":"Hessen",
    "wof:name":"Christa Figurski",
    "wof:placetype":"venue"
},
  "geometry": {"coordinates":[8.528571,50.584011],"type":"Point"}
}