{
  "type": "Feature",
  "properties": {
    "iso:country":"DE",
    "sg:address":"An der Brauerei 5",
    "sg:city":"Leipzig",
    "sg:phone":"+49 34297/42279",
    "sg:postcode":"04288",
    "sg:province":"Sachsen",
    "wof:name":"Obstland D\u00fcrrweitzschen Ag",
    "wof:placetype":"venue"
},
  "geometry": {"coordinates":[12.4582185745,51.2833099365],"type":"Point"}
}