{
  "type": "Feature",
  "properties": {
    "iso:country":"DE",
    "sg:address":"Schlo\u00dfstr. 2",
    "sg:city":"D\u00fcsseldorf",
    "sg:phone":"+49 211/5150584",
    "sg:postcode":"40477",
    "sg:province":"Nordrhein-Westfalen",
    "wof:name":"K-l-r Assekuranz-agentur E. K.",
    "wof:placetype":"venue"
},
  "geometry": {"coordinates":[6.7890901566,51.2383460999],"type":"Point"}
}