{
  "type": "Feature",
  "properties": {
    "iso:country":"DE",
    "sg:address":"Friedrichstr. 39",
    "sg:city":"Oberhausen",
    "sg:phone":"+49 208/6903634",
    "sg:postcode":"46145",
    "sg:province":"Nordrhein-Westfalen",
    "wof:name":"Rudolf Fenten Architekt",
    "wof:placetype":"venue"
},
  "geometry": {"coordinates":[6.84524,51.512241],"type":"Point"}
}