{
  "type": "Feature",
  "properties": {
    "iso:country":"DE",
    "sg:address":"Torgauer Str. 21",
    "sg:city":"Belgern",
    "sg:phone":"+49 34224/41879",
    "sg:postcode":"04874",
    "sg:province":"Sachsen",
    "wof:name":"Thomas Mieth",
    "wof:placetype":"venue"
},
  "geometry": {"coordinates":[13.1169662476,51.4861755371],"type":"Point"}
}