{
  "type": "Feature",
  "properties": {
    "iso:country":"DE",
    "sg:address":"Industriegebiet Bergheim",
    "sg:city":"Steinheim",
    "sg:phone":"+49 4952/3394940",
    "sg:postcode":"32839",
    "sg:province":"Nordrhein-Westfalen",
    "wof:name":"E + G Furniere Emde Und G\u00dcnther Gmbh & Co Kg",
    "wof:placetype":"venue"
},
  "geometry": {"coordinates":[9.0920648575,51.8672866821],"type":"Point"}
}