{
  "type": "Feature",
  "properties": {
    "iso:country":"DE",
    "sg:address":"Seestr. 1",
    "sg:city":"Bretten",
    "sg:phone":"+49 7252/6945",
    "sg:postcode":"75015",
    "sg:province":"Baden-W\u00fcrttemberg",
    "wof:name":"Wolfgang W\u00f6rner",
    "wof:placetype":"venue"
},
  "geometry": {"coordinates":[8.67982,49.042255],"type":"Point"}
}