{
  "type": "Feature",
  "properties": {
    "iso:country":"DE",
    "sg:address":"Leipziger Str. 71",
    "sg:city":"Fulda",
    "sg:phone":"+49 661/9628221",
    "sg:postcode":"36037",
    "sg:province":"Hessen",
    "wof:name":"Iris Vogt",
    "wof:placetype":"venue"
},
  "geometry": {"coordinates":[9.6839542389,50.5619888306],"type":"Point"}
}