{
  "type": "Feature",
  "properties": {
    "iso:country":"DE",
    "sg:address":"Buchheimer Str. 1",
    "sg:city":"Heideland",
    "sg:phone":"+49 36691/42482",
    "sg:postcode":"07613",
    "sg:province":"Th\u00fcringen",
    "wof:name":"L\u00d6blein Gutsverwaltungeisenberg Gmbh & Co. Kg",
    "wof:placetype":"venue"
},
  "geometry": {"coordinates":[11.947981,50.994221],"type":"Point"}
}