{
  "type": "Feature",
  "properties": {
    "iso:country":"DE",
    "sg:address":"Marktplatz 22",
    "sg:city":"Aidenbach",
    "sg:phone":"+49 8543/3515",
    "sg:postcode":"94501",
    "sg:province":"Bayern",
    "wof:name":"Mimos Pizzaabholservice",
    "wof:placetype":"venue"
},
  "geometry": {"coordinates":[13.0872821808,48.56798172],"type":"Point"}
}