{
  "type": "Feature",
  "properties": {
    "iso:country":"DE",
    "sg:address":"Miraustr. 42",
    "sg:city":"Berlin",
    "sg:phone":"+49 30/4117081",
    "sg:postcode":"13509",
    "sg:province":"Berlin",
    "wof:name":"Minderjahn Untern.- Und Beteil.-verw. Mbh",
    "wof:placetype":"venue"
},
  "geometry": {"coordinates":[13.3100767136,52.5837402344],"type":"Point"}
}