{
  "type": "Feature",
  "properties": {
    "iso:country":"DE",
    "sg:address":"Steinstr.",
    "sg:city":"Brandenburg",
    "sg:phone":"+49 3381/200330",
    "sg:postcode":"14776",
    "sg:province":"Brandenburg",
    "wof:name":"Mc Donalds Deutschland",
    "wof:placetype":"venue"
},
  "geometry": {"coordinates":[12.5595216751,52.4066696167],"type":"Point"}
}