{
  "type": "Feature",
  "properties": {
    "iso:country":"DE",
    "sg:address":"R\u00f6derweg 33",
    "sg:city":"R\u00fcdesheim am Rhein",
    "sg:phone":"+49 6722/3505",
    "sg:postcode":"65385",
    "sg:province":"Hessen",
    "wof:name":"Ulrich Abel",
    "wof:placetype":"venue"
},
  "geometry": {"coordinates":[7.893222,49.993114],"type":"Point"}
}