{
  "type": "Feature",
  "properties": {
    "iso:country":"DE",
    "sg:address":"Herrenwiese 23",
    "sg:city":"Wetzlar",
    "sg:phone":"+49 6441/72841",
    "sg:postcode":"35581",
    "sg:province":"Hessen",
    "wof:name":"Manfred Schmidt",
    "wof:placetype":"venue"
},
  "geometry": {"coordinates":[8.5822782516,50.5490226746],"type":"Point"}
}