{
  "type": "Feature",
  "properties": {
    "iso:country":"DE",
    "sg:address":"Todtgl\u00fcsinger Stra\u00dfe 4",
    "sg:city":"Tostedt",
    "sg:phone":"+49 4182/291282",
    "sg:postcode":"21255",
    "sg:province":"Niedersachsen",
    "wof:name":"Modelagentur Pegasus Stadtmittelpunkt",
    "wof:placetype":"venue"
},
  "geometry": {"coordinates":[9.71901,53.283348],"type":"Point"}
}