{
  "type": "Feature",
  "properties": {
    "iso:country":"DE",
    "sg:address":"Klingenhofstr. 77",
    "sg:city":"N\u00fcrnberg",
    "sg:phone":"+49 911/5298017",
    "sg:postcode":"90411",
    "sg:province":"Bayern",
    "wof:name":"Reinhard Keil",
    "wof:placetype":"venue"
},
  "geometry": {"coordinates":[11.116579,49.477951],"type":"Point"}
}