{
  "type": "Feature",
  "properties": {
    "iso:country":"DE",
    "sg:address":"Bachtelm\u00fchlstr. 37",
    "sg:city":"Kempten",
    "sg:phone":"+49 831/78805",
    "sg:postcode":"87437",
    "sg:province":"Bayern",
    "wof:name":"Ehc Extrakt Und Harz Chemie Gmbh",
    "wof:placetype":"venue"
},
  "geometry": {"coordinates":[10.33677,47.722912],"type":"Point"}
}