{
  "type": "Feature",
  "properties": {
    "iso:country":"DE",
    "sg:address":"M\u00fclheimer Str. 74",
    "sg:city":"Ratingen",
    "sg:phone":"+49 2102/870487",
    "sg:postcode":"40878",
    "sg:province":"Nordrhein-Westfalen",
    "wof:name":"Euromex-mikroskope Optische Erzeugnisse",
    "wof:placetype":"venue"
},
  "geometry": {"coordinates":[6.8556981087,51.3029785156],"type":"Point"}
}