{
  "type": "Feature",
  "properties": {
    "iso:country":"DE",
    "sg:address":"Heideweg 20",
    "sg:city":"Maxdorf",
    "sg:phone":"+49 6237/7600",
    "sg:postcode":"67133",
    "sg:province":"Rheinland-Pfalz",
    "wof:name":"Dr. Karl Nagel Rechtsanwalt",
    "wof:placetype":"venue"
},
  "geometry": {"coordinates":[8.2863235474,49.4860115051],"type":"Point"}
}