{
  "type": "Feature",
  "properties": {
    "iso:country":"DE",
    "sg:address":"Hackenbaum 18",
    "sg:city":"Wiesbaden",
    "sg:phone":"+49 611/502527",
    "sg:postcode":"65207",
    "sg:province":"Hessen",
    "wof:name":"Gossmann Fensterhandel Gmbh",
    "wof:placetype":"venue"
},
  "geometry": {"coordinates":[8.3038682938,50.0975227356],"type":"Point"}
}