{
  "type": "Feature",
  "properties": {
    "iso:country":"DE",
    "sg:address":"Kollaustr. 84",
    "sg:city":"Hamburg",
    "sg:phone":"+49 40/583376",
    "sg:postcode":"22453",
    "sg:province":"Hamburg",
    "wof:name":"Walter Kuhnigk Architekt",
    "wof:placetype":"venue"
},
  "geometry": {"coordinates":[9.960846,53.607689],"type":"Point"}
}