{
  "type": "Feature",
  "properties": {
    "iso:country":"DE",
    "sg:address":"Lesmonastr. 4",
    "sg:city":"Bremen",
    "sg:phone":"+49 421/635541",
    "sg:postcode":"28717",
    "sg:province":"Bremen",
    "wof:name":"Dat - Sch\u00e4tzungsstelle Lesum",
    "wof:placetype":"venue"
},
  "geometry": {"coordinates":[8.688183,53.168114],"type":"Point"}
}