{
  "type": "Feature",
  "properties": {
    "iso:country":"DE",
    "sg:address":"Selbecker Str 141-143",
    "sg:city":"Hagen",
    "sg:phone":"+49 2331/9770",
    "sg:postcode":"58091",
    "sg:province":"Nordrhein-Westfalen",
    "wof:name":"Hermann Huster Gmbh & Co. Kg",
    "wof:placetype":"venue"
},
  "geometry": {"coordinates":[7.48365,51.340443],"type":"Point"}
}