{
  "type": "Feature",
  "properties": {
    "iso:country":"DE",
    "sg:address":"Hohenzollernstr. 82",
    "sg:city":"Recklinghausen",
    "sg:phone":"+49 2361/22814",
    "sg:postcode":"45659",
    "sg:province":"Nordrhein-Westfalen",
    "wof:name":"Franz B. Feldhaus",
    "wof:placetype":"venue"
},
  "geometry": {"coordinates":[7.1866650581,51.6094703674],"type":"Point"}
}