{
  "type": "Feature",
  "properties": {
    "iso:country":"DE",
    "sg:address":"Haselbach",
    "sg:city":"Ellenberg",
    "sg:phone":"+49 7965/587",
    "sg:postcode":"73488",
    "sg:province":"Baden-W\u00fcrttemberg",
    "wof:name":"Gastst\u00e4tte Friedrich Pfisterer",
    "wof:placetype":"venue"
},
  "geometry": {"coordinates":[10.2204885483,48.9847831726],"type":"Point"}
}