{
  "type": "Feature",
  "properties": {
    "iso:country":"DE",
    "sg:address":"Leipziger Str. 70",
    "sg:city":"Frankfurt",
    "sg:phone":"+49 69/703017",
    "sg:postcode":"60487",
    "sg:province":"Hessen",
    "wof:name":"E. Salatini Dolmetscher Und \u00dcbersetzer",
    "wof:placetype":"venue"
},
  "geometry": {"coordinates":[8.644489,50.123131],"type":"Point"}
}