{
  "type": "Feature",
  "properties": {
    "iso:country":"DE",
    "sg:address":"Alfred-Stumpf-Str. 2",
    "sg:city":"Lohr",
    "sg:phone":"+49 9352/9341",
    "sg:postcode":"97816",
    "sg:province":"Bayern",
    "wof:name":"Br\u00e4ust\u00fcbl",
    "wof:placetype":"venue"
},
  "geometry": {"coordinates":[9.5790500641,50.0230102539],"type":"Point"}
}