{
  "type": "Feature",
  "properties": {
    "iso:country":"DE",
    "sg:address":"Stra\u00dfe der Deutschen Einheit",
    "sg:city":"Geithain",
    "sg:postcode":"04643",
    "sg:province":"Sachsen",
    "wof:name":"Joachim Dedicke",
    "wof:placetype":"venue"
},
  "geometry": {"coordinates":[12.6865148544,51.0585746765],"type":"Point"}
}