{
  "type": "Feature",
  "properties": {
    "iso:country":"DE",
    "sg:address":"D\u00e4nische Str. 18",
    "sg:city":"Kiel",
    "sg:phone":"+49 431/95317",
    "sg:postcode":"24103",
    "sg:province":"Schleswig-Holstein",
    "wof:name":"Fred Richter Antiquit\u00e4ten",
    "wof:placetype":"venue"
},
  "geometry": {"coordinates":[10.140823,54.323925],"type":"Point"}
}