{
  "type": "Feature",
  "properties": {
    "iso:country":"DE",
    "sg:address":"Wagnerstr 20",
    "sg:city":"Steinhagen",
    "sg:phone":"+49 521/5229621",
    "sg:postcode":"33803",
    "sg:province":"Nordrhein-Westfalen",
    "wof:name":"Eurocont 2000 Agentur Deutschland",
    "wof:placetype":"venue"
},
  "geometry": {"coordinates":[8.4193820953,52.002696991],"type":"Point"}
}