{
  "type": "Feature",
  "properties": {
    "iso:country":"DE",
    "sg:address":"Zum Anger 8",
    "sg:city":"Landau",
    "sg:phone":"+49 9951/5230",
    "sg:postcode":"94405",
    "sg:province":"Bayern",
    "wof:name":"Sfs Bekleidungs- Und Spielwarenhandels Gmbh",
    "wof:placetype":"venue"
},
  "geometry": {"coordinates":[12.761524,48.661324],"type":"Point"}
}