{
  "type": "Feature",
  "properties": {
    "iso:country":"DE",
    "sg:address":"Sophie-Charlotten-Str. 41",
    "sg:city":"Berlin",
    "sg:postcode":"14059",
    "sg:province":"Berlin",
    "wof:name":"Extra",
    "wof:placetype":"venue"
},
  "geometry": {"coordinates":[13.2879724503,52.513671875],"type":"Point"}
}