{
  "type": "Feature",
  "properties": {
    "iso:country":"DE",
    "sg:address":"Maxstr. 17",
    "sg:city":"Donaustauf",
    "sg:phone":"+49 9403/4990",
    "sg:postcode":"93093",
    "sg:province":"Bayern",
    "wof:name":"Dr. Med. Michaela Faltermeier",
    "wof:placetype":"venue"
},
  "geometry": {"coordinates":[12.2088699341,49.0287742615],"type":"Point"}
}