{
  "type": "Feature",
  "properties": {
    "iso:country":"DE",
    "sg:address":"Hermann-Henning-Str. 4",
    "sg:city":"Wetter",
    "sg:phone":"+49 2335/680971",
    "sg:postcode":"58300",
    "sg:province":"Nordrhein-Westfalen",
    "wof:name":"Thomas Schmalenbeck Architekt",
    "wof:placetype":"venue"
},
  "geometry": {"coordinates":[7.373044,51.380318],"type":"Point"}
}