{
  "type": "Feature",
  "properties": {
    "iso:country":"DE",
    "sg:address":"Schubartstr. 6",
    "sg:city":"Berlin",
    "sg:phone":"+49 30/4121520",
    "sg:postcode":"13509",
    "sg:province":"Berlin",
    "wof:name":"Ernst Schmidt Inh. Ronald Schmidt",
    "wof:placetype":"venue"
},
  "geometry": {"coordinates":[13.305122,52.582531],"type":"Point"}
}