{
  "type": "Feature",
  "properties": {
    "iso:country":"DE",
    "sg:address":"Fraenkelufer 30",
    "sg:city":"Berlin",
    "sg:phone":"+49 30/6146086",
    "sg:postcode":"10999",
    "sg:province":"Berlin",
    "wof:name":"Reinhard Und Barbara Hanke Garten- Und",
    "wof:placetype":"venue"
},
  "geometry": {"coordinates":[13.414114,52.495712],"type":"Point"}
}