{
  "type": "Feature",
  "properties": {
    "iso:country":"DE",
    "sg:address":"Schillerstr. 102",
    "sg:city":"Duisburg",
    "sg:phone":"+49 2066/10753",
    "sg:postcode":"47166",
    "sg:province":"Nordrhein-Westfalen",
    "wof:name":"Dietrich Roeder Rechtsanwalt",
    "wof:placetype":"venue"
},
  "geometry": {"coordinates":[6.7819080353,51.49659729],"type":"Point"}
}