{
  "type": "Feature",
  "properties": {
    "iso:country":"DE",
    "sg:address":"Krenzliner Str. 4",
    "sg:city":"Kummer",
    "sg:phone":"+49 38751/20632",
    "sg:postcode":"19288",
    "sg:province":"Mecklenburg-Vorpommern",
    "wof:name":"Siegmund Genz",
    "wof:placetype":"venue"
},
  "geometry": {"coordinates":[11.388321,53.330696],"type":"Point"}
}