{
  "type": "Feature",
  "properties": {
    "iso:country":"DE",
    "sg:address":"Gewerbegebiet",
    "sg:city":"Camburg",
    "sg:phone":"+49 36421/7110",
    "sg:postcode":"07774",
    "sg:province":"Th\u00fcringen",
    "wof:name":"H\u00fcttig Gmbh",
    "wof:placetype":"venue"
},
  "geometry": {"coordinates":[11.7128896713,51.0429382324],"type":"Point"}
}