{
  "type": "Feature",
  "properties": {
    "iso:country":"DE",
    "sg:address":"Riesestr. 12",
    "sg:city":"Dortmund",
    "sg:phone":"+49 4962/86180",
    "sg:postcode":"44287",
    "sg:province":"Nordrhein-Westfalen",
    "wof:name":"Dossmann Gmbh",
    "wof:placetype":"venue"
},
  "geometry": {"coordinates":[9.290532,49.62418],"type":"Point"}
}