{
  "type": "Feature",
  "properties": {
    "iso:country":"DE",
    "sg:address":"Karlstr. 40",
    "sg:city":"M\u00f6glingen",
    "sg:phone":"+49 7141/482552",
    "sg:postcode":"71696",
    "sg:province":"Baden-W\u00fcrttemberg",
    "wof:name":"Ishak Bardakcioglu",
    "wof:placetype":"venue"
},
  "geometry": {"coordinates":[9.1213827133,48.8898658752],"type":"Point"}
}