{
  "type": "Feature",
  "properties": {
    "iso:country":"DE",
    "sg:address":"Fischeln 8",
    "sg:city":"Schwalmtal",
    "sg:phone":"+49 2163/49277",
    "sg:postcode":"41366",
    "sg:province":"Nordrhein-Westfalen",
    "wof:name":"Johann Boers",
    "wof:placetype":"venue"
},
  "geometry": {"coordinates":[6.312669,51.195419],"type":"Point"}
}