{
  "type": "Feature",
  "properties": {
    "iso:country":"DE",
    "sg:address":"Oefelestr. 11",
    "sg:city":"M\u00fcnchen",
    "sg:phone":"+49 89/653673",
    "sg:postcode":"81543",
    "sg:province":"Bayern",
    "wof:name":"Lithocolor Helmut Finsterwald",
    "wof:placetype":"venue"
},
  "geometry": {"coordinates":[11.573512,48.119614],"type":"Point"}
}