{
  "type": "Feature",
  "properties": {
    "iso:country":"DE",
    "sg:address":"Stollberger Str. 65",
    "sg:city":"Berlin",
    "sg:phone":"+49 30/99499108",
    "sg:postcode":"12627",
    "sg:province":"Berlin",
    "wof:name":"Peter Winter",
    "wof:placetype":"venue"
},
  "geometry": {"coordinates":[13.6027841568,52.533290863],"type":"Point"}
}