{
  "type": "Feature",
  "properties": {
    "iso:country":"DE",
    "sg:address":"Schomburgstr 116",
    "sg:city":"Hamburg",
    "sg:phone":"+49 4403/919310",
    "sg:postcode":"22767",
    "sg:province":"Hamburg",
    "wof:name":"Kws K\u00fcttler Gmbh",
    "wof:placetype":"venue"
},
  "geometry": {"coordinates":[7.9428138733,53.1744842529],"type":"Point"}
}