{
  "type": "Feature",
  "properties": {
    "iso:country":"DE",
    "sg:address":"Moosen",
    "sg:city":"Taufkirchen",
    "sg:phone":"+49 8084/8700",
    "sg:postcode":"84416",
    "sg:province":"Bayern",
    "wof:name":"Manfred U. Ingrid Zuhr",
    "wof:placetype":"venue"
},
  "geometry": {"coordinates":[12.1809101105,48.3425483704],"type":"Point"}
}