{
  "type": "Feature",
  "properties": {
    "iso:country":"DE",
    "sg:address":"Hagelstr. 15",
    "sg:city":"Waltrop",
    "sg:phone":"+49 2309/2639",
    "sg:postcode":"45731",
    "sg:province":"Nordrhein-Westfalen",
    "wof:name":"Pampam",
    "wof:placetype":"venue"
},
  "geometry": {"coordinates":[7.3967480659,51.6239395142],"type":"Point"}
}