{
  "type": "Feature",
  "properties": {
    "iso:country":"DE",
    "sg:address":"Muldestr.",
    "sg:city":"Zwickau",
    "sg:phone":"+49 375/270050",
    "sg:postcode":"08056",
    "sg:province":"Sachsen",
    "wof:name":"Tbg Transportbeton Zwickau Gmbh & Co. Kg",
    "wof:placetype":"venue"
},
  "geometry": {"coordinates":[12.501075,50.684528],"type":"Point"}
}