{
  "type": "Feature",
  "properties": {
    "iso:country":"DE",
    "sg:address":"Ostbahnstr. 124",
    "sg:city":"Hersbruck",
    "sg:phone":"+49 9151/2071",
    "sg:postcode":"91217",
    "sg:province":"Bayern",
    "wof:name":"Tbg Pegnitz-beton Verwaltungsgesellschaft Mbh",
    "wof:placetype":"venue"
},
  "geometry": {"coordinates":[11.428033,49.499046],"type":"Point"}
}