{
  "type": "Feature",
  "properties": {
    "iso:country":"DE",
    "sg:address":"Hauptstr. 12",
    "sg:city":"Ergoldsbach",
    "sg:phone":"+49 8771/3528",
    "sg:postcode":"84061",
    "sg:province":"Bayern",
    "wof:name":"Michael Kunze Rechtsanwalt",
    "wof:placetype":"venue"
},
  "geometry": {"coordinates":[12.2042798996,48.6902503967],"type":"Point"}
}