{
  "type": "Feature",
  "properties": {
    "iso:country":"DE",
    "sg:address":"Semmelweg 92",
    "sg:city":"B\u00fcnde",
    "sg:phone":"+49 5223/42379",
    "sg:postcode":"32257",
    "sg:province":"Nordrhein-Westfalen",
    "wof:name":"Kurt Weitkamp",
    "wof:placetype":"venue"
},
  "geometry": {"coordinates":[8.603425,52.209179],"type":"Point"}
}