{
  "type": "Feature",
  "properties": {
    "iso:country":"DE",
    "sg:address":"Horather Str. 189",
    "sg:city":"Wuppertal",
    "sg:phone":"+49 202/77683",
    "sg:postcode":"42111",
    "sg:province":"Nordrhein-Westfalen",
    "wof:name":"Restaurant D\u00f6nberger Krug",
    "wof:placetype":"venue"
},
  "geometry": {"coordinates":[7.1632437706,51.2999305725],"type":"Point"}
}