{
  "type": "Feature",
  "properties": {
    "iso:country":"DE",
    "sg:address":"Stra\u00dfe des Friedens 7",
    "sg:city":"Kesselsdorf",
    "sg:phone":"+49 35204/9470",
    "sg:postcode":"01723",
    "sg:province":"Sachsen",
    "wof:name":"Kleber & Krumbiegel Gmbh",
    "wof:placetype":"venue"
},
  "geometry": {"coordinates":[13.5910072327,51.0320892334],"type":"Point"}
}