{
  "type": "Feature",
  "properties": {
    "iso:country":"DE",
    "sg:address":"Carl-Benz-Ring 5",
    "sg:city":"Schwarzheide",
    "sg:phone":"+49 35752/7562",
    "sg:postcode":"01987",
    "sg:province":"Brandenburg",
    "wof:name":"Duo-n T\u00fcrenmarkt & Fachgro\u00dfhandel",
    "wof:placetype":"venue"
},
  "geometry": {"coordinates":[13.82595,51.47213],"type":"Point"}
}