{
  "type": "Feature",
  "properties": {
    "iso:country":"DE",
    "sg:address":"Kr\u00e4merstr. 1",
    "sg:city":"Neuss",
    "sg:phone":"+49 2131/222916",
    "sg:postcode":"41460",
    "sg:province":"Nordrhein-Westfalen",
    "wof:name":"Restaurant Steak-haus",
    "wof:placetype":"venue"
},
  "geometry": {"coordinates":[6.6928877831,51.1981124878],"type":"Point"}
}