{
  "type": "Feature",
  "properties": {
    "iso:country":"DE",
    "sg:address":"Ernst-Ludwig-Str. 2",
    "sg:city":"Badenheim",
    "sg:phone":"+49 6701/93090",
    "sg:postcode":"55576",
    "sg:province":"Rheinland-Pfalz",
    "wof:name":"Volkmar Fuhr",
    "wof:placetype":"venue"
},
  "geometry": {"coordinates":[7.968419075,49.8414421082],"type":"Point"}
}