{
  "type": "Feature",
  "properties": {
    "iso:country":"DE",
    "sg:address":"Wertherstr. 311",
    "sg:city":"Bielefeld",
    "sg:phone":"+49 521/103128",
    "sg:postcode":"33619",
    "sg:province":"Nordrhein-Westfalen",
    "wof:name":"Culturclub E. V. Im Pappelkrug",
    "wof:placetype":"venue"
},
  "geometry": {"coordinates":[8.478549,52.039234],"type":"Point"}
}