{
  "type": "Feature",
  "properties": {
    "iso:country":"DE",
    "sg:address":"Poschm\u00fchle 93",
    "sg:city":"Hausham",
    "sg:postcode":"83734",
    "sg:province":"Bayern",
    "wof:name":"Albert Hirschm\u00fcller",
    "wof:placetype":"venue"
},
  "geometry": {"coordinates":[11.8256454468,47.7715148926],"type":"Point"}
}