{
  "type": "Feature",
  "properties": {
    "iso:country":"DE",
    "sg:address":"Mirweilerweg 4",
    "sg:city":"D\u00fcren",
    "sg:phone":"+49 2421/61450",
    "sg:postcode":"52349",
    "sg:province":"Nordrhein-Westfalen",
    "wof:name":"Textoris Apparate- Und Rohrleitungsbau Gmbh",
    "wof:placetype":"venue"
},
  "geometry": {"coordinates":[6.4534950256,50.8028793335],"type":"Point"}
}