{
  "type": "Feature",
  "properties": {
    "iso:country":"DE",
    "sg:address":"Wettinerstr. 33",
    "sg:city":"Aue",
    "sg:phone":"+49 3771/22953",
    "sg:postcode":"08280",
    "sg:province":"Sachsen",
    "wof:name":"Ulrich Otto Rechtsanwalt",
    "wof:placetype":"venue"
},
  "geometry": {"coordinates":[12.6993303299,50.5827178955],"type":"Point"}
}