{
  "type": "Feature",
  "properties": {
    "iso:country":"DE",
    "sg:address":"Volksbadstr. 11",
    "sg:city":"Neustadt",
    "sg:phone":"+49 6321/32613",
    "sg:postcode":"67434",
    "sg:province":"Rheinland-Pfalz",
    "wof:name":"F. Tretschock",
    "wof:placetype":"venue"
},
  "geometry": {"coordinates":[8.132106781,49.3515777588],"type":"Point"}
}