{
  "type": "Feature",
  "properties": {
    "iso:country":"DE",
    "sg:address":"Alte Wildunger Str. 6",
    "sg:city":"Fritzlar",
    "sg:phone":"+49 5622/915178",
    "sg:postcode":"34560",
    "sg:province":"Hessen",
    "wof:name":"Mcdonald's",
    "wof:placetype":"venue"
},
  "geometry": {"coordinates":[9.276263237,51.1208953857],"type":"Point"}
}