{
  "type": "Feature",
  "properties": {
    "iso:country":"DE",
    "sg:address":"Katharinenhof",
    "sg:city":"Bad Breisig",
    "sg:phone":"+49 2633/95115",
    "sg:postcode":"53498",
    "sg:province":"Rheinland-Pfalz",
    "wof:name":"Karl Kurp",
    "wof:placetype":"venue"
},
  "geometry": {"coordinates":[7.282,50.526997],"type":"Point"}
}