{
  "type": "Feature",
  "properties": {
    "iso:country":"DE",
    "sg:address":"Herderstra\u00dfe 18",
    "sg:city":"D\u00fcsseldorf",
    "sg:phone":"+49 4921/1665353",
    "sg:postcode":"40237",
    "sg:province":"Nordrhein-Westfalen",
    "wof:name":"Global Press Nachrichtenagentur & Informationsdienste Gmbh",
    "wof:placetype":"venue"
},
  "geometry": {"coordinates":[6.798516,51.234978],"type":"Point"}
}