{
  "type": "Feature",
  "properties": {
    "iso:country":"DE",
    "sg:address":"Oberdorf 62",
    "sg:city":"Marienberg",
    "sg:phone":"+49 3735/25928",
    "sg:postcode":"09496",
    "sg:province":"Sachsen",
    "wof:name":"J. Bergelt",
    "wof:placetype":"venue"
},
  "geometry": {"coordinates":[13.1659049988,50.6820335388],"type":"Point"}
}