{
  "type": "Feature",
  "properties": {
    "iso:country":"DE",
    "sg:address":"K\u00f6nigstrasse 67",
    "sg:city":"Magdeburg",
    "sg:phone":"+49 391/635050",
    "sg:postcode":"39116",
    "sg:province":"Sachsen-Anhalt",
    "wof:name":"Aom - Allofmedia.de",
    "wof:placetype":"venue"
},
  "geometry": {"coordinates":[11.566546,52.087208],"type":"Point"}
}