{
  "type": "Feature",
  "properties": {
    "iso:country":"DE",
    "sg:address":"Obergasse 5",
    "sg:city":"Alsfeld",
    "sg:phone":"+49 6631/73580",
    "sg:postcode":"36304",
    "sg:province":"Hessen",
    "wof:name":"Top Center",
    "wof:placetype":"venue"
},
  "geometry": {"coordinates":[9.271002,50.751282],"type":"Point"}
}