{
  "type": "Feature",
  "properties": {
    "iso:country":"DE",
    "sg:address":"Rodheimer Str. 3",
    "sg:city":"Oberickelsheim",
    "sg:phone":"+49 9339/991551",
    "sg:postcode":"97258",
    "sg:province":"Bayern",
    "wof:name":"Dietmar Schuster Heilpraktiker",
    "wof:placetype":"venue"
},
  "geometry": {"coordinates":[10.1363601685,49.5991706848],"type":"Point"}
}