{
  "type": "Feature",
  "properties": {
    "iso:country":"DE",
    "sg:address":"Hauptstr. 54",
    "sg:city":"Bottrop",
    "sg:phone":"+49 2045/2001",
    "sg:postcode":"46244",
    "sg:province":"Nordrhein-Westfalen",
    "wof:name":"Wbr Wohnbau-rustige Gmbh",
    "wof:placetype":"venue"
},
  "geometry": {"coordinates":[6.923355,51.603832],"type":"Point"}
}