{
  "type": "Feature",
  "properties": {
    "iso:country":"DE",
    "sg:address":"J\u00fcdefelderstr. 47",
    "sg:city":"M\u00fcnster",
    "sg:phone":"+49 251/46371",
    "sg:postcode":"48143",
    "sg:province":"Nordrhein-Westfalen",
    "wof:name":"Karl Krekeler",
    "wof:placetype":"venue"
},
  "geometry": {"coordinates":[7.618473,51.96637],"type":"Point"}
}