{
  "type": "Feature",
  "properties": {
    "iso:country":"DE",
    "sg:address":"Mozartallee 23",
    "sg:city":"Gr\u00f6ditz",
    "sg:phone":"+49 35263/30132",
    "sg:postcode":"01609",
    "sg:province":"Sachsen",
    "wof:name":"Atalntic-discothek",
    "wof:placetype":"venue"
},
  "geometry": {"coordinates":[13.458769,51.410648],"type":"Point"}
}