{
  "type": "Feature",
  "properties": {
    "iso:country":"DE",
    "sg:address":"Dornenkreuzstr. 35",
    "sg:city":"Bonn",
    "sg:phone":"+49 228/464614",
    "sg:postcode":"53227",
    "sg:province":"Nordrhein-Westfalen",
    "wof:name":"E. -p. Gertzen",
    "wof:placetype":"venue"
},
  "geometry": {"coordinates":[7.147432,50.728809],"type":"Point"}
}