{
  "type": "Feature",
  "properties": {
    "iso:country":"DE",
    "sg:address":"Georg-Dietr.-B\u00fccking-Str 20",
    "sg:city":"Alsfeld",
    "sg:phone":"+49 6631/1850",
    "sg:postcode":"36304",
    "sg:province":"Hessen",
    "wof:name":"Alsfelder Kleiderwerke B\u00fccking-dreinaht Gmbh",
    "wof:placetype":"venue"
},
  "geometry": {"coordinates":[9.2640428543,50.7542037964],"type":"Point"}
}