{
  "type": "Feature",
  "properties": {
    "iso:country":"DE",
    "sg:address":"Uferstr. 9",
    "sg:city":"Dillenburg",
    "sg:phone":"+49 2771/24610",
    "sg:postcode":"35683",
    "sg:province":"Hessen",
    "wof:name":"Fleischer & Lorch",
    "wof:placetype":"venue"
},
  "geometry": {"coordinates":[8.291164,50.736897],"type":"Point"}
}