{
  "type": "Feature",
  "properties": {
    "iso:country":"DE",
    "sg:address":"Hauptstr. 117",
    "sg:city":"Tauer",
    "sg:phone":"+49 35601/31106",
    "sg:postcode":"03185",
    "sg:province":"Brandenburg",
    "wof:name":"K. Tschirner Anlageberater",
    "wof:placetype":"venue"
},
  "geometry": {"coordinates":[14.4478979111,51.8944206238],"type":"Point"}
}