{
  "type": "Feature",
  "properties": {
    "iso:country":"DE",
    "sg:address":"Karl-Liebknecht-Str. 9",
    "sg:city":"Regis-Breitingen",
    "sg:phone":"+49 34343/51528",
    "sg:postcode":"04565",
    "sg:province":"Sachsen",
    "wof:name":"Manfred Koch",
    "wof:placetype":"venue"
},
  "geometry": {"coordinates":[12.434293,51.084831],"type":"Point"}
}