{
  "type": "Feature",
  "properties": {
    "iso:country":"DE",
    "sg:address":"Barbarossastr. 8",
    "sg:city":"Freigericht",
    "sg:phone":"+49 6055/5459",
    "sg:postcode":"63579",
    "sg:province":"Hessen",
    "wof:name":"A. Silke Bergmann",
    "wof:placetype":"venue"
},
  "geometry": {"coordinates":[9.130765,50.123665],"type":"Point"}
}