{
  "type": "Feature",
  "properties": {
    "iso:country":"DE",
    "sg:address":"Schleswiger Weg 14",
    "sg:city":"Prettin",
    "sg:phone":"+49 35386/23185",
    "sg:postcode":"06922",
    "sg:province":"Sachsen-Anhalt",
    "wof:name":"G\u00fctec-fritsch Gmbh",
    "wof:placetype":"venue"
},
  "geometry": {"coordinates":[12.936951,51.667152],"type":"Point"}
}