{
  "type": "Feature",
  "properties": {
    "iso:country":"DE",
    "sg:address":"F\u00fcrstenstr. 8",
    "sg:city":"Waldb\u00fcttelbrunn",
    "sg:phone":"+49 931/48736",
    "sg:postcode":"97297",
    "sg:province":"Bayern",
    "wof:name":"K. Spanheimer",
    "wof:placetype":"venue"
},
  "geometry": {"coordinates":[9.8460063934,49.787776947],"type":"Point"}
}