{
  "type": "Feature",
  "properties": {
    "iso:country":"DE",
    "sg:address":"Gro\u00dfe Werlstr. 60",
    "sg:city":"Hamm",
    "sg:phone":"+49 2381/400940",
    "sg:postcode":"59077",
    "sg:province":"Nordrhein-Westfalen",
    "wof:name":"H. Neuhaus",
    "wof:placetype":"venue"
},
  "geometry": {"coordinates":[7.7689628601,51.6369056702],"type":"Point"}
}