{
  "type": "Feature",
  "properties": {
    "iso:country":"DE",
    "sg:address":"Hertfelderstr. 9",
    "sg:city":"Esslingen",
    "sg:phone":"+49 711/3705229",
    "sg:postcode":"73733",
    "sg:province":"Baden-W\u00fcrttemberg",
    "wof:name":"Rosenbauer & Schneider Gmbh",
    "wof:placetype":"venue"
},
  "geometry": {"coordinates":[9.297181,48.760063],"type":"Point"}
}