{
  "type": "Feature",
  "properties": {
    "iso:country":"DE",
    "sg:address":"S\u00fcderloog 15",
    "sg:city":"Spiekeroog",
    "sg:phone":"+49 4976/224",
    "sg:postcode":"26474",
    "sg:province":"Niedersachsen",
    "wof:name":"Fr. Kr\u00f6ger",
    "wof:placetype":"venue"
},
  "geometry": {"coordinates":[7.6969380379,53.7704353333],"type":"Point"}
}