{
  "type": "Feature",
  "properties": {
    "iso:country":"DE",
    "sg:address":"Blomberger Weg 5",
    "sg:city":"Berlin",
    "sg:phone":"+49 30/4140200",
    "sg:postcode":"13437",
    "sg:province":"Berlin",
    "wof:name":"Fenster-technik Kg Theo Bockmayer Gmbh & Co.",
    "wof:placetype":"venue"
},
  "geometry": {"coordinates":[13.327668,52.598892],"type":"Point"}
}