{
  "type": "Feature",
  "properties": {
    "iso:country":"DE",
    "sg:address":"J\u00fclicher Str. 24",
    "sg:city":"Elsdorf",
    "sg:phone":"+49 2274/1019",
    "sg:postcode":"50189",
    "sg:province":"Nordrhein-Westfalen",
    "wof:name":"Hausmann Projektges. Mbh",
    "wof:placetype":"venue"
},
  "geometry": {"coordinates":[6.4980649948,50.9570198059],"type":"Point"}
}