{
  "type": "Feature",
  "properties": {
    "iso:country":"DE",
    "sg:address":"Werdauer Str. 9 b",
    "sg:city":"Greiz",
    "sg:phone":"+49 3661/62860",
    "sg:postcode":"07973",
    "sg:province":"Th\u00fcringen",
    "wof:name":"Caspar Bau Gmbh",
    "wof:placetype":"venue"
},
  "geometry": {"coordinates":[12.229761,50.65461],"type":"Point"}
}