{
  "type": "Feature",
  "properties": {
    "iso:country":"DE",
    "sg:address":"L\u00fcbecker Str. 119",
    "sg:city":"Magdeburg",
    "sg:phone":"+49 391/2515466",
    "sg:postcode":"39124",
    "sg:province":"Sachsen-Anhalt",
    "wof:name":"Fotoatelier Mentzel",
    "wof:placetype":"venue"
},
  "geometry": {"coordinates":[11.6373643875,52.1548461914],"type":"Point"}
}