{
  "type": "Feature",
  "properties": {
    "iso:country":"DE",
    "sg:address":"Neue Linner Str. 97",
    "sg:city":"Krefeld",
    "sg:phone":"+49 2151/25481",
    "sg:postcode":"47798",
    "sg:province":"Nordrhein-Westfalen",
    "wof:name":"La Strada Damenmoden Sch\u00fcrmann-baudy & Ritterbach",
    "wof:placetype":"venue"
},
  "geometry": {"coordinates":[6.564349,51.33202],"type":"Point"}
}