{
  "type": "Feature",
  "properties": {
    "iso:country":"DE",
    "sg:address":"Nu\u00dfallee 17",
    "sg:city":"Bonn",
    "sg:phone":"+49 228/732621",
    "sg:postcode":"53115",
    "sg:province":"Nordrhein-Westfalen",
    "wof:name":"Institut F\u00fcr Theotrische Geod\u00e4sie",
    "wof:placetype":"venue"
},
  "geometry": {"coordinates":[7.0864090919,50.7278556824],"type":"Point"}
}