{
  "type": "Feature",
  "properties": {
    "iso:country":"DE",
    "sg:address":"Waller Weg 22",
    "sg:city":"Braunschweig",
    "sg:phone":"+49 531/2646420",
    "sg:postcode":"38112",
    "sg:province":"Niedersachsen",
    "wof:name":"Market-team Gesellschaft F\u00fcr Marketing",
    "wof:placetype":"venue"
},
  "geometry": {"coordinates":[10.481807,52.309147],"type":"Point"}
}