{
  "type": "Feature",
  "properties": {
    "iso:country":"DE",
    "sg:address":"Grevener Str. 5",
    "sg:city":"Saerbeck",
    "sg:phone":"+49 2574/720",
    "sg:postcode":"48369",
    "sg:province":"Nordrhein-Westfalen",
    "wof:name":"Ute Brinkmann",
    "wof:placetype":"venue"
},
  "geometry": {"coordinates":[7.635033,52.172688],"type":"Point"}
}