{
  "type": "Feature",
  "properties": {
    "iso:country":"DE",
    "sg:address":"Sommerdeich 3",
    "sg:city":"Kleve",
    "sg:phone":"+49 2821/5960",
    "sg:postcode":"47533",
    "sg:province":"Nordrhein-Westfalen",
    "wof:name":"Hemeyer Verpackungen Gmbh",
    "wof:placetype":"venue"
},
  "geometry": {"coordinates":[6.1421771049,51.7959289551],"type":"Point"}
}