{
  "type": "Feature",
  "properties": {
    "iso:country":"DE",
    "sg:address":"Bertholdsplatz 1a",
    "sg:city":"St. Peter",
    "sg:phone":"+49 4976/6091000",
    "sg:postcode":"79271",
    "sg:province":"Baden-W\u00fcrttemberg",
    "wof:name":"Raiffeisenbank S\u00fcdlicher Schwarzw.",
    "wof:placetype":"venue"
},
  "geometry": {"coordinates":[8.031212,48.016262],"type":"Point"}
}