{
  "type": "Feature",
  "properties": {
    "iso:country":"DE",
    "sg:address":"Bahrenfelder Str. 242",
    "sg:city":"Hamburg",
    "sg:phone":"+49 40/391193",
    "sg:postcode":"22765",
    "sg:province":"Hamburg",
    "wof:name":"Wildlife Bild- Und Textagentur Gmbh",
    "wof:placetype":"venue"
},
  "geometry": {"coordinates":[9.9284667969,53.5563240051],"type":"Point"}
}