{
  "type": "Feature",
  "properties": {
    "iso:country":"DE",
    "sg:address":"Benefiziumweg 9",
    "sg:city":"K\u00fchbach",
    "sg:phone":"+49 8257/1361",
    "sg:postcode":"86556",
    "sg:province":"Bayern",
    "wof:name":"Arzberger Elektroinstallation",
    "wof:placetype":"venue"
},
  "geometry": {"coordinates":[11.174394,48.513405],"type":"Point"}
}