{
  "type": "Feature",
  "properties": {
    "iso:country":"DE",
    "sg:address":"Im Fichtental 1",
    "sg:city":"Kuppenheim",
    "sg:phone":"+49 7222/42865",
    "sg:postcode":"76456",
    "sg:province":"Baden-W\u00fcrttemberg",
    "wof:name":"Massivhaus Kolb Gmbh & Co. Kg",
    "wof:placetype":"venue"
},
  "geometry": {"coordinates":[8.24927,48.821674],"type":"Point"}
}