{
  "type": "Feature",
  "properties": {
    "iso:country":"DE",
    "sg:address":"Schleswigstr. 5",
    "sg:city":"Langenhagen",
    "sg:phone":"+49 511/973830",
    "sg:postcode":"30853",
    "sg:province":"Niedersachsen",
    "wof:name":"Wagner Alarm- Und Sicherungssysteme Gmbh",
    "wof:placetype":"venue"
},
  "geometry": {"coordinates":[9.7341098785,52.4583511353],"type":"Point"}
}