{
  "type": "Feature",
  "properties": {
    "iso:country":"DE",
    "sg:address":"Freiheitsm\u00fchle 1",
    "sg:city":"Sundern",
    "sg:phone":"+49 2933/77576",
    "sg:postcode":"59846",
    "sg:province":"Nordrhein-Westfalen",
    "wof:name":"U. H\u00fchne",
    "wof:placetype":"venue"
},
  "geometry": {"coordinates":[8.01669,51.313568],"type":"Point"}
}