{
  "type": "Feature",
  "properties": {
    "iso:country":"DE",
    "sg:address":"F\u00fcrstenwalder Str. 12",
    "sg:city":"Grevenbroich",
    "sg:phone":"+49 2181/24010",
    "sg:postcode":"41515",
    "sg:province":"Nordrhein-Westfalen",
    "wof:name":"A. Panzer",
    "wof:placetype":"venue"
},
  "geometry": {"coordinates":[6.578352,51.098526],"type":"Point"}
}