{
  "type": "Feature",
  "properties": {
    "iso:country":"DE",
    "sg:address":"Rohnbachstr. 63",
    "sg:city":"Enzkl\u00f6sterle",
    "sg:phone":"+49 7085/92380",
    "sg:postcode":"75337",
    "sg:province":"Baden-W\u00fcrttemberg",
    "wof:name":"Hotel Forsthaus",
    "wof:placetype":"venue"
},
  "geometry": {"coordinates":[8.4498224258,48.6552619934],"type":"Point"}
}