{
  "type": "Feature",
  "properties": {
    "iso:country":"DE",
    "sg:address":"Sucystr. 15",
    "sg:city":"Bietigheim-Bissingen",
    "sg:phone":"+49 7142/51910",
    "sg:postcode":"74321",
    "sg:province":"Baden-W\u00fcrttemberg",
    "wof:name":"B\u00e4rbel Preskitt Steuerberaterin",
    "wof:placetype":"venue"
},
  "geometry": {"coordinates":[9.1520013809,48.9407806396],"type":"Point"}
}