{
  "type": "Feature",
  "properties": {
    "iso:country":"DE",
    "sg:address":"Hauptstr. 46",
    "sg:city":"Hohenberg-Krusemark",
    "sg:phone":"+49 39394/81125",
    "sg:postcode":"39596",
    "sg:province":"Sachsen-Anhalt",
    "wof:name":"Restaurant Hoppe Inh. Detlef Hoppe",
    "wof:placetype":"venue"
},
  "geometry": {"coordinates":[11.9471225739,52.7258987427],"type":"Point"}
}