{
  "type": "Feature",
  "properties": {
    "iso:country":"DE",
    "sg:address":"In der Laach 19",
    "sg:city":"Koblenz",
    "sg:phone":"+49 261/42139",
    "sg:postcode":"56072",
    "sg:province":"Rheinland-Pfalz",
    "wof:name":"Willi Heimes",
    "wof:placetype":"venue"
},
  "geometry": {"coordinates":[7.5506510735,50.346950531],"type":"Point"}
}