{
  "type": "Feature",
  "properties": {
    "iso:country":"DE",
    "sg:address":"Stahlbaustr. 9",
    "sg:city":"Castrop-Rauxel",
    "sg:phone":"+49 2305/61020",
    "sg:postcode":"44577",
    "sg:province":"Nordrhein-Westfalen",
    "wof:name":"Thimm Verpackung Gmbh & Co.",
    "wof:placetype":"venue"
},
  "geometry": {"coordinates":[7.3298101425,51.5303688049],"type":"Point"}
}