{
  "type": "Feature",
  "properties": {
    "iso:country":"DE",
    "sg:address":"Ketzberger Str. 44",
    "sg:city":"Solingen",
    "sg:phone":"+49 212/50348",
    "sg:postcode":"42653",
    "sg:province":"Nordrhein-Westfalen",
    "wof:name":"Otto Palm Steuerberater Und",
    "wof:placetype":"venue"
},
  "geometry": {"coordinates":[7.0795249939,51.1932868958],"type":"Point"}
}