{
  "type": "Feature",
  "properties": {
    "iso:country":"DE",
    "sg:address":"M\u00fchlenstr. 41",
    "sg:city":"Bad Breisig",
    "sg:phone":"+49 2633/95796",
    "sg:postcode":"53498",
    "sg:province":"Rheinland-Pfalz",
    "wof:name":"Ingrid Kuhl-fetz",
    "wof:placetype":"venue"
},
  "geometry": {"coordinates":[7.310674,50.494461],"type":"Point"}
}