{
  "type": "Feature",
  "properties": {
    "iso:country":"DE",
    "sg:address":"Gehrenhof",
    "sg:city":"M\u00fcllheim",
    "sg:phone":"+49 7631/4482",
    "sg:postcode":"79379",
    "sg:province":"Baden-W\u00fcrttemberg",
    "wof:name":"Gerhard Emmler",
    "wof:placetype":"venue"
},
  "geometry": {"coordinates":[7.601545,47.830006],"type":"Point"}
}