{
  "type": "Feature",
  "properties": {
    "iso:country":"DE",
    "sg:address":"Casteller Str. 45",
    "sg:city":"Hofheim",
    "sg:phone":"+49 6192/39930",
    "sg:postcode":"65719",
    "sg:province":"Hessen",
    "wof:name":"Pizzeria Da Giovanni",
    "wof:placetype":"venue"
},
  "geometry": {"coordinates":[8.4190835953,50.0611305237],"type":"Point"}
}