{
  "type": "Feature",
  "properties": {
    "iso:country":"DE",
    "sg:address":"Gl\u00e4serswende 6",
    "sg:city":"Siegen",
    "sg:phone":"+49 271/334945",
    "sg:postcode":"57074",
    "sg:province":"Nordrhein-Westfalen",
    "wof:name":"Karl Hofius Inh. Erich Kroke",
    "wof:placetype":"venue"
},
  "geometry": {"coordinates":[8.01482,50.864967],"type":"Point"}
}