{
  "type": "Feature",
  "properties": {
    "iso:country":"DE",
    "sg:address":"Cherbourger Str. 25",
    "sg:city":"Bremerhaven",
    "sg:phone":"+49 471/984620",
    "sg:postcode":"27580",
    "sg:province":"Bremen",
    "wof:name":"Bremer Pharma Gmbh",
    "wof:placetype":"venue"
},
  "geometry": {"coordinates":[8.596408844,53.5847091675],"type":"Point"}
}