{
  "type": "Feature",
  "properties": {
    "iso:country":"DE",
    "sg:address":"Herforder Str. 299a",
    "sg:city":"Bielefeld",
    "sg:phone":"+49 4952/171252",
    "sg:postcode":"33609",
    "sg:province":"Nordrhein-Westfalen",
    "wof:name":"Abbar Automobile Hecham Abbar",
    "wof:placetype":"venue"
},
  "geometry": {"coordinates":[8.5717821121,52.0406112671],"type":"Point"}
}