{
  "type": "Feature",
  "properties": {
    "iso:country":"DE",
    "sg:address":"Postfach 1802",
    "sg:city":"Gronau",
    "sg:postcode":"48579",
    "sg:province":"Niedersachsen",
    "wof:name":"Sander Foto",
    "wof:placetype":"venue"
},
  "geometry": {"coordinates":[7.0179300308,52.209941864],"type":"Point"}
}