{
  "type": "Feature",
  "properties": {
    "iso:country":"DE",
    "sg:address":"Kaiser-Friedrich-Promenade 111",
    "sg:city":"Bad Homburg",
    "sg:phone":"+49 6172/40300",
    "sg:postcode":"61348",
    "sg:province":"Hessen",
    "wof:name":"Sab Real Estate Gmbh & Co. Siebenundsiebzigste Wohnpark",
    "wof:placetype":"venue"
},
  "geometry": {"coordinates":[8.6276283264,50.2241668701],"type":"Point"}
}