{
  "type": "Feature",
  "properties": {
    "iso:country":"DE",
    "sg:address":"Breiter Weg 2",
    "sg:city":"Katlenburg-Lindau",
    "sg:phone":"+49 5556/265",
    "sg:postcode":"37191",
    "sg:province":"Niedersachsen",
    "wof:name":"August Kreitz",
    "wof:placetype":"venue"
},
  "geometry": {"coordinates":[10.098443,51.634605],"type":"Point"}
}