{
  "type": "Feature",
  "properties": {
    "iso:country":"DE",
    "sg:address":"Overstolzenstr. 2 a",
    "sg:city":"K\u00f6ln",
    "sg:phone":"+49 221/3319855",
    "sg:postcode":"50677",
    "sg:province":"Nordrhein-Westfalen",
    "wof:name":"Tizian Produktions- Und Medien-vertriebs-gmbh",
    "wof:placetype":"venue"
},
  "geometry": {"coordinates":[6.9493708611,50.9236717224],"type":"Point"}
}