{
  "type": "Feature",
  "properties": {
    "iso:country":"DE",
    "sg:address":"Wilhelmstr. 46",
    "sg:city":"Bonn",
    "sg:phone":"+49 228/635655",
    "sg:postcode":"53111",
    "sg:province":"Nordrhein-Westfalen",
    "wof:name":"Peter Gerhards Steuerberater",
    "wof:placetype":"venue"
},
  "geometry": {"coordinates":[7.0986089706,50.7391014099],"type":"Point"}
}