{
  "type": "Feature",
  "properties": {
    "iso:country":"DE",
    "sg:address":"Kaiserpfalzstr. 22 B",
    "sg:city":"Bodman-Ludwigshafen",
    "sg:postcode":"78351",
    "sg:province":"Baden-W\u00fcrttemberg",
    "wof:name":"Schuur Gmbh",
    "wof:placetype":"venue"
},
  "geometry": {"coordinates":[9.0310344696,47.8020629883],"type":"Point"}
}