{
  "type": "Feature",
  "properties": {
    "iso:country":"DE",
    "sg:address":"H\u00e4u\u00dflerstr. 19",
    "sg:city":"Hamburg",
    "sg:phone":"+49 40/7397021",
    "sg:postcode":"21031",
    "sg:province":"Hamburg",
    "wof:name":"Hansa-vertrieb Hans-j\u00fcrgen Holthus",
    "wof:placetype":"venue"
},
  "geometry": {"coordinates":[10.212072,53.511581],"type":"Point"}
}