{
  "type": "Feature",
  "properties": {
    "iso:country":"DE",
    "sg:address":"In der Kerb 24",
    "sg:city":"Dillenburg",
    "sg:phone":"+49 2771/41536",
    "sg:postcode":"35683",
    "sg:province":"Hessen",
    "wof:name":"R. Grams",
    "wof:placetype":"venue"
},
  "geometry": {"coordinates":[8.27577,50.7356],"type":"Point"}
}