{
  "type": "Feature",
  "properties": {
    "iso:country":"DE",
    "sg:address":"Rahlstedter Str. 142",
    "sg:city":"Hamburg",
    "sg:phone":"+49 40/6775710",
    "sg:postcode":"22143",
    "sg:province":"Hamburg",
    "wof:name":"Hildburg Wiesner",
    "wof:placetype":"venue"
},
  "geometry": {"coordinates":[10.1592903137,53.603313446],"type":"Point"}
}