{
  "type": "Feature",
  "properties": {
    "iso:country":"DE",
    "sg:address":"Wotanstr. 4",
    "sg:city":"Neubiberg",
    "sg:phone":"+49 89/604550",
    "sg:postcode":"85579",
    "sg:province":"Bayern",
    "wof:name":"Manfred Bauer Ingenieur",
    "wof:placetype":"venue"
},
  "geometry": {"coordinates":[11.6797733307,48.0746154785],"type":"Point"}
}