{
  "type": "Feature",
  "properties": {
    "iso:country":"DE",
    "sg:address":"Scheibenhardter Str. 10",
    "sg:city":"Ettlingen",
    "sg:phone":"+49 7243/90922",
    "sg:postcode":"76275",
    "sg:province":"Baden-W\u00fcrttemberg",
    "wof:name":"Concurrent Computer Gmbh",
    "wof:placetype":"venue"
},
  "geometry": {"coordinates":[8.3897123337,48.9307785034],"type":"Point"}
}