{
  "type": "Feature",
  "properties": {
    "iso:country":"DE",
    "sg:address":"Bauernbr\u00e4ustr. 10",
    "sg:city":"Friedberg",
    "sg:phone":"+49 821",
    "sg:postcode":"86316",
    "sg:province":"Bayern",
    "wof:name":"Fotostudio Prisma",
    "wof:placetype":"venue"
},
  "geometry": {"coordinates":[10.978105,48.354309],"type":"Point"}
}