{
  "type": "Feature",
  "properties": {
    "iso:country":"DE",
    "sg:address":"Robert-Bosch-Str. 4",
    "sg:city":"Hofheim",
    "sg:phone":"+49 6122/70040",
    "sg:postcode":"65719",
    "sg:province":"Hessen",
    "wof:name":"Eigenheim Gesellschaft F\u00fcr Immobilien-verwaltungen",
    "wof:placetype":"venue"
},
  "geometry": {"coordinates":[8.3859453201,50.0643157959],"type":"Point"}
}