{
  "type": "Feature",
  "properties": {
    "iso:country":"DE",
    "sg:address":"Kirchhoffstr. 14",
    "sg:city":"Regensburg",
    "sg:phone":"+49 941/784070",
    "sg:postcode":"93055",
    "sg:province":"Bayern",
    "wof:name":"Di Dach- Und Isolierbau Gmbh",
    "wof:placetype":"venue"
},
  "geometry": {"coordinates":[12.154567,48.991219],"type":"Point"}
}