{
  "type": "Feature",
  "properties": {
    "iso:country":"DE",
    "sg:address":"Josef-B\u00e4der-Weg 2",
    "sg:city":"B\u00fchl",
    "sg:phone":"+49 7223/24488",
    "sg:postcode":"77815",
    "sg:province":"Baden-W\u00fcrttemberg",
    "wof:name":"Markus Geissler Heilpraktiker",
    "wof:placetype":"venue"
},
  "geometry": {"coordinates":[8.1731929779,48.6640434265],"type":"Point"}
}