{
  "type": "Feature",
  "properties": {
    "iso:country":"DE",
    "sg:address":"Am Rodter Fels 9",
    "sg:city":"Taben-Rodt",
    "sg:postcode":"54441",
    "sg:province":"Rheinland-Pfalz",
    "wof:name":"Minna Biss Hebamme",
    "wof:placetype":"venue"
},
  "geometry": {"coordinates":[6.590052,49.551998],"type":"Point"}
}