{
  "type": "Feature",
  "properties": {
    "iso:country":"DE",
    "sg:address":"Oberndorfstr. 11",
    "sg:city":"Herbstein",
    "sg:phone":"+49 6643/236",
    "sg:postcode":"36358",
    "sg:province":"Hessen",
    "wof:name":"A. Und W. Schrimpf Basaltwerke",
    "wof:placetype":"venue"
},
  "geometry": {"coordinates":[9.3476629257,50.5557060242],"type":"Point"}
}