{
  "type": "Feature",
  "properties": {
    "iso:country":"DE",
    "sg:address":"Willi-Eichler-Str. 22",
    "sg:city":"G\u00f6ttingen",
    "sg:phone":"+49 4955/1506800",
    "sg:postcode":"37079",
    "sg:province":"Niedersachsen",
    "wof:name":"Lamprecht Verpackungen Gmbh",
    "wof:placetype":"venue"
},
  "geometry": {"coordinates":[9.8857908249,51.5505981445],"type":"Point"}
}