{
  "type": "Feature",
  "properties": {
    "iso:country":"DE",
    "sg:address":"Am Bildst\u00f6ckle 12",
    "sg:city":"Mochenwangen",
    "sg:phone":"+49 7502/1736",
    "sg:postcode":"88284",
    "sg:province":"Baden-W\u00fcrttemberg",
    "wof:name":"Guaranaimport",
    "wof:placetype":"venue"
},
  "geometry": {"coordinates":[9.6349010468,47.8797607422],"type":"Point"}
}