{
  "type": "Feature",
  "properties": {
    "iso:country":"DE",
    "sg:address":"Durchdeich 167",
    "sg:city":"Hamburg",
    "sg:postcode":"21037",
    "sg:province":"Hamburg",
    "wof:name":"Memo Verwaltungs Gmbh",
    "wof:placetype":"venue"
},
  "geometry": {"coordinates":[10.1383457184,53.4539871216],"type":"Point"}
}