{
  "type": "Feature",
  "properties": {
    "iso:country":"DE",
    "sg:address":"M\u00fcnzmeisterstr. 17",
    "sg:city":"Dresden",
    "sg:phone":"+49 351/4033691",
    "sg:postcode":"01217",
    "sg:province":"Sachsen",
    "wof:name":"Dr. Med. Konrad Weber",
    "wof:placetype":"venue"
},
  "geometry": {"coordinates":[13.741513,51.018841],"type":"Point"}
}