{
  "type": "Feature",
  "properties": {
    "iso:country":"DE",
    "sg:address":"Im Oberdorf 7",
    "sg:city":"K\u00f6ln",
    "sg:phone":"+49 221/838393",
    "sg:postcode":"51105",
    "sg:province":"Nordrhein-Westfalen",
    "wof:name":"D. Und S. Hackenbroch",
    "wof:placetype":"venue"
},
  "geometry": {"coordinates":[6.9898481369,50.9100074768],"type":"Point"}
}