{
  "type": "Feature",
  "properties": {
    "iso:country":"DE",
    "sg:address":"Buchbergstr. 9",
    "sg:city":"Alzenau",
    "sg:postcode":"63755",
    "sg:province":"Bayern",
    "wof:name":"Ragon-tec Gmbh",
    "wof:placetype":"venue"
},
  "geometry": {"coordinates":[9.1117706299,50.1166038513],"type":"Point"}
}