{
  "type": "Feature",
  "properties": {
    "iso:country":"DE",
    "sg:address":"Solmsstr.2-26(City West)",
    "sg:city":"Frankfurt",
    "sg:phone":"+49 4969/79206",
    "sg:postcode":"60486",
    "sg:province":"Hessen",
    "wof:name":"Adca-bank Ag",
    "wof:placetype":"venue"
},
  "geometry": {"coordinates":[8.638681,50.119068],"type":"Point"}
}