{
  "type": "Feature",
  "properties": {
    "iso:country":"DE",
    "sg:address":"Stuttgarter Str. 119",
    "sg:city":"Bietigheim-Bissingen",
    "sg:phone":"+49 7142/940154",
    "sg:postcode":"74321",
    "sg:province":"Baden-W\u00fcrttemberg",
    "wof:name":"Hkc Consult Gmbh",
    "wof:placetype":"venue"
},
  "geometry": {"coordinates":[9.139118,48.947712],"type":"Point"}
}