{
  "type": "Feature",
  "properties": {
    "iso:country":"DE",
    "sg:address":"An den Tongruben 42",
    "sg:city":"Rheinzabern",
    "sg:phone":"+49 7272/71755",
    "sg:postcode":"76764",
    "sg:province":"Rheinland-Pfalz",
    "wof:name":"Kl\u00fcber Bau-consult Gmbh",
    "wof:placetype":"venue"
},
  "geometry": {"coordinates":[8.2758979797,49.1066932678],"type":"Point"}
}