{
  "type": "Feature",
  "properties": {
    "iso:country":"DE",
    "sg:address":"Oberhofer Str. 13",
    "sg:city":"Steinbach-Hallenberg",
    "sg:phone":"+49 36847/40883",
    "sg:postcode":"98587",
    "sg:province":"Th\u00fcringen",
    "wof:name":"Heval-grill",
    "wof:placetype":"venue"
},
  "geometry": {"coordinates":[10.5711946487,50.7100372314],"type":"Point"}
}