{
  "type": "Feature",
  "properties": {
    "iso:country":"DE",
    "sg:address":"Parkallee 24",
    "sg:city":"Stahnsdorf",
    "sg:phone":"+49 3329/63254",
    "sg:postcode":"14532",
    "sg:province":"Brandenburg",
    "wof:name":"Michael Fritzsch Gastst\u00e4ttenservice",
    "wof:placetype":"venue"
},
  "geometry": {"coordinates":[13.206859,52.387497],"type":"Point"}
}