{
  "type": "Feature",
  "properties": {
    "iso:country":"DE",
    "sg:address":"Hauptstr. 1",
    "sg:city":"Weesby",
    "sg:phone":"+49 4605/1285",
    "sg:postcode":"24994",
    "sg:province":"Schleswig-Holstein",
    "wof:name":"Carl Peter Sporn",
    "wof:placetype":"venue"
},
  "geometry": {"coordinates":[9.194385,54.822762],"type":"Point"}
}