{
  "type": "Feature",
  "properties": {
    "iso:country":"DE",
    "sg:address":"B\u00e4ckerstr. 12",
    "sg:city":"Brandenburg",
    "sg:phone":"+49 3381/522884",
    "sg:postcode":"14770",
    "sg:province":"Brandenburg",
    "wof:name":"Fritz Rettig",
    "wof:placetype":"venue"
},
  "geometry": {"coordinates":[12.555076,52.413811],"type":"Point"}
}