{
  "type": "Feature",
  "properties": {
    "iso:country":"DE",
    "sg:address":"Bahnhofstr. 69",
    "sg:city":"Biesenthal",
    "sg:postcode":"16359",
    "sg:province":"Brandenburg",
    "wof:name":"El.-kom.-da. Gmbh",
    "wof:placetype":"venue"
},
  "geometry": {"coordinates":[13.668696,52.756531],"type":"Point"}
}