{
  "type": "Feature",
  "properties": {
    "iso:country":"DE",
    "sg:address":"Joseph-Haas-Str. 24",
    "sg:city":"Krumbach",
    "sg:phone":"+49 8282/5773",
    "sg:postcode":"86381",
    "sg:province":"Bayern",
    "wof:name":"Werner Baumann Steuerberater",
    "wof:placetype":"venue"
},
  "geometry": {"coordinates":[10.3767986298,48.2397575378],"type":"Point"}
}