{
  "type": "Feature",
  "properties": {
    "iso:country":"DE",
    "sg:address":"Sch\u00fctzenstr 6",
    "sg:city":"Werl",
    "sg:phone":"+49 2922/6737",
    "sg:postcode":"59457",
    "sg:province":"Nordrhein-Westfalen",
    "wof:name":"Gebr. Stockmann Gmbh & Co Orgelbau Kg",
    "wof:placetype":"venue"
},
  "geometry": {"coordinates":[7.9174051285,51.5556945801],"type":"Point"}
}