{
  "type": "Feature",
  "properties": {
    "iso:country":"DE",
    "sg:address":"K\u00f6nig-Wilhelm-Str. 18",
    "sg:city":"Ilsfeld",
    "sg:phone":"+49 7062/975287",
    "sg:postcode":"74360",
    "sg:province":"Baden-W\u00fcrttemberg",
    "wof:name":"R. Sandner",
    "wof:placetype":"venue"
},
  "geometry": {"coordinates":[9.2489595413,49.0558319092],"type":"Point"}
}