{
  "type": "Feature",
  "properties": {
    "iso:country":"DE",
    "sg:address":"Teichstr. 40",
    "sg:city":"Gevelsberg",
    "sg:phone":"+49 2332/921450",
    "sg:postcode":"58285",
    "sg:province":"Nordrhein-Westfalen",
    "wof:name":"Iva Johann Gmbh",
    "wof:placetype":"venue"
},
  "geometry": {"coordinates":[7.331376,51.325134],"type":"Point"}
}