{
  "type": "Feature",
  "properties": {
    "iso:country":"DE",
    "sg:address":"August-Bebel-Str. 55",
    "sg:city":"Bielefeld",
    "sg:phone":"+49 521/121516",
    "sg:postcode":"33602",
    "sg:province":"Nordrhein-Westfalen",
    "wof:name":"Jugendforum",
    "wof:placetype":"venue"
},
  "geometry": {"coordinates":[8.539984,52.027954],"type":"Point"}
}