{
  "type": "Feature",
  "properties": {
    "iso:country":"DE",
    "sg:address":"Theodor-Reh-Str. 2",
    "sg:city":"Darmstadt",
    "sg:phone":"+49 6151/712553",
    "sg:postcode":"64289",
    "sg:province":"Hessen",
    "wof:name":"B. Just Hausbau Gmbh",
    "wof:placetype":"venue"
},
  "geometry": {"coordinates":[8.683785,49.901356],"type":"Point"}
}