{
  "type": "Feature",
  "properties": {
    "iso:country":"DE",
    "sg:address":"Lindenstr. 10",
    "sg:city":"Scheer",
    "sg:phone":"+49 7572/76240",
    "sg:postcode":"72516",
    "sg:province":"Baden-W\u00fcrttemberg",
    "wof:name":"Sch\u00f6nweiler Gmbh",
    "wof:placetype":"venue"
},
  "geometry": {"coordinates":[9.327951,48.093018],"type":"Point"}
}