{
  "type": "Feature",
  "properties": {
    "iso:country":"DE",
    "sg:address":"Untere K\u00f6nigsstr. 85",
    "sg:city":"Kassel",
    "sg:phone":"+49 561/16379",
    "sg:postcode":"34117",
    "sg:province":"Hessen",
    "wof:name":"Nightshift",
    "wof:placetype":"venue"
},
  "geometry": {"coordinates":[9.5003986359,51.3187522888],"type":"Point"}
}