{
  "type": "Feature",
  "properties": {
    "iso:country":"DE",
    "sg:address":"Am Mantelsgraben 20",
    "sg:city":"H\u00f6pfingen",
    "sg:phone":"+49 6283/22050",
    "sg:postcode":"74746",
    "sg:province":"Baden-W\u00fcrttemberg",
    "wof:name":"Klr M\u00f6belfronten Gmbh",
    "wof:placetype":"venue"
},
  "geometry": {"coordinates":[9.4266881943,49.5961341858],"type":"Point"}
}