{
  "type": "Feature",
  "properties": {
    "iso:country":"DE",
    "sg:address":"Otto-Hahn-Str. 4",
    "sg:city":"Riemerling",
    "sg:postcode":"85521",
    "sg:province":"Bayern",
    "wof:name":"Edv Und Elektronik Baretzky Gmbh",
    "wof:placetype":"venue"
},
  "geometry": {"coordinates":[11.671254,48.054108],"type":"Point"}
}