{
  "type": "Feature",
  "properties": {
    "iso:country":"DE",
    "sg:address":"Wilhelm-Franke-Str. 8",
    "sg:city":"Dresden",
    "sg:phone":"+49 351/4713841",
    "sg:postcode":"01219",
    "sg:province":"Sachsen",
    "wof:name":"Claudia Mittag Heilpraktikerin",
    "wof:placetype":"venue"
},
  "geometry": {"coordinates":[13.7677583694,51.0191650391],"type":"Point"}
}