{
  "type": "Feature",
  "properties": {
    "iso:country":"DE",
    "sg:address":"Lindenstr. 7a",
    "sg:city":"Illesheim",
    "sg:phone":"+49 9841/8881",
    "sg:postcode":"91471",
    "sg:province":"Bayern",
    "wof:name":"Gebhardt Massiv Blockhaus",
    "wof:placetype":"venue"
},
  "geometry": {"coordinates":[10.3775577545,49.4803848267],"type":"Point"}
}