{
  "type": "Feature",
  "properties": {
    "iso:country":"DE",
    "sg:address":"Kappel 8",
    "sg:city":"Creu\u00dfen",
    "sg:phone":"+49 9270/326",
    "sg:postcode":"95473",
    "sg:province":"Bayern",
    "wof:name":"Alfred Dietel",
    "wof:placetype":"venue"
},
  "geometry": {"coordinates":[11.6227817535,49.8407058716],"type":"Point"}
}