{
  "type": "Feature",
  "properties": {
    "iso:country":"DE",
    "sg:address":"Martinistr. 34",
    "sg:city":"Bremen",
    "sg:phone":"+49 421/614045",
    "sg:postcode":"28195",
    "sg:province":"Bremen",
    "wof:name":"Swg Grundst\u00fccks- Verwaltungs-gmbh",
    "wof:placetype":"venue"
},
  "geometry": {"coordinates":[8.8038415909,53.0764198303],"type":"Point"}
}