{
  "type": "Feature",
  "properties": {
    "iso:country":"DE",
    "sg:address":"Gr\u00e4frather Str. 124",
    "sg:city":"Wuppertal",
    "sg:phone":"+49 202/2731146",
    "sg:postcode":"42329",
    "sg:province":"Nordrhein-Westfalen",
    "wof:name":"Jos Rausch",
    "wof:placetype":"venue"
},
  "geometry": {"coordinates":[7.07154,51.223091],"type":"Point"}
}