{
  "type": "Feature",
  "properties": {
    "iso:country":"DE",
    "sg:address":"Seether Str. 3",
    "sg:city":"Seeth-Ekholt",
    "sg:phone":"+49 4120/353",
    "sg:postcode":"25337",
    "sg:province":"Schleswig-Holstein",
    "wof:name":"Herbert Thies",
    "wof:placetype":"venue"
},
  "geometry": {"coordinates":[9.73061,53.731415],"type":"Point"}
}