{
  "type": "Feature",
  "properties": {
    "iso:country":"DE",
    "sg:address":"Am Steierk\u00f6ppel 9",
    "sg:city":"Waldeck",
    "sg:phone":"+49 5634/6411",
    "sg:postcode":"34513",
    "sg:province":"Hessen",
    "wof:name":"Werner Kn\u00f6fel",
    "wof:placetype":"venue"
},
  "geometry": {"coordinates":[8.982531,51.278118],"type":"Point"}
}