{
  "type": "Feature",
  "properties": {
    "iso:country":"DE",
    "sg:address":"Linzer Str. 9",
    "sg:city":"Ro\u00dfbach",
    "sg:phone":"+49 2638/6076",
    "sg:postcode":"53547",
    "sg:province":"Rheinland-Pfalz",
    "wof:name":"Rudolf Speich",
    "wof:placetype":"venue"
},
  "geometry": {"coordinates":[7.3878040314,50.5663642883],"type":"Point"}
}