{
  "type": "Feature",
  "properties": {
    "iso:country":"DE",
    "sg:address":"Wintersteinstr. 2",
    "sg:city":"Oberursel",
    "sg:postcode":"61440",
    "sg:province":"Hessen",
    "wof:name":"Pronet Netzwerkl\u00f6sungen F\u00fcr Professionelle Anwendungen",
    "wof:placetype":"venue"
},
  "geometry": {"coordinates":[8.5865926743,50.204120636],"type":"Point"}
}