{
  "type": "Feature",
  "properties": {
    "iso:country":"DE",
    "sg:address":"Neufels",
    "sg:city":"Neuenstein",
    "sg:phone":"+49 7942/523",
    "sg:postcode":"74632",
    "sg:province":"Baden-W\u00fcrttemberg",
    "wof:name":"Gastst\u00e4tte W. Schwenzer",
    "wof:placetype":"venue"
},
  "geometry": {"coordinates":[9.6328144073,49.251209259],"type":"Point"}
}