{
  "type": "Feature",
  "properties": {
    "iso:country":"DE",
    "sg:address":"Midlich 68",
    "sg:city":"Rosendahl",
    "sg:phone":"+49 2547/884",
    "sg:postcode":"48720",
    "sg:province":"Nordrhein-Westfalen",
    "wof:name":"Hubert Scharlau Verwaltungs Gmbh",
    "wof:placetype":"venue"
},
  "geometry": {"coordinates":[7.1956119537,52.0010414124],"type":"Point"}
}