{
  "type": "Feature",
  "properties": {
    "iso:country":"DE",
    "sg:address":"Kuhm\u00fchle 12",
    "sg:city":"Hamburg",
    "sg:phone":"+49 40/2297341",
    "sg:postcode":"22087",
    "sg:province":"Hamburg",
    "wof:name":"Holger Conrady",
    "wof:placetype":"venue"
},
  "geometry": {"coordinates":[10.0242910385,53.5646591187],"type":"Point"}
}