{
  "type": "Feature",
  "properties": {
    "iso:country":"DE",
    "sg:address":"Eschenweg 17",
    "sg:city":"Miesbach",
    "sg:phone":"+49 8025/4241",
    "sg:postcode":"83714",
    "sg:province":"Bayern",
    "wof:name":"Josef W. Keller-k\u00fchne Kunstmaler",
    "wof:placetype":"venue"
},
  "geometry": {"coordinates":[11.843857,47.786057],"type":"Point"}
}