{
  "type": "Feature",
  "properties": {
    "iso:country":"DE",
    "sg:address":"Richard-Wagner-Str. 41",
    "sg:city":"Freiburg",
    "sg:phone":"+49 761/57261",
    "sg:postcode":"79104",
    "sg:province":"Baden-W\u00fcrttemberg",
    "wof:name":"Bernard St\u00f6ffler Masseur",
    "wof:placetype":"venue"
},
  "geometry": {"coordinates":[7.861115,48.012733],"type":"Point"}
}