{
  "type": "Feature",
  "properties": {
    "iso:country":"DE",
    "sg:address":"Simbacher Str. 13",
    "sg:city":"Pocking",
    "sg:phone":"+49 8531/4535",
    "sg:postcode":"94060",
    "sg:province":"Bayern",
    "wof:name":"Pension Johann Riermeier",
    "wof:placetype":"venue"
},
  "geometry": {"coordinates":[13.3109092712,48.4004936218],"type":"Point"}
}