{
  "type": "Feature",
  "properties": {
    "iso:country":"DE",
    "sg:address":"Minslebener Str. 1 A",
    "sg:city":"Wernigerode",
    "sg:phone":"+49 3943/21489",
    "sg:postcode":"38855",
    "sg:province":"Sachsen-Anhalt",
    "wof:name":"Walter M\u00e4nz",
    "wof:placetype":"venue"
},
  "geometry": {"coordinates":[10.7924938202,51.8390197754],"type":"Point"}
}