{
  "type": "Feature",
  "properties": {
    "iso:country":"DE",
    "sg:address":"Gartenstr 38",
    "sg:city":"Tittling",
    "sg:phone":"+49 8504/4126",
    "sg:postcode":"94104",
    "sg:province":"Bayern",
    "wof:name":"Bl Produktions Gmbh",
    "wof:placetype":"venue"
},
  "geometry": {"coordinates":[13.37926,48.72303],"type":"Point"}
}