{
  "type": "Feature",
  "properties": {
    "iso:country":"DE",
    "sg:address":"St\u00e4ffeleswiesen 28-30",
    "sg:city":"Heidenheim",
    "sg:phone":"+49 7321/51018",
    "sg:postcode":"89522",
    "sg:province":"Baden-W\u00fcrttemberg",
    "wof:name":"Werz Gmbh",
    "wof:placetype":"venue"
},
  "geometry": {"coordinates":[10.15689,48.653278],"type":"Point"}
}