{
  "type": "Feature",
  "properties": {
    "iso:country":"DE",
    "sg:address":"Ditzinger Str. 45",
    "sg:city":"Gerlingen",
    "sg:postcode":"70839",
    "sg:province":"Baden-W\u00fcrttemberg",
    "wof:name":"Iwot-innovative Werkstoff- Und Oberfl\u00e4chentechnik Gmbh",
    "wof:placetype":"venue"
},
  "geometry": {"coordinates":[9.0649175644,48.8045806885],"type":"Point"}
}