{
  "type": "Feature",
  "properties": {
    "iso:country":"DE",
    "sg:address":"Wenger H\u00f6fe 3",
    "sg:city":"Dorsten",
    "sg:phone":"+49 2362/71278",
    "sg:postcode":"46284",
    "sg:province":"Nordrhein-Westfalen",
    "wof:name":"Stolte Fliesen",
    "wof:placetype":"venue"
},
  "geometry": {"coordinates":[6.9998607635,51.6755409241],"type":"Point"}
}