{
  "type": "Feature",
  "properties": {
    "iso:country":"DE",
    "sg:address":"Georgstr. 59",
    "sg:city":"Bremerhaven",
    "sg:phone":"+49 471/38042",
    "sg:postcode":"27570",
    "sg:province":"Bremen",
    "wof:name":"Bruns Reisen Gmbh",
    "wof:placetype":"venue"
},
  "geometry": {"coordinates":[8.589802742,53.5311508179],"type":"Point"}
}