{
  "type": "Feature",
  "properties": {
    "iso:country":"DE",
    "sg:address":"Karolinenstr. 21",
    "sg:city":"Augsburg",
    "sg:postcode":"86150",
    "sg:province":"Bayern",
    "wof:name":"Dis Dt. Industrie Service Gmbh",
    "wof:placetype":"venue"
},
  "geometry": {"coordinates":[10.89769,48.370388],"type":"Point"}
}