{
  "type": "Feature",
  "properties": {
    "iso:country":"DE",
    "sg:address":"Bismarckstr. 21",
    "sg:city":"M\u00fcnchen",
    "sg:phone":"+49 89/347518",
    "sg:postcode":"80803",
    "sg:province":"Bayern",
    "wof:name":"Malerbetrieb Rickert",
    "wof:placetype":"venue"
},
  "geometry": {"coordinates":[11.58286,48.164635],"type":"Point"}
}