{
  "type": "Feature",
  "properties": {
    "iso:country":"DE",
    "sg:address":"Husumer Str. 81",
    "sg:city":"Bielefeld",
    "sg:phone":"+49 521/76882",
    "sg:postcode":"33729",
    "sg:province":"Nordrhein-Westfalen",
    "wof:name":"J\u00fcrgen Sturm",
    "wof:placetype":"venue"
},
  "geometry": {"coordinates":[8.595519,52.078503],"type":"Point"}
}