{
  "type": "Feature",
  "properties": {
    "iso:country":"DE",
    "sg:address":"Carmerstr. 29",
    "sg:city":"Essen",
    "sg:phone":"+49 201/780444",
    "sg:postcode":"45147",
    "sg:province":"Nordrhein-Westfalen",
    "wof:name":"Die Deele",
    "wof:placetype":"venue"
},
  "geometry": {"coordinates":[6.9920191765,51.443069458],"type":"Point"}
}