{
  "type": "Feature",
  "properties": {
    "iso:country":"DE",
    "sg:address":"Meldorfer Str. 43",
    "sg:city":"Hemmingstedt",
    "sg:phone":"+49 481/63028",
    "sg:postcode":"25770",
    "sg:province":"Schleswig-Holstein",
    "wof:name":"Zerssen Mineral\u00f6lhandel Gmbh",
    "wof:placetype":"venue"
},
  "geometry": {"coordinates":[9.0810613632,54.1574020386],"type":"Point"}
}