{
  "type": "Feature",
  "properties": {
    "iso:country":"DE",
    "sg:address":"Hauptstr. 2",
    "sg:city":"Seelbach",
    "sg:phone":"+49 4978/232084",
    "sg:postcode":"77960",
    "sg:province":"Baden-W\u00fcrttemberg",
    "wof:name":"Sparkasse Lahr-ettenheim",
    "wof:placetype":"venue"
},
  "geometry": {"coordinates":[7.941177,48.310051],"type":"Point"}
}