{
  "type": "Feature",
  "properties": {
    "iso:country":"DE",
    "sg:address":"Gottlob-Schneider-Str. 33",
    "sg:city":"Ettlingen",
    "sg:postcode":"76275",
    "sg:province":"Baden-W\u00fcrttemberg",
    "wof:name":"Hoai-rb 1996 Excel-l\u00f6sung",
    "wof:placetype":"venue"
},
  "geometry": {"coordinates":[8.402452,48.942471],"type":"Point"}
}