{
  "type": "Feature",
  "properties": {
    "iso:country":"DE",
    "sg:address":"Bromberger Str. 49",
    "sg:city":"Oberhausen",
    "sg:phone":"+49 208/607373",
    "sg:postcode":"46145",
    "sg:province":"Nordrhein-Westfalen",
    "wof:name":"W. Gmeiner Steuerberater",
    "wof:placetype":"venue"
},
  "geometry": {"coordinates":[6.8581461906,51.535446167],"type":"Point"}
}