{
  "type": "Feature",
  "properties": {
    "iso:country":"DE",
    "sg:address":"Am R\u00f6merlager",
    "sg:city":"Hofheim",
    "sg:phone":"+49 6192/26749",
    "sg:postcode":"65719",
    "sg:province":"Hessen",
    "wof:name":"Objekt Data Unternehmensberatung",
    "wof:placetype":"venue"
},
  "geometry": {"coordinates":[8.4456195831,50.0831604004],"type":"Point"}
}