{
  "type": "Feature",
  "properties": {
    "iso:country":"DE",
    "sg:address":"Sulzburger Str. 68",
    "sg:city":"Freiburg",
    "sg:phone":"+49 761/499528",
    "sg:postcode":"79114",
    "sg:province":"Baden-W\u00fcrttemberg",
    "wof:name":"Haug",
    "wof:placetype":"venue"
},
  "geometry": {"coordinates":[7.8096151352,47.9963226318],"type":"Point"}
}