{
  "type": "Feature",
  "properties": {
    "iso:country":"DE",
    "sg:address":"N\u00f6rdliche Mauerstr. 26",
    "sg:city":"Schwabach",
    "sg:phone":"+49 9122/2116",
    "sg:postcode":"91126",
    "sg:province":"Bayern",
    "wof:name":"Hans Emil Lipps",
    "wof:placetype":"venue"
},
  "geometry": {"coordinates":[11.01739,49.331745],"type":"Point"}
}