{
  "type": "Feature",
  "properties": {
    "iso:country":"DE",
    "sg:address":"Richardstr. 38",
    "sg:city":"Berlin",
    "sg:phone":"+49 30/68809047",
    "sg:postcode":"12043",
    "sg:province":"Berlin",
    "wof:name":"J\u00fcrgen Lorenz Elektromeister Gmbh",
    "wof:placetype":"venue"
},
  "geometry": {"coordinates":[13.444497,52.474792],"type":"Point"}
}