{
  "type": "Feature",
  "properties": {
    "iso:country":"DE",
    "sg:address":"Bahnhofplatz 8",
    "sg:city":"Horb",
    "sg:phone":"+49 7451/55540",
    "sg:postcode":"72160",
    "sg:province":"Baden-W\u00fcrttemberg",
    "wof:name":"Karl Kaufmann Gmbh",
    "wof:placetype":"venue"
},
  "geometry": {"coordinates":[8.63259,48.471352],"type":"Point"}
}