{
  "type": "Feature",
  "properties": {
    "iso:country":"DE",
    "sg:address":"Fichtenweg 12",
    "sg:city":"Mittelneufnach",
    "sg:phone":"+49 8262/611",
    "sg:postcode":"86868",
    "sg:province":"Bayern",
    "wof:name":"L. Fuchs",
    "wof:placetype":"venue"
},
  "geometry": {"coordinates":[10.595152,48.17992],"type":"Point"}
}