{
  "type": "Feature",
  "properties": {
    "iso:country":"DE",
    "sg:address":"Wielandstr. 8",
    "sg:city":"Sinsheim",
    "sg:phone":"+49 7261/913013",
    "sg:postcode":"74889",
    "sg:province":"Baden-W\u00fcrttemberg",
    "wof:name":"Hewe Immobilien Gmbh",
    "wof:placetype":"venue"
},
  "geometry": {"coordinates":[8.875585556,49.2599639893],"type":"Point"}
}