{
  "type": "Feature",
  "properties": {
    "iso:country":"DE",
    "sg:address":"Klingenbrunnstr. 47",
    "sg:city":"Schweinfurt",
    "sg:phone":"+49 9721/21459",
    "sg:postcode":"97422",
    "sg:province":"Bayern",
    "wof:name":"Ingeborg Meis",
    "wof:placetype":"venue"
},
  "geometry": {"coordinates":[10.2362194061,50.0535430908],"type":"Point"}
}