{
  "type": "Feature",
  "properties": {
    "iso:country":"DE",
    "sg:address":"Endelner Feld 9",
    "sg:city":"Dorsten",
    "sg:phone":"+49 2369/20850",
    "sg:postcode":"46286",
    "sg:province":"Nordrhein-Westfalen",
    "wof:name":"Tic Medizintechnik Gmbh & Co Kg",
    "wof:placetype":"venue"
},
  "geometry": {"coordinates":[6.962992,51.753403],"type":"Point"}
}