{
  "type": "Feature",
  "properties": {
    "iso:country":"DE",
    "sg:address":"Bahnhofstr. 32",
    "sg:city":"Dornum",
    "sg:phone":"+49 4933/622",
    "sg:postcode":"26553",
    "sg:province":"Niedersachsen",
    "wof:name":"Von Vett Gmbh",
    "wof:placetype":"venue"
},
  "geometry": {"coordinates":[7.4381728172,53.6434440613],"type":"Point"}
}