{
  "type": "Feature",
  "properties": {
    "iso:country":"DE",
    "sg:address":"Ernst-Th\u00e4lmann-Str. 20",
    "sg:city":"Brieskow-Finkenheerd",
    "sg:phone":"+49 33609/35655",
    "sg:postcode":"15295",
    "sg:province":"Brandenburg",
    "wof:name":"H. Zippan Anlageberater",
    "wof:placetype":"venue"
},
  "geometry": {"coordinates":[14.5757236481,52.2502861023],"type":"Point"}
}