{
  "type": "Feature",
  "properties": {
    "iso:country":"DE",
    "sg:address":"M\u00fcnsterstr. 15",
    "sg:city":"Rheine",
    "sg:phone":"+49 5971/51035",
    "sg:postcode":"48431",
    "sg:province":"Nordrhein-Westfalen",
    "wof:name":"Sport Und Chic",
    "wof:placetype":"venue"
},
  "geometry": {"coordinates":[7.439801,52.278397],"type":"Point"}
}