{
  "type": "Feature",
  "properties": {
    "iso:country":"DE",
    "sg:address":"Hochgernstr. 47",
    "sg:city":"Rosenheim",
    "sg:phone":"+49 8031/44457",
    "sg:postcode":"83026",
    "sg:province":"Bayern",
    "wof:name":"Elfriede Schwarzfischer Antiques & Specials",
    "wof:placetype":"venue"
},
  "geometry": {"coordinates":[12.1024,47.848492],"type":"Point"}
}