{
  "type": "Feature",
  "properties": {
    "iso:country":"DE",
    "sg:address":"Deisenhofener Str. 97",
    "sg:city":"M\u00fcnchen",
    "sg:phone":"+49 89/6911203",
    "sg:postcode":"81539",
    "sg:province":"Bayern",
    "wof:name":"S. Ozdemir Hebamme",
    "wof:placetype":"venue"
},
  "geometry": {"coordinates":[11.59141,48.111118],"type":"Point"}
}