{
  "type": "Feature",
  "properties": {
    "iso:country":"DE",
    "sg:address":"Sibirien 4",
    "sg:city":"Elmshorn",
    "sg:postcode":"25335",
    "sg:province":"Schleswig-Holstein",
    "wof:name":"Aldi Gmbh & Co. Kg",
    "wof:placetype":"venue"
},
  "geometry": {"coordinates":[9.6607542038,53.7733879089],"type":"Point"}
}