{
  "type": "Feature",
  "properties": {
    "iso:country":"DE",
    "sg:address":"Herrengasse 10",
    "sg:city":"Rhodt",
    "sg:phone":"+49 6323/5319",
    "sg:postcode":"76835",
    "sg:province":"Rheinland-Pfalz",
    "wof:name":"Karl J\u00e4ger",
    "wof:placetype":"venue"
},
  "geometry": {"coordinates":[-81.12242126460001,38.9796791077],"type":"Point"}
}