{
  "type": "Feature",
  "properties": {
    "iso:country":"DE",
    "sg:address":"Josef-Schregel-Str. 3a",
    "sg:city":"D\u00fcren",
    "sg:phone":"+49 2421/16404",
    "sg:postcode":"52349",
    "sg:province":"Nordrhein-Westfalen",
    "wof:name":"G. Kaiser",
    "wof:placetype":"venue"
},
  "geometry": {"coordinates":[6.482732,50.805294],"type":"Point"}
}