{
  "type": "Feature",
  "properties": {
    "iso:country":"DE",
    "sg:address":"Kirchstr. 16",
    "sg:city":"Frickingen",
    "sg:phone":"+49 7554/205",
    "sg:postcode":"88699",
    "sg:province":"Baden-W\u00fcrttemberg",
    "wof:name":"Kath. \u00d6ffentliche Bibliothek St. Martin",
    "wof:placetype":"venue"
},
  "geometry": {"coordinates":[9.27269,47.813904],"type":"Point"}
}