{
  "type": "Feature",
  "properties": {
    "iso:country":"DE",
    "sg:address":"Rathausstr. 2",
    "sg:city":"R\u00fcdesheim am Rhein",
    "sg:phone":"+49 6726/9162",
    "sg:postcode":"65385",
    "sg:province":"Hessen",
    "wof:name":"Zahntechnisches Labor Kirstein Gmbh",
    "wof:placetype":"venue"
},
  "geometry": {"coordinates":[7.892943,50.051846],"type":"Point"}
}