{
  "type": "Feature",
  "properties": {
    "iso:country":"DE",
    "sg:address":"Bayreuther Str. 6",
    "sg:city":"Hof",
    "sg:phone":"+49 9281/18108",
    "sg:postcode":"95028",
    "sg:province":"Bayern",
    "wof:name":"Rainbow",
    "wof:placetype":"venue"
},
  "geometry": {"coordinates":[11.9142847061,50.3132209778],"type":"Point"}
}