{
  "type": "Feature",
  "properties": {
    "iso:country":"DE",
    "sg:address":"Vorwerkstr. 7",
    "sg:city":"Grimma",
    "sg:postcode":"04668",
    "sg:province":"Sachsen",
    "wof:name":"Grimaer Computer & Software Gmbh",
    "wof:placetype":"venue"
},
  "geometry": {"coordinates":[12.715227,51.235985],"type":"Point"}
}