{
  "type": "Feature",
  "properties": {
    "iso:country":"DE",
    "sg:address":"Fabersweg 6",
    "sg:city":"Norderstedt",
    "sg:postcode":"22848",
    "sg:province":"Schleswig-Holstein",
    "wof:name":"Kappa Deutschland Gmbh",
    "wof:placetype":"venue"
},
  "geometry": {"coordinates":[9.989367,53.66444],"type":"Point"}
}