{
  "type": "Feature",
  "properties": {
    "iso:country":"DE",
    "sg:address":"Lindlarer Str. 38",
    "sg:city":"Overath",
    "sg:phone":"+49 2204/73168",
    "sg:postcode":"51491",
    "sg:province":"Nordrhein-Westfalen",
    "wof:name":"Jakob Gierlich",
    "wof:placetype":"venue"
},
  "geometry": {"coordinates":[7.2318668365,50.9566307068],"type":"Point"}
}