{
  "type": "Feature",
  "properties": {
    "iso:country":"DE",
    "sg:address":"Hauptstr. 92",
    "sg:city":"Stuttgart",
    "sg:phone":"+49 711/732302",
    "sg:postcode":"70563",
    "sg:province":"Baden-W\u00fcrttemberg",
    "wof:name":"Walter Lehmann",
    "wof:placetype":"venue"
},
  "geometry": {"coordinates":[9.1020746231,48.7302818298],"type":"Point"}
}