{
  "type": "Feature",
  "properties": {
    "iso:country":"DE",
    "sg:address":"Hohe Str. 7",
    "sg:city":"Eisenach",
    "sg:phone":"+49 3691/898196",
    "sg:postcode":"99817",
    "sg:province":"Th\u00fcringen",
    "wof:name":"Icg Industrie Consulting Gmbh",
    "wof:placetype":"venue"
},
  "geometry": {"coordinates":[10.332465,50.983768],"type":"Point"}
}