{
  "type": "Feature",
  "properties": {
    "iso:country":"DE",
    "sg:address":"Herweghstr. 13",
    "sg:city":"Mahlow",
    "sg:postcode":"15831",
    "sg:province":"Brandenburg",
    "wof:name":"Audit Bautr\u00e4ger Und Treuhand Gmbh",
    "wof:placetype":"venue"
},
  "geometry": {"coordinates":[13.41498,52.363708],"type":"Point"}
}