{
  "type": "Feature",
  "properties": {
    "iso:country":"DE",
    "sg:address":"Junkersstr 14",
    "sg:city":"Regensburg",
    "sg:phone":"+49 941/70850",
    "sg:postcode":"93055",
    "sg:province":"Bayern",
    "wof:name":"Landauer Transportges. Doll Kg",
    "wof:placetype":"venue"
},
  "geometry": {"coordinates":[12.1512298584,48.9915962219],"type":"Point"}
}