{
  "type": "Feature",
  "properties": {
    "iso:country":"DE",
    "sg:address":"Matthiasstr. 15",
    "sg:city":"Dinklage",
    "sg:phone":"+49 4443/3919",
    "sg:postcode":"49413",
    "sg:province":"Niedersachsen",
    "wof:name":"Fliesenfachgesch\u00e4ft Bl\u00f6mer Gmbh",
    "wof:placetype":"venue"
},
  "geometry": {"coordinates":[8.1309766769,52.6501235962],"type":"Point"}
}