{
  "type": "Feature",
  "properties": {
    "iso:country":"DE",
    "sg:address":"Sch\u00fctzenstr. 9",
    "sg:city":"Iserlohn",
    "sg:phone":"+49 2371/40199",
    "sg:postcode":"58640",
    "sg:province":"Nordrhein-Westfalen",
    "wof:name":"Hildegard Bongard",
    "wof:placetype":"venue"
},
  "geometry": {"coordinates":[7.7149701118,51.411239624],"type":"Point"}
}