{
  "type": "Feature",
  "properties": {
    "iso:country":"DE",
    "sg:address":"Altenberger Str. 38 POSTFACH 2130",
    "sg:city":"Steinfurt",
    "sg:phone":"+49 4925/524416",
    "sg:postcode":"48550",
    "sg:province":"Nordrhein-Westfalen",
    "wof:name":"Ludwig Dwersteg Jun.gmbh & Co. Kg",
    "wof:placetype":"venue"
},
  "geometry": {"coordinates":[7.33943,52.147701],"type":"Point"}
}