{
  "type": "Feature",
  "properties": {
    "iso:country":"DE",
    "sg:address":"Harlestr.",
    "sg:city":"Wittmund",
    "sg:phone":"+49 4462/5113",
    "sg:postcode":"26409",
    "sg:province":"Niedersachsen",
    "wof:name":"Deutsche Bahn Ag",
    "wof:placetype":"venue"
},
  "geometry": {"coordinates":[7.7680959702,53.5800971985],"type":"Point"}
}