{
  "type": "Feature",
  "properties": {
    "iso:country":"DE",
    "sg:address":"Ludwigstra\u00dfe 18",
    "sg:city":"Bad Kissingen",
    "sg:phone":"+49 971/65643",
    "sg:postcode":"97688",
    "sg:province":"Bayern",
    "wof:name":"Heeg Marketing",
    "wof:placetype":"venue"
},
  "geometry": {"coordinates":[10.077985,50.199295],"type":"Point"}
}