{
  "type": "Feature",
  "properties": {
    "iso:country":"DE",
    "sg:address":"Klosterstr. 15",
    "sg:city":"Offenbach-Hundheim",
    "sg:phone":"+49 6382/7420",
    "sg:postcode":"67749",
    "sg:province":"Rheinland-Pfalz",
    "wof:name":"Evang. Rentamt",
    "wof:placetype":"venue"
},
  "geometry": {"coordinates":[7.5499119759,49.6243782043],"type":"Point"}
}