{
  "type": "Feature",
  "properties": {
    "iso:country":"DE",
    "sg:address":"Kasinostra\u00dfe 19-21",
    "sg:city":"Wuppertal",
    "sg:postcode":"42103",
    "sg:province":"Nordrhein-Westfalen",
    "wof:name":"Wtg Wirtschaftstreuhand Kg",
    "wof:placetype":"venue"
},
  "geometry": {"coordinates":[7.142086,51.256767],"type":"Point"}
}