{
  "type": "Feature",
  "properties": {
    "iso:country":"DE",
    "sg:address":"Boschstr. 18",
    "sg:city":"Wiernsheim",
    "sg:phone":"+49 7044/92210",
    "sg:postcode":"75446",
    "sg:province":"Baden-W\u00fcrttemberg",
    "wof:name":"Scheuermann Gmbh",
    "wof:placetype":"venue"
},
  "geometry": {"coordinates":[8.8430643082,48.8908424377],"type":"Point"}
}