{
  "type": "Feature",
  "properties": {
    "iso:country":"DE",
    "sg:address":"Heidestr. 91",
    "sg:city":"Velbert",
    "sg:phone":"+49 2051/253813",
    "sg:postcode":"42549",
    "sg:province":"Nordrhein-Westfalen",
    "wof:name":"Prei\u00df",
    "wof:placetype":"venue"
},
  "geometry": {"coordinates":[7.040647,51.331364],"type":"Point"}
}