{
  "type": "Feature",
  "properties": {
    "iso:country":"DE",
    "sg:address":"Liebigstr. 38",
    "sg:city":"Hamburg",
    "sg:phone":"+49 40/7313190",
    "sg:postcode":"22113",
    "sg:province":"Schleswig-Holstein",
    "wof:name":"C. Erg\u00fcn Gmbh",
    "wof:placetype":"venue"
},
  "geometry": {"coordinates":[10.087401,53.533894],"type":"Point"}
}