{
  "type": "Feature",
  "properties": {
    "iso:country":"DE",
    "sg:address":"Friedrichstr. 303",
    "sg:city":"Velbert",
    "sg:phone":"+49 2051/23505",
    "sg:postcode":"42551",
    "sg:province":"Nordrhein-Westfalen",
    "wof:name":"Pro Vita Concept",
    "wof:placetype":"venue"
},
  "geometry": {"coordinates":[7.05473423,51.3310813904],"type":"Point"}
}