{
  "type": "Feature",
  "properties": {
    "iso:country":"DE",
    "sg:address":"Winkelstr. 11",
    "sg:city":"Zirndorf",
    "sg:phone":"+49 9127/7623",
    "sg:postcode":"90513",
    "sg:province":"Bayern",
    "wof:name":"Max Bauer",
    "wof:placetype":"venue"
},
  "geometry": {"coordinates":[10.9146118164,49.4277610779],"type":"Point"}
}