{
  "type": "Feature",
  "properties": {
    "iso:country":"DE",
    "sg:address":"Achter de Wisch 7",
    "sg:city":"Schwerin",
    "sg:postcode":"19061",
    "sg:province":"Mecklenburg-Vorpommern",
    "wof:name":"Klaus Heinecke",
    "wof:placetype":"venue"
},
  "geometry": {"coordinates":[11.395935,53.590183],"type":"Point"}
}