{
  "type": "Feature",
  "properties": {
    "iso:country":"DE",
    "sg:address":"Falkenweg 3",
    "sg:city":"Kleve",
    "sg:phone":"+49 2821/30322",
    "sg:postcode":"47533",
    "sg:province":"Nordrhein-Westfalen",
    "wof:name":"J\u00fcrgen Cronauer",
    "wof:placetype":"venue"
},
  "geometry": {"coordinates":[6.1234130859,51.809715271],"type":"Point"}
}