{
  "type": "Feature",
  "properties": {
    "iso:country":"DE",
    "sg:address":"An der Schlo\u00dffabrik 26",
    "sg:city":"H\u00fcckeswagen",
    "sg:phone":"+49 2192/2064",
    "sg:postcode":"42499",
    "sg:province":"Nordrhein-Westfalen",
    "wof:name":"Innova-mgm Gmbh",
    "wof:placetype":"venue"
},
  "geometry": {"coordinates":[7.35103,51.14212],"type":"Point"}
}