{
  "type": "Feature",
  "properties": {
    "iso:country":"DE",
    "sg:address":"Kurt-A.-K\u00f6rber-Chaussee 114",
    "sg:city":"Hamburg",
    "sg:phone":"+49 40/7212028",
    "sg:postcode":"21033",
    "sg:province":"Hamburg",
    "wof:name":"Hotel Heckkaten",
    "wof:placetype":"venue"
},
  "geometry": {"coordinates":[10.1880083084,53.4905738831],"type":"Point"}
}