{
  "type": "Feature",
  "properties": {
    "iso:country":"DE",
    "sg:address":"Bahnhofstr. 5",
    "sg:city":"Emsdetten",
    "sg:postcode":"48282",
    "sg:province":"Nordrhein-Westfalen",
    "wof:name":"Br\u00fcggemann & Prokop Ohg",
    "wof:placetype":"venue"
},
  "geometry": {"coordinates":[7.530687809,52.1754875183],"type":"Point"}
}