{
  "type": "Feature",
  "properties": {
    "iso:country":"DE",
    "sg:address":"Chemnitzer Stra\u00dfe 105",
    "sg:city":"Dresden",
    "sg:phone":"+49 351/4728800",
    "sg:postcode":"01187",
    "sg:province":"Sachsen",
    "wof:name":"Falo Geb\u00e4udeber\u00e4umungsservice Gmbh I.g.",
    "wof:placetype":"venue"
},
  "geometry": {"coordinates":[13.7083930969,51.0302009583],"type":"Point"}
}