{
  "type": "Feature",
  "properties": {
    "iso:country":"DE",
    "sg:address":"Blauenweg 28",
    "sg:city":"St. Georgen",
    "sg:phone":"+49 7724/3091",
    "sg:postcode":"78112",
    "sg:province":"Baden-W\u00fcrttemberg",
    "wof:name":"A. Maier Hitec Kg",
    "wof:placetype":"venue"
},
  "geometry": {"coordinates":[8.3441171646,48.1381492615],"type":"Point"}
}