{
  "type": "Feature",
  "properties": {
    "iso:country":"DE",
    "sg:address":"Stuttgarter Str. 78",
    "sg:city":"Metzingen",
    "sg:phone":"+49 7123/42946",
    "sg:postcode":"72555",
    "sg:province":"Baden-W\u00fcrttemberg",
    "wof:name":"Bohn",
    "wof:placetype":"venue"
},
  "geometry": {"coordinates":[9.2746076584,48.5429840088],"type":"Point"}
}