{
  "type": "Feature",
  "properties": {
    "iso:country":"DE",
    "sg:address":"Georg-Schipper-Str. 56",
    "sg:city":"Wilhelmshaven",
    "sg:phone":"+49 4423/2838",
    "sg:postcode":"26388",
    "sg:province":"Niedersachsen",
    "wof:name":"Dieter Becker",
    "wof:placetype":"venue"
},
  "geometry": {"coordinates":[8.0453500748,53.5583953857],"type":"Point"}
}