{
  "type": "Feature",
  "properties": {
    "iso:country":"DE",
    "sg:address":"Bergisch Gladbacher Str. 576",
    "sg:city":"K\u00f6ln",
    "sg:phone":"+49 221/638233",
    "sg:postcode":"51067",
    "sg:province":"Nordrhein-Westfalen",
    "wof:name":"M. Und G. Albrecht Steuerberater",
    "wof:placetype":"venue"
},
  "geometry": {"coordinates":[7.0459928513,50.9697418213],"type":"Point"}
}