{
  "type": "Feature",
  "properties": {
    "iso:country":"DE",
    "sg:address":"Bunsenstr. 7",
    "sg:city":"G\u00f6ttingen",
    "sg:phone":"+49 551/397632",
    "sg:postcode":"37073",
    "sg:province":"Niedersachsen",
    "wof:name":"Ii Physikalisches Institut",
    "wof:placetype":"venue"
},
  "geometry": {"coordinates":[9.931801796,51.5282554626],"type":"Point"}
}