{
  "type": "Feature",
  "properties": {
    "iso:country":"DE",
    "sg:address":"Pastinakelstr. 8",
    "sg:city":"Malchin",
    "sg:phone":"+49 3994/631018",
    "sg:postcode":"17139",
    "sg:province":"Mecklenburg-Vorpommern",
    "wof:name":"Medicare Gmbh",
    "wof:placetype":"venue"
},
  "geometry": {"coordinates":[12.7632226944,53.7381706238],"type":"Point"}
}