{
  "type": "Feature",
  "properties": {
    "iso:country":"DE",
    "sg:address":"Altst\u00e4dter Markt 3",
    "sg:city":"Rendsburg",
    "sg:phone":"+49 4331/22656",
    "sg:postcode":"24768",
    "sg:province":"Schleswig-Holstein",
    "wof:name":"J\u00e4ger-optik Hans-werner J\u00e4ger",
    "wof:placetype":"venue"
},
  "geometry": {"coordinates":[9.6642398834,54.3045845032],"type":"Point"}
}