{
  "type": "Feature",
  "properties": {
    "iso:country":"DE",
    "sg:address":"Romain-Rolland-Str. 14-24",
    "sg:city":"Berlin",
    "sg:phone":"+49 4956/819915",
    "sg:postcode":"13089",
    "sg:province":"Berlin",
    "wof:name":"Ari-armaturen Albert Richter Gmbh & Co Kg",
    "wof:placetype":"venue"
},
  "geometry": {"coordinates":[9.4269075394,51.0234947205],"type":"Point"}
}