{
  "type": "Feature",
  "properties": {
    "iso:country":"DE",
    "sg:address":"Heinrich-W\u00f6hler-Str. 2",
    "sg:city":"Burgwedel",
    "sg:phone":"+49 5139/5771",
    "sg:postcode":"30938",
    "sg:province":"Niedersachsen",
    "wof:name":"Das Tierparadies",
    "wof:placetype":"venue"
},
  "geometry": {"coordinates":[9.849995,52.491837],"type":"Point"}
}