{
  "type": "Feature",
  "properties": {
    "iso:country":"DE",
    "sg:address":"Lennestra\u00dfe 13a",
    "sg:city":"Potsdam",
    "sg:phone":"+49 331",
    "sg:postcode":"14471",
    "sg:province":"Brandenburg",
    "wof:name":"Alpha-immobilien Gmbh Rdm-maklerb\u00fcro",
    "wof:placetype":"venue"
},
  "geometry": {"coordinates":[13.0367240906,52.3981933594],"type":"Point"}
}