{
  "type": "Feature",
  "properties": {
    "iso:country":"DE",
    "sg:address":"Sonnenberg 29",
    "sg:city":"Isenburg",
    "sg:phone":"+49 2601/1634",
    "sg:postcode":"56271",
    "sg:province":"Rheinland-Pfalz",
    "wof:name":"Eva-maria Hahn Hebamme",
    "wof:placetype":"venue"
},
  "geometry": {"coordinates":[7.598257,50.478428],"type":"Point"}
}