{
  "type": "Feature",
  "properties": {
    "iso:country":"DE",
    "sg:address":"H\u00f6chster Str. 100",
    "sg:city":"Brensbach",
    "sg:phone":"+49 4961/61414",
    "sg:postcode":"64395",
    "sg:province":"Hessen",
    "wof:name":"Oe-ku Oertl Kunststofftechnik Gmbh",
    "wof:placetype":"venue"
},
  "geometry": {"coordinates":[8.885933876,49.7738265991],"type":"Point"}
}