{
  "type": "Feature",
  "properties": {
    "iso:country":"DE",
    "sg:address":"Kapuzinergasse 6",
    "sg:city":"Oberkirch",
    "sg:phone":"+49 7802/2252",
    "sg:postcode":"77704",
    "sg:province":"Baden-W\u00fcrttemberg",
    "wof:name":"M. Gmeiner",
    "wof:placetype":"venue"
},
  "geometry": {"coordinates":[8.077165,48.532578],"type":"Point"}
}