{
  "type": "Feature",
  "properties": {
    "iso:country":"DE",
    "sg:address":"Fleischstr. 11",
    "sg:city":"Bamberg",
    "sg:phone":"+49 951/98300",
    "sg:postcode":"96047",
    "sg:province":"Bayern",
    "wof:name":"Volksf\u00fcrsorge Deutsche Lebensversicherung Ag",
    "wof:placetype":"venue"
},
  "geometry": {"coordinates":[10.8885536194,49.8948020935],"type":"Point"}
}