{
  "type": "Feature",
  "properties": {
    "iso:country":"DE",
    "sg:address":"Staufener Str. 14",
    "sg:city":"Bad Krozingen",
    "sg:phone":"+49 7633/3336",
    "sg:postcode":"79189",
    "sg:province":"Baden-W\u00fcrttemberg",
    "wof:name":"Hettiger M\u00f6belhaus Gmbh",
    "wof:placetype":"venue"
},
  "geometry": {"coordinates":[7.7015938759,47.9189338684],"type":"Point"}
}