{
  "type": "Feature",
  "properties": {
    "iso:country":"DE",
    "sg:address":"Garterlaie 21-25",
    "sg:city":"Wuppertal",
    "sg:phone":"+49 202/741223",
    "sg:postcode":"42327",
    "sg:province":"Nordrhein-Westfalen",
    "wof:name":"Kath. \u00d6ffentliche Bibliothek St. Remigius",
    "wof:placetype":"venue"
},
  "geometry": {"coordinates":[7.097475,51.239136],"type":"Point"}
}