{
  "type": "Feature",
  "properties": {
    "iso:country":"DE",
    "sg:address":"Siemensstr. 7",
    "sg:city":"Diepholz",
    "sg:postcode":"49356",
    "sg:province":"Niedersachsen",
    "wof:name":"Cable-competence Gmbh",
    "wof:placetype":"venue"
},
  "geometry": {"coordinates":[8.346433,52.592609],"type":"Point"}
}