{
  "type": "Feature",
  "properties": {
    "iso:country":"DE",
    "sg:address":"M\u00fchlg\u00e4\u00dfle 12",
    "sg:city":"Horb",
    "sg:phone":"+49 7451/55240",
    "sg:postcode":"72160",
    "sg:province":"Baden-W\u00fcrttemberg",
    "wof:name":"Lbs Landesbausparkasse",
    "wof:placetype":"venue"
},
  "geometry": {"coordinates":[8.691821,48.444183],"type":"Point"}
}