{
  "type": "Feature",
  "properties": {
    "iso:country":"DE",
    "sg:address":"Fl\u00e4sheimer Str. 1",
    "sg:city":"Haltern",
    "sg:phone":"+49 4923/6494910",
    "sg:postcode":"45721",
    "sg:province":"Nordrhein-Westfalen",
    "wof:name":"Jos. Dickerhoff & Co. Bauunternehmung Gmbh",
    "wof:placetype":"venue"
},
  "geometry": {"coordinates":[7.187537,51.727859],"type":"Point"}
}