{
  "type": "Feature",
  "properties": {
    "iso:country":"DE",
    "sg:address":"Paderborner Str. 36",
    "sg:city":"Detmold",
    "sg:phone":"+49 5231/47625",
    "sg:postcode":"32760",
    "sg:province":"Nordrhein-Westfalen",
    "wof:name":"Falken-apotheke",
    "wof:placetype":"venue"
},
  "geometry": {"coordinates":[8.863507,51.919445],"type":"Point"}
}