{
  "type": "Feature",
  "properties": {
    "iso:country":"DE",
    "sg:address":"Goldenstedter Str. 3a",
    "sg:city":"Wildeshausen",
    "sg:phone":"+49 4431/72454",
    "sg:postcode":"27793",
    "sg:province":"Niedersachsen",
    "wof:name":"Schubert\u00b4s Erste Hilfe Am Hund",
    "wof:placetype":"venue"
},
  "geometry": {"coordinates":[8.431099,52.892143],"type":"Point"}
}