{
  "type": "Feature",
  "properties": {
    "iso:country":"DE",
    "sg:address":"Altheimer Str. 2",
    "sg:city":"Rosenberg",
    "sg:phone":"+49 6295/251",
    "sg:postcode":"74749",
    "sg:province":"Baden-W\u00fcrttemberg",
    "wof:name":"Drei Hasen",
    "wof:placetype":"venue"
},
  "geometry": {"coordinates":[9.4537153244,49.488609314],"type":"Point"}
}