{
  "type": "Feature",
  "properties": {
    "iso:country":"DE",
    "sg:address":"Willibald-Groh-Str. 21",
    "sg:city":"St. Ingbert",
    "sg:phone":"+49 6894/36440",
    "sg:postcode":"66386",
    "sg:province":"Saarland",
    "wof:name":"Kurt Broschart Architekt",
    "wof:placetype":"venue"
},
  "geometry": {"coordinates":[7.122156,49.289135],"type":"Point"}
}