{
  "type": "Feature",
  "properties": {
    "iso:country":"DE",
    "sg:address":"Kressenstein 16",
    "sg:city":"Kulmbach",
    "sg:phone":"+49 9221/82280",
    "sg:postcode":"95326",
    "sg:province":"Bayern",
    "wof:name":"Redaktion Frankenpost",
    "wof:placetype":"venue"
},
  "geometry": {"coordinates":[11.4533376694,50.10779953],"type":"Point"}
}