{
  "type": "Feature",
  "properties": {
    "iso:country":"DE",
    "sg:address":"N\u00f6rdlinger Str. 6",
    "sg:city":"Rothenburg",
    "sg:phone":"+49 9861/936555",
    "sg:postcode":"91541",
    "sg:province":"Bayern",
    "wof:name":"Restaurant Hellas",
    "wof:placetype":"venue"
},
  "geometry": {"coordinates":[10.1821527481,49.3700485229],"type":"Point"}
}