{
  "type": "Feature",
  "properties": {
    "iso:country":"DE",
    "sg:address":"Niederberger H\u00f6he 66",
    "sg:city":"Koblenz",
    "sg:phone":"+49 261/66148",
    "sg:postcode":"56077",
    "sg:province":"Rheinland-Pfalz",
    "wof:name":"Josef Diewald",
    "wof:placetype":"venue"
},
  "geometry": {"coordinates":[7.63904,50.3713],"type":"Point"}
}