{
  "type": "Feature",
  "properties": {
    "iso:country":"DE",
    "sg:address":"Breiter Weg 128",
    "sg:city":"Magdeburg",
    "sg:phone":"+49 391/59590",
    "sg:postcode":"39104",
    "sg:province":"Sachsen-Anhalt",
    "wof:name":"Karstadt Warenhaus Ag",
    "wof:placetype":"venue"
},
  "geometry": {"coordinates":[11.636964,52.132538],"type":"Point"}
}