{
  "type": "Feature",
  "properties": {
    "iso:country":"DE",
    "sg:address":"Pyrmonterstr. 42",
    "sg:city":"Hameln",
    "sg:phone":"+49 5151/6099700",
    "sg:postcode":"31855",
    "sg:province":"Niedersachsen",
    "wof:name":"Phpmysearch",
    "wof:placetype":"venue"
},
  "geometry": {"coordinates":[9.262033,52.046825],"type":"Point"}
}