{
  "type": "Feature",
  "properties": {
    "iso:country":"DE",
    "sg:address":"Christian-Klausmann-Str. 6",
    "sg:city":"Pulheim",
    "sg:phone":"+49 2238/2594",
    "sg:postcode":"50259",
    "sg:province":"Nordrhein-Westfalen",
    "wof:name":"Gertrud Th\u00f6nnessen Versicherungsvertreterin",
    "wof:placetype":"venue"
},
  "geometry": {"coordinates":[6.756282,51.018524],"type":"Point"}
}