{
  "type": "Feature",
  "properties": {
    "iso:country":"DE",
    "sg:address":"Schlo\u00dfstr. 44",
    "sg:city":"Koblenz",
    "sg:phone":"+49 261/32393",
    "sg:postcode":"56068",
    "sg:province":"Rheinland-Pfalz",
    "wof:name":"Pelzmodellhaus Bert Schmidt",
    "wof:placetype":"venue"
},
  "geometry": {"coordinates":[7.5930662155,50.3571777344],"type":"Point"}
}