{
  "type": "Feature",
  "properties": {
    "iso:country":"DE",
    "sg:address":"Alter Winkel 6",
    "sg:city":"Wunstorf",
    "sg:phone":"+49 5033/8467",
    "sg:postcode":"31515",
    "sg:province":"Niedersachsen",
    "wof:name":"Schweers Aalr\u00e4ucherei Gmbh",
    "wof:placetype":"venue"
},
  "geometry": {"coordinates":[9.3508939743,52.4542160034],"type":"Point"}
}