{
  "type": "Feature",
  "properties": {
    "iso:country":"DE",
    "sg:address":"Ellerer Str. 15",
    "sg:city":"Cochem",
    "sg:phone":"+49 2671/7571",
    "sg:postcode":"56812",
    "sg:province":"Rheinland-Pfalz",
    "wof:name":"H. Zens Elektroinstallation",
    "wof:placetype":"venue"
},
  "geometry": {"coordinates":[7.175474,50.135071],"type":"Point"}
}