{
  "type": "Feature",
  "properties": {
    "iso:country":"DE",
    "sg:address":"Oberrod",
    "sg:city":"Alsfeld",
    "sg:phone":"+49 6631/3634",
    "sg:postcode":"36304",
    "sg:province":"Hessen",
    "wof:name":"A. Zimmermann",
    "wof:placetype":"venue"
},
  "geometry": {"coordinates":[9.2407751083,50.7120704651],"type":"Point"}
}