{
  "type": "Feature",
  "properties": {
    "iso:country":"DE",
    "sg:address":"Bettenbergstr 11",
    "sg:city":"Dornhan",
    "sg:phone":"+49 7455/335886",
    "sg:postcode":"72175",
    "sg:province":"Baden-W\u00fcrttemberg",
    "wof:name":"Sts Gmbh",
    "wof:placetype":"venue"
},
  "geometry": {"coordinates":[8.523285,48.378139],"type":"Point"}
}