{
  "type": "Feature",
  "properties": {
    "iso:country":"DE",
    "sg:address":"Verl\u00fc\u00dfmoorer Str. 6",
    "sg:city":"Vollersode",
    "sg:phone":"+49 4793/1698",
    "sg:postcode":"27729",
    "sg:province":"Niedersachsen",
    "wof:name":"Verl\u00fc\u00dfmoorer Windkraft Gmbh",
    "wof:placetype":"venue"
},
  "geometry": {"coordinates":[8.898489,53.299881],"type":"Point"}
}