{
  "type": "Feature",
  "properties": {
    "iso:country":"DE",
    "sg:city":"Charlottenberg",
    "sg:phone":"+49 6439/7883",
    "sg:postcode":"56379",
    "sg:province":"Rheinland-Pfalz",
    "wof:name":"A. Beck",
    "wof:placetype":"venue"
},
  "geometry": {"coordinates":[7.879427,50.343185],"type":"Point"}
}