{
  "type": "Feature",
  "properties": {
    "iso:country":"DE",
    "sg:address":"Sp\u00f6rleinstr. 28",
    "sg:city":"Bad Neustadt",
    "sg:phone":"+49 9771/5023",
    "sg:postcode":"97616",
    "sg:province":"Bayern",
    "wof:name":"Josef Wollbach Inh. Anton Friedel",
    "wof:placetype":"venue"
},
  "geometry": {"coordinates":[10.21737957,50.3229141235],"type":"Point"}
}