{
  "type": "Feature",
  "properties": {
    "iso:country":"DE",
    "sg:address":"Wolfsbankring 13",
    "sg:city":"Essen",
    "sg:phone":"+49 201/689500",
    "sg:postcode":"45355",
    "sg:province":"Nordrhein-Westfalen",
    "wof:name":"Das Futterhaus Gmbh",
    "wof:placetype":"venue"
},
  "geometry": {"coordinates":[6.958851,51.471153],"type":"Point"}
}