{
  "type": "Feature",
  "properties": {
    "iso:country":"DE",
    "sg:address":"Beutterstr. 7",
    "sg:city":"Stuttgart",
    "sg:phone":"+49 711/333638",
    "sg:postcode":"70327",
    "sg:province":"Baden-W\u00fcrttemberg",
    "wof:name":"Theodor Kurrle",
    "wof:placetype":"venue"
},
  "geometry": {"coordinates":[9.2721099854,48.783744812],"type":"Point"}
}