{
  "type": "Feature",
  "properties": {
    "iso:country":"DE",
    "sg:address":"St.-Georg-Weg 2",
    "sg:city":"Prackenbach",
    "sg:phone":"+49 9942/8574",
    "sg:postcode":"94267",
    "sg:province":"Bayern",
    "wof:name":"A. Lummer",
    "wof:placetype":"venue"
},
  "geometry": {"coordinates":[12.8247232437,49.0937957764],"type":"Point"}
}