{
  "type": "Feature",
  "properties": {
    "iso:country":"DE",
    "sg:address":"Lange Str. 43",
    "sg:city":"Sulingen",
    "sg:phone":"+49 4271/2327",
    "sg:postcode":"27232",
    "sg:province":"Niedersachsen",
    "wof:name":"Hermann Meyer",
    "wof:placetype":"venue"
},
  "geometry": {"coordinates":[8.804643631,52.6822509766],"type":"Point"}
}