{
  "type": "Feature",
  "properties": {
    "iso:country":"DE",
    "sg:address":"B\u00e4ckerstr. 7",
    "sg:city":"Hameln",
    "sg:phone":"+49 5151/44325",
    "sg:postcode":"31785",
    "sg:province":"Niedersachsen",
    "wof:name":"W. Th\u00f6ner",
    "wof:placetype":"venue"
},
  "geometry": {"coordinates":[9.356565,52.1036],"type":"Point"}
}