{
  "type": "Feature",
  "properties": {
    "iso:country":"DE",
    "sg:address":"Karl-Marx-Str. 24",
    "sg:city":"Hartha",
    "sg:phone":"+49 34328/41905",
    "sg:postcode":"04746",
    "sg:province":"Sachsen",
    "wof:name":"Mario Dietrich",
    "wof:placetype":"venue"
},
  "geometry": {"coordinates":[12.972841,51.098003],"type":"Point"}
}