{
  "type": "Feature",
  "properties": {
    "iso:country":"DE",
    "sg:address":"Ortsstr. 17",
    "sg:city":"Waldshut-Tiengen",
    "sg:phone":"+49 7751/2780",
    "sg:postcode":"79761",
    "sg:province":"Baden-W\u00fcrttemberg",
    "wof:name":"Alpenblick",
    "wof:placetype":"venue"
},
  "geometry": {"coordinates":[8.1710548401,47.6468696594],"type":"Point"}
}