{
  "type": "Feature",
  "properties": {
    "iso:country":"DE",
    "sg:address":"Am Bahnhof 31",
    "sg:city":"Salzgitter",
    "sg:phone":"+49 5341/264217",
    "sg:postcode":"38239",
    "sg:province":"Niedersachsen",
    "wof:name":"Mkd-dachdeckerei Gmbh",
    "wof:placetype":"venue"
},
  "geometry": {"coordinates":[10.49333,52.180561],"type":"Point"}
}