{
  "type": "Feature",
  "properties": {
    "iso:country":"DE",
    "sg:address":"Friedrich-von-F\u00fcrer-Str. 33",
    "sg:city":"R\u00f6thenbach",
    "sg:postcode":"90552",
    "sg:province":"Bayern",
    "wof:name":"Mo-creation Manuela Oberd\u00f6rfer",
    "wof:placetype":"venue"
},
  "geometry": {"coordinates":[11.2957658768,49.475692749],"type":"Point"}
}