{
  "type": "Feature",
  "properties": {
    "iso:country":"DE",
    "sg:address":"Stiftstr. 48",
    "sg:city":"M\u00fchltal",
    "sg:phone":"+49 6151/145166",
    "sg:postcode":"64367",
    "sg:province":"Hessen",
    "wof:name":"Sturm-chemie",
    "wof:placetype":"venue"
},
  "geometry": {"coordinates":[8.699634,49.827698],"type":"Point"}
}