{
  "type": "Feature",
  "properties": {
    "iso:country":"DE",
    "sg:address":"Bahnhofstr. 68",
    "sg:city":"Sulz",
    "sg:phone":"+49 7454/2008",
    "sg:postcode":"72172",
    "sg:province":"Baden-W\u00fcrttemberg",
    "wof:name":"Industrie-dienstleistung Entrostungen",
    "wof:placetype":"venue"
},
  "geometry": {"coordinates":[8.641748,48.369442],"type":"Point"}
}