{
  "type": "Feature",
  "properties": {
    "iso:country":"DE",
    "sg:address":"Eisenbernreut 40",
    "sg:city":"Perlesreut",
    "sg:phone":"+49 8555/324",
    "sg:postcode":"94157",
    "sg:province":"Bayern",
    "wof:name":"Max Putz",
    "wof:placetype":"venue"
},
  "geometry": {"coordinates":[13.453153,48.760292],"type":"Point"}
}