{
  "type": "Feature",
  "properties": {
    "iso:country":"DE",
    "sg:address":"Domplatz 40",
    "sg:city":"M\u00fcnster",
    "sg:phone":"+49 251/43146",
    "sg:postcode":"48143",
    "sg:province":"Nordrhein-Westfalen",
    "wof:name":"Wohnen Und Ideen Beteiligungsges. Mbh",
    "wof:placetype":"venue"
},
  "geometry": {"coordinates":[7.627184,51.96228],"type":"Point"}
}