{
  "type": "Feature",
  "properties": {
    "iso:country":"DE",
    "sg:address":"Uelpebergstr 38a",
    "sg:city":"Wiehl",
    "sg:phone":"+49 2262/701791",
    "sg:postcode":"51674",
    "sg:province":"Nordrhein-Westfalen",
    "wof:name":"Wet-wertstoff Gmbh",
    "wof:placetype":"venue"
},
  "geometry": {"coordinates":[7.4958729744,50.9578514099],"type":"Point"}
}