{
  "type": "Feature",
  "properties": {
    "iso:country":"DE",
    "sg:address":"Stra\u00dfe der Einheit 2",
    "sg:city":"Jahnsdorf",
    "sg:phone":"+49 3721/22502",
    "sg:postcode":"09387",
    "sg:province":"Sachsen",
    "wof:name":"Rundstrickerei H. Nagel Gmbh",
    "wof:placetype":"venue"
},
  "geometry": {"coordinates":[12.8597078323,50.7523422241],"type":"Point"}
}