{
  "type": "Feature",
  "properties": {
    "iso:country":"DE",
    "sg:address":"Wiesenstr. 18",
    "sg:city":"Niesky",
    "sg:postcode":"02906",
    "sg:province":"Sachsen",
    "wof:name":"V & V Bau-management Gmbh",
    "wof:placetype":"venue"
},
  "geometry": {"coordinates":[14.83562,51.285519],"type":"Point"}
}