{
  "type": "Feature",
  "properties": {
    "iso:country":"DE",
    "sg:address":"Via Maccani",
    "sg:city":"Trento",
    "sg:phone":"+39 00",
    "sg:postcode":"38100",
    "sg:province":"Niedersachsen",
    "wof:name":"Risto3 Azienda Leader Della Ristorazione Trentina",
    "wof:placetype":"venue"
},
  "geometry": {"coordinates":[11.112134,46.086105],"type":"Point"}
}