{
  "type": "Feature",
  "properties": {
    "iso:country":"DE",
    "sg:address":"Jahnstr. 11 a",
    "sg:city":"W\u00fcrselen",
    "sg:phone":"+49 2405/73798",
    "sg:postcode":"52146",
    "sg:province":"Nordrhein-Westfalen",
    "wof:name":"Gerd Richardt Steuerberater",
    "wof:placetype":"venue"
},
  "geometry": {"coordinates":[6.163225174,50.8267707825],"type":"Point"}
}