{
  "type": "Feature",
  "properties": {
    "iso:country":"DE",
    "sg:address":"Neutorstr. 34",
    "sg:city":"Ulm",
    "sg:phone":"+49 731/9691454",
    "sg:postcode":"89073",
    "sg:province":"Baden-W\u00fcrttemberg",
    "wof:name":"Restaurant Hollywood",
    "wof:placetype":"venue"
},
  "geometry": {"coordinates":[9.9860916138,48.4035797119],"type":"Point"}
}