{
  "type": "Feature",
  "properties": {
    "iso:country":"DE",
    "sg:address":"Unterkotzauer Weg 42",
    "sg:city":"Hof",
    "sg:phone":"+49 9281/71710",
    "sg:postcode":"95028",
    "sg:province":"Bayern",
    "wof:name":"J\u00fcrgen M\u00fcller Software B\u00fcro",
    "wof:placetype":"venue"
},
  "geometry": {"coordinates":[11.9070005417,50.3259468079],"type":"Point"}
}