{
  "type": "Feature",
  "properties": {
    "iso:country":"DE",
    "sg:address":"Herthastr. 12",
    "sg:city":"Hamburg",
    "sg:phone":"+49 40/6414441",
    "sg:postcode":"22179",
    "sg:province":"Hamburg",
    "wof:name":"Nails & Sun",
    "wof:placetype":"venue"
},
  "geometry": {"coordinates":[10.076478,53.611771],"type":"Point"}
}