{
  "type": "Feature",
  "properties": {
    "iso:country":"DE",
    "sg:address":"Wolfsheide 76",
    "sg:city":"Bielefeld",
    "sg:phone":"+49 521/392520",
    "sg:postcode":"33729",
    "sg:province":"Nordrhein-Westfalen",
    "wof:name":"K. Ritzko",
    "wof:placetype":"venue"
},
  "geometry": {"coordinates":[8.6504297256,52.0517692566],"type":"Point"}
}