{
  "type": "Feature",
  "properties": {
    "iso:country":"DE",
    "sg:address":"Bamberger Str. 9",
    "sg:city":"K\u00fcps",
    "sg:phone":"+49 9264/595",
    "sg:postcode":"96328",
    "sg:province":"Bayern",
    "wof:name":"Lindner Porzellanfabrik Kg",
    "wof:placetype":"venue"
},
  "geometry": {"coordinates":[11.271376,50.192436],"type":"Point"}
}