{
  "type": "Feature",
  "properties": {
    "iso:country":"DE",
    "sg:address":"Stubbenkamp 18",
    "sg:city":"Bad Zwischenahn",
    "sg:phone":"+49 4403/63300",
    "sg:postcode":"26160",
    "sg:province":"Niedersachsen",
    "wof:name":"J. P. Sauer & Sohn Maschinen Gmbh & Co.",
    "wof:placetype":"venue"
},
  "geometry": {"coordinates":[7.976014,53.183952],"type":"Point"}
}