{
  "type": "Feature",
  "properties": {
    "iso:country":"DE",
    "sg:address":"Bahnhofstr. 75",
    "sg:city":"Maintal",
    "sg:phone":"+49 6181/46808",
    "sg:postcode":"63477",
    "sg:province":"Hessen",
    "wof:name":"W. Kagelmann",
    "wof:placetype":"venue"
},
  "geometry": {"coordinates":[8.8361101151,50.142742157],"type":"Point"}
}