{
  "type": "Feature",
  "properties": {
    "iso:country":"DE",
    "sg:address":"Vor dem Clauswerth 8",
    "sg:city":"Bad Hersfeld",
    "sg:phone":"+49 6621/92390",
    "sg:postcode":"36251",
    "sg:province":"Hessen",
    "wof:name":"Kurt R\u00e4uber Beteiligungs- Und Verwaltungs Gmbh",
    "wof:placetype":"venue"
},
  "geometry": {"coordinates":[9.73245,50.86594],"type":"Point"}
}