{
  "type": "Feature",
  "properties": {
    "iso:country":"DE",
    "sg:address":"Ichenhauser Str. 5",
    "sg:city":"Kammeltal",
    "sg:phone":"+49 8223/96970",
    "sg:postcode":"89358",
    "sg:province":"Bayern",
    "wof:name":"Maschinen- Und Betriebs- Hilfering G\u00fcnzburg-krumbach",
    "wof:placetype":"venue"
},
  "geometry": {"coordinates":[10.363022,48.372478],"type":"Point"}
}