{
  "type": "Feature",
  "properties": {
    "iso:country":"DE",
    "sg:address":"Am Reichenbacher Weg 1",
    "sg:city":"Hessisch Lichtenau",
    "sg:phone":"+49 5602/93520",
    "sg:postcode":"37235",
    "sg:province":"Hessen",
    "wof:name":"Baustoffmarkt Mei\u00dfner Beteiligungs-gmbh",
    "wof:placetype":"venue"
},
  "geometry": {"coordinates":[9.7254114151,51.1872329712],"type":"Point"}
}