{
  "type": "Feature",
  "properties": {
    "iso:country":"DE",
    "sg:address":"Trierer Str. 32",
    "sg:city":"Wittlich",
    "sg:phone":"+49 6571/29940",
    "sg:postcode":"54516",
    "sg:province":"Rheinland-Pfalz",
    "wof:name":"Franz Josef Kr\u00e4mer Gmbh",
    "wof:placetype":"venue"
},
  "geometry": {"coordinates":[6.8862538338,49.985042572],"type":"Point"}
}