{
  "type": "Feature",
  "properties": {
    "iso:country":"DE",
    "sg:address":"Paradiesstr. 3",
    "sg:city":"Babenhausen",
    "sg:phone":"+49 8333/1302",
    "sg:postcode":"87727",
    "sg:province":"Bayern",
    "wof:name":"Josef Petrul",
    "wof:placetype":"venue"
},
  "geometry": {"coordinates":[10.2535629272,48.14635849],"type":"Point"}
}