{
  "type": "Feature",
  "properties": {
    "iso:country":"DE",
    "sg:address":"Redkerstr.13",
    "sg:city":"Troisdorf",
    "sg:phone":"+49 2241/408609",
    "sg:postcode":"53842",
    "sg:province":"Nordrhein-Westfalen",
    "wof:name":"Vomfell Gmbh",
    "wof:placetype":"venue"
},
  "geometry": {"coordinates":[7.12534,50.826801],"type":"Point"}
}