{
  "type": "Feature",
  "properties": {
    "iso:country":"DE",
    "sg:address":"Ihmerter Str. 255",
    "sg:city":"Hemer",
    "sg:phone":"+49 2372/8630",
    "sg:postcode":"58675",
    "sg:province":"Nordrhein-Westfalen",
    "wof:name":"L & P Automotive Europe Gmbh",
    "wof:placetype":"venue"
},
  "geometry": {"coordinates":[7.734967,51.332233],"type":"Point"}
}