{
  "type": "Feature",
  "properties": {
    "iso:country":"DE",
    "sg:address":"Adalbertstr. 102",
    "sg:city":"M\u00fcnchen",
    "sg:phone":"+49 89/2725747",
    "sg:postcode":"80799",
    "sg:province":"Bayern",
    "wof:name":"Ludwig Breugl",
    "wof:placetype":"venue"
},
  "geometry": {"coordinates":[11.570035,48.154793],"type":"Point"}
}