{
  "type": "Feature",
  "properties": {
    "iso:country":"DE",
    "sg:address":"Dobbenweg 1",
    "sg:city":"Weyhe",
    "sg:phone":"+49 4203/1029",
    "sg:postcode":"28844",
    "sg:province":"Niedersachsen",
    "wof:name":"Treibholz M\u00f6belhandelsges. Mbh",
    "wof:placetype":"venue"
},
  "geometry": {"coordinates":[8.8721,52.993626],"type":"Point"}
}