{
  "type": "Feature",
  "properties": {
    "iso:country":"DE",
    "sg:address":"Kirchstr. 12",
    "sg:city":"Reichenschwand",
    "sg:phone":"+49 9151/6129",
    "sg:postcode":"91244",
    "sg:province":"Bayern",
    "wof:name":"Ev. Luth. Pfarramt",
    "wof:placetype":"venue"
},
  "geometry": {"coordinates":[11.3752746582,49.5117874146],"type":"Point"}
}