{
  "type": "Feature",
  "properties": {
    "iso:country":"DE",
    "sg:address":"Kruppstr. 7",
    "sg:city":"Dormagen",
    "sg:phone":"+49 2133/60507",
    "sg:postcode":"41540",
    "sg:province":"Nordrhein-Westfalen",
    "wof:name":"Horst-g\u00fcnther Struzina Metzgerei E. K.",
    "wof:placetype":"venue"
},
  "geometry": {"coordinates":[6.8228178024,51.0613441467],"type":"Point"}
}