{
  "type": "Feature",
  "properties": {
    "iso:country":"DE",
    "sg:address":"Unter Sachsenhausen 35",
    "sg:city":"K\u00f6ln",
    "sg:phone":"+49 221/132091",
    "sg:postcode":"50667",
    "sg:province":"Nordrhein-Westfalen",
    "wof:name":"Argento La Costa Dargento Charter Boat Gmbh",
    "wof:placetype":"venue"
},
  "geometry": {"coordinates":[6.9512147903,50.942401886],"type":"Point"}
}