{
  "type": "Feature",
  "properties": {
    "iso:country":"DE",
    "sg:address":"Hermann-von-Sicherer-Str. 32",
    "sg:city":"M\u00fcnchen",
    "sg:phone":"+49 89/78588871",
    "sg:postcode":"81369",
    "sg:province":"Bayern",
    "wof:name":"Claus Eisenmann Rechtsanwalt",
    "wof:placetype":"venue"
},
  "geometry": {"coordinates":[11.525305748,48.1041641235],"type":"Point"}
}