{
  "type": "Feature",
  "properties": {
    "iso:country":"DE",
    "sg:address":"Ringseisstr. 10a",
    "sg:city":"M\u00fcnchen",
    "sg:phone":"+49 89/4587110",
    "sg:postcode":"80337",
    "sg:province":"Bayern",
    "wof:name":"Warner Bros Film Gmbh",
    "wof:placetype":"venue"
},
  "geometry": {"coordinates":[11.5610523224,48.1292953491],"type":"Point"}
}