{
  "type": "Feature",
  "properties": {
    "iso:country":"DE",
    "sg:address":"Kellerstr. 68",
    "sg:city":"Rellingen",
    "sg:phone":"+49 4101/32874",
    "sg:postcode":"25462",
    "sg:province":"Schleswig-Holstein",
    "wof:name":"Reinhard U. Birgit Pein",
    "wof:placetype":"venue"
},
  "geometry": {"coordinates":[9.872212,53.635025],"type":"Point"}
}