{
  "type": "Feature",
  "properties": {
    "iso:country":"DE",
    "sg:address":"Basler Str. 162",
    "sg:city":"L\u00f6rrach",
    "sg:phone":"+49 7621/93430",
    "sg:postcode":"79539",
    "sg:province":"Baden-W\u00fcrttemberg",
    "wof:name":"Creperie Hotel Meyerhof",
    "wof:placetype":"venue"
},
  "geometry": {"coordinates":[7.6608018875,47.6109619141],"type":"Point"}
}