{
  "type": "Feature",
  "properties": {
    "iso:country":"DE",
    "sg:address":"Haager Winkel 4",
    "sg:city":"Kammerstein",
    "sg:phone":"+49 9122/93580",
    "sg:postcode":"91126",
    "sg:province":"Bayern",
    "wof:name":"Ft Fuchs Tiefbau Gmbh",
    "wof:placetype":"venue"
},
  "geometry": {"coordinates":[10.998744,49.308784],"type":"Point"}
}