{
  "type": "Feature",
  "properties": {
    "iso:country":"DE",
    "sg:address":"M\u00fchlenstra\u00dfe 76",
    "sg:city":"Pinneberg",
    "sg:postcode":"25421",
    "sg:province":"Schleswig-Holstein",
    "wof:name":"Intermarco - Eltec Gmbh",
    "wof:placetype":"venue"
},
  "geometry": {"coordinates":[9.7789163589,53.6576766968],"type":"Point"}
}