{
  "type": "Feature",
  "properties": {
    "iso:country":"DE",
    "sg:address":"Aggerstr. 1",
    "sg:city":"K\u00f6ln",
    "sg:phone":"+49 2234/78528",
    "sg:postcode":"50859",
    "sg:province":"Nordrhein-Westfalen",
    "wof:name":"Beate Sommerheuser Steuerbevollm\u00e4chtigte",
    "wof:placetype":"venue"
},
  "geometry": {"coordinates":[6.8194451332,50.9462051392],"type":"Point"}
}