{
  "type": "Feature",
  "properties": {
    "iso:country":"DE",
    "sg:address":"M\u00fchlenstr. 6",
    "sg:city":"Walsrode",
    "sg:phone":"+49 5161/3267",
    "sg:postcode":"29664",
    "sg:province":"Niedersachsen",
    "wof:name":"Hermann Unger",
    "wof:placetype":"venue"
},
  "geometry": {"coordinates":[9.635984,52.823563],"type":"Point"}
}