{
  "type": "Feature",
  "properties": {
    "iso:country":"DE",
    "sg:address":"Ebertstr. 96",
    "sg:city":"Wilhelmshaven",
    "sg:phone":"+49 4421/48080",
    "sg:postcode":"26382",
    "sg:province":"Niedersachsen",
    "wof:name":"Deutsches Windenergie- Institut Gmbh Dewi",
    "wof:placetype":"venue"
},
  "geometry": {"coordinates":[8.1205539703,53.5178451538],"type":"Point"}
}