{
  "type": "Feature",
  "properties": {
    "iso:country":"DE",
    "sg:address":"Lamertzweg 50",
    "sg:city":"Niederkr\u00fcchten",
    "sg:phone":"+49 2163/45135",
    "sg:postcode":"41372",
    "sg:province":"Nordrhein-Westfalen",
    "wof:name":"Hermann-josef Wortmann",
    "wof:placetype":"venue"
},
  "geometry": {"coordinates":[6.179947,51.188023],"type":"Point"}
}