{
  "type": "Feature",
  "properties": {
    "iso:country":"DE",
    "sg:address":"Bahnhofstr. 76",
    "sg:city":"Sulz",
    "sg:phone":"+49 7454/96900",
    "sg:postcode":"72172",
    "sg:province":"Baden-W\u00fcrttemberg",
    "wof:name":"Verzinkerei Sulz Gmbh",
    "wof:placetype":"venue"
},
  "geometry": {"coordinates":[8.6454401016,48.3706512451],"type":"Point"}
}