{
  "type": "Feature",
  "properties": {
    "iso:country":"DE",
    "sg:address":"S\u00fcdring 1",
    "sg:city":"M\u00fccke",
    "sg:postcode":"35325",
    "sg:province":"Hessen",
    "wof:name":"S\u00fcdwind Gmbh & Co. Kg \u00d6ko-strom",
    "wof:placetype":"venue"
},
  "geometry": {"coordinates":[8.97893,50.636932],"type":"Point"}
}