{
  "type": "Feature",
  "properties": {
    "iso:country":"DE",
    "sg:address":"Marktplatz 5",
    "sg:city":"Waldbronn",
    "sg:phone":"+49 7243/68376",
    "sg:postcode":"76337",
    "sg:province":"Baden-W\u00fcrttemberg",
    "wof:name":"Brillen-becker Gmbh",
    "wof:placetype":"venue"
},
  "geometry": {"coordinates":[8.4705581665,48.9295692444],"type":"Point"}
}