{
  "type": "Feature",
  "properties": {
    "iso:country":"DE",
    "sg:address":"Elisenstr. 12",
    "sg:city":"Essen",
    "sg:phone":"+49 201/234832",
    "sg:postcode":"45139",
    "sg:province":"Nordrhein-Westfalen",
    "wof:name":"H. Rottl\u00e4nder Gmbh",
    "wof:placetype":"venue"
},
  "geometry": {"coordinates":[7.029094,51.459389],"type":"Point"}
}