{
  "type": "Feature",
  "properties": {
    "iso:country":"DE",
    "sg:address":"Rathausstr 2",
    "sg:city":"Ludwigsfelde",
    "sg:phone":"+49 3378/511282",
    "sg:postcode":"14974",
    "sg:province":"Brandenburg",
    "wof:name":"T&t Datentechnik Gmbh",
    "wof:placetype":"venue"
},
  "geometry": {"coordinates":[13.2616643906,52.3007164001],"type":"Point"}
}