{
  "type": "Feature",
  "properties": {
    "iso:country":"DE",
    "sg:address":"August-Bebel-Stra\u00dfe 22",
    "sg:city":"Reichenberg",
    "sg:phone":"+49 351/8382332",
    "sg:postcode":"01468",
    "sg:province":"Sachsen",
    "wof:name":"Willkommen Bei Tischlerei Proschmann Im Internet",
    "wof:placetype":"venue"
},
  "geometry": {"coordinates":[13.679371,51.125229],"type":"Point"}
}