{
  "type": "Feature",
  "properties": {
    "iso:country":"DE",
    "sg:address":"Leitensteige 6",
    "sg:city":"Waldb\u00fcttelbrunn",
    "sg:phone":"+49 9369/1534",
    "sg:postcode":"97297",
    "sg:province":"Bayern",
    "wof:name":"Redelbach Transport- Unternehmen Gmbh",
    "wof:placetype":"venue"
},
  "geometry": {"coordinates":[9.754993,49.795528],"type":"Point"}
}