{
  "type": "Feature",
  "properties": {
    "iso:country":"DE",
    "sg:address":"Jacobstr. 4",
    "sg:city":"Haldensleben",
    "sg:phone":"+49 3904/72227",
    "sg:postcode":"39340",
    "sg:province":"Sachsen-Anhalt",
    "wof:name":"Christina Machts",
    "wof:placetype":"venue"
},
  "geometry": {"coordinates":[11.410203,52.289928],"type":"Point"}
}