{
  "type": "Feature",
  "properties": {
    "iso:country":"DE",
    "sg:address":"Eschersheimer Landstr. 520",
    "sg:city":"Frankfurt",
    "sg:phone":"+49 69/525282",
    "sg:postcode":"60433",
    "sg:province":"Hessen",
    "wof:name":"Calmano B\u00e4ckerei",
    "wof:placetype":"venue"
},
  "geometry": {"coordinates":[8.659009,50.155033],"type":"Point"}
}