{
  "type": "Feature",
  "properties": {
    "iso:country":"DE",
    "sg:address":"Gerichtstr. 30",
    "sg:city":"Berlin",
    "sg:phone":"+49 30/4621071",
    "sg:postcode":"13347",
    "sg:province":"Berlin",
    "wof:name":"Dubrovnik-grill",
    "wof:placetype":"venue"
},
  "geometry": {"coordinates":[13.3688430786,52.5447731018],"type":"Point"}
}