{
  "type": "Feature",
  "properties": {
    "iso:country":"DE",
    "sg:city":"Flensburg",
    "sg:phone":"+49 461/12345",
    "sg:postcode":"24939",
    "sg:province":"Schleswig-Holstein",
    "wof:name":"Restaurant Marco Polo Mit Pizzaservice - Flensburg",
    "wof:placetype":"venue"
},
  "geometry": {"coordinates":[9.435455,54.786404],"type":"Point"}
}