{
  "type": "Feature",
  "properties": {
    "iso:country":"DE",
    "sg:address":"Bergstr. 2",
    "sg:city":"Horb",
    "sg:phone":"+49 7451/2289",
    "sg:postcode":"72160",
    "sg:province":"Baden-W\u00fcrttemberg",
    "wof:name":"Sonne",
    "wof:placetype":"venue"
},
  "geometry": {"coordinates":[8.6509056091,48.4396095276],"type":"Point"}
}