{
  "type": "Feature",
  "properties": {
    "iso:country":"DE",
    "sg:address":"Bahnhofstr. 6",
    "sg:city":"Spornitz",
    "sg:phone":"+49 38726/20493",
    "sg:postcode":"19372",
    "sg:province":"Mecklenburg-Vorpommern",
    "wof:name":"Karin Bliemeister",
    "wof:placetype":"venue"
},
  "geometry": {"coordinates":[11.718755,53.410549],"type":"Point"}
}