{
  "type": "Feature",
  "properties": {
    "iso:country":"DE",
    "sg:address":"Rothenkirchener Str 23a",
    "sg:city":"Hartmannsdorf",
    "sg:phone":"+49 37602/7744",
    "sg:postcode":"08107",
    "sg:province":"Sachsen",
    "wof:name":"H&s Elektroanlagen Gmbh",
    "wof:placetype":"venue"
},
  "geometry": {"coordinates":[12.546438,50.598087],"type":"Point"}
}