{
  "type": "Feature",
  "properties": {
    "iso:country":"DE",
    "sg:address":"Vorm Eichh\u00f6lzchen 10",
    "sg:city":"Netphen",
    "sg:phone":"+49 2737/98540",
    "sg:postcode":"57250",
    "sg:province":"Nordrhein-Westfalen",
    "wof:name":"B\u00fcdenbender-hausbau Gmbh",
    "wof:placetype":"venue"
},
  "geometry": {"coordinates":[8.2159433365,50.8583488464],"type":"Point"}
}