{
  "type": "Feature",
  "properties": {
    "iso:country":"DE",
    "sg:address":"Am Hellbach 29",
    "sg:city":"Ahlen",
    "sg:phone":"+49 2528/1224",
    "sg:postcode":"59227",
    "sg:province":"Nordrhein-Westfalen",
    "wof:name":"Automaten Idze Helmut Idzkowiak E. K.",
    "wof:placetype":"venue"
},
  "geometry": {"coordinates":[7.948515892,51.8075714111],"type":"Point"}
}