{
  "type": "Feature",
  "properties": {
    "iso:country":"DE",
    "sg:address":"Herzogau",
    "sg:city":"Waldm\u00fcnchen",
    "sg:phone":"+49 9972/8497",
    "sg:postcode":"93449",
    "sg:province":"Bayern",
    "wof:name":"Pension Gibacht",
    "wof:placetype":"venue"
},
  "geometry": {"coordinates":[12.704375267,49.377784729],"type":"Point"}
}