{
  "type": "Feature",
  "properties": {
    "iso:country":"DE",
    "sg:address":"Rappengasse 36",
    "sg:city":"Rheinzabern",
    "sg:phone":"+49 7272/2396",
    "sg:postcode":"76764",
    "sg:province":"Rheinland-Pfalz",
    "wof:name":"Weinstube Tenne",
    "wof:placetype":"venue"
},
  "geometry": {"coordinates":[8.2756280899,49.1166114807],"type":"Point"}
}