{
  "type": "Feature",
  "properties": {
    "iso:country":"DE",
    "sg:address":"Lange Str. 42",
    "sg:city":"Kirchlinteln",
    "sg:phone":"+49 4237/1097",
    "sg:postcode":"27308",
    "sg:province":"Niedersachsen",
    "wof:name":"Hermann Heldberg",
    "wof:placetype":"venue"
},
  "geometry": {"coordinates":[9.3190402985,52.9401893616],"type":"Point"}
}