{
  "type": "Feature",
  "properties": {
    "iso:country":"DE",
    "sg:address":"Am Burgfriedhof 7",
    "sg:city":"Bonn",
    "sg:phone":"+49 228/316992",
    "sg:postcode":"53177",
    "sg:province":"Nordrhein-Westfalen",
    "wof:name":"Claus Blatzheim",
    "wof:placetype":"venue"
},
  "geometry": {"coordinates":[7.14809,50.684772],"type":"Point"}
}