{
  "type": "Feature",
  "properties": {
    "iso:country":"DE",
    "sg:address":"Holzheimer Str. 12",
    "sg:city":"G\u00f6ppingen",
    "sg:phone":"+49 7161/67290",
    "sg:postcode":"73037",
    "sg:province":"Baden-W\u00fcrttemberg",
    "wof:name":"Husse Verwaltungsges. Mbh",
    "wof:placetype":"venue"
},
  "geometry": {"coordinates":[9.6751050949,48.6925888062],"type":"Point"}
}