{
  "type": "Feature",
  "properties": {
    "iso:country":"DE",
    "sg:address":"N\u00fcrnberger Str. 15",
    "sg:city":"Donauw\u00f6rth",
    "sg:phone":"+49 906/1587",
    "sg:postcode":"86609",
    "sg:province":"Bayern",
    "wof:name":"Bp Tankstelle",
    "wof:placetype":"venue"
},
  "geometry": {"coordinates":[10.7778921127,48.7311325073],"type":"Point"}
}