{
  "type": "Feature",
  "properties": {
    "iso:country":"DE",
    "sg:address":"Severinusstr. 25",
    "sg:city":"Selfkant",
    "sg:phone":"+49 2456/1570",
    "sg:postcode":"52538",
    "sg:province":"Nordrhein-Westfalen",
    "wof:name":"Paul Heynen",
    "wof:placetype":"venue"
},
  "geometry": {"coordinates":[5.9208359718,50.9976387024],"type":"Point"}
}