{
  "type": "Feature",
  "properties": {
    "iso:country":"DE",
    "sg:address":"Stein\u00e4cker 13",
    "sg:city":"Werne",
    "sg:phone":"+49 2389/537864",
    "sg:postcode":"59368",
    "sg:province":"Nordrhein-Westfalen",
    "wof:name":"Baakensch\u00e4nke",
    "wof:placetype":"venue"
},
  "geometry": {"coordinates":[7.6156020164,51.6647071838],"type":"Point"}
}