{
  "type": "Feature",
  "properties": {
    "iso:country":"DE",
    "sg:address":"Tunxdorfer Str.",
    "sg:city":"Papenburg",
    "sg:phone":"+49 4962/248",
    "sg:postcode":"26871",
    "sg:province":"Niedersachsen",
    "wof:name":"Werths Gmbh",
    "wof:placetype":"venue"
},
  "geometry": {"coordinates":[7.3144922256,53.0830917358],"type":"Point"}
}