{
  "type": "Feature",
  "properties": {
    "iso:country":"DE",
    "sg:address":"Hindenburgstr. 27",
    "sg:city":"Esslingen",
    "sg:phone":"+49 711/3167431",
    "sg:postcode":"73728",
    "sg:province":"Baden-W\u00fcrttemberg",
    "wof:name":"A. Lechner",
    "wof:placetype":"venue"
},
  "geometry": {"coordinates":[9.3180437088,48.7381896973],"type":"Point"}
}