{
  "type": "Feature",
  "properties": {
    "iso:country":"DE",
    "sg:address":"Rathausstr. 3",
    "sg:city":"Schwandorf",
    "sg:phone":"+49 9431/1668",
    "sg:postcode":"92421",
    "sg:province":"Bayern",
    "wof:name":"M. J\u00e4ger Beteiligungs Gmbh",
    "wof:placetype":"venue"
},
  "geometry": {"coordinates":[12.105917,49.329857],"type":"Point"}
}