{
  "type": "Feature",
  "properties": {
    "iso:country":"DE",
    "sg:address":"8 rue fontaine",
    "sg:city":"paris",
    "sg:phone":"+49 142811767",
    "sg:postcode":"75009",
    "wof:name":"Cham Musique",
    "wof:placetype":"venue"
},
  "geometry": {"coordinates":[2.334792,48.881065],"type":"Point"}
}