{
  "type": "Feature",
  "properties": {
    "iso:country":"DE",
    "sg:address":"Am Kielsgraben 10",
    "sg:city":"Monheim",
    "sg:phone":"+49 2173/39620",
    "sg:postcode":"40789",
    "sg:province":"Nordrhein-Westfalen",
    "wof:name":"Marbert Gmbh",
    "wof:placetype":"venue"
},
  "geometry": {"coordinates":[6.891097,51.10622],"type":"Point"}
}