{
  "type": "Feature",
  "properties": {
    "iso:country":"DE",
    "sg:address":"Berlinghausen",
    "sg:city":"Meinerzhagen",
    "sg:phone":"+49 2358/243",
    "sg:postcode":"58540",
    "sg:province":"Nordrhein-Westfalen",
    "wof:name":"Basalt- Ag",
    "wof:placetype":"venue"
},
  "geometry": {"coordinates":[7.7744498253,51.0787582397],"type":"Point"}
}