{
  "type": "Feature",
  "properties": {
    "iso:country":"DE",
    "sg:address":"Str\u00fcmpfelbacher Str. 52",
    "sg:city":"Weinstadt",
    "sg:phone":"+49 7151/62696",
    "sg:postcode":"71384",
    "sg:province":"Baden-W\u00fcrttemberg",
    "wof:name":"Hans Schwegler",
    "wof:placetype":"venue"
},
  "geometry": {"coordinates":[9.361489296,48.8115997314],"type":"Point"}
}