{
  "type": "Feature",
  "properties": {
    "iso:country":"DE",
    "sg:address":"Luisenstr. 7",
    "sg:city":"St. Blasien",
    "sg:phone":"+49 7672/4999",
    "sg:postcode":"79837",
    "sg:province":"Baden-W\u00fcrttemberg",
    "wof:name":"Deutsches Haus",
    "wof:placetype":"venue"
},
  "geometry": {"coordinates":[8.12996,47.761913],"type":"Point"}
}