{
  "type": "Feature",
  "properties": {
    "iso:country":"DE",
    "sg:address":"Bergstr. 168",
    "sg:city":"Frankfurt",
    "sg:phone":"+49 335/6857161",
    "sg:postcode":"15230",
    "sg:province":"Brandenburg",
    "wof:name":"Lmt - Leschke Me\u00dftechnik Gmbh",
    "wof:placetype":"venue"
},
  "geometry": {"coordinates":[14.543413,52.351833],"type":"Point"}
}