{
  "type": "Feature",
  "properties": {
    "iso:country":"DE",
    "sg:address":"Willaringen",
    "sg:city":"Rickenbach",
    "sg:phone":"+49 7765/316",
    "sg:postcode":"79736",
    "sg:province":"Baden-W\u00fcrttemberg",
    "wof:name":"Ehrfried Mutter Ingenieur",
    "wof:placetype":"venue"
},
  "geometry": {"coordinates":[7.9728097916,47.6057701111],"type":"Point"}
}