{
  "type": "Feature",
  "properties": {
    "iso:country":"DE",
    "sg:address":"Pfarrer-Schneider-Str. 10",
    "sg:city":"Wei\u00dfenfels",
    "sg:phone":"+49 3443/300239",
    "sg:postcode":"06667",
    "sg:province":"Sachsen-Anhalt",
    "wof:name":"Drk Kreisverband Wei\u00dfenfels E. V.",
    "wof:placetype":"venue"
},
  "geometry": {"coordinates":[11.985668,51.201866],"type":"Point"}
}