{
  "type": "Feature",
  "properties": {
    "iso:country":"DE",
    "sg:address":"Richard-Wagner-Str. 52",
    "sg:city":"Hamm",
    "sg:phone":"+49 2381/50508",
    "sg:postcode":"59063",
    "sg:province":"Nordrhein-Westfalen",
    "wof:name":"Herbert Franke Steuerberater",
    "wof:placetype":"venue"
},
  "geometry": {"coordinates":[7.8266210556,51.6675376892],"type":"Point"}
}