{
  "type": "Feature",
  "properties": {
    "iso:country":"DE",
    "sg:address":"Auf dem Troppenbruch 29",
    "sg:city":"W\u00fcrselen",
    "sg:phone":"+49 2405/419675",
    "sg:postcode":"52146",
    "sg:province":"Nordrhein-Westfalen",
    "wof:name":"Josef Mix",
    "wof:placetype":"venue"
},
  "geometry": {"coordinates":[6.137062,50.810204],"type":"Point"}
}