{
  "type": "Feature",
  "properties": {
    "iso:country":"DE",
    "sg:address":"Adrianstr. 181",
    "sg:city":"Bonn",
    "sg:phone":"+49 228/442950",
    "sg:postcode":"53227",
    "sg:province":"Nordrhein-Westfalen",
    "wof:name":"Hans Vogel",
    "wof:placetype":"venue"
},
  "geometry": {"coordinates":[7.172098,50.71106],"type":"Point"}
}