{
  "type": "Feature",
  "properties": {
    "iso:country":"DE",
    "sg:address":"Zum Maidlebach 3",
    "sg:city":"Staufen",
    "sg:postcode":"79219",
    "sg:province":"Baden-W\u00fcrttemberg",
    "wof:name":"I. M. S. Imaging Marketing Und Service Beteiligungs Gmbh",
    "wof:placetype":"venue"
},
  "geometry": {"coordinates":[7.726549,47.882664],"type":"Point"}
}