{
  "type": "Feature",
  "properties": {
    "iso:country":"DE",
    "sg:address":"B\u00fcrgermeister-Mahr-Str. 28",
    "sg:city":"Obertshausen",
    "sg:phone":"+49 4961/0473373",
    "sg:postcode":"63179",
    "sg:province":"Hessen",
    "wof:name":"Hermann Fl\u00d6rke Gmbh",
    "wof:placetype":"venue"
},
  "geometry": {"coordinates":[8.8725948334,50.0775642395],"type":"Point"}
}