{
  "type": "Feature",
  "properties": {
    "iso:country":"DE",
    "sg:address":"Kapfham 3",
    "sg:city":"Hohenau",
    "sg:phone":"+49 8558/1089",
    "sg:postcode":"94545",
    "sg:province":"Bayern",
    "wof:name":"Gastst\u00e4tte Josef Riedl",
    "wof:placetype":"venue"
},
  "geometry": {"coordinates":[13.4489679337,48.8489341736],"type":"Point"}
}