{
  "type": "Feature",
  "properties": {
    "iso:country":"DE",
    "sg:address":"Kreuzhof 4",
    "sg:city":"Ramstein-Miesenbach",
    "sg:phone":"+49 6371/71527",
    "sg:postcode":"66877",
    "sg:province":"Rheinland-Pfalz",
    "wof:name":"Manfred K\u00fcster Masseur U. Med. Bademeister",
    "wof:placetype":"venue"
},
  "geometry": {"coordinates":[7.552248,49.44838],"type":"Point"}
}