{
  "type": "Feature",
  "properties": {
    "iso:country":"DE",
    "sg:address":"Kumper Landstr. 13",
    "sg:city":"Hamm",
    "sg:phone":"+49 2385/68837",
    "sg:postcode":"59069",
    "sg:province":"Nordrhein-Westfalen",
    "wof:name":"Detlev Altena",
    "wof:placetype":"venue"
},
  "geometry": {"coordinates":[7.830784,51.590885],"type":"Point"}
}