{
  "type": "Feature",
  "properties": {
    "iso:country":"DE",
    "sg:address":"Grairich 4",
    "sg:city":"Kaisersbach",
    "sg:phone":"+49 7184/367",
    "sg:postcode":"73667",
    "sg:province":"Baden-W\u00fcrttemberg",
    "wof:name":"G. St\u00f6cker",
    "wof:placetype":"venue"
},
  "geometry": {"coordinates":[9.651708,48.916946],"type":"Point"}
}