{
  "type": "Feature",
  "properties": {
    "iso:country":"DE",
    "sg:address":"Lachentorstr. 12",
    "sg:city":"Leonberg",
    "sg:phone":"+49 7152/24624",
    "sg:postcode":"71229",
    "sg:province":"Baden-W\u00fcrttemberg",
    "wof:name":"J. Brotz",
    "wof:placetype":"venue"
},
  "geometry": {"coordinates":[9.00916,48.820461],"type":"Point"}
}