{
  "type": "Feature",
  "properties": {
    "iso:country":"DE",
    "sg:address":"Kaiserstr. 82",
    "sg:city":"Dortmund",
    "sg:phone":"+49 231",
    "sg:postcode":"44135",
    "sg:province":"Nordrhein-Westfalen",
    "wof:name":"Versicherungsmakler",
    "wof:placetype":"venue"
},
  "geometry": {"coordinates":[7.481232,51.513378],"type":"Point"}
}