{
  "type": "Feature",
  "properties": {
    "iso:country":"DE",
    "sg:address":"Unterfeld 3",
    "sg:city":"Ro\u00dfbach",
    "sg:phone":"+49 8547/1364",
    "sg:postcode":"94439",
    "sg:province":"Bayern",
    "wof:name":"Franz Wagenthaler",
    "wof:placetype":"venue"
},
  "geometry": {"coordinates":[12.924792,48.603802],"type":"Point"}
}