{
  "type": "Feature",
  "properties": {
    "iso:country":"DE",
    "sg:address":"L\u00fcnener Str. 99",
    "sg:city":"Selm",
    "sg:phone":"+49 2592/62416",
    "sg:postcode":"59379",
    "sg:province":"Nordrhein-Westfalen",
    "wof:name":"Ristorante Pizzeria Sicilia",
    "wof:placetype":"venue"
},
  "geometry": {"coordinates":[7.486811161,51.664264679],"type":"Point"}
}