{
  "type": "Feature",
  "properties": {
    "iso:country":"DE",
    "sg:address":"Julius-Doms-Str. 15",
    "sg:city":"Leverkusen",
    "sg:phone":"+49 214/868520",
    "sg:postcode":"51373",
    "sg:province":"Nordrhein-Westfalen",
    "wof:name":"Ost-pharma-handels Gmbh",
    "wof:placetype":"venue"
},
  "geometry": {"coordinates":[7.0023860931,51.0525398254],"type":"Point"}
}