{
  "type": "Feature",
  "properties": {
    "iso:country":"DE",
    "sg:address":"Albert-Leidl-Str. 6",
    "sg:city":"Augsburg",
    "sg:postcode":"86179",
    "sg:province":"Bayern",
    "wof:name":"Spindler Gmbh",
    "wof:placetype":"venue"
},
  "geometry": {"coordinates":[10.899688,48.298393],"type":"Point"}
}