{
  "type": "Feature",
  "properties": {
    "iso:country":"DE",
    "sg:address":"Falkenstr. 2",
    "sg:city":"Sonnenb\u00fchl",
    "sg:phone":"+49 7128/511",
    "sg:postcode":"72820",
    "sg:province":"Baden-W\u00fcrttemberg",
    "wof:name":"Gottlieb Leibfritz",
    "wof:placetype":"venue"
},
  "geometry": {"coordinates":[9.1849937439,48.3881568909],"type":"Point"}
}