{
  "type": "Feature",
  "properties": {
    "iso:country":"DE",
    "sg:address":"Dreierbergweg 14",
    "sg:city":"Ulm",
    "sg:phone":"+49 731/389408",
    "sg:postcode":"89081",
    "sg:province":"Baden-W\u00fcrttemberg",
    "wof:name":"Anton Fa\u00dfbinder",
    "wof:placetype":"venue"
},
  "geometry": {"coordinates":[9.9373321533,48.4007720947],"type":"Point"}
}