{
  "type": "Feature",
  "properties": {
    "iso:country":"DE",
    "sg:address":"Simsseestr. 48",
    "sg:city":"Frasdorf",
    "sg:phone":"+49 8052/398",
    "sg:postcode":"83112",
    "sg:province":"Bayern",
    "wof:name":"Matthias Staber",
    "wof:placetype":"venue"
},
  "geometry": {"coordinates":[12.278707,47.803699],"type":"Point"}
}