{
  "type": "Feature",
  "properties": {
    "iso:country":"DE",
    "sg:address":"Schladener Str. 15",
    "sg:city":"Liebenburg",
    "sg:phone":"+49 5339/618",
    "sg:postcode":"38704",
    "sg:province":"Niedersachsen",
    "wof:name":"Heinrich Wesche",
    "wof:placetype":"venue"
},
  "geometry": {"coordinates":[10.46882,52.022209],"type":"Point"}
}