{
  "type": "Feature",
  "properties": {
    "iso:country":"DE",
    "sg:city":"Adelhausen",
    "sg:phone":"+49 4976/271324",
    "sg:postcode":"79618",
    "sg:province":"Baden-W\u00fcrttemberg",
    "wof:name":"Raiffeisenbank Eg",
    "wof:placetype":"venue"
},
  "geometry": {"coordinates":[7.761165,47.614769],"type":"Point"}
}