{
  "type": "Feature",
  "properties": {
    "iso:country":"DE",
    "sg:address":"Im Sch\u00e4tzendorf 37",
    "sg:city":"Egestorf",
    "sg:phone":"+49 4175/528",
    "sg:postcode":"21272",
    "sg:province":"Niedersachsen",
    "wof:name":"Martin M\u00fcller",
    "wof:placetype":"venue"
},
  "geometry": {"coordinates":[10.030127,53.211899],"type":"Point"}
}