{
  "type": "Feature",
  "properties": {
    "iso:country":"DE",
    "sg:address":"Hufelandstr. 5",
    "sg:city":"Berlin",
    "sg:phone":"+49 30/4213795",
    "sg:postcode":"10407",
    "sg:province":"Berlin",
    "wof:name":"Carola Dieckert",
    "wof:placetype":"venue"
},
  "geometry": {"coordinates":[13.4304571152,52.5327568054],"type":"Point"}
}