{
  "type": "Feature",
  "properties": {
    "iso:country":"DE",
    "sg:address":"Honoldweg 11",
    "sg:city":"Giengen",
    "sg:phone":"+49 7322/3536",
    "sg:postcode":"89537",
    "sg:province":"Baden-W\u00fcrttemberg",
    "wof:name":"Gr\u00f6schl",
    "wof:placetype":"venue"
},
  "geometry": {"coordinates":[10.241085,48.631424],"type":"Point"}
}