{
  "type": "Feature",
  "properties": {
    "iso:country":"DE",
    "sg:address":"Auf der Geest 11",
    "sg:city":"Oyten",
    "sg:postcode":"28876",
    "sg:province":"Niedersachsen",
    "wof:name":"Lako Trans Container Beteiligungs Gmbh",
    "wof:placetype":"venue"
},
  "geometry": {"coordinates":[9.013878,53.061428],"type":"Point"}
}