{
  "type": "Feature",
  "properties": {
    "iso:country":"DE",
    "sg:address":"Mooswinkl 5",
    "sg:city":"Bischofswiesen",
    "sg:phone":"+49 8652/1747",
    "sg:postcode":"83483",
    "sg:province":"Bayern",
    "wof:name":"G\u00e4stehaus Fritz Und Rita Huber",
    "wof:placetype":"venue"
},
  "geometry": {"coordinates":[12.9689292908,47.6383857727],"type":"Point"}
}