{
  "type": "Feature",
  "properties": {
    "iso:country":"DE",
    "sg:address":"Nibelungenstr. 19",
    "sg:city":"Grasellenbach",
    "sg:phone":"+49 6207/82136",
    "sg:postcode":"64689",
    "sg:province":"Hessen",
    "wof:name":"Gabriele Fromm-frymark Rechtsanw\u00e4ltin Und Notarin",
    "wof:placetype":"venue"
},
  "geometry": {"coordinates":[8.8605442047,49.6317634583],"type":"Point"}
}