{
  "type": "Feature",
  "properties": {
    "iso:country":"DE",
    "sg:address":"M\u00fchlenstr. 61",
    "sg:city":"L\u00fcdinghausen",
    "sg:phone":"+49 2591/4240",
    "sg:postcode":"59348",
    "sg:province":"Nordrhein-Westfalen",
    "wof:name":"Elke Pochert",
    "wof:placetype":"venue"
},
  "geometry": {"coordinates":[7.451168,51.771252],"type":"Point"}
}