{
  "type": "Feature",
  "properties": {
    "iso:country":"DE",
    "sg:address":"Bremker Str. 100",
    "sg:city":"Detmold",
    "sg:phone":"+49 5231/28833",
    "sg:postcode":"32758",
    "sg:province":"Nordrhein-Westfalen",
    "wof:name":"Franz Kleine Landtechnik Gmbh & Co.",
    "wof:placetype":"venue"
},
  "geometry": {"coordinates":[8.865945,51.966385],"type":"Point"}
}