{
  "type": "Feature",
  "properties": {
    "iso:country":"DE",
    "sg:address":"Allee der Kosmonauten 28a",
    "sg:city":"Berlin",
    "sg:phone":"+49 30/54780360",
    "sg:postcode":"12681",
    "sg:province":"Berlin",
    "wof:name":"Ratioprojekt Gmbh",
    "wof:placetype":"venue"
},
  "geometry": {"coordinates":[13.524017334,52.5254707336],"type":"Point"}
}