{
  "type": "Feature",
  "properties": {
    "iso:country":"DE",
    "sg:address":"Pleichfelder Str. 2",
    "sg:city":"K\u00fcrnach",
    "sg:phone":"+49 9367/90750",
    "sg:postcode":"97273",
    "sg:province":"Bayern",
    "wof:name":"Emil Und Georg Bieber",
    "wof:placetype":"venue"
},
  "geometry": {"coordinates":[10.0401678085,49.8464355469],"type":"Point"}
}