{
  "type": "Feature",
  "properties": {
    "iso:country":"DE",
    "sg:address":"Alte Vockenroter Steige 29",
    "sg:city":"Wertheim",
    "sg:postcode":"97877",
    "sg:province":"Baden-W\u00fcrttemberg",
    "wof:name":"Terra Leasobjekt Gmbh",
    "wof:placetype":"venue"
},
  "geometry": {"coordinates":[9.510641098,49.7538642883],"type":"Point"}
}