{
  "type": "Feature",
  "properties": {
    "iso:country":"DE",
    "sg:address":"Hummelsb\u00fctteler Markt 13",
    "sg:city":"Hamburg",
    "sg:phone":"+49 40/53897333",
    "sg:postcode":"22339",
    "sg:province":"Hamburg",
    "wof:name":"Hopsi Med",
    "wof:placetype":"venue"
},
  "geometry": {"coordinates":[10.046935,53.642853],"type":"Point"}
}