{
  "type": "Feature",
  "properties": {
    "iso:country":"DE",
    "sg:address":"Marktstr. 10",
    "sg:city":"H\u00f6xter",
    "sg:phone":"+49 4952/713061",
    "sg:postcode":"37671",
    "sg:province":"Nordrhein-Westfalen",
    "wof:name":"Volksbank H\u00f6xter",
    "wof:placetype":"venue"
},
  "geometry": {"coordinates":[9.381598,51.774929],"type":"Point"}
}