{
  "type": "Feature",
  "properties": {
    "iso:country":"DE",
    "sg:address":"Am Griesebach 2",
    "sg:city":"Seesen",
    "sg:postcode":"38723",
    "sg:province":"Niedersachsen",
    "wof:name":"Transportbeton S\u00fcdharz Gmbh & Co. Kg",
    "wof:placetype":"venue"
},
  "geometry": {"coordinates":[10.191485405,51.8408164978],"type":"Point"}
}