{
  "type": "Feature",
  "properties": {
    "iso:country":"DE",
    "sg:address":"Kirchenstr. 4",
    "sg:city":"Baierbrunn",
    "sg:phone":"+49 89/7932546",
    "sg:postcode":"82065",
    "sg:province":"Bayern",
    "wof:name":"Josef Mehringer Gmbh",
    "wof:placetype":"venue"
},
  "geometry": {"coordinates":[11.4859933853,48.0203056335],"type":"Point"}
}