{
  "type": "Feature",
  "properties": {
    "iso:country":"DE",
    "sg:address":"An den H\u00f6fen 21",
    "sg:city":"B\u00fcnde",
    "sg:phone":"+49 5223/12781",
    "sg:postcode":"32257",
    "sg:province":"Nordrhein-Westfalen",
    "wof:name":"L. Sch\u00e4ffer",
    "wof:placetype":"venue"
},
  "geometry": {"coordinates":[8.570587,52.169121],"type":"Point"}
}