{
  "type": "Feature",
  "properties": {
    "iso:country":"DE",
    "sg:address":"Glash\u00fctter Str. 6",
    "sg:city":"Sankt Englmar",
    "sg:phone":"+49 9965/282",
    "sg:postcode":"94379",
    "sg:province":"Bayern",
    "wof:name":"Sport-bugl & Co.",
    "wof:placetype":"venue"
},
  "geometry": {"coordinates":[12.823439,49.001755],"type":"Point"}
}