{
  "type": "Feature",
  "properties": {
    "iso:country":"DE",
    "sg:address":"Hindenburgstr. 5a",
    "sg:city":"Bad Sachsa",
    "sg:phone":"+49 5523/8727",
    "sg:postcode":"37441",
    "sg:province":"Niedersachsen",
    "wof:name":"Hans Weiss Inh. Gernot Pawlik",
    "wof:placetype":"venue"
},
  "geometry": {"coordinates":[10.5493650436,51.5979881287],"type":"Point"}
}