{
  "type": "Feature",
  "properties": {
    "iso:country":"DE",
    "sg:address":"W\u00e4ssernachstr. 36",
    "sg:city":"Ha\u00dffurt",
    "sg:phone":"+49 9521/8242",
    "sg:postcode":"97437",
    "sg:province":"Bayern",
    "wof:name":"L. Und U. Rehm",
    "wof:placetype":"venue"
},
  "geometry": {"coordinates":[10.4747495651,50.0320854187],"type":"Point"}
}