{
  "type": "Feature",
  "properties": {
    "iso:country":"DE",
    "sg:address":"Schachenb\u00fchlstr. 31",
    "sg:city":"Herrischried",
    "sg:phone":"+49 7764/227",
    "sg:postcode":"79737",
    "sg:province":"Baden-W\u00fcrttemberg",
    "wof:name":"Friedrich Hofmann",
    "wof:placetype":"venue"
},
  "geometry": {"coordinates":[7.995265007,47.666885376],"type":"Point"}
}