{
  "type": "Feature",
  "properties": {
    "iso:country":"DE",
    "sg:address":"Stockumer Str. 28",
    "sg:city":"Witten",
    "sg:phone":"+49 2302",
    "sg:postcode":"58453",
    "sg:province":"Nordrhein-Westfalen",
    "wof:name":"Dip - Digital Print",
    "wof:placetype":"venue"
},
  "geometry": {"coordinates":[7.376988,51.45129],"type":"Point"}
}