{
  "type": "Feature",
  "properties": {
    "iso:country":"DE",
    "sg:address":"Beckermannstr 3",
    "sg:city":"Greven",
    "sg:phone":"+49 2571/93840",
    "sg:postcode":"48268",
    "sg:province":"Nordrhein-Westfalen",
    "wof:name":"S\u00f6dahl Design A/s",
    "wof:placetype":"venue"
},
  "geometry": {"coordinates":[7.611316,52.1073],"type":"Point"}
}