{
  "type": "Feature",
  "properties": {
    "iso:country":"DE",
    "sg:address":"Neustr. 5",
    "sg:city":"Bocholt",
    "sg:phone":"+49 2871/14215",
    "sg:postcode":"46399",
    "sg:province":"Nordrhein-Westfalen",
    "wof:name":"Thonhausensche Stiftung",
    "wof:placetype":"venue"
},
  "geometry": {"coordinates":[6.6152148247,51.8378334045],"type":"Point"}
}