{
  "type": "Feature",
  "properties": {
    "iso:country":"DE",
    "sg:address":"Bremer Tor 7",
    "sg:city":"Visbek",
    "sg:phone":"+49 4445/470",
    "sg:postcode":"49429",
    "sg:province":"Niedersachsen",
    "wof:name":"Restaurant Bremer Tor Inh. Elisabeth Gelhaus",
    "wof:placetype":"venue"
},
  "geometry": {"coordinates":[8.3132362366,52.8378334045],"type":"Point"}
}