{
  "type": "Feature",
  "properties": {
    "iso:country":"DE",
    "sg:address":"Bergstr. 6",
    "sg:city":"St\u00f6ttwang",
    "sg:phone":"+49 8345/549",
    "sg:postcode":"87677",
    "sg:province":"Bayern",
    "wof:name":"Franz Paul",
    "wof:placetype":"venue"
},
  "geometry": {"coordinates":[10.7023277283,47.8985900879],"type":"Point"}
}