{
  "type": "Feature",
  "properties": {
    "iso:country":"DE",
    "sg:address":"Ulmenweg 44",
    "sg:city":"Neum\u00fcnster",
    "sg:phone":"+49 4321/54448",
    "sg:postcode":"24537",
    "sg:province":"Schleswig-Holstein",
    "wof:name":"Helmut Bachmann",
    "wof:placetype":"venue"
},
  "geometry": {"coordinates":[9.9636182785,54.0945701599],"type":"Point"}
}