{
  "type": "Feature",
  "properties": {
    "iso:country":"DE",
    "sg:address":"Seligenstaedter Str. 52 Hausen::",
    "sg:city":"Obertshausen",
    "sg:phone":"+49 4961/04701",
    "sg:postcode":"63179",
    "sg:province":"Hessen",
    "wof:name":"Volksbank Maingau Eg",
    "wof:placetype":"venue"
},
  "geometry": {"coordinates":[8.84683,50.069656],"type":"Point"}
}