{
  "type": "Feature",
  "properties": {
    "iso:country":"DE",
    "sg:address":"Birkenweg 16",
    "sg:city":"L\u00fcbberstedt",
    "sg:phone":"+49 4793/96140",
    "sg:postcode":"27729",
    "sg:province":"Niedersachsen",
    "wof:name":"J. Sanders",
    "wof:placetype":"venue"
},
  "geometry": {"coordinates":[8.8172903061,53.3366851807],"type":"Point"}
}