{
  "type": "Feature",
  "properties": {
    "iso:country":"DE",
    "sg:address":"Darmst\u00e4dter Str. 34",
    "sg:city":"Zwingenberg",
    "sg:postcode":"64673",
    "sg:province":"Hessen",
    "wof:name":"Viscum Ag",
    "wof:placetype":"venue"
},
  "geometry": {"coordinates":[8.6109304428,49.7278785706],"type":"Point"}
}