{
  "type": "Feature",
  "properties": {
    "iso:country":"DE",
    "sg:address":"Kirchstr. 2",
    "sg:city":"Colnrade",
    "sg:postcode":"27243",
    "sg:province":"Niedersachsen",
    "wof:name":"Ev.-luth. Kirchengemeinde B\u00fcro 1",
    "wof:placetype":"venue"
},
  "geometry": {"coordinates":[8.476392746,52.8220596313],"type":"Point"}
}