{
  "type": "Feature",
  "properties": {
    "iso:country":"DE",
    "sg:address":"Ringstr. 52",
    "sg:city":"Steinau",
    "sg:postcode":"36396",
    "sg:province":"Hessen",
    "wof:name":"Praxis Dr. Leisenberg Steinau",
    "wof:placetype":"venue"
},
  "geometry": {"coordinates":[9.46548,50.311161],"type":"Point"}
}