{
  "type": "Feature",
  "properties": {
    "iso:country":"DE",
    "sg:address":"Kirchstr. 24",
    "sg:city":"Berod",
    "sg:phone":"+49 6435/2662",
    "sg:postcode":"56414",
    "sg:province":"Rheinland-Pfalz",
    "wof:name":"G. Hill",
    "wof:placetype":"venue"
},
  "geometry": {"coordinates":[7.934468,50.481636],"type":"Point"}
}