{
  "type": "Feature",
  "properties": {
    "iso:country":"DE",
    "sg:address":"Postfach",
    "sg:city":"Ostfildern",
    "sg:postcode":"73744",
    "sg:province":"Baden-W\u00fcrttemberg",
    "wof:name":"Topkauf Beteiligungs Gmbh",
    "wof:placetype":"venue"
},
  "geometry": {"coordinates":[9.26936,48.708549],"type":"Point"}
}