{
  "type": "Feature",
  "properties": {
    "iso:country":"DE",
    "sg:address":"R\u00f6ntgenstr. 13",
    "sg:city":"Rutesheim",
    "sg:postcode":"71277",
    "sg:province":"Baden-W\u00fcrttemberg",
    "wof:name":"M. Weichert Anlageberater",
    "wof:placetype":"venue"
},
  "geometry": {"coordinates":[8.9469604492,48.8131256104],"type":"Point"}
}