{
  "type": "Feature",
  "properties": {
    "iso:country":"DE",
    "sg:address":"Insel Reichenau",
    "sg:city":"Reichenau",
    "sg:phone":"+49 7534/7384",
    "sg:postcode":"78479",
    "sg:province":"Baden-W\u00fcrttemberg",
    "wof:name":"Sandseele Campingplatz",
    "wof:placetype":"venue"
},
  "geometry": {"coordinates":[9.061253,47.697899],"type":"Point"}
}