{
  "type": "Feature",
  "properties": {
    "iso:country":"DE",
    "sg:address":"Im Sackhof 5",
    "sg:city":"Attendorn",
    "sg:phone":"+49 2722/4225",
    "sg:postcode":"57439",
    "sg:province":"Nordrhein-Westfalen",
    "wof:name":"Stadtsch\u00e4nke",
    "wof:placetype":"venue"
},
  "geometry": {"coordinates":[7.904818058,51.1256599426],"type":"Point"}
}