{
  "type": "Feature",
  "properties": {
    "iso:country":"DE",
    "sg:address":"Schulstr. 19",
    "sg:city":"Sandhausen",
    "sg:phone":"+49 6224/2378",
    "sg:postcode":"69207",
    "sg:province":"Baden-W\u00fcrttemberg",
    "wof:name":"H. Und W. Baumann Elektroinstallation",
    "wof:placetype":"venue"
},
  "geometry": {"coordinates":[8.655969,49.340843],"type":"Point"}
}