{
  "type": "Feature",
  "properties": {
    "iso:country":"DE",
    "sg:address":"Max-Planck-Str. 20",
    "sg:city":"Kornwestheim",
    "sg:phone":"+49 7154/2509",
    "sg:postcode":"70806",
    "sg:province":"Baden-W\u00fcrttemberg",
    "wof:name":"Kurt Schweyher",
    "wof:placetype":"venue"
},
  "geometry": {"coordinates":[9.172694,48.852772],"type":"Point"}
}