{
  "type": "Feature",
  "properties": {
    "iso:country":"DE",
    "sg:address":"H\u00e4ndelstr. 34",
    "sg:city":"Schwaig",
    "sg:phone":"+49 911/505515",
    "sg:postcode":"90571",
    "sg:province":"Bayern",
    "wof:name":"Peter Dietz",
    "wof:placetype":"venue"
},
  "geometry": {"coordinates":[11.214556694,49.4793281555],"type":"Point"}
}