{
  "type": "Feature",
  "properties": {
    "iso:country":"DE",
    "sg:address":"Karlsgraben 4",
    "sg:city":"Aachen",
    "sg:phone":"+49 241/403077",
    "sg:postcode":"52064",
    "sg:province":"Nordrhein-Westfalen",
    "wof:name":"India-hut",
    "wof:placetype":"venue"
},
  "geometry": {"coordinates":[6.077147007,50.7729072571],"type":"Point"}
}