{
  "type": "Feature",
  "properties": {
    "iso:country":"DE",
    "sg:address":"Heideweg 11",
    "sg:city":"Horn-Bad Meinberg",
    "sg:phone":"+49 5234/3964",
    "sg:postcode":"32805",
    "sg:province":"Nordrhein-Westfalen",
    "wof:name":"Manfred Goos",
    "wof:placetype":"venue"
},
  "geometry": {"coordinates":[8.9506130219,51.8670768738],"type":"Point"}
}