{
  "type": "Feature",
  "properties": {
    "iso:country":"DE",
    "sg:address":"Robert-Bosch-Str. 13",
    "sg:city":"Geislingen",
    "sg:phone":"+49 7331/20040",
    "sg:postcode":"73312",
    "sg:province":"Baden-W\u00fcrttemberg",
    "wof:name":"Medipha Gmbh",
    "wof:placetype":"venue"
},
  "geometry": {"coordinates":[9.8440160751,48.628780365],"type":"Point"}
}