{
  "type": "Feature",
  "properties": {
    "iso:country":"DE",
    "sg:address":"Achtruper Str. 1",
    "sg:city":"Ladelund",
    "sg:phone":"+49 4666/300",
    "sg:postcode":"25926",
    "sg:province":"Schleswig-Holstein",
    "wof:name":"Pension Carl Nissen",
    "wof:placetype":"venue"
},
  "geometry": {"coordinates":[9.0256090164,54.8402709961],"type":"Point"}
}