{
  "type": "Feature",
  "properties": {
    "iso:country":"DE",
    "sg:address":"Hechinger Str. 5",
    "sg:city":"Stuttgart",
    "sg:phone":"+49 711/717141",
    "sg:postcode":"70567",
    "sg:province":"Baden-W\u00fcrttemberg",
    "wof:name":"B\u00e4ren",
    "wof:placetype":"venue"
},
  "geometry": {"coordinates":[9.1466741562,48.7258262634],"type":"Point"}
}