{
  "type": "Feature",
  "properties": {
    "iso:country":"DE",
    "sg:address":"Wiedbachstr. 5",
    "sg:city":"Dreifelden",
    "sg:phone":"+49 2666/95120",
    "sg:postcode":"57629",
    "sg:province":"Rheinland-Pfalz",
    "wof:name":"Rheinl\u00e4nder",
    "wof:placetype":"venue"
},
  "geometry": {"coordinates":[7.835656,50.591019],"type":"Point"}
}