{
  "type": "Feature",
  "properties": {
    "iso:country":"DE",
    "sg:address":"Weidenweg 12",
    "sg:city":"Boll",
    "sg:phone":"+49 4971/644016",
    "sg:postcode":"73087",
    "sg:province":"Baden-W\u00fcrttemberg",
    "wof:name":"Act Aerosol-chemie-technik Gmbh",
    "wof:placetype":"venue"
},
  "geometry": {"coordinates":[8.985327,48.328739],"type":"Point"}
}