{
  "type": "Feature",
  "properties": {
    "iso:country":"DE",
    "sg:address":"Bachstr. 1",
    "sg:city":"Bad Rothenfelde",
    "sg:postcode":"49214",
    "sg:province":"Niedersachsen",
    "wof:name":"Karin T\u00e4ubert-schr\u00f6er Industrievertretungen E. Kfr.",
    "wof:placetype":"venue"
},
  "geometry": {"coordinates":[8.164926,52.111588],"type":"Point"}
}