{
  "type": "Feature",
  "properties": {
    "iso:country":"DE",
    "sg:address":"Kardinal-Volk-Platz 1",
    "sg:city":"Hanau",
    "sg:postcode":"63456",
    "sg:province":"Hessen",
    "wof:name":"Gabriele Christ",
    "wof:placetype":"venue"
},
  "geometry": {"coordinates":[8.9144611359,50.1062545776],"type":"Point"}
}