{
  "type": "Feature",
  "properties": {
    "iso:country":"DE",
    "sg:address":"Oeder Weg 78",
    "sg:city":"Frankfurt",
    "sg:phone":"+49 69/598994",
    "sg:postcode":"60318",
    "sg:province":"Hessen",
    "wof:name":"Dieter Ebert",
    "wof:placetype":"venue"
},
  "geometry": {"coordinates":[8.6814947128,50.1234970093],"type":"Point"}
}