{
  "type": "Feature",
  "properties": {
    "iso:country":"DE",
    "sg:address":"Leimengasse 9",
    "sg:city":"Zotzenheim",
    "sg:phone":"+49 6701/568",
    "sg:postcode":"55576",
    "sg:province":"Rheinland-Pfalz",
    "wof:name":"Werner Pitthan",
    "wof:placetype":"venue"
},
  "geometry": {"coordinates":[7.9697289467,49.8725242615],"type":"Point"}
}