{
  "type": "Feature",
  "properties": {
    "iso:country":"DE",
    "sg:address":"Schulstr 39",
    "sg:city":"Walddorfh\u00e4slach",
    "sg:phone":"+49 7127/31593",
    "sg:postcode":"72141",
    "sg:province":"Baden-W\u00fcrttemberg",
    "wof:name":"Necker Gmbh",
    "wof:placetype":"venue"
},
  "geometry": {"coordinates":[9.189933,48.596207],"type":"Point"}
}