{
  "type": "Feature",
  "properties": {
    "iso:country":"DE",
    "sg:address":"Waldenburger Str. 17",
    "sg:city":"Paderborn",
    "sg:phone":"+49 5251/771970",
    "sg:postcode":"33098",
    "sg:province":"Nordrhein-Westfalen",
    "wof:name":"M\u00fcller Gmbh",
    "wof:placetype":"venue"
},
  "geometry": {"coordinates":[8.7329006195,51.7075538635],"type":"Point"}
}