{
  "type": "Feature",
  "properties": {
    "iso:country":"DE",
    "sg:address":"Stirper Warte 1",
    "sg:city":"Lippstadt",
    "sg:phone":"+49 2941/28880",
    "sg:postcode":"59557",
    "sg:province":"Nordrhein-Westfalen",
    "wof:name":"Bio-pack Verwaltungs Gmbh",
    "wof:placetype":"venue"
},
  "geometry": {"coordinates":[8.3263244629,51.6467514038],"type":"Point"}
}