{
  "type": "Feature",
  "properties": {
    "iso:country":"DE",
    "sg:address":"Kolmarer Str. 30",
    "sg:city":"Mannheim",
    "sg:phone":"+49 621/473586",
    "sg:postcode":"68229",
    "sg:province":"Baden-W\u00fcrttemberg",
    "wof:name":"Humke & Slottke Engineering Gmbh",
    "wof:placetype":"venue"
},
  "geometry": {"coordinates":[8.5793075562,49.4405326843],"type":"Point"}
}