{
  "type": "Feature",
  "properties": {
    "iso:country":"DE",
    "sg:address":"Grindelberg 75",
    "sg:city":"Hamburg",
    "sg:postcode":"20144",
    "sg:province":"Hamburg",
    "wof:name":"Pieper Zehnte Verm\u00f6gensverwaltungs- Gmbh",
    "wof:placetype":"venue"
},
  "geometry": {"coordinates":[9.9775943756,53.5771980286],"type":"Point"}
}