{
  "type": "Feature",
  "properties": {
    "iso:country":"DE",
    "sg:address":"Oberringstr. 19",
    "sg:city":"Ingolstadt",
    "sg:phone":"+49 841/78285",
    "sg:postcode":"85051",
    "sg:province":"Bayern",
    "wof:name":"Bim Bam Bino",
    "wof:placetype":"venue"
},
  "geometry": {"coordinates":[11.4104452133,48.7426452637],"type":"Point"}
}