{
  "type": "Feature",
  "properties": {
    "iso:country":"DE",
    "sg:address":"Tertius T\u00f6rn 40",
    "sg:city":"B\u00fcsum",
    "sg:phone":"+49 4834/8709",
    "sg:postcode":"25761",
    "sg:province":"Schleswig-Holstein",
    "wof:name":"Pension Haus Timpe Te",
    "wof:placetype":"venue"
},
  "geometry": {"coordinates":[8.8469657898,54.1348876953],"type":"Point"}
}