{
  "type": "Feature",
  "properties": {
    "iso:country":"DE",
    "sg:address":"Ringstr. 1",
    "sg:city":"Dossenheim",
    "sg:phone":"+49 6221/869909",
    "sg:postcode":"69221",
    "sg:province":"Baden-W\u00fcrttemberg",
    "wof:name":"Karl-heinz K\u00f6rbel",
    "wof:placetype":"venue"
},
  "geometry": {"coordinates":[8.674282,49.44614],"type":"Point"}
}