{
  "type": "Feature",
  "properties": {
    "iso:country":"DE",
    "sg:address":"Schlesierstr. 2",
    "sg:city":"Bad Bentheim",
    "sg:phone":"+49 5924/1781",
    "sg:postcode":"48455",
    "sg:province":"Niedersachsen",
    "wof:name":"M. Kochendorf Radio-fernseh-technik",
    "wof:placetype":"venue"
},
  "geometry": {"coordinates":[7.1032018661,52.3003883362],"type":"Point"}
}