{
  "type": "Feature",
  "properties": {
    "iso:country":"DE",
    "sg:address":"Walchsing 1",
    "sg:city":"Aldersbach",
    "sg:phone":"+49 8543/4111",
    "sg:postcode":"94501",
    "sg:province":"Bayern",
    "wof:name":"Kies- Und Betonwerk Max Maierhofer",
    "wof:placetype":"venue"
},
  "geometry": {"coordinates":[13.0805892944,48.59009552],"type":"Point"}
}