{
  "type": "Feature",
  "properties": {
    "iso:country":"DE",
    "sg:address":"Sudetenstrasse 5",
    "sg:city":"Kaufbeuren",
    "sg:phone":"+49 8341/8781",
    "sg:postcode":"87600",
    "sg:province":"Bayern",
    "wof:name":"Webopac-logistics Gmbh",
    "wof:placetype":"venue"
},
  "geometry": {"coordinates":[10.6424684525,47.8991317749],"type":"Point"}
}