{
  "type": "Feature",
  "properties": {
    "iso:country":"DE",
    "sg:address":"Wester\u00f6der Str. 20",
    "sg:city":"Duderstadt",
    "sg:phone":"+49 5527/4305",
    "sg:postcode":"37115",
    "sg:province":"Niedersachsen",
    "wof:name":"E. Weiss Bettfedernreinigung",
    "wof:placetype":"venue"
},
  "geometry": {"coordinates":[10.232874,51.518929],"type":"Point"}
}