{
  "type": "Feature",
  "properties": {
    "iso:country":"DE",
    "sg:address":"Radegundis 6",
    "sg:city":"Augsburg",
    "sg:phone":"+49 821/432619",
    "sg:postcode":"86199",
    "sg:province":"Bayern",
    "wof:name":"Pizzeria O Solo Mio",
    "wof:placetype":"venue"
},
  "geometry": {"coordinates":[10.8341598511,48.3406715393],"type":"Point"}
}