{
  "type": "Feature",
  "properties": {
    "iso:country":"DE",
    "sg:address":"Bahnhofstr. 15 c",
    "sg:city":"Weyhe",
    "sg:postcode":"28844",
    "sg:province":"Niedersachsen",
    "wof:name":"Texim-technischer Export- Und Importhandels Gmbh",
    "wof:placetype":"venue"
},
  "geometry": {"coordinates":[8.8506660461,52.9833106995],"type":"Point"}
}