{
  "type": "Feature",
  "properties": {
    "iso:country":"DE",
    "sg:address":"Dornbuscher Str. 9",
    "sg:city":"Drochtersen",
    "sg:phone":"+49 4143/5419",
    "sg:postcode":"21706",
    "sg:province":"Niedersachsen",
    "wof:name":"Friedrich Eylmann",
    "wof:placetype":"venue"
},
  "geometry": {"coordinates":[9.328534,53.728001],"type":"Point"}
}