{
  "type": "Feature",
  "properties": {
    "iso:country":"DE",
    "sg:address":"Hauptstr. 100",
    "sg:city":"M\u00fcllheim",
    "sg:postcode":"79379",
    "sg:province":"Baden-W\u00fcrttemberg",
    "wof:name":"Karl L\u00e4uger",
    "wof:placetype":"venue"
},
  "geometry": {"coordinates":[7.6247429848,47.8067474365],"type":"Point"}
}