{
  "type": "Feature",
  "properties": {
    "iso:country":"DE",
    "sg:address":"Oberfeldstr. 30",
    "sg:city":"Berlin",
    "sg:phone":"+49 30/54398254",
    "sg:postcode":"12683",
    "sg:province":"Berlin",
    "wof:name":"Skarab\u00e4us-apotheke E. K.",
    "wof:placetype":"venue"
},
  "geometry": {"coordinates":[13.555813,52.520443],"type":"Point"}
}