{
  "type": "Feature",
  "properties": {
    "iso:country":"DE",
    "sg:address":"Am Ke\u00dfling 21",
    "sg:city":"Ettersburg",
    "sg:postcode":"99439",
    "sg:province":"Th\u00fcringen",
    "wof:name":"Inter Bauregie Gmbh",
    "wof:placetype":"venue"
},
  "geometry": {"coordinates":[11.282541,51.034431],"type":"Point"}
}