{
  "type": "Feature",
  "properties": {
    "iso:country":"DE",
    "sg:address":"Schozacher Str. 51",
    "sg:city":"Stuttgart",
    "sg:postcode":"70437",
    "sg:province":"Baden-W\u00fcrttemberg",
    "wof:name":"H.-d. Schmidt",
    "wof:placetype":"venue"
},
  "geometry": {"coordinates":[9.187589,48.82938],"type":"Point"}
}