{
  "type": "Feature",
  "properties": {
    "iso:country":"DE",
    "sg:address":"Dorfstr. 28",
    "sg:city":"Wannweil",
    "sg:phone":"+49 7121/58858",
    "sg:postcode":"72827",
    "sg:province":"Baden-W\u00fcrttemberg",
    "wof:name":"Heinz K\u00fchn Immobilienmakler",
    "wof:placetype":"venue"
},
  "geometry": {"coordinates":[9.1510829926,48.51379776],"type":"Point"}
}