{
  "type": "Feature",
  "properties": {
    "iso:country":"DE",
    "sg:address":"Mackebenstr. 17",
    "sg:city":"Bielefeld",
    "sg:phone":"+49 521/441705",
    "sg:postcode":"33647",
    "sg:province":"Nordrhein-Westfalen",
    "wof:name":"Kath. Pfarramt Herz Jesu",
    "wof:placetype":"venue"
},
  "geometry": {"coordinates":[8.5111188889,51.9939117432],"type":"Point"}
}