{
  "type": "Feature",
  "properties": {
    "iso:country":"DE",
    "sg:address":"Elisabethstr 14",
    "sg:city":"D\u00fcsseldorf",
    "sg:phone":"+49 211/386880",
    "sg:postcode":"40217",
    "sg:province":"Nordrhein-Westfalen",
    "wof:name":"Deutsche Direktmarketing Akademie",
    "wof:placetype":"venue"
},
  "geometry": {"coordinates":[6.775497,51.216961],"type":"Point"}
}