{
  "type": "Feature",
  "properties": {
    "iso:country":"DE",
    "sg:address":"Sydowstr. 27",
    "sg:city":"Gelsenkirchen",
    "sg:phone":"+49 209/32640",
    "sg:postcode":"45894",
    "sg:province":"Nordrhein-Westfalen",
    "wof:name":"Katholisches Pfarramt Christus K\u00f6nig",
    "wof:placetype":"venue"
},
  "geometry": {"coordinates":[7.0416641235,51.5874595642],"type":"Point"}
}