{
  "type": "Feature",
  "properties": {
    "iso:country":"DE",
    "sg:address":"Nickelstr. 4",
    "sg:city":"Isernhagen",
    "sg:phone":"+49 511/7260960",
    "sg:postcode":"30916",
    "sg:province":"Niedersachsen",
    "wof:name":"Siprox Gmbh & Co. Kg",
    "wof:placetype":"venue"
},
  "geometry": {"coordinates":[9.8082170486,52.4847335815],"type":"Point"}
}