{
  "type": "Feature",
  "properties": {
    "iso:country":"DE",
    "sg:address":"Hagellocher Weg 64",
    "sg:city":"T\u00fcbingen",
    "sg:phone":"+49 7071/42244",
    "sg:postcode":"72070",
    "sg:province":"Baden-W\u00fcrttemberg",
    "wof:name":"U. Rein",
    "wof:placetype":"venue"
},
  "geometry": {"coordinates":[9.02748,48.525063],"type":"Point"}
}