{
  "type": "Feature",
  "properties": {
    "iso:country":"DE",
    "sg:address":"Gaiglstr. 8",
    "sg:city":"M\u00fcnchen",
    "sg:phone":"+49 89/1293392",
    "sg:postcode":"80335",
    "sg:province":"Bayern",
    "wof:name":"Werner Fries",
    "wof:placetype":"venue"
},
  "geometry": {"coordinates":[11.551907,48.151978],"type":"Point"}
}