{
  "type": "Feature",
  "properties": {
    "iso:country":"DE",
    "sg:address":"G\u00f6rlitzer Str. 23",
    "sg:city":"Rietschen",
    "sg:phone":"+49 35772/40855",
    "sg:postcode":"02956",
    "sg:province":"Sachsen",
    "wof:name":"Hans-dietrich Kuchra",
    "wof:placetype":"venue"
},
  "geometry": {"coordinates":[14.785401,51.393181],"type":"Point"}
}