{
  "type": "Feature",
  "properties": {
    "iso:country":"DE",
    "sg:address":"Zugspitzstr. 34",
    "sg:city":"Putzbrunn",
    "sg:phone":"+49 89/604315",
    "sg:postcode":"85640",
    "sg:province":"Bayern",
    "wof:name":"Manfred Schierle Ms Textilvertretungen",
    "wof:placetype":"venue"
},
  "geometry": {"coordinates":[11.6920309067,48.0754165649],"type":"Point"}
}