{
  "type": "Feature",
  "properties": {
    "iso:country":"DE",
    "sg:address":"Rosenaustr. 38",
    "sg:city":"Stuttgart",
    "sg:phone":"+49 711/5498370",
    "sg:postcode":"70376",
    "sg:province":"Baden-W\u00fcrttemberg",
    "wof:name":"G. Zachiridis",
    "wof:placetype":"venue"
},
  "geometry": {"coordinates":[9.211278,48.809872],"type":"Point"}
}