{
  "type": "Feature",
  "properties": {
    "iso:country":"DE",
    "sg:address":"Tarpenring 7",
    "sg:city":"Hamburg",
    "sg:phone":"+49 40/5287200",
    "sg:postcode":"22419",
    "sg:province":"Hamburg",
    "wof:name":"Carstensen Import-export Handelsgesellschaft Mbh",
    "wof:placetype":"venue"
},
  "geometry": {"coordinates":[9.9998674393,53.6643714905],"type":"Point"}
}