{
  "type": "Feature",
  "properties": {
    "iso:country":"DE",
    "sg:address":"Steinerne Furt 75",
    "sg:city":"Augsburg",
    "sg:phone":"+49 821/7404317",
    "sg:postcode":"86167",
    "sg:province":"Bayern",
    "wof:name":"Hartmann",
    "wof:placetype":"venue"
},
  "geometry": {"coordinates":[10.9318552017,48.3959350586],"type":"Point"}
}