{
  "type": "Feature",
  "properties": {
    "iso:country":"DE",
    "sg:address":"Adalbert-Stifter-Str. 41",
    "sg:city":"Erkrath",
    "sg:phone":"+49 211/253629",
    "sg:postcode":"40699",
    "sg:province":"Nordrhein-Westfalen",
    "wof:name":"Horst Flach Elektroinstallation",
    "wof:placetype":"venue"
},
  "geometry": {"coordinates":[6.92634,51.203789],"type":"Point"}
}