{
  "type": "Feature",
  "properties": {
    "iso:country":"DE",
    "sg:address":"Cuxhavener Str. 9",
    "sg:city":"D\u00fcsseldorf",
    "sg:phone":"+49 211/308277",
    "sg:postcode":"40221",
    "sg:province":"Nordrhein-Westfalen",
    "wof:name":"Erich G\u00fcnther",
    "wof:placetype":"venue"
},
  "geometry": {"coordinates":[6.735608,51.214264],"type":"Point"}
}