{
  "type": "Feature",
  "properties": {
    "iso:country":"DE",
    "sg:address":"Fischzug 2",
    "sg:city":"Salzgitter",
    "sg:phone":"+49 5341/46101",
    "sg:postcode":"38226",
    "sg:province":"Niedersachsen",
    "wof:name":"California-kleidung",
    "wof:placetype":"venue"
},
  "geometry": {"coordinates":[10.331926,52.153034],"type":"Point"}
}