{
  "type": "Feature",
  "properties": {
    "iso:country":"DE",
    "sg:address":"Gro\u00dftalstr. 57",
    "sg:city":"Freiburg",
    "sg:phone":"+49 761/67603",
    "sg:postcode":"79117",
    "sg:province":"Baden-W\u00fcrttemberg",
    "wof:name":"Erwin Br\u00fcstle",
    "wof:placetype":"venue"
},
  "geometry": {"coordinates":[7.91186,47.973042],"type":"Point"}
}