{
  "type": "Feature",
  "properties": {
    "iso:country":"DE",
    "sg:address":"Marktplatz 14",
    "sg:city":"Reutlingen",
    "sg:phone":"+49 7121/330809",
    "sg:postcode":"72764",
    "sg:province":"Baden-W\u00fcrttemberg",
    "wof:name":"Elementi Gertruad Schranz E. K.",
    "wof:placetype":"venue"
},
  "geometry": {"coordinates":[9.210756,48.491581],"type":"Point"}
}