{
  "type": "Feature",
  "properties": {
    "iso:country":"DE",
    "sg:address":"Spervogelstr. 15",
    "sg:city":"Sinsheim",
    "sg:phone":"+49 7261/12130",
    "sg:postcode":"74889",
    "sg:province":"Baden-W\u00fcrttemberg",
    "wof:name":"Margit Ziesel",
    "wof:placetype":"venue"
},
  "geometry": {"coordinates":[8.87186,49.21653],"type":"Point"}
}