{
  "type": "Feature",
  "properties": {
    "iso:country":"DE",
    "sg:address":"Annabergstr. 10",
    "sg:city":"Rodeberg",
    "sg:phone":"+49 36026/90592",
    "sg:postcode":"99976",
    "sg:province":"Th\u00fcringen",
    "wof:name":"Michael Jakobi",
    "wof:placetype":"venue"
},
  "geometry": {"coordinates":[10.2978839874,51.2238388062],"type":"Point"}
}