{
  "type": "Feature",
  "properties": {
    "iso:country":"DE",
    "sg:address":"Guffertstr. 4",
    "sg:city":"M\u00fcnchen",
    "sg:postcode":"81825",
    "sg:province":"Bayern",
    "wof:name":"Street Food Gmbh",
    "wof:placetype":"venue"
},
  "geometry": {"coordinates":[11.6412467957,48.1181564331],"type":"Point"}
}