{
  "type": "Feature",
  "properties": {
    "iso:country":"DE",
    "sg:address":"Pfarrweg 2",
    "sg:city":"Kreuth",
    "sg:phone":"+49 8029/267",
    "sg:postcode":"83708",
    "sg:province":"Bayern",
    "wof:name":"Kath. Pfarramt St. Leonhard",
    "wof:placetype":"venue"
},
  "geometry": {"coordinates":[11.7423391342,47.6459236145],"type":"Point"}
}