{
  "type": "Feature",
  "properties": {
    "iso:country":"DE",
    "sg:address":"Marin Niem\u00f6ller Weg 2",
    "sg:city":"Neu Anspach",
    "sg:postcode":"61267",
    "sg:province":"Hessen",
    "wof:name":"Service Rund Um Das B\u00fcro",
    "wof:placetype":"venue"
},
  "geometry": {"coordinates":[8.511233,50.300892],"type":"Point"}
}