{
  "type": "Feature",
  "properties": {
    "iso:country":"DE",
    "sg:address":"Kormoranweg 27",
    "sg:city":"Wasserburg",
    "sg:phone":"+49 8071/51484",
    "sg:postcode":"83512",
    "sg:province":"Bayern",
    "wof:name":"Claus Dei\u00dfler Rechtsanwalt",
    "wof:placetype":"venue"
},
  "geometry": {"coordinates":[12.2081298828,48.0573310852],"type":"Point"}
}