{
  "type": "Feature",
  "properties": {
    "iso:country":"DE",
    "sg:address":"Bornknechtstr. 5",
    "sg:city":"Halle",
    "sg:phone":"+49 345/77900",
    "sg:postcode":"06108",
    "sg:province":"Sachsen-Anhalt",
    "wof:name":"Heizkraftwerk Halle- Trotha Gmbh",
    "wof:placetype":"venue"
},
  "geometry": {"coordinates":[11.964405,51.480545],"type":"Point"}
}