{
  "type": "Feature",
  "properties": {
    "iso:country":"DE",
    "sg:address":"Werlter Str. 41",
    "sg:city":"Lorup",
    "sg:phone":"+49 5954/445",
    "sg:postcode":"26901",
    "sg:province":"Niedersachsen",
    "wof:name":"H. Schwarte",
    "wof:placetype":"venue"
},
  "geometry": {"coordinates":[7.6453337669,52.914855957],"type":"Point"}
}