{
  "type": "Feature",
  "properties": {
    "iso:country":"DE",
    "sg:address":"Salierstr. 42",
    "sg:city":"R\u00f6merberg",
    "sg:phone":"+49 6232/85352",
    "sg:postcode":"67354",
    "sg:province":"Rheinland-Pfalz",
    "wof:name":"Bios Beratung In Organisation Und Software Gmbh",
    "wof:placetype":"venue"
},
  "geometry": {"coordinates":[8.4038715363,49.2829322815],"type":"Point"}
}