{
  "type": "Feature",
  "properties": {
    "iso:country":"DE",
    "sg:address":"Frauenstr. 4",
    "sg:city":"M\u00fcnchen",
    "sg:phone":"+49 89/265516",
    "sg:postcode":"80469",
    "sg:province":"Bayern",
    "wof:name":"Lotterleben Restaurant",
    "wof:placetype":"venue"
},
  "geometry": {"coordinates":[11.575838089,48.1344070435],"type":"Point"}
}