{
  "type": "Feature",
  "properties": {
    "iso:country":"DE",
    "sg:address":"Lehderstr. 16",
    "sg:city":"Berlin",
    "sg:phone":"+49 30/477910",
    "sg:postcode":"13086",
    "sg:province":"Berlin",
    "wof:name":"Detewe Kommunikationssysteme",
    "wof:placetype":"venue"
},
  "geometry": {"coordinates":[13.443778038,52.548866272],"type":"Point"}
}