{
  "type": "Feature",
  "properties": {
    "iso:country":"DE",
    "sg:address":"Kanalstr. 57",
    "sg:city":"Senden",
    "sg:phone":"+49 2597/98770",
    "sg:postcode":"48308",
    "sg:province":"Nordrhein-Westfalen",
    "wof:name":"Porschmann & Waldmann",
    "wof:placetype":"venue"
},
  "geometry": {"coordinates":[7.483744,51.849449],"type":"Point"}
}