{
  "type": "Feature",
  "properties": {
    "iso:country":"DE",
    "sg:address":"Schlo\u00dfstr. 25",
    "sg:city":"Berlin",
    "sg:phone":"+49 30/7931928",
    "sg:postcode":"12163",
    "sg:province":"Berlin",
    "wof:name":"Runners Point",
    "wof:placetype":"venue"
},
  "geometry": {"coordinates":[13.322864,52.459465],"type":"Point"}
}