{
  "type": "Feature",
  "properties": {
    "iso:country":"DE",
    "sg:address":"Kohlhof 9",
    "sg:city":"Limburgerhof",
    "sg:postcode":"67117",
    "sg:province":"Rheinland-Pfalz",
    "wof:name":"Gastst\u00e4tte Sonne",
    "wof:placetype":"venue"
},
  "geometry": {"coordinates":[8.3901376724,49.403175354],"type":"Point"}
}