{
  "type": "Feature",
  "properties": {
    "iso:country":"DE",
    "sg:address":"Wagnerwirtsgasse 8",
    "sg:city":"Ingolstadt",
    "sg:phone":"+49 841/1328",
    "sg:postcode":"85049",
    "sg:province":"Bayern",
    "wof:name":"Arne Gietl Rechtsanwalt",
    "wof:placetype":"venue"
},
  "geometry": {"coordinates":[11.4233617783,48.7612609863],"type":"Point"}
}