{
  "type": "Feature",
  "properties": {
    "iso:country":"DE",
    "sg:address":"Pfalzburger Str. 214",
    "sg:city":"Bremen",
    "sg:phone":"+49 4942/1453208",
    "sg:postcode":"28207",
    "sg:province":"Bremen",
    "wof:name":"Austermeier Gmbh & Co. Kg",
    "wof:placetype":"venue"
},
  "geometry": {"coordinates":[8.8793716431,53.0610389709],"type":"Point"}
}