{
  "type": "Feature",
  "properties": {
    "iso:country":"DE",
    "sg:address":"Wolfsb\u00fchler Str. 5",
    "sg:city":"Wilburgstetten",
    "sg:phone":"+49 9853/892",
    "sg:postcode":"91634",
    "sg:province":"Bayern",
    "wof:name":"F. Beck",
    "wof:placetype":"venue"
},
  "geometry": {"coordinates":[10.4056406021,49.0231628418],"type":"Point"}
}