{
  "type": "Feature",
  "properties": {
    "iso:country":"DE",
    "sg:address":"Weckmarkt 3",
    "sg:city":"Frankfurt",
    "sg:phone":"+49 69/291034",
    "sg:postcode":"60311",
    "sg:province":"Hessen",
    "wof:name":"Mobilia Alles Aus Einer Hand Immobilien- Und Finanz-",
    "wof:placetype":"venue"
},
  "geometry": {"coordinates":[8.6867160797,50.1103897095],"type":"Point"}
}