{
  "type": "Feature",
  "properties": {
    "iso:country":"DE",
    "sg:address":"Hanauer Str. 1",
    "sg:city":"Alzenau",
    "sg:phone":"+49 6023/502160",
    "sg:postcode":"63755",
    "sg:province":"Bayern",
    "wof:name":"Stadtarchiv",
    "wof:placetype":"venue"
},
  "geometry": {"coordinates":[9.072646,50.085907],"type":"Point"}
}