{
  "type": "Feature",
  "properties": {
    "iso:country":"DE",
    "sg:address":"Bergstr. 6",
    "sg:city":"Billerbeck",
    "sg:phone":"+49 2543/25789",
    "sg:postcode":"48727",
    "sg:province":"Nordrhein-Westfalen",
    "wof:name":"Mishra Import-export Gmbh",
    "wof:placetype":"venue"
},
  "geometry": {"coordinates":[7.300183773,51.9746665955],"type":"Point"}
}