{
  "type": "Feature",
  "properties": {
    "iso:country":"DE",
    "sg:address":"Brennerstr. 30",
    "sg:city":"Rinteln",
    "sg:phone":"+49 5751/3250",
    "sg:postcode":"31737",
    "sg:province":"Niedersachsen",
    "wof:name":"Ev. Pfarramt Ii St. Nicolai",
    "wof:placetype":"venue"
},
  "geometry": {"coordinates":[9.082868576,52.1874580383],"type":"Point"}
}