{
  "type": "Feature",
  "properties": {
    "iso:country":"DE",
    "sg:address":"Tibarg 28",
    "sg:city":"Hamburg",
    "sg:phone":"+49 40/582098",
    "sg:postcode":"22459",
    "sg:province":"Hamburg",
    "wof:name":"Bike-shop Buck",
    "wof:placetype":"venue"
},
  "geometry": {"coordinates":[9.951559,53.619213],"type":"Point"}
}