{
  "type": "Feature",
  "properties": {
    "iso:country":"DE",
    "sg:address":"Drakestr. 3",
    "sg:city":"D\u00fcsseldorf",
    "sg:phone":"+49 211/329977",
    "sg:postcode":"40545",
    "sg:province":"Nordrhein-Westfalen",
    "wof:name":"Rudolf Stratmann Rechtsanwalt",
    "wof:placetype":"venue"
},
  "geometry": {"coordinates":[6.7530050278,51.2307052612],"type":"Point"}
}