{
  "type": "Feature",
  "properties": {
    "iso:country":"DE",
    "sg:address":"Eberswalder Str. 92",
    "sg:city":"Britz",
    "sg:phone":"+49 3334/42516",
    "sg:postcode":"16230",
    "sg:province":"Brandenburg",
    "wof:name":"Fleischerei Mai Gmbh",
    "wof:placetype":"venue"
},
  "geometry": {"coordinates":[13.8209104538,52.8743362427],"type":"Point"}
}