{
  "type": "Feature",
  "properties": {
    "iso:country":"DE",
    "sg:address":"Knorrstr. 15",
    "sg:city":"Neustadt",
    "sg:phone":"+49 9602/7092",
    "sg:postcode":"92660",
    "sg:province":"Bayern",
    "wof:name":"Volksbank Weiden Eg",
    "wof:placetype":"venue"
},
  "geometry": {"coordinates":[12.173908,49.731533],"type":"Point"}
}