{
  "type": "Feature",
  "properties": {
    "iso:country":"DE",
    "sg:address":"Am Weinberg 22",
    "sg:city":"Ranstadt",
    "sg:phone":"+49 6035/920072",
    "sg:postcode":"63691",
    "sg:province":"Hessen",
    "wof:name":"Martin Goldmann",
    "wof:placetype":"venue"
},
  "geometry": {"coordinates":[8.9426259995,50.3626594543],"type":"Point"}
}