{
  "type": "Feature",
  "properties": {
    "iso:country":"DE",
    "sg:address":"Heinefelder Weg 12",
    "sg:city":"Brakel",
    "sg:phone":"+49 5272/1720",
    "sg:postcode":"33034",
    "sg:province":"Nordrhein-Westfalen",
    "wof:name":"Fischerh\u00fctte",
    "wof:placetype":"venue"
},
  "geometry": {"coordinates":[9.1872396469,51.7206573486],"type":"Point"}
}