{
  "type": "Feature",
  "properties": {
    "iso:country":"DE",
    "sg:address":"Barlachstr. 5",
    "sg:city":"Altenburg",
    "sg:phone":"+49 3447/81851",
    "sg:postcode":"04600",
    "sg:province":"Th\u00fcringen",
    "wof:name":"Pension Nord",
    "wof:placetype":"venue"
},
  "geometry": {"coordinates":[12.4213619232,50.9953575134],"type":"Point"}
}