{
  "type": "Feature",
  "properties": {
    "iso:country":"DE",
    "sg:address":"Ohl-D\u00f6rp 60",
    "sg:city":"Wrixum",
    "sg:phone":"+49 4681/8234",
    "sg:postcode":"25938",
    "sg:province":"Schleswig-Holstein",
    "wof:name":"Erich Schlender",
    "wof:placetype":"venue"
},
  "geometry": {"coordinates":[8.552843,54.699448],"type":"Point"}
}