{
  "type": "Feature",
  "properties": {
    "iso:country":"DE",
    "sg:address":"Pfaffenhalde 3",
    "sg:city":"Donzdorf",
    "sg:phone":"+49 7162/23686",
    "sg:postcode":"73072",
    "sg:province":"Baden-W\u00fcrttemberg",
    "wof:name":"Vereinsgastst\u00e4tte Sch\u00fctzen- Gesellschaft 1560 E. V.",
    "wof:placetype":"venue"
},
  "geometry": {"coordinates":[9.8104972839,48.6865692139],"type":"Point"}
}