{
  "type": "Feature",
  "properties": {
    "iso:country":"DE",
    "sg:address":"F\u00fcrther Str. 1",
    "sg:city":"Eckental",
    "sg:postcode":"90542",
    "sg:province":"Bayern",
    "wof:name":"Matthias Br\u00e4unlein Immobilienmakler",
    "wof:placetype":"venue"
},
  "geometry": {"coordinates":[11.1986627579,49.5727310181],"type":"Point"}
}