{
  "type": "Feature",
  "properties": {
    "iso:country":"DE",
    "sg:address":"Carl-Thiersch-Str. 3",
    "sg:city":"Erlangen",
    "sg:postcode":"91052",
    "sg:province":"Bayern",
    "wof:name":"Theim Gmbh",
    "wof:placetype":"venue"
},
  "geometry": {"coordinates":[11.0265960693,49.5939369202],"type":"Point"}
}