{
  "type": "Feature",
  "properties": {
    "iso:country":"DE",
    "sg:address":"Hauptstr. 5",
    "sg:city":"Schlemmin",
    "sg:phone":"+49 38225/734",
    "sg:postcode":"18320",
    "sg:province":"Mecklenburg-Vorpommern",
    "wof:name":"Landb\u00e4ckerei Bartelt Gmbh",
    "wof:placetype":"venue"
},
  "geometry": {"coordinates":[12.681917,54.22155],"type":"Point"}
}