{
  "type": "Feature",
  "properties": {
    "iso:country":"DE",
    "sg:address":"Sch\u00fctzenallee 11",
    "sg:city":"Bienenb\u00fcttel",
    "sg:phone":"+49 5823/7206",
    "sg:postcode":"29553",
    "sg:province":"Niedersachsen",
    "wof:name":"Nieders. Landesagentur Der Fahrlehrerversicherung Gmbh",
    "wof:placetype":"venue"
},
  "geometry": {"coordinates":[10.4807605743,53.1430664062],"type":"Point"}
}