{
  "type": "Feature",
  "properties": {
    "iso:country":"DE",
    "sg:address":"An der Wiesent 3",
    "sg:city":"Ebermannstadt",
    "sg:phone":"+49 9194/8388",
    "sg:postcode":"91320",
    "sg:province":"Bayern",
    "wof:name":"Hans-hugo Faltermaier Heilpraktiker",
    "wof:placetype":"venue"
},
  "geometry": {"coordinates":[11.1869363785,49.7780075073],"type":"Point"}
}