{
  "type": "Feature",
  "properties": {
    "iso:country":"DE",
    "sg:address":"Gutenbergstr. 21-32",
    "sg:city":"W\u00f6rrstadt",
    "sg:postcode":"55286",
    "sg:province":"Rheinland-Pfalz",
    "wof:name":"Thimm Display Service Gmbh",
    "wof:placetype":"venue"
},
  "geometry": {"coordinates":[8.118564,49.850803],"type":"Point"}
}