{
  "type": "Feature",
  "properties": {
    "iso:country":"DE",
    "sg:address":"Campestr. 7",
    "sg:city":"Braunschweig",
    "sg:phone":"+49 531/238330",
    "sg:postcode":"38102",
    "sg:province":"Niedersachsen",
    "wof:name":"Alcatel Sel Ag",
    "wof:placetype":"venue"
},
  "geometry": {"coordinates":[10.5304822922,52.2558326721],"type":"Point"}
}