{
  "type": "Feature",
  "properties": {
    "iso:country":"DE",
    "sg:address":"In den Almen 17",
    "sg:city":"Bad D\u00fcrkheim",
    "sg:phone":"+49 6322/2921",
    "sg:postcode":"67098",
    "sg:province":"Rheinland-Pfalz",
    "wof:name":"Rudolf Freunscht Weinanbau",
    "wof:placetype":"venue"
},
  "geometry": {"coordinates":[8.196685791,49.4713897705],"type":"Point"}
}