{
  "type": "Feature",
  "properties": {
    "iso:country":"DE",
    "sg:address":"Neuffener Str. 29",
    "sg:city":"N\u00fcrtingen",
    "sg:postcode":"72622",
    "sg:province":"Baden-W\u00fcrttemberg",
    "wof:name":"B.s.steel-business Gmbh",
    "wof:placetype":"venue"
},
  "geometry": {"coordinates":[9.343148,48.62318],"type":"Point"}
}