{
  "type": "Feature",
  "properties": {
    "iso:country":"DE",
    "sg:address":"Am Bahndamm 17",
    "sg:city":"R\u00f6thenbach",
    "sg:postcode":"90552",
    "sg:province":"Bayern",
    "wof:name":"K. Von Irblich Anlageberater",
    "wof:placetype":"venue"
},
  "geometry": {"coordinates":[11.2457256317,49.4834098816],"type":"Point"}
}