{
  "type": "Feature",
  "properties": {
    "iso:country":"DE",
    "sg:address":"Scheyrer Str.",
    "sg:city":"Jetzendorf",
    "sg:postcode":"85305",
    "sg:province":"Bayern",
    "wof:name":"Katholisches Pfarramt Mari\u00e4 Heimsuchung",
    "wof:placetype":"venue"
},
  "geometry": {"coordinates":[11.3721237183,48.449508667],"type":"Point"}
}