{
  "type": "Feature",
  "properties": {
    "iso:country":"DE",
    "sg:address":"Feldstr. 67 a",
    "sg:city":"Lutherstadt Wittenberg",
    "sg:phone":"+49 3491/412777",
    "sg:postcode":"06886",
    "sg:province":"Sachsen-Anhalt",
    "wof:name":"Manfred Kulbe",
    "wof:placetype":"venue"
},
  "geometry": {"coordinates":[12.6325702667,51.877658844],"type":"Point"}
}