{
  "type": "Feature",
  "properties": {
    "iso:country":"DE",
    "sg:address":"Geschwister-Scholl-Stra\u00dfe 24D",
    "sg:city":"Stuttgart",
    "sg:phone":"+49 711",
    "sg:postcode":"70174",
    "sg:province":"Baden-W\u00fcrttemberg",
    "wof:name":"Iagb-homepage",
    "wof:placetype":"venue"
},
  "geometry": {"coordinates":[9.176316,48.782761],"type":"Point"}
}