{
  "type": "Feature",
  "properties": {
    "iso:country":"DE",
    "sg:address":"Krahnstr. 6",
    "sg:city":"Osnabr\u00fcck",
    "sg:phone":"+49 541/335300",
    "sg:postcode":"49074",
    "sg:province":"Niedersachsen",
    "wof:name":"Dr. Horst Simon Und Gabriele Lausch",
    "wof:placetype":"venue"
},
  "geometry": {"coordinates":[8.041639328,52.276599884],"type":"Point"}
}