{
  "type": "Feature",
  "properties": {
    "iso:country":"DE",
    "sg:address":"Markt 16",
    "sg:city":"W\u00fcrselen",
    "sg:phone":"+49 2405/93296",
    "sg:postcode":"52146",
    "sg:province":"Nordrhein-Westfalen",
    "wof:name":"Manfred Quandel",
    "wof:placetype":"venue"
},
  "geometry": {"coordinates":[6.133121,50.818085],"type":"Point"}
}