{
  "type": "Feature",
  "properties": {
    "iso:country":"DE",
    "sg:address":"Hans-Sachs-Str. 29",
    "sg:city":"Oberhausen",
    "sg:phone":"+49 208/896907",
    "sg:postcode":"46117",
    "sg:province":"Nordrhein-Westfalen",
    "wof:name":"K.-h. Niederstein",
    "wof:placetype":"venue"
},
  "geometry": {"coordinates":[6.8828349113,51.502456665],"type":"Point"}
}