{
  "type": "Feature",
  "properties": {
    "iso:country":"DE",
    "sg:address":"Robert-Bosch-Str. 15-17",
    "sg:city":"Maintal",
    "sg:phone":"+49 6181/493016",
    "sg:postcode":"63477",
    "sg:province":"Hessen",
    "wof:name":"Heinrich Burger Baudekoration Gmbh",
    "wof:placetype":"venue"
},
  "geometry": {"coordinates":[8.86154,50.131317],"type":"Point"}
}