{
  "type": "Feature",
  "properties": {
    "iso:country":"DE",
    "sg:address":"Rolfsen Nr. 16",
    "sg:city":"Soderstorf",
    "sg:phone":"+49 4172/7448",
    "sg:postcode":"21388",
    "sg:province":"Niedersachsen",
    "wof:name":"Gisela Alich",
    "wof:placetype":"venue"
},
  "geometry": {"coordinates":[10.1456212997,53.1423225403],"type":"Point"}
}