{
  "type": "Feature",
  "properties": {
    "iso:country":"DE",
    "sg:city":"M\u00f6rfelden-Walldorf",
    "sg:postcode":"64546",
    "sg:province":"Hessen",
    "wof:name":"Eleonore Blasberg Gmbh",
    "wof:placetype":"venue"
},
  "geometry": {"coordinates":[8.569015,49.974266],"type":"Point"}
}