{
  "type": "Feature",
  "properties": {
    "iso:country":"DE",
    "sg:address":"August-Bebel-Str. 5",
    "sg:city":"G\u00f6\u00dfnitz",
    "sg:phone":"+49 34493/22490",
    "sg:postcode":"04639",
    "sg:province":"Th\u00fcringen",
    "wof:name":"F. Am Ende",
    "wof:placetype":"venue"
},
  "geometry": {"coordinates":[12.4315071106,50.8893585205],"type":"Point"}
}