{
  "type": "Feature",
  "properties": {
    "iso:country":"DE",
    "sg:address":"David-R\u00f6ntgen-Str. 3",
    "sg:city":"Koblenz",
    "sg:phone":"+49 261/460230",
    "sg:postcode":"56073",
    "sg:province":"Rheinland-Pfalz",
    "wof:name":"Fritz M\u00fcller Gmbh",
    "wof:placetype":"venue"
},
  "geometry": {"coordinates":[7.5846328735,50.3589096069],"type":"Point"}
}