{
  "type": "Feature",
  "properties": {
    "iso:country":"DE",
    "sg:address":"Friedrichstr. 7",
    "sg:city":"Wittlich",
    "sg:phone":"+49 6571/4015",
    "sg:postcode":"54516",
    "sg:province":"Rheinland-Pfalz",
    "wof:name":"Kutscheid Und Ma\u00dfem Rechtsanw\u00e4lte",
    "wof:placetype":"venue"
},
  "geometry": {"coordinates":[6.8925600052,49.9875183105],"type":"Point"}
}