{
  "type": "Feature",
  "properties": {
    "iso:country":"DE",
    "sg:address":"Hannoversche Str. 69 Koerne",
    "sg:city":"Dortmund",
    "sg:phone":"+49 4923/1593010",
    "sg:postcode":"44143",
    "sg:province":"Nordrhein-Westfalen",
    "wof:name":"Verzinkerei Dortmund Kaufmann Gmbh & Co Kg",
    "wof:placetype":"venue"
},
  "geometry": {"coordinates":[7.523494,51.521053],"type":"Point"}
}