{
  "type": "Feature",
  "properties": {
    "iso:country":"DE",
    "sg:address":"Salzstr. 11",
    "sg:city":"Hanau",
    "sg:phone":"+49 6181/252147",
    "sg:postcode":"63450",
    "sg:province":"Hessen",
    "wof:name":"Ahorn-apotheke",
    "wof:placetype":"venue"
},
  "geometry": {"coordinates":[8.920846,50.133003],"type":"Point"}
}