{
  "type": "Feature",
  "properties": {
    "iso:country":"DE",
    "sg:address":"Seulberger Str. 12d",
    "sg:city":"Bad Homburg",
    "sg:phone":"+49 6172/451150",
    "sg:postcode":"61352",
    "sg:province":"Hessen",
    "wof:name":"Peter Zanner",
    "wof:placetype":"venue"
},
  "geometry": {"coordinates":[8.6763010025,50.225982666],"type":"Point"}
}