{
  "type": "Feature",
  "properties": {
    "iso:country":"DE",
    "sg:address":"Schnaitheimer Str. 167",
    "sg:city":"Heidenheim",
    "sg:phone":"+49 7321/93570",
    "sg:postcode":"89520",
    "sg:province":"Baden-W\u00fcrttemberg",
    "wof:name":"Autopark Haz Beteiligungs Gmbh",
    "wof:placetype":"venue"
},
  "geometry": {"coordinates":[10.155332,48.690334],"type":"Point"}
}