{
  "type": "Feature",
  "properties": {
    "iso:country":"DE",
    "sg:address":"Bahnhofstr. 84",
    "sg:city":"R\u00f6dinghausen",
    "sg:phone":"+49 5746/8251",
    "sg:postcode":"32289",
    "sg:province":"Nordrhein-Westfalen",
    "wof:name":"Walter Eilhard",
    "wof:placetype":"venue"
},
  "geometry": {"coordinates":[8.5227003098,52.23487854],"type":"Point"}
}