{
  "type": "Feature",
  "properties": {
    "iso:country":"DE",
    "sg:address":"Breite Str. 13",
    "sg:city":"Bremen",
    "sg:phone":"+49 421/662213",
    "sg:postcode":"28757",
    "sg:province":"Bremen",
    "wof:name":"Blumen Rogge Inh. Heike Sudholz",
    "wof:placetype":"venue"
},
  "geometry": {"coordinates":[8.62758,53.170986],"type":"Point"}
}