{
  "type": "Feature",
  "properties": {
    "iso:country":"DE",
    "sg:address":"Julius-Ludowieg-Str 21b",
    "sg:city":"Hamburg",
    "sg:phone":"+49 40/777149",
    "sg:postcode":"21073",
    "sg:province":"Hamburg",
    "wof:name":"Dierk Eisenschmidt",
    "wof:placetype":"venue"
},
  "geometry": {"coordinates":[9.977112,53.459499],"type":"Point"}
}