{
  "type": "Feature",
  "properties": {
    "iso:country":"DE",
    "sg:address":"Asternweg 5",
    "sg:city":"Auenwald",
    "sg:phone":"+49 7191/51369",
    "sg:postcode":"71549",
    "sg:province":"Baden-W\u00fcrttemberg",
    "wof:name":"Helmut Schock",
    "wof:placetype":"venue"
},
  "geometry": {"coordinates":[9.510692,48.9576],"type":"Point"}
}