{
  "type": "Feature",
  "properties": {
    "iso:country":"DE",
    "sg:address":"Rathausstr. 13",
    "sg:city":"Klingenberg",
    "sg:phone":"+49 9372/2512",
    "sg:postcode":"63911",
    "sg:province":"Bayern",
    "wof:name":"Kaiser Mode Und Sport Hermann Kaiser E. K.",
    "wof:placetype":"venue"
},
  "geometry": {"coordinates":[9.181878,49.783161],"type":"Point"}
}