{
  "type": "Feature",
  "properties": {
    "iso:country":"DE",
    "sg:address":"Industriestr. 20",
    "sg:city":"Meckesheim",
    "sg:phone":"+49 6226/8421",
    "sg:postcode":"74909",
    "sg:province":"Baden-W\u00fcrttemberg",
    "wof:name":"Printed Motors Gmbh",
    "wof:placetype":"venue"
},
  "geometry": {"coordinates":[8.808501,49.324787],"type":"Point"}
}