{
  "type": "Feature",
  "properties": {
    "iso:country":"DE",
    "sg:address":"Bloher Landstr. 2",
    "sg:city":"Bad Zwischenahn",
    "sg:phone":"+49 441/69481",
    "sg:postcode":"26160",
    "sg:province":"Niedersachsen",
    "wof:name":"Dr. Med. Erich Hofer",
    "wof:placetype":"venue"
},
  "geometry": {"coordinates":[8.1399021149,53.1591911316],"type":"Point"}
}