{
  "type": "Feature",
  "properties": {
    "iso:country":"DE",
    "sg:address":"Im Ort 2",
    "sg:city":"Rullstorf",
    "sg:phone":"+49 4136/1301",
    "sg:postcode":"21379",
    "sg:province":"Niedersachsen",
    "wof:name":"Gastst\u00e4tte L. Vo\u00df",
    "wof:placetype":"venue"
},
  "geometry": {"coordinates":[10.5049085617,53.2879447937],"type":"Point"}
}