{
  "type": "Feature",
  "properties": {
    "iso:country":"DE",
    "sg:address":"Weserstr. 82",
    "sg:city":"Bremen",
    "sg:phone":"+49 421/662319",
    "sg:postcode":"28757",
    "sg:province":"Bremen",
    "wof:name":"Johann Graubohm",
    "wof:placetype":"venue"
},
  "geometry": {"coordinates":[8.614599,53.172085],"type":"Point"}
}