{
  "type": "Feature",
  "properties": {
    "iso:country":"DE",
    "sg:address":"Lange Str. 33",
    "sg:city":"Finsterwalde",
    "sg:phone":"+49 3531/8215",
    "sg:postcode":"03238",
    "sg:province":"Brandenburg",
    "wof:name":"G. M\u00fcller",
    "wof:placetype":"venue"
},
  "geometry": {"coordinates":[13.714814,51.628174],"type":"Point"}
}