{
  "type": "Feature",
  "properties": {
    "iso:country":"DE",
    "sg:address":"Im Steiner 2/4",
    "sg:city":"Kleinheubach",
    "sg:phone":"+49 9371/940247",
    "sg:postcode":"63924",
    "sg:province":"Bayern",
    "wof:name":"Erbacher Gmbh & Co Betriebs Kg",
    "wof:placetype":"venue"
},
  "geometry": {"coordinates":[9.221133,49.714275],"type":"Point"}
}