{
  "type": "Feature",
  "properties": {
    "iso:country":"DE",
    "sg:address":"Poststr. 6",
    "sg:city":"Winterberg",
    "sg:phone":"+49 2981/7736",
    "sg:postcode":"59955",
    "sg:province":"Nordrhein-Westfalen",
    "wof:name":"Allfrisch",
    "wof:placetype":"venue"
},
  "geometry": {"coordinates":[8.5335960388,51.193157196],"type":"Point"}
}