{
  "type": "Feature",
  "properties": {
    "iso:country":"DE",
    "sg:address":"Oderbruchstr. 11",
    "sg:city":"Berlin",
    "sg:postcode":"10407",
    "sg:province":"Berlin",
    "wof:name":"Detectiv-b\u00fcro Inh. Liane M\u00fcller",
    "wof:placetype":"venue"
},
  "geometry": {"coordinates":[13.461342,52.530563],"type":"Point"}
}