{
  "type": "Feature",
  "properties": {
    "iso:country":"DE",
    "sg:address":"Kirchstr. 3",
    "sg:city":"Me\u00dfkirch",
    "sg:phone":"+49 7575/4048",
    "sg:postcode":"88605",
    "sg:province":"Baden-W\u00fcrttemberg",
    "wof:name":"Hospiz Bewegung",
    "wof:placetype":"venue"
},
  "geometry": {"coordinates":[9.110575,47.993771],"type":"Point"}
}