{
  "type": "Feature",
  "properties": {
    "iso:country":"DE",
    "sg:address":"Wimpfener Str. 4",
    "sg:city":"Stuttgart",
    "sg:postcode":"70435",
    "sg:province":"Baden-W\u00fcrttemberg",
    "wof:name":"Monien & Franke Gmbh",
    "wof:placetype":"venue"
},
  "geometry": {"coordinates":[9.161413,48.838757],"type":"Point"}
}