{
  "type": "Feature",
  "properties": {
    "iso:country":"DE",
    "sg:address":"Erlweg 4",
    "sg:city":"Eurasburg",
    "sg:phone":"+49 8179/305",
    "sg:postcode":"82547",
    "sg:province":"Bayern",
    "wof:name":"E. Huber",
    "wof:placetype":"venue"
},
  "geometry": {"coordinates":[11.4081707001,47.8301086426],"type":"Point"}
}