{
  "type": "Feature",
  "properties": {
    "iso:country":"DE",
    "sg:address":"Pausitzer Str. 34",
    "sg:city":"Riesa",
    "sg:phone":"+49 3525/632165",
    "sg:postcode":"01589",
    "sg:province":"Sachsen",
    "wof:name":"Sportlerklause",
    "wof:placetype":"venue"
},
  "geometry": {"coordinates":[13.3140363693,51.2870445251],"type":"Point"}
}