{
  "type": "Feature",
  "properties": {
    "iso:country":"DE",
    "sg:address":"Ringstr. 22",
    "sg:city":"Erdmannhausen",
    "sg:phone":"+49 7144/38542",
    "sg:postcode":"71729",
    "sg:province":"Baden-W\u00fcrttemberg",
    "wof:name":"P. Und J. Weber",
    "wof:placetype":"venue"
},
  "geometry": {"coordinates":[9.296323,48.946083],"type":"Point"}
}