{
  "type": "Feature",
  "properties": {
    "iso:country":"DE",
    "sg:address":"An der Ladestr. 1",
    "sg:city":"Korschenbroich",
    "sg:phone":"+49 2161/67489",
    "sg:postcode":"41352",
    "sg:province":"Nordrhein-Westfalen",
    "wof:name":"Feracier Eisen- Und Stahl- Handelsges. Mbh",
    "wof:placetype":"venue"
},
  "geometry": {"coordinates":[6.520115,51.188591],"type":"Point"}
}