{
  "type": "Feature",
  "properties": {
    "iso:country":"DE",
    "sg:address":"Kappel",
    "sg:city":"Kappel",
    "sg:phone":"+49 7822/6590",
    "sg:postcode":"77966",
    "sg:province":"Baden-W\u00fcrttemberg",
    "wof:name":"Sparkasse Lahr-ettenheim",
    "wof:placetype":"venue"
},
  "geometry": {"coordinates":[7.73777,48.291599],"type":"Point"}
}