{
  "type": "Feature",
  "properties": {
    "iso:country":"DE",
    "sg:address":"Leipziger Str. 84",
    "sg:city":"Penig",
    "sg:phone":"+49 37381/9915",
    "sg:postcode":"09322",
    "sg:province":"Sachsen",
    "wof:name":"Peniger Mahlwerk Gmbh",
    "wof:placetype":"venue"
},
  "geometry": {"coordinates":[12.6961297989,50.9384117126],"type":"Point"}
}