{
  "type": "Feature",
  "properties": {
    "iso:country":"DE",
    "sg:address":"Altefelds Holz 4",
    "sg:city":"Nordkirchen",
    "sg:phone":"+49 2596/742",
    "sg:postcode":"59394",
    "sg:province":"Nordrhein-Westfalen",
    "wof:name":"Felix Neuhaus",
    "wof:placetype":"venue"
},
  "geometry": {"coordinates":[7.582738,51.735748],"type":"Point"}
}