{
  "type": "Feature",
  "properties": {
    "iso:country":"DE",
    "sg:address":"Industriestr. 40",
    "sg:city":"Althengstett",
    "sg:phone":"+49 7051/20056",
    "sg:postcode":"75382",
    "sg:province":"Baden-W\u00fcrttemberg",
    "wof:name":"Ernst Rottke Gmbh",
    "wof:placetype":"venue"
},
  "geometry": {"coordinates":[8.782993,48.724373],"type":"Point"}
}