{
  "type": "Feature",
  "properties": {
    "iso:country":"DE",
    "sg:address":"Dorfstr. 14",
    "sg:city":"Apolda",
    "sg:phone":"+49 3644/619796",
    "sg:postcode":"99510",
    "sg:province":"Th\u00fcringen",
    "wof:name":"Bed Baustoffhandel Elementeproduktion Und",
    "wof:placetype":"venue"
},
  "geometry": {"coordinates":[11.479031,51.021553],"type":"Point"}
}