{
  "type": "Feature",
  "properties": {
    "iso:country":"DE",
    "sg:address":"Bahnhofstr. 18",
    "sg:city":"Bayreuth",
    "sg:phone":"+49 921/23150",
    "sg:postcode":"95444",
    "sg:province":"Bayern",
    "wof:name":"Blumen Meyer Inh. Meinert Meyer",
    "wof:placetype":"venue"
},
  "geometry": {"coordinates":[11.579762,49.949303],"type":"Point"}
}