{
  "type": "Feature",
  "properties": {
    "iso:country":"DE",
    "sg:address":"Ungerstr. 8",
    "sg:city":"Celle",
    "sg:phone":"+49 5141/25477",
    "sg:postcode":"29221",
    "sg:province":"Niedersachsen",
    "wof:name":"Ilse Gutzmer",
    "wof:placetype":"venue"
},
  "geometry": {"coordinates":[10.0644569397,52.6101570129],"type":"Point"}
}