{
  "type": "Feature",
  "properties": {
    "iso:country":"DE",
    "sg:address":"Hermsdorfer Damm 221",
    "sg:city":"Berlin",
    "sg:phone":"+49 30/4041109",
    "sg:postcode":"13467",
    "sg:province":"Berlin",
    "wof:name":"Esso Deutschland Gmbh",
    "wof:placetype":"venue"
},
  "geometry": {"coordinates":[13.3126087189,52.6224746704],"type":"Point"}
}