{
  "type": "Feature",
  "properties": {
    "iso:country":"DE",
    "sg:address":"Damaschkeweg 6",
    "sg:city":"Coswig",
    "sg:postcode":"06869",
    "sg:province":"Sachsen-Anhalt",
    "wof:name":"I. Grasshoff",
    "wof:placetype":"venue"
},
  "geometry": {"coordinates":[12.473764,51.874825],"type":"Point"}
}