{
  "type": "Feature",
  "properties": {
    "iso:country":"DE",
    "sg:address":"Bergstr. 13",
    "sg:city":"Grafenberg",
    "sg:phone":"+49 7123/31065",
    "sg:postcode":"72661",
    "sg:province":"Baden-W\u00fcrttemberg",
    "wof:name":"Irmgard Keppler Steuerbevollm\u00e4chtigte",
    "wof:placetype":"venue"
},
  "geometry": {"coordinates":[9.3056726456,48.5681991577],"type":"Point"}
}