{
  "type": "Feature",
  "properties": {
    "iso:country":"DE",
    "sg:address":"Wildgartenstr. 21",
    "sg:city":"Mitterteich",
    "sg:phone":"+49 9633/1357",
    "sg:postcode":"95666",
    "sg:province":"Bayern",
    "wof:name":"Karl-heinz Amft",
    "wof:placetype":"venue"
},
  "geometry": {"coordinates":[12.2406396866,49.945274353],"type":"Point"}
}