{
  "type": "Feature",
  "properties": {
    "iso:country":"DE",
    "sg:address":"Kirchenstr. 18",
    "sg:city":"Gr\u00f6mitz",
    "sg:phone":"+49 4562/9892",
    "sg:postcode":"23743",
    "sg:province":"Schleswig-Holstein",
    "wof:name":"P. Arff",
    "wof:placetype":"venue"
},
  "geometry": {"coordinates":[10.959167,54.149445],"type":"Point"}
}