{
  "type": "Feature",
  "properties": {
    "iso:country":"DE",
    "sg:address":"Burgplatz 5",
    "sg:city":"Bautzen",
    "sg:postcode":"02625",
    "sg:province":"Sachsen",
    "wof:name":"R\u00f6sner Verwaltungs Gmbh",
    "wof:placetype":"venue"
},
  "geometry": {"coordinates":[14.420843,51.182598],"type":"Point"}
}