{
  "type": "Feature",
  "properties": {
    "iso:country":"DE",
    "sg:address":"Hauptstr. 4",
    "sg:city":"Gronau",
    "sg:phone":"+49 5182/4747",
    "sg:postcode":"31028",
    "sg:province":"Niedersachsen",
    "wof:name":"Norbert Kosinski Heilpraktiker",
    "wof:placetype":"venue"
},
  "geometry": {"coordinates":[8.7810974121,50.1943321228],"type":"Point"}
}