{
  "type": "Feature",
  "properties": {
    "iso:country":"DE",
    "sg:address":"Sternstr. 13",
    "sg:city":"Uelzen",
    "sg:phone":"+49 581/6329",
    "sg:postcode":"29525",
    "sg:province":"Niedersachsen",
    "wof:name":"Am Stern",
    "wof:placetype":"venue"
},
  "geometry": {"coordinates":[10.547129631,52.97082901],"type":"Point"}
}