{
  "type": "Feature",
  "properties": {
    "iso:country":"DE",
    "sg:address":"Ringstr. 120",
    "sg:city":"Petershagen",
    "sg:phone":"+49 5707/474",
    "sg:postcode":"32469",
    "sg:province":"Nordrhein-Westfalen",
    "wof:name":"Wilhelm Buhre Gmbh & Co. Kg",
    "wof:placetype":"venue"
},
  "geometry": {"coordinates":[8.970995903,52.4206962585],"type":"Point"}
}