{
  "type": "Feature",
  "properties": {
    "iso:country":"DE",
    "sg:address":"Weinreb 8",
    "sg:city":"Wiesbaden",
    "sg:phone":"+49 611/560432",
    "sg:postcode":"65191",
    "sg:province":"Hessen",
    "wof:name":"Kurt Huniek",
    "wof:placetype":"venue"
},
  "geometry": {"coordinates":[8.268908,50.092575],"type":"Point"}
}