{
  "type": "Feature",
  "properties": {
    "iso:country":"DE",
    "sg:address":"Nachtigallenweg 14",
    "sg:city":"Wuppertal",
    "sg:phone":"+49 2202/937360",
    "sg:postcode":"42349",
    "sg:province":"Nordrhein-Westfalen",
    "wof:name":"K\u00d6ttgen Kabelgarnituren Gmbh",
    "wof:placetype":"venue"
},
  "geometry": {"coordinates":[7.12374,50.977009],"type":"Point"}
}