{
  "type": "Feature",
  "properties": {
    "iso:country":"DE",
    "sg:address":"L\u00fcbbecker Str. 123",
    "sg:city":"Kirchlengern",
    "sg:phone":"+49 5223/71892",
    "sg:postcode":"32278",
    "sg:province":"Nordrhein-Westfalen",
    "wof:name":"C. Schneider Steuerbevollm\u00e4chtigter",
    "wof:placetype":"venue"
},
  "geometry": {"coordinates":[8.6396799088,52.2048988342],"type":"Point"}
}