{
  "type": "Feature",
  "properties": {
    "iso:country":"DE",
    "sg:address":"Lehmkaul 9",
    "sg:city":"Bad M\u00fcnstereifel",
    "sg:postcode":"53902",
    "sg:province":"Nordrhein-Westfalen",
    "wof:name":"Reakon Gmbh",
    "wof:placetype":"venue"
},
  "geometry": {"coordinates":[6.756686,50.536919],"type":"Point"}
}