{
  "type": "Feature",
  "properties": {
    "iso:country":"DE",
    "sg:address":"W\u00f6rthstr. 22",
    "sg:city":"M\u00fcnchen",
    "sg:phone":"+49 89/4801989",
    "sg:postcode":"81667",
    "sg:province":"Bayern",
    "wof:name":"Peter Blachetzki Architekt",
    "wof:placetype":"venue"
},
  "geometry": {"coordinates":[11.600091,48.130138],"type":"Point"}
}