{
  "type": "Feature",
  "properties": {
    "iso:country":"DE",
    "sg:address":"Berliner Str. 5",
    "sg:city":"Friedberg",
    "sg:phone":"+49 6031/4500",
    "sg:postcode":"61169",
    "sg:province":"Hessen",
    "wof:name":"D\u00f6nges Saunabau",
    "wof:placetype":"venue"
},
  "geometry": {"coordinates":[8.728258,50.331142],"type":"Point"}
}