{
  "type": "Feature",
  "properties": {
    "iso:country":"DE",
    "sg:address":"Langenackerweg 2",
    "sg:city":"H\u00f6fen",
    "sg:phone":"+49 7081/5837",
    "sg:postcode":"75339",
    "sg:province":"Baden-W\u00fcrttemberg",
    "wof:name":"P. Mettler",
    "wof:placetype":"venue"
},
  "geometry": {"coordinates":[8.580511,48.798882],"type":"Point"}
}