{
  "type": "Feature",
  "properties": {
    "iso:country":"DE",
    "sg:address":"Eichhof",
    "sg:city":"Kalletal",
    "sg:phone":"+49 5264/9229",
    "sg:postcode":"32689",
    "sg:province":"Nordrhein-Westfalen",
    "wof:name":"Pflegedienst Zuhilfe Sad Lippe E. V.",
    "wof:placetype":"venue"
},
  "geometry": {"coordinates":[8.90128,52.100197],"type":"Point"}
}