{
  "type": "Feature",
  "properties": {
    "iso:country":"DE",
    "sg:address":"Mittelstr. 54",
    "sg:city":"Lemgo",
    "sg:phone":"+49 5261/13644",
    "sg:postcode":"32657",
    "sg:province":"Nordrhein-Westfalen",
    "wof:name":"Restaurant Marathon Inh. S. Gegas",
    "wof:placetype":"venue"
},
  "geometry": {"coordinates":[8.9016675949,52.028465271],"type":"Point"}
}