{
  "type": "Feature",
  "properties": {
    "iso:country":"DE",
    "sg:address":"St.-Wendelin-Str. 23",
    "sg:city":"B\u00fcrstadt",
    "sg:phone":"+49 6206/71436",
    "sg:postcode":"68642",
    "sg:province":"Hessen",
    "wof:name":"Hans-heinrich Hesse",
    "wof:placetype":"venue"
},
  "geometry": {"coordinates":[8.479856,49.628185],"type":"Point"}
}