{
  "type": "Feature",
  "properties": {
    "iso:country":"DE",
    "sg:address":"Rathausallee 72-76",
    "sg:city":"Norderstedt",
    "sg:phone":"+49 40/356160",
    "sg:postcode":"22846",
    "sg:province":"Schleswig-Holstein",
    "wof:name":"Opel Bank Gmbh",
    "wof:placetype":"venue"
},
  "geometry": {"coordinates":[9.990073204,53.7076644897],"type":"Point"}
}