{
  "type": "Feature",
  "properties": {
    "iso:country":"DE",
    "sg:address":"Fasanenweg 4",
    "sg:city":"Barsinghausen",
    "sg:phone":"+49 5105/8980",
    "sg:postcode":"30890",
    "sg:province":"Niedersachsen",
    "wof:name":"Klaus Mentzel",
    "wof:placetype":"venue"
},
  "geometry": {"coordinates":[9.4962377548,52.2954673767],"type":"Point"}
}