{
  "type": "Feature",
  "properties": {
    "iso:country":"DE",
    "sg:address":"Gerhart-Hauptmann-Str. 15",
    "sg:city":"Cottbus",
    "sg:postcode":"03044",
    "sg:province":"Brandenburg",
    "wof:name":"Ega Elektrische Geb\u00e4udeaus- R\u00fcstung Und Anlagenbau Gmbh",
    "wof:placetype":"venue"
},
  "geometry": {"coordinates":[14.345788002,51.7743797302],"type":"Point"}
}