{
  "type": "Feature",
  "properties": {
    "iso:country":"DE",
    "sg:address":"M\u00fchlweg 34",
    "sg:city":"Gerbrunn",
    "sg:phone":"+49 931/707033",
    "sg:postcode":"97218",
    "sg:province":"Bayern",
    "wof:name":"Fleckenstein H. G. Buch- U. Offsetdruckerei",
    "wof:placetype":"venue"
},
  "geometry": {"coordinates":[9.982727,49.782677],"type":"Point"}
}