{
  "type": "Feature",
  "properties": {
    "iso:country":"DE",
    "sg:address":"Ulrichstr. 28",
    "sg:city":"Abensberg",
    "sg:phone":"+49 9443/6958",
    "sg:postcode":"93326",
    "sg:province":"Bayern",
    "wof:name":"Claudia Brandl Das Fotoatelier",
    "wof:placetype":"venue"
},
  "geometry": {"coordinates":[11.8472414017,48.8156661987],"type":"Point"}
}