{
  "type": "Feature",
  "properties": {
    "iso:country":"DE",
    "sg:address":"Scheelenkamp 11",
    "sg:city":"Garbsen",
    "sg:phone":"+49 5131/49890",
    "sg:postcode":"30827",
    "sg:province":"Niedersachsen",
    "wof:name":"Inter. Food Td Tomasz Daniluk",
    "wof:placetype":"venue"
},
  "geometry": {"coordinates":[9.6162509918,52.432220459],"type":"Point"}
}