{
  "type": "Feature",
  "properties": {
    "iso:country":"DE",
    "sg:address":"Florianweg 39",
    "sg:city":"Frankfurt",
    "sg:phone":"+49 6109/35560",
    "sg:postcode":"60388",
    "sg:province":"Hessen",
    "wof:name":"Fritz Hauck",
    "wof:placetype":"venue"
},
  "geometry": {"coordinates":[8.7493753433,50.1479187012],"type":"Point"}
}