{
  "type": "Feature",
  "properties": {
    "iso:country":"DE",
    "sg:address":"Buscherbahn 27",
    "sg:city":"Erkelenz",
    "sg:phone":"+49 2431/74153",
    "sg:postcode":"41812",
    "sg:province":"Nordrhein-Westfalen",
    "wof:name":"J.-g. Friedrichs",
    "wof:placetype":"venue"
},
  "geometry": {"coordinates":[6.263548851,51.0931358337],"type":"Point"}
}