{
  "type": "Feature",
  "properties": {
    "iso:country":"DE",
    "sg:address":"Heusingerstr. 1",
    "sg:city":"Holzminden",
    "sg:phone":"+49 5531/3180",
    "sg:postcode":"37603",
    "sg:province":"Niedersachsen",
    "wof:name":"F\u00f6rstemann Garten- Und Landschaftsbau Gmbh",
    "wof:placetype":"venue"
},
  "geometry": {"coordinates":[9.470403,51.833519],"type":"Point"}
}