{
  "type": "Feature",
  "properties": {
    "iso:country":"DE",
    "sg:address":"M\u00fchlgraben 2",
    "sg:city":"Untersiemau",
    "sg:phone":"+49 9565/847",
    "sg:postcode":"96253",
    "sg:province":"Bayern",
    "wof:name":"Peter Matthe Immobilienmakler",
    "wof:placetype":"venue"
},
  "geometry": {"coordinates":[10.992764473,50.188747406],"type":"Point"}
}