{
  "type": "Feature",
  "properties": {
    "iso:country":"DE",
    "sg:address":"Ermlandstr. 90 A",
    "sg:city":"Isernhagen",
    "sg:phone":"+49 511/732797",
    "sg:postcode":"30916",
    "sg:province":"Niedersachsen",
    "wof:name":"Dr. Lothar Mehrkens Tierarzt",
    "wof:placetype":"venue"
},
  "geometry": {"coordinates":[9.8029794693,52.4574432373],"type":"Point"}
}