{
  "type": "Feature",
  "properties": {
    "iso:country":"DE",
    "sg:address":"Kleemeier Ring 10",
    "sg:city":"Petershagen",
    "sg:phone":"+49 5705/94090",
    "sg:postcode":"32469",
    "sg:province":"Nordrhein-Westfalen",
    "wof:name":"Br Baustoff Recycling Verwaltungsges. Mbh",
    "wof:placetype":"venue"
},
  "geometry": {"coordinates":[9.079409,52.435108],"type":"Point"}
}