{
  "type": "Feature",
  "properties": {
    "iso:country":"DE",
    "sg:address":"Ritterstr. 96",
    "sg:city":"Berlin",
    "sg:phone":"+49 30/61609034",
    "sg:postcode":"10969",
    "sg:province":"Berlin",
    "wof:name":"Dieter Groos",
    "wof:placetype":"venue"
},
  "geometry": {"coordinates":[13.406886,52.502312],"type":"Point"}
}