{
  "type": "Feature",
  "properties": {
    "iso:country":"DE",
    "sg:address":"R\u00f6merstr. 15",
    "sg:city":"Kobern-Gondorf",
    "sg:phone":"+49 2607/4619",
    "sg:postcode":"56330",
    "sg:province":"Rheinland-Pfalz",
    "wof:name":"Hoersch-haupt Weinanbau",
    "wof:placetype":"venue"
},
  "geometry": {"coordinates":[7.4588160515,50.3083114624],"type":"Point"}
}