{
  "type": "Feature",
  "properties": {
    "iso:country":"DE",
    "sg:address":"Kulmbacher Str. 7",
    "sg:city":"Kronach",
    "sg:phone":"+49 9261/94059",
    "sg:postcode":"96317",
    "sg:province":"Bayern",
    "wof:name":"Hotel Bauer Gmbh",
    "wof:placetype":"venue"
},
  "geometry": {"coordinates":[11.3244543076,50.237411499],"type":"Point"}
}