{
  "type": "Feature",
  "properties": {
    "iso:country":"DE",
    "sg:address":"Leipziger Str. 1",
    "sg:city":"Remscheid",
    "sg:phone":"+49 2191/341035",
    "sg:postcode":"42859",
    "sg:province":"Nordrhein-Westfalen",
    "wof:name":"Ev. Johannes-kirchengemeinde",
    "wof:placetype":"venue"
},
  "geometry": {"coordinates":[7.2236871719,51.1761703491],"type":"Point"}
}