{
  "type": "Feature",
  "properties": {
    "iso:country":"DE",
    "sg:address":"Gro\u00dfenhainer Str. 95",
    "sg:city":"Dresden",
    "sg:phone":"+49 351/4769253",
    "sg:postcode":"01127",
    "sg:province":"Sachsen",
    "wof:name":"Trapez Grundst\u00fccksver- Waltungs Gmbh",
    "wof:placetype":"venue"
},
  "geometry": {"coordinates":[13.7305183411,51.0816993713],"type":"Point"}
}