{
  "type": "Feature",
  "properties": {
    "iso:country":"DE",
    "sg:address":"Stadtplatz 32",
    "sg:city":"Neumarkt St. Veit",
    "sg:phone":"+49 8639/8008",
    "sg:postcode":"84494",
    "sg:province":"Bayern",
    "wof:name":"Kreissparkasse M\u00fchldorf",
    "wof:placetype":"venue"
},
  "geometry": {"coordinates":[12.508403,48.361191],"type":"Point"}
}