{
  "type": "Feature",
  "properties": {
    "iso:country":"DE",
    "sg:address":"Westernmauer 54",
    "sg:city":"Paderborn",
    "sg:phone":"+49 5251/291660",
    "sg:postcode":"33098",
    "sg:province":"Nordrhein-Westfalen",
    "wof:name":"Heinrich Werner Rechtsanwalt",
    "wof:placetype":"venue"
},
  "geometry": {"coordinates":[8.7485466003,51.7195053101],"type":"Point"}
}