{
  "type": "Feature",
  "properties": {
    "iso:country":"DE",
    "sg:address":"Dornbreede 14",
    "sg:city":"Ahlen",
    "sg:phone":"+49 2528/415",
    "sg:postcode":"59227",
    "sg:province":"Nordrhein-Westfalen",
    "wof:name":"Peter Bendik",
    "wof:placetype":"venue"
},
  "geometry": {"coordinates":[7.948153019,51.80052948],"type":"Point"}
}