{
  "type": "Feature",
  "properties": {
    "iso:country":"DE",
    "sg:address":"J\u00e4ckstr. 18",
    "sg:city":"Bamberg",
    "sg:phone":"+49 951/968343",
    "sg:postcode":"96052",
    "sg:province":"Bayern",
    "wof:name":"Georg Gunreben Parkettfabrik S\u00e4gewerk Und Holzhandlung",
    "wof:placetype":"venue"
},
  "geometry": {"coordinates":[10.8853597641,49.9025764465],"type":"Point"}
}