{
  "type": "Feature",
  "properties": {
    "iso:country":"DE",
    "sg:address":"Fernewaldstr. 9",
    "sg:city":"Oberhausen",
    "sg:phone":"+49 208/605426",
    "sg:postcode":"46119",
    "sg:province":"Nordrhein-Westfalen",
    "wof:name":"B. Noll",
    "wof:placetype":"venue"
},
  "geometry": {"coordinates":[6.8845119476,51.5297660828],"type":"Point"}
}