{
  "type": "Feature",
  "properties": {
    "iso:country":"DE",
    "sg:address":"Litschentalstr. 5",
    "sg:city":"Seelbach",
    "sg:postcode":"77960",
    "sg:province":"Baden-W\u00fcrttemberg",
    "wof:name":"Schwarzwald-versand Gmbh",
    "wof:placetype":"venue"
},
  "geometry": {"coordinates":[7.9396290779,48.307472229],"type":"Point"}
}