{
  "type": "Feature",
  "properties": {
    "iso:country":"DE",
    "sg:address":"Roermonder Str. 226",
    "sg:city":"Aachen",
    "sg:phone":"+49 241/12600",
    "sg:postcode":"52072",
    "sg:province":"Nordrhein-Westfalen",
    "wof:name":"Jean Monti",
    "wof:placetype":"venue"
},
  "geometry": {"coordinates":[6.066891,50.791573],"type":"Point"}
}