{
  "type": "Feature",
  "properties": {
    "iso:country":"DE",
    "sg:address":"Friedrich-Rech-Str. 191",
    "sg:city":"Neuwied",
    "sg:phone":"+49 2631/47526",
    "sg:postcode":"56566",
    "sg:province":"Rheinland-Pfalz",
    "wof:name":"Otto Kochh\u00e4user",
    "wof:placetype":"venue"
},
  "geometry": {"coordinates":[7.5017061234,50.4741821289],"type":"Point"}
}