{
  "type": "Feature",
  "properties": {
    "iso:country":"DE",
    "sg:address":"Holzgartenstr. 47",
    "sg:city":"N\u00fcrnberg",
    "sg:phone":"+49 911/463440",
    "sg:postcode":"90461",
    "sg:province":"Bayern",
    "wof:name":"Herbert Hilmer Heilpraktiker",
    "wof:placetype":"venue"
},
  "geometry": {"coordinates":[11.096736908,49.4379005432],"type":"Point"}
}