{
  "type": "Feature",
  "properties": {
    "iso:country":"DE",
    "sg:address":"Sellstedter Str. 6",
    "sg:city":"Schiffdorf",
    "sg:phone":"+49 4706/750888",
    "sg:postcode":"27619",
    "sg:province":"Niedersachsen",
    "wof:name":"Eiscafe Florenz",
    "wof:placetype":"venue"
},
  "geometry": {"coordinates":[8.654337,53.530361],"type":"Point"}
}