{
  "type": "Feature",
  "properties": {
    "iso:country":"DE",
    "sg:address":"Rothenbaumchaussee 1",
    "sg:city":"Hamburg",
    "sg:phone":"+49 40/4607750",
    "sg:postcode":"20148",
    "sg:province":"Hamburg",
    "wof:name":"Hock & Partner Beratungs- Gesellschaft F\u00fcr Marketing",
    "wof:placetype":"venue"
},
  "geometry": {"coordinates":[9.9890861511,53.5641784668],"type":"Point"}
}