{
  "type": "Feature",
  "properties": {
    "iso:country":"DE",
    "sg:address":"R\u00f6merstr. 28",
    "sg:city":"Heidelberg",
    "sg:phone":"+49 6221/600070",
    "sg:postcode":"69115",
    "sg:province":"Baden-W\u00fcrttemberg",
    "wof:name":"Immobilien Kellner Gmbh",
    "wof:placetype":"venue"
},
  "geometry": {"coordinates":[8.6845188141,49.4038772583],"type":"Point"}
}