{
  "type": "Feature",
  "properties": {
    "iso:country":"DE",
    "sg:address":"Vennekenweg 21",
    "sg:city":"Raesfeld",
    "sg:phone":"+49 2865/95970",
    "sg:postcode":"46348",
    "sg:province":"Nordrhein-Westfalen",
    "wof:name":"Wehling Ladenbau- Innenausbau Gmbh",
    "wof:placetype":"venue"
},
  "geometry": {"coordinates":[6.8307237625,51.7782974243],"type":"Point"}
}