{
  "type": "Feature",
  "properties": {
    "iso:country":"DE",
    "sg:address":"Schachtstr. 8",
    "sg:city":"Reinsdorf",
    "sg:phone":"+49 375/295637",
    "sg:postcode":"08141",
    "sg:province":"Sachsen",
    "wof:name":"Sportlerheim",
    "wof:placetype":"venue"
},
  "geometry": {"coordinates":[12.5416545868,50.6963424683],"type":"Point"}
}