{
  "type": "Feature",
  "properties": {
    "iso:country":"DE",
    "sg:address":"Im Kleinen Bruch 6-7",
    "sg:city":"Eberbach",
    "sg:phone":"+49 6271/6127",
    "sg:postcode":"69412",
    "sg:province":"Baden-W\u00fcrttemberg",
    "wof:name":"Burkhardt Gmbh",
    "wof:placetype":"venue"
},
  "geometry": {"coordinates":[8.9851760864,49.4722709656],"type":"Point"}
}