{
  "type": "Feature",
  "properties": {
    "iso:country":"DE",
    "sg:address":"Wallenbr\u00fccker Str. 58",
    "sg:city":"Melle",
    "sg:phone":"+49 5428/629",
    "sg:postcode":"49326",
    "sg:province":"Niedersachsen",
    "wof:name":"Hans Dr\u00fcner Elektro-meister",
    "wof:placetype":"venue"
},
  "geometry": {"coordinates":[8.441069,52.155716],"type":"Point"}
}