{
  "type": "Feature",
  "properties": {
    "iso:country":"DE",
    "sg:address":"Dorfstr. 68",
    "sg:city":"Ismaning",
    "sg:phone":"+49 89/969673",
    "sg:postcode":"85737",
    "sg:province":"Bayern",
    "wof:name":"Max Sigl Beteiligungs Gmbh",
    "wof:placetype":"venue"
},
  "geometry": {"coordinates":[11.683529,48.213871],"type":"Point"}
}