{
  "type": "Feature",
  "properties": {
    "iso:country":"DE",
    "sg:address":"Am Weiher 11",
    "sg:city":"Reiskirchen",
    "sg:phone":"+49 6408/63164",
    "sg:postcode":"35447",
    "sg:province":"Hessen",
    "wof:name":"Heinrich R\u00f6mer",
    "wof:placetype":"venue"
},
  "geometry": {"coordinates":[8.853207,50.618454],"type":"Point"}
}