{
  "type": "Feature",
  "properties": {
    "iso:country":"DE",
    "sg:address":"Trebbiner Str. 18",
    "sg:city":"Sperenberg",
    "sg:phone":"+49 33703/70443",
    "sg:postcode":"15838",
    "sg:province":"Brandenburg",
    "wof:name":"Peter Bieler Ingenieur",
    "wof:placetype":"venue"
},
  "geometry": {"coordinates":[13.360329628,52.1454048157],"type":"Point"}
}