{
  "type": "Feature",
  "properties": {
    "iso:country":"DE",
    "sg:address":"B\u00fchlerweg 31",
    "sg:city":"Baiersbronn",
    "sg:phone":"+49 7447/660",
    "sg:postcode":"72270",
    "sg:province":"Baden-W\u00fcrttemberg",
    "wof:name":"Hugo Zifle",
    "wof:placetype":"venue"
},
  "geometry": {"coordinates":[8.383842,48.589966],"type":"Point"}
}