{
  "type": "Feature",
  "properties": {
    "iso:country":"DE",
    "sg:address":"Gartensparte",
    "sg:city":"Edderitz",
    "sg:phone":"+49 34976/32347",
    "sg:postcode":"06388",
    "sg:province":"Sachsen-Anhalt",
    "wof:name":"Sportlerheim",
    "wof:placetype":"venue"
},
  "geometry": {"coordinates":[11.9180612564,51.6863059998],"type":"Point"}
}