{
  "type": "Feature",
  "properties": {
    "iso:country":"DE",
    "sg:address":"Sudetenstr. 36",
    "sg:city":"Neutraubling",
    "sg:phone":"+49 9401/1324",
    "sg:postcode":"93073",
    "sg:province":"Bayern",
    "wof:name":"G. J\u00f6rss",
    "wof:placetype":"venue"
},
  "geometry": {"coordinates":[12.196602,48.992619],"type":"Point"}
}