{
  "type": "Feature",
  "properties": {
    "iso:country":"DE",
    "sg:address":"Neustr. 18",
    "sg:city":"Wittlich",
    "sg:phone":"+49 6571/29044",
    "sg:postcode":"54516",
    "sg:province":"Rheinland-Pfalz",
    "wof:name":"Karl-josef M\u00fcller Naturheilpraxis",
    "wof:placetype":"venue"
},
  "geometry": {"coordinates":[6.8883919716,49.9866294861],"type":"Point"}
}