{
  "type": "Feature",
  "properties": {
    "iso:country":"DE",
    "sg:address":"Ludwig-Thoma-Str. 36",
    "sg:city":"Bad Reichenhall",
    "sg:phone":"+49 8651/5526",
    "sg:postcode":"83435",
    "sg:province":"Bayern",
    "wof:name":"G\u00e4stehaus Anton Bergmair",
    "wof:placetype":"venue"
},
  "geometry": {"coordinates":[12.8834924698,47.7362060547],"type":"Point"}
}