{
  "type": "Feature",
  "properties": {
    "iso:country":"DE",
    "sg:address":"Jakob-Zwiebel-Str. 5",
    "sg:city":"Thannhausen",
    "sg:phone":"+49 8281/2425",
    "sg:postcode":"86470",
    "sg:province":"Bayern",
    "wof:name":"Ev. Luth. Pfarramt",
    "wof:placetype":"venue"
},
  "geometry": {"coordinates":[10.4669427872,48.2797851562],"type":"Point"}
}