{
  "type": "Feature",
  "properties": {
    "iso:country":"DE",
    "sg:address":"Im Kazenloch 17",
    "sg:city":"Wiernsheim",
    "sg:phone":"+49 7044/914221",
    "sg:postcode":"75446",
    "sg:province":"Baden-W\u00fcrttemberg",
    "wof:name":"Probis Gmbh",
    "wof:placetype":"venue"
},
  "geometry": {"coordinates":[8.8544483185,48.8864898682],"type":"Point"}
}