{
  "type": "Feature",
  "properties": {
    "iso:country":"DE",
    "sg:address":"Im Lein 2",
    "sg:city":"Salzkotten",
    "sg:phone":"+49 5258/7550",
    "sg:postcode":"33154",
    "sg:province":"Nordrhein-Westfalen",
    "wof:name":"Wilhelm Okesson",
    "wof:placetype":"venue"
},
  "geometry": {"coordinates":[8.6015529633,51.6651725769],"type":"Point"}
}