{
  "type": "Feature",
  "properties": {
    "iso:country":"DE",
    "sg:address":"Friedhofstr. 60",
    "sg:city":"Lorsch",
    "sg:phone":"+49 6251/51151",
    "sg:postcode":"64653",
    "sg:province":"Hessen",
    "wof:name":"Wendelin Trares Jun.",
    "wof:placetype":"venue"
},
  "geometry": {"coordinates":[8.56437,49.663399],"type":"Point"}
}