{
  "type": "Feature",
  "properties": {
    "iso:country":"DE",
    "sg:address":"Eisenbahnstr. 2",
    "sg:city":"Wickede",
    "sg:postcode":"58739",
    "sg:province":"Nordrhein-Westfalen",
    "wof:name":"Koch Gmbh",
    "wof:placetype":"venue"
},
  "geometry": {"coordinates":[7.8631830215,51.4914932251],"type":"Point"}
}