{
  "type": "Feature",
  "properties": {
    "iso:country":"DE",
    "sg:address":"Hans-Loch-Str. 31",
    "sg:city":"Erfurt",
    "sg:phone":"+49 361/349520",
    "sg:postcode":"99099",
    "sg:province":"Th\u00fcringen",
    "wof:name":"Schl\u00fcssel Ansch\u00fctz",
    "wof:placetype":"venue"
},
  "geometry": {"coordinates":[11.0546102524,50.9649047852],"type":"Point"}
}