{
  "type": "Feature",
  "properties": {
    "iso:country":"DE",
    "sg:address":"Disselhof 2",
    "sg:city":"Haltern",
    "sg:phone":"+49 2364/92340",
    "sg:postcode":"45721",
    "sg:province":"Nordrhein-Westfalen",
    "wof:name":"Vesta Assekuranz- Kontor Gmbh",
    "wof:placetype":"venue"
},
  "geometry": {"coordinates":[7.1875591278,51.7441711426],"type":"Point"}
}