{
  "type": "Feature",
  "properties": {
    "iso:country":"DE",
    "sg:address":"Zur R\u00f6mertreppe 6",
    "sg:city":"Neunkirchen",
    "sg:phone":"+49 6821/41604",
    "sg:postcode":"66539",
    "sg:province":"Saarland",
    "wof:name":"Berthold Bumb Masseur",
    "wof:placetype":"venue"
},
  "geometry": {"coordinates":[7.216241,49.343128],"type":"Point"}
}