{
  "type": "Feature",
  "properties": {
    "iso:country":"DE",
    "sg:address":"Carl-Zeiss-Str. 2",
    "sg:city":"Gr\u00fcnstadt",
    "sg:phone":"+49 6359/83083",
    "sg:postcode":"67269",
    "sg:province":"Rheinland-Pfalz",
    "wof:name":"Joa-treppenbau Gmbh",
    "wof:placetype":"venue"
},
  "geometry": {"coordinates":[8.174665451,49.5626564026],"type":"Point"}
}