{
  "type": "Feature",
  "properties": {
    "iso:country":"DE",
    "sg:address":"Sch\u00f6neberger Str. 4",
    "sg:city":"Berlin",
    "sg:phone":"+49 30/7924926",
    "sg:postcode":"12163",
    "sg:province":"Berlin",
    "wof:name":"Erwin Schattauer",
    "wof:placetype":"venue"
},
  "geometry": {"coordinates":[13.330109,52.464176],"type":"Point"}
}