{
  "type": "Feature",
  "properties": {
    "iso:country":"DE",
    "sg:address":"Krankenhausstr. 37",
    "sg:city":"Jettingen-Scheppach",
    "sg:phone":"+49 8225/1377",
    "sg:postcode":"89343",
    "sg:province":"Bayern",
    "wof:name":"Voba Industrieanlagen- Putz Gmbh",
    "wof:placetype":"venue"
},
  "geometry": {"coordinates":[10.4399309158,48.3939285278],"type":"Point"}
}