{
  "type": "Feature",
  "properties": {
    "iso:country":"DE",
    "sg:address":"R\u00fcbenkamp 5",
    "sg:city":"Hamburg",
    "sg:phone":"+49 40/6902556",
    "sg:postcode":"22305",
    "sg:province":"Hamburg",
    "wof:name":"Wolfgang Bulda",
    "wof:placetype":"venue"
},
  "geometry": {"coordinates":[10.041117,53.588997],"type":"Point"}
}