{
  "type": "Feature",
  "properties": {
    "iso:country":"DE",
    "sg:address":"An der Kirche 1a",
    "sg:city":"Springe",
    "sg:phone":"+49 5041/63888",
    "sg:postcode":"31832",
    "sg:province":"Niedersachsen",
    "wof:name":"Else Lange Und Helmut Kroworz",
    "wof:placetype":"venue"
},
  "geometry": {"coordinates":[9.554565,52.207863],"type":"Point"}
}