{
  "type": "Feature",
  "properties": {
    "iso:country":"DE",
    "sg:address":"Waldstr. 11",
    "sg:city":"Zinnowitz",
    "sg:postcode":"17454",
    "sg:province":"Mecklenburg-Vorpommern",
    "wof:name":"Katholisches Pfarramt Zinnowitz",
    "wof:placetype":"venue"
},
  "geometry": {"coordinates":[13.9175405502,54.0769920349],"type":"Point"}
}