{
  "type": "Feature",
  "properties": {
    "iso:country":"DE",
    "sg:address":"Lessingstr. 17",
    "sg:city":"Emmendingen",
    "sg:phone":"+49 7641/912130",
    "sg:postcode":"79312",
    "sg:province":"Baden-W\u00fcrttemberg",
    "wof:name":"Reiseb\u00fcro Im Kaufland",
    "wof:placetype":"venue"
},
  "geometry": {"coordinates":[7.8658351898,48.1081123352],"type":"Point"}
}