{
  "type": "Feature",
  "properties": {
    "iso:country":"DE",
    "sg:address":"Lange Str. 9",
    "sg:city":"Cloppenburg",
    "sg:phone":"+49 4471/1780",
    "sg:postcode":"49661",
    "sg:province":"Niedersachsen",
    "wof:name":"Hermann Imsiecke Druck Und Verlag",
    "wof:placetype":"venue"
},
  "geometry": {"coordinates":[8.0425262451,52.845615387],"type":"Point"}
}