{
  "type": "Feature",
  "properties": {
    "iso:country":"DE",
    "sg:address":"Grimpenwall 24",
    "sg:city":"Minden",
    "sg:phone":"+49 571/9730000",
    "sg:postcode":"32423",
    "sg:province":"Nordrhein-Westfalen",
    "wof:name":"Avis Schwarzkopf Gmbh",
    "wof:placetype":"venue"
},
  "geometry": {"coordinates":[8.922256,52.291519],"type":"Point"}
}