{
  "type": "Feature",
  "properties": {
    "iso:country":"DE",
    "sg:address":"Wiedbach 35",
    "sg:city":"Essen",
    "sg:phone":"+49 201/690657",
    "sg:postcode":"45357",
    "sg:province":"Nordrhein-Westfalen",
    "wof:name":"Franz Lutzius Werbeagentur",
    "wof:placetype":"venue"
},
  "geometry": {"coordinates":[6.9388308525,51.4767341614],"type":"Point"}
}