{
  "type": "Feature",
  "properties": {
    "iso:country":"DE",
    "sg:address":"Am Obertor",
    "sg:city":"Neuss",
    "sg:phone":"+49 2131/904140",
    "sg:postcode":"41460",
    "sg:province":"Nordrhein-Westfalen",
    "wof:name":"Clemens-sels-museum",
    "wof:placetype":"venue"
},
  "geometry": {"coordinates":[6.698385,51.194401],"type":"Point"}
}