{
  "type": "Feature",
  "properties": {
    "iso:country":"DE",
    "sg:address":"Alsterdorfer Str. 260",
    "sg:city":"Hamburg",
    "sg:phone":"+49 40/5114647",
    "sg:postcode":"22297",
    "sg:province":"Hamburg",
    "wof:name":"Liane Meier",
    "wof:placetype":"venue"
},
  "geometry": {"coordinates":[10.006189,53.607399],"type":"Point"}
}