{
  "type": "Feature",
  "properties": {
    "iso:country":"DE",
    "sg:address":"Kornweg 10",
    "sg:city":"Kempen",
    "sg:phone":"+49 2845/80361",
    "sg:postcode":"47906",
    "sg:province":"Nordrhein-Westfalen",
    "wof:name":"P. Adams",
    "wof:placetype":"venue"
},
  "geometry": {"coordinates":[6.505852,51.415264],"type":"Point"}
}