{
  "type": "Feature",
  "properties": {
    "iso:country":"DE",
    "sg:address":"Dreibr\u00fcderstr. 11",
    "sg:city":"Annaberg-Buchholz",
    "sg:phone":"+49 3733/21737",
    "sg:postcode":"09456",
    "sg:province":"Sachsen",
    "wof:name":"Glas- Und Geb\u00e4udereinigung Langer In Annaberg-buch",
    "wof:placetype":"venue"
},
  "geometry": {"coordinates":[13.00743,50.565422],"type":"Point"}
}