{
  "type": "Feature",
  "properties": {
    "iso:country":"DE",
    "sg:address":"Schulplatz 4",
    "sg:city":"M\u00fcgeln",
    "sg:postcode":"04769",
    "sg:province":"Sachsen",
    "wof:name":"Heimatmuseum",
    "wof:placetype":"venue"
},
  "geometry": {"coordinates":[13.049778,51.236664],"type":"Point"}
}