{
  "type": "Feature",
  "properties": {
    "iso:country":"DE",
    "sg:address":"Steinacher Str. 53",
    "sg:city":"Sonneberg",
    "sg:phone":"+49 3675/402135",
    "sg:postcode":"96515",
    "sg:province":"Th\u00fcringen",
    "wof:name":"M. Reichelt",
    "wof:placetype":"venue"
},
  "geometry": {"coordinates":[11.2098436356,50.3583450317],"type":"Point"}
}