{
  "type": "Feature",
  "properties": {
    "iso:country":"DE",
    "sg:address":"Triftstr. 41",
    "sg:city":"Oberau",
    "sg:phone":"+49 8824/944163",
    "sg:postcode":"82496",
    "sg:province":"Bayern",
    "wof:name":"Elisabeth Und Jose Van Acker",
    "wof:placetype":"venue"
},
  "geometry": {"coordinates":[11.1393203735,47.5659866333],"type":"Point"}
}