{
  "type": "Feature",
  "properties": {
    "iso:country":"DE",
    "sg:address":"Dornierstr 4",
    "sg:city":"Wiedemar",
    "sg:phone":"+49 34207/40680",
    "sg:postcode":"04509",
    "sg:province":"Sachsen",
    "wof:name":"Dokuhaus Archivcenter Gmbh",
    "wof:placetype":"venue"
},
  "geometry": {"coordinates":[12.21168,51.470661],"type":"Point"}
}