{
  "type": "Feature",
  "properties": {
    "iso:country":"DE",
    "sg:address":"Lotter Str. 127",
    "sg:city":"Osnabr\u00fcck",
    "sg:phone":"+49 541/430973",
    "sg:postcode":"49078",
    "sg:province":"Niedersachsen",
    "wof:name":"Pizzeria Bei Rocco",
    "wof:placetype":"venue"
},
  "geometry": {"coordinates":[8.0364837646,52.2754135132],"type":"Point"}
}