{
  "type": "Feature",
  "properties": {
    "iso:country":"DE",
    "sg:address":"Waldstr. 12",
    "sg:city":"Billigheim-Ingenheim",
    "sg:phone":"+49 6349/5808",
    "sg:postcode":"76831",
    "sg:province":"Rheinland-Pfalz",
    "wof:name":"Ernst-peter Knaetsch",
    "wof:placetype":"venue"
},
  "geometry": {"coordinates":[8.093112,49.128681],"type":"Point"}
}