{
  "type": "Feature",
  "properties": {
    "iso:country":"DE",
    "sg:address":"Solitudeallee 30",
    "sg:city":"Ludwigsburg",
    "sg:phone":"+49 7141/924881",
    "sg:postcode":"71636",
    "sg:province":"Baden-W\u00fcrttemberg",
    "wof:name":"Thomas Knodel",
    "wof:placetype":"venue"
},
  "geometry": {"coordinates":[9.1853084564,48.8862838745],"type":"Point"}
}