{
  "type": "Feature",
  "properties": {
    "iso:country":"DE",
    "sg:address":"Fasanenstr. 22",
    "sg:city":"Rellingen",
    "sg:phone":"+49 4101/33572",
    "sg:postcode":"25462",
    "sg:province":"Schleswig-Holstein",
    "wof:name":"Ponce Grafische Produktionsges. Mbh",
    "wof:placetype":"venue"
},
  "geometry": {"coordinates":[9.892865181,53.6342544556],"type":"Point"}
}