{
  "type": "Feature",
  "properties": {
    "iso:country":"DE",
    "sg:address":"Martin-Luther-Platz 1",
    "sg:city":"Dresden",
    "sg:phone":"+49 351/8038790",
    "sg:postcode":"01099",
    "sg:province":"Sachsen",
    "wof:name":"H\u00fcbner Und Michel Rechtsanw\u00e4lte",
    "wof:placetype":"venue"
},
  "geometry": {"coordinates":[13.7562551498,51.0646743774],"type":"Point"}
}