{
  "type": "Feature",
  "properties": {
    "iso:country":"DE",
    "sg:address":"Schotteweg 6",
    "sg:city":"Dortmund",
    "sg:phone":"+49 231/6790364",
    "sg:postcode":"44379",
    "sg:province":"Nordrhein-Westfalen",
    "wof:name":"H. Bosch",
    "wof:placetype":"venue"
},
  "geometry": {"coordinates":[7.360314846,51.5226287842],"type":"Point"}
}