{
  "type": "Feature",
  "properties": {
    "iso:country":"DE",
    "sg:address":"Kurf\u00fcrstendamm 33",
    "sg:city":"Berlin",
    "sg:phone":"+49 30/25570",
    "sg:postcode":"10719",
    "sg:province":"Berlin",
    "wof:name":"Deutsche Bau- Und Bodenbank Ag",
    "wof:placetype":"venue"
},
  "geometry": {"coordinates":[13.324366,52.502594],"type":"Point"}
}