{
  "type": "Feature",
  "properties": {
    "iso:country":"DE",
    "sg:address":"Ufergasse 2",
    "sg:city":"Saarbr\u00fccken",
    "sg:phone":"+49 681/36938",
    "sg:postcode":"66111",
    "sg:province":"Saarland",
    "wof:name":"Heinz Falk",
    "wof:placetype":"venue"
},
  "geometry": {"coordinates":[6.99352,49.235291],"type":"Point"}
}