{
  "type": "Feature",
  "properties": {
    "iso:country":"DE",
    "sg:address":"F\u00fcrstenwalder Damm 369",
    "sg:city":"Berlin",
    "sg:phone":"+49 30/6455116",
    "sg:postcode":"12587",
    "sg:province":"Berlin",
    "wof:name":"Frank Grubitz",
    "wof:placetype":"venue"
},
  "geometry": {"coordinates":[13.662704,52.449783],"type":"Point"}
}