{
  "type": "Feature",
  "properties": {
    "iso:country":"DE",
    "sg:address":"W\u00fcstenh\u00f6fener Weg 15",
    "sg:city":"Tostedt",
    "sg:phone":"+49 4182/6539",
    "sg:postcode":"21255",
    "sg:province":"Niedersachsen",
    "wof:name":"Helmut Friederich",
    "wof:placetype":"venue"
},
  "geometry": {"coordinates":[9.68421,53.282413],"type":"Point"}
}