{
  "type": "Feature",
  "properties": {
    "iso:country":"DE",
    "sg:address":"Vautierstr. 9",
    "sg:city":"D\u00fcsseldorf",
    "sg:phone":"+49 211/685348",
    "sg:postcode":"40237",
    "sg:province":"Nordrhein-Westfalen",
    "wof:name":"Adam Heise",
    "wof:placetype":"venue"
},
  "geometry": {"coordinates":[6.816453,51.242542],"type":"Point"}
}