{
  "type": "Feature",
  "properties": {
    "iso:country":"DE",
    "sg:address":"Senderweg 1",
    "sg:city":"Kirchheim",
    "sg:phone":"+49 4951/3989900",
    "sg:postcode":"87757",
    "sg:province":"Bayern",
    "wof:name":"Frauenberger- Benta Vertriebs- Gmbh",
    "wof:placetype":"venue"
},
  "geometry": {"coordinates":[-81.9753570557,33.4790916443],"type":"Point"}
}