{
  "type": "Feature",
  "properties": {
    "iso:country":"DE",
    "sg:address":"Granitzstr. 12",
    "sg:city":"Balingen",
    "sg:phone":"+49 7433/4571",
    "sg:postcode":"72336",
    "sg:province":"Baden-W\u00fcrttemberg",
    "wof:name":"Oskar Narr",
    "wof:placetype":"venue"
},
  "geometry": {"coordinates":[8.877061,48.250565],"type":"Point"}
}