{
  "type": "Feature",
  "properties": {
    "iso:country":"DE",
    "sg:address":"Bahnhofstr. 35",
    "sg:city":"Heidelberg",
    "sg:phone":"+49 6221/27290",
    "sg:postcode":"69115",
    "sg:province":"Baden-W\u00fcrttemberg",
    "wof:name":"Intertext \u00dcbersetzungsb\u00fcro",
    "wof:placetype":"venue"
},
  "geometry": {"coordinates":[8.688368,49.405479],"type":"Point"}
}