{
  "type": "Feature",
  "properties": {
    "iso:country":"DE",
    "sg:address":"Auenstr. 3",
    "sg:city":"Gattendorf",
    "sg:phone":"+49 9281/40248",
    "sg:postcode":"95185",
    "sg:province":"Bayern",
    "wof:name":"Merkel Maler U. Coatings E. K.",
    "wof:placetype":"venue"
},
  "geometry": {"coordinates":[11.999659,50.323006],"type":"Point"}
}