{
  "type": "Feature",
  "properties": {
    "iso:country":"DE",
    "sg:address":"Dorotheenstr. 89",
    "sg:city":"D\u00fcsseldorf",
    "sg:phone":"+49 211/7334148",
    "sg:postcode":"40235",
    "sg:province":"Nordrhein-Westfalen",
    "wof:name":"Aral Tankstelle",
    "wof:placetype":"venue"
},
  "geometry": {"coordinates":[6.8113799095,51.22631073],"type":"Point"}
}