{
  "type": "Feature",
  "properties": {
    "iso:country":"DE",
    "sg:address":"Hauptstr. 168a",
    "sg:city":"Eibau",
    "sg:phone":"+49 3586/7540",
    "sg:postcode":"02739",
    "sg:province":"Sachsen",
    "wof:name":"Seniorenpflegezentrum Am Kottmar Gmbh",
    "wof:placetype":"venue"
},
  "geometry": {"coordinates":[14.652434,50.987667],"type":"Point"}
}