{
  "type": "Feature",
  "properties": {
    "iso:country":"DE",
    "sg:address":"Alt-Heiligensee",
    "sg:city":"Berlin",
    "sg:phone":"+49 30/4315133",
    "sg:postcode":"13503",
    "sg:province":"Berlin",
    "wof:name":"Imbi\u00df Volkmar Stiebeler",
    "wof:placetype":"venue"
},
  "geometry": {"coordinates":[13.2499065399,52.6001663208],"type":"Point"}
}