{
  "type": "Feature",
  "properties": {
    "iso:country":"DE",
    "sg:address":"Eichstr. 9-44",
    "sg:city":"Langenhagen",
    "sg:phone":"+49 511/6042121",
    "sg:postcode":"30855",
    "sg:province":"Niedersachsen",
    "wof:name":"Beratungsgruppe Lah Ingenieurgesellschaft",
    "wof:placetype":"venue"
},
  "geometry": {"coordinates":[9.7426204681,52.4603462219],"type":"Point"}
}