{
  "type": "Feature",
  "properties": {
    "iso:country":"DE",
    "sg:address":"Silverbergstr. 7",
    "sg:city":"Bergheim",
    "sg:phone":"+49 2271/52752",
    "sg:postcode":"50129",
    "sg:province":"Nordrhein-Westfalen",
    "wof:name":"Ro\u00dfbach Gmbh",
    "wof:placetype":"venue"
},
  "geometry": {"coordinates":[6.665543,50.981792],"type":"Point"}
}