{
  "type": "Feature",
  "properties": {
    "iso:country":"DE",
    "sg:address":"Niederh\u00f6chst\u00e4dter Str. 20",
    "sg:city":"Steinbach",
    "sg:postcode":"61449",
    "sg:province":"Hessen",
    "wof:name":"Steinbacher Hausbau Gmbh",
    "wof:placetype":"venue"
},
  "geometry": {"coordinates":[8.5677499771,50.1663169861],"type":"Point"}
}