{
  "type": "Feature",
  "properties": {
    "iso:country":"DE",
    "sg:address":"Gro\u00dfe Str. 20",
    "sg:city":"Aum\u00fchle",
    "sg:postcode":"21521",
    "sg:province":"Schleswig-Holstein",
    "wof:name":"Engel & V\u00f6lkers Sachsenwald Gmbh",
    "wof:placetype":"venue"
},
  "geometry": {"coordinates":[10.3039169312,53.5255355835],"type":"Point"}
}