{
  "type": "Feature",
  "properties": {
    "iso:country":"DE",
    "sg:address":"Postillionstr. 23",
    "sg:city":"Moers",
    "sg:phone":"+49 2841/76075",
    "sg:postcode":"47445",
    "sg:province":"Nordrhein-Westfalen",
    "wof:name":"Walter W\u00fcrfel Steuerberater",
    "wof:placetype":"venue"
},
  "geometry": {"coordinates":[6.6053309441,51.4793319702],"type":"Point"}
}