{
  "type": "Feature",
  "properties": {
    "iso:country":"DE",
    "sg:address":"Lindwurmstr. 95",
    "sg:city":"M\u00fcnchen",
    "sg:phone":"+49 89/5309311",
    "sg:postcode":"80337",
    "sg:province":"Bayern",
    "wof:name":"Vereinigte Papierwaren- Fabriken Gmbh",
    "wof:placetype":"venue"
},
  "geometry": {"coordinates":[11.5570840836,48.1287307739],"type":"Point"}
}