{
  "type": "Feature",
  "properties": {
    "iso:country":"DE",
    "sg:address":"Anton-Kux-Str. 2",
    "sg:city":"Neuss",
    "sg:phone":"+49 2131/167432",
    "sg:postcode":"41460",
    "sg:province":"Nordrhein-Westfalen",
    "wof:name":"Ih Collection Modevertrieb Gmbh",
    "wof:placetype":"venue"
},
  "geometry": {"coordinates":[6.71362,51.193161],"type":"Point"}
}