{
  "type": "Feature",
  "properties": {
    "iso:country":"DE",
    "sg:address":"Halskestr. 24",
    "sg:city":"Ratingen",
    "sg:phone":"+49 2102/46544",
    "sg:postcode":"40880",
    "sg:province":"Nordrhein-Westfalen",
    "wof:name":"Leuchtenhalle Ratingen Reck Gmbh & Co. Kg",
    "wof:placetype":"venue"
},
  "geometry": {"coordinates":[6.834835,51.305317],"type":"Point"}
}