{
  "type": "Feature",
  "properties": {
    "iso:country":"DE",
    "sg:address":"Stettiner Chaussee 3",
    "sg:city":"Pasewalk",
    "sg:phone":"+49 3973/216250",
    "sg:postcode":"17309",
    "sg:province":"Mecklenburg-Vorpommern",
    "wof:name":"Otb Sanit\u00e4tshaus Erwerth Gmbh",
    "wof:placetype":"venue"
},
  "geometry": {"coordinates":[13.9906482697,53.5047836304],"type":"Point"}
}