{
  "type": "Feature",
  "properties": {
    "iso:country":"DE",
    "sg:address":"H\u00f6henstr. 18",
    "sg:city":"Eichenb\u00fchl",
    "sg:phone":"+49 9378/359",
    "sg:postcode":"63928",
    "sg:province":"Bayern",
    "wof:name":"Rose",
    "wof:placetype":"venue"
},
  "geometry": {"coordinates":[9.3588562012,49.6656265259],"type":"Point"}
}