{
  "type": "Feature",
  "properties": {
    "iso:country":"DE",
    "sg:address":"Dr.-von-Schmitt-Str. 6",
    "sg:city":"Bamberg",
    "sg:phone":"+49 951/22677",
    "sg:postcode":"96050",
    "sg:province":"Bayern",
    "wof:name":"W. Wittko Steuerberater",
    "wof:placetype":"venue"
},
  "geometry": {"coordinates":[10.895693779,49.8955383301],"type":"Point"}
}