{
  "type": "Feature",
  "properties": {
    "iso:country":"DE",
    "sg:address":"Weiherstr. 20",
    "sg:city":"Dettingen",
    "sg:phone":"+49 4975/3394030",
    "sg:postcode":"78465",
    "sg:province":"Baden-W\u00fcrttemberg",
    "wof:name":"Oralia Dentalprodukte Gmbh",
    "wof:placetype":"venue"
},
  "geometry": {"coordinates":[9.1729650497,47.7141342163],"type":"Point"}
}