{
  "type": "Feature",
  "properties": {
    "iso:country":"DE",
    "sg:address":"Arnisser Str. 1",
    "sg:city":"Kappeln",
    "sg:postcode":"24376",
    "sg:province":"Schleswig-Holstein",
    "wof:name":"Lci Spielverwaltung Und Spielbetreuung Gmbh",
    "wof:placetype":"venue"
},
  "geometry": {"coordinates":[9.930939,54.659878],"type":"Point"}
}