{
  "type": "Feature",
  "properties": {
    "iso:country":"DE",
    "sg:address":"Parkweg 1 -3",
    "sg:city":"Nordstemmen",
    "sg:phone":"+49 5069/1890",
    "sg:postcode":"31171",
    "sg:province":"Niedersachsen",
    "wof:name":"Nitec Druck Verwaltungs Gmbh",
    "wof:placetype":"venue"
},
  "geometry": {"coordinates":[9.81295681,52.1824569702],"type":"Point"}
}