{
  "type": "Feature",
  "properties": {
    "iso:country":"DE",
    "sg:address":"Darmst\u00e4dter Str. 111",
    "sg:city":"Gro\u00df-Zimmern",
    "sg:phone":"+49 6071/749110",
    "sg:postcode":"64846",
    "sg:province":"Hessen",
    "wof:name":"Bernd Pullmann",
    "wof:placetype":"venue"
},
  "geometry": {"coordinates":[8.8100662231,49.8662834167],"type":"Point"}
}