{
  "type": "Feature",
  "properties": {
    "iso:country":"DE",
    "sg:address":"R\u00fcttenscheider Str. 227",
    "sg:city":"Essen",
    "sg:phone":"+49 201/412913",
    "sg:postcode":"45131",
    "sg:province":"Nordrhein-Westfalen",
    "wof:name":"Minos",
    "wof:placetype":"venue"
},
  "geometry": {"coordinates":[7.0032548904,51.4283447266],"type":"Point"}
}