{
  "type": "Feature",
  "properties": {
    "iso:country":"DE",
    "sg:address":"Marienstr. 9",
    "sg:city":"Pattensen",
    "sg:phone":"+49 5101/12412",
    "sg:postcode":"30982",
    "sg:province":"Niedersachsen",
    "wof:name":"Marien-apotheke Apoth. Nicola Kallmeyer E. K.",
    "wof:placetype":"venue"
},
  "geometry": {"coordinates":[9.76119,52.264912],"type":"Point"}
}