{
  "type": "Feature",
  "properties": {
    "iso:country":"DE",
    "sg:address":"Merianstr. 32",
    "sg:city":"N\u00fcrnberg",
    "sg:phone":"+49 911/51950",
    "sg:postcode":"90409",
    "sg:province":"Bayern",
    "wof:name":"De Te System Deutsche Telekom Systeml\u00f6sungen Gmbh",
    "wof:placetype":"venue"
},
  "geometry": {"coordinates":[11.1010742188,49.4725837708],"type":"Point"}
}