{
  "type": "Feature",
  "properties": {
    "iso:country":"DE",
    "sg:address":"D\u00f6rnthal 11",
    "sg:city":"Selbitz",
    "sg:phone":"+49 9280/5383",
    "sg:postcode":"95152",
    "sg:province":"Bayern",
    "wof:name":"H. Strobel",
    "wof:placetype":"venue"
},
  "geometry": {"coordinates":[11.7815265656,50.3286933899],"type":"Point"}
}