{
  "type": "Feature",
  "properties": {
    "iso:country":"DE",
    "sg:address":"Lindenaustrasse 44",
    "sg:city":"Ohrdruf",
    "sg:phone":"+49 3624/37190",
    "sg:postcode":"99885",
    "sg:province":"Th\u00fcringen",
    "wof:name":"Karmelitenkloster St. Elija",
    "wof:placetype":"venue"
},
  "geometry": {"coordinates":[10.73129,50.825985],"type":"Point"}
}