{
  "type": "Feature",
  "properties": {
    "iso:country":"DE",
    "sg:address":"Bahnhofstr. 8",
    "sg:city":"Freiburg",
    "sg:postcode":"79117",
    "sg:province":"Baden-W\u00fcrttemberg",
    "wof:name":"Michael Reiner Freier Finanzberater E. K.",
    "wof:placetype":"venue"
},
  "geometry": {"coordinates":[7.9144511223,47.9752235413],"type":"Point"}
}