{
  "type": "Feature",
  "properties": {
    "iso:country":"DE",
    "sg:address":"Kurt-Schumacher-Str. 21",
    "sg:city":"Hinte",
    "sg:phone":"+49 4925/2228",
    "sg:postcode":"26759",
    "sg:province":"Niedersachsen",
    "wof:name":"Edzard Van Hove",
    "wof:placetype":"venue"
},
  "geometry": {"coordinates":[7.2029571533,53.3991355896],"type":"Point"}
}