{
  "type": "Feature",
  "properties": {
    "iso:country":"DE",
    "sg:address":"Klinikstr. 51",
    "sg:city":"Bochum",
    "sg:phone":"+49 234/592570",
    "sg:postcode":"44791",
    "sg:province":"Nordrhein-Westfalen",
    "wof:name":"Restaurant Zum Tierpark",
    "wof:placetype":"venue"
},
  "geometry": {"coordinates":[7.227809906,51.4902038574],"type":"Point"}
}