{
  "type": "Feature",
  "properties": {
    "iso:country":"DE",
    "sg:address":"Warferweg 1",
    "sg:city":"Norden",
    "sg:phone":"+49 4931/2639",
    "sg:postcode":"26506",
    "sg:province":"Niedersachsen",
    "wof:name":"Ulrich Kanzler",
    "wof:placetype":"venue"
},
  "geometry": {"coordinates":[7.151731,53.587112],"type":"Point"}
}