{
  "type": "Feature",
  "properties": {
    "iso:country":"DE",
    "sg:address":"Postfach 101345:: 31763 Hameln:: Germany.^^Osterstr 25::",
    "sg:city":"Hameln",
    "sg:phone":"+49 5151/7850",
    "sg:postcode":"31785",
    "sg:province":"Niedersachsen",
    "wof:name":"Stadtsparkasse Hameln",
    "wof:placetype":"venue"
},
  "geometry": {"coordinates":[9.357038,52.100719],"type":"Point"}
}