{
  "type": "Feature",
  "properties": {
    "iso:country":"DE",
    "sg:address":"An der Kirche 13",
    "sg:city":"Aerzen",
    "sg:phone":"+49 5154/578",
    "sg:postcode":"31855",
    "sg:province":"Niedersachsen",
    "wof:name":"Gerd Korf",
    "wof:placetype":"venue"
},
  "geometry": {"coordinates":[9.3103322983,52.065864563],"type":"Point"}
}