{
  "type": "Feature",
  "properties": {
    "iso:country":"DE",
    "sg:address":"Bahnhofstr. 21 a",
    "sg:city":"Grafrath",
    "sg:postcode":"82284",
    "sg:province":"Bayern",
    "wof:name":"Laser Job Gmbh",
    "wof:placetype":"venue"
},
  "geometry": {"coordinates":[11.1596126556,48.127494812],"type":"Point"}
}