{
  "type": "Feature",
  "properties": {
    "iso:country":"DE",
    "sg:address":"Nordweg 2",
    "sg:city":"Legau",
    "sg:phone":"+49 8330/201",
    "sg:postcode":"87764",
    "sg:province":"Bayern",
    "wof:name":"Ludwig Und Otto B\u00e4cker Gmbh",
    "wof:placetype":"venue"
},
  "geometry": {"coordinates":[10.1272277832,47.8613319397],"type":"Point"}
}