{
  "type": "Feature",
  "properties": {
    "iso:country":"DE",
    "sg:address":"Thurow 24",
    "sg:city":"R\u00f6dlin-Thurow",
    "sg:phone":"+49 39826/12701",
    "sg:postcode":"17237",
    "sg:province":"Mecklenburg-Vorpommern",
    "wof:name":"Dieter Engler",
    "wof:placetype":"venue"
},
  "geometry": {"coordinates":[13.1787567139,53.3747062683],"type":"Point"}
}