{
  "type": "Feature",
  "properties": {
    "iso:country":"DE",
    "sg:address":"Kolpingstr. 1",
    "sg:city":"Collenberg",
    "sg:phone":"+49 9376/180",
    "sg:postcode":"97903",
    "sg:province":"Bayern",
    "wof:name":"Stumpf",
    "wof:placetype":"venue"
},
  "geometry": {"coordinates":[9.33145,49.772331],"type":"Point"}
}