{
  "type": "Feature",
  "properties": {
    "iso:country":"DE",
    "sg:address":"Eiserweg 47 A",
    "sg:city":"R\u00f6srath",
    "sg:postcode":"51503",
    "sg:province":"Nordrhein-Westfalen",
    "wof:name":"Tanz-forum K\u00f6ln Gmbh",
    "wof:placetype":"venue"
},
  "geometry": {"coordinates":[7.153441906,50.9063644409],"type":"Point"}
}