{
  "type": "Feature",
  "properties": {
    "iso:country":"DE",
    "sg:address":"Am Maradies",
    "sg:city":"Marktheidenfeld",
    "sg:phone":"+49 9391/4131",
    "sg:postcode":"97828",
    "sg:province":"Bayern",
    "wof:name":"Maradies-freizeitzentrum",
    "wof:placetype":"venue"
},
  "geometry": {"coordinates":[9.61703,49.849636],"type":"Point"}
}