{
  "type": "Feature",
  "properties": {
    "iso:country":"DE",
    "sg:address":"Tabakried 11",
    "sg:city":"Pfeffenhausen",
    "sg:phone":"+49 8782",
    "sg:postcode":"84076",
    "sg:province":"Bayern",
    "wof:name":"Gebrauchte Landmaschinen",
    "wof:placetype":"venue"
},
  "geometry": {"coordinates":[11.9061031342,48.6684188843],"type":"Point"}
}