{
  "type": "Feature",
  "properties": {
    "iso:country":"DE",
    "sg:address":"Hindenburgstr. 29",
    "sg:city":"Langenau",
    "sg:phone":"+49 4973/458010",
    "sg:postcode":"89129",
    "sg:province":"Baden-W\u00fcrttemberg",
    "wof:name":"Lobinger Hotels Gmbh",
    "wof:placetype":"venue"
},
  "geometry": {"coordinates":[10.119049,48.496292],"type":"Point"}
}