{
  "type": "Feature",
  "properties": {
    "iso:country":"DE",
    "sg:address":"Linsenstr. 14",
    "sg:city":"M\u00fchlhausen",
    "sg:phone":"+49 36018/16434",
    "sg:postcode":"99974",
    "sg:province":"Th\u00fcringen",
    "wof:name":"Detlev Janke",
    "wof:placetype":"venue"
},
  "geometry": {"coordinates":[10.4581804276,51.207611084],"type":"Point"}
}