{
  "type": "Feature",
  "properties": {
    "iso:country":"DE",
    "sg:address":"Wetterauer Str. 4",
    "sg:city":"Karben",
    "sg:phone":"+49 6034/3957",
    "sg:postcode":"61184",
    "sg:province":"Hessen",
    "wof:name":"Klaus Eifler Architekt",
    "wof:placetype":"venue"
},
  "geometry": {"coordinates":[8.797827,50.257832],"type":"Point"}
}