{
  "type": "Feature",
  "properties": {
    "iso:country":"DE",
    "sg:address":"Natrup-Hagener-Str. 1",
    "sg:city":"Tecklenburg",
    "sg:phone":"+49 5481/93650",
    "sg:postcode":"49545",
    "sg:province":"Nordrhein-Westfalen",
    "wof:name":"Reinhard Juraschka Steuerberater",
    "wof:placetype":"venue"
},
  "geometry": {"coordinates":[7.8925299644,52.2193336487],"type":"Point"}
}