{
  "type": "Feature",
  "properties": {
    "iso:country":"DE",
    "sg:address":"Heudorfer Str. 5",
    "sg:city":"Worpswede",
    "sg:phone":"+49 4794/235",
    "sg:postcode":"27726",
    "sg:province":"Niedersachsen",
    "wof:name":"Herbert Wendelken",
    "wof:placetype":"venue"
},
  "geometry": {"coordinates":[8.9938726425,53.2887077332],"type":"Point"}
}