{
  "type": "Feature",
  "properties": {
    "iso:country":"DE",
    "sg:address":"Neue Str. 12",
    "sg:city":"Bad Urach",
    "sg:phone":"+49 7125/4155",
    "sg:postcode":"72574",
    "sg:province":"Baden-W\u00fcrttemberg",
    "wof:name":"Reformhaus Hiller Gmbh",
    "wof:placetype":"venue"
},
  "geometry": {"coordinates":[9.4009666443,48.4927711487],"type":"Point"}
}