{
  "type": "Feature",
  "properties": {
    "iso:country":"DE",
    "sg:address":"Schmiedeweg 8",
    "sg:city":"Sohland",
    "sg:postcode":"02689",
    "sg:province":"Sachsen",
    "wof:name":"Katholisches Pfarramt Sohland",
    "wof:placetype":"venue"
},
  "geometry": {"coordinates":[14.3773174286,51.0537147522],"type":"Point"}
}