{
  "type": "Feature",
  "properties": {
    "iso:country":"DE",
    "sg:address":"Schramberger Str. 36",
    "sg:city":"Berlin",
    "sg:phone":"+49 30/4048236",
    "sg:postcode":"13467",
    "sg:province":"Berlin",
    "wof:name":"Erich Wimmer",
    "wof:placetype":"venue"
},
  "geometry": {"coordinates":[13.304268837,52.6181144714],"type":"Point"}
}