{
  "type": "Feature",
  "properties": {
    "iso:country":"DE",
    "sg:address":"Beim Breitenstein 23",
    "sg:city":"Efringen-Kirchen",
    "sg:phone":"+49 4972/346538",
    "sg:postcode":"79588",
    "sg:province":"Baden-W\u00fcrttemberg",
    "wof:name":"Ottmar Mayer Pr\u00c4zisions- Drehteile Gmbh",
    "wof:placetype":"venue"
},
  "geometry": {"coordinates":[8.76902,48.820274],"type":"Point"}
}