{
  "type": "Feature",
  "properties": {
    "iso:country":"DE",
    "sg:address":"Am Franzenbach 15",
    "sg:city":"Merzig",
    "sg:phone":"+49 6861/2228",
    "sg:postcode":"66663",
    "sg:province":"Saarland",
    "wof:name":"Walter Konz",
    "wof:placetype":"venue"
},
  "geometry": {"coordinates":[6.673227,49.470005],"type":"Point"}
}