{
  "type": "Feature",
  "properties": {
    "iso:country":"DE",
    "sg:address":"Keplerstr. 14",
    "sg:city":"Wenzenbach",
    "sg:phone":"+49 9407/30157",
    "sg:postcode":"93173",
    "sg:province":"Bayern",
    "wof:name":"W. Schwank Jun.",
    "wof:placetype":"venue"
},
  "geometry": {"coordinates":[12.1926994324,49.0717697144],"type":"Point"}
}