{
  "type": "Feature",
  "properties": {
    "iso:country":"DE",
    "sg:address":"Rackwitzer Str. 39 a",
    "sg:city":"Kletzen-Zsch\u00f6lkau",
    "sg:phone":"+49 34294/7730",
    "sg:postcode":"04519",
    "sg:province":"Sachsen",
    "wof:name":"Taf Gmbh",
    "wof:placetype":"venue"
},
  "geometry": {"coordinates":[12.379872,51.450665],"type":"Point"}
}