{
  "type": "Feature",
  "properties": {
    "iso:country":"DE",
    "sg:address":"Obergasse 3",
    "sg:city":"Bad Homburg",
    "sg:phone":"+49 6172/22549",
    "sg:postcode":"61348",
    "sg:province":"Hessen",
    "wof:name":"Peter St\u00f6ckel",
    "wof:placetype":"venue"
},
  "geometry": {"coordinates":[8.6112642288,50.2309074402],"type":"Point"}
}