{
  "type": "Feature",
  "properties": {
    "iso:country":"DE",
    "sg:address":"Friedenstr. 60",
    "sg:city":"Solingen",
    "sg:phone":"+49 212/2640160",
    "sg:postcode":"42699",
    "sg:province":"Nordrhein-Westfalen",
    "wof:name":"Groka M\u00e4rkte",
    "wof:placetype":"venue"
},
  "geometry": {"coordinates":[7.0220098495,51.1545410156],"type":"Point"}
}