{
  "type": "Feature",
  "properties": {
    "iso:country":"DE",
    "sg:address":"Brauerstr. 50",
    "sg:city":"Karlsruhe",
    "sg:phone":"+49 721/828060",
    "sg:postcode":"76135",
    "sg:province":"Baden-W\u00fcrttemberg",
    "wof:name":"Tmg Technologie Management Gruppe I-tec Ges. F\u00fcr Industr.",
    "wof:placetype":"venue"
},
  "geometry": {"coordinates":[8.38567,48.998829],"type":"Point"}
}