{
  "type": "Feature",
  "properties": {
    "iso:country":"DE",
    "sg:address":"Hauptstr. 71 a",
    "sg:city":"Homburg",
    "sg:phone":"+49 6848/202",
    "sg:postcode":"66424",
    "sg:province":"Saarland",
    "wof:name":"Josef Klein",
    "wof:placetype":"venue"
},
  "geometry": {"coordinates":[7.317797,49.269955],"type":"Point"}
}