{
  "type": "Feature",
  "properties": {
    "iso:country":"DE",
    "sg:address":"Scheuerlenstr. 22",
    "sg:city":"Titisee-Neustadt",
    "sg:phone":"+49 7651/7558",
    "sg:postcode":"79822",
    "sg:province":"Baden-W\u00fcrttemberg",
    "wof:name":"Spritzenh\u00e4usle",
    "wof:placetype":"venue"
},
  "geometry": {"coordinates":[8.2146167755,47.9134178162],"type":"Point"}
}