{
  "type": "Feature",
  "properties": {
    "iso:country":"DE",
    "sg:address":"Weiserlenstr. 19",
    "sg:city":"Freiburg",
    "sg:phone":"+49 761/152255",
    "sg:postcode":"79119",
    "sg:province":"Niedersachsen",
    "wof:name":"Antony Kalender Design",
    "wof:placetype":"venue"
},
  "geometry": {"coordinates":[7.809618,48.040649],"type":"Point"}
}