{
  "type": "Feature",
  "properties": {
    "iso:country":"DE",
    "sg:address":"postfach 1241",
    "sg:city":"peiting",
    "sg:phone":"+49 8861/9309490",
    "sg:postcode":"86968",
    "sg:province":"Bayern",
    "wof:name":"Auftragsbeschaffung F\u00fcr Callcenter Bietet Pronto Werbung",
    "wof:placetype":"venue"
},
  "geometry": {"coordinates":[10.92367,47.7943],"type":"Point"}
}