{
  "type": "Feature",
  "properties": {
    "iso:country":"DE",
    "sg:address":"Findorffstr. 94",
    "sg:city":"Bremen",
    "sg:phone":"+49 421/354207",
    "sg:postcode":"28215",
    "sg:province":"Bremen",
    "wof:name":"Massagepraxis Findorff",
    "wof:placetype":"venue"
},
  "geometry": {"coordinates":[8.811407,53.089512],"type":"Point"}
}