{
  "type": "Feature",
  "properties": {
    "iso:country":"DE",
    "sg:address":"Alemannenstr. 2",
    "sg:city":"Geisenfeld",
    "sg:phone":"+49 8457/930885",
    "sg:postcode":"85290",
    "sg:province":"Bayern",
    "wof:name":"Top Discothek",
    "wof:placetype":"venue"
},
  "geometry": {"coordinates":[11.628122,48.73843],"type":"Point"}
}