{
  "type": "Feature",
  "properties": {
    "iso:country":"DE",
    "sg:address":"Hedern 8",
    "sg:city":"Frankenfeld",
    "sg:phone":"+49 5165/3961",
    "sg:postcode":"27336",
    "sg:province":"Niedersachsen",
    "wof:name":"J\u00fcrgen Poppe",
    "wof:placetype":"venue"
},
  "geometry": {"coordinates":[9.406655,52.77177],"type":"Point"}
}