{
  "type": "Feature",
  "properties": {
    "iso:country":"DE",
    "sg:address":"Rudolf-Breitscheid-Str. 14",
    "sg:city":"Bad Salzungen",
    "sg:phone":"+49 3695/2543",
    "sg:postcode":"36433",
    "sg:province":"Th\u00fcringen",
    "wof:name":"Heinrich Eichhorn Gmbh",
    "wof:placetype":"venue"
},
  "geometry": {"coordinates":[10.2327804565,50.8125801086],"type":"Point"}
}