{
  "type": "Feature",
  "properties": {
    "iso:country":"DE",
    "sg:address":"Iburger Str. 82a",
    "sg:city":"Osnabr\u00fcck",
    "sg:phone":"+49 541/53564",
    "sg:postcode":"49082",
    "sg:province":"Niedersachsen",
    "wof:name":"K\u00f6nemann",
    "wof:placetype":"venue"
},
  "geometry": {"coordinates":[8.0568189621,52.2586364746],"type":"Point"}
}