{
  "type": "Feature",
  "properties": {
    "iso:country":"DE",
    "sg:address":"Brandshofer Deich 27",
    "sg:city":"Hamburg",
    "sg:phone":"+49 40/784045",
    "sg:postcode":"20539",
    "sg:province":"Hamburg",
    "wof:name":"Otg Oberer Transport Gmbh",
    "wof:placetype":"venue"
},
  "geometry": {"coordinates":[10.0281057358,53.5387001038],"type":"Point"}
}