{
  "type": "Feature",
  "properties": {
    "iso:country":"DE",
    "sg:address":"Am Moosbach 1-3",
    "sg:city":"Mainhardt",
    "sg:phone":"+49 7903",
    "sg:postcode":"74535",
    "sg:province":"Baden-W\u00fcrttemberg",
    "wof:name":"W. H\u00e4fele - Transporte, Heiz\u00f6lhandel",
    "wof:placetype":"venue"
},
  "geometry": {"coordinates":[9.5597400665,49.0758399963],"type":"Point"}
}