{
  "type": "Feature",
  "properties": {
    "iso:country":"DE",
    "sg:address":"Weingartenstr. 57",
    "sg:city":"Bernkastel-Kues",
    "sg:phone":"+49 6531/91173",
    "sg:postcode":"54470",
    "sg:province":"Rheinland-Pfalz",
    "wof:name":"Herbert Port-roels Weinanbau",
    "wof:placetype":"venue"
},
  "geometry": {"coordinates":[7.0569300652,49.9113349915],"type":"Point"}
}