{
  "type": "Feature",
  "properties": {
    "iso:country":"DE",
    "sg:address":"Sch\u00f6neberger Str. 29",
    "sg:city":"Pattensen",
    "sg:phone":"+49 5101/1793",
    "sg:postcode":"30982",
    "sg:province":"Niedersachsen",
    "wof:name":"Peter Thomas Rechtsanwalt",
    "wof:placetype":"venue"
},
  "geometry": {"coordinates":[9.7662506104,52.2697410583],"type":"Point"}
}