{
  "type": "Feature",
  "properties": {
    "iso:country":"DE",
    "sg:address":"Friedrich-Ebert-Str. 39",
    "sg:city":"W\u00f6rrstadt",
    "sg:phone":"+49 6732/1046",
    "sg:postcode":"55286",
    "sg:province":"Rheinland-Pfalz",
    "wof:name":"H. Kraft Und K. H. N\u00f6th",
    "wof:placetype":"venue"
},
  "geometry": {"coordinates":[8.114974,49.840191],"type":"Point"}
}