{
  "type": "Feature",
  "properties": {
    "iso:country":"DE",
    "sg:address":"Mittenwalder Str. 6",
    "sg:city":"Gro\u00df Machnow",
    "sg:phone":"+49 33708/22522",
    "sg:postcode":"15806",
    "sg:province":"Brandenburg",
    "wof:name":"Land Und Tier Gro\u00df Manchnow Agrar Gmbh",
    "wof:placetype":"venue"
},
  "geometry": {"coordinates":[13.470431,52.275543],"type":"Point"}
}