{
  "type": "Feature",
  "properties": {
    "iso:country":"DE",
    "sg:address":"Roitzscher Str.23",
    "sg:city":"Dresden",
    "sg:phone":"+49 351/4226883",
    "sg:postcode":"01157",
    "sg:province":"Sachsen",
    "wof:name":"Rainer Hesse - Import Export",
    "wof:placetype":"venue"
},
  "geometry": {"coordinates":[13.652922,51.053638],"type":"Point"}
}