{
  "type": "Feature",
  "properties": {
    "iso:country":"DE",
    "sg:address":"Obervielander Str. 63",
    "sg:city":"Bremen",
    "sg:phone":"+49 421/581516",
    "sg:postcode":"28259",
    "sg:province":"Bremen",
    "wof:name":"Wulfers Reisen",
    "wof:placetype":"venue"
},
  "geometry": {"coordinates":[8.7313318253,53.0525436401],"type":"Point"}
}