{
  "type": "Feature",
  "properties": {
    "iso:country":"DE",
    "sg:address":"Holtenauer Str. 38",
    "sg:city":"Kiel",
    "sg:phone":"+49 431/578355",
    "sg:postcode":"24105",
    "sg:province":"Schleswig-Holstein",
    "wof:name":"S. Wiens",
    "wof:placetype":"venue"
},
  "geometry": {"coordinates":[10.132294,54.330894],"type":"Point"}
}