{
  "type": "Feature",
  "properties": {
    "iso:country":"DE",
    "sg:address":"J\u00e4gerstr. 59",
    "sg:city":"Berlin",
    "sg:phone":"+49 30/3245135",
    "sg:postcode":"10117",
    "sg:province":"Berlin",
    "wof:name":"Gerald Schindler",
    "wof:placetype":"venue"
},
  "geometry": {"coordinates":[13.390386,52.514076],"type":"Point"}
}