{
  "type": "Feature",
  "properties": {
    "iso:country":"DE",
    "sg:address":"Senefelder Str 1",
    "sg:city":"Rodgau",
    "sg:phone":"+49 6106/74075",
    "sg:postcode":"63110",
    "sg:province":"Hessen",
    "wof:name":"Sepro Robotique Gmbh",
    "wof:placetype":"venue"
},
  "geometry": {"coordinates":[8.867816925,49.9889259338],"type":"Point"}
}