{
  "type": "Feature",
  "properties": {
    "iso:country":"DE",
    "sg:address":"Riedingerstr. 7",
    "sg:city":"Essen",
    "sg:phone":"+49 4920/1314091",
    "sg:postcode":"45141",
    "sg:province":"Nordrhein-Westfalen",
    "wof:name":"P\u00dcschel Gmbh",
    "wof:placetype":"venue"
},
  "geometry": {"coordinates":[7.002942,51.472816],"type":"Point"}
}