{
  "type": "Feature",
  "properties": {
    "iso:country":"DE",
    "sg:address":"Felder Bruchstr. 23",
    "sg:city":"Riede",
    "sg:phone":"+49 4294/344",
    "sg:postcode":"27339",
    "sg:province":"Niedersachsen",
    "wof:name":"Dietrich K\u00f6hler",
    "wof:placetype":"venue"
},
  "geometry": {"coordinates":[8.941307,52.944447],"type":"Point"}
}