{
  "type": "Feature",
  "properties": {
    "iso:country":"DE",
    "sg:address":"Carl-Orff-Ring 14",
    "sg:city":"Rodgau",
    "sg:phone":"+49 6106/14912",
    "sg:postcode":"63110",
    "sg:province":"Hessen",
    "wof:name":"Alte Kreuzm\u00fchle Gmbh",
    "wof:placetype":"venue"
},
  "geometry": {"coordinates":[8.8899869919,50.0327262878],"type":"Point"}
}