{
  "type": "Feature",
  "properties": {
    "iso:country":"DE",
    "sg:address":"Biedenbergstr. 22",
    "sg:city":"Hauenstein",
    "sg:phone":"+49 6392/7841",
    "sg:postcode":"76846",
    "sg:province":"Rheinland-Pfalz",
    "wof:name":"Wolfgang Herold Heilpraktiker",
    "wof:placetype":"venue"
},
  "geometry": {"coordinates":[7.8304781914,49.1955375671],"type":"Point"}
}