{
  "type": "Feature",
  "properties": {
    "iso:country":"DE",
    "sg:address":"In Der Hollerhecke 1",
    "sg:city":"Worms",
    "sg:phone":"+49 4962/414030",
    "sg:postcode":"67547",
    "sg:province":"Rheinland-Pfalz",
    "wof:name":"Grace Gmbh",
    "wof:placetype":"venue"
},
  "geometry": {"coordinates":[8.356315,49.662712],"type":"Point"}
}