{
  "type": "Feature",
  "properties": {
    "iso:country":"DE",
    "sg:address":"Tenholter Str. 85",
    "sg:city":"Erkelenz",
    "sg:phone":"+49 2431/81174",
    "sg:postcode":"41812",
    "sg:province":"Nordrhein-Westfalen",
    "wof:name":"Rolf U. Monika Tjeerdstra Immobilienmakler",
    "wof:placetype":"venue"
},
  "geometry": {"coordinates":[6.3144421577,51.0701255798],"type":"Point"}
}