{
  "type": "Feature",
  "properties": {
    "iso:country":"DE",
    "sg:address":"Gr\u00fcner Weg 23",
    "sg:city":"W\u00fcrselen",
    "sg:phone":"+49 2405/73992",
    "sg:postcode":"52146",
    "sg:province":"Nordrhein-Westfalen",
    "wof:name":"Willi Becker",
    "wof:placetype":"venue"
},
  "geometry": {"coordinates":[6.166621,50.829552],"type":"Point"}
}