{
  "type": "Feature",
  "properties": {
    "iso:country":"DE",
    "sg:address":"Rheinstr. 5",
    "sg:city":"Neitersen",
    "sg:phone":"+49 2681/6911",
    "sg:postcode":"57638",
    "sg:province":"Rheinland-Pfalz",
    "wof:name":"C. Weller",
    "wof:placetype":"venue"
},
  "geometry": {"coordinates":[7.5911707878,50.6675491333],"type":"Point"}
}