{
  "type": "Feature",
  "properties": {
    "iso:country":"DE",
    "sg:address":"K\u00f6lner Str. 65-67",
    "sg:city":"Kierspe",
    "sg:phone":"+49 2359/291099",
    "sg:postcode":"58566",
    "sg:province":"Nordrhein-Westfalen",
    "wof:name":"S & M Telefonvertrieb Gmbh",
    "wof:placetype":"venue"
},
  "geometry": {"coordinates":[7.6138110161,51.126209259],"type":"Point"}
}