{
  "type": "Feature",
  "properties": {
    "iso:country":"DE",
    "sg:address":"Bergstr. 1",
    "sg:city":"Bischoffen",
    "sg:phone":"+49 6444/309",
    "sg:postcode":"35649",
    "sg:province":"Hessen",
    "wof:name":"Ch-hilfs- Und Notfunk Gemeinschaft E. V.",
    "wof:placetype":"venue"
},
  "geometry": {"coordinates":[8.4512405396,50.7031936646],"type":"Point"}
}