{
  "type": "Feature",
  "properties": {
    "iso:country":"DE",
    "sg:address":"Im Berg 18",
    "sg:city":"Neunburg",
    "sg:phone":"+49 9672/869",
    "sg:postcode":"92431",
    "sg:province":"Bayern",
    "wof:name":"Kath. \u00d6ffentliche B\u00fccherei",
    "wof:placetype":"venue"
},
  "geometry": {"coordinates":[12.38447,49.348839],"type":"Point"}
}