{
  "type": "Feature",
  "properties": {
    "iso:country":"DE",
    "sg:address":"Edith-Stein-Str. 18",
    "sg:city":"M\u00fcnster",
    "sg:postcode":"64839",
    "sg:province":"Hessen",
    "wof:name":"Witze Und Anekdoten",
    "wof:placetype":"venue"
},
  "geometry": {"coordinates":[8.868237,49.926208],"type":"Point"}
}