{
  "type": "Feature",
  "properties": {
    "iso:country":"DE",
    "sg:address":"Birkenfelder Str. 29",
    "sg:city":"Saarbr\u00fccken",
    "sg:phone":"+49 681/47293",
    "sg:postcode":"66113",
    "sg:province":"Saarland",
    "wof:name":"H. Und M. Thamerus",
    "wof:placetype":"venue"
},
  "geometry": {"coordinates":[6.994102,49.24987],"type":"Point"}
}