{
  "type": "Feature",
  "properties": {
    "iso:country":"DE",
    "sg:address":"Ritter-Tuschl-Str. 40",
    "sg:city":"Aldersbach",
    "sg:phone":"+49 8543/917801",
    "sg:postcode":"94501",
    "sg:province":"Bayern",
    "wof:name":"Maier Elektro Gmbh",
    "wof:placetype":"venue"
},
  "geometry": {"coordinates":[13.0928964615,48.5898704529],"type":"Point"}
}