{
  "type": "Feature",
  "properties": {
    "iso:country":"DE",
    "sg:address":"Hainstr. 16",
    "sg:city":"Leipzig",
    "sg:phone":"+49 341/2118462",
    "sg:postcode":"04109",
    "sg:province":"Sachsen",
    "wof:name":"A. Ritter Und Dr. Kretzschmar Rechtsanw\u00e4lte",
    "wof:placetype":"venue"
},
  "geometry": {"coordinates":[12.3737564087,51.3421325684],"type":"Point"}
}