{
  "type": "Feature",
  "properties": {
    "iso:country":"DE",
    "sg:address":"Danziger Str. 12",
    "sg:city":"Hemsbach",
    "sg:phone":"+49 6201/592075",
    "sg:postcode":"69502",
    "sg:province":"Baden-W\u00fcrttemberg",
    "wof:name":"Blanca Biochemische Produkte Vertriebsgesellschaft Mbh",
    "wof:placetype":"venue"
},
  "geometry": {"coordinates":[8.642692,49.590843],"type":"Point"}
}