{
  "type": "Feature",
  "properties": {
    "iso:country":"DE",
    "sg:address":"Hauptstr. 35",
    "sg:city":"Badbergen",
    "sg:postcode":"49635",
    "sg:province":"Niedersachsen",
    "wof:name":"Hubert Riedel",
    "wof:placetype":"venue"
},
  "geometry": {"coordinates":[7.9815468788,52.6404876709],"type":"Point"}
}