{
  "type": "Feature",
  "properties": {
    "iso:country":"DE",
    "sg:address":"Am B\u00f6hler Pfad 13",
    "sg:city":"Hochdorf-Assenheim",
    "sg:phone":"+49 6231/98634",
    "sg:postcode":"67126",
    "sg:province":"Rheinland-Pfalz",
    "wof:name":"Horst Gl\u00e4ser",
    "wof:placetype":"venue"
},
  "geometry": {"coordinates":[8.2745294571,49.413318634],"type":"Point"}
}