{
  "type": "Feature",
  "properties": {
    "iso:country":"DE",
    "sg:address":"K\u00f6nigstr. 62",
    "sg:city":"Buckow",
    "sg:phone":"+49 33433/57444",
    "sg:postcode":"15377",
    "sg:province":"Brandenburg",
    "wof:name":"B. Michaelis",
    "wof:placetype":"venue"
},
  "geometry": {"coordinates":[14.0779848099,52.5669593811],"type":"Point"}
}