{
  "type": "Feature",
  "properties": {
    "iso:country":"DE",
    "sg:address":"J\u00fcrgen-Gl\u00fce-Koppel 30",
    "sg:city":"Ratekau",
    "sg:phone":"+49 4504/1713",
    "sg:postcode":"23626",
    "sg:province":"Schleswig-Holstein",
    "wof:name":"F. Scharfenberg",
    "wof:placetype":"venue"
},
  "geometry": {"coordinates":[10.7307481766,53.9464759827],"type":"Point"}
}