{
  "type": "Feature",
  "properties": {
    "iso:country":"DE",
    "sg:address":"Bogenstr. 3",
    "sg:city":"Pinneberg",
    "sg:phone":"+49 4941/0158500",
    "sg:postcode":"25421",
    "sg:province":"Schleswig-Holstein",
    "wof:name":"Cst Gmbh",
    "wof:placetype":"venue"
},
  "geometry": {"coordinates":[9.8174266815,53.6458892822],"type":"Point"}
}