{
  "type": "Feature",
  "properties": {
    "iso:country":"DE",
    "sg:address":"Schlo\u00dfstr. 14",
    "sg:city":"Koblenz",
    "sg:phone":"+49 261/34111",
    "sg:postcode":"56068",
    "sg:province":"Rheinland-Pfalz",
    "wof:name":"Hans-j\u00fcrgen H\u00f6rnberger Sven-ingo K\u00f6lzsch",
    "wof:placetype":"venue"
},
  "geometry": {"coordinates":[7.596353054,50.3566360474],"type":"Point"}
}