{
  "type": "Feature",
  "properties": {
    "iso:country":"DE",
    "sg:address":"Hauptstr. 55",
    "sg:city":"Bad Nenndorf",
    "sg:phone":"+49 5723/4387",
    "sg:postcode":"31542",
    "sg:province":"Niedersachsen",
    "wof:name":"B. B\u00f6lsing",
    "wof:placetype":"venue"
},
  "geometry": {"coordinates":[9.3867845535,52.3379325867],"type":"Point"}
}