{
  "type": "Feature",
  "properties": {
    "iso:country":"DE",
    "sg:address":"Alte Dorfstr. 21",
    "sg:city":"R\u00f6dinghausen",
    "sg:phone":"+49 5746/8655",
    "sg:postcode":"32289",
    "sg:province":"Nordrhein-Westfalen",
    "wof:name":"P\u00f6sse-blumenbinderei",
    "wof:placetype":"venue"
},
  "geometry": {"coordinates":[8.478753,52.253658],"type":"Point"}
}