{
  "type": "Feature",
  "properties": {
    "iso:country":"DE",
    "sg:address":"Am Redder 36",
    "sg:city":"Klein Nordende",
    "sg:phone":"+49 4121/91453",
    "sg:postcode":"25336",
    "sg:province":"Schleswig-Holstein",
    "wof:name":"Bernd Schulz",
    "wof:placetype":"venue"
},
  "geometry": {"coordinates":[9.655426,53.723969],"type":"Point"}
}