{
  "type": "Feature",
  "properties": {
    "iso:country":"DE",
    "sg:address":"Helmholtzstr. 17 B",
    "sg:city":"Potsdam",
    "sg:phone":"+49 331/28150",
    "sg:postcode":"14467",
    "sg:province":"Brandenburg",
    "wof:name":"Stardust Rental Gmbh",
    "wof:placetype":"venue"
},
  "geometry": {"coordinates":[13.072366,52.407558],"type":"Point"}
}