{
  "type": "Feature",
  "properties": {
    "iso:country":"DE",
    "sg:address":"Rabenwiesenstr. 41",
    "sg:city":"S\u00fc\u00dfen",
    "sg:phone":"+49 7162/6511",
    "sg:postcode":"73079",
    "sg:province":"Baden-W\u00fcrttemberg",
    "wof:name":"Helmut Nickl Ingenieur",
    "wof:placetype":"venue"
},
  "geometry": {"coordinates":[9.7415008545,48.6762886047],"type":"Point"}
}