{
  "type": "Feature",
  "properties": {
    "iso:country":"DE",
    "sg:address":"Ludwigstr. 7",
    "sg:city":"Neu-Ulm",
    "sg:phone":"+49 731/77251",
    "sg:postcode":"89231",
    "sg:province":"Bayern",
    "wof:name":"Albert Albrecht Ohg",
    "wof:placetype":"venue"
},
  "geometry": {"coordinates":[10.0015077591,48.394329071],"type":"Point"}
}