{
  "type": "Feature",
  "properties": {
    "iso:country":"DE",
    "sg:address":"Schwerter Str. 71a",
    "sg:city":"Hagen",
    "sg:phone":"+49 2331/687963",
    "sg:postcode":"58099",
    "sg:province":"Nordrhein-Westfalen",
    "wof:name":"Tura 1872 Hagen E. V. Manfred Busch",
    "wof:placetype":"venue"
},
  "geometry": {"coordinates":[7.463121891,51.3888015747],"type":"Point"}
}