{
  "type": "Feature",
  "properties": {
    "iso:country":"DE",
    "sg:address":"Eibacher Hauptstr. 66",
    "sg:city":"N\u00fcrnberg",
    "sg:postcode":"90451",
    "sg:province":"Bayern",
    "wof:name":"Euro-immobilien N\u00fcrnberg",
    "wof:placetype":"venue"
},
  "geometry": {"coordinates":[11.0352277756,49.4027519226],"type":"Point"}
}