{
  "type": "Feature",
  "properties": {
    "iso:country":"DE",
    "sg:address":"Bogenstr. 10",
    "sg:city":"Zirndorf",
    "sg:phone":"+49 911/605139",
    "sg:postcode":"90513",
    "sg:province":"Bayern",
    "wof:name":"Renate Maxeiner-balkow",
    "wof:placetype":"venue"
},
  "geometry": {"coordinates":[10.96441,49.440529],"type":"Point"}
}