{
  "type": "Feature",
  "properties": {
    "iso:country":"DE",
    "sg:address":"K\u00f6nigsdorfer Str. 69",
    "sg:city":"Bad T\u00f6lz",
    "sg:phone":"+49 8041/76590",
    "sg:postcode":"83646",
    "sg:province":"Bayern",
    "wof:name":"Seniorenheim Pater-ruper-mayer-heim",
    "wof:placetype":"venue"
},
  "geometry": {"coordinates":[11.549514,47.762585],"type":"Point"}
}