{
  "type": "Feature",
  "properties": {
    "iso:country":"DE",
    "sg:address":"Bahnhofstra\u00dfe 68",
    "sg:city":"Niederorschel",
    "sg:phone":"+49 36076/50298",
    "sg:postcode":"37355",
    "sg:province":"Th\u00fcringen",
    "wof:name":"Werbetechnik M\u00fcller",
    "wof:placetype":"venue"
},
  "geometry": {"coordinates":[10.419159,51.377254],"type":"Point"}
}