{
  "type": "Feature",
  "properties": {
    "iso:country":"DE",
    "sg:address":"Tautewalde 30",
    "sg:city":"Wilthen",
    "sg:phone":"+49 3592/32939",
    "sg:postcode":"02681",
    "sg:province":"Sachsen",
    "wof:name":"Gottfried Lerche",
    "wof:placetype":"venue"
},
  "geometry": {"coordinates":[14.360973,51.09861],"type":"Point"}
}