{
  "type": "Feature",
  "properties": {
    "iso:country":"DE",
    "sg:address":"Hintergasse 25-27",
    "sg:city":"Kusel",
    "sg:phone":"+49 6381/2189",
    "sg:postcode":"66869",
    "sg:province":"Rheinland-Pfalz",
    "wof:name":"Jakob Kuhn, S\u00f6hne Gmbh & Co. Kg",
    "wof:placetype":"venue"
},
  "geometry": {"coordinates":[7.401456,49.538513],"type":"Point"}
}