{
  "type": "Feature",
  "properties": {
    "iso:country":"DE",
    "sg:address":"Fuggerstr. 11",
    "sg:city":"Bielefeld",
    "sg:phone":"+49 5205/9401",
    "sg:postcode":"33689",
    "sg:province":"Nordrhein-Westfalen",
    "wof:name":"Ava Immobilien Und Anlagenverwaltungs-gmbh",
    "wof:placetype":"venue"
},
  "geometry": {"coordinates":[8.562491,51.944984],"type":"Point"}
}