{
  "type": "Feature",
  "properties": {
    "iso:country":"DE",
    "sg:address":"Plauer Chaussee 22b",
    "sg:city":"Krakow",
    "sg:postcode":"18292",
    "sg:province":"Mecklenburg-Vorpommern",
    "wof:name":"Altmann-k\u00fchl Bau Gmbh",
    "wof:placetype":"venue"
},
  "geometry": {"coordinates":[12.266276,53.648529],"type":"Point"}
}