{
  "type": "Feature",
  "properties": {
    "iso:country":"DE",
    "sg:address":"Marktstr. 4",
    "sg:city":"Glan-M\u00fcnchweiler",
    "sg:phone":"+49 6383/7756",
    "sg:postcode":"66907",
    "sg:province":"Rheinland-Pfalz",
    "wof:name":"Willi Ohliger",
    "wof:placetype":"venue"
},
  "geometry": {"coordinates":[7.439884,49.472023],"type":"Point"}
}