{
  "type": "Feature",
  "properties": {
    "iso:country":"DE",
    "sg:address":"Detmolder Str. 261",
    "sg:city":"Bielefeld",
    "sg:phone":"+49 521/2389292",
    "sg:postcode":"33605",
    "sg:province":"Nordrhein-Westfalen",
    "wof:name":"Golf Discount Vertriebs Gmbh & Co. Kg",
    "wof:placetype":"venue"
},
  "geometry": {"coordinates":[8.563373,52.00362],"type":"Point"}
}