{
  "type": "Feature",
  "properties": {
    "iso:country":"DE",
    "sg:address":"Schnuckenstall 2",
    "sg:city":"Verden",
    "sg:phone":"+49 4236/93030",
    "sg:postcode":"27283",
    "sg:province":"Niedersachsen",
    "wof:name":"G. Ziech Gmbh Kachelofen- Und Kaminbau",
    "wof:placetype":"venue"
},
  "geometry": {"coordinates":[9.2853841782,52.9359931946],"type":"Point"}
}