{
  "type": "Feature",
  "properties": {
    "iso:country":"DE",
    "sg:address":"Industriestr. 10",
    "sg:city":"Arberg",
    "sg:postcode":"91722",
    "sg:province":"Bayern",
    "wof:name":"Antritt Veraltungs- Und Beteiligungs- Gmbh",
    "wof:placetype":"venue"
},
  "geometry": {"coordinates":[10.6174650192,49.1475524902],"type":"Point"}
}