{
  "type": "Feature",
  "properties": {
    "iso:country":"DE",
    "sg:address":"Herrnstr. 1",
    "sg:city":"Wolnzach",
    "sg:phone":"+49 8442/3431",
    "sg:postcode":"85283",
    "sg:province":"Bayern",
    "wof:name":"H. Werkmann",
    "wof:placetype":"venue"
},
  "geometry": {"coordinates":[11.6261081696,48.6039276123],"type":"Point"}
}