{
  "type": "Feature",
  "properties": {
    "iso:country":"DE",
    "sg:address":"H\u00fcttenstr. 30",
    "sg:city":"Altenau",
    "sg:phone":"+49 5328/8320",
    "sg:postcode":"38707",
    "sg:province":"Niedersachsen",
    "wof:name":"Helmut Heller",
    "wof:placetype":"venue"
},
  "geometry": {"coordinates":[10.437829,51.807728],"type":"Point"}
}