{
  "type": "Feature",
  "properties": {
    "iso:country":"DE",
    "sg:address":"Albrechtstr. 31",
    "sg:city":"M\u00fcnchen",
    "sg:phone":"+49 89/187697",
    "sg:postcode":"80636",
    "sg:province":"Bayern",
    "wof:name":"Kinderfreunde E. V.",
    "wof:placetype":"venue"
},
  "geometry": {"coordinates":[11.5421152115,48.153339386],"type":"Point"}
}