{
  "type": "Feature",
  "properties": {
    "iso:country":"DE",
    "sg:address":"Hallesche Str. 25",
    "sg:city":"Niemberg",
    "sg:phone":"+49 34604/20381",
    "sg:postcode":"06188",
    "sg:province":"Sachsen-Anhalt",
    "wof:name":"Dieter Tralls",
    "wof:placetype":"venue"
},
  "geometry": {"coordinates":[12.0865764618,51.5505180359],"type":"Point"}
}