{
  "type": "Feature",
  "properties": {
    "iso:country":"DE",
    "sg:address":"Gerhart-Hauptmann-Str. 66",
    "sg:city":"Straubing",
    "sg:phone":"+49 9421/40527",
    "sg:postcode":"94315",
    "sg:province":"Bayern",
    "wof:name":"Claudia Elsner",
    "wof:placetype":"venue"
},
  "geometry": {"coordinates":[12.565246582,48.8624916077],"type":"Point"}
}