{
  "type": "Feature",
  "properties": {
    "iso:country":"DE",
    "sg:address":"Neufahrner Str. 12 Gr\u00fcneck",
    "sg:city":"Neufahrn",
    "sg:postcode":"85375",
    "sg:province":"Bayern",
    "wof:name":"W. B. C. Dienstleistung Gmbh",
    "wof:placetype":"venue"
},
  "geometry": {"coordinates":[11.6917104721,48.3193893433],"type":"Point"}
}