{
  "type": "Feature",
  "properties": {
    "iso:country":"DE",
    "sg:address":"Dr. Hans Eisenmann Str. 15",
    "sg:city":"Wolnzach",
    "sg:phone":"+49 8442/4844",
    "sg:postcode":"85283",
    "sg:province":"Bayern",
    "wof:name":"Abc-music.de (fachversand F\u00fcr Noten, Musikb\u00fccher & Songbook)",
    "wof:placetype":"venue"
},
  "geometry": {"coordinates":[11.616399765,48.6048355103],"type":"Point"}
}