{
  "type": "Feature",
  "properties": {
    "iso:country":"DE",
    "sg:address":"Klingenthaler Str. 8",
    "sg:city":"Taunusstein",
    "sg:phone":"+49 6128/84711",
    "sg:postcode":"65232",
    "sg:province":"Hessen",
    "wof:name":"Rolf R. Barenberg Rechtsanwalt",
    "wof:placetype":"venue"
},
  "geometry": {"coordinates":[8.2006616592,50.15259552],"type":"Point"}
}