{
  "type": "Feature",
  "properties": {
    "iso:country":"DE",
    "sg:address":"Hebbelstr. 49",
    "sg:city":"Potsdam",
    "sg:phone":"+49 331/2702913",
    "sg:postcode":"14467",
    "sg:province":"Brandenburg",
    "wof:name":"Vidon Gmbh",
    "wof:placetype":"venue"
},
  "geometry": {"coordinates":[13.062383,52.403416],"type":"Point"}
}