{
  "type": "Feature",
  "properties": {
    "iso:country":"DE",
    "sg:address":"An der Klinge 5",
    "sg:city":"Dorfhain",
    "sg:phone":"+49 35055/61838",
    "sg:postcode":"01738",
    "sg:province":"Sachsen",
    "wof:name":"S. Richter",
    "wof:placetype":"venue"
},
  "geometry": {"coordinates":[13.563942,50.936382],"type":"Point"}
}