{
  "type": "Feature",
  "properties": {
    "iso:country":"DE",
    "sg:address":"Heerweg 19",
    "sg:city":"M\u00f6ssingen",
    "sg:phone":"+49 4974/7394930",
    "sg:postcode":"72116",
    "sg:province":"Baden-W\u00fcrttemberg",
    "wof:name":"Karl Ayen Maschinenfabrik Gmbh",
    "wof:placetype":"venue"
},
  "geometry": {"coordinates":[9.072049,48.409279],"type":"Point"}
}