{
  "type": "Feature",
  "properties": {
    "iso:country":"DE",
    "sg:address":"Schattenhof 1",
    "sg:city":"Kammerstein",
    "sg:phone":"+49 9122/85059",
    "sg:postcode":"91126",
    "sg:province":"Bayern",
    "wof:name":"Lift Service S\u00fcd Johannes Frese",
    "wof:placetype":"venue"
},
  "geometry": {"coordinates":[10.975357,49.300678],"type":"Point"}
}