{
  "type": "Feature",
  "properties": {
    "iso:country":"DE",
    "sg:address":"Postfach 82",
    "sg:city":"Haldensleben",
    "sg:postcode":"39331",
    "sg:province":"Sachsen-Anhalt",
    "wof:name":"Haniel Baustoff-industrie Zuschlagstoffe",
    "wof:placetype":"venue"
},
  "geometry": {"coordinates":[11.4129495621,52.2905807495],"type":"Point"}
}