{
  "type": "Feature",
  "properties": {
    "iso:country":"DE",
    "sg:address":"Wehlener Str. 46",
    "sg:city":"Dresden",
    "sg:phone":"+49 351/255070",
    "sg:postcode":"01279",
    "sg:province":"Sachsen",
    "wof:name":"Elb-immobilien Verwaltungs-gmbh",
    "wof:placetype":"venue"
},
  "geometry": {"coordinates":[13.819519043,51.0344047546],"type":"Point"}
}