{
  "type": "Feature",
  "properties": {
    "iso:country":"DE",
    "sg:address":"S\u00fcsterstr. 3",
    "sg:city":"Osnabr\u00fcck",
    "sg:phone":"+49 541/331270",
    "sg:postcode":"49074",
    "sg:province":"Niedersachsen",
    "wof:name":"Gev Gro\u00dfeinkaufsverband Des Wein- Und Spirituosenhand.",
    "wof:placetype":"venue"
},
  "geometry": {"coordinates":[8.0511045456,52.2698898315],"type":"Point"}
}