{
  "type": "Feature",
  "properties": {
    "iso:country":"DE",
    "sg:address":"M\u00fchlenweg 47 b",
    "sg:city":"Frankfurt",
    "sg:phone":"+49 335/536626",
    "sg:postcode":"15232",
    "sg:province":"Brandenburg",
    "wof:name":"Karin Adler",
    "wof:placetype":"venue"
},
  "geometry": {"coordinates":[14.548347,52.325199],"type":"Point"}
}