{
  "type": "Feature",
  "properties": {
    "iso:country":"DE",
    "sg:address":"Ruppiner Str. 12",
    "sg:city":"Rathenow",
    "sg:phone":"+49 3385/514600",
    "sg:postcode":"14712",
    "sg:province":"Brandenburg",
    "wof:name":"Fliesenlegerarbeiten Gmbh",
    "wof:placetype":"venue"
},
  "geometry": {"coordinates":[12.3405761719,52.61277771],"type":"Point"}
}