{
  "type": "Feature",
  "properties": {
    "iso:country":"DE",
    "sg:address":"Lohbr\u00fcgger Weg 16",
    "sg:city":"Hamburg",
    "sg:phone":"+49 40/7399665",
    "sg:postcode":"21031",
    "sg:province":"Hamburg",
    "wof:name":"Michael Meyer",
    "wof:placetype":"venue"
},
  "geometry": {"coordinates":[10.205608,53.500465],"type":"Point"}
}