{
  "type": "Feature",
  "properties": {
    "iso:country":"DE",
    "sg:address":"Plochinger Str. 4",
    "sg:city":"Kirchheim",
    "sg:phone":"+49 7021/75922",
    "sg:postcode":"73230",
    "sg:province":"Baden-W\u00fcrttemberg",
    "wof:name":"Fotoprojektstudio Ralph Steckelbach",
    "wof:placetype":"venue"
},
  "geometry": {"coordinates":[9.4507408142,48.6498451233],"type":"Point"}
}