{
  "type": "Feature",
  "properties": {
    "iso:country":"DE",
    "sg:address":"Gleiwitzer Str. 19",
    "sg:city":"Langenhagen",
    "sg:phone":"+49 511/789855",
    "sg:postcode":"30855",
    "sg:province":"Niedersachsen",
    "wof:name":"Erwin Jarius Druckerei-bedarf Gmbh",
    "wof:placetype":"venue"
},
  "geometry": {"coordinates":[9.685057,52.432598],"type":"Point"}
}