{
  "type": "Feature",
  "properties": {
    "iso:country":"DE",
    "sg:address":"Heisenbergstr. 10",
    "sg:city":"Kerpen",
    "sg:phone":"+49 2237/973060",
    "sg:postcode":"50169",
    "sg:province":"Nordrhein-Westfalen",
    "wof:name":"Spedition Rheinland H. Freund Gmbh & Co. Kg",
    "wof:placetype":"venue"
},
  "geometry": {"coordinates":[6.7544322014,50.8700942993],"type":"Point"}
}