{
  "type": "Feature",
  "properties": {
    "iso:country":"DE",
    "sg:address":"Kolpingstr 46",
    "sg:city":"Kaufering",
    "sg:phone":"+49 8191/96410",
    "sg:postcode":"86916",
    "sg:province":"Bayern",
    "wof:name":"B-quadrat Verlags Gmbh",
    "wof:placetype":"venue"
},
  "geometry": {"coordinates":[10.8545417786,48.0963058472],"type":"Point"}
}