{
  "type": "Feature",
  "properties": {
    "iso:country":"DE",
    "sg:address":"Birkenstr. 79",
    "sg:city":"D\u00fcsseldorf",
    "sg:phone":"+49 211/664459",
    "sg:postcode":"40233",
    "sg:province":"Nordrhein-Westfalen",
    "wof:name":"Foto-ellis",
    "wof:placetype":"venue"
},
  "geometry": {"coordinates":[6.8049149513,51.2267837524],"type":"Point"}
}