{
  "type": "Feature",
  "properties": {
    "iso:country":"DE",
    "sg:address":"Christoph-Selhamer-Str. 2-4",
    "sg:city":"Weilheim",
    "sg:phone":"+49 881/638376",
    "sg:postcode":"82362",
    "sg:province":"Bayern",
    "wof:name":"Minimal",
    "wof:placetype":"venue"
},
  "geometry": {"coordinates":[11.1525173187,47.8473587036],"type":"Point"}
}