{
  "type": "Feature",
  "properties": {
    "iso:country":"DE",
    "sg:address":"Alter Gartenweg 14",
    "sg:city":"D\u00fclmen",
    "sg:phone":"+49 2594/783322",
    "sg:postcode":"48249",
    "sg:province":"Nordrhein-Westfalen",
    "wof:name":"Kesselmann Und Harden",
    "wof:placetype":"venue"
},
  "geometry": {"coordinates":[7.2830929756,51.8286094666],"type":"Point"}
}