{
  "type": "Feature",
  "properties": {
    "iso:country":"DE",
    "sg:address":"Wisserswandstr. 1 b",
    "sg:city":"Waldkirch",
    "sg:phone":"+49 7681/8374",
    "sg:postcode":"79183",
    "sg:province":"Baden-W\u00fcrttemberg",
    "wof:name":"Michael Gro\u00df",
    "wof:placetype":"venue"
},
  "geometry": {"coordinates":[7.9731998444,48.0912818909],"type":"Point"}
}