{
  "type": "Feature",
  "properties": {
    "iso:country":"DE",
    "sg:address":"Prager Str. 187",
    "sg:city":"Leipzig",
    "sg:postcode":"04299",
    "sg:province":"Sachsen",
    "wof:name":"Natursteinwerk Schiffer Gmbh Ndl. Leipzig",
    "wof:placetype":"venue"
},
  "geometry": {"coordinates":[12.4156284332,51.3124275208],"type":"Point"}
}