{
  "type": "Feature",
  "properties": {
    "iso:country":"DE",
    "sg:address":"Ulrichsberg 7",
    "sg:city":"Grafling",
    "sg:phone":"+49 991/26980",
    "sg:postcode":"94539",
    "sg:province":"Bayern",
    "wof:name":"Hotel Berghof",
    "wof:placetype":"venue"
},
  "geometry": {"coordinates":[12.9822950363,48.8719787598],"type":"Point"}
}