{
  "type": "Feature",
  "properties": {
    "iso:country":"DE",
    "sg:address":"Ettinger Str. 20",
    "sg:city":"Ingolstadt",
    "sg:phone":"+49 841/82077",
    "sg:postcode":"85057",
    "sg:province":"Bayern",
    "wof:name":"Minitron Elektronik Gmbh",
    "wof:placetype":"venue"
},
  "geometry": {"coordinates":[11.417232,48.774315],"type":"Point"}
}