{
  "type": "Feature",
  "properties": {
    "iso:country":"DE",
    "sg:address":"Hauptstr. 18",
    "sg:city":"Blumberg",
    "sg:phone":"+49 7702/3331",
    "sg:postcode":"78176",
    "sg:province":"Baden-W\u00fcrttemberg",
    "wof:name":"Falk Wohnhas",
    "wof:placetype":"venue"
},
  "geometry": {"coordinates":[8.535374,47.839901],"type":"Point"}
}