{
  "type": "Feature",
  "properties": {
    "iso:country":"DE",
    "sg:address":"Culitzscher Str. 25",
    "sg:city":"Wilkau-Ha\u00dflau",
    "sg:phone":"+49 375/671335",
    "sg:postcode":"08112",
    "sg:province":"Sachsen",
    "wof:name":"W. John",
    "wof:placetype":"venue"
},
  "geometry": {"coordinates":[12.512211,50.671791],"type":"Point"}
}