{
  "type": "Feature",
  "properties": {
    "iso:country":"DE",
    "sg:address":"Forsthausstr. 5a",
    "sg:city":"Gr\u00fcnwald",
    "sg:phone":"+49 89/6492426",
    "sg:postcode":"82031",
    "sg:province":"Bayern",
    "wof:name":"Atwerb-verlag Kommunikation Und Werbung Gmbh & Co. Kg",
    "wof:placetype":"venue"
},
  "geometry": {"coordinates":[11.5462579727,48.0588798523],"type":"Point"}
}