{
  "type": "Feature",
  "properties": {
    "iso:country":"DE",
    "sg:address":"M\u00f6lmer Ring 29",
    "sg:city":"S\u00f6hlde",
    "sg:phone":"+49 5129/427",
    "sg:postcode":"31185",
    "sg:province":"Niedersachsen",
    "wof:name":"J\u00fcrgen Friehe",
    "wof:placetype":"venue"
},
  "geometry": {"coordinates":[10.159456,52.217522],"type":"Point"}
}