{
  "type": "Feature",
  "properties": {
    "iso:country":"DE",
    "sg:address":"Hambrocker Str. 53",
    "sg:city":"Uelzen",
    "sg:phone":"+49 581/30940",
    "sg:postcode":"29525",
    "sg:province":"Niedersachsen",
    "wof:name":"Apotheke Am Hambrocker Berg",
    "wof:placetype":"venue"
},
  "geometry": {"coordinates":[10.568301,52.960167],"type":"Point"}
}