{
  "type": "Feature",
  "properties": {
    "iso:country":"DE",
    "sg:address":"Franziskanerweg 1",
    "sg:city":"Leimen",
    "sg:phone":"+49 6224/54920",
    "sg:postcode":"69181",
    "sg:province":"Baden-W\u00fcrttemberg",
    "wof:name":"H. & S. Immobilien- Und Bautr\u00e4ger Gmbh",
    "wof:placetype":"venue"
},
  "geometry": {"coordinates":[8.672445,49.345406],"type":"Point"}
}