{
  "type": "Feature",
  "properties": {
    "iso:country":"DE",
    "sg:address":"Weidengrund 9",
    "sg:city":"Bochum",
    "sg:phone":"+49 234/473987",
    "sg:postcode":"44797",
    "sg:province":"Nordrhein-Westfalen",
    "wof:name":"Gtvk Verm\u00f6gens- Verwaltungs Gmbh",
    "wof:placetype":"venue"
},
  "geometry": {"coordinates":[7.2183551788,51.4357948303],"type":"Point"}
}