{
  "type": "Feature",
  "properties": {
    "iso:country":"DE",
    "sg:address":"Premmenfeld",
    "sg:city":"Saarbr\u00fccken",
    "sg:phone":"+49 681/894311",
    "sg:postcode":"66132",
    "sg:province":"Saarland",
    "wof:name":"Reiterklause",
    "wof:placetype":"venue"
},
  "geometry": {"coordinates":[7.0734500885,49.2183685303],"type":"Point"}
}