{
  "type": "Feature",
  "properties": {
    "iso:country":"DE",
    "sg:address":"Weiherstr. 38",
    "sg:city":"Stadtroda",
    "sg:phone":"+49 36428/62259",
    "sg:postcode":"07646",
    "sg:province":"Th\u00fcringen",
    "wof:name":"Karl-heinz Grimm",
    "wof:placetype":"venue"
},
  "geometry": {"coordinates":[11.735843,50.857307],"type":"Point"}
}