{
  "type": "Feature",
  "properties": {
    "iso:country":"DE",
    "sg:address":"Oelhausenweg 1",
    "sg:city":"Krefeld",
    "sg:phone":"+49 2151/564283",
    "sg:postcode":"47803",
    "sg:province":"Nordrhein-Westfalen",
    "wof:name":"Kamp",
    "wof:placetype":"venue"
},
  "geometry": {"coordinates":[6.5661711693,51.3528404236],"type":"Point"}
}