{
  "type": "Feature",
  "properties": {
    "iso:country":"DE",
    "sg:address":"Gartenstr 1",
    "sg:city":"Rielasingen-Worblingen",
    "sg:phone":"+49 6101/542697",
    "sg:postcode":"78239",
    "sg:province":"Baden-W\u00fcrttemberg",
    "wof:name":"Mor Service",
    "wof:placetype":"venue"
},
  "geometry": {"coordinates":[8.7185239792,50.1893081665],"type":"Point"}
}