{
  "type": "Feature",
  "properties": {
    "iso:country":"DE",
    "sg:address":"K\u00f6lner Str. 64",
    "sg:city":"Euskirchen",
    "sg:phone":"+49 2251/52472",
    "sg:postcode":"53879",
    "sg:province":"Nordrhein-Westfalen",
    "wof:name":"Sex-shop",
    "wof:placetype":"venue"
},
  "geometry": {"coordinates":[6.797429,50.66048],"type":"Point"}
}