{
  "type": "Feature",
  "properties": {
    "iso:country":"DE",
    "sg:address":"Bahndammweg 5",
    "sg:city":"Bad Krozingen",
    "sg:phone":"+49 7633/2222",
    "sg:postcode":"79189",
    "sg:province":"Baden-W\u00fcrttemberg",
    "wof:name":"Ksb Taxi-u.transportges.mbh Transportges. Mbh",
    "wof:placetype":"venue"
},
  "geometry": {"coordinates":[7.6971468925,47.919128418],"type":"Point"}
}