{
  "type": "Feature",
  "properties": {
    "iso:country":"DE",
    "sg:address":"Auestr. 18",
    "sg:city":"Wohratal",
    "sg:phone":"+49 6425/304",
    "sg:postcode":"35288",
    "sg:province":"Hessen",
    "wof:name":"Heinz Metke",
    "wof:placetype":"venue"
},
  "geometry": {"coordinates":[8.9435148239,50.913066864],"type":"Point"}
}