{
  "type": "Feature",
  "properties": {
    "iso:country":"DE",
    "sg:address":"Friedrichstr. 7",
    "sg:city":"Ronneburg",
    "sg:phone":"+49 36602/22458",
    "sg:postcode":"07580",
    "sg:province":"Th\u00fcringen",
    "wof:name":"Dieter Scheffel",
    "wof:placetype":"venue"
},
  "geometry": {"coordinates":[12.184885,50.861599],"type":"Point"}
}