{
  "type": "Feature",
  "properties": {
    "iso:country":"DE",
    "sg:address":"Karl-Liebknecht-Allee 38-42",
    "sg:city":"Dahme",
    "sg:postcode":"15936",
    "sg:province":"Brandenburg",
    "wof:name":"Retrans Immobilien- Verwaltungsgesellschaft Mbh",
    "wof:placetype":"venue"
},
  "geometry": {"coordinates":[13.4338951111,51.870803833],"type":"Point"}
}