{
  "type": "Feature",
  "properties": {
    "iso:country":"DE",
    "sg:address":"Denkmalstr. 16",
    "sg:city":"Eitorf",
    "sg:phone":"+49 2243/6757",
    "sg:postcode":"53783",
    "sg:province":"Nordrhein-Westfalen",
    "wof:name":"Willi R\u00f6sgen",
    "wof:placetype":"venue"
},
  "geometry": {"coordinates":[7.452009201,50.7854385376],"type":"Point"}
}