{
  "type": "Feature",
  "properties": {
    "iso:country":"DE",
    "sg:address":"Br\u00fccherhofstr. 122",
    "sg:city":"Dortmund",
    "sg:phone":"+49 231/464669",
    "sg:postcode":"44267",
    "sg:province":"Nordrhein-Westfalen",
    "wof:name":"Hoven-automaten Kg",
    "wof:placetype":"venue"
},
  "geometry": {"coordinates":[7.5034098625,51.4687690735],"type":"Point"}
}