{
  "type": "Feature",
  "properties": {
    "iso:country":"DE",
    "sg:address":"Hexberg 58",
    "sg:city":"M\u00fclheim",
    "sg:phone":"+49 208/995546",
    "sg:postcode":"45475",
    "sg:province":"Nordrhein-Westfalen",
    "wof:name":"Landgasthof M\u00fchlebach",
    "wof:placetype":"venue"
},
  "geometry": {"coordinates":[6.9049701691,51.469291687],"type":"Point"}
}