{
  "type": "Feature",
  "properties": {
    "iso:country":"DE",
    "sg:address":"M\u00fchlenstr. 101",
    "sg:city":"Stadtlohn",
    "sg:phone":"+49 2563/93230",
    "sg:postcode":"48703",
    "sg:province":"Nordrhein-Westfalen",
    "wof:name":"Excellent Air Gmbh",
    "wof:placetype":"venue"
},
  "geometry": {"coordinates":[6.914544,52.003288],"type":"Point"}
}