{
  "type": "Feature",
  "properties": {
    "iso:country":"DE",
    "sg:address":"Stephansgasse 18",
    "sg:city":"Worms",
    "sg:phone":"+49 6241/25534",
    "sg:postcode":"67547",
    "sg:province":"Rheinland-Pfalz",
    "wof:name":"Anni Strack",
    "wof:placetype":"venue"
},
  "geometry": {"coordinates":[8.360458,49.631367],"type":"Point"}
}