{
  "type": "Feature",
  "properties": {
    "iso:country":"DE",
    "sg:address":"Freiburger Str. 14",
    "sg:city":"Pforzheim",
    "sg:phone":"+49 7231/93010",
    "sg:postcode":"75179",
    "sg:province":"Baden-W\u00fcrttemberg",
    "wof:name":"Studio Miko Gmbh",
    "wof:placetype":"venue"
},
  "geometry": {"coordinates":[8.6603908539,48.9005584717],"type":"Point"}
}