{
  "type": "Feature",
  "properties": {
    "iso:country":"DE",
    "sg:address":"\u00dcber der Stra\u00dfe 14",
    "sg:city":"L\u00fcdenscheid",
    "sg:phone":"+49 2351/786241",
    "sg:postcode":"58515",
    "sg:province":"Nordrhein-Westfalen",
    "wof:name":"N. Und E. Schlosser",
    "wof:placetype":"venue"
},
  "geometry": {"coordinates":[7.593651,51.20755],"type":"Point"}
}