{
  "type": "Feature",
  "properties": {
    "iso:country":"DE",
    "sg:address":"Bahnhofstr. 17",
    "sg:city":"Magdeburg",
    "sg:phone":"+49 391/59990",
    "sg:postcode":"39104",
    "sg:province":"Sachsen-Anhalt",
    "wof:name":"Druckerei Volksstimme Magdeburg",
    "wof:placetype":"venue"
},
  "geometry": {"coordinates":[11.628251,52.128227],"type":"Point"}
}