{
  "type": "Feature",
  "properties": {
    "iso:country":"DE",
    "sg:address":"Demetriusstr. 15",
    "sg:city":"L\u00f6ffingen",
    "sg:phone":"+49 7654/312",
    "sg:postcode":"79843",
    "sg:province":"Baden-W\u00fcrttemberg",
    "wof:name":"Dieter Butsch",
    "wof:placetype":"venue"
},
  "geometry": {"coordinates":[8.3437204361,47.8839492798],"type":"Point"}
}