{
  "type": "Feature",
  "properties": {
    "iso:country":"DE",
    "sg:address":"Hindenburgstr. 22",
    "sg:city":"Ludwigshafen",
    "sg:phone":"+49 621/551575",
    "sg:postcode":"67067",
    "sg:province":"Rheinland-Pfalz",
    "wof:name":"M. Steil",
    "wof:placetype":"venue"
},
  "geometry": {"coordinates":[8.3796062469,49.455280304],"type":"Point"}
}