{
  "type": "Feature",
  "properties": {
    "iso:country":"DE",
    "sg:address":"Sudetenstr. 33",
    "sg:city":"Hochheim",
    "sg:phone":"+49 6146/7601",
    "sg:postcode":"65239",
    "sg:province":"Hessen",
    "wof:name":"J\u00fcrgen Spreitzer",
    "wof:placetype":"venue"
},
  "geometry": {"coordinates":[8.338799,50.017143],"type":"Point"}
}