{
  "type": "Feature",
  "properties": {
    "iso:country":"DE",
    "sg:address":"Einemstr. 4",
    "sg:city":"Berlin",
    "sg:postcode":"10787",
    "sg:province":"Berlin",
    "wof:name":"Mondialmar Gro\u00dfhandel Import - Export Gmbh",
    "wof:placetype":"venue"
},
  "geometry": {"coordinates":[13.3540506363,52.5005455017],"type":"Point"}
}