{
  "type": "Feature",
  "properties": {
    "iso:country":"DE",
    "sg:address":"Fritz-Neuert-Str. 49-51",
    "sg:city":"Pforzheim",
    "sg:phone":"+49 4972/3153036",
    "sg:postcode":"75181",
    "sg:province":"Baden-W\u00fcrttemberg",
    "wof:name":"Uron Oberfl\u00c4chen- & Umwelttechnik",
    "wof:placetype":"venue"
},
  "geometry": {"coordinates":[8.743497,48.910454],"type":"Point"}
}