{
  "type": "Feature",
  "properties": {
    "iso:country":"DE",
    "sg:address":"Am Kuhlenfeld 48",
    "sg:city":"Duisburg",
    "sg:postcode":"47199",
    "sg:province":"Nordrhein-Westfalen",
    "wof:name":"G-schenkidee Gmbh",
    "wof:placetype":"venue"
},
  "geometry": {"coordinates":[6.6795239449,51.4567108154],"type":"Point"}
}