{
  "type": "Feature",
  "properties": {
    "iso:country":"DE",
    "sg:address":"Sch\u00fctzenrain 20",
    "sg:city":"Friedberg",
    "sg:phone":"+49 6031/92900",
    "sg:postcode":"61169",
    "sg:province":"Hessen",
    "wof:name":"Momberger Und Lang Rechtsanw\u00e4lte",
    "wof:placetype":"venue"
},
  "geometry": {"coordinates":[8.7573747635,50.3312034607],"type":"Point"}
}