{
  "type": "Feature",
  "properties": {
    "iso:country":"DE",
    "sg:address":"Bongartstr. 10",
    "sg:city":"Jettingen",
    "sg:phone":"+49 4974/527310",
    "sg:postcode":"71131",
    "sg:province":"Baden-W\u00fcrttemberg",
    "wof:name":"Seiser Gmbh",
    "wof:placetype":"venue"
},
  "geometry": {"coordinates":[8.7802038193,48.5675315857],"type":"Point"}
}