{
  "type": "Feature",
  "properties": {
    "iso:country":"DE",
    "sg:address":"Klings\u00f6hrstr. 8",
    "sg:city":"Hannover",
    "sg:phone":"+49 511/631341",
    "sg:postcode":"30659",
    "sg:province":"Niedersachsen",
    "wof:name":"Klaus G. Schmidt",
    "wof:placetype":"venue"
},
  "geometry": {"coordinates":[9.8123750687,52.4249229431],"type":"Point"}
}