{
  "type": "Feature",
  "properties": {
    "iso:country":"DE",
    "sg:address":"Goethestr. 3",
    "sg:city":"Auerbach",
    "sg:phone":"+49 3744/213908",
    "sg:postcode":"08209",
    "sg:province":"Sachsen",
    "wof:name":"Marion Penning",
    "wof:placetype":"venue"
},
  "geometry": {"coordinates":[12.397599,50.510368],"type":"Point"}
}