{
  "type": "Feature",
  "properties": {
    "iso:country":"DE",
    "sg:address":"Am Papenholz 11",
    "sg:city":"Sehnde",
    "sg:postcode":"31319",
    "sg:province":"Niedersachsen",
    "wof:name":"Gemeindeb\u00fccherei Sehnde Schulzentrum",
    "wof:placetype":"venue"
},
  "geometry": {"coordinates":[9.956827,52.320133],"type":"Point"}
}