{
  "type": "Feature",
  "properties": {
    "iso:country":"DE",
    "sg:address":"Lemseler Str. 5",
    "sg:city":"Radefeld",
    "sg:phone":"+49 34207/41064",
    "sg:postcode":"04509",
    "sg:province":"Sachsen",
    "wof:name":"Agrarproduktion Wolteritz Gmbh",
    "wof:placetype":"venue"
},
  "geometry": {"coordinates":[12.353228569,51.5111045837],"type":"Point"}
}