{
  "type": "Feature",
  "properties": {
    "iso:country":"DE",
    "sg:address":"Lessingstr. 18",
    "sg:city":"Neustrelitz",
    "sg:phone":"+49 3981/443274",
    "sg:postcode":"17235",
    "sg:province":"Mecklenburg-Vorpommern",
    "wof:name":"Maria Forberger",
    "wof:placetype":"venue"
},
  "geometry": {"coordinates":[13.078967,53.357185],"type":"Point"}
}