{
  "type": "Feature",
  "properties": {
    "iso:country":"DE",
    "sg:address":"G\u00fcnther-Scharowsky-Str. 2",
    "sg:city":"Erlangen",
    "sg:phone":"+49 9131/722002",
    "sg:postcode":"91058",
    "sg:province":"Bayern",
    "wof:name":"Siemens Ag",
    "wof:placetype":"venue"
},
  "geometry": {"coordinates":[11.003847,49.577171],"type":"Point"}
}