{
  "type": "Feature",
  "properties": {
    "iso:country":"DE",
    "sg:address":"Flughafenstr. 561",
    "sg:city":"Dortmund",
    "sg:phone":"+49 231/9231010",
    "sg:postcode":"44329",
    "sg:province":"Nordrhein-Westfalen",
    "wof:name":"Timmer W\u00e4scherei-gro\u00dfk\u00fcchen Technik Gmbh & Co. Kg",
    "wof:placetype":"venue"
},
  "geometry": {"coordinates":[7.5372657776,51.5604171753],"type":"Point"}
}