{
  "type": "Feature",
  "properties": {
    "iso:country":"DE",
    "sg:address":"Bahnhofstr. 15",
    "sg:city":"Adelsdorf",
    "sg:phone":"+49 9195/8341",
    "sg:postcode":"91325",
    "sg:province":"Bayern",
    "wof:name":"Gram\u00df Gmbh",
    "wof:placetype":"venue"
},
  "geometry": {"coordinates":[10.898542,49.711178],"type":"Point"}
}