{
  "type": "Feature",
  "properties": {
    "iso:country":"DE",
    "sg:address":"Milsper Str. 111",
    "sg:city":"Ennepetal",
    "sg:phone":"+49 2333/62110",
    "sg:postcode":"58256",
    "sg:province":"Nordrhein-Westfalen",
    "wof:name":"R. U. B. Stein",
    "wof:placetype":"venue"
},
  "geometry": {"coordinates":[7.371629,51.303558],"type":"Point"}
}