{
  "type": "Feature",
  "properties": {
    "iso:country":"DE",
    "sg:address":"Michelsbergstr.",
    "sg:city":"Ochtendung",
    "sg:postcode":"56299",
    "sg:province":"Rheinland-Pfalz",
    "wof:name":"Hc Fertigungs- Und Handels Gmbh",
    "wof:placetype":"venue"
},
  "geometry": {"coordinates":[7.3977022171,50.3540382385],"type":"Point"}
}