{
  "type": "Feature",
  "properties": {
    "iso:country":"DE",
    "sg:address":"Feldstr. 35",
    "sg:city":"Gr\u00fcna",
    "sg:phone":"+49 371/858751",
    "sg:postcode":"09224",
    "sg:province":"Sachsen",
    "wof:name":"Hilmar Kanschat",
    "wof:placetype":"venue"
},
  "geometry": {"coordinates":[12.7839698792,50.8132247925],"type":"Point"}
}