{
  "type": "Feature",
  "properties": {
    "iso:country":"DE",
    "sg:address":"T\u00f6pfer Erde 1",
    "sg:city":"Limburg",
    "sg:phone":"+49 6431/961820",
    "sg:postcode":"65550",
    "sg:province":"Hessen",
    "wof:name":"Weil-beton Gmbh & Co. Kg",
    "wof:placetype":"venue"
},
  "geometry": {"coordinates":[8.095004,50.364902],"type":"Point"}
}