{
  "type": "Feature",
  "properties": {
    "iso:country":"DE",
    "sg:address":"Kappisweg 41",
    "sg:city":"Waibstadt",
    "sg:phone":"+49 7263/1360",
    "sg:postcode":"74915",
    "sg:province":"Baden-W\u00fcrttemberg",
    "wof:name":"Wilhelm M\u00fchlbacher",
    "wof:placetype":"venue"
},
  "geometry": {"coordinates":[8.909011,49.303913],"type":"Point"}
}