{
  "type": "Feature",
  "properties": {
    "iso:country":"DE",
    "sg:address":"Sch\u00f6nbergstr. 22",
    "sg:city":"Sonneberg",
    "sg:phone":"+49 3675/702117",
    "sg:postcode":"96515",
    "sg:province":"Th\u00fcringen",
    "wof:name":"Carolin Hill",
    "wof:placetype":"venue"
},
  "geometry": {"coordinates":[11.1849088669,50.358505249],"type":"Point"}
}