{
  "type": "Feature",
  "properties": {
    "iso:country":"DE",
    "sg:address":"Erdenbach 10 a",
    "sg:city":"Saarburg",
    "sg:phone":"+49 6581/2647",
    "sg:postcode":"54439",
    "sg:province":"Rheinland-Pfalz",
    "wof:name":"Makusa-m\u00e4rkte Manfred E. Kurz",
    "wof:placetype":"venue"
},
  "geometry": {"coordinates":[6.5591049194,49.6150779724],"type":"Point"}
}