{
  "type": "Feature",
  "properties": {
    "iso:country":"DE",
    "sg:address":"Silcherstr. 3",
    "sg:city":"Bad Oeynhausen",
    "sg:phone":"+49 5731/29604",
    "sg:postcode":"32549",
    "sg:province":"Nordrhein-Westfalen",
    "wof:name":"Wilfried Folle",
    "wof:placetype":"venue"
},
  "geometry": {"coordinates":[8.8030538559,52.211063385],"type":"Point"}
}