{
  "type": "Feature",
  "properties": {
    "iso:country":"DE",
    "sg:address":"Harburger Str. 5",
    "sg:city":"Seevetal",
    "sg:phone":"+49 4105/2666",
    "sg:postcode":"21218",
    "sg:province":"Niedersachsen",
    "wof:name":"Wwv W\u00e4rmeverwertung Gmbh & Co. Kg",
    "wof:placetype":"venue"
},
  "geometry": {"coordinates":[9.97685,53.385605],"type":"Point"}
}