{
  "type": "Feature",
  "properties": {
    "iso:country":"DE",
    "sg:address":"Schlo\u00dfstr. 298",
    "sg:city":"M\u00f6nchengladbach",
    "sg:phone":"+49 2166/20575",
    "sg:postcode":"41238",
    "sg:province":"Nordrhein-Westfalen",
    "wof:name":"E. Frentzen Jun.",
    "wof:placetype":"venue"
},
  "geometry": {"coordinates":[6.478241,51.180767],"type":"Point"}
}