{
  "type": "Feature",
  "properties": {
    "iso:country":"DE",
    "sg:address":"An der B 30",
    "sg:city":"Bad Waldsee",
    "sg:phone":"+49 7524/1369",
    "sg:postcode":"88339",
    "sg:province":"Baden-W\u00fcrttemberg",
    "wof:name":"Kreuz",
    "wof:placetype":"venue"
},
  "geometry": {"coordinates":[9.7541303635,47.9191436768],"type":"Point"}
}