{
  "type": "Feature",
  "properties": {
    "iso:country":"DE",
    "sg:address":"Heinrich-Mauersberger-Ring 8d",
    "sg:city":"Limbach-Oberfrohna",
    "sg:phone":"+49 3722/82151",
    "sg:postcode":"09212",
    "sg:province":"Sachsen",
    "wof:name":"Rudolf G\u00f6tz",
    "wof:placetype":"venue"
},
  "geometry": {"coordinates":[12.766707,50.854736],"type":"Point"}
}