{
  "type": "Feature",
  "properties": {
    "iso:country":"DE",
    "sg:address":"Uhlandweg 11",
    "sg:city":"Selb",
    "sg:phone":"+49 9287/2526",
    "sg:postcode":"95100",
    "sg:province":"Bayern",
    "wof:name":"Herbert Kirschnek Architekt",
    "wof:placetype":"venue"
},
  "geometry": {"coordinates":[12.123565,50.176277],"type":"Point"}
}