{
  "type": "Feature",
  "properties": {
    "iso:country":"DE",
    "sg:address":"Gereonstr. 57",
    "sg:city":"Vettwei\u00df",
    "sg:phone":"+49 2424/1584",
    "sg:postcode":"52391",
    "sg:province":"Nordrhein-Westfalen",
    "wof:name":"Rolf Heinrichs",
    "wof:placetype":"venue"
},
  "geometry": {"coordinates":[6.597847,50.73917],"type":"Point"}
}