{
  "type": "Feature",
  "properties": {
    "iso:country":"DE",
    "sg:address":"Stuberstr. 11 a",
    "sg:city":"M\u00fcnchen",
    "sg:phone":"+49 89/645102",
    "sg:postcode":"80638",
    "sg:province":"Bayern",
    "wof:name":"Rudolf M\u00fcller Gmbh",
    "wof:placetype":"venue"
},
  "geometry": {"coordinates":[11.5156745911,48.1637268066],"type":"Point"}
}