{
  "type": "Feature",
  "properties": {
    "iso:country":"DE",
    "sg:address":"Geisbergstr. 96",
    "sg:city":"K\u00f6ln",
    "sg:phone":"+49 221/462989",
    "sg:postcode":"50939",
    "sg:province":"Nordrhein-Westfalen",
    "wof:name":"Fritz Fischer Flaschengrosshdl.",
    "wof:placetype":"venue"
},
  "geometry": {"coordinates":[6.9240198135,50.9036827087],"type":"Point"}
}