{
  "type": "Feature",
  "properties": {
    "iso:country":"DE",
    "sg:address":"Lupinenstr. 93 a",
    "sg:city":"Neuss",
    "sg:phone":"+49 2131/461518",
    "sg:postcode":"41466",
    "sg:province":"Nordrhein-Westfalen",
    "wof:name":"Hartmut G\u00f6tze Holding Gmbh",
    "wof:placetype":"venue"
},
  "geometry": {"coordinates":[6.691132,51.171753],"type":"Point"}
}