{
  "type": "Feature",
  "properties": {
    "iso:country":"DE",
    "sg:address":"Hertzstr. 1",
    "sg:city":"Herrenberg",
    "sg:phone":"+49 4926/357890",
    "sg:postcode":"71083",
    "sg:province":"Baden-W\u00fcrttemberg",
    "wof:name":"Carbo Kohlensaeurewerke Gmbh & Cokg",
    "wof:placetype":"venue"
},
  "geometry": {"coordinates":[7.31142,50.51569],"type":"Point"}
}