{
  "type": "Feature",
  "properties": {
    "iso:country":"DE",
    "sg:address":"Ebermergen 6",
    "sg:city":"Harburg",
    "sg:postcode":"86655",
    "sg:province":"Bayern",
    "wof:name":"F. Buser",
    "wof:placetype":"venue"
},
  "geometry": {"coordinates":[10.6941995621,48.7785301208],"type":"Point"}
}