{
  "type": "Feature",
  "properties": {
    "iso:country":"DE",
    "sg:address":"L\u00f6hner Str. 221 b",
    "sg:city":"L\u00f6hne",
    "sg:phone":"+49 5731/785309",
    "sg:postcode":"32584",
    "sg:province":"Nordrhein-Westfalen",
    "wof:name":"Brink Service",
    "wof:placetype":"venue"
},
  "geometry": {"coordinates":[8.750191,52.199444],"type":"Point"}
}