{
  "type": "Feature",
  "properties": {
    "iso:country":"DE",
    "sg:address":"Brunnengasse 12/1",
    "sg:city":"Heidelberg",
    "sg:phone":"+49 6221/28267",
    "sg:postcode":"69117",
    "sg:province":"Baden-W\u00fcrttemberg",
    "wof:name":"Hermann Simon Bootsverleih",
    "wof:placetype":"venue"
},
  "geometry": {"coordinates":[8.697245,49.411152],"type":"Point"}
}