{
  "type": "Feature",
  "properties": {
    "iso:country":"DE",
    "sg:address":"Goethestr. 55 A",
    "sg:city":"Idar-Oberstein",
    "sg:phone":"+49 4971/7166935",
    "sg:postcode":"55743",
    "sg:province":"Rheinland-Pfalz",
    "wof:name":"Arthur M\u00d6hrle E. K.",
    "wof:placetype":"venue"
},
  "geometry": {"coordinates":[9.7930307388,48.7958450317],"type":"Point"}
}