{
  "type": "Feature",
  "properties": {
    "iso:country":"DE",
    "sg:address":"Ihlendieksweg 16",
    "sg:city":"Gro\u00dfhansdorf",
    "sg:phone":"+49 4102/692069",
    "sg:postcode":"22927",
    "sg:province":"Schleswig-Holstein",
    "wof:name":"Dagmar F\u00f6rster Gmbh",
    "wof:placetype":"venue"
},
  "geometry": {"coordinates":[10.268804,53.65538],"type":"Point"}
}