{
  "type": "Feature",
  "properties": {
    "iso:country":"DE",
    "sg:address":"Christoph-von-Schmid-Str. 3",
    "sg:city":"Ichenhausen",
    "sg:postcode":"89335",
    "sg:province":"Bayern",
    "wof:name":"Ks Beteiligungs Gmbh",
    "wof:placetype":"venue"
},
  "geometry": {"coordinates":[10.309118,48.366585],"type":"Point"}
}