{
  "type": "Feature",
  "properties": {
    "iso:country":"DE",
    "sg:address":"Kamper Weg 64",
    "sg:city":"Itzehoe",
    "sg:phone":"+49 4821",
    "sg:postcode":"25524",
    "sg:province":"Schleswig-Holstein",
    "wof:name":"Saab K\u00fcrschner, Itzehoe",
    "wof:placetype":"venue"
},
  "geometry": {"coordinates":[9.4921674728,53.9114608765],"type":"Point"}
}