{
  "type": "Feature",
  "properties": {
    "iso:country":"DE",
    "sg:address":"Bergstr. 16",
    "sg:city":"Kall",
    "sg:phone":"+49 2441/5895",
    "sg:postcode":"53925",
    "sg:province":"Nordrhein-Westfalen",
    "wof:name":"Ceramix Winter Gmbh",
    "wof:placetype":"venue"
},
  "geometry": {"coordinates":[6.5392398834,50.5127258301],"type":"Point"}
}