{
  "type": "Feature",
  "properties": {
    "iso:country":"DE",
    "sg:address":"Rekener Str. 11",
    "sg:city":"Velen",
    "sg:phone":"+49 2863/2707",
    "sg:postcode":"46342",
    "sg:province":"Nordrhein-Westfalen",
    "wof:name":"Weidemann",
    "wof:placetype":"venue"
},
  "geometry": {"coordinates":[6.986578,51.893894],"type":"Point"}
}