{
  "type": "Feature",
  "properties": {
    "iso:country":"DE",
    "sg:address":"Schwarzwaldstr. 56",
    "sg:city":"B\u00fchl",
    "sg:phone":"+49 7223/902753",
    "sg:postcode":"77815",
    "sg:province":"Baden-W\u00fcrttemberg",
    "wof:name":"Labe",
    "wof:placetype":"venue"
},
  "geometry": {"coordinates":[8.1561565399,48.6580886841],"type":"Point"}
}