{
  "type": "Feature",
  "properties": {
    "iso:country":"DE",
    "sg:address":"Wittgensteiner Str. 49a",
    "sg:city":"Hilchenbach",
    "sg:phone":"+49 2733/3089",
    "sg:postcode":"57271",
    "sg:province":"Nordrhein-Westfalen",
    "wof:name":"Otto Stein",
    "wof:placetype":"venue"
},
  "geometry": {"coordinates":[8.0889282227,50.9797592163],"type":"Point"}
}