{
  "type": "Feature",
  "properties": {
    "iso:country":"DE",
    "sg:address":"Gartenstr. 7",
    "sg:city":"Ringsheim",
    "sg:phone":"+49 7822/89490",
    "sg:postcode":"77975",
    "sg:province":"Baden-W\u00fcrttemberg",
    "wof:name":"Weber Gmbh",
    "wof:placetype":"venue"
},
  "geometry": {"coordinates":[7.777949,48.243824],"type":"Point"}
}