{
  "type": "Feature",
  "properties": {
    "iso:country":"DE",
    "sg:address":"B\u00fcndstr. 11",
    "sg:city":"Mellrichstadt",
    "sg:phone":"+49 9776/5871",
    "sg:postcode":"97638",
    "sg:province":"Bayern",
    "wof:name":"Karl Groenen",
    "wof:placetype":"venue"
},
  "geometry": {"coordinates":[10.297072,50.431152],"type":"Point"}
}