{
  "type": "Feature",
  "properties": {
    "iso:country":"DE",
    "sg:address":"Brunntaler Str. 3",
    "sg:city":"Werbach",
    "sg:phone":"+49 9349/1376",
    "sg:postcode":"97956",
    "sg:province":"Baden-W\u00fcrttemberg",
    "wof:name":"Joachim Sommer",
    "wof:placetype":"venue"
},
  "geometry": {"coordinates":[9.6957406998,49.6905708313],"type":"Point"}
}