{
  "type": "Feature",
  "properties": {
    "iso:country":"DE",
    "sg:address":"Badenbergstr. 16",
    "sg:city":"Heidenheim",
    "sg:phone":"+49 7321/35040",
    "sg:postcode":"89520",
    "sg:province":"Baden-W\u00fcrttemberg",
    "wof:name":"Beteiligungs-ges. Fischer Mbh",
    "wof:placetype":"venue"
},
  "geometry": {"coordinates":[10.169259,48.697857],"type":"Point"}
}