{
  "type": "Feature",
  "properties": {
    "iso:country":"DE",
    "sg:address":"Weilerstr. 135",
    "sg:city":"Oberhausen",
    "sg:phone":"+49 208/200587",
    "sg:postcode":"46049",
    "sg:province":"Nordrhein-Westfalen",
    "wof:name":"U. P. Elektroanlagenbau Und Automatisierungstechnik Gmbh",
    "wof:placetype":"venue"
},
  "geometry": {"coordinates":[6.82572,51.483795],"type":"Point"}
}