{
  "type": "Feature",
  "properties": {
    "iso:country":"DE",
    "sg:address":"Mainstr. 40",
    "sg:city":"Gro\u00dfwallstadt",
    "sg:phone":"+49 6022/654109",
    "sg:postcode":"63868",
    "sg:province":"Bayern",
    "wof:name":"H2o Tuachsport Gmbh",
    "wof:placetype":"venue"
},
  "geometry": {"coordinates":[9.159,49.873581],"type":"Point"}
}