{
  "type": "Feature",
  "properties": {
    "iso:country":"DE",
    "sg:address":"Niemegh",
    "sg:city":"Niemegk",
    "sg:postcode":"14823",
    "sg:province":"Brandenburg",
    "wof:name":"Autobahnrastst\u00e4tte Niemegh West",
    "wof:placetype":"venue"
},
  "geometry": {"coordinates":[12.6586170197,52.0750579834],"type":"Point"}
}