{
  "type": "Feature",
  "properties": {
    "iso:country":"DE",
    "sg:address":"Birkenstr. 8",
    "sg:city":"Laichingen",
    "sg:phone":"+49 7333/6534",
    "sg:postcode":"89150",
    "sg:province":"Baden-W\u00fcrttemberg",
    "wof:name":"Hans Baumann",
    "wof:placetype":"venue"
},
  "geometry": {"coordinates":[9.6232337952,48.4788475037],"type":"Point"}
}