{
  "type": "Feature",
  "properties": {
    "iso:country":"DE",
    "sg:address":"Hohe Str. 11a",
    "sg:city":"Eschweiler",
    "sg:phone":"+49 2403/22137",
    "sg:postcode":"52249",
    "sg:province":"Nordrhein-Westfalen",
    "wof:name":"Michael Nie\u00dfen",
    "wof:placetype":"venue"
},
  "geometry": {"coordinates":[6.2883439064,50.8078918457],"type":"Point"}
}