{
  "type": "Feature",
  "properties": {
    "iso:country":"DE",
    "sg:address":"Bechtstr. 11",
    "sg:city":"Heilbronn",
    "sg:phone":"+49 7131/75521",
    "sg:postcode":"74076",
    "sg:province":"Baden-W\u00fcrttemberg",
    "wof:name":"Arthur Fuhrmann",
    "wof:placetype":"venue"
},
  "geometry": {"coordinates":[9.231605,49.150223],"type":"Point"}
}