{
  "type": "Feature",
  "properties": {
    "iso:country":"DE",
    "sg:address":"Beyer\u00f6hde 14",
    "sg:city":"Wuppertal",
    "sg:phone":"+49 202/602744",
    "sg:postcode":"42389",
    "sg:province":"Nordrhein-Westfalen",
    "wof:name":"Frauke Kafka",
    "wof:placetype":"venue"
},
  "geometry": {"coordinates":[7.250154,51.274292],"type":"Point"}
}