{
  "type": "Feature",
  "properties": {
    "iso:country":"DE",
    "sg:address":"M\u00e4rchenweg 21",
    "sg:city":"Ulm",
    "sg:phone":"+49 731/384916",
    "sg:postcode":"89077",
    "sg:province":"Baden-W\u00fcrttemberg",
    "wof:name":"Kath. Pfarramt Heilig Geist",
    "wof:placetype":"venue"
},
  "geometry": {"coordinates":[9.9618682861,48.3864898682],"type":"Point"}
}