{
  "type": "Feature",
  "properties": {
    "iso:country":"DE",
    "sg:address":"B\u00f6chinger Str. 51",
    "sg:city":"Landau",
    "sg:postcode":"76829",
    "sg:province":"Rheinland-Pfalz",
    "wof:name":"Lothar Kessler & S\u00f6hne",
    "wof:placetype":"venue"
},
  "geometry": {"coordinates":[8.0827350616,49.2151412964],"type":"Point"}
}