{
  "type": "Feature",
  "properties": {
    "iso:country":"DE",
    "sg:address":"Ludwigstr 19",
    "sg:city":"Margetsh\u00f6chheim",
    "sg:phone":"+49 931/4650250",
    "sg:postcode":"97276",
    "sg:province":"Bayern",
    "wof:name":"Dsp-print-tec Gmbh",
    "wof:placetype":"venue"
},
  "geometry": {"coordinates":[9.865881,49.838623],"type":"Point"}
}