{
  "type": "Feature",
  "properties": {
    "iso:country":"DE",
    "sg:address":"Otto-Lilienthal-Str. 68",
    "sg:city":"Finsterwalde",
    "sg:phone":"+49 3531/605728",
    "sg:postcode":"03238",
    "sg:province":"Brandenburg",
    "wof:name":"H\u00e4usliche Alten- Und Krankenpflege",
    "wof:placetype":"venue"
},
  "geometry": {"coordinates":[13.737945,51.598694],"type":"Point"}
}