{
  "type": "Feature",
  "properties": {
    "iso:country":"DE",
    "sg:address":"Trierer Str. 26",
    "sg:city":"Schmelz",
    "sg:phone":"+49 6887/7581",
    "sg:postcode":"66839",
    "sg:province":"Saarland",
    "wof:name":"Karins Model\u00e4dchen",
    "wof:placetype":"venue"
},
  "geometry": {"coordinates":[6.8513898849,49.444278717],"type":"Point"}
}