{
  "type": "Feature",
  "properties": {
    "iso:country":"DE",
    "sg:address":"Schusterstr. 20",
    "sg:city":"M\u00fcnchen",
    "sg:phone":"+49 89/797979",
    "sg:postcode":"81477",
    "sg:province":"Bayern",
    "wof:name":"Dr. Med. Erich Grassl",
    "wof:placetype":"venue"
},
  "geometry": {"coordinates":[11.5108242035,48.0852012634],"type":"Point"}
}