{
  "type": "Feature",
  "properties": {
    "iso:country":"DE",
    "sg:address":"Vor dem Rohre 8",
    "sg:city":"Ronnenberg",
    "sg:phone":"+49 511/432092",
    "sg:postcode":"30952",
    "sg:province":"Niedersachsen",
    "wof:name":"Heinz Scheidler",
    "wof:placetype":"venue"
},
  "geometry": {"coordinates":[9.65811,52.335522],"type":"Point"}
}