{
  "type": "Feature",
  "properties": {
    "iso:country":"DE",
    "sg:address":"Gewerbegebiet",
    "sg:city":"B\u00fcchenbeuren",
    "sg:phone":"+49 6543/9220",
    "sg:postcode":"55491",
    "sg:province":"Rheinland-Pfalz",
    "wof:name":"Jasch Komm Packt-studio",
    "wof:placetype":"venue"
},
  "geometry": {"coordinates":[7.27692,49.919968],"type":"Point"}
}