{
  "type": "Feature",
  "properties": {
    "iso:country":"DE",
    "sg:address":"Hellweg 11",
    "sg:city":"Erwitte",
    "sg:phone":"+49 2943/2985",
    "sg:postcode":"59597",
    "sg:province":"Nordrhein-Westfalen",
    "wof:name":"G. Bergkemper",
    "wof:placetype":"venue"
},
  "geometry": {"coordinates":[8.339012,51.611919],"type":"Point"}
}