{
  "type": "Feature",
  "properties": {
    "iso:country":"DE",
    "sg:address":"Am Driesch 12",
    "sg:city":"Dernbach",
    "sg:phone":"+49 2602/7270",
    "sg:postcode":"56428",
    "sg:province":"Rheinland-Pfalz",
    "wof:name":"Alfons Siry",
    "wof:placetype":"venue"
},
  "geometry": {"coordinates":[7.7925000191,50.4563751221],"type":"Point"}
}