{
  "type": "Feature",
  "properties": {
    "iso:country":"DE",
    "sg:address":"Erlenstr. 12",
    "sg:city":"Hersbruck",
    "sg:phone":"+49 9151/5645",
    "sg:postcode":"91217",
    "sg:province":"Bayern",
    "wof:name":"Bruno L. Behnke Architekt",
    "wof:placetype":"venue"
},
  "geometry": {"coordinates":[11.446001,49.512054],"type":"Point"}
}