{
  "type": "Feature",
  "properties": {
    "iso:country":"DE",
    "sg:address":"Brakeweg 10",
    "sg:city":"Zeven",
    "sg:postcode":"27404",
    "sg:province":"Niedersachsen",
    "wof:name":"Viehhandels-union Gmbh",
    "wof:placetype":"venue"
},
  "geometry": {"coordinates":[9.2832622528,53.2882003784],"type":"Point"}
}