{
  "type": "Feature",
  "properties": {
    "iso:country":"DE",
    "sg:address":"Salacher Str 90-92",
    "sg:city":"Eislingen",
    "sg:phone":"+49 7161/360406",
    "sg:postcode":"73054",
    "sg:province":"Baden-W\u00fcrttemberg",
    "wof:name":"Staudacher Maschinenbau + Retrofit",
    "wof:placetype":"venue"
},
  "geometry": {"coordinates":[9.7171602249,48.7010917664],"type":"Point"}
}