{
  "type": "Feature",
  "properties": {
    "iso:country":"DE",
    "sg:address":"Plauener Str.163-165",
    "sg:city":"Berlin",
    "sg:phone":"+49 4930/3906710",
    "sg:postcode":"13053",
    "sg:province":"Berlin",
    "wof:name":"Abus-a.f.e. Gmbh Cabelsystems & Dristriebution",
    "wof:placetype":"venue"
},
  "geometry": {"coordinates":[13.515775,52.545189],"type":"Point"}
}