{
  "type": "Feature",
  "properties": {
    "iso:country":"DE",
    "sg:address":"Frankfurter Allee 154",
    "sg:city":"Berlin",
    "sg:postcode":"10365",
    "sg:province":"Berlin",
    "wof:name":"Ch. Wenzel",
    "wof:placetype":"venue"
},
  "geometry": {"coordinates":[13.482336,52.512749],"type":"Point"}
}