{
  "type": "Feature",
  "properties": {
    "iso:country":"DE",
    "sg:address":"Isestr. 79",
    "sg:city":"Hamburg",
    "sg:phone":"+49 40/482464",
    "sg:postcode":"20149",
    "sg:province":"Hamburg",
    "wof:name":"Karl Frank",
    "wof:placetype":"venue"
},
  "geometry": {"coordinates":[9.9854927063,53.5836219788],"type":"Point"}
}