{
  "type": "Feature",
  "properties": {
    "iso:country":"DE",
    "sg:address":"Sehringer Str. 5",
    "sg:city":"Badenweiler",
    "sg:phone":"+49 7632/1303",
    "sg:postcode":"79410",
    "sg:province":"Baden-W\u00fcrttemberg",
    "wof:name":"Pension Landhaus Ingrid",
    "wof:placetype":"venue"
},
  "geometry": {"coordinates":[7.6691961288,47.7835731506],"type":"Point"}
}