{
  "type": "Feature",
  "properties": {
    "iso:country":"DE",
    "sg:address":"Hartmannstr. 7a",
    "sg:city":"Chemnitz",
    "sg:phone":"+49 371/600420",
    "sg:postcode":"09111",
    "sg:province":"Sachsen",
    "wof:name":"Poppa Adamietz Und Kollegen Rechtsanw\u00e4lte",
    "wof:placetype":"venue"
},
  "geometry": {"coordinates":[12.9169569016,50.8369598389],"type":"Point"}
}