{
  "type": "Feature",
  "properties": {
    "iso:country":"DE",
    "sg:address":"Treitschkestr. 6a",
    "sg:city":"Karlsruhe",
    "sg:phone":"+49 721/386550",
    "sg:postcode":"76137",
    "sg:province":"Baden-W\u00fcrttemberg",
    "wof:name":"Svalina",
    "wof:placetype":"venue"
},
  "geometry": {"coordinates":[8.406697,48.996758],"type":"Point"}
}