{
  "type": "Feature",
  "properties": {
    "iso:country":"DE",
    "sg:address":"Kurt-Schumacher-Str. 1",
    "sg:city":"Linden",
    "sg:phone":"+49 6403/9750",
    "sg:postcode":"35440",
    "sg:province":"Hessen",
    "wof:name":"Compu-tech Hard- Und Software Gmbh",
    "wof:placetype":"venue"
},
  "geometry": {"coordinates":[8.6678819656,50.5262756348],"type":"Point"}
}