{
  "type": "Feature",
  "properties": {
    "iso:country":"DE",
    "sg:address":"Schallfelder Str. 51",
    "sg:city":"Gerolzhofen",
    "sg:phone":"+49 9382/1300",
    "sg:postcode":"97447",
    "sg:province":"Bayern",
    "wof:name":"Vereinsgastst\u00e4tte Fc Stadion",
    "wof:placetype":"venue"
},
  "geometry": {"coordinates":[10.3528909683,49.8903503418],"type":"Point"}
}