{
  "type": "Feature",
  "properties": {
    "iso:country":"DE",
    "sg:address":"Schleusinger Str. 21",
    "sg:city":"Hildburghausen",
    "sg:postcode":"98646",
    "sg:province":"Th\u00fcringen",
    "wof:name":"Gemeindeschwesterstation",
    "wof:placetype":"venue"
},
  "geometry": {"coordinates":[10.728927,50.429684],"type":"Point"}
}