{
  "type": "Feature",
  "properties": {
    "iso:country":"DE",
    "sg:address":"Vl\u00e4mische Str. 48",
    "sg:city":"Lastrup",
    "sg:phone":"+49 4472/920003",
    "sg:postcode":"49688",
    "sg:province":"Niedersachsen",
    "wof:name":"Alwin Sommer",
    "wof:placetype":"venue"
},
  "geometry": {"coordinates":[7.873026,52.800064],"type":"Point"}
}