{
  "type": "Feature",
  "properties": {
    "iso:country":"DE",
    "sg:address":"Robert-Bosch-Str. 40",
    "sg:city":"Bamberg",
    "sg:phone":"+49 951/1810",
    "sg:postcode":"96050",
    "sg:province":"Bayern",
    "wof:name":"Robert Bosch Gmbh",
    "wof:placetype":"venue"
},
  "geometry": {"coordinates":[10.9171171188,49.8929405212],"type":"Point"}
}