{
  "type": "Feature",
  "properties": {
    "iso:country":"DE",
    "sg:address":"Bellevuestr. 1",
    "sg:city":"Berlin",
    "sg:postcode":"10785",
    "sg:province":"Berlin",
    "wof:name":"Kaisersaal Vermarktung Gmbh",
    "wof:placetype":"venue"
},
  "geometry": {"coordinates":[13.374645,52.510063],"type":"Point"}
}