{
  "type": "Feature",
  "properties": {
    "iso:country":"DE",
    "sg:address":"Neuenhofer Str. 121a",
    "sg:city":"Solingen",
    "sg:phone":"+49 212/809986",
    "sg:postcode":"42657",
    "sg:province":"Nordrhein-Westfalen",
    "wof:name":"Eiscafe Aldo Roccatani",
    "wof:placetype":"venue"
},
  "geometry": {"coordinates":[7.072991,51.158447],"type":"Point"}
}