{
  "type": "Feature",
  "properties": {
    "iso:country":"DE",
    "sg:address":"Kaiserstr. 16",
    "sg:city":"Hildesheim",
    "sg:phone":"+49 5121/32667",
    "sg:postcode":"31134",
    "sg:province":"Niedersachsen",
    "wof:name":"Heino Berger",
    "wof:placetype":"venue"
},
  "geometry": {"coordinates":[9.9503755569,52.1553230286],"type":"Point"}
}