{
  "type": "Feature",
  "properties": {
    "iso:country":"DE",
    "sg:address":"Rheider Weg 3",
    "sg:city":"Kropp",
    "sg:phone":"+49 4624/1763",
    "sg:postcode":"24848",
    "sg:province":"Schleswig-Holstein",
    "wof:name":"Clausens Feierabendheim",
    "wof:placetype":"venue"
},
  "geometry": {"coordinates":[9.507492,54.413231],"type":"Point"}
}