{
  "type": "Feature",
  "properties": {
    "iso:country":"DE",
    "sg:address":"Hildesheimer Str. 390",
    "sg:city":"Hannover",
    "sg:phone":"+49 511/869575",
    "sg:postcode":"30519",
    "sg:province":"Niedersachsen",
    "wof:name":"J\u00fcrgen Lehnigk E. K.",
    "wof:placetype":"venue"
},
  "geometry": {"coordinates":[9.7797689438,52.3272857666],"type":"Point"}
}