{
  "type": "Feature",
  "properties": {
    "iso:country":"DE",
    "sg:address":"Schmetzweg 14",
    "sg:city":"Essen",
    "sg:phone":"+49 201/356417",
    "sg:postcode":"45326",
    "sg:province":"Nordrhein-Westfalen",
    "wof:name":"Marion Tutta\u00df",
    "wof:placetype":"venue"
},
  "geometry": {"coordinates":[7.021083,51.494884],"type":"Point"}
}