{
  "type": "Feature",
  "properties": {
    "iso:country":"DE",
    "sg:address":"Ammerstr. 101",
    "sg:city":"M\u00fchlhausen",
    "sg:phone":"+49 36014/40220",
    "sg:postcode":"99974",
    "sg:province":"Th\u00fcringen",
    "wof:name":"T. Hecht",
    "wof:placetype":"venue"
},
  "geometry": {"coordinates":[10.454372406,51.2132339478],"type":"Point"}
}