{
  "type": "Feature",
  "properties": {
    "iso:country":"DE",
    "sg:address":"Seegrabenweg 34",
    "sg:city":"Halstenbek",
    "sg:phone":"+49 4101/402723",
    "sg:postcode":"25469",
    "sg:province":"Schleswig-Holstein",
    "wof:name":"Peter-detlef Szimber Rechtsanwalt",
    "wof:placetype":"venue"
},
  "geometry": {"coordinates":[9.8717212677,53.6258850098],"type":"Point"}
}