{
  "type": "Feature",
  "properties": {
    "iso:country":"DE",
    "sg:address":"Steinheimer Str 37",
    "sg:city":"Heidenheim",
    "sg:phone":"+49 7321/98530",
    "sg:postcode":"89518",
    "sg:province":"Baden-W\u00fcrttemberg",
    "wof:name":"Dannenmann Gmbh",
    "wof:placetype":"venue"
},
  "geometry": {"coordinates":[10.117685,48.679432],"type":"Point"}
}