{
  "type": "Feature",
  "properties": {
    "iso:country":"DE",
    "sg:address":"Koblenzer Str. 32",
    "sg:city":"Wenden",
    "sg:phone":"+49 2762/1311",
    "sg:postcode":"57482",
    "sg:province":"Nordrhein-Westfalen",
    "wof:name":"August Ridder",
    "wof:placetype":"venue"
},
  "geometry": {"coordinates":[7.845087,50.987682],"type":"Point"}
}