{
  "type": "Feature",
  "properties": {
    "iso:country":"DE",
    "sg:address":"Hans-Thoma-Weg 13",
    "sg:city":"Kirchheim",
    "sg:phone":"+49 7021/55651",
    "sg:postcode":"73230",
    "sg:province":"Baden-W\u00fcrttemberg",
    "wof:name":"Sabine Bosch Steuerberaterin",
    "wof:placetype":"venue"
},
  "geometry": {"coordinates":[9.4486932755,48.6404342651],"type":"Point"}
}