{
  "type": "Feature",
  "properties": {
    "iso:country":"DE",
    "sg:address":"Moorbeerenweg 1",
    "sg:city":"Peine",
    "sg:phone":"+49 5171/4030",
    "sg:postcode":"31228",
    "sg:province":"Niedersachsen",
    "wof:name":"Pwr Wasser Und Rohrtechnik Gmbh",
    "wof:placetype":"venue"
},
  "geometry": {"coordinates":[10.241479,52.352158],"type":"Point"}
}