{
  "type": "Feature",
  "properties": {
    "iso:country":"DE",
    "sg:address":"76703",
    "sg:city":"Kraichtal-Bahnbrucken",
    "sg:postcode":"76703",
    "sg:province":"Baden-W\u00fcrttemberg",
    "wof:name":"Raiffeisenbank Bahnbr\u00fccken Eg",
    "wof:placetype":"venue"
},
  "geometry": {"coordinates":[8.78671,49.118649],"type":"Point"}
}