{
  "type": "Feature",
  "properties": {
    "iso:country":"DE",
    "sg:address":"Friedensplatz 15",
    "sg:city":"Kevelaer",
    "sg:phone":"+49 2832/3093",
    "sg:postcode":"47625",
    "sg:province":"Nordrhein-Westfalen",
    "wof:name":"Marktgrill",
    "wof:placetype":"venue"
},
  "geometry": {"coordinates":[6.2927727699,51.5701599121],"type":"Point"}
}