{
  "type": "Feature",
  "properties": {
    "iso:country":"DE",
    "sg:address":"Allg\u00e4uer Str. 3",
    "sg:city":"Halblech",
    "sg:phone":"+49 8368/305",
    "sg:postcode":"87642",
    "sg:province":"Bayern",
    "wof:name":"Alfons L\u00f6chle",
    "wof:placetype":"venue"
},
  "geometry": {"coordinates":[10.828005,47.64336],"type":"Point"}
}