{
  "type": "Feature",
  "properties": {
    "iso:country":"DE",
    "sg:address":"Karl-May-Str. 20",
    "sg:city":"Erlangen",
    "sg:phone":"+49 9131/991347",
    "sg:postcode":"91056",
    "sg:province":"Bayern",
    "wof:name":"Gerd Scheidel",
    "wof:placetype":"venue"
},
  "geometry": {"coordinates":[10.95358181,49.5696792603],"type":"Point"}
}