{
  "type": "Feature",
  "properties": {
    "iso:country":"DE",
    "sg:address":"Monschauer Str. 7",
    "sg:city":"D\u00fcsseldorf",
    "sg:postcode":"40549",
    "sg:province":"Nordrhein-Westfalen",
    "wof:name":"Bazzar Caff\u00e8 Vertriebs Gmbh & Co. Kg",
    "wof:placetype":"venue"
},
  "geometry": {"coordinates":[6.7010769844,51.2334022522],"type":"Point"}
}