{
  "type": "Feature",
  "properties": {
    "iso:country":"DE",
    "sg:address":"Nordstr. 48",
    "sg:city":"Bocholt",
    "sg:phone":"+49 2871/186459",
    "sg:postcode":"46399",
    "sg:province":"Nordrhein-Westfalen",
    "wof:name":"G. Pehl",
    "wof:placetype":"venue"
},
  "geometry": {"coordinates":[6.615745,51.840897],"type":"Point"}
}