{
  "type": "Feature",
  "properties": {
    "iso:country":"DE",
    "sg:address":"Ammerseestr. 44",
    "sg:city":"Augsburg",
    "sg:phone":"+49 821/61851",
    "sg:postcode":"86163",
    "sg:province":"Bayern",
    "wof:name":"Wolfgang Fahnert",
    "wof:placetype":"venue"
},
  "geometry": {"coordinates":[10.940934,48.364506],"type":"Point"}
}