{
  "type": "Feature",
  "properties": {
    "iso:country":"DE",
    "sg:address":"Westfalendamm 96",
    "sg:city":"Dortmund",
    "sg:phone":"+49 231/540000",
    "sg:postcode":"44141",
    "sg:province":"Nordrhein-Westfalen",
    "wof:name":"Gothaer Lebensversicherung Gothaer Lebensversicherung Ag",
    "wof:placetype":"venue"
},
  "geometry": {"coordinates":[7.493368,51.503483],"type":"Point"}
}