{
  "type": "Feature",
  "properties": {
    "iso:country":"DE",
    "sg:address":"Mauerstr. 8",
    "sg:city":"Eschwege",
    "sg:phone":"+49 5651/70222",
    "sg:postcode":"37269",
    "sg:province":"Hessen",
    "wof:name":"Kirchning Und Throm",
    "wof:placetype":"venue"
},
  "geometry": {"coordinates":[10.0565471649,51.1834144592],"type":"Point"}
}