{
  "type": "Feature",
  "properties": {
    "iso:country":"DE",
    "sg:address":"Spielberger Weg 58",
    "sg:city":"D\u00fcsseldorf",
    "sg:phone":"+49 211/3859332",
    "sg:postcode":"40474",
    "sg:province":"Nordrhein-Westfalen",
    "wof:name":"Digit Digitale Medienproduktion Gmbh",
    "wof:placetype":"venue"
},
  "geometry": {"coordinates":[6.744835,51.27866],"type":"Point"}
}