{
  "type": "Feature",
  "properties": {
    "iso:country":"DE",
    "sg:address":"Hechendorf",
    "sg:city":"Seefeld",
    "sg:phone":"+49 8152/70107",
    "sg:postcode":"82229",
    "sg:province":"Bayern",
    "wof:name":"M. Merz Wirtschaftspr\u00fcfer Und",
    "wof:placetype":"venue"
},
  "geometry": {"coordinates":[11.1834697723,48.0334815979],"type":"Point"}
}