{
  "type": "Feature",
  "properties": {
    "iso:country":"DE",
    "sg:address":"Klingenberg 1-3",
    "sg:city":"L\u00fcbeck",
    "sg:postcode":"23552",
    "sg:province":"Schleswig-Holstein",
    "wof:name":"K & P - Beteiligungs Gmbh",
    "wof:placetype":"venue"
},
  "geometry": {"coordinates":[10.684898,53.864578],"type":"Point"}
}