{
  "type": "Feature",
  "properties": {
    "iso:country":"DE",
    "sg:address":"Am Stadthafen 22",
    "sg:city":"Recklinghausen",
    "sg:phone":"+49 2361/66080",
    "sg:postcode":"45663",
    "sg:province":"Nordrhein-Westfalen",
    "wof:name":"Emil Stenzel Gmbh & Co. Kg",
    "wof:placetype":"venue"
},
  "geometry": {"coordinates":[7.215415,51.56155],"type":"Point"}
}