{
  "type": "Feature",
  "properties": {
    "iso:country":"DE",
    "sg:address":"Alfred-Nobel-Str. 19",
    "sg:city":"Mainz",
    "sg:postcode":"55124",
    "sg:province":"Rheinland-Pfalz",
    "wof:name":"Antoniaus Mode",
    "wof:placetype":"venue"
},
  "geometry": {"coordinates":[8.190204,49.997623],"type":"Point"}
}