{
  "type": "Feature",
  "properties": {
    "iso:country":"DE",
    "sg:address":"Ehrsamer Weg 8",
    "sg:city":"Gie\u00dfen",
    "sg:phone":"+49 6403/2539",
    "sg:postcode":"35398",
    "sg:province":"Hessen",
    "wof:name":"Gerhard Volk Architekt",
    "wof:placetype":"venue"
},
  "geometry": {"coordinates":[8.622913,50.552868],"type":"Point"}
}