{
  "type": "Feature",
  "properties": {
    "iso:country":"DE",
    "sg:address":"Broicher Waldweg 113",
    "sg:city":"M\u00fclheim",
    "sg:phone":"+49 208/591124",
    "sg:postcode":"45478",
    "sg:province":"Nordrhein-Westfalen",
    "wof:name":"U. Stralkowski",
    "wof:placetype":"venue"
},
  "geometry": {"coordinates":[6.84056,51.413834],"type":"Point"}
}