{
  "type": "Feature",
  "properties": {
    "iso:country":"DE",
    "sg:address":"Maximilian-Kolbe-Str. 30",
    "sg:city":"Alzey",
    "sg:phone":"+49 6731/3142",
    "sg:postcode":"55232",
    "sg:province":"Rheinland-Pfalz",
    "wof:name":"Gerhard Schifferstein Architekt",
    "wof:placetype":"venue"
},
  "geometry": {"coordinates":[8.09474,49.737911],"type":"Point"}
}