{
  "type": "Feature",
  "properties": {
    "iso:country":"DE",
    "sg:address":"Hauptstr. 30",
    "sg:city":"Rabenau",
    "sg:phone":"+49 351/6413335",
    "sg:postcode":"01734",
    "sg:province":"Sachsen",
    "wof:name":"A. K\u00f6hler",
    "wof:placetype":"venue"
},
  "geometry": {"coordinates":[13.6717596054,50.9444694519],"type":"Point"}
}