{
  "type": "Feature",
  "properties": {
    "iso:country":"DE",
    "sg:address":"Hauptstr. 8",
    "sg:city":"Rieth",
    "sg:phone":"+49 36871/29260",
    "sg:postcode":"98663",
    "sg:province":"Th\u00fcringen",
    "wof:name":"Elektro Roba",
    "wof:placetype":"venue"
},
  "geometry": {"coordinates":[10.6318750381,50.2632408142],"type":"Point"}
}