{
  "type": "Feature",
  "properties": {
    "iso:country":"DE",
    "sg:address":"Kirchweyher Str.",
    "sg:city":"Uelzen",
    "sg:phone":"+49 581/16110",
    "sg:postcode":"29525",
    "sg:province":"Niedersachsen",
    "wof:name":"W. Barenscheer",
    "wof:placetype":"venue"
},
  "geometry": {"coordinates":[10.5352497101,53.0023574829],"type":"Point"}
}