{
  "type": "Feature",
  "properties": {
    "iso:country":"DE",
    "sg:address":"Kauffahrtei 23",
    "sg:city":"Chemnitz",
    "sg:phone":"+49 371/2800216",
    "sg:postcode":"09120",
    "sg:province":"Sachsen",
    "wof:name":"Mako Ges. F\u00fcr Projektent- Wicklung Und Baubetreuung Mbh",
    "wof:placetype":"venue"
},
  "geometry": {"coordinates":[12.905033,50.811718],"type":"Point"}
}