{
  "type": "Feature",
  "properties": {
    "iso:country":"DE",
    "sg:address":"Bergbreite 4",
    "sg:city":"Wolmirstedt",
    "sg:phone":"+49 39201/70743",
    "sg:postcode":"39326",
    "sg:province":"Sachsen-Anhalt",
    "wof:name":"Jh-bauservice Gmbh",
    "wof:placetype":"venue"
},
  "geometry": {"coordinates":[11.6334676743,52.2532806396],"type":"Point"}
}