{
  "type": "Feature",
  "properties": {
    "iso:country":"DE",
    "sg:address":"Vogelreichsweg 1",
    "sg:city":"Bad Pyrmont",
    "sg:phone":"+49 5281/93050",
    "sg:postcode":"31812",
    "sg:province":"Niedersachsen",
    "wof:name":"Werner Rohden Und Partner",
    "wof:placetype":"venue"
},
  "geometry": {"coordinates":[9.2624874115,51.9873962402],"type":"Point"}
}