{
  "type": "Feature",
  "properties": {
    "iso:country":"DE",
    "sg:address":"Lorenzstr. 15",
    "sg:city":"Grimma",
    "sg:phone":"+49 3437/917547",
    "sg:postcode":"04668",
    "sg:province":"Sachsen",
    "wof:name":"Fahrschule Rosenberger , Grimma",
    "wof:placetype":"venue"
},
  "geometry": {"coordinates":[12.7296180725,51.2356529236],"type":"Point"}
}