{
  "type": "Feature",
  "properties": {
    "iso:country":"DE",
    "sg:address":"Nienburger Str. 76",
    "sg:city":"Rehden",
    "sg:postcode":"49453",
    "sg:province":"Niedersachsen",
    "wof:name":"Aeros Logistik Gmbh",
    "wof:placetype":"venue"
},
  "geometry": {"coordinates":[8.5142478943,52.6107940674],"type":"Point"}
}