{
  "type": "Feature",
  "properties": {
    "iso:country":"DE",
    "sg:address":"Neust\u00e4dter Str. 8",
    "sg:city":"Gr\u00f6mitz",
    "sg:phone":"+49 4562/22888",
    "sg:postcode":"23743",
    "sg:province":"Schleswig-Holstein",
    "wof:name":"Ostsee-apotheke",
    "wof:placetype":"venue"
},
  "geometry": {"coordinates":[10.955594,54.152004],"type":"Point"}
}