{
  "type": "Feature",
  "properties": {
    "iso:country":"DE",
    "sg:address":"Am Dorfteich 1",
    "sg:city":"Reu\u00dfen",
    "sg:phone":"+49 34602/52104",
    "sg:postcode":"06188",
    "sg:province":"Sachsen-Anhalt",
    "wof:name":"Karl-heinz Keindorf",
    "wof:placetype":"venue"
},
  "geometry": {"coordinates":[12.1299762726,51.5010604858],"type":"Point"}
}