{
  "type": "Feature",
  "properties": {
    "iso:country":"DE",
    "sg:address":"Bergstr. 13",
    "sg:city":"Landsberg",
    "sg:phone":"+49 34602/20708",
    "sg:postcode":"06188",
    "sg:province":"Sachsen-Anhalt",
    "wof:name":"Manfred Berger",
    "wof:placetype":"venue"
},
  "geometry": {"coordinates":[12.1669025421,51.5262451172],"type":"Point"}
}