{
  "type": "Feature",
  "properties": {
    "iso:country":"DE",
    "sg:address":"Rosenweg 22",
    "sg:city":"Niederrieden",
    "sg:phone":"+49 8335/9116",
    "sg:postcode":"87767",
    "sg:province":"Bayern",
    "wof:name":"J. Turzer Ingenieur",
    "wof:placetype":"venue"
},
  "geometry": {"coordinates":[10.1827716827,48.059211731],"type":"Point"}
}