{
  "type": "Feature",
  "properties": {
    "iso:country":"DE",
    "sg:address":"Ansbacher Str. 1",
    "sg:city":"Marktbergel",
    "sg:phone":"+49 9843/97990",
    "sg:postcode":"91613",
    "sg:province":"Bayern",
    "wof:name":"Brunnen Apotheke G\u00fcnter Opel",
    "wof:placetype":"venue"
},
  "geometry": {"coordinates":[10.364249,49.441639],"type":"Point"}
}