{
  "type": "Feature",
  "properties": {
    "iso:country":"DE",
    "sg:address":"Betzenriedstr. 30",
    "sg:city":"Reutlingen",
    "sg:phone":"+49 7121/490555",
    "sg:postcode":"72764",
    "sg:province":"Baden-W\u00fcrttemberg",
    "wof:name":"Volker B\u00e4chtle",
    "wof:placetype":"venue"
},
  "geometry": {"coordinates":[9.22605896,48.4875144958],"type":"Point"}
}