{
  "type": "Feature",
  "properties": {
    "iso:country":"DE",
    "sg:address":"Franzstr. 36",
    "sg:city":"Bonn",
    "sg:phone":"+49 228/638629",
    "sg:postcode":"53111",
    "sg:province":"Nordrhein-Westfalen",
    "wof:name":"Babel",
    "wof:placetype":"venue"
},
  "geometry": {"coordinates":[7.09248209,50.7372322083],"type":"Point"}
}