{
  "type": "Feature",
  "properties": {
    "iso:country":"DE",
    "sg:address":"Halsdorfer Str. 56",
    "sg:city":"Wohratal",
    "sg:phone":"+49 6453/1201",
    "sg:postcode":"35288",
    "sg:province":"Hessen",
    "wof:name":"B\u00fcrgerhaus",
    "wof:placetype":"venue"
},
  "geometry": {"coordinates":[8.945400238,50.9262695312],"type":"Point"}
}