{
  "type": "Feature",
  "properties": {
    "iso:country":"DE",
    "sg:address":"Bornstr. 5",
    "sg:city":"Berlin",
    "sg:phone":"+49 30/8528949",
    "sg:postcode":"12163",
    "sg:province":"Berlin",
    "wof:name":"Dorothea Goldbeck-knorr Steuerberaterin",
    "wof:placetype":"venue"
},
  "geometry": {"coordinates":[13.3263721466,52.4653587341],"type":"Point"}
}