{
  "type": "Feature",
  "properties": {
    "iso:country":"DE",
    "sg:address":"Dresdener Str. 26",
    "sg:city":"Spremberg",
    "sg:postcode":"03130",
    "sg:province":"Brandenburg",
    "wof:name":"Bautr\u00e4gergesellschaft Mbh",
    "wof:placetype":"venue"
},
  "geometry": {"coordinates":[14.3680582047,51.5675506592],"type":"Point"}
}