{
  "type": "Feature",
  "properties": {
    "iso:country":"DE",
    "sg:address":"Berliner Allee 7",
    "sg:city":"Hannover",
    "sg:phone":"+49 4927/529348",
    "sg:postcode":"30175",
    "sg:province":"Niedersachsen",
    "wof:name":"Steinberg-bau Gmbh",
    "wof:placetype":"venue"
},
  "geometry": {"coordinates":[8.4330234528,50.9268875122],"type":"Point"}
}