{
  "type": "Feature",
  "properties": {
    "iso:country":"DE",
    "sg:address":"Schlaunstr. 9",
    "sg:city":"Warendorf",
    "sg:phone":"+49 2581/3017",
    "sg:postcode":"48231",
    "sg:province":"Nordrhein-Westfalen",
    "wof:name":"K. Dotterweich Anlageberatung",
    "wof:placetype":"venue"
},
  "geometry": {"coordinates":[7.9923567772,51.9614295959],"type":"Point"}
}