{
  "type": "Feature",
  "properties": {
    "iso:country":"DE",
    "sg:address":"An Der Haselmauer 3",
    "sg:city":"Nisterau",
    "sg:phone":"+49 2741/281555",
    "sg:postcode":"56472",
    "sg:province":"Rheinland-Pfalz",
    "wof:name":"Wolf-garten Gmbh & Co. Kg Eurogreen",
    "wof:placetype":"venue"
},
  "geometry": {"coordinates":[7.978734,50.664047],"type":"Point"}
}