{
  "type": "Feature",
  "properties": {
    "iso:country":"DE",
    "sg:address":"An der Strusbek 8 d",
    "sg:city":"Ahrensburg",
    "sg:phone":"+49 4102/21130",
    "sg:postcode":"22926",
    "sg:province":"Schleswig-Holstein",
    "wof:name":"I. K. F. Klaus Falk",
    "wof:placetype":"venue"
},
  "geometry": {"coordinates":[10.2675447464,53.6839866638],"type":"Point"}
}