{
  "type": "Feature",
  "properties": {
    "iso:country":"DE",
    "sg:address":"Wellesweilerstr. 15",
    "sg:city":"Neunkirchen",
    "sg:phone":"+49 6821/22305",
    "sg:postcode":"66538",
    "sg:province":"Saarland",
    "wof:name":"Gerd Weingard",
    "wof:placetype":"venue"
},
  "geometry": {"coordinates":[7.1764330864,49.3513031006],"type":"Point"}
}