{
  "type": "Feature",
  "properties": {
    "iso:country":"DE",
    "sg:address":"Alkener Weg 2",
    "sg:city":"Oberfell",
    "sg:phone":"+49 2605/2342",
    "sg:postcode":"56332",
    "sg:province":"Rheinland-Pfalz",
    "wof:name":"Gerhard Dr\u00e4ger",
    "wof:placetype":"venue"
},
  "geometry": {"coordinates":[7.444682,50.258667],"type":"Point"}
}