{
  "type": "Feature",
  "properties": {
    "iso:country":"DE",
    "sg:address":"Zum Feldberg 9",
    "sg:city":"Schmitten",
    "sg:phone":"+49 6084/3623",
    "sg:postcode":"61389",
    "sg:province":"Hessen",
    "wof:name":"Destille",
    "wof:placetype":"venue"
},
  "geometry": {"coordinates":[8.4441308975,50.26902771],"type":"Point"}
}