{
  "type": "Feature",
  "properties": {
    "iso:country":"DE",
    "sg:address":"Burgstr. 17",
    "sg:city":"Walld\u00fcrn",
    "sg:phone":"+49 6282/325",
    "sg:postcode":"74731",
    "sg:province":"Baden-W\u00fcrttemberg",
    "wof:name":"Pfarrb\u00fccherei Im Kath. Kindergarten",
    "wof:placetype":"venue"
},
  "geometry": {"coordinates":[9.366361,49.584885],"type":"Point"}
}