{
  "type": "Feature",
  "properties": {
    "iso:country":"DE",
    "sg:address":"Industriepark Stra\u00dfe A 1",
    "sg:city":"Gommern",
    "sg:phone":"+49 39200/50040",
    "sg:postcode":"39245",
    "sg:province":"Sachsen-Anhalt",
    "wof:name":"Immuna Gmbh",
    "wof:placetype":"venue"
},
  "geometry": {"coordinates":[11.8213672638,52.0823135376],"type":"Point"}
}