{
  "type": "Feature",
  "properties": {
    "iso:country":"DE",
    "sg:address":"Schottstr. 1",
    "sg:city":"Mainz",
    "sg:phone":"+49 6131/960110",
    "sg:postcode":"55116",
    "sg:province":"Rheinland-Pfalz",
    "wof:name":"Hotel K\u00f6nigshof Gmbh",
    "wof:placetype":"venue"
},
  "geometry": {"coordinates":[8.2605142593,50.0020599365],"type":"Point"}
}