{
  "type": "Feature",
  "properties": {
    "iso:country":"DE",
    "sg:address":"Industriestr. 35",
    "sg:city":"M\u00fchlheim",
    "sg:phone":"+49 6108/69427",
    "sg:postcode":"63165",
    "sg:province":"Hessen",
    "wof:name":"Baugesch\u00e4ft Alfred Griesbach Gmbh",
    "wof:placetype":"venue"
},
  "geometry": {"coordinates":[8.849737,50.118298],"type":"Point"}
}