{
  "type": "Feature",
  "properties": {
    "iso:country":"DE",
    "sg:address":"Rupprechtstr. 28",
    "sg:city":"Bayreuth",
    "sg:phone":"+49 921/69493",
    "sg:postcode":"95444",
    "sg:province":"Bayern",
    "wof:name":"Th. Silberberger",
    "wof:placetype":"venue"
},
  "geometry": {"coordinates":[11.56577,49.941559],"type":"Point"}
}