{
  "type": "Feature",
  "properties": {
    "iso:country":"DE",
    "sg:address":"Zum Wei\u00dfenstein 9",
    "sg:city":"Adendorf",
    "sg:phone":"+49 4131/188613",
    "sg:postcode":"21365",
    "sg:province":"Niedersachsen",
    "wof:name":"L\u00fcneburger Kakteeng\u00e4rtnerei",
    "wof:placetype":"venue"
},
  "geometry": {"coordinates":[10.463896,53.281628],"type":"Point"}
}