{
  "type": "Feature",
  "properties": {
    "iso:country":"DE",
    "sg:address":"Bachweg 2",
    "sg:city":"Wiesbaden",
    "sg:phone":"+49 6122/13363",
    "sg:postcode":"65207",
    "sg:province":"Hessen",
    "wof:name":"Bernhard K\u00f6hler",
    "wof:placetype":"venue"
},
  "geometry": {"coordinates":[8.3711910248,50.0795211792],"type":"Point"}
}