{
  "type": "Feature",
  "properties": {
    "iso:country":"DE",
    "sg:address":"Oberes Brunnental 1 b",
    "sg:city":"Lauingen",
    "sg:phone":"+49 9072/3055",
    "sg:postcode":"89415",
    "sg:province":"Bayern",
    "wof:name":"Altenheim Der Hospital-stiftung",
    "wof:placetype":"venue"
},
  "geometry": {"coordinates":[10.431915,48.568832],"type":"Point"}
}