{
  "type": "Feature",
  "properties": {
    "iso:country":"DE",
    "sg:address":"Am Ilmbach 44",
    "sg:city":"Leutenberg",
    "sg:phone":"+49 36734/33544",
    "sg:postcode":"07338",
    "sg:province":"Th\u00fcringen",
    "wof:name":"Sm Labor Gmbh",
    "wof:placetype":"venue"
},
  "geometry": {"coordinates":[11.454974,50.564831],"type":"Point"}
}