{
  "type": "Feature",
  "properties": {
    "iso:country":"DE",
    "sg:address":"Senator-Schwartz-Ring 26",
    "sg:city":"Soest",
    "sg:phone":"+49 4929/21690",
    "sg:postcode":"59494",
    "sg:province":"Nordrhein-Westfalen",
    "wof:name":"Ceag Sicherheits- Technik Gmbh",
    "wof:placetype":"venue"
},
  "geometry": {"coordinates":[8.084195,51.558823],"type":"Point"}
}