{
  "type": "Feature",
  "properties": {
    "iso:country":"DE",
    "sg:address":"Marktstr. 47",
    "sg:city":"Bad T\u00f6lz",
    "sg:phone":"+49 8041/9561",
    "sg:postcode":"83646",
    "sg:province":"Bayern",
    "wof:name":"Modehaus Franz Schneller",
    "wof:placetype":"venue"
},
  "geometry": {"coordinates":[11.560424,47.761116],"type":"Point"}
}