{
  "type": "Feature",
  "properties": {
    "iso:country":"DE",
    "sg:address":"Danziger Str 10",
    "sg:city":"Bockenem",
    "sg:phone":"+49 5067/2131",
    "sg:postcode":"31167",
    "sg:province":"Niedersachsen",
    "wof:name":"Wittenberg Antennen Gmbh",
    "wof:placetype":"venue"
},
  "geometry": {"coordinates":[10.132099,52.003662],"type":"Point"}
}