{
  "type": "Feature",
  "properties": {
    "iso:country":"DE",
    "sg:address":"Stuttgarter Str. 63",
    "sg:city":"Leonberg",
    "sg:phone":"+49 7152/6275",
    "sg:postcode":"71229",
    "sg:province":"Baden-W\u00fcrttemberg",
    "wof:name":"Alexander Rilling Rechtsanwalt",
    "wof:placetype":"venue"
},
  "geometry": {"coordinates":[9.022942543,48.8037109375],"type":"Point"}
}