{
  "type": "Feature",
  "properties": {
    "iso:country":"DE",
    "sg:address":"Bosseborner Str. 19",
    "sg:city":"H\u00f6xter",
    "sg:postcode":"37671",
    "sg:province":"Nordrhein-Westfalen",
    "wof:name":"M\u00f6ller Metallverarbeitung Gmbh & Co. Kg",
    "wof:placetype":"venue"
},
  "geometry": {"coordinates":[9.2983436584,51.7762527466],"type":"Point"}
}