{
  "type": "Feature",
  "properties": {
    "iso:country":"DE",
    "sg:address":"Festungsstr. 1",
    "sg:city":"Schnaittach",
    "sg:phone":"+49 9153/923918",
    "sg:postcode":"91220",
    "sg:province":"Bayern",
    "wof:name":"Dachdeckerei Satilmis Gmbh",
    "wof:placetype":"venue"
},
  "geometry": {"coordinates":[11.340961,49.558861],"type":"Point"}
}