{
  "type": "Feature",
  "properties": {
    "iso:country":"DE",
    "sg:address":"Mengener Str. 15",
    "sg:city":"Scheer",
    "sg:phone":"+49 7572/8230",
    "sg:postcode":"72516",
    "sg:province":"Baden-W\u00fcrttemberg",
    "wof:name":"Norbert Herde Architekt",
    "wof:placetype":"venue"
},
  "geometry": {"coordinates":[9.294888,48.07196],"type":"Point"}
}