{
  "type": "Feature",
  "properties": {
    "iso:country":"DE",
    "sg:address":"Martin-Luther-Ring 3",
    "sg:city":"Leipzig",
    "sg:phone":"+49 341/25630",
    "sg:postcode":"04109",
    "sg:province":"Sachsen",
    "wof:name":"Carrier Network Services Management Gmbh",
    "wof:placetype":"venue"
},
  "geometry": {"coordinates":[12.370673,51.337719],"type":"Point"}
}