{
  "type": "Feature",
  "properties": {
    "iso:country":"DE",
    "sg:address":"Weinstr. 14",
    "sg:city":"Pegnitz",
    "sg:phone":"+49 9241/3459",
    "sg:postcode":"91257",
    "sg:province":"Bayern",
    "wof:name":"Albin Persau",
    "wof:placetype":"venue"
},
  "geometry": {"coordinates":[11.5309991837,49.725730896],"type":"Point"}
}