{
  "type": "Feature",
  "properties": {
    "iso:country":"DE",
    "sg:address":"Palaisstr. 10",
    "sg:city":"Detmold",
    "sg:postcode":"32756",
    "sg:province":"Nordrhein-Westfalen",
    "wof:name":"Palais-wohnungsbauges. Mbh",
    "wof:placetype":"venue"
},
  "geometry": {"coordinates":[8.870721817,51.9342346191],"type":"Point"}
}