{
  "type": "Feature",
  "properties": {
    "iso:country":"DE",
    "sg:address":"G\u00fcterstr. 12",
    "sg:city":"Wilhelmshaven",
    "sg:phone":"+49 4421/745351",
    "sg:postcode":"26389",
    "sg:province":"Niedersachsen",
    "wof:name":"Miele Spezialist Kolb",
    "wof:placetype":"venue"
},
  "geometry": {"coordinates":[8.084569931,53.5202903748],"type":"Point"}
}