{
  "type": "Feature",
  "properties": {
    "iso:country":"DE",
    "sg:address":"Hollefeldstr. 59",
    "sg:city":"Emsdetten",
    "sg:phone":"+49 4925/7293000",
    "sg:postcode":"48282",
    "sg:province":"Nordrhein-Westfalen",
    "wof:name":"Autohaus Maria Czekalla Gmbah & Co. Kg",
    "wof:placetype":"venue"
},
  "geometry": {"coordinates":[7.563313961,52.1482582092],"type":"Point"}
}