{
  "type": "Feature",
  "properties": {
    "iso:country":"DE",
    "sg:address":"Krugstr. 4",
    "sg:city":"Wingerode",
    "sg:phone":"+49 3605/509809",
    "sg:postcode":"37327",
    "sg:province":"Th\u00fcringen",
    "wof:name":"Interfunk Stratmann",
    "wof:placetype":"venue"
},
  "geometry": {"coordinates":[10.2423677444,51.3919754028],"type":"Point"}
}