{
  "type": "Feature",
  "properties": {
    "iso:country":"DE",
    "sg:address":"Schwedenstr. 17",
    "sg:city":"M\u00fcnchen",
    "sg:phone":"+49 89/36192939",
    "sg:postcode":"80805",
    "sg:province":"Bayern",
    "wof:name":"Dr. Annegret Wiese Rechtsanw\u00e4ltin",
    "wof:placetype":"venue"
},
  "geometry": {"coordinates":[11.6007833481,48.1660270691],"type":"Point"}
}