{
  "type": "Feature",
  "properties": {
    "iso:country":"DE",
    "sg:address":"Dorfstr. 1",
    "sg:city":"Seefeld",
    "sg:phone":"+49 8153/1071",
    "sg:postcode":"82229",
    "sg:province":"Bayern",
    "wof:name":"Gerald Schulz",
    "wof:placetype":"venue"
},
  "geometry": {"coordinates":[11.22561,48.051517],"type":"Point"}
}