{
  "type": "Feature",
  "properties": {
    "iso:country":"DE",
    "sg:address":"Sfaxer Str. 8",
    "sg:city":"Marburg",
    "sg:phone":"+49 6421/931851",
    "sg:postcode":"35037",
    "sg:province":"Hessen",
    "wof:name":"Loop Light",
    "wof:placetype":"venue"
},
  "geometry": {"coordinates":[8.774256,50.804977],"type":"Point"}
}