{
  "type": "Feature",
  "properties": {
    "iso:country":"DE",
    "sg:address":"Schulgasse 3",
    "sg:city":"Altensteig",
    "sg:phone":"+49 7453/8413",
    "sg:postcode":"72213",
    "sg:province":"Baden-W\u00fcrttemberg",
    "wof:name":"Manfred Kirn",
    "wof:placetype":"venue"
},
  "geometry": {"coordinates":[8.651212,48.574982],"type":"Point"}
}