{
  "type": "Feature",
  "properties": {
    "iso:country":"DE",
    "sg:address":"Neue Stuttgarter Str. 37",
    "sg:city":"Magstadt",
    "sg:phone":"+49 7159/41256",
    "sg:postcode":"71106",
    "sg:province":"Baden-W\u00fcrttemberg",
    "wof:name":"J\u00fcrgen Und Rainer Bebion",
    "wof:placetype":"venue"
},
  "geometry": {"coordinates":[8.963512,48.745289],"type":"Point"}
}