{
  "type": "Feature",
  "properties": {
    "iso:country":"DE",
    "sg:address":"Lange Str. 43",
    "sg:city":"Hann. M\u00fcnden",
    "sg:phone":"+49 5541/72021",
    "sg:postcode":"34346",
    "sg:province":"Niedersachsen",
    "wof:name":"G\u00fcnther Brehme Automatenbetrieb Gmbh",
    "wof:placetype":"venue"
},
  "geometry": {"coordinates":[9.6520013809,51.4171104431],"type":"Point"}
}