{
  "type": "Feature",
  "properties": {
    "iso:country":"DE",
    "sg:address":"Haardstr. 29",
    "sg:city":"N\u00fcdlingen",
    "sg:phone":"+49 971/66929",
    "sg:postcode":"97720",
    "sg:province":"Bayern",
    "wof:name":"Theodor Kiesel",
    "wof:placetype":"venue"
},
  "geometry": {"coordinates":[10.123454,50.223],"type":"Point"}
}