{
  "type": "Feature",
  "properties": {
    "iso:country":"DE",
    "sg:address":"Friedrich-H\u00e4ndel-Str. 22",
    "sg:city":"Worms",
    "sg:postcode":"67551",
    "sg:province":"Rheinland-Pfalz",
    "wof:name":"Wei\u00df Kg Produktentwicklung & Service",
    "wof:placetype":"venue"
},
  "geometry": {"coordinates":[8.284964,49.632206],"type":"Point"}
}