{
  "type": "Feature",
  "properties": {
    "iso:country":"DE",
    "sg:address":"Schulstr. 13",
    "sg:city":"Gudow",
    "sg:phone":"+49 4547/395",
    "sg:postcode":"23899",
    "sg:province":"Schleswig-Holstein",
    "wof:name":"U. Renk",
    "wof:placetype":"venue"
},
  "geometry": {"coordinates":[10.771835,53.558075],"type":"Point"}
}