{
  "type": "Feature",
  "properties": {
    "iso:country":"DE",
    "sg:address":"In der Lach 59",
    "sg:city":"Bad Homburg",
    "sg:phone":"+49 6172/41141",
    "sg:postcode":"61352",
    "sg:province":"Hessen",
    "wof:name":"D. P. Dreisbach Steuerberater",
    "wof:placetype":"venue"
},
  "geometry": {"coordinates":[8.6383190155,50.2171440125],"type":"Point"}
}