{
  "type": "Feature",
  "properties": {
    "iso:country":"DE",
    "sg:address":"Marktstr. 195",
    "sg:city":"Pfullingen",
    "sg:phone":"+49 7121/59282",
    "sg:postcode":"72793",
    "sg:province":"Baden-W\u00fcrttemberg",
    "wof:name":"W. M\u00fcllersch\u00f6n Sandstrahlarbeiten",
    "wof:placetype":"venue"
},
  "geometry": {"coordinates":[9.225154,48.483704],"type":"Point"}
}