{
  "type": "Feature",
  "properties": {
    "iso:country":"DE",
    "sg:address":"Kottenheimer Str. 5",
    "sg:city":"Ettringen",
    "sg:phone":"+49 2651/2819",
    "sg:postcode":"56729",
    "sg:province":"Rheinland-Pfalz",
    "wof:name":"W. Schlaf",
    "wof:placetype":"venue"
},
  "geometry": {"coordinates":[7.221407,50.360538],"type":"Point"}
}