{
  "type": "Feature",
  "properties": {
    "iso:country":"DE",
    "sg:address":"Am Gut Baarking 21::",
    "sg:city":"Bocholt",
    "sg:phone":"+49 4928/7121420",
    "sg:postcode":"46395",
    "sg:province":"Nordrhein-Westfalen",
    "wof:name":"Wm Holding Gmbh & Co / Wm Group",
    "wof:placetype":"venue"
},
  "geometry": {"coordinates":[6.57407,51.812],"type":"Point"}
}