{
  "type": "Feature",
  "properties": {
    "iso:country":"DE",
    "sg:address":"M\u00fchlberg 4",
    "sg:city":"Bad Soden-Salm\u00fcnster",
    "sg:phone":"+49 6056/900465",
    "sg:postcode":"63628",
    "sg:province":"Hessen",
    "wof:name":"Ludwig Potocnik",
    "wof:placetype":"venue"
},
  "geometry": {"coordinates":[9.368414,50.276245],"type":"Point"}
}