{
  "type": "Feature",
  "properties": {
    "iso:country":"DE",
    "sg:address":"H\u00f6henweg 2",
    "sg:city":"Leubsdorf",
    "sg:phone":"+49 37291/20860",
    "sg:postcode":"09573",
    "sg:province":"Sachsen",
    "wof:name":"Theo K\u00f6hler",
    "wof:placetype":"venue"
},
  "geometry": {"coordinates":[13.1325,50.784348],"type":"Point"}
}