{
  "type": "Feature",
  "properties": {
    "iso:country":"DE",
    "sg:address":"Feldstr. 6a",
    "sg:city":"Wolgast",
    "sg:phone":"+49 3836/202850",
    "sg:postcode":"17438",
    "sg:province":"Mecklenburg-Vorpommern",
    "wof:name":"Eva Streblow",
    "wof:placetype":"venue"
},
  "geometry": {"coordinates":[13.772901,54.051121],"type":"Point"}
}