{
  "type": "Feature",
  "properties": {
    "iso:country":"DE",
    "sg:address":"Am Ziegelbrand 1",
    "sg:city":"Menden",
    "sg:phone":"+49 2373/963493",
    "sg:postcode":"58706",
    "sg:province":"Nordrhein-Westfalen",
    "wof:name":"Kress Gmbh & Co. Kg Menden",
    "wof:placetype":"venue"
},
  "geometry": {"coordinates":[7.79205,51.433949],"type":"Point"}
}