{
  "type": "Feature",
  "properties": {
    "iso:country":"DE",
    "sg:address":"B\u00f6tzinger Str. 8",
    "sg:city":"Freiburg",
    "sg:phone":"+49 761/4005490",
    "sg:postcode":"79111",
    "sg:province":"Baden-W\u00fcrttemberg",
    "wof:name":"Maschinen Bader-ritter Gmbh & Co. Kg",
    "wof:placetype":"venue"
},
  "geometry": {"coordinates":[7.788533,47.993847],"type":"Point"}
}