{
  "type": "Feature",
  "properties": {
    "iso:country":"DE",
    "sg:address":"Karlsruher Str. 9",
    "sg:city":"Schwetzingen",
    "sg:phone":"+49 6202/25502",
    "sg:postcode":"68723",
    "sg:province":"Baden-W\u00fcrttemberg",
    "wof:name":"Athen",
    "wof:placetype":"venue"
},
  "geometry": {"coordinates":[8.5727500916,49.3834877014],"type":"Point"}
}