{
  "type": "Feature",
  "properties": {
    "iso:country":"DE",
    "sg:address":"97285",
    "sg:city":"R\u00f6ttingen",
    "sg:phone":"+49 9338/1788",
    "sg:postcode":"97285",
    "sg:province":"Bayern",
    "wof:name":"Vereinsgastst\u00e4tte Sportheim",
    "wof:placetype":"venue"
},
  "geometry": {"coordinates":[9.9692821503,49.5100898743],"type":"Point"}
}