{
  "type": "Feature",
  "properties": {
    "iso:country":"DE",
    "sg:address":"Luitgardstr. 14",
    "sg:city":"Pforzheim",
    "sg:phone":"+49 7231/33002",
    "sg:postcode":"75177",
    "sg:province":"Baden-W\u00fcrttemberg",
    "wof:name":"Thumm & Partner Gmbh",
    "wof:placetype":"venue"
},
  "geometry": {"coordinates":[8.697224617,48.8959236145],"type":"Point"}
}