{
  "type": "Feature",
  "properties": {
    "iso:country":"DE",
    "sg:address":"Am Fuchsbau 15a",
    "sg:city":"Neuseddin",
    "sg:phone":"+49 33205/59017",
    "sg:postcode":"14554",
    "sg:province":"Brandenburg",
    "wof:name":"Bautransport U Kranservice Neuseddin Gmbh",
    "wof:placetype":"venue"
},
  "geometry": {"coordinates":[13.0069847107,52.2863426208],"type":"Point"}
}