{
  "type": "Feature",
  "properties": {
    "iso:country":"DE",
    "sg:address":"Liebigstr. 257",
    "sg:city":"K\u00f6ln",
    "sg:phone":"+49 221/173391",
    "sg:postcode":"50739",
    "sg:province":"Nordrhein-Westfalen",
    "wof:name":"B. Cremer",
    "wof:placetype":"venue"
},
  "geometry": {"coordinates":[6.9406452179,50.9585227966],"type":"Point"}
}