{
  "type": "Feature",
  "properties": {
    "iso:country":"DE",
    "sg:address":"Kaiserstr. 66",
    "sg:city":"Lahr",
    "sg:phone":"+49 7821/30219",
    "sg:postcode":"77933",
    "sg:province":"Baden-W\u00fcrttemberg",
    "wof:name":"Michael Nestler",
    "wof:placetype":"venue"
},
  "geometry": {"coordinates":[7.8653421402,48.3411865234],"type":"Point"}
}