{
  "type": "Feature",
  "properties": {
    "iso:country":"DE",
    "sg:address":"Am Ochsenberg 1",
    "sg:city":"R\u00f6tgesb\u00fcttel",
    "sg:phone":"+49 5304",
    "sg:postcode":"38531",
    "sg:province":"Niedersachsen",
    "wof:name":"Firma Motelco",
    "wof:placetype":"venue"
},
  "geometry": {"coordinates":[10.53212,52.41634],"type":"Point"}
}