{
  "type": "Feature",
  "properties": {
    "iso:country":"DE",
    "sg:address":"Arndtstr. 12",
    "sg:city":"Worms",
    "sg:phone":"+49 6241/43540",
    "sg:postcode":"67547",
    "sg:province":"Rheinland-Pfalz",
    "wof:name":"W. Hehmann Inh. Udo Katz",
    "wof:placetype":"venue"
},
  "geometry": {"coordinates":[8.3632116318,49.637298584],"type":"Point"}
}