{
  "type": "Feature",
  "properties": {
    "iso:country":"DE",
    "sg:address":"Naumburger Str. 28",
    "sg:city":"Leipzig",
    "sg:phone":"+49 341/4417118",
    "sg:postcode":"04229",
    "sg:province":"Sachsen",
    "wof:name":"Manfred Enghardt",
    "wof:placetype":"venue"
},
  "geometry": {"coordinates":[12.329395,51.326828],"type":"Point"}
}