{
  "type": "Feature",
  "properties": {
    "iso:country":"DE",
    "sg:address":"Industriestr 8",
    "sg:city":"Hamminkeln",
    "sg:phone":"+49 2852/2951",
    "sg:postcode":"46499",
    "sg:province":"Nordrhein-Westfalen",
    "wof:name":"Intertrans Speditions-gmbh",
    "wof:placetype":"venue"
},
  "geometry": {"coordinates":[6.6057729721,51.7323303223],"type":"Point"}
}