{
  "type": "Feature",
  "properties": {
    "iso:country":"DE",
    "sg:address":"Prosperstr. 183 a",
    "sg:city":"Bottrop",
    "sg:phone":"+49 2041/61367",
    "sg:postcode":"46238",
    "sg:province":"Nordrhein-Westfalen",
    "wof:name":"H. Fischer",
    "wof:placetype":"venue"
},
  "geometry": {"coordinates":[6.947293,51.521111],"type":"Point"}
}