{
  "type": "Feature",
  "properties": {
    "iso:country":"DE",
    "sg:address":"Im Stockm\u00e4dle 4",
    "sg:city":"Karlsbad",
    "sg:phone":"+49 7248/924690",
    "sg:postcode":"76307",
    "sg:province":"Baden-W\u00fcrttemberg",
    "wof:name":"Michelbr\u00c4u Gmbh",
    "wof:placetype":"venue"
},
  "geometry": {"coordinates":[8.510787,48.875103],"type":"Point"}
}