{
  "type": "Feature",
  "properties": {
    "iso:country":"DE",
    "sg:address":"Zeilaeckerstr. 22a",
    "sg:city":"Weiden",
    "sg:postcode":"92637",
    "sg:province":"Bayern",
    "wof:name":"Oberpfaelzer-wirtschafts-forum",
    "wof:placetype":"venue"
},
  "geometry": {"coordinates":[12.102924,49.672535],"type":"Point"}
}