{
  "type": "Feature",
  "properties": {
    "iso:country":"DE",
    "sg:address":"Schubystr. 89a",
    "sg:city":"Schleswig",
    "sg:phone":"+49 4621/21664",
    "sg:postcode":"24837",
    "sg:province":"Schleswig-Holstein",
    "wof:name":"A & N B\u00fcrotechnik Gmbh",
    "wof:placetype":"venue"
},
  "geometry": {"coordinates":[9.551186,54.521999],"type":"Point"}
}