{
  "type": "Feature",
  "properties": {
    "iso:country":"DE",
    "sg:address":"Bitzenhofer Weg 6",
    "sg:city":"Dasing",
    "sg:phone":"+49 8205/1077",
    "sg:postcode":"86453",
    "sg:province":"Bayern",
    "wof:name":"Dr. Med. Hermann Lauter Arzt F\u00fcr Allgemeinmedizin",
    "wof:placetype":"venue"
},
  "geometry": {"coordinates":[11.0425653458,48.3862533569],"type":"Point"}
}