{
  "type": "Feature",
  "properties": {
    "iso:country":"DE",
    "sg:address":"Hellendorfer Str. 8",
    "sg:city":"Wedemark",
    "sg:phone":"+49 5130/4523",
    "sg:postcode":"30900",
    "sg:province":"Niedersachsen",
    "wof:name":"Fitness-studio Wedemark Inh. H. Wenzel",
    "wof:placetype":"venue"
},
  "geometry": {"coordinates":[9.7273769379,52.5627403259],"type":"Point"}
}