{
  "type": "Feature",
  "properties": {
    "iso:country":"DE",
    "sg:address":"Zum Imberg 10",
    "sg:city":"Neuenrade",
    "sg:phone":"+49 2394/8177",
    "sg:postcode":"58809",
    "sg:province":"Nordrhein-Westfalen",
    "wof:name":"A. M\u00fcller",
    "wof:placetype":"venue"
},
  "geometry": {"coordinates":[7.855713,51.271637],"type":"Point"}
}