{
  "type": "Feature",
  "properties": {
    "iso:country":"DE",
    "sg:address":"Lanzenweg 10",
    "sg:city":"Aldenhoven",
    "sg:phone":"+49 2464/7617",
    "sg:postcode":"52457",
    "sg:province":"Nordrhein-Westfalen",
    "wof:name":"Tiefbau - Unternehmung Gebr. Wohlrab Gmbh",
    "wof:placetype":"venue"
},
  "geometry": {"coordinates":[6.2186150551,50.8968505859],"type":"Point"}
}