{
  "type": "Feature",
  "properties": {
    "iso:country":"DE",
    "sg:address":"Rotdornstr 5",
    "sg:city":"Lichtenstein",
    "sg:phone":"+49 37204/76350",
    "sg:postcode":"09350",
    "sg:province":"Sachsen",
    "wof:name":"Werbung & Datentechnik Elke Junghanns",
    "wof:placetype":"venue"
},
  "geometry": {"coordinates":[12.63477,50.754108],"type":"Point"}
}