{
  "type": "Feature",
  "properties": {
    "iso:country":"DE",
    "sg:address":"Wagemannstr. 28",
    "sg:city":"Wiesbaden",
    "sg:postcode":"65183",
    "sg:province":"Hessen",
    "wof:name":"Kft Musik Und Wein Ohg",
    "wof:placetype":"venue"
},
  "geometry": {"coordinates":[8.2402095795,50.0836105347],"type":"Point"}
}