{
  "type": "Feature",
  "properties": {
    "iso:country":"DE",
    "sg:address":"Postfach 251501",
    "sg:city":"Leipzig",
    "sg:phone":"+49 4934/1686596",
    "sg:postcode":"04109",
    "sg:province":"Sachsen",
    "wof:name":"Venus & Phebus - Live -s/m - Fetisch-show",
    "wof:placetype":"venue"
},
  "geometry": {"coordinates":[12.36844,51.338112],"type":"Point"}
}