{
  "type": "Feature",
  "properties": {
    "iso:country":"DE",
    "sg:address":"Bremserstr. 124",
    "sg:city":"Ludwigshafen",
    "sg:phone":"+49 621/693826",
    "sg:postcode":"67063",
    "sg:province":"Rheinland-Pfalz",
    "wof:name":"Barbara Gnilka Krankengymnastin",
    "wof:placetype":"venue"
},
  "geometry": {"coordinates":[8.421376,49.489147],"type":"Point"}
}