{
  "type": "Feature",
  "properties": {
    "iso:country":"DE",
    "sg:address":"Marktstr. 1",
    "sg:city":"Neuwied",
    "sg:phone":"+49 2631/24611",
    "sg:postcode":"56564",
    "sg:province":"Rheinland-Pfalz",
    "wof:name":"Dr. Wolfgang Knuth Steuerberater",
    "wof:placetype":"venue"
},
  "geometry": {"coordinates":[7.4562149048,50.4266014099],"type":"Point"}
}