{
  "type": "Feature",
  "properties": {
    "iso:country":"DE",
    "sg:address":"Marienstr. 38",
    "sg:city":"F\u00fcrth",
    "sg:phone":"+49 911/774055",
    "sg:postcode":"90762",
    "sg:province":"Bayern",
    "wof:name":"Mehmet Yesil",
    "wof:placetype":"venue"
},
  "geometry": {"coordinates":[10.9839105606,49.474155426],"type":"Point"}
}