{
  "type": "Feature",
  "properties": {
    "iso:country":"DE",
    "sg:address":"Dorfstr. 8",
    "sg:city":"Vohenstrau\u00df",
    "sg:phone":"+49 9651/813",
    "sg:postcode":"92648",
    "sg:province":"Bayern",
    "wof:name":"Gasthof-pension Anzer",
    "wof:placetype":"venue"
},
  "geometry": {"coordinates":[12.317688942,49.606628418],"type":"Point"}
}