{
  "type": "Feature",
  "properties": {
    "iso:country":"DE",
    "sg:address":"Stahlgruberring 34",
    "sg:city":"M\u00fcnchen",
    "sg:phone":"+49 89/43650083",
    "sg:postcode":"81829",
    "sg:province":"Bayern",
    "wof:name":"Rudolf Kreitmaier Gmbh",
    "wof:placetype":"venue"
},
  "geometry": {"coordinates":[11.670173645,48.1337852478],"type":"Point"}
}