{
  "type": "Feature",
  "properties": {
    "iso:country":"DE",
    "sg:address":"Kiebitzweg 12",
    "sg:city":"Braunschweig",
    "sg:phone":"+49 5307/8100",
    "sg:postcode":"38110",
    "sg:province":"Niedersachsen",
    "wof:name":"C. Thiesen Immobilienmakler",
    "wof:placetype":"venue"
},
  "geometry": {"coordinates":[10.5642547607,52.3269081116],"type":"Point"}
}