{
  "type": "Feature",
  "properties": {
    "iso:country":"DE",
    "sg:address":"Ehrenfriedstr. 19",
    "sg:city":"Pulheim",
    "sg:postcode":"50259",
    "sg:province":"Nordrhein-Westfalen",
    "wof:name":"Behindertenwerkstatt",
    "wof:placetype":"venue"
},
  "geometry": {"coordinates":[6.782146,50.961353],"type":"Point"}
}