{
  "type": "Feature",
  "properties": {
    "iso:country":"DE",
    "sg:address":"Dorfstr. 31",
    "sg:city":"Lieth",
    "sg:phone":"+49 481/63408",
    "sg:postcode":"25770",
    "sg:province":"Schleswig-Holstein",
    "wof:name":"Alte Schule",
    "wof:placetype":"venue"
},
  "geometry": {"coordinates":[9.0609302521,54.1563453674],"type":"Point"}
}