{
  "type": "Feature",
  "properties": {
    "iso:country":"DE",
    "sg:address":"Holzm\u00fchlenstr. 59",
    "sg:city":"Hamburg",
    "sg:phone":"+49 40/6938913",
    "sg:postcode":"22041",
    "sg:province":"Hamburg",
    "wof:name":"Holzm\u00fchlen-apotheke Inh. Manfred Meyer-justus",
    "wof:placetype":"venue"
},
  "geometry": {"coordinates":[10.080339,53.582047],"type":"Point"}
}