{
  "type": "Feature",
  "properties": {
    "iso:country":"DE",
    "sg:address":"Leipziger Str. 120",
    "sg:city":"Chemnitz",
    "sg:phone":"+49 371/91790",
    "sg:postcode":"09114",
    "sg:province":"Sachsen",
    "wof:name":"Gwu Geld- Und Werttransport- Union Wienert & Morgenstern",
    "wof:placetype":"venue"
},
  "geometry": {"coordinates":[12.8896608353,50.8514251709],"type":"Point"}
}