{
  "type": "Feature",
  "properties": {
    "iso:country":"DE",
    "sg:address":"Neugasse 19",
    "sg:city":"Kehl",
    "sg:phone":"+49 7854/9090",
    "sg:postcode":"77694",
    "sg:province":"Baden-W\u00fcrttemberg",
    "wof:name":"Higel",
    "wof:placetype":"venue"
},
  "geometry": {"coordinates":[7.8217701912,48.5234146118],"type":"Point"}
}