{
  "type": "Feature",
  "properties": {
    "iso:country":"DE",
    "sg:address":"Tiroler Str. 49",
    "sg:city":"Frankfurt",
    "sg:phone":"+49 69/685021",
    "sg:postcode":"60596",
    "sg:province":"Hessen",
    "wof:name":"G.u.k. Scheffels Gmbh",
    "wof:placetype":"venue"
},
  "geometry": {"coordinates":[8.6767654419,50.0942993164],"type":"Point"}
}