{
  "type": "Feature",
  "properties": {
    "iso:country":"DE",
    "sg:address":"Breiter M\u00fchle 7",
    "sg:city":"Blieskastel",
    "sg:phone":"+49 6842/51167",
    "sg:postcode":"66440",
    "sg:province":"Saarland",
    "wof:name":"Schrift Und Design Schwab Gmbh",
    "wof:placetype":"venue"
},
  "geometry": {"coordinates":[7.228984,49.247974],"type":"Point"}
}