{
  "type": "Feature",
  "properties": {
    "iso:country":"DE",
    "sg:address":"Junkersstr 14",
    "sg:city":"Karlsruhe",
    "sg:phone":"+49 721/948620",
    "sg:postcode":"76139",
    "sg:province":"Baden-W\u00fcrttemberg",
    "wof:name":"Scheidt + Wormer Promotion Gmbh",
    "wof:placetype":"venue"
},
  "geometry": {"coordinates":[8.464711,49.023369],"type":"Point"}
}