{
  "type": "Feature",
  "properties": {
    "iso:country":"DE",
    "sg:address":"Klosterstrasse 2",
    "sg:city":"Kempen",
    "sg:postcode":"47906",
    "sg:province":"Nordrhein-Westfalen",
    "wof:name":"Skk Van De Rydt, Kempen",
    "wof:placetype":"venue"
},
  "geometry": {"coordinates":[6.417854,51.36578],"type":"Point"}
}