{
  "type": "Feature",
  "properties": {
    "iso:country":"DE",
    "sg:address":"Friedhofstr. 207",
    "sg:city":"Gro\u00df Schierstedt",
    "sg:phone":"+49 3473/3697",
    "sg:postcode":"06449",
    "sg:province":"Sachsen-Anhalt",
    "wof:name":"Sasse Und Junghans Gmbh",
    "wof:placetype":"venue"
},
  "geometry": {"coordinates":[11.521417,51.745476],"type":"Point"}
}