{
  "type": "Feature",
  "properties": {
    "iso:country":"DE",
    "sg:address":"Hambacher Tal 163b",
    "sg:city":"Heppenheim",
    "sg:postcode":"64646",
    "sg:province":"Hessen",
    "wof:name":"Containerdienst Holz Inh. Bernd Holz E. Kfm.",
    "wof:placetype":"venue"
},
  "geometry": {"coordinates":[8.651809,49.659271],"type":"Point"}
}