{
  "type": "Feature",
  "properties": {
    "iso:country":"DE",
    "sg:address":"Saalfelder Str. 18",
    "sg:city":"Gera",
    "sg:postcode":"07549",
    "sg:province":"Th\u00fcringen",
    "wof:name":"\u00c4rztehaus Saalfelder Stra\u00dfe Gmbh & Co. Kg",
    "wof:placetype":"venue"
},
  "geometry": {"coordinates":[12.0600261688,50.8465156555],"type":"Point"}
}