{
  "type": "Feature",
  "properties": {
    "iso:country":"DE",
    "sg:address":"Rott am Wald",
    "sg:city":"Eggenfelden",
    "sg:phone":"+49 8721/4214",
    "sg:postcode":"84307",
    "sg:province":"Bayern",
    "wof:name":"Christine Eckbauer-hohensinn",
    "wof:placetype":"venue"
},
  "geometry": {"coordinates":[12.7388048172,48.4025001526],"type":"Point"}
}