{
  "type": "Feature",
  "properties": {
    "iso:country":"DE",
    "sg:address":"Industriestr. 8",
    "sg:city":"Me\u00dfkirch",
    "sg:phone":"+49 7575/858",
    "sg:postcode":"88605",
    "sg:province":"Baden-W\u00fcrttemberg",
    "wof:name":"Fecht Omnibus Gmbh",
    "wof:placetype":"venue"
},
  "geometry": {"coordinates":[9.1234426498,47.9991722107],"type":"Point"}
}