{
  "type": "Feature",
  "properties": {
    "iso:country":"DE",
    "sg:address":"Liboristr. 8",
    "sg:city":"Paderborn",
    "sg:phone":"+49 5251/22512",
    "sg:postcode":"33098",
    "sg:province":"Nordrhein-Westfalen",
    "wof:name":"Auffenberg Rechtsanw\u00e4lte Und Notare",
    "wof:placetype":"venue"
},
  "geometry": {"coordinates":[8.7565727234,51.7157211304],"type":"Point"}
}