{
  "type": "Feature",
  "properties": {
    "iso:country":"DE",
    "sg:address":"Eichenring 9",
    "sg:city":"Germersheim",
    "sg:phone":"+49 7274/3670",
    "sg:postcode":"76726",
    "sg:province":"Rheinland-Pfalz",
    "wof:name":"Bolz & Eisold Bauunternehmung Gmbh",
    "wof:placetype":"venue"
},
  "geometry": {"coordinates":[8.354112,49.201115],"type":"Point"}
}