{
  "type": "Feature",
  "properties": {
    "iso:country":"DE",
    "sg:address":"Hauptstr. 10",
    "sg:city":"Leutenbach",
    "sg:phone":"+49 7195/66545",
    "sg:postcode":"71397",
    "sg:province":"Baden-W\u00fcrttemberg",
    "wof:name":"Lenz Gmbh",
    "wof:placetype":"venue"
},
  "geometry": {"coordinates":[9.392079,48.888176],"type":"Point"}
}