{
  "type": "Feature",
  "properties": {
    "iso:country":"DE",
    "sg:address":"Am Rupertsberg 16",
    "sg:city":"Bingen",
    "sg:phone":"+49 4967/219360",
    "sg:postcode":"55411",
    "sg:province":"Rheinland-Pfalz",
    "wof:name":"Corporate Express Gmbh & Co Vertriebskg",
    "wof:placetype":"venue"
},
  "geometry": {"coordinates":[7.8888859749,49.9659767151],"type":"Point"}
}