{
  "type": "Feature",
  "properties": {
    "iso:country":"DE",
    "sg:address":"Br\u00fcderstr. 4 -6",
    "sg:city":"Hagen",
    "sg:phone":"+49 2331/83577",
    "sg:postcode":"58097",
    "sg:province":"Nordrhein-Westfalen",
    "wof:name":"Corofa Handel Und Transport Gmbh",
    "wof:placetype":"venue"
},
  "geometry": {"coordinates":[7.4634218216,51.3711929321],"type":"Point"}
}