{
  "type": "Feature",
  "properties": {
    "iso:country":"DE",
    "sg:address":"Bismarckstr. 15",
    "sg:city":"Radolfzell",
    "sg:phone":"+49 7732/3055",
    "sg:postcode":"78315",
    "sg:province":"Baden-W\u00fcrttemberg",
    "wof:name":"E. Kern",
    "wof:placetype":"venue"
},
  "geometry": {"coordinates":[8.9668607712,47.7396202087],"type":"Point"}
}