{
  "type": "Feature",
  "properties": {
    "iso:country":"DE",
    "sg:address":"Deutschtaler Str. 113",
    "sg:city":"Berlin",
    "sg:phone":"+49 30/6631931",
    "sg:postcode":"12355",
    "sg:province":"Berlin",
    "wof:name":"Horst Bark",
    "wof:placetype":"venue"
},
  "geometry": {"coordinates":[13.5091924667,52.4086456299],"type":"Point"}
}