{
  "type": "Feature",
  "properties": {
    "iso:country":"DE",
    "sg:address":"Darmst\u00e4dter Str. 22",
    "sg:city":"Burgwald",
    "sg:phone":"+49 6457/205",
    "sg:postcode":"35099",
    "sg:province":"Hessen",
    "wof:name":"Heinrich D\u00f6nges Und Gisela Ernst",
    "wof:placetype":"venue"
},
  "geometry": {"coordinates":[8.7287569046,50.9872245789],"type":"Point"}
}