{
  "type": "Feature",
  "properties": {
    "iso:country":"DE",
    "sg:address":"Rehrstieg 148",
    "sg:city":"Hamburg",
    "sg:phone":"+49 40/7018879",
    "sg:postcode":"21147",
    "sg:province":"Hamburg",
    "wof:name":"Herbert Langeloh",
    "wof:placetype":"venue"
},
  "geometry": {"coordinates":[9.865037,53.48349],"type":"Point"}
}