{
  "type": "Feature",
  "properties": {
    "iso:country":"DE",
    "sg:address":"Antoniusstr. 18",
    "sg:city":"Langerwehe",
    "sg:phone":"+49 2423/3828",
    "sg:postcode":"52379",
    "sg:province":"Nordrhein-Westfalen",
    "wof:name":"Robert Kuck",
    "wof:placetype":"venue"
},
  "geometry": {"coordinates":[6.3964791298,50.7998771667],"type":"Point"}
}