{
  "type": "Feature",
  "properties": {
    "iso:country":"DE",
    "sg:address":"Wormser Str. 123",
    "sg:city":"Frankenthal",
    "sg:phone":"+49 6233/6040",
    "sg:postcode":"67227",
    "sg:province":"Rheinland-Pfalz",
    "wof:name":"Pfalzgas Gmbh",
    "wof:placetype":"venue"
},
  "geometry": {"coordinates":[8.352976,49.551117],"type":"Point"}
}