{
  "type": "Feature",
  "properties": {
    "iso:country":"DE",
    "sg:address":"In der K\u00fcrz 4",
    "sg:city":"Crailsheim",
    "sg:phone":"+49 7951/22544",
    "sg:postcode":"74564",
    "sg:province":"Baden-W\u00fcrttemberg",
    "wof:name":"H. Platzky Heiz\u00f6l- Und Kohlenhandlung",
    "wof:placetype":"venue"
},
  "geometry": {"coordinates":[10.0626001358,49.1371002197],"type":"Point"}
}