{
  "type": "Feature",
  "properties": {
    "iso:country":"DE",
    "sg:address":"Gerhart-Hauptmann-Str. 6",
    "sg:city":"Hameln",
    "sg:phone":"+49 5151/15044",
    "sg:postcode":"31787",
    "sg:province":"Niedersachsen",
    "wof:name":"Stock Bautr\u00e4ger Kg",
    "wof:placetype":"venue"
},
  "geometry": {"coordinates":[9.369809,52.118744],"type":"Point"}
}