{
  "type": "Feature",
  "properties": {
    "iso:country":"DE",
    "sg:address":"S\u00fcderholm 16",
    "sg:city":"Gelting",
    "sg:phone":"+49 4643/2218",
    "sg:postcode":"24395",
    "sg:province":"Schleswig-Holstein",
    "wof:name":"Landkrog Gelting",
    "wof:placetype":"venue"
},
  "geometry": {"coordinates":[9.8966636658,54.7442817688],"type":"Point"}
}