{
  "type": "Feature",
  "properties": {
    "iso:country":"DE",
    "sg:address":"Kapellenstr. 1",
    "sg:city":"Lauda-K\u00f6nigshofen",
    "sg:phone":"+49 9343/4420",
    "sg:postcode":"97922",
    "sg:province":"Baden-W\u00fcrttemberg",
    "wof:name":"Cafe Rialto",
    "wof:placetype":"venue"
},
  "geometry": {"coordinates":[9.702154,49.570389],"type":"Point"}
}