{
  "type": "Feature",
  "properties": {
    "iso:country":"DE",
    "sg:address":"Frankfurter Str.",
    "sg:city":"Brechen",
    "sg:phone":"+49 6483",
    "sg:postcode":"65611",
    "sg:province":"Hessen",
    "wof:name":"Schreinerei Und Fensterbau Rudloff Und Sohn",
    "wof:placetype":"venue"
},
  "geometry": {"coordinates":[8.198194,50.349037],"type":"Point"}
}