{
  "type": "Feature",
  "properties": {
    "iso:country":"DE",
    "sg:address":"Hauptstr. 42",
    "sg:city":"Medelby",
    "sg:phone":"+49 4605/336",
    "sg:postcode":"24994",
    "sg:province":"Schleswig-Holstein",
    "wof:name":"Abild Bauunternehmensges. Mbh",
    "wof:placetype":"venue"
},
  "geometry": {"coordinates":[9.1748933792,54.8120651245],"type":"Point"}
}