{
  "type": "Feature",
  "properties": {
    "iso:country":"DE",
    "sg:address":"Matthiasstr. 65",
    "sg:city":"Trier",
    "sg:phone":"+49 651/33600",
    "sg:postcode":"54290",
    "sg:province":"Rheinland-Pfalz",
    "wof:name":"Aktuell Immobilien",
    "wof:placetype":"venue"
},
  "geometry": {"coordinates":[6.6317658424,49.739490509],"type":"Point"}
}