{
  "type": "Feature",
  "properties": {
    "iso:country":"DE",
    "sg:address":"Pratzschwitzer Str. 45",
    "sg:city":"Pirna",
    "sg:postcode":"01796",
    "sg:province":"Sachsen",
    "wof:name":"Gardinen-glaser",
    "wof:placetype":"venue"
},
  "geometry": {"coordinates":[13.888601,50.975574],"type":"Point"}
}