{
  "type": "Feature",
  "properties": {
    "iso:country":"DE",
    "sg:address":"Von-Galen-Str. 2",
    "sg:city":"Heek",
    "sg:phone":"+49 2568/1296",
    "sg:postcode":"48619",
    "sg:province":"Nordrhein-Westfalen",
    "wof:name":"H. Nienhaus",
    "wof:placetype":"venue"
},
  "geometry": {"coordinates":[7.107644,52.11874],"type":"Point"}
}