{
  "type": "Feature",
  "properties": {
    "iso:country":"DE",
    "sg:address":"Jahnstr. 10",
    "sg:city":"Sersheim",
    "sg:phone":"+49 7042/32974",
    "sg:postcode":"74372",
    "sg:province":"Baden-W\u00fcrttemberg",
    "wof:name":"Rolf Mozer",
    "wof:placetype":"venue"
},
  "geometry": {"coordinates":[9.008596,48.960724],"type":"Point"}
}