{
  "type": "Feature",
  "properties": {
    "iso:country":"DE",
    "sg:address":"Badstr. 14",
    "sg:city":"Berlin",
    "sg:phone":"+49 30/4936702",
    "sg:postcode":"13357",
    "sg:province":"Berlin",
    "wof:name":"Peter Wellnitz Vorm. Dase",
    "wof:placetype":"venue"
},
  "geometry": {"coordinates":[13.3846788406,52.5509109497],"type":"Point"}
}