{
  "type": "Feature",
  "properties": {
    "iso:country":"DE",
    "sg:address":"Ritzweg 92",
    "sg:city":"S\u00fcdbrookmerland",
    "sg:phone":"+49 4941/8105",
    "sg:postcode":"26624",
    "sg:province":"Niedersachsen",
    "wof:name":"Foline Janssen",
    "wof:placetype":"venue"
},
  "geometry": {"coordinates":[7.3978610039,53.4736671448],"type":"Point"}
}