{
  "type": "Feature",
  "properties": {
    "iso:country":"DE",
    "sg:address":"Heidesheimer Str. 17",
    "sg:city":"Budenheim",
    "sg:phone":"+49 6139/405",
    "sg:postcode":"55257",
    "sg:province":"Rheinland-Pfalz",
    "wof:name":"Jakob Veit",
    "wof:placetype":"venue"
},
  "geometry": {"coordinates":[8.1515512466,50.0168762207],"type":"Point"}
}