{
  "type": "Feature",
  "properties": {
    "iso:country":"DE",
    "sg:address":"Bahnhofstr. 16",
    "sg:city":"Dinkelscherben",
    "sg:phone":"+49 8292/848",
    "sg:postcode":"86424",
    "sg:province":"Bayern",
    "wof:name":"Cafe Pension Rolf Kindler",
    "wof:placetype":"venue"
},
  "geometry": {"coordinates":[10.5887203217,48.3452987671],"type":"Point"}
}