{
  "type": "Feature",
  "properties": {
    "iso:country":"DE",
    "sg:address":"F\u00fcrstenberger Str. 4",
    "sg:city":"Lichtenau",
    "sg:phone":"+49 5292/517",
    "sg:postcode":"33165",
    "sg:province":"Nordrhein-Westfalen",
    "wof:name":"Xaver Piepenbrock",
    "wof:placetype":"venue"
},
  "geometry": {"coordinates":[8.827048,51.552494],"type":"Point"}
}