{
  "type": "Feature",
  "properties": {
    "iso:country":"DE",
    "sg:address":"Johann-Scholz-Str. 31",
    "sg:city":"Bad Berka",
    "sg:phone":"+49 36458/30314",
    "sg:postcode":"99438",
    "sg:province":"Th\u00fcringen",
    "wof:name":"M. Neubauer",
    "wof:placetype":"venue"
},
  "geometry": {"coordinates":[11.275732,50.902378],"type":"Point"}
}