{
  "type": "Feature",
  "properties": {
    "iso:country":"DE",
    "sg:address":"Hauptstr. 14",
    "sg:city":"Freudenberg",
    "sg:phone":"+49 9377/379",
    "sg:postcode":"97896",
    "sg:province":"Baden-W\u00fcrttemberg",
    "wof:name":"Hirschen",
    "wof:placetype":"venue"
},
  "geometry": {"coordinates":[9.3189954758,49.7394485474],"type":"Point"}
}