{
  "type": "Feature",
  "properties": {
    "iso:country":"DE",
    "sg:address":"Forststr. 19",
    "sg:city":"Kaisersbach",
    "sg:phone":"+49 7184/937370",
    "sg:postcode":"73667",
    "sg:province":"Baden-W\u00fcrttemberg",
    "wof:name":"Walter",
    "wof:placetype":"venue"
},
  "geometry": {"coordinates":[9.6391181946,48.9286384583],"type":"Point"}
}