{
  "type": "Feature",
  "properties": {
    "iso:country":"DE",
    "sg:address":"Am Kranen 12",
    "sg:city":"Bamberg",
    "sg:postcode":"96047",
    "sg:province":"Bayern",
    "wof:name":"Forschungsstelle F\u00fcr Die Geometrie Der Polarl\u00e4nder",
    "wof:placetype":"venue"
},
  "geometry": {"coordinates":[10.8868818283,49.8926467896],"type":"Point"}
}