{
  "type": "Feature",
  "properties": {
    "iso:country":"DE",
    "sg:address":"Sauerlacher Str. 7-9",
    "sg:city":"Wolfratshausen",
    "sg:phone":"+49 8171/2670",
    "sg:postcode":"82515",
    "sg:province":"Bayern",
    "wof:name":"Kreissparkasse, Wolfratshausen",
    "wof:placetype":"venue"
},
  "geometry": {"coordinates":[11.423507,47.91304],"type":"Point"}
}