{
  "type": "Feature",
  "properties": {
    "iso:country":"DE",
    "sg:address":"Reichsbahnstr. 30",
    "sg:city":"Hamburg",
    "sg:phone":"+49 40/5703714",
    "sg:postcode":"22525",
    "sg:province":"Hamburg",
    "wof:name":"Hellas",
    "wof:placetype":"venue"
},
  "geometry": {"coordinates":[9.9063901901,53.6021728516],"type":"Point"}
}