{
  "type": "Feature",
  "properties": {
    "iso:country":"DE",
    "sg:address":"Augustinerstr. 12",
    "sg:city":"W\u00fcrzburg",
    "sg:phone":"+49 931/50674",
    "sg:postcode":"97070",
    "sg:province":"Bayern",
    "wof:name":"Schweizerische Lebensver- Sicherungs- Und Rentenanstalt",
    "wof:placetype":"venue"
},
  "geometry": {"coordinates":[9.9285154343,49.791721344],"type":"Point"}
}