{
  "type": "Feature",
  "properties": {
    "iso:country":"DE",
    "sg:address":"Longericher Hauptstr. 78a",
    "sg:city":"K\u00f6ln",
    "sg:phone":"+49 221/5995474",
    "sg:postcode":"50739",
    "sg:province":"Nordrhein-Westfalen",
    "wof:name":"Staidex Electronics Gmbh",
    "wof:placetype":"venue"
},
  "geometry": {"coordinates":[6.9051861763,50.9967842102],"type":"Point"}
}