{
  "type": "Feature",
  "properties": {
    "iso:country":"DE",
    "sg:address":"Gro\u00dfe Freiheit 21",
    "sg:city":"Hamburg",
    "sg:phone":"+49 40/314150",
    "sg:postcode":"22767",
    "sg:province":"Hamburg",
    "wof:name":"Imbi\u00df Lienau",
    "wof:placetype":"venue"
},
  "geometry": {"coordinates":[9.9573726654,53.5506401062],"type":"Point"}
}