{
  "type": "Feature",
  "properties": {
    "iso:country":"DE",
    "sg:address":"Am Somborn 11 Hohenlimburg",
    "sg:city":"Hagen",
    "sg:phone":"+49 4923/349870",
    "sg:postcode":"58119",
    "sg:province":"Nordrhein-Westfalen",
    "wof:name":"Siegfried B\u00d6cker Gmbh & Co.",
    "wof:placetype":"venue"
},
  "geometry": {"coordinates":[7.5674548149,51.3608283997],"type":"Point"}
}