{
  "type": "Feature",
  "properties": {
    "iso:country":"DE",
    "sg:address":"Queichheimer Hauptstr. 175",
    "sg:city":"Landau",
    "sg:phone":"+49 6341/50084",
    "sg:postcode":"76829",
    "sg:province":"Rheinland-Pfalz",
    "wof:name":"Saturn-druck Sigrid Hurth",
    "wof:placetype":"venue"
},
  "geometry": {"coordinates":[8.148218,49.196304],"type":"Point"}
}