{
  "type": "Feature",
  "properties": {
    "iso:country":"DE",
    "sg:address":"Heinrich-Hertz-Str. 13",
    "sg:city":"Filderstadt",
    "sg:phone":"+49 711/776166",
    "sg:postcode":"70794",
    "sg:province":"Baden-W\u00fcrttemberg",
    "wof:name":"G. Clement",
    "wof:placetype":"venue"
},
  "geometry": {"coordinates":[9.202752,48.655827],"type":"Point"}
}