{
  "type": "Feature",
  "properties": {
    "iso:country":"DE",
    "sg:address":"Linprunstr. 27",
    "sg:city":"Viechtach",
    "sg:phone":"+49 9942/6792",
    "sg:postcode":"94234",
    "sg:province":"Bayern",
    "wof:name":"Bergbauer Licht Ambiente Gmbh",
    "wof:placetype":"venue"
},
  "geometry": {"coordinates":[12.88375,49.078041],"type":"Point"}
}