{
  "type": "Feature",
  "properties": {
    "iso:country":"DE",
    "sg:address":"Feldstr. 7",
    "sg:city":"Willich",
    "sg:phone":"+49 2154/2612",
    "sg:postcode":"47877",
    "sg:province":"Nordrhein-Westfalen",
    "wof:name":"Lions-club Willich Hans-dieter Poppe",
    "wof:placetype":"venue"
},
  "geometry": {"coordinates":[6.5543808937,51.2652511597],"type":"Point"}
}