{
  "type": "Feature",
  "properties": {
    "iso:country":"DE",
    "sg:address":"Hochstr. 23",
    "sg:city":"Friedrichshafen",
    "sg:phone":"+49 7541/22349",
    "sg:postcode":"88045",
    "sg:province":"Baden-W\u00fcrttemberg",
    "wof:name":"G. Ziegler Bildhauer",
    "wof:placetype":"venue"
},
  "geometry": {"coordinates":[9.464543,47.656887],"type":"Point"}
}