{
  "type": "Feature",
  "properties": {
    "iso:country":"DE",
    "sg:address":"Am Hummelb\u00fchl 5",
    "sg:city":"Alpirsbach",
    "sg:phone":"+49 7444/2420",
    "sg:postcode":"72275",
    "sg:province":"Baden-W\u00fcrttemberg",
    "wof:name":"Klaus S\u00fcsser",
    "wof:placetype":"venue"
},
  "geometry": {"coordinates":[8.39455,48.339172],"type":"Point"}
}