{
  "type": "Feature",
  "properties": {
    "iso:country":"DE",
    "sg:address":"Enckestr. 5",
    "sg:city":"Hannover",
    "sg:phone":"+49 511/832602",
    "sg:postcode":"30519",
    "sg:province":"Niedersachsen",
    "wof:name":"Fernsehdienst In D\u00f6hren",
    "wof:placetype":"venue"
},
  "geometry": {"coordinates":[9.7758178711,52.3400115967],"type":"Point"}
}