{
  "type": "Feature",
  "properties": {
    "iso:country":"DE",
    "sg:address":"Fritz-Reuter-Weg 16",
    "sg:city":"Tornesch",
    "sg:phone":"+49 4122/54008",
    "sg:postcode":"25436",
    "sg:province":"Schleswig-Holstein",
    "wof:name":"Glismann Hausbau Gmbh",
    "wof:placetype":"venue"
},
  "geometry": {"coordinates":[9.717076,53.705605],"type":"Point"}
}