{
  "type": "Feature",
  "properties": {
    "iso:country":"DE",
    "sg:address":"Gro\u00dfenhainer Str. 19",
    "sg:city":"Dresden",
    "sg:postcode":"01097",
    "sg:province":"Sachsen",
    "wof:name":"B. Knauthe",
    "wof:placetype":"venue"
},
  "geometry": {"coordinates":[13.7364444733,51.0716438293],"type":"Point"}
}