{
  "type": "Feature",
  "properties": {
    "iso:country":"DE",
    "sg:address":"Lindich",
    "sg:city":"\u00d6hringen",
    "sg:phone":"+49 7948/832",
    "sg:postcode":"74613",
    "sg:province":"Baden-W\u00fcrttemberg",
    "wof:name":"Elfe Gebert",
    "wof:placetype":"venue"
},
  "geometry": {"coordinates":[9.4542198181,49.2268600464],"type":"Point"}
}