{
  "type": "Feature",
  "properties": {
    "iso:country":"DE",
    "sg:address":"Rathausplatz",
    "sg:city":"Schierling",
    "sg:phone":"+49 9451/1332",
    "sg:postcode":"84069",
    "sg:province":"Bayern",
    "wof:name":"B. Lederer Und I. Amann",
    "wof:placetype":"venue"
},
  "geometry": {"coordinates":[12.1382303238,48.8376998901],"type":"Point"}
}