{
  "type": "Feature",
  "properties": {
    "iso:country":"DE",
    "sg:address":"Paringer Str. 8",
    "sg:city":"Bad Abbach",
    "sg:phone":"+49 9453/71985",
    "sg:postcode":"93077",
    "sg:province":"Bayern",
    "wof:name":"Martin Mittermeier",
    "wof:placetype":"venue"
},
  "geometry": {"coordinates":[12.1100435257,48.8836784363],"type":"Point"}
}