{
  "type": "Feature",
  "properties": {
    "iso:country":"DE",
    "sg:address":"Untere Langgasse 10",
    "sg:city":"Speyer",
    "sg:phone":"+49 6232/70207",
    "sg:postcode":"67346",
    "sg:province":"Rheinland-Pfalz",
    "wof:name":"Pierrot",
    "wof:placetype":"venue"
},
  "geometry": {"coordinates":[8.4294300079,49.3185691833],"type":"Point"}
}