{
  "type": "Feature",
  "properties": {
    "iso:country":"DE",
    "sg:address":"Grolmanstr. 35",
    "sg:city":"Berlin",
    "sg:phone":"+49 4926/037990",
    "sg:postcode":"10623",
    "sg:province":"Berlin",
    "wof:name":"Heckers Kurhotel",
    "wof:placetype":"venue"
},
  "geometry": {"coordinates":[7.72877,50.330418],"type":"Point"}
}