{
  "type": "Feature",
  "properties": {
    "iso:country":"DE",
    "sg:address":"Robert-Lindig-Platz 7",
    "sg:city":"Mitterteich",
    "sg:phone":"+49 9633/1263",
    "sg:postcode":"95666",
    "sg:province":"Bayern",
    "wof:name":"Kurt Teske Steuerbevollm\u00e4chtigter",
    "wof:placetype":"venue"
},
  "geometry": {"coordinates":[12.2428092957,49.9451713562],"type":"Point"}
}