{
  "type": "Feature",
  "properties": {
    "iso:country":"DE",
    "sg:address":"In der Gartel 9",
    "sg:city":"Rodenbach",
    "sg:phone":"+49 6184/54874",
    "sg:postcode":"63517",
    "sg:province":"Hessen",
    "wof:name":"Brasserie",
    "wof:placetype":"venue"
},
  "geometry": {"coordinates":[9.0230569839,50.1420516968],"type":"Point"}
}