{
  "type": "Feature",
  "properties": {
    "iso:country":"DE",
    "sg:address":"R\u00fcmannstr. 39/5",
    "sg:city":"M\u00fcnchen",
    "sg:phone":"+49 89/3009455",
    "sg:postcode":"80804",
    "sg:province":"Bayern",
    "wof:name":"Dr. Peter Plank Tierarzt",
    "wof:placetype":"venue"
},
  "geometry": {"coordinates":[11.5778589249,48.176071167],"type":"Point"}
}