{
  "type": "Feature",
  "properties": {
    "iso:country":"DE",
    "sg:address":"Staffelweg 12",
    "sg:city":"Bad \u00dcberkingen",
    "sg:phone":"+49 7334/21848",
    "sg:postcode":"73337",
    "sg:province":"Baden-W\u00fcrttemberg",
    "wof:name":"Karte 24 Gmbh",
    "wof:placetype":"venue"
},
  "geometry": {"coordinates":[9.7655096054,48.6090202332],"type":"Point"}
}