{
  "type": "Feature",
  "properties": {
    "iso:country":"DE",
    "sg:address":"Langestr. 29",
    "sg:city":"B\u00fctzow",
    "sg:phone":"+49 38461/3184",
    "sg:postcode":"18246",
    "sg:province":"Mecklenburg-Vorpommern",
    "wof:name":"M. Meyer",
    "wof:placetype":"venue"
},
  "geometry": {"coordinates":[11.9835214615,53.8477783203],"type":"Point"}
}