{
  "type": "Feature",
  "properties": {
    "iso:country":"DE",
    "sg:address":"Hintergasse",
    "sg:city":"Rohrbach",
    "sg:phone":"+49 6349/8211",
    "sg:postcode":"76865",
    "sg:province":"Rheinland-Pfalz",
    "wof:name":"Framin Mineral\u00f6l Gmbh & Co.",
    "wof:placetype":"venue"
},
  "geometry": {"coordinates":[8.1279859543,49.1383323669],"type":"Point"}
}