{
  "type": "Feature",
  "properties": {
    "iso:country":"DE",
    "sg:address":"Eichendorffstr. 12",
    "sg:city":"Bamberg",
    "sg:phone":"+49 951/31167",
    "sg:postcode":"96050",
    "sg:province":"Bayern",
    "wof:name":"Ewald Mark",
    "wof:placetype":"venue"
},
  "geometry": {"coordinates":[10.924872,49.903137],"type":"Point"}
}