{
  "type": "Feature",
  "properties": {
    "iso:country":"DE",
    "sg:address":"Goldscheuerstr. 37",
    "sg:city":"Kehl",
    "sg:phone":"+49 7851/77712",
    "sg:postcode":"77694",
    "sg:province":"Baden-W\u00fcrttemberg",
    "wof:name":"W\u00f6hrle Gmbh",
    "wof:placetype":"venue"
},
  "geometry": {"coordinates":[7.8152961731,48.5680770874],"type":"Point"}
}