{
  "type": "Feature",
  "properties": {
    "iso:country":"DE",
    "sg:address":"Bessenbacher Weg 54",
    "sg:city":"Aschaffenburg",
    "sg:phone":"+49 6021/91167",
    "sg:postcode":"63739",
    "sg:province":"Bayern",
    "wof:name":"Heiner Osthus Ingenieur",
    "wof:placetype":"venue"
},
  "geometry": {"coordinates":[9.1669969559,49.9710998535],"type":"Point"}
}