{
  "type": "Feature",
  "properties": {
    "iso:country":"DE",
    "sg:address":"Grevener Str. 13",
    "sg:city":"Bielefeld",
    "sg:phone":"+49 521/100552",
    "sg:postcode":"33619",
    "sg:province":"Nordrhein-Westfalen",
    "wof:name":"Hartwig Schmidbauer",
    "wof:placetype":"venue"
},
  "geometry": {"coordinates":[8.4549093246,52.0452690125],"type":"Point"}
}