{
  "type": "Feature",
  "properties": {
    "iso:country":"DE",
    "sg:address":"Linkentalstr. 34",
    "sg:city":"Neckarsulm",
    "sg:phone":"+49 7132/2468",
    "sg:postcode":"74172",
    "sg:province":"Baden-W\u00fcrttemberg",
    "wof:name":"Eugen Denz Architekt",
    "wof:placetype":"venue"
},
  "geometry": {"coordinates":[9.233606,49.188019],"type":"Point"}
}