{
  "type": "Feature",
  "properties": {
    "iso:country":"DE",
    "sg:address":"Ichenheim G\u00e4nsgie\u00dfen",
    "sg:city":"Neuried",
    "sg:phone":"+49 7807/3303",
    "sg:postcode":"77743",
    "sg:province":"Baden-W\u00fcrttemberg",
    "wof:name":"Anglerheim G\u00e4nsgie\u00dfen",
    "wof:placetype":"venue"
},
  "geometry": {"coordinates":[7.8139338493,48.4650535583],"type":"Point"}
}