{
  "type": "Feature",
  "properties": {
    "iso:country":"DE",
    "sg:address":"Arndtstr. 5",
    "sg:city":"Bernkastel-Kues",
    "sg:phone":"+49 6531/3283",
    "sg:postcode":"54470",
    "sg:province":"Rheinland-Pfalz",
    "wof:name":"Nando Franchi Komponist",
    "wof:placetype":"venue"
},
  "geometry": {"coordinates":[7.0681471825,49.9174041748],"type":"Point"}
}