{
  "type": "Feature",
  "properties": {
    "iso:country":"DE",
    "sg:address":"Bitburger Str. 6",
    "sg:city":"Krautscheid",
    "sg:phone":"+49 6554/469",
    "sg:postcode":"54673",
    "sg:province":"Rheinland-Pfalz",
    "wof:name":"Helmut Bretz",
    "wof:placetype":"venue"
},
  "geometry": {"coordinates":[6.3327889442,50.0638237],"type":"Point"}
}