{
  "type": "Feature",
  "properties": {
    "iso:country":"DE",
    "sg:address":"Im Stieg 1",
    "sg:city":"Au",
    "sg:phone":"+49 761/407323",
    "sg:postcode":"79280",
    "sg:province":"Baden-W\u00fcrttemberg",
    "wof:name":"Eugen Und Angelika Wissler",
    "wof:placetype":"venue"
},
  "geometry": {"coordinates":[7.8312010765,47.9560127258],"type":"Point"}
}