{
  "type": "Feature",
  "properties": {
    "iso:country":"DE",
    "sg:address":"Rosengasse 342",
    "sg:city":"Landshut",
    "sg:phone":"+49 871/89611",
    "sg:postcode":"84028",
    "sg:province":"Bayern",
    "wof:name":"Volksb\u00fccherei Des St. Michaelsbundes E. V.",
    "wof:placetype":"venue"
},
  "geometry": {"coordinates":[12.153066,48.536728],"type":"Point"}
}