{
  "type": "Feature",
  "properties": {
    "iso:country":"DE",
    "sg:address":"Hilligenwarf 4",
    "sg:city":"Lilienthal",
    "sg:phone":"+49 4298/3232",
    "sg:postcode":"28865",
    "sg:province":"Niedersachsen",
    "wof:name":"R.meyerdierks Fernmelde- Montage U.kabelverlegung",
    "wof:placetype":"venue"
},
  "geometry": {"coordinates":[8.922242,53.162647],"type":"Point"}
}