{
  "type": "Feature",
  "properties": {
    "iso:country":"DE",
    "sg:address":"Traunfeld",
    "sg:city":"Lauterhofen",
    "sg:phone":"+49 9189/1097",
    "sg:postcode":"92283",
    "sg:province":"Bayern",
    "wof:name":"F. Endres",
    "wof:placetype":"venue"
},
  "geometry": {"coordinates":[11.47904,49.41214],"type":"Point"}
}