{
  "type": "Feature",
  "properties": {
    "iso:country":"DE",
    "sg:address":"Alte N\u00fcrnberger Str. 19-21",
    "sg:city":"Regensburg",
    "sg:postcode":"93059",
    "sg:province":"Bayern",
    "wof:name":"Sieber Gmbh",
    "wof:placetype":"venue"
},
  "geometry": {"coordinates":[12.0942182541,49.0291748047],"type":"Point"}
}