{
  "type": "Feature",
  "properties": {
    "iso:country":"DE",
    "sg:address":"Lehnsgrund 59",
    "sg:city":"Essen",
    "sg:phone":"+49 201/713885",
    "sg:postcode":"45149",
    "sg:province":"Nordrhein-Westfalen",
    "wof:name":"R.-e. Kubacki Steuerberater",
    "wof:placetype":"venue"
},
  "geometry": {"coordinates":[6.9737710953,51.4273757935],"type":"Point"}
}