{
  "type": "Feature",
  "properties": {
    "iso:country":"DE",
    "sg:address":"Karl-Lange-Str. 53",
    "sg:city":"Bochum",
    "sg:phone":"+49 234/313152",
    "sg:postcode":"44791",
    "sg:province":"Nordrhein-Westfalen",
    "wof:name":"Erich G\u00e4rtner",
    "wof:placetype":"venue"
},
  "geometry": {"coordinates":[7.2438211441,51.4856719971],"type":"Point"}
}