{
  "type": "Feature",
  "properties": {
    "iso:country":"DE",
    "sg:address":"Redinger Str. 5",
    "sg:city":"Neuhaus",
    "sg:phone":"+49 8503/8185",
    "sg:postcode":"94152",
    "sg:province":"Bayern",
    "wof:name":"Agrom\u00e9 Gmbh",
    "wof:placetype":"venue"
},
  "geometry": {"coordinates":[13.399148,48.427982],"type":"Point"}
}