{
  "type": "Feature",
  "properties": {
    "iso:country":"DE",
    "sg:address":"Lindenstr. 2",
    "sg:city":"Gingen",
    "sg:phone":"+49 7162/43141",
    "sg:postcode":"73333",
    "sg:province":"Baden-W\u00fcrttemberg",
    "wof:name":"Peter Seybold B\u00e4ckerei",
    "wof:placetype":"venue"
},
  "geometry": {"coordinates":[9.78178,48.657845],"type":"Point"}
}