{
  "type": "Feature",
  "properties": {
    "iso:country":"DE",
    "sg:address":"Freiherr-Von-Aretin-Platz 1",
    "sg:city":"Aldersbach",
    "sg:phone":"+49 8543/96040",
    "sg:postcode":"94501",
    "sg:province":"Bayern",
    "wof:name":"Brauerei Aldersbach Freiherr V. Aretin Kg",
    "wof:placetype":"venue"
},
  "geometry": {"coordinates":[13.086428,48.587364],"type":"Point"}
}