{
  "type": "Feature",
  "properties": {
    "iso:country":"DE",
    "sg:address":"Hauptstr. 10",
    "sg:city":"Nittenau",
    "sg:phone":"+49 9436/94170",
    "sg:postcode":"93149",
    "sg:province":"Bayern",
    "wof:name":"Winkelmass Planungsb\u00fcro Gmbh",
    "wof:placetype":"venue"
},
  "geometry": {"coordinates":[12.272333,49.197716],"type":"Point"}
}