{
  "type": "Feature",
  "properties": {
    "iso:country":"DE",
    "sg:address":"Berliner Ring 9/1",
    "sg:city":"Tuttlingen",
    "sg:phone":"+49 7461/2431",
    "sg:postcode":"78532",
    "sg:province":"Baden-W\u00fcrttemberg",
    "wof:name":"Ing. Helmut Schliemann Ingenieur",
    "wof:placetype":"venue"
},
  "geometry": {"coordinates":[8.8150377274,47.9928512573],"type":"Point"}
}