{
  "type": "Feature",
  "properties": {
    "iso:country":"DE",
    "sg:address":"Rosenthal 3",
    "sg:city":"Plettenberg",
    "sg:phone":"+49 2391/10535",
    "sg:postcode":"58840",
    "sg:province":"Nordrhein-Westfalen",
    "wof:name":"Robert Schulte Gmbh & Co. Kg",
    "wof:placetype":"venue"
},
  "geometry": {"coordinates":[7.8425498009,51.1999206543],"type":"Point"}
}