{
  "type": "Feature",
  "properties": {
    "iso:country":"DE",
    "sg:address":"Alleestr. 14",
    "sg:city":"Fr\u00f6ndenberg",
    "sg:phone":"+49 2373/71503",
    "sg:postcode":"58730",
    "sg:province":"Nordrhein-Westfalen",
    "wof:name":"Pizzeria Pronto Salvatore",
    "wof:placetype":"venue"
},
  "geometry": {"coordinates":[7.7701301575,51.4734077454],"type":"Point"}
}