{
  "type": "Feature",
  "properties": {
    "iso:country":"DE",
    "sg:address":"Sudermannstr. 1",
    "sg:city":"Augsburg",
    "sg:phone":"+49 821/811244",
    "sg:postcode":"86179",
    "sg:province":"Bayern",
    "wof:name":"R. Haas Architekt",
    "wof:placetype":"venue"
},
  "geometry": {"coordinates":[10.907095,48.306808],"type":"Point"}
}