{
  "type": "Feature",
  "properties": {
    "iso:country":"DE",
    "sg:address":"Christianstr. 44",
    "sg:city":"Neum\u00fcnster",
    "sg:phone":"+49 4321/42256",
    "sg:postcode":"24534",
    "sg:province":"Schleswig-Holstein",
    "wof:name":"Hans-joachim Vauk",
    "wof:placetype":"venue"
},
  "geometry": {"coordinates":[9.9879026413,54.0777359009],"type":"Point"}
}