{
  "type": "Feature",
  "properties": {
    "iso:country":"DE",
    "sg:address":"Birkenauer Talstr. 55",
    "sg:city":"Weinheim",
    "sg:phone":"+49 6201/13885",
    "sg:postcode":"69469",
    "sg:province":"Baden-W\u00fcrttemberg",
    "wof:name":"Fritz Stamm",
    "wof:placetype":"venue"
},
  "geometry": {"coordinates":[8.6766862869,49.554069519],"type":"Point"}
}