{
  "type": "Feature",
  "properties": {
    "iso:country":"DE",
    "sg:address":"Im Zauberwald",
    "sg:city":"Ramsau",
    "sg:phone":"+49 8657/235",
    "sg:postcode":"83486",
    "sg:province":"Bayern",
    "wof:name":"Pension Josef Datzmann",
    "wof:placetype":"venue"
},
  "geometry": {"coordinates":[12.8734817505,47.6096725464],"type":"Point"}
}