{
  "type": "Feature",
  "properties": {
    "iso:country":"DE",
    "sg:address":"Eichendorffweg 8",
    "sg:city":"Greven",
    "sg:phone":"+49 2575/98757",
    "sg:postcode":"48268",
    "sg:province":"Nordrhein-Westfalen",
    "wof:name":"Iap Eckstein Gmbh",
    "wof:placetype":"venue"
},
  "geometry": {"coordinates":[7.547497,52.133923],"type":"Point"}
}