{
  "type": "Feature",
  "properties": {
    "iso:country":"DE",
    "sg:address":"Konrad-Adenauer-Str. 113",
    "sg:city":"Salzgitter",
    "sg:phone":"+49 5341/43336",
    "sg:postcode":"38226",
    "sg:province":"Niedersachsen",
    "wof:name":"Europcar Autovermietung Gmbh",
    "wof:placetype":"venue"
},
  "geometry": {"coordinates":[10.346931,52.153049],"type":"Point"}
}