{
  "type": "Feature",
  "properties": {
    "iso:country":"DE",
    "sg:address":"Theodor-Naarmann-Str. 7",
    "sg:city":"Oelde",
    "sg:phone":"+49 2522/2134",
    "sg:postcode":"59302",
    "sg:province":"Nordrhein-Westfalen",
    "wof:name":"Wilhelm Sch\u00fcrhoff",
    "wof:placetype":"venue"
},
  "geometry": {"coordinates":[8.1386604309,51.8207397461],"type":"Point"}
}