{
  "type": "Feature",
  "properties": {
    "iso:country":"DE",
    "sg:address":"Schirmerstr. 76",
    "sg:city":"D\u00fcsseldorf",
    "sg:phone":"+49 211/684975",
    "sg:postcode":"40211",
    "sg:province":"Nordrhein-Westfalen",
    "wof:name":"Nachla\u00df Wilhelm Krings Grund- St\u00fcckverwaltungsges. Mbh",
    "wof:placetype":"venue"
},
  "geometry": {"coordinates":[6.7961978912,51.2303161621],"type":"Point"}
}