{
  "type": "Feature",
  "properties": {
    "iso:country":"DE",
    "sg:address":"Nordholter Weg 2",
    "sg:city":"Drensteinfurt",
    "sg:phone":"+49 2387/470",
    "sg:postcode":"48317",
    "sg:province":"Nordrhein-Westfalen",
    "wof:name":"A. Eckmann",
    "wof:placetype":"venue"
},
  "geometry": {"coordinates":[7.7959971428,51.7621269226],"type":"Point"}
}