{
  "type": "Feature",
  "properties": {
    "iso:country":"DE",
    "sg:address":"Erlanger Str. 2",
    "sg:city":"Uttenreuth",
    "sg:phone":"+49 9131/5067580",
    "sg:postcode":"91080",
    "sg:province":"Bayern",
    "wof:name":"B\u00f6hmer Und Meinke Rechtsanw\u00e4lte",
    "wof:placetype":"venue"
},
  "geometry": {"coordinates":[11.0720682144,49.5968818665],"type":"Point"}
}