{
  "type": "Feature",
  "properties": {
    "iso:country":"DE",
    "sg:address":"G\u00f6ppinger Str. 8",
    "sg:city":"Schlat",
    "sg:phone":"+49 7161/818557",
    "sg:postcode":"73114",
    "sg:province":"Baden-W\u00fcrttemberg",
    "wof:name":"R. Und S. Weinhardt",
    "wof:placetype":"venue"
},
  "geometry": {"coordinates":[9.7064123154,48.6562843323],"type":"Point"}
}