{
  "type": "Feature",
  "properties": {
    "iso:country":"DE",
    "sg:address":"Rudolf-Breitscheid-Str. 5",
    "sg:city":"Wernigerode",
    "sg:phone":"+49 3943/501283",
    "sg:postcode":"38855",
    "sg:province":"Sachsen-Anhalt",
    "wof:name":"Andreas Klewe Rechtsanwalt",
    "wof:placetype":"venue"
},
  "geometry": {"coordinates":[10.7913007736,51.8389320374],"type":"Point"}
}