{
  "type": "Feature",
  "properties": {
    "iso:country":"DE",
    "sg:address":"Strobelallee 75",
    "sg:city":"Pirmasens",
    "sg:phone":"+49 6331/73993",
    "sg:postcode":"66953",
    "sg:province":"Rheinland-Pfalz",
    "wof:name":"Fritz Becker Ingenieur",
    "wof:placetype":"venue"
},
  "geometry": {"coordinates":[7.6185750961,49.1989631653],"type":"Point"}
}