{
  "type": "Feature",
  "properties": {
    "iso:country":"DE",
    "sg:address":"Auf der Leer 46",
    "sg:city":"Dieburg",
    "sg:phone":"+49 6071/820737",
    "sg:postcode":"64807",
    "sg:province":"Hessen",
    "wof:name":"M. Mattern Rechtsanw\u00e4ltin",
    "wof:placetype":"venue"
},
  "geometry": {"coordinates":[8.8340711594,49.9024047852],"type":"Point"}
}