{
  "type": "Feature",
  "properties": {
    "iso:country":"DE",
    "sg:address":"Schiltachstr. 34",
    "sg:city":"Schramberg",
    "sg:phone":"+49 7422/922220",
    "sg:postcode":"78713",
    "sg:province":"Baden-W\u00fcrttemberg",
    "wof:name":"Karl Haas",
    "wof:placetype":"venue"
},
  "geometry": {"coordinates":[8.3826026917,48.2297706604],"type":"Point"}
}