{
  "type": "Feature",
  "properties": {
    "iso:country":"DE",
    "sg:address":"Industriestr. 2",
    "sg:city":"Altendorf",
    "sg:postcode":"96146",
    "sg:province":"Bayern",
    "wof:name":"Lk Klebeband Systeme Verwaltungs Gmbh",
    "wof:placetype":"venue"
},
  "geometry": {"coordinates":[11.01514,49.796207],"type":"Point"}
}