{
  "type": "Feature",
  "properties": {
    "iso:country":"DE",
    "sg:address":"Breite Str. 61",
    "sg:city":"Witten",
    "sg:phone":"+49 2302/56468",
    "sg:postcode":"58452",
    "sg:province":"Nordrhein-Westfalen",
    "wof:name":"H. B\u00f6rger",
    "wof:placetype":"venue"
},
  "geometry": {"coordinates":[7.330743,51.442055],"type":"Point"}
}