{
  "type": "Feature",
  "properties": {
    "iso:country":"DE",
    "sg:address":"Steinbeisweg 9",
    "sg:city":"Winnenden",
    "sg:phone":"+49 7195/3269",
    "sg:postcode":"71364",
    "sg:province":"Baden-W\u00fcrttemberg",
    "wof:name":"Winnender Backwaren H\u00fcttinger & J\u00e4ger Jun.",
    "wof:placetype":"venue"
},
  "geometry": {"coordinates":[9.391281,48.876041],"type":"Point"}
}