{
  "type": "Feature",
  "properties": {
    "iso:country":"DE",
    "sg:address":"Wanger Str. 4",
    "sg:city":"Nu\u00dfdorf",
    "sg:phone":"+49 8669/6816",
    "sg:postcode":"83365",
    "sg:province":"Bayern",
    "wof:name":"Kath. Pfarramt St. Laurentius",
    "wof:placetype":"venue"
},
  "geometry": {"coordinates":[12.5975694656,47.9050483704],"type":"Point"}
}