{
  "type": "Feature",
  "properties": {
    "iso:country":"DE",
    "sg:address":"Contrescarpe 121",
    "sg:city":"Bremen",
    "sg:postcode":"28195",
    "sg:province":"Bremen",
    "wof:name":"Ani-avati Verein F\u00fcr Suchtherapie E. V.",
    "wof:placetype":"venue"
},
  "geometry": {"coordinates":[8.804315,53.081886],"type":"Point"}
}