{
  "type": "Feature",
  "properties": {
    "iso:country":"DE",
    "sg:address":"Militschstr. 58",
    "sg:city":"Braunschweig",
    "sg:phone":"+49 531/602442",
    "sg:postcode":"38124",
    "sg:province":"Niedersachsen",
    "wof:name":"Peter Skupin Architekt",
    "wof:placetype":"venue"
},
  "geometry": {"coordinates":[10.528328,52.225883],"type":"Point"}
}