{
  "type": "Feature",
  "properties": {
    "iso:country":"DE",
    "sg:address":"Wilonstr. 73",
    "sg:city":"T\u00fcbingen",
    "sg:phone":"+49 7071/73328",
    "sg:postcode":"72072",
    "sg:province":"Baden-W\u00fcrttemberg",
    "wof:name":"Hirsch",
    "wof:placetype":"venue"
},
  "geometry": {"coordinates":[9.0324907303,48.4894714355],"type":"Point"}
}