{
  "type": "Feature",
  "properties": {
    "iso:country":"DE",
    "sg:address":"Marienstr. 1",
    "sg:city":"Limeshain",
    "sg:phone":"+49 6047/950733",
    "sg:postcode":"63694",
    "sg:province":"Hessen",
    "wof:name":"Visicon Edv-integration Gmbh",
    "wof:placetype":"venue"
},
  "geometry": {"coordinates":[8.9674472809,50.2607383728],"type":"Point"}
}