{
  "type": "Feature",
  "properties": {
    "iso:country":"DE",
    "sg:address":"Minnefelder Seestr. 28",
    "sg:city":"Dieburg",
    "sg:phone":"+49 6071/23929",
    "sg:postcode":"64807",
    "sg:province":"Hessen",
    "wof:name":"Alt Berliner Bierstubb",
    "wof:placetype":"venue"
},
  "geometry": {"coordinates":[8.8466796875,49.9019966125],"type":"Point"}
}