{
  "type": "Feature",
  "properties": {
    "iso:country":"DE",
    "sg:address":"Burkhardtstr. 31",
    "sg:city":"Triptis",
    "sg:phone":"+49 36482/380",
    "sg:postcode":"07819",
    "sg:province":"Th\u00fcringen",
    "wof:name":"Kbi Fahrschule Und Fahrlehrerausbildungsst\u00e4tte",
    "wof:placetype":"venue"
},
  "geometry": {"coordinates":[11.8801736832,50.7371292114],"type":"Point"}
}