{
  "type": "Feature",
  "properties": {
    "iso:country":"DE",
    "sg:address":"Schlierbacher Str. 28",
    "sg:city":"Babenhausen",
    "sg:phone":"+49 6073/87123",
    "sg:postcode":"64832",
    "sg:province":"Hessen",
    "wof:name":"Susanna Und Josef Venczel",
    "wof:placetype":"venue"
},
  "geometry": {"coordinates":[8.95498,49.923012],"type":"Point"}
}