{
  "type": "Feature",
  "properties": {
    "iso:country":"DE",
    "sg:address":"Am Dittwarer Bahnhof 1",
    "sg:city":"Tauberbischofsheim",
    "sg:phone":"+49 9341/4288",
    "sg:postcode":"97941",
    "sg:province":"Baden-W\u00fcrttemberg",
    "wof:name":"Pilsstube Ritter",
    "wof:placetype":"venue"
},
  "geometry": {"coordinates":[9.6419363022,49.603302002],"type":"Point"}
}