{
  "type": "Feature",
  "properties": {
    "iso:country":"DE",
    "sg:address":"Aloys-Schneider-Str. 37",
    "sg:city":"Gerolstein",
    "sg:phone":"+49 6591/170",
    "sg:postcode":"54568",
    "sg:province":"Rheinland-Pfalz",
    "wof:name":"St. Elisabeth-krankenhaus",
    "wof:placetype":"venue"
},
  "geometry": {"coordinates":[6.663975,50.226505],"type":"Point"}
}