{
  "type": "Feature",
  "properties": {
    "iso:country":"DE",
    "sg:address":"Raiffeisenstr. 12",
    "sg:city":"Veitsh\u00f6chheim",
    "sg:phone":"+49 931/94603",
    "sg:postcode":"97209",
    "sg:province":"Bayern",
    "wof:name":"G. Schmelzeisen",
    "wof:placetype":"venue"
},
  "geometry": {"coordinates":[9.899365,49.831966],"type":"Point"}
}