{
  "type": "Feature",
  "properties": {
    "iso:country":"DE",
    "sg:address":"Mauthstr. 7",
    "sg:city":"Freising",
    "sg:phone":"+49 8161/86076",
    "sg:postcode":"85356",
    "sg:province":"Bayern",
    "wof:name":"Gottfried Joos",
    "wof:placetype":"venue"
},
  "geometry": {"coordinates":[11.774022,48.380978],"type":"Point"}
}