{
  "type": "Feature",
  "properties": {
    "iso:country":"DE",
    "sg:address":"Postfach 810510",
    "sg:city":"Stuttgart",
    "sg:phone":"+49 711/900870",
    "sg:postcode":"70001",
    "sg:province":"Baden-W\u00fcrttemberg",
    "wof:name":"Peter Siesser Immobilienmakler",
    "wof:placetype":"venue"
},
  "geometry": {"coordinates":[9.180729866,48.7772216797],"type":"Point"}
}