{
  "type": "Feature",
  "properties": {
    "iso:country":"DE",
    "sg:address":"Pr\u00fcfeninger Str. 83a",
    "sg:city":"Regensburg",
    "sg:phone":"+49 941/21580",
    "sg:postcode":"93049",
    "sg:province":"Bayern",
    "wof:name":"Gastst\u00e4tte Katharinen",
    "wof:placetype":"venue"
},
  "geometry": {"coordinates":[12.0654792786,49.0155525208],"type":"Point"}
}