{
  "type": "Feature",
  "properties": {
    "iso:country":"DE",
    "sg:address":"Hauptstr. 29",
    "sg:city":"B\u00f6hl-Iggelheim",
    "sg:phone":"+49 6324/64761",
    "sg:postcode":"67459",
    "sg:province":"Rheinland-Pfalz",
    "wof:name":"H.e. Hery",
    "wof:placetype":"venue"
},
  "geometry": {"coordinates":[8.2982883453,49.3844947815],"type":"Point"}
}