{
  "type": "Feature",
  "properties": {
    "iso:country":"DE",
    "sg:address":"Putzbrunner Str. 71",
    "sg:city":"M\u00fcnchen",
    "sg:phone":"+49 89/6780000",
    "sg:postcode":"81739",
    "sg:province":"Bayern",
    "wof:name":"Eiwobau M\u00fcnchen Eigenheim- Und Wohnungsbau-",
    "wof:placetype":"venue"
},
  "geometry": {"coordinates":[11.6453866959,48.096862793],"type":"Point"}
}