{
  "type": "Feature",
  "properties": {
    "iso:country":"DE",
    "sg:address":"Berliner Str. 67",
    "sg:city":"Halle",
    "sg:phone":"+49 345/5601909",
    "sg:postcode":"06116",
    "sg:province":"Sachsen-Anhalt",
    "wof:name":"Jochen Schmidt",
    "wof:placetype":"venue"
},
  "geometry": {"coordinates":[12.0113973618,51.496131897],"type":"Point"}
}