{
  "type": "Feature",
  "properties": {
    "iso:country":"DE",
    "sg:address":"Marktstr. 71",
    "sg:city":"Oberhausen",
    "sg:phone":"+49 208/2057902",
    "sg:postcode":"46045",
    "sg:province":"Nordrhein-Westfalen",
    "wof:name":"Ulrich Eickeler Praxis F\u00fcr Ergotherapie",
    "wof:placetype":"venue"
},
  "geometry": {"coordinates":[6.854219,51.468784],"type":"Point"}
}