{
  "type": "Feature",
  "properties": {
    "iso:country":"DE",
    "sg:address":"Karlstr. 9-11",
    "sg:city":"Biberach",
    "sg:phone":"+49 7351/5820",
    "sg:postcode":"88400",
    "sg:province":"Baden-W\u00fcrttemberg",
    "wof:name":"Fachhochschule Mit Den Studienrichtungen Architektur",
    "wof:placetype":"venue"
},
  "geometry": {"coordinates":[9.787824,48.093891],"type":"Point"}
}