{
  "type": "Feature",
  "properties": {
    "iso:country":"DE",
    "sg:address":"Am Seehafen 1",
    "sg:city":"Rostock",
    "sg:postcode":"18147",
    "sg:province":"Mecklenburg-Vorpommern",
    "wof:name":"Ms Northern Pleasure Schiffahrtsges. Mbh",
    "wof:placetype":"venue"
},
  "geometry": {"coordinates":[12.11025,54.143417],"type":"Point"}
}