{
  "type": "Feature",
  "properties": {
    "iso:country":"DE",
    "sg:address":"Im Attich 25",
    "sg:city":"Bischofsheim",
    "sg:phone":"+49 6144",
    "sg:postcode":"65474",
    "sg:province":"Hessen",
    "wof:name":"Dampf By Dietz",
    "wof:placetype":"venue"
},
  "geometry": {"coordinates":[8.365038,49.985546],"type":"Point"}
}