{
  "type": "Feature",
  "properties": {
    "iso:country":"DE",
    "sg:address":"Flieth 4a",
    "sg:city":"Coswig",
    "sg:postcode":"06869",
    "sg:province":"Sachsen-Anhalt",
    "wof:name":"Neuapostolische Kirche",
    "wof:placetype":"venue"
},
  "geometry": {"coordinates":[12.3857955933,51.9276199341],"type":"Point"}
}