{
  "type": "Feature",
  "properties": {
    "iso:country":"DE",
    "sg:address":"Rh\u00f6nstr. 46",
    "sg:city":"Offenbach/M",
    "sg:postcode":"63071",
    "sg:province":"Hessen",
    "wof:name":"Interconnect Reisen Gmbh",
    "wof:placetype":"venue"
},
  "geometry": {"coordinates":[8.7830152512,50.0959701538],"type":"Point"}
}