{
  "type": "Feature",
  "properties": {
    "iso:country":"DE",
    "sg:address":"Pfarrer-Ki\u00dflinger-Str. 29",
    "sg:city":"Reichertshausen",
    "sg:phone":"+49 8137/8959",
    "sg:postcode":"85293",
    "sg:province":"Bayern",
    "wof:name":"Eva R\u00f6mer",
    "wof:placetype":"venue"
},
  "geometry": {"coordinates":[11.4651622772,48.4400520325],"type":"Point"}
}