{
  "type": "Feature",
  "properties": {
    "iso:country":"DE",
    "sg:address":"Gerichtsweg 5",
    "sg:city":"Mei\u00dfen",
    "sg:phone":"+49 3521/737668",
    "sg:postcode":"01662",
    "sg:province":"Sachsen",
    "wof:name":"Pro-media-communications- Vertriebsgesellschaft Mbh",
    "wof:placetype":"venue"
},
  "geometry": {"coordinates":[13.4952993393,51.1758995056],"type":"Point"}
}