{
  "type": "Feature",
  "properties": {
    "iso:country":"DE",
    "sg:address":"Am Steigenberg 2",
    "sg:city":"Bad Liebenwerda",
    "sg:phone":"+49 35341/1570",
    "sg:postcode":"04924",
    "sg:province":"Brandenburg",
    "wof:name":"Ingenieurgemeinschaft Wtu Gmbh",
    "wof:placetype":"venue"
},
  "geometry": {"coordinates":[13.3934612274,51.5286483765],"type":"Point"}
}