{
  "type": "Feature",
  "properties": {
    "iso:country":"DE",
    "sg:address":"Hermann-Fein-Str. 9",
    "sg:city":"Stuttgart",
    "sg:phone":"+49 711/4567334",
    "sg:postcode":"70599",
    "sg:province":"Baden-W\u00fcrttemberg",
    "wof:name":"I.o. Interaktive Objekte Gesellschaft F\u00fcr Informations-",
    "wof:placetype":"venue"
},
  "geometry": {"coordinates":[9.2193346024,48.6975898743],"type":"Point"}
}