{
  "type": "Feature",
  "properties": {
    "iso:country":"DE",
    "sg:address":"H\u00f6seler Platz 2",
    "sg:city":"Heiligenhaus",
    "sg:phone":"+49 2056/921010",
    "sg:postcode":"42579",
    "sg:province":"Nordrhein-Westfalen",
    "wof:name":"Hartmann & Braun Ag & Co. Verwaltungsgesellschaft Ohg",
    "wof:placetype":"venue"
},
  "geometry": {"coordinates":[6.956269,51.32478],"type":"Point"}
}