{
  "type": "Feature",
  "properties": {
    "iso:country":"DE",
    "sg:address":"Bahnstr. 17",
    "sg:city":"Zeuthen",
    "sg:phone":"+49 33762/92502",
    "sg:postcode":"15738",
    "sg:province":"Brandenburg",
    "wof:name":"Dr. Med. Dieter Hannemann",
    "wof:placetype":"venue"
},
  "geometry": {"coordinates":[13.629149,52.344818],"type":"Point"}
}