{
  "type": "Feature",
  "properties": {
    "iso:country":"DE",
    "sg:address":"Grieblweg 8",
    "sg:city":"Feldkirchen-Westerham",
    "sg:phone":"+49 8063/204",
    "sg:postcode":"83620",
    "sg:province":"Bayern",
    "wof:name":"Frick Gmbh",
    "wof:placetype":"venue"
},
  "geometry": {"coordinates":[11.84794,47.90873],"type":"Point"}
}