{
  "type": "Feature",
  "properties": {
    "iso:country":"DE",
    "sg:address":"Rheinstr 6",
    "sg:city":"Ettenheim",
    "sg:phone":"+49 7822/445880",
    "sg:postcode":"77955",
    "sg:province":"Baden-W\u00fcrttemberg",
    "wof:name":"Fenster Gmbh",
    "wof:placetype":"venue"
},
  "geometry": {"coordinates":[7.811421,48.257824],"type":"Point"}
}