{
  "type": "Feature",
  "properties": {
    "iso:country":"DE",
    "sg:address":"Gr\u00fcntalstr. 8",
    "sg:city":"Todtmoos",
    "sg:phone":"+49 7674/329",
    "sg:postcode":"79682",
    "sg:province":"Baden-W\u00fcrttemberg",
    "wof:name":"Fremdenheim E. Und L. Klein",
    "wof:placetype":"venue"
},
  "geometry": {"coordinates":[8.0021858215,47.7418022156],"type":"Point"}
}