{
  "type": "Feature",
  "properties": {
    "iso:country":"DE",
    "sg:address":"Poststr. 35",
    "sg:city":"Bad Neuenahr-Ahrweiler",
    "sg:phone":"+49 2641/28941",
    "sg:postcode":"53474",
    "sg:province":"Rheinland-Pfalz",
    "wof:name":"Lady-h",
    "wof:placetype":"venue"
},
  "geometry": {"coordinates":[7.137515,50.543533],"type":"Point"}
}