{
  "type": "Feature",
  "properties": {
    "iso:country":"DE",
    "sg:address":"Strudelbachstr. 35",
    "sg:city":"Vaihingen",
    "sg:phone":"+49 7042/7054",
    "sg:postcode":"71665",
    "sg:province":"Baden-W\u00fcrttemberg",
    "wof:name":"Ernst Hauser",
    "wof:placetype":"venue"
},
  "geometry": {"coordinates":[8.9697742462,48.8942527771],"type":"Point"}
}