{
  "type": "Feature",
  "properties": {
    "iso:country":"DE",
    "sg:address":"H\u00f6lscherstr. 10",
    "sg:city":"Duisburg",
    "sg:phone":"+49 203/581584",
    "sg:postcode":"47167",
    "sg:province":"Nordrhein-Westfalen",
    "wof:name":"Stahlbau Ternieden",
    "wof:placetype":"venue"
},
  "geometry": {"coordinates":[6.809857,51.492599],"type":"Point"}
}