{
  "type": "Feature",
  "properties": {
    "iso:country":"DE",
    "sg:address":"Charlottenstr 66",
    "sg:city":"Berlin",
    "sg:phone":"+49 30/5900670",
    "sg:postcode":"10117",
    "sg:province":"Berlin",
    "wof:name":"Space2go.com Gmbh & Co Kg",
    "wof:placetype":"venue"
},
  "geometry": {"coordinates":[13.3915338516,52.510761261],"type":"Point"}
}