{
  "type": "Feature",
  "properties": {
    "iso:country":"DE",
    "sg:address":"Bardenflethstr. 9",
    "sg:city":"Bremen",
    "sg:phone":"+49 421/5148000",
    "sg:postcode":"28259",
    "sg:province":"Bremen",
    "wof:name":"Pick",
    "wof:placetype":"venue"
},
  "geometry": {"coordinates":[8.7675409317,53.0617256165],"type":"Point"}
}