{
  "type": "Feature",
  "properties": {
    "iso:country":"DE",
    "sg:address":"Hauptstr. 39",
    "sg:city":"Regenstauf",
    "sg:phone":"+49 9402/1278",
    "sg:postcode":"93128",
    "sg:province":"Bayern",
    "wof:name":"Max Amann Grundst\u00fccksverwaltungs Gmbh",
    "wof:placetype":"venue"
},
  "geometry": {"coordinates":[12.1292,49.126827],"type":"Point"}
}