{
  "type": "Feature",
  "properties": {
    "iso:country":"DE",
    "sg:address":"\u00c4u\u00dfere Landshuter Str. 42",
    "sg:city":"Mainburg",
    "sg:postcode":"84048",
    "sg:province":"Bayern",
    "wof:name":"Omnia-transport Gmbh",
    "wof:placetype":"venue"
},
  "geometry": {"coordinates":[11.794500351,48.6268386841],"type":"Point"}
}