{
  "type": "Feature",
  "properties": {
    "iso:country":"DE",
    "sg:address":"Doblbach 1",
    "sg:city":"Bruck",
    "sg:phone":"+49 8091/7601",
    "sg:postcode":"85567",
    "sg:province":"Bayern",
    "wof:name":"Ren\u00e9 Und Daniela Breite",
    "wof:placetype":"venue"
},
  "geometry": {"coordinates":[11.8810930252,48.0285186768],"type":"Point"}
}