{
  "type": "Feature",
  "properties": {
    "iso:country":"DE",
    "sg:address":"Stroppel 4",
    "sg:city":"Wolpertswende",
    "sg:phone":"+49 7502/3777",
    "sg:postcode":"88284",
    "sg:province":"Baden-W\u00fcrttemberg",
    "wof:name":"Italian Design Gmbh",
    "wof:placetype":"venue"
},
  "geometry": {"coordinates":[9.6165122986,47.8863258362],"type":"Point"}
}