{
  "type": "Feature",
  "properties": {
    "iso:country":"DE",
    "sg:address":"M\u00f6beck 28a",
    "sg:city":"Wuppertal",
    "sg:phone":"+49 202/2546239",
    "sg:postcode":"42327",
    "sg:province":"Nordrhein-Westfalen",
    "wof:name":"Dipl.-ing. J\u00f6rg Anders - Unternehmensberatung",
    "wof:placetype":"venue"
},
  "geometry": {"coordinates":[7.097378,51.242458],"type":"Point"}
}