{
  "type": "Feature",
  "properties": {
    "iso:country":"DE",
    "sg:address":"Hecklinger Str. 10",
    "sg:city":"Neundorf",
    "sg:phone":"+49 3925/382256",
    "sg:postcode":"39418",
    "sg:province":"Sachsen-Anhalt",
    "wof:name":"Schulze Hoch- Und Tief- Baugesellschaft Mbh",
    "wof:placetype":"venue"
},
  "geometry": {"coordinates":[11.58392,51.853966],"type":"Point"}
}