{
  "type": "Feature",
  "properties": {
    "iso:country":"DE",
    "sg:address":"Bahnhofstr. 6",
    "sg:city":"Gro\u00dfhabersdorf",
    "sg:phone":"+49 9105/305",
    "sg:postcode":"90613",
    "sg:province":"Bayern",
    "wof:name":"Vereinigte Sparkasse, Im Landkreis F\u00fcrth",
    "wof:placetype":"venue"
},
  "geometry": {"coordinates":[10.789543,49.403687],"type":"Point"}
}