{
  "type": "Feature",
  "properties": {
    "iso:country":"DE",
    "sg:address":"Siedlung 17",
    "sg:city":"Mackenbach",
    "sg:phone":"+49 6374/6430",
    "sg:postcode":"67686",
    "sg:province":"Rheinland-Pfalz",
    "wof:name":"Jakob Steig Getr\u00e4nkevertrieb",
    "wof:placetype":"venue"
},
  "geometry": {"coordinates":[7.583464,49.466568],"type":"Point"}
}