{
  "type": "Feature",
  "properties": {
    "iso:country":"DE",
    "sg:address":"Wehrdaer Weg 24",
    "sg:city":"Marburg",
    "sg:phone":"+49 6421/66871",
    "sg:postcode":"35037",
    "sg:province":"Hessen",
    "wof:name":"Bremsspur",
    "wof:placetype":"venue"
},
  "geometry": {"coordinates":[8.763428688,50.8232421875],"type":"Point"}
}