{
  "type": "Feature",
  "properties": {
    "iso:country":"DE",
    "sg:address":"Weidenweg 5",
    "sg:city":"Friedrichsdorf",
    "sg:phone":"+49 6172/78168",
    "sg:postcode":"61381",
    "sg:province":"Hessen",
    "wof:name":"Heinz M\u00fcller",
    "wof:placetype":"venue"
},
  "geometry": {"coordinates":[8.6452732086,50.2411231995],"type":"Point"}
}