{
  "type": "Feature",
  "properties": {
    "iso:country":"DE",
    "sg:address":"Hauptstr. 25",
    "sg:city":"Bonstetten",
    "sg:phone":"+49 8293/7946",
    "sg:postcode":"86486",
    "sg:province":"Bayern",
    "wof:name":"A. E. Schaller Brau Gmbh",
    "wof:placetype":"venue"
},
  "geometry": {"coordinates":[10.7100133896,48.4385108948],"type":"Point"}
}