{
  "type": "Feature",
  "properties": {
    "iso:country":"DE",
    "sg:address":"Harzstr. 9",
    "sg:city":"Sch\u00f6nwald",
    "sg:phone":"+49 7722/7999",
    "sg:postcode":"78141",
    "sg:province":"Baden-W\u00fcrttemberg",
    "wof:name":"Holger Riebesell",
    "wof:placetype":"venue"
},
  "geometry": {"coordinates":[8.203867,48.106884],"type":"Point"}
}