{
  "type": "Feature",
  "properties": {
    "iso:country":"DE",
    "sg:address":"Ludwigstr. 33",
    "sg:city":"Bad Reichenhall",
    "sg:phone":"+49 8651/6040",
    "sg:postcode":"83435",
    "sg:province":"Bayern",
    "wof:name":"Parkhotel Luisenbad Fritz Herkommer",
    "wof:placetype":"venue"
},
  "geometry": {"coordinates":[12.8799371719,47.7253417969],"type":"Point"}
}