{
  "type": "Feature",
  "properties": {
    "iso:country":"DE",
    "sg:address":"Ochsenbacher Str. 8",
    "sg:city":"Hohenhaslach",
    "sg:phone":"+49 4971/475533",
    "sg:postcode":"74343",
    "sg:province":"Baden-W\u00fcrttemberg",
    "wof:name":"Kreissparkasse Ludwigsburg",
    "wof:placetype":"venue"
},
  "geometry": {"coordinates":[9.020164,48.999619],"type":"Point"}
}