{
  "type": "Feature",
  "properties": {
    "iso:country":"DE",
    "sg:address":"Hintere H\u00f6he 7",
    "sg:city":"M\u00fcnchberg",
    "sg:phone":"+49 9251/94610",
    "sg:postcode":"95213",
    "sg:province":"Bayern",
    "wof:name":"Seehotel Hintere H\u00d6he Kg",
    "wof:placetype":"venue"
},
  "geometry": {"coordinates":[11.775496,50.180309],"type":"Point"}
}