{
  "type": "Feature",
  "properties": {
    "iso:country":"DE",
    "sg:address":"Fritz Kotz Str. 4",
    "sg:city":"Wiehl",
    "sg:phone":"+49 4977/243040",
    "sg:postcode":"51674",
    "sg:province":"Nordrhein-Westfalen",
    "wof:name":"Sts Schreibger\u00c4te-technik Schwarzwald Gmbh & Co. Kg",
    "wof:placetype":"venue"
},
  "geometry": {"coordinates":[8.3398685455,48.1267623901],"type":"Point"}
}