{
  "type": "Feature",
  "properties": {
    "iso:country":"DE",
    "sg:address":"Hamburger Str. 14",
    "sg:city":"Georgsmarienh\u00fctte",
    "sg:phone":"+49 5401/44255",
    "sg:postcode":"49124",
    "sg:province":"Niedersachsen",
    "wof:name":"H. M\u00fcller Bauunternehmen Gmbh",
    "wof:placetype":"venue"
},
  "geometry": {"coordinates":[8.084585,52.221184],"type":"Point"}
}