{
  "type": "Feature",
  "properties": {
    "iso:country":"DE",
    "sg:address":"Heideweg 28",
    "sg:city":"Thallichtenberg",
    "sg:phone":"+49 6381/7864",
    "sg:postcode":"66871",
    "sg:province":"Rheinland-Pfalz",
    "wof:name":"Wolfgang Loos Heilpraktiker",
    "wof:placetype":"venue"
},
  "geometry": {"coordinates":[7.3464550972,49.5575218201],"type":"Point"}
}