{
  "type": "Feature",
  "properties": {
    "iso:country":"DE",
    "sg:address":"L\u00f6hrstr. 68",
    "sg:city":"Vallendar",
    "sg:phone":"+49 261/60404",
    "sg:postcode":"56179",
    "sg:province":"Rheinland-Pfalz",
    "wof:name":"Wilh. Pusch",
    "wof:placetype":"venue"
},
  "geometry": {"coordinates":[7.617398,50.400528],"type":"Point"}
}