{
  "type": "Feature",
  "properties": {
    "iso:country":"DE",
    "sg:address":"L\u00f6stertalstr. 63",
    "sg:city":"Wadern",
    "sg:phone":"+49 6871/2352",
    "sg:postcode":"66687",
    "sg:province":"Saarland",
    "wof:name":"J. Thome",
    "wof:placetype":"venue"
},
  "geometry": {"coordinates":[6.9275131226,49.5660057068],"type":"Point"}
}