{
  "type": "Feature",
  "properties": {
    "iso:country":"DE",
    "sg:address":"Friedrichstr. 20",
    "sg:city":"Falkenberg",
    "sg:postcode":"04895",
    "sg:province":"Brandenburg",
    "wof:name":"Nur-molls Reiseb\u00fcro",
    "wof:placetype":"venue"
},
  "geometry": {"coordinates":[13.2426366806,51.5851898193],"type":"Point"}
}