{
  "type": "Feature",
  "properties": {
    "iso:country":"DE",
    "sg:address":"Br\u00fcckenstr. 2",
    "sg:city":"Nienburg",
    "sg:phone":"+49 5021/3800",
    "sg:postcode":"31582",
    "sg:province":"Niedersachsen",
    "wof:name":"Film-eck Kino 13",
    "wof:placetype":"venue"
},
  "geometry": {"coordinates":[9.207394,52.642784],"type":"Point"}
}