{
  "type": "Feature",
  "properties": {
    "iso:country":"DE",
    "sg:address":"Gottsfeld",
    "sg:city":"Creu\u00dfen",
    "sg:phone":"+49 9270/1553",
    "sg:postcode":"95473",
    "sg:province":"Bayern",
    "wof:name":"D. Und P. Fischer",
    "wof:placetype":"venue"
},
  "geometry": {"coordinates":[11.5917797089,49.8436698914],"type":"Point"}
}