{
  "type": "Feature",
  "properties": {
    "iso:country":"DE",
    "sg:address":"Gro\u00dfe Nelkenstr. 7b",
    "sg:city":"Frankfurt",
    "sg:phone":"+49 69/78960645",
    "sg:postcode":"60488",
    "sg:province":"Hessen",
    "wof:name":"Dth Datentechnik Honke Gmbh",
    "wof:placetype":"venue"
},
  "geometry": {"coordinates":[8.6267881393,50.1325035095],"type":"Point"}
}