{
  "type": "Feature",
  "properties": {
    "iso:country":"DE",
    "sg:address":"Mozartallee 129",
    "sg:city":"Gro\u00dfenhain",
    "sg:postcode":"01558",
    "sg:province":"Sachsen",
    "wof:name":"Gr\u00e4ser Verlag Gro\u00dfenhain Ohg",
    "wof:placetype":"venue"
},
  "geometry": {"coordinates":[13.5274333954,51.2914962769],"type":"Point"}
}