{
  "type": "Feature",
  "properties": {
    "iso:country":"DE",
    "sg:address":"B\u00f6dekerstr. 75",
    "sg:city":"Hannover",
    "sg:phone":"+49 511/909490",
    "sg:postcode":"30161",
    "sg:province":"Niedersachsen",
    "wof:name":"A.-p. Wegener Und Partner",
    "wof:placetype":"venue"
},
  "geometry": {"coordinates":[9.7507677078,52.3876724243],"type":"Point"}
}