{
  "type": "Feature",
  "properties": {
    "iso:country":"DE",
    "sg:address":"Rheinstr. 104",
    "sg:city":"H\u00fcckelhoven",
    "sg:phone":"+49 2433/979820",
    "sg:postcode":"41836",
    "sg:province":"Nordrhein-Westfalen",
    "wof:name":"Birgitt Keller Rechtsanw\u00e4ltin",
    "wof:placetype":"venue"
},
  "geometry": {"coordinates":[6.2295818329,51.0459632874],"type":"Point"}
}