{
  "type": "Feature",
  "properties": {
    "iso:country":"DE",
    "sg:address":"Wendemuthstr. 5",
    "sg:city":"Hamburg",
    "sg:phone":"+49 40/23859477",
    "sg:postcode":"22041",
    "sg:province":"Hamburg",
    "wof:name":"Sgt Saheem Germany Trading Im- Und Export E. K.",
    "wof:placetype":"venue"
},
  "geometry": {"coordinates":[10.0740127563,53.5754852295],"type":"Point"}
}