{
  "type": "Feature",
  "properties": {
    "iso:country":"DE",
    "sg:address":"L\u00fcderitzweg 7",
    "sg:city":"M\u00fcnster",
    "sg:phone":"+49 251/61392",
    "sg:postcode":"48167",
    "sg:province":"Nordrhein-Westfalen",
    "wof:name":"G\u00fcnter Schult",
    "wof:placetype":"venue"
},
  "geometry": {"coordinates":[7.678867,51.928864],"type":"Point"}
}