{
  "type": "Feature",
  "properties": {
    "iso:country":"DE",
    "sg:address":"Zum Wildgehege 22",
    "sg:city":"Siegen",
    "sg:phone":"+49 271/73142",
    "sg:postcode":"57078",
    "sg:province":"Nordrhein-Westfalen",
    "wof:name":"Dachdeckerbetrieb B\u00e4tzel Gmbh",
    "wof:placetype":"venue"
},
  "geometry": {"coordinates":[8.013969,50.905144],"type":"Point"}
}