{
  "type": "Feature",
  "properties": {
    "iso:country":"DE",
    "sg:address":"St.-Ulrich-Str. 6",
    "sg:city":"Bibertal",
    "sg:phone":"+49 8226/940704",
    "sg:postcode":"89346",
    "sg:province":"Bayern",
    "wof:name":"Indusim Gmbh",
    "wof:placetype":"venue"
},
  "geometry": {"coordinates":[10.1962003708,48.3955192566],"type":"Point"}
}