{
  "type": "Feature",
  "properties": {
    "iso:country":"DE",
    "sg:address":"Zypressenweg 15",
    "sg:city":"Hamburg",
    "sg:phone":"+49 40/8811947",
    "sg:postcode":"22605",
    "sg:province":"Hamburg",
    "wof:name":"Rolf Kellner Architekt",
    "wof:placetype":"venue"
},
  "geometry": {"coordinates":[9.886386,53.547138],"type":"Point"}
}