{
  "type": "Feature",
  "properties": {
    "iso:country":"DE",
    "sg:address":"Auf Der Lay 74",
    "sg:city":"Hanroth",
    "sg:phone":"+49 9352/87450",
    "sg:postcode":"56316",
    "sg:province":"Rheinland-Pfalz",
    "wof:name":"Hans Mattis Gmbh",
    "wof:placetype":"venue"
},
  "geometry": {"coordinates":[9.584873,50.002651],"type":"Point"}
}