{
  "type": "Feature",
  "properties": {
    "iso:country":"DE",
    "sg:address":"Hauptstr. 58 a",
    "sg:city":"Schwarzach",
    "sg:phone":"+49 6262/3601",
    "sg:postcode":"74869",
    "sg:province":"Baden-W\u00fcrttemberg",
    "wof:name":"Esther D\u00f6bert",
    "wof:placetype":"venue"
},
  "geometry": {"coordinates":[8.9819097519,49.3687934875],"type":"Point"}
}