{
  "type": "Feature",
  "properties": {
    "iso:country":"DE",
    "sg:address":"St\u00f6vergasse 4",
    "sg:city":"Grevenbroich",
    "sg:phone":"+49 2182/18765",
    "sg:postcode":"41516",
    "sg:province":"Nordrhein-Westfalen",
    "wof:name":"Merholz Gartenbaubedarf Inh. Ulrich Brinkmann",
    "wof:placetype":"venue"
},
  "geometry": {"coordinates":[6.6094121933,51.1212387085],"type":"Point"}
}