{
  "type": "Feature",
  "properties": {
    "iso:country":"DE",
    "sg:address":"Neuherbrumer Str. 180",
    "sg:city":"Papenburg",
    "sg:phone":"+49 4962/1661",
    "sg:postcode":"26871",
    "sg:province":"Niedersachsen",
    "wof:name":"Bernhard Wegmann",
    "wof:placetype":"venue"
},
  "geometry": {"coordinates":[7.371127,53.020241],"type":"Point"}
}