{
  "type": "Feature",
  "properties": {
    "iso:country":"DE",
    "sg:address":"Leester Str. 139",
    "sg:city":"Weyhe",
    "sg:postcode":"28844",
    "sg:province":"Niedersachsen",
    "wof:name":"Abwasserverband Stuhr-weyhe",
    "wof:placetype":"venue"
},
  "geometry": {"coordinates":[8.8348426819,52.9833717346],"type":"Point"}
}