{
  "type": "Feature",
  "properties": {
    "iso:country":"DE",
    "sg:address":"Teutoburger Str. 220",
    "sg:city":"Oberhausen",
    "sg:phone":"+49 208/22974",
    "sg:postcode":"46119",
    "sg:province":"Nordrhein-Westfalen",
    "wof:name":"Restaurant El Cadoro",
    "wof:placetype":"venue"
},
  "geometry": {"coordinates":[6.8838658333,51.5178565979],"type":"Point"}
}