{
  "type": "Feature",
  "properties": {
    "iso:country":"DE",
    "sg:address":"Neue Str. 4",
    "sg:city":"Boffzen",
    "sg:postcode":"37691",
    "sg:province":"Niedersachsen",
    "wof:name":"Efs Group Gmbh",
    "wof:placetype":"venue"
},
  "geometry": {"coordinates":[9.39677,51.751614],"type":"Point"}
}