{
  "type": "Feature",
  "properties": {
    "iso:country":"DE",
    "sg:address":"Karl-Marx-Platz 1",
    "sg:city":"M\u00fcnchenbernsdorf",
    "sg:phone":"+49 36604/80219",
    "sg:postcode":"07589",
    "sg:province":"Th\u00fcringen",
    "wof:name":"Helmut Gei\u00dfler",
    "wof:placetype":"venue"
},
  "geometry": {"coordinates":[11.9326257706,50.8199806213],"type":"Point"}
}