{
  "type": "Feature",
  "properties": {
    "iso:country":"DE",
    "sg:address":"Max-Braun-Str. 13",
    "sg:city":"Neunkirchen",
    "sg:phone":"+49 6821/22494",
    "sg:postcode":"66538",
    "sg:province":"Saarland",
    "wof:name":"H. Schwender Gmbh",
    "wof:placetype":"venue"
},
  "geometry": {"coordinates":[7.181707,49.343994],"type":"Point"}
}