{
  "type": "Feature",
  "properties": {
    "iso:country":"DE",
    "sg:address":"Stubenstr. 1",
    "sg:city":"Hameln",
    "sg:phone":"+49 5151/23091",
    "sg:postcode":"31785",
    "sg:province":"Niedersachsen",
    "wof:name":"Real",
    "wof:placetype":"venue"
},
  "geometry": {"coordinates":[9.3549404144,52.1058502197],"type":"Point"}
}