{
  "type": "Feature",
  "properties": {
    "iso:country":"DE",
    "sg:address":"Goethestr. 3",
    "sg:city":"Westerstede",
    "sg:phone":"+49 4488/2566",
    "sg:postcode":"26655",
    "sg:province":"Niedersachsen",
    "wof:name":"Willi Zywietz",
    "wof:placetype":"venue"
},
  "geometry": {"coordinates":[7.9359941483,53.2525634766],"type":"Point"}
}