{
  "type": "Feature",
  "properties": {
    "iso:country":"DE",
    "sg:address":"Bockstalstr. 39",
    "sg:city":"Pfinztal",
    "sg:phone":"+49 7240/206868",
    "sg:postcode":"76327",
    "sg:province":"Baden-W\u00fcrttemberg",
    "wof:name":"Martin H\u00f6pfinger",
    "wof:placetype":"venue"
},
  "geometry": {"coordinates":[8.5499897003,48.9651756287],"type":"Point"}
}