{
  "type": "Feature",
  "properties": {
    "iso:country":"DE",
    "sg:address":"Entengasse 21",
    "sg:city":"Schwaigern",
    "sg:postcode":"74193",
    "sg:province":"Baden-W\u00fcrttemberg",
    "wof:name":"Kahraman Elektro- Gmbh",
    "wof:placetype":"venue"
},
  "geometry": {"coordinates":[9.004855,49.129562],"type":"Point"}
}