{
  "type": "Feature",
  "properties": {
    "iso:country":"DE",
    "sg:address":"Grubenstr. 82b",
    "sg:city":"Leienkaul",
    "sg:phone":"+49 2653/3372",
    "sg:postcode":"56759",
    "sg:province":"Rheinland-Pfalz",
    "wof:name":"Reinhard Walgenbach",
    "wof:placetype":"venue"
},
  "geometry": {"coordinates":[7.0814,50.217197],"type":"Point"}
}