{
  "type": "Feature",
  "properties": {
    "iso:country":"DE",
    "sg:address":"Rajen 229",
    "sg:city":"Rhauderfehn",
    "sg:phone":"+49 4952/3705",
    "sg:postcode":"26817",
    "sg:province":"Niedersachsen",
    "wof:name":"Dieter Michaelsen",
    "wof:placetype":"venue"
},
  "geometry": {"coordinates":[7.530524,53.131474],"type":"Point"}
}