{
  "type": "Feature",
  "properties": {
    "iso:country":"DE",
    "sg:address":"Geitlingstr. 12",
    "sg:city":"Bochum",
    "sg:phone":"+49 2327/82325",
    "sg:postcode":"44866",
    "sg:province":"Nordrhein-Westfalen",
    "wof:name":"Katholisches Pfarramt St. Joseph",
    "wof:placetype":"venue"
},
  "geometry": {"coordinates":[7.1548771858,51.480594635],"type":"Point"}
}