{
  "type": "Feature",
  "properties": {
    "iso:country":"DE",
    "sg:address":"Lichtentaler Str. 36",
    "sg:city":"Baden-Baden",
    "sg:phone":"+49 7221/346600",
    "sg:postcode":"76530",
    "sg:province":"Baden-W\u00fcrttemberg",
    "wof:name":"Hotel Der Kleine Prinz Gmbh",
    "wof:placetype":"venue"
},
  "geometry": {"coordinates":[8.2420043945,48.7572021484],"type":"Point"}
}