{
  "type": "Feature",
  "properties": {
    "iso:country":"DE",
    "sg:address":"Bellermannstr. 92",
    "sg:city":"Berlin",
    "sg:phone":"+49 30/4934071",
    "sg:postcode":"13357",
    "sg:province":"Berlin",
    "wof:name":"Katholisches Pfarramt St. Petrus",
    "wof:placetype":"venue"
},
  "geometry": {"coordinates":[13.3853712082,52.554233551],"type":"Point"}
}