{
  "type": "Feature",
  "properties": {
    "iso:country":"DE",
    "sg:address":"Bachstr. 1",
    "sg:city":"Biesenthal",
    "sg:phone":"+49 3337/2230",
    "sg:postcode":"16359",
    "sg:province":"Brandenburg",
    "wof:name":"Gerhard Lutter",
    "wof:placetype":"venue"
},
  "geometry": {"coordinates":[13.65844,52.755745],"type":"Point"}
}