{
  "type": "Feature",
  "properties": {
    "iso:country":"DE",
    "sg:address":"Rosenweg 4",
    "sg:city":"Sch\u00f6nteichen",
    "sg:phone":"+49 35783/15633",
    "sg:postcode":"01920",
    "sg:province":"Sachsen",
    "wof:name":"Holger Bergmann",
    "wof:placetype":"venue"
},
  "geometry": {"coordinates":[14.09253,51.315666],"type":"Point"}
}