{
  "type": "Feature",
  "properties": {
    "iso:country":"DE",
    "sg:address":"Berliner Str. 31",
    "sg:city":"Herford",
    "sg:phone":"+49 5221/54545",
    "sg:postcode":"32052",
    "sg:province":"Nordrhein-Westfalen",
    "wof:name":"Gube Immobilienagentur Gesellschaft F\u00fcr",
    "wof:placetype":"venue"
},
  "geometry": {"coordinates":[8.6758127213,52.1177597046],"type":"Point"}
}