{
  "type": "Feature",
  "properties": {
    "iso:country":"DE",
    "sg:address":"Kelzenberger Str. 11",
    "sg:city":"J\u00fcchen",
    "sg:phone":"+49 2165/1379",
    "sg:postcode":"41363",
    "sg:province":"Nordrhein-Westfalen",
    "wof:name":"Anneliese Wirtz",
    "wof:placetype":"venue"
},
  "geometry": {"coordinates":[6.5016479492,51.1030349731],"type":"Point"}
}