{
  "type": "Feature",
  "properties": {
    "iso:country":"DE",
    "sg:address":"Leuchte 28 a",
    "sg:city":"Lemgo",
    "sg:phone":"+49 5261/3329",
    "sg:postcode":"32657",
    "sg:province":"Nordrhein-Westfalen",
    "wof:name":"U. Halle Steuerberater",
    "wof:placetype":"venue"
},
  "geometry": {"coordinates":[8.8903951645,52.0300064087],"type":"Point"}
}