{
  "type": "Feature",
  "properties": {
    "iso:country":"DE",
    "sg:address":"Sch\u00f6nhauser Allee 12",
    "sg:city":"Berlin",
    "sg:postcode":"10119",
    "sg:province":"Berlin",
    "wof:name":"Treviso Beteiligungs Gmbh",
    "wof:placetype":"venue"
},
  "geometry": {"coordinates":[13.412103653,52.5309791565],"type":"Point"}
}