{
  "type": "Feature",
  "properties": {
    "iso:country":"DE",
    "sg:address":"G\u00e4nslerweg 1",
    "sg:city":"Oberhaching",
    "sg:phone":"+49 89/6135182",
    "sg:postcode":"82041",
    "sg:province":"Bayern",
    "wof:name":"Art & Producing Verlag Gmbh",
    "wof:placetype":"venue"
},
  "geometry": {"coordinates":[11.5979995728,48.0301208496],"type":"Point"}
}