{
  "type": "Feature",
  "properties": {
    "iso:country":"DE",
    "sg:address":"Gewerbering 6",
    "sg:city":"Schwaigern",
    "sg:phone":"+49 7138/5340",
    "sg:postcode":"74193",
    "sg:province":"Baden-W\u00fcrttemberg",
    "wof:name":"B\u00fcrsten-bonnet B\u00fcrstenfabrik",
    "wof:placetype":"venue"
},
  "geometry": {"coordinates":[9.05521,49.167782],"type":"Point"}
}