{
  "type": "Feature",
  "properties": {
    "iso:country":"DE",
    "sg:address":"Birkenallee 125",
    "sg:city":"Rheine",
    "sg:phone":"+49 5971/84082",
    "sg:postcode":"48432",
    "sg:province":"Nordrhein-Westfalen",
    "wof:name":"Brink & Funke Gmbh",
    "wof:placetype":"venue"
},
  "geometry": {"coordinates":[7.445788,52.303192],"type":"Point"}
}