{
  "type": "Feature",
  "properties": {
    "iso:country":"DE",
    "sg:address":"Zum Querdamm 40",
    "sg:city":"Kranenburg",
    "sg:phone":"+49 2826/7358",
    "sg:postcode":"47559",
    "sg:province":"Nordrhein-Westfalen",
    "wof:name":"Heinz Ten Haaf",
    "wof:placetype":"venue"
},
  "geometry": {"coordinates":[5.959225,51.82486],"type":"Point"}
}