{
  "type": "Feature",
  "properties": {
    "iso:country":"DE",
    "sg:address":"Gaulstr. 6",
    "sg:city":"Wipperf\u00fcrth",
    "sg:phone":"+49 2267/880738",
    "sg:postcode":"51688",
    "sg:province":"Nordrhein-Westfalen",
    "wof:name":"Brunnen-apotheke G\u00fcnter Keil",
    "wof:placetype":"venue"
},
  "geometry": {"coordinates":[7.399637,51.115982],"type":"Point"}
}