{
  "type": "Feature",
  "properties": {
    "iso:country":"DE",
    "sg:address":"Finsterwalder Str. 5",
    "sg:city":"Cottbus",
    "sg:postcode":"03048",
    "sg:province":"Brandenburg",
    "wof:name":"Dr. Med. Wolfgang Gubatz",
    "wof:placetype":"venue"
},
  "geometry": {"coordinates":[14.325966,51.746014],"type":"Point"}
}