{
  "type": "Feature",
  "properties": {
    "iso:country":"DE",
    "sg:address":"Lothringer Str. 196",
    "sg:city":"Oberhausen",
    "sg:phone":"+49 208/853783",
    "sg:postcode":"46045",
    "sg:province":"Nordrhein-Westfalen",
    "wof:name":"Udo Piechottka Ingenieur",
    "wof:placetype":"venue"
},
  "geometry": {"coordinates":[6.8515501022,51.4599533081],"type":"Point"}
}