{
  "type": "Feature",
  "properties": {
    "iso:country":"DE",
    "sg:address":"Fr\u00f6hliche-T\u00fcrken-Str. 10",
    "sg:city":"Regensburg",
    "sg:phone":"+49 941/52199",
    "sg:postcode":"93047",
    "sg:province":"Bayern",
    "wof:name":"Mode-eck Inh. Sieglinde Pschorr",
    "wof:placetype":"venue"
},
  "geometry": {"coordinates":[12.097851,49.015804],"type":"Point"}
}