{
  "type": "Feature",
  "properties": {
    "iso:country":"DE",
    "sg:address":"Ohmweg 7",
    "sg:city":"Neufahrn",
    "sg:postcode":"85375",
    "sg:province":"Bayern",
    "wof:name":"Pescoller Gmbh",
    "wof:placetype":"venue"
},
  "geometry": {"coordinates":[11.67223,48.309856],"type":"Point"}
}