{
  "type": "Feature",
  "properties": {
    "iso:country":"DE",
    "sg:address":"Nordwall 54",
    "sg:city":"Celle",
    "sg:phone":"+49 5141/24588",
    "sg:postcode":"29221",
    "sg:province":"Niedersachsen",
    "wof:name":"Lvm Versicherung Andreas Fehlow",
    "wof:placetype":"venue"
},
  "geometry": {"coordinates":[10.0830831528,52.6261062622],"type":"Point"}
}