{
  "type": "Feature",
  "properties": {
    "iso:country":"DE",
    "sg:address":"Vogelrohrsheide 9",
    "sg:city":"M\u00fcnster",
    "sg:phone":"+49 251/61309",
    "sg:postcode":"48167",
    "sg:province":"Nordrhein-Westfalen",
    "wof:name":"Schopax",
    "wof:placetype":"venue"
},
  "geometry": {"coordinates":[7.684854,51.919392],"type":"Point"}
}