{
  "type": "Feature",
  "properties": {
    "iso:country":"DE",
    "sg:address":"Elisabethstr. 78",
    "sg:city":"Detmold",
    "sg:phone":"+49 5231/68271",
    "sg:postcode":"32756",
    "sg:province":"Nordrhein-Westfalen",
    "wof:name":"C. R. E. Kotzenberg Gmbh & Co. Kg",
    "wof:placetype":"venue"
},
  "geometry": {"coordinates":[8.863441,51.941441],"type":"Point"}
}