{
  "type": "Feature",
  "properties": {
    "iso:country":"DE",
    "sg:address":"Hahnstr. 1",
    "sg:city":"Speyer",
    "sg:phone":"+49 6232/640127",
    "sg:postcode":"67346",
    "sg:province":"Rheinland-Pfalz",
    "wof:name":"Klaus Rottmann Steuerberater",
    "wof:placetype":"venue"
},
  "geometry": {"coordinates":[8.4246616364,49.3385467529],"type":"Point"}
}