{
  "type": "Feature",
  "properties": {
    "iso:country":"DE",
    "sg:address":"An den Drei Eichen 1",
    "sg:city":"Brilon",
    "sg:phone":"+49 2963/306",
    "sg:postcode":"59929",
    "sg:province":"Nordrhein-Westfalen",
    "wof:name":"Peter Stickel Rechtsanwalt Und Notar",
    "wof:placetype":"venue"
},
  "geometry": {"coordinates":[8.6304636002,51.3884811401],"type":"Point"}
}