{
  "type": "Feature",
  "properties": {
    "iso:country":"DE",
    "sg:address":"Werwolf 59",
    "sg:city":"Solingen",
    "sg:phone":"+49 212/207352",
    "sg:postcode":"42651",
    "sg:province":"Nordrhein-Westfalen",
    "wof:name":"Stoff-lange Magdalena Lange",
    "wof:placetype":"venue"
},
  "geometry": {"coordinates":[7.0890650749,51.1664848328],"type":"Point"}
}