{
  "type": "Feature",
  "properties": {
    "iso:country":"DE",
    "sg:address":"Wei\u00dfenseeweg 11",
    "sg:city":"Mannheim",
    "sg:phone":"+49 621/896819",
    "sg:postcode":"68219",
    "sg:province":"Baden-W\u00fcrttemberg",
    "wof:name":"Wolfgang Fabian",
    "wof:placetype":"venue"
},
  "geometry": {"coordinates":[8.531447,49.417191],"type":"Point"}
}