{
  "type": "Feature",
  "properties": {
    "iso:country":"DE",
    "sg:address":"Steinweg 41",
    "sg:city":"Halle",
    "sg:phone":"+49 345/2029938",
    "sg:postcode":"06110",
    "sg:province":"Sachsen-Anhalt",
    "wof:name":"Restaurant Kr\u00fcgers Gute Stube",
    "wof:placetype":"venue"
},
  "geometry": {"coordinates":[11.9701299667,51.4760551453],"type":"Point"}
}