{
  "type": "Feature",
  "properties": {
    "iso:country":"DE",
    "sg:address":"Unterlimpurger Str. 21",
    "sg:city":"Schw\u00e4bisch Hall",
    "sg:phone":"+49 791/971500",
    "sg:postcode":"74523",
    "sg:province":"Baden-W\u00fcrttemberg",
    "wof:name":"Kraft Und Kraft Architekten Dipl.-ing.w.kraft Und Bda",
    "wof:placetype":"venue"
},
  "geometry": {"coordinates":[9.740337,49.108578],"type":"Point"}
}