{
  "type": "Feature",
  "properties": {
    "iso:country":"DE",
    "sg:address":"Wartburgstr. 1",
    "sg:city":"Fulda",
    "sg:phone":"+49 661/42434",
    "sg:postcode":"36043",
    "sg:province":"Hessen",
    "wof:name":"Ev. Pfarramt Bronnzell",
    "wof:placetype":"venue"
},
  "geometry": {"coordinates":[9.6845111847,50.5186691284],"type":"Point"}
}