{
  "type": "Feature",
  "properties": {
    "iso:country":"DE",
    "sg:address":"Hirtenweg 6",
    "sg:city":"C\u00f6lbe",
    "sg:phone":"+49 6427/8607",
    "sg:postcode":"35091",
    "sg:province":"Hessen",
    "wof:name":"Wiedenbach Apparatebau Gmbh",
    "wof:placetype":"venue"
},
  "geometry": {"coordinates":[8.799854,50.878223],"type":"Point"}
}