{
  "type": "Feature",
  "properties": {
    "iso:country":"DE",
    "sg:address":"Dorfstr. 36",
    "sg:city":"Herdwangen-Sch\u00f6nach",
    "sg:phone":"+49 7557/8548",
    "sg:postcode":"88634",
    "sg:province":"Baden-W\u00fcrttemberg",
    "wof:name":"Gerhard Keller",
    "wof:placetype":"venue"
},
  "geometry": {"coordinates":[9.1730976105,47.862701416],"type":"Point"}
}