{
  "type": "Feature",
  "properties": {
    "iso:country":"DE",
    "sg:address":"Lange Hecke 8",
    "sg:city":"Salzgitter",
    "sg:postcode":"38239",
    "sg:province":"Niedersachsen",
    "wof:name":"Beauty Trend Gmbh",
    "wof:placetype":"venue"
},
  "geometry": {"coordinates":[10.4629669189,52.1925849915],"type":"Point"}
}