{
  "type": "Feature",
  "properties": {
    "iso:country":"DE",
    "sg:address":"Thermalbadstr. 12",
    "sg:city":"Bad Griesbach",
    "sg:phone":"+49 8532/8923",
    "sg:postcode":"94086",
    "sg:province":"Bayern",
    "wof:name":"A. Pflieger",
    "wof:placetype":"venue"
},
  "geometry": {"coordinates":[13.1869783401,48.4283561707],"type":"Point"}
}