{
  "type": "Feature",
  "properties": {
    "iso:country":"DE",
    "sg:address":"Bergstr. 28A",
    "sg:city":"Walsrode",
    "sg:phone":"+49 5161/3091",
    "sg:postcode":"29664",
    "sg:province":"Niedersachsen",
    "wof:name":"Ralf Erbar Rechtsanwalt",
    "wof:placetype":"venue"
},
  "geometry": {"coordinates":[9.5868549347,52.8653793335],"type":"Point"}
}