{
  "type": "Feature",
  "properties": {
    "iso:country":"DE",
    "sg:address":"Marktplatz 1",
    "sg:city":"Nordenham",
    "sg:postcode":"26954",
    "sg:province":"Niedersachsen",
    "wof:name":"Ms Volkers Schiffahrts Gmbh & Co. Kg",
    "wof:placetype":"venue"
},
  "geometry": {"coordinates":[8.4834537506,53.4859542847],"type":"Point"}
}