{
  "type": "Feature",
  "properties": {
    "iso:country":"DE",
    "sg:address":"Elbstr. 14",
    "sg:city":"Sch\u00f6nebeck",
    "sg:phone":"+49 3928/404144",
    "sg:postcode":"39218",
    "sg:province":"Sachsen-Anhalt",
    "wof:name":"Dr. Med. Klaus Willmann",
    "wof:placetype":"venue"
},
  "geometry": {"coordinates":[11.73925,52.022991],"type":"Point"}
}