{
  "type": "Feature",
  "properties": {
    "iso:country":"DE",
    "sg:address":"Holzwarthstr. 23",
    "sg:city":"Dornhan",
    "sg:phone":"+49 7455/2315",
    "sg:postcode":"72175",
    "sg:province":"Baden-W\u00fcrttemberg",
    "wof:name":"Albert Kaufmann Natursteinwerkstatt",
    "wof:placetype":"venue"
},
  "geometry": {"coordinates":[8.5092992783,48.3534088135],"type":"Point"}
}