{
  "type": "Feature",
  "properties": {
    "iso:country":"DE",
    "sg:address":"N\u00f6rerstr. 26",
    "sg:city":"Deggendorf",
    "sg:phone":"+49 991/5877",
    "sg:postcode":"94469",
    "sg:province":"Bayern",
    "wof:name":"D. Schnarrer",
    "wof:placetype":"venue"
},
  "geometry": {"coordinates":[12.9704875946,48.8338813782],"type":"Point"}
}