{
  "type": "Feature",
  "properties": {
    "iso:country":"DE",
    "sg:address":"Hanauer Landstr. 136",
    "sg:city":"Frankfurt",
    "sg:phone":"+49 69/9043960",
    "sg:postcode":"60314",
    "sg:province":"Hessen",
    "wof:name":"Isl Marketing Deutschland Ag",
    "wof:placetype":"venue"
},
  "geometry": {"coordinates":[8.7134723663,50.1118583679],"type":"Point"}
}