{
  "type": "Feature",
  "properties": {
    "iso:country":"DE",
    "sg:address":"Am Kaufland 2",
    "sg:city":"L\u00fcbbenau",
    "sg:phone":"+49 3542/45231",
    "sg:postcode":"03222",
    "sg:province":"Brandenburg",
    "wof:name":"Andreas Moczko Die Apotheke Im Kaufland",
    "wof:placetype":"venue"
},
  "geometry": {"coordinates":[13.938425,51.867573],"type":"Point"}
}