{
  "type": "Feature",
  "properties": {
    "iso:country":"DE",
    "sg:address":"Am Hunzel",
    "sg:city":"Singhofen",
    "sg:postcode":"56379",
    "sg:province":"Rheinland-Pfalz",
    "wof:name":"Ch. Ridder Gmbh & Co. Kg",
    "wof:placetype":"venue"
},
  "geometry": {"coordinates":[7.8357801437,50.279083252],"type":"Point"}
}