{
  "type": "Feature",
  "properties": {
    "iso:country":"DE",
    "sg:address":"Breslaustr. 32",
    "sg:city":"Hof",
    "sg:phone":"+49 9281/44279",
    "sg:postcode":"95028",
    "sg:province":"Bayern",
    "wof:name":"N. Gebelein",
    "wof:placetype":"venue"
},
  "geometry": {"coordinates":[11.9350633621,50.3159942627],"type":"Point"}
}