{
  "type": "Feature",
  "properties": {
    "iso:country":"DE",
    "sg:address":"Rotehaus 1",
    "sg:city":"Wangerland",
    "sg:phone":"+49 4463/452",
    "sg:postcode":"26434",
    "sg:province":"Niedersachsen",
    "wof:name":"Manfred L\u00fcbben",
    "wof:placetype":"venue"
},
  "geometry": {"coordinates":[7.91605,53.677055],"type":"Point"}
}