{
  "type": "Feature",
  "properties": {
    "iso:country":"DE",
    "sg:address":"Luckenberger Str. 12",
    "sg:city":"Brandenburg",
    "sg:phone":"+49 3381/521513",
    "sg:postcode":"14770",
    "sg:province":"Brandenburg",
    "wof:name":"Kr\u00fcger Verwaltungs-gmbh",
    "wof:placetype":"venue"
},
  "geometry": {"coordinates":[12.548344,52.408676],"type":"Point"}
}