{
  "type": "Feature",
  "properties": {
    "iso:country":"DE",
    "sg:address":"N\u00fc\u00dfleinweg 33",
    "sg:city":"N\u00fcrnberg",
    "sg:phone":"+49 5207/91670",
    "sg:postcode":"90455",
    "sg:province":"Bayern",
    "wof:name":"M-form Gmbh",
    "wof:placetype":"venue"
},
  "geometry": {"coordinates":[8.61599,51.884033],"type":"Point"}
}