{
  "type": "Feature",
  "properties": {
    "iso:country":"DE",
    "sg:address":"Heidestr. 131",
    "sg:city":"Frankfurt",
    "sg:phone":"+49 69/455276",
    "sg:postcode":"60385",
    "sg:province":"Hessen",
    "wof:name":"Farnung & Leue Immobilienmakler Gmbh",
    "wof:placetype":"venue"
},
  "geometry": {"coordinates":[8.7073411942,50.1275939941],"type":"Point"}
}