{
  "type": "Feature",
  "properties": {
    "iso:country":"DE",
    "sg:address":"Hertingerstr. 187",
    "sg:city":"Unna",
    "sg:phone":"+49 2303/80677",
    "sg:postcode":"59427",
    "sg:province":"Nordrhein-Westfalen",
    "wof:name":"Diethelm Schr\u00f6er Werbegeschenke",
    "wof:placetype":"venue"
},
  "geometry": {"coordinates":[7.6655550003,51.512752533],"type":"Point"}
}