{
  "type": "Feature",
  "properties": {
    "iso:country":"DE",
    "sg:address":"Suevenstr. 14",
    "sg:city":"K\u00f6ln",
    "sg:phone":"+49 221/881798",
    "sg:postcode":"50679",
    "sg:province":"Nordrhein-Westfalen",
    "wof:name":"Josef Hegener",
    "wof:placetype":"venue"
},
  "geometry": {"coordinates":[6.9788098335,50.932182312],"type":"Point"}
}