{
  "type": "Feature",
  "properties": {
    "iso:country":"DE",
    "sg:address":"Industriestr. 6",
    "sg:city":"N\u00f6rten-Hardenberg",
    "sg:phone":"+49 5503/1058",
    "sg:postcode":"37176",
    "sg:province":"Niedersachsen",
    "wof:name":"Schumacher Gmbh",
    "wof:placetype":"venue"
},
  "geometry": {"coordinates":[9.9375228882,51.6214065552],"type":"Point"}
}