{
  "type": "Feature",
  "properties": {
    "iso:country":"DE",
    "sg:address":"Hohle Gasse 6",
    "sg:city":"Bredstedt",
    "sg:phone":"+49 4671/5250",
    "sg:postcode":"25821",
    "sg:province":"Schleswig-Holstein",
    "wof:name":"Catharina Staupe",
    "wof:placetype":"venue"
},
  "geometry": {"coordinates":[8.9632987976,54.6187515259],"type":"Point"}
}