{
  "type": "Feature",
  "properties": {
    "iso:country":"DE",
    "sg:address":"Schr\u00f6derstr. 1",
    "sg:city":"Berlin",
    "sg:phone":"+49 30/2824542",
    "sg:postcode":"10115",
    "sg:province":"Berlin",
    "wof:name":"Ibsb Privates Institut F\u00fcr Bildverarbeitung Und Soft-",
    "wof:placetype":"venue"
},
  "geometry": {"coordinates":[13.3924217224,52.5300674438],"type":"Point"}
}