{
  "type": "Feature",
  "properties": {
    "iso:country":"DE",
    "sg:address":"J\u00e4gerweg 21",
    "sg:city":"Bad Wildbad",
    "sg:phone":"+49 7081/8584",
    "sg:postcode":"75323",
    "sg:province":"Baden-W\u00fcrttemberg",
    "wof:name":"Emilie Tubach",
    "wof:placetype":"venue"
},
  "geometry": {"coordinates":[8.5499973297,48.7595252991],"type":"Point"}
}