{
  "type": "Feature",
  "properties": {
    "iso:country":"DE",
    "sg:address":"Leipziger Str. 53",
    "sg:city":"Zwickau",
    "sg:postcode":"08058",
    "sg:province":"Sachsen",
    "wof:name":"I-plan Industrieberatungs Gmbh",
    "wof:placetype":"venue"
},
  "geometry": {"coordinates":[12.4925289154,50.7291107178],"type":"Point"}
}