{
  "type": "Feature",
  "properties": {
    "iso:country":"DE",
    "sg:address":"Am Bauergarten 9",
    "sg:city":"Wohlmirstedt",
    "sg:phone":"+49 34672/62880",
    "sg:postcode":"06642",
    "sg:province":"Sachsen-Anhalt",
    "wof:name":"Breitunger K\u00c4sereiernst Rumpf Gmbh",
    "wof:placetype":"venue"
},
  "geometry": {"coordinates":[11.464942,51.248436],"type":"Point"}
}