{
  "type": "Feature",
  "properties": {
    "iso:country":"DE",
    "sg:address":"Hauptstr. 21",
    "sg:city":"Burtenbach",
    "sg:phone":"+49 8285/287",
    "sg:postcode":"89349",
    "sg:province":"Bayern",
    "wof:name":"Fritz Seitz",
    "wof:placetype":"venue"
},
  "geometry": {"coordinates":[10.448619,48.341415],"type":"Point"}
}