{
  "type": "Feature",
  "properties": {
    "iso:country":"DE",
    "sg:address":"Johann-Clanze-Str. 53",
    "sg:city":"M\u00fcnchen",
    "sg:phone":"+49 89/7606840",
    "sg:postcode":"81369",
    "sg:province":"Bayern",
    "wof:name":"Helene Smola Steuerberater",
    "wof:placetype":"venue"
},
  "geometry": {"coordinates":[11.5266809464,48.1126785278],"type":"Point"}
}