{
  "type": "Feature",
  "properties": {
    "iso:country":"DE",
    "sg:address":"Wilhelmsh\u00f6her Str. 173",
    "sg:city":"Frankfurt",
    "sg:phone":"+49 69/479331",
    "sg:postcode":"60389",
    "sg:province":"Hessen",
    "wof:name":"H. Gembus",
    "wof:placetype":"venue"
},
  "geometry": {"coordinates":[8.7287778854,50.1459007263],"type":"Point"}
}