{
  "type": "Feature",
  "properties": {
    "iso:country":"DE",
    "sg:address":"Salinger Feld 26",
    "sg:city":"Witten",
    "sg:phone":"+49 2302/80466",
    "sg:postcode":"58454",
    "sg:province":"Nordrhein-Westfalen",
    "wof:name":"Fliesen D Hone Gmbh",
    "wof:placetype":"venue"
},
  "geometry": {"coordinates":[7.3815188408,51.4558029175],"type":"Point"}
}