{
  "type": "Feature",
  "properties": {
    "iso:country":"DE",
    "sg:address":"Kirchheimer Str. 42",
    "sg:city":"Schlierbach",
    "sg:phone":"+49 7021/2550",
    "sg:postcode":"73278",
    "sg:province":"Baden-W\u00fcrttemberg",
    "wof:name":"G. Und H. Lutz",
    "wof:placetype":"venue"
},
  "geometry": {"coordinates":[9.5096130371,48.6716194153],"type":"Point"}
}