{
  "type": "Feature",
  "properties": {
    "iso:country":"DE",
    "sg:address":"Bergstr. 12",
    "sg:city":"Menteroda",
    "sg:postcode":"99996",
    "sg:province":"Th\u00fcringen",
    "wof:name":"Spangenberg Gmbh",
    "wof:placetype":"venue"
},
  "geometry": {"coordinates":[10.5589933395,51.3085784912],"type":"Point"}
}