{
  "type": "Feature",
  "properties": {
    "iso:country":"DE",
    "sg:address":"K\u00fccksberg 15",
    "sg:city":"Bremen",
    "sg:postcode":"28759",
    "sg:province":"Bremen",
    "wof:name":"Hhb Baubetreuung Und Bautr\u00e4ger Gmbh & Co. Kg",
    "wof:placetype":"venue"
},
  "geometry": {"coordinates":[8.641695,53.170055],"type":"Point"}
}