{
  "type": "Feature",
  "properties": {
    "iso:country":"DE",
    "sg:address":"Almweg 3",
    "sg:city":"Brunnthal",
    "sg:phone":"+49 8102/744648",
    "sg:postcode":"85649",
    "sg:province":"Bayern",
    "wof:name":"Brun\u00dfen Informations- Technik Gmbh",
    "wof:placetype":"venue"
},
  "geometry": {"coordinates":[11.6806020737,48.0034790039],"type":"Point"}
}