{
  "type": "Feature",
  "properties": {
    "iso:country":"DE",
    "sg:address":"Hildebrandstr. 16",
    "sg:city":"M\u00fcnchen",
    "sg:phone":"+49 89/153331",
    "sg:postcode":"80637",
    "sg:province":"Bayern",
    "wof:name":"Carl K\u00f6rbler Handelsvertretungen",
    "wof:placetype":"venue"
},
  "geometry": {"coordinates":[11.5358285904,48.1706161499],"type":"Point"}
}