{
  "type": "Feature",
  "properties": {
    "iso:country":"DE",
    "sg:address":"Industriestr. 13",
    "sg:city":"Renningen",
    "sg:postcode":"71272",
    "sg:province":"Baden-W\u00fcrttemberg",
    "wof:name":"Hansel & Heininger Metalltechnik Gmbh",
    "wof:placetype":"venue"
},
  "geometry": {"coordinates":[8.921918,48.774509],"type":"Point"}
}