{
  "type": "Feature",
  "properties": {
    "iso:country":"DE",
    "sg:address":"Hockengasse 4",
    "sg:city":"W\u00e4schenbeuren",
    "sg:phone":"+49 7172/8768",
    "sg:postcode":"73116",
    "sg:province":"Baden-W\u00fcrttemberg",
    "wof:name":"Kath. Pfarramt St. Johann Ev.",
    "wof:placetype":"venue"
},
  "geometry": {"coordinates":[9.6847934723,48.7593040466],"type":"Point"}
}