{
  "type": "Feature",
  "properties": {
    "iso:country":"DE",
    "sg:address":"Goldlackweg 6",
    "sg:city":"Karlsruhe",
    "sg:phone":"+49 721/885001",
    "sg:postcode":"76199",
    "sg:province":"Baden-W\u00fcrttemberg",
    "wof:name":"Forum Meditativer Tanz, Folklore, Sakraler Tanz",
    "wof:placetype":"venue"
},
  "geometry": {"coordinates":[8.412288,48.977505],"type":"Point"}
}