{
  "type": "Feature",
  "properties": {
    "iso:country":"DE",
    "sg:address":"Haus-Berge-Str. 129",
    "sg:city":"Essen",
    "sg:phone":"+49 201/661764",
    "sg:postcode":"45356",
    "sg:province":"Nordrhein-Westfalen",
    "wof:name":"Restaurant Bei Duro",
    "wof:placetype":"venue"
},
  "geometry": {"coordinates":[6.9774022102,51.4739608765],"type":"Point"}
}