{
  "type": "Feature",
  "properties": {
    "iso:country":"DE",
    "sg:address":"Herderstr. 4",
    "sg:city":"Bensheim",
    "sg:phone":"+49 6251/73627",
    "sg:postcode":"64625",
    "sg:province":"Hessen",
    "wof:name":"Wilhelm Hechler Dipl.-dolmetscher",
    "wof:placetype":"venue"
},
  "geometry": {"coordinates":[8.624685,49.692013],"type":"Point"}
}