{
  "type": "Feature",
  "properties": {
    "iso:country":"DE",
    "sg:address":"Pliensaustr. 31",
    "sg:city":"Esslingen",
    "sg:phone":"+49 711/359641",
    "sg:postcode":"73728",
    "sg:province":"Baden-W\u00fcrttemberg",
    "wof:name":"Parkhaus Frauenstrasse Verwaltungs-gmbh",
    "wof:placetype":"venue"
},
  "geometry": {"coordinates":[9.304796,48.738945],"type":"Point"}
}