{
  "type": "Feature",
  "properties": {
    "iso:country":"DE",
    "sg:address":"Egetterstr. 7",
    "sg:city":"M\u00fcnchen",
    "sg:phone":"+49 89/5802584",
    "sg:postcode":"80689",
    "sg:province":"Bayern",
    "wof:name":"Helmut Ettmayr Architekt",
    "wof:placetype":"venue"
},
  "geometry": {"coordinates":[11.489895,48.139256],"type":"Point"}
}