{
  "type": "Feature",
  "properties": {
    "iso:country":"DE",
    "sg:address":"Andersenstr. 1",
    "sg:city":"Halle",
    "sg:phone":"+49 345/6874666",
    "sg:postcode":"06126",
    "sg:province":"Sachsen-Anhalt",
    "wof:name":"Schwarzkopf Gbr",
    "wof:placetype":"venue"
},
  "geometry": {"coordinates":[11.905789,51.479546],"type":"Point"}
}