{
  "type": "Feature",
  "properties": {
    "iso:country":"DE",
    "sg:address":"Tegernseer Str. 8",
    "sg:city":"Gmund",
    "sg:phone":"+49 8022/75832",
    "sg:postcode":"83703",
    "sg:province":"Bayern",
    "wof:name":"E. B. Glasl Innenarchitekt",
    "wof:placetype":"venue"
},
  "geometry": {"coordinates":[11.738861,47.748833],"type":"Point"}
}