{
  "type": "Feature",
  "properties": {
    "iso:country":"DE",
    "sg:address":"Clemensstr. 24",
    "sg:city":"M\u00fcnchen",
    "sg:phone":"+49 89/399408",
    "sg:postcode":"80803",
    "sg:province":"Bayern",
    "wof:name":"Helmut Trunz Komponist",
    "wof:placetype":"venue"
},
  "geometry": {"coordinates":[11.5816116333,48.1639785767],"type":"Point"}
}