{
  "type": "Feature",
  "properties": {
    "iso:country":"DE",
    "sg:address":"Holunderstr. 15",
    "sg:city":"Mannheim",
    "sg:phone":"+49 621/856222",
    "sg:postcode":"68199",
    "sg:province":"Baden-W\u00fcrttemberg",
    "wof:name":"Elke Hartmann",
    "wof:placetype":"venue"
},
  "geometry": {"coordinates":[8.485575676,49.4577827454],"type":"Point"}
}