{
  "type": "Feature",
  "properties": {
    "iso:country":"DE",
    "sg:address":"Schrannenstr. 12",
    "sg:city":"Ingolstadt",
    "sg:phone":"+49 841/9312000",
    "sg:postcode":"85049",
    "sg:province":"Bayern",
    "wof:name":"Michael Maier Rechtsanwalt",
    "wof:placetype":"venue"
},
  "geometry": {"coordinates":[11.4245042801,48.7652130127],"type":"Point"}
}