{
  "type": "Feature",
  "properties": {
    "iso:country":"DE",
    "sg:address":"Am Priemengrund 11",
    "sg:city":"Biebertal",
    "sg:phone":"+49 6446/6550",
    "sg:postcode":"35444",
    "sg:province":"Hessen",
    "wof:name":"E. Ockel Immobilienmakler",
    "wof:placetype":"venue"
},
  "geometry": {"coordinates":[8.5669460297,50.6696815491],"type":"Point"}
}