{
  "type": "Feature",
  "properties": {
    "iso:country":"DE",
    "sg:address":"Im Lahrfeld 8",
    "sg:city":"Menden",
    "sg:phone":"+49 2373/4021",
    "sg:postcode":"58706",
    "sg:province":"Nordrhein-Westfalen",
    "wof:name":"Imb Lagertechnik Bittel E. K.",
    "wof:placetype":"venue"
},
  "geometry": {"coordinates":[7.804263,51.44458],"type":"Point"}
}