{
  "type": "Feature",
  "properties": {
    "iso:country":"DE",
    "sg:address":"Rheydter Str. 36",
    "sg:city":"Grevenbroich",
    "sg:phone":"+49 2181/659065",
    "sg:postcode":"41515",
    "sg:province":"Nordrhein-Westfalen",
    "wof:name":"G\u00fcnther Hellendahl",
    "wof:placetype":"venue"
},
  "geometry": {"coordinates":[6.580654,51.091274],"type":"Point"}
}