{
  "type": "Feature",
  "properties": {
    "iso:country":"DE",
    "sg:address":"Unter der Heide 23",
    "sg:city":"Freudenberg",
    "sg:phone":"+49 2734/1402",
    "sg:postcode":"57258",
    "sg:province":"Nordrhein-Westfalen",
    "wof:name":"Hotel Landhaus Zur Heide",
    "wof:placetype":"venue"
},
  "geometry": {"coordinates":[7.9181170464,50.9191131592],"type":"Point"}
}