{
  "type": "Feature",
  "properties": {
    "iso:country":"DE",
    "sg:address":"Hofgartenstr. 10",
    "sg:city":"Sulzbach-Rosenberg",
    "sg:phone":"+49 9661/876000",
    "sg:postcode":"92237",
    "sg:province":"Bayern",
    "wof:name":"\u00d6kumenische Sozialstation Sulzbach-rosenberg Ggmbh",
    "wof:placetype":"venue"
},
  "geometry": {"coordinates":[11.745213,49.499786],"type":"Point"}
}