{
  "type": "Feature",
  "properties": {
    "iso:country":"DE",
    "sg:address":"Wald-Eck 7",
    "sg:city":"Warin",
    "sg:phone":"+49 38482/78127",
    "sg:postcode":"19417",
    "sg:province":"Mecklenburg-Vorpommern",
    "wof:name":"Ladenbau-einrichtungsbau",
    "wof:placetype":"venue"
},
  "geometry": {"coordinates":[11.695,53.792095],"type":"Point"}
}