{
  "type": "Feature",
  "properties": {
    "iso:country":"DE",
    "sg:address":"Hauptstr. 50-52",
    "sg:city":"Bielefeld",
    "sg:phone":"+49 521/412471",
    "sg:postcode":"33647",
    "sg:province":"Nordrhein-Westfalen",
    "wof:name":"Sever Aliriza",
    "wof:placetype":"venue"
},
  "geometry": {"coordinates":[8.5136241913,51.9885597229],"type":"Point"}
}