{
  "type": "Feature",
  "properties": {
    "iso:country":"DE",
    "sg:address":"Am Hang 21",
    "sg:city":"Bad Soden-Salm\u00fcnster",
    "sg:phone":"+49 6056/91553",
    "sg:postcode":"63628",
    "sg:province":"Hessen",
    "wof:name":"Michael Baron",
    "wof:placetype":"venue"
},
  "geometry": {"coordinates":[9.388054,50.288055],"type":"Point"}
}