{
  "type": "Feature",
  "properties": {
    "iso:country":"DE",
    "sg:address":"Uellendahler Str. 503",
    "sg:city":"Wuppertal",
    "sg:phone":"+49 202/700472",
    "sg:postcode":"42109",
    "sg:province":"Nordrhein-Westfalen",
    "wof:name":"Martin Jannek",
    "wof:placetype":"venue"
},
  "geometry": {"coordinates":[7.170681,51.281448],"type":"Point"}
}