{
  "type": "Feature",
  "properties": {
    "iso:country":"DE",
    "sg:address":"Lange Str. 30",
    "sg:city":"Osnabr\u00fcck",
    "sg:phone":"+49 541/82006",
    "sg:postcode":"49080",
    "sg:province":"Niedersachsen",
    "wof:name":"R. Riehmann Gmbh",
    "wof:placetype":"venue"
},
  "geometry": {"coordinates":[8.040044,52.26852],"type":"Point"}
}