{
  "type": "Feature",
  "properties": {
    "iso:country":"DE",
    "sg:address":"Beckestr. 1",
    "sg:city":"Schwerte",
    "sg:phone":"+49 2304/18112",
    "sg:postcode":"58239",
    "sg:province":"Nordrhein-Westfalen",
    "wof:name":"Eiscafe Francesco Mattiuzzi",
    "wof:placetype":"venue"
},
  "geometry": {"coordinates":[7.561181,51.442032],"type":"Point"}
}