{
  "type": "Feature",
  "properties": {
    "iso:country":"DE",
    "sg:address":"Creidlitzer Str. 82a",
    "sg:city":"Coburg",
    "sg:phone":"+49 9561/10428",
    "sg:postcode":"96450",
    "sg:province":"Bayern",
    "wof:name":"Michael Und Claudia Eck",
    "wof:placetype":"venue"
},
  "geometry": {"coordinates":[10.978858,50.232449],"type":"Point"}
}