{
  "type": "Feature",
  "properties": {
    "iso:country":"DE",
    "sg:address":"Am Altenweiher 57",
    "sg:city":"Neumarkt",
    "sg:phone":"+49 9181/21610",
    "sg:postcode":"92318",
    "sg:province":"Bayern",
    "wof:name":"Georg Und Christl Riedl",
    "wof:placetype":"venue"
},
  "geometry": {"coordinates":[11.4287719727,49.2759246826],"type":"Point"}
}