{
  "type": "Feature",
  "properties": {
    "iso:country":"DE",
    "sg:address":"Hagedornstr. 5",
    "sg:city":"Halver",
    "sg:phone":"+49 2353/2095",
    "sg:postcode":"58553",
    "sg:province":"Nordrhein-Westfalen",
    "wof:name":"Dieter Osenberg",
    "wof:placetype":"venue"
},
  "geometry": {"coordinates":[7.5062398911,51.1868057251],"type":"Point"}
}