{
  "type": "Feature",
  "properties": {
    "iso:country":"DE",
    "sg:address":"Vinzenz-Zahn-Str. 28",
    "sg:city":"Freiburg",
    "sg:phone":"+49 761/443430",
    "sg:postcode":"79111",
    "sg:province":"Baden-W\u00fcrttemberg",
    "wof:name":"Ehret Bauunternehmen Gmbh",
    "wof:placetype":"venue"
},
  "geometry": {"coordinates":[7.8082852364,47.977596283],"type":"Point"}
}