{
  "type": "Feature",
  "properties": {
    "iso:country":"DE",
    "sg:address":"L\u00f6wenstr. 50",
    "sg:city":"Offenbach",
    "sg:phone":"+49 69/8007090",
    "sg:postcode":"63067",
    "sg:province":"Hessen",
    "wof:name":"Gerhard Van Amern",
    "wof:placetype":"venue"
},
  "geometry": {"coordinates":[8.7459354401,50.1035499573],"type":"Point"}
}