{
  "type": "Feature",
  "properties": {
    "iso:country":"DE",
    "sg:address":"Forlenweg 13",
    "sg:city":"Durmersheim",
    "sg:phone":"+49 7245/89368",
    "sg:postcode":"76448",
    "sg:province":"Baden-W\u00fcrttemberg",
    "wof:name":"K. Benschitz G. Benschitz",
    "wof:placetype":"venue"
},
  "geometry": {"coordinates":[8.2841901779,48.9445533752],"type":"Point"}
}