{
  "type": "Feature",
  "properties": {
    "iso:country":"DE",
    "sg:address":"Am Hasensprung 1",
    "sg:city":"Cadolzburg",
    "sg:phone":"+49 9103/1695",
    "sg:postcode":"90556",
    "sg:province":"Bayern",
    "wof:name":"Dieter Wierzchowski Ingenieur",
    "wof:placetype":"venue"
},
  "geometry": {"coordinates":[10.8932924271,49.4598922729],"type":"Point"}
}