{
  "type": "Feature",
  "properties": {
    "iso:country":"DE",
    "sg:address":"Bayernstr. 53",
    "sg:city":"Pforzheim",
    "sg:postcode":"75177",
    "sg:province":"Baden-W\u00fcrttemberg",
    "wof:name":"Studsvik Gmbh",
    "wof:placetype":"venue"
},
  "geometry": {"coordinates":[8.695244,48.89658],"type":"Point"}
}