{
  "type": "Feature",
  "properties": {
    "iso:country":"DE",
    "sg:address":"Europaplatz 11",
    "sg:city":"Bocholt",
    "sg:phone":"+49 2871/227501",
    "sg:postcode":"46399",
    "sg:province":"Nordrhein-Westfalen",
    "wof:name":"Freudenhaus",
    "wof:placetype":"venue"
},
  "geometry": {"coordinates":[6.6119022369,51.8393630981],"type":"Point"}
}