{
  "type": "Feature",
  "properties": {
    "iso:country":"DE",
    "sg:address":"Dachsbau 4",
    "sg:city":"Prisdorf",
    "sg:phone":"+49 4101/72202",
    "sg:postcode":"25497",
    "sg:province":"Schleswig-Holstein",
    "wof:name":"S\u00f6ren Studemund",
    "wof:placetype":"venue"
},
  "geometry": {"coordinates":[9.764377594,53.6754302979],"type":"Point"}
}