{
  "type": "Feature",
  "properties": {
    "iso:country":"DE",
    "sg:address":"Am Petersberg 16",
    "sg:city":"Oberstenfeld",
    "sg:phone":"+49 7062/8576",
    "sg:postcode":"71720",
    "sg:province":"Baden-W\u00fcrttemberg",
    "wof:name":"K. Und A. Stoll",
    "wof:placetype":"venue"
},
  "geometry": {"coordinates":[9.3239498138,49.0272216797],"type":"Point"}
}