{
  "type": "Feature",
  "properties": {
    "iso:country":"DE",
    "sg:address":"Handelstr. 6",
    "sg:city":"Wuppertal",
    "sg:phone":"+49 202/662609",
    "sg:postcode":"42277",
    "sg:province":"Nordrhein-Westfalen",
    "wof:name":"I. Und N. Schremper",
    "wof:placetype":"venue"
},
  "geometry": {"coordinates":[7.219465,51.280006],"type":"Point"}
}