{
  "type": "Feature",
  "properties": {
    "iso:country":"DE",
    "sg:address":"Schwarzwaldstr. 6",
    "sg:city":"Elzach",
    "sg:phone":"+49 7682/6070",
    "sg:postcode":"79215",
    "sg:province":"Baden-W\u00fcrttemberg",
    "wof:name":"Center Court Elzach Gmbh",
    "wof:placetype":"venue"
},
  "geometry": {"coordinates":[8.0640716553,48.1647491455],"type":"Point"}
}