{
  "type": "Feature",
  "properties": {
    "iso:country":"DE",
    "sg:address":"Grupellostr. 8",
    "sg:city":"D\u00fcsseldorf",
    "sg:phone":"+49 211/364365",
    "sg:postcode":"40210",
    "sg:province":"Nordrhein-Westfalen",
    "wof:name":"Le Clou",
    "wof:placetype":"venue"
},
  "geometry": {"coordinates":[6.7862591743,51.2211341858],"type":"Point"}
}