{
  "type": "Feature",
  "properties": {
    "iso:country":"DE",
    "sg:address":"Liliencronstr. 2 a",
    "sg:city":"Kellinghusen",
    "sg:phone":"+49 4822/950146",
    "sg:postcode":"25548",
    "sg:province":"Schleswig-Holstein",
    "wof:name":"Peter Wiese",
    "wof:placetype":"venue"
},
  "geometry": {"coordinates":[9.7347745895,53.9481964111],"type":"Point"}
}