{
  "type": "Feature",
  "properties": {
    "iso:country":"DE",
    "sg:address":"Eltz Str. 59",
    "sg:city":"Trier",
    "sg:phone":"+49 651/9960190",
    "sg:postcode":"54293",
    "sg:province":"Rheinland-Pfalz",
    "wof:name":"Fleischereibedarf Irmen, Trier",
    "wof:placetype":"venue"
},
  "geometry": {"coordinates":[6.6879649162,49.795463562],"type":"Point"}
}