{
  "type": "Feature",
  "properties": {
    "iso:country":"DE",
    "sg:address":"Talstr. 21",
    "sg:city":"Selb",
    "sg:phone":"+49 9287/70944",
    "sg:postcode":"95100",
    "sg:province":"Bayern",
    "wof:name":"Alfred Sommer",
    "wof:placetype":"venue"
},
  "geometry": {"coordinates":[12.1295928955,50.1684265137],"type":"Point"}
}