{
  "type": "Feature",
  "properties": {
    "iso:country":"DE",
    "sg:address":"Industriestr. 40",
    "sg:city":"H\u00f6velhof",
    "sg:phone":"+49 5257/98570",
    "sg:postcode":"33161",
    "sg:province":"Nordrhein-Westfalen",
    "wof:name":"R. Berenbrinker Gmbh",
    "wof:placetype":"venue"
},
  "geometry": {"coordinates":[8.651068,51.830933],"type":"Point"}
}