{
  "type": "Feature",
  "properties": {
    "iso:country":"DE",
    "sg:address":"Hauptstr. 96",
    "sg:city":"Bad Saulgau",
    "sg:phone":"+49 7581/51377",
    "sg:postcode":"88348",
    "sg:province":"Baden-W\u00fcrttemberg",
    "wof:name":"Addi-mode",
    "wof:placetype":"venue"
},
  "geometry": {"coordinates":[9.501603,48.015556],"type":"Point"}
}