{
  "type": "Feature",
  "properties": {
    "iso:country":"DE",
    "sg:address":"Lothringer Str. 31",
    "sg:city":"Saarlouis",
    "sg:phone":"+49 6831/43937",
    "sg:postcode":"66740",
    "sg:province":"Saarland",
    "wof:name":"Lidl Gmbh & Co. Kg",
    "wof:placetype":"venue"
},
  "geometry": {"coordinates":[6.7493672371,49.3111419678],"type":"Point"}
}