{
  "type": "Feature",
  "properties": {
    "iso:country":"DE",
    "sg:address":"Bramscher Str. 1",
    "sg:city":"Westerkappeln",
    "sg:phone":"+49 5404/3329",
    "sg:postcode":"49492",
    "sg:province":"Nordrhein-Westfalen",
    "wof:name":"Klaus-dieter Hennig",
    "wof:placetype":"venue"
},
  "geometry": {"coordinates":[7.877114,52.316517],"type":"Point"}
}