{
  "type": "Feature",
  "properties": {
    "iso:country":"DE",
    "sg:address":"Postfach 240",
    "sg:city":"Quierschied",
    "sg:postcode":"66282",
    "sg:province":"Saarland",
    "wof:name":"Mehrzweckhalle Fischbach-camphausen",
    "wof:placetype":"venue"
},
  "geometry": {"coordinates":[7.0527,49.326176],"type":"Point"}
}