{
  "type": "Feature",
  "properties": {
    "iso:country":"DE",
    "sg:address":"Contrescarpe 47-48",
    "sg:city":"Bremen",
    "sg:phone":"+49 421/321751",
    "sg:postcode":"28195",
    "sg:province":"Bremen",
    "wof:name":"Sch\u00fctte Richter Und Partner Rechtsanw\u00e4lte",
    "wof:placetype":"venue"
},
  "geometry": {"coordinates":[8.8143081665,53.0776252747],"type":"Point"}
}