{
  "type": "Feature",
  "properties": {
    "iso:country":"DE",
    "sg:address":"Ilzham 5",
    "sg:city":"Obing",
    "sg:phone":"+49 8624/2459",
    "sg:postcode":"83119",
    "sg:province":"Bayern",
    "wof:name":"Rupert Obermeier Masseur",
    "wof:placetype":"venue"
},
  "geometry": {"coordinates":[12.379483,48.004074],"type":"Point"}
}