{
  "type": "Feature",
  "properties": {
    "iso:country":"DE",
    "sg:address":"Hauptstr. 51",
    "sg:city":"R\u00f6srath",
    "sg:phone":"+49 2205/81019",
    "sg:postcode":"51503",
    "sg:province":"Nordrhein-Westfalen",
    "wof:name":"Sigrid Kronen-barth Praxis F\u00fcr Krankengymnastik",
    "wof:placetype":"venue"
},
  "geometry": {"coordinates":[7.182893,50.897415],"type":"Point"}
}