{
  "type": "Feature",
  "properties": {
    "iso:country":"DE",
    "sg:address":"Hauptstr. 30",
    "sg:city":"Bar\u00dfel",
    "sg:phone":"+49 4499/2810",
    "sg:postcode":"26676",
    "sg:province":"Niedersachsen",
    "wof:name":"Markant",
    "wof:placetype":"venue"
},
  "geometry": {"coordinates":[7.7132878304,53.152759552],"type":"Point"}
}