{
  "type": "Feature",
  "properties": {
    "iso:country":"DE",
    "sg:address":"Parkstr. 53",
    "sg:city":"Rostock",
    "sg:phone":"+49 381/51394",
    "sg:postcode":"18119",
    "sg:province":"Mecklenburg-Vorpommern",
    "wof:name":"Antaris Seetouristik Und Wassersport Gmbh",
    "wof:placetype":"venue"
},
  "geometry": {"coordinates":[12.0583753586,54.1757965088],"type":"Point"}
}