{
  "type": "Feature",
  "properties": {
    "iso:country":"DE",
    "sg:address":"Martinstr. 17",
    "sg:city":"Blaustein",
    "sg:phone":"+49 7304/7048",
    "sg:postcode":"89134",
    "sg:province":"Baden-W\u00fcrttemberg",
    "wof:name":"Joachim Wild Industrievertretungen Gmbh",
    "wof:placetype":"venue"
},
  "geometry": {"coordinates":[9.9203853607,48.4166259766],"type":"Point"}
}