{
  "type": "Feature",
  "properties": {
    "iso:country":"DE",
    "sg:address":"Jasperalle 7",
    "sg:city":"Braunschweig",
    "sg:phone":"+49 531",
    "sg:postcode":"38102",
    "sg:province":"Niedersachsen",
    "wof:name":"Personalagentur",
    "wof:placetype":"venue"
},
  "geometry": {"coordinates":[10.536221,52.267151],"type":"Point"}
}