{
  "type": "Feature",
  "properties": {
    "iso:country":"DE",
    "sg:address":"Domstr. 9",
    "sg:city":"G\u00fcstrow",
    "sg:phone":"+49 3843/682239",
    "sg:postcode":"18273",
    "sg:province":"Mecklenburg-Vorpommern",
    "wof:name":"Feilert Und Lindtner Notarinnen",
    "wof:placetype":"venue"
},
  "geometry": {"coordinates":[12.1752233505,53.7913284302],"type":"Point"}
}