{
  "type": "Feature",
  "properties": {
    "iso:country":"DE",
    "sg:address":"Ulrichstr. 11",
    "sg:city":"Neustadt",
    "sg:phone":"+49 9444/97095",
    "sg:postcode":"93333",
    "sg:province":"Bayern",
    "wof:name":"Telekommunikation Schirmeister",
    "wof:placetype":"venue"
},
  "geometry": {"coordinates":[11.7644510269,48.8063964844],"type":"Point"}
}