{
  "type": "Feature",
  "properties": {
    "iso:country":"DE",
    "sg:address":"Ewaldstr. 77",
    "sg:city":"Oer-Erkenschwick",
    "sg:phone":"+49 2368/6704",
    "sg:postcode":"45739",
    "sg:province":"Nordrhein-Westfalen",
    "wof:name":"Einhorn-apotheke Uta L\u00fccke E. Kfr.",
    "wof:placetype":"venue"
},
  "geometry": {"coordinates":[7.278281,51.641792],"type":"Point"}
}