{
  "type": "Feature",
  "properties": {
    "iso:country":"DE",
    "sg:address":"Gr\u00fcnwalder Str. 145",
    "sg:city":"M\u00fcnchen",
    "sg:phone":"+49 89/64281830",
    "sg:postcode":"81547",
    "sg:province":"Bayern",
    "wof:name":"Primavera Brillen- Fassungen Gmbh",
    "wof:placetype":"venue"
},
  "geometry": {"coordinates":[11.5655126572,48.0988998413],"type":"Point"}
}