{
  "type": "Feature",
  "properties": {
    "iso:country":"DE",
    "sg:address":"Tunnelstr. 12",
    "sg:city":"Stuttgart",
    "sg:phone":"+49 711/858063",
    "sg:postcode":"70469",
    "sg:province":"Baden-W\u00fcrttemberg",
    "wof:name":"Anadolo",
    "wof:placetype":"venue"
},
  "geometry": {"coordinates":[9.1705904007,48.8116760254],"type":"Point"}
}