{
  "type": "Feature",
  "properties": {
    "iso:country":"DE",
    "sg:address":"Sophienh\u00f6he 1",
    "sg:city":"Kerpen",
    "sg:postcode":"50171",
    "sg:province":"Nordrhein-Westfalen",
    "wof:name":"Badenia Wohn & Gewerbe- Industriebautr\u00e4ger Ges. F\u00fcr",
    "wof:placetype":"venue"
},
  "geometry": {"coordinates":[6.6288781166,50.8332595825],"type":"Point"}
}