{
  "type": "Feature",
  "properties": {
    "iso:country":"DE",
    "sg:address":"Puscherstr. 4",
    "sg:city":"N\u00fcrnberg",
    "sg:phone":"+49 911/5206560",
    "sg:postcode":"90411",
    "sg:province":"Bayern",
    "wof:name":"Dach U Ger\u00dcst Weidmann Gmbh",
    "wof:placetype":"venue"
},
  "geometry": {"coordinates":[11.124205,49.482647],"type":"Point"}
}