{
  "type": "Feature",
  "properties": {
    "iso:country":"DE",
    "sg:address":"Georg-August-Zinn-Str. 21",
    "sg:city":"Gro\u00df-Umstadt",
    "sg:phone":"+49 6078/3464",
    "sg:postcode":"64823",
    "sg:province":"Hessen",
    "wof:name":"Gardinenhaus Karl Spamer",
    "wof:placetype":"venue"
},
  "geometry": {"coordinates":[8.9303026199,49.8650665283],"type":"Point"}
}