{
  "type": "Feature",
  "properties": {
    "iso:country":"DE",
    "sg:address":"Richsteiner Str. 1",
    "sg:city":"Bad Berleburg",
    "sg:phone":"+49 2755/383",
    "sg:postcode":"57319",
    "sg:province":"Nordrhein-Westfalen",
    "wof:name":"Albrecht Duchardt Gmbh",
    "wof:placetype":"venue"
},
  "geometry": {"coordinates":[8.459221,50.987396],"type":"Point"}
}