{
  "type": "Feature",
  "properties": {
    "iso:country":"DE",
    "sg:address":"Schlo\u00dfstr. 88",
    "sg:city":"Hamburg",
    "sg:phone":"+49 40/6524828",
    "sg:postcode":"22041",
    "sg:province":"Hamburg",
    "wof:name":"Gert Wegerich Steuerberater",
    "wof:placetype":"venue"
},
  "geometry": {"coordinates":[10.0731344223,53.5721893311],"type":"Point"}
}