{
  "type": "Feature",
  "properties": {
    "iso:country":"DE",
    "sg:address":"Eimsb\u00fctteler Str. 26",
    "sg:city":"Hamburg",
    "sg:phone":"+49 40/434349",
    "sg:postcode":"22769",
    "sg:province":"Hamburg",
    "wof:name":"Hobusch Gmbh & Co. Kg",
    "wof:placetype":"venue"
},
  "geometry": {"coordinates":[9.9563827515,53.5653877258],"type":"Point"}
}