{
  "type": "Feature",
  "properties": {
    "iso:country":"DE",
    "sg:address":"Otto-Hahn-Str 36",
    "sg:city":"Bargteheide",
    "sg:phone":"+49 4532/20520",
    "sg:postcode":"22941",
    "sg:province":"Schleswig-Holstein",
    "wof:name":"Mws Werbeagentur Gmbh",
    "wof:placetype":"venue"
},
  "geometry": {"coordinates":[10.29334,53.719727],"type":"Point"}
}