{
  "type": "Feature",
  "properties": {
    "iso:country":"DE",
    "sg:address":"Emilienstr. 67",
    "sg:city":"Remscheid",
    "sg:phone":"+49 2191/292211",
    "sg:postcode":"42853",
    "sg:province":"Nordrhein-Westfalen",
    "wof:name":"F. Pleiss Versicherung",
    "wof:placetype":"venue"
},
  "geometry": {"coordinates":[7.1773729324,51.1868972778],"type":"Point"}
}