{
  "type": "Feature",
  "properties": {
    "iso:country":"DE",
    "sg:address":"Bahnhofstr. 4",
    "sg:city":"Hamm",
    "sg:phone":"+49 2381/23846",
    "sg:postcode":"59065",
    "sg:province":"Nordrhein-Westfalen",
    "wof:name":"Westentor-apotheke",
    "wof:placetype":"venue"
},
  "geometry": {"coordinates":[7.812726,51.67981],"type":"Point"}
}