{
  "type": "Feature",
  "properties": {
    "iso:country":"DE",
    "sg:address":"Kallmer\u00f6der Str. 2",
    "sg:city":"Leinefelde",
    "sg:phone":"+49 3605/501891",
    "sg:postcode":"37327",
    "sg:province":"Th\u00fcringen",
    "wof:name":"China-restaurant",
    "wof:placetype":"venue"
},
  "geometry": {"coordinates":[10.2816896439,51.3774681091],"type":"Point"}
}