{
  "type": "Feature",
  "properties": {
    "iso:country":"DE",
    "sg:address":"Bismarckstr. 13",
    "sg:city":"Lahr",
    "sg:phone":"+49 7821/23663",
    "sg:postcode":"77933",
    "sg:province":"Baden-W\u00fcrttemberg",
    "wof:name":"B\u00e4ren",
    "wof:placetype":"venue"
},
  "geometry": {"coordinates":[7.8737440109,48.3392028809],"type":"Point"}
}