{
  "type": "Feature",
  "properties": {
    "iso:country":"DE",
    "sg:address":"Karth\u00e4user Str 24",
    "sg:city":"Trier",
    "sg:phone":"+49 651/949010",
    "sg:postcode":"54290",
    "sg:province":"Rheinland-Pfalz",
    "wof:name":"Joh. Rendenbach Jr. Gmbh & Co Kg",
    "wof:placetype":"venue"
},
  "geometry": {"coordinates":[6.639629,49.747398],"type":"Point"}
}