{
  "type": "Feature",
  "properties": {
    "iso:country":"DE",
    "sg:address":"Kettelerstr. 5",
    "sg:city":"Viernheim",
    "sg:phone":"+49 6204/912120",
    "sg:postcode":"68519",
    "sg:province":"Hessen",
    "wof:name":"Christine Lambrecht Rechtsanw\u00e4ltin",
    "wof:placetype":"venue"
},
  "geometry": {"coordinates":[8.5775260925,49.5384025574],"type":"Point"}
}