{
  "type": "Feature",
  "properties": {
    "iso:country":"DE",
    "sg:address":"Hattinger Str. 404",
    "sg:city":"Bochum",
    "sg:phone":"+49 234/472379",
    "sg:postcode":"44795",
    "sg:province":"Nordrhein-Westfalen",
    "wof:name":"Waldemar Drosd",
    "wof:placetype":"venue"
},
  "geometry": {"coordinates":[7.1923489571,51.4428024292],"type":"Point"}
}