{
  "type": "Feature",
  "properties": {
    "iso:country":"DE",
    "sg:address":"Gro\u00dfk\u00f6lnstr. 62",
    "sg:city":"Aachen",
    "sg:phone":"+49 241/36671",
    "sg:postcode":"52062",
    "sg:province":"Nordrhein-Westfalen",
    "wof:name":"Walmrath Verwaltungs- Gmbh",
    "wof:placetype":"venue"
},
  "geometry": {"coordinates":[6.0866098404,50.7774200439],"type":"Point"}
}