{
  "type": "Feature",
  "properties": {
    "iso:country":"DE",
    "sg:address":"Neukronenberger Str. 41",
    "sg:city":"Leverkusen",
    "sg:phone":"+49 2171/55001",
    "sg:postcode":"51381",
    "sg:province":"Nordrhein-Westfalen",
    "wof:name":"Uwe Nohlen",
    "wof:placetype":"venue"
},
  "geometry": {"coordinates":[7.0308389664,51.0708389282],"type":"Point"}
}