{
  "type": "Feature",
  "properties": {
    "iso:country":"DE",
    "sg:address":"Neuffenstr. 28",
    "sg:city":"Leinfelden-Echterdingen",
    "sg:phone":"+49 711/7544136",
    "sg:postcode":"70771",
    "sg:province":"Baden-W\u00fcrttemberg",
    "wof:name":"Wolfgang Naumann Anlageberater",
    "wof:placetype":"venue"
},
  "geometry": {"coordinates":[9.1175031662,48.7050361633],"type":"Point"}
}