{
  "type": "Feature",
  "properties": {
    "iso:country":"DE",
    "sg:address":"Steinbachstr. 51",
    "sg:city":"Witten",
    "sg:phone":"+49 2302/963036",
    "sg:postcode":"58453",
    "sg:province":"Nordrhein-Westfalen",
    "wof:name":"P. Gr\u00fcnschl\u00e4ger",
    "wof:placetype":"venue"
},
  "geometry": {"coordinates":[7.3810520172,51.4378013611],"type":"Point"}
}