{
  "type": "Feature",
  "properties": {
    "iso:country":"DE",
    "sg:address":"Albstr. 26",
    "sg:city":"Wendlingen",
    "sg:phone":"+49 7024/54525",
    "sg:postcode":"73240",
    "sg:province":"Baden-W\u00fcrttemberg",
    "wof:name":"Eiscafe Slis Inh. Oscar Slis",
    "wof:placetype":"venue"
},
  "geometry": {"coordinates":[9.378403,48.671696],"type":"Point"}
}