{
  "type": "Feature",
  "properties": {
    "iso:country":"DE",
    "sg:city":"Leipzig",
    "sg:postcode":"04103",
    "sg:province":"Sachsen",
    "wof:name":"Institut F\u00fcr Technische Chemie Leipzig",
    "wof:placetype":"venue"
},
  "geometry": {"coordinates":[12.385518,51.344814],"type":"Point"}
}