{
  "type": "Feature",
  "properties": {
    "iso:country":"DE",
    "sg:address":"Marktstr. 7",
    "sg:city":"Berlin",
    "sg:phone":"+49 30/2910800",
    "sg:postcode":"10317",
    "sg:province":"Berlin",
    "wof:name":"C & P Versicherungs- Und Immobilienmakler Conrad Gmbh",
    "wof:placetype":"venue"
},
  "geometry": {"coordinates":[13.4721345901,52.5045852661],"type":"Point"}
}