{
  "type": "Feature",
  "properties": {
    "iso:country":"DE",
    "sg:address":"Magdeburger Str. 16",
    "sg:city":"Ro\u00dflau",
    "sg:phone":"+49 34901/5160",
    "sg:postcode":"06862",
    "sg:province":"Sachsen-Anhalt",
    "wof:name":"Sonnen-apotheke Axel Holzgr\u00e4be",
    "wof:placetype":"venue"
},
  "geometry": {"coordinates":[12.234264,51.887604],"type":"Point"}
}