{
  "type": "Feature",
  "properties": {
    "iso:country":"DE",
    "sg:address":"Markstr. 383",
    "sg:city":"Bochum",
    "sg:phone":"+49 234/9470295",
    "sg:postcode":"44795",
    "sg:province":"Nordrhein-Westfalen",
    "wof:name":"Am Steinknapp",
    "wof:placetype":"venue"
},
  "geometry": {"coordinates":[7.2186322212,51.4434890747],"type":"Point"}
}