{
  "type": "Feature",
  "properties": {
    "iso:country":"DE",
    "sg:address":"H\u00f6veler Ring 14",
    "sg:city":"Dinklage",
    "sg:phone":"+49 4944/3978287",
    "sg:postcode":"49413",
    "sg:province":"Niedersachsen",
    "wof:name":"Kowa Holzbearbeitung Gmbh",
    "wof:placetype":"venue"
},
  "geometry": {"coordinates":[8.1219244003,52.6762886047],"type":"Point"}
}