{
  "type": "Feature",
  "properties": {
    "iso:country":"DE",
    "sg:address":"Hoverkampstr. 19",
    "sg:city":"Nettetal",
    "sg:phone":"+49 2153/951677",
    "sg:postcode":"41334",
    "sg:province":"Nordrhein-Westfalen",
    "wof:name":"Hans J. Caelers",
    "wof:placetype":"venue"
},
  "geometry": {"coordinates":[6.279493,51.305656],"type":"Point"}
}