{
  "type": "Feature",
  "properties": {
    "iso:country":"DE",
    "sg:address":"Max-Planck-Str. 31",
    "sg:city":"Schramberg",
    "sg:phone":"+49 4974/2297040",
    "sg:postcode":"78713",
    "sg:province":"Baden-W\u00fcrttemberg",
    "wof:name":"A + B Werbeagentur Gmbh / Gwa",
    "wof:placetype":"venue"
},
  "geometry": {"coordinates":[8.426923,48.230736],"type":"Point"}
}