{
  "type": "Feature",
  "properties": {
    "iso:country":"DE",
    "sg:address":"Zwerenberger Str. 29",
    "sg:city":"Neuweiler",
    "sg:phone":"+49 7055/1361",
    "sg:postcode":"75389",
    "sg:province":"Baden-W\u00fcrttemberg",
    "wof:name":"David Traub",
    "wof:placetype":"venue"
},
  "geometry": {"coordinates":[8.608406,48.63139],"type":"Point"}
}