{
  "type": "Feature",
  "properties": {
    "iso:country":"DE",
    "sg:address":"Pr\u00f6llerstr. 18",
    "sg:city":"Dingolfing",
    "sg:phone":"+49 8731/71300",
    "sg:postcode":"84130",
    "sg:province":"Bayern",
    "wof:name":"Hubert Gassenhuber",
    "wof:placetype":"venue"
},
  "geometry": {"coordinates":[12.5050325394,48.6391143799],"type":"Point"}
}