{
  "type": "Feature",
  "properties": {
    "iso:country":"DE",
    "sg:address":"Am Zehentstadl 11",
    "sg:city":"Forstern",
    "sg:phone":"+49 8124/7667",
    "sg:postcode":"85659",
    "sg:province":"Bayern",
    "wof:name":"Georg Els Rechtsanwalt",
    "wof:placetype":"venue"
},
  "geometry": {"coordinates":[11.9766693115,48.1869316101],"type":"Point"}
}