{
  "type": "Feature",
  "properties": {
    "iso:country":"DE",
    "sg:address":"Niederro\u00dflaer Str. 1",
    "sg:city":"Apolda",
    "sg:phone":"+49 3644/553099",
    "sg:postcode":"99510",
    "sg:province":"Th\u00fcringen",
    "wof:name":"Apollo Laborbau Gmbh",
    "wof:placetype":"venue"
},
  "geometry": {"coordinates":[11.5069713593,51.0275535583],"type":"Point"}
}