{
  "type": "Feature",
  "properties": {
    "iso:country":"DE",
    "sg:address":"Lindenweg 14",
    "sg:city":"Donaueschingen",
    "sg:phone":"+49 7705/1359",
    "sg:postcode":"78166",
    "sg:province":"Baden-W\u00fcrttemberg",
    "wof:name":"Peter Schneider",
    "wof:placetype":"venue"
},
  "geometry": {"coordinates":[8.4195480347,47.9744606018],"type":"Point"}
}