{
  "type": "Feature",
  "properties": {
    "iso:country":"DE",
    "sg:address":"Kaiserstr. 183",
    "sg:city":"Karlsruhe",
    "sg:phone":"+49 4972/1913470",
    "sg:postcode":"76133",
    "sg:province":"Baden-W\u00fcrttemberg",
    "wof:name":"Fmm Gmbh",
    "wof:placetype":"venue"
},
  "geometry": {"coordinates":[8.399001,49.009689],"type":"Point"}
}