{
  "type": "Feature",
  "properties": {
    "iso:country":"DE",
    "sg:address":"G\u00e4rtnerweg 12",
    "sg:city":"Kelkheim",
    "sg:phone":"+49 6174/964796",
    "sg:postcode":"65779",
    "sg:province":"Hessen",
    "wof:name":"Ralf Poschmann",
    "wof:placetype":"venue"
},
  "geometry": {"coordinates":[8.4016494751,50.1746406555],"type":"Point"}
}