{
  "type": "Feature",
  "properties": {
    "iso:country":"DE",
    "sg:address":"Friedrichstr. 31",
    "sg:city":"Kappel-Grafenhausen",
    "sg:phone":"+49 7822/61876",
    "sg:postcode":"77966",
    "sg:province":"Baden-W\u00fcrttemberg",
    "wof:name":"Iss Edv & It Systemhaus Gmbh",
    "wof:placetype":"venue"
},
  "geometry": {"coordinates":[7.774114,48.286022],"type":"Point"}
}