{
  "type": "Feature",
  "properties": {
    "iso:country":"DE",
    "sg:address":"Petersbergstr. 10",
    "sg:city":"Wesseling",
    "sg:phone":"+49 2236/83338",
    "sg:postcode":"50389",
    "sg:province":"Nordrhein-Westfalen",
    "wof:name":"Kes Kappes Estrich Systeme Gmbh",
    "wof:placetype":"venue"
},
  "geometry": {"coordinates":[6.9850149155,50.8135910034],"type":"Point"}
}