{
  "type": "Feature",
  "properties": {
    "iso:country":"DE",
    "sg:address":"Zeuggasse 7",
    "sg:city":"Augsburg",
    "sg:phone":"+49 821/345550",
    "sg:postcode":"86150",
    "sg:province":"Bayern",
    "wof:name":"R\u00f6der Und Koch Notare",
    "wof:placetype":"venue"
},
  "geometry": {"coordinates":[10.8962583542,48.365852356],"type":"Point"}
}