{
  "type": "Feature",
  "properties": {
    "iso:country":"DE",
    "sg:address":"Am Wolfshof 2",
    "sg:city":"Bad Honnef",
    "sg:phone":"+49 2224/76949",
    "sg:postcode":"53604",
    "sg:province":"Nordrhein-Westfalen",
    "wof:name":"W. Wiedner",
    "wof:placetype":"venue"
},
  "geometry": {"coordinates":[7.2232708931,50.6424446106],"type":"Point"}
}