{
  "type": "Feature",
  "properties": {
    "iso:country":"DE",
    "sg:address":"Wiesenweg 7",
    "sg:city":"Henstedt-Ulzburg",
    "sg:phone":"+49 4193/998000",
    "sg:postcode":"24558",
    "sg:province":"Schleswig-Holstein",
    "wof:name":"Funke Sechste Verwaltungsgesellschaft Mbh",
    "wof:placetype":"venue"
},
  "geometry": {"coordinates":[9.9877786636,53.7931861877],"type":"Point"}
}