{
  "type": "Feature",
  "properties": {
    "iso:country":"DE",
    "sg:address":"R\u00f6delheimer Str. 8",
    "sg:city":"Eschborn",
    "sg:phone":"+49 6196/946874",
    "sg:postcode":"65760",
    "sg:province":"Hessen",
    "wof:name":"Polis Projekte Gmbh",
    "wof:placetype":"venue"
},
  "geometry": {"coordinates":[8.574709,50.143406],"type":"Point"}
}