{
  "type": "Feature",
  "properties": {
    "iso:country":"DE",
    "sg:address":"Dorfstr. 9",
    "sg:city":"Steinh\u00f6fel",
    "sg:phone":"+49 33334/496",
    "sg:postcode":"16278",
    "sg:province":"Brandenburg",
    "wof:name":"Martin Schulze",
    "wof:placetype":"venue"
},
  "geometry": {"coordinates":[14.00036,53.016426],"type":"Point"}
}