{
  "type": "Feature",
  "properties": {
    "iso:country":"DE",
    "sg:address":"Westendstr 28",
    "sg:city":"Frankfurt",
    "sg:phone":"+49 69/298070",
    "sg:postcode":"60325",
    "sg:province":"Hessen",
    "wof:name":"Bil Gt Holding (deutschland) Gmbh",
    "wof:placetype":"venue"
},
  "geometry": {"coordinates":[8.681624,50.117531],"type":"Point"}
}