{
  "type": "Feature",
  "properties": {
    "iso:country":"DE",
    "sg:address":"Marktstr. 17",
    "sg:city":"St. Leon-Rot",
    "sg:phone":"+49 6227/59617",
    "sg:postcode":"68789",
    "sg:province":"Baden-W\u00fcrttemberg",
    "wof:name":"Otto Brecht",
    "wof:placetype":"venue"
},
  "geometry": {"coordinates":[8.602906,49.265381],"type":"Point"}
}