{
  "type": "Feature",
  "properties": {
    "iso:country":"DE",
    "sg:address":"Bockenheimer Landstr. 98-100",
    "sg:city":"Frankfurt",
    "sg:postcode":"60323",
    "sg:province":"Hessen",
    "wof:name":"Ptl Zweiundzwanzigste Verm\u00f6gensverwaltungsges. Mbh",
    "wof:placetype":"venue"
},
  "geometry": {"coordinates":[8.6583557129,50.1195335388],"type":"Point"}
}