{
  "type": "Feature",
  "properties": {
    "iso:country":"DE",
    "sg:address":"Hauptstr. 105",
    "sg:city":"Rellingen",
    "sg:postcode":"25462",
    "sg:province":"Schleswig-Holstein",
    "wof:name":"Dieter Burmester E. K.",
    "wof:placetype":"venue"
},
  "geometry": {"coordinates":[9.8231573105,53.6547088623],"type":"Point"}
}