{
  "type": "Feature",
  "properties": {
    "iso:country":"DE",
    "sg:address":"Vollbrechtstr. 10 b",
    "sg:city":"Uftrungen",
    "sg:phone":"+49 34653/7200",
    "sg:postcode":"06548",
    "sg:province":"Sachsen-Anhalt",
    "wof:name":"Agrargenossenschaft Uftrungen Eg",
    "wof:placetype":"venue"
},
  "geometry": {"coordinates":[10.98227,51.496765],"type":"Point"}
}