{
  "type": "Feature",
  "properties": {
    "iso:country":"DE",
    "sg:address":"Bergwachtstr. 8",
    "sg:city":"M\u00fcnchen",
    "sg:phone":"+49 89/3130788",
    "sg:postcode":"80995",
    "sg:province":"Bayern",
    "wof:name":"Braun Und Leupold",
    "wof:placetype":"venue"
},
  "geometry": {"coordinates":[11.5293245316,48.2111625671],"type":"Point"}
}