{
  "type": "Feature",
  "properties": {
    "iso:country":"DE",
    "sg:address":"Kapellenstr. 16",
    "sg:city":"Medebach",
    "sg:phone":"+49 2982/3276",
    "sg:postcode":"59964",
    "sg:province":"Nordrhein-Westfalen",
    "wof:name":"Rosenthal",
    "wof:placetype":"venue"
},
  "geometry": {"coordinates":[8.7071390152,51.1975479126],"type":"Point"}
}