{
  "type": "Feature",
  "properties": {
    "iso:country":"DE",
    "sg:address":"Rendsburger Str. 8",
    "sg:city":"N\u00fcrnberg",
    "sg:phone":"+49 911/311528",
    "sg:postcode":"90427",
    "sg:province":"Bayern",
    "wof:name":"Klaus W\u00f6rnlein",
    "wof:placetype":"venue"
},
  "geometry": {"coordinates":[11.0310735703,49.4744033813],"type":"Point"}
}