{
  "type": "Feature",
  "properties": {
    "iso:country":"DE",
    "sg:address":"Hindenburgstr. 10",
    "sg:city":"Bad Liebenzell",
    "sg:phone":"+49 7052/2001",
    "sg:postcode":"75378",
    "sg:province":"Baden-W\u00fcrttemberg",
    "wof:name":"Susanne Rauch Rechtsanw\u00e4ltin",
    "wof:placetype":"venue"
},
  "geometry": {"coordinates":[8.7306251526,48.7758026123],"type":"Point"}
}