{
  "type": "Feature",
  "properties": {
    "iso:country":"DE",
    "sg:address":"M\u00fchlbachgasse 1",
    "sg:city":"Dingolfing",
    "sg:phone":"+49 8731/2078",
    "sg:postcode":"84130",
    "sg:province":"Bayern",
    "wof:name":"W. Leidl",
    "wof:placetype":"venue"
},
  "geometry": {"coordinates":[12.4952926636,48.6313514709],"type":"Point"}
}