{
  "type": "Feature",
  "properties": {
    "iso:country":"DE",
    "sg:address":"Am Schild 13",
    "sg:city":"Allstedt",
    "sg:phone":"+49 34652/330",
    "sg:postcode":"06542",
    "sg:province":"Sachsen-Anhalt",
    "wof:name":"Herbert Esther",
    "wof:placetype":"venue"
},
  "geometry": {"coordinates":[11.388835,51.4025],"type":"Point"}
}