{
  "type": "Feature",
  "properties": {
    "iso:country":"DE",
    "sg:address":"Tulpenstr. 13",
    "sg:city":"Oberteuringen",
    "sg:phone":"+49 7546/2213",
    "sg:postcode":"88094",
    "sg:province":"Baden-W\u00fcrttemberg",
    "wof:name":"Albert Jegler Steuerberater",
    "wof:placetype":"venue"
},
  "geometry": {"coordinates":[9.4815387726,47.7390060425],"type":"Point"}
}