{
  "type": "Feature",
  "properties": {
    "iso:country":"DE",
    "sg:address":"Dorfstr 25",
    "sg:city":"Pronstorf",
    "sg:phone":"+49 4506/282",
    "sg:postcode":"23820",
    "sg:province":"Schleswig-Holstein",
    "wof:name":"Pumpenfabrik Beyer",
    "wof:placetype":"venue"
},
  "geometry": {"coordinates":[10.5251197815,53.9530105591],"type":"Point"}
}