{
  "type": "Feature",
  "properties": {
    "iso:country":"DE",
    "sg:address":"Bruchstr. 78",
    "sg:city":"Kerken",
    "sg:phone":"+49 2833/93720",
    "sg:postcode":"47647",
    "sg:province":"Nordrhein-Westfalen",
    "wof:name":"Eilbrecht & Janssen Kg Ms Jan-willem",
    "wof:placetype":"venue"
},
  "geometry": {"coordinates":[6.412753,51.433369],"type":"Point"}
}