{
  "type": "Feature",
  "properties": {
    "iso:country":"DE",
    "sg:address":"Bahnhofstr. 7",
    "sg:city":"F\u00fcrstenau",
    "sg:phone":"+49 5901/4399",
    "sg:postcode":"49584",
    "sg:province":"Niedersachsen",
    "wof:name":"Fotostube Zientarra",
    "wof:placetype":"venue"
},
  "geometry": {"coordinates":[7.6744170189,52.5174980164],"type":"Point"}
}