{
  "type": "Feature",
  "properties": {
    "iso:country":"DE",
    "sg:address":"Auf dem Hohen Felde 3",
    "sg:city":"Kirchlinteln",
    "sg:phone":"+49 4237/1093",
    "sg:postcode":"27308",
    "sg:province":"Niedersachsen",
    "wof:name":"Richard Brandt",
    "wof:placetype":"venue"
},
  "geometry": {"coordinates":[9.423924,52.946537],"type":"Point"}
}