{
  "type": "Feature",
  "properties": {
    "iso:country":"DE",
    "sg:address":"Hauptstr. 4a",
    "sg:city":"Trebatsch",
    "sg:postcode":"15848",
    "sg:province":"Brandenburg",
    "wof:name":"M. Koschni",
    "wof:placetype":"venue"
},
  "geometry": {"coordinates":[14.17461,52.228821],"type":"Point"}
}