{
  "type": "Feature",
  "properties": {
    "iso:country":"DE",
    "sg:address":"Beuditzstr. 2 a",
    "sg:city":"Wei\u00dfenfels",
    "sg:phone":"+49 3443/302509",
    "sg:postcode":"06667",
    "sg:province":"Sachsen-Anhalt",
    "wof:name":"M. Ehrhardt",
    "wof:placetype":"venue"
},
  "geometry": {"coordinates":[11.965970993,51.1994857788],"type":"Point"}
}