{
  "type": "Feature",
  "properties": {
    "iso:country":"DE",
    "sg:address":"sonnenweg",
    "sg:city":"hamburg",
    "sg:phone":"+49 40/35711496",
    "sg:postcode":"22045",
    "sg:province":"Hamburg",
    "wof:name":"Individuelle Fernreisen Weltweit",
    "wof:placetype":"venue"
},
  "geometry": {"coordinates":[10.121723,53.594406],"type":"Point"}
}