{
  "type": "Feature",
  "properties": {
    "iso:country":"DE",
    "sg:address":"Justus-Liebig-Str. 8 a",
    "sg:city":"Bayreuth",
    "sg:phone":"+49 921/761507",
    "sg:postcode":"95447",
    "sg:province":"Bayern",
    "wof:name":"Bundesarchiv Lasten- Ausgleichsarchiv",
    "wof:placetype":"venue"
},
  "geometry": {"coordinates":[11.565072,49.932579],"type":"Point"}
}