{
  "type": "Feature",
  "properties": {
    "iso:country":"DE",
    "sg:address":"Dr.-Wilhelm-K\u00fclz-Platz 7",
    "sg:city":"Hohenstein-Ernstthal",
    "sg:phone":"+49 3723/65150",
    "sg:postcode":"09337",
    "sg:province":"Sachsen",
    "wof:name":"Redaktion Freie Presse",
    "wof:placetype":"venue"
},
  "geometry": {"coordinates":[12.7100629807,50.8001861572],"type":"Point"}
}