{
  "type": "Feature",
  "properties": {
    "iso:country":"DE",
    "sg:address":"Hertzstr. 53",
    "sg:city":"H\u00fcckelhoven",
    "sg:postcode":"41836",
    "sg:province":"Nordrhein-Westfalen",
    "wof:name":"Ruh Haushaltsger\u00e4te- Kundendienst Gmbh",
    "wof:placetype":"venue"
},
  "geometry": {"coordinates":[6.2801098824,51.0393409729],"type":"Point"}
}