{
  "type": "Feature",
  "properties": {
    "iso:country":"DE",
    "sg:address":"Wehr 250",
    "sg:city":"Legden",
    "sg:phone":"+49 2566/1258",
    "sg:postcode":"48739",
    "sg:province":"Nordrhein-Westfalen",
    "wof:name":"Herbert Roy\u00e9",
    "wof:placetype":"venue"
},
  "geometry": {"coordinates":[7.086006,52.069286],"type":"Point"}
}