{
  "type": "Feature",
  "properties": {
    "iso:country":"DE",
    "sg:address":"Radeburger Str. 102",
    "sg:city":"Gro\u00dfenhain",
    "sg:phone":"+49 3522/3610",
    "sg:postcode":"01558",
    "sg:province":"Sachsen",
    "wof:name":"Hintersatz-maschinenteile Und Metallbau Gmbh",
    "wof:placetype":"venue"
},
  "geometry": {"coordinates":[13.554234,51.295532],"type":"Point"}
}