{
  "type": "Feature",
  "properties": {
    "iso:country":"DE",
    "sg:address":"Mendener Str. 3",
    "sg:city":"M\u00fclheim",
    "sg:phone":"+49 208/382191",
    "sg:postcode":"45470",
    "sg:province":"Nordrhein-Westfalen",
    "wof:name":"Jugendherberge M\u00fclheim",
    "wof:placetype":"venue"
},
  "geometry": {"coordinates":[6.8886418343,51.4122581482],"type":"Point"}
}