{
  "type": "Feature",
  "properties": {
    "iso:country":"DE",
    "sg:address":"Zehnthausstr. 65",
    "sg:city":"Cochem",
    "sg:phone":"+49 2671/1503",
    "sg:postcode":"56812",
    "sg:province":"Rheinland-Pfalz",
    "wof:name":"G\u00e4stehaus W. Rossi",
    "wof:placetype":"venue"
},
  "geometry": {"coordinates":[7.170773983,50.1445960999],"type":"Point"}
}