{
  "type": "Feature",
  "properties": {
    "iso:country":"DE",
    "sg:address":"Rotenburger Str. 17",
    "sg:city":"Alheim",
    "sg:phone":"+49 6623/7305",
    "sg:postcode":"36211",
    "sg:province":"Hessen",
    "wof:name":"Heinrich J. N\u00f6ding",
    "wof:placetype":"venue"
},
  "geometry": {"coordinates":[9.705077,51.054779],"type":"Point"}
}