{
  "type": "Feature",
  "properties": {
    "iso:country":"DE",
    "sg:address":"Augustinerstr. 4",
    "sg:city":"Gro\u00dfheubach",
    "sg:phone":"+49 9371/67681",
    "sg:postcode":"63920",
    "sg:province":"Bayern",
    "wof:name":"Frank H\u00fcnefeld",
    "wof:placetype":"venue"
},
  "geometry": {"coordinates":[9.225685,49.72393],"type":"Point"}
}