{
  "type": "Feature",
  "properties": {
    "iso:country":"DE",
    "sg:address":"Prankelstr. 45",
    "sg:city":"Weinheim",
    "sg:phone":"+49 6201/14600",
    "sg:postcode":"69469",
    "sg:province":"Baden-W\u00fcrttemberg",
    "wof:name":"Hans M\u00fcller Ingenieur",
    "wof:placetype":"venue"
},
  "geometry": {"coordinates":[8.6607055664,49.5397033691],"type":"Point"}
}