{
  "type": "Feature",
  "properties": {
    "iso:country":"DE",
    "sg:address":"Im Dehnacker 13",
    "sg:city":"D\u00fcren",
    "sg:phone":"+49 2421/505375",
    "sg:postcode":"52355",
    "sg:province":"Nordrhein-Westfalen",
    "wof:name":"Franz Dahmen Elektroinstallation",
    "wof:placetype":"venue"
},
  "geometry": {"coordinates":[6.476526,50.771305],"type":"Point"}
}