{
  "type": "Feature",
  "properties": {
    "iso:country":"DE",
    "sg:address":"Iddensener Dorfstr. 5",
    "sg:city":"Rosengarten",
    "sg:phone":"+49 4108/8277",
    "sg:postcode":"21224",
    "sg:province":"Niedersachsen",
    "wof:name":"Wilhelm Kruse",
    "wof:placetype":"venue"
},
  "geometry": {"coordinates":[9.914346,53.390347],"type":"Point"}
}