{
  "type": "Feature",
  "properties": {
    "iso:country":"DE",
    "sg:address":"Hauptstr. 16",
    "sg:city":"Stegen",
    "sg:phone":"+49 7661/61350",
    "sg:postcode":"79252",
    "sg:province":"Baden-W\u00fcrttemberg",
    "wof:name":"T. Rombach",
    "wof:placetype":"venue"
},
  "geometry": {"coordinates":[7.969265,47.984592],"type":"Point"}
}