{
  "type": "Feature",
  "properties": {
    "iso:country":"DE",
    "sg:address":"Hauptstr. 11",
    "sg:city":"Tellig",
    "sg:phone":"+49 6545/6756",
    "sg:postcode":"56858",
    "sg:province":"Rheinland-Pfalz",
    "wof:name":"Hagedorn Gmbh",
    "wof:placetype":"venue"
},
  "geometry": {"coordinates":[7.254012,50.025684],"type":"Point"}
}