{
  "type": "Feature",
  "properties": {
    "iso:country":"DE",
    "sg:address":"Alte Basler Str. 3",
    "sg:city":"L\u00f6rrach",
    "sg:phone":"+49 7621/2663",
    "sg:postcode":"79540",
    "sg:province":"Baden-W\u00fcrttemberg",
    "wof:name":"M. Christl",
    "wof:placetype":"venue"
},
  "geometry": {"coordinates":[7.657346,47.599316],"type":"Point"}
}