{
  "type": "Feature",
  "properties": {
    "iso:country":"DE",
    "sg:address":"Behringstra\u00dfe 28A",
    "sg:city":"Hamburg",
    "sg:phone":"+49 40/39834370",
    "sg:postcode":"22765",
    "sg:province":"Hamburg",
    "wof:name":"Flick & Sa\u00df, Rechtsanw\u00e4lte, Hamburg",
    "wof:placetype":"venue"
},
  "geometry": {"coordinates":[9.923566,53.554436],"type":"Point"}
}