{
  "type": "Feature",
  "properties": {
    "iso:country":"DE",
    "sg:address":"Alte Poststr. 5",
    "sg:city":"Schleiz",
    "sg:phone":"+49 3663/422542",
    "sg:postcode":"07907",
    "sg:province":"Th\u00fcringen",
    "wof:name":"Hehne",
    "wof:placetype":"venue"
},
  "geometry": {"coordinates":[11.807737,50.577309],"type":"Point"}
}