{
  "type": "Feature",
  "properties": {
    "iso:country":"DE",
    "sg:address":"Vohren 80",
    "sg:city":"Warendorf",
    "sg:phone":"+49 2581/2661",
    "sg:postcode":"48231",
    "sg:province":"Nordrhein-Westfalen",
    "wof:name":"Theod. Schwakenberg-hagemense",
    "wof:placetype":"venue"
},
  "geometry": {"coordinates":[8.047787,51.942608],"type":"Point"}
}