{
  "type": "Feature",
  "properties": {
    "iso:country":"DE",
    "sg:address":"Im Dorfe 38",
    "sg:city":"Barsinghausen",
    "sg:phone":"+49 5105/3521",
    "sg:postcode":"30890",
    "sg:province":"Niedersachsen",
    "wof:name":"Ernst Rehren",
    "wof:placetype":"venue"
},
  "geometry": {"coordinates":[9.4071950912,52.3279190063],"type":"Point"}
}