{
  "type": "Feature",
  "properties": {
    "iso:country":"DE",
    "sg:address":"Carl-Zeiss-Str. 11",
    "sg:city":"S\u00fc\u00dfen",
    "sg:phone":"+49 7162/8326",
    "sg:postcode":"73079",
    "sg:province":"Baden-W\u00fcrttemberg",
    "wof:name":"Fridolin Binder",
    "wof:placetype":"venue"
},
  "geometry": {"coordinates":[9.743041,48.678989],"type":"Point"}
}