{
  "type": "Feature",
  "properties": {
    "iso:country":"DE",
    "sg:address":"R\u00f6ntgenstr. 19 a",
    "sg:city":"Radevormwald",
    "sg:phone":"+49 2195/8029",
    "sg:postcode":"42477",
    "sg:province":"Nordrhein-Westfalen",
    "wof:name":"Gerd Emde Zahn\u00e4rztebedarf",
    "wof:placetype":"venue"
},
  "geometry": {"coordinates":[7.3820991516,51.2003746033],"type":"Point"}
}