{
  "type": "Feature",
  "properties": {
    "iso:country":"DE",
    "sg:address":"Kaiserswerther Str. 90a",
    "sg:city":"Ratingen",
    "sg:phone":"+49 2102/33222",
    "sg:postcode":"40880",
    "sg:province":"Nordrhein-Westfalen",
    "wof:name":"Autoglas Schwertfeger Gmbh",
    "wof:placetype":"venue"
},
  "geometry": {"coordinates":[6.8253908157,51.2989082336],"type":"Point"}
}