{
  "type": "Feature",
  "properties": {
    "iso:country":"DE",
    "sg:address":"Schulstr. 15",
    "sg:city":"Recklinghausen",
    "sg:phone":"+49 2361/81086",
    "sg:postcode":"45665",
    "sg:province":"Nordrhein-Westfalen",
    "wof:name":"B\u00e4ckerei Martin E. K.",
    "wof:placetype":"venue"
},
  "geometry": {"coordinates":[7.260781,51.610558],"type":"Point"}
}