{
  "type": "Feature",
  "properties": {
    "iso:country":"DE",
    "sg:address":"Geb\u00e4ude 152 FAC 2",
    "sg:city":"Frankfurt",
    "sg:phone":"+49 69/69066076",
    "sg:postcode":"60549",
    "sg:province":"Hessen",
    "wof:name":"Luftfahrthistorische Sammlung Der Flughafen",
    "wof:placetype":"venue"
},
  "geometry": {"coordinates":[8.57003,50.050705],"type":"Point"}
}