{
  "type": "Feature",
  "properties": {
    "iso:country":"DE",
    "sg:address":"Kirchplatz 4",
    "sg:city":"Berglern",
    "sg:phone":"+49 8762/2765",
    "sg:postcode":"85459",
    "sg:province":"Bayern",
    "wof:name":"Kath. Pfarramt St. Peter Und Paul",
    "wof:placetype":"venue"
},
  "geometry": {"coordinates":[11.9299669266,48.3854866028],"type":"Point"}
}