{
  "type": "Feature",
  "properties": {
    "iso:country":"DE",
    "sg:address":"Grillostr. 6",
    "sg:city":"Duisburg",
    "sg:phone":"+49 203/405274",
    "sg:postcode":"47169",
    "sg:province":"Nordrhein-Westfalen",
    "wof:name":"Franz Leineweber",
    "wof:placetype":"venue"
},
  "geometry": {"coordinates":[6.757293,51.501507],"type":"Point"}
}