{
  "type": "Feature",
  "properties": {
    "iso:country":"DE",
    "sg:address":"Marktstr. 26",
    "sg:city":"Kaiserslautern",
    "sg:phone":"+49 631/316400",
    "sg:postcode":"67655",
    "sg:province":"Rheinland-Pfalz",
    "wof:name":"Gerling Versicherungen",
    "wof:placetype":"venue"
},
  "geometry": {"coordinates":[7.7704739571,49.4445838928],"type":"Point"}
}