{
  "type": "Feature",
  "properties": {
    "iso:country":"DE",
    "sg:address":"52146",
    "sg:city":"W\u00fcrselen",
    "sg:postcode":"52146",
    "sg:province":"Nordrhein-Westfalen",
    "wof:name":"Robert Gr\u00fcnzig",
    "wof:placetype":"venue"
},
  "geometry": {"coordinates":[6.14823,50.829239],"type":"Point"}
}