{
  "type": "Feature",
  "properties": {
    "iso:country":"DE",
    "sg:address":"Goetheweg 55",
    "sg:city":"Blaufelden",
    "sg:phone":"+49 7953/1021",
    "sg:postcode":"74572",
    "sg:province":"Baden-W\u00fcrttemberg",
    "wof:name":"Fr\u00f6bel Gmbh",
    "wof:placetype":"venue"
},
  "geometry": {"coordinates":[9.96589,49.301411],"type":"Point"}
}