{
  "type": "Feature",
  "properties": {
    "iso:country":"DE",
    "sg:address":"Kurhausstr. 44",
    "sg:city":"Bad Segeberg",
    "sg:phone":"+49 4551/2373",
    "sg:postcode":"23795",
    "sg:province":"Schleswig-Holstein",
    "wof:name":"G. Burchard",
    "wof:placetype":"venue"
},
  "geometry": {"coordinates":[10.3067121506,53.9401092529],"type":"Point"}
}