{
  "type": "Feature",
  "properties": {
    "iso:country":"DE",
    "sg:address":"Rathausplatz 2",
    "sg:city":"Buchloe",
    "sg:phone":"+49 8241/4540",
    "sg:postcode":"86807",
    "sg:province":"Bayern",
    "wof:name":"W. Beginen",
    "wof:placetype":"venue"
},
  "geometry": {"coordinates":[10.7278862,48.0373382568],"type":"Point"}
}