{
  "type": "Feature",
  "properties": {
    "iso:country":"DE",
    "sg:address":"In der Wann 41",
    "sg:city":"Marburg",
    "sg:phone":"+49 6421/31080",
    "sg:postcode":"35037",
    "sg:province":"Hessen",
    "wof:name":"J. M\u00fcller-wickenh\u00f6fer Steuerberaterin",
    "wof:placetype":"venue"
},
  "geometry": {"coordinates":[8.737862587,50.8008842468],"type":"Point"}
}