{
  "type": "Feature",
  "properties": {
    "iso:country":"DE",
    "sg:address":"Wei\u00dfer Kamp 8",
    "sg:city":"Nienburg",
    "sg:phone":"+49 5021/64073",
    "sg:postcode":"31582",
    "sg:province":"Niedersachsen",
    "wof:name":"Technobrau Vertriebsges. Mbh",
    "wof:placetype":"venue"
},
  "geometry": {"coordinates":[9.233183,52.673878],"type":"Point"}
}