{
  "type": "Feature",
  "properties": {
    "iso:country":"DE",
    "sg:address":"Dickertsm\u00fchlstr. 7",
    "sg:city":"Prien",
    "sg:phone":"+49 8051/91083",
    "sg:postcode":"83209",
    "sg:province":"Bayern",
    "wof:name":"Prospera Verm\u00f6gensverwaltungs- Und",
    "wof:placetype":"venue"
},
  "geometry": {"coordinates":[12.35181,47.839523],"type":"Point"}
}