{
  "type": "Feature",
  "properties": {
    "iso:country":"DE",
    "sg:address":"Amberger Str. 11",
    "sg:city":"Schnaittenbach",
    "sg:phone":"+49 9622/2271",
    "sg:postcode":"92253",
    "sg:province":"Bayern",
    "wof:name":"Georg Weich Gmbh",
    "wof:placetype":"venue"
},
  "geometry": {"coordinates":[11.9972085953,49.5464286804],"type":"Point"}
}