{
  "type": "Feature",
  "properties": {
    "iso:country":"DE",
    "sg:address":"Werkstr. 8",
    "sg:city":"Ellenberg",
    "sg:phone":"+49 7962/2292",
    "sg:postcode":"73488",
    "sg:province":"Baden-W\u00fcrttemberg",
    "wof:name":"August Fuchs",
    "wof:placetype":"venue"
},
  "geometry": {"coordinates":[10.2140159607,49.0152931213],"type":"Point"}
}