{
  "type": "Feature",
  "properties": {
    "iso:country":"DE",
    "sg:address":"Am Nordkreuz 26",
    "sg:city":"Rastede",
    "sg:phone":"+49 4402/81656",
    "sg:postcode":"26180",
    "sg:province":"Niedersachsen",
    "wof:name":"Lamschick Gbr",
    "wof:placetype":"venue"
},
  "geometry": {"coordinates":[8.226495,53.211166],"type":"Point"}
}