{
  "type": "Feature",
  "properties": {
    "iso:country":"DE",
    "sg:address":"Neumarkt 9",
    "sg:city":"Limburg",
    "sg:phone":"+49 6431290753572",
    "sg:postcode":"65549",
    "sg:province":"Hessen",
    "wof:name":"Naspa-versicherungs- Service Gmbh",
    "wof:placetype":"venue"
},
  "geometry": {"coordinates":[8.0628299713,50.3863182068],"type":"Point"}
}