{
  "type": "Feature",
  "properties": {
    "iso:country":"DE",
    "sg:address":"Gro\u00dfen-Busecker Str. 2",
    "sg:city":"Buseck",
    "sg:phone":"+49 6408/4336",
    "sg:postcode":"35418",
    "sg:province":"Hessen",
    "wof:name":"Hessischer Hof",
    "wof:placetype":"venue"
},
  "geometry": {"coordinates":[8.760890007,50.6197662354],"type":"Point"}
}