{
  "type": "Feature",
  "properties": {
    "iso:country":"DE",
    "sg:address":"Kirchhuchtinger Landstr. 92",
    "sg:city":"Bremen",
    "sg:postcode":"28259",
    "sg:province":"Bremen",
    "wof:name":"Gvb Grundst\u00fccks- Verwaltungs- Und",
    "wof:placetype":"venue"
},
  "geometry": {"coordinates":[8.738809,53.047504],"type":"Point"}
}