{
  "type": "Feature",
  "properties": {
    "iso:country":"DE",
    "sg:address":"Schnellenberger Weg 91",
    "sg:city":"L\u00fcneburg",
    "sg:phone":"+49 4131/62187",
    "sg:postcode":"21339",
    "sg:province":"Niedersachsen",
    "wof:name":"Kroll Gmbh Tief- Und Stra\u00dfenbau",
    "wof:placetype":"venue"
},
  "geometry": {"coordinates":[10.39217,53.247429],"type":"Point"}
}