{
  "type": "Feature",
  "properties": {
    "iso:country":"DE",
    "sg:address":"Bahnhofstr. 8",
    "sg:city":"Beratzhausen",
    "sg:phone":"+49 9493/90099",
    "sg:postcode":"93176",
    "sg:province":"Bayern",
    "wof:name":"Hauser-apotheke",
    "wof:placetype":"venue"
},
  "geometry": {"coordinates":[11.805089,49.095528],"type":"Point"}
}