{
  "type": "Feature",
  "properties": {
    "iso:country":"DE",
    "sg:address":"Karl-Mand-Str. 2",
    "sg:city":"Koblenz",
    "sg:phone":"+49 261/71053",
    "sg:postcode":"56070",
    "sg:province":"Rheinland-Pfalz",
    "wof:name":"Ingo Schmitt",
    "wof:placetype":"venue"
},
  "geometry": {"coordinates":[7.58101511,50.3884086609],"type":"Point"}
}