{
  "type": "Feature",
  "properties": {
    "iso:country":"DE",
    "sg:address":"Pfarrergasse 2",
    "sg:city":"Regensburg",
    "sg:phone":"+49 941/55496",
    "sg:postcode":"93047",
    "sg:province":"Bayern",
    "wof:name":"Timm Kranz Rechtsanwalt",
    "wof:placetype":"venue"
},
  "geometry": {"coordinates":[12.095993042,49.0178527832],"type":"Point"}
}