{
  "type": "Feature",
  "properties": {
    "iso:country":"DE",
    "sg:address":"Im M\u00fchlenpesch",
    "sg:city":"Hillesheim",
    "sg:phone":"+49 6593/516",
    "sg:postcode":"54576",
    "sg:province":"Rheinland-Pfalz",
    "wof:name":"H. Pitzen",
    "wof:placetype":"venue"
},
  "geometry": {"coordinates":[6.671,50.28756],"type":"Point"}
}