{
  "type": "Feature",
  "properties": {
    "iso:country":"DE",
    "sg:address":"V\u00f6genstr. 10",
    "sg:city":"Rostock",
    "sg:phone":"+49 381/4540183",
    "sg:postcode":"18055",
    "sg:province":"Mecklenburg-Vorpommern",
    "wof:name":"Gws Geb\u00e4ude Und Wohnungs- Sanierung Lorenzen Gmbh",
    "wof:placetype":"venue"
},
  "geometry": {"coordinates":[12.127183,54.086525],"type":"Point"}
}