{
  "type": "Feature",
  "properties": {
    "iso:country":"DE",
    "sg:address":"Im Brand 24",
    "sg:city":"Offenburg",
    "sg:phone":"+49 781/53850",
    "sg:postcode":"77656",
    "sg:province":"Baden-W\u00fcrttemberg",
    "wof:name":"Siegfried St\u00e4hle Architekt",
    "wof:placetype":"venue"
},
  "geometry": {"coordinates":[7.944869,48.418266],"type":"Point"}
}