{
  "type": "Feature",
  "properties": {
    "iso:country":"DE",
    "sg:address":"Hauptstr. 59",
    "sg:city":"Urbach",
    "sg:phone":"+49 7181/81320",
    "sg:postcode":"73660",
    "sg:province":"Baden-W\u00fcrttemberg",
    "wof:name":"Horst Herb",
    "wof:placetype":"venue"
},
  "geometry": {"coordinates":[9.5819063187,48.8090133667],"type":"Point"}
}