{
  "type": "Feature",
  "properties": {
    "iso:country":"DE",
    "sg:address":"Lanfer 45",
    "sg:city":"Warstein",
    "sg:phone":"+49 2902/52384",
    "sg:postcode":"59581",
    "sg:province":"Nordrhein-Westfalen",
    "wof:name":"Style Sportwear",
    "wof:placetype":"venue"
},
  "geometry": {"coordinates":[8.335104,51.47961],"type":"Point"}
}