{
  "type": "Feature",
  "properties": {
    "iso:country":"DE",
    "sg:address":"Hoyerweg 4",
    "sg:city":"Bremen",
    "sg:phone":"+49 421/259641",
    "sg:postcode":"28355",
    "sg:province":"Bremen",
    "wof:name":"Schwarz Grundst\u00fccks Gmbh",
    "wof:placetype":"venue"
},
  "geometry": {"coordinates":[8.9466314316,53.0886955261],"type":"Point"}
}