{
  "type": "Feature",
  "properties": {
    "iso:country":"DE",
    "sg:address":"Gewerbering 5",
    "sg:city":"Teising",
    "sg:phone":"+49 8633/89770",
    "sg:postcode":"84576",
    "sg:province":"Bayern",
    "wof:name":"F.i.a. Food Ingredientsanthes Gmbh",
    "wof:placetype":"venue"
},
  "geometry": {"coordinates":[12.619933,48.229065],"type":"Point"}
}