{
  "type": "Feature",
  "properties": {
    "iso:country":"DE",
    "sg:address":"Bergheimer Bruch 8",
    "sg:city":"Arnsberg",
    "sg:phone":"+49 2932/22514",
    "sg:postcode":"59757",
    "sg:province":"Nordrhein-Westfalen",
    "wof:name":"M. Geyer",
    "wof:placetype":"venue"
},
  "geometry": {"coordinates":[7.9470820427,51.4549179077],"type":"Point"}
}