{
  "type": "Feature",
  "properties": {
    "iso:country":"DE",
    "sg:address":"Wilhelmstr. 87",
    "sg:city":"Heilbad Heiligenstadt",
    "sg:phone":"+49 3606/603872",
    "sg:postcode":"37308",
    "sg:province":"Th\u00fcringen",
    "wof:name":"H. Schneider & A. Stitz",
    "wof:placetype":"venue"
},
  "geometry": {"coordinates":[10.140576,51.377472],"type":"Point"}
}