{
  "type": "Feature",
  "properties": {
    "iso:country":"DE",
    "sg:address":"Heilenstr. 7",
    "sg:city":"Witten",
    "sg:phone":"+49 2302/56413",
    "sg:postcode":"58452",
    "sg:province":"Nordrhein-Westfalen",
    "wof:name":"B\u00e4rbel Geppert",
    "wof:placetype":"venue"
},
  "geometry": {"coordinates":[7.336402,51.438393],"type":"Point"}
}