{
  "type": "Feature",
  "properties": {
    "iso:country":"DE",
    "sg:address":"Bahnhofstr. 14a",
    "sg:city":"Feldberg",
    "sg:phone":"+49 39831/20661",
    "sg:postcode":"17258",
    "sg:province":"Mecklenburg-Vorpommern",
    "wof:name":"Gerhard Lange",
    "wof:placetype":"venue"
},
  "geometry": {"coordinates":[13.43174,53.329834],"type":"Point"}
}