{
  "type": "Feature",
  "properties": {
    "iso:country":"DE",
    "sg:address":"Haylerstr. 28",
    "sg:city":"M\u00fcnchen",
    "sg:phone":"+49 89/1431310",
    "sg:postcode":"80993",
    "sg:province":"Bayern",
    "wof:name":"S\u00fcd-hansa Besichtigungen Karrosionsschutz",
    "wof:placetype":"venue"
},
  "geometry": {"coordinates":[11.5053462982,48.1885871887],"type":"Point"}
}