{
  "type": "Feature",
  "properties": {
    "iso:country":"DE",
    "sg:address":"Kufsteiner Str. 6",
    "sg:city":"Duisburg",
    "sg:phone":"+49 203/701410",
    "sg:postcode":"47249",
    "sg:province":"Nordrhein-Westfalen",
    "wof:name":"Willi Wassink",
    "wof:placetype":"venue"
},
  "geometry": {"coordinates":[6.759778,51.382423],"type":"Point"}
}