{
  "type": "Feature",
  "properties": {
    "iso:country":"DE",
    "sg:address":"Sandweg 6",
    "sg:city":"Bienenb\u00fcttel",
    "sg:phone":"+49 5823/225",
    "sg:postcode":"29553",
    "sg:province":"Niedersachsen",
    "wof:name":"Gardinen Zentrale Bienenb\u00fcttel Gmbh",
    "wof:placetype":"venue"
},
  "geometry": {"coordinates":[10.4965381622,53.136505127],"type":"Point"}
}