{
  "type": "Feature",
  "properties": {
    "iso:country":"DE",
    "sg:address":"Rheinstr. 36",
    "sg:city":"Wiesbaden",
    "sg:phone":"+49 611/9446956",
    "sg:postcode":"65185",
    "sg:province":"Hessen",
    "wof:name":"Matthias R\u00fcck Rechtsanwalt",
    "wof:placetype":"venue"
},
  "geometry": {"coordinates":[8.2406539917,50.077545166],"type":"Point"}
}