{
  "type": "Feature",
  "properties": {
    "iso:country":"DE",
    "sg:address":"Salinstr. 2/I",
    "sg:city":"Rosenheim",
    "sg:postcode":"83022",
    "sg:province":"Bayern",
    "wof:name":"Praxis Dr. Hans Rauch",
    "wof:placetype":"venue"
},
  "geometry": {"coordinates":[12.128755,47.856522],"type":"Point"}
}