{
  "type": "Feature",
  "properties": {
    "iso:country":"DE",
    "sg:address":"Im Brunneneck 18",
    "sg:city":"Kaiserslautern",
    "sg:phone":"+49 6306/1202",
    "sg:postcode":"67661",
    "sg:province":"Rheinland-Pfalz",
    "wof:name":"Monika Schick-m\u00fcller",
    "wof:placetype":"venue"
},
  "geometry": {"coordinates":[7.8212618828,49.3808097839],"type":"Point"}
}