{
  "type": "Feature",
  "properties": {
    "iso:country":"DE",
    "sg:address":"Kreuzweg 5",
    "sg:city":"Bad Essen",
    "sg:phone":"+49 5472/2707",
    "sg:postcode":"49152",
    "sg:province":"Niedersachsen",
    "wof:name":"Karl M\u00f6nnich",
    "wof:placetype":"venue"
},
  "geometry": {"coordinates":[8.370109,52.306496],"type":"Point"}
}