{
  "type": "Feature",
  "properties": {
    "iso:country":"DE",
    "sg:address":"Berlepschstr. 14",
    "sg:city":"Berlin",
    "sg:phone":"+49 30/8157770",
    "sg:postcode":"14165",
    "sg:province":"Berlin",
    "wof:name":"Karl Presuhn Inh. Claus Hansen",
    "wof:placetype":"venue"
},
  "geometry": {"coordinates":[13.255121,52.429382],"type":"Point"}
}