{
  "type": "Feature",
  "properties": {
    "iso:country":"DE",
    "sg:address":"Gewerbepark 17 b",
    "sg:city":"Neustadt",
    "sg:postcode":"93333",
    "sg:province":"Bayern",
    "wof:name":"H2-o Heizungs- Und Sanit\u00e4r- Gro\u00dfhandel Gmbh",
    "wof:placetype":"venue"
},
  "geometry": {"coordinates":[11.763466835,48.7933235168],"type":"Point"}
}