{
  "type": "Feature",
  "properties": {
    "iso:country":"DE",
    "sg:address":"Buchenb\u00fchlweg 2",
    "sg:city":"March",
    "sg:phone":"+49 7665/2074",
    "sg:postcode":"79232",
    "sg:province":"Baden-W\u00fcrttemberg",
    "wof:name":"Rohde & Liesenfeld International Gmbh & Co. Kg",
    "wof:placetype":"venue"
},
  "geometry": {"coordinates":[7.7741532326,48.0676574707],"type":"Point"}
}