{
  "type": "Feature",
  "properties": {
    "iso:country":"DE",
    "sg:address":"Marsstr. 23c",
    "sg:city":"Castrop-Rauxel",
    "sg:phone":"+49 2305/358080",
    "sg:postcode":"44579",
    "sg:province":"Nordrhein-Westfalen",
    "wof:name":"Printout Belichtungsservice Gmbh",
    "wof:placetype":"venue"
},
  "geometry": {"coordinates":[7.313459,51.57],"type":"Point"}
}