{
  "type": "Feature",
  "properties": {
    "iso:country":"DE",
    "sg:address":"Richard-Rentsch-Str. 40",
    "sg:city":"Oederan",
    "sg:phone":"+49 4937/2925110",
    "sg:postcode":"09569",
    "sg:province":"Sachsen",
    "wof:name":"Bega B\u00c4uerlicheerzeugergenossenschaftgahlenz E.g.",
    "wof:placetype":"venue"
},
  "geometry": {"coordinates":[13.183146,50.856033],"type":"Point"}
}