{
  "type": "Feature",
  "properties": {
    "iso:country":"DE",
    "sg:address":"Sonnenbergstr. 22",
    "sg:city":"Aalen",
    "sg:phone":"+49 7361/91050",
    "sg:postcode":"73433",
    "sg:province":"Baden-W\u00fcrttemberg",
    "wof:name":"Karl Schnepf Gmbh & Co. Kg Eisen-sperrholzhandlung",
    "wof:placetype":"venue"
},
  "geometry": {"coordinates":[10.108468,48.859756],"type":"Point"}
}