{
  "type": "Feature",
  "properties": {
    "iso:country":"DE",
    "sg:address":"Nierenberger Str. 148",
    "sg:city":"Emmerich",
    "sg:phone":"+49 4928/225049",
    "sg:postcode":"46446",
    "sg:province":"Nordrhein-Westfalen",
    "wof:name":"Theodor Heuvelmann Gmbh",
    "wof:placetype":"venue"
},
  "geometry": {"coordinates":[6.2667899132,51.8340682983],"type":"Point"}
}