{
  "type": "Feature",
  "properties": {
    "iso:country":"DE",
    "sg:address":"Westring 103",
    "sg:city":"Rheda-Wiedenbr\u00fcck",
    "sg:phone":"+49 5242/36659",
    "sg:postcode":"33378",
    "sg:province":"Nordrhein-Westfalen",
    "wof:name":"Bernhard Gro\u00dfestrangmann",
    "wof:placetype":"venue"
},
  "geometry": {"coordinates":[8.2953100204,51.8348922729],"type":"Point"}
}