{
  "type": "Feature",
  "properties": {
    "iso:country":"DE",
    "sg:address":"Romstr. 1 POSTFACH 1461",
    "sg:city":"Schweinfurt",
    "sg:phone":"+49 4967/2115460",
    "sg:postcode":"97404",
    "sg:province":"Bayern",
    "wof:name":"Stahl-maschinen-und Anh\u00c4ngerbau Carl Loosen Gmbh",
    "wof:placetype":"venue"
},
  "geometry": {"coordinates":[7.9065999985,49.9518699646],"type":"Point"}
}