{
  "type": "Feature",
  "properties": {
    "iso:country":"DE",
    "sg:address":"Wappenschmiedstr. 17",
    "sg:city":"Pleisweiler-Oberhofen",
    "sg:phone":"+49 6343/61252",
    "sg:postcode":"76889",
    "sg:province":"Rheinland-Pfalz",
    "wof:name":"Peter Getto",
    "wof:placetype":"venue"
},
  "geometry": {"coordinates":[7.9967260361,49.1135482788],"type":"Point"}
}