{
  "type": "Feature",
  "properties": {
    "iso:country":"DE",
    "sg:address":"Westerstr. 28",
    "sg:city":"Wolfsburg",
    "sg:phone":"+49 5362/51046",
    "sg:postcode":"38442",
    "sg:province":"Niedersachsen",
    "wof:name":"Heinrich Engler",
    "wof:placetype":"venue"
},
  "geometry": {"coordinates":[10.7136316299,52.4183235168],"type":"Point"}
}