{
  "type": "Feature",
  "properties": {
    "iso:country":"DE",
    "sg:address":"Louis-Pasteur-Str. 5",
    "sg:city":"W\u00fcrzburg",
    "sg:postcode":"97076",
    "sg:province":"Bayern",
    "wof:name":"Ursula Stein E. K. Bistro-cafe Im Pavillon",
    "wof:placetype":"venue"
},
  "geometry": {"coordinates":[9.996133,49.794544],"type":"Point"}
}