{
  "type": "Feature",
  "properties": {
    "iso:country":"DE",
    "sg:address":"Berliner Str. 37b",
    "sg:city":"Mainz",
    "sg:phone":"+49 6131/51521",
    "sg:postcode":"55131",
    "sg:province":"Rheinland-Pfalz",
    "wof:name":"Ev. Pfarramt Thomaskirche",
    "wof:placetype":"venue"
},
  "geometry": {"coordinates":[8.2665510178,49.978767395],"type":"Point"}
}