{
  "type": "Feature",
  "properties": {
    "iso:country":"DE",
    "sg:address":"Berliner Str. 13",
    "sg:city":"Cottbus",
    "sg:postcode":"03046",
    "sg:province":"Brandenburg",
    "wof:name":"Zkb",
    "wof:placetype":"venue"
},
  "geometry": {"coordinates":[14.327212,51.761173],"type":"Point"}
}