{
  "type": "Feature",
  "properties": {
    "iso:country":"DE",
    "sg:address":"Breierspfad 255",
    "sg:city":"Dortmund",
    "sg:phone":"+49 231/257018",
    "sg:postcode":"44309",
    "sg:province":"Nordrhein-Westfalen",
    "wof:name":"Reform-w\u00e4scherei Berger",
    "wof:placetype":"venue"
},
  "geometry": {"coordinates":[7.5408830643,51.5222473145],"type":"Point"}
}