{
  "type": "Feature",
  "properties": {
    "iso:country":"DE",
    "sg:address":"Westliche Karl-Friedrich-Str 128",
    "sg:city":"Pforzheim",
    "sg:phone":"+49 7231/355535",
    "sg:postcode":"75172",
    "sg:province":"Baden-W\u00fcrttemberg",
    "wof:name":"Ton Pur Bernhard Heizmann",
    "wof:placetype":"venue"
},
  "geometry": {"coordinates":[8.6904554367,48.8922996521],"type":"Point"}
}