{
  "type": "Feature",
  "properties": {
    "iso:country":"DE",
    "sg:address":"Kanalstr. 14",
    "sg:city":"Nettetal",
    "sg:phone":"+49 2157/5596",
    "sg:postcode":"41334",
    "sg:province":"Nordrhein-Westfalen",
    "wof:name":"Werner Trienes Gartengestaltung",
    "wof:placetype":"venue"
},
  "geometry": {"coordinates":[6.201662,51.321774],"type":"Point"}
}