{
  "type": "Feature",
  "properties": {
    "iso:country":"DE",
    "sg:address":"Neufchateaustr. 4",
    "sg:city":"Hamm",
    "sg:phone":"+49 2381/462686",
    "sg:postcode":"59077",
    "sg:province":"Nordrhein-Westfalen",
    "wof:name":"Alte-apotheke",
    "wof:placetype":"venue"
},
  "geometry": {"coordinates":[7.743631,51.660828],"type":"Point"}
}