{
  "type": "Feature",
  "properties": {
    "iso:country":"DE",
    "sg:address":"Oefelestr. 6",
    "sg:city":"M\u00fcnchen",
    "sg:postcode":"81543",
    "sg:province":"Bayern",
    "wof:name":"Elektro K\u00f6berle Gmbh",
    "wof:placetype":"venue"
},
  "geometry": {"coordinates":[11.574905,48.120464],"type":"Point"}
}