{
  "type": "Feature",
  "properties": {
    "iso:country":"DE",
    "sg:address":"Nohlmannstr. 5",
    "sg:city":"H\u00fcckelhoven",
    "sg:postcode":"41836",
    "sg:province":"Nordrhein-Westfalen",
    "wof:name":"Dohmen Verwaltungsges. Mbh",
    "wof:placetype":"venue"
},
  "geometry": {"coordinates":[6.2204298973,51.0358200073],"type":"Point"}
}