{
  "type": "Feature",
  "properties": {
    "iso:country":"DE",
    "sg:address":"Kolpingstr. 7",
    "sg:city":"Oberursel",
    "sg:phone":"+49 6171/59600",
    "sg:postcode":"61440",
    "sg:province":"Hessen",
    "wof:name":"Raimund Krieger Steinmetzbetrieb",
    "wof:placetype":"venue"
},
  "geometry": {"coordinates":[8.5831365585,50.2033081055],"type":"Point"}
}