{
  "type": "Feature",
  "properties": {
    "iso:country":"DE",
    "sg:address":"Wackenweiler Strass1",
    "sg:city":"\u00dcberlingen",
    "sg:phone":"+49 7553/1447",
    "sg:postcode":"88662",
    "sg:province":"Baden-W\u00fcrttemberg",
    "wof:name":"E & S Sonnenstrom Ohg",
    "wof:placetype":"venue"
},
  "geometry": {"coordinates":[9.1592054367,47.7673187256],"type":"Point"}
}