{
  "type": "Feature",
  "properties": {
    "iso:country":"DE",
    "sg:address":"Hauptstr. 43",
    "sg:city":"Waldfischbach-Burgalben",
    "sg:phone":"+49 6333/5018",
    "sg:postcode":"67714",
    "sg:province":"Rheinland-Pfalz",
    "wof:name":"Otto Krempel",
    "wof:placetype":"venue"
},
  "geometry": {"coordinates":[7.6533031464,49.286907196],"type":"Point"}
}