{
  "type": "Feature",
  "properties": {
    "iso:country":"DE",
    "sg:address":"Hofmannstr. 11",
    "sg:city":"Wiesbaden",
    "sg:phone":"+49 611/560368",
    "sg:postcode":"65191",
    "sg:province":"Hessen",
    "wof:name":"Siegfried D\u00f6rr",
    "wof:placetype":"venue"
},
  "geometry": {"coordinates":[8.28041,50.08453],"type":"Point"}
}