{
  "type": "Feature",
  "properties": {
    "iso:country":"DE",
    "sg:address":"Scharnweberstr. 54",
    "sg:city":"Berlin",
    "sg:phone":"+49 30/4136836",
    "sg:postcode":"13405",
    "sg:province":"Berlin",
    "wof:name":"Gastst\u00e4tte Balkan-paprika",
    "wof:placetype":"venue"
},
  "geometry": {"coordinates":[13.3150949478,52.5674285889],"type":"Point"}
}