{
  "type": "Feature",
  "properties": {
    "iso:country":"DE",
    "sg:address":"Am Heinichenberg 28",
    "sg:city":"Bruchk\u00f6bel",
    "sg:phone":"+49 6181/75676",
    "sg:postcode":"63486",
    "sg:province":"Hessen",
    "wof:name":"Walter Schreiber Steuerberater",
    "wof:placetype":"venue"
},
  "geometry": {"coordinates":[8.9225721359,50.189491272],"type":"Point"}
}