{
  "type": "Feature",
  "properties": {
    "iso:country":"DE",
    "sg:address":"Annette-Kolb-Str. 40 a",
    "sg:city":"Ingolstadt",
    "sg:postcode":"85055",
    "sg:province":"Bayern",
    "wof:name":"1 Innovation Gmbh",
    "wof:placetype":"venue"
},
  "geometry": {"coordinates":[11.4388780594,48.7830924988],"type":"Point"}
}