{
  "type": "Feature",
  "properties": {
    "iso:country":"DE",
    "sg:address":"Stollberger Str. 33",
    "sg:city":"Neukirchen",
    "sg:postcode":"09221",
    "sg:province":"Sachsen",
    "wof:name":"Eifrisch-vertriebsges. Mbh",
    "wof:placetype":"venue"
},
  "geometry": {"coordinates":[12.85623,50.774841],"type":"Point"}
}