{
  "type": "Feature",
  "properties": {
    "iso:country":"DE",
    "sg:address":"Weststr. 2",
    "sg:city":"Dennheritz",
    "sg:phone":"+49 3763/78553",
    "sg:postcode":"08393",
    "sg:province":"Sachsen",
    "wof:name":"Kurt D\u00f6rr",
    "wof:placetype":"venue"
},
  "geometry": {"coordinates":[12.500163,50.818775],"type":"Point"}
}