{
  "type": "Feature",
  "properties": {
    "iso:country":"DE",
    "sg:address":"Lambert-von-B\u00fcren-Str. 3",
    "sg:city":"Gengenbach",
    "sg:phone":"+49 7803/96760",
    "sg:postcode":"77723",
    "sg:province":"Baden-W\u00fcrttemberg",
    "wof:name":"Werner Konrad Steuerberater",
    "wof:placetype":"venue"
},
  "geometry": {"coordinates":[8.0165967941,48.39894104],"type":"Point"}
}