{
  "type": "Feature",
  "properties": {
    "iso:country":"DE",
    "sg:address":"Lagerhausstr. 12b",
    "sg:city":"Garmisch-Partenkirchen",
    "sg:phone":"+49 8821/2622",
    "sg:postcode":"82467",
    "sg:province":"Bayern",
    "wof:name":"A. Ranzinger",
    "wof:placetype":"venue"
},
  "geometry": {"coordinates":[11.0996770859,47.489692688],"type":"Point"}
}