{
  "type": "Feature",
  "properties": {
    "iso:country":"DE",
    "sg:address":"Dransfelder Str. 9",
    "sg:city":"G\u00f6ttingen",
    "sg:phone":"+49 551/92252",
    "sg:postcode":"37079",
    "sg:province":"Niedersachsen",
    "wof:name":"Hotel Lindenhof Ellershausen",
    "wof:placetype":"venue"
},
  "geometry": {"coordinates":[9.87018013,51.5222892761],"type":"Point"}
}