{
  "type": "Feature",
  "properties": {
    "iso:country":"DE",
    "sg:address":"Lindenstr. 20",
    "sg:city":"Freilassing",
    "sg:phone":"+49 8654/1405",
    "sg:postcode":"83395",
    "sg:province":"Bayern",
    "wof:name":"Rosy S\u00fc\u00df",
    "wof:placetype":"venue"
},
  "geometry": {"coordinates":[12.9799814224,47.8395652771],"type":"Point"}
}