{
  "type": "Feature",
  "properties": {
    "iso:country":"DE",
    "sg:address":"Ostlandstr. 27",
    "sg:city":"Bordesholm",
    "sg:postcode":"24582",
    "sg:province":"Schleswig-Holstein",
    "wof:name":"Opel-club Bordesholm Reiner Militzer",
    "wof:placetype":"venue"
},
  "geometry": {"coordinates":[10.0375232697,54.1759872437],"type":"Point"}
}