{
  "type": "Feature",
  "properties": {
    "iso:country":"DE",
    "sg:address":"Lange Str. 8-10",
    "sg:city":"Rietberg",
    "sg:phone":"+49 4952/444020",
    "sg:postcode":"33397",
    "sg:province":"Nordrhein-Westfalen",
    "wof:name":"Neuenkirchener Maschinenfabrik Gmbh",
    "wof:placetype":"venue"
},
  "geometry": {"coordinates":[8.4259395599,51.8065948486],"type":"Point"}
}