{
  "type": "Feature",
  "properties": {
    "iso:country":"DE",
    "sg:address":"Buchenstr. 3",
    "sg:city":"Geltendorf",
    "sg:phone":"+49 8193/5402",
    "sg:postcode":"82269",
    "sg:province":"Bayern",
    "wof:name":"Benno Kurz",
    "wof:placetype":"venue"
},
  "geometry": {"coordinates":[11.037779808,48.1103248596],"type":"Point"}
}