{
  "type": "Feature",
  "properties": {
    "iso:country":"DE",
    "sg:address":"Pfortengasse 10",
    "sg:city":"Schleiz",
    "sg:phone":"+49 3663/402410",
    "sg:postcode":"07907",
    "sg:province":"Th\u00fcringen",
    "wof:name":"Herbert Jakob",
    "wof:placetype":"venue"
},
  "geometry": {"coordinates":[11.811133,50.579102],"type":"Point"}
}