{
  "type": "Feature",
  "properties": {
    "iso:country":"DE",
    "sg:address":"Marktplatz 37",
    "sg:city":"Velden",
    "sg:phone":"+49 8742/8147",
    "sg:postcode":"84149",
    "sg:province":"Bayern",
    "wof:name":"Josef Zehtner",
    "wof:placetype":"venue"
},
  "geometry": {"coordinates":[12.2548351288,48.3657608032],"type":"Point"}
}