{
  "type": "Feature",
  "properties": {
    "iso:country":"DE",
    "sg:address":"Hegelstr. 5",
    "sg:city":"Bayreuth",
    "sg:postcode":"95447",
    "sg:province":"Bayern",
    "wof:name":"Transico",
    "wof:placetype":"venue"
},
  "geometry": {"coordinates":[11.5747089386,49.9346656799],"type":"Point"}
}