{
  "type": "Feature",
  "properties": {
    "iso:country":"DE",
    "sg:address":"Rechbergstr. 12",
    "sg:city":"Kornwestheim",
    "sg:phone":"+49 7154/26327",
    "sg:postcode":"70806",
    "sg:province":"Baden-W\u00fcrttemberg",
    "wof:name":"Alfred Raible Architekt",
    "wof:placetype":"venue"
},
  "geometry": {"coordinates":[9.187569,48.857433],"type":"Point"}
}