{
  "type": "Feature",
  "properties": {
    "iso:country":"DE",
    "sg:address":"Berkenkopfplatz 13",
    "sg:city":"Ense",
    "sg:phone":"+49 2938/738",
    "sg:postcode":"59469",
    "sg:province":"Nordrhein-Westfalen",
    "wof:name":"Hubert Schnieder & Sohn Gmbh",
    "wof:placetype":"venue"
},
  "geometry": {"coordinates":[7.9593248367,51.5041999817],"type":"Point"}
}