{
  "type": "Feature",
  "properties": {
    "iso:country":"DE",
    "sg:address":"Arnst\u00e4dter Str. 31",
    "sg:city":"Kranichfeld",
    "sg:phone":"+49 36450/42643",
    "sg:postcode":"99448",
    "sg:province":"Th\u00fcringen",
    "wof:name":"Matthias Hunger Ingenieur",
    "wof:placetype":"venue"
},
  "geometry": {"coordinates":[11.2017183304,50.8519477844],"type":"Point"}
}