{
  "type": "Feature",
  "properties": {
    "iso:country":"DE",
    "sg:address":"Bahnhofstr. 7",
    "sg:city":"Nidda",
    "sg:phone":"+49 6043/2213",
    "sg:postcode":"63667",
    "sg:province":"Hessen",
    "wof:name":"Gambrinus-lichtspiele",
    "wof:placetype":"venue"
},
  "geometry": {"coordinates":[9.00636,50.413761],"type":"Point"}
}