{
  "type": "Feature",
  "properties": {
    "iso:country":"DE",
    "sg:address":"Hauptstr. 20",
    "sg:city":"Baiersdorf",
    "sg:phone":"+49 9133/2282",
    "sg:postcode":"91083",
    "sg:province":"Bayern",
    "wof:name":"Hotel Brandenburger Hof",
    "wof:placetype":"venue"
},
  "geometry": {"coordinates":[11.0319280624,49.6559028625],"type":"Point"}
}