{
  "type": "Feature",
  "properties": {
    "iso:country":"DE",
    "sg:address":"Lindenstr. 33",
    "sg:city":"Wefensleben",
    "sg:phone":"+49 39400/2157",
    "sg:postcode":"39365",
    "sg:province":"Sachsen-Anhalt",
    "wof:name":"Kinderheim Hans L\u00f6scher",
    "wof:placetype":"venue"
},
  "geometry": {"coordinates":[11.1549043655,52.1779327393],"type":"Point"}
}