{
  "type": "Feature",
  "properties": {
    "iso:country":"DE",
    "sg:address":"Schottlandstr 7",
    "sg:city":"Hemer",
    "sg:phone":"+49 2372/6730",
    "sg:postcode":"58675",
    "sg:province":"Nordrhein-Westfalen",
    "wof:name":"Drahtwaren Und Abdeckmaterial Henke",
    "wof:placetype":"venue"
},
  "geometry": {"coordinates":[7.803731,51.385052],"type":"Point"}
}