{
  "type": "Feature",
  "properties": {
    "iso:country":"DE",
    "sg:address":"Sprungbachstr. 72",
    "sg:city":"Bielefeld",
    "sg:phone":"+49 5205/70862",
    "sg:postcode":"33689",
    "sg:province":"Nordrhein-Westfalen",
    "wof:name":"Kolb-autokrane Kranverleih",
    "wof:placetype":"venue"
},
  "geometry": {"coordinates":[8.5889911652,51.9391517639],"type":"Point"}
}