{
  "type": "Feature",
  "properties": {
    "iso:country":"DE",
    "sg:address":"Gartenstrasse 2",
    "sg:city":"Herold",
    "sg:phone":"+49 6486",
    "sg:postcode":"56368",
    "sg:province":"Rheinland-Pfalz",
    "wof:name":"Willkommen Bei Auto Weber Spezial",
    "wof:placetype":"venue"
},
  "geometry": {"coordinates":[7.932799,50.279408],"type":"Point"}
}