{
  "type": "Feature",
  "properties": {
    "iso:country":"DE",
    "sg:address":"Heinder Str. 9",
    "sg:city":"Bad Salzdetfurth",
    "sg:phone":"+49 5064/95960",
    "sg:postcode":"31162",
    "sg:province":"Niedersachsen",
    "wof:name":"Wedekin Tankschutz Gmbh",
    "wof:placetype":"venue"
},
  "geometry": {"coordinates":[10.025551796,52.098449707],"type":"Point"}
}