{
  "type": "Feature",
  "properties": {
    "iso:country":"DE",
    "sg:address":"Gewerbepark Gr\u00fcner Weg 17",
    "sg:city":"Beckum",
    "sg:phone":"+49 2521/93950",
    "sg:postcode":"59269",
    "sg:province":"Nordrhein-Westfalen",
    "wof:name":"Leifhelm & Pelkmann Gmbh",
    "wof:placetype":"venue"
},
  "geometry": {"coordinates":[8.0389289856,51.7643737793],"type":"Point"}
}