{
  "type": "Feature",
  "properties": {
    "iso:country":"DE",
    "sg:address":"Odenthaler Str. 259",
    "sg:city":"Bergisch Gladbach",
    "sg:postcode":"51467",
    "sg:province":"Nordrhein-Westfalen",
    "wof:name":"Kath. \u00d6ffentliche Bibliothek Heilige Drei K\u00f6nige",
    "wof:placetype":"venue"
},
  "geometry": {"coordinates":[7.130301,51.003235],"type":"Point"}
}