{
  "type": "Feature",
  "properties": {
    "iso:country":"DE",
    "sg:address":"Martin-Luther-Str. 49",
    "sg:city":"Daaden",
    "sg:phone":"+49 2743/6122",
    "sg:postcode":"57567",
    "sg:province":"Rheinland-Pfalz",
    "wof:name":"Erhard He\u00df Heilpraktiker",
    "wof:placetype":"venue"
},
  "geometry": {"coordinates":[7.9800581932,50.7367706299],"type":"Point"}
}