{
  "type": "Feature",
  "properties": {
    "iso:country":"DE",
    "sg:address":"Im Liefeld 44",
    "sg:city":"D\u00fcsseldorf",
    "sg:phone":"+49 211/784282",
    "sg:postcode":"40227",
    "sg:province":"Nordrhein-Westfalen",
    "wof:name":"Ossenb\u00fchl Vermietung Verwaltungs Gmbh",
    "wof:placetype":"venue"
},
  "geometry": {"coordinates":[6.8141279221,51.2095947266],"type":"Point"}
}