{
  "type": "Feature",
  "properties": {
    "iso:country":"DE",
    "sg:address":"Hauptstr. 24",
    "sg:city":"Blankenheim",
    "sg:phone":"+49 2449/95200",
    "sg:postcode":"53945",
    "sg:province":"Nordrhein-Westfalen",
    "wof:name":"K. Pfeil Gmbh & Co. Kg",
    "wof:placetype":"venue"
},
  "geometry": {"coordinates":[6.661792,50.387787],"type":"Point"}
}