{
  "type": "Feature",
  "properties": {
    "iso:country":"DE",
    "sg:address":"Auf der Heide 40",
    "sg:city":"Stolberg",
    "sg:phone":"+49 2402/30304",
    "sg:postcode":"52223",
    "sg:province":"Nordrhein-Westfalen",
    "wof:name":"Auf Der Heide",
    "wof:placetype":"venue"
},
  "geometry": {"coordinates":[6.2133560181,50.7313652039],"type":"Point"}
}