{
  "type": "Feature",
  "properties": {
    "iso:country":"DE",
    "sg:address":"Im Sack 15",
    "sg:city":"Warstein",
    "sg:phone":"+49 2902/1847",
    "sg:postcode":"59581",
    "sg:province":"Nordrhein-Westfalen",
    "wof:name":"C. Arndt",
    "wof:placetype":"venue"
},
  "geometry": {"coordinates":[8.3536701202,51.4467964172],"type":"Point"}
}