{
  "type": "Feature",
  "properties": {
    "iso:country":"DE",
    "sg:address":"Siegesstr. 23",
    "sg:city":"M\u00fcnchen",
    "sg:phone":"+49 89/38388413",
    "sg:postcode":"80802",
    "sg:province":"Bayern",
    "wof:name":"Music Shop Best Service Kandler & Greil Gmbh",
    "wof:placetype":"venue"
},
  "geometry": {"coordinates":[11.5880155563,48.1605796814],"type":"Point"}
}