{
  "type": "Feature",
  "properties": {
    "iso:country":"DE",
    "sg:address":"Bismarckstr. 7",
    "sg:city":"Berlin",
    "sg:phone":"+49 30/7951987",
    "sg:postcode":"12157",
    "sg:province":"Berlin",
    "wof:name":"Groschen Keller",
    "wof:placetype":"venue"
},
  "geometry": {"coordinates":[13.339050293,52.4621696472],"type":"Point"}
}