{
  "type": "Feature",
  "properties": {
    "iso:country":"DE",
    "sg:address":"Obere Steinfurt 8",
    "sg:city":"Stolberg",
    "sg:postcode":"52222",
    "sg:province":"Nordrhein-Westfalen",
    "wof:name":"Frischmarkt Endt Lojewski Stolberg Gmbh",
    "wof:placetype":"venue"
},
  "geometry": {"coordinates":[6.2175598145,50.7825889587],"type":"Point"}
}