{
  "type": "Feature",
  "properties": {
    "iso:country":"DE",
    "sg:address":"Robert-Bosch-Str 6",
    "sg:city":"Plattling",
    "sg:phone":"+49 9931/91790",
    "sg:postcode":"94447",
    "sg:province":"Bayern",
    "wof:name":"S\u00fcdluft Systemtechnik Gmbh & Co Kg",
    "wof:placetype":"venue"
},
  "geometry": {"coordinates":[12.877058,48.798794],"type":"Point"}
}