{
  "type": "Feature",
  "properties": {
    "iso:country":"DE",
    "sg:address":"Schillerstr. 1a",
    "sg:city":"Wei\u00dfenberg",
    "sg:phone":"+49 35876/4810",
    "sg:postcode":"02627",
    "sg:province":"Sachsen",
    "wof:name":"F\u00f6rdergurtservice Inh. Uwe Gro\u00df",
    "wof:placetype":"venue"
},
  "geometry": {"coordinates":[14.6595582962,51.1965866089],"type":"Point"}
}