{
  "type": "Feature",
  "properties": {
    "iso:country":"DE",
    "sg:address":"Dom\u00e4nenweg 1",
    "sg:city":"Coppenbr\u00fcgge",
    "sg:phone":"+49 5156/96100",
    "sg:postcode":"31863",
    "sg:province":"Niedersachsen",
    "wof:name":"Siegfried Templin Verwaltungs Gmbh",
    "wof:placetype":"venue"
},
  "geometry": {"coordinates":[9.540481,52.118942],"type":"Point"}
}