{
  "type": "Feature",
  "properties": {
    "iso:country":"DE",
    "sg:address":"Oestertalstr. 26",
    "sg:city":"Plettenberg",
    "sg:phone":"+49 4923/9170071",
    "sg:postcode":"58840",
    "sg:province":"Nordrhein-Westfalen",
    "wof:name":"Marl Gmbh",
    "wof:placetype":"venue"
},
  "geometry": {"coordinates":[7.86146,51.190781],"type":"Point"}
}