{
  "type": "Feature",
  "properties": {
    "iso:country":"DE",
    "sg:address":"Bahnhofstr. 2",
    "sg:city":"Bad H\u00f6nningen",
    "sg:phone":"+49 2635/95180",
    "sg:postcode":"53557",
    "sg:province":"Rheinland-Pfalz",
    "wof:name":"First Reiseb\u00fcro",
    "wof:placetype":"venue"
},
  "geometry": {"coordinates":[7.3101401329,50.5135002136],"type":"Point"}
}