{
  "type": "Feature",
  "properties": {
    "iso:country":"DE",
    "sg:address":"Hauptstr. 9d",
    "sg:city":"Zudar",
    "sg:phone":"+49 38304/66027",
    "sg:postcode":"18574",
    "sg:province":"Mecklenburg-Vorpommern",
    "wof:name":"G. Knoll",
    "wof:placetype":"venue"
},
  "geometry": {"coordinates":[13.3507480621,54.2614593506],"type":"Point"}
}