{
  "type": "Feature",
  "properties": {
    "iso:country":"DE",
    "sg:address":"Am Bichl 2",
    "sg:city":"Dietramszell",
    "sg:phone":"+49 8024/307633",
    "sg:postcode":"83623",
    "sg:province":"Bayern",
    "wof:name":"Roland Eckert",
    "wof:placetype":"venue"
},
  "geometry": {"coordinates":[11.6368179321,47.9018211365],"type":"Point"}
}