{
  "type": "Feature",
  "properties": {
    "iso:country":"DE",
    "sg:address":"Friedenstr. 85",
    "sg:city":"Pforzheim",
    "sg:phone":"+49 7231/27618",
    "sg:postcode":"75173",
    "sg:province":"Baden-W\u00fcrttemberg",
    "wof:name":"Dr. W. Rhein Wirtschaftspr\u00fcfer",
    "wof:placetype":"venue"
},
  "geometry": {"coordinates":[8.6948385239,48.8770294189],"type":"Point"}
}