{
  "type": "Feature",
  "properties": {
    "iso:country":"DE",
    "sg:address":"Schlo\u00dfbezirk 6",
    "sg:city":"Karlsruhe",
    "sg:phone":"+49 721/607879",
    "sg:postcode":"76131",
    "sg:province":"Baden-W\u00fcrttemberg",
    "wof:name":"Badische Weinstube",
    "wof:placetype":"venue"
},
  "geometry": {"coordinates":[8.4057226181,49.0132026672],"type":"Point"}
}