{
  "type": "Feature",
  "properties": {
    "iso:country":"DE",
    "sg:address":"Herderplatz 15",
    "sg:city":"Weimar",
    "sg:phone":"+49 3643/905684",
    "sg:postcode":"99423",
    "sg:province":"Th\u00fcringen",
    "wof:name":"Hertel-backwaren Und Gastronomie Gmbh",
    "wof:placetype":"venue"
},
  "geometry": {"coordinates":[11.330026,50.981129],"type":"Point"}
}