{
  "type": "Feature",
  "properties": {
    "iso:country":"DE",
    "sg:address":"Weichselstr. 7",
    "sg:city":"Berlin",
    "sg:phone":"+49 30/6241731",
    "sg:postcode":"12043",
    "sg:province":"Berlin",
    "wof:name":"Gastst\u00e4tte Union-st\u00fcbchen",
    "wof:placetype":"venue"
},
  "geometry": {"coordinates":[13.4331560135,52.484172821],"type":"Point"}
}