{
  "type": "Feature",
  "properties": {
    "iso:country":"DE",
    "sg:address":"Frankfurter Strasse 13",
    "sg:city":"Steinbach/Ts",
    "sg:phone":"+49 6171",
    "sg:postcode":"61449",
    "sg:province":"Hessen",
    "wof:name":"Katzensitter-club",
    "wof:placetype":"venue"
},
  "geometry": {"coordinates":[8.5810642242,50.1656188965],"type":"Point"}
}