{
  "type": "Feature",
  "properties": {
    "iso:country":"DE",
    "sg:address":"R\u00f6hrborngasse 60",
    "sg:city":"Frankfurt",
    "sg:phone":"+49 6109/35391",
    "sg:postcode":"60388",
    "sg:province":"Hessen",
    "wof:name":"Wilhelm V\u00f6lker",
    "wof:placetype":"venue"
},
  "geometry": {"coordinates":[8.755262,50.150288],"type":"Point"}
}