{
  "type": "Feature",
  "properties": {
    "iso:country":"DE",
    "sg:address":"Stahlstr. 9",
    "sg:city":"R\u00fcsselsheim",
    "sg:postcode":"65428",
    "sg:province":"Hessen",
    "wof:name":"Aldi Gmbh & Co. Kg",
    "wof:placetype":"venue"
},
  "geometry": {"coordinates":[8.4336223602,49.976524353],"type":"Point"}
}