{
  "type": "Feature",
  "properties": {
    "iso:country":"DE",
    "sg:address":"Lindenstr. 13",
    "sg:city":"Niederzier",
    "sg:phone":"+49 2428/6575",
    "sg:postcode":"52382",
    "sg:province":"Nordrhein-Westfalen",
    "wof:name":"J\u00fcrgen Vogt",
    "wof:placetype":"venue"
},
  "geometry": {"coordinates":[6.5013980865,50.8575515747],"type":"Point"}
}