{
  "type": "Feature",
  "properties": {
    "iso:country":"DE",
    "sg:address":"M\u00fcnchener Ring 2 / B",
    "sg:city":"Schkeuditz",
    "sg:phone":"+49 34204/65360",
    "sg:postcode":"04435",
    "sg:province":"Sachsen",
    "wof:name":"Deliva-textilvertrieb E. K.",
    "wof:placetype":"venue"
},
  "geometry": {"coordinates":[12.1989345551,51.4009361267],"type":"Point"}
}