{
  "type": "Feature",
  "properties": {
    "iso:country":"DE",
    "sg:address":"Noeggerathstr. 1",
    "sg:city":"Bonn",
    "sg:phone":"+49 228/653557",
    "sg:postcode":"53111",
    "sg:province":"Nordrhein-Westfalen",
    "wof:name":"Gesellschaft F\u00fcr Industrie- Bedarf Eich & Co.",
    "wof:placetype":"venue"
},
  "geometry": {"coordinates":[7.0947551727,50.7344665527],"type":"Point"}
}