{
  "type": "Feature",
  "properties": {
    "iso:country":"DE",
    "sg:address":"Altst\u00e4dter Kirchenweg 29",
    "sg:city":"Pforzheim",
    "sg:phone":"+49 7231/102999",
    "sg:postcode":"75175",
    "sg:province":"Baden-W\u00fcrttemberg",
    "wof:name":"Schaefer Edelmetall- Handels- Gmbh",
    "wof:placetype":"venue"
},
  "geometry": {"coordinates":[8.71015,48.890919],"type":"Point"}
}