{
  "type": "Feature",
  "properties": {
    "iso:country":"DE",
    "sg:address":"Zerrennerstr. 34",
    "sg:city":"Pforzheim",
    "sg:phone":"+49 7231/356776",
    "sg:postcode":"75172",
    "sg:province":"Baden-W\u00fcrttemberg",
    "wof:name":"Maharadia",
    "wof:placetype":"venue"
},
  "geometry": {"coordinates":[8.6946172714,48.8910713196],"type":"Point"}
}