{
  "type": "Feature",
  "properties": {
    "iso:country":"DE",
    "sg:address":"Kriekauer Str. 28",
    "sg:city":"Taucha",
    "sg:postcode":"04425",
    "sg:province":"Sachsen",
    "wof:name":"Hartmut Nevoigt",
    "wof:placetype":"venue"
},
  "geometry": {"coordinates":[12.4974155426,51.3757781982],"type":"Point"}
}