{
  "type": "Feature",
  "properties": {
    "iso:country":"DE",
    "sg:address":"Johann-Sebastian-Bach-Str. 5",
    "sg:city":"Bammental",
    "sg:phone":"+49 6223/40504",
    "sg:postcode":"69245",
    "sg:province":"Baden-W\u00fcrttemberg",
    "wof:name":"H. Reindl",
    "wof:placetype":"venue"
},
  "geometry": {"coordinates":[8.7804889679,49.3522338867],"type":"Point"}
}