{
  "type": "Feature",
  "properties": {
    "iso:country":"DE",
    "sg:address":"Niederwaldstr. 7",
    "sg:city":"Rastatt",
    "sg:phone":"+49 7222/150988",
    "sg:postcode":"76437",
    "sg:province":"Baden-W\u00fcrttemberg",
    "wof:name":"Badische Wohnbau Gmbh",
    "wof:placetype":"venue"
},
  "geometry": {"coordinates":[8.21798,48.862869],"type":"Point"}
}