{
  "type": "Feature",
  "properties": {
    "iso:country":"DE",
    "sg:address":"Johann-Flierl-Str. 18",
    "sg:city":"Neuendettelsau",
    "sg:phone":"+49 9874/1454",
    "sg:postcode":"91564",
    "sg:province":"Bayern",
    "wof:name":"Ev. Luth. Pfarramt",
    "wof:placetype":"venue"
},
  "geometry": {"coordinates":[10.7865858078,49.2869033813],"type":"Point"}
}