{
  "type": "Feature",
  "properties": {
    "iso:country":"DE",
    "sg:address":"Neusser Str. 27",
    "sg:city":"D\u00fcsseldorf",
    "sg:phone":"+49 211/392304",
    "sg:postcode":"40219",
    "sg:province":"Nordrhein-Westfalen",
    "wof:name":"Horst Und Klaus M\u00fclders Gmbh",
    "wof:placetype":"venue"
},
  "geometry": {"coordinates":[6.766117,51.217743],"type":"Point"}
}