{
  "type": "Feature",
  "properties": {
    "iso:country":"DE",
    "sg:address":"Hermannstr. 51a",
    "sg:city":"Neunkirchen",
    "sg:phone":"+49 6821/89823",
    "sg:postcode":"66538",
    "sg:province":"Saarland",
    "wof:name":"Oliver Rinder",
    "wof:placetype":"venue"
},
  "geometry": {"coordinates":[7.18371,49.333309],"type":"Point"}
}