{
  "type": "Feature",
  "properties": {
    "iso:country":"DE",
    "sg:address":"Marktplatz 8::",
    "sg:city":"Gr\u00e4fenberg",
    "sg:phone":"+49 9192/7070",
    "sg:postcode":"91322",
    "sg:province":"Bayern",
    "wof:name":"Verinigte Raiffeisenbanken Gr\u00e4fenberg-forchheim-eschenau-heroldsberg Eg",
    "wof:placetype":"venue"
},
  "geometry": {"coordinates":[11.249645,49.645012],"type":"Point"}
}