{
  "type": "Feature",
  "properties": {
    "iso:country":"DE",
    "sg:address":"Bahnhofstr. 2",
    "sg:city":"Hennickendorf",
    "sg:phone":"+49 33434/7255",
    "sg:postcode":"15378",
    "sg:province":"Brandenburg",
    "wof:name":"Pension Twrdek",
    "wof:placetype":"venue"
},
  "geometry": {"coordinates":[13.8467140198,52.5077018738],"type":"Point"}
}