{
  "type": "Feature",
  "properties": {
    "iso:country":"DE",
    "sg:address":"Gl\u00fcckaufstr. 41",
    "sg:city":"M\u00fclheim",
    "sg:phone":"+49 208/487213",
    "sg:postcode":"45481",
    "sg:province":"Nordrhein-Westfalen",
    "wof:name":"Helmut Tellmann Gmbh",
    "wof:placetype":"venue"
},
  "geometry": {"coordinates":[6.8602108955,51.3682670593],"type":"Point"}
}