{
  "type": "Feature",
  "properties": {
    "iso:country":"DE",
    "sg:address":"Christian-Wirth-Str. 18",
    "sg:city":"Fulda",
    "sg:phone":"+49 4966/194400",
    "sg:postcode":"36043",
    "sg:province":"Hessen",
    "wof:name":"Boc Computersysteme Gmbh",
    "wof:placetype":"venue"
},
  "geometry": {"coordinates":[9.6819019318,50.5241699219],"type":"Point"}
}