{
  "type": "Feature",
  "properties": {
    "iso:country":"DE",
    "sg:address":"Landgerichtsgasse 1",
    "sg:city":"M\u00fcnnerstadt",
    "sg:phone":"+49 9733/1255",
    "sg:postcode":"97702",
    "sg:province":"Bayern",
    "wof:name":"Otto Pfennig",
    "wof:placetype":"venue"
},
  "geometry": {"coordinates":[10.195181,50.247662],"type":"Point"}
}