{
  "type": "Feature",
  "properties": {
    "iso:country":"DE",
    "sg:address":"Ferdinand-Wallbrecht-Str. 13",
    "sg:city":"Hannover",
    "sg:phone":"+49 511/628262",
    "sg:postcode":"30163",
    "sg:province":"Niedersachsen",
    "wof:name":"Ahrens Werbeagentur & Fotosatz Gmbh",
    "wof:placetype":"venue"
},
  "geometry": {"coordinates":[9.7487535477,52.3902320862],"type":"Point"}
}