{
  "type": "Feature",
  "properties": {
    "iso:country":"DE",
    "sg:address":"Hohnerkamp 4c",
    "sg:city":"Hamburg",
    "sg:phone":"+49 40/67047991",
    "sg:postcode":"22175",
    "sg:province":"Hamburg",
    "wof:name":"Die Eventmaker",
    "wof:placetype":"venue"
},
  "geometry": {"coordinates":[10.089657,53.618408],"type":"Point"}
}