{
  "type": "Feature",
  "properties": {
    "iso:country":"DE",
    "sg:address":"Schillerstr. 15",
    "sg:city":"R\u00fcsselsheim",
    "sg:postcode":"65428",
    "sg:province":"Hessen",
    "wof:name":"Sozialberatungsstelle",
    "wof:placetype":"venue"
},
  "geometry": {"coordinates":[8.422754,49.998249],"type":"Point"}
}