{
  "type": "Feature",
  "properties": {
    "iso:country":"DE",
    "sg:address":"Noeggerathstr. 32",
    "sg:city":"Bonn",
    "sg:phone":"+49 228/632583",
    "sg:postcode":"53111",
    "sg:province":"Nordrhein-Westfalen",
    "wof:name":"Hans-a. Und Beate Vogel Architekten",
    "wof:placetype":"venue"
},
  "geometry": {"coordinates":[7.092462,50.735134],"type":"Point"}
}