{
  "type": "Feature",
  "properties": {
    "iso:country":"DE",
    "sg:address":"Veldenzer Str. 21",
    "sg:city":"M\u00fclheim",
    "sg:phone":"+49 6534/8807",
    "sg:postcode":"54486",
    "sg:province":"Rheinland-Pfalz",
    "wof:name":"Dieter Caspari Rechtsanwalt",
    "wof:placetype":"venue"
},
  "geometry": {"coordinates":[7.0085439682,49.9095916748],"type":"Point"}
}