{
  "type": "Feature",
  "properties": {
    "iso:country":"DE",
    "sg:address":"Gewerbeweg 5",
    "sg:city":"Hardegsen",
    "sg:phone":"+49 5505/2439",
    "sg:postcode":"37181",
    "sg:province":"Niedersachsen",
    "wof:name":"August Heinen",
    "wof:placetype":"venue"
},
  "geometry": {"coordinates":[9.83325,51.648289],"type":"Point"}
}