{
  "type": "Feature",
  "properties": {
    "iso:country":"DE",
    "sg:address":"Carl-Zeiss-Str. 5",
    "sg:city":"Wiehl",
    "sg:phone":"+49 2261/790853",
    "sg:postcode":"51674",
    "sg:province":"Nordrhein-Westfalen",
    "wof:name":"Linder-rolf Fenster Gmbh",
    "wof:placetype":"venue"
},
  "geometry": {"coordinates":[7.531135,50.974148],"type":"Point"}
}