{
  "type": "Feature",
  "properties": {
    "iso:country":"DE",
    "sg:address":"Hochkreuzallee 171",
    "sg:city":"Bonn",
    "sg:phone":"+49 228/316051",
    "sg:postcode":"53175",
    "sg:province":"Nordrhein-Westfalen",
    "wof:name":"Kraft Immobilien Gmbh",
    "wof:placetype":"venue"
},
  "geometry": {"coordinates":[7.1316690445,50.6922607422],"type":"Point"}
}