{
  "type": "Feature",
  "properties": {
    "iso:country":"DE",
    "sg:address":"Karl-Marx-Ring 35",
    "sg:city":"M\u00fcnchen",
    "sg:postcode":"81735",
    "sg:province":"Bayern",
    "wof:name":"Riedl Gmbh",
    "wof:placetype":"venue"
},
  "geometry": {"coordinates":[11.6550998688,48.1092987061],"type":"Point"}
}