{
  "type": "Feature",
  "properties": {
    "iso:country":"DE",
    "sg:address":"Haag 14",
    "sg:city":"Luckenwalde",
    "sg:phone":"+49 3371/633242",
    "sg:postcode":"14943",
    "sg:province":"Brandenburg",
    "wof:name":"Kurt Stielert",
    "wof:placetype":"venue"
},
  "geometry": {"coordinates":[13.171877,52.090626],"type":"Point"}
}