{
  "type": "Feature",
  "properties": {
    "iso:country":"DE",
    "sg:address":"Kalthofweg",
    "sg:city":"Essen",
    "sg:postcode":"45277",
    "sg:province":"Nordrhein-Westfalen",
    "wof:name":"Erotik Club",
    "wof:placetype":"venue"
},
  "geometry": {"coordinates":[7.079655,51.426247],"type":"Point"}
}