{
  "type": "Feature",
  "properties": {
    "iso:country":"DE",
    "sg:address":"Auf Periol 3",
    "sg:city":"Wasserliesch",
    "sg:postcode":"54332",
    "sg:province":"Rheinland-Pfalz",
    "wof:name":"Assist Krankenpflege Zu Hause Gmbh",
    "wof:placetype":"venue"
},
  "geometry": {"coordinates":[6.53453,49.708961],"type":"Point"}
}