{
  "type": "Feature",
  "properties": {
    "iso:country":"DE",
    "sg:address":"Dorfstr. 22",
    "sg:city":"S\u00f6llenthin",
    "sg:postcode":"19339",
    "sg:province":"Brandenburg",
    "wof:name":"Prunus Betratungs- U. Handels- Gesellschaft Mbh",
    "wof:placetype":"venue"
},
  "geometry": {"coordinates":[12.0288505554,52.9583969116],"type":"Point"}
}