{
  "type": "Feature",
  "properties": {
    "iso:country":"DE",
    "sg:address":"Kurhausstr. 3",
    "sg:city":"Bad Neustadt",
    "sg:phone":"+49 9771/2390",
    "sg:postcode":"97616",
    "sg:province":"Bayern",
    "wof:name":"Kath. Pfarramt St. St. Jakobus D.\u00c4.",
    "wof:placetype":"venue"
},
  "geometry": {"coordinates":[10.2233743668,50.3156890869],"type":"Point"}
}