{
  "type": "Feature",
  "properties": {
    "iso:country":"DE",
    "sg:address":"Talstr. 5a",
    "sg:city":"Breitenbrunn",
    "sg:phone":"+49 3774/27546",
    "sg:postcode":"08359",
    "sg:province":"Sachsen",
    "wof:name":"Planen Und Bauen Hima- Wohnungs- U. Gewerbebau Gmbh",
    "wof:placetype":"venue"
},
  "geometry": {"coordinates":[12.786965,50.499371],"type":"Point"}
}