{
  "type": "Feature",
  "properties": {
    "iso:country":"DE",
    "sg:address":"Gartenweg 12",
    "sg:city":"Bad Salzdetfurth",
    "sg:phone":"+49 5060/9000",
    "sg:postcode":"31162",
    "sg:province":"Niedersachsen",
    "wof:name":"Eisenberger Gmbh",
    "wof:placetype":"venue"
},
  "geometry": {"coordinates":[10.010149,52.065224],"type":"Point"}
}