{
  "type": "Feature",
  "properties": {
    "iso:country":"DE",
    "sg:address":"Altstadtstr. 13",
    "sg:city":"Leverkusen",
    "sg:phone":"+49 2171/742895",
    "sg:postcode":"51379",
    "sg:province":"Nordrhein-Westfalen",
    "wof:name":"Kolping Besch\u00e4ftigungsges. Mbh",
    "wof:placetype":"venue"
},
  "geometry": {"coordinates":[7.002193,51.066765],"type":"Point"}
}