{
  "type": "Feature",
  "properties": {
    "iso:country":"DE",
    "sg:address":"Lenther Str. 18",
    "sg:city":"Hannover",
    "sg:phone":"+49 511/4728970",
    "sg:postcode":"30455",
    "sg:province":"Niedersachsen",
    "wof:name":"Hotel-restaurant Kischers Landhaus",
    "wof:placetype":"venue"
},
  "geometry": {"coordinates":[9.6674461365,52.3557014465],"type":"Point"}
}