{
  "type": "Feature",
  "properties": {
    "iso:country":"DE",
    "sg:address":"Kanalstr. 73",
    "sg:city":"Berlin",
    "sg:phone":"+49 30/5351115",
    "sg:postcode":"12357",
    "sg:province":"Berlin",
    "wof:name":"Kulicke Kranservice K\u00f6penick Gmbh",
    "wof:placetype":"venue"
},
  "geometry": {"coordinates":[13.503687,52.428047],"type":"Point"}
}