{
  "type": "Feature",
  "properties": {
    "iso:country":"DE",
    "sg:address":"Baarleyweg 12",
    "sg:city":"Gerolstein",
    "sg:phone":"+49 6591/7273",
    "sg:postcode":"54568",
    "sg:province":"Rheinland-Pfalz",
    "wof:name":"Michael Blotzki",
    "wof:placetype":"venue"
},
  "geometry": {"coordinates":[6.6989188194,50.2209777832],"type":"Point"}
}