{
  "type": "Feature",
  "properties": {
    "iso:country":"DE",
    "sg:address":"Franz-Bl\u00e4si-Str. 17",
    "sg:city":"Bruchsal",
    "sg:phone":"+49 7251/85054",
    "sg:postcode":"76646",
    "sg:province":"Baden-W\u00fcrttemberg",
    "wof:name":"Digital Magic",
    "wof:placetype":"venue"
},
  "geometry": {"coordinates":[8.593918,49.128345],"type":"Point"}
}