{
  "type": "Feature",
  "properties": {
    "iso:country":"DE",
    "sg:address":"Wiederitzscher Str. 19",
    "sg:city":"Leipzig",
    "sg:phone":"+49 341/5640747",
    "sg:postcode":"04155",
    "sg:province":"Sachsen",
    "wof:name":"Grossmann Grundst\u00fccksges. Mbh",
    "wof:placetype":"venue"
},
  "geometry": {"coordinates":[12.3584671021,51.3643112183],"type":"Point"}
}