{
  "type": "Feature",
  "properties": {
    "iso:country":"DE",
    "sg:address":"R\u00f6nsahler Weg 22",
    "sg:city":"Marienheide",
    "sg:phone":"+49 2269/92880",
    "sg:postcode":"51709",
    "sg:province":"Nordrhein-Westfalen",
    "wof:name":"B\u00f6ckelt Gmbh Entwicklung Und Produktion",
    "wof:placetype":"venue"
},
  "geometry": {"coordinates":[7.499746,51.104637],"type":"Point"}
}