{
  "type": "Feature",
  "properties": {
    "iso:country":"DE",
    "sg:address":"Lange Str. 13",
    "sg:city":"Bad Salzuflen",
    "sg:phone":"+49 5222/40638",
    "sg:postcode":"32105",
    "sg:province":"Nordrhein-Westfalen",
    "wof:name":"Rolf T\u00f6lle",
    "wof:placetype":"venue"
},
  "geometry": {"coordinates":[8.7461500168,52.0831451416],"type":"Point"}
}