{
  "type": "Feature",
  "properties": {
    "iso:country":"DE",
    "sg:address":"Hauptstr. 440",
    "sg:city":"K\u00f6nigswinter",
    "sg:phone":"+49 2223/22656",
    "sg:postcode":"53639",
    "sg:province":"Nordrhein-Westfalen",
    "wof:name":"Josef K\u00e4ufer Personenschiffahrt",
    "wof:placetype":"venue"
},
  "geometry": {"coordinates":[7.194786,50.672779],"type":"Point"}
}