{
  "type": "Feature",
  "properties": {
    "iso:country":"DE",
    "sg:address":"Alrunastr. 6",
    "sg:city":"Cham",
    "sg:phone":"+49 9971/79327",
    "sg:postcode":"93413",
    "sg:province":"Bayern",
    "wof:name":"Dolomiti",
    "wof:placetype":"venue"
},
  "geometry": {"coordinates":[12.665077,49.218922],"type":"Point"}
}