{
  "type": "Feature",
  "properties": {
    "iso:country":"DE",
    "sg:address":"W\u00f6rdemanns Weg 36",
    "sg:city":"Hamburg",
    "sg:phone":"+49 40/543870",
    "sg:postcode":"22527",
    "sg:province":"Hamburg",
    "wof:name":"Bruhn Industrie-vermittlungs- Service Gmbh",
    "wof:placetype":"venue"
},
  "geometry": {"coordinates":[9.9273672104,53.5983200073],"type":"Point"}
}