{
  "type": "Feature",
  "properties": {
    "iso:country":"DE",
    "sg:address":"Bahnhofstr. 24",
    "sg:city":"Bad Salzschlirf",
    "sg:phone":"+49 6648/2370",
    "sg:postcode":"36364",
    "sg:province":"Hessen",
    "wof:name":"Kurheim St. Bonifatius",
    "wof:placetype":"venue"
},
  "geometry": {"coordinates":[9.5029640198,50.626285553],"type":"Point"}
}