{
  "type": "Feature",
  "properties": {
    "iso:country":"DE",
    "sg:address":"Dr. Aignerstr. 15",
    "sg:city":"Amberg",
    "sg:phone":"+49 9621/47290",
    "sg:postcode":"92224",
    "sg:province":"Bayern",
    "wof:name":"Amberger K\u00dchltechnik Gmbh",
    "wof:placetype":"venue"
},
  "geometry": {"coordinates":[11.846568,49.433651],"type":"Point"}
}