{
  "type": "Feature",
  "properties": {
    "iso:country":"DE",
    "sg:address":"Schustergasse 8",
    "sg:city":"Speyer",
    "sg:phone":"+49 6232/28080",
    "sg:postcode":"67346",
    "sg:province":"Rheinland-Pfalz",
    "wof:name":"Weras Moden",
    "wof:placetype":"venue"
},
  "geometry": {"coordinates":[8.437002,49.316868],"type":"Point"}
}