{
  "type": "Feature",
  "properties": {
    "iso:country":"DE",
    "sg:address":"Alter Deichsweg 66",
    "sg:city":"Wilhelmshaven",
    "sg:phone":"+49 4421/304525",
    "sg:postcode":"26384",
    "sg:province":"Niedersachsen",
    "wof:name":"Manfred Hiller",
    "wof:placetype":"venue"
},
  "geometry": {"coordinates":[8.1435308456,53.5281867981],"type":"Point"}
}