{
  "type": "Feature",
  "properties": {
    "iso:country":"DE",
    "sg:address":"Am Brauhaus 9",
    "sg:city":"Dresden",
    "sg:postcode":"01099",
    "sg:province":"Sachsen",
    "wof:name":"Immosan Gmbh",
    "wof:placetype":"venue"
},
  "geometry": {"coordinates":[13.779496,51.068546],"type":"Point"}
}