{
  "type": "Feature",
  "properties": {
    "iso:country":"DE",
    "sg:address":"Friedrichstr. 67",
    "sg:city":"Berlin",
    "sg:phone":"+49 30/20945400",
    "sg:postcode":"10117",
    "sg:province":"Berlin",
    "wof:name":"Tishman Speyer Properties Deutschland Gmbh",
    "wof:placetype":"venue"
},
  "geometry": {"coordinates":[13.389799118,52.5124206543],"type":"Point"}
}