{
  "type": "Feature",
  "properties": {
    "iso:country":"DE",
    "sg:address":"T\u00f6lzer Str. 35",
    "sg:city":"Lenggries",
    "sg:postcode":"83661",
    "sg:province":"Bayern",
    "wof:name":"Autohaus Zens Verwaltungs Gmbh",
    "wof:placetype":"venue"
},
  "geometry": {"coordinates":[11.5733146667,47.687625885],"type":"Point"}
}