{
  "type": "Feature",
  "properties": {
    "iso:country":"DE",
    "sg:address":"Markt 13",
    "sg:city":"Rochlitz",
    "sg:postcode":"09306",
    "sg:province":"Sachsen",
    "wof:name":"Wolfgang H\u00e4hnchen",
    "wof:placetype":"venue"
},
  "geometry": {"coordinates":[12.79916,51.045597],"type":"Point"}
}