{
  "type": "Feature",
  "properties": {
    "iso:country":"DE",
    "sg:address":"\u00d6lm\u00fchle 3",
    "sg:city":"Leutkirch",
    "sg:phone":"+49 7561/6066",
    "sg:postcode":"88299",
    "sg:province":"Baden-W\u00fcrttemberg",
    "wof:name":"Gkp-gummi- Und Kunststoff- Produkte Verwaltungs-gmbh",
    "wof:placetype":"venue"
},
  "geometry": {"coordinates":[10.058966,47.826046],"type":"Point"}
}