{
  "type": "Feature",
  "properties": {
    "iso:country":"DE",
    "sg:address":"L\u00f6he 2",
    "sg:city":"Himmelpforten",
    "sg:phone":"+49 4144/210291",
    "sg:postcode":"21709",
    "sg:province":"Niedersachsen",
    "wof:name":"Hand In Hand",
    "wof:placetype":"venue"
},
  "geometry": {"coordinates":[9.309481,53.624046],"type":"Point"}
}