{
  "type": "Feature",
  "properties": {
    "iso:country":"DE",
    "sg:address":"Ernst-Barlach-Str. 4",
    "sg:city":"Osterholz-Scharmbeck",
    "sg:phone":"+49 4791/7678",
    "sg:postcode":"27711",
    "sg:province":"Niedersachsen",
    "wof:name":"Heinz-georg Mehrtens",
    "wof:placetype":"venue"
},
  "geometry": {"coordinates":[8.7918949127,53.2372398376],"type":"Point"}
}