{
  "type": "Feature",
  "properties": {
    "iso:country":"DE",
    "sg:address":"Steinmeisterweg 51",
    "sg:city":"Berlin",
    "sg:phone":"+49 30/36281136",
    "sg:postcode":"13593",
    "sg:province":"Berlin",
    "wof:name":"Borchers Malerei Gmbh",
    "wof:placetype":"venue"
},
  "geometry": {"coordinates":[13.175505,52.515732],"type":"Point"}
}