{
  "type": "Feature",
  "properties": {
    "iso:country":"DE",
    "sg:address":"Grenzstr. 47",
    "sg:city":"Gelsenkirchen",
    "sg:phone":"+49 209/40940",
    "sg:postcode":"45881",
    "sg:province":"Nordrhein-Westfalen",
    "wof:name":"Sozialberatungsstelle Arbeiterwohlfahrt",
    "wof:placetype":"venue"
},
  "geometry": {"coordinates":[7.088513,51.51688],"type":"Point"}
}