{
  "type": "Feature",
  "properties": {
    "iso:country":"DE",
    "sg:address":"Magdeburger Kamp 12",
    "sg:city":"Goslar",
    "sg:phone":"+49 5321/50000",
    "sg:postcode":"38644",
    "sg:province":"Niedersachsen",
    "wof:name":"Glas Gl\u00f6tzer Gmbh",
    "wof:placetype":"venue"
},
  "geometry": {"coordinates":[10.422085762,51.9366836548],"type":"Point"}
}