{
  "type": "Feature",
  "properties": {
    "iso:country":"DE",
    "sg:address":"Marktplatz 7",
    "sg:city":"Deidesheim",
    "sg:phone":"+49 6326/7213",
    "sg:postcode":"67146",
    "sg:province":"Rheinland-Pfalz",
    "wof:name":"Klaus Lakos",
    "wof:placetype":"venue"
},
  "geometry": {"coordinates":[8.1876382828,49.4079093933],"type":"Point"}
}