{
  "type": "Feature",
  "properties": {
    "iso:country":"DE",
    "sg:address":"Am Rissener Bahnhof 15",
    "sg:city":"Hamburg",
    "sg:phone":"+49 800 9826982",
    "sg:postcode":"22559",
    "sg:province":"Hamburg",
    "wof:name":"China Drive Dun Huang",
    "wof:placetype":"venue"
},
  "geometry": {"coordinates":[9.7564897537,53.5825386047],"type":"Point"}
}