{
  "type": "Feature",
  "properties": {
    "iso:country":"DE",
    "sg:address":"Hofer Str. 39",
    "sg:city":"Regensburg",
    "sg:phone":"+49 941/62024",
    "sg:postcode":"93057",
    "sg:province":"Bayern",
    "wof:name":"Sav Antil\u00e4rm Regensburg D\u00e4mmstoff-gmbh",
    "wof:placetype":"venue"
},
  "geometry": {"coordinates":[12.138471,49.065704],"type":"Point"}
}