{
  "type": "Feature",
  "properties": {
    "iso:country":"DE",
    "sg:address":"Schillerstr. 7",
    "sg:city":"Glash\u00fctte",
    "sg:phone":"+49 35053/48742",
    "sg:postcode":"01768",
    "sg:province":"Sachsen",
    "wof:name":"Roland Roitzsch",
    "wof:placetype":"venue"
},
  "geometry": {"coordinates":[13.779086113,50.852268219],"type":"Point"}
}