{
  "type": "Feature",
  "properties": {
    "iso:country":"DE",
    "sg:address":"Westerholter Weg 81",
    "sg:city":"Recklinghausen",
    "sg:phone":"+49 2361/24795",
    "sg:postcode":"45657",
    "sg:province":"Nordrhein-Westfalen",
    "wof:name":"I. Herms",
    "wof:placetype":"venue"
},
  "geometry": {"coordinates":[7.184981,51.615875],"type":"Point"}
}