{
  "type": "Feature",
  "properties": {
    "iso:country":"DE",
    "sg:address":"Silcherstr. 12",
    "sg:city":"Weil im Sch\u00f6nbuch",
    "sg:phone":"+49 7031/750880",
    "sg:postcode":"71093",
    "sg:province":"Baden-W\u00fcrttemberg",
    "wof:name":"Diehl Nachrichtentechnische Projektierung Gmbh",
    "wof:placetype":"venue"
},
  "geometry": {"coordinates":[9.0612668991,48.6405105591],"type":"Point"}
}