{
  "type": "Feature",
  "properties": {
    "iso:country":"DE",
    "sg:address":"Hemdener Weg 80",
    "sg:city":"Bocholt",
    "sg:phone":"+49 2871/37339",
    "sg:postcode":"46399",
    "sg:province":"Nordrhein-Westfalen",
    "wof:name":"Christel Thesing",
    "wof:placetype":"venue"
},
  "geometry": {"coordinates":[6.612997,51.849339],"type":"Point"}
}