{
  "type": "Feature",
  "properties": {
    "iso:country":"DE",
    "sg:address":"Hohe Str. 1",
    "sg:city":"K\u00f6ln",
    "sg:postcode":"51149",
    "sg:province":"Nordrhein-Westfalen",
    "wof:name":"Dieter Gerhard Ml Collection Bekleidungs Gmbh",
    "wof:placetype":"venue"
},
  "geometry": {"coordinates":[7.035736084,50.8960723877],"type":"Point"}
}