{
  "type": "Feature",
  "properties": {
    "iso:country":"DE",
    "sg:address":"Veitstr. 13",
    "sg:city":"Stuttgart",
    "sg:phone":"+49 711/9537937",
    "sg:postcode":"70378",
    "sg:province":"Baden-W\u00fcrttemberg",
    "wof:name":"Printfixx Gmbh",
    "wof:placetype":"venue"
},
  "geometry": {"coordinates":[9.2307386398,48.842880249],"type":"Point"}
}