{
  "type": "Feature",
  "properties": {
    "iso:country":"DE",
    "sg:address":"Rosenweg 21",
    "sg:city":"Neuhausen",
    "sg:phone":"+49 7158/62948",
    "sg:postcode":"73765",
    "sg:province":"Baden-W\u00fcrttemberg",
    "wof:name":"Lamm Treuhand Gmbh",
    "wof:placetype":"venue"
},
  "geometry": {"coordinates":[9.278470993,48.6778564453],"type":"Point"}
}