{
  "type": "Feature",
  "properties": {
    "iso:country":"DE",
    "sg:address":"Feldstr.",
    "sg:city":"Unna",
    "sg:phone":"+49 2303/80090",
    "sg:postcode":"59423",
    "sg:province":"Nordrhein-Westfalen",
    "wof:name":"Aktiv-markt",
    "wof:placetype":"venue"
},
  "geometry": {"coordinates":[7.6716299057,51.5312690735],"type":"Point"}
}