{
  "type": "Feature",
  "properties": {
    "iso:country":"DE",
    "sg:address":"Trappstr. 5-8",
    "sg:city":"Wesel",
    "sg:phone":"+49 281/2090",
    "sg:postcode":"46483",
    "sg:province":"Nordrhein-Westfalen",
    "wof:name":"Trapp Holding Gmbh & Co.",
    "wof:placetype":"venue"
},
  "geometry": {"coordinates":[6.62687,51.664589],"type":"Point"}
}