{
  "type": "Feature",
  "properties": {
    "iso:country":"DE",
    "sg:address":"Graf-Anton-Weg 24",
    "sg:city":"Hamburg",
    "sg:phone":"+49 40/5514908",
    "sg:postcode":"22459",
    "sg:province":"Hamburg",
    "wof:name":"H. Sellschopp",
    "wof:placetype":"venue"
},
  "geometry": {"coordinates":[9.947172,53.627087],"type":"Point"}
}