{
  "type": "Feature",
  "properties": {
    "iso:country":"DE",
    "sg:address":"Im Schuhmachergewann 21",
    "sg:city":"Heidelberg",
    "sg:phone":"+49 6221/836529",
    "sg:postcode":"69123",
    "sg:province":"Baden-W\u00fcrttemberg",
    "wof:name":"Frank Scholl",
    "wof:placetype":"venue"
},
  "geometry": {"coordinates":[8.637217,49.42733],"type":"Point"}
}