{
  "type": "Feature",
  "properties": {
    "iso:country":"DE",
    "sg:address":"Bahnhofstr 5",
    "sg:city":"Neuensalz",
    "sg:phone":"+49 3741/41860",
    "sg:postcode":"08541",
    "sg:province":"Sachsen",
    "wof:name":"M&h Internationale Spedition & Logistik Gmbh & Co Kg",
    "wof:placetype":"venue"
},
  "geometry": {"coordinates":[12.2131271362,50.500328064],"type":"Point"}
}