{
  "type": "Feature",
  "properties": {
    "iso:country":"DE",
    "sg:address":"Fichtenstr. 5",
    "sg:city":"Unterschlei\u00dfheim",
    "sg:phone":"+49 89/3102563",
    "sg:postcode":"85716",
    "sg:province":"Bayern",
    "wof:name":"Beate Zaglauer Steuerberaterin",
    "wof:placetype":"venue"
},
  "geometry": {"coordinates":[11.5842132568,48.277557373],"type":"Point"}
}