{
  "type": "Feature",
  "properties": {
    "iso:country":"DE",
    "sg:address":"Am M\u00fchlwege 10",
    "sg:city":"Korbach",
    "sg:phone":"+49 5631/8131",
    "sg:postcode":"34497",
    "sg:province":"Hessen",
    "wof:name":"Horst Knippschild",
    "wof:placetype":"venue"
},
  "geometry": {"coordinates":[8.855905,51.288891],"type":"Point"}
}