{
  "type": "Feature",
  "properties": {
    "iso:country":"DE",
    "sg:address":"Villkuhlenweg 4",
    "sg:city":"Vechta",
    "sg:phone":"+49 4441/2300",
    "sg:postcode":"49377",
    "sg:province":"Niedersachsen",
    "wof:name":"Bernhard Sieve",
    "wof:placetype":"venue"
},
  "geometry": {"coordinates":[8.285397,52.734863],"type":"Point"}
}