{
  "type": "Feature",
  "properties": {
    "iso:country":"DE",
    "sg:address":"Bomshofstr. 23",
    "sg:city":"Kranenburg",
    "sg:phone":"+49 2826/1208",
    "sg:postcode":"47559",
    "sg:province":"Nordrhein-Westfalen",
    "wof:name":"Paul Jansen",
    "wof:placetype":"venue"
},
  "geometry": {"coordinates":[6.061794,51.784389],"type":"Point"}
}