{
  "type": "Feature",
  "properties": {
    "iso:country":"DE",
    "sg:address":"Talstr. 117",
    "sg:city":"Beckingen",
    "sg:phone":"+49 6835/68784",
    "sg:postcode":"66701",
    "sg:province":"Saarland",
    "wof:name":"Horst Andres",
    "wof:placetype":"venue"
},
  "geometry": {"coordinates":[6.702164,49.394356],"type":"Point"}
}