{
  "type": "Feature",
  "properties": {
    "iso:country":"DE",
    "sg:address":"Auf dem Hochst\u00fcck 11",
    "sg:city":"Herten",
    "sg:phone":"+49 2366/10070",
    "sg:postcode":"45701",
    "sg:province":"Nordrhein-Westfalen",
    "wof:name":"Heftruck-systemen Gmbh & Co.",
    "wof:placetype":"venue"
},
  "geometry": {"coordinates":[7.1054911613,51.6042823792],"type":"Point"}
}