{
  "type": "Feature",
  "properties": {
    "iso:country":"DE",
    "sg:address":"Borggraf 11",
    "sg:city":"Hamminkeln",
    "sg:phone":"+49 2856/1504",
    "sg:postcode":"46499",
    "sg:province":"Nordrhein-Westfalen",
    "wof:name":"Werner Eimers",
    "wof:placetype":"venue"
},
  "geometry": {"coordinates":[6.691676,51.713856],"type":"Point"}
}