{
  "type": "Feature",
  "properties": {
    "iso:country":"DE",
    "sg:address":"Im Klingenfeld 21",
    "sg:city":"Kressberg-Marktlustenau",
    "sg:phone":"+49 4979/5798860",
    "sg:postcode":"74594",
    "sg:province":"Baden-W\u00fcrttemberg",
    "wof:name":"Konfektion E Elektronik Gmbh",
    "wof:placetype":"venue"
},
  "geometry": {"coordinates":[10.243999,49.129253],"type":"Point"}
}