{
  "type": "Feature",
  "properties": {
    "iso:country":"DE",
    "sg:address":"Mittelstr. 6",
    "sg:city":"Saarbr\u00fccken",
    "sg:phone":"+49 6898/810329",
    "sg:postcode":"66126",
    "sg:province":"Saarland",
    "wof:name":"Pizzeria Da Adriano",
    "wof:placetype":"venue"
},
  "geometry": {"coordinates":[6.9137439728,49.2613143921],"type":"Point"}
}