{
  "type": "Feature",
  "properties": {
    "iso:country":"DE",
    "sg:address":"Graf-Reginar-Str. 15",
    "sg:city":"Trier",
    "sg:phone":"+49 651/9930190",
    "sg:postcode":"54294",
    "sg:province":"Rheinland-Pfalz",
    "wof:name":"Fritz Streipardt",
    "wof:placetype":"venue"
},
  "geometry": {"coordinates":[6.6257658005,49.7242851257],"type":"Point"}
}