{
  "type": "Feature",
  "properties": {
    "iso:country":"DE",
    "sg:address":"Am Haferkamp 7",
    "sg:city":"D\u00fcsseldorf",
    "sg:phone":"+49 211/752452",
    "sg:postcode":"40589",
    "sg:province":"Nordrhein-Westfalen",
    "wof:name":"Robert Ohl",
    "wof:placetype":"venue"
},
  "geometry": {"coordinates":[6.816245,51.179745],"type":"Point"}
}