{
  "type": "Feature",
  "properties": {
    "iso:country":"DE",
    "sg:address":"Niederholzstr. 11",
    "sg:city":"Friedrichshafen",
    "sg:phone":"+49 7541/25438",
    "sg:postcode":"88045",
    "sg:province":"Baden-W\u00fcrttemberg",
    "wof:name":"S\u00fcddeutsches Transportcontor Benedikt Brugger",
    "wof:placetype":"venue"
},
  "geometry": {"coordinates":[9.4437923431,47.6595611572],"type":"Point"}
}