{
  "type": "Feature",
  "properties": {
    "iso:country":"DE",
    "sg:address":"Konkordiastr. 10",
    "sg:city":"Edingen-Neckarhausen",
    "sg:phone":"+49 6203/82949",
    "sg:postcode":"68535",
    "sg:province":"Baden-W\u00fcrttemberg",
    "wof:name":"Wilhelm Ding",
    "wof:placetype":"venue"
},
  "geometry": {"coordinates":[8.611374855,49.4459190369],"type":"Point"}
}