{
  "type": "Feature",
  "properties": {
    "iso:country":"DE",
    "sg:address":"Vo\u00dfhaar 10a",
    "sg:city":"Telgte",
    "sg:phone":"+49 2504/88316",
    "sg:postcode":"48291",
    "sg:province":"Nordrhein-Westfalen",
    "wof:name":"Kurt Bellmann",
    "wof:placetype":"venue"
},
  "geometry": {"coordinates":[7.7504429817,52.0426368713],"type":"Point"}
}