{
  "type": "Feature",
  "properties": {
    "iso:country":"DE",
    "sg:address":"Steubenstr. 11",
    "sg:city":"Dortmund",
    "sg:phone":"+49 231/141455",
    "sg:postcode":"44137",
    "sg:province":"Nordrhein-Westfalen",
    "wof:name":"Reinhard Drevermann",
    "wof:placetype":"venue"
},
  "geometry": {"coordinates":[7.4461932182,51.5059509277],"type":"Point"}
}