{
  "type": "Feature",
  "properties": {
    "iso:country":"DE",
    "sg:address":"Theresienstr. 9",
    "sg:city":"Berg",
    "sg:phone":"+49 7273/1282",
    "sg:postcode":"76768",
    "sg:province":"Rheinland-Pfalz",
    "wof:name":"Drei K\u00f6nige",
    "wof:placetype":"venue"
},
  "geometry": {"coordinates":[8.2049684525,48.9824447632],"type":"Point"}
}