{
  "type": "Feature",
  "properties": {
    "iso:country":"DE",
    "sg:address":"Dorfstrasse 23",
    "sg:city":"Strande",
    "sg:phone":"+49 4943/498436",
    "sg:postcode":"24229",
    "sg:province":"Schleswig-Holstein",
    "wof:name":"Peter Walusch Bootsgutachter",
    "wof:placetype":"venue"
},
  "geometry": {"coordinates":[10.172374,54.439877],"type":"Point"}
}