{
  "type": "Feature",
  "properties": {
    "iso:country":"DE",
    "sg:address":"Raiffeisenweg 6",
    "sg:city":"Peiting",
    "sg:phone":"+49 8861/67936",
    "sg:postcode":"86971",
    "sg:province":"Bayern",
    "wof:name":"G\u00e4stehaus E. Zarda",
    "wof:placetype":"venue"
},
  "geometry": {"coordinates":[10.9319143295,47.7959289551],"type":"Point"}
}