{
  "type": "Feature",
  "properties": {
    "iso:country":"DE",
    "sg:address":"Spitzm\u00fchle",
    "sg:city":"Gro\u00dfbartloff",
    "sg:postcode":"37359",
    "sg:province":"Th\u00fcringen",
    "wof:name":"Obereichsfeldischer Wasser- Leitungsverband",
    "wof:placetype":"venue"
},
  "geometry": {"coordinates":[10.2229452133,51.2488250732],"type":"Point"}
}