{
  "type": "Feature",
  "properties": {
    "iso:country":"DE",
    "sg:address":"D\u00fcrener Str. 411",
    "sg:city":"K\u00f6ln",
    "sg:phone":"+49 221/92130022",
    "sg:postcode":"50858",
    "sg:province":"Nordrhein-Westfalen",
    "wof:name":"Stadtsportbund K\u00f6ln E. V.",
    "wof:placetype":"venue"
},
  "geometry": {"coordinates":[6.8695321083,50.9230384827],"type":"Point"}
}