{
  "type": "Feature",
  "properties": {
    "iso:country":"DE",
    "sg:address":"Mozartstr. 19",
    "sg:city":"Hagen",
    "sg:postcode":"58119",
    "sg:province":"Nordrhein-Westfalen",
    "wof:name":"Freizeitgruppe Hoesch Hohenlimburg",
    "wof:placetype":"venue"
},
  "geometry": {"coordinates":[7.5592899323,51.3701324463],"type":"Point"}
}