{
  "type": "Feature",
  "properties": {
    "iso:country":"DE",
    "sg:address":"Herforder Str. 22",
    "sg:city":"Bielefeld",
    "sg:phone":"+49 521/964360",
    "sg:postcode":"33602",
    "sg:province":"Nordrhein-Westfalen",
    "wof:name":"Prinz Und Pott",
    "wof:placetype":"venue"
},
  "geometry": {"coordinates":[8.535208,52.02615],"type":"Point"}
}