{
  "type": "Feature",
  "properties": {
    "iso:country":"DE",
    "sg:address":"Wilhelm-Leuschner-Str. 28",
    "sg:city":"Griesheim",
    "sg:phone":"+49 6155/830819",
    "sg:postcode":"64347",
    "sg:province":"Hessen",
    "wof:name":"Peller Und Michel Rechtsanw\u00e4lte",
    "wof:placetype":"venue"
},
  "geometry": {"coordinates":[8.5594959259,49.8603096008],"type":"Point"}
}