{
  "type": "Feature",
  "properties": {
    "iso:country":"DE",
    "sg:address":"Elsa-Brandstr\u00f6m-Str. 51",
    "sg:city":"Bad Salzdetfurth",
    "sg:phone":"+49 5063/605",
    "sg:postcode":"31162",
    "sg:province":"Niedersachsen",
    "wof:name":"Katholisches Pfarramt Hl. Familie",
    "wof:placetype":"venue"
},
  "geometry": {"coordinates":[10.007062912,52.050743103],"type":"Point"}
}