{
  "type": "Feature",
  "properties": {
    "iso:country":"DE",
    "sg:address":"Vorsterhauser Weg 26",
    "sg:city":"Hamm",
    "sg:phone":"+49 2381/445554",
    "sg:postcode":"59067",
    "sg:province":"Nordrhein-Westfalen",
    "wof:name":"B. Schleimer",
    "wof:placetype":"venue"
},
  "geometry": {"coordinates":[7.7907409668,51.6682319641],"type":"Point"}
}