{
  "type": "Feature",
  "properties": {
    "iso:country":"DE",
    "sg:address":"Hauptstr. 45",
    "sg:city":"Heidenheim",
    "sg:phone":"+49 4973/2193850",
    "sg:postcode":"89522",
    "sg:province":"Baden-W\u00fcrttemberg",
    "wof:name":"Ineltek Gmbh",
    "wof:placetype":"venue"
},
  "geometry": {"coordinates":[10.151771,48.675945],"type":"Point"}
}