{
  "type": "Feature",
  "properties": {
    "iso:country":"DE",
    "sg:address":"L\u00e4rchenstr. 1-3",
    "sg:city":"Kelkheim",
    "sg:postcode":"65779",
    "sg:province":"Hessen",
    "wof:name":"Fc Verm\u00f6gensverwaltung Gmbh",
    "wof:placetype":"venue"
},
  "geometry": {"coordinates":[8.4349603653,50.1598205566],"type":"Point"}
}