{
  "type": "Feature",
  "properties": {
    "iso:country":"DE",
    "sg:address":"Panoramastr. 3",
    "sg:city":"Stuttgart",
    "sg:phone":"+49 711/2270088",
    "sg:postcode":"70174",
    "sg:province":"Baden-W\u00fcrttemberg",
    "wof:name":"M\u00f6ller & Partner Gmbh",
    "wof:placetype":"venue"
},
  "geometry": {"coordinates":[9.1716623306,48.7849349976],"type":"Point"}
}