{
  "type": "Feature",
  "properties": {
    "iso:country":"DE",
    "sg:address":"Am Ossenbrink 66 d",
    "sg:city":"Herdecke",
    "sg:postcode":"58313",
    "sg:province":"Nordrhein-Westfalen",
    "wof:name":"Spielodrom Wilhelmstra\u00dfe In Hamm Gmbh",
    "wof:placetype":"venue"
},
  "geometry": {"coordinates":[7.464984,51.433979],"type":"Point"}
}