{
  "type": "Feature",
  "properties": {
    "iso:country":"DE",
    "sg:address":"Breyeller Str. 42",
    "sg:city":"Nettetal",
    "sg:phone":"+49 2153/2154",
    "sg:postcode":"41334",
    "sg:province":"Nordrhein-Westfalen",
    "wof:name":"Heinz-josef Voormanns",
    "wof:placetype":"venue"
},
  "geometry": {"coordinates":[6.271973,51.30431],"type":"Point"}
}