{
  "type": "Feature",
  "properties": {
    "iso:country":"DE",
    "sg:address":"Lindenring 4",
    "sg:city":"Taufkirchen",
    "sg:phone":"+49 89/6123219",
    "sg:postcode":"82024",
    "sg:province":"Bayern",
    "wof:name":"Manfred \u00d6ttinger",
    "wof:placetype":"venue"
},
  "geometry": {"coordinates":[11.6065816879,48.053943634],"type":"Point"}
}