{
  "type": "Feature",
  "properties": {
    "iso:country":"DE",
    "sg:address":"Bahnhofstr. 11",
    "sg:city":"L\u00fcbs",
    "sg:phone":"+49 39242/369",
    "sg:postcode":"39264",
    "sg:province":"Sachsen-Anhalt",
    "wof:name":"Henning Schwabe",
    "wof:placetype":"venue"
},
  "geometry": {"coordinates":[11.937916,52.020168],"type":"Point"}
}