{
  "type": "Feature",
  "properties": {
    "iso:country":"DE",
    "sg:address":"Lindenstr. 13",
    "sg:city":"K\u00f6then",
    "sg:phone":"+49 3496/40660",
    "sg:postcode":"06366",
    "sg:province":"Sachsen-Anhalt",
    "wof:name":"Julienhof Betreuungs- Zentrum Gmbh",
    "wof:placetype":"venue"
},
  "geometry": {"coordinates":[11.978523,51.753178],"type":"Point"}
}