{
  "type": "Feature",
  "properties": {
    "iso:country":"DE",
    "sg:address":"Grebbecker Weg 5",
    "sg:city":"L\u00fcdenscheid",
    "sg:phone":"+49 2351",
    "sg:postcode":"58509",
    "sg:province":"Nordrhein-Westfalen",
    "wof:name":"Wigger Automobile",
    "wof:placetype":"venue"
},
  "geometry": {"coordinates":[7.6100258827,51.2354888916],"type":"Point"}
}