{
  "type": "Feature",
  "properties": {
    "iso:country":"DE",
    "sg:address":"M\u00fcllerhartungstr. 1",
    "sg:city":"Bad Sulza",
    "sg:phone":"+49 36461/23192",
    "sg:postcode":"99518",
    "sg:province":"Th\u00fcringen",
    "wof:name":"Renate Krause",
    "wof:placetype":"venue"
},
  "geometry": {"coordinates":[11.6223468781,51.087097168],"type":"Point"}
}