{
  "type": "Feature",
  "properties": {
    "iso:country":"DE",
    "sg:address":"Hechinger Str. 38",
    "sg:city":"Hirrlingen",
    "sg:phone":"+49 4974/789210",
    "sg:postcode":"72145",
    "sg:province":"Baden-W\u00fcrttemberg",
    "wof:name":"Jostra Ag",
    "wof:placetype":"venue"
},
  "geometry": {"coordinates":[8.8835639954,48.4066085815],"type":"Point"}
}