{
  "type": "Feature",
  "properties": {
    "iso:country":"DE",
    "sg:address":"Henckelsstr. 39",
    "sg:city":"Solingen",
    "sg:phone":"+49 212/878930",
    "sg:postcode":"42657",
    "sg:province":"Nordrhein-Westfalen",
    "wof:name":"Datenservice J & P Gmbh",
    "wof:placetype":"venue"
},
  "geometry": {"coordinates":[7.075598,51.165131],"type":"Point"}
}