{
  "type": "Feature",
  "properties": {
    "iso:country":"DE",
    "sg:address":"B\u00f6ckenrad 52",
    "sg:city":"L\u00fcbeck",
    "sg:phone":"+49 451/302396",
    "sg:postcode":"23569",
    "sg:province":"Schleswig-Holstein",
    "wof:name":"Siegfried Schwarz",
    "wof:placetype":"venue"
},
  "geometry": {"coordinates":[10.8187046051,53.9112854004],"type":"Point"}
}