{
  "type": "Feature",
  "properties": {
    "iso:country":"DE",
    "sg:address":"Wickeder Hellweg 78",
    "sg:city":"Dortmund",
    "sg:phone":"+49 231/217004",
    "sg:postcode":"44319",
    "sg:province":"Nordrhein-Westfalen",
    "wof:name":"Hartmut Engler Rechtsanwalt",
    "wof:placetype":"venue"
},
  "geometry": {"coordinates":[7.6087098122,51.5321655273],"type":"Point"}
}