{
  "type": "Feature",
  "properties": {
    "iso:country":"DE",
    "sg:address":"Hainer Weg 10",
    "sg:city":"Siegen",
    "sg:phone":"+49 271/53624",
    "sg:postcode":"57074",
    "sg:province":"Nordrhein-Westfalen",
    "wof:name":"Walter Gayko",
    "wof:placetype":"venue"
},
  "geometry": {"coordinates":[8.0317831039,50.8759078979],"type":"Point"}
}