{
  "type": "Feature",
  "properties": {
    "iso:country":"DE",
    "sg:address":"Kremenholler Str. 95",
    "sg:city":"Remscheid",
    "sg:phone":"+49 2191/73774",
    "sg:postcode":"42857",
    "sg:province":"Nordrhein-Westfalen",
    "wof:name":"Friedel Petri Finanzberater",
    "wof:placetype":"venue"
},
  "geometry": {"coordinates":[7.1768479347,51.1719436646],"type":"Point"}
}