{
  "type": "Feature",
  "properties": {
    "iso:country":"DE",
    "sg:address":"Schlo\u00dfweg",
    "sg:city":"Drage",
    "sg:phone":"+49 4893/585",
    "sg:postcode":"25582",
    "sg:province":"Schleswig-Holstein",
    "wof:name":"Freibad Drage",
    "wof:placetype":"venue"
},
  "geometry": {"coordinates":[9.5190401077,54.0024032593],"type":"Point"}
}