{
  "type": "Feature",
  "properties": {
    "iso:country":"DE",
    "sg:address":"In Der Kolling 13 POSTFACH 1116",
    "sg:city":"Bexbach",
    "sg:phone":"+49 4968/2692280",
    "sg:postcode":"66442",
    "sg:province":"Saarland",
    "wof:name":"Ghmt Ag",
    "wof:placetype":"venue"
},
  "geometry": {"coordinates":[7.244257,49.345665],"type":"Point"}
}