{
  "type": "Feature",
  "properties": {
    "iso:country":"DE",
    "sg:address":"Dorfplatz 3",
    "sg:city":"Spalt",
    "sg:phone":"+49 9873/948913",
    "sg:postcode":"91174",
    "sg:province":"Bayern",
    "wof:name":"Elotec Elektroanlagen Gmbh",
    "wof:placetype":"venue"
},
  "geometry": {"coordinates":[10.93786,49.165131],"type":"Point"}
}