{
  "type": "Feature",
  "properties": {
    "iso:country":"DE",
    "sg:address":"Deiringser Weg 100",
    "sg:city":"Soest",
    "sg:phone":"+49 2921/769630",
    "sg:postcode":"59494",
    "sg:province":"Nordrhein-Westfalen",
    "wof:name":"Finance-management",
    "wof:placetype":"venue"
},
  "geometry": {"coordinates":[8.09503,51.56049],"type":"Point"}
}