{
  "type": "Feature",
  "properties": {
    "iso:country":"DE",
    "sg:address":"Liebknechtstr. 71",
    "sg:city":"Erfurt",
    "sg:phone":"+49 361/5624070",
    "sg:postcode":"99085",
    "sg:province":"Th\u00fcringen",
    "wof:name":"C. Und J. Birkhan",
    "wof:placetype":"venue"
},
  "geometry": {"coordinates":[11.040514946,50.9828948975],"type":"Point"}
}