{
  "type": "Feature",
  "properties": {
    "iso:country":"DE",
    "sg:address":"Welschgasse 10",
    "sg:city":"Ehingen",
    "sg:phone":"+49 7391/752025",
    "sg:postcode":"89584",
    "sg:province":"Baden-W\u00fcrttemberg",
    "wof:name":"T. Lerch",
    "wof:placetype":"venue"
},
  "geometry": {"coordinates":[9.727287,48.284298],"type":"Point"}
}