{
  "type": "Feature",
  "properties": {
    "iso:country":"DE",
    "sg:address":"An der Kirche 2",
    "sg:city":"Neustadt",
    "sg:phone":"+49 6692/7993",
    "sg:postcode":"35279",
    "sg:province":"Hessen",
    "wof:name":"Gastst\u00e4tte Herbert Ochs",
    "wof:placetype":"venue"
},
  "geometry": {"coordinates":[9.0992689133,50.9010162354],"type":"Point"}
}