{
  "type": "Feature",
  "properties": {
    "iso:country":"DE",
    "sg:address":"Lessingstr. 2",
    "sg:city":"Neu-Isenburg",
    "sg:phone":"+49 6102/6840",
    "sg:postcode":"63263",
    "sg:province":"Hessen",
    "wof:name":"Nolle Catering Services",
    "wof:placetype":"venue"
},
  "geometry": {"coordinates":[8.693804,50.054558],"type":"Point"}
}