{
  "type": "Feature",
  "properties": {
    "iso:country":"DE",
    "sg:address":"Grunewaldstr. 39",
    "sg:city":"M\u00f6nchengladbach",
    "sg:phone":"+49 2161/662273",
    "sg:postcode":"41066",
    "sg:province":"Nordrhein-Westfalen",
    "wof:name":"Bcvg Bau-chemie Verwaltungs- Und Beteiligungs-gmbh",
    "wof:placetype":"venue"
},
  "geometry": {"coordinates":[6.479929,51.230587],"type":"Point"}
}