{
  "type": "Feature",
  "properties": {
    "iso:country":"DE",
    "sg:address":"Eisenbahnstr. 9",
    "sg:city":"Bremerhaven",
    "sg:phone":"+49 471/86331",
    "sg:postcode":"27580",
    "sg:province":"Bremen",
    "wof:name":"Horst Kania Heilpraktiker",
    "wof:placetype":"venue"
},
  "geometry": {"coordinates":[8.5954494476,53.5670814514],"type":"Point"}
}