{
  "type": "Feature",
  "properties": {
    "iso:country":"DE",
    "sg:address":"Br\u00fcckenstr. 25",
    "sg:city":"Berlin",
    "sg:postcode":"12439",
    "sg:province":"Berlin",
    "wof:name":"Inss Informations- Und Daten-sicherungssysteme Gmbh",
    "wof:placetype":"venue"
},
  "geometry": {"coordinates":[13.510912,52.45768],"type":"Point"}
}