{
  "type": "Feature",
  "properties": {
    "iso:country":"DE",
    "sg:address":"Hofmarkstr. 1 Niedertraubling",
    "sg:city":"Obertraubling",
    "sg:phone":"+49 9401/96250",
    "sg:postcode":"93083",
    "sg:province":"Bayern",
    "wof:name":"Saatzucht Bauer Gmbh",
    "wof:placetype":"venue"
},
  "geometry": {"coordinates":[12.1666,48.965866],"type":"Point"}
}