{
  "type": "Feature",
  "properties": {
    "iso:country":"DE",
    "sg:address":"Bichlstr. 3",
    "sg:city":"Simbach",
    "sg:phone":"+49 9954/223",
    "sg:postcode":"94436",
    "sg:province":"Bayern",
    "wof:name":"Hermann Schachtner",
    "wof:placetype":"venue"
},
  "geometry": {"coordinates":[12.7357244492,48.5656852722],"type":"Point"}
}