{
  "type": "Feature",
  "properties": {
    "iso:country":"DE",
    "sg:address":"Carl-Hermann-J\u00e4ger-Str 3",
    "sg:city":"Ettenheim",
    "sg:phone":"+49 34243/3020",
    "sg:postcode":"77955",
    "sg:province":"Baden-W\u00fcrttemberg",
    "wof:name":"Seilerei Voigt",
    "wof:placetype":"venue"
},
  "geometry": {"coordinates":[12.59879,51.59396],"type":"Point"}
}