{
  "type": "Feature",
  "properties": {
    "iso:country":"DE",
    "sg:address":"Theodor-Heuss-Str. 28",
    "sg:city":"Ha\u00dfmersheim",
    "sg:phone":"+49 6266/528",
    "sg:postcode":"74855",
    "sg:province":"Baden-W\u00fcrttemberg",
    "wof:name":"Apotheke Hassmersheim",
    "wof:placetype":"venue"
},
  "geometry": {"coordinates":[9.149197,49.301582],"type":"Point"}
}