{
  "type": "Feature",
  "properties": {
    "iso:country":"DE",
    "sg:address":"Hans-B\u00f6ckler-Str. 18 -24",
    "sg:city":"R\u00f6srath Gewerbegebiet",
    "sg:phone":"+49 2205/92240",
    "sg:postcode":"51503",
    "sg:province":"Nordrhein-Westfalen",
    "wof:name":"Hans Trum Gmbh & Co. Kg., Holzhandlung",
    "wof:placetype":"venue"
},
  "geometry": {"coordinates":[7.1837182045,50.8872680664],"type":"Point"}
}