{
  "type": "Feature",
  "properties": {
    "iso:country":"DE",
    "sg:address":"M\u00fcnchhofstr. 42",
    "sg:city":"Mainz-Kostheim",
    "sg:phone":"+49 6134/24444",
    "sg:postcode":"55246",
    "sg:province":"Hessen",
    "wof:name":"R\u00fcdiger Daum",
    "wof:placetype":"venue"
},
  "geometry": {"coordinates":[8.304284,50.003601],"type":"Point"}
}