{
  "type": "Feature",
  "properties": {
    "iso:country":"DE",
    "sg:address":"Alemannenstr 25",
    "sg:city":"Maulburg",
    "sg:phone":"+49 7622/669166",
    "sg:postcode":"79689",
    "sg:province":"Baden-W\u00fcrttemberg",
    "wof:name":"Gie\u00dferei Hesterberg Gmbh",
    "wof:placetype":"venue"
},
  "geometry": {"coordinates":[7.765461,47.642918],"type":"Point"}
}