{
  "type": "Feature",
  "properties": {
    "iso:country":"DE",
    "sg:address":"Romanusstr. 9",
    "sg:city":"Gelsenkirchen",
    "sg:phone":"+49 209/394484",
    "sg:postcode":"45894",
    "sg:province":"Nordrhein-Westfalen",
    "wof:name":"A. Luczk Und L. Alberti",
    "wof:placetype":"venue"
},
  "geometry": {"coordinates":[7.0484461784,51.5765800476],"type":"Point"}
}