{
  "type": "Feature",
  "properties": {
    "iso:country":"DE",
    "sg:address":"Dorfstr 50-52",
    "sg:city":"Langg\u00f6ns",
    "sg:phone":"+49 6447/922222",
    "sg:postcode":"35428",
    "sg:province":"Hessen",
    "wof:name":"J. Bietz",
    "wof:placetype":"venue"
},
  "geometry": {"coordinates":[8.609562,50.494198],"type":"Point"}
}