{
  "type": "Feature",
  "properties": {
    "iso:country":"DE",
    "sg:address":"Auf der Rinne 45",
    "sg:city":"Heilbad Heiligenstadt",
    "sg:phone":"+49 3606/603355",
    "sg:postcode":"37308",
    "sg:province":"Th\u00fcringen",
    "wof:name":"J. Schuchardt",
    "wof:placetype":"venue"
},
  "geometry": {"coordinates":[10.150104,51.371117],"type":"Point"}
}