{
  "type": "Feature",
  "properties": {
    "iso:country":"DE",
    "sg:address":"Gaisbergstr. 63",
    "sg:city":"Heidelberg",
    "sg:phone":"+49 6221/168436",
    "sg:postcode":"69115",
    "sg:province":"Baden-W\u00fcrttemberg",
    "wof:name":"Druckwalze Sick",
    "wof:placetype":"venue"
},
  "geometry": {"coordinates":[8.692937,49.402439],"type":"Point"}
}