{
  "type": "Feature",
  "properties": {
    "iso:country":"DE",
    "sg:address":"Karl-Marx-Str. 130",
    "sg:city":"Mellenbach-Glasbach",
    "sg:phone":"+49 36705/60100",
    "sg:postcode":"98746",
    "sg:province":"Th\u00fcringen",
    "wof:name":"Christa Marr",
    "wof:placetype":"venue"
},
  "geometry": {"coordinates":[11.1036806107,50.5981559753],"type":"Point"}
}