{
  "type": "Feature",
  "properties": {
    "iso:country":"DE",
    "sg:address":"Postfach 126",
    "sg:city":"Finnentrop",
    "sg:phone":"+49 2721/70031",
    "sg:postcode":"57401",
    "sg:province":"Nordrhein-Westfalen",
    "wof:name":"Mobau Modernes Bauen Gmbh & Co. Handels-",
    "wof:placetype":"venue"
},
  "geometry": {"coordinates":[7.97175,51.168179],"type":"Point"}
}