{
  "type": "Feature",
  "properties": {
    "iso:country":"DE",
    "sg:address":"Hufnagelstr 10",
    "sg:city":"Frankfurt",
    "sg:phone":"+49 69/7508870",
    "sg:postcode":"60326",
    "sg:province":"Hessen",
    "wof:name":"Sixworx Gmbh",
    "wof:placetype":"venue"
},
  "geometry": {"coordinates":[8.643593,50.103809],"type":"Point"}
}