{
  "type": "Feature",
  "properties": {
    "iso:country":"DE",
    "sg:address":"Antwerpener Str. 39",
    "sg:city":"K\u00f6ln",
    "sg:phone":"+49 221/520272",
    "sg:postcode":"50672",
    "sg:province":"Nordrhein-Westfalen",
    "wof:name":"L Antipasto",
    "wof:placetype":"venue"
},
  "geometry": {"coordinates":[6.9352140427,50.94008255],"type":"Point"}
}