{
  "type": "Feature",
  "properties": {
    "iso:country":"DE",
    "sg:address":"Kuckelke 12",
    "sg:city":"Dortmund",
    "sg:phone":"+49 231/579001",
    "sg:postcode":"44135",
    "sg:province":"Nordrhein-Westfalen",
    "wof:name":"City-reiseb\u00fcro Gmbh",
    "wof:placetype":"venue"
},
  "geometry": {"coordinates":[7.4684939384,51.5158157349],"type":"Point"}
}