{
  "type": "Feature",
  "properties": {
    "iso:country":"DE",
    "sg:address":"Forsthausstr. 1",
    "sg:city":"Mittenaar",
    "sg:phone":"+49 2772/62319",
    "sg:postcode":"35756",
    "sg:province":"Hessen",
    "wof:name":"Planungsb\u00fcro Kopp Gmbh",
    "wof:placetype":"venue"
},
  "geometry": {"coordinates":[8.368519783,50.6824035645],"type":"Point"}
}