{
  "type": "Feature",
  "properties": {
    "iso:country":"DE",
    "sg:address":"Oststr. 18",
    "sg:city":"Leipzig",
    "sg:phone":"+49 341/2610358",
    "sg:postcode":"04317",
    "sg:province":"Sachsen",
    "wof:name":"Bestattungshaus Kristan Inh. W. Kristan",
    "wof:placetype":"venue"
},
  "geometry": {"coordinates":[12.398601,51.332115],"type":"Point"}
}