{
  "type": "Feature",
  "properties": {
    "iso:country":"DE",
    "sg:address":"Gallusstr. 3",
    "sg:city":"Lichtenstein",
    "sg:phone":"+49 7129/922628",
    "sg:postcode":"72805",
    "sg:province":"Baden-W\u00fcrttemberg",
    "wof:name":"It-bitfire Ag",
    "wof:placetype":"venue"
},
  "geometry": {"coordinates":[9.2598133087,48.4115180969],"type":"Point"}
}