{
  "type": "Feature",
  "properties": {
    "iso:country":"DE",
    "sg:address":"wilderstrasse 8-10",
    "sg:city":"n\u00fcrnberg",
    "sg:phone":"+49 911/9359543",
    "sg:postcode":"90409",
    "sg:province":"Bayern",
    "wof:name":"Mno N\u00fcrnberg",
    "wof:placetype":"venue"
},
  "geometry": {"coordinates":[11.079521,49.465931],"type":"Point"}
}