{
  "type": "Feature",
  "properties": {
    "iso:country":"DE",
    "sg:address":"Bismarckstr. 5",
    "sg:city":"V\u00f6lklingen",
    "sg:phone":"+49 6898/296125",
    "sg:postcode":"66333",
    "sg:province":"Saarland",
    "wof:name":"A. Campanella",
    "wof:placetype":"venue"
},
  "geometry": {"coordinates":[6.8546409607,49.2498512268],"type":"Point"}
}