{
  "type": "Feature",
  "properties": {
    "iso:country":"DE",
    "sg:address":"Im Pfarrfeld 31",
    "sg:city":"Netphen",
    "sg:postcode":"57250",
    "sg:province":"Nordrhein-Westfalen",
    "wof:name":"S. Reitmeier Immobilienmakler",
    "wof:placetype":"venue"
},
  "geometry": {"coordinates":[8.1964769363,50.8595428467],"type":"Point"}
}