{
  "type": "Feature",
  "properties": {
    "iso:country":"DE",
    "sg:address":"Hammerm\u00fchle 34",
    "sg:city":"Overath",
    "sg:phone":"+49 2206/84781",
    "sg:postcode":"51491",
    "sg:province":"Nordrhein-Westfalen",
    "wof:name":"Kunststoffensterfabrik Buchwaldt Gmbh",
    "wof:placetype":"venue"
},
  "geometry": {"coordinates":[7.305012,50.942253],"type":"Point"}
}