{
  "type": "Feature",
  "properties": {
    "iso:country":"DE",
    "sg:address":"Mittelstr. 4",
    "sg:city":"Hennstedt",
    "sg:phone":"+49 4836/1380",
    "sg:postcode":"25779",
    "sg:province":"Schleswig-Holstein",
    "wof:name":"Hotel R. Gosau",
    "wof:placetype":"venue"
},
  "geometry": {"coordinates":[9.1681623459,54.2842445374],"type":"Point"}
}