{
  "type": "Feature",
  "properties": {
    "iso:country":"DE",
    "sg:address":"Lengenfelder Str. 2",
    "sg:city":"Lengenfeld",
    "sg:phone":"+49 37606/2827",
    "sg:postcode":"08485",
    "sg:province":"Sachsen",
    "wof:name":"Wei\u00dfensand",
    "wof:placetype":"venue"
},
  "geometry": {"coordinates":[12.4284801483,50.6162910461],"type":"Point"}
}