{
  "type": "Feature",
  "properties": {
    "iso:country":"DE",
    "sg:address":"Hauptstr. 24",
    "sg:city":"Freiburg",
    "sg:phone":"+49 4779/248",
    "sg:postcode":"21729",
    "sg:province":"Niedersachsen",
    "wof:name":"Ev. Pfarramt Freiburg",
    "wof:placetype":"venue"
},
  "geometry": {"coordinates":[9.2900886536,53.8256034851],"type":"Point"}
}