{
  "type": "Feature",
  "properties": {
    "iso:country":"DE",
    "sg:address":"Jahnstr. 8",
    "sg:city":"Kehl",
    "sg:phone":"+49 7851/958617",
    "sg:postcode":"77694",
    "sg:province":"Baden-W\u00fcrttemberg",
    "wof:name":"Hotel-restaurant Rosengarten",
    "wof:placetype":"venue"
},
  "geometry": {"coordinates":[7.8091330528,48.5724945068],"type":"Point"}
}