{
  "type": "Feature",
  "properties": {
    "iso:country":"DE",
    "sg:address":"Neu-Afrika-Str. 56",
    "sg:city":"Kruchten",
    "sg:phone":"+49 6566/8487",
    "sg:postcode":"54675",
    "sg:province":"Rheinland-Pfalz",
    "wof:name":"Tima Unternehmens- Beratungsgesellschaft Mbh",
    "wof:placetype":"venue"
},
  "geometry": {"coordinates":[6.3253588676,49.8958587646],"type":"Point"}
}