{
  "type": "Feature",
  "properties": {
    "iso:country":"DE",
    "sg:address":"Berliner Str. 48",
    "sg:city":"Hohen Neuendorf",
    "sg:phone":"+49 3303/402157",
    "sg:postcode":"16540",
    "sg:province":"Brandenburg",
    "wof:name":"Helmut Wollschl\u00e4ger",
    "wof:placetype":"venue"
},
  "geometry": {"coordinates":[13.280307,52.670094],"type":"Point"}
}