{
  "type": "Feature",
  "properties": {
    "iso:country":"DE",
    "sg:address":"Klarastr. 27",
    "sg:city":"Essen",
    "sg:phone":"+49 201/772648",
    "sg:postcode":"45130",
    "sg:province":"Nordrhein-Westfalen",
    "wof:name":"Elefanten-apotheke",
    "wof:placetype":"venue"
},
  "geometry": {"coordinates":[7.00795,51.438522],"type":"Point"}
}