{
  "type": "Feature",
  "properties": {
    "iso:country":"DE",
    "sg:address":"Lindartstr. 9",
    "sg:city":"Halle",
    "sg:phone":"+49 5201/3110",
    "sg:postcode":"33790",
    "sg:province":"Nordrhein-Westfalen",
    "wof:name":"Verein Der Igelfreunde Horst Hurdelbrink",
    "wof:placetype":"venue"
},
  "geometry": {"coordinates":[8.3564758301,52.0597038269],"type":"Point"}
}