{
  "type": "Feature",
  "properties": {
    "iso:country":"DE",
    "sg:address":"Hauptstr. 4B",
    "sg:city":"Proseken",
    "sg:phone":"+49 38428/60040",
    "sg:postcode":"23968",
    "sg:province":"Mecklenburg-Vorpommern",
    "wof:name":"P. Gro\u00df & Co. Gmbh",
    "wof:placetype":"venue"
},
  "geometry": {"coordinates":[11.370341,53.90556],"type":"Point"}
}