{
  "type": "Feature",
  "properties": {
    "iso:country":"DE",
    "sg:address":"Wilhelm-Meu\u00dfdoerffer-Str. 19",
    "sg:city":"Kulmbach",
    "sg:phone":"+49 9221/90490",
    "sg:postcode":"95326",
    "sg:province":"Bayern",
    "wof:name":"Meussd\u00f6rfer Gmbh & Co. Kg",
    "wof:placetype":"venue"
},
  "geometry": {"coordinates":[11.444655,50.100014],"type":"Point"}
}