{
  "type": "Feature",
  "properties": {
    "iso:country":"DE",
    "sg:address":"Luisenhofstieg 12-16",
    "sg:city":"Hamburg",
    "sg:phone":"+49 40/7121373",
    "sg:postcode":"22117",
    "sg:province":"Hamburg",
    "wof:name":"Seniorenwohnanlage \u00d6jendorf",
    "wof:placetype":"venue"
},
  "geometry": {"coordinates":[10.124258,53.543091],"type":"Point"}
}