{
  "type": "Feature",
  "properties": {
    "iso:country":"DE",
    "sg:address":"Am Gewerbepark 1",
    "sg:city":"Ueckerm\u00fcnde",
    "sg:postcode":"17373",
    "sg:province":"Mecklenburg-Vorpommern",
    "wof:name":"Pawlak Gmbh",
    "wof:placetype":"venue"
},
  "geometry": {"coordinates":[14.0604763031,53.724811554],"type":"Point"}
}