{
  "type": "Feature",
  "properties": {
    "iso:country":"DE",
    "sg:address":"Bahnhofstr. 18",
    "sg:city":"Hainichen",
    "sg:phone":"+49 37207/2956",
    "sg:postcode":"09661",
    "sg:province":"Sachsen",
    "wof:name":"Gerhard Bartel",
    "wof:placetype":"venue"
},
  "geometry": {"coordinates":[13.1195726395,50.9702033997],"type":"Point"}
}