{
  "type": "Feature",
  "properties": {
    "iso:country":"DE",
    "sg:address":"Johannweg 5a",
    "sg:city":"Friedberg",
    "sg:phone":"+49 821/604589",
    "sg:postcode":"86316",
    "sg:province":"Bayern",
    "wof:name":"Dieter Komarek",
    "wof:placetype":"venue"
},
  "geometry": {"coordinates":[10.9977760315,48.3432693481],"type":"Point"}
}