{
  "type": "Feature",
  "properties": {
    "iso:country":"DE",
    "sg:address":"Selhofer Weg 89",
    "sg:city":"Melle",
    "sg:phone":"+49 5422/2714",
    "sg:postcode":"49324",
    "sg:province":"Niedersachsen",
    "wof:name":"Fritz Henke",
    "wof:placetype":"venue"
},
  "geometry": {"coordinates":[8.35795784,52.1779174805],"type":"Point"}
}