{
  "type": "Feature",
  "properties": {
    "iso:country":"DE",
    "sg:address":"Wettersteinstr. 47",
    "sg:city":"N\u00fcrnberg",
    "sg:phone":"+49 911/863827",
    "sg:postcode":"90471",
    "sg:province":"Bayern",
    "wof:name":"Cafe Elisabeth",
    "wof:placetype":"venue"
},
  "geometry": {"coordinates":[11.11961,49.410686],"type":"Point"}
}