{
  "type": "Feature",
  "properties": {
    "iso:country":"DE",
    "sg:address":"Westhauser Str. 17",
    "sg:city":"Remscheid",
    "sg:phone":"+49 2191/71781",
    "sg:postcode":"42857",
    "sg:province":"Nordrhein-Westfalen",
    "wof:name":"Weber Gmbh",
    "wof:placetype":"venue"
},
  "geometry": {"coordinates":[7.1508460045,51.153377533],"type":"Point"}
}