{
  "type": "Feature",
  "properties": {
    "iso:country":"DE",
    "sg:address":"Br\u00fcckenstr. 44",
    "sg:city":"Schweich",
    "sg:phone":"+49 6502/3956",
    "sg:postcode":"54338",
    "sg:province":"Rheinland-Pfalz",
    "wof:name":"Winfried Just Optiker",
    "wof:placetype":"venue"
},
  "geometry": {"coordinates":[6.7524600029,49.8208961487],"type":"Point"}
}