{
  "type": "Feature",
  "properties": {
    "iso:country":"DE",
    "sg:address":"W\u00f6hlerstr. 42",
    "sg:city":"Hannover",
    "sg:postcode":"30163",
    "sg:province":"Niedersachsen",
    "wof:name":"Wohn Wert Gmbh & Co. Projekt Laatzen Kg",
    "wof:placetype":"venue"
},
  "geometry": {"coordinates":[9.749354,52.397976],"type":"Point"}
}