{
  "type": "Feature",
  "properties": {
    "iso:country":"DE",
    "sg:address":"Bruchwiesenstr. 35 b",
    "sg:city":"Landstuhl",
    "sg:phone":"+49 6371/80060",
    "sg:postcode":"66849",
    "sg:province":"Rheinland-Pfalz",
    "wof:name":"Bofrost Vertriebs- Verwaltungs Liii Gmbh",
    "wof:placetype":"venue"
},
  "geometry": {"coordinates":[7.574051857,49.4175376892],"type":"Point"}
}