{
  "type": "Feature",
  "properties": {
    "iso:country":"DE",
    "sg:address":"Am Teich 18",
    "sg:city":"Neum\u00fcnster",
    "sg:phone":"+49 4321/24152",
    "sg:postcode":"24534",
    "sg:province":"Schleswig-Holstein",
    "wof:name":"Bank F\u00fcr Gemeinwirtschaft",
    "wof:placetype":"venue"
},
  "geometry": {"coordinates":[9.981389,54.072701],"type":"Point"}
}