{
  "type": "Feature",
  "properties": {
    "iso:country":"DE",
    "sg:address":"L\u00fcneburger Schanze 15",
    "sg:city":"Buxtehude",
    "sg:phone":"+49 4161/89722",
    "sg:postcode":"21614",
    "sg:province":"Niedersachsen",
    "wof:name":"Chronos Uhrmacher- Und Juwelierbedarf Gmbh",
    "wof:placetype":"venue"
},
  "geometry": {"coordinates":[9.696323,53.462906],"type":"Point"}
}