{
  "type": "Feature",
  "properties": {
    "iso:country":"DE",
    "sg:address":"Dr.-Hockertz-Str. 22",
    "sg:city":"Rudersberg",
    "sg:phone":"+49 7183/37294",
    "sg:postcode":"73635",
    "sg:province":"Baden-W\u00fcrttemberg",
    "wof:name":"Rudolf M\u00fcrdter",
    "wof:placetype":"venue"
},
  "geometry": {"coordinates":[9.529546,48.882824],"type":"Point"}
}