{
  "type": "Feature",
  "properties": {
    "iso:country":"DE",
    "sg:address":"Geschwister-Scholl-Str. 3",
    "sg:city":"Eisenberg",
    "sg:phone":"+49 36691/46789",
    "sg:postcode":"07607",
    "sg:province":"Th\u00fcringen",
    "wof:name":"Ilona Schulz",
    "wof:placetype":"venue"
},
  "geometry": {"coordinates":[11.894858,50.968773],"type":"Point"}
}