{
  "type": "Feature",
  "properties": {
    "iso:country":"DE",
    "sg:address":"Elsternweg 15",
    "sg:city":"M\u00f6nchengladbach",
    "sg:phone":"+49 2166/603693",
    "sg:postcode":"41199",
    "sg:province":"Nordrhein-Westfalen",
    "wof:name":"W. Kl\u00fcttermann",
    "wof:placetype":"venue"
},
  "geometry": {"coordinates":[6.462858,51.136295],"type":"Point"}
}