{
  "type": "Feature",
  "properties": {
    "iso:country":"DE",
    "sg:address":"Akazienweg 5",
    "sg:city":"Landshut",
    "sg:phone":"+49 871/75115",
    "sg:postcode":"84032",
    "sg:province":"Bayern",
    "wof:name":"Walter Parussel Ingenieur",
    "wof:placetype":"venue"
},
  "geometry": {"coordinates":[12.1285572052,48.5529937744],"type":"Point"}
}