{
  "type": "Feature",
  "properties": {
    "iso:country":"DE",
    "sg:address":"Binger Str. 26a",
    "sg:city":"Berlin",
    "sg:phone":"+49 30/8246506",
    "sg:postcode":"14197",
    "sg:province":"Berlin",
    "wof:name":"Hans-g. Ullrich Kameramann",
    "wof:placetype":"venue"
},
  "geometry": {"coordinates":[13.3092746735,52.4716072083],"type":"Point"}
}