{
  "type": "Feature",
  "properties": {
    "iso:country":"DE",
    "sg:address":"\u00d6lbergweg 33",
    "sg:city":"Bollschweil",
    "sg:phone":"+49 7633/982460",
    "sg:postcode":"79283",
    "sg:province":"Baden-W\u00fcrttemberg",
    "wof:name":"Wein Wehrle Gmbh",
    "wof:placetype":"venue"
},
  "geometry": {"coordinates":[7.7828660011,47.9235420227],"type":"Point"}
}