{
  "type": "Feature",
  "properties": {
    "iso:country":"DE",
    "sg:address":"Grevener Damm 141",
    "sg:city":"Emsdetten",
    "sg:phone":"+49 2572/953605",
    "sg:postcode":"48282",
    "sg:province":"Nordrhein-Westfalen",
    "wof:name":"Restaurant Stadion",
    "wof:placetype":"venue"
},
  "geometry": {"coordinates":[7.5471282005,52.1620025635],"type":"Point"}
}