{
  "type": "Feature",
  "properties": {
    "iso:country":"DE",
    "sg:address":"Wickst\u00e4dter Str. 21",
    "sg:city":"Florstadt",
    "sg:phone":"+49 6035/7406",
    "sg:postcode":"61197",
    "sg:province":"Hessen",
    "wof:name":"Karlheinz Schreitz",
    "wof:placetype":"venue"
},
  "geometry": {"coordinates":[8.8605661392,50.3165855408],"type":"Point"}
}