{
  "type": "Feature",
  "properties": {
    "iso:country":"DE",
    "sg:address":"Marktstr. 42",
    "sg:city":"Einbeck",
    "sg:phone":"+49 5561/71019",
    "sg:postcode":"37574",
    "sg:province":"Niedersachsen",
    "wof:name":"Bajohr-optik Inh. Christoph Bajohr",
    "wof:placetype":"venue"
},
  "geometry": {"coordinates":[9.865691185,51.8169136047],"type":"Point"}
}