{
  "type": "Feature",
  "properties": {
    "iso:country":"DE",
    "sg:address":"Kaiserstr. 88",
    "sg:city":"St. Ingbert",
    "sg:postcode":"66386",
    "sg:province":"Saarland",
    "wof:name":"Foto-gressung St. Ingbert Gmbh",
    "wof:placetype":"venue"
},
  "geometry": {"coordinates":[7.1175751686,49.27917099],"type":"Point"}
}