{
  "type": "Feature",
  "properties": {
    "iso:country":"DE",
    "sg:address":"Schulweg 1",
    "sg:city":"Gerdau",
    "sg:phone":"+49 5808/695",
    "sg:postcode":"29581",
    "sg:province":"Niedersachsen",
    "wof:name":"Liser",
    "wof:placetype":"venue"
},
  "geometry": {"coordinates":[10.4181461334,52.9632492065],"type":"Point"}
}