{
  "type": "Feature",
  "properties": {
    "iso:country":"DE",
    "sg:address":"Stadtweg 9",
    "sg:city":"Homberg",
    "sg:phone":"+49 5681/3033",
    "sg:postcode":"34576",
    "sg:province":"Hessen",
    "wof:name":"Gastst\u00e4tte Christa Simm",
    "wof:placetype":"venue"
},
  "geometry": {"coordinates":[9.3963727951,51.0469436646],"type":"Point"}
}