{
  "type": "Feature",
  "properties": {
    "iso:country":"DE",
    "sg:address":"Lilienstr. 1",
    "sg:city":"Pfinztal",
    "sg:phone":"+49 721/460331",
    "sg:postcode":"76327",
    "sg:province":"Baden-W\u00fcrttemberg",
    "wof:name":"W. Mayer",
    "wof:placetype":"venue"
},
  "geometry": {"coordinates":[8.51562,49.00338],"type":"Point"}
}