{
  "type": "Feature",
  "properties": {
    "iso:country":"DE",
    "sg:address":"Herlinghausen 9",
    "sg:city":"Kierspe",
    "sg:phone":"+49 2359/2120",
    "sg:postcode":"58566",
    "sg:province":"Nordrhein-Westfalen",
    "wof:name":"Ernst L\u00fctringhaus",
    "wof:placetype":"venue"
},
  "geometry": {"coordinates":[7.590136,51.15704],"type":"Point"}
}