{
  "type": "Feature",
  "properties": {
    "iso:country":"DE",
    "sg:address":"Gilgenmatten 10a",
    "sg:city":"Freiburg",
    "sg:phone":"+49 761/471023",
    "sg:postcode":"79114",
    "sg:province":"Baden-W\u00fcrttemberg",
    "wof:name":"Mathias Behrle",
    "wof:placetype":"venue"
},
  "geometry": {"coordinates":[7.8128938675,47.9988327026],"type":"Point"}
}