{
  "type": "Feature",
  "properties": {
    "iso:country":"DE",
    "sg:address":"Waldkraiburger Str. 14",
    "sg:city":"Neutraubling",
    "sg:phone":"+49 9401/912325",
    "sg:postcode":"93073",
    "sg:province":"Bayern",
    "wof:name":"Hekro Dr.-ing. E. H. H. Kronseder",
    "wof:placetype":"venue"
},
  "geometry": {"coordinates":[12.1926240921,48.9770584106],"type":"Point"}
}