{
  "type": "Feature",
  "properties": {
    "iso:country":"DE",
    "sg:address":"Am Kirchfeld 15",
    "sg:city":"Saaldorf-Surheim",
    "sg:phone":"+49 8654/694395",
    "sg:postcode":"83416",
    "sg:province":"Bayern",
    "wof:name":"Fliesenverlegung Exklusiv Giocondo Gmbh & Co. Kg",
    "wof:placetype":"venue"
},
  "geometry": {"coordinates":[12.9611597061,47.8754196167],"type":"Point"}
}