{
  "type": "Feature",
  "properties": {
    "iso:country":"DE",
    "sg:address":"Christinastr. 24",
    "sg:city":"K\u00f6ln",
    "sg:phone":"+49 221/728599",
    "sg:postcode":"50733",
    "sg:province":"Nordrhein-Westfalen",
    "wof:name":"Josef Kl\u00fctsch Architekt",
    "wof:placetype":"venue"
},
  "geometry": {"coordinates":[6.952895,50.960701],"type":"Point"}
}