{
  "type": "Feature",
  "properties": {
    "iso:country":"DE",
    "sg:address":"Werner-Seelenbinder-Str. 5",
    "sg:city":"Chemnitz",
    "sg:phone":"+49 371/523960",
    "sg:postcode":"09120",
    "sg:province":"Sachsen",
    "wof:name":"Hellweg Die Profi- Baum\u00e4rkte Gmbh & Co. Kg",
    "wof:placetype":"venue"
},
  "geometry": {"coordinates":[12.914794,50.803322],"type":"Point"}
}