{
  "type": "Feature",
  "properties": {
    "iso:country":"DE",
    "sg:address":"Dammstr. 66",
    "sg:city":"Heilbronn",
    "sg:phone":"+49 7131/171390",
    "sg:postcode":"74076",
    "sg:province":"Baden-W\u00fcrttemberg",
    "wof:name":"Barbara Von Zengen",
    "wof:placetype":"venue"
},
  "geometry": {"coordinates":[9.22706604,49.1469306946],"type":"Point"}
}