{
  "type": "Feature",
  "properties": {
    "iso:country":"DE",
    "sg:address":"Reuchlinstr. 4",
    "sg:city":"Bretten",
    "sg:phone":"+49 7252/2248",
    "sg:postcode":"75015",
    "sg:province":"Baden-W\u00fcrttemberg",
    "wof:name":"Ev. Pfarramt Luthergemeinde",
    "wof:placetype":"venue"
},
  "geometry": {"coordinates":[8.7128381729,49.03673172],"type":"Point"}
}