{
  "type": "Feature",
  "properties": {
    "iso:country":"DE",
    "sg:address":"Georg-Schumann-Str. 16",
    "sg:city":"Zwenkau",
    "sg:phone":"+49 34203/31973",
    "sg:postcode":"04442",
    "sg:province":"Sachsen",
    "wof:name":"Eberhard H\u00e4ndler Ingenieur",
    "wof:placetype":"venue"
},
  "geometry": {"coordinates":[12.334318161,51.2263526917],"type":"Point"}
}