{
  "type": "Feature",
  "properties": {
    "iso:country":"DE",
    "sg:address":"Siemensstra\u00dfe 21",
    "sg:city":"Dornstetten",
    "sg:phone":"+49 7443",
    "sg:postcode":"72280",
    "sg:province":"Baden-W\u00fcrttemberg",
    "wof:name":"Autohaus Sigle Gmbh Volvo Vertragsh\u00e4ndler",
    "wof:placetype":"venue"
},
  "geometry": {"coordinates":[8.495054245,48.4770355225],"type":"Point"}
}