{
  "type": "Feature",
  "properties": {
    "iso:country":"DE",
    "sg:address":"Friedrichstr. 12",
    "sg:city":"Ennepetal",
    "sg:phone":"+49 2333/860252",
    "sg:postcode":"58256",
    "sg:province":"Nordrhein-Westfalen",
    "wof:name":"Bedachungen Alberts Gmbh & Co. Kg",
    "wof:placetype":"venue"
},
  "geometry": {"coordinates":[7.346478,51.301487],"type":"Point"}
}