{
  "type": "Feature",
  "properties": {
    "iso:country":"DE",
    "sg:address":"Stra\u00dfburger Str. 3",
    "sg:city":"Chemnitz",
    "sg:phone":"+49 371/5202841",
    "sg:postcode":"09120",
    "sg:province":"Sachsen",
    "wof:name":"R & R Aktiv-bau Gmbh & Co. Kg",
    "wof:placetype":"venue"
},
  "geometry": {"coordinates":[12.912316,50.818989],"type":"Point"}
}