{
  "type": "Feature",
  "properties": {
    "iso:country":"DE",
    "sg:address":"Gewerbegebiet \u00dcrzigerm\u00fchle",
    "sg:city":"Zeltingen-Rachtig",
    "sg:phone":"+49 4965/3295300",
    "sg:postcode":"54492",
    "sg:province":"Rheinland-Pfalz",
    "wof:name":"Kuhn Auto- Technik Gmbh",
    "wof:placetype":"venue"
},
  "geometry": {"coordinates":[7.0085678101,49.97605896],"type":"Point"}
}