{
  "type": "Feature",
  "properties": {
    "iso:country":"DE",
    "sg:address":"Oppener Str. 140",
    "sg:city":"W\u00fcrselen",
    "sg:phone":"+49 2405/94392",
    "sg:postcode":"52146",
    "sg:province":"Nordrhein-Westfalen",
    "wof:name":"Gilbert",
    "wof:placetype":"venue"
},
  "geometry": {"coordinates":[6.141574,50.811005],"type":"Point"}
}