{
  "type": "Feature",
  "properties": {
    "iso:country":"DE",
    "sg:address":"Hauptstr. 9",
    "sg:city":"R\u00f6ckingen",
    "sg:phone":"+49 9832/463",
    "sg:postcode":"91740",
    "sg:province":"Bayern",
    "wof:name":"Wolfgang Malike",
    "wof:placetype":"venue"
},
  "geometry": {"coordinates":[10.573342,49.049107],"type":"Point"}
}