{
  "type": "Feature",
  "properties": {
    "iso:country":"DE",
    "sg:address":"Friedrichstr. 56",
    "sg:city":"Schleswig",
    "sg:phone":"+49 4621/32107",
    "sg:postcode":"24837",
    "sg:province":"Schleswig-Holstein",
    "wof:name":"Friedrichsberger Apotheke",
    "wof:placetype":"venue"
},
  "geometry": {"coordinates":[9.541884,54.502438],"type":"Point"}
}