{
  "type": "Feature",
  "properties": {
    "iso:country":"DE",
    "sg:address":"Eisenbahnstr. 19",
    "sg:city":"Berlin",
    "sg:phone":"+49 30/6181552",
    "sg:postcode":"10997",
    "sg:province":"Berlin",
    "wof:name":"Peter Rohr Ingenieur",
    "wof:placetype":"venue"
},
  "geometry": {"coordinates":[13.4341888428,52.5036697388],"type":"Point"}
}