{
  "type": "Feature",
  "properties": {
    "iso:country":"DE",
    "sg:address":"Bultkamp 3",
    "sg:city":"Bielefeld",
    "sg:phone":"+49 521/82863",
    "sg:postcode":"33611",
    "sg:province":"Nordrhein-Westfalen",
    "wof:name":"G. Vorsch\u00fctz Gmbh",
    "wof:placetype":"venue"
},
  "geometry": {"coordinates":[8.5419,52.054096],"type":"Point"}
}