{
  "type": "Feature",
  "properties": {
    "iso:country":"DE",
    "sg:address":"Limmerstr. 40",
    "sg:city":"Hannover",
    "sg:phone":"+49 511/451554",
    "sg:postcode":"30451",
    "sg:province":"Niedersachsen",
    "wof:name":"Ristorante Sorrento",
    "wof:placetype":"venue"
},
  "geometry": {"coordinates":[9.7081012726,52.3734016418],"type":"Point"}
}