{
  "type": "Feature",
  "properties": {
    "iso:country":"DE",
    "sg:address":"Klausenweg 18",
    "sg:city":"Hanau",
    "sg:phone":"+49 6181/85545",
    "sg:postcode":"63452",
    "sg:province":"Hessen",
    "wof:name":"Emil Gutmann",
    "wof:placetype":"venue"
},
  "geometry": {"coordinates":[8.9067153931,50.1468391418],"type":"Point"}
}