{
  "type": "Feature",
  "properties": {
    "iso:country":"DE",
    "sg:address":"Heideckstr. 6",
    "sg:city":"M\u00fcnchen",
    "sg:phone":"+49 89/1578303",
    "sg:postcode":"80637",
    "sg:province":"Bayern",
    "wof:name":"Helfried Haimerl",
    "wof:placetype":"venue"
},
  "geometry": {"coordinates":[11.5413341522,48.1624298096],"type":"Point"}
}