{
  "type": "Feature",
  "properties": {
    "iso:country":"DE",
    "sg:address":"Konradstr. 2",
    "sg:city":"Zwickau",
    "sg:phone":"+49 375/2304191",
    "sg:postcode":"08056",
    "sg:province":"Sachsen",
    "wof:name":"Niederth\u00e4ler Hof Weingut-weinkellerei Gmbh",
    "wof:placetype":"venue"
},
  "geometry": {"coordinates":[12.4850997925,50.7222709656],"type":"Point"}
}