{
  "type": "Feature",
  "properties": {
    "iso:country":"DE",
    "sg:address":"Merzenstr. 15",
    "sg:city":"Frankfurt",
    "sg:phone":"+49 6101/48078",
    "sg:postcode":"60437",
    "sg:province":"Hessen",
    "wof:name":"S. I. N. G. H Obst- Und Gem\u00fcsehandel Gmbh",
    "wof:placetype":"venue"
},
  "geometry": {"coordinates":[8.6950798035,50.1862602234],"type":"Point"}
}