{
  "type": "Feature",
  "properties": {
    "iso:country":"DE",
    "sg:address":"Abelweg 15 a",
    "sg:city":"Kronshagen",
    "sg:phone":"+49 431/544554",
    "sg:postcode":"24119",
    "sg:province":"Schleswig-Holstein",
    "wof:name":"Grundst\u00fccksverwaltungs- Gesellschaft Bartels Mbh",
    "wof:placetype":"venue"
},
  "geometry": {"coordinates":[10.0905008316,54.3392868042],"type":"Point"}
}