{
  "type": "Feature",
  "properties": {
    "iso:country":"DE",
    "sg:address":"Finkenweg 37",
    "sg:city":"Aschaffenburg",
    "sg:phone":"+49 6021/450202",
    "sg:postcode":"63741",
    "sg:province":"Bayern",
    "wof:name":"G. Walter",
    "wof:placetype":"venue"
},
  "geometry": {"coordinates":[9.119099617,49.989440918],"type":"Point"}
}