{
  "type": "Feature",
  "properties": {
    "iso:country":"DE",
    "sg:address":"Schnuckendrift 17",
    "sg:city":"Hamburg",
    "sg:phone":"+49 40/7018613",
    "sg:postcode":"21149",
    "sg:province":"Hamburg",
    "wof:name":"A. Neubacher",
    "wof:placetype":"venue"
},
  "geometry": {"coordinates":[9.842002,53.468178],"type":"Point"}
}