{
  "type": "Feature",
  "properties": {
    "iso:country":"DE",
    "sg:address":"St.-Jakob-Str. 1",
    "sg:city":"Wunsiedel",
    "sg:phone":"+49 9232/70205",
    "sg:postcode":"95632",
    "sg:province":"Bayern",
    "wof:name":"Martin Sch\u00f6ffel",
    "wof:placetype":"venue"
},
  "geometry": {"coordinates":[12.0029230118,50.0445365906],"type":"Point"}
}