{
  "type": "Feature",
  "properties": {
    "iso:country":"DE",
    "sg:city":"Freyung",
    "sg:phone":"+49 8551/58850",
    "sg:postcode":"94078",
    "sg:province":"Bayern",
    "wof:name":"Freizeitpark Solla",
    "wof:placetype":"venue"
},
  "geometry": {"coordinates":[13.547495,48.807678],"type":"Point"}
}