{
  "type": "Feature",
  "properties": {
    "iso:country":"DE",
    "sg:address":"Am Sch\u00fclerheim 8",
    "sg:city":"Berlin",
    "sg:phone":"+49 30/8929041",
    "sg:postcode":"14195",
    "sg:province":"Berlin",
    "wof:name":"Hans-j\u00fcrgen Juschkus Dipl.-ingenieur",
    "wof:placetype":"venue"
},
  "geometry": {"coordinates":[13.279086113,52.4577789307],"type":"Point"}
}