{
  "type": "Feature",
  "properties": {
    "iso:country":"DE",
    "sg:address":"Harzstr. 22/23",
    "sg:city":"Wolfenb\u00fcttel",
    "sg:postcode":"38300",
    "sg:province":"Niedersachsen",
    "wof:name":"Mcb Medienservice Center Beteiligungsgesellschaft Mbh",
    "wof:placetype":"venue"
},
  "geometry": {"coordinates":[10.535409,52.161095],"type":"Point"}
}