{
  "type": "Feature",
  "properties": {
    "iso:country":"DE",
    "sg:address":"Kleinsteinacher Weg 3",
    "sg:city":"Hofheim",
    "sg:phone":"+49 9523/5479",
    "sg:postcode":"97461",
    "sg:province":"Bayern",
    "wof:name":"Horst Graser",
    "wof:placetype":"venue"
},
  "geometry": {"coordinates":[10.508483,50.110943],"type":"Point"}
}