{
  "type": "Feature",
  "properties": {
    "iso:country":"DE",
    "sg:address":"Steintorwall 4",
    "sg:city":"Hamburg",
    "sg:phone":"+49 40/322343",
    "sg:postcode":"20095",
    "sg:province":"Hamburg",
    "wof:name":"Steinthorhaus",
    "wof:placetype":"venue"
},
  "geometry": {"coordinates":[10.0051002502,53.5523986816],"type":"Point"}
}