{
  "type": "Feature",
  "properties": {
    "iso:country":"DE",
    "sg:address":"Waltraudstr 25",
    "sg:city":"Berlin",
    "sg:phone":"+49 30/8137983",
    "sg:postcode":"14169",
    "sg:province":"Berlin",
    "wof:name":"Keri-werbung Rimbach Gmbh",
    "wof:placetype":"venue"
},
  "geometry": {"coordinates":[13.265094,52.447975],"type":"Point"}
}