{
  "type": "Feature",
  "properties": {
    "iso:country":"DE",
    "sg:address":"Ferdinand-Lassalle-Str. 2",
    "sg:city":"Taucha",
    "sg:phone":"+49 34298/13336",
    "sg:postcode":"04425",
    "sg:province":"Sachsen",
    "wof:name":"Zw-design, Der Werbedienstleister",
    "wof:placetype":"venue"
},
  "geometry": {"coordinates":[12.486484,51.3764],"type":"Point"}
}