{
  "type": "Feature",
  "properties": {
    "iso:country":"DE",
    "sg:address":"Im Rheinwinkel 22",
    "sg:city":"K\u00f6ln",
    "sg:phone":"+49 2203/15470",
    "sg:postcode":"51149",
    "sg:province":"Nordrhein-Westfalen",
    "wof:name":"Dr. Med. Reinhart Clemens Arzt F\u00fcr Nervenheilkunde",
    "wof:placetype":"venue"
},
  "geometry": {"coordinates":[7.042951,50.895252],"type":"Point"}
}