{
  "type": "Feature",
  "properties": {
    "iso:country":"DE",
    "sg:address":"Im Rottfeld 25",
    "sg:city":"D\u00fcsseldorf",
    "sg:phone":"+49 211/6415661",
    "sg:postcode":"40239",
    "sg:province":"Nordrhein-Westfalen",
    "wof:name":"Peter Zeisig Rechtsanwalt",
    "wof:placetype":"venue"
},
  "geometry": {"coordinates":[6.8068161011,51.2455978394],"type":"Point"}
}