{
  "type": "Feature",
  "properties": {
    "iso:country":"DE",
    "sg:address":"Spanische Allee 158",
    "sg:city":"Berlin",
    "sg:phone":"+49 30/8032054",
    "sg:postcode":"14129",
    "sg:province":"Berlin",
    "wof:name":"Dagmar Gail",
    "wof:placetype":"venue"
},
  "geometry": {"coordinates":[13.195242,52.433987],"type":"Point"}
}