{
  "type": "Feature",
  "properties": {
    "iso:country":"DE",
    "sg:address":"Burghaldenstr. 6",
    "sg:city":"Fluorn-Winzeln",
    "sg:phone":"+49 7402/92140",
    "sg:postcode":"78737",
    "sg:province":"Baden-W\u00fcrttemberg",
    "wof:name":"Dieterle Ingenieur",
    "wof:placetype":"venue"
},
  "geometry": {"coordinates":[8.4902858734,48.2820549011],"type":"Point"}
}