{
  "type": "Feature",
  "properties": {
    "iso:country":"DE",
    "sg:address":"Mengeder Str. 503",
    "sg:city":"Dortmund",
    "sg:phone":"+49 231/355710",
    "sg:postcode":"44359",
    "sg:province":"Nordrhein-Westfalen",
    "wof:name":"Haus Elling",
    "wof:placetype":"venue"
},
  "geometry": {"coordinates":[7.3969497681,51.5548782349],"type":"Point"}
}