{
  "type": "Feature",
  "properties": {
    "iso:country":"DE",
    "sg:address":"Obere Str. 3",
    "sg:city":"Freiberg",
    "sg:phone":"+49 3731/248058",
    "sg:postcode":"09599",
    "sg:province":"Sachsen",
    "wof:name":"Halsbach",
    "wof:placetype":"venue"
},
  "geometry": {"coordinates":[13.3434381485,50.916633606],"type":"Point"}
}