{
  "type": "Feature",
  "properties": {
    "iso:country":"DE",
    "sg:address":"Br\u00fcder-Grimm-Str. 121",
    "sg:city":"Steinau",
    "sg:phone":"+49 4966/6396040",
    "sg:postcode":"36396",
    "sg:province":"Hessen",
    "wof:name":"Rubiepharm Arzneimittel Gmbh",
    "wof:placetype":"venue"
},
  "geometry": {"coordinates":[9.455925,50.311634],"type":"Point"}
}