{
  "type": "Feature",
  "properties": {
    "iso:country":"DE",
    "sg:address":"Pankratiusstr. 26 A",
    "sg:city":"Darmstadt",
    "sg:postcode":"64289",
    "sg:province":"Hessen",
    "wof:name":"Delta-lohnsteuerhilfe- Verein E. V.",
    "wof:placetype":"venue"
},
  "geometry": {"coordinates":[8.6586046219,49.8798751831],"type":"Point"}
}