{
  "type": "Feature",
  "properties": {
    "iso:country":"DE",
    "sg:address":"Am Erkelsborn 11",
    "sg:city":"Wiesbaden",
    "sg:phone":"+49 611/74344",
    "sg:postcode":"65189",
    "sg:province":"Hessen",
    "wof:name":"M. Claussen Immobilienmakler",
    "wof:placetype":"venue"
},
  "geometry": {"coordinates":[8.2639780045,50.0760269165],"type":"Point"}
}