{
  "type": "Feature",
  "properties": {
    "iso:country":"DE",
    "sg:address":"Trillfinger Weg",
    "sg:city":"Haigerloch",
    "sg:phone":"+49 7474/8765",
    "sg:postcode":"72401",
    "sg:province":"Baden-W\u00fcrttemberg",
    "wof:name":"Vereinsheim",
    "wof:placetype":"venue"
},
  "geometry": {"coordinates":[8.7732896805,48.3831558228],"type":"Point"}
}