{
  "type": "Feature",
  "properties": {
    "iso:country":"DE",
    "sg:address":"Kastanienallee 1",
    "sg:city":"Bad Neustadt",
    "sg:postcode":"97616",
    "sg:province":"Bayern",
    "wof:name":"Matinet Ag",
    "wof:placetype":"venue"
},
  "geometry": {"coordinates":[10.2281303406,50.3328056335],"type":"Point"}
}