{
  "type": "Feature",
  "properties": {
    "iso:country":"DE",
    "sg:address":"Ludwig-Hermann-Str. 42",
    "sg:city":"Gersthofen",
    "sg:phone":"+49 821",
    "sg:postcode":"86368",
    "sg:province":"Bayern",
    "wof:name":"Giganetz.de",
    "wof:placetype":"venue"
},
  "geometry": {"coordinates":[10.8825283051,48.4333610535],"type":"Point"}
}