{
  "type": "Feature",
  "properties": {
    "iso:country":"DE",
    "sg:address":"Lindenstr. 8/1",
    "sg:city":"Berglen",
    "sg:phone":"+49 7195/73668",
    "sg:postcode":"73663",
    "sg:province":"Baden-W\u00fcrttemberg",
    "wof:name":"G. Oberer",
    "wof:placetype":"venue"
},
  "geometry": {"coordinates":[9.4533090591,48.8418083191],"type":"Point"}
}