{
  "type": "Feature",
  "properties": {
    "iso:country":"DE",
    "sg:address":"Wolfsgasse 8",
    "sg:city":"Wertheim",
    "sg:phone":"+49 9342/23842",
    "sg:postcode":"97877",
    "sg:province":"Baden-W\u00fcrttemberg",
    "wof:name":"Friedrich Lohmann",
    "wof:placetype":"venue"
},
  "geometry": {"coordinates":[9.5596837997,49.7720298767],"type":"Point"}
}