{
  "type": "Feature",
  "properties": {
    "iso:country":"DE",
    "sg:address":"Friedrichstr. 32",
    "sg:city":"Rheinfelden",
    "sg:phone":"+49 7623/8595",
    "sg:postcode":"79618",
    "sg:province":"Baden-W\u00fcrttemberg",
    "wof:name":"St. Vinzentiusverein Rheinfelden",
    "wof:placetype":"venue"
},
  "geometry": {"coordinates":[7.7914500237,47.5616493225],"type":"Point"}
}