{
  "type": "Feature",
  "properties": {
    "iso:country":"DE",
    "sg:address":"Neandertalstr. 5",
    "sg:city":"Gr\u00f6benzell",
    "sg:phone":"+49 8142/60499",
    "sg:postcode":"82194",
    "sg:province":"Bayern",
    "wof:name":"Siegfried Haubner Architekt",
    "wof:placetype":"venue"
},
  "geometry": {"coordinates":[11.377264,48.191349],"type":"Point"}
}