{
  "type": "Feature",
  "properties": {
    "iso:country":"DE",
    "sg:address":"Reichenstr. 14",
    "sg:city":"F\u00fcssen",
    "sg:phone":"+49 8362/38472",
    "sg:postcode":"87629",
    "sg:province":"Bayern",
    "wof:name":"Eiscafe Hohes Schlo\u00df",
    "wof:placetype":"venue"
},
  "geometry": {"coordinates":[10.700077,47.568203],"type":"Point"}
}