{
  "type": "Feature",
  "properties": {
    "iso:country":"DE",
    "sg:address":"B\u00fcrgerm.-Stocker-Ring 51",
    "sg:city":"Schrobenhausen",
    "sg:phone":"+49 8252/89210",
    "sg:postcode":"86529",
    "sg:province":"Bayern",
    "wof:name":"Reiseb\u00fcro Steinhauser",
    "wof:placetype":"venue"
},
  "geometry": {"coordinates":[11.2651576996,48.5587654114],"type":"Point"}
}