{
  "type": "Feature",
  "properties": {
    "iso:country":"DE",
    "sg:address":"Im Wohnpark 31",
    "sg:city":"Bergheim",
    "sg:phone":"+49 2271/91659",
    "sg:postcode":"50127",
    "sg:province":"Nordrhein-Westfalen",
    "wof:name":"G. Krekels",
    "wof:placetype":"venue"
},
  "geometry": {"coordinates":[6.653192997,50.9263687134],"type":"Point"}
}