{
  "type": "Feature",
  "properties": {
    "iso:country":"DE",
    "sg:address":"Im Dorf 26",
    "sg:city":"Reutlingen",
    "sg:phone":"+49 7121/54880",
    "sg:postcode":"72770",
    "sg:province":"Baden-W\u00fcrttemberg",
    "wof:name":"Manfred Renz",
    "wof:placetype":"venue"
},
  "geometry": {"coordinates":[9.174424,48.499004],"type":"Point"}
}