{
  "type": "Feature",
  "properties": {
    "iso:country":"DE",
    "sg:address":"Von-Kleist-Str. 4",
    "sg:city":"Mering",
    "sg:phone":"+49 8233/92407",
    "sg:postcode":"86415",
    "sg:province":"Bayern",
    "wof:name":"G\u00fcnter Wolf",
    "wof:placetype":"venue"
},
  "geometry": {"coordinates":[10.98250103,48.2590827942],"type":"Point"}
}