{
  "type": "Feature",
  "properties": {
    "iso:country":"DE",
    "sg:address":"Schweinmarkt 6",
    "sg:city":"Ulm",
    "sg:phone":"+49 731/6021600",
    "sg:postcode":"89073",
    "sg:province":"Baden-W\u00fcrttemberg",
    "wof:name":"Mevaco International Holding Gmbh",
    "wof:placetype":"venue"
},
  "geometry": {"coordinates":[9.989623,48.394932],"type":"Point"}
}