{
  "type": "Feature",
  "properties": {
    "iso:country":"DE",
    "sg:address":"Neusser Str. 113",
    "sg:city":"J\u00fcchen",
    "sg:phone":"+49 2165/5001",
    "sg:postcode":"41363",
    "sg:province":"Nordrhein-Westfalen",
    "wof:name":"Grabmale Wolf Gmbh",
    "wof:placetype":"venue"
},
  "geometry": {"coordinates":[6.5196390152,51.0992774963],"type":"Point"}
}