{
  "type": "Feature",
  "properties": {
    "iso:country":"DE",
    "sg:address":"Behnstr. 1",
    "sg:city":"Hannover",
    "sg:phone":"+49 511/232701",
    "sg:postcode":"30519",
    "sg:province":"Niedersachsen",
    "wof:name":"Kabeldienst Kabelanschluss- Verwaltungsges. Mbh",
    "wof:placetype":"venue"
},
  "geometry": {"coordinates":[9.7827072144,52.3253517151],"type":"Point"}
}