{
  "type": "Feature",
  "properties": {
    "iso:country":"DE",
    "sg:address":"Universit\u00e4tsplatz 1",
    "sg:city":"Fulda",
    "sg:phone":"+49 661/10094",
    "sg:postcode":"36037",
    "sg:province":"Hessen",
    "wof:name":"Steinmetz Und K\u00fcbel Rechtsanw\u00e4lte Und Notare",
    "wof:placetype":"venue"
},
  "geometry": {"coordinates":[9.6788597107,50.5522460938],"type":"Point"}
}