{
  "type": "Feature",
  "properties": {
    "iso:country":"DE",
    "sg:address":"Prinz-Wilhelm-Stra\u00dfe 33",
    "sg:city":"Bruchsal",
    "sg:phone":"+49 7251/97730",
    "sg:postcode":"76646",
    "sg:province":"Baden-W\u00fcrttemberg",
    "wof:name":"Wirtschaftspr\u00fcfung- Steuerberatungsgesellschaft",
    "wof:placetype":"venue"
},
  "geometry": {"coordinates":[8.588696,49.120834],"type":"Point"}
}