{
  "type": "Feature",
  "properties": {
    "iso:country":"DE",
    "sg:address":"Johannes-Albers-Allee 2",
    "sg:city":"K\u00f6nigswinter",
    "sg:postcode":"53639",
    "sg:province":"Nordrhein-Westfalen",
    "wof:name":"Einhundertundeins Communi- Cations Deutschland Gmbh",
    "wof:placetype":"venue"
},
  "geometry": {"coordinates":[7.182777,50.686203],"type":"Point"}
}