{
  "type": "Feature",
  "properties": {
    "iso:country":"DE",
    "sg:address":"Im Winkel 4",
    "sg:city":"Suthfeld",
    "sg:phone":"+49 5723/2758728",
    "sg:postcode":"31555",
    "sg:province":"Niedersachsen",
    "wof:name":"Otto Bock",
    "wof:placetype":"venue"
},
  "geometry": {"coordinates":[9.401696,52.352341],"type":"Point"}
}