{
  "type": "Feature",
  "properties": {
    "iso:country":"DE",
    "sg:address":"Muthesiusweg 27",
    "sg:city":"Hannover",
    "sg:phone":"+49 511/529720",
    "sg:postcode":"30559",
    "sg:province":"Niedersachsen",
    "wof:name":"Gerhard Lorenz Ingenieur",
    "wof:placetype":"venue"
},
  "geometry": {"coordinates":[9.838394165,52.356842041],"type":"Point"}
}