{
  "type": "Feature",
  "properties": {
    "iso:country":"DE",
    "sg:address":"Eggenfeldener Str. 6",
    "sg:city":"Pfarrkirchen",
    "sg:phone":"+49 8561/2870",
    "sg:postcode":"84347",
    "sg:province":"Bayern",
    "wof:name":"Die Sattelkammer Inh. Michael Deym",
    "wof:placetype":"venue"
},
  "geometry": {"coordinates":[12.93529,48.43224],"type":"Point"}
}