{
  "type": "Feature",
  "properties": {
    "iso:country":"DE",
    "sg:address":"Duisburger Str. 292",
    "sg:city":"M\u00fclheim",
    "sg:phone":"+49 208/50528",
    "sg:postcode":"45478",
    "sg:province":"Nordrhein-Westfalen",
    "wof:name":"R. H. Rehmann Tischlerei Gmbh",
    "wof:placetype":"venue"
},
  "geometry": {"coordinates":[6.840811,51.428905],"type":"Point"}
}