{
  "type": "Feature",
  "properties": {
    "iso:country":"DE",
    "sg:address":"Carl-Theodor-Str. 6",
    "sg:city":"Schwetzingen",
    "sg:phone":"+49 6202/272404",
    "sg:postcode":"68723",
    "sg:province":"Baden-W\u00fcrttemberg",
    "wof:name":"G. Baumann",
    "wof:placetype":"venue"
},
  "geometry": {"coordinates":[8.574363,49.384472],"type":"Point"}
}