{
  "type": "Feature",
  "properties": {
    "iso:country":"DE",
    "sg:address":"Burgwedeltwiete 23",
    "sg:city":"Hamburg",
    "sg:phone":"+49 40/5500350",
    "sg:postcode":"22457",
    "sg:province":"Hamburg",
    "wof:name":"J\u00fcrgen Str\u00fcven",
    "wof:placetype":"venue"
},
  "geometry": {"coordinates":[9.9114341736,53.6426887512],"type":"Point"}
}