{
  "type": "Feature",
  "properties": {
    "iso:country":"DE",
    "sg:address":"Ramsbergstr. 6",
    "sg:city":"S\u00fc\u00dfen",
    "sg:phone":"+49 7162/930000",
    "sg:postcode":"73079",
    "sg:province":"Baden-W\u00fcrttemberg",
    "wof:name":"Antares Informations- Systeme Gmbh",
    "wof:placetype":"venue"
},
  "geometry": {"coordinates":[9.7652359009,48.68384552],"type":"Point"}
}