{
  "type": "Feature",
  "properties": {
    "iso:country":"DE",
    "sg:address":"Hauptstr. 23",
    "sg:city":"Wolnzach",
    "sg:phone":"+49 8442/5102",
    "sg:postcode":"85283",
    "sg:province":"Bayern",
    "wof:name":"Akropolis",
    "wof:placetype":"venue"
},
  "geometry": {"coordinates":[11.622918129,48.5648803711],"type":"Point"}
}