{
  "type": "Feature",
  "properties": {
    "iso:country":"DE",
    "sg:address":"Gibitzenhofstr. 125",
    "sg:city":"N\u00fcrnberg",
    "sg:phone":"+49 911/429293",
    "sg:postcode":"90443",
    "sg:province":"Bayern",
    "wof:name":"Karin Hauke",
    "wof:placetype":"venue"
},
  "geometry": {"coordinates":[11.067951,49.433285],"type":"Point"}
}