{
  "type": "Feature",
  "properties": {
    "iso:country":"DE",
    "sg:address":"W\u00fcrzburger Str. 10",
    "sg:city":"Waldb\u00fcttelbrunn",
    "sg:phone":"+49 931/48904",
    "sg:postcode":"97297",
    "sg:province":"Bayern",
    "wof:name":"Gottfried Spiegel",
    "wof:placetype":"venue"
},
  "geometry": {"coordinates":[9.8487071991,49.7898406982],"type":"Point"}
}