{
  "type": "Feature",
  "properties": {
    "iso:country":"DE",
    "sg:address":"Hardstr. 9",
    "sg:city":"F\u00fcrth",
    "sg:phone":"+49 911/739368",
    "sg:postcode":"90766",
    "sg:province":"Bayern",
    "wof:name":"Andreas Bohn",
    "wof:placetype":"venue"
},
  "geometry": {"coordinates":[10.9771871567,49.4787788391],"type":"Point"}
}