{
  "type": "Feature",
  "properties": {
    "iso:country":"DE",
    "sg:address":"M\u00fcnzmeisterstr. 6",
    "sg:city":"Dresden",
    "sg:phone":"+49 351/4012412",
    "sg:postcode":"01217",
    "sg:province":"Sachsen",
    "wof:name":"J\u00f6rn Thomas",
    "wof:placetype":"venue"
},
  "geometry": {"coordinates":[13.7409973145,51.0230789185],"type":"Point"}
}