{
  "type": "Feature",
  "properties": {
    "iso:country":"DE",
    "sg:address":"Kanalstr. 24",
    "sg:city":"Wusterwitz",
    "sg:phone":"+49 33839/468",
    "sg:postcode":"14789",
    "sg:province":"Brandenburg",
    "wof:name":"Fritz M\u00f6lter",
    "wof:placetype":"venue"
},
  "geometry": {"coordinates":[12.3717498779,52.3907089233],"type":"Point"}
}