{
  "type": "Feature",
  "properties": {
    "iso:country":"DE",
    "sg:address":"Industriestr. 3",
    "sg:city":"Bohmte",
    "sg:phone":"+49 5471/1599",
    "sg:postcode":"49163",
    "sg:province":"Niedersachsen",
    "wof:name":"Iwl Gmbh",
    "wof:placetype":"venue"
},
  "geometry": {"coordinates":[8.309214592,52.3823127747],"type":"Point"}
}