{
  "type": "Feature",
  "properties": {
    "iso:country":"DE",
    "sg:address":"Wohlesbosteler Str. 3",
    "sg:city":"Hollenstedt",
    "sg:phone":"+49 4165/80557",
    "sg:postcode":"21279",
    "sg:province":"Niedersachsen",
    "wof:name":"Gerhard Ritscher",
    "wof:placetype":"venue"
},
  "geometry": {"coordinates":[9.710426,53.367641],"type":"Point"}
}