{
  "type": "Feature",
  "properties": {
    "iso:country":"DE",
    "sg:address":"Kastanienallee",
    "sg:city":"Trossin",
    "sg:phone":"+49 34223/40340",
    "sg:postcode":"04880",
    "sg:province":"Sachsen",
    "wof:name":"I. M\u00fcller",
    "wof:placetype":"venue"
},
  "geometry": {"coordinates":[12.7689857483,51.6158103943],"type":"Point"}
}