{
  "type": "Feature",
  "properties": {
    "iso:country":"DE",
    "sg:address":"Weitseestr. 21",
    "sg:city":"Reit im Winkl",
    "sg:phone":"+49 8640/8441",
    "sg:postcode":"83242",
    "sg:province":"Bayern",
    "wof:name":"G\u00e4stehaus Anny Wiefarn",
    "wof:placetype":"venue"
},
  "geometry": {"coordinates":[12.4715824127,47.6746826172],"type":"Point"}
}