{
  "type": "Feature",
  "properties": {
    "iso:country":"DE",
    "sg:address":"Konrad-Adenauer-Str. 83",
    "sg:city":"Otterbach",
    "sg:phone":"+49 6301/9332",
    "sg:postcode":"67731",
    "sg:province":"Rheinland-Pfalz",
    "wof:name":"Meisenheimer & Liebl Gmbh",
    "wof:placetype":"venue"
},
  "geometry": {"coordinates":[7.728938,49.48505],"type":"Point"}
}