{
  "type": "Feature",
  "properties": {
    "iso:country":"DE",
    "sg:address":"Chausseestr. 17",
    "sg:city":"Estedt",
    "sg:phone":"+49 3907/5652",
    "sg:postcode":"39638",
    "sg:province":"Sachsen-Anhalt",
    "wof:name":"Horst Kr\u00fcger",
    "wof:placetype":"venue"
},
  "geometry": {"coordinates":[11.36053,52.573959],"type":"Point"}
}