{
  "type": "Feature",
  "properties": {
    "iso:country":"DE",
    "sg:address":"Ahornallee 24",
    "sg:city":"Dummerstorf",
    "sg:phone":"+49 38208/61841",
    "sg:postcode":"18196",
    "sg:province":"Mecklenburg-Vorpommern",
    "wof:name":"Rathke & Paulus Gmbh",
    "wof:placetype":"venue"
},
  "geometry": {"coordinates":[12.2357053757,54.0112876892],"type":"Point"}
}