{
  "type": "Feature",
  "properties": {
    "iso:country":"DE",
    "sg:address":"Sieberstr. 2",
    "sg:city":"Herzberg",
    "sg:phone":"+49 5521/89620",
    "sg:postcode":"37412",
    "sg:province":"Niedersachsen",
    "wof:name":"Klaus Radke Rechtsanwalt",
    "wof:placetype":"venue"
},
  "geometry": {"coordinates":[10.3347511292,51.6558303833],"type":"Point"}
}