{
  "type": "Feature",
  "properties": {
    "iso:country":"DE",
    "sg:address":"Friedenstr. 14 a",
    "sg:city":"Pulheim",
    "sg:phone":"+49 2234/984360",
    "sg:postcode":"50259",
    "sg:province":"Nordrhein-Westfalen",
    "wof:name":"Studio Pro Gmbh",
    "wof:placetype":"venue"
},
  "geometry": {"coordinates":[6.7649059296,50.9596252441],"type":"Point"}
}