{
  "type": "Feature",
  "properties": {
    "iso:country":"DE",
    "sg:address":"Hauptstr. 158",
    "sg:city":"Becherbach",
    "sg:phone":"+49 6364/1302",
    "sg:postcode":"67827",
    "sg:province":"Rheinland-Pfalz",
    "wof:name":"Herbert Haage",
    "wof:placetype":"venue"
},
  "geometry": {"coordinates":[7.686466,49.65519],"type":"Point"}
}