{
  "type": "Feature",
  "properties": {
    "iso:country":"DE",
    "sg:address":"Grampersdorf 5",
    "sg:city":"Beilngries",
    "sg:phone":"+49 8466/94000",
    "sg:postcode":"92339",
    "sg:province":"Bayern",
    "wof:name":"A. Meier Steuerberater",
    "wof:placetype":"venue"
},
  "geometry": {"coordinates":[11.4744138718,49.0346984863],"type":"Point"}
}