{
  "type": "Feature",
  "properties": {
    "iso:country":"DE",
    "sg:address":"Potsdamer Str. 109a",
    "sg:city":"Ludwigsfelde",
    "sg:phone":"+49 3378/804945",
    "sg:postcode":"14974",
    "sg:province":"Brandenburg",
    "wof:name":"C. K\u00e4seberg",
    "wof:placetype":"venue"
},
  "geometry": {"coordinates":[13.2443933487,52.3093605042],"type":"Point"}
}