{
  "type": "Feature",
  "properties": {
    "iso:country":"DE",
    "sg:address":"Mommsenstr. 49",
    "sg:city":"K\u00f6ln",
    "sg:phone":"+49 221/434676",
    "sg:postcode":"50935",
    "sg:province":"Nordrhein-Westfalen",
    "wof:name":"K\u00f6ln-lindenthaler Wohnungsgenossenschaft Eg",
    "wof:placetype":"venue"
},
  "geometry": {"coordinates":[6.9065170288,50.9220733643],"type":"Point"}
}