{
  "type": "Feature",
  "properties": {
    "iso:country":"DE",
    "sg:address":"Niederkasseler Str. 14",
    "sg:city":"K\u00f6ln",
    "sg:phone":"+49 4922/0366316",
    "sg:postcode":"51147",
    "sg:province":"Nordrhein-Westfalen",
    "wof:name":"Richard Axmann Spritzgussfoemenbau Gmbh",
    "wof:placetype":"venue"
},
  "geometry": {"coordinates":[7.1043419838,50.8410949707],"type":"Point"}
}