{
  "type": "Feature",
  "properties": {
    "iso:country":"DE",
    "sg:address":"Felder Weg 5",
    "sg:city":"Leichlingen",
    "sg:phone":"+49 2174/792734",
    "sg:postcode":"42799",
    "sg:province":"Nordrhein-Westfalen",
    "wof:name":"Mpp Medizin & Pflegeb. E. K.",
    "wof:placetype":"venue"
},
  "geometry": {"coordinates":[7.11287117,51.1141204834],"type":"Point"}
}