{
  "type": "Feature",
  "properties": {
    "iso:country":"DE",
    "sg:address":"Schorlemerstr. 26",
    "sg:city":"Steinfurt",
    "sg:phone":"+49 2551/3252",
    "sg:postcode":"48565",
    "sg:province":"Nordrhein-Westfalen",
    "wof:name":"Horst Steinigewe Elektromeister",
    "wof:placetype":"venue"
},
  "geometry": {"coordinates":[7.331388,52.136505],"type":"Point"}
}