{
  "type": "Feature",
  "properties": {
    "iso:country":"DE",
    "sg:address":"Hauptstr. 91",
    "sg:city":"Heidelberg",
    "sg:phone":"+49 6221/20379",
    "sg:postcode":"69117",
    "sg:province":"Baden-W\u00fcrttemberg",
    "wof:name":"G\u00fcnter Lang Steuerberater",
    "wof:placetype":"venue"
},
  "geometry": {"coordinates":[8.7023897171,49.4112586975],"type":"Point"}
}