{
  "type": "Feature",
  "properties": {
    "iso:country":"DE",
    "sg:address":"Parkstr. 23",
    "sg:city":"Dahlen",
    "sg:phone":"+49 34361/51419",
    "sg:postcode":"04774",
    "sg:province":"Sachsen",
    "wof:name":"Annemarie Opitz",
    "wof:placetype":"venue"
},
  "geometry": {"coordinates":[13.005242,51.363461],"type":"Point"}
}