{
  "type": "Feature",
  "properties": {
    "iso:country":"DE",
    "sg:address":"Hauptstr. 8",
    "sg:city":"Kelheim",
    "sg:phone":"+49 9441/8584",
    "sg:postcode":"93309",
    "sg:province":"Bayern",
    "wof:name":"Georg Merkel",
    "wof:placetype":"venue"
},
  "geometry": {"coordinates":[11.888958,48.878998],"type":"Point"}
}