{
  "type": "Feature",
  "properties": {
    "iso:country":"DE",
    "sg:address":"D\u00fcsseldorfer Str. 204",
    "sg:city":"M\u00fclheim",
    "sg:phone":"+49 208/487106",
    "sg:postcode":"45481",
    "sg:province":"Nordrhein-Westfalen",
    "wof:name":"Gam Gesellschaft F\u00fcr Anlagen- Maschinenbau Und Service Mbh",
    "wof:placetype":"venue"
},
  "geometry": {"coordinates":[6.86863,51.413029],"type":"Point"}
}