{
  "type": "Feature",
  "properties": {
    "iso:country":"DE",
    "sg:address":"Stettiner Str. 100",
    "sg:city":"Hattersheim",
    "sg:phone":"+49 6190/3609",
    "sg:postcode":"65795",
    "sg:province":"Hessen",
    "wof:name":"Kurt Walderbach",
    "wof:placetype":"venue"
},
  "geometry": {"coordinates":[8.488699913,50.0495529175],"type":"Point"}
}