{
  "type": "Feature",
  "properties": {
    "iso:country":"DE",
    "sg:address":"Obertraubenbach 26",
    "sg:city":"Schorndorf",
    "sg:postcode":"93489",
    "sg:province":"Bayern",
    "wof:name":"Brennereigenossenschaft Obertraubenbach Eg",
    "wof:placetype":"venue"
},
  "geometry": {"coordinates":[12.575206,49.196468],"type":"Point"}
}