{
  "type": "Feature",
  "properties": {
    "iso:country":"DE",
    "sg:address":"Zum Bauhof 11",
    "sg:city":"Weyhe",
    "sg:phone":"+49 4203/6143",
    "sg:postcode":"28844",
    "sg:province":"Niedersachsen",
    "wof:name":"H. Meyer",
    "wof:placetype":"venue"
},
  "geometry": {"coordinates":[8.858465,52.995449],"type":"Point"}
}