{
  "type": "Feature",
  "properties": {
    "iso:country":"DE",
    "sg:address":"Schwaigfurt",
    "sg:city":"Bad Schussenried",
    "sg:phone":"+49 7525/8368",
    "sg:postcode":"88427",
    "sg:province":"Baden-W\u00fcrttemberg",
    "wof:name":"Weiher",
    "wof:placetype":"venue"
},
  "geometry": {"coordinates":[9.6621551514,47.9799156189],"type":"Point"}
}