{
  "type": "Feature",
  "properties": {
    "iso:country":"DE",
    "sg:address":"Mariannenstr. 93",
    "sg:city":"Krefeld",
    "sg:postcode":"47799",
    "sg:province":"Nordrhein-Westfalen",
    "wof:name":"Axel Molls E. K.",
    "wof:placetype":"venue"
},
  "geometry": {"coordinates":[6.5700740814,51.3321037292],"type":"Point"}
}