{
  "type": "Feature",
  "properties": {
    "iso:country":"DE",
    "sg:address":"Garmischer Str. 4",
    "sg:city":"M\u00fcnchen",
    "sg:postcode":"80339",
    "sg:province":"Bayern",
    "wof:name":"Jfw Management Consulting Und Beteiligungs- Gmbh",
    "wof:placetype":"venue"
},
  "geometry": {"coordinates":[11.5328540802,48.1332740784],"type":"Point"}
}