{
  "type": "Feature",
  "properties": {
    "iso:country":"DE",
    "sg:address":"Hauptstr. 325",
    "sg:city":"K\u00f6ln",
    "sg:phone":"+49 2203/57040",
    "sg:postcode":"51143",
    "sg:province":"Nordrhein-Westfalen",
    "wof:name":"Verlag Wochenspiegel Porz Eppst\u00e4dt & Co. Kg",
    "wof:placetype":"venue"
},
  "geometry": {"coordinates":[7.0553798676,50.881603241],"type":"Point"}
}