{
  "type": "Feature",
  "properties": {
    "iso:country":"DE",
    "sg:address":"Am Rabenhufen 5",
    "sg:city":"Wesel",
    "sg:phone":"+49 281/963216",
    "sg:postcode":"46487",
    "sg:province":"Nordrhein-Westfalen",
    "wof:name":"Hermann Buchmann",
    "wof:placetype":"venue"
},
  "geometry": {"coordinates":[6.6122078896,51.6884536743],"type":"Point"}
}