{
  "type": "Feature",
  "properties": {
    "iso:country":"DE",
    "sg:address":"Ostertor 8 A",
    "sg:city":"Hildesheim",
    "sg:phone":"+49 5121/33645",
    "sg:postcode":"31134",
    "sg:province":"Niedersachsen",
    "wof:name":"Niemann",
    "wof:placetype":"venue"
},
  "geometry": {"coordinates":[9.9567871094,52.1545143127],"type":"Point"}
}