{
  "type": "Feature",
  "properties": {
    "iso:country":"DE",
    "sg:address":"Siebweg 69",
    "sg:city":"Berlin",
    "sg:phone":"+49 30/60084777",
    "sg:postcode":"12526",
    "sg:province":"Berlin",
    "wof:name":"Dege Dienstleistungs- Und Beteiligungsgesellschaft Mbh",
    "wof:placetype":"venue"
},
  "geometry": {"coordinates":[13.5636205673,52.3988037109],"type":"Point"}
}