{
  "type": "Feature",
  "properties": {
    "iso:country":"DE",
    "sg:address":"Hochstadenstr. 63",
    "sg:city":"M\u00f6nchengladbach",
    "sg:postcode":"41189",
    "sg:province":"Nordrhein-Westfalen",
    "wof:name":"Wo Schmeckt\u00b4s Ihr Restaurant Fuehrer",
    "wof:placetype":"venue"
},
  "geometry": {"coordinates":[6.420409,51.131893],"type":"Point"}
}