{
  "type": "Feature",
  "properties": {
    "iso:country":"DE",
    "sg:address":"Marktplatz 9",
    "sg:city":"Ulm",
    "sg:phone":"+49 731/1614300",
    "sg:postcode":"89073",
    "sg:province":"Baden-W\u00fcrttemberg",
    "wof:name":"Ulmer Museum Und Pr\u00e4histo- Rische Sammlungen Im Ulmer",
    "wof:placetype":"venue"
},
  "geometry": {"coordinates":[9.994605,48.396828],"type":"Point"}
}