{
  "type": "Feature",
  "properties": {
    "iso:country":"DE",
    "sg:address":"Dorfstr. 35",
    "sg:city":"Audenhain",
    "sg:phone":"+49 34244/50922",
    "sg:postcode":"04838",
    "sg:province":"Sachsen",
    "wof:name":"S. Steineck",
    "wof:placetype":"venue"
},
  "geometry": {"coordinates":[12.626225,51.493671],"type":"Point"}
}