{
  "type": "Feature",
  "properties": {
    "iso:country":"DE",
    "sg:address":"Am Schrickenhof 3",
    "sg:city":"J\u00fclich",
    "sg:phone":"+49 2461/2451",
    "sg:postcode":"52428",
    "sg:province":"Nordrhein-Westfalen",
    "wof:name":"Kath. Pfarramt Gem. Kirchberg",
    "wof:placetype":"venue"
},
  "geometry": {"coordinates":[6.3508181572,50.8968200684],"type":"Point"}
}