{
  "type": "Feature",
  "properties": {
    "iso:country":"DE",
    "sg:address":"Uelzener Weg 20",
    "sg:city":"Unna",
    "sg:phone":"+49 2303/13540",
    "sg:postcode":"59425",
    "sg:province":"Nordrhein-Westfalen",
    "wof:name":"L. Jaeger Gmbh",
    "wof:placetype":"venue"
},
  "geometry": {"coordinates":[7.702306,51.539062],"type":"Point"}
}