{
  "type": "Feature",
  "properties": {
    "iso:country":"DE",
    "sg:address":"Schwarzenbergstr. 40",
    "sg:city":"Hamburg",
    "sg:phone":"+49 40/7655801",
    "sg:postcode":"21073",
    "sg:province":"Hamburg",
    "wof:name":"Martina Schimanski",
    "wof:placetype":"venue"
},
  "geometry": {"coordinates":[9.9755277634,53.4621276855],"type":"Point"}
}