{
  "type": "Feature",
  "properties": {
    "iso:country":"DE",
    "sg:address":"Schillerstr. 12",
    "sg:city":"Lorch",
    "sg:phone":"+49 7172/5407",
    "sg:postcode":"73547",
    "sg:province":"Baden-W\u00fcrttemberg",
    "wof:name":"Rudi Renz",
    "wof:placetype":"venue"
},
  "geometry": {"coordinates":[9.693096,48.796467],"type":"Point"}
}