{
  "type": "Feature",
  "properties": {
    "iso:country":"DE",
    "sg:address":"Untere Hauptstr. 90",
    "sg:city":"Hartmannsdorf",
    "sg:phone":"+49 3722/93712",
    "sg:postcode":"09232",
    "sg:province":"Sachsen",
    "wof:name":"D. M\u00e4dger",
    "wof:placetype":"venue"
},
  "geometry": {"coordinates":[12.799463,50.887173],"type":"Point"}
}