{
  "type": "Feature",
  "properties": {
    "iso:country":"DE",
    "sg:address":"Rothenb\u00e4chlestr. 1",
    "sg:city":"Murg",
    "sg:phone":"+49 7763/91402",
    "sg:postcode":"79730",
    "sg:province":"Baden-W\u00fcrttemberg",
    "wof:name":"Ristorante Pizz. Mediterraneo Familie D Elia",
    "wof:placetype":"venue"
},
  "geometry": {"coordinates":[8.0130844116,47.5551757812],"type":"Point"}
}