{
  "type": "Feature",
  "properties": {
    "iso:country":"DE",
    "sg:address":"Zeile 9",
    "sg:city":"Trusetal",
    "sg:phone":"+49 36840/80380",
    "sg:postcode":"98596",
    "sg:province":"Th\u00fcringen",
    "wof:name":"A. K\u00fchn Anlageberater",
    "wof:placetype":"venue"
},
  "geometry": {"coordinates":[10.3994970322,50.7795028687],"type":"Point"}
}