{
  "type": "Feature",
  "properties": {
    "iso:country":"DE",
    "sg:address":"H\u00fcttenweg 421",
    "sg:city":"Warmensteinach",
    "sg:phone":"+49 9277/474",
    "sg:postcode":"95485",
    "sg:province":"Bayern",
    "wof:name":"Haus W. Brix",
    "wof:placetype":"venue"
},
  "geometry": {"coordinates":[11.773182869,49.9864311218],"type":"Point"}
}