{
  "type": "Feature",
  "properties": {
    "iso:country":"DE",
    "sg:address":"Altenberger Str. 6",
    "sg:city":"M\u00fcnster",
    "sg:phone":"+49 2533/1251",
    "sg:postcode":"48161",
    "sg:province":"Nordrhein-Westfalen",
    "wof:name":"Keller & Deutsch Gmbh",
    "wof:placetype":"venue"
},
  "geometry": {"coordinates":[7.563399,51.997589],"type":"Point"}
}