{
  "type": "Feature",
  "properties": {
    "iso:country":"DE",
    "sg:address":"Weidenstr. 28",
    "sg:city":"Solingen",
    "sg:phone":"+49 212/222690",
    "sg:postcode":"42655",
    "sg:province":"Nordrhein-Westfalen",
    "wof:name":"R\u00f6hrig Galvanozubeh\u00f6r Solingen Gmbh",
    "wof:placetype":"venue"
},
  "geometry": {"coordinates":[7.066939,51.179272],"type":"Point"}
}