{
  "type": "Feature",
  "properties": {
    "iso:country":"DE",
    "sg:address":"Schwabenstr. 22",
    "sg:city":"Ravensburg",
    "sg:phone":"+49 751/64089",
    "sg:postcode":"88214",
    "sg:province":"Baden-W\u00fcrttemberg",
    "wof:name":"Margret Willburger",
    "wof:placetype":"venue"
},
  "geometry": {"coordinates":[9.5962314606,47.7662658691],"type":"Point"}
}