{
  "type": "Feature",
  "properties": {
    "iso:country":"DE",
    "sg:address":"G\u00f6dringer Str. 16",
    "sg:city":"Sarstedt",
    "sg:phone":"+49 5066/65017",
    "sg:postcode":"31157",
    "sg:province":"Niedersachsen",
    "wof:name":"Eisenwerk B\u00fchrlein & Peters Gbr",
    "wof:placetype":"venue"
},
  "geometry": {"coordinates":[9.898054,52.241962],"type":"Point"}
}