{
  "type": "Feature",
  "properties": {
    "iso:country":"DE",
    "sg:address":"Max-Planck-Str. 8",
    "sg:city":"R\u00f6dermark",
    "sg:phone":"+49 6074/97434",
    "sg:postcode":"63322",
    "sg:province":"Hessen",
    "wof:name":"Kmb Kessler & Partner Gmbh",
    "wof:placetype":"venue"
},
  "geometry": {"coordinates":[8.8240222931,49.9690933228],"type":"Point"}
}