{
  "type": "Feature",
  "properties": {
    "iso:country":"DE",
    "sg:address":"Chausseestr. 18",
    "sg:city":"Linthe",
    "sg:phone":"+49 33844/51143",
    "sg:postcode":"14822",
    "sg:province":"Brandenburg",
    "wof:name":"Schr\u00f6ter Bau Gmbh",
    "wof:placetype":"venue"
},
  "geometry": {"coordinates":[12.78612,52.15472],"type":"Point"}
}