{
  "type": "Feature",
  "properties": {
    "iso:country":"DE",
    "sg:address":"N\u00fcrnberger Str. 163",
    "sg:city":"Bamberg",
    "sg:phone":"+49 951/9180300",
    "sg:postcode":"96050",
    "sg:province":"Bayern",
    "wof:name":"Aral Tankstelle",
    "wof:placetype":"venue"
},
  "geometry": {"coordinates":[10.9111604691,49.8903236389],"type":"Point"}
}