{
  "type": "Feature",
  "properties": {
    "iso:country":"DE",
    "sg:address":"Projensdorfer Str. 173",
    "sg:city":"Kiel",
    "sg:phone":"+49 431/333928",
    "sg:postcode":"24106",
    "sg:province":"Schleswig-Holstein",
    "wof:name":"Richard Ranz",
    "wof:placetype":"venue"
},
  "geometry": {"coordinates":[10.107484,54.363483],"type":"Point"}
}