{
  "type": "Feature",
  "properties": {
    "iso:country":"DE",
    "sg:address":"Marburger Str. 19",
    "sg:city":"Kreuztal",
    "sg:phone":"+49 2732/21645",
    "sg:postcode":"57223",
    "sg:province":"Nordrhein-Westfalen",
    "wof:name":"Gerd Vogels",
    "wof:placetype":"venue"
},
  "geometry": {"coordinates":[7.9914798737,50.9603118896],"type":"Point"}
}