{
  "type": "Feature",
  "properties": {
    "iso:country":"DE",
    "sg:address":"Karlstr. 2",
    "sg:city":"Rheinfelden",
    "sg:phone":"+49 7623/20099",
    "sg:postcode":"79618",
    "sg:province":"Baden-W\u00fcrttemberg",
    "wof:name":"L. M. Rodriguez",
    "wof:placetype":"venue"
},
  "geometry": {"coordinates":[7.787667,47.560387],"type":"Point"}
}