{
  "type": "Feature",
  "properties": {
    "iso:country":"DE",
    "sg:address":"Trecknase 10",
    "sg:city":"Remscheid",
    "sg:postcode":"42897",
    "sg:province":"Nordrhein-Westfalen",
    "wof:name":"Axel Felder Verwaltungs- Gmbh",
    "wof:placetype":"venue"
},
  "geometry": {"coordinates":[7.250865,51.180977],"type":"Point"}
}