{
  "type": "Feature",
  "properties": {
    "iso:country":"DE",
    "sg:address":"An der Untertrave 1",
    "sg:city":"L\u00fcbeck",
    "sg:phone":"+49 451/794928",
    "sg:postcode":"23552",
    "sg:province":"Schleswig-Holstein",
    "wof:name":"Segelzentrale L\u00fcbeck Inh. Gabriele Ullrich",
    "wof:placetype":"venue"
},
  "geometry": {"coordinates":[10.6902513504,53.8743896484],"type":"Point"}
}