{
  "type": "Feature",
  "properties": {
    "iso:country":"DE",
    "sg:address":"Hessinghook 28",
    "sg:city":"S\u00fcdlohn",
    "sg:phone":"+49 2862/6172",
    "sg:postcode":"46354",
    "sg:province":"Nordrhein-Westfalen",
    "wof:name":"Hermann Picker",
    "wof:placetype":"venue"
},
  "geometry": {"coordinates":[6.823652,51.957134],"type":"Point"}
}