{
  "type": "Feature",
  "properties": {
    "iso:country":"DE",
    "sg:address":"Euskirchener Str. 88",
    "sg:city":"Br\u00fchl",
    "sg:phone":"+49 2232/33170",
    "sg:postcode":"50321",
    "sg:province":"Nordrhein-Westfalen",
    "wof:name":"Josef Leyendecker Elektroinstallation",
    "wof:placetype":"venue"
},
  "geometry": {"coordinates":[6.888822,50.814774],"type":"Point"}
}