{
  "type": "Feature",
  "properties": {
    "iso:country":"DE",
    "sg:address":"Windausstr. 14",
    "sg:city":"Freiburg",
    "sg:phone":"+49 761/80410",
    "sg:postcode":"79110",
    "sg:province":"Baden-W\u00fcrttemberg",
    "wof:name":"Dr. Med. Udo Kruschke",
    "wof:placetype":"venue"
},
  "geometry": {"coordinates":[7.8104290962,48.0148506165],"type":"Point"}
}