{
  "type": "Feature",
  "properties": {
    "iso:country":"DE",
    "sg:address":"Auf der Sandkaule 14",
    "sg:city":"Hennef",
    "sg:phone":"+49 2248/2564",
    "sg:postcode":"53773",
    "sg:province":"Nordrhein-Westfalen",
    "wof:name":"Josef Wissmann",
    "wof:placetype":"venue"
},
  "geometry": {"coordinates":[7.384252,50.746777],"type":"Point"}
}