{
  "type": "Feature",
  "properties": {
    "iso:country":"DE",
    "sg:address":"Lindenstr. 62",
    "sg:city":"Itzehoe",
    "sg:phone":"+49 4821/73810",
    "sg:postcode":"25524",
    "sg:province":"Schleswig-Holstein",
    "wof:name":"Erich Haagen Inh. Inge Fischer-haagen",
    "wof:placetype":"venue"
},
  "geometry": {"coordinates":[9.506811,53.931351],"type":"Point"}
}