{
  "type": "Feature",
  "properties": {
    "iso:country":"DE",
    "sg:address":"Paul-Gruner-Str. 62",
    "sg:city":"Leipzig",
    "sg:phone":"+49 341/9603410",
    "sg:postcode":"04107",
    "sg:province":"Sachsen",
    "wof:name":"Upc-united Programm Consulting Ges. F. Planung Koordinierung",
    "wof:placetype":"venue"
},
  "geometry": {"coordinates":[12.3699960709,51.3291702271],"type":"Point"}
}