{
  "type": "Feature",
  "properties": {
    "iso:country":"DE",
    "sg:address":"Trift 15",
    "sg:city":"H\u00f6velhof",
    "sg:phone":"+49 5271/35890",
    "sg:postcode":"33161",
    "sg:province":"Nordrhein-Westfalen",
    "wof:name":"G. Fricke",
    "wof:placetype":"venue"
},
  "geometry": {"coordinates":[8.6777191162,51.8302650452],"type":"Point"}
}