{
  "type": "Feature",
  "properties": {
    "iso:country":"DE",
    "sg:address":"RosenhoferStr.8",
    "sg:city":"Sarching",
    "sg:phone":"+49 9403/969722",
    "sg:postcode":"93092",
    "sg:province":"Bayern",
    "wof:name":"Weltweit Erfolgreich Bei Den Goldenen Zeiten",
    "wof:placetype":"venue"
},
  "geometry": {"coordinates":[12.234116,49.013863],"type":"Point"}
}