{
  "type": "Feature",
  "properties": {
    "iso:country":"DE",
    "sg:address":"Im Stroth 1",
    "sg:city":"Herzebrock-Clarholz",
    "sg:phone":"+49 5245/6488",
    "sg:postcode":"33442",
    "sg:province":"Nordrhein-Westfalen",
    "wof:name":"Heinz D. Vogel Steuerberater",
    "wof:placetype":"venue"
},
  "geometry": {"coordinates":[8.1996803284,51.9129219055],"type":"Point"}
}