{
  "type": "Feature",
  "properties": {
    "iso:country":"DE",
    "sg:address":"F\u00fcrstenstr. 16",
    "sg:city":"Reichenbach",
    "sg:phone":"+49 7153/58335",
    "sg:postcode":"73262",
    "sg:province":"Baden-W\u00fcrttemberg",
    "wof:name":"W. Lepp",
    "wof:placetype":"venue"
},
  "geometry": {"coordinates":[9.461186,48.710144],"type":"Point"}
}