{
  "type": "Feature",
  "properties": {
    "iso:country":"DE",
    "sg:address":"Ibbenb\u00fcrener Str. 4",
    "sg:city":"H\u00f6rstel",
    "sg:phone":"+49 5459/4110",
    "sg:postcode":"48477",
    "sg:province":"Nordrhein-Westfalen",
    "wof:name":"Wolf",
    "wof:placetype":"venue"
},
  "geometry": {"coordinates":[7.5893368721,52.3002548218],"type":"Point"}
}