{
  "type": "Feature",
  "properties": {
    "iso:country":"DE",
    "sg:address":"Kraftwerkstr. 26",
    "sg:city":"Spremberg",
    "sg:phone":"+49 3563/93691",
    "sg:postcode":"03130",
    "sg:province":"Brandenburg",
    "wof:name":"Bernhard Schumann",
    "wof:placetype":"venue"
},
  "geometry": {"coordinates":[14.381863,51.551907],"type":"Point"}
}