{
  "type": "Feature",
  "properties": {
    "iso:country":"DE",
    "sg:address":"Hessenstr. 126",
    "sg:city":"W\u00fcrzburg",
    "sg:phone":"+49 931/25328",
    "sg:postcode":"97078",
    "sg:province":"Bayern",
    "wof:name":"Prof. Wolfram Schauberger Ingenieur",
    "wof:placetype":"venue"
},
  "geometry": {"coordinates":[9.9720020294,49.8124427795],"type":"Point"}
}