{
  "type": "Feature",
  "properties": {
    "iso:country":"DE",
    "sg:address":"Rheiner Str. 55",
    "sg:city":"Lingen",
    "sg:postcode":"49809",
    "sg:province":"Niedersachsen",
    "wof:name":"Gebr. Jansen Grundst\u00fccks- Und Verwaltungsges. Mbh",
    "wof:placetype":"venue"
},
  "geometry": {"coordinates":[7.3181400299,52.5122146606],"type":"Point"}
}