{
  "type": "Feature",
  "properties": {
    "iso:country":"DE",
    "sg:address":"Kaiserswerther Str. 22",
    "sg:city":"D\u00fcsseldorf",
    "sg:phone":"+49 211/49680",
    "sg:postcode":"40477",
    "sg:province":"Nordrhein-Westfalen",
    "wof:name":"Minmetals Germany Gmbh",
    "wof:placetype":"venue"
},
  "geometry": {"coordinates":[6.77795,51.238415],"type":"Point"}
}