{
  "type": "Feature",
  "properties": {
    "iso:country":"DE",
    "sg:address":"M\u00fcnchener Str. 20 b",
    "sg:city":"Pfaffenhofen",
    "sg:phone":"+49 8441/6811",
    "sg:postcode":"85276",
    "sg:province":"Bayern",
    "wof:name":"Mandala Naturkost",
    "wof:placetype":"venue"
},
  "geometry": {"coordinates":[11.510294,48.527607],"type":"Point"}
}