{
  "type": "Feature",
  "properties": {
    "iso:country":"DE",
    "sg:address":"H\u00e4ngebank 8",
    "sg:city":"Essen",
    "sg:phone":"+49 201/592071",
    "sg:postcode":"45307",
    "sg:province":"Nordrhein-Westfalen",
    "wof:name":"H\u00fcck & Design Gmbh",
    "wof:placetype":"venue"
},
  "geometry": {"coordinates":[7.070909,51.460278],"type":"Point"}
}