{
  "type": "Feature",
  "properties": {
    "iso:country":"DE",
    "sg:address":"Schilfufer 121",
    "sg:city":"Salzgitter",
    "sg:phone":"+49 5341/51151",
    "sg:postcode":"38228",
    "sg:province":"Niedersachsen",
    "wof:name":"Guido L\u00f6cke Ingenieur",
    "wof:placetype":"venue"
},
  "geometry": {"coordinates":[10.296378,52.148987],"type":"Point"}
}