{
  "type": "Feature",
  "properties": {
    "iso:country":"DE",
    "sg:address":"R\u00f6ttgener Str. 217",
    "sg:city":"Bonn",
    "sg:phone":"+49 228/9181727",
    "sg:postcode":"53125",
    "sg:province":"Nordrhein-Westfalen",
    "wof:name":"Rainer Bendowski",
    "wof:placetype":"venue"
},
  "geometry": {"coordinates":[7.0777211189,50.6854057312],"type":"Point"}
}