{
  "type": "Feature",
  "properties": {
    "iso:country":"DE",
    "sg:address":"Am Getreidespeicher 26",
    "sg:city":"Rheinbach",
    "sg:phone":"+49 2226/908077",
    "sg:postcode":"53359",
    "sg:province":"Nordrhein-Westfalen",
    "wof:name":"Atmosphaere Wohnen Mit Flair Jutta Claushues E. K.",
    "wof:placetype":"venue"
},
  "geometry": {"coordinates":[6.9482998848,50.6289405823],"type":"Point"}
}