{
  "type": "Feature",
  "properties": {
    "iso:country":"DE",
    "sg:address":"Fischseestr.",
    "sg:city":"Schwandorf",
    "sg:phone":"+49 9431/55691",
    "sg:postcode":"92421",
    "sg:province":"Bayern",
    "wof:name":"H. Donhauser",
    "wof:placetype":"venue"
},
  "geometry": {"coordinates":[12.107225,49.321075],"type":"Point"}
}