{
  "type": "Feature",
  "properties": {
    "iso:country":"DE",
    "sg:address":"Tanzstr. 26",
    "sg:city":"Edenkoben",
    "sg:phone":"+49 6323/6899",
    "sg:postcode":"67480",
    "sg:province":"Rheinland-Pfalz",
    "wof:name":"G. Grosse",
    "wof:placetype":"venue"
},
  "geometry": {"coordinates":[8.1269073486,49.2799186707],"type":"Point"}
}