{
  "type": "Feature",
  "properties": {
    "iso:country":"DE",
    "sg:address":"Theodor-Heuss-Str. 21",
    "sg:city":"Weinstadt",
    "sg:phone":"+49 7151/906026",
    "sg:postcode":"71384",
    "sg:province":"Baden-W\u00fcrttemberg",
    "wof:name":"W. Wagner Gmbh",
    "wof:placetype":"venue"
},
  "geometry": {"coordinates":[9.3675317764,48.8099517822],"type":"Point"}
}