{
  "type": "Feature",
  "properties": {
    "iso:country":"DE",
    "sg:address":"Am Max-Klemens-Kanal 143b",
    "sg:city":"M\u00fcnster",
    "sg:phone":"+49 251/211640",
    "sg:postcode":"48159",
    "sg:province":"Nordrhein-Westfalen",
    "wof:name":"H. Weber-dahlmann",
    "wof:placetype":"venue"
},
  "geometry": {"coordinates":[7.6031498909,52.0175056458],"type":"Point"}
}