{
  "type": "Feature",
  "properties": {
    "iso:country":"DE",
    "sg:address":"Bergheimer Str. 26",
    "sg:city":"Grevenbroich",
    "sg:phone":"+49 2181/3910",
    "sg:postcode":"41515",
    "sg:province":"Nordrhein-Westfalen",
    "wof:name":"Schr\u00f6ter & Lausen Handelsgesellschaft",
    "wof:placetype":"venue"
},
  "geometry": {"coordinates":[6.58083,51.088974],"type":"Point"}
}