{
  "type": "Feature",
  "properties": {
    "iso:country":"DE",
    "sg:address":"Gro\u00dfe Str. 41",
    "sg:city":"Wittenburg",
    "sg:phone":"+49 38852/50313",
    "sg:postcode":"19243",
    "sg:province":"Mecklenburg-Vorpommern",
    "wof:name":"G. Lenz",
    "wof:placetype":"venue"
},
  "geometry": {"coordinates":[11.073277,53.511898],"type":"Point"}
}