{
  "type": "Feature",
  "properties": {
    "iso:country":"DE",
    "sg:address":"Bahnhofstr. 38",
    "sg:city":"M\u00f6ssingen",
    "sg:phone":"+49 7473/1373",
    "sg:postcode":"72116",
    "sg:province":"Baden-W\u00fcrttemberg",
    "wof:name":"Movie Plus",
    "wof:placetype":"venue"
},
  "geometry": {"coordinates":[9.0508403778,48.4066543579],"type":"Point"}
}