{
  "type": "Feature",
  "properties": {
    "iso:country":"DE",
    "sg:address":"Alter M\u00fcnsterweg 75",
    "sg:city":"Ahlen",
    "sg:phone":"+49 2528/8505",
    "sg:postcode":"59227",
    "sg:province":"Nordrhein-Westfalen",
    "wof:name":"Wilhelm Wienker Ingenieur",
    "wof:placetype":"venue"
},
  "geometry": {"coordinates":[7.9271302223,51.8043212891],"type":"Point"}
}