{
  "type": "Feature",
  "properties": {
    "iso:country":"DE",
    "sg:address":"Im Runnenwieschen 3",
    "sg:city":"Gerolstein",
    "sg:phone":"+49 6591/628",
    "sg:postcode":"54568",
    "sg:province":"Rheinland-Pfalz",
    "wof:name":"Bongartz Gmbh",
    "wof:placetype":"venue"
},
  "geometry": {"coordinates":[6.658362,50.217075],"type":"Point"}
}