{
  "type": "Feature",
  "properties": {
    "iso:country":"DE",
    "sg:address":"Industriepark 14",
    "sg:city":"Osterburken",
    "sg:phone":"+49 6291/416160",
    "sg:postcode":"74706",
    "sg:province":"Baden-W\u00fcrttemberg",
    "wof:name":"Reichmann Gmbh",
    "wof:placetype":"venue"
},
  "geometry": {"coordinates":[9.4470663071,49.4211997986],"type":"Point"}
}