{
  "type": "Feature",
  "properties": {
    "iso:country":"DE",
    "sg:address":"Fraunhoferstr. 10",
    "sg:city":"L\u00fcbeck",
    "sg:phone":"+49 451/602656",
    "sg:postcode":"23566",
    "sg:province":"Schleswig-Holstein",
    "wof:name":"Walter Thomsen Ingenieur",
    "wof:placetype":"venue"
},
  "geometry": {"coordinates":[10.7394571304,53.8582992554],"type":"Point"}
}