{
  "type": "Feature",
  "properties": {
    "iso:country":"DE",
    "sg:address":"F\u00fcrstenbergstr. 16",
    "sg:city":"Bad Rippoldsau-Schapbach",
    "sg:phone":"+49 7440/913143",
    "sg:postcode":"77776",
    "sg:province":"Baden-W\u00fcrttemberg",
    "wof:name":"Bruno Leuthner",
    "wof:placetype":"venue"
},
  "geometry": {"coordinates":[8.315377,48.437469],"type":"Point"}
}