{
  "type": "Feature",
  "properties": {
    "iso:country":"DE",
    "sg:address":"Am Sch\u00fcrmannsh\u00fctt 6",
    "sg:city":"Moers",
    "sg:phone":"+49 2841/25209",
    "sg:postcode":"47441",
    "sg:province":"Nordrhein-Westfalen",
    "wof:name":"Rheinisch-westf\u00e4lischer T\u00dcv Fahrzeug Gmbh",
    "wof:placetype":"venue"
},
  "geometry": {"coordinates":[6.6104550362,51.4527587891],"type":"Point"}
}