{
  "type": "Feature",
  "properties": {
    "iso:country":"DE",
    "sg:address":"Burgstr. 3",
    "sg:city":"Ense",
    "sg:phone":"+49 2938/565",
    "sg:postcode":"59469",
    "sg:province":"Nordrhein-Westfalen",
    "wof:name":"Bernhard Dierkes",
    "wof:placetype":"venue"
},
  "geometry": {"coordinates":[7.971081,51.483536],"type":"Point"}
}