{
  "type": "Feature",
  "properties": {
    "iso:country":"DE",
    "sg:address":"Brettener Str. 39",
    "sg:city":"Eppingen",
    "sg:phone":"+49 7262/5664",
    "sg:postcode":"75031",
    "sg:province":"Baden-W\u00fcrttemberg",
    "wof:name":"Hersa-mode-filialen-gmbh",
    "wof:placetype":"venue"
},
  "geometry": {"coordinates":[8.90759,49.135925],"type":"Point"}
}