{
  "type": "Feature",
  "properties": {
    "iso:country":"DE",
    "sg:address":"Rathausstr. 13",
    "sg:city":"Windeck",
    "sg:phone":"+49 2292/5151",
    "sg:postcode":"51570",
    "sg:province":"Nordrhein-Westfalen",
    "wof:name":"Hotel-restaurant Zur Post",
    "wof:placetype":"venue"
},
  "geometry": {"coordinates":[7.6109352112,50.7965202332],"type":"Point"}
}