{
  "type": "Feature",
  "properties": {
    "iso:country":"DE",
    "sg:address":"Robert-Bosch-Str. 8",
    "sg:city":"Radevormwald",
    "sg:phone":"+49 2195/91860",
    "sg:postcode":"42477",
    "sg:province":"Nordrhein-Westfalen",
    "wof:name":"Paroll Doppelboden-systeme Gmbh & Co. Kg",
    "wof:placetype":"venue"
},
  "geometry": {"coordinates":[7.38377,51.201008],"type":"Point"}
}