{
  "type": "Feature",
  "properties": {
    "iso:country":"DE",
    "sg:address":"Laufamholzstr. 4",
    "sg:city":"N\u00fcrnberg",
    "sg:phone":"+49 911/547675",
    "sg:postcode":"90482",
    "sg:province":"Bayern",
    "wof:name":"Picobello",
    "wof:placetype":"venue"
},
  "geometry": {"coordinates":[11.132349,49.461185],"type":"Point"}
}