{
  "type": "Feature",
  "properties": {
    "iso:country":"DE",
    "sg:address":"Bahnhofsplatz 1",
    "sg:city":"Wilhelmshaven",
    "sg:phone":"+49 4421",
    "sg:postcode":"26382",
    "sg:province":"Niedersachsen",
    "wof:name":"Gedankenflieger - Alle B\u00fccher Dieser Welt!",
    "wof:placetype":"venue"
},
  "geometry": {"coordinates":[8.1180429459,53.5166168213],"type":"Point"}
}