{
  "type": "Feature",
  "properties": {
    "iso:country":"DE",
    "sg:address":"Prinz-Eugen-Str. 18",
    "sg:city":"Blaustein",
    "sg:phone":"+49 7304/2379",
    "sg:postcode":"89134",
    "sg:province":"Baden-W\u00fcrttemberg",
    "wof:name":"Ev. Pfarramt",
    "wof:placetype":"venue"
},
  "geometry": {"coordinates":[9.862953186,48.4284362793],"type":"Point"}
}