{
  "type": "Feature",
  "properties": {
    "iso:country":"DE",
    "sg:address":"Bruderhofstr. 29",
    "sg:city":"M\u00fcnchen",
    "sg:phone":"+49 89/7233713",
    "sg:postcode":"81371",
    "sg:province":"Bayern",
    "wof:name":"Wilhelm Liebl",
    "wof:placetype":"venue"
},
  "geometry": {"coordinates":[11.5505247116,48.1100158691],"type":"Point"}
}