{
  "type": "Feature",
  "properties": {
    "iso:country":"DE",
    "sg:address":"Luruper Weg 15",
    "sg:city":"Halstenbek",
    "sg:postcode":"25469",
    "sg:province":"Schleswig-Holstein",
    "wof:name":"Lunei Elektrotechnik Mbh",
    "wof:placetype":"venue"
},
  "geometry": {"coordinates":[9.838627,53.625057],"type":"Point"}
}