{
  "type": "Feature",
  "properties": {
    "iso:country":"DE",
    "sg:address":"Adolph-Roemer-Str. 2 a",
    "sg:city":"Clausthal-Zellerfeld",
    "sg:phone":"+49 5323/722246",
    "sg:postcode":"38678",
    "sg:province":"Niedersachsen",
    "wof:name":"Institut F\u00fcr Wirtschaftswissenschaft",
    "wof:placetype":"venue"
},
  "geometry": {"coordinates":[10.334071,51.804741],"type":"Point"}
}