{
  "type": "Feature",
  "properties": {
    "iso:country":"DE",
    "sg:address":"Friedrichstr. 10",
    "sg:city":"Bad S\u00e4ckingen",
    "sg:phone":"+49 7761/59590",
    "sg:postcode":"79713",
    "sg:province":"Baden-W\u00fcrttemberg",
    "wof:name":"Juve",
    "wof:placetype":"venue"
},
  "geometry": {"coordinates":[7.940153,47.554508],"type":"Point"}
}