{
  "type": "Feature",
  "properties": {
    "iso:country":"DE",
    "sg:address":"Am Jacobsberg 6",
    "sg:city":"Wuppertal",
    "sg:phone":"+49 202/473757",
    "sg:postcode":"42349",
    "sg:province":"Nordrhein-Westfalen",
    "wof:name":"Jacobs Gmbh",
    "wof:placetype":"venue"
},
  "geometry": {"coordinates":[7.109817028,51.1939277649],"type":"Point"}
}