{
  "type": "Feature",
  "properties": {
    "iso:country":"DE",
    "sg:address":"Kirchplatz 11",
    "sg:city":"M\u00f6nchengladbach",
    "sg:phone":"+49 2161/182039",
    "sg:postcode":"41061",
    "sg:province":"Nordrhein-Westfalen",
    "wof:name":"Katholisches Pfarramt Mari\u00e4 Himmelfahrt",
    "wof:placetype":"venue"
},
  "geometry": {"coordinates":[6.4318127632,51.1936759949],"type":"Point"}
}