{
  "type": "Feature",
  "properties": {
    "iso:country":"DE",
    "sg:address":"Ehrlichstr. 53",
    "sg:city":"Berlin",
    "sg:phone":"+49 3877/74954",
    "sg:postcode":"10318",
    "sg:province":"Berlin",
    "wof:name":"P. Thiermann Finanzberater",
    "wof:placetype":"venue"
},
  "geometry": {"coordinates":[13.5161600113,52.48204422],"type":"Point"}
}