{
  "type": "Feature",
  "properties": {
    "iso:country":"DE",
    "sg:address":"M\u00fchlenstr. 20",
    "sg:city":"Paderborn",
    "sg:phone":"+49 5251/281555",
    "sg:postcode":"33098",
    "sg:province":"Nordrhein-Westfalen",
    "wof:name":"Wolfgang Kabella",
    "wof:placetype":"venue"
},
  "geometry": {"coordinates":[8.7546205521,51.7211303711],"type":"Point"}
}