{
  "type": "Feature",
  "properties": {
    "iso:country":"DE",
    "sg:address":"Trippsteinstr. 54",
    "sg:city":"Berlin",
    "sg:phone":"+49 30/7111115",
    "sg:postcode":"12249",
    "sg:province":"Berlin",
    "wof:name":"Selecta Unternehmensberatung Gmbh",
    "wof:placetype":"venue"
},
  "geometry": {"coordinates":[13.3468551636,52.4177818298],"type":"Point"}
}