{
  "type": "Feature",
  "properties": {
    "iso:country":"DE",
    "sg:address":"Rostocker Str. 4",
    "sg:city":"Pritzwalk",
    "sg:phone":"+49 3395/7460",
    "sg:postcode":"16928",
    "sg:province":"Brandenburg",
    "wof:name":"Sparkasse Prignitz",
    "wof:placetype":"venue"
},
  "geometry": {"coordinates":[12.1736412048,53.1583061218],"type":"Point"}
}