{
  "type": "Feature",
  "properties": {
    "iso:country":"DE",
    "sg:address":"Speckestr. 11",
    "sg:city":"Borgentreich",
    "sg:phone":"+49 5643/201",
    "sg:postcode":"34434",
    "sg:province":"Nordrhein-Westfalen",
    "wof:name":"Franz Gocke",
    "wof:placetype":"venue"
},
  "geometry": {"coordinates":[9.24254,51.567291],"type":"Point"}
}