{
  "type": "Feature",
  "properties": {
    "iso:country":"DE",
    "sg:address":"Fliederweg 06",
    "sg:city":"Trebsen",
    "sg:phone":"+49 34383/44395",
    "sg:postcode":"04687",
    "sg:province":"Sachsen",
    "wof:name":"Bernd Kreim",
    "wof:placetype":"venue"
},
  "geometry": {"coordinates":[12.7598133087,51.2799263],"type":"Point"}
}