{
  "type": "Feature",
  "properties": {
    "iso:country":"DE",
    "sg:address":"Friedrichstr. 9",
    "sg:city":"Paderborn",
    "sg:phone":"+49 5251/24246",
    "sg:postcode":"33102",
    "sg:province":"Nordrhein-Westfalen",
    "wof:name":"Wema Web- Und Maschen-meterwaren-",
    "wof:placetype":"venue"
},
  "geometry": {"coordinates":[8.7466363907,51.7172203064],"type":"Point"}
}