{
  "type": "Feature",
  "properties": {
    "iso:country":"DE",
    "sg:address":"Eppelheimer Str. 32",
    "sg:city":"Plankstadt",
    "sg:phone":"+49 6202/21698",
    "sg:postcode":"68723",
    "sg:province":"Baden-W\u00fcrttemberg",
    "wof:name":"E. Schmitt",
    "wof:placetype":"venue"
},
  "geometry": {"coordinates":[8.601542,49.393913],"type":"Point"}
}