{
  "type": "Feature",
  "properties": {
    "iso:country":"DE",
    "sg:address":"Garnstr. 29",
    "sg:city":"Potsdam",
    "sg:phone":"+49 331/719282",
    "sg:postcode":"14482",
    "sg:province":"Brandenburg",
    "wof:name":"Esprite-cafe",
    "wof:placetype":"venue"
},
  "geometry": {"coordinates":[13.090982,52.394184],"type":"Point"}
}