{
  "type": "Feature",
  "properties": {
    "iso:country":"DE",
    "sg:address":"Huestr. 93",
    "sg:city":"Essen",
    "sg:phone":"+49 201/210482",
    "sg:postcode":"45309",
    "sg:province":"Nordrhein-Westfalen",
    "wof:name":"Karl Arnold Gmbh",
    "wof:placetype":"venue"
},
  "geometry": {"coordinates":[7.0631809235,51.483959198],"type":"Point"}
}