{
  "type": "Feature",
  "properties": {
    "iso:country":"DE",
    "sg:address":"Augustaanlage 66",
    "sg:city":"Mannheim",
    "sg:postcode":"68165",
    "sg:province":"Baden-W\u00fcrttemberg",
    "wof:name":"Cgu International Insurance Plc",
    "wof:placetype":"venue"
},
  "geometry": {"coordinates":[8.4911079407,49.4783287048],"type":"Point"}
}