{
  "type": "Feature",
  "properties": {
    "iso:country":"DE",
    "sg:address":"Gerhart-Hauptmann-Str. 17",
    "sg:city":"Sindelfingen",
    "sg:phone":"+49 7031/384199",
    "sg:postcode":"71069",
    "sg:province":"Baden-W\u00fcrttemberg",
    "wof:name":"Helmut Trudel Architekt",
    "wof:placetype":"venue"
},
  "geometry": {"coordinates":[8.959487,48.719612],"type":"Point"}
}