{
  "type": "Feature",
  "properties": {
    "iso:country":"DE",
    "sg:address":"Breitenweg 17",
    "sg:city":"R\u00f6merberg",
    "sg:phone":"+49 6232/82828",
    "sg:postcode":"67354",
    "sg:province":"Rheinland-Pfalz",
    "wof:name":"Karl Schuster Landwirt. Lohnbetrieb",
    "wof:placetype":"venue"
},
  "geometry": {"coordinates":[8.39506,49.26709],"type":"Point"}
}