{
  "type": "Feature",
  "properties": {
    "iso:country":"DE",
    "sg:address":"Eimer Landstr. 1",
    "sg:city":"Gronau",
    "sg:phone":"+49 5182/3073",
    "sg:postcode":"31028",
    "sg:province":"Niedersachsen",
    "wof:name":"Buchmann Natursteine + Grabmale Gmbh",
    "wof:placetype":"venue"
},
  "geometry": {"coordinates":[9.7607212067,52.0848197937],"type":"Point"}
}