{
  "type": "Feature",
  "properties": {
    "iso:country":"DE",
    "sg:address":"Austr. 20",
    "sg:city":"Siegbach",
    "sg:phone":"+49 2778/405",
    "sg:postcode":"35768",
    "sg:province":"Hessen",
    "wof:name":"Volksbank Gladenbach Eg.",
    "wof:placetype":"venue"
},
  "geometry": {"coordinates":[8.416984,50.736622],"type":"Point"}
}