{
  "type": "Feature",
  "properties": {
    "iso:country":"DE",
    "sg:address":"Bahnhofstr. 4",
    "sg:city":"Jessen",
    "sg:phone":"+49 3537/26510",
    "sg:postcode":"06917",
    "sg:province":"Sachsen-Anhalt",
    "wof:name":"Albrecht Gmbh",
    "wof:placetype":"venue"
},
  "geometry": {"coordinates":[12.9550113678,51.7909049988],"type":"Point"}
}