{
  "type": "Feature",
  "properties": {
    "iso:country":"DE",
    "sg:address":"Augustaanlage 33",
    "sg:city":"Mannheim",
    "sg:postcode":"68165",
    "sg:province":"Baden-W\u00fcrttemberg",
    "wof:name":"Ella Grundst\u00fccks - Verwaltungsgesellschaft Mbh",
    "wof:placetype":"venue"
},
  "geometry": {"coordinates":[8.483322,49.481373],"type":"Point"}
}