{
  "type": "Feature",
  "properties": {
    "iso:country":"DE",
    "sg:address":"Hermeskeiler Str. 20",
    "sg:city":"Waldrach",
    "sg:phone":"+49 6500/307",
    "sg:postcode":"54320",
    "sg:province":"Rheinland-Pfalz",
    "wof:name":"Gerhard Krell",
    "wof:placetype":"venue"
},
  "geometry": {"coordinates":[6.741988,49.744968],"type":"Point"}
}