{
  "type": "Feature",
  "properties": {
    "iso:country":"DE",
    "sg:address":"Ledererweg 9",
    "sg:city":"Tegernsee",
    "sg:phone":"+49 8022/95379",
    "sg:postcode":"83684",
    "sg:province":"Bayern",
    "wof:name":"Golfshop Birdie Golfcenter Tegernsee",
    "wof:placetype":"venue"
},
  "geometry": {"coordinates":[11.775037,47.692638],"type":"Point"}
}