{
  "type": "Feature",
  "properties": {
    "iso:country":"DE",
    "sg:address":"Schlo\u00dfkellerweg 20",
    "sg:city":"Grosselfingen",
    "sg:phone":"+49 7476/7096",
    "sg:postcode":"72415",
    "sg:province":"Baden-W\u00fcrttemberg",
    "wof:name":"Josef Sulzer Immobilienmakler",
    "wof:placetype":"venue"
},
  "geometry": {"coordinates":[8.8866672516,48.3301925659],"type":"Point"}
}