{
  "type": "Feature",
  "properties": {
    "iso:country":"DE",
    "sg:address":"Dechant-Deckers-Str. 13",
    "sg:city":"Eschweiler",
    "sg:phone":"+49 2403/35554",
    "sg:postcode":"52249",
    "sg:province":"Nordrhein-Westfalen",
    "wof:name":"Hans Bock Immobilienmakler",
    "wof:placetype":"venue"
},
  "geometry": {"coordinates":[6.2629241943,50.8189544678],"type":"Point"}
}