{
  "type": "Feature",
  "properties": {
    "iso:country":"DE",
    "sg:address":"Lachemer Dorfstr. 24",
    "sg:city":"Hessisch Oldendorf",
    "sg:phone":"+49 5158/741",
    "sg:postcode":"31840",
    "sg:province":"Niedersachsen",
    "wof:name":"Friedrich Amelung",
    "wof:placetype":"venue"
},
  "geometry": {"coordinates":[9.271819,52.140446],"type":"Point"}
}