{
  "type": "Feature",
  "properties": {
    "iso:country":"DE",
    "sg:address":"D\u00fcrrbachstr. 5",
    "sg:city":"Karlsruhe",
    "sg:phone":"+49 721/44680",
    "sg:postcode":"76227",
    "sg:province":"Baden-W\u00fcrttemberg",
    "wof:name":"Dr. Susanne Sch\u00e4fer-guber",
    "wof:placetype":"venue"
},
  "geometry": {"coordinates":[8.4796705246,48.9972839355],"type":"Point"}
}