{
  "type": "Feature",
  "properties": {
    "iso:country":"DE",
    "sg:address":"Oberbr\u00e4nder Str. 27",
    "sg:city":"Eisenbach",
    "sg:phone":"+49 7657/1431",
    "sg:postcode":"79871",
    "sg:province":"Baden-W\u00fcrttemberg",
    "wof:name":"Spitzwald",
    "wof:placetype":"venue"
},
  "geometry": {"coordinates":[8.28236866,47.9477348328],"type":"Point"}
}