{
  "type": "Feature",
  "properties": {
    "iso:country":"DE",
    "sg:address":"Auf dem Schollbruch 15",
    "sg:city":"Gelsenkirchen",
    "sg:phone":"+49 209/55651",
    "sg:postcode":"45899",
    "sg:province":"Nordrhein-Westfalen",
    "wof:name":"Hans-richard Ferfers",
    "wof:placetype":"venue"
},
  "geometry": {"coordinates":[7.0229082108,51.5394515991],"type":"Point"}
}