{
  "type": "Feature",
  "properties": {
    "iso:country":"DE",
    "sg:address":"Verler Str. 6",
    "sg:city":"G\u00fctersloh",
    "sg:postcode":"33332",
    "sg:province":"Nordrhein-Westfalen",
    "wof:name":"Jumbo-service Gmbh",
    "wof:placetype":"venue"
},
  "geometry": {"coordinates":[8.392852,51.904243],"type":"Point"}
}