{
  "type": "Feature",
  "properties": {
    "iso:country":"DE",
    "sg:address":"Bahnhofstr. 4",
    "sg:city":"Gro\u00df-Bieberau",
    "sg:postcode":"64401",
    "sg:province":"Hessen",
    "wof:name":"Sch\u00f6nberger Verwaltungs-gmbh",
    "wof:placetype":"venue"
},
  "geometry": {"coordinates":[8.8268890381,49.8012123108],"type":"Point"}
}