{
  "type": "Feature",
  "properties": {
    "iso:country":"DE",
    "sg:address":"Bernhard-Warnecke-Str 18",
    "sg:city":"Verden",
    "sg:phone":"+49 4231/2837",
    "sg:postcode":"27283",
    "sg:province":"Niedersachsen",
    "wof:name":"Kleineidam Gmbh & Co Kg",
    "wof:placetype":"venue"
},
  "geometry": {"coordinates":[9.2398443222,52.9134597778],"type":"Point"}
}