{
  "type": "Feature",
  "properties": {
    "iso:country":"DE",
    "sg:address":"Arnulf-Klett-Platz 3",
    "sg:city":"Stuttgart",
    "sg:postcode":"70173",
    "sg:province":"Baden-W\u00fcrttemberg",
    "wof:name":"Usd Immobilien Gmbh",
    "wof:placetype":"venue"
},
  "geometry": {"coordinates":[9.181236,48.782894],"type":"Point"}
}