{
  "type": "Feature",
  "properties": {
    "iso:country":"DE",
    "sg:address":"Enzianweg 10",
    "sg:city":"Obers\u00f6chering",
    "sg:postcode":"82395",
    "sg:province":"Bayern",
    "wof:name":"Delizza Gmbh",
    "wof:placetype":"venue"
},
  "geometry": {"coordinates":[11.2159070969,47.7359161377],"type":"Point"}
}