{
  "type": "Feature",
  "properties": {
    "iso:country":"DE",
    "sg:address":"Kirnberg 58",
    "sg:city":"Wiesent",
    "sg:phone":"+49 9482/3090",
    "sg:postcode":"93109",
    "sg:province":"Bayern",
    "wof:name":"Weinstube Josef Heitzer",
    "wof:placetype":"venue"
},
  "geometry": {"coordinates":[12.4138002396,49.0448684692],"type":"Point"}
}