{
  "type": "Feature",
  "properties": {
    "iso:country":"DE",
    "sg:address":"Schwebelstr. 2",
    "sg:city":"Neunkirchen",
    "sg:phone":"+49 6821/23541",
    "sg:postcode":"66538",
    "sg:province":"Saarland",
    "wof:name":"Zur Tenne",
    "wof:placetype":"venue"
},
  "geometry": {"coordinates":[7.1799249649,49.3438644409],"type":"Point"}
}