{"geometry":{"type":"Point","coordinates":[10.866050,48.393703]},"type":"Feature","id":102560817,"bbox":[10.866050,48.393703,10.866050,48.393703],"properties":{"sg:province":"Bayern","geom:longitude":10.866050,"wof:breaches":[],"sg:href":"http://api.simplegeo.com/1.0/features/SG_0FcllrfOeEMC4lISwjSPdp_48.393703_10.866050@1306268793.json","sg:owner":"simplegeo","sg:postcode":"86156","geom:latitude":48.393703,"sg:classifiers":[],"sg:address":"Hirblinger Str. 133::","sg:phone":"+49 821/2077702","wof:hierarchy":[{"venue_id":102560817,"region_id":85682571,"country_id":85633111,"locality_id":101748481,"county_id":102063283,"neighbourhood_id":85899443}],"geom:area":0.000000,"sg:city":"Augsburg","wof:lastmodified":1438093374,"iso:country":"DE","wof:geomhash":"ad2ef13c98542ce848bafbe4cbb6f091","wof:name":"Wach Und Schliess Gmbh","wof:belongsto":[85682571,85633111,101748481,102063283,85899443],"src:geom":"simplegeo","wof:placetype":"venue","wof:supersedes":[],"wof:id":102560817,"wof:superseded_by":[],"wof:concordances":{"sg:id":"SG_0FcllrfOeEMC4lISwjSPdp_48.393703_10.866050@1306268793"},"wof:parent_id":85899443}}