{
  "type": "Feature",
  "properties": {
    "iso:country":"DE",
    "sg:address":"Hirblinger Str. 133::",
    "sg:city":"Augsburg",
    "sg:href":"http://api.simplegeo.com/1.0/features/SG_0FcllrfOeEMC4lISwjSPdp_48.393703_10.866050@1306268793.json",
    "sg:phone":"+49 821/2077702",
    "sg:postcode":"86156",
    "sg:province":"Bayern",
    "wof:name":"Wach Und Schliess Gmbh",
    "wof:placetype":"venue"
},
  "geometry": {"coordinates":[10.86605,48.393703],"type":"Point"}
}