{
  "type": "Feature",
  "properties": {
    "iso:country":"DE",
    "sg:address":"Alte Jakobstr. 76",
    "sg:city":"Berlin",
    "sg:phone":"+49 30/2312030",
    "sg:postcode":"10179",
    "sg:province":"Berlin",
    "wof:name":"Premier Deutschland Gmbh",
    "wof:placetype":"venue"
},
  "geometry": {"coordinates":[13.409126,52.510593],"type":"Point"}
}