{
  "type": "Feature",
  "properties": {
    "iso:country":"DE",
    "sg:address":"Schmiedgasse 3",
    "sg:city":"Kaufbeuren",
    "sg:phone":"+49 8341/95280",
    "sg:postcode":"87600",
    "sg:province":"Bayern",
    "wof:name":"Deutsche Woolworth Gmbh & Co. Ohg",
    "wof:placetype":"venue"
},
  "geometry": {"coordinates":[10.618804,47.880585],"type":"Point"}
}