{
  "type": "Feature",
  "properties": {
    "iso:country":"DE",
    "sg:city":"Bad Bertrich",
    "sg:phone":"+49 2674/733",
    "sg:postcode":"56864",
    "sg:province":"Rheinland-Pfalz",
    "wof:name":"Tanzcafe Flair",
    "wof:placetype":"venue"
},
  "geometry": {"coordinates":[7.031925,50.070011],"type":"Point"}
}