{
  "type": "Feature",
  "properties": {
    "iso:country":"DE",
    "sg:address":"An der Ziegelei 29",
    "sg:city":"Essen",
    "sg:phone":"+49 201/7103084",
    "sg:postcode":"45133",
    "sg:province":"Nordrhein-Westfalen",
    "wof:name":"Arnd Deuter",
    "wof:placetype":"venue"
},
  "geometry": {"coordinates":[6.9731,51.412971],"type":"Point"}
}