{
  "type": "Feature",
  "properties": {
    "iso:country":"DE",
    "sg:address":"Deggendorfer Str. 13",
    "sg:city":"Schwarzach",
    "sg:phone":"+49 9962/432",
    "sg:postcode":"94374",
    "sg:province":"Bayern",
    "wof:name":"Ida Brandl",
    "wof:placetype":"venue"
},
  "geometry": {"coordinates":[12.813353,48.919601],"type":"Point"}
}