{
  "type": "Feature",
  "properties": {
    "iso:country":"DE",
    "sg:address":"Theodor-Heuss-Str. 49 b",
    "sg:city":"Hanau",
    "sg:postcode":"63457",
    "sg:province":"Hessen",
    "wof:name":"Tr Office-service Gmbh",
    "wof:placetype":"venue"
},
  "geometry": {"coordinates":[8.970905304,50.1019973755],"type":"Point"}
}