{
  "type": "Feature",
  "properties": {
    "iso:country":"DE",
    "sg:address":"Bollmannsdamm 24 a",
    "sg:city":"Weyhe",
    "sg:phone":"+49 421/803659",
    "sg:postcode":"28844",
    "sg:province":"Niedersachsen",
    "wof:name":"Marianne Schr\u00f6der",
    "wof:placetype":"venue"
},
  "geometry": {"coordinates":[8.7831497192,52.9760513306],"type":"Point"}
}