{
  "type": "Feature",
  "properties": {
    "iso:country":"DE",
    "sg:address":"Kronenstr. 4",
    "sg:city":"Stuttgart",
    "sg:phone":"+49 711/295628",
    "sg:postcode":"70173",
    "sg:province":"Baden-W\u00fcrttemberg",
    "wof:name":"Gerda M\u00f6bus",
    "wof:placetype":"venue"
},
  "geometry": {"coordinates":[9.179746,48.78233],"type":"Point"}
}