{
  "type": "Feature",
  "properties": {
    "iso:country":"DE",
    "sg:address":"Hauptstr. 19",
    "sg:city":"Dannstadt-Schauernheim",
    "sg:postcode":"67125",
    "sg:province":"Rheinland-Pfalz",
    "wof:name":"Vielhauer Verwaltungs-gmbh",
    "wof:placetype":"venue"
},
  "geometry": {"coordinates":[8.311887,49.431297],"type":"Point"}
}