{
  "type": "Feature",
  "properties": {
    "iso:country":"DE",
    "sg:address":"Hans-B\u00f6ckler-Str. 3",
    "sg:city":"Trautskirchen",
    "sg:phone":"+49 9107/225",
    "sg:postcode":"90619",
    "sg:province":"Bayern",
    "wof:name":"Restaurant Schwarzer Adler",
    "wof:placetype":"venue"
},
  "geometry": {"coordinates":[10.5935239792,49.4567527771],"type":"Point"}
}