{
  "type": "Feature",
  "properties": {
    "iso:country":"DE",
    "sg:address":"Poststr. 5",
    "sg:city":"Boppard",
    "sg:phone":"+49 6742/3862",
    "sg:postcode":"56154",
    "sg:province":"Rheinland-Pfalz",
    "wof:name":"Mh Promotion E. K.",
    "wof:placetype":"venue"
},
  "geometry": {"coordinates":[7.5290808678,50.2096252441],"type":"Point"}
}