{
  "type": "Feature",
  "properties": {
    "iso:country":"DE",
    "sg:address":"86744",
    "sg:city":"Hainsfarth",
    "sg:phone":"+49 9082/1474",
    "sg:postcode":"86744",
    "sg:province":"Bayern",
    "wof:name":"Gemeindeb\u00fccherei Schule",
    "wof:placetype":"venue"
},
  "geometry": {"coordinates":[10.626447,48.959949],"type":"Point"}
}