{
  "type": "Feature",
  "properties": {
    "iso:country":"DE",
    "sg:address":"Zeisigweg 1/1",
    "sg:city":"Remchingen",
    "sg:phone":"+49 7232/70277",
    "sg:postcode":"75196",
    "sg:province":"Baden-W\u00fcrttemberg",
    "wof:name":"Franz K\u00fcnzler & Co. Ohg",
    "wof:placetype":"venue"
},
  "geometry": {"coordinates":[8.577794075,48.9565582275],"type":"Point"}
}