{
  "type": "Feature",
  "properties": {
    "iso:country":"DE",
    "sg:address":"Ludwigstr. 39",
    "sg:city":"Edesheim",
    "sg:phone":"+49 6323/5686",
    "sg:postcode":"67483",
    "sg:province":"Rheinland-Pfalz",
    "wof:name":"L. Klimm Weinanbau",
    "wof:placetype":"venue"
},
  "geometry": {"coordinates":[8.1272411346,49.2602653503],"type":"Point"}
}