{
  "type": "Feature",
  "properties": {
    "iso:country":"DE",
    "sg:address":"Konstantinstr. 117",
    "sg:city":"M\u00f6nchengladbach",
    "sg:phone":"+49 2166/87335",
    "sg:postcode":"41238",
    "sg:province":"Nordrhein-Westfalen",
    "wof:name":"Em Tetz Backes B\u00e4ckerei Und Konditorei Gmbh",
    "wof:placetype":"venue"
},
  "geometry": {"coordinates":[6.485028,51.15641],"type":"Point"}
}