{
  "type": "Feature",
  "properties": {
    "iso:country":"DE",
    "sg:address":"Dresdener Str. 66",
    "sg:city":"Bernsdorf",
    "sg:postcode":"02994",
    "sg:province":"Sachsen",
    "wof:name":"Ursula Baldermann",
    "wof:placetype":"venue"
},
  "geometry": {"coordinates":[14.055554,51.364536],"type":"Point"}
}