{
  "type": "Feature",
  "properties": {
    "iso:country":"DE",
    "sg:address":"Im Rebgarten 8",
    "sg:city":"Kl\u00fcsserath",
    "sg:postcode":"54340",
    "sg:province":"Rheinland-Pfalz",
    "wof:name":"G\u00fcnter Herres Ortsb\u00fcrgermeister Der",
    "wof:placetype":"venue"
},
  "geometry": {"coordinates":[6.8450360298,49.8478546143],"type":"Point"}
}