{
  "type": "Feature",
  "properties": {
    "iso:country":"DE",
    "sg:address":"Konrad-Adenauer-Str. 32",
    "sg:city":"Reutlingen",
    "sg:phone":"+49 7121/334981",
    "sg:postcode":"72762",
    "sg:province":"Baden-W\u00fcrttemberg",
    "wof:name":"Esso Deutschland Gmbh",
    "wof:placetype":"venue"
},
  "geometry": {"coordinates":[9.2027606964,48.4923171997],"type":"Point"}
}