{
  "type": "Feature",
  "properties": {
    "iso:country":"DE",
    "sg:address":"Schaumburger Str. 10",
    "sg:city":"Wunstorf",
    "sg:postcode":"31515",
    "sg:province":"Niedersachsen",
    "wof:name":"Andreas Kleina",
    "wof:placetype":"venue"
},
  "geometry": {"coordinates":[9.379838,52.416996],"type":"Point"}
}