{
  "type": "Feature",
  "properties": {
    "iso:country":"DE",
    "sg:address":"Theatergasse 14",
    "sg:city":"N\u00fcrnberg",
    "sg:phone":"+49 911/227000",
    "sg:postcode":"90402",
    "sg:province":"Bayern",
    "wof:name":"Lothar Bendull",
    "wof:placetype":"venue"
},
  "geometry": {"coordinates":[11.0794296265,49.4495773315],"type":"Point"}
}