{
  "type": "Feature",
  "properties": {
    "iso:country":"DE",
    "sg:address":"Hochstr. 12",
    "sg:city":"Marl",
    "sg:phone":"+49 2365/56616",
    "sg:postcode":"45768",
    "sg:province":"Nordrhein-Westfalen",
    "wof:name":"D. Mattukat Heilpraktiker",
    "wof:placetype":"venue"
},
  "geometry": {"coordinates":[7.0873031616,51.6464042664],"type":"Point"}
}