{
  "type": "Feature",
  "properties": {
    "iso:country":"DE",
    "sg:address":"Linnicher Str. 17",
    "sg:city":"J\u00fclich",
    "sg:phone":"+49 2461/31049",
    "sg:postcode":"52428",
    "sg:province":"Nordrhein-Westfalen",
    "wof:name":"Derichs & Partner Gmbh",
    "wof:placetype":"venue"
},
  "geometry": {"coordinates":[6.3554291725,50.928024292],"type":"Point"}
}