{
  "type": "Feature",
  "properties": {
    "iso:country":"DE",
    "sg:address":"H\u00fclscheiderbaum",
    "sg:city":"L\u00fcdenscheid",
    "sg:phone":"+49 2351/53410",
    "sg:postcode":"58513",
    "sg:province":"Nordrhein-Westfalen",
    "wof:name":"Imbi\u00df H\u00fclscheiderbaum",
    "wof:placetype":"venue"
},
  "geometry": {"coordinates":[7.5966367722,51.2483062744],"type":"Point"}
}