{
  "type": "Feature",
  "properties": {
    "iso:country":"DE",
    "sg:address":"Wallstr. 6",
    "sg:city":"Waldshut-Tiengen",
    "sg:phone":"+49 7751/91690",
    "sg:postcode":"79761",
    "sg:province":"Baden-W\u00fcrttemberg",
    "wof:name":"Tip Verlag Gmbh",
    "wof:placetype":"venue"
},
  "geometry": {"coordinates":[8.2142810822,47.6231307983],"type":"Point"}
}