{
  "type": "Feature",
  "properties": {
    "iso:country":"DE",
    "sg:address":"Am Kehlgraben 95",
    "sg:city":"Kronach",
    "sg:phone":"+49 9261/63344",
    "sg:postcode":"96317",
    "sg:province":"Bayern",
    "wof:name":"Elisabeth Foidl",
    "wof:placetype":"venue"
},
  "geometry": {"coordinates":[11.347269,50.237522],"type":"Point"}
}