{
  "type": "Feature",
  "properties": {
    "iso:country":"DE",
    "sg:address":"T\u00f6rles\u00e4ckerstr. 2 b",
    "sg:city":"Stuttgart",
    "sg:phone":"+49 711/455060",
    "sg:postcode":"70599",
    "sg:province":"Baden-W\u00fcrttemberg",
    "wof:name":"Spielwaren Veit",
    "wof:placetype":"venue"
},
  "geometry": {"coordinates":[9.2068681717,48.723991394],"type":"Point"}
}