{
  "type": "Feature",
  "properties": {
    "iso:country":"DE",
    "sg:address":"Frohnhauser Str. 330",
    "sg:city":"Essen",
    "sg:phone":"+49 201/8761055",
    "sg:postcode":"45144",
    "sg:province":"Nordrhein-Westfalen",
    "wof:name":"Gators Pizza",
    "wof:placetype":"venue"
},
  "geometry": {"coordinates":[6.9531297684,51.4489402771],"type":"Point"}
}