{
  "type": "Feature",
  "properties": {
    "iso:country":"DE",
    "sg:address":"Middeweg 11",
    "sg:city":"Bottrop",
    "sg:phone":"+49 2041/790148",
    "sg:postcode":"46240",
    "sg:province":"Nordrhein-Westfalen",
    "wof:name":"Ursula Heck",
    "wof:placetype":"venue"
},
  "geometry": {"coordinates":[6.9182248116,51.5465888977],"type":"Point"}
}