{
  "type": "Feature",
  "properties": {
    "iso:country":"DE",
    "sg:address":"Hunteburger Str. 11",
    "sg:city":"Ostercappeln",
    "sg:phone":"+49 5476/221",
    "sg:postcode":"49179",
    "sg:province":"Niedersachsen",
    "wof:name":"Ernst Ballmeyer",
    "wof:placetype":"venue"
},
  "geometry": {"coordinates":[8.173129,52.391037],"type":"Point"}
}