{
  "type": "Feature",
  "properties": {
    "iso:country":"DE",
    "sg:address":"Alleestr. 24",
    "sg:city":"Remscheid",
    "sg:phone":"+49 2191/420683",
    "sg:postcode":"42853",
    "sg:province":"Nordrhein-Westfalen",
    "wof:name":"Jean Pascale Vertrieb Gmbh & Co.",
    "wof:placetype":"venue"
},
  "geometry": {"coordinates":[7.192331,51.180412],"type":"Point"}
}