{
  "type": "Feature",
  "properties": {
    "iso:country":"DE",
    "sg:address":"Rottwerndorfer Str. 1",
    "sg:city":"Dresden",
    "sg:postcode":"01257",
    "sg:province":"Sachsen",
    "wof:name":"Gwf Mbh",
    "wof:placetype":"venue"
},
  "geometry": {"coordinates":[13.8183784485,51.0133552551],"type":"Point"}
}