{
  "type": "Feature",
  "properties": {
    "iso:country":"DE",
    "sg:address":"Albert-Schweitzer-Str. 13",
    "sg:city":"Raisdorf",
    "sg:phone":"+49 4307/839900",
    "sg:postcode":"24223",
    "sg:province":"Schleswig-Holstein",
    "wof:name":"Klaus Puls",
    "wof:placetype":"venue"
},
  "geometry": {"coordinates":[10.257504,54.281815],"type":"Point"}
}