{
  "type": "Feature",
  "properties": {
    "iso:country":"DE",
    "sg:address":"Langwahn 82",
    "sg:city":"Eschweiler",
    "sg:phone":"+49 2403/22103",
    "sg:postcode":"52249",
    "sg:province":"Nordrhein-Westfalen",
    "wof:name":"Blumenhaus Troniseck Martin Thelen",
    "wof:placetype":"venue"
},
  "geometry": {"coordinates":[6.260006,50.81686],"type":"Point"}
}