{
  "type": "Feature",
  "properties": {
    "iso:country":"DE",
    "sg:address":"Kr\u00fcgerbr\u00fccke 13",
    "sg:city":"Aschersleben",
    "sg:phone":"+49 3473/806951",
    "sg:postcode":"06449",
    "sg:province":"Sachsen-Anhalt",
    "wof:name":"Bexu Liberty Woman Gmbh",
    "wof:placetype":"venue"
},
  "geometry": {"coordinates":[11.457015,51.75491],"type":"Point"}
}