{
  "type": "Feature",
  "properties": {
    "iso:country":"DE",
    "sg:address":"Koblenzer Str. 74",
    "sg:city":"Simmern",
    "sg:phone":"+49 6761/94240",
    "sg:postcode":"55469",
    "sg:province":"Rheinland-Pfalz",
    "wof:name":"Dekra Automobil Gmbh",
    "wof:placetype":"venue"
},
  "geometry": {"coordinates":[7.4798870087,49.9743728638],"type":"Point"}
}