{
  "type": "Feature",
  "properties": {
    "iso:country":"DE",
    "sg:address":"Hahnenwall 2",
    "sg:city":"Menden",
    "sg:phone":"+49 2373/10542",
    "sg:postcode":"58706",
    "sg:province":"Nordrhein-Westfalen",
    "wof:name":"Stahl Gmbh",
    "wof:placetype":"venue"
},
  "geometry": {"coordinates":[7.798203,51.43861],"type":"Point"}
}