{
  "type": "Feature",
  "properties": {
    "iso:country":"DE",
    "sg:address":"Hirschstr. 4",
    "sg:city":"Nersingen",
    "sg:phone":"+49 7308/41610",
    "sg:postcode":"89278",
    "sg:province":"Bayern",
    "wof:name":"Peter Gunderlach",
    "wof:placetype":"venue"
},
  "geometry": {"coordinates":[10.1330432892,48.4128112793],"type":"Point"}
}