{
  "type": "Feature",
  "properties": {
    "iso:country":"DE",
    "sg:address":"R\u00fcttenscheider Str. 108",
    "sg:city":"Essen",
    "sg:phone":"+49 201/798221",
    "sg:postcode":"45130",
    "sg:province":"Nordrhein-Westfalen",
    "wof:name":"Geboda Gesellschaft F\u00fcr Bau- Logistik Und Ingenieur-",
    "wof:placetype":"venue"
},
  "geometry": {"coordinates":[7.0044140816,51.4344749451],"type":"Point"}
}