{
  "type": "Feature",
  "properties": {
    "iso:country":"DE",
    "sg:address":"Gie\u00dfener Str. 1",
    "sg:city":"Pohlheim",
    "sg:phone":"+49 6403/61017",
    "sg:postcode":"35415",
    "sg:province":"Hessen",
    "wof:name":"Marianne H\u00e4user",
    "wof:placetype":"venue"
},
  "geometry": {"coordinates":[8.708834,50.533321],"type":"Point"}
}