{
  "type": "Feature",
  "properties": {
    "iso:country":"DE",
    "sg:address":"Rechbergstr. 23",
    "sg:city":"Waldstetten",
    "sg:phone":"+49 7171/41707",
    "sg:postcode":"73550",
    "sg:province":"Baden-W\u00fcrttemberg",
    "wof:name":"Hubert Hahn",
    "wof:placetype":"venue"
},
  "geometry": {"coordinates":[9.8153982162,48.7641830444],"type":"Point"}
}