{
  "type": "Feature",
  "properties": {
    "iso:country":"DE",
    "sg:address":"Alex-M\u00fcller-Str. 102",
    "sg:city":"Kaiserslautern",
    "sg:postcode":"67657",
    "sg:province":"Rheinland-Pfalz",
    "wof:name":"Con-sero Management Gmbh",
    "wof:placetype":"venue"
},
  "geometry": {"coordinates":[7.7740077972,49.4547080994],"type":"Point"}
}