{
  "type": "Feature",
  "properties": {
    "iso:country":"DE",
    "sg:address":"Hauptstr. 57",
    "sg:city":"Fischbach",
    "sg:phone":"+49 6393/1257",
    "sg:postcode":"66996",
    "sg:province":"Rheinland-Pfalz",
    "wof:name":"Restaurant Grenzbachstuben",
    "wof:placetype":"venue"
},
  "geometry": {"coordinates":[7.3985447884,49.7414855957],"type":"Point"}
}