{
  "type": "Feature",
  "properties": {
    "iso:country":"DE",
    "sg:address":"Sonnenstr. 2",
    "sg:city":"Morsbach",
    "sg:phone":"+49 2294/7143",
    "sg:postcode":"51597",
    "sg:province":"Nordrhein-Westfalen",
    "wof:name":"Agnes M\u00fcller",
    "wof:placetype":"venue"
},
  "geometry": {"coordinates":[7.7358322144,50.9043579102],"type":"Point"}
}