{
  "type": "Feature",
  "properties": {
    "iso:country":"DE",
    "sg:address":"Karl-Marx-Str. 56",
    "sg:city":"Neuwied",
    "sg:phone":"+49 2631/75097",
    "sg:postcode":"56567",
    "sg:province":"Rheinland-Pfalz",
    "wof:name":"Hans-paul Ecker Elektroinstallation",
    "wof:placetype":"venue"
},
  "geometry": {"coordinates":[7.423484,50.453068],"type":"Point"}
}