{
  "type": "Feature",
  "properties": {
    "iso:country":"DE",
    "sg:address":"Hochstr. 40",
    "sg:city":"Br\u00fcggen",
    "sg:phone":"+49 2163/59830",
    "sg:postcode":"41379",
    "sg:province":"Nordrhein-Westfalen",
    "wof:name":"M. Reimann",
    "wof:placetype":"venue"
},
  "geometry": {"coordinates":[6.183181,51.244244],"type":"Point"}
}