{
  "type": "Feature",
  "properties": {
    "iso:country":"DE",
    "sg:address":"Schwarzenbergstr. 83",
    "sg:city":"Hamburg",
    "sg:phone":"+49 40/7665214",
    "sg:postcode":"21073",
    "sg:province":"Hamburg",
    "wof:name":"J. Weigel Immobilienmakler",
    "wof:placetype":"venue"
},
  "geometry": {"coordinates":[9.9714164734,53.4634056091],"type":"Point"}
}