{
  "type": "Feature",
  "properties": {
    "iso:country":"DE",
    "sg:address":"Lauterbadstr. 39",
    "sg:city":"Freudenstadt",
    "sg:postcode":"72250",
    "sg:province":"Baden-W\u00fcrttemberg",
    "wof:name":"Institut F\u00fcr Psychologie Und Seelsorge Ips",
    "wof:placetype":"venue"
},
  "geometry": {"coordinates":[8.414613,48.457905],"type":"Point"}
}