{
  "type": "Feature",
  "properties": {
    "iso:country":"DE",
    "sg:address":"Akazienweg 22",
    "sg:city":"Speyer",
    "sg:phone":"+49 4962/3232972",
    "sg:postcode":"67346",
    "sg:province":"Rheinland-Pfalz",
    "wof:name":"Eggensberger Buchbinderei Gmbh",
    "wof:placetype":"venue"
},
  "geometry": {"coordinates":[8.4277544022,49.3491744995],"type":"Point"}
}