{
  "type": "Feature",
  "properties": {
    "iso:country":"DE",
    "sg:address":"Weissacher Str. 89",
    "sg:city":"Backnang",
    "sg:phone":"+49 4971/918910",
    "sg:postcode":"71522",
    "sg:province":"Baden-W\u00fcrttemberg",
    "wof:name":"Schaufler & Schmidberger Gmbh & Co. Kg",
    "wof:placetype":"venue"
},
  "geometry": {"coordinates":[9.446169,48.933868],"type":"Point"}
}