{
  "type": "Feature",
  "properties": {
    "iso:country":"DE",
    "sg:address":"Wegscheid 12",
    "sg:city":"Alfter",
    "sg:phone":"+49 228/641155",
    "sg:postcode":"53347",
    "sg:province":"Nordrhein-Westfalen",
    "wof:name":"H. Johann Otto",
    "wof:placetype":"venue"
},
  "geometry": {"coordinates":[7.02524,50.718529],"type":"Point"}
}