{
  "type": "Feature",
  "properties": {
    "iso:country":"DE",
    "sg:address":"Kurze Str. 2",
    "sg:city":"Grapzow",
    "sg:postcode":"17089",
    "sg:province":"Mecklenburg-Vorpommern",
    "wof:name":"Evangelisch-lutherische Kirche",
    "wof:placetype":"venue"
},
  "geometry": {"coordinates":[13.2678403854,53.772605896],"type":"Point"}
}