{
  "type": "Feature",
  "properties": {
    "iso:country":"DE",
    "sg:address":"Am Neumarkt 9",
    "sg:city":"Senftenberg",
    "sg:phone":"+49 3573/797902",
    "sg:postcode":"01968",
    "sg:province":"Brandenburg",
    "wof:name":"G. Wulff",
    "wof:placetype":"venue"
},
  "geometry": {"coordinates":[14.0026445389,51.5177955627],"type":"Point"}
}