{
  "type": "Feature",
  "properties": {
    "iso:country":"DE",
    "sg:address":"Zum Kahleberg 61",
    "sg:city":"Potsdam",
    "sg:postcode":"14478",
    "sg:province":"Brandenburg",
    "wof:name":"Hans-joachim Bohn",
    "wof:placetype":"venue"
},
  "geometry": {"coordinates":[13.08585,52.366158],"type":"Point"}
}