{
  "type": "Feature",
  "properties": {
    "iso:country":"DE",
    "sg:address":"Bergstr. 73",
    "sg:city":"Hagen",
    "sg:phone":"+49 2331/24216",
    "sg:postcode":"58095",
    "sg:province":"Nordrhein-Westfalen",
    "wof:name":"Coiffeur Hilmar Schirmer",
    "wof:placetype":"venue"
},
  "geometry": {"coordinates":[7.4704837799,51.3557891846],"type":"Point"}
}