{
  "type": "Feature",
  "properties": {
    "iso:country":"DE",
    "sg:address":"Entenbachstr. 14",
    "sg:city":"M\u00fcnchen",
    "sg:phone":"+49 89/661060",
    "sg:postcode":"81541",
    "sg:province":"Bayern",
    "wof:name":"Pumpen Schall Inh. Peter Schwojer",
    "wof:placetype":"venue"
},
  "geometry": {"coordinates":[11.578693,48.12384],"type":"Point"}
}