{
  "type": "Feature",
  "properties": {
    "iso:country":"DE",
    "sg:address":"K\u00f6nitzer Str. 36",
    "sg:city":"Kaulsdorf",
    "sg:phone":"+49 36733/22362",
    "sg:postcode":"07338",
    "sg:province":"Th\u00fcringen",
    "wof:name":"Karl Wenzel",
    "wof:placetype":"venue"
},
  "geometry": {"coordinates":[11.482065,50.58802],"type":"Point"}
}