{
  "type": "Feature",
  "properties": {
    "iso:country":"DE",
    "sg:address":"Stiftstr 46",
    "sg:city":"M\u00fchltal",
    "sg:phone":"+49 6151/14081",
    "sg:postcode":"64367",
    "sg:province":"Hessen",
    "wof:name":"Bertsch Hotelw\u00e4sche Gmbh",
    "wof:placetype":"venue"
},
  "geometry": {"coordinates":[8.699583,49.827614],"type":"Point"}
}