{
  "type": "Feature",
  "properties": {
    "iso:country":"DE",
    "sg:address":"Dorfstr. 6",
    "sg:city":"Hohenfelde",
    "sg:phone":"+49 38203/3990",
    "sg:postcode":"18209",
    "sg:province":"Mecklenburg-Vorpommern",
    "wof:name":"Lihs Schornstein Und Bau Sanierungs Gmbh",
    "wof:placetype":"venue"
},
  "geometry": {"coordinates":[11.9102706909,54.0783996582],"type":"Point"}
}