{
  "type": "Feature",
  "properties": {
    "iso:country":"DE",
    "sg:address":"Gie\u00dfenstr. 7",
    "sg:city":"Kirchberg",
    "sg:phone":"+49 7354/8328",
    "sg:postcode":"88486",
    "sg:province":"Baden-W\u00fcrttemberg",
    "wof:name":"R. Und F. Wohlh\u00fcter",
    "wof:placetype":"venue"
},
  "geometry": {"coordinates":[10.0954551697,48.1458511353],"type":"Point"}
}