{
  "type": "Feature",
  "properties": {
    "iso:country":"DE",
    "sg:address":"bp 71",
    "sg:city":"aix en provence",
    "sg:phone":"+49 4422/16519",
    "sg:postcode":"13602",
    "wof:name":"Expats In A World",
    "wof:placetype":"venue"
},
  "geometry": {"coordinates":[5.44625,43.526409],"type":"Point"}
}