{
  "type": "Feature",
  "properties": {
    "iso:country":"DE",
    "sg:address":"Kampmoorweg 12",
    "sg:city":"Norderstedt",
    "sg:phone":"+49 40/5268550",
    "sg:postcode":"22844",
    "sg:province":"Schleswig-Holstein",
    "wof:name":"Torkret Gmbh",
    "wof:placetype":"venue"
},
  "geometry": {"coordinates":[9.97405,53.73793],"type":"Point"}
}