{
  "type": "Feature",
  "properties": {
    "iso:country":"DE",
    "sg:address":"Im Kreuzgewann 28",
    "sg:city":"Weinheim",
    "sg:phone":"+49 6201/55674",
    "sg:postcode":"69469",
    "sg:province":"Baden-W\u00fcrttemberg",
    "wof:name":"Rudi Henkel",
    "wof:placetype":"venue"
},
  "geometry": {"coordinates":[8.6698970795,49.5239334106],"type":"Point"}
}