{
  "type": "Feature",
  "properties": {
    "iso:country":"DE",
    "sg:address":"Sch\u00fctzenstr. 13",
    "sg:city":"Kutenholz",
    "sg:phone":"+49 4762/328",
    "sg:postcode":"27449",
    "sg:province":"Niedersachsen",
    "wof:name":"Heinrich L\u00f6h",
    "wof:placetype":"venue"
},
  "geometry": {"coordinates":[9.3177776337,53.481048584],"type":"Point"}
}