{
  "type": "Feature",
  "properties": {
    "iso:country":"DE",
    "sg:address":"Kirchstr. 16",
    "sg:city":"Hausen",
    "sg:phone":"+49 7424/2132",
    "sg:postcode":"78595",
    "sg:province":"Baden-W\u00fcrttemberg",
    "wof:name":"Ev. Pfarramt Hausen Ob Verena",
    "wof:placetype":"venue"
},
  "geometry": {"coordinates":[10.4844408035,48.1082725525],"type":"Point"}
}