{
  "type": "Feature",
  "properties": {
    "iso:country":"DE",
    "sg:address":"Carossaweg 15",
    "sg:city":"N\u00fcrnberg",
    "sg:phone":"+49 911/869658",
    "sg:postcode":"90471",
    "sg:province":"Bayern",
    "wof:name":"Craemer Spielwaren Handels Gmbh",
    "wof:placetype":"venue"
},
  "geometry": {"coordinates":[11.1257123947,49.4109916687],"type":"Point"}
}