{
  "type": "Feature",
  "properties": {
    "iso:country":"DE",
    "sg:address":"Krampnitzer Str. 11",
    "sg:city":"Potsdam",
    "sg:postcode":"14469",
    "sg:province":"Brandenburg",
    "wof:name":"Embassy The I-office Gmbh",
    "wof:placetype":"venue"
},
  "geometry": {"coordinates":[13.0911302567,52.4285469055],"type":"Point"}
}