{
  "type": "Feature",
  "properties": {
    "iso:country":"DE",
    "sg:address":"D\u00e4nnendiek 8",
    "sg:city":"Rhede",
    "sg:phone":"+49 2872/6159",
    "sg:postcode":"46414",
    "sg:province":"Nordrhein-Westfalen",
    "wof:name":"U. Buyting",
    "wof:placetype":"venue"
},
  "geometry": {"coordinates":[6.7010598183,51.833240509],"type":"Point"}
}