{
  "type": "Feature",
  "properties": {
    "iso:country":"DE",
    "sg:address":"Kleiner Moorweg 7",
    "sg:city":"Tornesch",
    "sg:phone":"+49 4122/95290",
    "sg:postcode":"25436",
    "sg:province":"Schleswig-Holstein",
    "wof:name":"Spangenberg Gmbh",
    "wof:placetype":"venue"
},
  "geometry": {"coordinates":[9.7274856567,53.6930885315],"type":"Point"}
}