{
  "type": "Feature",
  "properties": {
    "iso:country":"DE",
    "sg:address":"Mengstr. 4",
    "sg:city":"L\u00fcbeck",
    "sg:postcode":"23552",
    "sg:province":"Schleswig-Holstein",
    "wof:name":"Beteiligungsgesellschaft Mengstra\u00dfe 4 Mbh",
    "wof:placetype":"venue"
},
  "geometry": {"coordinates":[10.685978,53.868301],"type":"Point"}
}