{
  "type": "Feature",
  "properties": {
    "iso:country":"DE",
    "sg:address":"In der Schlo\u00dfdelle 1",
    "sg:city":"Spangenberg",
    "sg:phone":"+49 5663/493",
    "sg:postcode":"34286",
    "sg:province":"Hessen",
    "wof:name":"Heinz Eckhardt",
    "wof:placetype":"venue"
},
  "geometry": {"coordinates":[9.6651592255,51.1221733093],"type":"Point"}
}