{
  "type": "Feature",
  "properties": {
    "iso:country":"DE",
    "sg:address":"Auf der Heide 4",
    "sg:city":"Menslage",
    "sg:phone":"+49 5437/765",
    "sg:postcode":"49637",
    "sg:province":"Niedersachsen",
    "wof:name":"Horst B\u00f6hmer",
    "wof:placetype":"venue"
},
  "geometry": {"coordinates":[7.809839,52.666306],"type":"Point"}
}