{
  "type": "Feature",
  "properties": {
    "iso:country":"DE",
    "sg:address":"Benzstr. 22",
    "sg:city":"Pfullingen",
    "sg:phone":"+49 4971/2177525",
    "sg:postcode":"72793",
    "sg:province":"Baden-W\u00fcrttemberg",
    "wof:name":"Walter W\u00d6rner Gmbh & Co Kg",
    "wof:placetype":"venue"
},
  "geometry": {"coordinates":[9.225569,48.477085],"type":"Point"}
}