{
  "type": "Feature",
  "properties": {
    "iso:country":"DE",
    "sg:address":"Bahnhofstr. 11",
    "sg:city":"Ribnitz-Damgarten",
    "sg:phone":"+49 3821/87810",
    "sg:postcode":"18311",
    "sg:province":"Mecklenburg-Vorpommern",
    "wof:name":"Gebhard M\u00fcller Notar",
    "wof:placetype":"venue"
},
  "geometry": {"coordinates":[12.4379701614,54.2411499023],"type":"Point"}
}