{
  "type": "Feature",
  "properties": {
    "iso:country":"DE",
    "sg:address":"Nikolausberger Weg",
    "sg:city":"G\u00f6ttingen",
    "sg:phone":"+49 551/2011",
    "sg:postcode":"37073",
    "sg:province":"Niedersachsen",
    "wof:name":"Max-planck-institut F\u00fcr Biophysikalische Chemie",
    "wof:placetype":"venue"
},
  "geometry": {"coordinates":[9.9490852356,51.5428123474],"type":"Point"}
}