{
  "type": "Feature",
  "properties": {
    "iso:country":"DE",
    "sg:address":"Wellesweilerstr. 6",
    "sg:city":"Neunkirchen",
    "sg:postcode":"66538",
    "sg:province":"Saarland",
    "wof:name":"Saarland Versicherungen",
    "wof:placetype":"venue"
},
  "geometry": {"coordinates":[7.1760849953,49.3509788513],"type":"Point"}
}