{
  "type": "Feature",
  "properties": {
    "iso:country":"DE",
    "sg:address":"Braunschweiger Str. 21",
    "sg:city":"Peine",
    "sg:phone":"+49 5171/57155",
    "sg:postcode":"31226",
    "sg:province":"Niedersachsen",
    "wof:name":"Cafe Oriental",
    "wof:placetype":"venue"
},
  "geometry": {"coordinates":[10.233778,52.318077],"type":"Point"}
}