{
  "type": "Feature",
  "properties": {
    "iso:country":"DE",
    "sg:address":"Siebenmorgen 20",
    "sg:city":"Bergisch Gladbach",
    "sg:phone":"+49 2204/21820",
    "sg:postcode":"51427",
    "sg:province":"Nordrhein-Westfalen",
    "wof:name":"Skorpion",
    "wof:placetype":"venue"
},
  "geometry": {"coordinates":[7.117273,50.956211],"type":"Point"}
}