{
  "type": "Feature",
  "properties": {
    "iso:country":"DE",
    "sg:address":"Ermsstr. 10",
    "sg:city":"Metzingen",
    "sg:phone":"+49 7123/14124",
    "sg:postcode":"72555",
    "sg:province":"Baden-W\u00fcrttemberg",
    "wof:name":"Schreinerei Und Fensterbau K\u00f6nig Gmbh",
    "wof:placetype":"venue"
},
  "geometry": {"coordinates":[9.298094,48.531693],"type":"Point"}
}