{
  "type": "Feature",
  "properties": {
    "iso:country":"DE",
    "sg:address":"St.-Jobser-Str. 31",
    "sg:city":"W\u00fcrselen",
    "sg:phone":"+49 2405/48850",
    "sg:postcode":"52146",
    "sg:province":"Nordrhein-Westfalen",
    "wof:name":"Point Gesellschaft F\u00fcr Computertechnik Und",
    "wof:placetype":"venue"
},
  "geometry": {"coordinates":[6.1538357735,50.8104515076],"type":"Point"}
}