{
  "type": "Feature",
  "properties": {
    "iso:country":"DE",
    "sg:address":"Alsenzer Str. 5",
    "sg:city":"Schiersfeld",
    "sg:phone":"+49 6362/3247",
    "sg:postcode":"67823",
    "sg:province":"Rheinland-Pfalz",
    "wof:name":"O. Frohnh\u00f6fer",
    "wof:placetype":"venue"
},
  "geometry": {"coordinates":[7.7684822083,49.6938781738],"type":"Point"}
}