{
  "type": "Feature",
  "properties": {
    "iso:country":"DE",
    "sg:address":"Rheinstr. 15",
    "sg:city":"Oppenheim",
    "sg:phone":"+49 6133/2845",
    "sg:postcode":"55276",
    "sg:province":"Rheinland-Pfalz",
    "wof:name":"Johann Eckert",
    "wof:placetype":"venue"
},
  "geometry": {"coordinates":[8.3596048355,49.8560562134],"type":"Point"}
}