{
  "type": "Feature",
  "properties": {
    "iso:country":"DE",
    "sg:address":"Cloppenburger Str. 345",
    "sg:city":"Oldenburg",
    "sg:phone":"+49 441/43700",
    "sg:postcode":"26133",
    "sg:province":"Niedersachsen",
    "wof:name":"Sonnige Zeiten Sonnenstudio Gmbh",
    "wof:placetype":"venue"
},
  "geometry": {"coordinates":[8.210543,53.111221],"type":"Point"}
}