{
  "type": "Feature",
  "properties": {
    "iso:country":"DE",
    "sg:address":"Panzerstr. 12",
    "sg:city":"Hamburg",
    "sg:phone":"+49 40/867758",
    "sg:postcode":"22587",
    "sg:province":"Hamburg",
    "wof:name":"Seiler",
    "wof:placetype":"venue"
},
  "geometry": {"coordinates":[9.8196554184,53.5560417175],"type":"Point"}
}