{
  "type": "Feature",
  "properties": {
    "iso:country":"DE",
    "sg:address":"Mainburger Str. 19a",
    "sg:city":"Rudelzhausen",
    "sg:postcode":"84104",
    "sg:province":"Bayern",
    "wof:name":"Hbi-handels- Gmbh",
    "wof:placetype":"venue"
},
  "geometry": {"coordinates":[11.80240345,48.5826835632],"type":"Point"}
}