{
  "type": "Feature",
  "properties": {
    "iso:country":"DE",
    "sg:address":"Flurgasse 2",
    "sg:city":"K\u00f6nigswinter",
    "sg:phone":"+49 2223/911970",
    "sg:postcode":"53639",
    "sg:province":"Nordrhein-Westfalen",
    "wof:name":"Helmut Kentrup",
    "wof:placetype":"venue"
},
  "geometry": {"coordinates":[7.186532,50.700985],"type":"Point"}
}