{
  "type": "Feature",
  "properties": {
    "iso:country":"DE",
    "sg:address":"Langenstr. 14",
    "sg:city":"Bremen",
    "sg:postcode":"28195",
    "sg:province":"Bremen",
    "wof:name":"Tribus-treuhandges. Steuerberatungsges. Mbh",
    "wof:placetype":"venue"
},
  "geometry": {"coordinates":[8.8050127029,53.0763473511],"type":"Point"}
}