{
  "type": "Feature",
  "properties": {
    "iso:country":"DE",
    "sg:address":"Weyertshainstr. 44",
    "sg:city":"Netphen",
    "sg:postcode":"57250",
    "sg:province":"Nordrhein-Westfalen",
    "wof:name":"Hotel Und Objekt Design Gmbh",
    "wof:placetype":"venue"
},
  "geometry": {"coordinates":[8.0663738251,50.9129104614],"type":"Point"}
}