{
  "type": "Feature",
  "properties": {
    "iso:country":"DE",
    "sg:address":"Karlsbader Str. 5",
    "sg:city":"Herten",
    "sg:phone":"+49 2366/33967",
    "sg:postcode":"45699",
    "sg:province":"Nordrhein-Westfalen",
    "wof:name":"Hmi Industriemontagen Gmbh",
    "wof:placetype":"venue"
},
  "geometry": {"coordinates":[7.153996,51.60862],"type":"Point"}
}