{
  "type": "Feature",
  "properties": {
    "iso:country":"DE",
    "sg:address":"Kieler Str. 557",
    "sg:city":"Hamburg",
    "sg:phone":"+49 40/5403004",
    "sg:postcode":"22525",
    "sg:province":"Hamburg",
    "wof:name":"Tupperware",
    "wof:placetype":"venue"
},
  "geometry": {"coordinates":[9.9304246902,53.5907211304],"type":"Point"}
}