{
  "type": "Feature",
  "properties": {
    "iso:country":"DE",
    "sg:address":"Heinrich- Brauns- Weg",
    "sg:city":"Hildesheim",
    "sg:phone":"+49 5121/691588",
    "sg:postcode":"31141",
    "sg:province":"Niedersachsen",
    "wof:name":"Schrader Immobilien",
    "wof:placetype":"venue"
},
  "geometry": {"coordinates":[9.9883899689,52.1192207336],"type":"Point"}
}