{
  "type": "Feature",
  "properties": {
    "iso:country":"DE",
    "sg:address":"Eichendorffstr. 26",
    "sg:city":"Oberursel",
    "sg:phone":"+49 6171/209050",
    "sg:postcode":"61440",
    "sg:province":"Hessen",
    "wof:name":"Ifl Institut F\u00fcr Logistikberatung Gmbh",
    "wof:placetype":"venue"
},
  "geometry": {"coordinates":[8.5571022034,50.2094764709],"type":"Point"}
}