{
  "type": "Feature",
  "properties": {
    "iso:country":"DE",
    "sg:address":"Friedensallee 2",
    "sg:city":"Rangsdorf",
    "sg:phone":"+49 33708/20220",
    "sg:postcode":"15834",
    "sg:province":"Brandenburg",
    "wof:name":"Balk",
    "wof:placetype":"venue"
},
  "geometry": {"coordinates":[13.417839,52.292294],"type":"Point"}
}