{
  "type": "Feature",
  "properties": {
    "iso:country":"DE",
    "sg:address":"M\u00fchlenstr. 11-17",
    "sg:city":"Uelzen",
    "sg:postcode":"29525",
    "sg:province":"Niedersachsen",
    "wof:name":"United-company Corporate Services Gmbh",
    "wof:placetype":"venue"
},
  "geometry": {"coordinates":[10.562433,52.963848],"type":"Point"}
}