{
  "type": "Feature",
  "properties": {
    "iso:country":"DE",
    "sg:address":"Broicherdorfstr. 85 a",
    "sg:city":"Kaarst",
    "sg:postcode":"41564",
    "sg:province":"Nordrhein-Westfalen",
    "wof:name":"Lunar It-systems Gmbh",
    "wof:placetype":"venue"
},
  "geometry": {"coordinates":[6.5962109566,51.2316322327],"type":"Point"}
}