{
  "type": "Feature",
  "properties": {
    "iso:country":"DE",
    "sg:address":"Bahnhofstr. 22",
    "sg:city":"Dillenburg",
    "sg:phone":"+49 2771/81141",
    "sg:postcode":"35684",
    "sg:province":"Hessen",
    "wof:name":"Gute Botschaft Verlag",
    "wof:placetype":"venue"
},
  "geometry": {"coordinates":[8.3039808273,50.7719535828],"type":"Point"}
}