{
  "type": "Feature",
  "properties": {
    "iso:country":"DE",
    "sg:address":"Pfarrer-Heidbreder-Str.3",
    "sg:city":"Greven",
    "sg:phone":"+49 2575/3914",
    "sg:postcode":"48268",
    "sg:province":"Nordrhein-Westfalen",
    "wof:name":"Rederij Zoutkamp",
    "wof:placetype":"venue"
},
  "geometry": {"coordinates":[7.553057,52.127731],"type":"Point"}
}