{
  "type": "Feature",
  "properties": {
    "iso:country":"DE",
    "sg:address":"Helenenstr. 180",
    "sg:city":"Essen",
    "sg:phone":"+49 201/86246",
    "sg:postcode":"45143",
    "sg:province":"Nordrhein-Westfalen",
    "wof:name":"R & T Entsorgung Gmbh",
    "wof:placetype":"venue"
},
  "geometry": {"coordinates":[6.987434864,51.472240448],"type":"Point"}
}