{
  "type": "Feature",
  "properties": {
    "iso:country":"DE",
    "sg:address":"Gottfried-Keller-Str. 10",
    "sg:city":"Heilbronn",
    "sg:phone":"+49 7131/177219",
    "sg:postcode":"74076",
    "sg:province":"Baden-W\u00fcrttemberg",
    "wof:name":"U. Baumann Ingenieur",
    "wof:placetype":"venue"
},
  "geometry": {"coordinates":[9.2260770798,49.15391922],"type":"Point"}
}