{
  "type": "Feature",
  "properties": {
    "iso:country":"DE",
    "sg:address":"Ostendstr. 3",
    "sg:city":"Obertshausen",
    "sg:phone":"+49 6104/44593",
    "sg:postcode":"63179",
    "sg:province":"Hessen",
    "wof:name":"Christa Ziegler-neumann",
    "wof:placetype":"venue"
},
  "geometry": {"coordinates":[8.8541135788,50.0741157532],"type":"Point"}
}