{
  "type": "Feature",
  "properties": {
    "iso:country":"DE",
    "sg:address":"Rathausstr. 16",
    "sg:city":"Lippstadt",
    "sg:phone":"+49 2941/59682",
    "sg:postcode":"59555",
    "sg:province":"Nordrhein-Westfalen",
    "wof:name":"China Restaurant Hongkong",
    "wof:placetype":"venue"
},
  "geometry": {"coordinates":[8.3442602158,51.6754493713],"type":"Point"}
}