{
  "type": "Feature",
  "properties": {
    "iso:country":"DE",
    "sg:address":"Haslacher Str. 4",
    "sg:city":"Traunstein",
    "sg:phone":"+49 861/60094",
    "sg:postcode":"83278",
    "sg:province":"Bayern",
    "wof:name":"Rudolf Lechner Architekt",
    "wof:placetype":"venue"
},
  "geometry": {"coordinates":[12.643068,47.866554],"type":"Point"}
}