{
  "type": "Feature",
  "properties": {
    "iso:country":"DE",
    "sg:address":"Bischofstr. 95",
    "sg:city":"Krefeld",
    "sg:phone":"+49 2151/540004",
    "sg:postcode":"47809",
    "sg:province":"Nordrhein-Westfalen",
    "wof:name":"B\u00f6ker & Schwetzel Gmbh",
    "wof:placetype":"venue"
},
  "geometry": {"coordinates":[6.6234240532,51.3275184631],"type":"Point"}
}