{
  "type": "Feature",
  "properties": {
    "iso:country":"DE",
    "sg:address":"G\u00f6teborger Str. 2",
    "sg:city":"Leipzig",
    "sg:phone":"+49 341/9213888",
    "sg:postcode":"04349",
    "sg:province":"Sachsen",
    "wof:name":"Manfred Russler",
    "wof:placetype":"venue"
},
  "geometry": {"coordinates":[12.4349327087,51.3803367615],"type":"Point"}
}