{
  "type": "Feature",
  "properties": {
    "iso:country":"DE",
    "sg:address":"Aachener Str. 18",
    "sg:city":"Kall",
    "sg:phone":"+49 2441/4309",
    "sg:postcode":"53925",
    "sg:province":"Nordrhein-Westfalen",
    "wof:name":"Rolf Esser",
    "wof:placetype":"venue"
},
  "geometry": {"coordinates":[6.5565738678,50.5412597656],"type":"Point"}
}