{
  "type": "Feature",
  "properties": {
    "iso:country":"DE",
    "sg:address":"Lindenallee 30",
    "sg:city":"Remscheid",
    "sg:phone":"+49 2191/973601",
    "sg:postcode":"42899",
    "sg:province":"Nordrhein-Westfalen",
    "wof:name":"C. Ern",
    "wof:placetype":"venue"
},
  "geometry": {"coordinates":[7.2428240776,51.2086791992],"type":"Point"}
}