{
  "type": "Feature",
  "properties": {
    "iso:country":"DE",
    "sg:address":"Rebhalde 2",
    "sg:city":"Zell",
    "sg:phone":"+49 7835/5386",
    "sg:postcode":"77736",
    "sg:province":"Baden-W\u00fcrttemberg",
    "wof:name":"Hiller Stuhl- Und Tischfabrik Gmbh",
    "wof:placetype":"venue"
},
  "geometry": {"coordinates":[8.0848503113,48.3530540466],"type":"Point"}
}