{
  "type": "Feature",
  "properties": {
    "iso:country":"DE",
    "sg:address":"Mexikoring 33",
    "sg:city":"Hamburg",
    "sg:phone":"+49 40/6327920",
    "sg:postcode":"22297",
    "sg:province":"Hamburg",
    "wof:name":"I. Emsheimer Ingenieur",
    "wof:placetype":"venue"
},
  "geometry": {"coordinates":[10.0237407684,53.6043739319],"type":"Point"}
}