{
  "type": "Feature",
  "properties": {
    "iso:country":"DE",
    "sg:address":"Asperger Str. 39",
    "sg:city":"Ludwigsburg",
    "sg:postcode":"71634",
    "sg:province":"Baden-W\u00fcrttemberg",
    "wof:name":"As Share Management Gmbh",
    "wof:placetype":"venue"
},
  "geometry": {"coordinates":[9.1848917007,48.897151947],"type":"Point"}
}