{
  "type": "Feature",
  "properties": {
    "iso:country":"DE",
    "sg:address":"M\u00fchlweg 41",
    "sg:city":"R\u00fcckersdorf",
    "sg:phone":"+49 911/579999",
    "sg:postcode":"90607",
    "sg:province":"Bayern",
    "wof:name":"Gerhard Bezold",
    "wof:placetype":"venue"
},
  "geometry": {"coordinates":[11.2383756638,49.4914245605],"type":"Point"}
}