{
  "type": "Feature",
  "properties": {
    "iso:country":"DE",
    "sg:address":"Fischerrain 2",
    "sg:city":"Schweinfurt",
    "sg:phone":"+49 9721/20910",
    "sg:postcode":"97421",
    "sg:province":"Bayern",
    "wof:name":"Bfg Bank",
    "wof:placetype":"venue"
},
  "geometry": {"coordinates":[10.232142,50.043102],"type":"Point"}
}