{
  "type": "Feature",
  "properties": {
    "iso:country":"DE",
    "sg:address":"Am Unterwege 7",
    "sg:city":"S\u00f6mmerda",
    "sg:phone":"+49 3634/692656",
    "sg:postcode":"99610",
    "sg:province":"Th\u00fcringen",
    "wof:name":"Vemas Gmbh",
    "wof:placetype":"venue"
},
  "geometry": {"coordinates":[11.128675,51.172215],"type":"Point"}
}