{
  "type": "Feature",
  "properties": {
    "iso:country":"DE",
    "sg:address":"Xaver-Fuhr-Str. 101",
    "sg:city":"Mannheim",
    "sg:phone":"+49 621/445090",
    "sg:postcode":"68163",
    "sg:province":"Baden-W\u00fcrttemberg",
    "wof:name":"Mannheimer Weihnachtsmarkt Gmbh",
    "wof:placetype":"venue"
},
  "geometry": {"coordinates":[8.522682,49.469292],"type":"Point"}
}