{
  "type": "Feature",
  "properties": {
    "iso:country":"DE",
    "sg:address":"Heideweg 14",
    "sg:city":"Buxtehude",
    "sg:phone":"+49 4161/81610",
    "sg:postcode":"21614",
    "sg:province":"Niedersachsen",
    "wof:name":"J\u00fcrgen M\u00f6ller",
    "wof:placetype":"venue"
},
  "geometry": {"coordinates":[9.662589,53.448483],"type":"Point"}
}