{
  "type": "Feature",
  "properties": {
    "iso:country":"DE",
    "sg:address":"Weseler Str. 31",
    "sg:city":"Haltern",
    "sg:phone":"+49 2364/3744",
    "sg:postcode":"45721",
    "sg:province":"Nordrhein-Westfalen",
    "wof:name":"Halterner Stube",
    "wof:placetype":"venue"
},
  "geometry": {"coordinates":[7.1807899475,51.7432098389],"type":"Point"}
}