{
  "type": "Feature",
  "properties": {
    "iso:country":"DE",
    "sg:address":"Roggenbachstr. 16 a",
    "sg:city":"Schopfheim",
    "sg:phone":"+49 7622/669477",
    "sg:postcode":"79650",
    "sg:province":"Baden-W\u00fcrttemberg",
    "wof:name":"Sport Albrecht Inh. J. Albrecht",
    "wof:placetype":"venue"
},
  "geometry": {"coordinates":[7.828151,47.651058],"type":"Point"}
}