{
  "type": "Feature",
  "properties": {
    "iso:country":"DE",
    "sg:address":"Pfaffen\u00e4ckerweg 10",
    "sg:city":"M\u00f6gglingen",
    "sg:phone":"+49 7174/6716",
    "sg:postcode":"73563",
    "sg:province":"Baden-W\u00fcrttemberg",
    "wof:name":"Monika Und M. Gekeler",
    "wof:placetype":"venue"
},
  "geometry": {"coordinates":[9.9630613327,48.8177452087],"type":"Point"}
}