{
  "type": "Feature",
  "properties": {
    "iso:country":"DE",
    "sg:address":"Wintgensstr. 85-87",
    "sg:city":"Duisburg",
    "sg:phone":"+49 203/373365",
    "sg:postcode":"47058",
    "sg:province":"Nordrhein-Westfalen",
    "wof:name":"Fenster Becker Gmbh",
    "wof:placetype":"venue"
},
  "geometry": {"coordinates":[6.788561,51.441624],"type":"Point"}
}