{
  "type": "Feature",
  "properties": {
    "iso:country":"DE",
    "sg:address":"Wilsdruffer Str. 25",
    "sg:city":"Freital",
    "sg:phone":"+49 351/648810",
    "sg:postcode":"01705",
    "sg:province":"Sachsen",
    "wof:name":"Ziegelwerk Waschneck Gmbh",
    "wof:placetype":"venue"
},
  "geometry": {"coordinates":[13.6500205994,51.0126495361],"type":"Point"}
}