{
  "type": "Feature",
  "properties": {
    "iso:country":"DE",
    "sg:address":"Mannheimer Str. 4",
    "sg:city":"Schriesheim",
    "sg:phone":"+49 6203/692433",
    "sg:postcode":"69198",
    "sg:province":"Baden-W\u00fcrttemberg",
    "wof:name":"Dalmolin",
    "wof:placetype":"venue"
},
  "geometry": {"coordinates":[8.658512,49.47377],"type":"Point"}
}