{
  "type": "Feature",
  "properties": {
    "iso:country":"DE",
    "sg:address":"Kohlberg",
    "sg:city":"Kohlberg",
    "sg:phone":"+49 9608/400",
    "sg:postcode":"92702",
    "sg:province":"Bayern",
    "wof:name":"Sparkasse",
    "wof:placetype":"venue"
},
  "geometry": {"coordinates":[12.018461,49.592113],"type":"Point"}
}