{
  "type": "Feature",
  "properties": {
    "iso:country":"DE",
    "sg:address":"Ahornweg 6",
    "sg:city":"Sulingen",
    "sg:phone":"+49 4271/1590",
    "sg:postcode":"27232",
    "sg:province":"Niedersachsen",
    "wof:name":"Helmut Schmidt",
    "wof:placetype":"venue"
},
  "geometry": {"coordinates":[8.8258037567,52.6829681396],"type":"Point"}
}