{
  "type": "Feature",
  "properties": {
    "iso:country":"DE",
    "sg:address":"Bahnhofstr. 24 a",
    "sg:city":"Wasungen",
    "sg:phone":"+49 36941/71281",
    "sg:postcode":"98634",
    "sg:province":"Th\u00fcringen",
    "wof:name":"Bautro Bauunternehmung Gmbh",
    "wof:placetype":"venue"
},
  "geometry": {"coordinates":[10.361034,50.662724],"type":"Point"}
}