{
  "type": "Feature",
  "properties": {
    "iso:country":"DE",
    "sg:address":"Robert-Bosch-Str. 19",
    "sg:city":"Mainz",
    "sg:phone":"+49 6131/507740",
    "sg:postcode":"55129",
    "sg:province":"Rheinland-Pfalz",
    "wof:name":"Kago-kamine-kachelofen Gmbh & Co.-deutsche",
    "wof:placetype":"venue"
},
  "geometry": {"coordinates":[8.2591133118,49.9586601257],"type":"Point"}
}