{
  "type": "Feature",
  "properties": {
    "iso:country":"DE",
    "sg:address":"Danziger Str. 34",
    "sg:city":"K\u00f6ln",
    "sg:postcode":"50858",
    "sg:province":"Nordrhein-Westfalen",
    "wof:name":"Parkett Dietrich Gmbh",
    "wof:placetype":"venue"
},
  "geometry": {"coordinates":[6.8375558853,50.9370727539],"type":"Point"}
}