{
  "type": "Feature",
  "properties": {
    "iso:country":"DE",
    "sg:address":"Am Stadtpark 59",
    "sg:city":"M\u00fcnchen",
    "sg:phone":"+49 89/54662244",
    "sg:postcode":"81243",
    "sg:province":"Bayern",
    "wof:name":"Albema Beteiligungs Gmbh",
    "wof:placetype":"venue"
},
  "geometry": {"coordinates":[11.448669,48.135151],"type":"Point"}
}