{
  "type": "Feature",
  "properties": {
    "iso:country":"DE",
    "sg:address":"Reitgaarstr. 1-3",
    "sg:city":"Neuenhaus",
    "sg:phone":"+49 5941/1097",
    "sg:postcode":"49828",
    "sg:province":"Niedersachsen",
    "wof:name":"Dietrich Borggreve Zwieback- U. Keksfabrik Kg",
    "wof:placetype":"venue"
},
  "geometry": {"coordinates":[6.991456,52.479279],"type":"Point"}
}