{
  "type": "Feature",
  "properties": {
    "iso:country":"DE",
    "sg:address":"Siemensstr. 22",
    "sg:city":"Keltern",
    "sg:phone":"+49 7236/980053",
    "sg:postcode":"75210",
    "sg:province":"Baden-W\u00fcrttemberg",
    "wof:name":"Ludwig O\u00dfwald",
    "wof:placetype":"venue"
},
  "geometry": {"coordinates":[8.614918,48.890816],"type":"Point"}
}