{
  "type": "Feature",
  "properties": {
    "iso:country":"DE",
    "sg:address":"Neue Str. 10",
    "sg:city":"Bodenfelde",
    "sg:phone":"+49 5572/7625",
    "sg:postcode":"37194",
    "sg:province":"Hessen",
    "wof:name":"Pension D\u00f6rnte",
    "wof:placetype":"venue"
},
  "geometry": {"coordinates":[9.5549173355,51.6392364502],"type":"Point"}
}