{
  "type": "Feature",
  "properties": {
    "iso:country":"DE",
    "sg:address":"Gereonstr. 83",
    "sg:city":"Vettwei\u00df",
    "sg:phone":"+49 2424/7138",
    "sg:postcode":"52391",
    "sg:province":"Nordrhein-Westfalen",
    "wof:name":"Peter Peetz",
    "wof:placetype":"venue"
},
  "geometry": {"coordinates":[6.5972480774,50.7376022339],"type":"Point"}
}