{
  "type": "Feature",
  "properties": {
    "iso:country":"DE",
    "sg:address":"Bombergstr. 43",
    "sg:city":"Schieder-Schwalenberg",
    "sg:phone":"+49 5233/8128",
    "sg:postcode":"32816",
    "sg:province":"Nordrhein-Westfalen",
    "wof:name":"Heinz Runte",
    "wof:placetype":"venue"
},
  "geometry": {"coordinates":[9.147673,51.876408],"type":"Point"}
}