{
  "type": "Feature",
  "properties": {
    "iso:country":"DE",
    "sg:address":"An der Trift 1b",
    "sg:city":"Bad Wilsnack",
    "sg:phone":"+49 38791/2200",
    "sg:postcode":"19336",
    "sg:province":"Brandenburg",
    "wof:name":"Dr. Med. Rainer Vetter Arzt F\u00fcr Allgemeinmedizin",
    "wof:placetype":"venue"
},
  "geometry": {"coordinates":[11.9494104385,52.9522895813],"type":"Point"}
}