{
  "type": "Feature",
  "properties": {
    "iso:country":"DE",
    "sg:address":"Lehnstr. 10 a",
    "sg:city":"Kirchbrak",
    "sg:phone":"+49 5533/4970",
    "sg:postcode":"37619",
    "sg:province":"Niedersachsen",
    "wof:name":"G\u00fcnter Meier Gmbh",
    "wof:placetype":"venue"
},
  "geometry": {"coordinates":[9.57151,51.963921],"type":"Point"}
}