{
  "type": "Feature",
  "properties": {
    "iso:country":"DE",
    "sg:address":"Ewald-Dutschke-Str. 22",
    "sg:city":"Essen",
    "sg:phone":"+49 201/664767",
    "sg:postcode":"45357",
    "sg:province":"Nordrhein-Westfalen",
    "wof:name":"Ristorante Rizzo",
    "wof:placetype":"venue"
},
  "geometry": {"coordinates":[6.9391279221,51.4882621765],"type":"Point"}
}