{
  "type": "Feature",
  "properties": {
    "iso:country":"DE",
    "sg:address":"B\u00e4renstr. 6",
    "sg:city":"Stuttgart",
    "sg:phone":"+49 711/2364640",
    "sg:postcode":"70173",
    "sg:province":"Baden-W\u00fcrttemberg",
    "wof:name":"Modeinsel J. Klonner",
    "wof:placetype":"venue"
},
  "geometry": {"coordinates":[9.178618,48.775764],"type":"Point"}
}