{
  "type": "Feature",
  "properties": {
    "iso:country":"DE",
    "sg:address":"Autenbachstr. 15::",
    "sg:city":"G\u00f6ppingen",
    "sg:phone":"+49 7161/940330",
    "sg:postcode":"73035",
    "sg:province":"Baden-W\u00fcrttemberg",
    "wof:name":"Walter Schiller Gmbh Wirtschaftspruefungsges Steuerberatungsges",
    "wof:placetype":"venue"
},
  "geometry": {"coordinates":[9.629323,48.69162],"type":"Point"}
}