{
  "type": "Feature",
  "properties": {
    "iso:country":"DE",
    "sg:address":"Birkenstr. 10",
    "sg:city":"Aachen",
    "sg:phone":"+49 241/525941",
    "sg:postcode":"52078",
    "sg:province":"Nordrhein-Westfalen",
    "wof:name":"Johannes Lubos Maschinen- Und Formenbau Gmbh",
    "wof:placetype":"venue"
},
  "geometry": {"coordinates":[6.186451,50.754089],"type":"Point"}
}