{
  "type": "Feature",
  "properties": {
    "iso:country":"DE",
    "sg:address":"Severinsweg 23a",
    "sg:city":"Heinsberg",
    "sg:phone":"+49 2452/7781",
    "sg:postcode":"52525",
    "sg:province":"Nordrhein-Westfalen",
    "wof:name":"P. Lopacki",
    "wof:placetype":"venue"
},
  "geometry": {"coordinates":[6.07628,51.10569],"type":"Point"}
}