{
  "type": "Feature",
  "properties": {
    "iso:country":"DE",
    "sg:address":"Vor dem Steintor 45",
    "sg:city":"Bremen",
    "sg:phone":"+49 421/705733",
    "sg:postcode":"28203",
    "sg:province":"Bremen",
    "wof:name":"\u00d6ger-t\u00fcrk Tur Gmbh",
    "wof:placetype":"venue"
},
  "geometry": {"coordinates":[8.8260250092,53.0728530884],"type":"Point"}
}