{
  "type": "Feature",
  "properties": {
    "iso:country":"DE",
    "sg:address":"Industriestr. 2",
    "sg:city":"Flieden",
    "sg:phone":"+49 6655/96030",
    "sg:postcode":"36103",
    "sg:province":"Hessen",
    "wof:name":"Metzgerei Robert M\u00fcller Gmbh",
    "wof:placetype":"venue"
},
  "geometry": {"coordinates":[9.5748529434,50.4020614624],"type":"Point"}
}