{
  "type": "Feature",
  "properties": {
    "iso:country":"DE",
    "sg:address":"Von-Ketteler-Str. 111-113",
    "sg:city":"Leverkusen",
    "sg:phone":"+49 4921/464351",
    "sg:postcode":"51371",
    "sg:province":"Nordrhein-Westfalen",
    "wof:name":"Stuettgen Frischm\u00c4rkte Gmbh",
    "wof:placetype":"venue"
},
  "geometry": {"coordinates":[6.980035,51.047916],"type":"Point"}
}