{
  "type": "Feature",
  "properties": {
    "iso:country":"DE",
    "sg:address":"Stadionring 11 a",
    "sg:city":"Ratingen",
    "sg:phone":"+49 2102/24001",
    "sg:postcode":"40878",
    "sg:province":"Nordrhein-Westfalen",
    "wof:name":"Rudersdorf",
    "wof:placetype":"venue"
},
  "geometry": {"coordinates":[6.8399620056,51.2979011536],"type":"Point"}
}