{
  "type": "Feature",
  "properties": {
    "iso:country":"DE",
    "sg:address":"Adenauerstr. 106",
    "sg:city":"Mandelbachtal",
    "sg:postcode":"66399",
    "sg:province":"Saarland",
    "wof:name":"W-system Ag",
    "wof:placetype":"venue"
},
  "geometry": {"coordinates":[7.1249499321,49.1931190491],"type":"Point"}
}