{
  "type": "Feature",
  "properties": {
    "iso:country":"DE",
    "sg:address":"Burgstr. 99",
    "sg:city":"Schifferstadt",
    "sg:phone":"+49 6235/929040",
    "sg:postcode":"67105",
    "sg:province":"Rheinland-Pfalz",
    "wof:name":"Praxis Dr. Eckrich Und Dr. Schwarzmann",
    "wof:placetype":"venue"
},
  "geometry": {"coordinates":[8.3738708496,49.3793945312],"type":"Point"}
}