{
  "type": "Feature",
  "properties": {
    "iso:country":"DE",
    "sg:address":"Dorfstr. 13",
    "sg:city":"Oldenswort",
    "sg:phone":"+49 4864/898",
    "sg:postcode":"25870",
    "sg:province":"Schleswig-Holstein",
    "wof:name":"H.-h. Sass",
    "wof:placetype":"venue"
},
  "geometry": {"coordinates":[8.943158,54.372837],"type":"Point"}
}