{
  "type": "Feature",
  "properties": {
    "iso:country":"DE",
    "sg:address":"Barbaraweg 27",
    "sg:city":"Griesheim",
    "sg:phone":"+49 6155",
    "sg:postcode":"64347",
    "sg:province":"Hessen",
    "wof:name":"Telekommunikation Gie\u00df",
    "wof:placetype":"venue"
},
  "geometry": {"coordinates":[8.560442,49.85445],"type":"Point"}
}