{
  "type": "Feature",
  "properties": {
    "iso:country":"DE",
    "sg:address":"Hochstr. 32",
    "sg:city":"Nettetal",
    "sg:phone":"+49 2153/2263",
    "sg:postcode":"41334",
    "sg:province":"Nordrhein-Westfalen",
    "wof:name":"Ferdinand Pickers",
    "wof:placetype":"venue"
},
  "geometry": {"coordinates":[6.2760820389,51.3065719604],"type":"Point"}
}