{
  "type": "Feature",
  "properties": {
    "iso:country":"DE",
    "sg:address":"Brehmstr. 10",
    "sg:city":"Remscheid",
    "sg:phone":"+49 2191/963185",
    "sg:postcode":"42897",
    "sg:province":"Nordrhein-Westfalen",
    "wof:name":"Peter Kolfertz Rechtsanwalt",
    "wof:placetype":"venue"
},
  "geometry": {"coordinates":[7.2656707764,51.1913604736],"type":"Point"}
}