{
  "type": "Feature",
  "properties": {
    "iso:country":"DE",
    "sg:address":"Neum\u00fchle 1",
    "sg:city":"Glash\u00fctten",
    "sg:phone":"+49 6174/964712",
    "sg:postcode":"61479",
    "sg:province":"Hessen",
    "wof:name":"Kommunikations- Und Daten-technik",
    "wof:placetype":"venue"
},
  "geometry": {"coordinates":[8.391373,50.19215],"type":"Point"}
}