{
  "type": "Feature",
  "properties": {
    "iso:country":"DE",
    "sg:address":"Talstr. 1",
    "sg:city":"Geraberg",
    "sg:phone":"+49 3677/797522",
    "sg:postcode":"98716",
    "sg:province":"Th\u00fcringen",
    "wof:name":"Wolfgang Koch Anlageberater",
    "wof:placetype":"venue"
},
  "geometry": {"coordinates":[10.8496179581,50.7217292786],"type":"Point"}
}