{
  "type": "Feature",
  "properties": {
    "iso:country":"DE",
    "sg:address":"Lanterstr. 54",
    "sg:city":"Essen",
    "sg:phone":"+49 201/262627",
    "sg:postcode":"45136",
    "sg:province":"Nordrhein-Westfalen",
    "wof:name":"Zum Schwan",
    "wof:placetype":"venue"
},
  "geometry": {"coordinates":[7.0492401123,51.4414825439],"type":"Point"}
}