{
  "type": "Feature",
  "properties": {
    "iso:country":"DE",
    "sg:address":"Bookenbusch 22",
    "sg:city":"Ahaus",
    "sg:phone":"+49 2567/627",
    "sg:postcode":"48683",
    "sg:province":"Nordrhein-Westfalen",
    "wof:name":"Hausbau Winter Gmbh",
    "wof:placetype":"venue"
},
  "geometry": {"coordinates":[6.911561,52.125229],"type":"Point"}
}