{
  "type": "Feature",
  "properties": {
    "iso:country":"DE",
    "sg:address":"Koblenzer Str. 47",
    "sg:city":"Bingen",
    "sg:phone":"+49 6721/32837",
    "sg:postcode":"55411",
    "sg:province":"Rheinland-Pfalz",
    "wof:name":"Gert Dietz Rechtsanwalt",
    "wof:placetype":"venue"
},
  "geometry": {"coordinates":[7.8856577873,49.9667778015],"type":"Point"}
}