{
  "type": "Feature",
  "properties": {
    "iso:country":"DE",
    "sg:address":"Neuendorfer Str. 22",
    "sg:city":"Ueckerm\u00fcnde",
    "sg:phone":"+49 39771/27802",
    "sg:postcode":"17373",
    "sg:province":"Mecklenburg-Vorpommern",
    "wof:name":"Ingo L\u00fcbeck",
    "wof:placetype":"venue"
},
  "geometry": {"coordinates":[14.0745353699,53.7433662415],"type":"Point"}
}