{
  "type": "Feature",
  "properties": {
    "iso:country":"DE",
    "sg:address":"Petersfelder Str. 8",
    "sg:city":"Garrel",
    "sg:phone":"+49 4474/407",
    "sg:postcode":"49681",
    "sg:province":"Niedersachsen",
    "wof:name":"Heinrich Thole",
    "wof:placetype":"venue"
},
  "geometry": {"coordinates":[8.0216932297,52.9552764893],"type":"Point"}
}