{
  "type": "Feature",
  "properties": {
    "iso:country":"DE",
    "sg:address":"Drosselweg 6",
    "sg:city":"Oerlinghausen",
    "sg:phone":"+49 5202/71830",
    "sg:postcode":"33813",
    "sg:province":"Nordrhein-Westfalen",
    "wof:name":"Regina Dohle Architekten",
    "wof:placetype":"venue"
},
  "geometry": {"coordinates":[8.628533,51.934048],"type":"Point"}
}