{
  "type": "Feature",
  "properties": {
    "iso:country":"DE",
    "sg:address":"Steinstr. 15",
    "sg:city":"Viernheim",
    "sg:phone":"+49 6204/2795",
    "sg:postcode":"68519",
    "sg:province":"Hessen",
    "wof:name":"K. Lantz",
    "wof:placetype":"venue"
},
  "geometry": {"coordinates":[8.575644,49.532566],"type":"Point"}
}