{
  "type": "Feature",
  "properties": {
    "iso:country":"DE",
    "sg:address":"Wiesbadener Str. 1",
    "sg:city":"Essen",
    "sg:postcode":"45145",
    "sg:province":"Nordrhein-Westfalen",
    "wof:name":"Enigma Software Gmbh",
    "wof:placetype":"venue"
},
  "geometry": {"coordinates":[6.9685630798,51.4429931641],"type":"Point"}
}