{
  "type": "Feature",
  "properties": {
    "iso:country":"DE",
    "sg:address":"Lange Str. 54",
    "sg:city":"Dransfeld",
    "sg:phone":"+49 5502/3600",
    "sg:postcode":"37127",
    "sg:province":"Niedersachsen",
    "wof:name":"Eiscafe Venezia",
    "wof:placetype":"venue"
},
  "geometry": {"coordinates":[9.761135,51.502502],"type":"Point"}
}