{
  "type": "Feature",
  "properties": {
    "iso:country":"DE",
    "sg:address":"Brunhildestr. 38",
    "sg:city":"Bad Oeynhausen",
    "sg:phone":"+49 5732/3579",
    "sg:postcode":"32547",
    "sg:province":"Nordrhein-Westfalen",
    "wof:name":"Walter Junggebauer",
    "wof:placetype":"venue"
},
  "geometry": {"coordinates":[8.815815,52.19701],"type":"Point"}
}