{
  "type": "Feature",
  "properties": {
    "iso:country":"DE",
    "sg:address":"Olpe 35",
    "sg:city":"Dortmund",
    "sg:phone":"+49 231/54090",
    "sg:postcode":"44135",
    "sg:province":"Nordrhein-Westfalen",
    "wof:name":"Evangelisches Erwachsenenbildungswerk",
    "wof:placetype":"venue"
},
  "geometry": {"coordinates":[7.4710869789,51.5125007629],"type":"Point"}
}