{
  "type": "Feature",
  "properties": {
    "iso:country":"DE",
    "sg:address":"Schulstr. 22",
    "sg:city":"Kleinbundenbach",
    "sg:phone":"+49 6337/711",
    "sg:postcode":"66501",
    "sg:province":"Rheinland-Pfalz",
    "wof:name":"Aloys Kunz",
    "wof:placetype":"venue"
},
  "geometry": {"coordinates":[7.442867,49.309101],"type":"Point"}
}