{
  "type": "Feature",
  "properties": {
    "iso:country":"DE",
    "sg:address":"Am Fuchsloch",
    "sg:city":"Mochau",
    "sg:phone":"+49 3431/611627",
    "sg:postcode":"04720",
    "sg:province":"Sachsen",
    "wof:name":"Trus Transport & Umschlag Gmbh",
    "wof:placetype":"venue"
},
  "geometry": {"coordinates":[13.1789169312,51.1144485474],"type":"Point"}
}