{
  "type": "Feature",
  "properties": {
    "iso:country":"DE",
    "sg:address":"Dorfstr. 15",
    "sg:city":"Sch\u00f6neiche",
    "sg:postcode":"15566",
    "sg:province":"Brandenburg",
    "wof:name":"Woltersdorfer Stra\u00dfenbahn Gmbh",
    "wof:placetype":"venue"
},
  "geometry": {"coordinates":[12.91929245,51.7488136292],"type":"Point"}
}