{
  "type": "Feature",
  "properties": {
    "iso:country":"DE",
    "sg:address":"Adalbertsteinweg 1",
    "sg:city":"Aachen",
    "sg:phone":"+49 241/504934",
    "sg:postcode":"52070",
    "sg:province":"Nordrhein-Westfalen",
    "wof:name":"M. Mohr Rechtsanwalt",
    "wof:placetype":"venue"
},
  "geometry": {"coordinates":[6.0967350006,50.7747344971],"type":"Point"}
}