{
  "type": "Feature",
  "properties": {
    "iso:country":"DE",
    "sg:address":"Warngauer Str. 47",
    "sg:city":"M\u00fcnchen",
    "sg:phone":"+49 89/620690",
    "sg:postcode":"81539",
    "sg:province":"Bayern",
    "wof:name":"Versicherungskammer Bayern",
    "wof:placetype":"venue"
},
  "geometry": {"coordinates":[11.5909986496,48.1132965088],"type":"Point"}
}