{
  "type": "Feature",
  "properties": {
    "iso:country":"DE",
    "sg:address":"Elisabethstr. 88",
    "sg:city":"Kiel",
    "sg:phone":"+49 431/9719455",
    "sg:postcode":"24143",
    "sg:province":"Schleswig-Holstein",
    "wof:name":"Kammerer Masseur",
    "wof:placetype":"venue"
},
  "geometry": {"coordinates":[10.144923,54.309982],"type":"Point"}
}