{
  "type": "Feature",
  "properties": {
    "iso:country":"DE",
    "sg:address":"Hochstr. 22",
    "sg:city":"Altena",
    "sg:phone":"+49 2352/71957",
    "sg:postcode":"58762",
    "sg:province":"Nordrhein-Westfalen",
    "wof:name":"Michaela Giebelhausen",
    "wof:placetype":"venue"
},
  "geometry": {"coordinates":[7.755032,51.302284],"type":"Point"}
}