{
  "type": "Feature",
  "properties": {
    "iso:country":"DE",
    "sg:address":"Hohenzollernstr. 24",
    "sg:city":"Essen",
    "sg:phone":"+49 201/8182720",
    "sg:postcode":"45128",
    "sg:province":"Nordrhein-Westfalen",
    "wof:name":"Gesellschaft F\u00fcr Verm\u00f6gens- Verwaltung Mbh",
    "wof:placetype":"venue"
},
  "geometry": {"coordinates":[7.009828,51.442856],"type":"Point"}
}