{
  "type": "Feature",
  "properties": {
    "iso:country":"DE",
    "sg:address":"Stephanstr. 44",
    "sg:city":"Gie\u00dfen",
    "sg:phone":"+49 641/71208",
    "sg:postcode":"35390",
    "sg:province":"Hessen",
    "wof:name":"W. Lagemann Steuerberater",
    "wof:placetype":"venue"
},
  "geometry": {"coordinates":[8.6754169464,50.578414917],"type":"Point"}
}