{
  "type": "Feature",
  "properties": {
    "iso:country":"DE",
    "sg:address":"Zum Breitmaar 1",
    "sg:city":"Kerpen",
    "sg:phone":"+49 2273/949736",
    "sg:postcode":"50170",
    "sg:province":"Nordrhein-Westfalen",
    "wof:name":"Ms Sportsbar Im Ms Kart Center R. Wilkens Beteiligungs Gmbh",
    "wof:placetype":"venue"
},
  "geometry": {"coordinates":[6.672999,50.907108],"type":"Point"}
}