{
  "type": "Feature",
  "properties": {
    "iso:country":"DE",
    "sg:address":"Am Dammtor 16",
    "sg:city":"J\u00fcterbog",
    "sg:postcode":"14913",
    "sg:province":"Brandenburg",
    "wof:name":"Kommunalarchiv Landkreis J\u00fcterbog",
    "wof:placetype":"venue"
},
  "geometry": {"coordinates":[13.07351,51.990643],"type":"Point"}
}