{
  "type": "Feature",
  "properties": {
    "iso:country":"DE",
    "sg:address":"Binger Str. 15",
    "sg:city":"Mainz",
    "sg:phone":"+49 6131/226051",
    "sg:postcode":"55116",
    "sg:province":"Rheinland-Pfalz",
    "wof:name":"Bierklause",
    "wof:placetype":"venue"
},
  "geometry": {"coordinates":[8.2614650726,49.9999809265],"type":"Point"}
}