{
  "type": "Feature",
  "properties": {
    "iso:country":"DE",
    "sg:address":"Kneheim",
    "sg:city":"Lastrup",
    "sg:phone":"+49 4477/231",
    "sg:postcode":"49688",
    "sg:province":"Niedersachsen",
    "wof:name":"Heinrich Kr\u00f6ger",
    "wof:placetype":"venue"
},
  "geometry": {"coordinates":[7.962145,52.784817],"type":"Point"}
}