{
  "type": "Feature",
  "properties": {
    "iso:country":"DE",
    "sg:address":"Chausseehausstr. 8",
    "sg:city":"Dresden",
    "sg:phone":"+49 351/4215615",
    "sg:postcode":"01159",
    "sg:province":"Sachsen",
    "wof:name":"Gerhard Krumbiegel",
    "wof:placetype":"venue"
},
  "geometry": {"coordinates":[13.703115,51.039494],"type":"Point"}
}