{
  "type": "Feature",
  "properties": {
    "iso:country":"DE",
    "sg:address":"Hangeberg 21",
    "sg:city":"Ilmenau",
    "sg:phone":"+49 3677/872785",
    "sg:postcode":"98693",
    "sg:province":"Th\u00fcringen",
    "wof:name":"Dieter Fliedner",
    "wof:placetype":"venue"
},
  "geometry": {"coordinates":[10.905351,50.687675],"type":"Point"}
}