{
  "type": "Feature",
  "properties": {
    "iso:country":"DE",
    "sg:address":"Scheffelweg 9",
    "sg:city":"Wangen",
    "sg:phone":"+49 7522/2525",
    "sg:postcode":"88239",
    "sg:province":"Baden-W\u00fcrttemberg",
    "wof:name":"Wilfried Lakner",
    "wof:placetype":"venue"
},
  "geometry": {"coordinates":[9.8202295303,47.6899147034],"type":"Point"}
}