{
  "type": "Feature",
  "properties": {
    "iso:country":"DE",
    "sg:address":"H\u00fcllbeen 11 c",
    "sg:city":"Hamburg",
    "sg:phone":"+49 40/7631777",
    "sg:postcode":"21079",
    "sg:province":"Hamburg",
    "wof:name":"Willi Netzler Foto- Und Kinoapparate",
    "wof:placetype":"venue"
},
  "geometry": {"coordinates":[9.9984035492,53.4356575012],"type":"Point"}
}