{
  "type": "Feature",
  "properties": {
    "iso:country":"DE",
    "sg:address":"Alte Engterstr. 8",
    "sg:city":"Bramsche",
    "sg:phone":"+49 5461/3616",
    "sg:postcode":"49565",
    "sg:province":"Niedersachsen",
    "wof:name":"Tsch\u00f6rtner Grabmale Gmbh",
    "wof:placetype":"venue"
},
  "geometry": {"coordinates":[7.9902610779,52.4039535522],"type":"Point"}
}