{
  "type": "Feature",
  "properties": {
    "iso:country":"DE",
    "sg:address":"Im Wasen 2",
    "sg:city":"R\u00f6ttingen",
    "sg:phone":"+49 9338/97200",
    "sg:postcode":"97285",
    "sg:province":"Bayern",
    "wof:name":"Winkler Design Gmbh & Co",
    "wof:placetype":"venue"
},
  "geometry": {"coordinates":[9.96448,49.517681],"type":"Point"}
}