{
  "type": "Feature",
  "properties": {
    "iso:country":"DE",
    "sg:address":"Hauptstr. 20",
    "sg:city":"Eisenbach",
    "sg:phone":"+49 7657/269",
    "sg:postcode":"79871",
    "sg:province":"Baden-W\u00fcrttemberg",
    "wof:name":"Hermann Pfaff",
    "wof:placetype":"venue"
},
  "geometry": {"coordinates":[8.264267,47.956326],"type":"Point"}
}