{
  "type": "Feature",
  "properties": {
    "iso:country":"DE",
    "sg:address":"Fuggerstr. 1",
    "sg:city":"Ludwigshafen",
    "sg:phone":"+49 621/533148",
    "sg:postcode":"67065",
    "sg:province":"Rheinland-Pfalz",
    "wof:name":"Poseidon",
    "wof:placetype":"venue"
},
  "geometry": {"coordinates":[8.4106559753,49.4717025757],"type":"Point"}
}