{
  "type": "Feature",
  "properties": {
    "iso:country":"DE",
    "sg:address":"Bamberger Str. 27",
    "sg:city":"Zeil",
    "sg:phone":"+49 9524/850360",
    "sg:postcode":"97475",
    "sg:province":"Bayern",
    "wof:name":"Redaktion Fr\u00e4nkischer Tag",
    "wof:placetype":"venue"
},
  "geometry": {"coordinates":[10.5989971161,50.0070457458],"type":"Point"}
}