{
  "type": "Feature",
  "properties": {
    "iso:country":"DE",
    "sg:address":"Fr\u00f6belstr. 14",
    "sg:city":"Leipzig",
    "sg:phone":"+49 341/5213278",
    "sg:postcode":"04158",
    "sg:province":"Sachsen",
    "wof:name":"Tilo Geicke",
    "wof:placetype":"venue"
},
  "geometry": {"coordinates":[12.383125,51.401497],"type":"Point"}
}