{
  "type": "Feature",
  "properties": {
    "iso:country":"DE",
    "sg:address":"Kaygasse 1",
    "sg:city":"K\u00f6ln",
    "sg:phone":"+49 221/2720687",
    "sg:postcode":"50676",
    "sg:province":"Nordrhein-Westfalen",
    "wof:name":"Die Plattform E. K.",
    "wof:placetype":"venue"
},
  "geometry": {"coordinates":[6.951337,50.931316],"type":"Point"}
}