{
  "type": "Feature",
  "properties": {
    "iso:country":"DE",
    "sg:address":"Lindenstr. 6",
    "sg:city":"Vehlow",
    "sg:phone":"+49 33976/50246",
    "sg:postcode":"16866",
    "sg:province":"Brandenburg",
    "wof:name":"Leval E.g.",
    "wof:placetype":"venue"
},
  "geometry": {"coordinates":[12.3250875473,53.0115394592],"type":"Point"}
}