{
  "type": "Feature",
  "properties": {
    "iso:country":"DE",
    "sg:address":"Leipziger Str. 179",
    "sg:city":"Crimmitschau",
    "sg:phone":"+49 3762/3678",
    "sg:postcode":"08451",
    "sg:province":"Sachsen",
    "wof:name":"Rolf Lippmann",
    "wof:placetype":"venue"
},
  "geometry": {"coordinates":[12.391553,50.832745],"type":"Point"}
}