{
  "type": "Feature",
  "properties": {
    "iso:country":"DE",
    "sg:address":"Zum Baggersee 5",
    "sg:city":"Lengerich",
    "sg:phone":"+49 5481/1720",
    "sg:postcode":"49525",
    "sg:province":"Nordrhein-Westfalen",
    "wof:name":"Friedrich Caldemeyer",
    "wof:placetype":"venue"
},
  "geometry": {"coordinates":[7.881575,52.150196],"type":"Point"}
}