{
  "type": "Feature",
  "properties": {
    "iso:country":"DE",
    "sg:address":"Burgeffstr. 32",
    "sg:city":"Hochheim",
    "sg:phone":"+49 6146/1563",
    "sg:postcode":"65239",
    "sg:province":"Hessen",
    "wof:name":"Artek Ingenieurgesellschaft Zur Planung Und Realisierung",
    "wof:placetype":"venue"
},
  "geometry": {"coordinates":[8.3491621017,50.0128135681],"type":"Point"}
}