{
  "type": "Feature",
  "properties": {
    "iso:country":"DE",
    "sg:address":"Ornachstr. 5",
    "sg:city":"Hindelang",
    "sg:postcode":"87541",
    "sg:province":"Bayern",
    "wof:name":"Pro Oberjoch Tourismus- F\u00f6rderung Gmbh",
    "wof:placetype":"venue"
},
  "geometry": {"coordinates":[10.40429,47.515839],"type":"Point"}
}