{
  "type": "Feature",
  "properties": {
    "iso:country":"DE",
    "sg:address":"Geretsrieder Str. 5",
    "sg:city":"M\u00fcnchen",
    "sg:phone":"+49 89/7853053",
    "sg:postcode":"81379",
    "sg:province":"Bayern",
    "wof:name":"Preimesser",
    "wof:placetype":"venue"
},
  "geometry": {"coordinates":[11.53291,48.100845],"type":"Point"}
}