{
  "type": "Feature",
  "properties": {
    "iso:country":"DE",
    "sg:address":"Kirchwinkel 1",
    "sg:city":"Hameln",
    "sg:phone":"+49 5151/12694",
    "sg:postcode":"31789",
    "sg:province":"Niedersachsen",
    "wof:name":"Tischlerei Schmedeke Gmbh",
    "wof:placetype":"venue"
},
  "geometry": {"coordinates":[9.418265,52.077393],"type":"Point"}
}