{
  "type": "Feature",
  "properties": {
    "iso:country":"DE",
    "sg:address":"Liebenwerdaer Chaussee 2",
    "sg:city":"Tr\u00f6bitz",
    "sg:postcode":"03253",
    "sg:province":"Brandenburg",
    "wof:name":"S. L. Spezialtiefbau Und Umwelttechnik Gmbh",
    "wof:placetype":"venue"
},
  "geometry": {"coordinates":[13.4297437668,51.5940322876],"type":"Point"}
}