{
  "type": "Feature",
  "properties": {
    "iso:country":"DE",
    "sg:address":"Friedhofsweg 4",
    "sg:city":"Bunde",
    "sg:phone":"+49 4953/91110",
    "sg:postcode":"26831",
    "sg:province":"Niedersachsen",
    "wof:name":"Klaus-peter Uebersohn Heilpraktiker",
    "wof:placetype":"venue"
},
  "geometry": {"coordinates":[7.2665038109,53.1856498718],"type":"Point"}
}