{
  "type": "Feature",
  "properties": {
    "iso:country":"DE",
    "sg:address":"Wilhelm-K\u00fclz-Str. 70",
    "sg:city":"Stahnsdorf",
    "sg:phone":"+49 3329/612878",
    "sg:postcode":"14532",
    "sg:province":"Brandenburg",
    "wof:name":"Pension Hoffmann",
    "wof:placetype":"venue"
},
  "geometry": {"coordinates":[13.2265672684,52.3919487],"type":"Point"}
}