{
  "type": "Feature",
  "properties": {
    "iso:country":"DE",
    "sg:address":"Sternbuschweg 2",
    "sg:city":"Duisburg",
    "sg:phone":"+49 203/354531",
    "sg:postcode":"47057",
    "sg:province":"Nordrhein-Westfalen",
    "wof:name":"I. Gerstung",
    "wof:placetype":"venue"
},
  "geometry": {"coordinates":[6.796164,51.433067],"type":"Point"}
}