{
  "type": "Feature",
  "properties": {
    "iso:country":"DE",
    "sg:address":"Lange Str. 27",
    "sg:city":"Berne",
    "sg:phone":"+49 4406/787",
    "sg:postcode":"27804",
    "sg:province":"Niedersachsen",
    "wof:name":"Versicherungsagentur R\u00fcsselmann",
    "wof:placetype":"venue"
},
  "geometry": {"coordinates":[8.4790410995,53.1841316223],"type":"Point"}
}