{
  "type": "Feature",
  "properties": {
    "iso:country":"DE",
    "sg:address":"Lotharstr. 94",
    "sg:city":"Duisburg",
    "sg:postcode":"47057",
    "sg:province":"Nordrhein-Westfalen",
    "wof:name":"Projekt Siebzehn Gmbh",
    "wof:placetype":"venue"
},
  "geometry": {"coordinates":[6.79721,51.427002],"type":"Point"}
}