{
  "type": "Feature",
  "properties": {
    "iso:country":"DE",
    "sg:address":"Raiffeisenstr. 10",
    "sg:city":"Magdeburg",
    "sg:phone":"+49 391/6216158",
    "sg:postcode":"39112",
    "sg:province":"Sachsen-Anhalt",
    "wof:name":"A. Kopprasch",
    "wof:placetype":"venue"
},
  "geometry": {"coordinates":[11.627314,52.108704],"type":"Point"}
}