{
  "type": "Feature",
  "properties": {
    "iso:country":"DE",
    "sg:address":"Im Wiesengrund 8",
    "sg:city":"Wegberg",
    "sg:phone":"+49 2434/4217",
    "sg:postcode":"41844",
    "sg:province":"Nordrhein-Westfalen",
    "wof:name":"Theo Sch\u00f6ll",
    "wof:placetype":"venue"
},
  "geometry": {"coordinates":[6.302497,51.13343],"type":"Point"}
}