{
  "type": "Feature",
  "properties": {
    "iso:country":"DE",
    "sg:address":"Franzensbader Str. 3",
    "sg:city":"Kitzingen",
    "sg:phone":"+49 9321/33455",
    "sg:postcode":"97318",
    "sg:province":"Bayern",
    "wof:name":"T\u00dcv Bayern",
    "wof:placetype":"venue"
},
  "geometry": {"coordinates":[10.1903209686,49.7333641052],"type":"Point"}
}