{
  "type": "Feature",
  "properties": {
    "iso:country":"DE",
    "sg:address":"Klingelswiese 16",
    "sg:city":"Andernach",
    "sg:phone":"+49 2632/251630",
    "sg:postcode":"56626",
    "sg:province":"Rheinland-Pfalz",
    "wof:name":"Fritz Herzog Ag",
    "wof:placetype":"venue"
},
  "geometry": {"coordinates":[7.3877072334,50.4271354675],"type":"Point"}
}