{
  "type": "Feature",
  "properties": {
    "iso:country":"DE",
    "sg:address":"Bernhardweg 2",
    "sg:city":"Kamenz",
    "sg:phone":"+49 35783/15046",
    "sg:postcode":"01917",
    "sg:province":"Sachsen",
    "wof:name":"St.-georg Senioren- Und Pflegeheim",
    "wof:placetype":"venue"
},
  "geometry": {"coordinates":[14.104725,51.273487],"type":"Point"}
}