{
  "type": "Feature",
  "properties": {
    "iso:country":"DE",
    "sg:address":"Postfach 240:: 77951 Ettenheim:: Germany.^^Friedrichstr 38::",
    "sg:city":"Ettenheim",
    "sg:phone":"+49 7822/8900",
    "sg:postcode":"77955",
    "sg:province":"Baden-W\u00fcrttemberg",
    "wof:name":"Volksbank Unterer Breisgau Eg",
    "wof:placetype":"venue"
},
  "geometry": {"coordinates":[7.813615,48.256317],"type":"Point"}
}