{
  "type": "Feature",
  "properties": {
    "iso:country":"DE",
    "sg:address":"Detmolder Str. 48",
    "sg:city":"Bad Oeynhausen",
    "sg:phone":"+49 5731/92378",
    "sg:postcode":"32545",
    "sg:province":"Nordrhein-Westfalen",
    "wof:name":"Ehc Br\u00fcnger",
    "wof:placetype":"venue"
},
  "geometry": {"coordinates":[8.8012237549,52.1929512024],"type":"Point"}
}