{
  "type": "Feature",
  "properties": {
    "iso:country":"DE",
    "sg:address":"Kniebisstr. 7",
    "sg:city":"Aidlingen",
    "sg:phone":"+49 7034/62772",
    "sg:postcode":"71134",
    "sg:province":"Baden-W\u00fcrttemberg",
    "wof:name":"Ingenieurb\u00fcro F\u00fcr Antriebstechnik G\u00fcnther Hess",
    "wof:placetype":"venue"
},
  "geometry": {"coordinates":[8.8917961121,48.6814575195],"type":"Point"}
}