{
  "type": "Feature",
  "properties": {
    "iso:country":"DE",
    "sg:address":"Unterhof 154",
    "sg:city":"Schimberg",
    "sg:postcode":"37308",
    "sg:province":"Th\u00fcringen",
    "wof:name":"Feierabendheim St.-johannes-stift",
    "wof:placetype":"venue"
},
  "geometry": {"coordinates":[10.161398,51.255146],"type":"Point"}
}