{
  "type": "Feature",
  "properties": {
    "iso:country":"DE",
    "sg:address":"Friedrichstr. 20",
    "sg:city":"Minden",
    "sg:phone":"+49 571/23041",
    "sg:postcode":"32427",
    "sg:province":"Nordrhein-Westfalen",
    "wof:name":"Bohres M\u00f6ller S\u00f6fker Partnerschaft Krankengymnasten",
    "wof:placetype":"venue"
},
  "geometry": {"coordinates":[8.902645,52.292843],"type":"Point"}
}