{
  "type": "Feature",
  "properties": {
    "iso:country":"DE",
    "sg:address":"Strunksberg 4",
    "sg:city":"Extertal",
    "sg:phone":"+49 5262/3154",
    "sg:postcode":"32699",
    "sg:province":"Nordrhein-Westfalen",
    "wof:name":"Alfred Kamp",
    "wof:placetype":"venue"
},
  "geometry": {"coordinates":[9.086096,52.078506],"type":"Point"}
}