{
  "type": "Feature",
  "properties": {
    "iso:country":"DE",
    "sg:address":"Hauptstr. 71",
    "sg:city":"Simmerath",
    "sg:phone":"+49 2473/1324",
    "sg:postcode":"52152",
    "sg:province":"Nordrhein-Westfalen",
    "wof:name":"Ursula Kessel",
    "wof:placetype":"venue"
},
  "geometry": {"coordinates":[6.301986,50.608452],"type":"Point"}
}