{
  "type": "Feature",
  "properties": {
    "iso:country":"DE",
    "sg:address":"Subbelrather Str. 221",
    "sg:city":"K\u00f6ln",
    "sg:phone":"+49 221/555193",
    "sg:postcode":"50823",
    "sg:province":"Nordrhein-Westfalen",
    "wof:name":"Eugen Herrmuth",
    "wof:placetype":"venue"
},
  "geometry": {"coordinates":[6.9204349518,50.9535827637],"type":"Point"}
}