{
  "type": "Feature",
  "properties": {
    "iso:country":"DE",
    "sg:address":"Alter Hellweg 96",
    "sg:city":"Dortmund",
    "sg:phone":"+49 231/9614124",
    "sg:postcode":"44379",
    "sg:province":"Nordrhein-Westfalen",
    "wof:name":"Mazhar Shaikh",
    "wof:placetype":"venue"
},
  "geometry": {"coordinates":[7.3728961945,51.4985046387],"type":"Point"}
}