{
  "type": "Feature",
  "properties": {
    "iso:country":"DE",
    "sg:address":"Stevern 58",
    "sg:city":"Nottuln",
    "sg:phone":"+49 2502/1363",
    "sg:postcode":"48301",
    "sg:province":"Nordrhein-Westfalen",
    "wof:name":"Haus Stevertal",
    "wof:placetype":"venue"
},
  "geometry": {"coordinates":[7.375667,51.93993],"type":"Point"}
}