{
  "type": "Feature",
  "properties": {
    "iso:country":"DE",
    "sg:address":"Brunnenstr. 34",
    "sg:city":"Weil der Stadt",
    "sg:phone":"+49 7033/32446",
    "sg:postcode":"71263",
    "sg:province":"Baden-W\u00fcrttemberg",
    "wof:name":"G\u00fcnter Bauer",
    "wof:placetype":"venue"
},
  "geometry": {"coordinates":[8.838595,48.78693],"type":"Point"}
}