{
  "type": "Feature",
  "properties": {
    "iso:country":"DE",
    "sg:address":"Uhlandstr 68",
    "sg:city":"Pfullingen",
    "sg:phone":"+49 7121/77071",
    "sg:postcode":"72793",
    "sg:province":"Baden-W\u00fcrttemberg",
    "wof:name":"Mr Produktion Inh. Erhard Langeneck",
    "wof:placetype":"venue"
},
  "geometry": {"coordinates":[9.223947,48.474846],"type":"Point"}
}