{
  "type": "Feature",
  "properties": {
    "iso:country":"DE",
    "sg:address":"Schmiedgasse 12",
    "sg:city":"Waldkirchen",
    "sg:phone":"+49 8581/4664",
    "sg:postcode":"94065",
    "sg:province":"Bayern",
    "wof:name":"Chaplins Bar",
    "wof:placetype":"venue"
},
  "geometry": {"coordinates":[13.602302,48.731384],"type":"Point"}
}