{
  "type": "Feature",
  "properties": {
    "iso:country":"DE",
    "sg:address":"Bachstr. 31",
    "sg:city":"M\u00f6mlingen",
    "sg:phone":"+49 6022/38738",
    "sg:postcode":"63853",
    "sg:province":"Bayern",
    "wof:name":"Christoph M\u00fcller",
    "wof:placetype":"venue"
},
  "geometry": {"coordinates":[9.0813570023,49.8585700989],"type":"Point"}
}