{
  "type": "Feature",
  "properties": {
    "iso:country":"DE",
    "sg:address":"Steigstr. 41",
    "sg:city":"Oberboihingen",
    "sg:phone":"+49 7022/65146",
    "sg:postcode":"72644",
    "sg:province":"Baden-W\u00fcrttemberg",
    "wof:name":"Alois Aigner",
    "wof:placetype":"venue"
},
  "geometry": {"coordinates":[9.3702125549,48.647518158],"type":"Point"}
}