{
  "type": "Feature",
  "properties": {
    "iso:country":"DE",
    "sg:address":"Eberst\u00e4dter Str. 191",
    "sg:city":"Pfungstadt",
    "sg:phone":"+49 6157/2114",
    "sg:postcode":"64319",
    "sg:province":"Hessen",
    "wof:name":"K.-h. Und M. Weber",
    "wof:placetype":"venue"
},
  "geometry": {"coordinates":[8.6173706055,49.8117675781],"type":"Point"}
}