{
  "type": "Feature",
  "properties": {
    "iso:country":"DE",
    "sg:address":"Koldingstr. 6",
    "sg:city":"Hamburg",
    "sg:phone":"+49 40/8506599",
    "sg:postcode":"22769",
    "sg:province":"Hamburg",
    "wof:name":"Hilla Peyk-wiegel",
    "wof:placetype":"venue"
},
  "geometry": {"coordinates":[9.946544,53.564545],"type":"Point"}
}