{
  "type": "Feature",
  "properties": {
    "iso:country":"DE",
    "sg:address":"Landrat-Schultz-Str. 19",
    "sg:city":"Mettingen",
    "sg:phone":"+49 5452/1403",
    "sg:postcode":"49497",
    "sg:province":"Nordrhein-Westfalen",
    "wof:name":"M\u00e4hlmann",
    "wof:placetype":"venue"
},
  "geometry": {"coordinates":[7.782891,52.313847],"type":"Point"}
}