{
  "type": "Feature",
  "properties": {
    "iso:country":"DE",
    "sg:address":"Stegelstr. 37",
    "sg:city":"Herzogenrath",
    "sg:phone":"+49 2407/951897",
    "sg:postcode":"52134",
    "sg:province":"Nordrhein-Westfalen",
    "wof:name":"Peter Ladewig Rechtsanwalt",
    "wof:placetype":"venue"
},
  "geometry": {"coordinates":[6.0643939972,50.8472862244],"type":"Point"}
}