{
  "type": "Feature",
  "properties": {
    "iso:country":"DE",
    "sg:address":"Ahornring 3",
    "sg:city":"Taufkirchen",
    "sg:phone":"+49 89/54642136",
    "sg:postcode":"82024",
    "sg:province":"Bayern",
    "wof:name":"Willkommen Auf Der Internetpr\u00e4senz Von Gdcmedia",
    "wof:placetype":"venue"
},
  "geometry": {"coordinates":[11.599206,48.052898],"type":"Point"}
}