{
  "type": "Feature",
  "properties": {
    "iso:country":"DE",
    "sg:address":"M\u00fcnsterstr. 13",
    "sg:city":"Birkenwerder",
    "sg:phone":"+49 3303/403704",
    "sg:postcode":"16547",
    "sg:province":"Brandenburg",
    "wof:name":"Bodo Gadzikowski",
    "wof:placetype":"venue"
},
  "geometry": {"coordinates":[13.271012,52.691425],"type":"Point"}
}