{
  "type": "Feature",
  "properties": {
    "iso:country":"DE",
    "sg:address":"Darmstaedter Strasse 124",
    "sg:city":"Weiterstadt",
    "sg:phone":"+49 6150/4533",
    "sg:postcode":"64331",
    "sg:province":"Hessen",
    "wof:name":"Yamaha Motorradcenter Weiterstadt",
    "wof:placetype":"venue"
},
  "geometry": {"coordinates":[8.5951814651,49.9021492004],"type":"Point"}
}