{
  "type": "Feature",
  "properties": {
    "iso:country":"DE",
    "sg:address":"Abensbergerstr. 9",
    "sg:city":"Rohr-Bachl",
    "sg:phone":"+49 8783",
    "sg:postcode":"93352",
    "sg:province":"Bayern",
    "wof:name":"Kudet Strickmode, Herstellung Und Versand",
    "wof:placetype":"venue"
},
  "geometry": {"coordinates":[11.95034,48.810589],"type":"Point"}
}