{
  "type": "Feature",
  "properties": {
    "iso:country":"DE",
    "sg:address":"Bayernstr 10",
    "sg:city":"Langenhagen",
    "sg:phone":"+49 511/983810",
    "sg:postcode":"30855",
    "sg:province":"Niedersachsen",
    "wof:name":"Altec Computersysteme Gmbh",
    "wof:placetype":"venue"
},
  "geometry": {"coordinates":[9.706407,52.44302],"type":"Point"}
}