{
  "type": "Feature",
  "properties": {
    "iso:country":"DE",
    "sg:address":"Mittelstr. 126",
    "sg:city":"Lemgo",
    "sg:phone":"+49 5261/4162",
    "sg:postcode":"32657",
    "sg:province":"Nordrhein-Westfalen",
    "wof:name":"R\u00f6ding",
    "wof:placetype":"venue"
},
  "geometry": {"coordinates":[8.8953342438,52.028427124],"type":"Point"}
}