{
  "type": "Feature",
  "properties": {
    "iso:country":"DE",
    "sg:address":"Industriestr. 2",
    "sg:city":"Wehrheim",
    "sg:postcode":"61273",
    "sg:province":"Hessen",
    "wof:name":"Buckingham Pool & Wellness Gmbh",
    "wof:placetype":"venue"
},
  "geometry": {"coordinates":[8.5680513382,50.2946434021],"type":"Point"}
}