{
  "type": "Feature",
  "properties": {
    "iso:country":"DE",
    "sg:address":"Kurtalstr. 47",
    "sg:city":"Bad Bergzabern",
    "sg:phone":"+49 6343/1075",
    "sg:postcode":"76887",
    "sg:province":"Rheinland-Pfalz",
    "wof:name":"Hotel Petronella",
    "wof:placetype":"venue"
},
  "geometry": {"coordinates":[7.9862518311,49.0995368958],"type":"Point"}
}