{
  "type": "Feature",
  "properties": {
    "iso:country":"DE",
    "sg:address":"August-Bebel-Str. 10",
    "sg:city":"Viernheim",
    "sg:phone":"+49 6204/76257",
    "sg:postcode":"68519",
    "sg:province":"Hessen",
    "wof:name":"Heinrich Adler",
    "wof:placetype":"venue"
},
  "geometry": {"coordinates":[8.58835,49.538979],"type":"Point"}
}