{
  "type": "Feature",
  "properties": {
    "iso:country":"DE",
    "sg:address":"Wattstr. 10",
    "sg:city":"Berlin",
    "sg:phone":"+49 30/4648495",
    "sg:postcode":"13355",
    "sg:province":"Berlin",
    "wof:name":"Mima D\u00e4mmtechnik E. K.",
    "wof:placetype":"venue"
},
  "geometry": {"coordinates":[13.390395,52.540901],"type":"Point"}
}