{
  "type": "Feature",
  "properties": {
    "iso:country":"DE",
    "sg:address":"Heiliger Weg 60",
    "sg:city":"Dortmund",
    "sg:phone":"+49 231/5569520",
    "sg:postcode":"44135",
    "sg:province":"Nordrhein-Westfalen",
    "wof:name":"Teampenta Gmbh",
    "wof:placetype":"venue"
},
  "geometry": {"coordinates":[7.474706,51.509327],"type":"Point"}
}