{
  "type": "Feature",
  "properties": {
    "iso:country":"DE",
    "sg:address":"Vorderdorfstr. 61",
    "sg:city":"St. Blasien",
    "sg:phone":"+49 7675/1074",
    "sg:postcode":"79837",
    "sg:province":"Baden-W\u00fcrttemberg",
    "wof:name":"K.-h. H\u00f6fler",
    "wof:placetype":"venue"
},
  "geometry": {"coordinates":[8.071003,47.822189],"type":"Point"}
}