{
  "type": "Feature",
  "properties": {
    "iso:country":"DE",
    "sg:address":"Kettelerstr. 4",
    "sg:city":"Zornheim",
    "sg:phone":"+49 6136/45065",
    "sg:postcode":"55270",
    "sg:province":"Rheinland-Pfalz",
    "wof:name":"Hotel Vogelsang",
    "wof:placetype":"venue"
},
  "geometry": {"coordinates":[8.2225999832,49.8902778625],"type":"Point"}
}