{
  "type": "Feature",
  "properties": {
    "iso:country":"DE",
    "sg:address":"Hessgasse 2",
    "sg:city":"Bergheim",
    "sg:postcode":"50129",
    "sg:province":"Nordrhein-Westfalen",
    "wof:name":"Maler Fa. Wunderlich",
    "wof:placetype":"venue"
},
  "geometry": {"coordinates":[6.71088,50.989201],"type":"Point"}
}