{
  "type": "Feature",
  "properties": {
    "iso:country":"DE",
    "sg:address":"Eisenbahnstr. 64",
    "sg:city":"Freiburg",
    "sg:phone":"+49 761/382245",
    "sg:postcode":"79098",
    "sg:province":"Baden-W\u00fcrttemberg",
    "wof:name":"Dr. Med. Heribert M\u00f6llinger",
    "wof:placetype":"venue"
},
  "geometry": {"coordinates":[7.8437600136,47.997177124],"type":"Point"}
}