{
  "type": "Feature",
  "properties": {
    "iso:country":"DE",
    "sg:address":"Postwirtstr. 7",
    "sg:city":"Ergolding",
    "sg:phone":"+49 871/12587",
    "sg:postcode":"84030",
    "sg:province":"Bayern",
    "wof:name":"M. Starflinger",
    "wof:placetype":"venue"
},
  "geometry": {"coordinates":[12.1613140106,48.5729141235],"type":"Point"}
}