{
  "type": "Feature",
  "properties": {
    "iso:country":"DE",
    "sg:address":"Am Kromberg 1",
    "sg:city":"Eurasburg",
    "sg:phone":"+49 8179/8909",
    "sg:postcode":"82547",
    "sg:province":"Bayern",
    "wof:name":"J. Nocker",
    "wof:placetype":"venue"
},
  "geometry": {"coordinates":[11.369247,47.861958],"type":"Point"}
}