{
  "type": "Feature",
  "properties": {
    "iso:country":"DE",
    "sg:address":"Rappenberghalde 24",
    "sg:city":"T\u00fcbingen",
    "sg:phone":"+49 7071/41441",
    "sg:postcode":"72070",
    "sg:province":"Baden-W\u00fcrttemberg",
    "wof:name":"Kilger Und Kilger Rechtsanw\u00e4lte",
    "wof:placetype":"venue"
},
  "geometry": {"coordinates":[9.0390720367,48.5136795044],"type":"Point"}
}