{
  "type": "Feature",
  "properties": {
    "iso:country":"DE",
    "sg:address":"K\u00f6ttersweg 9",
    "sg:city":"Soest",
    "sg:phone":"+49 2921/65089",
    "sg:postcode":"59494",
    "sg:province":"Nordrhein-Westfalen",
    "wof:name":"Ottfriede Schaffrath",
    "wof:placetype":"venue"
},
  "geometry": {"coordinates":[8.074648,51.530025],"type":"Point"}
}