{
  "type": "Feature",
  "properties": {
    "iso:country":"DE",
    "sg:address":"Ulmer Str. 4",
    "sg:city":"Wendlingen",
    "sg:phone":"+49 7024/500400",
    "sg:postcode":"73240",
    "sg:province":"Baden-W\u00fcrttemberg",
    "wof:name":"Claudias Floraldesign",
    "wof:placetype":"venue"
},
  "geometry": {"coordinates":[9.379455,48.672394],"type":"Point"}
}