{
  "type": "Feature",
  "properties": {
    "iso:country":"DE",
    "sg:address":"Ringstr. 193",
    "sg:city":"Kamp-Lintfort",
    "sg:phone":"+49 2842/2225",
    "sg:postcode":"47475",
    "sg:province":"Nordrhein-Westfalen",
    "wof:name":"Altes Kasino",
    "wof:placetype":"venue"
},
  "geometry": {"coordinates":[6.5517201424,51.4959182739],"type":"Point"}
}