{
  "type": "Feature",
  "properties": {
    "iso:country":"DE",
    "sg:address":"Auf der Morgenstelle 17",
    "sg:city":"T\u00fcbingen",
    "sg:postcode":"72076",
    "sg:province":"Baden-W\u00fcrttemberg",
    "wof:name":"Lehrstuhl F\u00fcr Organische Chemie Ii",
    "wof:placetype":"venue"
},
  "geometry": {"coordinates":[9.0625352859,48.542514801],"type":"Point"}
}