{
  "type": "Feature",
  "properties": {
    "iso:country":"DE",
    "sg:address":"Scharnhorststr. 11-16",
    "sg:city":"L\u00fcnen",
    "sg:phone":"+49 2306/9490",
    "sg:postcode":"44532",
    "sg:province":"Nordrhein-Westfalen",
    "wof:name":"Neuh\u00e4user Lagersysteme Gmbh",
    "wof:placetype":"venue"
},
  "geometry": {"coordinates":[7.5394330025,51.593208313],"type":"Point"}
}