{
  "type": "Feature",
  "properties": {
    "iso:country":"DE",
    "sg:address":"Schleswiger Str. 6",
    "sg:city":"Sieverstedt",
    "sg:phone":"+49 4603/339",
    "sg:postcode":"24885",
    "sg:province":"Schleswig-Holstein",
    "wof:name":"Jahr & Kroll",
    "wof:placetype":"venue"
},
  "geometry": {"coordinates":[9.4590997696,54.6398735046],"type":"Point"}
}