{
  "type": "Feature",
  "properties": {
    "iso:country":"DE",
    "sg:address":"Kirchstr. 22",
    "sg:city":"Selfkant",
    "sg:phone":"+49 2456/1225",
    "sg:postcode":"52538",
    "sg:province":"Nordrhein-Westfalen",
    "wof:name":"Kentgens",
    "wof:placetype":"venue"
},
  "geometry": {"coordinates":[5.938571,51.02544],"type":"Point"}
}