{
  "type": "Feature",
  "properties": {
    "iso:country":"DE",
    "sg:address":"Rungestr. 19",
    "sg:city":"Berlin",
    "sg:phone":"+49 30/2434660",
    "sg:postcode":"10179",
    "sg:province":"Berlin",
    "wof:name":"Hannelore Vetter",
    "wof:placetype":"venue"
},
  "geometry": {"coordinates":[13.420009,52.512371],"type":"Point"}
}