{
  "type": "Feature",
  "properties": {
    "iso:country":"DE",
    "sg:address":"Brunnenstr. 2",
    "sg:city":"Weilheim",
    "sg:phone":"+49 7023/6752",
    "sg:postcode":"73235",
    "sg:province":"Baden-W\u00fcrttemberg",
    "wof:name":"Modehaus Mack Gmbh",
    "wof:placetype":"venue"
},
  "geometry": {"coordinates":[9.5377502441,48.6160392761],"type":"Point"}
}