{
  "type": "Feature",
  "properties": {
    "iso:country":"DE",
    "sg:address":"Cyclopstr. 23",
    "sg:city":"Berlin",
    "sg:phone":"+49 30/40912936",
    "sg:postcode":"13469",
    "sg:province":"Berlin",
    "wof:name":"Hella Jordan Architektin",
    "wof:placetype":"venue"
},
  "geometry": {"coordinates":[13.325509,52.601307],"type":"Point"}
}