{
  "type": "Feature",
  "properties": {
    "iso:country":"DE",
    "sg:address":"Lange Reihe 20",
    "sg:city":"Wettin",
    "sg:phone":"+49 34607/20974",
    "sg:postcode":"06198",
    "sg:province":"Sachsen-Anhalt",
    "wof:name":"D. Hoyer",
    "wof:placetype":"venue"
},
  "geometry": {"coordinates":[11.8081464767,51.5832366943],"type":"Point"}
}