{
  "type": "Feature",
  "properties": {
    "iso:country":"DE",
    "sg:address":"Am Stadttheater",
    "sg:city":"Kempten",
    "sg:phone":"+49 831/16565",
    "sg:postcode":"87435",
    "sg:province":"Bayern",
    "wof:name":"Warsteiner",
    "wof:placetype":"venue"
},
  "geometry": {"coordinates":[10.3016796112,47.7116508484],"type":"Point"}
}