{
  "type": "Feature",
  "properties": {
    "iso:country":"DE",
    "sg:address":"Winzenheimer Str. 26",
    "sg:city":"Bretzenheim",
    "sg:phone":"+49 671/31698",
    "sg:postcode":"55559",
    "sg:province":"Rheinland-Pfalz",
    "wof:name":"Nahegold Reiseb\u00fcro Werner Gemeinhardt",
    "wof:placetype":"venue"
},
  "geometry": {"coordinates":[7.8914318085,49.8764343262],"type":"Point"}
}