{
  "type": "Feature",
  "properties": {
    "iso:country":"DE",
    "sg:address":"Mannheimer Str. 120",
    "sg:city":"Bad Kreuznach",
    "sg:phone":"+49 671",
    "sg:postcode":"55545",
    "sg:province":"Rheinland-Pfalz",
    "wof:name":"Photo Porst Bad Kreuznach",
    "wof:placetype":"venue"
},
  "geometry": {"coordinates":[7.85658,49.845329],"type":"Point"}
}