{
  "type": "Feature",
  "properties": {
    "iso:country":"DE",
    "sg:address":"Bellevue 25",
    "sg:city":"Hamburg",
    "sg:phone":"+49 40/276266",
    "sg:postcode":"22301",
    "sg:province":"Hamburg",
    "wof:name":"G.l. Bohn & Co.",
    "wof:placetype":"venue"
},
  "geometry": {"coordinates":[10.0046539307,53.5773391724],"type":"Point"}
}