{
  "type": "Feature",
  "properties": {
    "iso:country":"DE",
    "sg:address":"Zum Feldberg 31",
    "sg:city":"Schmitten",
    "sg:phone":"+49 6084/2264",
    "sg:postcode":"61389",
    "sg:province":"Hessen",
    "wof:name":"Reiseb\u00fcro Christian Sch\u00fctz Kg",
    "wof:placetype":"venue"
},
  "geometry": {"coordinates":[8.4456367493,50.2679138184],"type":"Point"}
}