{
  "type": "Feature",
  "properties": {
    "iso:country":"DE",
    "sg:address":"Meisenweg 2",
    "sg:city":"Michelfeld",
    "sg:phone":"+49 791/89556",
    "sg:postcode":"74545",
    "sg:province":"Baden-W\u00fcrttemberg",
    "wof:name":"Norbert Polo",
    "wof:placetype":"venue"
},
  "geometry": {"coordinates":[9.6764888763,49.1009902954],"type":"Point"}
}