{
  "type": "Feature",
  "properties": {
    "iso:country":"DE",
    "sg:address":"Mauerstr. 2",
    "sg:city":"Marburg",
    "sg:phone":"+49 6421/66900",
    "sg:postcode":"35039",
    "sg:province":"Hessen",
    "wof:name":"Cacablanca",
    "wof:placetype":"venue"
},
  "geometry": {"coordinates":[8.7724895477,50.820274353],"type":"Point"}
}