{
  "type": "Feature",
  "properties": {
    "iso:country":"DE",
    "sg:address":"Wolkeringerstr. 14",
    "sg:city":"Prutting",
    "sg:phone":"+49 8036/7007",
    "sg:postcode":"83134",
    "sg:province":"Bayern",
    "wof:name":"F. Niedermayr",
    "wof:placetype":"venue"
},
  "geometry": {"coordinates":[12.186165,47.879627],"type":"Point"}
}