{
  "type": "Feature",
  "properties": {
    "iso:country":"DE",
    "sg:address":"Schlo\u00dfstr. 36",
    "sg:city":"Schwerin",
    "sg:phone":"+49 385/5811960",
    "sg:postcode":"19053",
    "sg:province":"Mecklenburg-Vorpommern",
    "wof:name":"Dr. Wentzel Immobilienmakler",
    "wof:placetype":"venue"
},
  "geometry": {"coordinates":[11.4114675522,53.6278457642],"type":"Point"}
}