{
  "type": "Feature",
  "properties": {
    "iso:country":"DE",
    "sg:address":"Ostseeallee 15",
    "sg:city":"K\u00fchlungsborn",
    "sg:postcode":"18225",
    "sg:province":"Mecklenburg-Vorpommern",
    "wof:name":"Foto Rauchstein",
    "wof:placetype":"venue"
},
  "geometry": {"coordinates":[11.7521505356,54.1529350281],"type":"Point"}
}