{
  "type": "Feature",
  "properties": {
    "iso:country":"DE",
    "sg:address":"Mosblech 15",
    "sg:city":"Wuppertal",
    "sg:phone":"+49 202/611309",
    "sg:postcode":"42399",
    "sg:province":"Nordrhein-Westfalen",
    "wof:name":"Christoph B\u00f6ddicker",
    "wof:placetype":"venue"
},
  "geometry": {"coordinates":[7.285313,51.243839],"type":"Point"}
}