{
  "type": "Feature",
  "properties": {
    "iso:country":"DE",
    "sg:address":"Garreler Str. 20",
    "sg:city":"Gro\u00dfenkneten",
    "sg:phone":"+49 4944/3597390",
    "sg:postcode":"26197",
    "sg:province":"Niedersachsen",
    "wof:name":"Baos Anh\u00c4ngerbau Gmbh",
    "wof:placetype":"venue"
},
  "geometry": {"coordinates":[8.1888408661,52.9491043091],"type":"Point"}
}