{
  "type": "Feature",
  "properties": {
    "iso:country":"DE",
    "sg:address":"Strandweg 2",
    "sg:city":"Neuss",
    "sg:phone":"+49 2131/37079",
    "sg:postcode":"41468",
    "sg:province":"Nordrhein-Westfalen",
    "wof:name":"Leo Buys Gmbh",
    "wof:placetype":"venue"
},
  "geometry": {"coordinates":[6.7482709885,51.1787033081],"type":"Point"}
}