{
  "type": "Feature",
  "properties": {
    "iso:country":"DE",
    "sg:address":"Silbergasse 3",
    "sg:city":"Waldsolms",
    "sg:phone":"+49 6085/1300",
    "sg:postcode":"35647",
    "sg:province":"Hessen",
    "wof:name":"Willi Bangel",
    "wof:placetype":"venue"
},
  "geometry": {"coordinates":[8.4547872543,50.4559173584],"type":"Point"}
}