{
  "type": "Feature",
  "properties": {
    "iso:country":"DE",
    "sg:address":"Weihergasse 23/1",
    "sg:city":"Schemmerhofen",
    "sg:phone":"+49 7129/92520",
    "sg:postcode":"88433",
    "sg:province":"Baden-W\u00fcrttemberg",
    "wof:name":"Haberbosch Gmbh",
    "wof:placetype":"venue"
},
  "geometry": {"coordinates":[9.737478,48.151947],"type":"Point"}
}