{
  "type": "Feature",
  "properties": {
    "iso:country":"DE",
    "sg:address":"Elbinger Str. 2",
    "sg:city":"Vechta",
    "sg:postcode":"49377",
    "sg:province":"Niedersachsen",
    "wof:name":"Remo-gastst\u00e4tten-betrieb Gmbh",
    "wof:placetype":"venue"
},
  "geometry": {"coordinates":[8.279142,52.737553],"type":"Point"}
}