{
  "type": "Feature",
  "properties": {
    "iso:country":"DE",
    "sg:address":"Tunau 10",
    "sg:city":"Kressbronn",
    "sg:phone":"+49 7543/6302",
    "sg:postcode":"88079",
    "sg:province":"Baden-W\u00fcrttemberg",
    "wof:name":"Virginia Bronfen \u00dcbersetzerin U. Dolmetscherin",
    "wof:placetype":"venue"
},
  "geometry": {"coordinates":[9.575805,47.590492],"type":"Point"}
}