{
  "type": "Feature",
  "properties": {
    "iso:country":"DE",
    "sg:address":"Friedrichstr. 11",
    "sg:city":"Iserlohn",
    "sg:phone":"+49 2371/25372",
    "sg:postcode":"58636",
    "sg:province":"Nordrhein-Westfalen",
    "wof:name":"Christian Kall\u00e4hne Immobilienmakler",
    "wof:placetype":"venue"
},
  "geometry": {"coordinates":[7.7037191391,51.3735694885],"type":"Point"}
}