{
  "type": "Feature",
  "properties": {
    "iso:country":"DE",
    "sg:address":"Frankfurter Str 27",
    "sg:city":"Eschborn",
    "sg:phone":"+49 6196/9030",
    "sg:postcode":"65760",
    "sg:province":"Hessen",
    "wof:name":"Detecon International Gmbh",
    "wof:placetype":"venue"
},
  "geometry": {"coordinates":[8.569907,50.133629],"type":"Point"}
}