{
  "type": "Feature",
  "properties": {
    "iso:country":"DE",
    "sg:address":"Mittelstr. 75-79::",
    "sg:city":"Lemgo",
    "sg:phone":"+49 4952/612140",
    "sg:postcode":"32657",
    "sg:province":"Nordrhein-Westfalen",
    "wof:name":"Sparkasse Lemgo",
    "wof:placetype":"venue"
},
  "geometry": {"coordinates":[8.899594,52.028358],"type":"Point"}
}