{
  "type": "Feature",
  "properties": {
    "iso:country":"DE",
    "sg:address":"Hans-Sachs-Str. 1 a",
    "sg:city":"Hilden",
    "sg:phone":"+49 2103/40400",
    "sg:postcode":"40721",
    "sg:province":"Nordrhein-Westfalen",
    "wof:name":"Jutta Funk Von Rosainsky Bildhauerin",
    "wof:placetype":"venue"
},
  "geometry": {"coordinates":[6.920082,51.174667],"type":"Point"}
}