{
  "type": "Feature",
  "properties": {
    "iso:country":"DE",
    "sg:address":"Memminger Str. 18",
    "sg:city":"Illertissen",
    "sg:phone":"+49 7303/7416",
    "sg:postcode":"89257",
    "sg:province":"Bayern",
    "wof:name":"K\u00f6nig-kebab",
    "wof:placetype":"venue"
},
  "geometry": {"coordinates":[10.102355957,48.2204055786],"type":"Point"}
}