{
  "type": "Feature",
  "properties": {
    "iso:country":"DE",
    "sg:address":"Zum Sch\u00e4ferstall 45",
    "sg:city":"H\u00e4melhausen",
    "sg:postcode":"27324",
    "sg:province":"Niedersachsen",
    "wof:name":"K. Ohlmeier Cvf Computer Kg",
    "wof:placetype":"venue"
},
  "geometry": {"coordinates":[9.2890586853,52.7859115601],"type":"Point"}
}