{
  "type": "Feature",
  "properties": {
    "iso:country":"DE",
    "sg:address":"Flughafen",
    "sg:city":"Frankfurt am Main",
    "sg:postcode":"60549",
    "sg:province":"Hessen",
    "wof:name":"Airport Communication Service Gmbh",
    "wof:placetype":"venue"
},
  "geometry": {"coordinates":[8.56364,50.041012],"type":"Point"}
}