{
  "type": "Feature",
  "properties": {
    "iso:country":"DE",
    "sg:address":"Johann-Heinrich-Schr\u00f6der-Str.",
    "sg:city":"Springe",
    "sg:phone":"+49 5041/5330",
    "sg:postcode":"31832",
    "sg:province":"Niedersachsen",
    "wof:name":"Ev. Luth. Pfarramt Gem. St. Petrus",
    "wof:placetype":"venue"
},
  "geometry": {"coordinates":[9.5434904099,52.2158584595],"type":"Point"}
}