{
  "type": "Feature",
  "properties": {
    "iso:country":"DE",
    "sg:address":"Unterer Neubergweg 25",
    "sg:city":"W\u00fcrzburg",
    "sg:phone":"+49 931/71992",
    "sg:postcode":"97074",
    "sg:province":"Bayern",
    "wof:name":"Albert & B\u00f6ker Grundst\u00fccks Gmbh",
    "wof:placetype":"venue"
},
  "geometry": {"coordinates":[9.9471530914,49.7737998962],"type":"Point"}
}