{
  "type": "Feature",
  "properties": {
    "iso:country":"DE",
    "sg:address":"M\u00fcnsterstr. 16",
    "sg:city":"\u00dcberlingen",
    "sg:phone":"+49 7551/4613",
    "sg:postcode":"88662",
    "sg:province":"Baden-W\u00fcrttemberg",
    "wof:name":"Textilhaus Grabherr Inh. Erika Koch E. K.",
    "wof:placetype":"venue"
},
  "geometry": {"coordinates":[9.1609153748,47.7666816711],"type":"Point"}
}