{
  "type": "Feature",
  "properties": {
    "iso:country":"DE",
    "sg:address":"Lange Str. 2",
    "sg:city":"Weener",
    "sg:phone":"+49 4951/2888",
    "sg:postcode":"26826",
    "sg:province":"Niedersachsen",
    "wof:name":"Jan Koenen",
    "wof:placetype":"venue"
},
  "geometry": {"coordinates":[7.349441,53.161087],"type":"Point"}
}