{
  "type": "Feature",
  "properties": {
    "iso:country":"DE",
    "sg:address":"Brunnenweg 6",
    "sg:city":"M\u00fcnchen",
    "sg:phone":"+49 89/6906146",
    "sg:postcode":"81547",
    "sg:province":"Bayern",
    "wof:name":"C. W\u00fcnsch",
    "wof:placetype":"venue"
},
  "geometry": {"coordinates":[11.581075,48.100609],"type":"Point"}
}