{
  "type": "Feature",
  "properties": {
    "iso:country":"DE",
    "sg:address":"G\u00e4rtnerweg 13",
    "sg:city":"Reinhardshagen",
    "sg:phone":"+49 5544/7804",
    "sg:postcode":"34359",
    "sg:province":"Hessen",
    "wof:name":"Fridolin Becker",
    "wof:placetype":"venue"
},
  "geometry": {"coordinates":[9.617439,51.472481],"type":"Point"}
}