{
  "type": "Feature",
  "properties": {
    "iso:country":"DE",
    "sg:address":"Hauptstr. 11",
    "sg:city":"Furth im Wald",
    "sg:phone":"+49 9973/1640",
    "sg:postcode":"93437",
    "sg:province":"Bayern",
    "wof:name":"F. X. Wagner",
    "wof:placetype":"venue"
},
  "geometry": {"coordinates":[12.7955636978,49.2933502197],"type":"Point"}
}