{
  "type": "Feature",
  "properties": {
    "iso:country":"DE",
    "sg:address":"Winsener Str. 50",
    "sg:city":"Hamburg",
    "sg:phone":"+49 40/7634769",
    "sg:postcode":"21077",
    "sg:province":"Hamburg",
    "wof:name":"Emil Heuer",
    "wof:placetype":"venue"
},
  "geometry": {"coordinates":[9.9890975952,53.4479637146],"type":"Point"}
}