{
  "type": "Feature",
  "properties": {
    "iso:country":"DE",
    "sg:address":"Heinrichstr. 26",
    "sg:city":"Braunschweig",
    "sg:phone":"+49 531/334790",
    "sg:postcode":"38106",
    "sg:province":"Niedersachsen",
    "wof:name":"Restaurant Sukiyaki",
    "wof:placetype":"venue"
},
  "geometry": {"coordinates":[10.5442237854,52.271648407],"type":"Point"}
}