{
  "type": "Feature",
  "properties": {
    "iso:country":"DE",
    "sg:address":"Blumenstr. 17",
    "sg:city":"Wolpertswende",
    "sg:phone":"+49 7502/4298",
    "sg:postcode":"88284",
    "sg:province":"Baden-W\u00fcrttemberg",
    "wof:name":"Anton Bochtler",
    "wof:placetype":"venue"
},
  "geometry": {"coordinates":[9.6096382141,47.8973922729],"type":"Point"}
}