{
  "type": "Feature",
  "properties": {
    "iso:country":"DE",
    "sg:address":"Sauerbruchstr. 21",
    "sg:city":"Potsdam",
    "sg:phone":"+49 331/707562",
    "sg:postcode":"14482",
    "sg:province":"Brandenburg",
    "wof:name":"Kerstin Majowski",
    "wof:placetype":"venue"
},
  "geometry": {"coordinates":[13.112445,52.401058],"type":"Point"}
}