{
  "type": "Feature",
  "properties": {
    "iso:country":"DE",
    "sg:address":"Richtstr. 21",
    "sg:city":"Schweich",
    "sg:phone":"+49 6502/2361",
    "sg:postcode":"54338",
    "sg:province":"Rheinland-Pfalz",
    "wof:name":"Josef Mauerer",
    "wof:placetype":"venue"
},
  "geometry": {"coordinates":[6.753478,49.823383],"type":"Point"}
}