{
  "type": "Feature",
  "properties": {
    "iso:country":"DE",
    "sg:address":"Kupferstr. 8",
    "sg:city":"R\u00fcsselsheim",
    "sg:phone":"+49 6142/65262",
    "sg:postcode":"65428",
    "sg:province":"Hessen",
    "wof:name":"Karl Becherer",
    "wof:placetype":"venue"
},
  "geometry": {"coordinates":[8.425539,49.976616],"type":"Point"}
}