{
  "type": "Feature",
  "properties": {
    "iso:country":"DE",
    "sg:address":"In der Au 17-19",
    "sg:city":"Sternenfels",
    "sg:phone":"+49 7043/901040",
    "sg:postcode":"75447",
    "sg:province":"Baden-W\u00fcrttemberg",
    "wof:name":"Sieber Gmbh Teilefertigung",
    "wof:placetype":"venue"
},
  "geometry": {"coordinates":[8.852096,49.031052],"type":"Point"}
}