{
  "type": "Feature",
  "properties": {
    "iso:country":"DE",
    "sg:address":"Breslauer Str. 16",
    "sg:city":"Metzingen",
    "sg:phone":"+49 7123/21020",
    "sg:postcode":"72555",
    "sg:province":"Baden-W\u00fcrttemberg",
    "wof:name":"Notheis & Killmayer",
    "wof:placetype":"venue"
},
  "geometry": {"coordinates":[9.2884321213,48.5480232239],"type":"Point"}
}