{
  "type": "Feature",
  "properties": {
    "iso:country":"DE",
    "sg:address":"Polcher Str 50",
    "sg:city":"Kehrig",
    "sg:phone":"+49 2651/2600",
    "sg:postcode":"56729",
    "sg:province":"Rheinland-Pfalz",
    "wof:name":"Spedition G\u00f6rgen Gmbh",
    "wof:placetype":"venue"
},
  "geometry": {"coordinates":[7.2267098427,50.2802085876],"type":"Point"}
}