{
  "type": "Feature",
  "properties": {
    "iso:country":"DE",
    "sg:address":"Knappstrasse 18a",
    "sg:city":"Dortmund",
    "sg:phone":"+49 4923/04",
    "sg:postcode":"44267",
    "sg:province":"Nordrhein-Westfalen",
    "wof:name":"Patrick T. Vater Datentechnik Online",
    "wof:placetype":"venue"
},
  "geometry": {"coordinates":[7.531761,51.457047],"type":"Point"}
}