{
  "type": "Feature",
  "properties": {
    "iso:country":"DE",
    "sg:address":"Avenariusstr. 30",
    "sg:city":"Hamburg",
    "sg:phone":"+49 40/868110",
    "sg:postcode":"22587",
    "sg:province":"Hamburg",
    "wof:name":"Peter-cl. Blechschmidt Architekt",
    "wof:placetype":"venue"
},
  "geometry": {"coordinates":[9.819591,53.562572],"type":"Point"}
}