{
  "type": "Feature",
  "properties": {
    "iso:country":"DE",
    "sg:address":"Bayernstr. 11",
    "sg:city":"Illertissen",
    "sg:phone":"+49 7303/41349",
    "sg:postcode":"89257",
    "sg:province":"Bayern",
    "wof:name":"Franz Miller",
    "wof:placetype":"venue"
},
  "geometry": {"coordinates":[10.112452,48.202568],"type":"Point"}
}