{
  "type": "Feature",
  "properties": {
    "iso:country":"DE",
    "sg:address":"Nu\u00dfdorfer Str. 13",
    "sg:city":"Brannenburg",
    "sg:phone":"+49 8034/4453",
    "sg:postcode":"83098",
    "sg:province":"Bayern",
    "wof:name":"St. Franziskus Altenheim",
    "wof:placetype":"venue"
},
  "geometry": {"coordinates":[12.11012,47.735458],"type":"Point"}
}