{
  "type": "Feature",
  "properties": {
    "iso:country":"DE",
    "sg:address":"Auerbacher Str. 15",
    "sg:city":"Sch\u00f6nheide",
    "sg:postcode":"08304",
    "sg:province":"Sachsen",
    "wof:name":"Seidel & G\u00f6pel Hoterlbetriebs Ohg",
    "wof:placetype":"venue"
},
  "geometry": {"coordinates":[12.4985742569,50.5031547546],"type":"Point"}
}