{
  "type": "Feature",
  "properties": {
    "iso:country":"DE",
    "sg:address":"Brassertstr. 95 f",
    "sg:city":"Marl",
    "sg:phone":"+49 2365/65424",
    "sg:postcode":"45768",
    "sg:province":"Nordrhein-Westfalen",
    "wof:name":"Kurt Czerwanski Architekt",
    "wof:placetype":"venue"
},
  "geometry": {"coordinates":[7.099452,51.655895],"type":"Point"}
}