{
  "type": "Feature",
  "properties": {
    "iso:country":"DE",
    "sg:address":"Beethovenstr. 16",
    "sg:city":"D\u00fcsseldorf",
    "sg:phone":"+49 211/683868",
    "sg:postcode":"40233",
    "sg:province":"Nordrhein-Westfalen",
    "wof:name":"Willi Pitthan",
    "wof:placetype":"venue"
},
  "geometry": {"coordinates":[6.802376,51.229828],"type":"Point"}
}