{
  "type": "Feature",
  "properties": {
    "iso:country":"DE",
    "sg:address":"Immenh\u00e4user Str. 2",
    "sg:city":"Kassel",
    "sg:phone":"+49 561/885918",
    "sg:postcode":"34128",
    "sg:province":"Hessen",
    "wof:name":"Wolfgang J. St\u00fcckrath Steuerberater",
    "wof:placetype":"venue"
},
  "geometry": {"coordinates":[9.4480199814,51.3334274292],"type":"Point"}
}