{
  "type": "Feature",
  "properties": {
    "iso:country":"DE",
    "sg:address":"Speyerer Str.",
    "sg:city":"Schifferstadt",
    "sg:phone":"+49 6235/5515",
    "sg:postcode":"67105",
    "sg:province":"Rheinland-Pfalz",
    "wof:name":"Waldfesthalle",
    "wof:placetype":"venue"
},
  "geometry": {"coordinates":[8.37541,49.376816],"type":"Point"}
}