{
  "type": "Feature",
  "properties": {
    "iso:country":"DE",
    "sg:address":"Am Lesumdeich 9",
    "sg:city":"Bremen",
    "sg:postcode":"28719",
    "sg:province":"Bremen",
    "wof:name":"Tietjen Werksvertretungen Inh. Martin Stelljes E. K.",
    "wof:placetype":"venue"
},
  "geometry": {"coordinates":[8.720872879,53.1609535217],"type":"Point"}
}