{
  "type": "Feature",
  "properties": {
    "iso:country":"DE",
    "sg:address":"Bahnhofstr. 3",
    "sg:city":"Werdohl",
    "sg:phone":"+49 2392/93950",
    "sg:postcode":"58791",
    "sg:province":"Nordrhein-Westfalen",
    "wof:name":"Carl-ludwig L\u00fcling Kg",
    "wof:placetype":"venue"
},
  "geometry": {"coordinates":[7.7587118149,51.258972168],"type":"Point"}
}