{
  "type": "Feature",
  "properties": {
    "iso:country":"DE",
    "sg:address":"Mainzer stra\u00dfe 47",
    "sg:city":"Spay",
    "sg:phone":"+49 2628/3342",
    "sg:postcode":"56322",
    "sg:province":"Rheinland-Pfalz",
    "wof:name":"Flair Hotel",
    "wof:placetype":"venue"
},
  "geometry": {"coordinates":[7.6467471123,50.2531776428],"type":"Point"}
}