{
  "type": "Feature",
  "properties": {
    "iso:country":"DE",
    "sg:address":"Augustusstr. 9",
    "sg:city":"Haltern",
    "sg:postcode":"45721",
    "sg:province":"Nordrhein-Westfalen",
    "wof:name":"Sem Eisen- Und Metallhandelsges. Mbh",
    "wof:placetype":"venue"
},
  "geometry": {"coordinates":[7.173863,51.742085],"type":"Point"}
}