{
  "type": "Feature",
  "properties": {
    "iso:country":"DE",
    "sg:address":"Rotb\u00fchlstr. 40",
    "sg:city":"Nabburg",
    "sg:phone":"+49 9433/8294",
    "sg:postcode":"92507",
    "sg:province":"Bayern",
    "wof:name":"Friedrich Raab",
    "wof:placetype":"venue"
},
  "geometry": {"coordinates":[12.173242569,49.4549827576],"type":"Point"}
}