{
  "type": "Feature",
  "properties": {
    "iso:country":"DE",
    "sg:address":"An der Ziegelei 22",
    "sg:city":"Dueren",
    "sg:phone":"+49 2421/780601",
    "sg:postcode":"52355",
    "sg:province":"Nordrhein-Westfalen",
    "wof:name":"Das War Einmal - Fotos Aus Der Vergangenheit",
    "wof:placetype":"venue"
},
  "geometry": {"coordinates":[6.462526,50.789989],"type":"Point"}
}