{
  "type": "Feature",
  "properties": {
    "iso:country":"DE",
    "sg:address":"Dorfplatz 2",
    "sg:city":"Rattenberg",
    "sg:phone":"+49 9963/9500",
    "sg:postcode":"94371",
    "sg:province":"Bayern",
    "wof:name":"Hotel Zur Post",
    "wof:placetype":"venue"
},
  "geometry": {"coordinates":[12.7509202957,49.0866737366],"type":"Point"}
}