{
  "type": "Feature",
  "properties": {
    "iso:country":"DE",
    "sg:address":"Im Hohen Felde 8",
    "sg:city":"Minden",
    "sg:phone":"+49 571/28431",
    "sg:postcode":"32425",
    "sg:province":"Nordrhein-Westfalen",
    "wof:name":"A. Laurischkat",
    "wof:placetype":"venue"
},
  "geometry": {"coordinates":[8.893721,52.298512],"type":"Point"}
}