{
  "type": "Feature",
  "properties": {
    "iso:country":"DE",
    "sg:address":"Dabetsweiler 35",
    "sg:city":"Wangen",
    "sg:phone":"+49 4975/286819",
    "sg:postcode":"88239",
    "sg:province":"Baden-W\u00fcrttemberg",
    "wof:name":"Dieter Hartneck",
    "wof:placetype":"venue"
},
  "geometry": {"coordinates":[9.81269,47.688381],"type":"Point"}
}