{
  "type": "Feature",
  "properties": {
    "iso:country":"DE",
    "sg:address":"Tassilostr. 6",
    "sg:city":"Neuching",
    "sg:phone":"+49 8123/889565",
    "sg:postcode":"85467",
    "sg:province":"Bayern",
    "wof:name":"Martin Vilgertshofer",
    "wof:placetype":"venue"
},
  "geometry": {"coordinates":[11.853999,48.239307],"type":"Point"}
}