{
  "type": "Feature",
  "properties": {
    "iso:country":"DE",
    "sg:address":"Krausenhof 1",
    "sg:city":"B\u00f6bingen",
    "sg:phone":"+49 7173/8949",
    "sg:postcode":"73560",
    "sg:province":"Baden-W\u00fcrttemberg",
    "wof:name":"M. Fuchs-franke Hebamme",
    "wof:placetype":"venue"
},
  "geometry": {"coordinates":[9.930539,48.835564],"type":"Point"}
}