{
  "type": "Feature",
  "properties": {
    "iso:country":"DE",
    "sg:address":"Kilianst\u00e4dter Str 29",
    "sg:city":"Sch\u00f6neck",
    "sg:phone":"+49 6187/9517221",
    "sg:postcode":"61137",
    "sg:province":"Hessen",
    "wof:name":"Ferdinand Feinwerktechnik Gmbh",
    "wof:placetype":"venue"
},
  "geometry": {"coordinates":[8.8410730362,50.2123146057],"type":"Point"}
}