{
  "type": "Feature",
  "properties": {
    "iso:country":"DE",
    "sg:address":"Frohsinnstr. 29",
    "sg:city":"Aschaffenburg",
    "sg:phone":"+49 6021/21328",
    "sg:postcode":"63739",
    "sg:province":"Bayern",
    "wof:name":"G\u00f6dert Immobilien Gmbh",
    "wof:placetype":"venue"
},
  "geometry": {"coordinates":[9.1446199417,49.9796791077],"type":"Point"}
}