{
  "type": "Feature",
  "properties": {
    "iso:country":"DE",
    "sg:address":"Heuchterstr. 68",
    "sg:city":"Wegberg",
    "sg:postcode":"41844",
    "sg:province":"Nordrhein-Westfalen",
    "wof:name":"Simw Markt- Und Produktanalysen Gmbh",
    "wof:placetype":"venue"
},
  "geometry": {"coordinates":[6.202918,51.142555],"type":"Point"}
}