{
  "type": "Feature",
  "properties": {
    "iso:country":"DE",
    "sg:address":"Lauterbachstr. 73",
    "sg:city":"Eggenfelden",
    "sg:phone":"+49 8721/8138",
    "sg:postcode":"84307",
    "sg:province":"Bayern",
    "wof:name":"Brand Gmbh",
    "wof:placetype":"venue"
},
  "geometry": {"coordinates":[12.739207,48.398094],"type":"Point"}
}