{
  "type": "Feature",
  "properties": {
    "iso:country":"DE",
    "sg:address":"Zum Husterbruch 41",
    "sg:city":"Petershagen",
    "sg:phone":"+49 5705/7829",
    "sg:postcode":"32469",
    "sg:province":"Nordrhein-Westfalen",
    "wof:name":"Wolfgang Riesner Architekt",
    "wof:placetype":"venue"
},
  "geometry": {"coordinates":[9.079353,52.420551],"type":"Point"}
}