{
  "type": "Feature",
  "properties": {
    "iso:country":"DE",
    "sg:address":"Landstr. 42",
    "sg:city":"Frankfurt",
    "sg:phone":"+49 4969/7191170",
    "sg:postcode":"60388",
    "sg:province":"Hessen",
    "wof:name":"Imi Bank Ag",
    "wof:placetype":"venue"
},
  "geometry": {"coordinates":[8.75415,50.155327],"type":"Point"}
}