{
  "type": "Feature",
  "properties": {
    "iso:country":"DE",
    "sg:address":"Josef-Koch-Str. 4d",
    "sg:city":"Gro\u00dfostheim",
    "sg:phone":"+49 6026/8190",
    "sg:postcode":"63762",
    "sg:province":"Bayern",
    "wof:name":"O. Grimm Immobilienmakler",
    "wof:placetype":"venue"
},
  "geometry": {"coordinates":[9.0308704376,49.9325180054],"type":"Point"}
}