{
  "type": "Feature",
  "properties": {
    "iso:country":"DE",
    "sg:address":"Saargem\u00fcnder Str. 56",
    "sg:city":"Mandelbachtal",
    "sg:phone":"+49 6803/3014",
    "sg:postcode":"66399",
    "sg:province":"Saarland",
    "wof:name":"Horst Mayer",
    "wof:placetype":"venue"
},
  "geometry": {"coordinates":[7.162437,49.186623],"type":"Point"}
}