{
  "type": "Feature",
  "properties": {
    "iso:country":"DE",
    "sg:address":"S\u00fcdstr. 8",
    "sg:city":"Bad Essen",
    "sg:phone":"+49 5472/2039",
    "sg:postcode":"49152",
    "sg:province":"Niedersachsen",
    "wof:name":"W. Und R. Benthien",
    "wof:placetype":"venue"
},
  "geometry": {"coordinates":[8.3658018112,52.3197975159],"type":"Point"}
}