{
  "type": "Feature",
  "properties": {
    "iso:country":"DE",
    "sg:address":"Hagener Str. 14",
    "sg:city":"Georgsmarienh\u00fctte",
    "sg:phone":"+49 5401/2344",
    "sg:postcode":"49124",
    "sg:province":"Niedersachsen",
    "wof:name":"Franz Gerwe",
    "wof:placetype":"venue"
},
  "geometry": {"coordinates":[8.029095,52.208382],"type":"Point"}
}