{
  "type": "Feature",
  "properties": {
    "iso:country":"DE",
    "sg:address":"Untere Rainstr. 22",
    "sg:city":"Weilheim",
    "sg:postcode":"73235",
    "sg:province":"Baden-W\u00fcrttemberg",
    "wof:name":"Frasch Verwaltungs Gmbh",
    "wof:placetype":"venue"
},
  "geometry": {"coordinates":[9.5327854156,48.6156845093],"type":"Point"}
}