{
  "type": "Feature",
  "properties": {
    "iso:country":"DE",
    "sg:address":"Ludwig-Cr\u00f6\u00dfmann-Str. 2",
    "sg:city":"Kulmbach",
    "sg:phone":"+49 9221/60600",
    "sg:postcode":"95326",
    "sg:province":"Bayern",
    "wof:name":"Nordseebad Kampen Auf Sylt-gmbh",
    "wof:placetype":"venue"
},
  "geometry": {"coordinates":[11.4476480484,50.099445343],"type":"Point"}
}