{
  "type": "Feature",
  "properties": {
    "iso:country":"DE",
    "sg:address":"Hofstr. 1",
    "sg:city":"M\u00fchlacker",
    "sg:phone":"+49 7041/5050",
    "sg:postcode":"75417",
    "sg:province":"Baden-W\u00fcrttemberg",
    "wof:name":"Enztal-immobilien Gmbh",
    "wof:placetype":"venue"
},
  "geometry": {"coordinates":[8.8422279358,48.9401359558],"type":"Point"}
}