{
  "type": "Feature",
  "properties": {
    "iso:country":"DE",
    "sg:address":"Artilleriestr. 43",
    "sg:city":"Osnabr\u00fcck",
    "sg:phone":"+49 541/64110",
    "sg:postcode":"49076",
    "sg:province":"Niedersachsen",
    "wof:name":"Frank-j\u00fcrgen Schwalb Architekt",
    "wof:placetype":"venue"
},
  "geometry": {"coordinates":[8.019707,52.284843],"type":"Point"}
}