{
  "type": "Feature",
  "properties": {
    "iso:country":"DE",
    "sg:address":"Weissenbachstr. 10",
    "sg:city":"Ravensburg",
    "sg:phone":"+49 751/24376",
    "sg:postcode":"88214",
    "sg:province":"Baden-W\u00fcrttemberg",
    "wof:name":"Martin Bott",
    "wof:placetype":"venue"
},
  "geometry": {"coordinates":[9.6090087891,47.7707290649],"type":"Point"}
}