{
  "type": "Feature",
  "properties": {
    "iso:country":"DE",
    "sg:address":"Schlo\u00dfberg 6a",
    "sg:city":"Harzgerode",
    "sg:phone":"+49 39484/2482",
    "sg:postcode":"06493",
    "sg:province":"Sachsen-Anhalt",
    "wof:name":"Gebr\u00fcder Bamberg Gmbh",
    "wof:placetype":"venue"
},
  "geometry": {"coordinates":[11.140949,51.64262],"type":"Point"}
}