{
  "type": "Feature",
  "properties": {
    "iso:country":"DE",
    "sg:address":"Privatweg 16a",
    "sg:city":"Hamburg",
    "sg:phone":"+49 40/543254",
    "sg:postcode":"22527",
    "sg:province":"Hamburg",
    "wof:name":"Wolfgang Stahmann Masseur",
    "wof:placetype":"venue"
},
  "geometry": {"coordinates":[9.934781,53.584175],"type":"Point"}
}