{
  "type": "Feature",
  "properties": {
    "iso:country":"DE",
    "sg:address":"Obergasse 2",
    "sg:city":"Oberwiesen",
    "sg:phone":"+49 6358/1284",
    "sg:postcode":"67294",
    "sg:province":"Rheinland-Pfalz",
    "wof:name":"Wolfgang Daub",
    "wof:placetype":"venue"
},
  "geometry": {"coordinates":[7.95857,49.698471],"type":"Point"}
}