{
  "type": "Feature",
  "properties": {
    "iso:country":"DE",
    "sg:address":"Schnepfenweg 2",
    "sg:city":"Wedemark",
    "sg:phone":"+49 5130/6185",
    "sg:postcode":"30900",
    "sg:province":"Niedersachsen",
    "wof:name":"H. Fehrmann",
    "wof:placetype":"venue"
},
  "geometry": {"coordinates":[9.776841,52.506924],"type":"Point"}
}