{
  "type": "Feature",
  "properties": {
    "iso:country":"DE",
    "sg:address":"Talstr. 10 a",
    "sg:city":"Langenfeld",
    "sg:phone":"+49 2173/13109",
    "sg:postcode":"40764",
    "sg:province":"Nordrhein-Westfalen",
    "wof:name":"Wilfried Schl\u00f6sser",
    "wof:placetype":"venue"
},
  "geometry": {"coordinates":[6.9524698257,51.1090698242],"type":"Point"}
}