{
  "type": "Feature",
  "properties": {
    "iso:country":"DE",
    "sg:address":"Zugspitzstr. 7",
    "sg:city":"Pullach",
    "sg:phone":"+49 89/744910",
    "sg:postcode":"82049",
    "sg:province":"Bayern",
    "wof:name":"Ifco System",
    "wof:placetype":"venue"
},
  "geometry": {"coordinates":[11.506785,48.038982],"type":"Point"}
}