{
  "type": "Feature",
  "properties": {
    "iso:country":"DE",
    "sg:address":"Mozartstr. 72",
    "sg:city":"Wendelstein",
    "sg:phone":"+49 9129/7692",
    "sg:postcode":"90530",
    "sg:province":"Bayern",
    "wof:name":"Im Fv-sportpark",
    "wof:placetype":"venue"
},
  "geometry": {"coordinates":[11.1548709869,49.3470497131],"type":"Point"}
}