{
  "type": "Feature",
  "properties": {
    "iso:country":"DE",
    "sg:address":"Frankfurter Str. 62",
    "sg:city":"L\u00fcbben",
    "sg:phone":"+49 3546/8114",
    "sg:postcode":"15907",
    "sg:province":"Brandenburg",
    "wof:name":"Mera Rabeler E. K. Inh. J\u00fcrgen Rabeler",
    "wof:placetype":"venue"
},
  "geometry": {"coordinates":[13.90331,51.945271],"type":"Point"}
}