{
  "type": "Feature",
  "properties": {
    "iso:country":"DE",
    "sg:address":"Bruchwiesenstr. 1",
    "sg:city":"Saarbr\u00fccken",
    "sg:phone":"+49 681/398786",
    "sg:postcode":"66111",
    "sg:province":"Saarland",
    "wof:name":"N. Kiefer Und R. Kiefer \u00dcbersetzungsb\u00fcro",
    "wof:placetype":"venue"
},
  "geometry": {"coordinates":[7.002101,49.234276],"type":"Point"}
}