{
  "type": "Feature",
  "properties": {
    "iso:country":"DE",
    "sg:address":"Fillibachstr. 16",
    "sg:city":"Freiburg",
    "sg:phone":"+49 761/554087",
    "sg:postcode":"79104",
    "sg:province":"Baden-W\u00fcrttemberg",
    "wof:name":"H.-j. Welke",
    "wof:placetype":"venue"
},
  "geometry": {"coordinates":[7.8649711609,48.0209197998],"type":"Point"}
}