{
  "type": "Feature",
  "properties": {
    "iso:country":"DE",
    "sg:address":"Kirchstr. 7",
    "sg:city":"Geilenkirchen",
    "sg:phone":"+49 2451/5224",
    "sg:postcode":"52511",
    "sg:province":"Nordrhein-Westfalen",
    "wof:name":"Restaurant M. Theves",
    "wof:placetype":"venue"
},
  "geometry": {"coordinates":[6.1690778732,50.9521636963],"type":"Point"}
}