{
  "type": "Feature",
  "properties": {
    "iso:country":"DE",
    "sg:address":"Guttenberger Hammer 2",
    "sg:city":"Grafengehaig",
    "sg:phone":"+49 4963/227990",
    "sg:postcode":"95356",
    "sg:province":"Bayern",
    "wof:name":"Kst Motorenversuch Gmbh & Co Kg",
    "wof:placetype":"venue"
},
  "geometry": {"coordinates":[8.204674,49.470181],"type":"Point"}
}