{
  "type": "Feature",
  "properties": {
    "iso:country":"DE",
    "sg:address":"Grotendonker Str. 60",
    "sg:city":"Kevelaer",
    "sg:phone":"+49 2832/80146",
    "sg:postcode":"47626",
    "sg:province":"Nordrhein-Westfalen",
    "wof:name":"Wilhelm Steenmans",
    "wof:placetype":"venue"
},
  "geometry": {"coordinates":[6.252392,51.597473],"type":"Point"}
}