{
  "type": "Feature",
  "properties": {
    "iso:country":"DE",
    "sg:address":"Berliner Str. 120",
    "sg:city":"Berlin",
    "sg:phone":"+49 30/8910010",
    "sg:postcode":"10713",
    "sg:province":"Berlin",
    "wof:name":"Harry Gerlach Wohnungsunternehmen Gmbh",
    "wof:placetype":"venue"
},
  "geometry": {"coordinates":[13.3178024292,52.4863777161],"type":"Point"}
}