{
  "type": "Feature",
  "properties": {
    "iso:country":"DE",
    "sg:address":"Oehmchenstr. 18",
    "sg:city":"Bergisch Gladbach",
    "sg:phone":"+49 2202/38762",
    "sg:postcode":"51469",
    "sg:province":"Nordrhein-Westfalen",
    "wof:name":"Lux Baustoffe Gmbh",
    "wof:placetype":"venue"
},
  "geometry": {"coordinates":[7.136802,50.981125],"type":"Point"}
}