{
  "type": "Feature",
  "properties": {
    "iso:country":"DE",
    "sg:address":"Wachtelstr. 5",
    "sg:city":"Wuppertal",
    "sg:phone":"+49 202/509246",
    "sg:postcode":"42281",
    "sg:province":"Nordrhein-Westfalen",
    "wof:name":"Dirk Alberding",
    "wof:placetype":"venue"
},
  "geometry": {"coordinates":[7.196618,51.280987],"type":"Point"}
}