{
  "type": "Feature",
  "properties": {
    "iso:country":"DE",
    "sg:address":"Lessingstr. 3",
    "sg:city":"Singen",
    "sg:phone":"+49 7731/48551",
    "sg:postcode":"78224",
    "sg:province":"Baden-W\u00fcrttemberg",
    "wof:name":"Waltraud Glatzel",
    "wof:placetype":"venue"
},
  "geometry": {"coordinates":[8.836883,47.76712],"type":"Point"}
}