{
  "type": "Feature",
  "properties": {
    "iso:country":"DE",
    "sg:address":"Neuenkirchener Str. 32",
    "sg:city":"Melle",
    "sg:phone":"+49 5422/2515",
    "sg:postcode":"49324",
    "sg:province":"Niedersachsen",
    "wof:name":"Pizzeria Fattoria",
    "wof:placetype":"venue"
},
  "geometry": {"coordinates":[8.334647,52.197197],"type":"Point"}
}