{
  "type": "Feature",
  "properties": {
    "iso:country":"DE",
    "sg:address":"Beim Rathaus 1",
    "sg:city":"Waiblingen",
    "sg:phone":"+49 7151/81694",
    "sg:postcode":"71336",
    "sg:province":"Baden-W\u00fcrttemberg",
    "wof:name":"Werner Baur Architekt",
    "wof:placetype":"venue"
},
  "geometry": {"coordinates":[9.321295,48.847755],"type":"Point"}
}