{
  "type": "Feature",
  "properties": {
    "iso:country":"DE",
    "sg:address":"Hauptstr. 36a",
    "sg:city":"Zeithain",
    "sg:postcode":"01619",
    "sg:province":"Sachsen",
    "wof:name":"Gup Transfer Ges. F\u00fcr Umwelt- Schutz Und Projektmanagem. Mbh",
    "wof:placetype":"venue"
},
  "geometry": {"coordinates":[13.3322134018,51.3377761841],"type":"Point"}
}