{
  "type": "Feature",
  "properties": {
    "iso:country":"DE",
    "sg:address":"\u00c4usserm\u00fchlstr. 35",
    "sg:city":"Dahn",
    "sg:phone":"+49 6391/92190",
    "sg:postcode":"66994",
    "sg:province":"Rheinland-Pfalz",
    "wof:name":"Hochd\u00f6rffer Gmbh",
    "wof:placetype":"venue"
},
  "geometry": {"coordinates":[7.770991,49.154385],"type":"Point"}
}