{
  "type": "Feature",
  "properties": {
    "iso:country":"DE",
    "sg:address":"Bahnhofstr. 71",
    "sg:city":"Ratingen",
    "sg:phone":"+49 2102/965212",
    "sg:postcode":"40883",
    "sg:province":"Nordrhein-Westfalen",
    "wof:name":"Archiv Der Eichendorff- Gesellschaft",
    "wof:placetype":"venue"
},
  "geometry": {"coordinates":[6.900204,51.336815],"type":"Point"}
}