{
  "type": "Feature",
  "properties": {
    "iso:country":"DE",
    "sg:address":"Beethovenstr. 31",
    "sg:city":"Malchow",
    "sg:phone":"+49 39932/83168",
    "sg:postcode":"17213",
    "sg:province":"Mecklenburg-Vorpommern",
    "wof:name":"Herbert Ziegler",
    "wof:placetype":"venue"
},
  "geometry": {"coordinates":[12.4087085724,53.4749259949],"type":"Point"}
}