{
  "type": "Feature",
  "properties": {
    "iso:country":"DE",
    "sg:address":"Wahrbrink 16",
    "sg:city":"Werne",
    "sg:phone":"+49 2389/533071",
    "sg:postcode":"59368",
    "sg:province":"Nordrhein-Westfalen",
    "wof:name":"Fliesen Klaverkamp Gmbh",
    "wof:placetype":"venue"
},
  "geometry": {"coordinates":[7.6058049202,51.6601333618],"type":"Point"}
}