{
  "type": "Feature",
  "properties": {
    "iso:country":"DE",
    "sg:address":"Karlsbrunner Str. 165",
    "sg:city":"V\u00f6lklingen",
    "sg:phone":"+49 6898/40464",
    "sg:postcode":"66333",
    "sg:province":"Saarland",
    "wof:name":"M. Stupp Heissmangel",
    "wof:placetype":"venue"
},
  "geometry": {"coordinates":[6.8006329536,49.2134590149],"type":"Point"}
}