{
  "type": "Feature",
  "properties": {
    "iso:country":"DE",
    "sg:address":"Kapfholzer Weg 2",
    "sg:city":"Weiler-Simmerberg",
    "sg:phone":"+49 8387/1095",
    "sg:postcode":"88171",
    "sg:province":"Bayern",
    "wof:name":"Eugen Wucherer",
    "wof:placetype":"venue"
},
  "geometry": {"coordinates":[9.918359,47.582165],"type":"Point"}
}