{
  "type": "Feature",
  "properties": {
    "iso:country":"DE",
    "sg:address":"Mozartstr. 77",
    "sg:city":"Osnabr\u00fcck",
    "sg:postcode":"49076",
    "sg:province":"Niedersachsen",
    "wof:name":"Gepol Projektmanagement Gmbh",
    "wof:placetype":"venue"
},
  "geometry": {"coordinates":[8.0134716034,52.2818641663],"type":"Point"}
}