{
  "type": "Feature",
  "properties": {
    "iso:country":"DE",
    "sg:address":"Zum Bilsknop 2",
    "sg:city":"Rehlingen-Siersburg",
    "sg:phone":"+49 6861/5035",
    "sg:postcode":"66780",
    "sg:province":"Saarland",
    "wof:name":"Hirtz Gmbh",
    "wof:placetype":"venue"
},
  "geometry": {"coordinates":[6.655652,49.399364],"type":"Point"}
}