{
  "type": "Feature",
  "properties": {
    "iso:country":"DE",
    "sg:address":"Im Winkel 2",
    "sg:city":"Fellheim",
    "sg:postcode":"87748",
    "sg:province":"Bayern",
    "wof:name":"Beauty-center",
    "wof:placetype":"venue"
},
  "geometry": {"coordinates":[10.150056839,48.0745010376],"type":"Point"}
}