{
  "type": "Feature",
  "properties": {
    "iso:country":"DE",
    "sg:address":"Bahnhofstr. 20",
    "sg:city":"Altenahr",
    "sg:phone":"+49 2643/8327",
    "sg:postcode":"53505",
    "sg:province":"Rheinland-Pfalz",
    "wof:name":"Restaurant Im Wurstkessel",
    "wof:placetype":"venue"
},
  "geometry": {"coordinates":[6.9779338837,50.5078430176],"type":"Point"}
}