{
  "type": "Feature",
  "properties": {
    "iso:country":"DE",
    "sg:address":"Wischenstieg 3a",
    "sg:city":"G\u00f6denstorf",
    "sg:phone":"+49 4175/842613",
    "sg:postcode":"21376",
    "sg:province":"Niedersachsen",
    "wof:name":"Ulrich Weselmann Architekt",
    "wof:placetype":"venue"
},
  "geometry": {"coordinates":[10.104518,53.196304],"type":"Point"}
}