{
  "type": "Feature",
  "properties": {
    "iso:country":"DE",
    "sg:address":"Richthofenstr. 75",
    "sg:city":"Kiel",
    "sg:phone":"+49 431/364590",
    "sg:postcode":"24159",
    "sg:province":"Schleswig-Holstein",
    "wof:name":"Ulrich Ibsch-russu Rechtsanwalt",
    "wof:placetype":"venue"
},
  "geometry": {"coordinates":[10.1331510544,54.3731994629],"type":"Point"}
}