{
  "type": "Feature",
  "properties": {
    "iso:country":"DE",
    "sg:address":"Marktstr. 7",
    "sg:city":"Friedrichroda",
    "sg:phone":"+49 3623/36600",
    "sg:postcode":"99894",
    "sg:province":"Th\u00fcringen",
    "wof:name":"Hof-apotheke",
    "wof:placetype":"venue"
},
  "geometry": {"coordinates":[10.566797,50.857334],"type":"Point"}
}