{
  "type": "Feature",
  "properties": {
    "iso:country":"DE",
    "sg:address":"Wiesenweg 3",
    "sg:city":"F\u00fcrth",
    "sg:phone":"+49 6253/3623",
    "sg:postcode":"64658",
    "sg:province":"Hessen",
    "wof:name":"H. Klunker",
    "wof:placetype":"venue"
},
  "geometry": {"coordinates":[8.7872972488,49.66015625],"type":"Point"}
}