{
  "type": "Feature",
  "properties": {
    "iso:country":"DE",
    "sg:address":"M\u00fchlw\u00f6rthweg 30",
    "sg:city":"Wertheim",
    "sg:phone":"+49 9342/7362",
    "sg:postcode":"97877",
    "sg:province":"Baden-W\u00fcrttemberg",
    "wof:name":"Josef Oetzel",
    "wof:placetype":"venue"
},
  "geometry": {"coordinates":[9.525219,49.74464],"type":"Point"}
}