{
  "type": "Feature",
  "properties": {
    "iso:country":"DE",
    "sg:address":"Martin-Luther-Str. 8",
    "sg:city":"B\u00f6hlen",
    "sg:postcode":"04564",
    "sg:province":"Sachsen",
    "wof:name":"Rolf Dembski",
    "wof:placetype":"venue"
},
  "geometry": {"coordinates":[12.384683,51.237026],"type":"Point"}
}