{
  "type": "Feature",
  "properties": {
    "iso:country":"DE",
    "sg:address":"Schrobenhausener Str. 54",
    "sg:city":"P\u00f6ttmes",
    "sg:phone":"+49 8253/515",
    "sg:postcode":"86554",
    "sg:province":"Bayern",
    "wof:name":"Bay Wa Ag",
    "wof:placetype":"venue"
},
  "geometry": {"coordinates":[11.101186,48.58276],"type":"Point"}
}