{
  "type": "Feature",
  "properties": {
    "iso:country":"DE",
    "sg:address":"Wetterstr. 58",
    "sg:city":"Herdecke",
    "sg:phone":"+49 2330/9260",
    "sg:postcode":"58313",
    "sg:province":"Nordrhein-Westfalen",
    "wof:name":"Cd-color Gmbh & Co. Kg",
    "wof:placetype":"venue"
},
  "geometry": {"coordinates":[7.422153,51.402306],"type":"Point"}
}