{
  "type": "Feature",
  "properties": {
    "iso:country":"DE",
    "sg:address":"Ferdinandstr. 8",
    "sg:city":"Dresden",
    "sg:postcode":"01069",
    "sg:province":"Sachsen",
    "wof:name":"K\u00f6ster-r\u00fctz Gastro Gmbh",
    "wof:placetype":"venue"
},
  "geometry": {"coordinates":[13.7376871109,51.0457801819],"type":"Point"}
}