{
  "type": "Feature",
  "properties": {
    "iso:country":"DE",
    "sg:address":"Langebr\u00fcckstr. 5",
    "sg:city":"Eckernf\u00f6rde",
    "sg:phone":"+49 4351/712450",
    "sg:postcode":"24340",
    "sg:province":"Schleswig-Holstein",
    "wof:name":"Mobiltel Communication Inh. Gunnar Lentz",
    "wof:placetype":"venue"
},
  "geometry": {"coordinates":[9.8357830048,54.4724807739],"type":"Point"}
}