{
  "type": "Feature",
  "properties": {
    "iso:country":"DE",
    "sg:address":"Berkersheimer Weg 6",
    "sg:city":"Frankfurt",
    "sg:phone":"+49 69/5481202",
    "sg:postcode":"60433",
    "sg:province":"Hessen",
    "wof:name":"Apotheke Am Frankfurter Berg",
    "wof:placetype":"venue"
},
  "geometry": {"coordinates":[8.680678,50.167831],"type":"Point"}
}