{
  "type": "Feature",
  "properties": {
    "iso:country":"DE",
    "sg:address":"Na\u00df\u00e4ckerstr. 35",
    "sg:city":"P\u00f6\u00dfneck",
    "sg:phone":"+49 3647/431090",
    "sg:postcode":"07381",
    "sg:province":"Th\u00fcringen",
    "wof:name":"Lochner & Franke",
    "wof:placetype":"venue"
},
  "geometry": {"coordinates":[11.625053,50.700867],"type":"Point"}
}