{
  "type": "Feature",
  "properties": {
    "iso:country":"DE",
    "sg:address":"Kirchweg 39",
    "sg:city":"Rethwisch",
    "sg:phone":"+49 4828/9220",
    "sg:postcode":"25566",
    "sg:province":"Schleswig-Holstein",
    "wof:name":"Dagmar Ritter",
    "wof:placetype":"venue"
},
  "geometry": {"coordinates":[9.5822172165,53.8652534485],"type":"Point"}
}