{
  "type": "Feature",
  "properties": {
    "iso:country":"DE",
    "sg:address":"Querstr. 11",
    "sg:city":"G\u00fcstrow",
    "sg:phone":"+49 3843/211988",
    "sg:postcode":"18273",
    "sg:province":"Mecklenburg-Vorpommern",
    "wof:name":"Ingo R\u00f6sler",
    "wof:placetype":"venue"
},
  "geometry": {"coordinates":[12.1796588898,53.7994232178],"type":"Point"}
}