{
  "type": "Feature",
  "properties": {
    "iso:country":"DE",
    "sg:address":"Im Wennetal 26",
    "sg:city":"Eslohe",
    "sg:phone":"+49 2973/97200",
    "sg:postcode":"59889",
    "sg:province":"Nordrhein-Westfalen",
    "wof:name":"Josef Baust Holzbetriebe Gmbh",
    "wof:placetype":"venue"
},
  "geometry": {"coordinates":[8.1980819702,51.2544708252],"type":"Point"}
}