{
  "type": "Feature",
  "properties": {
    "iso:country":"DE",
    "sg:address":"Hallplatz 90",
    "sg:city":"Zweibr\u00fccken",
    "sg:phone":"+49 6332/17005",
    "sg:postcode":"66482",
    "sg:province":"Rheinland-Pfalz",
    "wof:name":"Optica Uhren-petersch\u00fctz- Optik Gmbh",
    "wof:placetype":"venue"
},
  "geometry": {"coordinates":[7.360959053,49.2494735718],"type":"Point"}
}