{
  "type": "Feature",
  "properties": {
    "iso:country":"DE",
    "sg:address":"Lindwurmstr. 3",
    "sg:city":"M\u00fcnchen",
    "sg:phone":"+49 89/237280",
    "sg:postcode":"80337",
    "sg:province":"Bayern",
    "wof:name":"Universa Lebensversicherung Ag",
    "wof:placetype":"venue"
},
  "geometry": {"coordinates":[11.5656309128,48.1327514648],"type":"Point"}
}