{
  "type": "Feature",
  "properties": {
    "iso:country":"DE",
    "sg:address":"Kirchstr. 23",
    "sg:city":"Ehrenberg",
    "sg:phone":"+49 6681/364",
    "sg:postcode":"36115",
    "sg:province":"Hessen",
    "wof:name":"Ernst K\u00fcmpel",
    "wof:placetype":"venue"
},
  "geometry": {"coordinates":[10.0128507614,50.5411453247],"type":"Point"}
}