{
  "type": "Feature",
  "properties": {
    "iso:country":"DE",
    "sg:address":"Bornhardtstr. 18",
    "sg:city":"Clausthal-Zellerfeld",
    "sg:phone":"+49 5323/81640",
    "sg:postcode":"38678",
    "sg:province":"Niedersachsen",
    "wof:name":"Walter Winterhoff",
    "wof:placetype":"venue"
},
  "geometry": {"coordinates":[10.3356895447,51.8171653748],"type":"Point"}
}