{
  "type": "Feature",
  "properties": {
    "iso:country":"DE",
    "sg:address":"Marienring 11",
    "sg:city":"Landau",
    "sg:phone":"+49 6341/20086",
    "sg:postcode":"76829",
    "sg:province":"Rheinland-Pfalz",
    "wof:name":"Peter Laux Und U. Rieder",
    "wof:placetype":"venue"
},
  "geometry": {"coordinates":[8.1173372269,49.1944007874],"type":"Point"}
}