{
  "type": "Feature",
  "properties": {
    "iso:country":"DE",
    "sg:address":"St.-Georgen-Str. 41",
    "sg:city":"Pocking",
    "sg:phone":"+49 8531/7358",
    "sg:postcode":"94060",
    "sg:province":"Bayern",
    "wof:name":"Alois Lindinger",
    "wof:placetype":"venue"
},
  "geometry": {"coordinates":[13.3149118423,48.4039001465],"type":"Point"}
}