{
  "type": "Feature",
  "properties": {
    "iso:country":"DE",
    "sg:address":"Sebastianusstr. 41",
    "sg:city":"Lahnstein",
    "sg:phone":"+49 2621/4150",
    "sg:postcode":"56112",
    "sg:province":"Rheinland-Pfalz",
    "wof:name":"Gesellschaftlicher Verein Fidelio",
    "wof:placetype":"venue"
},
  "geometry": {"coordinates":[7.6160187721,50.2978134155],"type":"Point"}
}