{
  "type": "Feature",
  "properties": {
    "iso:country":"DE",
    "sg:address":"Vagedesstr. 23",
    "sg:city":"Ahaus",
    "sg:phone":"+49 2561/43644",
    "sg:postcode":"48683",
    "sg:province":"Nordrhein-Westfalen",
    "wof:name":"Gr\u00fcnewald Bautr\u00e4ger Gmbh",
    "wof:placetype":"venue"
},
  "geometry": {"coordinates":[7.002862,52.077915],"type":"Point"}
}