{
  "type": "Feature",
  "properties": {
    "iso:country":"DE",
    "sg:address":"Rochusstr. 38",
    "sg:city":"Aachen",
    "sg:postcode":"52062",
    "sg:province":"Nordrhein-Westfalen",
    "wof:name":"Rafael Vives Gastro Gmbh",
    "wof:placetype":"venue"
},
  "geometry": {"coordinates":[6.0873851776,50.7798728943],"type":"Point"}
}