{
  "type": "Feature",
  "properties": {
    "iso:country":"DE",
    "sg:address":"Junker-J\u00f6rg-Platz 9",
    "sg:city":"M\u00fcnster",
    "sg:postcode":"48167",
    "sg:province":"Nordrhein-Westfalen",
    "wof:name":"Eq-com Germany Gmbh",
    "wof:placetype":"venue"
},
  "geometry": {"coordinates":[7.689786911,51.9162826538],"type":"Point"}
}