{
  "type": "Feature",
  "properties": {
    "iso:country":"DE",
    "sg:address":"Wilhelmstr. 11",
    "sg:city":"M\u00fcllheim",
    "sg:phone":"+49 4976/312422",
    "sg:postcode":"79379",
    "sg:province":"Baden-W\u00fcrttemberg",
    "wof:name":"Luginsland Gmbh",
    "wof:placetype":"venue"
},
  "geometry": {"coordinates":[7.6291031837,47.8066177368],"type":"Point"}
}