{
  "type": "Feature",
  "properties": {
    "iso:country":"DE",
    "sg:address":"Sulzdorfer Str. 14",
    "sg:city":"Schw\u00e4bisch Hall",
    "sg:phone":"+49 791/2322",
    "sg:postcode":"74523",
    "sg:province":"Baden-W\u00fcrttemberg",
    "wof:name":"Hirsch",
    "wof:placetype":"venue"
},
  "geometry": {"coordinates":[9.7756071091,49.1071014404],"type":"Point"}
}