{
  "type": "Feature",
  "properties": {
    "iso:country":"DE",
    "sg:address":"Wollingster Str. 3",
    "sg:city":"Beverstedt",
    "sg:phone":"+49 4747/372",
    "sg:postcode":"27616",
    "sg:province":"Niedersachsen",
    "wof:name":"Hans Pleyn",
    "wof:placetype":"venue"
},
  "geometry": {"coordinates":[8.8326740265,53.4430046082],"type":"Point"}
}