{
  "type": "Feature",
  "properties": {
    "iso:country":"DE",
    "sg:address":"Kaiserstr. 2",
    "sg:city":"Uetze",
    "sg:phone":"+49 5173/98030",
    "sg:postcode":"31311",
    "sg:province":"Niedersachsen",
    "wof:name":"Die Neue Apotheke",
    "wof:placetype":"venue"
},
  "geometry": {"coordinates":[10.203142,52.464241],"type":"Point"}
}