{
  "type": "Feature",
  "properties": {
    "iso:country":"DE",
    "sg:address":"Duisburger Str. 76",
    "sg:city":"Emmerich",
    "sg:postcode":"46446",
    "sg:province":"Nordrhein-Westfalen",
    "wof:name":"Interactive Frischluft- Und Abgassysteme Gmbh",
    "wof:placetype":"venue"
},
  "geometry": {"coordinates":[6.276614,51.833157],"type":"Point"}
}