{
  "type": "Feature",
  "properties": {
    "iso:country":"DE",
    "sg:address":"Leuchterstr. 38",
    "sg:city":"K\u00f6ln",
    "sg:phone":"+49 221/9604201",
    "sg:postcode":"51069",
    "sg:province":"Nordrhein-Westfalen",
    "wof:name":"Marion Lehner-k\u00f6nig Rechtsanw\u00e4ltin",
    "wof:placetype":"venue"
},
  "geometry": {"coordinates":[7.0413780212,50.9965400696],"type":"Point"}
}