{
  "type": "Feature",
  "properties": {
    "iso:country":"DE",
    "sg:address":"Heddernheimer Kirchstr. 20",
    "sg:city":"Frankfurt",
    "sg:postcode":"60439",
    "sg:province":"Hessen",
    "wof:name":"Ev. St. Thomas Gemeinde",
    "wof:placetype":"venue"
},
  "geometry": {"coordinates":[8.646027565,50.1582603455],"type":"Point"}
}