{
  "type": "Feature",
  "properties": {
    "iso:country":"DE",
    "sg:address":"Oskar-von-Miller-Str. 10",
    "sg:city":"Dachau",
    "sg:phone":"+49 8131/72460",
    "sg:postcode":"85221",
    "sg:province":"Bayern",
    "wof:name":"G\u00fcnter Fill",
    "wof:placetype":"venue"
},
  "geometry": {"coordinates":[11.437987,48.247501],"type":"Point"}
}