{
  "type": "Feature",
  "properties": {
    "iso:country":"DE",
    "sg:city":"G\u00fctersloh",
    "sg:phone":"+49 5241/337575",
    "sg:postcode":"33330",
    "sg:province":"Nordrhein-Westfalen",
    "wof:name":"Institut F\u00fcr Ganzheitliche Kommunikation",
    "wof:placetype":"venue"
},
  "geometry": {"coordinates":[8.38098,51.909306],"type":"Point"}
}