{
  "type": "Feature",
  "properties": {
    "iso:country":"DE",
    "sg:address":"Wilhelm-Sommer-Str. 8",
    "sg:city":"Elsdorf",
    "sg:phone":"+49 2274/3255",
    "sg:postcode":"50189",
    "sg:province":"Nordrhein-Westfalen",
    "wof:name":"Kath. Pfarramt St. Lucia",
    "wof:placetype":"venue"
},
  "geometry": {"coordinates":[6.5542078018,50.9392204285],"type":"Point"}
}