{
  "type": "Feature",
  "properties": {
    "iso:country":"DE",
    "sg:address":"D\u00fcrerstr. 17",
    "sg:city":"Dissen",
    "sg:phone":"+49 5421/4712",
    "sg:postcode":"49201",
    "sg:province":"Niedersachsen",
    "wof:name":"Jochen Kipker Seeschiffahrts-u.",
    "wof:placetype":"venue"
},
  "geometry": {"coordinates":[8.215352,52.116379],"type":"Point"}
}