{
  "type": "Feature",
  "properties": {
    "iso:country":"DE",
    "sg:address":"Rennbahnstr. 4",
    "sg:city":"Pfarrkirchen",
    "sg:phone":"+49 8561/6847",
    "sg:postcode":"84347",
    "sg:province":"Bayern",
    "wof:name":"Felix Gibis",
    "wof:placetype":"venue"
},
  "geometry": {"coordinates":[12.9336662292,48.4317626953],"type":"Point"}
}