{
  "type": "Feature",
  "properties": {
    "iso:country":"DE",
    "sg:address":"Sch\u00f6llkrautstr. 40 a",
    "sg:city":"Berlin",
    "sg:phone":"+49 30/4363839",
    "sg:postcode":"13503",
    "sg:province":"Berlin",
    "wof:name":"Andreas Seifert Trockenbaugesellschaft Mbh",
    "wof:placetype":"venue"
},
  "geometry": {"coordinates":[13.240182,52.616245],"type":"Point"}
}