{
  "type": "Feature",
  "properties": {
    "iso:country":"DE",
    "sg:address":"Huosiring 10",
    "sg:city":"Weilheim",
    "sg:postcode":"82362",
    "sg:province":"Bayern",
    "wof:name":"Rover Mobili S. R. L. B & D Handelsagentur",
    "wof:placetype":"venue"
},
  "geometry": {"coordinates":[11.1272535324,47.8408050537],"type":"Point"}
}