{
  "type": "Feature",
  "properties": {
    "iso:country":"DE",
    "sg:address":"Otto-Schuster-Str. 51",
    "sg:city":"Ostfildern",
    "sg:phone":"+49 711/3412772",
    "sg:postcode":"73760",
    "sg:province":"Baden-W\u00fcrttemberg",
    "wof:name":"Baugenossenschaft Filder Eg",
    "wof:placetype":"venue"
},
  "geometry": {"coordinates":[9.2966604233,48.7156715393],"type":"Point"}
}