{
  "type": "Feature",
  "properties": {
    "iso:country":"DE",
    "sg:address":"Im Johannistal 53",
    "sg:city":"Wuppertal",
    "sg:phone":"+49 202/427225",
    "sg:postcode":"42119",
    "sg:province":"Nordrhein-Westfalen",
    "wof:name":"Hans Zimmermann Architekt",
    "wof:placetype":"venue"
},
  "geometry": {"coordinates":[7.151135,51.237705],"type":"Point"}
}