{
  "type": "Feature",
  "properties": {
    "iso:country":"DE",
    "sg:address":"Frankfurter Str. 101",
    "sg:city":"Raunheim",
    "sg:postcode":"65479",
    "sg:province":"Hessen",
    "wof:name":"Ilyas Solutions Gmbh",
    "wof:placetype":"venue"
},
  "geometry": {"coordinates":[8.4629468918,50.0168075562],"type":"Point"}
}