{
  "type": "Feature",
  "properties": {
    "iso:country":"DE",
    "sg:address":"Wohlfarth 19",
    "sg:city":"Much",
    "sg:phone":"+49 2245/3145",
    "sg:postcode":"53804",
    "sg:province":"Nordrhein-Westfalen",
    "wof:name":"Heinrich Kraus",
    "wof:placetype":"venue"
},
  "geometry": {"coordinates":[7.398786,50.874081],"type":"Point"}
}