{
  "type": "Feature",
  "properties": {
    "iso:country":"DE",
    "sg:address":"Braugasse 7",
    "sg:city":"Sonneberg",
    "sg:phone":"+49 3675/742040",
    "sg:postcode":"96515",
    "sg:province":"Th\u00fcringen",
    "wof:name":"Braun Steiner & Co. Kg",
    "wof:placetype":"venue"
},
  "geometry": {"coordinates":[11.1731309891,50.3644065857],"type":"Point"}
}