{
  "type": "Feature",
  "properties": {
    "iso:country":"DE",
    "sg:address":"Oberdorf 9",
    "sg:city":"Winterbach",
    "sg:phone":"+49 7181/72110",
    "sg:postcode":"73650",
    "sg:province":"Baden-W\u00fcrttemberg",
    "wof:name":"Hans Raithle Gmbh",
    "wof:placetype":"venue"
},
  "geometry": {"coordinates":[9.479541,48.798878],"type":"Point"}
}