{
  "type": "Feature",
  "properties": {
    "iso:country":"DE",
    "sg:address":"Im Winkel 1",
    "sg:city":"Bovenau",
    "sg:phone":"+49 4334/1210",
    "sg:postcode":"24796",
    "sg:province":"Schleswig-Holstein",
    "wof:name":"Kaethe Arndt Heissmangel",
    "wof:placetype":"venue"
},
  "geometry": {"coordinates":[9.8250188828,54.3300743103],"type":"Point"}
}