{
  "type": "Feature",
  "properties": {
    "iso:country":"DE",
    "sg:address":"Eidinghausener Str. 103",
    "sg:city":"Bad Oeynhausen",
    "sg:phone":"+49 5731/51515",
    "sg:postcode":"32549",
    "sg:province":"Nordrhein-Westfalen",
    "wof:name":"M. K\u00f6string",
    "wof:placetype":"venue"
},
  "geometry": {"coordinates":[8.799941,52.220402],"type":"Point"}
}