{
  "type": "Feature",
  "properties": {
    "iso:country":"DE",
    "sg:address":"Wilhelm-Leuschner-Str. 97",
    "sg:city":"Griesheim",
    "sg:phone":"+49 6155/84060",
    "sg:postcode":"64347",
    "sg:province":"Hessen",
    "wof:name":"Marcus Gass",
    "wof:placetype":"venue"
},
  "geometry": {"coordinates":[8.5670967102,49.8610649109],"type":"Point"}
}