{
  "type": "Feature",
  "properties": {
    "iso:country":"DE",
    "sg:address":"Albert-Schweitzer-Str. 63",
    "sg:city":"Kraichtal",
    "sg:phone":"+49 7251/60547",
    "sg:postcode":"76703",
    "sg:province":"Baden-W\u00fcrttemberg",
    "wof:name":"Karl-r. Ermert Automatenstickerei",
    "wof:placetype":"venue"
},
  "geometry": {"coordinates":[8.689330101,49.1413650513],"type":"Point"}
}