{
  "type": "Feature",
  "properties": {
    "iso:country":"DE",
    "sg:address":"K\u00f6lner Stra\u00dfe 85",
    "sg:city":"Leverkusen",
    "sg:postcode":"51379",
    "sg:province":"Nordrhein-Westfalen",
    "wof:name":"Stempelkrempel",
    "wof:placetype":"venue"
},
  "geometry": {"coordinates":[7.003925,51.062275],"type":"Point"}
}