{
  "type": "Feature",
  "properties": {
    "iso:country":"DE",
    "sg:address":"Gremberger Str. 80",
    "sg:city":"K\u00f6ln",
    "sg:phone":"+49 221/836546",
    "sg:postcode":"51105",
    "sg:province":"Nordrhein-Westfalen",
    "wof:name":"Ernst Streng",
    "wof:placetype":"venue"
},
  "geometry": {"coordinates":[6.999352932,50.9290771484],"type":"Point"}
}