{
  "type": "Feature",
  "properties": {
    "iso:country":"DE",
    "sg:address":"Zuckelhausener Ring 8",
    "sg:city":"Leipzig-Holzhausen",
    "sg:phone":"+49 34927/48697",
    "sg:postcode":"04454",
    "wof:name":"Thomas Ohrenschall Gmbh",
    "wof:placetype":"venue"
},
  "geometry": {"coordinates":[12.47149,51.300549],"type":"Point"}
}