{
  "type": "Feature",
  "properties": {
    "iso:country":"DE",
    "sg:address":"Br\u00fchlmatten 11",
    "sg:city":"Sulzburg",
    "sg:phone":"+49 7634/8355",
    "sg:postcode":"79295",
    "sg:province":"Baden-W\u00fcrttemberg",
    "wof:name":"Dieter Willy",
    "wof:placetype":"venue"
},
  "geometry": {"coordinates":[7.7007908821,47.8475112915],"type":"Point"}
}