{
  "type": "Feature",
  "properties": {
    "iso:country":"DE",
    "sg:address":"Pegauer Str. 75",
    "sg:city":"Zwenkau",
    "sg:phone":"+49 34203/52813",
    "sg:postcode":"04442",
    "sg:province":"Sachsen",
    "wof:name":"Christiane Heilmann",
    "wof:placetype":"venue"
},
  "geometry": {"coordinates":[12.325318,51.213402],"type":"Point"}
}