{
  "type": "Feature",
  "properties": {
    "iso:country":"DE",
    "sg:address":"Lange Str. 19a",
    "sg:city":"Klein Oschersleben",
    "sg:phone":"+49 39408/5029",
    "sg:postcode":"39398",
    "sg:province":"Sachsen-Anhalt",
    "wof:name":"Kindertagesst\u00e4tte",
    "wof:placetype":"venue"
},
  "geometry": {"coordinates":[11.3016529083,51.9900398254],"type":"Point"}
}