{
  "type": "Feature",
  "properties": {
    "iso:country":"DE",
    "sg:address":"Hohenzollerndamm 11",
    "sg:city":"Berlin",
    "sg:postcode":"10717",
    "sg:province":"Berlin",
    "wof:name":"Evergreens Comeback Medien Gesch\u00e4ftsf\u00fchrungs Gmbh",
    "wof:placetype":"venue"
},
  "geometry": {"coordinates":[13.326152,52.494877],"type":"Point"}
}