{
  "type": "Feature",
  "properties": {
    "iso:country":"DE",
    "sg:address":"Hauptstr. 458",
    "sg:city":"K\u00f6nigswinter",
    "sg:phone":"+49 2223/22650",
    "sg:postcode":"53639",
    "sg:province":"Nordrhein-Westfalen",
    "wof:name":"Weingut A. Und U. Pieper",
    "wof:placetype":"venue"
},
  "geometry": {"coordinates":[7.1948928833,50.6720046997],"type":"Point"}
}