{
  "type": "Feature",
  "properties": {
    "iso:country":"DE",
    "sg:address":"Johannisstr. 5",
    "sg:city":"N\u00fcrnberg",
    "sg:phone":"+49 911/337777",
    "sg:postcode":"90419",
    "sg:province":"Bayern",
    "wof:name":"Institut F\u00fcr K\u00fcnstliche Augen Kurt Rauch Gmbh",
    "wof:placetype":"venue"
},
  "geometry": {"coordinates":[11.069742,49.456833],"type":"Point"}
}