{
  "type": "Feature",
  "properties": {
    "iso:country":"DE",
    "sg:address":"Auf der Goldbreite 16",
    "sg:city":"Dortmund",
    "sg:phone":"+49 231/672203",
    "sg:postcode":"44379",
    "sg:province":"Nordrhein-Westfalen",
    "wof:name":"Paul Emmerich",
    "wof:placetype":"venue"
},
  "geometry": {"coordinates":[7.366774,51.526222],"type":"Point"}
}