{
  "type": "Feature",
  "properties": {
    "iso:country":"DE",
    "sg:address":"Kussenberg 5",
    "sg:city":"St. M\u00e4rgen",
    "sg:phone":"+49 7669/672",
    "sg:postcode":"79274",
    "sg:province":"Baden-W\u00fcrttemberg",
    "wof:name":"August Guth",
    "wof:placetype":"venue"
},
  "geometry": {"coordinates":[8.064916,47.99889],"type":"Point"}
}