{
  "type": "Feature",
  "properties": {
    "iso:country":"DE",
    "sg:address":"Haselhecke 5",
    "sg:city":"Marburg",
    "sg:phone":"+49 6421/32160",
    "sg:postcode":"35041",
    "sg:province":"Hessen",
    "wof:name":"Hans Fischer",
    "wof:placetype":"venue"
},
  "geometry": {"coordinates":[8.748345,50.81551],"type":"Point"}
}