{
  "type": "Feature",
  "properties": {
    "iso:country":"DE",
    "sg:address":"Juteweberstr. 1",
    "sg:city":"Rheine",
    "sg:phone":"+49 5975/93187",
    "sg:postcode":"48432",
    "sg:province":"Nordrhein-Westfalen",
    "wof:name":"Rohrbiegerei Robitec Gmbh",
    "wof:placetype":"venue"
},
  "geometry": {"coordinates":[7.4717478752,52.2193260193],"type":"Point"}
}