{
  "type": "Feature",
  "properties": {
    "iso:country":"DE",
    "sg:address":"Kreillerstr. 138a",
    "sg:city":"M\u00fcnchen",
    "sg:phone":"+49 89/435886",
    "sg:postcode":"81825",
    "sg:province":"Bayern",
    "wof:name":"Heinz Schulz Kameramann",
    "wof:placetype":"venue"
},
  "geometry": {"coordinates":[11.6516122818,48.1250152588],"type":"Point"}
}