{
  "type": "Feature",
  "properties": {
    "iso:country":"DE",
    "sg:address":"Op de Berg 1A",
    "sg:city":"Selfkant",
    "sg:phone":"+49 2456/1555",
    "sg:postcode":"52538",
    "sg:province":"Nordrhein-Westfalen",
    "wof:name":"Hubert Jessen Gmbh Elektro Und Heizung",
    "wof:placetype":"venue"
},
  "geometry": {"coordinates":[5.939444,51.024864],"type":"Point"}
}