{
  "type": "Feature",
  "properties": {
    "iso:country":"DE",
    "sg:address":"Altstadt 29",
    "sg:city":"Landshut",
    "sg:phone":"+49 871/821960",
    "sg:postcode":"84028",
    "sg:province":"Bayern",
    "wof:name":"Filmtheater - Betriebe Anna Wimmer & S\u00f6hne Ohg",
    "wof:placetype":"venue"
},
  "geometry": {"coordinates":[12.1503915787,48.5341682434],"type":"Point"}
}