{
  "type": "Feature",
  "properties": {
    "iso:country":"DE",
    "sg:address":"Cockerillstr. 69",
    "sg:city":"Stolberg",
    "sg:phone":"+49 2402/860380",
    "sg:postcode":"52222",
    "sg:province":"Nordrhein-Westfalen",
    "wof:name":"Allsan Brand- Wasserschadensanierung Gmbh",
    "wof:placetype":"venue"
},
  "geometry": {"coordinates":[6.2174100876,50.7756309509],"type":"Point"}
}