{
  "type": "Feature",
  "properties": {
    "iso:country":"DE",
    "sg:address":"Untere Krankenhausstr. 14",
    "sg:city":"Schneeberg",
    "sg:phone":"+49 3772/382059",
    "sg:postcode":"08289",
    "sg:province":"Sachsen",
    "wof:name":"Mario Stephan",
    "wof:placetype":"venue"
},
  "geometry": {"coordinates":[12.6379232407,50.5917816162],"type":"Point"}
}