{
  "type": "Feature",
  "properties": {
    "iso:country":"DE",
    "sg:address":"Raiffeisenstr. 3",
    "sg:city":"Egling",
    "sg:phone":"+49 8176/93000",
    "sg:postcode":"82544",
    "sg:province":"Bayern",
    "wof:name":"Raiffeisen-versicherungsdienst Endlhausen Gmbh",
    "wof:placetype":"venue"
},
  "geometry": {"coordinates":[11.5751304626,47.9428329468],"type":"Point"}
}