{
  "type": "Feature",
  "properties": {
    "iso:country":"DE",
    "sg:address":"Emminghausstr. 36",
    "sg:city":"Usingen",
    "sg:phone":"+49 6081/3955",
    "sg:postcode":"61250",
    "sg:province":"Hessen",
    "wof:name":"Professional Consulting Simon E. A. Payne",
    "wof:placetype":"venue"
},
  "geometry": {"coordinates":[8.5403308868,50.3269004822],"type":"Point"}
}