{
  "type": "Feature",
  "properties": {
    "iso:country":"DE",
    "sg:address":"B\u00e4renberg",
    "sg:city":"Plettenberg",
    "sg:phone":"+49 2391/3972",
    "sg:postcode":"58840",
    "sg:province":"Nordrhein-Westfalen",
    "wof:name":"Philipp Heist",
    "wof:placetype":"venue"
},
  "geometry": {"coordinates":[7.921725,51.208988],"type":"Point"}
}