{
  "type": "Feature",
  "properties": {
    "iso:country":"DE",
    "sg:address":"M\u00fcnsterstra\u00dfe 33",
    "sg:city":"Harsewinkel",
    "sg:phone":"+49 5247/120",
    "sg:postcode":"33428",
    "sg:province":"Nordrhein-Westfalen",
    "wof:name":"Claas Kgaa",
    "wof:placetype":"venue"
},
  "geometry": {"coordinates":[8.2182512283,51.9610595703],"type":"Point"}
}