{
  "type": "Feature",
  "properties": {
    "iso:country":"DE",
    "sg:address":"Borkenstr. 15a",
    "sg:city":"Torgelow",
    "sg:phone":"+49 3976/432690",
    "sg:postcode":"17358",
    "sg:province":"Mecklenburg-Vorpommern",
    "wof:name":"O. Matthee",
    "wof:placetype":"venue"
},
  "geometry": {"coordinates":[14.000648,53.63327],"type":"Point"}
}