{
  "type": "Feature",
  "properties": {
    "iso:country":"DE",
    "sg:address":"Industriestr. 22",
    "sg:city":"Edewecht",
    "sg:phone":"+49 4405/7673",
    "sg:postcode":"26188",
    "sg:province":"Niedersachsen",
    "wof:name":"Schiedel & Von Saint Gmbh",
    "wof:placetype":"venue"
},
  "geometry": {"coordinates":[7.989855,53.115761],"type":"Point"}
}