{
  "type": "Feature",
  "properties": {
    "iso:country":"DE",
    "sg:address":"Naturfreundestr. 21",
    "sg:city":"Hausham",
    "sg:phone":"+49 8026/95730",
    "sg:postcode":"83734",
    "sg:province":"Bayern",
    "wof:name":"Sieglinde Fischer Steuerbevollm\u00e4chtigte",
    "wof:placetype":"venue"
},
  "geometry": {"coordinates":[11.837647438,47.7458534241],"type":"Point"}
}