{
  "type": "Feature",
  "properties": {
    "iso:country":"DE",
    "sg:address":"Carl-von-Linde-Str. 2",
    "sg:city":"Untersteinach",
    "sg:phone":"+49 9225/6099",
    "sg:postcode":"95369",
    "sg:province":"Bayern",
    "wof:name":"Wimmer Gmbh",
    "wof:placetype":"venue"
},
  "geometry": {"coordinates":[11.54368,50.139923],"type":"Point"}
}