{
  "type": "Feature",
  "properties": {
    "iso:country":"DE",
    "sg:address":"Ha-Martin-Schleyer-Str 12-14",
    "sg:city":"Willich",
    "sg:phone":"+49 2154/4980",
    "sg:postcode":"47877",
    "sg:province":"Nordrhein-Westfalen",
    "wof:name":"Rmp Elektroniksysteme Gmbh",
    "wof:placetype":"venue"
},
  "geometry": {"coordinates":[6.512557,51.278625],"type":"Point"}
}