{
  "type": "Feature",
  "properties": {
    "iso:country":"DE",
    "sg:address":"D\u00f6rrieloh 39",
    "sg:city":"Varrel",
    "sg:phone":"+49 4274/494",
    "sg:postcode":"27259",
    "sg:province":"Niedersachsen",
    "wof:name":"Fritz G\u00f6tze",
    "wof:placetype":"venue"
},
  "geometry": {"coordinates":[8.700462,52.602028],"type":"Point"}
}