{
  "type": "Feature",
  "properties": {
    "iso:country":"DE",
    "sg:address":"Lokstedter Steindamm 23",
    "sg:city":"Hamburg",
    "sg:phone":"+49 40/5531722",
    "sg:postcode":"22529",
    "sg:province":"Hamburg",
    "wof:name":"Dr. Med. Klaus Reich",
    "wof:placetype":"venue"
},
  "geometry": {"coordinates":[9.9662466049,53.5964813232],"type":"Point"}
}