{
  "type": "Feature",
  "properties": {
    "iso:country":"DE",
    "sg:address":"Bachstr. 4",
    "sg:city":"Tiefthal",
    "sg:phone":"+49 36201/7087",
    "sg:postcode":"99189",
    "sg:province":"Th\u00fcringen",
    "wof:name":"H.-georg Heinze",
    "wof:placetype":"venue"
},
  "geometry": {"coordinates":[10.9491100311,51.0224494934],"type":"Point"}
}