{
  "type": "Feature",
  "properties": {
    "iso:country":"DE",
    "sg:address":"Gartenweg 7",
    "sg:city":"Greifswald",
    "sg:postcode":"17493",
    "sg:province":"Mecklenburg-Vorpommern",
    "wof:name":"Dr. Med. Ursula Frick",
    "wof:placetype":"venue"
},
  "geometry": {"coordinates":[13.443433,54.089909],"type":"Point"}
}