{
  "type": "Feature",
  "properties": {
    "iso:country":"DE",
    "sg:address":"Am Kamp 6",
    "sg:city":"Bad Doberan",
    "sg:phone":"+49 38203/63114",
    "sg:postcode":"18209",
    "sg:province":"Mecklenburg-Vorpommern",
    "wof:name":"R. Zeug",
    "wof:placetype":"venue"
},
  "geometry": {"coordinates":[11.909581,54.110542],"type":"Point"}
}