{
  "type": "Feature",
  "properties": {
    "iso:country":"DE",
    "sg:address":"Augsburger Str. 38",
    "sg:city":"Schongau",
    "sg:phone":"+49 8861/20198",
    "sg:postcode":"86956",
    "sg:province":"Bayern",
    "wof:name":"Robert Heidenreich",
    "wof:placetype":"venue"
},
  "geometry": {"coordinates":[10.896743,47.818142],"type":"Point"}
}