{
  "type": "Feature",
  "properties": {
    "iso:country":"DE",
    "sg:address":"Lahnstr. 86a",
    "sg:city":"Berlin",
    "sg:phone":"+49 30/68058910",
    "sg:postcode":"12055",
    "sg:province":"Berlin",
    "wof:name":"Aedes Bauteam Gmbh",
    "wof:placetype":"venue"
},
  "geometry": {"coordinates":[13.44381,52.468002],"type":"Point"}
}