{
  "type": "Feature",
  "properties": {
    "iso:country":"DE",
    "sg:address":"Klingemannstr. 8",
    "sg:city":"Wolfsburg",
    "sg:phone":"+49 5363/73160",
    "sg:postcode":"38448",
    "sg:province":"Niedersachsen",
    "wof:name":"B. Aschemann",
    "wof:placetype":"venue"
},
  "geometry": {"coordinates":[10.8488025665,52.4339637756],"type":"Point"}
}