{
  "type": "Feature",
  "properties": {
    "iso:country":"DE",
    "sg:address":"Ostseeallee 32",
    "sg:city":"Ostseebad Boltenhagen",
    "sg:phone":"+49 3881/712966",
    "sg:postcode":"23946",
    "sg:province":"Mecklenburg-Vorpommern",
    "wof:name":"W\u00fcrtembergische Versicherung Kurt Viergutz",
    "wof:placetype":"venue"
},
  "geometry": {"coordinates":[11.207734108,53.9454841614],"type":"Point"}
}