{
  "type": "Feature",
  "properties": {
    "iso:country":"DE",
    "sg:address":"Wilhelmstr. 15a",
    "sg:city":"Bad D\u00fcrrheim",
    "sg:phone":"+49 7726/5380",
    "sg:postcode":"78073",
    "sg:province":"Baden-W\u00fcrttemberg",
    "wof:name":"Imbi\u00df G. Eck",
    "wof:placetype":"venue"
},
  "geometry": {"coordinates":[8.5327739716,48.023021698],"type":"Point"}
}