{
  "type": "Feature",
  "properties": {
    "iso:country":"DE",
    "sg:address":"Mittelpromenade 23",
    "sg:city":"Ostseebad Boltenhagen",
    "sg:phone":"+49 38825/400",
    "sg:postcode":"23946",
    "sg:province":"Mecklenburg-Vorpommern",
    "wof:name":"Hotel John Brickmann",
    "wof:placetype":"venue"
},
  "geometry": {"coordinates":[11.207734108,53.9454841614],"type":"Point"}
}