{
  "type": "Feature",
  "properties": {
    "iso:country":"DE",
    "sg:address":"Buchenstr. 11",
    "sg:city":"Leopoldsh\u00f6he",
    "sg:phone":"+49 5202/81093",
    "sg:postcode":"33818",
    "sg:province":"Nordrhein-Westfalen",
    "wof:name":"Elfriede Brunner",
    "wof:placetype":"venue"
},
  "geometry": {"coordinates":[8.6695070267,51.9770622253],"type":"Point"}
}