{
  "type": "Feature",
  "properties": {
    "iso:country":"DE",
    "sg:address":"Eibergweg 13",
    "sg:city":"Essen",
    "sg:phone":"+49 201/521253",
    "sg:postcode":"45279",
    "sg:province":"Nordrhein-Westfalen",
    "wof:name":"Heinz Asmut",
    "wof:placetype":"venue"
},
  "geometry": {"coordinates":[7.121312,51.451363],"type":"Point"}
}