{
  "type": "Feature",
  "properties": {
    "iso:country":"DE",
    "sg:address":"Nordenstiftsweg 105",
    "sg:city":"Hamm",
    "sg:phone":"+49 2381/65072",
    "sg:postcode":"59065",
    "sg:province":"Nordrhein-Westfalen",
    "wof:name":"Anton Stock",
    "wof:placetype":"venue"
},
  "geometry": {"coordinates":[7.792382,51.687145],"type":"Point"}
}