{
  "type": "Feature",
  "properties": {
    "iso:country":"DE",
    "sg:address":"Am Bahnhof 4",
    "sg:city":"Bad Tennstedt",
    "sg:phone":"+49 36041/57689",
    "sg:postcode":"99955",
    "sg:province":"Th\u00fcringen",
    "wof:name":"Halung & Co. Gmbh",
    "wof:placetype":"venue"
},
  "geometry": {"coordinates":[10.840088,51.15229],"type":"Point"}
}