{
  "type": "Feature",
  "properties": {
    "iso:country":"DE",
    "sg:address":"Bahnstr. 38",
    "sg:city":"Bochum",
    "sg:phone":"+49 4944/4199940",
    "sg:postcode":"44793",
    "sg:province":"Nordrhein-Westfalen",
    "wof:name":"Fienhage Gmbh",
    "wof:placetype":"venue"
},
  "geometry": {"coordinates":[8.395855,52.781006],"type":"Point"}
}