{
  "type": "Feature",
  "properties": {
    "iso:country":"DE",
    "sg:address":"Obergasse 31",
    "sg:city":"Lauterbach",
    "sg:phone":"+49 6641/63884",
    "sg:postcode":"36341",
    "sg:province":"Hessen",
    "wof:name":"Hahn & Tobisch",
    "wof:placetype":"venue"
},
  "geometry": {"coordinates":[9.3951749802,50.6369972229],"type":"Point"}
}