{
  "type": "Feature",
  "properties": {
    "iso:country":"DE",
    "sg:address":"Hauptstr. 96",
    "sg:city":"Garmisch-Partenkirchen",
    "sg:phone":"+49 8821/53838",
    "sg:postcode":"82467",
    "sg:province":"Bayern",
    "wof:name":"D. Ulbrich",
    "wof:placetype":"venue"
},
  "geometry": {"coordinates":[11.111526,47.490349],"type":"Point"}
}