{
  "type": "Feature",
  "properties": {
    "iso:country":"DE",
    "sg:address":"Walpurgisstr. 46",
    "sg:city":"Gelsenkirchen",
    "sg:phone":"+49 209/83720",
    "sg:postcode":"45888",
    "sg:province":"Nordrhein-Westfalen",
    "wof:name":"Herbert Weidenb\u00f6rner",
    "wof:placetype":"venue"
},
  "geometry": {"coordinates":[7.1037378311,51.5189933777],"type":"Point"}
}