{
  "type": "Feature",
  "properties": {
    "iso:country":"DE",
    "sg:address":"Dieskaustr. 20",
    "sg:city":"Leipzig",
    "sg:phone":"+49 341/4247111",
    "sg:postcode":"04229",
    "sg:province":"Sachsen",
    "wof:name":"Hans-j\u00fcrgen Heinrich",
    "wof:placetype":"venue"
},
  "geometry": {"coordinates":[12.328054,51.318745],"type":"Point"}
}