{
  "type": "Feature",
  "properties": {
    "iso:country":"DE",
    "sg:address":"Schwingstr. 4-6",
    "sg:city":"Mannheim",
    "sg:phone":"+49 621/851201",
    "sg:postcode":"68199",
    "sg:province":"Baden-W\u00fcrttemberg",
    "wof:name":"Malerbetrieb Heer Kg",
    "wof:placetype":"venue"
},
  "geometry": {"coordinates":[8.4927,49.449924],"type":"Point"}
}