{
  "type": "Feature",
  "properties": {
    "iso:country":"DE",
    "sg:address":"Zur Osterwiese 46",
    "sg:city":"Marsberg",
    "sg:phone":"+49 2991/305",
    "sg:postcode":"34431",
    "sg:province":"Nordrhein-Westfalen",
    "wof:name":"Reinhard Zeitler Immolilien- Consulting Und Vertrieb Gmbh",
    "wof:placetype":"venue"
},
  "geometry": {"coordinates":[8.771689415,51.4210624695],"type":"Point"}
}