{
  "type": "Feature",
  "properties": {
    "iso:country":"DE",
    "sg:address":"Fuhrstr 47",
    "sg:city":"Solingen",
    "sg:phone":"+49 212/312524",
    "sg:postcode":"42719",
    "sg:province":"Nordrhein-Westfalen",
    "wof:name":"Hgs Besteckfabrik Herbert Gosebrink Kg",
    "wof:placetype":"venue"
},
  "geometry": {"coordinates":[7.059902,51.193542],"type":"Point"}
}