{
  "type": "Feature",
  "properties": {
    "iso:country":"DE",
    "sg:address":"Kurt-Schumacher-Str. 58",
    "sg:city":"F\u00fcrstenfeldbruck",
    "sg:phone":"+49 8141/20810",
    "sg:postcode":"82256",
    "sg:province":"Bayern",
    "wof:name":"Glas Spenglerei-bedachung Gmbh",
    "wof:placetype":"venue"
},
  "geometry": {"coordinates":[11.23858,48.180679],"type":"Point"}
}