{
  "type": "Feature",
  "properties": {
    "iso:country":"DE",
    "sg:address":"Dorfring 11",
    "sg:city":"Barsb\u00fcttel",
    "sg:phone":"+49 40/7109450",
    "sg:postcode":"22885",
    "sg:province":"Schleswig-Holstein",
    "wof:name":"Mk Schornstein Gmbh",
    "wof:placetype":"venue"
},
  "geometry": {"coordinates":[10.242622,53.57016],"type":"Point"}
}