{
  "type": "Feature",
  "properties": {
    "iso:country":"DE",
    "sg:address":"Am Rathaus 7",
    "sg:city":"Kurort Seiffen",
    "sg:phone":"+49 37362/8694",
    "sg:postcode":"09548",
    "sg:province":"Sachsen",
    "wof:name":"G. Schalling",
    "wof:placetype":"venue"
},
  "geometry": {"coordinates":[13.450343132,50.6477088928],"type":"Point"}
}