{
  "type": "Feature",
  "properties": {
    "iso:country":"DE",
    "sg:address":"M\u00fcnzgasse 2",
    "sg:city":"Hechingen",
    "sg:phone":"+49 7471/4994",
    "sg:postcode":"72379",
    "sg:province":"Baden-W\u00fcrttemberg",
    "wof:name":"Wolfgang Barthelmes",
    "wof:placetype":"venue"
},
  "geometry": {"coordinates":[8.962635,48.352283],"type":"Point"}
}