{
  "type": "Feature",
  "properties": {
    "iso:country":"DE",
    "sg:address":"Dechant-Vogt-Str. 31",
    "sg:city":"Euskirchen",
    "sg:phone":"+49 2251/3767",
    "sg:postcode":"53879",
    "sg:province":"Nordrhein-Westfalen",
    "wof:name":"Peter Kurth",
    "wof:placetype":"venue"
},
  "geometry": {"coordinates":[6.783725,50.661388],"type":"Point"}
}