{
  "type": "Feature",
  "properties": {
    "iso:country":"DE",
    "sg:address":"Am Neuerb 8",
    "sg:city":"Sommerach",
    "sg:phone":"+49 9381/3030",
    "sg:postcode":"97334",
    "sg:province":"Bayern",
    "wof:name":"C. \u00d6streicher",
    "wof:placetype":"venue"
},
  "geometry": {"coordinates":[10.2076740265,49.8326416016],"type":"Point"}
}