{
  "type": "Feature",
  "properties": {
    "iso:country":"DE",
    "sg:address":"Hauptstr. 31",
    "sg:city":"Coswig",
    "sg:phone":"+49 3523/75776",
    "sg:postcode":"01640",
    "sg:province":"Sachsen",
    "wof:name":"G\u00fcnther Beuhne",
    "wof:placetype":"venue"
},
  "geometry": {"coordinates":[13.580365181,51.1285095215],"type":"Point"}
}