{
  "type": "Feature",
  "properties": {
    "iso:country":"DE",
    "sg:address":"Frauenstr. 51",
    "sg:city":"Ulm",
    "sg:phone":"+49 731/96490",
    "sg:postcode":"89073",
    "sg:province":"Baden-W\u00fcrttemberg",
    "wof:name":"Hotel Comfor",
    "wof:placetype":"venue"
},
  "geometry": {"coordinates":[9.9966316223,48.4012145996],"type":"Point"}
}