{
  "type": "Feature",
  "properties": {
    "iso:country":"DE",
    "sg:address":"Gemen 53",
    "sg:city":"Sch\u00f6ppingen",
    "sg:phone":"+49 2568/1322",
    "sg:postcode":"48624",
    "sg:province":"Nordrhein-Westfalen",
    "wof:name":"A. Speckmann",
    "wof:placetype":"venue"
},
  "geometry": {"coordinates":[7.1369199753,52.0903816223],"type":"Point"}
}