{
  "type": "Feature",
  "properties": {
    "iso:country":"DE",
    "sg:address":"Ernst-Heinkel-Ring 19",
    "sg:city":"Hohenbrunn",
    "sg:phone":"+49 8102/3086",
    "sg:postcode":"85662",
    "sg:province":"Bayern",
    "wof:name":"Leopold Friedl Sen.& Sohn Ohg",
    "wof:placetype":"venue"
},
  "geometry": {"coordinates":[11.7204675674,48.044631958],"type":"Point"}
}