{
  "type": "Feature",
  "properties": {
    "iso:country":"DE",
    "sg:address":"Nobelstr. 45",
    "sg:city":"B\u00fcnde",
    "sg:phone":"+49 5223/6776",
    "sg:postcode":"32257",
    "sg:province":"Nordrhein-Westfalen",
    "wof:name":"Handverarbeitungsservice",
    "wof:placetype":"venue"
},
  "geometry": {"coordinates":[8.536683,52.202061],"type":"Point"}
}