{
  "type": "Feature",
  "properties": {
    "iso:country":"DE",
    "sg:address":"R\u00fcmpeler Weg 36",
    "sg:city":"Bad Oldesloe",
    "sg:phone":"+49 4531/82721",
    "sg:postcode":"23843",
    "sg:province":"Schleswig-Holstein",
    "wof:name":"D. Schulze",
    "wof:placetype":"venue"
},
  "geometry": {"coordinates":[10.367304,53.801544],"type":"Point"}
}