{
  "type": "Feature",
  "properties": {
    "iso:country":"DE",
    "sg:address":"Oberstr. 6",
    "sg:city":"Mettmann",
    "sg:phone":"+49 2104/27776",
    "sg:postcode":"40822",
    "sg:province":"Nordrhein-Westfalen",
    "wof:name":"Braukeller",
    "wof:placetype":"venue"
},
  "geometry": {"coordinates":[6.9767289162,51.2518539429],"type":"Point"}
}