{
  "type": "Feature",
  "properties": {
    "iso:country":"DE",
    "sg:address":"Guntherstr. 7",
    "sg:city":"N\u00fcrnberg",
    "sg:phone":"+49 911/468183",
    "sg:postcode":"90461",
    "sg:province":"Bayern",
    "wof:name":"Fritz Eckart",
    "wof:placetype":"venue"
},
  "geometry": {"coordinates":[11.0934114456,49.4358940125],"type":"Point"}
}