{
  "type": "Feature",
  "properties": {
    "iso:country":"DE",
    "sg:address":"Seestr. 22",
    "sg:city":"Schwaikheim",
    "sg:phone":"+49 7195/52651",
    "sg:postcode":"71409",
    "sg:province":"Baden-W\u00fcrttemberg",
    "wof:name":"W. D\u00fcrr",
    "wof:placetype":"venue"
},
  "geometry": {"coordinates":[9.34658,48.879902],"type":"Point"}
}