{
  "type": "Feature",
  "properties": {
    "iso:country":"DE",
    "sg:address":"Dyroffstr. 18",
    "sg:city":"M\u00fcnchen",
    "sg:phone":"+49 89/89224920",
    "sg:postcode":"80999",
    "sg:province":"Bayern",
    "wof:name":"Harald P. Schmid Rechtsanwalt",
    "wof:placetype":"venue"
},
  "geometry": {"coordinates":[11.447728157,48.1836662292],"type":"Point"}
}