{
  "type": "Feature",
  "properties": {
    "iso:country":"DE",
    "sg:address":"Weizenweg 22",
    "sg:city":"Schee\u00dfel",
    "sg:phone":"+49 4263/4763",
    "sg:postcode":"27383",
    "sg:province":"Niedersachsen",
    "wof:name":"Heino Frick Steuerberater",
    "wof:placetype":"venue"
},
  "geometry": {"coordinates":[9.4623031616,53.1692466736],"type":"Point"}
}