{
  "type": "Feature",
  "properties": {
    "iso:country":"DE",
    "sg:address":"Walddorfer Str. 51",
    "sg:city":"Altenriet",
    "sg:phone":"+49 7127/3832",
    "sg:postcode":"72657",
    "sg:province":"Baden-W\u00fcrttemberg",
    "wof:name":"Die Haarmacher Sandra Schw\u00f6rer Und",
    "wof:placetype":"venue"
},
  "geometry": {"coordinates":[9.2188205719,48.5899543762],"type":"Point"}
}