{
  "type": "Feature",
  "properties": {
    "iso:country":"DE",
    "sg:address":"Gewerbestr. 22 a",
    "sg:city":"Bochum",
    "sg:phone":"+49 2327/84403",
    "sg:postcode":"44866",
    "sg:province":"Nordrhein-Westfalen",
    "wof:name":"Dunschen Gmbh",
    "wof:placetype":"venue"
},
  "geometry": {"coordinates":[7.1614170074,51.489238739],"type":"Point"}
}