{
  "type": "Feature",
  "properties": {
    "iso:country":"DE",
    "sg:address":"Turnerstr. 69",
    "sg:city":"Kaiserslautern",
    "sg:phone":"+49 631/79991",
    "sg:postcode":"67659",
    "sg:province":"Rheinland-Pfalz",
    "wof:name":"Heinz Fuder Ingenieur",
    "wof:placetype":"venue"
},
  "geometry": {"coordinates":[7.754151,49.445503],"type":"Point"}
}