{
  "type": "Feature",
  "properties": {
    "iso:country":"DE",
    "sg:address":"Emcostr. 5",
    "sg:city":"Kirchhain",
    "sg:phone":"+49 6422/94280",
    "sg:postcode":"35274",
    "sg:province":"Hessen",
    "wof:name":"Leege Automobile Inh. Paul Leege",
    "wof:placetype":"venue"
},
  "geometry": {"coordinates":[8.914414,50.827621],"type":"Point"}
}