{
  "type": "Feature",
  "properties": {
    "iso:country":"DE",
    "sg:address":"Wingertstr. 9",
    "sg:city":"Frankfurt",
    "sg:phone":"+49 69/431009",
    "sg:postcode":"60316",
    "sg:province":"Hessen",
    "wof:name":"Werner Bischoff Gmbh",
    "wof:placetype":"venue"
},
  "geometry": {"coordinates":[8.700624,50.120354],"type":"Point"}
}