{
  "type": "Feature",
  "properties": {
    "iso:country":"DE",
    "sg:address":"Poststr. 3",
    "sg:city":"Kirchberg",
    "sg:phone":"+49 7954/373",
    "sg:postcode":"74592",
    "sg:province":"Baden-W\u00fcrttemberg",
    "wof:name":"Gertrud Krau\u00df",
    "wof:placetype":"venue"
},
  "geometry": {"coordinates":[9.98072,49.20105],"type":"Point"}
}