{
  "type": "Feature",
  "properties": {
    "iso:country":"DE",
    "sg:address":"Veldener Str. 4",
    "sg:city":"Vilsbiburg",
    "sg:phone":"+49 8741/3060",
    "sg:postcode":"84137",
    "sg:province":"Bayern",
    "wof:name":"K. Zollner Kg",
    "wof:placetype":"venue"
},
  "geometry": {"coordinates":[12.3568639755,48.4470214844],"type":"Point"}
}