{
  "type": "Feature",
  "properties": {
    "iso:country":"DE",
    "sg:address":"Schlo\u00dfplatz 1",
    "sg:city":"Wiesent",
    "sg:phone":"+49 9482/638",
    "sg:postcode":"93109",
    "sg:province":"Bayern",
    "wof:name":"Raiffeisenbank W\u00f6rth-wiesent Eg",
    "wof:placetype":"venue"
},
  "geometry": {"coordinates":[12.379161,49.007648],"type":"Point"}
}