{
  "type": "Feature",
  "properties": {
    "iso:country":"DE",
    "sg:address":"Hemingkamp 6",
    "sg:city":"Coesfeld",
    "sg:phone":"+49 2546/637",
    "sg:postcode":"48653",
    "sg:province":"Nordrhein-Westfalen",
    "wof:name":"Paul Hunkem\u00f6ller Gmbh",
    "wof:placetype":"venue"
},
  "geometry": {"coordinates":[7.1925988197,51.9011802673],"type":"Point"}
}