{
  "type": "Feature",
  "properties": {
    "iso:country":"DE",
    "sg:address":"Schubertstr. 48",
    "sg:city":"Plankstadt",
    "sg:phone":"+49 6202/15804",
    "sg:postcode":"68723",
    "sg:province":"Baden-W\u00fcrttemberg",
    "wof:name":"Dlw Metecno Gmbh",
    "wof:placetype":"venue"
},
  "geometry": {"coordinates":[8.5862226486,49.390460968],"type":"Point"}
}