{
  "type": "Feature",
  "properties": {
    "iso:country":"DE",
    "sg:address":"Kurze Geismarstr. 11",
    "sg:city":"G\u00f6ttingen",
    "sg:phone":"+49 551/485433",
    "sg:postcode":"37073",
    "sg:province":"Niedersachsen",
    "wof:name":"3-tage-bar",
    "wof:placetype":"venue"
},
  "geometry": {"coordinates":[9.938059,51.53104],"type":"Point"}
}