{
  "type": "Feature",
  "properties": {
    "iso:country":"DE",
    "sg:address":"Alfredstr. 239-241",
    "sg:city":"Essen",
    "sg:phone":"+49 201/790044",
    "sg:postcode":"45133",
    "sg:province":"Nordrhein-Westfalen",
    "wof:name":"Ralf Zuhorn",
    "wof:placetype":"venue"
},
  "geometry": {"coordinates":[6.9992637634,51.422580719],"type":"Point"}
}