{
  "type": "Feature",
  "properties": {
    "iso:country":"DE",
    "sg:address":"Steinkatz 22",
    "sg:city":"Hutthurm",
    "sg:phone":"+49 8505/6615",
    "sg:postcode":"94116",
    "sg:province":"Bayern",
    "wof:name":"Paul Rysavy Architekt",
    "wof:placetype":"venue"
},
  "geometry": {"coordinates":[13.485909,48.672531],"type":"Point"}
}