{
  "type": "Feature",
  "properties": {
    "iso:country":"DE",
    "sg:address":"Franz\u00f6sische Str. 9-12",
    "sg:city":"Berlin",
    "sg:phone":"+49 30/4243880",
    "sg:postcode":"10117",
    "sg:province":"Berlin",
    "wof:name":"Wittem\u00f6ller Radack M\u00fcller & Partner Berlin",
    "wof:placetype":"venue"
},
  "geometry": {"coordinates":[13.386811,52.514481],"type":"Point"}
}