{
  "type": "Feature",
  "properties": {
    "iso:country":"DE",
    "sg:address":"Obers\u00f6chering",
    "sg:city":"Obers\u00f6chering",
    "sg:phone":"+49 8847/260",
    "sg:postcode":"82395",
    "sg:province":"Bayern",
    "wof:name":"Raiffeisenkasse Obers\u00f6chering Egmbh",
    "wof:placetype":"venue"
},
  "geometry": {"coordinates":[11.218512,47.737797],"type":"Point"}
}