{
  "type": "Feature",
  "properties": {
    "iso:country":"DE",
    "sg:address":"Fliederbusch 32",
    "sg:city":"D\u00fcren",
    "sg:phone":"+49 2421/65340",
    "sg:postcode":"52355",
    "sg:province":"Nordrhein-Westfalen",
    "wof:name":"J. Schlensok",
    "wof:placetype":"venue"
},
  "geometry": {"coordinates":[6.4429922104,50.7751235962],"type":"Point"}
}