{
  "type": "Feature",
  "properties": {
    "iso:country":"DE",
    "sg:address":"Tucholskystr. 2",
    "sg:city":"N\u00fcrnberg",
    "sg:phone":"+49 911/861292",
    "sg:postcode":"90471",
    "sg:province":"Bayern",
    "wof:name":"Pfeuffer & Co. Gmbh",
    "wof:placetype":"venue"
},
  "geometry": {"coordinates":[11.135474205,49.4138336182],"type":"Point"}
}