{
  "type": "Feature",
  "properties": {
    "iso:country":"DE",
    "sg:address":"Zinnberger Str. 21A",
    "sg:city":"Penig",
    "sg:phone":"+49 37381/80427",
    "sg:postcode":"09322",
    "sg:province":"Sachsen",
    "wof:name":"Stadtbad",
    "wof:placetype":"venue"
},
  "geometry": {"coordinates":[12.7011013031,50.9299354553],"type":"Point"}
}