{
  "type": "Feature",
  "properties": {
    "iso:country":"DE",
    "sg:address":"Ign-Ph-Semmelweis-Str 5",
    "sg:city":"Gunzenhausen",
    "sg:postcode":"91710",
    "sg:province":"Bayern",
    "wof:name":"Nega Bau Service Gmbh",
    "wof:placetype":"venue"
},
  "geometry": {"coordinates":[10.7719974518,49.1046447754],"type":"Point"}
}