{
  "type": "Feature",
  "properties": {
    "iso:country":"DE",
    "sg:address":"Bahnhofstr. 3",
    "sg:city":"M\u00f6gglingen",
    "sg:phone":"+49 7174/802050",
    "sg:postcode":"73563",
    "sg:province":"Baden-W\u00fcrttemberg",
    "wof:name":"Arbeiterwohlfahrt Kreisverband Ostalb E. V.",
    "wof:placetype":"venue"
},
  "geometry": {"coordinates":[9.96196,48.823746],"type":"Point"}
}