{
  "type": "Feature",
  "properties": {
    "iso:country":"DE",
    "sg:address":"Lindener Str. 153 i",
    "sg:city":"Bochum",
    "sg:phone":"+49 234/497301",
    "sg:postcode":"44879",
    "sg:province":"Nordrhein-Westfalen",
    "wof:name":"Dieter Plischke",
    "wof:placetype":"venue"
},
  "geometry": {"coordinates":[7.1622509956,51.427116394],"type":"Point"}
}