{
  "type": "Feature",
  "properties": {
    "iso:country":"DE",
    "sg:address":"Falkenstr. 26",
    "sg:city":"Hannover",
    "sg:phone":"+49 511/441774",
    "sg:postcode":"30449",
    "sg:province":"Niedersachsen",
    "wof:name":"Akropolis-grill",
    "wof:placetype":"venue"
},
  "geometry": {"coordinates":[9.7158622742,52.3669433594],"type":"Point"}
}