{
  "type": "Feature",
  "properties": {
    "iso:country":"DE",
    "sg:address":"Riesebach 14",
    "sg:city":"Espelkamp",
    "sg:phone":"+49 5772/1572",
    "sg:postcode":"32339",
    "sg:province":"Nordrhein-Westfalen",
    "wof:name":"Heinrich Kr\u00f6ger",
    "wof:placetype":"venue"
},
  "geometry": {"coordinates":[8.642399,52.375443],"type":"Point"}
}