{
  "type": "Feature",
  "properties": {
    "iso:country":"DE",
    "sg:address":"Birkenweg 2",
    "sg:city":"Reit im Winkl",
    "sg:phone":"+49 8640/1387",
    "sg:postcode":"83242",
    "sg:province":"Bayern",
    "wof:name":"G\u00e4stehaus Sonnenhang",
    "wof:placetype":"venue"
},
  "geometry": {"coordinates":[12.4627809525,47.6749458313],"type":"Point"}
}