{
  "type": "Feature",
  "properties": {
    "iso:country":"DE",
    "sg:address":"M\u00fcllensiefenstr. 8",
    "sg:city":"Iserlohn",
    "sg:phone":"+49 2371/22305",
    "sg:postcode":"58636",
    "sg:province":"Nordrhein-Westfalen",
    "wof:name":"Hermann Lehmann Kg",
    "wof:placetype":"venue"
},
  "geometry": {"coordinates":[7.7082099915,51.3754577637],"type":"Point"}
}