{
  "type": "Feature",
  "properties": {
    "iso:country":"DE",
    "sg:address":"Rohlofs Hof 7",
    "sg:city":"Dorsten",
    "sg:phone":"+49 2362/65254",
    "sg:postcode":"46284",
    "sg:province":"Nordrhein-Westfalen",
    "wof:name":"Walter Van Der Valk Steuerberater",
    "wof:placetype":"venue"
},
  "geometry": {"coordinates":[6.9757947922,51.676700592],"type":"Point"}
}