{
  "type": "Feature",
  "properties": {
    "iso:country":"DE",
    "sg:address":"Gr\u00fcner Weg 42",
    "sg:city":"Hiddenhausen",
    "sg:phone":"+49 5223/8921",
    "sg:postcode":"32120",
    "sg:province":"Nordrhein-Westfalen",
    "wof:name":"H. G. Kr\u00f6hnert Gmbh",
    "wof:placetype":"venue"
},
  "geometry": {"coordinates":[8.6332921982,52.1715774536],"type":"Point"}
}