{
  "type": "Feature",
  "properties": {
    "iso:country":"DE",
    "sg:address":"Schoellerstr. 32",
    "sg:city":"D\u00fcren",
    "sg:phone":"+49 2421/35777",
    "sg:postcode":"52351",
    "sg:province":"Nordrhein-Westfalen",
    "wof:name":"Chinesische Mauer",
    "wof:placetype":"venue"
},
  "geometry": {"coordinates":[6.4925718307,50.807849884],"type":"Point"}
}