{
  "type": "Feature",
  "properties": {
    "iso:country":"DE",
    "sg:address":"Darmst\u00e4dter Str. 79",
    "sg:city":"Bensheim",
    "sg:phone":"+49 6251/709290",
    "sg:postcode":"64625",
    "sg:province":"Hessen",
    "wof:name":"Rudolf H. Dufner Verm\u00f6gensberatung Gmbh",
    "wof:placetype":"venue"
},
  "geometry": {"coordinates":[8.6223697662,49.6912841797],"type":"Point"}
}