{
  "type": "Feature",
  "properties": {
    "iso:country":"DE",
    "sg:address":"Im Hofert 28",
    "sg:city":"Heidelberg",
    "sg:phone":"+49 6221/89930",
    "sg:postcode":"69118",
    "sg:province":"Baden-W\u00fcrttemberg",
    "wof:name":"Zum Neckartal",
    "wof:placetype":"venue"
},
  "geometry": {"coordinates":[8.7721147537,49.4104576111],"type":"Point"}
}