{
  "type": "Feature",
  "properties": {
    "iso:country":"DE",
    "sg:address":"Kapit\u00e4n-Lehmann-Str .2",
    "sg:city":"Bottrop",
    "sg:phone":"+49 2041/27244",
    "sg:postcode":"46236",
    "sg:province":"Nordrhein-Westfalen",
    "wof:name":"Bioladen Gr\u00fcner Zweig",
    "wof:placetype":"venue"
},
  "geometry": {"coordinates":[6.9253349304,51.5188713074],"type":"Point"}
}