{
  "type": "Feature",
  "properties": {
    "iso:country":"DE",
    "sg:address":"Bei der Ziegelh\u00fctte 6",
    "sg:city":"Langenbrettach",
    "sg:phone":"+49 7139/2646",
    "sg:postcode":"74243",
    "sg:province":"Baden-W\u00fcrttemberg",
    "wof:name":"Elcon Industrieelektronik Gmbh",
    "wof:placetype":"venue"
},
  "geometry": {"coordinates":[9.384502,49.225464],"type":"Point"}
}