{
  "type": "Feature",
  "properties": {
    "iso:country":"DE",
    "sg:address":"Schlo\u00dfstra\u00dfe 90",
    "sg:city":"Berlin",
    "sg:phone":"+49 30/79702310",
    "sg:postcode":"12163",
    "sg:province":"Berlin",
    "wof:name":"Berliner Buchhalter",
    "wof:placetype":"venue"
},
  "geometry": {"coordinates":[13.322075,52.457954],"type":"Point"}
}