{
  "type": "Feature",
  "properties": {
    "iso:country":"DE",
    "sg:address":"Nonnengasse 14",
    "sg:city":"T\u00fcbingen",
    "sg:postcode":"72070",
    "sg:province":"Baden-W\u00fcrttemberg",
    "wof:name":"Aktiv-markt",
    "wof:placetype":"venue"
},
  "geometry": {"coordinates":[9.0561599731,48.5224342346],"type":"Point"}
}