{
  "type": "Feature",
  "properties": {
    "iso:country":"DE",
    "sg:address":"Hansaallee 150",
    "sg:city":"Frankfurt",
    "sg:phone":"+49 69/9562460",
    "sg:postcode":"60320",
    "sg:province":"Hessen",
    "wof:name":"Wbt Weiterbildungs- Testsysteme Gmbh",
    "wof:placetype":"venue"
},
  "geometry": {"coordinates":[8.668278,50.136162],"type":"Point"}
}