{
  "type": "Feature",
  "properties": {
    "iso:country":"DE",
    "sg:address":"Unter den Linden 12",
    "sg:city":"Peine",
    "sg:phone":"+49 5171/55197",
    "sg:postcode":"31226",
    "sg:province":"Niedersachsen",
    "wof:name":"Restaurant Landhaus Lindenkrug",
    "wof:placetype":"venue"
},
  "geometry": {"coordinates":[10.1877069473,52.3062400818],"type":"Point"}
}