{
  "type": "Feature",
  "properties": {
    "iso:country":"DE",
    "sg:address":"Weberstr. 40",
    "sg:city":"Stendal",
    "sg:phone":"+49 3931/794886",
    "sg:postcode":"39576",
    "sg:province":"Sachsen-Anhalt",
    "wof:name":"Lohmann Bautenschutz",
    "wof:placetype":"venue"
},
  "geometry": {"coordinates":[11.8579273224,52.6023178101],"type":"Point"}
}