{
  "type": "Feature",
  "properties": {
    "iso:country":"DE",
    "sg:address":"Von-Bronsart-Str. 11",
    "sg:city":"Barsb\u00fcttel",
    "sg:postcode":"22885",
    "sg:province":"Schleswig-Holstein",
    "wof:name":"Wotrans Internationale M\u00f6belspedition Peter Wohsmann",
    "wof:placetype":"venue"
},
  "geometry": {"coordinates":[10.1885223389,53.5732307434],"type":"Point"}
}