{
  "type": "Feature",
  "properties": {
    "iso:country":"DE",
    "sg:address":"Schulstr. 6",
    "sg:city":"Ruhmannsfelden",
    "sg:phone":"+49 9929/3777",
    "sg:postcode":"94239",
    "sg:province":"Bayern",
    "wof:name":"Xaver Karl",
    "wof:placetype":"venue"
},
  "geometry": {"coordinates":[12.9856939316,48.9830207825],"type":"Point"}
}