{
  "type": "Feature",
  "properties": {
    "iso:country":"DE",
    "sg:address":"Zeidlersiedlung 21",
    "sg:city":"Feucht",
    "sg:phone":"+49 9128/5266",
    "sg:postcode":"90537",
    "sg:province":"Bayern",
    "wof:name":"Hermann He\u00dfler",
    "wof:placetype":"venue"
},
  "geometry": {"coordinates":[11.204737,49.36911],"type":"Point"}
}