{
  "type": "Feature",
  "properties": {
    "iso:country":"DE",
    "sg:address":"Halfmannsweg 53 b",
    "sg:city":"Gelsenkirchen",
    "sg:phone":"+49 209/22834",
    "sg:postcode":"45886",
    "sg:province":"Nordrhein-Westfalen",
    "wof:name":"Prinz Und Cittrich Architekten",
    "wof:placetype":"venue"
},
  "geometry": {"coordinates":[7.100644,51.490173],"type":"Point"}
}