{
  "type": "Feature",
  "properties": {
    "iso:country":"DE",
    "sg:address":"\u00c4u\u00dfere Bayreuther Str. 103",
    "sg:city":"N\u00fcrnberg",
    "sg:phone":"+49 911/511251",
    "sg:postcode":"90409",
    "sg:province":"Bayern",
    "wof:name":"Eiscafe Val Gardena Gmbh",
    "wof:placetype":"venue"
},
  "geometry": {"coordinates":[11.102122,49.471573],"type":"Point"}
}