{
  "type": "Feature",
  "properties": {
    "iso:country":"DE",
    "sg:address":"Haffkruger Weg 17",
    "sg:city":"Hamburg",
    "sg:phone":"+49 40",
    "sg:postcode":"22143",
    "sg:province":"Hamburg",
    "wof:name":"Verlagslogistik-hamburg",
    "wof:placetype":"venue"
},
  "geometry": {"coordinates":[10.149309,53.610615],"type":"Point"}
}