{
  "type": "Feature",
  "properties": {
    "iso:country":"DE",
    "sg:address":"Hauptstr. 7",
    "sg:city":"Rimbach",
    "sg:phone":"+49 6253/6125",
    "sg:postcode":"64668",
    "sg:province":"Hessen",
    "wof:name":"Karl Eberle",
    "wof:placetype":"venue"
},
  "geometry": {"coordinates":[8.766057,49.602802],"type":"Point"}
}