{
  "type": "Feature",
  "properties": {
    "iso:country":"DE",
    "sg:address":"Ostenstr. 16",
    "sg:city":"Eichst\u00e4tt",
    "sg:phone":"+49 8421/901313",
    "sg:postcode":"85072",
    "sg:province":"Bayern",
    "wof:name":"Pilsbar Arames",
    "wof:placetype":"venue"
},
  "geometry": {"coordinates":[11.1875658035,48.8901824951],"type":"Point"}
}