{
  "type": "Feature",
  "properties": {
    "iso:country":"DE",
    "sg:address":"Im W\u00e4ldchen 5",
    "sg:city":"Frankenau",
    "sg:phone":"+49 6455/8622",
    "sg:postcode":"35110",
    "sg:province":"Hessen",
    "wof:name":"U. Und E. Wickert",
    "wof:placetype":"venue"
},
  "geometry": {"coordinates":[8.911262,51.077312],"type":"Point"}
}