{
  "type": "Feature",
  "properties": {
    "iso:country":"DE",
    "sg:address":"Gartenstr. 1",
    "sg:city":"Bad Sassendorf",
    "sg:phone":"+49 2921/943648",
    "sg:postcode":"59505",
    "sg:province":"Nordrhein-Westfalen",
    "wof:name":"Hosselmann Gmbh Cafe-restaurant",
    "wof:placetype":"venue"
},
  "geometry": {"coordinates":[8.165496,51.588909],"type":"Point"}
}