{
  "type": "Feature",
  "properties": {
    "iso:country":"DE",
    "sg:address":"S\u00fcdwestpark 37-41",
    "sg:city":"N\u00fcrnberg",
    "sg:phone":"+49 911/967880",
    "sg:postcode":"90449",
    "sg:province":"Bayern",
    "wof:name":"Reiner E. Gro\u00df",
    "wof:placetype":"venue"
},
  "geometry": {"coordinates":[11.02145,49.427959],"type":"Point"}
}