{
  "type": "Feature",
  "properties": {
    "iso:country":"DE",
    "sg:address":"Isarstr. 28",
    "sg:city":"Regensburg",
    "sg:phone":"+49 941/40414",
    "sg:postcode":"93057",
    "sg:province":"Bayern",
    "wof:name":"August Vollath Architekt",
    "wof:placetype":"venue"
},
  "geometry": {"coordinates":[12.119207,49.033401],"type":"Point"}
}