{
  "type": "Feature",
  "properties": {
    "iso:country":"DE",
    "sg:address":"Ernst-Th\u00e4lmann-Str. 16",
    "sg:city":"Vetschau",
    "sg:phone":"+49 35433/2208",
    "sg:postcode":"03226",
    "sg:province":"Brandenburg",
    "wof:name":"Guenter Seifert",
    "wof:placetype":"venue"
},
  "geometry": {"coordinates":[14.072611,51.789677],"type":"Point"}
}