{
  "type": "Feature",
  "properties": {
    "iso:country":"DE",
    "sg:address":"Im R-Kauf",
    "sg:city":"Brachbach",
    "sg:phone":"+49 2745/8622",
    "sg:postcode":"57555",
    "sg:province":"Rheinland-Pfalz",
    "wof:name":"W. Debus",
    "wof:placetype":"venue"
},
  "geometry": {"coordinates":[7.948421,50.826046],"type":"Point"}
}