{
  "type": "Feature",
  "properties": {
    "iso:country":"DE",
    "sg:address":"Julius-Sturm-Platz 6",
    "sg:city":"Bad K\u00f6stritz",
    "sg:phone":"+49 36605/84020",
    "sg:postcode":"07586",
    "sg:province":"Th\u00fcringen",
    "wof:name":"M\u00fcbe Domizil Hausverwaltungs- Und Baubetreuungs Gmbh",
    "wof:placetype":"venue"
},
  "geometry": {"coordinates":[12.0110721588,50.9299354553],"type":"Point"}
}