{
  "type": "Feature",
  "properties": {
    "iso:country":"DE",
    "sg:address":"An der Lach 10",
    "sg:city":"N\u00f6rdlingen",
    "sg:phone":"+49 9081/22400",
    "sg:postcode":"86720",
    "sg:province":"Bayern",
    "wof:name":"Elestra Elektronische Verkaufshilfen Und",
    "wof:placetype":"venue"
},
  "geometry": {"coordinates":[10.5082540512,48.8445129395],"type":"Point"}
}