{
  "type": "Feature",
  "properties": {
    "iso:country":"DE",
    "sg:address":"Industriegebiet",
    "sg:city":"Windhagen",
    "sg:phone":"+49 2645/3031",
    "sg:postcode":"53578",
    "sg:province":"Rheinland-Pfalz",
    "wof:name":"Noma-getriebebau Gottfried Pietzsch Gmbh",
    "wof:placetype":"venue"
},
  "geometry": {"coordinates":[7.354674,50.641777],"type":"Point"}
}