{
  "type": "Feature",
  "properties": {
    "iso:country":"DE",
    "sg:address":"Hauptstr. 2",
    "sg:city":"Alttrebbin",
    "sg:postcode":"16259",
    "sg:province":"Brandenburg",
    "wof:name":"Motorsport Brandenburg",
    "wof:placetype":"venue"
},
  "geometry": {"coordinates":[14.248567,52.691692],"type":"Point"}
}