{
  "type": "Feature",
  "properties": {
    "iso:country":"DE",
    "sg:address":"Raiffeisenstrasse",
    "sg:city":"Steinfeld",
    "sg:phone":"+49 6340/331",
    "sg:postcode":"76889",
    "sg:province":"Rheinland-Pfalz",
    "wof:name":"Auto-bolender, Fiat-vertretung, Wohnmobilverleih",
    "wof:placetype":"venue"
},
  "geometry": {"coordinates":[8.0394296646,49.0509338379],"type":"Point"}
}