{
  "type": "Feature",
  "properties": {
    "iso:country":"DE",
    "sg:address":"Frische Grube 3",
    "sg:city":"Wismar",
    "sg:phone":"+49 3841/213614",
    "sg:postcode":"23966",
    "sg:province":"Mecklenburg-Vorpommern",
    "wof:name":"Schwartzens Grubenstuw",
    "wof:placetype":"venue"
},
  "geometry": {"coordinates":[11.4606389999,53.8951644897],"type":"Point"}
}