{
  "type": "Feature",
  "properties": {
    "iso:country":"DE",
    "sg:address":"Erhardigasse 11",
    "sg:city":"Regensburg",
    "sg:phone":"+49 941/565355",
    "sg:postcode":"93047",
    "sg:province":"Bayern",
    "wof:name":"R\u00f6merkrug",
    "wof:placetype":"venue"
},
  "geometry": {"coordinates":[12.101436615,49.018989563],"type":"Point"}
}