{
  "type": "Feature",
  "properties": {
    "iso:country":"DE",
    "sg:address":"Am Eichenrangen 9",
    "sg:city":"Schwaig",
    "sg:phone":"+49 911/5074239",
    "sg:postcode":"90571",
    "sg:province":"Bayern",
    "wof:name":"Karl Friedrich Von Eggeling",
    "wof:placetype":"venue"
},
  "geometry": {"coordinates":[11.2131767273,49.4853477478],"type":"Point"}
}