{
  "type": "Feature",
  "properties": {
    "iso:country":"DE",
    "sg:address":"Bergerstr. 91",
    "sg:city":"K\u00f6ln",
    "sg:phone":"+49 2203/39697",
    "sg:postcode":"51145",
    "sg:province":"Nordrhein-Westfalen",
    "wof:name":"Hans-j\u00fcrgen Bauer Rechtsanwalt",
    "wof:placetype":"venue"
},
  "geometry": {"coordinates":[7.0632138252,50.8907432556],"type":"Point"}
}