{
  "type": "Feature",
  "properties": {
    "iso:country":"DE",
    "sg:address":"Stephanopel 30",
    "sg:city":"Hemer",
    "sg:phone":"+49 2372",
    "sg:postcode":"58675",
    "sg:province":"Nordrhein-Westfalen",
    "wof:name":"Man Trifft Sich Im Haus Winterhof",
    "wof:placetype":"venue"
},
  "geometry": {"coordinates":[7.7937941551,51.351234436],"type":"Point"}
}