{
  "type": "Feature",
  "properties": {
    "iso:country":"DE",
    "sg:address":"Wixh\u00e4user Str.",
    "sg:city":"Darmstadt",
    "sg:phone":"+49 6150/7061",
    "sg:postcode":"64291",
    "sg:province":"Hessen",
    "wof:name":"Stefan Keute Rechtsanwalt",
    "wof:placetype":"venue"
},
  "geometry": {"coordinates":[8.6521024704,49.9146347046],"type":"Point"}
}