{
  "type": "Feature",
  "properties": {
    "iso:country":"DE",
    "sg:address":"Herbigstr. 24",
    "sg:city":"M\u00fcnchen",
    "sg:phone":"+49 89/8122376",
    "sg:postcode":"80999",
    "sg:province":"Bayern",
    "wof:name":"G\u00dcnter Hartmann Gmbh",
    "wof:placetype":"venue"
},
  "geometry": {"coordinates":[11.442473,48.182453],"type":"Point"}
}