{
  "type": "Feature",
  "properties": {
    "iso:country":"DE",
    "sg:address":"Malepartusweg 6",
    "sg:city":"Lienen",
    "sg:phone":"+49 5483/8337",
    "sg:postcode":"49536",
    "sg:province":"Nordrhein-Westfalen",
    "wof:name":"Gastst\u00e4tten, Bierg\u00e4rten",
    "wof:placetype":"venue"
},
  "geometry": {"coordinates":[7.980418,52.159866],"type":"Point"}
}