{
  "type": "Feature",
  "properties": {
    "iso:country":"DE",
    "sg:address":"Negenbarger Str. 98",
    "sg:city":"Wittmund",
    "sg:phone":"+49 4973/429",
    "sg:postcode":"26409",
    "sg:province":"Niedersachsen",
    "wof:name":"Gastst\u00e4tte Theodor Janssen",
    "wof:placetype":"venue"
},
  "geometry": {"coordinates":[7.6724410057,53.5731964111],"type":"Point"}
}