{
  "type": "Feature",
  "properties": {
    "iso:country":"DE",
    "sg:address":"Siemensstr. 12",
    "sg:city":"Marktleuthen",
    "sg:phone":"+49 9285/92410",
    "sg:postcode":"95168",
    "sg:province":"Bayern",
    "wof:name":"Jochen Donaubauer Consulting Gmbh",
    "wof:placetype":"venue"
},
  "geometry": {"coordinates":[12.0109024048,50.1347389221],"type":"Point"}
}