{
  "type": "Feature",
  "properties": {
    "iso:country":"DE",
    "sg:address":"Rappenberghalde 33",
    "sg:city":"Rottenburg",
    "sg:phone":"+49 7472/6815",
    "sg:postcode":"72108",
    "sg:province":"Baden-W\u00fcrttemberg",
    "wof:name":"Laboklinika Gmbh",
    "wof:placetype":"venue"
},
  "geometry": {"coordinates":[8.92507,48.448376],"type":"Point"}
}