{
  "type": "Feature",
  "properties": {
    "iso:country":"DE",
    "sg:address":"Marktplatz 10",
    "sg:city":"Dischingen",
    "sg:phone":"+49 7327/300",
    "sg:postcode":"89561",
    "sg:province":"Baden-W\u00fcrttemberg",
    "wof:name":"Rudolf Schmid",
    "wof:placetype":"venue"
},
  "geometry": {"coordinates":[10.361632,48.696762],"type":"Point"}
}