{
  "type": "Feature",
  "properties": {
    "iso:country":"DE",
    "sg:address":"Hirzstr. 27",
    "sg:city":"K\u00f6ln",
    "sg:postcode":"50937",
    "sg:province":"Nordrhein-Westfalen",
    "wof:name":"Ptu E. K.",
    "wof:placetype":"venue"
},
  "geometry": {"coordinates":[6.916532,50.906849],"type":"Point"}
}