{
  "type": "Feature",
  "properties": {
    "iso:country":"DE",
    "sg:address":"Gutenbergstr 2",
    "sg:city":"Ratzeburg",
    "sg:phone":"+49 4541/4645",
    "sg:postcode":"23909",
    "sg:province":"Schleswig-Holstein",
    "wof:name":"R. Walter Dittmann Hohlwellen Und Zylinderwerk Gmbh & Co Kg",
    "wof:placetype":"venue"
},
  "geometry": {"coordinates":[10.741084,53.702587],"type":"Point"}
}