{
  "type": "Feature",
  "properties": {
    "iso:country":"DE",
    "sg:address":"Pr\u00e4latenweg 11",
    "sg:city":"Weilheim",
    "sg:phone":"+49 881/2674",
    "sg:postcode":"82362",
    "sg:province":"Bayern",
    "wof:name":"Dr. Ottmar Schuberth Architekt",
    "wof:placetype":"venue"
},
  "geometry": {"coordinates":[11.140717,47.83223],"type":"Point"}
}