{
  "type": "Feature",
  "properties": {
    "iso:country":"DE",
    "sg:address":"Ringstr. 88-90",
    "sg:city":"Sankt Augustin",
    "sg:postcode":"53757",
    "sg:province":"Nordrhein-Westfalen",
    "wof:name":"Bhv Aviation Consultans Gmbh",
    "wof:placetype":"venue"
},
  "geometry": {"coordinates":[7.2381429672,50.7840614319],"type":"Point"}
}