{
  "type": "Feature",
  "properties": {
    "iso:country":"DE",
    "sg:address":"St.-Georg-Str. 1",
    "sg:city":"Eitting",
    "sg:phone":"+49 8122/12520",
    "sg:postcode":"85462",
    "sg:province":"Bayern",
    "wof:name":"Scharl Immobilien- Verwaltungs Gmbh",
    "wof:placetype":"venue"
},
  "geometry": {"coordinates":[11.889032,48.359734],"type":"Point"}
}