{
  "type": "Feature",
  "properties": {
    "iso:country":"DE",
    "sg:address":"Am Wiesengarten 9",
    "sg:city":"Seebad Ahlbeck",
    "sg:phone":"+49 38378/30308",
    "sg:postcode":"17419",
    "sg:province":"Mecklenburg-Vorpommern",
    "wof:name":"Eckhard Schmoldt",
    "wof:placetype":"venue"
},
  "geometry": {"coordinates":[14.0650997162,53.8867111206],"type":"Point"}
}