{
  "type": "Feature",
  "properties": {
    "iso:country":"DE",
    "sg:address":"H\u00fcgelstr. 2a",
    "sg:city":"Puchheim",
    "sg:phone":"+49 89/806422",
    "sg:postcode":"82178",
    "sg:province":"Bayern",
    "wof:name":"Ohner Ges. F. Hafner- Und Fliesenlegerarbeiten Mbh",
    "wof:placetype":"venue"
},
  "geometry": {"coordinates":[11.344751358,48.1502494812],"type":"Point"}
}