{
  "type": "Feature",
  "properties": {
    "iso:country":"DE",
    "sg:address":"Br\u00fchlstr. 1",
    "sg:city":"Deckenpfronn",
    "sg:phone":"+49 7056/1455",
    "sg:postcode":"75392",
    "sg:province":"Baden-W\u00fcrttemberg",
    "wof:name":"Hans Tischer",
    "wof:placetype":"venue"
},
  "geometry": {"coordinates":[8.831258,48.652229],"type":"Point"}
}