{
  "type": "Feature",
  "properties": {
    "iso:country":"DE",
    "sg:address":"Biberkopfstr 4",
    "sg:city":"Mindelheim",
    "sg:phone":"+49 8261/8176",
    "sg:postcode":"87719",
    "sg:province":"Bayern",
    "wof:name":"Weber Werkzeugmaschinen-handels Gmbh",
    "wof:placetype":"venue"
},
  "geometry": {"coordinates":[10.504972,48.037884],"type":"Point"}
}