{
  "type": "Feature",
  "properties": {
    "iso:country":"DE",
    "sg:address":"Stettiner Str. 10",
    "sg:city":"Marl",
    "sg:phone":"+49 2365/17529",
    "sg:postcode":"45770",
    "sg:province":"Nordrhein-Westfalen",
    "wof:name":"Volker Schmeisser Schilder Und Lichtreklame",
    "wof:placetype":"venue"
},
  "geometry": {"coordinates":[7.093968,51.645718],"type":"Point"}
}