{
  "type": "Feature",
  "properties": {
    "iso:country":"DE",
    "sg:address":"Linzer Str. 60",
    "sg:city":"Bad Honnef",
    "sg:phone":"+49 2224/76454",
    "sg:postcode":"53604",
    "sg:province":"Nordrhein-Westfalen",
    "wof:name":"Harald Wegener Und Hoppert Architekten",
    "wof:placetype":"venue"
},
  "geometry": {"coordinates":[7.226447,50.639435],"type":"Point"}
}