{
  "type": "Feature",
  "properties": {
    "iso:country":"DE",
    "sg:address":"Nartenstra\u00dfe 24::",
    "sg:city":"Hamburg",
    "sg:phone":"+49 40/30953386",
    "sg:postcode":"21079",
    "sg:province":"Hamburg",
    "wof:name":"Collection Narin",
    "wof:placetype":"venue"
},
  "geometry": {"coordinates":[9.9930715561,53.4693260193],"type":"Point"}
}