{
  "type": "Feature",
  "properties": {
    "iso:country":"DE",
    "sg:address":"Homburger Landstr. 84",
    "sg:city":"Frankfurt",
    "sg:phone":"+49 69/541074",
    "sg:postcode":"60435",
    "sg:province":"Hessen",
    "wof:name":"Hannelore Otto Rechtsanw\u00e4ltin Und Notarin",
    "wof:placetype":"venue"
},
  "geometry": {"coordinates":[8.6926050186,50.1463508606],"type":"Point"}
}