{
  "type": "Feature",
  "properties": {
    "iso:country":"DE",
    "sg:address":"Kreuzweg 4",
    "sg:city":"Heidgraben",
    "sg:phone":"+49 4122/901313",
    "sg:postcode":"25436",
    "sg:province":"Schleswig-Holstein",
    "wof:name":"G\u00fcnther Falk",
    "wof:placetype":"venue"
},
  "geometry": {"coordinates":[9.692126,53.706032],"type":"Point"}
}