{
  "type": "Feature",
  "properties": {
    "iso:country":"DE",
    "sg:address":"Salzstr. 11",
    "sg:city":"Bad T\u00f6lz",
    "sg:phone":"+49 8041/72033",
    "sg:postcode":"83646",
    "sg:province":"Bayern",
    "wof:name":"Andreas Und Marguerite Sander Rechtsanw\u00e4lte",
    "wof:placetype":"venue"
},
  "geometry": {"coordinates":[11.5635643005,47.7614097595],"type":"Point"}
}