{
  "type": "Feature",
  "properties": {
    "iso:country":"DE",
    "sg:address":"Hinterdorfstr. 22",
    "sg:city":"Rollshausen",
    "sg:phone":"+49 5528/8233",
    "sg:postcode":"37434",
    "sg:province":"Niedersachsen",
    "wof:name":"K.-h. Wedekind",
    "wof:placetype":"venue"
},
  "geometry": {"coordinates":[10.214006424,51.5731468201],"type":"Point"}
}