{
  "type": "Feature",
  "properties": {
    "iso:country":"DE",
    "sg:address":"Vor dem Celler Tor 3",
    "sg:city":"Burgdorf",
    "sg:phone":"+49 5136/7048",
    "sg:postcode":"31303",
    "sg:province":"Niedersachsen",
    "wof:name":"Arve",
    "wof:placetype":"venue"
},
  "geometry": {"coordinates":[10.012047,52.448975],"type":"Point"}
}