{
  "type": "Feature",
  "properties": {
    "iso:country":"DE",
    "sg:address":"Itzehoer Str. 38",
    "sg:city":"Gnutz",
    "sg:phone":"+49 4392/1790",
    "sg:postcode":"24622",
    "sg:province":"Schleswig-Holstein",
    "wof:name":"Gastst\u00e4tte Zur Erholung",
    "wof:placetype":"venue"
},
  "geometry": {"coordinates":[9.8259124756,54.1328392029],"type":"Point"}
}