{
  "type": "Feature",
  "properties": {
    "iso:country":"DE",
    "sg:address":"Stelzendorfer Str. 281",
    "sg:city":"Chemnitz",
    "sg:phone":"+49 371/221206",
    "sg:postcode":"09116",
    "sg:province":"Sachsen",
    "wof:name":"Sporthaus Mantel",
    "wof:placetype":"venue"
},
  "geometry": {"coordinates":[12.860333,50.797035],"type":"Point"}
}