{
  "type": "Feature",
  "properties": {
    "iso:country":"DE",
    "sg:address":"Kaplan-Nagel-Weg 13",
    "sg:city":"Bopfingen",
    "sg:phone":"+49 7362/5866",
    "sg:postcode":"73441",
    "sg:province":"Baden-W\u00fcrttemberg",
    "wof:name":"H. Stahl Heissmangel",
    "wof:placetype":"venue"
},
  "geometry": {"coordinates":[10.3643655777,48.851146698],"type":"Point"}
}