{
  "type": "Feature",
  "properties": {
    "iso:country":"DE",
    "sg:address":"Geranienhof 2",
    "sg:city":"K\u00f6ln",
    "sg:phone":"+49 221/701761",
    "sg:postcode":"50769",
    "sg:province":"Nordrhein-Westfalen",
    "wof:name":"Reiner Nix",
    "wof:placetype":"venue"
},
  "geometry": {"coordinates":[6.91602,51.016945],"type":"Point"}
}