{
  "type": "Feature",
  "properties": {
    "iso:country":"DE",
    "sg:address":"Hugo-Asbach-Str. 28",
    "sg:city":"R\u00fcdesheim am Rhein",
    "sg:postcode":"65385",
    "sg:province":"Hessen",
    "wof:name":"Move Ges. F. Unternehmens- Beratung, Organisation Und",
    "wof:placetype":"venue"
},
  "geometry": {"coordinates":[7.9308929443,49.9834213257],"type":"Point"}
}