{
  "type": "Feature",
  "properties": {
    "iso:country":"DE",
    "sg:address":"Arsterdamm 96 A",
    "sg:city":"Bremen",
    "sg:phone":"+49 421/86513",
    "sg:postcode":"28277",
    "sg:province":"Bremen",
    "wof:name":"\u00dcnal Brot Gmbh",
    "wof:placetype":"venue"
},
  "geometry": {"coordinates":[8.831367,53.04089],"type":"Point"}
}