{
  "type": "Feature",
  "properties": {
    "iso:country":"DE",
    "sg:address":"Fichtestr. 6",
    "sg:city":"Hamburg",
    "sg:phone":"+49 40/205110",
    "sg:postcode":"22089",
    "sg:province":"Hamburg",
    "wof:name":"M. Lader Masseur",
    "wof:placetype":"venue"
},
  "geometry": {"coordinates":[10.050807,53.569084],"type":"Point"}
}