{
  "type": "Feature",
  "properties": {
    "iso:country":"DE",
    "sg:address":"Trumpgenstr. 2",
    "sg:city":"Linnich",
    "sg:phone":"+49 2462/6501",
    "sg:postcode":"52441",
    "sg:province":"Nordrhein-Westfalen",
    "wof:name":"F. K\u00fcppers Rechtsanwalt",
    "wof:placetype":"venue"
},
  "geometry": {"coordinates":[6.2744069099,50.9793128967],"type":"Point"}
}