{
  "type": "Feature",
  "properties": {
    "iso:country":"DE",
    "sg:address":"Kastanienstr. 5",
    "sg:city":"W\u00f6rth",
    "sg:phone":"+49 9372/72187",
    "sg:postcode":"63939",
    "sg:province":"Bayern",
    "wof:name":"Hermann Platz",
    "wof:placetype":"venue"
},
  "geometry": {"coordinates":[9.159843,49.789951],"type":"Point"}
}