{
  "type": "Feature",
  "properties": {
    "iso:country":"DE",
    "sg:address":"Bahnhofstr. 160",
    "sg:city":"Ratingen",
    "sg:phone":"+49 2102/60947",
    "sg:postcode":"40883",
    "sg:province":"Nordrhein-Westfalen",
    "wof:name":"Micky",
    "wof:placetype":"venue"
},
  "geometry": {"coordinates":[6.9091410637,51.3301429749],"type":"Point"}
}