{
  "type": "Feature",
  "properties": {
    "iso:country":"DE",
    "sg:address":"Lange Wand 16",
    "sg:city":"Delmenhorst",
    "sg:postcode":"27753",
    "sg:province":"Niedersachsen",
    "wof:name":"M@gic Web Internetagentur Gmbh",
    "wof:placetype":"venue"
},
  "geometry": {"coordinates":[8.5873651505,53.0375938416],"type":"Point"}
}