{
  "type": "Feature",
  "properties": {
    "iso:country":"DE",
    "sg:address":"Tornquiststr. 21",
    "sg:city":"Hamburg",
    "sg:phone":"+49 40/4908544",
    "sg:postcode":"20259",
    "sg:province":"Hamburg",
    "wof:name":"Gretiza Jaenke Architektin",
    "wof:placetype":"venue"
},
  "geometry": {"coordinates":[9.9571,53.572472],"type":"Point"}
}