{
  "type": "Feature",
  "properties": {
    "iso:country":"DE",
    "sg:address":"Elfriedenstr. 13",
    "sg:city":"M\u00fcnchen",
    "sg:phone":"+49 89/43987825",
    "sg:postcode":"81827",
    "sg:province":"Bayern",
    "wof:name":"Bwa Ursula Bringmann",
    "wof:placetype":"venue"
},
  "geometry": {"coordinates":[11.6827201843,48.115436554],"type":"Point"}
}