{
  "type": "Feature",
  "properties": {
    "iso:country":"DE",
    "sg:address":"D\u00fcrrenbacher H\u00fctte 1 b",
    "sg:city":"Weimar",
    "sg:postcode":"99427",
    "sg:province":"Th\u00fcringen",
    "wof:name":"Vereinigte Metallbau Gmbh",
    "wof:placetype":"venue"
},
  "geometry": {"coordinates":[11.3492078781,51.0007896423],"type":"Point"}
}