{
  "type": "Feature",
  "properties": {
    "iso:country":"DE",
    "sg:address":"H\u00fchnerstr. 4",
    "sg:city":"Dorsten",
    "sg:phone":"+49 2362/42989",
    "sg:postcode":"46282",
    "sg:province":"Nordrhein-Westfalen",
    "wof:name":"Herbert Wiethoff Immobilien Gmbh",
    "wof:placetype":"venue"
},
  "geometry": {"coordinates":[6.9643440247,51.6618919373],"type":"Point"}
}