{
  "type": "Feature",
  "properties": {
    "iso:country":"DE",
    "sg:address":"Schillerstr. 10",
    "sg:city":"Schwerin",
    "sg:phone":"+49 385/714697",
    "sg:postcode":"19059",
    "sg:province":"Mecklenburg-Vorpommern",
    "wof:name":"Roland Jawi Architekt",
    "wof:placetype":"venue"
},
  "geometry": {"coordinates":[11.398211,53.635071],"type":"Point"}
}