{
  "type": "Feature",
  "properties": {
    "iso:country":"DE",
    "sg:address":"Schlo\u00dfstr. 12",
    "sg:city":"Haiterbach",
    "sg:phone":"+49 7456/7391",
    "sg:postcode":"72221",
    "sg:province":"Baden-W\u00fcrttemberg",
    "wof:name":"Maria Rippl Heilpraktikerin",
    "wof:placetype":"venue"
},
  "geometry": {"coordinates":[8.6717987061,48.5412826538],"type":"Point"}
}