{
  "type": "Feature",
  "properties": {
    "iso:country":"DE",
    "sg:address":"Poststr. 3",
    "sg:city":"Wilkau-Ha\u00dflau",
    "sg:phone":"+49 375/671114",
    "sg:postcode":"08112",
    "sg:province":"Sachsen",
    "wof:name":"Uwe Bax Notariat",
    "wof:placetype":"venue"
},
  "geometry": {"coordinates":[12.5112571716,50.6740036011],"type":"Point"}
}