{
  "type": "Feature",
  "properties": {
    "iso:country":"DE",
    "sg:address":"Neusser Str. 87",
    "sg:city":"Kaarst",
    "sg:phone":"+49 2131/797171",
    "sg:postcode":"41564",
    "sg:province":"Nordrhein-Westfalen",
    "wof:name":"Dieter Junker",
    "wof:placetype":"venue"
},
  "geometry": {"coordinates":[6.632985,51.230736],"type":"Point"}
}