{
  "type": "Feature",
  "properties": {
    "iso:country":"DE",
    "sg:address":"Dresdner Str. 15",
    "sg:city":"Gro\u00dfostheim",
    "sg:phone":"+49 6026/1238",
    "sg:postcode":"63762",
    "sg:province":"Bayern",
    "wof:name":"Hery Thomas Container Dienst Gmbh",
    "wof:placetype":"venue"
},
  "geometry": {"coordinates":[9.0354204178,49.9326972961],"type":"Point"}
}