{
  "type": "Feature",
  "properties": {
    "iso:country":"DE",
    "sg:address":"Silcherstr. 10",
    "sg:city":"Asperg",
    "sg:phone":"+49 7141/62188",
    "sg:postcode":"71679",
    "sg:province":"Baden-W\u00fcrttemberg",
    "wof:name":"Wilhelm Sch\u00e4fer",
    "wof:placetype":"venue"
},
  "geometry": {"coordinates":[9.12776,48.90419],"type":"Point"}
}