{
  "type": "Feature",
  "properties": {
    "iso:country":"DE",
    "sg:address":"Obergasse 13",
    "sg:city":"Usingen",
    "sg:phone":"+49 6081/66742",
    "sg:postcode":"61250",
    "sg:province":"Hessen",
    "wof:name":"Adler-apotheke",
    "wof:placetype":"venue"
},
  "geometry": {"coordinates":[8.53707,50.33532],"type":"Point"}
}