{
  "type": "Feature",
  "properties": {
    "iso:country":"DE",
    "sg:address":"Zirkelstr. 6",
    "sg:city":"Ha\u00dffurt",
    "sg:phone":"+49 9521/94060",
    "sg:postcode":"97437",
    "sg:province":"Bayern",
    "wof:name":"Kurt Kr\u00e4mer Steuerberater",
    "wof:placetype":"venue"
},
  "geometry": {"coordinates":[10.5193223953,50.0470314026],"type":"Point"}
}