{
  "type": "Feature",
  "properties": {
    "iso:country":"DE",
    "sg:address":"Frankenwaldstr 27-29",
    "sg:city":"Selbitz",
    "sg:phone":"+49 9280/98300",
    "sg:postcode":"95152",
    "sg:province":"Bayern",
    "wof:name":"Ferntrans-internationale Speditions-gmbh",
    "wof:placetype":"venue"
},
  "geometry": {"coordinates":[11.7417812347,50.3119010925],"type":"Point"}
}