{
  "type": "Feature",
  "properties": {
    "iso:country":"DE",
    "sg:city":"Wuppertal",
    "sg:postcode":"42281",
    "sg:province":"Nordrhein-Westfalen",
    "wof:name":"E. Christ & Co.",
    "wof:placetype":"venue"
},
  "geometry": {"coordinates":[7.19032,51.285889],"type":"Point"}
}