{
  "type": "Feature",
  "properties": {
    "iso:country":"DE",
    "sg:address":"Berliner Str. 45",
    "sg:city":"Gr\u00e4fenhainichen",
    "sg:phone":"+49 34953/22801",
    "sg:postcode":"06773",
    "sg:province":"Sachsen-Anhalt",
    "wof:name":"Ltk Montage Und Ausbau Gmbh",
    "wof:placetype":"venue"
},
  "geometry": {"coordinates":[12.4787759781,51.7383842468],"type":"Point"}
}