{
  "type": "Feature",
  "properties": {
    "iso:country":"DE",
    "sg:address":"Lazarettstr. 3",
    "sg:city":"Sulzbach",
    "sg:phone":"+49 6897/5720",
    "sg:postcode":"66280",
    "sg:province":"Saarland",
    "wof:name":"Hotel L Auberge",
    "wof:placetype":"venue"
},
  "geometry": {"coordinates":[7.0559549332,49.2988395691],"type":"Point"}
}