{
  "type": "Feature",
  "properties": {
    "iso:country":"DE",
    "sg:address":"Duringstr. 9",
    "sg:city":"T\u00fcrkenfeld",
    "sg:phone":"+49 8193/7660",
    "sg:postcode":"82299",
    "sg:province":"Bayern",
    "wof:name":"Edeka",
    "wof:placetype":"venue"
},
  "geometry": {"coordinates":[11.0856571198,48.1071929932],"type":"Point"}
}