{
  "type": "Feature",
  "properties": {
    "iso:country":"DE",
    "sg:address":"Peterstr. 15",
    "sg:city":"Weinheim",
    "sg:phone":"+49 6201/15998",
    "sg:postcode":"69469",
    "sg:province":"Baden-W\u00fcrttemberg",
    "wof:name":"Peter Meng",
    "wof:placetype":"venue"
},
  "geometry": {"coordinates":[8.673458,49.557007],"type":"Point"}
}