{
  "type": "Feature",
  "properties": {
    "iso:country":"DE",
    "sg:address":"Von-P\u00fcnzendorf-Str. 4a",
    "sg:city":"Oberaurach",
    "sg:phone":"+49 9522/419",
    "sg:postcode":"97514",
    "sg:province":"Bayern",
    "wof:name":"Albert Transport Gmbh",
    "wof:placetype":"venue"
},
  "geometry": {"coordinates":[10.653628,49.930462],"type":"Point"}
}