{
  "type": "Feature",
  "properties": {
    "iso:country":"DE",
    "sg:address":"Bergstr. 13",
    "sg:city":"Altdorf",
    "sg:phone":"+49 871/32374",
    "sg:postcode":"84032",
    "sg:province":"Bayern",
    "wof:name":"Heinrich Buchmeier",
    "wof:placetype":"venue"
},
  "geometry": {"coordinates":[12.1142225266,48.5565223694],"type":"Point"}
}