{
  "type": "Feature",
  "properties": {
    "iso:country":"DE",
    "sg:address":"Platz der Republik 6",
    "sg:city":"Fambach",
    "sg:phone":"+49 36848/31259",
    "sg:postcode":"98597",
    "sg:province":"Th\u00fcringen",
    "wof:name":"Ute Heimel",
    "wof:placetype":"venue"
},
  "geometry": {"coordinates":[10.37465,50.7393],"type":"Point"}
}