{
  "type": "Feature",
  "properties": {
    "iso:country":"DE",
    "sg:address":"Adolf-Spie\u00df-Str. 6",
    "sg:city":"Lauterbach",
    "sg:phone":"+49 6641/2235",
    "sg:postcode":"36341",
    "sg:province":"Hessen",
    "wof:name":"Kath. \u00d6ffentliche Bibliothek St. Michael",
    "wof:placetype":"venue"
},
  "geometry": {"coordinates":[9.392983,50.638428],"type":"Point"}
}