{
  "type": "Feature",
  "properties": {
    "iso:country":"DE",
    "sg:address":"Fischpfortenstr. 21",
    "sg:city":"Hameln",
    "sg:phone":"+49 5151/43900",
    "sg:postcode":"31785",
    "sg:province":"Niedersachsen",
    "wof:name":"Wind Und Wetter E. Kfr.",
    "wof:placetype":"venue"
},
  "geometry": {"coordinates":[9.355548,52.104099],"type":"Point"}
}