{
  "type": "Feature",
  "properties": {
    "iso:country":"DE",
    "sg:address":"Benrather Str. 6 a",
    "sg:city":"D\u00fcsseldorf",
    "sg:postcode":"40213",
    "sg:province":"Nordrhein-Westfalen",
    "wof:name":"Daily Chance Ohg",
    "wof:placetype":"venue"
},
  "geometry": {"coordinates":[6.772654,51.22327],"type":"Point"}
}