{
  "type": "Feature",
  "properties": {
    "iso:country":"DE",
    "sg:address":"Am Kalten Born 45",
    "sg:city":"G\u00f6ttingen",
    "sg:phone":"+49 551/7905316",
    "sg:postcode":"37085",
    "sg:province":"Niedersachsen",
    "wof:name":"Hans-j\u00fcrgen Rockstroh Steuerberater",
    "wof:placetype":"venue"
},
  "geometry": {"coordinates":[9.9647607803,51.5069465637],"type":"Point"}
}