{
  "type": "Feature",
  "properties": {
    "iso:country":"DE",
    "sg:address":"Moerser Str. 455",
    "sg:city":"Krefeld",
    "sg:phone":"+49 2151/597115",
    "sg:postcode":"47803",
    "sg:province":"Nordrhein-Westfalen",
    "wof:name":"Dr. B. Dietrich Steuerberater",
    "wof:placetype":"venue"
},
  "geometry": {"coordinates":[6.5742001534,51.355052948],"type":"Point"}
}