{
  "type": "Feature",
  "properties": {
    "iso:country":"DE",
    "sg:address":"Lenaustr. 25",
    "sg:city":"Biblis",
    "sg:phone":"+49 6245/7438",
    "sg:postcode":"68647",
    "sg:province":"Hessen",
    "wof:name":"J. Bieber Ingenieur",
    "wof:placetype":"venue"
},
  "geometry": {"coordinates":[8.4590988159,49.6942367554],"type":"Point"}
}