{
  "type": "Feature",
  "properties": {
    "iso:country":"DE",
    "sg:address":"Am Stein 23",
    "sg:city":"Simmerath",
    "sg:phone":"+49 2473/2147",
    "sg:postcode":"52152",
    "sg:province":"Nordrhein-Westfalen",
    "wof:name":"Bernd Hallmann",
    "wof:placetype":"venue"
},
  "geometry": {"coordinates":[6.309855938,50.6360244751],"type":"Point"}
}