{
  "type": "Feature",
  "properties": {
    "iso:country":"DE",
    "sg:address":"Strau\u00dfweg 33",
    "sg:city":"Stuttgart",
    "sg:phone":"+49 711/467273",
    "sg:postcode":"70184",
    "sg:province":"Baden-W\u00fcrttemberg",
    "wof:name":"Walter Murko Architekt",
    "wof:placetype":"venue"
},
  "geometry": {"coordinates":[9.200908,48.776588],"type":"Point"}
}