{
  "type": "Feature",
  "properties": {
    "iso:country":"DE",
    "sg:address":"D\u00fcbener Str. 18",
    "sg:city":"Delitzsch",
    "sg:postcode":"04509",
    "sg:province":"Sachsen",
    "wof:name":"Frank Rembarz",
    "wof:placetype":"venue"
},
  "geometry": {"coordinates":[12.340473,51.52692],"type":"Point"}
}