{
  "type": "Feature",
  "properties": {
    "iso:country":"DE",
    "sg:address":"Kolpingstr. 2",
    "sg:city":"Marienm\u00fcnster",
    "sg:phone":"+49 5276/222",
    "sg:postcode":"37696",
    "sg:province":"Nordrhein-Westfalen",
    "wof:name":"Johannes Meyer",
    "wof:placetype":"venue"
},
  "geometry": {"coordinates":[9.189525,51.809128],"type":"Point"}
}