{
  "type": "Feature",
  "properties": {
    "iso:country":"DE",
    "sg:address":"Hauptstr. 1",
    "sg:city":"Halle",
    "sg:phone":"+49 345/7758537",
    "sg:postcode":"06132",
    "sg:province":"Sachsen-Anhalt",
    "wof:name":"Saigon Palace",
    "wof:placetype":"venue"
},
  "geometry": {"coordinates":[9.5567054749,52.0322990417],"type":"Point"}
}