{
  "type": "Feature",
  "properties": {
    "iso:country":"DE",
    "sg:address":"Prisdorfer Weg 1",
    "sg:city":"Tornesch",
    "sg:phone":"+49 4120/238",
    "sg:postcode":"25436",
    "sg:province":"Schleswig-Holstein",
    "wof:name":"Hermann Fr\u00fcchtenicht",
    "wof:placetype":"venue"
},
  "geometry": {"coordinates":[9.749476,53.718975],"type":"Point"}
}