{
  "type": "Feature",
  "properties": {
    "iso:country":"DE",
    "sg:address":"Herforder Str. 37",
    "sg:city":"Bad Salzuflen",
    "sg:phone":"+49 5222/58357",
    "sg:postcode":"32105",
    "sg:province":"Nordrhein-Westfalen",
    "wof:name":"China Imbi\u00df",
    "wof:placetype":"venue"
},
  "geometry": {"coordinates":[8.7372045517,52.0867462158],"type":"Point"}
}