{
  "type": "Feature",
  "properties": {
    "iso:country":"DE",
    "sg:address":"Blaubach 6",
    "sg:city":"K\u00f6ln",
    "sg:phone":"+49 221/230090",
    "sg:postcode":"50676",
    "sg:province":"Nordrhein-Westfalen",
    "wof:name":"Karin Lindenberg",
    "wof:placetype":"venue"
},
  "geometry": {"coordinates":[6.9556970596,50.9328422546],"type":"Point"}
}