{
  "type": "Feature",
  "properties": {
    "iso:country":"DE",
    "sg:address":"Appelkampstr. 20",
    "sg:city":"Bad Oeynhausen",
    "sg:phone":"+49 5734/7633",
    "sg:postcode":"32549",
    "sg:province":"Nordrhein-Westfalen",
    "wof:name":"K Und B K\u00fcche Und Bad Gmbh",
    "wof:placetype":"venue"
},
  "geometry": {"coordinates":[8.766026,52.243095],"type":"Point"}
}