{
  "type": "Feature",
  "properties": {
    "iso:country":"DE",
    "sg:address":"Im Freihafen 9",
    "sg:city":"Duisburg",
    "sg:phone":"+49 203/800601",
    "sg:postcode":"47138",
    "sg:province":"Nordrhein-Westfalen",
    "wof:name":"Wm Kontrakt-logistik Duisburg Gmbh",
    "wof:placetype":"venue"
},
  "geometry": {"coordinates":[6.7497057915,51.4579315186],"type":"Point"}
}