{
  "type": "Feature",
  "properties": {
    "iso:country":"DE",
    "sg:address":"Iltishof 9",
    "sg:city":"Hamm",
    "sg:phone":"+49 2381/84504",
    "sg:postcode":"59071",
    "sg:province":"Nordrhein-Westfalen",
    "wof:name":"Elias Immobilien Gmbh",
    "wof:placetype":"venue"
},
  "geometry": {"coordinates":[7.8682470322,51.6936035156],"type":"Point"}
}