{
  "type": "Feature",
  "properties": {
    "iso:country":"DE",
    "sg:address":"Friedrich-Ebert-Str. 41",
    "sg:city":"Emden",
    "sg:phone":"+49 4921/28454",
    "sg:postcode":"26725",
    "sg:province":"Niedersachsen",
    "wof:name":"B. Wenzel",
    "wof:placetype":"venue"
},
  "geometry": {"coordinates":[7.214468956,53.3651924133],"type":"Point"}
}