{
  "type": "Feature",
  "properties": {
    "iso:country":"DE",
    "sg:address":"Wiesbadener Str. 36",
    "sg:city":"Stuttgart",
    "sg:phone":"+49 711/565040",
    "sg:postcode":"70372",
    "sg:province":"Baden-W\u00fcrttemberg",
    "wof:name":"Rainer Schweitzer Steuerberater",
    "wof:placetype":"venue"
},
  "geometry": {"coordinates":[9.2233495712,48.8058815002],"type":"Point"}
}