{
  "type": "Feature",
  "properties": {
    "iso:country":"DE",
    "sg:address":"Am Kaiser-Friedrich-Bad 6",
    "sg:city":"Wiesbaden",
    "sg:phone":"+49 611/51332",
    "sg:postcode":"65183",
    "sg:province":"Hessen",
    "wof:name":"Dr. Med. Sylvia Sommer \u00c4rztin F\u00fcr Allgemeinmedizin",
    "wof:placetype":"venue"
},
  "geometry": {"coordinates":[8.2387552261,50.0846595764],"type":"Point"}
}