{
  "type": "Feature",
  "properties": {
    "iso:country":"DE",
    "sg:address":"Domb\u00fchler Str. 9",
    "sg:city":"N\u00fcrnberg",
    "sg:phone":"+49 911/670420",
    "sg:postcode":"90449",
    "sg:province":"Bayern",
    "wof:name":"Ilona Reisen Inh. Ilona Wutzer-voleske",
    "wof:placetype":"venue"
},
  "geometry": {"coordinates":[11.0305109024,49.4220619202],"type":"Point"}
}