{
  "type": "Feature",
  "properties": {
    "iso:country":"DE",
    "sg:address":"Sch\u00fclernbrockhof 2",
    "sg:city":"Schneverdingen",
    "sg:postcode":"29640",
    "sg:province":"Niedersachsen",
    "wof:name":"A. Und H. Bosselmann Verwaltungsgesellschaft Mbh",
    "wof:placetype":"venue"
},
  "geometry": {"coordinates":[9.7503080368,53.0882263184],"type":"Point"}
}