{
  "type": "Feature",
  "properties": {
    "iso:country":"DE",
    "sg:address":"Galeonenweg 15",
    "sg:city":"L\u00fcbeck",
    "sg:phone":"+49 451/8966276",
    "sg:postcode":"23558",
    "sg:province":"Schleswig-Holstein",
    "wof:name":"Nord Gmbh Schweisserei Und Maschinenbau",
    "wof:placetype":"venue"
},
  "geometry": {"coordinates":[10.6456184387,53.857421875],"type":"Point"}
}