{
  "type": "Feature",
  "properties": {
    "iso:country":"DE",
    "sg:address":"Am Schulplatz 2",
    "sg:city":"Stemwede",
    "sg:phone":"+49 5745/2210",
    "sg:postcode":"32351",
    "sg:province":"Nordrhein-Westfalen",
    "wof:name":"Werner Schl\u00fcter",
    "wof:placetype":"venue"
},
  "geometry": {"coordinates":[8.4554386139,52.3732032776],"type":"Point"}
}