{
  "type": "Feature",
  "properties": {
    "iso:country":"DE",
    "sg:address":"Waldschmidtweg 1",
    "sg:city":"Deggendorf",
    "sg:postcode":"94469",
    "sg:province":"Bayern",
    "wof:name":"Junghanns Medizintechnik Gmbh",
    "wof:placetype":"venue"
},
  "geometry": {"coordinates":[12.9714002609,48.8346290588],"type":"Point"}
}