{
  "type": "Feature",
  "properties": {
    "iso:country":"DE",
    "sg:address":"Alter Markt 4",
    "sg:city":"Hachenburg",
    "sg:phone":"+49 2662/1840",
    "sg:postcode":"57627",
    "sg:province":"Rheinland-Pfalz",
    "wof:name":"Otto Zimmermann",
    "wof:placetype":"venue"
},
  "geometry": {"coordinates":[7.8237171173,50.6608848572],"type":"Point"}
}