{
  "type": "Feature",
  "properties": {
    "iso:country":"DE",
    "sg:address":"Luchsstr. 11",
    "sg:city":"Oberhausen",
    "sg:phone":"+49 208/645836",
    "sg:postcode":"46149",
    "sg:province":"Nordrhein-Westfalen",
    "wof:name":"U. Krames",
    "wof:placetype":"venue"
},
  "geometry": {"coordinates":[6.841011,51.53141],"type":"Point"}
}