{
  "type": "Feature",
  "properties": {
    "iso:country":"DE",
    "sg:address":"Klaus-Scheufelen-Platz 2",
    "sg:city":"Lenningen",
    "sg:phone":"+49 7026/2616",
    "sg:postcode":"73252",
    "sg:province":"Baden-W\u00fcrttemberg",
    "wof:name":"Ev. Pfarramt Hochwang",
    "wof:placetype":"venue"
},
  "geometry": {"coordinates":[9.4492988586,48.5504570007],"type":"Point"}
}