{
  "type": "Feature",
  "properties": {
    "iso:country":"DE",
    "sg:address":"Bartschiner Str 14",
    "sg:city":"Berlin",
    "sg:phone":"+49 30/6632244",
    "sg:postcode":"12355",
    "sg:province":"Berlin",
    "wof:name":"Dr. M\u00fcller Bautechnik Gmbh",
    "wof:placetype":"venue"
},
  "geometry": {"coordinates":[13.496225,52.411102],"type":"Point"}
}