{
  "type": "Feature",
  "properties": {
    "iso:country":"DE",
    "sg:address":"Kiefernweg 3a",
    "sg:city":"Starnberg",
    "sg:phone":"+49 8151/21742",
    "sg:postcode":"82319",
    "sg:province":"Bayern",
    "wof:name":"Integra Computersysteme",
    "wof:placetype":"venue"
},
  "geometry": {"coordinates":[11.3061847687,47.999671936],"type":"Point"}
}