{
  "type": "Feature",
  "properties": {
    "iso:country":"DE",
    "sg:address":"Erftstr. 51",
    "sg:city":"M\u00f6nchengladbach",
    "sg:postcode":"41238",
    "sg:province":"Nordrhein-Westfalen",
    "wof:name":"Sfg Handels- Gmbh",
    "wof:placetype":"venue"
},
  "geometry": {"coordinates":[6.4905748367,51.1558418274],"type":"Point"}
}