{
  "type": "Feature",
  "properties": {
    "iso:country":"DE",
    "sg:address":"Sallstr.Ecke Krausenstr.",
    "sg:city":"Hannover",
    "sg:phone":"+49 4951/1887669",
    "sg:postcode":"30171",
    "sg:province":"Niedersachsen",
    "wof:name":"Dresdner Bank",
    "wof:placetype":"venue"
},
  "geometry": {"coordinates":[9.754125,52.368679],"type":"Point"}
}