{
  "type": "Feature",
  "properties": {
    "iso:country":"DE",
    "sg:address":"Offenau 63",
    "sg:city":"Bokholt-Hanredder",
    "sg:phone":"+49 4121/84881",
    "sg:postcode":"25335",
    "sg:province":"Schleswig-Holstein",
    "wof:name":"Erhard Wiebicke",
    "wof:placetype":"venue"
},
  "geometry": {"coordinates":[9.6916809082,53.7725334167],"type":"Point"}
}