{
  "type": "Feature",
  "properties": {
    "iso:country":"DE",
    "sg:address":"K\u00f6lner Str. 7",
    "sg:city":"Bad M\u00fcnstereifel",
    "sg:phone":"+49 2253/7726",
    "sg:postcode":"53902",
    "sg:province":"Nordrhein-Westfalen",
    "wof:name":"Helga Sack Massage- Und B\u00e4derpraxis",
    "wof:placetype":"venue"
},
  "geometry": {"coordinates":[6.765033,50.557655],"type":"Point"}
}