{
  "type": "Feature",
  "properties": {
    "iso:country":"DE",
    "sg:address":"Siedlungsstr. 2",
    "sg:city":"Grafenau",
    "sg:phone":"+49 8552/96430",
    "sg:postcode":"94481",
    "sg:province":"Bayern",
    "wof:name":"Pension Franz Fuchs",
    "wof:placetype":"venue"
},
  "geometry": {"coordinates":[13.4155550003,48.8510971069],"type":"Point"}
}