{
  "type": "Feature",
  "properties": {
    "iso:country":"DE",
    "sg:address":"Hochzoller Str. 19a",
    "sg:city":"Augsburg",
    "sg:phone":"+49 821/64004",
    "sg:postcode":"86163",
    "sg:province":"Bayern",
    "wof:name":"Diabos Gmbh",
    "wof:placetype":"venue"
},
  "geometry": {"coordinates":[10.9446363449,48.3525314331],"type":"Point"}
}