{
  "type": "Feature",
  "properties": {
    "iso:country":"DE",
    "sg:address":"Reinfeld 2",
    "sg:city":"Blomesche Wildnis",
    "sg:phone":"+49 4124/3355",
    "sg:postcode":"25348",
    "sg:province":"Schleswig-Holstein",
    "wof:name":"Dieter Saul",
    "wof:placetype":"venue"
},
  "geometry": {"coordinates":[9.445311,53.793079],"type":"Point"}
}