{
  "type": "Feature",
  "properties": {
    "iso:country":"DE",
    "sg:address":"Junkerstr. 7",
    "sg:city":"Wittingen",
    "sg:phone":"+49 5831/2065",
    "sg:postcode":"29378",
    "sg:province":"Niedersachsen",
    "wof:name":"Anja Pewestorff",
    "wof:placetype":"venue"
},
  "geometry": {"coordinates":[10.7374277115,52.7286758423],"type":"Point"}
}