{
  "type": "Feature",
  "properties": {
    "iso:country":"DE",
    "sg:address":"Feldstr. 195",
    "sg:city":"Goch",
    "sg:phone":"+49 2823/10080",
    "sg:postcode":"47574",
    "sg:province":"Nordrhein-Westfalen",
    "wof:name":"Gvw Garnveredlungswerke Gmbh",
    "wof:placetype":"venue"
},
  "geometry": {"coordinates":[6.155479908,51.6892471313],"type":"Point"}
}