{
  "type": "Feature",
  "properties": {
    "iso:country":"DE",
    "sg:address":"Rheinstr. 14",
    "sg:city":"Rheinberg",
    "sg:phone":"+49 2843/2303",
    "sg:postcode":"47495",
    "sg:province":"Nordrhein-Westfalen",
    "wof:name":"Babyk\u00f6rbchen Vanessa",
    "wof:placetype":"venue"
},
  "geometry": {"coordinates":[6.6014618874,51.5465164185],"type":"Point"}
}