{
  "type": "Feature",
  "properties": {
    "iso:country":"DE",
    "sg:address":"Obere Hauptstr. 9a",
    "sg:city":"L\u00f6ffingen",
    "sg:phone":"+49 7654/8707",
    "sg:postcode":"79843",
    "sg:province":"Baden-W\u00fcrttemberg",
    "wof:name":"Pizzeria Hexenschopf",
    "wof:placetype":"venue"
},
  "geometry": {"coordinates":[8.3468399048,47.8844680786],"type":"Point"}
}