{
  "type": "Feature",
  "properties": {
    "iso:country":"DE",
    "sg:address":"Czeminskistr. 1 a",
    "sg:city":"Berlin",
    "sg:phone":"+49 30/7844844",
    "sg:postcode":"10829",
    "sg:province":"Berlin",
    "wof:name":"Allegro Reproservice Gmbh",
    "wof:placetype":"venue"
},
  "geometry": {"coordinates":[13.3618755341,52.4862213135],"type":"Point"}
}