{
  "type": "Feature",
  "properties": {
    "iso:country":"DE",
    "sg:address":"Feldstr. 6",
    "sg:city":"Wulften",
    "sg:phone":"+49 5556/1622",
    "sg:postcode":"37199",
    "sg:province":"Niedersachsen",
    "wof:name":"A. Deppe",
    "wof:placetype":"venue"
},
  "geometry": {"coordinates":[10.175117,51.65506],"type":"Point"}
}