{
  "type": "Feature",
  "properties": {
    "iso:country":"DE",
    "sg:address":"Ro\u00dfmarkt 23",
    "sg:city":"Frankfurt",
    "sg:phone":"+49 69/20159",
    "sg:postcode":"60311",
    "sg:province":"Hessen",
    "wof:name":"Israeli Charter Services Ltd.",
    "wof:placetype":"venue"
},
  "geometry": {"coordinates":[8.676004,50.111973],"type":"Point"}
}