{
  "type": "Feature",
  "properties": {
    "iso:country":"DE",
    "sg:address":"Guntersrieth 11",
    "sg:city":"Pommelsbrunn",
    "sg:phone":"+49 9154/4881",
    "sg:postcode":"91224",
    "sg:province":"Bayern",
    "wof:name":"G. Sperber-bayer",
    "wof:placetype":"venue"
},
  "geometry": {"coordinates":[11.572933197,49.4828987122],"type":"Point"}
}