{
  "type": "Feature",
  "properties": {
    "iso:country":"DE",
    "sg:address":"Bahnhofstr. 30",
    "sg:city":"Linden",
    "sg:phone":"+49 6403/73347",
    "sg:postcode":"35440",
    "sg:province":"Hessen",
    "wof:name":"Michael Marny",
    "wof:placetype":"venue"
},
  "geometry": {"coordinates":[8.6523170471,50.5283546448],"type":"Point"}
}