{
  "type": "Feature",
  "properties": {
    "iso:country":"DE",
    "sg:address":"Marktplatz 29",
    "sg:city":"Schw\u00e4bisch Gm\u00fcnd",
    "sg:phone":"+49 7171/929078",
    "sg:postcode":"73525",
    "sg:province":"Baden-W\u00fcrttemberg",
    "wof:name":"Klaus Illig",
    "wof:placetype":"venue"
},
  "geometry": {"coordinates":[9.7969684601,48.800907135],"type":"Point"}
}