{
  "type": "Feature",
  "properties": {
    "iso:country":"DE",
    "sg:address":"Bahnhofstr. 10",
    "sg:city":"Burg",
    "sg:phone":"+49 4825/1441",
    "sg:postcode":"25712",
    "sg:province":"Schleswig-Holstein",
    "wof:name":"Penns-kluch",
    "wof:placetype":"venue"
},
  "geometry": {"coordinates":[9.2608728409,53.998714447],"type":"Point"}
}