{
  "type": "Feature",
  "properties": {
    "iso:country":"DE",
    "sg:address":"Neuenh\u00e4userstr. 4",
    "sg:city":"Velpke",
    "sg:phone":"+49 5364/3688",
    "sg:postcode":"38458",
    "sg:province":"Niedersachsen",
    "wof:name":"R. Wolters",
    "wof:placetype":"venue"
},
  "geometry": {"coordinates":[10.934847,52.408203],"type":"Point"}
}