{
  "type": "Feature",
  "properties": {
    "iso:country":"DE",
    "sg:address":"Wallstr. 52",
    "sg:city":"Gelsenkirchen",
    "sg:phone":"+49 209/56014",
    "sg:postcode":"45899",
    "sg:province":"Nordrhein-Westfalen",
    "wof:name":"Horster Motorrad-museum",
    "wof:placetype":"venue"
},
  "geometry": {"coordinates":[7.03849,51.525017],"type":"Point"}
}