{
  "type": "Feature",
  "properties": {
    "iso:country":"DE",
    "sg:address":"Hersbrucker Str. 1",
    "sg:city":"Alfeld",
    "sg:phone":"+49 9157/226",
    "sg:postcode":"91236",
    "sg:province":"Bayern",
    "wof:name":"Ev. Luth. Pfarramt",
    "wof:placetype":"venue"
},
  "geometry": {"coordinates":[11.5443954468,49.4304351807],"type":"Point"}
}