{
  "type": "Feature",
  "properties": {
    "iso:country":"DE",
    "sg:address":"Kirschstr. 12",
    "sg:city":"M\u00fcnchen",
    "sg:phone":"+49 89/35487240",
    "sg:postcode":"80999",
    "sg:province":"Bayern",
    "wof:name":"Sv-computer- Und Kommunikations-verlag Gmbh",
    "wof:placetype":"venue"
},
  "geometry": {"coordinates":[11.4671669006,48.1824188232],"type":"Point"}
}