{
  "type": "Feature",
  "properties": {
    "iso:country":"DE",
    "sg:address":"Cleverhofer Weg 2",
    "sg:city":"Bad Schwartau",
    "sg:phone":"+49 451/24458",
    "sg:postcode":"23611",
    "sg:province":"Schleswig-Holstein",
    "wof:name":"Bauservice K\u00fchl Ohg",
    "wof:placetype":"venue"
},
  "geometry": {"coordinates":[10.684119,53.907707],"type":"Point"}
}