{
  "type": "Feature",
  "properties": {
    "iso:country":"DE",
    "sg:address":"Hof am Born",
    "sg:city":"Wallmerod",
    "sg:phone":"+49 6435/1014",
    "sg:postcode":"56414",
    "sg:province":"Rheinland-Pfalz",
    "wof:name":"Hans-josef Weiand",
    "wof:placetype":"venue"
},
  "geometry": {"coordinates":[7.954642,50.48679],"type":"Point"}
}