{
  "type": "Feature",
  "properties": {
    "iso:country":"DE",
    "sg:address":"Hafenstr. 25",
    "sg:city":"Stralsund",
    "sg:phone":"+49 3831/292065",
    "sg:postcode":"18439",
    "sg:province":"Mecklenburg-Vorpommern",
    "wof:name":"Rosa Luxemburg",
    "wof:placetype":"venue"
},
  "geometry": {"coordinates":[13.098881,54.309284],"type":"Point"}
}