{
  "type": "Feature",
  "properties": {
    "iso:country":"DE",
    "sg:address":"Achternbergstr. 11a",
    "sg:city":"Gelsenkirchen",
    "sg:phone":"+49 209/134014",
    "sg:postcode":"45884",
    "sg:province":"Nordrhein-Westfalen",
    "wof:name":"Rauschendorf Gmbh",
    "wof:placetype":"venue"
},
  "geometry": {"coordinates":[7.0857157707,51.4864463806],"type":"Point"}
}