{
  "type": "Feature",
  "properties": {
    "iso:country":"DE",
    "sg:city":"Oberhausen-Rheinhausen",
    "sg:phone":"+49 7254/2282",
    "sg:postcode":"68794",
    "sg:province":"Baden-W\u00fcrttemberg",
    "wof:name":"Was Anlagenversicherung Gmbh",
    "wof:placetype":"venue"
},
  "geometry": {"coordinates":[8.483247,49.260353],"type":"Point"}
}