{
  "type": "Feature",
  "properties": {
    "iso:country":"DE",
    "sg:address":"Waldhofstr. 19",
    "sg:city":"Vilshofen",
    "sg:postcode":"94474",
    "sg:province":"Bayern",
    "wof:name":"M & S Immobilien Gmbh & Co. Kg",
    "wof:placetype":"venue"
},
  "geometry": {"coordinates":[13.1946763992,48.593547821],"type":"Point"}
}