{
  "type": "Feature",
  "properties": {
    "iso:country":"DE",
    "sg:address":"Fliederstr. 13",
    "sg:city":"Battenberg",
    "sg:phone":"+49 6452/8560",
    "sg:postcode":"35088",
    "sg:province":"Hessen",
    "wof:name":"Frank Kosilowski & Dagmar Falk",
    "wof:placetype":"venue"
},
  "geometry": {"coordinates":[8.6434640884,51.0086097717],"type":"Point"}
}