{
  "type": "Feature",
  "properties": {
    "iso:country":"DE",
    "sg:address":"Panoramastr. 47",
    "sg:city":"Herrsching",
    "sg:postcode":"82211",
    "sg:province":"Bayern",
    "wof:name":"Fegu Immobilien Gmbh",
    "wof:placetype":"venue"
},
  "geometry": {"coordinates":[11.1689147949,47.9830703735],"type":"Point"}
}