{
  "type": "Feature",
  "properties": {
    "iso:country":"DE",
    "sg:address":"Am Sinnerauwer 3",
    "sg:city":"Hemer",
    "sg:phone":"+49 2372/10912",
    "sg:postcode":"58675",
    "sg:province":"Nordrhein-Westfalen",
    "wof:name":"Katholisches Pfarramt Christk\u00f6nig",
    "wof:placetype":"venue"
},
  "geometry": {"coordinates":[7.7635111809,51.3869590759],"type":"Point"}
}