{
  "type": "Feature",
  "properties": {
    "iso:country":"DE",
    "sg:address":"Lange Gasse 1",
    "sg:city":"Wangen",
    "sg:phone":"+49 7522/4369",
    "sg:postcode":"88239",
    "sg:province":"Baden-W\u00fcrttemberg",
    "wof:name":"Gustav Freytag-archiv",
    "wof:placetype":"venue"
},
  "geometry": {"coordinates":[9.835816,47.687469],"type":"Point"}
}