{
  "type": "Feature",
  "properties": {
    "iso:country":"DE",
    "sg:address":"Mainzer Str. 14",
    "sg:city":"S\u00f6mmerda",
    "sg:phone":"+49 3634/30896",
    "sg:postcode":"99610",
    "sg:province":"Th\u00fcringen",
    "wof:name":"Furkert-optik",
    "wof:placetype":"venue"
},
  "geometry": {"coordinates":[11.1191854477,51.1598815918],"type":"Point"}
}