{
  "type": "Feature",
  "properties": {
    "iso:country":"DE",
    "sg:address":"Rathofplatz 5",
    "sg:city":"Bad Sooden-Allendorf",
    "sg:phone":"+49 5629/18919",
    "sg:postcode":"37242",
    "sg:province":"Hessen",
    "wof:name":"Hix Und Schulz Rechtsanw\u00e4lte",
    "wof:placetype":"venue"
},
  "geometry": {"coordinates":[9.9766798019,51.2745132446],"type":"Point"}
}