{
  "type": "Feature",
  "properties": {
    "iso:country":"DE",
    "sg:address":"Flachsbleiche 70",
    "sg:city":"Kaarst",
    "sg:phone":"+49 2131/68063",
    "sg:postcode":"41564",
    "sg:province":"Nordrhein-Westfalen",
    "wof:name":"Gerhard Eggers Ingenieur",
    "wof:placetype":"venue"
},
  "geometry": {"coordinates":[6.5933589935,51.2304153442],"type":"Point"}
}