{
  "type": "Feature",
  "properties": {
    "iso:country":"DE",
    "sg:address":"Oschatzer Str. 3",
    "sg:city":"Dahlen",
    "sg:phone":"+49 34361/51313",
    "sg:postcode":"04774",
    "sg:province":"Sachsen",
    "wof:name":"K. Hartwig Masseur",
    "wof:placetype":"venue"
},
  "geometry": {"coordinates":[12.998951,51.365459],"type":"Point"}
}