{
  "type": "Feature",
  "properties": {
    "iso:country":"DE",
    "sg:address":"Scharnhorststr. 13",
    "sg:city":"Fritzlar",
    "sg:phone":"+49 5622/2155",
    "sg:postcode":"34560",
    "sg:province":"Hessen",
    "wof:name":"Freundeskreis Der Wirbels\u00e4ulenerkrankten E. V.",
    "wof:placetype":"venue"
},
  "geometry": {"coordinates":[9.2928800583,51.1215744019],"type":"Point"}
}