{
  "type": "Feature",
  "properties": {
    "iso:country":"DE",
    "sg:address":"Rhein-Mosel-Str. 39",
    "sg:city":"Emmelshausen",
    "sg:phone":"+49 6747/6088",
    "sg:postcode":"56281",
    "sg:province":"Rheinland-Pfalz",
    "wof:name":"H. Braun Und F. J. Werdier",
    "wof:placetype":"venue"
},
  "geometry": {"coordinates":[7.558494,50.155872],"type":"Point"}
}