{
  "type": "Feature",
  "properties": {
    "iso:country":"DE",
    "sg:address":"Hauptstr. 32",
    "sg:city":"Neubulach",
    "sg:phone":"+49 7053/7724",
    "sg:postcode":"75387",
    "sg:province":"Baden-W\u00fcrttemberg",
    "wof:name":"Anna Rathfelder",
    "wof:placetype":"venue"
},
  "geometry": {"coordinates":[8.6807823181,48.6551971436],"type":"Point"}
}