{
  "type": "Feature",
  "properties": {
    "iso:country":"DE",
    "sg:address":"Pfannm\u00fcllerweg 12",
    "sg:city":"Darmstadt",
    "sg:phone":"+49 6151/76339",
    "sg:postcode":"64289",
    "sg:province":"Hessen",
    "wof:name":"Dr. Wolfgang Billig Architekt Ingenieur",
    "wof:placetype":"venue"
},
  "geometry": {"coordinates":[8.685009,49.894573],"type":"Point"}
}