{
  "type": "Feature",
  "properties": {
    "iso:country":"DE",
    "sg:address":"Mozartstr. 39",
    "sg:city":"Leverkusen",
    "sg:phone":"+49 214/502175",
    "sg:postcode":"51375",
    "sg:province":"Nordrhein-Westfalen",
    "wof:name":"Dr. G\u00fcnter Kaesberg Steuerberater",
    "wof:placetype":"venue"
},
  "geometry": {"coordinates":[7.0460629463,51.0254707336],"type":"Point"}
}