{
  "type": "Feature",
  "properties": {
    "iso:country":"DE",
    "sg:address":"Zum Stein 13",
    "sg:city":"Fritzlar",
    "sg:phone":"+49 5622/6464",
    "sg:postcode":"34560",
    "sg:province":"Hessen",
    "wof:name":"Norbert Petersen",
    "wof:placetype":"venue"
},
  "geometry": {"coordinates":[9.3156223297,51.1305770874],"type":"Point"}
}