{
  "type": "Feature",
  "properties": {
    "iso:country":"DE",
    "sg:address":"Am Sch\u00f6nenkamp 192",
    "sg:city":"D\u00fcsseldorf",
    "sg:phone":"+49 211/743897",
    "sg:postcode":"40599",
    "sg:province":"Nordrhein-Westfalen",
    "wof:name":"Sven Und Alice Jan\u00dfen",
    "wof:placetype":"venue"
},
  "geometry": {"coordinates":[6.8796601295,51.1781349182],"type":"Point"}
}