{
  "type": "Feature",
  "properties": {
    "iso:country":"DE",
    "sg:address":"Ravenstr. 27",
    "sg:city":"Alfeld",
    "sg:phone":"+49 5181/3044",
    "sg:postcode":"31061",
    "sg:province":"Niedersachsen",
    "wof:name":"Weist Bodenbel\u00e4ge",
    "wof:placetype":"venue"
},
  "geometry": {"coordinates":[9.8230361938,51.9957580566],"type":"Point"}
}