{
  "type": "Feature",
  "properties": {
    "iso:country":"DE",
    "sg:address":"Linzer Str. 21",
    "sg:city":"Bad Honnef",
    "sg:phone":"+49 2224/918273",
    "sg:postcode":"53604",
    "sg:province":"Nordrhein-Westfalen",
    "wof:name":"Power Adress Zielgruppen- Marketing Gmbh",
    "wof:placetype":"venue"
},
  "geometry": {"coordinates":[7.22815,50.642719],"type":"Point"}
}