{
  "type": "Feature",
  "properties": {
    "iso:country":"DE",
    "sg:address":"H\u00fcbelstr. 22",
    "sg:city":"Tirschenreuth",
    "sg:phone":"+49 9631/3469",
    "sg:postcode":"95643",
    "sg:province":"Bayern",
    "wof:name":"Elmar Sch\u00f6n",
    "wof:placetype":"venue"
},
  "geometry": {"coordinates":[12.3315029144,49.8825569153],"type":"Point"}
}