{
  "type": "Feature",
  "properties": {
    "iso:country":"DE",
    "sg:address":"Sieben-Planeten-Str. 40",
    "sg:city":"Witten",
    "sg:phone":"+49 2302/19364",
    "sg:postcode":"58454",
    "sg:province":"Nordrhein-Westfalen",
    "wof:name":"A. Capuozzo",
    "wof:placetype":"venue"
},
  "geometry": {"coordinates":[7.3491339684,51.4815711975],"type":"Point"}
}