{
  "type": "Feature",
  "properties": {
    "iso:country":"DE",
    "sg:address":"Seligmann-Baer-Platz",
    "sg:city":"Wiesbaden",
    "sg:phone":"+49 611/692497",
    "sg:postcode":"65203",
    "sg:province":"Hessen",
    "wof:name":"Kbw K\u00fcnstlerb\u00fcro Gmbh",
    "wof:placetype":"venue"
},
  "geometry": {"coordinates":[8.2371549606,50.0483589172],"type":"Point"}
}