{
  "type": "Feature",
  "properties": {
    "iso:country":"DE",
    "sg:address":"Altwieslocher Str. 3",
    "sg:city":"Wiesloch",
    "sg:phone":"+49 6222/51954",
    "sg:postcode":"69168",
    "sg:province":"Baden-W\u00fcrttemberg",
    "wof:name":"Jeans Und Mode Inh. Maria Erner",
    "wof:placetype":"venue"
},
  "geometry": {"coordinates":[8.702354,49.295498],"type":"Point"}
}