{
  "type": "Feature",
  "properties": {
    "iso:country":"DE",
    "sg:address":"Luitpoldstr. 24",
    "sg:city":"Obermoschel",
    "sg:phone":"+49 6362/1265",
    "sg:postcode":"67823",
    "sg:province":"Rheinland-Pfalz",
    "wof:name":"Herbert Schmidt",
    "wof:placetype":"venue"
},
  "geometry": {"coordinates":[7.774641037,49.7242469788],"type":"Point"}
}