{
  "type": "Feature",
  "properties": {
    "iso:country":"DE",
    "sg:address":"Hagebuttenweg 6",
    "sg:city":"Dierhagen",
    "sg:phone":"+49 38226/216",
    "sg:postcode":"18347",
    "sg:province":"Mecklenburg-Vorpommern",
    "wof:name":"Hans-otto Kl\u00fctzow",
    "wof:placetype":"venue"
},
  "geometry": {"coordinates":[12.315368,54.282955],"type":"Point"}
}