{
  "type": "Feature",
  "properties": {
    "iso:country":"DE",
    "sg:address":"Plankenschwaige 3",
    "sg:city":"Landau",
    "sg:phone":"+49 9951/6597",
    "sg:postcode":"94405",
    "sg:province":"Bayern",
    "wof:name":"Xaver Hei\u00dfenhuber",
    "wof:placetype":"venue"
},
  "geometry": {"coordinates":[12.6884613037,48.6931114197],"type":"Point"}
}