{
  "type": "Feature",
  "properties": {
    "iso:country":"DE",
    "sg:address":"Leester Str. 46",
    "sg:city":"Weyhe",
    "sg:phone":"+49 421/895200",
    "sg:postcode":"28844",
    "sg:province":"Niedersachsen",
    "wof:name":"Gerlach Reisen Reiseb\u00fcro Weyhe",
    "wof:placetype":"venue"
},
  "geometry": {"coordinates":[8.816192627,52.9875717163],"type":"Point"}
}