{
  "type": "Feature",
  "properties": {
    "iso:country":"DE",
    "sg:address":"Am Wolfes 8",
    "sg:city":"Kelkheim",
    "sg:phone":"+49 6174/62153",
    "sg:postcode":"65779",
    "sg:province":"Hessen",
    "wof:name":"Dieter Von Goetze Komponist",
    "wof:placetype":"venue"
},
  "geometry": {"coordinates":[8.4016199112,50.1761131287],"type":"Point"}
}