{
  "type": "Feature",
  "properties": {
    "iso:country":"DE",
    "sg:address":"Talstr. 3",
    "sg:city":"Inden",
    "sg:phone":"+49 2423/404525",
    "sg:postcode":"52459",
    "sg:province":"Nordrhein-Westfalen",
    "wof:name":"Gastst\u00e4tte Olympia",
    "wof:placetype":"venue"
},
  "geometry": {"coordinates":[6.3704352379,50.8447227478],"type":"Point"}
}