{
  "type": "Feature",
  "properties": {
    "iso:country":"DE",
    "sg:address":"Attilastr. 110",
    "sg:city":"Berlin",
    "sg:phone":"+49 30/75494910",
    "sg:postcode":"12105",
    "sg:province":"Berlin",
    "wof:name":"Immobilien J\u00f6rg Becker",
    "wof:placetype":"venue"
},
  "geometry": {"coordinates":[13.362698,52.447437],"type":"Point"}
}