{
  "type": "Feature",
  "properties": {
    "iso:country":"DE",
    "sg:address":"Kirchweg 68",
    "sg:city":"Birkenfeld",
    "sg:phone":"+49 7231/47317",
    "sg:postcode":"75217",
    "sg:province":"Baden-W\u00fcrttemberg",
    "wof:name":"Ev. Pfarramt Ii",
    "wof:placetype":"venue"
},
  "geometry": {"coordinates":[8.6424760818,48.8746032715],"type":"Point"}
}