{
  "type": "Feature",
  "properties": {
    "iso:country":"DE",
    "sg:address":"Eichendorffstr. 36",
    "sg:city":"Kiel",
    "sg:phone":"+49 431/14218",
    "sg:postcode":"24116",
    "sg:province":"Schleswig-Holstein",
    "wof:name":"Herbert Schnoor",
    "wof:placetype":"venue"
},
  "geometry": {"coordinates":[10.112904,54.327984],"type":"Point"}
}