{
  "type": "Feature",
  "properties": {
    "iso:country":"DE",
    "sg:address":"Freiheitsstr. 59",
    "sg:city":"Dorsten",
    "sg:phone":"+49 2362/61583",
    "sg:postcode":"46284",
    "sg:province":"Nordrhein-Westfalen",
    "wof:name":"Dieter Filipowski",
    "wof:placetype":"venue"
},
  "geometry": {"coordinates":[6.9499101639,51.6808509827],"type":"Point"}
}