{
  "type": "Feature",
  "properties": {
    "iso:country":"DE",
    "sg:address":"Rothenbaumchaussee 225",
    "sg:city":"Hamburg",
    "sg:phone":"+49 40/458080",
    "sg:postcode":"20149",
    "sg:province":"Hamburg",
    "wof:name":"Abc 4 Margritt Borchers.",
    "wof:placetype":"venue"
},
  "geometry": {"coordinates":[9.988564,53.580189],"type":"Point"}
}