{
  "type": "Feature",
  "properties": {
    "iso:country":"DE",
    "sg:address":"Am S\u00fcdhang 11",
    "sg:city":"Mengerschied",
    "sg:phone":"+49 6765/960003",
    "sg:postcode":"55490",
    "sg:province":"Rheinland-Pfalz",
    "wof:name":"Rolf Ries",
    "wof:placetype":"venue"
},
  "geometry": {"coordinates":[7.503204,49.913254],"type":"Point"}
}