{
  "type": "Feature",
  "properties": {
    "iso:country":"DE",
    "sg:address":"Hauptstr. 2",
    "sg:city":"Illingen",
    "sg:phone":"+49 6825/43040",
    "sg:postcode":"66557",
    "sg:province":"Saarland",
    "wof:name":"Chinarestaurant Nam Kinh",
    "wof:placetype":"venue"
},
  "geometry": {"coordinates":[7.05560112,49.376865387],"type":"Point"}
}