{
  "type": "Feature",
  "properties": {
    "iso:country":"DE",
    "sg:address":"Robert-Bosch-Str. 3",
    "sg:city":"Steinen",
    "sg:phone":"+49 7627/3662",
    "sg:postcode":"79585",
    "sg:province":"Baden-W\u00fcrttemberg",
    "wof:name":"Anita Wagner Heilpraktikerin",
    "wof:placetype":"venue"
},
  "geometry": {"coordinates":[7.7289981842,47.6415367126],"type":"Point"}
}