{
  "type": "Feature",
  "properties": {
    "iso:country":"DE",
    "sg:address":"Dorfstr. 88",
    "sg:city":"Isernhagen",
    "sg:phone":"+49 5139/87173",
    "sg:postcode":"30916",
    "sg:province":"Niedersachsen",
    "wof:name":"Heinrich Schneider",
    "wof:placetype":"venue"
},
  "geometry": {"coordinates":[9.812586,52.459522],"type":"Point"}
}