{
  "type": "Feature",
  "properties": {
    "iso:country":"DE",
    "sg:address":"Schedestr. 17",
    "sg:city":"Hamburg",
    "sg:postcode":"20251",
    "sg:province":"Hamburg",
    "wof:name":"Hbg. Stadthaus Immobilien E.k.",
    "wof:placetype":"venue"
},
  "geometry": {"coordinates":[9.9803905487,53.5938034058],"type":"Point"}
}