{
  "type": "Feature",
  "properties": {
    "iso:country":"DE",
    "sg:address":"Hauptstr. 69",
    "sg:city":"Nickenich",
    "sg:postcode":"56645",
    "sg:province":"Rheinland-Pfalz",
    "wof:name":"Kerstin Leonhard",
    "wof:placetype":"venue"
},
  "geometry": {"coordinates":[7.32652,50.411751],"type":"Point"}
}