{
  "type": "Feature",
  "properties": {
    "iso:country":"DE",
    "sg:address":"Bergischer Ring 31",
    "sg:city":"Hagen",
    "sg:postcode":"58095",
    "sg:province":"Nordrhein-Westfalen",
    "wof:name":"Ortec Verwaltungs- Gmbh",
    "wof:placetype":"venue"
},
  "geometry": {"coordinates":[7.4720392227,51.3541908264],"type":"Point"}
}