{
  "type": "Feature",
  "properties": {
    "iso:country":"DE",
    "sg:address":"Einsteinstr. 2",
    "sg:city":"Tirschenreuth",
    "sg:phone":"+49 9631/6040",
    "sg:postcode":"95643",
    "sg:province":"Bayern",
    "wof:name":"Ernst Gleissner & Co.",
    "wof:placetype":"venue"
},
  "geometry": {"coordinates":[12.34216,49.868336],"type":"Point"}
}