{
  "type": "Feature",
  "properties": {
    "iso:country":"DE",
    "sg:address":"Seelingst\u00e4dter Str.",
    "sg:city":"Trebsen",
    "sg:phone":"+49 34383/41201",
    "sg:postcode":"04687",
    "sg:province":"Sachsen",
    "wof:name":"S\u00e4chs. Quarzporphyr-werke Gmbh",
    "wof:placetype":"venue"
},
  "geometry": {"coordinates":[12.7391271591,51.2866249084],"type":"Point"}
}