{
  "type": "Feature",
  "properties": {
    "iso:country":"DE",
    "sg:address":"Roteb\u00fchlstr 121",
    "sg:city":"Stuttgart",
    "sg:phone":"+49 711/61554311",
    "sg:postcode":"70178",
    "sg:province":"Baden-W\u00fcrttemberg",
    "wof:name":"Mentz Datenverarbeitung Gmbh",
    "wof:placetype":"venue"
},
  "geometry": {"coordinates":[9.159466,48.770817],"type":"Point"}
}