{
  "type": "Feature",
  "properties": {
    "iso:country":"DE",
    "sg:address":"Baumwaide 24",
    "sg:city":"Ilsfeld",
    "sg:phone":"+49 7062/95300",
    "sg:postcode":"74360",
    "sg:province":"Baden-W\u00fcrttemberg",
    "wof:name":"Fastner Gmbh",
    "wof:placetype":"venue"
},
  "geometry": {"coordinates":[9.28196,49.055851],"type":"Point"}
}