{
  "type": "Feature",
  "properties": {
    "iso:country":"DE",
    "sg:address":"Feldkirchenstr.14",
    "sg:city":"WINH\u00d6RING",
    "sg:phone":"+49 8671/979996",
    "sg:postcode":"84543",
    "sg:province":"Bayern",
    "wof:name":"Secomm Technicaldataline",
    "wof:placetype":"venue"
},
  "geometry": {"coordinates":[12.6483373642,48.2640762329],"type":"Point"}
}