{
  "type": "Feature",
  "properties": {
    "iso:country":"DE",
    "sg:address":"Hans-Weigel-Str.",
    "sg:city":"Leipzig",
    "sg:phone":"+49 341/6010412",
    "sg:postcode":"04319",
    "sg:province":"Sachsen",
    "wof:name":"Extra J. Stenten & S\u00f6hne",
    "wof:placetype":"venue"
},
  "geometry": {"coordinates":[12.4712848663,51.3356895447],"type":"Point"}
}