{
  "type": "Feature",
  "properties": {
    "iso:country":"DE",
    "sg:address":"Paul-Warmuth-Str. 3",
    "sg:city":"Dittelbrunn",
    "sg:phone":"+49 9725/4448",
    "sg:postcode":"97456",
    "sg:province":"Bayern",
    "wof:name":"K. Wildanger",
    "wof:placetype":"venue"
},
  "geometry": {"coordinates":[10.206029892,50.0969085693],"type":"Point"}
}