{
  "type": "Feature",
  "properties": {
    "iso:country":"DE",
    "sg:address":"Ludwigstr. 41",
    "sg:city":"Hof",
    "sg:phone":"+49 9281/141323",
    "sg:postcode":"95028",
    "sg:province":"Bayern",
    "wof:name":"K. Greim Architekt",
    "wof:placetype":"venue"
},
  "geometry": {"coordinates":[11.918528,50.32095],"type":"Point"}
}