{
  "type": "Feature",
  "properties": {
    "iso:country":"DE",
    "sg:address":"Schellenwiesen 1",
    "sg:city":"Nehren",
    "sg:phone":"+49 4974/7394560",
    "sg:postcode":"72147",
    "sg:province":"Baden-W\u00fcrttemberg",
    "wof:name":"Vogt Plastic Gmbh",
    "wof:placetype":"venue"
},
  "geometry": {"coordinates":[9.0751438141,48.4365234375],"type":"Point"}
}