{
  "type": "Feature",
  "properties": {
    "iso:country":"DE",
    "sg:address":"Am Weiten Weg 11",
    "sg:city":"Hammelburg",
    "sg:phone":"+49 9732/2757",
    "sg:postcode":"97762",
    "sg:province":"Bayern",
    "wof:name":"Kunststoff-veredelung Franz Kistenberger Kg",
    "wof:placetype":"venue"
},
  "geometry": {"coordinates":[9.8781061172,50.1198883057],"type":"Point"}
}