{
  "type": "Feature",
  "properties": {
    "iso:country":"DE",
    "sg:address":"Schulstr. 7",
    "sg:city":"Bad Bentheim",
    "sg:phone":"+49 5924/372",
    "sg:postcode":"48455",
    "sg:province":"Niedersachsen",
    "wof:name":"Herbert Focke Steinmetzbetrieb",
    "wof:placetype":"venue"
},
  "geometry": {"coordinates":[7.0993518829,52.2949676514],"type":"Point"}
}