{
  "type": "Feature",
  "properties": {
    "iso:country":"DE",
    "sg:address":"Ziegeleistr. 3",
    "sg:city":"Rohr",
    "sg:phone":"+49 8783/91101",
    "sg:postcode":"93352",
    "sg:province":"Bayern",
    "wof:name":"Josef Brand",
    "wof:placetype":"venue"
},
  "geometry": {"coordinates":[11.972215,48.770168],"type":"Point"}
}