{
  "type": "Feature",
  "properties": {
    "iso:country":"DE",
    "sg:address":"Neust\u00e4dter Str. 24",
    "sg:city":"Bischofswerda",
    "sg:phone":"+49 3594/703794",
    "sg:postcode":"01877",
    "sg:province":"Sachsen",
    "wof:name":"C.-j. Behrendt",
    "wof:placetype":"venue"
},
  "geometry": {"coordinates":[14.187062,51.121433],"type":"Point"}
}