{
  "type": "Feature",
  "properties": {
    "iso:country":"DE",
    "sg:address":"Hauptstr. 9",
    "sg:city":"Schraden",
    "sg:phone":"+49 3574/760164",
    "sg:postcode":"04928",
    "sg:province":"Brandenburg",
    "wof:name":"Schradener Landfleischerei Und Handels Gmbh",
    "wof:placetype":"venue"
},
  "geometry": {"coordinates":[13.7016124725,51.4274482727],"type":"Point"}
}