{
  "type": "Feature",
  "properties": {
    "iso:country":"DE",
    "sg:address":"Museumstr. 9",
    "sg:city":"Albstadt",
    "sg:phone":"+49 7431/13140",
    "sg:postcode":"72458",
    "sg:province":"Baden-W\u00fcrttemberg",
    "wof:name":"P. Bickelhaupt Wwe. Gmbh & Co. Kg",
    "wof:placetype":"venue"
},
  "geometry": {"coordinates":[9.0253477097,48.2118721008],"type":"Point"}
}