{
  "type": "Feature",
  "properties": {
    "iso:country":"DE",
    "sg:address":"Gie\u00dfener Str. 22",
    "sg:city":"N\u00fcrnberg",
    "sg:phone":"+49 911/302875",
    "sg:postcode":"90427",
    "sg:province":"Bayern",
    "wof:name":"Stetter Gmbh",
    "wof:placetype":"venue"
},
  "geometry": {"coordinates":[11.004867,49.517063],"type":"Point"}
}