{
  "type": "Feature",
  "properties": {
    "iso:country":"DE",
    "sg:address":"Heu\u00dfweg 35",
    "sg:city":"Hamburg",
    "sg:phone":"+49 40/409059",
    "sg:postcode":"20255",
    "sg:province":"Hamburg",
    "wof:name":"Vita-apotheke Inh. Julia Scheel E. K.",
    "wof:placetype":"venue"
},
  "geometry": {"coordinates":[9.951444,53.576405],"type":"Point"}
}