{
  "type": "Feature",
  "properties": {
    "iso:country":"DE",
    "sg:address":"Wilhelmstr. 35",
    "sg:city":"Heilbronn",
    "sg:phone":"+49 7131/87012",
    "sg:postcode":"74074",
    "sg:province":"Baden-W\u00fcrttemberg",
    "wof:name":"City Grill",
    "wof:placetype":"venue"
},
  "geometry": {"coordinates":[9.2187547684,49.1336746216],"type":"Point"}
}