{
  "type": "Feature",
  "properties": {
    "iso:country":"DE",
    "sg:address":"An der Ro\u00dfm\u00fchle 17",
    "sg:city":"Krefeld",
    "sg:phone":"+49 2151/98870",
    "sg:postcode":"47839",
    "sg:province":"Nordrhein-Westfalen",
    "wof:name":"Itwh Industrie Technik Walzwerkanlagen Handel Gmbh",
    "wof:placetype":"venue"
},
  "geometry": {"coordinates":[6.500181,51.372894],"type":"Point"}
}