{
  "type": "Feature",
  "properties": {
    "iso:country":"DE",
    "sg:address":"Ahornweg 13",
    "sg:city":"Coppenbr\u00fcgge",
    "sg:phone":"+49 5159/96057",
    "sg:postcode":"31863",
    "sg:province":"Niedersachsen",
    "wof:name":"Bergland-pilze Gmbh & Co. Kg",
    "wof:placetype":"venue"
},
  "geometry": {"coordinates":[9.492483139,52.0857467651],"type":"Point"}
}