{
  "type": "Feature",
  "properties": {
    "iso:country":"DE",
    "sg:address":"Weinsteige 1",
    "sg:city":"G\u00fcglingen",
    "sg:phone":"+49 7135/6610",
    "sg:postcode":"74363",
    "sg:province":"Baden-W\u00fcrttemberg",
    "wof:name":"Weinsteige",
    "wof:placetype":"venue"
},
  "geometry": {"coordinates":[8.9983654022,49.0679664612],"type":"Point"}
}