{
  "type": "Feature",
  "properties": {
    "iso:country":"DE",
    "sg:address":"Panscheberg 23",
    "sg:city":"Salzgitter",
    "sg:phone":"+49 5341/265930",
    "sg:postcode":"38239",
    "sg:province":"Niedersachsen",
    "wof:name":"Thieder Reiseb\u00fcro",
    "wof:placetype":"venue"
},
  "geometry": {"coordinates":[10.4816417694,52.1888427734],"type":"Point"}
}