{
  "type": "Feature",
  "properties": {
    "iso:country":"DE",
    "sg:address":"Frankfurter Str. 76",
    "sg:city":"Fulda",
    "sg:postcode":"36043",
    "sg:province":"Hessen",
    "wof:name":"Pro Den Com Vertriebs- Gesellschaft Mbh",
    "wof:placetype":"venue"
},
  "geometry": {"coordinates":[9.676139,50.535126],"type":"Point"}
}