{
  "type": "Feature",
  "properties": {
    "iso:country":"DE",
    "sg:address":"Gro\u00dfe Wollweberstr. 33",
    "sg:city":"Neubrandenburg",
    "sg:phone":"+49 395/5443089",
    "sg:postcode":"17033",
    "sg:province":"Mecklenburg-Vorpommern",
    "wof:name":"Conform Gmbh",
    "wof:placetype":"venue"
},
  "geometry": {"coordinates":[13.256342,53.555031],"type":"Point"}
}