{
  "type": "Feature",
  "properties": {
    "iso:country":"DE",
    "sg:address":"An der Droth 20",
    "sg:city":"Koldingen",
    "sg:postcode":"30982",
    "sg:province":"Niedersachsen",
    "wof:name":"Atc - Wege Zum Erfolg",
    "wof:placetype":"venue"
},
  "geometry": {"coordinates":[9.800947,52.272915],"type":"Point"}
}