{
  "type": "Feature",
  "properties": {
    "iso:country":"DE",
    "sg:address":"Goethestr. 9",
    "sg:city":"Kolbingen",
    "sg:postcode":"78600",
    "sg:province":"Baden-W\u00fcrttemberg",
    "wof:name":"R. Fleischmann",
    "wof:placetype":"venue"
},
  "geometry": {"coordinates":[8.8861646652,48.0525283813],"type":"Point"}
}