{
  "type": "Feature",
  "properties": {
    "iso:country":"DE",
    "sg:address":"Berliner Str. 11",
    "sg:city":"Maintal",
    "sg:phone":"+49 6181/491550",
    "sg:postcode":"63477",
    "sg:province":"Hessen",
    "wof:name":"Theodor Streng",
    "wof:placetype":"venue"
},
  "geometry": {"coordinates":[8.839097023,50.14112854],"type":"Point"}
}