{
  "type": "Feature",
  "properties": {
    "iso:country":"DE",
    "sg:address":"Am Wagrain 38",
    "sg:city":"Amberg",
    "sg:phone":"+49 9621/61164",
    "sg:postcode":"92224",
    "sg:province":"Bayern",
    "wof:name":"Dietrich Von Stein-lausnitz",
    "wof:placetype":"venue"
},
  "geometry": {"coordinates":[11.8540287018,49.4657974243],"type":"Point"}
}