{
  "type": "Feature",
  "properties": {
    "iso:country":"DE",
    "sg:address":"Eisenbahnstr. 33",
    "sg:city":"Pfullingen",
    "sg:phone":"+49 7121/73130",
    "sg:postcode":"72793",
    "sg:province":"Baden-W\u00fcrttemberg",
    "wof:name":"Werner Losch",
    "wof:placetype":"venue"
},
  "geometry": {"coordinates":[9.230425,48.463413],"type":"Point"}
}