{
  "type": "Feature",
  "properties": {
    "iso:country":"DE",
    "sg:address":"Struthstr. 8",
    "sg:city":"Brachttal",
    "sg:phone":"+49 6053/600444",
    "sg:postcode":"63636",
    "sg:province":"Hessen",
    "wof:name":"Dietmar B\u00e4hr",
    "wof:placetype":"venue"
},
  "geometry": {"coordinates":[9.298746,50.305763],"type":"Point"}
}