{
  "type": "Feature",
  "properties": {
    "iso:country":"DE",
    "sg:address":"Bockumer Str. 284",
    "sg:city":"D\u00fcsseldorf",
    "sg:phone":"+49 211/402422",
    "sg:postcode":"40489",
    "sg:province":"Nordrhein-Westfalen",
    "wof:name":"B. Nowag Schiffahrt",
    "wof:placetype":"venue"
},
  "geometry": {"coordinates":[6.728237,51.329857],"type":"Point"}
}