{
  "type": "Feature",
  "properties": {
    "iso:country":"DE",
    "sg:address":"Hofbreede 193",
    "sg:city":"Osnabr\u00fcck",
    "sg:phone":"+49 541/442304",
    "sg:postcode":"49078",
    "sg:province":"Niedersachsen",
    "wof:name":"Hans Lange Architekt",
    "wof:placetype":"venue"
},
  "geometry": {"coordinates":[7.986734,52.257076],"type":"Point"}
}