{
  "type": "Feature",
  "properties": {
    "iso:country":"DE",
    "sg:address":"Westendstr. 19",
    "sg:city":"Betzigau",
    "sg:phone":"+49 831/571200",
    "sg:postcode":"87488",
    "sg:province":"Bayern",
    "wof:name":"Itv Ges. F. Industrie- Tv Mbh",
    "wof:placetype":"venue"
},
  "geometry": {"coordinates":[10.376909256,47.7412490845],"type":"Point"}
}