{
  "type": "Feature",
  "properties": {
    "iso:country":"DE",
    "sg:address":"Eugen-Richter-Str. 19 a",
    "sg:city":"Kassel",
    "sg:phone":"+49 561/311103",
    "sg:postcode":"34134",
    "sg:province":"Hessen",
    "wof:name":"Werner Nolte",
    "wof:placetype":"venue"
},
  "geometry": {"coordinates":[9.4488582611,51.3015632629],"type":"Point"}
}