{
  "type": "Feature",
  "properties": {
    "iso:country":"DE",
    "sg:address":"Br\u00fchler Str. 13",
    "sg:city":"Erfurt",
    "sg:phone":"+49 361/2251616",
    "sg:postcode":"99084",
    "sg:province":"Th\u00fcringen",
    "wof:name":"Karl Ga\u00dfmann",
    "wof:placetype":"venue"
},
  "geometry": {"coordinates":[11.0182647705,50.9737968445],"type":"Point"}
}