{
  "type": "Feature",
  "properties": {
    "iso:country":"DE",
    "sg:address":"Maistr. 15",
    "sg:city":"Oberarnbach",
    "sg:phone":"+49 6371/15295",
    "sg:postcode":"66851",
    "sg:province":"Rheinland-Pfalz",
    "wof:name":"Feuerwehrverein Feuerteufel E. V.",
    "wof:placetype":"venue"
},
  "geometry": {"coordinates":[7.5890870094,49.3870353699],"type":"Point"}
}