{
  "type": "Feature",
  "properties": {
    "iso:country":"DE",
    "sg:address":"Robert-Koch-Str.",
    "sg:city":"Eisenh\u00fcttenstadt",
    "sg:postcode":"15890",
    "sg:province":"Brandenburg",
    "wof:name":"Evangelische Friedensgemeinde",
    "wof:placetype":"venue"
},
  "geometry": {"coordinates":[14.6293096542,52.1387634277],"type":"Point"}
}