{
  "type": "Feature",
  "properties": {
    "iso:country":"DE",
    "sg:address":"Industriestra\u00dfe 2",
    "sg:city":"Ettlingen",
    "sg:phone":"+49 7243/99020",
    "sg:postcode":"76275",
    "sg:province":"Baden-W\u00fcrttemberg",
    "wof:name":"Klaus Kg Ettlingen",
    "wof:placetype":"venue"
},
  "geometry": {"coordinates":[8.4024524689,48.9424705505],"type":"Point"}
}