{
  "type": "Feature",
  "properties": {
    "iso:country":"DE",
    "sg:address":"Heinrich-Hertz-Str. 13",
    "sg:city":"Filderstadt",
    "sg:phone":"+49 711/773965",
    "sg:postcode":"70794",
    "sg:province":"Baden-W\u00fcrttemberg",
    "wof:name":"Busser & Gerstemeyer Gmbh",
    "wof:placetype":"venue"
},
  "geometry": {"coordinates":[9.2027521133,48.6558265686],"type":"Point"}
}