{
  "type": "Feature",
  "properties": {
    "iso:country":"DE",
    "sg:address":"Gartenstr. 9",
    "sg:city":"Geschwenda",
    "sg:phone":"+49 36205/76455",
    "sg:postcode":"98716",
    "sg:province":"Th\u00fcringen",
    "wof:name":"Ludwig Kummer",
    "wof:placetype":"venue"
},
  "geometry": {"coordinates":[10.8217821121,50.7335128784],"type":"Point"}
}