{
  "type": "Feature",
  "properties": {
    "iso:country":"DE",
    "sg:address":"Altonaer Chaussee 6",
    "sg:city":"Schenefeld",
    "sg:phone":"+49 40/8308481",
    "sg:postcode":"22869",
    "sg:province":"Schleswig-Holstein",
    "wof:name":"Blickpunkt Farbe Malerei Gmbh Grebner",
    "wof:placetype":"venue"
},
  "geometry": {"coordinates":[9.853456,53.598484],"type":"Point"}
}