{
  "type": "Feature",
  "properties": {
    "iso:country":"DE",
    "sg:address":"Im Stadtfeld 22",
    "sg:city":"Wolfenb\u00fcttel",
    "sg:phone":"+49 5331/68761",
    "sg:postcode":"38304",
    "sg:province":"Niedersachsen",
    "wof:name":"Bernd M\u00fcller - Schl\u00fcsselfertiges Bauen Und",
    "wof:placetype":"venue"
},
  "geometry": {"coordinates":[10.5409727097,52.1425971985],"type":"Point"}
}