{
  "type": "Feature",
  "properties": {
    "iso:country":"DE",
    "sg:address":"An der Seefahrtsschule 16",
    "sg:city":"Gro\u00dfefehn",
    "sg:phone":"+49 4945/1284",
    "sg:postcode":"26629",
    "sg:province":"Niedersachsen",
    "wof:name":"Hedwig Cassens",
    "wof:placetype":"venue"
},
  "geometry": {"coordinates":[7.522466,53.362659],"type":"Point"}
}