{
  "type": "Feature",
  "properties": {
    "iso:country":"DE",
    "sg:address":"Lutherstr. 23",
    "sg:city":"Lutherstadt Eisleben",
    "sg:phone":"+49 3475/648210",
    "sg:postcode":"06295",
    "sg:province":"Sachsen-Anhalt",
    "wof:name":"Eislebener Bau- Und Sanierungs Gmbh",
    "wof:placetype":"venue"
},
  "geometry": {"coordinates":[11.548867,51.527039],"type":"Point"}
}