{
  "type": "Feature",
  "properties": {
    "iso:country":"DE",
    "sg:address":"F\u00e4rbergasse 6",
    "sg:city":"Lohr",
    "sg:phone":"+49 9352/2223",
    "sg:postcode":"97816",
    "sg:province":"Bayern",
    "wof:name":"W. Stufler",
    "wof:placetype":"venue"
},
  "geometry": {"coordinates":[9.5747318268,49.9941139221],"type":"Point"}
}