{
  "type": "Feature",
  "properties": {
    "iso:country":"DE",
    "sg:address":"H\u00e4spelerstr. 8",
    "sg:city":"Schemmerhofen",
    "sg:phone":"+49 4973/562306",
    "sg:postcode":"88433",
    "sg:province":"Baden-W\u00fcrttemberg",
    "wof:name":"Hugo Klein",
    "wof:placetype":"venue"
},
  "geometry": {"coordinates":[9.7873220444,48.1702423096],"type":"Point"}
}