{
  "type": "Feature",
  "properties": {
    "iso:country":"DE",
    "sg:address":"Maschstr. 6",
    "sg:city":"Uetze",
    "sg:phone":"+49 5147/437",
    "sg:postcode":"31311",
    "sg:province":"Niedersachsen",
    "wof:name":"Heinrich Fricke",
    "wof:placetype":"venue"
},
  "geometry": {"coordinates":[10.100414,52.4856],"type":"Point"}
}