{
  "type": "Feature",
  "properties": {
    "iso:country":"DE",
    "sg:address":"Jahnplatz 5",
    "sg:city":"Worms",
    "sg:phone":"+49 6241/82311",
    "sg:postcode":"67547",
    "sg:province":"Rheinland-Pfalz",
    "wof:name":"G. Br\u00fcckbauer",
    "wof:placetype":"venue"
},
  "geometry": {"coordinates":[8.36656,49.626961],"type":"Point"}
}