{
  "type": "Feature",
  "properties": {
    "iso:country":"DE",
    "sg:address":"Scharnweberstr. 70",
    "sg:city":"Berlin",
    "sg:phone":"+49 30/410300",
    "sg:postcode":"13405",
    "sg:province":"Berlin",
    "wof:name":"Sectronic Ag",
    "wof:placetype":"venue"
},
  "geometry": {"coordinates":[13.3095569611,52.5682601929],"type":"Point"}
}