{
  "type": "Feature",
  "properties": {
    "iso:country":"DE",
    "sg:address":"Max-Beckmann-Str. 57",
    "sg:city":"M\u00fcnchen",
    "sg:phone":"+49 89/421027",
    "sg:postcode":"81735",
    "sg:province":"Bayern",
    "wof:name":"Maria Sellmaier",
    "wof:placetype":"venue"
},
  "geometry": {"coordinates":[11.6539411545,48.1113510132],"type":"Point"}
}