{
  "type": "Feature",
  "properties": {
    "iso:country":"DE",
    "sg:address":"S\u00fcdwall 30",
    "sg:city":"Stendal",
    "sg:phone":"+49 3931/213712",
    "sg:postcode":"39576",
    "sg:province":"Sachsen-Anhalt",
    "wof:name":"Hans Fude",
    "wof:placetype":"venue"
},
  "geometry": {"coordinates":[11.8666410446,52.6027107239],"type":"Point"}
}