{
  "type": "Feature",
  "properties": {
    "iso:country":"DE",
    "sg:address":"Elisabethenstr. 68-70",
    "sg:city":"Darmstadt",
    "sg:phone":"+49 6151/33225",
    "sg:postcode":"64283",
    "sg:province":"Hessen",
    "wof:name":"Wilhelm Klein Verm\u00f6gens- Verwaltungs Gmbh & Co. Kg",
    "wof:placetype":"venue"
},
  "geometry": {"coordinates":[8.644435,49.86919],"type":"Point"}
}