{
  "type": "Feature",
  "properties": {
    "iso:country":"DE",
    "sg:address":"K\u00fcstnerstr. 2",
    "sg:city":"M\u00fcnchen",
    "sg:phone":"+49 89/932491",
    "sg:postcode":"81929",
    "sg:province":"Bayern",
    "wof:name":"G\u00e4rtnerei Ensle",
    "wof:placetype":"venue"
},
  "geometry": {"coordinates":[11.664311409,48.1520690918],"type":"Point"}
}