{
  "type": "Feature",
  "properties": {
    "iso:country":"DE",
    "sg:address":"Johannes-R.-Becher-Str. 1",
    "sg:city":"Gera",
    "sg:phone":"+49 365/486214215",
    "sg:postcode":"07546",
    "sg:province":"Th\u00fcringen",
    "wof:name":"Pro Medi Praxis- Und Krankenhausausstattungen",
    "wof:placetype":"venue"
},
  "geometry": {"coordinates":[12.082564,50.894306],"type":"Point"}
}