{
  "type": "Feature",
  "properties": {
    "iso:country":"DE",
    "sg:address":"Untertaxetweg 148",
    "sg:city":"Gauting",
    "sg:postcode":"82131",
    "sg:province":"Bayern",
    "wof:name":"Barthel & Co. Ingenieurgesellschaft Mbh",
    "wof:placetype":"venue"
},
  "geometry": {"coordinates":[11.3962717056,48.0696525574],"type":"Point"}
}