{
  "type": "Feature",
  "properties": {
    "iso:country":"DE",
    "sg:address":"R\u00f6therweg 12",
    "sg:city":"Wolfstein",
    "sg:phone":"+49 6304/8405",
    "sg:postcode":"67752",
    "sg:province":"Rheinland-Pfalz",
    "wof:name":"Ledwig Gehr Architekt",
    "wof:placetype":"venue"
},
  "geometry": {"coordinates":[7.606549,49.584316],"type":"Point"}
}