{
  "type": "Feature",
  "properties": {
    "iso:country":"DE",
    "sg:address":"Hauptstr. 39",
    "sg:city":"Mudau",
    "sg:phone":"+49 6284/201",
    "sg:postcode":"69427",
    "sg:province":"Baden-W\u00fcrttemberg",
    "wof:name":"Rose",
    "wof:placetype":"venue"
},
  "geometry": {"coordinates":[9.2048768997,49.5338058472],"type":"Point"}
}