{
  "type": "Feature",
  "properties": {
    "iso:country":"DE",
    "sg:address":"Backnanger Str. 38",
    "sg:city":"Allmersbach",
    "sg:phone":"+49 7191/318439",
    "sg:postcode":"71573",
    "sg:province":"Baden-W\u00fcrttemberg",
    "wof:name":"Gerhard Hauser",
    "wof:placetype":"venue"
},
  "geometry": {"coordinates":[9.4674606323,48.9073104858],"type":"Point"}
}