{
  "type": "Feature",
  "properties": {
    "iso:country":"DE",
    "sg:address":"Martinstr. 34",
    "sg:city":"Solingen",
    "sg:phone":"+49 212/222550",
    "sg:postcode":"42655",
    "sg:province":"Nordrhein-Westfalen",
    "wof:name":"Eugen Scalabrin Gmbh & Co.",
    "wof:placetype":"venue"
},
  "geometry": {"coordinates":[7.0448141098,51.1708297729],"type":"Point"}
}