{
  "type": "Feature",
  "properties": {
    "iso:country":"DE",
    "sg:address":"M\u00fcnstermannweg 16",
    "sg:city":"M\u00fcnster",
    "sg:phone":"+49 251/972150",
    "sg:postcode":"48153",
    "sg:province":"Nordrhein-Westfalen",
    "wof:name":"Scheffer Neugebauer Gmbh & Co. Kg",
    "wof:placetype":"venue"
},
  "geometry": {"coordinates":[7.627546,51.93988],"type":"Point"}
}