{
  "type": "Feature",
  "properties": {
    "iso:country":"DE",
    "sg:address":"Satzunger Hauptstr. 23",
    "sg:city":"Satzung",
    "sg:phone":"+49 37364/88285",
    "sg:postcode":"09496",
    "sg:province":"Sachsen",
    "wof:name":"Drehteile Haustein Gmbh",
    "wof:placetype":"venue"
},
  "geometry": {"coordinates":[13.20195,50.525841],"type":"Point"}
}