{
  "type": "Feature",
  "properties": {
    "iso:country":"DE",
    "sg:address":"Weststr. 2",
    "sg:city":"Reichenbach",
    "sg:phone":"+49 3765/12310",
    "sg:postcode":"08468",
    "sg:province":"Sachsen",
    "wof:name":"West-side-shop Die Modeadresse",
    "wof:placetype":"venue"
},
  "geometry": {"coordinates":[12.300246,50.623695],"type":"Point"}
}