{
  "type": "Feature",
  "properties": {
    "iso:country":"DE",
    "sg:address":"Weimarische Str. 3a",
    "sg:city":"Rudolstadt",
    "sg:phone":"+49 3672/43280",
    "sg:postcode":"07407",
    "sg:province":"Th\u00fcringen",
    "wof:name":"Berthold Graser Steuerberater",
    "wof:placetype":"venue"
},
  "geometry": {"coordinates":[11.3353757858,50.72889328],"type":"Point"}
}