{
  "type": "Feature",
  "properties": {
    "iso:country":"DE",
    "sg:address":"Hermann-Daur-Weg 14",
    "sg:city":"Binzen",
    "sg:phone":"+49 7621/61422",
    "sg:postcode":"79589",
    "sg:province":"Baden-W\u00fcrttemberg",
    "wof:name":"Gerhard V\u00f6gtlin",
    "wof:placetype":"venue"
},
  "geometry": {"coordinates":[7.6274881363,47.6301803589],"type":"Point"}
}