{
  "type": "Feature",
  "properties": {
    "iso:country":"DE",
    "sg:address":"Sachsenh\u00e4user Landwehrweg 93",
    "sg:city":"Frankfurt",
    "sg:phone":"+49 69/68608336",
    "sg:postcode":"60599",
    "sg:province":"Hessen",
    "wof:name":"Anwaltskanzlei Marwitz",
    "wof:placetype":"venue"
},
  "geometry": {"coordinates":[8.7011756897,50.0887336731],"type":"Point"}
}