{
  "type": "Feature",
  "properties": {
    "iso:country":"DE",
    "sg:address":"Louis-Krages-Str. 18",
    "sg:city":"Bremen",
    "sg:phone":"+49 421/612528",
    "sg:postcode":"28237",
    "sg:province":"Bremen",
    "wof:name":"Stier Gmbh & Co.",
    "wof:placetype":"venue"
},
  "geometry": {"coordinates":[8.7417697906,53.123840332],"type":"Point"}
}