{
  "type": "Feature",
  "properties": {
    "iso:country":"DE",
    "sg:address":"An der L\u00f6derburger Bahn 49",
    "sg:city":"Sta\u00dffurt",
    "sg:phone":"+49 3925/625897",
    "sg:postcode":"39418",
    "sg:province":"Sachsen-Anhalt",
    "wof:name":"Pension D. Riedel",
    "wof:placetype":"venue"
},
  "geometry": {"coordinates":[11.5782051086,51.8626365662],"type":"Point"}
}