{
  "type": "Feature",
  "properties": {
    "iso:country":"DE",
    "sg:address":"Donnerbrink 19",
    "sg:city":"Bielefeld",
    "sg:phone":"+49 521/109387",
    "sg:postcode":"33619",
    "sg:province":"Nordrhein-Westfalen",
    "wof:name":"R. Hoebel H. Hoebel",
    "wof:placetype":"venue"
},
  "geometry": {"coordinates":[8.4776668549,52.0334129333],"type":"Point"}
}