{
  "type": "Feature",
  "properties": {
    "iso:country":"DE",
    "sg:address":"Hartfeldstr. 49",
    "sg:city":"M\u00fchlacker",
    "sg:phone":"+49 7041/43679",
    "sg:postcode":"75417",
    "sg:province":"Baden-W\u00fcrttemberg",
    "wof:name":"C. Stefanovic",
    "wof:placetype":"venue"
},
  "geometry": {"coordinates":[8.7964477539,48.9377593994],"type":"Point"}
}