{
  "type": "Feature",
  "properties": {
    "iso:country":"DE",
    "sg:address":"Nelkenstr. 1",
    "sg:city":"Leinfelden-Echterdingen",
    "sg:phone":"+49 711/903810",
    "sg:postcode":"70771",
    "sg:province":"Baden-W\u00fcrttemberg",
    "wof:name":"Immo Concept Verm\u00f6gensverwaltung Gmbh",
    "wof:placetype":"venue"
},
  "geometry": {"coordinates":[9.1395616531,48.6938781738],"type":"Point"}
}