{
  "type": "Feature",
  "properties": {
    "iso:country":"DE",
    "sg:address":"Kampstr. 41",
    "sg:city":"Dortmund",
    "sg:phone":"+49 231/144942",
    "sg:postcode":"44137",
    "sg:province":"Nordrhein-Westfalen",
    "wof:name":"Millis Corner Dieter Borges Gmbh & Co. Kg",
    "wof:placetype":"venue"
},
  "geometry": {"coordinates":[7.4626178741,51.5152359009],"type":"Point"}
}