{
  "type": "Feature",
  "properties": {
    "iso:country":"DE",
    "sg:address":"Bormiger Weg 40",
    "sg:city":"Straelen",
    "sg:phone":"+49 2834/92048",
    "sg:postcode":"47638",
    "sg:province":"Nordrhein-Westfalen",
    "wof:name":"Walter Gellen",
    "wof:placetype":"venue"
},
  "geometry": {"coordinates":[6.256436,51.447289],"type":"Point"}
}