{
  "type": "Feature",
  "properties": {
    "iso:country":"DE",
    "sg:address":"Marktstr. 11",
    "sg:city":"V\u00f6lklingen",
    "sg:phone":"+49 6898/26689",
    "sg:postcode":"66333",
    "sg:province":"Saarland",
    "wof:name":"Bit Am Markt",
    "wof:placetype":"venue"
},
  "geometry": {"coordinates":[6.8581848145,49.2511711121],"type":"Point"}
}