{
  "type": "Feature",
  "properties": {
    "iso:country":"DE",
    "sg:address":"Steinweg 37",
    "sg:city":"L\u00f6\u00dfnitz",
    "sg:phone":"+49 3771/32012",
    "sg:postcode":"08294",
    "sg:province":"Sachsen",
    "wof:name":"Andreas Becher Fliesen Und Naturstein Handels Gmbh",
    "wof:placetype":"venue"
},
  "geometry": {"coordinates":[12.7301092148,50.6249008179],"type":"Point"}
}