{
  "type": "Feature",
  "properties": {
    "iso:country":"DE",
    "sg:address":"S\u00fcderstr. 37",
    "sg:city":"Heide",
    "sg:phone":"+49 481/64390",
    "sg:postcode":"25746",
    "sg:province":"Schleswig-Holstein",
    "wof:name":"A. Eixmann",
    "wof:placetype":"venue"
},
  "geometry": {"coordinates":[9.090388298,54.1921005249],"type":"Point"}
}