{
  "type": "Feature",
  "properties": {
    "iso:country":"DE",
    "sg:address":"Auf dem Berge 7",
    "sg:city":"Korbach",
    "sg:phone":"+49 5631/8781",
    "sg:postcode":"34497",
    "sg:province":"Hessen",
    "wof:name":"Gastst\u00e4tte W. Baumann",
    "wof:placetype":"venue"
},
  "geometry": {"coordinates":[8.8720693588,51.3219833374],"type":"Point"}
}