{
  "type": "Feature",
  "properties": {
    "iso:country":"DE",
    "sg:address":"Reideburger Landstr. 10",
    "sg:city":"Halle",
    "sg:postcode":"06116",
    "sg:province":"Sachsen-Anhalt",
    "wof:name":"Fkb Projektsteuerungs- Gmbh",
    "wof:placetype":"venue"
},
  "geometry": {"coordinates":[12.0119714737,51.4905738831],"type":"Point"}
}