{
  "type": "Feature",
  "properties": {
    "iso:country":"DE",
    "sg:address":"J\u00fctlandstr. 14",
    "sg:city":"Werne",
    "sg:postcode":"59368",
    "sg:province":"Nordrhein-Westfalen",
    "wof:name":"Wias Transporte Gmbh",
    "wof:placetype":"venue"
},
  "geometry": {"coordinates":[7.619248867,51.658821106],"type":"Point"}
}