{
  "type": "Feature",
  "properties": {
    "iso:country":"DE",
    "sg:address":"Silberbach 18",
    "sg:city":"Selb",
    "sg:phone":"+49 9287/60332",
    "sg:postcode":"95100",
    "sg:province":"Bayern",
    "wof:name":"Hollywood Cafe",
    "wof:placetype":"venue"
},
  "geometry": {"coordinates":[12.165235,50.131359],"type":"Point"}
}