{
  "type": "Feature",
  "properties": {
    "iso:country":"DE",
    "sg:address":"Weststr. 19",
    "sg:city":"Kamen",
    "sg:phone":"+49 2307/10228",
    "sg:postcode":"59174",
    "sg:province":"Nordrhein-Westfalen",
    "wof:name":"Herta Seck",
    "wof:placetype":"venue"
},
  "geometry": {"coordinates":[7.6619300842,51.5925712585],"type":"Point"}
}