{
  "type": "Feature",
  "properties": {
    "iso:country":"DE",
    "sg:address":"Eisenbahnstr. 13",
    "sg:city":"Schliengen",
    "sg:phone":"+49 7635/556",
    "sg:postcode":"79418",
    "sg:province":"Baden-W\u00fcrttemberg",
    "wof:name":"Fohmannsche Apotheke",
    "wof:placetype":"venue"
},
  "geometry": {"coordinates":[7.575616,47.755966],"type":"Point"}
}