{
  "type": "Feature",
  "properties": {
    "iso:country":"DE",
    "sg:address":"R\u00f6ntgenstr. 2",
    "sg:city":"Ehingen",
    "sg:phone":"+49 7391/71037",
    "sg:postcode":"89584",
    "sg:province":"Baden-W\u00fcrttemberg",
    "wof:name":"C. Gower-barrington Masseur",
    "wof:placetype":"venue"
},
  "geometry": {"coordinates":[9.723001,48.291794],"type":"Point"}
}