{
  "type": "Feature",
  "properties": {
    "iso:country":"DE",
    "sg:city":"Padaborn",
    "sg:postcode":"33098",
    "sg:province":"Nordrhein-Westfalen",
    "wof:name":"Beutler Steuerberatungsgesellschaft Mbh",
    "wof:placetype":"venue"
},
  "geometry": {"coordinates":[8.75151,51.712372],"type":"Point"}
}