{
  "type": "Feature",
  "properties": {
    "iso:country":"DE",
    "sg:address":"Werkstr 11",
    "sg:city":"Eisenh\u00fcttenstadt",
    "sg:phone":"+49 3364/375546",
    "sg:postcode":"15890",
    "sg:province":"Brandenburg",
    "wof:name":"Bergmann & Partner Gmbh",
    "wof:placetype":"venue"
},
  "geometry": {"coordinates":[14.6145534515,52.138759613],"type":"Point"}
}