{
  "type": "Feature",
  "properties": {
    "iso:country":"DE",
    "sg:address":"Treckinghauser Str.",
    "sg:city":"L\u00fcdenscheid",
    "sg:phone":"+49 2351/459400",
    "sg:postcode":"58515",
    "sg:province":"Nordrhein-Westfalen",
    "wof:name":"Michael Kaiser",
    "wof:placetype":"venue"
},
  "geometry": {"coordinates":[7.6868748665,51.195400238],"type":"Point"}
}