{
  "type": "Feature",
  "properties": {
    "iso:country":"DE",
    "sg:address":"Hauptstr. 63",
    "sg:city":"M\u00fclheim",
    "sg:phone":"+49 6534/200",
    "sg:postcode":"54486",
    "sg:province":"Rheinland-Pfalz",
    "wof:name":"Helmut Haag-becker",
    "wof:placetype":"venue"
},
  "geometry": {"coordinates":[7.0113039017,49.9127883911],"type":"Point"}
}