{
  "type": "Feature",
  "properties": {
    "iso:country":"DE",
    "sg:address":"K\u00f6nigstr. 64",
    "sg:city":"Duisburg",
    "sg:phone":"+49 2066/10901",
    "sg:postcode":"47198",
    "sg:province":"Nordrhein-Westfalen",
    "wof:name":"Ruffing Engineering",
    "wof:placetype":"venue"
},
  "geometry": {"coordinates":[6.7173371315,51.4519081116],"type":"Point"}
}