{
  "type": "Feature",
  "properties": {
    "iso:country":"DE",
    "sg:address":"Teichplatz 2",
    "sg:city":"Greiz",
    "sg:phone":"+49 3661/675313",
    "sg:postcode":"07973",
    "sg:province":"Th\u00fcringen",
    "wof:name":"Hermann Clau\u00df",
    "wof:placetype":"venue"
},
  "geometry": {"coordinates":[12.1977100372,50.6586380005],"type":"Point"}
}