{
  "type": "Feature",
  "properties": {
    "iso:country":"DE",
    "sg:address":"M\u00fchlenweg 1",
    "sg:city":"Bredenbek",
    "sg:phone":"+49 4334/834",
    "sg:postcode":"24796",
    "sg:province":"Schleswig-Holstein",
    "wof:name":"Reno Gesellschaft F\u00fcr Renovierung Mbh",
    "wof:placetype":"venue"
},
  "geometry": {"coordinates":[9.8776073456,54.3237380981],"type":"Point"}
}