{
  "type": "Feature",
  "properties": {
    "iso:country":"DE",
    "sg:address":"Mannheimer Str. 24",
    "sg:city":"Bad D\u00fcrkheim",
    "sg:phone":"+49 6322/935140",
    "sg:postcode":"67098",
    "sg:province":"Rheinland-Pfalz",
    "wof:name":"Stadtarchiv",
    "wof:placetype":"venue"
},
  "geometry": {"coordinates":[8.171459,49.461735],"type":"Point"}
}