{
  "type": "Feature",
  "properties": {
    "iso:country":"DE",
    "sg:address":"St\u00f6sserstr. 14",
    "sg:city":"M\u00fcnchen",
    "sg:phone":"+49 89/3142043",
    "sg:postcode":"80933",
    "sg:province":"Bayern",
    "wof:name":"Rolf Weis Masseur",
    "wof:placetype":"venue"
},
  "geometry": {"coordinates":[11.556603,48.221779],"type":"Point"}
}