{
  "type": "Feature",
  "properties": {
    "iso:country":"DE",
    "sg:address":"Wilhelmstr. 34",
    "sg:city":"Wiesbaden",
    "sg:postcode":"65183",
    "sg:province":"Hessen",
    "wof:name":"Rewi Rechenzentrum Wilhelmstrasse Gmbh",
    "wof:placetype":"venue"
},
  "geometry": {"coordinates":[8.2445659637,50.0821647644],"type":"Point"}
}