{
  "type": "Feature",
  "properties": {
    "iso:country":"DE",
    "sg:address":"Schulstr. 4",
    "sg:city":"Sandhausen",
    "sg:phone":"+49 6224/2840",
    "sg:postcode":"69207",
    "sg:province":"Baden-W\u00fcrttemberg",
    "wof:name":"Karl Schnabl",
    "wof:placetype":"venue"
},
  "geometry": {"coordinates":[8.6563863754,49.3413963318],"type":"Point"}
}