{
  "type": "Feature",
  "properties": {
    "iso:country":"DE",
    "sg:address":"Morr 1",
    "sg:city":"M\u00f6nchengladbach",
    "sg:phone":"+49 2166/31647",
    "sg:postcode":"41239",
    "sg:province":"Nordrhein-Westfalen",
    "wof:name":"Nette Ecke",
    "wof:placetype":"venue"
},
  "geometry": {"coordinates":[6.4250597954,51.1663398743],"type":"Point"}
}