{
  "type": "Feature",
  "properties": {
    "iso:country":"DE",
    "sg:address":"H\u00f6hbaum 6",
    "sg:city":"Bad Salzungen",
    "sg:postcode":"36433",
    "sg:province":"Th\u00fcringen",
    "wof:name":"Iva Gmbh",
    "wof:placetype":"venue"
},
  "geometry": {"coordinates":[10.2076778412,50.7902641296],"type":"Point"}
}