{
  "type": "Feature",
  "properties": {
    "iso:country":"DE",
    "sg:address":"Mercystra\u00dfe 24",
    "sg:city":"Freiburg",
    "sg:phone":"+49 761/709384",
    "sg:postcode":"79100",
    "sg:province":"Baden-W\u00fcrttemberg",
    "wof:name":"Augenblende",
    "wof:placetype":"venue"
},
  "geometry": {"coordinates":[7.839645,47.979843],"type":"Point"}
}