{
  "type": "Feature",
  "properties": {
    "iso:country":"DE",
    "sg:address":"Felsenstr. 10",
    "sg:city":"Sonnenb\u00fchl",
    "sg:postcode":"72820",
    "sg:province":"Baden-W\u00fcrttemberg",
    "wof:name":"Werner Schr\u00e4gle",
    "wof:placetype":"venue"
},
  "geometry": {"coordinates":[9.1934738159,48.3522186279],"type":"Point"}
}