{
  "type": "Feature",
  "properties": {
    "iso:country":"DE",
    "sg:address":"In der Trift 2",
    "sg:city":"Winterberg",
    "sg:phone":"+49 2981/7389",
    "sg:postcode":"59955",
    "sg:province":"Nordrhein-Westfalen",
    "wof:name":"Naturfreundehaus Mollseifen",
    "wof:placetype":"venue"
},
  "geometry": {"coordinates":[8.5316019058,51.1931495667],"type":"Point"}
}