{
  "type": "Feature",
  "properties": {
    "iso:country":"DE",
    "sg:address":"Georgstr. 16",
    "sg:city":"Hannover",
    "sg:phone":"+49 511/326618",
    "sg:postcode":"30159",
    "sg:province":"Niedersachsen",
    "wof:name":"Europa-apotheke Inh. Dr. Roswitha Knoll",
    "wof:placetype":"venue"
},
  "geometry": {"coordinates":[9.736557,52.374771],"type":"Point"}
}