{
  "type": "Feature",
  "properties": {
    "iso:country":"DE",
    "sg:address":"Parkweg 2",
    "sg:city":"Adendorf",
    "sg:phone":"+49 4131/188254",
    "sg:postcode":"21365",
    "sg:province":"Niedersachsen",
    "wof:name":"Manfred Laabs Ingenieur",
    "wof:placetype":"venue"
},
  "geometry": {"coordinates":[10.4330911636,53.2759208679],"type":"Point"}
}