{
  "type": "Feature",
  "properties": {
    "iso:country":"DE",
    "sg:address":"Neckarstr. 78",
    "sg:city":"Ludwigsburg",
    "sg:phone":"+49 7141/55050",
    "sg:postcode":"71640",
    "sg:province":"Baden-W\u00fcrttemberg",
    "wof:name":"Blumenhaus Fiori Inh. Doris Oehrle",
    "wof:placetype":"venue"
},
  "geometry": {"coordinates":[9.212523,48.902279],"type":"Point"}
}