{
  "type": "Feature",
  "properties": {
    "iso:country":"DE",
    "sg:address":"Kolbenm\u00fchle 3",
    "sg:city":"Gr\u00fcnberg",
    "sg:phone":"+49 6401/5313",
    "sg:postcode":"35305",
    "sg:province":"Hessen",
    "wof:name":"Volker Keetmann Architekt",
    "wof:placetype":"venue"
},
  "geometry": {"coordinates":[8.898453,50.567108],"type":"Point"}
}