{
  "type": "Feature",
  "properties": {
    "iso:country":"DE",
    "sg:address":"Grabenstr. 5",
    "sg:city":"Moers",
    "sg:phone":"+49 2841/64211",
    "sg:postcode":"47447",
    "sg:province":"Nordrhein-Westfalen",
    "wof:name":"Winfried Seifert",
    "wof:placetype":"venue"
},
  "geometry": {"coordinates":[6.593626,51.42104],"type":"Point"}
}