{
  "type": "Feature",
  "properties": {
    "iso:country":"DE",
    "sg:address":"Wellbachstr. 4",
    "sg:city":"Landau",
    "sg:phone":"+49 6341/51200",
    "sg:postcode":"76829",
    "sg:province":"Rheinland-Pfalz",
    "wof:name":"R. Schreiber",
    "wof:placetype":"venue"
},
  "geometry": {"coordinates":[8.129599,49.203854],"type":"Point"}
}