{
  "type": "Feature",
  "properties": {
    "iso:country":"DE",
    "sg:address":"Hauptstr. 26 f",
    "sg:city":"Wendorf",
    "sg:phone":"+49 38486/20546",
    "sg:postcode":"19412",
    "sg:province":"Mecklenburg-Vorpommern",
    "wof:name":"J. Bornh\u00f6ft",
    "wof:placetype":"venue"
},
  "geometry": {"coordinates":[11.7144842148,53.7358436584],"type":"Point"}
}