{
  "type": "Feature",
  "properties": {
    "iso:country":"DE",
    "sg:address":"K\u00f6ssener Str. 6b",
    "sg:city":"M\u00fcnchen",
    "sg:phone":"+49 89/7695534",
    "sg:postcode":"81373",
    "sg:province":"Bayern",
    "wof:name":"Hans-joachim Sonntag Architekt",
    "wof:placetype":"venue"
},
  "geometry": {"coordinates":[11.532048,48.117958],"type":"Point"}
}