{
  "type": "Feature",
  "properties": {
    "iso:country":"DE",
    "sg:address":"Seckbacher Landstr. 10",
    "sg:city":"Frankfurt",
    "sg:phone":"+49 69/452828",
    "sg:postcode":"60389",
    "sg:province":"Hessen",
    "wof:name":"U & S Verm\u00f6gensverwaltungs-gmbh",
    "wof:placetype":"venue"
},
  "geometry": {"coordinates":[8.710222,50.131542],"type":"Point"}
}