{
  "type": "Feature",
  "properties": {
    "iso:country":"DE",
    "sg:address":"Fockestr. 11",
    "sg:city":"Garbsen",
    "sg:phone":"+49 5131/700630",
    "sg:postcode":"30827",
    "sg:province":"Niedersachsen",
    "wof:name":"Diesing & Schulz Werbesystem Hannover Gmbh",
    "wof:placetype":"venue"
},
  "geometry": {"coordinates":[9.6147003174,52.4451637268],"type":"Point"}
}