{
  "type": "Feature",
  "properties": {
    "iso:country":"DE",
    "sg:address":"Alter Markt 3",
    "sg:city":"Viersen",
    "sg:phone":"+49 2162/42581",
    "sg:postcode":"41751",
    "sg:province":"Nordrhein-Westfalen",
    "wof:name":"Abma 3",
    "wof:placetype":"venue"
},
  "geometry": {"coordinates":[6.335100174,51.2519454956],"type":"Point"}
}