{
  "type": "Feature",
  "properties": {
    "iso:country":"DE",
    "sg:address":"Gunkelsrainstr. 8 B",
    "sg:city":"Alzenau",
    "sg:phone":"+49 6023/1830",
    "sg:postcode":"63755",
    "sg:province":"Bayern",
    "wof:name":"Wilfried Antoni",
    "wof:placetype":"venue"
},
  "geometry": {"coordinates":[9.0714044571,50.0827255249],"type":"Point"}
}