{
  "type": "Feature",
  "properties": {
    "iso:country":"DE",
    "sg:address":"Einemstr. 16",
    "sg:city":"Berlin",
    "sg:phone":"+49 30/883907677",
    "sg:postcode":"10785",
    "sg:province":"Berlin",
    "wof:name":"Laris Vermittlung Und Verwaltung",
    "wof:placetype":"venue"
},
  "geometry": {"coordinates":[13.353266716,52.502658844],"type":"Point"}
}