{
  "type": "Feature",
  "properties": {
    "iso:country":"DE",
    "sg:address":"Kottmarsdorfer Str. 33",
    "sg:city":"Obercunnersdorf",
    "sg:phone":"+49 35875/60324",
    "sg:postcode":"02708",
    "sg:province":"Sachsen",
    "wof:name":"G. Klo\u00df",
    "wof:placetype":"venue"
},
  "geometry": {"coordinates":[14.661712,51.032448],"type":"Point"}
}