{
  "type": "Feature",
  "properties": {
    "iso:country":"DE",
    "sg:address":"Am B\u00fcchel 5",
    "sg:city":"Bonn",
    "sg:phone":"+49 228/362268",
    "sg:postcode":"53173",
    "sg:province":"Nordrhein-Westfalen",
    "wof:name":"Ferdinand V\u00f6lzgen",
    "wof:placetype":"venue"
},
  "geometry": {"coordinates":[7.1658558846,50.6969490051],"type":"Point"}
}