{
  "type": "Feature",
  "properties": {
    "iso:country":"DE",
    "sg:address":"Freiheiter Str. 2",
    "sg:city":"Osterode",
    "sg:postcode":"37520",
    "sg:province":"Niedersachsen",
    "wof:name":"Eusana Beratungs- Und Vertriebsgesellschaft Im",
    "wof:placetype":"venue"
},
  "geometry": {"coordinates":[10.3089799881,51.6765785217],"type":"Point"}
}