{
  "type": "Feature",
  "properties": {
    "iso:country":"DE",
    "sg:address":"Plummendorfer Str.",
    "sg:city":"Ribnitz-Damgarten",
    "sg:postcode":"18311",
    "sg:province":"Mecklenburg-Vorpommern",
    "wof:name":"Gier Industrie- Und Stahlhandel Kg",
    "wof:placetype":"venue"
},
  "geometry": {"coordinates":[12.431385,54.24369],"type":"Point"}
}