{
  "type": "Feature",
  "properties": {
    "iso:country":"DE",
    "sg:address":"Runertstrasse 1",
    "sg:city":"Emmelshuasen",
    "sg:phone":"+49 4967/47252",
    "sg:postcode":"56281",
    "sg:province":"Rheinland-Pfalz",
    "wof:name":"Cigar Zigarre Zigarren Zigarren Zigarren",
    "wof:placetype":"venue"
},
  "geometry": {"coordinates":[7.557516098,50.1548156738],"type":"Point"}
}