{
  "type": "Feature",
  "properties": {
    "iso:country":"DE",
    "sg:address":"Friedrich-Ebert-Str 29",
    "sg:city":"Regensburg",
    "sg:phone":"+49 941/997494",
    "sg:postcode":"93051",
    "sg:province":"Bayern",
    "wof:name":"Frost Engineering Gmbh",
    "wof:placetype":"venue"
},
  "geometry": {"coordinates":[12.07016,49.008671],"type":"Point"}
}