{
  "type": "Feature",
  "properties": {
    "iso:country":"DE",
    "sg:address":"Am Drostenst\u00fcck 16+29",
    "sg:city":"L\u00fcdenscheid",
    "sg:phone":"+49 4923/5196490",
    "sg:postcode":"58507",
    "sg:province":"Nordrhein-Westfalen",
    "wof:name":"Max Schuster",
    "wof:placetype":"venue"
},
  "geometry": {"coordinates":[7.6161189079,51.2296981812],"type":"Point"}
}