{
  "type": "Feature",
  "properties": {
    "iso:country":"DE",
    "sg:address":"Schramberger Str. 9",
    "sg:city":"Lauterbach",
    "sg:phone":"+49 7422/22021",
    "sg:postcode":"78730",
    "sg:province":"Baden-W\u00fcrttemberg",
    "wof:name":"Gastst\u00e4tte Ratsstube",
    "wof:placetype":"venue"
},
  "geometry": {"coordinates":[8.3493719101,48.2273712158],"type":"Point"}
}