{
  "type": "Feature",
  "properties": {
    "iso:country":"DE",
    "sg:address":"Bahnhofstr. 7",
    "sg:city":"Pittenhart",
    "sg:phone":"+49 8624/1545",
    "sg:postcode":"83132",
    "sg:province":"Bayern",
    "wof:name":"Erna Hundsberger",
    "wof:placetype":"venue"
},
  "geometry": {"coordinates":[12.3895130157,47.9773254395],"type":"Point"}
}