{
  "type": "Feature",
  "properties": {
    "iso:country":"DE",
    "sg:address":"Berggasse 1a",
    "sg:city":"Ronneburg",
    "sg:phone":"+49 36602/37316",
    "sg:postcode":"07580",
    "sg:province":"Th\u00fcringen",
    "wof:name":"M\u00fcller",
    "wof:placetype":"venue"
},
  "geometry": {"coordinates":[12.1840028763,50.8630638123],"type":"Point"}
}