{
  "type": "Feature",
  "properties": {
    "iso:country":"DE",
    "sg:address":"Gartenfeldstr. 23",
    "sg:city":"Wadern",
    "sg:postcode":"66687",
    "sg:province":"Saarland",
    "wof:name":"Gemeinde Sch\u00fclerb\u00fccherei",
    "wof:placetype":"venue"
},
  "geometry": {"coordinates":[6.887425,49.540081],"type":"Point"}
}