{
  "type": "Feature",
  "properties": {
    "iso:country":"DE",
    "sg:address":"Im J\u00fcden 3",
    "sg:city":"Bruchsal",
    "sg:phone":"+49 7257/2316",
    "sg:postcode":"76646",
    "sg:province":"Baden-W\u00fcrttemberg",
    "wof:name":"Paul J. Mack Architekt",
    "wof:placetype":"venue"
},
  "geometry": {"coordinates":[8.554056,49.083523],"type":"Point"}
}