{
  "type": "Feature",
  "properties": {
    "iso:country":"DE",
    "sg:address":"Eichbergstr. 7",
    "sg:city":"Saarwellingen",
    "sg:phone":"+49 6838/2910",
    "sg:postcode":"66793",
    "sg:province":"Saarland",
    "wof:name":"Borrom\u00e4us-b\u00fccherei Saarwellingen",
    "wof:placetype":"venue"
},
  "geometry": {"coordinates":[6.809218,49.354164],"type":"Point"}
}