{
  "type": "Feature",
  "properties": {
    "iso:country":"DE",
    "sg:address":"Danziger Str. 1",
    "sg:city":"Dingolfing",
    "sg:phone":"+49 8731/757265",
    "sg:postcode":"84130",
    "sg:province":"Bayern",
    "wof:name":"P. Finsterwald",
    "wof:placetype":"venue"
},
  "geometry": {"coordinates":[12.495769,48.639275],"type":"Point"}
}