{
  "type": "Feature",
  "properties": {
    "iso:country":"DE",
    "sg:address":"Thomas-Mann-Str. 73",
    "sg:city":"M\u00f6nchengladbach",
    "sg:phone":"+49 2161/532160",
    "sg:postcode":"41068",
    "sg:province":"Nordrhein-Westfalen",
    "wof:name":"Gerd Hansen",
    "wof:placetype":"venue"
},
  "geometry": {"coordinates":[6.442685,51.195499],"type":"Point"}
}