{
  "type": "Feature",
  "properties": {
    "iso:country":"DE",
    "sg:address":"Frahmredder 62 A",
    "sg:city":"Hamburg",
    "sg:phone":"+49 40/6001970",
    "sg:postcode":"22393",
    "sg:province":"Hamburg",
    "wof:name":"D. Eggert Und R. Schwarz Steuerberater",
    "wof:placetype":"venue"
},
  "geometry": {"coordinates":[10.1012716293,53.6473579407],"type":"Point"}
}