{
  "type": "Feature",
  "properties": {
    "iso:country":"DE",
    "sg:address":"Graf-Seyssel-Str. 8",
    "sg:city":"Gr\u00fcnwald",
    "sg:phone":"+49 89/6492211",
    "sg:postcode":"82031",
    "sg:province":"Bayern",
    "wof:name":"M. Dienhold Immobilienmakler",
    "wof:placetype":"venue"
},
  "geometry": {"coordinates":[11.5489063263,48.0629425049],"type":"Point"}
}