{
  "type": "Feature",
  "properties": {
    "iso:country":"DE",
    "sg:address":"In den Herrnwiesen 10",
    "sg:city":"Kreuzwertheim",
    "sg:phone":"+49 9342/6507",
    "sg:postcode":"97892",
    "sg:province":"Bayern",
    "wof:name":"Edwin Rohracker",
    "wof:placetype":"venue"
},
  "geometry": {"coordinates":[9.515779,49.768608],"type":"Point"}
}