{
  "type": "Feature",
  "properties": {
    "iso:country":"DE",
    "sg:address":"Herbstwiesen\u00e4cker 2",
    "sg:city":"Lorch",
    "sg:phone":"+49 7172/7347",
    "sg:postcode":"73547",
    "sg:province":"Baden-W\u00fcrttemberg",
    "wof:name":"J. Oettle",
    "wof:placetype":"venue"
},
  "geometry": {"coordinates":[9.629023,48.782578],"type":"Point"}
}