{
  "type": "Feature",
  "properties": {
    "iso:country":"DE",
    "sg:address":"Bahnhofstr. 1",
    "sg:city":"P\u00f6\u00dfneck",
    "sg:phone":"+49 3647/422039",
    "sg:postcode":"07381",
    "sg:province":"Th\u00fcringen",
    "wof:name":"Fritz Immobilienmakler",
    "wof:placetype":"venue"
},
  "geometry": {"coordinates":[11.5903196335,50.6940879822],"type":"Point"}
}