{
  "type": "Feature",
  "properties": {
    "iso:country":"DE",
    "sg:address":"Wiechertstr. 8",
    "sg:city":"Rheinberg",
    "sg:phone":"+49 2843/860655",
    "sg:postcode":"47495",
    "sg:province":"Nordrhein-Westfalen",
    "wof:name":"Resi Pooten Heilpraktikerin",
    "wof:placetype":"venue"
},
  "geometry": {"coordinates":[6.5557961464,51.5576591492],"type":"Point"}
}