{
  "type": "Feature",
  "properties": {
    "iso:country":"DE",
    "sg:address":"Heidefeldstr. 5",
    "sg:city":"Rathenow",
    "sg:phone":"+49 3385/510140",
    "sg:postcode":"14712",
    "sg:province":"Brandenburg",
    "wof:name":"Getr\u00e4nkehimmel",
    "wof:placetype":"venue"
},
  "geometry": {"coordinates":[12.3367843628,52.5997390747],"type":"Point"}
}