{
  "type": "Feature",
  "properties": {
    "iso:country":"DE",
    "sg:address":"Dorfstr. 39",
    "sg:city":"Wredenhagen",
    "sg:phone":"+49 39925/28028",
    "sg:postcode":"17209",
    "sg:province":"Mecklenburg-Vorpommern",
    "wof:name":"J. Renneke Anlageberater",
    "wof:placetype":"venue"
},
  "geometry": {"coordinates":[12.5192203522,53.2904281616],"type":"Point"}
}