{
  "type": "Feature",
  "properties": {
    "iso:country":"DE",
    "sg:address":"Gr\u00f6benrieder Str. 76",
    "sg:city":"Dachau",
    "sg:phone":"+49 8131/72129",
    "sg:postcode":"85221",
    "sg:province":"Bayern",
    "wof:name":"Friedrich Gross",
    "wof:placetype":"venue"
},
  "geometry": {"coordinates":[11.43579,48.246284],"type":"Point"}
}