{
  "type": "Feature",
  "properties": {
    "iso:country":"DE",
    "sg:address":"Sch\u00fctzenstr. 8",
    "sg:city":"Biedenkopf",
    "sg:phone":"+49 6461/89204",
    "sg:postcode":"35216",
    "sg:province":"Hessen",
    "wof:name":"Bernd Mertin",
    "wof:placetype":"venue"
},
  "geometry": {"coordinates":[8.478049,50.929321],"type":"Point"}
}