{
  "type": "Feature",
  "properties": {
    "iso:country":"DE",
    "sg:address":"K\u00f6nigsbacher Str 2",
    "sg:city":"Ludwigshafen",
    "sg:phone":"+49 621/586180",
    "sg:postcode":"67067",
    "sg:province":"Rheinland-Pfalz",
    "wof:name":"Horst Arnold Gmbh",
    "wof:placetype":"venue"
},
  "geometry": {"coordinates":[8.40952,49.462879],"type":"Point"}
}