{
  "type": "Feature",
  "properties": {
    "iso:country":"DE",
    "sg:address":"Bieberer Str. 23",
    "sg:city":"Offenbach",
    "sg:phone":"+49 69/887761",
    "sg:postcode":"63065",
    "sg:province":"Hessen",
    "wof:name":"L Abbate",
    "wof:placetype":"venue"
},
  "geometry": {"coordinates":[8.767685,50.104275],"type":"Point"}
}