{
  "type": "Feature",
  "properties": {
    "iso:country":"DE",
    "sg:address":"Von-Bocholtz-Str. 17",
    "sg:city":"Nettetal",
    "sg:phone":"+49 2153/2391",
    "sg:postcode":"41334",
    "sg:province":"Nordrhein-Westfalen",
    "wof:name":"Vertrauens\u00e4rztlicher-dienst D. Lva Rheinprovinz",
    "wof:placetype":"venue"
},
  "geometry": {"coordinates":[6.2744488716,51.3063201904],"type":"Point"}
}