{
  "type": "Feature",
  "properties": {
    "iso:country":"DE",
    "sg:address":"B\u00fcrgermeister-Reuter-Str. 2",
    "sg:city":"Bremen",
    "sg:phone":"+49 421/4673741",
    "sg:postcode":"28327",
    "sg:province":"Bremen",
    "wof:name":"Egon Hallmann",
    "wof:placetype":"venue"
},
  "geometry": {"coordinates":[8.8954486847,53.08070755],"type":"Point"}
}