{
  "type": "Feature",
  "properties": {
    "iso:country":"DE",
    "sg:address":"Am Eisenberg 11",
    "sg:city":"M\u00fccke",
    "sg:phone":"+49 6400/950888",
    "sg:postcode":"35325",
    "sg:province":"Hessen",
    "wof:name":"W Kl\u00f6ss",
    "wof:placetype":"venue"
},
  "geometry": {"coordinates":[9.0254144669,50.6100349426],"type":"Point"}
}