{
  "type": "Feature",
  "properties": {
    "iso:country":"DE",
    "sg:address":"Carl-Wery-Str. 28::",
    "sg:city":"Muenchen",
    "sg:phone":"+49 89/62730",
    "sg:postcode":"81739",
    "sg:province":"Bayern",
    "wof:name":"Aok Bayern Die Gesundheitskasse",
    "wof:placetype":"venue"
},
  "geometry": {"coordinates":[11.644865,48.090454],"type":"Point"}
}