{
  "type": "Feature",
  "properties": {
    "iso:country":"DE",
    "sg:address":"Bachstr. 5",
    "sg:city":"Esslingen",
    "sg:phone":"+49 69/71470",
    "sg:postcode":"73730",
    "sg:province":"Baden-W\u00fcrttemberg",
    "wof:name":"Deka Investment Management Gmbh",
    "wof:placetype":"venue"
},
  "geometry": {"coordinates":[8.6843,50.112251],"type":"Point"}
}