{
  "type": "Feature",
  "properties": {
    "iso:country":"DE",
    "sg:address":"Kirchenweg 3",
    "sg:city":"Westerland",
    "sg:phone":"+49 4651/24021",
    "sg:postcode":"25980",
    "sg:province":"Schleswig-Holstein",
    "wof:name":"Hansen Und Schlums Architekten",
    "wof:placetype":"venue"
},
  "geometry": {"coordinates":[8.309183,54.908146],"type":"Point"}
}