{
  "type": "Feature",
  "properties": {
    "iso:country":"DE",
    "sg:address":"Zum Jadebusen 141",
    "sg:city":"Varel",
    "sg:phone":"+49 4451/82350",
    "sg:postcode":"26316",
    "sg:province":"Niedersachsen",
    "wof:name":"Jugendgruppe Des Jade-yacht- Clubs Varel-dangast",
    "wof:placetype":"venue"
},
  "geometry": {"coordinates":[8.1076402664,53.4205703735],"type":"Point"}
}