{
  "type": "Feature",
  "properties": {
    "iso:country":"DE",
    "sg:address":"Hauptstr. 60",
    "sg:city":"Bilshausen",
    "sg:phone":"+49 5528/98044",
    "sg:postcode":"37434",
    "sg:province":"Niedersachsen",
    "wof:name":"Heiko Meckel Masseur",
    "wof:placetype":"venue"
},
  "geometry": {"coordinates":[10.159589,51.628124],"type":"Point"}
}