{
  "type": "Feature",
  "properties": {
    "iso:country":"DE",
    "sg:address":"\u00dcber den H\u00f6fen 30",
    "sg:city":"Hessisch Oldendorf",
    "sg:phone":"+49 5152/98367",
    "sg:postcode":"31840",
    "sg:province":"Niedersachsen",
    "wof:name":"Franz Kinzel",
    "wof:placetype":"venue"
},
  "geometry": {"coordinates":[9.327219,52.175636],"type":"Point"}
}