{
  "type": "Feature",
  "properties": {
    "iso:country":"DE",
    "sg:address":"Wackersteinstr. 28",
    "sg:city":"Pfullingen",
    "sg:phone":"+49 7121/97980",
    "sg:postcode":"72793",
    "sg:province":"Baden-W\u00fcrttemberg",
    "wof:name":"D\u00f6ttinger Spezial- Beschichtungen Gmbh",
    "wof:placetype":"venue"
},
  "geometry": {"coordinates":[9.2179393768,48.4492111206],"type":"Point"}
}