{
  "type": "Feature",
  "properties": {
    "iso:country":"DE",
    "sg:address":"Waaggasse 1",
    "sg:city":"Rosengarten",
    "sg:phone":"+49 791/52635",
    "sg:postcode":"74538",
    "sg:province":"Baden-W\u00fcrttemberg",
    "wof:name":"Alfred Kurz",
    "wof:placetype":"venue"
},
  "geometry": {"coordinates":[9.7354545593,49.0892524719],"type":"Point"}
}