{
  "type": "Feature",
  "properties": {
    "iso:country":"DE",
    "sg:address":"Emdener Str 105a",
    "sg:city":"K\u00f6ln",
    "sg:phone":"+49 221/715250",
    "sg:postcode":"50735",
    "sg:province":"Nordrhein-Westfalen",
    "wof:name":"Willi Sch\u00fcchen Internationale Spedition Transport Logistik Gmbh & Co Kg",
    "wof:placetype":"venue"
},
  "geometry": {"coordinates":[6.9548430443,51.0047187805],"type":"Point"}
}