{
  "type": "Feature",
  "properties": {
    "iso:country":"DE",
    "sg:address":"Schlesierstr. 3",
    "sg:city":"Wertingen",
    "sg:postcode":"86637",
    "sg:province":"Bayern",
    "wof:name":"Venterra Gmbh",
    "wof:placetype":"venue"
},
  "geometry": {"coordinates":[10.673333,48.556953],"type":"Point"}
}