{
  "type": "Feature",
  "properties": {
    "iso:country":"DE",
    "sg:address":"Frienstedter Str. 18",
    "sg:city":"Gottstedt",
    "sg:phone":"+49 36208/71884",
    "sg:postcode":"99192",
    "sg:province":"Th\u00fcringen",
    "wof:name":"Knuth Kuntze",
    "wof:placetype":"venue"
},
  "geometry": {"coordinates":[10.9137039185,50.9699172974],"type":"Point"}
}