{
  "type": "Feature",
  "properties": {
    "iso:country":"DE",
    "sg:address":"Carl-Hahn-Str. 9",
    "sg:city":"Ingolstadt",
    "sg:phone":"+49 841/96228",
    "sg:postcode":"85053",
    "sg:province":"Bayern",
    "wof:name":"Wenzl Und Wenzl Steuerberater",
    "wof:placetype":"venue"
},
  "geometry": {"coordinates":[11.4785547256,48.747959137],"type":"Point"}
}