{
  "type": "Feature",
  "properties": {
    "iso:country":"DE",
    "sg:address":"Hoffeldstr. 2",
    "sg:city":"Ludwigsburg",
    "sg:phone":"+49 7141/929764",
    "sg:postcode":"71636",
    "sg:province":"Baden-W\u00fcrttemberg",
    "wof:name":"R. Schebesta",
    "wof:placetype":"venue"
},
  "geometry": {"coordinates":[9.161885,48.886555],"type":"Point"}
}