{
  "type": "Feature",
  "properties": {
    "iso:country":"DE",
    "sg:address":"Grabenstr. 7",
    "sg:city":"Baden-Baden",
    "sg:phone":"+49 7223/52115",
    "sg:postcode":"76534",
    "sg:province":"Baden-W\u00fcrttemberg",
    "wof:name":"Hildegard Nickweiler",
    "wof:placetype":"venue"
},
  "geometry": {"coordinates":[8.159932,48.729439],"type":"Point"}
}