{
  "type": "Feature",
  "properties": {
    "iso:country":"DE",
    "sg:address":"Kirchgasse 3",
    "sg:city":"B\u00fcrgel",
    "sg:phone":"+49 36692/22575",
    "sg:postcode":"07616",
    "sg:province":"Th\u00fcringen",
    "wof:name":"Birgit Auerswald",
    "wof:placetype":"venue"
},
  "geometry": {"coordinates":[11.7556838989,50.9422950745],"type":"Point"}
}