{
  "type": "Feature",
  "properties": {
    "iso:country":"DE",
    "sg:address":"Jahnstr. 1",
    "sg:city":"Klettgau",
    "sg:phone":"+49 7742/7066",
    "sg:postcode":"79771",
    "sg:province":"Baden-W\u00fcrttemberg",
    "wof:name":"Max Schweizer",
    "wof:placetype":"venue"
},
  "geometry": {"coordinates":[8.409703,47.626343],"type":"Point"}
}