{
  "type": "Feature",
  "properties": {
    "iso:country":"DE",
    "sg:address":"Lemgoer Str. 23",
    "sg:city":"Detmold",
    "sg:phone":"+49 5231/28066",
    "sg:postcode":"32756",
    "sg:province":"Nordrhein-Westfalen",
    "wof:name":"Taxi Funkzentrale Deta Detmold",
    "wof:placetype":"venue"
},
  "geometry": {"coordinates":[8.8791503906,51.9446907043],"type":"Point"}
}