{
  "type": "Feature",
  "properties": {
    "iso:country":"DE",
    "sg:address":"Argonnenstr. 15",
    "sg:city":"Weingarten",
    "sg:phone":"+49 751/42059",
    "sg:postcode":"88250",
    "sg:province":"Baden-W\u00fcrttemberg",
    "wof:name":"Anna Mayer Brennstoffhandel",
    "wof:placetype":"venue"
},
  "geometry": {"coordinates":[9.63628,47.814247],"type":"Point"}
}