{
  "type": "Feature",
  "properties": {
    "iso:country":"DE",
    "sg:address":"Harsleber Torstr. 15",
    "sg:city":"Helmstedt",
    "sg:phone":"+49 5351/180",
    "sg:postcode":"38350",
    "sg:province":"Niedersachsen",
    "wof:name":"Wohnungsbaugesellschaft Nieders\u00e4chsischer Braun-",
    "wof:placetype":"venue"
},
  "geometry": {"coordinates":[11.0046243668,52.2276802063],"type":"Point"}
}