{
  "type": "Feature",
  "properties": {
    "iso:country":"DE",
    "sg:address":"Dammtorstr. 35",
    "sg:city":"Hamburg",
    "sg:phone":"+49 40/353451",
    "sg:postcode":"20354",
    "sg:province":"Hamburg",
    "wof:name":"Eurohypo Ag",
    "wof:placetype":"venue"
},
  "geometry": {"coordinates":[9.9879570007,53.5557403564],"type":"Point"}
}