{
  "type": "Feature",
  "properties": {
    "iso:country":"DE",
    "sg:address":"Friesische Str. 8",
    "sg:city":"Flensburg",
    "sg:phone":"+49 461/25919",
    "sg:postcode":"24937",
    "sg:province":"Schleswig-Holstein",
    "wof:name":"W\u00fcstenrot",
    "wof:placetype":"venue"
},
  "geometry": {"coordinates":[9.43499,54.782566],"type":"Point"}
}