{
  "type": "Feature",
  "properties": {
    "iso:country":"DE",
    "sg:address":"Wirther Feldweg 33",
    "sg:city":"Borken",
    "sg:phone":"+49 2862/1481",
    "sg:postcode":"46325",
    "sg:province":"Nordrhein-Westfalen",
    "wof:name":"Josef Meyer",
    "wof:placetype":"venue"
},
  "geometry": {"coordinates":[6.779409,51.881172],"type":"Point"}
}