{
  "type": "Feature",
  "properties": {
    "iso:country":"DE",
    "sg:address":"Heinrich-Hofmann-Str. 26",
    "sg:city":"Hasselroth",
    "sg:phone":"+49 6055/3486",
    "sg:postcode":"63594",
    "sg:province":"Hessen",
    "wof:name":"Gs-leasing Gmbh",
    "wof:placetype":"venue"
},
  "geometry": {"coordinates":[9.1156,50.179134],"type":"Point"}
}