{
  "type": "Feature",
  "properties": {
    "iso:country":"DE",
    "sg:address":"Benzstr. 7",
    "sg:city":"Miltenberg",
    "sg:phone":"+49 9371/2765",
    "sg:postcode":"63897",
    "sg:province":"Bayern",
    "wof:name":"Heimberger Metallbau Gmbh",
    "wof:placetype":"venue"
},
  "geometry": {"coordinates":[9.246674,49.709801],"type":"Point"}
}