{
  "type": "Feature",
  "properties": {
    "iso:country":"DE",
    "sg:address":"Breite Str. 19",
    "sg:city":"Grevenbroich",
    "sg:phone":"+49 2181/61731",
    "sg:postcode":"41515",
    "sg:province":"Nordrhein-Westfalen",
    "wof:name":"Pizzeria Quattro Mori",
    "wof:placetype":"venue"
},
  "geometry": {"coordinates":[6.5886998177,51.0889968872],"type":"Point"}
}