{
  "type": "Feature",
  "properties": {
    "iso:country":"DE",
    "sg:address":"Panoramastr. 33",
    "sg:city":"Wendlingen",
    "sg:phone":"+49 7024/53708",
    "sg:postcode":"73240",
    "sg:province":"Baden-W\u00fcrttemberg",
    "wof:name":"Bernhard Weber Bauunternehmen",
    "wof:placetype":"venue"
},
  "geometry": {"coordinates":[9.384759903,48.6772422791],"type":"Point"}
}