{
  "type": "Feature",
  "properties": {
    "iso:country":"DE",
    "sg:address":"Hochstr. 178",
    "sg:city":"Duisburg",
    "sg:phone":"+49 2065/61085",
    "sg:postcode":"47228",
    "sg:province":"Nordrhein-Westfalen",
    "wof:name":"Hermanns Pr\u00e4zisons-werkzg. Handels-gmbh",
    "wof:placetype":"venue"
},
  "geometry": {"coordinates":[6.6895008087,51.4204444885],"type":"Point"}
}