{
  "type": "Feature",
  "properties": {
    "iso:country":"DE",
    "sg:address":"Luitpoldstr. 13",
    "sg:city":"Kulmbach",
    "sg:postcode":"95326",
    "sg:province":"Bayern",
    "wof:name":"U. Heinemann Architekt",
    "wof:placetype":"venue"
},
  "geometry": {"coordinates":[11.444154,50.101398],"type":"Point"}
}