{
  "type": "Feature",
  "properties": {
    "iso:country":"DE",
    "sg:address":"Schuhstr. 52",
    "sg:city":"Celle",
    "sg:phone":"+49 5141/24683",
    "sg:postcode":"29221",
    "sg:province":"Niedersachsen",
    "wof:name":"Cafe Am Markt",
    "wof:placetype":"venue"
},
  "geometry": {"coordinates":[10.082005,52.62524],"type":"Point"}
}