{
  "type": "Feature",
  "properties": {
    "iso:country":"DE",
    "sg:address":"Hartenthal 2",
    "sg:city":"Bad W\u00f6rishofen",
    "sg:phone":"+49 8247/39000",
    "sg:postcode":"86825",
    "sg:province":"Bayern",
    "wof:name":"Hotel-restaurant Hartenthaler Hof",
    "wof:placetype":"venue"
},
  "geometry": {"coordinates":[10.5596866608,47.9809989929],"type":"Point"}
}