{
  "type": "Feature",
  "properties": {
    "iso:country":"DE",
    "sg:address":"Friedensstr. 14",
    "sg:city":"Hohenm\u00f6lsen",
    "sg:phone":"+49 34441/33025",
    "sg:postcode":"06679",
    "sg:province":"Sachsen-Anhalt",
    "wof:name":"A. M\u00fcller",
    "wof:placetype":"venue"
},
  "geometry": {"coordinates":[12.0993537903,51.1586036682],"type":"Point"}
}