{
  "type": "Feature",
  "properties": {
    "iso:country":"DE",
    "sg:address":"Fritz-Thiele-Str. 7-9",
    "sg:city":"Bremen",
    "sg:postcode":"28279",
    "sg:province":"Bremen",
    "wof:name":"Mc Foto Handels Gmbh",
    "wof:placetype":"venue"
},
  "geometry": {"coordinates":[8.8433685303,53.0486755371],"type":"Point"}
}