{
  "type": "Feature",
  "properties": {
    "iso:country":"DE",
    "sg:address":"Hauptstr. 69",
    "sg:city":"Reilingen",
    "sg:phone":"+49 6205/4823",
    "sg:postcode":"68799",
    "sg:province":"Baden-W\u00fcrttemberg",
    "wof:name":"Glockenst\u00fcble",
    "wof:placetype":"venue"
},
  "geometry": {"coordinates":[8.5725908279,49.2941665649],"type":"Point"}
}