{
  "type": "Feature",
  "properties": {
    "iso:country":"DE",
    "sg:address":"Rigaer Str. 15",
    "sg:city":"Berlin",
    "sg:phone":"+49 30/42780092",
    "sg:postcode":"10247",
    "sg:province":"Berlin",
    "wof:name":"R. Schneider",
    "wof:placetype":"venue"
},
  "geometry": {"coordinates":[13.4579353333,52.5175247192],"type":"Point"}
}