{
  "type": "Feature",
  "properties": {
    "iso:country":"DE",
    "sg:address":"Feldstr. 22",
    "sg:city":"Boostedt",
    "sg:postcode":"24598",
    "sg:province":"Schleswig-Holstein",
    "wof:name":"River Line",
    "wof:placetype":"venue"
},
  "geometry": {"coordinates":[10.018588,54.012131],"type":"Point"}
}