{
  "type": "Feature",
  "properties": {
    "iso:country":"DE",
    "sg:address":"Katzenbacher Str. 108",
    "sg:city":"Kirchen",
    "sg:phone":"+49 2741/930206",
    "sg:postcode":"57548",
    "sg:province":"Rheinland-Pfalz",
    "wof:name":"Hebel Shop",
    "wof:placetype":"venue"
},
  "geometry": {"coordinates":[7.8980798721,50.8111610413],"type":"Point"}
}