{
  "type": "Feature",
  "properties": {
    "iso:country":"DE",
    "sg:address":"Kronshagener Weg 128 a",
    "sg:city":"Kiel",
    "sg:phone":"+49 431/1496216",
    "sg:postcode":"24116",
    "sg:province":"Schleswig-Holstein",
    "wof:name":"Deutsches Rotes Kreuz Anschar-schwesternschaft",
    "wof:placetype":"venue"
},
  "geometry": {"coordinates":[10.101466,54.328445],"type":"Point"}
}