{
  "type": "Feature",
  "properties": {
    "iso:country":"DE",
    "sg:address":"Fliederweg 8",
    "sg:city":"Visselh\u00f6vede",
    "sg:phone":"+49 4262/4171",
    "sg:postcode":"27374",
    "sg:province":"Niedersachsen",
    "wof:name":"Heinz-otto Sch\u00fcler Steuerberater",
    "wof:placetype":"venue"
},
  "geometry": {"coordinates":[9.5709781647,52.9777412415],"type":"Point"}
}