{
  "type": "Feature",
  "properties": {
    "iso:country":"DE",
    "sg:address":"Bergstr. 23",
    "sg:city":"Alfeld",
    "sg:phone":"+49 5181/3460",
    "sg:postcode":"31061",
    "sg:province":"Niedersachsen",
    "wof:name":"Hans-joachim Vogt",
    "wof:placetype":"venue"
},
  "geometry": {"coordinates":[9.8367958069,51.9882926941],"type":"Point"}
}