{
  "type": "Feature",
  "properties": {
    "iso:country":"DE",
    "sg:address":"Dalbker Str. 138",
    "sg:city":"Oerlinghausen",
    "sg:phone":"+49 5205/75110",
    "sg:postcode":"33813",
    "sg:province":"Nordrhein-Westfalen",
    "wof:name":"Dve Ges. F\u00fcr Display Und Verpackungsentwicklung Mbh",
    "wof:placetype":"venue"
},
  "geometry": {"coordinates":[8.6131505966,51.9302139282],"type":"Point"}
}