{
  "type": "Feature",
  "properties": {
    "iso:country":"DE",
    "sg:address":"Dolberger Str. 84",
    "sg:city":"Lippetal",
    "sg:phone":"+49 2388/2266",
    "sg:postcode":"59510",
    "sg:province":"Nordrhein-Westfalen",
    "wof:name":"Total Fina Elf Mineral\u00f6l Und Chemie Gmbh",
    "wof:placetype":"venue"
},
  "geometry": {"coordinates":[7.969397068,51.694568634],"type":"Point"}
}