{
  "type": "Feature",
  "properties": {
    "iso:country":"DE",
    "sg:city":"Bernburg",
    "sg:phone":"+49 3471/27184",
    "sg:postcode":"06406",
    "sg:province":"Sachsen-Anhalt",
    "wof:name":"Blume 2000 Gmbh",
    "wof:placetype":"venue"
},
  "geometry": {"coordinates":[11.738054,51.79343],"type":"Point"}
}