{
  "type": "Feature",
  "properties": {
    "iso:country":"DE",
    "sg:address":"Me\u00dftor 7",
    "sg:city":"Neustadt",
    "sg:phone":"+49 5036/1412",
    "sg:postcode":"31535",
    "sg:province":"Niedersachsen",
    "wof:name":"Wilhelm Kruse",
    "wof:placetype":"venue"
},
  "geometry": {"coordinates":[9.334156,52.532524],"type":"Point"}
}