{
  "type": "Feature",
  "properties": {
    "iso:country":"DE",
    "sg:address":"Freiherr-vom-Stein-Str. 2",
    "sg:city":"Baumholder",
    "sg:phone":"+49 6783/4688",
    "sg:postcode":"55774",
    "sg:province":"Rheinland-Pfalz",
    "wof:name":"Eurospar",
    "wof:placetype":"venue"
},
  "geometry": {"coordinates":[7.3412599564,49.6149253845],"type":"Point"}
}