{
  "type": "Feature",
  "properties": {
    "iso:country":"DE",
    "sg:address":"Edmund-Weber-Str. 165",
    "sg:city":"Herne",
    "sg:phone":"+49 2325/93590",
    "sg:postcode":"44651",
    "sg:province":"Nordrhein-Westfalen",
    "wof:name":"Amvz Arbeitsmedizinisches Vorsorgezentrum Gmbh",
    "wof:placetype":"venue"
},
  "geometry": {"coordinates":[7.162449,51.512016],"type":"Point"}
}