{
  "type": "Feature",
  "properties": {
    "iso:country":"DE",
    "sg:address":"Franzh\u00e4uschenstr. 8",
    "sg:city":"Lohmar",
    "sg:phone":"+49 2241/383466",
    "sg:postcode":"53797",
    "sg:province":"Nordrhein-Westfalen",
    "wof:name":"Altmiks Sanit\u00e4r- Und Heizungsbau Gmbh",
    "wof:placetype":"venue"
},
  "geometry": {"coordinates":[7.265217,50.826656],"type":"Point"}
}