{
  "type": "Feature",
  "properties": {
    "iso:country":"DE",
    "sg:address":"Bahnhofstra\u00dfe 175",
    "sg:city":"Ratingen",
    "sg:postcode":"40883",
    "sg:province":"Nordrhein-Westfalen",
    "wof:name":"Jugendkantorei H\u00f6sel",
    "wof:placetype":"venue"
},
  "geometry": {"coordinates":[6.9092612267,51.3304138184],"type":"Point"}
}