{
  "type": "Feature",
  "properties": {
    "iso:country":"DE",
    "sg:address":"Kohlwaldweg 3",
    "sg:city":"Oberrot",
    "sg:phone":"+49 7977/89029",
    "sg:postcode":"74420",
    "sg:province":"Baden-W\u00fcrttemberg",
    "wof:name":"Marianne Munz Heilpraktikerin",
    "wof:placetype":"venue"
},
  "geometry": {"coordinates":[9.6789321899,49.0275039673],"type":"Point"}
}