{
  "type": "Feature",
  "properties": {
    "iso:country":"DE",
    "sg:address":"D\u00fcsseldorfer Str. 139",
    "sg:city":"Leverkusen",
    "sg:phone":"+49 2171/1773",
    "sg:postcode":"51379",
    "sg:province":"Nordrhein-Westfalen",
    "wof:name":"H. Gerlach",
    "wof:placetype":"venue"
},
  "geometry": {"coordinates":[6.9952349663,51.0732841492],"type":"Point"}
}