{
  "type": "Feature",
  "properties": {
    "iso:country":"DE",
    "sg:address":"Markt 14-16",
    "sg:city":"Celle",
    "sg:phone":"+49 5141/12224",
    "sg:postcode":"29221",
    "sg:province":"Niedersachsen",
    "wof:name":"Stadthauptamt Der Stadt Celle",
    "wof:placetype":"venue"
},
  "geometry": {"coordinates":[10.081518,52.624203],"type":"Point"}
}