{
  "type": "Feature",
  "properties": {
    "iso:country":"DE",
    "sg:address":"Hauptstr. 68",
    "sg:city":"Fischbach",
    "sg:phone":"+49 6784/1788",
    "sg:postcode":"55743",
    "sg:province":"Rheinland-Pfalz",
    "wof:name":"Liesel Gepert",
    "wof:placetype":"venue"
},
  "geometry": {"coordinates":[7.395108223,49.7428092957],"type":"Point"}
}