{
  "type": "Feature",
  "properties": {
    "iso:country":"DE",
    "sg:address":"Lauenb\u00fchlstr. 74",
    "sg:city":"Lindenberg",
    "sg:phone":"+49 8381/81191",
    "sg:postcode":"88161",
    "sg:province":"Bayern",
    "wof:name":"Kapelle",
    "wof:placetype":"venue"
},
  "geometry": {"coordinates":[9.8980531693,47.6042671204],"type":"Point"}
}