{
  "type": "Feature",
  "properties": {
    "iso:country":"DE",
    "sg:address":"Industriestr. 3",
    "sg:city":"L\u00fcbbecke",
    "sg:phone":"+49 5741/3310",
    "sg:postcode":"32312",
    "sg:province":"Nordrhein-Westfalen",
    "wof:name":"Ima Vertriebsbeteiligungs Gmbh",
    "wof:placetype":"venue"
},
  "geometry": {"coordinates":[8.614344,52.326115],"type":"Point"}
}