{
  "type": "Feature",
  "properties": {
    "iso:country":"DE",
    "sg:address":"Lessingstr. 27",
    "sg:city":"Schwerin",
    "sg:phone":"+49 385/710393",
    "sg:postcode":"19059",
    "sg:province":"Mecklenburg-Vorpommern",
    "wof:name":"Joachim Lehmann",
    "wof:placetype":"venue"
},
  "geometry": {"coordinates":[11.3901443481,53.6344909668],"type":"Point"}
}