{
  "type": "Feature",
  "properties": {
    "iso:country":"DE",
    "sg:address":"Alte Landstr. 18 a",
    "sg:city":"Lindlar",
    "sg:phone":"+49 2266/2542",
    "sg:postcode":"51789",
    "sg:province":"Nordrhein-Westfalen",
    "wof:name":"B. J. Bechara Textilhandels-gmbh",
    "wof:placetype":"venue"
},
  "geometry": {"coordinates":[7.439366,51.0546],"type":"Point"}
}