{
  "type": "Feature",
  "properties": {
    "iso:country":"DE",
    "sg:address":"Gerwischer Str. 4",
    "sg:city":"Biederitz",
    "sg:phone":"+49 4939/2922036",
    "sg:postcode":"39175",
    "sg:province":"Sachsen-Anhalt",
    "wof:name":"Norex Gmbh",
    "wof:placetype":"venue"
},
  "geometry": {"coordinates":[11.7228908539,52.1601028442],"type":"Point"}
}