{
  "type": "Feature",
  "properties": {
    "iso:country":"DE",
    "sg:address":"B\u00e4ckergasse 4",
    "sg:city":"Viechtach",
    "sg:phone":"+49 9942/1366",
    "sg:postcode":"94234",
    "sg:province":"Bayern",
    "wof:name":"Anton Ebner",
    "wof:placetype":"venue"
},
  "geometry": {"coordinates":[12.8864746094,49.0808105469],"type":"Point"}
}