{
  "type": "Feature",
  "properties": {
    "iso:country":"DE",
    "sg:address":"Bachgasse 65",
    "sg:city":"Hemsbach",
    "sg:phone":"+49 6201/45643",
    "sg:postcode":"69502",
    "sg:province":"Baden-W\u00fcrttemberg",
    "wof:name":"Bock",
    "wof:placetype":"venue"
},
  "geometry": {"coordinates":[8.6527662277,49.5901794434],"type":"Point"}
}