{
  "type": "Feature",
  "properties": {
    "iso:country":"DE",
    "sg:address":"Urdenbacher Dorfstr. 46",
    "sg:city":"D\u00fcsseldorf",
    "sg:postcode":"40593",
    "sg:province":"Nordrhein-Westfalen",
    "wof:name":"Lotsen Transporte Jagemann Kg",
    "wof:placetype":"venue"
},
  "geometry": {"coordinates":[6.8656358719,51.1472740173],"type":"Point"}
}