{
  "type": "Feature",
  "properties": {
    "iso:country":"DE",
    "sg:address":"Erdinger Str. 11",
    "sg:city":"Aschheim",
    "sg:phone":"+49 89/90539766",
    "sg:postcode":"85609",
    "sg:province":"Bayern",
    "wof:name":"Renner Versicherungsb\u00fcro Inh. H. Wetzel",
    "wof:placetype":"venue"
},
  "geometry": {"coordinates":[11.7190551758,48.1715545654],"type":"Point"}
}