{
  "type": "Feature",
  "properties": {
    "iso:country":"DE",
    "sg:address":"Max-Obermayer-Str. 8",
    "sg:city":"Gmund",
    "sg:phone":"+49 8022/96930",
    "sg:postcode":"83703",
    "sg:province":"Bayern",
    "wof:name":"Tegernseer Leasing- Und Handelsgesellschaft Mbh",
    "wof:placetype":"venue"
},
  "geometry": {"coordinates":[11.7387,47.750214],"type":"Point"}
}