{
  "type": "Feature",
  "properties": {
    "iso:country":"DE",
    "sg:address":"Hirschenstr. 31",
    "sg:city":"F\u00fcrth",
    "sg:phone":"+49 911/774056",
    "sg:postcode":"90762",
    "sg:province":"Bayern",
    "wof:name":"Vatan",
    "wof:placetype":"venue"
},
  "geometry": {"coordinates":[10.987203598,49.4744224548],"type":"Point"}
}