{
  "type": "Feature",
  "properties": {
    "iso:country":"DE",
    "sg:address":"Schulstra\u00dfe 6a",
    "sg:city":"Neubulach",
    "sg:phone":"+49 7053",
    "sg:postcode":"75387",
    "sg:province":"Baden-W\u00fcrttemberg",
    "wof:name":"Pagion - Full Mediaservice",
    "wof:placetype":"venue"
},
  "geometry": {"coordinates":[8.679642,48.653419],"type":"Point"}
}