{
  "type": "Feature",
  "properties": {
    "iso:country":"DE",
    "sg:address":"Eberst\u00e4dter Str. 38",
    "sg:city":"Pfungstadt",
    "sg:phone":"+49 6157/949924",
    "sg:postcode":"64319",
    "sg:province":"Hessen",
    "wof:name":"Volksf\u00fcrsorge Pfungstadt",
    "wof:placetype":"venue"
},
  "geometry": {"coordinates":[8.5995931625,49.8041725159],"type":"Point"}
}