{
  "type": "Feature",
  "properties": {
    "iso:country":"DE",
    "sg:address":"Geroldseckstr. 20",
    "sg:city":"M\u00fcnchen",
    "sg:phone":"+49 89/712852",
    "sg:postcode":"81375",
    "sg:province":"Bayern",
    "wof:name":"Walter Umlauf Kameramann",
    "wof:placetype":"venue"
},
  "geometry": {"coordinates":[11.4912004471,48.1161117554],"type":"Point"}
}