{
  "type": "Feature",
  "properties": {
    "iso:country":"DE",
    "sg:address":"Walther-Hensel-Str. 52",
    "sg:city":"D\u00fcsseldorf",
    "sg:postcode":"40547",
    "sg:province":"Nordrhein-Westfalen",
    "wof:name":"Fotomax Gmbh & Co. Kg",
    "wof:placetype":"venue"
},
  "geometry": {"coordinates":[6.7319688797,51.2420425415],"type":"Point"}
}