{
  "type": "Feature",
  "properties": {
    "iso:country":"DE",
    "sg:address":"Einbecker Str. 23",
    "sg:city":"Holzminden",
    "sg:phone":"+49 5531/3071",
    "sg:postcode":"37603",
    "sg:province":"Niedersachsen",
    "wof:name":"Hansj\u00f6rg Osenberg Rechtsanwalt",
    "wof:placetype":"venue"
},
  "geometry": {"coordinates":[9.4865512848,51.8261795044],"type":"Point"}
}