{
  "type": "Feature",
  "properties": {
    "iso:country":"DE",
    "sg:address":"Sachsenh\u00e4user Str. 31",
    "sg:city":"Babenhausen",
    "sg:phone":"+49 6073/2197",
    "sg:postcode":"64832",
    "sg:province":"Hessen",
    "wof:name":"Arthur Held",
    "wof:placetype":"venue"
},
  "geometry": {"coordinates":[8.9315156937,49.9469528198],"type":"Point"}
}