{
  "type": "Feature",
  "properties": {
    "iso:country":"DE",
    "sg:address":"Friedrichstr. 22",
    "sg:city":"Mei\u00dfenheim",
    "sg:phone":"+49 7824/64970",
    "sg:postcode":"77974",
    "sg:province":"Baden-W\u00fcrttemberg",
    "wof:name":"Sozialstation Ried E. V.",
    "wof:placetype":"venue"
},
  "geometry": {"coordinates":[7.773465,48.411415],"type":"Point"}
}