{
  "type": "Feature",
  "properties": {
    "iso:country":"DE",
    "sg:address":"Am Stadtgarten 52",
    "sg:city":"Castrop-Rauxel",
    "sg:phone":"+49 2305/24635",
    "sg:postcode":"44575",
    "sg:province":"Nordrhein-Westfalen",
    "wof:name":"Magdalene Adler-sprenger",
    "wof:placetype":"venue"
},
  "geometry": {"coordinates":[7.312775135,51.5417518616],"type":"Point"}
}