{
  "type": "Feature",
  "properties": {
    "iso:country":"DE",
    "sg:address":"Ernst-Mittelbach-Ring 37",
    "sg:city":"Hamburg",
    "sg:phone":"+49 40/5511061",
    "sg:postcode":"22455",
    "sg:province":"Hamburg",
    "wof:name":"Norddeutsche Hypotheken-, Und Wechselbank Ag",
    "wof:placetype":"venue"
},
  "geometry": {"coordinates":[9.946912,53.643162],"type":"Point"}
}