{
  "type": "Feature",
  "properties": {
    "iso:country":"DE",
    "sg:address":"Rhein-Mosel-Str. 24",
    "sg:city":"Laudert",
    "sg:phone":"+49 6746/330",
    "sg:postcode":"56291",
    "sg:province":"Rheinland-Pfalz",
    "wof:name":"Frieda Breuer",
    "wof:placetype":"venue"
},
  "geometry": {"coordinates":[7.6019868851,50.0771179199],"type":"Point"}
}