{
  "type": "Feature",
  "properties": {
    "iso:country":"DE",
    "sg:address":"Hauptstr. 29",
    "sg:city":"Schnaittenbach",
    "sg:postcode":"92253",
    "sg:province":"Bayern",
    "wof:name":"Carinthia Gmbh",
    "wof:placetype":"venue"
},
  "geometry": {"coordinates":[12.0024633408,49.5480422974],"type":"Point"}
}