{
  "type": "Feature",
  "properties": {
    "iso:country":"DE",
    "sg:address":"Sweder-Hopp-Stra\u00dfe 37",
    "sg:city":"Emmerich",
    "sg:phone":"+49 2822/981792",
    "sg:postcode":"46446",
    "sg:province":"Nordrhein-Westfalen",
    "wof:name":"Issmich - Rezepte Zum Nachkochen Und Sammeln",
    "wof:placetype":"venue"
},
  "geometry": {"coordinates":[6.256089,51.844952],"type":"Point"}
}