{
  "type": "Feature",
  "properties": {
    "iso:country":"DE",
    "sg:address":"Am R\u00f6merlager 1",
    "sg:city":"Bergkamen",
    "sg:phone":"+49 2389/951730",
    "sg:postcode":"59192",
    "sg:province":"Nordrhein-Westfalen",
    "wof:name":"Ferienwelt Reiseb\u00fcro Gmbh",
    "wof:placetype":"venue"
},
  "geometry": {"coordinates":[7.6764249802,51.6511917114],"type":"Point"}
}