{
  "type": "Feature",
  "properties": {
    "iso:country":"DE",
    "sg:address":"Fuerther Str. 27",
    "sg:city":"Nuernberg",
    "sg:phone":"+49 911/28707180",
    "sg:postcode":"90429",
    "sg:province":"Bayern",
    "wof:name":"Coreoptics Homepage, Optical Networking Solutions",
    "wof:placetype":"venue"
},
  "geometry": {"coordinates":[11.060227,49.449566],"type":"Point"}
}