{
  "type": "Feature",
  "properties": {
    "iso:country":"DE",
    "sg:address":"Preetzer Chaussee 142",
    "sg:city":"Kiel",
    "sg:phone":"+49 431/784131",
    "sg:postcode":"24146",
    "sg:province":"Schleswig-Holstein",
    "wof:name":"H. Clausen Augenoptiker",
    "wof:placetype":"venue"
},
  "geometry": {"coordinates":[10.1775903702,54.2960891724],"type":"Point"}
}