{
  "type": "Feature",
  "properties": {
    "iso:country":"DE",
    "sg:address":"Salinenstr. 60",
    "sg:city":"Erfurt",
    "sg:phone":"+49 361/7917490",
    "sg:postcode":"99085",
    "sg:province":"Th\u00fcringen",
    "wof:name":"Tasch Bauelemente Gmbh",
    "wof:placetype":"venue"
},
  "geometry": {"coordinates":[11.038803,51.003971],"type":"Point"}
}