{
  "type": "Feature",
  "properties": {
    "iso:country":"DE",
    "sg:address":"K\u00e4mmererstr. 23a",
    "sg:city":"Speyer",
    "sg:phone":"+49 6232/629252",
    "sg:postcode":"67346",
    "sg:province":"Rheinland-Pfalz",
    "wof:name":"Hoffmann & Sattler Ohg",
    "wof:placetype":"venue"
},
  "geometry": {"coordinates":[8.4266309738,49.3139953613],"type":"Point"}
}