{
  "type": "Feature",
  "properties": {
    "iso:country":"DE",
    "sg:address":"Ernst-Ebeling-Str. 9",
    "sg:city":"Hannover",
    "sg:phone":"+49 511/520011",
    "sg:postcode":"30539",
    "sg:province":"Niedersachsen",
    "wof:name":"Dr. Gerd Buschmann Tierarzt",
    "wof:placetype":"venue"
},
  "geometry": {"coordinates":[9.8328952789,52.3491516113],"type":"Point"}
}