{
  "type": "Feature",
  "properties": {
    "iso:country":"DE",
    "sg:address":"Irfersgr\u00fcner Str. 17",
    "sg:city":"Waldkirchen",
    "sg:phone":"+49 37606/8412",
    "sg:postcode":"08485",
    "sg:province":"Sachsen",
    "wof:name":"Marienh\u00f6her Milchproduktion Agro Waldkirchen Gmbh & Co. Kg",
    "wof:placetype":"venue"
},
  "geometry": {"coordinates":[12.38224,50.598297],"type":"Point"}
}