{
  "type": "Feature",
  "properties": {
    "iso:country":"DE",
    "sg:address":"Potsdamer Str. 7",
    "sg:city":"Bad Pyrmont",
    "sg:postcode":"31812",
    "sg:province":"Niedersachsen",
    "wof:name":"Parit\u00e4tische Gesellschaft F\u00fcr Jugendarbeit Gmbh & Co. Kg",
    "wof:placetype":"venue"
},
  "geometry": {"coordinates":[9.2799043655,51.986328125],"type":"Point"}
}