{
  "type": "Feature",
  "properties": {
    "iso:country":"DE",
    "sg:address":"Leibnizstr. 28",
    "sg:city":"Berlin",
    "sg:phone":"+49 30/31508727",
    "sg:postcode":"10625",
    "sg:province":"Berlin",
    "wof:name":"Angelika Grotehenne Rechtsanw\u00e4ltin",
    "wof:placetype":"venue"
},
  "geometry": {"coordinates":[13.314414978,52.5083236694],"type":"Point"}
}