{
  "type": "Feature",
  "properties": {
    "iso:country":"DE",
    "sg:address":"An der Brauerei 1",
    "sg:city":"Potsdam",
    "sg:postcode":"14478",
    "sg:province":"Brandenburg",
    "wof:name":"Apd Sicherheitsdienste Gmbh",
    "wof:placetype":"venue"
},
  "geometry": {"coordinates":[13.1076345444,52.3571472168],"type":"Point"}
}