{
  "type": "Feature",
  "properties": {
    "iso:country":"DE",
    "sg:address":"Ringstr. 21",
    "sg:city":"Eichenau",
    "sg:phone":"+49 8141/38237",
    "sg:postcode":"82223",
    "sg:province":"Bayern",
    "wof:name":"G\u00fcnter Kromes",
    "wof:placetype":"venue"
},
  "geometry": {"coordinates":[11.323617,48.157722],"type":"Point"}
}