{
  "type": "Feature",
  "properties": {
    "iso:country":"DE",
    "sg:address":"Rehwiesenweg 10",
    "sg:city":"Niedenstein",
    "sg:phone":"+49 5624/2488",
    "sg:postcode":"34305",
    "sg:province":"Hessen",
    "wof:name":"C. H\u00f6hn Immobilienmakler",
    "wof:placetype":"venue"
},
  "geometry": {"coordinates":[9.3169841766,51.2328338623],"type":"Point"}
}