{
  "type": "Feature",
  "properties": {
    "iso:country":"DE",
    "sg:address":"Auf dem Baggersand 17",
    "sg:city":"L\u00fcbeck-Travem\u00fcnde",
    "sg:phone":"+49 4502",
    "sg:postcode":"23570",
    "sg:province":"Schleswig-Holstein",
    "wof:name":"Immobilien & Hausverwaltung Detlef Olschewski",
    "wof:placetype":"venue"
},
  "geometry": {"coordinates":[10.8843746185,53.9536018372],"type":"Point"}
}