{
  "type": "Feature",
  "properties": {
    "iso:country":"DE",
    "sg:address":"Hofener Str. 2",
    "sg:city":"Peiting",
    "sg:phone":"+49 8869/809",
    "sg:postcode":"86971",
    "sg:province":"Bayern",
    "wof:name":"Franz Schuster",
    "wof:placetype":"venue"
},
  "geometry": {"coordinates":[10.954971,47.85696],"type":"Point"}
}