{
  "type": "Feature",
  "properties": {
    "iso:country":"DE",
    "sg:address":"Neusser Str. 33",
    "sg:city":"D\u00fcsseldorf",
    "sg:phone":"+49 211/901890",
    "sg:postcode":"40219",
    "sg:province":"Nordrhein-Westfalen",
    "wof:name":"Wsg Wohnungs- Und Siedlunggsges. Mbh",
    "wof:placetype":"venue"
},
  "geometry": {"coordinates":[6.7657408714,51.2173995972],"type":"Point"}
}