{
  "type": "Feature",
  "properties": {
    "iso:country":"DE",
    "sg:address":"Vogelsbruch 3",
    "sg:city":"Wuppertal",
    "sg:phone":"+49 202/720689",
    "sg:postcode":"42111",
    "sg:province":"Nordrhein-Westfalen",
    "wof:name":"Harald Puley",
    "wof:placetype":"venue"
},
  "geometry": {"coordinates":[7.124274,51.284794],"type":"Point"}
}