{
  "type": "Feature",
  "properties": {
    "iso:country":"DE",
    "sg:address":"Graf-Salm-Str. 35",
    "sg:city":"Passau",
    "sg:phone":"+49 851/58489",
    "sg:postcode":"94036",
    "sg:province":"Bayern",
    "wof:name":"F. Apel Ingenieur",
    "wof:placetype":"venue"
},
  "geometry": {"coordinates":[13.438246727,48.5624313354],"type":"Point"}
}