{
  "type": "Feature",
  "properties": {
    "iso:country":"DE",
    "sg:address":"Klausnerring 16",
    "sg:city":"Kirchheim",
    "sg:postcode":"85551",
    "sg:province":"Bayern",
    "wof:name":"Multi Vermietungs- Und Verwaltungsgesellschaft",
    "wof:placetype":"venue"
},
  "geometry": {"coordinates":[11.7431793213,48.1523590088],"type":"Point"}
}