{
  "type": "Feature",
  "properties": {
    "iso:country":"DE",
    "sg:address":"Berliner Str. 312",
    "sg:city":"Offenbach",
    "sg:phone":"+49 69/822182",
    "sg:postcode":"63067",
    "sg:province":"Hessen",
    "wof:name":"Ibb Ingenieurb\u00fcro F\u00fcr Betriebs- Und Anlagen-",
    "wof:placetype":"venue"
},
  "geometry": {"coordinates":[8.739459,50.105518],"type":"Point"}
}