{
  "type": "Feature",
  "properties": {
    "iso:country":"DE",
    "sg:address":"Rostocker Str. 1E",
    "sg:city":"Satow",
    "sg:phone":"+49 38295/78229",
    "sg:postcode":"18239",
    "sg:province":"Mecklenburg-Vorpommern",
    "wof:name":"Satower Marktbau Verwaltungs Gmbh",
    "wof:placetype":"venue"
},
  "geometry": {"coordinates":[11.904291153,53.9921798706],"type":"Point"}
}