{
  "type": "Feature",
  "properties": {
    "iso:country":"DE",
    "sg:address":"Siemensstr. 35",
    "sg:city":"Essen",
    "sg:phone":"+49 201/642749",
    "sg:postcode":"45143",
    "sg:province":"Nordrhein-Westfalen",
    "wof:name":"F. Und M. Willnat",
    "wof:placetype":"venue"
},
  "geometry": {"coordinates":[6.9754528999,51.4589385986],"type":"Point"}
}