{
  "type": "Feature",
  "properties": {
    "iso:country":"DE",
    "sg:address":"Ridderstr. 41",
    "sg:city":"Ahaus",
    "sg:phone":"+49 2561/93630",
    "sg:postcode":"48683",
    "sg:province":"Nordrhein-Westfalen",
    "wof:name":"Csm-caritas-sozialmarketing Und Beratungs- Gmbh",
    "wof:placetype":"venue"
},
  "geometry": {"coordinates":[7.0209970474,52.083065033],"type":"Point"}
}