{
  "type": "Feature",
  "properties": {
    "iso:country":"DE",
    "sg:address":"Burgstr. 4",
    "sg:city":"Sankt Augustin",
    "sg:phone":"+49 2241/926680",
    "sg:postcode":"53757",
    "sg:province":"Nordrhein-Westfalen",
    "wof:name":"Kaisers Tengelmann Ag",
    "wof:placetype":"venue"
},
  "geometry": {"coordinates":[7.1649432182,50.7899169922],"type":"Point"}
}