{
  "type": "Feature",
  "properties": {
    "iso:country":"DE",
    "sg:address":"Schwaben 5",
    "sg:city":"Kelheim",
    "sg:phone":"+49 9447/920880",
    "sg:postcode":"93309",
    "sg:province":"Bayern",
    "wof:name":"Gut Schwaben-ei-gmbh",
    "wof:placetype":"venue"
},
  "geometry": {"coordinates":[11.7604255676,48.910282135],"type":"Point"}
}