{
  "type": "Feature",
  "properties": {
    "iso:country":"DE",
    "sg:address":"Schlo\u00dfstr. 169",
    "sg:city":"Udenheim",
    "sg:phone":"+49 6732/2657",
    "sg:postcode":"55288",
    "sg:province":"Rheinland-Pfalz",
    "wof:name":"Erich Jost",
    "wof:placetype":"venue"
},
  "geometry": {"coordinates":[8.1719799042,49.8642997742],"type":"Point"}
}