{
  "type": "Feature",
  "properties": {
    "iso:country":"DE",
    "sg:address":"Sieglgut 27",
    "sg:city":"Passau",
    "sg:postcode":"94034",
    "sg:province":"Bayern",
    "wof:name":"Deutscher Verband F\u00fcr Schwei\u00dftechnik E. V.",
    "wof:placetype":"venue"
},
  "geometry": {"coordinates":[13.4732522964,48.5913047791],"type":"Point"}
}