{
  "type": "Feature",
  "properties": {
    "iso:country":"DE",
    "sg:address":"Von-Bodelschwingh-Str. 77",
    "sg:city":"Bad Lippspringe",
    "sg:phone":"+49 5252/81786",
    "sg:postcode":"33175",
    "sg:province":"Nordrhein-Westfalen",
    "wof:name":"Esref Reisen",
    "wof:placetype":"venue"
},
  "geometry": {"coordinates":[8.839887619,51.7975921631],"type":"Point"}
}