{
  "type": "Feature",
  "properties": {
    "iso:country":"DE",
    "sg:address":"Josef-F\u00f6rster-Str. 8",
    "sg:city":"H\u00f6velhof",
    "sg:phone":"+49 5257/940055",
    "sg:postcode":"33161",
    "sg:province":"Nordrhein-Westfalen",
    "wof:name":"Metec Metallverarbeitung Gmbh",
    "wof:placetype":"venue"
},
  "geometry": {"coordinates":[8.648503,51.840076],"type":"Point"}
}