{
  "type": "Feature",
  "properties": {
    "iso:country":"DE",
    "sg:address":"Brunnenstr.50",
    "sg:city":"D\u00fcsseldorf",
    "sg:phone":"+49 211/31000310",
    "sg:postcode":"40223",
    "sg:province":"Nordrhein-Westfalen",
    "wof:name":"Lts Logistik & Transport-service Gmbh",
    "wof:placetype":"venue"
},
  "geometry": {"coordinates":[6.780424118,51.2050743103],"type":"Point"}
}