{
  "type": "Feature",
  "properties": {
    "iso:country":"DE",
    "sg:address":"Frankfurter Str. 200",
    "sg:city":"Kelkheim",
    "sg:phone":"+49 6195/3171",
    "sg:postcode":"65779",
    "sg:province":"Hessen",
    "wof:name":"E. Eisenbach",
    "wof:placetype":"venue"
},
  "geometry": {"coordinates":[8.4681692123,50.1232833862],"type":"Point"}
}