{
  "type": "Feature",
  "properties": {
    "iso:country":"DE",
    "sg:address":"Friedrichshafener Str. 103 /1",
    "sg:city":"Ravensburg",
    "sg:phone":"+49 751/62927",
    "sg:postcode":"88214",
    "sg:province":"Baden-W\u00fcrttemberg",
    "wof:name":"Wirl Gmbh",
    "wof:placetype":"venue"
},
  "geometry": {"coordinates":[9.591114,47.73164],"type":"Point"}
}