{
  "type": "Feature",
  "properties": {
    "iso:country":"DE",
    "sg:address":"Fischerei 16",
    "sg:city":"Dingolfing",
    "sg:phone":"+49 8731/2314",
    "sg:postcode":"84130",
    "sg:province":"Bayern",
    "wof:name":"Neue Apotheke Engelbert Klofat E. K.",
    "wof:placetype":"venue"
},
  "geometry": {"coordinates":[12.495023,48.630562],"type":"Point"}
}