{
  "type": "Feature",
  "properties": {
    "iso:country":"DE",
    "sg:address":"Albrecht-D\u00fcrer-Str. 11",
    "sg:city":"Dillenburg",
    "sg:phone":"+49 2771/32314",
    "sg:postcode":"35684",
    "sg:province":"Hessen",
    "wof:name":"Bev Bastian Gmbh",
    "wof:placetype":"venue"
},
  "geometry": {"coordinates":[8.294929,50.774708],"type":"Point"}
}