{
  "type": "Feature",
  "properties": {
    "iso:country":"DE",
    "sg:address":"Kirchstr. 8",
    "sg:city":"Kasendorf",
    "sg:phone":"+49 9228/246",
    "sg:postcode":"95359",
    "sg:province":"Bayern",
    "wof:name":"Ev. Luth. Pfarramt",
    "wof:placetype":"venue"
},
  "geometry": {"coordinates":[11.3516235352,50.0361442566],"type":"Point"}
}