{
  "type": "Feature",
  "properties": {
    "iso:country":"DE",
    "sg:address":"Herforder Str. 33",
    "sg:city":"Bielefeld",
    "sg:phone":"+49 521/177943",
    "sg:postcode":"33602",
    "sg:province":"Nordrhein-Westfalen",
    "wof:name":"Ada Grillrestaurant",
    "wof:placetype":"venue"
},
  "geometry": {"coordinates":[8.5347490311,52.0266265869],"type":"Point"}
}