{
  "type": "Feature",
  "properties": {
    "iso:country":"DE",
    "sg:address":"Alte Str. 8",
    "sg:city":"Remagen",
    "sg:phone":"+49 2642/23392",
    "sg:postcode":"53424",
    "sg:province":"Rheinland-Pfalz",
    "wof:name":"F. Fassbender Steuerberater",
    "wof:placetype":"venue"
},
  "geometry": {"coordinates":[7.2362551689,50.5773735046],"type":"Point"}
}