{
  "type": "Feature",
  "properties": {
    "iso:country":"DE",
    "sg:address":"Wilhelmstr 39",
    "sg:city":"Bretten",
    "sg:phone":"+49 7252/975697",
    "sg:postcode":"75015",
    "sg:province":"Baden-W\u00fcrttemberg",
    "wof:name":"Sob - Infosys Gmbh",
    "wof:placetype":"venue"
},
  "geometry": {"coordinates":[8.700762,49.036304],"type":"Point"}
}