{
  "type": "Feature",
  "properties": {
    "iso:country":"DE",
    "sg:address":"Kirchweg 10",
    "sg:city":"Geisenheim",
    "sg:phone":"+49 6722/64413",
    "sg:postcode":"65366",
    "sg:province":"Hessen",
    "wof:name":"Arnold Stettler",
    "wof:placetype":"venue"
},
  "geometry": {"coordinates":[7.969584,49.983475],"type":"Point"}
}