{
  "type": "Feature",
  "properties": {
    "iso:country":"DE",
    "sg:address":"N\u00fcrtinger Str. 52",
    "sg:city":"Gro\u00dfbettlingen",
    "sg:phone":"+49 7022/46868",
    "sg:postcode":"72663",
    "sg:province":"Baden-W\u00fcrttemberg",
    "wof:name":"Karl Kraus",
    "wof:placetype":"venue"
},
  "geometry": {"coordinates":[9.3090829849,48.5915412903],"type":"Point"}
}