{
  "type": "Feature",
  "properties": {
    "iso:country":"DE",
    "sg:address":"Kohlwald 11",
    "sg:city":"Sulzbach-Laufen",
    "sg:phone":"+49 7976/1305",
    "sg:postcode":"74429",
    "sg:province":"Baden-W\u00fcrttemberg",
    "wof:name":"Holztransporte Und Handel Dorothea H\u00e4hnle",
    "wof:placetype":"venue"
},
  "geometry": {"coordinates":[9.8749904633,48.9701499939],"type":"Point"}
}