{
  "type": "Feature",
  "properties": {
    "iso:country":"DE",
    "sg:address":"Fleetrade 1B",
    "sg:city":"Bremen",
    "sg:phone":"+49 421/494651",
    "sg:postcode":"28207",
    "sg:province":"Bremen",
    "wof:name":"Preen",
    "wof:placetype":"venue"
},
  "geometry": {"coordinates":[8.860704,53.066032],"type":"Point"}
}