{
  "type": "Feature",
  "properties": {
    "iso:country":"DE",
    "sg:address":"Gro\u00dfenhainer Str. 24",
    "sg:city":"Ebersbach",
    "sg:phone":"+49 3522/310113",
    "sg:postcode":"01561",
    "sg:province":"Sachsen",
    "wof:name":"R. Kretzschmar",
    "wof:placetype":"venue"
},
  "geometry": {"coordinates":[13.6316995621,51.2736206055],"type":"Point"}
}