{
  "type": "Feature",
  "properties": {
    "iso:country":"DE",
    "sg:address":"Eurichsgasse 9",
    "sg:city":"Speyer",
    "sg:phone":"+49 6232/71790",
    "sg:postcode":"67346",
    "sg:province":"Rheinland-Pfalz",
    "wof:name":"Gerda Rimmler",
    "wof:placetype":"venue"
},
  "geometry": {"coordinates":[8.4312057495,49.3199119568],"type":"Point"}
}