{
  "type": "Feature",
  "properties": {
    "iso:country":"DE",
    "sg:address":"Birkenweg 10",
    "sg:city":"Neuhaus",
    "sg:phone":"+49 8503/353",
    "sg:postcode":"94152",
    "sg:province":"Bayern",
    "wof:name":"Forstner",
    "wof:placetype":"venue"
},
  "geometry": {"coordinates":[13.4207439423,48.4632492065],"type":"Point"}
}