{
  "type": "Feature",
  "properties": {
    "iso:country":"DE",
    "sg:address":"Alsbach 23",
    "sg:city":"Mettendorf",
    "sg:postcode":"54675",
    "sg:province":"Rheinland-Pfalz",
    "wof:name":"Behindertenwerkstatt",
    "wof:placetype":"venue"
},
  "geometry": {"coordinates":[6.331055,49.941349],"type":"Point"}
}