{
  "type": "Feature",
  "properties": {
    "iso:country":"DE",
    "sg:address":"Hermannstr. 49",
    "sg:city":"Bonn",
    "sg:phone":"+49 228/466644",
    "sg:postcode":"53225",
    "sg:province":"Nordrhein-Westfalen",
    "wof:name":"Paul P\u00fctzer",
    "wof:placetype":"venue"
},
  "geometry": {"coordinates":[7.1184468269,50.734752655],"type":"Point"}
}