{
  "type": "Feature",
  "properties": {
    "iso:country":"DE",
    "sg:address":"Gerbergasse 2",
    "sg:city":"Kirn",
    "sg:phone":"+49 6752/2218",
    "sg:postcode":"55606",
    "sg:province":"Rheinland-Pfalz",
    "wof:name":"J. Paulussen",
    "wof:placetype":"venue"
},
  "geometry": {"coordinates":[7.461135,49.785568],"type":"Point"}
}