{
  "type": "Feature",
  "properties": {
    "iso:country":"DE",
    "sg:address":"Kirchfeldstr. 98",
    "sg:city":"D\u00fcsseldorf",
    "sg:phone":"+49 211/378266",
    "sg:postcode":"40215",
    "sg:province":"Nordrhein-Westfalen",
    "wof:name":"Dieter Peters",
    "wof:placetype":"venue"
},
  "geometry": {"coordinates":[6.781554,51.212524],"type":"Point"}
}