{
  "type": "Feature",
  "properties": {
    "iso:country":"DE",
    "sg:address":"Berliner Platz 5",
    "sg:city":"Windeck",
    "sg:phone":"+49 2292/5543",
    "sg:postcode":"51570",
    "sg:province":"Nordrhein-Westfalen",
    "wof:name":"Rudi Hermes",
    "wof:placetype":"venue"
},
  "geometry": {"coordinates":[7.6084241867,50.797870636],"type":"Point"}
}