{
  "type": "Feature",
  "properties": {
    "iso:country":"DE",
    "sg:address":"Bahnhofstr. 19",
    "sg:city":"Grafenau",
    "sg:phone":"+49 8552/91700",
    "sg:postcode":"94481",
    "sg:province":"Bayern",
    "wof:name":"Hans H\u00f6fling",
    "wof:placetype":"venue"
},
  "geometry": {"coordinates":[13.3953466415,48.8549537659],"type":"Point"}
}