{
  "type": "Feature",
  "properties": {
    "iso:country":"DE",
    "sg:address":"Bayernstr. 24",
    "sg:city":"Trostberg",
    "sg:phone":"+49 8621/98710",
    "sg:postcode":"83308",
    "sg:province":"Bayern",
    "wof:name":"Offsetdruck Zuber Gmbh",
    "wof:placetype":"venue"
},
  "geometry": {"coordinates":[12.55936,48.028625],"type":"Point"}
}