{
  "type": "Feature",
  "properties": {
    "iso:country":"DE",
    "sg:address":"Pommernstr. 6",
    "sg:city":"Bad Kreuznach",
    "sg:phone":"+49 671/42911",
    "sg:postcode":"55545",
    "sg:province":"Rheinland-Pfalz",
    "wof:name":"Klaus Heinze",
    "wof:placetype":"venue"
},
  "geometry": {"coordinates":[7.870308,49.87196],"type":"Point"}
}