{
  "type": "Feature",
  "properties": {
    "iso:country":"DE",
    "sg:address":"Friedhofstr. 3-11",
    "sg:city":"Ravensburg",
    "sg:phone":"+49 751/88030",
    "sg:postcode":"88212",
    "sg:province":"Baden-W\u00fcrttemberg",
    "wof:name":"B\u00fcrgerliches Brauhaus Ravensburg-lindau Ag",
    "wof:placetype":"venue"
},
  "geometry": {"coordinates":[9.615709,47.783257],"type":"Point"}
}