{
  "type": "Feature",
  "properties": {
    "iso:country":"DE",
    "sg:address":"Georg-Friedrich-H\u00e4ndel-Str. 1",
    "sg:city":"Hamm",
    "sg:phone":"+49 2381/75618",
    "sg:postcode":"59075",
    "sg:province":"Nordrhein-Westfalen",
    "wof:name":"O. Ries",
    "wof:placetype":"venue"
},
  "geometry": {"coordinates":[7.7683811188,51.6985702515],"type":"Point"}
}