{
  "type": "Feature",
  "properties": {
    "iso:country":"DE",
    "sg:address":"Schmerberger Str. 31",
    "sg:city":"Michendorf",
    "sg:phone":"+49 33205/44057",
    "sg:postcode":"14552",
    "sg:province":"Brandenburg",
    "wof:name":"Detlef Lieckefett",
    "wof:placetype":"venue"
},
  "geometry": {"coordinates":[13.022669,52.308601],"type":"Point"}
}