{
  "type": "Feature",
  "properties": {
    "iso:country":"DE",
    "sg:address":"Brunnenstr. 65",
    "sg:city":"Horn-Bad Meinberg",
    "sg:phone":"+49 5234/9761",
    "sg:postcode":"32805",
    "sg:province":"Nordrhein-Westfalen",
    "wof:name":"Pension Haus Egeria",
    "wof:placetype":"venue"
},
  "geometry": {"coordinates":[8.9833250046,51.8978004456],"type":"Point"}
}