{
  "type": "Feature",
  "properties": {
    "iso:country":"DE",
    "sg:address":"Rathausplatz 7",
    "sg:city":"Kaarst",
    "sg:phone":"+49 2131/985804",
    "sg:postcode":"41564",
    "sg:province":"Nordrhein-Westfalen",
    "wof:name":"S. Fabry",
    "wof:placetype":"venue"
},
  "geometry": {"coordinates":[6.616728,51.230087],"type":"Point"}
}