{
  "type": "Feature",
  "properties": {
    "iso:country":"DE",
    "sg:address":"Kr\u00e4henweg 78",
    "sg:city":"F\u00fcrth",
    "sg:phone":"+49 911/7540502",
    "sg:postcode":"90768",
    "sg:province":"Bayern",
    "wof:name":"Otmar H\u00fcbner Steuerberater",
    "wof:placetype":"venue"
},
  "geometry": {"coordinates":[10.9391403198,49.4915275574],"type":"Point"}
}