{
  "type": "Feature",
  "properties": {
    "iso:country":"DE",
    "sg:address":"Breidenbachstr. 18",
    "sg:city":"Leverkusen",
    "sg:postcode":"51373",
    "sg:province":"Nordrhein-Westfalen",
    "wof:name":"Hell-sport Ges. F\u00fcr Sport- Marketing Und Werbung Mbh",
    "wof:placetype":"venue"
},
  "geometry": {"coordinates":[6.9830460548,51.0302886963],"type":"Point"}
}