{
  "type": "Feature",
  "properties": {
    "iso:country":"DE",
    "sg:address":"Itzenb\u00fctteler Str. 42",
    "sg:city":"Jesteburg",
    "sg:postcode":"21266",
    "sg:province":"Niedersachsen",
    "wof:name":"C & P Baubetreuungs- Gesellschaft Mbh",
    "wof:placetype":"venue"
},
  "geometry": {"coordinates":[9.948363,53.313202],"type":"Point"}
}