{
  "type": "Feature",
  "properties": {
    "iso:country":"DE",
    "sg:address":"Lange Str. 43",
    "sg:city":"Baden-Baden",
    "sg:phone":"+49 7221/22414",
    "sg:postcode":"76530",
    "sg:province":"Baden-W\u00fcrttemberg",
    "wof:name":"Minh Tran-quang",
    "wof:placetype":"venue"
},
  "geometry": {"coordinates":[8.2374296188,48.7638320923],"type":"Point"}
}