{
  "type": "Feature",
  "properties": {
    "iso:country":"DE",
    "sg:address":"Marktstr. 6",
    "sg:city":"Weilheim",
    "sg:phone":"+49 7023/8382",
    "sg:postcode":"73235",
    "sg:province":"Baden-W\u00fcrttemberg",
    "wof:name":"Pizzeria Weinstube Traube",
    "wof:placetype":"venue"
},
  "geometry": {"coordinates":[9.5387382507,48.6148452759],"type":"Point"}
}