{
  "type": "Feature",
  "properties": {
    "iso:country":"DE",
    "sg:address":"Kreuzstr. 62",
    "sg:city":"M\u00fclheim",
    "sg:phone":"+49 208/449188",
    "sg:postcode":"45468",
    "sg:province":"Nordrhein-Westfalen",
    "wof:name":"Weller Gmbh",
    "wof:placetype":"venue"
},
  "geometry": {"coordinates":[6.8933901787,51.4389190674],"type":"Point"}
}