{
  "type": "Feature",
  "properties": {
    "iso:country":"DE",
    "sg:address":"Ludwigsburger Str. 59",
    "sg:city":"Waiblingen",
    "sg:phone":"+49 7151/54884",
    "sg:postcode":"71332",
    "sg:province":"Baden-W\u00fcrttemberg",
    "wof:name":"I. Frey Wettannahme",
    "wof:placetype":"venue"
},
  "geometry": {"coordinates":[9.30649,48.833889],"type":"Point"}
}