{
  "type": "Feature",
  "properties": {
    "iso:country":"DE",
    "sg:address":"Am Welschen Brunnen 43",
    "sg:city":"Crailsheim",
    "sg:phone":"+49 7951/42811",
    "sg:postcode":"74564",
    "sg:province":"Baden-W\u00fcrttemberg",
    "wof:name":"World Class Germany Gmbh",
    "wof:placetype":"venue"
},
  "geometry": {"coordinates":[10.0758342743,49.1256256104],"type":"Point"}
}