{
  "type": "Feature",
  "properties": {
    "iso:country":"DE",
    "sg:address":"Mei\u00dfner Weg 28 a",
    "sg:city":"Berlin",
    "sg:phone":"+49 30/6615300",
    "sg:postcode":"12355",
    "sg:province":"Berlin",
    "wof:name":"Heinz Guenter Michels",
    "wof:placetype":"venue"
},
  "geometry": {"coordinates":[13.4743251801,52.4172172546],"type":"Point"}
}