{
  "type": "Feature",
  "properties": {
    "iso:country":"DE",
    "sg:address":"Badstr. 62",
    "sg:city":"Boll",
    "sg:phone":"+49 7164/93101",
    "sg:postcode":"73087",
    "sg:province":"Baden-W\u00fcrttemberg",
    "wof:name":"Staufen Akademie Bad Boll Privates Schulungszentrum F\u00fcr",
    "wof:placetype":"venue"
},
  "geometry": {"coordinates":[9.605176,48.638863],"type":"Point"}
}