{
  "type": "Feature",
  "properties": {
    "iso:country":"DE",
    "sg:address":"Krefelder Str. 3",
    "sg:city":"T\u00f6nisvorst",
    "sg:phone":"+49 2151/790178",
    "sg:postcode":"47918",
    "sg:province":"Nordrhein-Westfalen",
    "wof:name":"A. Ziegler",
    "wof:placetype":"venue"
},
  "geometry": {"coordinates":[6.49551,51.320587],"type":"Point"}
}