{
  "type": "Feature",
  "properties": {
    "iso:country":"DE",
    "sg:address":"Bismarckstr. 1",
    "sg:city":"M\u00fcnchberg",
    "sg:phone":"+49 9251/5488",
    "sg:postcode":"95213",
    "sg:province":"Bayern",
    "wof:name":"Kulmbacher Bierstube",
    "wof:placetype":"venue"
},
  "geometry": {"coordinates":[11.7887496948,50.1915664673],"type":"Point"}
}