{
  "type": "Feature",
  "properties": {
    "iso:country":"DE",
    "sg:address":"Bergstr. 6",
    "sg:city":"Lauben",
    "sg:phone":"+49 8336/672",
    "sg:postcode":"87761",
    "sg:province":"Bayern",
    "wof:name":"Ev. Luth. Pfarramt",
    "wof:placetype":"venue"
},
  "geometry": {"coordinates":[10.3132762909,48.0740356445],"type":"Point"}
}