{
  "type": "Feature",
  "properties": {
    "iso:country":"DE",
    "sg:address":"Anton-Hockelmann-Str. 5 b",
    "sg:city":"Augsburg",
    "sg:phone":"+49 821/707684",
    "sg:postcode":"86169",
    "sg:province":"Bayern",
    "wof:name":"J. Marquard Steuerberater Und",
    "wof:placetype":"venue"
},
  "geometry": {"coordinates":[10.8985443115,48.399143219],"type":"Point"}
}