{
  "type": "Feature",
  "properties": {
    "iso:country":"DE",
    "sg:address":"Podbielskistr.4",
    "sg:city":"Hannover",
    "sg:phone":"+49 511/3945333",
    "sg:postcode":"30163",
    "sg:province":"Niedersachsen",
    "wof:name":"Stilista",
    "wof:placetype":"venue"
},
  "geometry": {"coordinates":[9.75117,52.388897],"type":"Point"}
}