{
  "type": "Feature",
  "properties": {
    "iso:country":"DE",
    "sg:address":"Am H\u00fchnerberg 17",
    "sg:city":"Hofheim",
    "sg:phone":"+49 6122/6071",
    "sg:postcode":"65719",
    "sg:province":"Hessen",
    "wof:name":"Bsb Besenbruch Bau Gmbh",
    "wof:placetype":"venue"
},
  "geometry": {"coordinates":[8.3745279312,50.0672149658],"type":"Point"}
}