{
  "type": "Feature",
  "properties": {
    "iso:country":"DE",
    "sg:address":"Schaafau 1",
    "sg:city":"Wackernheim",
    "sg:phone":"+49 6132/5111",
    "sg:postcode":"55263",
    "sg:province":"Rheinland-Pfalz",
    "wof:name":"Vereinigte Gro\u00dfm\u00e4rkte F\u00fcr Obst Und Gem\u00fcse Rheinhessen Eg",
    "wof:placetype":"venue"
},
  "geometry": {"coordinates":[8.1160039902,49.9794464111],"type":"Point"}
}