{
  "type": "Feature",
  "properties": {
    "iso:country":"DE",
    "sg:address":"Oldenburger Str. 1",
    "sg:city":"Ganderkesee",
    "sg:postcode":"27777",
    "sg:province":"Niedersachsen",
    "wof:name":"Kanaltechnik Kunz Nord Gmbh",
    "wof:placetype":"venue"
},
  "geometry": {"coordinates":[8.5153837204,53.0446052551],"type":"Point"}
}