{
  "type": "Feature",
  "properties": {
    "iso:country":"DE",
    "sg:address":"Von-Eichendorff-Str. 13",
    "sg:city":"Feldkirchen-Westerham",
    "sg:phone":"+49 8063/7258",
    "sg:postcode":"83620",
    "sg:province":"Bayern",
    "wof:name":"Acs Automatic Control Systems Informatik-systemtechnik Gmbh",
    "wof:placetype":"venue"
},
  "geometry": {"coordinates":[11.84794,47.90873],"type":"Point"}
}