{
  "type": "Feature",
  "properties": {
    "iso:country":"DE",
    "sg:address":"Hauptstr. 14",
    "sg:city":"Filderstadt",
    "sg:phone":"+49 711/7000470",
    "sg:postcode":"70794",
    "sg:province":"Baden-W\u00fcrttemberg",
    "wof:name":"Bernhauser Bank Eg",
    "wof:placetype":"venue"
},
  "geometry": {"coordinates":[9.21613,48.678261],"type":"Point"}
}