{
  "type": "Feature",
  "properties": {
    "iso:country":"DE",
    "sg:address":"Franz-Burger-Str. 21 c",
    "sg:city":"Zeil",
    "sg:phone":"+49 9524/5224",
    "sg:postcode":"97475",
    "sg:province":"Bayern",
    "wof:name":"M\u00fcller & Co. Naturheizsysteme",
    "wof:placetype":"venue"
},
  "geometry": {"coordinates":[10.5849647522,50.0160255432],"type":"Point"}
}