{
  "type": "Feature",
  "properties": {
    "iso:country":"DE",
    "sg:address":"Im Wiesenhof 26",
    "sg:city":"Hannover",
    "sg:postcode":"30559",
    "sg:province":"Niedersachsen",
    "wof:name":"Hans-joachim Graul Graphischer Fachhandel",
    "wof:placetype":"venue"
},
  "geometry": {"coordinates":[9.861209,52.361671],"type":"Point"}
}