{
  "type": "Feature",
  "properties": {
    "iso:country":"DE",
    "sg:address":"Waltersh\u00e4user Str. 37",
    "sg:city":"Gotha",
    "sg:postcode":"99867",
    "sg:province":"Th\u00fcringen",
    "wof:name":"Ritterklause",
    "wof:placetype":"venue"
},
  "geometry": {"coordinates":[10.692902565,50.9431648254],"type":"Point"}
}