{
  "type": "Feature",
  "properties": {
    "iso:country":"DE",
    "sg:address":"Schlo\u00dfstr. 17",
    "sg:city":"Waldfischbach-Burgalben",
    "sg:phone":"+49 6333/3074",
    "sg:postcode":"67714",
    "sg:province":"Rheinland-Pfalz",
    "wof:name":"B. Bohl",
    "wof:placetype":"venue"
},
  "geometry": {"coordinates":[7.6554899216,49.2838134766],"type":"Point"}
}