{
  "type": "Feature",
  "properties": {
    "iso:country":"DE",
    "sg:address":"Burgstr. 39",
    "sg:city":"Wittlich",
    "sg:phone":"+49 6571/5634",
    "sg:postcode":"54516",
    "sg:province":"Rheinland-Pfalz",
    "wof:name":"Anna M. Meilen Modewaren",
    "wof:placetype":"venue"
},
  "geometry": {"coordinates":[6.8888220787,49.9863891602],"type":"Point"}
}