{
  "type": "Feature",
  "properties": {
    "iso:country":"DE",
    "sg:address":"Rostocker Str. 27",
    "sg:city":"Teterow",
    "sg:phone":"+49 3996/182927",
    "sg:postcode":"17166",
    "sg:province":"Mecklenburg-Vorpommern",
    "wof:name":"Cafe Sulz Inh. Renate Und Ewald Sulz",
    "wof:placetype":"venue"
},
  "geometry": {"coordinates":[12.573744,53.775295],"type":"Point"}
}