{
  "type": "Feature",
  "properties": {
    "iso:country":"DE",
    "sg:address":"Fichtenstr. 3",
    "sg:city":"Wissen",
    "sg:phone":"+49 2742/2960",
    "sg:postcode":"57537",
    "sg:province":"Rheinland-Pfalz",
    "wof:name":"Karl Burbach Bauunternehmen",
    "wof:placetype":"venue"
},
  "geometry": {"coordinates":[7.735383,50.776054],"type":"Point"}
}