{
  "type": "Feature",
  "properties": {
    "iso:country":"DE",
    "sg:address":"Schlottergasse 29",
    "sg:city":"Bischofsheim",
    "sg:phone":"+49 9772/8038",
    "sg:postcode":"97653",
    "sg:province":"Bayern",
    "wof:name":"Theo Fuchs",
    "wof:placetype":"venue"
},
  "geometry": {"coordinates":[10.0338754654,50.3965988159],"type":"Point"}
}