{
  "type": "Feature",
  "properties": {
    "iso:country":"DE",
    "sg:address":"Habichtweg 10",
    "sg:city":"Kirchheim",
    "sg:phone":"+49 7021/43123",
    "sg:postcode":"73230",
    "sg:province":"Baden-W\u00fcrttemberg",
    "wof:name":"Franz St\u00fchler",
    "wof:placetype":"venue"
},
  "geometry": {"coordinates":[9.4681959152,48.6475372314],"type":"Point"}
}