{
  "type": "Feature",
  "properties": {
    "iso:country":"DE",
    "sg:address":"Scheffelstr. 31",
    "sg:city":"Frankfurt",
    "sg:phone":"+49 69/551741",
    "sg:postcode":"60318",
    "sg:province":"Hessen",
    "wof:name":"Holtz Immobilien",
    "wof:placetype":"venue"
},
  "geometry": {"coordinates":[8.6893787384,50.1219215393],"type":"Point"}
}