{
  "type": "Feature",
  "properties": {
    "iso:country":"DE",
    "sg:address":"Alleestr. 13a",
    "sg:city":"Dorsten",
    "sg:phone":"+49 2362/954940",
    "sg:postcode":"46282",
    "sg:province":"Nordrhein-Westfalen",
    "wof:name":"M - Tec Messtechnik Gmbh",
    "wof:placetype":"venue"
},
  "geometry": {"coordinates":[6.964584,51.657906],"type":"Point"}
}