{
  "type": "Feature",
  "properties": {
    "iso:country":"DE",
    "sg:address":"Hauptstr. 16",
    "sg:city":"Heilbronn",
    "sg:postcode":"74081",
    "sg:province":"Baden-W\u00fcrttemberg",
    "wof:name":"Take Off Reisen Gmbh",
    "wof:placetype":"venue"
},
  "geometry": {"coordinates":[9.1903533936,49.1188659668],"type":"Point"}
}