{
  "type": "Feature",
  "properties": {
    "iso:country":"DE",
    "sg:address":"Bahnhofstr. 1",
    "sg:city":"Illingen",
    "sg:phone":"+49 7042/22233",
    "sg:postcode":"75428",
    "sg:province":"Baden-W\u00fcrttemberg",
    "wof:name":"Eric Schach",
    "wof:placetype":"venue"
},
  "geometry": {"coordinates":[8.918102,48.954426],"type":"Point"}
}