{
  "type": "Feature",
  "properties": {
    "iso:country":"DE",
    "sg:address":"F\u00e4rberstr. 46",
    "sg:city":"Villingen-Schwenningen",
    "sg:phone":"+49 7721/25116",
    "sg:postcode":"78050",
    "sg:province":"Baden-W\u00fcrttemberg",
    "wof:name":"Friedbert Kersten",
    "wof:placetype":"venue"
},
  "geometry": {"coordinates":[8.4593954086,48.0573883057],"type":"Point"}
}