{
  "type": "Feature",
  "properties": {
    "iso:country":"DE",
    "sg:address":"Rost\u00e4dter Str. 62",
    "sg:city":"Dreieich",
    "sg:phone":"+49 6103/64036",
    "sg:postcode":"63303",
    "sg:province":"Hessen",
    "wof:name":"Tagis-tropical-marin E. Kfr.",
    "wof:placetype":"venue"
},
  "geometry": {"coordinates":[8.686,50.012402],"type":"Point"}
}