{
  "type": "Feature",
  "properties": {
    "iso:country":"DE",
    "sg:address":"Anton-G\u00fcnther-Str. 13",
    "sg:city":"Offingen",
    "sg:phone":"+49 8224/697",
    "sg:postcode":"89362",
    "sg:province":"Bayern",
    "wof:name":"Franz Chiba",
    "wof:placetype":"venue"
},
  "geometry": {"coordinates":[10.376604,48.479927],"type":"Point"}
}