{
  "type": "Feature",
  "properties": {
    "iso:country":"DE",
    "sg:address":"Hemmelsdorfer-See",
    "sg:city":"Timmendorfer Strand",
    "sg:postcode":"23669",
    "sg:province":"Schleswig-Holstein",
    "wof:name":"Hemmelsdorfer See Bootsverleih",
    "wof:placetype":"venue"
},
  "geometry": {"coordinates":[10.7787647247,54.0001564026],"type":"Point"}
}