{
  "type": "Feature",
  "properties": {
    "iso:country":"DE",
    "sg:address":"Markt 5",
    "sg:city":"Mylau",
    "sg:phone":"+49 3765/34262",
    "sg:postcode":"08499",
    "sg:province":"Sachsen",
    "wof:name":"Hotel Meisinger",
    "wof:placetype":"venue"
},
  "geometry": {"coordinates":[12.2640390396,50.6199188232],"type":"Point"}
}