{
  "type": "Feature",
  "properties": {
    "iso:country":"DE",
    "sg:address":"K\u00f6nigstr. 34",
    "sg:city":"Stuttgart",
    "sg:phone":"+49 711/2991868",
    "sg:postcode":"70173",
    "sg:province":"Baden-W\u00fcrttemberg",
    "wof:name":"Parf\u00fcmerie Douglas S\u00fcd Gmbh & Co. Kg",
    "wof:placetype":"venue"
},
  "geometry": {"coordinates":[9.17721,48.777596],"type":"Point"}
}