{
  "type": "Feature",
  "properties": {
    "iso:country":"DE",
    "sg:address":"Fraenkelufer 2",
    "sg:city":"Berlin",
    "sg:phone":"+49 30/6151782",
    "sg:postcode":"10999",
    "sg:province":"Berlin",
    "wof:name":"Imbi\u00dfstube I. Und H. \u00dcnal",
    "wof:placetype":"venue"
},
  "geometry": {"coordinates":[13.4187803268,52.4963798523],"type":"Point"}
}