{
  "type": "Feature",
  "properties": {
    "iso:country":"DE",
    "sg:address":"Jahnstr. 17",
    "sg:city":"Eisdorf",
    "sg:postcode":"37534",
    "sg:province":"Niedersachsen",
    "wof:name":"Gemeindeb\u00fccherei",
    "wof:placetype":"venue"
},
  "geometry": {"coordinates":[10.173253,51.759506],"type":"Point"}
}