{
  "type": "Feature",
  "properties": {
    "iso:country":"DE",
    "sg:address":"Muengstener Strasse 10",
    "sg:city":"Wuppertal",
    "sg:phone":"+49 202/2581118",
    "sg:postcode":"42285",
    "sg:province":"Nordrhein-Westfalen",
    "wof:name":"Ideenreich",
    "wof:placetype":"venue"
},
  "geometry": {"coordinates":[7.189901,51.247395],"type":"Point"}
}