{
  "type": "Feature",
  "properties": {
    "iso:country":"DE",
    "sg:city":"Siefersheim",
    "sg:phone":"+49 6703/703",
    "sg:postcode":"55599",
    "sg:province":"Rheinland-Pfalz",
    "wof:name":"Johann Stumpf",
    "wof:placetype":"venue"
},
  "geometry": {"coordinates":[7.95693,49.796772],"type":"Point"}
}