{
  "type": "Feature",
  "properties": {
    "iso:country":"DE",
    "sg:address":"Stra\u00dfe der Einheit 1",
    "sg:city":"Sch\u00f6nfels",
    "sg:phone":"+49 37600/9430",
    "sg:postcode":"08115",
    "sg:province":"Sachsen",
    "wof:name":"Kaufland",
    "wof:placetype":"venue"
},
  "geometry": {"coordinates":[12.4292898178,50.6786384583],"type":"Point"}
}