{
  "type": "Feature",
  "properties": {
    "iso:country":"DE",
    "sg:address":"Keltenstr. 19",
    "sg:city":"Augsburg",
    "sg:phone":"+49 821/96040",
    "sg:postcode":"86199",
    "sg:province":"Bayern",
    "wof:name":"Azoren Bautr\u00e4ger Und Imobilien Gmbh",
    "wof:placetype":"venue"
},
  "geometry": {"coordinates":[10.871241,48.335155],"type":"Point"}
}