{
  "type": "Feature",
  "properties": {
    "iso:country":"DE",
    "sg:address":"Seestr. 2",
    "sg:city":"Seefeld",
    "sg:phone":"+49 8152/7799",
    "sg:postcode":"82229",
    "sg:province":"Bayern",
    "wof:name":"Bauunternehmung Rogorsch Gmbh",
    "wof:placetype":"venue"
},
  "geometry": {"coordinates":[11.183808,48.027935],"type":"Point"}
}