{
  "type": "Feature",
  "properties": {
    "iso:country":"DE",
    "sg:address":"Gebindstr. 4",
    "sg:city":"Caaschwitz",
    "sg:phone":"+49 4936/6058013",
    "sg:postcode":"07586",
    "sg:province":"Th\u00fcringen",
    "wof:name":"Pulako-pulverlackierungs Gmbh",
    "wof:placetype":"venue"
},
  "geometry": {"coordinates":[11.98918,50.944279],"type":"Point"}
}