{
  "type": "Feature",
  "properties": {
    "iso:country":"DE",
    "sg:address":"Sommerleite 8",
    "sg:city":"Marktrodach",
    "sg:phone":"+49 9261/4468",
    "sg:postcode":"96364",
    "sg:province":"Bayern",
    "wof:name":"Rediche Bejsla Gretel B\u00e4r",
    "wof:placetype":"venue"
},
  "geometry": {"coordinates":[11.3846559525,50.2536773682],"type":"Point"}
}