{
  "type": "Feature",
  "properties": {
    "iso:country":"DE",
    "sg:address":"Industriepark Magdeburger Str 3D",
    "sg:city":"Gommern",
    "sg:phone":"+49 39200/50068",
    "sg:postcode":"39245",
    "sg:province":"Sachsen-Anhalt",
    "wof:name":"Dr. Schulze Gmbh",
    "wof:placetype":"venue"
},
  "geometry": {"coordinates":[11.827277,52.073078],"type":"Point"}
}