{
  "type": "Feature",
  "properties": {
    "iso:country":"DE",
    "sg:address":"Hauptstra\u00dfe 51",
    "sg:city":"Kappel-Grafenhausen",
    "sg:phone":"+49 7822/866838",
    "sg:postcode":"77966",
    "sg:province":"Baden-W\u00fcrttemberg",
    "wof:name":"Glaser M. Msr Elektrotechnik Gmbh",
    "wof:placetype":"venue"
},
  "geometry": {"coordinates":[7.7632951736,48.2860717773],"type":"Point"}
}