{
  "type": "Feature",
  "properties": {
    "iso:country":"DE",
    "sg:address":"Am Ginsterberg 21",
    "sg:city":"D\u00fcsseldorf",
    "sg:phone":"+49 211/203377",
    "sg:postcode":"40627",
    "sg:province":"Nordrhein-Westfalen",
    "wof:name":"Karl Volz Gmbh & Co. Kg",
    "wof:placetype":"venue"
},
  "geometry": {"coordinates":[6.895214,51.200996],"type":"Point"}
}