{
  "type": "Feature",
  "properties": {
    "iso:country":"DE",
    "sg:address":"Rudower Chaussee 3",
    "sg:city":"Berlin",
    "sg:phone":"+49 30/677640",
    "sg:postcode":"12489",
    "sg:province":"Berlin",
    "wof:name":"Deutsches Rundfunkarchiv",
    "wof:placetype":"venue"
},
  "geometry": {"coordinates":[13.538078,52.433762],"type":"Point"}
}