{
  "type": "Feature",
  "properties": {
    "iso:country":"DE",
    "sg:address":"Ohmstr. 1",
    "sg:city":"Eutin",
    "sg:phone":"+49 4945/218070",
    "sg:postcode":"23701",
    "sg:province":"Schleswig-Holstein",
    "wof:name":"Brandes Gmbh",
    "wof:placetype":"venue"
},
  "geometry": {"coordinates":[10.6383752823,54.1250228882],"type":"Point"}
}