{
  "type": "Feature",
  "properties": {
    "iso:country":"DE",
    "sg:address":"Am Yachthafen 134",
    "sg:city":"Wittmund",
    "sg:phone":"+49 4464/942130",
    "sg:postcode":"26409",
    "sg:province":"Niedersachsen",
    "wof:name":"Reinhard Uphoff",
    "wof:placetype":"venue"
},
  "geometry": {"coordinates":[7.8057188988,53.7033042908],"type":"Point"}
}