{
  "type": "Feature",
  "properties": {
    "iso:country":"DE",
    "sg:address":"Lange Gasse 6",
    "sg:city":"Zw\u00f6nitz",
    "sg:phone":"+49 37754/2949",
    "sg:postcode":"08297",
    "sg:province":"Sachsen",
    "wof:name":"H. Meischner",
    "wof:placetype":"venue"
},
  "geometry": {"coordinates":[12.8123216629,50.6301307678],"type":"Point"}
}