{
  "type": "Feature",
  "properties": {
    "iso:country":"DE",
    "sg:address":"Fischerstr. 90",
    "sg:city":"Duisburg",
    "sg:phone":"+49 203/771749",
    "sg:postcode":"47055",
    "sg:province":"Nordrhein-Westfalen",
    "wof:name":"Apotheke Am Michaelplatz Lore Bilhuber E. Kfr.",
    "wof:placetype":"venue"
},
  "geometry": {"coordinates":[6.759467,51.402161],"type":"Point"}
}