{
  "type": "Feature",
  "properties": {
    "iso:country":"DE",
    "sg:address":"Auestr. 35",
    "sg:city":"Bebra",
    "sg:phone":"+49 6622/918183",
    "sg:postcode":"36179",
    "sg:province":"Hessen",
    "wof:name":"Erich Fritzsch Kg",
    "wof:placetype":"venue"
},
  "geometry": {"coordinates":[9.7944498062,50.9654502869],"type":"Point"}
}