{
  "type": "Feature",
  "properties": {
    "iso:country":"DE",
    "sg:address":"Kirchenstr. 4",
    "sg:city":"Eppelborn",
    "sg:phone":"+49 6806/81518",
    "sg:postcode":"66571",
    "sg:province":"Saarland",
    "wof:name":"Restaurant Die Flint",
    "wof:placetype":"venue"
},
  "geometry": {"coordinates":[6.9805140495,49.3697433472],"type":"Point"}
}