{
  "type": "Feature",
  "properties": {
    "iso:country":"DE",
    "sg:address":"Siemersweg 2",
    "sg:city":"Garrel",
    "sg:phone":"+49 4474/1276",
    "sg:postcode":"49681",
    "sg:province":"Niedersachsen",
    "wof:name":"Johannes W\u00fcbbelmann",
    "wof:placetype":"venue"
},
  "geometry": {"coordinates":[8.110345,52.972698],"type":"Point"}
}