{
  "type": "Feature",
  "properties": {
    "iso:country":"DE",
    "sg:address":"Lindenstr. 28a",
    "sg:city":"Frankfurt",
    "sg:phone":"+49 335/526181",
    "sg:postcode":"15236",
    "sg:province":"Brandenburg",
    "wof:name":"R. Wiesner",
    "wof:placetype":"venue"
},
  "geometry": {"coordinates":[14.550522,52.287827],"type":"Point"}
}