{
  "type": "Feature",
  "properties": {
    "iso:country":"DE",
    "sg:address":"Aschener Str. 19",
    "sg:city":"Diepholz",
    "sg:phone":"+49 5441/2106",
    "sg:postcode":"49356",
    "sg:province":"Niedersachsen",
    "wof:name":"L. Schneider",
    "wof:placetype":"venue"
},
  "geometry": {"coordinates":[8.35081,52.654278],"type":"Point"}
}