{
  "type": "Feature",
  "properties": {
    "iso:country":"DE",
    "sg:address":"Wiesentor 8",
    "sg:city":"Schwaneberg",
    "sg:phone":"+49 39205/20137",
    "sg:postcode":"39171",
    "sg:province":"Sachsen-Anhalt",
    "wof:name":"Gabriele Keune",
    "wof:placetype":"venue"
},
  "geometry": {"coordinates":[11.474656105,51.9979324341],"type":"Point"}
}