{
  "type": "Feature",
  "properties": {
    "iso:country":"DE",
    "sg:address":"Am M\u00fchlenrain 1",
    "sg:city":"Frammersbach",
    "sg:phone":"+49 9355/2061",
    "sg:postcode":"97833",
    "sg:province":"Bayern",
    "wof:name":"Peter Blatz",
    "wof:placetype":"venue"
},
  "geometry": {"coordinates":[9.450654,50.065628],"type":"Point"}
}