{
  "type": "Feature",
  "properties": {
    "iso:country":"DE",
    "sg:address":"Rosenheimer Str. 93",
    "sg:city":"Raubling",
    "sg:phone":"+49 8035/800",
    "sg:postcode":"83064",
    "sg:province":"Bayern",
    "wof:name":"Pwa Zellstoff- Und Holzhandels- Gmbh",
    "wof:placetype":"venue"
},
  "geometry": {"coordinates":[12.119698,47.805595],"type":"Point"}
}