{
  "type": "Feature",
  "properties": {
    "iso:country":"DE",
    "sg:address":"Gelderstr. 5",
    "sg:city":"Rheinberg",
    "sg:phone":"+49 2843/2325",
    "sg:postcode":"47495",
    "sg:province":"Nordrhein-Westfalen",
    "wof:name":"Schubert Gmbh",
    "wof:placetype":"venue"
},
  "geometry": {"coordinates":[6.6022119522,51.5450820923],"type":"Point"}
}