{
  "type": "Feature",
  "properties": {
    "iso:country":"DE",
    "sg:address":"Hauptstr. 12",
    "sg:city":"K\u00fcssaberg",
    "sg:phone":"+49 7741/2277",
    "sg:postcode":"79790",
    "sg:province":"Baden-W\u00fcrttemberg",
    "wof:name":"Restaurant \u00d6pfelbaum",
    "wof:placetype":"venue"
},
  "geometry": {"coordinates":[8.2959251404,47.6097679138],"type":"Point"}
}