{
  "type": "Feature",
  "properties": {
    "iso:country":"DE",
    "sg:address":"Lappersdorfer Str. 76",
    "sg:city":"Regensburg",
    "sg:phone":"+49 941/81850",
    "sg:postcode":"93059",
    "sg:province":"Bayern",
    "wof:name":"Berr & Schedlbauer Rost- Und Bautenschutz Gmbh",
    "wof:placetype":"venue"
},
  "geometry": {"coordinates":[12.096463,49.036575],"type":"Point"}
}