{
  "type": "Feature",
  "properties": {
    "iso:country":"DE",
    "sg:address":"Untere Hohl 6",
    "sg:city":"Waldbrunn",
    "sg:phone":"+49 6436/4978",
    "sg:postcode":"65620",
    "sg:province":"Hessen",
    "wof:name":"Leopold Zeiger",
    "wof:placetype":"venue"
},
  "geometry": {"coordinates":[8.09585,50.511822],"type":"Point"}
}