{
  "type": "Feature",
  "properties": {
    "iso:country":"DE",
    "sg:address":"Konrad-Kurzbold-Str. 6A",
    "sg:city":"Limburg",
    "sg:phone":"+49 6431/6868",
    "sg:postcode":"65549",
    "sg:province":"Hessen",
    "wof:name":"Dr. Med. Joachim Rudersdorf",
    "wof:placetype":"venue"
},
  "geometry": {"coordinates":[8.0622177124,50.3903198242],"type":"Point"}
}