{
  "type": "Feature",
  "properties": {
    "iso:country":"DE",
    "sg:address":"Danziger Str. 53",
    "sg:city":"Ludwigsburg",
    "sg:postcode":"71638",
    "sg:province":"Baden-W\u00fcrttemberg",
    "wof:name":"Michael Schreyer Gmbh",
    "wof:placetype":"venue"
},
  "geometry": {"coordinates":[9.2086286545,48.8900527954],"type":"Point"}
}