{
  "type": "Feature",
  "properties": {
    "iso:country":"DE",
    "sg:address":"Kolbstr. 28",
    "sg:city":"B\u00f6blingen",
    "sg:phone":"+49 7031/672439",
    "sg:postcode":"71034",
    "sg:province":"Baden-W\u00fcrttemberg",
    "wof:name":"Hero Hotel-und Gastst\u00e4tten- Betriebsges. Mbh",
    "wof:placetype":"venue"
},
  "geometry": {"coordinates":[8.9576816559,48.6918716431],"type":"Point"}
}