{
  "type": "Feature",
  "properties": {
    "iso:country":"DE",
    "sg:address":"Grabenstr. 12",
    "sg:city":"Sta\u00dffurt",
    "sg:phone":"+49 3925/323415",
    "sg:postcode":"39418",
    "sg:province":"Sachsen-Anhalt",
    "wof:name":"M. Prielop",
    "wof:placetype":"venue"
},
  "geometry": {"coordinates":[11.5910463333,51.8498420715],"type":"Point"}
}