{
  "type": "Feature",
  "properties": {
    "iso:country":"DE",
    "sg:address":"Kaiser-Otto-Str. 5",
    "sg:city":"Quedlinburg",
    "sg:phone":"+49 3946/779960",
    "sg:postcode":"06484",
    "sg:province":"Sachsen-Anhalt",
    "wof:name":"Apotheke Im Vitalhaus Simone Schnelle E. Kfr.",
    "wof:placetype":"venue"
},
  "geometry": {"coordinates":[11.138465,51.783985],"type":"Point"}
}