{
  "type": "Feature",
  "properties": {
    "iso:country":"DE",
    "sg:address":"Quellenweg 4",
    "sg:city":"Gilserberg",
    "sg:phone":"+49 6696/7117",
    "sg:postcode":"34630",
    "sg:province":"Hessen",
    "wof:name":"Gasthaus Quellenhof",
    "wof:placetype":"venue"
},
  "geometry": {"coordinates":[9.054564476,50.9971160889],"type":"Point"}
}