{
  "type": "Feature",
  "properties": {
    "iso:country":"DE",
    "sg:address":"Robert-Bosch-Str. 3",
    "sg:city":"Heddesheim",
    "sg:phone":"+49 6203/4805",
    "sg:postcode":"68542",
    "sg:province":"Baden-W\u00fcrttemberg",
    "wof:name":"Schulz K\u00e4lte- Und Klimatechnik Gmbh",
    "wof:placetype":"venue"
},
  "geometry": {"coordinates":[8.6285276413,49.5095901489],"type":"Point"}
}