{
  "type": "Feature",
  "properties": {
    "iso:country":"DE",
    "sg:address":"Donauw\u00f6rther Str. 71b",
    "sg:city":"Neuburg",
    "sg:phone":"+49 8431/7114",
    "sg:postcode":"86633",
    "sg:province":"Bayern",
    "wof:name":"Restaurant Asien-haus",
    "wof:placetype":"venue"
},
  "geometry": {"coordinates":[11.1695346832,48.7339134216],"type":"Point"}
}