{
  "type": "Feature",
  "properties": {
    "iso:country":"DE",
    "sg:address":"Tuxhornweg 8",
    "sg:city":"G\u00fctersloh",
    "sg:phone":"+49 5241/67201",
    "sg:postcode":"33334",
    "sg:province":"Nordrhein-Westfalen",
    "wof:name":"E. Westerhellweg",
    "wof:placetype":"venue"
},
  "geometry": {"coordinates":[8.41519,51.950901],"type":"Point"}
}