{
  "type": "Feature",
  "properties": {
    "iso:country":"DE",
    "sg:city":"Schotten",
    "sg:phone":"+49 6044/660",
    "sg:postcode":"63679",
    "sg:province":"Hessen",
    "wof:name":"Stadtarchiv",
    "wof:placetype":"venue"
},
  "geometry": {"coordinates":[9.120958,50.499378],"type":"Point"}
}