{
  "type": "Feature",
  "properties": {
    "iso:country":"DE",
    "sg:address":"Saarstr. 36",
    "sg:city":"Birkenfeld",
    "sg:phone":"+49 6782/5133",
    "sg:postcode":"55765",
    "sg:province":"Rheinland-Pfalz",
    "wof:name":"Gangolf Gmbh",
    "wof:placetype":"venue"
},
  "geometry": {"coordinates":[7.162956,49.644588],"type":"Point"}
}