{
  "type": "Feature",
  "properties": {
    "iso:country":"DE",
    "sg:address":"Karl-Prendel-Str. 33",
    "sg:city":"Garbsen",
    "sg:phone":"+49 5031/909523",
    "sg:postcode":"30826",
    "sg:province":"Niedersachsen",
    "wof:name":"Fehrn-stender Und Zeiner Architekten",
    "wof:placetype":"venue"
},
  "geometry": {"coordinates":[9.503326,52.427818],"type":"Point"}
}