{
  "type": "Feature",
  "properties": {
    "iso:country":"DE",
    "sg:address":"Kalkstr. 39",
    "sg:city":"Chemnitz",
    "sg:phone":"+49 371/306385",
    "sg:postcode":"09116",
    "sg:province":"Sachsen",
    "wof:name":"Dyckerhoff Transportbeton Chemnitz Gmbh & Co. Kg",
    "wof:placetype":"venue"
},
  "geometry": {"coordinates":[12.8657884598,50.832233429],"type":"Point"}
}