{
  "type": "Feature",
  "properties": {
    "iso:country":"DE",
    "sg:address":"Wei\u00dferlenstr 6",
    "sg:city":"Freiburg",
    "sg:phone":"+49 34601/25702",
    "sg:postcode":"79108",
    "sg:province":"Baden-W\u00fcrttemberg",
    "wof:name":"G\u00f6tze Speditions Gmbh",
    "wof:placetype":"venue"
},
  "geometry": {"coordinates":[11.7556314468,51.4595184326],"type":"Point"}
}