{
  "type": "Feature",
  "properties": {
    "iso:country":"DE",
    "sg:address":"Bosestr. 20",
    "sg:city":"Zwickau",
    "sg:phone":"+49 375/281414",
    "sg:postcode":"08056",
    "sg:province":"Sachsen",
    "wof:name":"Restaurant Levantes",
    "wof:placetype":"venue"
},
  "geometry": {"coordinates":[12.492398262,50.7216110229],"type":"Point"}
}