{
  "type": "Feature",
  "properties": {
    "iso:country":"DE",
    "sg:address":"Zum Rischanger 15",
    "sg:city":"Neustadt",
    "sg:phone":"+49 5032/5474",
    "sg:postcode":"31535",
    "sg:province":"Niedersachsen",
    "wof:name":"Leinemann Bauunternehmen Gmbh",
    "wof:placetype":"venue"
},
  "geometry": {"coordinates":[9.510105,52.552162],"type":"Point"}
}