{
  "type": "Feature",
  "properties": {
    "iso:country":"DE",
    "sg:address":"Lindenweg 4a",
    "sg:city":"Grafrath",
    "sg:phone":"+49 8144/7420",
    "sg:postcode":"82284",
    "sg:province":"Bayern",
    "wof:name":"Theo H\u00f6fter Handlungsvertreter",
    "wof:placetype":"venue"
},
  "geometry": {"coordinates":[11.1585130692,48.1278648376],"type":"Point"}
}