{
  "type": "Feature",
  "properties": {
    "iso:country":"DE",
    "sg:address":"Am Sonnenhang 6",
    "sg:city":"Coesfeld",
    "sg:phone":"+49 2541/2982",
    "sg:postcode":"48653",
    "sg:province":"Nordrhein-Westfalen",
    "wof:name":"Otto Coesfeld",
    "wof:placetype":"venue"
},
  "geometry": {"coordinates":[7.1861100197,51.9524383545],"type":"Point"}
}