{
  "type": "Feature",
  "properties": {
    "iso:country":"DE",
    "sg:address":"Hauptstr. 35",
    "sg:city":"Sche\u00dflitz",
    "sg:phone":"+49 9542/921126",
    "sg:postcode":"96110",
    "sg:province":"Bayern",
    "wof:name":"Die Reiseinsel In Sche\u00dflitz Ohg",
    "wof:placetype":"venue"
},
  "geometry": {"coordinates":[11.0331840515,49.9763412476],"type":"Point"}
}