{
  "type": "Feature",
  "properties": {
    "iso:country":"DE",
    "sg:address":"Ellerstr 101",
    "sg:city":"Hilden",
    "sg:phone":"+49 2103/55914",
    "sg:postcode":"40721",
    "sg:province":"Nordrhein-Westfalen",
    "wof:name":"Metallverarbeitung Kann Gmbh",
    "wof:placetype":"venue"
},
  "geometry": {"coordinates":[6.919416,51.171242],"type":"Point"}
}