{
  "type": "Feature",
  "properties": {
    "iso:country":"DE",
    "sg:address":"Walter-Rathenau-Str. 14",
    "sg:city":"Villingen-Schwenningen",
    "sg:phone":"+49 7720/35398",
    "sg:postcode":"78054",
    "sg:province":"Baden-W\u00fcrttemberg",
    "wof:name":"Reinhold Rudolf Mueller",
    "wof:placetype":"venue"
},
  "geometry": {"coordinates":[8.5249109268,48.0603408813],"type":"Point"}
}