{
  "type": "Feature",
  "properties": {
    "iso:country":"DE",
    "sg:address":"Kurparkallee 5",
    "sg:city":"Bad Oldesloe",
    "sg:phone":"+49 4531/176701",
    "sg:postcode":"23843",
    "sg:province":"Schleswig-Holstein",
    "wof:name":"Elvers L\u00f6her Und Link Rechtsanw\u00e4lte Und Notar",
    "wof:placetype":"venue"
},
  "geometry": {"coordinates":[10.3766441345,53.8070526123],"type":"Point"}
}