{
  "type": "Feature",
  "properties": {
    "iso:country":"DE",
    "sg:address":"Bellealliancestr. 58",
    "sg:city":"Hamburg",
    "sg:phone":"+49 40/4325760",
    "sg:postcode":"20259",
    "sg:province":"Hamburg",
    "wof:name":"Hertz & Selck",
    "wof:placetype":"venue"
},
  "geometry": {"coordinates":[9.9625167847,53.5686073303],"type":"Point"}
}