{
  "type": "Feature",
  "properties": {
    "iso:country":"DE",
    "sg:address":"Uhlandstr. 20",
    "sg:city":"Neuenb\u00fcrg",
    "sg:phone":"+49 7082/8342",
    "sg:postcode":"75305",
    "sg:province":"Baden-W\u00fcrttemberg",
    "wof:name":"Rudi Schlittenhardt Gmbh & Co. Kg",
    "wof:placetype":"venue"
},
  "geometry": {"coordinates":[8.6105117798,48.8353729248],"type":"Point"}
}