{
  "type": "Feature",
  "properties": {
    "iso:country":"DE",
    "sg:address":"Erlachstr. 14",
    "sg:city":"Zirndorf",
    "sg:phone":"+49 9127/8193",
    "sg:postcode":"90513",
    "sg:province":"Bayern",
    "wof:name":"Gefl\u00fcgelzuchtverein Zirndorf Und Umgebung",
    "wof:placetype":"venue"
},
  "geometry": {"coordinates":[10.8895654678,49.4210853577],"type":"Point"}
}