{
  "type": "Feature",
  "properties": {
    "iso:country":"DE",
    "sg:address":"Am Sonnenplan 5",
    "sg:city":"Niedercunnersdorf",
    "sg:phone":"+49 35875/62730",
    "sg:postcode":"02708",
    "sg:province":"Sachsen",
    "wof:name":"Moto-in Gmbh",
    "wof:placetype":"venue"
},
  "geometry": {"coordinates":[14.665395,51.047497],"type":"Point"}
}