{
  "type": "Feature",
  "properties": {
    "iso:country":"DE",
    "sg:address":"Oststr. 46",
    "sg:city":"Hamm",
    "sg:phone":"+49 2381/25087",
    "sg:postcode":"59065",
    "sg:province":"Nordrhein-Westfalen",
    "wof:name":"Franz Kallerhoff",
    "wof:placetype":"venue"
},
  "geometry": {"coordinates":[7.823879,51.682632],"type":"Point"}
}