{
  "type": "Feature",
  "properties": {
    "iso:country":"DE",
    "sg:address":"Pillnitzer Landstr. 148",
    "sg:city":"Dresden",
    "sg:phone":"+49 3591/5480",
    "sg:postcode":"01326",
    "sg:province":"Sachsen",
    "wof:name":"Markant Schreibger\u00e4te Gmbh",
    "wof:placetype":"venue"
},
  "geometry": {"coordinates":[13.830387,51.037704],"type":"Point"}
}