{
  "type": "Feature",
  "properties": {
    "iso:country":"DE",
    "sg:address":"Staufenstr. 6",
    "sg:city":"Denkendorf",
    "sg:phone":"+49 711/3464467",
    "sg:postcode":"73770",
    "sg:province":"Baden-W\u00fcrttemberg",
    "wof:name":"Gernot Sch\u00f6nhaar Architekt",
    "wof:placetype":"venue"
},
  "geometry": {"coordinates":[9.313849,48.700584],"type":"Point"}
}