{
  "type": "Feature",
  "properties": {
    "iso:country":"DE",
    "sg:address":"Bayernwerk 8",
    "sg:city":"Schwandorf",
    "sg:phone":"+49 9431/7510",
    "sg:postcode":"92421",
    "sg:province":"Bayern",
    "wof:name":"Schmack Biogas Ag",
    "wof:placetype":"venue"
},
  "geometry": {"coordinates":[12.108527,49.327663],"type":"Point"}
}