{
  "type": "Feature",
  "properties": {
    "iso:country":"DE",
    "sg:address":"Steigerwaldstr. 1",
    "sg:city":"Geiselwind",
    "sg:phone":"+49 9556/558",
    "sg:postcode":"96160",
    "sg:province":"Bayern",
    "wof:name":"R. Br\u00e4utigam",
    "wof:placetype":"venue"
},
  "geometry": {"coordinates":[10.47315,49.773594],"type":"Point"}
}