{
  "type": "Feature",
  "properties": {
    "iso:country":"DE",
    "sg:address":"Talstr. 80",
    "sg:city":"Saarbr\u00fccken",
    "sg:phone":"+49 681/581087",
    "sg:postcode":"66119",
    "sg:province":"Saarland",
    "wof:name":"Mina Adjdadi",
    "wof:placetype":"venue"
},
  "geometry": {"coordinates":[6.9999442101,49.2247200012],"type":"Point"}
}