{
  "type": "Feature",
  "properties": {
    "iso:country":"DE",
    "sg:address":"Albert-Schweitzer-Str. 35",
    "sg:city":"L\u00f6hne",
    "sg:phone":"+49 5732/10120",
    "sg:postcode":"32584",
    "sg:province":"Nordrhein-Westfalen",
    "wof:name":"Reiseb\u00fcro Ernstmeier Gmbh & Co. Kg",
    "wof:placetype":"venue"
},
  "geometry": {"coordinates":[8.7268629074,52.201587677],"type":"Point"}
}