{
  "type": "Feature",
  "properties": {
    "iso:country":"DE",
    "sg:address":"Langenhagener Str. 42",
    "sg:city":"Langenhagen",
    "sg:phone":"+49 511/789639",
    "sg:postcode":"30855",
    "sg:province":"Niedersachsen",
    "wof:name":"Helmut Bruns",
    "wof:placetype":"venue"
},
  "geometry": {"coordinates":[9.6813602448,52.4408531189],"type":"Point"}
}