{
  "type": "Feature",
  "properties": {
    "iso:country":"DE",
    "sg:address":"Glafeystr. 21a",
    "sg:city":"Leipzig",
    "sg:postcode":"04299",
    "sg:province":"Sachsen",
    "wof:name":"Tennispark Zwenkau Gmbh",
    "wof:placetype":"venue"
},
  "geometry": {"coordinates":[12.4203739166,51.3204498291],"type":"Point"}
}