{
  "type": "Feature",
  "properties": {
    "iso:country":"DE",
    "sg:address":"K\u00f6nigstr. 40",
    "sg:city":"Bad Bergzabern",
    "sg:phone":"+49 6343/1526",
    "sg:postcode":"76887",
    "sg:province":"Rheinland-Pfalz",
    "wof:name":"Sanit\u00e4tshaus R\u00f6mer Orthop\u00e4die-technik-schuhtechni",
    "wof:placetype":"venue"
},
  "geometry": {"coordinates":[7.9980568886,49.1023330688],"type":"Point"}
}