{
  "type": "Feature",
  "properties": {
    "iso:country":"DE",
    "sg:address":"Gnesener Str. 35",
    "sg:city":"Mannheim",
    "sg:phone":"+49 621/782565",
    "sg:postcode":"68307",
    "sg:province":"Baden-W\u00fcrttemberg",
    "wof:name":"Messner",
    "wof:placetype":"venue"
},
  "geometry": {"coordinates":[8.475082,49.541714],"type":"Point"}
}