{
  "type": "Feature",
  "properties": {
    "iso:country":"DE",
    "sg:address":"Hubertusweg 2",
    "sg:city":"Br\u00fcggen",
    "sg:phone":"+49 2157/909005",
    "sg:postcode":"41379",
    "sg:province":"Nordrhein-Westfalen",
    "wof:name":"Hans-dieter Krosse",
    "wof:placetype":"venue"
},
  "geometry": {"coordinates":[6.1865549088,51.2829551697],"type":"Point"}
}