{
  "type": "Feature",
  "properties": {
    "iso:country":"DE",
    "sg:address":"Karlsbader Str. 10",
    "sg:city":"Neuburg",
    "sg:phone":"+49 8431/8663",
    "sg:postcode":"86633",
    "sg:province":"Bayern",
    "wof:name":"Sigmund Hagl Architekt",
    "wof:placetype":"venue"
},
  "geometry": {"coordinates":[11.20463,48.745602],"type":"Point"}
}