{
  "type": "Feature",
  "properties": {
    "iso:country":"DE",
    "sg:address":"Werner-von-Siemens-Str. 14",
    "sg:city":"Neu Wulmstorf",
    "sg:postcode":"21629",
    "sg:province":"Niedersachsen",
    "wof:name":"Fliesen-berliner Inh. Michale Berliner E. Kfm.",
    "wof:placetype":"venue"
},
  "geometry": {"coordinates":[9.77184,53.46611],"type":"Point"}
}