{
  "type": "Feature",
  "properties": {
    "iso:country":"DE",
    "sg:address":"Stader Str. 50",
    "sg:city":"Buxtehude",
    "sg:phone":"+49 4161/713801",
    "sg:postcode":"21614",
    "sg:province":"Niedersachsen",
    "wof:name":"Funk Elektroanlagen Und Sicherheitstechnik Gmbh",
    "wof:placetype":"venue"
},
  "geometry": {"coordinates":[9.679948,53.469341],"type":"Point"}
}