{
  "type": "Feature",
  "properties": {
    "iso:country":"DE",
    "sg:address":"Trifelsstr. 4",
    "sg:city":"Knittelsheim",
    "sg:phone":"+49 6348/919526",
    "sg:postcode":"76879",
    "sg:province":"Rheinland-Pfalz",
    "wof:name":"Reno Kunststoff- Produkte Gmbh",
    "wof:placetype":"venue"
},
  "geometry": {"coordinates":[8.250187,49.196018],"type":"Point"}
}