{
  "type": "Feature",
  "properties": {
    "iso:country":"DE",
    "sg:address":"Alte Pfarrgasse 4",
    "sg:city":"Ober-Olm",
    "sg:phone":"+49 6136/99460",
    "sg:postcode":"55270",
    "sg:province":"Rheinland-Pfalz",
    "wof:name":"Bst Becker Studio Technik Gmbh",
    "wof:placetype":"venue"
},
  "geometry": {"coordinates":[8.1905975342,49.9370231628],"type":"Point"}
}