{
  "type": "Feature",
  "properties": {
    "iso:country":"DE",
    "sg:address":"Ingolst\u00e4dter Str. 21",
    "sg:city":"Schrobenhausen",
    "sg:phone":"+49 8252/2630",
    "sg:postcode":"86529",
    "sg:province":"Bayern",
    "wof:name":"Max Sailer",
    "wof:placetype":"venue"
},
  "geometry": {"coordinates":[11.278694,48.567616],"type":"Point"}
}