{
  "type": "Feature",
  "properties": {
    "iso:country":"DE",
    "sg:address":"Rosenpl\u00fctstr. 19",
    "sg:city":"N\u00fcrnberg",
    "sg:phone":"+49 911/262060",
    "sg:postcode":"90439",
    "sg:province":"Bayern",
    "wof:name":"J. Petzoldt",
    "wof:placetype":"venue"
},
  "geometry": {"coordinates":[11.0510129929,49.4441184998],"type":"Point"}
}