{
  "type": "Feature",
  "properties": {
    "iso:country":"DE",
    "sg:address":"Hansaplatz 1",
    "sg:city":"Hamburg",
    "sg:postcode":"20099",
    "sg:province":"Hamburg",
    "wof:name":"A Muse Add Christian Thomas Gmbh",
    "wof:placetype":"venue"
},
  "geometry": {"coordinates":[10.012611,53.554485],"type":"Point"}
}