{
  "type": "Feature",
  "properties": {
    "iso:country":"DE",
    "sg:address":"Colonnaden 72",
    "sg:city":"Hamburg",
    "sg:postcode":"20354",
    "sg:province":"Hamburg",
    "wof:name":"Albus Xlvi Sechsundvierzigste Betriebs- Und Beteiligungs-",
    "wof:placetype":"venue"
},
  "geometry": {"coordinates":[9.990409,53.556984],"type":"Point"}
}