{
  "type": "Feature",
  "properties": {
    "iso:country":"DE",
    "sg:address":"Lange Str. 54",
    "sg:city":"Viersen",
    "sg:phone":"+49 2162/58832",
    "sg:postcode":"41751",
    "sg:province":"Nordrhein-Westfalen",
    "wof:name":"Hotel D\u00fclkener Hof",
    "wof:placetype":"venue"
},
  "geometry": {"coordinates":[6.3325991631,51.2510261536],"type":"Point"}
}