{
  "type": "Feature",
  "properties": {
    "iso:country":"DE",
    "sg:address":"Eichlesstr. 14",
    "sg:city":"Langenau",
    "sg:phone":"+49 7345/7165",
    "sg:postcode":"89129",
    "sg:province":"Baden-W\u00fcrttemberg",
    "wof:name":"K. Raff Immobilienmakler",
    "wof:placetype":"venue"
},
  "geometry": {"coordinates":[10.1389694214,48.5054244995],"type":"Point"}
}