{
  "type": "Feature",
  "properties": {
    "iso:country":"DE",
    "sg:address":"Butendieksweg",
    "sg:city":"Cuxhaven",
    "sg:phone":"+49 4721/61152",
    "sg:postcode":"27476",
    "sg:province":"Niedersachsen",
    "wof:name":"Schmidt Mineral\u00f6l Gmbh",
    "wof:placetype":"venue"
},
  "geometry": {"coordinates":[8.580563,53.844196],"type":"Point"}
}