{
  "type": "Feature",
  "properties": {
    "iso:country":"DE",
    "sg:address":"Robert-Koch-Str. 2",
    "sg:city":"Stutensee",
    "sg:phone":"+49 7249/6103",
    "sg:postcode":"76297",
    "sg:province":"Baden-W\u00fcrttemberg",
    "wof:name":"Friedrich-magnus-apotheke",
    "wof:placetype":"venue"
},
  "geometry": {"coordinates":[8.482887,49.103458],"type":"Point"}
}