{
  "type": "Feature",
  "properties": {
    "iso:country":"DE",
    "sg:address":"Zum Burgh\u00fcgel 6",
    "sg:city":"Wallenhorst",
    "sg:phone":"+49 5407/6151",
    "sg:postcode":"49134",
    "sg:province":"Niedersachsen",
    "wof:name":"Ruller Hof We\u00dfling Kg",
    "wof:placetype":"venue"
},
  "geometry": {"coordinates":[8.066876,52.339928],"type":"Point"}
}