{
  "type": "Feature",
  "properties": {
    "iso:country":"DE",
    "sg:address":"Breitenstr. 1",
    "sg:city":"Bad Hersfeld",
    "sg:phone":"+49 6621/14982",
    "sg:postcode":"36251",
    "sg:province":"Hessen",
    "wof:name":"Venezia",
    "wof:placetype":"venue"
},
  "geometry": {"coordinates":[9.708762,50.868519],"type":"Point"}
}