{
  "type": "Feature",
  "properties": {
    "iso:country":"DE",
    "sg:address":"Westerwaldstr. 203",
    "sg:city":"Hennef",
    "sg:phone":"+49 2248/2600",
    "sg:postcode":"53773",
    "sg:province":"Nordrhein-Westfalen",
    "wof:name":"Siegfried Hastrich",
    "wof:placetype":"venue"
},
  "geometry": {"coordinates":[7.370674,50.728809],"type":"Point"}
}