{
  "type": "Feature",
  "properties": {
    "iso:country":"DE",
    "sg:address":"Industriestr.",
    "sg:city":"Zeven",
    "sg:phone":"+49 4281/72525",
    "sg:postcode":"27404",
    "sg:province":"Niedersachsen",
    "wof:name":"Milch-handel & Transport Elbe-weser Gmbh",
    "wof:placetype":"venue"
},
  "geometry": {"coordinates":[9.3145418167,53.2810668945],"type":"Point"}
}