{
  "type": "Feature",
  "properties": {
    "iso:country":"DE",
    "sg:address":"Schulstr. 26",
    "sg:city":"Schmalkalden",
    "sg:postcode":"98574",
    "sg:province":"Th\u00fcringen",
    "wof:name":"M. Ellschl\u00e4ger Immobilienmakler",
    "wof:placetype":"venue"
},
  "geometry": {"coordinates":[10.4622011185,50.7221221924],"type":"Point"}
}