{
  "type": "Feature",
  "properties": {
    "iso:country":"DE",
    "sg:address":"Nistergasse 6",
    "sg:city":"Frankfurt",
    "sg:phone":"+49 69/589408",
    "sg:postcode":"60439",
    "sg:province":"Hessen",
    "wof:name":"Stamm Schreinerei Und Glaserei Gmbh",
    "wof:placetype":"venue"
},
  "geometry": {"coordinates":[8.649098,50.159256],"type":"Point"}
}