{
  "type": "Feature",
  "properties": {
    "iso:country":"DE",
    "sg:address":"Stra\u00dfe der Einheit 2",
    "sg:city":"Eckstedt",
    "sg:phone":"+49 36371/883",
    "sg:postcode":"99195",
    "sg:province":"Th\u00fcringen",
    "wof:name":"H. Stepputtis",
    "wof:placetype":"venue"
},
  "geometry": {"coordinates":[11.149054,51.070015],"type":"Point"}
}