{
  "type": "Feature",
  "properties": {
    "iso:country":"DE",
    "sg:address":"Pestalozzistr. 1",
    "sg:city":"Koblenz",
    "sg:phone":"+49 261/403491",
    "sg:postcode":"56073",
    "sg:province":"Rheinland-Pfalz",
    "wof:name":"Thiele Gmbh",
    "wof:placetype":"venue"
},
  "geometry": {"coordinates":[7.578577,50.355976],"type":"Point"}
}