{
  "type": "Feature",
  "properties": {
    "iso:country":"DE",
    "sg:address":"Reeser Str. 384",
    "sg:city":"Emmerich",
    "sg:phone":"+49 2822/80466",
    "sg:postcode":"46446",
    "sg:province":"Nordrhein-Westfalen",
    "wof:name":"Restaurant Heering Gmbh",
    "wof:placetype":"venue"
},
  "geometry": {"coordinates":[6.3164978027,51.8268318176],"type":"Point"}
}