{
  "type": "Feature",
  "properties": {
    "iso:country":"DE",
    "sg:address":"Kopernikusstr. 7",
    "sg:city":"Hildesheim",
    "sg:phone":"+49 5121/264189",
    "sg:postcode":"31139",
    "sg:province":"Niedersachsen",
    "wof:name":"Josef Schnabl",
    "wof:placetype":"venue"
},
  "geometry": {"coordinates":[9.942621,52.129395],"type":"Point"}
}