{
  "type": "Feature",
  "properties": {
    "iso:country":"DE",
    "sg:address":"Hochstr. 16",
    "sg:city":"Aldorf",
    "sg:phone":"+49 871/33258",
    "sg:postcode":"84034",
    "sg:province":"Bayern",
    "wof:name":"Sparkasse Landshut",
    "wof:placetype":"venue"
},
  "geometry": {"coordinates":[-113.986084,40.039284],"type":"Point"}
}