{
  "type": "Feature",
  "properties": {
    "iso:country":"DE",
    "sg:address":"Gerberstr. 6",
    "sg:city":"Trier",
    "sg:phone":"+49 651/970470",
    "sg:postcode":"54290",
    "sg:province":"Rheinland-Pfalz",
    "wof:name":"Fritz Krieger Gmbh & Co. Kg Zweigniederlassung Trier",
    "wof:placetype":"venue"
},
  "geometry": {"coordinates":[6.6392631531,49.749004364],"type":"Point"}
}