{
  "type": "Feature",
  "properties": {
    "iso:country":"DE",
    "sg:address":"Gerolfinger Str. 115",
    "sg:city":"Ingolstadt",
    "sg:phone":"+49 841/41756",
    "sg:postcode":"85049",
    "sg:province":"Bayern",
    "wof:name":"Raum Und Design Margit Schwarz E. K.",
    "wof:placetype":"venue"
},
  "geometry": {"coordinates":[11.395098,48.764317],"type":"Point"}
}