{
  "type": "Feature",
  "properties": {
    "iso:country":"DE",
    "sg:address":"Feldm\u00fchlenweg 43",
    "sg:city":"Soest",
    "sg:phone":"+49 2921/13365",
    "sg:postcode":"59494",
    "sg:province":"Nordrhein-Westfalen",
    "wof:name":"R. Herlitzius Immobilienmakler",
    "wof:placetype":"venue"
},
  "geometry": {"coordinates":[8.0970287323,51.5774536133],"type":"Point"}
}