{
  "type": "Feature",
  "properties": {
    "iso:country":"DE",
    "sg:address":"Breiter Weg 4",
    "sg:city":"Meschede",
    "sg:phone":"+49 2903/558",
    "sg:postcode":"59872",
    "sg:province":"Nordrhein-Westfalen",
    "wof:name":"Josef Folle",
    "wof:placetype":"venue"
},
  "geometry": {"coordinates":[8.172669,51.374371],"type":"Point"}
}