{
  "type": "Feature",
  "properties": {
    "iso:country":"DE",
    "sg:address":"Horstdyk 10",
    "sg:city":"Krefeld",
    "sg:phone":"+49 2151/761279",
    "sg:postcode":"47803",
    "sg:province":"Nordrhein-Westfalen",
    "wof:name":"Interweb Design",
    "wof:placetype":"venue"
},
  "geometry": {"coordinates":[6.543721199,51.3516044617],"type":"Point"}
}