{
  "type": "Feature",
  "properties": {
    "iso:country":"DE",
    "sg:address":"Am Fischerbreuel 6",
    "sg:city":"D\u00fcsseldorf",
    "sg:postcode":"40489",
    "sg:province":"Nordrhein-Westfalen",
    "wof:name":"Immobilien D\u00fcsseldorf",
    "wof:placetype":"venue"
},
  "geometry": {"coordinates":[6.775537,51.326775],"type":"Point"}
}