{
  "type": "Feature",
  "properties": {
    "iso:country":"DE",
    "sg:address":"Gabelsbergerstr. 50",
    "sg:city":"Wetzlar",
    "sg:phone":"+49 6441/93880",
    "sg:postcode":"35576",
    "sg:province":"Hessen",
    "wof:name":"Karl-heinz Arnold Fleischhandel Gmbh",
    "wof:placetype":"venue"
},
  "geometry": {"coordinates":[8.5058097839,50.5693321228],"type":"Point"}
}