{
  "type": "Feature",
  "properties": {
    "iso:country":"DE",
    "sg:address":"Steinstr. 27",
    "sg:city":"Bad Oeynhausen",
    "sg:phone":"+49 5731/21295",
    "sg:postcode":"32547",
    "sg:province":"Nordrhein-Westfalen",
    "wof:name":"Karl P\u00f6nninghaus Lvm Versicherungen",
    "wof:placetype":"venue"
},
  "geometry": {"coordinates":[8.805932045,52.2039413452],"type":"Point"}
}