{
  "type": "Feature",
  "properties": {
    "iso:country":"DE",
    "sg:address":"Sandrartstr. 24",
    "sg:city":"M\u00fcnchen",
    "sg:phone":"+49 89/5469649",
    "sg:postcode":"80687",
    "sg:province":"Bayern",
    "wof:name":"Hollywood Nails",
    "wof:placetype":"venue"
},
  "geometry": {"coordinates":[11.506942749,48.1401405334],"type":"Point"}
}