{
  "type": "Feature",
  "properties": {
    "iso:country":"DE",
    "sg:address":"Heinrich-Sch\u00fctz-Str. 13",
    "sg:city":"Chemnitz",
    "sg:phone":"+49 371/4449071",
    "sg:postcode":"09130",
    "sg:province":"Sachsen",
    "wof:name":"Mega K\u00fcchenmarkt Gmbh",
    "wof:placetype":"venue"
},
  "geometry": {"coordinates":[12.9448509216,50.84116745],"type":"Point"}
}