{
  "type": "Feature",
  "properties": {
    "iso:country":"DE",
    "sg:address":"Uhlbergstr. 27",
    "sg:city":"Aichtal",
    "sg:phone":"+49 7127/51010",
    "sg:postcode":"72631",
    "sg:province":"Baden-W\u00fcrttemberg",
    "wof:name":"Helene Weinmann Immobilienmaklerin",
    "wof:placetype":"venue"
},
  "geometry": {"coordinates":[9.2416496277,48.6332054138],"type":"Point"}
}