{
  "type": "Feature",
  "properties": {
    "iso:country":"DE",
    "sg:address":"Wielandstr. 6",
    "sg:city":"H\u00fcffenhardt",
    "sg:phone":"+49 6268/300",
    "sg:postcode":"74928",
    "sg:province":"Baden-W\u00fcrttemberg",
    "wof:name":"Josef Kaltwasser",
    "wof:placetype":"venue"
},
  "geometry": {"coordinates":[9.0768718719,49.2902030945],"type":"Point"}
}