{
  "type": "Feature",
  "properties": {
    "iso:country":"DE",
    "sg:address":"Celsiusstr. 5",
    "sg:city":"Landsberg",
    "sg:phone":"+49 8191/927911",
    "sg:postcode":"86899",
    "sg:province":"Bayern",
    "wof:name":"Ess Elektro-service Gmbh",
    "wof:placetype":"venue"
},
  "geometry": {"coordinates":[10.85126,48.066719],"type":"Point"}
}