{
  "type": "Feature",
  "properties": {
    "iso:country":"DE",
    "sg:address":"Strandstr. 39",
    "sg:city":"K\u00fchlungsborn",
    "sg:phone":"+49 38293/7425",
    "sg:postcode":"18225",
    "sg:province":"Mecklenburg-Vorpommern",
    "wof:name":"Wei\u00dfe & Co. Gmbh",
    "wof:placetype":"venue"
},
  "geometry": {"coordinates":[11.7588996887,54.1503944397],"type":"Point"}
}