{
  "type": "Feature",
  "properties": {
    "iso:country":"DE",
    "sg:address":"Niederwaldstr. 17",
    "sg:city":"R\u00fcdesheim am Rhein",
    "sg:phone":"+49 6722/4430",
    "sg:postcode":"65385",
    "sg:province":"Hessen",
    "wof:name":"Max Und Moritz-schenke",
    "wof:placetype":"venue"
},
  "geometry": {"coordinates":[7.9251971245,49.9809036255],"type":"Point"}
}