{
  "type": "Feature",
  "properties": {
    "iso:country":"DE",
    "sg:address":"Hauptstr. 17",
    "sg:city":"Hohentengen",
    "sg:phone":"+49 7742/2750",
    "sg:postcode":"79801",
    "sg:province":"Baden-W\u00fcrttemberg",
    "wof:name":"Demelius Design Gmbh",
    "wof:placetype":"venue"
},
  "geometry": {"coordinates":[8.436290741,47.5707740784],"type":"Point"}
}