{
  "type": "Feature",
  "properties": {
    "iso:country":"DE",
    "sg:address":"Karlstr. 40",
    "sg:city":"Tuttlingen",
    "sg:phone":"+49 7461/79179",
    "sg:postcode":"78532",
    "sg:province":"Baden-W\u00fcrttemberg",
    "wof:name":"Karin Bacher",
    "wof:placetype":"venue"
},
  "geometry": {"coordinates":[8.814801,47.981789],"type":"Point"}
}