{
  "type": "Feature",
  "properties": {
    "iso:country":"DE",
    "sg:address":"Gottsackerweg 9",
    "sg:city":"M\u00fcllheim",
    "sg:phone":"+49 7631/2016",
    "sg:postcode":"79379",
    "sg:province":"Baden-W\u00fcrttemberg",
    "wof:name":"Heinz Schwab Bildhauer",
    "wof:placetype":"venue"
},
  "geometry": {"coordinates":[7.6457190514,47.8087425232],"type":"Point"}
}