{
  "type": "Feature",
  "properties": {
    "iso:country":"DE",
    "sg:address":"Werkhausgasse 1a",
    "sg:city":"Bretten",
    "sg:phone":"+49 7252/2148",
    "sg:postcode":"75015",
    "sg:province":"Baden-W\u00fcrttemberg",
    "wof:name":"K. Br\u00e4uning",
    "wof:placetype":"venue"
},
  "geometry": {"coordinates":[8.70597,49.035187],"type":"Point"}
}