{
  "type": "Feature",
  "properties": {
    "iso:country":"DE",
    "sg:address":"Gaimersheimer Str. 40",
    "sg:city":"Ingolstadt",
    "sg:phone":"+49 841/4574",
    "sg:postcode":"85057",
    "sg:province":"Bayern",
    "wof:name":"Nordstern",
    "wof:placetype":"venue"
},
  "geometry": {"coordinates":[11.4105072021,48.7742347717],"type":"Point"}
}