{
  "type": "Feature",
  "properties": {
    "iso:country":"DE",
    "sg:address":"Karl-Friedrich-Str. 100",
    "sg:city":"Bochum",
    "sg:phone":"+49 234/470582",
    "sg:postcode":"44795",
    "sg:province":"Nordrhein-Westfalen",
    "wof:name":"Ernst Roland Mees Und Christine Stamm",
    "wof:placetype":"venue"
},
  "geometry": {"coordinates":[7.210003,51.440807],"type":"Point"}
}