{
  "type": "Feature",
  "properties": {
    "iso:country":"DE",
    "sg:address":"Neuenhauser Str. 28",
    "sg:city":"Overath",
    "sg:phone":"+49 2206/6344",
    "sg:postcode":"51491",
    "sg:province":"Nordrhein-Westfalen",
    "wof:name":"Michael Kl\u00fcpfel",
    "wof:placetype":"venue"
},
  "geometry": {"coordinates":[7.2495908737,50.9400100708],"type":"Point"}
}