{
  "type": "Feature",
  "properties": {
    "iso:country":"DE",
    "sg:address":"Bahnhofstr. 11",
    "sg:city":"Detzem",
    "sg:phone":"+49 6507/3501",
    "sg:postcode":"54340",
    "sg:province":"Rheinland-Pfalz",
    "wof:name":"Erich Esch",
    "wof:placetype":"venue"
},
  "geometry": {"coordinates":[6.8464012146,49.8248596191],"type":"Point"}
}