{
  "type": "Feature",
  "properties": {
    "iso:country":"DE",
    "sg:address":"Lindenstr. 5",
    "sg:city":"Neustadt",
    "sg:phone":"+49 5032/94488",
    "sg:postcode":"31535",
    "sg:province":"Niedersachsen",
    "wof:name":"Huk-coburg Kundendienstb\u00fcro",
    "wof:placetype":"venue"
},
  "geometry": {"coordinates":[8.2019538879,47.9220046997],"type":"Point"}
}