{
  "type": "Feature",
  "properties": {
    "iso:country":"DE",
    "sg:address":"R\u00f6merstr. 38",
    "sg:city":"Pollenfeld",
    "sg:phone":"+49 8421/8755",
    "sg:postcode":"85131",
    "sg:province":"Bayern",
    "wof:name":"Anton K\u00f6gler",
    "wof:placetype":"venue"
},
  "geometry": {"coordinates":[11.202207,48.918907],"type":"Point"}
}