{
  "type": "Feature",
  "properties": {
    "iso:country":"DE",
    "sg:address":"Torstr. 3",
    "sg:city":"Sulz",
    "sg:phone":"+49 7454/2329",
    "sg:postcode":"72172",
    "sg:province":"Baden-W\u00fcrttemberg",
    "wof:name":"Paul Frick",
    "wof:placetype":"venue"
},
  "geometry": {"coordinates":[8.632921,48.362354],"type":"Point"}
}