{
  "type": "Feature",
  "properties": {
    "iso:country":"DE",
    "sg:address":"Badenstedter Str. 178",
    "sg:city":"Hannover",
    "sg:phone":"+49 511/494171",
    "sg:postcode":"30455",
    "sg:province":"Niedersachsen",
    "wof:name":"Siegfried Hennersdorf",
    "wof:placetype":"venue"
},
  "geometry": {"coordinates":[9.6756668091,52.3568763733],"type":"Point"}
}