{
  "type": "Feature",
  "properties": {
    "iso:country":"DE",
    "sg:address":"Am Schaumberg 1",
    "sg:city":"Tholey",
    "sg:phone":"+49 6853/2275",
    "sg:postcode":"66636",
    "sg:province":"Saarland",
    "wof:name":"Herbert Wahlen",
    "wof:placetype":"venue"
},
  "geometry": {"coordinates":[7.035965,49.483925],"type":"Point"}
}