{
  "type": "Feature",
  "properties": {
    "iso:country":"DE",
    "sg:address":"Wilhelmstr. 15",
    "sg:city":"Diez",
    "sg:phone":"+49 6432/2309",
    "sg:postcode":"65582",
    "sg:province":"Rheinland-Pfalz",
    "wof:name":"H. Stillger & Sohn",
    "wof:placetype":"venue"
},
  "geometry": {"coordinates":[8.011156,50.37162],"type":"Point"}
}