{
  "type": "Feature",
  "properties": {
    "iso:country":"DE",
    "sg:address":"Sontumer Str 7",
    "sg:city":"Velbert",
    "sg:phone":"+49 2051/22277",
    "sg:postcode":"42551",
    "sg:province":"Nordrhein-Westfalen",
    "wof:name":"Paul Overhamm Gmbh",
    "wof:placetype":"venue"
},
  "geometry": {"coordinates":[7.0542669296,51.3340263367],"type":"Point"}
}