{
  "type": "Feature",
  "properties": {
    "iso:country":"DE",
    "sg:address":"Lange \u00c4cker 2",
    "sg:city":"Backnang",
    "sg:phone":"+49 7191/952700",
    "sg:postcode":"71522",
    "sg:province":"Baden-W\u00fcrttemberg",
    "wof:name":"Feuchter-interplan",
    "wof:placetype":"venue"
},
  "geometry": {"coordinates":[9.4425888062,48.9339675903],"type":"Point"}
}