{
  "type": "Feature",
  "properties": {
    "iso:country":"DE",
    "sg:address":"Birther Str. 57",
    "sg:city":"Velbert",
    "sg:phone":"+49 2051/602770",
    "sg:postcode":"42549",
    "sg:province":"Nordrhein-Westfalen",
    "wof:name":"Eiscafe Bistro",
    "wof:placetype":"venue"
},
  "geometry": {"coordinates":[7.011339,51.339855],"type":"Point"}
}