{
  "type": "Feature",
  "properties": {
    "iso:country":"DE",
    "sg:address":"Bahnhofstr. 36",
    "sg:city":"Lathen",
    "sg:phone":"+49 5933/8887",
    "sg:postcode":"49762",
    "sg:province":"Niedersachsen",
    "wof:name":"Gasthaus Hans Klasen",
    "wof:placetype":"venue"
},
  "geometry": {"coordinates":[7.3222579956,52.8599357605],"type":"Point"}
}