{
  "type": "Feature",
  "properties": {
    "iso:country":"DE",
    "sg:address":"Bildst\u00f6ckleweg 3",
    "sg:city":"Baiersbronn",
    "sg:phone":"+49 7442/2818",
    "sg:postcode":"72270",
    "sg:province":"Baden-W\u00fcrttemberg",
    "wof:name":"Hermann Eberhardt",
    "wof:placetype":"venue"
},
  "geometry": {"coordinates":[8.36999,48.507057],"type":"Point"}
}