{
  "type": "Feature",
  "properties": {
    "iso:country":"DE",
    "sg:address":"Maximilianstrasse 10",
    "sg:city":"Mannheim",
    "sg:phone":"+49 228/93631717",
    "sg:postcode":"68165",
    "sg:province":"Baden-W\u00fcrttemberg",
    "wof:name":"T-mobile International Ag & Co. Kg",
    "wof:placetype":"venue"
},
  "geometry": {"coordinates":[7.1441111565,50.7224311829],"type":"Point"}
}