{
  "type": "Feature",
  "properties": {
    "iso:country":"DE",
    "sg:address":"Hafengrenzweg 1",
    "sg:city":"M\u00fcnster",
    "sg:postcode":"48155",
    "sg:province":"Nordrhein-Westfalen",
    "wof:name":"Claudia Bartels",
    "wof:placetype":"venue"
},
  "geometry": {"coordinates":[7.6422147751,51.9483566284],"type":"Point"}
}