{
  "type": "Feature",
  "properties": {
    "iso:country":"DE",
    "sg:address":"Burgstr. 7",
    "sg:city":"Dinklage",
    "sg:phone":"+49 4443/961227",
    "sg:postcode":"49413",
    "sg:province":"Niedersachsen",
    "wof:name":"Foto-h\u00f6lzen & Strehler Gmbh",
    "wof:placetype":"venue"
},
  "geometry": {"coordinates":[8.1253023148,52.6608047485],"type":"Point"}
}