{
  "type": "Feature",
  "properties": {
    "iso:country":"DE",
    "sg:address":"Eppendorfer Weg 163",
    "sg:city":"Hamburg",
    "sg:postcode":"20253",
    "sg:province":"Hamburg",
    "wof:name":"Open One Gmbh",
    "wof:placetype":"venue"
},
  "geometry": {"coordinates":[9.9654655457,53.5792617798],"type":"Point"}
}