{
  "type": "Feature",
  "properties": {
    "iso:country":"DE",
    "sg:address":"Hofmarkstr. 15 a",
    "sg:city":"Aicha",
    "sg:phone":"+49 8544/8734",
    "sg:postcode":"94529",
    "sg:province":"Bayern",
    "wof:name":"Josef Schneider",
    "wof:placetype":"venue"
},
  "geometry": {"coordinates":[11.1902971268,48.4279441833],"type":"Point"}
}