{
  "type": "Feature",
  "properties": {
    "iso:country":"DE",
    "sg:address":"Dr.-Schumacher-Str. 1",
    "sg:city":"F\u00fcrth",
    "sg:phone":"+49 911/732409",
    "sg:postcode":"90766",
    "sg:province":"Bayern",
    "wof:name":"E. Studtrucker",
    "wof:placetype":"venue"
},
  "geometry": {"coordinates":[10.9699611664,49.4878616333],"type":"Point"}
}