{
  "type": "Feature",
  "properties": {
    "iso:country":"DE",
    "sg:address":"Stehnweg 8",
    "sg:city":"Seligenstadt",
    "sg:phone":"+49 4961/8266162",
    "sg:postcode":"63500",
    "sg:province":"Hessen",
    "wof:name":"Majunke Leder Gmbh",
    "wof:placetype":"venue"
},
  "geometry": {"coordinates":[8.951012,50.053947],"type":"Point"}
}