{
  "type": "Feature",
  "properties": {
    "iso:country":"DE",
    "sg:address":"Binger Landstr. 37",
    "sg:city":"Kirn",
    "sg:postcode":"55606",
    "sg:province":"Rheinland-Pfalz",
    "wof:name":"Bauko Baukooperation Gmbh",
    "wof:placetype":"venue"
},
  "geometry": {"coordinates":[7.480765,49.789467],"type":"Point"}
}