{
  "type": "Feature",
  "properties": {
    "iso:country":"DE",
    "sg:address":"Dritter Hagen 37",
    "sg:city":"Essen",
    "sg:postcode":"45127",
    "sg:province":"Nordrhein-Westfalen",
    "wof:name":"Vvs Holding Vertriebs- Verwaltungs- Und Service Gmbh",
    "wof:placetype":"venue"
},
  "geometry": {"coordinates":[7.0090289116,51.4560813904],"type":"Point"}
}