{
  "type": "Feature",
  "properties": {
    "iso:country":"DE",
    "sg:address":"Dorfstr. 27",
    "sg:city":"Westerhorn",
    "sg:phone":"+49 4127/247",
    "sg:postcode":"25364",
    "sg:province":"Schleswig-Holstein",
    "wof:name":"Haus Christine Altenheim",
    "wof:placetype":"venue"
},
  "geometry": {"coordinates":[9.681595,53.858017],"type":"Point"}
}