{
  "type": "Feature",
  "properties": {
    "iso:country":"DE",
    "sg:address":"Im Dorffeld 55",
    "sg:city":"Hemmigen",
    "sg:phone":"+49 511/2330939",
    "sg:postcode":"30966",
    "sg:province":"Niedersachsen",
    "wof:name":"Internet Magazin Newspaper Online",
    "wof:placetype":"venue"
},
  "geometry": {"coordinates":[9.744612,52.323368],"type":"Point"}
}