{
  "type": "Feature",
  "properties": {
    "iso:country":"DE",
    "sg:address":"Zum Hohen Brunnen 32",
    "sg:city":"G\u00f6ttingen",
    "sg:phone":"+49 551/23336",
    "sg:postcode":"37075",
    "sg:province":"Niedersachsen",
    "wof:name":"Manfred Lockemann",
    "wof:placetype":"venue"
},
  "geometry": {"coordinates":[9.995586,51.536758],"type":"Point"}
}