{
  "type": "Feature",
  "properties": {
    "iso:country":"DE",
    "sg:address":"Dorfstr. 3",
    "sg:city":"Wasserlosen",
    "sg:phone":"+49 9728/202",
    "sg:postcode":"97535",
    "sg:province":"Bayern",
    "wof:name":"Kath. Pfarramt Mari\u00e4 Himmelfahrt",
    "wof:placetype":"venue"
},
  "geometry": {"coordinates":[9.9975566864,50.0421905518],"type":"Point"}
}