{
  "type": "Feature",
  "properties": {
    "iso:country":"DE",
    "sg:address":"Akaweg 8",
    "sg:city":"L\u00f6ningen",
    "sg:phone":"+49 5434/3722",
    "sg:postcode":"49624",
    "sg:province":"Niedersachsen",
    "wof:name":"Herbert Flerlage Gmbh",
    "wof:placetype":"venue"
},
  "geometry": {"coordinates":[7.8563199043,52.7326011658],"type":"Point"}
}