{
  "type": "Feature",
  "properties": {
    "iso:country":"DE",
    "sg:address":"Dorfstr. 40",
    "sg:city":"Spalt",
    "sg:phone":"+49 9175/872",
    "sg:postcode":"91174",
    "sg:province":"Bayern",
    "wof:name":"K. Hausmann",
    "wof:placetype":"venue"
},
  "geometry": {"coordinates":[10.942284,49.167439],"type":"Point"}
}