{
  "type": "Feature",
  "properties": {
    "iso:country":"DE",
    "sg:address":"Hauptstr. 50",
    "sg:city":"Heubach",
    "sg:phone":"+49 7173/4324",
    "sg:postcode":"73540",
    "sg:province":"Baden-W\u00fcrttemberg",
    "wof:name":"Hildegard Haag",
    "wof:placetype":"venue"
},
  "geometry": {"coordinates":[9.935092,48.788101],"type":"Point"}
}