{
  "type": "Feature",
  "properties": {
    "iso:country":"DE",
    "sg:address":"Sch\u00fctzenstr. 40",
    "sg:city":"Traunstein",
    "sg:phone":"+49 861/5459",
    "sg:postcode":"83278",
    "sg:province":"Bayern",
    "wof:name":"Engelbert Schmidt",
    "wof:placetype":"venue"
},
  "geometry": {"coordinates":[12.6492557526,47.8717842102],"type":"Point"}
}