{
  "type": "Feature",
  "properties": {
    "iso:country":"DE",
    "sg:address":"Schweigstr. 26",
    "sg:city":"Wei\u00dfwasser",
    "sg:phone":"+49 3576/241979",
    "sg:postcode":"02943",
    "sg:province":"Sachsen",
    "wof:name":"Bernd Gr\u00fcttner",
    "wof:placetype":"venue"
},
  "geometry": {"coordinates":[14.6353282928,51.4996795654],"type":"Point"}
}