{
  "type": "Feature",
  "properties": {
    "iso:country":"DE",
    "sg:address":"Eugen-Bolz-Pl. 1",
    "sg:city":"Rottenburg",
    "sg:phone":"+49 4974/721690",
    "sg:postcode":"72108",
    "sg:province":"Baden-W\u00fcrttemberg",
    "wof:name":"Bisch\u00d6fliches Ordinariat",
    "wof:placetype":"venue"
},
  "geometry": {"coordinates":[8.938245,48.475811],"type":"Point"}
}