{
  "type": "Feature",
  "properties": {
    "iso:country":"DE",
    "sg:address":"Heiligenwiesen 30-32",
    "sg:city":"Stuttgart",
    "sg:phone":"+49 711/409620",
    "sg:postcode":"70327",
    "sg:province":"Baden-W\u00fcrttemberg",
    "wof:name":"Heinz Jennert Bau-chemie Gmbh",
    "wof:placetype":"venue"
},
  "geometry": {"coordinates":[9.2544755936,48.7634429932],"type":"Point"}
}