{
  "type": "Feature",
  "properties": {
    "iso:country":"DE",
    "sg:address":"Treuenbrietzener Str. 50",
    "sg:city":"Beelitz",
    "sg:phone":"+49 33204/60222",
    "sg:postcode":"14547",
    "sg:province":"Brandenburg",
    "wof:name":"Provia Ingenieurb\u00fcro F\u00fcr Verkehrsanlagen Gmbh",
    "wof:placetype":"venue"
},
  "geometry": {"coordinates":[12.9738759995,52.2272377014],"type":"Point"}
}