{
  "type": "Feature",
  "properties": {
    "iso:country":"DE",
    "sg:address":"Frauenstein 27",
    "sg:city":"Bingen",
    "sg:phone":"+49 7571/52678",
    "sg:postcode":"72511",
    "sg:province":"Baden-W\u00fcrttemberg",
    "wof:name":"Uwe Quabeck Detektei",
    "wof:placetype":"venue"
},
  "geometry": {"coordinates":[9.29123,48.10294],"type":"Point"}
}