{
  "type": "Feature",
  "properties": {
    "iso:country":"DE",
    "sg:address":"Mainstr. 8",
    "sg:city":"Hattersheim",
    "sg:phone":"+49 6190/2077",
    "sg:postcode":"65795",
    "sg:province":"Hessen",
    "wof:name":"Peter Kulp Steuerberater",
    "wof:placetype":"venue"
},
  "geometry": {"coordinates":[8.499879837,50.0539550781],"type":"Point"}
}