{
  "type": "Feature",
  "properties": {
    "iso:country":"DE",
    "sg:address":"Oberhof 16",
    "sg:city":"Wei\u00dfensberg",
    "sg:phone":"+49 7334/969710",
    "sg:postcode":"88138",
    "sg:province":"Bayern",
    "wof:name":"Allmendinger Elektromechanik Gmbh",
    "wof:placetype":"venue"
},
  "geometry": {"coordinates":[9.759061,48.605854],"type":"Point"}
}