{
  "type": "Feature",
  "properties": {
    "iso:country":"DE",
    "sg:address":"Kirchplatz 2",
    "sg:city":"Wetzlar",
    "sg:phone":"+49 6441/28554",
    "sg:postcode":"35579",
    "sg:province":"Hessen",
    "wof:name":"Pizzeria Il Cilento",
    "wof:placetype":"venue"
},
  "geometry": {"coordinates":[8.4592599869,50.5486907959],"type":"Point"}
}