{
  "type": "Feature",
  "properties": {
    "iso:country":"DE",
    "sg:address":"Font\u00e4nestr. 31",
    "sg:city":"Kerpen",
    "sg:phone":"+49 2273/8470",
    "sg:postcode":"50169",
    "sg:province":"Nordrhein-Westfalen",
    "wof:name":"A. J. Koberg Bildhauer",
    "wof:placetype":"venue"
},
  "geometry": {"coordinates":[6.714324,50.909912],"type":"Point"}
}