{
  "type": "Feature",
  "properties": {
    "iso:country":"DE",
    "sg:address":"Hammer Str. 23-25",
    "sg:city":"Ahlen",
    "sg:phone":"+49 2382/940520",
    "sg:postcode":"59227",
    "sg:province":"Nordrhein-Westfalen",
    "wof:name":"Edo Competition Motorsport Gmbh",
    "wof:placetype":"venue"
},
  "geometry": {"coordinates":[7.880723,51.76083],"type":"Point"}
}