{
  "type": "Feature",
  "properties": {
    "iso:country":"DE",
    "sg:address":"Hirtengasse 48",
    "sg:city":"E\u00dfleben",
    "sg:phone":"+49 36373/40600",
    "sg:postcode":"99628",
    "sg:province":"Th\u00fcringen",
    "wof:name":"Bernd Fr\u00f6hlich",
    "wof:placetype":"venue"
},
  "geometry": {"coordinates":[11.45962,51.151791],"type":"Point"}
}