{
  "type": "Feature",
  "properties": {
    "iso:country":"DE",
    "sg:address":"Werdensteinstr. 23",
    "sg:city":"Erbach",
    "sg:phone":"+49 7305/96280",
    "sg:postcode":"89155",
    "sg:province":"Baden-W\u00fcrttemberg",
    "wof:name":"Elektrizit\u00e4tswerk Kaim",
    "wof:placetype":"venue"
},
  "geometry": {"coordinates":[9.897891,48.300491],"type":"Point"}
}