{
  "type": "Feature",
  "properties": {
    "iso:country":"DE",
    "sg:address":"Ederblick 7",
    "sg:city":"Guxhagen",
    "sg:phone":"+49 5665/2846",
    "sg:postcode":"34302",
    "sg:province":"Hessen",
    "wof:name":"Brigitte Wiederhold",
    "wof:placetype":"venue"
},
  "geometry": {"coordinates":[9.464379,51.180973],"type":"Point"}
}