{
  "type": "Feature",
  "properties": {
    "iso:country":"DE",
    "sg:address":"Bertha-von-Suttner-Platz 1",
    "sg:city":"D\u00fcsseldorf",
    "sg:postcode":"40227",
    "sg:province":"Nordrhein-Westfalen",
    "wof:name":"Zentralbibliothek",
    "wof:placetype":"venue"
},
  "geometry": {"coordinates":[6.796595,51.219105],"type":"Point"}
}