{
  "type": "Feature",
  "properties": {
    "iso:country":"DE",
    "sg:address":"Radlerstr. 12 a",
    "sg:city":"Hildesheim",
    "sg:phone":"+49 5121/76790",
    "sg:postcode":"31135",
    "sg:province":"Niedersachsen",
    "wof:name":"M\u00e4tschke Malerfachbetrieb Gmbh",
    "wof:placetype":"venue"
},
  "geometry": {"coordinates":[9.99245,52.16782],"type":"Point"}
}