{
  "type": "Feature",
  "properties": {
    "iso:country":"DE",
    "sg:address":"Eichelbergstr. 50a",
    "sg:city":"Mannheim",
    "sg:phone":"+49 621/811151",
    "sg:postcode":"68163",
    "sg:province":"Baden-W\u00fcrttemberg",
    "wof:name":"Mabeg-mannheimer Asphalt- Und Betonbau Gmbh",
    "wof:placetype":"venue"
},
  "geometry": {"coordinates":[8.474114418,49.4638595581],"type":"Point"}
}