{
  "type": "Feature",
  "properties": {
    "iso:country":"DE",
    "sg:address":"Am Kaninberg 7",
    "sg:city":"Troisdorf",
    "sg:phone":"+49 2241/804365",
    "sg:postcode":"53842",
    "sg:province":"Nordrhein-Westfalen",
    "wof:name":"Heinz Becker",
    "wof:placetype":"venue"
},
  "geometry": {"coordinates":[7.144375,50.811024],"type":"Point"}
}