{
  "type": "Feature",
  "properties": {
    "iso:country":"DE",
    "sg:address":"Auf der Sch\u00f6nauer H\u00f6he 2",
    "sg:city":"Aachen",
    "sg:phone":"+49 241/14359",
    "sg:postcode":"52072",
    "sg:province":"Nordrhein-Westfalen",
    "wof:name":"Heinz Tobolla Bildhauer",
    "wof:placetype":"venue"
},
  "geometry": {"coordinates":[6.069805,50.808479],"type":"Point"}
}