{
  "type": "Feature",
  "properties": {
    "iso:country":"DE",
    "sg:address":"Weinbergstr. 8",
    "sg:city":"Balingen",
    "sg:phone":"+49 7433/930195",
    "sg:postcode":"72336",
    "sg:province":"Baden-W\u00fcrttemberg",
    "wof:name":"Armin Rieg Anlageberater",
    "wof:placetype":"venue"
},
  "geometry": {"coordinates":[8.8674573898,48.2525558472],"type":"Point"}
}