{
  "type": "Feature",
  "properties": {
    "iso:country":"DE",
    "sg:address":"Bebelstr. 159",
    "sg:city":"L\u00fcnen",
    "sg:postcode":"44532",
    "sg:province":"Nordrhein-Westfalen",
    "wof:name":"Aldi Gmbh & Co. Kg",
    "wof:placetype":"venue"
},
  "geometry": {"coordinates":[7.5331401825,51.5974006653],"type":"Point"}
}