{
  "type": "Feature",
  "properties": {
    "iso:country":"DE",
    "sg:address":"Carl-Haag-Str. 37",
    "sg:city":"Villingen-Schwenningen",
    "sg:phone":"+49 7720/956690",
    "sg:postcode":"78054",
    "sg:province":"Baden-W\u00fcrttemberg",
    "wof:name":"Franzgrote Immobilienmakler",
    "wof:placetype":"venue"
},
  "geometry": {"coordinates":[8.5380182266,48.0621414185],"type":"Point"}
}