{
  "type": "Feature",
  "properties": {
    "iso:country":"DE",
    "sg:address":"Am Margaretenhof",
    "sg:city":"Schwerin",
    "sg:postcode":"19057",
    "sg:province":"Mecklenburg-Vorpommern",
    "wof:name":"Aldi Gmbh & Co. Kg",
    "wof:placetype":"venue"
},
  "geometry": {"coordinates":[11.3583517075,53.6617393494],"type":"Point"}
}