{
  "type": "Feature",
  "properties": {
    "iso:country":"DE",
    "sg:address":"Leipziger Str. 54",
    "sg:city":"Eilenburg",
    "sg:phone":"+49 3423/68430",
    "sg:postcode":"04838",
    "sg:province":"Sachsen",
    "wof:name":"Renaud & Partner Gmbh",
    "wof:placetype":"venue"
},
  "geometry": {"coordinates":[12.6290140152,51.4588012695],"type":"Point"}
}