{
  "type": "Feature",
  "properties": {
    "iso:country":"DE",
    "sg:address":"Hauptstr. 41",
    "sg:city":"Lamspringe",
    "sg:phone":"+49 5183/805",
    "sg:postcode":"31195",
    "sg:province":"Niedersachsen",
    "wof:name":"Fritz Schnelle",
    "wof:placetype":"venue"
},
  "geometry": {"coordinates":[10.011684,51.960964],"type":"Point"}
}