{
  "type": "Feature",
  "properties": {
    "iso:country":"DE",
    "sg:address":"Ebertstr. 23",
    "sg:city":"Pei\u00dfenberg",
    "sg:phone":"+49 8803/61141",
    "sg:postcode":"82380",
    "sg:province":"Bayern",
    "wof:name":"Dionysos",
    "wof:placetype":"venue"
},
  "geometry": {"coordinates":[11.0686693192,47.8018302917],"type":"Point"}
}