{
  "type": "Feature",
  "properties": {
    "iso:country":"DE",
    "sg:address":"Saalgasse 1",
    "sg:city":"Wiesbaden",
    "sg:phone":"+49 611/375319",
    "sg:postcode":"65183",
    "sg:province":"Hessen",
    "wof:name":"H.-j. H\u00f6rner",
    "wof:placetype":"venue"
},
  "geometry": {"coordinates":[8.240599,50.085457],"type":"Point"}
}