{
  "type": "Feature",
  "properties": {
    "iso:country":"DE",
    "sg:address":"Erlenweg 1",
    "sg:city":"Speyer",
    "sg:phone":"+49 6232/32892",
    "sg:postcode":"67346",
    "sg:province":"Rheinland-Pfalz",
    "wof:name":"J. Rettinger",
    "wof:placetype":"venue"
},
  "geometry": {"coordinates":[8.4324073792,49.3468894958],"type":"Point"}
}