{
  "type": "Feature",
  "properties": {
    "iso:country":"DE",
    "sg:address":"Bietigheimer Str. 31",
    "sg:city":"Ingersheim",
    "sg:phone":"+49 7142/51757",
    "sg:postcode":"74379",
    "sg:province":"Baden-W\u00fcrttemberg",
    "wof:name":"J. Kammerrer",
    "wof:placetype":"venue"
},
  "geometry": {"coordinates":[9.1821088791,48.9588813782],"type":"Point"}
}