{
  "type": "Feature",
  "properties": {
    "iso:country":"DE",
    "sg:address":"Kyffh\u00e4userstr. 17",
    "sg:city":"K\u00f6ln",
    "sg:phone":"+49 221/2400505",
    "sg:postcode":"50674",
    "sg:province":"Nordrhein-Westfalen",
    "wof:name":"Greyhound American Bar & Cafe",
    "wof:placetype":"venue"
},
  "geometry": {"coordinates":[6.939903,50.928783],"type":"Point"}
}