{
  "type": "Feature",
  "properties": {
    "iso:country":"DE",
    "sg:address":"Beningastr. 5",
    "sg:city":"Leer",
    "sg:phone":"+49 491/13337",
    "sg:postcode":"26789",
    "sg:province":"Niedersachsen",
    "wof:name":"Nasch Mal",
    "wof:placetype":"venue"
},
  "geometry": {"coordinates":[7.4724497795,53.2254829407],"type":"Point"}
}