{
  "type": "Feature",
  "properties": {
    "iso:country":"DE",
    "sg:address":"Ludwig-Uhland-Str. 28",
    "sg:city":"Neckargem\u00fcnd",
    "sg:phone":"+49 6223/6187",
    "sg:postcode":"69151",
    "sg:province":"Baden-W\u00fcrttemberg",
    "wof:name":"Polster Frei Gmbh",
    "wof:placetype":"venue"
},
  "geometry": {"coordinates":[8.804996,49.390469],"type":"Point"}
}