{
  "type": "Feature",
  "properties": {
    "iso:country":"DE",
    "sg:address":"Am Drostenst\u00fcck 23",
    "sg:city":"L\u00fcdenscheid",
    "sg:phone":"+49 2351/60750",
    "sg:postcode":"58507",
    "sg:province":"Nordrhein-Westfalen",
    "wof:name":"Geso Gmbh",
    "wof:placetype":"venue"
},
  "geometry": {"coordinates":[7.6167697906,51.2306480408],"type":"Point"}
}