{
  "type": "Feature",
  "properties": {
    "iso:country":"DE",
    "sg:address":"Westiger Str. 96",
    "sg:city":"Altena",
    "sg:phone":"+49 2352/22418",
    "sg:postcode":"58762",
    "sg:province":"Nordrhein-Westfalen",
    "wof:name":"B\u00e4ckerei Wilke Gmbh",
    "wof:placetype":"venue"
},
  "geometry": {"coordinates":[7.700759,51.300056],"type":"Point"}
}