{
  "type": "Feature",
  "properties": {
    "iso:country":"DE",
    "sg:address":"Obernstr. 12",
    "sg:city":"Varel",
    "sg:phone":"+49 4451/861115",
    "sg:postcode":"26316",
    "sg:province":"Niedersachsen",
    "wof:name":"Vareler Wein-eck Kr\u00fcgel & Duddeck Kg",
    "wof:placetype":"venue"
},
  "geometry": {"coordinates":[8.1404800415,53.3951377869],"type":"Point"}
}