{
  "type": "Feature",
  "properties": {
    "iso:country":"DE",
    "sg:address":"Bahnhofstr. 48",
    "sg:city":"Tuttlingen",
    "sg:phone":"+49 7461/12896",
    "sg:postcode":"78532",
    "sg:province":"Baden-W\u00fcrttemberg",
    "wof:name":"August Renz Kg",
    "wof:placetype":"venue"
},
  "geometry": {"coordinates":[8.8135890961,47.9835968018],"type":"Point"}
}