{
  "type": "Feature",
  "properties": {
    "iso:country":"DE",
    "sg:address":"Fuldaer Str. 24 A",
    "sg:city":"Schl\u00fcchtern",
    "sg:phone":"+49 6661/2061",
    "sg:postcode":"36381",
    "sg:province":"Hessen",
    "wof:name":"Artur Wahle Gmbh & Co. Kg",
    "wof:placetype":"venue"
},
  "geometry": {"coordinates":[9.5244913101,50.3536529541],"type":"Point"}
}