{
  "type": "Feature",
  "properties": {
    "iso:country":"DE",
    "sg:address":"Karl-Fries-Str. 16",
    "sg:city":"Bendorf",
    "sg:phone":"+49 2622/3319",
    "sg:postcode":"56170",
    "sg:province":"Rheinland-Pfalz",
    "wof:name":"Bernd Lellig",
    "wof:placetype":"venue"
},
  "geometry": {"coordinates":[7.573784,50.426373],"type":"Point"}
}