{
  "type": "Feature",
  "properties": {
    "iso:country":"DE",
    "sg:address":"Rheiner Str. 81",
    "sg:city":"Emsdetten",
    "sg:phone":"+49 2572/5836",
    "sg:postcode":"48282",
    "sg:province":"Nordrhein-Westfalen",
    "wof:name":"Hugo K\u00f6nig",
    "wof:placetype":"venue"
},
  "geometry": {"coordinates":[7.52255,52.1791],"type":"Point"}
}