{
  "type": "Feature",
  "properties": {
    "iso:country":"DE",
    "sg:address":"Im Spichelsfeld 84",
    "sg:city":"Sankt Augustin",
    "sg:phone":"+49 2241/924046",
    "sg:postcode":"53757",
    "sg:province":"Nordrhein-Westfalen",
    "wof:name":"Wolfgang Rau Rechtsanwalt",
    "wof:placetype":"venue"
},
  "geometry": {"coordinates":[7.1879768372,50.7818870544],"type":"Point"}
}