{
  "type": "Feature",
  "properties": {
    "iso:country":"DE",
    "sg:address":"von-Arenberg-Str. 14",
    "sg:city":"Meerbusch",
    "sg:phone":"+49 2159/961616",
    "sg:postcode":"40668",
    "sg:province":"Nordrhein-Westfalen",
    "wof:name":"Kohtes & Partner",
    "wof:placetype":"venue"
},
  "geometry": {"coordinates":[6.6306490898,51.3033332825],"type":"Point"}
}