{
  "type": "Feature",
  "properties": {
    "iso:country":"DE",
    "sg:address":"Konstantinstr. 4-10",
    "sg:city":"Trier",
    "sg:phone":"+49 651/71640",
    "sg:postcode":"54290",
    "sg:province":"Rheinland-Pfalz",
    "wof:name":"Dkv Deutsche Krankenversicherung Ag",
    "wof:placetype":"venue"
},
  "geometry": {"coordinates":[6.6402997971,49.7545585632],"type":"Point"}
}