{
  "type": "Feature",
  "properties": {
    "iso:country":"DE",
    "sg:address":"Schwimmbadstr. 14",
    "sg:city":"Heuchelheim",
    "sg:phone":"+49 641/62567",
    "sg:postcode":"35452",
    "sg:province":"Hessen",
    "wof:name":"Erwin Kuhn Wirtschaftspr\u00fcfer Und",
    "wof:placetype":"venue"
},
  "geometry": {"coordinates":[8.6206655502,50.581993103],"type":"Point"}
}