{
  "type": "Feature",
  "properties": {
    "iso:country":"DE",
    "sg:address":"Gropiusallee 78",
    "sg:city":"Dessau",
    "sg:phone":"+49 340/619161",
    "sg:postcode":"06846",
    "sg:province":"Sachsen-Anhalt",
    "wof:name":"Sebastian Kaps",
    "wof:placetype":"venue"
},
  "geometry": {"coordinates":[12.2244968414,51.8427581787],"type":"Point"}
}