{
  "type": "Feature",
  "properties": {
    "iso:country":"DE",
    "sg:address":"Stephanstr. 32",
    "sg:city":"Dresden",
    "sg:phone":"+49 351/8497303",
    "sg:postcode":"01129",
    "sg:province":"Sachsen",
    "wof:name":"Susanne Meyer Rechtsanw\u00e4ltin",
    "wof:placetype":"venue"
},
  "geometry": {"coordinates":[13.7147512436,51.092010498],"type":"Point"}
}