{
  "type": "Feature",
  "properties": {
    "iso:country":"DE",
    "sg:address":"Sartoriusstr. 2",
    "sg:city":"Essen",
    "sg:phone":"+49 201/472929",
    "sg:postcode":"45134",
    "sg:province":"Nordrhein-Westfalen",
    "wof:name":"J. Haffner",
    "wof:placetype":"venue"
},
  "geometry": {"coordinates":[7.0452342033,51.4258804321],"type":"Point"}
}