{
  "type": "Feature",
  "properties": {
    "iso:country":"DE",
    "sg:address":"Osserstr. 2",
    "sg:city":"Regen",
    "sg:phone":"+49 9921/94460",
    "sg:postcode":"94209",
    "sg:province":"Bayern",
    "wof:name":"Deutsches Rotes Kreuz",
    "wof:placetype":"venue"
},
  "geometry": {"coordinates":[13.1193141937,48.9745826721],"type":"Point"}
}