{
  "type": "Feature",
  "properties": {
    "iso:country":"DE",
    "sg:address":"Flachsmarkt 1",
    "sg:city":"Mainz",
    "sg:phone":"+49 6131/223883",
    "sg:postcode":"55116",
    "sg:province":"Rheinland-Pfalz",
    "wof:name":"Gerd Kr\u00e4mmer Steuerbevollm\u00e4chtigter",
    "wof:placetype":"venue"
},
  "geometry": {"coordinates":[8.2708082199,50.0021095276],"type":"Point"}
}