{
  "type": "Feature",
  "properties": {
    "iso:country":"DE",
    "sg:address":"Industriestr 3",
    "sg:city":"Sch\u00f6nebeck",
    "sg:phone":"+49 3928/410268",
    "sg:postcode":"39218",
    "sg:province":"Sachsen-Anhalt",
    "wof:name":"Bauschlosserei Bosse Gmbh",
    "wof:placetype":"venue"
},
  "geometry": {"coordinates":[11.760865,52.016945],"type":"Point"}
}