{
  "type": "Feature",
  "properties": {
    "iso:country":"DE",
    "sg:address":"Hopfengasse 13",
    "sg:city":"Berching",
    "sg:phone":"+49 8462/744",
    "sg:postcode":"92334",
    "sg:province":"Bayern",
    "wof:name":"A. M\u00fcller",
    "wof:placetype":"venue"
},
  "geometry": {"coordinates":[11.4339008331,49.118270874],"type":"Point"}
}