{
  "type": "Feature",
  "properties": {
    "iso:country":"DE",
    "sg:address":"Amendingen Kramerstr",
    "sg:city":"Memmingen",
    "sg:phone":"+49 8331/609438",
    "sg:postcode":"87700",
    "sg:province":"Bayern",
    "wof:name":"Sparkasse Memmingen-mindelheim",
    "wof:placetype":"venue"
},
  "geometry": {"coordinates":[10.17816,48.004959],"type":"Point"}
}