{
  "type": "Feature",
  "properties": {
    "iso:country":"DE",
    "sg:address":"Wahlscheider Str. 23",
    "sg:city":"Lohmar",
    "sg:phone":"+49 2206/8498",
    "sg:postcode":"53797",
    "sg:province":"Nordrhein-Westfalen",
    "wof:name":"K. Sch\u00f6nenberg",
    "wof:placetype":"venue"
},
  "geometry": {"coordinates":[7.2523789406,50.8902778625],"type":"Point"}
}