{
  "type": "Feature",
  "properties": {
    "iso:country":"DE",
    "sg:address":"Sch\u00f6nbergstr. 27a",
    "sg:city":"Schallstadt",
    "sg:phone":"+49 7664/600662",
    "sg:postcode":"79227",
    "sg:province":"Baden-W\u00fcrttemberg",
    "wof:name":"W. Fleitz Immobilienmakler",
    "wof:placetype":"venue"
},
  "geometry": {"coordinates":[7.7818651199,47.9665336609],"type":"Point"}
}