{
  "type": "Feature",
  "properties": {
    "iso:country":"DE",
    "sg:address":"Lange Zeile 6",
    "sg:city":"Erding",
    "sg:phone":"+49 8122/7088",
    "sg:postcode":"85435",
    "sg:province":"Bayern",
    "wof:name":"Schuh-sport-lederwaren Gerlspeck Gmbh",
    "wof:placetype":"venue"
},
  "geometry": {"coordinates":[11.9071178436,48.3069801331],"type":"Point"}
}