{
  "type": "Feature",
  "properties": {
    "iso:country":"DE",
    "sg:address":"Brunnenweg 47",
    "sg:city":"Darmstadt",
    "sg:phone":"+49 6151/55965",
    "sg:postcode":"64297",
    "sg:province":"Hessen",
    "wof:name":"Heinz Rosanowski Ingenieur Und Architekt",
    "wof:placetype":"venue"
},
  "geometry": {"coordinates":[8.635821,49.804413],"type":"Point"}
}