{
  "type": "Feature",
  "properties": {
    "iso:country":"DE",
    "sg:address":"Niederhofener Str. 20",
    "sg:city":"Wei\u00dfenburg",
    "sg:phone":"+49 9141/85550",
    "sg:postcode":"91781",
    "sg:province":"Bayern",
    "wof:name":"Friedrich L\u00f6w",
    "wof:placetype":"venue"
},
  "geometry": {"coordinates":[10.980159,49.030632],"type":"Point"}
}