{
  "type": "Feature",
  "properties": {
    "iso:country":"DE",
    "sg:address":"Stau 15-17",
    "sg:city":"Oldenburg",
    "sg:postcode":"26122",
    "sg:province":"Niedersachsen",
    "wof:name":"Grundst\u00fccks-gesellschaft Mbh",
    "wof:placetype":"venue"
},
  "geometry": {"coordinates":[8.2169704437,53.140209198],"type":"Point"}
}