{
  "type": "Feature",
  "properties": {
    "iso:country":"DE",
    "sg:address":"Gro\u00dfe Str. 72",
    "sg:city":"Verden",
    "sg:phone":"+49 4231/82790",
    "sg:postcode":"27283",
    "sg:province":"Niedersachsen",
    "wof:name":"Arko Gmbh",
    "wof:placetype":"venue"
},
  "geometry": {"coordinates":[9.2288722992,52.9205818176],"type":"Point"}
}