{
  "type": "Feature",
  "properties": {
    "iso:country":"DE",
    "sg:address":"Kreuzstrasse 1/1a",
    "sg:city":"Neuenburg/Rhein",
    "sg:phone":"+49 7631/796968",
    "sg:postcode":"79395",
    "sg:province":"Baden-W\u00fcrttemberg",
    "wof:name":"Rba-suedbaden",
    "wof:placetype":"venue"
},
  "geometry": {"coordinates":[7.5620388985,47.8133621216],"type":"Point"}
}