{
  "type": "Feature",
  "properties": {
    "iso:country":"DE",
    "sg:address":"Bahnhofstr. 38",
    "sg:city":"Eberbach",
    "sg:phone":"+49 6271/2041",
    "sg:postcode":"69412",
    "sg:province":"Baden-W\u00fcrttemberg",
    "wof:name":"Thomas Kaschper Rechtsanwalt",
    "wof:placetype":"venue"
},
  "geometry": {"coordinates":[8.9840745926,49.4651222229],"type":"Point"}
}