{
  "type": "Feature",
  "properties": {
    "iso:country":"DE",
    "sg:address":"Bl\u00f6ckenweg 5",
    "sg:city":"Winsen",
    "sg:postcode":"21423",
    "sg:province":"Niedersachsen",
    "wof:name":"Gig Gesellschaft F\u00fcr Industrie- Und",
    "wof:placetype":"venue"
},
  "geometry": {"coordinates":[10.310979,53.338261],"type":"Point"}
}