{
  "type": "Feature",
  "properties": {
    "iso:country":"DE",
    "sg:address":"Kennensteige 19",
    "sg:city":"Albstadt",
    "sg:postcode":"72459",
    "sg:province":"Baden-W\u00fcrttemberg",
    "wof:name":"Redaktion Vereinszeitung Turnerbund Tailfingen",
    "wof:placetype":"venue"
},
  "geometry": {"coordinates":[8.974986,48.252213],"type":"Point"}
}