{
  "type": "Feature",
  "properties": {
    "iso:country":"DE",
    "sg:address":"Urbanusstr. 34",
    "sg:city":"Gelsenkirchen",
    "sg:postcode":"45894",
    "sg:province":"Nordrhein-Westfalen",
    "wof:name":"New Live Gmbh",
    "wof:placetype":"venue"
},
  "geometry": {"coordinates":[7.04727,51.576668],"type":"Point"}
}