{
  "type": "Feature",
  "properties": {
    "iso:country":"DE",
    "sg:address":"Kirchstr. 181",
    "sg:city":"Goch",
    "sg:phone":"+49 2823/93040",
    "sg:postcode":"47574",
    "sg:province":"Nordrhein-Westfalen",
    "wof:name":"Lothar Hofmann",
    "wof:placetype":"venue"
},
  "geometry": {"coordinates":[6.1939067841,51.7247390747],"type":"Point"}
}