{
  "type": "Feature",
  "properties": {
    "iso:country":"DE",
    "sg:address":"A\u00dfmannsh\u00e4user Weg 9",
    "sg:city":"Frankfurt",
    "sg:phone":"+49 69/355334",
    "sg:postcode":"60529",
    "sg:province":"Hessen",
    "wof:name":"Alfred Philipp Elektromeister",
    "wof:placetype":"venue"
},
  "geometry": {"coordinates":[8.568922,50.083248],"type":"Point"}
}