{
  "type": "Feature",
  "properties": {
    "iso:country":"DE",
    "sg:address":"Im L\u00e4ndle 10",
    "sg:city":"Waldachtal",
    "sg:phone":"+49 7486/9442",
    "sg:postcode":"72178",
    "sg:province":"Baden-W\u00fcrttemberg",
    "wof:name":"Reinhold Luger",
    "wof:placetype":"venue"
},
  "geometry": {"coordinates":[8.600033,48.491085],"type":"Point"}
}