{
  "type": "Feature",
  "properties": {
    "iso:country":"DE",
    "sg:address":"Gabelsbergerstr 4",
    "sg:city":"Heidenau",
    "sg:phone":"+49 3529/56540",
    "sg:postcode":"01809",
    "sg:province":"Sachsen",
    "wof:name":"Vakutec Trocknungsanlagenbau",
    "wof:placetype":"venue"
},
  "geometry": {"coordinates":[13.869442,50.972603],"type":"Point"}
}