{
  "type": "Feature",
  "properties": {
    "iso:country":"DE",
    "sg:address":"V\u00f6hrenbacher Str. 23",
    "sg:city":"Villingen-Schwenningen",
    "sg:phone":"+49 7721/930",
    "sg:postcode":"78050",
    "sg:province":"Baden-W\u00fcrttemberg",
    "wof:name":"Krankenhausvollapotheke Der St\u00e4dtischen Krankenanstalten",
    "wof:placetype":"venue"
},
  "geometry": {"coordinates":[8.43832,48.057728],"type":"Point"}
}