{
  "type": "Feature",
  "properties": {
    "iso:country":"DE",
    "sg:address":"Remchinger Str. 18",
    "sg:city":"K\u00f6nigsbach-Stein",
    "sg:phone":"+49 4967/5193500",
    "sg:postcode":"75203",
    "sg:province":"Baden-W\u00fcrttemberg",
    "wof:name":"Roberto Design Ledermoden Vertriebs Gmbh",
    "wof:placetype":"venue"
},
  "geometry": {"coordinates":[7.6431651115,49.7843894958],"type":"Point"}
}