{
  "type": "Feature",
  "properties": {
    "iso:country":"DE",
    "sg:address":"Stadtgraben 47 a",
    "sg:city":"Straubing",
    "sg:phone":"+49 9421/85750",
    "sg:postcode":"94315",
    "sg:province":"Bayern",
    "wof:name":"Hubert H\u00f6rtensteiner Licht Aktuell",
    "wof:placetype":"venue"
},
  "geometry": {"coordinates":[12.573503,48.881413],"type":"Point"}
}