{
  "type": "Feature",
  "properties": {
    "iso:country":"DE",
    "sg:address":"Am Schallenberg 2 b",
    "sg:city":"Sipplingen",
    "sg:phone":"+49 7551/63254",
    "sg:postcode":"78354",
    "sg:province":"Baden-W\u00fcrttemberg",
    "wof:name":"Wilhelm Ruoff Architekt",
    "wof:placetype":"venue"
},
  "geometry": {"coordinates":[9.098193,47.800014],"type":"Point"}
}