{
  "type": "Feature",
  "properties": {
    "iso:country":"DE",
    "sg:address":"K\u00f6lner Str. 194",
    "sg:city":"K\u00fcrten",
    "sg:phone":"+49 2207/4218",
    "sg:postcode":"51515",
    "sg:province":"Nordrhein-Westfalen",
    "wof:name":"Annemarie Ballon",
    "wof:placetype":"venue"
},
  "geometry": {"coordinates":[7.234372139,51.0540008545],"type":"Point"}
}