{
  "type": "Feature",
  "properties": {
    "iso:country":"DE",
    "sg:address":"D\u00fcnscheder Str. 8",
    "sg:city":"Attendorn",
    "sg:phone":"+49 2721/94170",
    "sg:postcode":"57439",
    "sg:province":"Nordrhein-Westfalen",
    "wof:name":"Erich Wintersohle-teipel",
    "wof:placetype":"venue"
},
  "geometry": {"coordinates":[7.9733362198,51.1231918335],"type":"Point"}
}