{
  "type": "Feature",
  "properties": {
    "iso:country":"DE",
    "sg:address":"Rezatweg 42",
    "sg:city":"N\u00fcrnberg",
    "sg:phone":"+49 911/436422",
    "sg:postcode":"90449",
    "sg:province":"Bayern",
    "wof:name":"H. Und G. Walter Gmbh",
    "wof:placetype":"venue"
},
  "geometry": {"coordinates":[11.010035,49.430721],"type":"Point"}
}