{
  "type": "Feature",
  "properties": {
    "iso:country":"DE",
    "sg:address":"Hindenburgwall 35",
    "sg:city":"Wittingen",
    "sg:phone":"+49 5831/98000",
    "sg:postcode":"29378",
    "sg:province":"Niedersachsen",
    "wof:name":"Dr. Stein & Partner",
    "wof:placetype":"venue"
},
  "geometry": {"coordinates":[10.7418012619,52.7264022827],"type":"Point"}
}