{
  "type": "Feature",
  "properties": {
    "iso:country":"DE",
    "sg:address":"Rosendalstr. 133",
    "sg:city":"Ratingen",
    "sg:phone":"+49 2102/52376",
    "sg:postcode":"40882",
    "sg:province":"Nordrhein-Westfalen",
    "wof:name":"J\u00fcrgen Schneberger Rechtsanwalt",
    "wof:placetype":"venue"
},
  "geometry": {"coordinates":[6.9195790291,51.2907714844],"type":"Point"}
}