{
  "type": "Feature",
  "properties": {
    "iso:country":"DE",
    "sg:address":"Ramsloher W\u00e4ldchen 9",
    "sg:city":"Schalksm\u00fchle",
    "sg:phone":"+49 2355/2340",
    "sg:postcode":"58579",
    "sg:province":"Nordrhein-Westfalen",
    "wof:name":"Martina Gittel",
    "wof:placetype":"venue"
},
  "geometry": {"coordinates":[7.563754,51.258595],"type":"Point"}
}