{
  "type": "Feature",
  "properties": {
    "iso:country":"DE",
    "sg:address":"Sporker Ringstr. 18",
    "sg:city":"Bocholt",
    "sg:phone":"+49 2871/27860",
    "sg:postcode":"46399",
    "sg:province":"Nordrhein-Westfalen",
    "wof:name":"Hans Hund",
    "wof:placetype":"venue"
},
  "geometry": {"coordinates":[6.5517468452,51.8609161377],"type":"Point"}
}