{
  "type": "Feature",
  "properties": {
    "iso:country":"DE",
    "sg:address":"Im W\u00e4sele 22",
    "sg:city":"G\u00f6ppingen",
    "sg:phone":"+49 7161/816377",
    "sg:postcode":"73037",
    "sg:province":"Baden-W\u00fcrttemberg",
    "wof:name":"Lutz Peter Singer Architekt",
    "wof:placetype":"venue"
},
  "geometry": {"coordinates":[9.683447,48.674011],"type":"Point"}
}