{
  "type": "Feature",
  "properties": {
    "iso:country":"DE",
    "sg:address":"Dorfstr. 12",
    "sg:city":"Seedorf",
    "sg:phone":"+49 4545/1371",
    "sg:postcode":"23883",
    "sg:province":"Schleswig-Holstein",
    "wof:name":"Mar\u00e4ne",
    "wof:placetype":"venue"
},
  "geometry": {"coordinates":[10.8764333725,53.618598938],"type":"Point"}
}