{
  "type": "Feature",
  "properties": {
    "iso:country":"DE",
    "sg:address":"Boschetsrieder Str 125",
    "sg:city":"M\u00fcnchen",
    "sg:phone":"+49 89/7850070",
    "sg:postcode":"81379",
    "sg:province":"Bayern",
    "wof:name":"Schleicher Fahrzeugteile Gmbh & Co Kg",
    "wof:placetype":"venue"
},
  "geometry": {"coordinates":[11.519401,48.098686],"type":"Point"}
}