{
  "type": "Feature",
  "properties": {
    "iso:country":"DE",
    "sg:address":"Weimarische Stra\u00dfe 11",
    "sg:city":"Erfurt",
    "sg:phone":"+49 361/4231139",
    "sg:postcode":"99099",
    "sg:province":"Th\u00fcringen",
    "wof:name":"Willkommen Im Hotel-restaurant Zur Henne",
    "wof:placetype":"venue"
},
  "geometry": {"coordinates":[11.077525,50.97702],"type":"Point"}
}