{
  "type": "Feature",
  "properties": {
    "iso:country":"DE",
    "sg:address":"Lothringer Str. 15",
    "sg:city":"Saarlouis",
    "sg:phone":"+49 6831/1422",
    "sg:postcode":"66740",
    "sg:province":"Saarland",
    "wof:name":"Taxi-weiler Gmbh",
    "wof:placetype":"venue"
},
  "geometry": {"coordinates":[6.7506370544,49.3120918274],"type":"Point"}
}