{
  "type": "Feature",
  "properties": {
    "iso:country":"DE",
    "sg:address":"Niederkircher Str. 33",
    "sg:city":"Trier",
    "sg:phone":"+49 4965/188843",
    "sg:postcode":"54294",
    "sg:province":"Rheinland-Pfalz",
    "wof:name":"Reindl-maschinenbau",
    "wof:placetype":"venue"
},
  "geometry": {"coordinates":[6.5977988243,49.7231903076],"type":"Point"}
}