{
  "type": "Feature",
  "properties": {
    "iso:country":"DE",
    "sg:address":"Ulmer Str. 73",
    "sg:city":"Ochsenhausen",
    "sg:phone":"+49 7352/3832",
    "sg:postcode":"88416",
    "sg:province":"Baden-W\u00fcrttemberg",
    "wof:name":"Albert Winghart",
    "wof:placetype":"venue"
},
  "geometry": {"coordinates":[9.9488458633,48.078792572],"type":"Point"}
}