{
  "type": "Feature",
  "properties": {
    "iso:country":"DE",
    "sg:address":"Ovelg\u00f6nne 21",
    "sg:city":"Dinklage",
    "sg:phone":"+49 4443/2371",
    "sg:postcode":"49413",
    "sg:province":"Niedersachsen",
    "wof:name":"Peter M\u00f6ller Ingenieur",
    "wof:placetype":"venue"
},
  "geometry": {"coordinates":[8.1279211044,52.6618003845],"type":"Point"}
}