{
  "type": "Feature",
  "properties": {
    "iso:country":"DE",
    "sg:address":"Ludwigstr. 10",
    "sg:city":"Manching",
    "sg:postcode":"85077",
    "sg:province":"Bayern",
    "wof:name":"Waltl Bauelemente Gmbh",
    "wof:placetype":"venue"
},
  "geometry": {"coordinates":[11.469893,48.707623],"type":"Point"}
}