{
  "type": "Feature",
  "properties": {
    "iso:country":"DE",
    "sg:address":"Summter Str. 51",
    "sg:city":"Berlin",
    "sg:phone":"+49 30/56700440",
    "sg:postcode":"12623",
    "sg:province":"Berlin",
    "wof:name":"Bettina Voigt-ramlow Immobilienmaklerin",
    "wof:placetype":"venue"
},
  "geometry": {"coordinates":[13.6237707138,52.488948822],"type":"Point"}
}