{
  "type": "Feature",
  "properties": {
    "iso:country":"DE",
    "sg:address":"Friedrich-Engels-Str. 63",
    "sg:city":"Neuhardenberg",
    "sg:phone":"+49 33476/50464",
    "sg:postcode":"15320",
    "sg:province":"Brandenburg",
    "wof:name":"F. A. L. K. Dental Gmbh",
    "wof:placetype":"venue"
},
  "geometry": {"coordinates":[14.2391624451,52.5890579224],"type":"Point"}
}