{
  "type": "Feature",
  "properties": {
    "iso:country":"DE",
    "sg:address":"F\u00fcrstenstr. 6",
    "sg:city":"Bonn",
    "sg:phone":"+49 228/633949",
    "sg:postcode":"53111",
    "sg:province":"Nordrhein-Westfalen",
    "wof:name":"Stockhausen Immobilienmakler",
    "wof:placetype":"venue"
},
  "geometry": {"coordinates":[7.1013708115,50.7344245911],"type":"Point"}
}