{
  "type": "Feature",
  "properties": {
    "iso:country":"DE",
    "sg:address":"M\u00fclhauser Str 157",
    "sg:city":"Kempen",
    "sg:phone":"+49 2152/1431",
    "sg:postcode":"47906",
    "sg:province":"Nordrhein-Westfalen",
    "wof:name":"Gedak-gesellschaft F\u00fcr Datenverarbeitung Und Kommunikation Mbh",
    "wof:placetype":"venue"
},
  "geometry": {"coordinates":[6.403039,51.359589],"type":"Point"}
}