{
  "type": "Feature",
  "properties": {
    "iso:country":"DE",
    "sg:address":"Holtenklinker Str. 11",
    "sg:city":"Hamburg",
    "sg:phone":"+49 40/7248447",
    "sg:postcode":"21029",
    "sg:province":"Hamburg",
    "wof:name":"Marc Br\u00fcgmann",
    "wof:placetype":"venue"
},
  "geometry": {"coordinates":[10.2188596725,53.4849205017],"type":"Point"}
}