{
  "type": "Feature",
  "properties": {
    "iso:country":"DE",
    "sg:address":"Leipziger Str. 61",
    "sg:city":"Zwickau",
    "sg:phone":"+49 375/473296",
    "sg:postcode":"08058",
    "sg:province":"Sachsen",
    "wof:name":"Isolde Wetzel",
    "wof:placetype":"venue"
},
  "geometry": {"coordinates":[12.4924154282,50.7294425964],"type":"Point"}
}