{
  "type": "Feature",
  "properties": {
    "iso:country":"DE",
    "sg:address":"L\u00fctkefeld 15",
    "sg:city":"Warburg",
    "sg:phone":"+49 5641/950",
    "sg:postcode":"34414",
    "sg:province":"Nordrhein-Westfalen",
    "wof:name":"Brauns-heitmann Gmbh & Co. Kg",
    "wof:placetype":"venue"
},
  "geometry": {"coordinates":[9.0939235687,51.5327262878],"type":"Point"}
}