{
  "type": "Feature",
  "properties": {
    "iso:country":"DE",
    "sg:address":"Marktplatz 7",
    "sg:city":"Rinteln",
    "sg:phone":"+49 5751/42730",
    "sg:postcode":"31737",
    "sg:province":"Niedersachsen",
    "wof:name":"Neue Heimat Wohnungs- Und Siedlungsbau",
    "wof:placetype":"venue"
},
  "geometry": {"coordinates":[9.0811424255,52.1873512268],"type":"Point"}
}