{
  "type": "Feature",
  "properties": {
    "iso:country":"DE",
    "sg:address":"N\u00f6rdliches Sandfeld 30",
    "sg:city":"Winsen",
    "sg:phone":"+49 5143/669292",
    "sg:postcode":"29308",
    "sg:province":"Niedersachsen",
    "wof:name":"Wolf Heizungsbau Gmbh",
    "wof:placetype":"venue"
},
  "geometry": {"coordinates":[9.917678833,52.6896476746],"type":"Point"}
}