{
  "type": "Feature",
  "properties": {
    "iso:country":"DE",
    "sg:address":"M\u00fchlberger Str. 28",
    "sg:city":"Cavertitz",
    "sg:phone":"+49 35264/90447",
    "sg:postcode":"04758",
    "sg:province":"Sachsen",
    "wof:name":"Schirmenitzer Verm\u00f6gens- Verwaltungsgesellschaft",
    "wof:placetype":"venue"
},
  "geometry": {"coordinates":[13.1922168732,51.4070854187],"type":"Point"}
}