{
  "type": "Feature",
  "properties": {
    "iso:country":"DE",
    "sg:address":"Redcarstr 24",
    "sg:city":"Troisdorf",
    "sg:phone":"+49 2241/394220",
    "sg:postcode":"53842",
    "sg:province":"Nordrhein-Westfalen",
    "wof:name":"Karl Kochmann Gmbh & Co Kg",
    "wof:placetype":"venue"
},
  "geometry": {"coordinates":[7.1048049927,50.8236160278],"type":"Point"}
}