{
  "type": "Feature",
  "properties": {
    "iso:country":"DE",
    "sg:address":"Blinke 4",
    "sg:city":"Leer",
    "sg:postcode":"26789",
    "sg:province":"Niedersachsen",
    "wof:name":"Gesundheitszentrum Main-spessart Gmbh & Co. Kg",
    "wof:placetype":"venue"
},
  "geometry": {"coordinates":[7.4454112053,53.2259788513],"type":"Point"}
}