{
  "type": "Feature",
  "properties": {
    "iso:country":"DE",
    "sg:address":"Auf der Hochreuth 4",
    "sg:city":"Wei\u00dfensberg",
    "sg:phone":"+49 8389/8546",
    "sg:postcode":"88138",
    "sg:province":"Bayern",
    "wof:name":"D. Miotke Immobilienmakler",
    "wof:placetype":"venue"
},
  "geometry": {"coordinates":[9.7175979614,47.5798492432],"type":"Point"}
}