{
  "type": "Feature",
  "properties": {
    "iso:country":"DE",
    "sg:address":"Sonnenstr. 16",
    "sg:city":"Scheyern",
    "sg:phone":"+49 8441/3757",
    "sg:postcode":"85298",
    "sg:province":"Bayern",
    "wof:name":"G. Jun. Eisenmann",
    "wof:placetype":"venue"
},
  "geometry": {"coordinates":[11.458806,48.50473],"type":"Point"}
}