{
  "type": "Feature",
  "properties": {
    "iso:country":"DE",
    "sg:address":"Herderstr. 21",
    "sg:city":"Hochheim",
    "sg:phone":"+49 6146/9387",
    "sg:postcode":"65239",
    "sg:province":"Hessen",
    "wof:name":"H. P. Eifel Immobilienmakler",
    "wof:placetype":"venue"
},
  "geometry": {"coordinates":[8.3714370728,50.0091629028],"type":"Point"}
}