{
  "type": "Feature",
  "properties": {
    "iso:country":"DE",
    "sg:address":"Breidenbachstra\u00dfe 46",
    "sg:city":"Leverkusen",
    "sg:phone":"+49 214/46756",
    "sg:postcode":"51373",
    "sg:province":"Nordrhein-Westfalen",
    "wof:name":"Drs.(nl) Berend-j. Van Aalderen, Zahnarzt",
    "wof:placetype":"venue"
},
  "geometry": {"coordinates":[6.98362,51.029236],"type":"Point"}
}