{
  "type": "Feature",
  "properties": {
    "iso:country":"DE",
    "sg:address":"Neuenkirchener Str. 3",
    "sg:city":"Holdorf",
    "sg:phone":"+49 5494/6526",
    "sg:postcode":"49451",
    "sg:province":"Niedersachsen",
    "wof:name":"M\u00fcnsterl\u00e4ndische Vers. Vermittlung Wartenberg",
    "wof:placetype":"venue"
},
  "geometry": {"coordinates":[8.1236228943,52.5852851868],"type":"Point"}
}