{
  "type": "Feature",
  "properties": {
    "iso:country":"DE",
    "sg:address":"Sternweg 10 a",
    "sg:city":"Schleiden",
    "sg:postcode":"53937",
    "sg:province":"Nordrhein-Westfalen",
    "wof:name":"Wilhelm F. Marsch Gmbh",
    "wof:placetype":"venue"
},
  "geometry": {"coordinates":[6.4755249023,50.5266609192],"type":"Point"}
}