{
  "type": "Feature",
  "properties": {
    "iso:country":"DE",
    "sg:address":"Turfstr. 9",
    "sg:city":"Gelsenkirchen",
    "sg:phone":"+49 209/50066",
    "sg:postcode":"45899",
    "sg:province":"Nordrhein-Westfalen",
    "wof:name":"Reiseb\u00fcro Globe Tours Hans-j\u00fcrgen Jeromin",
    "wof:placetype":"venue"
},
  "geometry": {"coordinates":[7.0264439583,51.5396995544],"type":"Point"}
}