{
  "type": "Feature",
  "properties": {
    "iso:country":"DE",
    "sg:address":"Hauptstr. 62",
    "sg:city":"Steinheim",
    "sg:phone":"+49 7329/253",
    "sg:postcode":"89555",
    "sg:province":"Baden-W\u00fcrttemberg",
    "wof:name":"Landmetzgerei Wittlinger- Oberhammer Gmbh",
    "wof:placetype":"venue"
},
  "geometry": {"coordinates":[10.0606822968,48.6919708252],"type":"Point"}
}