{
  "type": "Feature",
  "properties": {
    "iso:country":"DE",
    "sg:address":"B\u00f6hmerwaldstr. 10",
    "sg:city":"Aichach",
    "sg:phone":"+49 8251/827171",
    "sg:postcode":"86551",
    "sg:province":"Bayern",
    "wof:name":"Herbert Stein",
    "wof:placetype":"venue"
},
  "geometry": {"coordinates":[11.1415596008,48.452999115],"type":"Point"}
}