{
  "type": "Feature",
  "properties": {
    "iso:country":"DE",
    "sg:address":"Hans-Ulrich-Breymann-Str. 10",
    "sg:city":"Osterburken",
    "sg:phone":"+49 4962/9164400",
    "sg:postcode":"74706",
    "sg:province":"Baden-W\u00fcrttemberg",
    "wof:name":"Mollet F\u00dcllstandtechnik",
    "wof:placetype":"venue"
},
  "geometry": {"coordinates":[9.416037,49.423359],"type":"Point"}
}