{
  "type": "Feature",
  "properties": {
    "iso:country":"DE",
    "sg:address":"Obere Grabenstr. 2",
    "sg:city":"Langenlonsheim",
    "sg:phone":"+49 6704/729",
    "sg:postcode":"55450",
    "sg:province":"Rheinland-Pfalz",
    "wof:name":"Clemens Honrath",
    "wof:placetype":"venue"
},
  "geometry": {"coordinates":[7.8961858749,49.898563385],"type":"Point"}
}