{
  "type": "Feature",
  "properties": {
    "iso:country":"DE",
    "sg:address":"Dettenh\u00e4user Str. 30",
    "sg:city":"Weil im Sch\u00f6nbuch",
    "sg:phone":"+49 7157/129082",
    "sg:postcode":"71093",
    "sg:province":"Baden-W\u00fcrttemberg",
    "wof:name":"Turnerheim",
    "wof:placetype":"venue"
},
  "geometry": {"coordinates":[9.0690536499,48.6215362549],"type":"Point"}
}