{
  "type": "Feature",
  "properties": {
    "iso:country":"DE",
    "sg:address":"Falkenhagener Str. 7",
    "sg:city":"Berlin",
    "sg:phone":"+49 49030",
    "sg:postcode":"13585",
    "sg:province":"Berlin",
    "wof:name":"Baertz Seminare & Coaching",
    "wof:placetype":"venue"
},
  "geometry": {"coordinates":[13.203068,52.545013],"type":"Point"}
}