{
  "type": "Feature",
  "properties": {
    "iso:country":"DE",
    "sg:address":"Selbecker Str. 271",
    "sg:city":"Hagen",
    "sg:phone":"+49 2331/77211",
    "sg:postcode":"58091",
    "sg:province":"Nordrhein-Westfalen",
    "wof:name":"Franz Kasch Architekturb\u00fcro Gmbh",
    "wof:placetype":"venue"
},
  "geometry": {"coordinates":[7.466476,51.326653],"type":"Point"}
}