{
  "type": "Feature",
  "properties": {
    "iso:country":"DE",
    "sg:address":"Egerer Str. 4 b",
    "sg:city":"Starnberg",
    "sg:phone":"+49 8151/28732",
    "sg:postcode":"82319",
    "sg:province":"Bayern",
    "wof:name":"Grita Schock Heilpraktikerin",
    "wof:placetype":"venue"
},
  "geometry": {"coordinates":[11.3336296082,48.0118751526],"type":"Point"}
}