{
  "type": "Feature",
  "properties": {
    "iso:country":"DE",
    "sg:address":"In den Br\u00fchlwiesen 14",
    "sg:city":"Bad Homburg",
    "sg:phone":"+49 6172/44243",
    "sg:postcode":"61352",
    "sg:province":"Hessen",
    "wof:name":"Heinrich Braum",
    "wof:placetype":"venue"
},
  "geometry": {"coordinates":[8.6586704254,50.2215385437],"type":"Point"}
}