{
  "type": "Feature",
  "properties": {
    "iso:country":"DE",
    "sg:address":"Walter-Flex-Str. 48b",
    "sg:city":"Stuttgart",
    "sg:phone":"+49 711/472853",
    "sg:postcode":"70619",
    "sg:province":"Baden-W\u00fcrttemberg",
    "wof:name":"Bruno Bauer Architekt",
    "wof:placetype":"venue"
},
  "geometry": {"coordinates":[9.209845,48.741577],"type":"Point"}
}