{
  "type": "Feature",
  "properties": {
    "iso:country":"DE",
    "sg:address":"Tullastr. 82a",
    "sg:city":"Freiburg",
    "sg:phone":"+49 761/502714",
    "sg:postcode":"79108",
    "sg:province":"Baden-W\u00fcrttemberg",
    "wof:name":"Bernard Felbinger Kg",
    "wof:placetype":"venue"
},
  "geometry": {"coordinates":[7.8438549042,48.0293273926],"type":"Point"}
}