{
  "type": "Feature",
  "properties": {
    "iso:country":"DE",
    "sg:address":"Engeldorfer Str. 57",
    "sg:city":"K\u00f6ln",
    "sg:phone":"+49 2232/6338",
    "sg:postcode":"50997",
    "sg:province":"Nordrhein-Westfalen",
    "wof:name":"Heinrich Tingart Steuerberater",
    "wof:placetype":"venue"
},
  "geometry": {"coordinates":[6.9290847778,50.8513565063],"type":"Point"}
}