{
  "type": "Feature",
  "properties": {
    "iso:country":"DE",
    "sg:address":"Landstr. 18",
    "sg:city":"Barsinghausen",
    "sg:phone":"+49 5105/81532",
    "sg:postcode":"30890",
    "sg:province":"Niedersachsen",
    "wof:name":"Manfred Herigslack",
    "wof:placetype":"venue"
},
  "geometry": {"coordinates":[9.50502491,52.2998428345],"type":"Point"}
}