{
  "type": "Feature",
  "properties": {
    "iso:country":"DE",
    "sg:address":"Schlimpfhofer Str. 18",
    "sg:city":"Oberthulba",
    "sg:phone":"+49 9736/9202",
    "sg:postcode":"97723",
    "sg:province":"Bayern",
    "wof:name":"Ke\u00dfler Fensterbau Gmbh",
    "wof:placetype":"venue"
},
  "geometry": {"coordinates":[9.960966,50.198826],"type":"Point"}
}