{
  "type": "Feature",
  "properties": {
    "iso:country":"DE",
    "sg:address":"Leipziger Str. 30",
    "sg:city":"Zwickau",
    "sg:phone":"+49 375/242454",
    "sg:postcode":"08056",
    "sg:province":"Sachsen",
    "wof:name":"Pizza Eck Heimservice",
    "wof:placetype":"venue"
},
  "geometry": {"coordinates":[12.49463,50.723709],"type":"Point"}
}