{
  "type": "Feature",
  "properties": {
    "iso:country":"DE",
    "sg:address":"F\u00fcllengartenweg",
    "sg:city":"Saarbr\u00fccken",
    "sg:phone":"+49 681/9977889",
    "sg:postcode":"66115",
    "sg:province":"Saarland",
    "wof:name":"Gruschke & Sohn Gmbh",
    "wof:placetype":"venue"
},
  "geometry": {"coordinates":[6.9262099266,49.2446594238],"type":"Point"}
}