{
  "type": "Feature",
  "properties": {
    "iso:country":"DE",
    "sg:address":"Bahnhofstr. 20",
    "sg:city":"Leichlingen",
    "sg:phone":"+49 2175/2843",
    "sg:postcode":"42799",
    "sg:province":"Nordrhein-Westfalen",
    "wof:name":"Cafe O. B\u00fcchel Inh. Renate Becker",
    "wof:placetype":"venue"
},
  "geometry": {"coordinates":[7.009385,51.105419],"type":"Point"}
}