{
  "type": "Feature",
  "properties": {
    "iso:country":"DE",
    "sg:address":"Pflaster\u00e4ckerstr. 14",
    "sg:city":"Stuttgart",
    "sg:phone":"+49 711/467222",
    "sg:postcode":"70186",
    "sg:province":"Baden-W\u00fcrttemberg",
    "wof:name":"Heinz Pfl\u00fcger Architekt",
    "wof:placetype":"venue"
},
  "geometry": {"coordinates":[9.206445,48.78017],"type":"Point"}
}