{
  "type": "Feature",
  "properties": {
    "iso:country":"DE",
    "sg:address":"Thomasstr. 13",
    "sg:city":"Recklinghausen",
    "sg:phone":"+49 2361/35515",
    "sg:postcode":"45661",
    "sg:province":"Nordrhein-Westfalen",
    "wof:name":"Siedelhofer Versicherung",
    "wof:placetype":"venue"
},
  "geometry": {"coordinates":[7.1812372208,51.5689735413],"type":"Point"}
}