{
  "type": "Feature",
  "properties": {
    "iso:country":"DE",
    "sg:address":"Sch\u00f6nm\u00fchlweg 4",
    "sg:city":"Neumarkt",
    "sg:phone":"+49 9181/465504",
    "sg:postcode":"92318",
    "sg:province":"Bayern",
    "wof:name":"Baur Grundst\u00fccks Gmbh & Co. Kg",
    "wof:placetype":"venue"
},
  "geometry": {"coordinates":[11.4656381607,49.2956199646],"type":"Point"}
}