{
  "type": "Feature",
  "properties": {
    "iso:country":"DE",
    "sg:address":"Oberlausitzer Str. 41",
    "sg:city":"Gro\u00dfpostwitz",
    "sg:phone":"+49 35938/50289",
    "sg:postcode":"02692",
    "sg:province":"Sachsen",
    "wof:name":"Wgb-industriebedarf",
    "wof:placetype":"venue"
},
  "geometry": {"coordinates":[14.445764,51.112808],"type":"Point"}
}