{
  "type": "Feature",
  "properties": {
    "iso:country":"DE",
    "sg:address":"Stra\u00dfe des Friedens 22",
    "sg:city":"Leisnig",
    "sg:phone":"+49 34321/12639",
    "sg:postcode":"04703",
    "sg:province":"Sachsen",
    "wof:name":"Horst Rockmann",
    "wof:placetype":"venue"
},
  "geometry": {"coordinates":[12.923378,51.16811],"type":"Point"}
}