{
  "type": "Feature",
  "properties": {
    "iso:country":"DE",
    "sg:address":"Ahornweg 8",
    "sg:city":"Hildburghausen",
    "sg:phone":"+49 3685/79420",
    "sg:postcode":"98646",
    "sg:province":"Th\u00fcringen",
    "wof:name":"Bestattungsinstitut Piet\u00e4t Gmbh",
    "wof:placetype":"venue"
},
  "geometry": {"coordinates":[10.7311,50.433376],"type":"Point"}
}