{
  "type": "Feature",
  "properties": {
    "iso:country":"DE",
    "sg:address":"Schlachthofstr. 12",
    "sg:city":"Bad Wildungen",
    "sg:phone":"+49 5621/4306",
    "sg:postcode":"34537",
    "sg:province":"Hessen",
    "wof:name":"Helmut R\u00f6diger",
    "wof:placetype":"venue"
},
  "geometry": {"coordinates":[9.138269,51.116543],"type":"Point"}
}