{
  "type": "Feature",
  "properties": {
    "iso:country":"DE",
    "sg:address":"August-Bebel-Str. 35",
    "sg:city":"Reichenberg",
    "sg:phone":"+49 351/8304982",
    "sg:postcode":"01468",
    "sg:province":"Sachsen",
    "wof:name":"G\u00fcnter Angrees",
    "wof:placetype":"venue"
},
  "geometry": {"coordinates":[13.679528,51.126823],"type":"Point"}
}