{
  "type": "Feature",
  "properties": {
    "iso:country":"DE",
    "sg:address":"Hannoversche Str 48",
    "sg:city":"Osnabr\u00fcck",
    "sg:phone":"+49 541/584710",
    "sg:postcode":"49084",
    "sg:province":"Niedersachsen",
    "wof:name":"Peter Steinb\u00fcrger Gmbh & Co",
    "wof:placetype":"venue"
},
  "geometry": {"coordinates":[8.0691823959,52.2626304626],"type":"Point"}
}