{
  "type": "Feature",
  "properties": {
    "iso:country":"DE",
    "sg:address":"Schlo\u00dfallee 28",
    "sg:city":"Erding",
    "sg:phone":"+49 8122/91615",
    "sg:postcode":"85435",
    "sg:province":"Bayern",
    "wof:name":"Heidi Rauch-lange",
    "wof:placetype":"venue"
},
  "geometry": {"coordinates":[11.8896312714,48.2709083557],"type":"Point"}
}