{
  "type": "Feature",
  "properties": {
    "iso:country":"DE",
    "sg:address":"Anliegerweg 2",
    "sg:city":"Tr\u00f6bitz",
    "sg:postcode":"03253",
    "sg:province":"Brandenburg",
    "wof:name":"Katholisches Pfarramt Tr\u00f6bitz",
    "wof:placetype":"venue"
},
  "geometry": {"coordinates":[13.4296865463,51.5964202881],"type":"Point"}
}