{
  "type": "Feature",
  "properties": {
    "iso:country":"DE",
    "sg:address":"Niederrheinallee 325",
    "sg:city":"Neukirchen-Vluyn",
    "sg:phone":"+49 2845/1855",
    "sg:postcode":"47506",
    "sg:province":"Nordrhein-Westfalen",
    "wof:name":"Iga Optik Basso Gmbh",
    "wof:placetype":"venue"
},
  "geometry": {"coordinates":[6.5473198891,51.4415092468],"type":"Point"}
}