{
  "type": "Feature",
  "properties": {
    "iso:country":"DE",
    "sg:address":"Tesdorpfstr. 17",
    "sg:city":"Hamburg",
    "sg:phone":"+49 40/4146140",
    "sg:postcode":"20148",
    "sg:province":"Hamburg",
    "wof:name":"Dornheim Geising Dr. Plantholz Rechtsanw\u00e4lte Steuerberater",
    "wof:placetype":"venue"
},
  "geometry": {"coordinates":[9.9938077927,53.5646362305],"type":"Point"}
}