{
  "type": "Feature",
  "properties": {
    "iso:country":"DE",
    "sg:address":"Hohenroder Weg 53",
    "sg:city":"Salzgitter",
    "sg:phone":"+49 5341/8228",
    "sg:postcode":"38259",
    "sg:province":"Niedersachsen",
    "wof:name":"Geru Gesellschaft F\u00fcr Entsorgung Recycling",
    "wof:placetype":"venue"
},
  "geometry": {"coordinates":[10.34997,52.02887],"type":"Point"}
}