{
  "type": "Feature",
  "properties": {
    "iso:country":"DE",
    "sg:address":"Gr\u00fcner Ring 4",
    "sg:city":"Hipstedt",
    "sg:phone":"+49 4768/443",
    "sg:postcode":"27432",
    "sg:province":"Niedersachsen",
    "wof:name":"Elektro-allermann",
    "wof:placetype":"venue"
},
  "geometry": {"coordinates":[8.974101,53.521034],"type":"Point"}
}