{
  "type": "Feature",
  "properties": {
    "iso:country":"DE",
    "sg:address":"Am Markt 17",
    "sg:city":"Kempen",
    "sg:phone":"+49 2152/5669",
    "sg:postcode":"47906",
    "sg:province":"Nordrhein-Westfalen",
    "wof:name":"Kino 13",
    "wof:placetype":"venue"
},
  "geometry": {"coordinates":[6.411951,51.355022],"type":"Point"}
}