{
  "type": "Feature",
  "properties": {
    "iso:country":"DE",
    "sg:address":"Dornumer Str. 49",
    "sg:city":"Aurich",
    "sg:phone":"+49 4941/73606",
    "sg:postcode":"26607",
    "sg:province":"Niedersachsen",
    "wof:name":"T\u00f6pfer Inh. Struckmeyer",
    "wof:placetype":"venue"
},
  "geometry": {"coordinates":[7.4876899719,53.500289917],"type":"Point"}
}