{
  "type": "Feature",
  "properties": {
    "iso:country":"DE",
    "sg:address":"Amselweg 23",
    "sg:city":"Stolberg",
    "sg:phone":"+49 2402/29818",
    "sg:postcode":"52223",
    "sg:province":"Nordrhein-Westfalen",
    "wof:name":"Gunnar Sczepanski Masseur",
    "wof:placetype":"venue"
},
  "geometry": {"coordinates":[6.218251,50.764149],"type":"Point"}
}