{
  "type": "Feature",
  "properties": {
    "iso:country":"DE",
    "sg:address":"Oberlipper Str. 225",
    "sg:city":"Waltrop",
    "sg:phone":"+49 2309/2902",
    "sg:postcode":"45731",
    "sg:province":"Nordrhein-Westfalen",
    "wof:name":"Heinrich Schlingermann",
    "wof:placetype":"venue"
},
  "geometry": {"coordinates":[7.448692,51.624432],"type":"Point"}
}