{
  "type": "Feature",
  "properties": {
    "iso:country":"DE",
    "sg:address":"Ahornstr. 6",
    "sg:city":"Sinntal",
    "sg:phone":"+49 6664/322",
    "sg:postcode":"36391",
    "sg:province":"Hessen",
    "wof:name":"Wilhelm Schlembach Architekt",
    "wof:placetype":"venue"
},
  "geometry": {"coordinates":[9.590949,50.320904],"type":"Point"}
}