{
  "type": "Feature",
  "properties": {
    "iso:country":"DE",
    "sg:address":"Am Tiefen See 1/6",
    "sg:city":"Maulbronn",
    "sg:phone":"+49 7043/952330",
    "sg:postcode":"75433",
    "sg:province":"Baden-W\u00fcrttemberg",
    "wof:name":"Set Up Maschinen + Steuerungen Gmbh",
    "wof:placetype":"venue"
},
  "geometry": {"coordinates":[8.818188,49.003918],"type":"Point"}
}