{
  "type": "Feature",
  "properties": {
    "iso:country":"DE",
    "sg:address":"L\u00fcbecker Str. 10",
    "sg:city":"Attendorn",
    "sg:phone":"+49 2722/959206",
    "sg:postcode":"57439",
    "sg:province":"Nordrhein-Westfalen",
    "wof:name":"Apotheke Im Schwalbenohl",
    "wof:placetype":"venue"
},
  "geometry": {"coordinates":[7.909187,51.132732],"type":"Point"}
}