{
  "type": "Feature",
  "properties": {
    "iso:country":"DE",
    "sg:address":"Wagnerstr. 4",
    "sg:city":"Siegsdorf",
    "sg:phone":"+49 8662/9594",
    "sg:postcode":"83313",
    "sg:province":"Bayern",
    "wof:name":"G\u00e4stehaus F. K\u00f6berl",
    "wof:placetype":"venue"
},
  "geometry": {"coordinates":[12.6495819092,47.8205947876],"type":"Point"}
}