{
  "type": "Feature",
  "properties": {
    "iso:country":"DE",
    "sg:address":"Sesenheimer Str. 14",
    "sg:city":"Berlin",
    "sg:phone":"+49 30/3125789",
    "sg:postcode":"10627",
    "sg:province":"Berlin",
    "wof:name":"Obenaus & Henschke",
    "wof:placetype":"venue"
},
  "geometry": {"coordinates":[13.307967186,52.5104255676],"type":"Point"}
}