{
  "type": "Feature",
  "properties": {
    "iso:country":"DE",
    "sg:address":"Sch\u00f6ne Aussicht 60a",
    "sg:city":"Staufenberg",
    "sg:phone":"+49 5543/4108",
    "sg:postcode":"34355",
    "sg:province":"Niedersachsen",
    "wof:name":"Norbert Lucht",
    "wof:placetype":"venue"
},
  "geometry": {"coordinates":[9.5864152908,51.3471336365],"type":"Point"}
}