{
  "type": "Feature",
  "properties": {
    "iso:country":"DE",
    "sg:address":"Dorfstr. 24",
    "sg:city":"Bessenbach",
    "sg:phone":"+49 6095/578",
    "sg:postcode":"63856",
    "sg:province":"Bayern",
    "wof:name":"Hugo Seubert",
    "wof:placetype":"venue"
},
  "geometry": {"coordinates":[9.247206,49.963951],"type":"Point"}
}