{
  "type": "Feature",
  "properties": {
    "iso:country":"DE",
    "sg:address":"Erich-B\u00f6hmke-Str. 40",
    "sg:city":"Greifswald",
    "sg:postcode":"17489",
    "sg:province":"Mecklenburg-Vorpommern",
    "wof:name":"Dr. Med. Inge Fischer",
    "wof:placetype":"venue"
},
  "geometry": {"coordinates":[13.379196,54.092236],"type":"Point"}
}