{
  "type": "Feature",
  "properties": {
    "iso:country":"DE",
    "sg:address":"Habichtsweg 5",
    "sg:city":"Delbr\u00fcck",
    "sg:phone":"+49 5250/7026",
    "sg:postcode":"33129",
    "sg:province":"Nordrhein-Westfalen",
    "wof:name":"Spedition Menne",
    "wof:placetype":"venue"
},
  "geometry": {"coordinates":[8.552134,51.757801],"type":"Point"}
}