{
  "type": "Feature",
  "properties": {
    "iso:country":"DE",
    "sg:address":"Bayreuther Str. 4",
    "sg:city":"Marktredwitz",
    "sg:phone":"+49 9231/8488",
    "sg:postcode":"95615",
    "sg:province":"Bayern",
    "wof:name":"Teppichhaus Und Fu\u00dfbodenbau Warku\u00df Gmbh",
    "wof:placetype":"venue"
},
  "geometry": {"coordinates":[12.0771398544,50.0038719177],"type":"Point"}
}