{
  "type": "Feature",
  "properties": {
    "iso:country":"DE",
    "sg:address":"Kr\u00f6nerstr. 10",
    "sg:city":"Rinteln",
    "sg:phone":"+49 5751/14531",
    "sg:postcode":"31737",
    "sg:province":"Niedersachsen",
    "wof:name":"Bau-dienstleistungs- Agentur B Gmbh",
    "wof:placetype":"venue"
},
  "geometry": {"coordinates":[9.077716,52.195164],"type":"Point"}
}