{
  "type": "Feature",
  "properties": {
    "iso:country":"DE",
    "sg:address":"Hintergasse 27",
    "sg:city":"Partenheim",
    "sg:phone":"+49 6732/7032",
    "sg:postcode":"55288",
    "sg:province":"Rheinland-Pfalz",
    "wof:name":"Dieter Klippel",
    "wof:placetype":"venue"
},
  "geometry": {"coordinates":[8.0800323486,49.8850708008],"type":"Point"}
}