{
  "type": "Feature",
  "properties": {
    "iso:country":"DE",
    "sg:address":"Bl\u00fccherplatz 1",
    "sg:city":"Berlin",
    "sg:postcode":"10961",
    "sg:province":"Berlin",
    "wof:name":"Amerika-gedenkbibliothek",
    "wof:placetype":"venue"
},
  "geometry": {"coordinates":[13.392414,52.49696],"type":"Point"}
}