{
  "type": "Feature",
  "properties": {
    "iso:country":"DE",
    "sg:address":"Wernher-von-Braun-Str. 1",
    "sg:city":"Dreieich",
    "sg:phone":"+49 6074/68832",
    "sg:postcode":"63303",
    "sg:province":"Hessen",
    "wof:name":"Dr. Holger Linden Tierarzt",
    "wof:placetype":"venue"
},
  "geometry": {"coordinates":[8.7536296844,49.9832115173],"type":"Point"}
}