{
  "type": "Feature",
  "properties": {
    "iso:country":"DE",
    "sg:address":"Tannenallee 69",
    "sg:city":"Reinbek",
    "sg:phone":"+49 40/71140213",
    "sg:postcode":"21465",
    "sg:province":"Schleswig-Holstein",
    "wof:name":"Sympa Cosmetics Gmbh",
    "wof:placetype":"venue"
},
  "geometry": {"coordinates":[10.249536,53.555775],"type":"Point"}
}