{
  "type": "Feature",
  "properties": {
    "iso:country":"DE",
    "sg:address":"Frankfurter Str. 14",
    "sg:city":"Uettingen",
    "sg:postcode":"97292",
    "sg:province":"Bayern",
    "wof:name":"Werner Schl\u00f6tterlein Heilpraktiker",
    "wof:placetype":"venue"
},
  "geometry": {"coordinates":[9.7233991623,49.7971839905],"type":"Point"}
}