{
  "type": "Feature",
  "properties": {
    "iso:country":"DE",
    "sg:address":"Bahnhofstr. 29",
    "sg:city":"Rotenburg",
    "sg:phone":"+49 6623/3109",
    "sg:postcode":"36199",
    "sg:province":"Hessen",
    "wof:name":"\u00d6ffentliche B\u00fccherei Lispenhausen",
    "wof:placetype":"venue"
},
  "geometry": {"coordinates":[9.769549,50.991055],"type":"Point"}
}