{
  "type": "Feature",
  "properties": {
    "iso:country":"DE",
    "sg:address":"Leberbl\u00fcmchenstr. 20",
    "sg:city":"M\u00fcnchen",
    "sg:phone":"+49 89/1505636",
    "sg:postcode":"80995",
    "sg:province":"Bayern",
    "wof:name":"E. Rittner",
    "wof:placetype":"venue"
},
  "geometry": {"coordinates":[11.525546,48.196594],"type":"Point"}
}