{
  "type": "Feature",
  "properties": {
    "iso:country":"DE",
    "sg:address":"Marktplatz 10",
    "sg:city":"Villingen-Schwenningen",
    "sg:phone":"+49 7720/36519",
    "sg:postcode":"78054",
    "sg:province":"Baden-W\u00fcrttemberg",
    "wof:name":"Hornstein Immobilienmakler",
    "wof:placetype":"venue"
},
  "geometry": {"coordinates":[8.5359382629,48.0662918091],"type":"Point"}
}