{
  "type": "Feature",
  "properties": {
    "iso:country":"DE",
    "sg:address":"Regensburger Str. 18",
    "sg:city":"Burglengenfeld",
    "sg:phone":"+49 9471/8881",
    "sg:postcode":"93133",
    "sg:province":"Bayern",
    "wof:name":"Mode-palette Gmbh",
    "wof:placetype":"venue"
},
  "geometry": {"coordinates":[12.042326,49.204906],"type":"Point"}
}