{
  "type": "Feature",
  "properties": {
    "iso:country":"DE",
    "sg:address":"Boschstr. 12",
    "sg:city":"Puchheim",
    "sg:phone":"+49 89/8002232",
    "sg:postcode":"82178",
    "sg:province":"Bayern",
    "wof:name":"Dr. Schetter Bmc Ingenieur- Gesellschaft Mbh",
    "wof:placetype":"venue"
},
  "geometry": {"coordinates":[11.365296,48.169865],"type":"Point"}
}