{
  "type": "Feature",
  "properties": {
    "iso:country":"DE",
    "sg:address":"Steinriede 3",
    "sg:city":"Garbsen",
    "sg:phone":"+49 5131/709320",
    "sg:postcode":"30827",
    "sg:province":"Niedersachsen",
    "wof:name":"Helios Software Gmbh",
    "wof:placetype":"venue"
},
  "geometry": {"coordinates":[9.6094560623,52.4299201965],"type":"Point"}
}