{
  "type": "Feature",
  "properties": {
    "iso:country":"DE",
    "sg:address":"Sieperting 24",
    "sg:city":"Eslohe",
    "sg:phone":"+49 2973/6327",
    "sg:postcode":"59889",
    "sg:province":"Nordrhein-Westfalen",
    "wof:name":"Hotel Limbergs Hof",
    "wof:placetype":"venue"
},
  "geometry": {"coordinates":[8.1445960999,51.2577590942],"type":"Point"}
}