{
  "type": "Feature",
  "properties": {
    "iso:country":"DE",
    "sg:address":"Merseburger Str. 237",
    "sg:city":"Halle",
    "sg:phone":"+49 345/41326",
    "sg:postcode":"06130",
    "sg:province":"Sachsen-Anhalt",
    "wof:name":"Bonn Hallesche",
    "wof:placetype":"venue"
},
  "geometry": {"coordinates":[11.9841842651,51.453754425],"type":"Point"}
}