{
  "type": "Feature",
  "properties": {
    "iso:country":"DE",
    "sg:address":"Missenharterweg 61",
    "sg:city":"Gerlingen",
    "sg:postcode":"70839",
    "sg:province":"Baden-W\u00fcrttemberg",
    "wof:name":"Rung-druck Gmbh",
    "wof:placetype":"venue"
},
  "geometry": {"coordinates":[9.046567,48.790073],"type":"Point"}
}