{
  "type": "Feature",
  "properties": {
    "iso:country":"DE",
    "sg:address":"Langer Hof 6-8",
    "sg:city":"Braunschweig",
    "sg:phone":"+49 531/45107",
    "sg:postcode":"38100",
    "sg:province":"Niedersachsen",
    "wof:name":"Doh",
    "wof:placetype":"venue"
},
  "geometry": {"coordinates":[10.525931,52.263966],"type":"Point"}
}