{
  "type": "Feature",
  "properties": {
    "iso:country":"DE",
    "sg:address":"B\u00fclowstr. 56-57",
    "sg:city":"Berlin",
    "sg:postcode":"10783",
    "sg:province":"Berlin",
    "wof:name":"Bav Berliner Acrylglas Gmbh",
    "wof:placetype":"venue"
},
  "geometry": {"coordinates":[13.366934,52.494923],"type":"Point"}
}