{
  "type": "Feature",
  "properties": {
    "iso:country":"DE",
    "sg:address":"Ansbacher Str. 20",
    "sg:city":"Feuchtwangen",
    "sg:phone":"+49 9852",
    "sg:postcode":"91555",
    "sg:province":"Bayern",
    "wof:name":"Bayerische Bauakademie",
    "wof:placetype":"venue"
},
  "geometry": {"coordinates":[10.334247,49.176876],"type":"Point"}
}