{
  "type": "Feature",
  "properties": {
    "iso:country":"DE",
    "sg:address":"Alte Mainzer Str. 121",
    "sg:city":"Mainz",
    "sg:phone":"+49 6131/801070",
    "sg:postcode":"55129",
    "sg:province":"Rheinland-Pfalz",
    "wof:name":"Dr. Reiner Hartmann Und Wolfgang Ehses",
    "wof:placetype":"venue"
},
  "geometry": {"coordinates":[8.2816562653,49.9721488953],"type":"Point"}
}