{
  "type": "Feature",
  "properties": {
    "iso:country":"DE",
    "sg:address":"Gr\u00fcnrathstr 2",
    "sg:city":"Greiz",
    "sg:phone":"+49 3661/3324",
    "sg:postcode":"07973",
    "sg:province":"Th\u00fcringen",
    "wof:name":"Blaudruckerei Schwinkowski",
    "wof:placetype":"venue"
},
  "geometry": {"coordinates":[12.2079963684,50.6540298462],"type":"Point"}
}