{
  "type": "Feature",
  "properties": {
    "iso:country":"DE",
    "sg:address":"Am B\u00f6hmerwald 12 a",
    "sg:city":"Norderstedt",
    "sg:phone":"+49 40/52985381",
    "sg:postcode":"22851",
    "sg:province":"Schleswig-Holstein",
    "wof:name":"Stousler Handelsgesellschaft Mbh",
    "wof:placetype":"venue"
},
  "geometry": {"coordinates":[10.0269136429,53.6830215454],"type":"Point"}
}