{
  "type": "Feature",
  "properties": {
    "iso:country":"DE",
    "sg:address":"Wahnscheid",
    "sg:city":"Herschbach",
    "sg:phone":"+49 6435/92230",
    "sg:postcode":"56414",
    "sg:province":"Rheinland-Pfalz",
    "wof:name":"Arno Witgert",
    "wof:placetype":"venue"
},
  "geometry": {"coordinates":[7.93777,50.509819],"type":"Point"}
}