{
  "type": "Feature",
  "properties": {
    "iso:country":"DE",
    "sg:address":"Neufeldweg 22",
    "sg:city":"Bergisch Gladbach",
    "sg:phone":"+49 2204/64390",
    "sg:postcode":"51427",
    "sg:province":"Nordrhein-Westfalen",
    "wof:name":"Friedel Schlomann Rechtsanwalt",
    "wof:placetype":"venue"
},
  "geometry": {"coordinates":[7.1174530983,50.9485435486],"type":"Point"}
}