{
  "type": "Feature",
  "properties": {
    "iso:country":"DE",
    "sg:address":"Wilhelmsh\u00f6her Str. 20",
    "sg:city":"Seesen",
    "sg:phone":"+49 5381/2179",
    "sg:postcode":"38723",
    "sg:province":"Niedersachsen",
    "wof:name":"Irmgard M\u00fcller",
    "wof:placetype":"venue"
},
  "geometry": {"coordinates":[10.196675,51.890427],"type":"Point"}
}