{
  "type": "Feature",
  "properties": {
    "iso:country":"DE",
    "sg:address":"Kanalstr. 4",
    "sg:city":"Bad Oeynhausen",
    "sg:phone":"+49 5731/29200",
    "sg:postcode":"32545",
    "sg:province":"Nordrhein-Westfalen",
    "wof:name":"\u00d6zlem",
    "wof:placetype":"venue"
},
  "geometry": {"coordinates":[8.7994709015,52.2057533264],"type":"Point"}
}