{
  "type": "Feature",
  "properties": {
    "iso:country":"DE",
    "sg:address":"In den Blumentriften",
    "sg:city":"Salzgitter",
    "sg:phone":"+49 5341/14040",
    "sg:postcode":"38226",
    "sg:province":"Niedersachsen",
    "wof:name":"Fritz & Co.",
    "wof:placetype":"venue"
},
  "geometry": {"coordinates":[10.3293781281,52.1544151306],"type":"Point"}
}