{
  "type": "Feature",
  "properties": {
    "iso:country":"DE",
    "sg:address":"Steinbergweg 18",
    "sg:city":"Pl\u00f6n",
    "sg:phone":"+49 4522/6771",
    "sg:postcode":"24306",
    "sg:province":"Schleswig-Holstein",
    "wof:name":"Harry Hamann",
    "wof:placetype":"venue"
},
  "geometry": {"coordinates":[10.44449,54.160412],"type":"Point"}
}