{
  "type": "Feature",
  "properties": {
    "iso:country":"DE",
    "sg:address":"J\u00e4gerstr. 10",
    "sg:city":"Freital",
    "sg:phone":"+49 351/643925",
    "sg:postcode":"01705",
    "sg:province":"Sachsen",
    "wof:name":"S. Kunst",
    "wof:placetype":"venue"
},
  "geometry": {"coordinates":[13.647949,50.990917],"type":"Point"}
}