{
  "type": "Feature",
  "properties": {
    "iso:country":"DE",
    "sg:address":"Filderstr. 61",
    "sg:city":"Stuttgart",
    "sg:phone":"+49 711/603018",
    "sg:postcode":"70180",
    "sg:province":"Baden-W\u00fcrttemberg",
    "wof:name":"Exil",
    "wof:placetype":"venue"
},
  "geometry": {"coordinates":[9.1697301865,48.7638587952],"type":"Point"}
}