{
  "type": "Feature",
  "properties": {
    "iso:country":"DE",
    "sg:address":"Hauptstr. 38 a",
    "sg:city":"Esterwegen",
    "sg:phone":"+49 5955/1781",
    "sg:postcode":"26897",
    "sg:province":"Niedersachsen",
    "wof:name":"Lukas W\u00fcbbolt Rechtsanwalt Und Notar",
    "wof:placetype":"venue"
},
  "geometry": {"coordinates":[7.6337828636,52.9924583435],"type":"Point"}
}