{
  "type": "Feature",
  "properties": {
    "iso:country":"DE",
    "sg:address":"L\u00f6hrstr. 20",
    "sg:city":"Amorbach",
    "sg:phone":"+49 9373/4393",
    "sg:postcode":"63916",
    "sg:province":"Bayern",
    "wof:name":"M. Und F. Nolte",
    "wof:placetype":"venue"
},
  "geometry": {"coordinates":[9.217998,49.644688],"type":"Point"}
}