{
  "type": "Feature",
  "properties": {
    "iso:country":"DE",
    "sg:address":"Fraunhoferstr. 1",
    "sg:city":"Planegg",
    "sg:postcode":"82152",
    "sg:province":"Bayern",
    "wof:name":"Gardemann Arbeitsb\u00fchnenvermietung Gmbh",
    "wof:placetype":"venue"
},
  "geometry": {"coordinates":[11.4483690262,48.1095123291],"type":"Point"}
}