{
  "type": "Feature",
  "properties": {
    "iso:country":"DE",
    "sg:address":"Vogelwoogstr. 8 - 10",
    "sg:city":"Kaiserslautern",
    "sg:phone":"+49 631",
    "sg:postcode":"67659",
    "sg:province":"Rheinland-Pfalz",
    "wof:name":"Fliesen Mages",
    "wof:placetype":"venue"
},
  "geometry": {"coordinates":[7.7420978546,49.4412574768],"type":"Point"}
}