{
  "type": "Feature",
  "properties": {
    "iso:country":"DE",
    "sg:address":"Girardetstr. 1",
    "sg:city":"Essen",
    "sg:postcode":"45131",
    "sg:province":"Nordrhein-Westfalen",
    "wof:name":"Classen-convertronics Gmbh",
    "wof:placetype":"venue"
},
  "geometry": {"coordinates":[7.0040612221,51.4317436218],"type":"Point"}
}