{
  "type": "Feature",
  "properties": {
    "iso:country":"DE",
    "sg:address":"Alte Str. 76",
    "sg:city":"Bremerv\u00f6rde",
    "sg:phone":"+49 4761/71705",
    "sg:postcode":"27432",
    "sg:province":"Niedersachsen",
    "wof:name":"Adriatik",
    "wof:placetype":"venue"
},
  "geometry": {"coordinates":[9.1440925598,53.4856643677],"type":"Point"}
}