{
  "type": "Feature",
  "properties": {
    "iso:country":"DE",
    "sg:address":"Claudiusstr. 1",
    "sg:city":"Titz",
    "sg:phone":"+49 2463/8536",
    "sg:postcode":"52445",
    "sg:province":"Nordrhein-Westfalen",
    "wof:name":"Sibille Goertz Masseurin",
    "wof:placetype":"venue"
},
  "geometry": {"coordinates":[6.428649,51.004745],"type":"Point"}
}