{
  "type": "Feature",
  "properties": {
    "iso:country":"DE",
    "sg:address":"Seydlitzstr. 15",
    "sg:city":"Karlsruhe",
    "sg:phone":"+49 721/552366",
    "sg:postcode":"76185",
    "sg:province":"Baden-W\u00fcrttemberg",
    "wof:name":"Von Steffelin Gmbh",
    "wof:placetype":"venue"
},
  "geometry": {"coordinates":[8.3567228317,49.0218887329],"type":"Point"}
}