{
  "type": "Feature",
  "properties": {
    "iso:country":"DE",
    "sg:address":"Dominikanergasse 13",
    "sg:city":"Augsburg",
    "sg:phone":"+49 821/514403",
    "sg:postcode":"86150",
    "sg:province":"Bayern",
    "wof:name":"Petzak-sonohara Streichinstrumente",
    "wof:placetype":"venue"
},
  "geometry": {"coordinates":[10.9003324509,48.3655319214],"type":"Point"}
}