{
  "type": "Feature",
  "properties": {
    "iso:country":"DE",
    "sg:address":"Elsenztalsiedlung",
    "sg:city":"Eppingen",
    "sg:phone":"+49 7260/304",
    "sg:postcode":"75031",
    "sg:province":"Baden-W\u00fcrttemberg",
    "wof:name":"Volker Benz",
    "wof:placetype":"venue"
},
  "geometry": {"coordinates":[8.850068,49.166462],"type":"Point"}
}