{
  "type": "Feature",
  "properties": {
    "iso:country":"DE",
    "sg:address":"Scharnhorststr. 131",
    "sg:city":"Bremen",
    "sg:phone":"+49 421/234261",
    "sg:postcode":"28211",
    "sg:province":"Bremen",
    "wof:name":"Walter Schmidt",
    "wof:placetype":"venue"
},
  "geometry": {"coordinates":[8.859617,53.087589],"type":"Point"}
}