{
  "type": "Feature",
  "properties": {
    "iso:country":"DE",
    "sg:address":"Kuhleger 1",
    "sg:city":"Ostseebad Wustrow",
    "sg:phone":"+49 38220/80573",
    "sg:postcode":"18347",
    "sg:province":"Mecklenburg-Vorpommern",
    "wof:name":"Irma Lamowski",
    "wof:placetype":"venue"
},
  "geometry": {"coordinates":[12.3952198029,54.3450012207],"type":"Point"}
}