{
  "type": "Feature",
  "properties": {
    "iso:country":"DE",
    "sg:address":"Hardenbergstr 66",
    "sg:city":"Leverkusen",
    "sg:phone":"+49 214/6027963",
    "sg:postcode":"51373",
    "sg:province":"Nordrhein-Westfalen",
    "wof:name":"Emca Gmbh",
    "wof:placetype":"venue"
},
  "geometry": {"coordinates":[6.9930801392,51.0450057983],"type":"Point"}
}