{
  "type": "Feature",
  "properties": {
    "iso:country":"DE",
    "sg:address":"Sonnenwall 34",
    "sg:city":"Duisburg",
    "sg:phone":"+49 203/23166",
    "sg:postcode":"47051",
    "sg:province":"Nordrhein-Westfalen",
    "wof:name":"K. Haffke & Co.",
    "wof:placetype":"venue"
},
  "geometry": {"coordinates":[6.762342,51.432507],"type":"Point"}
}