{
  "type": "Feature",
  "properties": {
    "iso:country":"DE",
    "sg:address":"Gr\u00fcntenstr. 56",
    "sg:city":"Berlin",
    "sg:postcode":"12107",
    "sg:province":"Berlin",
    "wof:name":"Europlus Import Export Serguei Kitaev",
    "wof:placetype":"venue"
},
  "geometry": {"coordinates":[13.4023036957,52.4376564026],"type":"Point"}
}