{
  "type": "Feature",
  "properties": {
    "iso:country":"DE",
    "sg:address":"Rheurdter Str. 182",
    "sg:city":"Issum",
    "sg:phone":"+49 2835/6780",
    "sg:postcode":"47661",
    "sg:province":"Nordrhein-Westfalen",
    "wof:name":"Wilhelm Bettsteller",
    "wof:placetype":"venue"
},
  "geometry": {"coordinates":[6.461242,51.491444],"type":"Point"}
}