{
  "type": "Feature",
  "properties": {
    "iso:country":"DE",
    "sg:address":"Schmittstr. 55",
    "sg:city":"Bonn",
    "sg:phone":"+49 228/624176",
    "sg:postcode":"53123",
    "sg:province":"Nordrhein-Westfalen",
    "wof:name":"Karl Hochgeschurz Elektro-installation",
    "wof:placetype":"venue"
},
  "geometry": {"coordinates":[7.048003,50.711826],"type":"Point"}
}