{
  "type": "Feature",
  "properties": {
    "iso:country":"DE",
    "sg:address":"Hohes Ufer 1",
    "sg:city":"Neustadt",
    "sg:phone":"+49 5072/7330",
    "sg:postcode":"31535",
    "sg:province":"Niedersachsen",
    "wof:name":"Ulrich Gleser Heilpraktiker",
    "wof:placetype":"venue"
},
  "geometry": {"coordinates":[9.5837831497,52.5771369934],"type":"Point"}
}