{
  "type": "Feature",
  "properties": {
    "iso:country":"DE",
    "sg:address":"Am Schultenhof 1",
    "sg:city":"Gevelsberg",
    "sg:phone":"+49 2332/60307",
    "sg:postcode":"58285",
    "sg:province":"Nordrhein-Westfalen",
    "wof:name":"Stadtarchiv",
    "wof:placetype":"venue"
},
  "geometry": {"coordinates":[7.380617,51.335686],"type":"Point"}
}