{
  "type": "Feature",
  "properties": {
    "iso:country":"DE",
    "sg:address":"Kappelstr. 21",
    "sg:city":"T\u00fcbingen",
    "sg:phone":"+49 7071/791909",
    "sg:postcode":"72072",
    "sg:province":"Baden-W\u00fcrttemberg",
    "wof:name":"Gudrun Sinner Gravieranstalt",
    "wof:placetype":"venue"
},
  "geometry": {"coordinates":[9.0489959717,48.4991722107],"type":"Point"}
}