{
  "type": "Feature",
  "properties": {
    "iso:country":"DE",
    "sg:address":"Hauptstr. 7",
    "sg:city":"Altensteig",
    "sg:phone":"+49 7453/930364",
    "sg:postcode":"72213",
    "sg:province":"Baden-W\u00fcrttemberg",
    "wof:name":"Pizzaservice Ali Afsar",
    "wof:placetype":"venue"
},
  "geometry": {"coordinates":[8.617643,48.602558],"type":"Point"}
}