{
  "type": "Feature",
  "properties": {
    "iso:country":"DE",
    "sg:address":"Lessingstr. 17",
    "sg:city":"Wehretal",
    "sg:phone":"+49 5651/4327",
    "sg:postcode":"37287",
    "sg:province":"Hessen",
    "wof:name":"Lothar Sch\u00f6newolf",
    "wof:placetype":"venue"
},
  "geometry": {"coordinates":[10.0071983337,51.1535835266],"type":"Point"}
}