{
  "type": "Feature",
  "properties": {
    "iso:country":"DE",
    "sg:address":"Marktplatz 21",
    "sg:city":"Parkstein",
    "sg:phone":"+49 9602/61263",
    "sg:postcode":"92711",
    "sg:province":"Bayern",
    "wof:name":"A. Schaller",
    "wof:placetype":"venue"
},
  "geometry": {"coordinates":[12.06867,49.732189],"type":"Point"}
}