{
  "type": "Feature",
  "properties": {
    "iso:country":"DE",
    "sg:address":"William-Zipperer-Str. 134",
    "sg:city":"Leipzig",
    "sg:phone":"+49 341/4806613",
    "sg:postcode":"04179",
    "sg:province":"Sachsen",
    "wof:name":"J\u00fcrgen Moldt Wirtschaftsberater E. K.",
    "wof:placetype":"venue"
},
  "geometry": {"coordinates":[12.3169107437,51.3477897644],"type":"Point"}
}