{
  "type": "Feature",
  "properties": {
    "iso:country":"DE",
    "sg:address":"Bierhelderweg 4",
    "sg:city":"Heidelberg",
    "sg:phone":"+49 6221/314312",
    "sg:postcode":"69126",
    "sg:province":"Baden-W\u00fcrttemberg",
    "wof:name":"Bodega Don Jamon",
    "wof:placetype":"venue"
},
  "geometry": {"coordinates":[8.693145752,49.377784729],"type":"Point"}
}