{
  "type": "Feature",
  "properties": {
    "iso:country":"DE",
    "sg:address":"Nordwall 3 a",
    "sg:city":"Wunstorf",
    "sg:phone":"+49 5031/913344",
    "sg:postcode":"31515",
    "sg:province":"Niedersachsen",
    "wof:name":"Volker Wenskus Architekt",
    "wof:placetype":"venue"
},
  "geometry": {"coordinates":[9.425496,52.427197],"type":"Point"}
}