{
  "type": "Feature",
  "properties": {
    "iso:country":"DE",
    "sg:address":"K\u00f6hlerweg 40",
    "sg:city":"Schwanstetten",
    "sg:phone":"+49 9170/94550",
    "sg:postcode":"90596",
    "sg:province":"Bayern",
    "wof:name":"Kurt Wolter",
    "wof:placetype":"venue"
},
  "geometry": {"coordinates":[11.1283378601,49.3081169128],"type":"Point"}
}