{
  "type": "Feature",
  "properties": {
    "iso:country":"DE",
    "sg:address":"Fahrenbacher Str.",
    "sg:city":"F\u00fcrth",
    "sg:phone":"+49 6253/7992",
    "sg:postcode":"64658",
    "sg:province":"Hessen",
    "wof:name":"Uloth & Schneeberger",
    "wof:placetype":"venue"
},
  "geometry": {"coordinates":[8.77684,49.645321],"type":"Point"}
}