{
  "type": "Feature",
  "properties": {
    "iso:country":"DE",
    "sg:address":"Huppenbergstr. 35",
    "sg:city":"Wachtberg",
    "sg:phone":"+49 2225/99150",
    "sg:postcode":"53343",
    "sg:province":"Nordrhein-Westfalen",
    "wof:name":"Opt Art Home Service Feinschmecker Gmbh",
    "wof:placetype":"venue"
},
  "geometry": {"coordinates":[7.115380764,50.6551933289],"type":"Point"}
}