{
  "type": "Feature",
  "properties": {
    "iso:country":"DE",
    "sg:address":"Zum Biotop 1a",
    "sg:city":"Bergheim",
    "sg:phone":"+49 2271/767894",
    "sg:postcode":"50127",
    "sg:province":"Nordrhein-Westfalen",
    "wof:name":"A. Elberding",
    "wof:placetype":"venue"
},
  "geometry": {"coordinates":[6.652575016,50.9418373108],"type":"Point"}
}