{
  "type": "Feature",
  "properties": {
    "iso:country":"DE",
    "sg:address":"Nei\u00dfestr. 17",
    "sg:city":"Landshut",
    "sg:phone":"+49 871/53703",
    "sg:postcode":"84036",
    "sg:province":"Bayern",
    "wof:name":"K. Salisch",
    "wof:placetype":"venue"
},
  "geometry": {"coordinates":[12.2079229355,48.567440033],"type":"Point"}
}