{
  "type": "Feature",
  "properties": {
    "iso:country":"DE",
    "sg:address":"\u00d6stliche Rheinbr\u00fcckenstr. 25",
    "sg:city":"Karlsruhe",
    "sg:phone":"+49 721/956060",
    "sg:postcode":"76187",
    "sg:province":"Baden-W\u00fcrttemberg",
    "wof:name":"Richard Schmid Gmbh",
    "wof:placetype":"venue"
},
  "geometry": {"coordinates":[8.341006279,49.0312805176],"type":"Point"}
}