{
  "type": "Feature",
  "properties": {
    "iso:country":"DE",
    "sg:address":"Dorfstr. 4",
    "sg:city":"Burgwedel",
    "sg:phone":"+49 5139/87795",
    "sg:postcode":"30938",
    "sg:province":"Niedersachsen",
    "wof:name":"L\u00fcbbe & Potthoff Montageleistungen Gmbh",
    "wof:placetype":"venue"
},
  "geometry": {"coordinates":[9.8472881317,52.5635070801],"type":"Point"}
}