{
  "type": "Feature",
  "properties": {
    "iso:country":"DE",
    "sg:address":"Spreuerbergstr. 61",
    "sg:city":"Untergruppenbach",
    "sg:phone":"+49 7130/3471",
    "sg:postcode":"74199",
    "sg:province":"Baden-W\u00fcrttemberg",
    "wof:name":"Schettler Gmbh",
    "wof:placetype":"venue"
},
  "geometry": {"coordinates":[9.3287296295,49.0891723633],"type":"Point"}
}