{
  "type": "Feature",
  "properties": {
    "iso:country":"DE",
    "sg:address":"Wetschhauser Hof 1",
    "sg:city":"Ottweiler",
    "sg:phone":"+49 6858/8746",
    "sg:postcode":"66564",
    "sg:province":"Saarland",
    "wof:name":"Stoll Gmbh",
    "wof:placetype":"venue"
},
  "geometry": {"coordinates":[7.2086849213,49.4209594727],"type":"Point"}
}