{
  "type": "Feature",
  "properties": {
    "iso:country":"DE",
    "sg:address":"Schuhstr. 3",
    "sg:city":"Celle",
    "sg:phone":"+49 5141/22588",
    "sg:postcode":"29221",
    "sg:province":"Niedersachsen",
    "wof:name":"Rossmann Drogeriemarkt",
    "wof:placetype":"venue"
},
  "geometry": {"coordinates":[10.081632,52.62534],"type":"Point"}
}