{
  "type": "Feature",
  "properties": {
    "iso:country":"DE",
    "sg:address":"Im Gansbruch 15",
    "sg:city":"Linnich",
    "sg:phone":"+49 2462/3694",
    "sg:postcode":"52441",
    "sg:province":"Nordrhein-Westfalen",
    "wof:name":"Reiner Jungherz",
    "wof:placetype":"venue"
},
  "geometry": {"coordinates":[6.283033,50.98156],"type":"Point"}
}