{
  "type": "Feature",
  "properties": {
    "iso:country":"DE",
    "sg:address":"Max-Greve-Str. 30",
    "sg:city":"Bochum",
    "sg:phone":"+49 4923/451814",
    "sg:postcode":"44791",
    "sg:province":"Nordrhein-Westfalen",
    "wof:name":"H W\u00d6sthoff Messtechnik Gmbh",
    "wof:placetype":"venue"
},
  "geometry": {"coordinates":[7.232533,51.485897],"type":"Point"}
}