{
  "type": "Feature",
  "properties": {
    "iso:country":"DE",
    "sg:address":"Paulusstr. 6",
    "sg:city":"Dorsten",
    "sg:phone":"+49 2362/71503",
    "sg:postcode":"46284",
    "sg:province":"Nordrhein-Westfalen",
    "wof:name":"Katholisches Pfarramt St. Paul",
    "wof:placetype":"venue"
},
  "geometry": {"coordinates":[7.020775795,51.6732139587],"type":"Point"}
}