{
  "type": "Feature",
  "properties": {
    "iso:country":"DE",
    "sg:address":"Waldstr. 122",
    "sg:city":"Neu-Isenburg",
    "sg:phone":"+49 6102/17870",
    "sg:postcode":"63263",
    "sg:province":"Hessen",
    "wof:name":"Frosch",
    "wof:placetype":"venue"
},
  "geometry": {"coordinates":[8.6920957565,50.051815033],"type":"Point"}
}