{
  "type": "Feature",
  "properties": {
    "iso:country":"DE",
    "sg:address":"Weidestr. 29",
    "sg:city":"Eutin",
    "sg:phone":"+49 4521/72874",
    "sg:postcode":"23701",
    "sg:province":"Schleswig-Holstein",
    "wof:name":"T. Bichel",
    "wof:placetype":"venue"
},
  "geometry": {"coordinates":[10.6168546677,54.1311607361],"type":"Point"}
}