{
  "type": "Feature",
  "properties": {
    "iso:country":"DE",
    "sg:address":"Birkenweg 8",
    "sg:city":"Haiger",
    "sg:phone":"+49 2773/2150",
    "sg:postcode":"35708",
    "sg:province":"Hessen",
    "wof:name":"Ulrike B\u00f6hmer",
    "wof:placetype":"venue"
},
  "geometry": {"coordinates":[8.176046,50.750935],"type":"Point"}
}