{
  "type": "Feature",
  "properties": {
    "iso:country":"DE",
    "sg:address":"Heedfelder Str. 2",
    "sg:city":"Schalksm\u00fchle",
    "sg:phone":"+49 2351/54949",
    "sg:postcode":"58579",
    "sg:province":"Nordrhein-Westfalen",
    "wof:name":"Wohnen Und Baden Gmbh",
    "wof:placetype":"venue"
},
  "geometry": {"coordinates":[7.5819849968,51.2569351196],"type":"Point"}
}