{
  "type": "Feature",
  "properties": {
    "iso:country":"DE",
    "sg:address":"Dr.-Ernst-Derra-Str 2",
    "sg:city":"Passau",
    "sg:phone":"+49 851/4902880",
    "sg:postcode":"94036",
    "sg:province":"Bayern",
    "wof:name":"Silverwire Ag",
    "wof:placetype":"venue"
},
  "geometry": {"coordinates":[13.412338,48.556828],"type":"Point"}
}