{
  "type": "Feature",
  "properties": {
    "iso:country":"DE",
    "sg:address":"Bahnhofstr. 1",
    "sg:city":"Frankenberg",
    "sg:phone":"+49 37206/2942",
    "sg:postcode":"09669",
    "sg:province":"Sachsen",
    "wof:name":"Bahnhofsgastst\u00e4tte",
    "wof:placetype":"venue"
},
  "geometry": {"coordinates":[13.0431547165,50.91147995],"type":"Point"}
}