{
  "type": "Feature",
  "properties": {
    "iso:country":"DE",
    "sg:address":"Auf Der Wei\u00df 1",
    "sg:city":"Siegen",
    "sg:phone":"+49 4927/140580",
    "sg:postcode":"57074",
    "sg:province":"Nordrhein-Westfalen",
    "wof:name":"Reklame Rudolph Gmbh",
    "wof:placetype":"venue"
},
  "geometry": {"coordinates":[8.078801,50.86517],"type":"Point"}
}