{
  "type": "Feature",
  "properties": {
    "iso:country":"DE",
    "sg:address":"85049",
    "sg:city":"Ingolstadt-Zuchering",
    "sg:postcode":"85049",
    "sg:province":"Bayern",
    "wof:name":"Raiffeisenbank Zuchering-brunnenreuth Eg",
    "wof:placetype":"venue"
},
  "geometry": {"coordinates":[11.40555,48.71241],"type":"Point"}
}