{
  "type": "Feature",
  "properties": {
    "iso:country":"DE",
    "sg:address":"Ringstr. 18",
    "sg:city":"Itterbeck",
    "sg:phone":"+49 5948/542",
    "sg:postcode":"49847",
    "sg:province":"Niedersachsen",
    "wof:name":"Jan-hindrich Sch\u00fctte",
    "wof:placetype":"venue"
},
  "geometry": {"coordinates":[6.7501649857,52.4758262634],"type":"Point"}
}