{
  "type": "Feature",
  "properties": {
    "iso:country":"DE",
    "sg:address":"Kaiserstr. 16",
    "sg:city":"Duisburg",
    "sg:phone":"+49 2065/49626",
    "sg:postcode":"47229",
    "sg:province":"Nordrhein-Westfalen",
    "wof:name":"Hilbrans Speditions-gmbh",
    "wof:placetype":"venue"
},
  "geometry": {"coordinates":[6.707207,51.390488],"type":"Point"}
}