{
  "type": "Feature",
  "properties": {
    "iso:country":"DE",
    "sg:address":"Ochsenwerder Norderdeich 212",
    "sg:city":"Hamburg",
    "sg:phone":"+49 40/7373822",
    "sg:postcode":"21037",
    "sg:province":"Hamburg",
    "wof:name":"G\u00fcnter Sannmann",
    "wof:placetype":"venue"
},
  "geometry": {"coordinates":[10.112327,53.466148],"type":"Point"}
}