{
  "type": "Feature",
  "properties": {
    "iso:country":"DE",
    "sg:address":"Frerener Str. 20",
    "sg:city":"Messingen",
    "sg:phone":"+49 5905/233",
    "sg:postcode":"49832",
    "sg:province":"Niedersachsen",
    "wof:name":"Karl-heinz Strotmann Architekt",
    "wof:placetype":"venue"
},
  "geometry": {"coordinates":[7.457346,52.465954],"type":"Point"}
}