{
  "type": "Feature",
  "properties": {
    "iso:country":"DE",
    "sg:address":"Maximilianstr. 4",
    "sg:city":"Berchtesgaden",
    "sg:phone":"+49 8652/964976",
    "sg:postcode":"83471",
    "sg:province":"Bayern",
    "wof:name":"Fritz Dollinger Gmbh & Co. Kg",
    "wof:placetype":"venue"
},
  "geometry": {"coordinates":[13.001201,47.631283],"type":"Point"}
}