{
  "type": "Feature",
  "properties": {
    "iso:country":"DE",
    "sg:address":"Goldk\u00e4ferweg 17",
    "sg:city":"Berlin",
    "sg:phone":"+49 30/3732572",
    "sg:postcode":"13589",
    "sg:province":"Berlin",
    "wof:name":"K. Giersch & Partner Fertigfenster Vertrieb",
    "wof:placetype":"venue"
},
  "geometry": {"coordinates":[13.149756,52.558369],"type":"Point"}
}