{
  "type": "Feature",
  "properties": {
    "iso:country":"DE",
    "sg:address":"Windorfer Str. 7",
    "sg:city":"Leipzig",
    "sg:phone":"+49 341/4807426",
    "sg:postcode":"04229",
    "sg:province":"Sachsen",
    "wof:name":"Campus Immobilien Gmbh",
    "wof:placetype":"venue"
},
  "geometry": {"coordinates":[12.330526,51.319485],"type":"Point"}
}