{
  "type": "Feature",
  "properties": {
    "iso:country":"DE",
    "sg:address":"Dorfplatz 10",
    "sg:city":"Cremlingen",
    "sg:phone":"+49 5306/4116",
    "sg:postcode":"38162",
    "sg:province":"Niedersachsen",
    "wof:name":"Joachim Hornig",
    "wof:placetype":"venue"
},
  "geometry": {"coordinates":[10.625847,52.270992],"type":"Point"}
}