{
  "type": "Feature",
  "properties": {
    "iso:country":"DE",
    "sg:address":"Wiesenstr. 33",
    "sg:city":"Dietzenbach",
    "sg:phone":"+49 6074/865120",
    "sg:postcode":"63128",
    "sg:province":"Hessen",
    "wof:name":"Gerhard Fiedler Rechtsanwalt",
    "wof:placetype":"venue"
},
  "geometry": {"coordinates":[8.7713766098,50.0140304565],"type":"Point"}
}