{
  "type": "Feature",
  "properties": {
    "iso:country":"DE",
    "sg:address":"Am Ochsenzoll 51",
    "sg:city":"Norderstedt",
    "sg:postcode":"22850",
    "sg:province":"Schleswig-Holstein",
    "wof:name":"L\u00fcdemann & L\u00fcdemann Gmbh",
    "wof:placetype":"venue"
},
  "geometry": {"coordinates":[10.0125827789,53.6814956665],"type":"Point"}
}