{
  "type": "Feature",
  "properties": {
    "iso:country":"DE",
    "sg:address":"Bahnhofstr. 31",
    "sg:city":"Fridingen",
    "sg:phone":"+49 7463/458",
    "sg:postcode":"78567",
    "sg:province":"Baden-W\u00fcrttemberg",
    "wof:name":"Gebr. Spiegel Kg",
    "wof:placetype":"venue"
},
  "geometry": {"coordinates":[8.933372,48.022488],"type":"Point"}
}