{
  "type": "Feature",
  "properties": {
    "iso:country":"DE",
    "sg:address":"Steinb\u00fcchelstr. 32",
    "sg:city":"Roetgen",
    "sg:phone":"+49 2471/3597",
    "sg:postcode":"52159",
    "sg:province":"Nordrhein-Westfalen",
    "wof:name":"Dr. J. Kowalewski Ingenieur",
    "wof:placetype":"venue"
},
  "geometry": {"coordinates":[6.1916098595,50.6374702454],"type":"Point"}
}