{
  "type": "Feature",
  "properties": {
    "iso:country":"DE",
    "sg:address":"Schillerstr. 14",
    "sg:city":"Kolitzheim",
    "sg:phone":"+49 9723/1339",
    "sg:postcode":"97509",
    "sg:province":"Bayern",
    "wof:name":"K. H. M\u00fcller",
    "wof:placetype":"venue"
},
  "geometry": {"coordinates":[10.2670221329,49.9565963745],"type":"Point"}
}