{
  "type": "Feature",
  "properties": {
    "iso:country":"DE",
    "sg:address":"Industriestr. 1",
    "sg:city":"Gundelsheim",
    "sg:phone":"+49 951/4072958",
    "sg:postcode":"96163",
    "sg:province":"Bayern",
    "wof:name":"Flach Gmbh",
    "wof:placetype":"venue"
},
  "geometry": {"coordinates":[10.925544,49.937172],"type":"Point"}
}