{
  "type": "Feature",
  "properties": {
    "iso:country":"DE",
    "sg:address":"Am Kahlberg 7",
    "sg:city":"He\u00dfdorf",
    "sg:phone":"+49 9135/799427",
    "sg:postcode":"91093",
    "sg:province":"Bayern",
    "wof:name":"Hengster & Partner Gmbh",
    "wof:placetype":"venue"
},
  "geometry": {"coordinates":[10.9088773727,49.6175117493],"type":"Point"}
}