{
  "type": "Feature",
  "properties": {
    "iso:country":"DE",
    "sg:address":"Wilhelm-Hamacher-Platz 9",
    "sg:city":"Troisdorf",
    "sg:phone":"+49 2241/978071",
    "sg:postcode":"53840",
    "sg:province":"Nordrhein-Westfalen",
    "wof:name":"R. Schaarschmidt",
    "wof:placetype":"venue"
},
  "geometry": {"coordinates":[7.1565752029,50.814037323],"type":"Point"}
}