{
  "type": "Feature",
  "properties": {
    "iso:country":"DE",
    "sg:address":"Himmelsgasse 7",
    "sg:city":"Idstein",
    "sg:phone":"+49 6126/54593",
    "sg:postcode":"65510",
    "sg:province":"Hessen",
    "wof:name":"Kaffeehaus",
    "wof:placetype":"venue"
},
  "geometry": {"coordinates":[8.270678,50.221806],"type":"Point"}
}