{
  "type": "Feature",
  "properties": {
    "iso:country":"DE",
    "sg:address":"Mielenforster Str. 54",
    "sg:city":"K\u00f6ln",
    "sg:phone":"+49 221/681990",
    "sg:postcode":"51069",
    "sg:province":"Nordrhein-Westfalen",
    "wof:name":"Moderne Grabmalkunst Huppertz Gmbh",
    "wof:placetype":"venue"
},
  "geometry": {"coordinates":[7.0691862106,50.9611473083],"type":"Point"}
}