{
  "type": "Feature",
  "properties": {
    "iso:country":"DE",
    "sg:address":"Dorfstr. 60",
    "sg:city":"Tecklenburg",
    "sg:phone":"+49 5482/7100",
    "sg:postcode":"49545",
    "sg:province":"Nordrhein-Westfalen",
    "wof:name":"Heinz Folsche",
    "wof:placetype":"venue"
},
  "geometry": {"coordinates":[7.7521438599,52.2273139954],"type":"Point"}
}