{
  "type": "Feature",
  "properties": {
    "iso:country":"DE",
    "sg:address":"Fischerweg 15a",
    "sg:city":"Buchloe",
    "sg:postcode":"86807",
    "sg:province":"Bayern",
    "wof:name":"Net Sys Ag",
    "wof:placetype":"venue"
},
  "geometry": {"coordinates":[10.717287,48.01376],"type":"Point"}
}