{
  "type": "Feature",
  "properties": {
    "iso:country":"DE",
    "sg:address":"Bismarckstr. 11-13",
    "sg:city":"Pinneberg",
    "sg:phone":"+49 4101/5010",
    "sg:postcode":"25421",
    "sg:province":"Schleswig-Holstein",
    "wof:name":"Volksbank Pinneberg-uetersen Eg",
    "wof:placetype":"venue"
},
  "geometry": {"coordinates":[9.7963,53.661755],"type":"Point"}
}