{
  "type": "Feature",
  "properties": {
    "iso:country":"DE",
    "sg:address":"Auf dem Leimen 17",
    "sg:city":"Gr\u00fcnstadt",
    "sg:phone":"+49 6359/3242",
    "sg:postcode":"67269",
    "sg:province":"Rheinland-Pfalz",
    "wof:name":"Tisch & M\u00fcller Kino",
    "wof:placetype":"venue"
},
  "geometry": {"coordinates":[8.1613845825,49.5735321045],"type":"Point"}
}