{
  "type": "Feature",
  "properties": {
    "iso:country":"DE",
    "sg:address":"Moselstr. 14",
    "sg:city":"Traben-Trarbach",
    "sg:phone":"+49 6541/3438",
    "sg:postcode":"56841",
    "sg:province":"Rheinland-Pfalz",
    "wof:name":"Grube & M\u00fcller Handarbeitsstube",
    "wof:placetype":"venue"
},
  "geometry": {"coordinates":[7.11181,49.948288],"type":"Point"}
}