{
  "type": "Feature",
  "properties": {
    "iso:country":"DE",
    "sg:address":"Haller Weg 7",
    "sg:city":"Bielefeld",
    "sg:phone":"+49 521/141035",
    "sg:postcode":"33617",
    "sg:province":"Nordrhein-Westfalen",
    "wof:name":"W. Lewe",
    "wof:placetype":"venue"
},
  "geometry": {"coordinates":[8.519816,52.012703],"type":"Point"}
}