{
  "type": "Feature",
  "properties": {
    "iso:country":"DE",
    "sg:address":"Dorfstr. 38a",
    "sg:city":"Sch\u00f6nburg",
    "sg:phone":"+49 3445/702172",
    "sg:postcode":"06618",
    "sg:province":"Sachsen-Anhalt",
    "wof:name":"J\u00f6rg St\u00fctzer",
    "wof:placetype":"venue"
},
  "geometry": {"coordinates":[11.8687467575,51.1625442505],"type":"Point"}
}