{
  "type": "Feature",
  "properties": {
    "iso:country":"DE",
    "sg:address":"Rankbachstr.",
    "sg:city":"Renningen",
    "sg:phone":"+49 7159/924769",
    "sg:postcode":"71272",
    "sg:province":"Baden-W\u00fcrttemberg",
    "wof:name":"Musikschule Renningen",
    "wof:placetype":"venue"
},
  "geometry": {"coordinates":[8.9299097061,48.7712554932],"type":"Point"}
}