{
  "type": "Feature",
  "properties": {
    "iso:country":"DE",
    "sg:address":"Plantage 5",
    "sg:city":"Bremen",
    "sg:phone":"+49 421/3762002",
    "sg:postcode":"28215",
    "sg:province":"Bremen",
    "wof:name":"B. & L. Sportmanagement Gmbh",
    "wof:placetype":"venue"
},
  "geometry": {"coordinates":[8.8058900833,53.0880432129],"type":"Point"}
}