{
  "type": "Feature",
  "properties": {
    "iso:country":"DE",
    "sg:address":"Max-von-Laue-Str. 16",
    "sg:city":"Remscheid",
    "sg:phone":"+49 2191/609020",
    "sg:postcode":"42897",
    "sg:province":"Nordrhein-Westfalen",
    "wof:name":"H. D. Knorz Vertriebs Gmbh",
    "wof:placetype":"venue"
},
  "geometry": {"coordinates":[7.2723550797,51.1996040344],"type":"Point"}
}