{
  "type": "Feature",
  "properties": {
    "iso:country":"DE",
    "sg:address":"Ahornstr. 16",
    "sg:city":"Schwerin",
    "sg:phone":"+49 385/4841925",
    "sg:postcode":"19057",
    "sg:province":"Mecklenburg-Vorpommern",
    "wof:name":"Khb K\u00f6ppinger Holz & Bautenschutz",
    "wof:placetype":"venue"
},
  "geometry": {"coordinates":[11.3601036072,53.644618988],"type":"Point"}
}