{
  "type": "Feature",
  "properties": {
    "iso:country":"DE",
    "sg:address":"Marktstr. 14",
    "sg:city":"Ilmenau",
    "sg:phone":"+49 3677/841273",
    "sg:postcode":"98693",
    "sg:province":"Th\u00fcringen",
    "wof:name":"Alpha-immobilien",
    "wof:placetype":"venue"
},
  "geometry": {"coordinates":[10.9151468277,50.6862106323],"type":"Point"}
}