{
  "type": "Feature",
  "properties": {
    "iso:country":"DE",
    "sg:address":"Rochusstr. 496",
    "sg:city":"M\u00f6nchengladbach",
    "sg:phone":"+49 2161/570467",
    "sg:postcode":"41179",
    "sg:province":"Nordrhein-Westfalen",
    "wof:name":"Christoph Bergmann",
    "wof:placetype":"venue"
},
  "geometry": {"coordinates":[6.33027,51.158001],"type":"Point"}
}