{
  "type": "Feature",
  "properties": {
    "iso:country":"DE",
    "sg:address":"Heidensche Str. 70",
    "sg:city":"Lage",
    "sg:phone":"+49 4967/0863360",
    "sg:postcode":"32791",
    "sg:province":"Nordrhein-Westfalen",
    "wof:name":"Phillipp Schneider Gmbh & Co.",
    "wof:placetype":"venue"
},
  "geometry": {"coordinates":[7.8406410217,49.8033332825],"type":"Point"}
}