{
  "type": "Feature",
  "properties": {
    "iso:country":"DE",
    "sg:address":"Fasanenstr. 8a",
    "sg:city":"Unterhaching",
    "sg:phone":"+49 89/6110146",
    "sg:postcode":"82008",
    "sg:province":"Bayern",
    "wof:name":"Rawa-tec Gmbh",
    "wof:placetype":"venue"
},
  "geometry": {"coordinates":[11.6117048264,48.0691452026],"type":"Point"}
}