{
  "type": "Feature",
  "properties": {
    "iso:country":"DE",
    "sg:address":"Kirchstr. 2",
    "sg:city":"Kaltennordheim",
    "sg:phone":"+49 36966/80535",
    "sg:postcode":"36452",
    "sg:province":"Th\u00fcringen",
    "wof:name":"Eiscafe A. Jung",
    "wof:placetype":"venue"
},
  "geometry": {"coordinates":[10.158326,50.62698],"type":"Point"}
}