{
  "type": "Feature",
  "properties": {
    "iso:country":"DE",
    "sg:address":"Vorm W\u00fcrzburger Tor 6",
    "sg:city":"Rothenburg",
    "sg:phone":"+49 9861/95710",
    "sg:postcode":"91541",
    "sg:province":"Bayern",
    "wof:name":"Rappen",
    "wof:placetype":"venue"
},
  "geometry": {"coordinates":[10.1848211288,49.3796920776],"type":"Point"}
}