{
  "type": "Feature",
  "properties": {
    "iso:country":"DE",
    "sg:address":"Mittelstr. 2",
    "sg:city":"Duisburg",
    "sg:phone":"+49 203/400756",
    "sg:postcode":"47169",
    "sg:province":"Nordrhein-Westfalen",
    "wof:name":"Kath. Pfarramt St. Peter",
    "wof:placetype":"venue"
},
  "geometry": {"coordinates":[6.7552981377,51.5055046082],"type":"Point"}
}