{
  "type": "Feature",
  "properties": {
    "iso:country":"DE",
    "sg:address":"Albrechtstr. 10",
    "sg:city":"Bad Marienberg",
    "sg:phone":"+49 2661/939780",
    "sg:postcode":"56470",
    "sg:province":"Rheinland-Pfalz",
    "wof:name":"Sparkassen Versicherung",
    "wof:placetype":"venue"
},
  "geometry": {"coordinates":[7.949570179,50.6499481201],"type":"Point"}
}