{
  "type": "Feature",
  "properties": {
    "iso:country":"DE",
    "sg:address":"Querstr. 2",
    "sg:city":"Wiesbaden",
    "sg:phone":"+49 611/67762",
    "sg:postcode":"65203",
    "sg:province":"Hessen",
    "wof:name":"Peter R\u00f6hricht",
    "wof:placetype":"venue"
},
  "geometry": {"coordinates":[8.238756,50.04884],"type":"Point"}
}