{
  "type": "Feature",
  "properties": {
    "iso:country":"DE",
    "sg:address":"Im Greuth 7",
    "sg:city":"Bad Urach",
    "sg:phone":"+49 7125/4740",
    "sg:postcode":"72574",
    "sg:province":"Baden-W\u00fcrttemberg",
    "wof:name":"N. Oezdemir",
    "wof:placetype":"venue"
},
  "geometry": {"coordinates":[9.4012241364,48.4924545288],"type":"Point"}
}