{
  "type": "Feature",
  "properties": {
    "iso:country":"DE",
    "sg:address":"Rieterstr. 55",
    "sg:city":"N\u00fcrnberg",
    "sg:phone":"+49 911/3938681",
    "sg:postcode":"90419",
    "sg:province":"Bayern",
    "wof:name":"Bestattungsinstitut Anton Gmbh",
    "wof:placetype":"venue"
},
  "geometry": {"coordinates":[11.064286,49.462311],"type":"Point"}
}