{
  "type": "Feature",
  "properties": {
    "iso:country":"DE",
    "sg:address":"Bermbachtal 36 a",
    "sg:city":"Ruhla",
    "sg:phone":"+49 36929/80348",
    "sg:postcode":"99842",
    "sg:province":"Th\u00fcringen",
    "wof:name":"Turn- Und Sportgemeinschaft Ruhla E.v.",
    "wof:placetype":"venue"
},
  "geometry": {"coordinates":[10.3623275757,50.8909492493],"type":"Point"}
}