{
  "type": "Feature",
  "properties": {
    "iso:country":"DE",
    "sg:address":"Spitalwall 41",
    "sg:city":"Bad Windsheim",
    "sg:phone":"+49 9841/1657",
    "sg:postcode":"91438",
    "sg:province":"Bayern",
    "wof:name":"E. B\u00fcttner Inh. H. B\u00fcttner",
    "wof:placetype":"venue"
},
  "geometry": {"coordinates":[10.413983345,49.504901886],"type":"Point"}
}