{
  "type": "Feature",
  "properties": {
    "iso:country":"DE",
    "sg:address":"Rudolf-Breitscheid-Str. 66",
    "sg:city":"Zschopau",
    "sg:postcode":"09405",
    "sg:province":"Sachsen",
    "wof:name":"W. H\u00fcbler",
    "wof:placetype":"venue"
},
  "geometry": {"coordinates":[13.079252,50.746086],"type":"Point"}
}