{
  "type": "Feature",
  "properties": {
    "iso:country":"DE",
    "sg:address":"Schmiedestr. 19",
    "sg:city":"Stapel",
    "sg:phone":"+49 38841/20363",
    "sg:postcode":"19273",
    "sg:province":"Mecklenburg-Vorpommern",
    "wof:name":"Christoph Tiede",
    "wof:placetype":"venue"
},
  "geometry": {"coordinates":[10.9623699188,53.2539100647],"type":"Point"}
}