{
  "type": "Feature",
  "properties": {
    "iso:country":"DE",
    "sg:address":"Alte Str. 4",
    "sg:city":"Rudolstadt",
    "sg:postcode":"07407",
    "sg:province":"Th\u00fcringen",
    "wof:name":"Mdh Bad Design Und Haustechnik Gmbh",
    "wof:placetype":"venue"
},
  "geometry": {"coordinates":[11.336667,50.720139],"type":"Point"}
}