{
  "type": "Feature",
  "properties": {
    "iso:country":"DE",
    "sg:address":"Storkower Str. 1b",
    "sg:city":"Spreenhagen",
    "sg:phone":"+49 33633/6055",
    "sg:postcode":"15528",
    "sg:province":"Brandenburg",
    "wof:name":"Pik Gastronomie Kfz- Und Warenhandel Gmbh",
    "wof:placetype":"venue"
},
  "geometry": {"coordinates":[13.8980350494,52.3295822144],"type":"Point"}
}