{
  "type": "Feature",
  "properties": {
    "iso:country":"DE",
    "sg:address":"Fischerstr. 4",
    "sg:city":"Sternberg",
    "sg:phone":"+49 3847/2502",
    "sg:postcode":"19406",
    "sg:province":"Mecklenburg-Vorpommern",
    "wof:name":"An Der Bleiche",
    "wof:placetype":"venue"
},
  "geometry": {"coordinates":[11.8258666992,53.7118148804],"type":"Point"}
}