{
  "type": "Feature",
  "properties": {
    "iso:country":"DE",
    "sg:address":"Darmst\u00e4dter Str. 77",
    "sg:city":"M\u00fcnster",
    "sg:postcode":"64839",
    "sg:province":"Hessen",
    "wof:name":"Holthaus Textil- Handels Gmbh",
    "wof:placetype":"venue"
},
  "geometry": {"coordinates":[8.8553543091,49.9187736511],"type":"Point"}
}