{
  "type": "Feature",
  "properties": {
    "iso:country":"DE",
    "sg:address":"Werbenweg 4",
    "sg:city":"Bad Bellingen",
    "sg:phone":"+49 7635/1829",
    "sg:postcode":"79415",
    "sg:province":"Baden-W\u00fcrttemberg",
    "wof:name":"Eckbert Giesel",
    "wof:placetype":"venue"
},
  "geometry": {"coordinates":[7.533632,47.707584],"type":"Point"}
}