{
  "type": "Feature",
  "properties": {
    "iso:country":"DE",
    "sg:address":"Am Raseweg 3",
    "sg:city":"Pirna",
    "sg:postcode":"01796",
    "sg:province":"Sachsen",
    "wof:name":"Volker Matthe\u00df",
    "wof:placetype":"venue"
},
  "geometry": {"coordinates":[13.8896656036,50.9792823792],"type":"Point"}
}