{
  "type": "Feature",
  "properties": {
    "iso:country":"DE",
    "sg:address":"Am Kronsmoor 10",
    "sg:city":"Nahe",
    "sg:phone":"+49 4535/6037",
    "sg:postcode":"23866",
    "sg:province":"Schleswig-Holstein",
    "wof:name":"Heinz Hinzer",
    "wof:placetype":"venue"
},
  "geometry": {"coordinates":[10.1463432312,53.7963294983],"type":"Point"}
}