{
  "type": "Feature",
  "properties": {
    "iso:country":"DE",
    "sg:address":"T\u00f6ngesgasse 35",
    "sg:city":"Frankfurt",
    "sg:phone":"+49 69/284956",
    "sg:postcode":"60311",
    "sg:province":"Hessen",
    "wof:name":"Railslide Sport Und Mode Gmbh",
    "wof:placetype":"venue"
},
  "geometry": {"coordinates":[8.682544,50.113052],"type":"Point"}
}