{
  "type": "Feature",
  "properties": {
    "iso:country":"DE",
    "sg:address":"Breslauer Str. 62",
    "sg:city":"Langenhagen",
    "sg:phone":"+49 511/772521",
    "sg:postcode":"30853",
    "sg:province":"Niedersachsen",
    "wof:name":"Hubert Wehr Leiternverleih",
    "wof:placetype":"venue"
},
  "geometry": {"coordinates":[9.7635393143,52.4388847351],"type":"Point"}
}