{
  "type": "Feature",
  "properties": {
    "iso:country":"DE",
    "sg:address":"Max-Planck-Str. 1",
    "sg:city":"Dieburg",
    "sg:phone":"+49 6071/25290",
    "sg:postcode":"64807",
    "sg:province":"Hessen",
    "wof:name":"Andreas Baumer",
    "wof:placetype":"venue"
},
  "geometry": {"coordinates":[8.853995,49.902092],"type":"Point"}
}