{
  "type": "Feature",
  "properties": {
    "iso:country":"DE",
    "sg:address":"Theodor-Marwitz-Str 2",
    "sg:city":"L\u00fcneburg",
    "sg:phone":"+49 4131/89181936",
    "sg:postcode":"21337",
    "sg:province":"Niedersachsen",
    "wof:name":"Ico-system",
    "wof:placetype":"venue"
},
  "geometry": {"coordinates":[10.476565361,53.2439308167],"type":"Point"}
}