{
  "type": "Feature",
  "properties": {
    "iso:country":"DE",
    "sg:address":"An der Ringwiese",
    "sg:city":"Jena",
    "sg:phone":"+49 3641/617477",
    "sg:postcode":"07745",
    "sg:province":"Th\u00fcringen",
    "wof:name":"Klubhaus Ringwiese",
    "wof:placetype":"venue"
},
  "geometry": {"coordinates":[11.5785942078,50.9017906189],"type":"Point"}
}