{
  "type": "Feature",
  "properties": {
    "iso:country":"DE",
    "sg:address":"Krefelder Str. 97",
    "sg:city":"Duisburg",
    "sg:phone":"+49 2065/75606",
    "sg:postcode":"47226",
    "sg:province":"Nordrhein-Westfalen",
    "wof:name":"Eiscafe Roberto Polesel",
    "wof:placetype":"venue"
},
  "geometry": {"coordinates":[6.709083,51.406689],"type":"Point"}
}