{
  "type": "Feature",
  "properties": {
    "iso:country":"DE",
    "sg:address":"K\u00f6lner Str. 111-113",
    "sg:city":"Hellenthal",
    "sg:phone":"+49 2482/1533",
    "sg:postcode":"53940",
    "sg:province":"Nordrhein-Westfalen",
    "wof:name":"Josef Kirch",
    "wof:placetype":"venue"
},
  "geometry": {"coordinates":[6.4496297836,50.4887084961],"type":"Point"}
}