{
  "type": "Feature",
  "properties": {
    "iso:country":"DE",
    "sg:address":"Bahnhofstr. 67",
    "sg:city":"Schweich",
    "sg:phone":"+49 6502/2314",
    "sg:postcode":"54338",
    "sg:province":"Rheinland-Pfalz",
    "wof:name":"Josef Back",
    "wof:placetype":"venue"
},
  "geometry": {"coordinates":[6.744996,49.826763],"type":"Point"}
}