{
  "type": "Feature",
  "properties": {
    "iso:country":"DE",
    "sg:address":"Am Krebsgraben 15",
    "sg:city":"Villingen-Schwenningen",
    "sg:phone":"+49 7721/502166",
    "sg:postcode":"78048",
    "sg:province":"Baden-W\u00fcrttemberg",
    "wof:name":"Petrolplaza",
    "wof:placetype":"venue"
},
  "geometry": {"coordinates":[8.444209,48.069061],"type":"Point"}
}