{
  "type": "Feature",
  "properties": {
    "iso:country":"DE",
    "sg:address":"Bismarckstr. 14",
    "sg:city":"Versmold",
    "sg:phone":"+49 5423/5452",
    "sg:postcode":"33775",
    "sg:province":"Nordrhein-Westfalen",
    "wof:name":"Monika Scholz",
    "wof:placetype":"venue"
},
  "geometry": {"coordinates":[8.119056,52.02243],"type":"Point"}
}