{
  "type": "Feature",
  "properties": {
    "iso:country":"DE",
    "sg:address":"Dorfstr. 21",
    "sg:city":"Jersleben",
    "sg:phone":"+49 39201/29940",
    "sg:postcode":"39326",
    "sg:province":"Sachsen-Anhalt",
    "wof:name":"Heinz Penack",
    "wof:placetype":"venue"
},
  "geometry": {"coordinates":[11.582908,52.245075],"type":"Point"}
}