{
  "type": "Feature",
  "properties": {
    "iso:country":"DE",
    "sg:address":"P\u00fctterstr. 13",
    "sg:city":"Iserlohn",
    "sg:phone":"+49 2371/61767",
    "sg:postcode":"58636",
    "sg:province":"Nordrhein-Westfalen",
    "wof:name":"Heinz Guttek Elektroinstallation",
    "wof:placetype":"venue"
},
  "geometry": {"coordinates":[7.711192,51.376286],"type":"Point"}
}