{
  "type": "Feature",
  "properties": {
    "iso:country":"DE",
    "sg:address":"Etzelbach 67",
    "sg:city":"Kirchhasel",
    "sg:phone":"+49 36742/22306",
    "sg:postcode":"07407",
    "sg:province":"Th\u00fcringen",
    "wof:name":"Wid Bau Gmbh",
    "wof:placetype":"venue"
},
  "geometry": {"coordinates":[11.4310035706,50.7368774414],"type":"Point"}
}