{
  "type": "Feature",
  "properties": {
    "iso:country":"DE",
    "sg:address":"Parkstr. 44",
    "sg:city":"G\u00fctersloh",
    "sg:phone":"+49 5241/54370",
    "sg:postcode":"33332",
    "sg:province":"Nordrhein-Westfalen",
    "wof:name":"Restaurant Bockskrug",
    "wof:placetype":"venue"
},
  "geometry": {"coordinates":[8.3861246109,51.8993377686],"type":"Point"}
}