{
  "type": "Feature",
  "properties": {
    "iso:country":"DE",
    "sg:address":"Gronauer Str. 65",
    "sg:city":"Gronau",
    "sg:phone":"+49 2565/1546",
    "sg:postcode":"48599",
    "sg:province":"Nordrhein-Westfalen",
    "wof:name":"Karl Kramer",
    "wof:placetype":"venue"
},
  "geometry": {"coordinates":[7.0351061821,52.1811256409],"type":"Point"}
}