{
  "type": "Feature",
  "properties": {
    "iso:country":"DE",
    "sg:address":"Breslauer Str. 3",
    "sg:city":"Marktleugast",
    "sg:phone":"+49 9255/200",
    "sg:postcode":"95352",
    "sg:province":"Bayern",
    "wof:name":"G. Fischer",
    "wof:placetype":"venue"
},
  "geometry": {"coordinates":[11.6075897217,50.1662712097],"type":"Point"}
}