{
  "type": "Feature",
  "properties": {
    "iso:country":"DE",
    "sg:address":"Kirchfeldstr. 8",
    "sg:city":"Frielendorf",
    "sg:phone":"+49 5684/930067",
    "sg:postcode":"34621",
    "sg:province":"Hessen",
    "wof:name":"Rewe-markt Knapp Ohg",
    "wof:placetype":"venue"
},
  "geometry": {"coordinates":[9.321456,50.973392],"type":"Point"}
}