{
  "type": "Feature",
  "properties": {
    "iso:country":"DE",
    "sg:address":"Industriering 9",
    "sg:city":"Schm\u00f6lln",
    "sg:phone":"+49 34491/83341",
    "sg:postcode":"04626",
    "sg:province":"Th\u00fcringen",
    "wof:name":"Strakosa Gmbh Strassenbau Koppisch U.sachse",
    "wof:placetype":"venue"
},
  "geometry": {"coordinates":[12.384270668,50.8897361755],"type":"Point"}
}