{
  "type": "Feature",
  "properties": {
    "iso:country":"DE",
    "sg:address":"Hauptstr. 14",
    "sg:city":"Nordermeldorf",
    "sg:phone":"+49 4832/1450",
    "sg:postcode":"25704",
    "sg:province":"Schleswig-Holstein",
    "wof:name":"Hinrich Wiese",
    "wof:placetype":"venue"
},
  "geometry": {"coordinates":[9.014221,54.116055],"type":"Point"}
}