{
  "type": "Feature",
  "properties": {
    "iso:country":"DE",
    "sg:address":"Hein-Heckroth-Str. 20",
    "sg:city":"Giessen",
    "sg:phone":"+49 641/38990",
    "sg:postcode":"35390",
    "sg:province":"Hessen",
    "wof:name":"Best Western Hotel Steinsgarten",
    "wof:placetype":"venue"
},
  "geometry": {"coordinates":[8.683300972,50.5813560486],"type":"Point"}
}