{
  "type": "Feature",
  "properties": {
    "iso:country":"DE",
    "sg:address":"M\u00f6rfelder Landstr. 149",
    "sg:city":"Frankfurt",
    "sg:phone":"+49 69/6314226",
    "sg:postcode":"60598",
    "sg:province":"Hessen",
    "wof:name":"Epilationsstudio Eidmann",
    "wof:placetype":"venue"
},
  "geometry": {"coordinates":[8.6806945801,50.0948524475],"type":"Point"}
}