{
  "type": "Feature",
  "properties": {
    "iso:country":"DE",
    "sg:address":"B\u00e4renall. 16",
    "sg:city":"Hamburg",
    "sg:phone":"+49 40/68959970",
    "sg:postcode":"22041",
    "sg:province":"Hamburg",
    "wof:name":"Steffi Moden H.h. G\u00dclcher Gmbh",
    "wof:placetype":"venue"
},
  "geometry": {"coordinates":[10.064164,53.569458],"type":"Point"}
}