{
  "type": "Feature",
  "properties": {
    "iso:country":"DE",
    "sg:address":"Graf-Adolf-Str. 59",
    "sg:city":"D\u00fcsseldorf",
    "sg:phone":"+49 211/370121",
    "sg:postcode":"40210",
    "sg:province":"Nordrhein-Westfalen",
    "wof:name":"Kinsho Corporation D\u00fcsseldorf Branch Office",
    "wof:placetype":"venue"
},
  "geometry": {"coordinates":[6.7854471207,51.2187538147],"type":"Point"}
}