{
  "type": "Feature",
  "properties": {
    "iso:country":"DE",
    "sg:address":"Damaschkeweg 5",
    "sg:city":"Rheinsberg",
    "sg:postcode":"16831",
    "sg:province":"Brandenburg",
    "wof:name":"Rheinsberger Arbeitsf\u00f6rderungs Besch\u00e4ftigungs- Und",
    "wof:placetype":"venue"
},
  "geometry": {"coordinates":[12.895636,53.094788],"type":"Point"}
}