{
  "type": "Feature",
  "properties": {
    "iso:country":"DE",
    "sg:address":"Am Kohlgraben 25",
    "sg:city":"Minden",
    "sg:phone":"+49 571/56513",
    "sg:postcode":"32429",
    "sg:province":"Nordrhein-Westfalen",
    "wof:name":"H.-d. Jopp Rechtsanwalt",
    "wof:placetype":"venue"
},
  "geometry": {"coordinates":[8.8932151794,52.2727622986],"type":"Point"}
}