{
  "type": "Feature",
  "properties": {
    "iso:country":"DE",
    "sg:address":"Marktstr. 1",
    "sg:city":"Ennepetal",
    "sg:phone":"+49 2333/71717",
    "sg:postcode":"58256",
    "sg:province":"Nordrhein-Westfalen",
    "wof:name":"Pro Sicherheit Gmbh",
    "wof:placetype":"venue"
},
  "geometry": {"coordinates":[7.348798,51.299316],"type":"Point"}
}