{
  "type": "Feature",
  "properties": {
    "iso:country":"DE",
    "sg:address":"Kohlh\u00f6kerstr. 4",
    "sg:city":"Bremen",
    "sg:phone":"+49 421/792590",
    "sg:postcode":"28203",
    "sg:province":"Bremen",
    "wof:name":"Hans Sommer Beteiligungs-gmbh",
    "wof:placetype":"venue"
},
  "geometry": {"coordinates":[8.819781,53.074486],"type":"Point"}
}