{
  "type": "Feature",
  "properties": {
    "iso:country":"DE",
    "sg:address":"Prager Str. 19",
    "sg:city":"Frankfurt",
    "sg:phone":"+49 335/65876",
    "sg:postcode":"15234",
    "sg:province":"Brandenburg",
    "wof:name":"Bernd Dieter Lehm",
    "wof:placetype":"venue"
},
  "geometry": {"coordinates":[14.536539,52.350689],"type":"Point"}
}