{
  "type": "Feature",
  "properties": {
    "iso:country":"DE",
    "sg:address":"Nienstedter Str. 3",
    "sg:city":"Bad M\u00fcnder",
    "sg:phone":"+49 5042/8553",
    "sg:postcode":"31848",
    "sg:province":"Niedersachsen",
    "wof:name":"Hans H. Imhoff",
    "wof:placetype":"venue"
},
  "geometry": {"coordinates":[9.425337,52.235344],"type":"Point"}
}