{
  "type": "Feature",
  "properties": {
    "iso:country":"DE",
    "sg:address":"L\u00fcneburger Str. 7",
    "sg:city":"Ebstorf",
    "sg:phone":"+49 5822/2072",
    "sg:postcode":"29574",
    "sg:province":"Niedersachsen",
    "wof:name":"Klostersch\u00e4nke Hannemann",
    "wof:placetype":"venue"
},
  "geometry": {"coordinates":[10.4146137238,53.0297012329],"type":"Point"}
}