{
  "type": "Feature",
  "properties": {
    "iso:country":"DE",
    "sg:address":"Duisburger Str. 68",
    "sg:city":"N\u00fcrnberg",
    "sg:phone":"+49 911/646055",
    "sg:postcode":"90451",
    "sg:province":"Bayern",
    "wof:name":"Schulze & Co. Kg",
    "wof:placetype":"venue"
},
  "geometry": {"coordinates":[11.0477218628,49.3991508484],"type":"Point"}
}