{
  "type": "Feature",
  "properties": {
    "iso:country":"DE",
    "sg:address":"Schualnger 1",
    "sg:city":"Happurg",
    "sg:phone":"+49 9151",
    "sg:postcode":"91230",
    "sg:province":"Bayern",
    "wof:name":"Alles Rund Um Mittelfranken, Das Alnet.de",
    "wof:placetype":"venue"
},
  "geometry": {"coordinates":[11.4697704315,49.4939193726],"type":"Point"}
}