{
  "type": "Feature",
  "properties": {
    "iso:country":"DE",
    "sg:address":"Heidemannstr 1",
    "sg:city":"M\u00fcnchen",
    "sg:phone":"+49 89/31829414",
    "sg:postcode":"80939",
    "sg:province":"Bayern",
    "wof:name":"Newtec Gmbh",
    "wof:placetype":"venue"
},
  "geometry": {"coordinates":[11.585931778,48.2011604309],"type":"Point"}
}