{
  "type": "Feature",
  "properties": {
    "iso:country":"DE",
    "sg:address":"Martin-K\u00e4rcher-Str. 10",
    "sg:city":"Lampertheim",
    "sg:phone":"+49 6206/58793",
    "sg:postcode":"68623",
    "sg:province":"Hessen",
    "wof:name":"Gie\u00dfkanne",
    "wof:placetype":"venue"
},
  "geometry": {"coordinates":[8.4735202789,49.5935745239],"type":"Point"}
}