{
  "type": "Feature",
  "properties": {
    "iso:country":"DE",
    "sg:address":"Wettinerstr. 4",
    "sg:city":"Altenburg",
    "sg:phone":"+49 4600/4210",
    "sg:postcode":"04600",
    "sg:province":"Th\u00fcringen",
    "wof:name":"Max Willner Rechtsanwalt",
    "wof:placetype":"venue"
},
  "geometry": {"coordinates":[12.4442043304,50.9937973022],"type":"Point"}
}