{
  "type": "Feature",
  "properties": {
    "iso:country":"DE",
    "sg:address":"Schulstr. 1",
    "sg:city":"Gaildorf",
    "sg:phone":"+49 7971/8836",
    "sg:postcode":"74405",
    "sg:province":"Baden-W\u00fcrttemberg",
    "wof:name":"Dora Aberle",
    "wof:placetype":"venue"
},
  "geometry": {"coordinates":[9.76963,49.000019],"type":"Point"}
}