{
  "type": "Feature",
  "properties": {
    "iso:country":"DE",
    "sg:address":"Friedhofstr. 15",
    "sg:city":"Saterland",
    "sg:phone":"+49 4498/1863",
    "sg:postcode":"26683",
    "sg:province":"Niedersachsen",
    "wof:name":"Neiteler & Brand Bauelemente Gmbh",
    "wof:placetype":"venue"
},
  "geometry": {"coordinates":[7.68508,53.104111],"type":"Point"}
}