{
  "type": "Feature",
  "properties": {
    "iso:country":"DE",
    "sg:address":"Im Hamm 12",
    "sg:city":"Bedburg",
    "sg:phone":"+49 2272/3321",
    "sg:postcode":"50181",
    "sg:province":"Nordrhein-Westfalen",
    "wof:name":"Hans-dieter Zima",
    "wof:placetype":"venue"
},
  "geometry": {"coordinates":[6.5356459618,51.0034599304],"type":"Point"}
}