{
  "type": "Feature",
  "properties": {
    "iso:country":"DE",
    "sg:address":"Stadionring 16",
    "sg:city":"Ratingen",
    "sg:postcode":"40878",
    "sg:province":"Nordrhein-Westfalen",
    "wof:name":"Wilma Bauprojekte Nordrhein-westfalen Gmbh",
    "wof:placetype":"venue"
},
  "geometry": {"coordinates":[6.840683,51.297478],"type":"Point"}
}