{
  "type": "Feature",
  "properties": {
    "iso:country":"DE",
    "sg:address":"Ettlensegart 15",
    "sg:city":"Tuttlingen",
    "sg:phone":"+49 4974/612113",
    "sg:postcode":"78532",
    "sg:province":"Baden-W\u00fcrttemberg",
    "wof:name":"Frank Simmank",
    "wof:placetype":"venue"
},
  "geometry": {"coordinates":[8.8424444199,47.9701652527],"type":"Point"}
}