{
  "type": "Feature",
  "properties": {
    "iso:country":"DE",
    "sg:address":"Huntloser Str. 8",
    "sg:city":"Hatten",
    "sg:phone":"+49 4482/1559",
    "sg:postcode":"26209",
    "sg:province":"Niedersachsen",
    "wof:name":"Gastst\u00e4tte Renate Rothert",
    "wof:placetype":"venue"
},
  "geometry": {"coordinates":[8.3214502335,53.0107688904],"type":"Point"}
}