{
  "type": "Feature",
  "properties": {
    "iso:country":"DE",
    "sg:address":"Am Hochfeld 17",
    "sg:city":"Hofheim",
    "sg:phone":"+49 6192/37828",
    "sg:postcode":"65719",
    "sg:province":"Hessen",
    "wof:name":"Ivb Treuhand Ges. F\u00fcr Immobilien Verm\u00f6gensanlagen",
    "wof:placetype":"venue"
},
  "geometry": {"coordinates":[8.4463405609,50.0826873779],"type":"Point"}
}