{
  "type": "Feature",
  "properties": {
    "iso:country":"DE",
    "sg:address":"Augustenstrasse 44",
    "sg:city":"Muenchen",
    "sg:phone":"+49 89/5426260",
    "sg:postcode":"80333",
    "sg:province":"Bayern",
    "wof:name":"M.a.x. Informationstechnologie Ag",
    "wof:placetype":"venue"
},
  "geometry": {"coordinates":[11.562189,48.147682],"type":"Point"}
}