{
  "type": "Feature",
  "properties": {
    "iso:country":"DE",
    "sg:address":"Heinrich-Zille-Str. 16",
    "sg:city":"Bautzen",
    "sg:phone":"+49 3591/211186",
    "sg:postcode":"02625",
    "sg:province":"Sachsen",
    "wof:name":"Andreas Buhl",
    "wof:placetype":"venue"
},
  "geometry": {"coordinates":[14.4450721741,51.1625862122],"type":"Point"}
}