{
  "type": "Feature",
  "properties": {
    "iso:country":"DE",
    "sg:address":"Osterende 137",
    "sg:city":"Husum",
    "sg:phone":"+49 4841/72296",
    "sg:postcode":"25813",
    "sg:province":"Schleswig-Holstein",
    "wof:name":"Sir Henry",
    "wof:placetype":"venue"
},
  "geometry": {"coordinates":[9.0668821335,54.4806404114],"type":"Point"}
}