{
  "type": "Feature",
  "properties": {
    "iso:country":"DE",
    "sg:address":"Forststr. 26",
    "sg:city":"Chemnitz",
    "sg:phone":"+49 371/414252",
    "sg:postcode":"09130",
    "sg:province":"Sachsen",
    "wof:name":"Mitropa Mitteleurop\u00e4ische Schlafwagen- Und",
    "wof:placetype":"venue"
},
  "geometry": {"coordinates":[12.9452180862,50.844078064],"type":"Point"}
}