{
  "type": "Feature",
  "properties": {
    "iso:country":"DE",
    "sg:address":"Gr\u00f6pelinger Heerstr. 204",
    "sg:city":"Bremen",
    "sg:phone":"+49 421/691400",
    "sg:postcode":"28237",
    "sg:province":"Bremen",
    "wof:name":"Paco-reisen Gmbh",
    "wof:placetype":"venue"
},
  "geometry": {"coordinates":[8.7583370209,53.1162643433],"type":"Point"}
}