{
  "type": "Feature",
  "properties": {
    "iso:country":"DE",
    "sg:address":"Colsmanstr. 3",
    "sg:city":"Essen",
    "sg:phone":"+49 201/483848",
    "sg:postcode":"45257",
    "sg:province":"Nordrhein-Westfalen",
    "wof:name":"Wolfgang Schr\u00f6der Rechtsanwalt",
    "wof:placetype":"venue"
},
  "geometry": {"coordinates":[7.0814771652,51.3917350769],"type":"Point"}
}