{
  "type": "Feature",
  "properties": {
    "iso:country":"DE",
    "sg:city":"Berkau",
    "sg:phone":"+49 39089",
    "sg:postcode":"39624",
    "sg:province":"Sachsen-Anhalt",
    "wof:name":"Steuerb\u00fcro Leonhardt",
    "wof:placetype":"venue"
},
  "geometry": {"coordinates":[11.487907,52.63773],"type":"Point"}
}