{
  "type": "Feature",
  "properties": {
    "iso:country":"DE",
    "sg:address":"Liliencronstr. 23",
    "sg:city":"Hamburg",
    "sg:phone":"+49 40/6771435",
    "sg:postcode":"22149",
    "sg:province":"Hamburg",
    "wof:name":"Josephine Tornieporth",
    "wof:placetype":"venue"
},
  "geometry": {"coordinates":[10.161074,53.597576],"type":"Point"}
}