{
  "type": "Feature",
  "properties": {
    "iso:country":"DE",
    "sg:address":"Friesenstr 1",
    "sg:city":"Marienheide",
    "sg:phone":"+49 2264/28175",
    "sg:postcode":"51709",
    "sg:province":"Nordrhein-Westfalen",
    "wof:name":"Kreissparkasse K\u00f6ln",
    "wof:placetype":"venue"
},
  "geometry": {"coordinates":[7.5591,51.07],"type":"Point"}
}