{
  "type": "Feature",
  "properties": {
    "iso:country":"DE",
    "sg:address":"Hirsauer Str. 17",
    "sg:city":"Sindelfingen",
    "sg:phone":"+49 7031/801048",
    "sg:postcode":"71063",
    "sg:province":"Baden-W\u00fcrttemberg",
    "wof:name":"Steinle-m\u00f6bel Gmbh",
    "wof:placetype":"venue"
},
  "geometry": {"coordinates":[8.9982233047,48.711151123],"type":"Point"}
}