{
  "type": "Feature",
  "properties": {
    "iso:country":"DE",
    "sg:address":"Hintere Gasse 3",
    "sg:city":"Schw\u00e4bisch Gm\u00fcnd",
    "sg:phone":"+49 7173/8755",
    "sg:postcode":"73529",
    "sg:province":"Baden-W\u00fcrttemberg",
    "wof:name":"Paul Baumhauer",
    "wof:placetype":"venue"
},
  "geometry": {"coordinates":[9.8882360458,48.7888069153],"type":"Point"}
}