{
  "type": "Feature",
  "properties": {
    "iso:country":"DE",
    "sg:address":"B\u00fcrgerm.-Huber-Str. 11",
    "sg:city":"Krailling",
    "sg:phone":"+49 89/8598010",
    "sg:postcode":"82152",
    "sg:province":"Bayern",
    "wof:name":"Rudolf Wagner",
    "wof:placetype":"venue"
},
  "geometry": {"coordinates":[11.4132852554,48.0997657776],"type":"Point"}
}