{
  "type": "Feature",
  "properties": {
    "iso:country":"DE",
    "sg:address":"Bornewasserstr. 9",
    "sg:city":"Sulzbach",
    "sg:phone":"+49 6897/88642",
    "sg:postcode":"66280",
    "sg:province":"Saarland",
    "wof:name":"M. Pflieger & M. Knauber",
    "wof:placetype":"venue"
},
  "geometry": {"coordinates":[7.0701160431,49.3129119873],"type":"Point"}
}