{
  "type": "Feature",
  "properties": {
    "iso:country":"DE",
    "sg:address":"Lerchenweg 25a",
    "sg:city":"Lohmar",
    "sg:phone":"+49 2246/18110",
    "sg:postcode":"53797",
    "sg:province":"Nordrhein-Westfalen",
    "wof:name":"P. Unsel",
    "wof:placetype":"venue"
},
  "geometry": {"coordinates":[7.215605,50.830616],"type":"Point"}
}