{
  "type": "Feature",
  "properties": {
    "iso:country":"DE",
    "sg:address":"Schiffenberger Weg 109",
    "sg:city":"Gie\u00dfen",
    "sg:phone":"+49 641/9716501",
    "sg:postcode":"35394",
    "sg:province":"Hessen",
    "wof:name":"Bitprint",
    "wof:placetype":"venue"
},
  "geometry": {"coordinates":[8.689834,50.572102],"type":"Point"}
}