{
  "type": "Feature",
  "properties": {
    "iso:country":"DE",
    "sg:address":"Leopoldstr. 1",
    "sg:city":"Gaggenau",
    "sg:phone":"+49 7225/3011",
    "sg:postcode":"76571",
    "sg:province":"Baden-W\u00fcrttemberg",
    "wof:name":"Asga-scherer Verwaltungs Kg",
    "wof:placetype":"venue"
},
  "geometry": {"coordinates":[8.321484,48.805721],"type":"Point"}
}