{
  "type": "Feature",
  "properties": {
    "iso:country":"DE",
    "sg:address":"Sallstr. 48",
    "sg:city":"Hannover",
    "sg:postcode":"30171",
    "sg:province":"Niedersachsen",
    "wof:name":"Heinrich Nerge Gesellschaft F\u00fcr Finanzdienstleistungen",
    "wof:placetype":"venue"
},
  "geometry": {"coordinates":[9.7566556931,52.3646774292],"type":"Point"}
}