{
  "type": "Feature",
  "properties": {
    "iso:country":"DE",
    "sg:address":"Industriestr. 12",
    "sg:city":"Weyhe",
    "sg:phone":"+49 421/823222",
    "sg:postcode":"28844",
    "sg:province":"Niedersachsen",
    "wof:name":"Wilhelm Weber Gmbh & Co. Kg",
    "wof:placetype":"venue"
},
  "geometry": {"coordinates":[8.87047,53.021259],"type":"Point"}
}