{
  "type": "Feature",
  "properties": {
    "iso:country":"DE",
    "sg:address":"Ruschgraben 20",
    "sg:city":"Karlsruhe",
    "sg:phone":"+49 721/686656",
    "sg:postcode":"76139",
    "sg:province":"Baden-W\u00fcrttemberg",
    "wof:name":"Karl Heinz Thesen",
    "wof:placetype":"venue"
},
  "geometry": {"coordinates":[8.4576673508,49.0287437439],"type":"Point"}
}