{
  "type": "Feature",
  "properties": {
    "iso:country":"DE",
    "sg:address":"Plauener Str 23",
    "sg:city":"Netzschkau",
    "sg:phone":"+49 3765/39390",
    "sg:postcode":"08491",
    "sg:province":"Sachsen",
    "wof:name":"C. H. M\u00fcller Schuhtextilien U. Techn. Gewebe Gmbh",
    "wof:placetype":"venue"
},
  "geometry": {"coordinates":[12.249246,50.610512],"type":"Point"}
}