{
  "type": "Feature",
  "properties": {
    "iso:country":"DE",
    "sg:address":"Wieslensdorfer Str. 44",
    "sg:city":"Obersulm",
    "sg:phone":"+49 4971/30536",
    "sg:postcode":"74182",
    "sg:province":"Baden-W\u00fcrttemberg",
    "wof:name":"L & M Fahrzeugbau Gmbh",
    "wof:placetype":"venue"
},
  "geometry": {"coordinates":[9.4096317291,49.1410827637],"type":"Point"}
}