{
  "type": "Feature",
  "properties": {
    "iso:country":"DE",
    "sg:address":"Hauptstr. 30",
    "sg:city":"Ankum",
    "sg:phone":"+49 5462/1362",
    "sg:postcode":"49577",
    "sg:province":"Niedersachsen",
    "wof:name":"Pizzeria Piccolo",
    "wof:placetype":"venue"
},
  "geometry": {"coordinates":[7.8708138466,52.5422096252],"type":"Point"}
}