{
  "type": "Feature",
  "properties": {
    "iso:country":"DE",
    "sg:address":"Hans-Sachs-Str. 18b",
    "sg:city":"D\u00fcsseldorf",
    "sg:phone":"+49 211/673065",
    "sg:postcode":"40237",
    "sg:province":"Nordrhein-Westfalen",
    "wof:name":"Dr. Peter Baues",
    "wof:placetype":"venue"
},
  "geometry": {"coordinates":[6.8106079102,51.2340965271],"type":"Point"}
}