{
  "type": "Feature",
  "properties": {
    "iso:country":"DE",
    "sg:address":"Cannstatter Str. 21/1",
    "sg:city":"Remseck",
    "sg:phone":"+49 7146/90132",
    "sg:postcode":"71686",
    "sg:province":"Baden-W\u00fcrttemberg",
    "wof:name":"Kurt M\u00f6ssner",
    "wof:placetype":"venue"
},
  "geometry": {"coordinates":[9.2515907288,48.8630485535],"type":"Point"}
}