{
  "type": "Feature",
  "properties": {
    "iso:country":"DE",
    "sg:address":"Volksdorfer Weg 19",
    "sg:city":"Hamburg",
    "sg:phone":"+49 40/6401448",
    "sg:postcode":"22391",
    "sg:province":"Hamburg",
    "wof:name":"Werner Hoffmann Ingenieur",
    "wof:placetype":"venue"
},
  "geometry": {"coordinates":[10.0982971191,53.6407966614],"type":"Point"}
}