{
  "type": "Feature",
  "properties": {
    "iso:country":"DE",
    "sg:address":"Weinberg 10",
    "sg:city":"Alt Ruppin",
    "sg:phone":"+49 3391/7223",
    "sg:postcode":"16827",
    "sg:province":"Brandenburg",
    "wof:name":"D. Jahn",
    "wof:placetype":"venue"
},
  "geometry": {"coordinates":[12.84526,52.951447],"type":"Point"}
}