{
  "type": "Feature",
  "properties": {
    "iso:country":"DE",
    "sg:address":"Butzbachweg 7",
    "sg:city":"Aschaffenburg",
    "sg:phone":"+49 6021/930724",
    "sg:postcode":"63739",
    "sg:province":"Bayern",
    "wof:name":"Steurog Verm\u00f6gens- Verwaltungs Gmbh",
    "wof:placetype":"venue"
},
  "geometry": {"coordinates":[9.1694574356,49.9684143066],"type":"Point"}
}