{
  "type": "Feature",
  "properties": {
    "iso:country":"DE",
    "sg:address":"Stolzenfelsstr. 6",
    "sg:city":"Berlin",
    "sg:postcode":"10318",
    "sg:province":"Berlin",
    "wof:name":"Empa Projekt Gmbh",
    "wof:placetype":"venue"
},
  "geometry": {"coordinates":[13.5282020569,52.4806365967],"type":"Point"}
}