{
  "type": "Feature",
  "properties": {
    "iso:country":"DE",
    "sg:address":"Zur Deutschen Einheit 17",
    "sg:city":"M\u00fcnchen",
    "sg:phone":"+49 89/932979",
    "sg:postcode":"81929",
    "sg:province":"Bayern",
    "wof:name":"Rupert Kiesl Rechtsanwalt",
    "wof:placetype":"venue"
},
  "geometry": {"coordinates":[11.6428976059,48.151599884],"type":"Point"}
}