{
  "type": "Feature",
  "properties": {
    "iso:country":"DE",
    "sg:address":"Br\u00fcckenstr. 7",
    "sg:city":"Greiz",
    "sg:phone":"+49 3661/70550",
    "sg:postcode":"07973",
    "sg:province":"Th\u00fcringen",
    "wof:name":"Br\u00fccken-apotheke Inh. Dietrich Seyffarth",
    "wof:placetype":"venue"
},
  "geometry": {"coordinates":[12.198013,50.656158],"type":"Point"}
}