{
  "type": "Feature",
  "properties": {
    "iso:country":"DE",
    "sg:address":"Bachstr. 17",
    "sg:city":"Hennef",
    "sg:phone":"+49 2242/83239",
    "sg:postcode":"53773",
    "sg:province":"Nordrhein-Westfalen",
    "wof:name":"E. Brozza",
    "wof:placetype":"venue"
},
  "geometry": {"coordinates":[7.353412,50.77449],"type":"Point"}
}