{
  "type": "Feature",
  "properties": {
    "iso:country":"DE",
    "sg:address":"Bredstedter Str. 1",
    "sg:city":"Handewitt",
    "sg:phone":"+49 4630/5210",
    "sg:postcode":"24983",
    "sg:province":"Schleswig-Holstein",
    "wof:name":"Bahnsen-kieswerk H\u00fcllerup",
    "wof:placetype":"venue"
},
  "geometry": {"coordinates":[9.344119072,54.7362937927],"type":"Point"}
}