{
  "type": "Feature",
  "properties": {
    "iso:country":"DE",
    "sg:address":"Frankfurter Str. 30",
    "sg:city":"K\u00f6ln",
    "sg:phone":"+49 221/623908",
    "sg:postcode":"51065",
    "sg:province":"Nordrhein-Westfalen",
    "wof:name":"City-hosen G\u00f6rgens Gmbh & Co. Kg",
    "wof:placetype":"venue"
},
  "geometry": {"coordinates":[7.0065507889,50.9605941772],"type":"Point"}
}