{
  "type": "Feature",
  "properties": {
    "iso:country":"DE",
    "sg:address":"Am Graben 16",
    "sg:city":"Althengstett",
    "sg:phone":"+49 7051/928027",
    "sg:postcode":"75382",
    "sg:province":"Baden-W\u00fcrttemberg",
    "wof:name":"Berner Edv-beratung",
    "wof:placetype":"venue"
},
  "geometry": {"coordinates":[8.7778558731,48.7371940613],"type":"Point"}
}