{
  "type": "Feature",
  "properties": {
    "iso:country":"DE",
    "sg:address":"Mittelstr. 1 a",
    "sg:city":"Annarode",
    "sg:phone":"+49 34772/30182",
    "sg:postcode":"06308",
    "sg:province":"Sachsen-Anhalt",
    "wof:name":"Gerhard Ballenthin",
    "wof:placetype":"venue"
},
  "geometry": {"coordinates":[11.408701,51.551971],"type":"Point"}
}