{
  "type": "Feature",
  "properties": {
    "iso:country":"DE",
    "sg:address":"Vormann-Stuhr-Weg 29",
    "sg:city":"Dornumersiel",
    "sg:phone":"+49 4933/8453",
    "sg:postcode":"26553",
    "sg:province":"Niedersachsen",
    "wof:name":"G\u00e4stehaus K. Fehr",
    "wof:placetype":"venue"
},
  "geometry": {"coordinates":[7.4701509476,53.672668457],"type":"Point"}
}