{
  "type": "Feature",
  "properties": {
    "iso:country":"DE",
    "sg:address":"Im Entenbad 23",
    "sg:city":"L\u00f6rrach",
    "sg:phone":"+49 7621/95860",
    "sg:postcode":"79541",
    "sg:province":"Baden-W\u00fcrttemberg",
    "wof:name":"B Computervertriebs- Und Dienstleistungsgesellsch. Mbh",
    "wof:placetype":"venue"
},
  "geometry": {"coordinates":[7.7001180649,47.6411209106],"type":"Point"}
}