{
  "type": "Feature",
  "properties": {
    "iso:country":"DE",
    "sg:address":"Entrup 120",
    "sg:city":"Altenberge",
    "sg:phone":"+49 2505/431",
    "sg:postcode":"48341",
    "sg:province":"Nordrhein-Westfalen",
    "wof:name":"Bernhard Temming",
    "wof:placetype":"venue"
},
  "geometry": {"coordinates":[7.530088,52.07206],"type":"Point"}
}