{
  "type": "Feature",
  "properties": {
    "iso:country":"DE",
    "sg:address":"Burgstr. 4",
    "sg:city":"Kottenheim",
    "sg:phone":"+49 2651/41230",
    "sg:postcode":"56736",
    "sg:province":"Rheinland-Pfalz",
    "wof:name":"Degen",
    "wof:placetype":"venue"
},
  "geometry": {"coordinates":[7.2564101219,50.3484039307],"type":"Point"}
}