{
  "type": "Feature",
  "properties": {
    "iso:country":"DE",
    "sg:address":"Rodenbacher Str. 15 POSTFACH 1239",
    "sg:city":"Haiger",
    "sg:phone":"+49 4957/317680",
    "sg:postcode":"35702",
    "sg:province":"Hessen",
    "wof:name":"Rodenberg Ag",
    "wof:placetype":"venue"
},
  "geometry": {"coordinates":[8.8789768219,52.2090835571],"type":"Point"}
}