{
  "type": "Feature",
  "properties": {
    "iso:country":"DE",
    "sg:address":"Osterallee 207",
    "sg:city":"Flendsburg",
    "sg:phone":"+49 461",
    "sg:postcode":"24944",
    "sg:province":"Schleswig-Holstein",
    "wof:name":"Autohaus Thurner Gmbh & Cokg",
    "wof:placetype":"venue"
},
  "geometry": {"coordinates":[-94.53010559080001,45.9534683228],"type":"Point"}
}