{
  "type": "Feature",
  "properties": {
    "iso:country":"DE",
    "sg:address":"Seestrasse 2",
    "sg:city":"Offenbach",
    "sg:phone":"+49 69/865558",
    "sg:postcode":"63075",
    "sg:province":"Hessen",
    "wof:name":"Pelagos",
    "wof:placetype":"venue"
},
  "geometry": {"coordinates":[8.7861566544,50.1202163696],"type":"Point"}
}