{
  "type": "Feature",
  "properties": {
    "iso:country":"DE",
    "sg:address":"Welzheimer Str. 19e",
    "sg:city":"Karlstein",
    "sg:phone":"+49 6188/95930",
    "sg:postcode":"63791",
    "sg:province":"Bayern",
    "wof:name":"Bit Verwaltungs Gmbh",
    "wof:placetype":"venue"
},
  "geometry": {"coordinates":[9.0290718079,50.0442733765],"type":"Point"}
}