{
  "type": "Feature",
  "properties": {
    "iso:country":"DE",
    "sg:address":"Markgrafenstr. 2-2",
    "sg:city":"Schwetzingen",
    "sg:phone":"+49 6202/3495",
    "sg:postcode":"68723",
    "sg:province":"Baden-W\u00fcrttemberg",
    "wof:name":"Hockenheimer Woche",
    "wof:placetype":"venue"
},
  "geometry": {"coordinates":[8.5763597488,49.379650116],"type":"Point"}
}