{
  "type": "Feature",
  "properties": {
    "iso:country":"DE",
    "sg:address":"Lange Str. 25-29",
    "sg:city":"Salzkotten",
    "sg:phone":"+49 5258/99944",
    "sg:postcode":"33154",
    "sg:province":"Nordrhein-Westfalen",
    "wof:name":"Elisabeth M\u00f6ller Kg",
    "wof:placetype":"venue"
},
  "geometry": {"coordinates":[8.605569,51.672577],"type":"Point"}
}