{
  "type": "Feature",
  "properties": {
    "iso:country":"DE",
    "sg:address":"Wettinerplatz 1",
    "sg:city":"Aue",
    "sg:phone":"+49 3771/22904",
    "sg:postcode":"08280",
    "sg:province":"Sachsen",
    "wof:name":"Rolf Heimer Drogerie",
    "wof:placetype":"venue"
},
  "geometry": {"coordinates":[12.699916,50.583431],"type":"Point"}
}