{
  "type": "Feature",
  "properties": {
    "iso:country":"DE",
    "sg:address":"Papendorfer Str. 7",
    "sg:city":"Brunsbek",
    "sg:phone":"+49 4107/850571",
    "sg:postcode":"22946",
    "sg:province":"Schleswig-Holstein",
    "wof:name":"Lescow Landmaschinen E. K.",
    "wof:placetype":"venue"
},
  "geometry": {"coordinates":[10.270459,53.596207],"type":"Point"}
}