{
  "type": "Feature",
  "properties": {
    "iso:country":"DE",
    "sg:address":"Wasenweg 3",
    "sg:city":"Mulfingen",
    "sg:phone":"+49 7938/427",
    "sg:postcode":"74673",
    "sg:province":"Baden-W\u00fcrttemberg",
    "wof:name":"Linus Braun",
    "wof:placetype":"venue"
},
  "geometry": {"coordinates":[9.74937,49.335659],"type":"Point"}
}