{
  "type": "Feature",
  "properties": {
    "iso:country":"DE",
    "sg:address":"Letschower Chaussee",
    "sg:city":"Schwaan",
    "sg:postcode":"18258",
    "sg:province":"Mecklenburg-Vorpommern",
    "wof:name":"Ksg Lager- Und Vermarktungsgesellschaft Mbh",
    "wof:placetype":"venue"
},
  "geometry": {"coordinates":[12.08921,53.936909],"type":"Point"}
}