{
  "type": "Feature",
  "properties": {
    "iso:country":"DE",
    "sg:address":"Beesenweide 3",
    "sg:city":"Moorrege",
    "sg:phone":"+49 4122/81633",
    "sg:postcode":"25436",
    "sg:province":"Schleswig-Holstein",
    "wof:name":"Vib-immobilien Inh. Dietrich Schulz",
    "wof:placetype":"venue"
},
  "geometry": {"coordinates":[9.680057,53.670776],"type":"Point"}
}