{
  "type": "Feature",
  "properties": {
    "iso:country":"DE",
    "sg:address":"Kr\u00e4merstr. 36",
    "sg:city":"Reutlingen",
    "sg:postcode":"72764",
    "sg:province":"Baden-W\u00fcrttemberg",
    "wof:name":"Gottfried Prochazka",
    "wof:placetype":"venue"
},
  "geometry": {"coordinates":[9.215993,48.494453],"type":"Point"}
}