{
  "type": "Feature",
  "properties": {
    "iso:country":"DE",
    "sg:address":"Metzholz 28",
    "sg:city":"Leichlingen",
    "sg:phone":"+49 2174/3775",
    "sg:postcode":"42799",
    "sg:province":"Nordrhein-Westfalen",
    "wof:name":"Schwebig Immobilienmakler",
    "wof:placetype":"venue"
},
  "geometry": {"coordinates":[7.0854568481,51.1096611023],"type":"Point"}
}