{
  "type": "Feature",
  "properties": {
    "iso:country":"DE",
    "sg:address":"Kreuzstr. 32",
    "sg:city":"Dingolfing",
    "sg:phone":"+49 8731/372116",
    "sg:postcode":"84130",
    "sg:province":"Bayern",
    "wof:name":"Frank Und Ernst Elektro-k\u00e4lte Gmbh",
    "wof:placetype":"venue"
},
  "geometry": {"coordinates":[12.48985672,48.6450576782],"type":"Point"}
}