{
  "type": "Feature",
  "properties": {
    "iso:country":"DE",
    "sg:address":"Haidhofstr. 2",
    "sg:city":"Wolfersdorf",
    "sg:phone":"+49 8168/4092",
    "sg:postcode":"85395",
    "sg:province":"Bayern",
    "wof:name":"Stark Verlags Gmbh",
    "wof:placetype":"venue"
},
  "geometry": {"coordinates":[11.738368988,48.477684021],"type":"Point"}
}