{
  "type": "Feature",
  "properties": {
    "iso:country":"DE",
    "sg:address":"J\u00f6rg-Ratgeb-Str. 29",
    "sg:city":"Pforzheim",
    "sg:phone":"+49 7231/24100",
    "sg:postcode":"75173",
    "sg:province":"Baden-W\u00fcrttemberg",
    "wof:name":"Peter Kreisz Heilpraktiker",
    "wof:placetype":"venue"
},
  "geometry": {"coordinates":[8.6965036392,48.8895988464],"type":"Point"}
}