{
  "type": "Feature",
  "properties": {
    "iso:country":"DE",
    "sg:address":"Brunnenstr. 5",
    "sg:city":"H\u00fcffelsheim",
    "sg:phone":"+49 671/32670",
    "sg:postcode":"55595",
    "sg:province":"Rheinland-Pfalz",
    "wof:name":"Ev. Pfarramt H\u00fcffelsheim",
    "wof:placetype":"venue"
},
  "geometry": {"coordinates":[7.8019480705,49.8234443665],"type":"Point"}
}