{
  "type": "Feature",
  "properties": {
    "iso:country":"DE",
    "sg:address":"Wittorfer Str. 43",
    "sg:city":"Visselh\u00f6vede",
    "sg:phone":"+49 4260/94141",
    "sg:postcode":"27374",
    "sg:province":"Niedersachsen",
    "wof:name":"Gebhard Lange",
    "wof:placetype":"venue"
},
  "geometry": {"coordinates":[9.5196466446,53.0081329346],"type":"Point"}
}