{
  "type": "Feature",
  "properties": {
    "iso:country":"DE",
    "sg:address":"Hermann-L\u00f6ns-Str. 83",
    "sg:city":"Aachen",
    "sg:phone":"+49 241/526940",
    "sg:postcode":"52078",
    "sg:province":"Nordrhein-Westfalen",
    "wof:name":"R. Reitz Immobilienmakler",
    "wof:placetype":"venue"
},
  "geometry": {"coordinates":[6.1671118736,50.757598877],"type":"Point"}
}