{
  "type": "Feature",
  "properties": {
    "iso:country":"DE",
    "sg:address":"Hohe Str. 49",
    "sg:city":"Twistringen",
    "sg:phone":"+49 4243/1260",
    "sg:postcode":"27239",
    "sg:province":"Niedersachsen",
    "wof:name":"Karl-heinz Lachmann",
    "wof:placetype":"venue"
},
  "geometry": {"coordinates":[8.6485214233,52.7975883484],"type":"Point"}
}