{
  "type": "Feature",
  "properties": {
    "iso:country":"DE",
    "sg:address":"Kesselsdorfer Str. 57",
    "sg:city":"Dresden",
    "sg:phone":"+49 351/4121523",
    "sg:postcode":"01159",
    "sg:province":"Sachsen",
    "wof:name":"R. Patzschewitz",
    "wof:placetype":"venue"
},
  "geometry": {"coordinates":[13.68758,51.04237],"type":"Point"}
}