{
  "type": "Feature",
  "properties": {
    "iso:country":"DE",
    "sg:address":"Steinfeldstr. 2",
    "sg:city":"Hannover",
    "sg:phone":"+49 511/2102444",
    "sg:postcode":"30453",
    "sg:province":"Niedersachsen",
    "wof:name":"Pizzeria Pizza-garten",
    "wof:placetype":"venue"
},
  "geometry": {"coordinates":[9.6821670532,52.3805236816],"type":"Point"}
}