{
  "type": "Feature",
  "properties": {
    "iso:country":"DE",
    "sg:address":"Burgstr. 40",
    "sg:city":"B\u00fcren",
    "sg:phone":"+49 2951/2272",
    "sg:postcode":"33142",
    "sg:province":"Nordrhein-Westfalen",
    "wof:name":"Wilhelm Roolf",
    "wof:placetype":"venue"
},
  "geometry": {"coordinates":[8.5584487915,51.5514373779],"type":"Point"}
}