{
  "type": "Feature",
  "properties": {
    "iso:country":"DE",
    "sg:address":"W\u00f6rthstr. 10",
    "sg:city":"Baden-Baden",
    "sg:phone":"+49 7221/51381",
    "sg:postcode":"76532",
    "sg:province":"Baden-W\u00fcrttemberg",
    "wof:name":"H. Peter",
    "wof:placetype":"venue"
},
  "geometry": {"coordinates":[8.199717,48.782944],"type":"Point"}
}