{
  "type": "Feature",
  "properties": {
    "iso:country":"DE",
    "sg:address":"Schweriner Str. 15",
    "sg:city":"Parchim",
    "sg:postcode":"19370",
    "sg:province":"Mecklenburg-Vorpommern",
    "wof:name":"Heike Pulz",
    "wof:placetype":"venue"
},
  "geometry": {"coordinates":[11.852189,53.431847],"type":"Point"}
}