{
  "type": "Feature",
  "properties": {
    "iso:country":"DE",
    "sg:address":"Talstr. 18",
    "sg:city":"Leinfelden-Echterdingen",
    "sg:phone":"+49 711/755747",
    "sg:postcode":"70771",
    "sg:province":"Baden-W\u00fcrttemberg",
    "wof:name":"Manfred Laubengaier Steuerberater",
    "wof:placetype":"venue"
},
  "geometry": {"coordinates":[9.1387462616,48.70470047],"type":"Point"}
}