{
  "type": "Feature",
  "properties": {
    "iso:country":"DE",
    "sg:address":"Im Gansdahl 12a",
    "sg:city":"Dormagen",
    "sg:phone":"+49 2133/238008",
    "sg:postcode":"41540",
    "sg:province":"Nordrhein-Westfalen",
    "wof:name":"Hans Josef Cremer",
    "wof:placetype":"venue"
},
  "geometry": {"coordinates":[6.77499,51.080875],"type":"Point"}
}