{
  "type": "Feature",
  "properties": {
    "iso:country":"DE",
    "sg:address":"Nu\u00dfbaumweg 66",
    "sg:city":"Lohmar",
    "sg:postcode":"53797",
    "sg:province":"Nordrhein-Westfalen",
    "wof:name":"Juetland Naturhaus Gmbh",
    "wof:placetype":"venue"
},
  "geometry": {"coordinates":[7.271146,50.896187],"type":"Point"}
}