{
  "type": "Feature",
  "properties": {
    "iso:country":"DE",
    "sg:address":"Wilhelm-Leuschner-Str. 42",
    "sg:city":"Bad Nauheim",
    "sg:postcode":"61231",
    "sg:province":"Hessen",
    "wof:name":"St. Rom Bau Gmbh",
    "wof:placetype":"venue"
},
  "geometry": {"coordinates":[8.770742,50.354946],"type":"Point"}
}