{
  "type": "Feature",
  "properties": {
    "iso:country":"DE",
    "sg:address":"Dietesheimer Str. 25",
    "sg:city":"Offenbach",
    "sg:phone":"+49 69/895911",
    "sg:postcode":"63073",
    "sg:province":"Hessen",
    "wof:name":"Kaspar Kreis",
    "wof:placetype":"venue"
},
  "geometry": {"coordinates":[8.8101129532,50.0901412964],"type":"Point"}
}