{
  "type": "Feature",
  "properties": {
    "iso:country":"DE",
    "sg:address":"Seestr. 22",
    "sg:city":"Schwerin",
    "sg:phone":"+49 385/557656",
    "sg:postcode":"19053",
    "sg:province":"Mecklenburg-Vorpommern",
    "wof:name":"Das Andere Abenteuer",
    "wof:placetype":"venue"
},
  "geometry": {"coordinates":[11.40351,53.62162],"type":"Point"}
}