{
  "type": "Feature",
  "properties": {
    "iso:country":"DE",
    "sg:address":"Richard-Wagner-Str. 38",
    "sg:city":"Obertshausen",
    "sg:phone":"+49 6104/73031",
    "sg:postcode":"63179",
    "sg:province":"Hessen",
    "wof:name":"Hms Immobilien",
    "wof:placetype":"venue"
},
  "geometry": {"coordinates":[8.8661594391,50.0775756836],"type":"Point"}
}