{
  "type": "Feature",
  "properties": {
    "iso:country":"DE",
    "sg:address":"Schulthei\u00dfstr. 42",
    "sg:city":"Wiesbaden",
    "sg:phone":"+49 611/508483",
    "sg:postcode":"65191",
    "sg:province":"Hessen",
    "wof:name":"Aski Edv-beratung Gmbh",
    "wof:placetype":"venue"
},
  "geometry": {"coordinates":[8.2778673172,50.0814552307],"type":"Point"}
}