{
  "type": "Feature",
  "properties": {
    "iso:country":"DE",
    "sg:address":"Samoastr. 7",
    "sg:city":"Berlin",
    "sg:phone":"+49 30/45482164",
    "sg:postcode":"13353",
    "sg:province":"Berlin",
    "wof:name":"Thomas Wolf Architekt",
    "wof:placetype":"venue"
},
  "geometry": {"coordinates":[13.355129,52.539864],"type":"Point"}
}