{
  "type": "Feature",
  "properties": {
    "iso:country":"DE",
    "sg:address":"Siegener Str. 31-33",
    "sg:city":"Lahntal",
    "sg:postcode":"35094",
    "sg:province":"Hessen",
    "wof:name":"Cobra Becker Sch\u00e4fer Kg",
    "wof:placetype":"venue"
},
  "geometry": {"coordinates":[8.735788,50.86853],"type":"Point"}
}