{
  "type": "Feature",
  "properties": {
    "iso:country":"DE",
    "sg:address":"Rosenweg 4",
    "sg:city":"B\u00f6hmfeld",
    "sg:phone":"+49 8406/650",
    "sg:postcode":"85113",
    "sg:province":"Bayern",
    "wof:name":"Kochschule Dietz",
    "wof:placetype":"venue"
},
  "geometry": {"coordinates":[11.370718956,48.8593330383],"type":"Point"}
}