{
  "type": "Feature",
  "properties": {
    "iso:country":"DE",
    "sg:address":"Friedhofstr. 126",
    "sg:city":"Bielefeld",
    "sg:phone":"+49 521/49645",
    "sg:postcode":"33659",
    "sg:province":"Nordrhein-Westfalen",
    "wof:name":"Brakensiek & Kralemann Ohg",
    "wof:placetype":"venue"
},
  "geometry": {"coordinates":[8.5324296951,51.9741706848],"type":"Point"}
}