{
  "type": "Feature",
  "properties": {
    "iso:country":"DE",
    "sg:address":"D\u00f6rnigheimer Weg 21",
    "sg:city":"Maintal",
    "sg:postcode":"63477",
    "sg:province":"Hessen",
    "wof:name":"A. Und J. Laschewskie Gmbh & Co. Gastronomie Kg",
    "wof:placetype":"venue"
},
  "geometry": {"coordinates":[8.812245369,50.1484336853],"type":"Point"}
}