{
  "type": "Feature",
  "properties": {
    "iso:country":"DE",
    "sg:address":"Gartenstr. 19",
    "sg:city":"Bad Salzungen",
    "sg:phone":"+49 3695/604070",
    "sg:postcode":"36433",
    "sg:province":"Th\u00fcringen",
    "wof:name":"Heidi Zimmermann",
    "wof:placetype":"venue"
},
  "geometry": {"coordinates":[10.237947464,50.8143730164],"type":"Point"}
}