{
  "type": "Feature",
  "properties": {
    "iso:country":"DE",
    "sg:address":"Aschaffstr. 48",
    "sg:city":"Aschaffenburg",
    "sg:phone":"+49 6021/41509",
    "sg:postcode":"63741",
    "sg:province":"Bayern",
    "wof:name":"Redaktion Mitteilungen Des Naturwissenschaftl. Museums",
    "wof:placetype":"venue"
},
  "geometry": {"coordinates":[9.1434984207,49.989730835],"type":"Point"}
}