{
  "type": "Feature",
  "properties": {
    "iso:country":"DE",
    "sg:address":"Warnem\u00fcnder Str. 12",
    "sg:city":"Rostock",
    "sg:phone":"+49 381/2060777",
    "sg:postcode":"18146",
    "sg:province":"Mecklenburg-Vorpommern",
    "wof:name":"Gustav G\u00fcnstig",
    "wof:placetype":"venue"
},
  "geometry": {"coordinates":[12.1554203033,54.1910018921],"type":"Point"}
}