{
  "type": "Feature",
  "properties": {
    "iso:country":"DE",
    "sg:address":"Schulstr. 2",
    "sg:city":"T\u00f6nisvorst",
    "sg:phone":"+49 2151/798793",
    "sg:postcode":"47918",
    "sg:province":"Nordrhein-Westfalen",
    "wof:name":"Musketier-klause",
    "wof:placetype":"venue"
},
  "geometry": {"coordinates":[6.4918818474,51.3226661682],"type":"Point"}
}