{
  "type": "Feature",
  "properties": {
    "iso:country":"DE",
    "sg:address":"Dorfstr. 22B",
    "sg:city":"Frankenstein",
    "sg:phone":"+49 37292/22160",
    "sg:postcode":"09569",
    "sg:province":"Sachsen",
    "wof:name":"Yvonne Rehwagen",
    "wof:placetype":"venue"
},
  "geometry": {"coordinates":[13.1935272217,50.8828811646],"type":"Point"}
}