{
  "type": "Feature",
  "properties": {
    "iso:country":"DE",
    "sg:address":"M\u00f6nchswiesenstr. 6",
    "sg:city":"Gladenbach",
    "sg:phone":"+49 6420/7840",
    "sg:postcode":"35075",
    "sg:province":"Hessen",
    "wof:name":"Gebr\u00fcder Hofmann G\u00fcterkraftverkehr Spedition",
    "wof:placetype":"venue"
},
  "geometry": {"coordinates":[8.627794,50.811249],"type":"Point"}
}