{
  "type": "Feature",
  "properties": {
    "iso:country":"DE",
    "sg:address":"Ernst-Th\u00e4lmann-Platz 10",
    "sg:city":"Hirschfelde",
    "sg:phone":"+49 35843/25221",
    "sg:postcode":"02788",
    "sg:province":"Sachsen",
    "wof:name":"Hotel Rieger",
    "wof:placetype":"venue"
},
  "geometry": {"coordinates":[14.8887434006,50.9454879761],"type":"Point"}
}