{
  "type": "Feature",
  "properties": {
    "iso:country":"DE",
    "sg:address":"Auf dem Hastert 26",
    "sg:city":"Duisburg",
    "sg:phone":"+49 2151/400315",
    "sg:postcode":"47239",
    "sg:province":"Nordrhein-Westfalen",
    "wof:name":"Rolf Jaschinski",
    "wof:placetype":"venue"
},
  "geometry": {"coordinates":[6.663,51.403053],"type":"Point"}
}