{
  "type": "Feature",
  "properties": {
    "iso:country":"DE",
    "sg:address":"Stauferweg 15",
    "sg:city":"Feuchtwangen",
    "sg:phone":"+49 9852/9247",
    "sg:postcode":"91555",
    "sg:province":"Bayern",
    "wof:name":"Christa Heller-mentrup",
    "wof:placetype":"venue"
},
  "geometry": {"coordinates":[10.3310594559,49.1788635254],"type":"Point"}
}