{
  "type": "Feature",
  "properties": {
    "iso:country":"DE",
    "sg:address":"Illinger Str. 110",
    "sg:city":"Illingen",
    "sg:phone":"+49 6825/48264",
    "sg:postcode":"66557",
    "sg:province":"Saarland",
    "wof:name":"Offm Hof",
    "wof:placetype":"venue"
},
  "geometry": {"coordinates":[7.0415267944,49.387386322],"type":"Point"}
}