{
  "type": "Feature",
  "properties": {
    "iso:country":"DE",
    "sg:address":"Heinrich-von-Stephan-Str. 8",
    "sg:city":"Freiburg",
    "sg:phone":"+49 761/502551",
    "sg:postcode":"79100",
    "sg:province":"Baden-W\u00fcrttemberg",
    "wof:name":"Real Wohn- Und Gewerbebau Gmbh",
    "wof:placetype":"venue"
},
  "geometry": {"coordinates":[7.8369860649,47.9887657166],"type":"Point"}
}