{
  "type": "Feature",
  "properties": {
    "iso:country":"DE",
    "sg:address":"Pfarrer-Kraus-Str. 50",
    "sg:city":"Koblenz",
    "sg:phone":"+49 261/61325",
    "sg:postcode":"56077",
    "sg:province":"Rheinland-Pfalz",
    "wof:name":"Rudolf Melzer",
    "wof:placetype":"venue"
},
  "geometry": {"coordinates":[7.6461019516,50.3676185608],"type":"Point"}
}