{
  "type": "Feature",
  "properties": {
    "iso:country":"DE",
    "sg:address":"An der Eben\u00f6de 21",
    "sg:city":"Bad Oeynhausen",
    "sg:phone":"+49 5731/95121",
    "sg:postcode":"32547",
    "sg:province":"Nordrhein-Westfalen",
    "wof:name":"Wik\u00f6l-oelbinder G. Korsmeier Gmbh",
    "wof:placetype":"venue"
},
  "geometry": {"coordinates":[8.833312,52.177799],"type":"Point"}
}