{
  "type": "Feature",
  "properties": {
    "iso:country":"DE",
    "sg:address":"Dumstr. 1",
    "sg:city":"Metzels",
    "sg:postcode":"98639",
    "sg:province":"Th\u00fcringen",
    "wof:name":"Evangelische-luth. Kirche",
    "wof:placetype":"venue"
},
  "geometry": {"coordinates":[10.4335393906,50.6475791931],"type":"Point"}
}