{
  "type": "Feature",
  "properties": {
    "iso:country":"DE",
    "sg:address":"L\u00f6her Str. 21",
    "sg:city":"Velbert",
    "sg:phone":"+49 2053/2177",
    "sg:postcode":"42553",
    "sg:province":"Nordrhein-Westfalen",
    "wof:name":"Fritz M\u00fcller",
    "wof:placetype":"venue"
},
  "geometry": {"coordinates":[7.086092,51.313156],"type":"Point"}
}