{
  "type": "Feature",
  "properties": {
    "iso:country":"DE",
    "sg:address":"F\u00fcrstenwall 85",
    "sg:city":"D\u00fcsseldorf",
    "sg:phone":"+49 211/3830589",
    "sg:postcode":"40217",
    "sg:province":"Nordrhein-Westfalen",
    "wof:name":"Story4all - Geschichten Schreiben, Mitschreiben",
    "wof:placetype":"venue"
},
  "geometry": {"coordinates":[6.771818,51.213875],"type":"Point"}
}