{
  "type": "Feature",
  "properties": {
    "iso:country":"DE",
    "sg:address":"Danziger Str. 12",
    "sg:city":"Hungen",
    "sg:phone":"+49 6402/2388",
    "sg:postcode":"35410",
    "sg:province":"Hessen",
    "wof:name":"M. Kreutschmann",
    "wof:placetype":"venue"
},
  "geometry": {"coordinates":[8.845355,50.445881],"type":"Point"}
}