{
  "type": "Feature",
  "properties": {
    "iso:country":"DE",
    "sg:address":"Berwartsteinstr. 8",
    "sg:city":"Hagenbach",
    "sg:phone":"+49 7273/4070",
    "sg:postcode":"76767",
    "sg:province":"Rheinland-Pfalz",
    "wof:name":"La Mare Meeresspezialit\u00e4ten Gmbh",
    "wof:placetype":"venue"
},
  "geometry": {"coordinates":[8.2498207092,49.0237007141],"type":"Point"}
}