{
  "type": "Feature",
  "properties": {
    "iso:country":"DE",
    "sg:address":"Friedrich-Ebert-Str. 17",
    "sg:city":"Ulm",
    "sg:phone":"+49 731/619867",
    "sg:postcode":"89073",
    "sg:province":"Baden-W\u00fcrttemberg",
    "wof:name":"Ernst K\u00e4\u00dfmeyer B\u00e4ckerei Kg",
    "wof:placetype":"venue"
},
  "geometry": {"coordinates":[9.987811,48.397186],"type":"Point"}
}