{
  "type": "Feature",
  "properties": {
    "iso:country":"DE",
    "sg:address":"G\u00f6ttinger Str. 38 b",
    "sg:city":"Bovenden",
    "sg:phone":"+49 551/508780",
    "sg:postcode":"37120",
    "sg:province":"Niedersachsen",
    "wof:name":"Wma Abrechnungsmanagement F\u00fcr Zahntechnische Laborato-",
    "wof:placetype":"venue"
},
  "geometry": {"coordinates":[9.9260482788,51.5877952576],"type":"Point"}
}