{
  "type": "Feature",
  "properties": {
    "iso:country":"DE",
    "sg:address":"O7",
    "sg:city":"Mannheim",
    "sg:phone":"+49 4962/116044",
    "sg:postcode":"68161",
    "sg:province":"Baden-W\u00fcrttemberg",
    "wof:name":"Rheinboden Hypothekenbank Ag",
    "wof:placetype":"venue"
},
  "geometry": {"coordinates":[8.473131,49.484047],"type":"Point"}
}