{
  "type": "Feature",
  "properties": {
    "iso:country":"DE",
    "sg:address":"Ingolst\u00e4dter Str. 7",
    "sg:city":"Pfaffenhofen",
    "sg:phone":"+49 8441/72174",
    "sg:postcode":"85276",
    "sg:province":"Bayern",
    "wof:name":"Die Kleine Kneipe",
    "wof:placetype":"venue"
},
  "geometry": {"coordinates":[11.5067949295,48.530544281],"type":"Point"}
}