{
  "type": "Feature",
  "properties": {
    "iso:country":"DE",
    "sg:address":"Heideweg 18",
    "sg:city":"Emsdetten",
    "sg:phone":"+49 2572/3689",
    "sg:postcode":"48282",
    "sg:province":"Nordrhein-Westfalen",
    "wof:name":"Ludwig Hewing Architekt",
    "wof:placetype":"venue"
},
  "geometry": {"coordinates":[7.5394,52.165756],"type":"Point"}
}