{
  "type": "Feature",
  "properties": {
    "iso:country":"DE",
    "sg:address":"Baumstr. 45",
    "sg:city":"Bremen",
    "sg:phone":"+49 421/383011",
    "sg:postcode":"28217",
    "sg:province":"Bremen",
    "wof:name":"Kraftverkehr Weser-ems Gmbh",
    "wof:placetype":"venue"
},
  "geometry": {"coordinates":[8.78893,53.085335],"type":"Point"}
}