{
  "type": "Feature",
  "properties": {
    "iso:country":"DE",
    "sg:address":"Keplerstr. 26",
    "sg:city":"Wernau",
    "sg:phone":"+49 7153/38489",
    "sg:postcode":"73249",
    "sg:province":"Baden-W\u00fcrttemberg",
    "wof:name":"Wilhelm Gamm B\u00e4ckerei",
    "wof:placetype":"venue"
},
  "geometry": {"coordinates":[9.421153,48.691528],"type":"Point"}
}