{
  "type": "Feature",
  "properties": {
    "iso:country":"DE",
    "sg:address":"Stratenweg 8",
    "sg:city":"Detmold",
    "sg:phone":"+49 5232/987103",
    "sg:postcode":"32758",
    "sg:province":"Nordrhein-Westfalen",
    "wof:name":"Rolf Geng",
    "wof:placetype":"venue"
},
  "geometry": {"coordinates":[8.7881622314,51.9469223022],"type":"Point"}
}