{
  "type": "Feature",
  "properties": {
    "iso:country":"DE",
    "sg:address":"Ziegelfeldstr. 54",
    "sg:city":"M\u00f6gglingen",
    "sg:phone":"+49 7174/6220",
    "sg:postcode":"73563",
    "sg:province":"Baden-W\u00fcrttemberg",
    "wof:name":"Frey & Sohn Kaminwerk Gmbh",
    "wof:placetype":"venue"
},
  "geometry": {"coordinates":[9.975282,48.82193],"type":"Point"}
}