{
  "type": "Feature",
  "properties": {
    "iso:country":"DE",
    "sg:address":"Im Niengrund 3",
    "sg:city":"Rheine",
    "sg:phone":"+49 5975/8001",
    "sg:postcode":"48432",
    "sg:province":"Nordrhein-Westfalen",
    "wof:name":"Ewald B\u00fcscher Gmbh",
    "wof:placetype":"venue"
},
  "geometry": {"coordinates":[7.48964,52.219181],"type":"Point"}
}