{
  "type": "Feature",
  "properties": {
    "iso:country":"DE",
    "sg:address":"Dientzenhoferstr. 6",
    "sg:city":"Fulda",
    "sg:postcode":"36043",
    "sg:province":"Hessen",
    "wof:name":"Fulmin Mineral\u00f6l-vertriebs- Gesellschaft Mbh",
    "wof:placetype":"venue"
},
  "geometry": {"coordinates":[9.691202,50.550758],"type":"Point"}
}