{
  "type": "Feature",
  "properties": {
    "iso:country":"DE",
    "sg:address":"Jella-Lepman-Str. 41",
    "sg:city":"M\u00fcnchen",
    "sg:phone":"+49 89/438612",
    "sg:postcode":"81673",
    "sg:province":"Bayern",
    "wof:name":"Rudolf Walter Heilpraktiker",
    "wof:placetype":"venue"
},
  "geometry": {"coordinates":[11.6420068741,48.1229934692],"type":"Point"}
}