{
  "type": "Feature",
  "properties": {
    "iso:country":"DE",
    "sg:address":"Kirchenweg 67",
    "sg:city":"Schrozberg",
    "sg:phone":"+49 7936/723",
    "sg:postcode":"74575",
    "sg:province":"Baden-W\u00fcrttemberg",
    "wof:name":"K. Sch\u00fcrger",
    "wof:placetype":"venue"
},
  "geometry": {"coordinates":[9.880925,49.353512],"type":"Point"}
}