{
  "type": "Feature",
  "properties": {
    "iso:country":"DE",
    "sg:address":"Stahlgruberring 11a",
    "sg:city":"M\u00fcnchen",
    "sg:postcode":"81829",
    "sg:province":"Bayern",
    "wof:name":"Mba Media Business Academy Gmbh",
    "wof:placetype":"venue"
},
  "geometry": {"coordinates":[11.665906,48.132755],"type":"Point"}
}