{
  "type": "Feature",
  "properties": {
    "iso:country":"DE",
    "sg:address":"Brunnenstr. 75",
    "sg:city":"Gingen",
    "sg:phone":"+49 7162/43033",
    "sg:postcode":"73333",
    "sg:province":"Baden-W\u00fcrttemberg",
    "wof:name":"Roland Schmid Baukunststoffe Gmbh",
    "wof:placetype":"venue"
},
  "geometry": {"coordinates":[9.7772703171,48.6675605774],"type":"Point"}
}