{
  "type": "Feature",
  "properties": {
    "iso:country":"DE",
    "sg:address":"Schacksdorfer Str. 45",
    "sg:city":"Finsterwalde",
    "sg:phone":"+49 3531/601980",
    "sg:postcode":"03238",
    "sg:province":"Brandenburg",
    "wof:name":"Mario Sanders Anlageberater",
    "wof:placetype":"venue"
},
  "geometry": {"coordinates":[13.7214002609,51.6239242554],"type":"Point"}
}