{
  "type": "Feature",
  "properties": {
    "iso:country":"DE",
    "sg:address":"Wendemarken 13",
    "sg:city":"Kleinmachnow",
    "sg:postcode":"14532",
    "sg:province":"Brandenburg",
    "wof:name":"H.a.k. Verwaltungsges. Mbh",
    "wof:placetype":"venue"
},
  "geometry": {"coordinates":[13.222530365,52.418258667],"type":"Point"}
}