{
  "type": "Feature",
  "properties": {
    "iso:country":"DE",
    "sg:address":"Burgberger Str 32-34",
    "sg:city":"K\u00f6nigsfeld",
    "sg:phone":"+49 7725/94280",
    "sg:postcode":"78126",
    "sg:province":"Baden-W\u00fcrttemberg",
    "wof:name":"Gebr\u00fcder Staiger Gmbh",
    "wof:placetype":"venue"
},
  "geometry": {"coordinates":[8.41528,48.150261],"type":"Point"}
}