{
  "type": "Feature",
  "properties": {
    "iso:country":"DE",
    "sg:address":"Am Zellerberg 46",
    "sg:city":"Ruhpolding",
    "sg:phone":"+49 8663/1541",
    "sg:postcode":"83324",
    "sg:province":"Bayern",
    "wof:name":"Georg Fr\u00f6mel Planungsb\u00fcro",
    "wof:placetype":"venue"
},
  "geometry": {"coordinates":[12.6639585495,47.7576942444],"type":"Point"}
}