{
  "type": "Feature",
  "properties": {
    "iso:country":"DE",
    "sg:address":"Marktstr. 151",
    "sg:city":"Oberhausen",
    "sg:phone":"+49 208/851528",
    "sg:postcode":"46045",
    "sg:province":"Nordrhein-Westfalen",
    "wof:name":"K. Diermann",
    "wof:placetype":"venue"
},
  "geometry": {"coordinates":[6.860462,51.468399],"type":"Point"}
}