{
  "type": "Feature",
  "properties": {
    "iso:country":"DE",
    "sg:address":"Eppendorfer Weg 240",
    "sg:city":"Hamburg",
    "sg:phone":"+49 40/4202903",
    "sg:postcode":"20251",
    "sg:province":"Hamburg",
    "wof:name":"Gastst\u00e4tte Casa De Aragon",
    "wof:placetype":"venue"
},
  "geometry": {"coordinates":[9.9751729965,53.5829238892],"type":"Point"}
}