{
  "type": "Feature",
  "properties": {
    "iso:country":"DE",
    "sg:address":"Gro\u00dfer H\u00f6henweg 2",
    "sg:city":"Bammental",
    "sg:phone":"+49 6223/5854",
    "sg:postcode":"69245",
    "sg:province":"Baden-W\u00fcrttemberg",
    "wof:name":"Pub Phoenix",
    "wof:placetype":"venue"
},
  "geometry": {"coordinates":[8.7811384201,49.3516197205],"type":"Point"}
}