{
  "type": "Feature",
  "properties": {
    "iso:country":"DE",
    "sg:address":"K\u00f6nigsallee 21-23",
    "sg:city":"D\u00fcsseldorf",
    "sg:phone":"+49 211/329525",
    "sg:postcode":"40212",
    "sg:province":"Nordrhein-Westfalen",
    "wof:name":"Petra Krautscheid Damenmoden Inh. Angelika Lange",
    "wof:placetype":"venue"
},
  "geometry": {"coordinates":[6.778311,51.224606],"type":"Point"}
}