{
  "type": "Feature",
  "properties": {
    "iso:country":"DE",
    "sg:address":"Wallstr. 2",
    "sg:city":"Alfeld",
    "sg:phone":"+49 5181/1018",
    "sg:postcode":"31061",
    "sg:province":"Niedersachsen",
    "wof:name":"Kirchenkreis Allfeldleine",
    "wof:placetype":"venue"
},
  "geometry": {"coordinates":[9.8266620636,51.9874725342],"type":"Point"}
}