{
  "type": "Feature",
  "properties": {
    "iso:country":"DE",
    "sg:address":"Am Mitterfeld 3",
    "sg:city":"M\u00fcnchen",
    "sg:phone":"+49 89/6881729",
    "sg:postcode":"81829",
    "sg:province":"Bayern",
    "wof:name":"La Traviata",
    "wof:placetype":"venue"
},
  "geometry": {"coordinates":[11.6737251282,48.126209259],"type":"Point"}
}