{
  "type": "Feature",
  "properties": {
    "iso:country":"DE",
    "sg:address":"Tonhallenstr. 13",
    "sg:city":"Duisburg",
    "sg:phone":"+49 203/21008",
    "sg:postcode":"47051",
    "sg:province":"Nordrhein-Westfalen",
    "wof:name":"Karl-heinz K\u00fcpper Verwaltungs-gmbh",
    "wof:placetype":"venue"
},
  "geometry": {"coordinates":[6.769583,51.431019],"type":"Point"}
}