{
  "type": "Feature",
  "properties": {
    "iso:country":"DE",
    "sg:address":"Nenndorf 4",
    "sg:city":"Bruchhausen-Vilsen",
    "sg:phone":"+49 4252/2623",
    "sg:postcode":"27305",
    "sg:province":"Niedersachsen",
    "wof:name":"Heinrich Klusmann-schumacher",
    "wof:placetype":"venue"
},
  "geometry": {"coordinates":[8.942448,52.828201],"type":"Point"}
}