{
  "type": "Feature",
  "properties": {
    "iso:country":"DE",
    "sg:address":"Industriestr. 13",
    "sg:city":"Gundelfingen",
    "sg:phone":"+49 9073/3260",
    "sg:postcode":"89423",
    "sg:province":"Bayern",
    "wof:name":"Stocker Immobilien Gmbh",
    "wof:placetype":"venue"
},
  "geometry": {"coordinates":[7.858934,48.039524],"type":"Point"}
}