{
  "type": "Feature",
  "properties": {
    "iso:country":"DE",
    "sg:address":"Zeppelinstr. 10",
    "sg:city":"Bad Homburg",
    "sg:phone":"+49 6172/288662",
    "sg:postcode":"61352",
    "sg:province":"Hessen",
    "wof:name":"Bad Homburger Brauhaus Gmbh & Co. Kg",
    "wof:placetype":"venue"
},
  "geometry": {"coordinates":[8.611785,50.214535],"type":"Point"}
}