{
  "type": "Feature",
  "properties": {
    "iso:country":"DE",
    "sg:address":"Altenschleuse 40 b",
    "sg:city":"Neuenkirchen",
    "sg:phone":"+49 4142/810018",
    "sg:postcode":"21640",
    "sg:province":"Niedersachsen",
    "wof:name":"A.b.a.c.u.s. Ulrike Rawolle",
    "wof:placetype":"venue"
},
  "geometry": {"coordinates":[9.6136388779,53.5377502441],"type":"Point"}
}