{
  "type": "Feature",
  "properties": {
    "iso:country":"DE",
    "sg:address":"Spiethl\u00e4nderweg 3",
    "sg:city":"Hemer",
    "sg:phone":"+49 2372/55285",
    "sg:postcode":"58675",
    "sg:province":"Nordrhein-Westfalen",
    "wof:name":"Solarien Im Hallenbad",
    "wof:placetype":"venue"
},
  "geometry": {"coordinates":[7.7677149773,51.3863716125],"type":"Point"}
}