{
  "type": "Feature",
  "properties": {
    "iso:country":"DE",
    "sg:address":"Industriestr 38",
    "sg:city":"Heusenstamm",
    "sg:phone":"+49 6104/68050",
    "sg:postcode":"63150",
    "sg:province":"Hessen",
    "wof:name":"Plastic-werk Kappich",
    "wof:placetype":"venue"
},
  "geometry": {"coordinates":[8.7942676544,50.0472831726],"type":"Point"}
}