{
  "type": "Feature",
  "properties": {
    "iso:country":"DE",
    "sg:address":"Lindenstr. 19",
    "sg:city":"Satteldorf",
    "sg:phone":"+49 7951/7687",
    "sg:postcode":"74589",
    "sg:province":"Baden-W\u00fcrttemberg",
    "wof:name":"C. Gallasch",
    "wof:placetype":"venue"
},
  "geometry": {"coordinates":[10.0836772919,49.1683235168],"type":"Point"}
}