{
  "type": "Feature",
  "properties": {
    "iso:country":"DE",
    "sg:address":"Wiesenstr. 6",
    "sg:city":"Hohnhorst",
    "sg:phone":"+49 5723/81643",
    "sg:postcode":"31559",
    "sg:province":"Niedersachsen",
    "wof:name":"Tus Germania Hohnhorst E. V. Erhard Phl",
    "wof:placetype":"venue"
},
  "geometry": {"coordinates":[9.3687448502,52.368850708],"type":"Point"}
}