{
  "type": "Feature",
  "properties": {
    "iso:country":"DE",
    "sg:address":"Am Buddeplatz",
    "sg:city":"Berlin",
    "sg:phone":"+49 30/4331045",
    "sg:postcode":"13507",
    "sg:province":"Berlin",
    "wof:name":"Leisten-tegel",
    "wof:placetype":"venue"
},
  "geometry": {"coordinates":[13.28789,52.58839],"type":"Point"}
}