{
  "type": "Feature",
  "properties": {
    "iso:country":"DE",
    "sg:address":"Veilchenweg 15",
    "sg:city":"Buchholz",
    "sg:phone":"+49 4181/97378",
    "sg:postcode":"21244",
    "sg:province":"Niedersachsen",
    "wof:name":"G\u00fcnter H\u00f6schele",
    "wof:placetype":"venue"
},
  "geometry": {"coordinates":[9.877827,53.332783],"type":"Point"}
}