{
  "type": "Feature",
  "properties": {
    "iso:country":"DE",
    "sg:address":"Lange Str. 20",
    "sg:city":"Freudenstadt",
    "sg:phone":"+49 7441/2094",
    "sg:postcode":"72250",
    "sg:province":"Baden-W\u00fcrttemberg",
    "wof:name":"Marija Haier",
    "wof:placetype":"venue"
},
  "geometry": {"coordinates":[8.423703,48.460949],"type":"Point"}
}