{
  "type": "Feature",
  "properties": {
    "iso:country":"DE",
    "sg:address":"M\u00fchlenstr. 10",
    "sg:city":"Heidenau",
    "sg:phone":"+49 3529/517709",
    "sg:postcode":"01809",
    "sg:province":"Sachsen",
    "wof:name":"Elektro Kirscht",
    "wof:placetype":"venue"
},
  "geometry": {"coordinates":[13.868661,50.97554],"type":"Point"}
}