{
  "type": "Feature",
  "properties": {
    "iso:country":"DE",
    "sg:address":"Bl\u00fctenstr. 1 B",
    "sg:city":"Schnaittach",
    "sg:postcode":"91220",
    "sg:province":"Bayern",
    "wof:name":"Macrolab Gmbh",
    "wof:placetype":"venue"
},
  "geometry": {"coordinates":[11.3327770233,49.556892395],"type":"Point"}
}