{
  "type": "Feature",
  "properties": {
    "iso:country":"DE",
    "sg:address":"Danckwerthstr. 2",
    "sg:city":"Kiel",
    "sg:phone":"+49 431/35800",
    "sg:postcode":"24106",
    "sg:province":"Schleswig-Holstein",
    "wof:name":"Norddeutscher Bautr\u00e4ger Gmbh & Co. Kg",
    "wof:placetype":"venue"
},
  "geometry": {"coordinates":[10.1326055527,54.3549766541],"type":"Point"}
}