{
  "type": "Feature",
  "properties": {
    "iso:country":"DE",
    "sg:address":"Lange Str. 15",
    "sg:city":"Langenau",
    "sg:phone":"+49 7345/96780",
    "sg:postcode":"89129",
    "sg:province":"Baden-W\u00fcrttemberg",
    "wof:name":"Hartmut Jacob Ingenieur",
    "wof:placetype":"venue"
},
  "geometry": {"coordinates":[10.1223125458,48.5010414124],"type":"Point"}
}