{
  "type": "Feature",
  "properties": {
    "iso:country":"DE",
    "sg:address":"Mauerstr. 1 a",
    "sg:city":"Bad Salzuflen",
    "sg:phone":"+49 5222/5340",
    "sg:postcode":"32105",
    "sg:province":"Nordrhein-Westfalen",
    "wof:name":"Hotel Lippischer Hof Peter Walter",
    "wof:placetype":"venue"
},
  "geometry": {"coordinates":[8.744416,52.084831],"type":"Point"}
}