{
  "type": "Feature",
  "properties": {
    "iso:country":"DE",
    "sg:address":"Kulmbacher Str. 49",
    "sg:city":"M\u00fcnchberg",
    "sg:phone":"+49 9251/6101",
    "sg:postcode":"95213",
    "sg:province":"Bayern",
    "wof:name":"Kurt Philipp Bedachungen Gmbh",
    "wof:placetype":"venue"
},
  "geometry": {"coordinates":[11.78439,50.191399],"type":"Point"}
}