{
  "type": "Feature",
  "properties": {
    "iso:country":"DE",
    "sg:address":"Schirnsdorf 16",
    "sg:city":"M\u00fchlhausen",
    "sg:phone":"+49 9548/736",
    "sg:postcode":"96172",
    "sg:province":"Bayern",
    "wof:name":"Leonhard Lorz",
    "wof:placetype":"venue"
},
  "geometry": {"coordinates":[10.780216,49.743839],"type":"Point"}
}