{
  "type": "Feature",
  "properties": {
    "iso:country":"DE",
    "sg:address":"Robert-Bosch-Str. 2-4",
    "sg:city":"K\u00f6ln",
    "sg:phone":"+49 4922/1709170",
    "sg:postcode":"50769",
    "sg:province":"Nordrhein-Westfalen",
    "wof:name":"R & S Mobile Raths Ohg",
    "wof:placetype":"venue"
},
  "geometry": {"coordinates":[6.9199109077,51.0322380066],"type":"Point"}
}