{
  "type": "Feature",
  "properties": {
    "iso:country":"DE",
    "sg:address":"Weusthoffstr. 8",
    "sg:city":"Hamburg",
    "sg:postcode":"21075",
    "sg:province":"Hamburg",
    "wof:name":"G & G Grundst\u00fccks Gmbh",
    "wof:placetype":"venue"
},
  "geometry": {"coordinates":[9.9547681808,53.4550743103],"type":"Point"}
}