{
  "type": "Feature",
  "properties": {
    "iso:country":"DE",
    "sg:address":"Albiger Str. 19",
    "sg:city":"Gau-Odernheim",
    "sg:phone":"+49 6733/1018",
    "sg:postcode":"55239",
    "sg:province":"Rheinland-Pfalz",
    "wof:name":"Dr. R. Giloth Steuerberater",
    "wof:placetype":"venue"
},
  "geometry": {"coordinates":[8.1839265823,49.7846641541],"type":"Point"}
}