{
  "type": "Feature",
  "properties": {
    "iso:country":"DE",
    "sg:address":"Dorstener Str. 47",
    "sg:city":"Reken",
    "sg:phone":"+49 2864/2069",
    "sg:postcode":"48734",
    "sg:province":"Nordrhein-Westfalen",
    "wof:name":"Osthoff",
    "wof:placetype":"venue"
},
  "geometry": {"coordinates":[7.0477142334,51.8210716248],"type":"Point"}
}