{
  "type": "Feature",
  "properties": {
    "iso:country":"DE",
    "sg:address":"Rathausplatz 11",
    "sg:city":"Gr\u00f6mitz",
    "sg:phone":"+49 4562/1880",
    "sg:postcode":"23743",
    "sg:province":"Schleswig-Holstein",
    "wof:name":"Zweckverband Karkbrook",
    "wof:placetype":"venue"
},
  "geometry": {"coordinates":[10.9581565857,54.149974823],"type":"Point"}
}