{
  "type": "Feature",
  "properties": {
    "iso:country":"DE",
    "sg:address":"Nordseestr. 2",
    "sg:city":"Krummh\u00f6rn",
    "sg:phone":"+49 4926/509",
    "sg:postcode":"26736",
    "sg:province":"Niedersachsen",
    "wof:name":"Gerd-dieter Ysker",
    "wof:placetype":"venue"
},
  "geometry": {"coordinates":[7.090239048,53.5041885376],"type":"Point"}
}