{
  "type": "Feature",
  "properties": {
    "iso:country":"DE",
    "sg:address":"Niederflurstr.",
    "sg:city":"Zeltingen-Rachtig",
    "sg:phone":"+49 6532/2786",
    "sg:postcode":"54492",
    "sg:province":"Rheinland-Pfalz",
    "wof:name":"Armin Lenard",
    "wof:placetype":"venue"
},
  "geometry": {"coordinates":[7.0106339455,49.9753913879],"type":"Point"}
}