{
  "type": "Feature",
  "properties": {
    "iso:country":"DE",
    "sg:address":"Hundemstr. 81",
    "sg:city":"Lennestadt",
    "sg:phone":"+49 2723/5926",
    "sg:postcode":"57368",
    "sg:province":"Nordrhein-Westfalen",
    "wof:name":"Gebr. Simon",
    "wof:placetype":"venue"
},
  "geometry": {"coordinates":[8.0697803497,51.0996818542],"type":"Point"}
}