{
  "type": "Feature",
  "properties": {
    "iso:country":"DE",
    "sg:address":"Scholte-Rahm-Str. 16",
    "sg:city":"Duisburg",
    "sg:phone":"+49 203/473290",
    "sg:postcode":"47178",
    "sg:province":"Nordrhein-Westfalen",
    "wof:name":"Allwetterbad",
    "wof:placetype":"venue"
},
  "geometry": {"coordinates":[6.7258558273,51.5335388184],"type":"Point"}
}