{
  "type": "Feature",
  "properties": {
    "iso:country":"DE",
    "sg:address":"Lindenstr. 53",
    "sg:city":"Oberkirch",
    "sg:phone":"+49 7805/3294",
    "sg:postcode":"77704",
    "sg:province":"Baden-W\u00fcrttemberg",
    "wof:name":"Blhv-ortsverein Zusenhofen Franz Josef M\u00fcller",
    "wof:placetype":"venue"
},
  "geometry": {"coordinates":[8.0825099945,48.5303688049],"type":"Point"}
}