{
  "type": "Feature",
  "properties": {
    "iso:country":"DE",
    "sg:address":"Sonnenbergstr. 26",
    "sg:city":"Schmitshausen",
    "sg:phone":"+49 6375/5868",
    "sg:postcode":"66484",
    "sg:province":"Rheinland-Pfalz",
    "wof:name":"A. Und G. Utzinger",
    "wof:placetype":"venue"
},
  "geometry": {"coordinates":[7.5151438713,49.3064651489],"type":"Point"}
}