{
  "type": "Feature",
  "properties": {
    "iso:country":"DE",
    "sg:address":"Strunkheider Weg 20",
    "sg:city":"Bielefeld",
    "sg:phone":"+49 4952/1390132",
    "sg:postcode":"33729",
    "sg:province":"Nordrhein-Westfalen",
    "wof:name":"J\u00d6rg Kuhlmann",
    "wof:placetype":"venue"
},
  "geometry": {"coordinates":[8.63895,52.056759],"type":"Point"}
}