{
  "type": "Feature",
  "properties": {
    "iso:country":"DE",
    "sg:address":"Michael-Dechant-Str. 6",
    "sg:city":"Weismain",
    "sg:phone":"+49 9575/1234",
    "sg:postcode":"96260",
    "sg:province":"Bayern",
    "wof:name":"Sch\u00fctz Gmbh",
    "wof:placetype":"venue"
},
  "geometry": {"coordinates":[11.2414016724,50.0929794312],"type":"Point"}
}