{
  "type": "Feature",
  "properties": {
    "iso:country":"DE",
    "sg:address":"Am Forst 7",
    "sg:city":"Wesel",
    "sg:phone":"+49 281/56018",
    "sg:postcode":"46485",
    "sg:province":"Nordrhein-Westfalen",
    "wof:name":"Meyer & Singer Industrieberatungs-gmbh",
    "wof:placetype":"venue"
},
  "geometry": {"coordinates":[6.663933,51.656776],"type":"Point"}
}