{
  "type": "Feature",
  "properties": {
    "iso:country":"DE",
    "sg:address":"Emsstr. 5",
    "sg:city":"Friesoythe",
    "sg:phone":"+49 7130/461000",
    "sg:postcode":"26169",
    "sg:province":"Niedersachsen",
    "wof:name":"B\u00d6ckle Gmbh",
    "wof:placetype":"venue"
},
  "geometry": {"coordinates":[9.4048261642,49.1398010254],"type":"Point"}
}