{
  "type": "Feature",
  "properties": {
    "iso:country":"DE",
    "sg:address":"Kleiststr. 35",
    "sg:city":"Wolfsburg",
    "sg:phone":"+49 5361/276766",
    "sg:postcode":"38440",
    "sg:province":"Niedersachsen",
    "wof:name":"Restaurant Taj-mahal",
    "wof:placetype":"venue"
},
  "geometry": {"coordinates":[10.7827978134,52.4249954224],"type":"Point"}
}