{
  "type": "Feature",
  "properties": {
    "iso:country":"DE",
    "sg:address":"Bachstr. 9",
    "sg:city":"Losheim",
    "sg:phone":"+49 6872/4801",
    "sg:postcode":"66679",
    "sg:province":"Saarland",
    "wof:name":"Michael Herrmann Industriemontage Gmbh",
    "wof:placetype":"venue"
},
  "geometry": {"coordinates":[6.7451691628,49.5101623535],"type":"Point"}
}