{
  "type": "Feature",
  "properties": {
    "iso:country":"DE",
    "sg:address":"Gerader Weg 12",
    "sg:city":"Dortmund",
    "sg:phone":"+49 231/230301",
    "sg:postcode":"44328",
    "sg:province":"Nordrhein-Westfalen",
    "wof:name":"Anton Junczyk Kanalisationsreinigungs-u.",
    "wof:placetype":"venue"
},
  "geometry": {"coordinates":[7.5343999863,51.5449829102],"type":"Point"}
}