{
  "type": "Feature",
  "properties": {
    "iso:country":"DE",
    "sg:address":"Steinweg 7",
    "sg:city":"Gro\u00dfenhain",
    "sg:phone":"+49 3522/507410",
    "sg:postcode":"01558",
    "sg:province":"Sachsen",
    "wof:name":"F. Dietze",
    "wof:placetype":"venue"
},
  "geometry": {"coordinates":[13.5344648361,51.293170929],"type":"Point"}
}