{
  "type": "Feature",
  "properties": {
    "iso:country":"DE",
    "sg:address":"Hauptstr. 4",
    "sg:city":"B\u00fcttstedt",
    "sg:phone":"+49 36075/60982",
    "sg:postcode":"37359",
    "sg:province":"Th\u00fcringen",
    "wof:name":"R. Wolf",
    "wof:placetype":"venue"
},
  "geometry": {"coordinates":[10.311553,51.259144],"type":"Point"}
}