{
  "type": "Feature",
  "properties": {
    "iso:country":"DE",
    "sg:address":"Bahnhofstr. 44",
    "sg:city":"Eggolsheim",
    "sg:phone":"+49 9545/94180",
    "sg:postcode":"91330",
    "sg:province":"Bayern",
    "wof:name":"Klumm Kg",
    "wof:placetype":"venue"
},
  "geometry": {"coordinates":[11.0488891602,49.7713394165],"type":"Point"}
}