{
  "type": "Feature",
  "properties": {
    "iso:country":"DE",
    "sg:address":"Marienstr. 94",
    "sg:city":"Oberhausen-Rheinhausen",
    "sg:phone":"+49 7254/1573",
    "sg:postcode":"68794",
    "sg:province":"Baden-W\u00fcrttemberg",
    "wof:name":"Bei Erika",
    "wof:placetype":"venue"
},
  "geometry": {"coordinates":[8.4916782379,49.2558517456],"type":"Point"}
}