{
  "type": "Feature",
  "properties": {
    "iso:country":"DE",
    "sg:address":"Karlstr. 4",
    "sg:city":"Bad Saulgau",
    "sg:phone":"+49 7581/7617",
    "sg:postcode":"88348",
    "sg:province":"Baden-W\u00fcrttemberg",
    "wof:name":"Redaktion Galvanotechnik Eugen G. Leuze Verlag",
    "wof:placetype":"venue"
},
  "geometry": {"coordinates":[9.5004148483,48.0143585205],"type":"Point"}
}