{
  "type": "Feature",
  "properties": {
    "iso:country":"DE",
    "sg:address":"Am Bodenbach 4",
    "sg:city":"Iffeldorf",
    "sg:phone":"+49 8856/6702",
    "sg:postcode":"82393",
    "sg:province":"Bayern",
    "wof:name":"Edith Und Karl G\u00e4rtner",
    "wof:placetype":"venue"
},
  "geometry": {"coordinates":[11.3353042603,47.7734642029],"type":"Point"}
}