{
  "type": "Feature",
  "properties": {
    "iso:country":"DE",
    "sg:address":"Oberschweinstiege",
    "sg:city":"Frankfurt",
    "sg:phone":"+49 69/684888",
    "sg:postcode":"60598",
    "sg:province":"Hessen",
    "wof:name":"Gastst\u00e4tte Oberschweinstiege",
    "wof:placetype":"venue"
},
  "geometry": {"coordinates":[8.6801996231,50.0724258423],"type":"Point"}
}