{
  "type": "Feature",
  "properties": {
    "iso:country":"DE",
    "sg:address":"Heerweg 146",
    "sg:city":"Gronau",
    "sg:phone":"+49 2562/4322",
    "sg:postcode":"48599",
    "sg:province":"Nordrhein-Westfalen",
    "wof:name":"R. Schlief Heissmangel",
    "wof:placetype":"venue"
},
  "geometry": {"coordinates":[7.0540142059,52.2099723816],"type":"Point"}
}