{
  "type": "Feature",
  "properties": {
    "iso:country":"DE",
    "sg:address":"Kranichstr. 7",
    "sg:city":"Euskirchen",
    "sg:phone":"+49 2255/4942",
    "sg:postcode":"53881",
    "sg:province":"Nordrhein-Westfalen",
    "wof:name":"Hans-joachim Kerk Ingenieur",
    "wof:placetype":"venue"
},
  "geometry": {"coordinates":[6.8550901413,50.625831604],"type":"Point"}
}