{
  "type": "Feature",
  "properties": {
    "iso:country":"DE",
    "sg:address":"Mannheimer Str. 133",
    "sg:city":"Kaiserslautern",
    "sg:phone":"+49 631/40710",
    "sg:postcode":"67657",
    "sg:province":"Rheinland-Pfalz",
    "wof:name":"Werner Bernd Bildhauer",
    "wof:placetype":"venue"
},
  "geometry": {"coordinates":[7.790513,49.445248],"type":"Point"}
}