{
  "type": "Feature",
  "properties": {
    "iso:country":"DE",
    "sg:address":"Flurstr. 5",
    "sg:city":"Ober-Ramstadt",
    "sg:phone":"+49 6154/2775",
    "sg:postcode":"64372",
    "sg:province":"Hessen",
    "wof:name":"P. Fehr",
    "wof:placetype":"venue"
},
  "geometry": {"coordinates":[8.762249,49.799828],"type":"Point"}
}