{
  "type": "Feature",
  "properties": {
    "iso:country":"DE",
    "sg:address":"Feldstr. 8",
    "sg:city":"Elxleben",
    "sg:phone":"+49 36201/86638",
    "sg:postcode":"99189",
    "sg:province":"Th\u00fcringen",
    "wof:name":"S. Schr\u00f6der",
    "wof:placetype":"venue"
},
  "geometry": {"coordinates":[10.9515867233,51.0458641052],"type":"Point"}
}