{
  "type": "Feature",
  "properties": {
    "iso:country":"DE",
    "sg:address":"Erzstr. 12",
    "sg:city":"Hagen",
    "sg:phone":"+49 2331/14353",
    "sg:postcode":"58135",
    "sg:province":"Nordrhein-Westfalen",
    "wof:name":"Emil Geitz Gmbh",
    "wof:placetype":"venue"
},
  "geometry": {"coordinates":[7.411947,51.340916],"type":"Point"}
}