{
  "type": "Feature",
  "properties": {
    "iso:country":"DE",
    "sg:address":"St.-Andreas-Weg 1",
    "sg:city":"St. Andreasberg",
    "sg:phone":"+49 5582/696",
    "sg:postcode":"37444",
    "sg:province":"Niedersachsen",
    "wof:name":"Pension Alfa",
    "wof:placetype":"venue"
},
  "geometry": {"coordinates":[10.5158395767,51.7164993286],"type":"Point"}
}