{
  "type": "Feature",
  "properties": {
    "iso:country":"DE",
    "sg:address":"Beckingsbusch 87",
    "sg:city":"Werne",
    "sg:phone":"+49 2389/51200",
    "sg:postcode":"59368",
    "sg:province":"Nordrhein-Westfalen",
    "wof:name":"G. M. Fedeler Steuerberater",
    "wof:placetype":"venue"
},
  "geometry": {"coordinates":[7.6547641754,51.6620063782],"type":"Point"}
}