{
  "type": "Feature",
  "properties": {
    "iso:country":"DE",
    "sg:address":"Poststr. 3",
    "sg:city":"L\u00f6bau",
    "sg:phone":"+49 3585/47010",
    "sg:postcode":"02708",
    "sg:province":"Sachsen",
    "wof:name":"Architekturb\u00fcro Kbs Architekten- Und",
    "wof:placetype":"venue"
},
  "geometry": {"coordinates":[14.665749,51.097675],"type":"Point"}
}