{
  "type": "Feature",
  "properties": {
    "iso:country":"DE",
    "sg:address":"Feldstiege 40-50",
    "sg:city":"M\u00fcnster",
    "sg:postcode":"48161",
    "sg:province":"Nordrhein-Westfalen",
    "wof:name":"Mp Beteiligungs- Gesellschaft Mbh",
    "wof:placetype":"venue"
},
  "geometry": {"coordinates":[7.54642,52.00116],"type":"Point"}
}