{
  "type": "Feature",
  "properties": {
    "iso:country":"DE",
    "sg:address":"Ringstr. 39-40",
    "sg:city":"Gro\u00dfbeeren",
    "sg:phone":"+49 33701/617",
    "sg:postcode":"14979",
    "sg:province":"Brandenburg",
    "wof:name":"Norbert Dre\u00dfler",
    "wof:placetype":"venue"
},
  "geometry": {"coordinates":[13.307356,52.362263],"type":"Point"}
}