{
  "type": "Feature",
  "properties": {
    "iso:country":"DE",
    "sg:address":"Minister-St\u00fcve-Str. 2",
    "sg:city":"Hannover",
    "sg:phone":"+49 511/454589",
    "sg:postcode":"30449",
    "sg:province":"Niedersachsen",
    "wof:name":"Wegener Sofortdruck Ohg",
    "wof:placetype":"venue"
},
  "geometry": {"coordinates":[9.719446,52.368301],"type":"Point"}
}