{
  "type": "Feature",
  "properties": {
    "iso:country":"DE",
    "sg:address":"Waltersdorfer Str. 26-27",
    "sg:city":"Berlin",
    "sg:phone":"+49 30/6766221",
    "sg:postcode":"12526",
    "sg:province":"Berlin",
    "wof:name":"Klaus Kr\u00fcger",
    "wof:placetype":"venue"
},
  "geometry": {"coordinates":[13.574676,52.397839],"type":"Point"}
}