{
  "type": "Feature",
  "properties": {
    "iso:country":"DE",
    "sg:address":"Wanner Str. 42",
    "sg:city":"Gelsenkirchen",
    "sg:phone":"+49 209/1791550",
    "sg:postcode":"45888",
    "sg:province":"Nordrhein-Westfalen",
    "wof:name":"Apd Ambulante Pflegedienste Gelsenkirchen Gmbh",
    "wof:placetype":"venue"
},
  "geometry": {"coordinates":[7.105567,51.513718],"type":"Point"}
}