{
  "type": "Feature",
  "properties": {
    "iso:country":"DE",
    "sg:address":"Pl\u00fcggentiner Str. 20",
    "sg:city":"Samtens",
    "sg:phone":"+49 4938/3061500",
    "sg:postcode":"18573",
    "sg:province":"Mecklenburg-Vorpommern",
    "wof:name":"Metallbau Gmbh R\u00dcgen",
    "wof:placetype":"venue"
},
  "geometry": {"coordinates":[13.296588,54.362762],"type":"Point"}
}