{
  "type": "Feature",
  "properties": {
    "iso:country":"DE",
    "sg:address":"Preister Str. 22",
    "sg:city":"Speicher",
    "sg:phone":"+49 6562/2060",
    "sg:postcode":"54662",
    "sg:province":"Rheinland-Pfalz",
    "wof:name":"Peter H\u00f6ser",
    "wof:placetype":"venue"
},
  "geometry": {"coordinates":[6.6382870674,49.9339447021],"type":"Point"}
}