{
  "type": "Feature",
  "properties": {
    "iso:country":"DE",
    "sg:address":"Hinter den H\u00f6fen 14",
    "sg:city":"Witzenhausen",
    "sg:phone":"+49 5542/999890",
    "sg:postcode":"37217",
    "sg:province":"Hessen",
    "wof:name":"W. Hartmann Handelshaus E. K.",
    "wof:placetype":"venue"
},
  "geometry": {"coordinates":[9.815902,51.35445],"type":"Point"}
}