{
  "type": "Feature",
  "properties": {
    "iso:country":"DE",
    "sg:address":"Deutscher Hof 10-11",
    "sg:city":"G\u00fcglingen",
    "sg:phone":"+49 7135/974450",
    "sg:postcode":"74363",
    "sg:province":"Baden-W\u00fcrttemberg",
    "wof:name":"Heinz Rall Architekt",
    "wof:placetype":"venue"
},
  "geometry": {"coordinates":[8.999772,49.066711],"type":"Point"}
}