{
  "type": "Feature",
  "properties": {
    "iso:country":"DE",
    "sg:address":"Oeger Str. 53",
    "sg:city":"Hagen",
    "sg:phone":"+49 2334/909522",
    "sg:postcode":"58119",
    "sg:province":"Nordrhein-Westfalen",
    "wof:name":"Heinrich Brinkmann Gmbh",
    "wof:placetype":"venue"
},
  "geometry": {"coordinates":[7.58259,51.346474],"type":"Point"}
}