{
  "type": "Feature",
  "properties": {
    "iso:country":"DE",
    "sg:address":"Am Doll 12",
    "sg:city":"Cottbus",
    "sg:phone":"+49 4935/5722212",
    "sg:postcode":"03042",
    "sg:province":"Brandenburg",
    "wof:name":"Gebr. Wienert Gmbh",
    "wof:placetype":"venue"
},
  "geometry": {"coordinates":[14.346039772,51.76171875],"type":"Point"}
}