{
  "type": "Feature",
  "properties": {
    "iso:country":"DE",
    "sg:address":"Hauptstr. 87",
    "sg:city":"Appenweier",
    "sg:phone":"+49 7805/3467",
    "sg:postcode":"77767",
    "sg:province":"Baden-W\u00fcrttemberg",
    "wof:name":"Wolfgang Schmidt",
    "wof:placetype":"venue"
},
  "geometry": {"coordinates":[7.9730148315,48.5453186035],"type":"Point"}
}