{
  "type": "Feature",
  "properties": {
    "iso:country":"DE",
    "sg:address":"Pfauenstr. 46",
    "sg:city":"Dormagen",
    "sg:phone":"+49 2133/238187",
    "sg:postcode":"41540",
    "sg:province":"Nordrhein-Westfalen",
    "wof:name":"Victor Dittmann",
    "wof:placetype":"venue"
},
  "geometry": {"coordinates":[6.7815442085,51.0819854736],"type":"Point"}
}