{
  "type": "Feature",
  "properties": {
    "iso:country":"DE",
    "sg:address":"Hofstr. 10",
    "sg:city":"Solingen",
    "sg:phone":"+49 212/330209",
    "sg:postcode":"42699",
    "sg:province":"Nordrhein-Westfalen",
    "wof:name":"Ev. \u00d6ffentliche Bibliothek Der Kirchengemeinde Merscheid",
    "wof:placetype":"venue"
},
  "geometry": {"coordinates":[7.029847,51.167526],"type":"Point"}
}