{
  "type": "Feature",
  "properties": {
    "iso:country":"DE",
    "sg:address":"Paul-Heyse-Stra\u00dfe 23",
    "sg:city":"M\u00fcnchen",
    "sg:postcode":"80336",
    "sg:province":"Bayern",
    "wof:name":"Hein & Partner M\u00fcnchen - Ihr Immobilienprofi",
    "wof:placetype":"venue"
},
  "geometry": {"coordinates":[11.5560617447,48.1365890503],"type":"Point"}
}