{
  "type": "Feature",
  "properties": {
    "iso:country":"DE",
    "sg:address":"Obereyller Str. 33",
    "sg:city":"Kerken",
    "sg:phone":"+49 2833/4261",
    "sg:postcode":"47647",
    "sg:province":"Nordrhein-Westfalen",
    "wof:name":"G. M\u00fcllers",
    "wof:placetype":"venue"
},
  "geometry": {"coordinates":[6.40646,51.43388],"type":"Point"}
}