{
  "type": "Feature",
  "properties": {
    "iso:country":"DE",
    "sg:address":"Weipertstr. 8",
    "sg:city":"Heilbronn",
    "sg:postcode":"74076",
    "sg:province":"Baden-W\u00fcrttemberg",
    "wof:name":"Em & S Media Gmbh",
    "wof:placetype":"venue"
},
  "geometry": {"coordinates":[9.2159566879,49.1520576477],"type":"Point"}
}