{
  "type": "Feature",
  "properties": {
    "iso:country":"DE",
    "sg:address":"Am Wehrberg 26",
    "sg:city":"Lohra",
    "sg:phone":"+49 6426/5221",
    "sg:postcode":"35102",
    "sg:province":"Hessen",
    "wof:name":"Dr. Dietrich Wiegand Tierarzt",
    "wof:placetype":"venue"
},
  "geometry": {"coordinates":[8.604227066,50.7031021118],"type":"Point"}
}