{
  "type": "Feature",
  "properties": {
    "iso:country":"DE",
    "sg:address":"Eiderweg 9",
    "sg:city":"Breiholz",
    "sg:phone":"+49 4332/734",
    "sg:postcode":"24797",
    "sg:province":"Schleswig-Holstein",
    "wof:name":"Hans-jacob Schulz",
    "wof:placetype":"venue"
},
  "geometry": {"coordinates":[9.520505,54.205322],"type":"Point"}
}