{
  "type": "Feature",
  "properties": {
    "iso:country":"DE",
    "sg:address":"Hardenbergstr. 71",
    "sg:city":"M\u00fclheim",
    "sg:phone":"+49 208/430783",
    "sg:postcode":"45472",
    "sg:province":"Nordrhein-Westfalen",
    "wof:name":"Dagmar Hodzic",
    "wof:placetype":"venue"
},
  "geometry": {"coordinates":[6.921979,51.437702],"type":"Point"}
}