{
  "type": "Feature",
  "properties": {
    "iso:country":"DE",
    "sg:address":"Hanauer Landstr. 135-137",
    "sg:city":"Frankfurt",
    "sg:postcode":"60314",
    "sg:province":"Hessen",
    "wof:name":"Think 4 You Ag",
    "wof:placetype":"venue"
},
  "geometry": {"coordinates":[8.7137260437,50.1122512817],"type":"Point"}
}