{
  "type": "Feature",
  "properties": {
    "iso:country":"DE",
    "sg:address":"Dahlienweg 1",
    "sg:city":"Leubingen",
    "sg:phone":"+49 3634/623193",
    "sg:postcode":"99610",
    "sg:province":"Th\u00fcringen",
    "wof:name":"Michael Schneider Bau Gmbh & Co. Kg",
    "wof:placetype":"venue"
},
  "geometry": {"coordinates":[11.150371,51.204185],"type":"Point"}
}