{
  "type": "Feature",
  "properties": {
    "iso:country":"DE",
    "sg:address":"In den Hehnen 1",
    "sg:city":"Aachen",
    "sg:phone":"+49 2408/80061",
    "sg:postcode":"52076",
    "sg:province":"Nordrhein-Westfalen",
    "wof:name":"Axel Spering Ingenieur",
    "wof:placetype":"venue"
},
  "geometry": {"coordinates":[6.1813468933,50.7078475952],"type":"Point"}
}