{
  "type": "Feature",
  "properties": {
    "iso:country":"DE",
    "sg:address":"Bahnhofstr. 1",
    "sg:city":"Peiting",
    "sg:phone":"+49 8861/6241",
    "sg:postcode":"86971",
    "sg:province":"Bayern",
    "wof:name":"M. Mair",
    "wof:placetype":"venue"
},
  "geometry": {"coordinates":[10.927675,47.793819],"type":"Point"}
}