{
  "type": "Feature",
  "properties": {
    "iso:country":"DE",
    "sg:address":"Am Maibach 32",
    "sg:city":"H\u00f6xter",
    "sg:phone":"+49 5271/2117",
    "sg:postcode":"37671",
    "sg:province":"Nordrhein-Westfalen",
    "wof:name":"Franz Wieneke",
    "wof:placetype":"venue"
},
  "geometry": {"coordinates":[9.35817,51.734699],"type":"Point"}
}