{
  "type": "Feature",
  "properties": {
    "iso:country":"DE",
    "sg:address":"Friedberger Landstr. 119",
    "sg:city":"Frankfurt",
    "sg:phone":"+49 69/599952",
    "sg:postcode":"60318",
    "sg:province":"Hessen",
    "wof:name":"Roland Jassmann Buchhandlung",
    "wof:placetype":"venue"
},
  "geometry": {"coordinates":[8.691450119,50.1261291504],"type":"Point"}
}