{
  "type": "Feature",
  "properties": {
    "iso:country":"DE",
    "sg:address":"Emekesweg 6",
    "sg:city":"Hamburg",
    "sg:phone":"+49 40/5363453",
    "sg:postcode":"22391",
    "sg:province":"Hamburg",
    "wof:name":"Dieter Haberland",
    "wof:placetype":"venue"
},
  "geometry": {"coordinates":[10.076669693,53.6471099854],"type":"Point"}
}