{
  "type": "Feature",
  "properties": {
    "iso:country":"DE",
    "sg:address":"Zimmermannsweg 2",
    "sg:city":"Salzbergen",
    "sg:phone":"+49 5976/1227",
    "sg:postcode":"48499",
    "sg:province":"Niedersachsen",
    "wof:name":"Gerhard Altevolmer",
    "wof:placetype":"venue"
},
  "geometry": {"coordinates":[7.3763990402,52.3064460754],"type":"Point"}
}