{
  "type": "Feature",
  "properties": {
    "iso:country":"DE",
    "sg:address":"Schleswiger Str. 9",
    "sg:city":"Sieverstedt",
    "sg:phone":"+49 4631/957",
    "sg:postcode":"24885",
    "sg:province":"Schleswig-Holstein",
    "wof:name":"Autohaus Rhode Gmbh",
    "wof:placetype":"venue"
},
  "geometry": {"coordinates":[9.466217041,54.6353874207],"type":"Point"}
}