{
  "type": "Feature",
  "properties": {
    "iso:country":"DE",
    "sg:address":"Dodendorfer Str. 114",
    "sg:city":"Magdeburg",
    "sg:phone":"+49 391/62926",
    "sg:postcode":"39120",
    "sg:province":"Sachsen-Anhalt",
    "wof:name":"Wohnungsbaugenossenschaft Stadt Magdeburg Von 1954 Eg",
    "wof:placetype":"venue"
},
  "geometry": {"coordinates":[11.6241645813,52.0984306335],"type":"Point"}
}