{
  "type": "Feature",
  "properties": {
    "iso:country":"DE",
    "sg:address":"Dianastr. 15",
    "sg:city":"Haar",
    "sg:phone":"+49 89/463626",
    "sg:postcode":"85540",
    "sg:province":"Bayern",
    "wof:name":"Hans Gassner Rechtsanwalt",
    "wof:placetype":"venue"
},
  "geometry": {"coordinates":[11.7198705673,48.1051445007],"type":"Point"}
}