{
  "type": "Feature",
  "properties": {
    "iso:country":"DE",
    "sg:address":"Postfach 222",
    "sg:city":"Mudersbach",
    "sg:phone":"+49 2745/270",
    "sg:postcode":"57550",
    "sg:province":"Rheinland-Pfalz",
    "wof:name":"Katholisches Pfarramt St. Josef",
    "wof:placetype":"venue"
},
  "geometry": {"coordinates":[7.9484210014,50.82604599],"type":"Point"}
}