{
  "type": "Feature",
  "properties": {
    "iso:country":"DE",
    "sg:address":"Hauptstr. 44",
    "sg:city":"Schwebheim",
    "sg:phone":"+49 9723/2236",
    "sg:postcode":"97525",
    "sg:province":"Bayern",
    "wof:name":"Oskar Gutbrot",
    "wof:placetype":"venue"
},
  "geometry": {"coordinates":[10.248238,49.991131],"type":"Point"}
}