{
  "type": "Feature",
  "properties": {
    "iso:country":"DE",
    "sg:address":"Augustin-Bea-Str. 8",
    "sg:city":"Oberteuringen",
    "sg:phone":"+49 7546/1324",
    "sg:postcode":"88094",
    "sg:province":"Baden-W\u00fcrttemberg",
    "wof:name":"Michael Pap",
    "wof:placetype":"venue"
},
  "geometry": {"coordinates":[9.4716453552,47.7262992859],"type":"Point"}
}