{
  "type": "Feature",
  "properties": {
    "iso:country":"DE",
    "sg:address":"Cirksenastr. 26",
    "sg:city":"Krummh\u00f6rn",
    "sg:phone":"+49 4923/912020",
    "sg:postcode":"26736",
    "sg:province":"Niedersachsen",
    "wof:name":"Kampe W\u00e4cken E. K.",
    "wof:placetype":"venue"
},
  "geometry": {"coordinates":[7.0964198112,53.4359588623],"type":"Point"}
}