{
  "type": "Feature",
  "properties": {
    "iso:country":"DE",
    "sg:address":"Reichsstr. 89",
    "sg:city":"Berlin",
    "sg:phone":"+49 30/3043768",
    "sg:postcode":"14052",
    "sg:province":"Berlin",
    "wof:name":"Kurzwaren Kopplow Inh. Frank Pullwitt",
    "wof:placetype":"venue"
},
  "geometry": {"coordinates":[13.2641162872,52.5139694214],"type":"Point"}
}