{
  "type": "Feature",
  "properties": {
    "iso:country":"DE",
    "sg:address":"Parkallee 25",
    "sg:city":"Hamburg",
    "sg:postcode":"20144",
    "sg:province":"Hamburg",
    "wof:name":"Hamburg Incentives And Events",
    "wof:placetype":"venue"
},
  "geometry": {"coordinates":[9.983714,53.575325],"type":"Point"}
}