{
  "type": "Feature",
  "properties": {
    "iso:country":"DE",
    "sg:address":"Karl-Erb-Ring 93",
    "sg:city":"Ravensburg",
    "sg:phone":"+49 751/92538",
    "sg:postcode":"88213",
    "sg:province":"Baden-W\u00fcrttemberg",
    "wof:name":"Horst-paul Nanz",
    "wof:placetype":"venue"
},
  "geometry": {"coordinates":[9.577793,47.78117],"type":"Point"}
}