{
  "type": "Feature",
  "properties": {
    "iso:country":"DE",
    "sg:address":"Lindenstr. 14",
    "sg:city":"Bleicherode",
    "sg:phone":"+49 36338/40820",
    "sg:postcode":"99752",
    "sg:province":"Th\u00fcringen",
    "wof:name":"W. Koch",
    "wof:placetype":"venue"
},
  "geometry": {"coordinates":[10.5704,51.441452],"type":"Point"}
}