{
  "type": "Feature",
  "properties": {
    "iso:country":"DE",
    "sg:address":"Erzbergerstr. 119",
    "sg:city":"Karlsruhe",
    "sg:phone":"+49 721/95970",
    "sg:postcode":"76133",
    "sg:province":"Baden-W\u00fcrttemberg",
    "wof:name":"Plan View Gmbh",
    "wof:placetype":"venue"
},
  "geometry": {"coordinates":[8.3851833344,49.0240020752],"type":"Point"}
}