{
  "type": "Feature",
  "properties": {
    "iso:country":"DE",
    "sg:address":"Friedrichstr. 5a",
    "sg:city":"Bad Neuenahr-Ahrweiler",
    "sg:phone":"+49 2641/389330",
    "sg:postcode":"53474",
    "sg:province":"Rheinland-Pfalz",
    "wof:name":"Hermann Terporten B\u00fcro F. Ing.- Und Tiefbau Gmbh",
    "wof:placetype":"venue"
},
  "geometry": {"coordinates":[7.0997719765,50.5436477661],"type":"Point"}
}