{
  "type": "Feature",
  "properties": {
    "iso:country":"DE",
    "sg:address":"Melchersstr. 54",
    "sg:city":"M\u00fcnster",
    "sg:phone":"+49 251/274051",
    "sg:postcode":"48149",
    "sg:province":"Nordrhein-Westfalen",
    "wof:name":"Clemens Verlage Steuerberater",
    "wof:placetype":"venue"
},
  "geometry": {"coordinates":[7.6171579361,51.9717407227],"type":"Point"}
}