{
  "type": "Feature",
  "properties": {
    "iso:country":"DE",
    "sg:address":"Karl-Arnold-Str. 98",
    "sg:city":"Geilenkirchen",
    "sg:phone":"+49 2451/68599",
    "sg:postcode":"52511",
    "sg:province":"Nordrhein-Westfalen",
    "wof:name":"K\u00e4thi Hoffmanns",
    "wof:placetype":"venue"
},
  "geometry": {"coordinates":[6.07456,50.981384],"type":"Point"}
}