{
  "type": "Feature",
  "properties": {
    "iso:country":"DE",
    "sg:address":"Eschersheimer Landstr. 311",
    "sg:city":"Frankfurt",
    "sg:phone":"+49 69/565620",
    "sg:postcode":"60320",
    "sg:province":"Hessen",
    "wof:name":"Eiscafe La Gelateria",
    "wof:placetype":"venue"
},
  "geometry": {"coordinates":[8.669631,50.139858],"type":"Point"}
}