{
  "type": "Feature",
  "properties": {
    "iso:country":"DE",
    "sg:address":"Boschens\u00e4ge 1",
    "sg:city":"Weitnau",
    "sg:phone":"+49 8375/8710",
    "sg:postcode":"87480",
    "sg:province":"Bayern",
    "wof:name":"E. Grosecker U. R. Thiel",
    "wof:placetype":"venue"
},
  "geometry": {"coordinates":[10.086403,47.656414],"type":"Point"}
}