{
  "type": "Feature",
  "properties": {
    "iso:country":"DE",
    "sg:address":"Finkenweg 24",
    "sg:city":"H\u00fcckelhoven",
    "sg:phone":"+49 2462/42094180",
    "sg:postcode":"41836",
    "sg:province":"Nordrhein-Westfalen",
    "wof:name":"Reischert & Schiffer",
    "wof:placetype":"venue"
},
  "geometry": {"coordinates":[6.23251,51.00724],"type":"Point"}
}