{
  "type": "Feature",
  "properties": {
    "iso:country":"DE",
    "sg:address":"Beutelsbach",
    "sg:city":"Weinstadt",
    "sg:phone":"+49 7151/99330",
    "sg:postcode":"71384",
    "sg:province":"Baden-W\u00fcrttemberg",
    "wof:name":"Landgut-burg Gmbh",
    "wof:placetype":"venue"
},
  "geometry": {"coordinates":[9.3759098053,48.8090248108],"type":"Point"}
}