{
  "type": "Feature",
  "properties": {
    "iso:country":"DE",
    "sg:address":"Alte Krakauer Str. 17",
    "sg:city":"Brandenburg",
    "sg:phone":"+49 4743/2550",
    "sg:postcode":"14776",
    "sg:province":"Brandenburg",
    "wof:name":"Planen Und Bauen Baubetreuungs Gmbh",
    "wof:placetype":"venue"
},
  "geometry": {"coordinates":[12.57294,52.419922],"type":"Point"}
}