{
  "type": "Feature",
  "properties": {
    "iso:country":"DE",
    "sg:address":"Czarnikauer Str. 1",
    "sg:city":"Berlin",
    "sg:phone":"+49 30/4457881",
    "sg:postcode":"10439",
    "sg:province":"Berlin",
    "wof:name":"Franziska Schmidt",
    "wof:placetype":"venue"
},
  "geometry": {"coordinates":[13.4080858231,52.5534057617],"type":"Point"}
}