{
  "type": "Feature",
  "properties": {
    "iso:country":"DE",
    "sg:address":"Geigenbergerstr. 11",
    "sg:city":"M\u00fcnchen",
    "sg:phone":"+49 89/792640",
    "sg:postcode":"81477",
    "sg:province":"Bayern",
    "wof:name":"Dr. Hans Schmidt",
    "wof:placetype":"venue"
},
  "geometry": {"coordinates":[11.5144958496,48.0824394226],"type":"Point"}
}