{
  "type": "Feature",
  "properties": {
    "iso:country":"DE",
    "sg:address":"Vogelstromweg 34",
    "sg:city":"Herford",
    "sg:phone":"+49 5221/73565",
    "sg:postcode":"32052",
    "sg:province":"Nordrhein-Westfalen",
    "wof:name":"Andreas Fleer Verwaltungs-gmbh",
    "wof:placetype":"venue"
},
  "geometry": {"coordinates":[8.680595,52.100388],"type":"Point"}
}