{
  "type": "Feature",
  "properties": {
    "iso:country":"DE",
    "sg:address":"Stra\u00dfe der Jugend 2",
    "sg:city":"Sputendorf",
    "sg:phone":"+49 33701/56266",
    "sg:postcode":"14532",
    "sg:province":"Brandenburg",
    "wof:name":"Reitanlage Gut Marggraffshof Gmbh",
    "wof:placetype":"venue"
},
  "geometry": {"coordinates":[13.2244348526,52.4157791138],"type":"Point"}
}