{
  "type": "Feature",
  "properties": {
    "iso:country":"DE",
    "sg:address":"Schetters Busch 10",
    "sg:city":"Essen",
    "sg:phone":"+49 201/211799",
    "sg:postcode":"45309",
    "sg:province":"Nordrhein-Westfalen",
    "wof:name":"Hans-joachim Klubert",
    "wof:placetype":"venue"
},
  "geometry": {"coordinates":[7.0679402351,51.479309082],"type":"Point"}
}