{
  "type": "Feature",
  "properties": {
    "iso:country":"DE",
    "sg:address":"Schlo\u00dfstr. 5",
    "sg:city":"Framersheim",
    "sg:phone":"+49 6733/6359",
    "sg:postcode":"55234",
    "sg:province":"Rheinland-Pfalz",
    "wof:name":"Harald G\u00f6tz",
    "wof:placetype":"venue"
},
  "geometry": {"coordinates":[8.1786499023,49.7584381104],"type":"Point"}
}