{
  "type": "Feature",
  "properties": {
    "iso:country":"DE",
    "sg:address":"Kaiser-Wilhelm-Ring 41",
    "sg:city":"D\u00fcsseldorf",
    "sg:postcode":"40545",
    "sg:province":"Nordrhein-Westfalen",
    "wof:name":"Philip Services Deutschland Gmbh",
    "wof:placetype":"venue"
},
  "geometry": {"coordinates":[6.760701,51.227844],"type":"Point"}
}