{
  "type": "Feature",
  "properties": {
    "iso:country":"DE",
    "sg:address":"Dietengasse 25",
    "sg:city":"Bingen",
    "sg:phone":"+49 6725/2692",
    "sg:postcode":"55411",
    "sg:province":"Rheinland-Pfalz",
    "wof:name":"Willi Lamoth",
    "wof:placetype":"venue"
},
  "geometry": {"coordinates":[7.9638571739,49.9236106873],"type":"Point"}
}