{
  "type": "Feature",
  "properties": {
    "iso:country":"DE",
    "sg:address":"Eduard-Oehler-Str. 55",
    "sg:city":"Offenbach",
    "sg:phone":"+49 69/863490",
    "sg:postcode":"63075",
    "sg:province":"Hessen",
    "wof:name":"Bernhard Sch\u00e4fer Elektromeister",
    "wof:placetype":"venue"
},
  "geometry": {"coordinates":[8.795857,50.110279],"type":"Point"}
}