{
  "type": "Feature",
  "properties": {
    "iso:country":"DE",
    "sg:address":"Marienh\u00f6he 152",
    "sg:city":"Quickborn",
    "sg:phone":"+49 4106/67223",
    "sg:postcode":"25451",
    "sg:province":"Schleswig-Holstein",
    "wof:name":"Karl-heinz G\u00f6pfert Architekt",
    "wof:placetype":"venue"
},
  "geometry": {"coordinates":[9.902336,53.722946],"type":"Point"}
}