{
  "type": "Feature",
  "properties": {
    "iso:country":"DE",
    "sg:address":"Hauptstr. 39",
    "sg:city":"Mutlangen",
    "sg:phone":"+49 7171/73500",
    "sg:postcode":"73557",
    "sg:province":"Baden-W\u00fcrttemberg",
    "wof:name":"Gisela Kaim",
    "wof:placetype":"venue"
},
  "geometry": {"coordinates":[9.797197,48.825119],"type":"Point"}
}