{
  "type": "Feature",
  "properties": {
    "iso:country":"DE",
    "sg:address":"Saareckstr. 17",
    "sg:city":"Merzig",
    "sg:postcode":"66663",
    "sg:province":"Saarland",
    "wof:name":"Bauunternehmung Konrad Gro\u00df Gmbh",
    "wof:placetype":"venue"
},
  "geometry": {"coordinates":[6.595651,49.464558],"type":"Point"}
}