{
  "type": "Feature",
  "properties": {
    "iso:country":"DE",
    "sg:address":"Ruhlandweg 4",
    "sg:city":"Cadolzburg",
    "sg:postcode":"90556",
    "sg:province":"Bayern",
    "wof:name":"J. Lorenz Gmbh",
    "wof:placetype":"venue"
},
  "geometry": {"coordinates":[10.882536,49.456169],"type":"Point"}
}