{
  "type": "Feature",
  "properties": {
    "iso:country":"DE",
    "sg:address":"Auf dem Steinocken 5",
    "sg:city":"Balve",
    "sg:phone":"+49 2375/910064",
    "sg:postcode":"58802",
    "sg:province":"Nordrhein-Westfalen",
    "wof:name":"Hlh Biovita Vertriebs Gmbh",
    "wof:placetype":"venue"
},
  "geometry": {"coordinates":[7.870907,51.342781],"type":"Point"}
}