{
  "type": "Feature",
  "properties": {
    "iso:country":"DE",
    "sg:address":"Gartenstr.",
    "sg:city":"Starkenburg",
    "sg:phone":"+49 6541/6611",
    "sg:postcode":"56843",
    "sg:province":"Rheinland-Pfalz",
    "wof:name":"Pension Horst Henn",
    "wof:placetype":"venue"
},
  "geometry": {"coordinates":[7.1408691406,49.9548873901],"type":"Point"}
}