{
  "type": "Feature",
  "properties": {
    "iso:country":"DE",
    "sg:address":"Oststr. 3",
    "sg:city":"Korschenbroich",
    "sg:phone":"+49 2161/671818",
    "sg:postcode":"41352",
    "sg:province":"Nordrhein-Westfalen",
    "wof:name":"Henrys Partyservice Gmbh",
    "wof:placetype":"venue"
},
  "geometry": {"coordinates":[6.5596289635,51.2057647705],"type":"Point"}
}