{
  "type": "Feature",
  "properties": {
    "iso:country":"DE",
    "sg:address":"Hundert-Morgen-Str. 38",
    "sg:city":"Kelsterbach",
    "sg:phone":"+49 6107/3946",
    "sg:postcode":"65451",
    "sg:province":"Hessen",
    "wof:name":"G\u00fcnther Allendorf",
    "wof:placetype":"venue"
},
  "geometry": {"coordinates":[8.530666,50.055592],"type":"Point"}
}