{
  "type": "Feature",
  "properties": {
    "iso:country":"DE",
    "sg:address":"Schleiferstr. 13",
    "sg:city":"Ratingen",
    "sg:phone":"+49 2102/24405",
    "sg:postcode":"40878",
    "sg:province":"Nordrhein-Westfalen",
    "wof:name":"H. Boltenburg",
    "wof:placetype":"venue"
},
  "geometry": {"coordinates":[6.8562698364,51.2948684692],"type":"Point"}
}