{
  "type": "Feature",
  "properties": {
    "iso:country":"DE",
    "sg:address":"Gildehauser Weg 114a",
    "sg:city":"Nordhorn",
    "sg:phone":"+49 5921/14729",
    "sg:postcode":"48529",
    "sg:province":"Niedersachsen",
    "wof:name":"Pizzeria Karawan",
    "wof:placetype":"venue"
},
  "geometry": {"coordinates":[7.0674190521,52.4106178284],"type":"Point"}
}