{
  "type": "Feature",
  "properties": {
    "iso:country":"DE",
    "sg:address":"Georgstr. 18",
    "sg:city":"Bad Rothenfelde",
    "sg:phone":"+49 5424/4172",
    "sg:postcode":"49214",
    "sg:province":"Niedersachsen",
    "wof:name":"Gerd Domann Architekt",
    "wof:placetype":"venue"
},
  "geometry": {"coordinates":[8.15631,52.107708],"type":"Point"}
}