{
  "type": "Feature",
  "properties": {
    "iso:country":"DE",
    "sg:address":"Parkstr. 6a",
    "sg:city":"Buchow-Karpzow",
    "sg:phone":"+49 33234/89473",
    "sg:postcode":"14641",
    "sg:province":"Brandenburg",
    "wof:name":"Poppe & Domr\u00f6s Gbr",
    "wof:placetype":"venue"
},
  "geometry": {"coordinates":[12.940798,52.517124],"type":"Point"}
}