{
  "type": "Feature",
  "properties": {
    "iso:country":"DE",
    "sg:address":"Obere Lerch 20",
    "sg:city":"Georgensgm\u00fcnd",
    "sg:phone":"+49 9172/69820",
    "sg:postcode":"91166",
    "sg:province":"Bayern",
    "wof:name":"Karl Breit",
    "wof:placetype":"venue"
},
  "geometry": {"coordinates":[11.003218,49.17543],"type":"Point"}
}