{
  "type": "Feature",
  "properties": {
    "iso:country":"DE",
    "sg:address":"Gr\u00fcner Weg 31",
    "sg:city":"Nottuln",
    "sg:phone":"+49 2502/223030",
    "sg:postcode":"48301",
    "sg:province":"Nordrhein-Westfalen",
    "wof:name":"Anstaltsbedarf-gro\u00dfhandel Lothar Oelmann",
    "wof:placetype":"venue"
},
  "geometry": {"coordinates":[7.3375778198,51.9300918579],"type":"Point"}
}