{
  "type": "Feature",
  "properties": {
    "iso:country":"DE",
    "sg:address":"Talstr. 23",
    "sg:city":"Eppenbrunn",
    "sg:phone":"+49 6335/7059",
    "sg:postcode":"66957",
    "sg:province":"Rheinland-Pfalz",
    "wof:name":"E. Kunz",
    "wof:placetype":"venue"
},
  "geometry": {"coordinates":[7.555922,49.116138],"type":"Point"}
}