{
  "type": "Feature",
  "properties": {
    "iso:country":"DE",
    "sg:address":"H\u00f6inger Str. 7",
    "sg:city":"Ebsdorfergrund",
    "sg:phone":"+49 6424/6817",
    "sg:postcode":"35085",
    "sg:province":"Hessen",
    "wof:name":"Johannes Rink",
    "wof:placetype":"venue"
},
  "geometry": {"coordinates":[8.88483,50.75238],"type":"Point"}
}