{
  "type": "Feature",
  "properties": {
    "iso:country":"DE",
    "sg:address":"Holbeinstr. 13",
    "sg:city":"Duisburg",
    "sg:phone":"+49 203/497275",
    "sg:postcode":"47179",
    "sg:province":"Nordrhein-Westfalen",
    "wof:name":"R. Lipka",
    "wof:placetype":"venue"
},
  "geometry": {"coordinates":[6.7454819679,51.5357513428],"type":"Point"}
}