{
  "type": "Feature",
  "properties": {
    "iso:country":"DE",
    "sg:address":"Paulstr. 51",
    "sg:city":"Rheine",
    "sg:phone":"+49 5971/64568",
    "sg:postcode":"48429",
    "sg:province":"Nordrhein-Westfalen",
    "wof:name":"Bernhard Essmann",
    "wof:placetype":"venue"
},
  "geometry": {"coordinates":[7.444291,52.285824],"type":"Point"}
}