{
  "type": "Feature",
  "properties": {
    "iso:country":"DE",
    "sg:address":"Falkensteiner Str. 6",
    "sg:city":"Bergen",
    "sg:phone":"+49 37463/88293",
    "sg:postcode":"08239",
    "sg:province":"Sachsen",
    "wof:name":"Taubner Und Partner Planungsb\u00fcro",
    "wof:placetype":"venue"
},
  "geometry": {"coordinates":[12.2762804031,50.4728355408],"type":"Point"}
}