{
  "type": "Feature",
  "properties": {
    "iso:country":"DE",
    "sg:address":"Babostr. 12",
    "sg:city":"Abensberg",
    "sg:phone":"+49 9443/1377",
    "sg:postcode":"93326",
    "sg:province":"Bayern",
    "wof:name":"Romana",
    "wof:placetype":"venue"
},
  "geometry": {"coordinates":[11.844565,48.814777],"type":"Point"}
}