{
  "type": "Feature",
  "properties": {
    "iso:country":"DE",
    "sg:address":"Roxheimer Str. 1a",
    "sg:city":"Worms",
    "sg:phone":"+49 6241/38193",
    "sg:postcode":"67547",
    "sg:province":"Rheinland-Pfalz",
    "wof:name":"Top-team Cnc Fertigung Gmbh",
    "wof:placetype":"venue"
},
  "geometry": {"coordinates":[8.3500576019,49.6131896973],"type":"Point"}
}