{
  "type": "Feature",
  "properties": {
    "iso:country":"DE",
    "sg:address":"Marktstr. 24",
    "sg:city":"Rauhenebrach",
    "sg:phone":"+49 9554/1777",
    "sg:postcode":"96181",
    "sg:province":"Bayern",
    "wof:name":"Alois Schraut",
    "wof:placetype":"venue"
},
  "geometry": {"coordinates":[10.6261539459,49.8731079102],"type":"Point"}
}