{
  "type": "Feature",
  "properties": {
    "iso:country":"DE",
    "sg:address":"K\u00f6nigsberger Str. 34 a",
    "sg:city":"Gelsenkirchen",
    "sg:phone":"+49 209/84923",
    "sg:postcode":"45881",
    "sg:province":"Nordrhein-Westfalen",
    "wof:name":"Horst Elshoff",
    "wof:placetype":"venue"
},
  "geometry": {"coordinates":[7.0945959091,51.5163459778],"type":"Point"}
}