{
  "type": "Feature",
  "properties": {
    "iso:country":"DE",
    "sg:address":"Petersbergstr. 9",
    "sg:city":"Meckesheim",
    "sg:phone":"+49 6226/9320",
    "sg:postcode":"74909",
    "sg:province":"Baden-W\u00fcrttemberg",
    "wof:name":"Herbold Zerkleinerungstechnik Gmbh",
    "wof:placetype":"venue"
},
  "geometry": {"coordinates":[8.805884,49.323002],"type":"Point"}
}