{
  "type": "Feature",
  "properties": {
    "iso:country":"DE",
    "sg:address":"Vogelweidestr. 3",
    "sg:city":"M\u00fcnchen",
    "sg:phone":"+49 89/418640",
    "sg:postcode":"81677",
    "sg:province":"Bayern",
    "wof:name":"Mercur Assistance Reise Service Zn Der Amtliches",
    "wof:placetype":"venue"
},
  "geometry": {"coordinates":[11.6196908951,48.1387023926],"type":"Point"}
}