{
  "type": "Feature",
  "properties": {
    "iso:country":"DE",
    "sg:address":"Berliner Str. 27",
    "sg:city":"G\u00fctersloh",
    "sg:phone":"+49 5241/236134",
    "sg:postcode":"33330",
    "sg:province":"Nordrhein-Westfalen",
    "wof:name":"Metro",
    "wof:placetype":"venue"
},
  "geometry": {"coordinates":[8.3790149689,51.9068717957],"type":"Point"}
}