{
  "type": "Feature",
  "properties": {
    "iso:country":"DE",
    "sg:address":"Mittelweg 19",
    "sg:city":"Markkleeberg",
    "sg:phone":"+49 341/3587370",
    "sg:postcode":"04416",
    "sg:province":"Sachsen",
    "wof:name":"Kurt M\u00fcller",
    "wof:placetype":"venue"
},
  "geometry": {"coordinates":[12.354191,51.265766],"type":"Point"}
}