{
  "type": "Feature",
  "properties": {
    "iso:country":"DE",
    "sg:address":"Nigerstr. 4",
    "sg:city":"M\u00fcnchen",
    "sg:phone":"+49 89/475344",
    "sg:postcode":"81675",
    "sg:province":"Bayern",
    "wof:name":"M. Heeg",
    "wof:placetype":"venue"
},
  "geometry": {"coordinates":[11.6049947739,48.1378364563],"type":"Point"}
}