{
  "type": "Feature",
  "properties": {
    "iso:country":"DE",
    "sg:address":"Postfach 13 26",
    "sg:city":"Waiblingen",
    "sg:phone":"+49 7151/92220",
    "sg:postcode":"71303",
    "sg:province":"Baden-W\u00fcrttemberg",
    "wof:name":"Verlagsb\u00fcro H\u00fcller & Partner",
    "wof:placetype":"venue"
},
  "geometry": {"coordinates":[9.31405,48.832001],"type":"Point"}
}