{
  "type": "Feature",
  "properties": {
    "iso:country":"DE",
    "sg:address":"Molkereiplatz 2",
    "sg:city":"Niederraunau",
    "sg:phone":"+49 8282",
    "sg:postcode":"86381",
    "sg:province":"Bayern",
    "wof:name":"Marketing & Promotion",
    "wof:placetype":"venue"
},
  "geometry": {"coordinates":[10.3799180984,48.2243919373],"type":"Point"}
}