{
  "type": "Feature",
  "properties": {
    "iso:country":"DE",
    "sg:address":"Ziegetsdorfer Str. 3",
    "sg:city":"Regensburg",
    "sg:phone":"+49 941/993131",
    "sg:postcode":"93051",
    "sg:province":"Bayern",
    "wof:name":"Heinrich Lobmeyer Ingenieur",
    "wof:placetype":"venue"
},
  "geometry": {"coordinates":[12.0693454742,48.9955177307],"type":"Point"}
}