{
  "type": "Feature",
  "properties": {
    "iso:country":"DE",
    "sg:address":"Sch\u00f6neworth 26",
    "sg:city":"Freiburg",
    "sg:phone":"+49 4779/272",
    "sg:postcode":"21729",
    "sg:province":"Niedersachsen",
    "wof:name":"Claus Horeis",
    "wof:placetype":"venue"
},
  "geometry": {"coordinates":[9.271731,53.824284],"type":"Point"}
}