{
  "type": "Feature",
  "properties": {
    "iso:country":"DE",
    "sg:address":"K\u00fcnkelstr. 44",
    "sg:city":"M\u00f6nchengladbach",
    "sg:phone":"+49 2161/182449",
    "sg:postcode":"41063",
    "sg:province":"Nordrhein-Westfalen",
    "wof:name":"H\u00e4nseroth Inh. Walter Leppinius",
    "wof:placetype":"venue"
},
  "geometry": {"coordinates":[6.4516839981,51.2106971741],"type":"Point"}
}