{
  "type": "Feature",
  "properties": {
    "iso:country":"DE",
    "sg:address":"Plabennecstr. 20",
    "sg:city":"Waltenhofen",
    "sg:phone":"+49 8303/1222",
    "sg:postcode":"87448",
    "sg:province":"Bayern",
    "wof:name":"Fritsche & Weigl Gbr",
    "wof:placetype":"venue"
},
  "geometry": {"coordinates":[10.3091163635,47.675945282],"type":"Point"}
}