{
  "type": "Feature",
  "properties": {
    "iso:country":"DE",
    "sg:address":"Blumenweg 3",
    "sg:city":"Rheinfelden",
    "sg:phone":"+49 7623/2123",
    "sg:postcode":"79618",
    "sg:province":"Baden-W\u00fcrttemberg",
    "wof:name":"Dfa Kathleen Rabis",
    "wof:placetype":"venue"
},
  "geometry": {"coordinates":[7.7868962288,47.5624351501],"type":"Point"}
}