{
  "type": "Feature",
  "properties": {
    "iso:country":"DE",
    "sg:address":"Steinheimer Str. 34",
    "sg:city":"Hanau",
    "sg:phone":"+49 6181/23602",
    "sg:postcode":"63450",
    "sg:province":"Hessen",
    "wof:name":"E. Costa",
    "wof:placetype":"venue"
},
  "geometry": {"coordinates":[8.915006,50.133965],"type":"Point"}
}