{
  "type": "Feature",
  "properties": {
    "iso:country":"DE",
    "sg:address":"Gro\u00dfe Str. 62-64",
    "sg:city":"Ibbenb\u00fcren",
    "sg:phone":"+49 5451/4041",
    "sg:postcode":"49477",
    "sg:province":"Nordrhein-Westfalen",
    "wof:name":"Wehmeyer Ohg",
    "wof:placetype":"venue"
},
  "geometry": {"coordinates":[7.711501,52.279587],"type":"Point"}
}