{
  "type": "Feature",
  "properties": {
    "iso:country":"DE",
    "sg:address":"Alter Postweg 3",
    "sg:city":"Isselburg",
    "sg:phone":"+49 2874/3325",
    "sg:postcode":"46419",
    "sg:province":"Nordrhein-Westfalen",
    "wof:name":"Franz-josef Kobs Heissmangel",
    "wof:placetype":"venue"
},
  "geometry": {"coordinates":[6.468380928,51.8306541443],"type":"Point"}
}