{
  "type": "Feature",
  "properties": {
    "iso:country":"DE",
    "sg:address":"Hauptstr. 105",
    "sg:city":"Alterk\u00fclz",
    "sg:phone":"+49 6762/7361",
    "sg:postcode":"56288",
    "sg:province":"Rheinland-Pfalz",
    "wof:name":"Friedel Simson",
    "wof:placetype":"venue"
},
  "geometry": {"coordinates":[7.45481,50.033863],"type":"Point"}
}