{
  "type": "Feature",
  "properties": {
    "iso:country":"DE",
    "sg:address":"Haiger Str. 15-16",
    "sg:city":"Kronach",
    "sg:phone":"+49 9261/3818",
    "sg:postcode":"96317",
    "sg:province":"Bayern",
    "wof:name":"R. Und M. K\u00fchlein Kg",
    "wof:placetype":"venue"
},
  "geometry": {"coordinates":[11.29961,50.274101],"type":"Point"}
}