{
  "type": "Feature",
  "properties": {
    "iso:country":"DE",
    "sg:address":"Iserlohner Str. 14",
    "sg:city":"Castrop-Rauxel",
    "sg:phone":"+49 2305/34326",
    "sg:postcode":"44575",
    "sg:province":"Nordrhein-Westfalen",
    "wof:name":"H & P. Verwaltungs- Und Verm\u00f6gensmanagement Gmbh",
    "wof:placetype":"venue"
},
  "geometry": {"coordinates":[7.3250150681,51.5606231689],"type":"Point"}
}