{
  "type": "Feature",
  "properties": {
    "iso:country":"DE",
    "sg:address":"Industriestr. 24",
    "sg:city":"Coesfeld",
    "sg:phone":"+49 2546/7087",
    "sg:postcode":"48653",
    "sg:province":"Nordrhein-Westfalen",
    "wof:name":"Br\u00fcder Kunz Gmbh & Co. Kg",
    "wof:placetype":"venue"
},
  "geometry": {"coordinates":[7.1786990166,51.8913421631],"type":"Point"}
}