{
  "type": "Feature",
  "properties": {
    "iso:country":"DE",
    "sg:address":"An den Eichen 9",
    "sg:city":"Dahmsdorf",
    "sg:phone":"+49 3535/20556",
    "sg:postcode":"15864",
    "sg:province":"Brandenburg",
    "wof:name":"Ralph Erdmann",
    "wof:placetype":"venue"
},
  "geometry": {"coordinates":[14.0047721863,52.2141647339],"type":"Point"}
}