{
  "type": "Feature",
  "properties": {
    "iso:country":"DE",
    "sg:address":"Schlo\u00dfstr. 46",
    "sg:city":"Bergisch Gladbach",
    "sg:phone":"+49 2204/584627",
    "sg:postcode":"51429",
    "sg:province":"Nordrhein-Westfalen",
    "wof:name":"J\u00fcrgen Kruiniger",
    "wof:placetype":"venue"
},
  "geometry": {"coordinates":[7.158396,50.965992],"type":"Point"}
}