{
  "type": "Feature",
  "properties": {
    "iso:country":"DE",
    "sg:address":"Unterm Enschede 6",
    "sg:city":"Olsberg",
    "sg:postcode":"59939",
    "sg:province":"Nordrhein-Westfalen",
    "wof:name":"Theodor Becker",
    "wof:placetype":"venue"
},
  "geometry": {"coordinates":[8.5012960434,51.3062591553],"type":"Point"}
}