{
  "type": "Feature",
  "properties": {
    "iso:country":"DE",
    "sg:address":"Lindenburgweg 1",
    "sg:city":"Murnau",
    "sg:phone":"+49 8841/9409",
    "sg:postcode":"82418",
    "sg:province":"Bayern",
    "wof:name":"Krolls Bierbrunnen",
    "wof:placetype":"venue"
},
  "geometry": {"coordinates":[11.206445694,47.6795043945],"type":"Point"}
}