{
  "type": "Feature",
  "properties": {
    "iso:country":"DE",
    "sg:address":"Spessartblick 15",
    "sg:city":"Freigericht",
    "sg:phone":"+49 6055/934288",
    "sg:postcode":"63579",
    "sg:province":"Hessen",
    "wof:name":"Schilling Concerts Freigericht",
    "wof:placetype":"venue"
},
  "geometry": {"coordinates":[9.15959,50.142166],"type":"Point"}
}