{
  "type": "Feature",
  "properties": {
    "iso:country":"DE",
    "sg:address":"Rosenthallohne 23",
    "sg:city":"Norden",
    "sg:phone":"+49 4931/13532",
    "sg:postcode":"26506",
    "sg:province":"Niedersachsen",
    "wof:name":"Jann Janssen",
    "wof:placetype":"venue"
},
  "geometry": {"coordinates":[7.2073540688,53.5977554321],"type":"Point"}
}