{
  "type": "Feature",
  "properties": {
    "iso:country":"DE",
    "sg:address":"Lederstr. 40",
    "sg:city":"Calw",
    "sg:phone":"+49 7051/2963",
    "sg:postcode":"75365",
    "sg:province":"Baden-W\u00fcrttemberg",
    "wof:name":"Karl Hermann M\u00f6hler Architekt",
    "wof:placetype":"venue"
},
  "geometry": {"coordinates":[8.73867,48.716019],"type":"Point"}
}