{
  "type": "Feature",
  "properties": {
    "iso:country":"DE",
    "sg:address":"Bachstr. 3",
    "sg:city":"Warburg",
    "sg:phone":"+49 5641/50841",
    "sg:postcode":"34414",
    "sg:province":"Nordrhein-Westfalen",
    "wof:name":"Martin Helling",
    "wof:placetype":"venue"
},
  "geometry": {"coordinates":[9.1284046173,51.4914512634],"type":"Point"}
}