{
  "type": "Feature",
  "properties": {
    "iso:country":"DE",
    "sg:address":"An der Thronpost 1",
    "sg:city":"Greifswald",
    "sg:phone":"+49 3834/500320",
    "sg:postcode":"17489",
    "sg:province":"Mecklenburg-Vorpommern",
    "wof:name":"Mcdonald's Deutschland Inc.",
    "wof:placetype":"venue"
},
  "geometry": {"coordinates":[13.3938436508,54.0726547241],"type":"Point"}
}