{
  "type": "Feature",
  "properties": {
    "iso:country":"DE",
    "sg:address":"Goethestr. 9",
    "sg:city":"Crivitz",
    "sg:phone":"+49 3863/555370",
    "sg:postcode":"19089",
    "sg:province":"Mecklenburg-Vorpommern",
    "wof:name":"Harry Sudrow",
    "wof:placetype":"venue"
},
  "geometry": {"coordinates":[11.6488790512,53.5771827698],"type":"Point"}
}