{
  "type": "Feature",
  "properties": {
    "iso:country":"DE",
    "sg:address":"Am Lindenknipp 4",
    "sg:city":"Herzogenrath",
    "sg:phone":"+49 2406/62581",
    "sg:postcode":"52134",
    "sg:province":"Nordrhein-Westfalen",
    "wof:name":"Johann Neu",
    "wof:placetype":"venue"
},
  "geometry": {"coordinates":[6.099977,50.883881],"type":"Point"}
}