{
  "type": "Feature",
  "properties": {
    "iso:country":"DE",
    "sg:address":"Meller Str. 15",
    "sg:city":"Osnabr\u00fcck",
    "sg:phone":"+49 541/588566",
    "sg:postcode":"49082",
    "sg:province":"Niedersachsen",
    "wof:name":"R. Steinkamp",
    "wof:placetype":"venue"
},
  "geometry": {"coordinates":[8.055839,52.265766],"type":"Point"}
}