{
  "type": "Feature",
  "properties": {
    "iso:country":"DE",
    "sg:address":"Martinstr. 5",
    "sg:city":"Stolberg",
    "sg:phone":"+49 2402/4823",
    "sg:postcode":"52222",
    "sg:province":"Nordrhein-Westfalen",
    "wof:name":"Hubert Rombach",
    "wof:placetype":"venue"
},
  "geometry": {"coordinates":[6.235835,50.780678],"type":"Point"}
}