{
  "type": "Feature",
  "properties": {
    "iso:country":"DE",
    "sg:address":"Vor der Brede 1a",
    "sg:city":"Bad Driburg",
    "sg:phone":"+49 5253/979911",
    "sg:postcode":"33014",
    "sg:province":"Nordrhein-Westfalen",
    "wof:name":"Kath. Pfarramt St. Peter Und Paul",
    "wof:placetype":"venue"
},
  "geometry": {"coordinates":[9.0212879181,51.7364387512],"type":"Point"}
}