{
  "type": "Feature",
  "properties": {
    "iso:country":"DE",
    "sg:address":"Imanuel-Maier-Str. 3",
    "sg:city":"K\u00f6ngen",
    "sg:phone":"+49 7024/81717",
    "sg:postcode":"73257",
    "sg:province":"Baden-W\u00fcrttemberg",
    "wof:name":"Tennishalle",
    "wof:placetype":"venue"
},
  "geometry": {"coordinates":[9.3615751266,48.6742858887],"type":"Point"}
}