{
  "type": "Feature",
  "properties": {
    "iso:country":"DE",
    "sg:address":"Lindenstr. 23 b",
    "sg:city":"Strehla",
    "sg:phone":"+49 35264/90824",
    "sg:postcode":"01616",
    "sg:province":"Sachsen",
    "wof:name":"A. Pestel",
    "wof:placetype":"venue"
},
  "geometry": {"coordinates":[13.227239,51.350796],"type":"Point"}
}