{
  "type": "Feature",
  "properties": {
    "iso:country":"DE",
    "sg:address":"Hofwiese 25",
    "sg:city":"Bottrop",
    "sg:phone":"+49 2045/3402",
    "sg:postcode":"46244",
    "sg:province":"Nordrhein-Westfalen",
    "wof:name":"Henry Benien",
    "wof:placetype":"venue"
},
  "geometry": {"coordinates":[6.910871,51.622395],"type":"Point"}
}