{
  "type": "Feature",
  "properties": {
    "iso:country":"DE",
    "sg:address":"Heinsberger Str. 2",
    "sg:city":"J\u00fclich",
    "sg:phone":"+49 2461/97250",
    "sg:postcode":"52428",
    "sg:province":"Nordrhein-Westfalen",
    "wof:name":"J. H. Ochsenbruch Steuerberater",
    "wof:placetype":"venue"
},
  "geometry": {"coordinates":[6.3598971367,50.9163818359],"type":"Point"}
}