{
  "type": "Feature",
  "properties": {
    "iso:country":"DE",
    "sg:address":"Schlo\u00dfstr. 15",
    "sg:city":"Heidenheim",
    "sg:phone":"+49 7321/43348",
    "sg:postcode":"89518",
    "sg:province":"Baden-W\u00fcrttemberg",
    "wof:name":"Reiber Gmbh",
    "wof:placetype":"venue"
},
  "geometry": {"coordinates":[10.149828,48.678089],"type":"Point"}
}