{
  "type": "Feature",
  "properties": {
    "iso:country":"DE",
    "sg:address":"Kasseler Str. 59",
    "sg:city":"Hann. M\u00fcnden",
    "sg:phone":"+49 5541/8889",
    "sg:postcode":"34346",
    "sg:province":"Niedersachsen",
    "wof:name":"Wintergarten-lichtspiele",
    "wof:placetype":"venue"
},
  "geometry": {"coordinates":[9.6500530243,51.4064826965],"type":"Point"}
}