{
  "type": "Feature",
  "properties": {
    "iso:country":"DE",
    "sg:address":"Ratzeburger Str. 40",
    "sg:city":"Bad Oldesloe",
    "sg:phone":"+49 4531/87889",
    "sg:postcode":"23843",
    "sg:province":"Schleswig-Holstein",
    "wof:name":"Dieter Hettmann",
    "wof:placetype":"venue"
},
  "geometry": {"coordinates":[10.3977918625,53.8050918579],"type":"Point"}
}