{
  "type": "Feature",
  "properties": {
    "iso:country":"DE",
    "sg:address":"Dillinger Str. 23",
    "sg:city":"Beckingen",
    "sg:phone":"+49 6835/2491",
    "sg:postcode":"66701",
    "sg:province":"Saarland",
    "wof:name":"St-ei-er Outfit Gabriele Hahn-mitterm\u00fcller",
    "wof:placetype":"venue"
},
  "geometry": {"coordinates":[6.699077,49.387489],"type":"Point"}
}