{
  "type": "Feature",
  "properties": {
    "iso:country":"DE",
    "sg:address":"Gro\u00df Eilstorf 47",
    "sg:city":"Walsrode",
    "sg:phone":"+49 5166/420",
    "sg:postcode":"29664",
    "sg:province":"Niedersachsen",
    "wof:name":"Rabens Maschinenbau Gmbh",
    "wof:placetype":"venue"
},
  "geometry": {"coordinates":[9.4540300369,52.8157806396],"type":"Point"}
}