{
  "type": "Feature",
  "properties": {
    "iso:country":"DE",
    "sg:address":"L\u00e4rchenweg 1",
    "sg:city":"S\u00f6chtenau",
    "sg:phone":"+49 8055/476",
    "sg:postcode":"83139",
    "sg:province":"Bayern",
    "wof:name":"Alois Fleidl",
    "wof:placetype":"venue"
},
  "geometry": {"coordinates":[12.2290773392,47.9329910278],"type":"Point"}
}