{
  "type": "Feature",
  "properties": {
    "iso:country":"DE",
    "sg:address":"Lessingstr. 33",
    "sg:city":"Weilburg",
    "sg:phone":"+49 6471/93790",
    "sg:postcode":"35781",
    "sg:province":"Hessen",
    "wof:name":"Gymnasium Philippinum Bibliothek",
    "wof:placetype":"venue"
},
  "geometry": {"coordinates":[8.2744522095,50.4868545532],"type":"Point"}
}