{
  "type": "Feature",
  "properties": {
    "iso:country":"DE",
    "sg:address":"Zum Pfingstberg 16",
    "sg:city":"Wormsdorf",
    "sg:phone":"+49 39409/528",
    "sg:postcode":"39365",
    "sg:province":"Sachsen-Anhalt",
    "wof:name":"H. Schwitzer",
    "wof:placetype":"venue"
},
  "geometry": {"coordinates":[11.1938552856,52.1348075867],"type":"Point"}
}