{
  "type": "Feature",
  "properties": {
    "iso:country":"DE",
    "sg:address":"Burgstr. 22",
    "sg:city":"Pfullingen",
    "sg:phone":"+49 7121/73053",
    "sg:postcode":"72793",
    "sg:province":"Baden-W\u00fcrttemberg",
    "wof:name":"B. Riester",
    "wof:placetype":"venue"
},
  "geometry": {"coordinates":[9.229729,48.470753],"type":"Point"}
}