{
  "type": "Feature",
  "properties": {
    "iso:country":"DE",
    "sg:address":"Wiesenstr. 43 a",
    "sg:city":"Hamburg",
    "sg:phone":"+49 40/40195938",
    "sg:postcode":"20255",
    "sg:province":"Hamburg",
    "wof:name":"Ulrich B\u00f6llert Heilpraktiker",
    "wof:placetype":"venue"
},
  "geometry": {"coordinates":[9.9536647797,53.5771942139],"type":"Point"}
}