{
  "type": "Feature",
  "properties": {
    "iso:country":"DE",
    "sg:address":"Daimlerstr. 7",
    "sg:city":"Maulbronn",
    "sg:phone":"+49 4970/438569",
    "sg:postcode":"75433",
    "sg:province":"Baden-W\u00fcrttemberg",
    "wof:name":"Stippl Gmbh",
    "wof:placetype":"venue"
},
  "geometry": {"coordinates":[8.789317131,48.9939956665],"type":"Point"}
}