{
  "type": "Feature",
  "properties": {
    "iso:country":"DE",
    "sg:address":"W-J-v-d-Wettern-Str 21",
    "sg:city":"K\u00f6ln",
    "sg:phone":"+49 2203/93350",
    "sg:postcode":"51149",
    "sg:province":"Nordrhein-Westfalen",
    "wof:name":"Wtw Engineering Maschinen- Und F\u00f6rderanlagenbau Gmbh",
    "wof:placetype":"venue"
},
  "geometry": {"coordinates":[7.031855,50.899223],"type":"Point"}
}