{
  "type": "Feature",
  "properties": {
    "iso:country":"DE",
    "sg:address":"Barwegskoppel 6d",
    "sg:city":"Winsen",
    "sg:postcode":"21423",
    "sg:province":"Niedersachsen",
    "wof:name":"Florissimo",
    "wof:placetype":"venue"
},
  "geometry": {"coordinates":[10.302168,53.334621],"type":"Point"}
}