{
  "type": "Feature",
  "properties": {
    "iso:country":"DE",
    "sg:address":"Sielstr. 12",
    "sg:city":"N\u00fcrnberg",
    "sg:phone":"+49 911/268665",
    "sg:postcode":"90429",
    "sg:province":"Bayern",
    "wof:name":"Lederer-kulturbrauerei",
    "wof:placetype":"venue"
},
  "geometry": {"coordinates":[11.0510702133,49.4545135498],"type":"Point"}
}