{
  "type": "Feature",
  "properties": {
    "iso:country":"DE",
    "sg:address":"Hauptstr. 18",
    "sg:city":"Ostrhauderfehn",
    "sg:phone":"+49 4952/6703",
    "sg:postcode":"26842",
    "sg:province":"Niedersachsen",
    "wof:name":"Heyen Verwaltungs Gmbh & Co. Kg",
    "wof:placetype":"venue"
},
  "geometry": {"coordinates":[7.6034379005,53.1379051208],"type":"Point"}
}