{
  "type": "Feature",
  "properties": {
    "iso:country":"DE",
    "sg:address":"Forsterbahnried 9 a",
    "sg:city":"Hilzingen",
    "sg:postcode":"78247",
    "sg:province":"Baden-W\u00fcrttemberg",
    "wof:name":"Gisela Hauch",
    "wof:placetype":"venue"
},
  "geometry": {"coordinates":[8.8002338409,47.7631187439],"type":"Point"}
}