{
  "type": "Feature",
  "properties": {
    "iso:country":"DE",
    "sg:address":"Westermarktstr. 1",
    "sg:city":"Salzwedel",
    "sg:phone":"+49 3901/422421",
    "sg:postcode":"29410",
    "sg:province":"Sachsen-Anhalt",
    "wof:name":"D2 Shop Salzwedel Stefan Kayser",
    "wof:placetype":"venue"
},
  "geometry": {"coordinates":[11.1512136459,52.8495750427],"type":"Point"}
}