{
  "type": "Feature",
  "properties": {
    "iso:country":"DE",
    "sg:address":"Im Kalkofen 40",
    "sg:city":"Fronreute",
    "sg:phone":"+49 7502/2413",
    "sg:postcode":"88273",
    "sg:province":"Baden-W\u00fcrttemberg",
    "wof:name":"Rolf Adis",
    "wof:placetype":"venue"
},
  "geometry": {"coordinates":[9.5865011215,47.8671188354],"type":"Point"}
}