{
  "type": "Feature",
  "properties": {
    "iso:country":"DE",
    "sg:address":"Max-Joseph-Str. 1",
    "sg:city":"Mannheim",
    "sg:phone":"+49 621/333700",
    "sg:postcode":"68167",
    "sg:province":"Baden-W\u00fcrttemberg",
    "wof:name":"Sybille Klein-borchers Krankengymnastin",
    "wof:placetype":"venue"
},
  "geometry": {"coordinates":[8.474357,49.496906],"type":"Point"}
}