{
  "type": "Feature",
  "properties": {
    "iso:country":"DE",
    "sg:address":"Hauptstr. 53-59",
    "sg:city":"Viersen",
    "sg:phone":"+49 2162/13094",
    "sg:postcode":"41747",
    "sg:province":"Nordrhein-Westfalen",
    "wof:name":"Wilhelm Genenger Gmbh & Co. Kg",
    "wof:placetype":"venue"
},
  "geometry": {"coordinates":[6.3889222145,51.2569541931],"type":"Point"}
}