{
  "type": "Feature",
  "properties": {
    "iso:country":"DE",
    "sg:address":"Beverstr. 31",
    "sg:city":"Bochum",
    "sg:phone":"+49 234/238514",
    "sg:postcode":"44894",
    "sg:province":"Nordrhein-Westfalen",
    "wof:name":"L. Pepe",
    "wof:placetype":"venue"
},
  "geometry": {"coordinates":[7.343036,51.491455],"type":"Point"}
}