{
  "type": "Feature",
  "properties": {
    "iso:country":"DE",
    "sg:address":"Hubertusstr. 9",
    "sg:city":"Schwanheim",
    "sg:postcode":"76848",
    "sg:province":"Rheinland-Pfalz",
    "wof:name":"Schuh-seibel Internationale Schuhmoden Und",
    "wof:placetype":"venue"
},
  "geometry": {"coordinates":[7.87697,49.16666],"type":"Point"}
}