{
  "type": "Feature",
  "properties": {
    "iso:country":"DE",
    "sg:address":"S\u00fcdfeldstr. 10-12",
    "sg:city":"Hannover",
    "sg:postcode":"30453",
    "sg:province":"Niedersachsen",
    "wof:name":"Cementa Grundst\u00fccks- Verwaltungs Ohg",
    "wof:placetype":"venue"
},
  "geometry": {"coordinates":[9.683053,52.368694],"type":"Point"}
}