{
  "type": "Feature",
  "properties": {
    "iso:country":"DE",
    "sg:address":"Hemmerder Dorfstr. 66",
    "sg:city":"Unna",
    "sg:phone":"+49 2308/827",
    "sg:postcode":"59427",
    "sg:province":"Nordrhein-Westfalen",
    "wof:name":"H. G. Robert",
    "wof:placetype":"venue"
},
  "geometry": {"coordinates":[7.8116750717,51.547203064],"type":"Point"}
}