{
  "type": "Feature",
  "properties": {
    "iso:country":"DE",
    "sg:address":"Autalstr. 44",
    "sg:city":"Nackenheim",
    "sg:postcode":"55299",
    "sg:province":"Rheinland-Pfalz",
    "wof:name":"Helfende Hand Gmbh",
    "wof:placetype":"venue"
},
  "geometry": {"coordinates":[8.332877,49.917706],"type":"Point"}
}