{
  "type": "Feature",
  "properties": {
    "iso:country":"DE",
    "sg:address":"Klein Ringmar 11",
    "sg:city":"Bassum",
    "sg:postcode":"27211",
    "sg:province":"Niedersachsen",
    "wof:name":"Vbb-baumaschinen- Vermittlungs Gmbh",
    "wof:placetype":"venue"
},
  "geometry": {"coordinates":[8.6576519012,52.8434295654],"type":"Point"}
}