{
  "type": "Feature",
  "properties": {
    "iso:country":"DE",
    "sg:address":"Am Radeland 5",
    "sg:city":"Hamburg",
    "sg:postcode":"21079",
    "sg:province":"Hamburg",
    "wof:name":"Cornehl Transporte Gmbh",
    "wof:placetype":"venue"
},
  "geometry": {"coordinates":[9.9592580795,53.470905304],"type":"Point"}
}