{
  "type": "Feature",
  "properties": {
    "iso:country":"DE",
    "sg:address":"Saalestr. 6 a",
    "sg:city":"Gro\u00dfkorbetha",
    "sg:phone":"+49 34446/20467",
    "sg:postcode":"06688",
    "sg:province":"Sachsen-Anhalt",
    "wof:name":"Alfred G\u00f6lz",
    "wof:placetype":"venue"
},
  "geometry": {"coordinates":[12.030772,51.259624],"type":"Point"}
}