{
  "type": "Feature",
  "properties": {
    "iso:country":"DE",
    "sg:address":"Kirchstr. 1",
    "sg:city":"Weingarten",
    "sg:phone":"+49 7244/2229",
    "sg:postcode":"76356",
    "sg:province":"Baden-W\u00fcrttemberg",
    "wof:name":"Kath. Pfarramt St. Michael",
    "wof:placetype":"venue"
},
  "geometry": {"coordinates":[8.5323610306,49.0515556335],"type":"Point"}
}