{
  "type": "Feature",
  "properties": {
    "iso:country":"DE",
    "sg:address":"Johannisplatz 18",
    "sg:city":"Leipzig",
    "sg:phone":"+49 341/9611959",
    "sg:postcode":"04103",
    "sg:province":"Sachsen",
    "wof:name":"G\u00fcnter Schremmer",
    "wof:placetype":"venue"
},
  "geometry": {"coordinates":[12.3857507706,51.3374061584],"type":"Point"}
}