{
  "type": "Feature",
  "properties": {
    "iso:country":"DE",
    "sg:address":"Coesfelder Stra\u00dfe 7",
    "sg:city":"D\u00fclmen",
    "sg:phone":"+49 2594/1442",
    "sg:postcode":"48249",
    "sg:province":"Nordrhein-Westfalen",
    "wof:name":"Radio Fernsehen",
    "wof:placetype":"venue"
},
  "geometry": {"coordinates":[7.278957,51.830685],"type":"Point"}
}