{
  "type": "Feature",
  "properties": {
    "iso:country":"DE",
    "sg:address":"Beethovenweg 23",
    "sg:city":"D\u00fcren",
    "sg:phone":"+49 2421/505525",
    "sg:postcode":"52349",
    "sg:province":"Nordrhein-Westfalen",
    "wof:name":"Dietrich St\u00f6rling Ingenieur",
    "wof:placetype":"venue"
},
  "geometry": {"coordinates":[6.4963102341,50.7910461426],"type":"Point"}
}