{
  "type": "Feature",
  "properties": {
    "iso:country":"DE",
    "sg:address":"Bachstr. 15",
    "sg:city":"Biesenthal",
    "sg:phone":"+49 3337/3401",
    "sg:postcode":"16359",
    "sg:province":"Brandenburg",
    "wof:name":"G\u00fcnther Lange",
    "wof:placetype":"venue"
},
  "geometry": {"coordinates":[13.66374,52.754429],"type":"Point"}
}