{
  "type": "Feature",
  "properties": {
    "iso:country":"DE",
    "sg:address":"Alexanderstr. 148",
    "sg:city":"Stuttgart",
    "sg:phone":"+49 711/6401853",
    "sg:postcode":"70180",
    "sg:province":"Baden-W\u00fcrttemberg",
    "wof:name":"Dr. Theo Grasser Werbe- Und Architektur-",
    "wof:placetype":"venue"
},
  "geometry": {"coordinates":[9.1793861389,48.7669677734],"type":"Point"}
}