{
  "type": "Feature",
  "properties": {
    "iso:country":"DE",
    "sg:address":"L\u00fctticher Str. 56",
    "sg:city":"K\u00f6ln",
    "sg:phone":"+49 221/2834777",
    "sg:postcode":"50674",
    "sg:province":"Nordrhein-Westfalen",
    "wof:name":"Kicks - K\u00f6lner Institut F\u00fcr Computergest\u00fctzte Kommuni-",
    "wof:placetype":"venue"
},
  "geometry": {"coordinates":[6.9342150688,50.9377326965],"type":"Point"}
}