{
  "type": "Feature",
  "properties": {
    "iso:country":"DE",
    "sg:address":"Dr.-Ruben-Str.",
    "sg:city":"H\u00fcckelhoven",
    "sg:phone":"+49 2433/8370",
    "sg:postcode":"41836",
    "sg:province":"Nordrhein-Westfalen",
    "wof:name":"Hotel Europa-haus",
    "wof:placetype":"venue"
},
  "geometry": {"coordinates":[6.2263059616,51.0557022095],"type":"Point"}
}