{
  "type": "Feature",
  "properties": {
    "iso:country":"DE",
    "sg:address":"Landauer Str. 90",
    "sg:city":"Zweibr\u00fccken",
    "sg:phone":"+49 6332/43789",
    "sg:postcode":"66482",
    "sg:province":"Rheinland-Pfalz",
    "wof:name":"Mohilo",
    "wof:placetype":"venue"
},
  "geometry": {"coordinates":[7.3756690025,49.2510910034],"type":"Point"}
}