{
  "type": "Feature",
  "properties": {
    "iso:country":"DE",
    "sg:address":"Hebborner Str. 92",
    "sg:city":"Bergisch Gladbach",
    "sg:phone":"+49 2202/59019",
    "sg:postcode":"51467",
    "sg:province":"Nordrhein-Westfalen",
    "wof:name":"J\u00fcrgen Willems Ingenieur",
    "wof:placetype":"venue"
},
  "geometry": {"coordinates":[7.1221718788,51.0046081543],"type":"Point"}
}