{
  "type": "Feature",
  "properties": {
    "iso:country":"DE",
    "sg:address":"Marktplatz 5",
    "sg:city":"Waging",
    "sg:phone":"+49 8681/278",
    "sg:postcode":"83329",
    "sg:province":"Bayern",
    "wof:name":"Strauss",
    "wof:placetype":"venue"
},
  "geometry": {"coordinates":[12.7343034744,47.9332618713],"type":"Point"}
}