{
  "type": "Feature",
  "properties": {
    "iso:country":"DE",
    "sg:address":"Anton-Ulrich-Str. 7",
    "sg:city":"Meiningen",
    "sg:phone":"+49 3693/3549",
    "sg:postcode":"98617",
    "sg:province":"Th\u00fcringen",
    "wof:name":"R. Knoth",
    "wof:placetype":"venue"
},
  "geometry": {"coordinates":[10.4148693085,50.5669288635],"type":"Point"}
}