{
  "type": "Feature",
  "properties": {
    "iso:country":"DE",
    "sg:address":"Wegmanns Hof 18",
    "sg:city":"Bochum",
    "sg:phone":"+49 2327/70968",
    "sg:postcode":"44869",
    "sg:province":"Nordrhein-Westfalen",
    "wof:name":"B. Und E. Eiter",
    "wof:placetype":"venue"
},
  "geometry": {"coordinates":[7.173955,51.456047],"type":"Point"}
}