{
  "type": "Feature",
  "properties": {
    "iso:country":"DE",
    "sg:address":"Havelberger Str. 76",
    "sg:city":"Pritzwalk",
    "sg:phone":"+49 3395/302915",
    "sg:postcode":"16928",
    "sg:province":"Brandenburg",
    "wof:name":"Capitol City-snack",
    "wof:placetype":"venue"
},
  "geometry": {"coordinates":[12.1747503281,53.1475563049],"type":"Point"}
}