{
  "type": "Feature",
  "properties": {
    "iso:country":"DE",
    "sg:address":"St\u00fchleinsh\u00f6hstr. 7",
    "sg:city":"Lauf",
    "sg:phone":"+49 9123/985891",
    "sg:postcode":"91207",
    "sg:province":"Bayern",
    "wof:name":"Nijhuis Heiztechnik Und Service Gmbh",
    "wof:placetype":"venue"
},
  "geometry": {"coordinates":[11.2769899368,49.5064506531],"type":"Point"}
}