{
  "type": "Feature",
  "properties": {
    "iso:country":"DE",
    "sg:address":"Vogteiweg 6",
    "sg:city":"Amelinghausen",
    "sg:phone":"+49 4132/693",
    "sg:postcode":"21385",
    "sg:province":"Niedersachsen",
    "wof:name":"Klaus Stelter Immobilienmakler",
    "wof:placetype":"venue"
},
  "geometry": {"coordinates":[10.2118396759,53.1261329651],"type":"Point"}
}