{
  "type": "Feature",
  "properties": {
    "iso:country":"DE",
    "sg:address":"Glockenstr. 8",
    "sg:city":"Masburg",
    "sg:phone":"+49 2653/910186",
    "sg:postcode":"56761",
    "sg:province":"Rheinland-Pfalz",
    "wof:name":"Ernst Henn",
    "wof:placetype":"venue"
},
  "geometry": {"coordinates":[7.1136240959,50.2415733337],"type":"Point"}
}