{
  "type": "Feature",
  "properties": {
    "iso:country":"DE",
    "sg:address":"Seitenstr. 1",
    "sg:city":"Baalsdorf",
    "sg:phone":"+49 341/6510257",
    "sg:postcode":"04457",
    "wof:name":"Johannes H\u00e4rting",
    "wof:placetype":"venue"
},
  "geometry": {"coordinates":[12.44966,51.329021],"type":"Point"}
}