{
  "type": "Feature",
  "properties": {
    "iso:country":"DE",
    "sg:address":"Otto-Hahn-Str. 15",
    "sg:city":"M\u00fclheim",
    "sg:postcode":"45473",
    "sg:province":"Nordrhein-Westfalen",
    "wof:name":"Erguinomic Inhaber Marcus Ridder E. K.",
    "wof:placetype":"venue"
},
  "geometry": {"coordinates":[6.914611,51.442623],"type":"Point"}
}