{
  "type": "Feature",
  "properties": {
    "iso:country":"DE",
    "sg:address":"Bottenbacher Weg",
    "sg:city":"Kleinsteinhausen",
    "sg:phone":"+49 6339/255",
    "sg:postcode":"66484",
    "sg:province":"Rheinland-Pfalz",
    "wof:name":"A. Lehner",
    "wof:placetype":"venue"
},
  "geometry": {"coordinates":[7.4706101418,49.2000312805],"type":"Point"}
}