{
  "type": "Feature",
  "properties": {
    "iso:country":"DE",
    "sg:address":"Ernst-Heinkel-Str. 12",
    "sg:city":"Augsburg",
    "sg:phone":"+49 821/596830",
    "sg:postcode":"86159",
    "sg:province":"Bayern",
    "wof:name":"Norma Lebensmittelfilialbetrieb",
    "wof:placetype":"venue"
},
  "geometry": {"coordinates":[10.905377388,48.3280143738],"type":"Point"}
}