{
  "type": "Feature",
  "properties": {
    "iso:country":"DE",
    "sg:address":"Hauptstr. 73",
    "sg:city":"Fellbach",
    "sg:phone":"+49 711/519352",
    "sg:postcode":"70736",
    "sg:province":"Baden-W\u00fcrttemberg",
    "wof:name":"H. Kleider",
    "wof:placetype":"venue"
},
  "geometry": {"coordinates":[9.2626848221,48.8389434814],"type":"Point"}
}