{
  "type": "Feature",
  "properties": {
    "iso:country":"DE",
    "sg:address":"Schulstr. 5",
    "sg:city":"Gauting",
    "sg:phone":"+49 89/8508825",
    "sg:postcode":"82131",
    "sg:province":"Bayern",
    "wof:name":"D. Kunst",
    "wof:placetype":"venue"
},
  "geometry": {"coordinates":[11.378439,48.065952],"type":"Point"}
}