{
  "type": "Feature",
  "properties": {
    "iso:country":"DE",
    "sg:address":"Hauptstr. 46",
    "sg:city":"Bleicherode",
    "sg:phone":"+49 36338/60252",
    "sg:postcode":"99752",
    "sg:province":"Th\u00fcringen",
    "wof:name":"Evangelisches Hospital Maria Im Elende",
    "wof:placetype":"venue"
},
  "geometry": {"coordinates":[10.570048,51.439102],"type":"Point"}
}