{
  "type": "Feature",
  "properties": {
    "iso:country":"DE",
    "sg:address":"Ahornstr. 16",
    "sg:city":"Berlin",
    "sg:postcode":"14163",
    "sg:province":"Berlin",
    "wof:name":"Thk-mahlow Wohnungsbauges. Mbh",
    "wof:placetype":"venue"
},
  "geometry": {"coordinates":[13.252719,52.432987],"type":"Point"}
}