{
  "type": "Feature",
  "properties": {
    "iso:country":"DE",
    "sg:address":"Stadtplatz 15",
    "sg:city":"Abensberg",
    "sg:phone":"+49 9443/6823",
    "sg:postcode":"93326",
    "sg:province":"Bayern",
    "wof:name":"D\u00f6rner Chic",
    "wof:placetype":"venue"
},
  "geometry": {"coordinates":[11.8460149765,48.8155822754],"type":"Point"}
}