{
  "type": "Feature",
  "properties": {
    "iso:country":"DE",
    "sg:address":"Hauptstr. 37",
    "sg:city":"Eggenstein-Leopoldshafen",
    "sg:phone":"+49 721/978460",
    "sg:postcode":"76344",
    "sg:province":"Baden-W\u00fcrttemberg",
    "wof:name":"Datamann Edv-service Herrmann & Partner Gmbh",
    "wof:placetype":"venue"
},
  "geometry": {"coordinates":[8.388915062,49.0788154602],"type":"Point"}
}