{
  "type": "Feature",
  "properties": {
    "iso:country":"DE",
    "sg:address":"Frauenstr. 61",
    "sg:city":"Ulm",
    "sg:phone":"+49 731/65400",
    "sg:postcode":"89073",
    "sg:province":"Baden-W\u00fcrttemberg",
    "wof:name":"Lichtburg-filmtheater",
    "wof:placetype":"venue"
},
  "geometry": {"coordinates":[9.996591,48.401562],"type":"Point"}
}