{
  "type": "Feature",
  "properties": {
    "iso:country":"DE",
    "sg:address":"Heidenkampsweg 76 b",
    "sg:city":"Hamburg",
    "sg:phone":"+49 40/2351290",
    "sg:postcode":"20097",
    "sg:province":"Hamburg",
    "wof:name":"L\u00fctcke & Wulff",
    "wof:placetype":"venue"
},
  "geometry": {"coordinates":[10.0289945602,53.5467720032],"type":"Point"}
}