{
  "type": "Feature",
  "properties": {
    "iso:country":"DE",
    "sg:address":"Dorfstr. 15",
    "sg:city":"Gaienhofen",
    "sg:phone":"+49 7735/3280",
    "sg:postcode":"78343",
    "sg:province":"Baden-W\u00fcrttemberg",
    "wof:name":"August Gri\u00df",
    "wof:placetype":"venue"
},
  "geometry": {"coordinates":[8.969216,47.673756],"type":"Point"}
}