{
  "type": "Feature",
  "properties": {
    "iso:country":"DE",
    "sg:address":"Raamshorst 8",
    "sg:city":"Bad Essen",
    "sg:phone":"+49 5745/816",
    "sg:postcode":"49152",
    "sg:province":"Niedersachsen",
    "wof:name":"Heinrich Heitmeyer",
    "wof:placetype":"venue"
},
  "geometry": {"coordinates":[8.408133,52.356537],"type":"Point"}
}