{
  "type": "Feature",
  "properties": {
    "iso:country":"DE",
    "sg:address":"Oberdorfstr. 5",
    "sg:city":"Katlenburg-Lindau",
    "sg:phone":"+49 5552/1373",
    "sg:postcode":"37191",
    "sg:province":"Niedersachsen",
    "wof:name":"Wilhelm Haupt",
    "wof:placetype":"venue"
},
  "geometry": {"coordinates":[10.094603,51.664749],"type":"Point"}
}