{
  "type": "Feature",
  "properties": {
    "iso:country":"DE",
    "sg:address":"Pf\u00e4nnerstr. 30b",
    "sg:city":"Sch\u00f6nebeck",
    "sg:phone":"+49 3928/67503",
    "sg:postcode":"39218",
    "sg:province":"Sachsen-Anhalt",
    "wof:name":"Sylvia",
    "wof:placetype":"venue"
},
  "geometry": {"coordinates":[11.721255,52.002953],"type":"Point"}
}