{
  "type": "Feature",
  "properties": {
    "iso:country":"DE",
    "sg:address":"In den Birken 99",
    "sg:city":"Hinterweidenthal",
    "sg:phone":"+49 6396/459",
    "sg:postcode":"66999",
    "sg:province":"Rheinland-Pfalz",
    "wof:name":"G\u00e4stehaus Ursula May",
    "wof:placetype":"venue"
},
  "geometry": {"coordinates":[7.74395895,49.1857566833],"type":"Point"}
}