{
  "type": "Feature",
  "properties": {
    "iso:country":"DE",
    "sg:address":"Jakob-Huber-Str. 9",
    "sg:city":"Weiler-Simmerberg",
    "sg:phone":"+49 8387/2510",
    "sg:postcode":"88171",
    "sg:province":"Bayern",
    "wof:name":"Thauros Verlag Gmbh",
    "wof:placetype":"venue"
},
  "geometry": {"coordinates":[9.9169425964,47.5795402527],"type":"Point"}
}