{
  "type": "Feature",
  "properties": {
    "iso:country":"DE",
    "sg:address":"Dorfstr. 71",
    "sg:city":"Hohberg",
    "sg:phone":"+49 7808/2311",
    "sg:postcode":"77749",
    "sg:province":"Baden-W\u00fcrttemberg",
    "wof:name":"H. Erhardt",
    "wof:placetype":"venue"
},
  "geometry": {"coordinates":[7.912501812,48.4226493835],"type":"Point"}
}