{
  "type": "Feature",
  "properties": {
    "iso:country":"DE",
    "sg:address":"Hans-B\u00f6ckler-Platz 10",
    "sg:city":"M\u00fclheim",
    "sg:phone":"+49 208/32096",
    "sg:postcode":"45468",
    "sg:province":"Nordrhein-Westfalen",
    "wof:name":"F. L\u00fccker",
    "wof:placetype":"venue"
},
  "geometry": {"coordinates":[6.887174,51.428818],"type":"Point"}
}