{
  "type": "Feature",
  "properties": {
    "iso:country":"DE",
    "sg:address":"Welserstra\u00dfe 1",
    "sg:city":"Ansbach",
    "sg:phone":"+49 981",
    "sg:postcode":"91522",
    "sg:province":"Bayern",
    "wof:name":"Ansbacher Frauenarztpraxis Dr. Siewert-neudeck & Dr. Schwarz",
    "wof:placetype":"venue"
},
  "geometry": {"coordinates":[10.573371,49.295811],"type":"Point"}
}