{
  "type": "Feature",
  "properties": {
    "iso:country":"DE",
    "sg:address":"Fischerstr. 4",
    "sg:city":"Celle",
    "sg:phone":"+49 5141/82091",
    "sg:postcode":"29227",
    "sg:province":"Niedersachsen",
    "wof:name":"H. Kuggel Elektroinstallation",
    "wof:placetype":"venue"
},
  "geometry": {"coordinates":[10.083891,52.608395],"type":"Point"}
}