{
  "type": "Feature",
  "properties": {
    "iso:country":"DE",
    "sg:address":"Zeiss-Str 34",
    "sg:city":"Ratekau",
    "sg:phone":"+49 451/41149",
    "sg:postcode":"23626",
    "sg:province":"Schleswig-Holstein",
    "wof:name":"Georg Janzen Schornsteinbau Gmbh",
    "wof:placetype":"venue"
},
  "geometry": {"coordinates":[10.72242,53.955582],"type":"Point"}
}