{
  "type": "Feature",
  "properties": {
    "iso:country":"DE",
    "sg:address":"M\u00fcnnichstr. 62",
    "sg:city":"Oldenburg",
    "sg:phone":"+49 441/43808",
    "sg:postcode":"26133",
    "sg:province":"Niedersachsen",
    "wof:name":"Dr. Med. Wolf-r\u00fcdiger D\u00e4hn",
    "wof:placetype":"venue"
},
  "geometry": {"coordinates":[8.2133607864,53.1134033203],"type":"Point"}
}