{
  "type": "Feature",
  "properties": {
    "iso:country":"DE",
    "sg:address":"Krefelder Str. 5",
    "sg:city":"Erkelenz",
    "sg:phone":"+49 2431/80540",
    "sg:postcode":"41812",
    "sg:province":"Nordrhein-Westfalen",
    "wof:name":"Cityb\u00fcro Busniness Services E. K.",
    "wof:placetype":"venue"
},
  "geometry": {"coordinates":[6.3134198189,51.0835113525],"type":"Point"}
}