{
  "type": "Feature",
  "properties": {
    "iso:country":"DE",
    "sg:address":"Hauptstr. 16",
    "sg:city":"Saarbr\u00fccken",
    "sg:phone":"+49 6893/1455",
    "sg:postcode":"66131",
    "sg:province":"Saarland",
    "wof:name":"V. Jost",
    "wof:placetype":"venue"
},
  "geometry": {"coordinates":[7.1093320847,49.2027130127],"type":"Point"}
}