{
  "type": "Feature",
  "properties": {
    "iso:country":"DE",
    "sg:address":"Talstr. 1",
    "sg:city":"Waldbrunn",
    "sg:phone":"+49 6274/92050",
    "sg:postcode":"69429",
    "sg:province":"Baden-W\u00fcrttemberg",
    "wof:name":"Ipa Industrie-proze\u00df- Automation Gmbh",
    "wof:placetype":"venue"
},
  "geometry": {"coordinates":[9.0780897141,49.4353599548],"type":"Point"}
}