{
  "type": "Feature",
  "properties": {
    "iso:country":"DE",
    "sg:address":"Daimlerstr. 8",
    "sg:city":"Ettlingen",
    "sg:phone":"+49 7243/536407",
    "sg:postcode":"76275",
    "sg:province":"Baden-W\u00fcrttemberg",
    "wof:name":"Courier Systeme Ak Gmbh",
    "wof:placetype":"venue"
},
  "geometry": {"coordinates":[8.39059,48.945801],"type":"Point"}
}