{
  "type": "Feature",
  "properties": {
    "iso:country":"DE",
    "sg:address":"H\u00f6llgasse 6",
    "sg:city":"Landensberg",
    "sg:phone":"+49 8222/1844",
    "sg:postcode":"89361",
    "sg:province":"Bayern",
    "wof:name":"Anton Demmelmaier",
    "wof:placetype":"venue"
},
  "geometry": {"coordinates":[10.504928,48.431541],"type":"Point"}
}