{
  "type": "Feature",
  "properties": {
    "iso:country":"DE",
    "sg:address":"Hauptstr. 14",
    "sg:city":"Aurachtal",
    "sg:phone":"+49 9132/9641",
    "sg:postcode":"91086",
    "sg:province":"Bayern",
    "wof:name":"Grosch Innenausbau Gmbh",
    "wof:placetype":"venue"
},
  "geometry": {"coordinates":[10.840193,49.578442],"type":"Point"}
}