{
  "type": "Feature",
  "properties": {
    "iso:country":"DE",
    "sg:address":"Sprengelstr. 33",
    "sg:city":"Burgdorf",
    "sg:phone":"+49 5136/89950",
    "sg:postcode":"31303",
    "sg:province":"Niedersachsen",
    "wof:name":"Arthur Schaper",
    "wof:placetype":"venue"
},
  "geometry": {"coordinates":[9.973244,52.46756],"type":"Point"}
}