{
  "type": "Feature",
  "properties": {
    "iso:country":"DE",
    "sg:address":"Raiffeisenstr. 9",
    "sg:city":"Braunschweig",
    "sg:phone":"+49 5300/6222",
    "sg:postcode":"38122",
    "sg:province":"Niedersachsen",
    "wof:name":"Pflegeeltern-verein Braunschweig E. V.",
    "wof:placetype":"venue"
},
  "geometry": {"coordinates":[10.4656524658,52.2082328796],"type":"Point"}
}