{
  "type": "Feature",
  "properties": {
    "iso:country":"DE",
    "sg:address":"Bruchgarten 2",
    "sg:city":"Paderborn",
    "sg:phone":"+49 5251/91820",
    "sg:postcode":"33106",
    "sg:province":"Nordrhein-Westfalen",
    "wof:name":"Karl Scheifers Gmbh",
    "wof:placetype":"venue"
},
  "geometry": {"coordinates":[8.6919698715,51.6904983521],"type":"Point"}
}