{
  "type": "Feature",
  "properties": {
    "iso:country":"DE",
    "sg:address":"Gro\u00dfe Binsachstr. 54",
    "sg:city":"M\u00f6ckm\u00fchl",
    "sg:phone":"+49 6298/1366",
    "sg:postcode":"74219",
    "sg:province":"Baden-W\u00fcrttemberg",
    "wof:name":"Ev. Pfarramt I",
    "wof:placetype":"venue"
},
  "geometry": {"coordinates":[9.3529968262,49.3215713501],"type":"Point"}
}