{
  "type": "Feature",
  "properties": {
    "iso:country":"DE",
    "sg:address":"Im Taubental 21",
    "sg:city":"Neuss",
    "sg:phone":"+49 2131/359110",
    "sg:postcode":"41468",
    "sg:province":"Nordrhein-Westfalen",
    "wof:name":"Ortmann Druckgie\u00dftechnik Gmbh",
    "wof:placetype":"venue"
},
  "geometry": {"coordinates":[6.750488,51.169224],"type":"Point"}
}