{
  "type": "Feature",
  "properties": {
    "iso:country":"DE",
    "sg:address":"Akazienstr. 2",
    "sg:city":"Reken",
    "sg:postcode":"48734",
    "sg:province":"Nordrhein-Westfalen",
    "wof:name":"Johannes Seitz Werbeagentur",
    "wof:placetype":"venue"
},
  "geometry": {"coordinates":[7.0397639275,51.8344955444],"type":"Point"}
}