{
  "type": "Feature",
  "properties": {
    "iso:country":"DE",
    "sg:address":"Mooslohstr. 93",
    "sg:city":"Weiden",
    "sg:phone":"+49 961/21366",
    "sg:postcode":"92637",
    "sg:province":"Bayern",
    "wof:name":"Condi Markt",
    "wof:placetype":"venue"
},
  "geometry": {"coordinates":[12.1510677338,49.6864051819],"type":"Point"}
}