{
  "type": "Feature",
  "properties": {
    "iso:country":"DE",
    "sg:address":"Lindauer Str. 88",
    "sg:city":"Langenargen",
    "sg:phone":"+49 7543/1646",
    "sg:postcode":"88085",
    "sg:province":"Baden-W\u00fcrttemberg",
    "wof:name":"B. Niechoj Ingenieur",
    "wof:placetype":"venue"
},
  "geometry": {"coordinates":[9.5555334091,47.5971794128],"type":"Point"}
}