{
  "type": "Feature",
  "properties": {
    "iso:country":"DE",
    "sg:address":"Hauptkanal Links 64",
    "sg:city":"Papenburg",
    "sg:phone":"+49 4961/4527",
    "sg:postcode":"26871",
    "sg:province":"Niedersachsen",
    "wof:name":"Lbs Immobilien Gmbh",
    "wof:placetype":"venue"
},
  "geometry": {"coordinates":[7.3933949471,53.0790710449],"type":"Point"}
}