{
  "type": "Feature",
  "properties": {
    "iso:country":"DE",
    "sg:address":"Schledehausener Str. 7",
    "sg:city":"Bissendorf",
    "sg:phone":"+49 5402/690659",
    "sg:postcode":"49143",
    "sg:province":"Niedersachsen",
    "wof:name":"Restaurant Mediterran",
    "wof:placetype":"venue"
},
  "geometry": {"coordinates":[8.1915216446,52.2773742676],"type":"Point"}
}