{
  "type": "Feature",
  "properties": {
    "iso:country":"DE",
    "sg:address":"Kasinoplatz 4",
    "sg:city":"Oldenburg",
    "sg:phone":"+49 441/26821",
    "sg:postcode":"26122",
    "sg:province":"Niedersachsen",
    "wof:name":"F. A. Eckhardt",
    "wof:placetype":"venue"
},
  "geometry": {"coordinates":[8.214050293,53.138256073],"type":"Point"}
}