{
  "type": "Feature",
  "properties": {
    "iso:country":"DE",
    "sg:address":"Breite Str. 12",
    "sg:city":"S\u00f6hlde",
    "sg:phone":"+49 5123/8603",
    "sg:postcode":"31185",
    "sg:province":"Niedersachsen",
    "wof:name":"Robert Bartels",
    "wof:placetype":"venue"
},
  "geometry": {"coordinates":[10.173052,52.189037],"type":"Point"}
}