{
  "type": "Feature",
  "properties": {
    "iso:country":"DE",
    "sg:address":"Taunusstr. 3",
    "sg:city":"Eltville",
    "sg:phone":"+49 6123/61769",
    "sg:postcode":"65343",
    "sg:province":"Hessen",
    "wof:name":"Bistro Kiwi",
    "wof:placetype":"venue"
},
  "geometry": {"coordinates":[8.1201820374,50.0279121399],"type":"Point"}
}