{
  "type": "Feature",
  "properties": {
    "iso:country":"DE",
    "sg:address":"Untere Hauptstr. 10",
    "sg:city":"Freising",
    "sg:phone":"+49 8161/532897",
    "sg:postcode":"85354",
    "sg:province":"Bayern",
    "wof:name":"Ihr Platz Drogeriemarkt",
    "wof:placetype":"venue"
},
  "geometry": {"coordinates":[11.745164,48.400997],"type":"Point"}
}