{
  "type": "Feature",
  "properties": {
    "iso:country":"DE",
    "sg:address":"Damm 2",
    "sg:city":"Oldenburg",
    "sg:phone":"+49 441/21011",
    "sg:postcode":"26135",
    "sg:province":"Niedersachsen",
    "wof:name":"Bfg Bank Ag",
    "wof:placetype":"venue"
},
  "geometry": {"coordinates":[8.217041,53.136208],"type":"Point"}
}