{
  "type": "Feature",
  "properties": {
    "iso:country":"DE",
    "sg:address":"Recker\u00f6der Str. 6",
    "sg:city":"Kirchheim",
    "sg:phone":"+49 6625/7101",
    "sg:postcode":"36275",
    "sg:province":"Hessen",
    "wof:name":"Karl Eckhardt Kg",
    "wof:placetype":"venue"
},
  "geometry": {"coordinates":[9.595833,50.861477],"type":"Point"}
}