{
  "type": "Feature",
  "properties": {
    "iso:country":"DE",
    "sg:address":"M\u00fchlenweg 3",
    "sg:city":"Konstanz",
    "sg:phone":"+49 7531/77109",
    "sg:postcode":"78467",
    "sg:province":"Baden-W\u00fcrttemberg",
    "wof:name":"Johann Bauer",
    "wof:placetype":"venue"
},
  "geometry": {"coordinates":[9.1449985504,47.6891517639],"type":"Point"}
}