{
  "type": "Feature",
  "properties": {
    "iso:country":"DE",
    "sg:address":"Wiesenweg 7",
    "sg:city":"Linsengericht",
    "sg:phone":"+49 6051/71971",
    "sg:postcode":"63589",
    "sg:province":"Hessen",
    "wof:name":"Lbv Gmbh",
    "wof:placetype":"venue"
},
  "geometry": {"coordinates":[9.2351016998,50.180606842],"type":"Point"}
}