{
  "type": "Feature",
  "properties": {
    "iso:country":"DE",
    "sg:address":"Borkumer Str. 19",
    "sg:city":"Berlin",
    "sg:phone":"+49 30/3313016",
    "sg:postcode":"13581",
    "sg:province":"Berlin",
    "wof:name":"Hans-werner Bergmann",
    "wof:placetype":"venue"
},
  "geometry": {"coordinates":[13.196665,52.53207],"type":"Point"}
}