{
  "type": "Feature",
  "properties": {
    "iso:country":"DE",
    "sg:address":"Fuchsberg 10",
    "sg:city":"Hamb\u00fchren",
    "sg:phone":"+49 5084/6288",
    "sg:postcode":"29313",
    "sg:province":"Niedersachsen",
    "wof:name":"Horst Baumgart Kunstmaler",
    "wof:placetype":"venue"
},
  "geometry": {"coordinates":[9.941573,52.637642],"type":"Point"}
}