{
  "type": "Feature",
  "properties": {
    "iso:country":"DE",
    "sg:address":"Ulmer Str. 16",
    "sg:city":"N\u00f6rdlingen",
    "sg:phone":"+49 9081/22670",
    "sg:postcode":"86720",
    "sg:province":"Bayern",
    "wof:name":"Nvs Verlag-service Gmbh",
    "wof:placetype":"venue"
},
  "geometry": {"coordinates":[10.483332634,48.8463935852],"type":"Point"}
}