{
  "type": "Feature",
  "properties": {
    "iso:country":"DE",
    "sg:address":"Hasselbrocker Str. 50",
    "sg:city":"Walchum",
    "sg:phone":"+49 5939/405",
    "sg:postcode":"26907",
    "sg:province":"Niedersachsen",
    "wof:name":"Wilhelm Osteresch",
    "wof:placetype":"venue"
},
  "geometry": {"coordinates":[7.230984,52.926983],"type":"Point"}
}