{
  "type": "Feature",
  "properties": {
    "iso:country":"DE",
    "sg:address":"Gartenstr. 63",
    "sg:city":"Kirchheim",
    "sg:phone":"+49 7021/55852",
    "sg:postcode":"73230",
    "sg:province":"Baden-W\u00fcrttemberg",
    "wof:name":"Ernst Friedrich Heuer Gmbh",
    "wof:placetype":"venue"
},
  "geometry": {"coordinates":[9.479156,48.612629],"type":"Point"}
}