{
  "type": "Feature",
  "properties": {
    "iso:country":"DE",
    "sg:address":"Ahornweg 4",
    "sg:city":"Sand",
    "sg:postcode":"97522",
    "sg:province":"Bayern",
    "wof:name":"Linea Nova Marketinggesellschaft F\u00fcr",
    "wof:placetype":"venue"
},
  "geometry": {"coordinates":[8.0135183334,53.4951667786],"type":"Point"}
}