{
  "type": "Feature",
  "properties": {
    "iso:country":"DE",
    "sg:address":"Otto-Follmann-Str. 13",
    "sg:city":"Landscheid",
    "sg:phone":"+49 6575/4750",
    "sg:postcode":"54526",
    "sg:province":"Rheinland-Pfalz",
    "wof:name":"Alfred Bayer",
    "wof:placetype":"venue"
},
  "geometry": {"coordinates":[6.776681,49.98613],"type":"Point"}
}