{
  "type": "Feature",
  "properties": {
    "iso:country":"DE",
    "sg:address":"Bienenbergweg 4",
    "sg:city":"Oestrich-Winkel",
    "sg:phone":"+49 6723/99600",
    "sg:postcode":"65375",
    "sg:province":"Hessen",
    "wof:name":"Werner Roer Steuerberater",
    "wof:placetype":"venue"
},
  "geometry": {"coordinates":[8.0106906891,50.0037574768],"type":"Point"}
}