{
  "type": "Feature",
  "properties": {
    "iso:country":"DE",
    "sg:address":"Fliederweg 44",
    "sg:city":"Bad Frankenhausen",
    "sg:phone":"+49 34671/62152",
    "sg:postcode":"06567",
    "sg:province":"Th\u00fcringen",
    "wof:name":"Peter Hau\u00dfingen Patentanwalt",
    "wof:placetype":"venue"
},
  "geometry": {"coordinates":[11.1153745651,51.3567123413],"type":"Point"}
}