{
  "type": "Feature",
  "properties": {
    "iso:country":"DE",
    "sg:address":"Bahnhofstr. 10",
    "sg:city":"Kirchberg",
    "sg:phone":"+49 6763/960127",
    "sg:postcode":"55481",
    "sg:province":"Rheinland-Pfalz",
    "wof:name":"Hans Werner Lamby",
    "wof:placetype":"venue"
},
  "geometry": {"coordinates":[12.524059,50.62318],"type":"Point"}
}