{
  "type": "Feature",
  "properties": {
    "iso:country":"DE",
    "sg:address":"Kapellenweg 4",
    "sg:city":"Eschweiler",
    "sg:phone":"+49 2403/23118",
    "sg:postcode":"52249",
    "sg:province":"Nordrhein-Westfalen",
    "wof:name":"Martin Esser",
    "wof:placetype":"venue"
},
  "geometry": {"coordinates":[6.295412,50.789726],"type":"Point"}
}