{
  "type": "Feature",
  "properties": {
    "iso:country":"DE",
    "sg:address":"Siedlungsring 42",
    "sg:city":"Manching",
    "sg:phone":"+49 8459/2204",
    "sg:postcode":"85077",
    "sg:province":"Bayern",
    "wof:name":"R. Scheitler",
    "wof:placetype":"venue"
},
  "geometry": {"coordinates":[11.496882,48.711536],"type":"Point"}
}