{
  "type": "Feature",
  "properties": {
    "iso:country":"DE",
    "sg:address":"Hauptstr. 25",
    "sg:city":"Eislingen",
    "sg:phone":"+49 7161/984140",
    "sg:postcode":"73054",
    "sg:province":"Baden-W\u00fcrttemberg",
    "wof:name":"Schloss-apotheke Karin Kaufmann E. K.",
    "wof:placetype":"venue"
},
  "geometry": {"coordinates":[9.70647,48.697651],"type":"Point"}
}