{
  "type": "Feature",
  "properties": {
    "iso:country":"DE",
    "sg:address":"Lange Str. 31",
    "sg:city":"Zschopau",
    "sg:phone":"+49 3725/22368",
    "sg:postcode":"09405",
    "sg:province":"Sachsen",
    "wof:name":"Peter M\u00fcller",
    "wof:placetype":"venue"
},
  "geometry": {"coordinates":[13.06984,50.748512],"type":"Point"}
}