{
  "type": "Feature",
  "properties": {
    "iso:country":"DE",
    "sg:address":"Olewiger Str. 125",
    "sg:city":"Trier",
    "sg:phone":"+49 651/34954",
    "sg:postcode":"54295",
    "sg:province":"Rheinland-Pfalz",
    "wof:name":"Les Valine Masseur",
    "wof:placetype":"venue"
},
  "geometry": {"coordinates":[6.658826,49.743156],"type":"Point"}
}