{
  "type": "Feature",
  "properties": {
    "iso:country":"DE",
    "sg:address":"Cauerstr. 12",
    "sg:city":"Dresden",
    "sg:phone":"+49 351/4714945",
    "sg:postcode":"01217",
    "sg:province":"Sachsen",
    "wof:name":"Dr. Klaus Methner",
    "wof:placetype":"venue"
},
  "geometry": {"coordinates":[13.7507762909,51.0248908997],"type":"Point"}
}