{
  "type": "Feature",
  "properties": {
    "iso:country":"DE",
    "sg:address":"Louise-Schroeder-Str. 6",
    "sg:city":"Bremerhaven",
    "sg:phone":"+49 471/63312",
    "sg:postcode":"27578",
    "sg:province":"Bremen",
    "wof:name":"Hans Graudenz Ingenieur",
    "wof:placetype":"venue"
},
  "geometry": {"coordinates":[8.6192216873,53.5886077881],"type":"Point"}
}