{
  "type": "Feature",
  "properties": {
    "iso:country":"DE",
    "sg:address":"Hauptstr. 34",
    "sg:city":"Luckau",
    "sg:phone":"+49 3544/14951",
    "sg:postcode":"15926",
    "sg:province":"Brandenburg",
    "wof:name":"Petra Maeter",
    "wof:placetype":"venue"
},
  "geometry": {"coordinates":[13.71117,51.852428],"type":"Point"}
}