{
  "type": "Feature",
  "properties": {
    "iso:country":"DE",
    "sg:address":"Goetheplatz 5",
    "sg:city":"Frankfurt",
    "sg:postcode":"60313",
    "sg:province":"Hessen",
    "wof:name":"Envotech Untertagedeponie Gmbh",
    "wof:placetype":"venue"
},
  "geometry": {"coordinates":[8.675975,50.113052],"type":"Point"}
}