{
  "type": "Feature",
  "properties": {
    "iso:country":"DE",
    "sg:address":"Kollmer Str. 18",
    "sg:city":"Niesky",
    "sg:phone":"+49 3588/252524",
    "sg:postcode":"02906",
    "sg:province":"Sachsen",
    "wof:name":"Italienisches Restaurant Bella Italia",
    "wof:placetype":"venue"
},
  "geometry": {"coordinates":[14.8175849915,51.2867584229],"type":"Point"}
}