{
  "type": "Feature",
  "properties": {
    "iso:country":"DE",
    "sg:address":"M\u00fcnchener Str. 9",
    "sg:city":"Freilassing",
    "sg:phone":"+49 8654/9928",
    "sg:postcode":"83395",
    "sg:province":"Bayern",
    "wof:name":"Optik Hartmann Gmbh Augenoptik",
    "wof:placetype":"venue"
},
  "geometry": {"coordinates":[12.9800691605,47.8416099548],"type":"Point"}
}