{
  "type": "Feature",
  "properties": {
    "iso:country":"DE",
    "sg:address":"Bernauer Str. 111",
    "sg:city":"Berlin",
    "sg:phone":"+49 30",
    "sg:postcode":"13355",
    "sg:province":"Berlin",
    "wof:name":"B\u00fcrgerb\u00fcro E. V. - Verein Zur Aufarbeitung Der Sed-diktatur",
    "wof:placetype":"venue"
},
  "geometry": {"coordinates":[13.3895206451,52.5352058411],"type":"Point"}
}