{
  "type": "Feature",
  "properties": {
    "iso:country":"DE",
    "sg:address":"Goldbergstr. 5",
    "sg:city":"Hagen",
    "sg:postcode":"58095",
    "sg:province":"Nordrhein-Westfalen",
    "wof:name":"Christian Hair Und Design Gmbh",
    "wof:placetype":"venue"
},
  "geometry": {"coordinates":[7.4724330902,51.356803894],"type":"Point"}
}