{
  "type": "Feature",
  "properties": {
    "iso:country":"DE",
    "sg:address":"Rathausstr. 2",
    "sg:city":"Poing",
    "sg:phone":"+49 8121/97800",
    "sg:postcode":"85586",
    "sg:province":"Bayern",
    "wof:name":"Fellermaier & Klose Gmbh",
    "wof:placetype":"venue"
},
  "geometry": {"coordinates":[11.8175783157,48.1697769165],"type":"Point"}
}