{
  "type": "Feature",
  "properties": {
    "iso:country":"DE",
    "sg:address":"Holbeinstr. 9",
    "sg:city":"Cottbus",
    "sg:phone":"+49 355/726379",
    "sg:postcode":"03042",
    "sg:province":"Brandenburg",
    "wof:name":"Dr. Hans-joachim Kowalewski Tierarzt",
    "wof:placetype":"venue"
},
  "geometry": {"coordinates":[14.361828804,51.7537727356],"type":"Point"}
}