{
  "type": "Feature",
  "properties": {
    "iso:country":"DE",
    "sg:address":"Wettersteinstr. 23",
    "sg:city":"Gr\u00f6benzell",
    "sg:phone":"+49 8142/597180",
    "sg:postcode":"82194",
    "sg:province":"Bayern",
    "wof:name":"Horst Emmerich Computerhandlungen",
    "wof:placetype":"venue"
},
  "geometry": {"coordinates":[11.3680906296,48.1873474121],"type":"Point"}
}