{
  "type": "Feature",
  "properties": {
    "iso:country":"DE",
    "sg:address":"Louis-F\u00fcrnberg-Str. 5",
    "sg:city":"Barth",
    "sg:phone":"+49 38231/89036",
    "sg:postcode":"18356",
    "sg:province":"Mecklenburg-Vorpommern",
    "wof:name":"Bodden-apotheke",
    "wof:placetype":"venue"
},
  "geometry": {"coordinates":[12.718846,54.354012],"type":"Point"}
}