{
  "type": "Feature",
  "properties": {
    "iso:country":"DE",
    "sg:address":"Hauptstr. 6",
    "sg:city":"Spiesen-Elversberg",
    "sg:phone":"+49 6821/70981",
    "sg:postcode":"66583",
    "sg:province":"Saarland",
    "wof:name":"Gefl\u00fcgelzuchtverein Spiesen Manfred Gl\u00f6\u00dfner",
    "wof:placetype":"venue"
},
  "geometry": {"coordinates":[7.1603741646,49.3208007812],"type":"Point"}
}