{
  "type": "Feature",
  "properties": {
    "iso:country":"DE",
    "sg:address":"Auenstr. 8 A",
    "sg:city":"Emmering",
    "sg:phone":"+49 8141/59257",
    "sg:postcode":"82275",
    "sg:province":"Bayern",
    "wof:name":"Georg Baptist Ingenieur",
    "wof:placetype":"venue"
},
  "geometry": {"coordinates":[11.2993125916,48.183391571],"type":"Point"}
}