{
  "type": "Feature",
  "properties": {
    "iso:country":"DE",
    "sg:address":"Schreinerstr. 4",
    "sg:city":"Breidenbach",
    "sg:phone":"+49 6465/7744",
    "sg:postcode":"35236",
    "sg:province":"Hessen",
    "wof:name":"Norbert Hoppe",
    "wof:placetype":"venue"
},
  "geometry": {"coordinates":[8.446695,50.888802],"type":"Point"}
}