{
  "type": "Feature",
  "properties": {
    "iso:country":"DE",
    "sg:address":"Adlerstr. 19",
    "sg:city":"Heubach",
    "sg:phone":"+49 7173/18070",
    "sg:postcode":"73540",
    "sg:province":"Baden-W\u00fcrttemberg",
    "wof:name":"D. Bartsch Ingenieur",
    "wof:placetype":"venue"
},
  "geometry": {"coordinates":[9.9312438965,48.7913475037],"type":"Point"}
}