{
  "type": "Feature",
  "properties": {
    "iso:country":"DE",
    "sg:address":"Unterer Graben 21",
    "sg:city":"Bad Mergentheim",
    "sg:phone":"+49 7931/8055",
    "sg:postcode":"97980",
    "sg:province":"Baden-W\u00fcrttemberg",
    "wof:name":"Hartmut Elsner Architekt",
    "wof:placetype":"venue"
},
  "geometry": {"coordinates":[9.76988,49.491131],"type":"Point"}
}