{
  "type": "Feature",
  "properties": {
    "iso:country":"DE",
    "sg:address":"Lessingstr. 24",
    "sg:city":"Altleiningen",
    "sg:phone":"+49 6356/5945",
    "sg:postcode":"67317",
    "sg:province":"Rheinland-Pfalz",
    "wof:name":"Horst Kleinert",
    "wof:placetype":"venue"
},
  "geometry": {"coordinates":[8.080075,49.504581],"type":"Point"}
}