{
  "type": "Feature",
  "properties": {
    "iso:country":"DE",
    "sg:address":"Tharandter Str. 25",
    "sg:city":"Wilsdruff",
    "sg:postcode":"01723",
    "sg:province":"Sachsen",
    "wof:name":"Feucht Verwaltungs Gmbh",
    "wof:placetype":"venue"
},
  "geometry": {"coordinates":[13.55932,51.015614],"type":"Point"}
}