{
  "type": "Feature",
  "properties": {
    "iso:country":"DE",
    "sg:address":"M\u00f6rikestra\u00dfe 33",
    "sg:city":"N\u00fcrnberg",
    "sg:phone":"+49 911/9198285",
    "sg:postcode":"90491",
    "sg:province":"Bayern",
    "wof:name":"Medialink",
    "wof:placetype":"venue"
},
  "geometry": {"coordinates":[11.1307678223,49.4756164551],"type":"Point"}
}