{
  "type": "Feature",
  "properties": {
    "iso:country":"DE",
    "sg:address":"Schwaben\u00e4cker 16",
    "sg:city":"Kre\u00dfberg",
    "sg:phone":"+49 7951/42475",
    "sg:postcode":"74594",
    "sg:province":"Baden-W\u00fcrttemberg",
    "wof:name":"Gr\u00fcner Wald",
    "wof:placetype":"venue"
},
  "geometry": {"coordinates":[10.126326561,49.1562156677],"type":"Point"}
}