{
  "type": "Feature",
  "properties": {
    "iso:country":"DE",
    "sg:address":"Mannheimer Str. 21",
    "sg:city":"Kaiserslautern",
    "sg:phone":"+49 631/68884",
    "sg:postcode":"67655",
    "sg:province":"Rheinland-Pfalz",
    "wof:name":"Oekumenische Sozialstation Krankenpflege Ahz",
    "wof:placetype":"venue"
},
  "geometry": {"coordinates":[7.778681,49.447159],"type":"Point"}
}