{
  "type": "Feature",
  "properties": {
    "iso:country":"DE",
    "sg:address":"Siegburger Str. 366",
    "sg:city":"K\u00f6ln",
    "sg:phone":"+49 221/8302890",
    "sg:postcode":"51105",
    "sg:province":"Nordrhein-Westfalen",
    "wof:name":"Radio Meller Gmbh",
    "wof:placetype":"venue"
},
  "geometry": {"coordinates":[6.9909582138,50.9161949158],"type":"Point"}
}