{
  "type": "Feature",
  "properties": {
    "iso:country":"DE",
    "sg:address":"Kranichstr. 7",
    "sg:city":"Krauchenwies",
    "sg:phone":"+49 7576/9135",
    "sg:postcode":"72505",
    "sg:province":"Baden-W\u00fcrttemberg",
    "wof:name":"Alfred H\u00f6lbing B\u00e4ckerei",
    "wof:placetype":"venue"
},
  "geometry": {"coordinates":[9.254744,48.016792],"type":"Point"}
}