{
  "type": "Feature",
  "properties": {
    "iso:country":"DE",
    "sg:address":"Alte Landstr. 60-62",
    "sg:city":"Quarnbek",
    "sg:phone":"+49 4340/9444",
    "sg:postcode":"24107",
    "sg:province":"Schleswig-Holstein",
    "wof:name":"Andersen & Behrmann",
    "wof:placetype":"venue"
},
  "geometry": {"coordinates":[10.00561,54.343357],"type":"Point"}
}