{
  "type": "Feature",
  "properties": {
    "iso:country":"DE",
    "sg:address":"Galileistr. 4",
    "sg:city":"Zwickau",
    "sg:phone":"+49 375/291108",
    "sg:postcode":"08056",
    "sg:province":"Sachsen",
    "wof:name":"Zwickauer Heinzelm\u00e4nnchen Gmbh",
    "wof:placetype":"venue"
},
  "geometry": {"coordinates":[12.4686288834,50.7261009216],"type":"Point"}
}