{
  "type": "Feature",
  "properties": {
    "iso:country":"DE",
    "sg:address":"Reichsstr. 84",
    "sg:city":"Berlin",
    "sg:phone":"+49 30/3042920",
    "sg:postcode":"14052",
    "sg:province":"Berlin",
    "wof:name":"Heidemarie Mohn",
    "wof:placetype":"venue"
},
  "geometry": {"coordinates":[13.2615356445,52.5155143738],"type":"Point"}
}