{
  "type": "Feature",
  "properties": {
    "iso:country":"DE",
    "sg:address":"Am Buchholz 16",
    "sg:city":"Hohwacht",
    "sg:phone":"+49 4381/6855",
    "sg:postcode":"24321",
    "sg:province":"Schleswig-Holstein",
    "wof:name":"G\u00e4stehaus Glenewinkel",
    "wof:placetype":"venue"
},
  "geometry": {"coordinates":[10.6680421829,54.3205566406],"type":"Point"}
}