{
  "type": "Feature",
  "properties": {
    "iso:country":"DE",
    "sg:address":"Friesenstr. 32",
    "sg:city":"Worms",
    "sg:phone":"+49 6241/46006",
    "sg:postcode":"67547",
    "sg:province":"Rheinland-Pfalz",
    "wof:name":"Jean Geiger Gmbh",
    "wof:placetype":"venue"
},
  "geometry": {"coordinates":[8.370103,49.635551],"type":"Point"}
}