{
  "type": "Feature",
  "properties": {
    "iso:country":"DE",
    "sg:address":"Magdeburger Chaussee 71",
    "sg:city":"Sennewitz",
    "sg:phone":"+49 34606/2870",
    "sg:postcode":"06193",
    "sg:province":"Sachsen-Anhalt",
    "wof:name":"Auto Halle-nord Gmbh",
    "wof:placetype":"venue"
},
  "geometry": {"coordinates":[11.939496994,51.5321807861],"type":"Point"}
}