{
  "type": "Feature",
  "properties": {
    "iso:country":"DE",
    "sg:address":"G\u00f6rresring 3",
    "sg:city":"Hamburg",
    "sg:phone":"+49 40",
    "sg:postcode":"22609",
    "sg:province":"Hamburg",
    "wof:name":"Bigalke Immobilien",
    "wof:placetype":"venue"
},
  "geometry": {"coordinates":[9.8512401581,53.5616035461],"type":"Point"}
}