{
  "type": "Feature",
  "properties": {
    "iso:country":"DE",
    "sg:address":"Enscheder Str. 42",
    "sg:city":"Gronau",
    "sg:phone":"+49 2562/3766",
    "sg:postcode":"48599",
    "sg:province":"Nordrhein-Westfalen",
    "wof:name":"Martin Sch\u00f6nherr",
    "wof:placetype":"venue"
},
  "geometry": {"coordinates":[7.015524,52.212975],"type":"Point"}
}