{
  "type": "Feature",
  "properties": {
    "iso:country":"DE",
    "sg:address":"Klosterhofstr. 36",
    "sg:city":"Weinheim",
    "sg:phone":"+49 6201/53641",
    "sg:postcode":"69469",
    "sg:province":"Baden-W\u00fcrttemberg",
    "wof:name":"Unigraph Gmbh",
    "wof:placetype":"venue"
},
  "geometry": {"coordinates":[8.6636133194,49.5321922302],"type":"Point"}
}