{
  "type": "Feature",
  "properties": {
    "iso:country":"DE",
    "sg:address":"Wildstr. 18",
    "sg:city":"Bad Aibling",
    "sg:phone":"+49 8061/8216",
    "sg:postcode":"83043",
    "sg:province":"Bayern",
    "wof:name":"Hoffmann Ohg",
    "wof:placetype":"venue"
},
  "geometry": {"coordinates":[12.002948761,47.8641853333],"type":"Point"}
}