{
  "type": "Feature",
  "properties": {
    "iso:country":"DE",
    "sg:address":"Untere Dorfstr. 9",
    "sg:city":"Kirchdorf",
    "sg:phone":"+49 8166/1203",
    "sg:postcode":"85414",
    "sg:province":"Bayern",
    "wof:name":"Thomas Mairiedl",
    "wof:placetype":"venue"
},
  "geometry": {"coordinates":[11.675489,48.456066],"type":"Point"}
}