{
  "type": "Feature",
  "properties": {
    "iso:country":"DE",
    "sg:address":"Am Trippelsberg 48::",
    "sg:city":"D\u00fcsseldorf",
    "sg:phone":"+49 4921/179500",
    "sg:postcode":"40589",
    "sg:province":"Nordrhein-Westfalen",
    "wof:name":"Corus Hille & M\u00dcller Gmbh",
    "wof:placetype":"venue"
},
  "geometry": {"coordinates":[6.825988,51.16552],"type":"Point"}
}