{
  "type": "Feature",
  "properties": {
    "iso:country":"DE",
    "sg:address":"Bei der Kirche 17a",
    "sg:city":"Grube",
    "sg:phone":"+49 4364/1267",
    "sg:postcode":"23749",
    "sg:province":"Schleswig-Holstein",
    "wof:name":"Rainer Passarge",
    "wof:placetype":"venue"
},
  "geometry": {"coordinates":[11.0324897766,54.2356338501],"type":"Point"}
}