{
  "type": "Feature",
  "properties": {
    "iso:country":"DE",
    "sg:address":"Benrader Str. 37",
    "sg:city":"T\u00f6nisvorst",
    "sg:phone":"+49 2151/757275",
    "sg:postcode":"47918",
    "sg:province":"Nordrhein-Westfalen",
    "wof:name":"B. Ludwig Schaufenstergestaltung",
    "wof:placetype":"venue"
},
  "geometry": {"coordinates":[6.501470089,51.3193321228],"type":"Point"}
}