{
  "type": "Feature",
  "properties": {
    "iso:country":"DE",
    "sg:address":"Rabenhofstr. 22",
    "sg:city":"Ansbach",
    "sg:phone":"+49 981/12798",
    "sg:postcode":"91522",
    "sg:province":"Bayern",
    "wof:name":"Starrampe.de - Die Adresse Zu Deinen Idolen!",
    "wof:placetype":"venue"
},
  "geometry": {"coordinates":[10.597525,49.310863],"type":"Point"}
}