{
  "type": "Feature",
  "properties": {
    "iso:country":"DE",
    "sg:address":"Obermarkt 10",
    "sg:city":"Frankenberg",
    "sg:phone":"+49 6451/9384",
    "sg:postcode":"35066",
    "sg:province":"Hessen",
    "wof:name":"Karl V\u00f6hl",
    "wof:placetype":"venue"
},
  "geometry": {"coordinates":[8.802068,51.058563],"type":"Point"}
}