{
  "type": "Feature",
  "properties": {
    "iso:country":"DE",
    "sg:address":"Parkstr. 8",
    "sg:city":"Bad Breisig",
    "sg:phone":"+49 2633/8811",
    "sg:postcode":"53498",
    "sg:province":"Rheinland-Pfalz",
    "wof:name":"Consilium Gmbh",
    "wof:placetype":"venue"
},
  "geometry": {"coordinates":[7.296291,50.498314],"type":"Point"}
}