{
  "type": "Feature",
  "properties": {
    "iso:country":"DE",
    "sg:address":"Landreiterstr. 6",
    "sg:city":"Rostock",
    "sg:phone":"+49 381/685957",
    "sg:postcode":"18147",
    "sg:province":"Mecklenburg-Vorpommern",
    "wof:name":"Mecklenburgische Immobilien Gmbh",
    "wof:placetype":"venue"
},
  "geometry": {"coordinates":[12.1153402328,54.1001014709],"type":"Point"}
}