{
  "type": "Feature",
  "properties": {
    "iso:country":"DE",
    "sg:address":"Bachlangenstr. 22",
    "sg:city":"Biberach",
    "sg:phone":"+49 7351/31411",
    "sg:postcode":"88400",
    "sg:province":"Baden-W\u00fcrttemberg",
    "wof:name":"Biber-druckerei Inh. Ulrich Von Taczada",
    "wof:placetype":"venue"
},
  "geometry": {"coordinates":[9.807706,48.09108],"type":"Point"}
}