{
  "type": "Feature",
  "properties": {
    "iso:country":"DE",
    "sg:address":"Laufener Str. 5",
    "sg:city":"Tittmoning",
    "sg:phone":"+49 8683/809690",
    "sg:postcode":"84529",
    "sg:province":"Bayern",
    "wof:name":"Pizza Heimservice Bei Daniela",
    "wof:placetype":"venue"
},
  "geometry": {"coordinates":[12.769005,48.059807],"type":"Point"}
}