{
  "type": "Feature",
  "properties": {
    "iso:country":"DE",
    "sg:address":"Wei\u00dfhausstr. 30",
    "sg:city":"K\u00f6ln",
    "sg:postcode":"50939",
    "sg:province":"Nordrhein-Westfalen",
    "wof:name":"Unykat Namefinding Gmbh & Co. Kg",
    "wof:placetype":"venue"
},
  "geometry": {"coordinates":[6.93576,50.919659],"type":"Point"}
}