{
  "type": "Feature",
  "properties": {
    "iso:country":"DE",
    "sg:address":"Niedervellmarer Str. 41a",
    "sg:city":"Kassel",
    "sg:phone":"+49 561/983380",
    "sg:postcode":"34127",
    "sg:province":"Hessen",
    "wof:name":"Ris-softwareentwicklung Gmbh",
    "wof:placetype":"venue"
},
  "geometry": {"coordinates":[9.483327,51.343132],"type":"Point"}
}