{
  "type": "Feature",
  "properties": {
    "iso:country":"DE",
    "sg:address":"Brucknerstr. 1",
    "sg:city":"Neu-Ulm",
    "sg:phone":"+49 731/724160",
    "sg:postcode":"89231",
    "sg:province":"Bayern",
    "wof:name":"K. Schuster",
    "wof:placetype":"venue"
},
  "geometry": {"coordinates":[10.018529892,48.4038085938],"type":"Point"}
}