{
  "type": "Feature",
  "properties": {
    "iso:country":"DE",
    "sg:address":"Am Bahnhofsplatz 3",
    "sg:city":"Pfinztal",
    "sg:phone":"+49 721/46141",
    "sg:postcode":"76327",
    "sg:province":"Baden-W\u00fcrttemberg",
    "wof:name":"Miltner",
    "wof:placetype":"venue"
},
  "geometry": {"coordinates":[8.529129982,49.0052566528],"type":"Point"}
}