{
  "type": "Feature",
  "properties": {
    "iso:country":"DE",
    "sg:address":"Solmserweg 25",
    "sg:city":"Wetzlar",
    "sg:phone":"+49 6441/26442",
    "sg:postcode":"35580",
    "sg:province":"Hessen",
    "wof:name":"B\u00fcrgerhaus",
    "wof:placetype":"venue"
},
  "geometry": {"coordinates":[8.4943532944,50.5327301025],"type":"Point"}
}