{
  "type": "Feature",
  "properties": {
    "iso:country":"DE",
    "sg:address":"Markt 17",
    "sg:city":"Schweinfurt",
    "sg:phone":"+49 9721/208240",
    "sg:postcode":"97421",
    "sg:province":"Bayern",
    "wof:name":"Adolf Rosa Textilhandelsges. Mbh",
    "wof:placetype":"venue"
},
  "geometry": {"coordinates":[10.2340688705,50.044719696],"type":"Point"}
}