{
  "type": "Feature",
  "properties": {
    "iso:country":"DE",
    "sg:address":"Niddastr. 1",
    "sg:city":"Bad Vilbel",
    "sg:phone":"+49 6101/7431",
    "sg:postcode":"61118",
    "sg:province":"Hessen",
    "wof:name":"Hallenbad",
    "wof:placetype":"venue"
},
  "geometry": {"coordinates":[8.7388954163,50.181854248],"type":"Point"}
}