{
  "type": "Feature",
  "properties": {
    "iso:country":"DE",
    "sg:address":"Vogelheimer Str. 147",
    "sg:city":"Essen",
    "sg:phone":"+49 201/353773",
    "sg:postcode":"45329",
    "sg:province":"Nordrhein-Westfalen",
    "wof:name":"Aynur Darici",
    "wof:placetype":"venue"
},
  "geometry": {"coordinates":[6.993956089,51.4916801453],"type":"Point"}
}