{
  "type": "Feature",
  "properties": {
    "iso:country":"DE",
    "sg:address":"Geisenrieder Str. 14",
    "sg:city":"Marktoberdorf",
    "sg:phone":"+49 8342/2246",
    "sg:postcode":"87616",
    "sg:province":"Bayern",
    "wof:name":"Schnupferclub Geisenried Xaver Stocker",
    "wof:placetype":"venue"
},
  "geometry": {"coordinates":[10.5614118576,47.7703666687],"type":"Point"}
}