{
  "type": "Feature",
  "properties": {
    "iso:country":"DE",
    "sg:address":"Dorfstr. 53",
    "sg:city":"Everingen",
    "sg:phone":"+49 39057/2955",
    "sg:postcode":"39359",
    "sg:province":"Sachsen-Anhalt",
    "wof:name":"Atzes Eiscafe",
    "wof:placetype":"venue"
},
  "geometry": {"coordinates":[11.091953,52.366032],"type":"Point"}
}