{
  "type": "Feature",
  "properties": {
    "iso:country":"DE",
    "sg:address":"Eduard-Goebel-Str. 5",
    "sg:city":"Fulda",
    "sg:phone":"+49 661/34448",
    "sg:postcode":"36043",
    "sg:province":"Hessen",
    "wof:name":"Wolfgang Reichel Steuerberater",
    "wof:placetype":"venue"
},
  "geometry": {"coordinates":[9.7159137726,50.5501937866],"type":"Point"}
}