{
  "type": "Feature",
  "properties": {
    "iso:country":"DE",
    "sg:address":"V\u00f6destr. 119",
    "sg:city":"Herne",
    "sg:phone":"+49 2323/43334",
    "sg:postcode":"44625",
    "sg:province":"Nordrhein-Westfalen",
    "wof:name":"E. L\u00f6ffler",
    "wof:placetype":"venue"
},
  "geometry": {"coordinates":[7.2277231216,51.5197944641],"type":"Point"}
}