{
  "type": "Feature",
  "properties": {
    "iso:country":"DE",
    "sg:address":"Kirchstr. 1",
    "sg:city":"Waldalgesheim",
    "sg:phone":"+49 6721/32397",
    "sg:postcode":"55425",
    "sg:province":"Rheinland-Pfalz",
    "wof:name":"Kath. Pfarramt St. Dionysius",
    "wof:placetype":"venue"
},
  "geometry": {"coordinates":[7.8309288025,49.950504303],"type":"Point"}
}