{
  "type": "Feature",
  "properties": {
    "iso:country":"DE",
    "sg:address":"Rathausstr. 1b",
    "sg:city":"Stolberg",
    "sg:phone":"+49 2402/25689",
    "sg:postcode":"52222",
    "sg:province":"Nordrhein-Westfalen",
    "wof:name":"M. Schnitzler",
    "wof:placetype":"venue"
},
  "geometry": {"coordinates":[6.2308921814,50.7690048218],"type":"Point"}
}