{
  "type": "Feature",
  "properties": {
    "iso:country":"DE",
    "sg:address":"Kirchwerder Hausdeich 6",
    "sg:city":"Hamburg",
    "sg:phone":"+49 40/7395959",
    "sg:postcode":"21037",
    "sg:province":"Hamburg",
    "wof:name":"Leverenz Steinmetzbetrieb Gmbh",
    "wof:placetype":"venue"
},
  "geometry": {"coordinates":[10.1753978729,53.443359375],"type":"Point"}
}