{
  "type": "Feature",
  "properties": {
    "iso:country":"DE",
    "sg:address":"Wiedener Str. 111",
    "sg:city":"Wuppertal",
    "sg:postcode":"42327",
    "sg:province":"Nordrhein-Westfalen",
    "wof:name":"Andrea M\u00fcller",
    "wof:placetype":"venue"
},
  "geometry": {"coordinates":[7.07283,51.261101],"type":"Point"}
}