{
  "type": "Feature",
  "properties": {
    "iso:country":"DE",
    "sg:address":"Knappsbrink 22",
    "sg:city":"Osnabr\u00fcck",
    "sg:phone":"+49 541/803517",
    "sg:postcode":"49080",
    "sg:province":"Niedersachsen",
    "wof:name":"Gewa",
    "wof:placetype":"venue"
},
  "geometry": {"coordinates":[8.0402927399,52.2603034973],"type":"Point"}
}