{
  "type": "Feature",
  "properties": {
    "iso:country":"DE",
    "sg:address":"Daimlerstr. 16",
    "sg:city":"Forchheim",
    "sg:phone":"+49 9191/72030",
    "sg:postcode":"91301",
    "sg:province":"Bayern",
    "wof:name":"Josef Riepl Gmbh",
    "wof:placetype":"venue"
},
  "geometry": {"coordinates":[11.063135,49.701279],"type":"Point"}
}