{
  "type": "Feature",
  "properties": {
    "iso:country":"DE",
    "sg:address":"K\u00f6nigstr. 135",
    "sg:city":"F\u00fcrth",
    "sg:phone":"+49 911/770542",
    "sg:postcode":"90762",
    "sg:province":"Bayern",
    "wof:name":"Das Versicherungen Bezirksdirektion",
    "wof:placetype":"venue"
},
  "geometry": {"coordinates":[10.9927778244,49.4737625122],"type":"Point"}
}