{
  "type": "Feature",
  "properties": {
    "iso:country":"DE",
    "sg:address":"Sch\u00f6nseer Str. 15",
    "sg:city":"Oberviechtach",
    "sg:phone":"+49 9671/91186",
    "sg:postcode":"92526",
    "sg:province":"Bayern",
    "wof:name":"Ralf Gohlke",
    "wof:placetype":"venue"
},
  "geometry": {"coordinates":[12.4217805862,49.4611549377],"type":"Point"}
}