{
  "type": "Feature",
  "properties": {
    "iso:country":"DE",
    "sg:address":"Steinweg 43",
    "sg:city":"Langenselbold",
    "sg:phone":"+49 6184/3409",
    "sg:postcode":"63505",
    "sg:province":"Hessen",
    "wof:name":"Mariele Weckmann Gmbh",
    "wof:placetype":"venue"
},
  "geometry": {"coordinates":[9.0412769318,50.1806488037],"type":"Point"}
}