{
  "type": "Feature",
  "properties": {
    "iso:country":"DE",
    "sg:address":"Bismarckstr. 2",
    "sg:city":"Radolfzell",
    "sg:phone":"+49 7732/2065",
    "sg:postcode":"78315",
    "sg:province":"Baden-W\u00fcrttemberg",
    "wof:name":"Klaus Diez & Sohn Gbr",
    "wof:placetype":"venue"
},
  "geometry": {"coordinates":[8.9686489105,47.739151001],"type":"Point"}
}