{
  "type": "Feature",
  "properties": {
    "iso:country":"DE",
    "sg:address":"Matthias-Claudius-Str. 27",
    "sg:city":"Wiesbaden",
    "sg:phone":"+49 611/303372",
    "sg:postcode":"65185",
    "sg:province":"Hessen",
    "wof:name":"Wolfgang K\u00fchn",
    "wof:placetype":"venue"
},
  "geometry": {"coordinates":[8.237665,50.073101],"type":"Point"}
}