{
  "type": "Feature",
  "properties": {
    "iso:country":"DE",
    "sg:address":"Stocksbergstr. 14",
    "sg:city":"Brackenheim",
    "sg:phone":"+49 7135/6663",
    "sg:postcode":"74336",
    "sg:province":"Baden-W\u00fcrttemberg",
    "wof:name":"Hertner Gmbh",
    "wof:placetype":"venue"
},
  "geometry": {"coordinates":[9.0131559372,49.0866394043],"type":"Point"}
}