{
  "type": "Feature",
  "properties": {
    "iso:country":"DE",
    "sg:address":"Robbenweg 1",
    "sg:city":"Westerland",
    "sg:phone":"+49 4651/92000",
    "sg:postcode":"25980",
    "sg:province":"Schleswig-Holstein",
    "wof:name":"Hotel Britta Br\u00fcggen",
    "wof:placetype":"venue"
},
  "geometry": {"coordinates":[8.3044176102,54.899520874],"type":"Point"}
}