{
  "type": "Feature",
  "properties": {
    "iso:country":"DE",
    "sg:address":"Haus-Knipp-Str. 33",
    "sg:city":"Duisburg",
    "sg:phone":"+49 203/870387",
    "sg:postcode":"47139",
    "sg:province":"Nordrhein-Westfalen",
    "wof:name":"Angelika Benninghoff",
    "wof:placetype":"venue"
},
  "geometry": {"coordinates":[6.7013068199,51.4758758545],"type":"Point"}
}