{
  "type": "Feature",
  "properties": {
    "iso:country":"DE",
    "sg:address":"Friedberger Str. 30",
    "sg:city":"Nidderau",
    "sg:phone":"+49 6187/901717",
    "sg:postcode":"61130",
    "sg:province":"Hessen",
    "wof:name":"Gastst\u00e4tte Hotel Am Zollhaus",
    "wof:placetype":"venue"
},
  "geometry": {"coordinates":[8.8602304459,50.2414894104],"type":"Point"}
}