{
  "type": "Feature",
  "properties": {
    "iso:country":"DE",
    "sg:address":"Bergstr. 7",
    "sg:city":"Remchingen",
    "sg:phone":"+49 7232/71393",
    "sg:postcode":"75196",
    "sg:province":"Baden-W\u00fcrttemberg",
    "wof:name":"J\u00fcrgen Weissmann",
    "wof:placetype":"venue"
},
  "geometry": {"coordinates":[8.5709457397,48.9588623047],"type":"Point"}
}