{
  "type": "Feature",
  "properties": {
    "iso:country":"DE",
    "sg:address":"Parkstr. 3",
    "sg:city":"Stadtbergen",
    "sg:phone":"+49 821/434112",
    "sg:postcode":"86391",
    "sg:province":"Bayern",
    "wof:name":"Realbau Terra Immobilien- Und Bautr\u00e4ger Gmbh",
    "wof:placetype":"venue"
},
  "geometry": {"coordinates":[10.833779,48.350739],"type":"Point"}
}