{
  "type": "Feature",
  "properties": {
    "iso:country":"DE",
    "sg:address":"Lyrenstr. 1",
    "sg:city":"Bochum",
    "sg:phone":"+49 2327/328279",
    "sg:postcode":"44866",
    "sg:province":"Nordrhein-Westfalen",
    "wof:name":"Versicherung M\u00fcnchener Verein",
    "wof:placetype":"venue"
},
  "geometry": {"coordinates":[7.1292510033,51.4815139771],"type":"Point"}
}