{
  "type": "Feature",
  "properties": {
    "iso:country":"DE",
    "sg:address":"Marktstr. 64",
    "sg:city":"Mayen",
    "sg:phone":"+49 2651/73218",
    "sg:postcode":"56727",
    "sg:province":"Rheinland-Pfalz",
    "wof:name":"Pizzeria Martineli",
    "wof:placetype":"venue"
},
  "geometry": {"coordinates":[7.2246699333,50.3307914734],"type":"Point"}
}