{
  "type": "Feature",
  "properties": {
    "iso:country":"DE",
    "sg:address":"Brandenburger Str. 47a",
    "sg:city":"Potsdam",
    "sg:phone":"+49 331/2804902",
    "sg:postcode":"14467",
    "sg:province":"Brandenburg",
    "wof:name":"Fielmann Fielmann Gmbh & Co.",
    "wof:placetype":"venue"
},
  "geometry": {"coordinates":[13.056188,52.400665],"type":"Point"}
}