{
  "type": "Feature",
  "properties": {
    "iso:country":"DE",
    "sg:address":"Schafdrift 45",
    "sg:city":"Aurich",
    "sg:phone":"+49 4941/2564",
    "sg:postcode":"26605",
    "sg:province":"Niedersachsen",
    "wof:name":"Gastst\u00e4tte C. Dirks",
    "wof:placetype":"venue"
},
  "geometry": {"coordinates":[7.5354762077,53.4765357971],"type":"Point"}
}