{
  "type": "Feature",
  "properties": {
    "iso:country":"DE",
    "sg:address":"Zum Lonnenhohl 36",
    "sg:city":"Dortmund",
    "sg:phone":"+49 231/9210300",
    "sg:postcode":"44319",
    "sg:province":"Nordrhein-Westfalen",
    "wof:name":"Geberit Produktions Gmbh",
    "wof:placetype":"venue"
},
  "geometry": {"coordinates":[7.6319990158,51.5310554504],"type":"Point"}
}