{
  "type": "Feature",
  "properties": {
    "iso:country":"DE",
    "sg:address":"Augustinergasse 2",
    "sg:city":"Freiburg",
    "sg:phone":"+49 761/33896",
    "sg:postcode":"79098",
    "sg:province":"Baden-W\u00fcrttemberg",
    "wof:name":"Pussy Due Inh. U. Mann",
    "wof:placetype":"venue"
},
  "geometry": {"coordinates":[7.8567199707,47.9921760559],"type":"Point"}
}