{
  "type": "Feature",
  "properties": {
    "iso:country":"DE",
    "sg:address":"Am Stellwerk 6a",
    "sg:city":"Kall",
    "sg:phone":"+49 2441/8664",
    "sg:postcode":"53925",
    "sg:province":"Nordrhein-Westfalen",
    "wof:name":"Hubert Appelhoff",
    "wof:placetype":"venue"
},
  "geometry": {"coordinates":[6.5581450462,50.5403137207],"type":"Point"}
}