{
  "type": "Feature",
  "properties": {
    "iso:country":"DE",
    "sg:address":"Maximilianstr. 28",
    "sg:city":"N\u00fcrnberg",
    "sg:phone":"+49 911/312976",
    "sg:postcode":"90429",
    "sg:province":"Bayern",
    "wof:name":"Maximiliansburg",
    "wof:placetype":"venue"
},
  "geometry": {"coordinates":[11.0424308777,49.4572181702],"type":"Point"}
}