{
  "type": "Feature",
  "properties": {
    "iso:country":"DE",
    "sg:city":"Waldstetten",
    "sg:phone":"+49 7171/44146",
    "sg:postcode":"73550",
    "sg:province":"Baden-W\u00fcrttemberg",
    "wof:name":"Kath. Schwesternhaus",
    "wof:placetype":"venue"
},
  "geometry": {"coordinates":[9.820323,48.766174],"type":"Point"}
}