{
  "type": "Feature",
  "properties": {
    "iso:country":"DE",
    "sg:address":"Am Freisch\u00fctz 16",
    "sg:city":"Duisburg",
    "sg:phone":"+49 203/332341",
    "sg:postcode":"47058",
    "sg:province":"Nordrhein-Westfalen",
    "wof:name":"Latona Verwaltungen Und Handel Conle Kg",
    "wof:placetype":"venue"
},
  "geometry": {"coordinates":[6.798785,51.435307],"type":"Point"}
}