{
  "type": "Feature",
  "properties": {
    "iso:country":"DE",
    "sg:address":"H\u00f6chberger Str. 41a",
    "sg:city":"Waldb\u00fcttelbrunn",
    "sg:phone":"+49 931/405936",
    "sg:postcode":"97297",
    "sg:province":"Bayern",
    "wof:name":"Eduard Zecherle",
    "wof:placetype":"venue"
},
  "geometry": {"coordinates":[9.8484420776,49.7880630493],"type":"Point"}
}