{
  "type": "Feature",
  "properties": {
    "iso:country":"DE",
    "sg:address":"Wallackerhof 1",
    "sg:city":"Kreimbach-Kaulbach",
    "sg:phone":"+49 6304/8404",
    "sg:postcode":"67757",
    "sg:province":"Rheinland-Pfalz",
    "wof:name":"E. Kauschke",
    "wof:placetype":"venue"
},
  "geometry": {"coordinates":[7.6192989349,49.5548286438],"type":"Point"}
}