{
  "type": "Feature",
  "properties": {
    "iso:country":"DE",
    "sg:address":"An den Kiesgruben 2",
    "sg:city":"Wendlingen",
    "sg:postcode":"73240",
    "sg:province":"Baden-W\u00fcrttemberg",
    "wof:name":"Wohnbau Gaus Verwaltungs Gmbh",
    "wof:placetype":"venue"
},
  "geometry": {"coordinates":[9.374034,48.679386],"type":"Point"}
}