{
  "type": "Feature",
  "properties": {
    "iso:country":"DE",
    "sg:address":"Sch\u00f6nwalder Str. 21",
    "sg:city":"Berlin",
    "sg:phone":"+49 30/4613619",
    "sg:postcode":"13347",
    "sg:province":"Berlin",
    "wof:name":"Gesch\u00e4ftsf\u00fchrender Verein Der Christlichen Gemeinschaften",
    "wof:placetype":"venue"
},
  "geometry": {"coordinates":[13.3717823029,52.5418930054],"type":"Point"}
}