{
  "type": "Feature",
  "properties": {
    "iso:country":"DE",
    "sg:address":"Steingasse 9",
    "sg:city":"W\u00f6lfersheim",
    "sg:phone":"+49 6036/6016",
    "sg:postcode":"61200",
    "sg:province":"Hessen",
    "wof:name":"Heinrich Pfeffer Architekt",
    "wof:placetype":"venue"
},
  "geometry": {"coordinates":[8.81523,50.402328],"type":"Point"}
}