{
  "type": "Feature",
  "properties": {
    "iso:country":"DE",
    "sg:address":"Bismarckstr. 28",
    "sg:city":"Friedberg",
    "sg:phone":"+49 6035/8786",
    "sg:postcode":"61169",
    "sg:province":"Hessen",
    "wof:name":"J. Philippi",
    "wof:placetype":"venue"
},
  "geometry": {"coordinates":[8.7576751709,50.332988739],"type":"Point"}
}