{
  "type": "Feature",
  "properties": {
    "iso:country":"DE",
    "sg:address":"Sponeckstr. 100",
    "sg:city":"Sasbach",
    "sg:phone":"+49 7662/6301",
    "sg:postcode":"79361",
    "sg:province":"Baden-W\u00fcrttemberg",
    "wof:name":"Franz Freund Obstanbau Und Weinbau",
    "wof:placetype":"venue"
},
  "geometry": {"coordinates":[7.603579998,48.1206207275],"type":"Point"}
}