{
  "type": "Feature",
  "properties": {
    "iso:country":"DE",
    "sg:address":"Unterer Markt 33",
    "sg:city":"Dorfen",
    "sg:phone":"+49 8081/3649",
    "sg:postcode":"84405",
    "sg:province":"Bayern",
    "wof:name":"Provita Gmbh",
    "wof:placetype":"venue"
},
  "geometry": {"coordinates":[12.1509304047,48.2737350464],"type":"Point"}
}