{
  "type": "Feature",
  "properties": {
    "iso:country":"DE",
    "sg:address":"Chausseestr. 59",
    "sg:city":"Glindow",
    "sg:phone":"+49 3327/41160",
    "sg:postcode":"14542",
    "sg:province":"Brandenburg",
    "wof:name":"S. Czasch",
    "wof:placetype":"venue"
},
  "geometry": {"coordinates":[12.890343,52.373383],"type":"Point"}
}