{
  "type": "Feature",
  "properties": {
    "iso:country":"DE",
    "sg:address":"Hauptstr. 35",
    "sg:city":"Wendelstein",
    "sg:phone":"+49 9129/5014",
    "sg:postcode":"90530",
    "sg:province":"Bayern",
    "wof:name":"K. Karg",
    "wof:placetype":"venue"
},
  "geometry": {"coordinates":[11.1446838379,49.3550567627],"type":"Point"}
}