{
  "type": "Feature",
  "properties": {
    "iso:country":"DE",
    "sg:address":"Silh\u00f6fer Str. 21",
    "sg:city":"Wetzlar",
    "sg:phone":"+49 6441/42356",
    "sg:postcode":"35578",
    "sg:province":"Hessen",
    "wof:name":"M. Geist",
    "wof:placetype":"venue"
},
  "geometry": {"coordinates":[8.500716,50.553394],"type":"Point"}
}