{
  "type": "Feature",
  "properties": {
    "iso:country":"DE",
    "sg:address":"Bettenwarfen 2-14",
    "sg:city":"Neuharlingersiel",
    "sg:postcode":"26427",
    "sg:province":"Niedersachsen",
    "wof:name":"Wasserschlo\u00df Handels- Gesellschaft Mbh",
    "wof:placetype":"venue"
},
  "geometry": {"coordinates":[7.6873440742,53.6914787292],"type":"Point"}
}