{
  "type": "Feature",
  "properties": {
    "iso:country":"DE",
    "sg:address":"Prinz-Albrecht-Str. 1",
    "sg:city":"Duisburg",
    "sg:phone":"+49 203/305860",
    "sg:postcode":"47058",
    "sg:province":"Nordrhein-Westfalen",
    "wof:name":"Dkv Deutsche Kranken- Versicherung Ag",
    "wof:placetype":"venue"
},
  "geometry": {"coordinates":[6.7914528847,51.4340896606],"type":"Point"}
}