{
  "type": "Feature",
  "properties": {
    "iso:country":"DE",
    "sg:address":"Aufkircher Str. 49",
    "sg:city":"\u00dcberlingen",
    "sg:phone":"+49 7551/64212",
    "sg:postcode":"88662",
    "sg:province":"Baden-W\u00fcrttemberg",
    "wof:name":"Albert Kaufmann",
    "wof:placetype":"venue"
},
  "geometry": {"coordinates":[9.1575374603,47.770362854],"type":"Point"}
}