{
  "type": "Feature",
  "properties": {
    "iso:country":"DE",
    "sg:address":"Lippestr. 2",
    "sg:city":"Lippetal",
    "sg:phone":"+49 2923/8607",
    "sg:postcode":"59510",
    "sg:province":"Nordrhein-Westfalen",
    "wof:name":"Oliver P\u00f6psel",
    "wof:placetype":"venue"
},
  "geometry": {"coordinates":[8.1433286667,51.6632194519],"type":"Point"}
}