{
  "type": "Feature",
  "properties": {
    "iso:country":"DE",
    "sg:address":"Dornhaner Str. 2",
    "sg:city":"Oberndorf",
    "sg:phone":"+49 7423/2335",
    "sg:postcode":"78727",
    "sg:province":"Baden-W\u00fcrttemberg",
    "wof:name":"Wolfgang S\u00f6ll",
    "wof:placetype":"venue"
},
  "geometry": {"coordinates":[8.530474,48.308674],"type":"Point"}
}