{
  "type": "Feature",
  "properties": {
    "iso:country":"DE",
    "sg:address":"Heidelberger Str. 12",
    "sg:city":"H\u00f6pfingen",
    "sg:phone":"+49 4962/836595",
    "sg:postcode":"74746",
    "sg:province":"Baden-W\u00fcrttemberg",
    "wof:name":"Werner U. Gerda B\u00d6hrer",
    "wof:placetype":"venue"
},
  "geometry": {"coordinates":[9.426895,49.60144],"type":"Point"}
}