{
  "type": "Feature",
  "properties": {
    "iso:country":"DE",
    "sg:address":"Marienfelder Damm 96-98",
    "sg:city":"Berlin",
    "sg:phone":"+49 30",
    "sg:postcode":"12109",
    "sg:province":"Berlin",
    "wof:name":"Ristorante Arcamone",
    "wof:placetype":"venue"
},
  "geometry": {"coordinates":[13.38586,52.443771],"type":"Point"}
}