{
  "type": "Feature",
  "properties": {
    "iso:country":"DE",
    "sg:address":"Dingbuchstr. 4",
    "sg:city":"Linnich",
    "sg:phone":"+49 2462/6529",
    "sg:postcode":"52441",
    "sg:province":"Nordrhein-Westfalen",
    "wof:name":"A. Gehlen",
    "wof:placetype":"venue"
},
  "geometry": {"coordinates":[6.319058,51.000343],"type":"Point"}
}