{
  "type": "Feature",
  "properties": {
    "iso:country":"DE",
    "sg:address":"Hagdorn 37",
    "sg:city":"M\u00fclheim",
    "sg:phone":"+49 208/360883",
    "sg:postcode":"45468",
    "sg:province":"Nordrhein-Westfalen",
    "wof:name":"Hermann Ro\u00dfhoff",
    "wof:placetype":"venue"
},
  "geometry": {"coordinates":[6.8862318993,51.4251174927],"type":"Point"}
}