{
  "type": "Feature",
  "properties": {
    "iso:country":"DE",
    "sg:address":"Rappengasse 36",
    "sg:city":"Schwegenheim",
    "sg:phone":"+49 6344/1259",
    "sg:postcode":"67365",
    "sg:province":"Rheinland-Pfalz",
    "wof:name":"Edgar Voltz",
    "wof:placetype":"venue"
},
  "geometry": {"coordinates":[8.33074,49.269333],"type":"Point"}
}