{
  "type": "Feature",
  "properties": {
    "iso:country":"DE",
    "sg:address":"Georgstr. 8",
    "sg:city":"L\u00fcchow",
    "sg:phone":"+49 5841/5174",
    "sg:postcode":"29439",
    "sg:province":"Niedersachsen",
    "wof:name":"Ernst Kamlade Architekt",
    "wof:placetype":"venue"
},
  "geometry": {"coordinates":[11.152717,52.969845],"type":"Point"}
}