{
  "type": "Feature",
  "properties": {
    "iso:country":"DE",
    "sg:address":"Neumarkt 12",
    "sg:city":"Netphen",
    "sg:phone":"+49 2738/1771",
    "sg:postcode":"57250",
    "sg:province":"Nordrhein-Westfalen",
    "wof:name":"Merdas Optik",
    "wof:placetype":"venue"
},
  "geometry": {"coordinates":[8.1036014557,50.9115104675],"type":"Point"}
}