{
  "type": "Feature",
  "properties": {
    "iso:country":"DE",
    "sg:address":"An der Lethe 9",
    "sg:city":"Garthe",
    "sg:phone":"+49 4435/2618",
    "sg:postcode":"49685",
    "sg:province":"Niedersachsen",
    "wof:name":"Lothar Hooge Bau",
    "wof:placetype":"venue"
},
  "geometry": {"coordinates":[8.155165,52.834484],"type":"Point"}
}