{
  "type": "Feature",
  "properties": {
    "iso:country":"DE",
    "sg:address":"Hirschberg 7",
    "sg:city":"Horn-Bad Meinberg",
    "sg:phone":"+49 5234/2676",
    "sg:postcode":"32805",
    "sg:province":"Nordrhein-Westfalen",
    "wof:name":"Horst Altemeier",
    "wof:placetype":"venue"
},
  "geometry": {"coordinates":[8.897902,51.878319],"type":"Point"}
}