{
  "type": "Feature",
  "properties": {
    "iso:country":"DE",
    "sg:address":"Saarbr\u00fccker Str. 81",
    "sg:city":"Losheim",
    "sg:phone":"+49 6872/2600",
    "sg:postcode":"66679",
    "sg:province":"Saarland",
    "wof:name":"Maler -u.lackiererei Berthold Mohm Gmbh",
    "wof:placetype":"venue"
},
  "geometry": {"coordinates":[6.752207,49.50478],"type":"Point"}
}