{
  "type": "Feature",
  "properties": {
    "iso:country":"DE",
    "sg:address":"Planegger Str. 13",
    "sg:city":"Gauting",
    "sg:phone":"+49 89/8507660",
    "sg:postcode":"82131",
    "sg:province":"Bayern",
    "wof:name":"Celpaplan Proze\u00dftechnische Planungs-gmbh",
    "wof:placetype":"venue"
},
  "geometry": {"coordinates":[11.3905668259,48.0710754395],"type":"Point"}
}