{
  "type": "Feature",
  "properties": {
    "iso:country":"DE",
    "sg:address":"Joan-Joseph-Fiege-Str. 1",
    "sg:city":"Greven",
    "sg:postcode":"48268",
    "sg:province":"Nordrhein-Westfalen",
    "wof:name":"Fiva Netlog Gmbh & Co. Kg",
    "wof:placetype":"venue"
},
  "geometry": {"coordinates":[7.689572,52.129124],"type":"Point"}
}