{
  "type": "Feature",
  "properties": {
    "iso:country":"DE",
    "sg:address":"Hofstr 64Halle 1807",
    "sg:city":"Hilden",
    "sg:phone":"+49 2103/967700",
    "sg:postcode":"40723",
    "sg:province":"Nordrhein-Westfalen",
    "wof:name":"Kvant",
    "wof:placetype":"venue"
},
  "geometry": {"coordinates":[6.930943,51.161144],"type":"Point"}
}