{
  "type": "Feature",
  "properties": {
    "iso:country":"DE",
    "sg:address":"Hauptstr. 23",
    "sg:city":"Neukirch",
    "sg:phone":"+49 35951/32185",
    "sg:postcode":"01904",
    "sg:province":"Sachsen",
    "wof:name":"Wtr Timo Richter E. Kfm.",
    "wof:placetype":"venue"
},
  "geometry": {"coordinates":[14.3150339127,51.0939102173],"type":"Point"}
}