{
  "type": "Feature",
  "properties": {
    "iso:country":"DE",
    "sg:address":"Georg-Blasel-Str. 1",
    "sg:city":"Ettlingen",
    "sg:phone":"+49 7243/99347",
    "sg:postcode":"76275",
    "sg:province":"Baden-W\u00fcrttemberg",
    "wof:name":"Benno Lumpp",
    "wof:placetype":"venue"
},
  "geometry": {"coordinates":[8.389789,48.929157],"type":"Point"}
}