{
  "type": "Feature",
  "properties": {
    "iso:country":"DE",
    "sg:address":"Laushamer Str. 7",
    "sg:city":"Reichertshausen",
    "sg:phone":"+49 8137/7026",
    "sg:postcode":"85293",
    "sg:province":"Bayern",
    "wof:name":"Bernhard K\u00fcblbeck",
    "wof:placetype":"venue"
},
  "geometry": {"coordinates":[11.483896,48.443123],"type":"Point"}
}