{
  "type": "Feature",
  "properties": {
    "iso:country":"DE",
    "sg:address":"Bahnhofstr. 24",
    "sg:city":"Schlitz",
    "sg:phone":"+49 6642/6577",
    "sg:postcode":"36110",
    "sg:province":"Hessen",
    "wof:name":"Norma Gmbh & Co. Kg",
    "wof:placetype":"venue"
},
  "geometry": {"coordinates":[9.5624341965,50.6771621704],"type":"Point"}
}