{
  "type": "Feature",
  "properties": {
    "iso:country":"DE",
    "sg:address":"Lehmkuhlstr. 21",
    "sg:city":"Bad Salzuflen",
    "sg:phone":"+49 5222/850188",
    "sg:postcode":"32108",
    "sg:province":"Nordrhein-Westfalen",
    "wof:name":"Sport- Und Fitnesstudio",
    "wof:placetype":"venue"
},
  "geometry": {"coordinates":[8.7629394531,52.071182251],"type":"Point"}
}