{
  "type": "Feature",
  "properties": {
    "iso:country":"DE",
    "sg:address":"Centrum 9",
    "sg:city":"Postbauer-Heng",
    "sg:phone":"+49 9188",
    "sg:postcode":"92353",
    "sg:province":"Bayern",
    "wof:name":"Graffitientfernung Und Graffitischutz",
    "wof:placetype":"venue"
},
  "geometry": {"coordinates":[11.348611,49.303288],"type":"Point"}
}