{
  "type": "Feature",
  "properties": {
    "iso:country":"DE",
    "sg:address":"K\u00fchlwetterstr 1",
    "sg:city":"Aachen",
    "sg:phone":"+49 241/9978682",
    "sg:postcode":"52072",
    "sg:province":"Nordrhein-Westfalen",
    "wof:name":"Duvivier & Szablewski Gbr",
    "wof:placetype":"venue"
},
  "geometry": {"coordinates":[6.071041,50.782032],"type":"Point"}
}