{
  "type": "Feature",
  "properties": {
    "iso:country":"DE",
    "sg:address":"Ripperter Str. 4",
    "sg:city":"Ramsen",
    "sg:phone":"+49 6351/41031",
    "sg:postcode":"67305",
    "sg:province":"Rheinland-Pfalz",
    "wof:name":"Thomas Fischer",
    "wof:placetype":"venue"
},
  "geometry": {"coordinates":[8.005417,49.537319],"type":"Point"}
}