{
  "type": "Feature",
  "properties": {
    "iso:country":"DE",
    "sg:address":"Karlstr. 37",
    "sg:city":"M\u00fcnchen",
    "sg:phone":"+49 89/5117320",
    "sg:postcode":"80333",
    "sg:province":"Bayern",
    "wof:name":"Redaktion Elektronik Franzis-verlag",
    "wof:placetype":"venue"
},
  "geometry": {"coordinates":[11.5619096756,48.14427948],"type":"Point"}
}