{
  "type": "Feature",
  "properties": {
    "iso:country":"DE",
    "sg:address":"Reichsstr. 79",
    "sg:city":"Duisburg",
    "sg:phone":"+49 2065/94920",
    "sg:postcode":"47229",
    "sg:province":"Nordrhein-Westfalen",
    "wof:name":"R\u00f6dding Gmbh",
    "wof:placetype":"venue"
},
  "geometry": {"coordinates":[6.706475,51.388641],"type":"Point"}
}