{
  "type": "Feature",
  "properties": {
    "iso:country":"DE",
    "sg:address":"B\u00f6vergeest 69",
    "sg:city":"Sankt Peter-Ording",
    "sg:phone":"+49 4863/3010",
    "sg:postcode":"25826",
    "sg:province":"Schleswig-Holstein",
    "wof:name":"Jens Leh Gmbh",
    "wof:placetype":"venue"
},
  "geometry": {"coordinates":[8.6482172012,54.3066291809],"type":"Point"}
}