{
  "type": "Feature",
  "properties": {
    "iso:country":"DE",
    "sg:address":"Neu-Etumer-Str.",
    "sg:city":"Krummh\u00f6rn",
    "sg:phone":"+49 4926/1724",
    "sg:postcode":"26736",
    "sg:province":"Niedersachsen",
    "wof:name":"Gastst\u00e4tte E. Janssen",
    "wof:placetype":"venue"
},
  "geometry": {"coordinates":[7.0604081154,53.4787445068],"type":"Point"}
}