{
  "type": "Feature",
  "properties": {
    "iso:country":"DE",
    "sg:address":"Feldstr. 4",
    "sg:city":"Rhede",
    "sg:phone":"+49 2872",
    "sg:postcode":"46414",
    "sg:province":"Nordrhein-Westfalen",
    "wof:name":"Mediaconcept Gmbh/ Rhede, B\u00fcromaterial, Kabel,",
    "wof:placetype":"venue"
},
  "geometry": {"coordinates":[6.6995072365,51.8526535034],"type":"Point"}
}