{
  "type": "Feature",
  "properties": {
    "iso:country":"DE",
    "sg:address":"Am Markt 17",
    "sg:city":"Hattersheim",
    "sg:phone":"+49 6190/9770028",
    "sg:postcode":"65795",
    "sg:province":"Hessen",
    "wof:name":"Web-portal Merlin",
    "wof:placetype":"venue"
},
  "geometry": {"coordinates":[8.48495,50.070621],"type":"Point"}
}