{
  "type": "Feature",
  "properties": {
    "iso:country":"DE",
    "sg:address":"Wiesenstr. 11",
    "sg:city":"Pirmasens",
    "sg:phone":"+49 6331/99779",
    "sg:postcode":"66954",
    "sg:province":"Rheinland-Pfalz",
    "wof:name":"Heinz Niski",
    "wof:placetype":"venue"
},
  "geometry": {"coordinates":[7.6014280319,49.1994171143],"type":"Point"}
}