{
  "type": "Feature",
  "properties": {
    "iso:country":"DE",
    "sg:address":"Wiesenstr. 12",
    "sg:city":"Hannover",
    "sg:phone":"+49 511/884174",
    "sg:postcode":"30169",
    "sg:province":"Niedersachsen",
    "wof:name":"Ulrike Knoll",
    "wof:placetype":"venue"
},
  "geometry": {"coordinates":[9.743392,52.362827],"type":"Point"}
}