{
  "type": "Feature",
  "properties": {
    "iso:country":"DE",
    "sg:address":"Sigmaringer Str. 26",
    "sg:city":"Gammertingen",
    "sg:phone":"+49 7574/93420",
    "sg:postcode":"72501",
    "sg:province":"Baden-W\u00fcrttemberg",
    "wof:name":"W. Preg S. Kiener Und W. Benz Steuerberater",
    "wof:placetype":"venue"
},
  "geometry": {"coordinates":[9.2213373184,48.2472610474],"type":"Point"}
}