{
  "type": "Feature",
  "properties": {
    "iso:country":"DE",
    "sg:address":"Johann-Wilhelm-Roth-Str. 49",
    "sg:city":"Wipperf\u00fcrth",
    "sg:phone":"+49 2267/1733",
    "sg:postcode":"51688",
    "sg:province":"Nordrhein-Westfalen",
    "wof:name":"Helmut K\u00f6ser",
    "wof:placetype":"venue"
},
  "geometry": {"coordinates":[7.365986,51.076813],"type":"Point"}
}