{
  "type": "Feature",
  "properties": {
    "iso:country":"DE",
    "sg:address":"Melkerstieg 9",
    "sg:city":"Hamburg",
    "sg:phone":"+49 40/811333",
    "sg:postcode":"22559",
    "sg:province":"Hamburg",
    "wof:name":"U. Adams-zacher Heilpraktiker",
    "wof:placetype":"venue"
},
  "geometry": {"coordinates":[9.7607192993,53.5862312317],"type":"Point"}
}