{
  "type": "Feature",
  "properties": {
    "iso:country":"DE",
    "sg:address":"K\u00f6nigsplatz 33",
    "sg:city":"Schwabach",
    "sg:phone":"+49 9122/85517",
    "sg:postcode":"91126",
    "sg:province":"Bayern",
    "wof:name":"Wei\u00dfes Lamm",
    "wof:placetype":"venue"
},
  "geometry": {"coordinates":[11.0208425522,49.3287124634],"type":"Point"}
}