{
  "type": "Feature",
  "properties": {
    "iso:country":"DE",
    "sg:address":"Hauptstr. 24",
    "sg:city":"P\u00f6lich",
    "sg:phone":"+49 6507/3004",
    "sg:postcode":"54340",
    "sg:province":"Rheinland-Pfalz",
    "wof:name":"G\u00fcnter Bartel",
    "wof:placetype":"venue"
},
  "geometry": {"coordinates":[6.8479909897,49.7979927063],"type":"Point"}
}