{
  "type": "Feature",
  "properties": {
    "iso:country":"DE",
    "sg:address":"Untere R\u00f6de 6",
    "sg:city":"Dermbach",
    "sg:phone":"+49 36964/95310",
    "sg:postcode":"36466",
    "sg:province":"Th\u00fcringen",
    "wof:name":"A. Kutscher",
    "wof:placetype":"venue"
},
  "geometry": {"coordinates":[10.126273,50.711231],"type":"Point"}
}