{
  "type": "Feature",
  "properties": {
    "iso:country":"DE",
    "sg:address":"Gau\u00dfstr. 5",
    "sg:city":"Holzminden",
    "sg:phone":"+49 5531/93560",
    "sg:postcode":"37603",
    "sg:province":"Niedersachsen",
    "wof:name":"Autohaus Stegemann & Heise Gmbh",
    "wof:placetype":"venue"
},
  "geometry": {"coordinates":[9.463918,51.840168],"type":"Point"}
}