{
  "type": "Feature",
  "properties": {
    "iso:country":"DE",
    "sg:address":"Stitzenburgstr. 7",
    "sg:city":"Stuttgart",
    "sg:phone":"+49 711/241010",
    "sg:postcode":"70182",
    "sg:province":"Baden-W\u00fcrttemberg",
    "wof:name":"Deutsche Evangelische Allianz E. V.",
    "wof:placetype":"venue"
},
  "geometry": {"coordinates":[9.1852588654,48.7705535889],"type":"Point"}
}