{
  "type": "Feature",
  "properties": {
    "iso:country":"DE",
    "sg:city":"Bochum",
    "sg:postcode":"44892",
    "sg:province":"Nordrhein-Westfalen",
    "wof:name":"Arbeitszeitlabor Gbr",
    "wof:placetype":"venue"
},
  "geometry": {"coordinates":[7.325005,51.473705],"type":"Point"}
}