{
  "type": "Feature",
  "properties": {
    "iso:country":"DE",
    "sg:address":"Alte Str 16",
    "sg:city":"Herdecke",
    "sg:phone":"+49 2330/974820",
    "sg:postcode":"58313",
    "sg:province":"Nordrhein-Westfalen",
    "wof:name":"Xedoc Datenverarbeitung Und Elektronik Gmbh",
    "wof:placetype":"venue"
},
  "geometry": {"coordinates":[7.4049978256,51.4171905518],"type":"Point"}
}