{
  "type": "Feature",
  "properties": {
    "iso:country":"DE",
    "sg:address":"Stooter Str. 32",
    "sg:city":"M\u00fclheim",
    "sg:phone":"+49 208/489208",
    "sg:postcode":"45481",
    "sg:province":"Nordrhein-Westfalen",
    "wof:name":"Karl-heinz Buschmann",
    "wof:placetype":"venue"
},
  "geometry": {"coordinates":[6.870211,51.370422],"type":"Point"}
}