{
  "type": "Feature",
  "properties": {
    "iso:country":"DE",
    "sg:address":"Im Hammereisen 39",
    "sg:city":"Kranenburg",
    "sg:phone":"+49 2826/803007",
    "sg:postcode":"47559",
    "sg:province":"Nordrhein-Westfalen",
    "wof:name":"Msb Gesellschaft F\u00fcr Verpackungsmaschinen- Und",
    "wof:placetype":"venue"
},
  "geometry": {"coordinates":[6.051704,51.784855],"type":"Point"}
}