{
  "type": "Feature",
  "properties": {
    "iso:country":"DE",
    "sg:address":"Breite Str. 15",
    "sg:city":"Grevenbroich",
    "sg:phone":"+49 2181/163000",
    "sg:postcode":"41515",
    "sg:province":"Nordrhein-Westfalen",
    "wof:name":"Chinarestaurant Lotus",
    "wof:placetype":"venue"
},
  "geometry": {"coordinates":[6.5885257721,51.0890274048],"type":"Point"}
}