{
  "type": "Feature",
  "properties": {
    "iso:country":"DE",
    "sg:address":"Gerichtstr. 1",
    "sg:city":"Hamburg",
    "sg:phone":"+49 40/388384",
    "sg:postcode":"22765",
    "sg:province":"Hamburg",
    "wof:name":"Studio F\u00fcr Gesundheit Frank Matz",
    "wof:placetype":"venue"
},
  "geometry": {"coordinates":[9.94189,53.555489],"type":"Point"}
}