{
  "type": "Feature",
  "properties": {
    "iso:country":"DE",
    "sg:address":"Gruneburgweg 57-62::",
    "sg:city":"Frankfurt",
    "sg:phone":"+49 69/95939100",
    "sg:postcode":"60322",
    "sg:province":"Hessen",
    "wof:name":"Palm Tresckow & Partner Informationssystem Gmbh",
    "wof:placetype":"venue"
},
  "geometry": {"coordinates":[8.6704,50.121609],"type":"Point"}
}