{
  "type": "Feature",
  "properties": {
    "iso:country":"DE",
    "sg:address":"Eberhard-Finckh-Str.",
    "sg:city":"Ulm",
    "sg:phone":"+49 731/263788",
    "sg:postcode":"89075",
    "sg:province":"Baden-W\u00fcrttemberg",
    "wof:name":"Sportstudio & Aerobic Zen",
    "wof:placetype":"venue"
},
  "geometry": {"coordinates":[10.0058097839,48.4225273132],"type":"Point"}
}