{
  "type": "Feature",
  "properties": {
    "iso:country":"DE",
    "sg:address":"Schillstr. 34",
    "sg:city":"Ulm",
    "sg:phone":"+49 731/33916",
    "sg:postcode":"89077",
    "sg:province":"Baden-W\u00fcrttemberg",
    "wof:name":"H. Sch\u00e4tzle",
    "wof:placetype":"venue"
},
  "geometry": {"coordinates":[9.9765090942,48.3947563171],"type":"Point"}
}