{
  "type": "Feature",
  "properties": {
    "iso:country":"DE",
    "sg:address":"Eschenweg 6",
    "sg:city":"Koblenz",
    "sg:phone":"+49 261/55181",
    "sg:postcode":"56075",
    "sg:province":"Rheinland-Pfalz",
    "wof:name":"Friedel Klein",
    "wof:placetype":"venue"
},
  "geometry": {"coordinates":[7.577252,50.333752],"type":"Point"}
}