{
  "type": "Feature",
  "properties": {
    "iso:country":"DE",
    "sg:address":"Kasernenstr. 67",
    "sg:city":"D\u00fcsseldorf",
    "sg:postcode":"40213",
    "sg:province":"Nordrhein-Westfalen",
    "wof:name":"Hb Europ\u00e4ische Fachmedien Verwaltungs- Und Beteil. Gmbh",
    "wof:placetype":"venue"
},
  "geometry": {"coordinates":[6.775365,51.220249],"type":"Point"}
}