{
  "type": "Feature",
  "properties": {
    "iso:country":"DE",
    "sg:address":"Ohmstr. 6",
    "sg:city":"N\u00fcrnberg",
    "sg:phone":"+49 911/447288",
    "sg:postcode":"90443",
    "sg:province":"Bayern",
    "wof:name":"Rudolf K\u00fcffner Gmbh",
    "wof:placetype":"venue"
},
  "geometry": {"coordinates":[11.0740690231,49.4408607483],"type":"Point"}
}