{
  "type": "Feature",
  "properties": {
    "iso:country":"DE",
    "sg:address":"M\u00fchlenstr. 7",
    "sg:city":"Berlin",
    "sg:phone":"+49 30/7743168",
    "sg:postcode":"12247",
    "sg:province":"Berlin",
    "wof:name":"G\u00fcnter Camin Bau- Und M\u00f6belwerkst\u00e4tten Gmbh",
    "wof:placetype":"venue"
},
  "geometry": {"coordinates":[13.353623,52.438145],"type":"Point"}
}