{
  "type": "Feature",
  "properties": {
    "iso:country":"DE",
    "sg:address":"Untere Vorstadt 14",
    "sg:city":"Deggendorf",
    "sg:phone":"+49 991/3792707",
    "sg:postcode":"94469",
    "sg:province":"Bayern",
    "wof:name":"Gransee Gmbh & Co. Kg",
    "wof:placetype":"venue"
},
  "geometry": {"coordinates":[12.9630537033,48.8285560608],"type":"Point"}
}