{
  "type": "Feature",
  "properties": {
    "iso:country":"DE",
    "sg:address":"Kuschkower Str. 31",
    "sg:city":"Schlepzig",
    "sg:postcode":"15910",
    "sg:province":"Brandenburg",
    "wof:name":"Bestrich & Nocka",
    "wof:placetype":"venue"
},
  "geometry": {"coordinates":[13.90363,52.032188],"type":"Point"}
}