{
  "type": "Feature",
  "properties": {
    "iso:country":"DE",
    "sg:address":"Glockenblumenweg 9a",
    "sg:city":"Berlin",
    "sg:phone":"+49 30/66063285",
    "sg:postcode":"12357",
    "sg:province":"Berlin",
    "wof:name":"Landestauchsportverband Berlin",
    "wof:placetype":"venue"
},
  "geometry": {"coordinates":[13.4734802246,52.436378479],"type":"Point"}
}