{
  "type": "Feature",
  "properties": {
    "iso:country":"DE",
    "sg:address":"Sonnenstr. 4",
    "sg:city":"Erlangen",
    "sg:phone":"+49 9131/604038",
    "sg:postcode":"91058",
    "sg:province":"Bayern",
    "wof:name":"B\u00fcrger Fragen Journalisten E. V.",
    "wof:placetype":"venue"
},
  "geometry": {"coordinates":[10.9942293167,49.5525131226],"type":"Point"}
}