{
  "type": "Feature",
  "properties": {
    "iso:country":"DE",
    "sg:address":"Norderweg 5",
    "sg:city":"Gro\u00dfenwiehe",
    "sg:postcode":"24969",
    "sg:province":"Schleswig-Holstein",
    "wof:name":"Amt Tontr\u00e4ger Gmbh",
    "wof:placetype":"venue"
},
  "geometry": {"coordinates":[9.2643861771,54.6924667358],"type":"Point"}
}