{
  "type": "Feature",
  "properties": {
    "iso:country":"DE",
    "sg:address":"M\u00fcnsterstr. 45",
    "sg:city":"Glandorf",
    "sg:phone":"+49 5426/5888",
    "sg:postcode":"49219",
    "sg:province":"Niedersachsen",
    "wof:name":"Heinz Vor-der-landwehr",
    "wof:placetype":"venue"
},
  "geometry": {"coordinates":[7.965375,52.071194],"type":"Point"}
}