{
  "type": "Feature",
  "properties": {
    "iso:country":"DE",
    "sg:address":"Nietzschestr. 21",
    "sg:city":"Aalen",
    "sg:phone":"+49 7361/31414",
    "sg:postcode":"73431",
    "sg:province":"Baden-W\u00fcrttemberg",
    "wof:name":"J. Krau\u00df Innenarchitekt",
    "wof:placetype":"venue"
},
  "geometry": {"coordinates":[10.122706,48.844013],"type":"Point"}
}