{
  "type": "Feature",
  "properties": {
    "iso:country":"DE",
    "sg:address":"Sandstr. 4",
    "sg:city":"Rosenheim",
    "sg:phone":"+49 8031/12329",
    "sg:postcode":"83022",
    "sg:province":"Bayern",
    "wof:name":"Manfred Mager",
    "wof:placetype":"venue"
},
  "geometry": {"coordinates":[12.1178445816,47.8528747559],"type":"Point"}
}