{
  "type": "Feature",
  "properties": {
    "iso:country":"DE",
    "sg:address":"Flachsspinnereistra\u00dfe 22",
    "sg:city":"Hirschfelde",
    "sg:phone":"+49 4935/8432650",
    "sg:postcode":"02788",
    "sg:province":"Sachsen",
    "wof:name":"Hiltex Hirschfelder Leinen Und Textil Gmbh",
    "wof:placetype":"venue"
},
  "geometry": {"coordinates":[14.8940105438,50.9532623291],"type":"Point"}
}