{
  "type": "Feature",
  "properties": {
    "iso:country":"DE",
    "sg:address":"Teutonenweg 50",
    "sg:city":"Frankfurt",
    "sg:phone":"+49 69/302381",
    "sg:postcode":"65929",
    "sg:province":"Hessen",
    "wof:name":"Arnold Lang",
    "wof:placetype":"venue"
},
  "geometry": {"coordinates":[8.5411643982,50.1173210144],"type":"Point"}
}