{
  "type": "Feature",
  "properties": {
    "iso:country":"DE",
    "sg:address":"Nieder-R\u00f6der-Str. 2",
    "sg:city":"Eppertshausen",
    "sg:phone":"+49 6071/31505",
    "sg:postcode":"64859",
    "sg:province":"Hessen",
    "wof:name":"Josef A. M\u00fcller",
    "wof:placetype":"venue"
},
  "geometry": {"coordinates":[8.8423652649,49.9478416443],"type":"Point"}
}