{
  "type": "Feature",
  "properties": {
    "iso:country":"DE",
    "sg:address":"Fr.-W.-Raiffeisen Strasse 6-8",
    "sg:city":"Reutlingen",
    "sg:phone":"+49 7121/9140",
    "sg:postcode":"72770",
    "sg:province":"Baden-W\u00fcrttemberg",
    "wof:name":"Der Maier - Online",
    "wof:placetype":"venue"
},
  "geometry": {"coordinates":[9.177243,48.499786],"type":"Point"}
}