{
  "type": "Feature",
  "properties": {
    "iso:country":"DE",
    "sg:address":"Volksdorfer Weg 142a",
    "sg:city":"Hamburg",
    "sg:phone":"+49 40/2196024",
    "sg:postcode":"22393",
    "sg:province":"Hamburg",
    "wof:name":"Bumann & Kobelius Ohg",
    "wof:placetype":"venue"
},
  "geometry": {"coordinates":[10.1176109314,53.6430091858],"type":"Point"}
}