{
  "type": "Feature",
  "properties": {
    "iso:country":"DE",
    "sg:address":"R\u00f6merstr. 72",
    "sg:city":"Gilching",
    "sg:phone":"+49 8105/1255",
    "sg:postcode":"82205",
    "sg:province":"Bayern",
    "wof:name":"Norma Lebensmittelfilial- Betrieb Gmbh & Co. Kg",
    "wof:placetype":"venue"
},
  "geometry": {"coordinates":[11.2948904037,48.1127929688],"type":"Point"}
}