{
  "type": "Feature",
  "properties": {
    "iso:country":"DE",
    "sg:address":"Schlo\u00dfstr. 5",
    "sg:city":"Wuppertal",
    "sg:phone":"+49 202/899732",
    "sg:postcode":"42285",
    "sg:province":"Nordrhein-Westfalen",
    "wof:name":"Datendistributionstechnologie",
    "wof:placetype":"venue"
},
  "geometry": {"coordinates":[7.17751,51.259907],"type":"Point"}
}