{
  "type": "Feature",
  "properties": {
    "iso:country":"DE",
    "sg:address":"Coldewehrstr. 3",
    "sg:city":"Krummh\u00f6rn",
    "sg:phone":"+49 4923/7116",
    "sg:postcode":"26736",
    "sg:province":"Niedersachsen",
    "wof:name":"Voss Verwaltungs- Und Beteiligungs- Gmbh",
    "wof:placetype":"venue"
},
  "geometry": {"coordinates":[7.10607,53.403671],"type":"Point"}
}