{
  "type": "Feature",
  "properties": {
    "iso:country":"DE",
    "sg:address":"Johannisstr. 31",
    "sg:city":"Weiden",
    "sg:phone":"+49 961/4050",
    "sg:postcode":"92637",
    "sg:province":"Bayern",
    "wof:name":"Genossenschaftsbank Weiden Eg",
    "wof:placetype":"venue"
},
  "geometry": {"coordinates":[12.156251,49.672729],"type":"Point"}
}