{
  "type": "Feature",
  "properties": {
    "iso:country":"DE",
    "sg:address":"M\u00fcnchner Stra\u00dfe 20",
    "sg:city":"Holzkirchen",
    "sg:phone":"+49 8024",
    "sg:postcode":"83607",
    "sg:province":"Bayern",
    "wof:name":"Adler-apotheke Holzkirchen",
    "wof:placetype":"venue"
},
  "geometry": {"coordinates":[11.699574,47.879917],"type":"Point"}
}