{
  "type": "Feature",
  "properties": {
    "iso:country":"DE",
    "sg:address":"Nu\u00dfbergstr. 22",
    "sg:city":"Schweinfurt",
    "sg:phone":"+49 9721/34002",
    "sg:postcode":"97422",
    "sg:province":"Bayern",
    "wof:name":"Anton Reichert",
    "wof:placetype":"venue"
},
  "geometry": {"coordinates":[10.2529802322,50.0737533569],"type":"Point"}
}