{
  "type": "Feature",
  "properties": {
    "iso:country":"DE",
    "sg:address":"K\u00e4the-Kruse-Weg 7",
    "sg:city":"Itzehoe",
    "sg:postcode":"25524",
    "sg:province":"Schleswig-Holstein",
    "wof:name":"Ibr Industrie- Und B\u00fcroreinigungsges. Mbh",
    "wof:placetype":"venue"
},
  "geometry": {"coordinates":[9.4924278259,53.9534797668],"type":"Point"}
}