{
  "type": "Feature",
  "properties": {
    "iso:country":"DE",
    "sg:address":"Adolf-Beermann-Str. 9",
    "sg:city":"V\u00f6hrenbach",
    "sg:phone":"+49 7727/1450",
    "sg:postcode":"78147",
    "sg:province":"Baden-W\u00fcrttemberg",
    "wof:name":"Stadtapotheke",
    "wof:placetype":"venue"
},
  "geometry": {"coordinates":[8.305306,48.044373],"type":"Point"}
}