{
  "type": "Feature",
  "properties": {
    "iso:country":"DE",
    "sg:address":"Gutenbergstr. 18",
    "sg:city":"Friesenheim",
    "sg:phone":"+49 7821/6064",
    "sg:postcode":"77948",
    "sg:province":"Baden-W\u00fcrttemberg",
    "wof:name":"Axel Zwach",
    "wof:placetype":"venue"
},
  "geometry": {"coordinates":[7.854764,48.391006],"type":"Point"}
}