{
  "type": "Feature",
  "properties": {
    "iso:country":"DE",
    "sg:address":"Freiburger Str. 54",
    "sg:city":"Mannheim",
    "sg:phone":"+49 621/479677",
    "sg:postcode":"68239",
    "sg:province":"Baden-W\u00fcrttemberg",
    "wof:name":"G\u00fcnter Frey",
    "wof:placetype":"venue"
},
  "geometry": {"coordinates":[8.5572738647,49.4643363953],"type":"Point"}
}