{
  "type": "Feature",
  "properties": {
    "iso:country":"DE",
    "sg:address":"Singoldstr. 2b",
    "sg:city":"Langerringen",
    "sg:phone":"+49 8248/90015",
    "sg:postcode":"86853",
    "sg:province":"Bayern",
    "wof:name":"Gerald H\u00f6fer Ingenieur",
    "wof:placetype":"venue"
},
  "geometry": {"coordinates":[10.7720680237,48.1062965393],"type":"Point"}
}