{
  "type": "Feature",
  "properties": {
    "iso:country":"DE",
    "sg:address":"Carl-Miele-Str. 14",
    "sg:city":"G\u00fctersloh",
    "sg:phone":"+49 4952/4115071",
    "sg:postcode":"33330",
    "sg:province":"Nordrhein-Westfalen",
    "wof:name":"Wilhelm Heuermann Gmbh & Co. Kg",
    "wof:placetype":"venue"
},
  "geometry": {"coordinates":[8.390753746,51.9124832153],"type":"Point"}
}