{
  "type": "Feature",
  "properties": {
    "iso:country":"DE",
    "sg:address":"Kaiserplatz 16",
    "sg:city":"D\u00fcren",
    "sg:phone":"+49 2421/15652",
    "sg:postcode":"52349",
    "sg:province":"Nordrhein-Westfalen",
    "wof:name":"Dieter Simons",
    "wof:placetype":"venue"
},
  "geometry": {"coordinates":[6.481400013,50.8022689819],"type":"Point"}
}