{
  "type": "Feature",
  "properties": {
    "iso:country":"DE",
    "sg:address":"Schneeberger Str. 82",
    "sg:city":"Aue",
    "sg:postcode":"08280",
    "sg:province":"Sachsen",
    "wof:name":"Katholisches Pfarramt Aue",
    "wof:placetype":"venue"
},
  "geometry": {"coordinates":[12.6907873154,50.5917854309],"type":"Point"}
}