{
  "type": "Feature",
  "properties": {
    "iso:country":"DE",
    "sg:address":"Roggenbachstr 1",
    "sg:city":"Villingen-Schwenningen",
    "sg:phone":"+49 7721/91750",
    "sg:postcode":"78050",
    "sg:province":"Baden-W\u00fcrttemberg",
    "wof:name":"Elsag Solutions Ag",
    "wof:placetype":"venue"
},
  "geometry": {"coordinates":[8.460033,48.050686],"type":"Point"}
}