{
  "type": "Feature",
  "properties": {
    "iso:country":"DE",
    "sg:address":"Konrad-Duden-Weg 12",
    "sg:city":"Frankfurt",
    "sg:phone":"+49 69/5071134",
    "sg:postcode":"60437",
    "sg:province":"Hessen",
    "wof:name":"Harald Meisert",
    "wof:placetype":"venue"
},
  "geometry": {"coordinates":[8.668381691,50.189868927],"type":"Point"}
}