{
  "type": "Feature",
  "properties": {
    "iso:country":"DE",
    "sg:address":"Brackweder Str. 33",
    "sg:city":"Halle",
    "sg:phone":"+49 5201/7541",
    "sg:postcode":"33790",
    "sg:province":"Nordrhein-Westfalen",
    "wof:name":"Werner Knetter Textilwaren",
    "wof:placetype":"venue"
},
  "geometry": {"coordinates":[8.390668869,52.040058136],"type":"Point"}
}