{
  "type": "Feature",
  "properties": {
    "iso:country":"DE",
    "sg:address":"Braunschweiger Str. 69",
    "sg:city":"Gifhorn",
    "sg:phone":"+49 5371/4051",
    "sg:postcode":"38518",
    "sg:province":"Niedersachsen",
    "wof:name":"B & B Gmbh",
    "wof:placetype":"venue"
},
  "geometry": {"coordinates":[10.5437374115,52.4743766785],"type":"Point"}
}