{
  "type": "Feature",
  "properties": {
    "iso:country":"DE",
    "sg:address":"Bahnhofplatz 1",
    "sg:city":"Bad Mergentheim",
    "sg:phone":"+49 7931",
    "sg:postcode":"97980",
    "sg:province":"Baden-W\u00fcrttemberg",
    "wof:name":"Life Coaching Gbr",
    "wof:placetype":"venue"
},
  "geometry": {"coordinates":[9.771968,49.493454],"type":"Point"}
}