{
  "type": "Feature",
  "properties": {
    "iso:country":"DE",
    "sg:address":"Pforzheimer Str. 105",
    "sg:city":"Bretten",
    "sg:phone":"+49 7252/5880",
    "sg:postcode":"75015",
    "sg:province":"Baden-W\u00fcrttemberg",
    "wof:name":"Federal-mogul Sealing Systems Bretten Verwaltungs Gmbh",
    "wof:placetype":"venue"
},
  "geometry": {"coordinates":[8.704097,49.028221],"type":"Point"}
}