{
  "type": "Feature",
  "properties": {
    "iso:country":"DE",
    "sg:address":"Pichlmayrstr. 25",
    "sg:city":"Rosenheim",
    "sg:phone":"+49 8031/30160",
    "sg:postcode":"83024",
    "sg:province":"Bayern",
    "wof:name":"Raab Karcher Baustoffe",
    "wof:placetype":"venue"
},
  "geometry": {"coordinates":[12.1076345444,47.8565864563],"type":"Point"}
}