{
  "type": "Feature",
  "properties": {
    "iso:country":"DE",
    "sg:address":"Fischersteige 8",
    "sg:city":"Kempten",
    "sg:phone":"+49 831/253820",
    "sg:postcode":"87435",
    "sg:province":"Bayern",
    "wof:name":"Orka Reisen Gmbh & Co. Kg",
    "wof:placetype":"venue"
},
  "geometry": {"coordinates":[10.3157949448,47.7260704041],"type":"Point"}
}