{
  "type": "Feature",
  "properties": {
    "iso:country":"DE",
    "sg:address":"Holzhofstr. 4",
    "sg:city":"Weilheim",
    "sg:phone":"+49 881/40422",
    "sg:postcode":"82362",
    "sg:province":"Bayern",
    "wof:name":"Gansneder Busreisen Kg",
    "wof:placetype":"venue"
},
  "geometry": {"coordinates":[11.1283388138,47.8340988159],"type":"Point"}
}