{
  "type": "Feature",
  "properties": {
    "iso:country":"DE",
    "sg:address":"Bahnhofstr. 19",
    "sg:city":"Duderstadt",
    "sg:phone":"+49 5527/73073",
    "sg:postcode":"37115",
    "sg:province":"Niedersachsen",
    "wof:name":"Nolte Fliesen Gmbh",
    "wof:placetype":"venue"
},
  "geometry": {"coordinates":[10.2528142929,51.5094299316],"type":"Point"}
}