{
  "type": "Feature",
  "properties": {
    "iso:country":"DE",
    "sg:address":"Neuenahrer Str. 1",
    "sg:city":"Bonn",
    "sg:phone":"+49 228/634415",
    "sg:postcode":"53115",
    "sg:province":"Nordrhein-Westfalen",
    "wof:name":"Jakob Niederberger Gro\u00dfbauten-reinigung Gmbh",
    "wof:placetype":"venue"
},
  "geometry": {"coordinates":[7.080160141,50.7304992676],"type":"Point"}
}