{
  "type": "Feature",
  "properties": {
    "iso:country":"DE",
    "sg:address":"Waldg\u00fcrtel 18",
    "sg:city":"Bergisch Gladbach",
    "sg:phone":"+49 2204/61809",
    "sg:postcode":"51427",
    "sg:province":"Nordrhein-Westfalen",
    "wof:name":"W. Schweigert Steuerberater",
    "wof:placetype":"venue"
},
  "geometry": {"coordinates":[7.1377491951,50.9584083557],"type":"Point"}
}