{
  "type": "Feature",
  "properties": {
    "iso:country":"DE",
    "sg:address":"Schlo\u00dfstr. 18",
    "sg:city":"Zusmarshausen",
    "sg:phone":"+49 8291/523",
    "sg:postcode":"86441",
    "sg:province":"Bayern",
    "wof:name":"Textilhaus St\u00f6rrle Gmbh & Co. Kg",
    "wof:placetype":"venue"
},
  "geometry": {"coordinates":[10.5962629318,48.3956985474],"type":"Point"}
}