{
  "type": "Feature",
  "properties": {
    "iso:country":"DE",
    "sg:address":"Sauterstr 5b",
    "sg:city":"Neustadt",
    "sg:phone":"+49 6321/35834",
    "sg:postcode":"67433",
    "sg:province":"Rheinland-Pfalz",
    "wof:name":"Gotthard Hellwig",
    "wof:placetype":"venue"
},
  "geometry": {"coordinates":[8.133089,49.355026],"type":"Point"}
}