{
  "type": "Feature",
  "properties": {
    "iso:country":"DE",
    "sg:address":"Klusberg 13",
    "sg:city":"Petershagen",
    "sg:phone":"+49 5768/265",
    "sg:postcode":"32469",
    "sg:province":"Nordrhein-Westfalen",
    "wof:name":"Christian Stadtl\u00e4nder Inh. Dietrich Stadtl\u00e4nder E.k.",
    "wof:placetype":"venue"
},
  "geometry": {"coordinates":[9.106347,52.468155],"type":"Point"}
}