{
  "type": "Feature",
  "properties": {
    "iso:country":"DE",
    "sg:address":"Lettenbachstr. 1 a",
    "sg:city":"Tussenhausen",
    "sg:phone":"+49 8268/1307",
    "sg:postcode":"86874",
    "sg:province":"Bayern",
    "wof:name":"Pankraz Jocham",
    "wof:placetype":"venue"
},
  "geometry": {"coordinates":[10.524848,48.110909],"type":"Point"}
}