{
  "type": "Feature",
  "properties": {
    "iso:country":"DE",
    "sg:address":"Marktplatz 11",
    "sg:city":"Norderstedt",
    "sg:phone":"+49 40/5251399",
    "sg:postcode":"22844",
    "sg:province":"Schleswig-Holstein",
    "wof:name":"C. Ringeling",
    "wof:placetype":"venue"
},
  "geometry": {"coordinates":[10.0080003738,53.7042312622],"type":"Point"}
}