{
  "type": "Feature",
  "properties": {
    "iso:country":"DE",
    "sg:address":"Im Schlage 1",
    "sg:city":"Ilsede",
    "sg:phone":"+49 5171/54878",
    "sg:postcode":"31241",
    "sg:province":"Niedersachsen",
    "wof:name":"H. Treumann",
    "wof:placetype":"venue"
},
  "geometry": {"coordinates":[10.227734,52.284752],"type":"Point"}
}