{
  "type": "Feature",
  "properties": {
    "iso:country":"DE",
    "sg:address":"D\u00fcrnauer Str. 42",
    "sg:city":"Boll",
    "sg:phone":"+49 7164/2761",
    "sg:postcode":"73087",
    "sg:province":"Baden-W\u00fcrttemberg",
    "wof:name":"Hermann Seitz",
    "wof:placetype":"venue"
},
  "geometry": {"coordinates":[9.6237516403,48.6390037537],"type":"Point"}
}