{
  "type": "Feature",
  "properties": {
    "iso:country":"DE",
    "sg:address":"Schl\u00fcsselstr. 1",
    "sg:city":"Neuenburg",
    "sg:phone":"+49 7631/72174",
    "sg:postcode":"79395",
    "sg:province":"Baden-W\u00fcrttemberg",
    "wof:name":"Pension Hedi Studer",
    "wof:placetype":"venue"
},
  "geometry": {"coordinates":[7.559484005,47.8141441345],"type":"Point"}
}