{
  "type": "Feature",
  "properties": {
    "iso:country":"DE",
    "sg:address":"Hochkamp 4",
    "sg:city":"Oststeinbek",
    "sg:phone":"+49 40/7132266",
    "sg:postcode":"22113",
    "sg:province":"Schleswig-Holstein",
    "wof:name":"Sport Student",
    "wof:placetype":"venue"
},
  "geometry": {"coordinates":[10.176285,53.543468],"type":"Point"}
}