{
  "type": "Feature",
  "properties": {
    "iso:country":"DE",
    "sg:address":"Georg-Kohl-Str. 1",
    "sg:city":"Brackenheim",
    "sg:phone":"+49 7135/6354",
    "sg:postcode":"74336",
    "sg:province":"Baden-W\u00fcrttemberg",
    "wof:name":"W. Kurz Heissmangel",
    "wof:placetype":"venue"
},
  "geometry": {"coordinates":[9.0672388077,49.0785255432],"type":"Point"}
}