{
  "type": "Feature",
  "properties": {
    "iso:country":"DE",
    "sg:address":"Farchacher Str. 5",
    "sg:city":"Berg",
    "sg:phone":"+49 8151/55120",
    "sg:postcode":"82335",
    "sg:province":"Bayern",
    "wof:name":"Kevin Fidler",
    "wof:placetype":"venue"
},
  "geometry": {"coordinates":[11.364749,47.956146],"type":"Point"}
}