{
  "type": "Feature",
  "properties": {
    "iso:country":"DE",
    "sg:address":"Aachener Str. 21",
    "sg:city":"W\u00fcrselen",
    "sg:phone":"+49 2405/21036",
    "sg:postcode":"52146",
    "sg:province":"Nordrhein-Westfalen",
    "wof:name":"M\u00f6bel Kuck Gmbh",
    "wof:placetype":"venue"
},
  "geometry": {"coordinates":[6.127016,50.823242],"type":"Point"}
}