{
  "type": "Feature",
  "properties": {
    "iso:country":"DE",
    "sg:address":"Kirchhellener Str. 149",
    "sg:city":"Oberhausen",
    "sg:phone":"+49 208/6102165",
    "sg:postcode":"46145",
    "sg:province":"Nordrhein-Westfalen",
    "wof:name":"Date Edv Und Telefonhandel Gmbh",
    "wof:placetype":"venue"
},
  "geometry": {"coordinates":[6.8683300018,51.5476303101],"type":"Point"}
}