{
  "type": "Feature",
  "properties": {
    "iso:country":"DE",
    "sg:address":"Franz\u00f6sische Str. 21",
    "sg:city":"Saarlouis",
    "sg:phone":"+49 6831/49313",
    "sg:postcode":"66740",
    "sg:province":"Saarland",
    "wof:name":"Barbara Und Gertrud Zapp Textil-einzelhandel",
    "wof:placetype":"venue"
},
  "geometry": {"coordinates":[6.7524552345,49.3144111633],"type":"Point"}
}