{
  "type": "Feature",
  "properties": {
    "iso:country":"DE",
    "sg:address":"Schillerplatz 6",
    "sg:city":"Zschopau",
    "sg:phone":"+49 3725/81243",
    "sg:postcode":"09405",
    "sg:province":"Sachsen",
    "wof:name":"Augustin Inh. M. Schmiedel",
    "wof:placetype":"venue"
},
  "geometry": {"coordinates":[13.0692949295,50.7492790222],"type":"Point"}
}