{
  "type": "Feature",
  "properties": {
    "iso:country":"DE",
    "sg:address":"Gru\u00dfdorfstr. 19",
    "sg:city":"Berlin",
    "sg:phone":"+49 30/4337219",
    "sg:postcode":"13507",
    "sg:province":"Berlin",
    "wof:name":"Woll Chritel",
    "wof:placetype":"venue"
},
  "geometry": {"coordinates":[13.287519,52.588692],"type":"Point"}
}