{
  "type": "Feature",
  "properties": {
    "iso:country":"DE",
    "sg:address":"Aachener Str. 72",
    "sg:city":"K\u00f6ln",
    "sg:phone":"+49 221/561219",
    "sg:postcode":"50674",
    "sg:province":"Nordrhein-Westfalen",
    "wof:name":"Pizzeria Pinocchio",
    "wof:placetype":"venue"
},
  "geometry": {"coordinates":[6.9331498146,50.9366722107],"type":"Point"}
}