{
  "type": "Feature",
  "properties": {
    "iso:country":"DE",
    "sg:address":"Bussmannsweg 14",
    "sg:city":"Warendorf",
    "sg:phone":"+49 4925/819440",
    "sg:postcode":"48231",
    "sg:province":"Nordrhein-Westfalen",
    "wof:name":"Freckenhorster Werkst\u00c4tten",
    "wof:placetype":"venue"
},
  "geometry": {"coordinates":[7.953341,51.92292],"type":"Point"}
}