{
  "type": "Feature",
  "properties": {
    "iso:country":"DE",
    "sg:address":"Provinzialstr. 57",
    "sg:city":"Saarbr\u00fccken",
    "sg:phone":"+49 6898/82650",
    "sg:postcode":"66126",
    "sg:province":"Saarland",
    "wof:name":"Pizzeria Da Carlo",
    "wof:placetype":"venue"
},
  "geometry": {"coordinates":[6.9147481918,49.2465782166],"type":"Point"}
}