{
  "type": "Feature",
  "properties": {
    "iso:country":"DE",
    "sg:address":"Lilienstr. 8",
    "sg:city":"Solingen",
    "sg:phone":"+49 212/314848",
    "sg:postcode":"42719",
    "sg:province":"Nordrhein-Westfalen",
    "wof:name":"Lenk & Holz Elektrotechnik Gmbh",
    "wof:placetype":"venue"
},
  "geometry": {"coordinates":[7.041799,51.179489],"type":"Point"}
}