{
  "type": "Feature",
  "properties": {
    "iso:country":"DE",
    "sg:address":"Sudholzstr. 1",
    "sg:city":"Bochum",
    "sg:phone":"+49 2327/72791",
    "sg:postcode":"44869",
    "sg:province":"Nordrhein-Westfalen",
    "wof:name":"M. P\u00f6chhacker",
    "wof:placetype":"venue"
},
  "geometry": {"coordinates":[7.159265995,51.444316864],"type":"Point"}
}