{
  "type": "Feature",
  "properties": {
    "iso:country":"DE",
    "sg:address":"Philipp-Merck-Weg 7",
    "sg:city":"Bensheim",
    "sg:phone":"+49 6251/680292",
    "sg:postcode":"64625",
    "sg:province":"Hessen",
    "wof:name":"R\u00f6sch Ingenieur",
    "wof:placetype":"venue"
},
  "geometry": {"coordinates":[8.609793663,49.6738433838],"type":"Point"}
}