{
  "type": "Feature",
  "properties": {
    "iso:country":"DE",
    "sg:address":"Osterburger Str. 97",
    "sg:city":"Stendal",
    "sg:phone":"+49 3931/213607",
    "sg:postcode":"39576",
    "sg:province":"Sachsen-Anhalt",
    "wof:name":"Hagen B\u00f6hme",
    "wof:placetype":"venue"
},
  "geometry": {"coordinates":[11.848521,52.612556],"type":"Point"}
}