{
  "type": "Feature",
  "properties": {
    "iso:country":"DE",
    "sg:address":"St\u00fcckenstr. 1-3",
    "sg:city":"Hamburg",
    "sg:phone":"+49 40/299000",
    "sg:postcode":"22081",
    "sg:province":"Hamburg",
    "wof:name":"Litton Marine Systems Gmbh & Co. Kg",
    "wof:placetype":"venue"
},
  "geometry": {"coordinates":[10.043978,53.581528],"type":"Point"}
}