{
  "type": "Feature",
  "properties": {
    "iso:country":"DE",
    "sg:address":"Mahlumer Str. 17a",
    "sg:city":"Bockenem",
    "sg:phone":"+49 5067/1626",
    "sg:postcode":"31167",
    "sg:province":"Niedersachsen",
    "wof:name":"Freibad",
    "wof:placetype":"venue"
},
  "geometry": {"coordinates":[10.1552820206,52.0018882751],"type":"Point"}
}