{
  "type": "Feature",
  "properties": {
    "iso:country":"DE",
    "sg:address":"Nonnbornstr. 17",
    "sg:city":"Kelkheim",
    "sg:phone":"+49 6195/73282",
    "sg:postcode":"65779",
    "sg:province":"Hessen",
    "wof:name":"Taunusclub M\u00fcnster E. V. Karlheinz Wittwer",
    "wof:placetype":"venue"
},
  "geometry": {"coordinates":[8.4596509933,50.1255302429],"type":"Point"}
}