{
  "type": "Feature",
  "properties": {
    "iso:country":"DE",
    "sg:address":"Zwischen\u00e4ckerle 73",
    "sg:city":"Backnang",
    "sg:phone":"+49 7191/83759",
    "sg:postcode":"71522",
    "sg:province":"Baden-W\u00fcrttemberg",
    "wof:name":"Bauphysik 5",
    "wof:placetype":"venue"
},
  "geometry": {"coordinates":[9.4360666275,48.949508667],"type":"Point"}
}