{
  "type": "Feature",
  "properties": {
    "iso:country":"DE",
    "sg:address":"Nikolaistr. 1",
    "sg:city":"Rosenheim",
    "sg:phone":"+49 8031/14489",
    "sg:postcode":"83022",
    "sg:province":"Bayern",
    "wof:name":"Brigitte Huster Krankengymnastin",
    "wof:placetype":"venue"
},
  "geometry": {"coordinates":[12.127436,47.85635],"type":"Point"}
}