{
  "type": "Feature",
  "properties": {
    "iso:country":"DE",
    "sg:address":"Poststr.",
    "sg:city":"Troisdorf",
    "sg:phone":"+49 2241/75036",
    "sg:postcode":"53840",
    "sg:province":"Nordrhein-Westfalen",
    "wof:name":"Deutsche Bahn Ag",
    "wof:placetype":"venue"
},
  "geometry": {"coordinates":[7.1498851776,50.8147392273],"type":"Point"}
}