{
  "type": "Feature",
  "properties": {
    "iso:country":"DE",
    "sg:address":"Marktstr. 6",
    "sg:city":"Wolfenb\u00fcttel",
    "sg:phone":"+49 5331/33704",
    "sg:postcode":"38300",
    "sg:province":"Niedersachsen",
    "wof:name":"Goldener L\u00f6we",
    "wof:placetype":"venue"
},
  "geometry": {"coordinates":[10.5456018448,52.1628684998],"type":"Point"}
}