{
  "type": "Feature",
  "properties": {
    "iso:country":"DE",
    "sg:address":"Buschm\u00fchlenweg 3",
    "sg:city":"Frankfurt",
    "sg:phone":"+49 335/533940",
    "sg:postcode":"15230",
    "sg:province":"Brandenburg",
    "wof:name":"Abh Consulting Gmbh",
    "wof:placetype":"venue"
},
  "geometry": {"coordinates":[14.5533638,52.3321075439],"type":"Point"}
}