{
  "type": "Feature",
  "properties": {
    "iso:country":"DE",
    "sg:address":"Schumannstr. 3",
    "sg:city":"Duisburg",
    "sg:phone":"+49 2151/40191",
    "sg:postcode":"47239",
    "sg:province":"Nordrhein-Westfalen",
    "wof:name":"Frankfurter Allianz Versicherung",
    "wof:placetype":"venue"
},
  "geometry": {"coordinates":[6.6533818245,51.4040222168],"type":"Point"}
}