{
  "type": "Feature",
  "properties": {
    "iso:country":"DE",
    "sg:address":"Dehmer Str. 33a",
    "sg:city":"Bad Oeynhausen",
    "sg:phone":"+49 5731/751280",
    "sg:postcode":"32549",
    "sg:province":"Nordrhein-Westfalen",
    "wof:name":"Heise Gmbh",
    "wof:placetype":"venue"
},
  "geometry": {"coordinates":[8.82308,52.226105],"type":"Point"}
}