{
  "type": "Feature",
  "properties": {
    "iso:country":"DE",
    "sg:address":"Bergstra\u00dfe 230",
    "sg:city":"Bochum",
    "sg:phone":"+49 234",
    "sg:postcode":"44807",
    "sg:province":"Nordrhein-Westfalen",
    "wof:name":"Planungsb\u00fcro Borgmann",
    "wof:placetype":"venue"
},
  "geometry": {"coordinates":[7.2246289253,51.5001564026],"type":"Point"}
}