{
  "type": "Feature",
  "properties": {
    "iso:country":"DE",
    "sg:address":"Nassauische Str. 26",
    "sg:city":"Burbach",
    "sg:phone":"+49 2736/6850",
    "sg:postcode":"57299",
    "sg:province":"Nordrhein-Westfalen",
    "wof:name":"Harald Diehl",
    "wof:placetype":"venue"
},
  "geometry": {"coordinates":[8.0790376663,50.7469863892],"type":"Point"}
}