{
  "type": "Feature",
  "properties": {
    "iso:country":"DE",
    "sg:address":"Ackerstr. 1 A",
    "sg:city":"Dessau",
    "sg:phone":"+49 340/260670",
    "sg:postcode":"06842",
    "sg:province":"Sachsen-Anhalt",
    "wof:name":"Rumph Und B\u00fcttner Rechtsanw\u00e4lte",
    "wof:placetype":"venue"
},
  "geometry": {"coordinates":[12.2431650162,51.821269989],"type":"Point"}
}