{
  "type": "Feature",
  "properties": {
    "iso:country":"DE",
    "sg:address":"Kilstetter Str. 33",
    "sg:city":"Berlin",
    "sg:phone":"+49 30/8112753",
    "sg:postcode":"14167",
    "sg:province":"Berlin",
    "wof:name":"B\u00e4renschenke",
    "wof:placetype":"venue"
},
  "geometry": {"coordinates":[13.2728281021,52.4349975586],"type":"Point"}
}