{
  "type": "Feature",
  "properties": {
    "iso:country":"DE",
    "sg:address":"Gneisenaustr. 20",
    "sg:city":"W\u00fcrzburg",
    "sg:phone":"+49 931/79400",
    "sg:postcode":"97074",
    "sg:province":"Bayern",
    "wof:name":"Aeg Ag",
    "wof:placetype":"venue"
},
  "geometry": {"coordinates":[9.957775116,49.7962684631],"type":"Point"}
}