{
  "type": "Feature",
  "properties": {
    "iso:country":"DE",
    "sg:address":"Holtenauer Str. 45a",
    "sg:city":"Kiel",
    "sg:phone":"+49 431/566003",
    "sg:postcode":"24105",
    "sg:province":"Schleswig-Holstein",
    "wof:name":"Stern-apotheke",
    "wof:placetype":"venue"
},
  "geometry": {"coordinates":[10.1319522858,54.331993103],"type":"Point"}
}