{
  "type": "Feature",
  "properties": {
    "iso:country":"DE",
    "sg:address":"Zum S\u00fc\u00dfen Grund 4",
    "sg:city":"Ratzeburg",
    "sg:phone":"+49 4541/870642",
    "sg:postcode":"23909",
    "sg:province":"Schleswig-Holstein",
    "wof:name":"Pro Secura Versicherungsmarkler",
    "wof:placetype":"venue"
},
  "geometry": {"coordinates":[10.7689971924,53.699306488],"type":"Point"}
}