{
  "type": "Feature",
  "properties": {
    "iso:country":"DE",
    "sg:address":"Dr.-Gustav-Schickedanz-Str. 7",
    "sg:city":"Hersbruck",
    "sg:phone":"+49 9151/70042",
    "sg:postcode":"91217",
    "sg:province":"Bayern",
    "wof:name":"U. Foerster Und D. Mogge Masseure",
    "wof:placetype":"venue"
},
  "geometry": {"coordinates":[11.432871,49.507919],"type":"Point"}
}