{
  "type": "Feature",
  "properties": {
    "iso:country":"DE",
    "sg:address":"Max-Planck-Str. 8",
    "sg:city":"Walldorf",
    "sg:phone":"+49 6227/819555",
    "sg:postcode":"69190",
    "sg:province":"Baden-W\u00fcrttemberg",
    "wof:name":"Fancourt Flugcharter Verwaltungs- Gmbh",
    "wof:placetype":"venue"
},
  "geometry": {"coordinates":[8.645463,49.287651],"type":"Point"}
}