{
  "type": "Feature",
  "properties": {
    "iso:country":"DE",
    "sg:address":"Heinrich-Hertz-Str. 4",
    "sg:city":"Erkrath",
    "sg:postcode":"40699",
    "sg:province":"Nordrhein-Westfalen",
    "wof:name":"Ost Video Handels Gmbh",
    "wof:placetype":"venue"
},
  "geometry": {"coordinates":[6.9144501686,51.198589325],"type":"Point"}
}