{
  "type": "Feature",
  "properties": {
    "iso:country":"DE",
    "sg:address":"Albert-Einstein-Str. 61",
    "sg:city":"Aachen",
    "sg:phone":"+49 2408/80051",
    "sg:postcode":"52076",
    "sg:province":"Nordrhein-Westfalen",
    "wof:name":"Peter Duggen & Partner Ingenieurgesellschaft Mbh",
    "wof:placetype":"venue"
},
  "geometry": {"coordinates":[6.1761832237,50.7088165283],"type":"Point"}
}