{
  "type": "Feature",
  "properties": {
    "iso:country":"DE",
    "sg:address":"Am Berge 4",
    "sg:city":"Eyendorf",
    "sg:phone":"+49 4172/6299",
    "sg:postcode":"21376",
    "sg:province":"Niedersachsen",
    "wof:name":"Tina Stobbe-auen Heilpraktikerin",
    "wof:placetype":"venue"
},
  "geometry": {"coordinates":[10.1558408737,53.2048530579],"type":"Point"}
}