{
  "type": "Feature",
  "properties": {
    "iso:country":"DE",
    "sg:address":"Bad Mergentheimer Str. 5",
    "sg:city":"Creglingen",
    "sg:phone":"+49 7933/567",
    "sg:postcode":"97993",
    "sg:province":"Baden-W\u00fcrttemberg",
    "wof:name":"Walter Zink Architekt",
    "wof:placetype":"venue"
},
  "geometry": {"coordinates":[10.030588,49.471443],"type":"Point"}
}