{
  "type": "Feature",
  "properties": {
    "iso:country":"DE",
    "sg:address":"Horresser Berg 1",
    "sg:city":"Montabaur",
    "sg:phone":"+49 2602/92130",
    "sg:postcode":"56410",
    "sg:province":"Rheinland-Pfalz",
    "wof:name":"R. Cegla Gmbh & Co. Kg",
    "wof:placetype":"venue"
},
  "geometry": {"coordinates":[7.806474,50.434818],"type":"Point"}
}