{
  "type": "Feature",
  "properties": {
    "iso:country":"DE",
    "sg:address":"Biergasse 1",
    "sg:city":"Buggingen",
    "sg:phone":"+49 7631/798440",
    "sg:postcode":"79426",
    "sg:province":"Baden-W\u00fcrttemberg",
    "wof:name":"M. H\u00e4mmerlin",
    "wof:placetype":"venue"
},
  "geometry": {"coordinates":[7.638775,47.847366],"type":"Point"}
}