{
  "type": "Feature",
  "properties": {
    "iso:country":"DE",
    "sg:address":"Max-Reger-Weg 35",
    "sg:city":"Wendelstein",
    "sg:phone":"+49 9129/27296",
    "sg:postcode":"90530",
    "sg:province":"Bayern",
    "wof:name":"M. Streber Wachdienst",
    "wof:placetype":"venue"
},
  "geometry": {"coordinates":[11.1582450867,49.3484649658],"type":"Point"}
}