{
  "type": "Feature",
  "properties": {
    "iso:country":"DE",
    "sg:address":"Lerchenstr. 25",
    "sg:city":"Pohlheim",
    "sg:phone":"+49 6404/65301",
    "sg:postcode":"35415",
    "sg:province":"Hessen",
    "wof:name":"H. Platz Immobilienmakler",
    "wof:placetype":"venue"
},
  "geometry": {"coordinates":[8.7533740997,50.5069351196],"type":"Point"}
}