{
  "type": "Feature",
  "properties": {
    "iso:country":"DE",
    "sg:address":"Alte Heerstr. 21",
    "sg:city":"Georgsmarienh\u00fctte",
    "sg:phone":"+49 5401/86990",
    "sg:postcode":"49124",
    "sg:province":"Niedersachsen",
    "wof:name":"Maler Tiesmeyer Gmbh",
    "wof:placetype":"venue"
},
  "geometry": {"coordinates":[8.08307,52.2201],"type":"Point"}
}