{
  "type": "Feature",
  "properties": {
    "iso:country":"DE",
    "sg:address":"Wilhelm-Busch-Weg 60",
    "sg:city":"Ganderkesee",
    "sg:phone":"+49 4222/6885",
    "sg:postcode":"27777",
    "sg:province":"Niedersachsen",
    "wof:name":"Matthias Jopen Immobilienmakler",
    "wof:placetype":"venue"
},
  "geometry": {"coordinates":[8.5379905701,53.0418777466],"type":"Point"}
}