{
  "type": "Feature",
  "properties": {
    "iso:country":"DE",
    "sg:address":"Opm Blockhorn 2b",
    "sg:city":"Schenefeld",
    "sg:phone":"+49 40/8307508",
    "sg:postcode":"22869",
    "sg:province":"Schleswig-Holstein",
    "wof:name":"Doris Birr Drogerie",
    "wof:placetype":"venue"
},
  "geometry": {"coordinates":[9.832388,53.599369],"type":"Point"}
}