{
  "type": "Feature",
  "properties": {
    "iso:country":"DE",
    "sg:address":"Hohreuschstr. 38",
    "sg:city":"Winnenden",
    "sg:phone":"+49 7195/178587",
    "sg:postcode":"71364",
    "sg:province":"Baden-W\u00fcrttemberg",
    "wof:name":"Wilhelm G\u00f6tz Berufskleiderfabrikation",
    "wof:placetype":"venue"
},
  "geometry": {"coordinates":[9.39017,48.873081],"type":"Point"}
}