{
  "type": "Feature",
  "properties": {
    "iso:country":"DE",
    "sg:address":"Industriestr. 55-57",
    "sg:city":"Rheine",
    "sg:postcode":"48432",
    "sg:province":"Nordrhein-Westfalen",
    "wof:name":"Natura Verpackungsges. Mbh",
    "wof:placetype":"venue"
},
  "geometry": {"coordinates":[7.4910402298,52.2192192078],"type":"Point"}
}