{
  "type": "Feature",
  "properties": {
    "iso:country":"DE",
    "sg:address":"Bleichstr. 7",
    "sg:city":"Hanau",
    "sg:phone":"+49 6181/92241",
    "sg:postcode":"63450",
    "sg:province":"Hessen",
    "wof:name":"Visual Design Viktor Diebold",
    "wof:placetype":"venue"
},
  "geometry": {"coordinates":[8.910984993,50.1347427368],"type":"Point"}
}