{
  "type": "Feature",
  "properties": {
    "iso:country":"DE",
    "sg:address":"Hubertusweg 14",
    "sg:city":"Taunusstein",
    "sg:phone":"+49 6128/43186",
    "sg:postcode":"65232",
    "sg:province":"Hessen",
    "wof:name":"Edgar Keiper Gmbh",
    "wof:placetype":"venue"
},
  "geometry": {"coordinates":[8.123018,50.128464],"type":"Point"}
}