{
  "type": "Feature",
  "properties": {
    "iso:country":"DE",
    "sg:address":"Proskauer Str. 36",
    "sg:city":"Berlin",
    "sg:postcode":"10247",
    "sg:province":"Berlin",
    "wof:name":"Asia Star Handels Gmbh",
    "wof:placetype":"venue"
},
  "geometry": {"coordinates":[13.4603786469,52.5161552429],"type":"Point"}
}