{
  "type": "Feature",
  "properties": {
    "iso:country":"DE",
    "sg:address":"Haskamp 5",
    "sg:city":"Hagen",
    "sg:phone":"+49 5401/99290",
    "sg:postcode":"49170",
    "sg:province":"Niedersachsen",
    "wof:name":"Osma-technik Albert Schenk Gmbh & Co. Kg",
    "wof:placetype":"venue"
},
  "geometry": {"coordinates":[7.9836478233,52.1957206726],"type":"Point"}
}