{
  "type": "Feature",
  "properties": {
    "iso:country":"DE",
    "sg:address":"Elsflether Str. 1",
    "sg:city":"Delmenhorst",
    "sg:postcode":"27751",
    "sg:province":"Niedersachsen",
    "wof:name":"Lvs \u00dcnsa Gmbh",
    "wof:placetype":"venue"
},
  "geometry": {"coordinates":[8.644096,53.064632],"type":"Point"}
}