{
  "type": "Feature",
  "properties": {
    "iso:country":"DE",
    "sg:city":"Armstedt",
    "sg:phone":"+49 4324/223",
    "sg:postcode":"24616",
    "sg:province":"Schleswig-Holstein",
    "wof:name":"Heinzis Disco",
    "wof:placetype":"venue"
},
  "geometry": {"coordinates":[9.849428,53.968575],"type":"Point"}
}