{
  "type": "Feature",
  "properties": {
    "iso:country":"DE",
    "sg:address":"Max-Planck-Str. 38",
    "sg:city":"Seligenstadt",
    "sg:phone":"+49 6182/60573",
    "sg:postcode":"63500",
    "sg:province":"Hessen",
    "wof:name":"Margot Haberer",
    "wof:placetype":"venue"
},
  "geometry": {"coordinates":[8.939406395,50.0515136719],"type":"Point"}
}