{
  "type": "Feature",
  "properties": {
    "iso:country":"DE",
    "sg:address":"Giflitzer Str. 3",
    "sg:city":"Edertal",
    "sg:phone":"+49 5623/1711",
    "sg:postcode":"34549",
    "sg:province":"Hessen",
    "wof:name":"Willi Wende",
    "wof:placetype":"venue"
},
  "geometry": {"coordinates":[9.113701,51.162144],"type":"Point"}
}