{
  "type": "Feature",
  "properties": {
    "iso:country":"DE",
    "sg:address":"Schmiedbergstr. 5",
    "sg:city":"F\u00fcrstenzell",
    "sg:phone":"+49 8506/455",
    "sg:postcode":"94081",
    "sg:province":"Bayern",
    "wof:name":"Bernstein Museum Bad F\u00fcssing",
    "wof:placetype":"venue"
},
  "geometry": {"coordinates":[13.356124,48.476707],"type":"Point"}
}