{
  "type": "Feature",
  "properties": {
    "iso:country":"DE",
    "sg:address":"Sande::",
    "sg:city":"Paderborn",
    "sg:phone":"+49 4421/70406",
    "sg:postcode":"26452",
    "sg:province":"Niedersachsen",
    "wof:name":"Raiffeisenbank Sande-wangerland Eg",
    "wof:placetype":"venue"
},
  "geometry": {"coordinates":[7.99683,53.493568],"type":"Point"}
}