{
  "type": "Feature",
  "properties": {
    "iso:country":"DE",
    "sg:address":"Brandkuhle 4",
    "sg:city":"S\u00fcderl\u00fcgum",
    "sg:phone":"+49 4663/1627",
    "sg:postcode":"25923",
    "sg:province":"Schleswig-Holstein",
    "wof:name":"Udo Meyer Rechtsanwalt",
    "wof:placetype":"venue"
},
  "geometry": {"coordinates":[8.9097709656,54.870677948],"type":"Point"}
}