{
  "type": "Feature",
  "properties": {
    "iso:country":"DE",
    "sg:address":"Sybelstr. 53",
    "sg:city":"Berlin",
    "sg:phone":"+49 30/3233439",
    "sg:postcode":"10629",
    "sg:province":"Berlin",
    "wof:name":"Dietrich Otto Architekt",
    "wof:placetype":"venue"
},
  "geometry": {"coordinates":[13.304868,52.501865],"type":"Point"}
}