{
  "type": "Feature",
  "properties": {
    "iso:country":"DE",
    "sg:address":"Wientapperweg 16 D",
    "sg:city":"Hamburg",
    "sg:phone":"+49 40/875354",
    "sg:postcode":"22589",
    "sg:province":"Hamburg",
    "wof:name":"Christfried Beutel Architekt",
    "wof:placetype":"venue"
},
  "geometry": {"coordinates":[9.832509,53.571873],"type":"Point"}
}