{
  "type": "Feature",
  "properties": {
    "iso:country":"DE",
    "sg:address":"K\u00f6nigsberger Str. 41",
    "sg:city":"Quierschied",
    "sg:phone":"+49 6897/62821",
    "sg:postcode":"66287",
    "sg:province":"Saarland",
    "wof:name":"Michael Zimmermann Heilpraktiker",
    "wof:placetype":"venue"
},
  "geometry": {"coordinates":[7.0593419075,49.3338165283],"type":"Point"}
}