{
  "type": "Feature",
  "properties": {
    "iso:country":"DE",
    "sg:address":"Moritz-Fischer-Str. 2",
    "sg:city":"Schwebheim",
    "sg:phone":"+49 9723/7447",
    "sg:postcode":"97525",
    "sg:province":"Bayern",
    "wof:name":"Taifun-teppich-service Tts Gmbh",
    "wof:placetype":"venue"
},
  "geometry": {"coordinates":[10.247782,49.987473],"type":"Point"}
}