{
  "type": "Feature",
  "properties": {
    "iso:country":"DE",
    "sg:address":"Mandrystr. 9",
    "sg:city":"Heilbronn",
    "sg:phone":"+49 7131/175296",
    "sg:postcode":"74074",
    "sg:province":"Baden-W\u00fcrttemberg",
    "wof:name":"Verein Der Freunde Des M\u00f6nchsee-gymnasiums E. V.",
    "wof:placetype":"venue"
},
  "geometry": {"coordinates":[9.2427368164,49.1371421814],"type":"Point"}
}