{
  "type": "Feature",
  "properties": {
    "iso:country":"DE",
    "sg:address":"Am Bahnhof 3",
    "sg:city":"Neubrandenburg",
    "sg:phone":"+49 395/5661822",
    "sg:postcode":"17033",
    "sg:province":"Mecklenburg-Vorpommern",
    "wof:name":"Gfb Gesellschaft F\u00fcr Bustouristik Mbh",
    "wof:placetype":"venue"
},
  "geometry": {"coordinates":[13.2617454529,53.5610618591],"type":"Point"}
}