{
  "type": "Feature",
  "properties": {
    "iso:country":"DE",
    "sg:address":"49448",
    "sg:city":"Lemf\u00f6rde",
    "sg:phone":"+49 5443/312",
    "sg:postcode":"49448",
    "sg:province":"Niedersachsen",
    "wof:name":"Deutsche Bahn Ag",
    "wof:placetype":"venue"
},
  "geometry": {"coordinates":[8.4010000229,52.4873199463],"type":"Point"}
}