{
  "type": "Feature",
  "properties": {
    "iso:country":"DE",
    "sg:address":"Schwalbenweg 4",
    "sg:city":"Altenkirchen",
    "sg:phone":"+49 2681/95140",
    "sg:postcode":"57610",
    "sg:province":"Rheinland-Pfalz",
    "wof:name":"Stanit Staats Brandschutz Gmbh",
    "wof:placetype":"venue"
},
  "geometry": {"coordinates":[7.6422719955,50.690071106],"type":"Point"}
}