{
  "type": "Feature",
  "properties": {
    "iso:country":"DE",
    "sg:address":"Fillastr. 8",
    "sg:city":"Meppen",
    "sg:phone":"+49 5931/3027",
    "sg:postcode":"49716",
    "sg:province":"Niedersachsen",
    "wof:name":"Georg Ull Gmbh",
    "wof:placetype":"venue"
},
  "geometry": {"coordinates":[7.3486790657,52.7037887573],"type":"Point"}
}