{
  "type": "Feature",
  "properties": {
    "iso:country":"DE",
    "sg:address":"Im Greut 33",
    "sg:city":"Rottenburg",
    "sg:phone":"+49 7472/41414",
    "sg:postcode":"72108",
    "sg:province":"Baden-W\u00fcrttemberg",
    "wof:name":"Joachim Frauz",
    "wof:placetype":"venue"
},
  "geometry": {"coordinates":[8.9307489395,48.4693145752],"type":"Point"}
}