{
  "type": "Feature",
  "properties": {
    "iso:country":"DE",
    "sg:address":"Landstr. 1",
    "sg:city":"Katlenburg-Lindau",
    "sg:phone":"+49 5552/7468",
    "sg:postcode":"37191",
    "sg:province":"Niedersachsen",
    "wof:name":"Flow Test Gmbh",
    "wof:placetype":"venue"
},
  "geometry": {"coordinates":[10.1142148972,51.68384552],"type":"Point"}
}