{
  "type": "Feature",
  "properties": {
    "iso:country":"DE",
    "sg:address":"M\u00e4rkische Str. 82 a",
    "sg:city":"Dortmund",
    "sg:phone":"+49 231/95880",
    "sg:postcode":"44141",
    "sg:province":"Nordrhein-Westfalen",
    "wof:name":"Sch\u00f6ler & Micke Sportartikel Vertriebsges. Mbh",
    "wof:placetype":"venue"
},
  "geometry": {"coordinates":[7.4757208824,51.5049858093],"type":"Point"}
}