{
  "type": "Feature",
  "properties": {
    "iso:country":"DE",
    "sg:address":"hackerstr.5",
    "sg:city":"berlin",
    "sg:postcode":"12161",
    "sg:province":"Berlin",
    "wof:name":"Sell-out",
    "wof:placetype":"venue"
},
  "geometry": {"coordinates":[13.3246088028,52.4662437439],"type":"Point"}
}