{
  "type": "Feature",
  "properties": {
    "iso:country":"DE",
    "sg:address":"Ludolfstr. 10",
    "sg:city":"Trier",
    "sg:phone":"+49 651/31132",
    "sg:postcode":"54290",
    "sg:province":"Rheinland-Pfalz",
    "wof:name":"P. Greif",
    "wof:placetype":"venue"
},
  "geometry": {"coordinates":[6.63427,49.738838],"type":"Point"}
}