{
  "type": "Feature",
  "properties": {
    "iso:country":"DE",
    "sg:address":"Bahnhofstra\u00dfe 21",
    "sg:city":"Osterfeld",
    "sg:phone":"+49 34422/22946",
    "sg:postcode":"06721",
    "sg:province":"Sachsen-Anhalt",
    "wof:name":"Pollm\u00e4cher Steinmetz",
    "wof:placetype":"venue"
},
  "geometry": {"coordinates":[11.920498,51.074509],"type":"Point"}
}