{
  "type": "Feature",
  "properties": {
    "iso:country":"DE",
    "sg:address":"Deutscher Rg. 30",
    "sg:city":"Wuppertal",
    "sg:phone":"+49 4920/274980",
    "sg:postcode":"42307",
    "sg:province":"Nordrhein-Westfalen",
    "wof:name":"Schenker Deutschland Ag",
    "wof:placetype":"venue"
},
  "geometry": {"coordinates":[7.1965498924,51.2715606689],"type":"Point"}
}