{
  "type": "Feature",
  "properties": {
    "iso:country":"DE",
    "sg:address":"Hochstr. 22",
    "sg:city":"Mandelbachtal",
    "sg:postcode":"66399",
    "sg:province":"Saarland",
    "wof:name":"Rosemarie Pilger Heilpraktikerin",
    "wof:placetype":"venue"
},
  "geometry": {"coordinates":[7.1574101448,49.2219734192],"type":"Point"}
}