{
  "type": "Feature",
  "properties": {
    "iso:country":"DE",
    "sg:address":"Neubertstr. 31",
    "sg:city":"Hamburg",
    "sg:phone":"+49 40/2507493",
    "sg:postcode":"22087",
    "sg:province":"Hamburg",
    "wof:name":"Heinz M\u00fcller Rechtsanwalt",
    "wof:placetype":"venue"
},
  "geometry": {"coordinates":[10.0294847488,53.5626411438],"type":"Point"}
}