{
  "type": "Feature",
  "properties": {
    "iso:country":"DE",
    "sg:address":"Sieler Weg 4",
    "sg:city":"Enger",
    "sg:phone":"+49 5224/3074",
    "sg:postcode":"32130",
    "sg:province":"Nordrhein-Westfalen",
    "wof:name":"Wilfried Stork",
    "wof:placetype":"venue"
},
  "geometry": {"coordinates":[8.556101,52.146366],"type":"Point"}
}