{
  "type": "Feature",
  "properties": {
    "iso:country":"DE",
    "sg:address":"Markt 9",
    "sg:city":"Wildberg",
    "sg:phone":"+49 33928/70339",
    "sg:postcode":"16845",
    "sg:province":"Brandenburg",
    "wof:name":"Am Markt",
    "wof:placetype":"venue"
},
  "geometry": {"coordinates":[12.631524086,52.8760528564],"type":"Point"}
}