{
  "type": "Feature",
  "properties": {
    "iso:country":"DE",
    "sg:address":"Schlo\u00dfstr. 22",
    "sg:city":"Gro\u00dfenhain",
    "sg:phone":"+49 3522/37378",
    "sg:postcode":"01558",
    "sg:province":"Sachsen",
    "wof:name":"H. Feske",
    "wof:placetype":"venue"
},
  "geometry": {"coordinates":[13.5317878723,51.2903327942],"type":"Point"}
}