{
  "type": "Feature",
  "properties": {
    "iso:country":"DE",
    "sg:address":"Dorfstr. 1",
    "sg:city":"Klein Upahl",
    "sg:phone":"+49 38458/20459",
    "sg:postcode":"18276",
    "sg:province":"Mecklenburg-Vorpommern",
    "wof:name":"Hans-dieter Vock",
    "wof:placetype":"venue"
},
  "geometry": {"coordinates":[12.063638,53.716915],"type":"Point"}
}