{
  "type": "Feature",
  "properties": {
    "iso:country":"DE",
    "sg:address":"Auf dem Graben 2",
    "sg:city":"Iserlohn",
    "sg:phone":"+49 2304/5253",
    "sg:postcode":"58640",
    "sg:province":"Nordrhein-Westfalen",
    "wof:name":"J\u00fcrgen Groth",
    "wof:placetype":"venue"
},
  "geometry": {"coordinates":[7.654984951,51.4428825378],"type":"Point"}
}