{
  "type": "Feature",
  "properties": {
    "iso:country":"DE",
    "sg:address":"Harlesh\u00e4user Str. 99",
    "sg:city":"Kassel",
    "sg:phone":"+49 561/61831",
    "sg:postcode":"34128",
    "sg:province":"Hessen",
    "wof:name":"Aschenbrenner Tankstelle- Und Kraftfahrzeug-reparaturen Gmbh",
    "wof:placetype":"venue"
},
  "geometry": {"coordinates":[9.4414768219,51.3311805725],"type":"Point"}
}