{
  "type": "Feature",
  "properties": {
    "iso:country":"DE",
    "sg:address":"Bleicherstr. 1",
    "sg:city":"Biberach",
    "sg:phone":"+49 7351/12563",
    "sg:postcode":"88400",
    "sg:province":"Baden-W\u00fcrttemberg",
    "wof:name":"Gurland Und Seher Architekten",
    "wof:placetype":"venue"
},
  "geometry": {"coordinates":[9.78857,48.101368],"type":"Point"}
}