{
  "type": "Feature",
  "properties": {
    "iso:country":"DE",
    "sg:address":"Dorotheenstr. 32",
    "sg:city":"Gotha",
    "sg:phone":"+49 3621/701530",
    "sg:postcode":"99867",
    "sg:province":"Th\u00fcringen",
    "wof:name":"Ernst-albert Ortmann",
    "wof:placetype":"venue"
},
  "geometry": {"coordinates":[10.6932611465,50.9448051453],"type":"Point"}
}