{
  "type": "Feature",
  "properties": {
    "iso:country":"DE",
    "sg:address":"Vierordtstr. 2",
    "sg:city":"Karlsruhe",
    "sg:phone":"+49 721/45590",
    "sg:postcode":"76228",
    "sg:province":"Baden-W\u00fcrttemberg",
    "wof:name":"Gerhard Perthes",
    "wof:placetype":"venue"
},
  "geometry": {"coordinates":[8.481949,48.94471],"type":"Point"}
}