{
  "type": "Feature",
  "properties": {
    "iso:country":"DE",
    "sg:address":"Leerer Landstr. 49",
    "sg:city":"Aurich",
    "sg:phone":"+49 4941/17930",
    "sg:postcode":"26603",
    "sg:province":"Niedersachsen",
    "wof:name":"Ingenierub\u00fcro Bultmann Und Dr. Schlichting Gmbh",
    "wof:placetype":"venue"
},
  "geometry": {"coordinates":[7.4891619682,53.4633522034],"type":"Point"}
}