{
  "type": "Feature",
  "properties": {
    "iso:country":"DE",
    "sg:address":"Jakobistr. 21",
    "sg:city":"Soest",
    "sg:phone":"+49 2921/2859",
    "sg:postcode":"59494",
    "sg:province":"Nordrhein-Westfalen",
    "wof:name":"Orthop. Schuhtechnik Horst Kokenkemper",
    "wof:placetype":"venue"
},
  "geometry": {"coordinates":[8.1060495377,51.5702056885],"type":"Point"}
}