{
  "type": "Feature",
  "properties": {
    "iso:country":"DE",
    "sg:address":"Lindenbergstr. 5",
    "sg:city":"Rostock",
    "sg:phone":"+49 381/26664",
    "sg:postcode":"18055",
    "sg:province":"Mecklenburg-Vorpommern",
    "wof:name":"Klaus Und Erika Storny",
    "wof:placetype":"venue"
},
  "geometry": {"coordinates":[12.135038,54.078079],"type":"Point"}
}