{
  "type": "Feature",
  "properties": {
    "iso:country":"DE",
    "sg:address":"Hauptstr. 44",
    "sg:city":"Meerbusch",
    "sg:phone":"+49 2150/918922",
    "sg:postcode":"40668",
    "sg:province":"Nordrhein-Westfalen",
    "wof:name":"Teloy-apotheke",
    "wof:placetype":"venue"
},
  "geometry": {"coordinates":[6.680191,51.303368],"type":"Point"}
}