{
  "type": "Feature",
  "properties": {
    "iso:country":"DE",
    "sg:address":"Goethestr. 5a",
    "sg:city":"Neustadt",
    "sg:phone":"+49 9568/5961",
    "sg:postcode":"96465",
    "sg:province":"Bayern",
    "wof:name":"Praxis Dr. Med. Zwick \u00c4rzte F\u00fcr Allgemeinmedizin",
    "wof:placetype":"venue"
},
  "geometry": {"coordinates":[8.2122545242,47.9153404236],"type":"Point"}
}