{
  "type": "Feature",
  "properties": {
    "iso:country":"DE",
    "sg:address":"Hei\u00dfener Str. 63",
    "sg:city":"Essen",
    "sg:phone":"+49 201/675596",
    "sg:postcode":"45359",
    "sg:province":"Nordrhein-Westfalen",
    "wof:name":"Hans-joachim Lindow",
    "wof:placetype":"venue"
},
  "geometry": {"coordinates":[6.9433870316,51.4606323242],"type":"Point"}
}