{
  "type": "Feature",
  "properties": {
    "iso:country":"DE",
    "sg:address":"Schlitzer Str. 92",
    "sg:city":"Fulda",
    "sg:phone":"+49 661/56633",
    "sg:postcode":"36039",
    "sg:province":"Hessen",
    "wof:name":"H. Exler",
    "wof:placetype":"venue"
},
  "geometry": {"coordinates":[9.658955574,50.5652732849],"type":"Point"}
}