{
  "type": "Feature",
  "properties": {
    "iso:country":"DE",
    "sg:address":"Industriering 6",
    "sg:city":"Gro\u00dfwallstadt",
    "sg:phone":"+49 6022/22313",
    "sg:postcode":"63868",
    "sg:province":"Bayern",
    "wof:name":"Robert Geis Gmbh",
    "wof:placetype":"venue"
},
  "geometry": {"coordinates":[9.147984,49.879372],"type":"Point"}
}