{
  "type": "Feature",
  "properties": {
    "iso:country":"DE",
    "sg:address":"Bahnhofstr. 4",
    "sg:city":"Quedlinburg",
    "sg:phone":"+49 3946/514248",
    "sg:postcode":"06484",
    "sg:province":"Sachsen-Anhalt",
    "wof:name":"Gerhard Popp Rechtsanwalt",
    "wof:placetype":"venue"
},
  "geometry": {"coordinates":[11.1489925385,51.78673172],"type":"Point"}
}