{
  "type": "Feature",
  "properties": {
    "iso:country":"DE",
    "sg:address":"Brunnenstr. 69",
    "sg:city":"Maring-Noviand",
    "sg:postcode":"54484",
    "sg:province":"Rheinland-Pfalz",
    "wof:name":"Weingut M\u00fchlenhof",
    "wof:placetype":"venue"
},
  "geometry": {"coordinates":[6.9823231697,49.9241867065],"type":"Point"}
}