{
  "type": "Feature",
  "properties": {
    "iso:country":"DE",
    "sg:address":"Kleine Hochstr. 4",
    "sg:city":"Frankfurt",
    "sg:phone":"+49 69/13308725",
    "sg:postcode":"60313",
    "sg:province":"Hessen",
    "wof:name":"Tobias Heinemann Rechtsanwalt",
    "wof:placetype":"venue"
},
  "geometry": {"coordinates":[8.6751890182,50.1141624451],"type":"Point"}
}