{
  "type": "Feature",
  "properties": {
    "iso:country":"DE",
    "sg:address":"Hirtenackerstr. 56",
    "sg:city":"Zirndorf",
    "sg:phone":"+49 911/606454",
    "sg:postcode":"90513",
    "sg:province":"Bayern",
    "wof:name":"Veronika Nefzger",
    "wof:placetype":"venue"
},
  "geometry": {"coordinates":[10.962091,49.435894],"type":"Point"}
}