{
  "type": "Feature",
  "properties": {
    "iso:country":"DE",
    "sg:address":"Br\u00fcsseler Str. 72",
    "sg:city":"Z\u00fclpich",
    "sg:phone":"+49 2252/833940",
    "sg:postcode":"53909",
    "sg:province":"Nordrhein-Westfalen",
    "wof:name":"Bernd Nellen",
    "wof:placetype":"venue"
},
  "geometry": {"coordinates":[6.62464,50.703182],"type":"Point"}
}