{
  "type": "Feature",
  "properties": {
    "iso:country":"DE",
    "sg:address":"Schlo\u00dfstr. 23",
    "sg:city":"Ludwigslust",
    "sg:phone":"+49 3874/47666",
    "sg:postcode":"19288",
    "sg:province":"Mecklenburg-Vorpommern",
    "wof:name":"Electronic 2000 Beratung Verkauf",
    "wof:placetype":"venue"
},
  "geometry": {"coordinates":[11.492609,53.324265],"type":"Point"}
}