{
  "type": "Feature",
  "properties": {
    "iso:country":"DE",
    "sg:address":"Hauptstr. 46",
    "sg:city":"Elzach",
    "sg:phone":"+49 7682/367",
    "sg:postcode":"79215",
    "sg:province":"Baden-W\u00fcrttemberg",
    "wof:name":"F. Riegger",
    "wof:placetype":"venue"
},
  "geometry": {"coordinates":[8.0712156296,48.1741676331],"type":"Point"}
}