{
  "type": "Feature",
  "properties": {
    "iso:country":"DE",
    "sg:address":"Hauptwachstr. 32",
    "sg:city":"Bamberg",
    "sg:phone":"+49 951/27004",
    "sg:postcode":"96047",
    "sg:province":"Bayern",
    "wof:name":"Western-store Inh. Elfriede Franke",
    "wof:placetype":"venue"
},
  "geometry": {"coordinates":[10.890630722,49.8949279785],"type":"Point"}
}