{
  "type": "Feature",
  "properties": {
    "iso:country":"DE",
    "sg:address":"Weinhof",
    "sg:city":"Pfinztal",
    "sg:phone":"+49 7240/1524",
    "sg:postcode":"76327",
    "sg:province":"Baden-W\u00fcrttemberg",
    "wof:name":"Weinhof Rupp",
    "wof:placetype":"venue"
},
  "geometry": {"coordinates":[8.5253353119,48.9855117798],"type":"Point"}
}