{
  "type": "Feature",
  "properties": {
    "iso:country":"DE",
    "sg:address":"Hirschbergstr. 46",
    "sg:city":"Saarbr\u00fccken",
    "sg:phone":"+49 681/817958",
    "sg:postcode":"66121",
    "sg:province":"Saarland",
    "wof:name":"Ingrid Zapp",
    "wof:placetype":"venue"
},
  "geometry": {"coordinates":[7.053284,49.23254],"type":"Point"}
}