{
  "type": "Feature",
  "properties": {
    "iso:country":"DE",
    "sg:address":"Fasaneriestr. 2",
    "sg:city":"Seligenstadt",
    "sg:phone":"+49 6182/67756",
    "sg:postcode":"63500",
    "sg:province":"Hessen",
    "wof:name":"3 Ring Inh. Heinz Mittler",
    "wof:placetype":"venue"
},
  "geometry": {"coordinates":[8.9286899567,50.0557861328],"type":"Point"}
}