{
  "type": "Feature",
  "properties": {
    "iso:country":"DE",
    "sg:address":"Im Thal 8",
    "sg:city":"Penzberg",
    "sg:postcode":"82377",
    "sg:province":"Bayern",
    "wof:name":"Attosensor Gmbh",
    "wof:placetype":"venue"
},
  "geometry": {"coordinates":[11.37906,47.755646],"type":"Point"}
}