{
  "type": "Feature",
  "properties": {
    "iso:country":"DE",
    "sg:address":"Monschauer Str. 2",
    "sg:city":"Schleiden",
    "sg:phone":"+49 2445/912328",
    "sg:postcode":"53937",
    "sg:province":"Nordrhein-Westfalen",
    "wof:name":"Musikcafe Barnana",
    "wof:placetype":"venue"
},
  "geometry": {"coordinates":[6.476337,50.529835],"type":"Point"}
}