{
  "type": "Feature",
  "properties": {
    "iso:country":"DE",
    "sg:address":"Kleeweg 42 c",
    "sg:city":"Tecklenburg",
    "sg:postcode":"49545",
    "sg:province":"Nordrhein-Westfalen",
    "wof:name":"Grieger Gmbh",
    "wof:placetype":"venue"
},
  "geometry": {"coordinates":[7.73547,52.226212],"type":"Point"}
}