{
  "type": "Feature",
  "properties": {
    "iso:country":"DE",
    "sg:address":"Thormeyerstr. 16",
    "sg:city":"Dresden",
    "sg:phone":"+49 351/4710854",
    "sg:postcode":"01217",
    "sg:province":"Sachsen",
    "wof:name":"Uwe Eibig",
    "wof:placetype":"venue"
},
  "geometry": {"coordinates":[13.7507209778,51.0254325867],"type":"Point"}
}