{
  "type": "Feature",
  "properties": {
    "iso:country":"DE",
    "sg:address":"Unterrather Str. 115",
    "sg:city":"D\u00fcsseldorf",
    "sg:phone":"+49 211/4180586",
    "sg:postcode":"40468",
    "sg:province":"Nordrhein-Westfalen",
    "wof:name":"Pizzeria Bella Venezia",
    "wof:placetype":"venue"
},
  "geometry": {"coordinates":[6.7803621292,51.2730865479],"type":"Point"}
}