{
  "type": "Feature",
  "properties": {
    "iso:country":"DE",
    "sg:address":"Breisgaustr. 75",
    "sg:city":"Leipzig",
    "sg:postcode":"04209",
    "sg:province":"Sachsen",
    "wof:name":"G\u00fcnther Ziehbold",
    "wof:placetype":"venue"
},
  "geometry": {"coordinates":[12.283378,51.317337],"type":"Point"}
}