{
  "type": "Feature",
  "properties": {
    "iso:country":"DE",
    "sg:address":"Gro\u00dfe Kalandstr. 39",
    "sg:city":"Wei\u00dfenfels",
    "sg:postcode":"06667",
    "sg:province":"Sachsen-Anhalt",
    "wof:name":"Gebo Wohnbau- Und Vermietungs Gmbh",
    "wof:placetype":"venue"
},
  "geometry": {"coordinates":[11.968911,51.201851],"type":"Point"}
}