{
  "type": "Feature",
  "properties": {
    "iso:country":"DE",
    "sg:address":"Koblenzer Str. 61",
    "sg:city":"Bonn",
    "sg:postcode":"53173",
    "sg:province":"Nordrhein-Westfalen",
    "wof:name":"Dr. Haag-stienen Immobilien Gmbh",
    "wof:placetype":"venue"
},
  "geometry": {"coordinates":[7.1558670998,50.6837615967],"type":"Point"}
}