{
  "type": "Feature",
  "properties": {
    "iso:country":"DE",
    "sg:address":"Am Roten Rain 4-6",
    "sg:city":"Burkardroth",
    "sg:phone":"+49 9734/272",
    "sg:postcode":"97705",
    "sg:province":"Bayern",
    "wof:name":"Textilhaus Ernst Grom Kg",
    "wof:placetype":"venue"
},
  "geometry": {"coordinates":[9.996882,50.268791],"type":"Point"}
}