{
  "type": "Feature",
  "properties": {
    "iso:country":"DE",
    "sg:address":"Ifenstr. 2",
    "sg:city":"Mindelheim",
    "sg:phone":"+49 8261/3030",
    "sg:postcode":"87719",
    "sg:province":"Bayern",
    "wof:name":"Charlotte Baur Gmbh",
    "wof:placetype":"venue"
},
  "geometry": {"coordinates":[10.497963,48.036015],"type":"Point"}
}