{
  "type": "Feature",
  "properties": {
    "iso:country":"DE",
    "sg:address":"Thyssenstr. 153",
    "sg:city":"Dinslaken",
    "sg:phone":"+49 2064/52275",
    "sg:postcode":"46535",
    "sg:province":"Nordrhein-Westfalen",
    "wof:name":"Renate Horn",
    "wof:placetype":"venue"
},
  "geometry": {"coordinates":[6.750153,51.557392],"type":"Point"}
}