{
  "type": "Feature",
  "properties": {
    "iso:country":"DE",
    "sg:address":"Am Bahndamm 13",
    "sg:city":"Hungen",
    "sg:phone":"+49 6402/7186",
    "sg:postcode":"35410",
    "sg:province":"Hessen",
    "wof:name":"M. Findt-he\u00dfler",
    "wof:placetype":"venue"
},
  "geometry": {"coordinates":[8.897433,50.476704],"type":"Point"}
}