{
  "type": "Feature",
  "properties": {
    "iso:country":"DE",
    "sg:address":"Rabenberg 20",
    "sg:city":"Hamburg",
    "sg:phone":"+49 40/6405683",
    "sg:postcode":"22391",
    "sg:province":"Hamburg",
    "wof:name":"C. Ziegler Ingenieur",
    "wof:placetype":"venue"
},
  "geometry": {"coordinates":[10.0897140503,53.6406784058],"type":"Point"}
}