{
  "type": "Feature",
  "properties": {
    "iso:country":"DE",
    "sg:address":"Eggertstr. 28",
    "sg:city":"Paderborn",
    "sg:phone":"+49 5251/542404",
    "sg:postcode":"33100",
    "sg:province":"Nordrhein-Westfalen",
    "wof:name":"Brevis Gmbh",
    "wof:placetype":"venue"
},
  "geometry": {"coordinates":[8.7994279861,51.7256240845],"type":"Point"}
}