{
  "type": "Feature",
  "properties": {
    "iso:country":"DE",
    "sg:address":"Roonstr. 5",
    "sg:city":"Dinslaken",
    "sg:phone":"+49 2064/13165",
    "sg:postcode":"46535",
    "sg:province":"Nordrhein-Westfalen",
    "wof:name":"Dietrich Schmitz Rechtsanwalt",
    "wof:placetype":"venue"
},
  "geometry": {"coordinates":[6.7390151024,51.5642967224],"type":"Point"}
}