{
  "type": "Feature",
  "properties": {
    "iso:country":"DE",
    "sg:address":"Lise-Meitner-Str. 12",
    "sg:city":"Nordhorn",
    "sg:phone":"+49 4959/2189890",
    "sg:postcode":"48529",
    "sg:province":"Niedersachsen",
    "wof:name":"Variotech Neerken Kg",
    "wof:placetype":"venue"
},
  "geometry": {"coordinates":[7.070499897,52.4377365112],"type":"Point"}
}