{
  "type": "Feature",
  "properties": {
    "iso:country":"DE",
    "sg:address":"Butenwall 4",
    "sg:city":"Borken",
    "sg:phone":"+49 2861/2793",
    "sg:postcode":"46325",
    "sg:province":"Nordrhein-Westfalen",
    "wof:name":"Foto Schmitz",
    "wof:placetype":"venue"
},
  "geometry": {"coordinates":[6.8579821587,51.8413238525],"type":"Point"}
}