{
  "type": "Feature",
  "properties": {
    "iso:country":"DE",
    "sg:address":"Schulzenstr. 98",
    "sg:city":"Barby",
    "sg:phone":"+49 39298/3491",
    "sg:postcode":"39249",
    "sg:province":"Sachsen-Anhalt",
    "wof:name":"Wohnungsbaugesell. Barby Mbh",
    "wof:placetype":"venue"
},
  "geometry": {"coordinates":[11.87852,51.962616],"type":"Point"}
}