{
  "type": "Feature",
  "properties": {
    "iso:country":"DE",
    "sg:address":"Gewerbestr. 79",
    "sg:city":"Gundelfingen",
    "sg:phone":"+49 761/589049",
    "sg:postcode":"79194",
    "sg:province":"Baden-W\u00fcrttemberg",
    "wof:name":"Ralf Fischer Immobilienmakler",
    "wof:placetype":"venue"
},
  "geometry": {"coordinates":[7.8616871834,48.0442047119],"type":"Point"}
}