{
  "type": "Feature",
  "properties": {
    "iso:country":"DE",
    "sg:address":"Hauptstr. 12a",
    "sg:city":"Obermehler",
    "sg:phone":"+49 36021/92833",
    "sg:postcode":"99996",
    "sg:province":"Th\u00fcringen",
    "wof:name":"Sitex Gmbh",
    "wof:placetype":"venue"
},
  "geometry": {"coordinates":[10.61789,51.264839],"type":"Point"}
}