{
  "type": "Feature",
  "properties": {
    "iso:country":"DE",
    "sg:address":"Weinstr. 35",
    "sg:city":"Neckarsulm",
    "sg:postcode":"74172",
    "sg:province":"Baden-W\u00fcrttemberg",
    "wof:name":"Washington Avenue Holding Gmbh",
    "wof:placetype":"venue"
},
  "geometry": {"coordinates":[9.232058,49.19025],"type":"Point"}
}