{
  "type": "Feature",
  "properties": {
    "iso:country":"DE",
    "sg:address":"Elvirasteig 11",
    "sg:city":"Berlin",
    "sg:phone":"+49 30/8099870",
    "sg:postcode":"14163",
    "sg:province":"Berlin",
    "wof:name":"Akustik Ingenieurb\u00fcro Moll Gmbh",
    "wof:placetype":"venue"
},
  "geometry": {"coordinates":[13.2272977829,52.4402389526],"type":"Point"}
}