{
  "type": "Feature",
  "properties": {
    "iso:country":"DE",
    "sg:address":"Ring 4",
    "sg:city":"Radegast",
    "sg:phone":"+49 34978/21252",
    "sg:postcode":"06369",
    "sg:province":"Sachsen-Anhalt",
    "wof:name":"Breinker Bautechnik",
    "wof:placetype":"venue"
},
  "geometry": {"coordinates":[12.0920295715,51.654586792],"type":"Point"}
}