{
  "type": "Feature",
  "properties": {
    "iso:country":"DE",
    "sg:address":"Riethnordh\u00e4user Weg 3",
    "sg:city":"Alperstedt",
    "sg:phone":"+49 36204/50836",
    "sg:postcode":"99195",
    "sg:province":"Th\u00fcringen",
    "wof:name":"Ricona Maschinenvertrieb Erfurt Gmbh",
    "wof:placetype":"venue"
},
  "geometry": {"coordinates":[11.038005,51.093155],"type":"Point"}
}