{
  "type": "Feature",
  "properties": {
    "iso:country":"DE",
    "sg:address":"K\u00fcckstr. 47",
    "sg:city":"Baesweiler",
    "sg:phone":"+49 2401/7324",
    "sg:postcode":"52499",
    "sg:province":"Nordrhein-Westfalen",
    "wof:name":"Wolfgang K\u00f6nigstein",
    "wof:placetype":"venue"
},
  "geometry": {"coordinates":[6.178534,50.910542],"type":"Point"}
}