{
  "type": "Feature",
  "properties": {
    "iso:country":"DE",
    "sg:address":"Weidestr. 20b",
    "sg:city":"Hamburg",
    "sg:phone":"+49 40/2991281",
    "sg:postcode":"22083",
    "sg:province":"Hamburg",
    "wof:name":"Werkhaus Dienstleistungs- Handwerks- Und Handels-",
    "wof:placetype":"venue"
},
  "geometry": {"coordinates":[10.0377492905,53.5804901123],"type":"Point"}
}