{
  "type": "Feature",
  "properties": {
    "iso:country":"DE",
    "sg:address":"St.-J\u00fcrgen-Ring 43",
    "sg:city":"L\u00fcbeck",
    "sg:phone":"+49 451/53845",
    "sg:postcode":"23564",
    "sg:province":"Schleswig-Holstein",
    "wof:name":"Gertrud Michl",
    "wof:placetype":"venue"
},
  "geometry": {"coordinates":[10.6948518753,53.8516998291],"type":"Point"}
}