{
  "type": "Feature",
  "properties": {
    "iso:country":"DE",
    "sg:address":"Markt 38",
    "sg:city":"Ronneburg",
    "sg:phone":"+49 36602/22404",
    "sg:postcode":"07580",
    "sg:province":"Th\u00fcringen",
    "wof:name":"Owt Steuer- Beratungsges. Mbh",
    "wof:placetype":"venue"
},
  "geometry": {"coordinates":[12.1811199188,50.8629112244],"type":"Point"}
}