{
  "type": "Feature",
  "properties": {
    "iso:country":"DE",
    "sg:address":"Moselstr.",
    "sg:city":"Mettlach",
    "sg:phone":"+49 6865/1320",
    "sg:postcode":"66693",
    "sg:province":"Saarland",
    "wof:name":"Accord",
    "wof:placetype":"venue"
},
  "geometry": {"coordinates":[6.5172791481,49.5051383972],"type":"Point"}
}