{
  "type": "Feature",
  "properties": {
    "iso:country":"DE",
    "sg:address":"Hagemannshof 14",
    "sg:city":"Gelsenkirchen",
    "sg:postcode":"45889",
    "sg:province":"Nordrhein-Westfalen",
    "wof:name":"Gonzo`s Schalker Homepage",
    "wof:placetype":"venue"
},
  "geometry": {"coordinates":[7.119085,51.532742],"type":"Point"}
}