{
  "type": "Feature",
  "properties": {
    "iso:country":"DE",
    "sg:address":"Am N\u00fcttermoorer Sieltief 3",
    "sg:city":"Leer",
    "sg:postcode":"26789",
    "sg:province":"Niedersachsen",
    "wof:name":"Vieregge Verwaltungsgesellschaft Mbh",
    "wof:placetype":"venue"
},
  "geometry": {"coordinates":[7.456517,53.25835],"type":"Point"}
}