{
  "type": "Feature",
  "properties": {
    "iso:country":"DE",
    "sg:address":"Hauptstr. 157",
    "sg:city":"Merchweiler",
    "sg:postcode":"66589",
    "sg:province":"Saarland",
    "wof:name":"Volksbank Im Kreis Ottweiler Eg",
    "wof:placetype":"venue"
},
  "geometry": {"coordinates":[7.130311,49.370701],"type":"Point"}
}