{
  "type": "Feature",
  "properties": {
    "iso:country":"DE",
    "sg:address":"Hessentaler Str. 16",
    "sg:city":"Schw\u00e4bisch Hall",
    "sg:phone":"+49 791/2364",
    "sg:postcode":"74523",
    "sg:province":"Baden-W\u00fcrttemberg",
    "wof:name":"Thomas Leipersberger",
    "wof:placetype":"venue"
},
  "geometry": {"coordinates":[9.747547,49.099762],"type":"Point"}
}