{
  "type": "Feature",
  "properties": {
    "iso:country":"DE",
    "sg:address":"Schulstr. 1a",
    "sg:city":"Fu\u00dfg\u00f6nheim",
    "sg:phone":"+49 6237/929174",
    "sg:postcode":"67136",
    "sg:province":"Rheinland-Pfalz",
    "wof:name":"Wolfgang Berndt",
    "wof:placetype":"venue"
},
  "geometry": {"coordinates":[8.2889432907,49.4620170593],"type":"Point"}
}