{
  "type": "Feature",
  "properties": {
    "iso:country":"DE",
    "sg:address":"Hauptstr 29",
    "sg:city":"Niederstadtfeld",
    "sg:phone":"+49 6596/790",
    "sg:postcode":"54570",
    "sg:province":"Rheinland-Pfalz",
    "wof:name":"Warmpresswerk Max B. Schachmann Gmbh",
    "wof:placetype":"venue"
},
  "geometry": {"coordinates":[6.761159,50.159859],"type":"Point"}
}