{
  "type": "Feature",
  "properties": {
    "iso:country":"DE",
    "sg:address":"Im Taubental 52",
    "sg:city":"Neuss",
    "sg:phone":"+49 2131/9330",
    "sg:postcode":"41468",
    "sg:province":"Nordrhein-Westfalen",
    "wof:name":"Keynes Planungsgesellschaft F\u00fcr Industrieanlagen Mbh",
    "wof:placetype":"venue"
},
  "geometry": {"coordinates":[6.7464060783,51.1697463989],"type":"Point"}
}