{
  "type": "Feature",
  "properties": {
    "iso:country":"DE",
    "sg:address":"Rottweg 34",
    "sg:city":"Ahaus",
    "sg:phone":"+49 2561/2782",
    "sg:postcode":"48683",
    "sg:province":"Nordrhein-Westfalen",
    "wof:name":"Ewald Terhaar",
    "wof:placetype":"venue"
},
  "geometry": {"coordinates":[7.027328,52.082008],"type":"Point"}
}