{
  "type": "Feature",
  "properties": {
    "iso:country":"DE",
    "sg:address":"Selsinger Str. 63",
    "sg:city":"Bremerv\u00f6rde",
    "sg:phone":"+49 4767/667",
    "sg:postcode":"27432",
    "sg:province":"Niedersachsen",
    "wof:name":"Duxbachtal Campingplatz",
    "wof:placetype":"venue"
},
  "geometry": {"coordinates":[9.193288,53.40871],"type":"Point"}
}