{
  "type": "Feature",
  "properties": {
    "iso:country":"DE",
    "sg:address":"Grimmenstein 15",
    "sg:city":"Wolfegg",
    "sg:phone":"+49 700 9393 6778",
    "sg:postcode":"88364",
    "sg:province":"Baden-W\u00fcrttemberg",
    "wof:name":"Waldburg Forstmaschinen Gmbh",
    "wof:placetype":"venue"
},
  "geometry": {"coordinates":[9.813277,47.825165],"type":"Point"}
}