{
  "type": "Feature",
  "properties": {
    "iso:country":"DE",
    "sg:address":"Zinksgartenstr. 14",
    "sg:city":"Halle",
    "sg:phone":"+49 345/2029895",
    "sg:postcode":"06108",
    "sg:province":"Sachsen-Anhalt",
    "wof:name":"Dr. G\u00fcnter Scholz Rechtsanwalt",
    "wof:placetype":"venue"
},
  "geometry": {"coordinates":[11.9745082855,51.4863471985],"type":"Point"}
}