{
  "type": "Feature",
  "properties": {
    "iso:country":"DE",
    "sg:address":"Salzhausener Str. 6",
    "sg:city":"Oldendorf",
    "sg:phone":"+49 4132/493",
    "sg:postcode":"21385",
    "sg:province":"Niedersachsen",
    "wof:name":"H. M\u00fcller",
    "wof:placetype":"venue"
},
  "geometry": {"coordinates":[10.213844,53.157742],"type":"Point"}
}