{
  "type": "Feature",
  "properties": {
    "iso:country":"DE",
    "sg:address":"Waldstr. 22",
    "sg:city":"Dormagen",
    "sg:phone":"+49 2133/80082",
    "sg:postcode":"41542",
    "sg:province":"Nordrhein-Westfalen",
    "wof:name":"Haus Hubertus",
    "wof:placetype":"venue"
},
  "geometry": {"coordinates":[6.7603669167,51.0911026001],"type":"Point"}
}