{
  "type": "Feature",
  "properties": {
    "iso:country":"DE",
    "sg:address":"Schulstr. 8",
    "sg:city":"Lichtenstein",
    "sg:phone":"+49 4971/294196",
    "sg:postcode":"72805",
    "sg:province":"Baden-W\u00fcrttemberg",
    "wof:name":"Kreissparkasse Reutlingen",
    "wof:placetype":"venue"
},
  "geometry": {"coordinates":[9.261771,48.411766],"type":"Point"}
}