{
  "type": "Feature",
  "properties": {
    "iso:country":"DE",
    "sg:address":"Ramsaystr. 18",
    "sg:city":"Hanau",
    "sg:postcode":"63450",
    "sg:province":"Hessen",
    "wof:name":"Mitterer Verwaltungs Gmbh",
    "wof:placetype":"venue"
},
  "geometry": {"coordinates":[8.9159097672,50.137172699],"type":"Point"}
}