{
  "type": "Feature",
  "properties": {
    "iso:country":"DE",
    "sg:address":"Nieperfitz",
    "sg:city":"Nahrendorf",
    "sg:phone":"+49 5855/560",
    "sg:postcode":"21369",
    "sg:province":"Niedersachsen",
    "wof:name":"Pension Hartmut Meyer",
    "wof:placetype":"venue"
},
  "geometry": {"coordinates":[10.875544548,53.1607780457],"type":"Point"}
}