{
  "type": "Feature",
  "properties": {
    "iso:country":"DE",
    "sg:address":"Postfach 1920",
    "sg:city":"Arnsberg",
    "sg:postcode":"59709",
    "sg:province":"Nordrhein-Westfalen",
    "wof:name":"Magney Kg",
    "wof:placetype":"venue"
},
  "geometry": {"coordinates":[8.0686702728,51.3952789307],"type":"Point"}
}