{
  "type": "Feature",
  "properties": {
    "iso:country":"DE",
    "sg:address":"Augsburger Str. 94",
    "sg:city":"Neu-Ulm",
    "sg:phone":"+49 731/77672",
    "sg:postcode":"89231",
    "sg:province":"Bayern",
    "wof:name":"Hotel-restaurant Bad Wolf",
    "wof:placetype":"venue"
},
  "geometry": {"coordinates":[10.0087776184,48.4001808167],"type":"Point"}
}