{
  "type": "Feature",
  "properties": {
    "iso:country":"DE",
    "sg:address":"Oderwaldstr. 17",
    "sg:city":"Fl\u00f6the",
    "sg:phone":"+49 5341/92697",
    "sg:postcode":"38312",
    "sg:province":"Niedersachsen",
    "wof:name":"Renate Binder",
    "wof:placetype":"venue"
},
  "geometry": {"coordinates":[10.4702987671,52.0873031616],"type":"Point"}
}