{
  "type": "Feature",
  "properties": {
    "iso:country":"DE",
    "sg:address":"Schwedler Str. 6",
    "sg:city":"Frankfurt",
    "sg:phone":"+49 4969/405760",
    "sg:postcode":"60314",
    "sg:province":"Hessen",
    "wof:name":"J.walter Thompson Gmbh",
    "wof:placetype":"venue"
},
  "geometry": {"coordinates":[8.71989,50.113632],"type":"Point"}
}