{
  "type": "Feature",
  "properties": {
    "iso:country":"DE",
    "sg:address":"Auf Kellerchen 5",
    "sg:city":"Losheim",
    "sg:phone":"+49 6872/1808",
    "sg:postcode":"66679",
    "sg:province":"Saarland",
    "wof:name":"Kath. Pfarramt St. Blasius",
    "wof:placetype":"venue"
},
  "geometry": {"coordinates":[6.7548217773,49.4677429199],"type":"Point"}
}