{
  "type": "Feature",
  "properties": {
    "iso:country":"DE",
    "sg:address":"Anne-Frank-Str. 35",
    "sg:city":"Rheine",
    "sg:phone":"+49 5971/3588",
    "sg:postcode":"48431",
    "sg:province":"Nordrhein-Westfalen",
    "wof:name":"B. Gertner Werbeagentur",
    "wof:placetype":"venue"
},
  "geometry": {"coordinates":[7.4454698563,52.2630462646],"type":"Point"}
}