{
  "type": "Feature",
  "properties": {
    "iso:country":"DE",
    "sg:address":"Mariabrunn 1",
    "sg:city":"R\u00f6hrmoos",
    "sg:postcode":"85244",
    "sg:province":"Bayern",
    "wof:name":"Privatbrauerei Erdinger Wei\u00dfbr\u00e4u Werner Brombach Gmbh",
    "wof:placetype":"venue"
},
  "geometry": {"coordinates":[11.477198,48.312397],"type":"Point"}
}