{
  "type": "Feature",
  "properties": {
    "iso:country":"DE",
    "sg:address":"Friedrichstr. 7",
    "sg:city":"W\u00fcrselen",
    "sg:phone":"+49 2405/2452",
    "sg:postcode":"52146",
    "sg:province":"Nordrhein-Westfalen",
    "wof:name":"Ew. Nolden",
    "wof:placetype":"venue"
},
  "geometry": {"coordinates":[6.138808,50.821728],"type":"Point"}
}