{
  "type": "Feature",
  "properties": {
    "iso:country":"DE",
    "sg:address":"Leipziger Str. 12",
    "sg:city":"Grimma",
    "sg:phone":"+49 3437/917909",
    "sg:postcode":"04668",
    "sg:province":"Sachsen",
    "wof:name":"Imbi\u00df P. Findeisen",
    "wof:placetype":"venue"
},
  "geometry": {"coordinates":[12.7237129211,51.2329292297],"type":"Point"}
}