{
  "type": "Feature",
  "properties": {
    "iso:country":"DE",
    "sg:address":"Sophienplatz 2",
    "sg:city":"Colditz",
    "sg:postcode":"04680",
    "sg:province":"Sachsen",
    "wof:name":"Gastro Gmbh",
    "wof:placetype":"venue"
},
  "geometry": {"coordinates":[12.806394577,51.1282844543],"type":"Point"}
}