{
  "type": "Feature",
  "properties": {
    "iso:country":"DE",
    "sg:address":"Georg-Schumann-Str. 176",
    "sg:city":"Leipzig",
    "sg:phone":"+49 341/9101012",
    "sg:postcode":"04159",
    "sg:province":"Sachsen",
    "wof:name":"Urlauberservice Reiseb\u00fcro Gisela Gr\u00fcnert",
    "wof:placetype":"venue"
},
  "geometry": {"coordinates":[12.3466005325,51.3669433594],"type":"Point"}
}