{
  "type": "Feature",
  "properties": {
    "iso:country":"DE",
    "sg:address":"Andreas-Hofer-Str. 10",
    "sg:city":"Mannheim",
    "sg:phone":"+49 621/796755",
    "sg:postcode":"68259",
    "sg:province":"Baden-W\u00fcrttemberg",
    "wof:name":"Bernhard Strobel Architekt",
    "wof:placetype":"venue"
},
  "geometry": {"coordinates":[8.528204,49.490791],"type":"Point"}
}