{
  "type": "Feature",
  "properties": {
    "iso:country":"DE",
    "sg:address":"Gro\u00dfe Hub 10",
    "sg:city":"Eltville",
    "sg:postcode":"65344",
    "sg:province":"Hessen",
    "wof:name":"Haas & Health Partner Public Relations Gmbh",
    "wof:placetype":"venue"
},
  "geometry": {"coordinates":[8.1250200272,50.0468902588],"type":"Point"}
}