{
  "type": "Feature",
  "properties": {
    "iso:country":"DE",
    "sg:address":"Weberstr. 8",
    "sg:city":"Oderberg",
    "sg:phone":"+49 8669/87860",
    "sg:postcode":"83374",
    "sg:province":"Bayern",
    "wof:name":"Hotel Austermayer",
    "wof:placetype":"venue"
},
  "geometry": {"coordinates":[12.6057758331,47.9469337463],"type":"Point"}
}