{
  "type": "Feature",
  "properties": {
    "iso:country":"DE",
    "sg:address":"Ritzerstr. 36",
    "sg:city":"Erlangen",
    "sg:phone":"+49 9131/59938",
    "sg:postcode":"91054",
    "sg:province":"Bayern",
    "wof:name":"Ursula Hofer Lichtpausen",
    "wof:placetype":"venue"
},
  "geometry": {"coordinates":[11.0402116776,49.5954322815],"type":"Point"}
}