{
  "type": "Feature",
  "properties": {
    "iso:country":"DE",
    "sg:address":"Deitersweg 16",
    "sg:city":"M\u00fcnster",
    "sg:phone":"+49 251/212116",
    "sg:postcode":"48159",
    "sg:province":"Nordrhein-Westfalen",
    "wof:name":"Wilhelm Dreier Gmbh",
    "wof:placetype":"venue"
},
  "geometry": {"coordinates":[7.593199,51.99229],"type":"Point"}
}