{
  "type": "Feature",
  "properties": {
    "iso:country":"DE",
    "sg:address":"Schloitweg 11b",
    "sg:city":"Soest",
    "sg:phone":"+49 2921/96320",
    "sg:postcode":"59494",
    "sg:province":"Nordrhein-Westfalen",
    "wof:name":"I-center Elektrogro\u00dfhandel Gmbh & Co.",
    "wof:placetype":"venue"
},
  "geometry": {"coordinates":[8.0830087662,51.5565910339],"type":"Point"}
}