{
  "type": "Feature",
  "properties": {
    "iso:country":"DE",
    "sg:city":"Reimlingen",
    "sg:phone":"+49 721/151241692",
    "sg:postcode":"86756",
    "sg:province":"Bayern",
    "wof:name":"Musikkapelle Reimlingen E.v.",
    "wof:placetype":"venue"
},
  "geometry": {"coordinates":[10.51597,48.818321],"type":"Point"}
}