{
  "type": "Feature",
  "properties": {
    "iso:country":"DE",
    "sg:address":"Ernst-Deger-Str. 5",
    "sg:city":"Bockenem",
    "sg:postcode":"31167",
    "sg:province":"Niedersachsen",
    "wof:name":"K. H. B\u00e4dje Gmbh",
    "wof:placetype":"venue"
},
  "geometry": {"coordinates":[10.12545,52.013077],"type":"Point"}
}