{
  "type": "Feature",
  "properties": {
    "iso:country":"DE",
    "sg:address":"POSTFACH 1 1 33",
    "sg:city":"OESTRICH - WINKEL",
    "sg:phone":"+49 6723/88258",
    "sg:postcode":"65367",
    "wof:name":"Die Miniperfume.de - Parf\u00fcmminiaturen F\u00fcr Wenig Ge",
    "wof:placetype":"venue"
},
  "geometry": {"coordinates":[8.03052,50.005421],"type":"Point"}
}