{
  "type": "Feature",
  "properties": {
    "iso:country":"DE",
    "sg:address":"Martinswinkelstr. 2",
    "sg:city":"Garmisch-Partenkirchen",
    "sg:phone":"+49 8821/2680",
    "sg:postcode":"82467",
    "sg:province":"Bayern",
    "wof:name":"Friedrich Hochschild",
    "wof:placetype":"venue"
},
  "geometry": {"coordinates":[11.09694,47.496555],"type":"Point"}
}