{
  "type": "Feature",
  "properties": {
    "iso:country":"DE",
    "sg:address":"Von-Ketteler-Str. 110",
    "sg:city":"Krefeld",
    "sg:phone":"+49 2151/33990",
    "sg:postcode":"47807",
    "sg:province":"Nordrhein-Westfalen",
    "wof:name":"Bodden",
    "wof:placetype":"venue"
},
  "geometry": {"coordinates":[6.5870752335,51.3156814575],"type":"Point"}
}