{
  "type": "Feature",
  "properties": {
    "iso:country":"DE",
    "sg:address":"Sektion Ost 38",
    "sg:city":"Willich",
    "sg:phone":"+49 2156/912790",
    "sg:postcode":"47877",
    "sg:province":"Nordrhein-Westfalen",
    "wof:name":"Permament Die Sein Company Gesellschaft Mbh Messe Design",
    "wof:placetype":"venue"
},
  "geometry": {"coordinates":[6.473271,51.26886],"type":"Point"}
}