{
  "type": "Feature",
  "properties": {
    "iso:country":"DE",
    "sg:address":"Herderstr. 81",
    "sg:city":"Hilden",
    "sg:phone":"+49 2103/48022",
    "sg:postcode":"40721",
    "sg:province":"Nordrhein-Westfalen",
    "wof:name":"Gtw Formularmaschinen Gmbh",
    "wof:placetype":"venue"
},
  "geometry": {"coordinates":[6.920443,51.180103],"type":"Point"}
}