{
  "type": "Feature",
  "properties": {
    "iso:country":"DE",
    "sg:address":"Marktstr. 34",
    "sg:city":"Winnenden",
    "sg:phone":"+49 7195/68966",
    "sg:postcode":"71364",
    "sg:province":"Baden-W\u00fcrttemberg",
    "wof:name":"Eugen Haag",
    "wof:placetype":"venue"
},
  "geometry": {"coordinates":[9.399402,48.875935],"type":"Point"}
}