{
  "type": "Feature",
  "properties": {
    "iso:country":"DE",
    "sg:address":"Kirchweg 1",
    "sg:city":"Cunewalde",
    "sg:phone":"+49 35877/27431",
    "sg:postcode":"02733",
    "sg:province":"Sachsen",
    "wof:name":"Evangelische Kirche Cunewalde",
    "wof:placetype":"venue"
},
  "geometry": {"coordinates":[14.502323,51.099312],"type":"Point"}
}