{
  "type": "Feature",
  "properties": {
    "iso:country":"DE",
    "sg:address":"Innere Herlasgr\u00fcner Str. 29",
    "sg:city":"Treuen",
    "sg:phone":"+49 37468/2242",
    "sg:postcode":"08233",
    "sg:province":"Sachsen",
    "wof:name":"Torsten Forner",
    "wof:placetype":"venue"
},
  "geometry": {"coordinates":[12.298522,50.544487],"type":"Point"}
}