{
  "type": "Feature",
  "properties": {
    "iso:country":"DE",
    "sg:address":"Bahnhofstr. 33",
    "sg:city":"W\u00fclknitz",
    "sg:phone":"+49 35263/64131",
    "sg:postcode":"01609",
    "sg:province":"Sachsen",
    "wof:name":"Ssw Spiel- Und Sportger\u00e4te W\u00fclknitz Gmbh",
    "wof:placetype":"venue"
},
  "geometry": {"coordinates":[13.396818161,51.3690414429],"type":"Point"}
}