{
  "type": "Feature",
  "properties": {
    "iso:country":"DE",
    "sg:address":"Am Windbusch 5",
    "sg:city":"Detmold",
    "sg:phone":"+49 5231/96870",
    "sg:postcode":"32758",
    "sg:province":"Nordrhein-Westfalen",
    "wof:name":"E. R. O. B\u00e4cker & Meyer Ohg",
    "wof:placetype":"venue"
},
  "geometry": {"coordinates":[8.848972,51.954128],"type":"Point"}
}