{
  "type": "Feature",
  "properties": {
    "iso:country":"DE",
    "sg:address":"Bahnhofstr. 28",
    "sg:city":"Saarbr\u00fccken",
    "sg:phone":"+49 681/30950",
    "sg:postcode":"66111",
    "sg:province":"Saarland",
    "wof:name":"Ibm Deutschland Gmbh",
    "wof:placetype":"venue"
},
  "geometry": {"coordinates":[6.9950690269,49.2343330383],"type":"Point"}
}