{
  "type": "Feature",
  "properties": {
    "iso:country":"DE",
    "sg:address":"Reutenhofstr. 6",
    "sg:city":"Oppenweiler",
    "sg:phone":"+49 7191/44385",
    "sg:postcode":"71570",
    "sg:province":"Baden-W\u00fcrttemberg",
    "wof:name":"Walter Bertsch",
    "wof:placetype":"venue"
},
  "geometry": {"coordinates":[9.461615,48.979042],"type":"Point"}
}