{
  "type": "Feature",
  "properties": {
    "iso:country":"DE",
    "sg:address":"Veilchenstr. 43",
    "sg:city":"Metten",
    "sg:phone":"+49 991/90120",
    "sg:postcode":"94526",
    "sg:province":"Bayern",
    "wof:name":"H. Weinzierl",
    "wof:placetype":"venue"
},
  "geometry": {"coordinates":[12.906247139,48.863445282],"type":"Point"}
}