{
  "type": "Feature",
  "properties": {
    "iso:country":"DE",
    "sg:address":"Klosterweg 12",
    "sg:city":"Wasserburg",
    "sg:phone":"+49 8071/50112",
    "sg:postcode":"83512",
    "sg:province":"Bayern",
    "wof:name":"Brand Bestattungsinsitut",
    "wof:placetype":"venue"
},
  "geometry": {"coordinates":[12.225085,48.058453],"type":"Point"}
}