{
  "type": "Feature",
  "properties": {
    "iso:country":"DE",
    "sg:address":"Kalkarer Str. 25",
    "sg:city":"Goch",
    "sg:phone":"+49 2823/18081",
    "sg:postcode":"47574",
    "sg:province":"Nordrhein-Westfalen",
    "wof:name":"Karl-heinz Silz Rechtsanwalt",
    "wof:placetype":"venue"
},
  "geometry": {"coordinates":[6.163424015,51.6798744202],"type":"Point"}
}