{
  "type": "Feature",
  "properties": {
    "iso:country":"DE",
    "sg:address":"Pastor-Wolff-Str. 12",
    "sg:city":"K\u00f6ln",
    "sg:phone":"+49 221/7123317",
    "sg:postcode":"50735",
    "sg:province":"Nordrhein-Westfalen",
    "wof:name":"Am Sportplatz",
    "wof:placetype":"venue"
},
  "geometry": {"coordinates":[6.9559497833,50.9928817749],"type":"Point"}
}