{
  "type": "Feature",
  "properties": {
    "iso:country":"DE",
    "sg:address":"Luchstr. 29",
    "sg:city":"Trebbin",
    "sg:phone":"+49 33731/15482",
    "sg:postcode":"14959",
    "sg:province":"Brandenburg",
    "wof:name":"U. Zamaitat",
    "wof:placetype":"venue"
},
  "geometry": {"coordinates":[13.23367,52.226482],"type":"Point"}
}