{
  "type": "Feature",
  "properties": {
    "iso:country":"DE",
    "sg:address":"Rellinghauser Str. 269",
    "sg:city":"Essen",
    "sg:phone":"+49 201/251618",
    "sg:postcode":"45136",
    "sg:province":"Nordrhein-Westfalen",
    "wof:name":"Soul Dog",
    "wof:placetype":"venue"
},
  "geometry": {"coordinates":[7.0327157974,51.4369392395],"type":"Point"}
}