{
  "type": "Feature",
  "properties": {
    "iso:country":"DE",
    "sg:address":"Hintere Bleiche 28",
    "sg:city":"Mainz",
    "sg:phone":"+49 6131/237600",
    "sg:postcode":"55116",
    "sg:province":"Rheinland-Pfalz",
    "wof:name":"Human Help Network E. V.",
    "wof:placetype":"venue"
},
  "geometry": {"coordinates":[8.2650108337,50.0030097961],"type":"Point"}
}