{
  "type": "Feature",
  "properties": {
    "iso:country":"DE",
    "sg:address":"Schmandgasse 32",
    "sg:city":"Gerbershausen",
    "sg:phone":"+49 36081/723",
    "sg:postcode":"37318",
    "sg:province":"Th\u00fcringen",
    "wof:name":"Erich Serverin",
    "wof:placetype":"venue"
},
  "geometry": {"coordinates":[9.985064,51.33651],"type":"Point"}
}