{
  "type": "Feature",
  "properties": {
    "iso:country":"DE",
    "sg:address":"Beim St. Peter 3",
    "sg:city":"M\u00fchlacker",
    "sg:phone":"+49 7041/4770",
    "sg:postcode":"75417",
    "sg:province":"Baden-W\u00fcrttemberg",
    "wof:name":"Karl-heinz Z\u00f6hner Bildhauer",
    "wof:placetype":"venue"
},
  "geometry": {"coordinates":[8.840952,48.949909],"type":"Point"}
}