{
  "type": "Feature",
  "properties": {
    "iso:country":"DE",
    "sg:address":"Bieberer Str. 286",
    "sg:city":"Offenbach",
    "sg:phone":"+49 69/855595",
    "sg:postcode":"63071",
    "sg:province":"Hessen",
    "wof:name":"Kickers Stadion",
    "wof:placetype":"venue"
},
  "geometry": {"coordinates":[8.7979259491,50.0941619873],"type":"Point"}
}