{
  "type": "Feature",
  "properties": {
    "iso:country":"DE",
    "sg:address":"Ried\u00e4cker 9",
    "sg:city":"Kressbronn",
    "sg:phone":"+49 7543/7188",
    "sg:postcode":"88079",
    "sg:province":"Baden-W\u00fcrttemberg",
    "wof:name":"Damhofer Immobilienmakler",
    "wof:placetype":"venue"
},
  "geometry": {"coordinates":[9.596575737,47.5932922363],"type":"Point"}
}