{
  "type": "Feature",
  "properties": {
    "iso:country":"DE",
    "sg:address":"Jahnstr. 35",
    "sg:city":"Erolzheim",
    "sg:phone":"+49 7354/577",
    "sg:postcode":"88453",
    "sg:province":"Baden-W\u00fcrttemberg",
    "wof:name":"Vereinsgastst\u00e4tte Sportverein Erolzheim E. V.",
    "wof:placetype":"venue"
},
  "geometry": {"coordinates":[10.0751113892,48.0873222351],"type":"Point"}
}