{
  "type": "Feature",
  "properties": {
    "iso:country":"DE",
    "sg:address":"Am B\u00fchl 7",
    "sg:city":"Mesenich",
    "sg:phone":"+49 2673/4578",
    "sg:postcode":"56820",
    "sg:province":"Rheinland-Pfalz",
    "wof:name":"Metzgerei Andries Gmbh",
    "wof:placetype":"venue"
},
  "geometry": {"coordinates":[7.1954350471,50.0970802307],"type":"Point"}
}