{
  "type": "Feature",
  "properties": {
    "iso:country":"DE",
    "sg:address":"Ringstr. 60 a",
    "sg:city":"Kranzberg",
    "sg:phone":"+49 8166/5525",
    "sg:postcode":"85402",
    "sg:province":"Bayern",
    "wof:name":"Sport-treff",
    "wof:placetype":"venue"
},
  "geometry": {"coordinates":[11.6014032364,48.4070129395],"type":"Point"}
}