{
  "type": "Feature",
  "properties": {
    "iso:country":"DE",
    "sg:address":"Am Tannenhof 14",
    "sg:city":"Schwerin",
    "sg:phone":"+49 385/5507033",
    "sg:postcode":"19061",
    "sg:province":"Mecklenburg-Vorpommern",
    "wof:name":"Dr. Med. Alfred Gerber",
    "wof:placetype":"venue"
},
  "geometry": {"coordinates":[11.433125,53.612755],"type":"Point"}
}