{
  "type": "Feature",
  "properties": {
    "iso:country":"DE",
    "sg:address":"Hauptstr. 136",
    "sg:city":"Sundern",
    "sg:phone":"+49 2933/4120",
    "sg:postcode":"59846",
    "sg:province":"Nordrhein-Westfalen",
    "wof:name":"Margarete De Boer",
    "wof:placetype":"venue"
},
  "geometry": {"coordinates":[8.004697,51.330482],"type":"Point"}
}