{
  "type": "Feature",
  "properties": {
    "iso:country":"DE",
    "sg:address":"Breitwasen 17",
    "sg:city":"Dettenhausen",
    "sg:phone":"+49 7157/5348995",
    "sg:postcode":"72135",
    "sg:province":"Baden-W\u00fcrttemberg",
    "wof:name":"Fliesen Meyer Gmbh",
    "wof:placetype":"venue"
},
  "geometry": {"coordinates":[9.1113166809,48.6094551086],"type":"Point"}
}