{
  "type": "Feature",
  "properties": {
    "iso:country":"DE",
    "sg:address":"Schwaikheimer Str. 20",
    "sg:city":"Winnenden",
    "sg:phone":"+49 7195/2227",
    "sg:postcode":"71364",
    "sg:province":"Baden-W\u00fcrttemberg",
    "wof:name":"Heinz Luckert",
    "wof:placetype":"venue"
},
  "geometry": {"coordinates":[9.395121,48.876076],"type":"Point"}
}