{
  "type": "Feature",
  "properties": {
    "iso:country":"DE",
    "sg:address":"Ehringhausen 66",
    "sg:city":"Remscheid",
    "sg:postcode":"42859",
    "sg:province":"Nordrhein-Westfalen",
    "wof:name":"Vanaloy Elektronik Handels Gmbh",
    "wof:placetype":"venue"
},
  "geometry": {"coordinates":[7.1742501259,51.1565284729],"type":"Point"}
}