{
  "type": "Feature",
  "properties": {
    "iso:country":"DE",
    "sg:address":"Bahnhofplatz 2",
    "sg:city":"Wangen",
    "sg:phone":"+49 7522/7020",
    "sg:postcode":"88239",
    "sg:province":"Baden-W\u00fcrttemberg",
    "wof:name":"Jehle Mineral\u00f6le- Vertriebs Gmbh",
    "wof:placetype":"venue"
},
  "geometry": {"coordinates":[9.81269,47.688381],"type":"Point"}
}