{
  "type": "Feature",
  "properties": {
    "iso:country":"DE",
    "sg:address":"Hauptstr. 31",
    "sg:city":"Lindenberg",
    "sg:phone":"+49 8381/2844",
    "sg:postcode":"88161",
    "sg:province":"Bayern",
    "wof:name":"Mode-merk Inh. Herbert Merk",
    "wof:placetype":"venue"
},
  "geometry": {"coordinates":[8.0953073502,49.3759765625],"type":"Point"}
}