{
  "type": "Feature",
  "properties": {
    "iso:country":"DE",
    "sg:address":"Kleine Gildewart 11",
    "sg:city":"Osnabr\u00fcck",
    "sg:phone":"+49 541/23345",
    "sg:postcode":"49074",
    "sg:province":"Niedersachsen",
    "wof:name":"Anzeigenverwaltung Harald H. Sch\u00e4del",
    "wof:placetype":"venue"
},
  "geometry": {"coordinates":[8.040564537,52.2772026062],"type":"Point"}
}