{
  "type": "Feature",
  "properties": {
    "iso:country":"DE",
    "sg:address":"Stolzingstr. 6a",
    "sg:city":"Bayreuth",
    "sg:phone":"+49 921/1662",
    "sg:postcode":"95445",
    "sg:province":"Bayern",
    "wof:name":"Manfred Hornfeck Versicherungsmakler Gmbh",
    "wof:placetype":"venue"
},
  "geometry": {"coordinates":[11.5901861191,49.9623413086],"type":"Point"}
}