{
  "type": "Feature",
  "properties": {
    "iso:country":"DE",
    "sg:address":"Streudorf 43",
    "sg:city":"Gunzenhausen",
    "sg:phone":"+49 9831/67710",
    "sg:postcode":"91710",
    "sg:province":"Bayern",
    "wof:name":"Claudia Rummer",
    "wof:placetype":"venue"
},
  "geometry": {"coordinates":[10.6901254654,49.1374053955],"type":"Point"}
}