{
  "type": "Feature",
  "properties": {
    "iso:country":"DE",
    "sg:address":"Bogenstr. 16",
    "sg:city":"Burg",
    "sg:phone":"+49 4825/9134",
    "sg:postcode":"25712",
    "sg:province":"Schleswig-Holstein",
    "wof:name":"H. Wunsch",
    "wof:placetype":"venue"
},
  "geometry": {"coordinates":[9.255757,53.994446],"type":"Point"}
}