{
  "type": "Feature",
  "properties": {
    "iso:country":"DE",
    "sg:address":"Ohmstr. 20a",
    "sg:city":"Langen",
    "sg:phone":"+49 6103/79017",
    "sg:postcode":"63225",
    "sg:province":"Hessen",
    "wof:name":"Kr\u00fcger Gmbh",
    "wof:placetype":"venue"
},
  "geometry": {"coordinates":[8.646358,50.000904],"type":"Point"}
}