{
  "type": "Feature",
  "properties": {
    "iso:country":"DE",
    "sg:address":"Rat-Deycks-Str. 12",
    "sg:city":"Leverkusen",
    "sg:phone":"+49 2171/27778",
    "sg:postcode":"51379",
    "sg:province":"Nordrhein-Westfalen",
    "wof:name":"Johan Vogelzang Praxis F\u00fcr Krankengymnastik",
    "wof:placetype":"venue"
},
  "geometry": {"coordinates":[7.003523,51.070461],"type":"Point"}
}