{
  "type": "Feature",
  "properties": {
    "iso:country":"DE",
    "sg:address":"Carl-Benz-Str. 16",
    "sg:city":"F\u00fcrth",
    "sg:phone":"+49 6253/5067",
    "sg:postcode":"64658",
    "sg:province":"Hessen",
    "wof:name":"Helferich & Sohn T\u00fcr- Und Fensterbau Gmbh",
    "wof:placetype":"venue"
},
  "geometry": {"coordinates":[8.77417,49.644466],"type":"Point"}
}