{
  "type": "Feature",
  "properties": {
    "iso:country":"DE",
    "sg:address":"Hauptstr. 230",
    "sg:city":"Gersdorf",
    "sg:phone":"+49 37203/4257",
    "sg:postcode":"09355",
    "sg:province":"Sachsen",
    "wof:name":"Dieter Jentsch",
    "wof:placetype":"venue"
},
  "geometry": {"coordinates":[12.707415,50.755863],"type":"Point"}
}