{
  "type": "Feature",
  "properties": {
    "iso:country":"DE",
    "sg:address":"G\u00e4nsetor 2",
    "sg:city":"Gifhorn",
    "sg:phone":"+49 5371/7964",
    "sg:postcode":"38518",
    "sg:province":"Niedersachsen",
    "wof:name":"Otto Franke",
    "wof:placetype":"venue"
},
  "geometry": {"coordinates":[10.54074,52.512718],"type":"Point"}
}