{
  "type": "Feature",
  "properties": {
    "iso:country":"DE",
    "sg:address":"Koblenzer Str. 242244",
    "sg:city":"Boppard",
    "sg:postcode":"56154",
    "sg:province":"Rheinland-Pfalz",
    "wof:name":"Breising Gmbh",
    "wof:placetype":"venue"
},
  "geometry": {"coordinates":[7.5801100731,50.2335510254],"type":"Point"}
}