{
  "type": "Feature",
  "properties": {
    "iso:country":"DE",
    "sg:address":"Br\u00fcckenstr. 30",
    "sg:city":"M\u00fchlhausen",
    "sg:phone":"+49 36014/6520",
    "sg:postcode":"99974",
    "sg:province":"Th\u00fcringen",
    "wof:name":"Br\u00fccken-apotheke",
    "wof:placetype":"venue"
},
  "geometry": {"coordinates":[10.460303,51.208794],"type":"Point"}
}