{
  "type": "Feature",
  "properties": {
    "iso:country":"DE",
    "sg:address":"Br\u00fcckenstr. 57",
    "sg:city":"Rheine",
    "sg:phone":"+49 5975/297",
    "sg:postcode":"48432",
    "sg:province":"Nordrhein-Westfalen",
    "wof:name":"Heinz Homann",
    "wof:placetype":"venue"
},
  "geometry": {"coordinates":[7.516849,52.236931],"type":"Point"}
}