{
  "type": "Feature",
  "properties": {
    "iso:country":"DE",
    "sg:address":"Apostelgasse 4",
    "sg:city":"Bad Blankenburg",
    "sg:phone":"+49 36741/42042",
    "sg:postcode":"07422",
    "sg:province":"Th\u00fcringen",
    "wof:name":"G. Gr\u00fcner",
    "wof:placetype":"venue"
},
  "geometry": {"coordinates":[11.2644252777,50.6838302612],"type":"Point"}
}