{
  "type": "Feature",
  "properties": {
    "iso:country":"DE",
    "sg:address":"Lange Reihe 84",
    "sg:city":"Hamburg",
    "sg:phone":"+49 40/247168",
    "sg:postcode":"20099",
    "sg:province":"Hamburg",
    "wof:name":"A. Haargenau Kg",
    "wof:placetype":"venue"
},
  "geometry": {"coordinates":[10.0126190186,53.5582237244],"type":"Point"}
}