{
  "type": "Feature",
  "properties": {
    "iso:country":"DE",
    "sg:address":"Ingolst\u00e4dter Str. 20",
    "sg:city":"M\u00fcnchen",
    "sg:phone":"+49 89/3598410",
    "sg:postcode":"80807",
    "sg:province":"Bayern",
    "wof:name":"China Restaurant Lychee-garden",
    "wof:placetype":"venue"
},
  "geometry": {"coordinates":[11.5848073959,48.1858406067],"type":"Point"}
}