{
  "type": "Feature",
  "properties": {
    "iso:country":"DE",
    "sg:address":"Weihestr. 33",
    "sg:city":"L\u00f6hne",
    "sg:phone":"+49 5731/8886",
    "sg:postcode":"32584",
    "sg:province":"Nordrhein-Westfalen",
    "wof:name":"Reinhard Fu\u00df",
    "wof:placetype":"venue"
},
  "geometry": {"coordinates":[8.758524,52.198021],"type":"Point"}
}