{
  "type": "Feature",
  "properties": {
    "iso:country":"DE",
    "sg:address":"Weinmarkt 15",
    "sg:city":"Memmingen",
    "sg:postcode":"87700",
    "sg:province":"Bayern",
    "wof:name":"Rotary-club",
    "wof:placetype":"venue"
},
  "geometry": {"coordinates":[10.1809988022,47.9846229553],"type":"Point"}
}