{
  "type": "Feature",
  "properties": {
    "iso:country":"DE",
    "sg:address":"Holtenauer Str. 96",
    "sg:city":"Kiel",
    "sg:phone":"+49 431/570230",
    "sg:postcode":"24105",
    "sg:province":"Schleswig-Holstein",
    "wof:name":"Media Port Anja Wettengel E. K.",
    "wof:placetype":"venue"
},
  "geometry": {"coordinates":[10.133482933,54.3345832825],"type":"Point"}
}