{
  "type": "Feature",
  "properties": {
    "iso:country":"DE",
    "sg:address":"Niederstr. 15",
    "sg:city":"Krefeld",
    "sg:phone":"+49 2151/480004",
    "sg:postcode":"47829",
    "sg:province":"Nordrhein-Westfalen",
    "wof:name":"Eisendiegel",
    "wof:placetype":"venue"
},
  "geometry": {"coordinates":[6.6491222382,51.3545875549],"type":"Point"}
}