{
  "type": "Feature",
  "properties": {
    "iso:country":"DE",
    "sg:address":"Baumwall 7",
    "sg:city":"Hamburg",
    "sg:phone":"+49 40/3709040",
    "sg:postcode":"20459",
    "sg:province":"Hamburg",
    "wof:name":"Pfl\u00fcger & Schulz Unternehmensberatung Gmbh",
    "wof:placetype":"venue"
},
  "geometry": {"coordinates":[9.98188591,53.5445594788],"type":"Point"}
}