{
  "type": "Feature",
  "properties": {
    "iso:country":"DE",
    "sg:address":"Alpenstr. 31",
    "sg:city":"Legau",
    "sg:postcode":"87764",
    "sg:province":"Bayern",
    "wof:name":"Fassnacht Ingenieure Gmbh",
    "wof:placetype":"venue"
},
  "geometry": {"coordinates":[10.1234445572,47.8531341553],"type":"Point"}
}