{
  "type": "Feature",
  "properties": {
    "iso:country":"DE",
    "sg:address":"Pfaffengasse 32",
    "sg:city":"Koblenz",
    "sg:phone":"+49 261/21202",
    "sg:postcode":"56072",
    "sg:province":"Rheinland-Pfalz",
    "wof:name":"August Oellig",
    "wof:placetype":"venue"
},
  "geometry": {"coordinates":[7.548517,50.367134],"type":"Point"}
}