{
  "type": "Feature",
  "properties": {
    "iso:country":"DE",
    "sg:address":"Westerwaldstrasse 30",
    "sg:city":"Bendorf-Stromberg",
    "sg:phone":"+49 2601/912303",
    "sg:postcode":"56170",
    "sg:province":"Rheinland-Pfalz",
    "wof:name":"Euro-kurier",
    "wof:placetype":"venue"
},
  "geometry": {"coordinates":[7.604141,50.461575],"type":"Point"}
}