{
  "type": "Feature",
  "properties": {
    "iso:country":"DE",
    "sg:address":"Hedelfinger Str. 8",
    "sg:city":"Stuttgart",
    "sg:phone":"+49 711/4065482",
    "sg:postcode":"70327",
    "sg:province":"Baden-W\u00fcrttemberg",
    "wof:name":"Digital Imaging International Gmbh",
    "wof:placetype":"venue"
},
  "geometry": {"coordinates":[9.2454967499,48.7709922791],"type":"Point"}
}