{
  "type": "Feature",
  "properties": {
    "iso:country":"DE",
    "sg:address":"Am Winterhafen 19",
    "sg:city":"Mainz",
    "sg:phone":"+49 6131/228681",
    "sg:postcode":"55131",
    "sg:province":"Rheinland-Pfalz",
    "wof:name":"Bistro De Les",
    "wof:placetype":"venue"
},
  "geometry": {"coordinates":[8.2866020203,49.9919090271],"type":"Point"}
}