{
  "type": "Feature",
  "properties": {
    "iso:country":"DE",
    "sg:address":"Bahnhofstr. 3",
    "sg:city":"Seeheim-Jugenheim",
    "sg:phone":"+49 6257/1753",
    "sg:postcode":"64342",
    "sg:province":"Hessen",
    "wof:name":"Frank-henry Arnold Architekt",
    "wof:placetype":"venue"
},
  "geometry": {"coordinates":[8.6352,49.755787],"type":"Point"}
}