{
  "type": "Feature",
  "properties": {
    "iso:country":"DE",
    "sg:address":"Brambarg 6",
    "sg:city":"Pinneberg",
    "sg:phone":"+49 4101/61843",
    "sg:postcode":"25421",
    "sg:province":"Schleswig-Holstein",
    "wof:name":"Martin Brenke",
    "wof:placetype":"venue"
},
  "geometry": {"coordinates":[9.775839,53.626263],"type":"Point"}
}