{
  "type": "Feature",
  "properties": {
    "iso:country":"DE",
    "sg:address":"Stadtfeldstr. 24",
    "sg:city":"Ornbau",
    "sg:phone":"+49 9826/416",
    "sg:postcode":"91737",
    "sg:province":"Bayern",
    "wof:name":"Bz Pinselentwicklungs- U. Herstellungs Gmbh",
    "wof:placetype":"venue"
},
  "geometry": {"coordinates":[10.663860321,49.1764602661],"type":"Point"}
}