{
  "type": "Feature",
  "properties": {
    "iso:country":"DE",
    "sg:address":"Bonner Str. 56",
    "sg:city":"Erftstadt",
    "sg:phone":"+49 2235/955510",
    "sg:postcode":"50374",
    "sg:province":"Nordrhein-Westfalen",
    "wof:name":"K. H. Scherer Heilpraktiker",
    "wof:placetype":"venue"
},
  "geometry": {"coordinates":[6.7724318504,50.7996025085],"type":"Point"}
}