{
  "type": "Feature",
  "properties": {
    "iso:country":"DE",
    "sg:address":"Emser Str. 143",
    "sg:city":"Koblenz",
    "sg:phone":"+49 261/73700",
    "sg:postcode":"56076",
    "sg:province":"Rheinland-Pfalz",
    "wof:name":"Reimund Bender Architekt",
    "wof:placetype":"venue"
},
  "geometry": {"coordinates":[7.600534,50.343834],"type":"Point"}
}