{
  "type": "Feature",
  "properties": {
    "iso:country":"DE",
    "sg:address":"Reiherweg 19",
    "sg:city":"Wesel",
    "sg:phone":"+49 281/63544",
    "sg:postcode":"46487",
    "sg:province":"Nordrhein-Westfalen",
    "wof:name":"Ps Gesellschaft F\u00fcr Tragwerksplanung Mbh",
    "wof:placetype":"venue"
},
  "geometry": {"coordinates":[6.604364872,51.6889610291],"type":"Point"}
}