{
  "type": "Feature",
  "properties": {
    "iso:country":"DE",
    "sg:address":"Im H\u00f6nzel 17",
    "sg:city":"Gangelt",
    "sg:phone":"+49 2454/939568",
    "sg:postcode":"52538",
    "sg:province":"Nordrhein-Westfalen",
    "wof:name":"Gonstalla Keramik-fliesenstudio",
    "wof:placetype":"venue"
},
  "geometry": {"coordinates":[6.0495629311,51.000667572],"type":"Point"}
}