{
  "type": "Feature",
  "properties": {
    "iso:country":"DE",
    "sg:address":"Fichtenstr. 15",
    "sg:city":"Obertshausen",
    "sg:phone":"+49 6104/74132",
    "sg:postcode":"63179",
    "sg:province":"Hessen",
    "wof:name":"G\u00fcnter Holm",
    "wof:placetype":"venue"
},
  "geometry": {"coordinates":[8.857796,50.077904],"type":"Point"}
}