{
  "type": "Feature",
  "properties": {
    "iso:country":"DE",
    "sg:address":"Unterstadtstr. 16",
    "sg:city":"Meersburg",
    "sg:phone":"+49 7532/6548",
    "sg:postcode":"88709",
    "sg:province":"Baden-W\u00fcrttemberg",
    "wof:name":"A. Federer",
    "wof:placetype":"venue"
},
  "geometry": {"coordinates":[9.270322,47.693069],"type":"Point"}
}