{
  "type": "Feature",
  "properties": {
    "iso:country":"DE",
    "sg:address":"Darmst\u00e4dter Str. 22",
    "sg:city":"Bischofsheim",
    "sg:phone":"+49 6144/8098",
    "sg:postcode":"65474",
    "sg:province":"Hessen",
    "wof:name":"Klaus Dornheim Steuerberater",
    "wof:placetype":"venue"
},
  "geometry": {"coordinates":[8.3570604324,49.9868888855],"type":"Point"}
}