{
  "type": "Feature",
  "properties": {
    "iso:country":"DE",
    "sg:address":"Trilluper Weg 65",
    "sg:city":"Hamburg",
    "sg:phone":"+49 40/6071015",
    "sg:postcode":"22397",
    "sg:province":"Hamburg",
    "wof:name":"Heinz Schniete Werbegeschenke",
    "wof:placetype":"venue"
},
  "geometry": {"coordinates":[10.1115255356,53.6989326477],"type":"Point"}
}