{
  "type": "Feature",
  "properties": {
    "iso:country":"DE",
    "sg:address":"Zur Dringe 10",
    "sg:city":"Bad Driburg-Dringenberg",
    "sg:phone":"+49 5259",
    "sg:postcode":"33014",
    "sg:province":"Nordrhein-Westfalen",
    "wof:name":"Leifer & Hamann Elektrotechnik",
    "wof:placetype":"venue"
},
  "geometry": {"coordinates":[9.0532751083,51.6754074097],"type":"Point"}
}