{
  "type": "Feature",
  "properties": {
    "iso:country":"DE",
    "sg:address":"Alt R\u00f6delheim 7",
    "sg:city":"Frankfurt",
    "sg:phone":"+49 69/785573",
    "sg:postcode":"60489",
    "sg:province":"Hessen",
    "wof:name":"S. Karan",
    "wof:placetype":"venue"
},
  "geometry": {"coordinates":[8.6125516891,50.1244812012],"type":"Point"}
}