{
  "type": "Feature",
  "properties": {
    "iso:country":"DE",
    "sg:address":"H\u00f6henstr. 4",
    "sg:city":"F\u00fcssen",
    "sg:phone":"+49 8362/7269",
    "sg:postcode":"87629",
    "sg:province":"Bayern",
    "wof:name":"X. Hipp",
    "wof:placetype":"venue"
},
  "geometry": {"coordinates":[10.6836051941,47.6046104431],"type":"Point"}
}