{
  "type": "Feature",
  "properties": {
    "iso:country":"DE",
    "sg:address":"Alte Poststr. 9",
    "sg:city":"Fichtenau",
    "sg:phone":"+49 7962/577",
    "sg:postcode":"74579",
    "sg:province":"Baden-W\u00fcrttemberg",
    "wof:name":"Stollenmeier & Bidlingmaier Textilvertriebs-gmbh",
    "wof:placetype":"venue"
},
  "geometry": {"coordinates":[10.225435257,49.0546875],"type":"Point"}
}