{
  "type": "Feature",
  "properties": {
    "iso:country":"DE",
    "sg:address":"Hauptstr. 74",
    "sg:city":"Lobbach",
    "sg:phone":"+49 6226/41419",
    "sg:postcode":"74931",
    "sg:province":"Baden-W\u00fcrttemberg",
    "wof:name":"Wilhelm Saueressig",
    "wof:placetype":"venue"
},
  "geometry": {"coordinates":[8.8924198151,49.3749504089],"type":"Point"}
}