{
  "type": "Feature",
  "properties": {
    "iso:country":"DE",
    "sg:address":"Machnower Str. 17",
    "sg:city":"Berlin",
    "sg:phone":"+49 30/8156076",
    "sg:postcode":"14165",
    "sg:province":"Berlin",
    "wof:name":"Michael Geisler",
    "wof:placetype":"venue"
},
  "geometry": {"coordinates":[13.2570972443,52.4295310974],"type":"Point"}
}