{
  "type": "Feature",
  "properties": {
    "iso:country":"DE",
    "sg:address":"Festplatzstr. 8",
    "sg:city":"W\u00e4chtersbach",
    "sg:phone":"+49 6053/61666",
    "sg:postcode":"63607",
    "sg:province":"Hessen",
    "wof:name":"Rieser Gmbh",
    "wof:placetype":"venue"
},
  "geometry": {"coordinates":[9.317369,50.252495],"type":"Point"}
}