{
  "type": "Feature",
  "properties": {
    "iso:country":"DE",
    "sg:address":"Alter Stadtweg 5 a",
    "sg:city":"Stockstadt",
    "sg:phone":"+49 6027/1574",
    "sg:postcode":"63811",
    "sg:province":"Bayern",
    "wof:name":"Inge Egner",
    "wof:placetype":"venue"
},
  "geometry": {"coordinates":[9.065169,49.979233],"type":"Point"}
}