{
  "type": "Feature",
  "properties": {
    "iso:country":"DE",
    "sg:address":"Oehlertring 13",
    "sg:city":"Berlin",
    "sg:phone":"+49 30/45978505",
    "sg:postcode":"12169",
    "sg:province":"Berlin",
    "wof:name":"Frank Thiedemann",
    "wof:placetype":"venue"
},
  "geometry": {"coordinates":[13.3533,52.452915],"type":"Point"}
}