{
  "type": "Feature",
  "properties": {
    "iso:country":"DE",
    "sg:address":"Karlstadter Str. 18",
    "sg:city":"Karlstadt",
    "sg:postcode":"97753",
    "sg:province":"Bayern",
    "wof:name":"Landb\u00e4ckerei Schaub Gmbh",
    "wof:placetype":"venue"
},
  "geometry": {"coordinates":[9.682626,49.991016],"type":"Point"}
}