{
  "type": "Feature",
  "properties": {
    "iso:country":"DE",
    "sg:address":"Bolzhurststr 75b",
    "sg:city":"Willst\u00e4tt",
    "sg:phone":"+49 7852/91290",
    "sg:postcode":"77731",
    "sg:province":"Baden-W\u00fcrttemberg",
    "wof:name":"Moser Gmbh",
    "wof:placetype":"venue"
},
  "geometry": {"coordinates":[7.923912,48.578129],"type":"Point"}
}