{
  "type": "Feature",
  "properties": {
    "iso:country":"DE",
    "sg:address":"Giebel 37",
    "sg:city":"Wuppertal",
    "sg:phone":"+49 4920/2746255",
    "sg:postcode":"42327",
    "sg:province":"Nordrhein-Westfalen",
    "wof:name":"Steimer Leiterplatten Gmbh",
    "wof:placetype":"venue"
},
  "geometry": {"coordinates":[7.094561,51.248379],"type":"Point"}
}