{
  "type": "Feature",
  "properties": {
    "iso:country":"DE",
    "sg:address":"Augsburger Str. 38",
    "sg:city":"Memmingerberg",
    "sg:phone":"+49 8331/80303",
    "sg:postcode":"87766",
    "sg:province":"Bayern",
    "wof:name":"Dr. Scheiber Consulting Unternehmensberatung Gmbh",
    "wof:placetype":"venue"
},
  "geometry": {"coordinates":[10.208325,47.991444],"type":"Point"}
}