{
  "type": "Feature",
  "properties": {
    "iso:country":"DE",
    "sg:address":"Erlen 13",
    "sg:city":"Wipperf\u00fcrth",
    "sg:phone":"+49 2267/9230",
    "sg:postcode":"51688",
    "sg:province":"Nordrhein-Westfalen",
    "wof:name":"Hotel Biesenbach",
    "wof:placetype":"venue"
},
  "geometry": {"coordinates":[7.3734760284,51.0969581604],"type":"Point"}
}