{
  "type": "Feature",
  "properties": {
    "iso:country":"DE",
    "sg:address":"Bahnhofstr. 100",
    "sg:city":"Oberthal",
    "sg:phone":"+49 6854/8542",
    "sg:postcode":"66649",
    "sg:province":"Saarland",
    "wof:name":"Alice Ost",
    "wof:placetype":"venue"
},
  "geometry": {"coordinates":[7.0799670219,49.5127334595],"type":"Point"}
}