{
  "type": "Feature",
  "properties": {
    "iso:country":"DE",
    "sg:address":"Aroser Allee 104",
    "sg:city":"Berlin",
    "sg:postcode":"13407",
    "sg:province":"Berlin",
    "wof:name":"Ebnet-homesitting",
    "wof:placetype":"venue"
},
  "geometry": {"coordinates":[13.352469,52.565838],"type":"Point"}
}