{
  "type": "Feature",
  "properties": {
    "iso:country":"DE",
    "sg:address":"Kleine Wefersstr. 100",
    "sg:city":"Krefeld",
    "sg:phone":"+49 4945/511221",
    "sg:postcode":"47803",
    "sg:province":"Nordrhein-Westfalen",
    "wof:name":"Do Druck",
    "wof:placetype":"venue"
},
  "geometry": {"coordinates":[10.3206548691,53.9250488281],"type":"Point"}
}