{
  "type": "Feature",
  "properties": {
    "iso:country":"DE",
    "sg:address":"Rembrandtstrasse 3",
    "sg:city":"Heddesheim",
    "sg:postcode":"68542",
    "sg:province":"Baden-W\u00fcrttemberg",
    "wof:name":"Sohns-wildlife Tier Und Naturfotografie",
    "wof:placetype":"venue"
},
  "geometry": {"coordinates":[8.594686,49.504204],"type":"Point"}
}