{
  "type": "Feature",
  "properties": {
    "iso:country":"DE",
    "sg:address":"Werther Str. 78",
    "sg:city":"Bocholt",
    "sg:phone":"+49 2871/27960",
    "sg:postcode":"46395",
    "sg:province":"Nordrhein-Westfalen",
    "wof:name":"W\u00fcst Marketing Und Logistik Gmbh",
    "wof:placetype":"venue"
},
  "geometry": {"coordinates":[6.594566,51.836651],"type":"Point"}
}