{
  "type": "Feature",
  "properties": {
    "iso:country":"DE",
    "sg:address":"Bayreuther Str. 6",
    "sg:city":"Igensdorf",
    "sg:postcode":"91338",
    "sg:province":"Bayern",
    "wof:name":"Immobilien Erlwein Gmbh",
    "wof:placetype":"venue"
},
  "geometry": {"coordinates":[11.2344341278,49.6193695068],"type":"Point"}
}