{
  "type": "Feature",
  "properties": {
    "iso:country":"DE",
    "sg:address":"Dreik\u00f6nigstr. 15",
    "sg:city":"Schwetzingen",
    "sg:phone":"+49 4962/0210056",
    "sg:postcode":"68723",
    "sg:province":"Baden-W\u00fcrttemberg",
    "wof:name":"Bayerische Hypotheken- Und Wechsel, Bank Ag",
    "wof:placetype":"venue"
},
  "geometry": {"coordinates":[8.572506,49.38607],"type":"Point"}
}