{
  "type": "Feature",
  "properties": {
    "iso:country":"DE",
    "sg:address":"Bahnhofstr. 33",
    "sg:city":"Speicher",
    "sg:phone":"+49 6562/2445",
    "sg:postcode":"54662",
    "sg:province":"Rheinland-Pfalz",
    "wof:name":"K. G. Faber",
    "wof:placetype":"venue"
},
  "geometry": {"coordinates":[6.6353120804,49.9351844788],"type":"Point"}
}