{
  "type": "Feature",
  "properties": {
    "iso:country":"DE",
    "sg:address":"Lange Str. 83",
    "sg:city":"Waldkirch",
    "sg:phone":"+49 7681/491860",
    "sg:postcode":"79183",
    "sg:province":"Baden-W\u00fcrttemberg",
    "wof:name":"St\u00f6rr Fensterbau Gmbh",
    "wof:placetype":"venue"
},
  "geometry": {"coordinates":[7.963555,48.096169],"type":"Point"}
}