{
  "type": "Feature",
  "properties": {
    "iso:country":"DE",
    "sg:address":"Scheidemannstr. 17",
    "sg:city":"Nidderau",
    "sg:phone":"+49 6187/25006",
    "sg:postcode":"61130",
    "sg:province":"Hessen",
    "wof:name":"W. Emmerich",
    "wof:placetype":"venue"
},
  "geometry": {"coordinates":[8.888469,50.219555],"type":"Point"}
}