{
  "type": "Feature",
  "properties": {
    "iso:country":"DE",
    "sg:address":"Rotdornstr. 18",
    "sg:city":"Velbert",
    "sg:phone":"+49 2051/250545",
    "sg:postcode":"42549",
    "sg:province":"Nordrhein-Westfalen",
    "wof:name":"Bembe-parkett-fabrik Jucker Gmbh & Co. Kg",
    "wof:placetype":"venue"
},
  "geometry": {"coordinates":[7.0440459251,51.3328552246],"type":"Point"}
}