{
  "type": "Feature",
  "properties": {
    "iso:country":"DE",
    "sg:address":"Wittinger Str. 3",
    "sg:city":"Steinhorst",
    "sg:phone":"+49 5148/301",
    "sg:postcode":"29367",
    "sg:province":"Niedersachsen",
    "wof:name":"Heinrich Buhr",
    "wof:placetype":"venue"
},
  "geometry": {"coordinates":[10.410506,52.690182],"type":"Point"}
}