{
  "type": "Feature",
  "properties": {
    "iso:country":"DE",
    "sg:address":"Wilhelmstr. 1b",
    "sg:city":"Bielefeld",
    "sg:phone":"+49 521/60864",
    "sg:postcode":"33602",
    "sg:province":"Nordrhein-Westfalen",
    "wof:name":"Reichsbund Der Kriegsopfer Behinderten Sozialrenter E. V.",
    "wof:placetype":"venue"
},
  "geometry": {"coordinates":[8.534992218,52.0239143372],"type":"Point"}
}