{
  "type": "Feature",
  "properties": {
    "iso:country":"DE",
    "sg:address":"Illesheimer Str. 18",
    "sg:city":"Bad Windsheim",
    "sg:phone":"+49 9841/3732",
    "sg:postcode":"91438",
    "sg:province":"Bayern",
    "wof:name":"Pr\u00e4zisions-formenbau Lothar Lehnardt Kg",
    "wof:placetype":"venue"
},
  "geometry": {"coordinates":[10.404984,49.496361],"type":"Point"}
}