{
  "type": "Feature",
  "properties": {
    "iso:country":"DE",
    "sg:address":"Taunusstr. 45",
    "sg:city":"M\u00fcnchen",
    "sg:phone":"+49 89/352311",
    "sg:postcode":"80807",
    "sg:province":"Bayern",
    "wof:name":"Hegener",
    "wof:placetype":"venue"
},
  "geometry": {"coordinates":[11.5813980103,48.1886901855],"type":"Point"}
}