{
  "type": "Feature",
  "properties": {
    "iso:country":"DE",
    "sg:address":"Am Brustert 56",
    "sg:city":"Krefeld",
    "sg:phone":"+49 2151/730364",
    "sg:postcode":"47839",
    "sg:province":"Nordrhein-Westfalen",
    "wof:name":"Kurt Sch\u00fcrmanns Elektroinstallation",
    "wof:placetype":"venue"
},
  "geometry": {"coordinates":[6.509375,51.383312],"type":"Point"}
}