{
  "type": "Feature",
  "properties": {
    "iso:country":"DE",
    "sg:address":"Elisabethstr. 10",
    "sg:city":"Aachen",
    "sg:phone":"+49 241/4325216",
    "sg:postcode":"52062",
    "sg:province":"Nordrhein-Westfalen",
    "wof:name":"Elisabethhalle",
    "wof:placetype":"venue"
},
  "geometry": {"coordinates":[6.0853228569,50.7733535767],"type":"Point"}
}