{
  "type": "Feature",
  "properties": {
    "iso:country":"DE",
    "sg:address":"Schulstr. 11",
    "sg:city":"Schwesing",
    "sg:phone":"+49 4841/1010",
    "sg:postcode":"25813",
    "sg:province":"Schleswig-Holstein",
    "wof:name":"Wolfgang Eggert Inh. Peter Eggert",
    "wof:placetype":"venue"
},
  "geometry": {"coordinates":[9.1396226883,54.4954605103],"type":"Point"}
}