{
  "type": "Feature",
  "properties": {
    "iso:country":"DE",
    "sg:address":"Ernst Rein Str. 84",
    "sg:city":"Bielefeld",
    "sg:postcode":"33613",
    "sg:province":"Nordrhein-Westfalen",
    "wof:name":"Springbohnen.de \u00b4der Kuriose Internetshop\u00b4",
    "wof:placetype":"venue"
},
  "geometry": {"coordinates":[8.5283517838,52.0336608887],"type":"Point"}
}