{
  "type": "Feature",
  "properties": {
    "iso:country":"DE",
    "sg:address":"Bischof-Rei\u00dfmann-Platz 2",
    "sg:city":"Giebelstadt",
    "sg:phone":"+49 9336/99862",
    "sg:postcode":"97232",
    "sg:province":"Bayern",
    "wof:name":"H. Glos",
    "wof:placetype":"venue"
},
  "geometry": {"coordinates":[9.900803566,49.6272621155],"type":"Point"}
}