{
  "type": "Feature",
  "properties": {
    "iso:country":"DE",
    "sg:address":"Helene-Lange-Str. 10",
    "sg:city":"Hamburg",
    "sg:phone":"+49 40/4229779",
    "sg:postcode":"20144",
    "sg:province":"Hamburg",
    "wof:name":"H. J\u00fcptner",
    "wof:placetype":"venue"
},
  "geometry": {"coordinates":[9.976185,53.574425],"type":"Point"}
}