{
  "type": "Feature",
  "properties": {
    "iso:country":"DE",
    "sg:address":"Brassertstr. 95",
    "sg:city":"Marl",
    "sg:phone":"+49 2365/63645",
    "sg:postcode":"45768",
    "sg:province":"Nordrhein-Westfalen",
    "wof:name":"G. Sch\u00e4tzlein",
    "wof:placetype":"venue"
},
  "geometry": {"coordinates":[7.0825910568,51.6585655212],"type":"Point"}
}