{
  "type": "Feature",
  "properties": {
    "iso:country":"DE",
    "sg:address":"Fuhsestr. 2",
    "sg:city":"Hannover",
    "sg:phone":"+49 511/2716910",
    "sg:postcode":"30419",
    "sg:province":"Niedersachsen",
    "wof:name":"Hannagret Bueker",
    "wof:placetype":"venue"
},
  "geometry": {"coordinates":[9.670674324,52.4000549316],"type":"Point"}
}