{
  "type": "Feature",
  "properties": {
    "iso:country":"DE",
    "sg:address":"Heidkampsweg 113",
    "sg:city":"Rellingen",
    "sg:phone":"+49 4101/473063",
    "sg:postcode":"25462",
    "sg:province":"Schleswig-Holstein",
    "wof:name":"Acosa Wohnungsbauges. Mbh",
    "wof:placetype":"venue"
},
  "geometry": {"coordinates":[9.8557920456,53.6373023987],"type":"Point"}
}