{
  "type": "Feature",
  "properties": {
    "iso:country":"DE",
    "sg:address":"Waagestr. 1",
    "sg:city":"Neubrandenburg",
    "sg:phone":"+49 395/5826661",
    "sg:postcode":"17033",
    "sg:province":"Mecklenburg-Vorpommern",
    "wof:name":"Marien-apotheke Maria Gro\u00dfe Hokamp",
    "wof:placetype":"venue"
},
  "geometry": {"coordinates":[13.2593259811,53.5567970276],"type":"Point"}
}