{
  "type": "Feature",
  "properties": {
    "iso:country":"DE",
    "sg:address":"Berliner Str. 13 A",
    "sg:city":"Homberg",
    "sg:phone":"+49 6633/9770",
    "sg:postcode":"35315",
    "sg:province":"Hessen",
    "wof:name":"Cadform Msx Engineering Gmbh",
    "wof:placetype":"venue"
},
  "geometry": {"coordinates":[9.0015916824,50.732460022],"type":"Point"}
}