{
  "type": "Feature",
  "properties": {
    "iso:country":"DE",
    "sg:address":"Gartenstr. 5",
    "sg:city":"Grenzach-Wyhlen",
    "sg:phone":"+49 7624/3415",
    "sg:postcode":"79639",
    "sg:province":"Baden-W\u00fcrttemberg",
    "wof:name":"Klaus Blubacher Steuerberater",
    "wof:placetype":"venue"
},
  "geometry": {"coordinates":[7.6913042068,47.549041748],"type":"Point"}
}