{
  "type": "Feature",
  "properties": {
    "iso:country":"DE",
    "sg:address":"Hauptstr. 39",
    "sg:city":"Busenberg",
    "sg:phone":"+49 6391",
    "sg:postcode":"76891",
    "sg:province":"Rheinland-Pfalz",
    "wof:name":"Gruppen\u00fcbernachtungen B\u00fcrgerst\u00fcbchen",
    "wof:placetype":"venue"
},
  "geometry": {"coordinates":[7.8312158585,49.130531311],"type":"Point"}
}