{
  "type": "Feature",
  "properties": {
    "iso:country":"DE",
    "sg:address":"Am Germansberg 60",
    "sg:city":"Speyer",
    "sg:phone":"+49 6232/75490",
    "sg:postcode":"67346",
    "sg:province":"Rheinland-Pfalz",
    "wof:name":"Bisch\u00f6fliches Priesterseminar",
    "wof:placetype":"venue"
},
  "geometry": {"coordinates":[8.436127,49.307507],"type":"Point"}
}