{
  "type": "Feature",
  "properties": {
    "iso:country":"DE",
    "sg:address":"Dallhofweg 19",
    "sg:city":"Dissen",
    "sg:phone":"+49 5421/1682",
    "sg:postcode":"49201",
    "sg:province":"Niedersachsen",
    "wof:name":"Heinz Wiethe Ingenieur",
    "wof:placetype":"venue"
},
  "geometry": {"coordinates":[8.1898899078,52.1033401489],"type":"Point"}
}