{
  "type": "Feature",
  "properties": {
    "iso:country":"DE",
    "sg:address":"Cyriaksring 9A",
    "sg:city":"Braunschweig",
    "sg:phone":"+49 531/890255",
    "sg:postcode":"38118",
    "sg:province":"Niedersachsen",
    "wof:name":"Transfer Tech Computer Gmbh",
    "wof:placetype":"venue"
},
  "geometry": {"coordinates":[10.5084209442,52.2534866333],"type":"Point"}
}