{
  "type": "Feature",
  "properties": {
    "iso:country":"DE",
    "sg:address":"Verdistr. 64",
    "sg:city":"Hilden",
    "sg:phone":"+49 2103/45336",
    "sg:postcode":"40724",
    "sg:province":"Nordrhein-Westfalen",
    "wof:name":"Peter Janke",
    "wof:placetype":"venue"
},
  "geometry": {"coordinates":[6.930344,51.178082],"type":"Point"}
}