{
  "type": "Feature",
  "properties": {
    "iso:country":"DE",
    "sg:address":"Kaiserring 12",
    "sg:city":"Villingen-Schwenningen",
    "sg:phone":"+49 7721/96020",
    "sg:postcode":"78050",
    "sg:province":"Baden-W\u00fcrttemberg",
    "wof:name":"Friesia Gmbh & Co.",
    "wof:placetype":"venue"
},
  "geometry": {"coordinates":[8.4633646011,48.0568122864],"type":"Point"}
}