{
  "type": "Feature",
  "properties": {
    "iso:country":"DE",
    "sg:address":"Derler Str. 43",
    "sg:city":"P\u00fcttlingen",
    "sg:phone":"+49 6898/66374",
    "sg:postcode":"66346",
    "sg:province":"Saarland",
    "wof:name":"H. J. Karrenbauer",
    "wof:placetype":"venue"
},
  "geometry": {"coordinates":[6.8766179085,49.28647995],"type":"Point"}
}