{
  "type": "Feature",
  "properties": {
    "iso:country":"DE",
    "sg:address":"Oeseder Str. 99",
    "sg:city":"Georgsmarienh\u00fctte",
    "sg:phone":"+49 5401/86570",
    "sg:postcode":"49124",
    "sg:province":"Niedersachsen",
    "wof:name":"Buchhandlung Sedlmair",
    "wof:placetype":"venue"
},
  "geometry": {"coordinates":[8.0664548874,52.2036972046],"type":"Point"}
}