{
  "type": "Feature",
  "properties": {
    "iso:country":"DE",
    "sg:address":"Berghauser Str 31",
    "sg:city":"Wuppertal",
    "sg:phone":"+49 202/473045",
    "sg:postcode":"42349",
    "sg:province":"Nordrhein-Westfalen",
    "wof:name":"Otto Wirths Gmbh & Co",
    "wof:placetype":"venue"
},
  "geometry": {"coordinates":[7.1316361427,51.2009544373],"type":"Point"}
}