{
  "type": "Feature",
  "properties": {
    "iso:country":"DE",
    "sg:address":"St.-Josef-Str. 9 c",
    "sg:city":"Forchheim",
    "sg:phone":"+49 9191/32422",
    "sg:postcode":"91301",
    "sg:province":"Bayern",
    "wof:name":"Ernst Hoffmann",
    "wof:placetype":"venue"
},
  "geometry": {"coordinates":[11.044994,49.728142],"type":"Point"}
}