{
  "type": "Feature",
  "properties": {
    "iso:country":"DE",
    "sg:address":"Wittensteinstr. 200 - 204 Barmen",
    "sg:city":"Wuppertal",
    "sg:phone":"+49 4920/2557036",
    "sg:postcode":"42285",
    "sg:province":"Nordrhein-Westfalen",
    "wof:name":"Josef Jansen & Co. Kg",
    "wof:placetype":"venue"
},
  "geometry": {"coordinates":[7.17464,51.256859],"type":"Point"}
}