{
  "type": "Feature",
  "properties": {
    "iso:country":"DE",
    "sg:address":"Hauptstr. 48",
    "sg:city":"Pegnitz",
    "sg:phone":"+49 9241/91448",
    "sg:postcode":"91257",
    "sg:province":"Bayern",
    "wof:name":"Vereinte Versicherungs Ag",
    "wof:placetype":"venue"
},
  "geometry": {"coordinates":[11.5402994156,49.7567901611],"type":"Point"}
}