{
  "type": "Feature",
  "properties": {
    "iso:country":"DE",
    "sg:address":"Bubenheimer Weg 52",
    "sg:city":"Koblenz",
    "sg:phone":"+49 261/280365",
    "sg:postcode":"56072",
    "sg:province":"Rheinland-Pfalz",
    "wof:name":"B. Modrok",
    "wof:placetype":"venue"
},
  "geometry": {"coordinates":[7.5696539879,50.3718452454],"type":"Point"}
}