{
  "type": "Feature",
  "properties": {
    "iso:country":"DE",
    "sg:address":"Scheffelstr. 16",
    "sg:city":"Frankenthal",
    "sg:phone":"+49 6233/63028",
    "sg:postcode":"67227",
    "sg:province":"Rheinland-Pfalz",
    "wof:name":"M. Siegmayer Ingenieur",
    "wof:placetype":"venue"
},
  "geometry": {"coordinates":[8.3626327515,49.5436668396],"type":"Point"}
}