{
  "type": "Feature",
  "properties": {
    "iso:country":"DE",
    "sg:address":"Orkotten 5",
    "sg:city":"Telgte",
    "sg:postcode":"48291",
    "sg:province":"Nordrhein-Westfalen",
    "wof:name":"Extra",
    "wof:placetype":"venue"
},
  "geometry": {"coordinates":[7.7838811874,51.9794387817],"type":"Point"}
}