{
  "type": "Feature",
  "properties": {
    "iso:country":"DE",
    "sg:address":"Hauptstr. 35",
    "sg:city":"Wallhausen",
    "sg:phone":"+49 6706/346",
    "sg:postcode":"55595",
    "sg:province":"Rheinland-Pfalz",
    "wof:name":"Peter-josef Und R. Peitz",
    "wof:placetype":"venue"
},
  "geometry": {"coordinates":[7.7698640823,49.8893966675],"type":"Point"}
}