{
  "type": "Feature",
  "properties": {
    "iso:country":"DE",
    "sg:address":"W\u00e4chtersbacher Stra\u00dfe 4",
    "sg:city":"Langenselbold",
    "sg:phone":"+49 700",
    "sg:postcode":"63505",
    "sg:province":"Hessen",
    "wof:name":"Panther Softworks",
    "wof:placetype":"venue"
},
  "geometry": {"coordinates":[9.0555562973,50.1790084839],"type":"Point"}
}