{
  "type": "Feature",
  "properties": {
    "iso:country":"DE",
    "sg:address":"Bornaische Str. 120 a",
    "sg:city":"Leipzig",
    "sg:phone":"+49 341/336210",
    "sg:postcode":"04279",
    "sg:province":"Sachsen",
    "wof:name":"Leipziger Stra\u00dfeninstandsetzungsges. Mbh",
    "wof:placetype":"venue"
},
  "geometry": {"coordinates":[12.384865,51.298256],"type":"Point"}
}