{
  "type": "Feature",
  "properties": {
    "iso:country":"DE",
    "sg:address":"Fischadlerstieg 21",
    "sg:city":"Hamburg",
    "sg:phone":"+49 40/7327250",
    "sg:postcode":"22119",
    "sg:province":"Hamburg",
    "wof:name":"Hans-helmut Schulz",
    "wof:placetype":"venue"
},
  "geometry": {"coordinates":[10.105636,53.55331],"type":"Point"}
}