{
  "type": "Feature",
  "properties": {
    "iso:country":"DE",
    "sg:address":"Schlo\u00dfweg 2",
    "sg:city":"Ortenburg",
    "sg:phone":"+49 8542/7180",
    "sg:postcode":"94496",
    "sg:province":"Bayern",
    "wof:name":"Katholisches Pfarramt St. Joh. Nepomuk",
    "wof:placetype":"venue"
},
  "geometry": {"coordinates":[13.238275528,48.5271568298],"type":"Point"}
}