{
  "type": "Feature",
  "properties": {
    "iso:country":"DE",
    "sg:address":"Seckbacher Landstr. 16a",
    "sg:city":"Frankfurt",
    "sg:phone":"+49 69/4693044",
    "sg:postcode":"60389",
    "sg:province":"Hessen",
    "wof:name":"Blauelinie Marketing Und Communication Gmbh",
    "wof:placetype":"venue"
},
  "geometry": {"coordinates":[8.7105436325,50.1318321228],"type":"Point"}
}