{
  "type": "Feature",
  "properties": {
    "iso:country":"DE",
    "sg:address":"Alleestr. 59",
    "sg:city":"Remscheid",
    "sg:phone":"+49 2191/26376",
    "sg:postcode":"42853",
    "sg:province":"Nordrhein-Westfalen",
    "wof:name":"Hermann Jansen Gmbh",
    "wof:placetype":"venue"
},
  "geometry": {"coordinates":[7.1876997948,51.1807479858],"type":"Point"}
}