{
  "type": "Feature",
  "properties": {
    "iso:country":"DE",
    "sg:address":"Birkenstr. 7",
    "sg:city":"Gensingen",
    "sg:phone":"+49 6727/1073",
    "sg:postcode":"55457",
    "sg:province":"Rheinland-Pfalz",
    "wof:name":"M. Ruby",
    "wof:placetype":"venue"
},
  "geometry": {"coordinates":[7.929636,49.893627],"type":"Point"}
}