{
  "type": "Feature",
  "properties": {
    "iso:country":"DE",
    "sg:address":"Marienstr. 9",
    "sg:city":"P\u00f6\u00dfneck",
    "sg:phone":"+49 3647/2561",
    "sg:postcode":"07557",
    "sg:province":"Th\u00fcringen",
    "wof:name":"Raiffeisenbank P\u00f6\u00dfneck E. G.",
    "wof:placetype":"venue"
},
  "geometry": {"coordinates":[11.588621,50.69099],"type":"Point"}
}