{
  "type": "Feature",
  "properties": {
    "iso:country":"DE",
    "sg:address":"Lindemannstr. 12",
    "sg:city":"Dortmund",
    "sg:phone":"+49 231/124137",
    "sg:postcode":"44137",
    "sg:province":"Nordrhein-Westfalen",
    "wof:name":"Lydia Maties",
    "wof:placetype":"venue"
},
  "geometry": {"coordinates":[7.451327,51.505627],"type":"Point"}
}