{
  "type": "Feature",
  "properties": {
    "iso:country":"DE",
    "sg:address":"Willy-Anker-Weg 2",
    "sg:city":"Velbert",
    "sg:phone":"+49 2053/6578",
    "sg:postcode":"42553",
    "sg:province":"Nordrhein-Westfalen",
    "wof:name":"Agu Gmbh",
    "wof:placetype":"venue"
},
  "geometry": {"coordinates":[7.070129,51.313522],"type":"Point"}
}