{
  "type": "Feature",
  "properties": {
    "iso:country":"DE",
    "sg:address":"Dusemonder Str. 73",
    "sg:city":"Brauneberg",
    "sg:phone":"+49 6534/612",
    "sg:postcode":"54472",
    "sg:province":"Rheinland-Pfalz",
    "wof:name":"Horst Fehres",
    "wof:placetype":"venue"
},
  "geometry": {"coordinates":[6.9917478561,49.9091262817],"type":"Point"}
}