{
  "type": "Feature",
  "properties": {
    "iso:country":"DE",
    "sg:address":"Wolliner Weg 6",
    "sg:city":"Kiel",
    "sg:phone":"+49 431/311018",
    "sg:postcode":"24107",
    "sg:province":"Schleswig-Holstein",
    "wof:name":"Freimut H. D. Quednau Rechtsanwalt",
    "wof:placetype":"venue"
},
  "geometry": {"coordinates":[10.0776758194,54.3635025024],"type":"Point"}
}