{
  "type": "Feature",
  "properties": {
    "iso:country":"DE",
    "sg:address":"Preu\u00dfenstr. 14 a",
    "sg:city":"Wilhelmshaven",
    "sg:phone":"+49 4421/995293",
    "sg:postcode":"26388",
    "sg:province":"Niedersachsen",
    "wof:name":"Kaisers Markt",
    "wof:placetype":"venue"
},
  "geometry": {"coordinates":[8.0939741135,53.5704460144],"type":"Point"}
}