{
  "type": "Feature",
  "properties": {
    "iso:country":"DE",
    "sg:address":"Egid-Harrer-Str. 37",
    "sg:city":"Georgensgm\u00fcnd",
    "sg:phone":"+49 9172/67916",
    "sg:postcode":"91166",
    "sg:province":"Bayern",
    "wof:name":"Uwe Gs\u00e4nger S.b. Tankstelle",
    "wof:placetype":"venue"
},
  "geometry": {"coordinates":[11.0165243149,49.1925506592],"type":"Point"}
}