{
  "type": "Feature",
  "properties": {
    "iso:country":"DE",
    "sg:address":"Mercedesstr.",
    "sg:city":"Sindelfingen",
    "sg:postcode":"71063",
    "sg:province":"Baden-W\u00fcrttemberg",
    "wof:name":"Eiscafe Florenz Gmbh",
    "wof:placetype":"venue"
},
  "geometry": {"coordinates":[8.9999303818,48.7052345276],"type":"Point"}
}