{
  "type": "Feature",
  "properties": {
    "iso:country":"DE",
    "sg:address":"Krietzschwitz 8",
    "sg:city":"Pirna",
    "sg:phone":"+49 3501/774015",
    "sg:postcode":"01796",
    "sg:province":"Sachsen",
    "wof:name":"E. Ullrich",
    "wof:placetype":"venue"
},
  "geometry": {"coordinates":[13.980646,50.926289],"type":"Point"}
}