{
  "type": "Feature",
  "properties": {
    "iso:country":"DE",
    "sg:address":"Ennigerloher Str. 64",
    "sg:city":"Oelde",
    "sg:postcode":"59302",
    "sg:province":"Nordrhein-Westfalen",
    "wof:name":"Saati-gmbh",
    "wof:placetype":"venue"
},
  "geometry": {"coordinates":[8.1423168182,51.8228912354],"type":"Point"}
}