{
  "type": "Feature",
  "properties": {
    "iso:country":"DE",
    "sg:address":"Am Neuen Wall 31",
    "sg:city":"Steinfurt",
    "sg:phone":"+49 2551/5362",
    "sg:postcode":"48565",
    "sg:province":"Nordrhein-Westfalen",
    "wof:name":"Ernst Wenking",
    "wof:placetype":"venue"
},
  "geometry": {"coordinates":[7.34211,52.146648],"type":"Point"}
}