{
  "type": "Feature",
  "properties": {
    "iso:country":"DE",
    "sg:address":"R\u00f6merstr. 55",
    "sg:city":"Marl",
    "sg:phone":"+49 2365/45085",
    "sg:postcode":"45772",
    "sg:province":"Nordrhein-Westfalen",
    "wof:name":"Klaus Martin Hochbau - Tiefbau Gmbh",
    "wof:placetype":"venue"
},
  "geometry": {"coordinates":[7.1274609566,51.6671981812],"type":"Point"}
}