{
  "type": "Feature",
  "properties": {
    "iso:country":"DE",
    "sg:address":"Von-Haxthausen-Str. 6",
    "sg:city":"Barntrup",
    "sg:phone":"+49 5263/2388",
    "sg:postcode":"32683",
    "sg:province":"Nordrhein-Westfalen",
    "wof:name":"D\u00f6bel Druck Gmbh",
    "wof:placetype":"venue"
},
  "geometry": {"coordinates":[9.1205005646,51.9908332825],"type":"Point"}
}