{
  "type": "Feature",
  "properties": {
    "iso:country":"DE",
    "sg:address":"Thingstr. 13",
    "sg:city":"Hattingen",
    "sg:phone":"+49 2324/96300",
    "sg:postcode":"45527",
    "sg:province":"Nordrhein-Westfalen",
    "wof:name":"Gartenstadt H\u00fcttenau Eg",
    "wof:placetype":"venue"
},
  "geometry": {"coordinates":[7.200521946,51.4115447998],"type":"Point"}
}