{
  "type": "Feature",
  "properties": {
    "iso:country":"DE",
    "sg:address":"Wagh\u00e4useler Str. 44",
    "sg:city":"Wagh\u00e4usel",
    "sg:phone":"+49 7254/93300",
    "sg:postcode":"68753",
    "sg:province":"Baden-W\u00fcrttemberg",
    "wof:name":"Badische Anzeigen Verlags Gmbh",
    "wof:placetype":"venue"
},
  "geometry": {"coordinates":[8.5445585251,49.243309021],"type":"Point"}
}