{
  "type": "Feature",
  "properties": {
    "iso:country":"DE",
    "sg:address":"Heutalstr 79",
    "sg:city":"Albstadt",
    "sg:phone":"+49 7334/740",
    "sg:postcode":"72461",
    "sg:province":"Baden-W\u00fcrttemberg",
    "wof:name":"Gr\u00fcner Systemtechnik Gmbh & Co Kg",
    "wof:placetype":"venue"
},
  "geometry": {"coordinates":[9.762017,48.608341],"type":"Point"}
}