{
  "type": "Feature",
  "properties": {
    "iso:country":"DE",
    "sg:address":"K\u00f6hlerhang 1",
    "sg:city":"Bad Lauterberg",
    "sg:phone":"+49 5524/3262",
    "sg:postcode":"37431",
    "sg:province":"Niedersachsen",
    "wof:name":"Vidovic & Partner Gmbh",
    "wof:placetype":"venue"
},
  "geometry": {"coordinates":[10.489843,51.637264],"type":"Point"}
}