{
  "type": "Feature",
  "properties": {
    "iso:country":"DE",
    "sg:address":"Kasterstr. 60",
    "sg:city":"Grevenbroich",
    "sg:phone":"+49 2181/8586",
    "sg:postcode":"41517",
    "sg:province":"Nordrhein-Westfalen",
    "wof:name":"Peter Gottlebe",
    "wof:placetype":"venue"
},
  "geometry": {"coordinates":[6.573219,51.044075],"type":"Point"}
}