{
  "type": "Feature",
  "properties": {
    "iso:country":"DE",
    "sg:address":"Winterstr. 29",
    "sg:city":"Karlsruhe",
    "sg:phone":"+49 721/31063",
    "sg:postcode":"76137",
    "sg:province":"Baden-W\u00fcrttemberg",
    "wof:name":"St. Josef-haus Altersheim",
    "wof:placetype":"venue"
},
  "geometry": {"coordinates":[8.407639,48.998371],"type":"Point"}
}