{
  "type": "Feature",
  "properties": {
    "iso:country":"DE",
    "sg:address":"Lohbachstr. 10",
    "sg:city":"Velbert",
    "sg:phone":"+49 2053/2026",
    "sg:postcode":"42553",
    "sg:province":"Nordrhein-Westfalen",
    "wof:name":"Tele-pizza-service",
    "wof:placetype":"venue"
},
  "geometry": {"coordinates":[7.090208,51.311222],"type":"Point"}
}