{
  "type": "Feature",
  "properties": {
    "iso:country":"DE",
    "sg:address":"Hackesstr. 9",
    "sg:city":"M\u00f6nchengladbach",
    "sg:phone":"+49 2161/971300",
    "sg:postcode":"41066",
    "sg:province":"Nordrhein-Westfalen",
    "wof:name":"R. Neunzig",
    "wof:placetype":"venue"
},
  "geometry": {"coordinates":[6.447276,51.223816],"type":"Point"}
}