{
  "type": "Feature",
  "properties": {
    "iso:country":"DE",
    "sg:address":"Hauptstr. 23",
    "sg:city":"Birstein",
    "sg:phone":"+49 6054/374",
    "sg:postcode":"63633",
    "sg:province":"Hessen",
    "wof:name":"Kath. Pfarramt Mari\u00e4 Heimsuchung",
    "wof:placetype":"venue"
},
  "geometry": {"coordinates":[9.309756279,50.3532867432],"type":"Point"}
}