{
  "type": "Feature",
  "properties": {
    "iso:country":"DE",
    "sg:address":"Karl-Marx-Str. 36",
    "sg:city":"Wittenberge",
    "sg:postcode":"19322",
    "sg:province":"Brandenburg",
    "wof:name":"Berendt & Sohn Gmbh",
    "wof:placetype":"venue"
},
  "geometry": {"coordinates":[11.7562446594,52.999042511],"type":"Point"}
}