{
  "type": "Feature",
  "properties": {
    "iso:country":"DE",
    "sg:address":"Keltenstr. 11",
    "sg:city":"Kitzingen",
    "sg:phone":"+49 9321/91860",
    "sg:postcode":"97318",
    "sg:province":"Bayern",
    "wof:name":"Norbert Wittig Steuerberater",
    "wof:placetype":"venue"
},
  "geometry": {"coordinates":[10.1487503052,49.7431793213],"type":"Point"}
}