{
  "type": "Feature",
  "properties": {
    "iso:country":"DE",
    "sg:address":"Siegweg 1",
    "sg:city":"Breitscheid",
    "sg:phone":"+49 2777/91410",
    "sg:postcode":"35767",
    "sg:province":"Hessen",
    "wof:name":"Ewald Becker Gmbh & Co.kg",
    "wof:placetype":"venue"
},
  "geometry": {"coordinates":[8.1936435699,50.689365387],"type":"Point"}
}