{
  "type": "Feature",
  "properties": {
    "iso:country":"DE",
    "sg:address":"Burgweg 17",
    "sg:city":"M\u00fcnsingen",
    "sg:phone":"+49 7383/1251",
    "sg:postcode":"72525",
    "sg:province":"Baden-W\u00fcrttemberg",
    "wof:name":"Ev. Pfarramt Hundersingen",
    "wof:placetype":"venue"
},
  "geometry": {"coordinates":[9.4888715744,48.3435401917],"type":"Point"}
}