{
  "type": "Feature",
  "properties": {
    "iso:country":"DE",
    "sg:address":"Fabianstr. 6",
    "sg:city":"Bad Lausick",
    "sg:phone":"+49 34345/91921",
    "sg:postcode":"04651",
    "sg:province":"Sachsen",
    "wof:name":"H\u00e4usliche Krankenpflege R. K\u00fchn",
    "wof:placetype":"venue"
},
  "geometry": {"coordinates":[12.647395,51.143871],"type":"Point"}
}