{
  "type": "Feature",
  "properties": {
    "iso:country":"DE",
    "sg:address":"Dr.-Kremser-Str. 31",
    "sg:city":"S\u00fclzhayn",
    "sg:phone":"+49 36332/20347",
    "sg:postcode":"99755",
    "sg:province":"Th\u00fcringen",
    "wof:name":"G. Mau\u00df",
    "wof:placetype":"venue"
},
  "geometry": {"coordinates":[10.693608284,51.6061286926],"type":"Point"}
}