{
  "type": "Feature",
  "properties": {
    "iso:country":"DE",
    "sg:address":"Stadtwaldg\u00fcrtel 62",
    "sg:city":"K\u00f6ln",
    "sg:phone":"+49 221/402010",
    "sg:postcode":"50931",
    "sg:province":"Nordrhein-Westfalen",
    "wof:name":"Inge Tramitz Rechtsanw\u00e4ltin",
    "wof:placetype":"venue"
},
  "geometry": {"coordinates":[6.9085140228,50.9357185364],"type":"Point"}
}