{
  "type": "Feature",
  "properties": {
    "iso:country":"DE",
    "sg:address":"Am Hallenbad 38",
    "sg:city":"Kirchlengern",
    "sg:phone":"+49 5223/761650",
    "sg:postcode":"32278",
    "sg:province":"Nordrhein-Westfalen",
    "wof:name":"Preisagentur B. Steffen",
    "wof:placetype":"venue"
},
  "geometry": {"coordinates":[8.62897,52.202065],"type":"Point"}
}