{
  "type": "Feature",
  "properties": {
    "iso:country":"DE",
    "sg:address":"Nelkenweg 14",
    "sg:city":"Bad Zwischenahn",
    "sg:phone":"+49 4403/3464",
    "sg:postcode":"26160",
    "sg:province":"Niedersachsen",
    "wof:name":"Friedrich-karl Weiss",
    "wof:placetype":"venue"
},
  "geometry": {"coordinates":[8.029817,53.182205],"type":"Point"}
}