{
  "type": "Feature",
  "properties": {
    "iso:country":"DE",
    "sg:address":"Hallesche Str. 76",
    "sg:city":"K\u00f6then",
    "sg:phone":"+49 3496/210056",
    "sg:postcode":"06366",
    "sg:province":"Sachsen-Anhalt",
    "wof:name":"Vanessa Frauen-fitne\u00df Gmbh",
    "wof:placetype":"venue"
},
  "geometry": {"coordinates":[11.9730587006,51.7497520447],"type":"Point"}
}