{
  "type": "Feature",
  "properties": {
    "iso:country":"DE",
    "sg:address":"Feldstr. 9",
    "sg:city":"Hainichen",
    "sg:phone":"+49 37207/51118",
    "sg:postcode":"09661",
    "sg:province":"Sachsen",
    "wof:name":"T. Schwiertz",
    "wof:placetype":"venue"
},
  "geometry": {"coordinates":[13.116167,50.973591],"type":"Point"}
}