{
  "type": "Feature",
  "properties": {
    "iso:country":"DE",
    "sg:address":"Friedrich-List-Str 2",
    "sg:city":"Leinfelden-Echterdingen",
    "sg:phone":"+49 711/902810",
    "sg:postcode":"70771",
    "sg:province":"Baden-W\u00fcrttemberg",
    "wof:name":"Fr. Meyer's Sohn Gmbh & Co",
    "wof:placetype":"venue"
},
  "geometry": {"coordinates":[9.1609201431,48.6913146973],"type":"Point"}
}