{
  "type": "Feature",
  "properties": {
    "iso:country":"DE",
    "sg:address":"Happenort 23",
    "sg:city":"Harsewinkel",
    "sg:phone":"+49 5247/3355",
    "sg:postcode":"33428",
    "sg:province":"Nordrhein-Westfalen",
    "wof:name":"Siebrecht",
    "wof:placetype":"venue"
},
  "geometry": {"coordinates":[8.228441,51.963596],"type":"Point"}
}