{
  "type": "Feature",
  "properties": {
    "iso:country":"DE",
    "sg:address":"Eichgasse 2",
    "sg:city":"Karlsbad",
    "sg:phone":"+49 7248/5576",
    "sg:postcode":"76307",
    "sg:province":"Baden-W\u00fcrttemberg",
    "wof:name":"Kappler",
    "wof:placetype":"venue"
},
  "geometry": {"coordinates":[8.504953,48.865551],"type":"Point"}
}