{
  "type": "Feature",
  "properties": {
    "iso:country":"DE",
    "sg:address":"Hahnst\u00fcckenweg 98",
    "sg:city":"Bitterfeld",
    "sg:phone":"+49 3493/41347",
    "sg:postcode":"06749",
    "sg:province":"Sachsen-Anhalt",
    "wof:name":"Dr. Friedrich Schreier Tierarzt",
    "wof:placetype":"venue"
},
  "geometry": {"coordinates":[12.3360700607,51.6385383606],"type":"Point"}
}