{
  "type": "Feature",
  "properties": {
    "iso:country":"DE",
    "sg:address":"Bickelstr. 2",
    "sg:city":"Plauen",
    "sg:phone":"+49 3741/431658",
    "sg:postcode":"08527",
    "sg:province":"Sachsen",
    "wof:name":"D. Schmidt",
    "wof:placetype":"venue"
},
  "geometry": {"coordinates":[12.140692,50.484257],"type":"Point"}
}