{
  "type": "Feature",
  "properties": {
    "iso:country":"DE",
    "sg:address":"Gr\u00fcntenseestr. 12",
    "sg:city":"Oy-Mittelberg",
    "sg:postcode":"87466",
    "sg:province":"Bayern",
    "wof:name":"Sawi Tungsanlage-vertrieb",
    "wof:placetype":"venue"
},
  "geometry": {"coordinates":[10.459874,47.628742],"type":"Point"}
}