{
  "type": "Feature",
  "properties": {
    "iso:country":"DE",
    "sg:address":"Vogteistr. 7",
    "sg:city":"Dorfmark",
    "sg:phone":"+49 4951/636966",
    "sg:postcode":"29683",
    "sg:province":"Niedersachsen",
    "wof:name":"Kreissparkasse Fallingbostel I",
    "wof:placetype":"venue"
},
  "geometry": {"coordinates":[9.694399,52.86599],"type":"Point"}
}