{
  "type": "Feature",
  "properties": {
    "iso:country":"DE",
    "sg:address":"Nibelungenstr. 18",
    "sg:city":"Gernsheim",
    "sg:postcode":"64579",
    "sg:province":"Hessen",
    "wof:name":"Nibelungen 18 Sch\u00e4fer",
    "wof:placetype":"venue"
},
  "geometry": {"coordinates":[8.481697,49.746059],"type":"Point"}
}