{
  "type": "Feature",
  "properties": {
    "iso:country":"DE",
    "sg:address":"Elsassergasse 2",
    "sg:city":"Dinkelsb\u00fchl",
    "sg:phone":"+49 9851/894",
    "sg:postcode":"91550",
    "sg:province":"Bayern",
    "wof:name":"Alfred Michel Asphalt- Und Isolierbau Gmbh",
    "wof:placetype":"venue"
},
  "geometry": {"coordinates":[10.3184814453,49.0703849792],"type":"Point"}
}