{
  "type": "Feature",
  "properties": {
    "iso:country":"DE",
    "sg:address":"Waldm\u00fcnchener Str. 10",
    "sg:city":"Furth im Wald",
    "sg:phone":"+49 9973/4018",
    "sg:postcode":"93437",
    "sg:province":"Bayern",
    "wof:name":"Lemberger Gmbh",
    "wof:placetype":"venue"
},
  "geometry": {"coordinates":[12.8299703598,49.3046951294],"type":"Point"}
}