{
  "type": "Feature",
  "properties": {
    "iso:country":"DE",
    "sg:address":"Lange Str. 44",
    "sg:city":"Bamberg",
    "sg:phone":"+49 951/27137",
    "sg:postcode":"96047",
    "sg:province":"Bayern",
    "wof:name":"Eil Zur Keil Gabriele Hagel",
    "wof:placetype":"venue"
},
  "geometry": {"coordinates":[10.8914,49.891853],"type":"Point"}
}