{
  "type": "Feature",
  "properties": {
    "iso:country":"DE",
    "sg:address":"Hauptstr. 24",
    "sg:city":"Lienen",
    "sg:phone":"+49 5483/8322",
    "sg:postcode":"49536",
    "sg:province":"Nordrhein-Westfalen",
    "wof:name":"Heinrich Achelpohl",
    "wof:placetype":"venue"
},
  "geometry": {"coordinates":[7.975071,52.146271],"type":"Point"}
}