{
  "type": "Feature",
  "properties": {
    "iso:country":"DE",
    "sg:address":"Hochwaldstr 22",
    "sg:city":"Morbach",
    "sg:phone":"+49 6533/790",
    "sg:postcode":"54497",
    "sg:province":"Rheinland-Pfalz",
    "wof:name":"Papier-mettler",
    "wof:placetype":"venue"
},
  "geometry": {"coordinates":[7.126361,49.808357],"type":"Point"}
}