{
  "type": "Feature",
  "properties": {
    "iso:country":"DE",
    "sg:address":"Irminfriedstr. 16",
    "sg:city":"Gr\u00e4felfing",
    "sg:phone":"+49 89/855214",
    "sg:postcode":"82166",
    "sg:province":"Bayern",
    "wof:name":"Eduard G\u00fcnther",
    "wof:placetype":"venue"
},
  "geometry": {"coordinates":[11.4211740494,48.119304657],"type":"Point"}
}