{
  "type": "Feature",
  "properties": {
    "iso:country":"DE",
    "sg:address":"V\u00f6rstetter Str. 33",
    "sg:city":"March",
    "sg:phone":"+49 7665/1736",
    "sg:postcode":"79232",
    "sg:province":"Baden-W\u00fcrttemberg",
    "wof:name":"Shell-station Thomas Birkenmeier",
    "wof:placetype":"venue"
},
  "geometry": {"coordinates":[7.8037881851,48.0718803406],"type":"Point"}
}