{
  "type": "Feature",
  "properties": {
    "iso:country":"DE",
    "sg:address":"Leipziger Str. 268",
    "sg:city":"Kaufungen",
    "sg:phone":"+49 5605/927944",
    "sg:postcode":"34260",
    "sg:province":"Hessen",
    "wof:name":"Cafe Sahne",
    "wof:placetype":"venue"
},
  "geometry": {"coordinates":[9.603762,51.284264],"type":"Point"}
}