{
  "type": "Feature",
  "properties": {
    "iso:country":"DE",
    "sg:address":"Schliebener Str. 7",
    "sg:city":"Herzberg",
    "sg:phone":"+49 3535/23833",
    "sg:postcode":"04916",
    "sg:province":"Brandenburg",
    "wof:name":"Gerhard Nagel",
    "wof:placetype":"venue"
},
  "geometry": {"coordinates":[13.2367105484,51.6927909851],"type":"Point"}
}