{
  "type": "Feature",
  "properties": {
    "iso:country":"DE",
    "sg:address":"Wasentegernbach 42",
    "sg:city":"Dorfen",
    "sg:phone":"+49 8082/226290",
    "sg:postcode":"84405",
    "sg:province":"Bayern",
    "wof:name":"Albert Schmid",
    "wof:placetype":"venue"
},
  "geometry": {"coordinates":[12.214814,48.274796],"type":"Point"}
}