{
  "type": "Feature",
  "properties": {
    "iso:country":"DE",
    "sg:address":"Bahnhofstr. 41",
    "sg:city":"Pirmasens",
    "sg:postcode":"66953",
    "sg:province":"Rheinland-Pfalz",
    "wof:name":"Stadtverwaltung Pirmasens",
    "wof:placetype":"venue"
},
  "geometry": {"coordinates":[7.5999970436,49.203327179],"type":"Point"}
}