{
  "type": "Feature",
  "properties": {
    "iso:country":"DE",
    "sg:address":"In den Schafwiesen 19",
    "sg:city":"Oberstenfeld",
    "sg:phone":"+49 7062/94090",
    "sg:postcode":"71720",
    "sg:province":"Baden-W\u00fcrttemberg",
    "wof:name":"Gtb Gesellschaft F\u00fcr Trocknung Und Beschichtung Mbh",
    "wof:placetype":"venue"
},
  "geometry": {"coordinates":[9.3294773102,49.0212478638],"type":"Point"}
}