{
  "type": "Feature",
  "properties": {
    "iso:country":"DE",
    "sg:address":"Heeder Dorfstr. 38",
    "sg:city":"Diepholz",
    "sg:phone":"+49 5441/2706",
    "sg:postcode":"49356",
    "sg:province":"Niedersachsen",
    "wof:name":"Fritz Ahrens",
    "wof:placetype":"venue"
},
  "geometry": {"coordinates":[8.392833,52.63908],"type":"Point"}
}