{
  "type": "Feature",
  "properties": {
    "iso:country":"DE",
    "sg:address":"Obere Marktstr. 27",
    "sg:city":"Hildburghausen",
    "sg:phone":"+49 3685/706780",
    "sg:postcode":"98646",
    "sg:province":"Th\u00fcringen",
    "wof:name":"Egon Gr\u00f6tenhardt Architekt",
    "wof:placetype":"venue"
},
  "geometry": {"coordinates":[10.730745,50.425854],"type":"Point"}
}