{
  "type": "Feature",
  "properties": {
    "iso:country":"DE",
    "sg:address":"Johannesstr.",
    "sg:city":"Birkungen",
    "sg:phone":"+49 3605/513724",
    "sg:postcode":"37327",
    "sg:province":"Th\u00fcringen",
    "wof:name":"Baumaschinen- Und Fahrzeugtechnik",
    "wof:placetype":"venue"
},
  "geometry": {"coordinates":[10.336434,51.36972],"type":"Point"}
}