{
  "type": "Feature",
  "properties": {
    "iso:country":"DE",
    "sg:address":"An der Kirche 2",
    "sg:city":"Hardegsen",
    "sg:phone":"+49 5505/2365",
    "sg:postcode":"37181",
    "sg:province":"Niedersachsen",
    "wof:name":"Friedrich Wellhausen",
    "wof:placetype":"venue"
},
  "geometry": {"coordinates":[9.827961,51.651188],"type":"Point"}
}