{
  "type": "Feature",
  "properties": {
    "iso:country":"DE",
    "sg:address":"Zollamtstr. 3",
    "sg:city":"Zweibr\u00fccken",
    "sg:postcode":"66482",
    "sg:province":"Rheinland-Pfalz",
    "wof:name":"Deutsche Bahn Ag",
    "wof:placetype":"venue"
},
  "geometry": {"coordinates":[7.3572502136,49.2483291626],"type":"Point"}
}