{
  "type": "Feature",
  "properties": {
    "iso:country":"DE",
    "sg:address":"Weisestr. 59",
    "sg:city":"Berlin",
    "sg:phone":"+49 30/6212030",
    "sg:postcode":"12049",
    "sg:province":"Berlin",
    "wof:name":"Br\u00f6tje Werkskundendienst Peter K\u00fchling",
    "wof:placetype":"venue"
},
  "geometry": {"coordinates":[13.4237823486,52.4787368774],"type":"Point"}
}