{
  "type": "Feature",
  "properties": {
    "iso:country":"DE",
    "sg:address":"An der Bode 12",
    "sg:city":"Sta\u00dffurt",
    "sg:postcode":"39418",
    "sg:province":"Sachsen-Anhalt",
    "wof:name":"Richard Kraehling",
    "wof:placetype":"venue"
},
  "geometry": {"coordinates":[11.5783815384,51.8551101685],"type":"Point"}
}