{
  "type": "Feature",
  "properties": {
    "iso:country":"DE",
    "sg:address":"An der Marburger Str. 44",
    "sg:city":"M\u00fcnchhausen",
    "sg:phone":"+49 6423/1433",
    "sg:postcode":"35117",
    "sg:province":"Hessen",
    "wof:name":"Uschi",
    "wof:placetype":"venue"
},
  "geometry": {"coordinates":[8.7056617737,50.9370346069],"type":"Point"}
}