{
  "type": "Feature",
  "properties": {
    "iso:country":"DE",
    "sg:address":"Rostocker Chaussee 16",
    "sg:city":"Stralsund",
    "sg:phone":"+49 3831/44840",
    "sg:postcode":"18437",
    "sg:province":"Mecklenburg-Vorpommern",
    "wof:name":"D\u00e4nisches Bettenlager Gmbh & Co. Kg",
    "wof:placetype":"venue"
},
  "geometry": {"coordinates":[13.0594301224,54.3056144714],"type":"Point"}
}