{
  "type": "Feature",
  "properties": {
    "iso:country":"DE",
    "sg:address":"Schie\u00dfgrabenstr. 21/2",
    "sg:city":"Augsburg",
    "sg:phone":"+49 821/154027",
    "sg:postcode":"86150",
    "sg:province":"Bayern",
    "wof:name":"Hello Concerts Gmbh",
    "wof:placetype":"venue"
},
  "geometry": {"coordinates":[10.89637,48.361721],"type":"Point"}
}