{
  "type": "Feature",
  "properties": {
    "iso:country":"DE",
    "sg:address":"Kaulhausen 109",
    "sg:city":"Erkelenz",
    "sg:phone":"+49 4924/3171439",
    "sg:postcode":"41812",
    "sg:province":"Nordrhein-Westfalen",
    "wof:name":"Winfried Frank Gmbh",
    "wof:placetype":"venue"
},
  "geometry": {"coordinates":[6.367957,51.082588],"type":"Point"}
}