{
  "type": "Feature",
  "properties": {
    "iso:country":"DE",
    "sg:address":"Enge Str. 19",
    "sg:city":"Garding",
    "sg:phone":"+49 4862/8800",
    "sg:postcode":"25836",
    "sg:province":"Schleswig-Holstein",
    "wof:name":"Hans-peter Prieg",
    "wof:placetype":"venue"
},
  "geometry": {"coordinates":[8.7812433243,54.3295135498],"type":"Point"}
}