{
  "type": "Feature",
  "properties": {
    "iso:country":"DE",
    "sg:address":"Glasbergstr. 23",
    "sg:city":"Hamburg",
    "sg:phone":"+49 40/7323857",
    "sg:postcode":"22119",
    "sg:province":"Hamburg",
    "wof:name":"Harald Goertz",
    "wof:placetype":"venue"
},
  "geometry": {"coordinates":[10.114952,53.560062],"type":"Point"}
}