{
  "type": "Feature",
  "properties": {
    "iso:country":"DE",
    "sg:address":"Hauptstr. 23",
    "sg:city":"Reichenbach",
    "sg:postcode":"08468",
    "sg:province":"Sachsen",
    "wof:name":"Mtb Mikrowellen Trocknungs- Ger\u00e4te Bauwerkserhaltung Gmbh",
    "wof:placetype":"venue"
},
  "geometry": {"coordinates":[11.414949,50.426041],"type":"Point"}
}