{
  "type": "Feature",
  "properties": {
    "iso:country":"DE",
    "sg:address":"Langstr. 5",
    "sg:city":"Hadamar",
    "sg:postcode":"65589",
    "sg:province":"Hessen",
    "wof:name":"Ludwig Broeske",
    "wof:placetype":"venue"
},
  "geometry": {"coordinates":[8.104727,50.470573],"type":"Point"}
}