{
  "type": "Feature",
  "properties": {
    "iso:country":"DE",
    "sg:address":"Schottereyer Str. 43",
    "sg:city":"Bad Lauchst\u00e4dt",
    "sg:phone":"+49 34635/20384",
    "sg:postcode":"06246",
    "sg:province":"Sachsen-Anhalt",
    "wof:name":"K. May",
    "wof:placetype":"venue"
},
  "geometry": {"coordinates":[11.8379268646,51.3917808533],"type":"Point"}
}