{
  "type": "Feature",
  "properties": {
    "iso:country":"DE",
    "sg:address":"Hauptstr. 45",
    "sg:city":"Brandenburg",
    "sg:phone":"+49 3381/225450",
    "sg:postcode":"14776",
    "sg:province":"Brandenburg",
    "wof:name":"Blugesa Floristik Und Gartenbau Gmbh",
    "wof:placetype":"venue"
},
  "geometry": {"coordinates":[12.5595359802,52.410358429],"type":"Point"}
}