{
  "type": "Feature",
  "properties": {
    "iso:country":"DE",
    "sg:address":"Grabenstr. 7",
    "sg:city":"Ringleben",
    "sg:phone":"+49 3466/31205",
    "sg:postcode":"06556",
    "sg:province":"Th\u00fcringen",
    "wof:name":"M. Koller",
    "wof:placetype":"venue"
},
  "geometry": {"coordinates":[11.2194328308,51.3672943115],"type":"Point"}
}