{
  "type": "Feature",
  "properties": {
    "iso:country":"DE",
    "sg:address":"Carl-Stockhinger-Str. 1c",
    "sg:city":"Bremen",
    "sg:phone":"+49 421/521717",
    "sg:postcode":"28197",
    "sg:province":"Bremen",
    "wof:name":"Tol Gmbh",
    "wof:placetype":"venue"
},
  "geometry": {"coordinates":[8.75825,53.078419],"type":"Point"}
}