{
  "type": "Feature",
  "properties": {
    "iso:country":"DE",
    "sg:address":"Heinrich-Heine-Str. 32",
    "sg:city":"Eggesin",
    "sg:phone":"+49 39779/20664",
    "sg:postcode":"17367",
    "sg:province":"Mecklenburg-Vorpommern",
    "wof:name":"Wolfgang Ehrke",
    "wof:placetype":"venue"
},
  "geometry": {"coordinates":[14.105129,53.669266],"type":"Point"}
}