{
  "type": "Feature",
  "properties": {
    "iso:country":"DE",
    "sg:address":"Augustastr. 11",
    "sg:city":"D\u00fcsseldorf",
    "sg:phone":"+49 211/1623266",
    "sg:postcode":"40477",
    "sg:province":"Nordrhein-Westfalen",
    "wof:name":"Mecklenburgische Versicherungsgruppe",
    "wof:placetype":"venue"
},
  "geometry": {"coordinates":[6.7908420563,51.2380027771],"type":"Point"}
}