{
  "type": "Feature",
  "properties": {
    "iso:country":"DE",
    "sg:address":"Eschenstr. 4",
    "sg:city":"Dresden",
    "sg:phone":"+49 351/8024460",
    "sg:postcode":"01097",
    "sg:province":"Sachsen",
    "wof:name":"Ingenieurb\u00fcro Wolfgang Kling",
    "wof:placetype":"venue"
},
  "geometry": {"coordinates":[13.7482967377,51.0701980591],"type":"Point"}
}