{
  "type": "Feature",
  "properties": {
    "iso:country":"DE",
    "sg:address":"Hersfelder Tor 11",
    "sg:city":"Grebenau",
    "sg:phone":"+49 6646/240",
    "sg:postcode":"36323",
    "sg:province":"Hessen",
    "wof:name":"Georg M\u00f6ller",
    "wof:placetype":"venue"
},
  "geometry": {"coordinates":[9.475866,50.743416],"type":"Point"}
}