{
  "type": "Feature",
  "properties": {
    "iso:country":"DE",
    "sg:address":"Dorfstr. 4",
    "sg:city":"Bad Griesbach",
    "sg:phone":"+49 8532/7825",
    "sg:postcode":"94086",
    "sg:province":"Bayern",
    "wof:name":"Martin Erbinger",
    "wof:placetype":"venue"
},
  "geometry": {"coordinates":[13.150042,48.447693],"type":"Point"}
}