{
  "type": "Feature",
  "properties": {
    "iso:country":"DE",
    "sg:address":"Fahrt 2",
    "sg:city":"Buseck",
    "sg:phone":"+49 6408/7861",
    "sg:postcode":"35418",
    "sg:province":"Hessen",
    "wof:name":"Kleintierzuchtverein Oppenrod E. V.",
    "wof:placetype":"venue"
},
  "geometry": {"coordinates":[8.8022794724,50.5846290588],"type":"Point"}
}