{
  "type": "Feature",
  "properties": {
    "iso:country":"DE",
    "sg:address":"Siegstr. 3",
    "sg:city":"Betzdorf",
    "sg:phone":"+49 2741/21888",
    "sg:postcode":"57518",
    "sg:province":"Rheinland-Pfalz",
    "wof:name":"Gastst\u00e4tte Club Old London",
    "wof:placetype":"venue"
},
  "geometry": {"coordinates":[7.8737659454,50.7896995544],"type":"Point"}
}