{
  "type": "Feature",
  "properties": {
    "iso:country":"DE",
    "sg:address":"M\u00fcnchsdorfer Str. 16",
    "sg:city":"Ro\u00dfbach",
    "sg:phone":"+49 8547/7901",
    "sg:postcode":"94439",
    "sg:province":"Bayern",
    "wof:name":"W. Maidl",
    "wof:placetype":"venue"
},
  "geometry": {"coordinates":[12.93764,48.60004],"type":"Point"}
}