{
  "type": "Feature",
  "properties": {
    "iso:country":"DE",
    "sg:address":"Brinkerstr. 1-7",
    "sg:city":"Sprockh\u00f6vel",
    "sg:phone":"+49 2324/7504",
    "sg:postcode":"45549",
    "sg:province":"Nordrhein-Westfalen",
    "wof:name":"Rudolf Von Scheven Gmbh",
    "wof:placetype":"venue"
},
  "geometry": {"coordinates":[7.243663,51.361298],"type":"Point"}
}