{
  "type": "Feature",
  "properties": {
    "iso:country":"DE",
    "sg:address":"Wilhelm-Stolze-Str. 18",
    "sg:city":"Berlin",
    "sg:phone":"+49 30/4224037",
    "sg:postcode":"10249",
    "sg:province":"Berlin",
    "wof:name":"Richard Kraushaar Dachdeckungs Gmbh",
    "wof:placetype":"venue"
},
  "geometry": {"coordinates":[13.447141,52.522587],"type":"Point"}
}