{
  "type": "Feature",
  "properties": {
    "iso:country":"DE",
    "sg:address":"Litauenring 44",
    "sg:city":"Arnsberg",
    "sg:phone":"+49 2932/22016",
    "sg:postcode":"59755",
    "sg:province":"Nordrhein-Westfalen",
    "wof:name":"Constantin Post Architekt",
    "wof:placetype":"venue"
},
  "geometry": {"coordinates":[7.984052,51.444538],"type":"Point"}
}