{
  "type": "Feature",
  "properties": {
    "iso:country":"DE",
    "sg:address":"Mozartstr. 61",
    "sg:city":"Burgkirchen",
    "sg:phone":"+49 8679/6652",
    "sg:postcode":"84508",
    "sg:province":"Bayern",
    "wof:name":"Josef Wenleder",
    "wof:placetype":"venue"
},
  "geometry": {"coordinates":[12.7127065659,48.1719436646],"type":"Point"}
}