{
  "type": "Feature",
  "properties": {
    "iso:country":"DE",
    "sg:address":"Frankfurter Str. 22a",
    "sg:city":"Bad K\u00f6nig",
    "sg:phone":"+49 6063/2233",
    "sg:postcode":"64732",
    "sg:province":"Hessen",
    "wof:name":"Hotel G. Br\u00e4unig",
    "wof:placetype":"venue"
},
  "geometry": {"coordinates":[9.0048303604,49.7437515259],"type":"Point"}
}