{
  "type": "Feature",
  "properties": {
    "iso:country":"DE",
    "sg:address":"Am Schlo\u00df 4",
    "sg:city":"Freiburg",
    "sg:postcode":"79117",
    "sg:province":"Baden-W\u00fcrttemberg",
    "wof:name":"Easy Electronische Anlagen Und Systeme Gmbh",
    "wof:placetype":"venue"
},
  "geometry": {"coordinates":[7.900982,47.987583],"type":"Point"}
}