{
  "type": "Feature",
  "properties": {
    "iso:country":"DE",
    "sg:address":"Nerotal 19 A",
    "sg:city":"Wiesbaden",
    "sg:postcode":"65193",
    "sg:province":"Hessen",
    "wof:name":"Tvs The Virtual Sphere Beratungs- Und Betei-",
    "wof:placetype":"venue"
},
  "geometry": {"coordinates":[8.2353830338,50.0927429199],"type":"Point"}
}