{
  "type": "Feature",
  "properties": {
    "iso:country":"DE",
    "sg:address":"Badstr. 2",
    "sg:city":"Oranienburg",
    "sg:phone":"+49 3301/530164",
    "sg:postcode":"16515",
    "sg:province":"Brandenburg",
    "wof:name":"Peter Fischer",
    "wof:placetype":"venue"
},
  "geometry": {"coordinates":[13.2482337952,52.7283668518],"type":"Point"}
}