{
  "type": "Feature",
  "properties": {
    "iso:country":"DE",
    "sg:address":"Christinenstr. 4",
    "sg:city":"Ratingen",
    "sg:phone":"+49 2102/99680",
    "sg:postcode":"40880",
    "sg:province":"Nordrhein-Westfalen",
    "wof:name":"David Brown Group Deutschland Gmbh",
    "wof:placetype":"venue"
},
  "geometry": {"coordinates":[6.822653,51.305916],"type":"Point"}
}