{
  "type": "Feature",
  "properties": {
    "iso:country":"DE",
    "sg:address":"J\u00e4gerweg 2",
    "sg:city":"Bayerbach",
    "sg:phone":"+49 8532/96100",
    "sg:postcode":"94137",
    "sg:province":"Bayern",
    "wof:name":"Hubert Wolfsfellner",
    "wof:placetype":"venue"
},
  "geometry": {"coordinates":[13.133480072,48.4137496948],"type":"Point"}
}