{
  "type": "Feature",
  "properties": {
    "iso:country":"DE",
    "sg:address":"Dahlerdyk 1-27",
    "sg:city":"Krefeld",
    "sg:phone":"+49 2151/818780",
    "sg:postcode":"47803",
    "sg:province":"Nordrhein-Westfalen",
    "wof:name":"C. A. Lensing Gmbh",
    "wof:placetype":"venue"
},
  "geometry": {"coordinates":[6.5603899956,51.3420295715],"type":"Point"}
}