{
  "type": "Feature",
  "properties": {
    "iso:country":"DE",
    "sg:address":"Waldstr. 11a",
    "sg:city":"Berlin",
    "sg:phone":"+49 4930/4137001",
    "sg:postcode":"13403",
    "sg:province":"Berlin",
    "wof:name":"Vollmann Garderobenanlagen Gmbh",
    "wof:placetype":"venue"
},
  "geometry": {"coordinates":[13.328468,52.575768],"type":"Point"}
}