{
  "type": "Feature",
  "properties": {
    "iso:country":"DE",
    "sg:address":"R\u00fcsternweg 11",
    "sg:city":"Halle",
    "sg:phone":"+49 345/5504697",
    "sg:postcode":"06120",
    "sg:province":"Sachsen-Anhalt",
    "wof:name":"Karl-heinz Troll",
    "wof:placetype":"venue"
},
  "geometry": {"coordinates":[11.908022,51.511875],"type":"Point"}
}