{
  "type": "Feature",
  "properties": {
    "iso:country":"DE",
    "sg:address":"Uttenweiler Str. 11",
    "sg:city":"Betzenweiler",
    "sg:phone":"+49 7374/539",
    "sg:postcode":"88422",
    "sg:province":"Baden-W\u00fcrttemberg",
    "wof:name":"A. W\u00e4scher",
    "wof:placetype":"venue"
},
  "geometry": {"coordinates":[9.5748806,48.1188812256],"type":"Point"}
}