{
  "type": "Feature",
  "properties": {
    "iso:country":"DE",
    "sg:address":"K\u00f6nigstr. 29",
    "sg:city":"Aachen",
    "sg:phone":"+49 241/4012831",
    "sg:postcode":"52064",
    "sg:province":"Nordrhein-Westfalen",
    "wof:name":"Imperia Ag",
    "wof:placetype":"venue"
},
  "geometry": {"coordinates":[6.0763669014,50.775554657],"type":"Point"}
}