{
  "type": "Feature",
  "properties": {
    "iso:country":"DE",
    "sg:address":"Westwall 179",
    "sg:city":"Krefeld",
    "sg:phone":"+49 2151/23589",
    "sg:postcode":"47798",
    "sg:province":"Nordrhein-Westfalen",
    "wof:name":"Herbert Horster",
    "wof:placetype":"venue"
},
  "geometry": {"coordinates":[6.557313,51.336498],"type":"Point"}
}