{
  "type": "Feature",
  "properties": {
    "iso:country":"DE",
    "sg:address":"Am Lerchenfeld 12",
    "sg:city":"N\u00fcrnberg",
    "sg:phone":"+49 9122/75384",
    "sg:postcode":"90455",
    "sg:province":"Bayern",
    "wof:name":"Harandt Gastst\u00e4ttenbetriebe Gmbh",
    "wof:placetype":"venue"
},
  "geometry": {"coordinates":[11.0602779388,49.3543777466],"type":"Point"}
}