{
  "type": "Feature",
  "properties": {
    "iso:country":"DE",
    "sg:address":"Achternhof 29",
    "sg:city":"L\u00fcbeck",
    "sg:postcode":"23554",
    "sg:province":"Schleswig-Holstein",
    "wof:name":"Economy Holding Forderungsankauf Gmbh",
    "wof:placetype":"venue"
},
  "geometry": {"coordinates":[10.6783237457,53.8948097229],"type":"Point"}
}