{
  "type": "Feature",
  "properties": {
    "iso:country":"DE",
    "sg:address":"Dorfstr. 25",
    "sg:city":"Riethgen",
    "sg:phone":"+49 36375/50437",
    "sg:postcode":"99638",
    "sg:province":"Th\u00fcringen",
    "wof:name":"E. Steinicke Grundst\u00dccks-verwaltungs Gmbh",
    "wof:placetype":"venue"
},
  "geometry": {"coordinates":[11.118578,51.240852],"type":"Point"}
}