{
  "type": "Feature",
  "properties": {
    "iso:country":"DE",
    "sg:address":"R\u00f6gitzstr. 6",
    "sg:city":"Haselbach",
    "sg:phone":"+49 36762/80549",
    "sg:postcode":"96523",
    "sg:province":"Th\u00fcringen",
    "wof:name":"Kulturhaus",
    "wof:placetype":"venue"
},
  "geometry": {"coordinates":[11.1951980591,50.4523277283],"type":"Point"}
}