{
  "type": "Feature",
  "properties": {
    "iso:country":"DE",
    "sg:address":"Steinweg 27",
    "sg:city":"Braunschweig",
    "sg:phone":"+49 531/18224",
    "sg:postcode":"38100",
    "sg:province":"Niedersachsen",
    "wof:name":"Restaurant Block House",
    "wof:placetype":"venue"
},
  "geometry": {"coordinates":[10.5304794312,52.2656440735],"type":"Point"}
}