{
  "type": "Feature",
  "properties": {
    "iso:country":"DE",
    "sg:address":"Eichendorffstr. 8",
    "sg:city":"Weil der Stadt",
    "sg:phone":"+49 7033/2489",
    "sg:postcode":"71263",
    "sg:province":"Baden-W\u00fcrttemberg",
    "wof:name":"Dietrich Tr\u00f6ster Ingenieur",
    "wof:placetype":"venue"
},
  "geometry": {"coordinates":[8.8604927063,48.7498207092],"type":"Point"}
}