{
  "type": "Feature",
  "properties": {
    "iso:country":"DE",
    "sg:address":"Ludwig-Ganghofer-Str. 6",
    "sg:city":"Geiselh\u00f6ring",
    "sg:phone":"+49 9423/2899",
    "sg:postcode":"94333",
    "sg:province":"Bayern",
    "wof:name":"H.-j. Hebrok Makler",
    "wof:placetype":"venue"
},
  "geometry": {"coordinates":[12.4061918259,48.8284454346],"type":"Point"}
}