{
  "type": "Feature",
  "properties": {
    "iso:country":"DE",
    "sg:address":"Im Wismat 19",
    "sg:city":"M\u00fcnchen",
    "sg:phone":"+49 89/8144400",
    "sg:postcode":"81247",
    "sg:province":"Bayern",
    "wof:name":"Sophie Fr\u00f6hlich Heilpraktikerin",
    "wof:placetype":"venue"
},
  "geometry": {"coordinates":[11.4704990387,48.1737327576],"type":"Point"}
}