{
  "type": "Feature",
  "properties": {
    "iso:country":"DE",
    "sg:address":"Daimlerstr. 10",
    "sg:city":"Bad Salzuflen",
    "sg:postcode":"32108",
    "sg:province":"Nordrhein-Westfalen",
    "wof:name":"Greferath Grundst\u00fccks-verwaltung Gmbh",
    "wof:placetype":"venue"
},
  "geometry": {"coordinates":[8.752575,52.055096],"type":"Point"}
}