{
  "type": "Feature",
  "properties": {
    "iso:country":"DE",
    "sg:address":"Wismarsche Str.",
    "sg:city":"Neubukow",
    "sg:phone":"+49 38294/9169",
    "sg:postcode":"18233",
    "sg:province":"Mecklenburg-Vorpommern",
    "wof:name":"Sportlergastst\u00e4tte",
    "wof:placetype":"venue"
},
  "geometry": {"coordinates":[11.6618700027,54.0244560242],"type":"Point"}
}