{
  "type": "Feature",
  "properties": {
    "iso:country":"DE",
    "sg:address":"Raiffeisenstr. 21",
    "sg:city":"Unterschlei\u00dfheim",
    "sg:phone":"+49 89/3106522",
    "sg:postcode":"85716",
    "sg:province":"Bayern",
    "wof:name":"Hmb Kft. Zweigniederlassung Deutschland Gmbh",
    "wof:placetype":"venue"
},
  "geometry": {"coordinates":[11.572883,48.274555],"type":"Point"}
}