{
  "type": "Feature",
  "properties": {
    "iso:country":"DE",
    "sg:address":"Holbeinstr. 65",
    "sg:city":"Berlin",
    "sg:phone":"+49 30/8438940",
    "sg:postcode":"12205",
    "sg:province":"Berlin",
    "wof:name":"Peter Tarnogrocki Steuerberater",
    "wof:placetype":"venue"
},
  "geometry": {"coordinates":[13.3007488251,52.4377746582],"type":"Point"}
}