{
  "type": "Feature",
  "properties": {
    "iso:country":"DE",
    "sg:address":"Hafnerstr. 24",
    "sg:city":"Cham",
    "sg:phone":"+49 9971/803983",
    "sg:postcode":"93413",
    "sg:province":"Bayern",
    "wof:name":"Pace`n Style E. K.",
    "wof:placetype":"venue"
},
  "geometry": {"coordinates":[12.666874,49.219082],"type":"Point"}
}