{
  "type": "Feature",
  "properties": {
    "iso:country":"DE",
    "sg:address":"Klosterstr. 20",
    "sg:city":"Rietberg",
    "sg:phone":"+49 5244/7113",
    "sg:postcode":"33397",
    "sg:province":"Nordrhein-Westfalen",
    "wof:name":"St. Johannes",
    "wof:placetype":"venue"
},
  "geometry": {"coordinates":[8.42977,51.80798],"type":"Point"}
}