{
  "type": "Feature",
  "properties": {
    "iso:country":"DE",
    "sg:address":"Gewerbering 6",
    "sg:city":"Steinach",
    "sg:postcode":"94377",
    "sg:province":"Bayern",
    "wof:name":"Bello Mobile E. K.",
    "wof:placetype":"venue"
},
  "geometry": {"coordinates":[12.621995,48.955971],"type":"Point"}
}