{
  "type": "Feature",
  "properties": {
    "iso:country":"DE",
    "sg:address":"Uhlandstr. 62",
    "sg:city":"Berlin",
    "sg:phone":"+49 30/86409407",
    "sg:postcode":"10719",
    "sg:province":"Berlin",
    "wof:name":"Jacket Haar Gmbh",
    "wof:placetype":"venue"
},
  "geometry": {"coordinates":[13.323459,52.494247],"type":"Point"}
}