{
  "type": "Feature",
  "properties": {
    "iso:country":"DE",
    "sg:address":"Henckellweg 15",
    "sg:city":"Hannover",
    "sg:phone":"+49 511/422881",
    "sg:postcode":"30459",
    "sg:province":"Niedersachsen",
    "wof:name":"Rudolf Innig",
    "wof:placetype":"venue"
},
  "geometry": {"coordinates":[9.7266349792,52.3468132019],"type":"Point"}
}