{
  "type": "Feature",
  "properties": {
    "iso:country":"DE",
    "sg:address":"Am Westpark 8",
    "sg:city":"M\u00fcnchen",
    "sg:phone":"+49 89/76760",
    "sg:postcode":"81373",
    "sg:province":"Bayern",
    "wof:name":"Archiv Des Allgemeinen Deutschen Automobil-clubs",
    "wof:placetype":"venue"
},
  "geometry": {"coordinates":[11.533663,48.124149],"type":"Point"}
}