{
  "type": "Feature",
  "properties": {
    "iso:country":"DE",
    "sg:address":"Kreuzwiesenweg 17",
    "sg:city":"Dornhan",
    "sg:phone":"+49 7455/8851",
    "sg:postcode":"72175",
    "sg:province":"Baden-W\u00fcrttemberg",
    "wof:name":"Hans G\u00fcnthner",
    "wof:placetype":"venue"
},
  "geometry": {"coordinates":[8.5433778763,48.3906097412],"type":"Point"}
}