{
  "type": "Feature",
  "properties": {
    "iso:country":"DE",
    "sg:address":"Scho\u00dfbergstr. 18",
    "sg:city":"Wiesbaden",
    "sg:phone":"+49 611/27181",
    "sg:postcode":"65201",
    "sg:province":"Hessen",
    "wof:name":"B. K.-stahlhandel Gmbh",
    "wof:placetype":"venue"
},
  "geometry": {"coordinates":[8.207488,50.046021],"type":"Point"}
}