{
  "type": "Feature",
  "properties": {
    "iso:country":"DE",
    "sg:address":"Bahnhofstr. 1",
    "sg:city":"Neustadt",
    "sg:postcode":"91413",
    "sg:province":"Bayern",
    "wof:name":"Geno Net Gmbh",
    "wof:placetype":"venue"
},
  "geometry": {"coordinates":[8.210682869,47.9107551575],"type":"Point"}
}