{
  "type": "Feature",
  "properties": {
    "iso:country":"DE",
    "sg:address":"Hindenburgstr. 36",
    "sg:city":"Neustadt",
    "sg:phone":"+49 6692/6236",
    "sg:postcode":"35279",
    "sg:province":"Hessen",
    "wof:name":"T. Henkel",
    "wof:placetype":"venue"
},
  "geometry": {"coordinates":[9.11281,50.849541],"type":"Point"}
}