{
  "type": "Feature",
  "properties": {
    "iso:country":"DE",
    "sg:address":"Lichtenberger Str. 19",
    "sg:city":"Gro\u00dfbottwar",
    "sg:phone":"+49 7148/5766",
    "sg:postcode":"71723",
    "sg:province":"Baden-W\u00fcrttemberg",
    "wof:name":"Manfred Maier",
    "wof:placetype":"venue"
},
  "geometry": {"coordinates":[9.3154726028,49.0110778809],"type":"Point"}
}