{
  "type": "Feature",
  "properties": {
    "iso:country":"DE",
    "sg:address":"B\u00fcdinger Weg 15",
    "sg:city":"W\u00e4chtersbach",
    "sg:phone":"+49 6053/2891",
    "sg:postcode":"63607",
    "sg:province":"Hessen",
    "wof:name":"E. Schicke",
    "wof:placetype":"venue"
},
  "geometry": {"coordinates":[9.2227144241,50.3013305664],"type":"Point"}
}