{
  "type": "Feature",
  "properties": {
    "iso:country":"DE",
    "sg:address":"Zentralstr. 20",
    "sg:city":"Hameln",
    "sg:phone":"+49 5151/106042",
    "sg:postcode":"31785",
    "sg:province":"Niedersachsen",
    "wof:name":"M. Todte",
    "wof:placetype":"venue"
},
  "geometry": {"coordinates":[9.3668823242,52.1007156372],"type":"Point"}
}