{
  "type": "Feature",
  "properties": {
    "iso:country":"DE",
    "sg:address":"Am Sch\u00fctzenplatz 20",
    "sg:city":"Wiefelstede",
    "sg:postcode":"26215",
    "sg:province":"Niedersachsen",
    "wof:name":"G\u00fcnter Schr\u00f6der Parkett-fu\u00dfbodentechnik",
    "wof:placetype":"venue"
},
  "geometry": {"coordinates":[8.1105,53.250469],"type":"Point"}
}