{
  "type": "Feature",
  "properties": {
    "iso:country":"DE",
    "sg:address":"Kappelner Str. 27",
    "sg:city":"Flensburg",
    "sg:phone":"+49 461/17223",
    "sg:postcode":"24943",
    "sg:province":"Schleswig-Holstein",
    "wof:name":"Beteiligungsgesellschaft Wilhelm Jensen Mbh",
    "wof:placetype":"venue"
},
  "geometry": {"coordinates":[9.446576,54.782803],"type":"Point"}
}