{
  "type": "Feature",
  "properties": {
    "iso:country":"DE",
    "sg:address":"An der Trift 19",
    "sg:city":"Clausthal-Zellerfeld",
    "sg:phone":"+49 5323/1774",
    "sg:postcode":"38678",
    "sg:province":"Niedersachsen",
    "wof:name":"Pension Landhaus Kemper",
    "wof:placetype":"venue"
},
  "geometry": {"coordinates":[10.3331336975,51.772644043],"type":"Point"}
}