{
  "type": "Feature",
  "properties": {
    "iso:country":"DE",
    "sg:address":"Templergraben 55",
    "sg:city":"Aachen",
    "sg:phone":"+49 241/805041",
    "sg:postcode":"52062",
    "sg:province":"Nordrhein-Westfalen",
    "wof:name":"Technische Hochschule Aachen Kooperierende Lehrst\u00fchle",
    "wof:placetype":"venue"
},
  "geometry": {"coordinates":[6.078294,50.777779],"type":"Point"}
}