{
  "type": "Feature",
  "properties": {
    "iso:country":"DE",
    "sg:address":"Glauchauer Str. 24",
    "sg:city":"Waldenburg",
    "sg:phone":"+49 37608/3263",
    "sg:postcode":"08396",
    "sg:province":"Sachsen",
    "wof:name":"Steffi Schubert Physiotherapiepraxis",
    "wof:placetype":"venue"
},
  "geometry": {"coordinates":[12.601094,50.873066],"type":"Point"}
}