{
  "type": "Feature",
  "properties": {
    "iso:country":"DE",
    "sg:address":"Gollierstr. 70",
    "sg:city":"M\u00fcnchen",
    "sg:phone":"+49 89/5003170",
    "sg:postcode":"80339",
    "sg:province":"Bayern",
    "wof:name":"Thermoplan Gmbh",
    "wof:placetype":"venue"
},
  "geometry": {"coordinates":[11.533681,48.13636],"type":"Point"}
}