{
  "type": "Feature",
  "properties": {
    "iso:country":"DE",
    "sg:address":"S\u00e4uerlingstr. 34",
    "sg:city":"Boppard",
    "sg:phone":"+49 6742/5857",
    "sg:postcode":"56154",
    "sg:province":"Rheinland-Pfalz",
    "wof:name":"Olympia",
    "wof:placetype":"venue"
},
  "geometry": {"coordinates":[7.5842251778,50.2312698364],"type":"Point"}
}