{
  "type": "Feature",
  "properties": {
    "iso:country":"DE",
    "sg:address":"Bruckstr. 3",
    "sg:city":"Fellbach",
    "sg:phone":"+49 711/9579860",
    "sg:postcode":"70734",
    "sg:province":"Baden-W\u00fcrttemberg",
    "wof:name":"Hotel City Garni",
    "wof:placetype":"venue"
},
  "geometry": {"coordinates":[9.2772941589,48.8125762939],"type":"Point"}
}