{
  "type": "Feature",
  "properties": {
    "iso:country":"DE",
    "sg:address":"Obere Breite Str. 8",
    "sg:city":"Ravensburg",
    "sg:phone":"+49 751/363670",
    "sg:postcode":"88212",
    "sg:province":"Baden-W\u00fcrttemberg",
    "wof:name":"M\u00fcller Gmbh & Co. Kg",
    "wof:placetype":"venue"
},
  "geometry": {"coordinates":[9.611556,47.78241],"type":"Point"}
}