{
  "type": "Feature",
  "properties": {
    "iso:country":"DE",
    "sg:address":"Korneliusstr. 12",
    "sg:city":"Aachen",
    "sg:phone":"+49 2408/3979",
    "sg:postcode":"52076",
    "sg:province":"Nordrhein-Westfalen",
    "wof:name":"Joachim Axhausen Architekt",
    "wof:placetype":"venue"
},
  "geometry": {"coordinates":[6.184103,50.728756],"type":"Point"}
}