{
  "type": "Feature",
  "properties": {
    "iso:country":"DE",
    "sg:address":"M\u00fchlstr. 3",
    "sg:city":"Michelfeld",
    "sg:phone":"+49 791/855181",
    "sg:postcode":"74545",
    "sg:province":"Baden-W\u00fcrttemberg",
    "wof:name":"Hkr Wohnbau Gmbh",
    "wof:placetype":"venue"
},
  "geometry": {"coordinates":[9.676792,49.101284],"type":"Point"}
}