{
  "type": "Feature",
  "properties": {
    "iso:country":"DE",
    "sg:address":"Ringstr 28",
    "sg:city":"Eichenau",
    "sg:phone":"+49 8141/82058",
    "sg:postcode":"82223",
    "sg:province":"Bayern",
    "wof:name":"Dataline Kabel Gmbh",
    "wof:placetype":"venue"
},
  "geometry": {"coordinates":[11.32264,48.158039],"type":"Point"}
}