{
  "type": "Feature",
  "properties": {
    "iso:country":"DE",
    "sg:address":"Burgunder Str. 4",
    "sg:city":"Freiburg",
    "sg:phone":"+49 761/34917",
    "sg:postcode":"79104",
    "sg:province":"Baden-W\u00fcrttemberg",
    "wof:name":"Ingrid Le\u00df Steuerberater",
    "wof:placetype":"venue"
},
  "geometry": {"coordinates":[7.8559708595,48.006023407],"type":"Point"}
}