{
  "type": "Feature",
  "properties": {
    "iso:country":"DE",
    "sg:address":"Liebigstr. 19",
    "sg:city":"Gie\u00dfen",
    "sg:phone":"+49 641/75462",
    "sg:postcode":"35390",
    "sg:province":"Hessen",
    "wof:name":"Baba Jaga Hexenkessel",
    "wof:placetype":"venue"
},
  "geometry": {"coordinates":[8.6674890518,50.580696106],"type":"Point"}
}