{
  "type": "Feature",
  "properties": {
    "iso:country":"DE",
    "sg:address":"Friedrich-Ebert-Str. 35",
    "sg:city":"Erlensee",
    "sg:phone":"+49 6183/6398",
    "sg:postcode":"63526",
    "sg:province":"Hessen",
    "wof:name":"H\u00e4nfs Bierstube",
    "wof:placetype":"venue"
},
  "geometry": {"coordinates":[8.9798259735,50.1702690125],"type":"Point"}
}