{
  "type": "Feature",
  "properties": {
    "iso:country":"DE",
    "sg:address":"Am Stadtbad 31",
    "sg:city":"Essen",
    "sg:phone":"+49 2054/83983",
    "sg:postcode":"45219",
    "sg:province":"Nordrhein-Westfalen",
    "wof:name":"Jm Durchflu\u00dfmesstechnik Gmbh",
    "wof:placetype":"venue"
},
  "geometry": {"coordinates":[6.9377689362,51.3760757446],"type":"Point"}
}