{
  "type": "Feature",
  "properties": {
    "iso:country":"DE",
    "sg:address":"Gro\u00dfe Oelbruchstr. 20",
    "sg:city":"H\u00fcrth",
    "sg:phone":"+49 2233/41088",
    "sg:postcode":"50354",
    "sg:province":"Nordrhein-Westfalen",
    "wof:name":"C. Ketter Getr\u00e4nkevertrieb",
    "wof:placetype":"venue"
},
  "geometry": {"coordinates":[6.8597178459,50.8685035706],"type":"Point"}
}