{
  "type": "Feature",
  "properties": {
    "iso:country":"DE",
    "sg:address":"Berliner Allee 124",
    "sg:city":"Berlin",
    "sg:phone":"+49 30/9250771",
    "sg:postcode":"13088",
    "sg:province":"Berlin",
    "wof:name":"Susanne Wandel",
    "wof:placetype":"venue"
},
  "geometry": {"coordinates":[13.461525,52.550522],"type":"Point"}
}