{
  "type": "Feature",
  "properties": {
    "iso:country":"DE",
    "sg:address":"Breisacher Str. 1",
    "sg:city":"Berlin",
    "sg:postcode":"14195",
    "sg:province":"Berlin",
    "wof:name":"Crsr Verm\u00f6gens- Verwaltungsges. Mbh & Co.",
    "wof:placetype":"venue"
},
  "geometry": {"coordinates":[13.283222,52.444138],"type":"Point"}
}