{
  "type": "Feature",
  "properties": {
    "iso:country":"DE",
    "sg:address":"Am Recyclingpark 1",
    "sg:city":"Liebenau",
    "sg:postcode":"31618",
    "sg:province":"Niedersachsen",
    "wof:name":"Cpe Recycling Gmbh",
    "wof:placetype":"venue"
},
  "geometry": {"coordinates":[9.109478,52.595924],"type":"Point"}
}