{
  "type": "Feature",
  "properties": {
    "iso:country":"DE",
    "sg:address":"Str\u00f6hleweg 7",
    "sg:city":"Hagnau",
    "sg:postcode":"88709",
    "sg:province":"Baden-W\u00fcrttemberg",
    "wof:name":"R. Harder",
    "wof:placetype":"venue"
},
  "geometry": {"coordinates":[9.310205,47.675591],"type":"Point"}
}