{
  "type": "Feature",
  "properties": {
    "iso:country":"DE",
    "sg:address":"Wiembecker Str. 61",
    "sg:city":"Lemgo",
    "sg:phone":"+49 4952/6187691",
    "sg:postcode":"32657",
    "sg:province":"Nordrhein-Westfalen",
    "wof:name":"Hei-bu Holzbau Gbr",
    "wof:placetype":"venue"
},
  "geometry": {"coordinates":[8.9365901947,51.9992790222],"type":"Point"}
}