{
  "type": "Feature",
  "properties": {
    "iso:country":"DE",
    "sg:address":"Metzer Str. 3",
    "sg:city":"Saarlouis",
    "sg:phone":"+49 6831/3900",
    "sg:postcode":"66740",
    "sg:province":"Saarland",
    "wof:name":"Stern-apotheke Inh. Karl-heinz Mensch",
    "wof:placetype":"venue"
},
  "geometry": {"coordinates":[6.747314,49.309673],"type":"Point"}
}