{
  "type": "Feature",
  "properties": {
    "iso:country":"DE",
    "sg:address":"Alt Fermersleben 25",
    "sg:city":"Magdeburg",
    "sg:phone":"+49 391/4048188",
    "sg:postcode":"39122",
    "sg:province":"Sachsen-Anhalt",
    "wof:name":"Schmidt Und Kosab",
    "wof:placetype":"venue"
},
  "geometry": {"coordinates":[11.6559391022,52.0916824341],"type":"Point"}
}