{
  "type": "Feature",
  "properties": {
    "iso:country":"DE",
    "sg:address":"M\u00fchlenweg 2",
    "sg:city":"Kreuztal",
    "sg:phone":"+49 2732/5520",
    "sg:postcode":"57223",
    "sg:province":"Nordrhein-Westfalen",
    "wof:name":"Bender Gmbh",
    "wof:placetype":"venue"
},
  "geometry": {"coordinates":[8.0104093552,50.9581947327],"type":"Point"}
}