{
  "type": "Feature",
  "properties": {
    "iso:country":"DE",
    "sg:address":"Emil-Grabow-Str. 14",
    "sg:city":"Halle",
    "sg:phone":"+49 345/4449985",
    "sg:postcode":"06128",
    "sg:province":"Sachsen-Anhalt",
    "wof:name":"Helmut Klostermann & Sohn",
    "wof:placetype":"venue"
},
  "geometry": {"coordinates":[11.941395,51.454258],"type":"Point"}
}