{
  "type": "Feature",
  "properties": {
    "iso:country":"DE",
    "sg:address":"Zum Volksgarten 18",
    "sg:city":"Iserlohn",
    "sg:phone":"+49 2374/16450",
    "sg:postcode":"58642",
    "sg:province":"Nordrhein-Westfalen",
    "wof:name":"R. Figge",
    "wof:placetype":"venue"
},
  "geometry": {"coordinates":[7.617817,51.366753],"type":"Point"}
}