{
  "type": "Feature",
  "properties": {
    "iso:country":"DE",
    "sg:address":"Hirschstr. 9",
    "sg:city":"Ulm",
    "sg:phone":"+49 731/62536",
    "sg:postcode":"89073",
    "sg:province":"Baden-W\u00fcrttemberg",
    "wof:name":"Geber Intertabaco Gmbh",
    "wof:placetype":"venue"
},
  "geometry": {"coordinates":[9.9889688492,48.3982505798],"type":"Point"}
}