{
  "type": "Feature",
  "properties": {
    "iso:country":"DE",
    "sg:address":"Moorstr. 88",
    "sg:city":"Walsrode",
    "sg:phone":"+49 5161/2411",
    "sg:postcode":"29664",
    "sg:province":"Niedersachsen",
    "wof:name":"Kamaci Imbiss",
    "wof:placetype":"venue"
},
  "geometry": {"coordinates":[9.5876274109,52.8631401062],"type":"Point"}
}