{
  "type": "Feature",
  "properties": {
    "iso:country":"DE",
    "sg:address":"R\u00f6merstr. 33",
    "sg:city":"Brey",
    "sg:phone":"+49 2628/8395",
    "sg:postcode":"56321",
    "sg:province":"Rheinland-Pfalz",
    "wof:name":"Areal Immobilien Gmbh",
    "wof:placetype":"venue"
},
  "geometry": {"coordinates":[7.6225271225,50.2743186951],"type":"Point"}
}