{
  "type": "Feature",
  "properties": {
    "iso:country":"DE",
    "sg:address":"Am Jungholz 25",
    "sg:city":"Lohra",
    "sg:phone":"+49 6462/91155",
    "sg:postcode":"35102",
    "sg:province":"Hessen",
    "wof:name":"Wolfgang Zieske",
    "wof:placetype":"venue"
},
  "geometry": {"coordinates":[8.6388301849,50.7356491089],"type":"Point"}
}