{
  "type": "Feature",
  "properties": {
    "iso:country":"DE",
    "sg:address":"Amesdorfer Str. 37a",
    "sg:city":"G\u00fcsten",
    "sg:phone":"+49 39262/8780",
    "sg:postcode":"39439",
    "sg:province":"Sachsen-Anhalt",
    "wof:name":"Eurotec Personal Service Gmbh",
    "wof:placetype":"venue"
},
  "geometry": {"coordinates":[11.6061687469,51.7899131775],"type":"Point"}
}