{
  "type": "Feature",
  "properties": {
    "iso:country":"DE",
    "sg:address":"Schmuckerweg 6",
    "sg:city":"M\u00fcnchen",
    "sg:phone":"+49 89/422051",
    "sg:postcode":"81825",
    "sg:province":"Bayern",
    "wof:name":"Hartmut Laube",
    "wof:placetype":"venue"
},
  "geometry": {"coordinates":[11.671707,48.122108],"type":"Point"}
}