{
  "type": "Feature",
  "properties": {
    "iso:country":"DE",
    "sg:address":"Meischenstr. 2a",
    "sg:city":"Varel",
    "sg:phone":"+49 4451/2662",
    "sg:postcode":"26316",
    "sg:province":"Niedersachsen",
    "wof:name":"Heinz Heiss",
    "wof:placetype":"venue"
},
  "geometry": {"coordinates":[8.14688,53.396778],"type":"Point"}
}