{
  "type": "Feature",
  "properties": {
    "iso:country":"DE",
    "sg:address":"Willis",
    "sg:city":"Oberstaufen",
    "sg:phone":"+49 8386/1240",
    "sg:postcode":"87534",
    "sg:province":"Bayern",
    "wof:name":"Blockh\u00fctte",
    "wof:placetype":"venue"
},
  "geometry": {"coordinates":[10.0034036636,47.545753479],"type":"Point"}
}