{
  "type": "Feature",
  "properties": {
    "iso:country":"DE",
    "sg:address":"Kurf\u00fcrstenstr. 22",
    "sg:city":"Bad Bertrich",
    "sg:phone":"+49 2674/1260",
    "sg:postcode":"56864",
    "sg:province":"Rheinland-Pfalz",
    "wof:name":"Pension J\u00fcrgen Schinnen",
    "wof:placetype":"venue"
},
  "geometry": {"coordinates":[7.0289611816,50.0713043213],"type":"Point"}
}