{
  "type": "Feature",
  "properties": {
    "iso:country":"DE",
    "sg:address":"Wernerusstr. 39 A",
    "sg:city":"Celle",
    "sg:phone":"+49 5141/881894",
    "sg:postcode":"29227",
    "sg:province":"Niedersachsen",
    "wof:name":"G. Osterloh Bauunternehmen Kg",
    "wof:placetype":"venue"
},
  "geometry": {"coordinates":[10.056302,52.593269],"type":"Point"}
}