{
  "type": "Feature",
  "properties": {
    "iso:country":"DE",
    "sg:address":"Neudammstr. 24",
    "sg:city":"Braunschweig",
    "sg:phone":"+49 531/511026",
    "sg:postcode":"38116",
    "sg:province":"Niedersachsen",
    "wof:name":"Hermann Otte",
    "wof:placetype":"venue"
},
  "geometry": {"coordinates":[10.444998,52.269936],"type":"Point"}
}