{
  "type": "Feature",
  "properties": {
    "iso:country":"DE",
    "sg:address":"Buschhausen",
    "sg:city":"Halver",
    "sg:phone":"+49 2353/4936",
    "sg:postcode":"58553",
    "sg:province":"Nordrhein-Westfalen",
    "wof:name":"E. Krenzer Werkzeuge",
    "wof:placetype":"venue"
},
  "geometry": {"coordinates":[7.447621,51.212986],"type":"Point"}
}