{
  "type": "Feature",
  "properties": {
    "iso:country":"DE",
    "sg:address":"Buchener Str. 6",
    "sg:city":"Bad T\u00f6lz",
    "sg:postcode":"83646",
    "sg:province":"Bayern",
    "wof:name":"Therapie Und Wellness Zentrum - Nlp - Gmbh",
    "wof:placetype":"venue"
},
  "geometry": {"coordinates":[11.549164772,47.7602653503],"type":"Point"}
}