{
  "type": "Feature",
  "properties": {
    "iso:country":"DE",
    "sg:address":"Grovestr. 11",
    "sg:city":"Hamburg",
    "sg:postcode":"22083",
    "sg:province":"Hamburg",
    "wof:name":"Fs Autoteile E. K.",
    "wof:placetype":"venue"
},
  "geometry": {"coordinates":[10.0224895477,53.5811080933],"type":"Point"}
}