{
  "type": "Feature",
  "properties": {
    "iso:country":"DE",
    "sg:address":"Gerhart-Hauptmann-Weg 3",
    "sg:city":"L\u00fcchow",
    "sg:phone":"+49 5841/6797",
    "sg:postcode":"29439",
    "sg:province":"Niedersachsen",
    "wof:name":"Frieda Schumacher",
    "wof:placetype":"venue"
},
  "geometry": {"coordinates":[11.1458797455,52.9636116028],"type":"Point"}
}