{
  "type": "Feature",
  "properties": {
    "iso:country":"DE",
    "sg:address":"Allmannsried 179",
    "sg:city":"Scheidegg",
    "sg:phone":"+49 8381/940300",
    "sg:postcode":"88175",
    "sg:province":"Bayern",
    "wof:name":"Winnen Gmbh",
    "wof:placetype":"venue"
},
  "geometry": {"coordinates":[9.8468570709,47.6003341675],"type":"Point"}
}