{
  "type": "Feature",
  "properties": {
    "iso:country":"DE",
    "sg:address":"M\u00fchlenweg 12",
    "sg:city":"D\u00fcsseldorf",
    "sg:phone":"+49 4587/458",
    "sg:postcode":"45445",
    "sg:province":"Nordrhein-Westfalen",
    "wof:name":"Kerstin Und Steffen Homepage",
    "wof:placetype":"venue"
},
  "geometry": {"coordinates":[6.862743,51.254589],"type":"Point"}
}