{
  "type": "Feature",
  "properties": {
    "iso:country":"DE",
    "sg:address":"R\u00f6cknitzstr. 2",
    "sg:city":"Dargun",
    "sg:phone":"+49 39959/21721",
    "sg:postcode":"17159",
    "sg:province":"Mecklenburg-Vorpommern",
    "wof:name":"Vgd Verwaltungsges. Mbh",
    "wof:placetype":"venue"
},
  "geometry": {"coordinates":[12.8458309174,53.9038581848],"type":"Point"}
}