{
  "type": "Feature",
  "properties": {
    "iso:country":"DE",
    "sg:address":"Ebereschenweg 9",
    "sg:city":"Ludwigshafen",
    "sg:phone":"+49 621/551339",
    "sg:postcode":"67067",
    "sg:province":"Rheinland-Pfalz",
    "wof:name":"Helmut Burger",
    "wof:placetype":"venue"
},
  "geometry": {"coordinates":[8.4040327072,49.4621925354],"type":"Point"}
}