{
  "type": "Feature",
  "properties": {
    "iso:country":"DE",
    "sg:address":"Kneeser Str. 8",
    "sg:city":"Roggendorf",
    "sg:postcode":"19205",
    "sg:province":"Mecklenburg-Vorpommern",
    "wof:name":"Manthei Handelsgesellschaft",
    "wof:placetype":"venue"
},
  "geometry": {"coordinates":[11.0148296356,53.6916046143],"type":"Point"}
}