{
  "type": "Feature",
  "properties": {
    "iso:country":"DE",
    "sg:address":"Hauptstr. 12",
    "sg:city":"Schk\u00f6na",
    "sg:phone":"+49 34955/21157",
    "sg:postcode":"06773",
    "sg:province":"Sachsen-Anhalt",
    "wof:name":"C. Dorber",
    "wof:placetype":"venue"
},
  "geometry": {"coordinates":[12.5383253098,51.6810646057],"type":"Point"}
}