{
  "type": "Feature",
  "properties": {
    "iso:country":"DE",
    "sg:address":"Ahmser Str. 134 a",
    "sg:city":"Herford",
    "sg:phone":"+49 5221/73088",
    "sg:postcode":"32052",
    "sg:province":"Nordrhein-Westfalen",
    "wof:name":"General Woods Furnier-handels Gmbh",
    "wof:placetype":"venue"
},
  "geometry": {"coordinates":[8.6815080643,52.0979957581],"type":"Point"}
}