{
  "type": "Feature",
  "properties": {
    "iso:country":"DE",
    "sg:address":"Waldbadstr. 9-13",
    "sg:city":"Steinhagen",
    "sg:postcode":"33803",
    "sg:province":"Nordrhein-Westfalen",
    "wof:name":"Markt-promotion Ges. F\u00fcr Professionelle Vermarktung Von",
    "wof:placetype":"venue"
},
  "geometry": {"coordinates":[8.424257,52.0187],"type":"Point"}
}