{
  "type": "Feature",
  "properties": {
    "iso:country":"DE",
    "sg:address":"Hauptstr. 1",
    "sg:city":"Nehren",
    "sg:phone":"+49 4974/736587",
    "sg:postcode":"72147",
    "sg:province":"Baden-W\u00fcrttemberg",
    "wof:name":"Kreissparkasse T\u00fcbingen",
    "wof:placetype":"venue"
},
  "geometry": {"coordinates":[9.069288,48.431416],"type":"Point"}
}