{
  "type": "Feature",
  "properties": {
    "iso:country":"DE",
    "sg:address":"Kaiserstr. 27",
    "sg:city":"Kitzingen",
    "sg:phone":"+49 9321/5475",
    "sg:postcode":"97318",
    "sg:province":"Bayern",
    "wof:name":"Heinr. Sauer L\u00f6wen-drogerie F. Loy",
    "wof:placetype":"venue"
},
  "geometry": {"coordinates":[10.160586,49.738537],"type":"Point"}
}