{
  "type": "Feature",
  "properties": {
    "iso:country":"DE",
    "sg:address":"Mainstr. 17",
    "sg:city":"Norderney",
    "sg:phone":"+49 4932/447",
    "sg:postcode":"26548",
    "sg:province":"Niedersachsen",
    "wof:name":"Ev. Pfarramt Ostbezirk",
    "wof:placetype":"venue"
},
  "geometry": {"coordinates":[7.1677927971,53.7138137817],"type":"Point"}
}