{
  "type": "Feature",
  "properties": {
    "iso:country":"DE",
    "sg:address":"Robert-Bosch-Str 7",
    "sg:city":"Weilerswist",
    "sg:phone":"+49 2254/4061",
    "sg:postcode":"53919",
    "sg:province":"Nordrhein-Westfalen",
    "wof:name":"Imbert Gmbh",
    "wof:placetype":"venue"
},
  "geometry": {"coordinates":[6.852973,50.751305],"type":"Point"}
}