{
  "type": "Feature",
  "properties": {
    "iso:country":"DE",
    "sg:address":"Schleefstr. 5",
    "sg:city":"Dortmund",
    "sg:phone":"+49 231/94550",
    "sg:postcode":"44287",
    "sg:province":"Nordrhein-Westfalen",
    "wof:name":"Hecker Glastechnik Beteiligungs- Gmbh",
    "wof:placetype":"venue"
},
  "geometry": {"coordinates":[7.570093,51.50124],"type":"Point"}
}