{
  "type": "Feature",
  "properties": {
    "iso:country":"DE",
    "sg:address":"Bahnhofstr. 21",
    "sg:city":"Bad Camberg",
    "sg:phone":"+49 6434/4731",
    "sg:postcode":"65520",
    "sg:province":"Hessen",
    "wof:name":"Horst Thimm Architekt",
    "wof:placetype":"venue"
},
  "geometry": {"coordinates":[8.263628,50.297142],"type":"Point"}
}