{
  "type": "Feature",
  "properties": {
    "iso:country":"DE",
    "sg:address":"Ulmenstr. 4a",
    "sg:city":"Kaiserslautern",
    "sg:phone":"+49 631/56359",
    "sg:postcode":"67661",
    "sg:province":"Rheinland-Pfalz",
    "wof:name":"Christine Martin-spies",
    "wof:placetype":"venue"
},
  "geometry": {"coordinates":[7.696931839,49.4192352295],"type":"Point"}
}