{
  "type": "Feature",
  "properties": {
    "iso:country":"DE",
    "sg:address":"R\u00f6dgerbachstr. 77",
    "sg:city":"Aachen",
    "sg:phone":"+49 241/9519051",
    "sg:postcode":"52080",
    "sg:province":"Nordrhein-Westfalen",
    "wof:name":"Klaus Vanderheyden Gmbh",
    "wof:placetype":"venue"
},
  "geometry": {"coordinates":[6.1444201469,50.7750587463],"type":"Point"}
}