{
  "type": "Feature",
  "properties": {
    "iso:country":"DE",
    "sg:address":"Sundergaustr. 3",
    "sg:city":"Obing",
    "sg:phone":"+49 8624/2276",
    "sg:postcode":"83119",
    "sg:province":"Bayern",
    "wof:name":"Konrad Mayer B\u00e4ckerei",
    "wof:placetype":"venue"
},
  "geometry": {"coordinates":[12.405014,48.006897],"type":"Point"}
}