{
  "type": "Feature",
  "properties": {
    "iso:country":"DE",
    "sg:address":"Donopskuppe 12",
    "sg:city":"Meiningen",
    "sg:phone":"+49 3693/502432",
    "sg:postcode":"98617",
    "sg:province":"Th\u00fcringen",
    "wof:name":"Bergastst\u00e4tte Helenenh\u00f6he",
    "wof:placetype":"venue"
},
  "geometry": {"coordinates":[10.4269266129,50.5615844727],"type":"Point"}
}