{
  "type": "Feature",
  "properties": {
    "iso:country":"DE",
    "sg:address":"Hauptstr. 21",
    "sg:city":"Goldisthal",
    "sg:phone":"+49 36781/37147",
    "sg:postcode":"98746",
    "sg:province":"Th\u00fcringen",
    "wof:name":"Druckerei Drautsch",
    "wof:placetype":"venue"
},
  "geometry": {"coordinates":[11.005565,50.521374],"type":"Point"}
}