{
  "type": "Feature",
  "properties": {
    "iso:country":"DE",
    "sg:address":"Postfach",
    "sg:city":"Achern",
    "sg:phone":"+49 7841/5206",
    "sg:postcode":"77841",
    "sg:province":"Baden-W\u00fcrttemberg",
    "wof:name":"Hallenbad Und Freischwimmbad",
    "wof:placetype":"venue"
},
  "geometry": {"coordinates":[8.0746498108,48.6317596436],"type":"Point"}
}