{
  "type": "Feature",
  "properties": {
    "iso:country":"DE",
    "sg:address":"M\u00fchlenstr. 1",
    "sg:city":"Gladbeck",
    "sg:postcode":"45964",
    "sg:province":"Nordrhein-Westfalen",
    "wof:name":"Behindertenwerkstatt",
    "wof:placetype":"venue"
},
  "geometry": {"coordinates":[6.977202,51.573456],"type":"Point"}
}