{
  "type": "Feature",
  "properties": {
    "iso:country":"DE",
    "sg:address":"Hauptstr. 49",
    "sg:city":"Butjadingen",
    "sg:phone":"+49 4735/1219",
    "sg:postcode":"26969",
    "sg:province":"Niedersachsen",
    "wof:name":"Klaus Ammermann",
    "wof:placetype":"venue"
},
  "geometry": {"coordinates":[8.26648,53.577461],"type":"Point"}
}