{
  "type": "Feature",
  "properties": {
    "iso:country":"DE",
    "sg:address":"Jakobstr. 6-8",
    "sg:city":"Weimar",
    "sg:postcode":"99423",
    "sg:province":"Th\u00fcringen",
    "wof:name":"Dmb Musica Film- Und Videoproduktion Gmbh",
    "wof:placetype":"venue"
},
  "geometry": {"coordinates":[11.3302211761,50.9816169739],"type":"Point"}
}