{
  "type": "Feature",
  "properties": {
    "iso:country":"DE",
    "sg:address":"Am Karlsplatz 1",
    "sg:city":"Dissen",
    "sg:phone":"+49 5421/930788",
    "sg:postcode":"49201",
    "sg:province":"Niedersachsen",
    "wof:name":"Gastst\u00e4tte Am Karlsplatz",
    "wof:placetype":"venue"
},
  "geometry": {"coordinates":[8.204631,52.114536],"type":"Point"}
}