{
  "type": "Feature",
  "properties": {
    "iso:country":"DE",
    "sg:address":"Aussiedler 13",
    "sg:city":"Nidderau",
    "sg:postcode":"61130",
    "sg:province":"Hessen",
    "wof:name":"Karl Dott",
    "wof:placetype":"venue"
},
  "geometry": {"coordinates":[8.865045,50.237968],"type":"Point"}
}