{
  "type": "Feature",
  "properties": {
    "iso:country":"DE",
    "sg:address":"Niedersachsenstr. 15a",
    "sg:city":"Osnabr\u00fcck",
    "sg:phone":"+49 541/357910",
    "sg:postcode":"49074",
    "sg:province":"Niedersachsen",
    "wof:name":"Siegfried Erxleben Rechtsanwalt",
    "wof:placetype":"venue"
},
  "geometry": {"coordinates":[8.0580615997,52.2706642151],"type":"Point"}
}