{
  "type": "Feature",
  "properties": {
    "iso:country":"DE",
    "sg:address":"Alzeyer Str. 24-26",
    "sg:city":"Worms",
    "sg:phone":"+49 6241/52047",
    "sg:postcode":"67549",
    "sg:province":"Rheinland-Pfalz",
    "wof:name":"Redaktion Die Grossk\u00fcche Verlagsgemeinschaft Siebdruck",
    "wof:placetype":"venue"
},
  "geometry": {"coordinates":[8.3519687653,49.6311645508],"type":"Point"}
}