{
  "type": "Feature",
  "properties": {
    "iso:country":"DE",
    "sg:address":"Kettelerstr. 19",
    "sg:city":"Michelstadt",
    "sg:phone":"+49 6066/262",
    "sg:postcode":"64720",
    "sg:province":"Hessen",
    "wof:name":"Ludwig Siefert",
    "wof:placetype":"venue"
},
  "geometry": {"coordinates":[9.10463,49.713074],"type":"Point"}
}