{
  "type": "Feature",
  "properties": {
    "iso:country":"DE",
    "sg:address":"F\u00e4hrstr. 34",
    "sg:city":"Petershagen",
    "sg:phone":"+49 5702/9309",
    "sg:postcode":"32469",
    "sg:province":"Nordrhein-Westfalen",
    "wof:name":"Raiffeisen-landbund Eg An- Und Verkaufsgenossenschaft",
    "wof:placetype":"venue"
},
  "geometry": {"coordinates":[8.990561,52.377628],"type":"Point"}
}