{
  "type": "Feature",
  "properties": {
    "iso:country":"DE",
    "sg:address":"Daimlerstr. 7-11",
    "sg:city":"B\u00fcnde",
    "sg:phone":"+49 5223/62308",
    "sg:postcode":"32257",
    "sg:province":"Nordrhein-Westfalen",
    "wof:name":"Teilkemeier Gmbh",
    "wof:placetype":"venue"
},
  "geometry": {"coordinates":[8.53186,52.20089],"type":"Point"}
}