{
  "type": "Feature",
  "properties": {
    "iso:country":"DE",
    "sg:address":"Schwabenstr. 14",
    "sg:city":"Veringenstadt",
    "sg:phone":"+49 7577/1605",
    "sg:postcode":"72519",
    "sg:province":"Baden-W\u00fcrttemberg",
    "wof:name":"Martin Gratz Massagepraxis",
    "wof:placetype":"venue"
},
  "geometry": {"coordinates":[9.209989,48.184631],"type":"Point"}
}