{
  "type": "Feature",
  "properties": {
    "iso:country":"DE",
    "sg:address":"Heinzerath",
    "sg:city":"Morbach",
    "sg:phone":"+49 6533/3661",
    "sg:postcode":"54497",
    "sg:province":"Rheinland-Pfalz",
    "wof:name":"Hiltrud Kiefer Immobilienmakler Vdm",
    "wof:placetype":"venue"
},
  "geometry": {"coordinates":[7.0851302147,49.8301811218],"type":"Point"}
}