{
  "type": "Feature",
  "properties": {
    "iso:country":"DE",
    "sg:address":"Paul-Ehrlich-Str. 61",
    "sg:city":"Kempen",
    "sg:phone":"+49 2152/3083",
    "sg:postcode":"47906",
    "sg:province":"Nordrhein-Westfalen",
    "wof:name":"Hermann Schmidt Medizinische Ger\u00e4te",
    "wof:placetype":"venue"
},
  "geometry": {"coordinates":[6.40996,51.375793],"type":"Point"}
}