{
  "type": "Feature",
  "properties": {
    "iso:country":"DE",
    "sg:address":"Schopenhauerstr. 31",
    "sg:city":"N\u00fcrnberg",
    "sg:phone":"+49 911/356175",
    "sg:postcode":"90409",
    "sg:province":"Bayern",
    "wof:name":"Klaus Hager",
    "wof:placetype":"venue"
},
  "geometry": {"coordinates":[11.0883131027,49.4705047607],"type":"Point"}
}