{
  "type": "Feature",
  "properties": {
    "iso:country":"DE",
    "sg:address":"Salzweg 53",
    "sg:city":"Rheine",
    "sg:postcode":"48431",
    "sg:province":"Nordrhein-Westfalen",
    "wof:name":"Beasy Management Gmbh",
    "wof:placetype":"venue"
},
  "geometry": {"coordinates":[7.4085631371,52.2835426331],"type":"Point"}
}