{
  "type": "Feature",
  "properties": {
    "iso:country":"DE",
    "sg:address":"Bergkamp 24",
    "sg:city":"Steinfurt",
    "sg:phone":"+49 2552/97696",
    "sg:postcode":"48565",
    "sg:province":"Nordrhein-Westfalen",
    "wof:name":"Kunststoffrecycling U. Textil- Handel H\u00e4nel Gmbh & Co. Kg",
    "wof:placetype":"venue"
},
  "geometry": {"coordinates":[7.396775,52.133617],"type":"Point"}
}