{
  "type": "Feature",
  "properties": {
    "iso:country":"DE",
    "sg:address":"Wilhelm-Blos-Str. 39",
    "sg:city":"Stuttgart",
    "sg:postcode":"70191",
    "sg:province":"Baden-W\u00fcrttemberg",
    "wof:name":"W\u00f6rimax Gmbh",
    "wof:placetype":"venue"
},
  "geometry": {"coordinates":[9.1816835403,48.8011779785],"type":"Point"}
}