{
  "type": "Feature",
  "properties": {
    "iso:country":"DE",
    "sg:address":"Dresdner Str. 75",
    "sg:city":"Weinb\u00f6hla",
    "sg:phone":"+49 35243/3510",
    "sg:postcode":"01689",
    "sg:province":"Sachsen",
    "wof:name":"Stahl- Und Maschinenbau Graf Gmbh",
    "wof:placetype":"venue"
},
  "geometry": {"coordinates":[13.567984,51.150669],"type":"Point"}
}