{
  "type": "Feature",
  "properties": {
    "iso:country":"DE",
    "sg:address":"Krugstr. 14 Broistedt",
    "sg:city":"Lengede",
    "sg:phone":"+49 5344/920900",
    "sg:postcode":"38268",
    "sg:province":"Niedersachsen",
    "wof:name":"H Ludewig Gmbh",
    "wof:placetype":"venue"
},
  "geometry": {"coordinates":[10.3089046478,52.2035217285],"type":"Point"}
}