{
  "type": "Feature",
  "properties": {
    "iso:country":"DE",
    "sg:address":"F\u00fcrst-Ernst-Str. 2",
    "sg:city":"Rinteln",
    "sg:phone":"+49 5751/3769",
    "sg:postcode":"31737",
    "sg:province":"Niedersachsen",
    "wof:name":"Wolfgang Wilke Steuerbevollm\u00e4chtigter",
    "wof:placetype":"venue"
},
  "geometry": {"coordinates":[9.0732746124,52.1874580383],"type":"Point"}
}