{
  "type": "Feature",
  "properties": {
    "iso:country":"DE",
    "sg:address":"Holtzenrech 18",
    "sg:city":"Neunkirchen",
    "sg:phone":"+49 6821/47440",
    "sg:postcode":"66539",
    "sg:province":"Saarland",
    "wof:name":"W. Abels Gmbh",
    "wof:placetype":"venue"
},
  "geometry": {"coordinates":[7.2199220657,49.3448486328],"type":"Point"}
}