{
  "type": "Feature",
  "properties": {
    "iso:country":"DE",
    "sg:address":"Buttermarkt 15",
    "sg:city":"Kempen",
    "sg:phone":"+49 2152/54141",
    "sg:postcode":"47906",
    "sg:province":"Nordrhein-Westfalen",
    "wof:name":"Filmtheaterbetriebe Janssen Gmbh",
    "wof:placetype":"venue"
},
  "geometry": {"coordinates":[6.4178872108,51.3644485474],"type":"Point"}
}