{
  "type": "Feature",
  "properties": {
    "iso:country":"DE",
    "sg:address":"Savignyplatz 3",
    "sg:city":"Berlin",
    "sg:phone":"+49 30/3138044",
    "sg:postcode":"10623",
    "sg:province":"Berlin",
    "wof:name":"C. Adolph Inh. Veronika Savary E. K.",
    "wof:placetype":"venue"
},
  "geometry": {"coordinates":[13.3232698441,52.5059776306],"type":"Point"}
}