{
  "type": "Feature",
  "properties": {
    "iso:country":"DE",
    "sg:address":"Breisacher Str. 16",
    "sg:city":"Mannheim",
    "sg:phone":"+49 621/471683",
    "sg:postcode":"68239",
    "sg:province":"Baden-W\u00fcrttemberg",
    "wof:name":"E. Treusch",
    "wof:placetype":"venue"
},
  "geometry": {"coordinates":[8.562572,49.469223],"type":"Point"}
}