{
  "type": "Feature",
  "properties": {
    "iso:country":"DE",
    "sg:address":"Hauptstr. 71a",
    "sg:city":"Tangendorf",
    "sg:phone":"+49 38782/40298",
    "sg:postcode":"19348",
    "sg:province":"Brandenburg",
    "wof:name":"Ronald Schr\u00f6der",
    "wof:placetype":"venue"
},
  "geometry": {"coordinates":[11.957052,53.170242],"type":"Point"}
}