{
  "type": "Feature",
  "properties": {
    "iso:country":"DE",
    "sg:address":"Dorfstr. 11",
    "sg:city":"Reken",
    "sg:phone":"+49 2864/7662",
    "sg:postcode":"48734",
    "sg:province":"Nordrhein-Westfalen",
    "wof:name":"Heinz Heiming Und Ursula Ross",
    "wof:placetype":"venue"
},
  "geometry": {"coordinates":[7.0378918648,51.7865753174],"type":"Point"}
}