{
  "type": "Feature",
  "properties": {
    "iso:country":"DE",
    "sg:address":"Gnadentaler Allee 23",
    "sg:city":"Neuss",
    "sg:phone":"+49 2131/101226",
    "sg:postcode":"41468",
    "sg:province":"Nordrhein-Westfalen",
    "wof:name":"R. Oleimeulen",
    "wof:placetype":"venue"
},
  "geometry": {"coordinates":[6.7170801163,51.1762046814],"type":"Point"}
}