{
  "type": "Feature",
  "properties": {
    "iso:country":"DE",
    "sg:address":"Dorfstr. 12",
    "sg:city":"Gutach",
    "sg:phone":"+49 7685/910590",
    "sg:postcode":"79261",
    "sg:province":"Baden-W\u00fcrttemberg",
    "wof:name":"Carre Planungsgesellschaft Mbh",
    "wof:placetype":"venue"
},
  "geometry": {"coordinates":[-100.68109893800001,34.4714698792],"type":"Point"}
}