{
  "type": "Feature",
  "properties": {
    "iso:country":"DE",
    "sg:address":"Bornaer Chaussee 118",
    "sg:city":"Markkleeberg",
    "sg:phone":"+49 34297/45377",
    "sg:postcode":"04416",
    "sg:province":"Sachsen",
    "wof:name":"Wiesner Transporte Gmbh",
    "wof:placetype":"venue"
},
  "geometry": {"coordinates":[12.431186676,51.2795257568],"type":"Point"}
}