{
  "type": "Feature",
  "properties": {
    "iso:country":"DE",
    "sg:address":"Waldh\u00f6henstr. 7",
    "sg:city":"Ilsenburg",
    "sg:postcode":"38871",
    "sg:province":"Sachsen-Anhalt",
    "wof:name":"J. P. Verwaltungsges. Mbh",
    "wof:placetype":"venue"
},
  "geometry": {"coordinates":[10.6720247269,51.8629264832],"type":"Point"}
}