{
  "type": "Feature",
  "properties": {
    "iso:country":"DE",
    "sg:address":"Im Dorfe 25",
    "sg:city":"Calberlah",
    "sg:postcode":"38547",
    "sg:province":"Niedersachsen",
    "wof:name":"Angebotssammlung F\u00fcr Webspace, Domains, Server.",
    "wof:placetype":"venue"
},
  "geometry": {"coordinates":[10.656778,52.383305],"type":"Point"}
}