{
  "type": "Feature",
  "properties": {
    "iso:country":"DE",
    "sg:address":"Bellermannstr. 79",
    "sg:city":"Berlin",
    "sg:phone":"+49 30/4937919",
    "sg:postcode":"13357",
    "sg:province":"Berlin",
    "wof:name":"Annemarie Bruhn",
    "wof:placetype":"venue"
},
  "geometry": {"coordinates":[13.3883562088,52.5522918701],"type":"Point"}
}