{
  "type": "Feature",
  "properties": {
    "iso:country":"DE",
    "sg:address":"B\u00f6kelstr. 66",
    "sg:city":"M\u00f6nchengladbach",
    "sg:phone":"+49 2161/178250",
    "sg:postcode":"41063",
    "sg:province":"Nordrhein-Westfalen",
    "wof:name":"Peter Gellner",
    "wof:placetype":"venue"
},
  "geometry": {"coordinates":[6.4391608238,51.2048110962],"type":"Point"}
}