{
  "type": "Feature",
  "properties": {
    "iso:country":"DE",
    "sg:address":"Ludwigsburger Str. 13",
    "sg:city":"Benningen",
    "sg:phone":"+49 7144/5097",
    "sg:postcode":"71726",
    "sg:province":"Baden-W\u00fcrttemberg",
    "wof:name":"Bauer-breckle Und K\u00f6lbel-schmid",
    "wof:placetype":"venue"
},
  "geometry": {"coordinates":[9.2422151566,48.947013855],"type":"Point"}
}