{
  "type": "Feature",
  "properties": {
    "iso:country":"DE",
    "sg:address":"F\u00f6rsterweg 20",
    "sg:city":"Barntrup",
    "sg:postcode":"32683",
    "sg:province":"Nordrhein-Westfalen",
    "wof:name":"Rita Burghoff",
    "wof:placetype":"venue"
},
  "geometry": {"coordinates":[9.1321516037,51.9881134033],"type":"Point"}
}