{
  "type": "Feature",
  "properties": {
    "iso:country":"DE",
    "sg:address":"Marktplatz 10",
    "sg:city":"Lahr",
    "sg:phone":"+49 7821/22324",
    "sg:postcode":"77933",
    "sg:province":"Baden-W\u00fcrttemberg",
    "wof:name":"Marktsch\u00e4nke",
    "wof:placetype":"venue"
},
  "geometry": {"coordinates":[7.8721308708,48.34034729],"type":"Point"}
}