{
  "type": "Feature",
  "properties": {
    "iso:country":"DE",
    "sg:address":"Ostlandstr. 53",
    "sg:city":"Cloppenburg",
    "sg:phone":"+49 4471/3470",
    "sg:postcode":"49661",
    "sg:province":"Niedersachsen",
    "wof:name":"G\u00fcnter Kneifel Elektroinstallation",
    "wof:placetype":"venue"
},
  "geometry": {"coordinates":[8.030011,52.853676],"type":"Point"}
}