{
  "type": "Feature",
  "properties": {
    "iso:country":"DE",
    "sg:address":"Kraienbruch 20",
    "sg:city":"Essen",
    "sg:phone":"+49 201/665741",
    "sg:postcode":"45357",
    "sg:province":"Nordrhein-Westfalen",
    "wof:name":"Werner Schwermann Mode Und Textil",
    "wof:placetype":"venue"
},
  "geometry": {"coordinates":[6.9354667664,51.4861488342],"type":"Point"}
}