{
  "type": "Feature",
  "properties": {
    "iso:country":"DE",
    "sg:address":"Tonghsweg 16",
    "sg:city":"Issum",
    "sg:phone":"+49 2835/5063",
    "sg:postcode":"47661",
    "sg:province":"Nordrhein-Westfalen",
    "wof:name":"Felke Gmbh",
    "wof:placetype":"venue"
},
  "geometry": {"coordinates":[6.423751,51.495392],"type":"Point"}
}