{
  "type": "Feature",
  "properties": {
    "iso:country":"DE",
    "sg:address":"B\u00f6rnste 108",
    "sg:city":"D\u00fclmen",
    "sg:phone":"+49 2594/84545",
    "sg:postcode":"48249",
    "sg:province":"Nordrhein-Westfalen",
    "wof:name":"W. Stein",
    "wof:placetype":"venue"
},
  "geometry": {"coordinates":[7.2291889191,51.8334579468],"type":"Point"}
}