{
  "type": "Feature",
  "properties": {
    "iso:country":"DE",
    "sg:address":"Burgring 12",
    "sg:city":"Maroldsweisach",
    "sg:phone":"+49 9535/388",
    "sg:postcode":"96126",
    "sg:province":"Bayern",
    "wof:name":"Christian Prediger",
    "wof:placetype":"venue"
},
  "geometry": {"coordinates":[10.7361307144,50.1729736328],"type":"Point"}
}