{
  "type": "Feature",
  "properties": {
    "iso:country":"DE",
    "sg:address":"Pater-Rupert-Mayer-Str. 1",
    "sg:city":"Forchheim",
    "sg:phone":"+49 9191/31863",
    "sg:postcode":"91301",
    "sg:province":"Bayern",
    "wof:name":"Paul V\u00f6llner",
    "wof:placetype":"venue"
},
  "geometry": {"coordinates":[11.0494737625,49.7295455933],"type":"Point"}
}