{
  "type": "Feature",
  "properties": {
    "iso:country":"DE",
    "sg:address":"Carl-Schurz-Str. 10",
    "sg:city":"K\u00f6ln",
    "sg:phone":"+49 221/9439200",
    "sg:postcode":"50935",
    "sg:province":"Nordrhein-Westfalen",
    "wof:name":"Claus Krengel Rechtsanwalt",
    "wof:placetype":"venue"
},
  "geometry": {"coordinates":[6.9011731148,50.92370224],"type":"Point"}
}