{
  "type": "Feature",
  "properties": {
    "iso:country":"DE",
    "sg:address":"Asmusweg 13",
    "sg:city":"Hamburg",
    "sg:phone":"+49 40/686877",
    "sg:postcode":"22043",
    "sg:province":"Hamburg",
    "wof:name":"Wilhelm O. Dierk",
    "wof:placetype":"venue"
},
  "geometry": {"coordinates":[10.068145752,53.5645370483],"type":"Point"}
}