{
  "type": "Feature",
  "properties": {
    "iso:country":"DE",
    "sg:address":"Altes Feld 28",
    "sg:city":"Arnsberg",
    "sg:postcode":"59821",
    "sg:province":"Nordrhein-Westfalen",
    "wof:name":"Behindertenwerkstatt",
    "wof:placetype":"venue"
},
  "geometry": {"coordinates":[8.065667,51.381962],"type":"Point"}
}