{
  "type": "Feature",
  "properties": {
    "iso:country":"DE",
    "sg:address":"Hoherting 5",
    "sg:city":"Prien",
    "sg:phone":"+49 8051/5519",
    "sg:postcode":"83209",
    "sg:province":"Bayern",
    "wof:name":"Thomas Geisler",
    "wof:placetype":"venue"
},
  "geometry": {"coordinates":[12.334304,47.838081],"type":"Point"}
}