{
  "type": "Feature",
  "properties": {
    "iso:country":"DE",
    "sg:address":"T\u00e4ubchenweg 76",
    "sg:city":"Leipzig",
    "sg:phone":"+49 341/6994567",
    "sg:postcode":"04317",
    "sg:province":"Sachsen",
    "wof:name":"Bernd H\u00e4hnel",
    "wof:placetype":"venue"
},
  "geometry": {"coordinates":[12.4055213928,51.3358612061],"type":"Point"}
}