{
  "type": "Feature",
  "properties": {
    "iso:country":"DE",
    "sg:address":"Kn\u00fcllweg 18",
    "sg:city":"Kassel",
    "sg:phone":"+49 561/401400",
    "sg:postcode":"34134",
    "sg:province":"Hessen",
    "wof:name":"Private Krankenversicherungen Von Der Lkh",
    "wof:placetype":"venue"
},
  "geometry": {"coordinates":[9.445653,51.296146],"type":"Point"}
}