{
  "type": "Feature",
  "properties": {
    "iso:country":"DE",
    "sg:city":"Glasau",
    "sg:postcode":"23719",
    "sg:province":"Schleswig-Holstein",
    "wof:name":"Von Der Sode",
    "wof:placetype":"venue"
},
  "geometry": {"coordinates":[10.519733,54.060261],"type":"Point"}
}