{
  "type": "Feature",
  "properties": {
    "iso:country":"DE",
    "sg:address":"Elbinger Weg 2",
    "sg:city":"Marne",
    "sg:phone":"+49 4851/3061",
    "sg:postcode":"25709",
    "sg:province":"Schleswig-Holstein",
    "wof:name":"Siegfried Melzer",
    "wof:placetype":"venue"
},
  "geometry": {"coordinates":[9.020325,53.960861],"type":"Point"}
}