{
  "type": "Feature",
  "properties": {
    "iso:country":"DE",
    "sg:address":"Resselsteig 5",
    "sg:city":"Berlin",
    "sg:phone":"+49 30/7735638",
    "sg:postcode":"12209",
    "sg:province":"Berlin",
    "wof:name":"Eckart Budde Rechtsanwalt",
    "wof:placetype":"venue"
},
  "geometry": {"coordinates":[13.3265609741,52.4164772034],"type":"Point"}
}