{
  "type": "Feature",
  "properties": {
    "iso:country":"DE",
    "sg:address":"W\u00f6rsbachstr. 17a",
    "sg:city":"H\u00fcnstetten",
    "sg:postcode":"65510",
    "sg:province":"Hessen",
    "wof:name":"Heidler Gmbh",
    "wof:placetype":"venue"
},
  "geometry": {"coordinates":[8.2082414627,50.2813262939],"type":"Point"}
}