{
  "type": "Feature",
  "properties": {
    "iso:country":"DE",
    "sg:address":"Friedrich-Ebert-Str. 8",
    "sg:city":"Worms",
    "sg:phone":"+49 6241/591782",
    "sg:postcode":"67549",
    "sg:province":"Rheinland-Pfalz",
    "wof:name":"Petra Rauth",
    "wof:placetype":"venue"
},
  "geometry": {"coordinates":[8.354516,49.633209],"type":"Point"}
}