{
  "type": "Feature",
  "properties": {
    "iso:country":"DE",
    "sg:address":"Schierhorner Weg 80",
    "sg:city":"Jesteburg",
    "sg:phone":"+49 4183/4700",
    "sg:postcode":"21266",
    "sg:province":"Niedersachsen",
    "wof:name":"Eberhard Dalberg",
    "wof:placetype":"venue"
},
  "geometry": {"coordinates":[9.9461278915,53.2958145142],"type":"Point"}
}