{
  "type": "Feature",
  "properties": {
    "iso:country":"DE",
    "sg:address":"Pfandturmstr. 15",
    "sg:city":"Bechtheim",
    "sg:phone":"+49 6242/1495",
    "sg:postcode":"67595",
    "sg:province":"Rheinland-Pfalz",
    "wof:name":"Wolfgang Schoeneck",
    "wof:placetype":"venue"
},
  "geometry": {"coordinates":[8.2939167023,49.7256011963],"type":"Point"}
}