{
  "type": "Feature",
  "properties": {
    "iso:country":"DE",
    "sg:address":"Marktplatz 13",
    "sg:city":"Rottenburg",
    "sg:phone":"+49 7472/22944",
    "sg:postcode":"72108",
    "sg:province":"Baden-W\u00fcrttemberg",
    "wof:name":"Goldener Schl\u00fcssel",
    "wof:placetype":"venue"
},
  "geometry": {"coordinates":[8.9346561432,48.4766769409],"type":"Point"}
}