{
  "type": "Feature",
  "properties": {
    "iso:country":"DE",
    "sg:address":"Gesmolder Str. 207",
    "sg:city":"Melle",
    "sg:phone":"+49 5422/2200",
    "sg:postcode":"49326",
    "sg:province":"Niedersachsen",
    "wof:name":"Lorenz",
    "wof:placetype":"venue"
},
  "geometry": {"coordinates":[8.2960596085,52.20703125],"type":"Point"}
}