{
  "type": "Feature",
  "properties": {
    "iso:country":"DE",
    "sg:address":"Holzmarkt 1",
    "sg:city":"Burg",
    "sg:phone":"+49 4825/8555",
    "sg:postcode":"25712",
    "sg:province":"Schleswig-Holstein",
    "wof:name":"Wolfgang Pehrs Rechtsanwalt Und Notar",
    "wof:placetype":"venue"
},
  "geometry": {"coordinates":[9.2632436752,53.9977798462],"type":"Point"}
}