{
  "type": "Feature",
  "properties": {
    "iso:country":"DE",
    "sg:address":"Dorfstr. 13c",
    "sg:city":"Wei\u00dfandt-G\u00f6lzau",
    "sg:phone":"+49 34978/20593",
    "sg:postcode":"06369",
    "sg:province":"Sachsen-Anhalt",
    "wof:name":"Reinhold & Reinhold Gbr",
    "wof:placetype":"venue"
},
  "geometry": {"coordinates":[12.0711755753,51.6795959473],"type":"Point"}
}