{
  "type": "Feature",
  "properties": {
    "iso:country":"DE",
    "sg:address":"Niendorf 2",
    "sg:city":"Insel Poel",
    "sg:postcode":"23999",
    "sg:province":"Mecklenburg-Vorpommern",
    "wof:name":"Helge Marnitz Rechtsanwalt",
    "wof:placetype":"venue"
},
  "geometry": {"coordinates":[11.4492120743,53.9919624329],"type":"Point"}
}