{
  "type": "Feature",
  "properties": {
    "iso:country":"DE",
    "sg:address":"Bautzner Str. 95",
    "sg:city":"Dresden",
    "sg:phone":"+49 351/8024146",
    "sg:postcode":"01099",
    "sg:province":"Sachsen",
    "wof:name":"Fiduciaria Gesellschaft F\u00fcr Wohnwirtschaftliche",
    "wof:placetype":"venue"
},
  "geometry": {"coordinates":[13.7637786865,51.0646820068],"type":"Point"}
}