{
  "type": "Feature",
  "properties": {
    "iso:country":"DE",
    "sg:address":"Zum Steinb\u00fchl 3",
    "sg:city":"Feilitzsch",
    "sg:phone":"+49 9295/8115",
    "sg:postcode":"95183",
    "sg:province":"Bayern",
    "wof:name":"Heiko Vogel",
    "wof:placetype":"venue"
},
  "geometry": {"coordinates":[11.923805,50.413551],"type":"Point"}
}