{
  "type": "Feature",
  "properties": {
    "iso:country":"DE",
    "sg:address":"Belfortstr. 31",
    "sg:city":"Freiburg",
    "sg:phone":"+49 761/288077",
    "sg:postcode":"79098",
    "sg:province":"Baden-W\u00fcrttemberg",
    "wof:name":"My Way",
    "wof:placetype":"venue"
},
  "geometry": {"coordinates":[7.8422980309,47.9940605164],"type":"Point"}
}