{
  "type": "Feature",
  "properties": {
    "iso:country":"DE",
    "sg:address":"Krankenhausstr 1",
    "sg:city":"Parthenstein",
    "sg:phone":"+49 34293/29795",
    "sg:postcode":"04668",
    "sg:province":"Sachsen",
    "wof:name":"Licht Design Management Eckhard Hofmann",
    "wof:placetype":"venue"
},
  "geometry": {"coordinates":[12.639545,51.274433],"type":"Point"}
}