{
  "type": "Feature",
  "properties": {
    "iso:country":"DE",
    "sg:address":"Regerstr. 1",
    "sg:city":"Neus\u00e4\u00df",
    "sg:phone":"+49 821/483395",
    "sg:postcode":"86356",
    "sg:province":"Bayern",
    "wof:name":"Kobelschutzverein E. V. Augsburg",
    "wof:placetype":"venue"
},
  "geometry": {"coordinates":[10.8273572922,48.3864746094],"type":"Point"}
}