{
  "type": "Feature",
  "properties": {
    "iso:country":"DE",
    "sg:address":"Mittelpilghauser Weg 9",
    "sg:city":"Solingen",
    "sg:phone":"+49 212/815035",
    "sg:postcode":"42657",
    "sg:province":"Nordrhein-Westfalen",
    "wof:name":"H. Blotzki Gmbh & Co.",
    "wof:placetype":"venue"
},
  "geometry": {"coordinates":[7.067634,51.156071],"type":"Point"}
}