{
  "type": "Feature",
  "properties": {
    "iso:country":"DE",
    "sg:address":"Breslauer Str. 5",
    "sg:city":"Oyten",
    "sg:phone":"+49 4207/801783",
    "sg:postcode":"28876",
    "sg:province":"Niedersachsen",
    "wof:name":"Borchers Transporte Gmbh",
    "wof:placetype":"venue"
},
  "geometry": {"coordinates":[9.0118837357,53.0669898987],"type":"Point"}
}