{
  "type": "Feature",
  "properties": {
    "iso:country":"DE",
    "sg:address":"Oberdorfstr. 5",
    "sg:city":"Friesenheim",
    "sg:phone":"+49 7808/541",
    "sg:postcode":"77948",
    "sg:province":"Baden-W\u00fcrttemberg",
    "wof:name":"Tanzcafe Olympia",
    "wof:placetype":"venue"
},
  "geometry": {"coordinates":[7.901422,48.396671],"type":"Point"}
}