{
  "type": "Feature",
  "properties": {
    "iso:country":"DE",
    "sg:address":"Isfeldstr. 8",
    "sg:city":"Hamburg",
    "sg:phone":"+49 40/877314",
    "sg:postcode":"22589",
    "sg:province":"Hamburg",
    "wof:name":"Frank Militzer",
    "wof:placetype":"venue"
},
  "geometry": {"coordinates":[9.82785,53.566978],"type":"Point"}
}