{
  "type": "Feature",
  "properties": {
    "iso:country":"DE",
    "sg:address":"Im Feld 34",
    "sg:city":"Gerstungen",
    "sg:phone":"+49 36922/31764",
    "sg:postcode":"99834",
    "sg:province":"Th\u00fcringen",
    "wof:name":"Karl Stelter",
    "wof:placetype":"venue"
},
  "geometry": {"coordinates":[10.060276,50.956913],"type":"Point"}
}