{
  "type": "Feature",
  "properties": {
    "iso:country":"DE",
    "sg:address":"Hainebuchenweg 13",
    "sg:city":"Aerzen",
    "sg:phone":"+49 5154/3743",
    "sg:postcode":"31855",
    "sg:province":"Niedersachsen",
    "wof:name":"Katholisches Pfarramt St. Bonifatius",
    "wof:placetype":"venue"
},
  "geometry": {"coordinates":[9.2671432495,52.047794342],"type":"Point"}
}