{
  "type": "Feature",
  "properties": {
    "iso:country":"DE",
    "sg:address":"Ocke-Nerong-Str. 27",
    "sg:city":"Wyk",
    "sg:phone":"+49 4681/4464",
    "sg:postcode":"25938",
    "sg:province":"Schleswig-Holstein",
    "wof:name":"Ev. Pfarramt I St. Nicolai",
    "wof:placetype":"venue"
},
  "geometry": {"coordinates":[8.5530948639,54.6965866089],"type":"Point"}
}