{
  "type": "Feature",
  "properties": {
    "iso:country":"DE",
    "sg:address":"Gro\u00dfe Wasserpfortstr. 1",
    "sg:city":"Jever",
    "sg:phone":"+49 4461/3181",
    "sg:postcode":"26441",
    "sg:province":"Niedersachsen",
    "wof:name":"Kath. Pfarramt St. Marien",
    "wof:placetype":"venue"
},
  "geometry": {"coordinates":[7.8992300034,53.5731086731],"type":"Point"}
}