{
  "type": "Feature",
  "properties": {
    "iso:country":"DE",
    "sg:address":"Glaswandstr. 44",
    "sg:city":"Penzberg",
    "sg:phone":"+49 8856/7799",
    "sg:postcode":"82377",
    "sg:province":"Bayern",
    "wof:name":"Dipl.ing. Peter Simmet Architekt",
    "wof:placetype":"venue"
},
  "geometry": {"coordinates":[11.356676,47.763844],"type":"Point"}
}