{
  "type": "Feature",
  "properties": {
    "iso:country":"DE",
    "sg:address":"Graf-Bernadotte-Str. 34",
    "sg:city":"Essen",
    "sg:phone":"+49 201/41711",
    "sg:postcode":"45133",
    "sg:province":"Nordrhein-Westfalen",
    "wof:name":"Gleibs Und Partner",
    "wof:placetype":"venue"
},
  "geometry": {"coordinates":[6.995173,51.410694],"type":"Point"}
}