{
  "type": "Feature",
  "properties": {
    "iso:country":"DE",
    "sg:address":"Graf-Lodron-Str. 17",
    "sg:city":"Haag",
    "sg:phone":"+49 8167/9134",
    "sg:postcode":"85410",
    "sg:province":"Bayern",
    "wof:name":"Armin Gr\u00fcnwald",
    "wof:placetype":"venue"
},
  "geometry": {"coordinates":[11.837634,48.457966],"type":"Point"}
}