{
  "type": "Feature",
  "properties": {
    "iso:country":"DE",
    "sg:address":"Lindenplatz 3",
    "sg:city":"Hagenow",
    "sg:phone":"+49 3883/722836",
    "sg:postcode":"19230",
    "sg:province":"Mecklenburg-Vorpommern",
    "wof:name":"I. Sager-wulf",
    "wof:placetype":"venue"
},
  "geometry": {"coordinates":[11.1928663254,53.4316673279],"type":"Point"}
}