{
  "type": "Feature",
  "properties": {
    "iso:country":"DE",
    "sg:address":"Trentiner Ring 5",
    "sg:city":"Neus\u00e4\u00df",
    "sg:phone":"+49 821/461024",
    "sg:postcode":"86356",
    "sg:province":"Bayern",
    "wof:name":"Fuchs Baumaschinen Vertriebs Gmbh",
    "wof:placetype":"venue"
},
  "geometry": {"coordinates":[10.829046,48.415936],"type":"Point"}
}