{
  "type": "Feature",
  "properties": {
    "iso:country":"DE",
    "sg:address":"Bahnhofstr. 11",
    "sg:city":"Tettnang",
    "sg:phone":"+49 7542/8850",
    "sg:postcode":"88069",
    "sg:province":"Baden-W\u00fcrttemberg",
    "wof:name":"Ulrich Schmidt Steuerberater",
    "wof:placetype":"venue"
},
  "geometry": {"coordinates":[9.5907964706,47.673122406],"type":"Point"}
}