{
  "type": "Feature",
  "properties": {
    "iso:country":"DE",
    "sg:address":"Ferdinand-Wallbrecht-Str. 27",
    "sg:city":"Hannover",
    "sg:phone":"+49 511/668734",
    "sg:postcode":"30163",
    "sg:province":"Niedersachsen",
    "wof:name":"G. Haynitzsch",
    "wof:placetype":"venue"
},
  "geometry": {"coordinates":[9.7474393845,52.3915863037],"type":"Point"}
}