{
  "type": "Feature",
  "properties": {
    "iso:country":"DE",
    "sg:address":"Liebknechtstr. 30",
    "sg:city":"Magdeburg",
    "sg:phone":"+49 391/7332138",
    "sg:postcode":"39108",
    "sg:province":"Sachsen-Anhalt",
    "wof:name":"Am Schlachthof",
    "wof:placetype":"venue"
},
  "geometry": {"coordinates":[11.6126298904,52.1238975525],"type":"Point"}
}