{
  "type": "Feature",
  "properties": {
    "iso:country":"DE",
    "sg:address":"Herressener Str.",
    "sg:city":"Apolda",
    "sg:phone":"+49 3644/563167",
    "sg:postcode":"99510",
    "sg:province":"Th\u00fcringen",
    "wof:name":"Restaurant Geschwister-scholl-stadion",
    "wof:placetype":"venue"
},
  "geometry": {"coordinates":[11.5003852844,51.0140991211],"type":"Point"}
}