{
  "type": "Feature",
  "properties": {
    "iso:country":"DE",
    "sg:address":"Remshart",
    "sg:city":"Rettenbach",
    "sg:phone":"+49 8224/1735",
    "sg:postcode":"89364",
    "sg:province":"Bayern",
    "wof:name":"Silberseestuben",
    "wof:placetype":"venue"
},
  "geometry": {"coordinates":[10.3557653427,48.4481544495],"type":"Point"}
}