{
  "type": "Feature",
  "properties": {
    "iso:country":"DE",
    "sg:address":"Goethestr. 28",
    "sg:city":"Borkum",
    "sg:phone":"+49 4922/2416",
    "sg:postcode":"26757",
    "sg:province":"Niedersachsen",
    "wof:name":"Hotel Haus Passat Garni",
    "wof:placetype":"venue"
},
  "geometry": {"coordinates":[6.6598601341,53.5860786438],"type":"Point"}
}