{
  "type": "Feature",
  "properties": {
    "iso:country":"DE",
    "sg:address":"Carl-von-Ossietzky-Str. 41",
    "sg:city":"G\u00f6rlitz",
    "sg:postcode":"02826",
    "sg:province":"Sachsen",
    "wof:name":"Apostolische Administratur Ordinariat",
    "wof:placetype":"venue"
},
  "geometry": {"coordinates":[14.981798172,51.142906189],"type":"Point"}
}