{
  "type": "Feature",
  "properties": {
    "iso:country":"DE",
    "sg:address":"Zschopauer Str. 169",
    "sg:city":"Chemnitz",
    "sg:phone":"+49 371/519207",
    "sg:postcode":"09126",
    "sg:province":"Sachsen",
    "wof:name":"L. Leichsenring",
    "wof:placetype":"venue"
},
  "geometry": {"coordinates":[12.940372467,50.8205947876],"type":"Point"}
}