{
  "type": "Feature",
  "properties": {
    "iso:country":"DE",
    "sg:address":"Alpenstr. 3a",
    "sg:city":"Gr\u00f6benzell",
    "sg:phone":"+49 8142/8605",
    "sg:postcode":"82194",
    "sg:province":"Bayern",
    "wof:name":"Forner",
    "wof:placetype":"venue"
},
  "geometry": {"coordinates":[11.366481,48.193432],"type":"Point"}
}