{
  "type": "Feature",
  "properties": {
    "iso:country":"DE",
    "sg:address":"Georg-Schumann-Str. 8",
    "sg:city":"Leipzig",
    "sg:phone":"+49 341/5906914",
    "sg:postcode":"04105",
    "sg:province":"Sachsen",
    "wof:name":"Regina Schmidt",
    "wof:placetype":"venue"
},
  "geometry": {"coordinates":[12.3762521744,51.3582115173],"type":"Point"}
}