{
  "type": "Feature",
  "properties": {
    "iso:country":"DE",
    "sg:address":"Malterstr. 1",
    "sg:city":"Dresden",
    "sg:phone":"+49 351/4112060",
    "sg:postcode":"01159",
    "sg:province":"Sachsen",
    "wof:name":"Steffen Stelzer",
    "wof:placetype":"venue"
},
  "geometry": {"coordinates":[13.690328,51.045677],"type":"Point"}
}