{
  "type": "Feature",
  "properties": {
    "iso:country":"DE",
    "sg:address":"Kollenburger Weg 10",
    "sg:city":"Meerbusch",
    "sg:phone":"+49 2159/51917",
    "sg:postcode":"40670",
    "sg:province":"Nordrhein-Westfalen",
    "wof:name":"Heinr. Platen",
    "wof:placetype":"venue"
},
  "geometry": {"coordinates":[6.599798,51.262211],"type":"Point"}
}