{
  "type": "Feature",
  "properties": {
    "iso:country":"DE",
    "sg:address":"Bindstr. 49",
    "sg:city":"Wangen",
    "sg:phone":"+49 7522/2460",
    "sg:postcode":"88239",
    "sg:province":"Baden-W\u00fcrttemberg",
    "wof:name":"St. Martins-apotheke",
    "wof:placetype":"venue"
},
  "geometry": {"coordinates":[9.835244,47.685383],"type":"Point"}
}