{
  "type": "Feature",
  "properties": {
    "iso:country":"DE",
    "sg:address":"Stehfenstr. 63",
    "sg:city":"Holzwickede",
    "sg:postcode":"59439",
    "sg:province":"Nordrhein-Westfalen",
    "wof:name":"Schrasitec W\u00fcstenfeld Gmbh & Co. Kg",
    "wof:placetype":"venue"
},
  "geometry": {"coordinates":[7.6254210472,51.5083312988],"type":"Point"}
}