{
  "type": "Feature",
  "properties": {
    "iso:country":"DE",
    "sg:address":"Kirchenstr. 6",
    "sg:city":"Westerstede",
    "sg:phone":"+49 4488/6091",
    "sg:postcode":"26655",
    "sg:province":"Niedersachsen",
    "wof:name":"Wilhelm Friedrich",
    "wof:placetype":"venue"
},
  "geometry": {"coordinates":[7.92911,53.258228],"type":"Point"}
}