{
  "type": "Feature",
  "properties": {
    "iso:country":"DE",
    "sg:address":"Schwanenweg 24",
    "sg:city":"Laboe",
    "sg:phone":"+49 4343/8815",
    "sg:postcode":"24235",
    "sg:province":"Schleswig-Holstein",
    "wof:name":"H. Kohn",
    "wof:placetype":"venue"
},
  "geometry": {"coordinates":[10.231308,54.397717],"type":"Point"}
}