{
  "type": "Feature",
  "properties": {
    "iso:country":"DE",
    "sg:address":"Fritz-Reuter-Weg 41",
    "sg:city":"Zeven",
    "sg:phone":"+49 4281/3440",
    "sg:postcode":"27404",
    "sg:province":"Niedersachsen",
    "wof:name":"Hannelore Wundram",
    "wof:placetype":"venue"
},
  "geometry": {"coordinates":[9.262147,53.296993],"type":"Point"}
}