{
  "type": "Feature",
  "properties": {
    "iso:country":"DE",
    "sg:address":"Auf dem Hochst\u00fcck 12",
    "sg:city":"Herten",
    "sg:phone":"+49 2366/953105",
    "sg:postcode":"45701",
    "sg:province":"Nordrhein-Westfalen",
    "wof:name":"Schmidtke Holzbau Gmbh",
    "wof:placetype":"venue"
},
  "geometry": {"coordinates":[7.1052379608,51.6050415039],"type":"Point"}
}