{
  "type": "Feature",
  "properties": {
    "iso:country":"DE",
    "sg:address":"Wetzlarer Str. 26",
    "sg:city":"N\u00fcrnberg",
    "sg:phone":"+49 911/930600",
    "sg:postcode":"90427",
    "sg:province":"Bayern",
    "wof:name":"August Hoff Import Inh.walter Adler",
    "wof:placetype":"venue"
},
  "geometry": {"coordinates":[11.0026626587,49.518245697],"type":"Point"}
}