{
  "type": "Feature",
  "properties": {
    "iso:country":"DE",
    "sg:address":"Bahnhofstr.",
    "sg:city":"Laichingen",
    "sg:phone":"+49 7333/6555",
    "sg:postcode":"89150",
    "sg:province":"Baden-W\u00fcrttemberg",
    "wof:name":"Mattheis Gmbh",
    "wof:placetype":"venue"
},
  "geometry": {"coordinates":[9.687921,48.489422],"type":"Point"}
}