{
  "type": "Feature",
  "properties": {
    "iso:country":"DE",
    "sg:address":"Im Karweg 3",
    "sg:city":"Sundern",
    "sg:phone":"+49 2933/8460",
    "sg:postcode":"59846",
    "sg:province":"Nordrhein-Westfalen",
    "wof:name":"Blome Gmbh",
    "wof:placetype":"venue"
},
  "geometry": {"coordinates":[7.981685,51.297489],"type":"Point"}
}