{
  "type": "Feature",
  "properties": {
    "iso:country":"DE",
    "sg:address":"Uhlandweg 34",
    "sg:city":"Rheinfelden",
    "sg:phone":"+49 7623/61788",
    "sg:postcode":"79618",
    "sg:province":"Baden-W\u00fcrttemberg",
    "wof:name":"K.-h. Und B. Misera",
    "wof:placetype":"venue"
},
  "geometry": {"coordinates":[7.773316,47.560982],"type":"Point"}
}