{
  "type": "Feature",
  "properties": {
    "iso:country":"DE",
    "sg:address":"Frankfurter Str. 147-149",
    "sg:city":"Neu-Isenburg",
    "sg:phone":"+49 6102/787272",
    "sg:postcode":"63263",
    "sg:province":"Hessen",
    "wof:name":"Mobil Com Shop",
    "wof:placetype":"venue"
},
  "geometry": {"coordinates":[8.6950511932,50.0498886108],"type":"Point"}
}