{
  "type": "Feature",
  "properties": {
    "iso:country":"DE",
    "sg:address":"Weseler Str. 32",
    "sg:city":"M\u00fcnster",
    "sg:phone":"+49 251/522684",
    "sg:postcode":"48151",
    "sg:province":"Nordrhein-Westfalen",
    "wof:name":"Bier-u. Weinsch\u00e4nke Dos Passos",
    "wof:placetype":"venue"
},
  "geometry": {"coordinates":[7.6196689606,51.9538154602],"type":"Point"}
}