{
  "type": "Feature",
  "properties": {
    "iso:country":"DE",
    "sg:address":"An der F\u00e4hre 3",
    "sg:city":"Frankfurt",
    "sg:postcode":"65933",
    "sg:province":"Hessen",
    "wof:name":"Gap E. K.",
    "wof:placetype":"venue"
},
  "geometry": {"coordinates":[8.6093616486,50.0905990601],"type":"Point"}
}