{
  "type": "Feature",
  "properties": {
    "iso:country":"DE",
    "sg:address":"Friedrich-K\u00f6nig-Str 3-5",
    "sg:city":"Mannheim",
    "sg:phone":"+49 621/3390681",
    "sg:postcode":"68167",
    "sg:province":"Baden-W\u00fcrttemberg",
    "wof:name":"Mst Micro Surface Treatment Gmbh",
    "wof:placetype":"venue"
},
  "geometry": {"coordinates":[8.502343,49.494785],"type":"Point"}
}