{
  "type": "Feature",
  "properties": {
    "iso:country":"DE",
    "sg:address":"H\u00fcttenstr. 24",
    "sg:city":"Blankenburg",
    "sg:phone":"+49 3944/9280",
    "sg:postcode":"38889",
    "sg:province":"Sachsen-Anhalt",
    "wof:name":"Umwelttechnik Und Wasserbau Gmbh",
    "wof:placetype":"venue"
},
  "geometry": {"coordinates":[10.9412765503,51.7951469421],"type":"Point"}
}