{
  "type": "Feature",
  "properties": {
    "iso:country":"DE",
    "sg:address":"Eisenbahnstr. 25",
    "sg:city":"Ravensburg",
    "sg:phone":"+49 751/23005",
    "sg:postcode":"88212",
    "sg:province":"Baden-W\u00fcrttemberg",
    "wof:name":"Kath. Pfarramt St. Jodok",
    "wof:placetype":"venue"
},
  "geometry": {"coordinates":[9.6108188629,47.7829742432],"type":"Point"}
}