{
  "type": "Feature",
  "properties": {
    "iso:country":"DE",
    "sg:address":"Hagenstr. 5",
    "sg:city":"Northeim",
    "sg:phone":"+49 5551/2151",
    "sg:postcode":"37154",
    "sg:province":"Niedersachsen",
    "wof:name":"Nolte",
    "wof:placetype":"venue"
},
  "geometry": {"coordinates":[9.999958,51.704617],"type":"Point"}
}