{
  "type": "Feature",
  "properties": {
    "iso:country":"DE",
    "sg:address":"Windm\u00fchlenstr. 25",
    "sg:city":"Naumburg",
    "sg:phone":"+49 3445/203989",
    "sg:postcode":"06618",
    "sg:province":"Sachsen-Anhalt",
    "wof:name":"B. Jenner",
    "wof:placetype":"venue"
},
  "geometry": {"coordinates":[11.8069753647,51.1559829712],"type":"Point"}
}