{
  "type": "Feature",
  "properties": {
    "iso:country":"DE",
    "sg:address":"Luitpoldstr. 62",
    "sg:city":"Ludwigshafen",
    "sg:postcode":"67063",
    "sg:province":"Rheinland-Pfalz",
    "wof:name":"Kath. \u00d6ffentliche Bibliothek St. Gallus",
    "wof:placetype":"venue"
},
  "geometry": {"coordinates":[8.410258,49.498112],"type":"Point"}
}