{
  "type": "Feature",
  "properties": {
    "iso:country":"DE",
    "sg:address":"Ha\u00dffurter Str. 20",
    "sg:city":"Ha\u00dffurt",
    "sg:phone":"+49 9521/3521",
    "sg:postcode":"97437",
    "sg:province":"Bayern",
    "wof:name":"Krauser Gmbh",
    "wof:placetype":"venue"
},
  "geometry": {"coordinates":[10.5231552124,50.0604057312],"type":"Point"}
}