{
  "type": "Feature",
  "properties": {
    "iso:country":"DE",
    "sg:address":"Gro\u00dfmoorkehre 2",
    "sg:city":"Hamburg",
    "sg:phone":"+49 40/7673380",
    "sg:postcode":"21079",
    "sg:province":"Hamburg",
    "wof:name":"Albert Block Gmbh Armaturen",
    "wof:placetype":"venue"
},
  "geometry": {"coordinates":[10.0099191666,53.4587249756],"type":"Point"}
}