{
  "type": "Feature",
  "properties": {
    "iso:country":"DE",
    "sg:address":"Ziegelh\u00fcttenwg. 27-31",
    "sg:city":"Frankfurt",
    "sg:phone":"+49 69/63300633",
    "sg:postcode":"60598",
    "sg:province":"Hessen",
    "wof:name":"Peter Naacher Gmbh & Co. Kg",
    "wof:placetype":"venue"
},
  "geometry": {"coordinates":[8.6805362701,50.0929260254],"type":"Point"}
}