{
  "type": "Feature",
  "properties": {
    "iso:country":"DE",
    "sg:address":"Frankfurter Allee",
    "sg:city":"Berlin",
    "sg:postcode":"10247",
    "sg:province":"Berlin",
    "wof:name":"D2-shop",
    "wof:placetype":"venue"
},
  "geometry": {"coordinates":[13.4615097046,52.5151252747],"type":"Point"}
}