{
  "type": "Feature",
  "properties": {
    "iso:country":"DE",
    "sg:address":"Konstantinstr. 85",
    "sg:city":"M\u00f6nchengladbach",
    "sg:phone":"+49 2166/87554",
    "sg:postcode":"41238",
    "sg:province":"Nordrhein-Westfalen",
    "wof:name":"Pizzeria Bella Italia 1",
    "wof:placetype":"venue"
},
  "geometry": {"coordinates":[6.4835839272,51.1571502686],"type":"Point"}
}