{
  "type": "Feature",
  "properties": {
    "iso:country":"DE",
    "sg:address":"Am R\u00fcbenberg 10",
    "sg:city":"Steinhorst",
    "sg:postcode":"29367",
    "sg:province":"Niedersachsen",
    "wof:name":"Pikobello-hoch- Und Tiefbau Gmbh",
    "wof:placetype":"venue"
},
  "geometry": {"coordinates":[10.4011211395,52.7247695923],"type":"Point"}
}