{
  "type": "Feature",
  "properties": {
    "iso:country":"DE",
    "sg:address":"Schallfelder Str. 26",
    "sg:city":"Gerolzhofen",
    "sg:postcode":"97447",
    "sg:province":"Bayern",
    "wof:name":"Oswald Kleinhenz Verwaltungs Gmbh",
    "wof:placetype":"venue"
},
  "geometry": {"coordinates":[10.351524,49.898453],"type":"Point"}
}