{
  "type": "Feature",
  "properties": {
    "iso:country":"DE",
    "sg:address":"Geschwister-Scholl-Str. 12",
    "sg:city":"Finsterwalde",
    "sg:phone":"+49 3531/8808",
    "sg:postcode":"03238",
    "sg:province":"Brandenburg",
    "wof:name":"Musicshop 4u",
    "wof:placetype":"venue"
},
  "geometry": {"coordinates":[13.7151889801,51.6250114441],"type":"Point"}
}