{
  "type": "Feature",
  "properties": {
    "iso:country":"DE",
    "sg:address":"Lange Laube 18",
    "sg:city":"Hannover",
    "sg:phone":"+49 511/1697201",
    "sg:postcode":"30159",
    "sg:province":"Niedersachsen",
    "wof:name":"Siggelkow Computer Hannover Gmbh",
    "wof:placetype":"venue"
},
  "geometry": {"coordinates":[9.7291440964,52.3766555786],"type":"Point"}
}