{
  "type": "Feature",
  "properties": {
    "iso:country":"DE",
    "sg:address":"Stapeler Dorfstr 23",
    "sg:city":"Horstedt",
    "sg:phone":"+49 4288/93010",
    "sg:postcode":"27367",
    "sg:province":"Niedersachsen",
    "wof:name":"Aries",
    "wof:placetype":"venue"
},
  "geometry": {"coordinates":[9.202421,53.176212],"type":"Point"}
}