{
  "type": "Feature",
  "properties": {
    "iso:country":"DE",
    "sg:address":"Im Tr\u00fcmpchen 11",
    "sg:city":"Dernbach",
    "sg:phone":"+49 2689/7496",
    "sg:postcode":"56307",
    "sg:province":"Rheinland-Pfalz",
    "wof:name":"Verlagsb\u00fcro Pantle Trunnk",
    "wof:placetype":"venue"
},
  "geometry": {"coordinates":[7.5936331749,50.5430641174],"type":"Point"}
}