{
  "type": "Feature",
  "properties": {
    "iso:country":"DE",
    "sg:address":"Wangsa\u00df",
    "sg:city":"Hemau",
    "sg:postcode":"93155",
    "sg:province":"Bayern",
    "wof:name":"Johann M\u00fcller",
    "wof:placetype":"venue"
},
  "geometry": {"coordinates":[11.8535,49.059677],"type":"Point"}
}