{
  "type": "Feature",
  "properties": {
    "iso:country":"DE",
    "sg:address":"H\u00fcnegr\u00e4ben 28",
    "sg:city":"Schmallenberg",
    "sg:phone":"+49 2972/47875",
    "sg:postcode":"57392",
    "sg:province":"Nordrhein-Westfalen",
    "wof:name":"Oberfl\u00e4chentechnik Reinhold Blum",
    "wof:placetype":"venue"
},
  "geometry": {"coordinates":[8.3052797318,51.1581611633],"type":"Point"}
}