{
  "type": "Feature",
  "properties": {
    "iso:country":"DE",
    "sg:address":"Ganslbachstr. 5",
    "sg:city":"Witzmannsberg",
    "sg:phone":"+49 8504/8956",
    "sg:postcode":"94104",
    "sg:province":"Bayern",
    "wof:name":"Elektro Pauli Gmbh",
    "wof:placetype":"venue"
},
  "geometry": {"coordinates":[13.411813,48.742157],"type":"Point"}
}