{
  "type": "Feature",
  "properties": {
    "iso:country":"DE",
    "sg:address":"Roter Weg 39",
    "sg:city":"Freiberg",
    "sg:phone":"+49 3731/355500",
    "sg:postcode":"09599",
    "sg:province":"Sachsen",
    "wof:name":"Funk-taxi-service Gmbh",
    "wof:placetype":"venue"
},
  "geometry": {"coordinates":[13.34278965,50.9108924866],"type":"Point"}
}