{
  "type": "Feature",
  "properties": {
    "iso:country":"DE",
    "sg:address":"Metzer Str. 14",
    "sg:city":"Wiesbaden",
    "sg:phone":"+49 611/1860232",
    "sg:postcode":"65203",
    "sg:province":"Hessen",
    "wof:name":"Jarax Bau Gmbh",
    "wof:placetype":"venue"
},
  "geometry": {"coordinates":[8.225709,50.04438],"type":"Point"}
}