{
  "type": "Feature",
  "properties": {
    "iso:country":"DE",
    "sg:address":"Daimlerstr. 44",
    "sg:city":"Waldbronn",
    "sg:phone":"+49 7243/67268",
    "sg:postcode":"76337",
    "sg:province":"Baden-W\u00fcrttemberg",
    "wof:name":"Dr. Schade & Partner Informationsverarbeitungs-",
    "wof:placetype":"venue"
},
  "geometry": {"coordinates":[8.4873476028,48.9258117676],"type":"Point"}
}