{
  "type": "Feature",
  "properties": {
    "iso:country":"DE",
    "sg:address":"Werner-von-Siemens-Str. 116",
    "sg:city":"W\u00fcrzburg",
    "sg:phone":"+49 931/271131",
    "sg:postcode":"97076",
    "sg:province":"Bayern",
    "wof:name":"Theodor \u00d6hrlein",
    "wof:placetype":"venue"
},
  "geometry": {"coordinates":[9.985359,49.810581],"type":"Point"}
}