{
  "type": "Feature",
  "properties": {
    "iso:country":"DE",
    "sg:address":"Bahnhofstr. 27",
    "sg:city":"Burg",
    "sg:phone":"+49 3921/94140",
    "sg:postcode":"39288",
    "sg:province":"Sachsen-Anhalt",
    "wof:name":"Versicherungs-gesellschaft Dan-peter Poetke",
    "wof:placetype":"venue"
},
  "geometry": {"coordinates":[11.8464822769,52.2721633911],"type":"Point"}
}