{
  "type": "Feature",
  "properties": {
    "iso:country":"DE",
    "sg:address":"Pappelstr. 52",
    "sg:city":"Bremen",
    "sg:phone":"+49 421/506072",
    "sg:postcode":"28199",
    "sg:province":"Bremen",
    "wof:name":"Reformhaus Maas Gmbh",
    "wof:placetype":"venue"
},
  "geometry": {"coordinates":[8.7890987396,53.0691184998],"type":"Point"}
}