{
  "type": "Feature",
  "properties": {
    "iso:country":"DE",
    "sg:address":"Pirmasenser Str. 24",
    "sg:city":"Kaiserslautern",
    "sg:phone":"+49 631/60497",
    "sg:postcode":"67655",
    "sg:province":"Rheinland-Pfalz",
    "wof:name":"M\u00f6ckel",
    "wof:placetype":"venue"
},
  "geometry": {"coordinates":[7.7664852142,49.4410896301],"type":"Point"}
}