{
  "type": "Feature",
  "properties": {
    "iso:country":"DE",
    "sg:address":"August-Nagel-Str. 22",
    "sg:city":"Ulm",
    "sg:phone":"+49 8457/92910",
    "sg:postcode":"89079",
    "sg:province":"Baden-W\u00fcrttemberg",
    "wof:name":"Item-bayern Gmbh",
    "wof:placetype":"venue"
},
  "geometry": {"coordinates":[11.602513,48.73584],"type":"Point"}
}