{
  "type": "Feature",
  "properties": {
    "iso:country":"DE",
    "sg:address":"Kapellenstr. 82",
    "sg:city":"Ahlen",
    "sg:phone":"+49 2382/3641",
    "sg:postcode":"59227",
    "sg:province":"Nordrhein-Westfalen",
    "wof:name":"Theodor Beckl\u00f6nne",
    "wof:placetype":"venue"
},
  "geometry": {"coordinates":[7.8747811317,51.7677078247],"type":"Point"}
}