{
  "type": "Feature",
  "properties": {
    "iso:country":"DE",
    "sg:address":"Kirchheimer Str. 51",
    "sg:city":"Wernau",
    "sg:phone":"+49 7153/36213",
    "sg:postcode":"73249",
    "sg:province":"Baden-W\u00fcrttemberg",
    "wof:name":"K. G\u00f6tz B\u00e4ckerei",
    "wof:placetype":"venue"
},
  "geometry": {"coordinates":[9.417242,48.691395],"type":"Point"}
}