{
  "type": "Feature",
  "properties": {
    "iso:country":"DE",
    "sg:address":"Oraniensteiner Str. 18 a",
    "sg:city":"Diez",
    "sg:postcode":"65582",
    "sg:province":"Rheinland-Pfalz",
    "wof:name":"Von Wellean Eigenart Ohg",
    "wof:placetype":"venue"
},
  "geometry": {"coordinates":[8.004358,50.374352],"type":"Point"}
}