{
  "type": "Feature",
  "properties": {
    "iso:country":"DE",
    "sg:address":"An der Streu 27",
    "sg:city":"Stockheim",
    "sg:phone":"+49 9776/9597",
    "sg:postcode":"97640",
    "sg:province":"Bayern",
    "wof:name":"Heinz Bartholmess Rwb Rh\u00f6nwerbung",
    "wof:placetype":"venue"
},
  "geometry": {"coordinates":[10.2706956863,50.4571075439],"type":"Point"}
}