{
  "type": "Feature",
  "properties": {
    "iso:country":"DE",
    "sg:address":"Auf dem H\u00fcls 23",
    "sg:city":"Mettmann",
    "sg:phone":"+49 2104/73573",
    "sg:postcode":"40822",
    "sg:province":"Nordrhein-Westfalen",
    "wof:name":"Steinmann Gmbh",
    "wof:placetype":"venue"
},
  "geometry": {"coordinates":[6.955327,51.253323],"type":"Point"}
}