{
  "type": "Feature",
  "properties": {
    "iso:country":"DE",
    "sg:address":"Hansaring 23",
    "sg:city":"K\u00f6ln",
    "sg:phone":"+49 221/9138380",
    "sg:postcode":"50670",
    "sg:province":"Nordrhein-Westfalen",
    "wof:name":"Newco Ferrous Trading",
    "wof:placetype":"venue"
},
  "geometry": {"coordinates":[6.944975,50.946415],"type":"Point"}
}