{
  "type": "Feature",
  "properties": {
    "iso:country":"DE",
    "sg:address":"Oderstr. 4",
    "sg:city":"Leverkusen",
    "sg:phone":"+49 214/21858",
    "sg:postcode":"51371",
    "sg:province":"Nordrhein-Westfalen",
    "wof:name":"Helmut Greyer",
    "wof:placetype":"venue"
},
  "geometry": {"coordinates":[6.959119,51.057873],"type":"Point"}
}