{
  "type": "Feature",
  "properties": {
    "iso:country":"DE",
    "sg:address":"Kalkhorster Str. 13",
    "sg:city":"Berlin",
    "sg:phone":"+49 30/8249703",
    "sg:postcode":"10713",
    "sg:province":"Berlin",
    "wof:name":"Sinus Service Gmbh",
    "wof:placetype":"venue"
},
  "geometry": {"coordinates":[13.307825,52.484936],"type":"Point"}
}