{
  "type": "Feature",
  "properties": {
    "iso:country":"DE",
    "sg:address":"Auf dem Hachenei",
    "sg:city":"B\u00f6nen",
    "sg:postcode":"59199",
    "sg:province":"Nordrhein-Westfalen",
    "wof:name":"Peg Rheinland Gmbh",
    "wof:placetype":"venue"
},
  "geometry": {"coordinates":[7.7783551216,51.5659942627],"type":"Point"}
}