{
  "type": "Feature",
  "properties": {
    "iso:country":"DE",
    "sg:address":"Erbdrostenstr. 3",
    "sg:city":"Ostbevern",
    "sg:phone":"+49 2532/5905",
    "sg:postcode":"48346",
    "sg:province":"Nordrhein-Westfalen",
    "wof:name":"W. K\u00f6vener",
    "wof:placetype":"venue"
},
  "geometry": {"coordinates":[7.8386640549,52.0389289856],"type":"Point"}
}