{
  "type": "Feature",
  "properties": {
    "iso:country":"DE",
    "sg:address":"Esserstr. 17",
    "sg:city":"K\u00f6ln",
    "sg:phone":"+49 221/8301132",
    "sg:postcode":"51105",
    "sg:province":"Nordrhein-Westfalen",
    "wof:name":"Rudolf G\u00f6rres",
    "wof:placetype":"venue"
},
  "geometry": {"coordinates":[6.998065,50.932709],"type":"Point"}
}