{
  "type": "Feature",
  "properties": {
    "iso:country":"DE",
    "sg:address":"Ritterstr. 16",
    "sg:city":"Hamburg",
    "sg:phone":"+49 40/29834370",
    "sg:postcode":"22089",
    "sg:province":"Hamburg",
    "wof:name":"Il Bacco",
    "wof:placetype":"venue"
},
  "geometry": {"coordinates":[10.0444440842,53.5675506592],"type":"Point"}
}