{
  "type": "Feature",
  "properties": {
    "iso:country":"DE",
    "sg:address":"Treunertstr. 10",
    "sg:city":"Jena",
    "sg:postcode":"07749",
    "sg:province":"Th\u00fcringen",
    "wof:name":"Dr. Med. Renate G\u00f6tz",
    "wof:placetype":"venue"
},
  "geometry": {"coordinates":[11.597057,50.920753],"type":"Point"}
}