{
  "type": "Feature",
  "properties": {
    "iso:country":"DE",
    "sg:address":"Hopfenstr. 14",
    "sg:city":"Bad Camberg",
    "sg:phone":"+49 6434/8342",
    "sg:postcode":"65520",
    "sg:province":"Hessen",
    "wof:name":"Franz Weyrich",
    "wof:placetype":"venue"
},
  "geometry": {"coordinates":[8.272326,50.301445],"type":"Point"}
}