{
  "type": "Feature",
  "properties": {
    "iso:country":"DE",
    "sg:address":"Tishelbrink 20",
    "sg:city":"L\u00f6hne",
    "sg:phone":"+49 5731/844426",
    "sg:postcode":"32584",
    "sg:province":"Nordrhein-Westfalen",
    "wof:name":"Elektro Bekemeier Gmbh",
    "wof:placetype":"venue"
},
  "geometry": {"coordinates":[8.759583,52.190411],"type":"Point"}
}