{
  "type": "Feature",
  "properties": {
    "iso:country":"DE",
    "sg:address":"Sch\u00f6nheider Str. 28",
    "sg:city":"Eibenstock",
    "sg:phone":"+49 37752/2587",
    "sg:postcode":"08309",
    "sg:province":"Sachsen",
    "wof:name":"Autolackiererei Gaube",
    "wof:placetype":"venue"
},
  "geometry": {"coordinates":[12.5912904739,50.4961585999],"type":"Point"}
}