{
  "type": "Feature",
  "properties": {
    "iso:country":"DE",
    "sg:address":"Ludwigsgraben 65",
    "sg:city":"K\u00f6sching",
    "sg:phone":"+49 8456/7816",
    "sg:postcode":"85092",
    "sg:province":"Bayern",
    "wof:name":"Georg Hallermeier",
    "wof:placetype":"venue"
},
  "geometry": {"coordinates":[11.4985408783,48.8096046448],"type":"Point"}
}