{
  "type": "Feature",
  "properties": {
    "iso:country":"DE",
    "sg:address":"Daimlerstr. 6",
    "sg:city":"Aurich",
    "sg:phone":"+49 4941/96010",
    "sg:postcode":"26607",
    "sg:province":"Niedersachsen",
    "wof:name":"Sch\u00f6ller Gmbh",
    "wof:placetype":"venue"
},
  "geometry": {"coordinates":[7.4912891388,53.5044555664],"type":"Point"}
}