{
  "type": "Feature",
  "properties": {
    "iso:country":"DE",
    "sg:address":"Am Kapellenkamp 38",
    "sg:city":"Diepholz",
    "sg:phone":"+49 5441/2887",
    "sg:postcode":"49356",
    "sg:province":"Niedersachsen",
    "wof:name":"R. Hesslau",
    "wof:placetype":"venue"
},
  "geometry": {"coordinates":[8.3722963333,52.6149940491],"type":"Point"}
}