{
  "type": "Feature",
  "properties": {
    "iso:country":"DE",
    "sg:address":"Bundesallee 100",
    "sg:city":"Braunschweig",
    "sg:phone":"+49 531/5920",
    "sg:postcode":"38116",
    "sg:province":"Niedersachsen",
    "wof:name":"Physikalisch-technische Bundesanstalt",
    "wof:placetype":"venue"
},
  "geometry": {"coordinates":[10.457318,52.295513],"type":"Point"}
}