{
  "type": "Feature",
  "properties": {
    "iso:country":"DE",
    "sg:address":"Augustenstr. 10",
    "sg:city":"M\u00fcnchen",
    "sg:postcode":"80333",
    "sg:province":"Bayern",
    "wof:name":"Metro Administration Gmbh",
    "wof:placetype":"venue"
},
  "geometry": {"coordinates":[11.5605783463,48.1451416016],"type":"Point"}
}