{
  "type": "Feature",
  "properties": {
    "iso:country":"DE",
    "sg:address":"Radstr. 12",
    "sg:city":"Laupheim",
    "sg:phone":"+49 7392/8321",
    "sg:postcode":"88471",
    "sg:province":"Baden-W\u00fcrttemberg",
    "wof:name":"Ev. Pfarramt",
    "wof:placetype":"venue"
},
  "geometry": {"coordinates":[9.8817682266,48.2311897278],"type":"Point"}
}