{
  "type": "Feature",
  "properties": {
    "iso:country":"DE",
    "sg:address":"Uhlandstr. 46",
    "sg:city":"Frankfurt",
    "sg:phone":"+49 69/494559",
    "sg:postcode":"60314",
    "sg:province":"Hessen",
    "wof:name":"Wolfgang Krobb Anlageberater",
    "wof:placetype":"venue"
},
  "geometry": {"coordinates":[8.6967363358,50.1119766235],"type":"Point"}
}