{
  "type": "Feature",
  "properties": {
    "iso:country":"DE",
    "sg:address":"Ulmenweg 13",
    "sg:city":"Sonsbeck",
    "sg:phone":"+49 2838/2020",
    "sg:postcode":"47665",
    "sg:province":"Nordrhein-Westfalen",
    "wof:name":"U. H. Mutzek",
    "wof:placetype":"venue"
},
  "geometry": {"coordinates":[6.3754267693,51.6051063538],"type":"Point"}
}