{
  "type": "Feature",
  "properties": {
    "iso:country":"DE",
    "sg:address":"Hans-Heinrich-Warnke-Str. 12",
    "sg:city":"Celle",
    "sg:postcode":"29227",
    "sg:province":"Niedersachsen",
    "wof:name":"Halliburton Holding Germany Gmbh",
    "wof:placetype":"venue"
},
  "geometry": {"coordinates":[10.11505,52.600815],"type":"Point"}
}