{
  "type": "Feature",
  "properties": {
    "iso:country":"DE",
    "sg:address":"Aulenh\u00e4user Weg 1",
    "sg:city":"Weilm\u00fcnster",
    "sg:phone":"+49 6472/2177",
    "sg:postcode":"35789",
    "sg:province":"Hessen",
    "wof:name":"Ernst Radu",
    "wof:placetype":"venue"
},
  "geometry": {"coordinates":[8.349984,50.44994],"type":"Point"}
}