{
  "type": "Feature",
  "properties": {
    "iso:country":"DE",
    "sg:address":"Scholtenweg 17",
    "sg:city":"Kalkar",
    "sg:phone":"+49 2824/965050",
    "sg:postcode":"47546",
    "sg:province":"Nordrhein-Westfalen",
    "wof:name":"Gtc Generator Trading Center",
    "wof:placetype":"venue"
},
  "geometry": {"coordinates":[6.2924528122,51.7734718323],"type":"Point"}
}