{
  "type": "Feature",
  "properties": {
    "iso:country":"DE",
    "sg:address":"Destouchesstr. 11",
    "sg:city":"M\u00fcnchen",
    "sg:phone":"+49 89/396937",
    "sg:postcode":"80803",
    "sg:province":"Bayern",
    "wof:name":"Dr. Christine Grahamer",
    "wof:placetype":"venue"
},
  "geometry": {"coordinates":[11.5819549561,48.1648025513],"type":"Point"}
}