{
  "type": "Feature",
  "properties": {
    "iso:country":"DE",
    "sg:address":"Hospitalstr. 44",
    "sg:city":"Biedenkopf",
    "sg:phone":"+49 6461/924726",
    "sg:postcode":"35216",
    "sg:province":"Hessen",
    "wof:name":"Ristorante Italia Inh. D. Gamma",
    "wof:placetype":"venue"
},
  "geometry": {"coordinates":[8.5320644379,50.9088058472],"type":"Point"}
}