{
  "type": "Feature",
  "properties": {
    "iso:country":"DE",
    "sg:address":"Adlerstr. 48a",
    "sg:city":"Stutensee",
    "sg:phone":"+49 7249/4193",
    "sg:postcode":"76297",
    "sg:province":"Baden-W\u00fcrttemberg",
    "wof:name":"Rwr Rohstoff-wertstoff- Reststoff Beratungs- Handels-",
    "wof:placetype":"venue"
},
  "geometry": {"coordinates":[8.514626,49.114178],"type":"Point"}
}