{
  "type": "Feature",
  "properties": {
    "iso:country":"DE",
    "sg:address":"Stockumer Str. 196",
    "sg:city":"Dortmund",
    "sg:phone":"+49 231/7900455",
    "sg:postcode":"44225",
    "sg:province":"Nordrhein-Westfalen",
    "wof:name":"Haus Endlich Inh. Tima Devedtija",
    "wof:placetype":"venue"
},
  "geometry": {"coordinates":[7.4371600151,51.4818229675],"type":"Point"}
}