{
  "type": "Feature",
  "properties": {
    "iso:country":"DE",
    "sg:address":"Am Grenzadler 2",
    "sg:city":"Oberhof",
    "sg:phone":"+49 36842/22278",
    "sg:postcode":"98559",
    "sg:province":"Th\u00fcringen",
    "wof:name":"Schanzenbaude",
    "wof:placetype":"venue"
},
  "geometry": {"coordinates":[10.6945543289,50.7057189941],"type":"Point"}
}