{
  "type": "Feature",
  "properties": {
    "iso:country":"DE",
    "sg:address":"Berliner Freiheit 14",
    "sg:city":"Bremen",
    "sg:phone":"+49 421/461746",
    "sg:postcode":"28327",
    "sg:province":"Bremen",
    "wof:name":"Otg Objekt-technik Ges. F\u00fcr Technische Betreuung Mbh",
    "wof:placetype":"venue"
},
  "geometry": {"coordinates":[8.8925447464,53.0811882019],"type":"Point"}
}