{
  "type": "Feature",
  "properties": {
    "iso:country":"DE",
    "sg:address":"Im Schie\u00dfhaus 5A",
    "sg:city":"Stuttgart",
    "sg:phone":"+49 711/4202749",
    "sg:postcode":"70329",
    "sg:province":"Baden-W\u00fcrttemberg",
    "wof:name":"Ralf Mohr",
    "wof:placetype":"venue"
},
  "geometry": {"coordinates":[9.2548284531,48.7553825378],"type":"Point"}
}