{
  "type": "Feature",
  "properties": {
    "iso:country":"DE",
    "sg:address":"Hauptstr. 619",
    "sg:city":"Apen",
    "sg:phone":"+49 4489/1487",
    "sg:postcode":"26689",
    "sg:province":"Niedersachsen",
    "wof:name":"Vahlenkamp & Boekhoff Metallbau Gmbh",
    "wof:placetype":"venue"
},
  "geometry": {"coordinates":[7.737621,53.21595],"type":"Point"}
}