{
  "type": "Feature",
  "properties": {
    "iso:country":"DE",
    "sg:address":"Rummelsburger Str. 49",
    "sg:city":"Hamburg",
    "sg:phone":"+49 40/6481129",
    "sg:postcode":"22147",
    "sg:province":"Hamburg",
    "wof:name":"Dvbs Softwareberatung Gmbh",
    "wof:placetype":"venue"
},
  "geometry": {"coordinates":[10.1333560944,53.6102867126],"type":"Point"}
}