{
  "type": "Feature",
  "properties": {
    "iso:country":"DE",
    "sg:address":"Hauptstr. 58",
    "sg:city":"Clau\u00dfnitz",
    "sg:phone":"+49 37202/40000",
    "sg:postcode":"09236",
    "sg:province":"Sachsen",
    "wof:name":"Dws Display Gmbh",
    "wof:placetype":"venue"
},
  "geometry": {"coordinates":[12.8553199768,50.9248695374],"type":"Point"}
}