{
  "type": "Feature",
  "properties": {
    "iso:country":"DE",
    "sg:address":"Hochburger Str. 35",
    "sg:city":"Emmendingen",
    "sg:phone":"+49 7641/91670",
    "sg:postcode":"79312",
    "sg:province":"Baden-W\u00fcrttemberg",
    "wof:name":"Erhard Kuder Steuerberater",
    "wof:placetype":"venue"
},
  "geometry": {"coordinates":[7.8560957909,48.1200523376],"type":"Point"}
}