{
  "type": "Feature",
  "properties": {
    "iso:country":"DE",
    "sg:address":"An der Burg S\u00fclz 17",
    "sg:city":"Lohmar",
    "sg:phone":"+49 2205/92000",
    "sg:postcode":"53797",
    "sg:province":"Nordrhein-Westfalen",
    "wof:name":"Etec Gesellschaft F\u00fcr Technische Keramik Mbh",
    "wof:placetype":"venue"
},
  "geometry": {"coordinates":[7.2023630142,50.8756599426],"type":"Point"}
}