{
  "type": "Feature",
  "properties": {
    "iso:country":"DE",
    "sg:address":"Am Neuen Kamp 10",
    "sg:city":"Brakel",
    "sg:phone":"+49 5276/95120",
    "sg:postcode":"33034",
    "sg:province":"Nordrhein-Westfalen",
    "wof:name":"Christian Bickmann",
    "wof:placetype":"venue"
},
  "geometry": {"coordinates":[9.214947,51.769501],"type":"Point"}
}