{
  "type": "Feature",
  "properties": {
    "iso:country":"DE",
    "sg:address":"Rosenstr. 9a",
    "sg:city":"Kelsterbach",
    "sg:postcode":"65451",
    "sg:province":"Hessen",
    "wof:name":"Stiftung Verkehrssicherheit",
    "wof:placetype":"venue"
},
  "geometry": {"coordinates":[8.5345087051,50.0629425049],"type":"Point"}
}