{
  "type": "Feature",
  "properties": {
    "iso:country":"DE",
    "sg:address":"Eimsheimer Str. 3",
    "sg:city":"Wintersheim",
    "sg:phone":"+49 6733/6332",
    "sg:postcode":"67587",
    "sg:province":"Rheinland-Pfalz",
    "wof:name":"Wilfried Martin",
    "wof:placetype":"venue"
},
  "geometry": {"coordinates":[8.2820692062,49.778213501],"type":"Point"}
}