{
  "type": "Feature",
  "properties": {
    "iso:country":"DE",
    "sg:address":"Bachh\u00f6hle 11",
    "sg:city":"Solms",
    "sg:phone":"+49 6441/51703",
    "sg:postcode":"35606",
    "sg:province":"Hessen",
    "wof:name":"Karlhans Koch",
    "wof:placetype":"venue"
},
  "geometry": {"coordinates":[8.4359874725,50.5573959351],"type":"Point"}
}