{
  "type": "Feature",
  "properties": {
    "iso:country":"DE",
    "sg:address":"Von-der-Reck-Str. 13",
    "sg:city":"Nottuln",
    "sg:phone":"+49 2502/7699",
    "sg:postcode":"48301",
    "sg:province":"Nordrhein-Westfalen",
    "wof:name":"Christel Gudzent",
    "wof:placetype":"venue"
},
  "geometry": {"coordinates":[7.353455,51.928562],"type":"Point"}
}