{
  "type": "Feature",
  "properties": {
    "iso:country":"DE",
    "sg:address":"Moosstr. 11",
    "sg:city":"Bad Feilnbach",
    "sg:phone":"+49 8066/330",
    "sg:postcode":"83075",
    "sg:province":"Bayern",
    "wof:name":"Josef Millauer Baugesch\u00e4ft Gmbh",
    "wof:placetype":"venue"
},
  "geometry": {"coordinates":[12.05178,47.76339],"type":"Point"}
}