{
  "type": "Feature",
  "properties": {
    "iso:country":"DE",
    "sg:address":"Industriestr. 2",
    "sg:city":"F\u00fcrth",
    "sg:phone":"+49 911/3067600",
    "sg:postcode":"90765",
    "sg:province":"Bayern",
    "wof:name":"G\u00f6gelein International Aktiengesellschaft",
    "wof:placetype":"venue"
},
  "geometry": {"coordinates":[11.005241394,49.5107154846],"type":"Point"}
}