{
  "type": "Feature",
  "properties": {
    "iso:country":"DE",
    "sg:address":"Frankenstr. 26",
    "sg:city":"Eltmann",
    "sg:phone":"+49 9522/92290",
    "sg:postcode":"97483",
    "sg:province":"Bayern",
    "wof:name":"Weiss R\u00f6sl Br\u00e4u",
    "wof:placetype":"venue"
},
  "geometry": {"coordinates":[10.724625,49.945652],"type":"Point"}
}