{
  "type": "Feature",
  "properties": {
    "iso:country":"DE",
    "sg:address":"Ottheinrichstr. 3",
    "sg:city":"Donauw\u00f6rth",
    "sg:phone":"+49 906/4109",
    "sg:postcode":"86609",
    "sg:province":"Bayern",
    "wof:name":"F. Futschik",
    "wof:placetype":"venue"
},
  "geometry": {"coordinates":[10.77762,48.729851],"type":"Point"}
}