{
  "type": "Feature",
  "properties": {
    "iso:country":"DE",
    "sg:address":"Am Birkenw\u00e4ldchen 21 d",
    "sg:city":"Halstenbek",
    "sg:phone":"+49 4101",
    "sg:postcode":"25469",
    "sg:province":"Schleswig-Holstein",
    "wof:name":"Kerzenkurier - Ihr Individueller Pr\u00e4sent-service",
    "wof:placetype":"venue"
},
  "geometry": {"coordinates":[9.8618040085,53.6200942993],"type":"Point"}
}