{
  "type": "Feature",
  "properties": {
    "iso:country":"DE",
    "sg:address":"Schurwaldstr. 86",
    "sg:city":"Schorndorf",
    "sg:phone":"+49 7181/75809",
    "sg:postcode":"73614",
    "sg:province":"Baden-W\u00fcrttemberg",
    "wof:name":"Helmut Auw\u00e4rter",
    "wof:placetype":"venue"
},
  "geometry": {"coordinates":[9.5003967285,48.7705230713],"type":"Point"}
}