{
  "type": "Feature",
  "properties": {
    "iso:country":"DE",
    "sg:address":"Waldstr. 15",
    "sg:city":"Fredersdorf",
    "sg:phone":"+49 33439/80444",
    "sg:postcode":"15370",
    "sg:province":"Brandenburg",
    "wof:name":"P. Markwald Steuerberaterin",
    "wof:placetype":"venue"
},
  "geometry": {"coordinates":[13.7491416931,52.5245552063],"type":"Point"}
}