{
  "type": "Feature",
  "properties": {
    "iso:country":"DE",
    "sg:address":"Hann\u00f6versche Str. 20",
    "sg:city":"Dortmund",
    "sg:postcode":"44143",
    "sg:province":"Nordrhein-Westfalen",
    "wof:name":"Start Forschungs- Und Beratungsgesgesellschaft Mbh",
    "wof:placetype":"venue"
},
  "geometry": {"coordinates":[7.4972929955,51.5191268921],"type":"Point"}
}