{
  "type": "Feature",
  "properties": {
    "iso:country":"DE",
    "sg:address":"Maubacher Str. 24",
    "sg:city":"Herzogenrath",
    "sg:phone":"+49 2406/4572",
    "sg:postcode":"52134",
    "sg:province":"Nordrhein-Westfalen",
    "wof:name":"Horst Ortmanns",
    "wof:placetype":"venue"
},
  "geometry": {"coordinates":[6.0829129219,50.8576126099],"type":"Point"}
}