{
  "type": "Feature",
  "properties": {
    "iso:country":"DE",
    "sg:address":"Lilienthalstr. 21A",
    "sg:city":"Kassel",
    "sg:phone":"+49 561/573078",
    "sg:postcode":"34123",
    "sg:province":"Hessen",
    "wof:name":"J. F. Thiele",
    "wof:placetype":"venue"
},
  "geometry": {"coordinates":[9.525548,51.300587],"type":"Point"}
}