{
  "type": "Feature",
  "properties": {
    "iso:country":"DE",
    "sg:address":"R\u00f6dergasse 17",
    "sg:city":"Rothenburg",
    "sg:postcode":"91541",
    "sg:province":"Bayern",
    "wof:name":"Vth Textil-und Haushalts- Waren-vertriebs-gmbh",
    "wof:placetype":"venue"
},
  "geometry": {"coordinates":[10.1826705933,49.3773574829],"type":"Point"}
}