{
  "type": "Feature",
  "properties": {
    "iso:country":"DE",
    "sg:address":"Ostlandwehr 67",
    "sg:city":"D\u00fclmen",
    "sg:phone":"+49 2594/2605",
    "sg:postcode":"48249",
    "sg:province":"Nordrhein-Westfalen",
    "wof:name":"K. Steppke",
    "wof:placetype":"venue"
},
  "geometry": {"coordinates":[7.294782,51.835857],"type":"Point"}
}