{
  "type": "Feature",
  "properties": {
    "iso:country":"DE",
    "sg:address":"Kistlerhofstr. 88",
    "sg:city":"M\u00fcnchen",
    "sg:phone":"+49 89/8649390",
    "sg:postcode":"81379",
    "sg:province":"Bayern",
    "wof:name":"Gerhard Emrich Ingenieur",
    "wof:placetype":"venue"
},
  "geometry": {"coordinates":[11.5221805573,48.0952033997],"type":"Point"}
}