{
  "type": "Feature",
  "properties": {
    "iso:country":"DE",
    "sg:address":"Grubenstr. 2",
    "sg:city":"Br\u00fccken",
    "sg:phone":"+49 6386/6542",
    "sg:postcode":"66904",
    "sg:province":"Rheinland-Pfalz",
    "wof:name":"Heribert Braun",
    "wof:placetype":"venue"
},
  "geometry": {"coordinates":[7.3608531952,49.4321479797],"type":"Point"}
}