{
  "type": "Feature",
  "properties": {
    "iso:country":"DE",
    "sg:address":"Bernsteinstr. 41 b",
    "sg:city":"Altdorf",
    "sg:phone":"+49 871/36021",
    "sg:postcode":"84032",
    "sg:province":"Bayern",
    "wof:name":"At Your Service Gmbh",
    "wof:placetype":"venue"
},
  "geometry": {"coordinates":[12.0917291641,48.5465278625],"type":"Point"}
}