{
  "type": "Feature",
  "properties": {
    "iso:country":"DE",
    "sg:address":"Talstr. 41",
    "sg:city":"Steinach",
    "sg:phone":"+49 36762/32652",
    "sg:postcode":"96523",
    "sg:province":"Th\u00fcringen",
    "wof:name":"Werner Schmidt",
    "wof:placetype":"venue"
},
  "geometry": {"coordinates":[11.1663627625,50.435344696],"type":"Point"}
}