{
  "type": "Feature",
  "properties": {
    "iso:country":"DE",
    "sg:address":"Berliner Str. 4",
    "sg:city":"Barsinghausen",
    "sg:postcode":"30890",
    "sg:province":"Niedersachsen",
    "wof:name":"Heinrich Von Der Brelje",
    "wof:placetype":"venue"
},
  "geometry": {"coordinates":[9.462135,52.307041],"type":"Point"}
}