{
  "type": "Feature",
  "properties": {
    "iso:country":"DE",
    "sg:address":"Balanstr. 28",
    "sg:city":"M\u00fcnchen",
    "sg:postcode":"81669",
    "sg:province":"Bayern",
    "wof:name":"Hiltl Ingenieurb\u00fcro F\u00fcr Bauwesen",
    "wof:placetype":"venue"
},
  "geometry": {"coordinates":[11.595602,48.125431],"type":"Point"}
}