{
  "type": "Feature",
  "properties": {
    "iso:country":"DE",
    "sg:address":"Bahnstr. 46",
    "sg:city":"Grevenbroich",
    "sg:phone":"+49 2181/9022",
    "sg:postcode":"41515",
    "sg:province":"Nordrhein-Westfalen",
    "wof:name":"Queens Pub",
    "wof:placetype":"venue"
},
  "geometry": {"coordinates":[6.5844697952,51.0902824402],"type":"Point"}
}