{
  "type": "Feature",
  "properties": {
    "iso:country":"DE",
    "sg:address":"Max-Paul-Str. 1",
    "sg:city":"D\u00fcrmentingen",
    "sg:phone":"+49 4973/715000",
    "sg:postcode":"88525",
    "sg:province":"Baden-W\u00fcrttemberg",
    "wof:name":"Paul Maschinenfabrik Gmbh & Co Kg",
    "wof:placetype":"venue"
},
  "geometry": {"coordinates":[9.539507,48.097939],"type":"Point"}
}