{
  "type": "Feature",
  "properties": {
    "iso:country":"DE",
    "sg:address":"Bracht 23",
    "sg:city":"Sendenhorst",
    "sg:phone":"+49 2526/874",
    "sg:postcode":"48324",
    "sg:province":"Nordrhein-Westfalen",
    "wof:name":"Bernhard Jungmann",
    "wof:placetype":"venue"
},
  "geometry": {"coordinates":[7.82553,51.81546],"type":"Point"}
}