{
  "type": "Feature",
  "properties": {
    "iso:country":"DE",
    "sg:address":"Reinbeker Weg 61",
    "sg:city":"Hamburg",
    "sg:phone":"+49 40/7242027",
    "sg:postcode":"21029",
    "sg:province":"Hamburg",
    "wof:name":"Debold & Lux Beratungsges.f\u00fcr Informationssysteme Und Organ.",
    "wof:placetype":"venue"
},
  "geometry": {"coordinates":[10.225182,53.492256],"type":"Point"}
}