{
  "type": "Feature",
  "properties": {
    "iso:country":"DE",
    "sg:address":"Holl\u00e4nderstr. 12",
    "sg:city":"Berlin",
    "sg:phone":"+49 30/4556005",
    "sg:postcode":"13407",
    "sg:province":"Berlin",
    "wof:name":"Klaus Gringel",
    "wof:placetype":"venue"
},
  "geometry": {"coordinates":[13.36104,52.562],"type":"Point"}
}