{
  "type": "Feature",
  "properties": {
    "iso:country":"DE",
    "sg:address":"Schie\u00dfmauerstr. 14",
    "sg:city":"Sachsenheim",
    "sg:phone":"+49 7147/9960",
    "sg:postcode":"74343",
    "sg:province":"Baden-W\u00fcrttemberg",
    "wof:name":"Komet Stahlhalter- Und Werkzeuge",
    "wof:placetype":"venue"
},
  "geometry": {"coordinates":[9.0192012787,49.000995636],"type":"Point"}
}