{
  "type": "Feature",
  "properties": {
    "iso:country":"DE",
    "sg:address":"Charlottenstr. 44",
    "sg:city":"Stuttgart",
    "sg:phone":"+49 711/2369854",
    "sg:postcode":"70182",
    "sg:province":"Baden-W\u00fcrttemberg",
    "wof:name":"Schweizerische Lebensver- Sicherungs- Und Rentenanstalt",
    "wof:placetype":"venue"
},
  "geometry": {"coordinates":[9.1870098114,48.7734184265],"type":"Point"}
}