{
  "type": "Feature",
  "properties": {
    "iso:country":"DE",
    "sg:address":"Am Teerhaus 4",
    "sg:city":"Oberstenfeld",
    "sg:phone":"+49 7062/978950",
    "sg:postcode":"71720",
    "sg:province":"Baden-W\u00fcrttemberg",
    "wof:name":"Delwo Metaltrading Gmbh",
    "wof:placetype":"venue"
},
  "geometry": {"coordinates":[9.329907,49.020645],"type":"Point"}
}