{
  "type": "Feature",
  "properties": {
    "iso:country":"DE",
    "sg:address":"Zwischen den Gr\u00e4ben 4",
    "sg:city":"Waldsolms",
    "sg:phone":"+49 6085/386",
    "sg:postcode":"35647",
    "sg:province":"Hessen",
    "wof:name":"R. Creutzmann",
    "wof:placetype":"venue"
},
  "geometry": {"coordinates":[8.5028800964,50.434211731],"type":"Point"}
}