{
  "type": "Feature",
  "properties": {
    "iso:country":"DE",
    "sg:address":"Altengrabeng\u00e4\u00dfchen 5",
    "sg:city":"K\u00f6ln",
    "sg:phone":"+49 221/135618",
    "sg:postcode":"50668",
    "sg:province":"Nordrhein-Westfalen",
    "wof:name":"Mathias A. F\u00fcser",
    "wof:placetype":"venue"
},
  "geometry": {"coordinates":[6.950213,50.944733],"type":"Point"}
}