{
  "type": "Feature",
  "properties": {
    "iso:country":"DE",
    "sg:address":"Schiffbeker Weg 23-27",
    "sg:city":"Hamburg",
    "sg:postcode":"22111",
    "sg:province":"Hamburg",
    "wof:name":"Autohaus Wolde Gmbh",
    "wof:placetype":"venue"
},
  "geometry": {"coordinates":[10.1023235321,53.5423278809],"type":"Point"}
}