{
  "type": "Feature",
  "properties": {
    "iso:country":"DE",
    "sg:address":"Hauptstr. 16",
    "sg:city":"Saarbr\u00fccken",
    "sg:phone":"+49 6898/32445",
    "sg:postcode":"66127",
    "sg:province":"Saarland",
    "wof:name":"Eisen Marx Gmbh",
    "wof:placetype":"venue"
},
  "geometry": {"coordinates":[6.893667,49.232365],"type":"Point"}
}