{
  "type": "Feature",
  "properties": {
    "iso:country":"DE",
    "sg:address":"Dossestra\u00dfe 21",
    "sg:city":"Berlin",
    "sg:postcode":"10247",
    "sg:province":"Berlin",
    "wof:name":"Insiderdate.de",
    "wof:placetype":"venue"
},
  "geometry": {"coordinates":[13.4738531113,52.5111236572],"type":"Point"}
}