{
  "type": "Feature",
  "properties": {
    "iso:country":"DE",
    "sg:address":"Ludwigsburger Str. 76",
    "sg:city":"Freiberg",
    "sg:phone":"+49 7141/73143",
    "sg:postcode":"71691",
    "sg:province":"Baden-W\u00fcrttemberg",
    "wof:name":"R. Gruber Steinmetzbetrieb",
    "wof:placetype":"venue"
},
  "geometry": {"coordinates":[9.2020406723,48.9299850464],"type":"Point"}
}