{
  "type": "Feature",
  "properties": {
    "iso:country":"DE",
    "sg:address":"Auf der Sch\u00fcpp 14",
    "sg:city":"Wallersheim",
    "sg:phone":"+49 6558/267",
    "sg:postcode":"54597",
    "sg:province":"Rheinland-Pfalz",
    "wof:name":"Otto Spoo",
    "wof:placetype":"venue"
},
  "geometry": {"coordinates":[6.3375430107,50.3012390137],"type":"Point"}
}