{
  "type": "Feature",
  "properties": {
    "iso:country":"DE",
    "sg:address":"Bieberberg 60",
    "sg:city":"Menden",
    "sg:phone":"+49 2373/81696",
    "sg:postcode":"58710",
    "sg:province":"Nordrhein-Westfalen",
    "wof:name":"Willkommen Im Gasthof Schulte",
    "wof:placetype":"venue"
},
  "geometry": {"coordinates":[7.841492,51.417137],"type":"Point"}
}