{
  "type": "Feature",
  "properties": {
    "iso:country":"DE",
    "sg:address":"Oberweyerer Str. 21",
    "sg:city":"Hadamar",
    "sg:phone":"+49 6433/2202",
    "sg:postcode":"65589",
    "sg:province":"Hessen",
    "wof:name":"Steinbacher Frisch-h\u00e4hnchen- Grill Gmbh",
    "wof:placetype":"venue"
},
  "geometry": {"coordinates":[8.1025218964,50.469078064],"type":"Point"}
}