{
  "type": "Feature",
  "properties": {
    "iso:country":"DE",
    "sg:address":"Drawehnertorstr. 5",
    "sg:city":"Hitzacker",
    "sg:phone":"+49 5862/6409",
    "sg:postcode":"29456",
    "sg:province":"Niedersachsen",
    "wof:name":"H. Haul Lebensmittel",
    "wof:placetype":"venue"
},
  "geometry": {"coordinates":[11.0465631485,53.1508331299],"type":"Point"}
}