{
  "type": "Feature",
  "properties": {
    "iso:country":"DE",
    "sg:address":"Keltenstr. 1",
    "sg:city":"Detzem",
    "sg:phone":"+49 6507/3873",
    "sg:postcode":"54340",
    "sg:province":"Rheinland-Pfalz",
    "wof:name":"Rudolf Lex",
    "wof:placetype":"venue"
},
  "geometry": {"coordinates":[6.8474411964,49.824546814],"type":"Point"}
}