{
  "type": "Feature",
  "properties": {
    "iso:country":"DE",
    "sg:address":"Br\u00f6kerstr. 9",
    "sg:city":"Gangelt",
    "sg:phone":"+49 2454/6955",
    "sg:postcode":"52538",
    "sg:province":"Nordrhein-Westfalen",
    "wof:name":"Josef Gradissen",
    "wof:placetype":"venue"
},
  "geometry": {"coordinates":[6.0365872383,51.015411377],"type":"Point"}
}