{
  "type": "Feature",
  "properties": {
    "iso:country":"DE",
    "sg:address":"Neue Kantstr. 19",
    "sg:city":"Berlin",
    "sg:phone":"+49 30/3222520",
    "sg:postcode":"14057",
    "sg:province":"Berlin",
    "wof:name":"La Pergola",
    "wof:placetype":"venue"
},
  "geometry": {"coordinates":[13.284570694,52.5062828064],"type":"Point"}
}