{
  "type": "Feature",
  "properties": {
    "iso:country":"DE",
    "sg:address":"Uzstr. 7",
    "sg:city":"Ansbach",
    "sg:phone":"+49 981/971300",
    "sg:postcode":"91522",
    "sg:province":"Bayern",
    "wof:name":"Friedrich Rummel",
    "wof:placetype":"venue"
},
  "geometry": {"coordinates":[10.572599411,49.3023338318],"type":"Point"}
}