{
  "type": "Feature",
  "properties": {
    "iso:country":"DE",
    "sg:address":"Vincent-van-Gogh-Str. 19",
    "sg:city":"Berlin",
    "sg:phone":"+49 30/92408505",
    "sg:postcode":"13057",
    "sg:province":"Berlin",
    "wof:name":"Parit\u00e4tische Gesellschaft F\u00fcr Gesundheit Und Sozial-",
    "wof:placetype":"venue"
},
  "geometry": {"coordinates":[13.524365,52.565319],"type":"Point"}
}