{
  "type": "Feature",
  "properties": {
    "iso:country":"DE",
    "sg:address":"Ellerweg 16",
    "sg:city":"Jossgrund",
    "sg:phone":"+49 6059/1073",
    "sg:postcode":"63637",
    "sg:province":"Hessen",
    "wof:name":"H. Und U. Noll Masseure",
    "wof:placetype":"venue"
},
  "geometry": {"coordinates":[9.47077,50.194035],"type":"Point"}
}