{
  "type": "Feature",
  "properties": {
    "iso:country":"DE",
    "sg:address":"Caspar-Voght-Str. 49",
    "sg:city":"Hamburg",
    "sg:postcode":"20535",
    "sg:province":"Hamburg",
    "wof:name":"Wiz Handel Gmbh",
    "wof:placetype":"venue"
},
  "geometry": {"coordinates":[10.0610704422,53.5606155396],"type":"Point"}
}