{
  "type": "Feature",
  "properties": {
    "iso:country":"DE",
    "sg:address":"Curslacker Heerweg 1",
    "sg:city":"Hamburg",
    "sg:phone":"+49 40/7231319",
    "sg:postcode":"21039",
    "sg:province":"Hamburg",
    "wof:name":"Gasthof Stadt Hamburg",
    "wof:placetype":"venue"
},
  "geometry": {"coordinates":[10.2347602844,53.4599304199],"type":"Point"}
}