{
  "type": "Feature",
  "properties": {
    "iso:country":"DE",
    "sg:address":"Friedrich-Ebert-Str. 4",
    "sg:city":"Osthofen",
    "sg:phone":"+49 6242/2342",
    "sg:postcode":"67574",
    "sg:province":"Rheinland-Pfalz",
    "wof:name":"Willi Und Erna Rothermel Inh. Annemarie Rothermel",
    "wof:placetype":"venue"
},
  "geometry": {"coordinates":[8.3259086609,49.7040901184],"type":"Point"}
}