{
  "type": "Feature",
  "properties": {
    "iso:country":"DE",
    "sg:address":"Marktstr. 2",
    "sg:city":"Spiesen-Elversberg",
    "sg:phone":"+49 6821/71755",
    "sg:postcode":"66583",
    "sg:province":"Saarland",
    "wof:name":"Kerstins Blumenstube",
    "wof:placetype":"venue"
},
  "geometry": {"coordinates":[7.151783,49.314175],"type":"Point"}
}