{
  "type": "Feature",
  "properties": {
    "iso:country":"DE",
    "sg:address":"Schneeberger Str. 8",
    "sg:city":"Langenwei\u00dfbach",
    "sg:phone":"+49 37603/2098",
    "sg:postcode":"08134",
    "sg:province":"Sachsen",
    "wof:name":"J. Tuffner",
    "wof:placetype":"venue"
},
  "geometry": {"coordinates":[12.591466,50.647781],"type":"Point"}
}