{
  "type": "Feature",
  "properties": {
    "iso:country":"DE",
    "sg:address":"Max-Planck-Str 28",
    "sg:city":"Erkrath",
    "sg:phone":"+49 211/925480",
    "sg:postcode":"40699",
    "sg:province":"Nordrhein-Westfalen",
    "wof:name":"Pumpentechnik Erkrath Gmbh + Co Kg",
    "wof:placetype":"venue"
},
  "geometry": {"coordinates":[6.93164,51.198582],"type":"Point"}
}