{
  "type": "Feature",
  "properties": {
    "iso:country":"DE",
    "sg:address":"Benderstr. 93",
    "sg:city":"D\u00fcsseldorf",
    "sg:phone":"+49 211/287672",
    "sg:postcode":"40625",
    "sg:province":"Nordrhein-Westfalen",
    "wof:name":"Heinz Wenning",
    "wof:placetype":"venue"
},
  "geometry": {"coordinates":[6.8503718376,51.2385444641],"type":"Point"}
}