{
  "type": "Feature",
  "properties": {
    "iso:country":"DE",
    "sg:address":"Schillerstra\u00dfe 23",
    "sg:city":"Sch\u00f6nebeck",
    "sg:phone":"+49 3928",
    "sg:postcode":"39218",
    "sg:province":"Sachsen-Anhalt",
    "wof:name":"Fb Kern-haus Gmbh",
    "wof:placetype":"venue"
},
  "geometry": {"coordinates":[11.732045,52.015392],"type":"Point"}
}