{
  "type": "Feature",
  "properties": {
    "iso:country":"DE",
    "sg:address":"Kasseler Str. 6",
    "sg:city":"Homberg",
    "sg:phone":"+49 5681/2278",
    "sg:postcode":"34576",
    "sg:province":"Hessen",
    "wof:name":"Homberger Tontheater",
    "wof:placetype":"venue"
},
  "geometry": {"coordinates":[9.400485,51.033813],"type":"Point"}
}