{
  "type": "Feature",
  "properties": {
    "iso:country":"DE",
    "sg:address":"Augustgroden 44",
    "sg:city":"Stadland",
    "sg:postcode":"26937",
    "sg:province":"Niedersachsen",
    "wof:name":"Hergen St\u00fchmer Gmbh",
    "wof:placetype":"venue"
},
  "geometry": {"coordinates":[8.3285,53.461411],"type":"Point"}
}