{
  "type": "Feature",
  "properties": {
    "iso:country":"DE",
    "sg:address":"Charlottenstr. 3",
    "sg:city":"D\u00fcsseldorf",
    "sg:phone":"+49 211/362123",
    "sg:postcode":"40210",
    "sg:province":"Nordrhein-Westfalen",
    "wof:name":"Eduard Schade Masseur",
    "wof:placetype":"venue"
},
  "geometry": {"coordinates":[6.786239,51.219364],"type":"Point"}
}