{
  "type": "Feature",
  "properties": {
    "iso:country":"DE",
    "sg:address":"Mindener Str. 432",
    "sg:city":"Hille",
    "sg:phone":"+49 571/61592",
    "sg:postcode":"32479",
    "sg:province":"Nordrhein-Westfalen",
    "wof:name":"Hartumer Blumendiele Inh. Heike Krysiak",
    "wof:placetype":"venue"
},
  "geometry": {"coordinates":[8.804469,52.31805],"type":"Point"}
}