{
  "type": "Feature",
  "properties": {
    "iso:country":"DE",
    "sg:address":"Sperlingstr. 26",
    "sg:city":"Bielefeld",
    "sg:phone":"+49 521/287165",
    "sg:postcode":"33607",
    "sg:province":"Nordrhein-Westfalen",
    "wof:name":"Projekt Support Gmbh",
    "wof:placetype":"venue"
},
  "geometry": {"coordinates":[8.570084,52.019485],"type":"Point"}
}