{
  "type": "Feature",
  "properties": {
    "iso:country":"DE",
    "sg:address":"Fuhrberger Landstr. 38",
    "sg:city":"Celle",
    "sg:phone":"+49 5141/46560",
    "sg:postcode":"29225",
    "sg:province":"Niedersachsen",
    "wof:name":"Bernhard Schellworth Vertriebs Gmbh",
    "wof:placetype":"venue"
},
  "geometry": {"coordinates":[10.0195999146,52.6049880981],"type":"Point"}
}