{
  "type": "Feature",
  "properties": {
    "iso:country":"DE",
    "sg:address":"Fliederstr. 14",
    "sg:city":"Gottmadingen",
    "sg:phone":"+49 7731/71740",
    "sg:postcode":"78244",
    "sg:province":"Baden-W\u00fcrttemberg",
    "wof:name":"Friedrich Hermann",
    "wof:placetype":"venue"
},
  "geometry": {"coordinates":[8.7829532623,47.7339248657],"type":"Point"}
}