{
  "type": "Feature",
  "properties": {
    "iso:country":"DE",
    "sg:address":"L\u00fcbecker Str. 24",
    "sg:city":"Magdeburg",
    "sg:phone":"+49 391/2523499",
    "sg:postcode":"39124",
    "sg:province":"Sachsen-Anhalt",
    "wof:name":"E. Schmidt",
    "wof:placetype":"venue"
},
  "geometry": {"coordinates":[11.6361227036,52.1567268372],"type":"Point"}
}