{
  "type": "Feature",
  "properties": {
    "iso:country":"DE",
    "sg:address":"Gartenweg 8",
    "sg:city":"Schemmerhofen",
    "sg:phone":"+49 7357/1006",
    "sg:postcode":"88433",
    "sg:province":"Baden-W\u00fcrttemberg",
    "wof:name":"Gerd Bergmann Ingenieur",
    "wof:placetype":"venue"
},
  "geometry": {"coordinates":[9.7414331436,48.156829834],"type":"Point"}
}