{
  "type": "Feature",
  "properties": {
    "iso:country":"DE",
    "sg:address":"Maschweg 26",
    "sg:city":"L\u00fcbbecke",
    "sg:phone":"+49 5741/7714",
    "sg:postcode":"32312",
    "sg:province":"Nordrhein-Westfalen",
    "wof:name":"Brinkmeyer",
    "wof:placetype":"venue"
},
  "geometry": {"coordinates":[8.6052865982,52.32554245],"type":"Point"}
}