{
  "type": "Feature",
  "properties": {
    "iso:country":"DE",
    "sg:address":"Berghofstr. 2",
    "sg:city":"Bad Sooden-Allendorf",
    "sg:phone":"+49 5652/2295",
    "sg:postcode":"37242",
    "sg:province":"Hessen",
    "wof:name":"Karl-heinz Trube Masseur",
    "wof:placetype":"venue"
},
  "geometry": {"coordinates":[9.939039,51.257862],"type":"Point"}
}