{
  "type": "Feature",
  "properties": {
    "iso:country":"DE",
    "sg:address":"H\u00e4llische Str. 22",
    "sg:city":"Frankenhardt",
    "sg:phone":"+49 7959/515",
    "sg:postcode":"74586",
    "sg:province":"Baden-W\u00fcrttemberg",
    "wof:name":"Gasthaus Rudolf K\u00fchnle",
    "wof:placetype":"venue"
},
  "geometry": {"coordinates":[10.0386533737,49.0692749023],"type":"Point"}
}