{
  "type": "Feature",
  "properties": {
    "iso:country":"DE",
    "sg:address":"Brunnsteige 16",
    "sg:city":"N\u00fcrtingen",
    "sg:phone":"+49 7022/36283",
    "sg:postcode":"72622",
    "sg:province":"Baden-W\u00fcrttemberg",
    "wof:name":"Chris Fotografie Inh. Michael Heyde Und",
    "wof:placetype":"venue"
},
  "geometry": {"coordinates":[9.3375053406,48.6254119873],"type":"Point"}
}