{
  "type": "Feature",
  "properties": {
    "iso:country":"DE",
    "sg:address":"Dornierstr. 4",
    "sg:city":"Renningen",
    "sg:phone":"+49 4971/5916370",
    "sg:postcode":"71272",
    "sg:province":"Baden-W\u00fcrttemberg",
    "wof:name":"Th Geyer Gmbh & Co Kg",
    "wof:placetype":"venue"
},
  "geometry": {"coordinates":[8.9310388565,48.7797813416],"type":"Point"}
}