{
  "type": "Feature",
  "properties": {
    "iso:country":"DE",
    "sg:address":"Dorfstr. 27",
    "sg:city":"Waltersdorf",
    "sg:phone":"+49 35454/362",
    "sg:postcode":"15926",
    "sg:province":"Brandenburg",
    "wof:name":"Johannes Herrmann",
    "wof:placetype":"venue"
},
  "geometry": {"coordinates":[14.652795,50.874313],"type":"Point"}
}