{
  "type": "Feature",
  "properties": {
    "iso:country":"DE",
    "sg:address":"Kirchenbleeck",
    "sg:city":"Bad Bramstedt",
    "sg:phone":"+49 4192/3001",
    "sg:postcode":"24576",
    "sg:province":"Schleswig-Holstein",
    "wof:name":"Neue-apotheke Am Kirchenbleeck",
    "wof:placetype":"venue"
},
  "geometry": {"coordinates":[9.881919,53.919388],"type":"Point"}
}