{
  "type": "Feature",
  "properties": {
    "iso:country":"DE",
    "sg:address":"Hauptstr. 1 a",
    "sg:city":"Deuna",
    "sg:postcode":"37355",
    "sg:province":"Th\u00fcringen",
    "wof:name":"Gmbh Rinderproduktion",
    "wof:placetype":"venue"
},
  "geometry": {"coordinates":[10.4680862427,51.3521499634],"type":"Point"}
}