{
  "type": "Feature",
  "properties": {
    "iso:country":"DE",
    "sg:address":"Rosenstr. 2",
    "sg:city":"Prien",
    "sg:phone":"+49 8051/2348",
    "sg:postcode":"83209",
    "sg:province":"Bayern",
    "wof:name":"Andreas Standl",
    "wof:placetype":"venue"
},
  "geometry": {"coordinates":[12.34606,47.859703],"type":"Point"}
}