{
  "type": "Feature",
  "properties": {
    "iso:country":"DE",
    "sg:address":"Mainberger Str. 18a",
    "sg:city":"Schweinfurt",
    "sg:phone":"+49 9721/299367",
    "sg:postcode":"97422",
    "sg:province":"Bayern",
    "wof:name":"Hans Schmid",
    "wof:placetype":"venue"
},
  "geometry": {"coordinates":[10.244022,50.048409],"type":"Point"}
}