{
  "type": "Feature",
  "properties": {
    "iso:country":"DE",
    "sg:address":"Steinweg 29::",
    "sg:city":"Bruehl",
    "sg:href":"http://api.simplegeo.com/1.0/features/SG_3fcOdCiODFseZRyl1d31Ab_50.828026_6.902296@1306268793.json",
    "sg:phone":"+49 4922/3270720",
    "sg:postcode":"50321",
    "sg:province":"Nordrhein-Westfalen",
    "wof:name":"Volksbank Bruehl Eingetragenegenossenschaft Zu Bruehl",
    "wof:placetype":"venue"
},
  "geometry": {"coordinates":[6.902296,50.828026],"type":"Point"}
}