{"geometry":{"type":"Point","coordinates":[6.902296,50.828026]},"type":"Feature","id":102560753,"bbox":[6.902296,50.828026,6.902296,50.828026],"properties":{"sg:province":"Nordrhein-Westfalen","geom:longitude":6.902296,"wof:breaches":[],"sg:href":"http://api.simplegeo.com/1.0/features/SG_3fcOdCiODFseZRyl1d31Ab_50.828026_6.902296@1306268793.json","sg:owner":"simplegeo","sg:postcode":"50321","geom:latitude":50.828026,"sg:classifiers":[],"sg:address":"Steinweg 29::","sg:phone":"+49 4922/3270720","wof:hierarchy":[{"venue_id":102560753,"region_id":85682513,"country_id":85633111,"locality_id":101811067,"county_id":102063709,"neighbourhood_id":85796051}],"geom:area":0.000000,"sg:city":"Bruehl","wof:lastmodified":1438093350,"iso:country":"DE","wof:geomhash":"752bcc89242c36803aa46e9b1f19dd74","wof:name":"Volksbank Bruehl Eingetragenegenossenschaft Zu Bruehl","wof:belongsto":[85682513,85633111,101811067,102063709,85796051],"src:geom":"simplegeo","wof:placetype":"venue","wof:supersedes":[],"wof:id":102560753,"wof:superseded_by":[],"wof:concordances":{"sg:id":"SG_3fcOdCiODFseZRyl1d31Ab_50.828026_6.902296@1306268793"},"wof:parent_id":85796051}}