{
  "type": "Feature",
  "properties": {
    "iso:country":"DE",
    "sg:address":"Mecklenburger Str. 30",
    "sg:city":"Wismar",
    "sg:phone":"+49 3841/282990",
    "sg:postcode":"23966",
    "sg:province":"Mecklenburg-Vorpommern",
    "wof:name":"Konrad Franikowski",
    "wof:placetype":"venue"
},
  "geometry": {"coordinates":[11.4658565521,53.8897972107],"type":"Point"}
}