{
  "type": "Feature",
  "properties": {
    "iso:country":"DE",
    "sg:address":"Stuberstr. 11",
    "sg:city":"M\u00fcnchen",
    "sg:postcode":"80638",
    "sg:province":"Bayern",
    "wof:name":"Ullrich Verm\u00f6gens- Verwaltungs Gmbh",
    "wof:placetype":"venue"
},
  "geometry": {"coordinates":[11.5156745911,48.1637268066],"type":"Point"}
}