{
  "type": "Feature",
  "properties": {
    "iso:country":"DE",
    "sg:address":"Siebenhitzer Str. 8",
    "sg:city":"Neustadt",
    "sg:postcode":"08223",
    "sg:province":"Sachsen",
    "wof:name":"S. Christmann",
    "wof:placetype":"venue"
},
  "geometry": {"coordinates":[12.3373975754,50.4699287415],"type":"Point"}
}