{
  "type": "Feature",
  "properties": {
    "iso:country":"DE",
    "sg:address":"Im H\u00e4gle 6",
    "sg:city":"Ehrenkirchen",
    "sg:phone":"+49 7633/2022",
    "sg:postcode":"79238",
    "sg:province":"Baden-W\u00fcrttemberg",
    "wof:name":"M\u00f6bel-schau-norsingen Gmbh & Co. M\u00f6belvertriebs Kg",
    "wof:placetype":"venue"
},
  "geometry": {"coordinates":[7.7222599983,47.9357528687],"type":"Point"}
}