{
  "type": "Feature",
  "properties": {
    "iso:country":"DE",
    "sg:address":"Geiststr. 36",
    "sg:city":"Halle",
    "sg:phone":"+49 345/30310",
    "sg:postcode":"06108",
    "sg:province":"Sachsen-Anhalt",
    "wof:name":"K. Eckardt",
    "wof:placetype":"venue"
},
  "geometry": {"coordinates":[11.9660491943,51.4908103943],"type":"Point"}
}