{
  "type": "Feature",
  "properties": {
    "iso:country":"DE",
    "sg:address":"Meller Str. 200 a",
    "sg:city":"Osnabr\u00fcck",
    "sg:phone":"+49 541/572653",
    "sg:postcode":"49082",
    "sg:province":"Niedersachsen",
    "wof:name":"Wiho-apotheke",
    "wof:placetype":"venue"
},
  "geometry": {"coordinates":[8.070731,52.258446],"type":"Point"}
}