{
  "type": "Feature",
  "properties": {
    "iso:country":"DE",
    "sg:address":"Stocksdorf 24",
    "sg:city":"Ehrenburg",
    "sg:phone":"+49 4243/3971",
    "sg:postcode":"27248",
    "sg:province":"Niedersachsen",
    "wof:name":"F. Sander",
    "wof:placetype":"venue"
},
  "geometry": {"coordinates":[8.704535,52.747913],"type":"Point"}
}