{
  "type": "Feature",
  "properties": {
    "iso:country":"DE",
    "sg:address":"Marktstr. 22",
    "sg:city":"Geseke",
    "sg:phone":"+49 2942/4551",
    "sg:postcode":"59590",
    "sg:province":"Nordrhein-Westfalen",
    "wof:name":"E. Rickert",
    "wof:placetype":"venue"
},
  "geometry": {"coordinates":[8.5090150833,51.6416816711],"type":"Point"}
}