{
  "type": "Feature",
  "properties": {
    "iso:country":"DE",
    "sg:address":"Kurf\u00fcrstenstr. 102",
    "sg:city":"Wuppertal",
    "sg:phone":"+49 202/466130",
    "sg:postcode":"42369",
    "sg:province":"Nordrhein-Westfalen",
    "wof:name":"Friedhelm Wiesenborn",
    "wof:placetype":"venue"
},
  "geometry": {"coordinates":[7.1969561577,51.2344665527],"type":"Point"}
}