{
  "type": "Feature",
  "properties": {
    "iso:country":"DE",
    "sg:address":"Schmachtenhagener Str. 1a",
    "sg:city":"Dabendorf",
    "sg:phone":"+49 3377/300699",
    "sg:postcode":"15806",
    "sg:province":"Brandenburg",
    "wof:name":"Qualitaet In Der Pflege Und Betreuung",
    "wof:placetype":"venue"
},
  "geometry": {"coordinates":[13.418132,52.248375],"type":"Point"}
}