{
  "type": "Feature",
  "properties": {
    "iso:country":"DE",
    "sg:address":"Uferstr. 19",
    "sg:city":"Hamburg",
    "sg:phone":"+49 40/292156",
    "sg:postcode":"22081",
    "sg:province":"Hamburg",
    "wof:name":"G\u00fcnter Henzler",
    "wof:placetype":"venue"
},
  "geometry": {"coordinates":[10.042132,53.571918],"type":"Point"}
}