{
  "type": "Feature",
  "properties": {
    "iso:country":"DE",
    "sg:address":"Am Wiesenbach 7",
    "sg:city":"Oberkirch",
    "sg:phone":"+49 7805/5016",
    "sg:postcode":"77704",
    "sg:province":"Baden-W\u00fcrttemberg",
    "wof:name":"Fischer Transport Gmbh",
    "wof:placetype":"venue"
},
  "geometry": {"coordinates":[8.0216522217,48.5429191589],"type":"Point"}
}