{
  "type": "Feature",
  "properties": {
    "iso:country":"DE",
    "sg:address":"Glogauer Str. 32",
    "sg:city":"N\u00fcrnberg",
    "sg:phone":"+49 911/808502",
    "sg:postcode":"90473",
    "sg:province":"Bayern",
    "wof:name":"Deutsche Woolworth Gmbh & Co. Ohg",
    "wof:placetype":"venue"
},
  "geometry": {"coordinates":[11.134354,49.404114],"type":"Point"}
}