{
  "type": "Feature",
  "properties": {
    "iso:country":"DE",
    "sg:address":"Rudolf-Dietz-Str. 30",
    "sg:city":"Taunusstein",
    "sg:phone":"+49 6128/742758",
    "sg:postcode":"65232",
    "sg:province":"Hessen",
    "wof:name":"Adolf Kirch Inh. Alfred Wiesenberger",
    "wof:placetype":"venue"
},
  "geometry": {"coordinates":[8.1433563232,50.1378364563],"type":"Point"}
}