{
  "type": "Feature",
  "properties": {
    "iso:country":"DE",
    "sg:address":"Pankstr. 50",
    "sg:city":"Berlin",
    "sg:phone":"+49 30/4653052",
    "sg:postcode":"13357",
    "sg:province":"Berlin",
    "wof:name":"Thail\u00e4ndisches Restaurant Viengthai",
    "wof:placetype":"venue"
},
  "geometry": {"coordinates":[13.3807735443,52.5516281128],"type":"Point"}
}