{
  "type": "Feature",
  "properties": {
    "iso:country":"DE",
    "sg:address":"Taubengasse 101",
    "sg:city":"Troisdorf",
    "sg:phone":"+49 2241/76668",
    "sg:postcode":"53840",
    "sg:province":"Nordrhein-Westfalen",
    "wof:name":"D. Danielzick Immobilienmakler",
    "wof:placetype":"venue"
},
  "geometry": {"coordinates":[7.1787219048,50.8196563721],"type":"Point"}
}