{
  "type": "Feature",
  "properties": {
    "iso:country":"DE",
    "sg:address":"Josef-Neuberger-Str. 14",
    "sg:city":"D\u00fcsseldorf",
    "sg:phone":"+49 211/9233221",
    "sg:postcode":"40625",
    "sg:province":"Nordrhein-Westfalen",
    "wof:name":"Ingensiep & Partner Gmbh",
    "wof:placetype":"venue"
},
  "geometry": {"coordinates":[6.8445711136,51.2337913513],"type":"Point"}
}