{
  "type": "Feature",
  "properties": {
    "iso:country":"DE",
    "sg:address":"Theodor-Heuss-Str. 5",
    "sg:city":"Konstanz",
    "sg:phone":"+49 7531/65822",
    "sg:postcode":"78467",
    "sg:province":"Baden-W\u00fcrttemberg",
    "wof:name":"Shakes-bier",
    "wof:placetype":"venue"
},
  "geometry": {"coordinates":[9.1807041168,47.668712616],"type":"Point"}
}