{
  "type": "Feature",
  "properties": {
    "iso:country":"DE",
    "sg:address":"Karl-Marx-Str. 13",
    "sg:city":"Langendorf",
    "sg:postcode":"06667",
    "sg:province":"Sachsen-Anhalt",
    "wof:name":"B. Landgraf",
    "wof:placetype":"venue"
},
  "geometry": {"coordinates":[11.9620923996,51.1791381836],"type":"Point"}
}