{
  "type": "Feature",
  "properties": {
    "iso:country":"DE",
    "sg:address":"Carl-Schurz-Str. 2",
    "sg:city":"Br\u00fchl",
    "sg:phone":"+49 2232/49515",
    "sg:postcode":"50321",
    "sg:province":"Nordrhein-Westfalen",
    "wof:name":"Stolpner",
    "wof:placetype":"venue"
},
  "geometry": {"coordinates":[6.901671,50.828285],"type":"Point"}
}