{
  "type": "Feature",
  "properties": {
    "iso:country":"DE",
    "sg:address":"Ruppertshainer Str. 9",
    "sg:city":"Kelkheim",
    "sg:phone":"+49 6195/99510",
    "sg:postcode":"65779",
    "sg:province":"Hessen",
    "wof:name":"Kreta",
    "wof:placetype":"venue"
},
  "geometry": {"coordinates":[8.4205694199,50.1551246643],"type":"Point"}
}