{
  "type": "Feature",
  "properties": {
    "iso:country":"DE",
    "sg:address":"Hauptstr. 54",
    "sg:city":"Badenheim",
    "sg:phone":"+49 6701/7295",
    "sg:postcode":"55576",
    "sg:province":"Rheinland-Pfalz",
    "wof:name":"Heinrich W\u00f6rth",
    "wof:placetype":"venue"
},
  "geometry": {"coordinates":[7.965968132,49.8443946838],"type":"Point"}
}