{
  "type": "Feature",
  "properties": {
    "iso:country":"DE",
    "sg:address":"Am Exerzierplatz 6",
    "sg:city":"Mannheim",
    "sg:postcode":"68167",
    "sg:province":"Baden-W\u00fcrttemberg",
    "wof:name":"Servicor Vermittlungs- Und Verwaltungsgesellschaft F\u00fcr",
    "wof:placetype":"venue"
},
  "geometry": {"coordinates":[8.495765686,49.5034446716],"type":"Point"}
}