{
  "type": "Feature",
  "properties": {
    "iso:country":"DE",
    "sg:address":"Hauptstr. 51",
    "sg:city":"Pegnitz",
    "sg:phone":"+49 9241/2426",
    "sg:postcode":"91257",
    "sg:province":"Bayern",
    "wof:name":"Ludwig Koukal",
    "wof:placetype":"venue"
},
  "geometry": {"coordinates":[11.539861,49.756561],"type":"Point"}
}