{
  "type": "Feature",
  "properties": {
    "iso:country":"DE",
    "sg:address":"Glockengie\u00dferstr. 91",
    "sg:city":"L\u00fcbeck",
    "sg:phone":"+49 451/76990",
    "sg:postcode":"23552",
    "sg:province":"Schleswig-Holstein",
    "wof:name":"Charlie Rivels Sohn Restaurant-museum",
    "wof:placetype":"venue"
},
  "geometry": {"coordinates":[10.6940040588,53.8690757751],"type":"Point"}
}