{
  "type": "Feature",
  "properties": {
    "iso:country":"DE",
    "sg:address":"Allmendstr. 28",
    "sg:city":"Furtwangen",
    "sg:phone":"+49 7723/5597",
    "sg:postcode":"78120",
    "sg:province":"Baden-W\u00fcrttemberg",
    "wof:name":"L\u00f6ffler Bau Gmbh",
    "wof:placetype":"venue"
},
  "geometry": {"coordinates":[8.213665,48.049648],"type":"Point"}
}