{
  "type": "Feature",
  "properties": {
    "iso:country":"DE",
    "sg:address":"Lanzstr. 8",
    "sg:city":"Wiesbaden",
    "sg:phone":"+49 611/527501",
    "sg:postcode":"65193",
    "sg:province":"Hessen",
    "wof:name":"U. Gresser",
    "wof:placetype":"venue"
},
  "geometry": {"coordinates":[8.2357740402,50.0949020386],"type":"Point"}
}