{
  "type": "Feature",
  "properties": {
    "iso:country":"DE",
    "sg:address":"In der Laach 62 A",
    "sg:city":"Koblenz",
    "sg:postcode":"56072",
    "sg:province":"Rheinland-Pfalz",
    "wof:name":"Kgs Kraftfahrzeug-garant-gmbh",
    "wof:placetype":"venue"
},
  "geometry": {"coordinates":[7.5499191284,50.3503799438],"type":"Point"}
}