{
  "type": "Feature",
  "properties": {
    "iso:country":"DE",
    "sg:address":"Zebertstr. 39",
    "sg:city":"Aalen",
    "sg:phone":"+49 7361/33155",
    "sg:postcode":"73431",
    "sg:province":"Baden-W\u00fcrttemberg",
    "wof:name":"Ev. Pfarramt Iv Martinskirche",
    "wof:placetype":"venue"
},
  "geometry": {"coordinates":[10.1113348007,48.8339653015],"type":"Point"}
}