{
  "type": "Feature",
  "properties": {
    "iso:country":"DE",
    "sg:address":"Regensburger Str. 6",
    "sg:city":"Pettendorf",
    "sg:phone":"+49 9404/4809",
    "sg:postcode":"93186",
    "sg:province":"Bayern",
    "wof:name":"W. Forstner",
    "wof:placetype":"venue"
},
  "geometry": {"coordinates":[12.022053,49.048107],"type":"Point"}
}