{
  "type": "Feature",
  "properties": {
    "iso:country":"DE",
    "sg:address":"Kreyenfeldstr. 4",
    "sg:city":"Bochum",
    "sg:phone":"+49 234/261689",
    "sg:postcode":"44894",
    "sg:province":"Nordrhein-Westfalen",
    "wof:name":"Heinrich Wronowski",
    "wof:placetype":"venue"
},
  "geometry": {"coordinates":[7.306942,51.485928],"type":"Point"}
}