{
  "type": "Feature",
  "properties": {
    "iso:country":"DE",
    "sg:address":"St.-Michael-Str. 13",
    "sg:city":"Bad Krozingen",
    "sg:phone":"+49 7633/3567",
    "sg:postcode":"79189",
    "sg:province":"Baden-W\u00fcrttemberg",
    "wof:name":"Kath. Pfarramt St. Michel",
    "wof:placetype":"venue"
},
  "geometry": {"coordinates":[7.6635298729,47.903629303],"type":"Point"}
}