{
  "type": "Feature",
  "properties": {
    "iso:country":"DE",
    "sg:address":"Marchstr. 5",
    "sg:city":"Freiburg",
    "sg:phone":"+49 761/287431",
    "sg:postcode":"79106",
    "sg:province":"Baden-W\u00fcrttemberg",
    "wof:name":"Kami Software Beratung Gmbh",
    "wof:placetype":"venue"
},
  "geometry": {"coordinates":[7.8435730934,48.0015258789],"type":"Point"}
}