{
  "type": "Feature",
  "properties": {
    "iso:country":"DE",
    "sg:address":"G\u00e4rtnerstr. 47",
    "sg:city":"Kiel",
    "sg:postcode":"24113",
    "sg:province":"Schleswig-Holstein",
    "wof:name":"Possel & Koselowske Holding Gmbh",
    "wof:placetype":"venue"
},
  "geometry": {"coordinates":[10.099138,54.306061],"type":"Point"}
}