{
  "type": "Feature",
  "properties": {
    "iso:country":"DE",
    "sg:address":"Zeppelinstr. 1",
    "sg:city":"Kavelstorf",
    "sg:phone":"+49 38208/6990",
    "sg:postcode":"18196",
    "sg:province":"Mecklenburg-Vorpommern",
    "wof:name":"H & F Industry Data Gmbh",
    "wof:placetype":"venue"
},
  "geometry": {"coordinates":[12.1962213516,54.0164985657],"type":"Point"}
}