{
  "type": "Feature",
  "properties": {
    "iso:country":"DE",
    "sg:address":"Staudenrain 2",
    "sg:city":"Dunningen",
    "sg:phone":"+49 7403/441",
    "sg:postcode":"78655",
    "sg:province":"Baden-W\u00fcrttemberg",
    "wof:name":"Fred Glunk",
    "wof:placetype":"venue"
},
  "geometry": {"coordinates":[8.524901,48.209923],"type":"Point"}
}