{
  "type": "Feature",
  "properties": {
    "iso:country":"DE",
    "sg:address":"Agnes-Bluhm-Str. 2",
    "sg:city":"Wendorf",
    "sg:postcode":"18442",
    "sg:province":"Mecklenburg-Vorpommern",
    "wof:name":"Kies Gmbh",
    "wof:placetype":"venue"
},
  "geometry": {"coordinates":[12.9795246124,54.2245483398],"type":"Point"}
}