{
  "type": "Feature",
  "properties": {
    "iso:country":"DE",
    "sg:address":"Alte Str. 2",
    "sg:city":"Wuppertal",
    "sg:phone":"+49 202/660701",
    "sg:postcode":"42277",
    "sg:province":"Nordrhein-Westfalen",
    "wof:name":"Ede Und Graf Rechtsanw\u00e4lte",
    "wof:placetype":"venue"
},
  "geometry": {"coordinates":[7.2172999382,51.2738418579],"type":"Point"}
}