{
  "type": "Feature",
  "properties": {
    "iso:country":"DE",
    "sg:address":"Oberweilerstr. 9",
    "sg:city":"Wangen",
    "sg:phone":"+49 7506/445",
    "sg:postcode":"88239",
    "sg:province":"Baden-W\u00fcrttemberg",
    "wof:name":"H. Fakler Ingenieur",
    "wof:placetype":"venue"
},
  "geometry": {"coordinates":[9.825094223,47.7504310608],"type":"Point"}
}