{
  "type": "Feature",
  "properties": {
    "iso:country":"DE",
    "sg:address":"Am Planetarium 8",
    "sg:city":"Jena",
    "sg:phone":"+49 3641/45490",
    "sg:postcode":"07743",
    "sg:province":"Th\u00fcringen",
    "wof:name":"Victoria Versicherung Ag",
    "wof:placetype":"venue"
},
  "geometry": {"coordinates":[11.587644577,50.9324607849],"type":"Point"}
}