{
  "type": "Feature",
  "properties": {
    "iso:country":"DE",
    "sg:address":"Elswigstr. 66",
    "sg:city":"L\u00fcbeck",
    "sg:phone":"+49 451/599641",
    "sg:postcode":"23562",
    "sg:province":"Schleswig-Holstein",
    "wof:name":"Alten- Und Pflegeheim",
    "wof:placetype":"venue"
},
  "geometry": {"coordinates":[10.703652,53.845543],"type":"Point"}
}