{
  "type": "Feature",
  "properties": {
    "iso:country":"DE",
    "sg:address":"Gerolsteiner Str. 11",
    "sg:city":"Oberstadtfeld",
    "sg:phone":"+49 6596/671",
    "sg:postcode":"54570",
    "sg:province":"Rheinland-Pfalz",
    "wof:name":"Handwerkerverein Arnold Thull",
    "wof:placetype":"venue"
},
  "geometry": {"coordinates":[6.5986409187,50.1507148743],"type":"Point"}
}