{
  "type": "Feature",
  "properties": {
    "iso:country":"DE",
    "sg:address":"Marktstr. 7 -11",
    "sg:city":"Calw",
    "sg:postcode":"75365",
    "sg:province":"Baden-W\u00fcrttemberg",
    "wof:name":"Calwer Stadtsanierungs- Gmbh",
    "wof:placetype":"venue"
},
  "geometry": {"coordinates":[8.74021,48.714054],"type":"Point"}
}