{
  "type": "Feature",
  "properties": {
    "iso:country":"DE",
    "sg:address":"Auf der B\u00f6ck 7",
    "sg:city":"D\u00fcsseldorf",
    "sg:phone":"+49 211/304969",
    "sg:postcode":"40221",
    "sg:province":"Nordrhein-Westfalen",
    "wof:name":"Heribert Michels",
    "wof:placetype":"venue"
},
  "geometry": {"coordinates":[6.736626,51.200542],"type":"Point"}
}