{
  "type": "Feature",
  "properties": {
    "iso:country":"DE",
    "sg:address":"Kloppenburgstr. 8",
    "sg:city":"B\u00fcnde",
    "sg:phone":"+49 5223/60140",
    "sg:postcode":"32257",
    "sg:province":"Nordrhein-Westfalen",
    "wof:name":"Wohnen Heute M\u00f6belhandels Gmbh",
    "wof:placetype":"venue"
},
  "geometry": {"coordinates":[8.557071,52.19965],"type":"Point"}
}