{
  "type": "Feature",
  "properties": {
    "iso:country":"DE",
    "sg:address":"Palatiumstr. 14",
    "sg:city":"Seligenstadt",
    "sg:phone":"+49 6182/28638",
    "sg:postcode":"63500",
    "sg:province":"Hessen",
    "wof:name":"Irina Esser",
    "wof:placetype":"venue"
},
  "geometry": {"coordinates":[8.976896,50.044132],"type":"Point"}
}