{
  "type": "Feature",
  "properties": {
    "iso:country":"DE",
    "sg:address":"An der H\u00f6ssen 4",
    "sg:city":"Westerstede",
    "sg:postcode":"26655",
    "sg:province":"Niedersachsen",
    "wof:name":"Martin Neumann Gmbh",
    "wof:placetype":"venue"
},
  "geometry": {"coordinates":[7.916838,53.253365],"type":"Point"}
}