{
  "type": "Feature",
  "properties": {
    "iso:country":"DE",
    "sg:address":"Oberstr. 18",
    "sg:city":"Mettmann",
    "sg:phone":"+49 2104/27337",
    "sg:postcode":"40822",
    "sg:province":"Nordrhein-Westfalen",
    "wof:name":"Franz Bergmann",
    "wof:placetype":"venue"
},
  "geometry": {"coordinates":[6.9767827988,51.2523956299],"type":"Point"}
}