{
  "type": "Feature",
  "properties": {
    "iso:country":"DE",
    "sg:address":"Binge 2",
    "sg:city":"Wetter",
    "sg:phone":"+49 6423/6634",
    "sg:postcode":"35083",
    "sg:province":"Hessen",
    "wof:name":"Hotel-restaur. Kegelsporthaus",
    "wof:placetype":"venue"
},
  "geometry": {"coordinates":[8.7213077545,50.9046440125],"type":"Point"}
}