{
  "type": "Feature",
  "properties": {
    "iso:country":"DE",
    "sg:address":"Tiergartenstr. 1",
    "sg:city":"Zeitz",
    "sg:postcode":"06712",
    "sg:province":"Sachsen-Anhalt",
    "wof:name":"Evangelisch-freikirchliche Gemeind",
    "wof:placetype":"venue"
},
  "geometry": {"coordinates":[12.1378202438,51.0559463501],"type":"Point"}
}