{
  "type": "Feature",
  "properties": {
    "iso:country":"DE",
    "sg:address":"Kastanienstr. 28",
    "sg:city":"Lalendorf",
    "sg:postcode":"18279",
    "sg:province":"Mecklenburg-Vorpommern",
    "wof:name":"Dieter Lietz Beteiligungs-gmbh",
    "wof:placetype":"venue"
},
  "geometry": {"coordinates":[12.388988,53.751793],"type":"Point"}
}