{
  "type": "Feature",
  "properties": {
    "iso:country":"DE",
    "sg:address":"Westring 61",
    "sg:city":"Herne",
    "sg:phone":"+49 2323/949197",
    "sg:postcode":"44623",
    "sg:province":"Nordrhein-Westfalen",
    "wof:name":"Frank-michael Kr\u00fcger",
    "wof:placetype":"venue"
},
  "geometry": {"coordinates":[7.2192912102,51.533416748],"type":"Point"}
}