{
  "type": "Feature",
  "properties": {
    "iso:country":"DE",
    "sg:address":"Bahnhofstr. 28",
    "sg:city":"Drentwede",
    "sg:phone":"+49 4246/93110",
    "sg:postcode":"49406",
    "sg:province":"Niedersachsen",
    "wof:name":"Georg Strahmann Beteiligungs Gmbh",
    "wof:placetype":"venue"
},
  "geometry": {"coordinates":[8.573213,52.743797],"type":"Point"}
}