{
  "type": "Feature",
  "properties": {
    "iso:country":"DE",
    "sg:address":"Marconiweg 5",
    "sg:city":"G\u00fctersloh",
    "sg:postcode":"33334",
    "sg:province":"Nordrhein-Westfalen",
    "wof:name":"Die Internetseite F\u00fcr Jedermann.",
    "wof:placetype":"venue"
},
  "geometry": {"coordinates":[8.426461,51.888947],"type":"Point"}
}