{
  "type": "Feature",
  "properties": {
    "iso:country":"DE",
    "sg:address":"Stiftstr. 21",
    "sg:city":"Minden",
    "sg:phone":"+49 571/946120",
    "sg:postcode":"32427",
    "sg:province":"Nordrhein-Westfalen",
    "wof:name":"Kellermeier & Salge Gmbh",
    "wof:placetype":"venue"
},
  "geometry": {"coordinates":[8.9128093719,52.2943344116],"type":"Point"}
}