{
  "type": "Feature",
  "properties": {
    "iso:country":"DE",
    "sg:address":"Kirrlacher Str. 11",
    "sg:city":"Wagh\u00e4usel",
    "sg:phone":"+49 7254/8733",
    "sg:postcode":"68753",
    "sg:province":"Baden-W\u00fcrttemberg",
    "wof:name":"Erwin Notheisen",
    "wof:placetype":"venue"
},
  "geometry": {"coordinates":[8.513948,49.252037],"type":"Point"}
}