{
  "type": "Feature",
  "properties": {
    "iso:country":"DE",
    "sg:address":"Im Winkel 5",
    "sg:city":"Anderbeck",
    "sg:phone":"+49 39422/60314",
    "sg:postcode":"38836",
    "sg:province":"Sachsen-Anhalt",
    "wof:name":"Elvira Diedrich",
    "wof:placetype":"venue"
},
  "geometry": {"coordinates":[10.9332618713,51.9835243225],"type":"Point"}
}