{
  "type": "Feature",
  "properties": {
    "iso:country":"DE",
    "sg:address":"Professor-Schr\u00f6der-Str. 74",
    "sg:city":"Geilenkirchen",
    "sg:phone":"+49 2453/2168",
    "sg:postcode":"52511",
    "sg:province":"Nordrhein-Westfalen",
    "wof:name":"Willi Coenen",
    "wof:placetype":"venue"
},
  "geometry": {"coordinates":[6.18687,50.979675],"type":"Point"}
}