{
  "type": "Feature",
  "properties": {
    "iso:country":"DE",
    "sg:address":"Hauptstr. 97",
    "sg:city":"Badeborn",
    "sg:phone":"+49 39483/8618",
    "sg:postcode":"06493",
    "sg:province":"Sachsen-Anhalt",
    "wof:name":"Goldenes Hufeisen",
    "wof:placetype":"venue"
},
  "geometry": {"coordinates":[11.243314743,51.7648391724],"type":"Point"}
}