{
  "type": "Feature",
  "properties": {
    "iso:country":"DE",
    "sg:address":"Gartenhausweg 18",
    "sg:city":"Widdern",
    "sg:phone":"+49 6298/95610",
    "sg:postcode":"74259",
    "sg:province":"Baden-W\u00fcrttemberg",
    "wof:name":"Tasa Elektrotechnik Gmbh",
    "wof:placetype":"venue"
},
  "geometry": {"coordinates":[9.419516,49.320919],"type":"Point"}
}