{
  "type": "Feature",
  "properties": {
    "iso:country":"DE",
    "sg:address":"Hanauer Landstr. 334",
    "sg:city":"Frankfurt",
    "sg:phone":"+49 69/9421560",
    "sg:postcode":"60314",
    "sg:province":"Hessen",
    "wof:name":"Europcar",
    "wof:placetype":"venue"
},
  "geometry": {"coordinates":[8.742485,50.123158],"type":"Point"}
}