{
  "type": "Feature",
  "properties": {
    "iso:country":"DE",
    "sg:address":"Lintforter Str. 66",
    "sg:city":"Moers",
    "sg:phone":"+49 2841/73462",
    "sg:postcode":"47445",
    "sg:province":"Nordrhein-Westfalen",
    "wof:name":"Novo-grill",
    "wof:placetype":"venue"
},
  "geometry": {"coordinates":[6.5971870422,51.4900627136],"type":"Point"}
}