{
  "type": "Feature",
  "properties": {
    "iso:country":"DE",
    "sg:address":"Rheinstr. 57",
    "sg:city":"Hagen",
    "sg:phone":"+49 2331/81819",
    "sg:postcode":"58097",
    "sg:province":"Nordrhein-Westfalen",
    "wof:name":"Margarete Kl\u00fcttermann",
    "wof:placetype":"venue"
},
  "geometry": {"coordinates":[7.4716501236,51.3681602478],"type":"Point"}
}