{
  "type": "Feature",
  "properties": {
    "iso:country":"DE",
    "sg:address":"Wessenbergstr. 11",
    "sg:city":"Konstanz",
    "sg:phone":"+49 7531/25288",
    "sg:postcode":"78462",
    "sg:province":"Baden-W\u00fcrttemberg",
    "wof:name":"Mohren-apotheke E. K.",
    "wof:placetype":"venue"
},
  "geometry": {"coordinates":[9.173871,47.661324],"type":"Point"}
}