{
  "type": "Feature",
  "properties": {
    "iso:country":"DE",
    "sg:address":"Lauterbacher Str 5",
    "sg:city":"Steinbach",
    "sg:phone":"+49 34345/56020",
    "sg:postcode":"04651",
    "sg:province":"Sachsen",
    "wof:name":"Norbert Morgenstern Gmbh",
    "wof:placetype":"venue"
},
  "geometry": {"coordinates":[12.5955343246,51.1686897278],"type":"Point"}
}