{
  "type": "Feature",
  "properties": {
    "iso:country":"DE",
    "sg:address":"Maximilianstr. 20-22",
    "sg:city":"Regensburg",
    "sg:phone":"+49 941/55737",
    "sg:postcode":"93047",
    "sg:province":"Bayern",
    "wof:name":"Benetton-ventura- Textilhandels Kg",
    "wof:placetype":"venue"
},
  "geometry": {"coordinates":[12.100092,49.016006],"type":"Point"}
}