{
  "type": "Feature",
  "properties": {
    "iso:country":"DE",
    "sg:address":"Dorfstr. 51",
    "sg:city":"Spantekow",
    "sg:phone":"+49 39727/20391",
    "sg:postcode":"17392",
    "sg:province":"Mecklenburg-Vorpommern",
    "wof:name":"E. Bohse",
    "wof:placetype":"venue"
},
  "geometry": {"coordinates":[13.521009,53.778744],"type":"Point"}
}