{
  "type": "Feature",
  "properties": {
    "iso:country":"DE",
    "sg:address":"Hauptstr. 11",
    "sg:city":"Nesselwang",
    "sg:phone":"+49 8361/425",
    "sg:postcode":"87484",
    "sg:province":"Bayern",
    "wof:name":"Bach Und Klaver Masseure",
    "wof:placetype":"venue"
},
  "geometry": {"coordinates":[10.500557,47.621471],"type":"Point"}
}