{
  "type": "Feature",
  "properties": {
    "iso:country":"DE",
    "sg:address":"Karl-Zucker-Str. 12",
    "sg:city":"Erlangen",
    "sg:phone":"+49 9131/14300",
    "sg:postcode":"91052",
    "sg:province":"Bayern",
    "wof:name":"Hssk M\u00f6bel-discount Gmbh",
    "wof:placetype":"venue"
},
  "geometry": {"coordinates":[11.005608,49.582829],"type":"Point"}
}