{
  "type": "Feature",
  "properties": {
    "iso:country":"DE",
    "sg:address":"Buchenweg 14",
    "sg:city":"Irxleben",
    "sg:postcode":"39167",
    "sg:province":"Sachsen-Anhalt",
    "wof:name":"Malerfachbetrieb Colour Gmbh",
    "wof:placetype":"venue"
},
  "geometry": {"coordinates":[11.489325,52.161167],"type":"Point"}
}