{
  "type": "Feature",
  "properties": {
    "iso:country":"DE",
    "sg:address":"Bernhard-Nocht-Str. 69",
    "sg:city":"Hamburg",
    "sg:phone":"+49 40/311140",
    "sg:postcode":"20359",
    "sg:province":"Hamburg",
    "wof:name":"Rvg Raboisen Verwaltungsgesellschaft Mbh",
    "wof:placetype":"venue"
},
  "geometry": {"coordinates":[9.961353302,53.5470848083],"type":"Point"}
}