{
  "type": "Feature",
  "properties": {
    "iso:country":"DE",
    "sg:address":"Gardolostr. 10",
    "sg:city":"Neufahrn",
    "sg:phone":"+49 8165/4781",
    "sg:postcode":"85375",
    "sg:province":"Bayern",
    "wof:name":"Gvh Verwaltungs-gmbh",
    "wof:placetype":"venue"
},
  "geometry": {"coordinates":[11.6724176407,48.3096046448],"type":"Point"}
}