{
  "type": "Feature",
  "properties": {
    "iso:country":"DE",
    "sg:address":"Br\u00fcckstr. 47",
    "sg:city":"Bochum",
    "sg:phone":"+49 234/15901",
    "sg:postcode":"44787",
    "sg:province":"Nordrhein-Westfalen",
    "wof:name":"China-restaurant",
    "wof:placetype":"venue"
},
  "geometry": {"coordinates":[7.215690136,51.4846305847],"type":"Point"}
}