{
  "type": "Feature",
  "properties": {
    "iso:country":"DE",
    "sg:address":"Holtenauer Str. 336",
    "sg:city":"Kiel",
    "sg:phone":"+49 431/335686",
    "sg:postcode":"24106",
    "sg:province":"Schleswig-Holstein",
    "wof:name":"Restorante Pizzeria Milano",
    "wof:placetype":"venue"
},
  "geometry": {"coordinates":[10.1308288574,54.3562088013],"type":"Point"}
}