{
  "type": "Feature",
  "properties": {
    "iso:country":"DE",
    "sg:address":"Wiesstr. 27",
    "sg:city":"Kempten",
    "sg:phone":"+49 831/17942",
    "sg:postcode":"87435",
    "sg:province":"Bayern",
    "wof:name":"Restaurant Pfefferm\u00fchle",
    "wof:placetype":"venue"
},
  "geometry": {"coordinates":[10.3160820007,47.7170906067],"type":"Point"}
}