{
  "type": "Feature",
  "properties": {
    "iso:country":"DE",
    "sg:address":"Steinstr. 1a",
    "sg:city":"Niederwerth",
    "sg:phone":"+49 261/65759",
    "sg:postcode":"56179",
    "sg:province":"Rheinland-Pfalz",
    "wof:name":"Kirmesgesellschaft 1981 Wolfgang Stein",
    "wof:placetype":"venue"
},
  "geometry": {"coordinates":[7.6107702255,50.395942688],"type":"Point"}
}