{
  "type": "Feature",
  "properties": {
    "iso:country":"DE",
    "sg:address":"Waldweg 2",
    "sg:city":"Gr\u00f6ditz",
    "sg:phone":"+49 35263/6490",
    "sg:postcode":"01609",
    "sg:province":"Sachsen",
    "wof:name":"Schuler Hoch- Und Tiefbau Betonfertigteile",
    "wof:placetype":"venue"
},
  "geometry": {"coordinates":[13.4398212433,51.412399292],"type":"Point"}
}