{
  "type": "Feature",
  "properties": {
    "iso:country":"DE",
    "sg:address":"Hofacker 85",
    "sg:city":"Kleve",
    "sg:phone":"+49 2821/30458",
    "sg:postcode":"47533",
    "sg:province":"Nordrhein-Westfalen",
    "wof:name":"Karl Cleusters",
    "wof:placetype":"venue"
},
  "geometry": {"coordinates":[6.063164,51.847336],"type":"Point"}
}