{
  "type": "Feature",
  "properties": {
    "iso:country":"DE",
    "sg:address":"Sch\u00f6naustr. 24",
    "sg:city":"D\u00fcsseldorf",
    "sg:phone":"+49 211/292940",
    "sg:postcode":"40625",
    "sg:province":"Nordrhein-Westfalen",
    "wof:name":"Zur Post",
    "wof:placetype":"venue"
},
  "geometry": {"coordinates":[6.8593621254,51.2347602844],"type":"Point"}
}