{
  "type": "Feature",
  "properties": {
    "iso:country":"DE",
    "sg:address":"Siedlungsstr. 8",
    "sg:city":"Burgwindheim",
    "sg:phone":"+49 9551/1033",
    "sg:postcode":"96154",
    "sg:province":"Bayern",
    "wof:name":"J. Dorn",
    "wof:placetype":"venue"
},
  "geometry": {"coordinates":[10.5960350037,49.8296089172],"type":"Point"}
}