{
  "type": "Feature",
  "properties": {
    "iso:country":"DE",
    "sg:address":"Konstantinstr. 94",
    "sg:city":"M\u00f6nchengladbach",
    "sg:phone":"+49 2166/83788",
    "sg:postcode":"41238",
    "sg:province":"Nordrhein-Westfalen",
    "wof:name":"Bix Und Eicker-bix Rechtsanw\u00e4lte",
    "wof:placetype":"venue"
},
  "geometry": {"coordinates":[6.4836239815,51.1567840576],"type":"Point"}
}