{
  "type": "Feature",
  "properties": {
    "iso:country":"DE",
    "sg:address":"Im Drachenacker 4",
    "sg:city":"Offenburg",
    "sg:phone":"+49 781/9682979",
    "sg:postcode":"77656",
    "sg:province":"Baden-W\u00fcrttemberg",
    "wof:name":"Freizeit Kuhn",
    "wof:placetype":"venue"
},
  "geometry": {"coordinates":[7.9279031754,48.4804496765],"type":"Point"}
}