{
  "type": "Feature",
  "properties": {
    "iso:country":"DE",
    "sg:address":"Max-Planck-Str. 17-19",
    "sg:city":"Geldern",
    "sg:phone":"+49 7171/925240",
    "sg:postcode":"47608",
    "sg:province":"Nordrhein-Westfalen",
    "wof:name":"Mpk Kemmer Gmbh",
    "wof:placetype":"venue"
},
  "geometry": {"coordinates":[9.748471,48.794937],"type":"Point"}
}