{
  "type": "Feature",
  "properties": {
    "iso:country":"DE",
    "sg:address":"L\u00f6berwallgraben 13",
    "sg:city":"Erfurt",
    "sg:phone":"+49 361/3461133",
    "sg:postcode":"99096",
    "sg:province":"Th\u00fcringen",
    "wof:name":"Bks Wohnbau Gmbh",
    "wof:placetype":"venue"
},
  "geometry": {"coordinates":[11.0329198837,50.9694213867],"type":"Point"}
}