{
  "type": "Feature",
  "properties": {
    "iso:country":"DE",
    "sg:address":"B\u00fchler Seite 22 b",
    "sg:city":"B\u00fchl",
    "sg:postcode":"77815",
    "sg:province":"Baden-W\u00fcrttemberg",
    "wof:name":"Vario-bauplan Gmbh",
    "wof:placetype":"venue"
},
  "geometry": {"coordinates":[8.135925293,48.6953582764],"type":"Point"}
}