{
  "type": "Feature",
  "properties": {
    "iso:country":"DE",
    "sg:address":"Fl\u00f6\u00dferstr. 2",
    "sg:city":"Ludwigshafen",
    "sg:phone":"+49 621/571996",
    "sg:postcode":"67065",
    "sg:province":"Rheinland-Pfalz",
    "wof:name":"Ursel Kuhnert",
    "wof:placetype":"venue"
},
  "geometry": {"coordinates":[8.4308843613,49.4595527649],"type":"Point"}
}