{
  "type": "Feature",
  "properties": {
    "iso:country":"DE",
    "sg:address":"Tschaikowskistr. 33",
    "sg:city":"Leipzig",
    "sg:phone":"+49 341/269970",
    "sg:postcode":"04105",
    "sg:province":"Sachsen",
    "wof:name":"Gustav Epple Hausverwaltungs Gmbh",
    "wof:placetype":"venue"
},
  "geometry": {"coordinates":[12.3598537445,51.346282959],"type":"Point"}
}