{
  "type": "Feature",
  "properties": {
    "iso:country":"DE",
    "sg:address":"Alte Bergstr. 11",
    "sg:city":"Lo\u00dfburg",
    "sg:phone":"+49 7446/682",
    "sg:postcode":"72290",
    "sg:province":"Baden-W\u00fcrttemberg",
    "wof:name":"G. Eisenbeis",
    "wof:placetype":"venue"
},
  "geometry": {"coordinates":[8.4752950668,48.4300079346],"type":"Point"}
}