{
  "type": "Feature",
  "properties": {
    "iso:country":"DE",
    "sg:address":"Braunsberg 94",
    "sg:city":"Bergisch Gladbach",
    "sg:phone":"+49 2207/6252",
    "sg:postcode":"51429",
    "sg:province":"Nordrhein-Westfalen",
    "wof:name":"W. Paffhausen",
    "wof:placetype":"venue"
},
  "geometry": {"coordinates":[7.2052760124,50.9933013916],"type":"Point"}
}