{
  "type": "Feature",
  "properties": {
    "iso:country":"DE",
    "sg:address":"Wernerwerkstr. 5",
    "sg:city":"Regensburg",
    "sg:phone":"+49 941/299250",
    "sg:postcode":"93049",
    "sg:province":"Bayern",
    "wof:name":"Aquila Inkasso Gmbh",
    "wof:placetype":"venue"
},
  "geometry": {"coordinates":[12.05671978,49.0211639404],"type":"Point"}
}