{
  "type": "Feature",
  "properties": {
    "iso:country":"DE",
    "sg:address":"Am Ostende 2",
    "sg:city":"Ostseebad Nienhagen",
    "sg:phone":"+49 38203/80330",
    "sg:postcode":"18211",
    "sg:province":"Mecklenburg-Vorpommern",
    "wof:name":"Lukas-projektbetreuung Gmbh",
    "wof:placetype":"venue"
},
  "geometry": {"coordinates":[11.9776296616,54.1110305786],"type":"Point"}
}