{
  "type": "Feature",
  "properties": {
    "iso:country":"DE",
    "sg:address":"Josephstr. 47",
    "sg:city":"Bochum",
    "sg:phone":"+49 234/511444",
    "sg:postcode":"44791",
    "sg:province":"Nordrhein-Westfalen",
    "wof:name":"Frank Wiederhold",
    "wof:placetype":"venue"
},
  "geometry": {"coordinates":[7.2109398842,51.490436554],"type":"Point"}
}