{
  "type": "Feature",
  "properties": {
    "iso:country":"DE",
    "sg:address":"Br\u00fchlstr. 54",
    "sg:city":"Lichtenstein",
    "sg:phone":"+49 7129/5166",
    "sg:postcode":"72805",
    "sg:province":"Baden-W\u00fcrttemberg",
    "wof:name":"Werner Gekeler",
    "wof:placetype":"venue"
},
  "geometry": {"coordinates":[9.2687854767,48.4229927063],"type":"Point"}
}