{
  "type": "Feature",
  "properties": {
    "iso:country":"DE",
    "sg:address":"Am Wall 14",
    "sg:city":"Pinneberg",
    "sg:phone":"+49 4101/64638",
    "sg:postcode":"25421",
    "sg:province":"Schleswig-Holstein",
    "wof:name":"H. Armbrecht",
    "wof:placetype":"venue"
},
  "geometry": {"coordinates":[9.783763,53.622078],"type":"Point"}
}