{
  "type": "Feature",
  "properties": {
    "iso:country":"DE",
    "sg:address":"Auf der H\u00fcls 17",
    "sg:city":"Aachen",
    "sg:phone":"+49 241/164826",
    "sg:postcode":"52080",
    "sg:province":"Nordrhein-Westfalen",
    "wof:name":"Schneider-fittings",
    "wof:placetype":"venue"
},
  "geometry": {"coordinates":[6.125628,50.793861],"type":"Point"}
}