{
  "type": "Feature",
  "properties": {
    "iso:country":"DE",
    "sg:address":"Parkstr. 5",
    "sg:city":"Sickte",
    "sg:phone":"+49 5305/1240",
    "sg:postcode":"38173",
    "sg:province":"Niedersachsen",
    "wof:name":"Hvi Bauprojektierung Gmbh",
    "wof:placetype":"venue"
},
  "geometry": {"coordinates":[10.636385,52.212059],"type":"Point"}
}