{
  "type": "Feature",
  "properties": {
    "iso:country":"DE",
    "sg:address":"Wilhelm-Busch-Weg 1",
    "sg:city":"Flein",
    "sg:phone":"+49 7131/578041",
    "sg:postcode":"74223",
    "sg:province":"Baden-W\u00fcrttemberg",
    "wof:name":"Rainer Wilhelm Ingenieur",
    "wof:placetype":"venue"
},
  "geometry": {"coordinates":[9.203912735,49.1033401489],"type":"Point"}
}