{
  "type": "Feature",
  "properties": {
    "iso:country":"DE",
    "sg:address":"H\u00f6flingerweg 8",
    "sg:city":"Mintraching",
    "sg:phone":"+49 9406/2130",
    "sg:postcode":"93098",
    "sg:province":"Bayern",
    "wof:name":"Karl Kellner",
    "wof:placetype":"venue"
},
  "geometry": {"coordinates":[12.2898836136,48.9240379333],"type":"Point"}
}