{
  "type": "Feature",
  "properties": {
    "iso:country":"DE",
    "sg:address":"J\u00fcrgensgaarder Str. 11 b",
    "sg:city":"Flensburg",
    "sg:phone":"+49 461/29581",
    "sg:postcode":"24943",
    "sg:province":"Schleswig-Holstein",
    "wof:name":"J. Stolch Bildhauerei",
    "wof:placetype":"venue"
},
  "geometry": {"coordinates":[9.443504,54.789398],"type":"Point"}
}