{
  "type": "Feature",
  "properties": {
    "iso:country":"DE",
    "sg:address":"Am Kirchsteig 3",
    "sg:city":"Salzhemmendorf",
    "sg:phone":"+49 5186/252",
    "sg:postcode":"31020",
    "sg:province":"Niedersachsen",
    "wof:name":"E. Preuss",
    "wof:placetype":"venue"
},
  "geometry": {"coordinates":[9.62953,52.024403],"type":"Point"}
}