{
  "type": "Feature",
  "properties": {
    "iso:country":"DE",
    "sg:address":"Oststr. 18 a",
    "sg:city":"Oberstdorf",
    "sg:phone":"+49 8322/3329",
    "sg:postcode":"87561",
    "sg:province":"Bayern",
    "wof:name":"Leder-eberhardt Gmbh",
    "wof:placetype":"venue"
},
  "geometry": {"coordinates":[10.281356,47.405979],"type":"Point"}
}