{
  "type": "Feature",
  "properties": {
    "iso:country":"DE",
    "sg:address":"Salzgitterstr 18",
    "sg:city":"Baunatal",
    "sg:phone":"+49 561/9489280",
    "sg:postcode":"34225",
    "sg:province":"Hessen",
    "wof:name":"Visa Stromerzeuger Gmbh",
    "wof:placetype":"venue"
},
  "geometry": {"coordinates":[9.450154,51.245781],"type":"Point"}
}