{
  "type": "Feature",
  "properties": {
    "iso:country":"DE",
    "sg:address":"Frauenschuhweg 11",
    "sg:city":"Sonthofen",
    "sg:phone":"+49 8321/68953",
    "sg:postcode":"87527",
    "sg:province":"Bayern",
    "wof:name":"Free Wear Sport- & Freizeit Markenmode E. K.",
    "wof:placetype":"venue"
},
  "geometry": {"coordinates":[10.269446373,47.5153808594],"type":"Point"}
}