{
  "type": "Feature",
  "properties": {
    "iso:country":"DE",
    "sg:address":"Konrad-Zuse-Str. 5",
    "sg:city":"Jena",
    "sg:phone":"+49 3641/653375",
    "sg:postcode":"07739",
    "sg:province":"Th\u00fcringen",
    "wof:name":"Pe-kontor, Personalentwicklung Und -management",
    "wof:placetype":"venue"
},
  "geometry": {"coordinates":[11.597661,50.884907],"type":"Point"}
}