{
  "type": "Feature",
  "properties": {
    "iso:country":"DE",
    "sg:address":"Ickhorster Weg 2",
    "sg:city":"Wedemark",
    "sg:phone":"+49 5130/7222",
    "sg:postcode":"30900",
    "sg:province":"Niedersachsen",
    "wof:name":"Egon Meyer",
    "wof:placetype":"venue"
},
  "geometry": {"coordinates":[9.7283840179,52.5069503784],"type":"Point"}
}