{
  "type": "Feature",
  "properties": {
    "iso:country":"DE",
    "sg:address":"Ludwig-Krohne-Str. 5",
    "sg:city":"Duisburg",
    "sg:phone":"+49 203/332481",
    "sg:postcode":"47058",
    "sg:province":"Nordrhein-Westfalen",
    "wof:name":"Heinrich Musly Inh. Rolf Gra\u00dfmann",
    "wof:placetype":"venue"
},
  "geometry": {"coordinates":[6.7952880859,51.4459075928],"type":"Point"}
}