{
  "type": "Feature",
  "properties": {
    "iso:country":"DE",
    "sg:address":"Edenkobener Str. 46",
    "sg:city":"St Martin",
    "sg:phone":"+49 6323/4516",
    "sg:postcode":"67487",
    "sg:province":"Rheinland-Pfalz",
    "wof:name":"Fritz R\u00f6ssler Weinanbau",
    "wof:placetype":"venue"
},
  "geometry": {"coordinates":[8.1064453125,49.2976303101],"type":"Point"}
}