{
  "type": "Feature",
  "properties": {
    "iso:country":"DE",
    "sg:address":"Riekbornweg 2",
    "sg:city":"Hamburg",
    "sg:phone":"+49 40/559990",
    "sg:postcode":"22457",
    "sg:province":"Hamburg",
    "wof:name":"O.i.l. Grundst\u00fccks- Gesellschaft Mbh",
    "wof:placetype":"venue"
},
  "geometry": {"coordinates":[9.9157075882,53.6344833374],"type":"Point"}
}