{
  "type": "Feature",
  "properties": {
    "iso:country":"DE",
    "sg:address":"Jahrmarktstr. 12",
    "sg:city":"L\u00fcbeck",
    "sg:phone":"+49 4502/4794",
    "sg:postcode":"23570",
    "sg:province":"Schleswig-Holstein",
    "wof:name":"Peter Stuerholdt",
    "wof:placetype":"venue"
},
  "geometry": {"coordinates":[10.8643770218,53.9567604065],"type":"Point"}
}