{
  "type": "Feature",
  "properties": {
    "iso:country":"DE",
    "sg:address":"Gartenstr. 17",
    "sg:city":"Gehrden",
    "sg:phone":"+49 5108/5044",
    "sg:postcode":"30989",
    "sg:province":"Niedersachsen",
    "wof:name":"A. Puchinger",
    "wof:placetype":"venue"
},
  "geometry": {"coordinates":[9.6018457413,52.3150978088],"type":"Point"}
}