{
  "type": "Feature",
  "properties": {
    "iso:country":"DE",
    "sg:address":"Ha\u00dffurter Str. 10",
    "sg:city":"N\u00fcrnberg",
    "sg:phone":"+49 911/302613",
    "sg:postcode":"90427",
    "sg:province":"Bayern",
    "wof:name":"E. Englbauer",
    "wof:placetype":"venue"
},
  "geometry": {"coordinates":[11.0104923248,49.5243186951],"type":"Point"}
}