{
  "type": "Feature",
  "properties": {
    "iso:country":"DE",
    "sg:address":"Traubenstr. 29",
    "sg:city":"Stuttgart",
    "sg:phone":"+49 711/2229606",
    "sg:postcode":"70176",
    "sg:province":"Baden-W\u00fcrttemberg",
    "wof:name":"Ego Immobilien Gmbh",
    "wof:placetype":"venue"
},
  "geometry": {"coordinates":[9.1615667343,48.7823867798],"type":"Point"}
}