{
  "type": "Feature",
  "properties": {
    "iso:country":"DE",
    "sg:address":"Moosm\u00fchle 4",
    "sg:city":"Wildpoldsried",
    "sg:phone":"+49 8304/745",
    "sg:postcode":"87499",
    "sg:province":"Bayern",
    "wof:name":"Dieter Br\u00fcggemann Architekt",
    "wof:placetype":"venue"
},
  "geometry": {"coordinates":[10.398159,47.785877],"type":"Point"}
}