{
  "type": "Feature",
  "properties": {
    "iso:country":"DE",
    "sg:address":"Daisbachtalstr. 39",
    "sg:city":"Waibstadt",
    "sg:phone":"+49 7261/3785",
    "sg:postcode":"74915",
    "sg:province":"Baden-W\u00fcrttemberg",
    "wof:name":"R. Czemmel",
    "wof:placetype":"venue"
},
  "geometry": {"coordinates":[8.87864,49.300549],"type":"Point"}
}