{
  "type": "Feature",
  "properties": {
    "iso:country":"DE",
    "sg:address":"Klemensstrasse 9",
    "sg:city":"Viersen",
    "sg:phone":"+49 2162",
    "sg:postcode":"41749",
    "sg:province":"Nordrhein-Westfalen",
    "wof:name":"Tanzsportverein Viersen E.v.",
    "wof:placetype":"venue"
},
  "geometry": {"coordinates":[6.369795,51.286942],"type":"Point"}
}