{
  "type": "Feature",
  "properties": {
    "iso:country":"DE",
    "sg:address":"Am Stadtpark 6 H",
    "sg:city":"Erfurt",
    "sg:phone":"+49 361/3465566",
    "sg:postcode":"99096",
    "sg:province":"Th\u00fcringen",
    "wof:name":"Rolf R. Rebhan Rechtsanwalt",
    "wof:placetype":"venue"
},
  "geometry": {"coordinates":[11.0366201401,50.9551086426],"type":"Point"}
}