{
  "type": "Feature",
  "properties": {
    "iso:country":"DE",
    "sg:address":"Wiesengrund 10",
    "sg:city":"Isenb\u00fcttel",
    "sg:phone":"+49 5374/4987",
    "sg:postcode":"38550",
    "sg:province":"Niedersachsen",
    "wof:name":"Dieter Dragendorf Ingenieur",
    "wof:placetype":"venue"
},
  "geometry": {"coordinates":[10.5845136642,52.429309845],"type":"Point"}
}