{
  "type": "Feature",
  "properties": {
    "iso:country":"DE",
    "sg:address":"Maximilianstr. 29",
    "sg:city":"Bayreuth",
    "sg:phone":"+49 921/66016",
    "sg:postcode":"95444",
    "sg:province":"Bayern",
    "wof:name":"Dr. Johannes Driendl Rechtsanwalt",
    "wof:placetype":"venue"
},
  "geometry": {"coordinates":[11.575504303,49.9440040588],"type":"Point"}
}