{
  "type": "Feature",
  "properties": {
    "iso:country":"DE",
    "sg:address":"An der Schule 4",
    "sg:city":"Seesen",
    "sg:phone":"+49 5381/75249",
    "sg:postcode":"38723",
    "sg:province":"Niedersachsen",
    "wof:name":"Stadtb\u00fccherei",
    "wof:placetype":"venue"
},
  "geometry": {"coordinates":[10.167579,51.890415],"type":"Point"}
}