{
  "type": "Feature",
  "properties": {
    "iso:country":"DE",
    "sg:address":"Schulstr.",
    "sg:city":"Reichshof",
    "sg:phone":"+49 2297/235",
    "sg:postcode":"51580",
    "sg:province":"Nordrhein-Westfalen",
    "wof:name":"Manfred Hochhard",
    "wof:placetype":"venue"
},
  "geometry": {"coordinates":[7.6461548805,50.9902267456],"type":"Point"}
}