{
  "type": "Feature",
  "properties": {
    "iso:country":"DE",
    "sg:address":"M\u00fcnchener Str. 2",
    "sg:city":"Mering",
    "sg:phone":"+49 8233/9526",
    "sg:postcode":"86415",
    "sg:province":"Bayern",
    "wof:name":"Hans Reich",
    "wof:placetype":"venue"
},
  "geometry": {"coordinates":[10.9864282608,48.2668800354],"type":"Point"}
}