{
  "type": "Feature",
  "properties": {
    "iso:country":"DE",
    "sg:address":"Clara-Zetkin-Str. 34",
    "sg:city":"Ro\u00dflau",
    "sg:postcode":"06862",
    "sg:province":"Sachsen-Anhalt",
    "wof:name":"Aws Rohrbau- Kunststofftechnik",
    "wof:placetype":"venue"
},
  "geometry": {"coordinates":[12.229177,51.883633],"type":"Point"}
}