{
  "type": "Feature",
  "properties": {
    "iso:country":"DE",
    "sg:address":"Engerser Str. 43",
    "sg:city":"Neuwied",
    "sg:phone":"+49 2631/25564",
    "sg:postcode":"56564",
    "sg:province":"Rheinland-Pfalz",
    "wof:name":"Maria K\u00fcsters Inh. Margot L\u00f6ber",
    "wof:placetype":"venue"
},
  "geometry": {"coordinates":[7.458642,50.427208],"type":"Point"}
}