{
  "type": "Feature",
  "properties": {
    "iso:country":"DE",
    "sg:address":"Hospitalstr. 3",
    "sg:city":"G\u00f6rlitz",
    "sg:phone":"+49 3581/409170",
    "sg:postcode":"02826",
    "sg:province":"Sachsen",
    "wof:name":"Nesako Netzwerk- Satelitentechnik-kommuni-",
    "wof:placetype":"venue"
},
  "geometry": {"coordinates":[14.9837093353,51.1495742798],"type":"Point"}
}