{
  "type": "Feature",
  "properties": {
    "iso:country":"DE",
    "sg:address":"Bruderrain",
    "sg:city":"Stuttgart",
    "sg:phone":"+49 711/605701",
    "sg:postcode":"70597",
    "sg:province":"Baden-W\u00fcrttemberg",
    "wof:name":"Copytec Martha Mast",
    "wof:placetype":"venue"
},
  "geometry": {"coordinates":[9.1479492188,48.7490768433],"type":"Point"}
}