{
  "type": "Feature",
  "properties": {
    "iso:country":"DE",
    "sg:address":"Gabel-Schaffen-Str. 2",
    "sg:city":"Schmallenberg",
    "sg:phone":"+49 2972/1461",
    "sg:postcode":"57392",
    "sg:province":"Nordrhein-Westfalen",
    "wof:name":"Annette Schauerte",
    "wof:placetype":"venue"
},
  "geometry": {"coordinates":[8.3297662735,51.1433486938],"type":"Point"}
}