{
  "type": "Feature",
  "properties": {
    "iso:country":"DE",
    "sg:address":"H\u00f6xterstr. 9",
    "sg:city":"Hamburg",
    "sg:phone":"+49 40/448464",
    "sg:postcode":"22529",
    "sg:province":"Hamburg",
    "wof:name":"Krw Kirk Rumland",
    "wof:placetype":"venue"
},
  "geometry": {"coordinates":[9.9671220779,53.5968742371],"type":"Point"}
}