{
  "type": "Feature",
  "properties": {
    "iso:country":"DE",
    "sg:address":"Bahnhofstr. 14",
    "sg:city":"Kleinheubach",
    "sg:phone":"+49 9371/97100",
    "sg:postcode":"63924",
    "sg:province":"Bayern",
    "wof:name":"Stahl Holzbearbeitung Gmbh",
    "wof:placetype":"venue"
},
  "geometry": {"coordinates":[9.2070808411,49.7223167419],"type":"Point"}
}