{
  "type": "Feature",
  "properties": {
    "iso:country":"DE",
    "sg:address":"Kirchheimer Str. 18",
    "sg:city":"Schlierbach",
    "sg:phone":"+49 7021/44255",
    "sg:postcode":"73278",
    "sg:province":"Baden-W\u00fcrttemberg",
    "wof:name":"Hermann Maurer",
    "wof:placetype":"venue"
},
  "geometry": {"coordinates":[9.512437,48.672222],"type":"Point"}
}