{
  "type": "Feature",
  "properties": {
    "iso:country":"DE",
    "sg:address":"Gutbrodstr. 12",
    "sg:city":"Stuttgart",
    "sg:phone":"+49 711/631588",
    "sg:postcode":"70197",
    "sg:province":"Baden-W\u00fcrttemberg",
    "wof:name":"Willy K\u00f6rner",
    "wof:placetype":"venue"
},
  "geometry": {"coordinates":[9.1541090012,48.7747192383],"type":"Point"}
}