{
  "type": "Feature",
  "properties": {
    "iso:country":"DE",
    "sg:address":"Triftstr. 92",
    "sg:city":"Kleve",
    "sg:phone":"+49 2821/28055",
    "sg:postcode":"47533",
    "sg:province":"Nordrhein-Westfalen",
    "wof:name":"H. N\u00f6llen",
    "wof:placetype":"venue"
},
  "geometry": {"coordinates":[6.1320981979,51.7763137817],"type":"Point"}
}