{
  "type": "Feature",
  "properties": {
    "iso:country":"DE",
    "sg:address":"Uml\u00e4nderwiek Links 76",
    "sg:city":"Papenburg",
    "sg:phone":"+49 4961/75121",
    "sg:postcode":"26871",
    "sg:province":"Niedersachsen",
    "wof:name":"Bernhard Rehbock",
    "wof:placetype":"venue"
},
  "geometry": {"coordinates":[7.460561,53.07193],"type":"Point"}
}