{
  "type": "Feature",
  "properties": {
    "iso:country":"DE",
    "sg:address":"Hauptstr. 93",
    "sg:city":"Waibstadt",
    "sg:phone":"+49 7263/2363",
    "sg:postcode":"74915",
    "sg:province":"Baden-W\u00fcrttemberg",
    "wof:name":"Nikolaus Schwab",
    "wof:placetype":"venue"
},
  "geometry": {"coordinates":[8.9186029434,49.2929954529],"type":"Point"}
}