{
  "type": "Feature",
  "properties": {
    "iso:country":"DE",
    "sg:address":"Winzenhofen",
    "sg:city":"Sch\u00f6ntal",
    "sg:phone":"+49 6294/205",
    "sg:postcode":"74214",
    "sg:province":"Baden-W\u00fcrttemberg",
    "wof:name":"Gasthaus Lamm",
    "wof:placetype":"venue"
},
  "geometry": {"coordinates":[9.5613527298,49.3416824341],"type":"Point"}
}