{
  "type": "Feature",
  "properties": {
    "iso:country":"DE",
    "sg:address":"Beckerhookstr. 71",
    "sg:city":"Gronau",
    "sg:phone":"+49 2562/1717",
    "sg:postcode":"48599",
    "sg:province":"Nordrhein-Westfalen",
    "wof:name":"Wilhelm Meyer",
    "wof:placetype":"venue"
},
  "geometry": {"coordinates":[6.9997758865,52.2094421387],"type":"Point"}
}