{
  "type": "Feature",
  "properties": {
    "iso:country":"DE",
    "sg:address":"F\u00e4hlmannweg 43a",
    "sg:city":"Berlin",
    "sg:postcode":"14089",
    "sg:province":"Berlin",
    "wof:name":"Kasachstan Trading Gmbh",
    "wof:placetype":"venue"
},
  "geometry": {"coordinates":[13.127513,52.457615],"type":"Point"}
}