{
  "type": "Feature",
  "properties": {
    "iso:country":"DE",
    "sg:address":"Neutorstr. 16",
    "sg:city":"Schweinfurt",
    "sg:phone":"+49 9721/18101",
    "sg:postcode":"97421",
    "sg:province":"Bayern",
    "wof:name":"Peter St\u00f6th Rechtsanwalt",
    "wof:placetype":"venue"
},
  "geometry": {"coordinates":[10.2271528244,50.0482788086],"type":"Point"}
}