{
  "type": "Feature",
  "properties": {
    "iso:country":"DE",
    "sg:address":"Zingster Str. 6",
    "sg:city":"Berlin",
    "sg:phone":"+49 30/9285025",
    "sg:postcode":"13051",
    "sg:province":"Berlin",
    "wof:name":"Der Heimwerker",
    "wof:placetype":"venue"
},
  "geometry": {"coordinates":[13.4981660843,52.5734024048],"type":"Point"}
}