{
  "type": "Feature",
  "properties": {
    "iso:country":"DE",
    "sg:address":"Mimosenweg 20 A",
    "sg:city":"Berlin",
    "sg:phone":"+49 30/6613750",
    "sg:postcode":"12357",
    "sg:province":"Berlin",
    "wof:name":"Isdn, T-online, Mobilfunk Handy - Telekommunikation -",
    "wof:placetype":"venue"
},
  "geometry": {"coordinates":[13.507264,52.424934],"type":"Point"}
}