{
  "type": "Feature",
  "properties": {
    "iso:country":"DE",
    "sg:city":"D\u00fcsseldorf / Ratingen",
    "sg:postcode":"40880",
    "sg:province":"Nordrhein-Westfalen",
    "wof:name":"Ilo Businesscenters Deutschland",
    "wof:placetype":"venue"
},
  "geometry": {"coordinates":[6.848095,51.29715],"type":"Point"}
}