{
  "type": "Feature",
  "properties": {
    "iso:country":"DE",
    "sg:address":"Pohlweg 42c",
    "sg:city":"Paderborn",
    "sg:phone":"+49 5251/63910",
    "sg:postcode":"33098",
    "sg:province":"Nordrhein-Westfalen",
    "wof:name":"Leonhard Heiny",
    "wof:placetype":"venue"
},
  "geometry": {"coordinates":[8.766357,51.710846],"type":"Point"}
}