{
  "type": "Feature",
  "properties": {
    "iso:country":"DE",
    "sg:address":"Schulstr. 15",
    "sg:city":"Rodalben",
    "sg:phone":"+49 6331/2550",
    "sg:postcode":"66976",
    "sg:province":"Rheinland-Pfalz",
    "wof:name":"Abel & Co. Gmbh",
    "wof:placetype":"venue"
},
  "geometry": {"coordinates":[7.632193,49.241596],"type":"Point"}
}