{
  "type": "Feature",
  "properties": {
    "iso:country":"DE",
    "sg:address":"Alte Dorfstr. 7",
    "sg:city":"Husum",
    "sg:phone":"+49 5027/608",
    "sg:postcode":"31632",
    "sg:province":"Niedersachsen",
    "wof:name":"Hermann Kruse",
    "wof:placetype":"venue"
},
  "geometry": {"coordinates":[9.2909927368,52.5633621216],"type":"Point"}
}