{
  "type": "Feature",
  "properties": {
    "iso:country":"DE",
    "sg:address":"Friedhofstr. 5",
    "sg:city":"Mandelbachtal",
    "sg:postcode":"66399",
    "sg:province":"Saarland",
    "wof:name":"Peter Walle",
    "wof:placetype":"venue"
},
  "geometry": {"coordinates":[7.1412849426,49.2296257019],"type":"Point"}
}