{
  "type": "Feature",
  "properties": {
    "iso:country":"DE",
    "sg:address":"Hammersbacher Str. 2",
    "sg:city":"Wechmar",
    "sg:phone":"+49 36256/21673",
    "sg:postcode":"99869",
    "sg:province":"Th\u00fcringen",
    "wof:name":"Bauzentrum K. Gerlach",
    "wof:placetype":"venue"
},
  "geometry": {"coordinates":[10.7639951706,50.8945884705],"type":"Point"}
}