{
  "type": "Feature",
  "properties": {
    "iso:country":"DE",
    "sg:address":"R\u00fcbezahlweg 14",
    "sg:city":"Wuppertal",
    "sg:phone":"+49 202/726881",
    "sg:postcode":"42111",
    "sg:province":"Nordrhein-Westfalen",
    "wof:name":"Manfred Br\u00fcninghaus Rechtsanwalt",
    "wof:placetype":"venue"
},
  "geometry": {"coordinates":[7.1241750717,51.2832298279],"type":"Point"}
}