{
  "type": "Feature",
  "properties": {
    "iso:country":"DE",
    "sg:address":"Klosterstr. 38",
    "sg:city":"Frechen",
    "sg:phone":"+49 2234/31188",
    "sg:postcode":"50226",
    "sg:province":"Nordrhein-Westfalen",
    "wof:name":"Heinz Klein",
    "wof:placetype":"venue"
},
  "geometry": {"coordinates":[6.7492918968,50.9107017517],"type":"Point"}
}