{
  "type": "Feature",
  "properties": {
    "iso:country":"DE",
    "sg:address":"Lange Reihe 113",
    "sg:city":"Hamburg",
    "sg:phone":"+49 40/2803108",
    "sg:postcode":"20099",
    "sg:province":"Hamburg",
    "wof:name":"Wahnsinn Comics Str\u00fcfing Wahl & Co.",
    "wof:placetype":"venue"
},
  "geometry": {"coordinates":[10.0144128799,53.5601158142],"type":"Point"}
}