{
  "type": "Feature",
  "properties": {
    "iso:country":"DE",
    "sg:address":"Werkstr. 305",
    "sg:city":"Schwerin",
    "sg:phone":"+49 385/615737",
    "sg:postcode":"19061",
    "sg:province":"Mecklenburg-Vorpommern",
    "wof:name":"B & K Stahlbau Gmbh",
    "wof:placetype":"venue"
},
  "geometry": {"coordinates":[11.386038,53.573997],"type":"Point"}
}