{
  "type": "Feature",
  "properties": {
    "iso:country":"DE",
    "sg:address":"Friedrichstr. 9",
    "sg:city":"Bernkastel-Kues",
    "sg:postcode":"54470",
    "sg:province":"Rheinland-Pfalz",
    "wof:name":"Bernkasteler Burghof Gmbh",
    "wof:placetype":"venue"
},
  "geometry": {"coordinates":[7.0698251724,49.9143104553],"type":"Point"}
}