{
  "type": "Feature",
  "properties": {
    "iso:country":"DE",
    "sg:address":"Paul-Bertz-Str. 199",
    "sg:city":"Chemnitz",
    "sg:phone":"+49 371/229178",
    "sg:postcode":"09120",
    "sg:province":"Sachsen",
    "wof:name":"Ingrid Oberl\u00e4nder",
    "wof:placetype":"venue"
},
  "geometry": {"coordinates":[12.8962945938,50.801109314],"type":"Point"}
}