{
  "type": "Feature",
  "properties": {
    "iso:country":"DE",
    "sg:address":"Heinrichgasse 4",
    "sg:city":"Kempten",
    "sg:phone":"+49 831/26322",
    "sg:postcode":"87435",
    "sg:province":"Bayern",
    "wof:name":"Josef Keckeisen",
    "wof:placetype":"venue"
},
  "geometry": {"coordinates":[10.3182296753,47.7268333435],"type":"Point"}
}