{
  "type": "Feature",
  "properties": {
    "iso:country":"DE",
    "sg:address":"In der Bredde 5",
    "sg:city":"Werl",
    "sg:postcode":"59457",
    "sg:province":"Nordrhein-Westfalen",
    "wof:name":"Gebr\u00fcder K\u00f6nig Bautr\u00e4gergesellschaft Mbh",
    "wof:placetype":"venue"
},
  "geometry": {"coordinates":[7.8477139473,51.54737854],"type":"Point"}
}