{
  "type": "Feature",
  "properties": {
    "iso:country":"DE",
    "sg:address":"Hauptstr. 93",
    "sg:city":"Lindenberg",
    "sg:phone":"+49 6325/2537",
    "sg:postcode":"67473",
    "sg:province":"Rheinland-Pfalz",
    "wof:name":"Speisegastst\u00e4tte Ratskeller",
    "wof:placetype":"venue"
},
  "geometry": {"coordinates":[8.0975246429,49.382484436],"type":"Point"}
}