{
  "type": "Feature",
  "properties": {
    "iso:country":"DE",
    "sg:address":"R\u00f6merstr. 64",
    "sg:city":"R\u00fclzheim",
    "sg:phone":"+49 7272/71020",
    "sg:postcode":"76761",
    "sg:province":"Rheinland-Pfalz",
    "wof:name":"Helmut Da\u00dfer Masseur",
    "wof:placetype":"venue"
},
  "geometry": {"coordinates":[8.301883,49.157085],"type":"Point"}
}