{
  "type": "Feature",
  "properties": {
    "iso:country":"DE",
    "sg:address":"St.-Viti-Str. 26",
    "sg:city":"Uelzen",
    "sg:phone":"+49 581/6805",
    "sg:postcode":"29525",
    "sg:province":"Niedersachsen",
    "wof:name":"Lothar Liber Masseur",
    "wof:placetype":"venue"
},
  "geometry": {"coordinates":[10.557418,52.970917],"type":"Point"}
}