{
  "type": "Feature",
  "properties": {
    "iso:country":"DE",
    "sg:address":"Untere Kaiserstr. 6",
    "sg:city":"St. Ingbert",
    "sg:phone":"+49 6894/2023",
    "sg:postcode":"66386",
    "sg:province":"Saarland",
    "wof:name":"Goldener Darm Saitlinge Gmbh",
    "wof:placetype":"venue"
},
  "geometry": {"coordinates":[7.0785031319,49.259929657],"type":"Point"}
}