{
  "type": "Feature",
  "properties": {
    "iso:country":"DE",
    "sg:address":"Altheider Str. 24",
    "sg:city":"Berlin",
    "sg:postcode":"12489",
    "sg:province":"Berlin",
    "wof:name":"Dr. Med. Gisela Marzahn",
    "wof:placetype":"venue"
},
  "geometry": {"coordinates":[13.542855,52.437431],"type":"Point"}
}