{
  "type": "Feature",
  "properties": {
    "iso:country":"DE",
    "sg:address":"M\u00fcnchentor",
    "sg:city":"Loburg",
    "sg:phone":"+49 39245/2245",
    "sg:postcode":"39279",
    "sg:province":"Sachsen-Anhalt",
    "wof:name":"Biggis Gartenklause",
    "wof:placetype":"venue"
},
  "geometry": {"coordinates":[12.0693788528,52.1103172302],"type":"Point"}
}