{
  "type": "Feature",
  "properties": {
    "iso:country":"DE",
    "sg:address":"Leichtmetallstr. 13",
    "sg:city":"Haan",
    "sg:phone":"+49 2104/61565",
    "sg:postcode":"42781",
    "sg:province":"Nordrhein-Westfalen",
    "wof:name":"Pressen-salomon Apparate Und Steuerungsbau Gmbh & Co. Kg",
    "wof:placetype":"venue"
},
  "geometry": {"coordinates":[7.00705,51.216942],"type":"Point"}
}