{
  "type": "Feature",
  "properties": {
    "iso:country":"DE",
    "sg:address":"Noorstr. 20",
    "sg:city":"Eckernf\u00f6rde",
    "sg:phone":"+49 4351/6062",
    "sg:postcode":"24340",
    "sg:province":"Schleswig-Holstein",
    "wof:name":"Giese Und Partner Gbr Architekten",
    "wof:placetype":"venue"
},
  "geometry": {"coordinates":[9.827836,54.472828],"type":"Point"}
}