{
  "type": "Feature",
  "properties": {
    "iso:country":"DE",
    "sg:address":"Limesstr.",
    "sg:city":"M\u00f6nchsroth",
    "sg:phone":"+49 9853/1309",
    "sg:postcode":"91614",
    "sg:province":"Bayern",
    "wof:name":"Freibad Limes",
    "wof:placetype":"venue"
},
  "geometry": {"coordinates":[10.3636522293,49.0182342529],"type":"Point"}
}