{
  "type": "Feature",
  "properties": {
    "iso:country":"DE",
    "sg:address":"K\u00f6nigstr. 4",
    "sg:city":"Schleswig",
    "sg:phone":"+49 4621/29990",
    "sg:postcode":"24837",
    "sg:province":"Schleswig-Holstein",
    "wof:name":"Rudolf Behn Und Norbert Maa\u00df Rechtsanw\u00e4lte",
    "wof:placetype":"venue"
},
  "geometry": {"coordinates":[9.56828022,54.5151557922],"type":"Point"}
}