{
  "type": "Feature",
  "properties": {
    "iso:country":"DE",
    "sg:address":"Langenbergstr. 20",
    "sg:city":"Retzstadt",
    "sg:phone":"+49 9364/4915",
    "sg:postcode":"97282",
    "sg:province":"Bayern",
    "wof:name":"L. Und N. Medon",
    "wof:placetype":"venue"
},
  "geometry": {"coordinates":[9.869494,49.912586],"type":"Point"}
}