{
  "type": "Feature",
  "properties": {
    "iso:country":"DE",
    "sg:address":"Arndtstr. 8a",
    "sg:city":"Herzebrock-Clarholz",
    "sg:phone":"+49 5242/402152",
    "sg:postcode":"33442",
    "sg:province":"Nordrhein-Westfalen",
    "wof:name":"Modeagentur Marx Gmbh",
    "wof:placetype":"venue"
},
  "geometry": {"coordinates":[8.2365398407,51.8767204285],"type":"Point"}
}