{
  "type": "Feature",
  "properties": {
    "iso:country":"DE",
    "sg:address":"Weiden\u00e4cker 4",
    "sg:city":"Me\u00dfkirch",
    "sg:phone":"+49 7575/92180",
    "sg:postcode":"88605",
    "sg:province":"Baden-W\u00fcrttemberg",
    "wof:name":"Heizung Und Sanit\u00e4r G\u00fcnther Nabenhauer E. K.",
    "wof:placetype":"venue"
},
  "geometry": {"coordinates":[9.078824,47.992146],"type":"Point"}
}