{
  "type": "Feature",
  "properties": {
    "iso:country":"DE",
    "sg:address":"Bachstr. 13",
    "sg:city":"Oberhausen-Rheinhausen",
    "sg:phone":"+49 7254/2681",
    "sg:postcode":"68794",
    "sg:province":"Baden-W\u00fcrttemberg",
    "wof:name":"Leo Schwabenland",
    "wof:placetype":"venue"
},
  "geometry": {"coordinates":[8.490472,49.255234],"type":"Point"}
}