{
  "type": "Feature",
  "properties": {
    "iso:country":"DE",
    "sg:address":"Koppeldamm 21",
    "sg:city":"Kiebitzreihe",
    "sg:phone":"+49 4121/5515",
    "sg:postcode":"25368",
    "sg:province":"Schleswig-Holstein",
    "wof:name":"Marten Bauelemente",
    "wof:placetype":"venue"
},
  "geometry": {"coordinates":[9.612088,53.780716],"type":"Point"}
}