{
  "type": "Feature",
  "properties": {
    "iso:country":"DE",
    "sg:address":"Kolbenstr. 10",
    "sg:city":"Hagen",
    "sg:phone":"+49 2334/45774",
    "sg:postcode":"58093",
    "sg:province":"Nordrhein-Westfalen",
    "wof:name":"Kh Beteiligungs Gmbh",
    "wof:placetype":"venue"
},
  "geometry": {"coordinates":[7.54788,51.354702],"type":"Point"}
}