{
  "type": "Feature",
  "properties": {
    "iso:country":"DE",
    "sg:address":"Farmstr. 16",
    "sg:city":"M\u00f6rfelden-Walldorf",
    "sg:phone":"+49 6105/6054",
    "sg:postcode":"64546",
    "sg:province":"Hessen",
    "wof:name":"Dr. Gerhard Sauer Und W. Ringling",
    "wof:placetype":"venue"
},
  "geometry": {"coordinates":[8.5801544189,50.002155304],"type":"Point"}
}