{
  "type": "Feature",
  "properties": {
    "iso:country":"DE",
    "sg:address":"Bircksstr. 6",
    "sg:city":"Kempen",
    "sg:phone":"+49 2152/518041",
    "sg:postcode":"47906",
    "sg:province":"Nordrhein-Westfalen",
    "wof:name":"Mts Medizinischer Transport-service Gmbh",
    "wof:placetype":"venue"
},
  "geometry": {"coordinates":[6.4332652092,51.3664665222],"type":"Point"}
}