{
  "type": "Feature",
  "properties": {
    "iso:country":"DE",
    "sg:address":"Dornbusch 6",
    "sg:city":"Rheda-Wiedenbr\u00fcck",
    "sg:phone":"+49 5242/90360",
    "sg:postcode":"33378",
    "sg:province":"Nordrhein-Westfalen",
    "wof:name":"Wilfried Suessmilch",
    "wof:placetype":"venue"
},
  "geometry": {"coordinates":[8.3697986603,51.8438835144],"type":"Point"}
}