{
  "type": "Feature",
  "properties": {
    "iso:country":"DE",
    "sg:address":"Maximilianstr. 22",
    "sg:city":"M\u00fcnchen",
    "sg:phone":"+49 89/2285268",
    "sg:postcode":"80539",
    "sg:province":"Bayern",
    "wof:name":"Kenzo",
    "wof:placetype":"venue"
},
  "geometry": {"coordinates":[11.581837,48.138687],"type":"Point"}
}