{
  "type": "Feature",
  "properties": {
    "iso:country":"DE",
    "sg:address":"Willbachstr. 1",
    "sg:city":"Diez",
    "sg:phone":"+49 6432/2041",
    "sg:postcode":"65582",
    "sg:province":"Rheinland-Pfalz",
    "wof:name":"Erwin Ehrles Rechtsanwalt",
    "wof:placetype":"venue"
},
  "geometry": {"coordinates":[8.0180006027,50.3691635132],"type":"Point"}
}