{
  "type": "Feature",
  "properties": {
    "iso:country":"DE",
    "sg:address":"B\u00f6kenf\u00f6rder Str. 20",
    "sg:city":"Lippstadt",
    "sg:phone":"+49 2941/14042",
    "sg:postcode":"59557",
    "sg:province":"Nordrhein-Westfalen",
    "wof:name":"Fachbuch: Beanspruchungsermittlung Mit Dehnungsme\u00dfstreifen",
    "wof:placetype":"venue"
},
  "geometry": {"coordinates":[8.3489236832,51.6683502197],"type":"Point"}
}