{
  "type": "Feature",
  "properties": {
    "iso:country":"DE",
    "sg:address":"Alemannenstr. 10",
    "sg:city":"Solingen",
    "sg:phone":"+49 212/62129",
    "sg:postcode":"42699",
    "sg:province":"Nordrhein-Westfalen",
    "wof:name":"H. Kolfhaus",
    "wof:placetype":"venue"
},
  "geometry": {"coordinates":[7.0194611549,51.1533508301],"type":"Point"}
}