{
  "type": "Feature",
  "properties": {
    "iso:country":"DE",
    "sg:address":"Schillerplatz 6",
    "sg:city":"Gifhorn",
    "sg:phone":"+49 5371/98850",
    "sg:postcode":"38518",
    "sg:province":"Niedersachsen",
    "wof:name":"Kutzner Kg",
    "wof:placetype":"venue"
},
  "geometry": {"coordinates":[10.54422,52.48243],"type":"Point"}
}