{
  "type": "Feature",
  "properties": {
    "iso:country":"DE",
    "sg:address":"Schillerstr. 4",
    "sg:city":"L\u00f6rrach",
    "sg:phone":"+49 7621/151980",
    "sg:postcode":"79540",
    "sg:province":"Baden-W\u00fcrttemberg",
    "wof:name":"St\u00e4dtische Wohnbaugesellschaft L\u00f6rrach Mbh",
    "wof:placetype":"venue"
},
  "geometry": {"coordinates":[7.6630778313,47.6062469482],"type":"Point"}
}