{
  "type": "Feature",
  "properties": {
    "iso:country":"DE",
    "sg:address":"Lise-Meitner-Str. 12",
    "sg:city":"M\u00fcnster",
    "sg:phone":"+49 491/928290",
    "sg:postcode":"48161",
    "sg:province":"Nordrhein-Westfalen",
    "wof:name":"Sandersfeld Sicherheitstechnik Gmbh",
    "wof:placetype":"venue"
},
  "geometry": {"coordinates":[7.4543838501,53.2589607239],"type":"Point"}
}