{
  "type": "Feature",
  "properties": {
    "iso:country":"DE",
    "sg:address":"Kolonie 15",
    "sg:city":"Buschow",
    "sg:phone":"+49 3876/233",
    "sg:postcode":"14715",
    "sg:province":"Brandenburg",
    "wof:name":"Jagdmuseum",
    "wof:placetype":"venue"
},
  "geometry": {"coordinates":[12.31067,52.519508],"type":"Point"}
}