{
  "type": "Feature",
  "properties": {
    "iso:country":"DE",
    "sg:address":"Van-Leyden-Str. 26",
    "sg:city":"Ludwigshafen",
    "sg:phone":"+49 621/5296525",
    "sg:postcode":"67061",
    "sg:province":"Rheinland-Pfalz",
    "wof:name":"V. Braunstein Architekt",
    "wof:placetype":"venue"
},
  "geometry": {"coordinates":[8.447286,49.466911],"type":"Point"}
}