{
  "type": "Feature",
  "properties": {
    "iso:country":"DE",
    "sg:address":"Bundesstr. 11",
    "sg:city":"Rheinfelden",
    "sg:phone":"+49 7623/5517",
    "sg:postcode":"79618",
    "sg:province":"Baden-W\u00fcrttemberg",
    "wof:name":"Agip Deutschland Ag",
    "wof:placetype":"venue"
},
  "geometry": {"coordinates":[7.8100419044,47.5818824768],"type":"Point"}
}