{
  "type": "Feature",
  "properties": {
    "iso:country":"DE",
    "sg:address":"Wenzelstr. 22",
    "sg:city":"Altenburg",
    "sg:phone":"+49 3447/313472",
    "sg:postcode":"04600",
    "sg:province":"Th\u00fcringen",
    "wof:name":"Reiner Gmbh",
    "wof:placetype":"venue"
},
  "geometry": {"coordinates":[12.4415664673,50.9943618774],"type":"Point"}
}