{
  "type": "Feature",
  "properties": {
    "iso:country":"DE",
    "sg:address":"Hindenburgstr. 25",
    "sg:city":"Denkendorf",
    "sg:phone":"+49 711/3464832",
    "sg:postcode":"73770",
    "sg:province":"Baden-W\u00fcrttemberg",
    "wof:name":"P. Paul",
    "wof:placetype":"venue"
},
  "geometry": {"coordinates":[9.317279,48.697369],"type":"Point"}
}