{
  "type": "Feature",
  "properties": {
    "iso:country":"DE",
    "sg:address":"Schlo\u00dfplatz 3",
    "sg:city":"Badenweiler",
    "sg:phone":"+49 7632/891867",
    "sg:postcode":"79410",
    "sg:province":"Baden-W\u00fcrttemberg",
    "wof:name":"Rbg Betreuungsgesellschaft F\u00fcr Anlageverm\u00f6gen Mbh",
    "wof:placetype":"venue"
},
  "geometry": {"coordinates":[7.668376,47.804302],"type":"Point"}
}