{
  "type": "Feature",
  "properties": {
    "iso:country":"DE",
    "sg:address":"Wormser Str. 5",
    "sg:city":"Westhofen",
    "sg:phone":"+49 6244/905444",
    "sg:postcode":"67593",
    "sg:province":"Rheinland-Pfalz",
    "wof:name":"Cs & P Bildungsmanagement Gmbh",
    "wof:placetype":"venue"
},
  "geometry": {"coordinates":[8.2476730347,49.7033996582],"type":"Point"}
}