{
  "type": "Feature",
  "properties": {
    "iso:country":"DE",
    "sg:address":"Schleusinger Str. 5",
    "sg:city":"Suhl",
    "sg:phone":"+49 3681/21148",
    "sg:postcode":"98527",
    "sg:province":"Th\u00fcringen",
    "wof:name":"Dpa Deutsche Presse Agentur Gmbh",
    "wof:placetype":"venue"
},
  "geometry": {"coordinates":[10.6898059845,50.6071205139],"type":"Point"}
}