{
  "type": "Feature",
  "properties": {
    "iso:country":"DE",
    "sg:address":"Im Weinberg 14",
    "sg:city":"Allensbach",
    "sg:phone":"+49 7533/6343",
    "sg:postcode":"78476",
    "sg:province":"Baden-W\u00fcrttemberg",
    "wof:name":"Dr. Hanns H. Fritze",
    "wof:placetype":"venue"
},
  "geometry": {"coordinates":[9.0705738068,47.717376709],"type":"Point"}
}