{
  "type": "Feature",
  "properties": {
    "iso:country":"DE",
    "sg:address":"D\u00f6brastr. 12",
    "sg:city":"M\u00fcnchen",
    "sg:phone":"+49 89/6806350",
    "sg:postcode":"81549",
    "sg:province":"Bayern",
    "wof:name":"Christine St\u00fcber Garten- Und",
    "wof:placetype":"venue"
},
  "geometry": {"coordinates":[11.608088,48.095463],"type":"Point"}
}