{
  "type": "Feature",
  "properties": {
    "iso:country":"DE",
    "sg:address":"Silcherplatz 4",
    "sg:city":"Heilbronn",
    "sg:phone":"+49 7131/627133",
    "sg:postcode":"74072",
    "sg:province":"Baden-W\u00fcrttemberg",
    "wof:name":"Fl",
    "wof:placetype":"venue"
},
  "geometry": {"coordinates":[9.226562,49.134338],"type":"Point"}
}