{
  "type": "Feature",
  "properties": {
    "iso:country":"DE",
    "sg:address":"Trendelbuscher Weg 145",
    "sg:city":"Ganderkesee",
    "sg:phone":"+49 4221/807460",
    "sg:postcode":"27777",
    "sg:province":"Niedersachsen",
    "wof:name":"Linde Ag",
    "wof:placetype":"venue"
},
  "geometry": {"coordinates":[8.576149,53.067303],"type":"Point"}
}