{
  "type": "Feature",
  "properties": {
    "iso:country":"DE",
    "sg:address":"Hauptstr. 22",
    "sg:city":"Rodenbach",
    "sg:phone":"+49 6374/4081",
    "sg:postcode":"67688",
    "sg:province":"Rheinland-Pfalz",
    "wof:name":"Biohof Gerd Lang",
    "wof:placetype":"venue"
},
  "geometry": {"coordinates":[7.660334,49.473534],"type":"Point"}
}