{
  "type": "Feature",
  "properties": {
    "iso:country":"DE",
    "sg:address":"G\u00fcnter-Gottlebe-Str. 4",
    "sg:city":"Colditz",
    "sg:phone":"+49 34381/40902",
    "sg:postcode":"04680",
    "sg:province":"Sachsen",
    "wof:name":"Heimatturm Inh. Barbara Sienel",
    "wof:placetype":"venue"
},
  "geometry": {"coordinates":[12.7949533463,51.1287231445],"type":"Point"}
}