{
  "type": "Feature",
  "properties": {
    "iso:country":"DE",
    "sg:address":"Kastanienstr. 15c",
    "sg:city":"Eisenh\u00fcttenstadt",
    "sg:phone":"+49 3364/29157",
    "sg:postcode":"15890",
    "sg:province":"Brandenburg",
    "wof:name":"Autohaus Finke E. Kfm.",
    "wof:placetype":"venue"
},
  "geometry": {"coordinates":[14.672974,52.147129],"type":"Point"}
}