{
  "type": "Feature",
  "properties": {
    "iso:country":"DE",
    "sg:address":"Guntherweg 4a",
    "sg:city":"Niederalteich",
    "sg:postcode":"94557",
    "sg:province":"Bayern",
    "wof:name":"G\u00e4stezimmer Kapfhammer",
    "wof:placetype":"venue"
},
  "geometry": {"coordinates":[13.0257873535,48.7653007507],"type":"Point"}
}