{
  "type": "Feature",
  "properties": {
    "iso:country":"DE",
    "sg:address":"Thomas-Mann-Str. 9",
    "sg:city":"Elmshorn",
    "sg:phone":"+49 4121/62403",
    "sg:postcode":"25336",
    "sg:province":"Schleswig-Holstein",
    "wof:name":"Horst Steinwender Elektroinstallation",
    "wof:placetype":"venue"
},
  "geometry": {"coordinates":[9.65907,53.744289],"type":"Point"}
}