{
  "type": "Feature",
  "properties": {
    "iso:country":"DE",
    "sg:address":"K\u00f6nigsallee 178b",
    "sg:city":"Bochum",
    "sg:phone":"+49 234/97620",
    "sg:postcode":"44799",
    "sg:province":"Nordrhein-Westfalen",
    "wof:name":"G Data Software Ag",
    "wof:placetype":"venue"
},
  "geometry": {"coordinates":[7.22347,51.458336],"type":"Point"}
}