{
  "type": "Feature",
  "properties": {
    "iso:country":"DE",
    "sg:address":"Zweckeler Str. 16",
    "sg:city":"Gelsenkirchen",
    "sg:phone":"+49 209/318370",
    "sg:postcode":"45896",
    "sg:province":"Nordrhein-Westfalen",
    "wof:name":"Giebel Electronic Und Kommunikations Gmbh",
    "wof:placetype":"venue"
},
  "geometry": {"coordinates":[7.0186038017,51.5839195251],"type":"Point"}
}