{
  "type": "Feature",
  "properties": {
    "iso:country":"DE",
    "sg:address":"Raschplatz 9d",
    "sg:city":"Hannover",
    "sg:phone":"+49 511/3885885",
    "sg:postcode":"30161",
    "sg:province":"Niedersachsen",
    "wof:name":"Spielraum",
    "wof:placetype":"venue"
},
  "geometry": {"coordinates":[9.7437162399,52.3788986206],"type":"Point"}
}