{
  "type": "Feature",
  "properties": {
    "iso:country":"DE",
    "sg:address":"Hathumarstr. 7-9",
    "sg:city":"Paderborn",
    "sg:phone":"+49 5251/831350",
    "sg:postcode":"33098",
    "sg:province":"Nordrhein-Westfalen",
    "wof:name":"Museum F\u00fcr Stadtgeschichte",
    "wof:placetype":"venue"
},
  "geometry": {"coordinates":[8.755154,51.721004],"type":"Point"}
}