{
  "type": "Feature",
  "properties": {
    "iso:country":"DE",
    "sg:address":"Westfalenstr. 9",
    "sg:city":"Seelze",
    "sg:phone":"+49 5137/94241",
    "sg:postcode":"30926",
    "sg:province":"Niedersachsen",
    "wof:name":"Ralf Schukowski",
    "wof:placetype":"venue"
},
  "geometry": {"coordinates":[9.5292234421,52.4083366394],"type":"Point"}
}