{
  "type": "Feature",
  "properties": {
    "iso:country":"DE",
    "sg:address":"Immermannstr. 65",
    "sg:city":"D\u00fcsseldorf",
    "sg:phone":"+49 211/166730",
    "sg:postcode":"40210",
    "sg:province":"Nordrhein-Westfalen",
    "wof:name":"Hitachi Chemical Europe Gmbh",
    "wof:placetype":"venue"
},
  "geometry": {"coordinates":[6.79283,51.221584],"type":"Point"}
}