{
  "type": "Feature",
  "properties": {
    "iso:country":"DE",
    "sg:address":"Rieslingstr. 18",
    "sg:city":"Aichwald",
    "sg:phone":"+49 711/36909",
    "sg:postcode":"73773",
    "sg:province":"Baden-W\u00fcrttemberg",
    "wof:name":"Krankenpflegeverein Aichwald E. V.",
    "wof:placetype":"venue"
},
  "geometry": {"coordinates":[9.3954772949,48.7787590027],"type":"Point"}
}