{
  "type": "Feature",
  "properties": {
    "iso:country":"DE",
    "sg:address":"Rudolf-Breitscheid-Str 07",
    "sg:city":"Meerane",
    "sg:phone":"+49 3764/401855",
    "sg:postcode":"08393",
    "sg:province":"Sachsen",
    "wof:name":"Bohne Hebetechnik",
    "wof:placetype":"venue"
},
  "geometry": {"coordinates":[12.463324,50.845531],"type":"Point"}
}