{
  "type": "Feature",
  "properties": {
    "iso:country":"DE",
    "sg:address":"Hauptstr. 97",
    "sg:city":"Oberfell",
    "sg:phone":"+49 2605/2524",
    "sg:postcode":"56332",
    "sg:province":"Rheinland-Pfalz",
    "wof:name":"Norbert Fischer",
    "wof:placetype":"venue"
},
  "geometry": {"coordinates":[7.4491930008,50.2574501038],"type":"Point"}
}