{
  "type": "Feature",
  "properties": {
    "iso:country":"DE",
    "sg:address":"Spitalerstr. 14",
    "sg:city":"Hamburg",
    "sg:phone":"+49 40/321162",
    "sg:postcode":"20095",
    "sg:province":"Hamburg",
    "wof:name":"Bernd F. Abel Heilpraktiker",
    "wof:placetype":"venue"
},
  "geometry": {"coordinates":[10.0021429062,53.5519714355],"type":"Point"}
}