{
  "type": "Feature",
  "properties": {
    "iso:country":"DE",
    "sg:address":"Langgasse 19a",
    "sg:city":"Neu-Anspach",
    "sg:phone":"+49 6081/962120",
    "sg:postcode":"61267",
    "sg:province":"Hessen",
    "wof:name":"Babsis Zwergenh\u00e4uschen Barbara Stahlmann",
    "wof:placetype":"venue"
},
  "geometry": {"coordinates":[8.5083265305,50.2898216248],"type":"Point"}
}