{
  "type": "Feature",
  "properties": {
    "iso:country":"DE",
    "sg:address":"Hohenzollernstr. 19",
    "sg:city":"Wald",
    "sg:phone":"+49 7578/1254",
    "sg:postcode":"88639",
    "sg:province":"Baden-W\u00fcrttemberg",
    "wof:name":"Gerhard Gabler",
    "wof:placetype":"venue"
},
  "geometry": {"coordinates":[9.172705,47.936226],"type":"Point"}
}