{
  "type": "Feature",
  "properties": {
    "iso:country":"DE",
    "sg:address":"Kaubstr. 9",
    "sg:city":"Berlin",
    "sg:phone":"+49 30/8611418",
    "sg:postcode":"10713",
    "sg:province":"Berlin",
    "wof:name":"Bund Deutscher Pfadfinder Landesverband Berlin",
    "wof:placetype":"venue"
},
  "geometry": {"coordinates":[13.3107948303,52.48802948],"type":"Point"}
}