{
  "type": "Feature",
  "properties": {
    "iso:country":"DE",
    "sg:address":"Ginsterweg 29",
    "sg:city":"Frankenberg",
    "sg:postcode":"35066",
    "sg:province":"Hessen",
    "wof:name":"Restaurant B\u00fcrgerhaus",
    "wof:placetype":"venue"
},
  "geometry": {"coordinates":[8.7971258163,51.0786399841],"type":"Point"}
}