{
  "type": "Feature",
  "properties": {
    "iso:country":"DE",
    "sg:address":"Kaiserstr. 13",
    "sg:city":"Gummersbach",
    "sg:phone":"+49 2261/23130",
    "sg:postcode":"51643",
    "sg:province":"Nordrhein-Westfalen",
    "wof:name":"Porst Fh Photo Gmbh",
    "wof:placetype":"venue"
},
  "geometry": {"coordinates":[7.566298008,51.0264587402],"type":"Point"}
}