{
  "type": "Feature",
  "properties": {
    "iso:country":"DE",
    "sg:address":"Mozartstr. 13",
    "sg:city":"Veringenstadt",
    "sg:phone":"+49 7577/1738",
    "sg:postcode":"72519",
    "sg:province":"Baden-W\u00fcrttemberg",
    "wof:name":"Siegfried Wagegg",
    "wof:placetype":"venue"
},
  "geometry": {"coordinates":[9.20421,48.18623],"type":"Point"}
}