{
  "type": "Feature",
  "properties": {
    "iso:country":"DE",
    "sg:address":"Krablerstr. 165",
    "sg:city":"Essen",
    "sg:phone":"+49 201/36482364",
    "sg:postcode":"45326",
    "sg:province":"Nordrhein-Westfalen",
    "wof:name":"Gfl Gesellschaft F\u00fcr Logistik Gmbh & Co. Kg",
    "wof:placetype":"venue"
},
  "geometry": {"coordinates":[6.991918,51.485634],"type":"Point"}
}