{
  "type": "Feature",
  "properties": {
    "iso:country":"DE",
    "sg:address":"Zechenstr. 5",
    "sg:city":"Eschweiler",
    "sg:phone":"+49 2403/22188",
    "sg:postcode":"52249",
    "sg:province":"Nordrhein-Westfalen",
    "wof:name":"Erwin G\u00f6rres",
    "wof:placetype":"venue"
},
  "geometry": {"coordinates":[6.27424,50.811913],"type":"Point"}
}