{
  "type": "Feature",
  "properties": {
    "iso:country":"DE",
    "sg:address":"Frankfurter Allee 24",
    "sg:city":"Berlin",
    "sg:phone":"+49 30/2917399",
    "sg:postcode":"10247",
    "sg:province":"Berlin",
    "wof:name":"Dr. Reiner Kluge Architekt",
    "wof:placetype":"venue"
},
  "geometry": {"coordinates":[13.459251,52.51506],"type":"Point"}
}