{
  "type": "Feature",
  "properties": {
    "iso:country":"DE",
    "sg:address":"Pelkovenstr. 143",
    "sg:city":"M\u00fcnchen",
    "sg:phone":"+49 89/1499070",
    "sg:postcode":"80992",
    "sg:province":"Bayern",
    "wof:name":"Julius Kleemann Handel Gmbh",
    "wof:placetype":"venue"
},
  "geometry": {"coordinates":[11.5303640366,48.1822166443],"type":"Point"}
}