{
  "type": "Feature",
  "properties": {
    "iso:country":"DE",
    "sg:address":"Siebenborner H\u00f6he 19",
    "sg:city":"Wipperf\u00fcrth",
    "sg:phone":"+49 2267/1286",
    "sg:postcode":"51688",
    "sg:province":"Nordrhein-Westfalen",
    "wof:name":"H. G. Kopp Ingenieur",
    "wof:placetype":"venue"
},
  "geometry": {"coordinates":[7.3761148453,51.1101875305],"type":"Point"}
}