{
  "type": "Feature",
  "properties": {
    "iso:country":"DE",
    "sg:address":"Ingersheimer Str. 35",
    "sg:city":"Ludwigsburg",
    "sg:phone":"+49 7141/33737",
    "sg:postcode":"71634",
    "sg:province":"Baden-W\u00fcrttemberg",
    "wof:name":"Siegfried K\u00f6hler Ingenieur",
    "wof:placetype":"venue"
},
  "geometry": {"coordinates":[9.1774873734,48.9124412537],"type":"Point"}
}