{
  "type": "Feature",
  "properties": {
    "iso:country":"DE",
    "sg:address":"Morellstr. 33",
    "sg:city":"Augsburg",
    "sg:phone":"+49 821/258450",
    "sg:postcode":"86159",
    "sg:province":"Bayern",
    "wof:name":"Plan-quadrat Ingenieur- Beteiligungs Gmbh",
    "wof:placetype":"venue"
},
  "geometry": {"coordinates":[10.8923902512,48.3561286926],"type":"Point"}
}