{
  "type": "Feature",
  "properties": {
    "iso:country":"DE",
    "sg:address":"Grimmestr. 4",
    "sg:city":"Wickede",
    "sg:phone":"+49 2377/6476",
    "sg:postcode":"58739",
    "sg:province":"Nordrhein-Westfalen",
    "wof:name":"Mechthild Keweloh Architektin",
    "wof:placetype":"venue"
},
  "geometry": {"coordinates":[7.874461,51.502586],"type":"Point"}
}