{
  "type": "Feature",
  "properties": {
    "iso:country":"DE",
    "sg:address":"Schlesische Str. 26",
    "sg:city":"Berlin",
    "sg:phone":"+49 4930/6121089",
    "sg:postcode":"10997",
    "sg:province":"Berlin",
    "wof:name":"Robert Helwig Gmbh",
    "wof:placetype":"venue"
},
  "geometry": {"coordinates":[13.448255,52.497837],"type":"Point"}
}