{
  "type": "Feature",
  "properties": {
    "iso:country":"DE",
    "sg:address":"Heinrich-Heine-Str. 21",
    "sg:city":"Reiskirchen",
    "sg:phone":"+49 6408/61606",
    "sg:postcode":"35447",
    "sg:province":"Hessen",
    "wof:name":"Karl Zenger Rechtsanwalt Und Notar",
    "wof:placetype":"venue"
},
  "geometry": {"coordinates":[8.8282966614,50.6015472412],"type":"Point"}
}