{
  "type": "Feature",
  "properties": {
    "iso:country":"DE",
    "sg:address":"Salzufer 14a",
    "sg:city":"Berlin",
    "sg:postcode":"10587",
    "sg:province":"Berlin",
    "wof:name":"Bit-side Gmbh",
    "wof:placetype":"venue"
},
  "geometry": {"coordinates":[13.323205,52.518196],"type":"Point"}
}