{
  "type": "Feature",
  "properties": {
    "iso:country":"DE",
    "sg:address":"Niedenau",
    "sg:city":"Frankfurt",
    "sg:postcode":"60325",
    "sg:province":"Hessen",
    "wof:name":"Mosby Gmbh",
    "wof:placetype":"venue"
},
  "geometry": {"coordinates":[8.666709,50.115879],"type":"Point"}
}