{
  "type": "Feature",
  "properties": {
    "iso:country":"DE",
    "sg:address":"Dorfstr. 2",
    "sg:city":"Drebber",
    "sg:phone":"+49 5445/998065",
    "sg:postcode":"49457",
    "sg:province":"Niedersachsen",
    "wof:name":"Reddig Gmbh",
    "wof:placetype":"venue"
},
  "geometry": {"coordinates":[8.4259653091,52.6502189636],"type":"Point"}
}