{
  "type": "Feature",
  "properties": {
    "iso:country":"DE",
    "sg:address":"Rutschbahn 15",
    "sg:city":"Hamburg",
    "sg:phone":"+49 40/447117",
    "sg:postcode":"20146",
    "sg:province":"Hamburg",
    "wof:name":"Ft-reisen Michel Moreau",
    "wof:placetype":"venue"
},
  "geometry": {"coordinates":[9.9806070328,53.5712738037],"type":"Point"}
}