{
  "type": "Feature",
  "properties": {
    "iso:country":"DE",
    "sg:address":"Kapellenstr. 13",
    "sg:city":"Feldkirchen",
    "sg:phone":"+49 4908/9908990",
    "sg:postcode":"85622",
    "sg:province":"Bayern",
    "wof:name":"Ebookman Von Franklin - Homepage, Organizer, Mp3-p",
    "wof:placetype":"venue"
},
  "geometry": {"coordinates":[11.743022,48.150803],"type":"Point"}
}