{
  "type": "Feature",
  "properties": {
    "iso:country":"DE",
    "sg:address":"Schaphauser Str. 59",
    "sg:city":"Grefrath",
    "sg:phone":"+49 2158/911690",
    "sg:postcode":"47929",
    "sg:province":"Nordrhein-Westfalen",
    "wof:name":"G. Jahrke",
    "wof:placetype":"venue"
},
  "geometry": {"coordinates":[6.327891,51.339218],"type":"Point"}
}