{
  "type": "Feature",
  "properties": {
    "iso:country":"DE",
    "sg:address":"Industriestr. 37",
    "sg:city":"V\u00f6hringen",
    "sg:phone":"+49 7306/31424",
    "sg:postcode":"89269",
    "sg:province":"Bayern",
    "wof:name":"Ernst K\u00e4\u00dfmeyer B\u00e4ckerei Kg",
    "wof:placetype":"venue"
},
  "geometry": {"coordinates":[10.078598,48.287781],"type":"Point"}
}