{
  "type": "Feature",
  "properties": {
    "iso:country":"DE",
    "sg:address":"H\u00f6rlstr. 13",
    "sg:city":"Ruhstorf",
    "sg:phone":"+49 8531/31286",
    "sg:postcode":"94099",
    "sg:province":"Bayern",
    "wof:name":"Hermann Staudinger Jun.",
    "wof:placetype":"venue"
},
  "geometry": {"coordinates":[13.3322620392,48.4328308105],"type":"Point"}
}