{
  "type": "Feature",
  "properties": {
    "iso:country":"DE",
    "sg:address":"Dieselstr. 12",
    "sg:city":"Griesheim",
    "sg:phone":"+49 6155/83960",
    "sg:postcode":"64347",
    "sg:province":"Hessen",
    "wof:name":"Heinrich Dauscher Architekt",
    "wof:placetype":"venue"
},
  "geometry": {"coordinates":[8.558116,49.870396],"type":"Point"}
}