{
  "type": "Feature",
  "properties": {
    "iso:country":"DE",
    "sg:address":"Am Markt 7",
    "sg:city":"Friedrichstadt",
    "sg:phone":"+49 4881/398",
    "sg:postcode":"25840",
    "sg:province":"Schleswig-Holstein",
    "wof:name":"Hans-joachim Schmidt",
    "wof:placetype":"venue"
},
  "geometry": {"coordinates":[9.0897693634,54.3757171631],"type":"Point"}
}