{
  "type": "Feature",
  "properties": {
    "iso:country":"DE",
    "sg:address":"Lindenstr. 30",
    "sg:city":"Straubing",
    "sg:phone":"+49 9421/80631",
    "sg:postcode":"94315",
    "sg:province":"Bayern",
    "wof:name":"Zur Linde",
    "wof:placetype":"venue"
},
  "geometry": {"coordinates":[12.5792388916,48.8836326599],"type":"Point"}
}