{
  "type": "Feature",
  "properties": {
    "iso:country":"DE",
    "sg:address":"Kindstr. 4",
    "sg:city":"Leipzig",
    "sg:phone":"+49 341/4011492",
    "sg:postcode":"04177",
    "sg:province":"Sachsen",
    "wof:name":"Acon Bau Gmbh",
    "wof:placetype":"venue"
},
  "geometry": {"coordinates":[12.3377246857,51.3339004517],"type":"Point"}
}