{
  "type": "Feature",
  "properties": {
    "iso:country":"DE",
    "sg:address":"Sch\u00f6ppinger Str. 76",
    "sg:city":"Rosendahl",
    "sg:phone":"+49 2547/7233",
    "sg:postcode":"48720",
    "sg:province":"Nordrhein-Westfalen",
    "wof:name":"Heinrich Meickmann",
    "wof:placetype":"venue"
},
  "geometry": {"coordinates":[7.216625,52.034382],"type":"Point"}
}