{
  "type": "Feature",
  "properties": {
    "iso:country":"DE",
    "sg:address":"Zu den M\u00fchlen 10",
    "sg:city":"Gie\u00dfen",
    "sg:phone":"+49 641/71630",
    "sg:postcode":"35390",
    "sg:province":"Hessen",
    "wof:name":"Standox Gmbh",
    "wof:placetype":"venue"
},
  "geometry": {"coordinates":[8.668166,50.588348],"type":"Point"}
}