{
  "type": "Feature",
  "properties": {
    "iso:country":"DE",
    "sg:address":"Dingolfinger Str. 21",
    "sg:city":"Reisbach",
    "sg:phone":"+49 8734/7734",
    "sg:postcode":"94419",
    "sg:province":"Bayern",
    "wof:name":"Massage- Und B\u00e4derpraxis Mayer",
    "wof:placetype":"venue"
},
  "geometry": {"coordinates":[12.625076,48.574657],"type":"Point"}
}