{
  "type": "Feature",
  "properties": {
    "iso:country":"DE",
    "sg:address":"Cosimastr. 290",
    "sg:city":"M\u00fcnchen",
    "sg:postcode":"81927",
    "sg:province":"Bayern",
    "wof:name":"Prozedere Gmbh",
    "wof:placetype":"venue"
},
  "geometry": {"coordinates":[11.6367101669,48.1735496521],"type":"Point"}
}