{
  "type": "Feature",
  "properties": {
    "iso:country":"DE",
    "sg:address":"Steinstr. 3",
    "sg:city":"Bretten",
    "sg:phone":"+49 7252/1576",
    "sg:postcode":"75015",
    "sg:province":"Baden-W\u00fcrttemberg",
    "wof:name":"Werner Wolff",
    "wof:placetype":"venue"
},
  "geometry": {"coordinates":[8.728304,49.00819],"type":"Point"}
}