{
  "type": "Feature",
  "properties": {
    "iso:country":"DE",
    "sg:address":"Bahnweg 3",
    "sg:city":"Loiching",
    "sg:phone":"+49 8731/31370",
    "sg:postcode":"84180",
    "sg:province":"Bayern",
    "wof:name":"Peter Amberger Gmbh",
    "wof:placetype":"venue"
},
  "geometry": {"coordinates":[12.4245185852,48.6395683289],"type":"Point"}
}