{
  "type": "Feature",
  "properties": {
    "iso:country":"DE",
    "sg:address":"Bolzstr. 6",
    "sg:city":"Stuttgart",
    "sg:phone":"+49 711/225650",
    "sg:postcode":"70173",
    "sg:province":"Baden-W\u00fcrttemberg",
    "wof:name":"Bofinger Busch Und Partner Rechtsanw\u00e4lte Und Notare Gbr",
    "wof:placetype":"venue"
},
  "geometry": {"coordinates":[9.1787385941,48.7798461914],"type":"Point"}
}