{
  "type": "Feature",
  "properties": {
    "iso:country":"DE",
    "sg:address":"Schubertstr. 7",
    "sg:city":"B\u00f6blingen",
    "sg:phone":"+49 7031/671199",
    "sg:postcode":"71034",
    "sg:province":"Baden-W\u00fcrttemberg",
    "wof:name":"Helga Ruoff Heilpraktiker",
    "wof:placetype":"venue"
},
  "geometry": {"coordinates":[8.9624614716,48.6913375854],"type":"Point"}
}