{
  "type": "Feature",
  "properties": {
    "iso:country":"DE",
    "sg:address":"Otto-Hahn-Str 4",
    "sg:city":"Neckarwestheim",
    "sg:phone":"+49 7133/962050",
    "sg:postcode":"74382",
    "sg:province":"Baden-W\u00fcrttemberg",
    "wof:name":"Kromatec Gmbh",
    "wof:placetype":"venue"
},
  "geometry": {"coordinates":[9.199892,49.042271],"type":"Point"}
}