{
  "type": "Feature",
  "properties": {
    "iso:country":"DE",
    "sg:address":"Friedrich-Ebert-Str. 24",
    "sg:city":"Nordenham",
    "sg:phone":"+49 4731/4324",
    "sg:postcode":"26954",
    "sg:province":"Niedersachsen",
    "wof:name":"Grabbert",
    "wof:placetype":"venue"
},
  "geometry": {"coordinates":[8.4853210449,53.4863624573],"type":"Point"}
}