{
  "type": "Feature",
  "properties": {
    "iso:country":"DE",
    "sg:address":"Annenheider Str 259",
    "sg:city":"Delmenhorst",
    "sg:phone":"+49 4221/925414",
    "sg:postcode":"27755",
    "sg:province":"Niedersachsen",
    "wof:name":"Ths Ingenieurgesellschaft Mbh",
    "wof:placetype":"venue"
},
  "geometry": {"coordinates":[8.636839,53.017479],"type":"Point"}
}