{
  "type": "Feature",
  "properties": {
    "iso:country":"DE",
    "sg:address":"Augustenstr. 94",
    "sg:city":"Stuttgart",
    "sg:postcode":"70197",
    "sg:province":"Baden-W\u00fcrttemberg",
    "wof:name":"Franz\u00f6sischer Schulverein Und Vorschule Georges Cuvier",
    "wof:placetype":"venue"
},
  "geometry": {"coordinates":[9.1584720612,48.769241333],"type":"Point"}
}