{
  "type": "Feature",
  "properties": {
    "iso:country":"DE",
    "sg:address":"Tomper Str. 13",
    "sg:city":"M\u00f6nchengladbach",
    "sg:phone":"+49 2161/559731",
    "sg:postcode":"41169",
    "sg:province":"Nordrhein-Westfalen",
    "wof:name":"J. Alberz Hardt",
    "wof:placetype":"venue"
},
  "geometry": {"coordinates":[6.339933,51.206177],"type":"Point"}
}