{
  "type": "Feature",
  "properties": {
    "iso:country":"DE",
    "sg:address":"Wulfsdorfer Weg 9",
    "sg:city":"Ammersbek",
    "sg:phone":"+49 40/6051225",
    "sg:postcode":"22949",
    "sg:province":"Schleswig-Holstein",
    "wof:name":"A. Korbanek",
    "wof:placetype":"venue"
},
  "geometry": {"coordinates":[10.16973,53.68861],"type":"Point"}
}