{
  "type": "Feature",
  "properties": {
    "iso:country":"DE",
    "sg:address":"Bergstr. 15-17",
    "sg:city":"Rathenow",
    "sg:phone":"+49 3385/5560",
    "sg:postcode":"14712",
    "sg:province":"Brandenburg",
    "wof:name":"Havell\u00e4ndische Bildungs- Gesellschaft Mbh",
    "wof:placetype":"venue"
},
  "geometry": {"coordinates":[12.3389396667,52.6041412354],"type":"Point"}
}