{
  "type": "Feature",
  "properties": {
    "iso:country":"DE",
    "sg:address":"Westring 28",
    "sg:city":"Datteln",
    "sg:phone":"+49 2363/32767",
    "sg:postcode":"45711",
    "sg:province":"Nordrhein-Westfalen",
    "wof:name":"Rolf Lange Drogerie",
    "wof:placetype":"venue"
},
  "geometry": {"coordinates":[7.331577,51.655491],"type":"Point"}
}