{
  "type": "Feature",
  "properties": {
    "iso:country":"DE",
    "sg:address":"Eickeler Str. 76",
    "sg:city":"Herne",
    "sg:phone":"+49 2325/3822",
    "sg:postcode":"44651",
    "sg:province":"Nordrhein-Westfalen",
    "wof:name":"Solicare H\u00e4usl. Pflege Gmbh",
    "wof:placetype":"venue"
},
  "geometry": {"coordinates":[7.183159,51.508495],"type":"Point"}
}