{
  "type": "Feature",
  "properties": {
    "iso:country":"DE",
    "sg:address":"Unterheydener Str. 72",
    "sg:city":"M\u00f6nchengladbach",
    "sg:phone":"+49 2166/49463",
    "sg:postcode":"41236",
    "sg:province":"Nordrhein-Westfalen",
    "wof:name":"Friedrich Lobigs",
    "wof:placetype":"venue"
},
  "geometry": {"coordinates":[6.4525427818,51.157081604],"type":"Point"}
}