{
  "type": "Feature",
  "properties": {
    "iso:country":"DE",
    "sg:address":"M\u00fchlbachstr. 3",
    "sg:city":"Ottobeuren",
    "sg:phone":"+49 8332/7728",
    "sg:postcode":"87724",
    "sg:province":"Bayern",
    "wof:name":"Erich Frisch",
    "wof:placetype":"venue"
},
  "geometry": {"coordinates":[10.299714,47.938107],"type":"Point"}
}