{
  "type": "Feature",
  "properties": {
    "iso:country":"DE",
    "sg:address":"Hans-B\u00f6ckler-Str 5",
    "sg:city":"Obertshausen",
    "sg:phone":"+49 6104/6682944",
    "sg:postcode":"63179",
    "sg:province":"Hessen",
    "wof:name":"Gsst - Gesellschaft F\u00fcr Schutz- Und Sicherheitstechnik Mbh",
    "wof:placetype":"venue"
},
  "geometry": {"coordinates":[8.84683,50.069656],"type":"Point"}
}