{
  "type": "Feature",
  "properties": {
    "iso:country":"DE",
    "sg:address":"In der Mirke 1",
    "sg:city":"Wuppertal",
    "sg:phone":"+49 202/754444",
    "sg:postcode":"42109",
    "sg:province":"Nordrhein-Westfalen",
    "wof:name":"Gastst\u00e4tte Mirke",
    "wof:placetype":"venue"
},
  "geometry": {"coordinates":[7.1460518837,51.2741165161],"type":"Point"}
}