{
  "type": "Feature",
  "properties": {
    "iso:country":"DE",
    "sg:address":"Sattelstr.4-5",
    "sg:city":"D\u00f6beln",
    "sg:phone":"+49 3431",
    "sg:postcode":"04720",
    "sg:province":"Sachsen",
    "wof:name":"Maa\u00df",
    "wof:placetype":"venue"
},
  "geometry": {"coordinates":[13.1232242584,51.1229515076],"type":"Point"}
}