{
  "type": "Feature",
  "properties": {
    "iso:country":"DE",
    "sg:address":"Backnanger Str. 46",
    "sg:city":"Sulzbach",
    "sg:phone":"+49 7193/266",
    "sg:postcode":"71560",
    "sg:province":"Baden-W\u00fcrttemberg",
    "wof:name":"Hirsch",
    "wof:placetype":"venue"
},
  "geometry": {"coordinates":[9.498632431,49.0036697388],"type":"Point"}
}