{
  "type": "Feature",
  "properties": {
    "iso:country":"DE",
    "sg:address":"Schroffstr. 56",
    "sg:city":"M\u00f6nchengladbach",
    "sg:phone":"+49 2166/17874",
    "sg:postcode":"41199",
    "sg:province":"Nordrhein-Westfalen",
    "wof:name":"Josef P\u00f6stges",
    "wof:placetype":"venue"
},
  "geometry": {"coordinates":[6.43306,51.14658],"type":"Point"}
}