{
  "type": "Feature",
  "properties": {
    "iso:country":"DE",
    "sg:address":"Eichborndamm 29",
    "sg:city":"Berlin",
    "sg:phone":"+49 30/4121829",
    "sg:postcode":"13403",
    "sg:province":"Berlin",
    "wof:name":"Lothar Und Martin Van Dahl Ohg",
    "wof:placetype":"venue"
},
  "geometry": {"coordinates":[13.31272,52.570625],"type":"Point"}
}