{
  "type": "Feature",
  "properties": {
    "iso:country":"DE",
    "sg:address":"In den Seewiesen 4",
    "sg:city":"Heidenheim",
    "sg:postcode":"89520",
    "sg:province":"Baden-W\u00fcrttemberg",
    "wof:name":"Eugen Sing Verwaltung Gmbh",
    "wof:placetype":"venue"
},
  "geometry": {"coordinates":[10.1600580215,48.6928939819],"type":"Point"}
}