{
  "type": "Feature",
  "properties": {
    "iso:country":"DE",
    "sg:address":"Am Birkenw\u00e4ldchen 13",
    "sg:city":"Halstenbek",
    "sg:phone":"+49 4101/401520",
    "sg:postcode":"25469",
    "sg:province":"Schleswig-Holstein",
    "wof:name":"A & R Vertriebsges. Mbh",
    "wof:placetype":"venue"
},
  "geometry": {"coordinates":[9.861631,53.62038],"type":"Point"}
}