{
  "type": "Feature",
  "properties": {
    "iso:country":"DE",
    "sg:address":"Vititorwall 4",
    "sg:city":"Goslar",
    "sg:phone":"+49 5321/24055",
    "sg:postcode":"38640",
    "sg:province":"Niedersachsen",
    "wof:name":"Wolfgang Lampe-traupe Rechtsanwalt",
    "wof:placetype":"venue"
},
  "geometry": {"coordinates":[10.4238519669,51.9095077515],"type":"Point"}
}