{
  "type": "Feature",
  "properties": {
    "iso:country":"DE",
    "sg:address":"Hinrichsring 12",
    "sg:city":"Hannover",
    "sg:phone":"+49 511/3942425",
    "sg:postcode":"30177",
    "sg:province":"Niedersachsen",
    "wof:name":"Restaurant Zum Zapfhahn",
    "wof:placetype":"venue"
},
  "geometry": {"coordinates":[9.7772064209,52.4054908752],"type":"Point"}
}