{
  "type": "Feature",
  "properties": {
    "iso:country":"DE",
    "sg:address":"Neupforte 2 b",
    "sg:city":"Aachen",
    "sg:phone":"+49 241/37476",
    "sg:postcode":"52062",
    "sg:province":"Nordrhein-Westfalen",
    "wof:name":"Restaurant Aragosta",
    "wof:placetype":"venue"
},
  "geometry": {"coordinates":[6.0829410553,50.7776145935],"type":"Point"}
}