{
  "type": "Feature",
  "properties": {
    "iso:country":"DE",
    "sg:address":"Werftstr. 25",
    "sg:city":"Herne",
    "sg:phone":"+49 2323/8540",
    "sg:postcode":"44628",
    "sg:province":"Nordrhein-Westfalen",
    "wof:name":"Katholisches Pfarramt St. Pius",
    "wof:placetype":"venue"
},
  "geometry": {"coordinates":[7.2431941032,51.5693855286],"type":"Point"}
}