{
  "type": "Feature",
  "properties": {
    "iso:country":"DE",
    "sg:address":"Brunnenstr. 74",
    "sg:city":"Bremm",
    "sg:phone":"+49 2675/893",
    "sg:postcode":"56814",
    "sg:province":"Rheinland-Pfalz",
    "wof:name":"Eduard Lehnen",
    "wof:placetype":"venue"
},
  "geometry": {"coordinates":[7.1151580811,50.0991783142],"type":"Point"}
}