{
  "type": "Feature",
  "properties": {
    "iso:country":"DE",
    "sg:address":"Queichheimer Hauptstr. 234",
    "sg:city":"Landau",
    "sg:phone":"+49 6341/50710",
    "sg:postcode":"76829",
    "sg:province":"Rheinland-Pfalz",
    "wof:name":"Elisabeth Blank",
    "wof:placetype":"venue"
},
  "geometry": {"coordinates":[8.1518278122,49.1959037781],"type":"Point"}
}