{
  "type": "Feature",
  "properties": {
    "iso:country":"DE",
    "sg:address":"Kirchenwinkel 8",
    "sg:city":"Gundelfingen",
    "sg:phone":"+49 761/580458",
    "sg:postcode":"79194",
    "sg:province":"Baden-W\u00fcrttemberg",
    "wof:name":"Herbstritt & Partner Ges. F. Datenverarbeitung Mbh",
    "wof:placetype":"venue"
},
  "geometry": {"coordinates":[7.8658041954,48.044921875],"type":"Point"}
}