{
  "type": "Feature",
  "properties": {
    "iso:country":"DE",
    "sg:address":"St.-Barbara-Str. 78",
    "sg:city":"St. Ingbert",
    "sg:phone":"+49 6894/34493",
    "sg:postcode":"66386",
    "sg:province":"Saarland",
    "wof:name":"J. Schenkelberger",
    "wof:placetype":"venue"
},
  "geometry": {"coordinates":[7.108141,49.280365],"type":"Point"}
}