{
  "type": "Feature",
  "properties": {
    "iso:country":"DE",
    "sg:address":"Walchstr. 46 b",
    "sg:city":"Deggendorf",
    "sg:phone":"+49 991/27860",
    "sg:postcode":"94469",
    "sg:province":"Bayern",
    "wof:name":"Joachim Wetzko",
    "wof:placetype":"venue"
},
  "geometry": {"coordinates":[12.963804245,48.8411979675],"type":"Point"}
}