{
  "type": "Feature",
  "properties": {
    "iso:country":"DE",
    "sg:address":"Sandbrede 27::",
    "sg:city":"Herford",
    "sg:phone":"+49 4952/2199100",
    "sg:postcode":"32049",
    "sg:province":"Nordrhein-Westfalen",
    "wof:name":"Abt U Petram Versich Makler Gmbh",
    "wof:placetype":"venue"
},
  "geometry": {"coordinates":[8.690181,52.122021],"type":"Point"}
}