{
  "type": "Feature",
  "properties": {
    "iso:country":"DE",
    "sg:address":"Craheim",
    "sg:city":"Stadtlauringen",
    "sg:postcode":"97488",
    "sg:province":"Bayern",
    "wof:name":"Der Sucher - Rollenspiel Downloads",
    "wof:placetype":"venue"
},
  "geometry": {"coordinates":[10.414627,50.199738],"type":"Point"}
}