{
  "type": "Feature",
  "properties": {
    "iso:country":"DE",
    "sg:address":"Hauptstr.",
    "sg:city":"Kammin",
    "sg:phone":"+49 38356/361",
    "sg:postcode":"17506",
    "sg:province":"Mecklenburg-Vorpommern",
    "wof:name":"Pommernstube",
    "wof:placetype":"venue"
},
  "geometry": {"coordinates":[13.4113445282,53.9364700317],"type":"Point"}
}