{
  "type": "Feature",
  "properties": {
    "iso:country":"DE",
    "sg:address":"L\u00fcckeweg 8",
    "sg:city":"Mellrichstadt",
    "sg:phone":"+49 9773/436",
    "sg:postcode":"97638",
    "sg:province":"Bayern",
    "wof:name":"Herbert Schmitt",
    "wof:placetype":"venue"
},
  "geometry": {"coordinates":[10.226976,50.406693],"type":"Point"}
}