{
  "type": "Feature",
  "properties": {
    "iso:country":"DE",
    "sg:address":"Gladbecker Str. 120",
    "sg:city":"Bottrop",
    "sg:postcode":"46236",
    "sg:province":"Nordrhein-Westfalen",
    "wof:name":"M\u00fcting Gmbh & Co. Leasing Kg",
    "wof:placetype":"venue"
},
  "geometry": {"coordinates":[6.931227,51.532822],"type":"Point"}
}