{
  "type": "Feature",
  "properties": {
    "iso:country":"DE",
    "sg:city":"Vachendorf",
    "sg:phone":"+49 861/4171",
    "sg:postcode":"83377",
    "sg:province":"Bayern",
    "wof:name":"Raiffeisenbank Traunstein Eg",
    "wof:placetype":"venue"
},
  "geometry": {"coordinates":[12.606875,47.841366],"type":"Point"}
}