{
  "type": "Feature",
  "properties": {
    "iso:country":"DE",
    "sg:address":"Zwerchallee 24",
    "sg:city":"Mainz",
    "sg:phone":"+49 6131/123425",
    "sg:postcode":"55120",
    "sg:province":"Rheinland-Pfalz",
    "wof:name":"Entsorgungsbetrieb Der Stadt Mainz",
    "wof:placetype":"venue"
},
  "geometry": {"coordinates":[8.2426996231,50.0196609497],"type":"Point"}
}