{
  "type": "Feature",
  "properties": {
    "iso:country":"DE",
    "sg:address":"Steintwietenhof 2",
    "sg:city":"Hamburg",
    "sg:phone":"+49 40/37500766",
    "sg:postcode":"20459",
    "sg:province":"Hamburg",
    "wof:name":"Wandel Und Kulesza Rechtsanw\u00e4lte",
    "wof:placetype":"venue"
},
  "geometry": {"coordinates":[9.9858036041,53.5462265015],"type":"Point"}
}