{
  "type": "Feature",
  "properties": {
    "iso:country":"DE",
    "sg:address":"Jakob-Klar-Str. 11",
    "sg:city":"M\u00fcnchen",
    "sg:postcode":"80796",
    "sg:province":"Bayern",
    "wof:name":"Florian Schwarz Beteiligungs Gmbh",
    "wof:placetype":"venue"
},
  "geometry": {"coordinates":[11.571443,48.160416],"type":"Point"}
}