{
  "type": "Feature",
  "properties": {
    "iso:country":"DE",
    "sg:address":"Riekerhofstr. 17",
    "sg:city":"Krefeld",
    "sg:phone":"+49 2151/316159",
    "sg:postcode":"47804",
    "sg:province":"Nordrhein-Westfalen",
    "wof:name":"Hans-gerd Bastians",
    "wof:placetype":"venue"
},
  "geometry": {"coordinates":[6.519698143,51.3073005676],"type":"Point"}
}