{
  "type": "Feature",
  "properties": {
    "iso:country":"DE",
    "sg:address":"Hinterm Reiherholz 4",
    "sg:city":"Berne",
    "sg:phone":"+49 4408/6606",
    "sg:postcode":"27804",
    "sg:province":"Niedersachsen",
    "wof:name":"Herbert Vosteen",
    "wof:placetype":"venue"
},
  "geometry": {"coordinates":[8.423407,53.125484],"type":"Point"}
}