{
  "type": "Feature",
  "properties": {
    "iso:country":"DE",
    "sg:address":"Osseweg 1",
    "sg:city":"Leer",
    "sg:phone":"+49 491/12796",
    "sg:postcode":"26789",
    "sg:province":"Niedersachsen",
    "wof:name":"Albertines Blumen",
    "wof:placetype":"venue"
},
  "geometry": {"coordinates":[7.474061,53.227829],"type":"Point"}
}