{
  "type": "Feature",
  "properties": {
    "iso:country":"DE",
    "sg:address":"Maybachstr. 11",
    "sg:city":"Hanau",
    "sg:phone":"+49 6181/96009",
    "sg:postcode":"63456",
    "sg:province":"Hessen",
    "wof:name":"Dap Tourismus-organisation Inh. Therese Schaich",
    "wof:placetype":"venue"
},
  "geometry": {"coordinates":[8.8946208954,50.1137008667],"type":"Point"}
}