{
  "type": "Feature",
  "properties": {
    "iso:country":"DE",
    "sg:address":"Neue Str. 19",
    "sg:city":"Me\u00dfstetten",
    "sg:phone":"+49 7436/732",
    "sg:postcode":"72469",
    "sg:province":"Baden-W\u00fcrttemberg",
    "wof:name":"Otto Sorg",
    "wof:placetype":"venue"
},
  "geometry": {"coordinates":[8.9625968933,48.1805992126],"type":"Point"}
}