{
  "type": "Feature",
  "properties": {
    "iso:country":"DE",
    "sg:address":"Sch\u00f6meringer Str. 26",
    "sg:city":"Stephanskirchen",
    "sg:phone":"+49 8036/628",
    "sg:postcode":"83071",
    "sg:province":"Bayern",
    "wof:name":"Raiffeisenbank Rosenheim Eg",
    "wof:placetype":"venue"
},
  "geometry": {"coordinates":[12.185167,47.855251],"type":"Point"}
}