{
  "type": "Feature",
  "properties": {
    "iso:country":"DE",
    "sg:address":"Werbelner Str. 52",
    "sg:city":"V\u00f6lklingen",
    "sg:phone":"+49 6898/41527",
    "sg:postcode":"66333",
    "sg:province":"Saarland",
    "wof:name":"W. Und B. Wahlster Schilder Und Lichtreklame",
    "wof:placetype":"venue"
},
  "geometry": {"coordinates":[6.798415,49.233555],"type":"Point"}
}