{
  "type": "Feature",
  "properties": {
    "iso:country":"DE",
    "sg:address":"Robert-Bosch-Str. 2",
    "sg:city":"G\u00f6ppingen",
    "sg:phone":"+49 7161/68786",
    "sg:postcode":"73037",
    "sg:province":"Baden-W\u00fcrttemberg",
    "wof:name":"E. Sapper",
    "wof:placetype":"venue"
},
  "geometry": {"coordinates":[9.686141,48.687576],"type":"Point"}
}