{
  "type": "Feature",
  "properties": {
    "iso:country":"DE",
    "sg:address":"Flughafenstra\u00dfe 4",
    "sg:city":"Erfurt",
    "sg:phone":"+49 361/224870",
    "sg:postcode":"99092",
    "sg:province":"Th\u00fcringen",
    "wof:name":"Profilpr Werbeagentur",
    "wof:placetype":"venue"
},
  "geometry": {"coordinates":[10.960163,50.973373],"type":"Point"}
}