{
  "type": "Feature",
  "properties": {
    "iso:country":"DE",
    "sg:address":"Stra\u00dfe der Republik 13",
    "sg:city":"Clingen",
    "sg:phone":"+49 3636/703687",
    "sg:postcode":"99718",
    "sg:province":"Th\u00fcringen",
    "wof:name":"D. K\u00e4stner",
    "wof:placetype":"venue"
},
  "geometry": {"coordinates":[10.9340057373,51.2345695496],"type":"Point"}
}