{
  "type": "Feature",
  "properties": {
    "iso:country":"DE",
    "sg:address":"Ludwigstr. 10",
    "sg:city":"Homberg",
    "sg:phone":"+49 6633/5088",
    "sg:postcode":"35315",
    "sg:province":"Hessen",
    "wof:name":"Modell Und Werkzeugbau Hans Wagner Kg",
    "wof:placetype":"venue"
},
  "geometry": {"coordinates":[9.0379457474,50.7466506958],"type":"Point"}
}