{
  "type": "Feature",
  "properties": {
    "iso:country":"DE",
    "sg:address":"Gernsheimer Str. 44",
    "sg:city":"Pfungstadt",
    "sg:postcode":"64319",
    "sg:province":"Hessen",
    "wof:name":"Stadtb\u00fccherei Hahn",
    "wof:placetype":"venue"
},
  "geometry": {"coordinates":[8.559554,49.793575],"type":"Point"}
}