{
  "type": "Feature",
  "properties": {
    "iso:country":"DE",
    "sg:address":"Falkenstr. 1",
    "sg:city":"Griesst\u00e4tt",
    "sg:phone":"+49 8039/5168",
    "sg:postcode":"83556",
    "sg:province":"Bayern",
    "wof:name":"K\u00f6rner Gmbh",
    "wof:placetype":"venue"
},
  "geometry": {"coordinates":[12.181474,47.994991],"type":"Point"}
}