{
  "type": "Feature",
  "properties": {
    "iso:country":"DE",
    "sg:address":"Oswaldstr. 11",
    "sg:city":"Hamm",
    "sg:phone":"+49 2381/73510",
    "sg:postcode":"59075",
    "sg:province":"Nordrhein-Westfalen",
    "wof:name":"Landesbausparkasse Beratungsstelle",
    "wof:placetype":"venue"
},
  "geometry": {"coordinates":[7.760012,51.697556],"type":"Point"}
}