{
  "type": "Feature",
  "properties": {
    "iso:country":"DE",
    "sg:address":"Landstr. 20",
    "sg:city":"Steinen",
    "sg:phone":"+49 7627/3669",
    "sg:postcode":"79585",
    "sg:province":"Baden-W\u00fcrttemberg",
    "wof:name":"Fitness-center",
    "wof:placetype":"venue"
},
  "geometry": {"coordinates":[7.7581501007,47.6427001953],"type":"Point"}
}