{
  "type": "Feature",
  "properties": {
    "iso:country":"DE",
    "sg:address":"Kurt-Schumacher Str.11",
    "sg:city":"Emmerich",
    "sg:phone":"+49 2822/94115",
    "sg:postcode":"46446",
    "sg:province":"Nordrhein-Westfalen",
    "wof:name":"Erotikcenter-chatline",
    "wof:placetype":"venue"
},
  "geometry": {"coordinates":[6.239565,51.841534],"type":"Point"}
}