{
  "type": "Feature",
  "properties": {
    "iso:country":"DE",
    "sg:address":"Schl\u00f6sselstr. 63",
    "sg:city":"J\u00f6hstadt",
    "sg:phone":"+49 69/576174",
    "sg:postcode":"09477",
    "sg:province":"Sachsen",
    "wof:name":"Helmut Ullmann",
    "wof:placetype":"venue"
},
  "geometry": {"coordinates":[13.1029310226,50.5149154663],"type":"Point"}
}