{
  "type": "Feature",
  "properties": {
    "iso:country":"DE",
    "sg:address":"Fischergasse 231 1/2",
    "sg:city":"Neuburg",
    "sg:phone":"+49 8431/3095",
    "sg:postcode":"86633",
    "sg:province":"Bayern",
    "wof:name":"Andreas Kaes Rechtsanwalt",
    "wof:placetype":"venue"
},
  "geometry": {"coordinates":[11.2046298981,48.7456016541],"type":"Point"}
}