{
  "type": "Feature",
  "properties": {
    "iso:country":"DE",
    "sg:address":"Hirschbergerstra\u00dfe 46",
    "sg:city":"Allersberg",
    "sg:postcode":"90584",
    "sg:province":"Bayern",
    "wof:name":"Regionale Auftragsb\u00f6rse Mit Homepageservice",
    "wof:placetype":"venue"
},
  "geometry": {"coordinates":[11.248952,49.25119],"type":"Point"}
}