{
  "type": "Feature",
  "properties": {
    "iso:country":"DE",
    "sg:address":"K\u00f6nigstr. 67",
    "sg:city":"Remscheid",
    "sg:phone":"+49 4921/9172684",
    "sg:postcode":"42853",
    "sg:province":"Nordrhein-Westfalen",
    "wof:name":"Stabil Fahrzeugteile Gmbh",
    "wof:placetype":"venue"
},
  "geometry": {"coordinates":[7.167424202,51.182144165],"type":"Point"}
}