{
  "type": "Feature",
  "properties": {
    "iso:country":"DE",
    "sg:address":"G\u00e4nseeck 7",
    "sg:city":"R\u00f6dermark",
    "sg:phone":"+49 6074/861011",
    "sg:postcode":"63322",
    "sg:province":"Hessen",
    "wof:name":"Michael G\u00f6hring",
    "wof:placetype":"venue"
},
  "geometry": {"coordinates":[8.7976903915,49.9711799622],"type":"Point"}
}