{
  "type": "Feature",
  "properties": {
    "iso:country":"DE",
    "sg:address":"Leipziger Str. 6",
    "sg:city":"Doberlug-Kirchhain",
    "sg:postcode":"03253",
    "sg:province":"Brandenburg",
    "wof:name":"Torsten Berl",
    "wof:placetype":"venue"
},
  "geometry": {"coordinates":[13.5605,51.634304],"type":"Point"}
}