{
  "type": "Feature",
  "properties": {
    "iso:country":"DE",
    "sg:address":"Portugieser Weg 8",
    "sg:city":"Gau-Odernheim",
    "sg:postcode":"55239",
    "sg:province":"Rheinland-Pfalz",
    "wof:name":"Gdt Ges. F\u00fcr Datenver- Arbeitung Und Tele-",
    "wof:placetype":"venue"
},
  "geometry": {"coordinates":[8.1944580078,49.7793464661],"type":"Point"}
}