{
  "type": "Feature",
  "properties": {
    "iso:country":"DE",
    "sg:address":"Neue Kasseler Str. 7 a",
    "sg:city":"Marburg",
    "sg:phone":"+49 6421/682303",
    "sg:postcode":"35039",
    "sg:province":"Hessen",
    "wof:name":"I See Videotheken Gmbh & Co. Kg",
    "wof:placetype":"venue"
},
  "geometry": {"coordinates":[8.7725601196,50.8209991455],"type":"Point"}
}