{
  "type": "Feature",
  "properties": {
    "iso:country":"DE",
    "sg:address":"Uellendahler Str. 385",
    "sg:city":"Wuppertal",
    "sg:phone":"+49 202/700107",
    "sg:postcode":"42109",
    "sg:province":"Nordrhein-Westfalen",
    "wof:name":"E. Enders",
    "wof:placetype":"venue"
},
  "geometry": {"coordinates":[7.163417,51.278957],"type":"Point"}
}