{
  "type": "Feature",
  "properties": {
    "iso:country":"DE",
    "sg:address":"Eintrachtstr. 82",
    "sg:city":"Bocholt",
    "sg:phone":"+49 2871/33663",
    "sg:postcode":"46397",
    "sg:province":"Nordrhein-Westfalen",
    "wof:name":"Uhlenbrock Immobilien",
    "wof:placetype":"venue"
},
  "geometry": {"coordinates":[6.6241579056,51.8429412842],"type":"Point"}
}