{
  "type": "Feature",
  "properties": {
    "iso:country":"DE",
    "sg:address":"Lindenh\u00f6he 40",
    "sg:city":"Neuburg",
    "sg:phone":"+49 8502/445",
    "sg:postcode":"94127",
    "sg:province":"Bayern",
    "wof:name":"J\u00fcrgen Rolfs Ingenieur",
    "wof:placetype":"venue"
},
  "geometry": {"coordinates":[13.3799648285,48.5200805664],"type":"Point"}
}