{
  "type": "Feature",
  "properties": {
    "iso:country":"DE",
    "sg:address":"\u00c4u\u00dfere Leipziger Str. 1",
    "sg:city":"Schkeuditz",
    "sg:postcode":"04435",
    "sg:province":"Sachsen",
    "wof:name":"Ev. Luth. Pfarramt Schkeuditz-ost",
    "wof:placetype":"venue"
},
  "geometry": {"coordinates":[12.2213411331,51.3937301636],"type":"Point"}
}