{
  "type": "Feature",
  "properties": {
    "iso:country":"DE",
    "sg:address":"Steinstr. 9",
    "sg:city":"Korschenbroich",
    "sg:phone":"+49 2161/64544",
    "sg:postcode":"41352",
    "sg:province":"Nordrhein-Westfalen",
    "wof:name":"Helmut Konnertz",
    "wof:placetype":"venue"
},
  "geometry": {"coordinates":[6.5145540237,51.1909675598],"type":"Point"}
}