{
  "type": "Feature",
  "properties": {
    "iso:country":"DE",
    "sg:address":"Zweigertstr. 32",
    "sg:city":"Essen",
    "sg:phone":"+49 201/784310",
    "sg:postcode":"45130",
    "sg:province":"Nordrhein-Westfalen",
    "wof:name":"Gerhard Kostorz-br\u00e4utigam Rechtsanwalt Und Notar",
    "wof:placetype":"venue"
},
  "geometry": {"coordinates":[7.0014920235,51.4372138977],"type":"Point"}
}