{
  "type": "Feature",
  "properties": {
    "iso:country":"DE",
    "sg:address":"Im St\u00e4dtle 1",
    "sg:city":"Lichtenstein",
    "sg:phone":"+49 7129/4526",
    "sg:postcode":"72805",
    "sg:province":"Baden-W\u00fcrttemberg",
    "wof:name":"Krone",
    "wof:placetype":"venue"
},
  "geometry": {"coordinates":[9.275343895,48.428150177],"type":"Point"}
}