{
  "type": "Feature",
  "properties": {
    "iso:country":"DE",
    "sg:address":"Wiesenstr. 10",
    "sg:city":"Zw\u00f6nitz",
    "sg:postcode":"08297",
    "sg:province":"Sachsen",
    "wof:name":"Tbt Transport Baumaschinen Und Technik Gmbh",
    "wof:placetype":"venue"
},
  "geometry": {"coordinates":[12.799516,50.629684],"type":"Point"}
}