{
  "type": "Feature",
  "properties": {
    "iso:country":"DE",
    "sg:address":"Br\u00fcckenweg 1",
    "sg:city":"Gessertshausen",
    "sg:phone":"+49 8238/1024",
    "sg:postcode":"86459",
    "sg:province":"Bayern",
    "wof:name":"H.g. Schmid Architekt",
    "wof:placetype":"venue"
},
  "geometry": {"coordinates":[10.697603,48.315388],"type":"Point"}
}