{
  "type": "Feature",
  "properties": {
    "iso:country":"DE",
    "sg:address":"Bahnhofstr. 31",
    "sg:city":"Roth",
    "sg:phone":"+49 9171/2551",
    "sg:postcode":"91154",
    "sg:province":"Bayern",
    "wof:name":"Wolfgang Sommer",
    "wof:placetype":"venue"
},
  "geometry": {"coordinates":[11.087186,49.246475],"type":"Point"}
}