{
  "type": "Feature",
  "properties": {
    "iso:country":"DE",
    "sg:address":"Baustra\u00dfe",
    "sg:city":"Ober-Ramstadt",
    "sg:phone":"+49 6154/574652",
    "sg:postcode":"64372",
    "sg:province":"Hessen",
    "wof:name":"Informatikkaufmannn In Ihrer N\u00e4he",
    "wof:placetype":"venue"
},
  "geometry": {"coordinates":[8.745978,49.82597],"type":"Point"}
}