{
  "type": "Feature",
  "properties": {
    "iso:country":"DE",
    "sg:address":"Hauptstr. 38",
    "sg:city":"Bad Orb",
    "sg:phone":"+49 6052/2271",
    "sg:postcode":"63619",
    "sg:province":"Hessen",
    "wof:name":"L. Und A. Rieger",
    "wof:placetype":"venue"
},
  "geometry": {"coordinates":[9.348397,50.225876],"type":"Point"}
}