{
  "type": "Feature",
  "properties": {
    "iso:country":"DE",
    "sg:address":"Lindhorststr. 288",
    "sg:city":"Bottrop",
    "sg:phone":"+49 2041/52818",
    "sg:postcode":"46242",
    "sg:province":"Nordrhein-Westfalen",
    "wof:name":"O. Koth",
    "wof:placetype":"venue"
},
  "geometry": {"coordinates":[6.891043,51.528606],"type":"Point"}
}