{
  "type": "Feature",
  "properties": {
    "iso:country":"DE",
    "sg:address":"Lindenstr. 40",
    "sg:city":"Pforzheim",
    "sg:phone":"+49 7231/168980",
    "sg:postcode":"75175",
    "sg:province":"Baden-W\u00fcrttemberg",
    "wof:name":"Dixi Polytool Gmbh",
    "wof:placetype":"venue"
},
  "geometry": {"coordinates":[8.709748,48.893024],"type":"Point"}
}