{
  "type": "Feature",
  "properties": {
    "iso:country":"DE",
    "sg:address":"Pr\u00e4mienstr. 7",
    "sg:city":"Titz",
    "sg:phone":"+49 2463/6899",
    "sg:postcode":"52445",
    "sg:province":"Nordrhein-Westfalen",
    "wof:name":"Birken",
    "wof:placetype":"venue"
},
  "geometry": {"coordinates":[6.4350352287,50.9870605469],"type":"Point"}
}