{
  "type": "Feature",
  "properties": {
    "iso:country":"DE",
    "sg:address":"Kr\u00fctzpoort 10",
    "sg:city":"Krefeld",
    "sg:phone":"+49 2151/72930",
    "sg:postcode":"47804",
    "sg:province":"Nordrhein-Westfalen",
    "wof:name":"Weve Vertriebsgesellschaft F\u00fcr Porzellan Mbh",
    "wof:placetype":"venue"
},
  "geometry": {"coordinates":[6.5270428658,51.32604599],"type":"Point"}
}