{
  "type": "Feature",
  "properties": {
    "iso:country":"DE",
    "sg:address":"Baumgartenstr. 16",
    "sg:city":"Neu-Ulm",
    "sg:phone":"+49 4973/1985770",
    "sg:postcode":"89231",
    "sg:province":"Bayern",
    "wof:name":"Passigatti Giorgio Gmbh",
    "wof:placetype":"venue"
},
  "geometry": {"coordinates":[10.000897,48.386253],"type":"Point"}
}