{
  "type": "Feature",
  "properties": {
    "iso:country":"DE",
    "sg:address":"Friesenstr. 4",
    "sg:city":"Leinfelden-Echterdingen",
    "sg:phone":"+49 711/755766",
    "sg:postcode":"70771",
    "sg:province":"Baden-W\u00fcrttemberg",
    "wof:name":"W. Kalbfell",
    "wof:placetype":"venue"
},
  "geometry": {"coordinates":[9.1459321976,48.6903762817],"type":"Point"}
}