{
  "type": "Feature",
  "properties": {
    "iso:country":"DE",
    "sg:address":"Friedrichstr. 10",
    "sg:city":"Reichenbach",
    "sg:phone":"+49 7153/98260",
    "sg:postcode":"73262",
    "sg:province":"Baden-W\u00fcrttemberg",
    "wof:name":"Org-delta Gmbh",
    "wof:placetype":"venue"
},
  "geometry": {"coordinates":[9.467758,48.711418],"type":"Point"}
}