{
  "type": "Feature",
  "properties": {
    "iso:country":"DE",
    "sg:address":"Markelsbach 2",
    "sg:city":"Much",
    "sg:phone":"+49 2245/91680",
    "sg:postcode":"53804",
    "sg:province":"Nordrhein-Westfalen",
    "wof:name":"Arc Machines Gmbh",
    "wof:placetype":"venue"
},
  "geometry": {"coordinates":[7.3668141365,50.8913230896],"type":"Point"}
}