{
  "type": "Feature",
  "properties": {
    "iso:country":"DE",
    "sg:address":"Ludwigsplatz 7",
    "sg:city":"N\u00fcrnberg",
    "sg:phone":"+49 911/223723",
    "sg:postcode":"90403",
    "sg:province":"Bayern",
    "wof:name":"Der Beck Inh. Siegfried Beck",
    "wof:placetype":"venue"
},
  "geometry": {"coordinates":[11.071375,49.45063],"type":"Point"}
}