{
  "type": "Feature",
  "properties": {
    "iso:country":"DE",
    "sg:address":"Lauterbacher Str. 8",
    "sg:city":"Ortenberg",
    "sg:phone":"+49 6046/7927",
    "sg:postcode":"63683",
    "sg:province":"Hessen",
    "wof:name":"City Autovermietung Beteiligungsges. Mbh",
    "wof:placetype":"venue"
},
  "geometry": {"coordinates":[9.0530529022,50.3572807312],"type":"Point"}
}