{
  "type": "Feature",
  "properties": {
    "iso:country":"DE",
    "sg:address":"Schulenberg 9",
    "sg:city":"Prinzh\u00f6fte",
    "sg:phone":"+49 4244/7408",
    "sg:postcode":"27243",
    "sg:province":"Niedersachsen",
    "wof:name":"D. Sander",
    "wof:placetype":"venue"
},
  "geometry": {"coordinates":[8.5521793365,52.9391822815],"type":"Point"}
}