{
  "type": "Feature",
  "properties": {
    "iso:country":"DE",
    "sg:address":"F\u00fcrstenrieder Str. 109",
    "sg:city":"M\u00fcnchen",
    "sg:phone":"+49 89/565346",
    "sg:postcode":"80686",
    "sg:province":"Bayern",
    "wof:name":"Espertshuber Zlunka & Co. Gmbh",
    "wof:placetype":"venue"
},
  "geometry": {"coordinates":[11.5031070709,48.1307868958],"type":"Point"}
}