{
  "type": "Feature",
  "properties": {
    "iso:country":"DE",
    "sg:address":"Orber Str. 15",
    "sg:city":"Frankfurt",
    "sg:phone":"+49 69/42004420",
    "sg:postcode":"60386",
    "sg:province":"Hessen",
    "wof:name":"City Karosseriebau Gmbh",
    "wof:placetype":"venue"
},
  "geometry": {"coordinates":[8.76838,50.12616],"type":"Point"}
}