{
  "type": "Feature",
  "properties": {
    "iso:country":"DE",
    "sg:address":"Kaninchenborn 35",
    "sg:city":"L\u00fcbeck",
    "sg:phone":"+49 451/52585",
    "sg:postcode":"23560",
    "sg:province":"Schleswig-Holstein",
    "wof:name":"Schmill",
    "wof:placetype":"venue"
},
  "geometry": {"coordinates":[10.677539,53.844727],"type":"Point"}
}