{
  "type": "Feature",
  "properties": {
    "iso:country":"DE",
    "sg:address":"Lindenplatz 3",
    "sg:city":"Reetz",
    "sg:phone":"+49 33849/51022",
    "sg:postcode":"14827",
    "sg:province":"Brandenburg",
    "wof:name":"B. Schulze",
    "wof:placetype":"venue"
},
  "geometry": {"coordinates":[12.370595,52.110928],"type":"Point"}
}