{
  "type": "Feature",
  "properties": {
    "iso:country":"DE",
    "sg:address":"Kleine Str. 19",
    "sg:city":"Wellen",
    "sg:phone":"+49 39206/50387",
    "sg:postcode":"39167",
    "sg:province":"Sachsen-Anhalt",
    "wof:name":"Frank Rodenbeck",
    "wof:placetype":"venue"
},
  "geometry": {"coordinates":[11.444743,52.144226],"type":"Point"}
}