{
  "type": "Feature",
  "properties": {
    "iso:country":"DE",
    "sg:address":"St.Fridolinstr.11",
    "sg:city":"Haeusern",
    "sg:phone":"+49 7672/907017",
    "sg:postcode":"79837",
    "sg:province":"Baden-W\u00fcrttemberg",
    "wof:name":"Herzlich Willkommen Im Hotel Waldeck",
    "wof:placetype":"venue"
},
  "geometry": {"coordinates":[8.1679487228,47.7520980835],"type":"Point"}
}