{
  "type": "Feature",
  "properties": {
    "iso:country":"DE",
    "sg:address":"Dorfstr. 4a",
    "sg:city":"Sch\u00f6nefeld",
    "sg:postcode":"12529",
    "sg:province":"Brandenburg",
    "wof:name":"Evangelisches Pfarramt",
    "wof:placetype":"venue"
},
  "geometry": {"coordinates":[13.4612197876,52.3738212585],"type":"Point"}
}