{
  "type": "Feature",
  "properties": {
    "iso:country":"DE",
    "sg:address":"Kelterstr 8",
    "sg:city":"Bempflingen",
    "sg:phone":"+49 7123/367374",
    "sg:postcode":"72658",
    "sg:province":"Baden-W\u00fcrttemberg",
    "wof:name":"Geo Tec Messtechnik J\u00fcrgen Emslander",
    "wof:placetype":"venue"
},
  "geometry": {"coordinates":[9.264042,48.571362],"type":"Point"}
}