{
  "type": "Feature",
  "properties": {
    "iso:country":"DE",
    "sg:address":"Margaretenweg 6",
    "sg:city":"Ludwigsburg",
    "sg:phone":"+49 7141/24571",
    "sg:postcode":"71640",
    "sg:province":"Baden-W\u00fcrttemberg",
    "wof:name":"Ilse Striffler-trentini",
    "wof:placetype":"venue"
},
  "geometry": {"coordinates":[9.222784996,48.8944854736],"type":"Point"}
}