{
  "type": "Feature",
  "properties": {
    "iso:country":"DE",
    "sg:address":"S\u00e4gm\u00fchle 1",
    "sg:city":"Herrenberg",
    "sg:phone":"+49 7032/9730",
    "sg:postcode":"71083",
    "sg:province":"Baden-W\u00fcrttemberg",
    "wof:name":"Abbundzentrum Sch\u00f6nbuch Gmbh",
    "wof:placetype":"venue"
},
  "geometry": {"coordinates":[8.8963775635,48.5668640137],"type":"Point"}
}