{
  "type": "Feature",
  "properties": {
    "iso:country":"DE",
    "sg:address":"Theaterplatz 13",
    "sg:city":"Bonn",
    "sg:phone":"+49 228/353335",
    "sg:postcode":"53177",
    "sg:province":"Nordrhein-Westfalen",
    "wof:name":"Kurpark-apotheke",
    "wof:placetype":"venue"
},
  "geometry": {"coordinates":[7.152852,50.682884],"type":"Point"}
}