{
  "type": "Feature",
  "properties": {
    "iso:country":"DE",
    "sg:address":"Bergstr. 59",
    "sg:city":"Dortmund",
    "sg:phone":"+49 231/851707",
    "sg:postcode":"44339",
    "sg:province":"Nordrhein-Westfalen",
    "wof:name":"Fritz Wolf M",
    "wof:placetype":"venue"
},
  "geometry": {"coordinates":[7.4552268982,51.5512466431],"type":"Point"}
}