{
  "type": "Feature",
  "properties": {
    "iso:country":"DE",
    "sg:city":"Petershausen",
    "sg:phone":"+49 8137/5330",
    "sg:postcode":"85238",
    "sg:province":"Bayern",
    "wof:name":"Raiffeisenbank Jetzendorf-petersh.",
    "wof:placetype":"venue"
},
  "geometry": {"coordinates":[11.467917,48.407848],"type":"Point"}
}