{
  "type": "Feature",
  "properties": {
    "iso:country":"DE",
    "sg:address":"Stickenb\u00fctteler Weg 8",
    "sg:city":"Cuxhaven",
    "sg:phone":"+49 4721/48406",
    "sg:postcode":"27476",
    "sg:province":"Niedersachsen",
    "wof:name":"Heinz Bender",
    "wof:placetype":"venue"
},
  "geometry": {"coordinates":[8.671538353,53.8811607361],"type":"Point"}
}