{
  "type": "Feature",
  "properties": {
    "iso:country":"DE",
    "sg:address":"Hammer Landstr. 83",
    "sg:city":"Neuss",
    "sg:phone":"+49 2131/102050",
    "sg:postcode":"41460",
    "sg:province":"Nordrhein-Westfalen",
    "wof:name":"Heinemann Automobile Gmbh",
    "wof:placetype":"venue"
},
  "geometry": {"coordinates":[6.7121682167,51.2027053833],"type":"Point"}
}