{
  "type": "Feature",
  "properties": {
    "iso:country":"DE",
    "sg:address":"Franz-Lenze-Platz",
    "sg:city":"Duisburg",
    "sg:postcode":"47178",
    "sg:province":"Nordrhein-Westfalen",
    "wof:name":"Edeka-markt Luft",
    "wof:placetype":"venue"
},
  "geometry": {"coordinates":[6.7253680229,51.5354957581],"type":"Point"}
}