{
  "type": "Feature",
  "properties": {
    "iso:country":"DE",
    "sg:address":"B\u00fcrgermeister-Widmeier-Str. 42",
    "sg:city":"Augsburg",
    "sg:phone":"+49 821/84800",
    "sg:postcode":"86179",
    "sg:province":"Bayern",
    "wof:name":"Billard Instroke",
    "wof:placetype":"venue"
},
  "geometry": {"coordinates":[10.9103546143,48.313369751],"type":"Point"}
}