{
  "type": "Feature",
  "properties": {
    "iso:country":"DE",
    "sg:address":"Merziger Str. 17",
    "sg:city":"Losheim",
    "sg:phone":"+49 6872/993118",
    "sg:postcode":"66679",
    "sg:province":"Saarland",
    "wof:name":"H.-w. M\u00fcller Architekt",
    "wof:placetype":"venue"
},
  "geometry": {"coordinates":[6.742725,49.50729],"type":"Point"}
}