{
  "type": "Feature",
  "properties": {
    "iso:country":"DE",
    "sg:address":"Markscheffelshof 10",
    "sg:city":"Eisenach",
    "sg:phone":"+49 3691/746069",
    "sg:postcode":"99817",
    "sg:province":"Th\u00fcringen",
    "wof:name":"Klaus Eickermann Immobilien Gmbh",
    "wof:placetype":"venue"
},
  "geometry": {"coordinates":[10.3222999573,50.9756355286],"type":"Point"}
}