{
  "type": "Feature",
  "properties": {
    "iso:country":"DE",
    "sg:address":"Wormser Str. 12",
    "sg:city":"Mannheim",
    "sg:phone":"+49 621/724219",
    "sg:postcode":"68309",
    "sg:province":"Baden-W\u00fcrttemberg",
    "wof:name":"K\u00e4fertaler Stubb",
    "wof:placetype":"venue"
},
  "geometry": {"coordinates":[8.5171098709,49.5133972168],"type":"Point"}
}