{
  "type": "Feature",
  "properties": {
    "iso:country":"DE",
    "sg:address":"Innere Schneeberger Str. 11",
    "sg:city":"Zwickau",
    "sg:phone":"+49 375/270890",
    "sg:postcode":"08056",
    "sg:province":"Sachsen",
    "wof:name":"Heiztec Gmbh",
    "wof:placetype":"venue"
},
  "geometry": {"coordinates":[12.4973506927,50.7167854309],"type":"Point"}
}