{
  "type": "Feature",
  "properties": {
    "iso:country":"DE",
    "sg:address":"Bergstr. 13",
    "sg:city":"Moschheim",
    "sg:phone":"+49 2602/70194",
    "sg:postcode":"56424",
    "sg:province":"Rheinland-Pfalz",
    "wof:name":"Gabriele Hilb",
    "wof:placetype":"venue"
},
  "geometry": {"coordinates":[7.8396430016,50.4766311646],"type":"Point"}
}