{
  "type": "Feature",
  "properties": {
    "iso:country":"DE",
    "sg:address":"Wilhelm-Zinn-Str. 6",
    "sg:city":"Schweinfurt",
    "sg:phone":"+49 9721/42806",
    "sg:postcode":"97424",
    "sg:province":"Bayern",
    "wof:name":"Egs Diskotheken Verwaltungs Gmbh",
    "wof:placetype":"venue"
},
  "geometry": {"coordinates":[10.2148418427,50.0593719482],"type":"Point"}
}