{
  "type": "Feature",
  "properties": {
    "iso:country":"DE",
    "sg:address":"Bergerhof 4",
    "sg:city":"Leichlingen",
    "sg:phone":"+49 2175/3854",
    "sg:postcode":"42799",
    "sg:province":"Nordrhein-Westfalen",
    "wof:name":"Kron Gmbh & Stirl Maschinenbau Kg",
    "wof:placetype":"venue"
},
  "geometry": {"coordinates":[7.014544,51.105412],"type":"Point"}
}