{
  "type": "Feature",
  "properties": {
    "iso:country":"DE",
    "sg:address":"Haydnstr. 4",
    "sg:city":"M\u00fchlheim",
    "sg:phone":"+49 7463/5255",
    "sg:postcode":"78570",
    "sg:province":"Baden-W\u00fcrttemberg",
    "wof:name":"Ulrich Und Karin Finckh",
    "wof:placetype":"venue"
},
  "geometry": {"coordinates":[8.881911,48.028446],"type":"Point"}
}