{
  "type": "Feature",
  "properties": {
    "iso:country":"DE",
    "sg:address":"Beginenstr. 1",
    "sg:city":"Bensheim",
    "sg:postcode":"64625",
    "sg:province":"Hessen",
    "wof:name":"Mosaik E. Kfr.",
    "wof:placetype":"venue"
},
  "geometry": {"coordinates":[8.61309,49.687008],"type":"Point"}
}