{
  "type": "Feature",
  "properties": {
    "iso:country":"DE",
    "sg:address":"Titlmoos 42",
    "sg:city":"Babensham",
    "sg:phone":"+49 8074/590",
    "sg:postcode":"83547",
    "sg:province":"Bayern",
    "wof:name":"Werner Kniebes",
    "wof:placetype":"venue"
},
  "geometry": {"coordinates":[12.3782110214,48.112701416],"type":"Point"}
}