{
  "type": "Feature",
  "properties": {
    "iso:country":"DE",
    "sg:address":"Am Flurdenkmal 13",
    "sg:city":"Sontheim",
    "sg:phone":"+49 8336/7091",
    "sg:postcode":"87776",
    "sg:province":"Bayern",
    "wof:name":"Alfons Koller",
    "wof:placetype":"venue"
},
  "geometry": {"coordinates":[10.3424291611,47.9920539856],"type":"Point"}
}