{
  "type": "Feature",
  "properties": {
    "iso:country":"DE",
    "sg:address":"Auweg 4",
    "sg:city":"Wenzenbach",
    "sg:phone":"+49 9407",
    "sg:postcode":"93173",
    "sg:province":"Bayern",
    "wof:name":"Stock-car-club Gr\u00fcnthal E.v.",
    "wof:placetype":"venue"
},
  "geometry": {"coordinates":[12.161609,49.056637],"type":"Point"}
}