{
  "type": "Feature",
  "properties": {
    "iso:country":"DE",
    "sg:address":"Grabenstr. 24",
    "sg:city":"Eschweiler",
    "sg:phone":"+49 2403/1678",
    "sg:postcode":"52249",
    "sg:province":"Nordrhein-Westfalen",
    "wof:name":"Rechtsanwaltskanzlei Steinorr Wunderlich U.kollegen",
    "wof:placetype":"venue"
},
  "geometry": {"coordinates":[6.2676382065,50.8197631836],"type":"Point"}
}