{
  "type": "Feature",
  "properties": {
    "iso:country":"DE",
    "sg:address":"Querental 1",
    "sg:city":"D\u00f6rentrup",
    "sg:phone":"+49 5265/6342",
    "sg:postcode":"32694",
    "sg:province":"Nordrhein-Westfalen",
    "wof:name":"Martin Corbach",
    "wof:placetype":"venue"
},
  "geometry": {"coordinates":[9.070734,52.027336],"type":"Point"}
}