{
  "type": "Feature",
  "properties": {
    "iso:country":"DE",
    "sg:address":"Schorndorfer Str. 5",
    "sg:city":"Weinstadt",
    "sg:phone":"+49 7151/600072",
    "sg:postcode":"71384",
    "sg:province":"Baden-W\u00fcrttemberg",
    "wof:name":"Metallbearbeitung Weigert",
    "wof:placetype":"venue"
},
  "geometry": {"coordinates":[9.36786,48.814137],"type":"Point"}
}