{
  "type": "Feature",
  "properties": {
    "iso:country":"DE",
    "sg:address":"Darmst\u00e4dter Landstr. 62",
    "sg:city":"Frankfurt",
    "sg:phone":"+49 69/6090000",
    "sg:postcode":"60598",
    "sg:province":"Hessen",
    "wof:name":"Trendreisen Gmbh",
    "wof:placetype":"venue"
},
  "geometry": {"coordinates":[8.6908607483,50.1015586853],"type":"Point"}
}