{
  "type": "Feature",
  "properties": {
    "iso:country":"DE",
    "sg:address":"Ostfeldstr. 8 a",
    "sg:city":"Bad Heilbrunn",
    "sg:phone":"+49 8046/9400",
    "sg:postcode":"83670",
    "sg:province":"Bayern",
    "wof:name":"G. Mohr",
    "wof:placetype":"venue"
},
  "geometry": {"coordinates":[11.4713392258,47.747051239],"type":"Point"}
}