{
  "type": "Feature",
  "properties": {
    "iso:country":"DE",
    "sg:address":"Geschwister-Scholl-Str. 24",
    "sg:city":"Hessisch Lichtenau",
    "sg:phone":"+49 5602/5741",
    "sg:postcode":"37235",
    "sg:province":"Hessen",
    "wof:name":"Reiner Heller",
    "wof:placetype":"venue"
},
  "geometry": {"coordinates":[9.7124938965,51.2050209045],"type":"Point"}
}