{
  "type": "Feature",
  "properties": {
    "iso:country":"DE",
    "sg:address":"Spessartstr. 14",
    "sg:city":"Hagen",
    "sg:phone":"+49 2331/53570",
    "sg:postcode":"58093",
    "sg:province":"Nordrhein-Westfalen",
    "wof:name":"R. Haase Steuerberater",
    "wof:placetype":"venue"
},
  "geometry": {"coordinates":[7.5100030899,51.3720588684],"type":"Point"}
}