{
  "type": "Feature",
  "properties": {
    "iso:country":"DE",
    "sg:address":"Wilhelm-Raabe-Str. 15",
    "sg:city":"Garbsen",
    "sg:phone":"+49 5131/2860",
    "sg:postcode":"30826",
    "sg:province":"Niedersachsen",
    "wof:name":"Osman Altiner Architekt",
    "wof:placetype":"venue"
},
  "geometry": {"coordinates":[9.578976,52.440029],"type":"Point"}
}