{
  "type": "Feature",
  "properties": {
    "iso:country":"DE",
    "sg:address":"Neu\u00f6ttinger Str. 36",
    "sg:city":"Winh\u00f6ring",
    "sg:postcode":"84543",
    "sg:province":"Bayern",
    "wof:name":"G\u00fcnther Gruber Gmbh",
    "wof:placetype":"venue"
},
  "geometry": {"coordinates":[12.65659,48.263275],"type":"Point"}
}