{
  "type": "Feature",
  "properties": {
    "iso:country":"DE",
    "sg:address":"Spitzstr. 1",
    "sg:city":"Burgau",
    "sg:phone":"+49 8222/960933",
    "sg:postcode":"89331",
    "sg:province":"Bayern",
    "wof:name":"Hallenschwimmbad",
    "wof:placetype":"venue"
},
  "geometry": {"coordinates":[10.4033288956,48.4252700806],"type":"Point"}
}