{
  "type": "Feature",
  "properties": {
    "iso:country":"DE",
    "sg:address":"Heideckstr. 12",
    "sg:city":"M\u00fcnchen",
    "sg:phone":"+49 89/153819",
    "sg:postcode":"80637",
    "sg:province":"Bayern",
    "wof:name":"Aeroplan",
    "wof:placetype":"venue"
},
  "geometry": {"coordinates":[11.5407896042,48.1619796753],"type":"Point"}
}