{
  "type": "Feature",
  "properties": {
    "iso:country":"DE",
    "sg:address":"Auf dem Spann 15",
    "sg:city":"Schneverdingen",
    "sg:phone":"+49 5193/6431",
    "sg:postcode":"29640",
    "sg:province":"Niedersachsen",
    "wof:name":"J\u00fcrgen R\u00f6hrs",
    "wof:placetype":"venue"
},
  "geometry": {"coordinates":[9.81049,53.063869],"type":"Point"}
}