{
  "type": "Feature",
  "properties": {
    "iso:country":"DE",
    "sg:address":"Alexanderstr. 3",
    "sg:city":"Hannover",
    "sg:phone":"+49 511/321093",
    "sg:postcode":"30159",
    "sg:province":"Niedersachsen",
    "wof:name":"Zach\u00e4us Hausverwaltung Inh. G. Usinger",
    "wof:placetype":"venue"
},
  "geometry": {"coordinates":[9.7450218201,52.3735427856],"type":"Point"}
}