{
  "type": "Feature",
  "properties": {
    "iso:country":"DE",
    "sg:address":"Maximiliansplatz 18",
    "sg:city":"M\u00fcnchen",
    "sg:phone":"+49 89/226654",
    "sg:postcode":"80333",
    "sg:province":"Bayern",
    "wof:name":"Dr. Achim Neumeister Rechtsanwalt",
    "wof:placetype":"venue"
},
  "geometry": {"coordinates":[11.5712738037,48.1416015625],"type":"Point"}
}