{
  "type": "Feature",
  "properties": {
    "iso:country":"DE",
    "sg:address":"Kreuzstr. 38",
    "sg:city":"Bielefeld",
    "sg:phone":"+49 521/172434",
    "sg:postcode":"33602",
    "sg:province":"Nordrhein-Westfalen",
    "wof:name":"Bibliothek Des Naturwissenschaftlichen",
    "wof:placetype":"venue"
},
  "geometry": {"coordinates":[8.52559,52.017288],"type":"Point"}
}