{
  "type": "Feature",
  "properties": {
    "iso:country":"DE",
    "sg:address":"Waltroper Str. 5",
    "sg:city":"L\u00fcnen",
    "sg:phone":"+49 231/870344",
    "sg:postcode":"44536",
    "sg:province":"Nordrhein-Westfalen",
    "wof:name":"G. Haupt Fleischerei-betrieb Einzelh.m. Ver. Lebensmitteln",
    "wof:placetype":"venue"
},
  "geometry": {"coordinates":[7.4389038086,51.5959777832],"type":"Point"}
}