{
  "type": "Feature",
  "properties": {
    "iso:country":"DE",
    "sg:address":"Siebengebirgsweg 30",
    "sg:city":"Remagen",
    "sg:phone":"+49 2228/8257",
    "sg:postcode":"53424",
    "sg:province":"Rheinland-Pfalz",
    "wof:name":"Detlef Schnitzer",
    "wof:placetype":"venue"
},
  "geometry": {"coordinates":[7.205997,50.606716],"type":"Point"}
}