{
  "type": "Feature",
  "properties": {
    "iso:country":"DE",
    "sg:address":"Waldburgstr. 5",
    "sg:city":"Oberstdorf",
    "sg:phone":"+49 8322/2590",
    "sg:postcode":"87561",
    "sg:province":"Bayern",
    "wof:name":"G\u00e4stehaus Walter Renn",
    "wof:placetype":"venue"
},
  "geometry": {"coordinates":[10.277973175,47.4140510559],"type":"Point"}
}