{
  "type": "Feature",
  "properties": {
    "iso:country":"DE",
    "sg:address":"Reinkenortstr. 95",
    "sg:city":"B\u00fcnde",
    "sg:phone":"+49 5223/71200",
    "sg:postcode":"32257",
    "sg:province":"Nordrhein-Westfalen",
    "wof:name":"Heinrich Obermark",
    "wof:placetype":"venue"
},
  "geometry": {"coordinates":[8.614461,52.218529],"type":"Point"}
}