{
  "type": "Feature",
  "properties": {
    "iso:country":"DE",
    "sg:address":"Bettinastra\u00dfe 35-37",
    "sg:city":"Frankfurt",
    "sg:phone":"+49 69/7561210",
    "sg:postcode":"60325",
    "sg:province":"Hessen",
    "wof:name":"Mpk Rechtsanw\u00e4lte Frankfurt",
    "wof:placetype":"venue"
},
  "geometry": {"coordinates":[8.65925,50.111858],"type":"Point"}
}