{
  "type": "Feature",
  "properties": {
    "iso:country":"DE",
    "sg:address":"Bergstrasse 21",
    "sg:city":"Nideggen-Schmidt",
    "sg:phone":"+49 2474/993862",
    "sg:postcode":"52385",
    "sg:province":"Nordrhein-Westfalen",
    "wof:name":"Das Teel\u00e4dchen",
    "wof:placetype":"venue"
},
  "geometry": {"coordinates":[6.410277,50.657082],"type":"Point"}
}