{
  "type": "Feature",
  "properties": {
    "iso:country":"DE",
    "sg:address":"Blasiusstr. 3",
    "sg:city":"D\u00fcsseldorf",
    "sg:phone":"+49 211/304614",
    "sg:postcode":"40221",
    "sg:province":"Nordrhein-Westfalen",
    "wof:name":"Konrad Br\u00e4mswig",
    "wof:placetype":"venue"
},
  "geometry": {"coordinates":[6.739425,51.208012],"type":"Point"}
}