{
  "type": "Feature",
  "properties": {
    "iso:country":"DE",
    "sg:address":"Bad Segeberger Str. 14",
    "sg:city":"Teterow",
    "sg:phone":"+49 3996/173171",
    "sg:postcode":"17166",
    "sg:province":"Mecklenburg-Vorpommern",
    "wof:name":"H. H\u00fcbner Immobilienmakler",
    "wof:placetype":"venue"
},
  "geometry": {"coordinates":[12.5828752518,53.7720108032],"type":"Point"}
}