{
  "type": "Feature",
  "properties": {
    "iso:country":"DE",
    "sg:address":"Niederstr. 46",
    "sg:city":"Monheim",
    "sg:phone":"+49 2173/51279",
    "sg:postcode":"40789",
    "sg:province":"Nordrhein-Westfalen",
    "wof:name":"Bernhard Krutwig",
    "wof:placetype":"venue"
},
  "geometry": {"coordinates":[6.891891,51.099304],"type":"Point"}
}