{
  "type": "Feature",
  "properties": {
    "iso:country":"DE",
    "sg:address":"Bahnhofstr. 11",
    "sg:city":"Gnarrenburg",
    "sg:postcode":"27442",
    "sg:province":"Niedersachsen",
    "wof:name":"Aldi Gmbh & Co. Kg",
    "wof:placetype":"venue"
},
  "geometry": {"coordinates":[9.0070457458,53.3816261292],"type":"Point"}
}