{
  "type": "Feature",
  "properties": {
    "iso:country":"DE",
    "sg:address":"Panoramastr. 1",
    "sg:city":"Reichelsheim",
    "sg:postcode":"64385",
    "sg:province":"Hessen",
    "wof:name":"Netteck Gmbh",
    "wof:placetype":"venue"
},
  "geometry": {"coordinates":[8.827857,49.709049],"type":"Point"}
}