{
  "type": "Feature",
  "properties": {
    "iso:country":"DE",
    "sg:address":"Arendseer Str.",
    "sg:city":"Seehausen",
    "sg:postcode":"39615",
    "sg:province":"Sachsen-Anhalt",
    "wof:name":"Aldi Gmbh & Co. Kg",
    "wof:placetype":"venue"
},
  "geometry": {"coordinates":[11.7439851761,52.8889465332],"type":"Point"}
}