{
  "type": "Feature",
  "properties": {
    "iso:country":"DE",
    "sg:address":"Zeppelinstr. 5 /1",
    "sg:city":"Ofterdingen",
    "sg:phone":"+49 7473/1849",
    "sg:postcode":"72131",
    "sg:province":"Baden-W\u00fcrttemberg",
    "wof:name":"Karl-martin Dreher",
    "wof:placetype":"venue"
},
  "geometry": {"coordinates":[9.034131,48.41806],"type":"Point"}
}