{
  "type": "Feature",
  "properties": {
    "iso:country":"DE",
    "sg:address":"Lange Str. 8",
    "sg:city":"Grimmen",
    "sg:phone":"+49 38326/2145",
    "sg:postcode":"18507",
    "sg:province":"Mecklenburg-Vorpommern",
    "wof:name":"Reinhard Hinz",
    "wof:placetype":"venue"
},
  "geometry": {"coordinates":[13.045006,54.1133],"type":"Point"}
}