{
  "type": "Feature",
  "properties": {
    "iso:country":"DE",
    "sg:address":"Lindenstr. 11",
    "sg:city":"H\u00fcttenberg",
    "sg:phone":"+49 6403/2905",
    "sg:postcode":"35625",
    "sg:province":"Hessen",
    "wof:name":"W. Best",
    "wof:placetype":"venue"
},
  "geometry": {"coordinates":[8.622921,50.510113],"type":"Point"}
}