{
  "type": "Feature",
  "properties": {
    "iso:country":"DE",
    "sg:address":"Sydowstr. 2",
    "sg:city":"Timmendorfer Strand",
    "sg:phone":"+49 4503/891866",
    "sg:postcode":"23669",
    "sg:province":"Schleswig-Holstein",
    "wof:name":"Gerd Hargus",
    "wof:placetype":"venue"
},
  "geometry": {"coordinates":[10.8328113556,53.9914741516],"type":"Point"}
}