{
  "type": "Feature",
  "properties": {
    "iso:country":"DE",
    "sg:address":"Am Alten Sportplatz 20",
    "sg:city":"Kehl",
    "sg:phone":"+49 7851/2981",
    "sg:postcode":"77694",
    "sg:province":"Baden-W\u00fcrttemberg",
    "wof:name":"Bkm Baustoffe Auer",
    "wof:placetype":"venue"
},
  "geometry": {"coordinates":[7.825583,48.569363],"type":"Point"}
}