{
  "type": "Feature",
  "properties": {
    "iso:country":"DE",
    "sg:address":"Mainzer Str. 110",
    "sg:city":"Kaiserslautern",
    "sg:phone":"+49 631/40548",
    "sg:postcode":"67657",
    "sg:province":"Rheinland-Pfalz",
    "wof:name":"Heimburger",
    "wof:placetype":"venue"
},
  "geometry": {"coordinates":[7.792113781,49.4537887573],"type":"Point"}
}