{
  "type": "Feature",
  "properties": {
    "iso:country":"DE",
    "sg:address":"Pilgersheimer Str. 50",
    "sg:city":"M\u00fcnchen",
    "sg:postcode":"81543",
    "sg:province":"Bayern",
    "wof:name":"Behindertenwerkstatt",
    "wof:placetype":"venue"
},
  "geometry": {"coordinates":[11.572435,48.115143],"type":"Point"}
}