{
  "type": "Feature",
  "properties": {
    "iso:country":"DE",
    "sg:address":"Breiter B\u00f6ren 22",
    "sg:city":"Rinteln",
    "sg:postcode":"31737",
    "sg:province":"Niedersachsen",
    "wof:name":"Gefl\u00fcgelzuchtverein F\u00fcr Rinteln Und Umgebung",
    "wof:placetype":"venue"
},
  "geometry": {"coordinates":[9.0304193497,52.1576538086],"type":"Point"}
}