{
  "type": "Feature",
  "properties": {
    "iso:country":"DE",
    "sg:address":"Schuhmacherstr. 9",
    "sg:city":"Kiel",
    "sg:phone":"+49 431/93050",
    "sg:postcode":"24103",
    "sg:province":"Schleswig-Holstein",
    "wof:name":"C. F. Dela Gmbh & Co. Kg",
    "wof:placetype":"venue"
},
  "geometry": {"coordinates":[10.14069,54.322414],"type":"Point"}
}