{
  "type": "Feature",
  "properties": {
    "iso:country":"DE",
    "sg:address":"Hirschstr. 18",
    "sg:city":"Baindt",
    "sg:phone":"+49 7502/1653",
    "sg:postcode":"88255",
    "sg:province":"Baden-W\u00fcrttemberg",
    "wof:name":"W. Knittel Ingenieur",
    "wof:placetype":"venue"
},
  "geometry": {"coordinates":[9.659412384,47.8473968506],"type":"Point"}
}