{
  "type": "Feature",
  "properties": {
    "iso:country":"DE",
    "sg:address":"Kunstm\u00fchlestr. 43",
    "sg:city":"Pfullingen",
    "sg:phone":"+49 7121/79747",
    "sg:postcode":"72793",
    "sg:province":"Baden-W\u00fcrttemberg",
    "wof:name":"Containerdienst B\u00e4chtle",
    "wof:placetype":"venue"
},
  "geometry": {"coordinates":[9.22301,48.47258],"type":"Point"}
}