{
  "type": "Feature",
  "properties": {
    "iso:country":"DE",
    "sg:address":"Pfarrer-Kneipp-Str. 14",
    "sg:city":"Dortmund",
    "sg:postcode":"44141",
    "sg:province":"Nordrhein-Westfalen",
    "wof:name":"Itb-gmbh",
    "wof:placetype":"venue"
},
  "geometry": {"coordinates":[7.5163960457,51.5048980713],"type":"Point"}
}