{
  "type": "Feature",
  "properties": {
    "iso:country":"DE",
    "sg:address":"Schwere-Reiter-Str. 35 Gbd. 14",
    "sg:city":"M\u00fcnchen",
    "sg:phone":"+49 89/3000910",
    "sg:postcode":"80797",
    "sg:province":"Bayern",
    "wof:name":"Linx Crossmarketing Gmbh",
    "wof:placetype":"venue"
},
  "geometry": {"coordinates":[11.5562801361,48.1608085632],"type":"Point"}
}