{
  "type": "Feature",
  "properties": {
    "iso:country":"DE",
    "sg:address":"Bismarckstr. 210",
    "sg:city":"Gelsenkirchen",
    "sg:phone":"+49 209/872277",
    "sg:postcode":"45889",
    "sg:province":"Nordrhein-Westfalen",
    "wof:name":"M. Gegek",
    "wof:placetype":"venue"
},
  "geometry": {"coordinates":[7.1063718796,51.5264663696],"type":"Point"}
}