{
  "type": "Feature",
  "properties": {
    "iso:country":"DE",
    "sg:address":"Landwehrstr. 26",
    "sg:city":"Rot am See",
    "sg:phone":"+49 7955/2311",
    "sg:postcode":"74585",
    "sg:province":"Baden-W\u00fcrttemberg",
    "wof:name":"Textil-braun Ohg",
    "wof:placetype":"venue"
},
  "geometry": {"coordinates":[10.084005,49.278683],"type":"Point"}
}