{
  "type": "Feature",
  "properties": {
    "iso:country":"DE",
    "sg:address":"Uelversheimer Str. 4",
    "sg:city":"Weinolsheim",
    "sg:phone":"+49 6249/2228",
    "sg:postcode":"55278",
    "sg:province":"Rheinland-Pfalz",
    "wof:name":"Hans-ernst Gr\u00f6hl",
    "wof:placetype":"venue"
},
  "geometry": {"coordinates":[8.2744693756,49.8142127991],"type":"Point"}
}