{
  "type": "Feature",
  "properties": {
    "iso:country":"DE",
    "sg:address":"Bl\u00f6tter Weg 185",
    "sg:city":"M\u00fclheim",
    "sg:phone":"+49 208/51810",
    "sg:postcode":"45478",
    "sg:province":"Nordrhein-Westfalen",
    "wof:name":"Kh Mode & Sport Gmbh",
    "wof:placetype":"venue"
},
  "geometry": {"coordinates":[6.8244328499,51.4198455811],"type":"Point"}
}