{
  "type": "Feature",
  "properties": {
    "iso:country":"DE",
    "sg:address":"Zimmert",
    "sg:city":"Rieseby",
    "sg:phone":"+49 4355/458",
    "sg:postcode":"24354",
    "sg:province":"Schleswig-Holstein",
    "wof:name":"Wanda Kuhl",
    "wof:placetype":"venue"
},
  "geometry": {"coordinates":[9.8616895676,54.5606002808],"type":"Point"}
}