{
  "type": "Feature",
  "properties": {
    "iso:country":"DE",
    "sg:address":"Heisenbergstr 55/57",
    "sg:city":"Kerpen",
    "sg:phone":"+49 2237/973040",
    "sg:postcode":"50169",
    "sg:province":"Nordrhein-Westfalen",
    "wof:name":"Gottfried Schmalfuss Gmbh",
    "wof:placetype":"venue"
},
  "geometry": {"coordinates":[6.746522,50.870476],"type":"Point"}
}