{
  "type": "Feature",
  "properties": {
    "iso:country":"DE",
    "sg:address":"Julienstr. 28",
    "sg:city":"Essen",
    "sg:phone":"+49 201/794455",
    "sg:postcode":"45130",
    "sg:province":"Nordrhein-Westfalen",
    "wof:name":"Thomas Draheim Wein- Und Glashandel Kg",
    "wof:placetype":"venue"
},
  "geometry": {"coordinates":[7.0093588829,51.4366378784],"type":"Point"}
}