{
  "type": "Feature",
  "properties": {
    "iso:country":"DE",
    "sg:address":"Heinrich-G\u00f6ding-Str. 49",
    "sg:city":"Augustusburg",
    "sg:phone":"+49 37291/69229",
    "sg:postcode":"09573",
    "sg:province":"Sachsen",
    "wof:name":"Petra P\u00fcrschel",
    "wof:placetype":"venue"
},
  "geometry": {"coordinates":[13.105174,50.804211],"type":"Point"}
}