{
  "type": "Feature",
  "properties": {
    "iso:country":"DE",
    "sg:address":"Am Hohen Feld 30",
    "sg:city":"Hamburg",
    "sg:phone":"+49 40/6535574",
    "sg:postcode":"22043",
    "sg:province":"Hamburg",
    "wof:name":"Interkeram Horst Herm. Krause",
    "wof:placetype":"venue"
},
  "geometry": {"coordinates":[10.1155757904,53.5713539124],"type":"Point"}
}