{
  "type": "Feature",
  "properties": {
    "iso:country":"DE",
    "sg:address":"F\u00fcrstenzeller Str. 20",
    "sg:city":"Ortenburg",
    "sg:phone":"+49 8542/7302",
    "sg:postcode":"94496",
    "sg:province":"Bayern",
    "wof:name":"Erich Dobler",
    "wof:placetype":"venue"
},
  "geometry": {"coordinates":[13.2242259979,48.541847229],"type":"Point"}
}