{
  "type": "Feature",
  "properties": {
    "iso:country":"DE",
    "sg:address":"Hauptmannstr. 14",
    "sg:city":"Dresden",
    "sg:postcode":"01139",
    "sg:province":"Sachsen",
    "wof:name":"H & N Immobilien Management Gmbh",
    "wof:placetype":"venue"
},
  "geometry": {"coordinates":[13.705722,51.080589],"type":"Point"}
}