{
  "type": "Feature",
  "properties": {
    "iso:country":"DE",
    "sg:address":"Hauptstr. 29",
    "sg:city":"Burgwald",
    "sg:phone":"+49 6451/8329",
    "sg:postcode":"35099",
    "sg:province":"Hessen",
    "wof:name":"Fleischerei Klotz Gmbh",
    "wof:placetype":"venue"
},
  "geometry": {"coordinates":[8.7574138641,51.0195388794],"type":"Point"}
}