{
  "type": "Feature",
  "properties": {
    "iso:country":"DE",
    "sg:address":"Bromberger Str. 22",
    "sg:city":"Wuppertal",
    "sg:phone":"+49 202/504888",
    "sg:postcode":"42283",
    "sg:province":"Nordrhein-Westfalen",
    "wof:name":"Eckhard Hammig",
    "wof:placetype":"venue"
},
  "geometry": {"coordinates":[7.1854190826,51.276927948],"type":"Point"}
}