{
  "type": "Feature",
  "properties": {
    "iso:country":"DE",
    "sg:address":"Bahnhofstr. 13",
    "sg:city":"Garding",
    "sg:postcode":"25836",
    "sg:province":"Schleswig-Holstein",
    "wof:name":"Media Profiles Gmbh",
    "wof:placetype":"venue"
},
  "geometry": {"coordinates":[8.7840490341,54.3274536133],"type":"Point"}
}