{
  "type": "Feature",
  "properties": {
    "iso:country":"DE",
    "sg:address":"Moosweg 4",
    "sg:city":"Affing",
    "sg:phone":"+49 8207/1742",
    "sg:postcode":"86444",
    "sg:province":"Bayern",
    "wof:name":"Anton Jemiller Baugeesch\u00e4ft Gmbh",
    "wof:placetype":"venue"
},
  "geometry": {"coordinates":[10.983436,48.45686],"type":"Point"}
}