{
  "type": "Feature",
  "properties": {
    "iso:country":"DE",
    "sg:address":"Simmelsdorfer Str. 7",
    "sg:city":"Simmelsdorf",
    "sg:phone":"+49 9155/816",
    "sg:postcode":"91245",
    "sg:province":"Bayern",
    "wof:name":"Ev. Pfarramt Gem. Sb. Helena Zu Grossengsee",
    "wof:placetype":"venue"
},
  "geometry": {"coordinates":[11.3569383621,49.6374893188],"type":"Point"}
}