{
  "type": "Feature",
  "properties": {
    "iso:country":"DE",
    "sg:address":"Talstr. 17",
    "sg:city":"Freiberg",
    "sg:phone":"+49 7141/72661",
    "sg:postcode":"71691",
    "sg:province":"Baden-W\u00fcrttemberg",
    "wof:name":"Stadiongastst\u00e4tte",
    "wof:placetype":"venue"
},
  "geometry": {"coordinates":[13.3468341827,50.9208526611],"type":"Point"}
}