{
  "type": "Feature",
  "properties": {
    "iso:country":"DE",
    "sg:address":"Gerberstr. 28",
    "sg:city":"Landau",
    "sg:phone":"+49 6341/283590",
    "sg:postcode":"76829",
    "sg:province":"Rheinland-Pfalz",
    "wof:name":"Kochl\u00f6ffel Gmbh & Co. Kg",
    "wof:placetype":"venue"
},
  "geometry": {"coordinates":[8.1139822006,49.1972541809],"type":"Point"}
}