{
  "type": "Feature",
  "properties": {
    "iso:country":"DE",
    "sg:address":"Saargaustr. 27",
    "sg:city":"Saarburg",
    "sg:phone":"+49 6581/6191",
    "sg:postcode":"54439",
    "sg:province":"Rheinland-Pfalz",
    "wof:name":"Otto Zehren",
    "wof:placetype":"venue"
},
  "geometry": {"coordinates":[6.507666,49.596592],"type":"Point"}
}