{
  "type": "Feature",
  "properties": {
    "iso:country":"DE",
    "sg:address":"Bichlmannstr. 3",
    "sg:city":"Eching",
    "sg:phone":"+49 8761/76410",
    "sg:postcode":"84174",
    "sg:province":"Bayern",
    "wof:name":"Hcs H\u00fcbner Computer Systeme Gmbh",
    "wof:placetype":"venue"
},
  "geometry": {"coordinates":[12.0113601685,48.4819526672],"type":"Point"}
}