{
  "type": "Feature",
  "properties": {
    "iso:country":"DE",
    "sg:address":"Marienstr. 3",
    "sg:city":"Schl\u00fcsselfeld",
    "sg:phone":"+49 9552/477",
    "sg:postcode":"96132",
    "sg:province":"Bayern",
    "wof:name":"K. Mayer",
    "wof:placetype":"venue"
},
  "geometry": {"coordinates":[10.619761467,49.7564544678],"type":"Point"}
}