{
  "type": "Feature",
  "properties": {
    "iso:country":"DE",
    "sg:address":"Unter den Eichen 9",
    "sg:city":"Radibor",
    "sg:postcode":"02627",
    "sg:province":"Sachsen",
    "wof:name":"Bau Com Gmbh",
    "wof:placetype":"venue"
},
  "geometry": {"coordinates":[14.541783,51.192757],"type":"Point"}
}