{
  "type": "Feature",
  "properties": {
    "iso:country":"DE",
    "sg:address":"Zum Waterland 25",
    "sg:city":"Attendorn",
    "sg:phone":"+49 2722/50248",
    "sg:postcode":"57439",
    "sg:province":"Nordrhein-Westfalen",
    "wof:name":"Friedhelm Koch",
    "wof:placetype":"venue"
},
  "geometry": {"coordinates":[7.8998360634,51.1508255005],"type":"Point"}
}