{
  "type": "Feature",
  "properties": {
    "iso:country":"DE",
    "sg:address":"Corneliusstr. 1",
    "sg:city":"M\u00fcnchen",
    "sg:phone":"+49 89/266318",
    "sg:postcode":"80469",
    "sg:province":"Bayern",
    "wof:name":"Harry Schiemann",
    "wof:placetype":"venue"
},
  "geometry": {"coordinates":[11.574515,48.132908],"type":"Point"}
}