{
  "type": "Feature",
  "properties": {
    "iso:country":"DE",
    "sg:address":"Gewerbestr. 7",
    "sg:city":"Ichtershausen",
    "sg:postcode":"99334",
    "sg:province":"Th\u00fcringen",
    "wof:name":"Spz - Service Postzustellung Gmbh",
    "wof:placetype":"venue"
},
  "geometry": {"coordinates":[10.938044,50.881229],"type":"Point"}
}