{
  "type": "Feature",
  "properties": {
    "iso:country":"DE",
    "sg:address":"K\u00f6nigsberger Str. 53",
    "sg:city":"M\u00f6glingen",
    "sg:phone":"+49 7141/491110",
    "sg:postcode":"71696",
    "sg:province":"Baden-W\u00fcrttemberg",
    "wof:name":"Nuova Montorsi Gmbh",
    "wof:placetype":"venue"
},
  "geometry": {"coordinates":[9.1179885864,48.8918304443],"type":"Point"}
}