{
  "type": "Feature",
  "properties": {
    "iso:country":"DE",
    "sg:address":"Seltersweg 24",
    "sg:city":"Gie\u00dfen",
    "sg:phone":"+49 641/76943",
    "sg:postcode":"35390",
    "sg:province":"Hessen",
    "wof:name":"Harald Ernst Masseur",
    "wof:placetype":"venue"
},
  "geometry": {"coordinates":[8.673154,50.584148],"type":"Point"}
}