{
  "type": "Feature",
  "properties": {
    "iso:country":"DE",
    "sg:address":"Viehweg 3",
    "sg:city":"Lichtenfels",
    "sg:phone":"+49 5636/646",
    "sg:postcode":"35104",
    "sg:province":"Hessen",
    "wof:name":"Karl Scriba",
    "wof:placetype":"venue"
},
  "geometry": {"coordinates":[8.809272,51.193184],"type":"Point"}
}