{
  "type": "Feature",
  "properties": {
    "iso:country":"DE",
    "sg:address":"Gewerbeparkstr. 2",
    "sg:city":"Vogelsdorf",
    "sg:phone":"+49 33439/4960",
    "sg:postcode":"15370",
    "sg:province":"Brandenburg",
    "wof:name":"Winfried Gronwald",
    "wof:placetype":"venue"
},
  "geometry": {"coordinates":[13.7472953796,52.5044784546],"type":"Point"}
}