{
  "type": "Feature",
  "properties": {
    "iso:country":"DE",
    "sg:address":"Lange Str. 36",
    "sg:city":"G\u00f6ppingen",
    "sg:phone":"+49 7161/67300",
    "sg:postcode":"73033",
    "sg:province":"Baden-W\u00fcrttemberg",
    "wof:name":"W.i.p. Werbung Und Vertrieb Im Privaten Rundfunk",
    "wof:placetype":"venue"
},
  "geometry": {"coordinates":[9.651241,48.703278],"type":"Point"}
}