{
  "type": "Feature",
  "properties": {
    "iso:country":"DE",
    "sg:address":"Martin-Luther-Str. 1",
    "sg:city":"W\u00fcrzburg",
    "sg:postcode":"97072",
    "sg:province":"Bayern",
    "wof:name":"Evangelischer Arbeiterverein 1854",
    "wof:placetype":"venue"
},
  "geometry": {"coordinates":[9.9436225891,49.7928657532],"type":"Point"}
}