{
  "type": "Feature",
  "properties": {
    "iso:country":"DE",
    "sg:address":"Sodentalstr. 76",
    "sg:city":"Sulzbach",
    "sg:phone":"+49 6028/8187",
    "sg:postcode":"63834",
    "sg:province":"Bayern",
    "wof:name":"Maria Keller",
    "wof:placetype":"venue"
},
  "geometry": {"coordinates":[9.209704,49.923061],"type":"Point"}
}