{
  "type": "Feature",
  "properties": {
    "iso:country":"DE",
    "sg:address":"In den Sauermatten 15",
    "sg:city":"Merzhausen",
    "sg:phone":"+49 761",
    "sg:postcode":"79249",
    "sg:province":"Baden-W\u00fcrttemberg",
    "wof:name":"Schreinerei Scheickenplfug - Leben Mit Holz",
    "wof:placetype":"venue"
},
  "geometry": {"coordinates":[7.823839,47.970703],"type":"Point"}
}