{
  "type": "Feature",
  "properties": {
    "iso:country":"DE",
    "sg:address":"Dahlenburger Landstr. 70",
    "sg:city":"L\u00fcneburg",
    "sg:phone":"+49 4131/52196",
    "sg:postcode":"21337",
    "sg:province":"Niedersachsen",
    "wof:name":"Flora-apotheke Inh. Klaus-dieter Flachmann",
    "wof:placetype":"venue"
},
  "geometry": {"coordinates":[10.43056,53.247967],"type":"Point"}
}