{
  "type": "Feature",
  "properties": {
    "iso:country":"DE",
    "sg:address":"Bahnhofstr. 89",
    "sg:city":"Gr\u00e4felfing",
    "sg:phone":"+49 89/8540223",
    "sg:postcode":"82166",
    "sg:province":"Bayern",
    "wof:name":"Till I.d. Gmbh",
    "wof:placetype":"venue"
},
  "geometry": {"coordinates":[11.4287576675,48.118686676],"type":"Point"}
}