{
  "type": "Feature",
  "properties": {
    "iso:country":"DE",
    "sg:address":"Hauptstr. 119",
    "sg:city":"Cunewalde",
    "sg:phone":"+49 35877/28248",
    "sg:postcode":"02733",
    "sg:province":"Sachsen",
    "wof:name":"Gerald Voigt",
    "wof:placetype":"venue"
},
  "geometry": {"coordinates":[14.5204153061,51.0987701416],"type":"Point"}
}