{
  "type": "Feature",
  "properties": {
    "iso:country":"DE",
    "sg:address":"Wallburgstr. 8",
    "sg:city":"Herne",
    "sg:phone":"+49 2323/23309",
    "sg:postcode":"44629",
    "sg:province":"Nordrhein-Westfalen",
    "wof:name":"Bruno Koeppen Bau Direktor",
    "wof:placetype":"venue"
},
  "geometry": {"coordinates":[7.206205,51.550076],"type":"Point"}
}