{
  "type": "Feature",
  "properties": {
    "iso:country":"DE",
    "sg:address":"Berliner Platz 4",
    "sg:city":"Leverkusen",
    "sg:phone":"+49 2171/2237",
    "sg:postcode":"51379",
    "sg:province":"Nordrhein-Westfalen",
    "wof:name":"Pizza-pazza",
    "wof:placetype":"venue"
},
  "geometry": {"coordinates":[6.9997310638,51.0707397461],"type":"Point"}
}