{
  "type": "Feature",
  "properties": {
    "iso:country":"DE",
    "sg:address":"Thalerweg 21",
    "sg:city":"Oberhaching",
    "sg:postcode":"82041",
    "sg:province":"Bayern",
    "wof:name":"Milenia 21 Grundbesitz- Verwaltungs- Und",
    "wof:placetype":"venue"
},
  "geometry": {"coordinates":[11.571893692,48.0293693542],"type":"Point"}
}