{
  "type": "Feature",
  "properties": {
    "iso:country":"DE",
    "sg:address":"Saarlandstr. 50",
    "sg:city":"Villingen-Schwenningen",
    "sg:phone":"+49 7721/25508",
    "sg:postcode":"78050",
    "sg:province":"Baden-W\u00fcrttemberg",
    "wof:name":"Marion G\u00fcntert Masseurin",
    "wof:placetype":"venue"
},
  "geometry": {"coordinates":[8.446601,48.056938],"type":"Point"}
}