{
  "type": "Feature",
  "properties": {
    "iso:country":"DE",
    "sg:address":"Sonnenstr. 84",
    "sg:city":"Duisburg",
    "sg:phone":"+49 203/22795",
    "sg:postcode":"47179",
    "sg:province":"Nordrhein-Westfalen",
    "wof:name":"Matthias Lukiewicz",
    "wof:placetype":"venue"
},
  "geometry": {"coordinates":[6.7500491142,51.524230957],"type":"Point"}
}