{
  "type": "Feature",
  "properties": {
    "iso:country":"DE",
    "sg:address":"W\u00fcrttembergstr. 1",
    "sg:city":"Ostfildern",
    "sg:phone":"+49 711/454114",
    "sg:postcode":"73760",
    "sg:province":"Baden-W\u00fcrttemberg",
    "wof:name":"Breining Farb- Und",
    "wof:placetype":"venue"
},
  "geometry": {"coordinates":[9.23179245,48.7219429016],"type":"Point"}
}