{
  "type": "Feature",
  "properties": {
    "iso:country":"DE",
    "sg:address":"Im Kissen 2",
    "sg:city":"Brilon",
    "sg:postcode":"59929",
    "sg:province":"Nordrhein-Westfalen",
    "wof:name":"Hustadt Internationale Beteiligungen Gmbh",
    "wof:placetype":"venue"
},
  "geometry": {"coordinates":[8.595211,51.406616],"type":"Point"}
}