{
  "type": "Feature",
  "properties": {
    "iso:country":"DE",
    "sg:address":"Hochheim 5",
    "sg:city":"B\u00f6singen",
    "sg:phone":"+49 7404/1812",
    "sg:postcode":"78662",
    "sg:province":"Baden-W\u00fcrttemberg",
    "wof:name":"Bernhard Seifried",
    "wof:placetype":"venue"
},
  "geometry": {"coordinates":[8.578471,48.227615],"type":"Point"}
}