{
  "type": "Feature",
  "properties": {
    "iso:country":"DE",
    "sg:address":"Siemensstr. 3",
    "sg:city":"Unterschlei\u00dfheim",
    "sg:phone":"+49 89/3214500",
    "sg:postcode":"85716",
    "sg:province":"Bayern",
    "wof:name":"Cross It. Media Ag",
    "wof:placetype":"venue"
},
  "geometry": {"coordinates":[11.576701,48.290611],"type":"Point"}
}