{
  "type": "Feature",
  "properties": {
    "iso:country":"DE",
    "sg:address":"Sedanstr. 23",
    "sg:city":"Hannover",
    "sg:phone":"+49 511/387670",
    "sg:postcode":"30161",
    "sg:province":"Niedersachsen",
    "wof:name":"J. Klinkert Rechtsanwalt",
    "wof:placetype":"venue"
},
  "geometry": {"coordinates":[9.7475881577,52.3817901611],"type":"Point"}
}