{
  "type": "Feature",
  "properties": {
    "iso:country":"DE",
    "sg:address":"Goethestr. 49",
    "sg:city":"Wolfsburg",
    "sg:phone":"+49 4971/189130",
    "sg:postcode":"38440",
    "sg:province":"Niedersachsen",
    "wof:name":"Deutsche Bkk",
    "wof:placetype":"venue"
},
  "geometry": {"coordinates":[10.783046,52.422489],"type":"Point"}
}