{
  "type": "Feature",
  "properties": {
    "iso:country":"DE",
    "sg:address":"Leonhardstr. 11",
    "sg:city":"Ravensburg",
    "sg:phone":"+49 751/23859",
    "sg:postcode":"88212",
    "sg:province":"Baden-W\u00fcrttemberg",
    "wof:name":"Hengge Gmbh",
    "wof:placetype":"venue"
},
  "geometry": {"coordinates":[9.617471,47.779522],"type":"Point"}
}