{
  "type": "Feature",
  "properties": {
    "iso:country":"DE",
    "sg:address":"Humboldtstr. 214",
    "sg:city":"Essen",
    "sg:postcode":"45149",
    "sg:province":"Nordrhein-Westfalen",
    "wof:name":"Aldi Gmbh & Co. Kg",
    "wof:placetype":"venue"
},
  "geometry": {"coordinates":[6.9614062309,51.4263420105],"type":"Point"}
}