{
  "type": "Feature",
  "properties": {
    "iso:country":"DE",
    "sg:address":"Steinberger Weg 60",
    "sg:city":"Gie\u00dfen",
    "sg:phone":"+49 641/79440",
    "sg:postcode":"35394",
    "sg:province":"Hessen",
    "wof:name":"Bieber & Co.",
    "wof:placetype":"venue"
},
  "geometry": {"coordinates":[8.69554,50.56786],"type":"Point"}
}