{
  "type": "Feature",
  "properties": {
    "iso:country":"DE",
    "sg:address":"Kaiserplatz 5",
    "sg:city":"Aachen",
    "sg:phone":"+49 241/31647",
    "sg:postcode":"52062",
    "sg:province":"Nordrhein-Westfalen",
    "wof:name":"Kaisersch\u00e4nke",
    "wof:placetype":"venue"
},
  "geometry": {"coordinates":[6.0958390236,50.7744064331],"type":"Point"}
}