{
  "type": "Feature",
  "properties": {
    "iso:country":"DE",
    "sg:address":"Bornholmer Str. 79",
    "sg:city":"Berlin",
    "sg:phone":"+49 30/44651199",
    "sg:postcode":"10439",
    "sg:province":"Berlin",
    "wof:name":"Valentin",
    "wof:placetype":"venue"
},
  "geometry": {"coordinates":[13.406623,52.553921],"type":"Point"}
}