{
  "type": "Feature",
  "properties": {
    "iso:country":"DE",
    "sg:address":"Justinus-Kerner-Str. 10",
    "sg:city":"Ludwigsburg",
    "sg:phone":"+49 7141/929292",
    "sg:postcode":"71636",
    "sg:province":"Baden-W\u00fcrttemberg",
    "wof:name":"K. R. Boss",
    "wof:placetype":"venue"
},
  "geometry": {"coordinates":[9.1748352051,48.8933029175],"type":"Point"}
}