{
  "type": "Feature",
  "properties": {
    "iso:country":"DE",
    "sg:address":"Braunsbacher Str. 37",
    "sg:city":"F\u00fcrth",
    "sg:phone":"+49 911/9301006",
    "sg:postcode":"90765",
    "sg:province":"Bayern",
    "wof:name":"Ar Rohm Gmbh",
    "wof:placetype":"venue"
},
  "geometry": {"coordinates":[11.0201883316,49.5040016174],"type":"Point"}
}