{
  "type": "Feature",
  "properties": {
    "iso:country":"DE",
    "sg:address":"Kolk 3",
    "sg:city":"L\u00fcbeck",
    "sg:phone":"+49 451/78054",
    "sg:postcode":"23552",
    "sg:province":"Schleswig-Holstein",
    "wof:name":"Restaurant L\u00fcbecker Hanse",
    "wof:placetype":"venue"
},
  "geometry": {"coordinates":[10.6824216843,53.8661651611],"type":"Point"}
}