{
  "type": "Feature",
  "properties": {
    "iso:country":"DE",
    "sg:address":"Hauptstr. 216 a",
    "sg:city":"Stutensee",
    "sg:phone":"+49 7244/91670",
    "sg:postcode":"76297",
    "sg:province":"Baden-W\u00fcrttemberg",
    "wof:name":"Iris Tycholis",
    "wof:placetype":"venue"
},
  "geometry": {"coordinates":[8.464658,49.055077],"type":"Point"}
}