{
  "type": "Feature",
  "properties": {
    "iso:country":"DE",
    "sg:address":"Potsdamer Str. 121",
    "sg:city":"Bielefeld",
    "sg:phone":"+49 521/201135",
    "sg:postcode":"33719",
    "sg:province":"Nordrhein-Westfalen",
    "wof:name":"Meister",
    "wof:placetype":"venue"
},
  "geometry": {"coordinates":[8.5984640121,52.0141334534],"type":"Point"}
}