{
  "type": "Feature",
  "properties": {
    "iso:country":"DE",
    "sg:address":"Am Salzpfad 47 b",
    "sg:city":"Friedrichsdorf",
    "sg:phone":"+49 6007/2520",
    "sg:postcode":"61381",
    "sg:province":"Hessen",
    "wof:name":"Der Knallfrosch:das E-zine F\u00fcr Deutschland.ein Besuch Lohnt!",
    "wof:placetype":"venue"
},
  "geometry": {"coordinates":[8.674769,50.263077],"type":"Point"}
}