{
  "type": "Feature",
  "properties": {
    "iso:country":"DE",
    "sg:address":"Nutzhorner Str. 37",
    "sg:city":"Delmenhorst",
    "sg:phone":"+49 4221/585577",
    "sg:postcode":"27753",
    "sg:province":"Niedersachsen",
    "wof:name":"Torsten Weise Bautr\u00e4ger Gmbh",
    "wof:placetype":"venue"
},
  "geometry": {"coordinates":[8.616064,53.064217],"type":"Point"}
}