{
  "type": "Feature",
  "properties": {
    "iso:country":"DE",
    "sg:address":"Universit\u00e4tsstr. 142",
    "sg:city":"Bochum",
    "sg:postcode":"44799",
    "sg:province":"Nordrhein-Westfalen",
    "wof:name":"Zeres Gmbh",
    "wof:placetype":"venue"
},
  "geometry": {"coordinates":[7.24145,51.455269],"type":"Point"}
}