{
  "type": "Feature",
  "properties": {
    "iso:country":"DE",
    "sg:address":"Eisenbahnstr. 2",
    "sg:city":"G\u00fcstrow",
    "sg:phone":"+49 3843/681671",
    "sg:postcode":"18273",
    "sg:province":"Mecklenburg-Vorpommern",
    "wof:name":"Svenska Is Huset Schwedische Eisspezialit\u00e4ten",
    "wof:placetype":"venue"
},
  "geometry": {"coordinates":[12.172402,53.799004],"type":"Point"}
}