{
  "type": "Feature",
  "properties": {
    "iso:country":"DE",
    "sg:address":"Potsdamer Str. 1",
    "sg:city":"Lauenau",
    "sg:phone":"+49 5043/5550",
    "sg:postcode":"31867",
    "sg:province":"Niedersachsen",
    "wof:name":"Beer-hochduck Gmbh",
    "wof:placetype":"venue"
},
  "geometry": {"coordinates":[9.373578,52.277374],"type":"Point"}
}