{
  "type": "Feature",
  "properties": {
    "iso:country":"DE",
    "sg:address":"Veckerhagener Str. 116a",
    "sg:city":"Fuldatal",
    "sg:phone":"+49 561/8169833",
    "sg:postcode":"34233",
    "sg:province":"Hessen",
    "wof:name":"Kentner-leuchten",
    "wof:placetype":"venue"
},
  "geometry": {"coordinates":[9.527085,51.354984],"type":"Point"}
}