{
  "type": "Feature",
  "properties": {
    "iso:country":"DE",
    "sg:address":"Desenberg 7",
    "sg:city":"Lippstadt",
    "sg:phone":"+49 2948/1074",
    "sg:postcode":"59558",
    "sg:province":"Nordrhein-Westfalen",
    "wof:name":"Friedhelm Kukuk",
    "wof:placetype":"venue"
},
  "geometry": {"coordinates":[8.4468765259,51.6934318542],"type":"Point"}
}