{
  "type": "Feature",
  "properties": {
    "iso:country":"DE",
    "sg:address":"Turnerstr. 5",
    "sg:city":"Leipzig",
    "sg:phone":"+49 341/9607991",
    "sg:postcode":"04103",
    "sg:province":"Sachsen",
    "wof:name":"Thomas Noack",
    "wof:placetype":"venue"
},
  "geometry": {"coordinates":[12.3814697266,51.3340263367],"type":"Point"}
}