{
  "type": "Feature",
  "properties": {
    "iso:country":"DE",
    "sg:address":"Deichstr. 1 b",
    "sg:city":"Bar\u00dfel",
    "sg:phone":"+49 4499/7517",
    "sg:postcode":"26676",
    "sg:province":"Niedersachsen",
    "wof:name":"Heinrich Ruder",
    "wof:placetype":"venue"
},
  "geometry": {"coordinates":[7.70705,53.1763],"type":"Point"}
}