{
  "type": "Feature",
  "properties": {
    "iso:country":"DE",
    "sg:address":"Lange Str. 6",
    "sg:city":"Wolgast",
    "sg:phone":"+49 3836/202390",
    "sg:postcode":"17438",
    "sg:province":"Mecklenburg-Vorpommern",
    "wof:name":"Helmut Arnold Architekt",
    "wof:placetype":"venue"
},
  "geometry": {"coordinates":[13.777225,54.053928],"type":"Point"}
}