{
  "type": "Feature",
  "properties": {
    "iso:country":"DE",
    "sg:address":"Karl-Marx-Str. 35 a",
    "sg:city":"Gr\u00fcnheide",
    "sg:phone":"+49 3362/24046",
    "sg:postcode":"15537",
    "sg:province":"Brandenburg",
    "wof:name":"Jugendfreizeitst\u00e4tte Des Cvjm Frankfurt E. V.",
    "wof:placetype":"venue"
},
  "geometry": {"coordinates":[13.8214931488,52.4230041504],"type":"Point"}
}