{
  "type": "Feature",
  "properties": {
    "iso:country":"DE",
    "sg:address":"Eichenhainallee 43 a",
    "sg:city":"Bergisch Gladbach",
    "sg:postcode":"51427",
    "sg:province":"Nordrhein-Westfalen",
    "wof:name":"Mctax Steuerberatungs- Ges. Mbh",
    "wof:placetype":"venue"
},
  "geometry": {"coordinates":[7.1397271156,50.95885849],"type":"Point"}
}