{
  "type": "Feature",
  "properties": {
    "iso:country":"DE",
    "sg:address":"Berg Str. 17",
    "sg:city":"Altendiez",
    "sg:phone":"+49 6432/982400",
    "sg:postcode":"65624",
    "sg:province":"Rheinland-Pfalz",
    "wof:name":"Naturstein2000",
    "wof:placetype":"venue"
},
  "geometry": {"coordinates":[7.985934,50.37368],"type":"Point"}
}