{
  "type": "Feature",
  "properties": {
    "iso:country":"DE",
    "sg:address":"Dorstbornstr. 3",
    "sg:city":"Erfurt",
    "sg:phone":"+49 361/7968264",
    "sg:postcode":"99094",
    "sg:province":"Th\u00fcringen",
    "wof:name":"Horst Burggraf",
    "wof:placetype":"venue"
},
  "geometry": {"coordinates":[10.9864263535,50.9374046326],"type":"Point"}
}