{
  "type": "Feature",
  "properties": {
    "iso:country":"DE",
    "sg:address":"Allendestr. 68",
    "sg:city":"Schmalkalden",
    "sg:phone":"+49 3683/798174",
    "sg:postcode":"98574",
    "sg:province":"Th\u00fcringen",
    "wof:name":"Erothitan Titanimplantate Ag",
    "wof:placetype":"venue"
},
  "geometry": {"coordinates":[10.47313,50.724445],"type":"Point"}
}