{
  "type": "Feature",
  "properties": {
    "iso:country":"DE",
    "sg:address":"Neum\u00e4rker Str. 35",
    "sg:city":"Helmstedt",
    "sg:phone":"+49 5351/2033",
    "sg:postcode":"38350",
    "sg:province":"Niedersachsen",
    "wof:name":"Atlasreisen",
    "wof:placetype":"venue"
},
  "geometry": {"coordinates":[11.0087718964,52.2276496887],"type":"Point"}
}