{
  "type": "Feature",
  "properties": {
    "iso:country":"DE",
    "sg:address":"Steinweg 4",
    "sg:city":"Langenselbold",
    "sg:phone":"+49 6184/1558",
    "sg:postcode":"63505",
    "sg:province":"Hessen",
    "wof:name":"Helma B\u00e4r",
    "wof:placetype":"venue"
},
  "geometry": {"coordinates":[9.040625,50.176891],"type":"Point"}
}