{
  "type": "Feature",
  "properties": {
    "iso:country":"DE",
    "sg:address":"Bahnhofstr. 33",
    "sg:city":"Sonneberg",
    "sg:phone":"+49 3675/703220",
    "sg:postcode":"96515",
    "sg:province":"Th\u00fcringen",
    "wof:name":"Gastst\u00e4tte Reiterlein",
    "wof:placetype":"venue"
},
  "geometry": {"coordinates":[11.1734447479,50.359703064],"type":"Point"}
}