{
  "type": "Feature",
  "properties": {
    "iso:country":"DE",
    "sg:address":"D\u00fcrbheimer Str. 15",
    "sg:city":"Rietheim-Weilheim",
    "sg:phone":"+49 7424/95570",
    "sg:postcode":"78604",
    "sg:province":"Baden-W\u00fcrttemberg",
    "wof:name":"Werma Signaltechnik Verwaltungs Gmbh",
    "wof:placetype":"venue"
},
  "geometry": {"coordinates":[8.77896,48.037258],"type":"Point"}
}