{
  "type": "Feature",
  "properties": {
    "iso:country":"DE",
    "sg:address":"Langenstr. 52-54",
    "sg:city":"Bremen",
    "sg:phone":"+49 421/1685050",
    "sg:postcode":"28195",
    "sg:province":"Bremen",
    "wof:name":"Johann Treis Kg",
    "wof:placetype":"venue"
},
  "geometry": {"coordinates":[8.8008699417,53.0777931213],"type":"Point"}
}