{
  "type": "Feature",
  "properties": {
    "iso:country":"DE",
    "sg:address":"Flachsmarkt 1",
    "sg:city":"Essen",
    "sg:phone":"+49 201/225706",
    "sg:postcode":"45127",
    "sg:province":"Nordrhein-Westfalen",
    "wof:name":"Det Norske Veritas Stahlhandel",
    "wof:placetype":"venue"
},
  "geometry": {"coordinates":[7.012646,51.457611],"type":"Point"}
}