{
  "type": "Feature",
  "properties": {
    "iso:country":"DE",
    "sg:address":"Martinstr. 17",
    "sg:city":"Munderkingen",
    "sg:phone":"+49 7393/1558",
    "sg:postcode":"89597",
    "sg:province":"Baden-W\u00fcrttemberg",
    "wof:name":"Restaurant Adler Pub",
    "wof:placetype":"venue"
},
  "geometry": {"coordinates":[9.6447591782,48.2356529236],"type":"Point"}
}