{
  "type": "Feature",
  "properties": {
    "iso:country":"DE",
    "sg:address":"Marienstr. 9",
    "sg:city":"Eisenach",
    "sg:phone":"+49 3691/203123",
    "sg:postcode":"99817",
    "sg:province":"Th\u00fcringen",
    "wof:name":"Fleischerei Waldemar Kaiser",
    "wof:placetype":"venue"
},
  "geometry": {"coordinates":[10.3236675262,50.9713401794],"type":"Point"}
}