{
  "type": "Feature",
  "properties": {
    "iso:country":"DE",
    "sg:address":"Am Saldergraben 54",
    "sg:city":"Salzgitter",
    "sg:phone":"+49 5341/45500",
    "sg:postcode":"38226",
    "sg:province":"Niedersachsen",
    "wof:name":"Ev. Pfarramt St. Johannes",
    "wof:placetype":"venue"
},
  "geometry": {"coordinates":[10.3352880478,52.1479568481],"type":"Point"}
}