{
  "type": "Feature",
  "properties": {
    "iso:country":"DE",
    "sg:address":"Seilnachtstr. 32",
    "sg:city":"Endingen",
    "sg:phone":"+49 7642/45234",
    "sg:postcode":"79346",
    "sg:province":"Baden-W\u00fcrttemberg",
    "wof:name":"Ibis Individual Business Information Services Gmbh",
    "wof:placetype":"venue"
},
  "geometry": {"coordinates":[7.7081651688,48.1450080872],"type":"Point"}
}