{
  "type": "Feature",
  "properties": {
    "iso:country":"DE",
    "sg:address":"Oberm\u00f6gersheim 23",
    "sg:city":"Wassertr\u00fcdingen",
    "sg:phone":"+49 9836/475",
    "sg:postcode":"91717",
    "sg:province":"Bayern",
    "wof:name":"Klaus Zinsmeister",
    "wof:placetype":"venue"
},
  "geometry": {"coordinates":[10.6616,49.056412],"type":"Point"}
}