{
  "type": "Feature",
  "properties": {
    "iso:country":"DE",
    "sg:address":"Eschenbachstr. 34",
    "sg:city":"Hannover",
    "sg:phone":"+49 511/580145",
    "sg:postcode":"30629",
    "sg:province":"Niedersachsen",
    "wof:name":"Bernd Heukroth",
    "wof:placetype":"venue"
},
  "geometry": {"coordinates":[9.8303852081,52.3977890015],"type":"Point"}
}