{
  "type": "Feature",
  "properties": {
    "iso:country":"DE",
    "sg:address":"Abteiweg 22",
    "sg:city":"Solingen",
    "sg:phone":"+49 212/590184",
    "sg:postcode":"42653",
    "sg:province":"Nordrhein-Westfalen",
    "wof:name":"Lothar Quabeck",
    "wof:placetype":"venue"
},
  "geometry": {"coordinates":[7.074707,51.211544],"type":"Point"}
}