{
  "type": "Feature",
  "properties": {
    "iso:country":"DE",
    "sg:address":"Odenwaldring 11",
    "sg:city":"Eppertshausen",
    "sg:phone":"+49 6071/37529",
    "sg:postcode":"64859",
    "sg:province":"Hessen",
    "wof:name":"W. Franze",
    "wof:placetype":"venue"
},
  "geometry": {"coordinates":[8.85926,49.948154],"type":"Point"}
}