{
  "type": "Feature",
  "properties": {
    "iso:country":"DE",
    "sg:address":"Eichendorffstr. 2",
    "sg:city":"Leipzig",
    "sg:phone":"+49 341/3076379",
    "sg:postcode":"04277",
    "sg:province":"Sachsen",
    "wof:name":"Archiv Der Hochschule F\u00fcr Technik Wirtschaft Und",
    "wof:placetype":"venue"
},
  "geometry": {"coordinates":[12.371919,51.313644],"type":"Point"}
}