{
  "type": "Feature",
  "properties": {
    "iso:country":"DE",
    "sg:address":"Schulgasse 4",
    "sg:city":"Burgheim",
    "sg:postcode":"86666",
    "sg:province":"Bayern",
    "wof:name":"Gemeindeb\u00fccherei Burgheim",
    "wof:placetype":"venue"
},
  "geometry": {"coordinates":[11.020632,48.700912],"type":"Point"}
}