{
  "type": "Feature",
  "properties": {
    "iso:country":"DE",
    "sg:address":"Possartstr. 9",
    "sg:city":"M\u00fcnchen",
    "sg:postcode":"81679",
    "sg:province":"Bayern",
    "wof:name":"Svm Star Ventures Management Gmbh Nr. 3",
    "wof:placetype":"venue"
},
  "geometry": {"coordinates":[11.6064157486,48.1406898499],"type":"Point"}
}