{
  "type": "Feature",
  "properties": {
    "iso:country":"DE",
    "sg:address":"Tichelbrink 68",
    "sg:city":"L\u00f6hne",
    "sg:phone":"+49 5731/78730",
    "sg:postcode":"32584",
    "sg:province":"Nordrhein-Westfalen",
    "wof:name":"Ratioplast Opto- Electronics Gmbh",
    "wof:placetype":"venue"
},
  "geometry": {"coordinates":[8.758779,52.185898],"type":"Point"}
}