{
  "type": "Feature",
  "properties": {
    "iso:country":"DE",
    "sg:address":"M\u00fchlenhof 1",
    "sg:city":"Haiger",
    "sg:phone":"+49 2774/2452",
    "sg:postcode":"35708",
    "sg:province":"Hessen",
    "wof:name":"Restaurant Landhaus M\u00fchlenhof",
    "wof:placetype":"venue"
},
  "geometry": {"coordinates":[8.2258996964,50.8235015869],"type":"Point"}
}