{
  "type": "Feature",
  "properties": {
    "iso:country":"DE",
    "sg:address":"Fuhrbleek 48-50",
    "sg:city":"Isernhagen",
    "sg:postcode":"30916",
    "sg:province":"Niedersachsen",
    "wof:name":"Fsi Fahrzeug-spezialausbau Isernhagen Gmbh",
    "wof:placetype":"venue"
},
  "geometry": {"coordinates":[9.787781,52.450592],"type":"Point"}
}