{
  "type": "Feature",
  "properties": {
    "iso:country":"DE",
    "sg:address":"Kulturenweg 6 a",
    "sg:city":"Syrau",
    "sg:phone":"+49 37431/3292",
    "sg:postcode":"08548",
    "sg:province":"Sachsen",
    "wof:name":"G\u00e4rtner & Floristen Plauen Eg",
    "wof:placetype":"venue"
},
  "geometry": {"coordinates":[12.076226,50.547607],"type":"Point"}
}