{
  "type": "Feature",
  "properties": {
    "iso:country":"DE",
    "sg:address":"Westendstr. 9",
    "sg:city":"Lauingen",
    "sg:phone":"+49 9072/2111",
    "sg:postcode":"89415",
    "sg:province":"Bayern",
    "wof:name":"Viktor Wioncek Gmbh",
    "wof:placetype":"venue"
},
  "geometry": {"coordinates":[10.417265892,48.571472168],"type":"Point"}
}