{
  "type": "Feature",
  "properties": {
    "iso:country":"DE",
    "sg:address":"Buchholzallee 4",
    "sg:city":"Parchim",
    "sg:phone":"+49 3871/265122",
    "sg:postcode":"19370",
    "sg:province":"Mecklenburg-Vorpommern",
    "wof:name":"Oase",
    "wof:placetype":"venue"
},
  "geometry": {"coordinates":[11.848641,53.423531],"type":"Point"}
}