{
  "type": "Feature",
  "properties": {
    "iso:country":"DE",
    "sg:address":"Dreisamstr. 3-5",
    "sg:city":"Freiburg",
    "sg:phone":"+49 761/36891156",
    "sg:postcode":"79098",
    "sg:province":"Baden-W\u00fcrttemberg",
    "wof:name":"Sozialstation Evang. Freiburg Im Breisgau E. V.",
    "wof:placetype":"venue"
},
  "geometry": {"coordinates":[7.848921,47.990646],"type":"Point"}
}