{
  "type": "Feature",
  "properties": {
    "iso:country":"DE",
    "sg:address":"Ebersstr. 78",
    "sg:city":"Berlin",
    "sg:phone":"+49 30/2133006",
    "sg:postcode":"10827",
    "sg:province":"Berlin",
    "wof:name":"Vhf Radio-fernsehen-video",
    "wof:placetype":"venue"
},
  "geometry": {"coordinates":[13.35318,52.480717],"type":"Point"}
}