{
  "type": "Feature",
  "properties": {
    "iso:country":"DE",
    "sg:address":"Gro\u00dfe Kirchstr. 18",
    "sg:city":"Wolfenb\u00fcttel",
    "sg:phone":"+49 5331/26843",
    "sg:postcode":"38300",
    "sg:province":"Niedersachsen",
    "wof:name":"Im Zentrum",
    "wof:placetype":"venue"
},
  "geometry": {"coordinates":[10.5388031006,52.1613464355],"type":"Point"}
}