{
  "type": "Feature",
  "properties": {
    "iso:country":"DE",
    "sg:address":"Margaretenstr. 29",
    "sg:city":"Barbing",
    "sg:phone":"+49 9401/51514",
    "sg:postcode":"93092",
    "sg:province":"Bayern",
    "wof:name":"Eduard W. Adamsky Heilpraktiker",
    "wof:placetype":"venue"
},
  "geometry": {"coordinates":[12.1871414185,49.0004463196],"type":"Point"}
}