{
  "type": "Feature",
  "properties": {
    "iso:country":"DE",
    "sg:address":"Hattinger Str. 381",
    "sg:city":"Bochum",
    "sg:phone":"+49 234/432306",
    "sg:postcode":"44795",
    "sg:province":"Nordrhein-Westfalen",
    "wof:name":"Pizzeria Ii Pastaro",
    "wof:placetype":"venue"
},
  "geometry": {"coordinates":[7.1930370331,51.4515457153],"type":"Point"}
}