{
  "type": "Feature",
  "properties": {
    "iso:country":"DE",
    "sg:address":"Hoflacher Str 34",
    "sg:city":"Eichenau",
    "sg:phone":"+49 8141/3794930",
    "sg:postcode":"82223",
    "sg:province":"Bayern",
    "wof:name":"Coachingpartner",
    "wof:placetype":"venue"
},
  "geometry": {"coordinates":[11.3163671494,48.1619567871],"type":"Point"}
}