{
  "type": "Feature",
  "properties": {
    "iso:country":"DE",
    "sg:address":"Hindenburgring 10",
    "sg:city":"Bad Harzburg",
    "sg:phone":"+49 5322/3437",
    "sg:postcode":"38667",
    "sg:province":"Niedersachsen",
    "wof:name":"Hotel Residenz Am Hochwald",
    "wof:placetype":"venue"
},
  "geometry": {"coordinates":[10.5529603958,51.8770713806],"type":"Point"}
}