{
  "type": "Feature",
  "properties": {
    "iso:country":"DE",
    "sg:address":"De-Vo\u00df-Str. 23",
    "sg:city":"Hamburg",
    "sg:phone":"+49 40/3892694",
    "sg:postcode":"22767",
    "sg:province":"Hamburg",
    "wof:name":"R. Gercken",
    "wof:placetype":"venue"
},
  "geometry": {"coordinates":[9.949569,53.545559],"type":"Point"}
}