{
  "type": "Feature",
  "properties": {
    "iso:country":"DE",
    "sg:address":"Bendenweg 24",
    "sg:city":"Bad M\u00fcnstereifel",
    "sg:phone":"+49 2253/95230",
    "sg:postcode":"53902",
    "sg:province":"Nordrhein-Westfalen",
    "wof:name":"Druckerei Heinen Gmbh",
    "wof:placetype":"venue"
},
  "geometry": {"coordinates":[6.761765,50.570766],"type":"Point"}
}