{
  "type": "Feature",
  "properties": {
    "iso:country":"DE",
    "sg:address":"Bahnhofstr. 12",
    "sg:city":"Jesberg",
    "sg:phone":"+49 6695/322",
    "sg:postcode":"34632",
    "sg:province":"Hessen",
    "wof:name":"Schwanen-apotheke Jesberg",
    "wof:placetype":"venue"
},
  "geometry": {"coordinates":[9.145525,50.997341],"type":"Point"}
}