{
  "type": "Feature",
  "properties": {
    "iso:country":"DE",
    "sg:address":"Berthin-Bleeg-Str. 15",
    "sg:city":"Wenningstedt",
    "sg:phone":"+49 4651/98470",
    "sg:postcode":"25996",
    "sg:province":"Schleswig-Holstein",
    "wof:name":"H. G. Kiose",
    "wof:placetype":"venue"
},
  "geometry": {"coordinates":[8.3215179443,54.9376869202],"type":"Point"}
}