{
  "type": "Feature",
  "properties": {
    "iso:country":"DE",
    "sg:address":"Friedrich-Mi\u00dfler-Str. 46-50",
    "sg:city":"Bremen",
    "sg:phone":"+49 421/2034663",
    "sg:postcode":"28211",
    "sg:province":"Bremen",
    "wof:name":"Nieders\u00e4chsisches Landesamt F\u00fcr Bodenforschung",
    "wof:placetype":"venue"
},
  "geometry": {"coordinates":[8.8695716858,53.0878448486],"type":"Point"}
}