{
  "type": "Feature",
  "properties": {
    "iso:country":"DE",
    "sg:address":"Jahnstr. 22",
    "sg:city":"Bad Homburg",
    "sg:phone":"+49 6172/451469",
    "sg:postcode":"61352",
    "sg:province":"Hessen",
    "wof:name":"Heuschkel Gmbh",
    "wof:placetype":"venue"
},
  "geometry": {"coordinates":[8.652819,50.21714],"type":"Point"}
}