{
  "type": "Feature",
  "properties": {
    "iso:country":"DE",
    "sg:address":"Oberf\u00f6hringer Str. 48",
    "sg:city":"M\u00fcnchen",
    "sg:postcode":"81925",
    "sg:province":"Bayern",
    "wof:name":"Com Projekt Gmbh",
    "wof:placetype":"venue"
},
  "geometry": {"coordinates":[11.614299,48.1562],"type":"Point"}
}