{
  "type": "Feature",
  "properties": {
    "iso:country":"DE",
    "sg:address":"Bolkerstr. 14",
    "sg:city":"D\u00fcsseldorf",
    "sg:phone":"+49 211/8993900",
    "sg:postcode":"40213",
    "sg:province":"Nordrhein-Westfalen",
    "wof:name":"D\u00fcsseldorfer Drogenhilfe E.v.",
    "wof:placetype":"venue"
},
  "geometry": {"coordinates":[6.773318,51.226162],"type":"Point"}
}