{
  "type": "Feature",
  "properties": {
    "iso:country":"DE",
    "sg:address":"Immelnbusch 10",
    "sg:city":"Viersen",
    "sg:phone":"+49 2162/34220",
    "sg:postcode":"41748",
    "sg:province":"Nordrhein-Westfalen",
    "wof:name":"Herbert Siemens",
    "wof:placetype":"venue"
},
  "geometry": {"coordinates":[6.416694,51.245075],"type":"Point"}
}