{
  "type": "Feature",
  "properties": {
    "iso:country":"DE",
    "sg:address":"Zwirnerstr. 27",
    "sg:city":"K\u00f6ln",
    "sg:phone":"+49 221/316866",
    "sg:postcode":"50678",
    "sg:province":"Nordrhein-Westfalen",
    "wof:name":"Webdesign-werbeberatung Karl-heinz Hilbrecht",
    "wof:placetype":"venue"
},
  "geometry": {"coordinates":[6.9619870186,50.9259033203],"type":"Point"}
}