{
  "type": "Feature",
  "properties": {
    "iso:country":"DE",
    "sg:address":"Bremer Platz 9",
    "sg:city":"M\u00fcnster",
    "sg:phone":"+49 251/66050",
    "sg:postcode":"48155",
    "sg:province":"Nordrhein-Westfalen",
    "wof:name":"Gwn Gemeinn\u00fctzige Wohnungs- Ges. Nordwestdeutschland Gmbh",
    "wof:placetype":"venue"
},
  "geometry": {"coordinates":[7.638183,51.957764],"type":"Point"}
}