{
  "type": "Feature",
  "properties": {
    "iso:country":"DE",
    "sg:address":"Geisfelder Str. 14",
    "sg:city":"Bamberg",
    "sg:postcode":"96050",
    "sg:province":"Bayern",
    "wof:name":"Peka Immobilien Und Verm\u00f6gensverwaltung Gmbh",
    "wof:placetype":"venue"
},
  "geometry": {"coordinates":[10.915302,49.889683],"type":"Point"}
}