{
  "type": "Feature",
  "properties": {
    "iso:country":"DE",
    "sg:address":"Glockengasse 15",
    "sg:city":"W\u00fcrzburg",
    "sg:phone":"+49 931/51303",
    "sg:postcode":"97070",
    "sg:province":"Bayern",
    "wof:name":"Rolf Th. Denker Steuerberater",
    "wof:placetype":"venue"
},
  "geometry": {"coordinates":[9.9280900955,49.7925186157],"type":"Point"}
}