{
  "type": "Feature",
  "properties": {
    "iso:country":"DE",
    "sg:address":"Wangener Str. 19",
    "sg:city":"Starnberg",
    "sg:phone":"+49 8151/8845",
    "sg:postcode":"82319",
    "sg:province":"Bayern",
    "wof:name":"J. B. Von Hoenning O Carroll",
    "wof:placetype":"venue"
},
  "geometry": {"coordinates":[11.3704967499,48.0275497437],"type":"Point"}
}