{
  "type": "Feature",
  "properties": {
    "iso:country":"DE",
    "sg:address":"Eckenberger Str. 40",
    "sg:city":"Aachen",
    "sg:phone":"+49 241/64262",
    "sg:postcode":"52066",
    "sg:province":"Nordrhein-Westfalen",
    "wof:name":"Indecor Gesellschaft F\u00fcr Innendekoration Mbh",
    "wof:placetype":"venue"
},
  "geometry": {"coordinates":[6.090592,50.759464],"type":"Point"}
}