{
  "type": "Feature",
  "properties": {
    "iso:country":"DE",
    "sg:address":"Ammerl\u00e4nder Str. 14",
    "sg:city":"Bar\u00dfel",
    "sg:postcode":"26676",
    "sg:province":"Niedersachsen",
    "wof:name":"Aldi Gmbh & Co. Kg",
    "wof:placetype":"venue"
},
  "geometry": {"coordinates":[7.7474842072,53.1700744629],"type":"Point"}
}