{
  "type": "Feature",
  "properties": {
    "iso:country":"DE",
    "sg:address":"Jungfernstieg 30",
    "sg:city":"Hamburg",
    "sg:phone":"+49 40/343843",
    "sg:postcode":"20354",
    "sg:province":"Hamburg",
    "wof:name":"Korean Air Lines",
    "wof:placetype":"venue"
},
  "geometry": {"coordinates":[9.991166,53.554062],"type":"Point"}
}