{
  "type": "Feature",
  "properties": {
    "iso:country":"DE",
    "sg:address":"Warthestr. 13",
    "sg:city":"M\u00fcnchen",
    "sg:phone":"+49 89/934519",
    "sg:postcode":"81927",
    "sg:province":"Bayern",
    "wof:name":"Franz Dahlheuser Gesell- Schaft Mit Beschr\u00e4nkter",
    "wof:placetype":"venue"
},
  "geometry": {"coordinates":[11.6365785599,48.1451454163],"type":"Point"}
}