{
  "type": "Feature",
  "properties": {
    "iso:country":"DE",
    "sg:address":"Birkenallee 63",
    "sg:city":"Pl\u00fcderhausen",
    "sg:postcode":"73655",
    "sg:province":"Baden-W\u00fcrttemberg",
    "wof:name":"Form Tec Technische Formholzteile Gmbh",
    "wof:placetype":"venue"
},
  "geometry": {"coordinates":[9.5920171738,48.797744751],"type":"Point"}
}