{
  "type": "Feature",
  "properties": {
    "iso:country":"DE",
    "sg:address":"Theodor-Lachmann-Str. 17",
    "sg:city":"\u00dcberlingen",
    "sg:postcode":"88662",
    "sg:province":"Baden-W\u00fcrttemberg",
    "wof:name":"Ascanis Ohg",
    "wof:placetype":"venue"
},
  "geometry": {"coordinates":[9.179775238,47.7668991089],"type":"Point"}
}