{
  "type": "Feature",
  "properties": {
    "iso:country":"DE",
    "sg:address":"Tannenwaldallee 13",
    "sg:city":"Bad Homburg",
    "sg:phone":"+49 6172/937930",
    "sg:postcode":"61348",
    "sg:province":"Hessen",
    "wof:name":"K. Dickfeld Immobilienmakler",
    "wof:placetype":"venue"
},
  "geometry": {"coordinates":[8.6037940979,50.2294654846],"type":"Point"}
}