{
  "type": "Feature",
  "properties": {
    "iso:country":"DE",
    "sg:address":"Linden 4",
    "sg:city":"Schwienau",
    "sg:phone":"+49 5822/3334",
    "sg:postcode":"29593",
    "sg:province":"Niedersachsen",
    "wof:name":"H. G. F.-holzmarkt- Gmbh",
    "wof:placetype":"venue"
},
  "geometry": {"coordinates":[10.413495,53.002899],"type":"Point"}
}