{
  "type": "Feature",
  "properties": {
    "iso:country":"DE",
    "sg:address":"Sternstr. 9",
    "sg:city":"Magdeburg",
    "sg:phone":"+49 391/5619608",
    "sg:postcode":"39104",
    "sg:province":"Sachsen-Anhalt",
    "wof:name":"D. Adametz",
    "wof:placetype":"venue"
},
  "geometry": {"coordinates":[11.6270952225,52.1186637878],"type":"Point"}
}