{
  "type": "Feature",
  "properties": {
    "iso:country":"DE",
    "sg:address":"Elisabeth-Wolf-Ufer 30",
    "sg:city":"Cottbus",
    "sg:phone":"+49 355/721384",
    "sg:postcode":"03042",
    "sg:province":"Brandenburg",
    "wof:name":"Fritz Kuhnke Architekt",
    "wof:placetype":"venue"
},
  "geometry": {"coordinates":[14.341638,51.76326],"type":"Point"}
}