{
  "type": "Feature",
  "properties": {
    "iso:country":"DE",
    "sg:address":"Buchenrade 9",
    "sg:city":"M\u00f6nkeberg",
    "sg:postcode":"24248",
    "sg:province":"Schleswig-Holstein",
    "wof:name":"Putz- Und Beschichtungs- Technik K\u00f6pke Gmbh",
    "wof:placetype":"venue"
},
  "geometry": {"coordinates":[10.2077856064,54.3446006775],"type":"Point"}
}