{
  "type": "Feature",
  "properties": {
    "iso:country":"DE",
    "sg:address":"Herrenstr. 4",
    "sg:city":"L\u00f6rrach",
    "sg:phone":"+49 7621/40130",
    "sg:postcode":"79539",
    "sg:province":"Baden-W\u00fcrttemberg",
    "wof:name":"H. Pfeifle W. Graf Von Kagenbeck",
    "wof:placetype":"venue"
},
  "geometry": {"coordinates":[7.6601109505,47.611289978],"type":"Point"}
}