{
  "type": "Feature",
  "properties": {
    "iso:country":"DE",
    "sg:address":"Niddastr. 84",
    "sg:city":"Frankfurt",
    "sg:phone":"+49 69/2445020",
    "sg:postcode":"60329",
    "sg:province":"Hessen",
    "wof:name":"Informationsdesign Ag",
    "wof:placetype":"venue"
},
  "geometry": {"coordinates":[8.659682,50.108101],"type":"Point"}
}