{
  "type": "Feature",
  "properties": {
    "iso:country":"DE",
    "sg:address":"Reinhardtstr. 4",
    "sg:city":"Balingen",
    "sg:phone":"+49 7433/8304",
    "sg:postcode":"72336",
    "sg:province":"Baden-W\u00fcrttemberg",
    "wof:name":"F. Ebner",
    "wof:placetype":"venue"
},
  "geometry": {"coordinates":[8.8399238586,48.2822723389],"type":"Point"}
}