{
  "type": "Feature",
  "properties": {
    "iso:country":"DE",
    "sg:address":"Goetheallee 7",
    "sg:city":"G\u00f6ttingen",
    "sg:phone":"+49 551/58968",
    "sg:postcode":"37073",
    "sg:province":"Niedersachsen",
    "wof:name":"Brillen Studio Inh. G. Franzke",
    "wof:placetype":"venue"
},
  "geometry": {"coordinates":[9.9313983917,51.5345535278],"type":"Point"}
}