{
  "type": "Feature",
  "properties": {
    "iso:country":"DE",
    "sg:address":"St\u00fctzenbergstr. 3",
    "sg:city":"Zellingen",
    "sg:phone":"+49 9364/6905",
    "sg:postcode":"97225",
    "sg:province":"Bayern",
    "wof:name":"Maxl B\u00e4ck B\u00e4ckerei Konditorei",
    "wof:placetype":"venue"
},
  "geometry": {"coordinates":[9.824803,49.890461],"type":"Point"}
}