{
  "type": "Feature",
  "properties": {
    "iso:country":"DE",
    "sg:city":"B\u00fcrchau",
    "sg:phone":"+49 4976/29745",
    "sg:postcode":"79683",
    "sg:province":"Baden-W\u00fcrttemberg",
    "wof:name":"Sparkasse Schopfheim",
    "wof:placetype":"venue"
},
  "geometry": {"coordinates":[7.826867,47.776161],"type":"Point"}
}