{
  "type": "Feature",
  "properties": {
    "iso:country":"DE",
    "sg:address":"Ranspacher Str. 36",
    "sg:city":"Pausa",
    "sg:phone":"+49 37432/21005",
    "sg:postcode":"07952",
    "sg:province":"Sachsen",
    "wof:name":"Gerlinde Tannh\u00e4user",
    "wof:placetype":"venue"
},
  "geometry": {"coordinates":[11.9867925644,50.5737113953],"type":"Point"}
}