{
  "type": "Feature",
  "properties": {
    "iso:country":"DE",
    "sg:address":"Krumme Stroot 12",
    "sg:city":"Hatten",
    "sg:phone":"+49 4482/927229",
    "sg:postcode":"26209",
    "sg:province":"Niedersachsen",
    "wof:name":"Heinz Grzech Isolierungen Gmbh",
    "wof:placetype":"venue"
},
  "geometry": {"coordinates":[8.356075,53.057297],"type":"Point"}
}