{
  "type": "Feature",
  "properties": {
    "iso:country":"DE",
    "sg:address":"Niederurseler Landstr. 49",
    "sg:city":"Frankfurt",
    "sg:phone":"+49 69/574403",
    "sg:postcode":"60439",
    "sg:province":"Hessen",
    "wof:name":"Walter Larson Gmbh",
    "wof:placetype":"venue"
},
  "geometry": {"coordinates":[8.6315107346,50.1643295288],"type":"Point"}
}