{
  "type": "Feature",
  "properties": {
    "iso:country":"DE",
    "sg:address":"Macherscheider Str. 21",
    "sg:city":"Neuss",
    "sg:phone":"+49 2131/365575",
    "sg:postcode":"41468",
    "sg:province":"Nordrhein-Westfalen",
    "wof:name":"Sv Uedesheim",
    "wof:placetype":"venue"
},
  "geometry": {"coordinates":[6.7893400192,51.1625518799],"type":"Point"}
}