{
  "type": "Feature",
  "properties": {
    "iso:country":"DE",
    "sg:address":"Roteichenring 1-7",
    "sg:city":"Mannheim",
    "sg:phone":"+49 621/305859",
    "sg:postcode":"68167",
    "sg:province":"Baden-W\u00fcrttemberg",
    "wof:name":"Dieter Sch\u00f6n Krankengymnast",
    "wof:placetype":"venue"
},
  "geometry": {"coordinates":[8.492445,49.506676],"type":"Point"}
}