{
  "type": "Feature",
  "properties": {
    "iso:country":"DE",
    "sg:address":"Immigh\u00e4user Str. 2",
    "sg:city":"Thalitter-V\u00f6hl",
    "sg:phone":"+49 5635/903392",
    "sg:postcode":"34516",
    "sg:province":"Hessen",
    "wof:name":"Siam-club Reisen Thailand",
    "wof:placetype":"venue"
},
  "geometry": {"coordinates":[8.944025,51.206348],"type":"Point"}
}