{
  "type": "Feature",
  "properties": {
    "iso:country":"DE",
    "sg:address":"Breite Str. 3",
    "sg:city":"Auma",
    "sg:phone":"+49 36626/29181",
    "sg:postcode":"07955",
    "sg:province":"Th\u00fcringen",
    "wof:name":"Birgit Ehlers",
    "wof:placetype":"venue"
},
  "geometry": {"coordinates":[11.9014024734,50.7008514404],"type":"Point"}
}