{
  "type": "Feature",
  "properties": {
    "iso:country":"DE",
    "sg:address":"M\u00fchlenstr. 24a",
    "sg:city":"Neum\u00fcnster",
    "sg:phone":"+49 4321/81591",
    "sg:postcode":"24539",
    "sg:province":"Schleswig-Holstein",
    "wof:name":"Karl Wall Kg",
    "wof:placetype":"venue"
},
  "geometry": {"coordinates":[9.970993042,54.0531044006],"type":"Point"}
}