{
  "type": "Feature",
  "properties": {
    "iso:country":"DE",
    "sg:address":"Parkstr. 109",
    "sg:city":"L\u00fcdenscheid",
    "sg:phone":"+49 2351/3104",
    "sg:postcode":"58509",
    "sg:province":"Nordrhein-Westfalen",
    "wof:name":"Buss Gmbh",
    "wof:placetype":"venue"
},
  "geometry": {"coordinates":[7.6081981659,51.2154464722],"type":"Point"}
}