{
  "type": "Feature",
  "properties": {
    "iso:country":"DE",
    "sg:address":"Grabenstr. 10",
    "sg:city":"Tettnang",
    "sg:phone":"+49 7542/52525",
    "sg:postcode":"88069",
    "sg:province":"Baden-W\u00fcrttemberg",
    "wof:name":"Kaffeek\u00e4nnle",
    "wof:placetype":"venue"
},
  "geometry": {"coordinates":[9.587391,47.6703],"type":"Point"}
}