{
  "type": "Feature",
  "properties": {
    "iso:country":"DE",
    "sg:address":"Lampestr. 7",
    "sg:city":"Leipzig",
    "sg:phone":"+49 341/964350",
    "sg:postcode":"04107",
    "sg:province":"Sachsen",
    "wof:name":"Erik Jochem Rechtsanwalt",
    "wof:placetype":"venue"
},
  "geometry": {"coordinates":[12.3699560165,51.3307914734],"type":"Point"}
}