{
  "type": "Feature",
  "properties": {
    "iso:country":"DE",
    "sg:address":"Rosa-Luxemburg-Str. 1",
    "sg:city":"Lichtenau",
    "sg:postcode":"09244",
    "sg:province":"Sachsen",
    "wof:name":"Dr. Christoph Schmid",
    "wof:placetype":"venue"
},
  "geometry": {"coordinates":[12.9608545303,50.915599823],"type":"Point"}
}