{
  "type": "Feature",
  "properties": {
    "iso:country":"DE",
    "sg:address":"Birkenweg 9",
    "sg:city":"Norderney",
    "sg:phone":"+49 4932/2303",
    "sg:postcode":"26548",
    "sg:province":"Niedersachsen",
    "wof:name":"G\u00e4stehaus Haus Am Birkenweg",
    "wof:placetype":"venue"
},
  "geometry": {"coordinates":[7.1695828438,53.7126274109],"type":"Point"}
}