{
  "type": "Feature",
  "properties": {
    "iso:country":"DE",
    "sg:address":"Alte Wipperf\u00fcrther Str. 80",
    "sg:city":"Odenthal",
    "sg:postcode":"51519",
    "sg:province":"Nordrhein-Westfalen",
    "wof:name":"Otto Gmbh",
    "wof:placetype":"venue"
},
  "geometry": {"coordinates":[7.1862001419,51.0188674927],"type":"Point"}
}