{
  "type": "Feature",
  "properties": {
    "iso:country":"DE",
    "sg:address":"Wasserturmstr. 59",
    "sg:city":"Halberstadt",
    "sg:phone":"+49 3941/27063",
    "sg:postcode":"38820",
    "sg:province":"Sachsen-Anhalt",
    "wof:name":"Raimund Jordann",
    "wof:placetype":"venue"
},
  "geometry": {"coordinates":[11.0363855362,51.8907623291],"type":"Point"}
}