{
  "type": "Feature",
  "properties": {
    "iso:country":"DE",
    "sg:address":"Schillerstr. 51",
    "sg:city":"Cottbus",
    "sg:postcode":"03046",
    "sg:province":"Brandenburg",
    "wof:name":"Vier Jahreszeiten Reisen & Handel E. Kfr.",
    "wof:placetype":"venue"
},
  "geometry": {"coordinates":[14.324262619,51.7571678162],"type":"Point"}
}