{
  "type": "Feature",
  "properties": {
    "iso:country":"DE",
    "sg:address":"Neuer Weg 21",
    "sg:city":"Hohenahr",
    "sg:phone":"+49 6446/303",
    "sg:postcode":"35644",
    "sg:province":"Hessen",
    "wof:name":"Fritz Biek",
    "wof:placetype":"venue"
},
  "geometry": {"coordinates":[8.5183582306,50.6525802612],"type":"Point"}
}