{
  "type": "Feature",
  "properties": {
    "iso:country":"DE",
    "sg:address":"Baderstr. 14",
    "sg:city":"Sch\u00f6ningen",
    "sg:phone":"+49 5352/909345",
    "sg:postcode":"38364",
    "sg:province":"Niedersachsen",
    "wof:name":"Schrift Art",
    "wof:placetype":"venue"
},
  "geometry": {"coordinates":[10.9702091217,52.1380271912],"type":"Point"}
}