{
  "type": "Feature",
  "properties": {
    "iso:country":"DE",
    "sg:address":"Uwestr. 12",
    "sg:city":"Hamburg",
    "sg:phone":"+49 40/54767006",
    "sg:postcode":"22525",
    "sg:province":"Hamburg",
    "wof:name":"Riedewald Gmbh",
    "wof:placetype":"venue"
},
  "geometry": {"coordinates":[9.9319524765,53.581615448],"type":"Point"}
}