{
  "type": "Feature",
  "properties": {
    "iso:country":"DE",
    "sg:address":"Prinz-Eugen-Str. 32 a",
    "sg:city":"Sankt Augustin",
    "sg:phone":"+49 2241/961247",
    "sg:postcode":"53757",
    "sg:province":"Nordrhein-Westfalen",
    "wof:name":"Binding Systems Deutschland Im- Und Export Gmbh",
    "wof:placetype":"venue"
},
  "geometry": {"coordinates":[7.238345,50.78294],"type":"Point"}
}