{
  "type": "Feature",
  "properties": {
    "iso:country":"DE",
    "sg:address":"M\u00fcnchener Ring 1",
    "sg:city":"Schkeuditz",
    "sg:phone":"+49 34204/32323",
    "sg:postcode":"04435",
    "sg:province":"Sachsen",
    "wof:name":"Globana Grundst\u00fccks- Vermietungsges. Mbh & Co.",
    "wof:placetype":"venue"
},
  "geometry": {"coordinates":[12.1989345551,51.4009361267],"type":"Point"}
}