{
  "type": "Feature",
  "properties": {
    "iso:country":"DE",
    "sg:address":"Robbenstr. 5",
    "sg:city":"Cloppenburg",
    "sg:postcode":"49661",
    "sg:province":"Niedersachsen",
    "wof:name":"Fehntechnischer Handel",
    "wof:placetype":"venue"
},
  "geometry": {"coordinates":[8.0206336975,52.845035553],"type":"Point"}
}