{
  "type": "Feature",
  "properties": {
    "iso:country":"DE",
    "sg:address":"Zittauer Str. 41 A",
    "sg:city":"Berlin",
    "sg:phone":"+49 30/6615366",
    "sg:postcode":"12355",
    "sg:province":"Berlin",
    "wof:name":"Harry Skuplik Gmbh",
    "wof:placetype":"venue"
},
  "geometry": {"coordinates":[13.4772939682,52.4182395935],"type":"Point"}
}