{
  "type": "Feature",
  "properties": {
    "iso:country":"DE",
    "sg:address":"Albert-Schweitzer-Str. 1",
    "sg:city":"Oftersheim",
    "sg:phone":"+49 6202/54332",
    "sg:postcode":"68723",
    "sg:province":"Baden-W\u00fcrttemberg",
    "wof:name":"E. Kurz Immobilienmakler",
    "wof:placetype":"venue"
},
  "geometry": {"coordinates":[8.5804862976,49.3662872314],"type":"Point"}
}