{
  "type": "Feature",
  "properties": {
    "iso:country":"DE",
    "sg:address":"Rochusweg 50",
    "sg:city":"Bonn",
    "sg:phone":"+49 228/231098",
    "sg:postcode":"53129",
    "sg:province":"Nordrhein-Westfalen",
    "wof:name":"Botschaft Der Republik Guinea",
    "wof:placetype":"venue"
},
  "geometry": {"coordinates":[7.1135339737,50.699016571],"type":"Point"}
}