{
  "type": "Feature",
  "properties": {
    "iso:country":"DE",
    "sg:address":"Lessingstr. 1 a",
    "sg:city":"Arnstadt",
    "sg:phone":"+49 3628/602270",
    "sg:postcode":"99310",
    "sg:province":"Th\u00fcringen",
    "wof:name":"Restaurant Akropolis",
    "wof:placetype":"venue"
},
  "geometry": {"coordinates":[10.9490528107,50.8391265869],"type":"Point"}
}