{
  "type": "Feature",
  "properties": {
    "iso:country":"DE",
    "sg:address":"Schlo\u00dfstr. 2a",
    "sg:city":"Liebenau",
    "sg:phone":"+49 5023/1831",
    "sg:postcode":"31618",
    "sg:province":"Niedersachsen",
    "wof:name":"Ernst Nordholz Rechtsanwalt",
    "wof:placetype":"venue"
},
  "geometry": {"coordinates":[9.0897903442,52.6037597656],"type":"Point"}
}