{
  "type": "Feature",
  "properties": {
    "iso:country":"DE",
    "sg:address":"Paulinenstr. 15",
    "sg:city":"Wiesbaden",
    "sg:phone":"+49 4961/13480",
    "sg:postcode":"65189",
    "sg:province":"Hessen",
    "wof:name":"Aarial Bank Ag",
    "wof:placetype":"venue"
},
  "geometry": {"coordinates":[8.247668,50.082821],"type":"Point"}
}