{
  "type": "Feature",
  "properties": {
    "iso:country":"DE",
    "sg:address":"Heuers Moor 12",
    "sg:city":"Lotte",
    "sg:postcode":"49504",
    "sg:province":"Nordrhein-Westfalen",
    "wof:name":"Technodent Beteiligungs-gmbh",
    "wof:placetype":"venue"
},
  "geometry": {"coordinates":[7.95337,52.308357],"type":"Point"}
}