{
  "type": "Feature",
  "properties": {
    "iso:country":"DE",
    "sg:address":"Markusweg 5",
    "sg:city":"Dorsten",
    "sg:postcode":"46282",
    "sg:province":"Nordrhein-Westfalen",
    "wof:name":"Baumann Beteiligungs- Gmbh",
    "wof:placetype":"venue"
},
  "geometry": {"coordinates":[6.959524,51.661732],"type":"Point"}
}