{
  "type": "Feature",
  "properties": {
    "iso:country":"DE",
    "sg:address":"Adlerstr. 47",
    "sg:city":"Greven",
    "sg:phone":"+49 2575/3837",
    "sg:postcode":"48268",
    "sg:province":"Nordrhein-Westfalen",
    "wof:name":"Helmut Siepert Gastst\u00e4tte",
    "wof:placetype":"venue"
},
  "geometry": {"coordinates":[7.5509500504,52.1149024963],"type":"Point"}
}