{
  "type": "Feature",
  "properties": {
    "iso:country":"DE",
    "sg:address":"Gasteiner Str. 25",
    "sg:city":"Duisburg",
    "sg:phone":"+49 203/799440",
    "sg:postcode":"47249",
    "sg:province":"Nordrhein-Westfalen",
    "wof:name":"R. Lange Gmbh",
    "wof:placetype":"venue"
},
  "geometry": {"coordinates":[6.761332,51.381554],"type":"Point"}
}