{
  "type": "Feature",
  "properties": {
    "iso:country":"DE",
    "sg:address":"Wesetalstr. 23",
    "sg:city":"Edertal",
    "sg:phone":"+49 5623/4218",
    "sg:postcode":"34549",
    "sg:province":"Hessen",
    "wof:name":"Waldecker Hof Inh. W. Rabe",
    "wof:placetype":"venue"
},
  "geometry": {"coordinates":[9.0673618317,51.141834259],"type":"Point"}
}