{
  "type": "Feature",
  "properties": {
    "iso:country":"DE",
    "sg:address":"Dorfstr. 174",
    "sg:city":"Adendorf",
    "sg:phone":"+49 4131/51179",
    "sg:postcode":"21365",
    "sg:province":"Niedersachsen",
    "wof:name":"Heinrich Heine",
    "wof:placetype":"venue"
},
  "geometry": {"coordinates":[10.474577,53.274399],"type":"Point"}
}