{
  "type": "Feature",
  "properties": {
    "iso:country":"DE",
    "sg:address":"Haagstr. 37",
    "sg:city":"Bad Griesbach",
    "sg:phone":"+49 8532/1388",
    "sg:postcode":"94086",
    "sg:province":"Bayern",
    "wof:name":"P. Mais",
    "wof:placetype":"venue"
},
  "geometry": {"coordinates":[13.1936683655,48.4523468018],"type":"Point"}
}