{
  "type": "Feature",
  "properties": {
    "iso:country":"DE",
    "sg:address":"B\u00fcrgerhaus",
    "sg:city":"Losheim",
    "sg:phone":"+49 6872/5867",
    "sg:postcode":"66679",
    "sg:province":"Saarland",
    "wof:name":"Sv Rimlingen E. V. Fu\u00dfballverein",
    "wof:placetype":"venue"
},
  "geometry": {"coordinates":[6.7777609825,49.5341377258],"type":"Point"}
}