{
  "type": "Feature",
  "properties": {
    "iso:country":"DE",
    "sg:address":"Gundenstr. 9",
    "sg:city":"Goslar",
    "sg:phone":"+49 5321/1299",
    "sg:postcode":"38640",
    "sg:province":"Niedersachsen",
    "wof:name":"Herbert Pohle E. K.",
    "wof:placetype":"venue"
},
  "geometry": {"coordinates":[10.4323720932,51.9090919495],"type":"Point"}
}