{
  "type": "Feature",
  "properties": {
    "iso:country":"DE",
    "sg:address":"Reiterweg 10a",
    "sg:city":"K\u00f6nigswinter",
    "sg:postcode":"53639",
    "sg:province":"Nordrhein-Westfalen",
    "wof:name":"Maler H\u00f6hner Gmbh & Co. Kg",
    "wof:placetype":"venue"
},
  "geometry": {"coordinates":[7.32991,50.68095],"type":"Point"}
}