{
  "type": "Feature",
  "properties": {
    "iso:country":"DE",
    "sg:address":"Arzheimer Str. 14",
    "sg:city":"Ilbesheim",
    "sg:phone":"+49 6341/30621",
    "sg:postcode":"76831",
    "sg:province":"Rheinland-Pfalz",
    "wof:name":"J\u00fcrgen Leiner",
    "wof:placetype":"venue"
},
  "geometry": {"coordinates":[8.0545969009,49.1835899353],"type":"Point"}
}