{
  "type": "Feature",
  "properties": {
    "iso:country":"DE",
    "sg:address":"Weiherstr. 6",
    "sg:city":"R\u00f6ttenbach",
    "sg:phone":"+49 9195/7124",
    "sg:postcode":"91341",
    "sg:province":"Bayern",
    "wof:name":"Wilfried Fuchs",
    "wof:placetype":"venue"
},
  "geometry": {"coordinates":[10.927379,49.659924],"type":"Point"}
}