{
  "type": "Feature",
  "properties": {
    "iso:country":"DE",
    "sg:address":"Alte Stiege 13",
    "sg:city":"Rhede",
    "sg:phone":"+49 4964/549",
    "sg:postcode":"26899",
    "sg:province":"Niedersachsen",
    "wof:name":"Gerhard Kr\u00f6ger",
    "wof:placetype":"venue"
},
  "geometry": {"coordinates":[7.270393,53.060436],"type":"Point"}
}