{
  "type": "Feature",
  "properties": {
    "iso:country":"DE",
    "sg:address":"Ackerstr. 8",
    "sg:city":"Schwedt",
    "sg:phone":"+49 3332/21880",
    "sg:postcode":"16303",
    "sg:province":"Brandenburg",
    "wof:name":"Wolter Automobile Beteiligungs Gmbh",
    "wof:placetype":"venue"
},
  "geometry": {"coordinates":[14.26792,53.046459],"type":"Point"}
}