{
  "type": "Feature",
  "properties": {
    "iso:country":"DE",
    "sg:address":"Loisachstr. 15",
    "sg:city":"Grainau",
    "sg:phone":"+49 8821/8030",
    "sg:postcode":"82491",
    "sg:province":"Bayern",
    "wof:name":"Alfred Demmel",
    "wof:placetype":"venue"
},
  "geometry": {"coordinates":[11.03362,47.480541],"type":"Point"}
}