{
  "type": "Feature",
  "properties": {
    "iso:country":"DE",
    "sg:address":"Stettiner Str. 19",
    "sg:city":"Neuwied",
    "sg:phone":"+49 2631/83940",
    "sg:postcode":"56564",
    "sg:province":"Rheinland-Pfalz",
    "wof:name":"Ofenbau Des Br\u00fcderhauses Gmbh",
    "wof:placetype":"venue"
},
  "geometry": {"coordinates":[7.4909877777,50.4355392456],"type":"Point"}
}