{
  "type": "Feature",
  "properties": {
    "iso:country":"DE",
    "sg:address":"Max-Planck-Str. 7",
    "sg:city":"Schramberg",
    "sg:phone":"+49 7422/6343",
    "sg:postcode":"78713",
    "sg:province":"Baden-W\u00fcrttemberg",
    "wof:name":"Max Kimmich Gmbh",
    "wof:placetype":"venue"
},
  "geometry": {"coordinates":[8.427216,48.234062],"type":"Point"}
}