{
  "type": "Feature",
  "properties": {
    "iso:country":"DE",
    "sg:address":"Wiesenweg 10",
    "sg:city":"Bad Neuenahr-Ahrweiler",
    "sg:phone":"+49 2641/202220",
    "sg:postcode":"53474",
    "sg:province":"Rheinland-Pfalz",
    "wof:name":"Kpw Maschinenbau Gmbh",
    "wof:placetype":"venue"
},
  "geometry": {"coordinates":[7.17105,50.546421],"type":"Point"}
}