{
  "type": "Feature",
  "properties": {
    "iso:country":"DE",
    "sg:address":"Mittelstr. 52",
    "sg:city":"Aschaffenburg",
    "sg:phone":"+49 6021/423222",
    "sg:postcode":"63741",
    "sg:province":"Bayern",
    "wof:name":"L. Spangenberger",
    "wof:placetype":"venue"
},
  "geometry": {"coordinates":[9.136315,49.986954],"type":"Point"}
}