{
  "type": "Feature",
  "properties": {
    "iso:country":"DE",
    "sg:address":"Emil-Obst-Str. 2",
    "sg:city":"Bitterfeld",
    "sg:phone":"+49 3493/401537",
    "sg:postcode":"06749",
    "sg:province":"Sachsen-Anhalt",
    "wof:name":"Congress-report Gmbh",
    "wof:placetype":"venue"
},
  "geometry": {"coordinates":[12.3257961273,51.6284484863],"type":"Point"}
}