{
  "type": "Feature",
  "properties": {
    "iso:country":"DE",
    "sg:address":"Gewerbestr.7",
    "sg:city":"Murg",
    "sg:phone":"+49 4977/6392210",
    "sg:postcode":"79730",
    "sg:province":"Baden-W\u00fcrttemberg",
    "wof:name":"Hanspeter Biehler Gmbh",
    "wof:placetype":"venue"
},
  "geometry": {"coordinates":[8.0402755737,47.5906982422],"type":"Point"}
}