{
  "type": "Feature",
  "properties": {
    "iso:country":"DE",
    "sg:address":"Hirtenweg 1",
    "sg:city":"Kassel",
    "sg:phone":"+49 561/880113",
    "sg:postcode":"34128",
    "sg:province":"Hessen",
    "wof:name":"Colonia Leather Lederhandels Gmbh",
    "wof:placetype":"venue"
},
  "geometry": {"coordinates":[9.438026,51.337463],"type":"Point"}
}