{
  "type": "Feature",
  "properties": {
    "iso:country":"DE",
    "sg:address":"Rott",
    "sg:city":"Rott",
    "sg:phone":"+49 8039/3053",
    "sg:postcode":"83543",
    "sg:province":"Bayern",
    "wof:name":"Raiffeisenbank Rosenheim Eg",
    "wof:placetype":"venue"
},
  "geometry": {"coordinates":[12.11594,47.984772],"type":"Point"}
}