{
  "type": "Feature",
  "properties": {
    "iso:country":"DE",
    "sg:address":"Vogelsanger Str. 193",
    "sg:city":"K\u00f6ln",
    "sg:phone":"+49 221/5463144",
    "sg:postcode":"50825",
    "sg:province":"Nordrhein-Westfalen",
    "wof:name":"F. Wenzel",
    "wof:placetype":"venue"
},
  "geometry": {"coordinates":[6.9130501747,50.9492645264],"type":"Point"}
}