{
  "type": "Feature",
  "properties": {
    "iso:country":"DE",
    "sg:address":"Kiebitzh\u00f6rn 16",
    "sg:city":"Wangerland",
    "sg:phone":"+49 4426/674",
    "sg:postcode":"26434",
    "sg:province":"Niedersachsen",
    "wof:name":"Pension Hilde U. G\u00fcnter Rotter",
    "wof:placetype":"venue"
},
  "geometry": {"coordinates":[8.0120105743,53.6877250671],"type":"Point"}
}