{
  "type": "Feature",
  "properties": {
    "iso:country":"DE",
    "sg:address":"Frankenstr. 19 n",
    "sg:city":"Wesel",
    "sg:phone":"+49 281/170920",
    "sg:postcode":"46487",
    "sg:province":"Nordrhein-Westfalen",
    "wof:name":"Ulrike Grootens Rechtsanw\u00e4ltin",
    "wof:placetype":"venue"
},
  "geometry": {"coordinates":[6.5695500374,51.6811141968],"type":"Point"}
}