{
  "type": "Feature",
  "properties": {
    "iso:country":"DE",
    "sg:address":"Bahnhofstr. 14",
    "sg:city":"Steinhagen",
    "sg:phone":"+49 5204/8696",
    "sg:postcode":"33803",
    "sg:province":"Nordrhein-Westfalen",
    "wof:name":"Regina Guder Und Siegmund Strochlitz",
    "wof:placetype":"venue"
},
  "geometry": {"coordinates":[8.413151741,52.0064506531],"type":"Point"}
}