{
  "type": "Feature",
  "properties": {
    "iso:country":"DE",
    "sg:address":"Gro\u00dfe Paaschburg 34",
    "sg:city":"Itzehoe",
    "sg:phone":"+49 4821/65753",
    "sg:postcode":"25524",
    "sg:province":"Schleswig-Holstein",
    "wof:name":"Rattan Trends",
    "wof:placetype":"venue"
},
  "geometry": {"coordinates":[9.5209264755,53.9217338562],"type":"Point"}
}