{
  "type": "Feature",
  "properties": {
    "iso:country":"DE",
    "sg:address":"Frankfurter Str. 58",
    "sg:city":"Gr\u00e4venwiesbach",
    "sg:phone":"+49 6086/919866",
    "sg:postcode":"61279",
    "sg:province":"Hessen",
    "wof:name":"Restaurant Aphrodite",
    "wof:placetype":"venue"
},
  "geometry": {"coordinates":[8.4604682922,50.3835525513],"type":"Point"}
}