{
  "type": "Feature",
  "properties": {
    "iso:country":"DE",
    "sg:address":"Marktplatz 1",
    "sg:city":"Oberviechtach",
    "sg:phone":"+49 9671/1503",
    "sg:postcode":"92526",
    "sg:province":"Bayern",
    "wof:name":"Pension Zur Post K. Betz",
    "wof:placetype":"venue"
},
  "geometry": {"coordinates":[12.4187374115,49.4602165222],"type":"Point"}
}