{
  "type": "Feature",
  "properties": {
    "iso:country":"DE",
    "sg:address":"Balduinstr. 86",
    "sg:city":"Frankfurt",
    "sg:phone":"+49 69/657071",
    "sg:postcode":"60599",
    "sg:province":"Hessen",
    "wof:name":"Epi Matic Handelsges. Mbh",
    "wof:placetype":"venue"
},
  "geometry": {"coordinates":[8.7152767181,50.0972137451],"type":"Point"}
}