{
  "type": "Feature",
  "properties": {
    "iso:country":"DE",
    "sg:address":"Kapit\u00e4n-Wittenberg-Str. 15",
    "sg:city":"Wangerooge",
    "sg:phone":"+49 4469/1420",
    "sg:postcode":"26486",
    "sg:province":"Niedersachsen",
    "wof:name":"K. Folkerts Gmbh",
    "wof:placetype":"venue"
},
  "geometry": {"coordinates":[7.8979730606,53.7899703979],"type":"Point"}
}