{
  "type": "Feature",
  "properties": {
    "iso:country":"DE",
    "sg:address":"Hochuferpromenade 5",
    "sg:city":"Sellin",
    "sg:phone":"+49 38303/85508",
    "sg:postcode":"18586",
    "sg:province":"Mecklenburg-Vorpommern",
    "wof:name":"N. Braun Immobilienmakler",
    "wof:placetype":"venue"
},
  "geometry": {"coordinates":[13.700961113,54.3815078735],"type":"Point"}
}