{
  "type": "Feature",
  "properties": {
    "iso:country":"DE",
    "sg:address":"Hammer Landstr. 234",
    "sg:city":"Hamburg",
    "sg:phone":"+49 40/213711",
    "sg:postcode":"20537",
    "sg:province":"Hamburg",
    "wof:name":"S. Michailoglou",
    "wof:placetype":"venue"
},
  "geometry": {"coordinates":[10.065568924,53.5537757874],"type":"Point"}
}