{
  "type": "Feature",
  "properties": {
    "iso:country":"DE",
    "sg:address":"Oberhofer Weg 21",
    "sg:city":"Berlin",
    "sg:phone":"+49 30/7722512",
    "sg:postcode":"12209",
    "sg:province":"Berlin",
    "wof:name":"Coiffeur K Und Nagelstudio Inh. P. Und E. Kummutat",
    "wof:placetype":"venue"
},
  "geometry": {"coordinates":[13.3276338577,52.4260749817],"type":"Point"}
}