{
  "type": "Feature",
  "properties": {
    "iso:country":"DE",
    "sg:address":"Gerlachstr. 4",
    "sg:city":"Holzheim",
    "sg:phone":"+49 9075/8920",
    "sg:postcode":"89438",
    "sg:province":"Bayern",
    "wof:name":"Karl-heinz B\u00f6hm",
    "wof:placetype":"venue"
},
  "geometry": {"coordinates":[10.5125112534,48.5119590759],"type":"Point"}
}