{
  "type": "Feature",
  "properties": {
    "iso:country":"DE",
    "sg:address":"Pa\u00dfstr. 152",
    "sg:city":"Aachen",
    "sg:phone":"+49 241/152560",
    "sg:postcode":"52070",
    "sg:province":"Nordrhein-Westfalen",
    "wof:name":"H. J. Birnbaum",
    "wof:placetype":"venue"
},
  "geometry": {"coordinates":[6.0959639549,50.787109375],"type":"Point"}
}