{
  "type": "Feature",
  "properties": {
    "iso:country":"DE",
    "sg:address":"Westendstr. 7",
    "sg:city":"Kempten",
    "sg:phone":"+49 831/24502",
    "sg:postcode":"87439",
    "sg:province":"Bayern",
    "wof:name":"Real-commerz Verwaltungs- Gesellschaft F\u00fcr Grund-",
    "wof:placetype":"venue"
},
  "geometry": {"coordinates":[10.3074998856,47.7234268188],"type":"Point"}
}