{
  "type": "Feature",
  "properties": {
    "iso:country":"DE",
    "sg:address":"Schmiedstrasse 4",
    "sg:city":"Altusried",
    "sg:phone":"+49 8373/93071",
    "sg:postcode":"87452",
    "sg:province":"Bayern",
    "wof:name":"Web-office",
    "wof:placetype":"venue"
},
  "geometry": {"coordinates":[10.2152442932,47.8042945862],"type":"Point"}
}