{
  "type": "Feature",
  "properties": {
    "iso:country":"DE",
    "sg:address":"Restrup 9",
    "sg:city":"Bippen",
    "sg:phone":"+49 5435/863",
    "sg:postcode":"49626",
    "sg:province":"Niedersachsen",
    "wof:name":"Karl-heinz Schwietert",
    "wof:placetype":"venue"
},
  "geometry": {"coordinates":[7.775708,52.582474],"type":"Point"}
}