{
  "type": "Feature",
  "properties": {
    "iso:country":"DE",
    "sg:address":"Neue Burger Str. 66",
    "sg:city":"Wilster",
    "sg:phone":"+49 4823/586",
    "sg:postcode":"25554",
    "sg:province":"Schleswig-Holstein",
    "wof:name":"G\u00fcnther Thumann",
    "wof:placetype":"venue"
},
  "geometry": {"coordinates":[9.372028,53.93005],"type":"Point"}
}