{
  "type": "Feature",
  "properties": {
    "iso:country":"DE",
    "sg:address":"Seewiesstr. 6",
    "sg:city":"Deggendorf",
    "sg:phone":"+49 9931/2454",
    "sg:postcode":"94469",
    "sg:province":"Bayern",
    "wof:name":"Bauunternehmung Wallner",
    "wof:placetype":"venue"
},
  "geometry": {"coordinates":[12.893567,48.81184],"type":"Point"}
}