{
  "type": "Feature",
  "properties": {
    "iso:country":"DE",
    "sg:address":"Buchenweg 29",
    "sg:city":"W\u00fcrzburg",
    "sg:phone":"+49 931/271170",
    "sg:postcode":"97076",
    "sg:province":"Bayern",
    "wof:name":"Marion Liebscher Rechtsanw\u00e4ltin",
    "wof:placetype":"venue"
},
  "geometry": {"coordinates":[9.9882507324,49.8062782288],"type":"Point"}
}