{
  "type": "Feature",
  "properties": {
    "iso:country":"DE",
    "sg:address":"Ingolst\u00e4dter Str. 23",
    "sg:city":"Reichertshofen",
    "sg:phone":"+49 8453/423",
    "sg:postcode":"85084",
    "sg:province":"Bayern",
    "wof:name":"Maola Reichertshofen Gmbh",
    "wof:placetype":"venue"
},
  "geometry": {"coordinates":[11.463887,48.660126],"type":"Point"}
}