{
  "type": "Feature",
  "properties": {
    "iso:country":"DE",
    "sg:address":"Weigelstr. 16",
    "sg:city":"Weiden",
    "sg:phone":"+49 961/850",
    "sg:postcode":"92637",
    "sg:province":"Bayern",
    "wof:name":"Oberpf\u00c4lzischer Kurier",
    "wof:placetype":"venue"
},
  "geometry": {"coordinates":[12.1600847244,49.6721916199],"type":"Point"}
}