{
  "type": "Feature",
  "properties": {
    "iso:country":"DE",
    "sg:address":"Tobelstr. 10",
    "sg:city":"Berg",
    "sg:phone":"+49 7153/53971",
    "sg:postcode":"88276",
    "sg:province":"Baden-W\u00fcrttemberg",
    "wof:name":"Eleonore St\u00f6cklein",
    "wof:placetype":"venue"
},
  "geometry": {"coordinates":[9.59342,47.802555],"type":"Point"}
}