{
  "type": "Feature",
  "properties": {
    "iso:country":"DE",
    "sg:address":"Bickbargen 160a",
    "sg:city":"Halstenbek",
    "sg:phone":"+49 4101/403030",
    "sg:postcode":"25469",
    "sg:province":"Schleswig-Holstein",
    "wof:name":"Majid Pourmoussavi",
    "wof:placetype":"venue"
},
  "geometry": {"coordinates":[9.8593902588,53.6229782104],"type":"Point"}
}