{
  "type": "Feature",
  "properties": {
    "iso:country":"DE",
    "sg:address":"Lindenstr. 13",
    "sg:city":"Sittensen",
    "sg:postcode":"27419",
    "sg:province":"Niedersachsen",
    "wof:name":"Auto-elektrik H\u00f6yns Inh. Diedrich H\u00f6yns E. K.",
    "wof:placetype":"venue"
},
  "geometry": {"coordinates":[9.502393,53.279568],"type":"Point"}
}