{
  "type": "Feature",
  "properties": {
    "iso:country":"DE",
    "sg:address":"Hammerstr. 14",
    "sg:city":"Bellheim",
    "sg:postcode":"76756",
    "sg:province":"Rheinland-Pfalz",
    "wof:name":"Klein Verwaltungs Gmbh",
    "wof:placetype":"venue"
},
  "geometry": {"coordinates":[8.2862491608,49.1920928955],"type":"Point"}
}