{
  "type": "Feature",
  "properties": {
    "iso:country":"DE",
    "sg:address":"Hauptstr. 46",
    "sg:city":"Holstenniendorf",
    "sg:phone":"+49 4827/9202",
    "sg:postcode":"25584",
    "sg:province":"Schleswig-Holstein",
    "wof:name":"Lampe Gmbh",
    "wof:placetype":"venue"
},
  "geometry": {"coordinates":[9.348708,54.042404],"type":"Point"}
}