{
  "type": "Feature",
  "properties": {
    "iso:country":"DE",
    "sg:address":"Dungestr. 80",
    "sg:city":"Arnsberg",
    "sg:phone":"+49 2932/36150",
    "sg:postcode":"59757",
    "sg:province":"Nordrhein-Westfalen",
    "wof:name":"H. Stammschr\u00f6er Architekt",
    "wof:placetype":"venue"
},
  "geometry": {"coordinates":[7.960128,51.426105],"type":"Point"}
}