{
  "type": "Feature",
  "properties": {
    "iso:country":"DE",
    "sg:address":"Pflaumheimer Str. 3",
    "sg:city":"Gro\u00dfostheim",
    "sg:phone":"+49 6026/1833",
    "sg:postcode":"63762",
    "sg:province":"Bayern",
    "wof:name":"Immuno Globe Antik\u00f6rpertechnik Gmbh",
    "wof:placetype":"venue"
},
  "geometry": {"coordinates":[9.073314,49.917549],"type":"Point"}
}