{
  "type": "Feature",
  "properties": {
    "iso:country":"DE",
    "sg:address":"K\u00f6nigstr. 1 A",
    "sg:city":"Stuttgart",
    "sg:postcode":"70173",
    "sg:province":"Baden-W\u00fcrttemberg",
    "wof:name":"Scholz Gmbh",
    "wof:placetype":"venue"
},
  "geometry": {"coordinates":[9.181435,48.781677],"type":"Point"}
}