{
  "type": "Feature",
  "properties": {
    "iso:country":"DE",
    "sg:address":"Lauterbacher Str. 58",
    "sg:city":"Wartenberg",
    "sg:phone":"+49 6641/919283",
    "sg:postcode":"36367",
    "sg:province":"Hessen",
    "wof:name":"Baudekoration Schmidt Gmbh",
    "wof:placetype":"venue"
},
  "geometry": {"coordinates":[9.438792,50.632004],"type":"Point"}
}