{
  "type": "Feature",
  "properties": {
    "iso:country":"DE",
    "sg:address":"Im Reidwasen 10",
    "sg:city":"Frankenhardt",
    "sg:phone":"+49 7959",
    "sg:postcode":"74586",
    "sg:province":"Baden-W\u00fcrttemberg",
    "wof:name":"Uwe Kraft Reitsportger\u00e4te & Metallbau Gmbh, Frankenhardt",
    "wof:placetype":"venue"
},
  "geometry": {"coordinates":[9.9789533615,49.0816116333],"type":"Point"}
}