{
  "type": "Feature",
  "properties": {
    "iso:country":"DE",
    "sg:address":"Spiecherg\u00e4ssle 13",
    "sg:city":"Grafenhausen",
    "sg:phone":"+49 7748/261",
    "sg:postcode":"79865",
    "sg:province":"Baden-W\u00fcrttemberg",
    "wof:name":"Johannes Amann",
    "wof:placetype":"venue"
},
  "geometry": {"coordinates":[8.255724,47.773506],"type":"Point"}
}