{
  "type": "Feature",
  "properties": {
    "iso:country":"DE",
    "sg:address":"Schulstr 1",
    "sg:city":"D\u00e4geling",
    "sg:phone":"+49 4821/85564",
    "sg:postcode":"25578",
    "sg:province":"Schleswig-Holstein",
    "wof:name":"M\u00fcller",
    "wof:placetype":"venue"
},
  "geometry": {"coordinates":[9.531538,53.876972],"type":"Point"}
}