{
  "type": "Feature",
  "properties": {
    "iso:country":"DE",
    "sg:address":"K\u00f6nigstr. 49",
    "sg:city":"Lommatzsch",
    "sg:phone":"+49 35241/58562",
    "sg:postcode":"01623",
    "sg:province":"Sachsen",
    "wof:name":"G. M\u00fcnch",
    "wof:placetype":"venue"
},
  "geometry": {"coordinates":[13.3062868118,51.198387146],"type":"Point"}
}