{
  "type": "Feature",
  "properties": {
    "iso:country":"DE",
    "sg:address":"L\u00f6tzener Str 3",
    "sg:city":"Bremen",
    "sg:phone":"+49 421/43210",
    "sg:postcode":"28207",
    "sg:province":"Bremen",
    "wof:name":"Boss Branchen-organisation Und Software-systeme Ag",
    "wof:placetype":"venue"
},
  "geometry": {"coordinates":[8.8671951294,53.0729675293],"type":"Point"}
}