{
  "type": "Feature",
  "properties": {
    "iso:country":"DE",
    "sg:address":"Alte Landstr. 36",
    "sg:city":"T\u00fcbingen",
    "sg:phone":"+49 7071/73454",
    "sg:postcode":"72072",
    "sg:province":"Baden-W\u00fcrttemberg",
    "wof:name":"Weilheimer Kneiple",
    "wof:placetype":"venue"
},
  "geometry": {"coordinates":[9.0317115784,48.4950294495],"type":"Point"}
}