{
  "type": "Feature",
  "properties": {
    "iso:country":"DE",
    "sg:address":"Erhardstr. 9",
    "sg:city":"Duisburg",
    "sg:phone":"+49 203/588535",
    "sg:postcode":"47167",
    "sg:province":"Nordrhein-Westfalen",
    "wof:name":"Wilfried Freund Grabdenkm\u00e4ler",
    "wof:placetype":"venue"
},
  "geometry": {"coordinates":[6.8190159798,51.5028915405],"type":"Point"}
}