{
  "type": "Feature",
  "properties": {
    "iso:country":"DE",
    "sg:address":"Strandpromenade 0",
    "sg:city":"L\u00fcbeck",
    "sg:postcode":"23570",
    "sg:province":"Schleswig-Holstein",
    "wof:name":"Fiction Kardinal Van De Church Noah E. K.",
    "wof:placetype":"venue"
},
  "geometry": {"coordinates":[10.881478,53.969162],"type":"Point"}
}