{
  "type": "Feature",
  "properties": {
    "iso:country":"DE",
    "sg:address":"Schwarzer Weg 13",
    "sg:city":"Leiferde",
    "sg:phone":"+49 5373/97810",
    "sg:postcode":"38542",
    "sg:province":"Niedersachsen",
    "wof:name":"Maretzki - Elektro",
    "wof:placetype":"venue"
},
  "geometry": {"coordinates":[10.4327096939,52.4517593384],"type":"Point"}
}