{
  "type": "Feature",
  "properties": {
    "iso:country":"DE",
    "sg:address":"Teggingerstr. 10",
    "sg:city":"Radolfzell",
    "sg:phone":"+49 7732/6144",
    "sg:postcode":"78315",
    "sg:province":"Baden-W\u00fcrttemberg",
    "wof:name":"Kraus-oexle Und Valentin Praxis F\u00fcr Krankengymnastik",
    "wof:placetype":"venue"
},
  "geometry": {"coordinates":[8.970122,47.738594],"type":"Point"}
}