{
  "type": "Feature",
  "properties": {
    "iso:country":"DE",
    "sg:address":"Wessumer Str. 88",
    "sg:city":"Ahaus",
    "sg:phone":"+49 2561/7061",
    "sg:postcode":"48683",
    "sg:province":"Nordrhein-Westfalen",
    "wof:name":"Heinz Frankem\u00f6lle Steuerberater",
    "wof:placetype":"venue"
},
  "geometry": {"coordinates":[7.0022258759,52.0841445923],"type":"Point"}
}