{
  "type": "Feature",
  "properties": {
    "iso:country":"DE",
    "sg:address":"Rathausplatz 1",
    "sg:city":"Ingolstadt",
    "sg:phone":"+49 841",
    "sg:postcode":"85049",
    "sg:province":"Bayern",
    "wof:name":"Tauchbasis Schwerelos",
    "wof:placetype":"venue"
},
  "geometry": {"coordinates":[11.4247550964,48.7629089355],"type":"Point"}
}