{
  "type": "Feature",
  "properties": {
    "iso:country":"DE",
    "sg:address":"Terlaner Str. 8",
    "sg:city":"Augsburg",
    "sg:phone":"+49 821/793341",
    "sg:postcode":"86165",
    "sg:province":"Bayern",
    "wof:name":"Schw\u00e4bischer Adre\u00dfbuchverlag Ludwig Vetter Zweigniederl. D.",
    "wof:placetype":"venue"
},
  "geometry": {"coordinates":[10.950224,48.382084],"type":"Point"}
}