{
  "type": "Feature",
  "properties": {
    "iso:country":"DE",
    "sg:address":"Auf dem Schnee 67",
    "sg:city":"Dortmund",
    "sg:phone":"+49 231/770146",
    "sg:postcode":"44227",
    "sg:province":"Nordrhein-Westfalen",
    "wof:name":"Paul Kimm Inh. Fr. Huster Nachfahren",
    "wof:placetype":"venue"
},
  "geometry": {"coordinates":[7.4249739647,51.4323120117],"type":"Point"}
}