{
  "type": "Feature",
  "properties": {
    "iso:country":"DE",
    "sg:address":"Talstr. 19 a",
    "sg:city":"Kitzingen",
    "sg:phone":"+49 9321/5485",
    "sg:postcode":"97318",
    "sg:province":"Bayern",
    "wof:name":"F. W. Kohl",
    "wof:placetype":"venue"
},
  "geometry": {"coordinates":[10.1503448486,49.737537384],"type":"Point"}
}