{
  "type": "Feature",
  "properties": {
    "iso:country":"DE",
    "sg:address":"Reichenwalder Str. 87",
    "sg:city":"Storkow",
    "sg:phone":"+49 33678/6530",
    "sg:postcode":"15859",
    "sg:province":"Brandenburg",
    "wof:name":"Cit Dv-beratung Gmbh",
    "wof:placetype":"venue"
},
  "geometry": {"coordinates":[13.9605226517,52.2634506226],"type":"Point"}
}