{
  "type": "Feature",
  "properties": {
    "iso:country":"DE",
    "sg:address":"Stra\u00dfburger Str. 2",
    "sg:city":"Herne",
    "sg:phone":"+49 2323/451364",
    "sg:postcode":"44623",
    "sg:province":"Nordrhein-Westfalen",
    "wof:name":"Ostentor",
    "wof:placetype":"venue"
},
  "geometry": {"coordinates":[7.229569912,51.5360450745],"type":"Point"}
}