{
  "type": "Feature",
  "properties": {
    "iso:country":"DE",
    "sg:address":"Georgstr. 28",
    "sg:city":"Bonn",
    "sg:phone":"+49 228/3694949",
    "sg:postcode":"53111",
    "sg:province":"Nordrhein-Westfalen",
    "wof:name":"Strandhaus Restaurant",
    "wof:placetype":"venue"
},
  "geometry": {"coordinates":[7.0920062065,50.7421569824],"type":"Point"}
}