{
  "type": "Feature",
  "properties": {
    "iso:country":"DE",
    "sg:address":"Infanteriestr. 1",
    "sg:city":"M\u00fcnchen",
    "sg:postcode":"80797",
    "sg:province":"Bayern",
    "wof:name":"Verband F\u00fcr L\u00e4nderentwicklung M\u00fcnchen",
    "wof:placetype":"venue"
},
  "geometry": {"coordinates":[11.55788517,48.1570892334],"type":"Point"}
}