{
  "type": "Feature",
  "properties": {
    "iso:country":"DE",
    "sg:address":"Pointweg 9",
    "sg:city":"Hauzenberg",
    "sg:phone":"+49 8586/96190",
    "sg:postcode":"94051",
    "sg:province":"Bayern",
    "wof:name":"Otto Bauer",
    "wof:placetype":"venue"
},
  "geometry": {"coordinates":[13.621866,48.653194],"type":"Point"}
}