{
  "type": "Feature",
  "properties": {
    "iso:country":"DE",
    "sg:address":"Kreuzberger Ring 44 A",
    "sg:city":"Wiesbaden",
    "sg:postcode":"65205",
    "sg:province":"Hessen",
    "wof:name":"N. Schlumberger & Cie Deutschland Gmbh",
    "wof:placetype":"venue"
},
  "geometry": {"coordinates":[8.289975,50.054337],"type":"Point"}
}