{
  "type": "Feature",
  "properties": {
    "iso:country":"DE",
    "sg:address":"Kreuzgasse 47d",
    "sg:city":"Markdorf",
    "sg:phone":"+49 7544/8314",
    "sg:postcode":"88677",
    "sg:province":"Baden-W\u00fcrttemberg",
    "wof:name":"Sonja Hedra",
    "wof:placetype":"venue"
},
  "geometry": {"coordinates":[9.387005806,47.7282867432],"type":"Point"}
}