{
  "type": "Feature",
  "properties": {
    "iso:country":"DE",
    "sg:address":"Marienplatz 4",
    "sg:city":"Stuttgart",
    "sg:phone":"+49 711/600133",
    "sg:postcode":"70178",
    "sg:province":"Baden-W\u00fcrttemberg",
    "wof:name":"Gasfeuer Gmbh",
    "wof:placetype":"venue"
},
  "geometry": {"coordinates":[9.1673460007,48.7646141052],"type":"Point"}
}