{
  "type": "Feature",
  "properties": {
    "iso:country":"DE",
    "sg:address":"Alter Markt 40",
    "sg:city":"Arnsberg",
    "sg:phone":"+49 2931/22870",
    "sg:postcode":"59821",
    "sg:province":"Nordrhein-Westfalen",
    "wof:name":"Silke Ossendoth Rechtsanwalt",
    "wof:placetype":"venue"
},
  "geometry": {"coordinates":[8.0638504028,51.3976593018],"type":"Point"}
}