{
  "type": "Feature",
  "properties": {
    "iso:country":"DE",
    "sg:address":"Talm\u00fchle 3",
    "sg:city":"Neubulach",
    "sg:phone":"+49 7053/96980",
    "sg:postcode":"75387",
    "sg:province":"Baden-W\u00fcrttemberg",
    "wof:name":"Wengen Gmbh & Co. Kg",
    "wof:placetype":"venue"
},
  "geometry": {"coordinates":[8.725809,48.657803],"type":"Point"}
}