{
  "type": "Feature",
  "properties": {
    "iso:country":"DE",
    "sg:address":"Brutkampsweg 12",
    "sg:city":"Albersdorf",
    "sg:phone":"+49 4835/8708",
    "sg:postcode":"25767",
    "sg:province":"Schleswig-Holstein",
    "wof:name":"Heinr. Und P. Thede Grabdenkm\u00e4ler",
    "wof:placetype":"venue"
},
  "geometry": {"coordinates":[9.2868776321,54.1446838379],"type":"Point"}
}