{
  "type": "Feature",
  "properties": {
    "iso:country":"DE",
    "sg:address":"Gartenweg 1",
    "sg:city":"Burghaun",
    "sg:phone":"+49 6652/2199",
    "sg:postcode":"36151",
    "sg:province":"Hessen",
    "wof:name":"Anselm G\u00f6bel Architekt",
    "wof:placetype":"venue"
},
  "geometry": {"coordinates":[9.723146,50.697384],"type":"Point"}
}