{
  "type": "Feature",
  "properties": {
    "iso:country":"DE",
    "sg:address":"Ringhofstr. 13",
    "sg:city":"Kassel",
    "sg:phone":"+49 561/571199",
    "sg:postcode":"34123",
    "sg:province":"Hessen",
    "wof:name":"Johann Kuhlen Detektei",
    "wof:placetype":"venue"
},
  "geometry": {"coordinates":[9.527975,51.306671],"type":"Point"}
}