{
  "type": "Feature",
  "properties": {
    "iso:country":"DE",
    "sg:address":"Vo\u00dfstr. 3",
    "sg:city":"Herzogenrath",
    "sg:phone":"+49 2406/61485",
    "sg:postcode":"52134",
    "sg:province":"Nordrhein-Westfalen",
    "wof:name":"Hermann Mikolajczak",
    "wof:placetype":"venue"
},
  "geometry": {"coordinates":[6.0961480141,50.8814125061],"type":"Point"}
}