{
  "type": "Feature",
  "properties": {
    "iso:country":"DE",
    "sg:address":"Krefelder Str.",
    "sg:city":"Meerbusch",
    "sg:postcode":"40670",
    "sg:province":"Nordrhein-Westfalen",
    "wof:name":"Maxus-baumarkt",
    "wof:placetype":"venue"
},
  "geometry": {"coordinates":[6.6140232086,51.2796440125],"type":"Point"}
}