{
  "type": "Feature",
  "properties": {
    "iso:country":"DE",
    "sg:address":"Genfer Str.",
    "sg:city":"Berlin",
    "sg:postcode":"13407",
    "sg:province":"Berlin",
    "wof:name":"M\u00fccke Malereibetriebs Gmbh",
    "wof:placetype":"venue"
},
  "geometry": {"coordinates":[13.353094,52.570198],"type":"Point"}
}