{
  "type": "Feature",
  "properties": {
    "iso:country":"DE",
    "sg:address":"Rodinger Str 5",
    "sg:city":"Cham",
    "sg:phone":"+49 7264/4032",
    "sg:postcode":"93413",
    "sg:province":"Bayern",
    "wof:name":"Druckerei Stein Gmbh",
    "wof:placetype":"venue"
},
  "geometry": {"coordinates":[9.1029014587,49.2387924194],"type":"Point"}
}