{
  "type": "Feature",
  "properties": {
    "iso:country":"DE",
    "sg:address":"Neustr. 25",
    "sg:city":"Schweich",
    "sg:phone":"+49 6502/2293",
    "sg:postcode":"54338",
    "sg:province":"Rheinland-Pfalz",
    "wof:name":"Marco Johl Gmbh",
    "wof:placetype":"venue"
},
  "geometry": {"coordinates":[6.755537,49.819725],"type":"Point"}
}