{
  "type": "Feature",
  "properties": {
    "iso:country":"DE",
    "sg:address":"Leverkusenstr. 3",
    "sg:city":"Hamburg",
    "sg:phone":"+49 40/8513232",
    "sg:postcode":"22761",
    "sg:province":"Hamburg",
    "wof:name":"Sternhagen Schlauchtechnik Vertretung",
    "wof:placetype":"venue"
},
  "geometry": {"coordinates":[9.9268007278,53.5647468567],"type":"Point"}
}