{
  "type": "Feature",
  "properties": {
    "iso:country":"DE",
    "sg:address":"Lindenstr. 14",
    "sg:city":"Gerlebogk",
    "sg:phone":"+49 34691/22598",
    "sg:postcode":"06420",
    "sg:province":"Sachsen-Anhalt",
    "wof:name":"Rolf Rau",
    "wof:placetype":"venue"
},
  "geometry": {"coordinates":[11.839715,51.70816],"type":"Point"}
}