{
  "type": "Feature",
  "properties": {
    "iso:country":"DE",
    "sg:address":"Hauptstr. 27",
    "sg:city":"Dallmin",
    "sg:phone":"+49 38783/60336",
    "sg:postcode":"19357",
    "sg:province":"Brandenburg",
    "wof:name":"I. M\u00fcller",
    "wof:placetype":"venue"
},
  "geometry": {"coordinates":[11.7710676193,53.2034683228],"type":"Point"}
}