{
  "type": "Feature",
  "properties": {
    "iso:country":"DE",
    "sg:address":"Yorckstr 22",
    "sg:city":"Regensburg",
    "sg:phone":"+49 941/3074330",
    "sg:postcode":"93049",
    "sg:province":"Bayern",
    "wof:name":"Ses Gmbh",
    "wof:placetype":"venue"
},
  "geometry": {"coordinates":[12.0601997375,49.0127983093],"type":"Point"}
}