{
  "type": "Feature",
  "properties": {
    "iso:country":"DE",
    "sg:address":"W\u00e4ssernachstr. 65",
    "sg:city":"Ha\u00dffurt",
    "sg:phone":"+49 9521/5477",
    "sg:postcode":"97437",
    "sg:province":"Bayern",
    "wof:name":"W\u00e4ssernachhalle",
    "wof:placetype":"venue"
},
  "geometry": {"coordinates":[10.4718704224,50.0339584351],"type":"Point"}
}