{
  "type": "Feature",
  "properties": {
    "iso:country":"DE",
    "sg:address":"Weilheimer Str. 20",
    "sg:city":"Vilgertshofen",
    "sg:phone":"+49 8194/376",
    "sg:postcode":"86946",
    "sg:province":"Bayern",
    "wof:name":"K. Gistl",
    "wof:placetype":"venue"
},
  "geometry": {"coordinates":[10.922142,47.965492],"type":"Point"}
}