{
  "type": "Feature",
  "properties": {
    "iso:country":"DE",
    "sg:address":"Am M\u00fchlenacker 33",
    "sg:city":"Uetze",
    "sg:phone":"+49 5147/603",
    "sg:postcode":"31311",
    "sg:province":"Niedersachsen",
    "wof:name":"Friedrich Flebbe",
    "wof:placetype":"venue"
},
  "geometry": {"coordinates":[10.0884666443,52.4850540161],"type":"Point"}
}