{
  "type": "Feature",
  "properties": {
    "iso:country":"DE",
    "sg:address":"Treuenbrietzener Str. 8",
    "sg:city":"Berlin",
    "sg:postcode":"13439",
    "sg:province":"Berlin",
    "wof:name":"Malereibetrieb Vom Hagen & Busch Gmbh",
    "wof:placetype":"venue"
},
  "geometry": {"coordinates":[13.360531,52.598743],"type":"Point"}
}