{
  "type": "Feature",
  "properties": {
    "iso:country":"DE",
    "sg:address":"Schwabstr. 117",
    "sg:city":"Marbach",
    "sg:phone":"+49 7144/5433",
    "sg:postcode":"71672",
    "sg:province":"Baden-W\u00fcrttemberg",
    "wof:name":"Kurt Kaiser Architekt",
    "wof:placetype":"venue"
},
  "geometry": {"coordinates":[9.27521,48.939327],"type":"Point"}
}