{
  "type": "Feature",
  "properties": {
    "iso:country":"DE",
    "sg:address":"R\u00fcckertstr. 6",
    "sg:city":"Frankfurt",
    "sg:phone":"+49 69/4950134",
    "sg:postcode":"60314",
    "sg:province":"Hessen",
    "wof:name":"Cooperation Atelier Gbr",
    "wof:placetype":"venue"
},
  "geometry": {"coordinates":[8.69984,50.11034],"type":"Point"}
}