{
  "type": "Feature",
  "properties": {
    "iso:country":"DE",
    "sg:address":"Am Michaelshof 4b",
    "sg:city":"Bonn",
    "sg:phone":"+49 228/356440",
    "sg:postcode":"53177",
    "sg:province":"Nordrhein-Westfalen",
    "wof:name":"Bonner Steffi",
    "wof:placetype":"venue"
},
  "geometry": {"coordinates":[7.1525568962,50.6837348938],"type":"Point"}
}