{
  "type": "Feature",
  "properties": {
    "iso:country":"DE",
    "sg:address":"Hauptstr. 63",
    "sg:city":"Esslingen",
    "sg:phone":"+49 711/367276",
    "sg:postcode":"73730",
    "sg:province":"Baden-W\u00fcrttemberg",
    "wof:name":"R. M\u00e4ckle Mech. Werkstatt",
    "wof:placetype":"venue"
},
  "geometry": {"coordinates":[6.525672,49.912453],"type":"Point"}
}