{
  "type": "Feature",
  "properties": {
    "iso:country":"DE",
    "sg:address":"Nu\u00dfallee 6",
    "sg:city":"Bonn",
    "sg:phone":"+49 228/732301",
    "sg:postcode":"53115",
    "sg:province":"Nordrhein-Westfalen",
    "wof:name":"Institut F. Pharmazeutische Biologie",
    "wof:placetype":"venue"
},
  "geometry": {"coordinates":[7.0901241302,50.7262840271],"type":"Point"}
}