{
  "type": "Feature",
  "properties": {
    "iso:country":"DE",
    "sg:address":"Hauptstr. 37",
    "sg:city":"Urmitz",
    "sg:phone":"+49 2630/7800",
    "sg:postcode":"56220",
    "sg:province":"Rheinland-Pfalz",
    "wof:name":"A. Dutz",
    "wof:placetype":"venue"
},
  "geometry": {"coordinates":[7.520512,50.415947],"type":"Point"}
}