{
  "type": "Feature",
  "properties": {
    "iso:country":"DE",
    "sg:address":"M\u00fcnchen-Flughafen",
    "sg:city":"M\u00fcnchen-Flughafen",
    "sg:phone":"+49 89/97596666",
    "sg:postcode":"85356",
    "sg:province":"Bayern",
    "wof:name":"Sixt Ag",
    "wof:placetype":"venue"
},
  "geometry": {"coordinates":[-114.195442,32.86412],"type":"Point"}
}