{
  "type": "Feature",
  "properties": {
    "iso:country":"DE",
    "sg:address":"Hauptstr 1",
    "sg:city":"H\u00f6ckendorf",
    "sg:phone":"+49 35055/61317",
    "sg:postcode":"01774",
    "sg:province":"Sachsen",
    "wof:name":"Lehmann Saunabau",
    "wof:placetype":"venue"
},
  "geometry": {"coordinates":[13.6140966415,50.9412689209],"type":"Point"}
}