{
  "type": "Feature",
  "properties": {
    "iso:country":"DE",
    "sg:address":"Hauptstr. 37",
    "sg:city":"Wunstorf",
    "sg:phone":"+49 5031/74217",
    "sg:postcode":"31515",
    "sg:province":"Niedersachsen",
    "wof:name":"Engelke Drogerie",
    "wof:placetype":"venue"
},
  "geometry": {"coordinates":[9.470755,52.426727],"type":"Point"}
}