{
  "type": "Feature",
  "properties": {
    "iso:country":"DE",
    "sg:address":"Angerm\u00fcnder Str.",
    "sg:city":"Joachimsthal",
    "sg:postcode":"16247",
    "sg:province":"Brandenburg",
    "wof:name":"Aldi Gmbh & Co. Kg",
    "wof:placetype":"venue"
},
  "geometry": {"coordinates":[13.76679039,52.9681892395],"type":"Point"}
}