{
  "type": "Feature",
  "properties": {
    "iso:country":"DE",
    "sg:address":"Wendelstr. 132",
    "sg:city":"Wadgassen",
    "sg:phone":"+49 6834/48182",
    "sg:postcode":"66787",
    "sg:province":"Saarland",
    "wof:name":"Pflegedienst Cavelius-kr\u00e4mer",
    "wof:placetype":"venue"
},
  "geometry": {"coordinates":[6.795118,49.256889],"type":"Point"}
}