{
  "type": "Feature",
  "properties": {
    "iso:country":"DE",
    "sg:address":"Hamburger Str. 36-44",
    "sg:city":"Dortmund",
    "sg:postcode":"44135",
    "sg:province":"Nordrhein-Westfalen",
    "wof:name":"Teppich Center Dortmund Gmbh & Co. Kg",
    "wof:placetype":"venue"
},
  "geometry": {"coordinates":[7.4790301323,51.5144309998],"type":"Point"}
}