{
  "type": "Feature",
  "properties": {
    "iso:country":"DE",
    "sg:address":"Lindenstr. 24-26",
    "sg:city":"Bad S\u00e4ckingen",
    "sg:phone":"+49 7761/2395",
    "sg:postcode":"79713",
    "sg:province":"Baden-W\u00fcrttemberg",
    "wof:name":"Pieper Maschinenbau Gmbh",
    "wof:placetype":"venue"
},
  "geometry": {"coordinates":[7.916246,47.561836],"type":"Point"}
}