{
  "type": "Feature",
  "properties": {
    "iso:country":"DE",
    "sg:address":"Grabenring 26",
    "sg:city":"Br\u00e4unlingen",
    "sg:phone":"+49 771/973203",
    "sg:postcode":"78199",
    "sg:province":"Baden-W\u00fcrttemberg",
    "wof:name":"Addimult Orthop\u00e4dische Apparate Gmbh",
    "wof:placetype":"venue"
},
  "geometry": {"coordinates":[8.449927,47.929943],"type":"Point"}
}