{
  "type": "Feature",
  "properties": {
    "iso:country":"DE",
    "sg:address":"Hauptstr. 22",
    "sg:city":"Wietzendorf",
    "sg:phone":"+49 5196/379",
    "sg:postcode":"29649",
    "sg:province":"Niedersachsen",
    "wof:name":"Ev. Luth. Pfarramt Gem. Wietzendorf",
    "wof:placetype":"venue"
},
  "geometry": {"coordinates":[9.9764032364,52.9162483215],"type":"Point"}
}