{
  "type": "Feature",
  "properties": {
    "iso:country":"DE",
    "sg:address":"Wiescher Str. 13",
    "sg:city":"Wuppertal",
    "sg:phone":"+49 4920/2523132",
    "sg:postcode":"42277",
    "sg:province":"Nordrhein-Westfalen",
    "wof:name":"R\u00dcckemann & Pfuhler Gmbh",
    "wof:placetype":"venue"
},
  "geometry": {"coordinates":[7.222656,51.287159],"type":"Point"}
}