{
  "type": "Feature",
  "properties": {
    "iso:country":"DE",
    "sg:address":"Gutenbergstr. 3",
    "sg:city":"Sarstedt",
    "sg:phone":"+49 4950/665272",
    "sg:postcode":"31157",
    "sg:province":"Niedersachsen",
    "wof:name":"Sch\u00c4fer Druckerei",
    "wof:placetype":"venue"
},
  "geometry": {"coordinates":[9.860162735,52.2458992004],"type":"Point"}
}