{
  "type": "Feature",
  "properties": {
    "iso:country":"DE",
    "sg:address":"K\u00f6nigswinterer Str. 598",
    "sg:city":"Bonn",
    "sg:phone":"+49 228/441444",
    "sg:postcode":"53227",
    "sg:province":"Nordrhein-Westfalen",
    "wof:name":"D. Georg Maximilian Masseur",
    "wof:placetype":"venue"
},
  "geometry": {"coordinates":[7.156337,50.720222],"type":"Point"}
}