{
  "type": "Feature",
  "properties": {
    "iso:country":"DE",
    "sg:address":"Breiteweg 11",
    "sg:city":"Egeln",
    "sg:phone":"+49 39268/2868",
    "sg:postcode":"39435",
    "sg:province":"Sachsen-Anhalt",
    "wof:name":"Herzog Und G\u00f6bbel Ingenieure",
    "wof:placetype":"venue"
},
  "geometry": {"coordinates":[11.4274492264,51.9417724609],"type":"Point"}
}