{
  "type": "Feature",
  "properties": {
    "iso:country":"DE",
    "sg:address":"Brenscheder Str. 72",
    "sg:city":"Bochum",
    "sg:phone":"+49 234/72579",
    "sg:postcode":"44799",
    "sg:province":"Nordrhein-Westfalen",
    "wof:name":"P. Weinz",
    "wof:placetype":"venue"
},
  "geometry": {"coordinates":[7.2299427986,51.44972229],"type":"Point"}
}