{
  "type": "Feature",
  "properties": {
    "iso:country":"DE",
    "sg:address":"Bismarckstr. 34",
    "sg:city":"Reutlingen",
    "sg:phone":"+49 7121/470583",
    "sg:postcode":"72764",
    "sg:province":"Baden-W\u00fcrttemberg",
    "wof:name":"M. Koch",
    "wof:placetype":"venue"
},
  "geometry": {"coordinates":[9.2175912857,48.4941520691],"type":"Point"}
}