{
  "type": "Feature",
  "properties": {
    "iso:country":"DE",
    "sg:address":"Frankfurter Str. 150",
    "sg:city":"Hennef",
    "sg:phone":"+49 2242/2633",
    "sg:postcode":"53773",
    "sg:province":"Nordrhein-Westfalen",
    "wof:name":"Hotel Johnel",
    "wof:placetype":"venue"
},
  "geometry": {"coordinates":[7.2777447701,50.7776756287],"type":"Point"}
}