{
  "type": "Feature",
  "properties": {
    "iso:country":"DE",
    "sg:address":"Rudolph-Zentgraf-Str. 1",
    "sg:city":"Echzell",
    "sg:phone":"+49 6035/91920",
    "sg:postcode":"61209",
    "sg:province":"Hessen",
    "wof:name":"Hans Hermann Nahrgang Heilpraktiker",
    "wof:placetype":"venue"
},
  "geometry": {"coordinates":[8.897143364,50.375579834],"type":"Point"}
}