{
  "type": "Feature",
  "properties": {
    "iso:country":"DE",
    "sg:address":"Ackerstr 6",
    "sg:city":"Neubrandenburg",
    "sg:phone":"+49 395/5443711",
    "sg:postcode":"17033",
    "sg:province":"Mecklenburg-Vorpommern",
    "wof:name":"Geb\u00e4ude- Und Industriereinigung D\u00f6hren Gmbh",
    "wof:placetype":"venue"
},
  "geometry": {"coordinates":[13.2732391357,53.5591011047],"type":"Point"}
}