{
  "type": "Feature",
  "properties": {
    "iso:country":"DE",
    "sg:address":"Eschersheimer Landstr. 55",
    "sg:city":"Frankfurt",
    "sg:phone":"+49 69/288531",
    "sg:postcode":"60322",
    "sg:province":"Hessen",
    "wof:name":"Orient-teppiche Jasman Bijan Motamedi",
    "wof:placetype":"venue"
},
  "geometry": {"coordinates":[8.6754379272,50.1216278076],"type":"Point"}
}