{
  "type": "Feature",
  "properties": {
    "iso:country":"DE",
    "sg:address":"Nieder-R\u00f6der-Str. 1",
    "sg:city":"Rodgau",
    "sg:phone":"+49 6106/82210",
    "sg:postcode":"63110",
    "sg:province":"Hessen",
    "wof:name":"Toom-markt Gmbh",
    "wof:placetype":"venue"
},
  "geometry": {"coordinates":[8.8904752731,50.0052680969],"type":"Point"}
}