{
  "type": "Feature",
  "properties": {
    "iso:country":"DE",
    "sg:address":"Vor dem Tore 6",
    "sg:city":"Wunstorf",
    "sg:phone":"+49 5033/8432",
    "sg:postcode":"31515",
    "sg:province":"Niedersachsen",
    "wof:name":"Heinrich Thiele",
    "wof:placetype":"venue"
},
  "geometry": {"coordinates":[9.3558597565,52.4538726807],"type":"Point"}
}