{
  "type": "Feature",
  "properties": {
    "iso:country":"DE",
    "sg:address":"Am Rosenberg 4",
    "sg:city":"Schlangen",
    "sg:phone":"+49 5252/7400",
    "sg:postcode":"33189",
    "sg:province":"Nordrhein-Westfalen",
    "wof:name":"Vasco Heizungsger\u00e4te Gmbh",
    "wof:placetype":"venue"
},
  "geometry": {"coordinates":[8.8599481583,51.8238258362],"type":"Point"}
}