{
  "type": "Feature",
  "properties": {
    "iso:country":"DE",
    "sg:address":"Bahnhofstr. 22",
    "sg:city":"Regensburg",
    "sg:phone":"+49 941/51515",
    "sg:postcode":"93047",
    "sg:province":"Bayern",
    "wof:name":"H & F Autovermietung Gmbh",
    "wof:placetype":"venue"
},
  "geometry": {"coordinates":[12.10222,49.012684],"type":"Point"}
}