{
  "type": "Feature",
  "properties": {
    "iso:country":"DE",
    "sg:address":"An der R\u00fcster 2",
    "sg:city":"Sommerfelde",
    "sg:phone":"+49 3334/24251",
    "sg:postcode":"16230",
    "sg:province":"Brandenburg",
    "wof:name":"R. K\u00fcter",
    "wof:placetype":"venue"
},
  "geometry": {"coordinates":[13.875075,52.905895],"type":"Point"}
}