{
  "type": "Feature",
  "properties": {
    "iso:country":"DE",
    "sg:address":"Dorfstr. 11",
    "sg:city":"Vaterstetten",
    "sg:phone":"+49 8106/1415",
    "sg:postcode":"85591",
    "sg:province":"Bayern",
    "wof:name":"David Bekker",
    "wof:placetype":"venue"
},
  "geometry": {"coordinates":[11.772315979,48.110824585],"type":"Point"}
}