{
  "type": "Feature",
  "properties": {
    "iso:country":"DE",
    "sg:address":"B\u00e4ckstr. 15",
    "sg:city":"Geseke",
    "sg:phone":"+49 2942/4681",
    "sg:postcode":"59590",
    "sg:province":"Nordrhein-Westfalen",
    "wof:name":"Dagmar Und Peter Fabritz",
    "wof:placetype":"venue"
},
  "geometry": {"coordinates":[8.5089159012,51.6406211853],"type":"Point"}
}