{
  "type": "Feature",
  "properties": {
    "iso:country":"DE",
    "sg:address":"Schlo\u00df Kirchberg",
    "sg:city":"Hagnau",
    "sg:postcode":"88709",
    "sg:province":"Baden-W\u00fcrttemberg",
    "wof:name":"Schlo\u00df Kirchberg Campingplatz",
    "wof:placetype":"venue"
},
  "geometry": {"coordinates":[9.272445,47.694664],"type":"Point"}
}