{
  "type": "Feature",
  "properties": {
    "iso:country":"DE",
    "sg:address":"Neuburger Str. 8",
    "sg:city":"Augsburg",
    "sg:phone":"+49 821/791374",
    "sg:postcode":"86167",
    "sg:province":"Bayern",
    "wof:name":"U. Geiger Wettannahme",
    "wof:placetype":"venue"
},
  "geometry": {"coordinates":[10.914548,48.377991],"type":"Point"}
}