{
  "type": "Feature",
  "properties": {
    "iso:country":"DE",
    "sg:address":"Berliner Ring 27",
    "sg:city":"Wyk",
    "sg:phone":"+49 4681/8277",
    "sg:postcode":"25938",
    "sg:province":"Schleswig-Holstein",
    "wof:name":"Heinz-georg Holtzer Masseur",
    "wof:placetype":"venue"
},
  "geometry": {"coordinates":[8.555486,54.687386],"type":"Point"}
}