{
  "type": "Feature",
  "properties": {
    "iso:country":"DE",
    "sg:address":"Lithweg 40",
    "sg:city":"Porta Westfalica",
    "sg:phone":"+49 5731/6101",
    "sg:postcode":"32457",
    "sg:province":"Nordrhein-Westfalen",
    "wof:name":"Dieter H\u00f6ltkemeyer M\u00f6belhandelsgesellschaft Mbh",
    "wof:placetype":"venue"
},
  "geometry": {"coordinates":[8.8776912689,52.226650238],"type":"Point"}
}