{
  "type": "Feature",
  "properties": {
    "iso:country":"DE",
    "sg:address":"Schaertzgensweg 14",
    "sg:city":"Meerbusch",
    "sg:phone":"+49 2132/71826",
    "sg:postcode":"40667",
    "sg:province":"Nordrhein-Westfalen",
    "wof:name":"H. W. Sevenich",
    "wof:placetype":"venue"
},
  "geometry": {"coordinates":[6.6911501884,51.2442817688],"type":"Point"}
}