{
  "type": "Feature",
  "properties": {
    "iso:country":"DE",
    "sg:address":"Eschenallee 24",
    "sg:city":"Burscheid",
    "sg:phone":"+49 2174/786097",
    "sg:postcode":"51399",
    "sg:province":"Nordrhein-Westfalen",
    "wof:name":"Peter Kintscher Unternehmungsberatung-",
    "wof:placetype":"venue"
},
  "geometry": {"coordinates":[7.1344308853,51.0995025635],"type":"Point"}
}