{
  "type": "Feature",
  "properties": {
    "iso:country":"DE",
    "sg:address":"T\u00fcckobsmoor 5",
    "sg:city":"Hamburg",
    "sg:phone":"+49 40/5276924",
    "sg:postcode":"22419",
    "sg:province":"Hamburg",
    "wof:name":"Alois Scheidler Architekt",
    "wof:placetype":"venue"
},
  "geometry": {"coordinates":[10.000641,53.671936],"type":"Point"}
}