{
  "type": "Feature",
  "properties": {
    "iso:country":"DE",
    "sg:address":"Beulenhof 26",
    "sg:city":"Essen",
    "sg:postcode":"45279",
    "sg:province":"Nordrhein-Westfalen",
    "wof:name":"Ruhr Dv Ohg",
    "wof:placetype":"venue"
},
  "geometry": {"coordinates":[7.101749897,51.4302024841],"type":"Point"}
}