{
  "type": "Feature",
  "properties": {
    "iso:country":"DE",
    "sg:address":"Kaiserstr. 77",
    "sg:city":"St. Ingbert",
    "sg:phone":"+49 6894/92660",
    "sg:postcode":"66386",
    "sg:province":"Saarland",
    "wof:name":"Gerhard Hartwig",
    "wof:placetype":"venue"
},
  "geometry": {"coordinates":[7.1176719666,49.2803039551],"type":"Point"}
}