{
  "type": "Feature",
  "properties": {
    "iso:country":"DE",
    "sg:address":"H\u00f6veler Str. 63",
    "sg:city":"Hamm",
    "sg:phone":"+49 2381/62251",
    "sg:postcode":"59073",
    "sg:province":"Nordrhein-Westfalen",
    "wof:name":"Ms-formenbau Gmbh",
    "wof:placetype":"venue"
},
  "geometry": {"coordinates":[7.792599,51.704689],"type":"Point"}
}