{
  "type": "Feature",
  "properties": {
    "iso:country":"DE",
    "sg:address":"Karlstr. 6",
    "sg:city":"Wendlingen",
    "sg:phone":"+49 7024/7504",
    "sg:postcode":"73240",
    "sg:province":"Baden-W\u00fcrttemberg",
    "wof:name":"Frank Schlegel",
    "wof:placetype":"venue"
},
  "geometry": {"coordinates":[9.387517,48.672253],"type":"Point"}
}