{
  "type": "Feature",
  "properties": {
    "iso:country":"DE",
    "sg:address":"Goldschmiedeschulstr. 1",
    "sg:city":"Pforzheim",
    "sg:postcode":"75173",
    "sg:province":"Baden-W\u00fcrttemberg",
    "wof:name":"Melanchthonpfarrei",
    "wof:placetype":"venue"
},
  "geometry": {"coordinates":[8.6991157532,48.8868103027],"type":"Point"}
}