{
  "type": "Feature",
  "properties": {
    "iso:country":"DE",
    "sg:address":"Moorbadstr. 14",
    "sg:city":"Bad Endorf",
    "sg:phone":"+49 8053/9461",
    "sg:postcode":"83093",
    "sg:province":"Bayern",
    "wof:name":"Schwimmbad",
    "wof:placetype":"venue"
},
  "geometry": {"coordinates":[12.3021202087,47.9126091003],"type":"Point"}
}