{
  "type": "Feature",
  "properties": {
    "iso:country":"DE",
    "sg:city":"Wei\u00dfenbrunn",
    "sg:phone":"+49 9261/63600",
    "sg:postcode":"96369",
    "sg:province":"Bayern",
    "wof:name":"G. Stalph",
    "wof:placetype":"venue"
},
  "geometry": {"coordinates":[11.346298,50.200218],"type":"Point"}
}