{
  "type": "Feature",
  "properties": {
    "iso:country":"DE",
    "sg:address":"Schulstr. 46",
    "sg:city":"Kissing",
    "sg:postcode":"86438",
    "sg:province":"Bayern",
    "wof:name":"S\u00fclzer Fahrzeugtechnik Planungs- Und Beratungs Gmbh",
    "wof:placetype":"venue"
},
  "geometry": {"coordinates":[10.9756259918,48.3022842407],"type":"Point"}
}