{
  "type": "Feature",
  "properties": {
    "iso:country":"DE",
    "sg:address":"Hocksteiner Weg 58",
    "sg:city":"M\u00f6nchengladbach",
    "sg:phone":"+49 2166/953829",
    "sg:postcode":"41189",
    "sg:province":"Nordrhein-Westfalen",
    "wof:name":"Dr. Gru\u00df Gmbh",
    "wof:placetype":"venue"
},
  "geometry": {"coordinates":[6.413865,51.138912],"type":"Point"}
}