{
  "type": "Feature",
  "properties": {
    "iso:country":"DE",
    "sg:address":"Vor der Kinzigbr\u00fccke 9b",
    "sg:city":"Hanau",
    "sg:phone":"+49 6181/81127",
    "sg:postcode":"63452",
    "sg:province":"Hessen",
    "wof:name":"O. Wilhelm Immobilienmaklker",
    "wof:placetype":"venue"
},
  "geometry": {"coordinates":[8.9108123779,50.1397399902],"type":"Point"}
}