{
  "type": "Feature",
  "properties": {
    "iso:country":"DE",
    "sg:address":"M\u00fcnchener Str. 15",
    "sg:city":"Erding",
    "sg:phone":"+49 8122/13007",
    "sg:postcode":"85435",
    "sg:province":"Bayern",
    "wof:name":"Heidrun Beer",
    "wof:placetype":"venue"
},
  "geometry": {"coordinates":[11.904504776,48.3049507141],"type":"Point"}
}