{
  "type": "Feature",
  "properties": {
    "iso:country":"DE",
    "sg:address":"Am Sch\u00e4nzchen 23",
    "sg:city":"Bonn",
    "sg:phone":"+49 228/655110",
    "sg:postcode":"53111",
    "sg:province":"Nordrhein-Westfalen",
    "wof:name":"Gerhard Winter",
    "wof:placetype":"venue"
},
  "geometry": {"coordinates":[7.103512,50.744232],"type":"Point"}
}