{
  "type": "Feature",
  "properties": {
    "iso:country":"DE",
    "sg:address":"Kleinfeldstr. 1 c",
    "sg:city":"Germering",
    "sg:phone":"+49 89/8942400",
    "sg:postcode":"82110",
    "sg:province":"Bayern",
    "wof:name":"Eupro Gesellschaft F\u00fcr Grafik Und Printproduktion Gmbh",
    "wof:placetype":"venue"
},
  "geometry": {"coordinates":[11.365647,48.127037],"type":"Point"}
}