{
  "type": "Feature",
  "properties": {
    "iso:country":"DE",
    "sg:address":"Bahnhofstr. 5",
    "sg:city":"Aue",
    "sg:phone":"+49 3771/29010",
    "sg:postcode":"08280",
    "sg:province":"Sachsen",
    "wof:name":"Freund Und Partner Gmbh",
    "wof:placetype":"venue"
},
  "geometry": {"coordinates":[12.7018547058,50.5868759155],"type":"Point"}
}