{
  "type": "Feature",
  "properties": {
    "iso:country":"DE",
    "sg:address":"Vacher Str. 20",
    "sg:city":"Herzogenaurach",
    "sg:phone":"+49 9132/7400",
    "sg:postcode":"91074",
    "sg:province":"Bayern",
    "wof:name":"Tmg Transportm\u00f6rtel Gmbh",
    "wof:placetype":"venue"
},
  "geometry": {"coordinates":[10.8808717728,49.5690612793],"type":"Point"}
}