{
  "type": "Feature",
  "properties": {
    "iso:country":"DE",
    "sg:address":"Hans-Bartels-Str. 5",
    "sg:city":"M\u00fcnchen",
    "sg:phone":"+49 89/337576",
    "sg:postcode":"81545",
    "sg:province":"Bayern",
    "wof:name":"Hans H. Rost Architekt",
    "wof:placetype":"venue"
},
  "geometry": {"coordinates":[11.54931,48.086891],"type":"Point"}
}