{
  "type": "Feature",
  "properties": {
    "iso:country":"DE",
    "sg:address":"Postfach 101733",
    "sg:city":"Moers",
    "sg:phone":"+49 2841/939537",
    "sg:postcode":"47407",
    "sg:province":"Nordrhein-Westfalen",
    "wof:name":"Pds Moers",
    "wof:placetype":"venue"
},
  "geometry": {"coordinates":[6.62172,51.453041],"type":"Point"}
}