{
  "type": "Feature",
  "properties": {
    "iso:country":"DE",
    "sg:address":"L\u00fcbecker Str. 91",
    "sg:city":"Schwerin",
    "sg:postcode":"19053",
    "sg:province":"Mecklenburg-Vorpommern",
    "wof:name":"Vhv-versichewrung",
    "wof:placetype":"venue"
},
  "geometry": {"coordinates":[11.4035921097,53.6334228516],"type":"Point"}
}