{
  "type": "Feature",
  "properties": {
    "iso:country":"DE",
    "sg:address":"Schulgasse 14",
    "sg:city":"Weiden",
    "sg:phone":"+49 961/4162162",
    "sg:postcode":"92637",
    "sg:province":"Bayern",
    "wof:name":"Restaurant Oppe",
    "wof:placetype":"venue"
},
  "geometry": {"coordinates":[12.1620349884,49.6763114929],"type":"Point"}
}