{
  "type": "Feature",
  "properties": {
    "iso:country":"DE",
    "sg:address":"Himmelreich 34",
    "sg:city":"Olsberg-Antfeld",
    "sg:phone":"+49 2962/5377",
    "sg:postcode":"59939",
    "sg:province":"Nordrhein-Westfalen",
    "wof:name":"Sch\u00fctzenverein Antfeld",
    "wof:placetype":"venue"
},
  "geometry": {"coordinates":[8.474753,51.372581],"type":"Point"}
}