{
  "type": "Feature",
  "properties": {
    "iso:country":"DE",
    "sg:address":"Alte Poststr. 13",
    "sg:city":"Bassum",
    "sg:phone":"+49 4241/2456",
    "sg:postcode":"27211",
    "sg:province":"Niedersachsen",
    "wof:name":"L\u00f6wen-apotheke",
    "wof:placetype":"venue"
},
  "geometry": {"coordinates":[8.728014,52.848125],"type":"Point"}
}