{
  "type": "Feature",
  "properties": {
    "iso:country":"DE",
    "sg:address":"Industriestr. 38",
    "sg:city":"Gundelfingen",
    "sg:phone":"+49 761/503190",
    "sg:postcode":"79194",
    "sg:province":"Baden-W\u00fcrttemberg",
    "wof:name":"Klotzbach Verwaltungs Gmbh",
    "wof:placetype":"venue"
},
  "geometry": {"coordinates":[7.8594350815,48.0463638306],"type":"Point"}
}