{
  "type": "Feature",
  "properties": {
    "iso:country":"DE",
    "sg:address":"Zwickauer Str. 404",
    "sg:city":"Chemnitz",
    "sg:phone":"+49 371/5229190",
    "sg:postcode":"09117",
    "sg:province":"Sachsen",
    "wof:name":"Ibis Acam Gmbh",
    "wof:placetype":"venue"
},
  "geometry": {"coordinates":[12.8508405685,50.8180999756],"type":"Point"}
}