{
  "type": "Feature",
  "properties": {
    "iso:country":"DE",
    "sg:address":"Kochstr 40",
    "sg:city":"Rietberg",
    "sg:phone":"+49 5244/988156",
    "sg:postcode":"33397",
    "sg:province":"Nordrhein-Westfalen",
    "wof:name":"Verfahrenstechnik Merschbrock Ek",
    "wof:placetype":"venue"
},
  "geometry": {"coordinates":[8.4393558502,51.8165435791],"type":"Point"}
}