{
  "type": "Feature",
  "properties": {
    "iso:country":"DE",
    "sg:address":"Celler Str. 14A",
    "sg:city":"Hermannsburg",
    "sg:phone":"+49 5052/3776",
    "sg:postcode":"29320",
    "sg:province":"Niedersachsen",
    "wof:name":"Restaurant Elena Gebr. Kosmidis Gmbh",
    "wof:placetype":"venue"
},
  "geometry": {"coordinates":[10.0872974396,52.830165863],"type":"Point"}
}