{
  "type": "Feature",
  "properties": {
    "iso:country":"DE",
    "sg:address":"Marktstr. 59",
    "sg:city":"Bad T\u00f6lz",
    "sg:phone":"+49 8041/78370",
    "sg:postcode":"83646",
    "sg:province":"Bayern",
    "wof:name":"Steinacker-optik",
    "wof:placetype":"venue"
},
  "geometry": {"coordinates":[11.5611486435,47.7611885071],"type":"Point"}
}