{
  "type": "Feature",
  "properties": {
    "iso:country":"DE",
    "sg:address":"M\u00f6gglinger Str. 35",
    "sg:city":"Heubach",
    "sg:phone":"+49 7173/4125",
    "sg:postcode":"73540",
    "sg:province":"Baden-W\u00fcrttemberg",
    "wof:name":"Wilhelm Maier",
    "wof:placetype":"venue"
},
  "geometry": {"coordinates":[9.9365568161,48.7958602905],"type":"Point"}
}