{
  "type": "Feature",
  "properties": {
    "iso:country":"DE",
    "sg:address":"Tiroler Str. 36a",
    "sg:city":"Recklinghausen",
    "sg:phone":"+49 2361/31759",
    "sg:postcode":"45659",
    "sg:province":"Nordrhein-Westfalen",
    "wof:name":"Brokbals",
    "wof:placetype":"venue"
},
  "geometry": {"coordinates":[7.203971,51.58791],"type":"Point"}
}