{
  "type": "Feature",
  "properties": {
    "iso:country":"DE",
    "sg:address":"Winsener Str. 33",
    "sg:city":"Hamburg",
    "sg:phone":"+49 40/7643701",
    "sg:postcode":"21077",
    "sg:province":"Hamburg",
    "wof:name":"Peter Kupfer",
    "wof:placetype":"venue"
},
  "geometry": {"coordinates":[9.98837,53.448837],"type":"Point"}
}