{
  "type": "Feature",
  "properties": {
    "iso:country":"DE",
    "sg:address":"Elverdisser Str. 42",
    "sg:city":"Herford",
    "sg:phone":"+49 5221/74703",
    "sg:postcode":"32052",
    "sg:province":"Nordrhein-Westfalen",
    "wof:name":"Laterne",
    "wof:placetype":"venue"
},
  "geometry": {"coordinates":[8.6679906845,52.1080436707],"type":"Point"}
}