{
  "type": "Feature",
  "properties": {
    "iso:country":"DE",
    "sg:address":"Untere M\u00fchle 1",
    "sg:city":"Krauchenwies",
    "sg:phone":"+49 7576/1714",
    "sg:postcode":"72505",
    "sg:province":"Baden-W\u00fcrttemberg",
    "wof:name":"Willi Knaus M\u00fchle Und Landhandel",
    "wof:placetype":"venue"
},
  "geometry": {"coordinates":[9.2365951538,47.9984588623],"type":"Point"}
}