{
  "type": "Feature",
  "properties": {
    "iso:country":"DE",
    "sg:address":"Hauptstr. 134",
    "sg:city":"Fischbach",
    "sg:phone":"+49 6784/1898",
    "sg:postcode":"55743",
    "sg:province":"Rheinland-Pfalz",
    "wof:name":"Klaus K\u00f6hler",
    "wof:placetype":"venue"
},
  "geometry": {"coordinates":[7.391685009,49.7450485229],"type":"Point"}
}