{
  "type": "Feature",
  "properties": {
    "iso:country":"DE",
    "sg:address":"Ritterb\u00fcschel 73",
    "sg:city":"Neustadt",
    "sg:phone":"+49 6327/677",
    "sg:postcode":"67435",
    "sg:province":"Rheinland-Pfalz",
    "wof:name":"Hermann Lagas",
    "wof:placetype":"venue"
},
  "geometry": {"coordinates":[8.1700162888,49.3700065613],"type":"Point"}
}