{
  "type": "Feature",
  "properties": {
    "iso:country":"DE",
    "sg:address":"Gahlener Str. 18",
    "sg:city":"Dorsten",
    "sg:postcode":"46282",
    "sg:province":"Nordrhein-Westfalen",
    "wof:name":"Praxis Dr.med.harbrecht Prof.dr.med.habil L.l\u00f6be",
    "wof:placetype":"venue"
},
  "geometry": {"coordinates":[6.960881,51.659348],"type":"Point"}
}