{
  "type": "Feature",
  "properties": {
    "iso:country":"DE",
    "sg:address":"Auf der Kunst 24",
    "sg:city":"Siegen",
    "sg:phone":"+49 271/354007",
    "sg:postcode":"57080",
    "sg:province":"Nordrhein-Westfalen",
    "wof:name":"Alfred Seidel",
    "wof:placetype":"venue"
},
  "geometry": {"coordinates":[7.962969,50.854645],"type":"Point"}
}