{
  "type": "Feature",
  "properties": {
    "iso:country":"DE",
    "sg:address":"Bahnhofstr. 1",
    "sg:city":"Niederndodeleben",
    "sg:phone":"+49 39204/85920",
    "sg:postcode":"39167",
    "sg:province":"Sachsen-Anhalt",
    "wof:name":"B\u00f6rde-sand Gmbh & Co. Kg",
    "wof:placetype":"venue"
},
  "geometry": {"coordinates":[11.5011034012,52.1314811707],"type":"Point"}
}