{
  "type": "Feature",
  "properties": {
    "iso:country":"DE",
    "sg:address":"Bahnhofstr. 10",
    "sg:city":"Hinzert-P\u00f6lert",
    "sg:phone":"+49 6586/583",
    "sg:postcode":"54421",
    "sg:province":"Rheinland-Pfalz",
    "wof:name":"N. Breit",
    "wof:placetype":"venue"
},
  "geometry": {"coordinates":[6.908272,49.699234],"type":"Point"}
}