{
  "type": "Feature",
  "properties": {
    "iso:country":"DE",
    "sg:address":"Hansaring 32",
    "sg:city":"M\u00fcnster",
    "sg:phone":"+49 251/665859",
    "sg:postcode":"48155",
    "sg:province":"Nordrhein-Westfalen",
    "wof:name":"Willi Sch\u00e4per Rechtsanwalt",
    "wof:placetype":"venue"
},
  "geometry": {"coordinates":[7.6403689384,51.9530258179],"type":"Point"}
}