{
  "type": "Feature",
  "properties": {
    "iso:country":"DE",
    "sg:address":"Clausewitzstr. 5",
    "sg:city":"Berlin",
    "sg:postcode":"10629",
    "sg:province":"Berlin",
    "wof:name":"Belipro Berliner Ingenieur-und Projektgesellschaft Mbh",
    "wof:placetype":"venue"
},
  "geometry": {"coordinates":[13.3090133667,52.5005989075],"type":"Point"}
}