{
  "type": "Feature",
  "properties": {
    "iso:country":"DE",
    "sg:address":"Gehlenbrink 105",
    "sg:city":"Spenge",
    "sg:phone":"+49 5225/859564",
    "sg:postcode":"32139",
    "sg:province":"Nordrhein-Westfalen",
    "wof:name":"\u00dcbsetzungsservice Heike Woehler",
    "wof:placetype":"venue"
},
  "geometry": {"coordinates":[8.52925,52.175789],"type":"Point"}
}