{
  "type": "Feature",
  "properties": {
    "iso:country":"DE",
    "sg:address":"Wedekindring 6",
    "sg:city":"Marienfeld",
    "sg:phone":"+49 5247/9880911",
    "sg:postcode":"33428",
    "sg:province":"Nordrhein-Westfalen",
    "wof:name":"Alfred Buchmann",
    "wof:placetype":"venue"
},
  "geometry": {"coordinates":[8.280453,51.953102],"type":"Point"}
}