{
  "type": "Feature",
  "properties": {
    "iso:country":"DE",
    "sg:address":"Luxemburger Str.190",
    "sg:city":"K\u00f6ln",
    "sg:phone":"+49 221",
    "sg:postcode":"50937",
    "sg:province":"Nordrhein-Westfalen",
    "wof:name":"Ma\u00dfstab E.v.",
    "wof:placetype":"venue"
},
  "geometry": {"coordinates":[6.930292,50.918797],"type":"Point"}
}