{
  "type": "Feature",
  "properties": {
    "iso:country":"DE",
    "sg:address":"Mutzenreisstr. 40",
    "sg:city":"Ostfildern",
    "sg:phone":"+49 711/343240",
    "sg:postcode":"73760",
    "sg:province":"Baden-W\u00fcrttemberg",
    "wof:name":"K. Und I. Baumann Druckerei",
    "wof:placetype":"venue"
},
  "geometry": {"coordinates":[9.300136,48.717686],"type":"Point"}
}