{
  "type": "Feature",
  "properties": {
    "iso:country":"DE",
    "sg:address":"Am Tescher Busch 6",
    "sg:city":"Wuppertal",
    "sg:phone":"+49 202/2741001",
    "sg:postcode":"42327",
    "sg:province":"Nordrhein-Westfalen",
    "wof:name":"Udo Scherer",
    "wof:placetype":"venue"
},
  "geometry": {"coordinates":[7.0794010162,51.2469406128],"type":"Point"}
}