{
  "type": "Feature",
  "properties": {
    "iso:country":"DE",
    "sg:address":"Kuckucksweg 45",
    "sg:city":"Wietzen",
    "sg:phone":"+49 5022/94155",
    "sg:postcode":"31613",
    "sg:province":"Niedersachsen",
    "wof:name":"Lohnunternehmer Service Gmbh & Co. Kg",
    "wof:placetype":"venue"
},
  "geometry": {"coordinates":[9.0762844086,52.7197532654],"type":"Point"}
}