{
  "type": "Feature",
  "properties": {
    "iso:country":"DE",
    "sg:address":"W\u00fcrzburger Str. 17",
    "sg:city":"Laatzen",
    "sg:postcode":"30880",
    "sg:province":"Niedersachsen",
    "wof:name":"Atmosphaere Gmbh",
    "wof:placetype":"venue"
},
  "geometry": {"coordinates":[9.8079299927,52.3089332581],"type":"Point"}
}