{
  "type": "Feature",
  "properties": {
    "iso:country":"DE",
    "sg:address":"Lindenstr. 89-91",
    "sg:city":"Siegburg",
    "sg:postcode":"53721",
    "sg:province":"Nordrhein-Westfalen",
    "wof:name":"Abc-tower Projektges. Mbh",
    "wof:placetype":"venue"
},
  "geometry": {"coordinates":[7.1907668114,50.7974662781],"type":"Point"}
}