{
  "type": "Feature",
  "properties": {
    "iso:country":"DE",
    "sg:address":"Sohlst\u00e4ttenstr. 52 a",
    "sg:city":"Ratingen",
    "sg:phone":"+49 2102/442620",
    "sg:postcode":"40880",
    "sg:province":"Nordrhein-Westfalen",
    "wof:name":"Kr\u00f6ll Einrichtungs Gmbh",
    "wof:placetype":"venue"
},
  "geometry": {"coordinates":[6.817534,51.308228],"type":"Point"}
}