{
  "type": "Feature",
  "properties": {
    "iso:country":"DE",
    "sg:address":"Bahnhofstr. 4",
    "sg:city":"Bad D\u00fcrrheim",
    "sg:phone":"+49 7726/4401",
    "sg:postcode":"78073",
    "sg:province":"Baden-W\u00fcrttemberg",
    "wof:name":"Brauchler's Weinstube",
    "wof:placetype":"venue"
},
  "geometry": {"coordinates":[8.5306472778,48.0190925598],"type":"Point"}
}