{
  "type": "Feature",
  "properties": {
    "iso:country":"DE",
    "sg:address":"Linprunstr. 8",
    "sg:city":"Viechtach",
    "sg:phone":"+49 9942/1382",
    "sg:postcode":"94234",
    "sg:province":"Bayern",
    "wof:name":"Hans Sirtl",
    "wof:placetype":"venue"
},
  "geometry": {"coordinates":[12.884209,49.078865],"type":"Point"}
}