{
  "type": "Feature",
  "properties": {
    "iso:country":"DE",
    "sg:address":"Bahnhofstr. 20",
    "sg:city":"Deggendorf",
    "sg:phone":"+49 991/6197",
    "sg:postcode":"94469",
    "sg:province":"Bayern",
    "wof:name":"Josef Schiller",
    "wof:placetype":"venue"
},
  "geometry": {"coordinates":[12.9606809616,48.8337745667],"type":"Point"}
}