{
  "type": "Feature",
  "properties": {
    "iso:country":"DE",
    "sg:address":"Kellerstr. 8",
    "sg:city":"Jandelsbrunn",
    "sg:phone":"+49 8583/91670",
    "sg:postcode":"94118",
    "sg:province":"Bayern",
    "wof:name":"Wernsdorfer Process Control- Gmbh",
    "wof:placetype":"venue"
},
  "geometry": {"coordinates":[13.695528,48.728348],"type":"Point"}
}