{
  "type": "Feature",
  "properties": {
    "iso:country":"DE",
    "sg:address":"Marktstr. 14",
    "sg:city":"Neustadt",
    "sg:phone":"+49 5032/917900",
    "sg:postcode":"31535",
    "sg:province":"Niedersachsen",
    "wof:name":"Rainer Herschel Gmbh",
    "wof:placetype":"venue"
},
  "geometry": {"coordinates":[9.116027832,50.8523178101],"type":"Point"}
}