{
  "type": "Feature",
  "properties": {
    "iso:country":"DE",
    "sg:address":"L\u00f6chgauer Str. 48",
    "sg:city":"Bietigheim-Bissingen",
    "sg:phone":"+49 7142/41079",
    "sg:postcode":"74321",
    "sg:province":"Baden-W\u00fcrttemberg",
    "wof:name":"Sch\u00e4ufele Und M\u00fcller Rechtsanw\u00e4lte",
    "wof:placetype":"venue"
},
  "geometry": {"coordinates":[9.1234121323,48.9622993469],"type":"Point"}
}