{
  "type": "Feature",
  "properties": {
    "iso:country":"DE",
    "sg:address":"B\u00fcchelstein",
    "sg:city":"Grattersdorf",
    "sg:phone":"+49 9904/566",
    "sg:postcode":"94541",
    "sg:province":"Bayern",
    "wof:name":"G. Sander",
    "wof:placetype":"venue"
},
  "geometry": {"coordinates":[13.1854133606,48.8052597046],"type":"Point"}
}