{
  "type": "Feature",
  "properties": {
    "iso:country":"DE",
    "sg:address":"K\u00f6nig-Marke-Str. 1",
    "sg:city":"M\u00fcnchen",
    "sg:phone":"+49 89/363647",
    "sg:postcode":"80804",
    "sg:province":"Bayern",
    "wof:name":"Dr. Hans-peter B\u00fchler",
    "wof:placetype":"venue"
},
  "geometry": {"coordinates":[11.5838756561,48.1728439331],"type":"Point"}
}