{
  "type": "Feature",
  "properties": {
    "iso:country":"DE",
    "sg:address":"Im Finigen 12",
    "sg:city":"Achim",
    "sg:phone":"+49 4202/97700",
    "sg:postcode":"28832",
    "sg:province":"Niedersachsen",
    "wof:name":"Rolf Meiners",
    "wof:placetype":"venue"
},
  "geometry": {"coordinates":[9.069315,53.011696],"type":"Point"}
}