{
  "type": "Feature",
  "properties": {
    "iso:country":"DE",
    "sg:address":"Goethestr. 9",
    "sg:city":"Wurzen",
    "sg:phone":"+49 3425/815517",
    "sg:postcode":"04808",
    "sg:province":"Sachsen",
    "wof:name":"Ute Zimmermann",
    "wof:placetype":"venue"
},
  "geometry": {"coordinates":[12.74494,51.366318],"type":"Point"}
}