{
  "type": "Feature",
  "properties": {
    "iso:country":"DE",
    "sg:address":"Wilhelmstr. 12",
    "sg:city":"Hofheim",
    "sg:phone":"+49 6192/1708",
    "sg:postcode":"65719",
    "sg:province":"Hessen",
    "wof:name":"Postkutsche",
    "wof:placetype":"venue"
},
  "geometry": {"coordinates":[8.4416322708,50.0862045288],"type":"Point"}
}