{
  "type": "Feature",
  "properties": {
    "iso:country":"DE",
    "sg:address":"Hardt 218",
    "sg:city":"Langenfeld",
    "sg:postcode":"40764",
    "sg:province":"Nordrhein-Westfalen",
    "wof:name":"Breite Stra\u00dfe Grundst\u00fccksgesellschaft Mbh",
    "wof:placetype":"venue"
},
  "geometry": {"coordinates":[6.98458004,51.1226501465],"type":"Point"}
}