{
  "type": "Feature",
  "properties": {
    "iso:country":"DE",
    "sg:address":"Friedrich-Ebert-Str. 236",
    "sg:city":"Kierspe",
    "sg:phone":"+49 2359/907350",
    "sg:postcode":"58566",
    "sg:province":"Nordrhein-Westfalen",
    "wof:name":"Manfred Ladwig",
    "wof:placetype":"venue"
},
  "geometry": {"coordinates":[7.5970602036,51.128578186],"type":"Point"}
}