{
  "type": "Feature",
  "properties": {
    "iso:country":"DE",
    "sg:address":"Streugasse 2",
    "sg:city":"Unsleben",
    "sg:phone":"+49 9773/215",
    "sg:postcode":"97618",
    "sg:province":"Bayern",
    "wof:name":"Karlheinz Gensler",
    "wof:placetype":"venue"
},
  "geometry": {"coordinates":[10.2573003769,50.3777275085],"type":"Point"}
}