{
  "type": "Feature",
  "properties": {
    "iso:country":"DE",
    "sg:address":"Carl-Zeiss-Str. 12",
    "sg:city":"Quickborn",
    "sg:postcode":"25451",
    "sg:province":"Schleswig-Holstein",
    "wof:name":"Gartenbilder, Flaggen, K\u00fcnstlerbilder, Dekortion",
    "wof:placetype":"venue"
},
  "geometry": {"coordinates":[9.935473,53.746826],"type":"Point"}
}