{
  "type": "Feature",
  "properties": {
    "iso:country":"DE",
    "sg:address":"Dorfstr. 3",
    "sg:city":"Alth\u00fcttendorf",
    "sg:postcode":"16247",
    "sg:province":"Brandenburg",
    "wof:name":"Gerhard Gutsch",
    "wof:placetype":"venue"
},
  "geometry": {"coordinates":[13.804767,52.960293],"type":"Point"}
}