{
  "type": "Feature",
  "properties": {
    "iso:country":"DE",
    "sg:address":"An der Plantage 25",
    "sg:city":"Mainz",
    "sg:phone":"+49 6131/682017",
    "sg:postcode":"55120",
    "sg:province":"Rheinland-Pfalz",
    "wof:name":"Ahema Handelsgesellschaft Mbh",
    "wof:placetype":"venue"
},
  "geometry": {"coordinates":[8.229362,50.015976],"type":"Point"}
}