{
  "type": "Feature",
  "properties": {
    "iso:country":"DE",
    "sg:address":"F\u00f6rsterweg 65",
    "sg:city":"Hamburg",
    "sg:phone":"+49 40/5407013",
    "sg:postcode":"22525",
    "sg:province":"Hamburg",
    "wof:name":"Graphischer Vertrieb James Burn International Gmbh",
    "wof:placetype":"venue"
},
  "geometry": {"coordinates":[9.926013,53.581036],"type":"Point"}
}