{
  "type": "Feature",
  "properties": {
    "iso:country":"DE",
    "sg:address":"Osterwechtern 38",
    "sg:city":"Krummendeich",
    "sg:phone":"+49 4779/538",
    "sg:postcode":"21732",
    "sg:province":"Niedersachsen",
    "wof:name":"Georg Wist",
    "wof:placetype":"venue"
},
  "geometry": {"coordinates":[9.210135,53.831154],"type":"Point"}
}