{
  "type": "Feature",
  "properties": {
    "iso:country":"DE",
    "sg:address":"Lichtentaler Str. 29",
    "sg:city":"Baden-Baden",
    "sg:phone":"+49 7221/23619",
    "sg:postcode":"76530",
    "sg:province":"Baden-W\u00fcrttemberg",
    "wof:name":"Pension Manfred Schuler",
    "wof:placetype":"venue"
},
  "geometry": {"coordinates":[8.2411413193,48.758644104],"type":"Point"}
}