{
  "type": "Feature",
  "properties": {
    "iso:country":"DE",
    "sg:address":"Untere Seestr. 54",
    "sg:city":"Langenargen",
    "sg:phone":"+49 7543/2188",
    "sg:postcode":"88085",
    "sg:province":"Baden-W\u00fcrttemberg",
    "wof:name":"Hermann Morandell",
    "wof:placetype":"venue"
},
  "geometry": {"coordinates":[9.5336380005,47.6019630432],"type":"Point"}
}