{
  "type": "Feature",
  "properties": {
    "iso:country":"DE",
    "sg:address":"Auf'M Brinke 19",
    "sg:city":"Meschede",
    "sg:phone":"+49 4929/13796",
    "sg:postcode":"59872",
    "sg:province":"Nordrhein-Westfalen",
    "wof:name":"Lausberg Kunststofftechnik",
    "wof:placetype":"venue"
},
  "geometry": {"coordinates":[8.2720804214,51.3561935425],"type":"Point"}
}