{
  "type": "Feature",
  "properties": {
    "iso:country":"DE",
    "sg:address":"B\u00f6hringsweiler",
    "sg:city":"Gro\u00dferlach",
    "sg:phone":"+49 7903/3393",
    "sg:postcode":"71577",
    "sg:province":"Baden-W\u00fcrttemberg",
    "wof:name":"Restaurant Schlo\u00dfm\u00fchle",
    "wof:placetype":"venue"
},
  "geometry": {"coordinates":[9.5107707977,49.0729217529],"type":"Point"}
}