{
  "type": "Feature",
  "properties": {
    "iso:country":"DE",
    "sg:address":"Raiffeisenstr. 38",
    "sg:city":"Katzwinkel",
    "sg:phone":"+49 2742/6006",
    "sg:postcode":"57581",
    "sg:province":"Rheinland-Pfalz",
    "wof:name":"Brendebach Solartechnik",
    "wof:placetype":"venue"
},
  "geometry": {"coordinates":[7.8051018715,50.8190422058],"type":"Point"}
}