{
  "type": "Feature",
  "properties": {
    "iso:country":"DE",
    "sg:address":"Burgstr. 7",
    "sg:city":"Nalbach",
    "sg:phone":"+49 6838/4274",
    "sg:postcode":"66809",
    "sg:province":"Saarland",
    "wof:name":"Croon & M\u00fcller Gmbh",
    "wof:placetype":"venue"
},
  "geometry": {"coordinates":[6.784345,49.382301],"type":"Point"}
}