{
  "type": "Feature",
  "properties": {
    "iso:country":"DE",
    "sg:address":"Neuhaldenstr. 35",
    "sg:city":"Korntal-M\u00fcnchingen",
    "sg:phone":"+49 711/8262494",
    "sg:postcode":"70825",
    "sg:province":"Baden-W\u00fcrttemberg",
    "wof:name":"Nullachtf\u00fcnfzehn Gmbh",
    "wof:placetype":"venue"
},
  "geometry": {"coordinates":[9.1171827316,48.8331298828],"type":"Point"}
}