{
  "type": "Feature",
  "properties": {
    "iso:country":"DE",
    "sg:address":"Hirschberg",
    "sg:city":"Beilngries",
    "sg:phone":"+49 8461/7337",
    "sg:postcode":"92339",
    "sg:province":"Bayern",
    "wof:name":"Extra",
    "wof:placetype":"venue"
},
  "geometry": {"coordinates":[11.45496,49.037579],"type":"Point"}
}