{
  "type": "Feature",
  "properties": {
    "iso:country":"DE",
    "sg:address":"Am Steinacher Kreuz 28 b",
    "sg:city":"N\u00fcrnberg",
    "sg:phone":"+49 911/3067838",
    "sg:postcode":"90427",
    "sg:province":"Bayern",
    "wof:name":"Witte & Ray N\u00fcrnberger Handwerks Lebk\u00fcchnerei Gmbh",
    "wof:placetype":"venue"
},
  "geometry": {"coordinates":[11.007822,49.511276],"type":"Point"}
}