{
  "type": "Feature",
  "properties": {
    "iso:country":"DE",
    "sg:address":"Rudolf-Breitscheid-Str. 27",
    "sg:city":"Scheibenberg",
    "sg:phone":"+49 37349/13788",
    "sg:postcode":"09481",
    "sg:province":"Sachsen",
    "wof:name":"Ursula R\u00f6tschke",
    "wof:placetype":"venue"
},
  "geometry": {"coordinates":[12.9140281677,50.5413589478],"type":"Point"}
}