{
  "type": "Feature",
  "properties": {
    "iso:country":"DE",
    "sg:address":"Dorfstr. 13",
    "sg:city":"R\u00fcde",
    "sg:phone":"+49 4633/313",
    "sg:postcode":"24986",
    "sg:province":"Schleswig-Holstein",
    "wof:name":"H.-h. M\u00f6ller",
    "wof:placetype":"venue"
},
  "geometry": {"coordinates":[9.638723,54.682484],"type":"Point"}
}