{
  "type": "Feature",
  "properties": {
    "iso:country":"DE",
    "sg:address":"Tannenweg 17",
    "sg:city":"Schorndorf",
    "sg:phone":"+49 7181/5534",
    "sg:postcode":"73614",
    "sg:province":"Baden-W\u00fcrttemberg",
    "wof:name":"Horst Ruhm Architekt",
    "wof:placetype":"venue"
},
  "geometry": {"coordinates":[9.534102,48.787601],"type":"Point"}
}