{
  "type": "Feature",
  "properties": {
    "iso:country":"DE",
    "sg:address":"Gohfelder Str. 21",
    "sg:city":"L\u00f6hne",
    "sg:phone":"+49 4957/3140044",
    "sg:postcode":"32584",
    "sg:province":"Nordrhein-Westfalen",
    "wof:name":"M K M Matratzen Kwiatkowski Gmbh & Co Kg",
    "wof:placetype":"venue"
},
  "geometry": {"coordinates":[8.7620458603,52.2155036926],"type":"Point"}
}