{
  "type": "Feature",
  "properties": {
    "iso:country":"DE",
    "sg:address":"Weinstr. 5",
    "sg:city":"Bad D\u00fcrkheim",
    "sg:phone":"+49 6322/5339",
    "sg:postcode":"67098",
    "sg:province":"Rheinland-Pfalz",
    "wof:name":"Kauss-karst Inh. L. Karst",
    "wof:placetype":"venue"
},
  "geometry": {"coordinates":[8.1760597229,49.4694366455],"type":"Point"}
}