{
  "type": "Feature",
  "properties": {
    "iso:country":"DE",
    "sg:address":"Hasel\u00fcnner Str. 60",
    "sg:city":"Meppen",
    "sg:phone":"+49 5931/2508",
    "sg:postcode":"49716",
    "sg:province":"Niedersachsen",
    "wof:name":"Hermann Janssen",
    "wof:placetype":"venue"
},
  "geometry": {"coordinates":[7.3044672012,52.7008247375],"type":"Point"}
}