{
  "type": "Feature",
  "properties": {
    "iso:country":"DE",
    "sg:address":"Bayerwaldstr. 27",
    "sg:city":"M\u00fcnchen",
    "sg:phone":"+49 89/6780900",
    "sg:postcode":"81737",
    "sg:province":"Bayern",
    "wof:name":"Mgv Margret Gruber Vertrieb Gmbh",
    "wof:placetype":"venue"
},
  "geometry": {"coordinates":[11.6304826736,48.0895118713],"type":"Point"}
}