{
  "type": "Feature",
  "properties": {
    "iso:country":"DE",
    "sg:address":"Barkhovenallee 1",
    "sg:city":"Essen",
    "sg:phone":"+49 4920/184010",
    "sg:postcode":"45239",
    "sg:province":"Nordrhein-Westfalen",
    "wof:name":"Stifterverband F\u00dcr Die Deutsche Wissenschaft",
    "wof:placetype":"venue"
},
  "geometry": {"coordinates":[7.00663,51.377331],"type":"Point"}
}