{
  "type": "Feature",
  "properties": {
    "iso:country":"DE",
    "sg:address":"Bendestorfer Str. 23",
    "sg:city":"Buchholz",
    "sg:phone":"+49 4181/290424",
    "sg:postcode":"21244",
    "sg:province":"Niedersachsen",
    "wof:name":"Alternative Und Axa Wolfgang Mertinelt",
    "wof:placetype":"venue"
},
  "geometry": {"coordinates":[9.887714386,53.3313751221],"type":"Point"}
}