{
  "type": "Feature",
  "properties": {
    "iso:country":"DE",
    "sg:address":"Ludwigstr. 20",
    "sg:city":"Bad Reichenhall",
    "sg:phone":"+49 8651/718771",
    "sg:postcode":"83435",
    "sg:province":"Bayern",
    "wof:name":"Ihr Platz Drogeriemarkt",
    "wof:placetype":"venue"
},
  "geometry": {"coordinates":[12.87912,47.724144],"type":"Point"}
}