{
  "type": "Feature",
  "properties": {
    "iso:country":"DE",
    "sg:address":"Bahnhofstr 87",
    "sg:city":"Gr\u00e4felfing",
    "sg:phone":"+49 89/8545452",
    "sg:postcode":"82166",
    "sg:province":"Bayern",
    "wof:name":"Awk",
    "wof:placetype":"venue"
},
  "geometry": {"coordinates":[11.428898,48.11861],"type":"Point"}
}