{
  "type": "Feature",
  "properties": {
    "iso:country":"DE",
    "sg:address":"Rathausstr. 4",
    "sg:city":"Wolsfeld",
    "sg:phone":"+49 6568/885",
    "sg:postcode":"54636",
    "sg:province":"Rheinland-Pfalz",
    "wof:name":"Wila Gmbh",
    "wof:placetype":"venue"
},
  "geometry": {"coordinates":[6.46914,49.907604],"type":"Point"}
}