{
  "type": "Feature",
  "properties": {
    "iso:country":"DE",
    "sg:address":"Dreispitzweg 7",
    "sg:city":"Erlenbach",
    "sg:phone":"+49 9372/13560",
    "sg:postcode":"63906",
    "sg:province":"Bayern",
    "wof:name":"Bfb Technische Geb\u00c4udeausr\u00dcstung",
    "wof:placetype":"venue"
},
  "geometry": {"coordinates":[9.14389,49.81171],"type":"Point"}
}