{
  "type": "Feature",
  "properties": {
    "iso:country":"DE",
    "sg:address":"Tr\u00e4nkestr. 1",
    "sg:city":"Blankenburg",
    "sg:phone":"+49 3944/364781",
    "sg:postcode":"38889",
    "sg:province":"Sachsen-Anhalt",
    "wof:name":"Exotencenter Radler",
    "wof:placetype":"venue"
},
  "geometry": {"coordinates":[10.953871,51.788727],"type":"Point"}
}