{
  "type": "Feature",
  "properties": {
    "iso:country":"DE",
    "sg:address":"Pferdebade",
    "sg:city":"Bremerhaven",
    "sg:phone":"+49 471/803370",
    "sg:postcode":"27580",
    "sg:province":"Bremen",
    "wof:name":"Manfred Waller",
    "wof:placetype":"venue"
},
  "geometry": {"coordinates":[8.5968599319,53.5722236633],"type":"Point"}
}