{
  "type": "Feature",
  "properties": {
    "iso:country":"DE",
    "sg:address":"M\u00fchlenweg 16",
    "sg:city":"Niedenstein",
    "sg:phone":"+49 5603/2249",
    "sg:postcode":"34305",
    "sg:province":"Hessen",
    "wof:name":"Dieter Spengler",
    "wof:placetype":"venue"
},
  "geometry": {"coordinates":[9.29591,51.197411],"type":"Point"}
}