{
  "type": "Feature",
  "properties": {
    "iso:country":"DE",
    "sg:address":"Mainzer Str. 34",
    "sg:city":"S\u00f6rgenloch",
    "sg:phone":"+49 6136/925007",
    "sg:postcode":"55270",
    "sg:province":"Rheinland-Pfalz",
    "wof:name":"Hms Edv Management & Vertriebs Gmbh",
    "wof:placetype":"venue"
},
  "geometry": {"coordinates":[8.201055,49.884228],"type":"Point"}
}