{
  "type": "Feature",
  "properties": {
    "iso:country":"DE",
    "sg:address":"Carl-Schurz-Str. 24",
    "sg:city":"Berlin",
    "sg:phone":"+49 30/3338083",
    "sg:postcode":"13597",
    "sg:province":"Berlin",
    "wof:name":"Buelent Ayranci",
    "wof:placetype":"venue"
},
  "geometry": {"coordinates":[13.2026643753,52.5365867615],"type":"Point"}
}