{
  "type": "Feature",
  "properties": {
    "iso:country":"DE",
    "sg:address":"Schornbaumstr. 22",
    "sg:city":"N\u00fcrnberg",
    "sg:phone":"+49 911/834416",
    "sg:postcode":"90475",
    "sg:province":"Bayern",
    "wof:name":"Dr. Med. Christoph Von Imhoff",
    "wof:placetype":"venue"
},
  "geometry": {"coordinates":[11.167965889,49.4062767029],"type":"Point"}
}