{
  "type": "Feature",
  "properties": {
    "iso:country":"DE",
    "sg:address":"Findorffstr. 17",
    "sg:city":"Worpswede",
    "sg:phone":"+49 4792/1827",
    "sg:postcode":"27726",
    "sg:province":"Niedersachsen",
    "wof:name":"Ingrid Kornadt",
    "wof:placetype":"venue"
},
  "geometry": {"coordinates":[8.923866272,53.2222709656],"type":"Point"}
}