{
  "type": "Feature",
  "properties": {
    "iso:country":"DE",
    "sg:address":"Lange Str 17",
    "sg:city":"Ronnenberg",
    "sg:phone":"+49 511/435041",
    "sg:postcode":"30952",
    "sg:province":"Niedersachsen",
    "wof:name":"Emil Schuchmann Kg",
    "wof:placetype":"venue"
},
  "geometry": {"coordinates":[9.6576890945,52.3186302185],"type":"Point"}
}