{
  "type": "Feature",
  "properties": {
    "iso:country":"DE",
    "sg:address":"Bahnhofstr 18",
    "sg:city":"Ochtrup",
    "sg:phone":"+49 2553/93940",
    "sg:postcode":"48607",
    "sg:province":"Nordrhein-Westfalen",
    "wof:name":"Druck- Und Verlag Konrad Kirch Gmbh",
    "wof:placetype":"venue"
},
  "geometry": {"coordinates":[7.1878261566,52.2067832947],"type":"Point"}
}