{
  "type": "Feature",
  "properties": {
    "iso:country":"DE",
    "sg:address":"Radbrucher Str. 12",
    "sg:city":"Winsen",
    "sg:phone":"+49 4171/71294",
    "sg:postcode":"21423",
    "sg:province":"Niedersachsen",
    "wof:name":"Gustav Peters",
    "wof:placetype":"venue"
},
  "geometry": {"coordinates":[10.20084,53.329453],"type":"Point"}
}