{
  "type": "Feature",
  "properties": {
    "iso:country":"DE",
    "sg:address":"Mellande 2 B",
    "sg:city":"Hamburg",
    "sg:phone":"+49 40/6003162",
    "sg:postcode":"22393",
    "sg:province":"Hamburg",
    "wof:name":"Geocon Geo-industrie- Consulting Gmbh",
    "wof:placetype":"venue"
},
  "geometry": {"coordinates":[10.1024036407,53.6465110779],"type":"Point"}
}