{
  "type": "Feature",
  "properties": {
    "iso:country":"DE",
    "sg:address":"Am Gr\u00fcnen Tal 19",
    "sg:city":"Schwerin",
    "sg:postcode":"19063",
    "sg:province":"Mecklenburg-Vorpommern",
    "wof:name":"Uwe Merkel E. K.",
    "wof:placetype":"venue"
},
  "geometry": {"coordinates":[11.4438495636,53.6033401489],"type":"Point"}
}