{
  "type": "Feature",
  "properties": {
    "iso:country":"DE",
    "sg:address":"Schnaatweg 8",
    "sg:city":"Glandorf",
    "sg:phone":"+49 5426/5313",
    "sg:postcode":"49219",
    "sg:province":"Niedersachsen",
    "wof:name":"Bauunternehmung Siegfried Uhlenhake Gmbh",
    "wof:placetype":"venue"
},
  "geometry": {"coordinates":[7.897727,52.075741],"type":"Point"}
}