{
  "type": "Feature",
  "properties": {
    "iso:country":"DE",
    "sg:address":"Mittelstr. 40",
    "sg:city":"Elchesheim-Illingen",
    "sg:phone":"+49 7245/81620",
    "sg:postcode":"76477",
    "sg:province":"Baden-W\u00fcrttemberg",
    "wof:name":"S. Lehel",
    "wof:placetype":"venue"
},
  "geometry": {"coordinates":[8.208118,48.936504],"type":"Point"}
}