{
  "type": "Feature",
  "properties": {
    "iso:country":"DE",
    "sg:address":"Hauptstr. 19",
    "sg:city":"Ilbesheim",
    "sg:phone":"+49 6341/34279",
    "sg:postcode":"76831",
    "sg:province":"Rheinland-Pfalz",
    "wof:name":"P. Schunck",
    "wof:placetype":"venue"
},
  "geometry": {"coordinates":[8.05576,49.181267],"type":"Point"}
}