{
  "type": "Feature",
  "properties": {
    "iso:country":"DE",
    "sg:address":"Rotweg 8",
    "sg:city":"Baden-Baden",
    "sg:phone":"+49 4972/2135010",
    "sg:postcode":"76532",
    "sg:province":"Baden-W\u00fcrttemberg",
    "wof:name":"Sonnenverlag Gmbh",
    "wof:placetype":"venue"
},
  "geometry": {"coordinates":[8.1943979263,48.779335022],"type":"Point"}
}