{
  "type": "Feature",
  "properties": {
    "iso:country":"DE",
    "sg:address":"Bahnhofstr. 39",
    "sg:city":"Montabaur",
    "sg:phone":"+49 2602/1320",
    "sg:postcode":"56410",
    "sg:province":"Rheinland-Pfalz",
    "wof:name":"Deutsche Post Ag",
    "wof:placetype":"venue"
},
  "geometry": {"coordinates":[7.826084137,50.4377479553],"type":"Point"}
}