{
  "type": "Feature",
  "properties": {
    "iso:country":"DE",
    "sg:address":"Giebfriedweg 7",
    "sg:city":"Aschaffenburg",
    "sg:phone":"+49 6021/625987",
    "sg:postcode":"63741",
    "sg:province":"Bayern",
    "wof:name":"Ignorat Design",
    "wof:placetype":"venue"
},
  "geometry": {"coordinates":[9.124686,49.972691],"type":"Point"}
}