{
  "type": "Feature",
  "properties": {
    "iso:country":"DE",
    "sg:address":"Schleusenstr. 11",
    "sg:city":"Voerde",
    "sg:phone":"+49 281/94210",
    "sg:postcode":"46562",
    "sg:province":"Nordrhein-Westfalen",
    "wof:name":"Corus Aluminium Voerde Gmbh",
    "wof:placetype":"venue"
},
  "geometry": {"coordinates":[6.680498,51.598362],"type":"Point"}
}