{
  "type": "Feature",
  "properties": {
    "iso:country":"DE",
    "sg:address":"Neuer Weg 19",
    "sg:city":"Peine",
    "sg:phone":"+49 5171/81138",
    "sg:postcode":"31226",
    "sg:province":"Niedersachsen",
    "wof:name":"I. Bullert",
    "wof:placetype":"venue"
},
  "geometry": {"coordinates":[10.267275,52.294151],"type":"Point"}
}