{
  "type": "Feature",
  "properties": {
    "iso:country":"DE",
    "sg:address":"Bahnhofstr. 32",
    "sg:city":"K\u00f6nigswinter",
    "sg:phone":"+49 2223/912403",
    "sg:postcode":"53639",
    "sg:province":"Nordrhein-Westfalen",
    "wof:name":"Josef Hinterkeuser",
    "wof:placetype":"venue"
},
  "geometry": {"coordinates":[7.193704,50.677345],"type":"Point"}
}