{
  "type": "Feature",
  "properties": {
    "iso:country":"DE",
    "sg:address":"Kienbergstr. 9",
    "sg:city":"Stein",
    "sg:phone":"+49 8621/7799",
    "sg:postcode":"83371",
    "sg:province":"Bayern",
    "wof:name":"Franz Maier Gmbh & Co. Kg",
    "wof:placetype":"venue"
},
  "geometry": {"coordinates":[-89.93901062010001,30.6870384216],"type":"Point"}
}