{
  "type": "Feature",
  "properties": {
    "iso:country":"DE",
    "sg:address":"Am Hogrevenkamp 1",
    "sg:city":"Wolfenb\u00fcttel",
    "sg:phone":"+49 5331/71892",
    "sg:postcode":"38302",
    "sg:province":"Niedersachsen",
    "wof:name":"Gerhard St\u00fctzer",
    "wof:placetype":"venue"
},
  "geometry": {"coordinates":[10.578332,52.197598],"type":"Point"}
}