{
  "type": "Feature",
  "properties": {
    "iso:country":"DE",
    "sg:address":"Steinsrott 4",
    "sg:city":"Nideggen",
    "sg:phone":"+49 2474/310",
    "sg:postcode":"52385",
    "sg:province":"Nordrhein-Westfalen",
    "wof:name":"Pension Marianne Falter",
    "wof:placetype":"venue"
},
  "geometry": {"coordinates":[6.4090399742,50.6569290161],"type":"Point"}
}