{
  "type": "Feature",
  "properties": {
    "iso:country":"DE",
    "sg:address":"Nikolaus-Gro\u00df-Str.4",
    "sg:city":"Dinslaken",
    "sg:phone":"+49 2064",
    "sg:postcode":"46525",
    "sg:province":"Nordrhein-Westfalen",
    "wof:name":"Willkommen Bei Albert-schweitzer-einrichtungen!",
    "wof:placetype":"venue"
},
  "geometry": {"coordinates":[6.73292,51.565121],"type":"Point"}
}