{
  "type": "Feature",
  "properties": {
    "iso:country":"DE",
    "sg:address":"Berliner Str. 12",
    "sg:city":"Neuenhaus",
    "sg:phone":"+49 5941/1010",
    "sg:postcode":"49828",
    "sg:province":"Niedersachsen",
    "wof:name":"Wasserbeschaffungsverband Niedergrafschaft Und Umgebung",
    "wof:placetype":"venue"
},
  "geometry": {"coordinates":[6.9595370293,52.494846344],"type":"Point"}
}