{
  "type": "Feature",
  "properties": {
    "iso:country":"DE",
    "sg:address":"Hauptstr. 12",
    "sg:city":"Orsingen-Nenzingen",
    "sg:phone":"+49 7774/475",
    "sg:postcode":"78359",
    "sg:province":"Baden-W\u00fcrttemberg",
    "wof:name":"Gasthaus Hecht",
    "wof:placetype":"venue"
},
  "geometry": {"coordinates":[8.9301576614,47.8368339539],"type":"Point"}
}