{
  "type": "Feature",
  "properties": {
    "iso:country":"DE",
    "sg:address":"Dornreichenbacher Str.",
    "sg:city":"Falkenhain",
    "sg:postcode":"04808",
    "sg:province":"Sachsen",
    "wof:name":"Msd Gastroservice Gmbh",
    "wof:placetype":"venue"
},
  "geometry": {"coordinates":[12.8878774643,51.3843917847],"type":"Point"}
}