{
  "type": "Feature",
  "properties": {
    "iso:country":"DE",
    "sg:address":"Benzinger\u00f6der Chaussee 72",
    "sg:city":"Wernigerode",
    "sg:phone":"+49 3943/47193",
    "sg:postcode":"38855",
    "sg:province":"Sachsen-Anhalt",
    "wof:name":"Isoliertechnik Helge Pentzlin Gmbh",
    "wof:placetype":"venue"
},
  "geometry": {"coordinates":[10.824311,51.839088],"type":"Point"}
}