{
  "type": "Feature",
  "properties": {
    "iso:country":"DE",
    "sg:address":"Hesselbach 22",
    "sg:city":"Oberkirch",
    "sg:phone":"+49 7802/2907",
    "sg:postcode":"77704",
    "sg:province":"Baden-W\u00fcrttemberg",
    "wof:name":"Georg Braun",
    "wof:placetype":"venue"
},
  "geometry": {"coordinates":[8.072305,48.506828],"type":"Point"}
}