{
  "type": "Feature",
  "properties": {
    "iso:country":"DE",
    "sg:address":"Schulplatz 1",
    "sg:city":"Kranenburg-Frasselt",
    "sg:phone":"+49 2826",
    "sg:postcode":"47559",
    "sg:province":"Nordrhein-Westfalen",
    "wof:name":"Grenzlandkuechen",
    "wof:placetype":"venue"
},
  "geometry": {"coordinates":[6.0237469673,51.7713928223],"type":"Point"}
}