{
  "type": "Feature",
  "properties": {
    "iso:country":"DE",
    "sg:address":"Sacker Hauptstr. 33",
    "sg:city":"F\u00fcrth",
    "sg:phone":"+49 911/936840",
    "sg:postcode":"90765",
    "sg:province":"Bayern",
    "wof:name":"B\u00e4cker Witte",
    "wof:placetype":"venue"
},
  "geometry": {"coordinates":[11.016471,49.501266],"type":"Point"}
}