{
  "type": "Feature",
  "properties": {
    "iso:country":"DE",
    "sg:address":"K\u00f6nigstr. 8",
    "sg:city":"Ahrensburg",
    "sg:phone":"+49 4102/56636",
    "sg:postcode":"22926",
    "sg:province":"Schleswig-Holstein",
    "wof:name":"Nils Drenkhahn Heilpraktiker",
    "wof:placetype":"venue"
},
  "geometry": {"coordinates":[10.2414360046,53.6740875244],"type":"Point"}
}