{
  "type": "Feature",
  "properties": {
    "iso:country":"DE",
    "sg:address":"Asternweg 19",
    "sg:city":"Bayreuth",
    "sg:phone":"+49 921/64496",
    "sg:postcode":"95447",
    "sg:province":"Bayern",
    "wof:name":"P. Hartmann",
    "wof:placetype":"venue"
},
  "geometry": {"coordinates":[11.5620670319,49.9216880798],"type":"Point"}
}