{
  "type": "Feature",
  "properties": {
    "iso:country":"DE",
    "sg:address":"Schillerstr. 26",
    "sg:city":"Bad Pyrmont",
    "sg:phone":"+49 5281/608723",
    "sg:postcode":"31812",
    "sg:province":"Niedersachsen",
    "wof:name":"Concordia Vvag",
    "wof:placetype":"venue"
},
  "geometry": {"coordinates":[9.243265152,51.9839668274],"type":"Point"}
}