{
  "type": "Feature",
  "properties": {
    "iso:country":"DE",
    "sg:address":"R\u00fcggenhofer Weg 14b",
    "sg:city":"Essen",
    "sg:phone":"+49 201/557755",
    "sg:postcode":"45309",
    "sg:province":"Nordrhein-Westfalen",
    "wof:name":"Vancouver Spiel- Und Unterhaltungsautomaten Gmbh",
    "wof:placetype":"venue"
},
  "geometry": {"coordinates":[7.0818920135,51.4768943787],"type":"Point"}
}