{
  "type": "Feature",
  "properties": {
    "iso:country":"DE",
    "sg:address":"Hindenburgstr. 4",
    "sg:city":"Gochsheim",
    "sg:phone":"+49 9721/61120",
    "sg:postcode":"97469",
    "sg:province":"Bayern",
    "wof:name":"Klaus Pfister",
    "wof:placetype":"venue"
},
  "geometry": {"coordinates":[10.281903,50.018547],"type":"Point"}
}