{
  "type": "Feature",
  "properties": {
    "iso:country":"DE",
    "sg:address":"Am See 1",
    "sg:city":"Waging",
    "sg:postcode":"83329",
    "sg:province":"Bayern",
    "wof:name":"Kurbetriebe Waging Am See Sebastian Schuhbeck",
    "wof:placetype":"venue"
},
  "geometry": {"coordinates":[12.7514648438,47.9439582825],"type":"Point"}
}