{
  "type": "Feature",
  "properties": {
    "iso:country":"DE",
    "sg:address":"Ernst-Moritz-Arndt-Str. 28",
    "sg:city":"Wolfenb\u00fcttel",
    "sg:phone":"+49 5331/43628",
    "sg:postcode":"38304",
    "sg:province":"Niedersachsen",
    "wof:name":"J\u00fcrgen Kurkowitz",
    "wof:placetype":"venue"
},
  "geometry": {"coordinates":[10.520942688,52.1574287415],"type":"Point"}
}