{
  "type": "Feature",
  "properties": {
    "iso:country":"DE",
    "sg:address":"Ganspohler Str. 5",
    "sg:city":"Langenfeld",
    "sg:phone":"+49 2173/90600",
    "sg:postcode":"40764",
    "sg:province":"Nordrhein-Westfalen",
    "wof:name":"Rechtsanwaltskanzlei Von Buddenbrock Und Partner",
    "wof:placetype":"venue"
},
  "geometry": {"coordinates":[6.9504709244,51.1093521118],"type":"Point"}
}