{
  "type": "Feature",
  "properties": {
    "iso:country":"DE",
    "sg:address":"Wilhelmstr. 35-37",
    "sg:city":"Bonn",
    "sg:phone":"+49 228/2872263",
    "sg:postcode":"53111",
    "sg:province":"Nordrhein-Westfalen",
    "wof:name":"Universit\u00e4ts-klinik Medizinische Poliklinik",
    "wof:placetype":"venue"
},
  "geometry": {"coordinates":[7.09845,50.739677],"type":"Point"}
}