{
  "type": "Feature",
  "properties": {
    "iso:country":"DE",
    "sg:address":"Arnst\u00e4dter Str. 10",
    "sg:city":"Ohrdruf",
    "sg:phone":"+49 3624/311486",
    "sg:postcode":"99885",
    "sg:province":"Th\u00fcringen",
    "wof:name":"B. John",
    "wof:placetype":"venue"
},
  "geometry": {"coordinates":[10.73869133,50.8282279968],"type":"Point"}
}