{
  "type": "Feature",
  "properties": {
    "iso:country":"DE",
    "sg:address":"Wilhelmine-P\u00f6tter-Str. 13",
    "sg:city":"Niestetal",
    "sg:phone":"+49 561/527559",
    "sg:postcode":"34266",
    "sg:province":"Hessen",
    "wof:name":"Bernd Schmitt",
    "wof:placetype":"venue"
},
  "geometry": {"coordinates":[9.5481052399,51.3201026917],"type":"Point"}
}