{
  "type": "Feature",
  "properties": {
    "iso:country":"DE",
    "sg:address":"Ritterstr. 69",
    "sg:city":"Brandenburg",
    "sg:phone":"+49 3381/25230",
    "sg:postcode":"14770",
    "sg:province":"Brandenburg",
    "wof:name":"Kultur-labor Veranstaltungs- Und Kulturprojekte Ggmbh",
    "wof:placetype":"venue"
},
  "geometry": {"coordinates":[12.555824,52.412014],"type":"Point"}
}