{
  "type": "Feature",
  "properties": {
    "iso:country":"DE",
    "sg:address":"Hauptstr. 25",
    "sg:city":"Stadtkyll",
    "sg:phone":"+49 6597/2319",
    "sg:postcode":"54589",
    "sg:province":"Rheinland-Pfalz",
    "wof:name":"Marien-apotheke",
    "wof:placetype":"venue"
},
  "geometry": {"coordinates":[6.52855,50.351219],"type":"Point"}
}