{
  "type": "Feature",
  "properties": {
    "iso:country":"DE",
    "sg:address":"Talstr. 2",
    "sg:city":"Virneburg",
    "sg:phone":"+49 2656/1244",
    "sg:postcode":"56729",
    "sg:province":"Rheinland-Pfalz",
    "wof:name":"Adhoc Dataservice Gmbh",
    "wof:placetype":"venue"
},
  "geometry": {"coordinates":[7.0780611038,50.342338562],"type":"Point"}
}