{
  "type": "Feature",
  "properties": {
    "iso:country":"DE",
    "sg:address":"Ringstr.",
    "sg:city":"Ohrdruf",
    "sg:postcode":"99885",
    "sg:province":"Th\u00fcringen",
    "wof:name":"Pvt Holding Kg",
    "wof:placetype":"venue"
},
  "geometry": {"coordinates":[10.715358,50.839172],"type":"Point"}
}