{
  "type": "Feature",
  "properties": {
    "iso:country":"DE",
    "sg:address":"Gasse 2",
    "sg:city":"Dyrotz",
    "sg:phone":"+49 33234/89232",
    "sg:postcode":"14641",
    "sg:province":"Brandenburg",
    "wof:name":"Pension Schwebel",
    "wof:placetype":"venue"
},
  "geometry": {"coordinates":[12.9555330276,52.5437660217],"type":"Point"}
}