{
  "type": "Feature",
  "properties": {
    "iso:country":"DE",
    "sg:address":"Richterstr. 4",
    "sg:city":"Herten",
    "sg:phone":"+49 2366/41625",
    "sg:postcode":"45701",
    "sg:province":"Nordrhein-Westfalen",
    "wof:name":"Dorfst\u00fcbchen",
    "wof:placetype":"venue"
},
  "geometry": {"coordinates":[7.1415109634,51.619644165],"type":"Point"}
}