{
  "type": "Feature",
  "properties": {
    "iso:country":"DE",
    "sg:address":"Herrenstr. 1",
    "sg:city":"Harsefeld",
    "sg:phone":"+49 4164/3076",
    "sg:postcode":"21698",
    "sg:province":"Niedersachsen",
    "wof:name":"Alte Apotheke Dr. Alfred Dick Nachf.",
    "wof:placetype":"venue"
},
  "geometry": {"coordinates":[9.500291,53.452492],"type":"Point"}
}