{
  "type": "Feature",
  "properties": {
    "iso:country":"DE",
    "sg:address":"Albaxer Str. 24",
    "sg:city":"H\u00f6xter",
    "sg:postcode":"37671",
    "sg:province":"Nordrhein-Westfalen",
    "wof:name":"Minimal",
    "wof:placetype":"venue"
},
  "geometry": {"coordinates":[9.3825550079,51.7734565735],"type":"Point"}
}