{
  "type": "Feature",
  "properties": {
    "iso:country":"DE",
    "sg:address":"Krumer Str. 4",
    "sg:city":"Zeil",
    "sg:phone":"+49 9524/7615",
    "sg:postcode":"97475",
    "sg:province":"Bayern",
    "wof:name":"Gerhard Roos",
    "wof:placetype":"venue"
},
  "geometry": {"coordinates":[10.593865,50.012913],"type":"Point"}
}