{
  "type": "Feature",
  "properties": {
    "iso:country":"DE",
    "sg:address":"Beethovenstr. 68",
    "sg:city":"Saarbr\u00fccken",
    "sg:phone":"+49 6897/73300",
    "sg:postcode":"66125",
    "sg:province":"Saarland",
    "wof:name":"Kaminstube Seewald",
    "wof:placetype":"venue"
},
  "geometry": {"coordinates":[7.0479311943,49.2661972046],"type":"Point"}
}