{
  "type": "Feature",
  "properties": {
    "iso:country":"DE",
    "sg:address":"Schneidem\u00fchler Str. 18",
    "sg:city":"Bremen",
    "sg:phone":"+49 421/650986",
    "sg:postcode":"28755",
    "sg:province":"Bremen",
    "wof:name":"M. Degenhardt",
    "wof:placetype":"venue"
},
  "geometry": {"coordinates":[8.6364850998,53.1948013306],"type":"Point"}
}