{
  "type": "Feature",
  "properties": {
    "iso:country":"DE",
    "sg:address":"Am Zehntstadel 2",
    "sg:city":"Augsburg",
    "sg:phone":"+49 821/94350",
    "sg:postcode":"86199",
    "sg:province":"Bayern",
    "wof:name":"E. Flach Nachf. E. K.",
    "wof:placetype":"venue"
},
  "geometry": {"coordinates":[10.8578796387,48.336227417],"type":"Point"}
}