{
  "type": "Feature",
  "properties": {
    "iso:country":"DE",
    "sg:address":"Zur Bergehalde 8",
    "sg:city":"P\u00fcttlingen",
    "sg:phone":"+49 6898/96110",
    "sg:postcode":"66346",
    "sg:province":"Saarland",
    "wof:name":"Druckerei D\u00f6rr Gmbh",
    "wof:placetype":"venue"
},
  "geometry": {"coordinates":[6.9043488503,49.2815818787],"type":"Point"}
}