{
  "type": "Feature",
  "properties": {
    "iso:country":"DE",
    "sg:address":"Untere Sonnhalde 37",
    "sg:city":"B\u00fcrchau",
    "sg:phone":"+49 7629/260",
    "sg:postcode":"79683",
    "sg:province":"Baden-W\u00fcrttemberg",
    "wof:name":"Hotel-restaurant Sonnenhalde",
    "wof:placetype":"venue"
},
  "geometry": {"coordinates":[7.8271141052,47.769115448],"type":"Point"}
}