{
  "type": "Feature",
  "properties": {
    "iso:country":"DE",
    "sg:address":"G\u00fctersloher Str. 331",
    "sg:city":"Bielefeld",
    "sg:phone":"+49 521/48566",
    "sg:postcode":"33649",
    "sg:province":"Nordrhein-Westfalen",
    "wof:name":"Harry Heitmann Elektroinstallation",
    "wof:placetype":"venue"
},
  "geometry": {"coordinates":[8.460037,51.967117],"type":"Point"}
}