{
  "type": "Feature",
  "properties": {
    "iso:country":"DE",
    "sg:address":"Sonnenstr. 1a",
    "sg:city":"Ergoldsbach",
    "sg:phone":"+49 8771/2196",
    "sg:postcode":"84061",
    "sg:province":"Bayern",
    "wof:name":"Wolfgang Hartwig",
    "wof:placetype":"venue"
},
  "geometry": {"coordinates":[12.2068223953,48.6841430664],"type":"Point"}
}