{
  "type": "Feature",
  "properties": {
    "iso:country":"DE",
    "sg:address":"H\u00fcltzstr. 4",
    "sg:city":"K\u00f6ln",
    "sg:postcode":"50933",
    "sg:province":"Nordrhein-Westfalen",
    "wof:name":"Strategische Kommunikation",
    "wof:placetype":"venue"
},
  "geometry": {"coordinates":[6.907284,50.936569],"type":"Point"}
}