{
  "type": "Feature",
  "properties": {
    "iso:country":"DE",
    "sg:address":"Tannenbergstr. 40",
    "sg:city":"Schwaan",
    "sg:phone":"+49 3844/813947",
    "sg:postcode":"18258",
    "sg:province":"Mecklenburg-Vorpommern",
    "wof:name":"Dr. Med. Horst Deptalla",
    "wof:placetype":"venue"
},
  "geometry": {"coordinates":[12.12197,53.93951],"type":"Point"}
}