{
  "type": "Feature",
  "properties": {
    "iso:country":"DE",
    "sg:address":"Hauptstr. 42 a",
    "sg:city":"Marsberg",
    "sg:phone":"+49 2992/2677",
    "sg:postcode":"34431",
    "sg:province":"Nordrhein-Westfalen",
    "wof:name":"Paul Kuhlmann",
    "wof:placetype":"venue"
},
  "geometry": {"coordinates":[8.856544,51.459572],"type":"Point"}
}