{
  "type": "Feature",
  "properties": {
    "iso:country":"DE",
    "sg:address":"St.-Georg-Str. 25",
    "sg:city":"Ellwangen",
    "sg:phone":"+49 7961/2628",
    "sg:postcode":"73479",
    "sg:province":"Baden-W\u00fcrttemberg",
    "wof:name":"Ulrich Eyberger",
    "wof:placetype":"venue"
},
  "geometry": {"coordinates":[10.11062,48.952805],"type":"Point"}
}