{
  "type": "Feature",
  "properties": {
    "iso:country":"DE",
    "sg:address":"Wolmirslebener Str. 9",
    "sg:city":"Egeln",
    "sg:phone":"+49 39268/2349",
    "sg:postcode":"39435",
    "sg:province":"Sachsen-Anhalt",
    "wof:name":"Friedrich Montag",
    "wof:placetype":"venue"
},
  "geometry": {"coordinates":[11.440102,51.956051],"type":"Point"}
}