{
  "type": "Feature",
  "properties": {
    "iso:country":"DE",
    "sg:address":"Paul-Baumann-Str. 1",
    "sg:city":"Marl",
    "sg:postcode":"45772",
    "sg:province":"Nordrhein-Westfalen",
    "wof:name":"Faserwerke H\u00fcls Gmbh",
    "wof:placetype":"venue"
},
  "geometry": {"coordinates":[7.101858139,51.6789855957],"type":"Point"}
}