{
  "type": "Feature",
  "properties": {
    "iso:country":"DE",
    "sg:address":"Leipziger Str. 47a",
    "sg:city":"Braunschweig",
    "sg:phone":"+49 531/60468",
    "sg:postcode":"38124",
    "sg:province":"Niedersachsen",
    "wof:name":"Otto Hujer",
    "wof:placetype":"venue"
},
  "geometry": {"coordinates":[10.5202131271,52.2290534973],"type":"Point"}
}