{
  "type": "Feature",
  "properties": {
    "iso:country":"DE",
    "sg:address":"L\u00fcchtringer Weg 46",
    "sg:city":"Holzminden",
    "sg:phone":"+49 5531/13777",
    "sg:postcode":"37603",
    "sg:province":"Niedersachsen",
    "wof:name":"Dea-tankstelle",
    "wof:placetype":"venue"
},
  "geometry": {"coordinates":[9.4389028549,51.8068389893],"type":"Point"}
}