{
  "type": "Feature",
  "properties": {
    "iso:country":"DE",
    "sg:address":"Hitzgutstr. 8",
    "sg:city":"Appenweier",
    "sg:postcode":"77767",
    "sg:province":"Baden-W\u00fcrttemberg",
    "wof:name":"Licht Perspektiven Gmbh",
    "wof:placetype":"venue"
},
  "geometry": {"coordinates":[7.966807,48.540096],"type":"Point"}
}