{
  "type": "Feature",
  "properties": {
    "iso:country":"DE",
    "sg:address":"Stadtplatz/Weinberger Str 2:: Hallertau::",
    "sg:city":"Abensberg",
    "sg:postcode":"93326",
    "sg:province":"Bayern",
    "wof:name":"Nicolaus Stark Bank Ag",
    "wof:placetype":"venue"
},
  "geometry": {"coordinates":[11.847394,48.815758],"type":"Point"}
}