{
  "type": "Feature",
  "properties": {
    "iso:country":"DE",
    "sg:address":"Oberer Graben 45",
    "sg:city":"Augsburg",
    "sg:phone":"+49 821/510310",
    "sg:postcode":"86152",
    "sg:province":"Bayern",
    "wof:name":"Robert Haas Architekt",
    "wof:placetype":"venue"
},
  "geometry": {"coordinates":[10.903262,48.367332],"type":"Point"}
}