{
  "type": "Feature",
  "properties": {
    "iso:country":"DE",
    "sg:address":"Rostocker Chaussee 3",
    "sg:city":"Stralsund",
    "sg:phone":"+49 3831/473527",
    "sg:postcode":"18437",
    "sg:province":"Mecklenburg-Vorpommern",
    "wof:name":"Raab Karcher Baustoffhandel Gmbh",
    "wof:placetype":"venue"
},
  "geometry": {"coordinates":[13.065943718,54.3066215515],"type":"Point"}
}