{
  "type": "Feature",
  "properties": {
    "iso:country":"DE",
    "sg:address":"Sophienblatt 92 -94",
    "sg:city":"Kiel",
    "sg:phone":"+49 431/685228",
    "sg:postcode":"24114",
    "sg:province":"Schleswig-Holstein",
    "wof:name":"S\u00f6rgel Sport Und Freizeit Gmbh",
    "wof:placetype":"venue"
},
  "geometry": {"coordinates":[10.126027,54.309586],"type":"Point"}
}