{
  "type": "Feature",
  "properties": {
    "iso:country":"DE",
    "sg:address":"Im St\u00fcckes 3",
    "sg:city":"Kelkheim",
    "sg:phone":"+49 6195/64233",
    "sg:postcode":"65779",
    "sg:province":"Hessen",
    "wof:name":"Eugen Und Holger Weil Steuerberater",
    "wof:placetype":"venue"
},
  "geometry": {"coordinates":[8.4489850998,50.1436195374],"type":"Point"}
}