{
  "type": "Feature",
  "properties": {
    "iso:country":"DE",
    "sg:address":"Euckenstr 19",
    "sg:city":"M\u00fcnchen",
    "sg:phone":"+49 89/8563560",
    "sg:postcode":"81369",
    "sg:province":"Bayern",
    "wof:name":"Licht & Ton Ger\u00e4teverleih Ltgv Gmbh",
    "wof:placetype":"venue"
},
  "geometry": {"coordinates":[11.5311975479,48.1146583557],"type":"Point"}
}