{
  "type": "Feature",
  "properties": {
    "iso:country":"DE",
    "sg:address":"Locher Weg 24",
    "sg:city":"Langenfeld",
    "sg:postcode":"40764",
    "sg:province":"Nordrhein-Westfalen",
    "wof:name":"Sieberg Immobilien Gmbh",
    "wof:placetype":"venue"
},
  "geometry": {"coordinates":[6.9633398056,51.0897827148],"type":"Point"}
}