{
  "type": "Feature",
  "properties": {
    "iso:country":"DE",
    "sg:address":"Bahnhofstr. 39",
    "sg:city":"Neu Wulmstorf",
    "sg:postcode":"21629",
    "sg:province":"Niedersachsen",
    "wof:name":"Gemeindeb\u00fccherei",
    "wof:placetype":"venue"
},
  "geometry": {"coordinates":[9.79148,53.468624],"type":"Point"}
}