{
  "type": "Feature",
  "properties": {
    "iso:country":"DE",
    "sg:address":"Schwimmbadallee 6",
    "sg:city":"Wingst",
    "sg:postcode":"21789",
    "sg:province":"Niedersachsen",
    "wof:name":"Aris Gmbh Versicherung",
    "wof:placetype":"venue"
},
  "geometry": {"coordinates":[9.0848350525,53.7533416748],"type":"Point"}
}