{
  "type": "Feature",
  "properties": {
    "iso:country":"DE",
    "sg:address":"Hartwigstr. 9",
    "sg:city":"Ruhland",
    "sg:phone":"+49 35752/2773",
    "sg:postcode":"01945",
    "sg:province":"Brandenburg",
    "wof:name":"M. Kurtz",
    "wof:placetype":"venue"
},
  "geometry": {"coordinates":[13.8611307144,51.4553527832],"type":"Point"}
}