{
  "type": "Feature",
  "properties": {
    "iso:country":"DE",
    "sg:address":"Auf der Wenge 5",
    "sg:city":"Herne",
    "sg:phone":"+49 2325/31526",
    "sg:postcode":"44651",
    "sg:province":"Nordrhein-Westfalen",
    "wof:name":"Glocken-apotheke Inh. Karin Hesseln",
    "wof:placetype":"venue"
},
  "geometry": {"coordinates":[7.15704,51.512939],"type":"Point"}
}