{
  "type": "Feature",
  "properties": {
    "iso:country":"DE",
    "sg:address":"Friedrich-Ebert-Str. 77",
    "sg:city":"Neckarsteinach",
    "sg:phone":"+49 6229/960120",
    "sg:postcode":"69239",
    "sg:province":"Hessen",
    "wof:name":"Wolfgang Nollert",
    "wof:placetype":"venue"
},
  "geometry": {"coordinates":[8.847522,49.399879],"type":"Point"}
}