{
  "type": "Feature",
  "properties": {
    "iso:country":"DE",
    "sg:address":"Obere K\u00f6nigsstr. 45 A",
    "sg:city":"Kassel",
    "sg:phone":"+49 561/102150",
    "sg:postcode":"34117",
    "sg:province":"Hessen",
    "wof:name":"Parf\u00fcmerie Douglas Nord Gmbh & Co. Kg",
    "wof:placetype":"venue"
},
  "geometry": {"coordinates":[9.496088,51.314884],"type":"Point"}
}