{
  "type": "Feature",
  "properties": {
    "iso:country":"DE",
    "sg:address":"Alter Rheder Weg 1",
    "sg:city":"Hamminkeln",
    "sg:phone":"+49 2856/1471",
    "sg:postcode":"46499",
    "sg:province":"Nordrhein-Westfalen",
    "wof:name":"Johann H\u00fclsmann",
    "wof:placetype":"venue"
},
  "geometry": {"coordinates":[6.679802,51.732986],"type":"Point"}
}