{
  "type": "Feature",
  "properties": {
    "iso:country":"DE",
    "sg:address":"L\u00f6ffelstr. 42",
    "sg:city":"Stuttgart",
    "sg:phone":"+49 711/1655401",
    "sg:postcode":"70597",
    "sg:province":"Baden-W\u00fcrttemberg",
    "wof:name":"Deloitte & Touche Gmbh",
    "wof:placetype":"venue"
},
  "geometry": {"coordinates":[9.16375,48.747246],"type":"Point"}
}