{
  "type": "Feature",
  "properties": {
    "iso:country":"DE",
    "sg:address":"Aachener Str. 72",
    "sg:city":"\u00dcbach-Palenberg",
    "sg:phone":"+49 2451/909329",
    "sg:postcode":"52531",
    "sg:province":"Nordrhein-Westfalen",
    "wof:name":"Bistro Intermezzo",
    "wof:placetype":"venue"
},
  "geometry": {"coordinates":[6.131975174,50.9384498596],"type":"Point"}
}