{
  "type": "Feature",
  "properties": {
    "iso:country":"DE",
    "sg:address":"Ostpreu\u00dfenstr. 6",
    "sg:city":"Neresheim",
    "sg:phone":"+49 7326/919306",
    "sg:postcode":"73450",
    "sg:province":"Baden-W\u00fcrttemberg",
    "wof:name":"Wolfgang Burkhard",
    "wof:placetype":"venue"
},
  "geometry": {"coordinates":[10.3199529648,48.7573051453],"type":"Point"}
}