{
  "type": "Feature",
  "properties": {
    "iso:country":"DE",
    "sg:address":"In der Siedlung 47",
    "sg:city":"Halblech",
    "sg:phone":"+49 8368/378",
    "sg:postcode":"87642",
    "sg:province":"Bayern",
    "wof:name":"Pension Haus Am Wildbach",
    "wof:placetype":"venue"
},
  "geometry": {"coordinates":[10.817530632,47.635055542],"type":"Point"}
}