{
  "type": "Feature",
  "properties": {
    "iso:country":"DE",
    "sg:address":"Beethovenstr. 47",
    "sg:city":"Wolfschlugen",
    "sg:phone":"+49 7022/52506",
    "sg:postcode":"72649",
    "sg:province":"Baden-W\u00fcrttemberg",
    "wof:name":"J. Peper",
    "wof:placetype":"venue"
},
  "geometry": {"coordinates":[9.2880897522,48.6599845886],"type":"Point"}
}