{
  "type": "Feature",
  "properties": {
    "iso:country":"DE",
    "sg:address":"August-Bebel-Str. 7",
    "sg:city":"Bruchk\u00f6bel",
    "sg:phone":"+49 6181618179163",
    "sg:postcode":"63486",
    "sg:province":"Hessen",
    "wof:name":"Madame Eshtars Schatzkiste",
    "wof:placetype":"venue"
},
  "geometry": {"coordinates":[8.9288740158,50.17527771],"type":"Point"}
}