{
  "type": "Feature",
  "properties": {
    "iso:country":"DE",
    "sg:address":"Sandstr. 33",
    "sg:city":"Waltrop",
    "sg:phone":"+49 2309/600904",
    "sg:postcode":"45731",
    "sg:province":"Nordrhein-Westfalen",
    "wof:name":"Jahnke Verm\u00f6gensverwaltungs Gmbh",
    "wof:placetype":"venue"
},
  "geometry": {"coordinates":[7.4205431938,51.6272659302],"type":"Point"}
}