{
  "type": "Feature",
  "properties": {
    "iso:country":"DE",
    "sg:address":"Schrabberdeich 30",
    "sg:city":"Brake",
    "sg:phone":"+49 4401/5005",
    "sg:postcode":"26919",
    "sg:province":"Niedersachsen",
    "wof:name":"Gundolf Jaegler Rechtsanwalt",
    "wof:placetype":"venue"
},
  "geometry": {"coordinates":[8.4747018814,53.3283958435],"type":"Point"}
}