{
  "type": "Feature",
  "properties": {
    "iso:country":"DE",
    "sg:address":"Sprangerstr. 5",
    "sg:city":"Schwandorf",
    "sg:postcode":"92421",
    "sg:province":"Bayern",
    "wof:name":"Friedrich Hochleitner Steuerberatungsges. Mbh",
    "wof:placetype":"venue"
},
  "geometry": {"coordinates":[12.1061792374,49.3376235962],"type":"Point"}
}