{
  "type": "Feature",
  "properties": {
    "iso:country":"DE",
    "sg:address":"Herbrandtstr. 19",
    "sg:city":"Giengen",
    "sg:phone":"+49 7322/7355",
    "sg:postcode":"89537",
    "sg:province":"Baden-W\u00fcrttemberg",
    "wof:name":"Dr. A. Schmautz Ingenieur",
    "wof:placetype":"venue"
},
  "geometry": {"coordinates":[10.2425775528,48.6300430298],"type":"Point"}
}