{
  "type": "Feature",
  "properties": {
    "iso:country":"DE",
    "sg:address":"Hudtwalckerstr. 11",
    "sg:city":"Hamburg",
    "sg:phone":"+49 40/46076611",
    "sg:postcode":"22299",
    "sg:province":"Hamburg",
    "wof:name":"Stuttgarter Allgemeine Versicherung Ag",
    "wof:placetype":"venue"
},
  "geometry": {"coordinates":[9.994811058,53.5938301086],"type":"Point"}
}