{
  "type": "Feature",
  "properties": {
    "iso:country":"DE",
    "sg:address":"Untergerbacherhof 1",
    "sg:city":"Ruppertsecken",
    "sg:phone":"+49 6361/8145",
    "sg:postcode":"67808",
    "sg:province":"Rheinland-Pfalz",
    "wof:name":"L. Portz",
    "wof:placetype":"venue"
},
  "geometry": {"coordinates":[7.908428,49.649895],"type":"Point"}
}