{
  "type": "Feature",
  "properties": {
    "iso:country":"DE",
    "sg:address":"Jettkofer Str. 2",
    "sg:city":"Ostrach",
    "sg:postcode":"88356",
    "sg:province":"Baden-W\u00fcrttemberg",
    "wof:name":"Ks Kies- Und Schotterwerk Beteiligungs- Gmbh",
    "wof:placetype":"venue"
},
  "geometry": {"coordinates":[9.37971,47.957111],"type":"Point"}
}