{
  "type": "Feature",
  "properties": {
    "iso:country":"DE",
    "sg:address":"Otto-Wels-Str. 5",
    "sg:city":"Weiterstadt",
    "sg:phone":"+49 6150/4659",
    "sg:postcode":"64331",
    "sg:province":"Hessen",
    "wof:name":"Kurt Langner Inh. Detelf Langner",
    "wof:placetype":"venue"
},
  "geometry": {"coordinates":[8.588739,49.906487],"type":"Point"}
}