{
  "type": "Feature",
  "properties": {
    "iso:country":"DE",
    "sg:address":"D\u00f6rfelsweg 2",
    "sg:city":"Buseck",
    "sg:postcode":"35418",
    "sg:province":"Hessen",
    "wof:name":"Biofrucht Oasis Gmbh",
    "wof:placetype":"venue"
},
  "geometry": {"coordinates":[8.8167285919,50.6183013916],"type":"Point"}
}