{
  "type": "Feature",
  "properties": {
    "iso:country":"DE",
    "sg:address":"Hauptstr. 40",
    "sg:city":"Bad Nenndorf",
    "sg:phone":"+49 5723/2360",
    "sg:postcode":"31542",
    "sg:province":"Niedersachsen",
    "wof:name":"Shell-station",
    "wof:placetype":"venue"
},
  "geometry": {"coordinates":[9.3834114075,52.3373451233],"type":"Point"}
}