{
  "type": "Feature",
  "properties": {
    "iso:country":"DE",
    "sg:address":"Nu\u00dfdorf",
    "sg:city":"\u00dcberlingen",
    "sg:phone":"+49 7551/62686",
    "sg:postcode":"88662",
    "sg:province":"Baden-W\u00fcrttemberg",
    "wof:name":"Grill-pub Laugele 17",
    "wof:placetype":"venue"
},
  "geometry": {"coordinates":[9.1733512878,47.7618865967],"type":"Point"}
}