{
  "type": "Feature",
  "properties": {
    "iso:country":"DE",
    "sg:address":"Eselspfad 3",
    "sg:city":"Hausen",
    "sg:phone":"+49 6022/22777",
    "sg:postcode":"63840",
    "sg:province":"Bayern",
    "wof:name":"Heinz Christ",
    "wof:placetype":"venue"
},
  "geometry": {"coordinates":[9.210486,49.868668],"type":"Point"}
}