{
  "type": "Feature",
  "properties": {
    "iso:country":"DE",
    "sg:address":"Alt Wachenbuchen 23",
    "sg:city":"Maintal",
    "sg:phone":"+49 6181/86764",
    "sg:postcode":"63477",
    "sg:province":"Hessen",
    "wof:name":"Hilberg & Partner Gmbh Automatisierungs-vakuumtechnik",
    "wof:placetype":"venue"
},
  "geometry": {"coordinates":[8.856822,50.169758],"type":"Point"}
}