{
  "type": "Feature",
  "properties": {
    "iso:country":"DE",
    "sg:address":"Hillenplatz 1",
    "sg:city":"Dillingen",
    "sg:phone":"+49 6831/71140",
    "sg:postcode":"66763",
    "sg:province":"Saarland",
    "wof:name":"Kath. Pfarramt St. Johannes",
    "wof:placetype":"venue"
},
  "geometry": {"coordinates":[6.727036953,49.3506851196],"type":"Point"}
}