{
  "type": "Feature",
  "properties": {
    "iso:country":"DE",
    "sg:address":"Werdener Str. 52",
    "sg:city":"Essen",
    "sg:phone":"+49 2054/81358",
    "sg:postcode":"45219",
    "sg:province":"Nordrhein-Westfalen",
    "wof:name":"Angelika Frost",
    "wof:placetype":"venue"
},
  "geometry": {"coordinates":[6.9389901161,51.3574333191],"type":"Point"}
}