{
  "type": "Feature",
  "properties": {
    "iso:country":"DE",
    "sg:address":"Pauliner Str.13",
    "sg:city":"Goettingen",
    "sg:postcode":"37073",
    "sg:province":"Niedersachsen",
    "wof:name":"Uhlendorff Reisebuero Gmbh",
    "wof:placetype":"venue"
},
  "geometry": {"coordinates":[9.9340276718,51.533405304],"type":"Point"}
}