{
  "type": "Feature",
  "properties": {
    "iso:country":"DE",
    "sg:address":"Schwerter Str. 31",
    "sg:city":"Iserlohn",
    "sg:postcode":"58642",
    "sg:province":"Nordrhein-Westfalen",
    "wof:name":"Gebr\u00fcder Pietro Und Antonio Leto Ohg",
    "wof:placetype":"venue"
},
  "geometry": {"coordinates":[7.6089601517,51.3742713928],"type":"Point"}
}