{
  "type": "Feature",
  "properties": {
    "iso:country":"DE",
    "sg:address":"Poststr. 15-17",
    "sg:city":"Weinstadt",
    "sg:phone":"+49 7151/999200",
    "sg:postcode":"71384",
    "sg:province":"Baden-W\u00fcrttemberg",
    "wof:name":"Rainer Sattler Gmbh",
    "wof:placetype":"venue"
},
  "geometry": {"coordinates":[9.385167,48.806385],"type":"Point"}
}