{
  "type": "Feature",
  "properties": {
    "iso:country":"DE",
    "sg:address":"Brodkorbweg 10",
    "sg:city":"Kempten",
    "sg:phone":"+49 831/73885",
    "sg:postcode":"87437",
    "sg:province":"Bayern",
    "wof:name":"Luise Sonner",
    "wof:placetype":"venue"
},
  "geometry": {"coordinates":[10.324018,47.728134],"type":"Point"}
}