{
  "type": "Feature",
  "properties": {
    "iso:country":"DE",
    "sg:address":"Lohsestr. 16",
    "sg:city":"K\u00f6ln",
    "sg:phone":"+49 221/7325781",
    "sg:postcode":"50733",
    "sg:province":"Nordrhein-Westfalen",
    "wof:name":"Kum-ho Sport-center Mudokwan",
    "wof:placetype":"venue"
},
  "geometry": {"coordinates":[6.9540100098,50.9631958008],"type":"Point"}
}