{
  "type": "Feature",
  "properties": {
    "iso:country":"DE",
    "sg:address":"Schnitzschulstr. 19",
    "sg:city":"Garmisch-Partenkirchen",
    "sg:phone":"+49 8821/1800",
    "sg:postcode":"82467",
    "sg:province":"Bayern",
    "wof:name":"Kongress-zentrum",
    "wof:placetype":"venue"
},
  "geometry": {"coordinates":[11.10797,47.493546],"type":"Point"}
}