{
  "type": "Feature",
  "properties": {
    "iso:country":"DE",
    "sg:address":"Cloppenburger Str. 179",
    "sg:city":"Oldenburg",
    "sg:phone":"+49 441/45585",
    "sg:postcode":"26133",
    "sg:province":"Niedersachsen",
    "wof:name":"Manfred Schmidt",
    "wof:placetype":"venue"
},
  "geometry": {"coordinates":[8.21645,53.120232],"type":"Point"}
}