{
  "type": "Feature",
  "properties": {
    "iso:country":"DE",
    "sg:address":"Harenberger Str. 2",
    "sg:city":"Hannover",
    "sg:phone":"+49 511/2199311",
    "sg:postcode":"30453",
    "sg:province":"Niedersachsen",
    "wof:name":"Mark Eldracher E. K.",
    "wof:placetype":"venue"
},
  "geometry": {"coordinates":[9.6904573441,52.3770980835],"type":"Point"}
}