{
  "type": "Feature",
  "properties": {
    "iso:country":"DE",
    "sg:address":"Friedrichshafener Str 18",
    "sg:city":"Brandenburg",
    "sg:phone":"+49 3381/75940",
    "sg:postcode":"14772",
    "sg:province":"Brandenburg",
    "wof:name":"Ger\u00fcstbau-service Zatlidis + Okon Gbr",
    "wof:placetype":"venue"
},
  "geometry": {"coordinates":[12.5061702728,52.438331604],"type":"Point"}
}