{
  "type": "Feature",
  "properties": {
    "iso:country":"DE",
    "sg:address":"Schubartstr. 12",
    "sg:city":"Backnang",
    "sg:phone":"+49 7191/66470",
    "sg:postcode":"71522",
    "sg:province":"Baden-W\u00fcrttemberg",
    "wof:name":"Modellbauverein Kondor Rolf K\u00f6ngeter",
    "wof:placetype":"venue"
},
  "geometry": {"coordinates":[9.4437103271,48.94165802],"type":"Point"}
}