{
  "type": "Feature",
  "properties": {
    "iso:country":"DE",
    "sg:address":"Friedrich-Ebert-Str. 19",
    "sg:city":"Lieberose",
    "sg:phone":"+49 33671/2335",
    "sg:postcode":"15868",
    "sg:province":"Brandenburg",
    "wof:name":"Dietmar Ulbrich",
    "wof:placetype":"venue"
},
  "geometry": {"coordinates":[14.2871751785,51.9906311035],"type":"Point"}
}