{
  "type": "Feature",
  "properties": {
    "iso:country":"DE",
    "sg:address":"Kirchweg 11",
    "sg:city":"Husum",
    "sg:phone":"+49 5027/8121",
    "sg:postcode":"31632",
    "sg:province":"Niedersachsen",
    "wof:name":"Vbb-baumaschinen- Vermittlungs Gmbh",
    "wof:placetype":"venue"
},
  "geometry": {"coordinates":[9.2480792999,52.5784378052],"type":"Point"}
}