{
  "type": "Feature",
  "properties": {
    "iso:country":"DE",
    "sg:address":"Kleine Ringstr. 8",
    "sg:city":"Finsterwalde",
    "sg:phone":"+49 3531/710130",
    "sg:postcode":"03238",
    "sg:province":"Brandenburg",
    "wof:name":"Reiseb\u00fcro Biebach",
    "wof:placetype":"venue"
},
  "geometry": {"coordinates":[13.7099161148,51.6309089661],"type":"Point"}
}