{
  "type": "Feature",
  "properties": {
    "iso:country":"DE",
    "sg:address":"Unterfeldstr. 15",
    "sg:city":"Garmisch-Partenkirchen",
    "sg:phone":"+49 8821/59765",
    "sg:postcode":"82467",
    "sg:province":"Bayern",
    "wof:name":"E. Schmidhuber",
    "wof:placetype":"venue"
},
  "geometry": {"coordinates":[11.1010227203,47.5036888123],"type":"Point"}
}