{
  "type": "Feature",
  "properties": {
    "iso:country":"DE",
    "sg:address":"Vogesenstra\u00dfe 1",
    "sg:city":"Badenweiler",
    "sg:postcode":"79410",
    "sg:province":"Baden-W\u00fcrttemberg",
    "wof:name":"Beratung F\u00fcr Banken Johannes G. Thoma",
    "wof:placetype":"venue"
},
  "geometry": {"coordinates":[7.666302,47.796734],"type":"Point"}
}