{
  "type": "Feature",
  "properties": {
    "iso:country":"DE",
    "sg:address":"M\u00fcnchener Str. 17",
    "sg:city":"Pfaffenhofen",
    "sg:postcode":"85276",
    "sg:province":"Bayern",
    "wof:name":"Im Ingrid-moden Vertriebs Gmbh",
    "wof:placetype":"venue"
},
  "geometry": {"coordinates":[11.510303,48.528156],"type":"Point"}
}