{
  "type": "Feature",
  "properties": {
    "iso:country":"DE",
    "sg:address":"Am M\u00fchlbach 13",
    "sg:city":"Wiggensbach",
    "sg:phone":"+49 8370/92070",
    "sg:postcode":"87487",
    "sg:province":"Bayern",
    "wof:name":"Praxair Services Gmbh & Co Kg",
    "wof:placetype":"venue"
},
  "geometry": {"coordinates":[10.2469577789,47.7462081909],"type":"Point"}
}