{
  "type": "Feature",
  "properties": {
    "iso:country":"DE",
    "sg:address":"Kieler Str. 3",
    "sg:city":"Bremen",
    "sg:phone":"+49 421/382682",
    "sg:postcode":"28219",
    "sg:province":"Bremen",
    "wof:name":"Gebr. Dill Gmbh",
    "wof:placetype":"venue"
},
  "geometry": {"coordinates":[8.7856807709,53.1027145386],"type":"Point"}
}