{
  "type": "Feature",
  "properties": {
    "iso:country":"DE",
    "sg:address":"Hauptstr. 32",
    "sg:city":"Kappelrodeck",
    "sg:phone":"+49 7842/2219",
    "sg:postcode":"77876",
    "sg:province":"Baden-W\u00fcrttemberg",
    "wof:name":"Herbert Maier",
    "wof:placetype":"venue"
},
  "geometry": {"coordinates":[8.116151,48.592403],"type":"Point"}
}