{
  "type": "Feature",
  "properties": {
    "iso:country":"DE",
    "sg:address":"Burgauerstr. 55a",
    "sg:city":"M\u00fcnchen",
    "sg:phone":"+49 89/932589",
    "sg:postcode":"81929",
    "sg:province":"Bayern",
    "wof:name":"Norbert Lipowsky",
    "wof:placetype":"venue"
},
  "geometry": {"coordinates":[11.6551990509,48.1454544067],"type":"Point"}
}