{
  "type": "Feature",
  "properties": {
    "iso:country":"DE",
    "sg:address":"Margueritenweg 6",
    "sg:city":"H\u00fcrth",
    "sg:phone":"+49 2233/72287",
    "sg:postcode":"50354",
    "sg:province":"Nordrhein-Westfalen",
    "wof:name":"Karin Gurbiers-hupp",
    "wof:placetype":"venue"
},
  "geometry": {"coordinates":[6.900126,50.878834],"type":"Point"}
}