{
  "type": "Feature",
  "properties": {
    "iso:country":"DE",
    "sg:address":"Calvinstr. 2",
    "sg:city":"Mannheim",
    "sg:phone":"+49 621/471256",
    "sg:postcode":"68229",
    "sg:province":"Baden-W\u00fcrttemberg",
    "wof:name":"Hermann Schneider",
    "wof:placetype":"venue"
},
  "geometry": {"coordinates":[8.579178,49.442966],"type":"Point"}
}