{
  "type": "Feature",
  "properties": {
    "iso:country":"DE",
    "sg:address":"Schopenhauerstr. 28",
    "sg:city":"Potsdam",
    "sg:phone":"+49 331/970319",
    "sg:postcode":"14467",
    "sg:province":"Brandenburg",
    "wof:name":"Rita Fuchs",
    "wof:placetype":"venue"
},
  "geometry": {"coordinates":[13.04789,52.400452],"type":"Point"}
}