{
  "type": "Feature",
  "properties": {
    "iso:country":"DE",
    "sg:address":"Passauerstr 45",
    "sg:city":"M\u00fcnchen",
    "sg:phone":"+49 89/7260970",
    "sg:postcode":"81369",
    "sg:province":"Bayern",
    "wof:name":"Megasystems Automatisierungssysteme Gmbh",
    "wof:placetype":"venue"
},
  "geometry": {"coordinates":[11.5340452194,48.1125183105],"type":"Point"}
}