{
  "type": "Feature",
  "properties": {
    "iso:country":"DE",
    "sg:address":"Birkenleite 8",
    "sg:city":"Starnberg",
    "sg:phone":"+49 8151/14309",
    "sg:postcode":"82319",
    "sg:province":"Bayern",
    "wof:name":"D. Forster Immobilienmakler",
    "wof:placetype":"venue"
},
  "geometry": {"coordinates":[11.3197345734,47.9976043701],"type":"Point"}
}