{
  "type": "Feature",
  "properties": {
    "iso:country":"DE",
    "sg:address":"Rheinstr. 3",
    "sg:city":"Offenburg",
    "sg:phone":"+49 781/36636",
    "sg:postcode":"77652",
    "sg:province":"Baden-W\u00fcrttemberg",
    "wof:name":"Kurt-friedrich Lehmann Siebdruck",
    "wof:placetype":"venue"
},
  "geometry": {"coordinates":[7.943979,48.478737],"type":"Point"}
}