{
  "type": "Feature",
  "properties": {
    "iso:country":"DE",
    "sg:address":"Schleefstr. 1",
    "sg:city":"Dortmund",
    "sg:phone":"+49 231/92490",
    "sg:postcode":"44287",
    "sg:province":"Nordrhein-Westfalen",
    "wof:name":"Erwin Huchtemeier Mbh & Co. Kg",
    "wof:placetype":"venue"
},
  "geometry": {"coordinates":[7.5721039772,51.5016136169],"type":"Point"}
}