{
  "type": "Feature",
  "properties": {
    "iso:country":"DE",
    "sg:address":"Dreik\u00f6nigenstr. 15-17",
    "sg:city":"Krefeld",
    "sg:phone":"+49 2151/802021",
    "sg:postcode":"47799",
    "sg:province":"Nordrhein-Westfalen",
    "wof:name":"Reiseb\u00fcro Br\u00fcck & Stephan Gmbh",
    "wof:placetype":"venue"
},
  "geometry": {"coordinates":[6.570661068,51.3312339783],"type":"Point"}
}