{
  "type": "Feature",
  "properties": {
    "iso:country":"DE",
    "sg:address":"Reichsstr. 31",
    "sg:city":"Gera",
    "sg:phone":"+49 365/7106584",
    "sg:postcode":"07545",
    "sg:province":"Th\u00fcringen",
    "wof:name":"Technische Orthop\u00e4die Gera Sanit\u00e4tshaus",
    "wof:placetype":"venue"
},
  "geometry": {"coordinates":[12.0855093002,50.8665275574],"type":"Point"}
}