{
  "type": "Feature",
  "properties": {
    "iso:country":"DE",
    "sg:address":"Heckenweg 25",
    "sg:city":"Grafenau",
    "sg:phone":"+49 7033/44847",
    "sg:postcode":"71120",
    "sg:province":"Baden-W\u00fcrttemberg",
    "wof:name":"Bernhard Gro\u00df",
    "wof:placetype":"venue"
},
  "geometry": {"coordinates":[8.910578,48.716225],"type":"Point"}
}