{
  "type": "Feature",
  "properties": {
    "iso:country":"DE",
    "sg:address":"Adolf-Damaschke-Str. 8",
    "sg:city":"Schwalbach",
    "sg:phone":"+49 6196/848473",
    "sg:postcode":"65824",
    "sg:province":"Hessen",
    "wof:name":"Gross Und Partner Rechtsanw\u00e4lte",
    "wof:placetype":"venue"
},
  "geometry": {"coordinates":[8.5286197662,50.1566390991],"type":"Point"}
}