{
  "type": "Feature",
  "properties": {
    "iso:country":"DE",
    "sg:address":"Karlstr. 52",
    "sg:city":"Herne",
    "sg:phone":"+49 2325/797537",
    "sg:postcode":"44649",
    "sg:province":"Nordrhein-Westfalen",
    "wof:name":"Torl\u00fcmke",
    "wof:placetype":"venue"
},
  "geometry": {"coordinates":[7.148006,51.536987],"type":"Point"}
}