{
  "type": "Feature",
  "properties": {
    "iso:country":"DE",
    "sg:address":"Wallfahrtsteich 18",
    "sg:city":"Minden",
    "sg:phone":"+49 571/45374",
    "sg:postcode":"32425",
    "sg:province":"Nordrhein-Westfalen",
    "wof:name":"Dach-steiger Gmbh",
    "wof:placetype":"venue"
},
  "geometry": {"coordinates":[8.917549,52.31612],"type":"Point"}
}