{
  "type": "Feature",
  "properties": {
    "iso:country":"DE",
    "sg:address":"Vogtstr. 20",
    "sg:city":"Donaueschingen",
    "sg:phone":"+49 771/2408",
    "sg:postcode":"78166",
    "sg:province":"Baden-W\u00fcrttemberg",
    "wof:name":"Gasthof Traube",
    "wof:placetype":"venue"
},
  "geometry": {"coordinates":[8.5642471313,47.9813461304],"type":"Point"}
}