{
  "type": "Feature",
  "properties": {
    "iso:country":"DE",
    "sg:address":"Weldingsfelder Weg",
    "sg:city":"Ingelfingen",
    "sg:postcode":"74653",
    "sg:province":"Baden-W\u00fcrttemberg",
    "wof:name":"Verwaltungsgesellschaft Ingelfinger Wohnbau Gmbh",
    "wof:placetype":"venue"
},
  "geometry": {"coordinates":[9.704895,49.330822],"type":"Point"}
}