{
  "type": "Feature",
  "properties": {
    "iso:country":"DE",
    "sg:address":"Riesebusch 10 b",
    "sg:city":"Bad Schwartau",
    "sg:phone":"+49 451/282917",
    "sg:postcode":"23611",
    "sg:province":"Schleswig-Holstein",
    "wof:name":"P. Sch\u00f6ttler Inh. Sabine Martinovs",
    "wof:placetype":"venue"
},
  "geometry": {"coordinates":[10.7010250092,53.9247055054],"type":"Point"}
}