{
  "type": "Feature",
  "properties": {
    "iso:country":"DE",
    "sg:address":"Hauptstr. 87",
    "sg:city":"Hornberg",
    "sg:phone":"+49 7833/506",
    "sg:postcode":"78132",
    "sg:province":"Baden-W\u00fcrttemberg",
    "wof:name":"Stefan Moser Ingenieur",
    "wof:placetype":"venue"
},
  "geometry": {"coordinates":[8.2300357819,48.2123222351],"type":"Point"}
}