{
  "type": "Feature",
  "properties": {
    "iso:country":"DE",
    "sg:address":"Stra\u00dfe der Freundschaft 12",
    "sg:city":"Frohburg",
    "sg:phone":"+49 34348/54919",
    "sg:postcode":"04654",
    "sg:province":"Sachsen",
    "wof:name":"G. Volk Rechtsanwalt",
    "wof:placetype":"venue"
},
  "geometry": {"coordinates":[12.5584917068,51.0559158325],"type":"Point"}
}