{
  "type": "Feature",
  "properties": {
    "iso:country":"DE",
    "sg:address":"Donnersbergstr. 1",
    "sg:city":"Schiffweiler",
    "sg:phone":"+49 6821/67195",
    "sg:postcode":"66578",
    "sg:province":"Saarland",
    "wof:name":"E. Biehl Gmbh",
    "wof:placetype":"venue"
},
  "geometry": {"coordinates":[7.126681,49.37191],"type":"Point"}
}