{
  "type": "Feature",
  "properties": {
    "iso:country":"DE",
    "sg:address":"Meckelfelder Weg 2",
    "sg:city":"Hamburg",
    "sg:phone":"+49 40/76981077",
    "sg:postcode":"21079",
    "sg:province":"Hamburg",
    "wof:name":"Hans-j\u00fcrgen Schoop Architekt",
    "wof:placetype":"venue"
},
  "geometry": {"coordinates":[9.993259,53.425316],"type":"Point"}
}