{
  "type": "Feature",
  "properties": {
    "iso:country":"DE",
    "sg:address":"Lehmbruckstr. 13",
    "sg:city":"Berlin",
    "sg:phone":"+49 30/2918598",
    "sg:postcode":"10245",
    "sg:province":"Berlin",
    "wof:name":"Gmd Gesellschaft F\u00fcr Marketing Und Dienstleistung",
    "wof:placetype":"venue"
},
  "geometry": {"coordinates":[13.4530239105,52.5027427673],"type":"Point"}
}