{
  "type": "Feature",
  "properties": {
    "iso:country":"DE",
    "sg:address":"Nordlichtstra\u00dfe 22",
    "sg:city":"Berlin",
    "sg:phone":"+49 30/4129161",
    "sg:postcode":"13405",
    "sg:province":"Berlin",
    "wof:name":"Glaserei Terasa - Reparatur Neuanfertigung",
    "wof:placetype":"venue"
},
  "geometry": {"coordinates":[13.3231258392,52.5639228821],"type":"Point"}
}