{
  "type": "Feature",
  "properties": {
    "iso:country":"DE",
    "sg:address":"Dieselstr. 11",
    "sg:city":"Neuhofen",
    "sg:phone":"+49 6236/51307",
    "sg:postcode":"67141",
    "sg:province":"Rheinland-Pfalz",
    "wof:name":"Heike Liebel-tancredi",
    "wof:placetype":"venue"
},
  "geometry": {"coordinates":[8.4141168594,49.4254493713],"type":"Point"}
}