{
  "type": "Feature",
  "properties": {
    "iso:country":"DE",
    "sg:address":"Biberacher Str. 10",
    "sg:city":"Uttenweiler",
    "sg:phone":"+49 7374/528",
    "sg:postcode":"88524",
    "sg:province":"Baden-W\u00fcrttemberg",
    "wof:name":"Erich Manz Elektroinstallation",
    "wof:placetype":"venue"
},
  "geometry": {"coordinates":[9.651445,48.125687],"type":"Point"}
}