{
  "type": "Feature",
  "properties": {
    "iso:country":"DE",
    "sg:address":"Am Sandberg 3",
    "sg:city":"Markt Wald",
    "sg:phone":"+49 8262/397",
    "sg:postcode":"86865",
    "sg:province":"Bayern",
    "wof:name":"H. M\u00fcller",
    "wof:placetype":"venue"
},
  "geometry": {"coordinates":[10.584919,48.135895],"type":"Point"}
}