{
  "type": "Feature",
  "properties": {
    "iso:country":"DE",
    "sg:address":"F\u00f6rsterkamp 11",
    "sg:city":"Hamburg",
    "sg:phone":"+49 40/760190",
    "sg:postcode":"21149",
    "sg:province":"Hamburg",
    "wof:name":"Elbe-werkst\u00e4tten Gmbh",
    "wof:placetype":"venue"
},
  "geometry": {"coordinates":[9.9134702682,53.471244812],"type":"Point"}
}