{
  "type": "Feature",
  "properties": {
    "iso:country":"DE",
    "sg:address":"Stavenhagener Str. 23",
    "sg:city":"Malchin",
    "sg:phone":"+49 3994/632992",
    "sg:postcode":"17139",
    "sg:province":"Mecklenburg-Vorpommern",
    "wof:name":"Wolfgang K\u00fcssner",
    "wof:placetype":"venue"
},
  "geometry": {"coordinates":[12.7738180161,53.7395706177],"type":"Point"}
}