{
  "type": "Feature",
  "properties": {
    "iso:country":"DE",
    "sg:address":"Delmenhorster Str. 12",
    "sg:city":"Wildeshausen",
    "sg:phone":"+49 4431/92379",
    "sg:postcode":"27793",
    "sg:province":"Niedersachsen",
    "wof:name":"Gs Tankstelle Gmbh",
    "wof:placetype":"venue"
},
  "geometry": {"coordinates":[8.4426212311,52.9058074951],"type":"Point"}
}