{
  "type": "Feature",
  "properties": {
    "iso:country":"DE",
    "sg:address":"L\u00f6bestr. 1",
    "sg:city":"Bonn",
    "sg:phone":"+49 228/361376",
    "sg:postcode":"53173",
    "sg:province":"Nordrhein-Westfalen",
    "wof:name":"Redaktion Dajv-newsletter Dt.-amerik. Juristen-",
    "wof:placetype":"venue"
},
  "geometry": {"coordinates":[7.1570620537,50.6832695007],"type":"Point"}
}