{
  "type": "Feature",
  "properties": {
    "iso:country":"DE",
    "sg:address":"Scheideholzweg 80",
    "sg:city":"Hamburg",
    "sg:postcode":"21149",
    "sg:province":"Hamburg",
    "wof:name":"Show Veranstaltungen Hamburg Elke Buhse",
    "wof:placetype":"venue"
},
  "geometry": {"coordinates":[9.838193,53.470993],"type":"Point"}
}