{
  "type": "Feature",
  "properties": {
    "iso:country":"DE",
    "sg:address":"Siedlung 13",
    "sg:city":"Falkenbach",
    "sg:phone":"+49 37369/9626",
    "sg:postcode":"09429",
    "sg:province":"Sachsen",
    "wof:name":"Sportlerheim",
    "wof:placetype":"venue"
},
  "geometry": {"coordinates":[13.0398044586,50.6457138062],"type":"Point"}
}