{
  "type": "Feature",
  "properties": {
    "iso:country":"DE",
    "sg:address":"Kandelstr. 4",
    "sg:city":"Waldkirch",
    "sg:phone":"+49 7681/7354",
    "sg:postcode":"79183",
    "sg:province":"Baden-W\u00fcrttemberg",
    "wof:name":"Bernd Lutz",
    "wof:placetype":"venue"
},
  "geometry": {"coordinates":[7.9631009102,48.0925483704],"type":"Point"}
}