{
  "type": "Feature",
  "properties": {
    "iso:country":"DE",
    "sg:address":"Otto-Hahn-Str. 6",
    "sg:city":"Schwandorf",
    "sg:phone":"+49 9431/757030",
    "sg:postcode":"92421",
    "sg:province":"Bayern",
    "wof:name":"Zweirad Bruckner Gmbh",
    "wof:placetype":"venue"
},
  "geometry": {"coordinates":[12.097721,49.310234],"type":"Point"}
}