{
  "type": "Feature",
  "properties": {
    "iso:country":"DE",
    "sg:address":"Schweizer Str. 42",
    "sg:city":"Frankfurt",
    "sg:phone":"+49 69/615010",
    "sg:postcode":"60594",
    "sg:province":"Hessen",
    "wof:name":"Meyer",
    "wof:placetype":"venue"
},
  "geometry": {"coordinates":[8.6798200607,50.1026916504],"type":"Point"}
}