{
  "type": "Feature",
  "properties": {
    "iso:country":"DE",
    "sg:address":"Bartholom\u00e4usstr. 29",
    "sg:city":"Warendorf",
    "sg:phone":"+49 2584/292",
    "sg:postcode":"48231",
    "sg:province":"Nordrhein-Westfalen",
    "wof:name":"Westf\u00e4lischer Hof",
    "wof:placetype":"venue"
},
  "geometry": {"coordinates":[7.8944621086,51.9740257263],"type":"Point"}
}