{
  "type": "Feature",
  "properties": {
    "iso:country":"DE",
    "sg:address":"Rennbaumer Str 57",
    "sg:city":"Wuppertal",
    "sg:phone":"+49 202/402254",
    "sg:postcode":"42349",
    "sg:province":"Nordrhein-Westfalen",
    "wof:name":"Otto Pabst Gmbh",
    "wof:placetype":"venue"
},
  "geometry": {"coordinates":[7.155575,51.219524],"type":"Point"}
}