{
  "type": "Feature",
  "properties": {
    "iso:country":"DE",
    "sg:address":"Bamberger Str. 7",
    "sg:city":"Bamberg",
    "sg:phone":"+49 951/59358",
    "sg:postcode":"96049",
    "sg:province":"Bayern",
    "wof:name":"Vvs Holding Vertriebs- Verwaltungs- Und Service Gmbh",
    "wof:placetype":"venue"
},
  "geometry": {"coordinates":[10.8957881927,49.8695411682],"type":"Point"}
}