{
  "type": "Feature",
  "properties": {
    "iso:country":"DE",
    "sg:address":"Westerengerstr. 55",
    "sg:city":"Bielefeld",
    "sg:phone":"+49 5206/3389",
    "sg:postcode":"33739",
    "sg:province":"Nordrhein-Westfalen",
    "wof:name":"Nolden & Uekermann Isoliertechnik Gmbh",
    "wof:placetype":"venue"
},
  "geometry": {"coordinates":[8.516823,52.110081],"type":"Point"}
}