{
  "type": "Feature",
  "properties": {
    "iso:country":"DE",
    "sg:address":"Martinsbogen 20",
    "sg:city":"Leipzig",
    "sg:phone":"+49 341/9617700",
    "sg:postcode":"04158",
    "sg:province":"Sachsen",
    "wof:name":"Wampfler Gmbh",
    "wof:placetype":"venue"
},
  "geometry": {"coordinates":[12.3596801758,51.38671875],"type":"Point"}
}