{
  "type": "Feature",
  "properties": {
    "iso:country":"DE",
    "sg:address":"Dunkerhofstr. 4",
    "sg:city":"Grefrath",
    "sg:phone":"+49 2158/2251",
    "sg:postcode":"47929",
    "sg:province":"Nordrhein-Westfalen",
    "wof:name":"Katholisches Pfarramt St. Laurentius",
    "wof:placetype":"venue"
},
  "geometry": {"coordinates":[6.3426408768,51.3359909058],"type":"Point"}
}