{
  "type": "Feature",
  "properties": {
    "iso:country":"DE",
    "sg:address":"Bahnhofstr. 19",
    "sg:city":"Kirchhain",
    "sg:phone":"+49 6422/6230",
    "sg:postcode":"35274",
    "sg:province":"Hessen",
    "wof:name":"K.-l. Bubenheim",
    "wof:placetype":"venue"
},
  "geometry": {"coordinates":[8.921081,50.823132],"type":"Point"}
}