{
  "type": "Feature",
  "properties": {
    "iso:country":"DE",
    "sg:address":"Coerm\u00fchle",
    "sg:city":"M\u00fcnster",
    "sg:postcode":"48157",
    "sg:province":"Nordrhein-Westfalen",
    "wof:name":"Bki Grundbesitz Verwaltungs Gmbh",
    "wof:placetype":"venue"
},
  "geometry": {"coordinates":[7.6665878296,52.0368690491],"type":"Point"}
}