{
  "type": "Feature",
  "properties": {
    "iso:country":"DE",
    "sg:address":"Hansaallee 65",
    "sg:city":"Rheine",
    "sg:phone":"+49 5971/963113",
    "sg:postcode":"48429",
    "sg:province":"Nordrhein-Westfalen",
    "wof:name":"Reddy K\u00fcchen Und Elektro Welt Gmbh",
    "wof:placetype":"venue"
},
  "geometry": {"coordinates":[7.4411010742,52.2861099243],"type":"Point"}
}