{
  "type": "Feature",
  "properties": {
    "iso:country":"DE",
    "sg:address":"Hohenzollernstr. 36",
    "sg:city":"M\u00fcnchen",
    "sg:phone":"+49 89/399311",
    "sg:postcode":"80801",
    "sg:province":"Bayern",
    "wof:name":"S J B Software Ing.-b\u00fcro",
    "wof:placetype":"venue"
},
  "geometry": {"coordinates":[11.5810556412,48.1600189209],"type":"Point"}
}