{
  "type": "Feature",
  "properties": {
    "iso:country":"DE",
    "sg:address":"Barthestr. 115",
    "sg:city":"Barth/Ostsee",
    "sg:phone":"+49 4938/2313262",
    "sg:postcode":"18356",
    "sg:province":"Mecklenburg-Vorpommern",
    "wof:name":"New Gastroline Gmbh",
    "wof:placetype":"venue"
},
  "geometry": {"coordinates":[12.723548,54.358158],"type":"Point"}
}