{
  "type": "Feature",
  "properties": {
    "iso:country":"DE",
    "sg:address":"Postfach 56",
    "sg:city":"Lauchheim",
    "sg:phone":"+49 7363/919144",
    "sg:postcode":"73466",
    "sg:province":"Baden-W\u00fcrttemberg",
    "wof:name":"Rohug- Dessous-versand",
    "wof:placetype":"venue"
},
  "geometry": {"coordinates":[10.2460699081,48.871761322],"type":"Point"}
}