{
  "type": "Feature",
  "properties": {
    "iso:country":"DE",
    "sg:address":"Unterheutal 13",
    "sg:city":"M\u00fcnsingen",
    "sg:phone":"+49 7381/3778",
    "sg:postcode":"72525",
    "sg:province":"Baden-W\u00fcrttemberg",
    "wof:name":"Bahnhof",
    "wof:placetype":"venue"
},
  "geometry": {"coordinates":[9.5316839218,48.3684692383],"type":"Point"}
}