{
  "type": "Feature",
  "properties": {
    "iso:country":"DE",
    "sg:address":"Accumer Riege 30",
    "sg:city":"Dornum",
    "sg:phone":"+49 4933/990090",
    "sg:postcode":"26553",
    "sg:province":"Niedersachsen",
    "wof:name":"Helga Weilage",
    "wof:placetype":"venue"
},
  "geometry": {"coordinates":[7.4339470863,53.6487617493],"type":"Point"}
}