{
  "type": "Feature",
  "properties": {
    "iso:country":"DE",
    "sg:address":"Oberer Graben 17",
    "sg:city":"Plauen",
    "sg:phone":"+49 3741/228416",
    "sg:postcode":"08527",
    "sg:province":"Sachsen",
    "wof:name":"Oliver Hopp Rechtsanwalt",
    "wof:placetype":"venue"
},
  "geometry": {"coordinates":[12.1331501007,50.4939918518],"type":"Point"}
}