{
  "type": "Feature",
  "properties": {
    "iso:country":"DE",
    "sg:address":"Drosselweg 2",
    "sg:city":"Dischingen",
    "sg:phone":"+49 7327/5376",
    "sg:postcode":"89561",
    "sg:province":"Baden-W\u00fcrttemberg",
    "wof:name":"J. Und A. Sturm",
    "wof:placetype":"venue"
},
  "geometry": {"coordinates":[10.4420127869,48.7119369507],"type":"Point"}
}