{
  "type": "Feature",
  "properties": {
    "iso:country":"DE",
    "sg:address":"Hof\u00e4ckerstr. 1/1",
    "sg:city":"Jettingen",
    "sg:phone":"+49 7452/75792",
    "sg:postcode":"71131",
    "sg:province":"Baden-W\u00fcrttemberg",
    "wof:name":"Werner Frasch",
    "wof:placetype":"venue"
},
  "geometry": {"coordinates":[8.772635,48.576458],"type":"Point"}
}