{
  "type": "Feature",
  "properties": {
    "iso:country":"DE",
    "sg:address":"Lange Str. 85",
    "sg:city":"Castrop-Rauxel",
    "sg:phone":"+49 2305/75041",
    "sg:postcode":"44579",
    "sg:province":"Nordrhein-Westfalen",
    "wof:name":"Flora-apotheke",
    "wof:placetype":"venue"
},
  "geometry": {"coordinates":[7.314351,51.585117],"type":"Point"}
}