{
  "type": "Feature",
  "properties": {
    "iso:country":"DE",
    "sg:address":"Steinweg 7",
    "sg:city":"Neustadt",
    "sg:phone":"+49 9568/5480",
    "sg:postcode":"96465",
    "sg:province":"Bayern",
    "wof:name":"Jochen Kath",
    "wof:placetype":"venue"
},
  "geometry": {"coordinates":[9.9819583893,53.5508155823],"type":"Point"}
}