{
  "type": "Feature",
  "properties": {
    "iso:country":"DE",
    "sg:address":"Auf dem Damm 8",
    "sg:city":"Heidenrod",
    "sg:phone":"+49 6120/8065",
    "sg:postcode":"65321",
    "sg:province":"Hessen",
    "wof:name":"Wilhelm Lampert",
    "wof:placetype":"venue"
},
  "geometry": {"coordinates":[7.9977498055,50.2107887268],"type":"Point"}
}