{
  "type": "Feature",
  "properties": {
    "iso:country":"DE",
    "sg:address":"Mittlerer Schafhofweg 5",
    "sg:city":"Frankfurt",
    "sg:phone":"+49 69/63152132",
    "sg:postcode":"60598",
    "sg:province":"Hessen",
    "wof:name":"Grundbesitzgesellschaft K\u00f6rnerstra\u00dfe 56 Kg",
    "wof:placetype":"venue"
},
  "geometry": {"coordinates":[8.6836471558,50.0917778015],"type":"Point"}
}