{
  "type": "Feature",
  "properties": {
    "iso:country":"DE",
    "sg:address":"Frohndbrunnengasse 23",
    "sg:city":"Mosbach",
    "sg:phone":"+49 6261/2696",
    "sg:postcode":"74821",
    "sg:province":"Baden-W\u00fcrttemberg",
    "wof:name":"Adolf Jost",
    "wof:placetype":"venue"
},
  "geometry": {"coordinates":[9.144898,49.350834],"type":"Point"}
}