{
  "type": "Feature",
  "properties": {
    "iso:country":"DE",
    "sg:address":"Sohra 26",
    "sg:city":"Bobritzsch",
    "sg:phone":"+49 37325/6314",
    "sg:postcode":"09627",
    "sg:province":"Sachsen",
    "wof:name":"Mathias Jungnickel",
    "wof:placetype":"venue"
},
  "geometry": {"coordinates":[13.43059,50.902481],"type":"Point"}
}