{
  "type": "Feature",
  "properties": {
    "iso:country":"DE",
    "sg:address":"Koelner Str. 123",
    "sg:city":"Attendorn",
    "sg:phone":"+49 4927/2292550",
    "sg:postcode":"57439",
    "sg:province":"Nordrhein-Westfalen",
    "wof:name":"Bms Gmbh & Co. Kg , Ges. Fuer Blechbearbeitung, Mechanische Bearbeitung Und Schweisskonstruktion",
    "wof:placetype":"venue"
},
  "geometry": {"coordinates":[7.8845000267,51.1178398132],"type":"Point"}
}