{
  "type": "Feature",
  "properties": {
    "iso:country":"DE",
    "sg:address":"Feldstr. 16-18",
    "sg:city":"Hainburg",
    "sg:phone":"+49 6182/4107",
    "sg:postcode":"63512",
    "sg:province":"Hessen",
    "wof:name":"M\u00f6bel - Eckrich Inh. Brigitte Eckrich",
    "wof:placetype":"venue"
},
  "geometry": {"coordinates":[8.9377069473,50.0814056396],"type":"Point"}
}