{
  "type": "Feature",
  "properties": {
    "iso:country":"DE",
    "sg:address":"Allee 3",
    "sg:city":"Alfeld",
    "sg:phone":"+49 5181/25208",
    "sg:postcode":"31061",
    "sg:province":"Niedersachsen",
    "wof:name":"Wilhelm Beie",
    "wof:placetype":"venue"
},
  "geometry": {"coordinates":[9.766592,51.987244],"type":"Point"}
}