{
  "type": "Feature",
  "properties": {
    "iso:country":"DE",
    "sg:address":"Woldsenweg 7",
    "sg:city":"Hamburg",
    "sg:phone":"+49 40/488103",
    "sg:postcode":"20249",
    "sg:province":"Hamburg",
    "wof:name":"Urse-b\u00e4rbel Omonsky Krankengymnastin",
    "wof:placetype":"venue"
},
  "geometry": {"coordinates":[9.987183,53.587849],"type":"Point"}
}