{
  "type": "Feature",
  "properties": {
    "iso:country":"DE",
    "sg:address":"Echternacher Str. 8",
    "sg:city":"Troisdorf",
    "sg:phone":"+49 2241/951340",
    "sg:postcode":"53842",
    "sg:province":"Nordrhein-Westfalen",
    "wof:name":"Auvitron Audio- Und Video Anlagen Gmbh",
    "wof:placetype":"venue"
},
  "geometry": {"coordinates":[7.1142749786,50.8180274963],"type":"Point"}
}