{
  "type": "Feature",
  "properties": {
    "iso:country":"DE",
    "sg:address":"M\u00fchldorfer Str. 1",
    "sg:city":"Forstinning",
    "sg:phone":"+49 8092/24081",
    "sg:postcode":"85661",
    "sg:province":"Bayern",
    "wof:name":"Sircom Gesellschaft F\u00fcr Systemintegration Und",
    "wof:placetype":"venue"
},
  "geometry": {"coordinates":[11.911277,48.168037],"type":"Point"}
}