{
  "type": "Feature",
  "properties": {
    "iso:country":"DE",
    "sg:address":"Loge 64",
    "sg:city":"Eydelstedt",
    "sg:phone":"+49 5442/2284",
    "sg:postcode":"49406",
    "sg:province":"Niedersachsen",
    "wof:name":"Wilhelm Klingenberg",
    "wof:placetype":"venue"
},
  "geometry": {"coordinates":[8.5869808197,52.6925926208],"type":"Point"}
}