{
  "type": "Feature",
  "properties": {
    "iso:country":"DE",
    "sg:address":"Spitalstr. 1",
    "sg:city":"Donauw\u00f6rth",
    "sg:phone":"+49 906/4078",
    "sg:postcode":"86609",
    "sg:province":"Bayern",
    "wof:name":"Schnitzer Und Kollegen Rechtsanw\u00e4lte",
    "wof:placetype":"venue"
},
  "geometry": {"coordinates":[10.7804889679,48.7177963257],"type":"Point"}
}