{
  "type": "Feature",
  "properties": {
    "iso:country":"DE",
    "sg:address":"Neum\u00fchler Str. 59",
    "sg:city":"Oberhausen",
    "sg:phone":"+49 208/663907",
    "sg:postcode":"46149",
    "sg:province":"Nordrhein-Westfalen",
    "wof:name":"U. Krames",
    "wof:placetype":"venue"
},
  "geometry": {"coordinates":[6.836137,51.510464],"type":"Point"}
}