{
  "type": "Feature",
  "properties": {
    "iso:country":"DE",
    "sg:address":"Gr\u00fcnstr. 11",
    "sg:city":"Berlin",
    "sg:phone":"+49 30/6557370",
    "sg:postcode":"12555",
    "sg:province":"Berlin",
    "wof:name":"Gartenbau- Und Verwaltungs Dom\u00e4ne K\u00f6penick Gmbh",
    "wof:placetype":"venue"
},
  "geometry": {"coordinates":[13.576649,52.444889],"type":"Point"}
}