{
  "type": "Feature",
  "properties": {
    "iso:country":"DE",
    "sg:address":"Markt 20",
    "sg:city":"Rehna",
    "sg:postcode":"19217",
    "sg:province":"Mecklenburg-Vorpommern",
    "wof:name":"Mht Haustechnik- Und Service Gmbh",
    "wof:placetype":"venue"
},
  "geometry": {"coordinates":[11.048754,53.780865],"type":"Point"}
}