{
  "type": "Feature",
  "properties": {
    "iso:country":"DE",
    "sg:address":"Schonnebecker Str. 28",
    "sg:city":"Gelsenkirchen",
    "sg:phone":"+49 209/130003",
    "sg:postcode":"45884",
    "sg:province":"Nordrhein-Westfalen",
    "wof:name":"Fuhrmannsruh",
    "wof:placetype":"venue"
},
  "geometry": {"coordinates":[7.0806999207,51.4916419983],"type":"Point"}
}