{
  "type": "Feature",
  "properties": {
    "iso:country":"DE",
    "sg:address":"Kapperundweg",
    "sg:city":"Winterberg",
    "sg:phone":"+49 2981/908060",
    "sg:postcode":"59955",
    "sg:province":"Nordrhein-Westfalen",
    "wof:name":"Sommerrodelbahn Verwaltungs Gmbh",
    "wof:placetype":"venue"
},
  "geometry": {"coordinates":[8.506815,51.184578],"type":"Point"}
}