{
  "type": "Feature",
  "properties": {
    "iso:country":"DE",
    "sg:address":"Brumbyer Weg 36-40",
    "sg:city":"Calbe",
    "sg:postcode":"39240",
    "sg:province":"Sachsen-Anhalt",
    "wof:name":"Landw. -verwaltungsges. Mbh",
    "wof:placetype":"venue"
},
  "geometry": {"coordinates":[11.763365,51.896259],"type":"Point"}
}