{
  "type": "Feature",
  "properties": {
    "iso:country":"DE",
    "sg:address":"Auf dem Keipersnickel 10",
    "sg:city":"Hanau",
    "sg:phone":"+49 6181/956326",
    "sg:postcode":"63457",
    "sg:province":"Hessen",
    "wof:name":"Michael Strunz",
    "wof:placetype":"venue"
},
  "geometry": {"coordinates":[8.9511194229,50.099029541],"type":"Point"}
}