{
  "type": "Feature",
  "properties": {
    "iso:country":"DE",
    "sg:address":"Schattbucher Str 16",
    "sg:city":"Amtzell",
    "sg:phone":"+49 7520/95650",
    "sg:postcode":"88279",
    "sg:province":"Baden-W\u00fcrttemberg",
    "wof:name":"Holzwerk K\u00fcbler Gmbh",
    "wof:placetype":"venue"
},
  "geometry": {"coordinates":[9.75745,47.69492],"type":"Point"}
}