{
  "type": "Feature",
  "properties": {
    "iso:country":"DE",
    "sg:address":"Bahnhofplatz 6",
    "sg:city":"Nordheim",
    "sg:phone":"+49 7133/8416",
    "sg:postcode":"74226",
    "sg:province":"Baden-W\u00fcrttemberg",
    "wof:name":"Pizzeria Carlo Grillo",
    "wof:placetype":"venue"
},
  "geometry": {"coordinates":[9.1349630356,49.1076583862],"type":"Point"}
}