{
  "type": "Feature",
  "properties": {
    "iso:country":"DE",
    "sg:address":"Blankenburger Str. 42",
    "sg:city":"Hasselfelde",
    "sg:phone":"+49 39459/71319",
    "sg:postcode":"38899",
    "sg:province":"Sachsen-Anhalt",
    "wof:name":"Wolfgang Pattok",
    "wof:placetype":"venue"
},
  "geometry": {"coordinates":[10.857192,51.692619],"type":"Point"}
}