{
  "type": "Feature",
  "properties": {
    "iso:country":"DE",
    "sg:address":"Th\u00fcler Str.",
    "sg:city":"Friesoythe",
    "sg:phone":"+49 4491/2315",
    "sg:postcode":"26169",
    "sg:province":"Niedersachsen",
    "wof:name":"Josef Hillen",
    "wof:placetype":"venue"
},
  "geometry": {"coordinates":[7.860088,53.014133],"type":"Point"}
}