{
  "type": "Feature",
  "properties": {
    "iso:country":"DE",
    "sg:address":"Werner-Heisenberg-Str. 20",
    "sg:city":"Leverkusen",
    "sg:phone":"+49 2171/768627",
    "sg:postcode":"51381",
    "sg:province":"Nordrhein-Westfalen",
    "wof:name":"Igs Ingenieurb\u00fcro F\u00fcr Geotechnische Sanierungs-",
    "wof:placetype":"venue"
},
  "geometry": {"coordinates":[7.0445227623,51.0650749207],"type":"Point"}
}