{
  "type": "Feature",
  "properties": {
    "iso:country":"DE",
    "sg:address":"Meisenweg 67",
    "sg:city":"G\u00f6ppingen",
    "sg:phone":"+49 7161/45336",
    "sg:postcode":"73035",
    "sg:province":"Baden-W\u00fcrttemberg",
    "wof:name":"F. Kothe",
    "wof:placetype":"venue"
},
  "geometry": {"coordinates":[9.636759758,48.6862297058],"type":"Point"}
}