{
  "type": "Feature",
  "properties": {
    "iso:country":"DE",
    "sg:address":"Wilhelm-Leuschner-Str. 43",
    "sg:city":"K\u00f6ln",
    "sg:phone":"+49 221/5993523",
    "sg:postcode":"50739",
    "sg:province":"Nordrhein-Westfalen",
    "wof:name":"Rwg Immobilienservice Gmbh",
    "wof:placetype":"venue"
},
  "geometry": {"coordinates":[6.9142951965,50.9914703369],"type":"Point"}
}