{
  "type": "Feature",
  "properties": {
    "iso:country":"DE",
    "sg:address":"Hauptstr. 106",
    "sg:city":"Sulzbach",
    "sg:phone":"+49 6196/60090",
    "sg:postcode":"65843",
    "sg:province":"Hessen",
    "wof:name":"Rudolf Achenbach Gmbh & Co. Kg",
    "wof:placetype":"venue"
},
  "geometry": {"coordinates":[8.5154953003,50.1388473511],"type":"Point"}
}