{
  "type": "Feature",
  "properties": {
    "iso:country":"DE",
    "sg:address":"Br\u00fcckenstr. 44",
    "sg:city":"Neudenau",
    "sg:phone":"+49 6298/1255",
    "sg:postcode":"74861",
    "sg:province":"Baden-W\u00fcrttemberg",
    "wof:name":"Werner Stammer",
    "wof:placetype":"venue"
},
  "geometry": {"coordinates":[9.3061990738,49.3020324707],"type":"Point"}
}