{
  "type": "Feature",
  "properties": {
    "iso:country":"DE",
    "sg:address":"Bahnhofstr. 2",
    "sg:city":"Waltershausen",
    "sg:phone":"+49 3622/69048",
    "sg:postcode":"99880",
    "sg:province":"Th\u00fcringen",
    "wof:name":"Thuringia-apotheke Dr. Horst Engelbert Wei\u00df E. K.",
    "wof:placetype":"venue"
},
  "geometry": {"coordinates":[10.559962,50.900795],"type":"Point"}
}