{
  "type": "Feature",
  "properties": {
    "iso:country":"DE",
    "sg:address":"Lauterbachstr. 20",
    "sg:city":"Eggenfelden",
    "sg:phone":"+49 8721/96960",
    "sg:postcode":"84307",
    "sg:province":"Bayern",
    "wof:name":"Baustoffh\u00e4ndler Otto Schmid Gmbh",
    "wof:placetype":"venue"
},
  "geometry": {"coordinates":[12.757023,48.400204],"type":"Point"}
}