{
  "type": "Feature",
  "properties": {
    "iso:country":"DE",
    "sg:address":"Rosenfelder Str. 18",
    "sg:city":"V\u00f6hringen",
    "sg:phone":"+49 7454/2860",
    "sg:postcode":"72189",
    "sg:province":"Baden-W\u00fcrttemberg",
    "wof:name":"W Schittenhelm",
    "wof:placetype":"venue"
},
  "geometry": {"coordinates":[8.6637878418,48.3342323303],"type":"Point"}
}