{
  "type": "Feature",
  "properties": {
    "iso:country":"DE",
    "sg:address":"Kieler Str. 18",
    "sg:city":"Eckernf\u00f6rde",
    "sg:phone":"+49 4351/2546",
    "sg:postcode":"24340",
    "sg:province":"Schleswig-Holstein",
    "wof:name":"Markus Witt Gmbh",
    "wof:placetype":"venue"
},
  "geometry": {"coordinates":[9.836623,54.471672],"type":"Point"}
}