{
  "type": "Feature",
  "properties": {
    "iso:country":"DE",
    "sg:address":"Eggetaler Str. 44",
    "sg:city":"Preu\u00dfisch Oldendorf",
    "sg:phone":"+49 5742/2291",
    "sg:postcode":"32361",
    "sg:province":"Nordrhein-Westfalen",
    "wof:name":"Wilfried Budde",
    "wof:placetype":"venue"
},
  "geometry": {"coordinates":[8.5094995499,52.2746009827],"type":"Point"}
}