{
  "type": "Feature",
  "properties": {
    "iso:country":"DE",
    "sg:address":"Giesenbach 39",
    "sg:city":"Kranzberg",
    "sg:phone":"+49 8165/989771",
    "sg:postcode":"85402",
    "sg:province":"Bayern",
    "wof:name":"Horstmann-anlagen-service E. K",
    "wof:placetype":"venue"
},
  "geometry": {"coordinates":[11.6157894135,48.3856468201],"type":"Point"}
}