{
  "type": "Feature",
  "properties": {
    "iso:country":"DE",
    "sg:address":"Esenser Str.",
    "sg:city":"Wittmund",
    "sg:postcode":"26409",
    "sg:province":"Niedersachsen",
    "wof:name":"Aldi Gmbh & Co. Kg",
    "wof:placetype":"venue"
},
  "geometry": {"coordinates":[7.7731747627,53.582775116],"type":"Point"}
}