{
  "type": "Feature",
  "properties": {
    "iso:country":"DE",
    "sg:address":"Landhausstr. 15",
    "sg:city":"Heidelberg",
    "sg:phone":"+49 6221/160568",
    "sg:postcode":"69115",
    "sg:province":"Baden-W\u00fcrttemberg",
    "wof:name":"Paninvesta Verm\u00f6gensgesellschaft Mbh",
    "wof:placetype":"venue"
},
  "geometry": {"coordinates":[8.6890058517,49.4041442871],"type":"Point"}
}