{
  "type": "Feature",
  "properties": {
    "iso:country":"DE",
    "sg:address":"Von-Alten-Str. 23",
    "sg:city":"Burgwedel",
    "sg:phone":"+49 5139/2125",
    "sg:postcode":"30938",
    "sg:province":"Niedersachsen",
    "wof:name":"U. Rissmann",
    "wof:placetype":"venue"
},
  "geometry": {"coordinates":[9.859953,52.493534],"type":"Point"}
}