{
  "type": "Feature",
  "properties": {
    "iso:country":"DE",
    "sg:address":"M\u00fchlstr. 7",
    "sg:city":"Bad Urach",
    "sg:phone":"+49 7125/84240",
    "sg:postcode":"72574",
    "sg:province":"Baden-W\u00fcrttemberg",
    "wof:name":"Herzog Christoph",
    "wof:placetype":"venue"
},
  "geometry": {"coordinates":[9.402559,48.489262],"type":"Point"}
}