{
  "type": "Feature",
  "properties": {
    "iso:country":"DE",
    "sg:address":"Altenburger Str. 1",
    "sg:city":"Frohburg",
    "sg:phone":"+49 34348/51634",
    "sg:postcode":"04654",
    "sg:province":"Sachsen",
    "wof:name":"G. Schurig",
    "wof:placetype":"venue"
},
  "geometry": {"coordinates":[12.554031,51.05447],"type":"Point"}
}