{
  "type": "Feature",
  "properties": {
    "iso:country":"DE",
    "sg:address":"Kirchstr. 3",
    "sg:city":"V\u00f6hringen",
    "sg:phone":"+49 7454/2669",
    "sg:postcode":"72189",
    "sg:province":"Baden-W\u00fcrttemberg",
    "wof:name":"Wilhelm Hagenlocher",
    "wof:placetype":"venue"
},
  "geometry": {"coordinates":[8.663982,48.334747],"type":"Point"}
}