{
  "type": "Feature",
  "properties": {
    "iso:country":"DE",
    "sg:address":"Nossener Str. 52",
    "sg:city":"Lommatzsch",
    "sg:phone":"+49 35241/58878",
    "sg:postcode":"01623",
    "sg:province":"Sachsen",
    "wof:name":"R. Wargel",
    "wof:placetype":"venue"
},
  "geometry": {"coordinates":[13.3156747818,51.1944656372],"type":"Point"}
}