{
  "type": "Feature",
  "properties": {
    "iso:country":"DE",
    "sg:address":"Mettinger Str. 33",
    "sg:city":"Esslingen",
    "sg:phone":"+49 711/373608",
    "sg:postcode":"73728",
    "sg:province":"Baden-W\u00fcrttemberg",
    "wof:name":"Dr. Roland Luithle Rechtsanwalt",
    "wof:placetype":"venue"
},
  "geometry": {"coordinates":[9.2981052399,48.7431411743],"type":"Point"}
}