{
  "type": "Feature",
  "properties": {
    "iso:country":"DE",
    "sg:address":"Ursulaplatz 1",
    "sg:city":"K\u00f6ln",
    "sg:phone":"+49 221/121121",
    "sg:postcode":"50668",
    "sg:province":"Nordrhein-Westfalen",
    "wof:name":"Internationaler \u00dcbersetzungs- Und Dolmetscherdienst",
    "wof:placetype":"venue"
},
  "geometry": {"coordinates":[6.955553,50.944775],"type":"Point"}
}