{
  "type": "Feature",
  "properties": {
    "iso:country":"DE",
    "sg:address":"Rudolf-Utsch-Str. 1a",
    "sg:city":"Brachbach",
    "sg:phone":"+49 2745/1873",
    "sg:postcode":"57555",
    "sg:province":"Rheinland-Pfalz",
    "wof:name":"Bernd Farnschl\u00e4der",
    "wof:placetype":"venue"
},
  "geometry": {"coordinates":[7.93119,50.818771],"type":"Point"}
}