{
  "type": "Feature",
  "properties": {
    "iso:country":"DE",
    "sg:address":"Luitpold-Baumann-Str. 12",
    "sg:city":"Dettelbach",
    "sg:phone":"+49 9324/99830",
    "sg:postcode":"97337",
    "sg:province":"Bayern",
    "wof:name":"Gl\u00f6ggler G\u00e4rtnerei",
    "wof:placetype":"venue"
},
  "geometry": {"coordinates":[10.166918,49.804287],"type":"Point"}
}