{
  "type": "Feature",
  "properties": {
    "iso:country":"DE",
    "sg:address":"Hauptstr. 3",
    "sg:city":"Schleching",
    "sg:phone":"+49 8649/243",
    "sg:postcode":"83259",
    "sg:province":"Bayern",
    "wof:name":"Josef Lukas Kaufhaus",
    "wof:placetype":"venue"
},
  "geometry": {"coordinates":[12.39769,47.720642],"type":"Point"}
}