{
  "type": "Feature",
  "properties": {
    "iso:country":"DE",
    "sg:address":"Templhof 3",
    "sg:city":"Wessobrunn",
    "sg:phone":"+49 8809/284",
    "sg:postcode":"82405",
    "sg:province":"Bayern",
    "wof:name":"Bernhard Resch",
    "wof:placetype":"venue"
},
  "geometry": {"coordinates":[11.032445,47.845711],"type":"Point"}
}