{
  "type": "Feature",
  "properties": {
    "iso:country":"DE",
    "sg:address":"Focksweg 42",
    "sg:city":"Hamburg",
    "sg:phone":"+49 40/7425191",
    "sg:postcode":"21129",
    "sg:province":"Hamburg",
    "wof:name":"Restaurant Finkenwerder Elbblick Gmbh",
    "wof:placetype":"venue"
},
  "geometry": {"coordinates":[9.8737306595,53.5384521484],"type":"Point"}
}