{
  "type": "Feature",
  "properties": {
    "iso:country":"DE",
    "sg:city":"Niedernhall",
    "sg:phone":"+49 7940",
    "sg:postcode":"74676",
    "sg:province":"Baden-W\u00fcrttemberg",
    "wof:name":"Compuchem Software Chemie",
    "wof:placetype":"venue"
},
  "geometry": {"coordinates":[9.616752,49.294769],"type":"Point"}
}