{
  "type": "Feature",
  "properties": {
    "iso:country":"DE",
    "sg:address":"Kadeltshofer Str. 20",
    "sg:city":"Holzheim",
    "sg:phone":"+49 7302/5103",
    "sg:postcode":"89291",
    "sg:province":"Bayern",
    "wof:name":"W. Botzenhard",
    "wof:placetype":"venue"
},
  "geometry": {"coordinates":[10.110232,48.379528],"type":"Point"}
}