{
  "type": "Feature",
  "properties": {
    "iso:country":"DE",
    "sg:address":"Neltestr. 1",
    "sg:city":"Berlin",
    "sg:postcode":"12489",
    "sg:province":"Berlin",
    "wof:name":"Sabine Hauthal",
    "wof:placetype":"venue"
},
  "geometry": {"coordinates":[13.535643,52.440132],"type":"Point"}
}