{
  "type": "Feature",
  "properties": {
    "iso:country":"DE",
    "sg:address":"M\u00fchlbachstr. 24",
    "sg:city":"Bodman Ludwigshafen",
    "sg:phone":"+49 4977/735342",
    "sg:postcode":"78351",
    "sg:province":"Baden-W\u00fcrttemberg",
    "wof:name":"Sparkasse Stockach",
    "wof:placetype":"venue"
},
  "geometry": {"coordinates":[9.057762,47.819595],"type":"Point"}
}