{
  "type": "Feature",
  "properties": {
    "iso:country":"DE",
    "sg:address":"Neckargr\u00f6ninger Str. 23",
    "sg:city":"Ludwigsburg",
    "sg:phone":"+49 4971/4129450",
    "sg:postcode":"71640",
    "sg:province":"Baden-W\u00fcrttemberg",
    "wof:name":"Telma Retarder Deutschland Gmbh",
    "wof:placetype":"venue"
},
  "geometry": {"coordinates":[9.2367963791,48.890007019],"type":"Point"}
}