{
  "type": "Feature",
  "properties": {
    "iso:country":"DE",
    "sg:address":"Thorwaldsenstr. 9",
    "sg:city":"Ludwigshafen",
    "sg:phone":"+49 621/562551",
    "sg:postcode":"67061",
    "sg:province":"Rheinland-Pfalz",
    "wof:name":"Ho Ka Montage Gmbh",
    "wof:placetype":"venue"
},
  "geometry": {"coordinates":[8.44616,49.468727],"type":"Point"}
}