{
  "type": "Feature",
  "properties": {
    "iso:country":"DE",
    "sg:address":"F\u00e4hrstr. 105",
    "sg:city":"Nordenham",
    "sg:phone":"+49 4731/37103",
    "sg:postcode":"26954",
    "sg:province":"Niedersachsen",
    "wof:name":"Weserschl\u00f6\u00dfchen",
    "wof:placetype":"venue"
},
  "geometry": {"coordinates":[8.542757988,53.5218544006],"type":"Point"}
}