{
  "type": "Feature",
  "properties": {
    "iso:country":"DE",
    "sg:address":"Industriestr. 15",
    "sg:city":"F\u00fcrth",
    "sg:phone":"+49 911/303550",
    "sg:postcode":"90765",
    "sg:province":"Bayern",
    "wof:name":"M\u00fcllers Fliesen Markt Gmbh",
    "wof:placetype":"venue"
},
  "geometry": {"coordinates":[11.001488,49.511456],"type":"Point"}
}