{
  "type": "Feature",
  "properties": {
    "iso:country":"DE",
    "sg:address":"Behrensstr. 5",
    "sg:city":"Ludwigshafen",
    "sg:phone":"+49 621/652944",
    "sg:postcode":"67069",
    "sg:province":"Rheinland-Pfalz",
    "wof:name":"F. Schneider",
    "wof:placetype":"venue"
},
  "geometry": {"coordinates":[8.398633,49.518688],"type":"Point"}
}