{
  "type": "Feature",
  "properties": {
    "iso:country":"DE",
    "sg:address":"Tornauer Weg 6",
    "sg:city":"Ro\u00dflau",
    "sg:phone":"+49 34901/84129",
    "sg:postcode":"06862",
    "sg:province":"Sachsen-Anhalt",
    "wof:name":"Toom-baumarkt",
    "wof:placetype":"venue"
},
  "geometry": {"coordinates":[12.2726202011,51.9025802612],"type":"Point"}
}