{
  "type": "Feature",
  "properties": {
    "iso:country":"DE",
    "sg:address":"Woorte 27",
    "sg:city":"Borken",
    "sg:phone":"+49 2862/2608",
    "sg:postcode":"46325",
    "sg:province":"Nordrhein-Westfalen",
    "wof:name":"Gerhard Rademacher",
    "wof:placetype":"venue"
},
  "geometry": {"coordinates":[6.796969,51.892757],"type":"Point"}
}