{
  "type": "Feature",
  "properties": {
    "iso:country":"DE",
    "sg:address":"Dorfstr. 46",
    "sg:city":"Boddin",
    "sg:phone":"+49 39971/17260",
    "sg:postcode":"17179",
    "sg:province":"Mecklenburg-Vorpommern",
    "wof:name":"Liedhaber Co J\u00f6rg Kokott",
    "wof:placetype":"venue"
},
  "geometry": {"coordinates":[12.649612,53.939037],"type":"Point"}
}