{
  "type": "Feature",
  "properties": {
    "iso:country":"DE",
    "sg:address":"Anton-Bruckner-Str. 3",
    "sg:city":"Vaterstetten",
    "sg:phone":"+49 8106/358035",
    "sg:postcode":"85591",
    "sg:province":"Bayern",
    "wof:name":"K. Drewes",
    "wof:placetype":"venue"
},
  "geometry": {"coordinates":[11.7795448303,48.1057739258],"type":"Point"}
}