{
  "type": "Feature",
  "properties": {
    "iso:country":"DE",
    "sg:address":"Merianstr. 27",
    "sg:city":"Frankfurt",
    "sg:phone":"+49 69/71035100",
    "sg:postcode":"60316",
    "sg:province":"Hessen",
    "wof:name":"Dhnr Ohg Deutsche Handelsges. F\u00fcr",
    "wof:placetype":"venue"
},
  "geometry": {"coordinates":[8.6935586929,50.1212882996],"type":"Point"}
}