{
  "type": "Feature",
  "properties": {
    "iso:country":"DE",
    "sg:address":"Bramscher Str. 18",
    "sg:city":"Osnabr\u00fcck",
    "sg:phone":"+49 541/63772",
    "sg:postcode":"49088",
    "sg:province":"Niedersachsen",
    "wof:name":"Bernd Grocholl Ingenieur",
    "wof:placetype":"venue"
},
  "geometry": {"coordinates":[8.0430450439,52.2838821411],"type":"Point"}
}