{
  "type": "Feature",
  "properties": {
    "iso:country":"DE",
    "sg:address":"Maibuscher Str. 15",
    "sg:city":"Hude",
    "sg:phone":"+49 4408/2969",
    "sg:postcode":"27798",
    "sg:province":"Niedersachsen",
    "wof:name":"Bsb Bauplanung Gmbh",
    "wof:placetype":"venue"
},
  "geometry": {"coordinates":[8.457828,53.132977],"type":"Point"}
}