{
  "type": "Feature",
  "properties": {
    "iso:country":"DE",
    "sg:address":"Max-Eyth-Str. 12",
    "sg:city":"Kirchheim",
    "sg:phone":"+49 7021/976220",
    "sg:postcode":"73230",
    "sg:province":"Baden-W\u00fcrttemberg",
    "wof:name":"Karl R\u00e4pple",
    "wof:placetype":"venue"
},
  "geometry": {"coordinates":[9.449159,48.648739],"type":"Point"}
}