{
  "type": "Feature",
  "properties": {
    "iso:country":"DE",
    "sg:address":"Am Ortfelde 9",
    "sg:city":"Lehrte",
    "sg:phone":"+49 5136/878627",
    "sg:postcode":"31275",
    "sg:province":"Niedersachsen",
    "wof:name":"Gawa Gasrohrbau Und Wassertechnik Gmbh",
    "wof:placetype":"venue"
},
  "geometry": {"coordinates":[9.9945011139,52.4149131775],"type":"Point"}
}