{
  "type": "Feature",
  "properties": {
    "iso:country":"DE",
    "sg:address":"Brunecker Str. 64",
    "sg:city":"N\u00fcrnberg",
    "sg:phone":"+49 911/441186",
    "sg:postcode":"90461",
    "sg:province":"Bayern",
    "wof:name":"Fl\u00d6ckinger Blechver- Arbeitungs Gmbh",
    "wof:placetype":"venue"
},
  "geometry": {"coordinates":[11.095074,49.426228],"type":"Point"}
}