{
  "type": "Feature",
  "properties": {
    "iso:country":"DE",
    "sg:address":"Triftstr. 44",
    "sg:city":"Bad Homburg",
    "sg:postcode":"61350",
    "sg:province":"Hessen",
    "wof:name":"Profashion Sales Company Inh. Wolfram Mader E. K.",
    "wof:placetype":"venue"
},
  "geometry": {"coordinates":[8.600458,50.231499],"type":"Point"}
}