{
  "type": "Feature",
  "properties": {
    "iso:country":"DE",
    "sg:address":"Plankemai 19",
    "sg:city":"Flensburg",
    "sg:phone":"+49 4634/1014",
    "sg:postcode":"24937",
    "sg:province":"Schleswig-Holstein",
    "wof:name":"Daarwin Beteiligungs- Gesellschaft Mbh",
    "wof:placetype":"venue"
},
  "geometry": {"coordinates":[9.440779,54.785046],"type":"Point"}
}