{
  "type": "Feature",
  "properties": {
    "iso:country":"DE",
    "sg:address":"Kopernikusstr. 8",
    "sg:city":"Kirchheim",
    "sg:phone":"+49 7021/57000",
    "sg:postcode":"73230",
    "sg:province":"Baden-W\u00fcrttemberg",
    "wof:name":"Vll Versand- Und Lager- Logistik Gmbh",
    "wof:placetype":"venue"
},
  "geometry": {"coordinates":[6.833621,50.610443],"type":"Point"}
}