{
  "type": "Feature",
  "properties": {
    "iso:country":"DE",
    "sg:address":"Am B\u00fcrgerpark 29 a",
    "sg:city":"Verden",
    "sg:phone":"+49 4231/82882",
    "sg:postcode":"27283",
    "sg:province":"Niedersachsen",
    "wof:name":"Horst Griemert Rechtsanwalt Und Notar",
    "wof:placetype":"venue"
},
  "geometry": {"coordinates":[9.2327032089,52.9308624268],"type":"Point"}
}