{
  "type": "Feature",
  "properties": {
    "iso:country":"DE",
    "sg:address":"Industriestr. 5",
    "sg:city":"Erzhausen",
    "sg:phone":"+49 6150/9629103",
    "sg:postcode":"64390",
    "sg:province":"Hessen",
    "wof:name":"Asc Aero Survey Consult Gmbh",
    "wof:placetype":"venue"
},
  "geometry": {"coordinates":[8.6499433517,49.9492874146],"type":"Point"}
}