{
  "type": "Feature",
  "properties": {
    "iso:country":"DE",
    "sg:address":"Krefelder Str. 673",
    "sg:city":"M\u00f6nchengladbach",
    "sg:phone":"+49 2161/650099",
    "sg:postcode":"41066",
    "sg:province":"Nordrhein-Westfalen",
    "wof:name":"Internationale Transporte M. Rieger Gmbh",
    "wof:placetype":"venue"
},
  "geometry": {"coordinates":[6.4849247932,51.2262382507],"type":"Point"}
}