{
  "type": "Feature",
  "properties": {
    "iso:country":"DE",
    "sg:address":"Bochumer Str. 73",
    "sg:city":"Recklinghausen",
    "sg:phone":"+49 2361/35644",
    "sg:postcode":"45663",
    "sg:province":"Nordrhein-Westfalen",
    "wof:name":"W. Schindler",
    "wof:placetype":"venue"
},
  "geometry": {"coordinates":[7.2133150101,51.5766181946],"type":"Point"}
}