{
  "type": "Feature",
  "properties": {
    "iso:country":"DE",
    "sg:address":"Wurmbergstr. 2",
    "sg:city":"Sindelfingen",
    "sg:phone":"+49 7031/224832",
    "sg:postcode":"71063",
    "sg:province":"Baden-W\u00fcrttemberg",
    "wof:name":"Roland Kurth",
    "wof:placetype":"venue"
},
  "geometry": {"coordinates":[8.9998149872,48.7107276917],"type":"Point"}
}