{
  "type": "Feature",
  "properties": {
    "iso:country":"DE",
    "sg:address":"Friedrich-Bergius-Ring 2-4",
    "sg:city":"W\u00fcrzburg",
    "sg:phone":"+49 6056/5115",
    "sg:postcode":"97076",
    "sg:province":"Bayern",
    "wof:name":"Zinkand",
    "wof:placetype":"venue"
},
  "geometry": {"coordinates":[9.374767,50.29298],"type":"Point"}
}