{
  "type": "Feature",
  "properties": {
    "iso:country":"DE",
    "sg:address":"Pastors Kamp 11",
    "sg:city":"Steinfeld",
    "sg:phone":"+49 5492/98698",
    "sg:postcode":"49439",
    "sg:province":"Niedersachsen",
    "wof:name":"Hugo Kohorst",
    "wof:placetype":"venue"
},
  "geometry": {"coordinates":[8.198887,52.61898],"type":"Point"}
}