{
  "type": "Feature",
  "properties": {
    "iso:country":"DE",
    "sg:address":"Obermarkt 8",
    "sg:city":"Neusalza-Spremberg",
    "sg:phone":"+49 35872/34711",
    "sg:postcode":"02742",
    "sg:province":"Sachsen",
    "wof:name":"Andreas Kloss",
    "wof:placetype":"venue"
},
  "geometry": {"coordinates":[14.530229,51.036907],"type":"Point"}
}