{
  "type": "Feature",
  "properties": {
    "iso:country":"DE",
    "sg:address":"Max-Planck-Str 5",
    "sg:city":"Straelen",
    "sg:phone":"+49 2834/91490",
    "sg:postcode":"47638",
    "sg:province":"Nordrhein-Westfalen",
    "wof:name":"Udo Blaschczok Gmbh Stahlkaminbau",
    "wof:placetype":"venue"
},
  "geometry": {"coordinates":[6.272804,51.431396],"type":"Point"}
}