{
  "type": "Feature",
  "properties": {
    "iso:country":"DE",
    "sg:address":"Pastiner Str. 34",
    "sg:city":"Sternberg",
    "sg:phone":"+49 3847/451071",
    "sg:postcode":"19406",
    "sg:province":"Mecklenburg-Vorpommern",
    "wof:name":"Kaufhaus R. M\u00f6ller Sternberg Gmbh",
    "wof:placetype":"venue"
},
  "geometry": {"coordinates":[11.82857,53.710625],"type":"Point"}
}