{
  "type": "Feature",
  "properties": {
    "iso:country":"DE",
    "sg:address":"Richard-Byrd-Str. 21",
    "sg:city":"K\u00f6ln",
    "sg:phone":"+49 221/593746",
    "sg:postcode":"50829",
    "sg:province":"Nordrhein-Westfalen",
    "wof:name":"Suppenkaspar Suppenk\u00fcchen Gmbh",
    "wof:placetype":"venue"
},
  "geometry": {"coordinates":[6.8845729828,50.9879722595],"type":"Point"}
}