{
  "type": "Feature",
  "properties": {
    "iso:country":"DE",
    "sg:address":"Sch\u00f6nflie\u00dfer Str. 65",
    "sg:city":"Hohen Neuendorf",
    "sg:phone":"+49 3303/500771",
    "sg:postcode":"16540",
    "sg:province":"Brandenburg",
    "wof:name":"Bestattungsinstitut Ralf Heinrich",
    "wof:placetype":"venue"
},
  "geometry": {"coordinates":[13.280547,52.671207],"type":"Point"}
}