{
  "type": "Feature",
  "properties": {
    "iso:country":"DE",
    "sg:address":"Westernstr. 21",
    "sg:city":"Borchen",
    "sg:phone":"+49 5292/930960",
    "sg:postcode":"33178",
    "sg:province":"Nordrhein-Westfalen",
    "wof:name":"Dopp",
    "wof:placetype":"venue"
},
  "geometry": {"coordinates":[8.7572832108,51.6293525696],"type":"Point"}
}