{
  "type": "Feature",
  "properties": {
    "iso:country":"DE",
    "sg:address":"Klosterstr. 26",
    "sg:city":"Ostritz",
    "sg:phone":"+49 35823/86347",
    "sg:postcode":"02899",
    "sg:province":"Sachsen",
    "wof:name":"C. Eichler Immobilienmakler",
    "wof:placetype":"venue"
},
  "geometry": {"coordinates":[14.9324007034,51.0100708008],"type":"Point"}
}