{
  "type": "Feature",
  "properties": {
    "iso:country":"DE",
    "sg:address":"Knochstr. 43",
    "sg:city":"Saalfeld",
    "sg:phone":"+49 3671/520041",
    "sg:postcode":"07318",
    "sg:province":"Th\u00fcringen",
    "wof:name":"Iris Kr\u00f6tzsch Masseurin",
    "wof:placetype":"venue"
},
  "geometry": {"coordinates":[11.362318,50.641502],"type":"Point"}
}