{
  "type": "Feature",
  "properties": {
    "iso:country":"DE",
    "sg:address":"Robert-Bosch-Str 5",
    "sg:city":"Markdorf",
    "sg:phone":"+49 7544/934020",
    "sg:postcode":"88677",
    "sg:province":"Baden-W\u00fcrttemberg",
    "wof:name":"Acm Gmbh",
    "wof:placetype":"venue"
},
  "geometry": {"coordinates":[9.40423,47.709522],"type":"Point"}
}