{
  "type": "Feature",
  "properties": {
    "iso:country":"DE",
    "sg:address":"Nadorster Str. 82",
    "sg:city":"Oldenburg",
    "sg:phone":"+49 441/8853148",
    "sg:postcode":"26123",
    "sg:province":"Niedersachsen",
    "wof:name":"Uwe Borchers",
    "wof:placetype":"venue"
},
  "geometry": {"coordinates":[8.21817,53.152313],"type":"Point"}
}