{
  "type": "Feature",
  "properties": {
    "iso:country":"DE",
    "sg:address":"Birkenweg 9",
    "sg:city":"L\u00f6ningen",
    "sg:phone":"+49 5432/2117",
    "sg:postcode":"49624",
    "sg:province":"Niedersachsen",
    "wof:name":"Heinrich Siefert",
    "wof:placetype":"venue"
},
  "geometry": {"coordinates":[7.751529,52.734634],"type":"Point"}
}