{
  "type": "Feature",
  "properties": {
    "iso:country":"DE",
    "sg:address":"Johannisthaler Chaussee 297",
    "sg:city":"Berlin",
    "sg:phone":"+49 30/6032033",
    "sg:postcode":"12351",
    "sg:province":"Berlin",
    "wof:name":"Arche Noah Inh. M\u00fcller & Co.",
    "wof:placetype":"venue"
},
  "geometry": {"coordinates":[13.456722,52.430485],"type":"Point"}
}