{
  "type": "Feature",
  "properties": {
    "iso:country":"DE",
    "sg:address":"Au\u00dferhalb 7",
    "sg:city":"Vendersheim",
    "sg:phone":"+49 6732/1631",
    "sg:postcode":"55578",
    "sg:province":"Rheinland-Pfalz",
    "wof:name":"Arno U. Elisabeth Kronenberger",
    "wof:placetype":"venue"
},
  "geometry": {"coordinates":[8.0663032532,49.8625221252],"type":"Point"}
}