{
  "type": "Feature",
  "properties": {
    "iso:country":"DE",
    "sg:address":"Mittelstr. 8",
    "sg:city":"H\u00f6hr-Grenzhausen",
    "sg:phone":"+49 2624/7791",
    "sg:postcode":"56203",
    "sg:province":"Rheinland-Pfalz",
    "wof:name":"Paul Freisberg",
    "wof:placetype":"venue"
},
  "geometry": {"coordinates":[7.6727747917,50.4328079224],"type":"Point"}
}