{
  "type": "Feature",
  "properties": {
    "iso:country":"DE",
    "sg:address":"Curtiusstr. 27",
    "sg:city":"Erkrath",
    "sg:phone":"+49 2104/44424",
    "sg:postcode":"40699",
    "sg:province":"Nordrhein-Westfalen",
    "wof:name":"Peter Printz Steuerberater",
    "wof:placetype":"venue"
},
  "geometry": {"coordinates":[6.9555997849,51.2132034302],"type":"Point"}
}