{
  "type": "Feature",
  "properties": {
    "iso:country":"DE",
    "sg:address":"Ichtersh\u00e4user Str. 07",
    "sg:city":"Arnstadt",
    "sg:postcode":"99310",
    "sg:province":"Th\u00fcringen",
    "wof:name":"Rba Regionalbus Arnstadt Gmbh",
    "wof:placetype":"venue"
},
  "geometry": {"coordinates":[10.9514398575,50.8431015015],"type":"Point"}
}