{
  "type": "Feature",
  "properties": {
    "iso:country":"DE",
    "sg:address":"Westheider Weg 3",
    "sg:city":"Versmold",
    "sg:phone":"+49 5423/8685",
    "sg:postcode":"33775",
    "sg:province":"Nordrhein-Westfalen",
    "wof:name":"Klaus Bulla",
    "wof:placetype":"venue"
},
  "geometry": {"coordinates":[8.142469,52.039661],"type":"Point"}
}