{
  "type": "Feature",
  "properties": {
    "iso:country":"DE",
    "sg:address":"Sonnenstr. 6",
    "sg:city":"Miesbach",
    "sg:phone":"+49 8025/1245",
    "sg:postcode":"83714",
    "sg:province":"Bayern",
    "wof:name":"Gabi Und Erich Wei\u00dfenbacher",
    "wof:placetype":"venue"
},
  "geometry": {"coordinates":[11.8309803009,47.7944145203],"type":"Point"}
}