{
  "type": "Feature",
  "properties": {
    "iso:country":"DE",
    "sg:address":"Hannoversche Str. 102",
    "sg:city":"Niestetal",
    "sg:phone":"+49 561/523521",
    "sg:postcode":"34266",
    "sg:province":"Hessen",
    "wof:name":"Eiscafe Sardegna",
    "wof:placetype":"venue"
},
  "geometry": {"coordinates":[9.549224,51.322338],"type":"Point"}
}