{
  "type": "Feature",
  "properties": {
    "iso:country":"DE",
    "sg:address":"Engelsberg 1",
    "sg:city":"Bretten",
    "sg:phone":"+49 7252/78827",
    "sg:postcode":"75015",
    "sg:province":"Baden-W\u00fcrttemberg",
    "wof:name":"Le Bistro",
    "wof:placetype":"venue"
},
  "geometry": {"coordinates":[8.70557,49.037464],"type":"Point"}
}