{
  "type": "Feature",
  "properties": {
    "iso:country":"DE",
    "sg:address":"Marburger Str. 251",
    "sg:city":"Gie\u00dfen",
    "sg:phone":"+49 641/9520599",
    "sg:postcode":"35396",
    "sg:province":"Hessen",
    "wof:name":"Peppler Gmbh & Co Kg",
    "wof:placetype":"venue"
},
  "geometry": {"coordinates":[8.6973876953,50.6073379517],"type":"Point"}
}