{
  "type": "Feature",
  "properties": {
    "iso:country":"DE",
    "sg:address":"Liebschwitzer Str. 110",
    "sg:city":"Gera",
    "sg:phone":"+49 365/7100637",
    "sg:postcode":"07551",
    "sg:province":"Th\u00fcringen",
    "wof:name":"F. B\u00f6ttcher",
    "wof:placetype":"venue"
},
  "geometry": {"coordinates":[12.085597,50.846691],"type":"Point"}
}