{
  "type": "Feature",
  "properties": {
    "iso:country":"DE",
    "sg:address":"Neugasse 18",
    "sg:city":"Wiesbaden",
    "sg:phone":"+49 611/373664",
    "sg:postcode":"65183",
    "sg:province":"Hessen",
    "wof:name":"Kreys Couture F\u00fcr Kinder",
    "wof:placetype":"venue"
},
  "geometry": {"coordinates":[8.2396631241,50.0819587708],"type":"Point"}
}