{
  "type": "Feature",
  "properties": {
    "iso:country":"DE",
    "sg:address":"Voerder Str. 88",
    "sg:city":"Ennepetal",
    "sg:phone":"+49 2333/81045",
    "sg:postcode":"58256",
    "sg:province":"Nordrhein-Westfalen",
    "wof:name":"Avantgarde Hair Studio Gmbh",
    "wof:placetype":"venue"
},
  "geometry": {"coordinates":[7.3526921272,51.2978210449],"type":"Point"}
}