{
  "type": "Feature",
  "properties": {
    "iso:country":"DE",
    "sg:address":"Pommergasse 1",
    "sg:city":"W\u00fcrzburg",
    "sg:phone":"+49 931/16711",
    "sg:postcode":"97070",
    "sg:province":"Bayern",
    "wof:name":"Ellen Seibel Ergotherapie",
    "wof:placetype":"venue"
},
  "geometry": {"coordinates":[9.927621,49.795208],"type":"Point"}
}