{
  "type": "Feature",
  "properties": {
    "iso:country":"DE",
    "sg:address":"Wallstr. 10",
    "sg:city":"Wesel",
    "sg:phone":"+49 281/338450",
    "sg:postcode":"46483",
    "sg:province":"Nordrhein-Westfalen",
    "wof:name":"Krahwinkel Und Oenning Rechtsanw\u00e4lte Und Notare",
    "wof:placetype":"venue"
},
  "geometry": {"coordinates":[6.6210489273,51.6565856934],"type":"Point"}
}