{
  "type": "Feature",
  "properties": {
    "iso:country":"DE",
    "sg:address":"Kirchstr. 6",
    "sg:city":"Polch",
    "sg:phone":"+49 2654/2451",
    "sg:postcode":"56751",
    "sg:province":"Rheinland-Pfalz",
    "wof:name":"Heinz M\u00fcller",
    "wof:placetype":"venue"
},
  "geometry": {"coordinates":[7.3128910065,50.2993621826],"type":"Point"}
}