{
  "type": "Feature",
  "properties": {
    "iso:country":"DE",
    "sg:address":"Am Spring 19",
    "sg:city":"Tostedt",
    "sg:phone":"+49 4182/6439",
    "sg:postcode":"21255",
    "sg:province":"Niedersachsen",
    "wof:name":"Walter Genzer",
    "wof:placetype":"venue"
},
  "geometry": {"coordinates":[9.68746,53.27877],"type":"Point"}
}