{
  "type": "Feature",
  "properties": {
    "iso:country":"DE",
    "sg:address":"Gelderstr. 15",
    "sg:city":"Rheinberg",
    "sg:phone":"+49 2843/2435",
    "sg:postcode":"47495",
    "sg:province":"Nordrhein-Westfalen",
    "wof:name":"H. F\u00fchrmann",
    "wof:placetype":"venue"
},
  "geometry": {"coordinates":[6.601443,51.544716],"type":"Point"}
}