{
  "type": "Feature",
  "properties": {
    "iso:country":"DE",
    "sg:address":"Milchstr. 32",
    "sg:city":"Oldenburg",
    "sg:phone":"+49 441/86042",
    "sg:postcode":"26123",
    "sg:province":"Niedersachsen",
    "wof:name":"Mohammed Ghezelayagh",
    "wof:placetype":"venue"
},
  "geometry": {"coordinates":[8.2173585892,53.1482467651],"type":"Point"}
}