{
  "type": "Feature",
  "properties": {
    "iso:country":"DE",
    "sg:address":"Molpertshaus",
    "sg:city":"Wolfegg",
    "sg:phone":"+49 7527/4285",
    "sg:postcode":"88364",
    "sg:province":"Baden-W\u00fcrttemberg",
    "wof:name":"Gasthof Adler",
    "wof:placetype":"venue"
},
  "geometry": {"coordinates":[9.806810379,47.8705787659],"type":"Point"}
}