{
  "type": "Feature",
  "properties": {
    "iso:country":"DE",
    "sg:address":"Hermann-L\u00f6ns-Weg 17 d",
    "sg:city":"Seevetal",
    "sg:phone":"+49 4105/84588",
    "sg:postcode":"21220",
    "sg:province":"Niedersachsen",
    "wof:name":"Jaskulski",
    "wof:placetype":"venue"
},
  "geometry": {"coordinates":[10.025219,53.375263],"type":"Point"}
}