{
  "type": "Feature",
  "properties": {
    "iso:country":"DE",
    "sg:address":"Rosenthaler Str. 31",
    "sg:city":"Duderstadt",
    "sg:phone":"+49 5527/9150",
    "sg:postcode":"37115",
    "sg:province":"Niedersachsen",
    "wof:name":"Rosenthaler Hof Hotel Restaurant U.",
    "wof:placetype":"venue"
},
  "geometry": {"coordinates":[10.2093248367,51.5146789551],"type":"Point"}
}