{
  "type": "Feature",
  "properties": {
    "iso:country":"DE",
    "sg:address":"L\u00f6bauer Str. 75",
    "sg:city":"Bautzen",
    "sg:phone":"+49 3591/2780",
    "sg:postcode":"02625",
    "sg:province":"Sachsen",
    "wof:name":"Dekra Ag",
    "wof:placetype":"venue"
},
  "geometry": {"coordinates":[14.4538955688,51.1783409119],"type":"Point"}
}