{
  "type": "Feature",
  "properties": {
    "iso:country":"DE",
    "sg:address":"Gutenbergstr. 9",
    "sg:city":"Schwegenheim",
    "sg:phone":"+49 6344/938838",
    "sg:postcode":"67365",
    "sg:province":"Rheinland-Pfalz",
    "wof:name":"Skytube Natural Lighting Systems Gmbh",
    "wof:placetype":"venue"
},
  "geometry": {"coordinates":[8.328422,49.273956],"type":"Point"}
}