{
  "type": "Feature",
  "properties": {
    "iso:country":"DE",
    "sg:address":"Hamsterweg 2",
    "sg:city":"Daun",
    "sg:phone":"+49 6592/96700",
    "sg:postcode":"54550",
    "sg:province":"Rheinland-Pfalz",
    "wof:name":"Hubert Binder Gmbh",
    "wof:placetype":"venue"
},
  "geometry": {"coordinates":[6.80592,50.191631],"type":"Point"}
}