{
  "type": "Feature",
  "properties": {
    "iso:country":"DE",
    "sg:address":"Hans-B\u00f6ckler-Str. 170a",
    "sg:city":"H\u00fcrth",
    "sg:phone":"+49 2233/75261",
    "sg:postcode":"50354",
    "sg:province":"Nordrhein-Westfalen",
    "wof:name":"Kath. Pfarramt St. Ursula",
    "wof:placetype":"venue"
},
  "geometry": {"coordinates":[6.9071960449,50.8773498535],"type":"Point"}
}