{
  "type": "Feature",
  "properties": {
    "iso:country":"DE",
    "sg:address":"53757",
    "sg:city":"Sankt Augustin",
    "sg:phone":"+49 2241/205691",
    "sg:postcode":"53757",
    "sg:province":"Nordrhein-Westfalen",
    "wof:name":"Bistro",
    "wof:placetype":"venue"
},
  "geometry": {"coordinates":[7.1857199669,50.7699584961],"type":"Point"}
}