{
  "type": "Feature",
  "properties": {
    "iso:country":"DE",
    "sg:address":"Goebenstr. 72",
    "sg:city":"Herford",
    "sg:phone":"+49 5221/56315",
    "sg:postcode":"32051",
    "sg:province":"Nordrhein-Westfalen",
    "wof:name":"Nermin G\u00fcng\u00f6r Gmbh",
    "wof:placetype":"venue"
},
  "geometry": {"coordinates":[8.669405,52.127888],"type":"Point"}
}