{
  "type": "Feature",
  "properties": {
    "iso:country":"DE",
    "sg:address":"Bertha-von-Suttner-Platz 1",
    "sg:city":"Hannover",
    "sg:phone":"+49 511/801700",
    "sg:postcode":"30173",
    "sg:province":"Niedersachsen",
    "wof:name":"Ameling Und Eicke",
    "wof:placetype":"venue"
},
  "geometry": {"coordinates":[9.7587509155,52.3591995239],"type":"Point"}
}