{
  "type": "Feature",
  "properties": {
    "iso:country":"DE",
    "sg:address":"Hohe Str. 44",
    "sg:city":"Datteln",
    "sg:phone":"+49 2363/8427",
    "sg:postcode":"45711",
    "sg:province":"Nordrhein-Westfalen",
    "wof:name":"Oase",
    "wof:placetype":"venue"
},
  "geometry": {"coordinates":[7.3393950462,51.6530342102],"type":"Point"}
}