{
  "type": "Feature",
  "properties": {
    "iso:country":"DE",
    "sg:address":"M\u00e4rkische Allee 45",
    "sg:city":"Gro\u00dfbeeren",
    "sg:postcode":"14979",
    "sg:province":"Brandenburg",
    "wof:name":"Pietsch Gmbh",
    "wof:placetype":"venue"
},
  "geometry": {"coordinates":[13.2967338562,52.369354248],"type":"Point"}
}