{
  "type": "Feature",
  "properties": {
    "iso:country":"DE",
    "sg:address":"Nordwestring 131",
    "sg:city":"N\u00fcrnberg",
    "sg:phone":"+49 911/3849123",
    "sg:postcode":"90419",
    "sg:province":"Bayern",
    "wof:name":"Institut F. Telekommunikatiion",
    "wof:placetype":"venue"
},
  "geometry": {"coordinates":[11.0569028854,49.4667663574],"type":"Point"}
}