{
  "type": "Feature",
  "properties": {
    "iso:country":"DE",
    "sg:address":"Davenstedter Str. 203",
    "sg:city":"Hannover",
    "sg:phone":"+49 511/949760",
    "sg:postcode":"30455",
    "sg:province":"Niedersachsen",
    "wof:name":"Gardinenhaus Spengler",
    "wof:placetype":"venue"
},
  "geometry": {"coordinates":[9.673374176,52.3651351929],"type":"Point"}
}