{
  "type": "Feature",
  "properties": {
    "iso:country":"DE",
    "sg:address":"Kurt-Schumacher-Str. 7",
    "sg:city":"Braunschweig",
    "sg:phone":"+49 531/794292",
    "sg:postcode":"38102",
    "sg:province":"Niedersachsen",
    "wof:name":"Dr. I. Emami-namini Ingenieur",
    "wof:placetype":"venue"
},
  "geometry": {"coordinates":[10.5363235474,52.2544441223],"type":"Point"}
}