{
  "type": "Feature",
  "properties": {
    "iso:country":"DE",
    "sg:address":"Obere Au 1",
    "sg:city":"Obrigheim",
    "sg:phone":"+49 6261/6370",
    "sg:postcode":"74847",
    "sg:province":"Baden-W\u00fcrttemberg",
    "wof:name":"Metzger-druck Gmbh",
    "wof:placetype":"venue"
},
  "geometry": {"coordinates":[9.09734,49.348011],"type":"Point"}
}