{
  "type": "Feature",
  "properties": {
    "iso:country":"DE",
    "sg:address":"Hanfl\u00e4nder 11",
    "sg:city":"Hattenhofen",
    "sg:phone":"+49 7164/6858",
    "sg:postcode":"73110",
    "sg:province":"Baden-W\u00fcrttemberg",
    "wof:name":"Arwin Bayer",
    "wof:placetype":"venue"
},
  "geometry": {"coordinates":[9.5749864578,48.6646308899],"type":"Point"}
}