{
  "type": "Feature",
  "properties": {
    "iso:country":"DE",
    "sg:address":"Taubenmarkt 11",
    "sg:city":"Traunstein",
    "sg:phone":"+49 861/15841",
    "sg:postcode":"83278",
    "sg:province":"Bayern",
    "wof:name":"Dr. Med. Wolfgang Weilacher Arzt F\u00fcr Allgemeinmedizin",
    "wof:placetype":"venue"
},
  "geometry": {"coordinates":[12.6481170654,47.8703155518],"type":"Point"}
}