{
  "type": "Feature",
  "properties": {
    "iso:country":"DE",
    "sg:address":"Planckstr. 60",
    "sg:city":"Stuttgart",
    "sg:phone":"+49 711/242331",
    "sg:postcode":"70184",
    "sg:province":"Baden-W\u00fcrttemberg",
    "wof:name":"W. Beck-erlang Architekt",
    "wof:placetype":"venue"
},
  "geometry": {"coordinates":[9.198653,48.773548],"type":"Point"}
}