{
  "type": "Feature",
  "properties": {
    "iso:country":"DE",
    "sg:address":"Pescher Str. 20",
    "sg:city":"Erkelenz",
    "sg:phone":"+49 2164/48211",
    "sg:postcode":"41812",
    "sg:province":"Nordrhein-Westfalen",
    "wof:name":"Hilar Goebels",
    "wof:placetype":"venue"
},
  "geometry": {"coordinates":[6.440959,51.051434],"type":"Point"}
}