{
  "type": "Feature",
  "properties": {
    "iso:country":"DE",
    "sg:address":"Nagolder Str. 12",
    "sg:city":"Horb",
    "sg:phone":"+49 7486/95288",
    "sg:postcode":"72160",
    "sg:province":"Baden-W\u00fcrttemberg",
    "wof:name":"Kaiser",
    "wof:placetype":"venue"
},
  "geometry": {"coordinates":[8.6601638794,48.4859428406],"type":"Point"}
}