{
  "type": "Feature",
  "properties": {
    "iso:country":"DE",
    "sg:address":"Waldesruh 86",
    "sg:city":"Schalksm\u00fchle",
    "sg:phone":"+49 2355/1213",
    "sg:postcode":"58579",
    "sg:province":"Nordrhein-Westfalen",
    "wof:name":"Heinrich Tent Architekt",
    "wof:placetype":"venue"
},
  "geometry": {"coordinates":[7.550788,51.248249],"type":"Point"}
}