{
  "type": "Feature",
  "properties": {
    "iso:country":"DE",
    "sg:address":"M\u00fchlwiesen 2",
    "sg:city":"Unlingen",
    "sg:phone":"+49 7371/923493",
    "sg:postcode":"88527",
    "sg:province":"Baden-W\u00fcrttemberg",
    "wof:name":"Karl Selig",
    "wof:placetype":"venue"
},
  "geometry": {"coordinates":[9.522663,48.16291],"type":"Point"}
}