{
  "type": "Feature",
  "properties": {
    "iso:country":"DE",
    "sg:address":"Ladenbeker Furtweg 182",
    "sg:city":"Hamburg",
    "sg:phone":"+49 40/7383188",
    "sg:postcode":"21033",
    "sg:province":"Hamburg",
    "wof:name":"Beratungsstelle F. Aussiedler",
    "wof:placetype":"venue"
},
  "geometry": {"coordinates":[10.18204,53.492245],"type":"Point"}
}