{
  "type": "Feature",
  "properties": {
    "iso:country":"DE",
    "sg:address":"An der Kirche 6",
    "sg:city":"Bad K\u00f6stritz",
    "sg:phone":"+49 36605/2354",
    "sg:postcode":"07586",
    "sg:province":"Th\u00fcringen",
    "wof:name":"F. Kirchgeorg",
    "wof:placetype":"venue"
},
  "geometry": {"coordinates":[12.010736,50.928429],"type":"Point"}
}