{
  "type": "Feature",
  "properties": {
    "iso:country":"DE",
    "sg:address":"Hauptstr. 63",
    "sg:city":"Winden",
    "sg:phone":"+49 6349/8599",
    "sg:postcode":"76872",
    "sg:province":"Rheinland-Pfalz",
    "wof:name":"Kurt Heintz",
    "wof:placetype":"venue"
},
  "geometry": {"coordinates":[8.1158246994,49.0988845825],"type":"Point"}
}