{
  "type": "Feature",
  "properties": {
    "iso:country":"DE",
    "sg:address":"Eversbuschstr. 92",
    "sg:city":"M\u00fcnchen",
    "sg:phone":"+49 89/8122159",
    "sg:postcode":"80999",
    "sg:province":"Bayern",
    "wof:name":"Eversbusch Apotheke Alexandra Nemeth",
    "wof:placetype":"venue"
},
  "geometry": {"coordinates":[11.460928,48.188179],"type":"Point"}
}