{
  "type": "Feature",
  "properties": {
    "iso:country":"DE",
    "sg:address":"Niederb\u00f6hmersdorf",
    "sg:city":"Niederb\u00f6hmersdorf",
    "sg:phone":"+49 36622/854",
    "sg:postcode":"07950",
    "sg:province":"Th\u00fcringen",
    "wof:name":"Weidatal Agrar Gmbh",
    "wof:placetype":"venue"
},
  "geometry": {"coordinates":[12.025321,50.666256],"type":"Point"}
}