{
  "type": "Feature",
  "properties": {
    "iso:country":"DE",
    "sg:address":"Heidenberg 49",
    "sg:city":"Apolda",
    "sg:phone":"+49 3644/562683",
    "sg:postcode":"99510",
    "sg:province":"Th\u00fcringen",
    "wof:name":"Wolfgang Jacob",
    "wof:placetype":"venue"
},
  "geometry": {"coordinates":[11.5103063583,51.0251960754],"type":"Point"}
}