{
  "type": "Feature",
  "properties": {
    "iso:country":"DE",
    "sg:address":"Kirchstr. 34",
    "sg:city":"Alsdorf",
    "sg:phone":"+49 2404/61860",
    "sg:postcode":"52477",
    "sg:province":"Nordrhein-Westfalen",
    "wof:name":"L. Libber",
    "wof:placetype":"venue"
},
  "geometry": {"coordinates":[6.2123718262,50.8708229065],"type":"Point"}
}