{
  "type": "Feature",
  "properties": {
    "iso:country":"DE",
    "sg:address":"Wildunger Str. 18",
    "sg:city":"Edertal",
    "sg:phone":"+49 4952/033001",
    "sg:postcode":"34549",
    "sg:province":"Hessen",
    "wof:name":"Werther Ladenausbau Gmbh",
    "wof:placetype":"venue"
},
  "geometry": {"coordinates":[8.403088,52.105614],"type":"Point"}
}