{
  "type": "Feature",
  "properties": {
    "iso:country":"DE",
    "sg:address":"Keplerstr. 10",
    "sg:city":"Bad Mergentheim",
    "sg:phone":"+49 7931/42470",
    "sg:postcode":"97980",
    "sg:province":"Baden-W\u00fcrttemberg",
    "wof:name":"F. Hornung Und E. Ott-hornung",
    "wof:placetype":"venue"
},
  "geometry": {"coordinates":[9.7829399109,49.4891929626],"type":"Point"}
}