{
  "type": "Feature",
  "properties": {
    "iso:country":"DE",
    "sg:address":"Zum Schieferberg 17",
    "sg:city":"Olsberg",
    "sg:phone":"+49 2962/4854",
    "sg:postcode":"59939",
    "sg:province":"Nordrhein-Westfalen",
    "wof:name":"Andreas Sch\u00fctte",
    "wof:placetype":"venue"
},
  "geometry": {"coordinates":[8.463327,51.373245],"type":"Point"}
}