{
  "type": "Feature",
  "properties": {
    "iso:country":"DE",
    "sg:address":"Egerlandstr. 50",
    "sg:city":"Geretsried",
    "sg:phone":"+49 8171/62021",
    "sg:postcode":"82538",
    "sg:province":"Bayern",
    "wof:name":"Manfred L. Fuchs Rechtsanwalt",
    "wof:placetype":"venue"
},
  "geometry": {"coordinates":[11.4683408737,47.8747138977],"type":"Point"}
}