{
  "type": "Feature",
  "properties": {
    "iso:country":"DE",
    "sg:address":"Rh\u00f6nstr. 15",
    "sg:city":"Wiesbaden",
    "sg:phone":"+49 611/810499",
    "sg:postcode":"65187",
    "sg:province":"Hessen",
    "wof:name":"Ulrich Seebach Heilpraktiker",
    "wof:placetype":"venue"
},
  "geometry": {"coordinates":[8.2454004288,50.0593681335],"type":"Point"}
}