{
  "type": "Feature",
  "properties": {
    "iso:country":"DE",
    "sg:address":"Spartastr. 41",
    "sg:city":"Erkelenz",
    "sg:phone":"+49 2432/979080",
    "sg:postcode":"41812",
    "sg:province":"Nordrhein-Westfalen",
    "wof:name":"Scheffel Gmbh & Co. Kg",
    "wof:placetype":"venue"
},
  "geometry": {"coordinates":[6.2091398239,51.0971069336],"type":"Point"}
}