{
  "type": "Feature",
  "properties": {
    "iso:country":"DE",
    "sg:address":"Pater - Delp - Stra\u00dfe 5",
    "sg:city":"Fellbach",
    "sg:phone":"+49 711",
    "sg:postcode":"70736",
    "sg:province":"Baden-W\u00fcrttemberg",
    "wof:name":"Internetpr\u00e4senz",
    "wof:placetype":"venue"
},
  "geometry": {"coordinates":[9.266409,48.843719],"type":"Point"}
}