{
  "type": "Feature",
  "properties": {
    "iso:country":"DE",
    "sg:address":"Vorderh\u00fcgel 11",
    "sg:city":"Zella-Mehlis",
    "sg:phone":"+49 3682/487291",
    "sg:postcode":"98544",
    "sg:province":"Th\u00fcringen",
    "wof:name":"M. Kaiser Immobilienmakler",
    "wof:placetype":"venue"
},
  "geometry": {"coordinates":[10.6707391739,50.6517906189],"type":"Point"}
}