{
  "type": "Feature",
  "properties": {
    "iso:country":"DE",
    "sg:address":"Chiemgaustr. 33",
    "sg:city":"Evenhausen",
    "sg:phone":"+49 8075/600",
    "sg:postcode":"83552",
    "sg:province":"Bayern",
    "wof:name":"Alois L\u00f6w",
    "wof:placetype":"venue"
},
  "geometry": {"coordinates":[12.288636,48.025307],"type":"Point"}
}