{
  "type": "Feature",
  "properties": {
    "iso:country":"DE",
    "sg:address":"Dahlorter Weg 6",
    "sg:city":"Nortrup",
    "sg:phone":"+49 5436/1845",
    "sg:postcode":"49638",
    "sg:province":"Niedersachsen",
    "wof:name":"Georg Schwertmann",
    "wof:placetype":"venue"
},
  "geometry": {"coordinates":[7.885442,52.626682],"type":"Point"}
}