{
  "type": "Feature",
  "properties": {
    "iso:country":"DE",
    "sg:address":"Neuruppiner Str. 107",
    "sg:city":"Berlin",
    "sg:phone":"+49 30/8017359",
    "sg:postcode":"14165",
    "sg:province":"Berlin",
    "wof:name":"Hans Melcher Ingenieur",
    "wof:placetype":"venue"
},
  "geometry": {"coordinates":[13.2371721268,52.4209480286],"type":"Point"}
}