{
  "type": "Feature",
  "properties": {
    "iso:country":"DE",
    "sg:address":"Hermann-Hesse-Str. 9",
    "sg:city":"Marbach",
    "sg:postcode":"71672",
    "sg:province":"Baden-W\u00fcrttemberg",
    "wof:name":"Erik Von Woedtke Ingenieur",
    "wof:placetype":"venue"
},
  "geometry": {"coordinates":[9.263494,48.940357],"type":"Point"}
}