{
  "type": "Feature",
  "properties": {
    "iso:country":"DE",
    "sg:address":"Glattalstr. 37",
    "sg:city":"Sulz",
    "sg:phone":"+49 7454/3644",
    "sg:postcode":"72172",
    "sg:province":"Baden-W\u00fcrttemberg",
    "wof:name":"E. Ziegler-mutschler",
    "wof:placetype":"venue"
},
  "geometry": {"coordinates":[8.5780715942,48.371963501],"type":"Point"}
}