{
  "type": "Feature",
  "properties": {
    "iso:country":"DE",
    "sg:address":"Auf dem Pickert 50",
    "sg:city":"Duisburg",
    "sg:phone":"+49 2065/81005",
    "sg:postcode":"47228",
    "sg:province":"Nordrhein-Westfalen",
    "wof:name":"Rainer Schmetzer",
    "wof:placetype":"venue"
},
  "geometry": {"coordinates":[6.667715,51.419773],"type":"Point"}
}