{
  "type": "Feature",
  "properties": {
    "iso:country":"DE",
    "sg:address":"Braunser Weg 12",
    "sg:city":"Bad Arolsen",
    "sg:postcode":"34454",
    "sg:province":"Hessen",
    "wof:name":"Vitalicum Gmbh",
    "wof:placetype":"venue"
},
  "geometry": {"coordinates":[9.023838,51.375683],"type":"Point"}
}