{
  "type": "Feature",
  "properties": {
    "iso:country":"DE",
    "sg:address":"Rostocker Str. 24",
    "sg:city":"Neubrandenburg",
    "sg:phone":"+49 395/5823311",
    "sg:postcode":"17033",
    "sg:province":"Mecklenburg-Vorpommern",
    "wof:name":"Hans Wotin",
    "wof:placetype":"venue"
},
  "geometry": {"coordinates":[13.2480688095,53.5573310852],"type":"Point"}
}