{
  "type": "Feature",
  "properties": {
    "iso:country":"DE",
    "sg:address":"Heinigstr. 45",
    "sg:city":"Ludwigshafen",
    "sg:phone":"+49 621/513750",
    "sg:postcode":"67059",
    "sg:province":"Rheinland-Pfalz",
    "wof:name":"Philharmonie",
    "wof:placetype":"venue"
},
  "geometry": {"coordinates":[8.4417142868,49.4798660278],"type":"Point"}
}