{
  "type": "Feature",
  "properties": {
    "iso:country":"DE",
    "sg:address":"Bahnhofstr. 29-30",
    "sg:city":"Erfurt",
    "sg:phone":"+49 361/6422433",
    "sg:postcode":"99084",
    "sg:province":"Th\u00fcringen",
    "wof:name":"Schnapp-markt Inh. Karin Homberger",
    "wof:placetype":"venue"
},
  "geometry": {"coordinates":[11.036194,50.973385],"type":"Point"}
}