{
  "type": "Feature",
  "properties": {
    "iso:country":"DE",
    "sg:address":"Markt 10",
    "sg:city":"Remscheid",
    "sg:phone":"+49 2191/291545",
    "sg:postcode":"42853",
    "sg:province":"Nordrhein-Westfalen",
    "wof:name":"Atelier Im Union",
    "wof:placetype":"venue"
},
  "geometry": {"coordinates":[7.1943030357,51.1789932251],"type":"Point"}
}