{
  "type": "Feature",
  "properties": {
    "iso:country":"DE",
    "sg:address":"Schwickersh\u00e4user Str. 89",
    "sg:city":"Nordheim",
    "sg:phone":"+49 36944/50350",
    "sg:postcode":"98631",
    "sg:province":"Th\u00fcringen",
    "wof:name":"H. Jentsch",
    "wof:placetype":"venue"
},
  "geometry": {"coordinates":[10.403594017,50.4543037415],"type":"Point"}
}