{
  "type": "Feature",
  "properties": {
    "iso:country":"DE",
    "sg:address":"B\u00fcrgerm.-Klages-Platz 16",
    "sg:city":"Wennigsen",
    "sg:phone":"+49 5103/2033",
    "sg:postcode":"30974",
    "sg:province":"Niedersachsen",
    "wof:name":"Gemeindeb\u00fccherei",
    "wof:placetype":"venue"
},
  "geometry": {"coordinates":[9.573535,52.27335],"type":"Point"}
}