{
  "type": "Feature",
  "properties": {
    "iso:country":"DE",
    "sg:address":"Tillystr 18-19",
    "sg:city":"Ingolstadt",
    "sg:phone":"+49 841/97440",
    "sg:postcode":"85051",
    "sg:province":"Bayern",
    "wof:name":"W&w Verwaltungs Gmbh",
    "wof:placetype":"venue"
},
  "geometry": {"coordinates":[11.4333848953,48.7445030212],"type":"Point"}
}