{
  "type": "Feature",
  "properties": {
    "iso:country":"DE",
    "sg:address":"Frankfurter Str. 2",
    "sg:city":"Waldems",
    "sg:phone":"+49 6126/581648",
    "sg:postcode":"65529",
    "sg:province":"Hessen",
    "wof:name":"Bistro Pinocchio",
    "wof:placetype":"venue"
},
  "geometry": {"coordinates":[8.3234424591,50.2492408752],"type":"Point"}
}