{
  "type": "Feature",
  "properties": {
    "iso:country":"DE",
    "sg:address":"Berliner Allee 21",
    "sg:city":"Illertissen",
    "sg:phone":"+49 7303/42412",
    "sg:postcode":"89257",
    "sg:province":"Bayern",
    "wof:name":"Tmc Gmbh",
    "wof:placetype":"venue"
},
  "geometry": {"coordinates":[10.094396,48.218929],"type":"Point"}
}