{
  "type": "Feature",
  "properties": {
    "iso:country":"DE",
    "sg:address":"Gau\u00dfstr. 15",
    "sg:city":"Hamburg",
    "sg:phone":"+49 40/3905138",
    "sg:postcode":"22765",
    "sg:province":"Hamburg",
    "wof:name":"Jochen Henkels",
    "wof:placetype":"venue"
},
  "geometry": {"coordinates":[9.933113,53.555695],"type":"Point"}
}