{
  "type": "Feature",
  "properties": {
    "iso:country":"DE",
    "sg:address":"Jungwaldstr. 5",
    "sg:city":"Quierschied",
    "sg:phone":"+49 6897/65999",
    "sg:postcode":"66287",
    "sg:province":"Saarland",
    "wof:name":"Bierdepot Willi Hoffmann Gmbh",
    "wof:placetype":"venue"
},
  "geometry": {"coordinates":[7.0578899384,49.3295860291],"type":"Point"}
}