{
  "type": "Feature",
  "properties": {
    "iso:country":"DE",
    "sg:address":"Nadorster Str. 125",
    "sg:city":"Oldenburg",
    "sg:postcode":"26123",
    "sg:province":"Niedersachsen",
    "wof:name":"Raiffeisen-immobilien",
    "wof:placetype":"venue"
},
  "geometry": {"coordinates":[8.2198457718,53.1554222107],"type":"Point"}
}