{
  "type": "Feature",
  "properties": {
    "iso:country":"DE",
    "sg:address":"Lindenstr. 19",
    "sg:city":"Falkenberg",
    "sg:phone":"+49 35365/36606",
    "sg:postcode":"04895",
    "sg:province":"Brandenburg",
    "wof:name":"B. Richter",
    "wof:placetype":"venue"
},
  "geometry": {"coordinates":[13.235794,51.589291],"type":"Point"}
}