{
  "type": "Feature",
  "properties": {
    "iso:country":"DE",
    "sg:address":"Rodenbecker Str. 44",
    "sg:city":"Minden",
    "sg:phone":"+49 571/20823",
    "sg:postcode":"32427",
    "sg:province":"Nordrhein-Westfalen",
    "wof:name":"Bernhard Engelke",
    "wof:placetype":"venue"
},
  "geometry": {"coordinates":[8.904443,52.285942],"type":"Point"}
}