{
  "type": "Feature",
  "properties": {
    "iso:country":"DE",
    "sg:address":"Hauptstr. 38",
    "sg:city":"Lo\u00dfburg",
    "sg:phone":"+49 7446/543",
    "sg:postcode":"72290",
    "sg:province":"Baden-W\u00fcrttemberg",
    "wof:name":"Georg Merz",
    "wof:placetype":"venue"
},
  "geometry": {"coordinates":[8.45084095,48.4133872986],"type":"Point"}
}