{
  "type": "Feature",
  "properties": {
    "iso:country":"DE",
    "sg:address":"Demminer Str. 78",
    "sg:city":"Neubrandenburg",
    "sg:phone":"+49 395/429570",
    "sg:postcode":"17034",
    "sg:province":"Mecklenburg-Vorpommern",
    "wof:name":"Mc Donalds",
    "wof:placetype":"venue"
},
  "geometry": {"coordinates":[13.2708730698,53.5855484009],"type":"Point"}
}