{
  "type": "Feature",
  "properties": {
    "iso:country":"DE",
    "sg:address":"Werdener Str 22",
    "sg:city":"Essen",
    "sg:phone":"+49 2054/940700",
    "sg:postcode":"45219",
    "sg:province":"Nordrhein-Westfalen",
    "wof:name":"Vogelbusch Gmbh",
    "wof:placetype":"venue"
},
  "geometry": {"coordinates":[6.933737,51.358452],"type":"Point"}
}