{
  "type": "Feature",
  "properties": {
    "iso:country":"DE",
    "sg:address":"Gaglower Str. 7",
    "sg:city":"Cottbus",
    "sg:phone":"+49 355/474741",
    "sg:postcode":"03048",
    "sg:province":"Brandenburg",
    "wof:name":"Erwin Piater",
    "wof:placetype":"venue"
},
  "geometry": {"coordinates":[14.29202,51.745022],"type":"Point"}
}