{
  "type": "Feature",
  "properties": {
    "iso:country":"DE",
    "sg:address":"Hastenbecker Weg 56",
    "sg:city":"Hameln",
    "sg:phone":"+49 5151/557910",
    "sg:postcode":"31785",
    "sg:province":"Niedersachsen",
    "wof:name":"Cox",
    "wof:placetype":"venue"
},
  "geometry": {"coordinates":[9.383826,52.102234],"type":"Point"}
}