{
  "type": "Feature",
  "properties": {
    "iso:country":"DE",
    "sg:address":"Elsedamm 18",
    "sg:city":"B\u00fcnde",
    "sg:phone":"+49 5223/10414",
    "sg:postcode":"32257",
    "sg:province":"Nordrhein-Westfalen",
    "wof:name":"M. Und T. K\u00e4mpfer Garten- Und Landschafts-",
    "wof:placetype":"venue"
},
  "geometry": {"coordinates":[8.577384,52.1968],"type":"Point"}
}