{
  "type": "Feature",
  "properties": {
    "iso:country":"DE",
    "sg:address":"Leipziger Str. 50",
    "sg:city":"Augsburg",
    "sg:phone":"+49 821/707074",
    "sg:postcode":"86169",
    "sg:province":"Bayern",
    "wof:name":"Wirthaus Am Lech Raila Gastst\u00e4tten Gmbh",
    "wof:placetype":"venue"
},
  "geometry": {"coordinates":[10.9047412872,48.3827476501],"type":"Point"}
}