{
  "type": "Feature",
  "properties": {
    "iso:country":"DE",
    "sg:address":"Irnicher Str. 61",
    "sg:city":"Z\u00fclpich",
    "sg:phone":"+49 2252/7412",
    "sg:postcode":"53909",
    "sg:province":"Nordrhein-Westfalen",
    "wof:name":"Hans-wilhelm Schmitz Zimmerei Gmbh",
    "wof:placetype":"venue"
},
  "geometry": {"coordinates":[6.6408348083,50.6424331665],"type":"Point"}
}