{
  "type": "Feature",
  "properties": {
    "iso:country":"DE",
    "sg:address":"M\u00fcnchberger Str. 36",
    "sg:city":"Sparneck",
    "sg:phone":"+49 9251/5164",
    "sg:postcode":"95234",
    "sg:province":"Bayern",
    "wof:name":"H. St\u00f6hr & S\u00f6hne",
    "wof:placetype":"venue"
},
  "geometry": {"coordinates":[11.837858,50.16246],"type":"Point"}
}