{
  "type": "Feature",
  "properties": {
    "iso:country":"DE",
    "sg:address":"Wittgasse 7",
    "sg:city":"Passau",
    "sg:phone":"+49 851/2643",
    "sg:postcode":"94032",
    "sg:province":"Bayern",
    "wof:name":"Gentleman",
    "wof:placetype":"venue"
},
  "geometry": {"coordinates":[13.4593715668,48.5752906799],"type":"Point"}
}