{
  "type": "Feature",
  "properties": {
    "iso:country":"DE",
    "sg:address":"Finkenstr. 37",
    "sg:city":"Bielefeld",
    "sg:phone":"+49 521/28896",
    "sg:postcode":"33609",
    "sg:province":"Nordrhein-Westfalen",
    "wof:name":"Carola Hartnick",
    "wof:placetype":"venue"
},
  "geometry": {"coordinates":[8.567057,52.032993],"type":"Point"}
}