{
  "type": "Feature",
  "properties": {
    "iso:country":"DE",
    "sg:address":"Alte Poststr. 4",
    "sg:city":"Stuttgart",
    "sg:phone":"+49 711/291210",
    "sg:postcode":"70173",
    "sg:province":"Baden-W\u00fcrttemberg",
    "wof:name":"Louis Lenz H\u00fcte",
    "wof:placetype":"venue"
},
  "geometry": {"coordinates":[9.1741437912,48.7748031616],"type":"Point"}
}