{
  "type": "Feature",
  "properties": {
    "iso:country":"DE",
    "sg:address":"L\u00e4nderweg 25-29",
    "sg:city":"Frankfurt",
    "sg:phone":"+49 69/612096",
    "sg:postcode":"60599",
    "sg:province":"Hessen",
    "wof:name":"Beba Plakat-werbung Gmbh",
    "wof:placetype":"venue"
},
  "geometry": {"coordinates":[8.701743,50.102566],"type":"Point"}
}