{
  "type": "Feature",
  "properties": {
    "iso:country":"DE",
    "sg:address":"R\u00f6merallee 1",
    "sg:city":"Z\u00fclpich",
    "sg:phone":"+49 2252/3800",
    "sg:postcode":"53909",
    "sg:province":"Nordrhein-Westfalen",
    "wof:name":"Extra",
    "wof:placetype":"venue"
},
  "geometry": {"coordinates":[6.6527600288,50.693901062],"type":"Point"}
}