{
  "type": "Feature",
  "properties": {
    "iso:country":"DE",
    "sg:address":"Am Seeufer 8",
    "sg:city":"Ransbach-Baumbach",
    "sg:phone":"+49 2623/4502",
    "sg:postcode":"56235",
    "sg:province":"Rheinland-Pfalz",
    "wof:name":"Horst Runkel",
    "wof:placetype":"venue"
},
  "geometry": {"coordinates":[7.7396960258,50.4614906311],"type":"Point"}
}