{
  "type": "Feature",
  "properties": {
    "iso:country":"DE",
    "sg:address":"92436",
    "sg:city":"Bruck",
    "sg:postcode":"92436",
    "sg:province":"Bayern",
    "wof:name":"Raiffeisenbank Bruck Eg",
    "wof:placetype":"venue"
},
  "geometry": {"coordinates":[12.29134,49.248569],"type":"Point"}
}