{
  "type": "Feature",
  "properties": {
    "iso:country":"DE",
    "sg:address":"Hildburgh\u00e4user Str. 16",
    "sg:city":"Eisfeld",
    "sg:phone":"+49 3686/300868",
    "sg:postcode":"98673",
    "sg:province":"Th\u00fcringen",
    "wof:name":"Zur Traube",
    "wof:placetype":"venue"
},
  "geometry": {"coordinates":[10.9015922546,50.4270324707],"type":"Point"}
}