{
  "type": "Feature",
  "properties": {
    "iso:country":"DE",
    "sg:address":"Cottastr. 45",
    "sg:city":"Stuttgart",
    "sg:phone":"+49 711/6404353",
    "sg:postcode":"70180",
    "sg:province":"Baden-W\u00fcrttemberg",
    "wof:name":"Valentin Wormbs",
    "wof:placetype":"venue"
},
  "geometry": {"coordinates":[9.1745529175,48.7663879395],"type":"Point"}
}