{
  "type": "Feature",
  "properties": {
    "iso:country":"DE",
    "sg:address":"Dr.-Gessler-Str. 31",
    "sg:city":"Regensburg",
    "sg:postcode":"93051",
    "sg:province":"Bayern",
    "wof:name":"Ostbayerische Service Gmbh",
    "wof:placetype":"venue"
},
  "geometry": {"coordinates":[12.0654811859,49.0044822693],"type":"Point"}
}