{
  "type": "Feature",
  "properties": {
    "iso:country":"DE",
    "sg:address":"Obere M\u00fcnsterstr. 11",
    "sg:city":"Castrop-Rauxel",
    "sg:phone":"+49 2305/31507",
    "sg:postcode":"44575",
    "sg:province":"Nordrhein-Westfalen",
    "wof:name":"L. Meier",
    "wof:placetype":"venue"
},
  "geometry": {"coordinates":[7.30979,51.55183],"type":"Point"}
}