{
  "type": "Feature",
  "properties": {
    "iso:country":"DE",
    "sg:address":"Postfach",
    "sg:city":"Frankfurt",
    "sg:postcode":"60591",
    "sg:province":"Brandenburg",
    "wof:name":"Menniger Br\u00e4u",
    "wof:placetype":"venue"
},
  "geometry": {"coordinates":[8.6843,50.112251],"type":"Point"}
}