{
  "type": "Feature",
  "properties": {
    "iso:country":"DE",
    "sg:address":"Waldstr. 36",
    "sg:city":"Erlangen",
    "sg:phone":"+49 9131/25035",
    "sg:postcode":"91054",
    "sg:province":"Bayern",
    "wof:name":"Frenzel Mineral\u00f6le Kg",
    "wof:placetype":"venue"
},
  "geometry": {"coordinates":[11.014166,49.594563],"type":"Point"}
}