{
  "type": "Feature",
  "properties": {
    "iso:country":"DE",
    "sg:address":"Arminiusstr. 2",
    "sg:city":"Berlin",
    "sg:postcode":"10551",
    "sg:province":"Berlin",
    "wof:name":"Regional-textilien-vertriebs Gmbh & Co. Einzelhandels Kg",
    "wof:placetype":"venue"
},
  "geometry": {"coordinates":[13.3388328552,52.5274620056],"type":"Point"}
}