{
  "type": "Feature",
  "properties": {
    "iso:country":"DE",
    "sg:address":"Pitzgasse 6",
    "sg:city":"Hahnst\u00e4tten",
    "sg:phone":"+49 6430/7081",
    "sg:postcode":"65623",
    "sg:province":"Rheinland-Pfalz",
    "wof:name":"Friedrich Wilhelm Hennemann Inh. Gunther Weber",
    "wof:placetype":"venue"
},
  "geometry": {"coordinates":[8.067223,50.305531],"type":"Point"}
}