{
  "type": "Feature",
  "properties": {
    "iso:country":"DE",
    "sg:address":"Sandweg 73",
    "sg:city":"K\u00f6ln",
    "sg:phone":"+49 221/5301588",
    "sg:postcode":"50827",
    "sg:province":"Nordrhein-Westfalen",
    "wof:name":"Arno Grever",
    "wof:placetype":"venue"
},
  "geometry": {"coordinates":[6.899335,50.964252],"type":"Point"}
}