{
  "type": "Feature",
  "properties": {
    "iso:country":"DE",
    "sg:address":"Raiffeisenstr. 5",
    "sg:city":"M\u00fccke",
    "sg:phone":"+49 6400/8622",
    "sg:postcode":"35325",
    "sg:province":"Hessen",
    "wof:name":"Erna Salge",
    "wof:placetype":"venue"
},
  "geometry": {"coordinates":[9.115214,50.616543],"type":"Point"}
}