{
  "type": "Feature",
  "properties": {
    "iso:country":"DE",
    "sg:address":"Pankower Allee 93",
    "sg:city":"Berlin",
    "sg:phone":"+49 30/4911133",
    "sg:postcode":"13409",
    "sg:province":"Berlin",
    "wof:name":"Wolf-dieter Koch Steuerberater",
    "wof:placetype":"venue"
},
  "geometry": {"coordinates":[13.377409935,52.5647468567],"type":"Point"}
}