{
  "type": "Feature",
  "properties": {
    "iso:country":"DE",
    "sg:address":"Kaiser-Wilhelm-Ring 47",
    "sg:city":"D\u00fcsseldorf",
    "sg:phone":"+49 211/556276",
    "sg:postcode":"40545",
    "sg:province":"Nordrhein-Westfalen",
    "wof:name":"Eva M\u00fcller",
    "wof:placetype":"venue"
},
  "geometry": {"coordinates":[6.7594327927,51.227016449],"type":"Point"}
}