{
  "type": "Feature",
  "properties": {
    "iso:country":"DE",
    "sg:address":"Marktstr.",
    "sg:city":"Bad H\u00f6nningen",
    "sg:postcode":"53557",
    "sg:province":"Rheinland-Pfalz",
    "wof:name":"Verbandsgemeindeverwaltung",
    "wof:placetype":"venue"
},
  "geometry": {"coordinates":[7.3058729172,50.5157012939],"type":"Point"}
}