{
  "type": "Feature",
  "properties": {
    "iso:country":"DE",
    "sg:address":"Gaismannshofstr. 30",
    "sg:city":"N\u00fcrnberg",
    "sg:phone":"+49 911/313194",
    "sg:postcode":"90431",
    "sg:province":"Bayern",
    "wof:name":"Wilhelm Tauber",
    "wof:placetype":"venue"
},
  "geometry": {"coordinates":[11.0265512466,49.4497375488],"type":"Point"}
}