{
  "type": "Feature",
  "properties": {
    "iso:country":"DE",
    "sg:address":"Schulstr. 9",
    "sg:city":"Kesselsdorf",
    "sg:phone":"+49 35204/54580",
    "sg:postcode":"01723",
    "sg:province":"Sachsen",
    "wof:name":"Peter Wennrich",
    "wof:placetype":"venue"
},
  "geometry": {"coordinates":[13.592364,51.029915],"type":"Point"}
}