{
  "type": "Feature",
  "properties": {
    "iso:country":"DE",
    "sg:address":"Bloisstr. 58",
    "sg:city":"Waldshut-Tiengen",
    "sg:phone":"+49 7751/7929",
    "sg:postcode":"79761",
    "sg:province":"Baden-W\u00fcrttemberg",
    "wof:name":"Irmgard Weh",
    "wof:placetype":"venue"
},
  "geometry": {"coordinates":[8.231457,47.617424],"type":"Point"}
}