{
  "type": "Feature",
  "properties": {
    "iso:country":"DE",
    "sg:address":"Alte Eisenstr. 1",
    "sg:city":"Kirchen",
    "sg:phone":"+49 2741/94630",
    "sg:postcode":"57548",
    "sg:province":"Rheinland-Pfalz",
    "wof:name":"Hotel Zum Doppeldecker Gmbh",
    "wof:placetype":"venue"
},
  "geometry": {"coordinates":[7.8328819275,50.8237342834],"type":"Point"}
}