{
  "type": "Feature",
  "properties": {
    "iso:country":"DE",
    "sg:address":"Lahnstr. 15",
    "sg:city":"Wetzlar",
    "sg:phone":"+49 6441/47403",
    "sg:postcode":"35578",
    "sg:province":"Hessen",
    "wof:name":"Mode F\u00fcr Sie Und Ihn Frank Kr\u00fcger",
    "wof:placetype":"venue"
},
  "geometry": {"coordinates":[8.5003976822,50.5546951294],"type":"Point"}
}