{
  "type": "Feature",
  "properties": {
    "iso:country":"DE",
    "sg:address":"Sandersh\u00e4user Str. 34",
    "sg:city":"Kassel",
    "sg:phone":"+49 561/9536608",
    "sg:postcode":"34123",
    "sg:province":"Hessen",
    "wof:name":"N. Frank",
    "wof:placetype":"venue"
},
  "geometry": {"coordinates":[9.5238370895,51.3098335266],"type":"Point"}
}