{
  "type": "Feature",
  "properties": {
    "iso:country":"DE",
    "sg:address":"Hauptstr. 4",
    "sg:city":"Oberndorf",
    "sg:phone":"+49 9090/90250",
    "sg:postcode":"86698",
    "sg:province":"Bayern",
    "wof:name":"Golfcenter Eggelstetten Gmbh",
    "wof:placetype":"venue"
},
  "geometry": {"coordinates":[10.84647,48.677925],"type":"Point"}
}