{
  "type": "Feature",
  "properties": {
    "iso:country":"DE",
    "sg:address":"Lipper Weg 36",
    "sg:city":"Marl",
    "sg:phone":"+49 2365/36763",
    "sg:postcode":"45770",
    "sg:province":"Nordrhein-Westfalen",
    "wof:name":"Ziegler",
    "wof:placetype":"venue"
},
  "geometry": {"coordinates":[7.120993,51.664925],"type":"Point"}
}