{
  "type": "Feature",
  "properties": {
    "iso:country":"DE",
    "sg:address":"Preetzer Str. 3",
    "sg:city":"L\u00f6ptin",
    "sg:phone":"+49 4302/1086",
    "sg:postcode":"24250",
    "sg:province":"Schleswig-Holstein",
    "wof:name":"Herbert Hantke",
    "wof:placetype":"venue"
},
  "geometry": {"coordinates":[10.219074,54.180828],"type":"Point"}
}