{
  "type": "Feature",
  "properties": {
    "iso:country":"DE",
    "sg:address":"Rosental 46",
    "sg:city":"T\u00f6nisvorst",
    "sg:phone":"+49 2151/798190",
    "sg:postcode":"47918",
    "sg:province":"Nordrhein-Westfalen",
    "wof:name":"Pittgens & Sohn Transport Und Spedition Gmbh",
    "wof:placetype":"venue"
},
  "geometry": {"coordinates":[6.4911408424,51.3295021057],"type":"Point"}
}