{
  "type": "Feature",
  "properties": {
    "iso:country":"DE",
    "sg:address":"Berliner Str. 105",
    "sg:city":"Bochum",
    "sg:phone":"+49 2327/36051",
    "sg:postcode":"44867",
    "sg:province":"Nordrhein-Westfalen",
    "wof:name":"Giese Kinderbekleidung Gmbh",
    "wof:placetype":"venue"
},
  "geometry": {"coordinates":[7.131934166,51.4651145935],"type":"Point"}
}