{
  "type": "Feature",
  "properties": {
    "iso:country":"DE",
    "sg:address":"Waldstr. 35 a",
    "sg:city":"W\u00f6lfis",
    "sg:phone":"+49 3624/33160",
    "sg:postcode":"99885",
    "sg:province":"Th\u00fcringen",
    "wof:name":"W\u00f6lfis-korte Gmbh",
    "wof:placetype":"venue"
},
  "geometry": {"coordinates":[10.774054,50.80521],"type":"Point"}
}