{
  "type": "Feature",
  "properties": {
    "iso:country":"DE",
    "sg:address":"Goslarsche Str. 56",
    "sg:city":"Wolfenb\u00fcttel",
    "sg:postcode":"38304",
    "sg:province":"Niedersachsen",
    "wof:name":"Aldi Gmbh & Co. Kg",
    "wof:placetype":"venue"
},
  "geometry": {"coordinates":[10.5320987701,52.1574478149],"type":"Point"}
}