{
  "type": "Feature",
  "properties": {
    "iso:country":"DE",
    "sg:address":"Schliemannstr. 40",
    "sg:city":"Rostock",
    "sg:phone":"+49 381/31190",
    "sg:postcode":"18059",
    "sg:province":"Mecklenburg-Vorpommern",
    "wof:name":"L\u00fcdecke & Schmidt Sicherheitstechnik Gmbh",
    "wof:placetype":"venue"
},
  "geometry": {"coordinates":[12.129831,54.036232],"type":"Point"}
}