{
  "type": "Feature",
  "properties": {
    "iso:country":"DE",
    "sg:address":"Hainer Weg 48",
    "sg:city":"Frankfurt",
    "sg:phone":"+49 69/292003",
    "sg:postcode":"60599",
    "sg:province":"Hessen",
    "wof:name":"Associated Merchandising Corporation Gmbh",
    "wof:placetype":"venue"
},
  "geometry": {"coordinates":[8.693128,50.098476],"type":"Point"}
}