{
  "type": "Feature",
  "properties": {
    "iso:country":"DE",
    "sg:address":"M\u00fchlberger Str. 51",
    "sg:city":"Ko\u00dfdorf",
    "sg:phone":"+49 35342/589",
    "sg:postcode":"04895",
    "sg:province":"Brandenburg",
    "wof:name":"Wauer Gmbh",
    "wof:placetype":"venue"
},
  "geometry": {"coordinates":[13.2293024063,51.4896659851],"type":"Point"}
}