{
  "type": "Feature",
  "properties": {
    "iso:country":"DE",
    "sg:address":"Am Lindenbach 27",
    "sg:city":"Sonneberg",
    "sg:phone":"+49 3675/40790",
    "sg:postcode":"96515",
    "sg:province":"Th\u00fcringen",
    "wof:name":"Privatbrauerei Gessner Gmbh & Co.",
    "wof:placetype":"venue"
},
  "geometry": {"coordinates":[11.20596,50.345978],"type":"Point"}
}