{
  "type": "Feature",
  "properties": {
    "iso:country":"DE",
    "sg:address":"Im Pekel 3",
    "sg:city":"Molbergen",
    "sg:phone":"+49 4475/1266",
    "sg:postcode":"49696",
    "sg:province":"Niedersachsen",
    "wof:name":"Josefa Thesken",
    "wof:placetype":"venue"
},
  "geometry": {"coordinates":[7.914463,52.859512],"type":"Point"}
}