{
  "type": "Feature",
  "properties": {
    "iso:country":"DE",
    "sg:address":"Zu den Eichen 7",
    "sg:city":"Bad Liebenzell",
    "sg:phone":"+49 7052/3061",
    "sg:postcode":"75378",
    "sg:province":"Baden-W\u00fcrttemberg",
    "wof:name":"Arbeitskreis F\u00fcr Ern\u00e4hrungsforschung E. V.",
    "wof:placetype":"venue"
},
  "geometry": {"coordinates":[8.7124977112,48.7820358276],"type":"Point"}
}