{
  "type": "Feature",
  "properties": {
    "iso:country":"DE",
    "sg:address":"Velberter Str. 152",
    "sg:city":"Heiligenhaus",
    "sg:phone":"+49 2056/69769",
    "sg:postcode":"42579",
    "sg:province":"Nordrhein-Westfalen",
    "wof:name":"J\u00fcrgen Wind",
    "wof:placetype":"venue"
},
  "geometry": {"coordinates":[6.998948,51.329548],"type":"Point"}
}