{
  "type": "Feature",
  "properties": {
    "iso:country":"DE",
    "sg:address":"Dudenstr. 10",
    "sg:city":"Berlin",
    "sg:phone":"+49 30/7851866",
    "sg:postcode":"10965",
    "sg:province":"Berlin",
    "wof:name":"J\u00fcrgen Mattner",
    "wof:placetype":"venue"
},
  "geometry": {"coordinates":[13.384005,52.485161],"type":"Point"}
}