{
  "type": "Feature",
  "properties": {
    "iso:country":"DE",
    "sg:address":"Bergstr. 33",
    "sg:city":"G\u00fcntersleben",
    "sg:phone":"+49 9365/3194",
    "sg:postcode":"97261",
    "sg:province":"Bayern",
    "wof:name":"G\u00fcnter Markert",
    "wof:placetype":"venue"
},
  "geometry": {"coordinates":[9.908073,49.86422],"type":"Point"}
}