{
  "type": "Feature",
  "properties": {
    "iso:country":"DE",
    "sg:address":"August-Klotz-Str. 14",
    "sg:city":"D\u00fcren",
    "sg:postcode":"52349",
    "sg:province":"Nordrhein-Westfalen",
    "wof:name":"Avis Autovermietung Rbe-voreifel Gmbh",
    "wof:placetype":"venue"
},
  "geometry": {"coordinates":[6.478481,50.801765],"type":"Point"}
}