{
  "type": "Feature",
  "properties": {
    "iso:country":"DE",
    "sg:address":"An der Hardt 10",
    "sg:city":"Kall",
    "sg:phone":"+49 2441/5406",
    "sg:postcode":"53925",
    "sg:province":"Nordrhein-Westfalen",
    "wof:name":"H. De La Motte",
    "wof:placetype":"venue"
},
  "geometry": {"coordinates":[6.5604991913,50.526725769],"type":"Point"}
}