{
  "type": "Feature",
  "properties": {
    "iso:country":"DE",
    "sg:address":"Bahnhofstr. 24",
    "sg:city":"Borken",
    "sg:phone":"+49 5682/5757",
    "sg:postcode":"34582",
    "sg:province":"Hessen",
    "wof:name":"Lidl",
    "wof:placetype":"venue"
},
  "geometry": {"coordinates":[9.2781991959,51.0480194092],"type":"Point"}
}