{
  "type": "Feature",
  "properties": {
    "iso:country":"DE",
    "sg:address":"Donaustr. 101",
    "sg:city":"N\u00fcrnberg",
    "sg:phone":"+49 911/6493003",
    "sg:postcode":"90451",
    "sg:province":"Bayern",
    "wof:name":"H. Bahlsens Keksfabrik Kg",
    "wof:placetype":"venue"
},
  "geometry": {"coordinates":[11.057217,49.411114],"type":"Point"}
}