{
  "type": "Feature",
  "properties": {
    "iso:country":"DE",
    "sg:address":"Peter-Thumb-Str. 5",
    "sg:city":"Waldshut-Tiengen",
    "sg:phone":"+49 7741/671621",
    "sg:postcode":"79761",
    "sg:province":"Baden-W\u00fcrttemberg",
    "wof:name":"Etsp\u00fcler",
    "wof:placetype":"venue"
},
  "geometry": {"coordinates":[8.273850441,47.6348381042],"type":"Point"}
}