{
  "type": "Feature",
  "properties": {
    "iso:country":"DE",
    "sg:address":"Bonhoefferstr. 16",
    "sg:city":"Oelde",
    "sg:phone":"+49 2522/6966",
    "sg:postcode":"59302",
    "sg:province":"Nordrhein-Westfalen",
    "wof:name":"Bernd Nopto",
    "wof:placetype":"venue"
},
  "geometry": {"coordinates":[8.1529569626,51.8408699036],"type":"Point"}
}