{
  "type": "Feature",
  "properties": {
    "iso:country":"DE",
    "sg:address":"Heidm\u00fchlenstr. 9-15",
    "sg:city":"Neubrandenburg",
    "sg:phone":"+49 395/5823608",
    "sg:postcode":"17033",
    "sg:province":"Mecklenburg-Vorpommern",
    "wof:name":"Katholisches Kinderheim",
    "wof:placetype":"venue"
},
  "geometry": {"coordinates":[13.2746944427,53.5542068481],"type":"Point"}
}