{
  "type": "Feature",
  "properties": {
    "iso:country":"DE",
    "sg:address":"Quirrenbacher Str.",
    "sg:city":"K\u00f6nigswinter",
    "sg:phone":"+49 2244/4171",
    "sg:postcode":"53639",
    "sg:province":"Nordrhein-Westfalen",
    "wof:name":"A. Dollnick",
    "wof:placetype":"venue"
},
  "geometry": {"coordinates":[7.3106799126,50.6875953674],"type":"Point"}
}