{
  "type": "Feature",
  "properties": {
    "iso:country":"DE",
    "sg:address":"Wiesenstr. 1",
    "sg:city":"Sugenheim",
    "sg:phone":"+49 9165/313",
    "sg:postcode":"91484",
    "sg:province":"Bayern",
    "wof:name":"G\u00fcnther Sch\u00f6ler Elektroinstallation",
    "wof:placetype":"venue"
},
  "geometry": {"coordinates":[10.434705,49.605049],"type":"Point"}
}