{
  "type": "Feature",
  "properties": {
    "iso:country":"DE",
    "sg:address":"Goosestr. 47",
    "sg:city":"Bremen",
    "sg:phone":"+49 421/615358",
    "sg:postcode":"28237",
    "sg:province":"Bremen",
    "wof:name":"Gr\u00f6ner",
    "wof:placetype":"venue"
},
  "geometry": {"coordinates":[8.7581071854,53.1116294861],"type":"Point"}
}