{
  "type": "Feature",
  "properties": {
    "iso:country":"DE",
    "sg:address":"Richelsdorfer Str. 128",
    "sg:city":"Gerstungen",
    "sg:postcode":"99834",
    "sg:province":"Th\u00fcringen",
    "wof:name":"Wasserversorgung Und Abwasserbehandlung Erfurt Gmbh",
    "wof:placetype":"venue"
},
  "geometry": {"coordinates":[10.0497598648,50.9572944641],"type":"Point"}
}