{
  "type": "Feature",
  "properties": {
    "iso:country":"DE",
    "sg:address":"Grondahlsm\u00fchle 12",
    "sg:city":"Euskirchen",
    "sg:phone":"+49 39209/46964",
    "sg:postcode":"53881",
    "sg:province":"Nordrhein-Westfalen",
    "wof:name":"Metallbau Greve",
    "wof:placetype":"venue"
},
  "geometry": {"coordinates":[11.369742,52.069942],"type":"Point"}
}