{
  "type": "Feature",
  "properties": {
    "iso:country":"DE",
    "sg:address":"Uhlandstr. 13",
    "sg:city":"Ludwigshafen",
    "sg:phone":"+49 621/661854",
    "sg:postcode":"67069",
    "sg:province":"Rheinland-Pfalz",
    "wof:name":"Jakoby",
    "wof:placetype":"venue"
},
  "geometry": {"coordinates":[8.388588,49.531822],"type":"Point"}
}