{
  "type": "Feature",
  "properties": {
    "iso:country":"DE",
    "sg:address":"Nollstr. 1",
    "sg:city":"Elsdorf",
    "sg:postcode":"50189",
    "sg:province":"Nordrhein-Westfalen",
    "wof:name":"Access Yukon Gmbh",
    "wof:placetype":"venue"
},
  "geometry": {"coordinates":[6.5629811287,50.9374504089],"type":"Point"}
}