{
  "type": "Feature",
  "properties": {
    "iso:country":"DE",
    "sg:address":"Eugen-Langen-Str. 9",
    "sg:city":"K\u00f6ln-Marienburg",
    "sg:phone":"+49 221",
    "sg:postcode":"50968",
    "sg:province":"Nordrhein-Westfalen",
    "wof:name":"Peter Houbois Grundst\u00fccksmakler",
    "wof:placetype":"venue"
},
  "geometry": {"coordinates":[6.9531698227,50.8996162415],"type":"Point"}
}