{
  "type": "Feature",
  "properties": {
    "iso:country":"DE",
    "sg:address":"In der Dille 43",
    "sg:city":"Bergkamen",
    "sg:phone":"+49 2389/6693",
    "sg:postcode":"59192",
    "sg:province":"Nordrhein-Westfalen",
    "wof:name":"Hella Rechenberg",
    "wof:placetype":"venue"
},
  "geometry": {"coordinates":[7.6578650475,51.6461830139],"type":"Point"}
}