{
  "type": "Feature",
  "properties": {
    "iso:country":"DE",
    "sg:address":"Oberlinder Str. 59",
    "sg:city":"Gefell",
    "sg:phone":"+49 36764/770",
    "sg:postcode":"96524",
    "sg:province":"Th\u00fcringen",
    "wof:name":"Alpla-design Lehner Gmbh",
    "wof:placetype":"venue"
},
  "geometry": {"coordinates":[11.232925,50.340397],"type":"Point"}
}