{
  "type": "Feature",
  "properties": {
    "iso:country":"DE",
    "sg:address":"G\u00fcldengossaer Str. 21",
    "sg:city":"Leipzig",
    "sg:phone":"+49 34297/45170",
    "sg:postcode":"04288",
    "sg:province":"Sachsen",
    "wof:name":"W. Schmid",
    "wof:placetype":"venue"
},
  "geometry": {"coordinates":[12.4572534561,51.2800941467],"type":"Point"}
}