{
  "type": "Feature",
  "properties": {
    "iso:country":"DE",
    "sg:address":"Rudolf-Weber-Str. 71",
    "sg:city":"L\u00f6\u00dfnitz",
    "sg:phone":"+49 371/446764",
    "sg:postcode":"08294",
    "sg:province":"Sachsen",
    "wof:name":"Rtm Anlagentechnik Gmbh",
    "wof:placetype":"venue"
},
  "geometry": {"coordinates":[12.727515,50.616619],"type":"Point"}
}