{
  "type": "Feature",
  "properties": {
    "iso:country":"DE",
    "sg:address":"Haagener Str. 45",
    "sg:city":"L\u00f6rrach",
    "sg:phone":"+49 7621/49850",
    "sg:postcode":"79539",
    "sg:province":"Baden-W\u00fcrttemberg",
    "wof:name":"Heidrun Pelz",
    "wof:placetype":"venue"
},
  "geometry": {"coordinates":[7.664359,47.619469],"type":"Point"}
}