{
  "type": "Feature",
  "properties": {
    "iso:country":"DE",
    "sg:address":"Bischof-Krautbauer-Str. 8",
    "sg:city":"Bruck",
    "sg:phone":"+49 9434/683",
    "sg:postcode":"92436",
    "sg:province":"Bayern",
    "wof:name":"Gustl Schuhbauer",
    "wof:placetype":"venue"
},
  "geometry": {"coordinates":[12.3066215515,49.2508239746],"type":"Point"}
}