{
  "type": "Feature",
  "properties": {
    "iso:country":"DE",
    "sg:address":"Windorfer Str. 24",
    "sg:city":"Leipzig",
    "sg:postcode":"04229",
    "sg:province":"Sachsen",
    "wof:name":"Sms Hausverwaltung- Und Immobilien Gmbh",
    "wof:placetype":"venue"
},
  "geometry": {"coordinates":[12.3297405243,51.3185462952],"type":"Point"}
}