{
  "type": "Feature",
  "properties": {
    "iso:country":"DE",
    "sg:address":"Talstr. 30",
    "sg:city":"M\u00fchlhausen",
    "sg:postcode":"69242",
    "sg:province":"Baden-W\u00fcrttemberg",
    "wof:name":"Platinum Consulting Group Gmbh",
    "wof:placetype":"venue"
},
  "geometry": {"coordinates":[8.754789,49.262341],"type":"Point"}
}