{
  "type": "Feature",
  "properties": {
    "iso:country":"DE",
    "sg:address":"Kampstr. 57",
    "sg:city":"Essen",
    "sg:phone":"+49 201/672489",
    "sg:postcode":"45355",
    "sg:province":"Nordrhein-Westfalen",
    "wof:name":"A. F\u00f6rster",
    "wof:placetype":"venue"
},
  "geometry": {"coordinates":[6.9566397667,51.4672737122],"type":"Point"}
}