{
  "type": "Feature",
  "properties": {
    "iso:country":"DE",
    "sg:address":"Wilhelmstr. 21-24",
    "sg:city":"Berlin",
    "sg:phone":"+49 30/31869060",
    "sg:postcode":"13593",
    "sg:province":"Berlin",
    "wof:name":"Ahlsen Immobilienges. Mbh",
    "wof:placetype":"venue"
},
  "geometry": {"coordinates":[13.187924,52.521389],"type":"Point"}
}