{
  "type": "Feature",
  "properties": {
    "iso:country":"DE",
    "sg:address":"Philipp-Reis-Str. 5",
    "sg:city":"Linden",
    "sg:postcode":"35440",
    "sg:province":"Hessen",
    "wof:name":"D\u00fcrrschmidt & Viehmann Planungsb\u00fcro F\u00fcr Geb\u00e4ude-",
    "wof:placetype":"venue"
},
  "geometry": {"coordinates":[8.6514587402,50.5363616943],"type":"Point"}
}