{
  "type": "Feature",
  "properties": {
    "iso:country":"DE",
    "sg:address":"Minoritenweg 31",
    "sg:city":"Regensburg",
    "sg:phone":"+49 941/53283",
    "sg:postcode":"93047",
    "sg:province":"Bayern",
    "wof:name":"Christian Ge\u00dfner",
    "wof:placetype":"venue"
},
  "geometry": {"coordinates":[12.1065750122,49.01720047],"type":"Point"}
}