{
  "type": "Feature",
  "properties": {
    "iso:country":"DE",
    "sg:address":"Turmstr. 26a",
    "sg:city":"Potsdam",
    "sg:phone":"+49 331/624020",
    "sg:postcode":"14480",
    "sg:province":"Brandenburg",
    "wof:name":"T & T Maler Gmbh",
    "wof:placetype":"venue"
},
  "geometry": {"coordinates":[13.12323,52.374313],"type":"Point"}
}