{
  "type": "Feature",
  "properties": {
    "iso:country":"DE",
    "sg:address":"B\u00e4umlstr. 10",
    "sg:city":"Amberg",
    "sg:phone":"+49 9621/78270",
    "sg:postcode":"92224",
    "sg:province":"Bayern",
    "wof:name":"Pegrasys Gmbh & Co. Kg",
    "wof:placetype":"venue"
},
  "geometry": {"coordinates":[11.8742313385,49.4428100586],"type":"Point"}
}