{
  "type": "Feature",
  "properties": {
    "iso:country":"DE",
    "sg:address":"Klandorfer Str. 13",
    "sg:city":"Marienwerder",
    "sg:phone":"+49 3335/231",
    "sg:postcode":"16348",
    "sg:province":"Brandenburg",
    "wof:name":"Vroni Leirer",
    "wof:placetype":"venue"
},
  "geometry": {"coordinates":[13.598008,52.844383],"type":"Point"}
}