{
  "type": "Feature",
  "properties": {
    "iso:country":"DE",
    "sg:address":"Waldstr. 3",
    "sg:city":"Preu\u00dfisch Oldendorf",
    "sg:phone":"+49 5742/96933",
    "sg:postcode":"32361",
    "sg:province":"Nordrhein-Westfalen",
    "wof:name":"Prahl Asphalttechnik Gmbh & Co.",
    "wof:placetype":"venue"
},
  "geometry": {"coordinates":[8.4810781479,52.302280426],"type":"Point"}
}