{
  "type": "Feature",
  "properties": {
    "iso:country":"DE",
    "sg:address":"H\u00e4ndelstr. 3",
    "sg:city":"Elsdorf",
    "sg:postcode":"50189",
    "sg:province":"Nordrhein-Westfalen",
    "wof:name":"Pld Private Label Distribution Gmbh",
    "wof:placetype":"venue"
},
  "geometry": {"coordinates":[6.5689301491,50.9416007996],"type":"Point"}
}