{
  "type": "Feature",
  "properties": {
    "iso:country":"DE",
    "sg:address":"Milsper Str 133A",
    "sg:city":"Ennepetal",
    "sg:phone":"+49 2333/2087",
    "sg:postcode":"58256",
    "sg:province":"Nordrhein-Westfalen",
    "wof:name":"Fws Gmbh & Co. Kg",
    "wof:placetype":"venue"
},
  "geometry": {"coordinates":[7.368846,51.302189],"type":"Point"}
}