{
  "type": "Feature",
  "properties": {
    "iso:country":"DE",
    "sg:address":"Neuburgstr. 16",
    "sg:city":"Wendlingen",
    "sg:phone":"+49 7024/7520",
    "sg:postcode":"73240",
    "sg:province":"Baden-W\u00fcrttemberg",
    "wof:name":"Robert Schaller Mech. Werkstatt",
    "wof:placetype":"venue"
},
  "geometry": {"coordinates":[9.376108,48.669754],"type":"Point"}
}