{
  "type": "Feature",
  "properties": {
    "iso:country":"DE",
    "sg:address":"B\u00fcrgerm.-Klingler-Str. 25 a",
    "sg:city":"M\u00f6rfelden-Walldorf",
    "sg:phone":"+49 6105/22950",
    "sg:postcode":"64546",
    "sg:province":"Hessen",
    "wof:name":"Ev. Pfarramt Gem. M\u00f6rfelden",
    "wof:placetype":"venue"
},
  "geometry": {"coordinates":[8.5690145493,49.9742660522],"type":"Point"}
}