{
  "type": "Feature",
  "properties": {
    "iso:country":"DE",
    "sg:address":"Duckwitzstr. 27",
    "sg:city":"Bremen",
    "sg:phone":"+49 421/5148191",
    "sg:postcode":"28199",
    "sg:province":"Bremen",
    "wof:name":"Teppich-b\u00f6rse, Fachhandel F\u00fcr Bodenbel\u00e4ge",
    "wof:placetype":"venue"
},
  "geometry": {"coordinates":[8.777099,53.063885],"type":"Point"}
}