{
  "type": "Feature",
  "properties": {
    "iso:country":"DE",
    "sg:address":"Johannesstr. 20",
    "sg:city":"Spelle",
    "sg:phone":"+49 5977/477",
    "sg:postcode":"48480",
    "sg:province":"Niedersachsen",
    "wof:name":"Rats-apotheke",
    "wof:placetype":"venue"
},
  "geometry": {"coordinates":[7.473556,52.36631],"type":"Point"}
}