{
  "type": "Feature",
  "properties": {
    "iso:country":"DE",
    "sg:address":"Gebsattelstr. 11",
    "sg:city":"M\u00fcnchen",
    "sg:phone":"+49 89/486544",
    "sg:postcode":"81541",
    "sg:province":"Bayern",
    "wof:name":"M\u00fcnchner Blech- Und Holzblas- Instrumente Gmbh",
    "wof:placetype":"venue"
},
  "geometry": {"coordinates":[11.5893831253,48.1247024536],"type":"Point"}
}