{
  "type": "Feature",
  "properties": {
    "iso:country":"DE",
    "sg:address":"Herdweg 35",
    "sg:city":"Stuttgart",
    "sg:phone":"+49 711/2262206",
    "sg:postcode":"70174",
    "sg:province":"Baden-W\u00fcrttemberg",
    "wof:name":"Rainer R. Czermak Architekt",
    "wof:placetype":"venue"
},
  "geometry": {"coordinates":[9.165717,48.785419],"type":"Point"}
}