{
  "type": "Feature",
  "properties": {
    "iso:country":"DE",
    "sg:address":"Baumbacher Str. 40",
    "sg:city":"Montabaur",
    "sg:phone":"+49 2602/4478",
    "sg:postcode":"56410",
    "sg:province":"Rheinland-Pfalz",
    "wof:name":"Gebr\u00fcder G\u00f6rg Inh. Edgar G\u00f6rg E. K.",
    "wof:placetype":"venue"
},
  "geometry": {"coordinates":[7.7926030159,50.4440917969],"type":"Point"}
}