{
  "type": "Feature",
  "properties": {
    "iso:country":"DE",
    "sg:address":"H\u00f6llweg 48",
    "sg:city":"Adelsried",
    "sg:phone":"+49 8294/802929",
    "sg:postcode":"86477",
    "sg:province":"Bayern",
    "wof:name":"Peter P. Krause Architekt",
    "wof:placetype":"venue"
},
  "geometry": {"coordinates":[10.727037,48.423534],"type":"Point"}
}