{
  "type": "Feature",
  "properties": {
    "iso:country":"DE",
    "sg:address":"Theodor-Heuss-Allee 6",
    "sg:city":"Bremen",
    "sg:phone":"+49 421/376613",
    "sg:postcode":"28215",
    "sg:province":"Bremen",
    "wof:name":"Eurospar",
    "wof:placetype":"venue"
},
  "geometry": {"coordinates":[8.813284874,53.085483551],"type":"Point"}
}