{
  "type": "Feature",
  "properties": {
    "iso:country":"DE",
    "sg:address":"Am Amtshaus 24",
    "sg:city":"Dortmund",
    "sg:postcode":"44359",
    "sg:province":"Nordrhein-Westfalen",
    "wof:name":"Omni-o Gmbh",
    "wof:placetype":"venue"
},
  "geometry": {"coordinates":[7.378552,51.570274],"type":"Point"}
}