{
  "type": "Feature",
  "properties": {
    "iso:country":"DE",
    "sg:address":"Weiherweg 37",
    "sg:city":"Oberhausen-Rheinhausen",
    "sg:phone":"+49 7254/1013",
    "sg:postcode":"68794",
    "sg:province":"Baden-W\u00fcrttemberg",
    "wof:name":"Scheurer Bauunternehmung Gmbh",
    "wof:placetype":"venue"
},
  "geometry": {"coordinates":[8.4730300903,49.2690010071],"type":"Point"}
}