{
  "type": "Feature",
  "properties": {
    "iso:country":"DE",
    "sg:address":"Rolandstr. 15",
    "sg:city":"Bielefeld",
    "sg:phone":"+49 521/132313",
    "sg:postcode":"33615",
    "sg:province":"Nordrhein-Westfalen",
    "wof:name":"Restaurant Der Koch",
    "wof:placetype":"venue"
},
  "geometry": {"coordinates":[8.5228528976,52.0278778076],"type":"Point"}
}