{
  "type": "Feature",
  "properties": {
    "iso:country":"DE",
    "sg:address":"W\u00fcrzburger Str. 1",
    "sg:city":"Giebelstadt",
    "sg:phone":"+49 9334/97470",
    "sg:postcode":"97232",
    "sg:province":"Bayern",
    "wof:name":"Grimm Und Nestmeier",
    "wof:placetype":"venue"
},
  "geometry": {"coordinates":[9.9473018646,49.6535072327],"type":"Point"}
}