{
  "type": "Feature",
  "properties": {
    "iso:country":"DE",
    "sg:address":"Heilmannstr.36",
    "sg:city":"Frankfurt/Main",
    "sg:phone":"+49 69",
    "sg:postcode":"60439",
    "sg:province":"Hessen",
    "wof:name":"Webprovider - Acn Internet Full Service Agentur",
    "wof:placetype":"venue"
},
  "geometry": {"coordinates":[8.6240730286,50.156829834],"type":"Point"}
}