{
  "type": "Feature",
  "properties": {
    "iso:country":"DE",
    "sg:address":"Rheinufer 1",
    "sg:city":"Bad Breisig",
    "sg:phone":"+49 2633/471866",
    "sg:postcode":"53498",
    "sg:province":"Rheinland-Pfalz",
    "wof:name":"Treidlstube",
    "wof:placetype":"venue"
},
  "geometry": {"coordinates":[7.3006000519,50.5108528137],"type":"Point"}
}