{
  "type": "Feature",
  "properties": {
    "iso:country":"DE",
    "sg:address":"Weiherstr. 9",
    "sg:city":"Ried",
    "sg:phone":"+49 8233/75960",
    "sg:postcode":"86510",
    "sg:province":"Bayern",
    "wof:name":"Rato-systems - Computer Mehr!",
    "wof:placetype":"venue"
},
  "geometry": {"coordinates":[11.042054,48.287735],"type":"Point"}
}