{
  "type": "Feature",
  "properties": {
    "iso:country":"DE",
    "sg:address":"\u00d6lbergstr. 12",
    "sg:city":"K\u00f6ln",
    "sg:phone":"+49 221/462625",
    "sg:postcode":"50939",
    "sg:province":"Nordrhein-Westfalen",
    "wof:name":"G. Rubin Ingenieur",
    "wof:placetype":"venue"
},
  "geometry": {"coordinates":[6.9280648232,50.9087219238],"type":"Point"}
}