{
  "type": "Feature",
  "properties": {
    "iso:country":"DE",
    "sg:address":"Meersburger Str 1",
    "sg:city":"Ravensburg",
    "sg:phone":"+49 4975/1841100",
    "sg:postcode":"88213",
    "sg:province":"Baden-W\u00fcrttemberg",
    "wof:name":"Kreissparkasse",
    "wof:placetype":"venue"
},
  "geometry": {"coordinates":[9.60814,47.781395],"type":"Point"}
}