{
  "type": "Feature",
  "properties": {
    "iso:country":"DE",
    "sg:address":"Deggendorfer Str. 1",
    "sg:city":"Teisnach",
    "sg:phone":"+49 9923/1818",
    "sg:postcode":"94244",
    "sg:province":"Bayern",
    "wof:name":"Gasthof Ettl-br\u00e4u",
    "wof:placetype":"venue"
},
  "geometry": {"coordinates":[12.995347023,49.037612915],"type":"Point"}
}