{
  "type": "Feature",
  "properties": {
    "iso:country":"DE",
    "sg:city":"Bottrop",
    "sg:postcode":"46236",
    "sg:province":"Nordrhein-Westfalen",
    "wof:name":"Klaus Raape",
    "wof:placetype":"venue"
},
  "geometry": {"coordinates":[6.925223,51.524704],"type":"Point"}
}