{
  "type": "Feature",
  "properties": {
    "iso:country":"DE",
    "sg:address":"Fasanenweg 8",
    "sg:city":"Bergkirchen",
    "sg:phone":"+49 8131/736333",
    "sg:postcode":"85232",
    "sg:province":"Bayern",
    "wof:name":"Karl Gutwein",
    "wof:placetype":"venue"
},
  "geometry": {"coordinates":[11.4045572281,48.2530250549],"type":"Point"}
}