{
  "type": "Feature",
  "properties": {
    "iso:country":"DE",
    "sg:address":"Rembertistr. 9",
    "sg:city":"Norden",
    "sg:phone":"+49 4931/13310",
    "sg:postcode":"26506",
    "sg:province":"Niedersachsen",
    "wof:name":"H. Kolle",
    "wof:placetype":"venue"
},
  "geometry": {"coordinates":[7.2229361534,53.5953865051],"type":"Point"}
}