{
  "type": "Feature",
  "properties": {
    "iso:country":"DE",
    "sg:address":"Schulstr. 4",
    "sg:city":"Arnsberg",
    "sg:phone":"+49 2932/22175",
    "sg:postcode":"59755",
    "sg:province":"Nordrhein-Westfalen",
    "wof:name":"Josef Schumacher",
    "wof:placetype":"venue"
},
  "geometry": {"coordinates":[7.96857,51.450497],"type":"Point"}
}