{
  "type": "Feature",
  "properties": {
    "iso:country":"DE",
    "sg:address":"Mittelweg 5",
    "sg:city":"Panschwitz-Kuckau",
    "sg:phone":"+49 35796/9730",
    "sg:postcode":"01920",
    "sg:province":"Sachsen",
    "wof:name":"St. Sebastian Apotheke Inh. Stefan Finger",
    "wof:placetype":"venue"
},
  "geometry": {"coordinates":[14.191932,51.233326],"type":"Point"}
}