{
  "type": "Feature",
  "properties": {
    "iso:country":"DE",
    "sg:address":"Gabelsbergerstrasse 30",
    "sg:city":"Hanau",
    "sg:phone":"+49 6181/1899790",
    "sg:postcode":"63452",
    "sg:province":"Hessen",
    "wof:name":"Kostenlos Geld: Verdienen. Sparen. Werben.",
    "wof:placetype":"venue"
},
  "geometry": {"coordinates":[8.931843,50.139389],"type":"Point"}
}