{
  "type": "Feature",
  "properties": {
    "iso:country":"DE",
    "sg:address":"Pommernstr. 9",
    "sg:city":"Engelskirchen",
    "sg:phone":"+49 2263/5832",
    "sg:postcode":"51766",
    "sg:province":"Nordrhein-Westfalen",
    "wof:name":"Oberbergischer Naturschutz- Verband Engelskirchen-",
    "wof:placetype":"venue"
},
  "geometry": {"coordinates":[7.461815834,50.9908332825],"type":"Point"}
}