{
  "type": "Feature",
  "properties": {
    "iso:country":"DE",
    "sg:address":"Lindenstr. 11",
    "sg:city":"Bad Nauheim",
    "sg:phone":"+49 6032/4092",
    "sg:postcode":"61231",
    "sg:province":"Hessen",
    "wof:name":"Miroslav Sifra",
    "wof:placetype":"venue"
},
  "geometry": {"coordinates":[8.7469215393,50.3651771545],"type":"Point"}
}