{
  "type": "Feature",
  "properties": {
    "iso:country":"DE",
    "sg:address":"Friedrichshagener Str. 11",
    "sg:city":"Berlin",
    "sg:postcode":"12555",
    "sg:province":"Berlin",
    "wof:name":"Kvvg Verm\u00f6gensverwaltungs- Und Verwertungsgesellschaft In",
    "wof:placetype":"venue"
},
  "geometry": {"coordinates":[13.5892524719,52.4512023926],"type":"Point"}
}