{
  "type": "Feature",
  "properties": {
    "iso:country":"DE",
    "sg:address":"Geiselinastr. 8",
    "sg:city":"Lauingen",
    "sg:phone":"+49 9072/95750",
    "sg:postcode":"89415",
    "sg:province":"Bayern",
    "wof:name":"J\u00fcrgen Lenzer",
    "wof:placetype":"venue"
},
  "geometry": {"coordinates":[10.431669,48.569992],"type":"Point"}
}