{
  "type": "Feature",
  "properties": {
    "iso:country":"DE",
    "sg:address":"Steinhagen 4",
    "sg:city":"Hattingen",
    "sg:phone":"+49 2324/52823",
    "sg:postcode":"45525",
    "sg:province":"Nordrhein-Westfalen",
    "wof:name":"Altstadt-treppchen",
    "wof:placetype":"venue"
},
  "geometry": {"coordinates":[7.1847581863,51.397518158],"type":"Point"}
}