{
  "type": "Feature",
  "properties": {
    "iso:country":"DE",
    "sg:address":"Zietenstr. 3",
    "sg:city":"Oldenburg",
    "sg:phone":"+49 441/51784",
    "sg:postcode":"26131",
    "sg:province":"Niedersachsen",
    "wof:name":"G\u00fclzau Heissmangelbetrieb",
    "wof:placetype":"venue"
},
  "geometry": {"coordinates":[8.1843414307,53.1360359192],"type":"Point"}
}