{
  "type": "Feature",
  "properties": {
    "iso:country":"DE",
    "sg:address":"Mecklenburger Str. 22",
    "sg:city":"Uetze",
    "sg:phone":"+49 5147/1422",
    "sg:postcode":"31311",
    "sg:province":"Niedersachsen",
    "wof:name":"Heilbadinstitut",
    "wof:placetype":"venue"
},
  "geometry": {"coordinates":[10.083996,52.485397],"type":"Point"}
}