{
  "type": "Feature",
  "properties": {
    "iso:country":"DE",
    "sg:address":"Am Markt 5",
    "sg:city":"Neuhaus",
    "sg:phone":"+49 38841/20747",
    "sg:postcode":"19273",
    "sg:province":"Mecklenburg-Vorpommern",
    "wof:name":"Wohnungsbau- Verwaltungs- Gmbh",
    "wof:placetype":"venue"
},
  "geometry": {"coordinates":[10.9291372299,53.2858314514],"type":"Point"}
}