{
  "type": "Feature",
  "properties": {
    "iso:country":"DE",
    "sg:address":"Forckestr. 16",
    "sg:city":"Wernigerode",
    "sg:phone":"+49 3943/32431",
    "sg:postcode":"38855",
    "sg:province":"Sachsen-Anhalt",
    "wof:name":"Ingenieurb\u00fcro S Und L",
    "wof:placetype":"venue"
},
  "geometry": {"coordinates":[10.7826776505,51.8306312561],"type":"Point"}
}