{
  "type": "Feature",
  "properties": {
    "iso:country":"DE",
    "sg:address":"Lindenstr. 4",
    "sg:city":"Crivitz",
    "sg:phone":"+49 3863/222259",
    "sg:postcode":"19089",
    "sg:province":"Mecklenburg-Vorpommern",
    "wof:name":"V. K\u00f6hn Immobilienmakler",
    "wof:placetype":"venue"
},
  "geometry": {"coordinates":[11.6498327255,53.5769309998],"type":"Point"}
}