{
  "type": "Feature",
  "properties": {
    "iso:country":"DE",
    "sg:address":"An der Mehle 34",
    "sg:city":"Waldbrunn",
    "sg:phone":"+49 9306/1625",
    "sg:postcode":"97295",
    "sg:province":"Bayern",
    "wof:name":"Bernhard Wiehl",
    "wof:placetype":"venue"
},
  "geometry": {"coordinates":[9.7979154587,49.7564506531],"type":"Point"}
}