{
  "type": "Feature",
  "properties": {
    "iso:country":"DE",
    "sg:address":"Raiffeisenstr. 8",
    "sg:city":"Sachsenheim",
    "sg:phone":"+49 7147/12222",
    "sg:postcode":"74343",
    "sg:province":"Baden-W\u00fcrttemberg",
    "wof:name":"Peter Klein",
    "wof:placetype":"venue"
},
  "geometry": {"coordinates":[9.021377,48.998051],"type":"Point"}
}