{
  "type": "Feature",
  "properties": {
    "iso:country":"DE",
    "sg:address":"Inselstr. 1",
    "sg:city":"Krummh\u00f6rn",
    "sg:phone":"+49 4926/1702",
    "sg:postcode":"26736",
    "sg:province":"Niedersachsen",
    "wof:name":"Hans-gerhard L\u00fcpkes",
    "wof:placetype":"venue"
},
  "geometry": {"coordinates":[7.089426,53.504406],"type":"Point"}
}