{
  "type": "Feature",
  "properties": {
    "iso:country":"DE",
    "sg:address":"Ramsdorfer Str. 64",
    "sg:city":"Borken",
    "sg:phone":"+49 2862/2532",
    "sg:postcode":"46325",
    "sg:province":"Nordrhein-Westfalen",
    "wof:name":"Gastst\u00e4tte Hubert L\u00fctjann",
    "wof:placetype":"venue"
},
  "geometry": {"coordinates":[6.8892550468,51.8942642212],"type":"Point"}
}