{
  "type": "Feature",
  "properties": {
    "iso:country":"DE",
    "sg:address":"H\u00f6kerstr 11",
    "sg:city":"Bremerhaven",
    "sg:phone":"+49 471/503668",
    "sg:postcode":"27568",
    "sg:province":"Bremen",
    "wof:name":"Hygros Gmbh",
    "wof:placetype":"venue"
},
  "geometry": {"coordinates":[8.584127,53.565422],"type":"Point"}
}