{
  "type": "Feature",
  "properties": {
    "iso:country":"DE",
    "sg:address":"Schulzendorfer Str. 104",
    "sg:city":"Berlin",
    "sg:phone":"+49 30/4311371",
    "sg:postcode":"13503",
    "sg:province":"Berlin",
    "wof:name":"Rainer Kock",
    "wof:placetype":"venue"
},
  "geometry": {"coordinates":[13.2268,52.613487],"type":"Point"}
}