{
  "type": "Feature",
  "properties": {
    "iso:country":"DE",
    "sg:address":"Am Troistedter Weg",
    "sg:city":"Nohra",
    "sg:phone":"+49 3643/54170",
    "sg:postcode":"99428",
    "sg:province":"Th\u00fcringen",
    "wof:name":"Fleischergen. Weimar Eg",
    "wof:placetype":"venue"
},
  "geometry": {"coordinates":[11.2342882156,50.9606437683],"type":"Point"}
}