{
  "type": "Feature",
  "properties": {
    "iso:country":"DE",
    "sg:address":"Castroper Str. 156",
    "sg:city":"Datteln",
    "sg:phone":"+49 2363/62092",
    "sg:postcode":"45711",
    "sg:province":"Nordrhein-Westfalen",
    "wof:name":"M\u00f6bel Meyer Gmbh",
    "wof:placetype":"venue"
},
  "geometry": {"coordinates":[7.334280014,51.6411323547],"type":"Point"}
}