{
  "type": "Feature",
  "properties": {
    "iso:country":"DE",
    "sg:address":"Kirchham",
    "sg:city":"Kirchham",
    "sg:phone":"+49 8533/1564",
    "sg:postcode":"94148",
    "sg:province":"Bayern",
    "wof:name":"Sparkasse Passau/kirchham",
    "wof:placetype":"venue"
},
  "geometry": {"coordinates":[13.266367,48.345886],"type":"Point"}
}