{
  "type": "Feature",
  "properties": {
    "iso:country":"DE",
    "sg:address":"Werdauer Str. 1",
    "sg:city":"Dresden",
    "sg:postcode":"01069",
    "sg:province":"Sachsen",
    "wof:name":"T\u00dcv Informationstechnik Gmbh",
    "wof:placetype":"venue"
},
  "geometry": {"coordinates":[13.7164916992,51.0396118164],"type":"Point"}
}