{
  "type": "Feature",
  "properties": {
    "iso:country":"DE",
    "sg:address":"Martinstr. 5",
    "sg:city":"L\u00f6bej\u00fcn",
    "sg:phone":"+49 34603/77995",
    "sg:postcode":"06193",
    "sg:province":"Sachsen-Anhalt",
    "wof:name":"H. Mangelsdorf",
    "wof:placetype":"venue"
},
  "geometry": {"coordinates":[11.90936,51.636528],"type":"Point"}
}