{
  "type": "Feature",
  "properties": {
    "iso:country":"DE",
    "sg:address":"Welte 125",
    "sg:city":"D\u00fclmen",
    "sg:phone":"+49 2594/949273",
    "sg:postcode":"48249",
    "sg:province":"Nordrhein-Westfalen",
    "wof:name":"Peter Fitz Ingenieur",
    "wof:placetype":"venue"
},
  "geometry": {"coordinates":[7.2243728638,51.8713302612],"type":"Point"}
}