{
  "type": "Feature",
  "properties": {
    "iso:country":"DE",
    "sg:address":"Im Bruch 1",
    "sg:city":"Kettenkamp",
    "sg:phone":"+49 5436/1555",
    "sg:postcode":"49577",
    "sg:province":"Niedersachsen",
    "wof:name":"Dokument Und Bild",
    "wof:placetype":"venue"
},
  "geometry": {"coordinates":[7.8351330757,52.5920219421],"type":"Point"}
}