{
  "type": "Feature",
  "properties": {
    "iso:country":"DE",
    "sg:address":"Eickhoffstr. 26-34",
    "sg:city":"G\u00fctersloh",
    "sg:phone":"+49 5241/13022",
    "sg:postcode":"33330",
    "sg:province":"Nordrhein-Westfalen",
    "wof:name":"M\u00f6bel Heinz Wellerdiek",
    "wof:placetype":"venue"
},
  "geometry": {"coordinates":[8.3826980591,51.9082641602],"type":"Point"}
}