{
  "type": "Feature",
  "properties": {
    "iso:country":"DE",
    "sg:address":"Bergstr. 83",
    "sg:city":"B\u00f6tzingen",
    "sg:postcode":"79268",
    "sg:province":"Baden-W\u00fcrttemberg",
    "wof:name":"M-tec Ibenthaler Gmbh",
    "wof:placetype":"venue"
},
  "geometry": {"coordinates":[7.711821,48.073917],"type":"Point"}
}