{
  "type": "Feature",
  "properties": {
    "iso:country":"DE",
    "sg:address":"Lindemannstr. 7",
    "sg:city":"Tutzing",
    "sg:phone":"+49 8158/99663",
    "sg:postcode":"82327",
    "sg:province":"Bayern",
    "wof:name":"Michael Zirngibl Stahl- Und Metallbau Gmbh",
    "wof:placetype":"venue"
},
  "geometry": {"coordinates":[11.272586,47.903511],"type":"Point"}
}