{
  "type": "Feature",
  "properties": {
    "iso:country":"DE",
    "sg:address":"Gro\u00dfer Moor 38",
    "sg:city":"Schwerin",
    "sg:phone":"+49 385/560971",
    "sg:postcode":"19055",
    "sg:province":"Mecklenburg-Vorpommern",
    "wof:name":"Historisches Museum",
    "wof:placetype":"venue"
},
  "geometry": {"coordinates":[11.418727,53.628052],"type":"Point"}
}