{
  "type": "Feature",
  "properties": {
    "iso:country":"DE",
    "sg:address":"G\u00f6ttiner Landstr. 1",
    "sg:city":"Brandenburg",
    "sg:phone":"+49 3381/661660",
    "sg:postcode":"14776",
    "sg:province":"Brandenburg",
    "wof:name":"Klaus Mesenberg",
    "wof:placetype":"venue"
},
  "geometry": {"coordinates":[12.5453300476,52.3931350708],"type":"Point"}
}