{
  "type": "Feature",
  "properties": {
    "iso:country":"DE",
    "sg:address":"Grenzstr. 22",
    "sg:city":"Ellefeld",
    "sg:phone":"+49 3745/70728",
    "sg:postcode":"08236",
    "sg:province":"Sachsen",
    "wof:name":"Frank Thoss",
    "wof:placetype":"venue"
},
  "geometry": {"coordinates":[12.3822374344,50.4819717407],"type":"Point"}
}