{
  "type": "Feature",
  "properties": {
    "iso:country":"DE",
    "sg:address":"Kr\u00e4her Weg 15",
    "sg:city":"Nienburg",
    "sg:phone":"+49 5021/63081",
    "sg:postcode":"31582",
    "sg:province":"Niedersachsen",
    "wof:name":"Fr\u00e4rks Gesch\u00e4ftsf\u00fchrungs-gmbh",
    "wof:placetype":"venue"
},
  "geometry": {"coordinates":[9.2287931442,52.6411705017],"type":"Point"}
}