{
  "type": "Feature",
  "properties": {
    "iso:country":"DE",
    "sg:address":"Silberweg 21",
    "sg:city":"B\u00f6blingen",
    "sg:phone":"+49 7031/228516",
    "sg:postcode":"71032",
    "sg:province":"Baden-W\u00fcrttemberg",
    "wof:name":"K. R. Saika",
    "wof:placetype":"venue"
},
  "geometry": {"coordinates":[9.021294,48.694576],"type":"Point"}
}