{
  "type": "Feature",
  "properties": {
    "iso:country":"DE",
    "sg:address":"Marktplatz 3",
    "sg:city":"Baumholder",
    "sg:phone":"+49 6783/4840",
    "sg:postcode":"55774",
    "sg:province":"Rheinland-Pfalz",
    "wof:name":"Cafe Vis A Vis",
    "wof:placetype":"venue"
},
  "geometry": {"coordinates":[7.33636,49.615879],"type":"Point"}
}