{
  "type": "Feature",
  "properties": {
    "iso:country":"DE",
    "sg:address":"Lukoer Str. 2",
    "sg:city":"Ro\u00dflau",
    "sg:postcode":"06862",
    "sg:province":"Sachsen-Anhalt",
    "wof:name":"Altenheim Otto Buchwitz",
    "wof:placetype":"venue"
},
  "geometry": {"coordinates":[12.267428,51.895966],"type":"Point"}
}