{
  "type": "Feature",
  "properties": {
    "iso:country":"DE",
    "sg:address":"Limburger Str. 55",
    "sg:city":"Idstein",
    "sg:phone":"+49 6126/70826",
    "sg:postcode":"65510",
    "sg:province":"Hessen",
    "wof:name":"G\u00fcnter Sypli",
    "wof:placetype":"venue"
},
  "geometry": {"coordinates":[8.2653064728,50.2261695862],"type":"Point"}
}