{
  "type": "Feature",
  "properties": {
    "iso:country":"DE",
    "sg:address":"Saalestr. 1 a",
    "sg:city":"Neum\u00fcnster",
    "sg:phone":"+49 4321/81445",
    "sg:postcode":"24539",
    "sg:province":"Schleswig-Holstein",
    "wof:name":"Pausentreff",
    "wof:placetype":"venue"
},
  "geometry": {"coordinates":[9.985748291,54.0475273132],"type":"Point"}
}