{
  "type": "Feature",
  "properties": {
    "iso:country":"DE",
    "sg:address":"Kopernikusstr. 10",
    "sg:city":"Karlsruhe",
    "sg:phone":"+49 721/572367",
    "sg:postcode":"76185",
    "sg:province":"Baden-W\u00fcrttemberg",
    "wof:name":"M. C. Salas-r\u00fcckert Dolmetscherin",
    "wof:placetype":"venue"
},
  "geometry": {"coordinates":[8.345294,49.003365],"type":"Point"}
}