{
  "type": "Feature",
  "properties": {
    "iso:country":"DE",
    "sg:address":"Osterstr. 10",
    "sg:city":"Oldenburg",
    "sg:phone":"+49 441/921780",
    "sg:postcode":"26122",
    "sg:province":"Niedersachsen",
    "wof:name":"Marius Eriksen",
    "wof:placetype":"venue"
},
  "geometry": {"coordinates":[8.2165279388,53.1429100037],"type":"Point"}
}