{
  "type": "Feature",
  "properties": {
    "iso:country":"DE",
    "sg:address":"Breidenplatz 10",
    "sg:city":"D\u00fcsseldorf",
    "sg:phone":"+49 211/202360",
    "sg:postcode":"40627",
    "sg:province":"Nordrhein-Westfalen",
    "wof:name":"Stadtb\u00fccherei Unterbach",
    "wof:placetype":"venue"
},
  "geometry": {"coordinates":[6.894667,51.204399],"type":"Point"}
}