{
  "type": "Feature",
  "properties": {
    "iso:country":"DE",
    "sg:address":"Frankfurter Allee 94a",
    "sg:city":"Berlin",
    "sg:phone":"+49 30/2910444",
    "sg:postcode":"10247",
    "sg:province":"Berlin",
    "wof:name":"Helmut Janoschka Und Dr. Alfons Sommer",
    "wof:placetype":"venue"
},
  "geometry": {"coordinates":[13.4720182419,52.5137825012],"type":"Point"}
}