{
  "type": "Feature",
  "properties": {
    "iso:country":"DE",
    "sg:address":"B\u00fcrgermeister-Seidl-Str 2",
    "sg:city":"Wolfratshausen",
    "sg:phone":"+49 8171/16000",
    "sg:postcode":"82515",
    "sg:province":"Bayern",
    "wof:name":"Icc Inchem Industrie Chemie Gmbh",
    "wof:placetype":"venue"
},
  "geometry": {"coordinates":[11.423164,47.90303],"type":"Point"}
}