{
  "type": "Feature",
  "properties": {
    "iso:country":"DE",
    "sg:address":"Burggartenstr. 48",
    "sg:city":"Pforzheim",
    "sg:phone":"+49 7231/71733",
    "sg:postcode":"75180",
    "sg:province":"Baden-W\u00fcrttemberg",
    "wof:name":"Manfred Deyhle",
    "wof:placetype":"venue"
},
  "geometry": {"coordinates":[8.6803998947,48.8672599792],"type":"Point"}
}