{
  "type": "Feature",
  "properties": {
    "iso:country":"DE",
    "sg:address":"Richard-Wagner-Str. 3",
    "sg:city":"Sand",
    "sg:phone":"+49 9524/850295",
    "sg:postcode":"97522",
    "sg:province":"Bayern",
    "wof:name":"Otto Ehehalt",
    "wof:placetype":"venue"
},
  "geometry": {"coordinates":[10.5862340927,49.9829788208],"type":"Point"}
}