{
  "type": "Feature",
  "properties": {
    "iso:country":"DE",
    "sg:address":"Brandenburger Str. 76",
    "sg:city":"Offenbach",
    "sg:phone":"+49 69/869661",
    "sg:postcode":"63075",
    "sg:province":"Hessen",
    "wof:name":"Uwelt Consulting Gmbh",
    "wof:placetype":"venue"
},
  "geometry": {"coordinates":[8.7834434509,50.1250076294],"type":"Point"}
}