{
  "type": "Feature",
  "properties": {
    "iso:country":"DE",
    "sg:address":"Geretsrieder Str. 4",
    "sg:city":"Traunreut",
    "sg:phone":"+49 8669/12977",
    "sg:postcode":"83301",
    "sg:province":"Bayern",
    "wof:name":"D. Eibl Jun.",
    "wof:placetype":"venue"
},
  "geometry": {"coordinates":[12.605514,47.96336],"type":"Point"}
}