{
  "type": "Feature",
  "properties": {
    "iso:country":"DE",
    "sg:address":"Moorhauser Landstr. 23",
    "sg:city":"Lilienthal",
    "sg:phone":"+49 4298/698111",
    "sg:postcode":"28865",
    "sg:province":"Niedersachsen",
    "wof:name":" Lilienthaler K\u00fcchenhalle Karl-heinz Flathmann E. Kfm.",
    "wof:placetype":"venue"
},
  "geometry": {"coordinates":[8.9093151093,53.1515350342],"type":"Point"}
}