{
  "type": "Feature",
  "properties": {
    "iso:country":"DE",
    "sg:address":"Bachgasse 41",
    "sg:city":"Gr\u00fcndau",
    "sg:phone":"+49 6058/90310",
    "sg:postcode":"63584",
    "sg:province":"Hessen",
    "wof:name":"Holger Hofmann Anlageberater",
    "wof:placetype":"venue"
},
  "geometry": {"coordinates":[9.1051502228,50.2319297791],"type":"Point"}
}