{
  "type": "Feature",
  "properties": {
    "iso:country":"DE",
    "sg:address":"Klopstockstr. 1",
    "sg:city":"Hamburg",
    "sg:phone":"+49 40/391040",
    "sg:postcode":"22765",
    "sg:province":"Hamburg",
    "wof:name":"Harmstorf & Co. Schiffs- Beteiligungs Gmbh",
    "wof:placetype":"venue"
},
  "geometry": {"coordinates":[9.93418,53.54631],"type":"Point"}
}