{
  "type": "Feature",
  "properties": {
    "iso:country":"DE",
    "sg:address":"Seestr. 6",
    "sg:city":"M\u00fcncheberg",
    "sg:phone":"+49 33432/89929",
    "sg:postcode":"15374",
    "sg:province":"Brandenburg",
    "wof:name":"Willi Pr\u00f6hl",
    "wof:placetype":"venue"
},
  "geometry": {"coordinates":[14.1106262207,52.5149078369],"type":"Point"}
}