{
  "type": "Feature",
  "properties": {
    "iso:country":"DE",
    "sg:address":"Gladbacher Str 83",
    "sg:city":"Schwalmtal",
    "sg:phone":"+49 2163/47623",
    "sg:postcode":"41366",
    "sg:province":"Nordrhein-Westfalen",
    "wof:name":"Pkh Blechverarbeitung Gmbh",
    "wof:placetype":"venue"
},
  "geometry": {"coordinates":[6.2838449478,51.2098236084],"type":"Point"}
}