{
  "type": "Feature",
  "properties": {
    "iso:country":"DE",
    "sg:address":"Schmiedestr. 42",
    "sg:city":"Kappeln",
    "sg:phone":"+49 4642/1221",
    "sg:postcode":"24376",
    "sg:province":"Schleswig-Holstein",
    "wof:name":"Thomas Winkels Verwaltung Von Grundbesitz",
    "wof:placetype":"venue"
},
  "geometry": {"coordinates":[9.9275856018,54.6621170044],"type":"Point"}
}