{
  "type": "Feature",
  "properties": {
    "iso:country":"DE",
    "sg:address":"Stadtweg 32",
    "sg:city":"Husum",
    "sg:phone":"+49 4841/5384",
    "sg:postcode":"25813",
    "sg:province":"Schleswig-Holstein",
    "wof:name":"Wohnungsges. Norden Mbh Wohnungs- Und Siedlungsbau",
    "wof:placetype":"venue"
},
  "geometry": {"coordinates":[9.0434951782,54.4845123291],"type":"Point"}
}