{
  "type": "Feature",
  "properties": {
    "iso:country":"DE",
    "sg:address":"M\u00fchlenweg 5",
    "sg:city":"Neu Darchau",
    "sg:postcode":"29490",
    "sg:province":"Niedersachsen",
    "wof:name":"Comerciala Forti-s. R. L.",
    "wof:placetype":"venue"
},
  "geometry": {"coordinates":[10.881634,53.227516],"type":"Point"}
}