{
  "type": "Feature",
  "properties": {
    "iso:country":"DE",
    "sg:address":"Lilienthalstr. 9",
    "sg:city":"Stadtallendorf",
    "sg:phone":"+49 6428/921800",
    "sg:postcode":"35260",
    "sg:province":"Hessen",
    "wof:name":"J. Zethner Steuerbevollm\u00e4chtigte",
    "wof:placetype":"venue"
},
  "geometry": {"coordinates":[9.0053243637,50.831867218],"type":"Point"}
}