{
  "type": "Feature",
  "properties": {
    "iso:country":"DE",
    "sg:address":"Rotes Knie",
    "sg:city":"Cleebronn",
    "sg:phone":"+49 7135/13383",
    "sg:postcode":"74389",
    "sg:province":"Baden-W\u00fcrttemberg",
    "wof:name":"U. Walderich",
    "wof:placetype":"venue"
},
  "geometry": {"coordinates":[9.0324878693,49.0370254517],"type":"Point"}
}