{
  "type": "Feature",
  "properties": {
    "iso:country":"DE",
    "sg:address":"Hauptstr. 13b",
    "sg:city":"Lindenberg",
    "sg:phone":"+49 33677/6150",
    "sg:postcode":"15864",
    "sg:province":"Brandenburg",
    "wof:name":"Kr\u00fcger Metallbau Gmbh",
    "wof:placetype":"venue"
},
  "geometry": {"coordinates":[14.112156,52.203995],"type":"Point"}
}