{
  "type": "Feature",
  "properties": {
    "iso:country":"DE",
    "sg:address":"Hauptstr. 4.",
    "sg:city":"Furth",
    "sg:phone":"+49 8704/1274",
    "sg:postcode":"84095",
    "sg:province":"Bayern",
    "wof:name":"G. Aigner",
    "wof:placetype":"venue"
},
  "geometry": {"coordinates":[12.0223474503,48.5889549255],"type":"Point"}
}