{
  "type": "Feature",
  "properties": {
    "iso:country":"DE",
    "sg:address":"Ringstr. 12",
    "sg:city":"Th\u00fcngersheim",
    "sg:phone":"+49 9364/9431",
    "sg:postcode":"97291",
    "sg:province":"Bayern",
    "wof:name":"Rudolf G\u00f6\u00dfwein Weinbau",
    "wof:placetype":"venue"
},
  "geometry": {"coordinates":[9.8490600586,49.8767852783],"type":"Point"}
}