{
  "type": "Feature",
  "properties": {
    "iso:country":"DE",
    "sg:address":"Rognacallee 6",
    "sg:city":"Rockenhausen",
    "sg:phone":"+49 6361/994660",
    "sg:postcode":"67806",
    "sg:province":"Rheinland-Pfalz",
    "wof:name":"Vinothek",
    "wof:placetype":"venue"
},
  "geometry": {"coordinates":[7.819029808,49.6297683716],"type":"Point"}
}