{
  "type": "Feature",
  "properties": {
    "iso:country":"DE",
    "sg:address":"Lichtstr.80",
    "sg:city":"D\u00fcsseldorf",
    "sg:phone":"+49 211/678057",
    "sg:postcode":"40235",
    "sg:province":"Nordrhein-Westfalen",
    "wof:name":"Dresdner Bank",
    "wof:placetype":"venue"
},
  "geometry": {"coordinates":[6.81495,51.22871],"type":"Point"}
}