{
  "type": "Feature",
  "properties": {
    "iso:country":"DE",
    "sg:address":"St.-Veit-Str. 17",
    "sg:city":"Mayen",
    "sg:phone":"+49 2651/2354",
    "sg:postcode":"56727",
    "sg:province":"Rheinland-Pfalz",
    "wof:name":"Brigitte Petri Notarin",
    "wof:placetype":"venue"
},
  "geometry": {"coordinates":[7.2286071777,50.3287239075],"type":"Point"}
}