{
  "type": "Feature",
  "properties": {
    "iso:country":"DE",
    "sg:address":"Nelkenweg 8",
    "sg:city":"Gmund",
    "sg:phone":"+49 8022/769550",
    "sg:postcode":"83703",
    "sg:province":"Bayern",
    "wof:name":"Holocom Computer- Systeme & Communications Ohg",
    "wof:placetype":"venue"
},
  "geometry": {"coordinates":[11.7313547134,47.7608108521],"type":"Point"}
}