{
  "type": "Feature",
  "properties": {
    "iso:country":"DE",
    "sg:address":"Nu\u00dfbaumgasse 8",
    "sg:city":"Landau",
    "sg:phone":"+49 6341/84281",
    "sg:postcode":"76829",
    "sg:province":"Rheinland-Pfalz",
    "wof:name":"Pizzeria-eiscafe Adria",
    "wof:placetype":"venue"
},
  "geometry": {"coordinates":[8.1113319397,49.1963806152],"type":"Point"}
}