{
  "type": "Feature",
  "properties": {
    "iso:country":"DE",
    "sg:address":"Oststr. 8",
    "sg:city":"Wiehl",
    "sg:phone":"+49 2262/72050",
    "sg:postcode":"51674",
    "sg:province":"Nordrhein-Westfalen",
    "wof:name":"J\u00fcrgen Schumacher Ingenieur",
    "wof:placetype":"venue"
},
  "geometry": {"coordinates":[7.514166832,50.9723205566],"type":"Point"}
}