{
  "type": "Feature",
  "properties": {
    "iso:country":"DE",
    "sg:address":"Marktstr. 10",
    "sg:city":"N\u00fcrtingen",
    "sg:phone":"+49 7022/8606",
    "sg:postcode":"72622",
    "sg:province":"Baden-W\u00fcrttemberg",
    "wof:name":"Garten-markt Samen-nagel Inh. Dieter Bleher",
    "wof:placetype":"venue"
},
  "geometry": {"coordinates":[9.336363,48.626385],"type":"Point"}
}