{
  "type": "Feature",
  "properties": {
    "iso:country":"DE",
    "sg:address":"Anhaltstr. 30",
    "sg:city":"Luckenwalde",
    "sg:phone":"+49 3371/622103",
    "sg:postcode":"14943",
    "sg:province":"Brandenburg",
    "wof:name":"G. Ladewig",
    "wof:placetype":"venue"
},
  "geometry": {"coordinates":[13.1507043839,52.084072113],"type":"Point"}
}