{
  "type": "Feature",
  "properties": {
    "iso:country":"DE",
    "sg:address":"Ligusterweg 60",
    "sg:city":"Braunschweig",
    "sg:phone":"+49 531/322168",
    "sg:postcode":"38112",
    "sg:province":"Niedersachsen",
    "wof:name":"Das Studio Sabine Neumann Und",
    "wof:placetype":"venue"
},
  "geometry": {"coordinates":[10.5099897385,52.2918930054],"type":"Point"}
}