{
  "type": "Feature",
  "properties": {
    "iso:country":"DE",
    "sg:address":"Kirchheide 24",
    "sg:city":"Bremen",
    "sg:phone":"+49 421/6900166",
    "sg:postcode":"28757",
    "sg:province":"Bremen",
    "wof:name":"Edda Jankowski Rechtsanw\u00e4ltin",
    "wof:placetype":"venue"
},
  "geometry": {"coordinates":[8.6195240021,53.1739463806],"type":"Point"}
}