{
  "type": "Feature",
  "properties": {
    "iso:country":"DE",
    "sg:address":"Wilhelmstr. 13",
    "sg:city":"Bad Nenndorf",
    "sg:phone":"+49 5723/2000",
    "sg:postcode":"31542",
    "sg:province":"Niedersachsen",
    "wof:name":"Dr. Felicia Rehage Tier\u00e4rztin",
    "wof:placetype":"venue"
},
  "geometry": {"coordinates":[9.3701553345,52.3355712891],"type":"Point"}
}