{
  "type": "Feature",
  "properties": {
    "iso:country":"DE",
    "sg:address":"Logestr. 39-41",
    "sg:city":"Beverstedt",
    "sg:postcode":"27616",
    "sg:province":"Niedersachsen",
    "wof:name":"Aldi Gmbh & Co. Kg",
    "wof:placetype":"venue"
},
  "geometry": {"coordinates":[8.824016571,53.432723999],"type":"Point"}
}