{
  "type": "Feature",
  "properties": {
    "iso:country":"DE",
    "sg:address":"Friedrichsthal 21",
    "sg:city":"Grebenstein",
    "sg:phone":"+49 5674/4477",
    "sg:postcode":"34393",
    "sg:province":"Hessen",
    "wof:name":"August J\u00e4ger Architekt",
    "wof:placetype":"venue"
},
  "geometry": {"coordinates":[9.368329,51.445866],"type":"Point"}
}