{
  "type": "Feature",
  "properties": {
    "iso:country":"DE",
    "sg:address":"Parksteiner Str. 43",
    "sg:city":"Schwarzenbach",
    "sg:postcode":"92720",
    "sg:province":"Bayern",
    "wof:name":"Amt Abendroth Montage Von Textilmaschinen Gmbh",
    "wof:placetype":"venue"
},
  "geometry": {"coordinates":[12.00338,49.729279],"type":"Point"}
}