{
  "type": "Feature",
  "properties": {
    "iso:country":"DE",
    "sg:address":"Martin-Luther-Str. 1",
    "sg:city":"Bad Orb",
    "sg:phone":"+49 6052/5951",
    "sg:postcode":"63619",
    "sg:province":"Hessen",
    "wof:name":"G\u00e4stehaus Wopienka",
    "wof:placetype":"venue"
},
  "geometry": {"coordinates":[9.3531160355,50.2249946594],"type":"Point"}
}