{
  "type": "Feature",
  "properties": {
    "iso:country":"DE",
    "sg:address":"Nagelspitzstr. 16a",
    "sg:city":"Schliersee",
    "sg:phone":"+49 8026/97930",
    "sg:postcode":"83727",
    "sg:province":"Bayern",
    "wof:name":"K. Huisgen Immobilienmakler",
    "wof:placetype":"venue"
},
  "geometry": {"coordinates":[11.8869552612,47.6938819885],"type":"Point"}
}