{
  "type": "Feature",
  "properties": {
    "iso:country":"DE",
    "sg:address":"Meckenheimer Allee 172",
    "sg:city":"Bonn",
    "sg:phone":"+49 228/233526",
    "sg:postcode":"53115",
    "sg:province":"Nordrhein-Westfalen",
    "wof:name":"Institut F\u00fcr Kartographie Und Topographie",
    "wof:placetype":"venue"
},
  "geometry": {"coordinates":[7.0910692215,50.7254142761],"type":"Point"}
}