{
  "type": "Feature",
  "properties": {
    "iso:country":"DE",
    "sg:address":"Neue Str. 2",
    "sg:city":"Lingen",
    "sg:phone":"+49 591/53009",
    "sg:postcode":"49808",
    "sg:province":"Niedersachsen",
    "wof:name":"City-cafe",
    "wof:placetype":"venue"
},
  "geometry": {"coordinates":[7.31586,52.521549],"type":"Point"}
}