{
  "type": "Feature",
  "properties": {
    "iso:country":"DE",
    "sg:address":"Im Hausgrund 12",
    "sg:city":"Eiterfeld",
    "sg:phone":"+49 6672/480",
    "sg:postcode":"36132",
    "sg:province":"Hessen",
    "wof:name":"Werner Hartmann Kohlen-handlung",
    "wof:placetype":"venue"
},
  "geometry": {"coordinates":[9.8012838364,50.7642745972],"type":"Point"}
}