{
  "type": "Feature",
  "properties": {
    "iso:country":"DE",
    "sg:address":"Marbacher Str. 107",
    "sg:city":"D\u00fcsseldorf",
    "sg:phone":"+49 211/716458",
    "sg:postcode":"40597",
    "sg:province":"Nordrhein-Westfalen",
    "wof:name":"J\u00fcrgen Holstein Rechtsanwalt",
    "wof:placetype":"venue"
},
  "geometry": {"coordinates":[6.8595209122,51.1643943787],"type":"Point"}
}