{
  "type": "Feature",
  "properties": {
    "iso:country":"DE",
    "sg:address":"August-Ruf-Str. 13",
    "sg:city":"Singen",
    "sg:phone":"+49 7731/62582",
    "sg:postcode":"78224",
    "sg:province":"Baden-W\u00fcrttemberg",
    "wof:name":"Herold",
    "wof:placetype":"venue"
},
  "geometry": {"coordinates":[8.838587,47.761463],"type":"Point"}
}