{
  "type": "Feature",
  "properties": {
    "iso:country":"DE",
    "sg:address":"Hersfelder Str. 15",
    "sg:city":"Kn\u00fcllwald",
    "sg:phone":"+49 5681/2592",
    "sg:postcode":"34593",
    "sg:province":"Hessen",
    "wof:name":"Pension Else Pfl\u00fcger",
    "wof:placetype":"venue"
},
  "geometry": {"coordinates":[9.4705295563,50.9995994568],"type":"Point"}
}