{
  "type": "Feature",
  "properties": {
    "iso:country":"DE",
    "sg:address":"Alpenblickweg 4",
    "sg:city":"Gmund",
    "sg:phone":"+49 8022/75260",
    "sg:postcode":"83703",
    "sg:province":"Bayern",
    "wof:name":"Atoll Gmbh",
    "wof:placetype":"venue"
},
  "geometry": {"coordinates":[11.734495163,47.7524261475],"type":"Point"}
}