{
  "type": "Feature",
  "properties": {
    "iso:country":"DE",
    "sg:address":"Rembrandtstr. 36",
    "sg:city":"Bremen",
    "sg:phone":"+49 421/342430",
    "sg:postcode":"28209",
    "sg:province":"Bremen",
    "wof:name":"Wolfgang Lehmann Steuerberater Und",
    "wof:placetype":"venue"
},
  "geometry": {"coordinates":[8.8304777145,53.0838317871],"type":"Point"}
}