{
  "type": "Feature",
  "properties": {
    "iso:country":"DE",
    "sg:address":"Eppinger Str. 22",
    "sg:city":"\u00d6stringen",
    "sg:phone":"+49 7259/477",
    "sg:postcode":"76684",
    "sg:province":"Baden-W\u00fcrttemberg",
    "wof:name":"Blume",
    "wof:placetype":"venue"
},
  "geometry": {"coordinates":[8.7507171631,49.1766357422],"type":"Point"}
}