{
  "type": "Feature",
  "properties": {
    "iso:country":"DE",
    "sg:address":"Baisieper Str. 80",
    "sg:city":"Remscheid",
    "sg:phone":"+49 4921/9131803",
    "sg:postcode":"42859",
    "sg:province":"Nordrhein-Westfalen",
    "wof:name":"Max Hakenberg",
    "wof:placetype":"venue"
},
  "geometry": {"coordinates":[7.225634,51.172127],"type":"Point"}
}