{
  "type": "Feature",
  "properties": {
    "iso:country":"DE",
    "sg:address":"Ammenser Str. 45",
    "sg:city":"Freden",
    "sg:phone":"+49 5184/424",
    "sg:postcode":"31084",
    "sg:province":"Niedersachsen",
    "wof:name":"H. Windrich",
    "wof:placetype":"venue"
},
  "geometry": {"coordinates":[9.8680696487,51.9237327576],"type":"Point"}
}