{
  "type": "Feature",
  "properties": {
    "iso:country":"DE",
    "sg:address":"Weidenh\u00e4user Str. 101",
    "sg:city":"Marburg",
    "sg:phone":"+49 6421/27772",
    "sg:postcode":"35037",
    "sg:province":"Hessen",
    "wof:name":"G. Zeckey Jun.",
    "wof:placetype":"venue"
},
  "geometry": {"coordinates":[8.777104,50.804935],"type":"Point"}
}