{
  "type": "Feature",
  "properties": {
    "iso:country":"DE",
    "sg:address":"Rathausweg",
    "sg:city":"Enzkl\u00f6sterle",
    "sg:phone":"+49 7085/517",
    "sg:postcode":"75337",
    "sg:province":"Baden-W\u00fcrttemberg",
    "wof:name":"Red. Enzkl\u00f6sterle Kurzeitung Kurverwaltung",
    "wof:placetype":"venue"
},
  "geometry": {"coordinates":[8.4692316055,48.6632728577],"type":"Point"}
}