{
  "type": "Feature",
  "properties": {
    "iso:country":"DE",
    "sg:address":"M\u00fchlenstr. 28",
    "sg:city":"Bremen",
    "sg:phone":"+49 421/600373",
    "sg:postcode":"28779",
    "sg:province":"Bremen",
    "wof:name":"R\u00f6nner",
    "wof:placetype":"venue"
},
  "geometry": {"coordinates":[8.5726556778,53.1838684082],"type":"Point"}
}