{
  "type": "Feature",
  "properties": {
    "iso:country":"DE",
    "sg:address":"Eppsteiner Str. 8",
    "sg:city":"Oberursel",
    "sg:phone":"+49 6171/4132",
    "sg:postcode":"61440",
    "sg:province":"Hessen",
    "wof:name":"Werner Erbacher",
    "wof:placetype":"venue"
},
  "geometry": {"coordinates":[8.578022,50.203457],"type":"Point"}
}