{
  "type": "Feature",
  "properties": {
    "iso:country":"DE",
    "sg:address":"Birkenstr. 6",
    "sg:city":"Bunde",
    "sg:phone":"+49 4953/326",
    "sg:postcode":"26831",
    "sg:province":"Niedersachsen",
    "wof:name":"H. Snater",
    "wof:placetype":"venue"
},
  "geometry": {"coordinates":[7.273303,53.18515],"type":"Point"}
}