{
  "type": "Feature",
  "properties": {
    "iso:country":"DE",
    "sg:address":"Weidebrunner Gasse",
    "sg:city":"Schmalkalden",
    "sg:phone":"+49 3683/607920",
    "sg:postcode":"98574",
    "sg:province":"Th\u00fcringen",
    "wof:name":"City-videothek",
    "wof:placetype":"venue"
},
  "geometry": {"coordinates":[10.4524326324,50.7238845825],"type":"Point"}
}