{
  "type": "Feature",
  "properties": {
    "iso:country":"DE",
    "sg:address":"Druckereistr. 4",
    "sg:city":"Leipzig",
    "sg:phone":"+49 341/467790",
    "sg:postcode":"04159",
    "sg:province":"Sachsen",
    "wof:name":"Gegenbauer Geb\u00e4udeservice Gmbh & Co. Kg",
    "wof:placetype":"venue"
},
  "geometry": {"coordinates":[12.312036,51.3787],"type":"Point"}
}