{
  "type": "Feature",
  "properties": {
    "iso:country":"DE",
    "sg:address":"Lilienstr. 20",
    "sg:city":"Olching",
    "sg:phone":"+49 8142/49567",
    "sg:postcode":"82140",
    "sg:province":"Bayern",
    "wof:name":"T. Gross",
    "wof:placetype":"venue"
},
  "geometry": {"coordinates":[11.337907,48.210346],"type":"Point"}
}