{
  "type": "Feature",
  "properties": {
    "iso:country":"DE",
    "sg:address":"Zur Burgm\u00fchle 22a",
    "sg:city":"M\u00f6nchengladbach",
    "sg:phone":"+49 2166/605505",
    "sg:postcode":"41199",
    "sg:province":"Nordrhein-Westfalen",
    "wof:name":"M. Clingen",
    "wof:placetype":"venue"
},
  "geometry": {"coordinates":[6.4513969421,51.1349143982],"type":"Point"}
}