{
  "type": "Feature",
  "properties": {
    "iso:country":"DE",
    "sg:address":"Markt 9",
    "sg:city":"Themar",
    "sg:phone":"+49 36873/60443",
    "sg:postcode":"98660",
    "sg:province":"Th\u00fcringen",
    "wof:name":"Gr\u00fcner Baum",
    "wof:placetype":"venue"
},
  "geometry": {"coordinates":[10.6143045425,50.5036582947],"type":"Point"}
}