{
  "type": "Feature",
  "properties": {
    "iso:country":"DE",
    "sg:address":"Am H\u00fclsberg 12",
    "sg:city":"Marl",
    "sg:phone":"+49 2365/880790",
    "sg:postcode":"45772",
    "sg:province":"Nordrhein-Westfalen",
    "wof:name":"Rosi-reisen Overhoff Inh. Joh. -gerd Overhoff E. K.",
    "wof:placetype":"venue"
},
  "geometry": {"coordinates":[7.1562318802,51.6742858887],"type":"Point"}
}