{
  "type": "Feature",
  "properties": {
    "iso:country":"DE",
    "sg:address":"Karl-Marx-Str. 14",
    "sg:city":"Trier",
    "sg:phone":"+49 651/74186",
    "sg:postcode":"54290",
    "sg:province":"Rheinland-Pfalz",
    "wof:name":"Cafe-konditorei Raab E. K.",
    "wof:placetype":"venue"
},
  "geometry": {"coordinates":[6.6339187622,49.7530784607],"type":"Point"}
}