{
  "type": "Feature",
  "properties": {
    "iso:country":"DE",
    "sg:address":"K\u00f6nigsberger Str. 21",
    "sg:city":"M\u00fcnchen",
    "sg:phone":"+49 89/932393",
    "sg:postcode":"81927",
    "sg:province":"Bayern",
    "wof:name":"Graphischer Betrieb Vogtmann Gmbh",
    "wof:placetype":"venue"
},
  "geometry": {"coordinates":[11.639996,48.152035],"type":"Point"}
}