{
  "type": "Feature",
  "properties": {
    "iso:country":"DE",
    "sg:address":"Sandstr. 16",
    "sg:city":"L\u00fcbeck",
    "sg:phone":"+49 451/73729",
    "sg:postcode":"23552",
    "sg:province":"Schleswig-Holstein",
    "wof:name":"Pegasus-apotheke Jan-uwe Kreuschner",
    "wof:placetype":"venue"
},
  "geometry": {"coordinates":[10.684969,53.865257],"type":"Point"}
}