{
  "type": "Feature",
  "properties": {
    "iso:country":"DE",
    "sg:address":"Haselweg 54",
    "sg:city":"Halstenbek",
    "sg:phone":"+49 4101/43254",
    "sg:postcode":"25469",
    "sg:province":"Schleswig-Holstein",
    "wof:name":"Dieter Heins Rechtsanwalt",
    "wof:placetype":"venue"
},
  "geometry": {"coordinates":[9.8616065979,53.6155128479],"type":"Point"}
}