{
  "type": "Feature",
  "properties": {
    "iso:country":"DE",
    "sg:address":"Nielandstr. 25",
    "sg:city":"Wetter",
    "sg:phone":"+49 2335/96850",
    "sg:postcode":"58300",
    "sg:province":"Nordrhein-Westfalen",
    "wof:name":"Spedition Lingnau Gmbh",
    "wof:placetype":"venue"
},
  "geometry": {"coordinates":[7.3834848404,51.3590393066],"type":"Point"}
}