{
  "type": "Feature",
  "properties": {
    "iso:country":"DE",
    "sg:address":"Rabanusstr. 12",
    "sg:city":"Fulda",
    "sg:phone":"+49 661/97970",
    "sg:postcode":"36037",
    "sg:province":"Hessen",
    "wof:name":"Landeszentralbank In Hessen",
    "wof:placetype":"venue"
},
  "geometry": {"coordinates":[9.6782979965,50.5531616211],"type":"Point"}
}