{
  "type": "Feature",
  "properties": {
    "iso:country":"DE",
    "sg:address":"Kaiserstr. 150",
    "sg:city":"Br\u00fchl",
    "sg:phone":"+49 2232/211501",
    "sg:postcode":"50321",
    "sg:province":"Nordrhein-Westfalen",
    "wof:name":"Siegfried Huhn",
    "wof:placetype":"venue"
},
  "geometry": {"coordinates":[6.890502,50.836502],"type":"Point"}
}