{
  "type": "Feature",
  "properties": {
    "iso:country":"DE",
    "sg:address":"Feldgedinger Str. 20",
    "sg:city":"Olching",
    "sg:phone":"+49 8142/1026",
    "sg:postcode":"82140",
    "sg:province":"Bayern",
    "wof:name":"Mode Sam",
    "wof:placetype":"venue"
},
  "geometry": {"coordinates":[11.382809639,48.220905304],"type":"Point"}
}