{
  "type": "Feature",
  "properties": {
    "iso:country":"DE",
    "sg:address":"Victoriastr. 43",
    "sg:city":"Marl",
    "sg:phone":"+49 2365/400",
    "sg:postcode":"45772",
    "sg:province":"Nordrhein-Westfalen",
    "wof:name":"Redaktion Av Information Gewerkschaft",
    "wof:placetype":"venue"
},
  "geometry": {"coordinates":[7.13337183,51.6664772034],"type":"Point"}
}