{
  "type": "Feature",
  "properties": {
    "iso:country":"DE",
    "sg:address":"Auf der Alm 24",
    "sg:city":"Baden-Baden",
    "sg:phone":"+49 7223/57045",
    "sg:postcode":"76534",
    "sg:province":"Baden-W\u00fcrttemberg",
    "wof:name":"Hotel Monpti",
    "wof:placetype":"venue"
},
  "geometry": {"coordinates":[8.1842002869,48.7324142456],"type":"Point"}
}