{
  "type": "Feature",
  "properties": {
    "iso:country":"DE",
    "sg:address":"Eckenheimer Landstr. 346",
    "sg:city":"Frankfurt",
    "sg:phone":"+49 69/542172",
    "sg:postcode":"60435",
    "sg:province":"Hessen",
    "wof:name":"King Creole",
    "wof:placetype":"venue"
},
  "geometry": {"coordinates":[8.6808071136,50.1495780945],"type":"Point"}
}