{
  "type": "Feature",
  "properties": {
    "iso:country":"DE",
    "sg:address":"Goebenstr. 1",
    "sg:city":"L\u00fcbeck",
    "sg:phone":"+49 451/610920",
    "sg:postcode":"23566",
    "sg:province":"Schleswig-Holstein",
    "wof:name":"Wohnungsbaugesellschaft Bauh\u00fctte L\u00fcbeck Ag",
    "wof:placetype":"venue"
},
  "geometry": {"coordinates":[10.714375,53.867268],"type":"Point"}
}