{
  "type": "Feature",
  "properties": {
    "iso:country":"DE",
    "sg:address":"Isselburger Str. 34",
    "sg:city":"Rees",
    "sg:phone":"+49 2850/257",
    "sg:postcode":"46459",
    "sg:province":"Nordrhein-Westfalen",
    "wof:name":"Theodor Van Den Boom",
    "wof:placetype":"venue"
},
  "geometry": {"coordinates":[6.464956,51.777843],"type":"Point"}
}