{
  "type": "Feature",
  "properties": {
    "iso:country":"DE",
    "sg:address":"Lindenallee 2",
    "sg:city":"Nettetal",
    "sg:phone":"+49 2153/7737",
    "sg:postcode":"41334",
    "sg:province":"Nordrhein-Westfalen",
    "wof:name":"Lindenhof",
    "wof:placetype":"venue"
},
  "geometry": {"coordinates":[6.2484312057,51.3045539856],"type":"Point"}
}