{
  "type": "Feature",
  "properties": {
    "iso:country":"DE",
    "sg:address":"An der Teichbreite 54",
    "sg:city":"Wolfsburg",
    "sg:phone":"+49 5361/61259",
    "sg:postcode":"38448",
    "sg:province":"Niedersachsen",
    "wof:name":"Otto Hau\u00df",
    "wof:placetype":"venue"
},
  "geometry": {"coordinates":[10.8131570816,52.4431304932],"type":"Point"}
}