{
  "type": "Feature",
  "properties": {
    "iso:country":"DE",
    "sg:address":"Dr.-Wilhelm-K\u00fclz-Str. 40",
    "sg:city":"Falkenstein",
    "sg:phone":"+49 3745/4478",
    "sg:postcode":"08223",
    "sg:province":"Sachsen",
    "wof:name":"Vertriebsdienstleistungen F\u00fcr Falkenstein-klingenthal",
    "wof:placetype":"venue"
},
  "geometry": {"coordinates":[12.3685102463,50.4721107483],"type":"Point"}
}