{
  "type": "Feature",
  "properties": {
    "iso:country":"DE",
    "sg:address":"Moizerlitzplatz 22",
    "sg:city":"Regen",
    "sg:phone":"+49 9921/3725",
    "sg:postcode":"94209",
    "sg:province":"Bayern",
    "wof:name":"H. Schnierle",
    "wof:placetype":"venue"
},
  "geometry": {"coordinates":[13.129704,48.968849],"type":"Point"}
}