{
  "type": "Feature",
  "properties": {
    "iso:country":"DE",
    "sg:address":"Brockweg 134",
    "sg:city":"G\u00fctersloh",
    "sg:phone":"+49 5241/51860",
    "sg:postcode":"33332",
    "sg:province":"Nordrhein-Westfalen",
    "wof:name":"Wickord Immobilien Beteiligungs Gmbh",
    "wof:placetype":"venue"
},
  "geometry": {"coordinates":[8.37479,51.887909],"type":"Point"}
}