{
  "type": "Feature",
  "properties": {
    "iso:country":"DE",
    "sg:address":"Heegbarg 14",
    "sg:city":"Hamburg",
    "sg:postcode":"22391",
    "sg:province":"Hamburg",
    "wof:name":"Firma/name:",
    "wof:placetype":"venue"
},
  "geometry": {"coordinates":[10.0925712585,53.6539382935],"type":"Point"}
}