{
  "type": "Feature",
  "properties": {
    "iso:country":"DE",
    "sg:address":"Gro\u00df-Ziethener Chaussee 17",
    "sg:city":"Berlin",
    "sg:phone":"+49 30/6635037",
    "sg:postcode":"12355",
    "sg:province":"Berlin",
    "wof:name":"Praxis Gutzmann Und Von Kalckreuth",
    "wof:placetype":"venue"
},
  "geometry": {"coordinates":[13.494866,52.414818],"type":"Point"}
}