{
  "type": "Feature",
  "properties": {
    "iso:country":"DE",
    "sg:address":"Fabrikstr. 3",
    "sg:city":"Sch\u00f6ningen",
    "sg:phone":"+49 5352/4069",
    "sg:postcode":"38364",
    "sg:province":"Niedersachsen",
    "wof:name":"Ff Hansa Feinkost Gmbh",
    "wof:placetype":"venue"
},
  "geometry": {"coordinates":[10.977183342,52.1362762451],"type":"Point"}
}