{
  "type": "Feature",
  "properties": {
    "iso:country":"DE",
    "sg:address":"Wulwerskammer 8 a",
    "sg:city":"B\u00fcren",
    "sg:phone":"+49 2951/6878",
    "sg:postcode":"33142",
    "sg:province":"Nordrhein-Westfalen",
    "wof:name":"J. Kotzorek",
    "wof:placetype":"venue"
},
  "geometry": {"coordinates":[8.5915908813,51.578994751],"type":"Point"}
}