{
  "type": "Feature",
  "properties": {
    "iso:country":"DE",
    "sg:address":"Lengericher Landstr. 48",
    "sg:city":"Osnabr\u00fcck",
    "sg:phone":"+49 541/442417",
    "sg:postcode":"49078",
    "sg:province":"Niedersachsen",
    "wof:name":"Venus W\u00e4rmetechnik Gmbh",
    "wof:placetype":"venue"
},
  "geometry": {"coordinates":[7.9863967896,52.2525482178],"type":"Point"}
}