{
  "type": "Feature",
  "properties": {
    "iso:country":"DE",
    "sg:address":"79183",
    "sg:city":"Waldkirch",
    "sg:phone":"+49 7681/24147",
    "sg:postcode":"79183",
    "sg:province":"Baden-W\u00fcrttemberg",
    "wof:name":"Gemeindeb\u00fccherei Schule",
    "wof:placetype":"venue"
},
  "geometry": {"coordinates":[7.96427,48.096008],"type":"Point"}
}