{
  "type": "Feature",
  "properties": {
    "iso:country":"DE",
    "sg:address":"Rudower Chaussee 29",
    "sg:city":"Berlin",
    "sg:postcode":"12489",
    "sg:province":"Berlin",
    "wof:name":"Gesenog Gesellschaft F\u00fcr Energieoptimierung Und",
    "wof:placetype":"venue"
},
  "geometry": {"coordinates":[13.528094,52.42889],"type":"Point"}
}