{
  "type": "Feature",
  "properties": {
    "iso:country":"DE",
    "sg:address":"Hermann-L\u00f6ns-Str. 14",
    "sg:city":"Lohmar",
    "sg:phone":"+49 2246/300735",
    "sg:postcode":"53797",
    "sg:province":"Nordrhein-Westfalen",
    "wof:name":"W. Setzepfand Makler",
    "wof:placetype":"venue"
},
  "geometry": {"coordinates":[7.2143659592,50.8376579285],"type":"Point"}
}