{
  "type": "Feature",
  "properties": {
    "iso:country":"DE",
    "sg:address":"Gr\u00e4terstr. 12",
    "sg:city":"Ludwigsburg",
    "sg:phone":"+49 7141/52511",
    "sg:postcode":"71642",
    "sg:province":"Baden-W\u00fcrttemberg",
    "wof:name":"Honold Broneske Huttenlocher",
    "wof:placetype":"venue"
},
  "geometry": {"coordinates":[9.2290620804,48.9096298218],"type":"Point"}
}