{
  "type": "Feature",
  "properties": {
    "iso:country":"DE",
    "sg:address":"Muehlenstr. 34",
    "sg:city":"Melsungen",
    "sg:phone":"+49 5661",
    "sg:postcode":"34212",
    "sg:province":"Hessen",
    "wof:name":"Neunes Internet Marketing",
    "wof:placetype":"venue"
},
  "geometry": {"coordinates":[9.5431070328,51.1326332092],"type":"Point"}
}