{
  "type": "Feature",
  "properties": {
    "iso:country":"DE",
    "sg:address":"J\u00e4gerstr. 16",
    "sg:city":"R\u00f6dermark",
    "sg:phone":"+49 6074/960650",
    "sg:postcode":"63322",
    "sg:province":"Hessen",
    "wof:name":"Ruth Maschke Rechtsanw\u00e4ltin",
    "wof:placetype":"venue"
},
  "geometry": {"coordinates":[8.8165512085,50.0044708252],"type":"Point"}
}