{
  "type": "Feature",
  "properties": {
    "iso:country":"DE",
    "sg:address":"Hindenburgplatz 22",
    "sg:city":"M\u00fcnster",
    "sg:phone":"+49 251/46526",
    "sg:postcode":"48143",
    "sg:province":"Nordrhein-Westfalen",
    "wof:name":"Meier-bornkamp Und Horstmann Rechtsanw\u00e4lte",
    "wof:placetype":"venue"
},
  "geometry": {"coordinates":[7.6179418564,51.9633598328],"type":"Point"}
}