{
  "type": "Feature",
  "properties": {
    "iso:country":"DE",
    "sg:address":"Chemnitzer Str. 5",
    "sg:city":"Stuttgart",
    "sg:phone":"+49 711/7261850",
    "sg:postcode":"70597",
    "sg:province":"Baden-W\u00fcrttemberg",
    "wof:name":"Dieruff Gmbh",
    "wof:placetype":"venue"
},
  "geometry": {"coordinates":[9.164912,48.739162],"type":"Point"}
}