{
  "type": "Feature",
  "properties": {
    "iso:country":"DE",
    "sg:address":"Arnold-Sommerfeld-Ring 6",
    "sg:city":"Baesweiler",
    "sg:phone":"+49 4924/014380",
    "sg:postcode":"52499",
    "sg:province":"Nordrhein-Westfalen",
    "wof:name":"Felten Metallbau",
    "wof:placetype":"venue"
},
  "geometry": {"coordinates":[6.1724619865,50.9179267883],"type":"Point"}
}