{
  "type": "Feature",
  "properties": {
    "iso:country":"DE",
    "sg:address":"Wallstr. 18",
    "sg:city":"Oldenburg",
    "sg:phone":"+49 441/26981",
    "sg:postcode":"26122",
    "sg:province":"Niedersachsen",
    "wof:name":"Spezi Gmbh",
    "wof:placetype":"venue"
},
  "geometry": {"coordinates":[8.2117700577,53.1423377991],"type":"Point"}
}