{
  "type": "Feature",
  "properties": {
    "iso:country":"DE",
    "sg:address":"Am Wenauer Hof 19 a",
    "sg:city":"Merzenich",
    "sg:phone":"+49 2275/4010",
    "sg:postcode":"52399",
    "sg:province":"Nordrhein-Westfalen",
    "wof:name":"Klara Kuss & Sohn Ohg",
    "wof:placetype":"venue"
},
  "geometry": {"coordinates":[6.5787,50.838959],"type":"Point"}
}