{
  "type": "Feature",
  "properties": {
    "iso:country":"DE",
    "sg:address":"Kirchstr. 35",
    "sg:city":"G\u00e4rtringen",
    "sg:phone":"+49 7034/28372",
    "sg:postcode":"71116",
    "sg:province":"Baden-W\u00fcrttemberg",
    "wof:name":"Kosmetik Am Marktplatz",
    "wof:placetype":"venue"
},
  "geometry": {"coordinates":[8.896286,48.641163],"type":"Point"}
}