{
  "type": "Feature",
  "properties": {
    "iso:country":"DE",
    "sg:address":"Neckartalstr. 4",
    "sg:city":"Reutlingen",
    "sg:phone":"+49 4971/2190090",
    "sg:postcode":"72768",
    "sg:province":"Baden-W\u00fcrttemberg",
    "wof:name":"Dieter Vogel Gmbh",
    "wof:placetype":"venue"
},
  "geometry": {"coordinates":[9.17884,48.551109],"type":"Point"}
}