{
  "type": "Feature",
  "properties": {
    "iso:country":"DE",
    "sg:address":"Wei\u00dfer Str. 2",
    "sg:city":"K\u00f6ln",
    "sg:phone":"+49 221/393993",
    "sg:postcode":"50996",
    "sg:province":"Nordrhein-Westfalen",
    "wof:name":"Elektro Parsch Gmbh",
    "wof:placetype":"venue"
},
  "geometry": {"coordinates":[6.9975471497,50.8907546997],"type":"Point"}
}