{
  "type": "Feature",
  "properties": {
    "iso:country":"DE",
    "sg:address":"Singerhoffstr. 1",
    "sg:city":"Dortmund",
    "sg:phone":"+49 231/710334",
    "sg:postcode":"44225",
    "sg:province":"Nordrhein-Westfalen",
    "wof:name":"Maedys",
    "wof:placetype":"venue"
},
  "geometry": {"coordinates":[7.437361,51.475361],"type":"Point"}
}