{
  "type": "Feature",
  "properties": {
    "iso:country":"DE",
    "sg:address":"Vor dem Tor 24",
    "sg:city":"Eiterfeld",
    "sg:postcode":"36132",
    "sg:province":"Hessen",
    "wof:name":"Gemeindeb\u00fccherei Ufhausen",
    "wof:placetype":"venue"
},
  "geometry": {"coordinates":[9.8617,50.776039],"type":"Point"}
}