{
  "type": "Feature",
  "properties": {
    "iso:country":"DE",
    "sg:address":"Essener Str. 21",
    "sg:city":"Hattingen",
    "sg:postcode":"45529",
    "sg:province":"Nordrhein-Westfalen",
    "wof:name":"Annegret Walder E. K.",
    "wof:placetype":"venue"
},
  "geometry": {"coordinates":[7.137419,51.404446],"type":"Point"}
}