{
  "type": "Feature",
  "properties": {
    "iso:country":"DE",
    "sg:address":"Thurnstein 2",
    "sg:city":"Postm\u00fcnster",
    "sg:postcode":"84389",
    "sg:province":"Bayern",
    "wof:name":"Andreas Otto",
    "wof:placetype":"venue"
},
  "geometry": {"coordinates":[12.906941,48.415531],"type":"Point"}
}