{
  "type": "Feature",
  "properties": {
    "iso:country":"DE",
    "sg:address":"Vor der Stephanskuppe 1",
    "sg:city":"Sinntal",
    "sg:phone":"+49 6664/1339",
    "sg:postcode":"36391",
    "sg:province":"Hessen",
    "wof:name":"Wolfgang Roth Heilpraktiker",
    "wof:placetype":"venue"
},
  "geometry": {"coordinates":[9.6309146881,50.3141708374],"type":"Point"}
}