{
  "type": "Feature",
  "properties": {
    "iso:country":"DE",
    "sg:address":"An der Lauterhecke 8",
    "sg:city":"Niederwerrn",
    "sg:phone":"+49 9726/3516",
    "sg:postcode":"97464",
    "sg:province":"Bayern",
    "wof:name":"H. Schreier",
    "wof:placetype":"venue"
},
  "geometry": {"coordinates":[10.164144,50.074104],"type":"Point"}
}