{
  "type": "Feature",
  "properties": {
    "iso:country":"DE",
    "sg:address":"Wehamer Str. 10",
    "sg:city":"Aresing",
    "sg:phone":"+49 8252/83813",
    "sg:postcode":"86561",
    "sg:province":"Bayern",
    "wof:name":"Georg Haas",
    "wof:placetype":"venue"
},
  "geometry": {"coordinates":[11.302923,48.533958],"type":"Point"}
}