{
  "type": "Feature",
  "properties": {
    "iso:country":"DE",
    "sg:address":"Jupiterstr. 22",
    "sg:city":"Kaarst",
    "sg:phone":"+49 2131/65698",
    "sg:postcode":"41564",
    "sg:province":"Nordrhein-Westfalen",
    "wof:name":"Oliver Dresser Immobilienmakler",
    "wof:placetype":"venue"
},
  "geometry": {"coordinates":[6.63397789,51.2251815796],"type":"Point"}
}