{
  "type": "Feature",
  "properties": {
    "iso:country":"DE",
    "sg:address":"Decksteiner Str. 73",
    "sg:city":"K\u00f6ln",
    "sg:phone":"+49 221/9439865",
    "sg:postcode":"50935",
    "sg:province":"Nordrhein-Westfalen",
    "wof:name":"J\u00fcrgen Reismann Architekt",
    "wof:placetype":"venue"
},
  "geometry": {"coordinates":[6.899872,50.917187],"type":"Point"}
}