{
  "type": "Feature",
  "properties": {
    "iso:country":"DE",
    "sg:address":"Hauptstr. 137",
    "sg:city":"Merchweiler",
    "sg:phone":"+49 6825/7315",
    "sg:postcode":"66589",
    "sg:province":"Saarland",
    "wof:name":"Handelshof",
    "wof:placetype":"venue"
},
  "geometry": {"coordinates":[7.0574688911,49.357963562],"type":"Point"}
}