{
  "type": "Feature",
  "properties": {
    "iso:country":"DE",
    "sg:address":"M\u00fcnchener Str. 10",
    "sg:city":"Feldkirchen-Westerham",
    "sg:phone":"+49 8063/83580",
    "sg:postcode":"83620",
    "sg:province":"Bayern",
    "wof:name":"Hotel-restaurant Mareis",
    "wof:placetype":"venue"
},
  "geometry": {"coordinates":[11.8437871933,47.9095916748],"type":"Point"}
}