{
  "type": "Feature",
  "properties": {
    "iso:country":"DE",
    "sg:address":"Siemensstr. 8a",
    "sg:city":"Diedorf",
    "sg:postcode":"86420",
    "sg:province":"Bayern",
    "wof:name":"Masino Einrichtung Und Objektdesign Gmbh",
    "wof:placetype":"venue"
},
  "geometry": {"coordinates":[10.7968034744,48.3595695496],"type":"Point"}
}