{
  "type": "Feature",
  "properties": {
    "iso:country":"DE",
    "sg:address":"Methfesselstr. 1",
    "sg:city":"Bad Gandersheim",
    "sg:phone":"+49 5563/910411",
    "sg:postcode":"37581",
    "sg:province":"Niedersachsen",
    "wof:name":"J\u00fcrgen Gehrke",
    "wof:placetype":"venue"
},
  "geometry": {"coordinates":[9.9656257629,51.885848999],"type":"Point"}
}