{
  "type": "Feature",
  "properties": {
    "iso:country":"DE",
    "sg:address":"Gewerbestra\u00dfe Eula-West 5",
    "sg:city":"Borna",
    "sg:phone":"+49 3433/915921",
    "sg:postcode":"04552",
    "sg:province":"Sachsen",
    "wof:name":"Vme Verbraucher- Markt Eula Gmbh",
    "wof:placetype":"venue"
},
  "geometry": {"coordinates":[12.4996595383,51.1245193481],"type":"Point"}
}