{
  "type": "Feature",
  "properties": {
    "iso:country":"DE",
    "sg:address":"Mindelheimer Str. 141",
    "sg:city":"Kaufbeuren",
    "sg:phone":"+49 8341/93840",
    "sg:postcode":"87600",
    "sg:province":"Bayern",
    "wof:name":"H\u00d6gg Anlagenpflege Gmbh",
    "wof:placetype":"venue"
},
  "geometry": {"coordinates":[10.609605,47.901909],"type":"Point"}
}