{
  "type": "Feature",
  "properties": {
    "iso:country":"DE",
    "sg:address":"Max-Joseph-Str. 5",
    "sg:city":"M\u00fcnchen",
    "sg:postcode":"80333",
    "sg:province":"Bayern",
    "wof:name":"Rs Rating Services Ag",
    "wof:placetype":"venue"
},
  "geometry": {"coordinates":[11.569837,48.143425],"type":"Point"}
}