{
  "type": "Feature",
  "properties": {
    "iso:country":"DE",
    "sg:address":"Stratmanns Weg 4",
    "sg:city":"Waltrop",
    "sg:phone":"+49 2309/921422",
    "sg:postcode":"45731",
    "sg:province":"Nordrhein-Westfalen",
    "wof:name":"Fliesenfachgesch\u00e4ft Kreimeyer Inh.: Bernd Kreimeyer E. K.",
    "wof:placetype":"venue"
},
  "geometry": {"coordinates":[7.4189238548,51.626285553],"type":"Point"}
}