{
  "type": "Feature",
  "properties": {
    "iso:country":"DE",
    "sg:address":"Wallerfangerstr. 102",
    "sg:city":"Saarlouis",
    "sg:phone":"+49 6831",
    "sg:postcode":"66740",
    "sg:province":"Saarland",
    "wof:name":"Autohaus Klein Gmbh",
    "wof:placetype":"venue"
},
  "geometry": {"coordinates":[6.7361960411,49.3174743652],"type":"Point"}
}