{
  "type": "Feature",
  "properties": {
    "iso:country":"DE",
    "sg:address":"Auer Str. 1b",
    "sg:city":"Schwarzenberg",
    "sg:phone":"+49 3774/17000",
    "sg:postcode":"08340",
    "sg:province":"Sachsen",
    "wof:name":"I-center Elektrogro\u00dfhandel Obererzgebirge Gmbh",
    "wof:placetype":"venue"
},
  "geometry": {"coordinates":[12.7595911026,50.5498542786],"type":"Point"}
}