{
  "type": "Feature",
  "properties": {
    "iso:country":"DE",
    "sg:address":"Mosen 55",
    "sg:city":"W\u00fcnschendorf",
    "sg:phone":"+49 36603/88580",
    "sg:postcode":"07570",
    "sg:province":"Th\u00fcringen",
    "wof:name":"Egon Wuckelt",
    "wof:placetype":"venue"
},
  "geometry": {"coordinates":[12.121266,50.790455],"type":"Point"}
}