{
  "type": "Feature",
  "properties": {
    "iso:country":"DE",
    "sg:address":"Gutenbergstr. 8",
    "sg:city":"Kriftel",
    "sg:postcode":"65830",
    "sg:province":"Hessen",
    "wof:name":"Werner Verlag Verwaltungsgesellschaft Mbh",
    "wof:placetype":"venue"
},
  "geometry": {"coordinates":[8.477416,50.079414],"type":"Point"}
}