{
  "type": "Feature",
  "properties": {
    "iso:country":"DE",
    "sg:address":"zu den Muehlen 18 A+B",
    "sg:city":"Perl/Besch",
    "sg:phone":"+49 6875/851",
    "sg:postcode":"66706",
    "sg:province":"Saarland",
    "wof:name":"Heinz Motschall Gmbh",
    "wof:placetype":"venue"
},
  "geometry": {"coordinates":[6.3890948296,49.4751205444],"type":"Point"}
}