{
  "type": "Feature",
  "properties": {
    "iso:country":"DE",
    "sg:address":"Zossener Str.",
    "sg:city":"Trebbin",
    "sg:phone":"+49 337318081014",
    "sg:postcode":"14959",
    "sg:province":"Brandenburg",
    "wof:name":"Transportbetonwerk Trebbin- Beteiligungs Gmbh",
    "wof:placetype":"venue"
},
  "geometry": {"coordinates":[13.23264,52.215004],"type":"Point"}
}