{
  "type": "Feature",
  "properties": {
    "iso:country":"DE",
    "sg:address":"Sommerhalde 24",
    "sg:city":"Bad D\u00fcrrheim",
    "sg:phone":"+49 7726/7774",
    "sg:postcode":"78073",
    "sg:province":"Baden-W\u00fcrttemberg",
    "wof:name":"H. Mehne Wirtschaftspr\u00fcfer",
    "wof:placetype":"venue"
},
  "geometry": {"coordinates":[8.5655403137,48.0309524536],"type":"Point"}
}