{
  "type": "Feature",
  "properties": {
    "iso:country":"DE",
    "sg:address":"Barnerstr. 30",
    "sg:city":"Hamburg",
    "sg:phone":"+49 40/397703",
    "sg:postcode":"22765",
    "sg:province":"Hamburg",
    "wof:name":"Gebr. Todt",
    "wof:placetype":"venue"
},
  "geometry": {"coordinates":[9.929544,53.556622],"type":"Point"}
}