{
  "type": "Feature",
  "properties": {
    "iso:country":"DE",
    "sg:address":"Altes Dorf 15",
    "sg:city":"Schkeuditz",
    "sg:phone":"+49 34204/62687",
    "sg:postcode":"04435",
    "sg:province":"Sachsen",
    "wof:name":"Rudolf Just",
    "wof:placetype":"venue"
},
  "geometry": {"coordinates":[12.2456579208,51.3878517151],"type":"Point"}
}