{
  "type": "Feature",
  "properties": {
    "iso:country":"DE",
    "sg:address":"Gartenweg 30",
    "sg:city":"Mosbach",
    "sg:phone":"+49 6261/4443",
    "sg:postcode":"74821",
    "sg:province":"Baden-W\u00fcrttemberg",
    "wof:name":"Wilfried Pape Rechtsanwalt",
    "wof:placetype":"venue"
},
  "geometry": {"coordinates":[9.1452302933,49.3535614014],"type":"Point"}
}