{
  "type": "Feature",
  "properties": {
    "iso:country":"DE",
    "sg:address":"An der Hohl 15",
    "sg:city":"Weilrod",
    "sg:phone":"+49 6083/1043",
    "sg:postcode":"61276",
    "sg:province":"Hessen",
    "wof:name":"Christa Brem Heilpraktikerin",
    "wof:placetype":"venue"
},
  "geometry": {"coordinates":[8.424079895,50.3181800842],"type":"Point"}
}