{
  "type": "Feature",
  "properties": {
    "iso:country":"DE",
    "sg:address":"Gisostr. 10",
    "sg:city":"Sch\u00f6ngeising",
    "sg:phone":"+49 8141/327930",
    "sg:postcode":"82296",
    "sg:province":"Bayern",
    "wof:name":"Heymans Verwaltungs Gmbh",
    "wof:placetype":"venue"
},
  "geometry": {"coordinates":[11.202158,48.142776],"type":"Point"}
}