{
  "type": "Feature",
  "properties": {
    "iso:country":"DE",
    "sg:address":"An der Damm\u00fchle 1",
    "sg:city":"Sch\u00f6nfeld",
    "sg:phone":"+49 35248/81980",
    "sg:postcode":"01561",
    "sg:province":"Sachsen",
    "wof:name":"Tth Transport-teichwirtschaft Handel Gmbh",
    "wof:placetype":"venue"
},
  "geometry": {"coordinates":[13.689179,51.286362],"type":"Point"}
}