{
  "type": "Feature",
  "properties": {
    "iso:country":"DE",
    "sg:address":"Robert-Bosch-Str. 1",
    "sg:city":"Homburg",
    "sg:phone":"+49 6841/755540",
    "sg:postcode":"66424",
    "sg:province":"Saarland",
    "wof:name":"Belle Onde",
    "wof:placetype":"venue"
},
  "geometry": {"coordinates":[7.3385601044,49.3290519714],"type":"Point"}
}