{
  "type": "Feature",
  "properties": {
    "iso:country":"DE",
    "sg:address":"Liebenscheider Str. 40",
    "sg:city":"Burbach",
    "sg:phone":"+49 2736/3026",
    "sg:postcode":"57299",
    "sg:province":"Nordrhein-Westfalen",
    "wof:name":"Theodor Stephan Kg",
    "wof:placetype":"venue"
},
  "geometry": {"coordinates":[8.1258583069,50.7063484192],"type":"Point"}
}