{
  "type": "Feature",
  "properties": {
    "iso:country":"DE",
    "sg:address":"Moosstr. 13",
    "sg:city":"Tettnang",
    "sg:phone":"+49 7542/7592",
    "sg:postcode":"88069",
    "sg:province":"Baden-W\u00fcrttemberg",
    "wof:name":"Hermann Hinderhofer",
    "wof:placetype":"venue"
},
  "geometry": {"coordinates":[9.584843,47.674377],"type":"Point"}
}