{
  "type": "Feature",
  "properties": {
    "iso:country":"DE",
    "sg:address":"Bahnhofstr. 10",
    "sg:city":"Schladen",
    "sg:phone":"+49 4953/35378",
    "sg:postcode":"38315",
    "sg:province":"Niedersachsen",
    "wof:name":"Sparkasse D. Ldkr. Goslar",
    "wof:placetype":"venue"
},
  "geometry": {"coordinates":[10.546164,52.021671],"type":"Point"}
}