{
  "type": "Feature",
  "properties": {
    "iso:country":"DE",
    "sg:address":"B\u00fcrgerm.-Heukamp-Str.",
    "sg:city":"Cloppenburg",
    "sg:phone":"+49 4471/5711",
    "sg:postcode":"49661",
    "sg:province":"Niedersachsen",
    "wof:name":"Buchdruckerei Ostendorf Gmbh",
    "wof:placetype":"venue"
},
  "geometry": {"coordinates":[8.040692,52.846203],"type":"Point"}
}