{
  "type": "Feature",
  "properties": {
    "iso:country":"DE",
    "sg:address":"Cusanusstr. 14",
    "sg:city":"Bernkastel-Kues",
    "sg:phone":"+49 6531/91290",
    "sg:postcode":"54470",
    "sg:province":"Rheinland-Pfalz",
    "wof:name":"Thomas Lutz",
    "wof:placetype":"venue"
},
  "geometry": {"coordinates":[7.0693712234,49.9175338745],"type":"Point"}
}