{
  "type": "Feature",
  "properties": {
    "iso:country":"DE",
    "sg:address":"Siemensstr. 19",
    "sg:city":"Hilden",
    "sg:phone":"+49 2103/985760",
    "sg:postcode":"40721",
    "sg:province":"Nordrhein-Westfalen",
    "wof:name":"Cvo Edv Beratung Und Realisation Gmbh",
    "wof:placetype":"venue"
},
  "geometry": {"coordinates":[6.9237542152,51.1624183655],"type":"Point"}
}