{
  "type": "Feature",
  "properties": {
    "iso:country":"DE",
    "sg:address":"M\u00fchlenweg 17",
    "sg:city":"Wuppertal",
    "sg:phone":"+49 202/5644988",
    "sg:postcode":"42275",
    "sg:province":"Nordrhein-Westfalen",
    "wof:name":"Vorwerk Teppichwerke Gmbh & Co. Kg",
    "wof:placetype":"venue"
},
  "geometry": {"coordinates":[7.2001028061,51.2735481262],"type":"Point"}
}