{
  "type": "Feature",
  "properties": {
    "iso:country":"DE",
    "sg:address":"Urbanstr. 34",
    "sg:city":"Plochingen",
    "sg:phone":"+49 4922/4283808",
    "sg:postcode":"73207",
    "sg:province":"Baden-W\u00fcrttemberg",
    "wof:name":"Karl Kock Gmbh",
    "wof:placetype":"venue"
},
  "geometry": {"coordinates":[7.2638020515,50.784702301],"type":"Point"}
}