{
  "type": "Feature",
  "properties": {
    "iso:country":"DE",
    "sg:address":"Robert-Schumann-Weg 10",
    "sg:city":"Oberhausen",
    "sg:phone":"+49 208/605544",
    "sg:postcode":"46145",
    "sg:province":"Nordrhein-Westfalen",
    "wof:name":"De Witt Baumaschinen Gmbh",
    "wof:placetype":"venue"
},
  "geometry": {"coordinates":[6.863852,51.535053],"type":"Point"}
}