{
  "type": "Feature",
  "properties": {
    "iso:country":"DE",
    "sg:address":"Rascher Str. 5",
    "sg:city":"Altdorf",
    "sg:phone":"+49 9187/2848",
    "sg:postcode":"90518",
    "sg:province":"Bayern",
    "wof:name":"C. Klebusch",
    "wof:placetype":"venue"
},
  "geometry": {"coordinates":[11.3863096237,49.3931884766],"type":"Point"}
}