{
  "type": "Feature",
  "properties": {
    "iso:country":"DE",
    "sg:address":"Steinforststr. 36",
    "sg:city":"Erlangen",
    "sg:phone":"+49 9131/440251",
    "sg:postcode":"91056",
    "sg:province":"Bayern",
    "wof:name":"Stefan Kr\u00e4geloh Ingenieur",
    "wof:placetype":"venue"
},
  "geometry": {"coordinates":[10.9781236649,49.6018791199],"type":"Point"}
}