{
  "type": "Feature",
  "properties": {
    "iso:country":"DE",
    "sg:address":"S\u00fcdstr. 1 a",
    "sg:city":"Velbert",
    "sg:phone":"+49 2051/253321",
    "sg:postcode":"42551",
    "sg:province":"Nordrhein-Westfalen",
    "wof:name":"Im St\u00e4llchen",
    "wof:placetype":"venue"
},
  "geometry": {"coordinates":[7.0512170792,51.3356208801],"type":"Point"}
}