{
  "type": "Feature",
  "properties": {
    "iso:country":"DE",
    "sg:address":"Bahnhofstr. 5",
    "sg:city":"Cursdorf",
    "sg:phone":"+49 36705/62262",
    "sg:postcode":"98744",
    "sg:province":"Th\u00fcringen",
    "wof:name":"Georg Lattermann",
    "wof:placetype":"venue"
},
  "geometry": {"coordinates":[11.129729,50.5718],"type":"Point"}
}