{
  "type": "Feature",
  "properties": {
    "iso:country":"DE",
    "sg:address":"Poststr. 83",
    "sg:city":"Eisenh\u00fcttenstadt",
    "sg:phone":"+49 3364/44990",
    "sg:postcode":"15890",
    "sg:province":"Brandenburg",
    "wof:name":"Walter Oppen",
    "wof:placetype":"venue"
},
  "geometry": {"coordinates":[14.6332960129,52.1320762634],"type":"Point"}
}