{
  "type": "Feature",
  "properties": {
    "iso:country":"DE",
    "sg:address":"Ritterfelddamm 19a",
    "sg:city":"Berlin",
    "sg:phone":"+49 30/36801340",
    "sg:postcode":"14089",
    "sg:province":"Berlin",
    "wof:name":"Mai & S\u00f6hne Produktions- Und Vertriebs Gmbh",
    "wof:placetype":"venue"
},
  "geometry": {"coordinates":[13.1408252716,52.4558334351],"type":"Point"}
}