{
  "type": "Feature",
  "properties": {
    "iso:country":"DE",
    "sg:address":"Weberweg 1",
    "sg:city":"Erkheim",
    "sg:phone":"+49 8336/7398",
    "sg:postcode":"87746",
    "sg:province":"Bayern",
    "wof:name":"Oskar Abr\u00f6ll",
    "wof:placetype":"venue"
},
  "geometry": {"coordinates":[10.335814476,48.0409240723],"type":"Point"}
}