{
  "type": "Feature",
  "properties": {
    "iso:country":"DE",
    "sg:address":"Stuttgarter Str. 50",
    "sg:city":"Rottweil",
    "sg:phone":"+49 741/174370",
    "sg:postcode":"78628",
    "sg:province":"Baden-W\u00fcrttemberg",
    "wof:name":"Gebr. Mayenberger Gmbh",
    "wof:placetype":"venue"
},
  "geometry": {"coordinates":[8.668746,48.130512],"type":"Point"}
}