{
  "type": "Feature",
  "properties": {
    "iso:country":"DE",
    "sg:address":"R\u00f6ntgenstr. 7g",
    "sg:city":"Gro\u00df-Umstadt",
    "sg:phone":"+49 6078/910588",
    "sg:postcode":"64823",
    "sg:province":"Hessen",
    "wof:name":"Lehr",
    "wof:placetype":"venue"
},
  "geometry": {"coordinates":[8.937159,49.868729],"type":"Point"}
}