{
  "type": "Feature",
  "properties": {
    "iso:country":"DE",
    "sg:address":"Am Steig 4",
    "sg:city":"Hauzenberg",
    "sg:phone":"+49 8586/918640",
    "sg:postcode":"94051",
    "sg:province":"Bayern",
    "wof:name":"G. Spreu",
    "wof:placetype":"venue"
},
  "geometry": {"coordinates":[13.6347112656,48.6469802856],"type":"Point"}
}