{
  "type": "Feature",
  "properties": {
    "iso:country":"DE",
    "sg:address":"B\u00fchlstr. 15",
    "sg:city":"Neubulach",
    "sg:postcode":"75387",
    "sg:province":"Baden-W\u00fcrttemberg",
    "wof:name":"Gcm Gmbh German Clothing & Machinery",
    "wof:placetype":"venue"
},
  "geometry": {"coordinates":[8.6832609177,48.6650161743],"type":"Point"}
}