{
  "type": "Feature",
  "properties": {
    "iso:country":"DE",
    "sg:address":"Grabengasse 1",
    "sg:city":"Heidelberg",
    "sg:phone":"+49 6221/20410",
    "sg:postcode":"69117",
    "sg:province":"Baden-W\u00fcrttemberg",
    "wof:name":"E. Heimann",
    "wof:placetype":"venue"
},
  "geometry": {"coordinates":[8.7060003281,49.4111328125],"type":"Point"}
}