{
  "type": "Feature",
  "properties": {
    "iso:country":"DE",
    "sg:address":"Wallenbrock 21",
    "sg:city":"Westerkappeln",
    "sg:phone":"+49 5404/2989",
    "sg:postcode":"49492",
    "sg:province":"Nordrhein-Westfalen",
    "wof:name":"Emil Hackmann",
    "wof:placetype":"venue"
},
  "geometry": {"coordinates":[7.85302,52.34581],"type":"Point"}
}