{
  "type": "Feature",
  "properties": {
    "iso:country":"DE",
    "sg:address":"Waldstr. 32",
    "sg:city":"Willst\u00e4tt",
    "sg:phone":"+49 7852/2311",
    "sg:postcode":"77731",
    "sg:province":"Baden-W\u00fcrttemberg",
    "wof:name":"Europa-camping Sand",
    "wof:placetype":"venue"
},
  "geometry": {"coordinates":[7.93329,48.54311],"type":"Point"}
}