{
  "type": "Feature",
  "properties": {
    "iso:country":"DE",
    "sg:address":"Berliner Str 24",
    "sg:city":"Murrhardt",
    "sg:phone":"+49 7192/5373",
    "sg:postcode":"71540",
    "sg:province":"Baden-W\u00fcrttemberg",
    "wof:name":"Gehring Bad Gmbh",
    "wof:placetype":"venue"
},
  "geometry": {"coordinates":[9.558922,48.983528],"type":"Point"}
}