{
  "type": "Feature",
  "properties": {
    "iso:country":"DE",
    "sg:address":"Im Sch\u00fctzengrund 72",
    "sg:city":"Neuwied",
    "sg:phone":"+49 2622/2646",
    "sg:postcode":"56566",
    "sg:province":"Rheinland-Pfalz",
    "wof:name":"Polster Mit Pep Desinger Gmbh",
    "wof:placetype":"venue"
},
  "geometry": {"coordinates":[7.5273308754,50.4285888672],"type":"Point"}
}