{
  "type": "Feature",
  "properties": {
    "iso:country":"DE",
    "sg:address":"Kruppstr. 12",
    "sg:city":"Dormagen",
    "sg:phone":"+49 2133/62951",
    "sg:postcode":"41540",
    "sg:province":"Nordrhein-Westfalen",
    "wof:name":"Heinz Kropp",
    "wof:placetype":"venue"
},
  "geometry": {"coordinates":[6.830534935,51.0615158081],"type":"Point"}
}