{
  "type": "Feature",
  "properties": {
    "iso:country":"DE",
    "sg:address":"Michael-Burgau-Str. 28",
    "sg:city":"Regensburg",
    "sg:phone":"+49 941/33147",
    "sg:postcode":"93049",
    "sg:province":"Bayern",
    "wof:name":"Siegfried Brunner",
    "wof:placetype":"venue"
},
  "geometry": {"coordinates":[12.0605478287,49.0184288025],"type":"Point"}
}