{
  "type": "Feature",
  "properties": {
    "iso:country":"DE",
    "sg:address":"Johann-von-Hieber-Str. 11",
    "sg:city":"Welzheim",
    "sg:phone":"+49 7182/8805",
    "sg:postcode":"73642",
    "sg:province":"Baden-W\u00fcrttemberg",
    "wof:name":"Ev. Pfarramt Ii",
    "wof:placetype":"venue"
},
  "geometry": {"coordinates":[9.6331062317,48.8760910034],"type":"Point"}
}