{
  "type": "Feature",
  "properties": {
    "iso:country":"DE",
    "sg:address":"Michelfelder Str. 1",
    "sg:city":"Schw\u00e4bisch Hall",
    "sg:phone":"+49 791/951950",
    "sg:postcode":"74523",
    "sg:province":"Baden-W\u00fcrttemberg",
    "wof:name":"Jurt Laun",
    "wof:placetype":"venue"
},
  "geometry": {"coordinates":[9.6876878738,49.0819587708],"type":"Point"}
}