{
  "type": "Feature",
  "properties": {
    "iso:country":"DE",
    "sg:address":"Auf Probert 38",
    "sg:city":"Wiltingen",
    "sg:postcode":"54459",
    "sg:province":"Rheinland-Pfalz",
    "wof:name":"Ferienwohnung In Wiltingen / Trier",
    "wof:placetype":"venue"
},
  "geometry": {"coordinates":[6.597166,49.654816],"type":"Point"}
}