{
  "type": "Feature",
  "properties": {
    "iso:country":"DE",
    "sg:address":"Hohenlohestr. 2",
    "sg:city":"Schillingsf\u00fcrst",
    "sg:phone":"+49 9868/224",
    "sg:postcode":"91583",
    "sg:province":"Bayern",
    "wof:name":"Ev. Luth. Pfarramt",
    "wof:placetype":"venue"
},
  "geometry": {"coordinates":[10.2620267868,49.2871208191],"type":"Point"}
}