{
  "type": "Feature",
  "properties": {
    "iso:country":"DE",
    "sg:address":"Am Strehl 89a",
    "sg:city":"Oldenburg",
    "sg:phone":"+49 441/602815",
    "sg:postcode":"26125",
    "sg:province":"Niedersachsen",
    "wof:name":"W. Harms Rechtsanwalt",
    "wof:placetype":"venue"
},
  "geometry": {"coordinates":[8.2094335556,53.1959953308],"type":"Point"}
}