{
  "type": "Feature",
  "properties": {
    "iso:country":"DE",
    "sg:address":"Bergstr. 14",
    "sg:city":"Ehekirchen",
    "sg:phone":"+49 8253/1727",
    "sg:postcode":"86676",
    "sg:province":"Bayern",
    "wof:name":"Robert Fischer",
    "wof:placetype":"venue"
},
  "geometry": {"coordinates":[11.089741,48.610229],"type":"Point"}
}