{
  "type": "Feature",
  "properties": {
    "iso:country":"DE",
    "sg:address":"Dorf 51",
    "sg:city":"Jachenau",
    "sg:phone":"+49 8043/919891",
    "sg:postcode":"83676",
    "sg:province":"Bayern",
    "wof:name":"Ferienort Jachenau In Den Oberbayerischen Alpen",
    "wof:placetype":"venue"
},
  "geometry": {"coordinates":[11.433803,47.605328],"type":"Point"}
}