{
  "type": "Feature",
  "properties": {
    "iso:country":"DE",
    "sg:address":"Lindenstr. 82",
    "sg:city":"Siegburg",
    "sg:phone":"+49 2241/69024",
    "sg:postcode":"53721",
    "sg:province":"Nordrhein-Westfalen",
    "wof:name":"B\u00fcttner",
    "wof:placetype":"venue"
},
  "geometry": {"coordinates":[7.191119194,50.797668457],"type":"Point"}
}