{
  "type": "Feature",
  "properties": {
    "iso:country":"DE",
    "sg:address":"Braunschweiger Tor 4a",
    "sg:city":"Helmstedt",
    "sg:phone":"+49 5351/8812",
    "sg:postcode":"38350",
    "sg:province":"Niedersachsen",
    "wof:name":"Imbi\u00df Kloster-eck",
    "wof:placetype":"venue"
},
  "geometry": {"coordinates":[11.0008602142,52.2292556763],"type":"Point"}
}