{
  "type": "Feature",
  "properties": {
    "iso:country":"DE",
    "sg:address":"In der Hinteren Au 3",
    "sg:city":"Badenweiler",
    "sg:phone":"+49 7632/348",
    "sg:postcode":"79410",
    "sg:province":"Baden-W\u00fcrttemberg",
    "wof:name":"Dr. Med. Helgard Scherf Arzt F\u00fcr Innere Medizin",
    "wof:placetype":"venue"
},
  "geometry": {"coordinates":[7.666779995,47.7948265076],"type":"Point"}
}