{
  "type": "Feature",
  "properties": {
    "iso:country":"DE",
    "sg:address":"Breslauer Str. 15",
    "sg:city":"Quakenbr\u00fcck",
    "sg:phone":"+49 5431/6746",
    "sg:postcode":"49610",
    "sg:province":"Niedersachsen",
    "wof:name":"Ambulantes Gesundheitszentrum Artland Gmbh",
    "wof:placetype":"venue"
},
  "geometry": {"coordinates":[7.940875,52.669868],"type":"Point"}
}