{
  "type": "Feature",
  "properties": {
    "iso:country":"DE",
    "sg:address":"Hafenstr.",
    "sg:city":"Saarbr\u00fccken",
    "sg:phone":"+49 681/32483",
    "sg:postcode":"66111",
    "sg:province":"Saarland",
    "wof:name":"Tabak Schulz Heinrich Schulz",
    "wof:placetype":"venue"
},
  "geometry": {"coordinates":[6.9896121025,49.2375526428],"type":"Point"}
}