{
  "type": "Feature",
  "properties": {
    "iso:country":"DE",
    "sg:address":"R\u00f6merberg 23",
    "sg:city":"Brensbach",
    "sg:phone":"+49 6161/477",
    "sg:postcode":"64395",
    "sg:province":"Hessen",
    "wof:name":"Adolf Schimmer",
    "wof:placetype":"venue"
},
  "geometry": {"coordinates":[8.8819093704,49.7715606689],"type":"Point"}
}