{
  "type": "Feature",
  "properties": {
    "iso:country":"DE",
    "sg:address":"Niendorf I 25",
    "sg:city":"R\u00f6mstedt",
    "sg:postcode":"29591",
    "sg:province":"Niedersachsen",
    "wof:name":"W. Je\u00df",
    "wof:placetype":"venue"
},
  "geometry": {"coordinates":[10.6523342133,53.0958709717],"type":"Point"}
}