{
  "type": "Feature",
  "properties": {
    "iso:country":"DE",
    "sg:address":"Inselstr. 20",
    "sg:city":"D\u00fcsseldorf",
    "sg:postcode":"40479",
    "sg:province":"Nordrhein-Westfalen",
    "wof:name":"Extracta Beteiligungs-gmbh",
    "wof:placetype":"venue"
},
  "geometry": {"coordinates":[6.776225,51.233444],"type":"Point"}
}