{
  "type": "Feature",
  "properties": {
    "iso:country":"DE",
    "sg:address":"Steinheide 4",
    "sg:city":"Bad Salzuflen",
    "sg:phone":"+49 5208/7360",
    "sg:postcode":"32107",
    "sg:province":"Nordrhein-Westfalen",
    "wof:name":"Wilhelm S\u00e4ger",
    "wof:placetype":"venue"
},
  "geometry": {"coordinates":[8.686591,52.056316],"type":"Point"}
}