{
  "type": "Feature",
  "properties": {
    "iso:country":"DE",
    "sg:address":"Kirchenstr. 8",
    "sg:city":"Brannenburg",
    "sg:phone":"+49 8034/3172",
    "sg:postcode":"83098",
    "sg:province":"Bayern",
    "wof:name":"\u00d6ffentl. B\u00fccherei",
    "wof:placetype":"venue"
},
  "geometry": {"coordinates":[12.103968,47.736046],"type":"Point"}
}