{
  "type": "Feature",
  "properties": {
    "iso:country":"DE",
    "sg:address":"Prinzregentenplatz 11",
    "sg:city":"M\u00fcnchen",
    "sg:phone":"+49 89/41242830",
    "sg:postcode":"81675",
    "sg:province":"Bayern",
    "wof:name":"Arcap Beteiligungsverwaltung Gmbh & Co. Columbus",
    "wof:placetype":"venue"
},
  "geometry": {"coordinates":[11.605955,48.13982],"type":"Point"}
}