{
  "type": "Feature",
  "properties": {
    "iso:country":"DE",
    "sg:address":"Oberstr. 46",
    "sg:city":"Bacharach",
    "sg:phone":"+49 6743/1213",
    "sg:postcode":"55422",
    "sg:province":"Rheinland-Pfalz",
    "wof:name":"Jean Leininger",
    "wof:placetype":"venue"
},
  "geometry": {"coordinates":[7.7681450844,50.0595741272],"type":"Point"}
}