{
  "type": "Feature",
  "properties": {
    "iso:country":"DE",
    "sg:address":"Burgenlandstr. 59",
    "sg:city":"Stuttgart",
    "sg:phone":"+49 711/854905",
    "sg:postcode":"70469",
    "sg:province":"Baden-W\u00fcrttemberg",
    "wof:name":"Rosa Mauch",
    "wof:placetype":"venue"
},
  "geometry": {"coordinates":[9.1617393494,48.811126709],"type":"Point"}
}