{
  "type": "Feature",
  "properties": {
    "iso:country":"DE",
    "sg:address":"Blumenstr. 17",
    "sg:city":"Halle",
    "sg:phone":"+49 345/2113344",
    "sg:postcode":"06108",
    "sg:province":"Sachsen-Anhalt",
    "wof:name":"Bartos Gesundheits-systeme",
    "wof:placetype":"venue"
},
  "geometry": {"coordinates":[11.96498,51.492828],"type":"Point"}
}