{
  "type": "Feature",
  "properties": {
    "iso:country":"DE",
    "sg:address":"Alter Kirchweg 1",
    "sg:city":"Leipzig",
    "sg:phone":"+49 341/4617510",
    "sg:postcode":"04159",
    "sg:province":"Sachsen",
    "wof:name":"Winckelmann Dienst- Leistungs Gmbh",
    "wof:placetype":"venue"
},
  "geometry": {"coordinates":[12.305636,51.377029],"type":"Point"}
}