{
  "type": "Feature",
  "properties": {
    "iso:country":"DE",
    "sg:address":"Moltkestr. 43",
    "sg:city":"V\u00f6lklingen",
    "sg:phone":"+49 6898/21798",
    "sg:postcode":"66333",
    "sg:province":"Saarland",
    "wof:name":"Pizzeria Italia",
    "wof:placetype":"venue"
},
  "geometry": {"coordinates":[6.8562841415,49.2525520325],"type":"Point"}
}