{
  "type": "Feature",
  "properties": {
    "iso:country":"DE",
    "sg:address":"Bliesstr. 2",
    "sg:city":"St. Wendel",
    "sg:phone":"+49 6854/8680",
    "sg:postcode":"66606",
    "sg:province":"Saarland",
    "wof:name":"O. Brodt",
    "wof:placetype":"venue"
},
  "geometry": {"coordinates":[7.1096529961,49.498085022],"type":"Point"}
}