{
  "type": "Feature",
  "properties": {
    "iso:country":"DE",
    "sg:address":"Kr\u00f6tenweg 5",
    "sg:city":"Stuttgart",
    "sg:phone":"+49 711/9867946",
    "sg:postcode":"70499",
    "sg:province":"Baden-W\u00fcrttemberg",
    "wof:name":"Reiseb\u00fcro Dettmer & Co. Gmbh",
    "wof:placetype":"venue"
},
  "geometry": {"coordinates":[9.0898551941,48.8033981323],"type":"Point"}
}