{
  "type": "Feature",
  "properties": {
    "iso:country":"DE",
    "sg:address":"D\u00fcsseldorfer Str. 11",
    "sg:city":"M\u00fcnchen",
    "sg:phone":"+49 89/30004954",
    "sg:postcode":"80804",
    "sg:province":"Bayern",
    "wof:name":"Dipl.-ing. Heinrich Maluche Architekt",
    "wof:placetype":"venue"
},
  "geometry": {"coordinates":[11.575464,48.168442],"type":"Point"}
}