{
  "type": "Feature",
  "properties": {
    "iso:country":"DE",
    "sg:address":"Ahornstr. 16",
    "sg:city":"Pampow",
    "sg:phone":"+49 3865/787342",
    "sg:postcode":"19075",
    "sg:province":"Mecklenburg-Vorpommern",
    "wof:name":"Nordhumus Gmbh",
    "wof:placetype":"venue"
},
  "geometry": {"coordinates":[11.370688,53.568722],"type":"Point"}
}