{
  "type": "Feature",
  "properties": {
    "iso:country":"DE",
    "sg:address":"Lindenstr. 27",
    "sg:city":"Ennepetal",
    "sg:phone":"+49 2333/631565",
    "sg:postcode":"58256",
    "sg:province":"Nordrhein-Westfalen",
    "wof:name":"Medizinische Versorgung Im Ennepe-ruhr-kreis",
    "wof:placetype":"venue"
},
  "geometry": {"coordinates":[7.38734,51.307194],"type":"Point"}
}