{
  "type": "Feature",
  "properties": {
    "iso:country":"DE",
    "sg:address":"Gumbinnenstr 4",
    "sg:city":"Neuwied",
    "sg:phone":"+49 2631/353091",
    "sg:postcode":"56566",
    "sg:province":"Rheinland-Pfalz",
    "wof:name":"Rainer May Gmbh",
    "wof:placetype":"venue"
},
  "geometry": {"coordinates":[7.497303,50.435734],"type":"Point"}
}