{
  "type": "Feature",
  "properties": {
    "iso:country":"DE",
    "sg:address":"Lindenstr. 20",
    "sg:city":"Gro\u00df Lindow",
    "sg:phone":"+49 33609/856",
    "sg:postcode":"15295",
    "sg:province":"Brandenburg",
    "wof:name":"B\u00e4rbel Kernchen",
    "wof:placetype":"venue"
},
  "geometry": {"coordinates":[14.5370721817,52.2394218445],"type":"Point"}
}