{
  "type": "Feature",
  "properties": {
    "iso:country":"DE",
    "sg:address":"Rheinstr. 93",
    "sg:city":"Bendorf",
    "sg:phone":"+49 2622/94060",
    "sg:postcode":"56170",
    "sg:province":"Rheinland-Pfalz",
    "wof:name":"Luckei Gmbh",
    "wof:placetype":"venue"
},
  "geometry": {"coordinates":[7.573186,50.415897],"type":"Point"}
}