{
  "type": "Feature",
  "properties": {
    "iso:country":"DE",
    "sg:address":"Am Schwarzbach 6",
    "sg:city":"M\u00f6nchengladbach",
    "sg:phone":"+49 2161/963565",
    "sg:postcode":"41066",
    "sg:province":"Nordrhein-Westfalen",
    "wof:name":"Zimmermann Franken Gbr Journalistenb\u00fcro",
    "wof:placetype":"venue"
},
  "geometry": {"coordinates":[6.4513950348,51.2281723022],"type":"Point"}
}