{
  "type": "Feature",
  "properties": {
    "iso:country":"DE",
    "sg:address":"Raiffeisenstr. 32",
    "sg:city":"Hofheim",
    "sg:phone":"+49 9523/950526",
    "sg:postcode":"97461",
    "sg:province":"Bayern",
    "wof:name":"Sie Und Wir Bauen Gmbh",
    "wof:placetype":"venue"
},
  "geometry": {"coordinates":[10.567665,50.132957],"type":"Point"}
}