{
  "type": "Feature",
  "properties": {
    "iso:country":"DE",
    "sg:address":"Billwerder Ring 6",
    "sg:city":"Hamburg",
    "sg:phone":"+49 40/7340233",
    "sg:postcode":"21035",
    "sg:province":"Hamburg",
    "wof:name":"Dworeck Elektrotechnik Gmbh",
    "wof:placetype":"venue"
},
  "geometry": {"coordinates":[10.118586,53.495831],"type":"Point"}
}