{
  "type": "Feature",
  "properties": {
    "iso:country":"DE",
    "sg:address":"Bahnhofstr. 5",
    "sg:city":"M\u00f6mbris",
    "sg:phone":"+49 4960/297030",
    "sg:postcode":"63776",
    "sg:province":"Bayern",
    "wof:name":"Raiffeisenbank M\u00f6mbris Eg",
    "wof:placetype":"venue"
},
  "geometry": {"coordinates":[9.166276,50.069939],"type":"Point"}
}