{
  "type": "Feature",
  "properties": {
    "iso:country":"DE",
    "sg:address":"Tepler Str. 7",
    "sg:city":"Butzbach",
    "sg:postcode":"35510",
    "sg:province":"Hessen",
    "wof:name":"Emba Trading Gmbh",
    "wof:placetype":"venue"
},
  "geometry": {"coordinates":[8.665193,50.435677],"type":"Point"}
}