{
  "type": "Feature",
  "properties": {
    "iso:country":"DE",
    "sg:address":"Kamminer Str. 27",
    "sg:city":"Berlin",
    "sg:phone":"+49 30/3445204",
    "sg:postcode":"10589",
    "sg:province":"Berlin",
    "wof:name":"Karl-heinz Picard Ingenieur",
    "wof:placetype":"venue"
},
  "geometry": {"coordinates":[13.3004398346,52.5270614624],"type":"Point"}
}