{
  "type": "Feature",
  "properties": {
    "iso:country":"DE",
    "sg:address":"Germendorfer Str. 94",
    "sg:city":"Velten",
    "sg:phone":"+49 3304/3680",
    "sg:postcode":"16727",
    "sg:province":"Brandenburg",
    "wof:name":"Autohaus Engelhardt Verwaltungs- Gmbh",
    "wof:placetype":"venue"
},
  "geometry": {"coordinates":[13.1792383194,52.6954841614],"type":"Point"}
}