{
  "type": "Feature",
  "properties": {
    "iso:country":"DE",
    "sg:address":"Eschenring 3",
    "sg:city":"Au",
    "sg:phone":"+49 8752/810233",
    "sg:postcode":"84072",
    "sg:province":"Bayern",
    "wof:name":"Kw-metalltechnik Kr\u00f6nauer & Werner Kg",
    "wof:placetype":"venue"
},
  "geometry": {"coordinates":[11.739381,48.565018],"type":"Point"}
}