{
  "type": "Feature",
  "properties": {
    "iso:country":"DE",
    "sg:address":"Putbuser Str. 9",
    "sg:city":"Rostock",
    "sg:postcode":"18109",
    "sg:province":"Mecklenburg-Vorpommern",
    "wof:name":"Raimund Schmidt E. K.",
    "wof:placetype":"venue"
},
  "geometry": {"coordinates":[12.063372612,54.1515922546],"type":"Point"}
}