{
  "type": "Feature",
  "properties": {
    "iso:country":"DE",
    "sg:address":"Berliner Str. 22",
    "sg:city":"Cottbus",
    "sg:phone":"+49 355/797236",
    "sg:postcode":"03046",
    "sg:province":"Brandenburg",
    "wof:name":"Springer Cash-electronic Gmbh",
    "wof:placetype":"venue"
},
  "geometry": {"coordinates":[14.3237485886,51.7610435486],"type":"Point"}
}