{
  "type": "Feature",
  "properties": {
    "iso:country":"DE",
    "sg:address":"Wittenberger Str. 9",
    "sg:city":"Oranienbaum",
    "sg:phone":"+49 34904/20286",
    "sg:postcode":"06785",
    "sg:province":"Sachsen-Anhalt",
    "wof:name":"Heinrich Gmbh",
    "wof:placetype":"venue"
},
  "geometry": {"coordinates":[12.4110937119,51.8030166626],"type":"Point"}
}