{
  "type": "Feature",
  "properties": {
    "iso:country":"DE",
    "sg:address":"Schwarzer Weg 21",
    "sg:city":"Melle",
    "sg:phone":"+49 5226/5628",
    "sg:postcode":"49328",
    "sg:province":"Niedersachsen",
    "wof:name":"H. Brackmann",
    "wof:placetype":"venue"
},
  "geometry": {"coordinates":[8.4513721466,52.2042541504],"type":"Point"}
}