{
  "type": "Feature",
  "properties": {
    "iso:country":"DE",
    "sg:address":"Friedhofstr. 11",
    "sg:city":"Kaiserslautern",
    "sg:phone":"+49 6301/8860",
    "sg:postcode":"67661",
    "sg:province":"Rheinland-Pfalz",
    "wof:name":"H. Hach Heissmangel",
    "wof:placetype":"venue"
},
  "geometry": {"coordinates":[7.6928639412,49.4660568237],"type":"Point"}
}