{
  "type": "Feature",
  "properties": {
    "iso:country":"DE",
    "sg:address":"Neumarkt 42",
    "sg:city":"Netphen",
    "sg:phone":"+49 2738/4938",
    "sg:postcode":"57250",
    "sg:province":"Nordrhein-Westfalen",
    "wof:name":"Pizzeria Angelo",
    "wof:placetype":"venue"
},
  "geometry": {"coordinates":[8.1039381027,50.9116516113],"type":"Point"}
}