{
  "type": "Feature",
  "properties": {
    "iso:country":"DE",
    "sg:address":"Klosterstr. 17",
    "sg:city":"Mengerskirchen",
    "sg:phone":"+49 6476/91027",
    "sg:postcode":"35794",
    "sg:province":"Hessen",
    "wof:name":"Peter H\u00f6rle",
    "wof:placetype":"venue"
},
  "geometry": {"coordinates":[8.1392288208,50.5408668518],"type":"Point"}
}