{
  "type": "Feature",
  "properties": {
    "iso:country":"DE",
    "sg:address":"Am Bargfeld 3 a",
    "sg:city":"Bargteheide",
    "sg:phone":"+49 4532/22630",
    "sg:postcode":"22941",
    "sg:province":"Schleswig-Holstein",
    "wof:name":"Helmut Krien",
    "wof:placetype":"venue"
},
  "geometry": {"coordinates":[10.2486591339,53.7271995544],"type":"Point"}
}