{
  "type": "Feature",
  "properties": {
    "iso:country":"DE",
    "sg:address":"Parkstr. 12",
    "sg:city":"Bad Berka",
    "sg:phone":"+49 36458/30268",
    "sg:postcode":"99438",
    "sg:province":"Th\u00fcringen",
    "wof:name":"Dr. Med. Annerose Entling \u00c4rztin F\u00fcr Allgemeinmedizin",
    "wof:placetype":"venue"
},
  "geometry": {"coordinates":[11.2912416458,50.902885437],"type":"Point"}
}