{
  "type": "Feature",
  "properties": {
    "iso:country":"DE",
    "sg:address":"Bonner Str. 47",
    "sg:city":"K\u00f6ln",
    "sg:phone":"+49 2203/292620",
    "sg:postcode":"51145",
    "sg:province":"Nordrhein-Westfalen",
    "wof:name":"Spitzweg-apotheke Inh. Monika Ihle",
    "wof:placetype":"venue"
},
  "geometry": {"coordinates":[7.074947,50.890156],"type":"Point"}
}