{
  "type": "Feature",
  "properties": {
    "iso:country":"DE",
    "sg:address":"Kuhfluchtweg 3",
    "sg:city":"Farchant",
    "sg:phone":"+49 8821/6794",
    "sg:postcode":"82490",
    "sg:province":"Bayern",
    "wof:name":"H. Heilgenthal",
    "wof:placetype":"venue"
},
  "geometry": {"coordinates":[11.1188201904,47.5299720764],"type":"Point"}
}