{
  "type": "Feature",
  "properties": {
    "iso:country":"DE",
    "sg:address":"Floriansm\u00fchlstr. 28",
    "sg:city":"M\u00fcnchen",
    "sg:phone":"+49 89/3226055",
    "sg:postcode":"80939",
    "sg:province":"Bayern",
    "wof:name":"Peter Barthel & Sohn",
    "wof:placetype":"venue"
},
  "geometry": {"coordinates":[11.6235685349,48.1908683777],"type":"Point"}
}