{
  "type": "Feature",
  "properties": {
    "iso:country":"DE",
    "sg:address":"Herdweg 40",
    "sg:city":"Schw\u00e4bisch Hall",
    "sg:phone":"+49 7907/8720",
    "sg:postcode":"74523",
    "sg:province":"Baden-W\u00fcrttemberg",
    "wof:name":"Mobau Baumarkt Leipzig-wiederitzsch",
    "wof:placetype":"venue"
},
  "geometry": {"coordinates":[9.839474678,49.0943374634],"type":"Point"}
}