{
  "type": "Feature",
  "properties": {
    "iso:country":"DE",
    "sg:address":"Ei\u00dfendorfer Str. 181",
    "sg:city":"Hamburg",
    "sg:phone":"+49 40/7905504",
    "sg:postcode":"21073",
    "sg:province":"Hamburg",
    "wof:name":"Konditorei Manfred Janeke Gmbh",
    "wof:placetype":"venue"
},
  "geometry": {"coordinates":[9.9572219849,53.456111908],"type":"Point"}
}