{
  "type": "Feature",
  "properties": {
    "iso:country":"DE",
    "sg:address":"Bahnhofstr. 22",
    "sg:city":"Hohenwarth",
    "sg:phone":"+49 9946/284",
    "sg:postcode":"93480",
    "sg:province":"Bayern",
    "wof:name":"Karlheinz Vogl",
    "wof:placetype":"venue"
},
  "geometry": {"coordinates":[12.9321241379,49.2064704895],"type":"Point"}
}