{
  "type": "Feature",
  "properties": {
    "iso:country":"DE",
    "sg:address":"Braamheide 32 b",
    "sg:city":"Hamburg",
    "sg:phone":"+49 40/6451145",
    "sg:postcode":"22175",
    "sg:province":"Hamburg",
    "wof:name":"I. Carstens Immobilienmakler",
    "wof:placetype":"venue"
},
  "geometry": {"coordinates":[10.1033554077,53.6162033081],"type":"Point"}
}