{
  "type": "Feature",
  "properties": {
    "iso:country":"DE",
    "sg:address":"Hasselwerder Str. 32",
    "sg:city":"Hamburg",
    "sg:phone":"+49 40/7459173",
    "sg:postcode":"21129",
    "sg:province":"Hamburg",
    "wof:name":"W. Drewes",
    "wof:placetype":"venue"
},
  "geometry": {"coordinates":[9.823974,53.517506],"type":"Point"}
}