{
  "type": "Feature",
  "properties": {
    "iso:country":"DE",
    "sg:address":"Peter-Grah-Str. 24",
    "sg:city":"Hemer",
    "sg:phone":"+49 2372/2253",
    "sg:postcode":"58675",
    "sg:province":"Nordrhein-Westfalen",
    "wof:name":"Heinz-g\u00fcnter Camminadi",
    "wof:placetype":"venue"
},
  "geometry": {"coordinates":[7.7752079964,51.372718811],"type":"Point"}
}