{
  "type": "Feature",
  "properties": {
    "iso:country":"DE",
    "sg:address":"Robert-Bosch-Str 15",
    "sg:city":"Augsburg",
    "sg:phone":"+49 821/7477140",
    "sg:postcode":"86167",
    "sg:province":"Bayern",
    "wof:name":"H.i.b Industriek\u00fchlung Und Temperierung",
    "wof:placetype":"venue"
},
  "geometry": {"coordinates":[10.919553,48.394508],"type":"Point"}
}