{
  "type": "Feature",
  "properties": {
    "iso:country":"DE",
    "sg:address":"Holthauser Str. 28",
    "sg:city":"Hagen",
    "sg:phone":"+49 2334/40614",
    "sg:postcode":"58093",
    "sg:province":"Nordrhein-Westfalen",
    "wof:name":"Mustafa Erkal Architekt",
    "wof:placetype":"venue"
},
  "geometry": {"coordinates":[7.549758,51.356956],"type":"Point"}
}