{
  "type": "Feature",
  "properties": {
    "iso:country":"DE",
    "sg:address":"Leinstr. 101",
    "sg:city":"Neustadt",
    "sg:phone":"+49 5032/98020",
    "sg:postcode":"31535",
    "sg:province":"Niedersachsen",
    "wof:name":"R & E Todtenhaupt Gmbh & Co. Kg",
    "wof:placetype":"venue"
},
  "geometry": {"coordinates":[9.4657354355,52.5164680481],"type":"Point"}
}