{
  "type": "Feature",
  "properties": {
    "iso:country":"DE",
    "sg:address":"Am Heilbrunnen 107",
    "sg:city":"Reutlingen",
    "sg:phone":"+49 7121/39528",
    "sg:postcode":"72766",
    "sg:province":"Baden-W\u00fcrttemberg",
    "wof:name":"Technische Betriebsdienste Der Stadt Reutlingen",
    "wof:placetype":"venue"
},
  "geometry": {"coordinates":[9.2222280502,48.5078392029],"type":"Point"}
}