{
  "type": "Feature",
  "properties": {
    "iso:country":"DE",
    "sg:address":"Karl-Marx-Allee 92",
    "sg:city":"Berlin",
    "sg:phone":"+49 30/2946429",
    "sg:postcode":"10243",
    "sg:province":"Berlin",
    "wof:name":"Peter G\u00fctte",
    "wof:placetype":"venue"
},
  "geometry": {"coordinates":[13.4417610168,52.5167808533],"type":"Point"}
}