{
  "type": "Feature",
  "properties": {
    "iso:country":"DE",
    "sg:address":"Im Hasenkamp 10",
    "sg:city":"Herne",
    "sg:phone":"+49 2325/47276",
    "sg:postcode":"44625",
    "sg:province":"Nordrhein-Westfalen",
    "wof:name":"F.-o. Jendrny",
    "wof:placetype":"venue"
},
  "geometry": {"coordinates":[7.200257,51.530209],"type":"Point"}
}