{
  "type": "Feature",
  "properties": {
    "iso:country":"DE",
    "sg:address":"Travem\u00fcnder Landstr. 7",
    "sg:city":"Timmendorfer Strand",
    "sg:phone":"+49 4503/1459",
    "sg:postcode":"23669",
    "sg:province":"Schleswig-Holstein",
    "wof:name":"Windrose Ferienzentrum",
    "wof:placetype":"venue"
},
  "geometry": {"coordinates":[10.8367834091,53.99010849],"type":"Point"}
}