{
  "type": "Feature",
  "properties": {
    "iso:country":"DE",
    "sg:address":"Fischerweg 5",
    "sg:city":"Niederalteich",
    "sg:phone":"+49 9901/5400",
    "sg:postcode":"94557",
    "sg:province":"Bayern",
    "wof:name":"Dipl.-ing. Hubert Ammer Landschaftsarchitekt",
    "wof:placetype":"venue"
},
  "geometry": {"coordinates":[13.024769,48.7635],"type":"Point"}
}