{
  "type": "Feature",
  "properties": {
    "iso:country":"DE",
    "sg:address":"Tulpenweg 21",
    "sg:city":"Kaarst",
    "sg:phone":"+49 2131/68739",
    "sg:postcode":"41564",
    "sg:province":"Nordrhein-Westfalen",
    "wof:name":"Bernd Voosen",
    "wof:placetype":"venue"
},
  "geometry": {"coordinates":[6.6320037842,51.2271194458],"type":"Point"}
}