{
  "type": "Feature",
  "properties": {
    "iso:country":"DE",
    "sg:address":"Neusser Str. 287",
    "sg:city":"K\u00f6ln",
    "sg:phone":"+49 221/726714",
    "sg:postcode":"50733",
    "sg:province":"Nordrhein-Westfalen",
    "wof:name":"Lichtex Imp.-exp. Naftali Licht",
    "wof:placetype":"venue"
},
  "geometry": {"coordinates":[6.953458786,50.9647712708],"type":"Point"}
}