{
  "type": "Feature",
  "properties": {
    "iso:country":"DE",
    "sg:address":"Gl\u00fcckaufstr. 11",
    "sg:city":"Wei\u00dfwasser",
    "sg:postcode":"02943",
    "sg:province":"Sachsen",
    "wof:name":"Lr Medienverlag Gmbh",
    "wof:placetype":"venue"
},
  "geometry": {"coordinates":[14.631187439,51.4995117188],"type":"Point"}
}