{
  "type": "Feature",
  "properties": {
    "iso:country":"DE",
    "sg:address":"Sch\u00fcppenstr. 12",
    "sg:city":"Coesfeld",
    "sg:phone":"+49 2541",
    "sg:postcode":"48653",
    "sg:province":"Nordrhein-Westfalen",
    "wof:name":"Niessing Immobilien",
    "wof:placetype":"venue"
},
  "geometry": {"coordinates":[7.166864872,51.9452667236],"type":"Point"}
}