{
  "type": "Feature",
  "properties": {
    "iso:country":"DE",
    "sg:address":"H\u00f6henweg 27",
    "sg:city":"Wilnsdorf",
    "sg:phone":"+49 271/394142",
    "sg:postcode":"57234",
    "sg:province":"Nordrhein-Westfalen",
    "wof:name":"Vermittlung Von Reisen Aller Art - Anke Br\u00fcck E. K.",
    "wof:placetype":"venue"
},
  "geometry": {"coordinates":[8.06944561,50.8447151184],"type":"Point"}
}