{
  "type": "Feature",
  "properties": {
    "iso:country":"DE",
    "sg:address":"Hauffstr. 26",
    "sg:city":"Marbach",
    "sg:phone":"+49 7144/12389",
    "sg:postcode":"71672",
    "sg:province":"Baden-W\u00fcrttemberg",
    "wof:name":"Nello Conforti",
    "wof:placetype":"venue"
},
  "geometry": {"coordinates":[9.266546,48.938942],"type":"Point"}
}