{
  "type": "Feature",
  "properties": {
    "iso:country":"DE",
    "sg:address":"Clara-Zetkin-Str. 8-16",
    "sg:city":"Beelitz",
    "sg:phone":"+49 33204/3900",
    "sg:postcode":"14547",
    "sg:province":"Brandenburg",
    "wof:name":"Bekina Lebensmittel Gmbh & Co. Kg",
    "wof:placetype":"venue"
},
  "geometry": {"coordinates":[12.9762916565,52.2359275818],"type":"Point"}
}