{
  "type": "Feature",
  "properties": {
    "iso:country":"DE",
    "sg:address":"Mitterweg 21",
    "sg:city":"Tirschenreuth",
    "sg:phone":"+49 9631/79390",
    "sg:postcode":"95643",
    "sg:province":"Bayern",
    "wof:name":"Gerro Fashion Bauer & Ernst Ohg",
    "wof:placetype":"venue"
},
  "geometry": {"coordinates":[12.339805603,49.8687553406],"type":"Point"}
}