{
  "type": "Feature",
  "properties": {
    "iso:country":"DE",
    "sg:address":"Ed 2",
    "sg:city":"Gstadt",
    "sg:phone":"+49 8054/202",
    "sg:postcode":"83257",
    "sg:province":"Bayern",
    "wof:name":"Elisab. Pyka",
    "wof:placetype":"venue"
},
  "geometry": {"coordinates":[12.4213047028,47.9070472717],"type":"Point"}
}