{
  "type": "Feature",
  "properties": {
    "iso:country":"DE",
    "sg:address":"Karl-Friedrich-Str. 243",
    "sg:city":"Pforzheim",
    "sg:phone":"+49 7231/392559",
    "sg:postcode":"75172",
    "sg:province":"Baden-W\u00fcrttemberg",
    "wof:name":"Stadtmuseum Pforzheim",
    "wof:placetype":"venue"
},
  "geometry": {"coordinates":[8.673014,48.891171],"type":"Point"}
}