{
  "type": "Feature",
  "properties": {
    "iso:country":"DE",
    "sg:address":"Hofmarkstr. 25",
    "sg:city":"Geisenfeld",
    "sg:phone":"+49 8452/9775",
    "sg:postcode":"85290",
    "sg:province":"Bayern",
    "wof:name":"Ernst List",
    "wof:placetype":"venue"
},
  "geometry": {"coordinates":[11.638309,48.693542],"type":"Point"}
}