{
  "type": "Feature",
  "properties": {
    "iso:country":"DE",
    "sg:address":"Rosentalgasse 9",
    "sg:city":"Leipzig",
    "sg:phone":"+49 341/9803618",
    "sg:postcode":"04105",
    "sg:province":"Sachsen",
    "wof:name":"Peter Schulze Patentanwalt",
    "wof:placetype":"venue"
},
  "geometry": {"coordinates":[12.3693332672,51.3450202942],"type":"Point"}
}