{
  "type": "Feature",
  "properties": {
    "iso:country":"DE",
    "sg:address":"Lanstroper Str. 119",
    "sg:city":"Dortmund",
    "sg:phone":"+49 231/290540",
    "sg:postcode":"44329",
    "sg:province":"Nordrhein-Westfalen",
    "wof:name":"Karl Behrle",
    "wof:placetype":"venue"
},
  "geometry": {"coordinates":[7.571594,51.576401],"type":"Point"}
}