{
  "type": "Feature",
  "properties": {
    "iso:country":"DE",
    "sg:address":"Alsfelder Str. 45",
    "sg:city":"Gr\u00fcnberg",
    "sg:phone":"+49 6401/21350",
    "sg:postcode":"35305",
    "sg:province":"Hessen",
    "wof:name":"Moustaki Restaurant",
    "wof:placetype":"venue"
},
  "geometry": {"coordinates":[8.968085289,50.5923423767],"type":"Point"}
}