{
  "type": "Feature",
  "properties": {
    "iso:country":"DE",
    "sg:address":"Maxburgstr. 9",
    "sg:city":"Maikammer",
    "sg:phone":"+49 6321/57295",
    "sg:postcode":"67487",
    "sg:province":"Rheinland-Pfalz",
    "wof:name":"G\u00e4stehaus Mandelh\u00f6he",
    "wof:placetype":"venue"
},
  "geometry": {"coordinates":[8.1280908585,49.309551239],"type":"Point"}
}