{
  "type": "Feature",
  "properties": {
    "iso:country":"DE",
    "sg:address":"Kirchstr. 7",
    "sg:city":"Neusalza-Spremberg",
    "sg:phone":"+49 35872/39515",
    "sg:postcode":"02742",
    "sg:province":"Sachsen",
    "wof:name":"Marcel P\u00e4tzold",
    "wof:placetype":"venue"
},
  "geometry": {"coordinates":[14.5300970078,51.0362930298],"type":"Point"}
}