{
  "type": "Feature",
  "properties": {
    "iso:country":"DE",
    "sg:address":"L\u00f6wengrube 6",
    "sg:city":"Grafing",
    "sg:phone":"+49 8092/31491",
    "sg:postcode":"85567",
    "sg:province":"Bayern",
    "wof:name":"Hans-j. Glissmann Ingenieur",
    "wof:placetype":"venue"
},
  "geometry": {"coordinates":[11.9073457718,48.0207824707],"type":"Point"}
}