{
  "type": "Feature",
  "properties": {
    "iso:country":"DE",
    "sg:address":"Bahnhofstr. 15",
    "sg:city":"Blaustein",
    "sg:phone":"+49 7304/41516",
    "sg:postcode":"89134",
    "sg:province":"Baden-W\u00fcrttemberg",
    "wof:name":"Bahnhof",
    "wof:placetype":"venue"
},
  "geometry": {"coordinates":[9.8976402283,48.418170929],"type":"Point"}
}