{
  "type": "Feature",
  "properties": {
    "iso:country":"DE",
    "sg:address":"Auf dem Berge 9",
    "sg:city":"Herne",
    "sg:phone":"+49 2323/32836",
    "sg:postcode":"44627",
    "sg:province":"Nordrhein-Westfalen",
    "wof:name":"Anny F\u00e4rber Masseurin",
    "wof:placetype":"venue"
},
  "geometry": {"coordinates":[7.264623,51.546799],"type":"Point"}
}