{
  "type": "Feature",
  "properties": {
    "iso:country":"DE",
    "sg:address":"Ulrichstr. 52",
    "sg:city":"G\u00f6ppingen",
    "sg:postcode":"73033",
    "sg:province":"Baden-W\u00fcrttemberg",
    "wof:name":"Glasschleiferei G\u00e4rlich Gmbh",
    "wof:placetype":"venue"
},
  "geometry": {"coordinates":[9.6504364014,48.7087020874],"type":"Point"}
}