{
  "type": "Feature",
  "properties": {
    "iso:country":"DE",
    "sg:address":"G\u00f6rlitzer Str. 55 a",
    "sg:city":"Zittau",
    "sg:phone":"+49 3583/701145",
    "sg:postcode":"02763",
    "sg:province":"Sachsen",
    "wof:name":"R. K\u00f6hler Blumenpavillon Am Krematorium",
    "wof:placetype":"venue"
},
  "geometry": {"coordinates":[14.826391,50.904152],"type":"Point"}
}