{
  "type": "Feature",
  "properties": {
    "iso:country":"DE",
    "sg:address":"Nordstr. 31",
    "sg:city":"Remscheid",
    "sg:phone":"+49 2191/294244",
    "sg:postcode":"42853",
    "sg:province":"Nordrhein-Westfalen",
    "wof:name":"Aro Heimtextilien Gmbh & Co. Kg",
    "wof:placetype":"venue"
},
  "geometry": {"coordinates":[7.1991448402,51.1811256409],"type":"Point"}
}