{
  "type": "Feature",
  "properties": {
    "iso:country":"DE",
    "sg:address":"Dammstr. 20",
    "sg:city":"Neuburg",
    "sg:phone":"+49 7273/4282",
    "sg:postcode":"76776",
    "sg:province":"Rheinland-Pfalz",
    "wof:name":"Damm-apotheke",
    "wof:placetype":"venue"
},
  "geometry": {"coordinates":[8.248587,48.984413],"type":"Point"}
}