{
  "type": "Feature",
  "properties": {
    "iso:country":"DE",
    "sg:address":"Daimlerstr. 14",
    "sg:city":"Koblenz",
    "sg:phone":"+49 261/83414",
    "sg:postcode":"56070",
    "sg:province":"Rheinland-Pfalz",
    "wof:name":"Holzbau Frommer Gmbh",
    "wof:placetype":"venue"
},
  "geometry": {"coordinates":[7.594218,50.382732],"type":"Point"}
}