{
  "type": "Feature",
  "properties": {
    "iso:country":"DE",
    "sg:address":"Hauptstr. 36",
    "sg:city":"Ma\u00dfweiler",
    "sg:phone":"+49 6334/4670",
    "sg:postcode":"66506",
    "sg:province":"Rheinland-Pfalz",
    "wof:name":"Willi Scherer",
    "wof:placetype":"venue"
},
  "geometry": {"coordinates":[7.5298881531,49.2705116272],"type":"Point"}
}