{
  "type": "Feature",
  "properties": {
    "iso:country":"DE",
    "sg:address":"D\u00fcsternortstr. 94",
    "sg:city":"Delmenhorst",
    "sg:phone":"+49 4221/61982",
    "sg:postcode":"27755",
    "sg:province":"Niedersachsen",
    "wof:name":"Oase",
    "wof:placetype":"venue"
},
  "geometry": {"coordinates":[8.6396856308,53.0344734192],"type":"Point"}
}