{
  "type": "Feature",
  "properties": {
    "iso:country":"DE",
    "sg:address":"Arlesrieder Str. 10",
    "sg:city":"Erkheim",
    "sg:phone":"+49 8336/7919",
    "sg:postcode":"87746",
    "sg:province":"Bayern",
    "wof:name":"G\u00f6stl Gmbh",
    "wof:placetype":"venue"
},
  "geometry": {"coordinates":[10.3381557465,48.0400924683],"type":"Point"}
}