{
  "type": "Feature",
  "properties": {
    "iso:country":"DE",
    "sg:address":"Karbe-Wagner-Str. 49",
    "sg:city":"Neustrelitz",
    "sg:phone":"+49 3981/440190",
    "sg:postcode":"17235",
    "sg:province":"Mecklenburg-Vorpommern",
    "wof:name":"Wilkens Backstuben Gmbh",
    "wof:placetype":"venue"
},
  "geometry": {"coordinates":[13.08657,53.35495],"type":"Point"}
}