{
  "type": "Feature",
  "properties": {
    "iso:country":"DE",
    "sg:address":"Grebenauer Weg 1",
    "sg:city":"Guxhagen",
    "sg:phone":"+49 5665/2170",
    "sg:postcode":"34302",
    "sg:province":"Hessen",
    "wof:name":"Wilhelm Damm",
    "wof:placetype":"venue"
},
  "geometry": {"coordinates":[9.506555,51.208736],"type":"Point"}
}