{
  "type": "Feature",
  "properties": {
    "iso:country":"DE",
    "sg:address":"Arsenius-Pfaff-Str. 6",
    "sg:city":"Radolfzell",
    "sg:phone":"+49 7732/919417",
    "sg:postcode":"78315",
    "sg:province":"Baden-W\u00fcrttemberg",
    "wof:name":"T. Buchheim",
    "wof:placetype":"venue"
},
  "geometry": {"coordinates":[8.9822864532,47.746635437],"type":"Point"}
}