{
  "type": "Feature",
  "properties": {
    "iso:country":"DE",
    "sg:address":"Arns Weide 7",
    "sg:city":"Arnsberg",
    "sg:phone":"+49 2932/33763",
    "sg:postcode":"59757",
    "sg:province":"Nordrhein-Westfalen",
    "wof:name":"Ulrich Br\u00fcggen",
    "wof:placetype":"venue"
},
  "geometry": {"coordinates":[7.9606580734,51.4193725586],"type":"Point"}
}