{
  "type": "Feature",
  "properties": {
    "iso:country":"DE",
    "sg:address":"Wolfsberger Str. 33",
    "sg:city":"L\u00fcdinghausen",
    "sg:phone":"+49 2591/6829",
    "sg:postcode":"59348",
    "sg:province":"Nordrhein-Westfalen",
    "wof:name":"Hans Sch\u00e4per",
    "wof:placetype":"venue"
},
  "geometry": {"coordinates":[7.4431,51.766003],"type":"Point"}
}