{
  "type": "Feature",
  "properties": {
    "iso:country":"DE",
    "sg:address":"Am Selder 53-55",
    "sg:city":"Kempen",
    "sg:phone":"+49 2152/519991",
    "sg:postcode":"47906",
    "sg:province":"Nordrhein-Westfalen",
    "wof:name":"Researching Engineers Group & Gerlach Kg",
    "wof:placetype":"venue"
},
  "geometry": {"coordinates":[6.422296,51.377502],"type":"Point"}
}