{
  "type": "Feature",
  "properties": {
    "iso:country":"DE",
    "sg:address":"Hauptstr. 20-22",
    "sg:city":"Elzach",
    "sg:phone":"+49 7682/394",
    "sg:postcode":"79215",
    "sg:province":"Baden-W\u00fcrttemberg",
    "wof:name":"Oschwald Wohnen & Mehr Gmbh",
    "wof:placetype":"venue"
},
  "geometry": {"coordinates":[8.071204,48.172997],"type":"Point"}
}