{
  "type": "Feature",
  "properties": {
    "iso:country":"DE",
    "sg:address":"Rolandsborn 6",
    "sg:city":"N\u00fcmbrecht",
    "sg:phone":"+49 2293/91260",
    "sg:postcode":"51588",
    "sg:province":"Nordrhein-Westfalen",
    "wof:name":"G\u00fcnter Fragel",
    "wof:placetype":"venue"
},
  "geometry": {"coordinates":[7.5791869164,50.9241104126],"type":"Point"}
}