{
  "type": "Feature",
  "properties": {
    "iso:country":"DE",
    "sg:address":"Neubrandslebener Chaussee 4",
    "sg:city":"Hornhausen",
    "sg:phone":"+49 3949/97591",
    "sg:postcode":"39387",
    "sg:province":"Sachsen-Anhalt",
    "wof:name":"Lutz Schulze",
    "wof:placetype":"venue"
},
  "geometry": {"coordinates":[11.166336,52.053009],"type":"Point"}
}