{
  "type": "Feature",
  "properties": {
    "iso:country":"DE",
    "sg:address":"Zum Schulzenhof 13",
    "sg:city":"Selm",
    "sg:phone":"+49 2592/9529",
    "sg:postcode":"59379",
    "sg:province":"Nordrhein-Westfalen",
    "wof:name":"Centra-bau Gmbh",
    "wof:placetype":"venue"
},
  "geometry": {"coordinates":[7.4690799713,51.6962509155],"type":"Point"}
}