{
  "type": "Feature",
  "properties": {
    "iso:country":"DE",
    "sg:address":"Pfarrkirchener Str. 44",
    "sg:city":"Arnstorf",
    "sg:phone":"+49 8723/910200",
    "sg:postcode":"94424",
    "sg:province":"Bayern",
    "wof:name":"Herbert Gabor",
    "wof:placetype":"venue"
},
  "geometry": {"coordinates":[12.8249568939,48.5595779419],"type":"Point"}
}