{
  "type": "Feature",
  "properties": {
    "iso:country":"DE",
    "sg:address":"R\u00f6slstr. 38",
    "sg:city":"Frammersbach",
    "sg:phone":"+49 9355/1725",
    "sg:postcode":"97833",
    "sg:province":"Bayern",
    "wof:name":"Hermann Friedel Steuerberater",
    "wof:placetype":"venue"
},
  "geometry": {"coordinates":[9.4631004333,50.0607070923],"type":"Point"}
}