{
  "type": "Feature",
  "properties": {
    "iso:country":"DE",
    "sg:address":"Alexander-Puschkin-Promenade 6",
    "sg:city":"Sondershausen",
    "sg:phone":"+49 3632/782626",
    "sg:postcode":"99706",
    "sg:province":"Th\u00fcringen",
    "wof:name":"Dr. Med. Rudolf Sch\u00fctz",
    "wof:placetype":"venue"
},
  "geometry": {"coordinates":[10.873027,51.368675],"type":"Point"}
}