{
  "type": "Feature",
  "properties": {
    "iso:country":"DE",
    "sg:address":"Holleweg 37",
    "sg:city":"Solingen",
    "sg:phone":"+49 212/592070",
    "sg:postcode":"42653",
    "sg:province":"Nordrhein-Westfalen",
    "wof:name":"Hans Paul Tepel Gmbh & Co.",
    "wof:placetype":"venue"
},
  "geometry": {"coordinates":[7.06665,51.196251],"type":"Point"}
}