{
  "type": "Feature",
  "properties": {
    "iso:country":"DE",
    "sg:address":"Hasestr. 38",
    "sg:city":"Osnabr\u00fcck",
    "sg:phone":"+49 541/21593",
    "sg:postcode":"49074",
    "sg:province":"Niedersachsen",
    "wof:name":"Mamis Laden",
    "wof:placetype":"venue"
},
  "geometry": {"coordinates":[8.043301,52.278091],"type":"Point"}
}