{
  "type": "Feature",
  "properties": {
    "iso:country":"DE",
    "sg:address":"Lehen 3",
    "sg:city":"Gai\u00dfach",
    "sg:phone":"+49 8041/70383",
    "sg:postcode":"83674",
    "sg:province":"Bayern",
    "wof:name":"Karosserie- Und Fahrzeugbau Gschwendtner Gmbh",
    "wof:placetype":"venue"
},
  "geometry": {"coordinates":[11.5816745758,47.7324981689],"type":"Point"}
}