{
  "type": "Feature",
  "properties": {
    "iso:country":"DE",
    "sg:address":"Waldstr. 42",
    "sg:city":"Brensbach",
    "sg:phone":"+49 6161/931880",
    "sg:postcode":"64395",
    "sg:province":"Hessen",
    "wof:name":"Industrie-service Helmut Tr\u00dcmner",
    "wof:placetype":"venue"
},
  "geometry": {"coordinates":[8.8812742233,49.776058197],"type":"Point"}
}