{
  "type": "Feature",
  "properties": {
    "iso:country":"DE",
    "sg:address":"Benatweg 17",
    "sg:city":"Lauterbach",
    "sg:phone":"+49 7422/7719",
    "sg:postcode":"78730",
    "sg:province":"Baden-W\u00fcrttemberg",
    "wof:name":"Paul Mayer Anlageberater",
    "wof:placetype":"venue"
},
  "geometry": {"coordinates":[8.3432283401,48.2327346802],"type":"Point"}
}