{
  "type": "Feature",
  "properties": {
    "iso:country":"DE",
    "sg:address":"Zollhausstr. 35",
    "sg:city":"Iserlohn",
    "sg:phone":"+49 2371/5449",
    "sg:postcode":"58640",
    "sg:province":"Nordrhein-Westfalen",
    "wof:name":"Peter Thiel & Co. Inh. Mario Giacomin",
    "wof:placetype":"venue"
},
  "geometry": {"coordinates":[7.6809,51.421749],"type":"Point"}
}