{
  "type": "Feature",
  "properties": {
    "iso:country":"DE",
    "sg:address":"Anzingerstr. 7a",
    "sg:city":"Ebersberg",
    "sg:phone":"+49 8092/82890",
    "sg:postcode":"85560",
    "sg:province":"Bayern",
    "wof:name":"Mwg-biotech Ag",
    "wof:placetype":"venue"
},
  "geometry": {"coordinates":[11.96856,48.07843],"type":"Point"}
}