{
  "type": "Feature",
  "properties": {
    "iso:country":"DE",
    "sg:address":"Jungfernstieg 3b",
    "sg:city":"Stralsund",
    "sg:phone":"+49 3831/290223",
    "sg:postcode":"18437",
    "sg:province":"Mecklenburg-Vorpommern",
    "wof:name":"W. Niemann Und Partner",
    "wof:placetype":"venue"
},
  "geometry": {"coordinates":[13.0781860352,54.3104705811],"type":"Point"}
}