{
  "type": "Feature",
  "properties": {
    "iso:country":"DE",
    "sg:address":"Im Viertel 1",
    "sg:city":"Hohenstein-Ernstthal",
    "sg:phone":"+49 3723/415251",
    "sg:postcode":"09337",
    "sg:province":"Sachsen",
    "wof:name":"Gastst\u00e4tte Oberwaldsch\u00e4nke",
    "wof:placetype":"venue"
},
  "geometry": {"coordinates":[12.6855230331,50.81199646],"type":"Point"}
}