{
  "type": "Feature",
  "properties": {
    "iso:country":"DE",
    "sg:address":"Parkstr. 2",
    "sg:city":"Schwaig",
    "sg:phone":"+49 911/500236",
    "sg:postcode":"90571",
    "sg:province":"Bayern",
    "wof:name":"T. Riedel",
    "wof:placetype":"venue"
},
  "geometry": {"coordinates":[11.19762,49.473858],"type":"Point"}
}