{
  "type": "Feature",
  "properties": {
    "iso:country":"DE",
    "sg:address":"Ritterstr. 12",
    "sg:city":"Hamm",
    "sg:phone":"+49 2381/926100",
    "sg:postcode":"59065",
    "sg:province":"Nordrhein-Westfalen",
    "wof:name":"Partnerschaft A. Maurer F. Weckwerth Staatlich",
    "wof:placetype":"venue"
},
  "geometry": {"coordinates":[7.815388,51.681484],"type":"Point"}
}