{
  "type": "Feature",
  "properties": {
    "iso:country":"DE",
    "sg:address":"Neue Str. 25",
    "sg:city":"Braunschweig",
    "sg:phone":"+49 531/124702",
    "sg:postcode":"38100",
    "sg:province":"Niedersachsen",
    "wof:name":"Classic",
    "wof:placetype":"venue"
},
  "geometry": {"coordinates":[10.520606,52.264442],"type":"Point"}
}