{
  "type": "Feature",
  "properties": {
    "iso:country":"DE",
    "sg:address":"Prinzenallee 10",
    "sg:city":"Berlin",
    "sg:phone":"+49 30/4939082",
    "sg:postcode":"13357",
    "sg:province":"Berlin",
    "wof:name":"Foto-atelier Schild-vogel",
    "wof:placetype":"venue"
},
  "geometry": {"coordinates":[13.3830785751,52.5536651611],"type":"Point"}
}