{
  "type": "Feature",
  "properties": {
    "iso:country":"DE",
    "sg:address":"Alte Landstr. 1",
    "sg:city":"Ottobrunn",
    "sg:phone":"+49 89/60860294",
    "sg:postcode":"85521",
    "sg:province":"Bayern",
    "wof:name":"Rettenberger Gmbh",
    "wof:placetype":"venue"
},
  "geometry": {"coordinates":[11.6560087204,48.0710792542],"type":"Point"}
}