{
  "type": "Feature",
  "properties": {
    "iso:country":"DE",
    "sg:address":"In den Sieben \u00c4ckern 7",
    "sg:city":"Bad Salzdetfurth",
    "sg:phone":"+49 5064/930310",
    "sg:postcode":"31162",
    "sg:province":"Niedersachsen",
    "wof:name":"Resch Electronic Innovation Gmbh",
    "wof:placetype":"venue"
},
  "geometry": {"coordinates":[10.024116,52.098633],"type":"Point"}
}