{
  "type": "Feature",
  "properties": {
    "iso:country":"DE",
    "sg:address":"\u00d6lbrechts 15",
    "sg:city":"Ottobeuren",
    "sg:postcode":"87724",
    "sg:province":"Bayern",
    "wof:name":"Josef Weinhardt",
    "wof:placetype":"venue"
},
  "geometry": {"coordinates":[10.340158,47.940208],"type":"Point"}
}