{
  "type": "Feature",
  "properties": {
    "iso:country":"DE",
    "sg:address":"Bahnhofstr. 38",
    "sg:city":"Kirchzarten",
    "sg:phone":"+49 7661/93350",
    "sg:postcode":"79199",
    "sg:province":"Baden-W\u00fcrttemberg",
    "wof:name":"Alte Post",
    "wof:placetype":"venue"
},
  "geometry": {"coordinates":[7.9601597786,47.9677505493],"type":"Point"}
}