{
  "type": "Feature",
  "properties": {
    "iso:country":"DE",
    "sg:address":"Hindenburgstr. 79",
    "sg:city":"Remscheid",
    "sg:phone":"+49 2191/76352",
    "sg:postcode":"42853",
    "sg:province":"Nordrhein-Westfalen",
    "wof:name":"Bernd K\u00fcppers",
    "wof:placetype":"venue"
},
  "geometry": {"coordinates":[7.1765170097,51.1846122742],"type":"Point"}
}