{
  "type": "Feature",
  "properties": {
    "iso:country":"DE",
    "sg:address":"Ruwoldtweg 1",
    "sg:city":"Hamburg",
    "sg:phone":"+49 40/6302444",
    "sg:postcode":"22309",
    "sg:province":"Hamburg",
    "wof:name":"Wilfried K\u00f6hnemann Architekt",
    "wof:placetype":"venue"
},
  "geometry": {"coordinates":[10.052011,53.609299],"type":"Point"}
}