{
  "type": "Feature",
  "properties": {
    "iso:country":"DE",
    "sg:address":"Meierstr. 29",
    "sg:city":"Stolzenau",
    "sg:phone":"+49 5761/3709",
    "sg:postcode":"31592",
    "sg:province":"Niedersachsen",
    "wof:name":"Ernst Langerwisch",
    "wof:placetype":"venue"
},
  "geometry": {"coordinates":[9.065553,52.51487],"type":"Point"}
}