{
  "type": "Feature",
  "properties": {
    "iso:country":"DE",
    "sg:address":"M\u00f6nkeh\u00f6fener Str. 5",
    "sg:city":"Ostercappeln",
    "sg:phone":"+49 5473/1691",
    "sg:postcode":"49179",
    "sg:province":"Niedersachsen",
    "wof:name":"Willi Hagedorn",
    "wof:placetype":"venue"
},
  "geometry": {"coordinates":[8.27409,52.320728],"type":"Point"}
}