{
  "type": "Feature",
  "properties": {
    "iso:country":"DE",
    "sg:address":"Schwarzm\u00fchlenstr. 102",
    "sg:city":"Gelsenkirchen",
    "sg:phone":"+49 209/135232",
    "sg:postcode":"45884",
    "sg:province":"Nordrhein-Westfalen",
    "wof:name":"Fero Kunststoffenster- U. Rolladenbau Gmbh",
    "wof:placetype":"venue"
},
  "geometry": {"coordinates":[7.078725,51.498913],"type":"Point"}
}