{
  "type": "Feature",
  "properties": {
    "iso:country":"DE",
    "sg:address":"Niddastr. 56",
    "sg:city":"Frankfurt",
    "sg:phone":"+49 69/235259",
    "sg:postcode":"60329",
    "sg:province":"Hessen",
    "wof:name":"Thorer Gmbh & Co. Pelzveredelung",
    "wof:placetype":"venue"
},
  "geometry": {"coordinates":[8.6633434296,50.1094970703],"type":"Point"}
}