{
  "type": "Feature",
  "properties": {
    "iso:country":"DE",
    "sg:address":"Weinsbergstr. 138",
    "sg:city":"K\u00f6ln",
    "sg:phone":"+49 221/525658",
    "sg:postcode":"50823",
    "sg:province":"Nordrhein-Westfalen",
    "wof:name":"Afk Arbeitskreis Friedhofsg\u00e4rtnerischer",
    "wof:placetype":"venue"
},
  "geometry": {"coordinates":[6.917893,50.943138],"type":"Point"}
}