{
  "type": "Feature",
  "properties": {
    "iso:country":"DE",
    "sg:address":"Tambacher Str. 44",
    "sg:city":"Floh-Seligenthal",
    "sg:phone":"+49 3683/69590",
    "sg:postcode":"98593",
    "sg:province":"Th\u00fcringen",
    "wof:name":"Arnika-apotheke Antje Mannest\u00e4tter",
    "wof:placetype":"venue"
},
  "geometry": {"coordinates":[10.484924,50.754341],"type":"Point"}
}