{
  "type": "Feature",
  "properties": {
    "iso:country":"DE",
    "sg:address":"Limesweg 3",
    "sg:city":"Erlensee",
    "sg:postcode":"63526",
    "sg:province":"Hessen",
    "wof:name":"Swa-procurement Consulting E. K.",
    "wof:placetype":"venue"
},
  "geometry": {"coordinates":[8.986875,50.167648],"type":"Point"}
}