{
  "type": "Feature",
  "properties": {
    "iso:country":"DE",
    "sg:address":"Das Weizenland 2",
    "sg:city":"L\u00fcderitz",
    "sg:phone":"+49 39361/203",
    "sg:postcode":"39517",
    "sg:province":"Sachsen-Anhalt",
    "wof:name":"Dachdecker-einkauf Soltau Eg",
    "wof:placetype":"venue"
},
  "geometry": {"coordinates":[11.739025,52.510963],"type":"Point"}
}