{
  "type": "Feature",
  "properties": {
    "iso:country":"DE",
    "sg:address":"Rathausstr. 12",
    "sg:city":"Altusried",
    "sg:phone":"+49 8373/352",
    "sg:postcode":"87452",
    "sg:province":"Bayern",
    "wof:name":"Xaver Fehnle",
    "wof:placetype":"venue"
},
  "geometry": {"coordinates":[10.215678,47.806068],"type":"Point"}
}