{
  "type": "Feature",
  "properties": {
    "iso:country":"DE",
    "sg:address":"Hafenstr. 60",
    "sg:city":"Braunschweig",
    "sg:phone":"+49 531/313209",
    "sg:postcode":"38112",
    "sg:province":"Niedersachsen",
    "wof:name":"Bel Air",
    "wof:placetype":"venue"
},
  "geometry": {"coordinates":[10.491602,52.310768],"type":"Point"}
}