{
  "type": "Feature",
  "properties": {
    "iso:country":"DE",
    "sg:address":"Industriestr. 22",
    "sg:city":"Bammental",
    "sg:phone":"+49 4962/2395320",
    "sg:postcode":"69245",
    "sg:province":"Baden-W\u00fcrttemberg",
    "wof:name":"B\u00c4r Gmbh",
    "wof:placetype":"venue"
},
  "geometry": {"coordinates":[8.7796602249,49.3520774841],"type":"Point"}
}