{
  "type": "Feature",
  "properties": {
    "iso:country":"DE",
    "sg:address":"Henschelstr. 7",
    "sg:city":"Maintal",
    "sg:phone":"+49 6181/494959",
    "sg:postcode":"63477",
    "sg:province":"Hessen",
    "wof:name":"E. Glaab Bauschlosserei",
    "wof:placetype":"venue"
},
  "geometry": {"coordinates":[8.848003,50.143753],"type":"Point"}
}