{
  "type": "Feature",
  "properties": {
    "iso:country":"DE",
    "sg:address":"Berliner Str. 144",
    "sg:city":"G\u00fctersloh",
    "sg:phone":"+49 5241/27545",
    "sg:postcode":"33330",
    "sg:province":"Nordrhein-Westfalen",
    "wof:name":"Edgar Sch\u00fclke",
    "wof:placetype":"venue"
},
  "geometry": {"coordinates":[8.3873643875,51.9121322632],"type":"Point"}
}