{
  "type": "Feature",
  "properties": {
    "iso:country":"DE",
    "sg:address":"Ziegeleiweg 5",
    "sg:city":"D\u00fcsseldorf",
    "sg:phone":"+49 211/773295",
    "sg:postcode":"40591",
    "sg:province":"Nordrhein-Westfalen",
    "wof:name":"Filrox & Co Ltd",
    "wof:placetype":"venue"
},
  "geometry": {"coordinates":[6.81122,51.197224],"type":"Point"}
}