{
  "type": "Feature",
  "properties": {
    "iso:country":"DE",
    "sg:address":"Detmolder Str. 122e",
    "sg:city":"Bielefeld",
    "sg:phone":"+49 521/9225999",
    "sg:postcode":"33604",
    "sg:province":"Nordrhein-Westfalen",
    "wof:name":"Thomas Thamm",
    "wof:placetype":"venue"
},
  "geometry": {"coordinates":[8.543627739,52.008190155],"type":"Point"}
}