{
  "type": "Feature",
  "properties": {
    "iso:country":"DE",
    "sg:address":"Schwarzenbergstr 4",
    "sg:city":"Bamberg",
    "sg:phone":"+49 951/980090",
    "sg:postcode":"96050",
    "sg:province":"Bayern",
    "wof:name":"Computop Wirtschaftsinformatik Gmbh",
    "wof:placetype":"venue"
},
  "geometry": {"coordinates":[10.901673,49.897671],"type":"Point"}
}