{
  "type": "Feature",
  "properties": {
    "iso:country":"DE",
    "sg:address":"Kirchgasse 9",
    "sg:city":"Schalksm\u00fchle",
    "sg:phone":"+49 2355/7466",
    "sg:postcode":"58579",
    "sg:province":"Nordrhein-Westfalen",
    "wof:name":"B. N\u00f6lke",
    "wof:placetype":"venue"
},
  "geometry": {"coordinates":[7.5298352242,51.2405433655],"type":"Point"}
}