{
  "type": "Feature",
  "properties": {
    "iso:country":"DE",
    "sg:address":"Exterbruch 1",
    "sg:city":"Gelsenkirchen",
    "sg:postcode":"45886",
    "sg:province":"Nordrhein-Westfalen",
    "wof:name":"Institut F\u00fcr Kanalisationstechnik",
    "wof:placetype":"venue"
},
  "geometry": {"coordinates":[7.135507,51.509602],"type":"Point"}
}