{
  "type": "Feature",
  "properties": {
    "iso:country":"DE",
    "sg:address":"Harrasser Str. 6",
    "sg:city":"Prien",
    "sg:postcode":"83209",
    "sg:province":"Bayern",
    "wof:name":"Prienamed Gmbh",
    "wof:placetype":"venue"
},
  "geometry": {"coordinates":[12.3639984131,47.8601646423],"type":"Point"}
}