{
  "type": "Feature",
  "properties": {
    "iso:country":"DE",
    "sg:address":"Oldenburger Str. 224",
    "sg:city":"Wardenburg",
    "sg:phone":"+49 4407/5178",
    "sg:postcode":"26203",
    "sg:province":"Niedersachsen",
    "wof:name":"Arthur Bremer",
    "wof:placetype":"venue"
},
  "geometry": {"coordinates":[8.1943893433,53.064453125],"type":"Point"}
}