{
  "type": "Feature",
  "properties": {
    "iso:country":"DE",
    "sg:address":"Winzergasse 2",
    "sg:city":"Hildburghausen",
    "sg:phone":"+49 3685/403404",
    "sg:postcode":"98646",
    "sg:province":"Th\u00fcringen",
    "wof:name":"B & D Dach- Und Fassadenbau Gmbh & Co. Kg",
    "wof:placetype":"venue"
},
  "geometry": {"coordinates":[10.736329,50.424301],"type":"Point"}
}