{
  "type": "Feature",
  "properties": {
    "iso:country":"DE",
    "sg:address":"Hornsiek 10",
    "sg:city":"D\u00f6rentrup",
    "sg:phone":"+49 5265/99941",
    "sg:postcode":"32694",
    "sg:province":"Nordrhein-Westfalen",
    "wof:name":"Ernst-wilhelm D\u00fcvel Steuerberater",
    "wof:placetype":"venue"
},
  "geometry": {"coordinates":[8.9982557297,52.0450820923],"type":"Point"}
}