{
  "type": "Feature",
  "properties": {
    "iso:country":"DE",
    "sg:address":"Donaustaufer Str. 314",
    "sg:city":"Regensburg",
    "sg:phone":"+49 941/45318",
    "sg:postcode":"93055",
    "sg:province":"Bayern",
    "wof:name":"Deutsche Shell Ag",
    "wof:placetype":"venue"
},
  "geometry": {"coordinates":[12.1481113434,49.0248527527],"type":"Point"}
}