{
  "type": "Feature",
  "properties": {
    "iso:country":"DE",
    "sg:address":"Sim-J\u00fc 10",
    "sg:city":"Werne",
    "sg:phone":"+49 2389/2000",
    "sg:postcode":"59368",
    "sg:province":"Nordrhein-Westfalen",
    "wof:name":"St\u00f6ver Und Partner",
    "wof:placetype":"venue"
},
  "geometry": {"coordinates":[7.640166,51.662022],"type":"Point"}
}