{
  "type": "Feature",
  "properties": {
    "iso:country":"DE",
    "sg:address":"Prager Str. 7",
    "sg:city":"Dresden",
    "sg:phone":"+49 351/4968042",
    "sg:postcode":"01069",
    "sg:province":"Sachsen",
    "wof:name":"Fielmann Ag & Co. Ohg",
    "wof:placetype":"venue"
},
  "geometry": {"coordinates":[13.7345542908,51.0425491333],"type":"Point"}
}