{
  "type": "Feature",
  "properties": {
    "iso:country":"DE",
    "sg:address":"Helenenberger Str. 9a",
    "sg:city":"Welschbillig",
    "sg:phone":"+49 6506/553",
    "sg:postcode":"54298",
    "sg:province":"Rheinland-Pfalz",
    "wof:name":"Ludwig Heizung-l\u00fcftung- Sanit\u00e4r Gmbh",
    "wof:placetype":"venue"
},
  "geometry": {"coordinates":[6.5623641014,49.853679657],"type":"Point"}
}