{
  "type": "Feature",
  "properties": {
    "iso:country":"DE",
    "sg:address":"Pfalzstr. 22",
    "sg:city":"St. Wendel",
    "sg:phone":"+49 6851/3936",
    "sg:postcode":"66606",
    "sg:province":"Saarland",
    "wof:name":"Hilde Schwenner",
    "wof:placetype":"venue"
},
  "geometry": {"coordinates":[7.1097931862,49.4765892029],"type":"Point"}
}