{
  "type": "Feature",
  "properties": {
    "iso:country":"DE",
    "sg:address":"Ro\u00dfplatz 11 a",
    "sg:city":"Eisenberg",
    "sg:phone":"+49 36691/52701",
    "sg:postcode":"07607",
    "sg:province":"Th\u00fcringen",
    "wof:name":"Franz Friedrich",
    "wof:placetype":"venue"
},
  "geometry": {"coordinates":[11.900583,50.966938],"type":"Point"}
}