{
  "type": "Feature",
  "properties": {
    "iso:country":"DE",
    "sg:address":"M\u00f6rsfelder Str. 3",
    "sg:city":"Stein-Bockenheim",
    "sg:phone":"+49 4967/0393080",
    "sg:postcode":"55599",
    "sg:province":"Rheinland-Pfalz",
    "wof:name":"Weingut Steitz",
    "wof:placetype":"venue"
},
  "geometry": {"coordinates":[7.955342,49.774071],"type":"Point"}
}