{
  "type": "Feature",
  "properties": {
    "iso:country":"DE",
    "sg:address":"Kirchstr. 3",
    "sg:city":"Solingen",
    "sg:phone":"+49 212/200341",
    "sg:postcode":"42651",
    "sg:province":"Nordrhein-Westfalen",
    "wof:name":"Heidi Breuer-heuser",
    "wof:placetype":"venue"
},
  "geometry": {"coordinates":[7.0831990242,51.1708984375],"type":"Point"}
}