{
  "type": "Feature",
  "properties": {
    "iso:country":"DE",
    "sg:address":"D\u00f6rrieloh 55",
    "sg:city":"Varrel",
    "sg:phone":"+49 4942/74587",
    "sg:postcode":"27259",
    "sg:province":"Niedersachsen",
    "wof:name":"Karl Hannuth Gmbh & Co. Kg",
    "wof:placetype":"venue"
},
  "geometry": {"coordinates":[8.706615448,52.6022605896],"type":"Point"}
}