{
  "type": "Feature",
  "properties": {
    "iso:country":"DE",
    "sg:address":"M\u00fcnchener Str. 1",
    "sg:city":"Mering",
    "sg:phone":"+49 8233/9705",
    "sg:postcode":"86415",
    "sg:province":"Bayern",
    "wof:name":"Eiscafe Gazzola",
    "wof:placetype":"venue"
},
  "geometry": {"coordinates":[10.986771,48.267181],"type":"Point"}
}