{
  "type": "Feature",
  "properties": {
    "iso:country":"DE",
    "sg:address":"Hofer Heide 7",
    "sg:city":"Velbert",
    "sg:phone":"+49 2051/603762",
    "sg:postcode":"42549",
    "sg:province":"Nordrhein-Westfalen",
    "wof:name":"U. Str\u00f6ter Beteiligungs- Gmbh",
    "wof:placetype":"venue"
},
  "geometry": {"coordinates":[7.016019,51.324249],"type":"Point"}
}