{
  "type": "Feature",
  "properties": {
    "iso:country":"DE",
    "sg:address":"Fr\u00f6belweg 18",
    "sg:city":"Dortmund",
    "sg:phone":"+49 177 5824310",
    "sg:postcode":"44339",
    "sg:province":"Nordrhein-Westfalen",
    "wof:name":"Aquariumkombinationen Friedeberg Atd",
    "wof:placetype":"venue"
},
  "geometry": {"coordinates":[7.4778599739,51.5573959351],"type":"Point"}
}