{
  "type": "Feature",
  "properties": {
    "iso:country":"DE",
    "sg:address":"Haunstetter Str. 8",
    "sg:city":"K\u00f6nigsbrunn",
    "sg:phone":"+49 8231/34690",
    "sg:postcode":"86343",
    "sg:province":"Bayern",
    "wof:name":"Marianne Wenninger",
    "wof:placetype":"venue"
},
  "geometry": {"coordinates":[10.8974895477,48.291809082],"type":"Point"}
}