{
  "type": "Feature",
  "properties": {
    "iso:country":"DE",
    "sg:address":"Corneliusplatz 51",
    "sg:city":"T\u00f6nisvorst",
    "sg:phone":"+49 2151/796454",
    "sg:postcode":"47918",
    "sg:province":"Nordrhein-Westfalen",
    "wof:name":"J. Peckholdt",
    "wof:placetype":"venue"
},
  "geometry": {"coordinates":[6.4882922173,51.3194236755],"type":"Point"}
}