{
  "type": "Feature",
  "properties": {
    "iso:country":"DE",
    "sg:address":"Ludwigstr. 12",
    "sg:city":"Landau",
    "sg:phone":"+49 9951/59304",
    "sg:postcode":"94405",
    "sg:province":"Bayern",
    "wof:name":"Hans Kick",
    "wof:placetype":"venue"
},
  "geometry": {"coordinates":[12.691676,48.670284],"type":"Point"}
}