{
  "type": "Feature",
  "properties": {
    "iso:country":"DE",
    "sg:address":"Karlstalstr.",
    "sg:city":"Trippstadt",
    "sg:phone":"+49 6306/309",
    "sg:postcode":"67705",
    "sg:province":"Rheinland-Pfalz",
    "wof:name":"Terrassenhotel Immenhof",
    "wof:placetype":"venue"
},
  "geometry": {"coordinates":[7.7617688179,49.3500938416],"type":"Point"}
}