{
  "type": "Feature",
  "properties": {
    "iso:country":"DE",
    "sg:address":"kleines G\u00e4sschen 13-15",
    "sg:city":"Offenbach",
    "sg:phone":"+49 69/8300560",
    "sg:postcode":"63075",
    "sg:province":"Hessen",
    "wof:name":"Langmaak Elektromaschinenbau",
    "wof:placetype":"venue"
},
  "geometry": {"coordinates":[8.796609,50.13343],"type":"Point"}
}