{
  "type": "Feature",
  "properties": {
    "iso:country":"DE",
    "sg:address":"Plattengasse 67",
    "sg:city":"Vachdorf",
    "sg:phone":"+49 36949/20541",
    "sg:postcode":"98617",
    "sg:province":"Th\u00fcringen",
    "wof:name":"Julius Fritz",
    "wof:placetype":"venue"
},
  "geometry": {"coordinates":[10.5370817184,50.5277366638],"type":"Point"}
}