{
  "type": "Feature",
  "properties": {
    "iso:country":"DE",
    "sg:address":"Ostrower Damm 9",
    "sg:city":"Cottbus",
    "sg:phone":"+49 355/792103",
    "sg:postcode":"03046",
    "sg:province":"Brandenburg",
    "wof:name":"Annette Richter",
    "wof:placetype":"venue"
},
  "geometry": {"coordinates":[14.3402080536,51.7549972534],"type":"Point"}
}