{
  "type": "Feature",
  "properties": {
    "iso:country":"DE",
    "sg:address":"Zollergasse 3",
    "sg:city":"Straubing",
    "sg:phone":"+49 9421/10809",
    "sg:postcode":"94315",
    "sg:province":"Bayern",
    "wof:name":"Wkv-bank Gmbh",
    "wof:placetype":"venue"
},
  "geometry": {"coordinates":[12.571539,48.883556],"type":"Point"}
}