{
  "type": "Feature",
  "properties": {
    "iso:country":"DE",
    "sg:address":"Osterfeldstr. 70",
    "sg:city":"Hamburg",
    "sg:phone":"+49 40/5531569",
    "sg:postcode":"22529",
    "sg:province":"Hamburg",
    "wof:name":"Holger Stege",
    "wof:placetype":"venue"
},
  "geometry": {"coordinates":[9.9681549072,53.5991973877],"type":"Point"}
}