{
  "type": "Feature",
  "properties": {
    "iso:country":"DE",
    "sg:address":"Ludwigsluster Str. 3",
    "sg:city":"Neustadt-Glewe",
    "sg:phone":"+49 38757/23730",
    "sg:postcode":"19306",
    "sg:province":"Mecklenburg-Vorpommern",
    "wof:name":"Betriebsrestaurant",
    "wof:placetype":"venue"
},
  "geometry": {"coordinates":[11.5815124512,53.3833618164],"type":"Point"}
}