{
  "type": "Feature",
  "properties": {
    "iso:country":"DE",
    "sg:address":"Berthelsdorfer Str. 77",
    "sg:city":"Freiberg",
    "sg:phone":"+49 4937/3178800",
    "sg:postcode":"09599",
    "sg:province":"Sachsen",
    "wof:name":"Thiele & Steinert Gmbh",
    "wof:placetype":"venue"
},
  "geometry": {"coordinates":[13.351365,50.90575],"type":"Point"}
}