{
  "type": "Feature",
  "properties": {
    "iso:country":"DE",
    "sg:address":"Flurstr 15-17",
    "sg:city":"Mettmann",
    "sg:phone":"+49 2104/9840",
    "sg:postcode":"40822",
    "sg:province":"Nordrhein-Westfalen",
    "wof:name":"Georg Fischer Gmbh & Co Kg",
    "wof:placetype":"venue"
},
  "geometry": {"coordinates":[6.98453,51.245667],"type":"Point"}
}