{
  "type": "Feature",
  "properties": {
    "iso:country":"DE",
    "sg:address":"Am Sportplatz 2",
    "sg:city":"Partenstein",
    "sg:phone":"+49 9355/1235",
    "sg:postcode":"97846",
    "sg:province":"Bayern",
    "wof:name":"A. Zei\u00dfner",
    "wof:placetype":"venue"
},
  "geometry": {"coordinates":[9.513243,50.043167],"type":"Point"}
}