{
  "type": "Feature",
  "properties": {
    "iso:country":"DE",
    "sg:address":"Sch\u00f6nber Landstrasse",
    "sg:city":"Sch\u00f6nkirchen",
    "sg:postcode":"24232",
    "sg:province":"Schleswig-Holstein",
    "wof:name":"F.d.p. Kreisverband Pl\u00f6n",
    "wof:placetype":"venue"
},
  "geometry": {"coordinates":[10.2298793793,54.3411827087],"type":"Point"}
}