{
  "type": "Feature",
  "properties": {
    "iso:country":"DE",
    "sg:address":"Erster Seeweg 2",
    "sg:city":"K\u00fckels",
    "sg:phone":"+49 4552/995900",
    "sg:postcode":"23829",
    "sg:province":"Schleswig-Holstein",
    "wof:name":"Spediton Hahn & Reher Gmbh",
    "wof:placetype":"venue"
},
  "geometry": {"coordinates":[10.2346954346,53.9010009766],"type":"Point"}
}