{
  "type": "Feature",
  "properties": {
    "iso:country":"DE",
    "sg:address":"Blumenweg 4",
    "sg:city":"Wedemark",
    "sg:phone":"+49 5130/79949",
    "sg:postcode":"30900",
    "sg:province":"Niedersachsen",
    "wof:name":"Marion Ebeling",
    "wof:placetype":"venue"
},
  "geometry": {"coordinates":[9.793801,52.519176],"type":"Point"}
}