{
  "type": "Feature",
  "properties": {
    "iso:country":"DE",
    "sg:address":"Gr\u00fcner Winkel 54",
    "sg:city":"Ribnitz-Damgarten",
    "sg:phone":"+49 3821/62081",
    "sg:postcode":"18311",
    "sg:province":"Mecklenburg-Vorpommern",
    "wof:name":"G & S Baugesellschaft Mbh",
    "wof:placetype":"venue"
},
  "geometry": {"coordinates":[12.4738960266,54.2608108521],"type":"Point"}
}