{
  "type": "Feature",
  "properties": {
    "iso:country":"DE",
    "sg:address":"Waldstr. 122",
    "sg:city":"Wiesbaden",
    "sg:phone":"+49 611/85344",
    "sg:postcode":"65187",
    "sg:province":"Hessen",
    "wof:name":"Siegfried Lundgr\u00fcn",
    "wof:placetype":"venue"
},
  "geometry": {"coordinates":[8.223567,50.066681],"type":"Point"}
}