{
  "type": "Feature",
  "properties": {
    "iso:country":"DE",
    "sg:address":"Wachtendonker Str. 10",
    "sg:city":"Kempen",
    "sg:phone":"+49 2152/2140",
    "sg:postcode":"47906",
    "sg:province":"Nordrhein-Westfalen",
    "wof:name":"Lochner Und Ick Rechtsanw\u00e4lte",
    "wof:placetype":"venue"
},
  "geometry": {"coordinates":[6.4155230522,51.3674125671],"type":"Point"}
}