{
  "type": "Feature",
  "properties": {
    "iso:country":"DE",
    "sg:address":"Karsp\u00fcle 2",
    "sg:city":"Uslar",
    "sg:phone":"+49 5571/2560",
    "sg:postcode":"37170",
    "sg:province":"Niedersachsen",
    "wof:name":"Erdmann Sommer",
    "wof:placetype":"venue"
},
  "geometry": {"coordinates":[9.6506290436,51.6152000427],"type":"Point"}
}