{
  "type": "Feature",
  "properties": {
    "iso:country":"DE",
    "sg:address":"Walther-v.-d.-Vogelweide-Str.",
    "sg:city":"Schweinfurt",
    "sg:phone":"+49 9721/41441",
    "sg:postcode":"97422",
    "sg:province":"Bayern",
    "wof:name":"H. Barth",
    "wof:placetype":"venue"
},
  "geometry": {"coordinates":[10.224919,50.063496],"type":"Point"}
}