{
  "type": "Feature",
  "properties": {
    "iso:country":"DE",
    "sg:address":"Max-Eyth-Str 25",
    "sg:city":"Wolfschlugen",
    "sg:phone":"+49 7022/951950",
    "sg:postcode":"72649",
    "sg:province":"Baden-W\u00fcrttemberg",
    "wof:name":"Heidler Strichcode Gmbh",
    "wof:placetype":"venue"
},
  "geometry": {"coordinates":[9.29829216,48.6480636597],"type":"Point"}
}