{
  "type": "Feature",
  "properties": {
    "iso:country":"DE",
    "sg:city":"Oberderdingen",
    "sg:phone":"+49 4972/58406",
    "sg:postcode":"75038",
    "sg:province":"Baden-W\u00fcrttemberg",
    "wof:name":"Sparkasse Bruchsal-bretten",
    "wof:placetype":"venue"
},
  "geometry": {"coordinates":[8.801774,49.062267],"type":"Point"}
}