{
  "type": "Feature",
  "properties": {
    "iso:country":"DE",
    "sg:address":"Bahnhofstr. 4",
    "sg:city":"G\u00f6rzke",
    "sg:phone":"+49 33847/40392",
    "sg:postcode":"14828",
    "sg:province":"Brandenburg",
    "wof:name":"R. Selent",
    "wof:placetype":"venue"
},
  "geometry": {"coordinates":[12.3775348663,52.1744995117],"type":"Point"}
}