{
  "type": "Feature",
  "properties": {
    "iso:country":"DE",
    "sg:address":"Goerdelerweg 1",
    "sg:city":"Darmstadt",
    "sg:phone":"+49 6151/51271",
    "sg:postcode":"64297",
    "sg:province":"Hessen",
    "wof:name":"Heinz Scheid Architekt",
    "wof:placetype":"venue"
},
  "geometry": {"coordinates":[8.652869,49.831715],"type":"Point"}
}