{
  "type": "Feature",
  "properties": {
    "iso:country":"DE",
    "sg:address":"Birkenstr. 21",
    "sg:city":"Wolfratshausen",
    "sg:postcode":"82515",
    "sg:province":"Bayern",
    "wof:name":"Bash It Ohg",
    "wof:placetype":"venue"
},
  "geometry": {"coordinates":[11.4365549088,47.9120864868],"type":"Point"}
}