{
  "type": "Feature",
  "properties": {
    "iso:country":"DE",
    "sg:address":"Schlesierstr. 14",
    "sg:city":"Radolfzell",
    "sg:phone":"+49 7732/988300",
    "sg:postcode":"78315",
    "sg:province":"Baden-W\u00fcrttemberg",
    "wof:name":"A. Gluschkow",
    "wof:placetype":"venue"
},
  "geometry": {"coordinates":[8.9711847305,47.7524185181],"type":"Point"}
}