{
  "type": "Feature",
  "properties": {
    "iso:country":"DE",
    "sg:address":"Werner-von-Siemens-Str. 9",
    "sg:city":"Neustadt",
    "sg:phone":"+49 9161/88780",
    "sg:postcode":"91413",
    "sg:province":"Bayern",
    "wof:name":"Erich Frodl Inh. Horst Frodl",
    "wof:placetype":"venue"
},
  "geometry": {"coordinates":[10.6342010498,49.5795783997],"type":"Point"}
}