{
  "type": "Feature",
  "properties": {
    "iso:country":"DE",
    "sg:address":"Neust\u00e4dter Str. 52",
    "sg:city":"Frankenberg",
    "sg:phone":"+49 6451/22562",
    "sg:postcode":"35066",
    "sg:province":"Hessen",
    "wof:name":"Aldos Kleine Kneipe",
    "wof:placetype":"venue"
},
  "geometry": {"coordinates":[8.7981023788,51.0601615906],"type":"Point"}
}