{
  "type": "Feature",
  "properties": {
    "iso:country":"DE",
    "sg:address":"Veltener Str. 54",
    "sg:city":"B\u00f6tzow",
    "sg:phone":"+49 3304/34011",
    "sg:postcode":"16727",
    "sg:province":"Brandenburg",
    "wof:name":"F.f. Peppel Gmbh",
    "wof:placetype":"venue"
},
  "geometry": {"coordinates":[13.148648262,52.6594924927],"type":"Point"}
}