{
  "type": "Feature",
  "properties": {
    "iso:country":"DE",
    "sg:address":"Stodthagener Weg 10",
    "sg:city":"Felm",
    "sg:postcode":"24244",
    "sg:province":"Schleswig-Holstein",
    "wof:name":"E. Koenig",
    "wof:placetype":"venue"
},
  "geometry": {"coordinates":[10.07583,54.416931],"type":"Point"}
}