{
  "type": "Feature",
  "properties": {
    "iso:country":"DE",
    "sg:address":"Quinckestr. 4",
    "sg:city":"Heidelberg",
    "sg:postcode":"69120",
    "sg:province":"Baden-W\u00fcrttemberg",
    "wof:name":"Fine Science Tools Gmbh",
    "wof:placetype":"venue"
},
  "geometry": {"coordinates":[8.683168,49.412785],"type":"Point"}
}