{
  "type": "Feature",
  "properties": {
    "iso:country":"DE",
    "sg:address":"Zehnthofstr. 2",
    "sg:city":"Mainz-Kastel",
    "sg:phone":"+49 6134/26408",
    "sg:postcode":"55252",
    "sg:province":"Hessen",
    "wof:name":"Weinstube Schott",
    "wof:placetype":"venue"
},
  "geometry": {"coordinates":[8.285153389,50.0084037781],"type":"Point"}
}