{
  "type": "Feature",
  "properties": {
    "iso:country":"DE",
    "sg:address":"Hauptstr. 7",
    "sg:city":"Spabr\u00fccken",
    "sg:phone":"+49 6706/351",
    "sg:postcode":"55595",
    "sg:province":"Rheinland-Pfalz",
    "wof:name":"Alfons Barth",
    "wof:placetype":"venue"
},
  "geometry": {"coordinates":[7.7116670609,49.9002151489],"type":"Point"}
}