{
  "type": "Feature",
  "properties": {
    "iso:country":"DE",
    "sg:address":"Stremmestr. 14",
    "sg:city":"Brettin",
    "sg:phone":"+49 3933/9770",
    "sg:postcode":"39307",
    "sg:province":"Sachsen-Anhalt",
    "wof:name":"Hotel-restaurant Gr\u00fcner Baum Inh. Jutta Hickethier",
    "wof:placetype":"venue"
},
  "geometry": {"coordinates":[12.19435215,52.4251747131],"type":"Point"}
}