{
  "type": "Feature",
  "properties": {
    "iso:country":"DE",
    "sg:address":"Am Anger 2",
    "sg:city":"Oberstaufen",
    "sg:phone":"+49 8386/8489",
    "sg:postcode":"87534",
    "sg:province":"Bayern",
    "wof:name":"Imbergbahn Und Ski-arena Steibis Verwaltungs Gmbh",
    "wof:placetype":"venue"
},
  "geometry": {"coordinates":[10.0205802917,47.5314483643],"type":"Point"}
}