{
  "type": "Feature",
  "properties": {
    "iso:country":"DE",
    "sg:address":"Ibenhainer Str. 58",
    "sg:city":"Waltershausen",
    "sg:phone":"+49 3622/65110",
    "sg:postcode":"99880",
    "sg:province":"Th\u00fcringen",
    "wof:name":"Wohnungsbau- Und Siedlungsgenossenschaft",
    "wof:placetype":"venue"
},
  "geometry": {"coordinates":[10.566797,50.891922],"type":"Point"}
}