{
  "type": "Feature",
  "properties": {
    "iso:country":"DE",
    "sg:address":"Nelkenstr. 12",
    "sg:city":"Ketsch",
    "sg:phone":"+49 6202/692595",
    "sg:postcode":"68775",
    "sg:province":"Baden-W\u00fcrttemberg",
    "wof:name":"Siegfried Hoppenrath",
    "wof:placetype":"venue"
},
  "geometry": {"coordinates":[8.533136,49.371696],"type":"Point"}
}