{
  "type": "Feature",
  "properties": {
    "iso:country":"DE",
    "sg:address":"Zum Erdwall 3",
    "sg:city":"Siershahn",
    "sg:phone":"+49 2623/5833",
    "sg:postcode":"56427",
    "sg:province":"Rheinland-Pfalz",
    "wof:name":"Helmut R\u00fcnz",
    "wof:placetype":"venue"
},
  "geometry": {"coordinates":[7.778096199,50.4853134155],"type":"Point"}
}