{
  "type": "Feature",
  "properties": {
    "iso:country":"DE",
    "sg:address":"Von-Neuburg-Str. 6",
    "sg:city":"Mainburg",
    "sg:phone":"+49 8751/2652",
    "sg:postcode":"84048",
    "sg:province":"Bayern",
    "wof:name":"Inge Stanglmair",
    "wof:placetype":"venue"
},
  "geometry": {"coordinates":[11.788946,48.629047],"type":"Point"}
}