{
  "type": "Feature",
  "properties": {
    "iso:country":"DE",
    "sg:address":"Mainstr. 8",
    "sg:city":"Hallstadt",
    "sg:phone":"+49 951/73527",
    "sg:postcode":"96103",
    "sg:province":"Bayern",
    "wof:name":"Christa G\u00f6ppner",
    "wof:placetype":"venue"
},
  "geometry": {"coordinates":[10.8740415573,49.9282798767],"type":"Point"}
}