{
  "type": "Feature",
  "properties": {
    "iso:country":"DE",
    "sg:address":"Talstr. 7",
    "sg:city":"Holzgerlingen",
    "sg:phone":"+49 7031/605526",
    "sg:postcode":"71088",
    "sg:province":"Baden-W\u00fcrttemberg",
    "wof:name":"Theodor Schweizer",
    "wof:placetype":"venue"
},
  "geometry": {"coordinates":[9.01282,48.633308],"type":"Point"}
}