{
  "type": "Feature",
  "properties": {
    "iso:country":"DE",
    "sg:address":"Clausstr. 50",
    "sg:city":"Chemnitz",
    "sg:phone":"+49 371/533590",
    "sg:postcode":"09126",
    "sg:province":"Sachsen",
    "wof:name":"Albrecht W\u00fcrker Anlageberater",
    "wof:placetype":"venue"
},
  "geometry": {"coordinates":[12.9409675598,50.8263473511],"type":"Point"}
}