{
  "type": "Feature",
  "properties": {
    "iso:country":"DE",
    "sg:address":"Schneereut 15 b",
    "sg:city":"Grabenst\u00e4tt",
    "sg:postcode":"83355",
    "sg:province":"Bayern",
    "wof:name":"T A C In Deutschland E. K.",
    "wof:placetype":"venue"
},
  "geometry": {"coordinates":[12.5523061752,47.8238563538],"type":"Point"}
}