{
  "type": "Feature",
  "properties": {
    "iso:country":"DE",
    "sg:address":"Marienstr. 62",
    "sg:city":"Krauschwitz",
    "sg:phone":"+49 35771/69176",
    "sg:postcode":"02957",
    "sg:province":"Sachsen",
    "wof:name":"Ruschke",
    "wof:placetype":"venue"
},
  "geometry": {"coordinates":[14.725787,51.518856],"type":"Point"}
}