{
  "type": "Feature",
  "properties": {
    "iso:country":"DE",
    "sg:address":"K\u00fchrener Str. 16",
    "sg:city":"Preetz",
    "sg:phone":"+49 4342/81304",
    "sg:postcode":"24211",
    "sg:province":"Schleswig-Holstein",
    "wof:name":"Olaf Schulz",
    "wof:placetype":"venue"
},
  "geometry": {"coordinates":[10.2796640396,54.2297325134],"type":"Point"}
}