{
  "type": "Feature",
  "properties": {
    "iso:country":"DE",
    "sg:address":"Nimbergstr. 6 a",
    "sg:city":"Freiburg",
    "sg:phone":"+49 7665/2602",
    "sg:postcode":"79108",
    "sg:province":"Baden-W\u00fcrttemberg",
    "wof:name":"Manfred J\u00e4ger",
    "wof:placetype":"venue"
},
  "geometry": {"coordinates":[7.8009600639,48.0516395569],"type":"Point"}
}