{
  "type": "Feature",
  "properties": {
    "iso:country":"DE",
    "sg:address":"Neibsheimer Str. 11",
    "sg:city":"Bretten",
    "sg:phone":"+49 7252/7411",
    "sg:postcode":"75015",
    "sg:province":"Baden-W\u00fcrttemberg",
    "wof:name":"G\u00fcnter Dausch",
    "wof:placetype":"venue"
},
  "geometry": {"coordinates":[8.702792,49.075809],"type":"Point"}
}