{
  "type": "Feature",
  "properties": {
    "iso:country":"DE",
    "sg:address":"Lehmdener Str. 24",
    "sg:city":"Damme",
    "sg:phone":"+49 5491/7607",
    "sg:postcode":"49401",
    "sg:province":"Niedersachsen",
    "wof:name":"H. Wehri",
    "wof:placetype":"venue"
},
  "geometry": {"coordinates":[8.288226,52.555637],"type":"Point"}
}