{
  "type": "Feature",
  "properties": {
    "iso:country":"DE",
    "sg:address":"Sch\u00f6nbuchstr. 45",
    "sg:city":"Leinfelden-Echterdingen",
    "sg:phone":"+49 711/753778",
    "sg:postcode":"70771",
    "sg:province":"Baden-W\u00fcrttemberg",
    "wof:name":"Ruck-zuck Zubeh\u00f6r- Vertriebs Gmbh",
    "wof:placetype":"venue"
},
  "geometry": {"coordinates":[9.1381568909,48.6887168884],"type":"Point"}
}