{
  "type": "Feature",
  "properties": {
    "iso:country":"DE",
    "sg:address":"Hauptstr. 72",
    "sg:city":"Bad Neuenahr-Ahrweiler",
    "sg:phone":"+49 2641/78286",
    "sg:postcode":"53474",
    "sg:province":"Rheinland-Pfalz",
    "wof:name":"B. Jallal",
    "wof:placetype":"venue"
},
  "geometry": {"coordinates":[7.1405878067,50.5465621948],"type":"Point"}
}