{
  "type": "Feature",
  "properties": {
    "iso:country":"DE",
    "sg:address":"Am Heidberg 23",
    "sg:city":"Duisburg",
    "sg:phone":"+49 203/7388224",
    "sg:postcode":"47259",
    "sg:province":"Nordrhein-Westfalen",
    "wof:name":"Viktoria Versicherung Agentur Ulrich Hennen",
    "wof:placetype":"venue"
},
  "geometry": {"coordinates":[6.7430849075,51.3551940918],"type":"Point"}
}