{
  "type": "Feature",
  "properties": {
    "iso:country":"DE",
    "sg:address":"Osterhofener Str. 1",
    "sg:city":"K\u00fcnzing",
    "sg:phone":"+49 8549/8427",
    "sg:postcode":"94550",
    "sg:province":"Bayern",
    "wof:name":"R\u00f6mer-apotheke",
    "wof:placetype":"venue"
},
  "geometry": {"coordinates":[13.077731,48.668213],"type":"Point"}
}