{
  "type": "Feature",
  "properties": {
    "iso:country":"DE",
    "sg:address":"Max-Planck-Str. 3",
    "sg:city":"Ritterhude",
    "sg:phone":"+49 421/6933810",
    "sg:postcode":"27721",
    "sg:province":"Niedersachsen",
    "wof:name":"High-tech-halle",
    "wof:placetype":"venue"
},
  "geometry": {"coordinates":[8.70444,53.190578],"type":"Point"}
}