{
  "type": "Feature",
  "properties": {
    "iso:country":"DE",
    "sg:address":"Dorfstr. 4",
    "sg:city":"Husum",
    "sg:phone":"+49 5027/314",
    "sg:postcode":"31632",
    "sg:province":"Niedersachsen",
    "wof:name":"Manfred D\u00f6pke",
    "wof:placetype":"venue"
},
  "geometry": {"coordinates":[9.249283,52.56691],"type":"Point"}
}