{
  "type": "Feature",
  "properties": {
    "iso:country":"DE",
    "sg:address":"Gro\u00dfe Milower Str. 67",
    "sg:city":"Rathenow",
    "sg:phone":"+49 3385/512571",
    "sg:postcode":"14712",
    "sg:province":"Brandenburg",
    "wof:name":"S\u00fcdstern-apotheke",
    "wof:placetype":"venue"
},
  "geometry": {"coordinates":[12.337592,52.601406],"type":"Point"}
}