{
  "type": "Feature",
  "properties": {
    "iso:country":"DE",
    "sg:address":"Mittelstr. 8",
    "sg:city":"Kaarst",
    "sg:phone":"+49 2131/795170",
    "sg:postcode":"41564",
    "sg:province":"Nordrhein-Westfalen",
    "wof:name":"Provinzial Versicherung Martin P\u00f6lking",
    "wof:placetype":"venue"
},
  "geometry": {"coordinates":[6.6180000305,51.2331008911],"type":"Point"}
}