{
  "type": "Feature",
  "properties": {
    "iso:country":"DE",
    "sg:address":"Zum Furtfeld 1",
    "sg:city":"March",
    "sg:postcode":"79232",
    "sg:province":"Baden-W\u00fcrttemberg",
    "wof:name":"Dr. Friedhelm Erschig Tierarzt",
    "wof:placetype":"venue"
},
  "geometry": {"coordinates":[7.7791609764,48.0563278198],"type":"Point"}
}