{
  "type": "Feature",
  "properties": {
    "iso:country":"DE",
    "sg:address":"Stichweg 12",
    "sg:city":"Siegen",
    "sg:phone":"+49 271/370110",
    "sg:postcode":"57072",
    "sg:province":"Nordrhein-Westfalen",
    "wof:name":"Gerhard Gr\u00fcbler Immobilien",
    "wof:placetype":"venue"
},
  "geometry": {"coordinates":[7.9710679054,50.8819351196],"type":"Point"}
}