{
  "type": "Feature",
  "properties": {
    "iso:country":"DE",
    "sg:address":"K\u00f6hlerweg 3",
    "sg:city":"Netphen",
    "sg:phone":"+49 271/772890",
    "sg:postcode":"57250",
    "sg:province":"Nordrhein-Westfalen",
    "wof:name":"Technoprint Druck Gmbh",
    "wof:placetype":"venue"
},
  "geometry": {"coordinates":[8.0714893341,50.9089355469],"type":"Point"}
}