{
  "type": "Feature",
  "properties": {
    "iso:country":"DE",
    "sg:address":"Kleinschmitthauser Weg 16",
    "sg:city":"D\u00fcsseldorf",
    "sg:phone":"+49 211/423005",
    "sg:postcode":"40468",
    "sg:province":"Nordrhein-Westfalen",
    "wof:name":"G. Sartingen",
    "wof:placetype":"venue"
},
  "geometry": {"coordinates":[6.775505,51.269363],"type":"Point"}
}