{
  "type": "Feature",
  "properties": {
    "iso:country":"DE",
    "sg:address":"Postfach 80:: 91075 Neunkirchen:: Germany.^^Innerer Markt 3::",
    "sg:city":"Neunkirchen",
    "sg:phone":"+49 9134/661663",
    "sg:postcode":"91077",
    "sg:province":"Bayern",
    "wof:name":"Raiffeisenbank Neunkirchen Am Brand Eg",
    "wof:placetype":"venue"
},
  "geometry": {"coordinates":[11.131025,49.61298],"type":"Point"}
}