{
  "type": "Feature",
  "properties": {
    "iso:country":"DE",
    "sg:address":"An der Isen 13",
    "sg:city":"Ampfing",
    "sg:phone":"+49 8636/698857",
    "sg:postcode":"84539",
    "sg:province":"Bayern",
    "wof:name":"Peppermint Lounge",
    "wof:placetype":"venue"
},
  "geometry": {"coordinates":[12.4226427078,48.2586250305],"type":"Point"}
}