{
  "type": "Feature",
  "properties": {
    "iso:country":"DE",
    "sg:address":"Hengebachstr. 27 OT Schmidt",
    "sg:city":"Nideggen",
    "sg:postcode":"52385",
    "sg:province":"Nordrhein-Westfalen",
    "wof:name":"Windpark Schmidt Nordeifel Beteiligungs-gmbh",
    "wof:placetype":"venue"
},
  "geometry": {"coordinates":[6.484137,50.691845],"type":"Point"}
}