{
  "type": "Feature",
  "properties": {
    "iso:country":"DE",
    "sg:address":"Schlo\u00dfstr. 23",
    "sg:city":"Borgentreich",
    "sg:phone":"+49 5645/418",
    "sg:postcode":"34434",
    "sg:province":"Nordrhein-Westfalen",
    "wof:name":"Josef K\u00fchlert",
    "wof:placetype":"venue"
},
  "geometry": {"coordinates":[9.234633,51.609566],"type":"Point"}
}