{
  "type": "Feature",
  "properties": {
    "iso:country":"DE",
    "sg:address":"Marktplatz 1",
    "sg:city":"Bad Teinach-Zavelstein",
    "sg:phone":"+49 7053/8469",
    "sg:postcode":"75385",
    "sg:province":"Baden-W\u00fcrttemberg",
    "wof:name":"H. Hahn",
    "wof:placetype":"venue"
},
  "geometry": {"coordinates":[8.689108,48.693981],"type":"Point"}
}