{
  "type": "Feature",
  "properties": {
    "iso:country":"DE",
    "sg:address":"Hirtsieferzeile 22",
    "sg:city":"Berlin",
    "sg:phone":"+49 30/6031840",
    "sg:postcode":"12351",
    "sg:province":"Berlin",
    "wof:name":"Jo Timm Architekt",
    "wof:placetype":"venue"
},
  "geometry": {"coordinates":[13.470831,52.431129],"type":"Point"}
}