{
  "type": "Feature",
  "properties": {
    "iso:country":"DE",
    "sg:address":"Wilhelmstr. 135",
    "sg:city":"Reutlingen",
    "sg:phone":"+49 7121/337873",
    "sg:postcode":"72764",
    "sg:province":"Baden-W\u00fcrttemberg",
    "wof:name":"Manfred Baum",
    "wof:placetype":"venue"
},
  "geometry": {"coordinates":[9.2151212692,48.4903030396],"type":"Point"}
}