{
  "type": "Feature",
  "properties": {
    "iso:country":"DE",
    "sg:address":"Wilhelm-Crone-Hain 42",
    "sg:city":"Ennepetal",
    "sg:phone":"+49 2333/913092",
    "sg:postcode":"58256",
    "sg:province":"Nordrhein-Westfalen",
    "wof:name":"Max Security Gmbh",
    "wof:placetype":"venue"
},
  "geometry": {"coordinates":[7.3709020615,51.301410675],"type":"Point"}
}