{
  "type": "Feature",
  "properties": {
    "iso:country":"DE",
    "sg:address":"R\u00f6sterweg 35",
    "sg:city":"M\u00fchlheim",
    "sg:phone":"+49 6108/74298",
    "sg:postcode":"63165",
    "sg:province":"Hessen",
    "wof:name":"Dietesheimer Hof",
    "wof:placetype":"venue"
},
  "geometry": {"coordinates":[8.8636751175,50.1138114929],"type":"Point"}
}