{
  "type": "Feature",
  "properties": {
    "iso:country":"DE",
    "sg:address":"Tischbeinweg 17",
    "sg:city":"Magdeburg",
    "sg:phone":"+49 391/7222855",
    "sg:postcode":"39128",
    "sg:province":"Sachsen-Anhalt",
    "wof:name":"Rudolf Purke",
    "wof:placetype":"venue"
},
  "geometry": {"coordinates":[11.601239,52.14772],"type":"Point"}
}