{
  "type": "Feature",
  "properties": {
    "iso:country":"DE",
    "sg:address":"Bamergasse 8",
    "sg:city":"Hebertshausen",
    "sg:phone":"+49 8139/375",
    "sg:postcode":"85241",
    "sg:province":"Bayern",
    "wof:name":"Anton G\u00f6ttler",
    "wof:placetype":"venue"
},
  "geometry": {"coordinates":[11.4875125885,48.3049087524],"type":"Point"}
}