{
  "type": "Feature",
  "properties": {
    "iso:country":"DE",
    "sg:address":"Schrieversweg 2",
    "sg:city":"Ratingen",
    "sg:phone":"+49 2104/52861",
    "sg:postcode":"40882",
    "sg:province":"Nordrhein-Westfalen",
    "wof:name":"Schreiber",
    "wof:placetype":"venue"
},
  "geometry": {"coordinates":[6.9456810951,51.29063797],"type":"Point"}
}