{
  "type": "Feature",
  "properties": {
    "iso:country":"DE",
    "sg:address":"Alte Landstr. 2",
    "sg:city":"Steinfeld",
    "sg:phone":"+49 6340/5490",
    "sg:postcode":"76889",
    "sg:province":"Rheinland-Pfalz",
    "wof:name":"T. Wilhelm",
    "wof:placetype":"venue"
},
  "geometry": {"coordinates":[8.033771,49.049755],"type":"Point"}
}