{
  "type": "Feature",
  "properties": {
    "iso:country":"DE",
    "sg:address":"Unterlimpurger Str. 87",
    "sg:city":"Schw\u00e4bisch Hall",
    "sg:phone":"+49 791/42385",
    "sg:postcode":"74523",
    "sg:province":"Baden-W\u00fcrttemberg",
    "wof:name":"K. W. Schied",
    "wof:placetype":"venue"
},
  "geometry": {"coordinates":[9.744715,49.104797],"type":"Point"}
}