{
  "type": "Feature",
  "properties": {
    "iso:country":"DE",
    "sg:address":"Emil-Sch\u00e4fer-Str. 20",
    "sg:city":"Krefeld",
    "sg:phone":"+49 4921/5149680",
    "sg:postcode":"47800",
    "sg:province":"Nordrhein-Westfalen",
    "wof:name":"Schages Gmbh & Co Kg",
    "wof:placetype":"venue"
},
  "geometry": {"coordinates":[6.61773,51.355892],"type":"Point"}
}