{
  "type": "Feature",
  "properties": {
    "iso:country":"DE",
    "sg:address":"Hauptstr. 38",
    "sg:city":"Derben",
    "sg:phone":"+49 39349/50908",
    "sg:postcode":"39317",
    "sg:province":"Sachsen-Anhalt",
    "wof:name":"Eckbert Giese",
    "wof:placetype":"venue"
},
  "geometry": {"coordinates":[11.9953975677,52.4224662781],"type":"Point"}
}