{
  "type": "Feature",
  "properties": {
    "iso:country":"DE",
    "sg:address":"Bahnhofstr. 1",
    "sg:city":"Colditz",
    "sg:postcode":"04680",
    "sg:province":"Sachsen",
    "wof:name":"Zilly's Modeboutique Inh. Z. Vamberszki",
    "wof:placetype":"venue"
},
  "geometry": {"coordinates":[12.802106,51.131065],"type":"Point"}
}