{
  "type": "Feature",
  "properties": {
    "iso:country":"DE",
    "sg:address":"Agricolaplatz 6",
    "sg:city":"M\u00fcnchen",
    "sg:phone":"+49 89/569859",
    "sg:postcode":"80687",
    "sg:province":"Bayern",
    "wof:name":"N. Und P. J\u00e4nsch",
    "wof:placetype":"venue"
},
  "geometry": {"coordinates":[11.4940452576,48.1410942078],"type":"Point"}
}