{
  "type": "Feature",
  "properties": {
    "iso:country":"DE",
    "sg:address":"Am Amtsgericht 2",
    "sg:city":"Eiterfeld",
    "sg:phone":"+49 6672/1720",
    "sg:postcode":"36132",
    "sg:province":"Hessen",
    "wof:name":"Wiegand",
    "wof:placetype":"venue"
},
  "geometry": {"coordinates":[9.7980279922,50.7613983154],"type":"Point"}
}