{
  "type": "Feature",
  "properties": {
    "iso:country":"DE",
    "sg:address":"Mellenseestr. 5",
    "sg:city":"Berlin",
    "sg:phone":"+49 30/5122524",
    "sg:postcode":"10319",
    "sg:province":"Berlin",
    "wof:name":"Dr. Peter Ulbrich",
    "wof:placetype":"venue"
},
  "geometry": {"coordinates":[13.510233,52.492939],"type":"Point"}
}