{
  "type": "Feature",
  "properties": {
    "iso:country":"DE",
    "sg:address":"Julius-Moser-Str. 9",
    "sg:city":"Pforzheim",
    "sg:phone":"+49 7231/38060",
    "sg:postcode":"75179",
    "sg:province":"Baden-W\u00fcrttemberg",
    "wof:name":"Rl Verwaltung Und Beteiligungen R. Lauterbach",
    "wof:placetype":"venue"
},
  "geometry": {"coordinates":[8.659762,48.901489],"type":"Point"}
}