{
  "type": "Feature",
  "properties": {
    "iso:country":"DE",
    "sg:address":"Hedem\u00fcndener Str. 20",
    "sg:city":"Hann. M\u00fcnden",
    "sg:phone":"+49 5541/903969",
    "sg:postcode":"34346",
    "sg:province":"Niedersachsen",
    "wof:name":"Restaurant Pekingenten-haus",
    "wof:placetype":"venue"
},
  "geometry": {"coordinates":[9.6688146591,51.417842865],"type":"Point"}
}