{
  "type": "Feature",
  "properties": {
    "iso:country":"DE",
    "sg:address":"Ebnerstr. 24",
    "sg:city":"Augsburg",
    "sg:phone":"+49 821/412601",
    "sg:postcode":"86154",
    "sg:province":"Bayern",
    "wof:name":"Eugen Sturm Schiersner",
    "wof:placetype":"venue"
},
  "geometry": {"coordinates":[10.8772668839,48.3789558411],"type":"Point"}
}