{
  "type": "Feature",
  "properties": {
    "iso:country":"DE",
    "sg:address":"Krumbachstr. 2",
    "sg:city":"Freising",
    "sg:phone":"+49 8161/83302",
    "sg:postcode":"85356",
    "sg:province":"Bayern",
    "wof:name":"H. Hubmann",
    "wof:placetype":"venue"
},
  "geometry": {"coordinates":[11.762342,48.396393],"type":"Point"}
}