{
  "type": "Feature",
  "properties": {
    "iso:country":"DE",
    "sg:address":"Zum Anleger 1",
    "sg:city":"Preu\u00dfisch Oldendorf",
    "sg:phone":"+49 5742/920708",
    "sg:postcode":"32361",
    "sg:province":"Nordrhein-Westfalen",
    "wof:name":"Otto Werdin",
    "wof:placetype":"venue"
},
  "geometry": {"coordinates":[8.514955,52.343712],"type":"Point"}
}