{
  "type": "Feature",
  "properties": {
    "iso:country":"DE",
    "sg:address":"G\u00e4nsemarkt 1",
    "sg:city":"Neum\u00fcnster",
    "sg:phone":"+49 4321/44097",
    "sg:postcode":"24534",
    "sg:province":"Schleswig-Holstein",
    "wof:name":"Michael Rettke",
    "wof:placetype":"venue"
},
  "geometry": {"coordinates":[9.9833517075,54.0739212036],"type":"Point"}
}