{
  "type": "Feature",
  "properties": {
    "iso:country":"DE",
    "sg:address":"Eberhardstr. 42b",
    "sg:city":"Ebersberg",
    "sg:phone":"+49 8092/22343",
    "sg:postcode":"85560",
    "sg:province":"Bayern",
    "wof:name":"J. K\u00fcrzeder Inh. Cornelia Schicht",
    "wof:placetype":"venue"
},
  "geometry": {"coordinates":[11.9681482315,48.0838432312],"type":"Point"}
}