{
  "type": "Feature",
  "properties": {
    "iso:country":"DE",
    "sg:address":"Marienplatz 7",
    "sg:city":"Trostberg",
    "sg:phone":"+49 8621",
    "sg:postcode":"83308",
    "sg:province":"Bayern",
    "wof:name":"Amler - O&p Werbung",
    "wof:placetype":"venue"
},
  "geometry": {"coordinates":[12.553508,48.027607],"type":"Point"}
}