{
  "type": "Feature",
  "properties": {
    "iso:country":"DE",
    "sg:address":"Ludwig-Einsiedel-Str. 24",
    "sg:city":"R\u00fcsselsheim",
    "sg:phone":"+49 6142/93560",
    "sg:postcode":"65428",
    "sg:province":"Hessen",
    "wof:name":"Harald Astheimer Rechtsanwalt",
    "wof:placetype":"venue"
},
  "geometry": {"coordinates":[8.4525995255,49.9622077942],"type":"Point"}
}