{
  "type": "Feature",
  "properties": {
    "iso:country":"DE",
    "sg:address":"Sommersstr. 20",
    "sg:city":"D\u00fcsseldorf",
    "sg:phone":"+49 211/486252",
    "sg:postcode":"40476",
    "sg:province":"Nordrhein-Westfalen",
    "wof:name":"H. Braun Finanzberater",
    "wof:placetype":"venue"
},
  "geometry": {"coordinates":[6.7901701927,51.2445106506],"type":"Point"}
}