{
  "type": "Feature",
  "properties": {
    "iso:country":"DE",
    "sg:address":"Westhofener Weg 2",
    "sg:city":"Monzernheim",
    "sg:phone":"+49 6244/7043",
    "sg:postcode":"55234",
    "sg:province":"Rheinland-Pfalz",
    "wof:name":"Werner Gerhard",
    "wof:placetype":"venue"
},
  "geometry": {"coordinates":[8.2289648056,49.7218780518],"type":"Point"}
}