{
  "type": "Feature",
  "properties": {
    "iso:country":"DE",
    "sg:address":"Sternbusch 14",
    "sg:city":"Emsdetten",
    "sg:phone":"+49 2572/93290",
    "sg:postcode":"48282",
    "sg:province":"Nordrhein-Westfalen",
    "wof:name":"Josef Weischer Modell- Und Prototypenbau",
    "wof:placetype":"venue"
},
  "geometry": {"coordinates":[7.512371,52.159996],"type":"Point"}
}