{
  "type": "Feature",
  "properties": {
    "iso:country":"DE",
    "sg:address":"Berg 209",
    "sg:city":"Heimenkirch",
    "sg:phone":"+49 8381/5388",
    "sg:postcode":"88178",
    "sg:province":"Bayern",
    "wof:name":"Wagner Montage Fachbetrieb Gmbh",
    "wof:placetype":"venue"
},
  "geometry": {"coordinates":[9.910901,47.632645],"type":"Point"}
}