{
  "type": "Feature",
  "properties": {
    "iso:country":"DE",
    "sg:address":"Am Nordstern 34",
    "sg:city":"Siegen",
    "sg:phone":"+49 271/72402",
    "sg:postcode":"57076",
    "sg:province":"Nordrhein-Westfalen",
    "wof:name":"Horn Beteiligungs- Und Verwaltungs Gmbh",
    "wof:placetype":"venue"
},
  "geometry": {"coordinates":[8.020199,50.906693],"type":"Point"}
}