{
  "type": "Feature",
  "properties": {
    "iso:country":"DE",
    "sg:address":"Theaterstr. 12",
    "sg:city":"W\u00fcrzburg",
    "sg:phone":"+49 931/53010",
    "sg:postcode":"97070",
    "sg:province":"Bayern",
    "wof:name":"Residenz-apotheke",
    "wof:placetype":"venue"
},
  "geometry": {"coordinates":[9.934327,49.796257],"type":"Point"}
}