{
  "type": "Feature",
  "properties": {
    "iso:country":"DE",
    "sg:address":"Birkenweg 7",
    "sg:city":"Reinbek",
    "sg:phone":"+49 40/7103512",
    "sg:postcode":"21465",
    "sg:province":"Schleswig-Holstein",
    "wof:name":"Eurocouvert Gmbh",
    "wof:placetype":"venue"
},
  "geometry": {"coordinates":[10.239895,53.557796],"type":"Point"}
}