{
  "type": "Feature",
  "properties": {
    "iso:country":"DE",
    "sg:address":"Preysingstr. 2",
    "sg:city":"Osterhofen",
    "sg:phone":"+49 9932/630",
    "sg:postcode":"94486",
    "sg:province":"Bayern",
    "wof:name":"Gastst\u00e4tte Ludwig Grunwald",
    "wof:placetype":"venue"
},
  "geometry": {"coordinates":[13.0195550919,48.7046203613],"type":"Point"}
}