{
  "type": "Feature",
  "properties": {
    "iso:country":"DE",
    "sg:address":"Kornstr. 283",
    "sg:city":"Bremen",
    "sg:phone":"+49 421/5360074",
    "sg:postcode":"28201",
    "sg:province":"Bremen",
    "wof:name":"Licht-werk",
    "wof:placetype":"venue"
},
  "geometry": {"coordinates":[8.8132295609,53.0557327271],"type":"Point"}
}