{
  "type": "Feature",
  "properties": {
    "iso:country":"DE",
    "sg:address":"Pyratalstr. 27",
    "sg:city":"Morgenr\u00f6the-Rautenkranz",
    "sg:phone":"+49 37465/2552",
    "sg:postcode":"08262",
    "sg:province":"Sachsen",
    "wof:name":"Eberhard Sch\u00fcrer",
    "wof:placetype":"venue"
},
  "geometry": {"coordinates":[12.512031,50.444897],"type":"Point"}
}