{
  "type": "Feature",
  "properties": {
    "iso:country":"DE",
    "sg:address":"Inselstr. 3",
    "sg:city":"Pforzheim",
    "sg:phone":"+49 7231/391079",
    "sg:postcode":"75181",
    "sg:province":"Baden-W\u00fcrttemberg",
    "wof:name":"Stadtteilbad Eutingen",
    "wof:placetype":"venue"
},
  "geometry": {"coordinates":[8.7472419739,48.9090995789],"type":"Point"}
}