{
  "type": "Feature",
  "properties": {
    "iso:country":"DE",
    "sg:address":"Oberlandstra\u00dfe 26-35",
    "sg:city":"Berlin",
    "sg:phone":"+49 4930/757820",
    "sg:postcode":"12099",
    "sg:province":"Berlin",
    "wof:name":"Berliner Union-film Gmbh & Co Studio Kg - Berlin",
    "wof:placetype":"venue"
},
  "geometry": {"coordinates":[13.4123868942,52.4644737244],"type":"Point"}
}