{
  "type": "Feature",
  "properties": {
    "iso:country":"DE",
    "sg:address":"John-F.-Kennedy-Str. 26",
    "sg:city":"Hanau",
    "sg:phone":"+49 6181/51270",
    "sg:postcode":"63457",
    "sg:province":"Hessen",
    "wof:name":"Schaub Automaten Betriebs Gmbh",
    "wof:placetype":"venue"
},
  "geometry": {"coordinates":[8.9659509659,50.1043510437],"type":"Point"}
}