{
  "type": "Feature",
  "properties": {
    "iso:country":"DE",
    "sg:address":"Bahnhofstr. 2",
    "sg:city":"Remshalden",
    "sg:phone":"+49 7151/71068",
    "sg:postcode":"73630",
    "sg:province":"Baden-W\u00fcrttemberg",
    "wof:name":"Christoph Fetzer Architekt",
    "wof:placetype":"venue"
},
  "geometry": {"coordinates":[9.418768,48.816406],"type":"Point"}
}