{
  "type": "Feature",
  "properties": {
    "iso:country":"DE",
    "sg:address":"Lindenstr. 18",
    "sg:city":"Hirschberg",
    "sg:phone":"+49 6201/52854",
    "sg:postcode":"69493",
    "sg:province":"Baden-W\u00fcrttemberg",
    "wof:name":"Gertrud Schrenk Masseur",
    "wof:placetype":"venue"
},
  "geometry": {"coordinates":[8.659131,49.500328],"type":"Point"}
}