{
  "type": "Feature",
  "properties": {
    "iso:country":"DE",
    "sg:address":"Oberstr. 142",
    "sg:city":"Boppard",
    "sg:phone":"+49 6742/2102",
    "sg:postcode":"56154",
    "sg:province":"Rheinland-Pfalz",
    "wof:name":"W. Brockamp",
    "wof:placetype":"venue"
},
  "geometry": {"coordinates":[7.5889849663,50.231754303],"type":"Point"}
}