{
  "type": "Feature",
  "properties": {
    "iso:country":"DE",
    "sg:address":"Papenstieg 3",
    "sg:city":"Hannover",
    "sg:phone":"+49 511/854997",
    "sg:postcode":"30171",
    "sg:province":"Niedersachsen",
    "wof:name":"Annelore Tonscheidt Rechtsanw\u00e4ltin",
    "wof:placetype":"venue"
},
  "geometry": {"coordinates":[9.7487277985,52.367477417],"type":"Point"}
}