{
  "type": "Feature",
  "properties": {
    "iso:country":"DE",
    "sg:address":"Gauaschacher Str. 35",
    "sg:city":"Hammelburg",
    "sg:phone":"+49 9350/280",
    "sg:postcode":"97762",
    "sg:province":"Bayern",
    "wof:name":"Burkard Bickel",
    "wof:placetype":"venue"
},
  "geometry": {"coordinates":[9.9316186905,50.0477561951],"type":"Point"}
}