{
  "type": "Feature",
  "properties": {
    "iso:country":"DE",
    "sg:address":"Lamstedter Str. 7",
    "sg:city":"Hemmoor",
    "sg:phone":"+49 4771/2031",
    "sg:postcode":"21745",
    "sg:province":"Niedersachsen",
    "wof:name":"M\u00f6belgro\u00dflager Hemmoor Gmbh",
    "wof:placetype":"venue"
},
  "geometry": {"coordinates":[9.1639404297,53.6867218018],"type":"Point"}
}