{
  "type": "Feature",
  "properties": {
    "iso:country":"DE",
    "sg:address":"Hauptstr. 16",
    "sg:city":"Lorup",
    "sg:phone":"+49 5954/609",
    "sg:postcode":"26901",
    "sg:province":"Niedersachsen",
    "wof:name":"Imbiss Kiebitz",
    "wof:placetype":"venue"
},
  "geometry": {"coordinates":[7.6422119141,52.9253730774],"type":"Point"}
}