{
  "type": "Feature",
  "properties": {
    "iso:country":"DE",
    "sg:address":"Cederwald 4",
    "sg:city":"Bergisch Gladbach",
    "sg:phone":"+49 2202/932544",
    "sg:postcode":"51465",
    "sg:province":"Nordrhein-Westfalen",
    "wof:name":"Manfred Haesemann Rechtsanwalt",
    "wof:placetype":"venue"
},
  "geometry": {"coordinates":[7.1248002052,50.9848632812],"type":"Point"}
}