{
  "type": "Feature",
  "properties": {
    "iso:country":"DE",
    "sg:address":"Westheimer Weg 61",
    "sg:city":"Remseck",
    "sg:phone":"+49 7146/163772",
    "sg:postcode":"71686",
    "sg:province":"Baden-W\u00fcrttemberg",
    "wof:name":"Aurenz",
    "wof:placetype":"venue"
},
  "geometry": {"coordinates":[9.26894,48.87714],"type":"Point"}
}