{
  "type": "Feature",
  "properties": {
    "iso:country":"DE",
    "sg:address":"Hauptstr. 27",
    "sg:city":"Lauterstein",
    "sg:phone":"+49 7332/921960",
    "sg:postcode":"73111",
    "sg:province":"Baden-W\u00fcrttemberg",
    "wof:name":"W. Wurzinger",
    "wof:placetype":"venue"
},
  "geometry": {"coordinates":[9.8605070114,48.709777832],"type":"Point"}
}