{
  "type": "Feature",
  "properties": {
    "iso:country":"DE",
    "sg:address":"Bahnhofstr. 10",
    "sg:city":"Wolfratshausen",
    "sg:phone":"+49 8171/18415",
    "sg:postcode":"82515",
    "sg:province":"Bayern",
    "wof:name":"Oswald Gmbh",
    "wof:placetype":"venue"
},
  "geometry": {"coordinates":[11.422368,47.914986],"type":"Point"}
}