{
  "type": "Feature",
  "properties": {
    "iso:country":"DE",
    "sg:address":"Lindenstr. 2",
    "sg:city":"Hohentengen",
    "sg:phone":"+49 7572/711316",
    "sg:postcode":"88367",
    "sg:province":"Baden-W\u00fcrttemberg",
    "wof:name":"Reck & Sohn Gmbh",
    "wof:placetype":"venue"
},
  "geometry": {"coordinates":[9.387132,48.033585],"type":"Point"}
}