{
  "type": "Feature",
  "properties": {
    "iso:country":"DE",
    "sg:address":"Unterer Markt 9",
    "sg:city":"Hersbruck",
    "sg:phone":"+49 9151/4974",
    "sg:postcode":"91217",
    "sg:province":"Bayern",
    "wof:name":"Walter Oertel",
    "wof:placetype":"venue"
},
  "geometry": {"coordinates":[11.429336,49.508251],"type":"Point"}
}