{
  "type": "Feature",
  "properties": {
    "iso:country":"DE",
    "sg:address":"Wunnensteinstr. 41",
    "sg:city":"Stuttgart",
    "sg:postcode":"70186",
    "sg:province":"Baden-W\u00fcrttemberg",
    "wof:name":"Szabo Gmbh",
    "wof:placetype":"venue"
},
  "geometry": {"coordinates":[9.204948,48.780018],"type":"Point"}
}