{
  "type": "Feature",
  "properties": {
    "iso:country":"DE",
    "sg:address":"Am Isarkanal 22",
    "sg:city":"M\u00fcnchen",
    "sg:postcode":"81379",
    "sg:province":"Bayern",
    "wof:name":"Isar Anlagen Gmbh",
    "wof:placetype":"venue"
},
  "geometry": {"coordinates":[11.549955368,48.103717804],"type":"Point"}
}