{
  "type": "Feature",
  "properties": {
    "iso:country":"DE",
    "sg:address":"Bachstr. 9",
    "sg:city":"M\u00fclheim",
    "sg:phone":"+49 208/380550",
    "sg:postcode":"45468",
    "sg:province":"Nordrhein-Westfalen",
    "wof:name":"Mens Hair Shop",
    "wof:placetype":"venue"
},
  "geometry": {"coordinates":[6.881881237,51.4264526367],"type":"Point"}
}