{
  "type": "Feature",
  "properties": {
    "iso:country":"DE",
    "sg:address":"Rottenackerstr. 11",
    "sg:city":"Munderkingen",
    "sg:phone":"+49 7393/530",
    "sg:postcode":"89597",
    "sg:province":"Baden-W\u00fcrttemberg",
    "wof:name":"Hahl Filaments Gmbh & Co. Kg",
    "wof:placetype":"venue"
},
  "geometry": {"coordinates":[9.649175,48.236435],"type":"Point"}
}