{
  "type": "Feature",
  "properties": {
    "iso:country":"DE",
    "sg:address":"Bo\u00dflerweg 18",
    "sg:city":"Leinfelden-Echterdingen",
    "sg:postcode":"70771",
    "sg:province":"Baden-W\u00fcrttemberg",
    "wof:name":"Zanders Feinpapiere Gmbh",
    "wof:placetype":"venue"
},
  "geometry": {"coordinates":[9.1196594238,48.7037620544],"type":"Point"}
}