{
  "type": "Feature",
  "properties": {
    "iso:country":"DE",
    "sg:address":"Landsberger Str. 3d",
    "sg:city":"Meiningen",
    "sg:phone":"+49 3693/470991",
    "sg:postcode":"98617",
    "sg:province":"Th\u00fcringen",
    "wof:name":"B\u00fcroteam Schneider & Partner Gmbh",
    "wof:placetype":"venue"
},
  "geometry": {"coordinates":[10.410669,50.576077],"type":"Point"}
}