{
  "type": "Feature",
  "properties": {
    "iso:country":"DE",
    "sg:address":"Konrad-Adenauer-Str. 2",
    "sg:city":"Griesheim",
    "sg:phone":"+49 6155/62324",
    "sg:postcode":"64347",
    "sg:province":"Hessen",
    "wof:name":"Sanbau Baubetreuungs Gmbh",
    "wof:placetype":"venue"
},
  "geometry": {"coordinates":[8.57201,49.865211],"type":"Point"}
}