{
  "type": "Feature",
  "properties": {
    "iso:country":"DE",
    "sg:address":"F\u00fcrstenberger Str. 18",
    "sg:city":"Feldberg",
    "sg:phone":"+49 39831/20358",
    "sg:postcode":"17258",
    "sg:province":"Mecklenburg-Vorpommern",
    "wof:name":"Elco Kl\u00f6ckner Heiztechnik Gmbh",
    "wof:placetype":"venue"
},
  "geometry": {"coordinates":[13.4376659393,53.3349723816],"type":"Point"}
}