{
  "type": "Feature",
  "properties": {
    "iso:country":"DE",
    "sg:address":"Mainzer Str. 54",
    "sg:city":"Ockenheim",
    "sg:phone":"+49 6725/2903",
    "sg:postcode":"55437",
    "sg:province":"Rheinland-Pfalz",
    "wof:name":"Kurt Eckes",
    "wof:placetype":"venue"
},
  "geometry": {"coordinates":[7.9732079506,49.9426803589],"type":"Point"}
}