{
  "type": "Feature",
  "properties": {
    "iso:country":"DE",
    "sg:address":"Bopserwaldstr. 45",
    "sg:city":"Stuttgart",
    "sg:phone":"+49 711/237380",
    "sg:postcode":"70184",
    "sg:province":"Baden-W\u00fcrttemberg",
    "wof:name":"Rat Rieker Alber Thoni Revisions- Und Treuhand Gmbh",
    "wof:placetype":"venue"
},
  "geometry": {"coordinates":[9.1876831055,48.7681427002],"type":"Point"}
}