{
  "type": "Feature",
  "properties": {
    "iso:country":"DE",
    "sg:address":"Gustav-Sch\u00f6ller-Str. 19",
    "sg:city":"M\u00f6ssingen",
    "sg:phone":"+49 7473/8274",
    "sg:postcode":"72116",
    "sg:province":"Baden-W\u00fcrttemberg",
    "wof:name":"Ulrich Schneider",
    "wof:placetype":"venue"
},
  "geometry": {"coordinates":[9.115579,48.414726],"type":"Point"}
}