{
  "type": "Feature",
  "properties": {
    "iso:country":"DE",
    "sg:address":"Wallstr. 11",
    "sg:city":"Emmerich",
    "sg:phone":"+49 4928/223440",
    "sg:postcode":"46446",
    "sg:province":"Nordrhein-Westfalen",
    "wof:name":"Stolz & Gerhards Gmbh",
    "wof:placetype":"venue"
},
  "geometry": {"coordinates":[6.2431221008,51.8349494934],"type":"Point"}
}