{
  "type": "Feature",
  "properties": {
    "iso:country":"DE",
    "sg:address":"Hauptstr. 30",
    "sg:city":"Weilbach",
    "sg:phone":"+49 9373/8581",
    "sg:postcode":"63937",
    "sg:province":"Bayern",
    "wof:name":"Sparkasse Miltenberg-obernburg",
    "wof:placetype":"venue"
},
  "geometry": {"coordinates":[9.214754,49.667862],"type":"Point"}
}