{
  "type": "Feature",
  "properties": {
    "iso:country":"DE",
    "sg:address":"Landstr. 61",
    "sg:city":"Hechthausen",
    "sg:phone":"+49 4774/1291",
    "sg:postcode":"21755",
    "sg:province":"Niedersachsen",
    "wof:name":"Hans-hinrich Dankers",
    "wof:placetype":"venue"
},
  "geometry": {"coordinates":[9.21349,53.635529],"type":"Point"}
}