{
  "type": "Feature",
  "properties": {
    "iso:country":"DE",
    "sg:address":"Germeringer Str. 23",
    "sg:city":"Gauting",
    "sg:phone":"+49 89/8507980",
    "sg:postcode":"82131",
    "sg:province":"Bayern",
    "wof:name":"D. Behringer",
    "wof:placetype":"venue"
},
  "geometry": {"coordinates":[11.378065,48.075207],"type":"Point"}
}