{
  "type": "Feature",
  "properties": {
    "iso:country":"DE",
    "sg:address":"Hallstrasse 4",
    "sg:city":"Augsburg",
    "sg:phone":"+49 821/152030",
    "sg:postcode":"86150",
    "sg:province":"Bayern",
    "wof:name":"Pianohaus Hermes & Weger Gmbh",
    "wof:placetype":"venue"
},
  "geometry": {"coordinates":[10.898519,48.36454],"type":"Point"}
}