{
  "type": "Feature",
  "properties": {
    "iso:country":"DE",
    "sg:address":"Frankfurter Str. 35",
    "sg:city":"Eisdorf",
    "sg:phone":"+49 5522/82009",
    "sg:postcode":"37534",
    "sg:province":"Niedersachsen",
    "wof:name":"A. Ohse Jun.",
    "wof:placetype":"venue"
},
  "geometry": {"coordinates":[10.1776981354,51.7611312866],"type":"Point"}
}