{
  "type": "Feature",
  "properties": {
    "iso:country":"DE",
    "sg:address":"Giersberg 32",
    "sg:city":"Dattenberg",
    "sg:phone":"+49 2644/2610",
    "sg:postcode":"53547",
    "sg:province":"Rheinland-Pfalz",
    "wof:name":"Schneider-beton Gmbh",
    "wof:placetype":"venue"
},
  "geometry": {"coordinates":[7.293577,50.550526],"type":"Point"}
}