{
  "type": "Feature",
  "properties": {
    "iso:country":"DE",
    "sg:address":"Vahlandstr. 1",
    "sg:city":"Nienburg",
    "sg:phone":"+49 5021/7473",
    "sg:postcode":"31582",
    "sg:province":"Niedersachsen",
    "wof:name":"A. Klepper",
    "wof:placetype":"venue"
},
  "geometry": {"coordinates":[9.216427803,52.6301116943],"type":"Point"}
}