{
  "type": "Feature",
  "properties": {
    "iso:country":"DE",
    "sg:address":"Rosenstr. 4",
    "sg:city":"Stadensen",
    "sg:phone":"+49 5802/4821",
    "sg:postcode":"29596",
    "sg:province":"Niedersachsen",
    "wof:name":"Arnold Schulz",
    "wof:placetype":"venue"
},
  "geometry": {"coordinates":[10.554925,52.873051],"type":"Point"}
}