{
  "type": "Feature",
  "properties": {
    "iso:country":"DE",
    "sg:address":"Dorfstra\u00dfe 110",
    "sg:city":"Langenhorn",
    "sg:phone":"+49 4672",
    "sg:postcode":"25842",
    "sg:province":"Schleswig-Holstein",
    "wof:name":"Parkett Steinmassl",
    "wof:placetype":"venue"
},
  "geometry": {"coordinates":[8.9224853516,54.6786499023],"type":"Point"}
}