{
  "type": "Feature",
  "properties": {
    "iso:country":"DE",
    "sg:address":"Feuerbachplatz",
    "sg:city":"Mannheim",
    "sg:phone":"+49 621/412408",
    "sg:postcode":"68163",
    "sg:province":"Baden-W\u00fcrttemberg",
    "wof:name":"Friebe Luftfahrt-bedarf Gmbh",
    "wof:placetype":"venue"
},
  "geometry": {"coordinates":[8.507825,49.480495],"type":"Point"}
}