{
  "type": "Feature",
  "properties": {
    "iso:country":"DE",
    "sg:address":"Friedrich-Menzefricke-Str 4",
    "sg:city":"Versmold",
    "sg:phone":"+49 5423/20760",
    "sg:postcode":"33775",
    "sg:province":"Nordrhein-Westfalen",
    "wof:name":"Novotec Handelsges. Mbh & Co",
    "wof:placetype":"venue"
},
  "geometry": {"coordinates":[8.1390590668,52.038192749],"type":"Point"}
}