{
  "type": "Feature",
  "properties": {
    "iso:country":"DE",
    "sg:address":"Egerlandstr. 7",
    "sg:city":"Bad Kissingen",
    "sg:phone":"+49 971/4503",
    "sg:postcode":"97688",
    "sg:province":"Bayern",
    "wof:name":"Andreas Stumpf",
    "wof:placetype":"venue"
},
  "geometry": {"coordinates":[10.0504417419,50.1917533875],"type":"Point"}
}