{
  "type": "Feature",
  "properties": {
    "iso:country":"DE",
    "sg:address":"Sch\u00f6nberger Weg 15",
    "sg:city":"Frankfurt",
    "sg:phone":"+49 69/762031",
    "sg:postcode":"60488",
    "sg:province":"Hessen",
    "wof:name":"K & G Karto & Grafik Verlagsgesellschaft Mbh",
    "wof:placetype":"venue"
},
  "geometry": {"coordinates":[8.6133680344,50.1496276855],"type":"Point"}
}