{
  "type": "Feature",
  "properties": {
    "iso:country":"DE",
    "sg:address":"Am Freibad 9",
    "sg:city":"Berlin",
    "sg:phone":"+49 30/4026050",
    "sg:postcode":"13469",
    "sg:province":"Berlin",
    "wof:name":"Strandbad L\u00fcbars",
    "wof:placetype":"venue"
},
  "geometry": {"coordinates":[13.3366794586,52.6181716919],"type":"Point"}
}