{
  "type": "Feature",
  "properties": {
    "iso:country":"DE",
    "sg:address":"Kurmainzstr. 50a",
    "sg:city":"Mainz",
    "sg:phone":"+49 6131",
    "sg:postcode":"55126",
    "sg:province":"Rheinland-Pfalz",
    "wof:name":"Schilz Immobilien Aktuell Gmbh",
    "wof:placetype":"venue"
},
  "geometry": {"coordinates":[8.1813697815,49.9847488403],"type":"Point"}
}