{
  "type": "Feature",
  "properties": {
    "iso:country":"DE",
    "sg:address":"Bahnhofstr. 4",
    "sg:city":"Jettingen-Scheppach",
    "sg:phone":"+49 8225/1034",
    "sg:postcode":"89343",
    "sg:province":"Bayern",
    "wof:name":"Deutsche Bahn Ag",
    "wof:placetype":"venue"
},
  "geometry": {"coordinates":[10.4457082748,48.3989028931],"type":"Point"}
}