{
  "type": "Feature",
  "properties": {
    "iso:country":"DE",
    "sg:address":"Bismarckstr. 79",
    "sg:city":"Gelsenkirchen",
    "sg:postcode":"45881",
    "sg:province":"Nordrhein-Westfalen",
    "wof:name":"Gothaer Versicherungsbank",
    "wof:placetype":"venue"
},
  "geometry": {"coordinates":[7.1029992104,51.5173606873],"type":"Point"}
}