{
  "type": "Feature",
  "properties": {
    "iso:country":"DE",
    "sg:address":"Schalker Str. 79",
    "sg:city":"Gelsenkirchen",
    "sg:phone":"+49 209/496608",
    "sg:postcode":"45881",
    "sg:province":"Nordrhein-Westfalen",
    "wof:name":"Nina Grill",
    "wof:placetype":"venue"
},
  "geometry": {"coordinates":[7.0915751457,51.516242981],"type":"Point"}
}