{
  "type": "Feature",
  "properties": {
    "iso:country":"DE",
    "sg:address":"M\u00fchlgasse 1",
    "sg:city":"Wertingen",
    "sg:phone":"+49 8272/99790",
    "sg:postcode":"86637",
    "sg:province":"Bayern",
    "wof:name":"Buhl Gastronomie Personalservice Gmbh",
    "wof:placetype":"venue"
},
  "geometry": {"coordinates":[10.6836442947,48.5606040955],"type":"Point"}
}