{
  "type": "Feature",
  "properties": {
    "iso:country":"DE",
    "sg:address":"Industriegel\u00e4nde Am Zoll",
    "sg:city":"Nonnweiler",
    "sg:phone":"+49 4968/73855",
    "sg:postcode":"66620",
    "sg:province":"Saarland",
    "wof:name":"Wagner Gmbh & Co. Kg",
    "wof:placetype":"venue"
},
  "geometry": {"coordinates":[6.97,49.606369],"type":"Point"}
}