{
  "type": "Feature",
  "properties": {
    "iso:country":"DE",
    "sg:address":"Lindenplatz 6",
    "sg:city":"Gerswalde",
    "sg:phone":"+49 39887/244",
    "sg:postcode":"17268",
    "sg:province":"Brandenburg",
    "wof:name":"Linden-apotheke",
    "wof:placetype":"venue"
},
  "geometry": {"coordinates":[13.752532,53.171692],"type":"Point"}
}