{
  "type": "Feature",
  "properties": {
    "iso:country":"DE",
    "sg:address":"Pillmannstr 35",
    "sg:city":"Braunschweig",
    "sg:phone":"+49 531/2372080",
    "sg:postcode":"38112",
    "sg:province":"Niedersachsen",
    "wof:name":"Bauvision Management Bvm Gmbh",
    "wof:placetype":"venue"
},
  "geometry": {"coordinates":[10.471162796,52.3181533813],"type":"Point"}
}