{
  "type": "Feature",
  "properties": {
    "iso:country":"DE",
    "sg:address":"Aulendorfer Str. 51",
    "sg:city":"Bad Schussenried",
    "sg:phone":"+49 7583/2327",
    "sg:postcode":"88427",
    "sg:province":"Baden-W\u00fcrttemberg",
    "wof:name":"Elisabeth Straub",
    "wof:placetype":"venue"
},
  "geometry": {"coordinates":[9.655101,47.999638],"type":"Point"}
}