{
  "type": "Feature",
  "properties": {
    "iso:country":"DE",
    "sg:address":"Buchenweg 9",
    "sg:city":"Kaufbeuren",
    "sg:phone":"+49 8341/62570",
    "sg:postcode":"87600",
    "sg:province":"Bayern",
    "wof:name":"S\u00fcd-optik Schirmer",
    "wof:placetype":"venue"
},
  "geometry": {"coordinates":[10.6284856796,47.9081459045],"type":"Point"}
}