{
  "type": "Feature",
  "properties": {
    "iso:country":"DE",
    "sg:address":"Hattinger Str. 804",
    "sg:city":"Bochum",
    "sg:phone":"+49 234/494641",
    "sg:postcode":"44879",
    "sg:province":"Nordrhein-Westfalen",
    "wof:name":"Pizzeria Bei Peppone",
    "wof:placetype":"venue"
},
  "geometry": {"coordinates":[7.1624441147,51.4274101257],"type":"Point"}
}