{
  "type": "Feature",
  "properties": {
    "iso:country":"DE",
    "sg:address":"ZAC de Chassagne",
    "sg:city":"TERNAY",
    "sg:postcode":"69360",
    "wof:name":"Soci\u00e9t\u00e9 Aipro",
    "wof:placetype":"venue"
},
  "geometry": {"coordinates":[4.810099,45.606453],"type":"Point"}
}