{
  "type": "Feature",
  "properties": {
    "iso:country":"DE",
    "sg:address":"Hauptstr. 26",
    "sg:city":"Salzhemmendorf",
    "sg:postcode":"31020",
    "sg:province":"Niedersachsen",
    "wof:name":"Taxi-meinecke E. K.",
    "wof:placetype":"venue"
},
  "geometry": {"coordinates":[9.5892267227,52.0661506653],"type":"Point"}
}