{
  "type": "Feature",
  "properties": {
    "iso:country":"DE",
    "sg:address":"Am Gries 32",
    "sg:city":"Isen",
    "sg:phone":"+49 8083/275",
    "sg:postcode":"84424",
    "sg:province":"Bayern",
    "wof:name":"Georg Reiter",
    "wof:placetype":"venue"
},
  "geometry": {"coordinates":[12.053875,48.213825],"type":"Point"}
}