{
  "type": "Feature",
  "properties": {
    "iso:country":"DE",
    "sg:address":"Neckarauer Str. 9",
    "sg:city":"Mannheim",
    "sg:phone":"+49 621/853035",
    "sg:postcode":"68199",
    "sg:province":"Baden-W\u00fcrttemberg",
    "wof:name":"Arthur Weiland",
    "wof:placetype":"venue"
},
  "geometry": {"coordinates":[8.494325,49.454533],"type":"Point"}
}