{
  "type": "Feature",
  "properties": {
    "iso:country":"DE",
    "sg:address":"Lenbachstr. 89",
    "sg:city":"Stuttgart",
    "sg:phone":"+49 711/853414",
    "sg:postcode":"70192",
    "sg:province":"Baden-W\u00fcrttemberg",
    "wof:name":"Prof. Detlev Simons Architekt",
    "wof:placetype":"venue"
},
  "geometry": {"coordinates":[9.168016,48.804989],"type":"Point"}
}