{
  "type": "Feature",
  "properties": {
    "iso:country":"DE",
    "sg:address":"Forsthausweg 4 a",
    "sg:city":"Meerbusch",
    "sg:phone":"+49 2132/10777",
    "sg:postcode":"40667",
    "sg:province":"Nordrhein-Westfalen",
    "wof:name":"R. Heider Metzgerei",
    "wof:placetype":"venue"
},
  "geometry": {"coordinates":[6.6766881943,51.2633895874],"type":"Point"}
}