{
  "type": "Feature",
  "properties": {
    "iso:country":"DE",
    "sg:address":"Bluntschlistr. 14",
    "sg:city":"Heidelberg",
    "sg:phone":"+49 6221/53050",
    "sg:postcode":"69115",
    "sg:province":"Baden-W\u00fcrttemberg",
    "wof:name":"Gesellschaft F\u00fcr Grund- Und Hausbesitz Mbh",
    "wof:placetype":"venue"
},
  "geometry": {"coordinates":[8.6808900833,49.4069328308],"type":"Point"}
}