{
  "type": "Feature",
  "properties": {
    "iso:country":"DE",
    "sg:address":"B\u00f6rstel 9",
    "sg:city":"Berge",
    "sg:phone":"+49 5435/418",
    "sg:postcode":"49626",
    "sg:province":"Niedersachsen",
    "wof:name":"Alte Stifts-sch\u00e4nke",
    "wof:placetype":"venue"
},
  "geometry": {"coordinates":[7.7323861122,52.6227493286],"type":"Point"}
}