{
  "type": "Feature",
  "properties": {
    "iso:country":"DE",
    "sg:address":"Gro\u00dfe Seestr. 28",
    "sg:city":"Frankfurt",
    "sg:phone":"+49 69/705775",
    "sg:postcode":"60486",
    "sg:province":"Hessen",
    "wof:name":"Flash Videothek",
    "wof:placetype":"venue"
},
  "geometry": {"coordinates":[8.644115448,50.1206512451],"type":"Point"}
}