{
  "type": "Feature",
  "properties": {
    "iso:country":"DE",
    "sg:address":"Op'n Stiegen 3",
    "sg:city":"B\u00f6nningstedt",
    "sg:phone":"+49 40/5567220",
    "sg:postcode":"25474",
    "sg:province":"Schleswig-Holstein",
    "wof:name":"Monique Ritz",
    "wof:placetype":"venue"
},
  "geometry": {"coordinates":[9.90431,53.665619],"type":"Point"}
}