{
  "type": "Feature",
  "properties": {
    "iso:country":"DE",
    "sg:address":"Erbacher Str. 37",
    "sg:city":"Brensbach",
    "sg:phone":"+49 6161/2369",
    "sg:postcode":"64395",
    "sg:province":"Hessen",
    "wof:name":"Philipp Reibold",
    "wof:placetype":"venue"
},
  "geometry": {"coordinates":[8.8832836151,49.7520713806],"type":"Point"}
}