{
  "type": "Feature",
  "properties": {
    "iso:country":"DE",
    "sg:address":"Hauptstr. 43",
    "sg:city":"Wallhausen",
    "sg:phone":"+49 6706/251",
    "sg:postcode":"55595",
    "sg:province":"Rheinland-Pfalz",
    "wof:name":"Friedrich Knichel",
    "wof:placetype":"venue"
},
  "geometry": {"coordinates":[7.7691001892,49.8891830444],"type":"Point"}
}