{
  "type": "Feature",
  "properties": {
    "iso:country":"DE",
    "sg:address":"Justinus-Kerner-Str. 7",
    "sg:city":"Kirchberg",
    "sg:phone":"+49 7144/3144",
    "sg:postcode":"71737",
    "sg:province":"Baden-W\u00fcrttemberg",
    "wof:name":"Reinhold Currle Wirtschaftspr\u00fcfer",
    "wof:placetype":"venue"
},
  "geometry": {"coordinates":[9.3437643051,48.9401893616],"type":"Point"}
}