{
  "type": "Feature",
  "properties": {
    "iso:country":"DE",
    "sg:address":"Frankenstr. 10",
    "sg:city":"Wolpertshausen",
    "sg:phone":"+49 7904/97110",
    "sg:postcode":"74549",
    "sg:province":"Baden-W\u00fcrttemberg",
    "wof:name":"Musik & Light",
    "wof:placetype":"venue"
},
  "geometry": {"coordinates":[9.8526830673,49.1680526733],"type":"Point"}
}