{
  "type": "Feature",
  "properties": {
    "iso:country":"DE",
    "sg:address":"Venloer Str. 252",
    "sg:city":"K\u00f6ln",
    "sg:phone":"+49 221/9525991",
    "sg:postcode":"50823",
    "sg:province":"Nordrhein-Westfalen",
    "wof:name":"Foto Strietzel E. K.",
    "wof:placetype":"venue"
},
  "geometry": {"coordinates":[6.9224529266,50.9475440979],"type":"Point"}
}