{
  "type": "Feature",
  "properties": {
    "iso:country":"DE",
    "sg:address":"Marie-Juchacz-Str. 11",
    "sg:city":"D\u00fcsseldorf",
    "sg:phone":"+49 211/614499",
    "sg:postcode":"40470",
    "sg:province":"Nordrhein-Westfalen",
    "wof:name":"G. Koestner",
    "wof:placetype":"venue"
},
  "geometry": {"coordinates":[6.808584,51.247787],"type":"Point"}
}