{
  "type": "Feature",
  "properties": {
    "iso:country":"DE",
    "sg:address":"Planckstr. 34",
    "sg:city":"Freiberg",
    "sg:phone":"+49 7141/73341",
    "sg:postcode":"71691",
    "sg:province":"Baden-W\u00fcrttemberg",
    "wof:name":"Mosolf",
    "wof:placetype":"venue"
},
  "geometry": {"coordinates":[9.177436,48.931995],"type":"Point"}
}