{
  "type": "Feature",
  "properties": {
    "iso:country":"DE",
    "sg:address":"Gartenstr. 2",
    "sg:city":"Riesa",
    "sg:phone":"+49 3525/744729",
    "sg:postcode":"01587",
    "sg:province":"Sachsen",
    "wof:name":"Klaus Sternberger",
    "wof:placetype":"venue"
},
  "geometry": {"coordinates":[13.283045,51.320927],"type":"Point"}
}