{
  "type": "Feature",
  "properties": {
    "iso:country":"DE",
    "sg:address":"Kaifeck 1",
    "sg:city":"Waidhofen",
    "sg:phone":"+49 8443/8264",
    "sg:postcode":"86579",
    "sg:province":"Bayern",
    "wof:name":"J. Tyroller",
    "wof:placetype":"venue"
},
  "geometry": {"coordinates":[11.326921,48.585037],"type":"Point"}
}