{
  "type": "Feature",
  "properties": {
    "iso:country":"DE",
    "sg:address":"An der Markung 4",
    "sg:city":"Germering",
    "sg:phone":"+49 89/894449",
    "sg:postcode":"82110",
    "sg:province":"Bayern",
    "wof:name":"Christian Schwenken Rechtsanwalt",
    "wof:placetype":"venue"
},
  "geometry": {"coordinates":[11.3663778305,48.1175689697],"type":"Point"}
}