{
  "type": "Feature",
  "properties": {
    "iso:country":"DE",
    "sg:address":"Theaterstr. 3",
    "sg:city":"W\u00fcrzburg",
    "sg:phone":"+49 931/53946",
    "sg:postcode":"97070",
    "sg:province":"Bayern",
    "wof:name":"Frankfurter Damen-m\u00e4ntel- Gesch\u00e4ft Kg",
    "wof:placetype":"venue"
},
  "geometry": {"coordinates":[9.9339761734,49.7972068787],"type":"Point"}
}