{
  "type": "Feature",
  "properties": {
    "iso:country":"DE",
    "sg:address":"Erkrather Str. 100",
    "sg:city":"D\u00fcsseldorf",
    "sg:phone":"+49 211/7334402",
    "sg:postcode":"40233",
    "sg:province":"Nordrhein-Westfalen",
    "wof:name":"Fritz Matthes",
    "wof:placetype":"venue"
},
  "geometry": {"coordinates":[6.806025,51.222065],"type":"Point"}
}