{
  "type": "Feature",
  "properties": {
    "iso:country":"DE",
    "sg:address":"K\u00e4lbersch\u00fcttstr. 2",
    "sg:city":"Ingolstadt",
    "sg:phone":"+49 841/62148",
    "sg:postcode":"85053",
    "sg:province":"Bayern",
    "wof:name":"Donau Holzfachmarkt Gmbh",
    "wof:placetype":"venue"
},
  "geometry": {"coordinates":[11.4763307571,48.7500953674],"type":"Point"}
}