{
  "type": "Feature",
  "properties": {
    "iso:country":"DE",
    "sg:address":"Hauptstr. 48",
    "sg:city":"Gaggenau",
    "sg:phone":"+49 7225/72101",
    "sg:postcode":"76571",
    "sg:province":"Baden-W\u00fcrttemberg",
    "wof:name":"Monika Werner",
    "wof:placetype":"venue"
},
  "geometry": {"coordinates":[8.3237342834,48.7980995178],"type":"Point"}
}