{
  "type": "Feature",
  "properties": {
    "iso:country":"DE",
    "sg:address":"Grottenau 18",
    "sg:city":"Bubesheim",
    "sg:phone":"+49 8221/251430",
    "sg:postcode":"89347",
    "sg:province":"Bayern",
    "wof:name":"Evelyn Beuth Ingenieur",
    "wof:placetype":"venue"
},
  "geometry": {"coordinates":[10.2517995834,48.4313240051],"type":"Point"}
}