{
  "type": "Feature",
  "properties": {
    "iso:country":"DE",
    "sg:address":"Lange Str. 54",
    "sg:city":"Stuttgart",
    "sg:phone":"+49 711/2261935",
    "sg:postcode":"70174",
    "sg:province":"Baden-W\u00fcrttemberg",
    "wof:name":"Bohl",
    "wof:placetype":"venue"
},
  "geometry": {"coordinates":[9.1698417664,48.7777862549],"type":"Point"}
}