{
  "type": "Feature",
  "properties": {
    "iso:country":"DE",
    "sg:address":"Elbchaussee 247",
    "sg:city":"Hamburg",
    "sg:phone":"+49 40/821448",
    "sg:postcode":"22605",
    "sg:province":"Hamburg",
    "wof:name":"Schmidt & Schmidt Gmbh",
    "wof:placetype":"venue"
},
  "geometry": {"coordinates":[9.8813323975,53.5464248657],"type":"Point"}
}