{
  "type": "Feature",
  "properties": {
    "iso:country":"DE",
    "sg:address":"Hermann-Heuking-Str. 12",
    "sg:city":"Lingen",
    "sg:phone":"+49 591/59912",
    "sg:postcode":"49808",
    "sg:province":"Niedersachsen",
    "wof:name":"W\u00e4chter Gmbh",
    "wof:placetype":"venue"
},
  "geometry": {"coordinates":[7.303825,52.520817],"type":"Point"}
}