{
  "type": "Feature",
  "properties": {
    "iso:country":"DE",
    "sg:address":"Hemauerstr. 6",
    "sg:city":"Regensburg",
    "sg:phone":"+49 941/561912",
    "sg:postcode":"93047",
    "sg:province":"Bayern",
    "wof:name":"Verein Der Bayerischen Metallindustrie E. V.",
    "wof:placetype":"venue"
},
  "geometry": {"coordinates":[12.1026134491,49.0131645203],"type":"Point"}
}