{
  "type": "Feature",
  "properties": {
    "iso:country":"DE",
    "sg:address":"Museumsgasse 11",
    "sg:city":"Donauw\u00f6rth",
    "sg:phone":"+49 906/789148",
    "sg:postcode":"86609",
    "sg:province":"Bayern",
    "wof:name":"Lovriner Stube Im Ried",
    "wof:placetype":"venue"
},
  "geometry": {"coordinates":[10.778815,48.717155],"type":"Point"}
}