{
  "type": "Feature",
  "properties": {
    "iso:country":"DE",
    "sg:address":"J\u00f6lleweg 21",
    "sg:city":"Bielefeld",
    "sg:phone":"+49 521/76897",
    "sg:postcode":"33729",
    "sg:province":"Nordrhein-Westfalen",
    "wof:name":"Wilfried Linnenbr\u00fcgger",
    "wof:placetype":"venue"
},
  "geometry": {"coordinates":[8.572511673,52.0714225769],"type":"Point"}
}