{
  "type": "Feature",
  "properties": {
    "iso:country":"DE",
    "sg:address":"Seestr. 5",
    "sg:city":"Ditzingen",
    "sg:phone":"+49 7156/8278",
    "sg:postcode":"71254",
    "sg:province":"Baden-W\u00fcrttemberg",
    "wof:name":"Andreas Leutz",
    "wof:placetype":"venue"
},
  "geometry": {"coordinates":[9.0385484695,48.8367004395],"type":"Point"}
}