{
  "type": "Feature",
  "properties": {
    "iso:country":"DE",
    "sg:address":"Rehefelder Str. 2",
    "sg:city":"Dresden",
    "sg:phone":"+49 351/8581715",
    "sg:postcode":"01127",
    "sg:province":"Sachsen",
    "wof:name":"Wolfgang Bail",
    "wof:placetype":"venue"
},
  "geometry": {"coordinates":[13.7194824219,51.0766105652],"type":"Point"}
}