{
  "type": "Feature",
  "properties": {
    "iso:country":"DE",
    "sg:address":"Peterstr. 13",
    "sg:city":"Westerstede",
    "sg:phone":"+49 4488/71505",
    "sg:postcode":"26655",
    "sg:province":"Niedersachsen",
    "wof:name":"Spielothek",
    "wof:placetype":"venue"
},
  "geometry": {"coordinates":[7.927380085,53.2558288574],"type":"Point"}
}