{
  "type": "Feature",
  "properties": {
    "iso:country":"DE",
    "sg:address":"Lindenstr. 2",
    "sg:city":"Bous",
    "sg:phone":"+49 6834/2241",
    "sg:postcode":"66359",
    "sg:province":"Saarland",
    "wof:name":"Eduard Fery",
    "wof:placetype":"venue"
},
  "geometry": {"coordinates":[6.808528,49.279686],"type":"Point"}
}