{
  "type": "Feature",
  "properties": {
    "iso:country":"DE",
    "sg:address":"89604",
    "sg:city":"Allmendingen",
    "sg:phone":"+49 7391/6777",
    "sg:postcode":"89604",
    "sg:province":"Baden-W\u00fcrttemberg",
    "wof:name":"Sportheim",
    "wof:placetype":"venue"
},
  "geometry": {"coordinates":[9.7181901932,48.3292732239],"type":"Point"}
}