{
  "type": "Feature",
  "properties": {
    "iso:country":"DE",
    "sg:address":"St.-Wendel-Str. 15",
    "sg:city":"N\u00fcrnberg",
    "sg:phone":"+49 911/482273",
    "sg:postcode":"90469",
    "sg:province":"Bayern",
    "wof:name":"Georg Richert",
    "wof:placetype":"venue"
},
  "geometry": {"coordinates":[11.084767,49.40295],"type":"Point"}
}