{
  "type": "Feature",
  "properties": {
    "iso:country":"DE",
    "sg:address":"Frankfurter Str. 13",
    "sg:city":"Kronberg",
    "sg:phone":"+49 6173/940901",
    "sg:postcode":"61476",
    "sg:province":"Hessen",
    "wof:name":"Desens & Kachane & Co. Kommunikation Und",
    "wof:placetype":"venue"
},
  "geometry": {"coordinates":[8.5127754211,50.1792907715],"type":"Point"}
}