{
  "type": "Feature",
  "properties": {
    "iso:country":"DE",
    "sg:address":"Sander Weg 30",
    "sg:city":"Lindau",
    "sg:postcode":"24214",
    "sg:province":"Schleswig-Holstein",
    "wof:name":"Bernhard Beckmann",
    "wof:placetype":"venue"
},
  "geometry": {"coordinates":[9.945407,54.391579],"type":"Point"}
}