{
  "type": "Feature",
  "properties": {
    "iso:country":"DE",
    "sg:address":"Behringer Str. 100",
    "sg:city":"Schneverdingen",
    "sg:phone":"+49 5198/980262",
    "sg:postcode":"29640",
    "sg:province":"Niedersachsen",
    "wof:name":"Pflegezentrum Wintermoor",
    "wof:placetype":"venue"
},
  "geometry": {"coordinates":[9.838566,53.184715],"type":"Point"}
}