{
  "type": "Feature",
  "properties": {
    "iso:country":"DE",
    "sg:address":"M\u00fchlenstr. 26",
    "sg:city":"Diemelstadt",
    "sg:postcode":"34474",
    "sg:province":"Hessen",
    "wof:name":"H\u00f6hle Vereinsbedarf",
    "wof:placetype":"venue"
},
  "geometry": {"coordinates":[8.959733,51.494087],"type":"Point"}
}