{
  "type": "Feature",
  "properties": {
    "iso:country":"DE",
    "sg:address":"Handstr. 318",
    "sg:city":"Bergisch Gladbach",
    "sg:phone":"+49 2202/58329",
    "sg:postcode":"51469",
    "sg:province":"Nordrhein-Westfalen",
    "wof:name":"Frank Esser",
    "wof:placetype":"venue"
},
  "geometry": {"coordinates":[7.109075,50.993763],"type":"Point"}
}