{
  "type": "Feature",
  "properties": {
    "iso:country":"DE",
    "sg:address":"Am Schwaiblbach 3",
    "sg:city":"M\u00fcnsing",
    "sg:phone":"+49 8177/546",
    "sg:postcode":"82541",
    "sg:province":"Bayern",
    "wof:name":"Campingplatz Hirth",
    "wof:placetype":"venue"
},
  "geometry": {"coordinates":[11.338823,47.854542],"type":"Point"}
}