{
  "type": "Feature",
  "properties": {
    "iso:country":"DE",
    "sg:address":"Guterstr. 4",
    "sg:city":"Senden",
    "sg:phone":"+49 7307/5206",
    "sg:postcode":"89250",
    "sg:province":"Bayern",
    "wof:name":"Hans Knott",
    "wof:placetype":"venue"
},
  "geometry": {"coordinates":[10.0464668274,48.3209877014],"type":"Point"}
}