{
  "type": "Feature",
  "properties": {
    "iso:country":"DE",
    "sg:address":"Ringstr. 4",
    "sg:city":"Ostrau",
    "sg:phone":"+49 34324/5070",
    "sg:postcode":"04749",
    "sg:province":"Sachsen",
    "wof:name":"Gaza - Holzhandels Gmbh",
    "wof:placetype":"venue"
},
  "geometry": {"coordinates":[13.148856,51.207321],"type":"Point"}
}