{
  "type": "Feature",
  "properties": {
    "iso:country":"DE",
    "sg:address":"Bahnhofstr 226",
    "sg:city":"Karben",
    "sg:phone":"+49 4960/392220",
    "sg:postcode":"61184",
    "sg:province":"Hessen",
    "wof:name":"Bvb Volksbank Eg",
    "wof:placetype":"venue"
},
  "geometry": {"coordinates":[8.752105,50.233219],"type":"Point"}
}