{
  "type": "Feature",
  "properties": {
    "iso:country":"DE",
    "sg:address":"S\u00fcrther Hauptstra\u00dfe 77",
    "sg:city":"K\u00f6ln",
    "sg:phone":"+49 2236/92930",
    "sg:postcode":"50999",
    "sg:province":"Nordrhein-Westfalen",
    "wof:name":"Volando Agentur F\u00fcr Integriertes Online-marketing",
    "wof:placetype":"venue"
},
  "geometry": {"coordinates":[7.008486,50.862743],"type":"Point"}
}