{
  "type": "Feature",
  "properties": {
    "iso:country":"DE",
    "sg:address":"Richard-Wagner-Str. 74",
    "sg:city":"Kriftel",
    "sg:phone":"+49 6192/41655",
    "sg:postcode":"65830",
    "sg:province":"Hessen",
    "wof:name":"Klaus Kalkowski Gmbh",
    "wof:placetype":"venue"
},
  "geometry": {"coordinates":[8.4709806442,50.0889778137],"type":"Point"}
}