{
  "type": "Feature",
  "properties": {
    "iso:country":"DE",
    "sg:address":"Salvador-Allende-Platz 23",
    "sg:city":"Jena",
    "sg:phone":"+49 3641/334453",
    "sg:postcode":"07747",
    "sg:province":"Th\u00fcringen",
    "wof:name":"K\u00fcnstleragentur Forner",
    "wof:placetype":"venue"
},
  "geometry": {"coordinates":[11.6191549301,50.8824119568],"type":"Point"}
}