{
  "type": "Feature",
  "properties": {
    "iso:country":"DE",
    "sg:address":"Ostring 22",
    "sg:city":"Kahl",
    "sg:phone":"+49 6188/1539",
    "sg:postcode":"63796",
    "sg:province":"Bayern",
    "wof:name":"Benedikt Sch\u00fctter",
    "wof:placetype":"venue"
},
  "geometry": {"coordinates":[9.0095586777,50.063293457],"type":"Point"}
}