{
  "type": "Feature",
  "properties": {
    "iso:country":"DE",
    "sg:address":"Holzfeldweg 10",
    "sg:city":"Giesen",
    "sg:phone":"+49 5066/4276",
    "sg:postcode":"31180",
    "sg:province":"Niedersachsen",
    "wof:name":"Hans Anders",
    "wof:placetype":"venue"
},
  "geometry": {"coordinates":[9.8824424744,52.2207336426],"type":"Point"}
}