{
  "type": "Feature",
  "properties": {
    "iso:country":"DE",
    "sg:address":"Kyritzer Str. 45",
    "sg:city":"St\u00fcdenitz",
    "sg:phone":"+49 33972/40351",
    "sg:postcode":"16845",
    "sg:province":"Brandenburg",
    "wof:name":"Ferdinand G\u00fcnther",
    "wof:placetype":"venue"
},
  "geometry": {"coordinates":[12.2784795761,52.8895072937],"type":"Point"}
}