{
  "type": "Feature",
  "properties": {
    "iso:country":"DE",
    "sg:address":"R\u00f6testr. 18",
    "sg:city":"Bietigheim-Bissingen",
    "sg:phone":"+49 4971/4251044",
    "sg:postcode":"74321",
    "sg:province":"Baden-W\u00fcrttemberg",
    "wof:name":"Pero-ag",
    "wof:placetype":"venue"
},
  "geometry": {"coordinates":[9.1512317657,48.951374054],"type":"Point"}
}