{
  "type": "Feature",
  "properties": {
    "iso:country":"DE",
    "sg:address":"Katernberger Str. 20",
    "sg:city":"Essen",
    "sg:phone":"+49 201/307232",
    "sg:postcode":"45327",
    "sg:province":"Nordrhein-Westfalen",
    "wof:name":"Annas Brautmoden",
    "wof:placetype":"venue"
},
  "geometry": {"coordinates":[7.048477,51.496662],"type":"Point"}
}