{
  "type": "Feature",
  "properties": {
    "iso:country":"DE",
    "sg:address":"\u00c4btissin-Jutta-Str. 1",
    "sg:city":"Wunstorf",
    "sg:phone":"+49 5031/16977",
    "sg:postcode":"31515",
    "sg:province":"Niedersachsen",
    "wof:name":"K. Engel Immobilienmakler",
    "wof:placetype":"venue"
},
  "geometry": {"coordinates":[9.4469079971,52.4153633118],"type":"Point"}
}