{
  "type": "Feature",
  "properties": {
    "iso:country":"DE",
    "sg:address":"Siegesstr. 24",
    "sg:city":"M\u00fcnchen",
    "sg:postcode":"80802",
    "sg:province":"Bayern",
    "wof:name":"Terdin Gmbh",
    "wof:placetype":"venue"
},
  "geometry": {"coordinates":[11.588507,48.160732],"type":"Point"}
}