{
  "type": "Feature",
  "properties": {
    "iso:country":"DE",
    "sg:address":"Lindenteichstr 8",
    "sg:city":"Rosdorf",
    "sg:phone":"+49 5545/6556",
    "sg:postcode":"37124",
    "sg:province":"Niedersachsen",
    "wof:name":"Dr. Ulonska",
    "wof:placetype":"venue"
},
  "geometry": {"coordinates":[9.8143863678,51.4208374023],"type":"Point"}
}