{
  "type": "Feature",
  "properties": {
    "iso:country":"DE",
    "sg:address":"Dorfstr 4",
    "sg:city":"Kakenstorf",
    "sg:phone":"+49 4186/889233",
    "sg:postcode":"21255",
    "sg:province":"Niedersachsen",
    "wof:name":"Jacta Gmbh & Co Kg",
    "wof:placetype":"venue"
},
  "geometry": {"coordinates":[9.746788,53.32093],"type":"Point"}
}