{
  "type": "Feature",
  "properties": {
    "iso:country":"DE",
    "sg:address":"Heimst\u00e4ttenstr. 30",
    "sg:city":"M\u00fcnchen",
    "sg:phone":"+49 89/3233281",
    "sg:postcode":"80805",
    "sg:province":"Bayern",
    "wof:name":"Bernhard Fischer",
    "wof:placetype":"venue"
},
  "geometry": {"coordinates":[11.608343,48.180634],"type":"Point"}
}