{
  "type": "Feature",
  "properties": {
    "iso:country":"DE",
    "sg:address":"Stra\u00dfkirchen",
    "sg:city":"Salzweg",
    "sg:phone":"+49 8505/1228",
    "sg:postcode":"94121",
    "sg:province":"Bayern",
    "wof:name":"Hendlstation Girmindl Manfred Bruckm\u00fcller",
    "wof:placetype":"venue"
},
  "geometry": {"coordinates":[13.4828119278,48.6165275574],"type":"Point"}
}