{
  "type": "Feature",
  "properties": {
    "iso:country":"DE",
    "sg:address":"Markt 8",
    "sg:city":"Bonn",
    "sg:phone":"+49 228/72670",
    "sg:postcode":"53111",
    "sg:province":"Nordrhein-Westfalen",
    "wof:name":"Sternhotel Haupt Kg",
    "wof:placetype":"venue"
},
  "geometry": {"coordinates":[7.1026911736,50.7354545593],"type":"Point"}
}