{
  "type": "Feature",
  "properties": {
    "iso:country":"DE",
    "sg:address":"Radolfzeller Str. 5a",
    "sg:city":"M\u00fcnchen",
    "sg:phone":"+49 89/8299700",
    "sg:postcode":"81243",
    "sg:province":"Bayern",
    "wof:name":"Fitnesspark M\u00fcnchen Gmbh",
    "wof:placetype":"venue"
},
  "geometry": {"coordinates":[11.4352798462,48.1502494812],"type":"Point"}
}