{
  "type": "Feature",
  "properties": {
    "iso:country":"DE",
    "sg:address":"Im Auchtert 11",
    "sg:city":"Kirchheim",
    "sg:phone":"+49 7021/53460",
    "sg:postcode":"73230",
    "sg:province":"Baden-W\u00fcrttemberg",
    "wof:name":"Heinz H\u00f6flinger Architekt",
    "wof:placetype":"venue"
},
  "geometry": {"coordinates":[9.479334,48.613945],"type":"Point"}
}