{
  "type": "Feature",
  "properties": {
    "iso:country":"DE",
    "sg:address":"M\u00fchlenkamp 38",
    "sg:city":"Hamburg",
    "sg:phone":"+49 40/2702783",
    "sg:postcode":"22303",
    "sg:province":"Hamburg",
    "wof:name":"Rossmann Drogeriemarkt",
    "wof:placetype":"venue"
},
  "geometry": {"coordinates":[10.011172,53.582275],"type":"Point"}
}