{
  "type": "Feature",
  "properties": {
    "iso:country":"DE",
    "sg:address":"Kirchstr. 15",
    "sg:city":"Oestrich-Winkel",
    "sg:phone":"+49 6723/3483",
    "sg:postcode":"65375",
    "sg:province":"Hessen",
    "wof:name":"Adam Basting Weinanbau",
    "wof:placetype":"venue"
},
  "geometry": {"coordinates":[8.0062017441,49.9998512268],"type":"Point"}
}