{
  "type": "Feature",
  "properties": {
    "iso:country":"DE",
    "sg:address":"Albringhausen 20",
    "sg:city":"Bassum",
    "sg:phone":"+49 4241/2185",
    "sg:postcode":"27211",
    "sg:province":"Niedersachsen",
    "wof:name":"H. Heitb\u00f6hn",
    "wof:placetype":"venue"
},
  "geometry": {"coordinates":[8.767214,52.831821],"type":"Point"}
}