{
  "type": "Feature",
  "properties": {
    "iso:country":"DE",
    "sg:address":"Luruper Hauptstr. 132",
    "sg:city":"Hamburg",
    "sg:phone":"+49 40/8316091",
    "sg:postcode":"22547",
    "sg:province":"Hamburg",
    "wof:name":"Redaktion Schenefelder Bote Luruper Nachrichten Verlag",
    "wof:placetype":"venue"
},
  "geometry": {"coordinates":[9.8739433289,53.590763092],"type":"Point"}
}