{
  "type": "Feature",
  "properties": {
    "iso:country":"DE",
    "sg:address":"Kirchgasse 6",
    "sg:city":"Wiesbaden",
    "sg:phone":"+49 611/30815",
    "sg:postcode":"65185",
    "sg:province":"Hessen",
    "wof:name":"T. Moschick Immobilienmakler",
    "wof:placetype":"venue"
},
  "geometry": {"coordinates":[8.2380523682,50.0782051086],"type":"Point"}
}