{
  "type": "Feature",
  "properties": {
    "iso:country":"DE",
    "sg:address":"Rehrhofer Weg 56",
    "sg:city":"Munster",
    "sg:postcode":"29633",
    "sg:province":"Niedersachsen",
    "wof:name":"Aldi Gmbh & Co. Kg",
    "wof:placetype":"venue"
},
  "geometry": {"coordinates":[10.1043176651,52.9899711609],"type":"Point"}
}