{
  "type": "Feature",
  "properties": {
    "iso:country":"DE",
    "sg:address":"Rathausstr. 40",
    "sg:city":"Stolberg",
    "sg:phone":"+49 2402/87637",
    "sg:postcode":"52222",
    "sg:province":"Nordrhein-Westfalen",
    "wof:name":"Haus Rosenthal",
    "wof:placetype":"venue"
},
  "geometry": {"coordinates":[6.2277078629,50.7716217041],"type":"Point"}
}