{
  "type": "Feature",
  "properties": {
    "iso:country":"DE",
    "sg:address":"Mittlere Str. 5",
    "sg:city":"Brilon",
    "sg:phone":"+49 2961/8435",
    "sg:postcode":"59929",
    "sg:province":"Nordrhein-Westfalen",
    "wof:name":"Franz Rickert",
    "wof:placetype":"venue"
},
  "geometry": {"coordinates":[8.5295667648,51.4246025085],"type":"Point"}
}