{
  "type": "Feature",
  "properties": {
    "iso:country":"DE",
    "sg:address":"Sch\u00e4risweg 44",
    "sg:city":"Waiblingen",
    "sg:phone":"+49 7151/8658",
    "sg:postcode":"71336",
    "sg:province":"Baden-W\u00fcrttemberg",
    "wof:name":"Martin Mayer",
    "wof:placetype":"venue"
},
  "geometry": {"coordinates":[9.3304862976,48.8544654846],"type":"Point"}
}