{
  "type": "Feature",
  "properties": {
    "iso:country":"DE",
    "sg:address":"Margarethenstr. 24",
    "sg:city":"Kronberg",
    "sg:phone":"+49 6173/79747",
    "sg:postcode":"61476",
    "sg:province":"Hessen",
    "wof:name":"Highcom Consulting.com Gmbh",
    "wof:placetype":"venue"
},
  "geometry": {"coordinates":[8.5166273117,50.1853675842],"type":"Point"}
}