{
  "type": "Feature",
  "properties": {
    "iso:country":"DE",
    "sg:address":"Pillmannstr. 12",
    "sg:city":"Braunschweig",
    "sg:phone":"+49 531/2319930",
    "sg:postcode":"38112",
    "sg:province":"Niedersachsen",
    "wof:name":"Induchem Gmbh",
    "wof:placetype":"venue"
},
  "geometry": {"coordinates":[10.4712257385,52.3162651062],"type":"Point"}
}