{
  "type": "Feature",
  "properties": {
    "iso:country":"DE",
    "sg:address":"Rebhuhnweg 25",
    "sg:city":"Zirndorf",
    "sg:phone":"+49 911/694473",
    "sg:postcode":"90513",
    "sg:province":"Bayern",
    "wof:name":"Hans-j\u00fcrgen Leopold Rechtsanwalt",
    "wof:placetype":"venue"
},
  "geometry": {"coordinates":[10.9140405655,49.4387130737],"type":"Point"}
}