{
  "type": "Feature",
  "properties": {
    "iso:country":"DE",
    "sg:address":"Georg-Westermann-Allee 66",
    "sg:city":"Braunschweig",
    "sg:phone":"+49 531/7080",
    "sg:postcode":"38104",
    "sg:province":"Niedersachsen",
    "wof:name":"Archiv Des Georg Westermann Verlages",
    "wof:placetype":"venue"
},
  "geometry": {"coordinates":[10.551636,52.260441],"type":"Point"}
}