{
  "type": "Feature",
  "properties": {
    "iso:country":"DE",
    "sg:address":"Wei\u00dfdornweg 3",
    "sg:city":"Heimsheim",
    "sg:phone":"+49 7033/34891",
    "sg:postcode":"71296",
    "sg:province":"Baden-W\u00fcrttemberg",
    "wof:name":"J\u00fcrgen Wurst Dentalprodukte Gmbh",
    "wof:placetype":"venue"
},
  "geometry": {"coordinates":[8.8652124405,48.8138465881],"type":"Point"}
}