{
  "type": "Feature",
  "properties": {
    "iso:country":"DE",
    "sg:address":"Wohlfahrtstr. 208",
    "sg:city":"Bochum",
    "sg:phone":"+49 234/9789888",
    "sg:postcode":"44799",
    "sg:province":"Nordrhein-Westfalen",
    "wof:name":"Haase Computer- Und Datensysteme Gmbh",
    "wof:placetype":"venue"
},
  "geometry": {"coordinates":[7.2252469063,51.4466896057],"type":"Point"}
}