{
  "type": "Feature",
  "properties": {
    "iso:country":"DE",
    "sg:address":"Ziegeleistr. 16-18",
    "sg:city":"Weinstadt",
    "sg:phone":"+49 7151/997966",
    "sg:postcode":"71384",
    "sg:province":"Baden-W\u00fcrttemberg",
    "wof:name":"Motec Modellsport Technik Vertriebs Gmbh",
    "wof:placetype":"venue"
},
  "geometry": {"coordinates":[9.375217,48.810581],"type":"Point"}
}