{
  "type": "Feature",
  "properties": {
    "iso:country":"DE",
    "sg:address":"Jahnstr. 6",
    "sg:city":"Rodewisch",
    "sg:phone":"+49 3744/33733",
    "sg:postcode":"08228",
    "sg:province":"Sachsen",
    "wof:name":"Harald Singer",
    "wof:placetype":"venue"
},
  "geometry": {"coordinates":[12.413045,50.529354],"type":"Point"}
}