{
  "type": "Feature",
  "properties": {
    "iso:country":"DE",
    "sg:address":"Meppener Str. 16",
    "sg:city":"Lingen",
    "sg:phone":"+49 591/65921",
    "sg:postcode":"49808",
    "sg:province":"Niedersachsen",
    "wof:name":"Mini-grill",
    "wof:placetype":"venue"
},
  "geometry": {"coordinates":[7.3130021095,52.5265846252],"type":"Point"}
}