{
  "type": "Feature",
  "properties": {
    "iso:country":"DE",
    "sg:address":"Claudiusweg 18",
    "sg:city":"Ro\u00dfdorf",
    "sg:phone":"+49 6154/9931",
    "sg:postcode":"64380",
    "sg:province":"Hessen",
    "wof:name":"Gabriele Anders Krankengymnastin",
    "wof:placetype":"venue"
},
  "geometry": {"coordinates":[8.749266,49.854717],"type":"Point"}
}