{
  "type": "Feature",
  "properties": {
    "iso:country":"DE",
    "sg:address":"Trelder Str. 46",
    "sg:city":"Drestedt",
    "sg:phone":"+49 4186/889150",
    "sg:postcode":"21279",
    "sg:province":"Niedersachsen",
    "wof:name":"Tolkemitt Gmbh",
    "wof:placetype":"venue"
},
  "geometry": {"coordinates":[9.77499,53.326706],"type":"Point"}
}