{
  "type": "Feature",
  "properties": {
    "iso:country":"DE",
    "sg:address":"M\u00fcckengasse 35",
    "sg:city":"Breitungen",
    "sg:phone":"+49 36848/8920",
    "sg:postcode":"98597",
    "sg:province":"Th\u00fcringen",
    "wof:name":"Perfect-werkzeuge Gmbh",
    "wof:placetype":"venue"
},
  "geometry": {"coordinates":[10.330311,50.76841],"type":"Point"}
}