{
  "type": "Feature",
  "properties": {
    "iso:country":"DE",
    "sg:address":"Schlachthofstr. 13",
    "sg:city":"Gr\u00fcnstadt",
    "sg:phone":"+49 6359/1411",
    "sg:postcode":"67269",
    "sg:province":"Rheinland-Pfalz",
    "wof:name":"Alfred Bauer",
    "wof:placetype":"venue"
},
  "geometry": {"coordinates":[8.171632,49.568638],"type":"Point"}
}