{
  "type": "Feature",
  "properties": {
    "iso:country":"DE",
    "sg:address":"Ensbachstr. 1",
    "sg:city":"Hilders",
    "sg:phone":"+49 6681/223",
    "sg:postcode":"36115",
    "sg:province":"Hessen",
    "wof:name":"Rh\u00f6n Leinen Industrie Alfred N\u00fcdling Vorm.",
    "wof:placetype":"venue"
},
  "geometry": {"coordinates":[10.0114936829,50.5543861389],"type":"Point"}
}