{
  "type": "Feature",
  "properties": {
    "iso:country":"DE",
    "sg:address":"Holsteinischer Kamp 95 a",
    "sg:city":"Hamburg",
    "sg:phone":"+49 40/2980370",
    "sg:postcode":"22081",
    "sg:province":"Hamburg",
    "wof:name":"Bishop Songs Musikverlag Breitung-wicke Ohg",
    "wof:placetype":"venue"
},
  "geometry": {"coordinates":[10.0474739075,53.5757064819],"type":"Point"}
}