{
  "type": "Feature",
  "properties": {
    "iso:country":"DE",
    "sg:address":"Tammegaster Str. 6",
    "sg:city":"Moormerland",
    "sg:phone":"+49 4924/358",
    "sg:postcode":"26802",
    "sg:province":"Niedersachsen",
    "wof:name":"Peter Groenewold",
    "wof:placetype":"venue"
},
  "geometry": {"coordinates":[7.357866,53.321091],"type":"Point"}
}