{
  "type": "Feature",
  "properties": {
    "iso:country":"DE",
    "sg:address":"Mitterfeldweg 21",
    "sg:city":"Dachau",
    "sg:phone":"+49 8131/735900",
    "sg:postcode":"85221",
    "sg:province":"Bayern",
    "wof:name":"Wolfgang Derlig Rechtsanwalt",
    "wof:placetype":"venue"
},
  "geometry": {"coordinates":[11.423368454,48.2607841492],"type":"Point"}
}