{
  "type": "Feature",
  "properties": {
    "iso:country":"DE",
    "sg:address":"Schwalbenstr. 6",
    "sg:city":"S\u00fcnching",
    "sg:phone":"+49 9480/813",
    "sg:postcode":"93104",
    "sg:province":"Bayern",
    "wof:name":"Wilhelm Raith Architekt",
    "wof:placetype":"venue"
},
  "geometry": {"coordinates":[12.360303,48.884731],"type":"Point"}
}