{
  "type": "Feature",
  "properties": {
    "iso:country":"DE",
    "sg:address":"Rendsburger Landstr. 71",
    "sg:city":"Kiel",
    "sg:phone":"+49 431/6409635",
    "sg:postcode":"24113",
    "sg:province":"Schleswig-Holstein",
    "wof:name":"Becker & Hanhart",
    "wof:placetype":"venue"
},
  "geometry": {"coordinates":[10.108559,54.305538],"type":"Point"}
}