{
  "type": "Feature",
  "properties": {
    "iso:country":"DE",
    "sg:address":"Hofm\u00fchlstr. 10",
    "sg:city":"Eichst\u00e4tt",
    "sg:phone":"+49 8421/98080",
    "sg:postcode":"85072",
    "sg:province":"Bayern",
    "wof:name":"Privatbrauerei Hofm\u00fchl Gmbh",
    "wof:placetype":"venue"
},
  "geometry": {"coordinates":[11.167276,48.893997],"type":"Point"}
}