{
  "type": "Feature",
  "properties": {
    "iso:country":"DE",
    "sg:address":"Papenhuder Str. 26",
    "sg:city":"Hamburg",
    "sg:phone":"+49 40/2297646",
    "sg:postcode":"22087",
    "sg:province":"Hamburg",
    "wof:name":"Souterrain",
    "wof:placetype":"venue"
},
  "geometry": {"coordinates":[10.019411087,53.5667457581],"type":"Point"}
}