{
  "type": "Feature",
  "properties": {
    "iso:country":"DE",
    "sg:address":"Fabriciusstr. 56",
    "sg:city":"Hamburg",
    "sg:phone":"+49 40/617119",
    "sg:postcode":"22177",
    "sg:province":"Hamburg",
    "wof:name":"Ev. Pfarramt Ii Thomaskirche",
    "wof:placetype":"venue"
},
  "geometry": {"coordinates":[10.0612001419,53.5980644226],"type":"Point"}
}