{
  "type": "Feature",
  "properties": {
    "iso:country":"DE",
    "sg:address":"Goethestr. 38",
    "sg:city":"Burgst\u00e4dt",
    "sg:postcode":"09217",
    "sg:province":"Sachsen",
    "wof:name":"Goldstar Tricot Gmbh",
    "wof:placetype":"venue"
},
  "geometry": {"coordinates":[12.8088378906,50.9109115601],"type":"Point"}
}