{
  "type": "Feature",
  "properties": {
    "iso:country":"DE",
    "sg:address":"Breitkopfstr. 22",
    "sg:city":"Leipzig",
    "sg:postcode":"04317",
    "sg:province":"Sachsen",
    "wof:name":"S\u00f6rgel Sport Und Freizeit Gmbh",
    "wof:placetype":"venue"
},
  "geometry": {"coordinates":[12.399553299,51.3379478455],"type":"Point"}
}