{
  "type": "Feature",
  "properties": {
    "iso:country":"DE",
    "sg:address":"Karl-Arnold-Str. 80",
    "sg:city":"Heinsberg",
    "sg:phone":"+49 2452/5555",
    "sg:postcode":"52525",
    "sg:province":"Nordrhein-Westfalen",
    "wof:name":"M. Kohnen",
    "wof:placetype":"venue"
},
  "geometry": {"coordinates":[6.121521,51.059566],"type":"Point"}
}