{
  "type": "Feature",
  "properties": {
    "iso:country":"DE",
    "sg:address":"Schmittgasse 71a",
    "sg:city":"K\u00f6ln",
    "sg:phone":"+49 2203/85104",
    "sg:postcode":"51143",
    "sg:province":"Nordrhein-Westfalen",
    "wof:name":"W. Kaufmann",
    "wof:placetype":"venue"
},
  "geometry": {"coordinates":[7.0450601578,50.8664131165],"type":"Point"}
}