{
  "type": "Feature",
  "properties": {
    "iso:country":"DE",
    "sg:address":"Am Strebkamp 22",
    "sg:city":"Bielefeld",
    "sg:phone":"+49 4952/1927960",
    "sg:postcode":"33607",
    "sg:province":"Nordrhein-Westfalen",
    "wof:name":"Reb Reinhard Elbracht Gmbh",
    "wof:placetype":"venue"
},
  "geometry": {"coordinates":[8.5797786713,52.0179252625],"type":"Point"}
}