{
  "type": "Feature",
  "properties": {
    "iso:country":"DE",
    "sg:address":"Trierer Str. 81",
    "sg:city":"Hermeskeil",
    "sg:postcode":"54411",
    "sg:province":"Rheinland-Pfalz",
    "wof:name":"Peko Gmbh",
    "wof:placetype":"venue"
},
  "geometry": {"coordinates":[6.938019,49.656742],"type":"Point"}
}