{
  "type": "Feature",
  "properties": {
    "iso:country":"DE",
    "sg:address":"Nordendstr. 20",
    "sg:city":"Frankfurt",
    "sg:phone":"+49 69/590097",
    "sg:postcode":"60318",
    "sg:province":"Hessen",
    "wof:name":"Alibaba-verlags Gmbh",
    "wof:placetype":"venue"
},
  "geometry": {"coordinates":[8.6898317337,50.1290931702],"type":"Point"}
}