{
  "type": "Feature",
  "properties": {
    "iso:country":"DE",
    "sg:address":"Markt 20",
    "sg:city":"Aschersleben",
    "sg:phone":"+49 3473/810076",
    "sg:postcode":"06449",
    "sg:province":"Sachsen-Anhalt",
    "wof:name":"Filmpalast",
    "wof:placetype":"venue"
},
  "geometry": {"coordinates":[11.456549,51.756191],"type":"Point"}
}