{
  "type": "Feature",
  "properties": {
    "iso:country":"DE",
    "sg:address":"Stuttgarter Str. 116",
    "sg:city":"Stuttgart",
    "sg:phone":"+49 711/816950",
    "sg:postcode":"70469",
    "sg:province":"Baden-W\u00fcrttemberg",
    "wof:name":"I. Micheel Immobilienmakler",
    "wof:placetype":"venue"
},
  "geometry": {"coordinates":[9.1569824219,48.8087272644],"type":"Point"}
}