{
  "type": "Feature",
  "properties": {
    "iso:country":"DE",
    "sg:address":"Am Plan 4",
    "sg:city":"Jena",
    "sg:phone":"+49 3641/424198",
    "sg:postcode":"07743",
    "sg:province":"Th\u00fcringen",
    "wof:name":"K.-h. J\u00e4ger",
    "wof:placetype":"venue"
},
  "geometry": {"coordinates":[11.613982,50.951611],"type":"Point"}
}