{
  "type": "Feature",
  "properties": {
    "iso:country":"DE",
    "sg:address":"Gerberweg 7",
    "sg:city":"Idstein",
    "sg:phone":"+49 6126/51989",
    "sg:postcode":"65510",
    "sg:province":"Hessen",
    "wof:name":"Sev Gmbh",
    "wof:placetype":"venue"
},
  "geometry": {"coordinates":[8.2648010254,50.2280006409],"type":"Point"}
}