{
  "type": "Feature",
  "properties": {
    "iso:country":"DE",
    "sg:address":"K\u00f6thener Str. 15",
    "sg:city":"Gr\u00f6bzig",
    "sg:phone":"+49 34976/22536",
    "sg:postcode":"06388",
    "sg:province":"Sachsen-Anhalt",
    "wof:name":"Stadt Gr\u00f6bzig",
    "wof:placetype":"venue"
},
  "geometry": {"coordinates":[11.8752069473,51.682975769],"type":"Point"}
}