{
  "type": "Feature",
  "properties": {
    "iso:country":"DE",
    "sg:address":"Altendorfer Str. 26",
    "sg:city":"Einbeck",
    "sg:phone":"+49 5561/3332",
    "sg:postcode":"37574",
    "sg:province":"Niedersachsen",
    "wof:name":"Alexander Christ",
    "wof:placetype":"venue"
},
  "geometry": {"coordinates":[9.8795995712,51.813747406],"type":"Point"}
}