{
  "type": "Feature",
  "properties": {
    "iso:country":"DE",
    "sg:address":"Philippstr. 61 a",
    "sg:city":"K\u00f6ln",
    "sg:phone":"+49 221/524397",
    "sg:postcode":"50823",
    "sg:province":"Nordrhein-Westfalen",
    "wof:name":"\u00d6. G\u00f6z",
    "wof:placetype":"venue"
},
  "geometry": {"coordinates":[6.92069,50.950546],"type":"Point"}
}