{
  "type": "Feature",
  "properties": {
    "iso:country":"DE",
    "sg:address":"Sendplatz 28",
    "sg:city":"Metelen",
    "sg:phone":"+49 2556/7746",
    "sg:postcode":"48629",
    "sg:province":"Nordrhein-Westfalen",
    "wof:name":"Hotel Peter Brink",
    "wof:placetype":"venue"
},
  "geometry": {"coordinates":[7.2155160904,52.143825531],"type":"Point"}
}