{
  "type": "Feature",
  "properties": {
    "iso:country":"DE",
    "sg:address":"Feuerbacher-Tal-Str. 14",
    "sg:city":"Stuttgart",
    "sg:phone":"+49 711/815128",
    "sg:postcode":"70469",
    "sg:province":"Baden-W\u00fcrttemberg",
    "wof:name":"Fundtruhe",
    "wof:placetype":"venue"
},
  "geometry": {"coordinates":[9.156414,48.807518],"type":"Point"}
}