{
  "type": "Feature",
  "properties": {
    "iso:country":"DE",
    "sg:address":"Wiesenweg 14 b",
    "sg:city":"Gutgl\u00fcck",
    "sg:phone":"+49 3361/57385",
    "sg:postcode":"18356",
    "sg:province":"Mecklenburg-Vorpommern",
    "wof:name":"Brigitte Schulze Hebamme",
    "wof:placetype":"venue"
},
  "geometry": {"coordinates":[12.655833,54.368847],"type":"Point"}
}