{
  "type": "Feature",
  "properties": {
    "iso:country":"DE",
    "sg:address":"Hofstr. 5",
    "sg:city":"K\u00fclsheim",
    "sg:phone":"+49 9345/1241",
    "sg:postcode":"97900",
    "sg:province":"Baden-W\u00fcrttemberg",
    "wof:name":"Gerd Sch\u00fc\u00dfler",
    "wof:placetype":"venue"
},
  "geometry": {"coordinates":[9.518757,49.667725],"type":"Point"}
}