{
  "type": "Feature",
  "properties": {
    "iso:country":"DE",
    "sg:address":"Nibelungenstr. 31",
    "sg:city":"Heidenheim",
    "sg:phone":"+49 7321/949892",
    "sg:postcode":"89518",
    "sg:province":"Baden-W\u00fcrttemberg",
    "wof:name":"G\u00fcnter T\u00fcch Anlageberater",
    "wof:placetype":"venue"
},
  "geometry": {"coordinates":[10.1284008026,48.6876144409],"type":"Point"}
}