{
  "type": "Feature",
  "properties": {
    "iso:country":"DE",
    "sg:city":"Ebermannstadt",
    "sg:postcode":"91320",
    "sg:province":"Bayern",
    "wof:name":"Campingplatz",
    "wof:placetype":"venue"
},
  "geometry": {"coordinates":[11.184495,49.779335],"type":"Point"}
}