{
  "type": "Feature",
  "properties": {
    "iso:country":"DE",
    "sg:address":"Jahnstr. 15",
    "sg:city":"Kamenz",
    "sg:phone":"+49 35783/10902",
    "sg:postcode":"01917",
    "sg:province":"Sachsen",
    "wof:name":"Malerbetrieb Scheede Gmbh",
    "wof:placetype":"venue"
},
  "geometry": {"coordinates":[14.10322,51.27433],"type":"Point"}
}