{
  "type": "Feature",
  "properties": {
    "iso:country":"DE",
    "sg:address":"Gabelsbergerstr. 6",
    "sg:city":"Gro\u00dfenhain",
    "sg:phone":"+49 3522/508275",
    "sg:postcode":"01558",
    "sg:province":"Sachsen",
    "wof:name":"Detlef Kruhl",
    "wof:placetype":"venue"
},
  "geometry": {"coordinates":[13.5298633575,51.2928504944],"type":"Point"}
}