{
  "type": "Feature",
  "properties": {
    "iso:country":"DE",
    "sg:address":"Karlsbader Str. 35",
    "sg:city":"Friedberg",
    "sg:phone":"+49 6031/14451",
    "sg:postcode":"61169",
    "sg:province":"Hessen",
    "wof:name":"Hans Hollmann Rechtsanwalt",
    "wof:placetype":"venue"
},
  "geometry": {"coordinates":[8.7538433075,50.3278694153],"type":"Point"}
}