{
  "type": "Feature",
  "properties": {
    "iso:country":"DE",
    "sg:address":"Schillerstr. 103",
    "sg:city":"Berlin",
    "sg:phone":"+49 30/3135650",
    "sg:postcode":"10625",
    "sg:province":"Berlin",
    "wof:name":"Taverna Kreta",
    "wof:placetype":"venue"
},
  "geometry": {"coordinates":[13.3138103485,52.5104751587],"type":"Point"}
}