{
  "type": "Feature",
  "properties": {
    "iso:country":"DE",
    "sg:address":"Tunnelstr. 14",
    "sg:city":"Stuttgart",
    "sg:phone":"+49 711/232884",
    "sg:postcode":"70469",
    "sg:province":"Baden-W\u00fcrttemberg",
    "wof:name":"Mb Treuhand Gmbh",
    "wof:placetype":"venue"
},
  "geometry": {"coordinates":[9.1708564758,48.8116416931],"type":"Point"}
}