{
  "type": "Feature",
  "properties": {
    "iso:country":"DE",
    "sg:address":"Pilzweg 6 A",
    "sg:city":"Gro\u00df Glienicke",
    "sg:phone":"+49 33201/21925",
    "sg:postcode":"14476",
    "sg:province":"Brandenburg",
    "wof:name":"Klaus Ullrich Architekt",
    "wof:placetype":"venue"
},
  "geometry": {"coordinates":[13.099107,52.456188],"type":"Point"}
}