{
  "type": "Feature",
  "properties": {
    "iso:country":"DE",
    "sg:address":"Waldstr. 1",
    "sg:city":"Friesenheim",
    "sg:phone":"+49 7821/61835",
    "sg:postcode":"77948",
    "sg:province":"Baden-W\u00fcrttemberg",
    "wof:name":"F. Oehl",
    "wof:placetype":"venue"
},
  "geometry": {"coordinates":[7.8982810974,48.3638458252],"type":"Point"}
}