{
  "type": "Feature",
  "properties": {
    "iso:country":"DE",
    "sg:address":"Virchowstr. 18",
    "sg:city":"Heidenheim",
    "sg:phone":"+49 7321/46533",
    "sg:postcode":"89518",
    "sg:province":"Baden-W\u00fcrttemberg",
    "wof:name":"Beratungsstelle D. Guttempler- Ordens",
    "wof:placetype":"venue"
},
  "geometry": {"coordinates":[10.15035,48.686722],"type":"Point"}
}