{
  "type": "Feature",
  "properties": {
    "iso:country":"DE",
    "sg:address":"F\u00fcrstenstr. 4-8",
    "sg:city":"Verl",
    "sg:phone":"+49 5246/3537",
    "sg:postcode":"33415",
    "sg:province":"Nordrhein-Westfalen",
    "wof:name":"W. Starp",
    "wof:placetype":"venue"
},
  "geometry": {"coordinates":[8.5580501556,51.8531188965],"type":"Point"}
}