{
  "type": "Feature",
  "properties": {
    "iso:country":"DE",
    "sg:address":"Zeisigweg 14",
    "sg:city":"Herzogenrath",
    "sg:phone":"+49 2407/917116",
    "sg:postcode":"52134",
    "sg:province":"Nordrhein-Westfalen",
    "wof:name":"Magnettherapie Und Hochzeitsgeschenke",
    "wof:placetype":"venue"
},
  "geometry": {"coordinates":[6.07535,50.838589],"type":"Point"}
}