{
  "type": "Feature",
  "properties": {
    "iso:country":"DE",
    "sg:address":"Regensburger Str. 6",
    "sg:city":"Regenstauf",
    "sg:phone":"+49 9402/70782",
    "sg:postcode":"93128",
    "sg:province":"Bayern",
    "wof:name":"Primavera",
    "wof:placetype":"venue"
},
  "geometry": {"coordinates":[12.1273431778,49.1222381592],"type":"Point"}
}