{
  "type": "Feature",
  "properties": {
    "iso:country":"DE",
    "sg:address":"Heidenheimer Str. 46",
    "sg:city":"Geislingen",
    "sg:phone":"+49 7331/951906",
    "sg:postcode":"73312",
    "sg:province":"Baden-W\u00fcrttemberg",
    "wof:name":"Restaurant Boxenstopp",
    "wof:placetype":"venue"
},
  "geometry": {"coordinates":[9.8452548981,48.6253585815],"type":"Point"}
}