{
  "type": "Feature",
  "properties": {
    "iso:country":"DE",
    "sg:address":"Moselstr 11",
    "sg:city":"Solingen",
    "sg:phone":"+49 212/332077",
    "sg:postcode":"42655",
    "sg:province":"Nordrhein-Westfalen",
    "wof:name":"Christian Linden",
    "wof:placetype":"venue"
},
  "geometry": {"coordinates":[7.074323,51.16811],"type":"Point"}
}