{
  "type": "Feature",
  "properties": {
    "iso:country":"DE",
    "sg:address":"Rathausstr. 40",
    "sg:city":"Bexbach",
    "sg:postcode":"66450",
    "sg:province":"Saarland",
    "wof:name":"Stadtb\u00fccherei",
    "wof:placetype":"venue"
},
  "geometry": {"coordinates":[7.256532,49.348858],"type":"Point"}
}