{
  "type": "Feature",
  "properties": {
    "iso:country":"DE",
    "sg:address":"Schwanthalerstr. 88",
    "sg:city":"M\u00fcnchen",
    "sg:phone":"+49 89/530140",
    "sg:postcode":"80336",
    "sg:province":"Bayern",
    "wof:name":"Schwanthaler Br\u00e4uwastl",
    "wof:placetype":"venue"
},
  "geometry": {"coordinates":[11.5520486832,48.1376800537],"type":"Point"}
}