{
  "type": "Feature",
  "properties": {
    "iso:country":"DE",
    "sg:address":"Raiffeisenstr. 4",
    "sg:city":"Todtenweis",
    "sg:phone":"+49 8237/804",
    "sg:postcode":"86447",
    "sg:province":"Bayern",
    "wof:name":"Josef Wackerl Jun.",
    "wof:placetype":"venue"
},
  "geometry": {"coordinates":[10.9293270111,48.5187110901],"type":"Point"}
}