{
  "type": "Feature",
  "properties": {
    "iso:country":"DE",
    "sg:address":"Holbeinstr. 16",
    "sg:city":"Freiburg",
    "sg:phone":"+49 761/703330",
    "sg:postcode":"79100",
    "sg:province":"Baden-W\u00fcrttemberg",
    "wof:name":"Vhv Vereinigte Haftpflicht- Versicherung Vvag",
    "wof:placetype":"venue"
},
  "geometry": {"coordinates":[7.8451871872,47.9811515808],"type":"Point"}
}