{
  "type": "Feature",
  "properties": {
    "iso:country":"DE",
    "sg:city":"L\u00fcnen",
    "sg:phone":"+49 2306/9480",
    "sg:postcode":"44532",
    "sg:province":"Nordrhein-Westfalen",
    "wof:name":"Victoria Bautr\u00e4ger Gmbh",
    "wof:placetype":"venue"
},
  "geometry": {"coordinates":[7.52782,51.587921],"type":"Point"}
}