{
  "type": "Feature",
  "properties": {
    "iso:country":"DE",
    "sg:address":"Germersheimer Str. 76a",
    "sg:city":"Lingenfeld",
    "sg:phone":"+49 6344/5720",
    "sg:postcode":"67360",
    "sg:province":"Rheinland-Pfalz",
    "wof:name":"Ernst Ackermann",
    "wof:placetype":"venue"
},
  "geometry": {"coordinates":[8.343255,49.247559],"type":"Point"}
}