{
  "type": "Feature",
  "properties": {
    "iso:country":"DE",
    "sg:address":"Bahnhofstr. 37",
    "sg:city":"Planegg",
    "sg:phone":"+49 89/8991510",
    "sg:postcode":"82152",
    "sg:province":"Bayern",
    "wof:name":"Ulrich Elsner Ingenieur",
    "wof:placetype":"venue"
},
  "geometry": {"coordinates":[11.4168987274,48.1044120789],"type":"Point"}
}