{
  "type": "Feature",
  "properties": {
    "iso:country":"DE",
    "sg:address":"Dorfstr. 8",
    "sg:city":"Dahlem",
    "sg:phone":"+49 6557/854",
    "sg:postcode":"53949",
    "sg:province":"Nordrhein-Westfalen",
    "wof:name":"Eduard Bungartz",
    "wof:placetype":"venue"
},
  "geometry": {"coordinates":[6.4619441032,50.3838119507],"type":"Point"}
}