{
  "type": "Feature",
  "properties": {
    "iso:country":"DE",
    "sg:address":"Cannstatter Str. 82 /1",
    "sg:city":"Fellbach",
    "sg:phone":"+49 711/581230",
    "sg:postcode":"70734",
    "sg:province":"Baden-W\u00fcrttemberg",
    "wof:name":"S\u00fcd-inkasso Willi Und J\u00f6rg Hoster Ohg",
    "wof:placetype":"venue"
},
  "geometry": {"coordinates":[9.2775850296,48.8109207153],"type":"Point"}
}