{
  "type": "Feature",
  "properties": {
    "iso:country":"DE",
    "sg:address":"Postillionsweg 15",
    "sg:city":"M\u00f6nchengladbach",
    "sg:phone":"+49 2166/57292",
    "sg:postcode":"41189",
    "sg:province":"Nordrhein-Westfalen",
    "wof:name":"Anke Sattelmeyer-heinrichs",
    "wof:placetype":"venue"
},
  "geometry": {"coordinates":[6.414497,51.115227],"type":"Point"}
}