{
  "type": "Feature",
  "properties": {
    "iso:country":"DE",
    "sg:address":"Werner-von-Siemens-Str. 3",
    "sg:city":"Wiehl",
    "sg:phone":"+49 2261/9750",
    "sg:postcode":"51674",
    "sg:province":"Nordrhein-Westfalen",
    "wof:name":"Bubenzer & Krefting",
    "wof:placetype":"venue"
},
  "geometry": {"coordinates":[7.5253348351,50.9695777893],"type":"Point"}
}