{
  "type": "Feature",
  "properties": {
    "iso:country":"DE",
    "sg:address":"Weinbrennerstr. 7b",
    "sg:city":"Rheinstetten",
    "sg:phone":"+49 721/519294",
    "sg:postcode":"76287",
    "sg:province":"Baden-W\u00fcrttemberg",
    "wof:name":"Libuse Iran",
    "wof:placetype":"venue"
},
  "geometry": {"coordinates":[8.321572,48.982697],"type":"Point"}
}