{
  "type": "Feature",
  "properties": {
    "iso:country":"DE",
    "sg:address":"Eheweg 3",
    "sg:city":"Aurich",
    "sg:phone":"+49 4941/7727",
    "sg:postcode":"26607",
    "sg:province":"Niedersachsen",
    "wof:name":"Schwitters Beteiligungs-gmbh",
    "wof:placetype":"venue"
},
  "geometry": {"coordinates":[7.505727,53.49263],"type":"Point"}
}