{
  "type": "Feature",
  "properties": {
    "iso:country":"DE",
    "sg:address":"Heinz-R\u00fchmann-Str. 10",
    "sg:city":"Neu-Ulm",
    "sg:phone":"+49 731/85503",
    "sg:postcode":"89231",
    "sg:province":"Bayern",
    "wof:name":"Edf Elektro- Daten- Und Fernmeldetechnik Gmbh",
    "wof:placetype":"venue"
},
  "geometry": {"coordinates":[10.007907,48.386086],"type":"Point"}
}