{
  "type": "Feature",
  "properties": {
    "iso:country":"DE",
    "sg:address":"Moorb\u00e4ksweg 9",
    "sg:city":"Wardenburg",
    "sg:phone":"+49 4407/1697",
    "sg:postcode":"26203",
    "sg:province":"Niedersachsen",
    "wof:name":"Mehrens Architekt",
    "wof:placetype":"venue"
},
  "geometry": {"coordinates":[8.202281,53.059765],"type":"Point"}
}