{
  "type": "Feature",
  "properties": {
    "iso:country":"DE",
    "sg:address":"D\u00fcsseldorfer Str. 35",
    "sg:city":"Ratingen",
    "sg:phone":"+49 2102/74240",
    "sg:postcode":"40878",
    "sg:province":"Nordrhein-Westfalen",
    "wof:name":"C & A Bekleidungen",
    "wof:placetype":"venue"
},
  "geometry": {"coordinates":[6.847497,51.296055],"type":"Point"}
}