{
  "type": "Feature",
  "properties": {
    "iso:country":"DE",
    "sg:address":"Talhausstr. 4",
    "sg:city":"Hockenheim",
    "sg:phone":"+49 6205/958100",
    "sg:postcode":"68766",
    "sg:province":"Baden-W\u00fcrttemberg",
    "wof:name":"Topcos Parf\u00fcmerie- Cooperations- Vertriebs-",
    "wof:placetype":"venue"
},
  "geometry": {"coordinates":[8.5378417969,49.3292312622],"type":"Point"}
}