{
  "type": "Feature",
  "properties": {
    "iso:country":"DE",
    "sg:address":"Julius-Echter-Str. 12",
    "sg:city":"Sulzdorf",
    "sg:phone":"+49 9763/1044",
    "sg:postcode":"97528",
    "sg:province":"Bayern",
    "wof:name":"Adolf Eschenbach",
    "wof:placetype":"venue"
},
  "geometry": {"coordinates":[10.5396556854,50.2676048279],"type":"Point"}
}