{
  "type": "Feature",
  "properties": {
    "iso:country":"DE",
    "sg:address":"Schlehenrain 10",
    "sg:city":"Freiburg",
    "sg:phone":"+49 761/5009775",
    "sg:postcode":"79108",
    "sg:province":"Baden-W\u00fcrttemberg",
    "wof:name":"F. Von Kajdacsy Innenarchitekt",
    "wof:placetype":"venue"
},
  "geometry": {"coordinates":[7.866662,48.020523],"type":"Point"}
}