{
  "type": "Feature",
  "properties": {
    "iso:country":"DE",
    "sg:address":"Otterzhofen 34",
    "sg:city":"Riedenburg",
    "sg:phone":"+49 9442/601",
    "sg:postcode":"93339",
    "sg:province":"Bayern",
    "wof:name":"Johann Roidl",
    "wof:placetype":"venue"
},
  "geometry": {"coordinates":[11.68953,49.007702],"type":"Point"}
}