{
  "type": "Feature",
  "properties": {
    "iso:country":"DE",
    "sg:address":"Friedrichsgaber Str 71",
    "sg:city":"Quickborn",
    "sg:phone":"+49 4106/77600",
    "sg:postcode":"25451",
    "sg:province":"Schleswig-Holstein",
    "wof:name":"Wohlenberg & Co. Theater- Und Dekostoffe",
    "wof:placetype":"venue"
},
  "geometry": {"coordinates":[9.94433,53.745888],"type":"Point"}
}