{
  "type": "Feature",
  "properties": {
    "iso:country":"DE",
    "sg:address":"Allee 2",
    "sg:city":"Holzwickede",
    "sg:phone":"+49 2301/14129",
    "sg:postcode":"59439",
    "sg:province":"Nordrhein-Westfalen",
    "wof:name":"Christa K\u00fchn",
    "wof:placetype":"venue"
},
  "geometry": {"coordinates":[7.617688,51.502834],"type":"Point"}
}