{
  "type": "Feature",
  "properties": {
    "iso:country":"DE",
    "sg:address":"Viehweg 32",
    "sg:city":"Leinfelden-Echterdingen",
    "sg:phone":"+49 711/7541179",
    "sg:postcode":"70771",
    "sg:province":"Baden-W\u00fcrttemberg",
    "wof:name":"Kuno Kaehne Verlagsvertreter",
    "wof:placetype":"venue"
},
  "geometry": {"coordinates":[9.116274,48.703159],"type":"Point"}
}