{
  "type": "Feature",
  "properties": {
    "iso:country":"DE",
    "sg:address":"Wilhelm-von-Leibniz-Str. 50",
    "sg:city":"Rathenow",
    "sg:phone":"+49 3385/515835",
    "sg:postcode":"14712",
    "sg:province":"Brandenburg",
    "wof:name":"Ehlert Metallbau Gmbh",
    "wof:placetype":"venue"
},
  "geometry": {"coordinates":[12.346882,52.613819],"type":"Point"}
}