{
  "type": "Feature",
  "properties": {
    "iso:country":"DE",
    "sg:address":"Oststr.2/2",
    "sg:city":"Marbach a/N.",
    "sg:phone":"+49 7144/998027",
    "sg:postcode":"71672",
    "sg:province":"Baden-W\u00fcrttemberg",
    "wof:name":"Y\u00fccel-elektro",
    "wof:placetype":"venue"
},
  "geometry": {"coordinates":[9.3300552368,48.9616012573],"type":"Point"}
}