{
  "type": "Feature",
  "properties": {
    "iso:country":"DE",
    "sg:address":"Badergasse 2",
    "sg:city":"Hainichen",
    "sg:phone":"+49 37207/3858",
    "sg:postcode":"09661",
    "sg:province":"Sachsen",
    "wof:name":"Schmiedebetrieb Manfred Hurras",
    "wof:placetype":"venue"
},
  "geometry": {"coordinates":[13.1230792999,50.9733085632],"type":"Point"}
}