{
  "type": "Feature",
  "properties": {
    "iso:country":"DE",
    "sg:address":"Hunoldstr. 54",
    "sg:city":"Hameln",
    "sg:phone":"+49 5151",
    "sg:postcode":"31785",
    "sg:province":"Niedersachsen",
    "wof:name":"Sylvias Kleine Strolche\u00b4",
    "wof:placetype":"venue"
},
  "geometry": {"coordinates":[9.370261,52.107704],"type":"Point"}
}