{
  "type": "Feature",
  "properties": {
    "iso:country":"DE",
    "sg:address":"Rasenm\u00fchlenweg 8",
    "sg:city":"Bad Langensalza",
    "sg:phone":"+49 3603/842818",
    "sg:postcode":"99947",
    "sg:province":"Th\u00fcringen",
    "wof:name":"M. Nu\u00dfbaum",
    "wof:placetype":"venue"
},
  "geometry": {"coordinates":[10.655133,51.117016],"type":"Point"}
}