{
  "type": "Feature",
  "properties": {
    "iso:country":"DE",
    "sg:address":"Siedlung 25",
    "sg:city":"Augustusburg",
    "sg:phone":"+49 37291/6295",
    "sg:postcode":"09573",
    "sg:province":"Sachsen",
    "wof:name":"H. Klemm",
    "wof:placetype":"venue"
},
  "geometry": {"coordinates":[13.104378,50.82119],"type":"Point"}
}