{
  "type": "Feature",
  "properties": {
    "iso:country":"DE",
    "sg:address":"Auheimer Str. 6",
    "sg:city":"Rodenbach",
    "sg:phone":"+49 6184/50567",
    "sg:postcode":"63517",
    "sg:province":"Hessen",
    "wof:name":"Wilma G\u00f6bel Hebamme",
    "wof:placetype":"venue"
},
  "geometry": {"coordinates":[9.017206,50.142673],"type":"Point"}
}