{
  "type": "Feature",
  "properties": {
    "iso:country":"DE",
    "sg:address":"Uferweg 17",
    "sg:city":"Delmenhorst",
    "sg:phone":"+49 4221/64448",
    "sg:postcode":"27749",
    "sg:province":"Niedersachsen",
    "wof:name":"Karl Meyer Steuerberater",
    "wof:placetype":"venue"
},
  "geometry": {"coordinates":[8.6443309784,53.0453796387],"type":"Point"}
}