{
  "type": "Feature",
  "properties": {
    "iso:country":"DE",
    "sg:address":"Germanenstr. 43",
    "sg:city":"Solingen",
    "sg:phone":"+49 212/2542773",
    "sg:postcode":"42653",
    "sg:province":"Nordrhein-Westfalen",
    "wof:name":"Uwe Scherf Rechtsanwalt",
    "wof:placetype":"venue"
},
  "geometry": {"coordinates":[7.0715827942,51.1874885559],"type":"Point"}
}