{
  "type": "Feature",
  "properties": {
    "iso:country":"DE",
    "sg:address":"Severiberg 6",
    "sg:city":"Fulda",
    "sg:phone":"+49 661/72707",
    "sg:postcode":"36037",
    "sg:province":"Hessen",
    "wof:name":"Klaus Jerwin Rechtsanwalt Und Notar",
    "wof:placetype":"venue"
},
  "geometry": {"coordinates":[9.6745853424,50.552154541],"type":"Point"}
}