{
  "type": "Feature",
  "properties": {
    "iso:country":"DE",
    "sg:address":"Bommichring 40",
    "sg:city":"Glattbach",
    "sg:phone":"+49 6021/421818",
    "sg:postcode":"63864",
    "sg:province":"Bayern",
    "wof:name":"Nikolaus Lessl Innenarchitekt",
    "wof:placetype":"venue"
},
  "geometry": {"coordinates":[9.153068,50.009766],"type":"Point"}
}