{
  "type": "Feature",
  "properties": {
    "iso:country":"DE",
    "sg:address":"Hastedter Heerstr. 141",
    "sg:city":"Bremen",
    "sg:phone":"+49 421/444565",
    "sg:postcode":"28207",
    "sg:province":"Bremen",
    "wof:name":"M. Streckel",
    "wof:placetype":"venue"
},
  "geometry": {"coordinates":[8.8655738831,53.0667533875],"type":"Point"}
}