{
  "type": "Feature",
  "properties": {
    "iso:country":"DE",
    "sg:address":"Lotterbergstr. 50",
    "sg:city":"Kempten",
    "sg:phone":"+49 831/91707",
    "sg:postcode":"87439",
    "sg:province":"Bayern",
    "wof:name":"Herbert H. Schmidt Heilpraktiker",
    "wof:placetype":"venue"
},
  "geometry": {"coordinates":[10.2995023727,47.7380943298],"type":"Point"}
}