{
  "type": "Feature",
  "properties": {
    "iso:country":"DE",
    "sg:address":"Carl-Schurz-Str. 53",
    "sg:city":"Berlin",
    "sg:phone":"+49 30/3335098",
    "sg:postcode":"13597",
    "sg:province":"Berlin",
    "wof:name":"Praxis Dr. Med. Pohlmann Dr. Med. Sohn Und",
    "wof:placetype":"venue"
},
  "geometry": {"coordinates":[13.2047367096,52.5387802124],"type":"Point"}
}