{
  "type": "Feature",
  "properties": {
    "iso:country":"DE",
    "sg:address":"Kirchstr. 26",
    "sg:city":"Kissing",
    "sg:phone":"+49 8233/6115",
    "sg:postcode":"86438",
    "sg:province":"Bayern",
    "wof:name":"W. Serf\u00f6z\u00f6",
    "wof:placetype":"venue"
},
  "geometry": {"coordinates":[10.9738559723,48.3044624329],"type":"Point"}
}