{
  "type": "Feature",
  "properties": {
    "iso:country":"DE",
    "sg:address":"Ludwigstr. 14",
    "sg:city":"Kempten",
    "sg:phone":"+49 831/561260",
    "sg:postcode":"87437",
    "sg:province":"Bayern",
    "wof:name":"Hin & Mit",
    "wof:placetype":"venue"
},
  "geometry": {"coordinates":[10.325134,47.712215],"type":"Point"}
}