{
  "type": "Feature",
  "properties": {
    "iso:country":"DE",
    "sg:address":"Hauptstr. 22",
    "sg:city":"Armsheim",
    "sg:phone":"+49 6734/1215",
    "sg:postcode":"55288",
    "sg:province":"Rheinland-Pfalz",
    "wof:name":"Hans Mohr",
    "wof:placetype":"venue"
},
  "geometry": {"coordinates":[8.0557146072,49.8061103821],"type":"Point"}
}