{
  "type": "Feature",
  "properties": {
    "iso:country":"DE",
    "sg:address":"Kirchstr. 38",
    "sg:city":"Oestrich-Winkel",
    "sg:phone":"+49 6723/3685",
    "sg:postcode":"65375",
    "sg:province":"Hessen",
    "wof:name":"Ferdi Holland",
    "wof:placetype":"venue"
},
  "geometry": {"coordinates":[8.00058,50.00386],"type":"Point"}
}