{
  "type": "Feature",
  "properties": {
    "iso:country":"DE",
    "sg:address":"Stubbenkamp 1",
    "sg:city":"D\u00f6rverden",
    "sg:phone":"+49 4234/454",
    "sg:postcode":"27313",
    "sg:province":"Niedersachsen",
    "wof:name":"Rudolf Sch\u00f6ner Steuerberater",
    "wof:placetype":"venue"
},
  "geometry": {"coordinates":[9.24477005,52.8545532227],"type":"Point"}
}