{
  "type": "Feature",
  "properties": {
    "iso:country":"DE",
    "sg:address":"Hoher Kamp 9",
    "sg:city":"Friedeburg",
    "sg:phone":"+49 4465/77397",
    "sg:postcode":"26446",
    "sg:province":"Niedersachsen",
    "wof:name":"Friedeburger Osterbasar",
    "wof:placetype":"venue"
},
  "geometry": {"coordinates":[7.824927,53.451164],"type":"Point"}
}