{
  "type": "Feature",
  "properties": {
    "iso:country":"DE",
    "sg:address":"Alte Langewahler Chaussee 44",
    "sg:city":"F\u00fcrstenwalde",
    "sg:phone":"+49 3361",
    "sg:postcode":"15517",
    "sg:province":"Brandenburg",
    "wof:name":"Druckerei Oehme",
    "wof:placetype":"venue"
},
  "geometry": {"coordinates":[14.061339,52.357471],"type":"Point"}
}