{
  "type": "Feature",
  "properties": {
    "iso:country":"DE",
    "sg:address":"Hubert-Wollenberg-Str. 17-19",
    "sg:city":"Ratingen",
    "sg:phone":"+49 2102/42530",
    "sg:postcode":"40878",
    "sg:province":"Nordrhein-Westfalen",
    "wof:name":"Rawa Stahlhandel Gmbh & Co. Kommanditgesellschaft",
    "wof:placetype":"venue"
},
  "geometry": {"coordinates":[6.835514,51.290871],"type":"Point"}
}