{
  "type": "Feature",
  "properties": {
    "iso:country":"DE",
    "sg:address":"Lederstr. 146",
    "sg:city":"Reutlingen",
    "sg:phone":"+49 7121/329976",
    "sg:postcode":"72764",
    "sg:province":"Baden-W\u00fcrttemberg",
    "wof:name":"A. Harb",
    "wof:placetype":"venue"
},
  "geometry": {"coordinates":[9.216502,48.489876],"type":"Point"}
}