{
  "type": "Feature",
  "properties": {
    "iso:country":"DE",
    "sg:address":"Herrenm\u00fchlweg 6",
    "sg:city":"Kronach",
    "sg:phone":"+49 9261/1556",
    "sg:postcode":"96317",
    "sg:province":"Bayern",
    "wof:name":"Pizzeria Mamma Piera",
    "wof:placetype":"venue"
},
  "geometry": {"coordinates":[11.3268232346,50.2402153015],"type":"Point"}
}