{
  "type": "Feature",
  "properties": {
    "iso:country":"DE",
    "sg:address":"Donauschwabenstr. 1",
    "sg:city":"Karlsruhe",
    "sg:phone":"+49 721/707096",
    "sg:postcode":"76149",
    "sg:province":"Baden-W\u00fcrttemberg",
    "wof:name":"Union Special Gmbh",
    "wof:placetype":"venue"
},
  "geometry": {"coordinates":[8.39633,49.049747],"type":"Point"}
}