{
  "type": "Feature",
  "properties": {
    "iso:country":"DE",
    "sg:address":"Eppendorfer Weg 276",
    "sg:city":"Hamburg",
    "sg:phone":"+49 40/487715",
    "sg:postcode":"20251",
    "sg:province":"Hamburg",
    "wof:name":"Meier V\u00fcmpf",
    "wof:placetype":"venue"
},
  "geometry": {"coordinates":[9.9800786972,53.5845069885],"type":"Point"}
}