{
  "type": "Feature",
  "properties": {
    "iso:country":"DE",
    "sg:address":"Th\u00fclener Bruch",
    "sg:city":"Brilon",
    "sg:postcode":"59929",
    "sg:province":"Nordrhein-Westfalen",
    "wof:name":"Flugplatzgesellschaft Brilon Mbh",
    "wof:placetype":"venue"
},
  "geometry": {"coordinates":[8.6388950348,51.399684906],"type":"Point"}
}