{
  "type": "Feature",
  "properties": {
    "iso:country":"DE",
    "sg:address":"Saarlandstr 377",
    "sg:city":"Bingen",
    "sg:phone":"+49 2751/5545",
    "sg:postcode":"55411",
    "sg:province":"Rheinland-Pfalz",
    "wof:name":"Bergner Kunststoffprofile Gmbh",
    "wof:placetype":"venue"
},
  "geometry": {"coordinates":[8.749902,50.396671],"type":"Point"}
}