{
  "type": "Feature",
  "properties": {
    "iso:country":"DE",
    "sg:address":"Sanitzer Str. 1",
    "sg:city":"Ribnitz-Damgarten",
    "sg:phone":"+49 3821/813665",
    "sg:postcode":"18311",
    "sg:province":"Mecklenburg-Vorpommern",
    "wof:name":"Ribnitzer Metall- Verarbeitung Gmbh",
    "wof:placetype":"venue"
},
  "geometry": {"coordinates":[12.4375991821,54.2385559082],"type":"Point"}
}