{
  "type": "Feature",
  "properties": {
    "iso:country":"DE",
    "sg:address":"Husbergermoor 79",
    "sg:city":"B\u00f6neb\u00fcttel",
    "sg:phone":"+49 4394/856",
    "sg:postcode":"24620",
    "sg:province":"Schleswig-Holstein",
    "wof:name":"Norbert Sperber Gmbh",
    "wof:placetype":"venue"
},
  "geometry": {"coordinates":[10.108744,54.062866],"type":"Point"}
}