{
  "type": "Feature",
  "properties": {
    "iso:country":"DE",
    "sg:address":"Haddorf 44",
    "sg:city":"Wettringen",
    "sg:phone":"+49 5973/3253",
    "sg:postcode":"48493",
    "sg:province":"Nordrhein-Westfalen",
    "wof:name":"Restaurant Wolters & L\u00f6bbers",
    "wof:placetype":"venue"
},
  "geometry": {"coordinates":[7.3145060539,52.257144928],"type":"Point"}
}