{
  "type": "Feature",
  "properties": {
    "iso:country":"DE",
    "sg:address":"Hauswiesenstr. 14",
    "sg:city":"Bad Wildbad",
    "sg:phone":"+49 7081/8498",
    "sg:postcode":"75323",
    "sg:province":"Baden-W\u00fcrttemberg",
    "wof:name":"Bushfire Trading Gmbh",
    "wof:placetype":"venue"
},
  "geometry": {"coordinates":[8.5486211777,48.7513504028],"type":"Point"}
}