{
  "type": "Feature",
  "properties": {
    "iso:country":"DE",
    "sg:address":"Moltkestr. 8",
    "sg:city":"Gie\u00dfen",
    "sg:phone":"+49 641/9303909",
    "sg:postcode":"35390",
    "sg:province":"Hessen",
    "wof:name":"G. Schmoranzer Ergotherapie",
    "wof:placetype":"venue"
},
  "geometry": {"coordinates":[8.682348,50.585861],"type":"Point"}
}