{
  "type": "Feature",
  "properties": {
    "iso:country":"DE",
    "sg:address":"Am Taubergrund 4",
    "sg:city":"Bad Mergentheim",
    "sg:phone":"+49 7931/52275",
    "sg:postcode":"97980",
    "sg:province":"Baden-W\u00fcrttemberg",
    "wof:name":"B\u00fcrgerstube Edelfingen",
    "wof:placetype":"venue"
},
  "geometry": {"coordinates":[9.7506952286,49.5113525391],"type":"Point"}
}