{
  "type": "Feature",
  "properties": {
    "iso:country":"DE",
    "sg:address":"Krayer Str. 63",
    "sg:city":"Essen",
    "sg:phone":"+49 201/595498",
    "sg:postcode":"45276",
    "sg:province":"Nordrhein-Westfalen",
    "wof:name":"Wolfgang Hackenberg Kg",
    "wof:placetype":"venue"
},
  "geometry": {"coordinates":[7.077064991,51.4550628662],"type":"Point"}
}