{
  "type": "Feature",
  "properties": {
    "iso:country":"DE",
    "sg:address":"Schillerstr. 18",
    "sg:city":"Dirmstein",
    "sg:phone":"+49 6238/2739",
    "sg:postcode":"67246",
    "sg:province":"Rheinland-Pfalz",
    "wof:name":"Horst Storzum",
    "wof:placetype":"venue"
},
  "geometry": {"coordinates":[8.2449092865,49.567489624],"type":"Point"}
}