{
  "type": "Feature",
  "properties": {
    "iso:country":"DE",
    "sg:address":"Lotter Str. 111",
    "sg:city":"Osnabr\u00fcck",
    "sg:phone":"+49 541/43973",
    "sg:postcode":"49078",
    "sg:province":"Niedersachsen",
    "wof:name":"Boutique-antik Antiquit\u00e4ten",
    "wof:placetype":"venue"
},
  "geometry": {"coordinates":[8.03162,52.274837],"type":"Point"}
}