{
  "type": "Feature",
  "properties": {
    "iso:country":"DE",
    "sg:address":"Schubertstr. 34",
    "sg:city":"Ravensburg",
    "sg:phone":"+49 751/2856",
    "sg:postcode":"88214",
    "sg:province":"Baden-W\u00fcrttemberg",
    "wof:name":"Renas Imbi\u00df",
    "wof:placetype":"venue"
},
  "geometry": {"coordinates":[9.5996656418,47.7727165222],"type":"Point"}
}