{
  "type": "Feature",
  "properties": {
    "iso:country":"DE",
    "sg:address":"Resselsteig 30",
    "sg:city":"Berlin",
    "sg:phone":"+49 30/77328099",
    "sg:postcode":"12209",
    "sg:province":"Berlin",
    "wof:name":"Openspace-online Gmbh",
    "wof:placetype":"venue"
},
  "geometry": {"coordinates":[13.3271989822,52.4148597717],"type":"Point"}
}