{
  "type": "Feature",
  "properties": {
    "iso:country":"DE",
    "sg:address":"Senftenberger Ring 3",
    "sg:city":"Berlin",
    "sg:phone":"+49 30/4162218",
    "sg:postcode":"13439",
    "sg:province":"Berlin",
    "wof:name":"Tzikas",
    "wof:placetype":"venue"
},
  "geometry": {"coordinates":[13.3558082581,52.5973739624],"type":"Point"}
}