{
  "type": "Feature",
  "properties": {
    "iso:country":"DE",
    "sg:address":"Emsstr. 16",
    "sg:city":"Emsdetten",
    "sg:phone":"+49 2572/953044",
    "sg:postcode":"48282",
    "sg:province":"Nordrhein-Westfalen",
    "wof:name":"Manhattan Spielcenter",
    "wof:placetype":"venue"
},
  "geometry": {"coordinates":[7.5295028687,52.1760253906],"type":"Point"}
}