{
  "type": "Feature",
  "properties": {
    "iso:country":"DE",
    "sg:address":"Rennergasse 6",
    "sg:city":"Sasbach",
    "sg:phone":"+49 7642/5880",
    "sg:postcode":"79361",
    "sg:province":"Baden-W\u00fcrttemberg",
    "wof:name":"Siegfried Tritschler",
    "wof:placetype":"venue"
},
  "geometry": {"coordinates":[7.6167769432,48.1415061951],"type":"Point"}
}