{
  "type": "Feature",
  "properties": {
    "iso:country":"DE",
    "sg:address":"Kandelstr. 3",
    "sg:city":"Glottertal",
    "sg:phone":"+49 7684/337",
    "sg:postcode":"79286",
    "sg:province":"Baden-W\u00fcrttemberg",
    "wof:name":"Karl Linder",
    "wof:placetype":"venue"
},
  "geometry": {"coordinates":[7.9548687935,48.0467414856],"type":"Point"}
}