{
  "type": "Feature",
  "properties": {
    "iso:country":"DE",
    "sg:address":"Nibelungenstr. 52",
    "sg:city":"Dietzenbach",
    "sg:phone":"+49 6074/26237",
    "sg:postcode":"63128",
    "sg:province":"Hessen",
    "wof:name":"T W S Treuhand Gmbh Steuerberatungsgesellschaft",
    "wof:placetype":"venue"
},
  "geometry": {"coordinates":[8.787566185,50.0246810913],"type":"Point"}
}