{
  "type": "Feature",
  "properties": {
    "iso:country":"DE",
    "sg:address":"Rosa-Luxemburg-Str. 2",
    "sg:city":"Eibenstock",
    "sg:phone":"+49 37752/2405",
    "sg:postcode":"08309",
    "sg:province":"Sachsen",
    "wof:name":"Sylvia Berger",
    "wof:placetype":"venue"
},
  "geometry": {"coordinates":[12.603624,50.493916],"type":"Point"}
}