{
  "type": "Feature",
  "properties": {
    "iso:country":"DE",
    "sg:address":"Parkstr. 15",
    "sg:city":"Nidda",
    "sg:phone":"+49 6043/3684",
    "sg:postcode":"63667",
    "sg:province":"Hessen",
    "wof:name":"Smb Gesellschaft F\u00fcr Automatisierungstechnik Mbh",
    "wof:placetype":"venue"
},
  "geometry": {"coordinates":[8.9695720673,50.4052467346],"type":"Point"}
}