{
  "type": "Feature",
  "properties": {
    "iso:country":"DE",
    "sg:address":"Mittelstr. 29",
    "sg:city":"Lemgo",
    "sg:phone":"+49 5261/14969",
    "sg:postcode":"32657",
    "sg:province":"Nordrhein-Westfalen",
    "wof:name":"Hans-georg Kolowrat Rechtsanwalt",
    "wof:placetype":"venue"
},
  "geometry": {"coordinates":[8.9036064148,52.0280838013],"type":"Point"}
}