{
  "type": "Feature",
  "properties": {
    "iso:country":"DE",
    "sg:address":"Heinrich-Roth-Platz 1",
    "sg:city":"Dillingen",
    "sg:phone":"+49 9071/9066",
    "sg:postcode":"89407",
    "sg:province":"Bayern",
    "wof:name":"Obere Stadt-apotheke Walter Schneider",
    "wof:placetype":"venue"
},
  "geometry": {"coordinates":[10.492221,48.576817],"type":"Point"}
}