{
  "type": "Feature",
  "properties": {
    "iso:country":"DE",
    "sg:address":"Alte Poststr. 3",
    "sg:city":"Bruckberg",
    "sg:phone":"+49 9824/922929",
    "sg:postcode":"91590",
    "sg:province":"Bayern",
    "wof:name":"Pizzeria Raffaele",
    "wof:placetype":"venue"
},
  "geometry": {"coordinates":[10.6979646683,49.3587684631],"type":"Point"}
}