{
  "type": "Feature",
  "properties": {
    "iso:country":"DE",
    "sg:address":"Landstr. 1",
    "sg:city":"Holzbunge",
    "sg:phone":"+49 4356/616",
    "sg:postcode":"24361",
    "sg:province":"Schleswig-Holstein",
    "wof:name":"Reiner Hargens",
    "wof:placetype":"venue"
},
  "geometry": {"coordinates":[9.7053098679,54.3776893616],"type":"Point"}
}