{
  "type": "Feature",
  "properties": {
    "iso:country":"DE",
    "sg:address":"R\u00f6merstr. 12",
    "sg:city":"Krefeld",
    "sg:postcode":"47809",
    "sg:province":"Nordrhein-Westfalen",
    "wof:name":"H & H Gebr\u00fcder Holloh Gmbh",
    "wof:placetype":"venue"
},
  "geometry": {"coordinates":[6.672771,51.327675],"type":"Point"}
}