{
  "type": "Feature",
  "properties": {
    "iso:country":"DE",
    "sg:address":"Am Herrenacker 9",
    "sg:city":"Bruchm\u00fchlbach-Miesau",
    "sg:phone":"+49 6372/8078",
    "sg:postcode":"66892",
    "sg:province":"Rheinland-Pfalz",
    "wof:name":"Turek System-technik",
    "wof:placetype":"venue"
},
  "geometry": {"coordinates":[7.46632,49.386902],"type":"Point"}
}