{
  "type": "Feature",
  "properties": {
    "iso:country":"DE",
    "sg:address":"Hauptstr. 107",
    "sg:city":"Viersen",
    "sg:postcode":"41747",
    "sg:province":"Nordrhein-Westfalen",
    "wof:name":"Vz Reformh\u00e4user Betriebsges. Mbh",
    "wof:placetype":"venue"
},
  "geometry": {"coordinates":[6.3915472031,51.2545013428],"type":"Point"}
}