{
  "type": "Feature",
  "properties": {
    "iso:country":"DE",
    "sg:address":"Ziegelstr. 3",
    "sg:city":"Hannover",
    "sg:phone":"+49 511/401066",
    "sg:postcode":"30453",
    "sg:province":"Niedersachsen",
    "wof:name":"W. Luft Gmbh",
    "wof:placetype":"venue"
},
  "geometry": {"coordinates":[9.661696,52.387409],"type":"Point"}
}