{
  "type": "Feature",
  "properties": {
    "iso:country":"DE",
    "sg:address":"Glaner Weg 19",
    "sg:city":"Bad Laer",
    "sg:phone":"+49 5424/3173",
    "sg:postcode":"49196",
    "sg:province":"Niedersachsen",
    "wof:name":"Dieter Klare",
    "wof:placetype":"venue"
},
  "geometry": {"coordinates":[8.09278,52.126453],"type":"Point"}
}