{
  "type": "Feature",
  "properties": {
    "iso:country":"DE",
    "sg:address":"Alter Markt 3",
    "sg:city":"Solingen",
    "sg:phone":"+49 212/202677",
    "sg:postcode":"42651",
    "sg:province":"Nordrhein-Westfalen",
    "wof:name":"Frank R\u00f6ltgen Immobilienmakler",
    "wof:placetype":"venue"
},
  "geometry": {"coordinates":[7.0835042,51.171333313],"type":"Point"}
}