{
  "type": "Feature",
  "properties": {
    "iso:country":"DE",
    "sg:address":"Am Stadtgraben 88",
    "sg:city":"Bopfingen",
    "sg:phone":"+49 7362/8050",
    "sg:postcode":"73441",
    "sg:province":"Baden-W\u00fcrttemberg",
    "wof:name":"Drk-altenheim",
    "wof:placetype":"venue"
},
  "geometry": {"coordinates":[10.350948,48.856453],"type":"Point"}
}