{
  "type": "Feature",
  "properties": {
    "iso:country":"DE",
    "sg:address":"Jahnplatz 1",
    "sg:city":"Kerpen",
    "sg:phone":"+49 2237/58103",
    "sg:postcode":"50171",
    "sg:province":"Nordrhein-Westfalen",
    "wof:name":"Stadtarchiv",
    "wof:placetype":"venue"
},
  "geometry": {"coordinates":[6.691523,50.87315],"type":"Point"}
}