{
  "type": "Feature",
  "properties": {
    "iso:country":"DE",
    "sg:address":"Dorfstr. 67a",
    "sg:city":"Nossentiner H\u00fctte",
    "sg:phone":"+49 39927/70379",
    "sg:postcode":"17214",
    "sg:province":"Mecklenburg-Vorpommern",
    "wof:name":"Robert Vollmer",
    "wof:placetype":"venue"
},
  "geometry": {"coordinates":[12.42589,53.536041],"type":"Point"}
}