{
  "type": "Feature",
  "properties": {
    "iso:country":"DE",
    "sg:address":"Ellenbacher Str. 21",
    "sg:city":"F\u00fcrth",
    "sg:phone":"+49 6253/5540",
    "sg:postcode":"64658",
    "sg:province":"Hessen",
    "wof:name":"Adam Arnold",
    "wof:placetype":"venue"
},
  "geometry": {"coordinates":[8.7769899368,49.6515083313],"type":"Point"}
}