{
  "type": "Feature",
  "properties": {
    "iso:country":"DE",
    "sg:address":"Wittelsbacherstr.",
    "sg:city":"Bad Griesbach",
    "sg:phone":"+49 8532/2300",
    "sg:postcode":"94086",
    "sg:province":"Bayern",
    "wof:name":"Robert Krau\u00df Masseur",
    "wof:placetype":"venue"
},
  "geometry": {"coordinates":[13.193401,48.455795],"type":"Point"}
}