{
  "type": "Feature",
  "properties": {
    "iso:country":"DE",
    "sg:address":"Bahnhofstr. 3",
    "sg:city":"Selsingen",
    "sg:phone":"+49 4284/1456",
    "sg:postcode":"27446",
    "sg:province":"Niedersachsen",
    "wof:name":"Rolf Viehbrock E. K.",
    "wof:placetype":"venue"
},
  "geometry": {"coordinates":[9.2132148743,53.3721656799],"type":"Point"}
}