{
  "type": "Feature",
  "properties": {
    "iso:country":"DE",
    "sg:address":"Manstedtener Str. 55",
    "sg:city":"Pulheim",
    "sg:phone":"+49 2238/7115",
    "sg:postcode":"50259",
    "sg:province":"Nordrhein-Westfalen",
    "wof:name":"Hugo Schmitz",
    "wof:placetype":"venue"
},
  "geometry": {"coordinates":[6.77856,50.984531],"type":"Point"}
}