{
  "type": "Feature",
  "properties": {
    "iso:country":"DE",
    "sg:address":"Von-Eicken-Str. 14",
    "sg:city":"Hamburg",
    "sg:phone":"+49 40/565787",
    "sg:postcode":"22529",
    "sg:province":"Hamburg",
    "wof:name":"Zielke",
    "wof:placetype":"venue"
},
  "geometry": {"coordinates":[9.953411,53.587345],"type":"Point"}
}