{
  "type": "Feature",
  "properties": {
    "iso:country":"DE",
    "sg:address":"B\u00fcrvigstr. 2",
    "sg:city":"Bonn",
    "sg:phone":"+49 228/322620",
    "sg:postcode":"53177",
    "sg:province":"Nordrhein-Westfalen",
    "wof:name":"Hans Magewirth",
    "wof:placetype":"venue"
},
  "geometry": {"coordinates":[7.1576647758,50.6736450195],"type":"Point"}
}