{
  "type": "Feature",
  "properties": {
    "iso:country":"DE",
    "sg:address":"Gr\u00fcner Weg 2",
    "sg:city":"Ludwigsau",
    "sg:phone":"+49 6621/914815",
    "sg:postcode":"36251",
    "sg:province":"Hessen",
    "wof:name":"Edeltraud H\u00e4slein",
    "wof:placetype":"venue"
},
  "geometry": {"coordinates":[9.7658405304,50.9174766541],"type":"Point"}
}