{
  "type": "Feature",
  "properties": {
    "iso:country":"DE",
    "sg:address":"Rosenthaler Str. 51",
    "sg:city":"Berlin",
    "sg:phone":"+49 30/2827793",
    "sg:postcode":"10178",
    "sg:province":"Berlin",
    "wof:name":"Kulturhaus Mitte",
    "wof:placetype":"venue"
},
  "geometry": {"coordinates":[13.403785,52.525497],"type":"Point"}
}