{
  "type": "Feature",
  "properties": {
    "iso:country":"DE",
    "sg:address":"Wittenhorster Weg 18",
    "sg:city":"Rees",
    "sg:phone":"+49 2850/7750",
    "sg:postcode":"46459",
    "sg:province":"Nordrhein-Westfalen",
    "wof:name":"Leo Bossmann",
    "wof:placetype":"venue"
},
  "geometry": {"coordinates":[6.512905,51.770622],"type":"Point"}
}