{
  "type": "Feature",
  "properties": {
    "iso:country":"DE",
    "sg:address":"G\u00e4rtnerstr. 1",
    "sg:city":"Linsengericht",
    "sg:phone":"+49 6051/73234",
    "sg:postcode":"63589",
    "sg:province":"Hessen",
    "wof:name":"Gastst\u00e4tte Mathilde Johanns",
    "wof:placetype":"venue"
},
  "geometry": {"coordinates":[9.1943292618,50.1914825439],"type":"Point"}
}