{
  "type": "Feature",
  "properties": {
    "iso:country":"DE",
    "sg:address":"Erbprinzenstr. 20",
    "sg:city":"Karlsruhe",
    "sg:phone":"+49 721/24568",
    "sg:postcode":"76133",
    "sg:province":"Baden-W\u00fcrttemberg",
    "wof:name":"Teppich-carpet-tapis Gmbh",
    "wof:placetype":"venue"
},
  "geometry": {"coordinates":[8.3979635239,49.0087928772],"type":"Point"}
}