{
  "type": "Feature",
  "properties": {
    "iso:country":"DE",
    "sg:address":"Sudetenstr. 7Ot Schwoersheim",
    "sg:city":"Munningen",
    "sg:phone":"+49 9082/2702",
    "sg:postcode":"86754",
    "sg:province":"Bayern",
    "wof:name":"H & W Wohnbau Gmbh",
    "wof:placetype":"venue"
},
  "geometry": {"coordinates":[10.6036281586,48.9176101685],"type":"Point"}
}