{
  "type": "Feature",
  "properties": {
    "iso:country":"DE",
    "sg:address":"Preysingstr. 7",
    "sg:city":"Plattling",
    "sg:phone":"+49 9931/2818",
    "sg:postcode":"94447",
    "sg:province":"Bayern",
    "wof:name":"Ev. Luth. Pfarramt",
    "wof:placetype":"venue"
},
  "geometry": {"coordinates":[12.8694210052,48.7774200439],"type":"Point"}
}