{
  "type": "Feature",
  "properties": {
    "iso:country":"DE",
    "sg:address":"Karlstr. 84",
    "sg:city":"Reutlingen",
    "sg:phone":"+49 4971/211000",
    "sg:postcode":"72766",
    "sg:province":"Baden-W\u00fcrttemberg",
    "wof:name":"Deutsche Telekom Ag",
    "wof:placetype":"venue"
},
  "geometry": {"coordinates":[9.2199735641,48.5017433167],"type":"Point"}
}