{
  "type": "Feature",
  "properties": {
    "iso:country":"DE",
    "sg:address":"Moselstr. 16",
    "sg:city":"Maring-Noviand",
    "sg:phone":"+49 6535/532",
    "sg:postcode":"54484",
    "sg:province":"Rheinland-Pfalz",
    "wof:name":"H. Und P. B\u00f6linger Weinanbau",
    "wof:placetype":"venue"
},
  "geometry": {"coordinates":[7.0024628639,49.9248695374],"type":"Point"}
}