{
  "type": "Feature",
  "properties": {
    "iso:country":"DE",
    "sg:address":"Maybachstr. 15a",
    "sg:city":"Essen",
    "sg:phone":"+49 201/413320",
    "sg:postcode":"45133",
    "sg:province":"Nordrhein-Westfalen",
    "wof:name":"Erich Vom Endt Fotoarchiv",
    "wof:placetype":"venue"
},
  "geometry": {"coordinates":[6.9908599854,51.4068946838],"type":"Point"}
}