{
  "type": "Feature",
  "properties": {
    "iso:country":"DE",
    "sg:address":"Pr\u00fc\u00dfberg",
    "sg:city":"Michelau",
    "sg:phone":"+49 9382/1512",
    "sg:postcode":"97513",
    "sg:province":"Bayern",
    "wof:name":"Hubert Hauck Masseur",
    "wof:placetype":"venue"
},
  "geometry": {"coordinates":[10.50846,49.924816],"type":"Point"}
}