{
  "type": "Feature",
  "properties": {
    "iso:country":"DE",
    "sg:address":"Bischofszeller Str. 15",
    "sg:city":"Tuttlingen",
    "sg:phone":"+49 7462/1533",
    "sg:postcode":"78532",
    "sg:province":"Baden-W\u00fcrttemberg",
    "wof:name":"E. Schilling Chirug. Instrumente",
    "wof:placetype":"venue"
},
  "geometry": {"coordinates":[8.767726,47.958981],"type":"Point"}
}