{
  "type": "Feature",
  "properties": {
    "iso:country":"DE",
    "sg:address":"Leverner Str. 72",
    "sg:city":"Stemwede",
    "sg:phone":"+49 5745/2523",
    "sg:postcode":"32351",
    "sg:province":"Nordrhein-Westfalen",
    "wof:name":"Zimmermann Immobilienmakler",
    "wof:placetype":"venue"
},
  "geometry": {"coordinates":[8.466460228,52.3736381531],"type":"Point"}
}