{
  "type": "Feature",
  "properties": {
    "iso:country":"DE",
    "sg:address":"Koellestr. 31 A",
    "sg:city":"Karlsruhe",
    "sg:phone":"+49 4972/1575814",
    "sg:postcode":"76189",
    "sg:province":"Baden-W\u00fcrttemberg",
    "wof:name":"Wehling Schweisstechnik",
    "wof:placetype":"venue"
},
  "geometry": {"coordinates":[8.311011,49.012077],"type":"Point"}
}