{
  "type": "Feature",
  "properties": {
    "iso:country":"DE",
    "sg:address":"Laurentiusstr. 47 a",
    "sg:city":"K\u00f6nigswinter",
    "sg:phone":"+49 2223/26738",
    "sg:postcode":"53639",
    "sg:province":"Nordrhein-Westfalen",
    "wof:name":"Afb Stahl- Und Filterhandels Gmbh",
    "wof:placetype":"venue"
},
  "geometry": {"coordinates":[7.18676,50.703281],"type":"Point"}
}