{
  "type": "Feature",
  "properties": {
    "iso:country":"DE",
    "sg:address":"Poststr. 2",
    "sg:city":"Gummersbach",
    "sg:phone":"+49 2261/29030",
    "sg:postcode":"51643",
    "sg:province":"Nordrhein-Westfalen",
    "wof:name":"Dekra Automobil Gmbh",
    "wof:placetype":"venue"
},
  "geometry": {"coordinates":[7.5559568405,51.0233726501],"type":"Point"}
}