{
  "type": "Feature",
  "properties": {
    "iso:country":"DE",
    "sg:address":"Querstr. 7",
    "sg:city":"N\u00fcrnberg",
    "sg:phone":"+49 911/9955520",
    "sg:postcode":"90489",
    "sg:province":"Bayern",
    "wof:name":"Zeiser Generalunternehmen F\u00fcr Sanierung Und Schl\u00fcssel-",
    "wof:placetype":"venue"
},
  "geometry": {"coordinates":[11.096742,49.455479],"type":"Point"}
}