{
  "type": "Feature",
  "properties": {
    "iso:country":"DE",
    "sg:address":"Hengsbachstr. 14",
    "sg:city":"Siegen",
    "sg:phone":"+49 271/311672",
    "sg:postcode":"57080",
    "sg:province":"Nordrhein-Westfalen",
    "wof:name":"Robert Latsch",
    "wof:placetype":"venue"
},
  "geometry": {"coordinates":[8.0112304688,50.8481407166],"type":"Point"}
}