{
  "type": "Feature",
  "properties": {
    "iso:country":"DE",
    "sg:address":"Bad Birkenhofweg 21",
    "sg:city":"Barwedel",
    "sg:postcode":"38476",
    "sg:province":"Niedersachsen",
    "wof:name":"A. V\u00f6ltz",
    "wof:placetype":"venue"
},
  "geometry": {"coordinates":[10.7274055481,52.5354347229],"type":"Point"}
}