{
  "type": "Feature",
  "properties": {
    "iso:country":"DE",
    "sg:address":"An der Heide 7",
    "sg:city":"Schwarme",
    "sg:phone":"+49 4258/1340",
    "sg:postcode":"27327",
    "sg:province":"Niedersachsen",
    "wof:name":"Friedrich Laackmann",
    "wof:placetype":"venue"
},
  "geometry": {"coordinates":[9.033756,52.914333],"type":"Point"}
}