{
  "type": "Feature",
  "properties": {
    "iso:country":"DE",
    "sg:address":"Kolkstr. 2",
    "sg:city":"Diepholz",
    "sg:phone":"+49 5441/6655",
    "sg:postcode":"49356",
    "sg:province":"Niedersachsen",
    "wof:name":"Leder-chic Monika Harbeck",
    "wof:placetype":"venue"
},
  "geometry": {"coordinates":[8.369827,52.606945],"type":"Point"}
}