{
  "type": "Feature",
  "properties": {
    "iso:country":"DE",
    "sg:address":"Christoph-Scheiner-Str. 34",
    "sg:city":"Mindelheim",
    "sg:phone":"+49 8261/8438",
    "sg:postcode":"87719",
    "sg:province":"Bayern",
    "wof:name":"Marei Mertens",
    "wof:placetype":"venue"
},
  "geometry": {"coordinates":[10.496485,48.053406],"type":"Point"}
}