{
  "type": "Feature",
  "properties": {
    "iso:country":"DE",
    "sg:address":"Magdeburger Str. 10",
    "sg:city":"Sangerhausen",
    "sg:phone":"+49 3464/572806",
    "sg:postcode":"06526",
    "sg:province":"Sachsen-Anhalt",
    "wof:name":"Sangerh\u00e4user Druckerei Gmbh",
    "wof:placetype":"venue"
},
  "geometry": {"coordinates":[11.299791,51.474606],"type":"Point"}
}