{
  "type": "Feature",
  "properties": {
    "iso:country":"DE",
    "sg:address":"Lennestr. 4",
    "sg:city":"Schwerin",
    "sg:phone":"+49 385/560952",
    "sg:postcode":"19061",
    "sg:province":"Mecklenburg-Vorpommern",
    "wof:name":"Kochs Bier- Und Weinstuben",
    "wof:placetype":"venue"
},
  "geometry": {"coordinates":[11.4187917709,53.6156005859],"type":"Point"}
}