{
  "type": "Feature",
  "properties": {
    "iso:country":"DE",
    "sg:address":"Busonistr. 2",
    "sg:city":"Berlin",
    "sg:phone":"+49 30/94632267",
    "sg:postcode":"13125",
    "sg:province":"Berlin",
    "wof:name":"Christian Grieger",
    "wof:placetype":"venue"
},
  "geometry": {"coordinates":[13.486663,52.622505],"type":"Point"}
}