{
  "type": "Feature",
  "properties": {
    "iso:country":"DE",
    "sg:address":"Th\u00fcringer Str. 10",
    "sg:city":"Gera",
    "sg:phone":"+49 365/414010",
    "sg:postcode":"07552",
    "sg:province":"Th\u00fcringen",
    "wof:name":"Manfred Becker",
    "wof:placetype":"venue"
},
  "geometry": {"coordinates":[12.083655,50.905025],"type":"Point"}
}