{
  "type": "Feature",
  "properties": {
    "iso:country":"DE",
    "sg:address":"Zastrowstr. 38",
    "sg:city":"Kiel",
    "sg:phone":"+49 431/16448",
    "sg:postcode":"24114",
    "sg:province":"Schleswig-Holstein",
    "wof:name":"Reinhard S\u00fcdel",
    "wof:placetype":"venue"
},
  "geometry": {"coordinates":[10.115541,54.320385],"type":"Point"}
}