{
  "type": "Feature",
  "properties": {
    "iso:country":"DE",
    "sg:address":"Neustadtstra\u00dfe 6",
    "sg:city":"Nordhausen",
    "sg:phone":"+49 3631/902385",
    "sg:postcode":"99734",
    "sg:province":"Th\u00fcringen",
    "wof:name":"Euro-domo Gmbh",
    "wof:placetype":"venue"
},
  "geometry": {"coordinates":[10.7913970947,51.4989051819],"type":"Point"}
}