{
  "type": "Feature",
  "properties": {
    "iso:country":"DE",
    "sg:address":"Weiherweg 68a",
    "sg:city":"Gr\u00f6benzell",
    "sg:phone":"+49 8142/540505",
    "sg:postcode":"82194",
    "sg:province":"Bayern",
    "wof:name":"G\u00fcnter Gutewort Ingenieur",
    "wof:placetype":"venue"
},
  "geometry": {"coordinates":[11.3847303391,48.2043991089],"type":"Point"}
}