{
  "type": "Feature",
  "properties": {
    "iso:country":"DE",
    "sg:address":"Orrer Str. 8",
    "sg:city":"Pulheim",
    "sg:phone":"+49 2238/51001",
    "sg:postcode":"50259",
    "sg:province":"Nordrhein-Westfalen",
    "wof:name":"Dr. Paulick Und Hahn Rechtsanw\u00e4lte",
    "wof:placetype":"venue"
},
  "geometry": {"coordinates":[6.8067140579,50.9973335266],"type":"Point"}
}