{
  "type": "Feature",
  "properties": {
    "iso:country":"DE",
    "sg:address":"Siedlerweg 2",
    "sg:city":"Kalbach",
    "sg:phone":"+49 9742/1255",
    "sg:postcode":"36148",
    "sg:province":"Hessen",
    "wof:name":"Andreas B\u00f6hm",
    "wof:placetype":"venue"
},
  "geometry": {"coordinates":[9.670459,50.406963],"type":"Point"}
}