{
  "type": "Feature",
  "properties": {
    "iso:country":"DE",
    "sg:address":"Siebenlindenstr. 42",
    "sg:city":"Rottenburg",
    "sg:phone":"+49 7472/98700",
    "sg:postcode":"72108",
    "sg:province":"Baden-W\u00fcrttemberg",
    "wof:name":"Omnibus Sailer Gmbh",
    "wof:placetype":"venue"
},
  "geometry": {"coordinates":[8.9535388947,48.4745140076],"type":"Point"}
}