{
  "type": "Feature",
  "properties": {
    "iso:country":"DE",
    "sg:address":"Schlo\u00dfstr. 22a",
    "sg:city":"Edesheim",
    "sg:phone":"+49 6323/7771",
    "sg:postcode":"67483",
    "sg:province":"Rheinland-Pfalz",
    "wof:name":"Gerhard B\u00f6hme",
    "wof:placetype":"venue"
},
  "geometry": {"coordinates":[8.1319103241,49.2652587891],"type":"Point"}
}