{
  "type": "Feature",
  "properties": {
    "iso:country":"DE",
    "sg:address":"Bahnhofstr. 46",
    "sg:city":"Asperg",
    "sg:phone":"+49 7141/62164",
    "sg:postcode":"71679",
    "sg:province":"Baden-W\u00fcrttemberg",
    "wof:name":"Ernst Kie\u00df & Sohn",
    "wof:placetype":"venue"
},
  "geometry": {"coordinates":[9.1412906647,48.9064559937],"type":"Point"}
}