{
  "type": "Feature",
  "properties": {
    "iso:country":"DE",
    "sg:address":"Goethering 23-29 POSTFACH 3629",
    "sg:city":"Osnabr\u00fcck",
    "sg:phone":"+49 4954/131601",
    "sg:postcode":"49026",
    "sg:province":"Niedersachsen",
    "wof:name":"Rwe Net Ag",
    "wof:placetype":"venue"
},
  "geometry": {"coordinates":[8.054906,52.274151],"type":"Point"}
}