{
  "type": "Feature",
  "properties": {
    "iso:country":"DE",
    "sg:address":"Hauptstr. 10",
    "sg:city":"Otterberg",
    "sg:phone":"+49 6301/9778",
    "sg:postcode":"67697",
    "sg:province":"Rheinland-Pfalz",
    "wof:name":"K. Weber",
    "wof:placetype":"venue"
},
  "geometry": {"coordinates":[7.7721772194,49.4987640381],"type":"Point"}
}