{
  "type": "Feature",
  "properties": {
    "iso:country":"DE",
    "sg:address":"Clemensstr. 10",
    "sg:city":"Bonn",
    "sg:phone":"+49 228/475420",
    "sg:postcode":"53225",
    "sg:province":"Nordrhein-Westfalen",
    "wof:name":"G\u00fcnther Schaal",
    "wof:placetype":"venue"
},
  "geometry": {"coordinates":[7.1175107956,50.7481422424],"type":"Point"}
}