{
  "type": "Feature",
  "properties": {
    "iso:country":"DE",
    "sg:address":"Kleine Schulstr. 12",
    "sg:city":"Burg",
    "sg:phone":"+49 4825/2279",
    "sg:postcode":"25712",
    "sg:province":"Schleswig-Holstein",
    "wof:name":"Schramm-verlag",
    "wof:placetype":"venue"
},
  "geometry": {"coordinates":[9.2636451721,53.9957504272],"type":"Point"}
}