{
  "type": "Feature",
  "properties": {
    "iso:country":"DE",
    "sg:address":"Weidenweg 11",
    "sg:city":"Klettbach",
    "sg:phone":"+49 361/4232899",
    "sg:postcode":"99102",
    "sg:province":"Th\u00fcringen",
    "wof:name":"Etap Hotel",
    "wof:placetype":"venue"
},
  "geometry": {"coordinates":[11.1513299942,50.9106292725],"type":"Point"}
}