{
  "type": "Feature",
  "properties": {
    "iso:country":"DE",
    "sg:address":"Stettiner Ring 28",
    "sg:city":"Albstadt",
    "sg:phone":"+49 7431/8888",
    "sg:postcode":"72458",
    "sg:province":"Baden-W\u00fcrttemberg",
    "wof:name":"F. Und H. Binder",
    "wof:placetype":"venue"
},
  "geometry": {"coordinates":[8.98292,48.20927],"type":"Point"}
}