{
  "type": "Feature",
  "properties": {
    "iso:country":"DE",
    "sg:address":"Rodener Str. 5",
    "sg:city":"Marktheidenfeld",
    "sg:phone":"+49 9391/2566",
    "sg:postcode":"97828",
    "sg:province":"Bayern",
    "wof:name":"Paul Und Irene Schmitt",
    "wof:placetype":"venue"
},
  "geometry": {"coordinates":[9.603212,49.8876],"type":"Point"}
}