{
  "type": "Feature",
  "properties": {
    "iso:country":"DE",
    "sg:address":"Von-dem-Bussche-M\u00fcnch-Str. 9",
    "sg:city":"Espelkamp",
    "sg:phone":"+49 5772/3452",
    "sg:postcode":"32339",
    "sg:province":"Nordrhein-Westfalen",
    "wof:name":"Polsterm\u00f6bel Hermann Peper Gmbh & Co.",
    "wof:placetype":"venue"
},
  "geometry": {"coordinates":[8.6226949692,52.3912811279],"type":"Point"}
}