{
  "type": "Feature",
  "properties": {
    "iso:country":"DE",
    "sg:address":"Calauer Str. 1",
    "sg:city":"Sa\u00dfleben",
    "sg:phone":"+49 3541/801245",
    "sg:postcode":"03205",
    "sg:province":"Brandenburg",
    "wof:name":"Kaltschmidt",
    "wof:placetype":"venue"
},
  "geometry": {"coordinates":[13.9825315475,51.7577514648],"type":"Point"}
}