{
  "type": "Feature",
  "properties": {
    "iso:country":"DE",
    "sg:address":"Heinrich-Hertz-Str. 3",
    "sg:city":"Unna",
    "sg:postcode":"59423",
    "sg:province":"Nordrhein-Westfalen",
    "wof:name":"Agentur Sch\u00f6nfeld Gmbh",
    "wof:placetype":"venue"
},
  "geometry": {"coordinates":[7.726858139,51.5353736877],"type":"Point"}
}