{
  "type": "Feature",
  "properties": {
    "iso:country":"DE",
    "sg:address":"Sudetenstr. 2",
    "sg:city":"Wilhermsdorf",
    "sg:phone":"+49 9102/640",
    "sg:postcode":"91452",
    "sg:province":"Bayern",
    "wof:name":"Egon Lausmann",
    "wof:placetype":"venue"
},
  "geometry": {"coordinates":[10.718635,49.484783],"type":"Point"}
}