{
  "type": "Feature",
  "properties": {
    "iso:country":"DE",
    "sg:address":"Holzhausen 4",
    "sg:city":"Beckeln",
    "sg:phone":"+49 4244/457",
    "sg:postcode":"27243",
    "sg:province":"Niedersachsen",
    "wof:name":"Hermann Bruns",
    "wof:placetype":"venue"
},
  "geometry": {"coordinates":[8.607798,52.889614],"type":"Point"}
}