{
  "type": "Feature",
  "properties": {
    "iso:country":"DE",
    "sg:address":"R\u00f6merplatz 2",
    "sg:city":"Bonn",
    "sg:phone":"+49 228/351438",
    "sg:postcode":"53173",
    "sg:province":"Nordrhein-Westfalen",
    "wof:name":"Nazif Kaya",
    "wof:placetype":"venue"
},
  "geometry": {"coordinates":[7.1694459915,50.6845169067],"type":"Point"}
}