{
  "type": "Feature",
  "properties": {
    "iso:country":"DE",
    "sg:address":"Friedrichstr. 12",
    "sg:city":"Lahr",
    "sg:phone":"+49 7821/39696",
    "sg:postcode":"77933",
    "sg:province":"Baden-W\u00fcrttemberg",
    "wof:name":"H. Sauer",
    "wof:placetype":"venue"
},
  "geometry": {"coordinates":[7.8738908768,48.3417816162],"type":"Point"}
}