{
  "type": "Feature",
  "properties": {
    "iso:country":"DE",
    "sg:address":"Am Bahnhof 15",
    "sg:city":"Marktleuthen",
    "sg:phone":"+49 9285/261",
    "sg:postcode":"95168",
    "sg:province":"Bayern",
    "wof:name":"Farbwerk Marktleuthen Gebhardt Gmbh & Co. Kg",
    "wof:placetype":"venue"
},
  "geometry": {"coordinates":[12.0138950348,50.1346092224],"type":"Point"}
}