{
  "type": "Feature",
  "properties": {
    "iso:country":"DE",
    "sg:address":"Carl-Schmincke-Str. 54",
    "sg:city":"Leonberg",
    "sg:phone":"+49 7152/44570",
    "sg:postcode":"71229",
    "sg:province":"Baden-W\u00fcrttemberg",
    "wof:name":"H. Kibellus",
    "wof:placetype":"venue"
},
  "geometry": {"coordinates":[9.005851,48.788963],"type":"Point"}
}