{
  "type": "Feature",
  "properties": {
    "iso:country":"DE",
    "sg:address":"D\u00fcrener Str. 5",
    "sg:city":"J\u00fclich",
    "sg:phone":"+49 2461/53015",
    "sg:postcode":"52428",
    "sg:province":"Nordrhein-Westfalen",
    "wof:name":"Leuffer Kg",
    "wof:placetype":"venue"
},
  "geometry": {"coordinates":[6.3697490692,50.9193649292],"type":"Point"}
}