{
  "type": "Feature",
  "properties": {
    "iso:country":"DE",
    "sg:address":"In der Pfaffengewann 12",
    "sg:city":"Bingen",
    "sg:postcode":"55411",
    "sg:province":"Rheinland-Pfalz",
    "wof:name":"Fwt Gmbh",
    "wof:placetype":"venue"
},
  "geometry": {"coordinates":[7.9189248085,49.9457168579],"type":"Point"}
}