{
  "type": "Feature",
  "properties": {
    "iso:country":"DE",
    "sg:address":"Korbacher Str. 49",
    "sg:city":"Schauenburg",
    "sg:phone":"+49 5601/1345",
    "sg:postcode":"34270",
    "sg:province":"Hessen",
    "wof:name":"L. Hoja",
    "wof:placetype":"venue"
},
  "geometry": {"coordinates":[9.375515,51.272911],"type":"Point"}
}