{
  "type": "Feature",
  "properties": {
    "iso:country":"DE",
    "sg:address":"Neustr. 29",
    "sg:city":"Bad H\u00f6nningen",
    "sg:phone":"+49 2635/2391",
    "sg:postcode":"53557",
    "sg:province":"Rheinland-Pfalz",
    "wof:name":"Hotel Lindenwirtin",
    "wof:placetype":"venue"
},
  "geometry": {"coordinates":[7.3076510429,50.5158920288],"type":"Point"}
}