{
  "type": "Feature",
  "properties": {
    "iso:country":"DE",
    "sg:address":"Urbanstr. 3",
    "sg:city":"M\u00fcnster",
    "sg:phone":"+49 251/46777",
    "sg:postcode":"48143",
    "sg:province":"Nordrhein-Westfalen",
    "wof:name":"Berkenheide Und Knecht Rechtsanw\u00e4lte Und Notare",
    "wof:placetype":"venue"
},
  "geometry": {"coordinates":[7.6333360672,51.9585838318],"type":"Point"}
}