{
  "type": "Feature",
  "properties": {
    "iso:country":"DE",
    "sg:address":"Georg-Gleistein-Str. 108",
    "sg:city":"Bremen",
    "sg:phone":"+49 421/661301",
    "sg:postcode":"28757",
    "sg:province":"Bremen",
    "wof:name":"Radio G\u00fcnter Sumpf Inh. R\u00fcdiger Ratzmann",
    "wof:placetype":"venue"
},
  "geometry": {"coordinates":[8.6191797256,53.1837844849],"type":"Point"}
}