{
  "type": "Feature",
  "properties": {
    "iso:country":"DE",
    "sg:address":"Sassenfeld 174",
    "sg:city":"Nettetal",
    "sg:phone":"+49 2153/4412",
    "sg:postcode":"41334",
    "sg:province":"Nordrhein-Westfalen",
    "wof:name":"E. Komainda",
    "wof:placetype":"venue"
},
  "geometry": {"coordinates":[6.248593,51.319397],"type":"Point"}
}