{
  "type": "Feature",
  "properties": {
    "iso:country":"DE",
    "sg:address":"Weberstr 17",
    "sg:city":"Mainz",
    "sg:phone":"+49 6131/801230",
    "sg:postcode":"55130",
    "sg:province":"Rheinland-Pfalz",
    "wof:name":"2mb Gmbh",
    "wof:placetype":"venue"
},
  "geometry": {"coordinates":[8.2875127792,49.9756546021],"type":"Point"}
}