{
  "type": "Feature",
  "properties": {
    "iso:country":"DE",
    "sg:address":"Fierlbach 18",
    "sg:city":"Oberschneiding",
    "sg:phone":"+49 9426/1424",
    "sg:postcode":"94363",
    "sg:province":"Bayern",
    "wof:name":"L. Anzinger",
    "wof:placetype":"venue"
},
  "geometry": {"coordinates":[12.691369,48.788677],"type":"Point"}
}