{
  "type": "Feature",
  "properties": {
    "iso:country":"DE",
    "sg:address":"Sch\u00fctzenstr. 11",
    "sg:city":"Cham",
    "sg:phone":"+49 9971/2667",
    "sg:postcode":"93413",
    "sg:province":"Bayern",
    "wof:name":"Max Bruckbauer",
    "wof:placetype":"venue"
},
  "geometry": {"coordinates":[12.6594982147,49.2194213867],"type":"Point"}
}