{
  "type": "Feature",
  "properties": {
    "iso:country":"DE",
    "sg:address":"Dorstener Str. 359",
    "sg:city":"Bochum",
    "sg:phone":"+49 234/9579506",
    "sg:postcode":"44809",
    "sg:province":"Nordrhein-Westfalen",
    "wof:name":"Gabriele Brauer",
    "wof:placetype":"venue"
},
  "geometry": {"coordinates":[7.1887378693,51.5027923584],"type":"Point"}
}