{
  "type": "Feature",
  "properties": {
    "iso:country":"DE",
    "sg:address":"Sch\u00f6nholthauser Weg 12",
    "sg:city":"Finnentrop",
    "sg:phone":"+49 2721/7450",
    "sg:postcode":"57413",
    "sg:province":"Nordrhein-Westfalen",
    "wof:name":"Ferdinand Wiethoff Architekt",
    "wof:placetype":"venue"
},
  "geometry": {"coordinates":[7.973941,51.182304],"type":"Point"}
}