{
  "type": "Feature",
  "properties": {
    "iso:country":"DE",
    "sg:address":"Servatiusstr. 17",
    "sg:city":"Erkelenz",
    "sg:phone":"+49 2431/2304",
    "sg:postcode":"41812",
    "sg:province":"Nordrhein-Westfalen",
    "wof:name":"Kath. Pfarramt St. Servatius",
    "wof:placetype":"venue"
},
  "geometry": {"coordinates":[6.3482398987,51.0610351562],"type":"Point"}
}