{
  "type": "Feature",
  "properties": {
    "iso:country":"DE",
    "sg:address":"Cecilienstr. 27",
    "sg:city":"Saarbr\u00fccken",
    "sg:postcode":"66111",
    "sg:province":"Saarland",
    "wof:name":"Voila Naturtextilien Ohg",
    "wof:placetype":"venue"
},
  "geometry": {"coordinates":[6.9994821548,49.23620224],"type":"Point"}
}