{
  "type": "Feature",
  "properties": {
    "iso:country":"DE",
    "sg:address":"M\u00fchlenstr. 136",
    "sg:city":"Delmenhorst",
    "sg:phone":"+49 4221/13461",
    "sg:postcode":"27753",
    "sg:province":"Niedersachsen",
    "wof:name":"P. Tiefuhr Gmbh",
    "wof:placetype":"venue"
},
  "geometry": {"coordinates":[8.624179,53.052929],"type":"Point"}
}