{
  "type": "Feature",
  "properties": {
    "iso:country":"DE",
    "sg:address":"Malvenweg 11",
    "sg:city":"Kirchheim",
    "sg:postcode":"85551",
    "sg:province":"Bayern",
    "wof:name":"Ceg Bautr\u00e4ger Gmbh",
    "wof:placetype":"venue"
},
  "geometry": {"coordinates":[11.758503,48.169418],"type":"Point"}
}