{
  "type": "Feature",
  "properties": {
    "iso:country":"DE",
    "sg:address":"Flachsbleiche 12",
    "sg:city":"Erkelenz",
    "sg:phone":"+49 2431/3435",
    "sg:postcode":"41812",
    "sg:province":"Nordrhein-Westfalen",
    "wof:name":"Wolfgang Heinzel",
    "wof:placetype":"venue"
},
  "geometry": {"coordinates":[6.3092050552,51.075176239],"type":"Point"}
}