{
  "type": "Feature",
  "properties": {
    "iso:country":"DE",
    "sg:address":"Hauptstr. 16",
    "sg:city":"Leuthen",
    "sg:phone":"+49 35602/745",
    "sg:postcode":"03058",
    "sg:province":"Brandenburg",
    "wof:name":"Hans-g\u00fcnter Kirchhoff",
    "wof:placetype":"venue"
},
  "geometry": {"coordinates":[14.246757,51.696232],"type":"Point"}
}