{
  "type": "Feature",
  "properties": {
    "iso:country":"DE",
    "sg:address":"Br\u00fchl 13",
    "sg:city":"Hildesheim",
    "sg:phone":"+49 5121/38549",
    "sg:postcode":"31134",
    "sg:province":"Niedersachsen",
    "wof:name":"Manfred Szczesniak",
    "wof:placetype":"venue"
},
  "geometry": {"coordinates":[9.950551033,52.1475563049],"type":"Point"}
}