{
  "type": "Feature",
  "properties": {
    "iso:country":"DE",
    "sg:address":"K\u00fchnh\u00e4user Str. 214 a",
    "sg:city":"Mittelhausen",
    "sg:postcode":"99195",
    "sg:province":"Th\u00fcringen",
    "wof:name":"Tas-th\u00fcrin As Gmbh",
    "wof:placetype":"venue"
},
  "geometry": {"coordinates":[11.000413,51.03994],"type":"Point"}
}