{
  "type": "Feature",
  "properties": {
    "iso:country":"DE",
    "sg:address":"Emanuel-Merck-Str. 1 - 3",
    "sg:city":"Gernsheim",
    "sg:phone":"+49 6258/52368",
    "sg:postcode":"64579",
    "sg:province":"Hessen",
    "wof:name":"Shammout Establishment For Tyres",
    "wof:placetype":"venue"
},
  "geometry": {"coordinates":[8.486534,49.765404],"type":"Point"}
}