{
  "type": "Feature",
  "properties": {
    "iso:country":"DE",
    "sg:address":"Maarstr. 213",
    "sg:city":"Bonn",
    "sg:phone":"+49 228/977470",
    "sg:postcode":"53227",
    "sg:province":"Nordrhein-Westfalen",
    "wof:name":"Astroforce Verlag Gmbh",
    "wof:placetype":"venue"
},
  "geometry": {"coordinates":[7.1443099976,50.739818573],"type":"Point"}
}