{
  "type": "Feature",
  "properties": {
    "iso:country":"DE",
    "sg:address":"P\u00f6tenitzer Weg 2",
    "sg:city":"L\u00fcbeck",
    "sg:phone":"+49 4502/5501",
    "sg:postcode":"23570",
    "sg:province":"Schleswig-Holstein",
    "wof:name":"Horst Hagen",
    "wof:placetype":"venue"
},
  "geometry": {"coordinates":[10.8810939789,53.9532699585],"type":"Point"}
}