{
  "type": "Feature",
  "properties": {
    "iso:country":"DE",
    "sg:address":"Arnheiter Str. 8",
    "sg:city":"Breuberg",
    "sg:phone":"+49 6165/840",
    "sg:postcode":"64747",
    "sg:province":"Hessen",
    "wof:name":"Georg B. Saul",
    "wof:placetype":"venue"
},
  "geometry": {"coordinates":[9.05204,49.824928],"type":"Point"}
}