{
  "type": "Feature",
  "properties": {
    "iso:country":"DE",
    "sg:address":"Richard-Wagner-Str. 16",
    "sg:city":"Kuchen",
    "sg:phone":"+49 7331/81260",
    "sg:postcode":"73329",
    "sg:province":"Baden-W\u00fcrttemberg",
    "wof:name":"R. Pressmar Und E. Eisele",
    "wof:placetype":"venue"
},
  "geometry": {"coordinates":[9.795731,48.639587],"type":"Point"}
}