{
  "type": "Feature",
  "properties": {
    "iso:country":"DE",
    "sg:address":"Im Sabel 14",
    "sg:city":"Trier",
    "sg:postcode":"54294",
    "sg:province":"Rheinland-Pfalz",
    "wof:name":"Marketing-service-becker",
    "wof:placetype":"venue"
},
  "geometry": {"coordinates":[6.6278090477,49.7631454468],"type":"Point"}
}