{
  "type": "Feature",
  "properties": {
    "iso:country":"DE",
    "sg:address":"Adolf-G\u00e4nshirt-Str. 1",
    "sg:city":"Friesenheim",
    "sg:phone":"+49 7821/997603",
    "sg:postcode":"77948",
    "sg:province":"Baden-W\u00fcrttemberg",
    "wof:name":"S. Klaus",
    "wof:placetype":"venue"
},
  "geometry": {"coordinates":[7.8744311333,48.3700485229],"type":"Point"}
}