{
  "type": "Feature",
  "properties": {
    "iso:country":"DE",
    "sg:address":"Bahnhofstr. 87",
    "sg:city":"Herne",
    "sg:phone":"+49 2323/910050",
    "sg:postcode":"44623",
    "sg:province":"Nordrhein-Westfalen",
    "wof:name":"Immofina Inh. Neyazi Deveci",
    "wof:placetype":"venue"
},
  "geometry": {"coordinates":[7.2197232246,51.5434417725],"type":"Point"}
}