{
  "type": "Feature",
  "properties": {
    "iso:country":"DE",
    "sg:address":"Am Kirchberg 9",
    "sg:city":"Gro\u00dfsolt",
    "sg:phone":"+49 4602/251",
    "sg:postcode":"24991",
    "sg:province":"Schleswig-Holstein",
    "wof:name":"M. Und G. Appel",
    "wof:placetype":"venue"
},
  "geometry": {"coordinates":[9.5139951706,54.6993255615],"type":"Point"}
}