{
  "type": "Feature",
  "properties": {
    "iso:country":"DE",
    "sg:address":"flerrentwiete 5",
    "sg:city":"hamburg",
    "sg:phone":"+49 40/81990868",
    "sg:postcode":"22559",
    "sg:province":"Hamburg",
    "wof:name":"Ikett Ab",
    "wof:placetype":"venue"
},
  "geometry": {"coordinates":[9.7520151138,53.5831565857],"type":"Point"}
}