{
  "type": "Feature",
  "properties": {
    "iso:country":"DE",
    "sg:address":"Gerichtsgasse 1",
    "sg:city":"Zierenberg",
    "sg:phone":"+49 5606/8563",
    "sg:postcode":"34289",
    "sg:province":"Hessen",
    "wof:name":"Julius Dittrich",
    "wof:placetype":"venue"
},
  "geometry": {"coordinates":[9.3009147644,51.3690986633],"type":"Point"}
}