{
  "type": "Feature",
  "properties": {
    "iso:country":"DE",
    "sg:address":"Zieglerstr. 1",
    "sg:city":"Wiesbaden",
    "sg:phone":"+49 611/5001140",
    "sg:postcode":"65191",
    "sg:province":"Hessen",
    "wof:name":"Hotel Garni Bierstadter Hof",
    "wof:placetype":"venue"
},
  "geometry": {"coordinates":[8.2816095352,50.0860099792],"type":"Point"}
}