{
  "type": "Feature",
  "properties": {
    "iso:country":"DE",
    "sg:address":"Am Au\u00dfenhafen 1-7",
    "sg:city":"Duisburg",
    "sg:phone":"+49 203/315035",
    "sg:postcode":"47059",
    "sg:province":"Nordrhein-Westfalen",
    "wof:name":"Roters & Buddenberg Gmbh",
    "wof:placetype":"venue"
},
  "geometry": {"coordinates":[6.74839,51.432308],"type":"Point"}
}