{
  "type": "Feature",
  "properties": {
    "iso:country":"DE",
    "sg:address":"Rosenheimer Stra\u00dfe 145 f",
    "sg:city":"M\u00fcnchen",
    "sg:phone":"+49 89",
    "sg:postcode":"81671",
    "sg:province":"Bayern",
    "wof:name":"Fey & Tescari",
    "wof:placetype":"venue"
},
  "geometry": {"coordinates":[11.61152,48.123199],"type":"Point"}
}