{
  "type": "Feature",
  "properties": {
    "iso:country":"DE",
    "sg:address":"Wei\u00dfer Str. 22",
    "sg:city":"K\u00f6ln",
    "sg:phone":"+49 221/394827",
    "sg:postcode":"50996",
    "sg:province":"Nordrhein-Westfalen",
    "wof:name":"S. Frese Massagepraxis",
    "wof:placetype":"venue"
},
  "geometry": {"coordinates":[6.999383,50.889225],"type":"Point"}
}