{
  "type": "Feature",
  "properties": {
    "iso:country":"DE",
    "sg:address":"Friedberger Str. 11",
    "sg:city":"Niddatal",
    "sg:phone":"+49 6034/3813",
    "sg:postcode":"61194",
    "sg:province":"Hessen",
    "wof:name":"Restaurant Zum Berghof",
    "wof:placetype":"venue"
},
  "geometry": {"coordinates":[8.7974462509,50.2821922302],"type":"Point"}
}