{
  "type": "Feature",
  "properties": {
    "iso:country":"DE",
    "sg:address":"Ganghoferstr. 96",
    "sg:city":"M\u00fcnchen",
    "sg:phone":"+49 89/768779",
    "sg:postcode":"81373",
    "sg:province":"Bayern",
    "wof:name":"J\u00fcrgen Elberskirch",
    "wof:placetype":"venue"
},
  "geometry": {"coordinates":[11.538861,48.126537],"type":"Point"}
}