{
  "type": "Feature",
  "properties": {
    "iso:country":"DE",
    "sg:address":"Hauptstr. 106",
    "sg:city":"Erlangen",
    "sg:phone":"+49 9131/8810",
    "sg:postcode":"91054",
    "sg:province":"Bayern",
    "wof:name":"Bichelmeier Und Bichelmeier Rechtsanw\u00e4lte",
    "wof:placetype":"venue"
},
  "geometry": {"coordinates":[11.0038604736,49.6024665833],"type":"Point"}
}