{
  "type": "Feature",
  "properties": {
    "iso:country":"DE",
    "sg:address":"Heubergstr. 5",
    "sg:city":"Tuningen",
    "sg:phone":"+49 4968/945930",
    "sg:postcode":"78609",
    "sg:province":"Baden-W\u00fcrttemberg",
    "wof:name":"Friatec Ag Bereich Armaturen",
    "wof:placetype":"venue"
},
  "geometry": {"coordinates":[7.16026,49.283619],"type":"Point"}
}