{
  "type": "Feature",
  "properties": {
    "iso:country":"DE",
    "sg:address":"Birkenweg 16",
    "sg:city":"H\u00f6xter",
    "sg:phone":"+49 5271/7920",
    "sg:postcode":"37671",
    "sg:province":"Nordrhein-Westfalen",
    "wof:name":"Winfried Tonn Ingenieur",
    "wof:placetype":"venue"
},
  "geometry": {"coordinates":[9.36992836,51.7817230225],"type":"Point"}
}