{
  "type": "Feature",
  "properties": {
    "iso:country":"DE",
    "sg:address":"Pinneberger Str. 133",
    "sg:city":"Ellerbek",
    "sg:phone":"+49 4941/0185590",
    "sg:postcode":"25474",
    "sg:province":"Schleswig-Holstein",
    "wof:name":"Agr Graf & Reimers Gmbh",
    "wof:placetype":"venue"
},
  "geometry": {"coordinates":[9.876219,53.646912],"type":"Point"}
}