{
  "type": "Feature",
  "properties": {
    "iso:country":"DE",
    "sg:address":"Bahnhofstr. 50",
    "sg:city":"Buchloe",
    "sg:phone":"+49 8241/90070",
    "sg:postcode":"86807",
    "sg:province":"Bayern",
    "wof:name":"J. Ihl",
    "wof:placetype":"venue"
},
  "geometry": {"coordinates":[10.7181797028,48.034236908],"type":"Point"}
}