{
  "type": "Feature",
  "properties": {
    "iso:country":"DE",
    "sg:address":"Seelach 25",
    "sg:city":"Kronach",
    "sg:phone":"+49 9261/20187",
    "sg:postcode":"96317",
    "sg:province":"Bayern",
    "wof:name":"Josef Ammer",
    "wof:placetype":"venue"
},
  "geometry": {"coordinates":[11.29885,50.248131],"type":"Point"}
}