{
  "type": "Feature",
  "properties": {
    "iso:country":"DE",
    "sg:address":"Hauptstr. 23",
    "sg:city":"Bad Essen",
    "sg:phone":"+49 5472/7828",
    "sg:postcode":"49152",
    "sg:province":"Niedersachsen",
    "wof:name":"Heinrich Lohmeyer",
    "wof:placetype":"venue"
},
  "geometry": {"coordinates":[8.404989,52.317101],"type":"Point"}
}