{
  "type": "Feature",
  "properties": {
    "iso:country":"DE",
    "sg:address":"Husarenstr. 27",
    "sg:city":"Hannover",
    "sg:phone":"+49 511/629421",
    "sg:postcode":"30163",
    "sg:province":"Niedersachsen",
    "wof:name":"Restaurant La Taberna",
    "wof:placetype":"venue"
},
  "geometry": {"coordinates":[9.7378530502,52.3929519653],"type":"Point"}
}