{
  "type": "Feature",
  "properties": {
    "iso:country":"DE",
    "sg:address":"Schlagweg 12",
    "sg:city":"M\u00fcnchen",
    "sg:phone":"+49 89/883695",
    "sg:postcode":"81241",
    "sg:province":"Bayern",
    "wof:name":"Sast Inh. Beatrice Castello",
    "wof:placetype":"venue"
},
  "geometry": {"coordinates":[11.4615659714,48.1344947815],"type":"Point"}
}