{
  "type": "Feature",
  "properties": {
    "iso:country":"DE",
    "sg:address":"Eitswiesenstr. 1",
    "sg:city":"Heiningen",
    "sg:phone":"+49 4971/6143009",
    "sg:postcode":"73092",
    "sg:province":"Baden-W\u00fcrttemberg",
    "wof:name":"Sima Maschinen Gmbh",
    "wof:placetype":"venue"
},
  "geometry": {"coordinates":[9.645615,48.654484],"type":"Point"}
}