{
  "type": "Feature",
  "properties": {
    "iso:country":"DE",
    "sg:address":"Marktstr. 72",
    "sg:city":"Wilhelmshaven",
    "sg:phone":"+49 4421/23124",
    "sg:postcode":"26382",
    "sg:province":"Niedersachsen",
    "wof:name":"Stuhl",
    "wof:placetype":"venue"
},
  "geometry": {"coordinates":[8.1114168167,53.5200042725],"type":"Point"}
}