{
  "type": "Feature",
  "properties": {
    "iso:country":"DE",
    "sg:address":"In der Wasche 1",
    "sg:city":"Olpe",
    "sg:phone":"+49 2761/2163",
    "sg:postcode":"57462",
    "sg:province":"Nordrhein-Westfalen",
    "wof:name":"Alfons Kebbekus",
    "wof:placetype":"venue"
},
  "geometry": {"coordinates":[7.83669,51.027828],"type":"Point"}
}