{
  "type": "Feature",
  "properties": {
    "iso:country":"DE",
    "sg:address":"Hofstr. 28",
    "sg:city":"Weiler",
    "sg:phone":"+49 6721/33641",
    "sg:postcode":"55413",
    "sg:province":"Rheinland-Pfalz",
    "wof:name":"Dieter Metz",
    "wof:placetype":"venue"
},
  "geometry": {"coordinates":[7.848796,50.010666],"type":"Point"}
}