{
  "type": "Feature",
  "properties": {
    "iso:country":"DE",
    "sg:address":"Eulenweg 6",
    "sg:city":"Rastatt",
    "sg:phone":"+49 7222/26514",
    "sg:postcode":"76437",
    "sg:province":"Baden-W\u00fcrttemberg",
    "wof:name":"Else Schorpp",
    "wof:placetype":"venue"
},
  "geometry": {"coordinates":[8.1603145599,48.8625640869],"type":"Point"}
}