{
  "type": "Feature",
  "properties": {
    "iso:country":"DE",
    "sg:address":"Poststr. 2",
    "sg:city":"Friedrichshafen",
    "sg:phone":"+49 7541/41668",
    "sg:postcode":"88048",
    "sg:province":"Baden-W\u00fcrttemberg",
    "wof:name":"Zeitler Gmbh",
    "wof:placetype":"venue"
},
  "geometry": {"coordinates":[9.4151706696,47.6698188782],"type":"Point"}
}