{
  "type": "Feature",
  "properties": {
    "iso:country":"DE",
    "sg:address":"Langwahn 98",
    "sg:city":"Eschweiler",
    "sg:phone":"+49 2403/26617",
    "sg:postcode":"52249",
    "sg:province":"Nordrhein-Westfalen",
    "wof:name":"Ch. Barnabas",
    "wof:placetype":"venue"
},
  "geometry": {"coordinates":[6.259372,50.816273],"type":"Point"}
}