{
  "type": "Feature",
  "properties": {
    "iso:country":"DE",
    "sg:address":"Bahnhof Triefenried 2",
    "sg:city":"Regen",
    "sg:phone":"+49 9921/2249",
    "sg:postcode":"94209",
    "sg:province":"Bayern",
    "wof:name":"J. Treml Lagerhaus",
    "wof:placetype":"venue"
},
  "geometry": {"coordinates":[13.053529,48.96946],"type":"Point"}
}