{
  "type": "Feature",
  "properties": {
    "iso:country":"DE",
    "sg:address":"Weinstr. 74",
    "sg:city":"Ranschbach",
    "sg:phone":"+49 6345/2782",
    "sg:postcode":"76829",
    "sg:province":"Rheinland-Pfalz",
    "wof:name":"E. Braun",
    "wof:placetype":"venue"
},
  "geometry": {"coordinates":[8.0292797089,49.1960411072],"type":"Point"}
}