{
  "type": "Feature",
  "properties": {
    "iso:country":"DE",
    "sg:address":"Otfried-M\u00fcller-Weg 10",
    "sg:city":"G\u00f6ttingen",
    "sg:phone":"+49 551/53070",
    "sg:postcode":"37075",
    "sg:province":"Niedersachsen",
    "wof:name":"Prof. Dr. Med. Wolfgang Bommer",
    "wof:placetype":"venue"
},
  "geometry": {"coordinates":[9.958184,51.541988],"type":"Point"}
}