{
  "type": "Feature",
  "properties": {
    "iso:country":"DE",
    "sg:address":"Toeplerstr. 36",
    "sg:city":"Dresden",
    "sg:phone":"+49 351/2517108",
    "sg:postcode":"01279",
    "sg:province":"Sachsen",
    "wof:name":"Rainer Herrmann",
    "wof:placetype":"venue"
},
  "geometry": {"coordinates":[13.8214006424,51.0293045044],"type":"Point"}
}