{
  "type": "Feature",
  "properties": {
    "iso:country":"DE",
    "sg:address":"Sandstr. 33",
    "sg:city":"M\u00fcnchen",
    "sg:phone":"+49 89/55027044",
    "sg:postcode":"80335",
    "sg:province":"Bayern",
    "wof:name":"Hm 1 Gesellschaft F\u00fcr Direkt Marketing Und",
    "wof:placetype":"venue"
},
  "geometry": {"coordinates":[11.5565290451,48.149559021],"type":"Point"}
}