{
  "type": "Feature",
  "properties": {
    "iso:country":"DE",
    "sg:address":"Schafhofer Str. 28",
    "sg:city":"Ahorn",
    "sg:phone":"+49 9565/531",
    "sg:postcode":"96482",
    "sg:province":"Bayern",
    "wof:name":"Johannes Scheurenbrand",
    "wof:placetype":"venue"
},
  "geometry": {"coordinates":[10.920922,50.213428],"type":"Point"}
}