{
  "type": "Feature",
  "properties": {
    "iso:country":"DE",
    "sg:address":"G\u00e4nsestr. 6-8",
    "sg:city":"Warendorf",
    "sg:postcode":"48231",
    "sg:province":"Nordrhein-Westfalen",
    "wof:name":"Commerciale Verwaltungs- Und Beteiligungs Gmbh",
    "wof:placetype":"venue"
},
  "geometry": {"coordinates":[7.967494,51.923077],"type":"Point"}
}