{
  "type": "Feature",
  "properties": {
    "iso:country":"DE",
    "sg:address":"Auf Der Breit 11",
    "sg:city":"Karlsruhe",
    "sg:phone":"+49 4972/1943320",
    "sg:postcode":"76227",
    "sg:province":"Baden-W\u00fcrttemberg",
    "wof:name":"Cfw Cold & Fresh Gmbh & Co. Kg",
    "wof:placetype":"venue"
},
  "geometry": {"coordinates":[8.477519989,49.0181427002],"type":"Point"}
}