{
  "type": "Feature",
  "properties": {
    "iso:country":"DE",
    "sg:address":"Albersweiler Str. 170",
    "sg:city":"Neuenhagen",
    "sg:phone":"+49 3342/205445",
    "sg:postcode":"15366",
    "sg:province":"Brandenburg",
    "wof:name":"Dr. Holger B\u00fcchler",
    "wof:placetype":"venue"
},
  "geometry": {"coordinates":[13.6996183395,52.5276870728],"type":"Point"}
}