{
  "type": "Feature",
  "properties": {
    "iso:country":"DE",
    "sg:address":"An der Kirche 2",
    "sg:city":"K\u00f6nigslutter",
    "sg:postcode":"38154",
    "sg:province":"Niedersachsen",
    "wof:name":"Deutsches Haus Inh. E. Harms",
    "wof:placetype":"venue"
},
  "geometry": {"coordinates":[10.8365526199,52.2393035889],"type":"Point"}
}