{
  "type": "Feature",
  "properties": {
    "iso:country":"DE",
    "sg:address":"Fuchsgasse 14",
    "sg:city":"N\u00f6rvenich",
    "sg:phone":"+49 2426/6578",
    "sg:postcode":"52388",
    "sg:province":"Nordrhein-Westfalen",
    "wof:name":"Jakob Kutz",
    "wof:placetype":"venue"
},
  "geometry": {"coordinates":[6.65401,50.813862],"type":"Point"}
}