{
  "type": "Feature",
  "properties": {
    "iso:country":"DE",
    "sg:address":"Markt 4",
    "sg:city":"Schlieben",
    "sg:phone":"+49 4935/361523",
    "sg:postcode":"04936",
    "sg:province":"Brandenburg",
    "wof:name":"Otto Kalex",
    "wof:placetype":"venue"
},
  "geometry": {"coordinates":[13.38291,51.72385],"type":"Point"}
}