{
  "type": "Feature",
  "properties": {
    "iso:country":"DE",
    "sg:address":"Am Rebberg 90",
    "sg:city":"Gundelfingen",
    "sg:phone":"+49 761/5563870",
    "sg:postcode":"79194",
    "sg:province":"Baden-W\u00fcrttemberg",
    "wof:name":"Heinz Gass",
    "wof:placetype":"venue"
},
  "geometry": {"coordinates":[7.8847031593,48.0367164612],"type":"Point"}
}