{
  "type": "Feature",
  "properties": {
    "iso:country":"DE",
    "sg:address":"Querstr. 4",
    "sg:city":"Ro\u00dflau",
    "sg:phone":"+49 34901/68881",
    "sg:postcode":"06862",
    "sg:province":"Sachsen-Anhalt",
    "wof:name":"Sonnek & Sohn Gmbh",
    "wof:placetype":"venue"
},
  "geometry": {"coordinates":[12.238329,51.888332],"type":"Point"}
}