{
  "type": "Feature",
  "properties": {
    "iso:country":"DE",
    "sg:address":"Richtstr. 8",
    "sg:city":"M\u00fclheim",
    "sg:phone":"+49 208/997056",
    "sg:postcode":"45479",
    "sg:province":"Nordrhein-Westfalen",
    "wof:name":"Ralf Franke Gmbh",
    "wof:placetype":"venue"
},
  "geometry": {"coordinates":[6.8588042259,51.4259109497],"type":"Point"}
}