{
  "type": "Feature",
  "properties": {
    "iso:country":"DE",
    "sg:address":"Kolonnenstr. 30f",
    "sg:city":"Berlin",
    "sg:phone":"+49 30/787800",
    "sg:postcode":"10829",
    "sg:province":"Berlin",
    "wof:name":"S\u00f6llner Projekt- Entwicklung Gmbh",
    "wof:placetype":"venue"
},
  "geometry": {"coordinates":[13.36843,52.483955],"type":"Point"}
}