{
  "type": "Feature",
  "properties": {
    "iso:country":"DE",
    "sg:address":"Hauptstr. 74",
    "sg:city":"Julbach",
    "sg:phone":"+49 8571/920607",
    "sg:postcode":"84387",
    "sg:province":"Bayern",
    "wof:name":"Klaus Schreiner",
    "wof:placetype":"venue"
},
  "geometry": {"coordinates":[12.9595136642,48.2482795715],"type":"Point"}
}