{
  "type": "Feature",
  "properties": {
    "iso:country":"DE",
    "sg:address":"Prie\u00dfnitzstr. 35",
    "sg:city":"N\u00fcrnberg",
    "sg:phone":"+49 911/3939398",
    "sg:postcode":"90419",
    "sg:province":"Bayern",
    "wof:name":"Dr. Helmut Babel Rechtsanwalt",
    "wof:placetype":"venue"
},
  "geometry": {"coordinates":[11.0595855713,49.4661750793],"type":"Point"}
}