{
  "type": "Feature",
  "properties": {
    "iso:country":"DE",
    "sg:address":"Britzinger Str. 62",
    "sg:city":"Freiburg",
    "sg:phone":"+49 761/443747",
    "sg:postcode":"79114",
    "sg:province":"Baden-W\u00fcrttemberg",
    "wof:name":"B. J. Willmann Steuerberater",
    "wof:placetype":"venue"
},
  "geometry": {"coordinates":[7.8148488998,47.9981040955],"type":"Point"}
}