{
  "type": "Feature",
  "properties": {
    "iso:country":"DE",
    "sg:address":"Schwabenstr. 41",
    "sg:city":"Schwabach",
    "sg:phone":"+49 9122/77700",
    "sg:postcode":"91126",
    "sg:province":"Bayern",
    "wof:name":"Alois Matuschek",
    "wof:placetype":"venue"
},
  "geometry": {"coordinates":[11.045375,49.334084],"type":"Point"}
}