{
  "type": "Feature",
  "properties": {
    "iso:country":"DE",
    "sg:address":"Eitnerweg 9",
    "sg:city":"Hamburg",
    "sg:phone":"+49 40/5384522",
    "sg:postcode":"22339",
    "sg:province":"Hamburg",
    "wof:name":"Wolfgang Burkhardt Architekt",
    "wof:placetype":"venue"
},
  "geometry": {"coordinates":[10.045084,53.641045],"type":"Point"}
}