{
  "type": "Feature",
  "properties": {
    "iso:country":"DE",
    "sg:address":"V\u00f6lckersstr. 14-20",
    "sg:city":"Hamburg",
    "sg:phone":"+49 4922/0420030",
    "sg:postcode":"22765",
    "sg:province":"Hamburg",
    "wof:name":"Carlton Musikverlage Hans Gerig & Co",
    "wof:placetype":"venue"
},
  "geometry": {"coordinates":[7.1382689476,50.9561233521],"type":"Point"}
}