{
  "type": "Feature",
  "properties": {
    "iso:country":"DE",
    "sg:address":"Helmholtzstrasse 18",
    "sg:city":"Ulm",
    "sg:phone":"+49 731/5023556",
    "sg:postcode":"89069",
    "sg:province":"Baden-W\u00fcrttemberg",
    "wof:name":"Abteilung Unternehmensplanung Universitaet Ulm",
    "wof:placetype":"venue"
},
  "geometry": {"coordinates":[9.962959,48.425781],"type":"Point"}
}