{
  "type": "Feature",
  "properties": {
    "iso:country":"DE",
    "sg:address":"Moorstr. 6",
    "sg:city":"Bremen",
    "sg:postcode":"28237",
    "sg:province":"Bremen",
    "wof:name":"Rk Gastronomietechnik Gmbh",
    "wof:placetype":"venue"
},
  "geometry": {"coordinates":[8.762991,53.112801],"type":"Point"}
}