{
  "type": "Feature",
  "properties": {
    "iso:country":"DE",
    "sg:address":"Ehinger Str. 23",
    "sg:city":"Blaubeuren",
    "sg:postcode":"89143",
    "sg:province":"Baden-W\u00fcrttemberg",
    "wof:name":"Burger Gmbh",
    "wof:placetype":"venue"
},
  "geometry": {"coordinates":[9.7772607803,48.4034729004],"type":"Point"}
}