{
  "type": "Feature",
  "properties": {
    "iso:country":"DE",
    "sg:address":"Nordstr. 10",
    "sg:city":"Ruhpolding",
    "sg:phone":"+49 8663/754",
    "sg:postcode":"83324",
    "sg:province":"Bayern",
    "wof:name":"Anton Honsowitz",
    "wof:placetype":"venue"
},
  "geometry": {"coordinates":[12.643548,47.771946],"type":"Point"}
}