{
  "type": "Feature",
  "properties": {
    "iso:country":"DE",
    "sg:address":"Gruber Str 46a",
    "sg:city":"Poing",
    "sg:phone":"+49 8121/951850",
    "sg:postcode":"85586",
    "sg:province":"Bayern",
    "wof:name":"Redtec Publishing Gmbh",
    "wof:placetype":"venue"
},
  "geometry": {"coordinates":[11.80563,48.171555],"type":"Point"}
}