{
  "type": "Feature",
  "properties": {
    "iso:country":"DE",
    "sg:address":"Bahnhofstr. 52",
    "sg:city":"Ottobeuren",
    "sg:phone":"+49 8332/937575",
    "sg:postcode":"87724",
    "sg:province":"Bayern",
    "wof:name":"Franz Rauh",
    "wof:placetype":"venue"
},
  "geometry": {"coordinates":[10.3057832718,47.9428024292],"type":"Point"}
}