{
  "type": "Feature",
  "properties": {
    "iso:country":"DE",
    "sg:address":"Gotenstr. 25",
    "sg:city":"Stadtbergen",
    "sg:phone":"+49 821/432676",
    "sg:postcode":"86391",
    "sg:province":"Bayern",
    "wof:name":"Armin Welser Architekt",
    "wof:placetype":"venue"
},
  "geometry": {"coordinates":[10.834768,48.358253],"type":"Point"}
}