{
  "type": "Feature",
  "properties": {
    "iso:country":"DE",
    "sg:address":"Ringstr. 42",
    "sg:city":"Siegburg",
    "sg:phone":"+49 2241/62491",
    "sg:postcode":"53721",
    "sg:province":"Nordrhein-Westfalen",
    "wof:name":"Heinz-josef Kurenbach",
    "wof:placetype":"venue"
},
  "geometry": {"coordinates":[7.2060480118,50.7984695435],"type":"Point"}
}