{
  "type": "Feature",
  "properties": {
    "iso:country":"DE",
    "sg:address":"Hauptstr. 91",
    "sg:city":"Frechen",
    "sg:postcode":"50226",
    "sg:province":"Nordrhein-Westfalen",
    "wof:name":"Capricon Ges. F\u00fcr Industrie- Beteiligungen Liegenschaften",
    "wof:placetype":"venue"
},
  "geometry": {"coordinates":[6.809429,50.909897],"type":"Point"}
}