{
  "type": "Feature",
  "properties": {
    "iso:country":"DE",
    "sg:address":"Am Niddatal 7",
    "sg:city":"Frankfurt",
    "sg:phone":"+49 69/764471",
    "sg:postcode":"60488",
    "sg:province":"Hessen",
    "wof:name":"Jochen Mickelthwate Ingenieur",
    "wof:placetype":"venue"
},
  "geometry": {"coordinates":[8.62016,50.136242],"type":"Point"}
}