{
  "type": "Feature",
  "properties": {
    "iso:country":"DE",
    "sg:address":"Mannheimer Str. 273",
    "sg:city":"Heidelberg",
    "sg:phone":"+49 6221/840199",
    "sg:postcode":"69123",
    "sg:province":"Baden-W\u00fcrttemberg",
    "wof:name":"Klaus Etzkorn",
    "wof:placetype":"venue"
},
  "geometry": {"coordinates":[8.6471576691,49.4262733459],"type":"Point"}
}