{
  "type": "Feature",
  "properties": {
    "iso:country":"DE",
    "sg:address":"Neust\u00e4dter Markt 55",
    "sg:city":"Hildesheim",
    "sg:phone":"+49 5121/34686",
    "sg:postcode":"31134",
    "sg:province":"Niedersachsen",
    "wof:name":"Cafe Am Dom",
    "wof:placetype":"venue"
},
  "geometry": {"coordinates":[9.954258,52.148685],"type":"Point"}
}