{
  "type": "Feature",
  "properties": {
    "iso:country":"DE",
    "sg:address":"Uhlandstr. 26 - 28",
    "sg:city":"Backnang",
    "sg:phone":"+49 4971/9160449",
    "sg:postcode":"71522",
    "sg:province":"Baden-W\u00fcrttemberg",
    "wof:name":"Merkle Bestecke",
    "wof:placetype":"venue"
},
  "geometry": {"coordinates":[9.4303655624,48.9477157593],"type":"Point"}
}