{
  "type": "Feature",
  "properties": {
    "iso:country":"DE",
    "sg:address":"Wermbachstr. 27",
    "sg:city":"Aschaffenburg",
    "sg:phone":"+49 6021/23191",
    "sg:postcode":"63739",
    "sg:province":"Bayern",
    "wof:name":"H. Janson Stahl- Und Schneidwaren",
    "wof:placetype":"venue"
},
  "geometry": {"coordinates":[9.1488256454,49.9732971191],"type":"Point"}
}