{
  "type": "Feature",
  "properties": {
    "iso:country":"DE",
    "sg:address":"Am Marktplatz 10",
    "sg:city":"Wedel",
    "sg:phone":"+49 4103/93000",
    "sg:postcode":"22880",
    "sg:province":"Schleswig-Holstein",
    "wof:name":"Dehn Steuerberatungs Gmbh",
    "wof:placetype":"venue"
},
  "geometry": {"coordinates":[9.6983127594,53.5836715698],"type":"Point"}
}