{
  "type": "Feature",
  "properties": {
    "iso:country":"DE",
    "sg:address":"Sch\u00fcppenstr. 11",
    "sg:city":"Coesfeld",
    "sg:phone":"+49 2541/83255",
    "sg:postcode":"48653",
    "sg:province":"Nordrhein-Westfalen",
    "wof:name":"Fashion Schmiemann Textil Gmbh & Co. Kg",
    "wof:placetype":"venue"
},
  "geometry": {"coordinates":[7.1668281555,51.9446563721],"type":"Point"}
}