{
  "type": "Feature",
  "properties": {
    "iso:country":"DE",
    "sg:address":"Thomas-Mann-Str. 15",
    "sg:city":"Lauchhammer",
    "sg:phone":"+49 3574/2600",
    "sg:postcode":"01979",
    "sg:province":"Brandenburg",
    "wof:name":"Gemeinn. Wohnungsgenossensch. Lauchhammer Eg",
    "wof:placetype":"venue"
},
  "geometry": {"coordinates":[13.7713747025,51.500164032],"type":"Point"}
}