{
  "type": "Feature",
  "properties": {
    "iso:country":"DE",
    "sg:address":"Laberstr. 6",
    "sg:city":"Memmingen",
    "sg:phone":"+49 8331/62001",
    "sg:postcode":"87700",
    "sg:province":"Bayern",
    "wof:name":"Comsys Petra Stephan",
    "wof:placetype":"venue"
},
  "geometry": {"coordinates":[10.165221,47.986599],"type":"Point"}
}