{
  "type": "Feature",
  "properties": {
    "iso:country":"DE",
    "sg:address":"Wittland 10",
    "sg:city":"Kiel",
    "sg:phone":"+49 431/519620",
    "sg:postcode":"24109",
    "sg:province":"Schleswig-Holstein",
    "wof:name":"Ttz Sh Technologie-transfer-zentrale Schleswig-holstein Gmbh",
    "wof:placetype":"venue"
},
  "geometry": {"coordinates":[10.0823459625,54.326965332],"type":"Point"}
}