{
  "type": "Feature",
  "properties": {
    "iso:country":"DE",
    "sg:address":"Burkhardt-u.-Weber-Str 57",
    "sg:city":"Reutlingen",
    "sg:phone":"+49 7121/2055360",
    "sg:postcode":"72760",
    "sg:province":"Baden-W\u00fcrttemberg",
    "wof:name":"Triple-sixty Lang & Hanstein Gbr",
    "wof:placetype":"venue"
},
  "geometry": {"coordinates":[9.210101,48.49976],"type":"Point"}
}