{
  "type": "Feature",
  "properties": {
    "iso:country":"DE",
    "sg:address":"Blutstr. 18",
    "sg:city":"Parchim",
    "sg:phone":"+49 3871/212373",
    "sg:postcode":"19370",
    "sg:province":"Mecklenburg-Vorpommern",
    "wof:name":"G. Gundske",
    "wof:placetype":"venue"
},
  "geometry": {"coordinates":[11.845657,53.427841],"type":"Point"}
}