{
  "type": "Feature",
  "properties": {
    "iso:country":"DE",
    "sg:address":"Berger Str. 25",
    "sg:city":"Anr\u00f6chte",
    "sg:phone":"+49 2947/281",
    "sg:postcode":"59609",
    "sg:province":"Nordrhein-Westfalen",
    "wof:name":"Raab Karcher Baustoffe",
    "wof:placetype":"venue"
},
  "geometry": {"coordinates":[8.3335266113,51.5627403259],"type":"Point"}
}