{
  "type": "Feature",
  "properties": {
    "iso:country":"DE",
    "sg:address":"Uferallee 29",
    "sg:city":"Bernkastel-Kues",
    "sg:phone":"+49 6531/3374",
    "sg:postcode":"54470",
    "sg:province":"Rheinland-Pfalz",
    "wof:name":"Ernst Fackler Weinanbau",
    "wof:placetype":"venue"
},
  "geometry": {"coordinates":[7.050588131,49.9389343262],"type":"Point"}
}