{
  "type": "Feature",
  "properties": {
    "iso:country":"DE",
    "sg:address":"Oberdamm 33",
    "sg:city":"Minden",
    "sg:phone":"+49 571/52498",
    "sg:postcode":"32429",
    "sg:province":"Nordrhein-Westfalen",
    "wof:name":"Manfred Timmermann",
    "wof:placetype":"venue"
},
  "geometry": {"coordinates":[8.858536,52.280048],"type":"Point"}
}