{
  "type": "Feature",
  "properties": {
    "iso:country":"DE",
    "sg:address":"Krefelder Str. 32",
    "sg:city":"Willich",
    "sg:phone":"+49 2154/3727",
    "sg:postcode":"47877",
    "sg:province":"Nordrhein-Westfalen",
    "wof:name":"B. Junker",
    "wof:placetype":"venue"
},
  "geometry": {"coordinates":[6.5540599823,51.2683830261],"type":"Point"}
}