{
  "type": "Feature",
  "properties": {
    "iso:country":"DE",
    "sg:address":"Zum Herrenberg 94",
    "sg:city":"Enkirch/Mosel",
    "sg:phone":"+49 6541",
    "sg:postcode":"56850",
    "sg:province":"Rheinland-Pfalz",
    "wof:name":"Becker-werbung",
    "wof:placetype":"venue"
},
  "geometry": {"coordinates":[7.270946,49.962318],"type":"Point"}
}