{
  "type": "Feature",
  "properties": {
    "iso:country":"DE",
    "sg:address":"Eckstr. 4",
    "sg:city":"Duisburg",
    "sg:postcode":"47249",
    "sg:province":"Nordrhein-Westfalen",
    "wof:name":"G. & G. Gmbh",
    "wof:placetype":"venue"
},
  "geometry": {"coordinates":[6.761424,51.377525],"type":"Point"}
}