{
  "type": "Feature",
  "properties": {
    "iso:country":"DE",
    "sg:address":"Ulhausgasse 9",
    "sg:city":"Langerwehe",
    "sg:phone":"+49 2423/3687",
    "sg:postcode":"52379",
    "sg:province":"Nordrhein-Westfalen",
    "wof:name":"Treffpunkt",
    "wof:placetype":"venue"
},
  "geometry": {"coordinates":[6.356593132,50.8177146912],"type":"Point"}
}