{
  "type": "Feature",
  "properties": {
    "iso:country":"DE",
    "sg:address":"Alte Str. 24",
    "sg:city":"Olbernhau",
    "sg:phone":"+49 37360/73169",
    "sg:postcode":"09526",
    "sg:province":"Sachsen",
    "wof:name":"Siegert Gmbh",
    "wof:placetype":"venue"
},
  "geometry": {"coordinates":[13.3795890808,50.6497039795],"type":"Point"}
}