{
  "type": "Feature",
  "properties": {
    "iso:country":"DE",
    "sg:address":"Hansastr. 85",
    "sg:city":"Unna",
    "sg:phone":"+49 2303/1721",
    "sg:postcode":"59425",
    "sg:province":"Nordrhein-Westfalen",
    "wof:name":"Franz Herbr\u00fcgger Kg",
    "wof:placetype":"venue"
},
  "geometry": {"coordinates":[7.6723189354,51.5415344238],"type":"Point"}
}