{
  "type": "Feature",
  "properties": {
    "iso:country":"DE",
    "sg:address":"Neustadtstr. 38",
    "sg:city":"M\u00fclheim",
    "sg:phone":"+49 4969/439533",
    "sg:postcode":"45476",
    "sg:province":"Nordrhein-Westfalen",
    "wof:name":"Egs Hessen Einkaufsgenossen- Schaft Schornsteinfeger E.g.",
    "wof:placetype":"venue"
},
  "geometry": {"coordinates":[8.731203,50.112404],"type":"Point"}
}