{
  "type": "Feature",
  "properties": {
    "iso:country":"DE",
    "sg:address":"Stadtkoppel 3",
    "sg:city":"L\u00fcneburg",
    "sg:postcode":"21337",
    "sg:province":"Niedersachsen",
    "wof:name":"Baumeister Programm Verwaltungs- Und",
    "wof:placetype":"venue"
},
  "geometry": {"coordinates":[10.446073,53.249283],"type":"Point"}
}