{
  "type": "Feature",
  "properties": {
    "iso:country":"DE",
    "sg:address":"Sch\u00f6ne Aussicht 15",
    "sg:city":"Schrecksbach",
    "sg:phone":"+49 6698/96160",
    "sg:postcode":"34637",
    "sg:province":"Hessen",
    "wof:name":"Sch\u00f6ne Aussicht Altenheim",
    "wof:placetype":"venue"
},
  "geometry": {"coordinates":[9.295516,50.856804],"type":"Point"}
}