{
  "type": "Feature",
  "properties": {
    "iso:country":"DE",
    "sg:address":"M\u00e4rchenhainstr. 19",
    "sg:city":"Niederheimbach",
    "sg:postcode":"55413",
    "sg:province":"Rheinland-Pfalz",
    "wof:name":"Meat-impex Gmbh",
    "wof:placetype":"venue"
},
  "geometry": {"coordinates":[7.812124,50.02943],"type":"Point"}
}