{
  "type": "Feature",
  "properties": {
    "iso:country":"DE",
    "sg:address":"Freiheider Str. 2",
    "sg:city":"Wegberg",
    "sg:postcode":"41844",
    "sg:province":"Nordrhein-Westfalen",
    "wof:name":"Marion M\u00fcller-platz Gmbh",
    "wof:placetype":"venue"
},
  "geometry": {"coordinates":[6.286024,51.138493],"type":"Point"}
}