{
  "type": "Feature",
  "properties": {
    "iso:country":"DE",
    "sg:address":"Harfenstr. 6",
    "sg:city":"Erlangen",
    "sg:phone":"+49 9131/202605",
    "sg:postcode":"91054",
    "sg:province":"Bayern",
    "wof:name":"Diem Carpe",
    "wof:placetype":"venue"
},
  "geometry": {"coordinates":[11.006313324,49.6012878418],"type":"Point"}
}