{
  "type": "Feature",
  "properties": {
    "iso:country":"DE",
    "sg:address":"Salweytal 8",
    "sg:city":"Eslohe",
    "sg:phone":"+49 2973/81600",
    "sg:postcode":"59889",
    "sg:province":"Nordrhein-Westfalen",
    "wof:name":"Hotel Woiler Hof",
    "wof:placetype":"venue"
},
  "geometry": {"coordinates":[8.1270666122,51.253326416],"type":"Point"}
}