{
  "type": "Feature",
  "properties": {
    "iso:country":"DE",
    "sg:address":"Bahnhofstr. 41",
    "sg:city":"Freyung",
    "sg:phone":"+49 8551/910221",
    "sg:postcode":"94078",
    "sg:province":"Bayern",
    "wof:name":"Heinz Und I. Stadler",
    "wof:placetype":"venue"
},
  "geometry": {"coordinates":[13.5479660034,48.8020935059],"type":"Point"}
}