{
  "type": "Feature",
  "properties": {
    "iso:country":"DE",
    "sg:address":"Taunusstr. 37",
    "sg:city":"Limeshain",
    "sg:phone":"+49 6048/1221",
    "sg:postcode":"63694",
    "sg:province":"Hessen",
    "wof:name":"Megatental Vertrieb Gmbh",
    "wof:placetype":"venue"
},
  "geometry": {"coordinates":[8.9941730499,50.2584915161],"type":"Point"}
}