{
  "type": "Feature",
  "properties": {
    "iso:country":"DE",
    "sg:address":"Breite Str. 44a",
    "sg:city":"S\u00fcpplingen",
    "sg:phone":"+49 4953/55445",
    "sg:postcode":"38373",
    "sg:province":"Niedersachsen",
    "wof:name":"Norddeutsche Landesbank Girozentr.",
    "wof:placetype":"venue"
},
  "geometry": {"coordinates":[10.90531,52.226109],"type":"Point"}
}