{
  "type": "Feature",
  "properties": {
    "iso:country":"DE",
    "sg:address":"Ostheimer Str. 4",
    "sg:city":"Berlin",
    "sg:postcode":"12349",
    "sg:province":"Berlin",
    "wof:name":"Bk-baukauf Und Anlagen Kg",
    "wof:placetype":"venue"
},
  "geometry": {"coordinates":[13.404975,52.414825],"type":"Point"}
}