{
  "type": "Feature",
  "properties": {
    "iso:country":"DE",
    "sg:address":"Poller Weg 1",
    "sg:city":"K\u00f6ln",
    "sg:phone":"+49 2203/14654",
    "sg:postcode":"51149",
    "sg:province":"Nordrhein-Westfalen",
    "wof:name":"Allianz",
    "wof:placetype":"venue"
},
  "geometry": {"coordinates":[7.0061650276,50.9073905945],"type":"Point"}
}