{
  "type": "Feature",
  "properties": {
    "iso:country":"DE",
    "sg:address":"Auchskopfstr 1",
    "sg:city":"Habichtswald",
    "sg:phone":"+49 5606/9728",
    "sg:postcode":"34317",
    "sg:province":"Hessen",
    "wof:name":"Info-center I. Schade",
    "wof:placetype":"venue"
},
  "geometry": {"coordinates":[9.313652,51.328102],"type":"Point"}
}