{
  "type": "Feature",
  "properties": {
    "iso:country":"DE",
    "sg:address":"Dr.-Haupt-Weg 4",
    "sg:city":"Nassau",
    "sg:phone":"+49 2604/95370",
    "sg:postcode":"56377",
    "sg:province":"Rheinland-Pfalz",
    "wof:name":"Hotel R\u00fcttgers Inh. Ralf K\u00f6ster",
    "wof:placetype":"venue"
},
  "geometry": {"coordinates":[7.7959899902,50.3155708313],"type":"Point"}
}