{
  "type": "Feature",
  "properties": {
    "iso:country":"DE",
    "sg:address":"Waldallee 7",
    "sg:city":"Eppstein",
    "sg:phone":"+49 6198/500095",
    "sg:postcode":"65817",
    "sg:province":"Hessen",
    "wof:name":"Liane Merbeck",
    "wof:placetype":"venue"
},
  "geometry": {"coordinates":[8.3632774353,50.1376190186],"type":"Point"}
}