{
  "type": "Feature",
  "properties": {
    "iso:country":"DE",
    "sg:address":"Am Bahnhof 3",
    "sg:city":"Waldkappel",
    "sg:phone":"+49 4956/5698960",
    "sg:postcode":"37284",
    "sg:province":"Hessen",
    "wof:name":"Mech. Werkst\u00c4tten Hildmann Gmbh",
    "wof:placetype":"venue"
},
  "geometry": {"coordinates":[9.88248,51.149456],"type":"Point"}
}