{
  "type": "Feature",
  "properties": {
    "iso:country":"DE",
    "sg:address":"Traubenbergweg 4",
    "sg:city":"Roding",
    "sg:phone":"+49 9461/5540",
    "sg:postcode":"93426",
    "sg:province":"Bayern",
    "wof:name":"Assopart Management- Beratung Gmbh",
    "wof:placetype":"venue"
},
  "geometry": {"coordinates":[12.544441,49.217682],"type":"Point"}
}