{
  "type": "Feature",
  "properties": {
    "iso:country":"DE",
    "sg:address":"T\u00e4ubchenweg 84",
    "sg:city":"Leipzig",
    "sg:phone":"+49 341/2619837",
    "sg:postcode":"04317",
    "sg:province":"Sachsen",
    "wof:name":"Konsumgenoss. Leipzig Eg",
    "wof:placetype":"venue"
},
  "geometry": {"coordinates":[12.4062242508,51.3357925415],"type":"Point"}
}