{
  "type": "Feature",
  "properties": {
    "iso:country":"DE",
    "sg:address":"Kaiser-Karl-Ring 2",
    "sg:city":"Bonn",
    "sg:phone":"+49 228/673400",
    "sg:postcode":"53111",
    "sg:province":"Nordrhein-Westfalen",
    "wof:name":"Kath. Pfarramt St. Joseph",
    "wof:placetype":"venue"
},
  "geometry": {"coordinates":[7.0941939354,50.7464866638],"type":"Point"}
}