{
  "type": "Feature",
  "properties": {
    "iso:country":"DE",
    "sg:address":"Sigburg 4",
    "sg:city":"Frankfurt",
    "sg:postcode":"32145",
    "sg:province":"Brandenburg",
    "wof:name":"Sub7germany Help Pages",
    "wof:placetype":"venue"
},
  "geometry": {"coordinates":[8.6834,50.11203],"type":"Point"}
}