{
  "type": "Feature",
  "properties": {
    "iso:country":"DE",
    "sg:address":"Am Neuhaus 43",
    "sg:city":"Langerwehe",
    "sg:phone":"+49 2423/1615",
    "sg:postcode":"52379",
    "sg:province":"Nordrhein-Westfalen",
    "wof:name":"Willi Rauer",
    "wof:placetype":"venue"
},
  "geometry": {"coordinates":[6.399942,50.797741],"type":"Point"}
}