{
  "type": "Feature",
  "properties": {
    "iso:country":"DE",
    "sg:address":"Trappentreustr. 8",
    "sg:city":"M\u00fcnchen",
    "sg:phone":"+49 89/505792",
    "sg:postcode":"80339",
    "sg:province":"Bayern",
    "wof:name":"Hans Schlei\u00dfheimer",
    "wof:placetype":"venue"
},
  "geometry": {"coordinates":[11.5339956284,48.1391029358],"type":"Point"}
}