{
  "type": "Feature",
  "properties": {
    "iso:country":"DE",
    "sg:address":"Schwachhauser Heerstr. 276",
    "sg:city":"Bremen",
    "sg:phone":"+49 421/235161",
    "sg:postcode":"28359",
    "sg:province":"Bremen",
    "wof:name":"Ziebart Tidycar",
    "wof:placetype":"venue"
},
  "geometry": {"coordinates":[8.870507,53.091492],"type":"Point"}
}