{
  "type": "Feature",
  "properties": {
    "iso:country":"DE",
    "sg:address":"Stromstr. 41",
    "sg:city":"D\u00fcsseldorf",
    "sg:postcode":"40221",
    "sg:province":"Nordrhein-Westfalen",
    "wof:name":"Dbh Deutsche Beteiligungs- Holding Ag",
    "wof:placetype":"venue"
},
  "geometry": {"coordinates":[6.761995,51.217056],"type":"Point"}
}