{
  "type": "Feature",
  "properties": {
    "iso:country":"DE",
    "sg:address":"Grootkoppel 8",
    "sg:city":"L\u00fcbeck",
    "sg:phone":"+49 4945/1624277",
    "sg:postcode":"23566",
    "sg:province":"Schleswig-Holstein",
    "wof:name":"Gero Hausding Gmbh",
    "wof:placetype":"venue"
},
  "geometry": {"coordinates":[10.745215416,53.8707389832],"type":"Point"}
}