{
  "type": "Feature",
  "properties": {
    "iso:country":"DE",
    "sg:address":"Genslerstr. 26",
    "sg:city":"Berlin",
    "sg:phone":"+49 30/9750349",
    "sg:postcode":"13055",
    "sg:province":"Berlin",
    "wof:name":"Gottfried Kellner Ingenieur",
    "wof:placetype":"venue"
},
  "geometry": {"coordinates":[13.4974355698,52.536857605],"type":"Point"}
}