{
  "type": "Feature",
  "properties": {
    "iso:country":"DE",
    "sg:address":"Am Br\u00fccksken 9",
    "sg:city":"H\u00fcnxe",
    "sg:phone":"+49 2064/31426",
    "sg:postcode":"46569",
    "sg:province":"Nordrhein-Westfalen",
    "wof:name":"Zahn-design Gmbh",
    "wof:placetype":"venue"
},
  "geometry": {"coordinates":[6.756063,51.600159],"type":"Point"}
}