{
  "type": "Feature",
  "properties": {
    "iso:country":"DE",
    "sg:address":"Arsterdamm 82",
    "sg:city":"Bremen",
    "sg:phone":"+49 421/874186",
    "sg:postcode":"28277",
    "sg:province":"Bremen",
    "wof:name":"Kurt Meyer",
    "wof:placetype":"venue"
},
  "geometry": {"coordinates":[8.8296604156,53.0416564941],"type":"Point"}
}