{
  "type": "Feature",
  "properties": {
    "iso:country":"DE",
    "sg:address":"Gunther-Pl\u00fcschow-Str. 22",
    "sg:city":"K\u00f6ln",
    "sg:postcode":"50829",
    "sg:province":"Nordrhein-Westfalen",
    "wof:name":"Dhs F\u00f6rdertechnik Gmbh",
    "wof:placetype":"venue"
},
  "geometry": {"coordinates":[6.8870120049,50.9820404053],"type":"Point"}
}