{
  "type": "Feature",
  "properties": {
    "iso:country":"DE",
    "sg:address":"An der D\u00f6rnte 6",
    "sg:city":"Wallenhorst",
    "sg:phone":"+49 5407/2835",
    "sg:postcode":"49134",
    "sg:province":"Niedersachsen",
    "wof:name":"Motos Motor-technik Gmbh",
    "wof:placetype":"venue"
},
  "geometry": {"coordinates":[8.0044765472,52.3520126343],"type":"Point"}
}