{
  "type": "Feature",
  "properties": {
    "iso:country":"DE",
    "sg:address":"Schwanthalerstr. 22",
    "sg:city":"M\u00fcnchen",
    "sg:phone":"+49 89/597402",
    "sg:postcode":"80336",
    "sg:province":"Bayern",
    "wof:name":"Bavaria Kinobetriebs- Und Beteiligungs-gmbh",
    "wof:placetype":"venue"
},
  "geometry": {"coordinates":[11.561331749,48.1375274658],"type":"Point"}
}