{
  "type": "Feature",
  "properties": {
    "iso:country":"DE",
    "sg:city":"Konstanz",
    "sg:postcode":"78465",
    "sg:province":"Baden-W\u00fcrttemberg",
    "wof:name":"Dlrg Gruppe Dettingen-dingelsdorf E.v.",
    "wof:placetype":"venue"
},
  "geometry": {"coordinates":[9.172965,47.714134],"type":"Point"}
}