{
  "type": "Feature",
  "properties": {
    "iso:country":"DE",
    "sg:address":"Nelkentor 17",
    "sg:city":"Chemnitz",
    "sg:phone":"+49 371/519125",
    "sg:postcode":"09126",
    "sg:province":"Sachsen",
    "wof:name":"M. Moser",
    "wof:placetype":"venue"
},
  "geometry": {"coordinates":[12.944793,50.811386],"type":"Point"}
}