{
  "type": "Feature",
  "properties": {
    "iso:country":"DE",
    "sg:city":"Iphofen",
    "sg:phone":"+49 9323/80452",
    "sg:postcode":"97348",
    "sg:province":"Bayern",
    "wof:name":"Esoteriko",
    "wof:placetype":"venue"
},
  "geometry": {"coordinates":[10.244059,49.728561],"type":"Point"}
}