{
  "type": "Feature",
  "properties": {
    "iso:country":"DE",
    "sg:address":"Chemnitzer Str. 39",
    "sg:city":"Oederan",
    "sg:phone":"+49 37292/60371",
    "sg:postcode":"09569",
    "sg:province":"Sachsen",
    "wof:name":"Ute Tippmann Ekz Zur Stanze",
    "wof:placetype":"venue"
},
  "geometry": {"coordinates":[13.162212,50.860813],"type":"Point"}
}