{
  "type": "Feature",
  "properties": {
    "iso:country":"DE",
    "sg:address":"Kapellenweg 15",
    "sg:city":"Gangkofen",
    "sg:phone":"+49 8722/1001",
    "sg:postcode":"84140",
    "sg:province":"Bayern",
    "wof:name":"Werra Bau Verwaltungs- Gmbh",
    "wof:placetype":"venue"
},
  "geometry": {"coordinates":[12.5668697357,48.4326972961],"type":"Point"}
}