{
  "type": "Feature",
  "properties": {
    "iso:country":"DE",
    "sg:address":"Neunkirchener Str. 5",
    "sg:city":"Bremerhaven",
    "sg:phone":"+49 471/803029",
    "sg:postcode":"27578",
    "sg:province":"Bremen",
    "wof:name":"Heinz Kr\u00fcger Architekt",
    "wof:placetype":"venue"
},
  "geometry": {"coordinates":[8.596523,53.593468],"type":"Point"}
}