{
  "type": "Feature",
  "properties": {
    "iso:country":"DE",
    "sg:address":"Scharfreiter Platz 22",
    "sg:city":"M\u00fcnchen",
    "sg:postcode":"81549",
    "sg:province":"Bayern",
    "wof:name":"Tippk\u00f6nigin 2001",
    "wof:placetype":"venue"
},
  "geometry": {"coordinates":[11.593519,48.104614],"type":"Point"}
}