{
  "type": "Feature",
  "properties": {
    "iso:country":"DE",
    "sg:address":"Karlumer Str. 2",
    "sg:city":"Achtrup",
    "sg:phone":"+49 4662/3538",
    "sg:postcode":"25917",
    "sg:province":"Schleswig-Holstein",
    "wof:name":"Christian Bonnichsen",
    "wof:placetype":"venue"
},
  "geometry": {"coordinates":[9.0258760452,54.7895774841],"type":"Point"}
}