{
  "type": "Feature",
  "properties": {
    "iso:country":"DE",
    "sg:address":"Zur Herrenau 1",
    "sg:city":"Kn\u00fcllwald",
    "sg:phone":"+49 5681/2295",
    "sg:postcode":"34593",
    "sg:province":"Hessen",
    "wof:name":"Forellenhof",
    "wof:placetype":"venue"
},
  "geometry": {"coordinates":[9.4772758484,50.9697532654],"type":"Point"}
}