{
  "type": "Feature",
  "properties": {
    "iso:country":"DE",
    "sg:address":"Richard-Wagner-Str. 23",
    "sg:city":"Ludwigsburg",
    "sg:phone":"+49 7141/920951",
    "sg:postcode":"71638",
    "sg:province":"Baden-W\u00fcrttemberg",
    "wof:name":"Lebensmittelladen Avsar",
    "wof:placetype":"venue"
},
  "geometry": {"coordinates":[9.1912822723,48.887462616],"type":"Point"}
}