{
  "type": "Feature",
  "properties": {
    "iso:country":"DE",
    "sg:address":"Dorfstr. 3",
    "sg:city":"Gro\u00dfeutersdorf",
    "sg:phone":"+49 36424/24029",
    "sg:postcode":"07768",
    "sg:province":"Th\u00fcringen",
    "wof:name":"Franks Gastst\u00e4tte",
    "wof:placetype":"venue"
},
  "geometry": {"coordinates":[11.5628824234,50.7886924744],"type":"Point"}
}