{
  "type": "Feature",
  "properties": {
    "iso:country":"DE",
    "sg:address":"M\u00fcnzstr. 27",
    "sg:city":"Schongau",
    "sg:phone":"+49 8861/4110",
    "sg:postcode":"86956",
    "sg:province":"Bayern",
    "wof:name":"Ludwig Feustle",
    "wof:placetype":"venue"
},
  "geometry": {"coordinates":[10.896717,47.813427],"type":"Point"}
}