{
  "type": "Feature",
  "properties": {
    "iso:country":"DE",
    "sg:address":"Untere Dorfgasse 2",
    "sg:city":"K\u00f6tz",
    "sg:phone":"+49 8221/251195",
    "sg:postcode":"89359",
    "sg:province":"Bayern",
    "wof:name":"Pizzeria Pinocchio",
    "wof:placetype":"venue"
},
  "geometry": {"coordinates":[10.2791452408,48.4071044922],"type":"Point"}
}