{
  "type": "Feature",
  "properties": {
    "iso:country":"DE",
    "sg:address":"Ackerstr. 88",
    "sg:city":"D\u00fcsseldorf",
    "sg:phone":"+49 211/663023",
    "sg:postcode":"40233",
    "sg:province":"Nordrhein-Westfalen",
    "wof:name":"Comeback",
    "wof:placetype":"venue"
},
  "geometry": {"coordinates":[6.8015151024,51.2277641296],"type":"Point"}
}