{
  "type": "Feature",
  "properties": {
    "iso:country":"DE",
    "sg:address":"Im St\u00f6cken 12",
    "sg:city":"Albstadt",
    "sg:postcode":"72458",
    "sg:province":"Baden-W\u00fcrttemberg",
    "wof:name":"L-baukonzept Gmbh & Co. Kg",
    "wof:placetype":"venue"
},
  "geometry": {"coordinates":[9.032891,48.206161],"type":"Point"}
}