{
  "type": "Feature",
  "properties": {
    "iso:country":"DE",
    "sg:address":"Am Wall 2",
    "sg:city":"Luckenwalde",
    "sg:phone":"+49 3371/611681",
    "sg:postcode":"14943",
    "sg:province":"Brandenburg",
    "wof:name":"Hans-peter Bischoff Anlageberater",
    "wof:placetype":"venue"
},
  "geometry": {"coordinates":[13.1814804077,52.0784454346],"type":"Point"}
}