{
  "type": "Feature",
  "properties": {
    "iso:country":"DE",
    "sg:address":"Roseggerstr. 43",
    "sg:city":"Heppenheim",
    "sg:phone":"+49 4962/5274177",
    "sg:postcode":"64646",
    "sg:province":"Hessen",
    "wof:name":"Greif Landschaftsbau",
    "wof:placetype":"venue"
},
  "geometry": {"coordinates":[8.626816,49.639946],"type":"Point"}
}