{
  "type": "Feature",
  "properties": {
    "iso:country":"DE",
    "sg:address":"Humboldtstr. 51",
    "sg:city":"Hamburg",
    "sg:postcode":"22083",
    "sg:province":"Hamburg",
    "wof:name":"G. O. S. Agentur F\u00fcr Mediaservice Gmbh & Co. Kg",
    "wof:placetype":"venue"
},
  "geometry": {"coordinates":[10.025220871,53.5739097595],"type":"Point"}
}