{
  "type": "Feature",
  "properties": {
    "iso:country":"DE",
    "sg:address":"Krefelderstr. 845",
    "sg:city":"M\u00f6nchengladbach",
    "sg:phone":"+49 4921/616690",
    "sg:postcode":"41066",
    "sg:province":"Nordrhein-Westfalen",
    "wof:name":"Nellen & Quack Logistik Gmbh & Co Kg",
    "wof:placetype":"venue"
},
  "geometry": {"coordinates":[6.488049984,51.2290115356],"type":"Point"}
}