{
  "type": "Feature",
  "properties": {
    "iso:country":"DE",
    "sg:address":"Allingerweg 10",
    "sg:city":"Abensberg",
    "sg:phone":"+49 9443/903550",
    "sg:postcode":"93326",
    "sg:province":"Bayern",
    "wof:name":"E. P\u00fcrkenauer",
    "wof:placetype":"venue"
},
  "geometry": {"coordinates":[11.9110860825,48.8008995056],"type":"Point"}
}