{
  "type": "Feature",
  "properties": {
    "iso:country":"DE",
    "sg:address":"Strebelstr. 18",
    "sg:city":"Stuttgart",
    "sg:phone":"+49 711/4560254",
    "sg:postcode":"70599",
    "sg:province":"Baden-W\u00fcrttemberg",
    "wof:name":"Hls Planungsb\u00fcro",
    "wof:placetype":"venue"
},
  "geometry": {"coordinates":[9.2035970688,48.7139854431],"type":"Point"}
}