{
  "type": "Feature",
  "properties": {
    "iso:country":"DE",
    "sg:address":"Flughafenstr. 9",
    "sg:city":"Pfatter",
    "sg:phone":"+49 9481/90009",
    "sg:postcode":"93102",
    "sg:province":"Bayern",
    "wof:name":"M. Steinberger",
    "wof:placetype":"venue"
},
  "geometry": {"coordinates":[12.41392,48.950169],"type":"Point"}
}