{
  "type": "Feature",
  "properties": {
    "iso:country":"DE",
    "sg:address":"Thailing",
    "sg:city":"Steinh\u00f6ring",
    "sg:postcode":"85643",
    "sg:province":"Bayern",
    "wof:name":"Golfplatz Gut Thailing Hub Gmbh & Co. Besitz Kg",
    "wof:placetype":"venue"
},
  "geometry": {"coordinates":[12.0023097992,48.1126060486],"type":"Point"}
}