{
  "type": "Feature",
  "properties": {
    "iso:country":"DE",
    "sg:address":"An der Stadthalle 7",
    "sg:city":"Baunatal",
    "sg:phone":"+49 561/9491750",
    "sg:postcode":"34225",
    "sg:province":"Hessen",
    "wof:name":"Manfred Bauer",
    "wof:placetype":"venue"
},
  "geometry": {"coordinates":[9.412853241,51.2541046143],"type":"Point"}
}