{
  "type": "Feature",
  "properties": {
    "iso:country":"DE",
    "sg:address":"Frankenfeld 6",
    "sg:city":"Baudenbach",
    "sg:phone":"+49 9164/1078",
    "sg:postcode":"91460",
    "sg:province":"Bayern",
    "wof:name":"Friedrich D\u00fcll",
    "wof:placetype":"venue"
},
  "geometry": {"coordinates":[10.4948043823,49.6309661865],"type":"Point"}
}