{
  "type": "Feature",
  "properties": {
    "iso:country":"DE",
    "sg:address":"Ge\u00dflerstr. 20",
    "sg:city":"Berlin",
    "sg:phone":"+49 30/7884191",
    "sg:postcode":"10829",
    "sg:province":"Berlin",
    "wof:name":"Olgo Gmbh",
    "wof:placetype":"venue"
},
  "geometry": {"coordinates":[13.3654766083,52.486240387],"type":"Point"}
}