{
  "type": "Feature",
  "properties": {
    "iso:country":"DE",
    "sg:address":"J\u00e4gerstr. 12",
    "sg:city":"Bischofsgr\u00fcn",
    "sg:phone":"+49 9276/235",
    "sg:postcode":"95493",
    "sg:province":"Bayern",
    "wof:name":"Hermann Krause",
    "wof:placetype":"venue"
},
  "geometry": {"coordinates":[11.796703,50.050926],"type":"Point"}
}