{
  "type": "Feature",
  "properties": {
    "iso:country":"DE",
    "sg:address":"Altengrodener Weg 65",
    "sg:city":"Wilhelmshaven",
    "sg:postcode":"26389",
    "sg:province":"Niedersachsen",
    "wof:name":"Knauf & Klein Gmbh",
    "wof:placetype":"venue"
},
  "geometry": {"coordinates":[8.080563,53.541473],"type":"Point"}
}