{
  "type": "Feature",
  "properties": {
    "iso:country":"DE",
    "sg:address":"Schlesische Str. 29-30",
    "sg:city":"Berlin",
    "sg:phone":"+49 30/6179920",
    "sg:postcode":"10997",
    "sg:province":"Berlin",
    "wof:name":"Data Archiv Und Management Gmbh",
    "wof:placetype":"venue"
},
  "geometry": {"coordinates":[13.446824,52.498672],"type":"Point"}
}