{
  "type": "Feature",
  "properties": {
    "iso:country":"DE",
    "sg:address":"Kinzigweg 23",
    "sg:city":"K\u00f6ln",
    "sg:phone":"+49 221/606755",
    "sg:postcode":"51061",
    "sg:province":"Nordrhein-Westfalen",
    "wof:name":"Wilhelm Siebert",
    "wof:placetype":"venue"
},
  "geometry": {"coordinates":[7.032134,50.987457],"type":"Point"}
}