{
  "type": "Feature",
  "properties": {
    "iso:country":"DE",
    "sg:address":"Elbestr 26",
    "sg:city":"Friesoythe",
    "sg:phone":"+49 4491/3152",
    "sg:postcode":"26169",
    "sg:province":"Niedersachsen",
    "wof:name":"Rost Maschinenbau Gmbh",
    "wof:placetype":"venue"
},
  "geometry": {"coordinates":[7.84961,53.017872],"type":"Point"}
}