{
  "type": "Feature",
  "properties": {
    "iso:country":"DE",
    "sg:address":"Ackermannstr. 41A",
    "sg:city":"Frankfurt",
    "sg:phone":"+49 69/7580653",
    "sg:postcode":"60326",
    "sg:province":"Hessen",
    "wof:name":"Elektrobau Weimar Gmbh & Co. Kg",
    "wof:placetype":"venue"
},
  "geometry": {"coordinates":[8.625647,50.099953],"type":"Point"}
}