{
  "type": "Feature",
  "properties": {
    "iso:country":"DE",
    "sg:address":"Taunusstr. 45 Haus 1",
    "sg:city":"M\u00fcnchen",
    "sg:postcode":"80807",
    "sg:province":"Bayern",
    "wof:name":"Spedition Berger Gmbh Bernd Hetzel",
    "wof:placetype":"venue"
},
  "geometry": {"coordinates":[11.5730495453,48.182258606],"type":"Point"}
}