{
  "type": "Feature",
  "properties": {
    "iso:country":"DE",
    "sg:address":"In den Helden 12",
    "sg:city":"Drolshagen",
    "sg:phone":"+49 2763/7279",
    "sg:postcode":"57489",
    "sg:province":"Nordrhein-Westfalen",
    "wof:name":"Bernd M\u00fcller",
    "wof:placetype":"venue"
},
  "geometry": {"coordinates":[7.7280340195,51.060459137],"type":"Point"}
}