{
  "type": "Feature",
  "properties": {
    "iso:country":"DE",
    "sg:address":"Schlo\u00dfstr. 14",
    "sg:city":"Marpingen",
    "sg:phone":"+49 6827/1061",
    "sg:postcode":"66646",
    "sg:province":"Saarland",
    "wof:name":"E. Jochum",
    "wof:placetype":"venue"
},
  "geometry": {"coordinates":[7.075938,49.43346],"type":"Point"}
}