{
  "type": "Feature",
  "properties": {
    "iso:country":"DE",
    "sg:address":"D\u00f6rleweg 10",
    "sg:city":"Diedorf",
    "sg:phone":"+49 8238/3185",
    "sg:postcode":"86420",
    "sg:province":"Bayern",
    "wof:name":"Peter Bock Handelsvertretungen Gmbh",
    "wof:placetype":"venue"
},
  "geometry": {"coordinates":[10.7481899261,48.3553695679],"type":"Point"}
}