{
  "type": "Feature",
  "properties": {
    "iso:country":"DE",
    "sg:address":"Seestr. 32",
    "sg:city":"Hagnau",
    "sg:phone":"+49 7532/7570",
    "sg:postcode":"88709",
    "sg:province":"Baden-W\u00fcrttemberg",
    "wof:name":"Reiseverkehrsb\u00fcro Hagnau",
    "wof:placetype":"venue"
},
  "geometry": {"coordinates":[9.3155002594,47.6741294861],"type":"Point"}
}