{
  "type": "Feature",
  "properties": {
    "iso:country":"DE",
    "sg:address":"Speckenstr. 4",
    "sg:city":"Dorum",
    "sg:phone":"+49 4742/92920",
    "sg:postcode":"27632",
    "sg:province":"Niedersachsen",
    "wof:name":"L\u00f6lls Wurster Backhus Gmbh",
    "wof:placetype":"venue"
},
  "geometry": {"coordinates":[8.567671,53.687904],"type":"Point"}
}