{
  "type": "Feature",
  "properties": {
    "iso:country":"DE",
    "sg:address":"Zeil 44",
    "sg:city":"Frankfurt",
    "sg:phone":"+49 69/20411",
    "sg:postcode":"60313",
    "sg:province":"Hessen",
    "wof:name":"Detektiv-lux Gmbh",
    "wof:placetype":"venue"
},
  "geometry": {"coordinates":[8.68897,50.114868],"type":"Point"}
}