{
  "type": "Feature",
  "properties": {
    "iso:country":"DE",
    "sg:address":"Ratiborstr. 23",
    "sg:city":"N\u00fcrnberg",
    "sg:phone":"+49 911/899069",
    "sg:postcode":"90473",
    "sg:province":"Bayern",
    "wof:name":"Ratibor-apotheke",
    "wof:placetype":"venue"
},
  "geometry": {"coordinates":[11.139339,49.401485],"type":"Point"}
}