{
  "type": "Feature",
  "properties": {
    "iso:country":"DE",
    "sg:address":"Vogelsbergstr. 28a",
    "sg:city":"Schotten",
    "sg:phone":"+49 6044/3616",
    "sg:postcode":"63679",
    "sg:province":"Hessen",
    "wof:name":"O. B. Fritzges Immobilinmakler",
    "wof:placetype":"venue"
},
  "geometry": {"coordinates":[9.1132507324,50.4963264465],"type":"Point"}
}