{
  "type": "Feature",
  "properties": {
    "iso:country":"DE",
    "sg:address":"H\u00f6henstr. 41",
    "sg:city":"Burkardroth",
    "sg:phone":"+49 9734/350",
    "sg:postcode":"97705",
    "sg:province":"Bayern",
    "wof:name":"S. Zehe",
    "wof:placetype":"venue"
},
  "geometry": {"coordinates":[9.9795598984,50.2899169922],"type":"Point"}
}