{
  "type": "Feature",
  "properties": {
    "iso:country":"DE",
    "sg:address":"Gr\u00fcner Graben 11",
    "sg:city":"G\u00f6rlitz",
    "sg:phone":"+49 3581/311181",
    "sg:postcode":"02826",
    "sg:province":"Sachsen",
    "wof:name":"Ost-line Logistik Gmbh",
    "wof:placetype":"venue"
},
  "geometry": {"coordinates":[14.9820995331,51.1468505859],"type":"Point"}
}