{
  "type": "Feature",
  "properties": {
    "iso:country":"DE",
    "sg:address":"Flurstr. 4",
    "sg:city":"Reppichau",
    "sg:phone":"+49 34909/71024",
    "sg:postcode":"06386",
    "sg:province":"Sachsen-Anhalt",
    "wof:name":"G\u00f6ring Gmbh",
    "wof:placetype":"venue"
},
  "geometry": {"coordinates":[12.079101,51.811535],"type":"Point"}
}