{
  "type": "Feature",
  "properties": {
    "iso:country":"DE",
    "sg:address":"Kreuzbergstr. 59",
    "sg:city":"Sandberg",
    "sg:phone":"+49 9701/375",
    "sg:postcode":"97657",
    "sg:province":"Bayern",
    "wof:name":"Karl-heinz S\u00f6der Inh. Helma S\u00f6der",
    "wof:placetype":"venue"
},
  "geometry": {"coordinates":[10.006748,50.348892],"type":"Point"}
}