{
  "type": "Feature",
  "properties": {
    "iso:country":"DE",
    "sg:address":"Lennestr. 35",
    "sg:city":"Werdohl",
    "sg:phone":"+49 2392/12345",
    "sg:postcode":"58791",
    "sg:province":"Nordrhein-Westfalen",
    "wof:name":"Willy Klauke Inh. Bernhard Christ",
    "wof:placetype":"venue"
},
  "geometry": {"coordinates":[7.7553877831,51.2559738159],"type":"Point"}
}