{
  "type": "Feature",
  "properties": {
    "iso:country":"DE",
    "sg:address":"F\u00f6hrengasse 37",
    "sg:city":"Neustadt/Do",
    "sg:phone":"+49 171",
    "sg:postcode":"93333",
    "sg:province":"Bayern",
    "wof:name":"Formulavital - Internetmarketing",
    "wof:placetype":"venue"
},
  "geometry": {"coordinates":[11.7629365921,48.7917442322],"type":"Point"}
}