{
  "type": "Feature",
  "properties": {
    "iso:country":"DE",
    "sg:address":"Hafenstr. 109",
    "sg:city":"Bremerhaven",
    "sg:postcode":"27576",
    "sg:province":"Bremen",
    "wof:name":"Hansa Assekuranz- Und Immobilienservice Gmbh",
    "wof:placetype":"venue"
},
  "geometry": {"coordinates":[8.5847530365,53.5569801331],"type":"Point"}
}