{
  "type": "Feature",
  "properties": {
    "iso:country":"DE",
    "sg:address":"Bleichstr. 9",
    "sg:city":"Offenbach",
    "sg:phone":"+49 69/819893",
    "sg:postcode":"63065",
    "sg:province":"Hessen",
    "wof:name":"Buchhandlung An Der Eichen- Dorffschule Inh. G. G\u00fcnther",
    "wof:placetype":"venue"
},
  "geometry": {"coordinates":[8.76282,50.102249],"type":"Point"}
}