{
  "type": "Feature",
  "properties": {
    "iso:country":"DE",
    "sg:address":"Harenberger Str. 24",
    "sg:city":"Hannover",
    "sg:phone":"+49 511/2104795",
    "sg:postcode":"30453",
    "sg:province":"Niedersachsen",
    "wof:name":"Aalto Bauelemente Sonnenschutz E. K.",
    "wof:placetype":"venue"
},
  "geometry": {"coordinates":[9.687184,52.377209],"type":"Point"}
}