{
  "type": "Feature",
  "properties": {
    "iso:country":"DE",
    "sg:address":"Bergisch Gladbacher Str. 626",
    "sg:city":"K\u00f6ln",
    "sg:phone":"+49 221/636180",
    "sg:postcode":"51067",
    "sg:province":"Nordrhein-Westfalen",
    "wof:name":"Christa Wienstroer",
    "wof:placetype":"venue"
},
  "geometry": {"coordinates":[7.0494551659,50.9709777832],"type":"Point"}
}