{
  "type": "Feature",
  "properties": {
    "iso:country":"DE",
    "sg:address":"Augustastr. 15 D",
    "sg:city":"Langenfeld",
    "sg:phone":"+49 2173/80058",
    "sg:postcode":"40764",
    "sg:province":"Nordrhein-Westfalen",
    "wof:name":"Achim Link",
    "wof:placetype":"venue"
},
  "geometry": {"coordinates":[6.9514088631,51.1358566284],"type":"Point"}
}