{
  "type": "Feature",
  "properties": {
    "iso:country":"DE",
    "sg:address":"An der Innerste 5",
    "sg:city":"Langelsheim",
    "sg:phone":"+49 5325/4176",
    "sg:postcode":"38685",
    "sg:province":"Niedersachsen",
    "wof:name":"Ernst Inh. H. Helmut Kleemann",
    "wof:placetype":"venue"
},
  "geometry": {"coordinates":[10.289112,51.875912],"type":"Point"}
}