{
  "type": "Feature",
  "properties": {
    "iso:country":"DE",
    "sg:address":"Aaraustr. 85",
    "sg:city":"Reutlingen",
    "sg:phone":"+49 7121/921921",
    "sg:postcode":"72762",
    "sg:province":"Baden-W\u00fcrttemberg",
    "wof:name":"Dr. L\u00fcetkens Ingenieur",
    "wof:placetype":"venue"
},
  "geometry": {"coordinates":[9.1942186356,48.4891471863],"type":"Point"}
}