{
  "type": "Feature",
  "properties": {
    "iso:country":"DE",
    "sg:address":"Hachborner Str. 46",
    "sg:city":"Ebsdorfergrund",
    "sg:phone":"+49 6424/6700",
    "sg:postcode":"35085",
    "sg:province":"Hessen",
    "wof:name":"Peter Vogel",
    "wof:placetype":"venue"
},
  "geometry": {"coordinates":[8.7880096436,50.7191314697],"type":"Point"}
}