{
  "type": "Feature",
  "properties": {
    "iso:country":"DE",
    "sg:address":"Nordstr. 1",
    "sg:city":"L\u00f6bau",
    "sg:phone":"+49 4935/8586360",
    "sg:postcode":"02708",
    "sg:province":"Sachsen",
    "wof:name":"Steinle Bau Gmbh",
    "wof:placetype":"venue"
},
  "geometry": {"coordinates":[14.668348,51.107063],"type":"Point"}
}