{
  "type": "Feature",
  "properties": {
    "iso:country":"DE",
    "sg:address":"Althener Str. 16",
    "sg:city":"Leipzig",
    "sg:postcode":"04319",
    "sg:province":"Sachsen",
    "wof:name":"Kinderheim St. Gertrud Engelsdorf",
    "wof:placetype":"venue"
},
  "geometry": {"coordinates":[12.4847421646,51.3332023621],"type":"Point"}
}