{
  "type": "Feature",
  "properties": {
    "iso:country":"DE",
    "sg:address":"Siemensstr. 36",
    "sg:city":"Bad Salzuflen",
    "sg:phone":"+49 5222/4514",
    "sg:postcode":"32105",
    "sg:province":"Nordrhein-Westfalen",
    "wof:name":"Reifen-uphoff Gmbh",
    "wof:placetype":"venue"
},
  "geometry": {"coordinates":[8.732257843,52.0874900818],"type":"Point"}
}