{
  "type": "Feature",
  "properties": {
    "iso:country":"DE",
    "sg:address":"Hauptstr. 75",
    "sg:city":"Wingerode",
    "sg:phone":"+49 3605/512079",
    "sg:postcode":"37327",
    "sg:province":"Th\u00fcringen",
    "wof:name":"A. Lerch",
    "wof:placetype":"venue"
},
  "geometry": {"coordinates":[10.2386951447,51.391292572],"type":"Point"}
}