{
  "type": "Feature",
  "properties": {
    "iso:country":"DE",
    "sg:address":"Westpreu\u00dfenweg 3 c",
    "sg:city":"Seevetal",
    "sg:postcode":"21217",
    "sg:province":"Niedersachsen",
    "wof:name":"Arag Versicherung Hans-arno Pauls",
    "wof:placetype":"venue"
},
  "geometry": {"coordinates":[9.9944076538,53.4112167358],"type":"Point"}
}