{
  "type": "Feature",
  "properties": {
    "iso:country":"DE",
    "sg:address":"Preu\u00dfborn 14",
    "sg:city":"L\u00fcdenscheid",
    "sg:phone":"+49 2351/53947",
    "sg:postcode":"58513",
    "sg:province":"Nordrhein-Westfalen",
    "wof:name":"J\u00fcrgen Hymmen",
    "wof:placetype":"venue"
},
  "geometry": {"coordinates":[7.612509,51.246059],"type":"Point"}
}