{
  "type": "Feature",
  "properties": {
    "iso:country":"DE",
    "sg:address":"Buscher Weg 5",
    "sg:city":"Viersen",
    "sg:phone":"+49 2162/55965",
    "sg:postcode":"41751",
    "sg:province":"Nordrhein-Westfalen",
    "wof:name":"Rch Elektronik Gmbh",
    "wof:placetype":"venue"
},
  "geometry": {"coordinates":[6.332985,51.245441],"type":"Point"}
}