{
  "type": "Feature",
  "properties": {
    "iso:country":"DE",
    "sg:address":"Oderstr. 55",
    "sg:city":"Teltow",
    "sg:phone":"+49 3328/471034",
    "sg:postcode":"14513",
    "sg:province":"Brandenburg",
    "wof:name":"Enro Con Gesellschaft F\u00fcr Geotechnik Und Consulting Mbh",
    "wof:placetype":"venue"
},
  "geometry": {"coordinates":[13.2429456711,52.3997001648],"type":"Point"}
}