{
  "type": "Feature",
  "properties": {
    "iso:country":"DE",
    "sg:address":"B\u00f6hringer Str. 2",
    "sg:city":"Grabenstetten",
    "sg:phone":"+49 7382/1817",
    "sg:postcode":"72582",
    "sg:province":"Baden-W\u00fcrttemberg",
    "wof:name":"Ochsenbeck Gmbh",
    "wof:placetype":"venue"
},
  "geometry": {"coordinates":[9.461556,48.523529],"type":"Point"}
}