{
  "type": "Feature",
  "properties": {
    "iso:country":"DE",
    "sg:address":"Br\u00fcninger Weg 10",
    "sg:city":"Ganderkesee",
    "sg:phone":"+49 4222/1028",
    "sg:postcode":"27777",
    "sg:province":"Niedersachsen",
    "wof:name":"Aloys Kl\u00e4ne Steuerbetrater",
    "wof:placetype":"venue"
},
  "geometry": {"coordinates":[8.543885231,53.0384941101],"type":"Point"}
}