{
  "type": "Feature",
  "properties": {
    "iso:country":"DE",
    "sg:address":"Gartenstr. 12",
    "sg:city":"Lastrup",
    "sg:phone":"+49 4472/542",
    "sg:postcode":"49688",
    "sg:province":"Niedersachsen",
    "wof:name":"Paul Rolfes Bauunternehmen Gmbh",
    "wof:placetype":"venue"
},
  "geometry": {"coordinates":[7.859583,52.792019],"type":"Point"}
}