{
  "type": "Feature",
  "properties": {
    "iso:country":"DE",
    "sg:address":"Im Bruche 14",
    "sg:city":"Neustadt",
    "sg:phone":"+49 5034/534",
    "sg:postcode":"31535",
    "sg:province":"Niedersachsen",
    "wof:name":"G\u00fcnter Scharnhorst",
    "wof:placetype":"venue"
},
  "geometry": {"coordinates":[9.3892593384,52.5910987854],"type":"Point"}
}