{
  "type": "Feature",
  "properties": {
    "iso:country":"DE",
    "sg:address":"Markt 8",
    "sg:city":"Bocholt",
    "sg:phone":"+49 2871/970",
    "sg:postcode":"46399",
    "sg:province":"Nordrhein-Westfalen",
    "wof:name":"Stadtsparkasse Bocholt",
    "wof:placetype":"venue"
},
  "geometry": {"coordinates":[6.4989500046,51.8598060608],"type":"Point"}
}