{
  "type": "Feature",
  "properties": {
    "iso:country":"DE",
    "sg:address":"Bachstr. 4",
    "sg:city":"Bad Breisig",
    "sg:phone":"+49 2633/8419",
    "sg:postcode":"53498",
    "sg:province":"Rheinland-Pfalz",
    "wof:name":"Immobilien Wimmer Gmbh",
    "wof:placetype":"venue"
},
  "geometry": {"coordinates":[7.297987,50.509792],"type":"Point"}
}