{
  "type": "Feature",
  "properties": {
    "iso:country":"DE",
    "sg:address":"Raschplatz 11H",
    "sg:city":"Hannover",
    "sg:phone":"+49 511/331221",
    "sg:postcode":"30161",
    "sg:province":"Niedersachsen",
    "wof:name":"Bio-logisch",
    "wof:placetype":"venue"
},
  "geometry": {"coordinates":[9.7441415787,52.3790283203],"type":"Point"}
}