{
  "type": "Feature",
  "properties": {
    "iso:country":"DE",
    "sg:address":"Kern\u00e4ckerstr. 3",
    "sg:city":"Tamm",
    "sg:phone":"+49 7141/607141",
    "sg:postcode":"71732",
    "sg:province":"Baden-W\u00fcrttemberg",
    "wof:name":"Danielle Rauch",
    "wof:placetype":"venue"
},
  "geometry": {"coordinates":[9.1188364029,48.9196739197],"type":"Point"}
}