{
  "type": "Feature",
  "properties": {
    "iso:country":"DE",
    "sg:address":"Am Stadtwald 19",
    "sg:city":"Plauen",
    "sg:phone":"+49 3741/54850",
    "sg:postcode":"08525",
    "sg:province":"Sachsen",
    "wof:name":"W. Maul Kfz-werkstattausr\u00fcstungen",
    "wof:placetype":"venue"
},
  "geometry": {"coordinates":[12.1229362488,50.5178489685],"type":"Point"}
}