{
  "type": "Feature",
  "properties": {
    "iso:country":"DE",
    "sg:address":"Ubbenstr. 22",
    "sg:city":"Hannover",
    "sg:postcode":"30159",
    "sg:province":"Niedersachsen",
    "wof:name":"X-zone Sportmarketing Gmbh",
    "wof:placetype":"venue"
},
  "geometry": {"coordinates":[9.7491731644,52.3717689514],"type":"Point"}
}