{
  "type": "Feature",
  "properties": {
    "iso:country":"DE",
    "sg:address":"Am Funkturm 1",
    "sg:city":"Dortmund",
    "sg:phone":"+49 231/251055",
    "sg:postcode":"44309",
    "sg:province":"Nordrhein-Westfalen",
    "wof:name":"Gds Druck Und Papier Gmbh",
    "wof:placetype":"venue"
},
  "geometry": {"coordinates":[7.5553421974,51.5124320984],"type":"Point"}
}