{
  "type": "Feature",
  "properties": {
    "iso:country":"DE",
    "sg:address":"Uhlandstr. 12 a",
    "sg:city":"Bochum",
    "sg:phone":"+49 234/15613",
    "sg:postcode":"44791",
    "sg:province":"Nordrhein-Westfalen",
    "wof:name":"Wilhelm Tutas",
    "wof:placetype":"venue"
},
  "geometry": {"coordinates":[7.2183017731,51.4860687256],"type":"Point"}
}