{
  "type": "Feature",
  "properties": {
    "iso:country":"DE",
    "sg:address":"Obertal 18",
    "sg:city":"Nassau",
    "sg:phone":"+49 2604/4338",
    "sg:postcode":"56377",
    "sg:province":"Rheinland-Pfalz",
    "wof:name":"Christel Hes",
    "wof:placetype":"venue"
},
  "geometry": {"coordinates":[7.799325,50.314075],"type":"Point"}
}