{
  "type": "Feature",
  "properties": {
    "iso:country":"DE",
    "sg:address":"Fahlheimer Weg 2",
    "sg:city":"Nersingen",
    "sg:phone":"+49 7308/2562",
    "sg:postcode":"89278",
    "sg:province":"Bayern",
    "wof:name":"A. M\u00fcller",
    "wof:placetype":"venue"
},
  "geometry": {"coordinates":[10.135311,48.417622],"type":"Point"}
}