{
  "type": "Feature",
  "properties": {
    "iso:country":"DE",
    "sg:address":"Scherlstr. 2",
    "sg:city":"Leipzig",
    "sg:phone":"+49 341/868300",
    "sg:postcode":"04103",
    "sg:province":"Sachsen",
    "wof:name":"Etl Energietechnik Leipzig Gmbh",
    "wof:placetype":"venue"
},
  "geometry": {"coordinates":[12.3926973343,51.339225769],"type":"Point"}
}