{
  "type": "Feature",
  "properties": {
    "iso:country":"DE",
    "sg:address":"Buschstr. 373",
    "sg:city":"Krefeld",
    "sg:phone":"+49 2151/503367",
    "sg:postcode":"47800",
    "sg:province":"Nordrhein-Westfalen",
    "wof:name":"Buchen-apotheke Herding-eilender Ohg",
    "wof:placetype":"venue"
},
  "geometry": {"coordinates":[6.617782,51.347569],"type":"Point"}
}