{
  "type": "Feature",
  "properties": {
    "iso:country":"DE",
    "sg:address":"Stettiner Str. 61",
    "sg:city":"Ritterhude",
    "sg:phone":"+49 4292/40161",
    "sg:postcode":"27721",
    "sg:province":"Niedersachsen",
    "wof:name":"Drk Deutsches Rotes Kreuz",
    "wof:placetype":"venue"
},
  "geometry": {"coordinates":[8.7486524582,53.1897163391],"type":"Point"}
}