{
  "type": "Feature",
  "properties": {
    "iso:country":"DE",
    "sg:address":"Wolfbertstr. 2",
    "sg:city":"Schwaigern",
    "sg:phone":"+49 7138/920200",
    "sg:postcode":"74193",
    "sg:province":"Baden-W\u00fcrttemberg",
    "wof:name":"Hauck Gmbh",
    "wof:placetype":"venue"
},
  "geometry": {"coordinates":[9.0417098999,49.1405105591],"type":"Point"}
}