{
  "type": "Feature",
  "properties": {
    "iso:country":"DE",
    "sg:address":"Leibnizstr. 22",
    "sg:city":"Berlin",
    "sg:postcode":"10625",
    "sg:province":"Berlin",
    "wof:name":"Albert Kopitzki Gesch\u00e4ftsf\u00fchrungs Gmbh",
    "wof:placetype":"venue"
},
  "geometry": {"coordinates":[13.314622,52.509666],"type":"Point"}
}