{
  "type": "Feature",
  "properties": {
    "iso:country":"DE",
    "sg:address":"Waldweg 1",
    "sg:city":"Gro\u00dfenwiehe",
    "sg:phone":"+49 4604/2155",
    "sg:postcode":"24969",
    "sg:province":"Schleswig-Holstein",
    "wof:name":"T\u00fcchsen",
    "wof:placetype":"venue"
},
  "geometry": {"coordinates":[9.2451372147,54.701259613],"type":"Point"}
}