{
  "type": "Feature",
  "properties": {
    "iso:country":"DE",
    "sg:address":"Junkerrech 34",
    "sg:city":"Idar-Oberstein",
    "sg:postcode":"55743",
    "sg:province":"Rheinland-Pfalz",
    "wof:name":"Spd-birkenfeld - Wir Im Kreis Birkenfeld",
    "wof:placetype":"venue"
},
  "geometry": {"coordinates":[7.387734,49.721237],"type":"Point"}
}