{
  "type": "Feature",
  "properties": {
    "iso:country":"DE",
    "sg:address":"Hauptstr. 40",
    "sg:city":"Gusenburg",
    "sg:phone":"+49 6503/3066",
    "sg:postcode":"54413",
    "sg:province":"Rheinland-Pfalz",
    "wof:name":"Wild Boar",
    "wof:placetype":"venue"
},
  "geometry": {"coordinates":[6.899766922,49.6356315613],"type":"Point"}
}