{
  "type": "Feature",
  "properties": {
    "iso:country":"DE",
    "sg:address":"Dr.-Georg-V\u00f6lkl-Str. 16",
    "sg:city":"Zolling",
    "sg:phone":"+49 8167/8447",
    "sg:postcode":"85406",
    "sg:province":"Bayern",
    "wof:name":"Helmut Kapitza",
    "wof:placetype":"venue"
},
  "geometry": {"coordinates":[11.7093048096,48.4592704773],"type":"Point"}
}