{
  "type": "Feature",
  "properties": {
    "iso:country":"DE",
    "sg:address":"Am Heiligen Kreuz 5a",
    "sg:city":"Nidda",
    "sg:phone":"+49 6043/40168",
    "sg:postcode":"63667",
    "sg:province":"Hessen",
    "wof:name":"H. Rank Gmbh",
    "wof:placetype":"venue"
},
  "geometry": {"coordinates":[9.010368,50.416889],"type":"Point"}
}