{
  "type": "Feature",
  "properties": {
    "iso:country":"DE",
    "sg:address":"Auf der Krautweide 28",
    "sg:city":"Bad Soden",
    "sg:phone":"+49 6196/63061",
    "sg:postcode":"65812",
    "sg:province":"Hessen",
    "wof:name":"Venema-verwaltungs- Gmbh",
    "wof:placetype":"venue"
},
  "geometry": {"coordinates":[8.5125398636,50.1375617981],"type":"Point"}
}