{
  "type": "Feature",
  "properties": {
    "iso:country":"DE",
    "sg:address":"Haldenweg 17",
    "sg:city":"Ochsenhausen",
    "sg:phone":"+49 7352/7535",
    "sg:postcode":"88416",
    "sg:province":"Baden-W\u00fcrttemberg",
    "wof:name":"Rudolf Zell",
    "wof:placetype":"venue"
},
  "geometry": {"coordinates":[9.9286909103,48.0591697693],"type":"Point"}
}