{
  "type": "Feature",
  "properties": {
    "iso:country":"DE",
    "sg:address":"Findorffstr. 2",
    "sg:city":"Grasberg",
    "sg:phone":"+49 4208/1814",
    "sg:postcode":"28879",
    "sg:province":"Niedersachsen",
    "wof:name":"Wilfried Fahrenholz Architekt",
    "wof:placetype":"venue"
},
  "geometry": {"coordinates":[8.985708,53.180908],"type":"Point"}
}