{
  "type": "Feature",
  "properties": {
    "iso:country":"DE",
    "sg:address":"Aletsberger Str. 14",
    "sg:city":"Deggendorf",
    "sg:phone":"+49 991/22017",
    "sg:postcode":"94469",
    "sg:province":"Bayern",
    "wof:name":"Max S\u00fcss Immobilienmakler",
    "wof:placetype":"venue"
},
  "geometry": {"coordinates":[12.9466161728,48.8460159302],"type":"Point"}
}