{
  "type": "Feature",
  "properties": {
    "iso:country":"DE",
    "sg:address":"Breite Str. 2",
    "sg:city":"Allstedt",
    "sg:phone":"+49 34652/421",
    "sg:postcode":"06542",
    "sg:province":"Sachsen-Anhalt",
    "wof:name":"H. M\u00e4rzke",
    "wof:placetype":"venue"
},
  "geometry": {"coordinates":[11.3894147873,51.4040527344],"type":"Point"}
}