{
  "type": "Feature",
  "properties": {
    "iso:country":"DE",
    "sg:address":"Im Rad 20",
    "sg:city":"Wiesbaden",
    "sg:phone":"+49 611/989900",
    "sg:postcode":"65197",
    "sg:province":"Hessen",
    "wof:name":"Druckerei Wurm Gmbh",
    "wof:placetype":"venue"
},
  "geometry": {"coordinates":[8.212812,50.074825],"type":"Point"}
}