{
  "type": "Feature",
  "properties": {
    "iso:country":"DE",
    "sg:address":"Einsiedelstr. 2",
    "sg:city":"Lauchhammer",
    "sg:phone":"+49 3574/892935",
    "sg:postcode":"01979",
    "sg:province":"Brandenburg",
    "wof:name":"Krantec F\u00f6rderger\u00e4teservice Gmbh",
    "wof:placetype":"venue"
},
  "geometry": {"coordinates":[13.7983150482,51.5038337708],"type":"Point"}
}