{
  "type": "Feature",
  "properties": {
    "iso:country":"DE",
    "sg:address":"Am Sportplatz 9",
    "sg:city":"Loburg",
    "sg:phone":"+49 39245/2432",
    "sg:postcode":"39279",
    "sg:province":"Sachsen-Anhalt",
    "wof:name":"Sportlerheim",
    "wof:placetype":"venue"
},
  "geometry": {"coordinates":[12.0836639404,52.1174888611],"type":"Point"}
}