{
  "type": "Feature",
  "properties": {
    "iso:country":"DE",
    "sg:address":"Hinter Der Mauer 4",
    "sg:city":"Rudolstadt",
    "sg:phone":"+49 4936/7242610",
    "sg:postcode":"07407",
    "sg:province":"Th\u00fcringen",
    "wof:name":"Heitlang & Petre Int. Gmbh",
    "wof:placetype":"venue"
},
  "geometry": {"coordinates":[11.3415002823,50.7194747925],"type":"Point"}
}