{
  "type": "Feature",
  "properties": {
    "iso:country":"DE",
    "sg:address":"Aehlenbach 24",
    "sg:city":"Marpingen",
    "sg:phone":"+49 6853/5617",
    "sg:postcode":"66646",
    "sg:province":"Saarland",
    "wof:name":"Bernhard Sauber Rechtsanwalt",
    "wof:placetype":"venue"
},
  "geometry": {"coordinates":[7.0567412376,49.4582557678],"type":"Point"}
}