{
  "type": "Feature",
  "properties": {
    "iso:country":"DE",
    "sg:address":"Wald 9",
    "sg:city":"Riezlern",
    "sg:phone":"+49 8329/5387",
    "sg:postcode":"87567",
    "sg:province":"Bayern",
    "wof:name":"Josef Klauser Architekt",
    "wof:placetype":"venue"
},
  "geometry": {"coordinates":[-106.036148,35.950378],"type":"Point"}
}