{
  "type": "Feature",
  "properties": {
    "iso:country":"DE",
    "sg:address":"Kasholz 3",
    "sg:city":"Wintrich",
    "sg:phone":"+49 6507/701516",
    "sg:postcode":"54487",
    "sg:province":"Rheinland-Pfalz",
    "wof:name":"Bernd Lindgens",
    "wof:placetype":"venue"
},
  "geometry": {"coordinates":[6.976469,49.857185],"type":"Point"}
}