{
  "type": "Feature",
  "properties": {
    "iso:country":"DE",
    "sg:address":"Vogesenstr. 18",
    "sg:city":"M\u00f6rfelden-Walldorf",
    "sg:phone":"+49 6105/946337",
    "sg:postcode":"64546",
    "sg:province":"Hessen",
    "wof:name":"M. B\u00fchner",
    "wof:placetype":"venue"
},
  "geometry": {"coordinates":[8.5666246414,49.9972267151],"type":"Point"}
}