{
  "type": "Feature",
  "properties": {
    "iso:country":"DE",
    "sg:address":"Hofstattstr. 215",
    "sg:city":"V\u00f6lklingen",
    "sg:phone":"+49 6898/21259",
    "sg:postcode":"66333",
    "sg:province":"Saarland",
    "wof:name":"Donnerquelle",
    "wof:placetype":"venue"
},
  "geometry": {"coordinates":[6.8441262245,49.2594833374],"type":"Point"}
}