{
  "type": "Feature",
  "properties": {
    "iso:country":"DE",
    "sg:address":"Hauptstr. 47",
    "sg:city":"M\u00f6gglingen",
    "sg:phone":"+49 7174/227",
    "sg:postcode":"73563",
    "sg:province":"Baden-W\u00fcrttemberg",
    "wof:name":"Walter Weber",
    "wof:placetype":"venue"
},
  "geometry": {"coordinates":[9.96308,48.823029],"type":"Point"}
}