{
  "type": "Feature",
  "properties": {
    "iso:country":"DE",
    "sg:address":"Sch\u00f6neggweg 26",
    "sg:city":"Babenhausen",
    "sg:phone":"+49 8333/8904",
    "sg:postcode":"87727",
    "sg:province":"Bayern",
    "wof:name":"Bader Gmbh",
    "wof:placetype":"venue"
},
  "geometry": {"coordinates":[10.240164,48.1474],"type":"Point"}
}