{
  "type": "Feature",
  "properties": {
    "iso:country":"DE",
    "sg:address":"W\u00fcrselener Str. 37",
    "sg:city":"Stolberg",
    "sg:phone":"+49 2402/25046",
    "sg:postcode":"52222",
    "sg:province":"Nordrhein-Westfalen",
    "wof:name":"Hans-josef Sommer",
    "wof:placetype":"venue"
},
  "geometry": {"coordinates":[6.2095189095,50.7878341675],"type":"Point"}
}