{
  "type": "Feature",
  "properties": {
    "iso:country":"DE",
    "sg:address":"Gr\u00fcneburgweg 102",
    "sg:city":"Frankfurt",
    "sg:phone":"+49 4969/959310",
    "sg:postcode":"60323",
    "sg:province":"Hessen",
    "wof:name":"Willes Gmbh & Co. Kg",
    "wof:placetype":"venue"
},
  "geometry": {"coordinates":[8.665527,50.123322],"type":"Point"}
}