{
  "type": "Feature",
  "properties": {
    "iso:country":"DE",
    "sg:address":"He\u00dfstr. 134",
    "sg:city":"M\u00fcnchen",
    "sg:phone":"+49 89/1214671",
    "sg:postcode":"80797",
    "sg:province":"Bayern",
    "wof:name":"Vestra-papier-streichtechnik- Forschungs- Und",
    "wof:placetype":"venue"
},
  "geometry": {"coordinates":[11.5530023575,48.1580924988],"type":"Point"}
}