{
  "type": "Feature",
  "properties": {
    "iso:country":"DE",
    "sg:address":"Uhlandstr. 86",
    "sg:city":"Berlin",
    "sg:phone":"+49 30/7823084",
    "sg:postcode":"10717",
    "sg:province":"Berlin",
    "wof:name":"Jutta Meyers-reichert Rechtsanw\u00e4ltin Und Notarin",
    "wof:placetype":"venue"
},
  "geometry": {"coordinates":[13.3225450516,52.4889450073],"type":"Point"}
}