{
  "type": "Feature",
  "properties": {
    "iso:country":"DE",
    "sg:address":"Am Predigertor 1",
    "sg:city":"Freiburg",
    "sg:phone":"+49 761/38610",
    "sg:postcode":"79098",
    "sg:province":"Baden-W\u00fcrttemberg",
    "wof:name":"News Net Informationssysteme Gmbh",
    "wof:placetype":"venue"
},
  "geometry": {"coordinates":[7.848224,47.997875],"type":"Point"}
}