{
  "type": "Feature",
  "properties": {
    "iso:country":"DE",
    "sg:address":"Rolandstr. 31",
    "sg:city":"K\u00f6ln",
    "sg:phone":"+49 2203/66550",
    "sg:postcode":"51147",
    "sg:province":"Nordrhein-Westfalen",
    "wof:name":"Manfred Und J\u00f6rg Micklin",
    "wof:placetype":"venue"
},
  "geometry": {"coordinates":[7.1068348885,50.8659210205],"type":"Point"}
}