{
  "type": "Feature",
  "properties": {
    "iso:country":"DE",
    "sg:address":"Adalbertstr. 88",
    "sg:city":"M\u00fcnchen",
    "sg:phone":"+49 89/27818643",
    "sg:postcode":"80799",
    "sg:province":"Bayern",
    "wof:name":"Reinhard Parche Architekt",
    "wof:placetype":"venue"
},
  "geometry": {"coordinates":[11.572505,48.154099],"type":"Point"}
}