{
  "type": "Feature",
  "properties": {
    "iso:country":"DE",
    "sg:address":"Ringstr. 25",
    "sg:city":"Plankstadt",
    "sg:phone":"+49 6202/12209",
    "sg:postcode":"68723",
    "sg:province":"Baden-W\u00fcrttemberg",
    "wof:name":"E. Riedl Steuerberater Und",
    "wof:placetype":"venue"
},
  "geometry": {"coordinates":[8.5917234421,49.3872795105],"type":"Point"}
}