{
  "type": "Feature",
  "properties": {
    "iso:country":"DE",
    "sg:address":"Ro\u00dfmarkt 23",
    "sg:city":"Frankfurt",
    "sg:phone":"+49 69/285064",
    "sg:postcode":"60311",
    "sg:province":"Hessen",
    "wof:name":"Dr. Wolfgang Schmalz Rechtsanwalt Und Notar",
    "wof:placetype":"venue"
},
  "geometry": {"coordinates":[8.6760044098,50.1119728088],"type":"Point"}
}