{
  "type": "Feature",
  "properties": {
    "iso:country":"DE",
    "sg:address":"Spiekerooger Str. 14",
    "sg:city":"Schortens",
    "sg:phone":"+49 4461/80345",
    "sg:postcode":"26419",
    "sg:province":"Niedersachsen",
    "wof:name":"Friedhelm Br\u00f6ske Elektro-bedarfshdl.",
    "wof:placetype":"venue"
},
  "geometry": {"coordinates":[7.924429,53.542522],"type":"Point"}
}