{
  "type": "Feature",
  "properties": {
    "iso:country":"DE",
    "sg:address":"Ostenallee 21",
    "sg:city":"Hamm",
    "sg:phone":"+49 2381/22637",
    "sg:postcode":"59063",
    "sg:province":"Nordrhein-Westfalen",
    "wof:name":"Silvia M\u00f6ller Heilpraktikerin",
    "wof:placetype":"venue"
},
  "geometry": {"coordinates":[7.8283162117,51.6841049194],"type":"Point"}
}