{
  "type": "Feature",
  "properties": {
    "iso:country":"DE",
    "sg:address":"Halberst\u00e4dter Chaussee 18",
    "sg:city":"Magdeburg",
    "sg:phone":"+49 391/6312200",
    "sg:postcode":"39116",
    "sg:province":"Sachsen-Anhalt",
    "wof:name":"H. H\u00e4rtig Ingenieur",
    "wof:placetype":"venue"
},
  "geometry": {"coordinates":[11.5691432953,52.0894165039],"type":"Point"}
}