{
  "type": "Feature",
  "properties": {
    "iso:country":"DE",
    "sg:address":"Schillerstr. 8 a",
    "sg:city":"Ha\u00dfloch",
    "sg:phone":"+49 6324/1709",
    "sg:postcode":"67454",
    "sg:province":"Rheinland-Pfalz",
    "wof:name":"E. Lutz",
    "wof:placetype":"venue"
},
  "geometry": {"coordinates":[8.258653,49.361992],"type":"Point"}
}