{
  "type": "Feature",
  "properties": {
    "iso:country":"DE",
    "sg:address":"Heinrich-Zille-Str. 65",
    "sg:city":"Beckum",
    "sg:phone":"+49 2525/950330",
    "sg:postcode":"59269",
    "sg:province":"Nordrhein-Westfalen",
    "wof:name":"F. Kaldewey Ingenieur",
    "wof:placetype":"venue"
},
  "geometry": {"coordinates":[8.020816803,51.7960205078],"type":"Point"}
}