{
  "type": "Feature",
  "properties": {
    "iso:country":"DE",
    "sg:address":"Damaschkestr. 29",
    "sg:city":"Guben",
    "sg:postcode":"03172",
    "sg:province":"Brandenburg",
    "wof:name":"Allianz Versicherungs Ag",
    "wof:placetype":"venue"
},
  "geometry": {"coordinates":[14.686671257,51.9510345459],"type":"Point"}
}