{
  "type": "Feature",
  "properties": {
    "iso:country":"DE",
    "sg:address":"Loher Str. 12",
    "sg:city":"Bakum",
    "sg:postcode":"49456",
    "sg:province":"Niedersachsen",
    "wof:name":"I. Buchen",
    "wof:placetype":"venue"
},
  "geometry": {"coordinates":[8.19647,52.742458],"type":"Point"}
}