{
  "type": "Feature",
  "properties": {
    "iso:country":"DE",
    "sg:address":"Landstr. 13",
    "sg:city":"Barsinghausen",
    "sg:phone":"+49 5105/82723",
    "sg:postcode":"30890",
    "sg:province":"Niedersachsen",
    "wof:name":"Atg Wohn- Und Gewerbebau Gmbh",
    "wof:placetype":"venue"
},
  "geometry": {"coordinates":[9.490365,52.293205],"type":"Point"}
}