{
  "type": "Feature",
  "properties": {
    "iso:country":"DE",
    "sg:address":"Mengeder Str. 51",
    "sg:city":"L\u00fcnen",
    "sg:phone":"+49 231/877676",
    "sg:postcode":"44536",
    "sg:province":"Nordrhein-Westfalen",
    "wof:name":"Gerhard Herzig",
    "wof:placetype":"venue"
},
  "geometry": {"coordinates":[7.432199955,51.5956535339],"type":"Point"}
}