{
  "type": "Feature",
  "properties": {
    "iso:country":"DE",
    "sg:address":"Bramfelder Chaussee 64",
    "sg:city":"Hamburg",
    "sg:phone":"+49 40/69704299",
    "sg:postcode":"22177",
    "sg:province":"Hamburg",
    "wof:name":"Ronald Seifert Baudienstleistungs Gmbh",
    "wof:placetype":"venue"
},
  "geometry": {"coordinates":[10.0645093918,53.5972671509],"type":"Point"}
}