{
  "type": "Feature",
  "properties": {
    "iso:country":"DE",
    "sg:address":"Bockenheimer Landstr. 9",
    "sg:city":"Frankfurt",
    "sg:phone":"+49 69/722399",
    "sg:postcode":"60325",
    "sg:province":"Hessen",
    "wof:name":"Becker & Klimitz",
    "wof:placetype":"venue"
},
  "geometry": {"coordinates":[8.6696329117,50.1155891418],"type":"Point"}
}