{
  "type": "Feature",
  "properties": {
    "iso:country":"DE",
    "sg:address":"Erbsb\u00fchl 7",
    "sg:city":"Zell",
    "sg:phone":"+49 9257/1370",
    "sg:postcode":"95239",
    "sg:province":"Bayern",
    "wof:name":"Gisela Fanck Garten- Und",
    "wof:placetype":"venue"
},
  "geometry": {"coordinates":[11.80694,50.150921],"type":"Point"}
}