{
  "type": "Feature",
  "properties": {
    "iso:country":"DE",
    "sg:address":"Alter Postweg 64",
    "sg:city":"Stemwede",
    "sg:phone":"+49 5745/2045",
    "sg:postcode":"32351",
    "sg:province":"Nordrhein-Westfalen",
    "wof:name":"Heinrich Katenbrink",
    "wof:placetype":"venue"
},
  "geometry": {"coordinates":[8.538693,52.390846],"type":"Point"}
}