{
  "type": "Feature",
  "properties": {
    "iso:country":"DE",
    "sg:address":"Karmelitenstr. 35-37",
    "sg:city":"W\u00fcrzburg",
    "sg:phone":"+49 931/16666",
    "sg:postcode":"97070",
    "sg:province":"Bayern",
    "wof:name":"Klopf",
    "wof:placetype":"venue"
},
  "geometry": {"coordinates":[9.9270219803,49.795124054],"type":"Point"}
}