{
  "type": "Feature",
  "properties": {
    "iso:country":"DE",
    "sg:address":"T\u00fctingstr. 13",
    "sg:city":"Osnabr\u00fcck",
    "sg:phone":"+49 541/63127",
    "sg:postcode":"49088",
    "sg:province":"Niedersachsen",
    "wof:name":"Michael Selker Steuerberater",
    "wof:placetype":"venue"
},
  "geometry": {"coordinates":[8.0397253036,52.2943572998],"type":"Point"}
}