{
  "type": "Feature",
  "properties": {
    "iso:country":"DE",
    "sg:address":"Amselweg 5",
    "sg:city":"Leezen",
    "sg:phone":"+49 3866/81576",
    "sg:postcode":"19067",
    "sg:province":"Mecklenburg-Vorpommern",
    "wof:name":"Dr. Med. Annedore Drews",
    "wof:placetype":"venue"
},
  "geometry": {"coordinates":[11.493329,53.659016],"type":"Point"}
}