{
  "type": "Feature",
  "properties": {
    "iso:country":"DE",
    "sg:address":"Wendelsteinstr. 2",
    "sg:city":"M\u00fcnchen",
    "sg:phone":"+49 89/227721",
    "sg:postcode":"81541",
    "sg:province":"Bayern",
    "wof:name":"Rudolf Weiss Rechtsanwalt",
    "wof:placetype":"venue"
},
  "geometry": {"coordinates":[11.5812416077,48.1164932251],"type":"Point"}
}