{
  "type": "Feature",
  "properties": {
    "iso:country":"DE",
    "sg:address":"Allersbergstr. 2",
    "sg:city":"Neubrunn",
    "sg:phone":"+49 9307/99234",
    "sg:postcode":"97277",
    "sg:province":"Bayern",
    "wof:name":"W. F\u00f6rsch",
    "wof:placetype":"venue"
},
  "geometry": {"coordinates":[9.6690254211,49.7335624695],"type":"Point"}
}