{
  "type": "Feature",
  "properties": {
    "iso:country":"DE",
    "sg:address":"Erikapfad 42",
    "sg:city":"Krefeld",
    "sg:phone":"+49 2151/395073",
    "sg:postcode":"47804",
    "sg:province":"Nordrhein-Westfalen",
    "wof:name":"Cafe-klatsch",
    "wof:placetype":"venue"
},
  "geometry": {"coordinates":[6.5047168732,51.3055801392],"type":"Point"}
}