{
  "type": "Feature",
  "properties": {
    "iso:country":"DE",
    "sg:address":"Herriedener Str. 38 b",
    "sg:city":"N\u00fcrnberg",
    "sg:phone":"+49 911/684484",
    "sg:postcode":"90449",
    "sg:province":"Bayern",
    "wof:name":"Noris-repro Gmbh",
    "wof:placetype":"venue"
},
  "geometry": {"coordinates":[11.0236339569,49.42004776],"type":"Point"}
}