{
  "type": "Feature",
  "properties": {
    "iso:country":"DE",
    "sg:address":"Kronacher Str. 5",
    "sg:city":"Naila",
    "sg:phone":"+49 9282/963990",
    "sg:postcode":"95119",
    "sg:province":"Bayern",
    "wof:name":"Monika Hoffmann",
    "wof:placetype":"venue"
},
  "geometry": {"coordinates":[11.7094802856,50.3286476135],"type":"Point"}
}