{
  "type": "Feature",
  "properties": {
    "iso:country":"DE",
    "sg:address":"Wickeder Hellweg 105",
    "sg:city":"Dortmund",
    "sg:phone":"+49 231/213443",
    "sg:postcode":"44319",
    "sg:province":"Nordrhein-Westfalen",
    "wof:name":"Brigitte Bartholome",
    "wof:placetype":"venue"
},
  "geometry": {"coordinates":[7.6120939255,51.532371521],"type":"Point"}
}