{
  "type": "Feature",
  "properties": {
    "iso:country":"DE",
    "sg:address":"Wolferter Weg 33",
    "sg:city":"Hellenthal",
    "sg:phone":"+49 2448/1477",
    "sg:postcode":"53940",
    "sg:province":"Nordrhein-Westfalen",
    "wof:name":"Vereinskartell Wolfert Karl Heup",
    "wof:placetype":"venue"
},
  "geometry": {"coordinates":[6.4671502113,50.4434089661],"type":"Point"}
}