{
  "type": "Feature",
  "properties": {
    "iso:country":"DE",
    "sg:address":"Ernteweg 10",
    "sg:city":"Mendig",
    "sg:postcode":"56743",
    "sg:province":"Rheinland-Pfalz",
    "wof:name":"Manufaktur Lappe Gmbh & Co. Kg",
    "wof:placetype":"venue"
},
  "geometry": {"coordinates":[7.2564888,50.3759841919],"type":"Point"}
}