{
  "type": "Feature",
  "properties": {
    "iso:country":"DE",
    "sg:address":"Im Wiesengrund 21",
    "sg:city":"Braunlage",
    "sg:phone":"+49 5520/2553",
    "sg:postcode":"38700",
    "sg:province":"Niedersachsen",
    "wof:name":"K. Farin",
    "wof:placetype":"venue"
},
  "geometry": {"coordinates":[10.6044139862,51.7264328003],"type":"Point"}
}