{
  "type": "Feature",
  "properties": {
    "iso:country":"DE",
    "sg:address":"Elsdorfer Str. 9",
    "sg:city":"Fockbek",
    "sg:phone":"+49 4331/62266",
    "sg:postcode":"24787",
    "sg:province":"Schleswig-Holstein",
    "wof:name":"Ernst Potthast Architektur Gmbh",
    "wof:placetype":"venue"
},
  "geometry": {"coordinates":[9.597464,54.301533],"type":"Point"}
}