{
  "type": "Feature",
  "properties": {
    "iso:country":"DE",
    "sg:address":"Wittestr. 46",
    "sg:city":"Berlin",
    "sg:phone":"+49 30/4023061",
    "sg:postcode":"13509",
    "sg:province":"Berlin",
    "wof:name":"Duscheleit & Sohn Verwaltungs Gmbh",
    "wof:placetype":"venue"
},
  "geometry": {"coordinates":[13.305164,52.577518],"type":"Point"}
}