{
  "type": "Feature",
  "properties": {
    "iso:country":"DE",
    "sg:address":"Am Kamp 4",
    "sg:city":"M\u00f6nkebude",
    "sg:phone":"+49 39774/29851",
    "sg:postcode":"17375",
    "sg:province":"Mecklenburg-Vorpommern",
    "wof:name":"V. Lieckfeld",
    "wof:placetype":"venue"
},
  "geometry": {"coordinates":[13.968685,53.768742],"type":"Point"}
}