{
  "type": "Feature",
  "properties": {
    "iso:country":"DE",
    "sg:address":"Volkhartstr. 11",
    "sg:city":"Augsburg",
    "sg:phone":"+49 821/515654",
    "sg:postcode":"86152",
    "sg:province":"Bayern",
    "wof:name":"Erich M\u00e4rkl",
    "wof:placetype":"venue"
},
  "geometry": {"coordinates":[10.8899393082,48.3708992004],"type":"Point"}
}