{
  "type": "Feature",
  "properties": {
    "iso:country":"DE",
    "sg:address":"Friedrichsplatz 2",
    "sg:city":"Bruchsal",
    "sg:phone":"+49 7251/83878",
    "sg:postcode":"76646",
    "sg:province":"Baden-W\u00fcrttemberg",
    "wof:name":"C. Fox",
    "wof:placetype":"venue"
},
  "geometry": {"coordinates":[8.59561,49.124695],"type":"Point"}
}