{
  "type": "Feature",
  "properties": {
    "iso:country":"DE",
    "sg:address":"Breslauer Str. 7",
    "sg:city":"Isernhagen",
    "sg:phone":"+49 5139/279370",
    "sg:postcode":"30916",
    "sg:province":"Niedersachsen",
    "wof:name":"Marktplatz Des Vikingnet",
    "wof:placetype":"venue"
},
  "geometry": {"coordinates":[9.8901834488,52.4673500061],"type":"Point"}
}