{
  "type": "Feature",
  "properties": {
    "iso:country":"DE",
    "sg:address":"Peterstr. 81",
    "sg:city":"Wilhelmshaven",
    "sg:phone":"+49 4421/22351",
    "sg:postcode":"26382",
    "sg:province":"Niedersachsen",
    "wof:name":"Restaurant Tutta Italia",
    "wof:placetype":"venue"
},
  "geometry": {"coordinates":[8.1037740707,53.5226135254],"type":"Point"}
}