{
  "type": "Feature",
  "properties": {
    "iso:country":"DE",
    "sg:address":"Georgstr. 8",
    "sg:city":"Bad Zwischenahn",
    "sg:phone":"+49 4403/92840",
    "sg:postcode":"26160",
    "sg:province":"Niedersachsen",
    "wof:name":"D. Bosse",
    "wof:placetype":"venue"
},
  "geometry": {"coordinates":[8.0086746216,53.1822929382],"type":"Point"}
}