{
  "type": "Feature",
  "properties": {
    "iso:country":"DE",
    "sg:address":"Custorstr. 17",
    "sg:city":"Bornheim",
    "sg:phone":"+49 2222/2157",
    "sg:postcode":"53332",
    "sg:province":"Nordrhein-Westfalen",
    "wof:name":"Agro-technik Dr. G. Haronska E. K.",
    "wof:placetype":"venue"
},
  "geometry": {"coordinates":[7.011044,50.757427],"type":"Point"}
}