{
  "type": "Feature",
  "properties": {
    "iso:country":"DE",
    "sg:address":"F\u00e4hrstr. 78",
    "sg:city":"Hamburg",
    "sg:phone":"+49 40/7526512",
    "sg:postcode":"21107",
    "sg:province":"Hamburg",
    "wof:name":"Gastst\u00e4tte Ritter-st\u00fcbl",
    "wof:placetype":"venue"
},
  "geometry": {"coordinates":[9.983215332,53.5166168213],"type":"Point"}
}