{
  "type": "Feature",
  "properties": {
    "iso:country":"DE",
    "sg:address":"Hildenbrandseck",
    "sg:city":"Neustadt",
    "sg:phone":"+49 6321/6181",
    "sg:postcode":"67435",
    "sg:province":"Rheinland-Pfalz",
    "wof:name":"Dr. H. Wolf Weinanbau",
    "wof:placetype":"venue"
},
  "geometry": {"coordinates":[8.1636199951,49.3847007751],"type":"Point"}
}