{
  "type": "Feature",
  "properties": {
    "iso:country":"DE",
    "sg:address":"Wettergasse 1",
    "sg:city":"Marburg",
    "sg:phone":"+49 6421/26977",
    "sg:postcode":"35037",
    "sg:province":"Hessen",
    "wof:name":"Paletti",
    "wof:placetype":"venue"
},
  "geometry": {"coordinates":[8.771369,50.809429],"type":"Point"}
}