{
  "type": "Feature",
  "properties": {
    "iso:country":"DE",
    "sg:address":"Atelierstr. 1",
    "sg:city":"Neubrandenburg",
    "sg:phone":"+49 395/4212362",
    "sg:postcode":"17034",
    "sg:province":"Mecklenburg-Vorpommern",
    "wof:name":"Buch Und Medien Gmbh",
    "wof:placetype":"venue"
},
  "geometry": {"coordinates":[13.2742166519,53.5747528076],"type":"Point"}
}