{
  "type": "Feature",
  "properties": {
    "iso:country":"DE",
    "sg:address":"Friedrich-Koenig-Str. 7",
    "sg:city":"Mainz",
    "sg:phone":"+49 6131/580896",
    "sg:postcode":"55129",
    "sg:province":"Rheinland-Pfalz",
    "wof:name":"Reck Gmbh",
    "wof:placetype":"venue"
},
  "geometry": {"coordinates":[8.268417,49.970261],"type":"Point"}
}