{
  "type": "Feature",
  "properties": {
    "iso:country":"DE",
    "sg:address":"Frankfurter Str. 39-45",
    "sg:city":"Offenbach",
    "sg:phone":"+49 69/82366804",
    "sg:postcode":"63065",
    "sg:province":"Hessen",
    "wof:name":"E-plus Shop",
    "wof:placetype":"venue"
},
  "geometry": {"coordinates":[8.7602567673,50.1050605774],"type":"Point"}
}