{
  "type": "Feature",
  "properties": {
    "iso:country":"DE",
    "sg:address":"Gro\u00dfe Elbstr. 145 d",
    "sg:city":"Hamburg",
    "sg:phone":"+49 40/254420",
    "sg:postcode":"22767",
    "sg:province":"Hamburg",
    "wof:name":"Dr. Wolf Und Partner",
    "wof:placetype":"venue"
},
  "geometry": {"coordinates":[9.9345388412,53.5445709229],"type":"Point"}
}