{
  "type": "Feature",
  "properties": {
    "iso:country":"DE",
    "sg:address":"T\u00f6lzer Str. 25",
    "sg:city":"Egling",
    "sg:phone":"+49 8176/7130",
    "sg:postcode":"82544",
    "sg:province":"Bayern",
    "wof:name":"Michael Thalhammer Jun.",
    "wof:placetype":"venue"
},
  "geometry": {"coordinates":[11.511618,47.914093],"type":"Point"}
}