{
  "type": "Feature",
  "properties": {
    "iso:country":"DE",
    "sg:address":"Parkstr. 10",
    "sg:city":"Bad Salzuflen",
    "sg:phone":"+49 5222/16022",
    "sg:postcode":"32105",
    "sg:province":"Nordrhein-Westfalen",
    "wof:name":"Park-apotheke Dr. Manfred Hannig",
    "wof:placetype":"venue"
},
  "geometry": {"coordinates":[8.746573,52.086575],"type":"Point"}
}