{
  "type": "Feature",
  "properties": {
    "iso:country":"DE",
    "sg:address":"Im Hauser Feld 19",
    "sg:city":"Neustetten",
    "sg:phone":"+49 7472/917980",
    "sg:postcode":"72149",
    "sg:province":"Baden-W\u00fcrttemberg",
    "wof:name":"Artax Lackieranlagen Gmbh",
    "wof:placetype":"venue"
},
  "geometry": {"coordinates":[8.873633,48.481899],"type":"Point"}
}