{
  "type": "Feature",
  "properties": {
    "iso:country":"DE",
    "sg:address":"D\u00f6rpfelderh\u00f6he 10",
    "sg:city":"H\u00fcckeswagen",
    "sg:postcode":"42499",
    "sg:province":"Nordrhein-Westfalen",
    "wof:name":"Gunia Kommunikations- Management Gmbh",
    "wof:placetype":"venue"
},
  "geometry": {"coordinates":[7.2901911736,51.1277923584],"type":"Point"}
}