{
  "type": "Feature",
  "properties": {
    "iso:country":"DE",
    "sg:address":"Angerstr. 3",
    "sg:city":"Ebermannstadt",
    "sg:phone":"+49 9194/5405",
    "sg:postcode":"91320",
    "sg:province":"Bayern",
    "wof:name":"Frank Und Simone Vaupel",
    "wof:placetype":"venue"
},
  "geometry": {"coordinates":[11.1446561813,49.7813720703],"type":"Point"}
}