{
  "type": "Feature",
  "properties": {
    "iso:country":"DE",
    "sg:address":"In den Birken\u00e4ckern 14",
    "sg:city":"Darmstadt",
    "sg:phone":"+49 6150/6526",
    "sg:postcode":"64291",
    "sg:province":"Hessen",
    "wof:name":"Wilhelm Fischer",
    "wof:placetype":"venue"
},
  "geometry": {"coordinates":[8.6466264725,49.9339942932],"type":"Point"}
}