{
  "type": "Feature",
  "properties": {
    "iso:country":"DE",
    "sg:address":"Hildebrandstr 16",
    "sg:city":"Dortmund",
    "sg:phone":"+49 231/217007",
    "sg:postcode":"44319",
    "sg:province":"Nordrhein-Westfalen",
    "wof:name":"Sehlke Gesellschaft F\u00fcr Elektrotechnik Mbh",
    "wof:placetype":"venue"
},
  "geometry": {"coordinates":[7.6266,51.530842],"type":"Point"}
}