{
  "type": "Feature",
  "properties": {
    "iso:country":"DE",
    "sg:address":"Hauptstr. 26",
    "sg:city":"Tutzing",
    "sg:phone":"+49 8158/2077",
    "sg:postcode":"82327",
    "sg:province":"Bayern",
    "wof:name":"Peter Gsinn",
    "wof:placetype":"venue"
},
  "geometry": {"coordinates":[11.2800683975,47.9080963135],"type":"Point"}
}