{
  "type": "Feature",
  "properties": {
    "iso:country":"DE",
    "sg:address":"Asternstr. 34",
    "sg:city":"Hannover",
    "sg:phone":"+49 511/717060",
    "sg:postcode":"30167",
    "sg:province":"Niedersachsen",
    "wof:name":"Terminal",
    "wof:placetype":"venue"
},
  "geometry": {"coordinates":[9.719417572,52.3859291077],"type":"Point"}
}