{
  "type": "Feature",
  "properties": {
    "iso:country":"DE",
    "sg:address":"M\u00fcnchener Str. 55",
    "sg:city":"Grafing",
    "sg:phone":"+49 8092/70220",
    "sg:postcode":"85567",
    "sg:province":"Bayern",
    "wof:name":"Lbv Betriebsanlagen Verwaltungs Gmbh & Co.",
    "wof:placetype":"venue"
},
  "geometry": {"coordinates":[11.907346,48.020782],"type":"Point"}
}