{
  "type": "Feature",
  "properties": {
    "iso:country":"DE",
    "sg:address":"Zum Runden Bruch 1",
    "sg:city":"Uelzen",
    "sg:phone":"+49 581/42848",
    "sg:postcode":"29525",
    "sg:province":"Niedersachsen",
    "wof:name":"Wilhelm B\u00f6rchers",
    "wof:placetype":"venue"
},
  "geometry": {"coordinates":[10.592919,52.975449],"type":"Point"}
}