{
  "type": "Feature",
  "properties": {
    "iso:country":"DE",
    "sg:address":"Kochstr. 16",
    "sg:city":"Berlin",
    "sg:phone":"+49 30/2519108",
    "sg:postcode":"10969",
    "sg:province":"Berlin",
    "wof:name":"Badaro-steakhaus",
    "wof:placetype":"venue"
},
  "geometry": {"coordinates":[13.3897666931,52.5068054199],"type":"Point"}
}