{
  "type": "Feature",
  "properties": {
    "iso:country":"DE",
    "sg:address":"Benzstr. 4",
    "sg:city":"Miltenberg",
    "sg:postcode":"63897",
    "sg:province":"Bayern",
    "wof:name":"Khz W\u00e4sche-service Gmbh",
    "wof:placetype":"venue"
},
  "geometry": {"coordinates":[9.247725,49.709351],"type":"Point"}
}