{
  "type": "Feature",
  "properties": {
    "iso:country":"DE",
    "sg:address":"Bergstr. 30",
    "sg:city":"Stemwede",
    "sg:phone":"+49 5773/410",
    "sg:postcode":"32351",
    "sg:province":"Nordrhein-Westfalen",
    "wof:name":"Heinz Kr\u00fcger",
    "wof:placetype":"venue"
},
  "geometry": {"coordinates":[8.453852,52.442852],"type":"Point"}
}