{
  "type": "Feature",
  "properties": {
    "iso:country":"DE",
    "sg:address":"Am Hagenblech 40",
    "sg:city":"Winterberg",
    "sg:phone":"+49 2981/530",
    "sg:postcode":"59955",
    "sg:province":"Nordrhein-Westfalen",
    "wof:name":"Dollberg",
    "wof:placetype":"venue"
},
  "geometry": {"coordinates":[8.532089,51.200726],"type":"Point"}
}