{
  "type": "Feature",
  "properties": {
    "iso:country":"DE",
    "sg:address":"Schl\u00fcsselstr. 18",
    "sg:city":"Neuenburg",
    "sg:phone":"+49 7631/73883",
    "sg:postcode":"79395",
    "sg:province":"Baden-W\u00fcrttemberg",
    "wof:name":"H. Boll Drogerie",
    "wof:placetype":"venue"
},
  "geometry": {"coordinates":[7.56117,47.813801],"type":"Point"}
}