{
  "type": "Feature",
  "properties": {
    "iso:country":"DE",
    "sg:address":"Kirchstr. 9",
    "sg:city":"Fuldatal",
    "sg:phone":"+49 561/813590",
    "sg:postcode":"34233",
    "sg:province":"Hessen",
    "wof:name":"Klaus Schweinsberg",
    "wof:placetype":"venue"
},
  "geometry": {"coordinates":[9.516746,51.369625],"type":"Point"}
}