{
  "type": "Feature",
  "properties": {
    "iso:country":"DE",
    "sg:address":"Ueckerstr. 117",
    "sg:city":"Ueckerm\u00fcnde",
    "sg:postcode":"17373",
    "sg:province":"Mecklenburg-Vorpommern",
    "wof:name":"R & S Handelsgesellschaft Mbh",
    "wof:placetype":"venue"
},
  "geometry": {"coordinates":[14.0484790802,53.7351799011],"type":"Point"}
}