{
  "type": "Feature",
  "properties": {
    "iso:country":"DE",
    "sg:address":"Waldstr. 3",
    "sg:city":"Bad Wildbad",
    "sg:phone":"+49 7081/6147",
    "sg:postcode":"75323",
    "sg:province":"Baden-W\u00fcrttemberg",
    "wof:name":"F. Pro\u00df",
    "wof:placetype":"venue"
},
  "geometry": {"coordinates":[8.5739622116,48.782951355],"type":"Point"}
}