{
  "type": "Feature",
  "properties": {
    "iso:country":"DE",
    "sg:address":"Goetheallee 18",
    "sg:city":"Dresden",
    "sg:phone":"+49 69/263130",
    "sg:postcode":"01309",
    "sg:province":"Sachsen",
    "wof:name":"Dresdnerbank Investment Management Kapitalanlage- Gmbh",
    "wof:placetype":"venue"
},
  "geometry": {"coordinates":[8.669595,50.107784],"type":"Point"}
}