{
  "type": "Feature",
  "properties": {
    "iso:country":"DE",
    "sg:address":"Schepersweg 71",
    "sg:city":"Wesel",
    "sg:phone":"+49 281/468571",
    "sg:postcode":"46485",
    "sg:province":"Nordrhein-Westfalen",
    "wof:name":"Ralf Stodtmeister",
    "wof:placetype":"venue"
},
  "geometry": {"coordinates":[6.640365,51.664265],"type":"Point"}
}