{
  "type": "Feature",
  "properties": {
    "iso:country":"DE",
    "sg:address":"Rotdornweg 6",
    "sg:city":"Wermelskirchen",
    "sg:phone":"+49 2196/3871",
    "sg:postcode":"42929",
    "sg:province":"Nordrhein-Westfalen",
    "wof:name":"W. Gerding Ingenieur",
    "wof:placetype":"venue"
},
  "geometry": {"coordinates":[7.21983,51.129539],"type":"Point"}
}