{
  "type": "Feature",
  "properties": {
    "iso:country":"DE",
    "sg:address":"Seestr. 32",
    "sg:city":"Pl\u00f6n",
    "sg:phone":"+49 4522/4083",
    "sg:postcode":"24306",
    "sg:province":"Schleswig-Holstein",
    "wof:name":"Pvg Handels-gmbh",
    "wof:placetype":"venue"
},
  "geometry": {"coordinates":[10.406292,54.155563],"type":"Point"}
}