{
  "type": "Feature",
  "properties": {
    "iso:country":"DE",
    "sg:address":"Bachstr. 12",
    "sg:city":"Oppach",
    "sg:phone":"+49 35872/32093",
    "sg:postcode":"02736",
    "sg:province":"Sachsen",
    "wof:name":"Rudolf Neumann",
    "wof:placetype":"venue"
},
  "geometry": {"coordinates":[14.4997348785,51.0581893921],"type":"Point"}
}