{
  "type": "Feature",
  "properties": {
    "iso:country":"DE",
    "sg:address":"Breite Gasse 32",
    "sg:city":"N\u00fcrnberg",
    "sg:phone":"+49 911/2405969",
    "sg:postcode":"90402",
    "sg:province":"Bayern",
    "wof:name":"Framode Gmbh",
    "wof:placetype":"venue"
},
  "geometry": {"coordinates":[11.075566,49.450165],"type":"Point"}
}