{
  "type": "Feature",
  "properties": {
    "iso:country":"DE",
    "sg:address":"Kirchstr. 40",
    "sg:city":"Baesweiler",
    "sg:postcode":"52499",
    "sg:province":"Nordrhein-Westfalen",
    "wof:name":"China-restaurant Rosengarden",
    "wof:placetype":"venue"
},
  "geometry": {"coordinates":[6.1840109825,50.9060554504],"type":"Point"}
}