{
  "type": "Feature",
  "properties": {
    "iso:country":"DE",
    "sg:address":"ErfurterStra\u00dfe 9",
    "sg:city":"Bad Frankenhausen",
    "sg:phone":"+49 34671/62432",
    "sg:postcode":"06567",
    "sg:province":"Th\u00fcringen",
    "wof:name":"Weinlokal Zum Schwan .- Bad Frankenhausen",
    "wof:placetype":"venue"
},
  "geometry": {"coordinates":[11.101258,51.357498],"type":"Point"}
}