{
  "type": "Feature",
  "properties": {
    "iso:country":"DE",
    "sg:address":"Ronnenberger Str 15",
    "sg:city":"Gehrden",
    "sg:phone":"+49 5108/92910",
    "sg:postcode":"30989",
    "sg:province":"Niedersachsen",
    "wof:name":"Repac Montagetechnik Gmbh & Co Kg",
    "wof:placetype":"venue"
},
  "geometry": {"coordinates":[9.609039,52.314808],"type":"Point"}
}