{
  "type": "Feature",
  "properties": {
    "iso:country":"DE",
    "sg:address":"Mellenbergstr 40",
    "sg:city":"Alsfeld",
    "sg:phone":"+49 6631/3442",
    "sg:postcode":"36304",
    "sg:province":"Hessen",
    "wof:name":"Spedition Arnold",
    "wof:placetype":"venue"
},
  "geometry": {"coordinates":[9.27292,50.76009],"type":"Point"}
}