{
  "type": "Feature",
  "properties": {
    "iso:country":"DE",
    "sg:address":"Mackenbacher Str. 23",
    "sg:city":"Ramstein-Miesenbach",
    "sg:phone":"+49 6371/58915",
    "sg:postcode":"66877",
    "sg:province":"Rheinland-Pfalz",
    "wof:name":"Joachim Marschall",
    "wof:placetype":"venue"
},
  "geometry": {"coordinates":[7.55818,49.466324],"type":"Point"}
}