{
  "type": "Feature",
  "properties": {
    "iso:country":"DE",
    "sg:address":"Birkenstr. 102",
    "sg:city":"Hiddenhausen",
    "sg:phone":"+49 5221/347223",
    "sg:postcode":"32120",
    "sg:province":"Nordrhein-Westfalen",
    "wof:name":"Hempelmann",
    "wof:placetype":"venue"
},
  "geometry": {"coordinates":[8.618379,52.133484],"type":"Point"}
}