{
  "type": "Feature",
  "properties": {
    "iso:country":"DE",
    "sg:address":"Am Kahlenberg 1",
    "sg:city":"Callenberg",
    "sg:phone":"+49 37608/3983",
    "sg:postcode":"09337",
    "sg:province":"Sachsen",
    "wof:name":"B\u00f6hms Gastst\u00e4tte",
    "wof:placetype":"venue"
},
  "geometry": {"coordinates":[12.6310348511,50.8442802429],"type":"Point"}
}