{
  "type": "Feature",
  "properties": {
    "iso:country":"DE",
    "sg:address":"Jahnstr 18",
    "sg:city":"Rednitzhembach",
    "sg:phone":"+49 6172/7890",
    "sg:postcode":"91126",
    "sg:province":"Bayern",
    "wof:name":"Tse Technical & Scientific Equipment Gmbh",
    "wof:placetype":"venue"
},
  "geometry": {"coordinates":[8.56321,50.250431],"type":"Point"}
}