{
  "type": "Feature",
  "properties": {
    "iso:country":"DE",
    "sg:address":"Eberhardstr. 13",
    "sg:city":"Remscheid",
    "sg:phone":"+49 2191/26744",
    "sg:postcode":"42853",
    "sg:province":"Nordrhein-Westfalen",
    "wof:name":"C. Pferdek\u00e4mper & A. Reu\u00dfer",
    "wof:placetype":"venue"
},
  "geometry": {"coordinates":[7.182597,51.188076],"type":"Point"}
}