{
  "type": "Feature",
  "properties": {
    "iso:country":"DE",
    "sg:address":"Gleiwitzer Str. 55",
    "sg:city":"Erding",
    "sg:phone":"+49 8122/91996",
    "sg:postcode":"85435",
    "sg:province":"Bayern",
    "wof:name":"Christa Perleb, Marketing - Werbekonzeption",
    "wof:placetype":"venue"
},
  "geometry": {"coordinates":[11.898057,48.301407],"type":"Point"}
}