{
  "type": "Feature",
  "properties": {
    "iso:country":"DE",
    "sg:address":"Rudolf Str. 8a",
    "sg:city":"Pforzheim",
    "sg:phone":"+49 7231",
    "sg:postcode":"75177",
    "sg:province":"Baden-W\u00fcrttemberg",
    "wof:name":"Tec Automogildesign Gmbh",
    "wof:placetype":"venue"
},
  "geometry": {"coordinates":[8.6993198395,48.8949928284],"type":"Point"}
}