{
  "type": "Feature",
  "properties": {
    "iso:country":"DE",
    "sg:address":"Am Uhrturm 22h",
    "sg:city":"Hannover",
    "sg:postcode":"30519",
    "sg:province":"Niedersachsen",
    "wof:name":"Preiss Gmbh",
    "wof:placetype":"venue"
},
  "geometry": {"coordinates":[9.7624378204,52.3324279785],"type":"Point"}
}