{
  "type": "Feature",
  "properties": {
    "iso:country":"DE",
    "sg:address":"Friedrich-Engels-Str.",
    "sg:city":"Schwerin",
    "sg:postcode":"19061",
    "sg:province":"Mecklenburg-Vorpommern",
    "wof:name":"Bibliothek Zweigstelle",
    "wof:placetype":"venue"
},
  "geometry": {"coordinates":[11.431595,53.604263],"type":"Point"}
}