{
  "type": "Feature",
  "properties": {
    "iso:country":"DE",
    "sg:address":"Lindenstr. 5",
    "sg:city":"G\u00fcllesheim",
    "sg:phone":"+49 2687/8436",
    "sg:postcode":"56593",
    "sg:province":"Rheinland-Pfalz",
    "wof:name":"A. Schmitt",
    "wof:placetype":"venue"
},
  "geometry": {"coordinates":[7.5281319618,50.5994338989],"type":"Point"}
}