{
  "type": "Feature",
  "properties": {
    "iso:country":"DE",
    "sg:address":"Hauptstr. 35",
    "sg:city":"Weisenbach",
    "sg:phone":"+49 4972/242766",
    "sg:postcode":"76599",
    "sg:province":"Baden-W\u00fcrttemberg",
    "wof:name":"Volksbank Baden-baden-rastatt Eg",
    "wof:placetype":"venue"
},
  "geometry": {"coordinates":[8.353905,48.727398],"type":"Point"}
}