{
  "type": "Feature",
  "properties": {
    "iso:country":"DE",
    "sg:address":"Moltkestr. 31",
    "sg:city":"Berlin",
    "sg:phone":"+49 30/8342013",
    "sg:postcode":"12203",
    "sg:province":"Berlin",
    "wof:name":"M. Metzner Und M. A. Klein Rechtsanw\u00e4lte Und Notar",
    "wof:placetype":"venue"
},
  "geometry": {"coordinates":[13.3157091141,52.4407501221],"type":"Point"}
}