{
  "type": "Feature",
  "properties": {
    "iso:country":"DE",
    "sg:address":"Turnstr. 5",
    "sg:city":"Haan",
    "sg:phone":"+49 212/96858",
    "sg:postcode":"42781",
    "sg:province":"Nordrhein-Westfalen",
    "wof:name":"Hokus Pokus",
    "wof:placetype":"venue"
},
  "geometry": {"coordinates":[7.0141849518,51.1929588318],"type":"Point"}
}