{
  "type": "Feature",
  "properties": {
    "iso:country":"DE",
    "sg:address":"Bl\u00e4tter\u00e4cker 6",
    "sg:city":"Schw\u00e4bisch Hall",
    "sg:phone":"+49 7907/96690",
    "sg:postcode":"74523",
    "sg:province":"Baden-W\u00fcrttemberg",
    "wof:name":"Werinox-edelstahltechnik Gmbh",
    "wof:placetype":"venue"
},
  "geometry": {"coordinates":[9.830323,49.098179],"type":"Point"}
}