{
  "type": "Feature",
  "properties": {
    "iso:country":"DE",
    "sg:address":"Hirschbaumstr. 14",
    "sg:city":"Bayreuth",
    "sg:phone":"+49 9209/913084",
    "sg:postcode":"95448",
    "sg:province":"Bayern",
    "wof:name":"Volkmar Murmann Architekt",
    "wof:placetype":"venue"
},
  "geometry": {"coordinates":[11.610707,49.904091],"type":"Point"}
}