{
  "type": "Feature",
  "properties": {
    "iso:country":"DE",
    "sg:address":"Helenenstr. 70",
    "sg:city":"Essen",
    "sg:phone":"+49 201/621399",
    "sg:postcode":"45143",
    "sg:province":"Nordrhein-Westfalen",
    "wof:name":"Hans Thier",
    "wof:placetype":"venue"
},
  "geometry": {"coordinates":[6.9824399948,51.4643707275],"type":"Point"}
}