{
  "type": "Feature",
  "properties": {
    "iso:country":"DE",
    "sg:address":"Holtroper Str. 3a",
    "sg:city":"Bergheim",
    "sg:phone":"+49 2271/52014",
    "sg:postcode":"50129",
    "sg:province":"Nordrhein-Westfalen",
    "wof:name":"Brand Gmbh",
    "wof:placetype":"venue"
},
  "geometry": {"coordinates":[6.667925,50.986614],"type":"Point"}
}