{
  "type": "Feature",
  "properties": {
    "iso:country":"DE",
    "sg:address":"Hohlweg 10",
    "sg:city":"Frankenstein",
    "sg:postcode":"09569",
    "sg:province":"Sachsen",
    "wof:name":"Ghoem Ges. F\u00fcr Historische Und \u00f6kologische Methoden Mbh",
    "wof:placetype":"venue"
},
  "geometry": {"coordinates":[13.2095623016,50.8980979919],"type":"Point"}
}