{
  "type": "Feature",
  "properties": {
    "iso:country":"DE",
    "sg:address":"Schulstr. 6",
    "sg:city":"Bernitt",
    "sg:phone":"+49 38464/20275",
    "sg:postcode":"18249",
    "sg:province":"Mecklenburg-Vorpommern",
    "wof:name":"Night-club 95",
    "wof:placetype":"venue"
},
  "geometry": {"coordinates":[11.8937711716,53.9026298523],"type":"Point"}
}