{
  "type": "Feature",
  "properties": {
    "iso:country":"DE",
    "sg:address":"Amendinger Str. 38",
    "sg:city":"Memmingen",
    "sg:phone":"+49 8331/490208",
    "sg:postcode":"87700",
    "sg:province":"Bayern",
    "wof:name":"E. Endra\u00df Immobilienmakler",
    "wof:placetype":"venue"
},
  "geometry": {"coordinates":[10.205904007,48.013633728],"type":"Point"}
}