{
  "type": "Feature",
  "properties": {
    "iso:country":"DE",
    "sg:address":"Graf-Tilly-Str.",
    "sg:city":"Berching",
    "sg:phone":"+49 8460/905188",
    "sg:postcode":"92334",
    "sg:province":"Bayern",
    "wof:name":"Diablo*s Skywalker Ranch",
    "wof:placetype":"venue"
},
  "geometry": {"coordinates":[11.5091152191,49.1108360291],"type":"Point"}
}