{
  "type": "Feature",
  "properties": {
    "iso:country":"DE",
    "sg:address":"Kirchstr. 33",
    "sg:city":"Pfalzgrafenweiler",
    "sg:phone":"+49 7445/6467",
    "sg:postcode":"72285",
    "sg:province":"Baden-W\u00fcrttemberg",
    "wof:name":"W. Hohl",
    "wof:placetype":"venue"
},
  "geometry": {"coordinates":[8.563313,48.527447],"type":"Point"}
}