{
  "type": "Feature",
  "properties": {
    "iso:country":"DE",
    "sg:address":"Wilhelm-K\u00fclz-Platz 3",
    "sg:city":"Kaltennordheim",
    "sg:phone":"+49 36966/8610",
    "sg:postcode":"36452",
    "sg:province":"Th\u00fcringen",
    "wof:name":"Immobilien Und Bauservice Keller Gmbh",
    "wof:placetype":"venue"
},
  "geometry": {"coordinates":[10.1570100784,50.6263656616],"type":"Point"}
}