{
  "type": "Feature",
  "properties": {
    "iso:country":"DE",
    "sg:address":"Unterommer",
    "sg:city":"Lindlar",
    "sg:phone":"+49 2266/5408",
    "sg:postcode":"51789",
    "sg:province":"Nordrhein-Westfalen",
    "wof:name":"Arno Wesenberg",
    "wof:placetype":"venue"
},
  "geometry": {"coordinates":[7.303407,51.018311],"type":"Point"}
}