{
  "type": "Feature",
  "properties": {
    "iso:country":"DE",
    "sg:address":"Zugspitzstr. 1 c",
    "sg:city":"Gr\u00f6benzell",
    "sg:phone":"+49 8142/51313",
    "sg:postcode":"82194",
    "sg:province":"Bayern",
    "wof:name":"C. Hopf",
    "wof:placetype":"venue"
},
  "geometry": {"coordinates":[11.3640708923,48.1931610107],"type":"Point"}
}