{
  "type": "Feature",
  "properties": {
    "iso:country":"DE",
    "sg:address":"Obernstr. 11",
    "sg:city":"Bielefeld",
    "sg:phone":"+49 521/122790",
    "sg:postcode":"33602",
    "sg:province":"Nordrhein-Westfalen",
    "wof:name":"Verivakis",
    "wof:placetype":"venue"
},
  "geometry": {"coordinates":[8.530857,52.02018],"type":"Point"}
}