{
  "type": "Feature",
  "properties": {
    "iso:country":"DE",
    "sg:address":"Rechenberger Str. 25",
    "sg:city":"Jagstzell",
    "sg:phone":"+49 7967/367",
    "sg:postcode":"73489",
    "sg:province":"Baden-W\u00fcrttemberg",
    "wof:name":"Anna May Hebamme",
    "wof:placetype":"venue"
},
  "geometry": {"coordinates":[10.10521,49.029976],"type":"Point"}
}