{
  "type": "Feature",
  "properties": {
    "iso:country":"DE",
    "sg:address":"Oberheldenberg 2",
    "sg:city":"Altfraunhofen",
    "sg:phone":"+49 8705/1257",
    "sg:postcode":"84169",
    "sg:province":"Bayern",
    "wof:name":"Xaver Weindl",
    "wof:placetype":"venue"
},
  "geometry": {"coordinates":[12.1931877136,48.4441413879],"type":"Point"}
}