{
  "type": "Feature",
  "properties": {
    "iso:country":"DE",
    "sg:address":"T\u00fcbinger Str. 33",
    "sg:city":"Leinfelden-Echterdingen",
    "sg:phone":"+49 711/7978393",
    "sg:postcode":"70771",
    "sg:province":"Baden-W\u00fcrttemberg",
    "wof:name":"Telxon",
    "wof:placetype":"venue"
},
  "geometry": {"coordinates":[9.1625499725,48.6835327148],"type":"Point"}
}