{
  "type": "Feature",
  "properties": {
    "iso:country":"DE",
    "sg:address":"G\u00f6rdelingerstr. 6-7",
    "sg:city":"Braunschweig",
    "sg:postcode":"38100",
    "sg:province":"Niedersachsen",
    "wof:name":"M\u00f6bel Sander Gmbh",
    "wof:placetype":"venue"
},
  "geometry": {"coordinates":[10.518040657,52.2636146545],"type":"Point"}
}