{
  "type": "Feature",
  "properties": {
    "iso:country":"DE",
    "sg:address":"Am Vorderfl\u00f6\u00df 42",
    "sg:city":"Bad Lippspringe",
    "sg:phone":"+49 5252/51366",
    "sg:postcode":"33175",
    "sg:province":"Nordrhein-Westfalen",
    "wof:name":"Alltrink Getr\u00e4nkehandels Gmbh",
    "wof:placetype":"venue"
},
  "geometry": {"coordinates":[8.795998,51.777237],"type":"Point"}
}