{
  "type": "Feature",
  "properties": {
    "iso:country":"DE",
    "sg:address":"Lange Wende 15",
    "sg:city":"Hamm",
    "sg:postcode":"59069",
    "sg:province":"Nordrhein-Westfalen",
    "wof:name":"Store-build Gmbh & Co. Kg",
    "wof:placetype":"venue"
},
  "geometry": {"coordinates":[7.857858,51.624599],"type":"Point"}
}