{
  "type": "Feature",
  "properties": {
    "iso:country":"DE",
    "sg:address":"Odenwaldstr. 36",
    "sg:city":"Frankenthal",
    "sg:phone":"+49 6233/54883",
    "sg:postcode":"67227",
    "sg:province":"Rheinland-Pfalz",
    "wof:name":"Wolfgang Awenius",
    "wof:placetype":"venue"
},
  "geometry": {"coordinates":[8.327914,49.511654],"type":"Point"}
}