{
  "type": "Feature",
  "properties": {
    "iso:country":"DE",
    "sg:address":"Rosa-Luxemburg-Str. 42",
    "sg:city":"Tangerm\u00fcnde",
    "sg:phone":"+49 39322/42757",
    "sg:postcode":"39590",
    "sg:province":"Sachsen-Anhalt",
    "wof:name":"Monika Sch\u00f6pp",
    "wof:placetype":"venue"
},
  "geometry": {"coordinates":[11.9765262604,52.5494232178],"type":"Point"}
}