{
  "type": "Feature",
  "properties": {
    "iso:country":"DE",
    "sg:address":"Lindenweg 1",
    "sg:city":"Greiling",
    "sg:phone":"+49 8041/9226",
    "sg:postcode":"83677",
    "sg:province":"Bayern",
    "wof:name":"Eva Pacher",
    "wof:placetype":"venue"
},
  "geometry": {"coordinates":[11.6156005859,47.7621231079],"type":"Point"}
}