{
  "type": "Feature",
  "properties": {
    "iso:country":"DE",
    "sg:address":"Rodeland 6",
    "sg:city":"Bielefeld",
    "sg:phone":"+49 521/85998",
    "sg:postcode":"33739",
    "sg:province":"Nordrhein-Westfalen",
    "wof:name":"Verein F\u00fcr Kinder- Und Jugendfreizeithilfen E. V.",
    "wof:placetype":"venue"
},
  "geometry": {"coordinates":[8.5313987732,52.0609512329],"type":"Point"}
}