{
  "type": "Feature",
  "properties": {
    "iso:country":"DE",
    "sg:address":"Augsburger Str. 50",
    "sg:city":"G\u00fcnzburg",
    "sg:postcode":"89312",
    "sg:province":"Bayern",
    "wof:name":"M\u00f6dinger Und H\u00e4nle Gmbh",
    "wof:placetype":"venue"
},
  "geometry": {"coordinates":[10.285089,48.453018],"type":"Point"}
}