{
  "type": "Feature",
  "properties": {
    "iso:country":"DE",
    "sg:address":"Oberh\u00e4userstr. 100e",
    "sg:city":"Ansbach",
    "sg:phone":"+49 981/61128",
    "sg:postcode":"91522",
    "sg:province":"Bayern",
    "wof:name":"Renate Fiedler Kunstmaler",
    "wof:placetype":"venue"
},
  "geometry": {"coordinates":[10.558897,49.292709],"type":"Point"}
}