{
  "type": "Feature",
  "properties": {
    "iso:country":"DE",
    "sg:address":"Clayallee 146",
    "sg:city":"Berlin",
    "sg:phone":"+49 30/8326870",
    "sg:postcode":"14195",
    "sg:province":"Berlin",
    "wof:name":"La Villa",
    "wof:placetype":"venue"
},
  "geometry": {"coordinates":[13.273059845,52.4543113708],"type":"Point"}
}