{
  "type": "Feature",
  "properties": {
    "iso:country":"DE",
    "sg:address":"Limburger Str. 84",
    "sg:city":"Limburg",
    "sg:phone":"+49 6431/95790",
    "sg:postcode":"65555",
    "sg:province":"Hessen",
    "wof:name":"Massa Einrichtungsmarkt",
    "wof:placetype":"venue"
},
  "geometry": {"coordinates":[8.0667295456,50.4134407043],"type":"Point"}
}