{
  "type": "Feature",
  "properties": {
    "iso:country":"DE",
    "sg:address":"Buntzelstr. 63",
    "sg:city":"Berlin",
    "sg:phone":"+49 30/6767418",
    "sg:postcode":"12526",
    "sg:province":"Berlin",
    "wof:name":"Bernd Debrodt",
    "wof:placetype":"venue"
},
  "geometry": {"coordinates":[13.56893,52.403133],"type":"Point"}
}