{
  "type": "Feature",
  "properties": {
    "iso:country":"DE",
    "sg:address":"Warener Stra\u00dfe 51",
    "sg:city":"Springe",
    "sg:phone":"+49 5041",
    "sg:postcode":"31832",
    "sg:province":"Niedersachsen",
    "wof:name":"Selbsthilfegruppe Multiple Sklerose",
    "wof:placetype":"venue"
},
  "geometry": {"coordinates":[9.540341,52.217064],"type":"Point"}
}