{
  "type": "Feature",
  "properties": {
    "iso:country":"DE",
    "sg:address":"M\u00f6llner Landstr. 37 d",
    "sg:city":"Glinde",
    "sg:phone":"+49 40/7112766",
    "sg:postcode":"21509",
    "sg:province":"Schleswig-Holstein",
    "wof:name":"Aribert Rabe",
    "wof:placetype":"venue"
},
  "geometry": {"coordinates":[10.201154,53.54055],"type":"Point"}
}