{
  "type": "Feature",
  "properties": {
    "iso:country":"DE",
    "sg:address":"Im Sulzbachtal",
    "sg:city":"Sch\u00f6naich",
    "sg:phone":"+49 7031/654054",
    "sg:postcode":"71101",
    "sg:province":"Baden-W\u00fcrttemberg",
    "wof:name":"Waldfreibad",
    "wof:placetype":"venue"
},
  "geometry": {"coordinates":[9.0913391113,48.6668548584],"type":"Point"}
}