{
  "type": "Feature",
  "properties": {
    "iso:country":"DE",
    "sg:address":"Perhamerstr. 4",
    "sg:city":"M\u00fcnchen",
    "sg:phone":"+49 89/54611178",
    "sg:postcode":"80687",
    "sg:province":"Bayern",
    "wof:name":"La Le Lu First Und Second Hand Kindermode Und Mehr E.k.",
    "wof:placetype":"venue"
},
  "geometry": {"coordinates":[11.502014,48.141762],"type":"Point"}
}