{
  "type": "Feature",
  "properties": {
    "iso:country":"DE",
    "sg:address":"Kreuzstr. 106",
    "sg:city":"H\u00fcrth",
    "sg:phone":"+49 2233/942430",
    "sg:postcode":"50354",
    "sg:province":"Nordrhein-Westfalen",
    "wof:name":"G\u00fcnter Schneider Ingenieur",
    "wof:placetype":"venue"
},
  "geometry": {"coordinates":[6.8746900558,50.8760147095],"type":"Point"}
}