{
  "type": "Feature",
  "properties": {
    "iso:country":"DE",
    "sg:address":"Johann-Christoph-Hilf-Str. 20",
    "sg:city":"Bad Elster",
    "sg:phone":"+49 37437/46721",
    "sg:postcode":"08645",
    "sg:province":"Sachsen",
    "wof:name":"Trampler Bestattungen Gmbh",
    "wof:placetype":"venue"
},
  "geometry": {"coordinates":[12.234663,50.279434],"type":"Point"}
}