{
  "type": "Feature",
  "properties": {
    "iso:country":"DE",
    "sg:address":"Wasserstr. 7",
    "sg:city":"Stapelburg",
    "sg:postcode":"38871",
    "sg:province":"Sachsen-Anhalt",
    "wof:name":"Abwassergesellschaft Stapelburg Mbh",
    "wof:placetype":"venue"
},
  "geometry": {"coordinates":[10.6617927551,51.9020118713],"type":"Point"}
}