{
  "type": "Feature",
  "properties": {
    "iso:country":"DE",
    "sg:address":"Bandelstr. 28",
    "sg:city":"Ansbach",
    "sg:phone":"+49 981/7161",
    "sg:postcode":"91522",
    "sg:province":"Bayern",
    "wof:name":"Trend",
    "wof:placetype":"venue"
},
  "geometry": {"coordinates":[10.5763368607,49.2940750122],"type":"Point"}
}