{
  "type": "Feature",
  "properties": {
    "iso:country":"DE",
    "sg:address":"Beethovenstr. 45",
    "sg:city":"K\u00f6werich",
    "sg:phone":"+49 6507/3786",
    "sg:postcode":"54340",
    "sg:province":"Rheinland-Pfalz",
    "wof:name":"Josef Becker-neisius",
    "wof:placetype":"venue"
},
  "geometry": {"coordinates":[6.861333847,49.8418121338],"type":"Point"}
}