{
  "type": "Feature",
  "properties": {
    "iso:country":"DE",
    "sg:address":"Amperleite 2",
    "sg:city":"F\u00fcrstenfeldbruck",
    "sg:phone":"+49 8141/43345",
    "sg:postcode":"82256",
    "sg:province":"Bayern",
    "wof:name":"Dr. Hannelore Ehrenreich Tier\u00e4rztin",
    "wof:placetype":"venue"
},
  "geometry": {"coordinates":[11.2666416168,48.1798553467],"type":"Point"}
}