{
  "type": "Feature",
  "properties": {
    "iso:country":"DE",
    "sg:address":"Kisseleffstr. 1",
    "sg:city":"Bad Homburg",
    "sg:phone":"+49 6172/928352",
    "sg:postcode":"61348",
    "sg:province":"Hessen",
    "wof:name":"Stephan Zwecker Rechtsanwalt",
    "wof:placetype":"venue"
},
  "geometry": {"coordinates":[8.620139122,50.2247009277],"type":"Point"}
}