{
  "type": "Feature",
  "properties": {
    "iso:country":"DE",
    "sg:address":"H\u00fcttersdorfer Str. 7",
    "sg:city":"Nalbach",
    "sg:phone":"+49 180 3 330500",
    "sg:postcode":"66809",
    "sg:province":"Saarland",
    "wof:name":"Game-4-you",
    "wof:placetype":"venue"
},
  "geometry": {"coordinates":[6.8389110565,49.3921089172],"type":"Point"}
}