{
  "type": "Feature",
  "properties": {
    "iso:country":"DE",
    "sg:address":"Malmsgel\u00e4nge 2",
    "sg:city":"P\u00f6\u00dfneck",
    "sg:phone":"+49 3647/424095",
    "sg:postcode":"07381",
    "sg:province":"Th\u00fcringen",
    "wof:name":"Frank G\u00fcnther Gmbh",
    "wof:placetype":"venue"
},
  "geometry": {"coordinates":[11.6179065704,50.6980018616],"type":"Point"}
}