{
  "type": "Feature",
  "properties": {
    "iso:country":"DE",
    "sg:address":"Birkenstr. 3 a",
    "sg:city":"Bad Soden",
    "sg:phone":"+49 6196/641575",
    "sg:postcode":"65812",
    "sg:province":"Hessen",
    "wof:name":"Michael Gehring Architekt",
    "wof:placetype":"venue"
},
  "geometry": {"coordinates":[8.502368,50.151501],"type":"Point"}
}