{
  "type": "Feature",
  "properties": {
    "iso:country":"DE",
    "sg:address":"Vogteistr. 2",
    "sg:city":"Geilenkirchen",
    "sg:postcode":"52511",
    "sg:province":"Nordrhein-Westfalen",
    "wof:name":"Kreismuseum",
    "wof:placetype":"venue"
},
  "geometry": {"coordinates":[6.119134,50.964458],"type":"Point"}
}