{
  "type": "Feature",
  "properties": {
    "iso:country":"DE",
    "sg:address":"Ginnheimer Str. 32",
    "sg:city":"Frankfurt",
    "sg:phone":"+49 69/9707070",
    "sg:postcode":"60487",
    "sg:province":"Hessen",
    "wof:name":"Glas-link Harald Link",
    "wof:placetype":"venue"
},
  "geometry": {"coordinates":[8.6402521133,50.1266784668],"type":"Point"}
}