{
  "type": "Feature",
  "properties": {
    "iso:country":"DE",
    "sg:address":"Wirtsg. 19",
    "sg:city":"Reichenberg",
    "sg:phone":"+49 9366/493",
    "sg:postcode":"97234",
    "sg:province":"Bayern",
    "wof:name":"Otto Zimmermann Kunstoffspritzerei Gmbh & Co Kg",
    "wof:placetype":"venue"
},
  "geometry": {"coordinates":[9.9120426178,49.702671051],"type":"Point"}
}