{
  "type": "Feature",
  "properties": {
    "iso:country":"DE",
    "sg:address":"Am Windm\u00fchlenfeld 20",
    "sg:city":"Frechen",
    "sg:phone":"+49 2234/61262",
    "sg:postcode":"50226",
    "sg:province":"Nordrhein-Westfalen",
    "wof:name":"Karlheinz Gillhausen",
    "wof:placetype":"venue"
},
  "geometry": {"coordinates":[6.782512188,50.9344978333],"type":"Point"}
}