{
  "type": "Feature",
  "properties": {
    "iso:country":"DE",
    "sg:address":"Kilianstr. 150",
    "sg:city":"N\u00fcrnberg",
    "sg:phone":"+49 911/361070",
    "sg:postcode":"90425",
    "sg:province":"Bayern",
    "wof:name":"Reinshagen Technik Gmbh & Co.",
    "wof:placetype":"venue"
},
  "geometry": {"coordinates":[11.0861730576,49.4734191895],"type":"Point"}
}