{
  "type": "Feature",
  "properties": {
    "iso:country":"DE",
    "sg:address":"Postfach",
    "sg:city":"Bad F\u00fcssing",
    "sg:phone":"+49 8531/21381",
    "sg:postcode":"94066",
    "sg:province":"Bayern",
    "wof:name":"Hotel Passauer Wolf Gmbh",
    "wof:placetype":"venue"
},
  "geometry": {"coordinates":[13.3109903336,48.3521308899],"type":"Point"}
}