{
  "type": "Feature",
  "properties": {
    "iso:country":"DE",
    "sg:address":"Eulerstr. 5",
    "sg:city":"Ransbach-Baumbach",
    "sg:phone":"+49 2623/80145",
    "sg:postcode":"56235",
    "sg:province":"Rheinland-Pfalz",
    "wof:name":"Ewald Spang Gmbh",
    "wof:placetype":"venue"
},
  "geometry": {"coordinates":[7.7265558243,50.4612007141],"type":"Point"}
}