{
  "type": "Feature",
  "properties": {
    "iso:country":"DE",
    "sg:address":"Niederstr. 57",
    "sg:city":"Erkelenz",
    "sg:phone":"+49 2164/940400",
    "sg:postcode":"41812",
    "sg:province":"Nordrhein-Westfalen",
    "wof:name":"Seilerei Gebr\u00fcder Brandenburg Ohg",
    "wof:placetype":"venue"
},
  "geometry": {"coordinates":[6.4036231041,51.0508842468],"type":"Point"}
}