{
  "type": "Feature",
  "properties": {
    "iso:country":"DE",
    "sg:address":"Rudolf-Breitscheid-Str. 15",
    "sg:city":"Gransee",
    "sg:postcode":"16775",
    "sg:province":"Brandenburg",
    "wof:name":"Luisenapotheke Inh. Thomas Faber E. K.",
    "wof:placetype":"venue"
},
  "geometry": {"coordinates":[13.159972,53.006794],"type":"Point"}
}