{
  "type": "Feature",
  "properties": {
    "iso:country":"DE",
    "sg:address":"Scholerholz 6",
    "sg:city":"Engeln",
    "sg:phone":"+49 4252/763",
    "sg:postcode":"27305",
    "sg:province":"Niedersachsen",
    "wof:name":"Heinrich Schr\u00f6der",
    "wof:placetype":"venue"
},
  "geometry": {"coordinates":[8.939748,52.788525],"type":"Point"}
}