{
  "type": "Feature",
  "properties": {
    "iso:country":"DE",
    "sg:address":"Langhans 1",
    "sg:city":"Beilstein",
    "sg:phone":"+49 7062/5770",
    "sg:postcode":"71717",
    "sg:province":"Baden-W\u00fcrttemberg",
    "wof:name":"Restaurant Burggastsst\u00e4tte Hohenbeilstein",
    "wof:placetype":"venue"
},
  "geometry": {"coordinates":[9.318148613,49.0420799255],"type":"Point"}
}