{
  "type": "Feature",
  "properties": {
    "iso:country":"DE",
    "sg:address":"Hauptstr. 34",
    "sg:city":"Heidenheim",
    "sg:phone":"+49 7321/327370",
    "sg:postcode":"89522",
    "sg:province":"Baden-W\u00fcrttemberg",
    "wof:name":"Stadtbibliothek Elmar-doch-haus",
    "wof:placetype":"venue"
},
  "geometry": {"coordinates":[10.151524,48.676247],"type":"Point"}
}