{
  "type": "Feature",
  "properties": {
    "iso:country":"DE",
    "sg:address":"Trippstadter Str. 4",
    "sg:city":"Hochspeyer",
    "sg:phone":"+49 6305/5228",
    "sg:postcode":"67691",
    "sg:province":"Rheinland-Pfalz",
    "wof:name":"Roman Egelhof",
    "wof:placetype":"venue"
},
  "geometry": {"coordinates":[7.8954901695,49.4433555603],"type":"Point"}
}