{
  "type": "Feature",
  "properties": {
    "iso:country":"DE",
    "sg:address":"Im Siebenborn 14",
    "sg:city":"Trier",
    "sg:phone":"+49 651/826370",
    "sg:postcode":"54294",
    "sg:province":"Rheinland-Pfalz",
    "wof:name":"Gothaer Versicherungen Manfred Fischer",
    "wof:placetype":"venue"
},
  "geometry": {"coordinates":[6.5875368118,49.7226409912],"type":"Point"}
}