{
  "type": "Feature",
  "properties": {
    "iso:country":"DE",
    "sg:address":"St.-Ottilien-Platz 3",
    "sg:city":"Forchheim",
    "sg:phone":"+49 9191/15754",
    "sg:postcode":"91301",
    "sg:province":"Bayern",
    "wof:name":"Kath. Pfarramt St. Johannes D.t\u00e4ufer",
    "wof:placetype":"venue"
},
  "geometry": {"coordinates":[11.0685300827,49.682094574],"type":"Point"}
}