{
  "type": "Feature",
  "properties": {
    "iso:country":"DE",
    "sg:address":"Industriestr. 23",
    "sg:city":"Utting",
    "sg:phone":"+49 8806/92080",
    "sg:postcode":"86919",
    "sg:province":"Bayern",
    "wof:name":"Sd Gmbh",
    "wof:placetype":"venue"
},
  "geometry": {"coordinates":[11.08583,48.029991],"type":"Point"}
}