{
  "type": "Feature",
  "properties": {
    "iso:country":"DE",
    "sg:address":"Ehestetter Weg 10",
    "sg:city":"Albstadt",
    "sg:phone":"+49 7431/2436",
    "sg:postcode":"72458",
    "sg:province":"Baden-W\u00fcrttemberg",
    "wof:name":"Ebro Color Gmbh",
    "wof:placetype":"venue"
},
  "geometry": {"coordinates":[9.0390977859,48.2057800293],"type":"Point"}
}