{
  "type": "Feature",
  "properties": {
    "iso:country":"DE",
    "sg:address":"Friedrichstr. 33",
    "sg:city":"M\u00fcnchen",
    "sg:phone":"+49 89/3839910",
    "sg:postcode":"80801",
    "sg:province":"Bayern",
    "wof:name":"Otto Schultz-brauns Architekt",
    "wof:placetype":"venue"
},
  "geometry": {"coordinates":[11.580167,48.160828],"type":"Point"}
}