{
  "type": "Feature",
  "properties": {
    "iso:country":"DE",
    "sg:address":"Schleizer Str. 10",
    "sg:city":"Gera",
    "sg:phone":"+49 365/7106056",
    "sg:postcode":"07549",
    "sg:province":"Th\u00fcringen",
    "wof:name":"K. R\u00f6hlich",
    "wof:placetype":"venue"
},
  "geometry": {"coordinates":[12.066740036,50.8484382629],"type":"Point"}
}