{
  "type": "Feature",
  "properties": {
    "iso:country":"DE",
    "sg:address":"R\u00f6merstr. 46",
    "sg:city":"Ertingen",
    "sg:phone":"+49 7371/5679",
    "sg:postcode":"88521",
    "sg:province":"Baden-W\u00fcrttemberg",
    "wof:name":"Roland Wahl",
    "wof:placetype":"venue"
},
  "geometry": {"coordinates":[9.416533,48.109787],"type":"Point"}
}