{
  "type": "Feature",
  "properties": {
    "iso:country":"DE",
    "sg:address":"Hochmode 15",
    "sg:city":"L\u00fctjenburg",
    "sg:phone":"+49 4381/9737",
    "sg:postcode":"24321",
    "sg:province":"Schleswig-Holstein",
    "wof:name":"Marlis Geith",
    "wof:placetype":"venue"
},
  "geometry": {"coordinates":[10.572711,54.29837],"type":"Point"}
}