{
  "type": "Feature",
  "properties": {
    "iso:country":"DE",
    "sg:address":"Untere Str. 35",
    "sg:city":"Heidelberg",
    "sg:postcode":"69117",
    "sg:province":"Baden-W\u00fcrttemberg",
    "wof:name":"Rala Gmbh",
    "wof:placetype":"venue"
},
  "geometry": {"coordinates":[8.7088537216,49.4124221802],"type":"Point"}
}