{
  "type": "Feature",
  "properties": {
    "iso:country":"DE",
    "sg:address":"\u00d6lkofer Str. 41",
    "sg:city":"Fronreute",
    "sg:phone":"+49 7505/279",
    "sg:postcode":"88273",
    "sg:province":"Baden-W\u00fcrttemberg",
    "wof:name":"Pr\u00fcfstation F\u00fcr Fleckvieh- Zuchteinheit S\u00fcd E. V.",
    "wof:placetype":"venue"
},
  "geometry": {"coordinates":[9.5903701782,47.861907959],"type":"Point"}
}