{
  "type": "Feature",
  "properties": {
    "iso:country":"DE",
    "sg:address":"Malkwitzer Weg 8",
    "sg:city":"Malente",
    "sg:phone":"+49 4523/4584",
    "sg:postcode":"23714",
    "sg:province":"Schleswig-Holstein",
    "wof:name":"H.-h. Kahllund",
    "wof:placetype":"venue"
},
  "geometry": {"coordinates":[10.573202,54.184528],"type":"Point"}
}