{
  "type": "Feature",
  "properties": {
    "iso:country":"DE",
    "sg:address":"Bernestr. 5",
    "sg:city":"Essen",
    "sg:phone":"+49 201/22043",
    "sg:postcode":"45127",
    "sg:province":"Nordrhein-Westfalen",
    "wof:name":"Adveniat",
    "wof:placetype":"venue"
},
  "geometry": {"coordinates":[7.016600132,51.4556541443],"type":"Point"}
}