{
  "type": "Feature",
  "properties": {
    "iso:country":"DE",
    "sg:address":"Dorfstr. 8",
    "sg:city":"Leschen",
    "sg:phone":"+49 34325/20302",
    "sg:postcode":"04720",
    "sg:province":"Sachsen",
    "wof:name":"Genossenschaft Agrarland Eg",
    "wof:placetype":"venue"
},
  "geometry": {"coordinates":[13.11965,51.128841],"type":"Point"}
}