{
  "type": "Feature",
  "properties": {
    "iso:country":"DE",
    "sg:address":"Rohrerweg 3",
    "sg:city":"Esch",
    "sg:phone":"+49 6508/91500",
    "sg:postcode":"54518",
    "sg:province":"Rheinland-Pfalz",
    "wof:name":"Ruppert-verwaltungs Gmbh",
    "wof:placetype":"venue"
},
  "geometry": {"coordinates":[6.849545,49.898773],"type":"Point"}
}