{
  "type": "Feature",
  "properties": {
    "iso:country":"DE",
    "sg:address":"Weilerstr. 6",
    "sg:city":"Niederrieden",
    "sg:phone":"+49 8335/226",
    "sg:postcode":"87767",
    "sg:province":"Bayern",
    "wof:name":"Michl Herz Samen- Und Saatenzucht",
    "wof:placetype":"venue"
},
  "geometry": {"coordinates":[10.185626,48.06424],"type":"Point"}
}