{
  "type": "Feature",
  "properties": {
    "iso:country":"DE",
    "sg:address":"Wilhelm-Liebknecht-Str. 25",
    "sg:city":"Crimmitschau",
    "sg:phone":"+49 3762/49418",
    "sg:postcode":"08451",
    "sg:province":"Sachsen",
    "wof:name":"Holger Lederer",
    "wof:placetype":"venue"
},
  "geometry": {"coordinates":[12.3709440231,50.8130912781],"type":"Point"}
}