{
  "type": "Feature",
  "properties": {
    "iso:country":"DE",
    "sg:address":"Heidkampsweg 21",
    "sg:city":"Schneverdingen",
    "sg:phone":"+49 5193/985121",
    "sg:postcode":"29640",
    "sg:province":"Niedersachsen",
    "wof:name":"Fischer Markenschuh Gmbh",
    "wof:placetype":"venue"
},
  "geometry": {"coordinates":[9.800238,53.107075],"type":"Point"}
}