{
  "type": "Feature",
  "properties": {
    "iso:country":"DE",
    "sg:address":"Maxdorfer Str. 60",
    "sg:city":"Birkenheide",
    "sg:phone":"+49 6237/3324",
    "sg:postcode":"67134",
    "sg:province":"Rheinland-Pfalz",
    "wof:name":"Hermann Hammann Schilder",
    "wof:placetype":"venue"
},
  "geometry": {"coordinates":[8.261938,49.481121],"type":"Point"}
}