{
  "type": "Feature",
  "properties": {
    "iso:country":"DE",
    "sg:address":"Mitterfeldstr. 12",
    "sg:city":"Garmisch-Partenkirchen",
    "sg:phone":"+49 8821/79693",
    "sg:postcode":"82467",
    "sg:province":"Bayern",
    "wof:name":"A. Kneilling",
    "wof:placetype":"venue"
},
  "geometry": {"coordinates":[11.0816984177,47.487865448],"type":"Point"}
}