{
  "type": "Feature",
  "properties": {
    "iso:country":"DE",
    "sg:address":"Lindenstr. 39",
    "sg:city":"Seebad Ahlbeck",
    "sg:phone":"+49 38378/28348",
    "sg:postcode":"17419",
    "sg:province":"Mecklenburg-Vorpommern",
    "wof:name":"Flok Bau Gmbh",
    "wof:placetype":"venue"
},
  "geometry": {"coordinates":[14.0650997162,53.8867111206],"type":"Point"}
}