{
  "type": "Feature",
  "properties": {
    "iso:country":"DE",
    "sg:address":"Dr.-K\u00fclz-Ufer 7",
    "sg:city":"Torgau",
    "sg:phone":"+49 3421/712949",
    "sg:postcode":"04860",
    "sg:province":"Sachsen",
    "wof:name":"G\u00f6tz Wernecke",
    "wof:placetype":"venue"
},
  "geometry": {"coordinates":[12.9921960831,51.560043335],"type":"Point"}
}