{
  "type": "Feature",
  "properties": {
    "iso:country":"DE",
    "sg:address":"Breisacher Str. 10.12",
    "sg:city":"Ihringen",
    "sg:phone":"+49 7668/1716",
    "sg:postcode":"79241",
    "sg:province":"Baden-W\u00fcrttemberg",
    "wof:name":"Christel Weis",
    "wof:placetype":"venue"
},
  "geometry": {"coordinates":[7.64478,48.045238],"type":"Point"}
}