{
  "type": "Feature",
  "properties": {
    "iso:country":"DE",
    "sg:address":"Pilsheim 12",
    "sg:city":"Burglengenfeld",
    "sg:phone":"+49 9474/209",
    "sg:postcode":"93133",
    "sg:province":"Bayern",
    "wof:name":"J. Auer",
    "wof:placetype":"venue"
},
  "geometry": {"coordinates":[11.962845,49.271862],"type":"Point"}
}