{
  "type": "Feature",
  "properties": {
    "iso:country":"DE",
    "sg:address":"R\u00fcderner Str. 57",
    "sg:city":"Esslingen",
    "sg:phone":"+49 711/322268",
    "sg:postcode":"73733",
    "sg:province":"Baden-W\u00fcrttemberg",
    "wof:name":"Alfred Baur Architekt",
    "wof:placetype":"venue"
},
  "geometry": {"coordinates":[9.287742,48.750717],"type":"Point"}
}