{
  "type": "Feature",
  "properties": {
    "iso:country":"DE",
    "sg:address":"Sonnenstr. 10",
    "sg:city":"Hann. M\u00fcnden",
    "sg:phone":"+49 5541/2868",
    "sg:postcode":"34346",
    "sg:province":"Niedersachsen",
    "wof:name":"Albrecht Heepe",
    "wof:placetype":"venue"
},
  "geometry": {"coordinates":[9.6626844406,51.4443969727],"type":"Point"}
}