{
  "type": "Feature",
  "properties": {
    "iso:country":"DE",
    "sg:address":"Alte R\u00f6merstr. 27",
    "sg:city":"Sinsheim",
    "sg:phone":"+49 7261/65061",
    "sg:postcode":"74889",
    "sg:province":"Baden-W\u00fcrttemberg",
    "wof:name":"Schlemmerimbi\u00df",
    "wof:placetype":"venue"
},
  "geometry": {"coordinates":[8.9025430679,49.2402153015],"type":"Point"}
}