{
  "type": "Feature",
  "properties": {
    "iso:country":"DE",
    "sg:address":"Ungerather Kirchweg 7b",
    "sg:city":"Schwalmtal",
    "sg:phone":"+49 2163/943046",
    "sg:postcode":"41366",
    "sg:province":"Nordrhein-Westfalen",
    "wof:name":"Levent Kurtulus Architekt",
    "wof:placetype":"venue"
},
  "geometry": {"coordinates":[6.276306,51.209061],"type":"Point"}
}