{
  "type": "Feature",
  "properties": {
    "iso:country":"DE",
    "sg:address":"Talkamp 13 d",
    "sg:city":"Garbsen",
    "sg:phone":"+49 5137/71562",
    "sg:postcode":"30823",
    "sg:province":"Niedersachsen",
    "wof:name":"Red. Bei Uns Auf Der Horst Spd Ortsverein",
    "wof:placetype":"venue"
},
  "geometry": {"coordinates":[9.6091165543,52.4210548401],"type":"Point"}
}