{
  "type": "Feature",
  "properties": {
    "iso:country":"DE",
    "sg:address":"Weimarer Str. 75",
    "sg:city":"Gotha",
    "sg:phone":"+49 3621/852332",
    "sg:postcode":"99867",
    "sg:province":"Th\u00fcringen",
    "wof:name":"Dr. Med. Wolfgang Klose Arzt F\u00fcr Allgemeinmedizin",
    "wof:placetype":"venue"
},
  "geometry": {"coordinates":[10.7358198166,50.9449691772],"type":"Point"}
}