{
  "type": "Feature",
  "properties": {
    "iso:country":"DE",
    "sg:address":"Alsenstr. 1a",
    "sg:city":"Leverkusen",
    "sg:phone":"+49 214/45463",
    "sg:postcode":"51373",
    "sg:province":"Nordrhein-Westfalen",
    "wof:name":"H. Krassa Ballettschule",
    "wof:placetype":"venue"
},
  "geometry": {"coordinates":[7.0068240166,51.0349159241],"type":"Point"}
}