{
  "type": "Feature",
  "properties": {
    "iso:country":"DE",
    "sg:address":"Osterend 19",
    "sg:city":"Werlte",
    "sg:phone":"+49 5951/1755",
    "sg:postcode":"49757",
    "sg:province":"Niedersachsen",
    "wof:name":"Bernhard K\u00f6ster",
    "wof:placetype":"venue"
},
  "geometry": {"coordinates":[7.68877,52.855419],"type":"Point"}
}