{
  "type": "Feature",
  "properties": {
    "iso:country":"DE",
    "sg:address":"Vorarlberger Str. 5",
    "sg:city":"Friedrichshafen",
    "sg:phone":"+49 7541/24340",
    "sg:postcode":"88045",
    "sg:province":"Baden-W\u00fcrttemberg",
    "wof:name":"Josef Schechinger",
    "wof:placetype":"venue"
},
  "geometry": {"coordinates":[9.4614257812,47.6539039612],"type":"Point"}
}