{
  "type": "Feature",
  "properties": {
    "iso:country":"DE",
    "sg:address":"Adolf-Damaschke-Str. 2",
    "sg:city":"L\u00fcnen",
    "sg:phone":"+49 2306/48909",
    "sg:postcode":"44532",
    "sg:province":"Nordrhein-Westfalen",
    "wof:name":"Markt-apotheke",
    "wof:placetype":"venue"
},
  "geometry": {"coordinates":[7.524464,51.588516],"type":"Point"}
}