{
  "type": "Feature",
  "properties": {
    "iso:country":"DE",
    "sg:address":"Fichtenweg 2",
    "sg:city":"T\u00fcbingen",
    "sg:postcode":"72076",
    "sg:province":"Baden-W\u00fcrttemberg",
    "wof:name":"Stadtb\u00fccherei Waldh\u00e4user Ost",
    "wof:placetype":"venue"
},
  "geometry": {"coordinates":[9.058226,48.542023],"type":"Point"}
}