{
  "type": "Feature",
  "properties": {
    "iso:country":"DE",
    "sg:address":"Leipziger Str. 21",
    "sg:city":"Rackwitz",
    "sg:phone":"+49 34294/73247",
    "sg:postcode":"04519",
    "sg:province":"Sachsen",
    "wof:name":"B\u00e4ckerei Fr\u00fchauf Gmbh",
    "wof:placetype":"venue"
},
  "geometry": {"coordinates":[12.374632,51.435204],"type":"Point"}
}