{
  "type": "Feature",
  "properties": {
    "iso:country":"DE",
    "sg:address":"Tiroler Str. 1",
    "sg:city":"F\u00fcssen",
    "sg:phone":"+49 8362/5915",
    "sg:postcode":"87629",
    "sg:province":"Bayern",
    "wof:name":"Pilsbar M 1",
    "wof:placetype":"venue"
},
  "geometry": {"coordinates":[10.7004804611,47.5652503967],"type":"Point"}
}