{
  "type": "Feature",
  "properties": {
    "iso:country":"DE",
    "sg:address":"Herrenweg 8",
    "sg:city":"Schwanau",
    "sg:phone":"+49 7824/562",
    "sg:postcode":"77963",
    "sg:province":"Baden-W\u00fcrttemberg",
    "wof:name":"U. Haller",
    "wof:placetype":"venue"
},
  "geometry": {"coordinates":[7.7770118713,48.3660888672],"type":"Point"}
}