{
  "type": "Feature",
  "properties": {
    "iso:country":"DE",
    "sg:address":"Am Hasenwinkel 2",
    "sg:city":"Waldheim",
    "sg:postcode":"04736",
    "sg:province":"Sachsen",
    "wof:name":"Wolfgang Koppisch",
    "wof:placetype":"venue"
},
  "geometry": {"coordinates":[13.036514,51.070988],"type":"Point"}
}