{
  "type": "Feature",
  "properties": {
    "iso:country":"DE",
    "sg:address":"Egerl\u00e4nder Str. 5",
    "sg:city":"Freilassing",
    "sg:phone":"+49 8654/2494",
    "sg:postcode":"83395",
    "sg:province":"Bayern",
    "wof:name":"Hermann Men Kunststoffwaren",
    "wof:placetype":"venue"
},
  "geometry": {"coordinates":[12.9687652588,47.8471946716],"type":"Point"}
}