{
  "type": "Feature",
  "properties": {
    "iso:country":"DE",
    "sg:address":"Albert-Einstein-Str. 18a",
    "sg:city":"R\u00f6dermark",
    "sg:phone":"+49 6074/99060",
    "sg:postcode":"63322",
    "sg:province":"Hessen",
    "wof:name":"Maria M. Becht Steuerberaterin",
    "wof:placetype":"venue"
},
  "geometry": {"coordinates":[8.8203268051,49.9706230164],"type":"Point"}
}