{
  "type": "Feature",
  "properties": {
    "iso:country":"DE",
    "sg:address":"Karl-Marx-Str. 14",
    "sg:city":"Calau",
    "sg:postcode":"03205",
    "sg:province":"Brandenburg",
    "wof:name":"Katholisches Pfarramt Calau",
    "wof:placetype":"venue"
},
  "geometry": {"coordinates":[13.9574594498,51.7444458008],"type":"Point"}
}