{
  "type": "Feature",
  "properties": {
    "iso:country":"DE",
    "sg:address":"Kapellenstr. 24",
    "sg:city":"Abtsgm\u00fcnd",
    "sg:phone":"+49 7366/6858",
    "sg:postcode":"73453",
    "sg:province":"Baden-W\u00fcrttemberg",
    "wof:name":"B. U. E. Abele",
    "wof:placetype":"venue"
},
  "geometry": {"coordinates":[9.96885,48.886147],"type":"Point"}
}