{
  "type": "Feature",
  "properties": {
    "iso:country":"DE",
    "sg:address":"Neue Str. 96a",
    "sg:city":"Zella",
    "sg:phone":"+49 36964/93369",
    "sg:postcode":"36452",
    "sg:province":"Th\u00fcringen",
    "wof:name":"Franz Jantsch",
    "wof:placetype":"venue"
},
  "geometry": {"coordinates":[10.1570100784,50.6263656616],"type":"Point"}
}