{
  "type": "Feature",
  "properties": {
    "iso:country":"DE",
    "sg:address":"Lotharstr. 60 A",
    "sg:city":"Hermannsburg",
    "sg:phone":"+49 5052/94274",
    "sg:postcode":"29320",
    "sg:province":"Niedersachsen",
    "wof:name":"Dr. Gisela G\u00f6rke Tier\u00e4rztin",
    "wof:placetype":"venue"
},
  "geometry": {"coordinates":[10.1050748825,52.8278388977],"type":"Point"}
}