{
  "type": "Feature",
  "properties": {
    "iso:country":"DE",
    "sg:address":"Dorfstr. 51",
    "sg:city":"Z\u00fctzen",
    "sg:phone":"+49 35452/797",
    "sg:postcode":"15938",
    "sg:province":"Brandenburg",
    "wof:name":"G\u00fcnter Kr\u00fcger",
    "wof:placetype":"venue"
},
  "geometry": {"coordinates":[13.595831871,51.9728622437],"type":"Point"}
}