{
  "type": "Feature",
  "properties": {
    "iso:country":"DE",
    "sg:address":"Eiserfelder Str. 425",
    "sg:city":"Siegen",
    "sg:phone":"+49 271/387468",
    "sg:postcode":"57080",
    "sg:province":"Nordrhein-Westfalen",
    "wof:name":"Eiscafe V. Brustolon",
    "wof:placetype":"venue"
},
  "geometry": {"coordinates":[7.988136,50.837776],"type":"Point"}
}