{
  "type": "Feature",
  "properties": {
    "iso:country":"DE",
    "sg:address":"Weingartenstr. 15",
    "sg:city":"Briedern",
    "sg:phone":"+49 2673/1737",
    "sg:postcode":"56820",
    "sg:province":"Rheinland-Pfalz",
    "wof:name":"Alfred Hirschen",
    "wof:placetype":"venue"
},
  "geometry": {"coordinates":[7.2068037987,50.1096954346],"type":"Point"}
}