{
  "type": "Feature",
  "properties": {
    "iso:country":"DE",
    "sg:address":"Kaufingerstr. 6",
    "sg:city":"M\u00fcnchen",
    "sg:phone":"+49 89/2900550",
    "sg:postcode":"80331",
    "sg:province":"Bayern",
    "wof:name":"S\u00f6hnges Optik Betriebs- Gmbh",
    "wof:placetype":"venue"
},
  "geometry": {"coordinates":[11.574582,48.137402],"type":"Point"}
}