{
  "type": "Feature",
  "properties": {
    "iso:country":"DE",
    "sg:address":"Huttenstr. 11",
    "sg:city":"Braunschweig",
    "sg:postcode":"38114",
    "sg:province":"Niedersachsen",
    "wof:name":"Datacircuits.de - Private Homepage",
    "wof:placetype":"venue"
},
  "geometry": {"coordinates":[10.517134,52.274273],"type":"Point"}
}