{
  "type": "Feature",
  "properties": {
    "iso:country":"DE",
    "sg:address":"Am Eichelacker 13",
    "sg:city":"Bernhardswald",
    "sg:phone":"+49 9407/90262",
    "sg:postcode":"93170",
    "sg:province":"Bayern",
    "wof:name":"K. Schmucker",
    "wof:placetype":"venue"
},
  "geometry": {"coordinates":[12.247973,49.089931],"type":"Point"}
}