{
  "type": "Feature",
  "properties": {
    "iso:country":"DE",
    "sg:address":"Janderstr 7",
    "sg:city":"Mannheim",
    "sg:phone":"+49 621/842150",
    "sg:postcode":"68199",
    "sg:province":"Baden-W\u00fcrttemberg",
    "wof:name":"Zeilfelder Vertrieb Gmbh",
    "wof:placetype":"venue"
},
  "geometry": {"coordinates":[8.497884,49.455231],"type":"Point"}
}