{
  "type": "Feature",
  "properties": {
    "iso:country":"DE",
    "sg:address":"Heidenbergstr. 4",
    "sg:city":"B\u00fcchenbach",
    "sg:postcode":"91186",
    "sg:province":"Bayern",
    "wof:name":"Maass & K\u00f6nig Gmbh & Co. Kg",
    "wof:placetype":"venue"
},
  "geometry": {"coordinates":[11.0220336914,49.2745018005],"type":"Point"}
}