{
  "type": "Feature",
  "properties": {
    "iso:country":"DE",
    "sg:address":"Schlo\u00df Wei\u00dfenstein",
    "sg:city":"Lauterstein",
    "sg:phone":"+49 7332/4196",
    "sg:postcode":"73111",
    "sg:province":"Baden-W\u00fcrttemberg",
    "wof:name":"Institut Zur Erforschung Der Sanskrit-schriften",
    "wof:placetype":"venue"
},
  "geometry": {"coordinates":[9.862573,48.710293],"type":"Point"}
}