{
  "type": "Feature",
  "properties": {
    "iso:country":"DE",
    "sg:address":"Blumenstr. 12",
    "sg:city":"Graben-Neudorf",
    "sg:phone":"+49 7255/9221",
    "sg:postcode":"76676",
    "sg:province":"Baden-W\u00fcrttemberg",
    "wof:name":"Andreas Sch\u00e4fer",
    "wof:placetype":"venue"
},
  "geometry": {"coordinates":[8.49627,49.170074],"type":"Point"}
}