{
  "type": "Feature",
  "properties": {
    "iso:country":"DE",
    "sg:city":"Rohlstorf",
    "sg:postcode":"23821",
    "sg:province":"Schleswig-Holstein",
    "wof:name":"Astrax: Dax-index-prognose",
    "wof:placetype":"venue"
},
  "geometry": {"coordinates":[10.373427,53.961037],"type":"Point"}
}