{
  "type": "Feature",
  "properties": {
    "iso:country":"DE",
    "sg:address":"Oberer M\u00fchlhof 6",
    "sg:city":"Daaden",
    "sg:postcode":"57567",
    "sg:province":"Rheinland-Pfalz",
    "wof:name":"B\u00e4ckerei Friedrich Scholl Gmbh",
    "wof:placetype":"venue"
},
  "geometry": {"coordinates":[7.949428,50.747627],"type":"Point"}
}