{
  "type": "Feature",
  "properties": {
    "iso:country":"DE",
    "sg:address":"Franz-Galitz-Str. 21",
    "sg:city":"Allershausen",
    "sg:postcode":"85391",
    "sg:province":"Bayern",
    "wof:name":"Telmed Medizintechnik Gmbh",
    "wof:placetype":"venue"
},
  "geometry": {"coordinates":[11.591063,48.434139],"type":"Point"}
}