{
  "type": "Feature",
  "properties": {
    "iso:country":"DE",
    "sg:address":"Lange Str. 27",
    "sg:city":"Wiebendorf",
    "sg:phone":"+49 38847/56500",
    "sg:postcode":"19258",
    "sg:province":"Mecklenburg-Vorpommern",
    "wof:name":"Tischlerei Rasmussen Und Erdt Gmbh",
    "wof:placetype":"venue"
},
  "geometry": {"coordinates":[10.722355,53.374004],"type":"Point"}
}