{
  "type": "Feature",
  "properties": {
    "iso:country":"DE",
    "sg:address":"Martin-Behaim-Str. 26",
    "sg:city":"Neu-Isenburg",
    "sg:phone":"+49 6102/327055",
    "sg:postcode":"63263",
    "sg:province":"Hessen",
    "wof:name":"Typestudio Evertz Gmbh",
    "wof:placetype":"venue"
},
  "geometry": {"coordinates":[8.716335,50.046803],"type":"Point"}
}