{
  "type": "Feature",
  "properties": {
    "iso:country":"DE",
    "sg:address":"Hamburger Str. 45",
    "sg:city":"Gifhorn",
    "sg:phone":"+49 5371/7920",
    "sg:postcode":"38518",
    "sg:province":"Niedersachsen",
    "wof:name":"Liedtke Verwaltungs Gmbh",
    "wof:placetype":"venue"
},
  "geometry": {"coordinates":[10.540346,52.507553],"type":"Point"}
}