{
  "type": "Feature",
  "properties": {
    "iso:country":"DE",
    "sg:address":"Hobeisenstr. 27",
    "sg:city":"Essen",
    "sg:phone":"+49 201/742834",
    "sg:postcode":"45147",
    "sg:province":"Nordrhein-Westfalen",
    "wof:name":"Pizzeria La Favola",
    "wof:placetype":"venue"
},
  "geometry": {"coordinates":[6.9876298904,51.4425697327],"type":"Point"}
}