{
  "type": "Feature",
  "properties": {
    "iso:country":"DE",
    "sg:address":"Lindenallee 7",
    "sg:city":"Malente",
    "sg:phone":"+49 4523/990595",
    "sg:postcode":"23714",
    "sg:province":"Schleswig-Holstein",
    "wof:name":"Nolte-franzen Immobilien Gmbh",
    "wof:placetype":"venue"
},
  "geometry": {"coordinates":[10.5572624207,54.1696014404],"type":"Point"}
}