{
  "type": "Feature",
  "properties": {
    "iso:country":"DE",
    "sg:address":"Irlachstr. 9",
    "sg:city":"Bad Aibling",
    "sg:phone":"+49 8061/2479",
    "sg:postcode":"83043",
    "sg:province":"Bayern",
    "wof:name":"Karl Stolle",
    "wof:placetype":"venue"
},
  "geometry": {"coordinates":[12.008873,47.862591],"type":"Point"}
}