{
  "type": "Feature",
  "properties": {
    "iso:country":"DE",
    "sg:address":"Scheddebrock 60",
    "sg:city":"Nordwalde",
    "sg:phone":"+49 2552/3810",
    "sg:postcode":"48356",
    "sg:province":"Nordrhein-Westfalen",
    "wof:name":"Joseph Nienau",
    "wof:placetype":"venue"
},
  "geometry": {"coordinates":[7.449825,52.119091],"type":"Point"}
}