{
  "type": "Feature",
  "properties": {
    "iso:country":"DE",
    "sg:address":"Schwedenweg 2",
    "sg:city":"Waldeck",
    "sg:phone":"+49 5634/7320",
    "sg:postcode":"34513",
    "sg:province":"Hessen",
    "wof:name":"Meyer",
    "wof:placetype":"venue"
},
  "geometry": {"coordinates":[9.0705041885,51.279499054],"type":"Point"}
}