{
  "type": "Feature",
  "properties": {
    "iso:country":"DE",
    "sg:address":"Vor Annen 39",
    "sg:city":"Delmenhorst",
    "sg:phone":"+49 4221/23590",
    "sg:postcode":"27755",
    "sg:province":"Niedersachsen",
    "wof:name":"Hinrich Hoyer",
    "wof:placetype":"venue"
},
  "geometry": {"coordinates":[8.612029,52.996548],"type":"Point"}
}