{
  "type": "Feature",
  "properties": {
    "iso:country":"DE",
    "sg:address":"Marktplatz 5",
    "sg:city":"Ampfing",
    "sg:phone":"+49 8636/212",
    "sg:postcode":"84539",
    "sg:province":"Bayern",
    "wof:name":"Franz Harter Haushaltswaren Inh. Annemarie Kupke",
    "wof:placetype":"venue"
},
  "geometry": {"coordinates":[12.4156951904,48.2552108765],"type":"Point"}
}