{
  "type": "Feature",
  "properties": {
    "iso:country":"DE",
    "sg:address":"Zur Schmiede 7",
    "sg:city":"Seggebruch",
    "sg:phone":"+49 5722/6218",
    "sg:postcode":"31691",
    "sg:province":"Niedersachsen",
    "wof:name":"Wilhelm Fauth",
    "wof:placetype":"venue"
},
  "geometry": {"coordinates":[9.086043,52.296619],"type":"Point"}
}