{
  "type": "Feature",
  "properties": {
    "iso:country":"DE",
    "sg:address":"Heinrichstr. 6",
    "sg:city":"Fulda",
    "sg:phone":"+49 661/77351",
    "sg:postcode":"36037",
    "sg:province":"Hessen",
    "wof:name":"Frankfurter Versicherungs Ag",
    "wof:placetype":"venue"
},
  "geometry": {"coordinates":[9.6813430786,50.5539665222],"type":"Point"}
}