{
  "type": "Feature",
  "properties": {
    "iso:country":"DE",
    "sg:address":"Insinger Str. 17",
    "sg:city":"B\u00fctthard",
    "sg:phone":"+49 9336/784",
    "sg:postcode":"97244",
    "sg:province":"Bayern",
    "wof:name":"Ludwig U. Edwin Balling",
    "wof:placetype":"venue"
},
  "geometry": {"coordinates":[9.919926,49.594852],"type":"Point"}
}