{
  "type": "Feature",
  "properties": {
    "iso:country":"DE",
    "sg:address":"Manderscheidtstr. 2/Ecke Langemarckstr.",
    "sg:city":"Essen",
    "sg:phone":"+49 4920/129917",
    "sg:postcode":"45141",
    "sg:province":"Nordrhein-Westfalen",
    "wof:name":"Werner Autoteile U.zubeh\u00d6r",
    "wof:placetype":"venue"
},
  "geometry": {"coordinates":[7.0385079384,51.4786300659],"type":"Point"}
}