{
  "type": "Feature",
  "properties": {
    "iso:country":"DE",
    "sg:address":"Scheyerer Str. 70b",
    "sg:city":"Pfaffenhofen",
    "sg:postcode":"85276",
    "sg:province":"Bayern",
    "wof:name":"Galant Gmbh",
    "wof:placetype":"venue"
},
  "geometry": {"coordinates":[11.4983358383,48.5271644592],"type":"Point"}
}