{
  "type": "Feature",
  "properties": {
    "iso:country":"DE",
    "sg:address":"Heinrich-Credner-Str 2",
    "sg:city":"Erfurt",
    "sg:phone":"+49 361/740290",
    "sg:postcode":"99087",
    "sg:province":"Th\u00fcringen",
    "wof:name":"Handmann Werbung Gmbh",
    "wof:placetype":"venue"
},
  "geometry": {"coordinates":[11.038690567,51.0305213928],"type":"Point"}
}