{
  "type": "Feature",
  "properties": {
    "iso:country":"DE",
    "sg:address":"Kettelerstr. 5",
    "sg:city":"Werne",
    "sg:phone":"+49 2389/531543",
    "sg:postcode":"59368",
    "sg:province":"Nordrhein-Westfalen",
    "wof:name":"Ewald Klute",
    "wof:placetype":"venue"
},
  "geometry": {"coordinates":[7.6263542175,51.6668395996],"type":"Point"}
}