{
  "type": "Feature",
  "properties": {
    "iso:country":"DE",
    "sg:city":"Langelsheim",
    "sg:phone":"+49 5326/4872",
    "sg:postcode":"38685",
    "sg:province":"Niedersachsen",
    "wof:name":"Am Kr\u00e4henberg Campingplatz",
    "wof:placetype":"venue"
},
  "geometry": {"coordinates":[10.33493,51.93911],"type":"Point"}
}