{
  "type": "Feature",
  "properties": {
    "iso:country":"DE",
    "sg:address":"Nikolsburger Str. 10",
    "sg:city":"Berlin",
    "sg:phone":"+49 30/8815850",
    "sg:postcode":"10717",
    "sg:province":"Berlin",
    "wof:name":"J\u00fcrgen Brewing Architekt",
    "wof:placetype":"venue"
},
  "geometry": {"coordinates":[13.327851,52.49437],"type":"Point"}
}