{
  "type": "Feature",
  "properties": {
    "iso:country":"DE",
    "sg:address":"L\u00f6ffelholzweg 6",
    "sg:city":"Heroldsbach",
    "sg:phone":"+49 9190/927890",
    "sg:postcode":"91336",
    "sg:province":"Bayern",
    "wof:name":"Lindenhof",
    "wof:placetype":"venue"
},
  "geometry": {"coordinates":[10.9925909042,49.6913108826],"type":"Point"}
}