{
  "type": "Feature",
  "properties": {
    "iso:country":"DE",
    "sg:address":"Zum Fischacker 3",
    "sg:city":"Eslohe",
    "sg:postcode":"59889",
    "sg:province":"Nordrhein-Westfalen",
    "wof:name":"Aldi Gmbh & Co. Kg",
    "wof:placetype":"venue"
},
  "geometry": {"coordinates":[8.174656868,51.2586669922],"type":"Point"}
}