{
  "type": "Feature",
  "properties": {
    "iso:country":"DE",
    "sg:address":"Hauptstr. 27",
    "sg:city":"Bad Pyrmont",
    "sg:phone":"+49 5281/8999",
    "sg:postcode":"31812",
    "sg:province":"Niedersachsen",
    "wof:name":"Dorfkrug",
    "wof:placetype":"venue"
},
  "geometry": {"coordinates":[9.3149433136,51.9886207581],"type":"Point"}
}