{
  "type": "Feature",
  "properties": {
    "iso:country":"DE",
    "sg:address":"Mahndorfer Heerstr. 39",
    "sg:city":"Bremen",
    "sg:phone":"+49 421/480391",
    "sg:postcode":"28307",
    "sg:province":"Bremen",
    "wof:name":"Fritz Schreiber",
    "wof:placetype":"venue"
},
  "geometry": {"coordinates":[8.941242,53.038013],"type":"Point"}
}