{
  "type": "Feature",
  "properties": {
    "iso:country":"DE",
    "sg:address":"Handwerkerhof 7",
    "sg:city":"Brandenburg",
    "sg:phone":"+49 3381/225938",
    "sg:postcode":"14770",
    "sg:province":"Brandenburg",
    "wof:name":"Ingo H\u00f6rske Transporte & Baustoffgro\u00dfhandel",
    "wof:placetype":"venue"
},
  "geometry": {"coordinates":[12.530745,52.412998],"type":"Point"}
}