{
  "type": "Feature",
  "properties": {
    "iso:country":"DE",
    "sg:address":"Lampertheimer Str. 16a",
    "sg:city":"Lampertheim",
    "sg:phone":"+49 6256/760",
    "sg:postcode":"68623",
    "sg:province":"Hessen",
    "wof:name":"Gaab It Consulting Gmbh",
    "wof:placetype":"venue"
},
  "geometry": {"coordinates":[8.5845918655,49.5983390808],"type":"Point"}
}