{
  "type": "Feature",
  "properties": {
    "iso:country":"DE",
    "sg:address":"Bahnhofstr. 2",
    "sg:city":"Wallersdorf",
    "sg:postcode":"94522",
    "sg:province":"Bayern",
    "wof:name":"Sw Multimedia Verlag E. K.",
    "wof:placetype":"venue"
},
  "geometry": {"coordinates":[12.746723175,48.7396774292],"type":"Point"}
}