{
  "type": "Feature",
  "properties": {
    "iso:country":"DE",
    "sg:address":"Bahnhofplatz 5",
    "sg:city":"Ulm",
    "sg:phone":"+49 4973/114120",
    "sg:postcode":"89073",
    "sg:province":"Baden-W\u00fcrttemberg",
    "wof:name":"Bayerische Vereinsbank Ag",
    "wof:placetype":"venue"
},
  "geometry": {"coordinates":[9.984528,48.399395],"type":"Point"}
}