{
  "type": "Feature",
  "properties": {
    "iso:country":"DE",
    "sg:address":"Bahnhofstr. 16",
    "sg:city":"Eggesin",
    "sg:postcode":"17367",
    "sg:province":"Mecklenburg-Vorpommern",
    "wof:name":"W. Tr\u00e4der",
    "wof:placetype":"venue"
},
  "geometry": {"coordinates":[14.0747423172,53.6816368103],"type":"Point"}
}