{
  "type": "Feature",
  "properties": {
    "iso:country":"DE",
    "sg:address":"Sch\u00fctzenstr. 14",
    "sg:city":"Solingen",
    "sg:phone":"+49 212/47267",
    "sg:postcode":"42659",
    "sg:province":"Nordrhein-Westfalen",
    "wof:name":"G. Kauska",
    "wof:placetype":"venue"
},
  "geometry": {"coordinates":[7.0897121429,51.1660194397],"type":"Point"}
}