{
  "type": "Feature",
  "properties": {
    "iso:country":"DE",
    "sg:address":"Dorfstr. 16",
    "sg:city":"Wiesenau",
    "sg:phone":"+49 33609/36959",
    "sg:postcode":"15295",
    "sg:province":"Brandenburg",
    "wof:name":"Hotel Garni-kastanienhof",
    "wof:placetype":"venue"
},
  "geometry": {"coordinates":[14.591342926,52.2308959961],"type":"Point"}
}