{
  "type": "Feature",
  "properties": {
    "iso:country":"DE",
    "sg:address":"Ndsstr",
    "sg:city":"Peine",
    "sg:postcode":"31226",
    "sg:province":"Niedersachsen",
    "wof:name":"Cashmaxx - Cooler Nebenverdienst Im Internet",
    "wof:placetype":"venue"
},
  "geometry": {"coordinates":[10.151953,52.30608],"type":"Point"}
}