{
  "type": "Feature",
  "properties": {
    "iso:country":"DE",
    "sg:address":"Schulstr. 19",
    "sg:city":"Kiebitzreihe",
    "sg:phone":"+49 4121/50205",
    "sg:postcode":"25368",
    "sg:province":"Schleswig-Holstein",
    "wof:name":"Heinz Emke",
    "wof:placetype":"venue"
},
  "geometry": {"coordinates":[9.6081562042,53.7819213867],"type":"Point"}
}