{
  "type": "Feature",
  "properties": {
    "iso:country":"DE",
    "sg:address":"Enzenmatt 18",
    "sg:city":"Laufenburg",
    "sg:phone":"+49 7763",
    "sg:postcode":"79725",
    "sg:province":"Baden-W\u00fcrttemberg",
    "wof:name":"Hochrhein Spielotheken",
    "wof:placetype":"venue"
},
  "geometry": {"coordinates":[8.051583,47.574604],"type":"Point"}
}