{
  "type": "Feature",
  "properties": {
    "iso:country":"DE",
    "sg:address":"Homek 10",
    "sg:city":"Erkelenz",
    "sg:phone":"+49 2431/70240",
    "sg:postcode":"41812",
    "sg:province":"Nordrhein-Westfalen",
    "wof:name":"Viktor Weisgerber",
    "wof:placetype":"venue"
},
  "geometry": {"coordinates":[6.2835049629,51.077457428],"type":"Point"}
}