{
  "type": "Feature",
  "properties": {
    "iso:country":"DE",
    "sg:address":"Lasurstr. 21",
    "sg:city":"Gera",
    "sg:phone":"+49 365/7107149",
    "sg:postcode":"07551",
    "sg:province":"Th\u00fcringen",
    "wof:name":"Raumausstattung-heinig",
    "wof:placetype":"venue"
},
  "geometry": {"coordinates":[12.087862,50.852242],"type":"Point"}
}