{
  "type": "Feature",
  "properties": {
    "iso:country":"DE",
    "sg:address":"Hohenwarter Stra\u00dfe 65",
    "sg:city":"Pfaffenhofen",
    "sg:phone":"+49 8441/803131",
    "sg:postcode":"85276",
    "sg:province":"Bayern",
    "wof:name":"Klartech Manfred R\u00f6sler",
    "wof:placetype":"venue"
},
  "geometry": {"coordinates":[11.494635,48.533497],"type":"Point"}
}