{
  "type": "Feature",
  "properties": {
    "iso:country":"DE",
    "sg:address":"Maximilianstr. 14",
    "sg:city":"Aschaffenburg",
    "sg:phone":"+49 6021/460101",
    "sg:postcode":"63739",
    "sg:province":"Bayern",
    "wof:name":"Amei Ladenbau Gmbh",
    "wof:placetype":"venue"
},
  "geometry": {"coordinates":[9.136647,49.979519],"type":"Point"}
}