{
  "type": "Feature",
  "properties": {
    "iso:country":"DE",
    "sg:address":"Hauptstr. 93",
    "sg:city":"Frensdorf",
    "sg:postcode":"96158",
    "sg:province":"Bayern",
    "wof:name":"Alfred Beck Komponist",
    "wof:placetype":"venue"
},
  "geometry": {"coordinates":[10.8665304184,49.8152809143],"type":"Point"}
}