{
  "type": "Feature",
  "properties": {
    "iso:country":"DE",
    "sg:address":"Kirchgasse 13",
    "sg:city":"Gangkofen",
    "sg:phone":"+49 8722/511",
    "sg:postcode":"84140",
    "sg:province":"Bayern",
    "wof:name":"Pizzeria Harlekin",
    "wof:placetype":"venue"
},
  "geometry": {"coordinates":[12.5635433197,48.4379005432],"type":"Point"}
}