{
  "type": "Feature",
  "properties": {
    "iso:country":"DE",
    "sg:address":"Alte Burgwedeler Str. 11",
    "sg:city":"Burgwedel",
    "sg:phone":"+49 5135/774",
    "sg:postcode":"30938",
    "sg:province":"Niedersachsen",
    "wof:name":"Maniewski Big Game Gmbh",
    "wof:placetype":"venue"
},
  "geometry": {"coordinates":[9.8516750336,52.5607070923],"type":"Point"}
}