{
  "type": "Feature",
  "properties": {
    "iso:country":"DE",
    "sg:address":"Am Rasen 14",
    "sg:city":"Lindewerra",
    "sg:phone":"+49 36087/98300",
    "sg:postcode":"37318",
    "sg:province":"Th\u00fcringen",
    "wof:name":"Stockmanufaktur Gmbh & Co. Kg",
    "wof:placetype":"venue"
},
  "geometry": {"coordinates":[9.946694,51.313629],"type":"Point"}
}