{
  "type": "Feature",
  "properties": {
    "iso:country":"DE",
    "sg:address":"Hauptstr. 16",
    "sg:city":"Kobern-Gondorf",
    "sg:phone":"+49 2607/1557",
    "sg:postcode":"56330",
    "sg:province":"Rheinland-Pfalz",
    "wof:name":"Frank Gmbh",
    "wof:placetype":"venue"
},
  "geometry": {"coordinates":[7.457221,50.289619],"type":"Point"}
}