{
  "type": "Feature",
  "properties": {
    "iso:country":"DE",
    "sg:address":"Neumannstr. 39",
    "sg:city":"Berlin",
    "sg:phone":"+49 30/4717381",
    "sg:postcode":"13189",
    "sg:province":"Berlin",
    "wof:name":"Schneiders Sprach-service",
    "wof:placetype":"venue"
},
  "geometry": {"coordinates":[13.419754,52.568043],"type":"Point"}
}