{
  "type": "Feature",
  "properties": {
    "iso:country":"DE",
    "sg:address":"Rotkehlchenweg 8",
    "sg:city":"Peine",
    "sg:phone":"+49 5171/13420",
    "sg:postcode":"31228",
    "sg:province":"Niedersachsen",
    "wof:name":"Werner Wiesrecker",
    "wof:placetype":"venue"
},
  "geometry": {"coordinates":[10.23411,52.341831],"type":"Point"}
}