{
  "type": "Feature",
  "properties": {
    "iso:country":"DE",
    "sg:address":"Elseyer Str. 9",
    "sg:city":"Hagen",
    "sg:phone":"+49 2334/51069",
    "sg:postcode":"58119",
    "sg:province":"Nordrhein-Westfalen",
    "wof:name":"J\u00fcrgen H\u00f6rdemann",
    "wof:placetype":"venue"
},
  "geometry": {"coordinates":[7.5584540367,51.3616638184],"type":"Point"}
}