{
  "type": "Feature",
  "properties": {
    "iso:country":"DE",
    "sg:address":"Wegscheide 5",
    "sg:city":"Randersacker",
    "sg:phone":"+49 931/708327",
    "sg:postcode":"97236",
    "sg:province":"Bayern",
    "wof:name":"Urlaubs Weinstuben",
    "wof:placetype":"venue"
},
  "geometry": {"coordinates":[9.9801301956,49.7604484558],"type":"Point"}
}