{
  "type": "Feature",
  "properties": {
    "iso:country":"DE",
    "sg:address":"Albert-Einstein-Str 3",
    "sg:city":"Ilmenau",
    "sg:phone":"+49 3677/20090",
    "sg:postcode":"98693",
    "sg:province":"Th\u00fcringen",
    "wof:name":"Inverso Gesellschaft F\u00fcr Innovative Versicherungssoftware Mbh",
    "wof:placetype":"venue"
},
  "geometry": {"coordinates":[10.9304952621,50.6815223694],"type":"Point"}
}