{
  "type": "Feature",
  "properties": {
    "iso:country":"DE",
    "sg:address":"Westerbachstr. 23",
    "sg:city":"Kronberg",
    "sg:phone":"+49 6173/92690",
    "sg:postcode":"61476",
    "sg:province":"Hessen",
    "wof:name":"Deutscher Verband Fl\u00fcssiggas E. V.",
    "wof:placetype":"venue"
},
  "geometry": {"coordinates":[8.527759552,50.1726264954],"type":"Point"}
}