{
  "type": "Feature",
  "properties": {
    "iso:country":"DE",
    "sg:address":"Am Bredschlag 15",
    "sg:city":"B\u00fcdelsdorf",
    "sg:postcode":"24782",
    "sg:province":"Schleswig-Holstein",
    "wof:name":"Kr-stadthaus Gmbh & Co. Kg",
    "wof:placetype":"venue"
},
  "geometry": {"coordinates":[9.690422,54.313602],"type":"Point"}
}