{
  "type": "Feature",
  "properties": {
    "iso:country":"DE",
    "sg:address":"Neusch\u00f6nberger Str",
    "sg:city":"D\u00fcrrhennersdorf",
    "sg:phone":"+49 35872",
    "sg:postcode":"02708",
    "sg:province":"Sachsen",
    "wof:name":"Kopsch Bauelemente",
    "wof:placetype":"venue"
},
  "geometry": {"coordinates":[14.582338,51.041378],"type":"Point"}
}