{
  "type": "Feature",
  "properties": {
    "iso:country":"DE",
    "sg:address":"Theodor-K\u00f6rner-Str. 9",
    "sg:city":"Ebhausen",
    "sg:phone":"+49 7458/1070",
    "sg:postcode":"72224",
    "sg:province":"Baden-W\u00fcrttemberg",
    "wof:name":"Artur Gr\u00fcnder Schaufenstergestaltung",
    "wof:placetype":"venue"
},
  "geometry": {"coordinates":[8.6614952087,48.6064338684],"type":"Point"}
}