{
  "type": "Feature",
  "properties": {
    "iso:country":"DE",
    "sg:address":"Postfach 100 329",
    "sg:city":"Burgdorf",
    "sg:postcode":"31288",
    "sg:province":"Niedersachsen",
    "wof:name":"Kuk-service.de",
    "wof:placetype":"venue"
},
  "geometry": {"coordinates":[10.006649971,52.4464302063],"type":"Point"}
}