{
  "type": "Feature",
  "properties": {
    "iso:country":"DE",
    "sg:address":"Alt-Tempelhof 21",
    "sg:city":"Berlin",
    "sg:phone":"+49 30/7579150",
    "sg:postcode":"12103",
    "sg:province":"Berlin",
    "wof:name":"Bhw Bausparkasse Ag",
    "wof:placetype":"venue"
},
  "geometry": {"coordinates":[13.385204,52.465611],"type":"Point"}
}