{
  "type": "Feature",
  "properties": {
    "iso:country":"DE",
    "sg:address":"Schartaustr. 1-3",
    "sg:city":"Magdeburg",
    "sg:phone":"+49 391/532860",
    "sg:postcode":"39106",
    "sg:province":"Sachsen-Anhalt",
    "wof:name":"Magdeburger M\u00fchlenwerke Beteiligungs Gmbh",
    "wof:placetype":"venue"
},
  "geometry": {"coordinates":[11.654504,52.145813],"type":"Point"}
}