{
  "type": "Feature",
  "properties": {
    "iso:country":"DE",
    "sg:address":"Borngasse 6",
    "sg:city":"Kirchhain",
    "sg:phone":"+49 6422/3010",
    "sg:postcode":"35274",
    "sg:province":"Hessen",
    "wof:name":"Kaufhaus Rudolf Georg Mittler Gmbh & Co. Kg",
    "wof:placetype":"venue"
},
  "geometry": {"coordinates":[8.922343,50.821217],"type":"Point"}
}