{
  "type": "Feature",
  "properties": {
    "iso:country":"DE",
    "sg:address":"Gartenstr. 50",
    "sg:city":"D\u00fcsseldorf",
    "sg:phone":"+49 211/5134350",
    "sg:postcode":"40479",
    "sg:province":"Nordrhein-Westfalen",
    "wof:name":"Hotel Ufer Garni Gmbh",
    "wof:placetype":"venue"
},
  "geometry": {"coordinates":[6.785392,51.232132],"type":"Point"}
}