{
  "type": "Feature",
  "properties": {
    "iso:country":"DE",
    "sg:address":"Marktstr. 48a",
    "sg:city":"Wanfried",
    "sg:phone":"+49 5655/612",
    "sg:postcode":"37281",
    "sg:province":"Hessen",
    "wof:name":"2 Rad Rabe Motorger\u00e4te Gmbh",
    "wof:placetype":"venue"
},
  "geometry": {"coordinates":[10.171628952,51.180480957],"type":"Point"}
}