{
  "type": "Feature",
  "properties": {
    "iso:country":"DE",
    "sg:address":"Lauheide",
    "sg:city":"Telgte",
    "sg:phone":"+49 2504/7895",
    "sg:postcode":"48291",
    "sg:province":"Nordrhein-Westfalen",
    "wof:name":"Woltering",
    "wof:placetype":"venue"
},
  "geometry": {"coordinates":[7.740901,52.002193],"type":"Point"}
}