{
  "type": "Feature",
  "properties": {
    "iso:country":"DE",
    "sg:address":"Mortelstr. 27",
    "sg:city":"Waldheim",
    "sg:phone":"+49 34327/54254",
    "sg:postcode":"04736",
    "sg:province":"Sachsen",
    "wof:name":"Gasevertrieb U. Rudolph Gmbh",
    "wof:placetype":"venue"
},
  "geometry": {"coordinates":[13.0311698914,51.0674705505],"type":"Point"}
}