{
  "type": "Feature",
  "properties": {
    "iso:country":"DE",
    "sg:address":"Drewenzweg 3",
    "sg:city":"Hannover",
    "sg:phone":"+49 511/527447",
    "sg:postcode":"30559",
    "sg:province":"Niedersachsen",
    "wof:name":"Wilhelm Detert Ingenieur",
    "wof:placetype":"venue"
},
  "geometry": {"coordinates":[9.8536195755,52.3671112061],"type":"Point"}
}