{
  "type": "Feature",
  "properties": {
    "iso:country":"DE",
    "sg:address":"Sunderner Str. 34",
    "sg:city":"Balve",
    "sg:phone":"+49 2375/4155",
    "sg:postcode":"58802",
    "sg:province":"Nordrhein-Westfalen",
    "wof:name":"Z\u00f6llner Verm\u00f6gens- Verwaltuings Gmbh",
    "wof:placetype":"venue"
},
  "geometry": {"coordinates":[7.8907461166,51.3103637695],"type":"Point"}
}