{
  "type": "Feature",
  "properties": {
    "iso:country":"DE",
    "sg:address":"Uhlandstr. 15",
    "sg:city":"Herten",
    "sg:phone":"+49 2366/1413",
    "sg:postcode":"45699",
    "sg:province":"Nordrhein-Westfalen",
    "wof:name":"Cetetherm W\u00e4rme- Tauschersysteme Gmbh",
    "wof:placetype":"venue"
},
  "geometry": {"coordinates":[7.1491990089,51.5980262756],"type":"Point"}
}