{
  "type": "Feature",
  "properties": {
    "iso:country":"DE",
    "sg:address":"Klinglesweg 1",
    "sg:city":"Ispringen",
    "sg:phone":"+49 7231/984123",
    "sg:postcode":"75228",
    "sg:province":"Baden-W\u00fcrttemberg",
    "wof:name":"Erich Reinhardt Gmbh",
    "wof:placetype":"venue"
},
  "geometry": {"coordinates":[8.6780796051,48.9138793945],"type":"Point"}
}