{
  "type": "Feature",
  "properties": {
    "iso:country":"DE",
    "sg:address":"Senfte 13",
    "sg:city":"Suhl",
    "sg:postcode":"98527",
    "sg:province":"Th\u00fcringen",
    "wof:name":"Empire Verlags-handels- Und Imob. Gmbh",
    "wof:placetype":"venue"
},
  "geometry": {"coordinates":[10.6880264282,50.6058006287],"type":"Point"}
}