{
  "type": "Feature",
  "properties": {
    "iso:country":"DE",
    "sg:address":"Neckartalstr. 5",
    "sg:city":"Reutlingen",
    "sg:phone":"+49 7121/600068",
    "sg:postcode":"72768",
    "sg:province":"Baden-W\u00fcrttemberg",
    "wof:name":"Vereinsgastst\u00e4tte Sch\u00fctzen- Verein Altenburg 1923 E. V.",
    "wof:placetype":"venue"
},
  "geometry": {"coordinates":[9.1816101074,48.5510826111],"type":"Point"}
}