{
  "type": "Feature",
  "properties": {
    "iso:country":"DE",
    "sg:address":"G\u00fcglinger Str. 9",
    "sg:city":"Eppingen",
    "sg:phone":"+49 7138/6523",
    "sg:postcode":"75031",
    "sg:province":"Baden-W\u00fcrttemberg",
    "wof:name":"G\u00e4stehaus Traube Friedrich Renninger",
    "wof:placetype":"venue"
},
  "geometry": {"coordinates":[8.9743480682,49.0999145508],"type":"Point"}
}