{
  "type": "Feature",
  "properties": {
    "iso:country":"DE",
    "sg:address":"Poststr. 41",
    "sg:city":"Eberswalde",
    "sg:phone":"+49 3334/363582",
    "sg:postcode":"16227",
    "sg:province":"Brandenburg",
    "wof:name":"Hbs - Holzverarbeitung - Bodenverwertung -",
    "wof:placetype":"venue"
},
  "geometry": {"coordinates":[13.7258329391,52.8369293213],"type":"Point"}
}