{
  "type": "Feature",
  "properties": {
    "iso:country":"DE",
    "sg:address":"Frenkingstr. 9",
    "sg:city":"Bochum",
    "sg:phone":"+49 234/2970394",
    "sg:postcode":"44894",
    "sg:province":"Nordrhein-Westfalen",
    "wof:name":"Neumann Recycling-service E.k.",
    "wof:placetype":"venue"
},
  "geometry": {"coordinates":[7.2913980484,51.4770355225],"type":"Point"}
}