{
  "type": "Feature",
  "properties": {
    "iso:country":"DE",
    "sg:address":"Wulfentange 2",
    "sg:city":"Surwold",
    "sg:phone":"+49 4965/990264",
    "sg:postcode":"26903",
    "sg:province":"Niedersachsen",
    "wof:name":"Oma Kortes Hus",
    "wof:placetype":"venue"
},
  "geometry": {"coordinates":[7.4858160019,53.0031776428],"type":"Point"}
}