{
  "type": "Feature",
  "properties": {
    "iso:country":"DE",
    "sg:address":"Hanekamp 21",
    "sg:city":"Brakel",
    "sg:phone":"+49 5272/6500",
    "sg:postcode":"33034",
    "sg:province":"Nordrhein-Westfalen",
    "wof:name":"J\u00fcrgen Fechner Lotto Zeitschriften",
    "wof:placetype":"venue"
},
  "geometry": {"coordinates":[9.1818180084,51.7156562805],"type":"Point"}
}