{
  "type": "Feature",
  "properties": {
    "iso:country":"DE",
    "sg:address":"M\u00fchlenstr. 1",
    "sg:city":"Friedland",
    "sg:phone":"+49 39601/26779",
    "sg:postcode":"17098",
    "sg:province":"Mecklenburg-Vorpommern",
    "wof:name":"Heimatmuseum",
    "wof:placetype":"venue"
},
  "geometry": {"coordinates":[13.5508956909,53.6711196899],"type":"Point"}
}