{
  "type": "Feature",
  "properties": {
    "iso:country":"DE",
    "sg:address":"Kaulbachstr. 64",
    "sg:city":"Essen",
    "sg:phone":"+49 201/703144",
    "sg:postcode":"45147",
    "sg:province":"Nordrhein-Westfalen",
    "wof:name":"Hans-j\u00fcrgen Berghane Architekt",
    "wof:placetype":"venue"
},
  "geometry": {"coordinates":[6.981844,51.438168],"type":"Point"}
}