{
  "type": "Feature",
  "properties": {
    "iso:country":"DE",
    "sg:address":"Brommerstr. 5",
    "sg:city":"Stuttgart",
    "sg:phone":"+49 711/7353013",
    "sg:postcode":"70563",
    "sg:province":"Baden-W\u00fcrttemberg",
    "wof:name":"J. Schwarz",
    "wof:placetype":"venue"
},
  "geometry": {"coordinates":[9.111131,48.733322],"type":"Point"}
}