{
  "type": "Feature",
  "properties": {
    "iso:country":"DE",
    "sg:address":"Dedelebener Str. 201",
    "sg:city":"Rohrsheim",
    "sg:phone":"+49 39426/473",
    "sg:postcode":"38836",
    "sg:province":"Sachsen-Anhalt",
    "wof:name":"Wolfgang Bock",
    "wof:placetype":"venue"
},
  "geometry": {"coordinates":[10.8353919983,52.0202255249],"type":"Point"}
}