{
  "type": "Feature",
  "properties": {
    "iso:country":"DE",
    "sg:address":"Kroatengasse 10",
    "sg:city":"W\u00fcrzburg",
    "sg:phone":"+49 931/573222",
    "sg:postcode":"97070",
    "sg:province":"Bayern",
    "wof:name":"Kopie Team W\u00fcrzburg",
    "wof:placetype":"venue"
},
  "geometry": {"coordinates":[9.9406929016,49.7979774475],"type":"Point"}
}