{
  "type": "Feature",
  "properties": {
    "iso:country":"DE",
    "sg:address":"Bergsteinstr. 41",
    "sg:city":"Neustadt",
    "sg:phone":"+49 6321/2606",
    "sg:postcode":"67434",
    "sg:province":"Rheinland-Pfalz",
    "wof:name":"Orient-teppich-handel Begin Inh. Anneliese Begin",
    "wof:placetype":"venue"
},
  "geometry": {"coordinates":[8.1178970337,49.3369636536],"type":"Point"}
}