{
  "type": "Feature",
  "properties": {
    "iso:country":"DE",
    "sg:address":"Obertorstr. 16",
    "sg:city":"Schl\u00fcchtern",
    "sg:phone":"+49 6661/2016",
    "sg:postcode":"36381",
    "sg:province":"Hessen",
    "wof:name":"Schuhhaus Flemmig Inh. Hans-ludwig Flemmig E. K.",
    "wof:placetype":"venue"
},
  "geometry": {"coordinates":[9.5247154236,50.3480796814],"type":"Point"}
}