{
  "type": "Feature",
  "properties": {
    "iso:country":"DE",
    "sg:address":"Marktplatz 8",
    "sg:city":"Hauzenberg",
    "sg:phone":"+49 8586/96200",
    "sg:postcode":"94051",
    "sg:province":"Bayern",
    "wof:name":"Rma",
    "wof:placetype":"venue"
},
  "geometry": {"coordinates":[13.6240196228,48.6512908936],"type":"Point"}
}