{
  "type": "Feature",
  "properties": {
    "iso:country":"DE",
    "sg:address":"Kapellenstr. 13a",
    "sg:city":"Hofstetten",
    "sg:postcode":"86928",
    "sg:province":"Bayern",
    "wof:name":"I & S Dienstleistungen",
    "wof:placetype":"venue"
},
  "geometry": {"coordinates":[10.952297,47.999809],"type":"Point"}
}