{
  "type": "Feature",
  "properties": {
    "iso:country":"DE",
    "sg:address":"Markttwiete 8 - 10",
    "sg:city":"Bad Schwartau",
    "sg:phone":"+49 451/208011",
    "sg:postcode":"23611",
    "sg:province":"Schleswig-Holstein",
    "wof:name":"Werkstatt F\u00fcr Schmuckgestaltung",
    "wof:placetype":"venue"
},
  "geometry": {"coordinates":[10.697267,53.918442],"type":"Point"}
}