{
  "type": "Feature",
  "properties": {
    "iso:country":"DE",
    "sg:address":"Neukirchener Str. 27",
    "sg:city":"Rheinbach",
    "sg:phone":"+49 2226/14416",
    "sg:postcode":"53359",
    "sg:province":"Nordrhein-Westfalen",
    "wof:name":"Hermann Rheindorf",
    "wof:placetype":"venue"
},
  "geometry": {"coordinates":[6.9283528328,50.5889205933],"type":"Point"}
}