{
  "type": "Feature",
  "properties": {
    "iso:country":"DE",
    "sg:address":"Wiegmannstr. 5",
    "sg:city":"Stadthagen",
    "sg:postcode":"31655",
    "sg:province":"Niedersachsen",
    "wof:name":"St\u00fcnckel Verm\u00f6gens- Verwaltungen Gmbh",
    "wof:placetype":"venue"
},
  "geometry": {"coordinates":[9.2015619278,52.3187637329],"type":"Point"}
}