{
  "type": "Feature",
  "properties": {
    "iso:country":"DE",
    "sg:address":"Meisenstieg 13",
    "sg:city":"Magdeburg",
    "sg:phone":"+49 391/7216498",
    "sg:postcode":"39110",
    "sg:province":"Sachsen-Anhalt",
    "wof:name":"Richard Wittig",
    "wof:placetype":"venue"
},
  "geometry": {"coordinates":[11.581319,52.137146],"type":"Point"}
}