{
  "type": "Feature",
  "properties": {
    "iso:country":"DE",
    "sg:address":"Carl-Zeiss-Str.2",
    "sg:city":"Koblenz",
    "sg:phone":"+49 4926/180750",
    "sg:postcode":"56070",
    "sg:province":"Rheinland-Pfalz",
    "wof:name":"Interform Moebel Rombelsheim Gmbh & Co Kg",
    "wof:placetype":"venue"
},
  "geometry": {"coordinates":[7.5612921715,50.3864326477],"type":"Point"}
}