{
  "type": "Feature",
  "properties": {
    "iso:country":"DE",
    "sg:address":"Voedestr. 61",
    "sg:city":"Bochum",
    "sg:phone":"+49 2327/89795",
    "sg:postcode":"44866",
    "sg:province":"Nordrhein-Westfalen",
    "wof:name":"Restaurant Akropolis",
    "wof:placetype":"venue"
},
  "geometry": {"coordinates":[7.1415910721,51.4817733765],"type":"Point"}
}