{
  "type": "Feature",
  "properties": {
    "iso:country":"DE",
    "sg:address":"Sch\u00fctzenh\u00f6he 12",
    "sg:city":"Dresden",
    "sg:phone":"+49 4935/1829050",
    "sg:postcode":"01099",
    "sg:province":"Sachsen",
    "wof:name":"Kassen\u00c4rztliche Vereinigung Sachsen",
    "wof:placetype":"venue"
},
  "geometry": {"coordinates":[13.75173,51.08083],"type":"Point"}
}