{
  "type": "Feature",
  "properties": {
    "iso:country":"DE",
    "sg:address":"Zur Kirche 2",
    "sg:city":"Greding",
    "sg:phone":"+49 8469/409",
    "sg:postcode":"91171",
    "sg:province":"Bayern",
    "wof:name":"Gei\u00dfler",
    "wof:placetype":"venue"
},
  "geometry": {"coordinates":[11.3404722214,49.0984992981],"type":"Point"}
}