{
  "type": "Feature",
  "properties": {
    "iso:country":"DE",
    "sg:address":"Grenzstr. 2",
    "sg:city":"Neuhaus",
    "sg:phone":"+49 38841/21659",
    "sg:postcode":"19273",
    "sg:province":"Mecklenburg-Vorpommern",
    "wof:name":"Manfred Ickert",
    "wof:placetype":"venue"
},
  "geometry": {"coordinates":[10.931965,53.282539],"type":"Point"}
}