{
  "type": "Feature",
  "properties": {
    "iso:country":"DE",
    "sg:address":"Notzentalweg 2",
    "sg:city":"Geislingen",
    "sg:phone":"+49 7331/66275",
    "sg:postcode":"73312",
    "sg:province":"Baden-W\u00fcrttemberg",
    "wof:name":"Erotikshop.treibs-mal-wieder",
    "wof:placetype":"venue"
},
  "geometry": {"coordinates":[9.840331,48.619308],"type":"Point"}
}