{
  "type": "Feature",
  "properties": {
    "iso:country":"DE",
    "sg:address":"Tile-Wardenberg-Str. 24",
    "sg:city":"Berlin",
    "sg:postcode":"10555",
    "sg:province":"Berlin",
    "wof:name":"Gateway R\u00fcckversicherungs- Vermittlungs Gmbh",
    "wof:placetype":"venue"
},
  "geometry": {"coordinates":[13.3327932358,52.519618988],"type":"Point"}
}