{
  "type": "Feature",
  "properties": {
    "iso:country":"DE",
    "sg:address":"Am Wembach 31",
    "sg:city":"Reinheim",
    "sg:phone":"+49 6162/2729",
    "sg:postcode":"64354",
    "sg:province":"Hessen",
    "wof:name":"Mmci Multi - Media - Consulting Gmbh",
    "wof:placetype":"venue"
},
  "geometry": {"coordinates":[8.8410024643,49.8312187195],"type":"Point"}
}