{
  "type": "Feature",
  "properties": {
    "iso:country":"DE",
    "sg:address":"Bergweg 1",
    "sg:city":"Donaueschingen",
    "sg:phone":"+49 771/13811",
    "sg:postcode":"78166",
    "sg:province":"Baden-W\u00fcrttemberg",
    "wof:name":"Micano",
    "wof:placetype":"venue"
},
  "geometry": {"coordinates":[8.4932899475,47.9490699768],"type":"Point"}
}