{
  "type": "Feature",
  "properties": {
    "iso:country":"DE",
    "sg:address":"Hellersbergstr. 12",
    "sg:city":"Neuss",
    "sg:postcode":"41460",
    "sg:province":"Nordrhein-Westfalen",
    "wof:name":"Acoreus Collection Service Gmbh",
    "wof:placetype":"venue"
},
  "geometry": {"coordinates":[6.706736,51.193787],"type":"Point"}
}