{
  "type": "Feature",
  "properties": {
    "iso:country":"DE",
    "sg:address":"Harburger Str. 12",
    "sg:city":"Rotenburg",
    "sg:phone":"+49 4261/92960",
    "sg:postcode":"27356",
    "sg:province":"Niedersachsen",
    "wof:name":"Fritz Gehrke Und Erik Erdmann Steuerberater Und",
    "wof:placetype":"venue"
},
  "geometry": {"coordinates":[9.4109706879,53.1120223999],"type":"Point"}
}