{
  "type": "Feature",
  "properties": {
    "iso:country":"DE",
    "sg:address":"Kurze Umbr\u00fcche 2",
    "sg:city":"Haiterbach",
    "sg:phone":"+49 7456/593",
    "sg:postcode":"72221",
    "sg:province":"Baden-W\u00fcrttemberg",
    "wof:name":"F. Frey Gmbh & Co.",
    "wof:placetype":"venue"
},
  "geometry": {"coordinates":[8.6277780533,48.504196167],"type":"Point"}
}