{
  "type": "Feature",
  "properties": {
    "iso:country":"DE",
    "sg:address":"Kammerlweg 11",
    "sg:city":"Icking",
    "sg:phone":"+49 8178/5604",
    "sg:postcode":"82057",
    "sg:province":"Bayern",
    "wof:name":"Frank Lafogler Architekt",
    "wof:placetype":"venue"
},
  "geometry": {"coordinates":[11.433463,47.951946],"type":"Point"}
}