{
  "type": "Feature",
  "properties": {
    "iso:country":"DE",
    "sg:address":"Marktstr. 2",
    "sg:city":"Bremen",
    "sg:postcode":"28195",
    "sg:province":"Bremen",
    "wof:name":"Verein Der Ehemaligen Der Deutschen Au\u00dfenhandels-und",
    "wof:placetype":"venue"
},
  "geometry": {"coordinates":[8.8077373505,53.0748634338],"type":"Point"}
}