{
  "type": "Feature",
  "properties": {
    "iso:country":"DE",
    "sg:address":"Funkenburgstr. 28",
    "sg:city":"Leipzig",
    "sg:phone":"+49 341/4212500",
    "sg:postcode":"04105",
    "sg:province":"Sachsen",
    "wof:name":"Bhm B\u00f6scher H\u00e4ber Muschter Partner-ingenieurgesellschaft",
    "wof:placetype":"venue"
},
  "geometry": {"coordinates":[12.3616228104,51.3465003967],"type":"Point"}
}