{
  "type": "Feature",
  "properties": {
    "iso:country":"DE",
    "sg:address":"Hellersdorfer Str. 70",
    "sg:city":"Berlin",
    "sg:postcode":"12619",
    "sg:province":"Berlin",
    "wof:name":"Voyager Shoe Commerce Gmbh",
    "wof:placetype":"venue"
},
  "geometry": {"coordinates":[13.5891399384,52.5175209045],"type":"Point"}
}