{
  "type": "Feature",
  "properties": {
    "iso:country":"DE",
    "sg:address":"Alte Kasseler Str. 52",
    "sg:city":"Marburg",
    "sg:phone":"+49 6421/62240",
    "sg:postcode":"35039",
    "sg:province":"Hessen",
    "wof:name":"Helmut K\u00f6hm",
    "wof:placetype":"venue"
},
  "geometry": {"coordinates":[8.7733411789,50.8263893127],"type":"Point"}
}