{
  "type": "Feature",
  "properties": {
    "iso:country":"DE",
    "sg:address":"Bonner Str. 212",
    "sg:city":"Sankt Augustin",
    "sg:phone":"+49 2241/93430",
    "sg:postcode":"53757",
    "sg:province":"Nordrhein-Westfalen",
    "wof:name":"Kirmse Und Partner Ingenieure",
    "wof:placetype":"venue"
},
  "geometry": {"coordinates":[7.1858429909,50.7738418579],"type":"Point"}
}