{
  "type": "Feature",
  "properties": {
    "iso:country":"DE",
    "sg:address":"K\u00f6nigsworther Str. 6",
    "sg:city":"Hannover",
    "sg:phone":"+49 511/709749",
    "sg:postcode":"30167",
    "sg:province":"Niedersachsen",
    "wof:name":"Bierstube Bei Taki",
    "wof:placetype":"venue"
},
  "geometry": {"coordinates":[9.7221012115,52.3783149719],"type":"Point"}
}