{
  "type": "Feature",
  "properties": {
    "iso:country":"DE",
    "sg:address":"Sendelbacher Str. 10",
    "sg:city":"Lohr",
    "sg:postcode":"97816",
    "sg:province":"Bayern",
    "wof:name":"Reiner Stegerwald Gmbh",
    "wof:placetype":"venue"
},
  "geometry": {"coordinates":[9.583944,49.991814],"type":"Point"}
}