{
  "type": "Feature",
  "properties": {
    "iso:country":"DE",
    "sg:address":"Schwanenstr. 132",
    "sg:city":"Solingen",
    "sg:postcode":"42697",
    "sg:province":"Nordrhein-Westfalen",
    "wof:name":"K Und Gesellschaft F\u00fcr Reha- Biliation Und Therapie Mbh",
    "wof:placetype":"venue"
},
  "geometry": {"coordinates":[6.9842710495,51.1547775269],"type":"Point"}
}