{
  "type": "Feature",
  "properties": {
    "iso:country":"DE",
    "sg:address":"Herrenstr. 23 a",
    "sg:city":"M\u00fcnster",
    "sg:phone":"+49 2506/1594",
    "sg:postcode":"48167",
    "sg:province":"Nordrhein-Westfalen",
    "wof:name":"August Diekrup",
    "wof:placetype":"venue"
},
  "geometry": {"coordinates":[7.731251,51.918118],"type":"Point"}
}