{
  "type": "Feature",
  "properties": {
    "iso:country":"DE",
    "sg:address":"Blumenstr. 23",
    "sg:city":"Du\u00dflingen",
    "sg:phone":"+49 7072/2148",
    "sg:postcode":"72144",
    "sg:province":"Baden-W\u00fcrttemberg",
    "wof:name":"Picknick",
    "wof:placetype":"venue"
},
  "geometry": {"coordinates":[9.0586872101,48.4474411011],"type":"Point"}
}