{
  "type": "Feature",
  "properties": {
    "iso:country":"DE",
    "sg:address":"Hauptstr. 7",
    "sg:city":"Gro\u00df Buchwald",
    "sg:phone":"+49 4322/6336",
    "sg:postcode":"24582",
    "sg:province":"Schleswig-Holstein",
    "wof:name":"G\u00e4stehaus Zum Alten Fritz",
    "wof:placetype":"venue"
},
  "geometry": {"coordinates":[10.0796957016,54.1635246277],"type":"Point"}
}