{
  "type": "Feature",
  "properties": {
    "iso:country":"DE",
    "sg:address":"Wasserstr. 13",
    "sg:city":"Donaueschingen",
    "sg:phone":"+49 771/832270",
    "sg:postcode":"78166",
    "sg:province":"Baden-W\u00fcrttemberg",
    "wof:name":"Margot Lambrecht",
    "wof:placetype":"venue"
},
  "geometry": {"coordinates":[8.4947853088,47.9513473511],"type":"Point"}
}