{
  "type": "Feature",
  "properties": {
    "iso:country":"DE",
    "sg:address":"Poststr. 23",
    "sg:city":"Nettetal",
    "sg:phone":"+49 2157/5698",
    "sg:postcode":"41334",
    "sg:province":"Nordrhein-Westfalen",
    "wof:name":"Peter Schr\u00f6mbges Steuerberater",
    "wof:placetype":"venue"
},
  "geometry": {"coordinates":[6.2028670311,51.3233337402],"type":"Point"}
}