{
  "type": "Feature",
  "properties": {
    "iso:country":"DE",
    "sg:address":"Egergasse 2",
    "sg:city":"M\u00f6ttingen",
    "sg:phone":"+49 9083/301",
    "sg:postcode":"86753",
    "sg:province":"Bayern",
    "wof:name":"Friedrich Hubel",
    "wof:placetype":"venue"
},
  "geometry": {"coordinates":[10.586148,48.811367],"type":"Point"}
}