{
  "type": "Feature",
  "properties": {
    "iso:country":"DE",
    "sg:address":"Schnackenburgallee 7",
    "sg:city":"Hamburg",
    "sg:phone":"+49 40/8517140",
    "sg:postcode":"22525",
    "sg:province":"Hamburg",
    "wof:name":"Diebenau Kg",
    "wof:placetype":"venue"
},
  "geometry": {"coordinates":[9.9183626175,53.5723342896],"type":"Point"}
}