{
  "type": "Feature",
  "properties": {
    "iso:country":"DE",
    "sg:address":"Waldstr. 9",
    "sg:city":"Filderstadt",
    "sg:phone":"+49 711/776005",
    "sg:postcode":"70794",
    "sg:province":"Baden-W\u00fcrttemberg",
    "wof:name":"Werner M\u00fcller Architekt",
    "wof:placetype":"venue"
},
  "geometry": {"coordinates":[9.184774,48.658936],"type":"Point"}
}