{
  "type": "Feature",
  "properties": {
    "iso:country":"DE",
    "sg:address":"Hermann-Staudinger-Str. 8",
    "sg:city":"Viernheim",
    "sg:phone":"+49 6204/8764",
    "sg:postcode":"68519",
    "sg:province":"Hessen",
    "wof:name":"Volker Friderich",
    "wof:placetype":"venue"
},
  "geometry": {"coordinates":[8.59156,49.554615],"type":"Point"}
}