{
  "type": "Feature",
  "properties": {
    "iso:country":"DE",
    "sg:address":"Im Gr\u00e4ble 7",
    "sg:city":"Neckartailfingen",
    "sg:phone":"+49 7127/927411",
    "sg:postcode":"72666",
    "sg:province":"Baden-W\u00fcrttemberg",
    "wof:name":"Dvn Druck- Und Verlagshaus Neckartailfingen Gmbh",
    "wof:placetype":"venue"
},
  "geometry": {"coordinates":[9.2595281601,48.6087684631],"type":"Point"}
}