{
  "type": "Feature",
  "properties": {
    "iso:country":"DE",
    "sg:address":"Lange Str. 2",
    "sg:city":"Elsterwerda",
    "sg:postcode":"04910",
    "sg:province":"Brandenburg",
    "wof:name":"Etv-medienservice Und Vertriebs- Gmbh",
    "wof:placetype":"venue"
},
  "geometry": {"coordinates":[13.522653,51.457684],"type":"Point"}
}