{
  "type": "Feature",
  "properties": {
    "iso:country":"DE",
    "sg:address":"Am Isarkanal 24",
    "sg:city":"M\u00fcnchen",
    "sg:phone":"+49 89/7234732",
    "sg:postcode":"81379",
    "sg:province":"Bayern",
    "wof:name":"Wida Wirtschafts- Und Daten- Dienst Gmbh",
    "wof:placetype":"venue"
},
  "geometry": {"coordinates":[11.5497941971,48.1034889221],"type":"Point"}
}