{
  "type": "Feature",
  "properties": {
    "iso:country":"DE",
    "sg:address":"K\u00f6lner Str. 105",
    "sg:city":"Bergisch Gladbach",
    "sg:phone":"+49 2204/94910",
    "sg:postcode":"51429",
    "sg:province":"Nordrhein-Westfalen",
    "wof:name":"Rainer Irrgang Steuerberater",
    "wof:placetype":"venue"
},
  "geometry": {"coordinates":[7.1445140839,50.9594306946],"type":"Point"}
}