{
  "type": "Feature",
  "properties": {
    "iso:country":"DE",
    "sg:address":"Feldstr.9",
    "sg:city":"Grossefehn",
    "sg:phone":"+49 4943/643",
    "sg:postcode":"26629",
    "sg:province":"Niedersachsen",
    "wof:name":"Juergen Bahr",
    "wof:placetype":"venue"
},
  "geometry": {"coordinates":[7.5530929565,53.3859977722],"type":"Point"}
}