{
  "type": "Feature",
  "properties": {
    "iso:country":"DE",
    "sg:address":"Am Ziegelweiher 1",
    "sg:city":"Erkelenz",
    "sg:phone":"+49 4924/315394",
    "sg:postcode":"41812",
    "sg:province":"Nordrhein-Westfalen",
    "wof:name":"Peter Roosen",
    "wof:placetype":"venue"
},
  "geometry": {"coordinates":[6.316564,51.08263],"type":"Point"}
}