{
  "type": "Feature",
  "properties": {
    "iso:country":"DE",
    "sg:address":"Am Kirchplatz 13",
    "sg:city":"Appenweier",
    "sg:phone":"+49 7805/3320",
    "sg:postcode":"77767",
    "sg:province":"Baden-W\u00fcrttemberg",
    "wof:name":"Kath. Pfarramt St. Michael",
    "wof:placetype":"venue"
},
  "geometry": {"coordinates":[7.9776201248,48.5394554138],"type":"Point"}
}