{
  "type": "Feature",
  "properties": {
    "iso:country":"DE",
    "sg:address":"N\u00fcrnberger Str.",
    "sg:city":"Gera",
    "sg:phone":"+49 365/32169",
    "sg:postcode":"07549",
    "sg:province":"Th\u00fcringen",
    "wof:name":"Shell Station Und Autowaschpark Kurt Bachmann",
    "wof:placetype":"venue"
},
  "geometry": {"coordinates":[12.0704107285,50.8486862183],"type":"Point"}
}