{
  "type": "Feature",
  "properties": {
    "iso:country":"DE",
    "sg:address":"An der S\u00e4ge 2",
    "sg:city":"Wiggensbach",
    "sg:phone":"+49 8370/1533",
    "sg:postcode":"87487",
    "sg:province":"Bayern",
    "wof:name":"Johannes Harlacher Tierarzt",
    "wof:placetype":"venue"
},
  "geometry": {"coordinates":[10.2311401367,47.7453308105],"type":"Point"}
}