{
  "type": "Feature",
  "properties": {
    "iso:country":"DE",
    "sg:address":"Strengerstr. 6",
    "sg:city":"G\u00fctersloh",
    "sg:phone":"+49 5241/27701",
    "sg:postcode":"33330",
    "sg:province":"Nordrhein-Westfalen",
    "wof:name":"Foto-ramhorst Frieda Ramhorst",
    "wof:placetype":"venue"
},
  "geometry": {"coordinates":[8.381146431,51.9079360962],"type":"Point"}
}