{
  "type": "Feature",
  "properties": {
    "iso:country":"DE",
    "sg:address":"Feldstr. 35",
    "sg:city":"Ro\u00dfla",
    "sg:phone":"+49 34651/2303",
    "sg:postcode":"06536",
    "sg:province":"Sachsen-Anhalt",
    "wof:name":"Raiffeisen Handelsgenossenschaft",
    "wof:placetype":"venue"
},
  "geometry": {"coordinates":[11.08125,51.465462],"type":"Point"}
}