{
  "type": "Feature",
  "properties": {
    "iso:country":"DE",
    "sg:address":"M\u00fchlenhofsweg 90",
    "sg:city":"Oldenburg",
    "sg:phone":"+49 441/34375",
    "sg:postcode":"26125",
    "sg:province":"Niedersachsen",
    "wof:name":"R. Mehrens",
    "wof:placetype":"venue"
},
  "geometry": {"coordinates":[8.236989975,53.1662445068],"type":"Point"}
}