{
  "type": "Feature",
  "properties": {
    "iso:country":"DE",
    "sg:address":"August-Bebel-Str. 73",
    "sg:city":"Bad Salzungen",
    "sg:phone":"+49 3695/872787",
    "sg:postcode":"36433",
    "sg:province":"Th\u00fcringen",
    "wof:name":"Restaurant Zur Linde",
    "wof:placetype":"venue"
},
  "geometry": {"coordinates":[10.2527799606,50.8120193481],"type":"Point"}
}