{
  "type": "Feature",
  "properties": {
    "iso:country":"DE",
    "sg:address":"Maybachstr. 22",
    "sg:city":"Dreieich",
    "sg:phone":"+49 6103/39970",
    "sg:postcode":"63303",
    "sg:province":"Hessen",
    "wof:name":"H Und H Heil Ausstattungs-gmbh",
    "wof:placetype":"venue"
},
  "geometry": {"coordinates":[8.7011499405,50.0281715393],"type":"Point"}
}