{
  "type": "Feature",
  "properties": {
    "iso:country":"DE",
    "sg:address":"F\u00fcnferplatz 2",
    "sg:city":"N\u00fcrnberg",
    "sg:phone":"+49 911/2312372",
    "sg:postcode":"90403",
    "sg:province":"Bayern",
    "wof:name":"Redaktion Betrifft Stadt Presse Und",
    "wof:placetype":"venue"
},
  "geometry": {"coordinates":[11.0781106949,49.4551963806],"type":"Point"}
}