{
  "type": "Feature",
  "properties": {
    "iso:country":"DE",
    "sg:address":"Friedrichstr. 24",
    "sg:city":"Grimmen",
    "sg:postcode":"18507",
    "sg:province":"Mecklenburg-Vorpommern",
    "wof:name":"Ev.-luth. Kirche",
    "wof:placetype":"venue"
},
  "geometry": {"coordinates":[13.0382499695,54.1104812622],"type":"Point"}
}