{
  "type": "Feature",
  "properties": {
    "iso:country":"DE",
    "sg:address":"Ravensberger Str. 39",
    "sg:city":"Duisburg",
    "sg:phone":"+49 203/782454",
    "sg:postcode":"47259",
    "sg:province":"Nordrhein-Westfalen",
    "wof:name":"Heribert Glesius Architekt",
    "wof:placetype":"venue"
},
  "geometry": {"coordinates":[6.73567,51.357288],"type":"Point"}
}