{
  "type": "Feature",
  "properties": {
    "iso:country":"DE",
    "sg:address":"Badegasse 3",
    "sg:city":"Hohenstein-Ernstthal",
    "sg:phone":"+49 3723/42170",
    "sg:postcode":"09337",
    "sg:province":"Sachsen",
    "wof:name":"Erich Anders",
    "wof:placetype":"venue"
},
  "geometry": {"coordinates":[12.715823,50.802273],"type":"Point"}
}