{
  "type": "Feature",
  "properties": {
    "iso:country":"DE",
    "sg:address":"Stichstr. 1",
    "sg:city":"Broderstorf",
    "sg:phone":"+49 38204/12259",
    "sg:postcode":"18184",
    "sg:province":"Mecklenburg-Vorpommern",
    "wof:name":"Siegfried Puls",
    "wof:placetype":"venue"
},
  "geometry": {"coordinates":[12.2054786682,54.0789260864],"type":"Point"}
}