{
  "type": "Feature",
  "properties": {
    "iso:country":"DE",
    "sg:address":"Kleines Feld 1",
    "sg:city":"Rahden",
    "sg:phone":"+49 5771/1568",
    "sg:postcode":"32369",
    "sg:province":"Nordrhein-Westfalen",
    "wof:name":"Werner Starke",
    "wof:placetype":"venue"
},
  "geometry": {"coordinates":[8.571381,52.433125],"type":"Point"}
}