{
  "type": "Feature",
  "properties": {
    "iso:country":"DE",
    "sg:address":"Salzhandelsstr. 2",
    "sg:city":"Leipzig",
    "sg:phone":"+49 341/5213276",
    "sg:postcode":"04158",
    "sg:province":"Sachsen",
    "wof:name":"Basilikum",
    "wof:placetype":"venue"
},
  "geometry": {"coordinates":[12.3686199188,51.4040565491],"type":"Point"}
}