{
  "type": "Feature",
  "properties": {
    "iso:country":"DE",
    "sg:address":"Maurenbrecherstr. 6",
    "sg:city":"Krefeld",
    "sg:phone":"+49 2151/778185",
    "sg:postcode":"47803",
    "sg:province":"Nordrhein-Westfalen",
    "wof:name":"M. Nieden",
    "wof:placetype":"venue"
},
  "geometry": {"coordinates":[6.548116,51.333515],"type":"Point"}
}