{
  "type": "Feature",
  "properties": {
    "iso:country":"DE",
    "sg:address":"Breithauptstr. 9",
    "sg:city":"Bickenbach",
    "sg:phone":"+49 6257/5257",
    "sg:postcode":"64404",
    "sg:province":"Hessen",
    "wof:name":"A. Schwerdt",
    "wof:placetype":"venue"
},
  "geometry": {"coordinates":[8.6023101807,49.7584381104],"type":"Point"}
}