{
  "type": "Feature",
  "properties": {
    "iso:country":"DE",
    "sg:address":"Seebadallee 59a",
    "sg:city":"Rangsdorf",
    "sg:phone":"+49 33708/22406",
    "sg:postcode":"15834",
    "sg:province":"Brandenburg",
    "wof:name":"Bauausf\u00fchrung Olaf Von Weschpfennig Gmbh",
    "wof:placetype":"venue"
},
  "geometry": {"coordinates":[13.419521,52.291451],"type":"Point"}
}