{
  "type": "Feature",
  "properties": {
    "iso:country":"DE",
    "sg:address":"Schanzweg 20",
    "sg:city":"Eschlkam",
    "sg:phone":"+49 9948/358",
    "sg:postcode":"93458",
    "sg:province":"Bayern",
    "wof:name":"E. Pongratz",
    "wof:placetype":"venue"
},
  "geometry": {"coordinates":[12.956377,49.308529],"type":"Point"}
}