{
  "type": "Feature",
  "properties": {
    "iso:country":"DE",
    "sg:address":"Glindesmoor 4",
    "sg:city":"Hohenfelde",
    "sg:phone":"+49 4127/291",
    "sg:postcode":"25358",
    "sg:province":"Schleswig-Holstein",
    "wof:name":"Hans Und Hans-hermann Gosau",
    "wof:placetype":"venue"
},
  "geometry": {"coordinates":[9.636563,53.843044],"type":"Point"}
}