{
  "type": "Feature",
  "properties": {
    "iso:country":"DE",
    "sg:address":"Dunninger Weg 1",
    "sg:city":"B\u00f6singen",
    "sg:phone":"+49 7404/1412",
    "sg:postcode":"78662",
    "sg:province":"Baden-W\u00fcrttemberg",
    "wof:name":"Josef Bihl",
    "wof:placetype":"venue"
},
  "geometry": {"coordinates":[8.572559,48.224091],"type":"Point"}
}