{
  "type": "Feature",
  "properties": {
    "iso:country":"DE",
    "sg:address":"Bismarckstr. 24",
    "sg:city":"Weiden",
    "sg:phone":"+49 961/32721",
    "sg:postcode":"92637",
    "sg:province":"Bayern",
    "wof:name":"H. G\u00f6\u00dfl",
    "wof:placetype":"venue"
},
  "geometry": {"coordinates":[12.1650419235,49.6805725098],"type":"Point"}
}