{
  "type": "Feature",
  "properties": {
    "iso:country":"DE",
    "sg:address":"Auer Gasse 17",
    "sg:city":"Schmalkalden",
    "sg:phone":"+49 3683/88107",
    "sg:postcode":"98574",
    "sg:province":"Th\u00fcringen",
    "wof:name":"E. M\u00f6schter",
    "wof:placetype":"venue"
},
  "geometry": {"coordinates":[10.449338913,50.7205848694],"type":"Point"}
}