{
  "type": "Feature",
  "properties": {
    "iso:country":"DE",
    "sg:address":"Hauptstr. 10",
    "sg:city":"Ebenheim",
    "sg:phone":"+49 36254/71404",
    "sg:postcode":"99869",
    "sg:province":"Th\u00fcringen",
    "wof:name":"Diethard Beese",
    "wof:placetype":"venue"
},
  "geometry": {"coordinates":[10.5124082565,50.9753913879],"type":"Point"}
}