{
  "type": "Feature",
  "properties": {
    "iso:country":"DE",
    "sg:address":"Schlachterstr. 16",
    "sg:city":"Lingen",
    "sg:phone":"+49 591/3663",
    "sg:postcode":"49808",
    "sg:province":"Niedersachsen",
    "wof:name":"Stadtgarten Vahrenhorst",
    "wof:placetype":"venue"
},
  "geometry": {"coordinates":[7.3162589073,52.5217399597],"type":"Point"}
}