{
  "type": "Feature",
  "properties": {
    "iso:country":"DE",
    "sg:address":"Bergstr. 15",
    "sg:city":"R\u00f6dinghausen",
    "sg:phone":"+49 5746/8256",
    "sg:postcode":"32289",
    "sg:province":"Nordrhein-Westfalen",
    "wof:name":"Berg-sch\u00e4nke",
    "wof:placetype":"venue"
},
  "geometry": {"coordinates":[8.5009431839,52.2586708069],"type":"Point"}
}