{
  "type": "Feature",
  "properties": {
    "iso:country":"DE",
    "sg:address":"Kirchberg 48",
    "sg:city":"Andernach",
    "sg:phone":"+49 2632/42074",
    "sg:postcode":"56626",
    "sg:province":"Rheinland-Pfalz",
    "wof:name":"Dr. Wolfram Haymann Und Partner",
    "wof:placetype":"venue"
},
  "geometry": {"coordinates":[7.3878540993,50.432849884],"type":"Point"}
}