{
  "type": "Feature",
  "properties": {
    "iso:country":"DE",
    "sg:address":"Am Haintor 1",
    "sg:city":"Bad Sooden-Allendorf",
    "sg:phone":"+49 5652/2161",
    "sg:postcode":"37242",
    "sg:province":"Hessen",
    "wof:name":"Oberbayern",
    "wof:placetype":"venue"
},
  "geometry": {"coordinates":[9.9617300034,51.2692718506],"type":"Point"}
}