{
  "type": "Feature",
  "properties": {
    "iso:country":"DE",
    "sg:address":"B\u00fchne 118",
    "sg:city":"Borgentreich",
    "sg:phone":"+49 5643/1611",
    "sg:postcode":"34434",
    "sg:province":"Nordrhein-Westfalen",
    "wof:name":"Engemann & Koch Ohg",
    "wof:placetype":"venue"
},
  "geometry": {"coordinates":[9.2447,51.571602],"type":"Point"}
}