{
  "type": "Feature",
  "properties": {
    "iso:country":"DE",
    "sg:address":"Hakeborner Weg 3a",
    "sg:city":"Egeln",
    "sg:postcode":"39435",
    "sg:province":"Sachsen-Anhalt",
    "wof:name":"B\u00f6rkies Gross B\u00f6rnecke Gmbh",
    "wof:placetype":"venue"
},
  "geometry": {"coordinates":[11.4182109833,51.9382705688],"type":"Point"}
}