{
  "type": "Feature",
  "properties": {
    "iso:country":"DE",
    "sg:address":"Westwall 1",
    "sg:city":"Schwerte",
    "sg:phone":"+49 2304/13066",
    "sg:postcode":"58239",
    "sg:province":"Nordrhein-Westfalen",
    "wof:name":"Hans-holger Herzig Rechtsanwalt Und Notar",
    "wof:placetype":"venue"
},
  "geometry": {"coordinates":[7.5658988953,51.4405937195],"type":"Point"}
}