{
  "type": "Feature",
  "properties": {
    "iso:country":"DE",
    "sg:address":"Ostring 28",
    "sg:city":"Roth",
    "sg:phone":"+49 9171/3288",
    "sg:postcode":"91154",
    "sg:province":"Bayern",
    "wof:name":"Vereinsgastst\u00e4tte Sportheim Sc Roth 52",
    "wof:placetype":"venue"
},
  "geometry": {"coordinates":[11.1053695679,49.2524795532],"type":"Point"}
}