{
  "type": "Feature",
  "properties": {
    "iso:country":"DE",
    "sg:address":"Walk\u00fcrenstr. 10",
    "sg:city":"Neubiberg",
    "sg:phone":"+49 89/6014444",
    "sg:postcode":"85579",
    "sg:province":"Bayern",
    "wof:name":"Erwin Schramm",
    "wof:placetype":"venue"
},
  "geometry": {"coordinates":[11.6775999069,48.0760002136],"type":"Point"}
}