{
  "type": "Feature",
  "properties": {
    "iso:country":"DE",
    "sg:address":"Sauerlandstr. 72",
    "sg:city":"Bielefeld",
    "sg:phone":"+49 521/445244",
    "sg:postcode":"33647",
    "sg:province":"Nordrhein-Westfalen",
    "wof:name":"M. Bienert",
    "wof:placetype":"venue"
},
  "geometry": {"coordinates":[8.5002183914,51.9851951599],"type":"Point"}
}