{
  "type": "Feature",
  "properties": {
    "iso:country":"DE",
    "sg:address":"Ostlandring 61",
    "sg:city":"Harrislee",
    "sg:phone":"+49 461/7610",
    "sg:postcode":"24955",
    "sg:province":"Schleswig-Holstein",
    "wof:name":"Alfred Messner Architekt",
    "wof:placetype":"venue"
},
  "geometry": {"coordinates":[9.398377,54.808567],"type":"Point"}
}