{
  "type": "Feature",
  "properties": {
    "iso:country":"DE",
    "sg:address":"Rudolf-Camerer-Str. 12",
    "sg:city":"M\u00fcnchen",
    "sg:phone":"+49 89/7855579",
    "sg:postcode":"81369",
    "sg:province":"Bayern",
    "wof:name":"Doina Pfennings Architekt",
    "wof:placetype":"venue"
},
  "geometry": {"coordinates":[11.527029,48.108311],"type":"Point"}
}