{
  "type": "Feature",
  "properties": {
    "iso:country":"DE",
    "sg:address":"Hanns-Martin-Schleyer-Str. 16",
    "sg:city":"Sindelfingen",
    "sg:phone":"+49 7031/811954",
    "sg:postcode":"71063",
    "sg:province":"Baden-W\u00fcrttemberg",
    "wof:name":"Indian Data Operation",
    "wof:placetype":"venue"
},
  "geometry": {"coordinates":[8.9972505569,48.7050094604],"type":"Point"}
}