{
  "type": "Feature",
  "properties": {
    "iso:country":"DE",
    "sg:address":"Wasgaustr. 6",
    "sg:city":"Karlsruhe",
    "sg:phone":"+49 721/491746",
    "sg:postcode":"76227",
    "sg:province":"Baden-W\u00fcrttemberg",
    "wof:name":"W. Und R. Riser",
    "wof:placetype":"venue"
},
  "geometry": {"coordinates":[8.4543304443,48.9890403748],"type":"Point"}
}