{
  "type": "Feature",
  "properties": {
    "iso:country":"DE",
    "sg:address":"Porschestr. 1",
    "sg:city":"Wolfsburg",
    "sg:phone":"+49 5361/20450",
    "sg:postcode":"38440",
    "sg:province":"Niedersachsen",
    "wof:name":"Nek Ingenieur Team Wolfsburg Gmbh",
    "wof:placetype":"venue"
},
  "geometry": {"coordinates":[10.7904977798,52.4275245667],"type":"Point"}
}