{
  "type": "Feature",
  "properties": {
    "iso:country":"DE",
    "sg:address":"Kaiser-Lothar-Str. 5",
    "sg:city":"Staffelstein",
    "sg:phone":"+49 9573/203",
    "sg:postcode":"96231",
    "sg:province":"Bayern",
    "wof:name":"W. Dumproff Verwaltungs Gmbh",
    "wof:placetype":"venue"
},
  "geometry": {"coordinates":[10.9902086258,50.101940155],"type":"Point"}
}