{
  "type": "Feature",
  "properties": {
    "iso:country":"DE",
    "sg:address":"Kleekamp 32",
    "sg:city":"Borgholzhausen",
    "sg:phone":"+49 5425/5049",
    "sg:postcode":"33829",
    "sg:province":"Nordrhein-Westfalen",
    "wof:name":"Otto Hardiek Gmbh & Co. Kg",
    "wof:placetype":"venue"
},
  "geometry": {"coordinates":[8.2409162521,52.0991592407],"type":"Point"}
}