{
  "type": "Feature",
  "properties": {
    "iso:country":"DE",
    "sg:address":"Weipertstr. 37",
    "sg:city":"Heilbronn",
    "sg:phone":"+49 7131/15690",
    "sg:postcode":"74076",
    "sg:province":"Baden-W\u00fcrttemberg",
    "wof:name":"Krupp Drauz Gmbh",
    "wof:placetype":"venue"
},
  "geometry": {"coordinates":[9.215335,49.150398],"type":"Point"}
}