{
  "type": "Feature",
  "properties": {
    "iso:country":"DE",
    "sg:address":"Deggendorfer Str. 18",
    "sg:city":"Pilsting",
    "sg:phone":"+49 9953/533",
    "sg:postcode":"94431",
    "sg:province":"Bayern",
    "wof:name":"Hubert Hobmaier",
    "wof:placetype":"venue"
},
  "geometry": {"coordinates":[12.651392,48.702419],"type":"Point"}
}