{
  "type": "Feature",
  "properties": {
    "iso:country":"DE",
    "sg:address":"Balkenstr. 8",
    "sg:city":"Dortmund",
    "sg:postcode":"44137",
    "sg:province":"Nordrhein-Westfalen",
    "wof:name":"Peter Schwenk Inh. Peter Schwenk E. K.",
    "wof:placetype":"venue"
},
  "geometry": {"coordinates":[7.466111,51.512325],"type":"Point"}
}