{
  "type": "Feature",
  "properties": {
    "iso:country":"DE",
    "sg:address":"Waldeckstr. 9",
    "sg:city":"T\u00fcbingen",
    "sg:phone":"+49 7071/24504",
    "sg:postcode":"72074",
    "sg:province":"Baden-W\u00fcrttemberg",
    "wof:name":"Rolf Dieterle Notar",
    "wof:placetype":"venue"
},
  "geometry": {"coordinates":[9.076292038,48.5325622559],"type":"Point"}
}