{
  "type": "Feature",
  "properties": {
    "iso:country":"DE",
    "sg:address":"Poststr. 48",
    "sg:city":"V\u00f6lklingen",
    "sg:phone":"+49 6898/22137",
    "sg:postcode":"66333",
    "sg:province":"Saarland",
    "wof:name":"Ev. Pfarramt Vers\u00f6hnungsgemeinde",
    "wof:placetype":"venue"
},
  "geometry": {"coordinates":[6.8542470932,49.2525253296],"type":"Point"}
}