{
  "type": "Feature",
  "properties": {
    "iso:country":"DE",
    "sg:address":"Engerstr. 4b",
    "sg:city":"Herford",
    "sg:postcode":"32051",
    "sg:province":"Nordrhein-Westfalen",
    "wof:name":"Export-marketinggesellschaft Der Holz- Und M\u00f6belindustrie",
    "wof:placetype":"venue"
},
  "geometry": {"coordinates":[8.660877,52.118359],"type":"Point"}
}