{
  "type": "Feature",
  "properties": {
    "iso:country":"DE",
    "sg:address":"Hessenstr. 25",
    "sg:city":"Hofheim",
    "sg:phone":"+49 6122/12869",
    "sg:postcode":"65719",
    "sg:province":"Hessen",
    "wof:name":"Wpl Bautr\u00e4ger Gmbh",
    "wof:placetype":"venue"
},
  "geometry": {"coordinates":[8.381745,50.07069],"type":"Point"}
}