{
  "type": "Feature",
  "properties": {
    "iso:country":"DE",
    "sg:address":"Bahnhofstr. 17",
    "sg:city":"Mihla",
    "sg:phone":"+49 36924/42005",
    "sg:postcode":"99826",
    "sg:province":"Th\u00fcringen",
    "wof:name":"Axel M\u00f6bius",
    "wof:placetype":"venue"
},
  "geometry": {"coordinates":[10.328181,51.077362],"type":"Point"}
}