{
  "type": "Feature",
  "properties": {
    "iso:country":"DE",
    "sg:address":"Baumgartnerweg 13",
    "sg:city":"Gauting",
    "sg:phone":"+49 89/8509337",
    "sg:postcode":"82131",
    "sg:province":"Bayern",
    "wof:name":"Schober Haus- Und Grundbe- Sitzbetreuungs- Gmbh",
    "wof:placetype":"venue"
},
  "geometry": {"coordinates":[11.4002733231,48.0566253662],"type":"Point"}
}