{
  "type": "Feature",
  "properties": {
    "iso:country":"DE",
    "sg:address":"Gr\u00fcner Weg 11",
    "sg:city":"Aachen",
    "sg:phone":"+49 241/911137",
    "sg:postcode":"52070",
    "sg:province":"Nordrhein-Westfalen",
    "wof:name":"Franz Siemons",
    "wof:placetype":"venue"
},
  "geometry": {"coordinates":[6.100893,50.786201],"type":"Point"}
}