{
  "type": "Feature",
  "properties": {
    "iso:country":"DE",
    "sg:address":"Poststr. 19-21",
    "sg:city":"V\u00f6lklingen",
    "sg:phone":"+49 6898/28444",
    "sg:postcode":"66333",
    "sg:province":"Saarland",
    "wof:name":"Sanit\u00e4tshaus Sander",
    "wof:placetype":"venue"
},
  "geometry": {"coordinates":[6.851993084,49.250995636],"type":"Point"}
}