{
  "type": "Feature",
  "properties": {
    "iso:country":"DE",
    "sg:address":"Lange Str. 41",
    "sg:city":"Rodenberg",
    "sg:phone":"+49 5723/5953",
    "sg:postcode":"31552",
    "sg:province":"Niedersachsen",
    "wof:name":"Klaus Lippmann",
    "wof:placetype":"venue"
},
  "geometry": {"coordinates":[9.355547905,52.3112716675],"type":"Point"}
}