{
  "type": "Feature",
  "properties": {
    "iso:country":"DE",
    "sg:address":"Rochusstr. 262",
    "sg:city":"Bonn",
    "sg:phone":"+49 228/623204",
    "sg:postcode":"53123",
    "sg:province":"Nordrhein-Westfalen",
    "wof:name":"Ute Vianden",
    "wof:placetype":"venue"
},
  "geometry": {"coordinates":[7.04569,50.713898],"type":"Point"}
}