{
  "type": "Feature",
  "properties": {
    "iso:country":"DE",
    "sg:address":"In der Sitters 1d",
    "sg:city":"Saarbr\u00fccken",
    "sg:phone":"+49 681/700044",
    "sg:postcode":"66128",
    "sg:province":"Saarland",
    "wof:name":"Div Druckweiterverarbeitung Und Industriebuchbinderei Vogl Gmbh",
    "wof:placetype":"venue"
},
  "geometry": {"coordinates":[6.915681839,49.2354316711],"type":"Point"}
}