{
  "type": "Feature",
  "properties": {
    "iso:country":"DE",
    "sg:address":"K\u00f6nigsallee 53-55",
    "sg:city":"D\u00fcsseldorf",
    "sg:phone":"+49 211/497730",
    "sg:postcode":"40212",
    "sg:province":"Nordrhein-Westfalen",
    "wof:name":"Generalkonsulat Der Franz\u00f6sischen Republik",
    "wof:placetype":"venue"
},
  "geometry": {"coordinates":[6.7782211304,51.2219963074],"type":"Point"}
}