{
  "type": "Feature",
  "properties": {
    "iso:country":"DE",
    "sg:address":"St.-Ulrich-Str. 14",
    "sg:city":"Eresing",
    "sg:postcode":"86922",
    "sg:province":"Bayern",
    "wof:name":"Edlich & Wagner Ohg Revolution Movie Film- Und",
    "wof:placetype":"venue"
},
  "geometry": {"coordinates":[11.0229520798,48.082950592],"type":"Point"}
}