{
  "type": "Feature",
  "properties": {
    "iso:country":"DE",
    "sg:address":"Hagener Str. 378",
    "sg:city":"Dortmund",
    "sg:phone":"+49 231",
    "sg:postcode":"44135",
    "sg:province":"Nordrhein-Westfalen",
    "wof:name":"Einrichtung",
    "wof:placetype":"venue"
},
  "geometry": {"coordinates":[7.458295,51.516617],"type":"Point"}
}