{
  "type": "Feature",
  "properties": {
    "iso:country":"DE",
    "sg:address":"Ehrenstr. 69",
    "sg:city":"K\u00f6ln",
    "sg:phone":"+49 221/2030830",
    "sg:postcode":"50672",
    "sg:province":"Nordrhein-Westfalen",
    "wof:name":"Kai Koschorreck Rechtsanwalt",
    "wof:placetype":"venue"
},
  "geometry": {"coordinates":[6.9409828186,50.9381752014],"type":"Point"}
}