{
  "type": "Feature",
  "properties": {
    "iso:country":"DE",
    "sg:address":"Stadelmannstr. 45",
    "sg:city":"Aschaffenburg",
    "sg:phone":"+49 6021/30770",
    "sg:postcode":"63739",
    "sg:province":"Bayern",
    "wof:name":"Candela Pr\u00e4sente Gmbh",
    "wof:placetype":"venue"
},
  "geometry": {"coordinates":[9.153634,49.970726],"type":"Point"}
}