{
  "type": "Feature",
  "properties": {
    "iso:country":"DE",
    "sg:address":"Enggleis 18",
    "sg:city":"Erlangen",
    "sg:phone":"+49 9131/603518",
    "sg:postcode":"91058",
    "sg:province":"Bayern",
    "wof:name":"Marja Schallner",
    "wof:placetype":"venue"
},
  "geometry": {"coordinates":[11.0278234482,49.5547866821],"type":"Point"}
}