{
  "type": "Feature",
  "properties": {
    "iso:country":"DE",
    "sg:address":"Maxburgstr. 5",
    "sg:city":"Landau",
    "sg:phone":"+49 6341/33564",
    "sg:postcode":"76829",
    "sg:province":"Rheinland-Pfalz",
    "wof:name":"Otto-karl Salg",
    "wof:placetype":"venue"
},
  "geometry": {"coordinates":[8.1015472412,49.1917915344],"type":"Point"}
}