{
  "type": "Feature",
  "properties": {
    "iso:country":"DE",
    "sg:address":"Freiligrathstr. 1",
    "sg:city":"D\u00fcsseldorf",
    "sg:phone":"+49 211/4480",
    "sg:postcode":"40479",
    "sg:province":"Nordrhein-Westfalen",
    "wof:name":"Bellsouth Mobilfunk Gmbh",
    "wof:placetype":"venue"
},
  "geometry": {"coordinates":[6.778253,51.233074],"type":"Point"}
}