{
  "type": "Feature",
  "properties": {
    "iso:country":"DE",
    "sg:address":"Centrumstr. 31",
    "sg:city":"Essen",
    "sg:phone":"+49 201/855190",
    "sg:postcode":"45307",
    "sg:province":"Nordrhein-Westfalen",
    "wof:name":"Martin & Wolff Gmbh",
    "wof:placetype":"venue"
},
  "geometry": {"coordinates":[7.1058111191,51.4655418396],"type":"Point"}
}