{
  "type": "Feature",
  "properties": {
    "iso:country":"DE",
    "sg:address":"Spandauer Str. 203",
    "sg:city":"Falkensee",
    "sg:phone":"+49 3322/209497",
    "sg:postcode":"14612",
    "sg:province":"Brandenburg",
    "wof:name":"Pension H\u00e4rtel",
    "wof:placetype":"venue"
},
  "geometry": {"coordinates":[13.1425876617,52.5557403564],"type":"Point"}
}