{
  "type": "Feature",
  "properties": {
    "iso:country":"DE",
    "sg:address":"Industriestr. 19",
    "sg:city":"Enger",
    "sg:phone":"+49 5223/10765",
    "sg:postcode":"32130",
    "sg:province":"Nordrhein-Westfalen",
    "wof:name":"Werk-chemie Gmbh",
    "wof:placetype":"venue"
},
  "geometry": {"coordinates":[8.590266,52.170216],"type":"Point"}
}