{
  "type": "Feature",
  "properties": {
    "iso:country":"DE",
    "sg:address":"Wespenstieg 13",
    "sg:city":"Hamburg",
    "sg:phone":"+49 40/814597",
    "sg:postcode":"22559",
    "sg:province":"Hamburg",
    "wof:name":"G\u00fcnther M\u00fcller",
    "wof:placetype":"venue"
},
  "geometry": {"coordinates":[9.743973,53.596409],"type":"Point"}
}