{
  "type": "Feature",
  "properties": {
    "iso:country":"DE",
    "sg:address":"Trunstadter Str. 5",
    "sg:city":"Viereth-Trunstadt",
    "sg:phone":"+49 9503/5222",
    "sg:postcode":"96191",
    "sg:province":"Bayern",
    "wof:name":"S. Wei\u00dfner",
    "wof:placetype":"venue"
},
  "geometry": {"coordinates":[10.769785,49.923935],"type":"Point"}
}