{
  "type": "Feature",
  "properties": {
    "iso:country":"DE",
    "sg:address":"Hauptstr. 28",
    "sg:city":"Neuenkirchen",
    "sg:phone":"+49 5973/2176",
    "sg:postcode":"48485",
    "sg:province":"Nordrhein-Westfalen",
    "wof:name":"Tiziano Fontana Kg",
    "wof:placetype":"venue"
},
  "geometry": {"coordinates":[7.371785,52.244171],"type":"Point"}
}