{
  "type": "Feature",
  "properties": {
    "iso:country":"DE",
    "sg:address":"Exerzierplatz 31",
    "sg:city":"Kiel",
    "sg:phone":"+49 431/93868",
    "sg:postcode":"24103",
    "sg:province":"Schleswig-Holstein",
    "wof:name":"Andreas Stelting Gegr\u00fcndet 1853",
    "wof:placetype":"venue"
},
  "geometry": {"coordinates":[10.1286315918,54.3218154907],"type":"Point"}
}