{
  "type": "Feature",
  "properties": {
    "iso:country":"DE",
    "sg:address":"M\u00fchlweg 41",
    "sg:city":"Halle",
    "sg:phone":"+49 345/2021565",
    "sg:postcode":"06114",
    "sg:province":"Sachsen-Anhalt",
    "wof:name":"Isp Verwaltungsges. Mbh",
    "wof:placetype":"venue"
},
  "geometry": {"coordinates":[11.9634599686,51.4935035706],"type":"Point"}
}