{
  "type": "Feature",
  "properties": {
    "iso:country":"DE",
    "sg:address":"Siebengebirgsallee 24",
    "sg:city":"K\u00f6ln",
    "sg:phone":"+49 221",
    "sg:postcode":"50939",
    "sg:province":"Nordrhein-Westfalen",
    "wof:name":"Photo Design Andreas Fein",
    "wof:placetype":"venue"
},
  "geometry": {"coordinates":[6.92747,50.91394],"type":"Point"}
}