{
  "type": "Feature",
  "properties": {
    "iso:country":"DE",
    "sg:address":"Limburger Str. 19",
    "sg:city":"Aarbergen",
    "sg:phone":"+49 6430/6544",
    "sg:postcode":"65326",
    "sg:province":"Hessen",
    "wof:name":"Angelika Vogt",
    "wof:placetype":"venue"
},
  "geometry": {"coordinates":[8.0524740219,50.2642250061],"type":"Point"}
}