{
  "type": "Feature",
  "properties": {
    "iso:country":"DE",
    "sg:address":"Schwanthalerstr. 124",
    "sg:city":"M\u00fcnchen",
    "sg:phone":"+49 89/501605",
    "sg:postcode":"80339",
    "sg:province":"Bayern",
    "wof:name":"Its Vermittlung Internationale Kfz.-verschiffungen Gmbh",
    "wof:placetype":"venue"
},
  "geometry": {"coordinates":[11.5467538834,48.1379623413],"type":"Point"}
}