{
  "type": "Feature",
  "properties": {
    "iso:country":"DE",
    "sg:address":"Heilbronner Str. 35",
    "sg:city":"G\u00fcglingen",
    "sg:phone":"+49 7135/5337",
    "sg:postcode":"74363",
    "sg:province":"Baden-W\u00fcrttemberg",
    "wof:name":"Wolfgang Schmid",
    "wof:placetype":"venue"
},
  "geometry": {"coordinates":[9.0051641464,49.0659446716],"type":"Point"}
}