{
  "type": "Feature",
  "properties": {
    "iso:country":"DE",
    "sg:address":"Paul-Baehr-Str. 6",
    "sg:city":"Bad Oeynhausen",
    "sg:phone":"+49 5731/20067",
    "sg:postcode":"32545",
    "sg:province":"Nordrhein-Westfalen",
    "wof:name":"Modehaus Ilse Lang Gmbh",
    "wof:placetype":"venue"
},
  "geometry": {"coordinates":[8.7967281342,52.2036170959],"type":"Point"}
}