{
  "type": "Feature",
  "properties": {
    "iso:country":"DE",
    "sg:address":"Niederzw\u00f6nitzer Str. 12",
    "sg:city":"Zw\u00f6nitz",
    "sg:phone":"+49 37754/2538",
    "sg:postcode":"08297",
    "sg:province":"Sachsen",
    "wof:name":"U. Mothes",
    "wof:placetype":"venue"
},
  "geometry": {"coordinates":[12.810502,50.63179],"type":"Point"}
}