{
  "type": "Feature",
  "properties": {
    "iso:country":"DE",
    "sg:address":"Haffstr. 11",
    "sg:city":"M\u00f6nkebude",
    "sg:phone":"+49 39774/20344",
    "sg:postcode":"17375",
    "sg:province":"Mecklenburg-Vorpommern",
    "wof:name":"M\u00f6nke`s Bude I",
    "wof:placetype":"venue"
},
  "geometry": {"coordinates":[13.973241,53.767944],"type":"Point"}
}