{
  "type": "Feature",
  "properties": {
    "iso:country":"DE",
    "sg:address":"Am Thing 2",
    "sg:city":"Buchholz",
    "sg:phone":"+49 4181/7866",
    "sg:postcode":"21244",
    "sg:province":"Niedersachsen",
    "wof:name":"A. W. Matthies Baugesch\u00e4ft Gmbh",
    "wof:placetype":"venue"
},
  "geometry": {"coordinates":[9.8813533783,53.3211097717],"type":"Point"}
}