{
  "type": "Feature",
  "properties": {
    "iso:country":"DE",
    "sg:address":"Industriepark 1",
    "sg:city":"K\u00fcrnach",
    "sg:phone":"+49 9367/98400",
    "sg:postcode":"97273",
    "sg:province":"Bayern",
    "wof:name":"Viktor Nu\u00dfbaumer Gmbh & Co Kg",
    "wof:placetype":"venue"
},
  "geometry": {"coordinates":[10.028545,49.849758],"type":"Point"}
}