{
  "type": "Feature",
  "properties": {
    "iso:country":"DE",
    "sg:address":"N\u00fcrnberger Str. 2",
    "sg:city":"Ro\u00dftal",
    "sg:phone":"+49 9127/8031",
    "sg:postcode":"90574",
    "sg:province":"Bayern",
    "wof:name":"Horst Mayer E. K.",
    "wof:placetype":"venue"
},
  "geometry": {"coordinates":[10.8862009048,49.3986053467],"type":"Point"}
}