{
  "type": "Feature",
  "properties": {
    "iso:country":"DE",
    "sg:address":"Br\u00fchlstr. 3",
    "sg:city":"Badenweiler",
    "sg:phone":"+49 40/5365287",
    "sg:postcode":"79410",
    "sg:province":"Baden-W\u00fcrttemberg",
    "wof:name":"K. M\u00fcller",
    "wof:placetype":"venue"
},
  "geometry": {"coordinates":[7.680298,47.804817],"type":"Point"}
}