{
  "type": "Feature",
  "properties": {
    "iso:country":"DE",
    "sg:address":"Bahnhofstr. 12",
    "sg:city":"Gersfeld",
    "sg:phone":"+49 6654/215",
    "sg:postcode":"36129",
    "sg:province":"Hessen",
    "wof:name":"Fahrradkneipe Am Bahnhof",
    "wof:placetype":"venue"
},
  "geometry": {"coordinates":[9.9133262634,50.4494438171],"type":"Point"}
}