{
  "type": "Feature",
  "properties": {
    "iso:country":"DE",
    "sg:address":"Beim Herbstenhof 21",
    "sg:city":"T\u00fcbingen",
    "sg:phone":"+49 7071/61393",
    "sg:postcode":"72076",
    "sg:province":"Baden-W\u00fcrttemberg",
    "wof:name":"Ev. Pfarramt Wanne",
    "wof:placetype":"venue"
},
  "geometry": {"coordinates":[9.0451908112,48.5406684875],"type":"Point"}
}