{
  "type": "Feature",
  "properties": {
    "iso:country":"DE",
    "sg:address":"Am Neuen Palais 10",
    "sg:city":"Potsdam",
    "sg:phone":"+49 4933/19770",
    "sg:postcode":"14469",
    "sg:province":"Brandenburg",
    "wof:name":"Universit\u00c4t Potsdam",
    "wof:placetype":"venue"
},
  "geometry": {"coordinates":[13.013672,52.398911],"type":"Point"}
}