{
  "type": "Feature",
  "properties": {
    "iso:country":"DE",
    "sg:address":"Bietigheimer Str. 62",
    "sg:city":"Tamm",
    "sg:postcode":"71732",
    "sg:province":"Baden-W\u00fcrttemberg",
    "wof:name":"Stoneland E. K.",
    "wof:placetype":"venue"
},
  "geometry": {"coordinates":[9.12071,48.930267],"type":"Point"}
}