{
  "type": "Feature",
  "properties": {
    "iso:country":"DE",
    "sg:address":"Ringstr. 3",
    "sg:city":"Bad Sobernheim",
    "sg:phone":"+49 6751/3033",
    "sg:postcode":"55566",
    "sg:province":"Rheinland-Pfalz",
    "wof:name":"Warenhandelsgesellschaft F\u00fcr Warenhaus-verwaltung",
    "wof:placetype":"venue"
},
  "geometry": {"coordinates":[7.6550841331,49.7849197388],"type":"Point"}
}