{
  "type": "Feature",
  "properties": {
    "iso:country":"DE",
    "sg:address":"Rundeel 17",
    "sg:city":"Neustadt",
    "sg:postcode":"31535",
    "sg:province":"Niedersachsen",
    "wof:name":"Hanebutt Gmbh",
    "wof:placetype":"venue"
},
  "geometry": {"coordinates":[9.458225,52.506462],"type":"Point"}
}