{
  "type": "Feature",
  "properties": {
    "iso:country":"DE",
    "sg:address":"Christianstr. 13",
    "sg:city":"K\u00f6ln",
    "sg:phone":"+49 221/543400",
    "sg:postcode":"50825",
    "sg:province":"Nordrhein-Westfalen",
    "wof:name":"Br\u00fcgelmann Gmbh",
    "wof:placetype":"venue"
},
  "geometry": {"coordinates":[6.910700798,50.9532966614],"type":"Point"}
}