{
  "type": "Feature",
  "properties": {
    "iso:country":"DE",
    "sg:address":"Hattorfer Str. 23",
    "sg:city":"Wolfsburg",
    "sg:phone":"+49 5361/72707",
    "sg:postcode":"38442",
    "sg:province":"Niedersachsen",
    "wof:name":"H. Meyer",
    "wof:placetype":"venue"
},
  "geometry": {"coordinates":[10.7332620621,52.3929138184],"type":"Point"}
}