{
  "type": "Feature",
  "properties": {
    "iso:country":"DE",
    "sg:address":"Hauptstr. 118",
    "sg:city":"Achern",
    "sg:phone":"+49 7841/3221",
    "sg:postcode":"77855",
    "sg:province":"Baden-W\u00fcrttemberg",
    "wof:name":"Christel Riehle",
    "wof:placetype":"venue"
},
  "geometry": {"coordinates":[8.0781612396,48.6292152405],"type":"Point"}
}