{
  "type": "Feature",
  "properties": {
    "iso:country":"DE",
    "sg:address":"Neuenberger Str. 1",
    "sg:city":"Neuss",
    "sg:phone":"+49 2137/60220",
    "sg:postcode":"41470",
    "sg:province":"Nordrhein-Westfalen",
    "wof:name":"Winfried Kessel",
    "wof:placetype":"venue"
},
  "geometry": {"coordinates":[6.7322292328,51.1264190674],"type":"Point"}
}