{
  "type": "Feature",
  "properties": {
    "iso:country":"DE",
    "sg:address":"Schlo\u00dfstr. 3",
    "sg:city":"Kalefeld",
    "sg:phone":"+49 5553/99090",
    "sg:postcode":"37589",
    "sg:province":"Niedersachsen",
    "wof:name":"Hofos Holzforstservice Gmbh",
    "wof:placetype":"venue"
},
  "geometry": {"coordinates":[10.0879,51.790794],"type":"Point"}
}