{
  "type": "Feature",
  "properties": {
    "iso:country":"DE",
    "sg:address":"Oskar-Von-Miller-Str. 9",
    "sg:city":"Germering",
    "sg:phone":"+49 89/840070",
    "sg:postcode":"82110",
    "sg:province":"Bayern",
    "wof:name":"Cewe-color Ag & Co.",
    "wof:placetype":"venue"
},
  "geometry": {"coordinates":[11.374963,48.131966],"type":"Point"}
}