{
  "type": "Feature",
  "properties": {
    "iso:country":"DE",
    "sg:address":"Erlenbachhof 1",
    "sg:city":"Dielheim",
    "sg:phone":"+49 6222/73925",
    "sg:postcode":"69234",
    "sg:province":"Baden-W\u00fcrttemberg",
    "wof:name":"F. Freudensprung",
    "wof:placetype":"venue"
},
  "geometry": {"coordinates":[8.7605457306,49.287689209],"type":"Point"}
}