{
  "type": "Feature",
  "properties": {
    "iso:country":"DE",
    "sg:address":"Brockhorstweg 4",
    "sg:city":"Heiligenhaus",
    "sg:phone":"+49 2054/18947",
    "sg:postcode":"42579",
    "sg:province":"Nordrhein-Westfalen",
    "wof:name":"Horst Oberwinster",
    "wof:placetype":"venue"
},
  "geometry": {"coordinates":[6.931974,51.341938],"type":"Point"}
}