{
  "type": "Feature",
  "properties": {
    "iso:country":"DE",
    "sg:address":"Friedrich-Ebert-Str. 7",
    "sg:city":"Bad K\u00f6sen",
    "sg:phone":"+49 34463/28859",
    "sg:postcode":"06628",
    "sg:province":"Sachsen-Anhalt",
    "wof:name":"G\u00e4stehaus Krischker",
    "wof:placetype":"venue"
},
  "geometry": {"coordinates":[11.7168073654,51.1355514526],"type":"Point"}
}