{
  "type": "Feature",
  "properties": {
    "iso:country":"DE",
    "sg:address":"Wallbergstr. 5 Potzham",
    "sg:city":"Taufkirchen",
    "sg:phone":"+49 89/6141560",
    "sg:postcode":"82024",
    "sg:province":"Bayern",
    "wof:name":"Andromeda Medizinische Systeme Gmbh",
    "wof:placetype":"venue"
},
  "geometry": {"coordinates":[11.6156396866,48.046207428],"type":"Point"}
}