{
  "type": "Feature",
  "properties": {
    "iso:country":"DE",
    "sg:address":"Wormser Str. 19",
    "sg:city":"Stuttgart",
    "sg:postcode":"70499",
    "sg:province":"Baden-W\u00fcrttemberg",
    "wof:name":"Aquarien- Und Terrarienverein Stuttgarter Zierfisch-",
    "wof:placetype":"venue"
},
  "geometry": {"coordinates":[9.1197376251,48.812702179],"type":"Point"}
}