{
  "type": "Feature",
  "properties": {
    "iso:country":"DE",
    "sg:address":"Noltzstr. 2 a",
    "sg:city":"Worms",
    "sg:postcode":"67549",
    "sg:province":"Rheinland-Pfalz",
    "wof:name":"Verkehrsclub Deutschland",
    "wof:placetype":"venue"
},
  "geometry": {"coordinates":[8.3543281555,49.6317214966],"type":"Point"}
}