{
  "type": "Feature",
  "properties": {
    "iso:country":"DE",
    "sg:address":"Wolfsgasse 7",
    "sg:city":"Trier",
    "sg:phone":"+49 651/86601",
    "sg:postcode":"54294",
    "sg:province":"Rheinland-Pfalz",
    "wof:name":"Wilhelm Kleis Abdichtungs Gmbh",
    "wof:placetype":"venue"
},
  "geometry": {"coordinates":[6.624816,49.759254],"type":"Point"}
}