{
  "type": "Feature",
  "properties": {
    "iso:country":"DE",
    "sg:address":"Neumarkter Str. 3",
    "sg:city":"Altdorf",
    "sg:phone":"+49 9187/7272",
    "sg:postcode":"90518",
    "sg:province":"Bayern",
    "wof:name":"E. Und B. Heinlein",
    "wof:placetype":"venue"
},
  "geometry": {"coordinates":[11.359082,49.38586],"type":"Point"}
}