{
  "type": "Feature",
  "properties": {
    "iso:country":"DE",
    "sg:address":"Bischof-Sproll-Str. 9",
    "sg:city":"Leutkirch",
    "sg:phone":"+49 7561/4231",
    "sg:postcode":"88299",
    "sg:province":"Baden-W\u00fcrttemberg",
    "wof:name":"Psych. Beratungsstelle F. Eltern Kinder Jugendliche",
    "wof:placetype":"venue"
},
  "geometry": {"coordinates":[10.023287,47.819767],"type":"Point"}
}