{
  "type": "Feature",
  "properties": {
    "iso:country":"DE",
    "sg:address":"Dorstener Str. 425",
    "sg:city":"Bochum",
    "sg:phone":"+49 234/9041050",
    "sg:postcode":"44809",
    "sg:province":"Nordrhein-Westfalen",
    "wof:name":"Jeans Fritz",
    "wof:placetype":"venue"
},
  "geometry": {"coordinates":[7.189598,51.507946],"type":"Point"}
}