{
  "type": "Feature",
  "properties": {
    "iso:country":"DE",
    "sg:address":"Hauptstr. 41",
    "sg:city":"Mettenheim",
    "sg:phone":"+49 6242/3761",
    "sg:postcode":"67582",
    "sg:province":"Rheinland-Pfalz",
    "wof:name":"Johann Muth Weinkellerei",
    "wof:placetype":"venue"
},
  "geometry": {"coordinates":[8.3227138519,49.7380180359],"type":"Point"}
}