{
  "type": "Feature",
  "properties": {
    "iso:country":"DE",
    "sg:address":"Kirchhofsallee 36",
    "sg:city":"Zeven",
    "sg:phone":"+49 4281/3408",
    "sg:postcode":"27404",
    "sg:province":"Niedersachsen",
    "wof:name":"M. Trutenau Hebamme",
    "wof:placetype":"venue"
},
  "geometry": {"coordinates":[9.273767,53.289783],"type":"Point"}
}