{
  "type": "Feature",
  "properties": {
    "iso:country":"DE",
    "sg:address":"Oberheckerweg 57b",
    "sg:city":"Lahnstein",
    "sg:phone":"+49 2621/180519",
    "sg:postcode":"56112",
    "sg:province":"Rheinland-Pfalz",
    "wof:name":"Hermann H\u00fcbner Finanzberater",
    "wof:placetype":"venue"
},
  "geometry": {"coordinates":[7.6215128899,50.2927627563],"type":"Point"}
}