{
  "type": "Feature",
  "properties": {
    "iso:country":"DE",
    "sg:address":"Bl\u00fccherstr. 8a",
    "sg:city":"Suhl",
    "sg:phone":"+49 3681/300247",
    "sg:postcode":"98527",
    "sg:province":"Th\u00fcringen",
    "wof:name":"Neupert & Partner",
    "wof:placetype":"venue"
},
  "geometry": {"coordinates":[10.6865196228,50.6050949097],"type":"Point"}
}