{
  "type": "Feature",
  "properties": {
    "iso:country":"DE",
    "sg:address":"Lauweg 18",
    "sg:city":"Hamburg",
    "sg:phone":"+49 40/73727543",
    "sg:postcode":"21037",
    "sg:province":"Hamburg",
    "wof:name":"Homepage Der Kirchengemeinde Kirchwerder",
    "wof:placetype":"venue"
},
  "geometry": {"coordinates":[10.1306,53.446026],"type":"Point"}
}