{
  "type": "Feature",
  "properties": {
    "iso:country":"DE",
    "sg:address":"Heidemannstr. 41 a",
    "sg:city":"M\u00fcnchen",
    "sg:phone":"+49 89/3181930",
    "sg:postcode":"80939",
    "sg:province":"Bayern",
    "wof:name":"L\u00f6wen-automaten Gerhard W. Schulze Gmbh",
    "wof:placetype":"venue"
},
  "geometry": {"coordinates":[11.591273,48.20163],"type":"Point"}
}