{
  "type": "Feature",
  "properties": {
    "iso:country":"DE",
    "sg:address":"Franz-K\u00fcnstler-Str. 9",
    "sg:city":"Berlin",
    "sg:phone":"+49 30/6156696",
    "sg:postcode":"10969",
    "sg:province":"Berlin",
    "wof:name":"Paul Gesell",
    "wof:placetype":"venue"
},
  "geometry": {"coordinates":[13.4005212784,52.5015640259],"type":"Point"}
}