{
  "type": "Feature",
  "properties": {
    "iso:country":"DE",
    "sg:address":"Arendsee 6",
    "sg:city":"Wandlitz",
    "sg:phone":"+49 33397/22314",
    "sg:postcode":"16348",
    "sg:province":"Brandenburg",
    "wof:name":"Weinhandel Sylvia Krohn",
    "wof:placetype":"venue"
},
  "geometry": {"coordinates":[13.4884490967,52.7568893433],"type":"Point"}
}