{
  "type": "Feature",
  "properties": {
    "iso:country":"DE",
    "sg:address":"Steinstr. 13a",
    "sg:city":"Gnevsdorf",
    "sg:phone":"+49 38737/20211",
    "sg:postcode":"19395",
    "sg:province":"Mecklenburg-Vorpommern",
    "wof:name":"Gnevsdorfer Agrargenossenschaft",
    "wof:placetype":"venue"
},
  "geometry": {"coordinates":[12.21732,53.403561],"type":"Point"}
}