{
  "type": "Feature",
  "properties": {
    "iso:country":"DE",
    "sg:address":"Kaiserstr. 2",
    "sg:city":"T\u00f6nisvorst",
    "sg:phone":"+49 2151/795904",
    "sg:postcode":"47918",
    "sg:province":"Nordrhein-Westfalen",
    "wof:name":"Monika Wolf",
    "wof:placetype":"venue"
},
  "geometry": {"coordinates":[6.4915728569,51.3208312988],"type":"Point"}
}