{
  "type": "Feature",
  "properties": {
    "iso:country":"DE",
    "sg:address":"Im Coesfeld 3",
    "sg:city":"Rheine",
    "sg:phone":"+49 5971/915119",
    "sg:postcode":"48431",
    "sg:province":"Nordrhein-Westfalen",
    "wof:name":"Restaurant China Town",
    "wof:placetype":"venue"
},
  "geometry": {"coordinates":[7.4412918091,52.2784996033],"type":"Point"}
}