{
  "type": "Feature",
  "properties": {
    "iso:country":"DE",
    "sg:address":"Battertstr. 16",
    "sg:city":"Karlsruhe",
    "sg:phone":"+49 721/574300",
    "sg:postcode":"76189",
    "sg:province":"Baden-W\u00fcrttemberg",
    "wof:name":"Walter Woll Architekt",
    "wof:placetype":"venue"
},
  "geometry": {"coordinates":[8.35515,48.994041],"type":"Point"}
}