{
  "type": "Feature",
  "properties": {
    "iso:country":"DE",
    "sg:address":"Haidlfing",
    "sg:city":"Wallersdorf",
    "sg:phone":"+49 9933/1351",
    "sg:postcode":"94522",
    "sg:province":"Bayern",
    "wof:name":"R. Hubbauer",
    "wof:placetype":"venue"
},
  "geometry": {"coordinates":[12.7377700806,48.737613678],"type":"Point"}
}