{
  "type": "Feature",
  "properties": {
    "iso:country":"DE",
    "sg:address":"S\u00e4gegasse 8",
    "sg:city":"Wellendingen",
    "sg:phone":"+49 7426/7000",
    "sg:postcode":"78669",
    "sg:province":"Baden-W\u00fcrttemberg",
    "wof:name":"Zimmerei-treppenbau Dietmar Baier Gmbh",
    "wof:placetype":"venue"
},
  "geometry": {"coordinates":[8.7033596039,48.145866394],"type":"Point"}
}