{
  "type": "Feature",
  "properties": {
    "iso:country":"DE",
    "sg:address":"H\u00fchndorfer Str. 19",
    "sg:city":"Wilsdruff",
    "sg:phone":"+49 35204/60706",
    "sg:postcode":"01723",
    "sg:province":"Sachsen",
    "wof:name":"Ernst Walther",
    "wof:placetype":"venue"
},
  "geometry": {"coordinates":[13.550819397,51.0604133606],"type":"Point"}
}