{
  "type": "Feature",
  "properties": {
    "iso:country":"DE",
    "sg:address":"Hauptstr. 128",
    "sg:city":"Esslingen",
    "sg:phone":"+49 711/366702",
    "sg:postcode":"73730",
    "sg:province":"Baden-W\u00fcrttemberg",
    "wof:name":"R. Andreoli",
    "wof:placetype":"venue"
},
  "geometry": {"coordinates":[9.3629617691,48.7245025635],"type":"Point"}
}