{
  "type": "Feature",
  "properties": {
    "iso:country":"DE",
    "sg:address":"Claudiusweg 15B",
    "sg:city":"Darmstadt",
    "sg:phone":"+49 6151/46717",
    "sg:postcode":"64285",
    "sg:province":"Hessen",
    "wof:name":"Dr. Wolfgang Neff",
    "wof:placetype":"venue"
},
  "geometry": {"coordinates":[8.6665496826,49.856716156],"type":"Point"}
}