{
  "type": "Feature",
  "properties": {
    "iso:country":"DE",
    "sg:address":"Egge Wiede 9",
    "sg:city":"Dortmund",
    "sg:phone":"+49 231/353070",
    "sg:postcode":"44359",
    "sg:province":"Nordrhein-Westfalen",
    "wof:name":"Norbert R\u00f6tte Gmbh",
    "wof:placetype":"venue"
},
  "geometry": {"coordinates":[7.3884010315,51.5556373596],"type":"Point"}
}