{
  "type": "Feature",
  "properties": {
    "iso:country":"DE",
    "sg:address":"Flughafen Hannover",
    "sg:city":"Hannover",
    "sg:postcode":"30669",
    "sg:province":"Niedersachsen",
    "wof:name":"Dr\u00e4ger & Koch Transport Gmbh",
    "wof:placetype":"venue"
},
  "geometry": {"coordinates":[9.6968297958,52.4600410461],"type":"Point"}
}