{
  "type": "Feature",
  "properties": {
    "iso:country":"DE",
    "sg:address":"Rosenstr 106",
    "sg:city":"Hagen",
    "sg:phone":"+49 2331/55999",
    "sg:postcode":"58095",
    "sg:province":"Nordrhein-Westfalen",
    "wof:name":"Eeg Elektronik & Energieanlagen Gmbh",
    "wof:placetype":"venue"
},
  "geometry": {"coordinates":[7.499112,51.364227],"type":"Point"}
}