{
  "type": "Feature",
  "properties": {
    "iso:country":"DE",
    "sg:address":"Ottoweg 19",
    "sg:city":"Merseburg",
    "sg:phone":"+49 3461/525425",
    "sg:postcode":"06217",
    "sg:province":"Sachsen-Anhalt",
    "wof:name":"Hotel Merseburger Rabe",
    "wof:placetype":"venue"
},
  "geometry": {"coordinates":[11.9796323776,51.3525810242],"type":"Point"}
}