{
  "type": "Feature",
  "properties": {
    "iso:country":"DE",
    "sg:address":"Hackenbroicher Str. 80",
    "sg:city":"Pulheim",
    "sg:phone":"+49 2238/969617",
    "sg:postcode":"50259",
    "sg:province":"Nordrhein-Westfalen",
    "wof:name":"Medicus Alten- Und Krankenpflege",
    "wof:placetype":"venue"
},
  "geometry": {"coordinates":[6.79884,51.008801],"type":"Point"}
}