{
  "type": "Feature",
  "properties": {
    "iso:country":"DE",
    "sg:address":"Pogwischrund 7f",
    "sg:city":"Hamburg",
    "sg:phone":"+49 40/6729002",
    "sg:postcode":"22149",
    "sg:province":"Hamburg",
    "wof:name":"Heinrich Braunholz",
    "wof:placetype":"venue"
},
  "geometry": {"coordinates":[10.1489744186,53.5901870728],"type":"Point"}
}