{
  "type": "Feature",
  "properties": {
    "iso:country":"DE",
    "sg:address":"Am Dicken Turm 47",
    "sg:city":"Iserlohn",
    "sg:phone":"+49 2371/82500",
    "sg:postcode":"58636",
    "sg:province":"Nordrhein-Westfalen",
    "wof:name":"Sanit\u00e4tshaus Horst Enneper Inh. Dirk Enneper E. K.",
    "wof:placetype":"venue"
},
  "geometry": {"coordinates":[7.7004289627,51.3741645813],"type":"Point"}
}