{
  "type": "Feature",
  "properties": {
    "iso:country":"DE",
    "sg:address":"Pfungst\u00e4dter Str. 16",
    "sg:city":"Bickenbach",
    "sg:phone":"+49 6257/69670",
    "sg:postcode":"64404",
    "sg:province":"Hessen",
    "wof:name":"Birgit Ziegler Heilpraktikerin",
    "wof:placetype":"venue"
},
  "geometry": {"coordinates":[8.6121902466,49.7576713562],"type":"Point"}
}