{
  "type": "Feature",
  "properties": {
    "iso:country":"DE",
    "sg:address":"Abelsbergstr. 77-85",
    "sg:city":"Stuttgart",
    "sg:phone":"+49 711/268640",
    "sg:postcode":"70188",
    "sg:province":"Baden-W\u00fcrttemberg",
    "wof:name":"Erhardt Gmbh",
    "wof:placetype":"venue"
},
  "geometry": {"coordinates":[9.2129917145,48.7851791382],"type":"Point"}
}