{
  "type": "Feature",
  "properties": {
    "iso:country":"DE",
    "sg:address":"Hermann-Ehlers-Str. 8",
    "sg:city":"Brake",
    "sg:phone":"+49 4401/71144",
    "sg:postcode":"26919",
    "sg:province":"Niedersachsen",
    "wof:name":"Helmut Hullmann Aalaufzucht-verwaltungs Gmbh",
    "wof:placetype":"venue"
},
  "geometry": {"coordinates":[8.478303,53.306713],"type":"Point"}
}