{
  "type": "Feature",
  "properties": {
    "iso:country":"DE",
    "sg:address":"Grindelallee 188",
    "sg:city":"Hamburg",
    "sg:phone":"+49 40/41498944",
    "sg:postcode":"20144",
    "sg:province":"Hamburg",
    "wof:name":"Dr. Cohnitz Und Dr. Langhein Rechtsanw\u00e4lte",
    "wof:placetype":"venue"
},
  "geometry": {"coordinates":[9.9788236618,53.5721092224],"type":"Point"}
}