{
  "type": "Feature",
  "properties": {
    "iso:country":"DE",
    "sg:address":"Dautenheimer Landstr. 66",
    "sg:city":"Alzey",
    "sg:postcode":"55232",
    "sg:province":"Rheinland-Pfalz",
    "wof:name":"S\u00fcdwestdeutsche Vereinigung F\u00fcr Klinische Nervenheilkunde",
    "wof:placetype":"venue"
},
  "geometry": {"coordinates":[8.1300439835,49.7432975769],"type":"Point"}
}