{
  "type": "Feature",
  "properties": {
    "iso:country":"DE",
    "sg:address":"Mainzer Str. 116",
    "sg:city":"Saarbr\u00fccken",
    "sg:postcode":"66121",
    "sg:province":"Saarland",
    "wof:name":"Adaptive Micro Systems Deutschland Gmbh",
    "wof:placetype":"venue"
},
  "geometry": {"coordinates":[7.010889,49.229473],"type":"Point"}
}