{
  "type": "Feature",
  "properties": {
    "iso:country":"DE",
    "sg:address":"Goldene-Horn-Str. 23",
    "sg:city":"Bad Essen",
    "sg:phone":"+49 5472/7004",
    "sg:postcode":"49152",
    "sg:province":"Niedersachsen",
    "wof:name":"Hans-friedrich Fricke",
    "wof:placetype":"venue"
},
  "geometry": {"coordinates":[8.424506,52.330029],"type":"Point"}
}