{
  "type": "Feature",
  "properties": {
    "iso:country":"DE",
    "sg:address":"Randstr. 76",
    "sg:city":"Krefeld",
    "sg:phone":"+49 2151/712727",
    "sg:postcode":"47804",
    "sg:province":"Nordrhein-Westfalen",
    "wof:name":"A. Wallich Oelwehr",
    "wof:placetype":"venue"
},
  "geometry": {"coordinates":[6.539204,51.315865],"type":"Point"}
}