{
  "type": "Feature",
  "properties": {
    "iso:country":"DE",
    "sg:address":"Lenbachstr. 24",
    "sg:city":"G\u00fcnzburg",
    "sg:phone":"+49 8221/8421",
    "sg:postcode":"89312",
    "sg:province":"Bayern",
    "wof:name":"Elisabeth Sepp",
    "wof:placetype":"venue"
},
  "geometry": {"coordinates":[10.2995710373,48.4469833374],"type":"Point"}
}