{
  "type": "Feature",
  "properties": {
    "iso:country":"DE",
    "sg:address":"Hochstr. 21",
    "sg:city":"Gelsenkirchen",
    "sg:phone":"+49 209/37318",
    "sg:postcode":"45894",
    "sg:province":"Nordrhein-Westfalen",
    "wof:name":"Buersche Alte Apotheke",
    "wof:placetype":"venue"
},
  "geometry": {"coordinates":[7.053205,51.57925],"type":"Point"}
}