{
  "type": "Feature",
  "properties": {
    "iso:country":"DE",
    "sg:address":"Fischersteig 7",
    "sg:city":"Schweinfurt",
    "sg:postcode":"97421",
    "sg:province":"Bayern",
    "wof:name":"Sauter Gmbh",
    "wof:placetype":"venue"
},
  "geometry": {"coordinates":[10.232235,50.042534],"type":"Point"}
}