{
  "type": "Feature",
  "properties": {
    "iso:country":"DE",
    "sg:address":"Nimmendohrstr. 53",
    "sg:city":"Kamp-Lintfort",
    "sg:phone":"+49 2842/10326",
    "sg:postcode":"47475",
    "sg:province":"Nordrhein-Westfalen",
    "wof:name":"Karl Rademaker",
    "wof:placetype":"venue"
},
  "geometry": {"coordinates":[6.564808,51.502995],"type":"Point"}
}