{
  "type": "Feature",
  "properties": {
    "iso:country":"DE",
    "sg:address":"H\u00fcttenfeldstr. 3",
    "sg:city":"Bamberg",
    "sg:phone":"+49 951/17342",
    "sg:postcode":"96050",
    "sg:province":"Bayern",
    "wof:name":"Gothaer Versicherungs Ag",
    "wof:placetype":"venue"
},
  "geometry": {"coordinates":[10.9124221802,49.8873176575],"type":"Point"}
}