{
  "type": "Feature",
  "properties": {
    "iso:country":"DE",
    "sg:address":"Bremer Reihe 17",
    "sg:city":"Hamburg",
    "sg:phone":"+49 40/243212",
    "sg:postcode":"20099",
    "sg:province":"Hamburg",
    "wof:name":"Alt-schwerin",
    "wof:placetype":"venue"
},
  "geometry": {"coordinates":[10.0100307465,53.5538215637],"type":"Point"}
}