{
  "type": "Feature",
  "properties": {
    "iso:country":"DE",
    "sg:address":"Karlstr. 15",
    "sg:city":"Karlsruhe",
    "sg:phone":"+49 721/28128",
    "sg:postcode":"76133",
    "sg:province":"Baden-W\u00fcrttemberg",
    "wof:name":"Rolf Kahn",
    "wof:placetype":"venue"
},
  "geometry": {"coordinates":[8.3953199387,49.0103874207],"type":"Point"}
}