{
  "type": "Feature",
  "properties": {
    "iso:country":"DE",
    "sg:address":"Fernewaldstr. 298",
    "sg:city":"Bottrop",
    "sg:phone":"+49 2041/54621",
    "sg:postcode":"46242",
    "sg:province":"Nordrhein-Westfalen",
    "wof:name":"Karl-heinz Feische",
    "wof:placetype":"venue"
},
  "geometry": {"coordinates":[6.892862,51.538822],"type":"Point"}
}