{
  "type": "Feature",
  "properties": {
    "iso:country":"DE",
    "sg:address":"Michaelstr. 71",
    "sg:city":"Neuss",
    "sg:phone":"+49 2131/222801",
    "sg:postcode":"41460",
    "sg:province":"Nordrhein-Westfalen",
    "wof:name":"Bahali Toros",
    "wof:placetype":"venue"
},
  "geometry": {"coordinates":[6.6928582191,51.1965484619],"type":"Point"}
}