{
  "type": "Feature",
  "properties": {
    "iso:country":"DE",
    "sg:address":"Wittener Str. 85",
    "sg:city":"Castrop-Rauxel",
    "sg:phone":"+49 2305/25052",
    "sg:postcode":"44575",
    "sg:province":"Nordrhein-Westfalen",
    "wof:name":"Karl Heinz Schaarmann Gmbh Tischlerei Und Schreinerei",
    "wof:placetype":"venue"
},
  "geometry": {"coordinates":[7.316206,51.544106],"type":"Point"}
}