{
  "type": "Feature",
  "properties": {
    "iso:country":"DE",
    "sg:address":"Mainzerhofstr. 8",
    "sg:city":"Erfurt",
    "sg:postcode":"99084",
    "sg:province":"Th\u00fcringen",
    "wof:name":"Dipl.-ing. Barth Und Partner Architekten",
    "wof:placetype":"venue"
},
  "geometry": {"coordinates":[11.019634,50.974758],"type":"Point"}
}