{
  "type": "Feature",
  "properties": {
    "iso:country":"DE",
    "sg:address":"Sonnenleite 26",
    "sg:city":"Wollbach",
    "sg:phone":"+49 9773/398",
    "sg:postcode":"97618",
    "sg:province":"Bayern",
    "wof:name":"Hella M\u00fcnch Gmbh",
    "wof:placetype":"venue"
},
  "geometry": {"coordinates":[10.2219295502,50.3690338135],"type":"Point"}
}