{
  "type": "Feature",
  "properties": {
    "iso:country":"DE",
    "sg:address":"Rathausstr. 67",
    "sg:city":"Geesthacht",
    "sg:phone":"+49 4152/2375",
    "sg:postcode":"21502",
    "sg:province":"Schleswig-Holstein",
    "wof:name":"Manfred Kreutzfeld Ofensetzerei",
    "wof:placetype":"venue"
},
  "geometry": {"coordinates":[10.3752450943,53.435710907],"type":"Point"}
}