{
  "type": "Feature",
  "properties": {
    "iso:country":"DE",
    "sg:address":"Goethestr. 16",
    "sg:city":"Ravenstein",
    "sg:postcode":"74747",
    "sg:province":"Baden-W\u00fcrttemberg",
    "wof:name":"Sternwarte",
    "wof:placetype":"venue"
},
  "geometry": {"coordinates":[9.5628824234,49.4299812317],"type":"Point"}
}