{
  "type": "Feature",
  "properties": {
    "iso:country":"DE",
    "sg:address":"Beyrodtstr. 15",
    "sg:city":"Berlin",
    "sg:phone":"+49 30/7218515",
    "sg:postcode":"12277",
    "sg:province":"Berlin",
    "wof:name":"Musikverein Und Orchester Berlin",
    "wof:placetype":"venue"
},
  "geometry": {"coordinates":[13.3676872253,52.423122406],"type":"Point"}
}