{
  "type": "Feature",
  "properties": {
    "iso:country":"DE",
    "sg:address":"Henrik-Ibsen-Str. 29",
    "sg:city":"Rostock",
    "sg:phone":"+49 381/2074960",
    "sg:postcode":"18106",
    "sg:province":"Mecklenburg-Vorpommern",
    "wof:name":"Poseidon-apotheke Inh. Torsten Stenzel E. K.",
    "wof:placetype":"venue"
},
  "geometry": {"coordinates":[12.06034,54.12009],"type":"Point"}
}