{
  "type": "Feature",
  "properties": {
    "iso:country":"DE",
    "sg:address":"Gottbillstr. 34",
    "sg:city":"Trier",
    "sg:phone":"+49 651/821765",
    "sg:postcode":"54294",
    "sg:province":"Rheinland-Pfalz",
    "wof:name":"Das Fachteam Andreas Gassel",
    "wof:placetype":"venue"
},
  "geometry": {"coordinates":[6.593386,49.725948],"type":"Point"}
}