{
  "type": "Feature",
  "properties": {
    "iso:country":"DE",
    "sg:address":"Lerchenstr. 5",
    "sg:city":"M\u00fcnchen",
    "sg:phone":"+49 89/3573390",
    "sg:postcode":"80995",
    "sg:province":"Bayern",
    "wof:name":"Balzers & Leybold Deutschland Holding Ag",
    "wof:placetype":"venue"
},
  "geometry": {"coordinates":[11.543342,48.201221],"type":"Point"}
}