{
  "type": "Feature",
  "properties": {
    "iso:country":"DE",
    "sg:address":"Karnapp 20",
    "sg:city":"Hamburg",
    "sg:phone":"+49 40/7660070",
    "sg:postcode":"21079",
    "sg:province":"Hamburg",
    "wof:name":"Harburger Binnenhafen Gmbh & Co. Kg",
    "wof:placetype":"venue"
},
  "geometry": {"coordinates":[9.9848928452,53.4633331299],"type":"Point"}
}