{
  "type": "Feature",
  "properties": {
    "iso:country":"DE",
    "sg:address":"Am Goldenen Feld 27",
    "sg:city":"Kulmbach",
    "sg:phone":"+49 9221/97460",
    "sg:postcode":"95326",
    "sg:province":"Bayern",
    "wof:name":"Ask Gmbh & Co. Kg",
    "wof:placetype":"venue"
},
  "geometry": {"coordinates":[11.420581,50.098324],"type":"Point"}
}