{
  "type": "Feature",
  "properties": {
    "iso:country":"DE",
    "sg:address":"Bergfelder Str. 8",
    "sg:city":"Birkenwerder",
    "sg:postcode":"16547",
    "sg:province":"Brandenburg",
    "wof:name":"Hamelow & Klenz Hausverwaltung Gmbh",
    "wof:placetype":"venue"
},
  "geometry": {"coordinates":[13.2920236588,52.6866760254],"type":"Point"}
}