{
  "type": "Feature",
  "properties": {
    "iso:country":"DE",
    "sg:address":"Plenterstr. 28",
    "sg:city":"Kr\u00f6v",
    "sg:phone":"+49 6541/9264",
    "sg:postcode":"54536",
    "sg:province":"Rheinland-Pfalz",
    "wof:name":"Krakau-junglen",
    "wof:placetype":"venue"
},
  "geometry": {"coordinates":[7.0858860016,49.9777030945],"type":"Point"}
}