{
  "type": "Feature",
  "properties": {
    "iso:country":"DE",
    "sg:address":"Pracherweg 1",
    "sg:city":"Vehlow",
    "sg:postcode":"16866",
    "sg:province":"Brandenburg",
    "wof:name":"Modische Damenober- Bekleidung Gmbh",
    "wof:placetype":"venue"
},
  "geometry": {"coordinates":[12.3964452744,52.9393882751],"type":"Point"}
}