{
  "type": "Feature",
  "properties": {
    "iso:country":"DE",
    "sg:address":"August-Bebel-Str. 231c",
    "sg:city":"Crottendorf/Erzgeb.",
    "sg:phone":"+49 4937/3447700",
    "sg:postcode":"09474",
    "sg:province":"Sachsen",
    "wof:name":"Aiv Kabelwerk Gmbh",
    "wof:placetype":"venue"
},
  "geometry": {"coordinates":[12.941757,50.511734],"type":"Point"}
}