{
  "type": "Feature",
  "properties": {
    "iso:country":"DE",
    "sg:address":"Kirchplatz 26",
    "sg:city":"Steinhagen",
    "sg:phone":"+49 5204/8289",
    "sg:postcode":"33803",
    "sg:province":"Nordrhein-Westfalen",
    "wof:name":"K\u00f6nig Verm\u00f6gens- Verwaltungs- Gmbh",
    "wof:placetype":"venue"
},
  "geometry": {"coordinates":[8.413399,52.005276],"type":"Point"}
}