{
  "type": "Feature",
  "properties": {
    "iso:country":"DE",
    "sg:address":"Ludwig-Thoma-Str. 23",
    "sg:city":"Bayreuth",
    "sg:phone":"+49 921/761686",
    "sg:postcode":"95447",
    "sg:province":"Bayern",
    "wof:name":"Scholz",
    "wof:placetype":"venue"
},
  "geometry": {"coordinates":[11.568782,49.933865],"type":"Point"}
}