{
  "type": "Feature",
  "properties": {
    "iso:country":"DE",
    "sg:address":"Kirchberger Str. 121",
    "sg:city":"Crailsheim",
    "sg:phone":"+49 7951/22622",
    "sg:postcode":"74564",
    "sg:province":"Baden-W\u00fcrttemberg",
    "wof:name":"Manfred Beiser",
    "wof:placetype":"venue"
},
  "geometry": {"coordinates":[10.041891,49.162769],"type":"Point"}
}