{
  "type": "Feature",
  "properties": {
    "iso:country":"DE",
    "sg:address":"Meinekestr. 7",
    "sg:city":"Berlin",
    "sg:phone":"+49 30/8831544",
    "sg:postcode":"10719",
    "sg:province":"Berlin",
    "wof:name":"Wilhelm Kunz Architekt",
    "wof:placetype":"venue"
},
  "geometry": {"coordinates":[13.328796,52.501766],"type":"Point"}
}