{
  "type": "Feature",
  "properties": {
    "iso:country":"DE",
    "sg:address":"Wangerstr. 3",
    "sg:city":"Jever",
    "sg:phone":"+49 4461/5253",
    "sg:postcode":"26441",
    "sg:province":"Niedersachsen",
    "wof:name":"Wilfried Lose",
    "wof:placetype":"venue"
},
  "geometry": {"coordinates":[7.901231,53.574245],"type":"Point"}
}