{
  "type": "Feature",
  "properties": {
    "iso:country":"DE",
    "sg:address":"Leopoldstr. 30",
    "sg:city":"Daun",
    "sg:phone":"+49 6592/4050",
    "sg:postcode":"54550",
    "sg:province":"Rheinland-Pfalz",
    "wof:name":"Thomas Schmitz",
    "wof:placetype":"venue"
},
  "geometry": {"coordinates":[6.8271250725,50.199634552],"type":"Point"}
}