{
  "type": "Feature",
  "properties": {
    "iso:country":"DE",
    "sg:address":"Landstr. 33",
    "sg:city":"Salzgitter",
    "sg:phone":"+49 5341/9880",
    "sg:postcode":"38229",
    "sg:province":"Niedersachsen",
    "wof:name":"Ev. Pfarramt Flahst\u00f6ckheim",
    "wof:placetype":"venue"
},
  "geometry": {"coordinates":[10.3804283142,52.0897903442],"type":"Point"}
}