{
  "type": "Feature",
  "properties": {
    "iso:country":"DE",
    "sg:address":"Hauptstr. 34",
    "sg:city":"Kirrweiler",
    "sg:phone":"+49 6321/952653",
    "sg:postcode":"67489",
    "sg:province":"Rheinland-Pfalz",
    "wof:name":"L. Dorst- Und A. Glaser-dorst",
    "wof:placetype":"venue"
},
  "geometry": {"coordinates":[8.163482666,49.3023681641],"type":"Point"}
}