{
  "type": "Feature",
  "properties": {
    "iso:country":"DE",
    "sg:address":"Vennhauser Allee 172",
    "sg:city":"D\u00fcsseldorf",
    "sg:phone":"+49 211/2099590",
    "sg:postcode":"40627",
    "sg:province":"Nordrhein-Westfalen",
    "wof:name":"Duarte & Weigl Gmbh",
    "wof:placetype":"venue"
},
  "geometry": {"coordinates":[6.8571791649,51.2065582275],"type":"Point"}
}