{
  "type": "Feature",
  "properties": {
    "iso:country":"DE",
    "sg:address":"Paradiesgasse 12",
    "sg:city":"Hainburg",
    "sg:phone":"+49 6182/69530",
    "sg:postcode":"63512",
    "sg:province":"Hessen",
    "wof:name":"Gerhard Kins",
    "wof:placetype":"venue"
},
  "geometry": {"coordinates":[8.9375810623,50.0808792114],"type":"Point"}
}