{
  "type": "Feature",
  "properties": {
    "iso:country":"DE",
    "sg:address":"Virchowstr. 1",
    "sg:city":"Friedrichshafen",
    "sg:phone":"+49 7541/41450",
    "sg:postcode":"88048",
    "sg:province":"Baden-W\u00fcrttemberg",
    "wof:name":"K. K\u00fchner",
    "wof:placetype":"venue"
},
  "geometry": {"coordinates":[9.43435,47.67049],"type":"Point"}
}