{
  "type": "Feature",
  "properties": {
    "iso:country":"DE",
    "sg:address":"Am Galgenberg 5",
    "sg:city":"Marktredwitz",
    "sg:phone":"+49 9231/61123",
    "sg:postcode":"95615",
    "sg:province":"Bayern",
    "wof:name":"Erhard Willumeit Ingenieur",
    "wof:placetype":"venue"
},
  "geometry": {"coordinates":[12.0970497131,50.0071983337],"type":"Point"}
}