{
  "type": "Feature",
  "properties": {
    "iso:country":"DE",
    "sg:address":"Theresienplatz 5",
    "sg:city":"Straubing",
    "sg:phone":"+49 9421/10960",
    "sg:postcode":"94315",
    "sg:province":"Bayern",
    "wof:name":"Hans-peter Hiller",
    "wof:placetype":"venue"
},
  "geometry": {"coordinates":[12.5665845871,48.8814811707],"type":"Point"}
}