{
  "type": "Feature",
  "properties": {
    "iso:country":"DE",
    "sg:address":"Brotstr. 18-19",
    "sg:city":"Trier",
    "sg:postcode":"54290",
    "sg:province":"Rheinland-Pfalz",
    "wof:name":"La Lernen Und Arbeiten Ggmbh",
    "wof:placetype":"venue"
},
  "geometry": {"coordinates":[6.64064,49.75473],"type":"Point"}
}