{
  "type": "Feature",
  "properties": {
    "iso:country":"DE",
    "sg:address":"Am Hollerborn 5",
    "sg:city":"Laufach",
    "sg:phone":"+49 6093/8259",
    "sg:postcode":"63846",
    "sg:province":"Bayern",
    "wof:name":"Klaus Beck",
    "wof:placetype":"venue"
},
  "geometry": {"coordinates":[9.301035,50.015446],"type":"Point"}
}