{
  "type": "Feature",
  "properties": {
    "iso:country":"DE",
    "sg:address":"Vorderstr. 46",
    "sg:city":"Siedenburg",
    "sg:phone":"+49 4272/1309",
    "sg:postcode":"27254",
    "sg:province":"Niedersachsen",
    "wof:name":"Willi Griffel",
    "wof:placetype":"venue"
},
  "geometry": {"coordinates":[8.936928,52.694057],"type":"Point"}
}