{
  "type": "Feature",
  "properties": {
    "iso:country":"DE",
    "sg:address":"Lobensteiner Str. 42",
    "sg:city":"Liebsch\u00fctz",
    "sg:phone":"+49 36640/22744",
    "sg:postcode":"07368",
    "sg:province":"Th\u00fcringen",
    "wof:name":"A. Hirt",
    "wof:placetype":"venue"
},
  "geometry": {"coordinates":[11.6028175354,50.5349655151],"type":"Point"}
}