{
  "type": "Feature",
  "properties": {
    "iso:country":"DE",
    "sg:address":"Erich-Ollenhauer-Str. 239",
    "sg:city":"Wiesbaden",
    "sg:phone":"+49 611/942860",
    "sg:postcode":"65199",
    "sg:province":"Hessen",
    "wof:name":"K\u00fcstermann Gmbh",
    "wof:placetype":"venue"
},
  "geometry": {"coordinates":[8.211292,50.06567],"type":"Point"}
}