{
  "type": "Feature",
  "properties": {
    "iso:country":"DE",
    "sg:address":"Marktstr. 40",
    "sg:city":"Boxberg",
    "sg:phone":"+49 7930/6225",
    "sg:postcode":"97944",
    "sg:province":"Baden-W\u00fcrttemberg",
    "wof:name":"Krone",
    "wof:placetype":"venue"
},
  "geometry": {"coordinates":[9.6696395874,49.4903526306],"type":"Point"}
}