{
  "type": "Feature",
  "properties": {
    "iso:country":"DE",
    "sg:address":"Tiergartenstr. 23",
    "sg:city":"Hannover",
    "sg:phone":"+49 511/520423",
    "sg:postcode":"30559",
    "sg:province":"Niedersachsen",
    "wof:name":"Vereinsgastst\u00e4tte Tkh",
    "wof:placetype":"venue"
},
  "geometry": {"coordinates":[9.8140306473,52.3649787903],"type":"Point"}
}