{
  "type": "Feature",
  "properties": {
    "iso:country":"DE",
    "sg:address":"18.-M\u00e4rz-Str. 34a",
    "sg:city":"Gotha",
    "sg:phone":"+49 3621/71400",
    "sg:postcode":"99867",
    "sg:province":"Th\u00fcringen",
    "wof:name":"Dr. Herbert Becherer",
    "wof:placetype":"venue"
},
  "geometry": {"coordinates":[10.6947069168,50.9451751709],"type":"Point"}
}