{
  "type": "Feature",
  "properties": {
    "iso:country":"DE",
    "sg:city":"Dransfeld",
    "sg:phone":"+49 5502/94193",
    "sg:postcode":"37127",
    "sg:province":"Niedersachsen",
    "wof:name":"Ralf Weitemeier Architekt",
    "wof:placetype":"venue"
},
  "geometry": {"coordinates":[9.75936,51.502956],"type":"Point"}
}