{
  "type": "Feature",
  "properties": {
    "iso:country":"DE",
    "sg:address":"K\u00f6nigstr. 1",
    "sg:city":"Dortmund",
    "sg:phone":"+49 231/2000562",
    "sg:postcode":"44309",
    "sg:province":"Nordrhein-Westfalen",
    "wof:name":"Gastst\u00e4tte Paperlapapp",
    "wof:placetype":"venue"
},
  "geometry": {"coordinates":[7.5499792099,51.5214385986],"type":"Point"}
}