{
  "type": "Feature",
  "properties": {
    "iso:country":"DE",
    "sg:address":"Friedrich-Hegel-Str. 27",
    "sg:city":"Dresden",
    "sg:postcode":"01187",
    "sg:province":"Sachsen",
    "wof:name":"Dr. Med. Eberhard Hahn",
    "wof:placetype":"venue"
},
  "geometry": {"coordinates":[13.714051,51.023258],"type":"Point"}
}