{
  "type": "Feature",
  "properties": {
    "iso:country":"DE",
    "sg:address":"V\u00f6hlinstr. 18",
    "sg:city":"V\u00f6hringen",
    "sg:phone":"+49 7306/928482",
    "sg:postcode":"89269",
    "sg:province":"Bayern",
    "wof:name":"Gewinnspiel 200 Kostenlose Gewinnspiele",
    "wof:placetype":"venue"
},
  "geometry": {"coordinates":[10.0760793686,48.27734375],"type":"Point"}
}