{
  "type": "Feature",
  "properties": {
    "iso:country":"DE",
    "sg:address":"Soester Str. 40",
    "sg:city":"Werl",
    "sg:phone":"+49 2922/3170",
    "sg:postcode":"59457",
    "sg:province":"Nordrhein-Westfalen",
    "wof:name":"Sch\u00e4fer",
    "wof:placetype":"venue"
},
  "geometry": {"coordinates":[7.92097,51.549286],"type":"Point"}
}