{
  "type": "Feature",
  "properties": {
    "iso:country":"DE",
    "sg:address":"Kolbestr. 4d",
    "sg:city":"Seelze",
    "sg:phone":"+49 5137/4055",
    "sg:postcode":"30926",
    "sg:province":"Niedersachsen",
    "wof:name":"Bgd Gesellschaft F\u00fcr Bauten Grundst\u00fccke Und",
    "wof:placetype":"venue"
},
  "geometry": {"coordinates":[9.593971,52.398193],"type":"Point"}
}