{
  "type": "Feature",
  "properties": {
    "iso:country":"DE",
    "sg:address":"Schweitenkirchen",
    "sg:city":"Schweitenkirchen",
    "sg:phone":"+49 8444/256",
    "sg:postcode":"85301",
    "sg:province":"Bayern",
    "wof:name":"Raiffeisenbank Pfaffenhofen/ilm Eg",
    "wof:placetype":"venue"
},
  "geometry": {"coordinates":[11.61501,48.511909],"type":"Point"}
}