{
  "type": "Feature",
  "properties": {
    "iso:country":"DE",
    "sg:address":"Wendelsteinstr. 6",
    "sg:city":"Prien",
    "sg:phone":"+49 8051/61020",
    "sg:postcode":"83209",
    "sg:province":"Bayern",
    "wof:name":"Willy Negele",
    "wof:placetype":"venue"
},
  "geometry": {"coordinates":[12.345717,47.85363],"type":"Point"}
}