{
  "type": "Feature",
  "properties": {
    "iso:country":"DE",
    "sg:address":"Rasenweg 20",
    "sg:city":"Malsfeld",
    "sg:phone":"+49 5661/52160",
    "sg:postcode":"34323",
    "sg:province":"Hessen",
    "wof:name":"Landsitz Elfershausen Fachpflege Gmbh",
    "wof:placetype":"venue"
},
  "geometry": {"coordinates":[9.50161,51.096111],"type":"Point"}
}