{
  "type": "Feature",
  "properties": {
    "iso:country":"DE",
    "sg:address":"Schluchsee",
    "sg:city":"Schluchsee",
    "sg:phone":"+49 4976/56304",
    "sg:postcode":"79859",
    "sg:province":"Baden-W\u00fcrttemberg",
    "wof:name":"Volksbank Schluchsee",
    "wof:placetype":"venue"
},
  "geometry": {"coordinates":[8.15688,47.802792],"type":"Point"}
}