{
  "type": "Feature",
  "properties": {
    "iso:country":"DE",
    "sg:address":"Anhaltische Str. 19 a",
    "sg:city":"K\u00f6then",
    "sg:postcode":"06366",
    "sg:province":"Sachsen-Anhalt",
    "wof:name":"Str\u00f6hla Stra\u00dfen- Und Tiefbau Gmbh",
    "wof:placetype":"venue"
},
  "geometry": {"coordinates":[11.9525184631,51.7430458069],"type":"Point"}
}