{
  "type": "Feature",
  "properties": {
    "iso:country":"DE",
    "sg:address":"Aign 2",
    "sg:city":"Mitterfels",
    "sg:postcode":"94360",
    "sg:province":"Bayern",
    "wof:name":"Domo Contract Bautr\u00e4ger Gmbh",
    "wof:placetype":"venue"
},
  "geometry": {"coordinates":[12.676865,48.97311],"type":"Point"}
}