{
  "type": "Feature",
  "properties": {
    "iso:country":"DE",
    "sg:address":"M\u00fcnsterstr. 59",
    "sg:city":"L\u00fcdinghausen",
    "sg:phone":"+49 2591/3339",
    "sg:postcode":"59348",
    "sg:province":"Nordrhein-Westfalen",
    "wof:name":"Gastst\u00e4tte Georg Pals",
    "wof:placetype":"venue"
},
  "geometry": {"coordinates":[7.4469771385,51.7748336792],"type":"Point"}
}