{
  "type": "Feature",
  "properties": {
    "iso:country":"DE",
    "sg:address":"Reeshoop 60",
    "sg:city":"Ahrensburg",
    "sg:phone":"+49 4102/42223",
    "sg:postcode":"22926",
    "sg:province":"Schleswig-Holstein",
    "wof:name":"Ehnert & G\u00f6lles Gmbh",
    "wof:placetype":"venue"
},
  "geometry": {"coordinates":[10.2341499329,53.6817131042],"type":"Point"}
}