{
  "type": "Feature",
  "properties": {
    "iso:country":"DE",
    "sg:address":"Memminger Str. 55",
    "sg:city":"Neu-Ulm",
    "sg:phone":"+49 731/985900",
    "sg:postcode":"89231",
    "sg:province":"Bayern",
    "wof:name":"Friedrich Sailer Gmbh",
    "wof:placetype":"venue"
},
  "geometry": {"coordinates":[10.0033550262,48.385635376],"type":"Point"}
}