{
  "type": "Feature",
  "properties": {
    "iso:country":"DE",
    "sg:address":"Carlsh\u00fctte 21",
    "sg:city":"Gnarrenburg",
    "sg:phone":"+49 4763/6035",
    "sg:postcode":"27442",
    "sg:province":"Niedersachsen",
    "wof:name":"Hans-heinrich Deppe",
    "wof:placetype":"venue"
},
  "geometry": {"coordinates":[9.011589,53.369202],"type":"Point"}
}