{
  "type": "Feature",
  "properties": {
    "iso:country":"DE",
    "sg:address":"Hanauer Landstr. 146",
    "sg:city":"Frankfurt",
    "sg:phone":"+49 69/4058840",
    "sg:postcode":"60314",
    "sg:province":"Hessen",
    "wof:name":"Frankfurt Lions",
    "wof:placetype":"venue"
},
  "geometry": {"coordinates":[8.7148971558,50.1123466492],"type":"Point"}
}