{
  "type": "Feature",
  "properties": {
    "iso:country":"DE",
    "sg:address":"Kaiserstr. 44",
    "sg:city":"D\u00fcsseldorf",
    "sg:phone":"+49 211/4931087",
    "sg:postcode":"40479",
    "sg:province":"Nordrhein-Westfalen",
    "wof:name":"Casa-verde Raum- Und Gartengestaltungs-gmbh",
    "wof:placetype":"venue"
},
  "geometry": {"coordinates":[6.780457,51.23177],"type":"Point"}
}