{
  "type": "Feature",
  "properties": {
    "iso:country":"DE",
    "sg:address":"August-Kronenberger-Str. 2",
    "sg:city":"Saarlouis",
    "sg:phone":"+49 6831/61648",
    "sg:postcode":"66740",
    "sg:province":"Saarland",
    "wof:name":"Beate Kreis",
    "wof:placetype":"venue"
},
  "geometry": {"coordinates":[6.7187600136,49.3078994751],"type":"Point"}
}