{
  "type": "Feature",
  "properties": {
    "iso:country":"DE",
    "sg:address":"Finkenkamp 48",
    "sg:city":"Braunschweig",
    "sg:phone":"+49 531/360540",
    "sg:postcode":"38104",
    "sg:province":"Niedersachsen",
    "wof:name":"Alan Lewis",
    "wof:placetype":"venue"
},
  "geometry": {"coordinates":[10.5870046616,52.2845573425],"type":"Point"}
}