{
  "type": "Feature",
  "properties": {
    "iso:country":"DE",
    "sg:address":"Dieselstr. 9",
    "sg:city":"Kempten",
    "sg:phone":"+49 831/7030450",
    "sg:postcode":"87437",
    "sg:province":"Bayern",
    "wof:name":"Der Reinigungsfachmarkt Lattemann & Geiger Ohg",
    "wof:placetype":"venue"
},
  "geometry": {"coordinates":[10.316431,47.754269],"type":"Point"}
}