{
  "type": "Feature",
  "properties": {
    "iso:country":"DE",
    "sg:address":"Kirchplatz 1",
    "sg:city":"Delbr\u00fcck",
    "sg:phone":"+49 5250/41317",
    "sg:postcode":"33129",
    "sg:province":"Nordrhein-Westfalen",
    "wof:name":"Haargenau - Keralogie Produktserien",
    "wof:placetype":"venue"
},
  "geometry": {"coordinates":[8.5622329712,51.7647628784],"type":"Point"}
}