{
  "type": "Feature",
  "properties": {
    "iso:country":"DE",
    "sg:address":"Maximilianstr. 43",
    "sg:city":"Augsburg",
    "sg:phone":"+49 821/33011",
    "sg:postcode":"86150",
    "sg:province":"Bayern",
    "wof:name":"Prosale Handelsges. Mbh",
    "wof:placetype":"venue"
},
  "geometry": {"coordinates":[10.8990259171,48.366481781],"type":"Point"}
}