{
  "type": "Feature",
  "properties": {
    "iso:country":"DE",
    "sg:address":"H\u00fcterplan 14",
    "sg:city":"Osterfeld",
    "sg:phone":"+49 34422/21310",
    "sg:postcode":"06721",
    "sg:province":"Sachsen-Anhalt",
    "wof:name":"Antje Salzmann",
    "wof:placetype":"venue"
},
  "geometry": {"coordinates":[11.930603981,51.0780448914],"type":"Point"}
}