{
  "type": "Feature",
  "properties": {
    "iso:country":"DE",
    "sg:address":"Hauptstr. 44",
    "sg:city":"Rockenhausen",
    "sg:postcode":"67806",
    "sg:province":"Rheinland-Pfalz",
    "wof:name":"Silicon Avionics Gmbh",
    "wof:placetype":"venue"
},
  "geometry": {"coordinates":[7.792611,49.616264],"type":"Point"}
}