{
  "type": "Feature",
  "properties": {
    "iso:country":"DE",
    "sg:address":"Augustastr. 14",
    "sg:city":"Hattingen",
    "sg:phone":"+49 2324/51157",
    "sg:postcode":"45525",
    "sg:province":"Nordrhein-Westfalen",
    "wof:name":"Thomas Philipp",
    "wof:placetype":"venue"
},
  "geometry": {"coordinates":[7.1839947701,51.3997154236],"type":"Point"}
}