{
  "type": "Feature",
  "properties": {
    "iso:country":"DE",
    "sg:address":"Im Woogtal 32",
    "sg:city":"Bobenheim am Berg",
    "sg:postcode":"67273",
    "sg:province":"Rheinland-Pfalz",
    "wof:name":"Scholze Beteiligungs-gmbh",
    "wof:placetype":"venue"
},
  "geometry": {"coordinates":[8.14115,49.520649],"type":"Point"}
}