{
  "type": "Feature",
  "properties": {
    "iso:country":"DE",
    "sg:address":"Martin-Reinhard-Str. 17",
    "sg:city":"Bad K\u00f6nigshofen",
    "sg:phone":"+49 9761/6367",
    "sg:postcode":"97631",
    "sg:province":"Bayern",
    "wof:name":"R. Schlimbach",
    "wof:placetype":"venue"
},
  "geometry": {"coordinates":[10.4690713882,50.2998962402],"type":"Point"}
}