{
  "type": "Feature",
  "properties": {
    "iso:country":"DE",
    "sg:address":"Bismarckstr. 35",
    "sg:city":"Fr\u00f6ndenberg",
    "sg:phone":"+49 2373/72288",
    "sg:postcode":"58730",
    "sg:province":"Nordrhein-Westfalen",
    "wof:name":"Josef Mertens Bedachungsgesellschaft Mbh",
    "wof:placetype":"venue"
},
  "geometry": {"coordinates":[7.778569,51.473694],"type":"Point"}
}