{
  "type": "Feature",
  "properties": {
    "iso:country":"DE",
    "sg:address":"Staig 18",
    "sg:city":"Hechingen",
    "sg:phone":"+49 7471/16964",
    "sg:postcode":"72379",
    "sg:province":"Baden-W\u00fcrttemberg",
    "wof:name":"\u00d6mer \u00d6zdemir",
    "wof:placetype":"venue"
},
  "geometry": {"coordinates":[8.9657506943,48.3532562256],"type":"Point"}
}