{
  "type": "Feature",
  "properties": {
    "iso:country":"DE",
    "sg:address":"Achtelstr. 20",
    "sg:city":"Simmelsdorf",
    "sg:phone":"+49 9155/430",
    "sg:postcode":"91245",
    "sg:province":"Bayern",
    "wof:name":"Konrad Lehmeier",
    "wof:placetype":"venue"
},
  "geometry": {"coordinates":[11.355609,49.606766],"type":"Point"}
}