{
  "type": "Feature",
  "properties": {
    "iso:country":"DE",
    "sg:address":"Dorfstr. 58",
    "sg:city":"Sollstedt",
    "sg:postcode":"99759",
    "sg:province":"Th\u00fcringen",
    "wof:name":"Wilhelm Bracht Tief- Und Stra\u00dfenbau Gmbh",
    "wof:placetype":"venue"
},
  "geometry": {"coordinates":[10.537909,51.412289],"type":"Point"}
}