{
  "type": "Feature",
  "properties": {
    "iso:country":"DE",
    "sg:address":"Krausestr.102",
    "sg:city":"Hamburg",
    "sg:phone":"+49 40/6894770",
    "sg:postcode":"22049",
    "sg:province":"Hamburg",
    "wof:name":"Agentur Alberts - Versicherungsvergleiche",
    "wof:placetype":"venue"
},
  "geometry": {"coordinates":[10.0579586029,53.5781173706],"type":"Point"}
}