{
  "type": "Feature",
  "properties": {
    "iso:country":"DE",
    "sg:address":"Unterer Burggarten 26",
    "sg:city":"Dossenheim",
    "sg:postcode":"69221",
    "sg:province":"Baden-W\u00fcrttemberg",
    "wof:name":"Helmut Hildebrand E. K.",
    "wof:placetype":"venue"
},
  "geometry": {"coordinates":[8.6760149002,49.4564437866],"type":"Point"}
}