{
  "type": "Feature",
  "properties": {
    "iso:country":"DE",
    "sg:address":"Schulstr. 3",
    "sg:city":"Kreiensen",
    "sg:phone":"+49 5563/910191",
    "sg:postcode":"37547",
    "sg:province":"Niedersachsen",
    "wof:name":"Pflegedienst Rother",
    "wof:placetype":"venue"
},
  "geometry": {"coordinates":[9.993606,51.827339],"type":"Point"}
}