{
  "type": "Feature",
  "properties": {
    "iso:country":"DE",
    "sg:address":"S\u00fcntelstr. 1",
    "sg:city":"Hamburg",
    "sg:phone":"+49 40/5592365",
    "sg:postcode":"22457",
    "sg:province":"Hamburg",
    "wof:name":"Bifurcated Engineering Gmbh",
    "wof:placetype":"venue"
},
  "geometry": {"coordinates":[9.9075298309,53.6322975159],"type":"Point"}
}