{
  "type": "Feature",
  "properties": {
    "iso:country":"DE",
    "sg:address":"Rudolf-Diesel-Ring 18",
    "sg:city":"Bad Neustadt",
    "sg:postcode":"97616",
    "sg:province":"Bayern",
    "wof:name":"G\u00fcnther Baumarkt Betriebsverwaltungs Gmbh",
    "wof:placetype":"venue"
},
  "geometry": {"coordinates":[10.2267789841,50.3336105347],"type":"Point"}
}