{
  "type": "Feature",
  "properties": {
    "iso:country":"DE",
    "sg:address":"Bachemer Str. 91",
    "sg:city":"K\u00f6ln",
    "sg:postcode":"50931",
    "sg:province":"Nordrhein-Westfalen",
    "wof:name":"Schmidt Media Gmbh",
    "wof:placetype":"venue"
},
  "geometry": {"coordinates":[6.917316,50.928616],"type":"Point"}
}