{
  "type": "Feature",
  "properties": {
    "iso:country":"DE",
    "sg:address":"Hafenstr. 2",
    "sg:city":"Forchheim",
    "sg:phone":"+49 9191/66614",
    "sg:postcode":"91301",
    "sg:province":"Bayern",
    "wof:name":"M\u00f6po-m\u00f6belposten Handelsgesellschaft Mbh",
    "wof:placetype":"venue"
},
  "geometry": {"coordinates":[11.060475,49.706772],"type":"Point"}
}