{
  "type": "Feature",
  "properties": {
    "iso:country":"DE",
    "sg:address":"Kirchgasse 30",
    "sg:city":"M\u00fcnzenberg",
    "sg:phone":"+49 6033/64488",
    "sg:postcode":"35516",
    "sg:province":"Hessen",
    "wof:name":"Adler-apotheke",
    "wof:placetype":"venue"
},
  "geometry": {"coordinates":[8.72895,50.460457],"type":"Point"}
}