{
  "type": "Feature",
  "properties": {
    "iso:country":"DE",
    "sg:address":"Niedersachsenweg 4",
    "sg:city":"Troisdorf",
    "sg:phone":"+49 2241/946610",
    "sg:postcode":"53844",
    "sg:province":"Nordrhein-Westfalen",
    "wof:name":"L & R Unternehmens- Beratung Gmbh",
    "wof:placetype":"venue"
},
  "geometry": {"coordinates":[7.1230897903,50.8103103638],"type":"Point"}
}