{
  "type": "Feature",
  "properties": {
    "iso:country":"DE",
    "sg:address":"Am Gutshof 6",
    "sg:city":"Werder",
    "sg:postcode":"14542",
    "sg:province":"Brandenburg",
    "wof:name":"Lts Bau Gmbh",
    "wof:placetype":"venue"
},
  "geometry": {"coordinates":[12.9373512268,52.3755264282],"type":"Point"}
}