{
  "type": "Feature",
  "properties": {
    "iso:country":"DE",
    "sg:address":"Leipziger Str. 51",
    "sg:city":"Grimma",
    "sg:phone":"+49 3437/944348",
    "sg:postcode":"04668",
    "sg:province":"Sachsen",
    "wof:name":"M. Schulz",
    "wof:placetype":"venue"
},
  "geometry": {"coordinates":[12.7152414322,51.2315559387],"type":"Point"}
}