{
  "type": "Feature",
  "properties": {
    "iso:country":"DE",
    "sg:address":"Hirschgartenallee 35b",
    "sg:city":"M\u00fcnchen",
    "sg:phone":"+49 89/173301",
    "sg:postcode":"80639",
    "sg:province":"Bayern",
    "wof:name":"H. Melkus Kunstmaler",
    "wof:placetype":"venue"
},
  "geometry": {"coordinates":[11.507046,48.15366],"type":"Point"}
}