{
  "type": "Feature",
  "properties": {
    "iso:country":"DE",
    "sg:address":"Merklinger Str. 22",
    "sg:city":"Renningen",
    "sg:phone":"+49 7159/5177",
    "sg:postcode":"71272",
    "sg:province":"Baden-W\u00fcrttemberg",
    "wof:name":"Ev. Pfarramt Malmsheim",
    "wof:placetype":"venue"
},
  "geometry": {"coordinates":[8.9017457962,48.7758293152],"type":"Point"}
}