{
  "type": "Feature",
  "properties": {
    "iso:country":"DE",
    "sg:address":"Am Delft 30",
    "sg:city":"Emden",
    "sg:phone":"+49 4921/20525",
    "sg:postcode":"26721",
    "sg:province":"Niedersachsen",
    "wof:name":"Ernst Otto Heinrichs Rechtsanwalt Und Notar",
    "wof:placetype":"venue"
},
  "geometry": {"coordinates":[7.2048740387,53.3640136719],"type":"Point"}
}