{
  "type": "Feature",
  "properties": {
    "iso:country":"DE",
    "sg:address":"Steig 2",
    "sg:city":"Rottweil",
    "sg:phone":"+49 741/12951",
    "sg:postcode":"78628",
    "sg:province":"Baden-W\u00fcrttemberg",
    "wof:name":"Isdh - Internet Service Dienst Hamann",
    "wof:placetype":"venue"
},
  "geometry": {"coordinates":[8.6389951706,48.1559143066],"type":"Point"}
}