{
  "type": "Feature",
  "properties": {
    "iso:country":"DE",
    "sg:address":"Rabenkopfstr. 19",
    "sg:city":"M\u00fcnchen",
    "sg:postcode":"81545",
    "sg:province":"Bayern",
    "wof:name":"Brandl Immobilien Gmbh",
    "wof:placetype":"venue"
},
  "geometry": {"coordinates":[11.5487108231,48.0785331726],"type":"Point"}
}