{
  "type": "Feature",
  "properties": {
    "iso:country":"DE",
    "sg:address":"Dangstetter Str. 1",
    "sg:city":"K\u00fcssaberg",
    "sg:phone":"+49 7741/5052",
    "sg:postcode":"79790",
    "sg:province":"Baden-W\u00fcrttemberg",
    "wof:name":"Caf\u00e9 Hello",
    "wof:placetype":"venue"
},
  "geometry": {"coordinates":[8.306807,47.591942],"type":"Point"}
}