{
  "type": "Feature",
  "properties": {
    "iso:country":"DE",
    "sg:address":"N\u00fcrnberger Str. 6 a",
    "sg:city":"Hanau",
    "sg:phone":"+49 6181/256224",
    "sg:postcode":"63450",
    "sg:province":"Hessen",
    "wof:name":"Kinderkiste Wissel Gmbh",
    "wof:placetype":"venue"
},
  "geometry": {"coordinates":[8.9222669601,50.1319046021],"type":"Point"}
}