{
  "type": "Feature",
  "properties": {
    "iso:country":"DE",
    "sg:address":"Weseler Str. 51",
    "sg:city":"D\u00fclmen",
    "sg:phone":"+49 2590/4210",
    "sg:postcode":"48249",
    "sg:province":"Nordrhein-Westfalen",
    "wof:name":"Restaurant-pizzeria Zur Dorfschmiede",
    "wof:placetype":"venue"
},
  "geometry": {"coordinates":[7.3687977791,51.8649330139],"type":"Point"}
}