{
  "type": "Feature",
  "properties": {
    "iso:country":"DE",
    "sg:address":"Westerwaldstr. 37",
    "sg:city":"Hadamar",
    "sg:phone":"+49 6433/6477",
    "sg:postcode":"65589",
    "sg:province":"Hessen",
    "wof:name":"Peter Feller Rechtsanwalt",
    "wof:placetype":"venue"
},
  "geometry": {"coordinates":[8.0370340347,50.4734916687],"type":"Point"}
}