{
  "type": "Feature",
  "properties": {
    "iso:country":"DE",
    "sg:address":"Christianstr. 22",
    "sg:city":"Moers",
    "sg:phone":"+49 2841/502847",
    "sg:postcode":"47441",
    "sg:province":"Nordrhein-Westfalen",
    "wof:name":"Helmut Petrausch",
    "wof:placetype":"venue"
},
  "geometry": {"coordinates":[6.652249,51.445938],"type":"Point"}
}