{
  "type": "Feature",
  "properties": {
    "iso:country":"DE",
    "sg:address":"Hauptstr. 31",
    "sg:city":"Rohr",
    "sg:phone":"+49 8783/260",
    "sg:postcode":"93352",
    "sg:province":"Bayern",
    "wof:name":"Xaver Salleck",
    "wof:placetype":"venue"
},
  "geometry": {"coordinates":[11.9696273804,48.7696914673],"type":"Point"}
}