{
  "type": "Feature",
  "properties": {
    "iso:country":"DE",
    "sg:address":"Dresdener Str. 10",
    "sg:city":"G\u00f6rlitz",
    "sg:phone":"+49 3581/409445",
    "sg:postcode":"02826",
    "sg:province":"Sachsen",
    "wof:name":"Dgg Dach- Und Geb\u00e4ude- Sanierung Gmbh",
    "wof:placetype":"venue"
},
  "geometry": {"coordinates":[14.979747,51.15041],"type":"Point"}
}