{
  "type": "Feature",
  "properties": {
    "iso:country":"DE",
    "sg:address":"Bahnhofstr. 10",
    "sg:city":"Gelsenkirchen",
    "sg:phone":"+49 209/205136",
    "sg:postcode":"45879",
    "sg:province":"Nordrhein-Westfalen",
    "wof:name":"Jean Pascale Vertriebs Gmbh & Co.",
    "wof:placetype":"venue"
},
  "geometry": {"coordinates":[7.096067,51.509411],"type":"Point"}
}