{
  "type": "Feature",
  "properties": {
    "iso:country":"DE",
    "sg:address":"Wilhelmstr. 35",
    "sg:city":"Emsdetten",
    "sg:phone":"+49 2572/93220",
    "sg:postcode":"48282",
    "sg:province":"Nordrhein-Westfalen",
    "wof:name":"Heitjans Und Partner",
    "wof:placetype":"venue"
},
  "geometry": {"coordinates":[7.5246248245,52.1737136841],"type":"Point"}
}