{
  "type": "Feature",
  "properties": {
    "iso:country":"DE",
    "sg:address":"Eibenstocker Str. 58",
    "sg:city":"Johanngeorgenstadt",
    "sg:phone":"+49 3773/882933",
    "sg:postcode":"08349",
    "sg:province":"Sachsen",
    "wof:name":"K. Thormann",
    "wof:placetype":"venue"
},
  "geometry": {"coordinates":[12.711845,50.433487],"type":"Point"}
}