{
  "type": "Feature",
  "properties": {
    "iso:country":"DE",
    "sg:address":"Dammstr. 21",
    "sg:city":"H\u00f6hn",
    "sg:phone":"+49 2661/8798",
    "sg:postcode":"56462",
    "sg:province":"Rheinland-Pfalz",
    "wof:name":"Adolf Noah",
    "wof:placetype":"venue"
},
  "geometry": {"coordinates":[7.991911,50.614929],"type":"Point"}
}