{
  "type": "Feature",
  "properties": {
    "iso:country":"DE",
    "sg:address":"Hofer Str. 11a",
    "sg:city":"Rehau",
    "sg:phone":"+49 9283/1232",
    "sg:postcode":"95111",
    "sg:province":"Bayern",
    "wof:name":"H. Adelmann",
    "wof:placetype":"venue"
},
  "geometry": {"coordinates":[12.030206,50.251755],"type":"Point"}
}