{
  "type": "Feature",
  "properties": {
    "iso:country":"DE",
    "sg:address":"Neumarkter Strasse 34",
    "sg:city":"M\u00fcnchen",
    "sg:phone":"+49 89/32424951",
    "sg:postcode":"81673",
    "sg:province":"Bayern",
    "wof:name":"Alpengl\u00fchen .group",
    "wof:placetype":"venue"
},
  "geometry": {"coordinates":[11.6215906143,48.1324043274],"type":"Point"}
}