{
  "type": "Feature",
  "properties": {
    "iso:country":"DE",
    "sg:address":"Schillerstrasse 71 a",
    "sg:city":"Heusweiler",
    "sg:phone":"+49 6806/78707",
    "sg:postcode":"66265",
    "sg:province":"Saarland",
    "wof:name":"Nachhilfe-studio Albert Stoffer",
    "wof:placetype":"venue"
},
  "geometry": {"coordinates":[6.918862,49.334064],"type":"Point"}
}