{
  "type": "Feature",
  "properties": {
    "iso:country":"DE",
    "sg:address":"Martin-Schleyer-Str. 6 b",
    "sg:city":"Konstanz",
    "sg:phone":"+49 7531/43213",
    "sg:postcode":"78465",
    "sg:province":"Baden-W\u00fcrttemberg",
    "wof:name":"Raiffeisen Warengenossenschaft Eg",
    "wof:placetype":"venue"
},
  "geometry": {"coordinates":[9.173467,47.71225],"type":"Point"}
}