{
  "type": "Feature",
  "properties": {
    "iso:country":"DE",
    "sg:address":"Xantener Str. 15a",
    "sg:city":"Berlin",
    "sg:phone":"+49 30/8804110",
    "sg:postcode":"10707",
    "sg:province":"Berlin",
    "wof:name":"Dr. Hertling Papoli-barawati Und M. Piepenbrock",
    "wof:placetype":"venue"
},
  "geometry": {"coordinates":[13.3111829758,52.4993133545],"type":"Point"}
}