{
  "type": "Feature",
  "properties": {
    "iso:country":"DE",
    "sg:address":"H\u00f6rsterstr. 52",
    "sg:city":"M\u00fcnster",
    "sg:phone":"+49 251/54769",
    "sg:postcode":"48143",
    "sg:province":"Nordrhein-Westfalen",
    "wof:name":"Herbert Stengel",
    "wof:placetype":"venue"
},
  "geometry": {"coordinates":[7.630657196,51.9644241333],"type":"Point"}
}