{
  "type": "Feature",
  "properties": {
    "iso:country":"DE",
    "sg:address":"Alte Gasse 20",
    "sg:city":"Bad Gandersheim",
    "sg:phone":"+49 5382/2738",
    "sg:postcode":"37581",
    "sg:province":"Niedersachsen",
    "wof:name":"Erich Busack",
    "wof:placetype":"venue"
},
  "geometry": {"coordinates":[10.022476,51.870049],"type":"Point"}
}