{
  "type": "Feature",
  "properties": {
    "iso:country":"DE",
    "sg:address":"Heidenheimer Str. 48",
    "sg:city":"Berlin",
    "sg:phone":"+49 30/4048953",
    "sg:postcode":"13467",
    "sg:province":"Berlin",
    "wof:name":"Deutsche Shell Ag",
    "wof:placetype":"venue"
},
  "geometry": {"coordinates":[13.3006677628,52.6158485413],"type":"Point"}
}