{
  "type": "Feature",
  "properties": {
    "iso:country":"DE",
    "sg:address":"Rosenfelder Str. 20",
    "sg:city":"V\u00f6hringen",
    "sg:phone":"+49 7454/2612",
    "sg:postcode":"72189",
    "sg:province":"Baden-W\u00fcrttemberg",
    "wof:name":"Werner G\u00fchring",
    "wof:placetype":"venue"
},
  "geometry": {"coordinates":[8.664059639,48.3340072632],"type":"Point"}
}