{
  "type": "Feature",
  "properties": {
    "iso:country":"DE",
    "sg:address":"Am Schlauweg 2",
    "sg:city":"Niederkirchen",
    "sg:phone":"+49 6363/993084",
    "sg:postcode":"67700",
    "sg:province":"Rheinland-Pfalz",
    "wof:name":"Sonnen-apotheke",
    "wof:placetype":"venue"
},
  "geometry": {"coordinates":[7.69936,49.578499],"type":"Point"}
}