{
  "type": "Feature",
  "properties": {
    "iso:country":"DE",
    "sg:address":"Hocheckstr. 29",
    "sg:city":"Bad Feilnbach",
    "sg:phone":"+49 8066/346",
    "sg:postcode":"83075",
    "sg:province":"Bayern",
    "wof:name":"Sebastian Gasteiger",
    "wof:placetype":"venue"
},
  "geometry": {"coordinates":[11.999125,47.77383],"type":"Point"}
}