{
  "type": "Feature",
  "properties": {
    "iso:country":"DE",
    "sg:address":"M\u00fchlenstr. 16",
    "sg:city":"Hadamar",
    "sg:phone":"+49 6433/81242",
    "sg:postcode":"65589",
    "sg:province":"Hessen",
    "wof:name":"R & P Metallgestaltung Gmbh",
    "wof:placetype":"venue"
},
  "geometry": {"coordinates":[8.039045,50.431942],"type":"Point"}
}