{
  "type": "Feature",
  "properties": {
    "iso:country":"DE",
    "sg:address":"Alerdsweg 9",
    "sg:city":"Braunschweig",
    "sg:phone":"+49 531/54886",
    "sg:postcode":"38118",
    "sg:province":"Niedersachsen",
    "wof:name":"Brigitte Der Familienfriseur",
    "wof:placetype":"venue"
},
  "geometry": {"coordinates":[10.5026578903,52.2660369873],"type":"Point"}
}