{
  "type": "Feature",
  "properties": {
    "iso:country":"DE",
    "sg:address":"Niederp\u00f6bel 8b",
    "sg:city":"Schmiedeberg",
    "sg:postcode":"01762",
    "sg:province":"Sachsen",
    "wof:name":"Volkmar Schlewitz",
    "wof:placetype":"venue"
},
  "geometry": {"coordinates":[13.665983,50.823318],"type":"Point"}
}