{
  "type": "Feature",
  "properties": {
    "iso:country":"DE",
    "sg:address":"Hohe Str. 29",
    "sg:city":"Gr\u00e4fenhain",
    "sg:phone":"+49 3624/2146",
    "sg:postcode":"99887",
    "sg:province":"Th\u00fcringen",
    "wof:name":"Uwe Hermann",
    "wof:placetype":"venue"
},
  "geometry": {"coordinates":[10.6598796844,50.8311233521],"type":"Point"}
}