{
  "type": "Feature",
  "properties": {
    "iso:country":"DE",
    "sg:address":"Buchenweg 20",
    "sg:city":"Raben Steinfeld",
    "sg:phone":"+49 3860/256",
    "sg:postcode":"19065",
    "sg:province":"Mecklenburg-Vorpommern",
    "wof:name":"Dietrich Dehl",
    "wof:placetype":"venue"
},
  "geometry": {"coordinates":[11.497832,53.594158],"type":"Point"}
}