{
  "type": "Feature",
  "properties": {
    "iso:country":"DE",
    "sg:address":"Basler Str. 17",
    "sg:city":"Bad S\u00e4ckingen",
    "sg:phone":"+49 7761/50464",
    "sg:postcode":"79713",
    "sg:province":"Baden-W\u00fcrttemberg",
    "wof:name":"Raumausstattung Peter Widmann",
    "wof:placetype":"venue"
},
  "geometry": {"coordinates":[7.945471,47.553848],"type":"Point"}
}