{
  "type": "Feature",
  "properties": {
    "iso:country":"DE",
    "sg:address":"Ingolst\u00e4dter Str. 5",
    "sg:city":"Reichertshofen",
    "sg:phone":"+49 8453/9311",
    "sg:postcode":"85084",
    "sg:province":"Bayern",
    "wof:name":"Georg Link Elektroinstallation",
    "wof:placetype":"venue"
},
  "geometry": {"coordinates":[11.465424,48.657734],"type":"Point"}
}