{
  "type": "Feature",
  "properties": {
    "iso:country":"DE",
    "sg:address":"Frankenring 70",
    "sg:city":"Krefeld",
    "sg:phone":"+49 2151/774117",
    "sg:postcode":"47798",
    "sg:province":"Nordrhein-Westfalen",
    "wof:name":"Christa Maier",
    "wof:placetype":"venue"
},
  "geometry": {"coordinates":[6.5505862236,51.3274688721],"type":"Point"}
}