{
  "type": "Feature",
  "properties": {
    "iso:country":"DE",
    "sg:address":"Am Kurhaus 4",
    "sg:city":"Schmallenberg",
    "sg:phone":"+49 2974/1374",
    "sg:postcode":"57392",
    "sg:province":"Nordrhein-Westfalen",
    "wof:name":"Restaurant Potthucke",
    "wof:placetype":"venue"
},
  "geometry": {"coordinates":[8.3124647141,51.190071106],"type":"Point"}
}