{
  "type": "Feature",
  "properties": {
    "iso:country":"DE",
    "sg:address":"Kirchenweg 10",
    "sg:city":"Georgensgm\u00fcnd",
    "sg:phone":"+49 9172/901",
    "sg:postcode":"91166",
    "sg:province":"Bayern",
    "wof:name":"Kath. \u00d6ffentliche B\u00fccherei",
    "wof:placetype":"venue"
},
  "geometry": {"coordinates":[11.015311,49.185539],"type":"Point"}
}