{
  "type": "Feature",
  "properties": {
    "iso:country":"DE",
    "sg:address":"Neustr. 11 a",
    "sg:city":"Haan",
    "sg:phone":"+49 212/934045",
    "sg:postcode":"42781",
    "sg:province":"Nordrhein-Westfalen",
    "wof:name":"Hotel E. Sohn",
    "wof:placetype":"venue"
},
  "geometry": {"coordinates":[7.0044932365,51.1937484741],"type":"Point"}
}