{
  "type": "Feature",
  "properties": {
    "iso:country":"DE",
    "sg:address":"Mattenburger Str. 29",
    "sg:city":"Bad Bederkesa",
    "sg:phone":"+49 4745/321",
    "sg:postcode":"27624",
    "sg:province":"Niedersachsen",
    "wof:name":"Egon Apel",
    "wof:placetype":"venue"
},
  "geometry": {"coordinates":[8.838214,53.62595],"type":"Point"}
}