{
  "type": "Feature",
  "properties": {
    "iso:country":"DE",
    "sg:address":"Sleperhof 11",
    "sg:city":"Arnsberg",
    "sg:phone":"+49 2932/7676",
    "sg:postcode":"59757",
    "sg:province":"Nordrhein-Westfalen",
    "wof:name":"Ursula Dassel Heilpraktikerin",
    "wof:placetype":"venue"
},
  "geometry": {"coordinates":[7.9407057762,51.4572677612],"type":"Point"}
}