{
  "type": "Feature",
  "properties": {
    "iso:country":"DE",
    "sg:address":"Hochstr. 94 a",
    "sg:city":"L\u00fcdenscheid",
    "sg:phone":"+49 2351/81178",
    "sg:postcode":"58511",
    "sg:province":"Nordrhein-Westfalen",
    "wof:name":"Br\u00e4ucken-apotheke",
    "wof:placetype":"venue"
},
  "geometry": {"coordinates":[7.634054,51.213425],"type":"Point"}
}