{
  "type": "Feature",
  "properties": {
    "iso:country":"DE",
    "sg:address":"Alpenstr. 6",
    "sg:city":"Starnberg",
    "sg:phone":"+49 8151/744765",
    "sg:postcode":"82319",
    "sg:province":"Bayern",
    "wof:name":"Annabelle H\u00f6ppel",
    "wof:placetype":"venue"
},
  "geometry": {"coordinates":[11.3189668655,47.9999656677],"type":"Point"}
}