{
  "type": "Feature",
  "properties": {
    "iso:country":"DE",
    "sg:address":"Schulweg 40",
    "sg:city":"Freiberg",
    "sg:phone":"+49 3731/248093",
    "sg:postcode":"09599",
    "sg:province":"Sachsen",
    "wof:name":"Rainer G\u00f6pfert",
    "wof:placetype":"venue"
},
  "geometry": {"coordinates":[13.3309230804,50.9284057617],"type":"Point"}
}