{
  "type": "Feature",
  "properties": {
    "iso:country":"DE",
    "sg:address":"Sie\u00dfweg 17",
    "sg:city":"Hohenstein",
    "sg:phone":"+49 7383/94950",
    "sg:postcode":"72531",
    "sg:province":"Baden-W\u00fcrttemberg",
    "wof:name":"Knupfer Metall- Verarbeitung Gmbh",
    "wof:placetype":"venue"
},
  "geometry": {"coordinates":[9.4235897064,48.3512992859],"type":"Point"}
}