{
  "type": "Feature",
  "properties": {
    "iso:country":"DE",
    "sg:address":"T\u00fcrkenstr. 48",
    "sg:city":"M\u00fcnchen",
    "sg:phone":"+49 89/283267",
    "sg:postcode":"80799",
    "sg:province":"Bayern",
    "wof:name":"Frank Zangl & Co. Antiquit\u00e4ten Gmbh",
    "wof:placetype":"venue"
},
  "geometry": {"coordinates":[11.5753650665,48.1490135193],"type":"Point"}
}