{
  "type": "Feature",
  "properties": {
    "iso:country":"DE",
    "sg:address":"Kissinger Str. 5",
    "sg:city":"N\u00fcdlingen",
    "sg:phone":"+49 971/4201",
    "sg:postcode":"97720",
    "sg:province":"Bayern",
    "wof:name":"Hugo D\u00fcring Inh. Isolde D\u00fcring",
    "wof:placetype":"venue"
},
  "geometry": {"coordinates":[10.1234416962,50.2209205627],"type":"Point"}
}