{
  "type": "Feature",
  "properties": {
    "iso:country":"DE",
    "sg:address":"Hauptstr. 41",
    "sg:city":"Syke",
    "sg:phone":"+49 4242/933962",
    "sg:postcode":"28857",
    "sg:province":"Niedersachsen",
    "wof:name":"Gross Pelze",
    "wof:placetype":"venue"
},
  "geometry": {"coordinates":[8.819579,52.914391],"type":"Point"}
}