{
  "type": "Feature",
  "properties": {
    "iso:country":"DE",
    "sg:address":"An der Autobahn 48-50",
    "sg:city":"Oyten",
    "sg:phone":"+49 4207/91540",
    "sg:postcode":"28876",
    "sg:province":"Niedersachsen",
    "wof:name":"Otto Knechtel M\u00f6bel-collektion Gmbh",
    "wof:placetype":"venue"
},
  "geometry": {"coordinates":[9.048915863,53.058681488],"type":"Point"}
}