{
  "type": "Feature",
  "properties": {
    "iso:country":"DE",
    "sg:address":"B\u00fcchlerhausen 3-7",
    "sg:city":"Engelskirchen",
    "sg:phone":"+49 2263/7170",
    "sg:postcode":"51766",
    "sg:province":"Nordrhein-Westfalen",
    "wof:name":"Steeger Baustoffe Gmbh",
    "wof:placetype":"venue"
},
  "geometry": {"coordinates":[7.451031,50.985733],"type":"Point"}
}