{
  "type": "Feature",
  "properties": {
    "iso:country":"DE",
    "sg:address":"Ostra-Allee",
    "sg:city":"Dresden",
    "sg:postcode":"01067",
    "sg:province":"Sachsen",
    "wof:name":"Verwaltungsges. Dresdner Druck- Und Verlagshaus Mbh",
    "wof:placetype":"venue"
},
  "geometry": {"coordinates":[13.728764534,51.0562438965],"type":"Point"}
}