{
  "type": "Feature",
  "properties": {
    "iso:country":"DE",
    "sg:address":"Kaiserstr. 35",
    "sg:city":"Hameln",
    "sg:phone":"+49 5151/41180",
    "sg:postcode":"31785",
    "sg:province":"Niedersachsen",
    "wof:name":"Helal Lokma Gmbh",
    "wof:placetype":"venue"
},
  "geometry": {"coordinates":[9.3681144714,52.1006774902],"type":"Point"}
}