{
  "type": "Feature",
  "properties": {
    "iso:country":"DE",
    "sg:address":"Weiherweg 6",
    "sg:city":"Sargenroth",
    "sg:phone":"+49 6761/4599",
    "sg:postcode":"55471",
    "sg:province":"Rheinland-Pfalz",
    "wof:name":"H. Maurer",
    "wof:placetype":"venue"
},
  "geometry": {"coordinates":[7.5111880302,49.9291915894],"type":"Point"}
}