{
  "type": "Feature",
  "properties": {
    "iso:country":"DE",
    "sg:address":"Hauptstr. 45",
    "sg:city":"Esterwegen",
    "sg:phone":"+49 5955/427",
    "sg:postcode":"26897",
    "sg:province":"Niedersachsen",
    "wof:name":"Imbiss",
    "wof:placetype":"venue"
},
  "geometry": {"coordinates":[7.6312918663,52.9946517944],"type":"Point"}
}