{
  "type": "Feature",
  "properties": {
    "iso:country":"DE",
    "sg:address":"Brahmsstrasse 61",
    "sg:city":"Wilhelmshaven",
    "sg:phone":"+49 4421/500785",
    "sg:postcode":"26386",
    "sg:province":"Niedersachsen",
    "wof:name":"Perschis Mp3-server",
    "wof:placetype":"venue"
},
  "geometry": {"coordinates":[8.100211,53.552219],"type":"Point"}
}