{
  "type": "Feature",
  "properties": {
    "iso:country":"DE",
    "sg:address":"Abts\u00e4ckerstr. 46",
    "sg:city":"Weinsberg",
    "sg:phone":"+49 7134/14447",
    "sg:postcode":"74189",
    "sg:province":"Baden-W\u00fcrttemberg",
    "wof:name":"Alfred G\u00f6tze Gmbh",
    "wof:placetype":"venue"
},
  "geometry": {"coordinates":[9.3015880585,49.1530570984],"type":"Point"}
}