{
  "type": "Feature",
  "properties": {
    "iso:country":"DE",
    "sg:address":"Ausblick 114",
    "sg:city":"Wuppertal",
    "sg:phone":"+49 202/722420",
    "sg:postcode":"42113",
    "sg:province":"Nordrhein-Westfalen",
    "wof:name":"Heinrich Gr\u00fcnendahl",
    "wof:placetype":"venue"
},
  "geometry": {"coordinates":[7.109012,51.280472],"type":"Point"}
}