{
  "type": "Feature",
  "properties": {
    "iso:country":"DE",
    "sg:address":"Am M\u00fchlberg 7",
    "sg:city":"Reinheim",
    "sg:phone":"+49 6162/1839",
    "sg:postcode":"64354",
    "sg:province":"Hessen",
    "wof:name":"Richard Meyer",
    "wof:placetype":"venue"
},
  "geometry": {"coordinates":[8.826762,49.82695],"type":"Point"}
}