{
  "type": "Feature",
  "properties": {
    "iso:country":"DE",
    "sg:address":"Eichenstr. 23",
    "sg:city":"Oberursel",
    "sg:phone":"+49 6171/72016",
    "sg:postcode":"61440",
    "sg:province":"Hessen",
    "wof:name":"Marion Lyner Rechtsanw\u00e4ltin",
    "wof:placetype":"venue"
},
  "geometry": {"coordinates":[8.5749759674,50.1879425049],"type":"Point"}
}