{
  "type": "Feature",
  "properties": {
    "iso:country":"DE",
    "sg:address":"Niederfeldstr 38",
    "sg:city":"Neufahrn",
    "sg:phone":"+49 7171/67018",
    "sg:postcode":"84088",
    "sg:province":"Bayern",
    "wof:name":"Colortechnics Gmbh",
    "wof:placetype":"venue"
},
  "geometry": {"coordinates":[9.789394,48.794392],"type":"Point"}
}