{
  "type": "Feature",
  "properties": {
    "iso:country":"DE",
    "sg:address":"Friedensstr. 59",
    "sg:city":"Sankt Augustin",
    "sg:phone":"+49 2241/206669",
    "sg:postcode":"53757",
    "sg:province":"Nordrhein-Westfalen",
    "wof:name":"Ulrike Garbers Rechtsanw\u00e4ltin",
    "wof:placetype":"venue"
},
  "geometry": {"coordinates":[7.1901950836,50.7737808228],"type":"Point"}
}