{
  "type": "Feature",
  "properties": {
    "iso:country":"DE",
    "sg:address":"Robert-Koch-Str. 3",
    "sg:city":"Pulsnitz",
    "sg:phone":"+49 35955/45056",
    "sg:postcode":"01896",
    "sg:province":"Sachsen",
    "wof:name":"Robert-koch-apotheke Inh. Ines H\u00f6rnig",
    "wof:placetype":"venue"
},
  "geometry": {"coordinates":[14.01007,51.181725],"type":"Point"}
}