{
  "type": "Feature",
  "properties": {
    "iso:country":"DE",
    "sg:city":"B\u00f6nen",
    "sg:postcode":"59199",
    "sg:province":"Nordrhein-Westfalen",
    "wof:name":"K & L Handelsgesellschaft Verwaltungs Gmbh",
    "wof:placetype":"venue"
},
  "geometry": {"coordinates":[7.757875,51.598579],"type":"Point"}
}