{
  "type": "Feature",
  "properties": {
    "iso:country":"DE",
    "sg:address":"Stuttgarter Str. 24a",
    "sg:city":"Br\u00fchl",
    "sg:phone":"+49 6202/78736",
    "sg:postcode":"68782",
    "sg:province":"Baden-W\u00fcrttemberg",
    "wof:name":"Prof. Dr. Hartmut D\u00f6ringer Margarete D\u00f6ringer",
    "wof:placetype":"venue"
},
  "geometry": {"coordinates":[8.5323705673,49.4021339417],"type":"Point"}
}