{
  "type": "Feature",
  "properties": {
    "iso:country":"DE",
    "sg:address":"Laustergasse 2",
    "sg:city":"Neustadt",
    "sg:phone":"+49 6321/480179",
    "sg:postcode":"67433",
    "sg:province":"Rheinland-Pfalz",
    "wof:name":"Vitamingarten",
    "wof:placetype":"venue"
},
  "geometry": {"coordinates":[8.1381483078,49.3527297974],"type":"Point"}
}