{
  "type": "Feature",
  "properties": {
    "iso:country":"DE",
    "sg:address":"An der Salzstr. 13",
    "sg:city":"Gera",
    "sg:postcode":"07551",
    "sg:province":"Th\u00fcringen",
    "wof:name":"Pro-life-warenhandels Gmbh",
    "wof:placetype":"venue"
},
  "geometry": {"coordinates":[12.079242,50.837505],"type":"Point"}
}