{
  "type": "Feature",
  "properties": {
    "iso:country":"DE",
    "sg:address":"Poststr 5",
    "sg:city":"Altenburg",
    "sg:phone":"+49 33393/324",
    "sg:postcode":"04600",
    "sg:province":"Th\u00fcringen",
    "wof:name":"K. Hentschke",
    "wof:placetype":"venue"
},
  "geometry": {"coordinates":[13.4726142883,52.7550354004],"type":"Point"}
}