{
  "type": "Feature",
  "properties": {
    "iso:country":"DE",
    "sg:address":"Dorfstr. 13",
    "sg:city":"Schwaberow",
    "sg:phone":"+49 38856/30522",
    "sg:postcode":"19230",
    "sg:province":"Mecklenburg-Vorpommern",
    "wof:name":"Sota Gmbh",
    "wof:placetype":"venue"
},
  "geometry": {"coordinates":[11.190071,53.431274],"type":"Point"}
}