{
  "type": "Feature",
  "properties": {
    "iso:country":"DE",
    "sg:address":"Riedweg 1",
    "sg:city":"Krauchenwies",
    "sg:phone":"+49 7576/1215",
    "sg:postcode":"72505",
    "sg:province":"Baden-W\u00fcrttemberg",
    "wof:name":"K.-h. Strobel",
    "wof:placetype":"venue"
},
  "geometry": {"coordinates":[9.2530899048,47.9903182983],"type":"Point"}
}