{
  "type": "Feature",
  "properties": {
    "iso:country":"DE",
    "sg:address":"Kienhorststr. 165",
    "sg:city":"Berlin",
    "sg:phone":"+49 30/4121903",
    "sg:postcode":"13403",
    "sg:province":"Berlin",
    "wof:name":"Gastst\u00e4tte Bierhaus",
    "wof:placetype":"venue"
},
  "geometry": {"coordinates":[13.3129673004,52.5748062134],"type":"Point"}
}