{
  "type": "Feature",
  "properties": {
    "iso:country":"DE",
    "sg:address":"Otto-Lilienthal-Str. 36",
    "sg:city":"B\u00f6blingen",
    "sg:phone":"+49 7031/714850",
    "sg:postcode":"71034",
    "sg:province":"Baden-W\u00fcrttemberg",
    "wof:name":"Xybernaut Gmbh",
    "wof:placetype":"venue"
},
  "geometry": {"coordinates":[8.9743671417,48.6819114685],"type":"Point"}
}