{
  "type": "Feature",
  "properties": {
    "iso:country":"DE",
    "sg:address":"Bendestorfer Ring 2",
    "sg:city":"Hamburg",
    "sg:postcode":"21079",
    "sg:province":"Hamburg",
    "wof:name":"Diner Grundst\u00fccksverwaltungs- Gesellschaft Mbh",
    "wof:placetype":"venue"
},
  "geometry": {"coordinates":[9.98772,53.431129],"type":"Point"}
}