{
  "type": "Feature",
  "properties": {
    "iso:country":"DE",
    "sg:address":"Unter Gereuth 11",
    "sg:city":"Bahlingen",
    "sg:phone":"+49 7663/948000",
    "sg:postcode":"79353",
    "sg:province":"Baden-W\u00fcrttemberg",
    "wof:name":"Otto M\u00e4nner Heisskanalsysteme Gmbh & Co Kg",
    "wof:placetype":"venue"
},
  "geometry": {"coordinates":[7.7381701469,48.1217803955],"type":"Point"}
}