{
  "type": "Feature",
  "properties": {
    "iso:country":"DE",
    "sg:address":"Gartenstr. 53",
    "sg:city":"Kitzingen",
    "sg:phone":"+49 9321/31872",
    "sg:postcode":"97318",
    "sg:province":"Bayern",
    "wof:name":"Karl Lang",
    "wof:placetype":"venue"
},
  "geometry": {"coordinates":[10.17306,49.740959],"type":"Point"}
}