{
  "type": "Feature",
  "properties": {
    "iso:country":"DE",
    "sg:address":"Celler Str. 74",
    "sg:city":"Winsen",
    "sg:phone":"+49 5143/98830",
    "sg:postcode":"29308",
    "sg:province":"Niedersachsen",
    "wof:name":"Greve Grundbau Gmbh",
    "wof:placetype":"venue"
},
  "geometry": {"coordinates":[9.909167,52.680019],"type":"Point"}
}