{
  "type": "Feature",
  "properties": {
    "iso:country":"DE",
    "sg:address":"78603",
    "sg:city":"Renquishausen",
    "sg:postcode":"78603",
    "sg:province":"Baden-W\u00fcrttemberg",
    "wof:name":"Kath. Pfarramt St. Stephanus",
    "wof:placetype":"venue"
},
  "geometry": {"coordinates":[8.8940258026,48.0833015442],"type":"Point"}
}