{
  "type": "Feature",
  "properties": {
    "iso:country":"DE",
    "sg:address":"Westerweg 15",
    "sg:city":"Struckum",
    "sg:phone":"+49 4671/930395",
    "sg:postcode":"25821",
    "sg:province":"Schleswig-Holstein",
    "wof:name":"Norberg Hansen",
    "wof:placetype":"venue"
},
  "geometry": {"coordinates":[8.9946947098,54.5853652954],"type":"Point"}
}