{
  "type": "Feature",
  "properties": {
    "iso:country":"DE",
    "sg:address":"Kammerlsperg 14",
    "sg:city":"Wiesenfelden",
    "sg:postcode":"94344",
    "sg:province":"Bayern",
    "wof:name":"Miga Gmbh",
    "wof:placetype":"venue"
},
  "geometry": {"coordinates":[12.577991,49.078995],"type":"Point"}
}