{
  "type": "Feature",
  "properties": {
    "iso:country":"DE",
    "sg:address":"Wittekindstr. 2",
    "sg:city":"Wildeshausen",
    "sg:phone":"+49 4431/1744",
    "sg:postcode":"27793",
    "sg:province":"Niedersachsen",
    "wof:name":"Dampfkornbranntweinbrennerei- Museum",
    "wof:placetype":"venue"
},
  "geometry": {"coordinates":[8.439655,52.897163],"type":"Point"}
}