{
  "type": "Feature",
  "properties": {
    "iso:country":"DE",
    "sg:address":"Pater-Hartmann-Str. 8",
    "sg:city":"Marktoberdorf",
    "sg:phone":"+49 8342/1648",
    "sg:postcode":"87616",
    "sg:province":"Bayern",
    "wof:name":"G. B\u00e4ckenbauer Holzbildhauer",
    "wof:placetype":"venue"
},
  "geometry": {"coordinates":[10.617294,47.765163],"type":"Point"}
}