{
  "type": "Feature",
  "properties": {
    "iso:country":"DE",
    "sg:address":"Heinrich-Heine-Str. 11",
    "sg:city":"Ummendorf",
    "sg:phone":"+49 7351/24295",
    "sg:postcode":"88444",
    "sg:province":"Baden-W\u00fcrttemberg",
    "wof:name":"Friedrich H\u00f6rnle",
    "wof:placetype":"venue"
},
  "geometry": {"coordinates":[9.828073,48.064671],"type":"Point"}
}