{
  "type": "Feature",
  "properties": {
    "iso:country":"DE",
    "sg:address":"Schneeberger Str. 7",
    "sg:city":"Stollberg",
    "sg:phone":"+49 37296/2478",
    "sg:postcode":"09366",
    "sg:province":"Sachsen",
    "wof:name":"Paul Scheunert & Sohn",
    "wof:placetype":"venue"
},
  "geometry": {"coordinates":[12.7759475708,50.7044754028],"type":"Point"}
}