{
  "type": "Feature",
  "properties": {
    "iso:country":"DE",
    "sg:address":"Franz-Lenders-Str. 30",
    "sg:city":"Frechen",
    "sg:phone":"+49 2234/691033",
    "sg:postcode":"50226",
    "sg:province":"Nordrhein-Westfalen",
    "wof:name":"G\u00fcnter Noll",
    "wof:placetype":"venue"
},
  "geometry": {"coordinates":[6.765316,50.940464],"type":"Point"}
}