{
  "type": "Feature",
  "properties": {
    "iso:country":"DE",
    "sg:address":"Erwin-Rommel-Str. 1",
    "sg:city":"Erlangen",
    "sg:phone":"+49 9131/851",
    "sg:postcode":"91058",
    "sg:province":"Bayern",
    "wof:name":"Bibliothek Der Physikal. Institute",
    "wof:placetype":"venue"
},
  "geometry": {"coordinates":[11.027231,49.581535],"type":"Point"}
}