{
  "type": "Feature",
  "properties": {
    "iso:country":"DE",
    "sg:address":"Schongauer Str. 7",
    "sg:city":"Marktoberdorf",
    "sg:phone":"+49 8342/5259",
    "sg:postcode":"87616",
    "sg:province":"Bayern",
    "wof:name":"Franz Heiland B\u00e4ckerei",
    "wof:placetype":"venue"
},
  "geometry": {"coordinates":[10.66185,47.78516],"type":"Point"}
}