{
  "type": "Feature",
  "properties": {
    "iso:country":"DE",
    "sg:address":"Am Schwimmbad",
    "sg:city":"Illingen",
    "sg:phone":"+49 6825/2518",
    "sg:postcode":"66557",
    "sg:province":"Saarland",
    "wof:name":"Schwimmbad",
    "wof:placetype":"venue"
},
  "geometry": {"coordinates":[7.0175428391,49.3842849731],"type":"Point"}
}