{
  "type": "Feature",
  "properties": {
    "iso:country":"DE",
    "sg:address":"Gewerbehof 25",
    "sg:city":"Bopfingen",
    "sg:phone":"+49 4973/6296110",
    "sg:postcode":"73441",
    "sg:province":"Baden-W\u00fcrttemberg",
    "wof:name":"Air Liquide Gmbh",
    "wof:placetype":"venue"
},
  "geometry": {"coordinates":[10.375836,48.850021],"type":"Point"}
}