{
  "type": "Feature",
  "properties": {
    "iso:country":"DE",
    "sg:address":"Biberacher Str. 12-1",
    "sg:city":"Ochsenhausen",
    "sg:phone":"+49 7352/8703",
    "sg:postcode":"88416",
    "sg:province":"Baden-W\u00fcrttemberg",
    "wof:name":"Wilhelm Liebhardt",
    "wof:placetype":"venue"
},
  "geometry": {"coordinates":[9.94793,48.072491],"type":"Point"}
}