{
  "type": "Feature",
  "properties": {
    "iso:country":"DE",
    "sg:address":"Kolkwitzer Str. 66 a",
    "sg:city":"Cottbus",
    "sg:phone":"+49 355/24008",
    "sg:postcode":"03046",
    "sg:province":"Brandenburg",
    "wof:name":"Elf Sb Station",
    "wof:placetype":"venue"
},
  "geometry": {"coordinates":[14.2971744537,51.7531967163],"type":"Point"}
}