{
  "type": "Feature",
  "properties": {
    "iso:country":"DE",
    "sg:address":"Am Berg 32",
    "sg:city":"M\u00f6rfelden-Walldorf",
    "sg:phone":"+49 6105/23081",
    "sg:postcode":"64546",
    "sg:province":"Hessen",
    "wof:name":"H. T. S. Haustechnik Service Gmbh & Co. Kg",
    "wof:placetype":"venue"
},
  "geometry": {"coordinates":[8.5642976761,49.9674530029],"type":"Point"}
}