{
  "type": "Feature",
  "properties": {
    "iso:country":"DE",
    "sg:address":"Gie\u00dfener Landstr. 14",
    "sg:city":"Lohra",
    "sg:phone":"+49 6426/6075",
    "sg:postcode":"35102",
    "sg:province":"Hessen",
    "wof:name":"Caf\u00e9 Kaktus Inh. Fam. Gro\u00df",
    "wof:placetype":"venue"
},
  "geometry": {"coordinates":[8.60722,50.686035],"type":"Point"}
}