{
  "type": "Feature",
  "properties": {
    "iso:country":"DE",
    "sg:address":"Kronacher Str. 94",
    "sg:city":"Bamberg",
    "sg:phone":"+49 951/420413",
    "sg:postcode":"96052",
    "sg:province":"Bayern",
    "wof:name":"B. Winterling",
    "wof:placetype":"venue"
},
  "geometry": {"coordinates":[10.902568,49.922546],"type":"Point"}
}