{
  "type": "Feature",
  "properties": {
    "iso:country":"DE",
    "sg:address":"Zum T\u00f6pferberg",
    "sg:city":"Schafstedt",
    "sg:phone":"+49 4805/227",
    "sg:postcode":"25725",
    "sg:province":"Schleswig-Holstein",
    "wof:name":"Sylvia Hesse",
    "wof:placetype":"venue"
},
  "geometry": {"coordinates":[9.3165798187,54.0929336548],"type":"Point"}
}