{
  "type": "Feature",
  "properties": {
    "iso:country":"DE",
    "sg:address":"Friedensstr. 38",
    "sg:city":"Hanau",
    "sg:phone":"+49 6181/28211",
    "sg:postcode":"63454",
    "sg:province":"Hessen",
    "wof:name":"Karl-robert Pfaff Architekt",
    "wof:placetype":"venue"
},
  "geometry": {"coordinates":[8.890638,50.136257],"type":"Point"}
}