{
  "type": "Feature",
  "properties": {
    "iso:country":"DE",
    "sg:address":"Bocholter Str. 2",
    "sg:city":"Hamminkeln",
    "sg:phone":"+49 2852/72907",
    "sg:postcode":"46499",
    "sg:province":"Nordrhein-Westfalen",
    "wof:name":"R. Winkelkmann",
    "wof:placetype":"venue"
},
  "geometry": {"coordinates":[6.6122040749,51.7774658203],"type":"Point"}
}