{
  "type": "Feature",
  "properties": {
    "iso:country":"DE",
    "sg:address":"Philipp-Reis-Str. 16",
    "sg:city":"M\u00fchlheim",
    "sg:phone":"+49 4961/087070",
    "sg:postcode":"63165",
    "sg:province":"Hessen",
    "wof:name":"Dienes Apparatebau Gmbh",
    "wof:placetype":"venue"
},
  "geometry": {"coordinates":[8.847658,50.114693],"type":"Point"}
}