{
  "type": "Feature",
  "properties": {
    "iso:country":"DE",
    "sg:address":"Hauptstr. 157",
    "sg:city":"Kappelrodeck",
    "sg:phone":"+49 7842/2208",
    "sg:postcode":"77876",
    "sg:province":"Baden-W\u00fcrttemberg",
    "wof:name":"Oskar Benz",
    "wof:placetype":"venue"
},
  "geometry": {"coordinates":[8.1228876114,48.5873146057],"type":"Point"}
}