{
  "type": "Feature",
  "properties": {
    "iso:country":"DE",
    "sg:address":"Wilhelmshof 5 a",
    "sg:city":"Warin",
    "sg:phone":"+49 38482/60275",
    "sg:postcode":"19417",
    "sg:province":"Mecklenburg-Vorpommern",
    "wof:name":"Leon Baugesellschaft Mbh",
    "wof:placetype":"venue"
},
  "geometry": {"coordinates":[11.733338356,53.8040275574],"type":"Point"}
}