{
  "type": "Feature",
  "properties": {
    "iso:country":"DE",
    "sg:address":"Volmestr. 4",
    "sg:city":"Meinerzhagen",
    "sg:phone":"+49 2354/92550",
    "sg:postcode":"58540",
    "sg:province":"Nordrhein-Westfalen",
    "wof:name":"Meinerzhagener Bau Gmbh",
    "wof:placetype":"venue"
},
  "geometry": {"coordinates":[7.6390352249,51.1076545715],"type":"Point"}
}