{
  "type": "Feature",
  "properties": {
    "iso:country":"DE",
    "sg:address":"Rinkensplatz 2 a",
    "sg:city":"Eschweiler",
    "sg:phone":"+49 2403/34345",
    "sg:postcode":"52249",
    "sg:province":"Nordrhein-Westfalen",
    "wof:name":"G\u00fcnter Wirtz",
    "wof:placetype":"venue"
},
  "geometry": {"coordinates":[6.2379550934,50.8227119446],"type":"Point"}
}