{
  "type": "Feature",
  "properties": {
    "iso:country":"DE",
    "sg:address":"Kom\u00f6dienstr. 41",
    "sg:city":"K\u00f6ln",
    "sg:phone":"+49 221/202010",
    "sg:postcode":"50667",
    "sg:province":"Nordrhein-Westfalen",
    "wof:name":"Reiseb\u00fcro H. Kreuzner Gmbh",
    "wof:placetype":"venue"
},
  "geometry": {"coordinates":[6.9541869164,50.9415397644],"type":"Point"}
}