{
  "type": "Feature",
  "properties": {
    "iso:country":"DE",
    "sg:address":"B\u00fcrgermeister-Seidl-Strasse 6",
    "sg:city":"Wolfratshausen",
    "sg:phone":"+49 8171",
    "sg:postcode":"82515",
    "sg:province":"Bayern",
    "wof:name":"Lorenz & Rankl Fahrzeugbau Gmbh Wolfratshausen",
    "wof:placetype":"venue"
},
  "geometry": {"coordinates":[11.4234361649,47.9040756226],"type":"Point"}
}