{
  "type": "Feature",
  "properties": {
    "iso:country":"DE",
    "sg:address":"Dingelst\u00e4dter Str. 39",
    "sg:city":"Berlin",
    "sg:phone":"+49 30/9867956",
    "sg:postcode":"13053",
    "sg:province":"Berlin",
    "wof:name":"Dieter Mauer",
    "wof:placetype":"venue"
},
  "geometry": {"coordinates":[13.519955,52.53899],"type":"Point"}
}