{
  "type": "Feature",
  "properties": {
    "iso:country":"DE",
    "sg:address":"Alte Dorfstr. 32",
    "sg:city":"Nerchau",
    "sg:phone":"+49 34382/42507",
    "sg:postcode":"04685",
    "sg:province":"Sachsen",
    "wof:name":"Albrecht & Mente Gbr",
    "wof:placetype":"venue"
},
  "geometry": {"coordinates":[12.833079,51.271698],"type":"Point"}
}