{
  "type": "Feature",
  "properties": {
    "iso:country":"DE",
    "sg:address":"Geestem\u00fcnder Str. 16",
    "sg:city":"Bremen",
    "sg:phone":"+49 421/391224",
    "sg:postcode":"28219",
    "sg:province":"Bremen",
    "wof:name":"Ingrid Behre",
    "wof:placetype":"venue"
},
  "geometry": {"coordinates":[8.7854623795,53.0999565125],"type":"Point"}
}