{
  "type": "Feature",
  "properties": {
    "iso:country":"DE",
    "sg:address":"Georg-Hennch-Str. 13",
    "sg:city":"N\u00fcrnberg",
    "sg:phone":"+49 911/3263415",
    "sg:postcode":"90431",
    "sg:province":"Bayern",
    "wof:name":"P. Sanndorf",
    "wof:placetype":"venue"
},
  "geometry": {"coordinates":[11.038274765,49.4535331726],"type":"Point"}
}