{
  "type": "Feature",
  "properties": {
    "iso:country":"DE",
    "sg:address":"Pfarrstr. 3",
    "sg:city":"Dietzh\u00f6lztal",
    "sg:phone":"+49 2774/2332",
    "sg:postcode":"35716",
    "sg:province":"Hessen",
    "wof:name":"Ev. Pfarramt Ewersbach",
    "wof:placetype":"venue"
},
  "geometry": {"coordinates":[8.3078279495,50.8306465149],"type":"Point"}
}