{
  "type": "Feature",
  "properties": {
    "iso:country":"DE",
    "sg:address":"Lorenz-Huber-Str. 16",
    "sg:city":"Haar",
    "sg:phone":"+49 89/4306460",
    "sg:postcode":"85540",
    "sg:province":"Bayern",
    "wof:name":"E. Freiherr Von Pechmann Architekt",
    "wof:placetype":"venue"
},
  "geometry": {"coordinates":[11.709182,48.119965],"type":"Point"}
}