{
  "type": "Feature",
  "properties": {
    "iso:country":"DE",
    "sg:address":"Limesstr. 14 a",
    "sg:city":"W\u00f6rth",
    "sg:postcode":"63939",
    "sg:province":"Bayern",
    "wof:name":"Interservis-holdex",
    "wof:placetype":"venue"
},
  "geometry": {"coordinates":[9.158312,49.789524],"type":"Point"}
}