{
  "type": "Feature",
  "properties": {
    "iso:country":"DE",
    "sg:address":"An der Diemel 21",
    "sg:city":"Marsberg",
    "sg:phone":"+49 2994/240",
    "sg:postcode":"34431",
    "sg:province":"Nordrhein-Westfalen",
    "wof:name":"Heinrich Garbes Westheim",
    "wof:placetype":"venue"
},
  "geometry": {"coordinates":[8.9262428284,51.4953994751],"type":"Point"}
}