{
  "type": "Feature",
  "properties": {
    "iso:country":"DE",
    "sg:address":"Faule Str. 9",
    "sg:city":"Rostock",
    "sg:phone":"+49 381/4900886",
    "sg:postcode":"18055",
    "sg:province":"Mecklenburg-Vorpommern",
    "wof:name":"Clemens Thiele",
    "wof:placetype":"venue"
},
  "geometry": {"coordinates":[12.145451,54.091885],"type":"Point"}
}