{
  "type": "Feature",
  "properties": {
    "iso:country":"DE",
    "sg:address":"Hechinger Str. 22",
    "sg:city":"Rangendingen",
    "sg:phone":"+49 7471/8420",
    "sg:postcode":"72414",
    "sg:province":"Baden-W\u00fcrttemberg",
    "wof:name":"Egon Becker",
    "wof:placetype":"venue"
},
  "geometry": {"coordinates":[8.8890619278,48.3811340332],"type":"Point"}
}