{
  "type": "Feature",
  "properties": {
    "iso:country":"DE",
    "sg:address":"Grenzh\u00f6fer Weg 31",
    "sg:city":"Heidelberg",
    "sg:phone":"+49 6221/833274",
    "sg:postcode":"69123",
    "sg:province":"Baden-W\u00fcrttemberg",
    "wof:name":"Blue M\u00f6bel Handelsges. Mbh",
    "wof:placetype":"venue"
},
  "geometry": {"coordinates":[8.639938,49.424644],"type":"Point"}
}