{
  "type": "Feature",
  "properties": {
    "iso:country":"DE",
    "sg:address":"Brunhildenstr. 9",
    "sg:city":"M\u00fcnchen",
    "sg:phone":"+49 89/172509",
    "sg:postcode":"80639",
    "sg:province":"Bayern",
    "wof:name":"Las-cad Gmbh",
    "wof:placetype":"venue"
},
  "geometry": {"coordinates":[11.5014333725,48.1533241272],"type":"Point"}
}