{
  "type": "Feature",
  "properties": {
    "iso:country":"DE",
    "sg:address":"Jaczostr. 58",
    "sg:city":"Berlin",
    "sg:phone":"+49 30/3615693",
    "sg:postcode":"13595",
    "sg:province":"Berlin",
    "wof:name":"Joachim Kluwe",
    "wof:placetype":"venue"
},
  "geometry": {"coordinates":[13.185208,52.511288],"type":"Point"}
}