{
  "type": "Feature",
  "properties": {
    "iso:country":"DE",
    "sg:address":"Neulehenstr. 8",
    "sg:city":"Halle",
    "sg:phone":"+49 5201/1850",
    "sg:postcode":"33790",
    "sg:province":"Nordrhein-Westfalen",
    "wof:name":"Gerry Weber Management Und Event Gmbh",
    "wof:placetype":"venue"
},
  "geometry": {"coordinates":[8.3736562729,52.047958374],"type":"Point"}
}