{
  "type": "Feature",
  "properties": {
    "iso:country":"DE",
    "sg:address":"Flebbestr. 18",
    "sg:city":"Hannover",
    "sg:phone":"+49 511/835699",
    "sg:postcode":"30519",
    "sg:province":"Niedersachsen",
    "wof:name":"Klaus-peter Reichert Architekt",
    "wof:placetype":"venue"
},
  "geometry": {"coordinates":[9.77016,52.332726],"type":"Point"}
}