{
  "type": "Feature",
  "properties": {
    "iso:country":"DE",
    "sg:address":"Marktplatz 5",
    "sg:city":"Dingolfing",
    "sg:phone":"+49 8731/8172",
    "sg:postcode":"84130",
    "sg:province":"Bayern",
    "wof:name":"Zeltverleih Bachmeier",
    "wof:placetype":"venue"
},
  "geometry": {"coordinates":[12.456826,48.62149],"type":"Point"}
}