{
  "type": "Feature",
  "properties": {
    "iso:country":"DE",
    "sg:address":"L\u00fcttwisch 3",
    "sg:city":"Hamburg",
    "sg:postcode":"22523",
    "sg:province":"Hamburg",
    "wof:name":"Export Gross- Und Baustoffhandel",
    "wof:placetype":"venue"
},
  "geometry": {"coordinates":[9.9035835266,53.6026306152],"type":"Point"}
}