{
  "type": "Feature",
  "properties": {
    "iso:country":"DE",
    "sg:address":"J\u00e4ckstrasse 4",
    "sg:city":"Bamberg",
    "sg:phone":"+49 951/2084301",
    "sg:postcode":"96052",
    "sg:province":"Bayern",
    "wof:name":"Fazit Intervision",
    "wof:placetype":"venue"
},
  "geometry": {"coordinates":[10.8859596252,49.9020462036],"type":"Point"}
}