{
  "type": "Feature",
  "properties": {
    "iso:country":"DE",
    "sg:address":"Dorfstr. 1",
    "sg:city":"Warrenzin",
    "sg:phone":"+49 3998/27550",
    "sg:postcode":"17111",
    "sg:province":"Mecklenburg-Vorpommern",
    "wof:name":"Wolkower Milchhof Kussmann Kg",
    "wof:placetype":"venue"
},
  "geometry": {"coordinates":[12.948174,53.905582],"type":"Point"}
}