{
  "type": "Feature",
  "properties": {
    "iso:country":"DE",
    "sg:address":"Karl-Marx-Str. 79",
    "sg:city":"Friedland",
    "sg:postcode":"15848",
    "sg:province":"Brandenburg",
    "wof:name":"Gemeindeschwesterstation",
    "wof:placetype":"venue"
},
  "geometry": {"coordinates":[14.25902,52.106861],"type":"Point"}
}