{
  "type": "Feature",
  "properties": {
    "iso:country":"DE",
    "sg:address":"Jutastr. 9",
    "sg:city":"M\u00fcnchen",
    "sg:phone":"+49 89/1297061",
    "sg:postcode":"80636",
    "sg:province":"Bayern",
    "wof:name":"Lukas Gmbh Elektroinstallation",
    "wof:placetype":"venue"
},
  "geometry": {"coordinates":[11.541153,48.152687],"type":"Point"}
}