{
  "type": "Feature",
  "properties": {
    "iso:country":"DE",
    "sg:address":"Kurt-Blaum-Platz 7",
    "sg:city":"Hanau",
    "sg:phone":"+49 6181/93730",
    "sg:postcode":"63450",
    "sg:province":"Hessen",
    "wof:name":"Unitec Gmbh",
    "wof:placetype":"venue"
},
  "geometry": {"coordinates":[8.9229125977,50.1299743652],"type":"Point"}
}