{
  "type": "Feature",
  "properties": {
    "iso:country":"DE",
    "sg:address":"Moltkestr. 28 a",
    "sg:city":"Freiburg",
    "sg:phone":"+49 761/35558",
    "sg:postcode":"79098",
    "sg:province":"Baden-W\u00fcrttemberg",
    "wof:name":"Delia H\u00f6fner Massagepraxis",
    "wof:placetype":"venue"
},
  "geometry": {"coordinates":[7.8434,47.993992],"type":"Point"}
}