{
  "type": "Feature",
  "properties": {
    "iso:country":"DE",
    "sg:address":"Rieder End 34",
    "sg:city":"Leese",
    "sg:phone":"+49 5761/1204",
    "sg:postcode":"31633",
    "sg:province":"Niedersachsen",
    "wof:name":"Edith Strempel Heilpraktikerin",
    "wof:placetype":"venue"
},
  "geometry": {"coordinates":[9.1225671768,52.5067634583],"type":"Point"}
}