{
  "type": "Feature",
  "properties": {
    "iso:country":"DE",
    "sg:address":"Schalksburgstr. 17",
    "sg:city":"Hechingen",
    "sg:phone":"+49 7471/4358",
    "sg:postcode":"72379",
    "sg:province":"Baden-W\u00fcrttemberg",
    "wof:name":"H. J. Schmidt",
    "wof:placetype":"venue"
},
  "geometry": {"coordinates":[8.9715995789,48.3492431641],"type":"Point"}
}