{
  "type": "Feature",
  "properties": {
    "iso:country":"DE",
    "sg:address":"Siegfried-Helbich-Str. 1",
    "sg:city":"Extertal",
    "sg:phone":"+49 5754/9690",
    "sg:postcode":"32699",
    "sg:province":"Nordrhein-Westfalen",
    "wof:name":"Freizeitpark Extertal Betriebsges. Mbh",
    "wof:placetype":"venue"
},
  "geometry": {"coordinates":[9.1261959076,52.067779541],"type":"Point"}
}