{
  "type": "Feature",
  "properties": {
    "iso:country":"DE",
    "sg:address":"Alte Str. 43",
    "sg:city":"N\u00fcrnberg",
    "sg:phone":"+49 911/6427783",
    "sg:postcode":"90451",
    "sg:province":"Bayern",
    "wof:name":"Hans Klein",
    "wof:placetype":"venue"
},
  "geometry": {"coordinates":[11.0344982147,49.4025764465],"type":"Point"}
}