{
  "type": "Feature",
  "properties": {
    "iso:country":"DE",
    "sg:address":"G\u00f6rau 8",
    "sg:city":"Weidenberg",
    "sg:phone":"+49 9278/985141",
    "sg:postcode":"95466",
    "sg:province":"Bayern",
    "wof:name":"Stark Heizung Gmbh",
    "wof:placetype":"venue"
},
  "geometry": {"coordinates":[11.6769351959,49.9574317932],"type":"Point"}
}