{
  "type": "Feature",
  "properties": {
    "iso:country":"DE",
    "sg:address":"Herderstr. 4",
    "sg:city":"Krefeld",
    "sg:phone":"+49 2151/602394",
    "sg:postcode":"47799",
    "sg:province":"Nordrhein-Westfalen",
    "wof:name":"Hans-j. Und Ursula Skupina Masseur",
    "wof:placetype":"venue"
},
  "geometry": {"coordinates":[6.571536,51.339458],"type":"Point"}
}