{
  "type": "Feature",
  "properties": {
    "iso:country":"DE",
    "sg:address":"Ortsstr. 82",
    "sg:city":"Meura",
    "sg:phone":"+49 36701/30413",
    "sg:postcode":"98744",
    "sg:province":"Th\u00fcringen",
    "wof:name":"Eiscafe Waldhaus",
    "wof:placetype":"venue"
},
  "geometry": {"coordinates":[11.21375,50.586021],"type":"Point"}
}