{
  "type": "Feature",
  "properties": {
    "iso:country":"DE",
    "sg:address":"Meisenweg 61",
    "sg:city":"Augsburg",
    "sg:phone":"+49 821/462777",
    "sg:postcode":"86156",
    "sg:province":"Bayern",
    "wof:name":"Hattler & Brendel Gmbh",
    "wof:placetype":"venue"
},
  "geometry": {"coordinates":[10.854604,48.39576],"type":"Point"}
}