{
  "type": "Feature",
  "properties": {
    "iso:country":"DE",
    "sg:address":"Thedestr. 2",
    "sg:city":"Hamburg",
    "sg:phone":"+49 40/3806016",
    "sg:postcode":"22767",
    "sg:province":"Hamburg",
    "wof:name":"Holstenkate",
    "wof:placetype":"venue"
},
  "geometry": {"coordinates":[9.9487667084,53.5512275696],"type":"Point"}
}