{
  "type": "Feature",
  "properties": {
    "iso:country":"DE",
    "sg:address":"Freesienstr. 37",
    "sg:city":"G\u00fctersloh",
    "sg:phone":"+49 5241/9049049",
    "sg:postcode":"33335",
    "sg:province":"Nordrhein-Westfalen",
    "wof:name":"Emailworker - Ihr Dienstleister Rund Um Email",
    "wof:placetype":"venue"
},
  "geometry": {"coordinates":[8.432247,51.913792],"type":"Point"}
}