{
  "type": "Feature",
  "properties": {
    "iso:country":"DE",
    "sg:address":"Bahnhofplatz 4",
    "sg:city":"Karlsruhe",
    "sg:phone":"+49 721/30853",
    "sg:postcode":"76137",
    "sg:province":"Baden-W\u00fcrttemberg",
    "wof:name":"Rainer Jurk Lebensmittel",
    "wof:placetype":"venue"
},
  "geometry": {"coordinates":[8.4010133743,48.9950256348],"type":"Point"}
}