{
  "type": "Feature",
  "properties": {
    "iso:country":"DE",
    "sg:address":"Hartwigstr. 9",
    "sg:city":"Bremerhaven",
    "sg:phone":"+49 471/21277",
    "sg:postcode":"27574",
    "sg:province":"Bremen",
    "wof:name":"Margaret Hoffmann Rechtsanw\u00e4ltin",
    "wof:placetype":"venue"
},
  "geometry": {"coordinates":[8.6011800766,53.5338554382],"type":"Point"}
}