{
  "type": "Feature",
  "properties": {
    "iso:country":"DE",
    "sg:address":"Rostesiepen 16",
    "sg:city":"Herdecke",
    "sg:phone":"+49 2330/72931",
    "sg:postcode":"58313",
    "sg:province":"Nordrhein-Westfalen",
    "wof:name":"Karl-heinz Lohkamp",
    "wof:placetype":"venue"
},
  "geometry": {"coordinates":[7.4097700119,51.4131011963],"type":"Point"}
}