{
  "type": "Feature",
  "properties": {
    "iso:country":"DE",
    "sg:address":"Im Winkel 11 a",
    "sg:city":"Niegripp",
    "sg:phone":"+49 3921/994323",
    "sg:postcode":"39291",
    "sg:province":"Sachsen-Anhalt",
    "wof:name":"Dh Bauelemente Inh. Dieter Hauschild",
    "wof:placetype":"venue"
},
  "geometry": {"coordinates":[11.765666,52.266029],"type":"Point"}
}