{
  "type": "Feature",
  "properties": {
    "iso:country":"DE",
    "sg:address":"Falkensteiner Str. 30",
    "sg:city":"Plauen",
    "sg:postcode":"08529",
    "sg:province":"Sachsen",
    "wof:name":"Krause Hoch- Und Tiefbau Gmbh",
    "wof:placetype":"venue"
},
  "geometry": {"coordinates":[12.1848039627,50.4953346252],"type":"Point"}
}