{
  "type": "Feature",
  "properties": {
    "iso:country":"DE",
    "sg:address":"Himmeroder Wall 11",
    "sg:city":"Rheinbach",
    "sg:phone":"+49 2226/17191",
    "sg:postcode":"53359",
    "sg:province":"Nordrhein-Westfalen",
    "wof:name":"Dr. Georg Kovermann Tierarzt",
    "wof:placetype":"venue"
},
  "geometry": {"coordinates":[6.9478859901,50.6240768433],"type":"Point"}
}