{
  "type": "Feature",
  "properties": {
    "iso:country":"DE",
    "sg:address":"Wilhelm-von-Siemens-Str 23",
    "sg:city":"Berlin",
    "sg:phone":"+49 30/7610666",
    "sg:postcode":"12277",
    "sg:province":"Berlin",
    "wof:name":"Explosiv Arbeitsschutz Gmbh",
    "wof:placetype":"venue"
},
  "geometry": {"coordinates":[13.38109,52.429558],"type":"Point"}
}