{
  "type": "Feature",
  "properties": {
    "iso:country":"DE",
    "sg:address":"Reitweg 3",
    "sg:city":"Rhauderfehn",
    "sg:phone":"+49 4952/3853",
    "sg:postcode":"26817",
    "sg:province":"Niedersachsen",
    "wof:name":"Enno H\u00fcls",
    "wof:placetype":"venue"
},
  "geometry": {"coordinates":[7.57297,53.169018],"type":"Point"}
}