{
  "type": "Feature",
  "properties": {
    "iso:country":"DE",
    "sg:address":"Reingard-Heider-Str. 6",
    "sg:city":"Bacharach",
    "sg:phone":"+49 6743/2379",
    "sg:postcode":"55422",
    "sg:province":"Rheinland-Pfalz",
    "wof:name":"Hermann Stiehl",
    "wof:placetype":"venue"
},
  "geometry": {"coordinates":[7.7717700005,50.0450592041],"type":"Point"}
}