{
  "type": "Feature",
  "properties": {
    "iso:country":"DE",
    "sg:address":"Forsterstr. 5",
    "sg:city":"Berlin",
    "sg:phone":"+49 30/61776272",
    "sg:postcode":"10999",
    "sg:province":"Berlin",
    "wof:name":"Kirchbauhof Ggmbh",
    "wof:placetype":"venue"
},
  "geometry": {"coordinates":[13.433564,52.495796],"type":"Point"}
}