{
  "type": "Feature",
  "properties": {
    "iso:country":"DE",
    "sg:address":"Rumbecker Str. 6a",
    "sg:city":"Arnsberg",
    "sg:phone":"+49 2931/10145",
    "sg:postcode":"59821",
    "sg:province":"Nordrhein-Westfalen",
    "wof:name":"Residenztheater Resi 13",
    "wof:placetype":"venue"
},
  "geometry": {"coordinates":[8.0709075928,51.3970336914],"type":"Point"}
}