{
  "type": "Feature",
  "properties": {
    "iso:country":"DE",
    "sg:address":"Weinstr. 4",
    "sg:city":"Bad D\u00fcrkheim",
    "sg:phone":"+49 6322/4137",
    "sg:postcode":"67098",
    "sg:province":"Rheinland-Pfalz",
    "wof:name":"Weingut B\u00e4renhof Helmut B\u00e4hr & Sohn",
    "wof:placetype":"venue"
},
  "geometry": {"coordinates":[8.1758098602,49.475025177],"type":"Point"}
}