{
  "type": "Feature",
  "properties": {
    "iso:country":"DE",
    "sg:address":"K\u00f6penicker Str. 180",
    "sg:city":"Berlin",
    "sg:postcode":"12355",
    "sg:province":"Berlin",
    "wof:name":"Ariane Krankengymnastik Und Physiotherapieinstitut",
    "wof:placetype":"venue"
},
  "geometry": {"coordinates":[13.496945,52.418499],"type":"Point"}
}