{
  "type": "Feature",
  "properties": {
    "iso:country":"DE",
    "sg:address":"Stadthausstr. 18",
    "sg:city":"Mainz",
    "sg:phone":"+49 6131/236588",
    "sg:postcode":"55116",
    "sg:province":"Rheinland-Pfalz",
    "wof:name":"Brauhaus Zur Sonne Gebr. Kohl Verwaltungs Gmbh & Co",
    "wof:placetype":"venue"
},
  "geometry": {"coordinates":[8.2711486816,50.0007247925],"type":"Point"}
}