{
  "type": "Feature",
  "properties": {
    "iso:country":"DE",
    "sg:address":"Hauptstr. 4",
    "sg:city":"Wittighausen",
    "sg:phone":"+49 9347/299",
    "sg:postcode":"97957",
    "sg:province":"Baden-W\u00fcrttemberg",
    "wof:name":"Lorenz Herzog",
    "wof:placetype":"venue"
},
  "geometry": {"coordinates":[9.8249397278,49.5918731689],"type":"Point"}
}