{
  "type": "Feature",
  "properties": {
    "iso:country":"DE",
    "sg:address":"Schlesische Str. 28",
    "sg:city":"Berlin",
    "sg:phone":"+49 30/6112018",
    "sg:postcode":"10997",
    "sg:province":"Berlin",
    "wof:name":"Ruiken Und Vetter Architekten",
    "wof:placetype":"venue"
},
  "geometry": {"coordinates":[13.447016,52.498569],"type":"Point"}
}