{
  "type": "Feature",
  "properties": {
    "iso:country":"DE",
    "sg:address":"Hans-Zanders-Str.",
    "sg:city":"Bergisch Gladbach",
    "sg:phone":"+49 2202/36650",
    "sg:postcode":"51465",
    "sg:province":"Nordrhein-Westfalen",
    "wof:name":"Hallenbad",
    "wof:placetype":"venue"
},
  "geometry": {"coordinates":[7.1329679489,50.9870910645],"type":"Point"}
}