{
  "type": "Feature",
  "properties": {
    "iso:country":"DE",
    "sg:address":"Bahnhofstr. 20",
    "sg:city":"Bielefeld",
    "sg:phone":"+49 521/179945",
    "sg:postcode":"33602",
    "sg:province":"Nordrhein-Westfalen",
    "wof:name":"New Yorker Gmbh",
    "wof:placetype":"venue"
},
  "geometry": {"coordinates":[8.531731,52.025246],"type":"Point"}
}