{
  "type": "Feature",
  "properties": {
    "iso:country":"DE",
    "sg:address":"Crinitztalstr. 128",
    "sg:city":"Crinitzberg",
    "sg:phone":"+49 37462/3674",
    "sg:postcode":"08147",
    "sg:province":"Sachsen",
    "wof:name":"L. Handschug",
    "wof:placetype":"venue"
},
  "geometry": {"coordinates":[12.4861898422,50.5595817566],"type":"Point"}
}