{
  "type": "Feature",
  "properties": {
    "iso:country":"DE",
    "sg:address":"Dresdner Str. 73",
    "sg:city":"Dresden",
    "sg:postcode":"01326",
    "sg:province":"Sachsen",
    "wof:name":"Katholisches Pfarramt Kath. Diasporamission",
    "wof:placetype":"venue"
},
  "geometry": {"coordinates":[13.8577365875,51.0216598511],"type":"Point"}
}