{
  "type": "Feature",
  "properties": {
    "iso:country":"DE",
    "sg:address":"Am Tiefenweg 17 B",
    "sg:city":"Sinzheim",
    "sg:phone":"+49 7221/987841",
    "sg:postcode":"76547",
    "sg:province":"Baden-W\u00fcrttemberg",
    "wof:name":"Ako",
    "wof:placetype":"venue"
},
  "geometry": {"coordinates":[8.16971,48.771141],"type":"Point"}
}