{
  "type": "Feature",
  "properties": {
    "iso:country":"DE",
    "sg:address":"Hauptstr. 1",
    "sg:city":"Herxheim am Berg",
    "sg:phone":"+49 6353/8442",
    "sg:postcode":"67273",
    "sg:province":"Rheinland-Pfalz",
    "wof:name":"Helmuth Herrscher",
    "wof:placetype":"venue"
},
  "geometry": {"coordinates":[8.1799850464,49.5096282959],"type":"Point"}
}