{
  "type": "Feature",
  "properties": {
    "iso:country":"DE",
    "sg:address":"B\u00fchlstr. 20",
    "sg:city":"Eckersdorf",
    "sg:phone":"+49 921/39378",
    "sg:postcode":"95488",
    "sg:province":"Bayern",
    "wof:name":"Dr. Heinrich Hertel Tierarzt",
    "wof:placetype":"venue"
},
  "geometry": {"coordinates":[11.513133049,49.9372787476],"type":"Point"}
}