{
  "type": "Feature",
  "properties": {
    "iso:country":"DE",
    "sg:address":"Theodor-Lessing-Str. 24",
    "sg:city":"Rathenow",
    "sg:phone":"+49 3385/502451",
    "sg:postcode":"14712",
    "sg:province":"Brandenburg",
    "wof:name":"Brigitte Haupt",
    "wof:placetype":"venue"
},
  "geometry": {"coordinates":[12.356693,52.614204],"type":"Point"}
}