{
  "type": "Feature",
  "properties": {
    "iso:country":"DE",
    "sg:address":"Bachstr. 8",
    "sg:city":"M\u00f6nchengladbach",
    "sg:phone":"+49 2166/611192",
    "sg:postcode":"41239",
    "sg:province":"Nordrhein-Westfalen",
    "wof:name":"Janssen Spiel- Und Unterhaltungsautomaten Gmbh",
    "wof:placetype":"venue"
},
  "geometry": {"coordinates":[6.4386701584,51.1663017273],"type":"Point"}
}