{
  "type": "Feature",
  "properties": {
    "iso:country":"DE",
    "sg:address":"Blumenstr. 39",
    "sg:city":"Waiblingen",
    "sg:phone":"+49 7151/51958",
    "sg:postcode":"71332",
    "sg:province":"Baden-W\u00fcrttemberg",
    "wof:name":"Wagner & Kramh\u00f6ller Gbr",
    "wof:placetype":"venue"
},
  "geometry": {"coordinates":[9.310097,48.830078],"type":"Point"}
}