{
  "type": "Feature",
  "properties": {
    "iso:country":"DE",
    "sg:address":"Neckarstr. 48",
    "sg:city":"Esslingen",
    "sg:postcode":"73728",
    "sg:province":"Baden-W\u00fcrttemberg",
    "wof:name":"Casa Bona Gmbh",
    "wof:placetype":"venue"
},
  "geometry": {"coordinates":[9.3116359711,48.7368583679],"type":"Point"}
}