{
  "type": "Feature",
  "properties": {
    "iso:country":"DE",
    "sg:address":"Hasenheide 50",
    "sg:city":"Berlin",
    "sg:phone":"+49 30/6941537",
    "sg:postcode":"10967",
    "sg:province":"Berlin",
    "wof:name":"H. M\u00fcller & D. Nollenberger Treppenbauunternehmen",
    "wof:placetype":"venue"
},
  "geometry": {"coordinates":[13.4109506607,52.4888305664],"type":"Point"}
}