{
  "type": "Feature",
  "properties": {
    "iso:country":"DE",
    "sg:address":"F\u00fcrstenberger Str. 15",
    "sg:city":"Frankfurt",
    "sg:phone":"+49 335/549842",
    "sg:postcode":"15232",
    "sg:province":"Brandenburg",
    "wof:name":"Commcat Kommunikationssysteme Gmbh",
    "wof:placetype":"venue"
},
  "geometry": {"coordinates":[14.541519165,52.3372497559],"type":"Point"}
}