{
  "type": "Feature",
  "properties": {
    "iso:country":"DE",
    "sg:address":"Bahnhofstra\u00dfe 78",
    "sg:city":"Buende",
    "sg:phone":"+49 5223/12501",
    "sg:postcode":"32257",
    "sg:province":"Nordrhein-Westfalen",
    "wof:name":"Er Sie Ledermoden",
    "wof:placetype":"venue"
},
  "geometry": {"coordinates":[8.5734891891,52.2014656067],"type":"Point"}
}