{
  "type": "Feature",
  "properties": {
    "iso:country":"DE",
    "sg:address":"Uerdinger Str. 725",
    "sg:city":"Krefeld",
    "sg:phone":"+49 2151/477992",
    "sg:postcode":"47800",
    "sg:province":"Nordrhein-Westfalen",
    "wof:name":"Frank Schnitzler",
    "wof:placetype":"venue"
},
  "geometry": {"coordinates":[6.6277341843,51.3491325378],"type":"Point"}
}