{
  "type": "Feature",
  "properties": {
    "iso:country":"DE",
    "sg:address":"Landhausstr. 20",
    "sg:city":"Albstadt",
    "sg:phone":"+49 7432/7822",
    "sg:postcode":"72461",
    "sg:province":"Baden-W\u00fcrttemberg",
    "wof:name":"F. Enzenro\u00df",
    "wof:placetype":"venue"
},
  "geometry": {"coordinates":[9.0175170898,48.2573852539],"type":"Point"}
}