{
  "type": "Feature",
  "properties": {
    "iso:country":"DE",
    "sg:address":"Industriestr. 94",
    "sg:city":"Pforzheim",
    "sg:phone":"+49 7231/978370",
    "sg:postcode":"75181",
    "sg:province":"Baden-W\u00fcrttemberg",
    "wof:name":"Tecsys Electronische Systeme Gmbh",
    "wof:placetype":"venue"
},
  "geometry": {"coordinates":[8.699892,48.860001],"type":"Point"}
}