{
  "type": "Feature",
  "properties": {
    "iso:country":"DE",
    "sg:address":"D\u00fcrerstr. 13",
    "sg:city":"Chemnitz",
    "sg:phone":"+49 371/586916",
    "sg:postcode":"09126",
    "sg:province":"Sachsen",
    "wof:name":"Franziska Gebhardt",
    "wof:placetype":"venue"
},
  "geometry": {"coordinates":[12.9358434677,50.8251228333],"type":"Point"}
}