{
  "type": "Feature",
  "properties": {
    "iso:country":"DE",
    "sg:address":"Maximilianstr. 30",
    "sg:city":"M\u00fcnchen",
    "sg:phone":"+49 89/297054",
    "sg:postcode":"80539",
    "sg:province":"Bayern",
    "wof:name":"Fritz Un\u00fctzer",
    "wof:placetype":"venue"
},
  "geometry": {"coordinates":[11.582957,48.13839],"type":"Point"}
}