{
  "type": "Feature",
  "properties": {
    "iso:country":"DE",
    "sg:address":"Brunnenstr. 30",
    "sg:city":"Lauchhammer",
    "sg:postcode":"01979",
    "sg:province":"Brandenburg",
    "wof:name":"E. Rolck",
    "wof:placetype":"venue"
},
  "geometry": {"coordinates":[13.768466,51.494694],"type":"Point"}
}