{
  "type": "Feature",
  "properties": {
    "iso:country":"DE",
    "sg:address":"Fahlenberg 51",
    "sg:city":"Linnich",
    "sg:phone":"+49 2462/6249",
    "sg:postcode":"52441",
    "sg:province":"Nordrhein-Westfalen",
    "wof:name":"Peter Naida",
    "wof:placetype":"venue"
},
  "geometry": {"coordinates":[6.259002,50.961964],"type":"Point"}
}