{
  "type": "Feature",
  "properties": {
    "iso:country":"DE",
    "sg:address":"Bockhorster Str. 31",
    "sg:city":"Esterwegen",
    "sg:phone":"+49 5955/93330",
    "sg:postcode":"26897",
    "sg:province":"Niedersachsen",
    "wof:name":"Gerhard Schmees Stahl Und Anlagenbau Gmbh",
    "wof:placetype":"venue"
},
  "geometry": {"coordinates":[7.59107,53.007858],"type":"Point"}
}