{
  "type": "Feature",
  "properties": {
    "iso:country":"DE",
    "sg:address":"Badgasse 1",
    "sg:city":"Lichtenfels",
    "sg:phone":"+49 9571/4227",
    "sg:postcode":"96215",
    "sg:province":"Bayern",
    "wof:name":"Nkd Vertriebsgesellschaft Mbh",
    "wof:placetype":"venue"
},
  "geometry": {"coordinates":[11.0625562668,50.1469039917],"type":"Point"}
}