{
  "type": "Feature",
  "properties": {
    "iso:country":"DE",
    "sg:address":"Greifweg 139",
    "sg:city":"D\u00fcsseldorf",
    "sg:phone":"+49 211/553852",
    "sg:postcode":"40549",
    "sg:province":"Nordrhein-Westfalen",
    "wof:name":"O. Herr & B. Meyer",
    "wof:placetype":"venue"
},
  "geometry": {"coordinates":[6.739799,51.233791],"type":"Point"}
}