{
  "type": "Feature",
  "properties": {
    "iso:country":"DE",
    "sg:address":"Industriestr. 5",
    "sg:city":"Wetzlar",
    "sg:postcode":"35580",
    "sg:province":"Hessen",
    "wof:name":"Ottek Gmbh & Co. Kg",
    "wof:placetype":"venue"
},
  "geometry": {"coordinates":[8.4996623993,50.5377464294],"type":"Point"}
}