{
  "type": "Feature",
  "properties": {
    "iso:country":"DE",
    "sg:address":"Alfred-Brehm-Platz 14",
    "sg:city":"Frankfurt",
    "sg:phone":"+49 69/491793",
    "sg:postcode":"60316",
    "sg:province":"Hessen",
    "wof:name":"B. Kreutz",
    "wof:placetype":"venue"
},
  "geometry": {"coordinates":[8.698559,50.115356],"type":"Point"}
}