{
  "type": "Feature",
  "properties": {
    "iso:country":"DE",
    "sg:address":"Uedorfer Weg 60",
    "sg:city":"Bornheim",
    "sg:phone":"+49 2222/81228",
    "sg:postcode":"53332",
    "sg:province":"Nordrhein-Westfalen",
    "wof:name":"Rudolf Beckert",
    "wof:placetype":"venue"
},
  "geometry": {"coordinates":[7.004353,50.768284],"type":"Point"}
}