{
  "type": "Feature",
  "properties": {
    "iso:country":"DE",
    "sg:address":"Weiherstr. 2a",
    "sg:city":"Landsberg",
    "sg:phone":"+49 8191/42505",
    "sg:postcode":"86899",
    "sg:province":"Bayern",
    "wof:name":"Schweiger & Kurz Wohnbau- U. Immobilien Gmbh",
    "wof:placetype":"venue"
},
  "geometry": {"coordinates":[10.872658,48.057297],"type":"Point"}
}