{
  "type": "Feature",
  "properties": {
    "iso:country":"DE",
    "sg:address":"Gro\u00dfe M\u00fchlenstr. 24",
    "sg:city":"Sch\u00f6nberg",
    "sg:phone":"+49 4344/30290",
    "sg:postcode":"24217",
    "sg:province":"Schleswig-Holstein",
    "wof:name":"Gisela Franke Altenheim",
    "wof:placetype":"venue"
},
  "geometry": {"coordinates":[10.377991,54.389648],"type":"Point"}
}