{
  "type": "Feature",
  "properties": {
    "iso:country":"DE",
    "sg:address":"S\u00fcplinger Str. 52",
    "sg:city":"Haldensleben",
    "sg:phone":"+49 3904/43211",
    "sg:postcode":"39340",
    "sg:province":"Sachsen-Anhalt",
    "wof:name":"Bauschloss. Staufenbiel",
    "wof:placetype":"venue"
},
  "geometry": {"coordinates":[11.390464,52.28442],"type":"Point"}
}