{
  "type": "Feature",
  "properties": {
    "iso:country":"DE",
    "sg:address":"Industriering Ost 74",
    "sg:city":"Kempen",
    "sg:phone":"+49 2152/916670",
    "sg:postcode":"47906",
    "sg:province":"Nordrhein-Westfalen",
    "wof:name":"Koervers & Krumpholz Gmbh",
    "wof:placetype":"venue"
},
  "geometry": {"coordinates":[6.4332299232,51.3730888367],"type":"Point"}
}