{
  "type": "Feature",
  "properties": {
    "iso:country":"DE",
    "sg:address":"Winnekendonker Strasse 12a",
    "sg:city":"Geldern",
    "sg:phone":"+49 2838",
    "sg:postcode":"47608",
    "sg:province":"Nordrhein-Westfalen",
    "wof:name":"Der Spezialist In Der Lichtwellen-technik",
    "wof:placetype":"venue"
},
  "geometry": {"coordinates":[6.289151,51.5355],"type":"Point"}
}