{
  "type": "Feature",
  "properties": {
    "iso:country":"DE",
    "sg:address":"Marktstr. 14",
    "sg:city":"Wassertr\u00fcdingen",
    "sg:phone":"+49 9832/9154",
    "sg:postcode":"91717",
    "sg:province":"Bayern",
    "wof:name":"M. Adanitsch",
    "wof:placetype":"venue"
},
  "geometry": {"coordinates":[10.597366,49.040058],"type":"Point"}
}