{
  "type": "Feature",
  "properties": {
    "iso:country":"DE",
    "sg:address":"Bohlenweg 2",
    "sg:city":"Aschaffenburg",
    "sg:phone":"+49 6021/91343",
    "sg:postcode":"63739",
    "sg:province":"Bayern",
    "wof:name":"Reinhard Neuber",
    "wof:placetype":"venue"
},
  "geometry": {"coordinates":[9.1630067825,49.9750976562],"type":"Point"}
}