{
  "type": "Feature",
  "properties": {
    "iso:country":"DE",
    "sg:address":"Weender Str. 19",
    "sg:city":"G\u00f6ttingen",
    "sg:phone":"+49 551/46031",
    "sg:postcode":"37073",
    "sg:province":"Niedersachsen",
    "wof:name":"C & A",
    "wof:placetype":"venue"
},
  "geometry": {"coordinates":[9.9350471497,51.5338630676],"type":"Point"}
}