{
  "type": "Feature",
  "properties": {
    "iso:country":"DE",
    "sg:address":"Tannenweg 3",
    "sg:city":"Dinklage",
    "sg:phone":"+49 4443/4902",
    "sg:postcode":"49413",
    "sg:province":"Niedersachsen",
    "wof:name":"B. Und K. Honkomp",
    "wof:placetype":"venue"
},
  "geometry": {"coordinates":[8.143012,52.663643],"type":"Point"}
}