{
  "type": "Feature",
  "properties": {
    "iso:country":"DE",
    "sg:address":"Walder Str 1-5",
    "sg:city":"Sauldorf",
    "sg:phone":"+49 7578/92140",
    "sg:postcode":"88605",
    "sg:province":"Baden-W\u00fcrttemberg",
    "wof:name":"Adolf Stadler Gmbh",
    "wof:placetype":"venue"
},
  "geometry": {"coordinates":[9.116851,47.94099],"type":"Point"}
}