{
  "type": "Feature",
  "properties": {
    "iso:country":"DE",
    "sg:address":"Biedensandstr. 56",
    "sg:city":"Lampertheim",
    "sg:phone":"+49 6206/9500",
    "sg:postcode":"68623",
    "sg:province":"Hessen",
    "wof:name":"Gdc Projektpartner Gmbh",
    "wof:placetype":"venue"
},
  "geometry": {"coordinates":[8.455391,49.597614],"type":"Point"}
}