{
  "type": "Feature",
  "properties": {
    "iso:country":"DE",
    "sg:address":"Arthur-Hoffmann-Str. 88",
    "sg:city":"Leipzig",
    "sg:phone":"+49 341/3016717",
    "sg:postcode":"04275",
    "sg:province":"Sachsen",
    "wof:name":"Pauling Eisenwaren Inh. Klaus Weber",
    "wof:placetype":"venue"
},
  "geometry": {"coordinates":[12.378271,51.320984],"type":"Point"}
}