{
  "type": "Feature",
  "properties": {
    "iso:country":"DE",
    "sg:address":"Hildastr. 29",
    "sg:city":"Baden-Baden",
    "sg:phone":"+49 7221/72336",
    "sg:postcode":"76534",
    "sg:province":"Baden-W\u00fcrttemberg",
    "wof:name":"Print Verlags- Und Beteiligungs Gmbh",
    "wof:placetype":"venue"
},
  "geometry": {"coordinates":[8.257913,48.748859],"type":"Point"}
}