{
  "type": "Feature",
  "properties": {
    "iso:country":"DE",
    "sg:address":"Am Fahrenkrog 15",
    "sg:city":"Sierksdorf",
    "sg:phone":"+49 4563/8347",
    "sg:postcode":"23730",
    "sg:province":"Schleswig-Holstein",
    "wof:name":"Futterst\u00fcbchen",
    "wof:placetype":"venue"
},
  "geometry": {"coordinates":[10.7837619781,54.0728378296],"type":"Point"}
}