{
  "type": "Feature",
  "properties": {
    "iso:country":"DE",
    "sg:address":"Waldgrubenweg 11",
    "sg:city":"Mannheim",
    "sg:phone":"+49 621/731997",
    "sg:postcode":"68309",
    "sg:province":"Baden-W\u00fcrttemberg",
    "wof:name":"M. Boch",
    "wof:placetype":"venue"
},
  "geometry": {"coordinates":[8.5421180725,49.518196106],"type":"Point"}
}