{
  "type": "Feature",
  "properties": {
    "iso:country":"DE",
    "sg:address":"Am Kappelbach 20",
    "sg:city":"Eningen",
    "sg:phone":"+49 7121/82900",
    "sg:postcode":"72800",
    "sg:province":"Baden-W\u00fcrttemberg",
    "wof:name":"Rainbow",
    "wof:placetype":"venue"
},
  "geometry": {"coordinates":[9.2530565262,48.4811668396],"type":"Point"}
}