{
  "type": "Feature",
  "properties": {
    "iso:country":"DE",
    "sg:address":"Marktstr. 21",
    "sg:city":"Kusel",
    "sg:phone":"+49 6381/2471",
    "sg:postcode":"66869",
    "sg:province":"Rheinland-Pfalz",
    "wof:name":"Pontes Gmbh",
    "wof:placetype":"venue"
},
  "geometry": {"coordinates":[7.401432,49.537209],"type":"Point"}
}