{
  "type": "Feature",
  "properties": {
    "iso:country":"DE",
    "sg:address":"G\u00e4ssla 30",
    "sg:city":"Redwitz",
    "sg:phone":"+49 9574/4844",
    "sg:postcode":"96257",
    "sg:province":"Bayern",
    "wof:name":"A. Mrosek",
    "wof:placetype":"venue"
},
  "geometry": {"coordinates":[11.2102050781,50.1752929688],"type":"Point"}
}