{
  "type": "Feature",
  "properties": {
    "iso:country":"DE",
    "sg:address":"Siegburger Str. 305",
    "sg:city":"K\u00f6nigswinter",
    "sg:phone":"+49 2244/873176",
    "sg:postcode":"53639",
    "sg:province":"Nordrhein-Westfalen",
    "wof:name":"Hans Klosterhalfen",
    "wof:placetype":"venue"
},
  "geometry": {"coordinates":[7.25826,50.734138],"type":"Point"}
}