{
  "type": "Feature",
  "properties": {
    "iso:country":"DE",
    "sg:address":"Daimlerstr. 97-111",
    "sg:city":"Berlin",
    "sg:phone":"+49 4930/74930",
    "sg:postcode":"12277",
    "sg:province":"Berlin",
    "wof:name":"Otto Reichelt Gmbh",
    "wof:placetype":"venue"
},
  "geometry": {"coordinates":[13.3845472336,52.4219932556],"type":"Point"}
}