{
  "type": "Feature",
  "properties": {
    "iso:country":"DE",
    "sg:address":"M\u00fcnchner Str. 4",
    "sg:city":"Markt Indersdorf",
    "sg:phone":"+49 8136/5835",
    "sg:postcode":"85229",
    "sg:province":"Bayern",
    "wof:name":"Hans H\u00e4ubl",
    "wof:placetype":"venue"
},
  "geometry": {"coordinates":[11.39863,48.374989],"type":"Point"}
}