{
  "type": "Feature",
  "properties": {
    "iso:country":"DE",
    "sg:address":"Niederhofheimer Str. 7",
    "sg:city":"Bad Soden",
    "sg:postcode":"65812",
    "sg:province":"Hessen",
    "wof:name":"Dent-rent Dienstleistungen Gmbh & Co. Kg",
    "wof:placetype":"venue"
},
  "geometry": {"coordinates":[8.498548,50.138763],"type":"Point"}
}