{
  "type": "Feature",
  "properties": {
    "iso:country":"DE",
    "sg:address":"Engadiner Str. 4",
    "sg:city":"M\u00fcnchen",
    "sg:phone":"+49 89/851384",
    "sg:postcode":"81475",
    "sg:province":"Bayern",
    "wof:name":"Bernd Heinl Kameramann",
    "wof:placetype":"venue"
},
  "geometry": {"coordinates":[11.4809532166,48.0897445679],"type":"Point"}
}