{
  "type": "Feature",
  "properties": {
    "iso:country":"DE",
    "sg:address":"Hauptstr. 2",
    "sg:city":"Alzenau",
    "sg:phone":"+49 6023/31538",
    "sg:postcode":"63755",
    "sg:province":"Bayern",
    "wof:name":"Brigitte Prei\u00dfler",
    "wof:placetype":"venue"
},
  "geometry": {"coordinates":[9.069978,50.054356],"type":"Point"}
}