{
  "type": "Feature",
  "properties": {
    "iso:country":"DE",
    "sg:address":"Max-Planck-Str. 16",
    "sg:city":"Eberswalde",
    "sg:postcode":"16225",
    "sg:province":"Brandenburg",
    "wof:name":"Steffen Branding",
    "wof:placetype":"venue"
},
  "geometry": {"coordinates":[13.8179588318,52.8384246826],"type":"Point"}
}