{
  "type": "Feature",
  "properties": {
    "iso:country":"DE",
    "sg:address":"Schanzenstr. 27",
    "sg:city":"Kassel",
    "sg:phone":"+49 561/61551",
    "sg:postcode":"34130",
    "sg:province":"Hessen",
    "wof:name":"Claudia Riedinger",
    "wof:placetype":"venue"
},
  "geometry": {"coordinates":[9.4416408539,51.3235588074],"type":"Point"}
}