{
  "type": "Feature",
  "properties": {
    "iso:country":"DE",
    "sg:address":"Hochsauerlandstr. 25",
    "sg:city":"Olsberg",
    "sg:phone":"+49 2962/2450",
    "sg:postcode":"59939",
    "sg:province":"Nordrhein-Westfalen",
    "wof:name":"R\u00fcther",
    "wof:placetype":"venue"
},
  "geometry": {"coordinates":[8.5301408768,51.3177528381],"type":"Point"}
}