{
  "type": "Feature",
  "properties": {
    "iso:country":"DE",
    "sg:address":"St\u00f6pselgasse 1",
    "sg:city":"N\u00fcrnberg",
    "sg:phone":"+49 911/227401",
    "sg:postcode":"90403",
    "sg:province":"Bayern",
    "wof:name":"Robert D\u00fcll",
    "wof:placetype":"venue"
},
  "geometry": {"coordinates":[11.078692,49.456802],"type":"Point"}
}