{
  "type": "Feature",
  "properties": {
    "iso:country":"DE",
    "sg:address":"Schoolstraat 2",
    "sg:city":"Langenhorn",
    "sg:phone":"+49 4672/247",
    "sg:postcode":"25842",
    "sg:province":"Schleswig-Holstein",
    "wof:name":"Hermann Ebsen",
    "wof:placetype":"venue"
},
  "geometry": {"coordinates":[8.931273,54.680931],"type":"Point"}
}