{
  "type": "Feature",
  "properties": {
    "iso:country":"DE",
    "sg:address":"Wiesenfeld 4",
    "sg:city":"Bad Karlshafen",
    "sg:phone":"+49 5672/711",
    "sg:postcode":"34385",
    "sg:province":"Hessen",
    "wof:name":"Klaus Ilse",
    "wof:placetype":"venue"
},
  "geometry": {"coordinates":[9.485705,51.654331],"type":"Point"}
}