{
  "type": "Feature",
  "properties": {
    "iso:country":"DE",
    "sg:address":"Schwarzwaldstr. 12",
    "sg:city":"Dreieich",
    "sg:phone":"+49 6103/82816",
    "sg:postcode":"63303",
    "sg:province":"Hessen",
    "wof:name":"Kath. Pfarramt St. Himmelfahrt",
    "wof:placetype":"venue"
},
  "geometry": {"coordinates":[8.7308073044,49.997051239],"type":"Point"}
}