{
  "type": "Feature",
  "properties": {
    "iso:country":"DE",
    "sg:address":"Leyer Str. 26",
    "sg:city":"Osnabr\u00fcck",
    "sg:postcode":"49076",
    "sg:province":"Niedersachsen",
    "wof:name":"Deeste Beteiligungsgesellschaft Mbh",
    "wof:placetype":"venue"
},
  "geometry": {"coordinates":[7.9797010422,52.2932472229],"type":"Point"}
}