{
  "type": "Feature",
  "properties": {
    "iso:country":"DE",
    "sg:address":"Z\u00f6rbiger Str. 24-25",
    "sg:city":"Bitterfeld",
    "sg:phone":"+49 3493/73900",
    "sg:postcode":"06749",
    "sg:province":"Sachsen-Anhalt",
    "wof:name":"Triton Umweltschutz Gmbh",
    "wof:placetype":"venue"
},
  "geometry": {"coordinates":[12.3046808243,51.6248817444],"type":"Point"}
}