{
  "type": "Feature",
  "properties": {
    "iso:country":"DE",
    "sg:address":"K\u00e4tnermoortwiete 5",
    "sg:city":"Hamburg",
    "sg:phone":"+49 40/6400338",
    "sg:postcode":"22175",
    "sg:province":"Hamburg",
    "wof:name":"Ingrid Janssen Heilpraktikerin",
    "wof:placetype":"venue"
},
  "geometry": {"coordinates":[10.0951356888,53.6274795532],"type":"Point"}
}