{
  "type": "Feature",
  "properties": {
    "iso:country":"DE",
    "sg:address":"Ferchl\u00e4nder Weg 1",
    "sg:city":"Jerichow",
    "sg:phone":"+49 39343/224",
    "sg:postcode":"39319",
    "sg:province":"Sachsen-Anhalt",
    "wof:name":"Rudolf Ehrecke",
    "wof:placetype":"venue"
},
  "geometry": {"coordinates":[12.0208311081,52.4677658081],"type":"Point"}
}