{
  "type": "Feature",
  "properties": {
    "iso:country":"DE",
    "sg:address":"Bahnhofplatz 1",
    "sg:city":"Bad K\u00f6nig",
    "sg:phone":"+49 6063/1412",
    "sg:postcode":"64732",
    "sg:province":"Hessen",
    "wof:name":"Deutsche Bahn Ag",
    "wof:placetype":"venue"
},
  "geometry": {"coordinates":[9.0046958923,49.7420921326],"type":"Point"}
}