{
  "type": "Feature",
  "properties": {
    "iso:country":"DE",
    "sg:address":"Rosenstr. 7",
    "sg:city":"Arnstadt",
    "sg:phone":"+49 3628/77070",
    "sg:postcode":"99310",
    "sg:province":"Th\u00fcringen",
    "wof:name":"Bestattungsinstitut Schwarze Rose",
    "wof:placetype":"venue"
},
  "geometry": {"coordinates":[10.942924,50.834717],"type":"Point"}
}