{
  "type": "Feature",
  "properties": {
    "iso:country":"DE",
    "sg:address":"Am Flugplatz 4",
    "sg:city":"L\u00fcbeck",
    "sg:phone":"+49 451/56644",
    "sg:postcode":"23560",
    "sg:province":"Schleswig-Holstein",
    "wof:name":"Ulmann-industrie-technik Inh. Paul Ulmann",
    "wof:placetype":"venue"
},
  "geometry": {"coordinates":[10.701569,53.794353],"type":"Point"}
}