{
  "type": "Feature",
  "properties": {
    "iso:country":"DE",
    "sg:address":"Bahnhofstr. 11",
    "sg:city":"Gauting",
    "sg:phone":"+49 89/8507464",
    "sg:postcode":"82131",
    "sg:province":"Bayern",
    "wof:name":"E. H\u00e4hr & C. Netzger",
    "wof:placetype":"venue"
},
  "geometry": {"coordinates":[11.377224,48.069942],"type":"Point"}
}