{
  "type": "Feature",
  "properties": {
    "iso:country":"DE",
    "sg:address":"Berliner Allee 74",
    "sg:city":"Hagen",
    "sg:phone":"+49 2334/51309",
    "sg:postcode":"58119",
    "sg:province":"Nordrhein-Westfalen",
    "wof:name":"Helmut Klaas",
    "wof:placetype":"venue"
},
  "geometry": {"coordinates":[7.5813379288,51.3684196472],"type":"Point"}
}