{
  "type": "Feature",
  "properties": {
    "iso:country":"DE",
    "sg:address":"Grundstr. 4",
    "sg:city":"Darmstadt",
    "sg:phone":"+49 6151/718450",
    "sg:postcode":"64289",
    "sg:province":"Hessen",
    "wof:name":"Alueda Handels Gmbh",
    "wof:placetype":"venue"
},
  "geometry": {"coordinates":[8.6817216873,49.8982124329],"type":"Point"}
}