{
  "type": "Feature",
  "properties": {
    "iso:country":"DE",
    "sg:address":"Siedlerstr. 6 a",
    "sg:city":"Lauchhammer",
    "sg:phone":"+49 3574/122173",
    "sg:postcode":"01979",
    "sg:province":"Brandenburg",
    "wof:name":"Viktoria-versicherung Christine Schoppan",
    "wof:placetype":"venue"
},
  "geometry": {"coordinates":[13.7499141693,51.5110816956],"type":"Point"}
}