{
  "type": "Feature",
  "properties": {
    "iso:country":"DE",
    "sg:address":"Weichselstr. 2",
    "sg:city":"Neu-Ulm",
    "sg:phone":"+49 731/81608",
    "sg:postcode":"89231",
    "sg:province":"Bayern",
    "wof:name":"Rudolf Schorp Rechtsanwalt",
    "wof:placetype":"venue"
},
  "geometry": {"coordinates":[9.9961795807,48.3863983154],"type":"Point"}
}