{
  "type": "Feature",
  "properties": {
    "iso:country":"DE",
    "sg:address":"Asberger Str. 39",
    "sg:city":"Duisburg",
    "sg:phone":"+49 2066/33259",
    "sg:postcode":"47198",
    "sg:province":"Nordrhein-Westfalen",
    "wof:name":"Heinz Berendsen",
    "wof:placetype":"venue"
},
  "geometry": {"coordinates":[6.6802158356,51.4430656433],"type":"Point"}
}