{
  "type": "Feature",
  "properties": {
    "iso:country":"DE",
    "sg:address":"F\u00fcrst-Walrad-Str. 11",
    "sg:city":"Waldsolms",
    "sg:phone":"+49 6085/2324",
    "sg:postcode":"35647",
    "sg:province":"Hessen",
    "wof:name":"G\u00e4stehaus Heinz K\u00f6hler",
    "wof:placetype":"venue"
},
  "geometry": {"coordinates":[8.4898395538,50.4065551758],"type":"Point"}
}