{
  "type": "Feature",
  "properties": {
    "iso:country":"DE",
    "sg:address":"Fahrenort 22",
    "sg:city":"Hamburg",
    "sg:phone":"+49 40/8322219",
    "sg:postcode":"22547",
    "sg:province":"Hamburg",
    "wof:name":"G.-h. Vogler",
    "wof:placetype":"venue"
},
  "geometry": {"coordinates":[9.872767,53.592396],"type":"Point"}
}