{
  "type": "Feature",
  "properties": {
    "iso:country":"DE",
    "sg:address":"Marktplatz 10",
    "sg:city":"Mehrstetten",
    "sg:phone":"+49 7381/2471",
    "sg:postcode":"72537",
    "sg:province":"Baden-W\u00fcrttemberg",
    "wof:name":"Horst Mettang",
    "wof:placetype":"venue"
},
  "geometry": {"coordinates":[9.5662593842,48.3764648438],"type":"Point"}
}