{
  "type": "Feature",
  "properties": {
    "iso:country":"DE",
    "sg:address":"Ringstr. 5",
    "sg:city":"Sippersfeld",
    "sg:postcode":"67729",
    "sg:province":"Rheinland-Pfalz",
    "wof:name":"Vereinte Versicherung Ag",
    "wof:placetype":"venue"
},
  "geometry": {"coordinates":[7.9389472008,49.5552902222],"type":"Point"}
}