{
  "type": "Feature",
  "properties": {
    "iso:country":"DE",
    "sg:address":"Hauptstr. 51a",
    "sg:city":"Stockum-P\u00fcschen",
    "sg:phone":"+49 2661/949206",
    "sg:postcode":"56459",
    "sg:province":"Rheinland-Pfalz",
    "wof:name":"Alfred Fink",
    "wof:placetype":"venue"
},
  "geometry": {"coordinates":[7.8992371559,50.6063041687],"type":"Point"}
}