{
  "type": "Feature",
  "properties": {
    "iso:country":"DE",
    "sg:address":"Achthaler Str. 39",
    "sg:city":"Bad Feilnbach",
    "sg:phone":"+49 8064/271",
    "sg:postcode":"83075",
    "sg:province":"Bayern",
    "wof:name":"Alfons Schlemer Gmbh",
    "wof:placetype":"venue"
},
  "geometry": {"coordinates":[11.96219,47.796902],"type":"Point"}
}