{
  "type": "Feature",
  "properties": {
    "iso:country":"DE",
    "sg:address":"Eichsfelder Str. 99",
    "sg:city":"Hannover",
    "sg:phone":"+49 511/790160",
    "sg:postcode":"30419",
    "sg:province":"Niedersachsen",
    "wof:name":"Hotel Garni Andrea",
    "wof:placetype":"venue"
},
  "geometry": {"coordinates":[9.6639976501,52.4095230103],"type":"Point"}
}