{
  "type": "Feature",
  "properties": {
    "iso:country":"DE",
    "sg:address":"Im Rehefeld 42",
    "sg:city":"Sankt Augustin",
    "sg:phone":"+49 2241/334815",
    "sg:postcode":"53757",
    "sg:province":"Nordrhein-Westfalen",
    "wof:name":"Dsgib Ditmar Sebeczek Gesellschaft F\u00fcr Angewandte",
    "wof:placetype":"venue"
},
  "geometry": {"coordinates":[7.2082529068,50.7618904114],"type":"Point"}
}