{
  "type": "Feature",
  "properties": {
    "iso:country":"DE",
    "sg:address":"Wielandstr. 21",
    "sg:city":"Ludwigshafen",
    "sg:phone":"+49 621/5792541",
    "sg:postcode":"67065",
    "sg:province":"Rheinland-Pfalz",
    "wof:name":"T. Mack Anlageberater",
    "wof:placetype":"venue"
},
  "geometry": {"coordinates":[8.432641983,49.4686088562],"type":"Point"}
}