{
  "type": "Feature",
  "properties": {
    "iso:country":"DE",
    "sg:address":"Kurf\u00fcrstendamm 188",
    "sg:city":"Berlin",
    "sg:postcode":"10707",
    "sg:province":"Berlin",
    "wof:name":"Bundesverband Der Dolmetscher Und \u00dcbersetzer E.v.",
    "wof:placetype":"venue"
},
  "geometry": {"coordinates":[13.316119,52.500874],"type":"Point"}
}