{
  "type": "Feature",
  "properties": {
    "iso:country":"DE",
    "sg:address":"92269",
    "sg:city":"Fensterbach",
    "sg:phone":"+49 9438/260",
    "sg:postcode":"92269",
    "sg:province":"Bayern",
    "wof:name":"Deutsche Bahn Ag",
    "wof:placetype":"venue"
},
  "geometry": {"coordinates":[12.0683698654,49.400844574],"type":"Point"}
}