{
  "type": "Feature",
  "properties": {
    "iso:country":"DE",
    "sg:address":"Am Weiher 8",
    "sg:city":"Fronhofen",
    "sg:phone":"+49 6761/12123",
    "sg:postcode":"55471",
    "sg:province":"Rheinland-Pfalz",
    "wof:name":"Helga Wie\u00df",
    "wof:placetype":"venue"
},
  "geometry": {"coordinates":[7.4696631432,49.9902267456],"type":"Point"}
}