{
  "type": "Feature",
  "properties": {
    "iso:country":"DE",
    "sg:address":"Aschbach 23",
    "sg:city":"Feldkirchen-Westerham",
    "sg:phone":"+49 89/6087600",
    "sg:postcode":"83620",
    "sg:province":"Bayern",
    "wof:name":"Kosmetika Sch\u00fctz Gmbh",
    "wof:placetype":"venue"
},
  "geometry": {"coordinates":[11.815348,47.919312],"type":"Point"}
}