{
  "type": "Feature",
  "properties": {
    "iso:country":"DE",
    "sg:address":"Gottlob-Bauknecht-Str. 33",
    "sg:city":"Calw",
    "sg:phone":"+49 7051/3936",
    "sg:postcode":"75365",
    "sg:province":"Baden-W\u00fcrttemberg",
    "wof:name":"Peter Morof Elektro- Anlagen Gmbh",
    "wof:placetype":"venue"
},
  "geometry": {"coordinates":[8.7674722672,48.7059364319],"type":"Point"}
}