{
  "type": "Feature",
  "properties": {
    "iso:country":"DE",
    "sg:address":"An der Bukoitza",
    "sg:city":"L\u00fcbben",
    "sg:postcode":"15907",
    "sg:province":"Brandenburg",
    "wof:name":"Agrargenossenschaft Radensdorf Eg",
    "wof:placetype":"venue"
},
  "geometry": {"coordinates":[13.976455,51.917931],"type":"Point"}
}