{
  "type": "Feature",
  "properties": {
    "iso:country":"DE",
    "sg:address":"Carl-Zeiss-Promenade 10",
    "sg:city":"Jena",
    "sg:phone":"+49 3641/642978",
    "sg:postcode":"07745",
    "sg:province":"Th\u00fcringen",
    "wof:name":"Jenaer Me\u00dftechnik Gmbh",
    "wof:placetype":"venue"
},
  "geometry": {"coordinates":[11.569326,50.918522],"type":"Point"}
}