{
  "type": "Feature",
  "properties": {
    "iso:country":"DE",
    "sg:address":"Elbstr. 33",
    "sg:city":"Wedel",
    "sg:phone":"+49 4103/88500",
    "sg:postcode":"22880",
    "sg:province":"Schleswig-Holstein",
    "wof:name":"Arnd Possehn",
    "wof:placetype":"venue"
},
  "geometry": {"coordinates":[9.707053,53.57],"type":"Point"}
}