{
  "type": "Feature",
  "properties": {
    "iso:country":"DE",
    "sg:address":"Auf dem Dreieck 2",
    "sg:city":"Bremen",
    "sg:phone":"+49 421/549950",
    "sg:postcode":"28197",
    "sg:province":"Bremen",
    "wof:name":"Manfred J. C. Niemann Hanseatischer Metallhandel",
    "wof:placetype":"venue"
},
  "geometry": {"coordinates":[8.784609,53.079075],"type":"Point"}
}