{
  "type": "Feature",
  "properties": {
    "iso:country":"DE",
    "sg:address":"Schwarze Heide",
    "sg:city":"L\u00fcbeck",
    "sg:phone":"+49 451/690915",
    "sg:postcode":"23568",
    "sg:province":"Schleswig-Holstein",
    "wof:name":"Ludwig Krobitsch",
    "wof:placetype":"venue"
},
  "geometry": {"coordinates":[10.789953,53.878693],"type":"Point"}
}