{
  "type": "Feature",
  "properties": {
    "iso:country":"DE",
    "sg:address":"Backhausgasse 13",
    "sg:city":"Leinfelden-Echterdingen",
    "sg:phone":"+49 711/796864",
    "sg:postcode":"70771",
    "sg:province":"Baden-W\u00fcrttemberg",
    "wof:name":"Dieter Schimpf",
    "wof:placetype":"venue"
},
  "geometry": {"coordinates":[9.1685600281,48.6893882751],"type":"Point"}
}