{
  "type": "Feature",
  "properties": {
    "iso:country":"DE",
    "sg:address":"M\u00fcnchener Str. 19",
    "sg:city":"Haar",
    "sg:phone":"+49 89/46204090",
    "sg:postcode":"85540",
    "sg:province":"Bayern",
    "wof:name":"Andreas Messerli Gmbh",
    "wof:placetype":"venue"
},
  "geometry": {"coordinates":[11.719903,48.109886],"type":"Point"}
}