{
  "type": "Feature",
  "properties": {
    "iso:country":"DE",
    "sg:address":"M\u00fchlenhardtstr. 24",
    "sg:city":"Herschbroich",
    "sg:phone":"+49 2691/7426",
    "sg:postcode":"53518",
    "sg:province":"Rheinland-Pfalz",
    "wof:name":"G\u00fcnter Nett",
    "wof:placetype":"venue"
},
  "geometry": {"coordinates":[6.968137,50.367447],"type":"Point"}
}