{
  "type": "Feature",
  "properties": {
    "iso:country":"DE",
    "sg:address":"Burchardkai 2",
    "sg:city":"Hamburg",
    "sg:phone":"+49 40/7411640",
    "sg:postcode":"21129",
    "sg:province":"Hamburg",
    "wof:name":"Ctd Container- Und Transport-dienst Gmbh",
    "wof:placetype":"venue"
},
  "geometry": {"coordinates":[9.9314203262,53.528049469],"type":"Point"}
}