{
  "type": "Feature",
  "properties": {
    "iso:country":"DE",
    "sg:address":"Pillauer Str. 72d",
    "sg:city":"Hamburg",
    "sg:phone":"+49 40/6958661",
    "sg:postcode":"22047",
    "sg:province":"Hamburg",
    "wof:name":"Olympia",
    "wof:placetype":"venue"
},
  "geometry": {"coordinates":[10.0876808167,53.5943641663],"type":"Point"}
}