{
  "type": "Feature",
  "properties": {
    "iso:country":"DE",
    "sg:address":"Kiautschoustr. 11",
    "sg:city":"Berlin",
    "sg:phone":"+49 30/4534923",
    "sg:postcode":"13353",
    "sg:province":"Berlin",
    "wof:name":"Spieckermann & Neumann Gmbh",
    "wof:placetype":"venue"
},
  "geometry": {"coordinates":[13.353533,52.540234],"type":"Point"}
}