{
  "type": "Feature",
  "properties": {
    "iso:country":"DE",
    "sg:address":"Fritz-Reuter-Str. 50",
    "sg:city":"Zierzow",
    "sg:phone":"+49 38752/80581",
    "sg:postcode":"19300",
    "sg:province":"Mecklenburg-Vorpommern",
    "wof:name":"Detlef Franke",
    "wof:placetype":"venue"
},
  "geometry": {"coordinates":[11.688000679,53.2823104858],"type":"Point"}
}