{
  "type": "Feature",
  "properties": {
    "iso:country":"DE",
    "sg:address":"56412",
    "sg:city":"H\u00fcbingen",
    "sg:phone":"+49 6439/1469",
    "sg:postcode":"56412",
    "sg:province":"Rheinland-Pfalz",
    "wof:name":"Coop",
    "wof:placetype":"venue"
},
  "geometry": {"coordinates":[7.8452091217,50.3598823547],"type":"Point"}
}