{
  "type": "Feature",
  "properties": {
    "iso:country":"DE",
    "sg:address":"Berghausen 9",
    "sg:city":"Hohenburg",
    "sg:phone":"+49 9626/263",
    "sg:postcode":"92277",
    "sg:province":"Bayern",
    "wof:name":"Josef Ederer",
    "wof:placetype":"venue"
},
  "geometry": {"coordinates":[11.8019514084,49.314491272],"type":"Point"}
}