{
  "type": "Feature",
  "properties": {
    "iso:country":"DE",
    "sg:address":"Oberhausen 4",
    "sg:city":"Much",
    "sg:phone":"+49 2245/2414",
    "sg:postcode":"53804",
    "sg:province":"Nordrhein-Westfalen",
    "wof:name":"Willi Balensiefer",
    "wof:placetype":"venue"
},
  "geometry": {"coordinates":[7.401922,50.865105],"type":"Point"}
}