{
  "type": "Feature",
  "properties": {
    "iso:country":"DE",
    "sg:address":"Johannisstr. 12",
    "sg:city":"Hofheim",
    "sg:phone":"+49 9523/337",
    "sg:postcode":"97461",
    "sg:province":"Bayern",
    "wof:name":"Manfred Jung",
    "wof:placetype":"venue"
},
  "geometry": {"coordinates":[10.524393,50.139908],"type":"Point"}
}