{
  "type": "Feature",
  "properties": {
    "iso:country":"DE",
    "sg:address":"Am Baum 25",
    "sg:city":"Hagen",
    "sg:phone":"+49 2331/961377",
    "sg:postcode":"58099",
    "sg:province":"Nordrhein-Westfalen",
    "wof:name":"Informationsdesign Thomas Uwe Roehl Www.itur.de",
    "wof:placetype":"venue"
},
  "geometry": {"coordinates":[7.465999,51.397137],"type":"Point"}
}