{
  "type": "Feature",
  "properties": {
    "iso:country":"DE",
    "sg:address":"Escheburger Weg 3",
    "sg:city":"Hamburg",
    "sg:phone":"+49 40/7235051",
    "sg:postcode":"21039",
    "sg:province":"Hamburg",
    "wof:name":"Seeliger Und Partner Ingenieur Gmbh",
    "wof:placetype":"venue"
},
  "geometry": {"coordinates":[10.3099632263,53.4433059692],"type":"Point"}
}