{
  "type": "Feature",
  "properties": {
    "iso:country":"DE",
    "sg:address":"Edisonstr. 13-15",
    "sg:city":"Leipzig",
    "sg:phone":"+49 4934/1659690",
    "sg:postcode":"04319",
    "sg:province":"Sachsen",
    "wof:name":"Zelch-bau Gmbh",
    "wof:placetype":"venue"
},
  "geometry": {"coordinates":[12.490855,51.34264],"type":"Point"}
}