{
  "type": "Feature",
  "properties": {
    "iso:country":"DE",
    "sg:address":"Zum Heidegarten 3",
    "sg:city":"Netphen",
    "sg:phone":"+49 2738/1018",
    "sg:postcode":"57250",
    "sg:province":"Nordrhein-Westfalen",
    "wof:name":"B. Groos Gmbh",
    "wof:placetype":"venue"
},
  "geometry": {"coordinates":[8.0878372192,50.9249687195],"type":"Point"}
}