{
  "type": "Feature",
  "properties": {
    "iso:country":"DE",
    "sg:address":"Merseburger Landstr. 12",
    "sg:city":"R\u00fcckmarsdorf",
    "sg:phone":"+49 341/446850",
    "sg:postcode":"04430",
    "wof:name":"R\u00fcma Industrieverpackung Leipzig Gmbh",
    "wof:placetype":"venue"
},
  "geometry": {"coordinates":[12.2526397705,51.3444786072],"type":"Point"}
}