{
  "type": "Feature",
  "properties": {
    "iso:country":"DE",
    "sg:address":"Via-Claudia-Str. 10",
    "sg:city":"Augsburg",
    "sg:phone":"+49 821/880151",
    "sg:postcode":"86179",
    "sg:province":"Bayern",
    "wof:name":"Hugo Klemm Jun. Kfz-verwertungsuntern.",
    "wof:placetype":"venue"
},
  "geometry": {"coordinates":[10.9023838043,48.3069801331],"type":"Point"}
}