{
  "type": "Feature",
  "properties": {
    "iso:country":"DE",
    "sg:address":"Ormessonstr.7",
    "sg:city":"Br\u00fchl",
    "sg:phone":"+49 6202/73389",
    "sg:postcode":"68782",
    "sg:province":"Baden-W\u00fcrttemberg",
    "wof:name":"Geldverdienen Im Internet Leicht Gemacht",
    "wof:placetype":"venue"
},
  "geometry": {"coordinates":[8.530931,49.406174],"type":"Point"}
}