{
  "type": "Feature",
  "properties": {
    "iso:country":"DE",
    "sg:address":"Karl-Heine-Str. 83",
    "sg:city":"Leipzig",
    "sg:phone":"+49 341/4773151",
    "sg:postcode":"04229",
    "sg:province":"Sachsen",
    "wof:name":"Play Up Gmbh",
    "wof:placetype":"venue"
},
  "geometry": {"coordinates":[12.3317184448,51.330745697],"type":"Point"}
}