{
  "type": "Feature",
  "properties": {
    "iso:country":"DE",
    "sg:address":"Hauptstr. 8-10",
    "sg:city":"Beckum",
    "sg:phone":"+49 2525/7971",
    "sg:postcode":"59269",
    "sg:province":"Nordrhein-Westfalen",
    "wof:name":"H. Ander",
    "wof:placetype":"venue"
},
  "geometry": {"coordinates":[8.031080246,51.787311554],"type":"Point"}
}