{
  "type": "Feature",
  "properties": {
    "iso:country":"DE",
    "sg:address":"Auf dem Kolben 15",
    "sg:city":"Bad Sobernheim",
    "sg:phone":"+49 6751/2712",
    "sg:postcode":"55566",
    "sg:province":"Rheinland-Pfalz",
    "wof:name":"G\u00e4stehaus Heimbrodt",
    "wof:placetype":"venue"
},
  "geometry": {"coordinates":[7.6619720459,49.7863922119],"type":"Point"}
}