{
  "type": "Feature",
  "properties": {
    "iso:country":"DE",
    "sg:address":"Pfeiferweg 16",
    "sg:city":"Breitenberg",
    "sg:phone":"+49 8584/1483",
    "sg:postcode":"94139",
    "sg:province":"Bayern",
    "wof:name":"Pfeiferwirt",
    "wof:placetype":"venue"
},
  "geometry": {"coordinates":[13.7759952545,48.6953468323],"type":"Point"}
}