{
  "type": "Feature",
  "properties": {
    "iso:country":"DE",
    "sg:address":"Implerstr. 8",
    "sg:city":"M\u00fcnchen",
    "sg:phone":"+49 89/7470800",
    "sg:postcode":"81371",
    "sg:province":"Bayern",
    "wof:name":"M\u00fcnchener Pflegekreis",
    "wof:placetype":"venue"
},
  "geometry": {"coordinates":[11.548426,48.123199],"type":"Point"}
}