{
  "type": "Feature",
  "properties": {
    "iso:country":"DE",
    "sg:address":"Adalbert-Stifter-Str. 7",
    "sg:city":"Bad Kreuznach",
    "sg:phone":"+49 671/8960350",
    "sg:postcode":"55543",
    "sg:province":"Rheinland-Pfalz",
    "wof:name":"Werner S\u00fchling",
    "wof:placetype":"venue"
},
  "geometry": {"coordinates":[7.8787918091,49.8280143738],"type":"Point"}
}