{
  "type": "Feature",
  "properties": {
    "iso:country":"DE",
    "sg:address":"M\u00fchlenweg 51",
    "sg:city":"Bad Zwischenahn",
    "sg:phone":"+49 4403/3722",
    "sg:postcode":"26160",
    "sg:province":"Niedersachsen",
    "wof:name":"Gerd Baumeister",
    "wof:placetype":"venue"
},
  "geometry": {"coordinates":[8.049195,53.175545],"type":"Point"}
}