{
  "type": "Feature",
  "properties": {
    "iso:country":"DE",
    "sg:address":"An der Bieg 8",
    "sg:city":"Herzogenaurach",
    "sg:phone":"+49 9132/4574",
    "sg:postcode":"91074",
    "sg:province":"Bayern",
    "wof:name":"F. Popp",
    "wof:placetype":"venue"
},
  "geometry": {"coordinates":[10.8752450943,49.5688552856],"type":"Point"}
}