{
  "type": "Feature",
  "properties": {
    "iso:country":"DE",
    "sg:address":"Heydaer Str. 31 a",
    "sg:city":"Martinroda",
    "sg:phone":"+49 3677/791363",
    "sg:postcode":"98693",
    "sg:province":"Th\u00fcringen",
    "wof:name":"Meier Martinroda Bausanierung Gmbh",
    "wof:placetype":"venue"
},
  "geometry": {"coordinates":[10.892278,50.722446],"type":"Point"}
}