{
  "type": "Feature",
  "properties": {
    "iso:country":"DE",
    "sg:address":"Gartenstr. 9",
    "sg:city":"Kehrig",
    "sg:phone":"+49 2651/2055",
    "sg:postcode":"56729",
    "sg:province":"Rheinland-Pfalz",
    "wof:name":"Raiffeisen-markt Kehrig Gmbh",
    "wof:placetype":"venue"
},
  "geometry": {"coordinates":[7.22108,50.280159],"type":"Point"}
}