{
  "type": "Feature",
  "properties": {
    "iso:country":"DE",
    "sg:address":"Alpenveilchenstr. 29",
    "sg:city":"M\u00fcnchen",
    "sg:phone":"+49 89/701288",
    "sg:postcode":"80689",
    "sg:province":"Bayern",
    "wof:name":"Kapplerhof",
    "wof:placetype":"venue"
},
  "geometry": {"coordinates":[11.4893665314,48.1276931763],"type":"Point"}
}