{
  "type": "Feature",
  "properties": {
    "iso:country":"DE",
    "sg:address":"Provinzialstr. 16",
    "sg:city":"Niederkassel",
    "sg:phone":"+49 228/453588",
    "sg:postcode":"53859",
    "sg:province":"Nordrhein-Westfalen",
    "wof:name":"Kl\u00f6fer Optik Gmbh",
    "wof:placetype":"venue"
},
  "geometry": {"coordinates":[7.0714740753,50.7748184204],"type":"Point"}
}