{
  "type": "Feature",
  "properties": {
    "iso:country":"DE",
    "sg:address":"Lange Str. 10",
    "sg:city":"Grimma",
    "sg:phone":"+49 3437/919717",
    "sg:postcode":"04668",
    "sg:province":"Sachsen",
    "wof:name":"Hans-joachim Bittner",
    "wof:placetype":"venue"
},
  "geometry": {"coordinates":[12.726485,51.233128],"type":"Point"}
}