{
  "type": "Feature",
  "properties": {
    "iso:country":"DE",
    "sg:address":"Lange Gasse 46",
    "sg:city":"Geislingen",
    "sg:phone":"+49 7331/43765",
    "sg:postcode":"73312",
    "sg:province":"Baden-W\u00fcrttemberg",
    "wof:name":"Regro",
    "wof:placetype":"venue"
},
  "geometry": {"coordinates":[9.842693,48.613861],"type":"Point"}
}