{
  "type": "Feature",
  "properties": {
    "iso:country":"DE",
    "sg:address":"Versmolder Str. 22",
    "sg:city":"Halle",
    "sg:phone":"+49 5201/81610",
    "sg:postcode":"33790",
    "sg:province":"Nordrhein-Westfalen",
    "wof:name":"Gerling Metall- Verarbeitung Gmbh",
    "wof:placetype":"venue"
},
  "geometry": {"coordinates":[8.3085927963,52.0446777344],"type":"Point"}
}