{
  "type": "Feature",
  "properties": {
    "iso:country":"DE",
    "sg:address":"Gro\u00dfe Bleichen 16",
    "sg:city":"Hamburg",
    "sg:phone":"+49 40/3553800",
    "sg:postcode":"20354",
    "sg:province":"Hamburg",
    "wof:name":"Institut Dr Von Keitz Gmbh",
    "wof:placetype":"venue"
},
  "geometry": {"coordinates":[9.990492,53.553535],"type":"Point"}
}