{
  "type": "Feature",
  "properties": {
    "iso:country":"DE",
    "sg:address":"Bergstr. 23",
    "sg:city":"V\u00f6hringen",
    "sg:phone":"+49 7306/919618",
    "sg:postcode":"89269",
    "sg:province":"Bayern",
    "wof:name":"F. Oehmke",
    "wof:placetype":"venue"
},
  "geometry": {"coordinates":[10.0988264084,48.2946205139],"type":"Point"}
}