{
  "type": "Feature",
  "properties": {
    "iso:country":"DE",
    "sg:address":"Bahnhofstr. 12",
    "sg:city":"Limburg",
    "sg:phone":"+49 6431/218880",
    "sg:postcode":"65549",
    "sg:province":"Hessen",
    "wof:name":"Sport-maldaner Ohg",
    "wof:placetype":"venue"
},
  "geometry": {"coordinates":[8.064643,50.387325],"type":"Point"}
}