{
  "type": "Feature",
  "properties": {
    "iso:country":"DE",
    "sg:address":"Bodewigstr. 30",
    "sg:city":"Lahnstein",
    "sg:phone":"+49 2621/2000",
    "sg:postcode":"56112",
    "sg:province":"Rheinland-Pfalz",
    "wof:name":"Reinhard G\u00f6rg M. Hewer",
    "wof:placetype":"venue"
},
  "geometry": {"coordinates":[7.60328722,50.3056106567],"type":"Point"}
}