{
  "type": "Feature",
  "properties": {
    "iso:country":"DE",
    "sg:address":"Fritz-Dobisch-Str. 16",
    "sg:city":"Saarbr\u00fccken",
    "sg:phone":"+49 681/46644",
    "sg:postcode":"66111",
    "sg:province":"Saarland",
    "wof:name":"Roland Vlaemynck Tisseur Gmbh",
    "wof:placetype":"venue"
},
  "geometry": {"coordinates":[6.98772192,49.2396736145],"type":"Point"}
}