{
  "type": "Feature",
  "properties": {
    "iso:country":"DE",
    "sg:address":"Dresdener Str. 4a",
    "sg:city":"Gro\u00dfharthau",
    "sg:phone":"+49 35954/50818",
    "sg:postcode":"01909",
    "sg:province":"Sachsen",
    "wof:name":"Schock Fensterwerk Bauelemente Gmbh",
    "wof:placetype":"venue"
},
  "geometry": {"coordinates":[14.104334,51.10778],"type":"Point"}
}