{
  "type": "Feature",
  "properties": {
    "iso:country":"DE",
    "sg:address":"M\u00fcnstereifeler Str. 4",
    "sg:city":"Altenahr",
    "sg:phone":"+49 2643/7928",
    "sg:postcode":"53505",
    "sg:province":"Rheinland-Pfalz",
    "wof:name":"Pension Haus Hoffmann",
    "wof:placetype":"venue"
},
  "geometry": {"coordinates":[6.975083828,50.5101966858],"type":"Point"}
}