{
  "type": "Feature",
  "properties": {
    "iso:country":"DE",
    "sg:address":"Fritschestr. 78",
    "sg:city":"Berlin",
    "sg:phone":"+49 30/3410084",
    "sg:postcode":"10585",
    "sg:province":"Berlin",
    "wof:name":"Dls Dentallegierungen Stra\u00dfer Gmbh",
    "wof:placetype":"venue"
},
  "geometry": {"coordinates":[13.2994346619,52.5143814087],"type":"Point"}
}