{
  "type": "Feature",
  "properties": {
    "iso:country":"DE",
    "sg:address":"Harkortstr. 60",
    "sg:city":"Essen",
    "sg:postcode":"45145",
    "sg:province":"Nordrhein-Westfalen",
    "wof:name":"Magnequench Gmbh",
    "wof:placetype":"venue"
},
  "geometry": {"coordinates":[6.990796,51.446735],"type":"Point"}
}