{
  "type": "Feature",
  "properties": {
    "iso:country":"DE",
    "sg:address":"R\u00fcdigerstr. 74 a",
    "sg:city":"K\u00f6ln",
    "sg:phone":"+49 221/692848",
    "sg:postcode":"51109",
    "sg:province":"Nordrhein-Westfalen",
    "wof:name":"Orthopro Odenthal E. K.",
    "wof:placetype":"venue"
},
  "geometry": {"coordinates":[7.0413098335,50.9515609741],"type":"Point"}
}