{
  "type": "Feature",
  "properties": {
    "iso:country":"DE",
    "sg:address":"Benrodestr 83",
    "sg:city":"D\u00fcsseldorf",
    "sg:phone":"+49 211/717189",
    "sg:postcode":"40597",
    "sg:province":"Nordrhein-Westfalen",
    "wof:name":"Spedition Willems Gmbh",
    "wof:placetype":"venue"
},
  "geometry": {"coordinates":[6.861346,51.163548],"type":"Point"}
}