{
  "type": "Feature",
  "properties": {
    "iso:country":"DE",
    "sg:address":"An den Ziegeleien 11",
    "sg:city":"Goldbach",
    "sg:phone":"+49 6021/540358",
    "sg:postcode":"63773",
    "sg:province":"Bayern",
    "wof:name":"Hirsch Mode Gmbh",
    "wof:placetype":"venue"
},
  "geometry": {"coordinates":[9.175046,50.003872],"type":"Point"}
}