{
  "type": "Feature",
  "properties": {
    "iso:country":"DE",
    "sg:address":"Hauptstr. 13",
    "sg:city":"Grafenau",
    "sg:phone":"+49 8552/91610",
    "sg:postcode":"94481",
    "sg:province":"Bayern",
    "wof:name":"Martin Schubert",
    "wof:placetype":"venue"
},
  "geometry": {"coordinates":[13.397108,48.857635],"type":"Point"}
}