{
  "type": "Feature",
  "properties": {
    "iso:country":"DE",
    "sg:address":"Auguststr. 38",
    "sg:city":"Luckenwalde",
    "sg:phone":"+49 3371/621431",
    "sg:postcode":"14943",
    "sg:province":"Brandenburg",
    "wof:name":"Regina Hausmann",
    "wof:placetype":"venue"
},
  "geometry": {"coordinates":[13.1614646912,52.0863037109],"type":"Point"}
}