{
  "type": "Feature",
  "properties": {
    "iso:country":"DE",
    "sg:address":"Ziegelberg 1",
    "sg:city":"Vestenbergsgreuth",
    "sg:phone":"+49 9163/377",
    "sg:postcode":"91487",
    "sg:province":"Bayern",
    "wof:name":"Wilhelm Jakob",
    "wof:placetype":"venue"
},
  "geometry": {"coordinates":[10.6494941711,49.6876869202],"type":"Point"}
}