{
  "type": "Feature",
  "properties": {
    "iso:country":"DE",
    "sg:address":"Am Hasselholz 16",
    "sg:city":"Aachen",
    "sg:phone":"+49 241/72188",
    "sg:postcode":"52074",
    "sg:province":"Nordrhein-Westfalen",
    "wof:name":"Hans-josef Charlier",
    "wof:placetype":"venue"
},
  "geometry": {"coordinates":[6.054898,50.759953],"type":"Point"}
}