{
  "type": "Feature",
  "properties": {
    "iso:country":"DE",
    "sg:address":"Zeidlerstr. 4",
    "sg:city":"Wendelstein",
    "sg:phone":"+49 9129/9452",
    "sg:postcode":"90530",
    "sg:province":"Bayern",
    "wof:name":"Kurt Bauer",
    "wof:placetype":"venue"
},
  "geometry": {"coordinates":[11.174996,49.364067],"type":"Point"}
}