{
  "type": "Feature",
  "properties": {
    "iso:country":"DE",
    "sg:address":"Karl-Gro\u00df-Str.",
    "sg:city":"Steinen",
    "sg:postcode":"79585",
    "sg:province":"Baden-W\u00fcrttemberg",
    "wof:name":"Minimal",
    "wof:placetype":"venue"
},
  "geometry": {"coordinates":[7.7458639145,47.6398963928],"type":"Point"}
}