{
  "type": "Feature",
  "properties": {
    "iso:country":"DE",
    "sg:address":"Eisenbahnstr. 17",
    "sg:city":"Wickede",
    "sg:phone":"+49 2377/2317",
    "sg:postcode":"58739",
    "sg:province":"Nordrhein-Westfalen",
    "wof:name":"Kerkenberg Gmbh",
    "wof:placetype":"venue"
},
  "geometry": {"coordinates":[7.856068,51.489937],"type":"Point"}
}