{
  "type": "Feature",
  "properties": {
    "iso:country":"DE",
    "sg:address":"Truderinger Str. 317-319",
    "sg:city":"M\u00fcnchen",
    "sg:phone":"+49 89/4204460",
    "sg:postcode":"81825",
    "sg:province":"Bayern",
    "wof:name":"Paul Schubert Kunststoffverarbeitung Gmbh",
    "wof:placetype":"venue"
},
  "geometry": {"coordinates":[11.6719169617,48.1216011047],"type":"Point"}
}