{
  "type": "Feature",
  "properties": {
    "iso:country":"DE",
    "sg:address":"Kopernikusplatz 5",
    "sg:city":"N\u00fcrnberg",
    "sg:phone":"+49 911/4597070",
    "sg:postcode":"90459",
    "sg:province":"Bayern",
    "wof:name":"Vermieterverein N\u00fcrnberg E. V.",
    "wof:placetype":"venue"
},
  "geometry": {"coordinates":[11.0809631348,49.4397583008],"type":"Point"}
}