{
  "type": "Feature",
  "properties": {
    "iso:country":"DE",
    "sg:address":"Kesselstr. 4",
    "sg:city":"Kalkar",
    "sg:phone":"+49 2824/2584",
    "sg:postcode":"47546",
    "sg:province":"Nordrhein-Westfalen",
    "wof:name":"Pizzeria La Mirage",
    "wof:placetype":"venue"
},
  "geometry": {"coordinates":[6.2918591499,51.7391395569],"type":"Point"}
}