{
  "type": "Feature",
  "properties": {
    "iso:country":"DE",
    "sg:address":"Nottebohmstr 29",
    "sg:city":"L\u00fcdenscheid",
    "sg:phone":"+49 2351/41595",
    "sg:postcode":"58511",
    "sg:province":"Nordrhein-Westfalen",
    "wof:name":"Peter Stein Gmbh",
    "wof:placetype":"venue"
},
  "geometry": {"coordinates":[7.661511898,51.211315155],"type":"Point"}
}