{
  "type": "Feature",
  "properties": {
    "iso:country":"DE",
    "sg:address":"Pastor-Schr\u00f6der-Str. 6",
    "sg:city":"Rendsburg",
    "sg:phone":"+49 4331/21546",
    "sg:postcode":"24768",
    "sg:province":"Schleswig-Holstein",
    "wof:name":"Lagune Kroatisches Gourmet Restaurant",
    "wof:placetype":"venue"
},
  "geometry": {"coordinates":[9.6792497635,54.3046417236],"type":"Point"}
}