{
  "type": "Feature",
  "properties": {
    "iso:country":"DE",
    "sg:address":"Fritz-Reuter-Weg 6",
    "sg:city":"Iserlohn",
    "sg:phone":"+49 2374/15483",
    "sg:postcode":"58642",
    "sg:province":"Nordrhein-Westfalen",
    "wof:name":"J\u00fcrgen Huck Gmbh",
    "wof:placetype":"venue"
},
  "geometry": {"coordinates":[7.603038,51.368298],"type":"Point"}
}