{
  "type": "Feature",
  "properties": {
    "iso:country":"DE",
    "sg:address":"Otto-Schmerbach-Str. 20",
    "sg:city":"Chemnitz",
    "sg:phone":"+49 371/815900",
    "sg:postcode":"09117",
    "sg:province":"Sachsen",
    "wof:name":"Chemnitzer Aluminium Technik Gmbh",
    "wof:placetype":"venue"
},
  "geometry": {"coordinates":[12.848346,50.80962],"type":"Point"}
}