{
  "type": "Feature",
  "properties": {
    "iso:country":"DE",
    "sg:address":"Maria Trost 25",
    "sg:city":"Koblenz",
    "sg:phone":"+49 261/807000",
    "sg:postcode":"56070",
    "sg:province":"Rheinland-Pfalz",
    "wof:name":"Compugroup Holding Ag",
    "wof:placetype":"venue"
},
  "geometry": {"coordinates":[7.579696,50.386707],"type":"Point"}
}