{
  "type": "Feature",
  "properties": {
    "iso:country":"DE",
    "sg:address":"Bylandtstr. 1",
    "sg:city":"M\u00f6nchengladbach",
    "sg:phone":"+49 2166/43666",
    "sg:postcode":"41236",
    "sg:province":"Nordrhein-Westfalen",
    "wof:name":"J. Hoppe",
    "wof:placetype":"venue"
},
  "geometry": {"coordinates":[6.455711,51.169693],"type":"Point"}
}