{
  "type": "Feature",
  "properties": {
    "iso:country":"DE",
    "sg:address":"Dorstener Str. 634",
    "sg:city":"Haltern",
    "sg:phone":"+49 2360/105275",
    "sg:postcode":"45721",
    "sg:province":"Nordrhein-Westfalen",
    "wof:name":"Michael Thran Rechtsanwalt",
    "wof:placetype":"venue"
},
  "geometry": {"coordinates":[7.0961470604,51.7153091431],"type":"Point"}
}