{
  "type": "Feature",
  "properties": {
    "iso:country":"DE",
    "sg:address":"Krohnstieg 4",
    "sg:city":"Hamburg",
    "sg:phone":"+49 40/5318942",
    "sg:postcode":"22415",
    "sg:province":"Hamburg",
    "wof:name":"G\u00fcnther",
    "wof:placetype":"venue"
},
  "geometry": {"coordinates":[9.9878034592,53.6493530273],"type":"Point"}
}