{
  "type": "Feature",
  "properties": {
    "iso:country":"DE",
    "sg:address":"An Gross St. Martin 7",
    "sg:city":"Cologne",
    "sg:classifiers":[
        {
            "category":"Professional",
            "subcategory":"Computer Services",
            "type":"Services"
        }
    ],
    "sg:postcode":"50667 ",
    "sg:tags":[
        "translation",
        "translation-company",
        "translation-agency",
        "translation-company-germany",
        "translation-company-usa",
        "translator",
        "translate",
        "interpreting",
        "localisation",
        "language-translation",
        "translation-services",
        "financial-translation",
        "legal-translation",
        "technical-"
    ],
    "sg:website":"http://www.evs-translations.com",
    "wof:name":"EVS Translations",
    "wof:placetype":"venue"
},
  "geometry": {"coordinates":[6.9607942,50.9384447],"type":"Point"}
}