{
  "type": "Feature",
  "properties": {
    "iso:country":"DE",
    "sg:address":"Rather Str. 126",
    "sg:city":"Nideggen",
    "sg:phone":"+49 2427/94020",
    "sg:postcode":"52385",
    "sg:province":"Nordrhein-Westfalen",
    "wof:name":"Hotel Forsthaus Rath",
    "wof:placetype":"venue"
},
  "geometry": {"coordinates":[6.483590126,50.6924095154],"type":"Point"}
}