{
  "type": "Feature",
  "properties": {
    "iso:country":"DE",
    "sg:address":"Blumenau 50",
    "sg:city":"Hamburg",
    "sg:phone":"+49 40/4419650",
    "sg:postcode":"22089",
    "sg:province":"Hamburg",
    "wof:name":"Rotos Shipping & Transport Agency Gmbh",
    "wof:placetype":"venue"
},
  "geometry": {"coordinates":[10.0363950729,53.5674324036],"type":"Point"}
}