{
  "type": "Feature",
  "properties": {
    "iso:country":"DE",
    "sg:address":"Goebenstr. 27",
    "sg:city":"Bonn",
    "sg:phone":"+49 228/210146",
    "sg:postcode":"53113",
    "sg:province":"Nordrhein-Westfalen",
    "wof:name":"Axel Wanzer",
    "wof:placetype":"venue"
},
  "geometry": {"coordinates":[7.100867,50.724903],"type":"Point"}
}