{
  "type": "Feature",
  "properties": {
    "iso:country":"DE",
    "sg:address":"Industriestr. 6",
    "sg:city":"Langenfeld",
    "sg:phone":"+49 9164/1451",
    "sg:postcode":"91474",
    "sg:province":"Bayern",
    "wof:name":"M. Schneider Gmbh Natursteinbetrieb",
    "wof:placetype":"venue"
},
  "geometry": {"coordinates":[10.516576,49.620716],"type":"Point"}
}