{
  "type": "Feature",
  "properties": {
    "iso:country":"DE",
    "sg:address":"Karlstr. 10",
    "sg:city":"Ludwigsburg",
    "sg:phone":"+49 7141/923605",
    "sg:postcode":"71638",
    "sg:province":"Baden-W\u00fcrttemberg",
    "wof:name":"M. Mantzaraki",
    "wof:placetype":"venue"
},
  "geometry": {"coordinates":[9.1877698898,48.8915939331],"type":"Point"}
}