{
  "type": "Feature",
  "properties": {
    "iso:country":"DE",
    "sg:address":"Magdeburger Str. 36",
    "sg:city":"Hessisch Lichtenau",
    "sg:phone":"+49 5602/919746",
    "sg:postcode":"37235",
    "sg:province":"Hessen",
    "wof:name":"B. Jung Flachdach- Und Grundwasserabdichtung Gmbh",
    "wof:placetype":"venue"
},
  "geometry": {"coordinates":[9.7071676254,51.2020378113],"type":"Point"}
}