{
  "type": "Feature",
  "properties": {
    "iso:country":"DE",
    "sg:address":"Palmstr. 29",
    "sg:city":"Chemnitz",
    "sg:phone":"+49 371/4028880",
    "sg:postcode":"09130",
    "sg:province":"Sachsen",
    "wof:name":"Pizzeria",
    "wof:placetype":"venue"
},
  "geometry": {"coordinates":[12.9411592484,50.8421020508],"type":"Point"}
}