{
  "type": "Feature",
  "properties": {
    "iso:country":"DE",
    "sg:address":"Rathausstr. 10 a",
    "sg:city":"Viernheim",
    "sg:phone":"+49 6204/912319",
    "sg:postcode":"68519",
    "sg:province":"Hessen",
    "wof:name":"System Consulting Dv Systemberatung Gmbh",
    "wof:placetype":"venue"
},
  "geometry": {"coordinates":[8.5802774429,49.538848877],"type":"Point"}
}