{
  "type": "Feature",
  "properties": {
    "iso:country":"DE",
    "sg:address":"Schepersweg 73",
    "sg:city":"Wesel",
    "sg:phone":"+49 281/89309",
    "sg:postcode":"46485",
    "sg:province":"Nordrhein-Westfalen",
    "wof:name":"Leos Gastronomie",
    "wof:placetype":"venue"
},
  "geometry": {"coordinates":[6.6406621933,51.6628265381],"type":"Point"}
}