{
  "type": "Feature",
  "properties": {
    "iso:country":"DE",
    "sg:address":"Waldshuter Str. 20",
    "sg:city":"Laufenburg",
    "sg:phone":"+49 7763/7041",
    "sg:postcode":"79725",
    "sg:province":"Baden-W\u00fcrttemberg",
    "wof:name":"Wuttig Pr\u00e4zision Gmbh & Co.",
    "wof:placetype":"venue"
},
  "geometry": {"coordinates":[8.0608167648,47.5651283264],"type":"Point"}
}