{
  "type": "Feature",
  "properties": {
    "iso:country":"DE",
    "sg:address":"Gl\u00fccksburger Str. 27",
    "sg:city":"Leverkusen",
    "sg:phone":"+49 214/77777",
    "sg:postcode":"51377",
    "sg:province":"Nordrhein-Westfalen",
    "wof:name":"Paul Pfennig",
    "wof:placetype":"venue"
},
  "geometry": {"coordinates":[7.0114078522,51.0390586853],"type":"Point"}
}