{
  "type": "Feature",
  "properties": {
    "iso:country":"DE",
    "sg:address":"Rahmengasse 28",
    "sg:city":"Heidelberg",
    "sg:phone":"+49 6221/436803",
    "sg:postcode":"69120",
    "sg:province":"Baden-W\u00fcrttemberg",
    "wof:name":"H.-j. Egner",
    "wof:placetype":"venue"
},
  "geometry": {"coordinates":[8.6908197403,49.4154052734],"type":"Point"}
}