{
  "type": "Feature",
  "properties": {
    "iso:country":"DE",
    "sg:address":"In den Eichen 29",
    "sg:city":"Liederbach",
    "sg:phone":"+49 69/9758380",
    "sg:postcode":"65835",
    "sg:province":"Hessen",
    "wof:name":"Erd\u00fcs & Partner Gmbh",
    "wof:placetype":"venue"
},
  "geometry": {"coordinates":[8.4922113419,50.1228485107],"type":"Point"}
}