{
  "type": "Feature",
  "properties": {
    "iso:country":"DE",
    "sg:address":"Bgm-Martin-Donandt-Pl 11",
    "sg:city":"Bremerhaven",
    "sg:phone":"+49 471/43733",
    "sg:postcode":"27568",
    "sg:province":"Bremen",
    "wof:name":"Ev. Pfarramt Kreuzkirche Mitte",
    "wof:placetype":"venue"
},
  "geometry": {"coordinates":[8.5734348297,53.5506401062],"type":"Point"}
}