{
  "type": "Feature",
  "properties": {
    "iso:country":"DE",
    "sg:address":"Martin-Luther-Platz 10",
    "sg:city":"Ansbach",
    "sg:phone":"+49 981/2509",
    "sg:postcode":"91522",
    "sg:province":"Bayern",
    "wof:name":"Geschenkhaus Green Hans Green",
    "wof:placetype":"venue"
},
  "geometry": {"coordinates":[10.5721883774,49.3030891418],"type":"Point"}
}