{
  "type": "Feature",
  "properties": {
    "iso:country":"DE",
    "sg:address":"Hammerschmiede",
    "sg:city":"Mainhardt",
    "sg:phone":"+49 7903/3851",
    "sg:postcode":"74535",
    "sg:province":"Baden-W\u00fcrttemberg",
    "wof:name":"Wolfgang Heil Architekt",
    "wof:placetype":"venue"
},
  "geometry": {"coordinates":[9.552813,49.055595],"type":"Point"}
}