{
  "type": "Feature",
  "properties": {
    "iso:country":"DE",
    "sg:address":"Durlacher Allee 4",
    "sg:city":"Karlsruhe",
    "sg:phone":"+49 721/607637",
    "sg:postcode":"76131",
    "sg:province":"Baden-W\u00fcrttemberg",
    "wof:name":"D. K. Busch Immobilienmakler",
    "wof:placetype":"venue"
},
  "geometry": {"coordinates":[8.4178285599,49.008644104],"type":"Point"}
}