{
  "type": "Feature",
  "properties": {
    "iso:country":"DE",
    "sg:address":"Sudm\u00fchlenstr. 167",
    "sg:city":"M\u00fcnster",
    "sg:phone":"+49 251/326671",
    "sg:postcode":"48157",
    "sg:province":"Nordrhein-Westfalen",
    "wof:name":"Franz-josef Schulze Leusing",
    "wof:placetype":"venue"
},
  "geometry": {"coordinates":[7.6950058937,51.9925308228],"type":"Point"}
}