{
  "type": "Feature",
  "properties": {
    "iso:country":"DE",
    "sg:address":"Auf dem B\u00f6cken 1",
    "sg:city":"Gevelsberg",
    "sg:phone":"+49 2332/51541",
    "sg:postcode":"58285",
    "sg:province":"Nordrhein-Westfalen",
    "wof:name":"Kramer & Luke",
    "wof:placetype":"venue"
},
  "geometry": {"coordinates":[7.3295469284,51.3603057861],"type":"Point"}
}