{
  "type": "Feature",
  "properties": {
    "iso:country":"DE",
    "sg:address":"Brandenburger Str. 38",
    "sg:city":"Br\u00fcck",
    "sg:postcode":"14822",
    "sg:province":"Brandenburg",
    "wof:name":"H. Hammermeister",
    "wof:placetype":"venue"
},
  "geometry": {"coordinates":[12.761341095,52.1968154907],"type":"Point"}
}