{
  "type": "Feature",
  "properties": {
    "iso:country":"DE",
    "sg:address":"Humboldtstr. 6 a",
    "sg:city":"Rudolstadt",
    "sg:postcode":"07407",
    "sg:province":"Th\u00fcringen",
    "wof:name":"Systempartner Computervertriebs Gmbh",
    "wof:placetype":"venue"
},
  "geometry": {"coordinates":[11.314019,50.687317],"type":"Point"}
}