{
  "type": "Feature",
  "properties": {
    "iso:country":"DE",
    "sg:address":"Eichenweg 41",
    "sg:city":"Schongau",
    "sg:phone":"+49 8861/900833",
    "sg:postcode":"86956",
    "sg:province":"Bayern",
    "wof:name":"Nischik",
    "wof:placetype":"venue"
},
  "geometry": {"coordinates":[10.886868,47.823719],"type":"Point"}
}