{
  "type": "Feature",
  "properties": {
    "iso:country":"DE",
    "sg:address":"Horneburger Str. 21",
    "sg:city":"Harsefeld",
    "sg:phone":"+49 4164/4127",
    "sg:postcode":"21698",
    "sg:province":"Niedersachsen",
    "wof:name":"Dammann Gmbh",
    "wof:placetype":"venue"
},
  "geometry": {"coordinates":[9.518277,53.486164],"type":"Point"}
}