{
  "type": "Feature",
  "properties": {
    "iso:country":"DE",
    "sg:address":"Unnersberg 38",
    "sg:city":"Solingen",
    "sg:phone":"+49 212/813827",
    "sg:postcode":"42659",
    "sg:province":"Nordrhein-Westfalen",
    "wof:name":"Friedrich Kramer",
    "wof:placetype":"venue"
},
  "geometry": {"coordinates":[7.086248,51.155243],"type":"Point"}
}