{
  "type": "Feature",
  "properties": {
    "iso:country":"DE",
    "sg:address":"Falkenring 9",
    "sg:city":"Reiskirchen",
    "sg:phone":"+49 6401/220104",
    "sg:postcode":"35447",
    "sg:province":"Hessen",
    "wof:name":"Henning Gmbh",
    "wof:placetype":"venue"
},
  "geometry": {"coordinates":[8.8736743927,50.5743141174],"type":"Point"}
}