{
  "type": "Feature",
  "properties": {
    "iso:country":"DE",
    "sg:address":"Auf dem Damme 13",
    "sg:city":"Seelze",
    "sg:postcode":"30926",
    "sg:province":"Niedersachsen",
    "wof:name":"Triwood Tischlerei Gmbh",
    "wof:placetype":"venue"
},
  "geometry": {"coordinates":[9.511603,52.404297],"type":"Point"}
}