{
  "type": "Feature",
  "properties": {
    "iso:country":"DE",
    "sg:address":"Karl-Liebknecht-Str. 3",
    "sg:city":"Leipzig",
    "sg:phone":"+49 341/9618126",
    "sg:postcode":"04107",
    "sg:province":"Sachsen",
    "wof:name":"Foto Ina",
    "wof:placetype":"venue"
},
  "geometry": {"coordinates":[12.3738803864,51.3315620422],"type":"Point"}
}