{
  "type": "Feature",
  "properties": {
    "iso:country":"DE",
    "sg:address":"Hinter dem Dorfe 4",
    "sg:city":"Hannover",
    "sg:phone":"+49 511/512215",
    "sg:postcode":"30539",
    "sg:province":"Niedersachsen",
    "wof:name":"Schaller's Fischspezialit\u00e4ten Gmbh",
    "wof:placetype":"venue"
},
  "geometry": {"coordinates":[9.8264570236,52.3418159485],"type":"Point"}
}