{
  "type": "Feature",
  "properties": {
    "iso:country":"DE",
    "sg:address":"Steinstr.81-83",
    "sg:city":"Giessen",
    "sg:phone":"+49 4964/1302030",
    "sg:postcode":"35390",
    "sg:province":"Hessen",
    "wof:name":"Ksm Buseck",
    "wof:placetype":"venue"
},
  "geometry": {"coordinates":[8.6775789261,50.5918006897],"type":"Point"}
}