{
  "type": "Feature",
  "properties": {
    "iso:country":"DE",
    "sg:address":"Postfach 840:: 57217 Kreuztal:: Germany.^^Hagener Str 436::",
    "sg:city":"Kreuztal",
    "sg:phone":"+49 2732/89400",
    "sg:postcode":"57223",
    "sg:province":"Nordrhein-Westfalen",
    "wof:name":"Volksbank Littfeld Eg",
    "wof:placetype":"venue"
},
  "geometry": {"coordinates":[7.990265,50.959305],"type":"Point"}
}