{
  "type": "Feature",
  "properties": {
    "iso:country":"DE",
    "sg:address":"Neue Str. 3",
    "sg:city":"Buchholz",
    "sg:phone":"+49 4181/35142",
    "sg:postcode":"21244",
    "sg:province":"Niedersachsen",
    "wof:name":"Beechwood Musikschule",
    "wof:placetype":"venue"
},
  "geometry": {"coordinates":[9.8801221848,53.3282814026],"type":"Point"}
}