{
  "type": "Feature",
  "properties": {
    "iso:country":"DE",
    "sg:address":"Eulenbergallee 37",
    "sg:city":"Markkleeberg",
    "sg:phone":"+49 341/3541961",
    "sg:postcode":"04416",
    "sg:province":"Sachsen",
    "wof:name":"Erfolgsweg.net",
    "wof:placetype":"venue"
},
  "geometry": {"coordinates":[12.357698,51.272583],"type":"Point"}
}