{
  "type": "Feature",
  "properties": {
    "iso:country":"DE",
    "sg:address":"Kreuznacher Str. 32",
    "sg:city":"Stadecken-Elsheim",
    "sg:phone":"+49 6136/6105",
    "sg:postcode":"55271",
    "sg:province":"Rheinland-Pfalz",
    "wof:name":"J\u00fcrgen Boller",
    "wof:placetype":"venue"
},
  "geometry": {"coordinates":[8.131231308,49.9093856812],"type":"Point"}
}