{
  "type": "Feature",
  "properties": {
    "iso:country":"DE",
    "sg:address":"Am Br\u00f6gel 17",
    "sg:city":"Wuppertal",
    "sg:phone":"+49 202/884746",
    "sg:postcode":"42283",
    "sg:province":"Nordrhein-Westfalen",
    "wof:name":"Kindertagesst\u00e4tte Elterninitiative \u00b4abraxas E.v.\u00b4",
    "wof:placetype":"venue"
},
  "geometry": {"coordinates":[7.18152,51.26643],"type":"Point"}
}