{
  "type": "Feature",
  "properties": {
    "iso:country":"DE",
    "sg:address":"B\u00e4rensteiner Str. 30",
    "sg:city":"Dresden",
    "sg:postcode":"01277",
    "sg:province":"Sachsen",
    "wof:name":"B\u00fccherpresse Vertriebs- Gesellschaft Mbh",
    "wof:placetype":"venue"
},
  "geometry": {"coordinates":[13.8009586334,51.0351524353],"type":"Point"}
}