{
  "type": "Feature",
  "properties": {
    "iso:country":"DE",
    "sg:address":"Obere Kaiserstr. 171",
    "sg:city":"St. Ingbert",
    "sg:phone":"+49 6894/570213",
    "sg:postcode":"66386",
    "sg:province":"Saarland",
    "wof:name":"Imbi\u00df Pizza Da Giorgio",
    "wof:placetype":"venue"
},
  "geometry": {"coordinates":[7.1331877708,49.2859802246],"type":"Point"}
}