{
  "type": "Feature",
  "properties": {
    "iso:country":"DE",
    "sg:address":"Holzgartenstr. 46",
    "sg:city":"Pforzheim",
    "sg:phone":"+49 7231/965649",
    "sg:postcode":"75175",
    "sg:province":"Baden-W\u00fcrttemberg",
    "wof:name":"Hans Wieland",
    "wof:placetype":"venue"
},
  "geometry": {"coordinates":[8.70945,48.888332],"type":"Point"}
}