{
  "type": "Feature",
  "properties": {
    "iso:country":"DE",
    "sg:address":"Dorfstr. 96",
    "sg:city":"Sassenburg",
    "sg:phone":"+49 5378/224",
    "sg:postcode":"38524",
    "sg:province":"Niedersachsen",
    "wof:name":"Adolf Wulfes",
    "wof:placetype":"venue"
},
  "geometry": {"coordinates":[10.6031694412,52.5358161926],"type":"Point"}
}