{
  "type": "Feature",
  "properties": {
    "iso:country":"DE",
    "sg:address":"H\u00f6hndorfstr. 9",
    "sg:city":"Berlin",
    "sg:phone":"+49 30/7884135",
    "sg:postcode":"12101",
    "sg:province":"Berlin",
    "wof:name":"Health Impex",
    "wof:placetype":"venue"
},
  "geometry": {"coordinates":[13.374438,52.484257],"type":"Point"}
}