{
  "type": "Feature",
  "properties": {
    "iso:country":"DE",
    "sg:address":"Winkhauser Weg 33a",
    "sg:city":"M\u00fclheim",
    "sg:phone":"+49 208/477160",
    "sg:postcode":"45473",
    "sg:province":"Nordrhein-Westfalen",
    "wof:name":"Burkhard Sch\u00fctte Heilpraktiker",
    "wof:placetype":"venue"
},
  "geometry": {"coordinates":[6.9010968208,51.4373397827],"type":"Point"}
}