{
  "type": "Feature",
  "properties": {
    "iso:country":"DE",
    "sg:address":"J\u00e4gerstr. 14",
    "sg:city":"Hirrlingen",
    "sg:phone":"+49 7478/622",
    "sg:postcode":"72145",
    "sg:province":"Baden-W\u00fcrttemberg",
    "wof:name":"H. Und R. Waller",
    "wof:placetype":"venue"
},
  "geometry": {"coordinates":[8.894008,48.409348],"type":"Point"}
}