{
  "type": "Feature",
  "properties": {
    "iso:country":"DE",
    "sg:address":"Kameruner Str. 25",
    "sg:city":"M\u00fcnchen",
    "sg:phone":"+49 89/4306203",
    "sg:postcode":"81827",
    "sg:province":"Bayern",
    "wof:name":"Michaela Neuhofer",
    "wof:placetype":"venue"
},
  "geometry": {"coordinates":[11.712018,48.109531],"type":"Point"}
}