{
  "type": "Feature",
  "properties": {
    "iso:country":"DE",
    "sg:address":"Uhlstr. 1",
    "sg:city":"Gera",
    "sg:phone":"+49 365/7314777",
    "sg:postcode":"07549",
    "sg:province":"Th\u00fcringen",
    "wof:name":"Car & Audio Project Ohg",
    "wof:placetype":"venue"
},
  "geometry": {"coordinates":[12.0728645325,50.8501472473],"type":"Point"}
}