{
  "type": "Feature",
  "properties": {
    "iso:country":"DE",
    "sg:address":"Marktplatz 9",
    "sg:city":"Neustadt",
    "sg:phone":"+49 9161/4921",
    "sg:postcode":"91413",
    "sg:province":"Bayern",
    "wof:name":"Restaurant \u00c4g\u00e4ische Inseln",
    "wof:placetype":"venue"
},
  "geometry": {"coordinates":[9.0354995728,49.8168869019],"type":"Point"}
}