{
  "type": "Feature",
  "properties": {
    "iso:country":"DE",
    "sg:address":"Friedrich-Ebert-Str. 121a",
    "sg:city":"Wuppertal",
    "sg:phone":"+49 202/3096870",
    "sg:postcode":"42117",
    "sg:province":"Nordrhein-Westfalen",
    "wof:name":"Klaus Dabringhausen",
    "wof:placetype":"venue"
},
  "geometry": {"coordinates":[7.129553,51.251541],"type":"Point"}
}