{
  "type": "Feature",
  "properties": {
    "iso:country":"DE",
    "sg:address":"Berliner Str. 13",
    "sg:city":"G\u00fctersloh",
    "sg:phone":"+49 5241/20834",
    "sg:postcode":"33330",
    "sg:province":"Nordrhein-Westfalen",
    "wof:name":"Foto Hoffschildt",
    "wof:placetype":"venue"
},
  "geometry": {"coordinates":[8.3774461746,51.9056053162],"type":"Point"}
}