{
  "type": "Feature",
  "properties": {
    "iso:country":"DE",
    "sg:address":"H\u00f6rvelsingen",
    "sg:city":"Langenau",
    "sg:phone":"+49 7348/5767",
    "sg:postcode":"89129",
    "sg:province":"Baden-W\u00fcrttemberg",
    "wof:name":"Ofenloch-halle",
    "wof:placetype":"venue"
},
  "geometry": {"coordinates":[10.1185541153,48.4938163757],"type":"Point"}
}