{
  "type": "Feature",
  "properties": {
    "iso:country":"DE",
    "sg:address":"Eikholte 11",
    "sg:city":"Hameln",
    "sg:phone":"+49 5151/53535",
    "sg:postcode":"31787",
    "sg:province":"Niedersachsen",
    "wof:name":"Uwe Hornig",
    "wof:placetype":"venue"
},
  "geometry": {"coordinates":[9.3872900009,52.1557693481],"type":"Point"}
}