{
  "type": "Feature",
  "properties": {
    "iso:country":"DE",
    "sg:address":"Kaiser-Wilhelm-Str. 10",
    "sg:city":"Bad Kreuznach",
    "sg:phone":"+49 671/41896",
    "sg:postcode":"55543",
    "sg:province":"Rheinland-Pfalz",
    "wof:name":"E. Gr\u00e4ff",
    "wof:placetype":"venue"
},
  "geometry": {"coordinates":[7.853975,49.839775],"type":"Point"}
}