{
  "type": "Feature",
  "properties": {
    "iso:country":"DE",
    "sg:address":"Rotk\u00e4ppchenstr. 68a",
    "sg:city":"M\u00fcnchen",
    "sg:phone":"+49 89/6018427",
    "sg:postcode":"81739",
    "sg:province":"Bayern",
    "wof:name":"Dowie Und Dowie Rechtsanw\u00e4lte",
    "wof:placetype":"venue"
},
  "geometry": {"coordinates":[11.6580638885,48.0805740356],"type":"Point"}
}