{
  "type": "Feature",
  "properties": {
    "iso:country":"DE",
    "sg:address":"Larstr. 2a",
    "sg:city":"Troisdorf",
    "sg:phone":"+49 2241/404598",
    "sg:postcode":"53844",
    "sg:province":"Nordrhein-Westfalen",
    "wof:name":"Deutsche Shell Ag",
    "wof:placetype":"venue"
},
  "geometry": {"coordinates":[7.1306171417,50.8067779541],"type":"Point"}
}