{
  "type": "Feature",
  "properties": {
    "iso:country":"DE",
    "sg:address":"Alter Schulpfad 1",
    "sg:city":"Frankfurt",
    "sg:phone":"+49 69/38997782",
    "sg:postcode":"65934",
    "sg:province":"Hessen",
    "wof:name":"Peter Mende",
    "wof:placetype":"venue"
},
  "geometry": {"coordinates":[8.5650691986,50.0995101929],"type":"Point"}
}