{
  "type": "Feature",
  "properties": {
    "iso:country":"DE",
    "sg:address":"Hochstr. 17a",
    "sg:city":"Wuppertal",
    "sg:phone":"+49 202/300108",
    "sg:postcode":"42105",
    "sg:province":"Nordrhein-Westfalen",
    "wof:name":"Hans Busch",
    "wof:placetype":"venue"
},
  "geometry": {"coordinates":[7.1375288963,51.2622871399],"type":"Point"}
}