{
  "type": "Feature",
  "properties": {
    "iso:country":"DE",
    "sg:address":"Thalkirchner Str. 280",
    "sg:city":"M\u00fcnchen",
    "sg:phone":"+49 89/72308484",
    "sg:postcode":"81371",
    "sg:province":"Bayern",
    "wof:name":"B\u00fcro Design Und Raumausbau Christine Leutloff",
    "wof:placetype":"venue"
},
  "geometry": {"coordinates":[11.5448284149,48.1063041687],"type":"Point"}
}