{
  "type": "Feature",
  "properties": {
    "iso:country":"DE",
    "sg:address":"Konrad-Adenauer-Str. 50",
    "sg:city":"L\u00fcnen",
    "sg:phone":"+49 2306/72041",
    "sg:postcode":"44534",
    "sg:province":"Nordrhein-Westfalen",
    "wof:name":"Marien-apotheke E. Kfm.",
    "wof:placetype":"venue"
},
  "geometry": {"coordinates":[7.522842,51.61845],"type":"Point"}
}