{
  "type": "Feature",
  "properties": {
    "iso:country":"DE",
    "sg:address":"Stuttgarter Str. 59",
    "sg:city":"Welzheim",
    "sg:phone":"+49 7182/8846",
    "sg:postcode":"73642",
    "sg:province":"Baden-W\u00fcrttemberg",
    "wof:name":"R. Wiedmaier",
    "wof:placetype":"venue"
},
  "geometry": {"coordinates":[9.625702,48.857288],"type":"Point"}
}