{
  "type": "Feature",
  "properties": {
    "iso:country":"DE",
    "sg:address":"Gutenbergstr. 12",
    "sg:city":"Markdorf",
    "sg:phone":"+49 7544/2406",
    "sg:postcode":"88677",
    "sg:province":"Baden-W\u00fcrttemberg",
    "wof:name":"Otto Zurell",
    "wof:placetype":"venue"
},
  "geometry": {"coordinates":[9.387993,47.719543],"type":"Point"}
}