{
  "type": "Feature",
  "properties": {
    "iso:country":"DE",
    "sg:address":"Am Kreuzanger",
    "sg:city":"Berg",
    "sg:postcode":"82335",
    "sg:province":"Bayern",
    "wof:name":"Schumann Verlag Kg",
    "wof:placetype":"venue"
},
  "geometry": {"coordinates":[11.3509349823,47.9551086426],"type":"Point"}
}