{
  "type": "Feature",
  "properties": {
    "iso:country":"DE",
    "sg:address":"Georgi-Dimitroff-Str. 62",
    "sg:city":"Halle",
    "sg:phone":"+49 345/7705749",
    "sg:postcode":"06132",
    "sg:province":"Sachsen-Anhalt",
    "wof:name":"Jana Krause",
    "wof:placetype":"venue"
},
  "geometry": {"coordinates":[11.980169,51.428459],"type":"Point"}
}