{
  "type": "Feature",
  "properties": {
    "iso:country":"DE",
    "sg:address":"Am Kutschenbuck 10",
    "sg:city":"Langenfeld",
    "sg:phone":"+49 9164/542",
    "sg:postcode":"91474",
    "sg:province":"Bayern",
    "wof:name":"Franz Kg",
    "wof:placetype":"venue"
},
  "geometry": {"coordinates":[10.5161657333,49.6127128601],"type":"Point"}
}