{
  "type": "Feature",
  "properties": {
    "iso:country":"DE",
    "sg:address":"Winnender Str. 24",
    "sg:city":"Korb",
    "sg:phone":"+49 7151/36671",
    "sg:postcode":"71404",
    "sg:province":"Baden-W\u00fcrttemberg",
    "wof:name":"Metaxas",
    "wof:placetype":"venue"
},
  "geometry": {"coordinates":[9.3607788086,48.8429374695],"type":"Point"}
}