{
  "type": "Feature",
  "properties": {
    "iso:country":"DE",
    "sg:address":"Hugostr. 19",
    "sg:city":"Castrop-Rauxel",
    "sg:phone":"+49 2305/75277",
    "sg:postcode":"44579",
    "sg:province":"Nordrhein-Westfalen",
    "wof:name":"Werner Ostfeld",
    "wof:placetype":"venue"
},
  "geometry": {"coordinates":[7.3126049042,51.5864753723],"type":"Point"}
}