{
  "type": "Feature",
  "properties": {
    "iso:country":"DE",
    "sg:address":"Serbitz 28 b",
    "sg:city":"Treben",
    "sg:phone":"+49 34343/52356",
    "sg:postcode":"04617",
    "sg:province":"Th\u00fcringen",
    "wof:name":"Barbara Und J\u00f6rg Ebert",
    "wof:placetype":"venue"
},
  "geometry": {"coordinates":[12.4520158768,51.0644569397],"type":"Point"}
}