{
  "type": "Feature",
  "properties": {
    "iso:country":"DE",
    "sg:address":"M\u00fchlenweg 4",
    "sg:city":"Nortrup",
    "sg:phone":"+49 5436/427",
    "sg:postcode":"49638",
    "sg:province":"Niedersachsen",
    "wof:name":"Jagdhaus Spark",
    "wof:placetype":"venue"
},
  "geometry": {"coordinates":[7.8807711601,52.6040687561],"type":"Point"}
}