{
  "type": "Feature",
  "properties": {
    "iso:country":"DE",
    "sg:address":"Niedernkirchen",
    "sg:city":"Hebertsfelden",
    "sg:phone":"+49 8726/1407",
    "sg:postcode":"84332",
    "sg:province":"Bayern",
    "wof:name":"Gasthaus Kirchenwirt",
    "wof:placetype":"venue"
},
  "geometry": {"coordinates":[12.8094997406,48.4659881592],"type":"Point"}
}