{
  "type": "Feature",
  "properties": {
    "iso:country":"DE",
    "sg:address":"Steinbr\u00fcckenstr. 20",
    "sg:city":"Moers",
    "sg:phone":"+49 2841/24230",
    "sg:postcode":"47441",
    "sg:province":"Nordrhein-Westfalen",
    "wof:name":"M. Van Der Eyk",
    "wof:placetype":"venue"
},
  "geometry": {"coordinates":[6.599779,51.439487],"type":"Point"}
}