{
  "type": "Feature",
  "properties": {
    "iso:country":"DE",
    "sg:address":"K\u00f6nigsberger Str. 8-10",
    "sg:city":"Harpstedt",
    "sg:phone":"+49 4244/1004",
    "sg:postcode":"27243",
    "sg:province":"Niedersachsen",
    "wof:name":"Kunststofftechnik Harpstedt Gmbh",
    "wof:placetype":"venue"
},
  "geometry": {"coordinates":[8.597233,52.916458],"type":"Point"}
}