{
  "type": "Feature",
  "properties": {
    "iso:country":"DE",
    "sg:address":"Ottmerstr. 7",
    "sg:city":"Braunschweig",
    "sg:phone":"+49 531/75509",
    "sg:postcode":"38102",
    "sg:province":"Niedersachsen",
    "wof:name":"Baron Hebestedt & Kuhle Gmbh",
    "wof:placetype":"venue"
},
  "geometry": {"coordinates":[10.535446167,52.2568016052],"type":"Point"}
}