{
  "type": "Feature",
  "properties": {
    "iso:country":"DE",
    "sg:address":"Pl\u00f6ck 1",
    "sg:city":"Heidelberg",
    "sg:phone":"+49 6221/905700",
    "sg:postcode":"69117",
    "sg:province":"Baden-W\u00fcrttemberg",
    "wof:name":"Hotel Nassauer Hof",
    "wof:placetype":"venue"
},
  "geometry": {"coordinates":[8.6943187714,49.4089012146],"type":"Point"}
}