{
  "type": "Feature",
  "properties": {
    "iso:country":"DE",
    "sg:address":"Salinenstr. 19 -20",
    "sg:city":"Erfurt",
    "sg:phone":"+49 361/749730",
    "sg:postcode":"99086",
    "sg:province":"Th\u00fcringen",
    "wof:name":"Cornelia Hopf",
    "wof:placetype":"venue"
},
  "geometry": {"coordinates":[11.0284967422,51.0005836487],"type":"Point"}
}