{
  "type": "Feature",
  "properties": {
    "iso:country":"DE",
    "sg:address":"Fehrenbachallee 12",
    "sg:city":"Freiburg",
    "sg:postcode":"79106",
    "sg:province":"Baden-W\u00fcrttemberg",
    "wof:name":"Neue Messe Freiburg Beteiligungs Gmbh",
    "wof:placetype":"venue"
},
  "geometry": {"coordinates":[7.832994,48.000515],"type":"Point"}
}