{
  "type": "Feature",
  "properties": {
    "iso:country":"DE",
    "sg:address":"Lange Str. 71",
    "sg:city":"Cloppenburg",
    "sg:phone":"+49 4471/3552",
    "sg:postcode":"49661",
    "sg:province":"Niedersachsen",
    "wof:name":"Helmuth Korth Immobilienmakler",
    "wof:placetype":"venue"
},
  "geometry": {"coordinates":[8.0367803574,52.8441505432],"type":"Point"}
}