{
  "type": "Feature",
  "properties": {
    "iso:country":"DE",
    "sg:address":"Huttenstr. 84",
    "sg:city":"Halle",
    "sg:phone":"+49 345/4820086",
    "sg:postcode":"06110",
    "sg:province":"Sachsen-Anhalt",
    "wof:name":"Ornithologischer Verein Halle E. V.",
    "wof:placetype":"venue"
},
  "geometry": {"coordinates":[11.9793653488,51.4629096985],"type":"Point"}
}