{
  "type": "Feature",
  "properties": {
    "iso:country":"DE",
    "sg:address":"Petersberger Weg 26",
    "sg:city":"Thalfang",
    "sg:phone":"+49 6504/1550",
    "sg:postcode":"54424",
    "sg:province":"Rheinland-Pfalz",
    "wof:name":"Borgsm\u00fcller",
    "wof:placetype":"venue"
},
  "geometry": {"coordinates":[6.9926538467,49.7521438599],"type":"Point"}
}