{
  "type": "Feature",
  "properties": {
    "iso:country":"DE",
    "sg:address":"Breite Werl 33",
    "sg:city":"Salzkotten",
    "sg:phone":"+49 5258/7069",
    "sg:postcode":"33154",
    "sg:province":"Nordrhein-Westfalen",
    "wof:name":"Karl-josef Gerke Elektromeister",
    "wof:placetype":"venue"
},
  "geometry": {"coordinates":[8.599092,51.683304],"type":"Point"}
}