{
  "type": "Feature",
  "properties": {
    "iso:country":"DE",
    "sg:address":"Zedernstr. 14",
    "sg:city":"Ergoldsbach",
    "sg:phone":"+49 8771/1255",
    "sg:postcode":"84061",
    "sg:province":"Bayern",
    "wof:name":"O. K\u00f6nigbauer",
    "wof:placetype":"venue"
},
  "geometry": {"coordinates":[12.208313942,48.6971321106],"type":"Point"}
}