{
  "type": "Feature",
  "properties": {
    "iso:country":"DE",
    "sg:address":"Magnusstr. 13",
    "sg:city":"Kempten",
    "sg:phone":"+49 831/564969",
    "sg:postcode":"87437",
    "sg:province":"Bayern",
    "wof:name":"H. Rupp",
    "wof:placetype":"venue"
},
  "geometry": {"coordinates":[10.3294687271,47.7083511353],"type":"Point"}
}