{
  "type": "Feature",
  "properties": {
    "iso:country":"DE",
    "sg:address":"Landvogtstr. 3",
    "sg:city":"Augsburg",
    "sg:phone":"+49 821/404045",
    "sg:postcode":"86156",
    "sg:province":"Bayern",
    "wof:name":"Josef Manz",
    "wof:placetype":"venue"
},
  "geometry": {"coordinates":[10.8723459244,48.379283905],"type":"Point"}
}