{
  "type": "Feature",
  "properties": {
    "iso:country":"DE",
    "sg:address":"Richthofenstr. 51",
    "sg:city":"Hildesheim",
    "sg:phone":"+49 5121/510285",
    "sg:postcode":"31137",
    "sg:province":"Niedersachsen",
    "wof:name":"Wolfgang Krause",
    "wof:placetype":"venue"
},
  "geometry": {"coordinates":[9.950282,52.167248],"type":"Point"}
}