{
  "type": "Feature",
  "properties": {
    "iso:country":"DE",
    "sg:address":"Weberstr. 24",
    "sg:city":"Bocholt",
    "sg:phone":"+49 2871/15608",
    "sg:postcode":"46397",
    "sg:province":"Nordrhein-Westfalen",
    "wof:name":"S. \u00d6ztas",
    "wof:placetype":"venue"
},
  "geometry": {"coordinates":[6.6177158356,51.8413848877],"type":"Point"}
}