{
  "type": "Feature",
  "properties": {
    "iso:country":"DE",
    "sg:address":"Kemptener Str. 4",
    "sg:city":"Bad Gr\u00f6nenbach",
    "sg:phone":"+49 8334/222",
    "sg:postcode":"87730",
    "sg:province":"Bayern",
    "wof:name":"Erich Reisacher",
    "wof:placetype":"venue"
},
  "geometry": {"coordinates":[10.2226867676,47.8739585876],"type":"Point"}
}