{
  "type": "Feature",
  "properties": {
    "iso:country":"DE",
    "sg:address":"Siedenburger Str. 13",
    "sg:city":"Borstel",
    "sg:phone":"+49 4276/520",
    "sg:postcode":"27246",
    "sg:province":"Niedersachsen",
    "wof:name":"I. Niemeyer",
    "wof:placetype":"venue"
},
  "geometry": {"coordinates":[8.964275,52.672863],"type":"Point"}
}