{
  "type": "Feature",
  "properties": {
    "iso:country":"DE",
    "sg:address":"Am Forsthaus 5",
    "sg:city":"Hartmannsdorf",
    "sg:phone":"+49 37602/64829",
    "sg:postcode":"08107",
    "sg:province":"Sachsen",
    "wof:name":"B. Lorenz",
    "wof:placetype":"venue"
},
  "geometry": {"coordinates":[12.543375,50.576267],"type":"Point"}
}