{
  "type": "Feature",
  "properties": {
    "iso:country":"DE",
    "sg:address":"Hofackerweg 51",
    "sg:city":"Schwabach",
    "sg:phone":"+49 911/6370912",
    "sg:postcode":"91126",
    "sg:province":"Bayern",
    "wof:name":"Immobilien Mau\u00dfner-verge Gmbh",
    "wof:placetype":"venue"
},
  "geometry": {"coordinates":[11.0227975845,49.3598403931],"type":"Point"}
}