{
  "type": "Feature",
  "properties": {
    "iso:country":"DE",
    "sg:address":"Wenzlower Str. 1b",
    "sg:city":"Wollin",
    "sg:phone":"+49 33833/70220",
    "sg:postcode":"14778",
    "sg:province":"Brandenburg",
    "wof:name":"M\u00fcller Bau Gmbh",
    "wof:placetype":"venue"
},
  "geometry": {"coordinates":[12.466366,52.285423],"type":"Point"}
}