{
  "type": "Feature",
  "properties": {
    "iso:country":"DE",
    "sg:address":"Paul-Maurer-Str.",
    "sg:city":"Viechtach",
    "sg:postcode":"94234",
    "sg:province":"Bayern",
    "wof:name":"Aktiv-markt",
    "wof:placetype":"venue"
},
  "geometry": {"coordinates":[12.8842201233,49.0821914673],"type":"Point"}
}