{
  "type": "Feature",
  "properties": {
    "iso:country":"DE",
    "sg:address":"Neuer Weg 27",
    "sg:city":"Altenweddingen",
    "sg:phone":"+49 39205/9236",
    "sg:postcode":"39171",
    "sg:province":"Sachsen-Anhalt",
    "wof:name":"Moderne Bauelemente Gmbh & Co.",
    "wof:placetype":"venue"
},
  "geometry": {"coordinates":[11.526201,51.995964],"type":"Point"}
}