{
  "type": "Feature",
  "properties": {
    "iso:country":"DE",
    "sg:address":"Schulthei\u00dfwies 5",
    "sg:city":"Boppard",
    "sg:phone":"+49 6742/4706",
    "sg:postcode":"56154",
    "sg:province":"Rheinland-Pfalz",
    "wof:name":"Holtey",
    "wof:placetype":"venue"
},
  "geometry": {"coordinates":[7.6424942017,50.1621780396],"type":"Point"}
}