{
  "type": "Feature",
  "properties": {
    "iso:country":"DE",
    "sg:address":"Hohenzollernstr. 17",
    "sg:city":"Hannover",
    "sg:phone":"+49 511/343666",
    "sg:postcode":"30161",
    "sg:province":"Niedersachsen",
    "wof:name":"Dr. C. Voges Rechtsanwalt",
    "wof:placetype":"venue"
},
  "geometry": {"coordinates":[9.7554721832,52.3807792664],"type":"Point"}
}