{
  "type": "Feature",
  "properties": {
    "iso:country":"DE",
    "sg:address":"Kronprinzenstr. 29",
    "sg:city":"Pforzheim",
    "sg:phone":"+49 7231/32769",
    "sg:postcode":"75177",
    "sg:province":"Baden-W\u00fcrttemberg",
    "wof:name":"Vallon & K\u00fchn",
    "wof:placetype":"venue"
},
  "geometry": {"coordinates":[8.7000074387,48.8953514099],"type":"Point"}
}