{
  "type": "Feature",
  "properties": {
    "iso:country":"DE",
    "sg:address":"Hammerbruch 3",
    "sg:city":"Sonsbeck",
    "sg:phone":"+49 170 4308725",
    "sg:postcode":"47665",
    "sg:province":"Nordrhein-Westfalen",
    "wof:name":"Anlagenbau 24",
    "wof:placetype":"venue"
},
  "geometry": {"coordinates":[6.382089138,51.6132698059],"type":"Point"}
}