{
  "type": "Feature",
  "properties": {
    "iso:country":"DE",
    "sg:address":"Schmarsauer Str. 9",
    "sg:city":"Dannenberg",
    "sg:phone":"+49 5861/7708",
    "sg:postcode":"29451",
    "sg:province":"Niedersachsen",
    "wof:name":"Rudolf Elvers",
    "wof:placetype":"venue"
},
  "geometry": {"coordinates":[11.0614557266,53.0867958069],"type":"Point"}
}