{
  "type": "Feature",
  "properties": {
    "iso:country":"DE",
    "sg:address":"Bahnhofstr. 7",
    "sg:city":"Dippoldiswalde",
    "sg:postcode":"01744",
    "sg:province":"Sachsen",
    "wof:name":"He\u00df & Co. Gmbh",
    "wof:placetype":"venue"
},
  "geometry": {"coordinates":[13.666151,50.894291],"type":"Point"}
}