{
  "type": "Feature",
  "properties": {
    "iso:country":"DE",
    "sg:address":"Saalstr. 44",
    "sg:city":"Saalfeld",
    "sg:phone":"+49 3671/2732",
    "sg:postcode":"07318",
    "sg:province":"Th\u00fcringen",
    "wof:name":"Hotel Weltrich",
    "wof:placetype":"venue"
},
  "geometry": {"coordinates":[11.3646936417,50.6492576599],"type":"Point"}
}