{
  "type": "Feature",
  "properties": {
    "iso:country":"DE",
    "sg:address":"Liebigstr. 19",
    "sg:city":"W\u00fcrzburg",
    "sg:phone":"+49 931/91646",
    "sg:postcode":"97080",
    "sg:province":"Bayern",
    "wof:name":"L.-c. F\u00f6rster Bildhauer",
    "wof:placetype":"venue"
},
  "geometry": {"coordinates":[9.9279212952,49.8203353882],"type":"Point"}
}