{
  "type": "Feature",
  "properties": {
    "iso:country":"DE",
    "sg:address":"Bachg\u00e4\u00dfle 12",
    "sg:city":"Ebersbach",
    "sg:phone":"+49 7163/7527",
    "sg:postcode":"73061",
    "sg:province":"Baden-W\u00fcrttemberg",
    "wof:name":"Otto Buchele",
    "wof:placetype":"venue"
},
  "geometry": {"coordinates":[9.522258,48.716167],"type":"Point"}
}