{
  "type": "Feature",
  "properties": {
    "iso:country":"DE",
    "sg:address":"R\u00f6merstr. 22 B",
    "sg:city":"Weilheim",
    "sg:phone":"+49 881/3360",
    "sg:postcode":"82362",
    "sg:province":"Bayern",
    "wof:name":"Max M\u00fcller",
    "wof:placetype":"venue"
},
  "geometry": {"coordinates":[11.1530399323,47.8433303833],"type":"Point"}
}