{
  "type": "Feature",
  "properties": {
    "iso:country":"DE",
    "sg:address":"Dresdener Str. 6",
    "sg:city":"Minden",
    "sg:phone":"+49 571/3201710",
    "sg:postcode":"32423",
    "sg:province":"Nordrhein-Westfalen",
    "wof:name":"Rolf We\u00dfling Finanzberater",
    "wof:placetype":"venue"
},
  "geometry": {"coordinates":[8.9678049088,52.308052063],"type":"Point"}
}