{
  "type": "Feature",
  "properties": {
    "iso:country":"DE",
    "sg:address":"Halker Zeile 83a",
    "sg:city":"Berlin",
    "sg:postcode":"12305",
    "sg:province":"Berlin",
    "wof:name":"Dr. Hans-j\u00f6rg Leuchte Immobilien Und Beteiligungen",
    "wof:placetype":"venue"
},
  "geometry": {"coordinates":[13.3983602524,52.404258728],"type":"Point"}
}