{
  "type": "Feature",
  "properties": {
    "iso:country":"DE",
    "sg:address":"Hauptstr. 15",
    "sg:city":"Ihrlerstein",
    "sg:phone":"+49 9441/7432",
    "sg:postcode":"93346",
    "sg:province":"Bayern",
    "wof:name":"Raiffeisenbank Bad Abbach-saal Eg",
    "wof:placetype":"venue"
},
  "geometry": {"coordinates":[11.863372,48.938763],"type":"Point"}
}