{
  "type": "Feature",
  "properties": {
    "iso:country":"DE",
    "sg:address":"Poststr. 3",
    "sg:city":"Neuerburg",
    "sg:phone":"+49 6564/4767",
    "sg:postcode":"54673",
    "sg:province":"Rheinland-Pfalz",
    "wof:name":"Baumarkt Klinkhammer Beteiligungs Gmbh",
    "wof:placetype":"venue"
},
  "geometry": {"coordinates":[6.291386,50.013325],"type":"Point"}
}