{
  "type": "Feature",
  "properties": {
    "iso:country":"DE",
    "sg:address":"Otto-Hahn-Str 18",
    "sg:city":"Ettlingen",
    "sg:phone":"+49 6172/910",
    "sg:postcode":"76275",
    "sg:province":"Baden-W\u00fcrttemberg",
    "wof:name":"Start Amadeus Gmbh",
    "wof:placetype":"venue"
},
  "geometry": {"coordinates":[8.620652,50.221928],"type":"Point"}
}