{
  "type": "Feature",
  "properties": {
    "iso:country":"DE",
    "sg:address":"Am Zwieback 3",
    "sg:city":"Sersheim",
    "sg:phone":"+49 7042/840904",
    "sg:postcode":"74372",
    "sg:province":"Baden-W\u00fcrttemberg",
    "wof:name":"K\u00fcbler Internet-service",
    "wof:placetype":"venue"
},
  "geometry": {"coordinates":[9.0203819275,48.9620780945],"type":"Point"}
}