{
  "type": "Feature",
  "properties": {
    "iso:country":"DE",
    "sg:address":"Kerststr. 9-13",
    "sg:city":"Kaiserslautern",
    "sg:postcode":"67655",
    "sg:province":"Rheinland-Pfalz",
    "wof:name":"R. Gondrom Verwaltungs- Gmbh",
    "wof:placetype":"venue"
},
  "geometry": {"coordinates":[7.7687110901,49.4428024292],"type":"Point"}
}