{
  "type": "Feature",
  "properties": {
    "iso:country":"DE",
    "sg:address":"Coburger Str. 122",
    "sg:city":"Weitramsdorf",
    "sg:phone":"+49 9561/30716",
    "sg:postcode":"96479",
    "sg:province":"Bayern",
    "wof:name":"Horst Treibig",
    "wof:placetype":"venue"
},
  "geometry": {"coordinates":[10.9040203094,50.2648658752],"type":"Point"}
}