{
  "type": "Feature",
  "properties": {
    "iso:country":"DE",
    "sg:address":"Ringstr. 30",
    "sg:city":"Ranstadt",
    "sg:phone":"+49 6041/820281",
    "sg:postcode":"63691",
    "sg:province":"Hessen",
    "wof:name":"Dr. Med. Heike H\u00e4fner-see \u00c4rztin F\u00fcr Allgemeinmedizin",
    "wof:placetype":"venue"
},
  "geometry": {"coordinates":[8.978852272,50.3557014465],"type":"Point"}
}