{
  "type": "Feature",
  "properties": {
    "iso:country":"DE",
    "sg:address":"Sporbecker Weg 13",
    "sg:city":"Hagen",
    "sg:phone":"+49 2331/305962",
    "sg:postcode":"58089",
    "sg:province":"Nordrhein-Westfalen",
    "wof:name":"Werner Grass Holzbau Gmbh",
    "wof:placetype":"venue"
},
  "geometry": {"coordinates":[7.444023,51.384567],"type":"Point"}
}