{
  "type": "Feature",
  "properties": {
    "iso:country":"DE",
    "sg:address":"Altenbochumer Str. 43",
    "sg:city":"Bochum",
    "sg:phone":"+49 234/350156",
    "sg:postcode":"44803",
    "sg:province":"Nordrhein-Westfalen",
    "wof:name":"Dickhoff Werkst\u00e4tten Gmbh",
    "wof:placetype":"venue"
},
  "geometry": {"coordinates":[7.24041605,51.4760818481],"type":"Point"}
}