{
  "type": "Feature",
  "properties": {
    "iso:country":"DE",
    "sg:address":"Lindenau 77",
    "sg:city":"Issum",
    "sg:phone":"+49 2835/2013",
    "sg:postcode":"47661",
    "sg:province":"Nordrhein-Westfalen",
    "wof:name":"Schneider & Klippel Kg",
    "wof:placetype":"venue"
},
  "geometry": {"coordinates":[6.4218401909,51.5455093384],"type":"Point"}
}