{
  "type": "Feature",
  "properties": {
    "iso:country":"DE",
    "sg:address":"Im Kirchtal 28",
    "sg:city":"Troisdorf",
    "sg:phone":"+49 2241/41912",
    "sg:postcode":"53844",
    "sg:province":"Nordrhein-Westfalen",
    "wof:name":"Werner Pfeiffer-floristen- Dekorationsbedarf Gmbh",
    "wof:placetype":"venue"
},
  "geometry": {"coordinates":[7.119689,50.795147],"type":"Point"}
}