{
  "type": "Feature",
  "properties": {
    "iso:country":"DE",
    "sg:address":"An der Holl 1",
    "sg:city":"Asbach",
    "sg:postcode":"53567",
    "sg:province":"Rheinland-Pfalz",
    "wof:name":"Katzen Vom Andree Hof",
    "wof:placetype":"venue"
},
  "geometry": {"coordinates":[7.408854,50.648552],"type":"Point"}
}