{
  "type": "Feature",
  "properties": {
    "iso:country":"DE",
    "sg:address":"Ingrimstr. 8",
    "sg:city":"Heidelberg",
    "sg:phone":"+49 6221/162738",
    "sg:postcode":"69117",
    "sg:province":"Baden-W\u00fcrttemberg",
    "wof:name":"Gisela Fuchs Architektin",
    "wof:placetype":"venue"
},
  "geometry": {"coordinates":[8.709357,49.41116],"type":"Point"}
}