{
  "type": "Feature",
  "properties": {
    "iso:country":"DE",
    "sg:address":"Mittelstr. 39",
    "sg:city":"Kl\u00fcsserath",
    "sg:phone":"+49 6507/4636",
    "sg:postcode":"54340",
    "sg:province":"Rheinland-Pfalz",
    "wof:name":"Franz-josef Regnery",
    "wof:placetype":"venue"
},
  "geometry": {"coordinates":[6.8523187637,49.8439788818],"type":"Point"}
}