{
  "type": "Feature",
  "properties": {
    "iso:country":"DE",
    "sg:address":"Delitzscher Str. 47",
    "sg:city":"Halle",
    "sg:phone":"+49 345/5600933",
    "sg:postcode":"06112",
    "sg:province":"Sachsen-Anhalt",
    "wof:name":"Befa Behinderten- Kfz-vertrieb Horst Wolf",
    "wof:placetype":"venue"
},
  "geometry": {"coordinates":[11.9977941513,51.4790077209],"type":"Point"}
}