{
  "type": "Feature",
  "properties": {
    "iso:country":"DE",
    "sg:address":"Londorfer Str. 31",
    "sg:city":"Gr\u00fcnberg",
    "sg:phone":"+49 6401/6394",
    "sg:postcode":"35305",
    "sg:province":"Hessen",
    "wof:name":"F. Kurth Steuerberater",
    "wof:placetype":"venue"
},
  "geometry": {"coordinates":[8.9579267502,50.594329834],"type":"Point"}
}