{
  "type": "Feature",
  "properties": {
    "iso:country":"DE",
    "sg:address":"Ottensteiner Str. 5",
    "sg:city":"Vreden",
    "sg:phone":"+49 2564/2599",
    "sg:postcode":"48691",
    "sg:province":"Nordrhein-Westfalen",
    "wof:name":"Erich Schwering",
    "wof:placetype":"venue"
},
  "geometry": {"coordinates":[6.8286662102,52.0362243652],"type":"Point"}
}