{
  "type": "Feature",
  "properties": {
    "iso:country":"DE",
    "sg:address":"Friedrichstr.",
    "sg:city":"Knittlingen",
    "sg:phone":"+49 7043/33367",
    "sg:postcode":"75438",
    "sg:province":"Baden-W\u00fcrttemberg",
    "wof:name":"Lidl-markt",
    "wof:placetype":"venue"
},
  "geometry": {"coordinates":[8.7608346939,49.0232200623],"type":"Point"}
}