{
  "type": "Feature",
  "properties": {
    "iso:country":"DE",
    "sg:address":"Bauhof 383b",
    "sg:city":"Neustrelitz",
    "sg:phone":"+49 3981/447710",
    "sg:postcode":"17235",
    "sg:province":"Mecklenburg-Vorpommern",
    "wof:name":"Bauhof Altrelitz Gmbh",
    "wof:placetype":"venue"
},
  "geometry": {"coordinates":[13.098684,53.327824],"type":"Point"}
}