{
  "type": "Feature",
  "properties": {
    "iso:country":"DE",
    "sg:address":"An Der Stadtautobahn 1",
    "sg:city":"Rostock",
    "sg:phone":"+49 4922/029580",
    "sg:postcode":"18069",
    "sg:province":"Mecklenburg-Vorpommern",
    "wof:name":"Deuta-werke Gmbh",
    "wof:placetype":"venue"
},
  "geometry": {"coordinates":[7.117153,50.994663],"type":"Point"}
}