{
  "type": "Feature",
  "properties": {
    "iso:country":"DE",
    "sg:address":"Max-Beckmann-Str. 23",
    "sg:city":"M\u00fcnchen",
    "sg:postcode":"81735",
    "sg:province":"Bayern",
    "wof:name":"Vautec Vertriebs- Und Verwaltungs-gmbh",
    "wof:placetype":"venue"
},
  "geometry": {"coordinates":[11.6517047882,48.1113815308],"type":"Point"}
}