{
  "type": "Feature",
  "properties": {
    "iso:country":"DE",
    "sg:address":"Arnoldusstr. 65",
    "sg:city":"D\u00fcren",
    "sg:phone":"+49 2421/32351",
    "sg:postcode":"52353",
    "sg:province":"Nordrhein-Westfalen",
    "wof:name":"E. Keller",
    "wof:placetype":"venue"
},
  "geometry": {"coordinates":[6.4872050285,50.8379516602],"type":"Point"}
}