{
  "type": "Feature",
  "properties": {
    "iso:country":"DE",
    "sg:address":"Steinbruchsweg 5",
    "sg:city":"Hungen",
    "sg:phone":"+49 6402/1515",
    "sg:postcode":"35410",
    "sg:province":"Hessen",
    "wof:name":"Haus Versicherungsb\u00fcro",
    "wof:placetype":"venue"
},
  "geometry": {"coordinates":[8.953289032,50.4699211121],"type":"Point"}
}