{
  "type": "Feature",
  "properties": {
    "iso:country":"DE",
    "sg:address":"Schneebruch 12",
    "sg:city":"Iserlohn",
    "sg:phone":"+49 2371/41603",
    "sg:postcode":"58640",
    "sg:province":"Nordrhein-Westfalen",
    "wof:name":"Johann Baki",
    "wof:placetype":"venue"
},
  "geometry": {"coordinates":[7.7163977623,51.4259376526],"type":"Point"}
}