{
  "type": "Feature",
  "properties": {
    "iso:country":"DE",
    "sg:address":"H\u00f6fener Str. 16",
    "sg:city":"Neuenb\u00fcrg",
    "sg:phone":"+49 7082/943390",
    "sg:postcode":"75305",
    "sg:province":"Baden-W\u00fcrttemberg",
    "wof:name":"Werner Eickele Finanzberater",
    "wof:placetype":"venue"
},
  "geometry": {"coordinates":[8.6070289612,48.831363678],"type":"Point"}
}