{
  "type": "Feature",
  "properties": {
    "iso:country":"DE",
    "sg:address":"Residenzstr. 16",
    "sg:city":"M\u00fcnchen",
    "sg:phone":"+49 89/224166",
    "sg:postcode":"80333",
    "sg:province":"Bayern",
    "wof:name":"Max Dietl Haute Couture Gmbh & Co. Kg",
    "wof:placetype":"venue"
},
  "geometry": {"coordinates":[11.577334,48.139999],"type":"Point"}
}