{
  "type": "Feature",
  "properties": {
    "iso:country":"DE",
    "sg:address":"Westerbuchberg 98",
    "sg:city":"\u00dcbersee",
    "sg:phone":"+49 8642/955",
    "sg:postcode":"83236",
    "sg:province":"Bayern",
    "wof:name":"Chiemton Gmbh",
    "wof:placetype":"venue"
},
  "geometry": {"coordinates":[12.4658899307,47.809551239],"type":"Point"}
}