{
  "type": "Feature",
  "properties": {
    "iso:country":"DE",
    "sg:address":"Friederikenstr. 112",
    "sg:city":"Papenburg",
    "sg:postcode":"26871",
    "sg:province":"Niedersachsen",
    "wof:name":"Ab-medical Gmbh",
    "wof:placetype":"venue"
},
  "geometry": {"coordinates":[7.380609,53.072922],"type":"Point"}
}