{
  "type": "Feature",
  "properties": {
    "iso:country":"DE",
    "sg:address":"Lange Str. 15",
    "sg:city":"Geldern",
    "sg:phone":"+49 2838/77755",
    "sg:postcode":"47608",
    "sg:province":"Nordrhein-Westfalen",
    "wof:name":"Drei Kronen Hof",
    "wof:placetype":"venue"
},
  "geometry": {"coordinates":[6.3314800262,51.5197181702],"type":"Point"}
}