{
  "type": "Feature",
  "properties": {
    "iso:country":"DE",
    "sg:address":"In der Loge 3",
    "sg:city":"Westerstede",
    "sg:phone":"+49 4488/4488",
    "sg:postcode":"26655",
    "sg:province":"Niedersachsen",
    "wof:name":"G. Warntjen",
    "wof:placetype":"venue"
},
  "geometry": {"coordinates":[7.8753728867,53.2382087708],"type":"Point"}
}