{
  "type": "Feature",
  "properties": {
    "iso:country":"DE",
    "sg:address":"Dorfstr.",
    "sg:city":"Beggerow",
    "sg:phone":"+49 39996/70317",
    "sg:postcode":"17111",
    "sg:province":"Mecklenburg-Vorpommern",
    "wof:name":"Beggerower Landgut Gmbh & Co. Kg",
    "wof:placetype":"venue"
},
  "geometry": {"coordinates":[13.0556106567,53.828037262],"type":"Point"}
}