{
  "type": "Feature",
  "properties": {
    "iso:country":"DE",
    "sg:address":"Hauptstr. 38",
    "sg:city":"Steinweiler",
    "sg:phone":"+49 6349/6383",
    "sg:postcode":"76872",
    "sg:province":"Rheinland-Pfalz",
    "wof:name":"Gemeindeb\u00fccherei",
    "wof:placetype":"venue"
},
  "geometry": {"coordinates":[8.141562,49.122482],"type":"Point"}
}