{
  "type": "Feature",
  "properties": {
    "iso:country":"DE",
    "sg:address":"L\u00f6wenplatz 9",
    "sg:city":"Weingarten",
    "sg:phone":"+49 751/42118",
    "sg:postcode":"88250",
    "sg:province":"Baden-W\u00fcrttemberg",
    "wof:name":"Central-reiseb\u00fcro",
    "wof:placetype":"venue"
},
  "geometry": {"coordinates":[9.6399068832,47.8070220947],"type":"Point"}
}