{
  "type": "Feature",
  "properties": {
    "iso:country":"DE",
    "sg:address":"Holzstr. 14",
    "sg:city":"Oberhausen",
    "sg:phone":"+49 208/680169",
    "sg:postcode":"46147",
    "sg:province":"Nordrhein-Westfalen",
    "wof:name":"Thomas Ruiling Gmbh",
    "wof:placetype":"venue"
},
  "geometry": {"coordinates":[6.8006148338,51.5290031433],"type":"Point"}
}