{
  "type": "Feature",
  "properties": {
    "iso:country":"DE",
    "sg:address":"\u00d6hrigstr. 12",
    "sg:city":"Creuzburg",
    "sg:phone":"+49 36926/90004",
    "sg:postcode":"99831",
    "sg:province":"Th\u00fcringen",
    "wof:name":"E. Bremer Immobilienmakler",
    "wof:placetype":"venue"
},
  "geometry": {"coordinates":[10.2500553131,51.0544281006],"type":"Point"}
}