{
  "type": "Feature",
  "properties": {
    "iso:country":"DE",
    "sg:address":"Augsburger Str. 37",
    "sg:city":"Memmingen",
    "sg:phone":"+49 8331/2377",
    "sg:postcode":"87700",
    "sg:province":"Bayern",
    "wof:name":"Hans Erhard Finanzberater",
    "wof:placetype":"venue"
},
  "geometry": {"coordinates":[10.1940717697,47.9886894226],"type":"Point"}
}