{
  "type": "Feature",
  "properties": {
    "iso:country":"DE",
    "sg:address":"Prielmayerstr. 12",
    "sg:city":"Friedrichshafen",
    "sg:phone":"+49 7541/370015",
    "sg:postcode":"88045",
    "sg:province":"Baden-W\u00fcrttemberg",
    "wof:name":"Isis - Gesundheit Sch\u00f6nheit Wellness Gmbh",
    "wof:placetype":"venue"
},
  "geometry": {"coordinates":[9.4752702713,47.6578521729],"type":"Point"}
}