{
  "type": "Feature",
  "properties": {
    "iso:country":"DE",
    "sg:address":"Dorfstr. 28",
    "sg:city":"Jesewitz",
    "sg:phone":"+49 34241/50674",
    "sg:postcode":"04838",
    "sg:province":"Sachsen",
    "wof:name":"A. Schmidtchen",
    "wof:placetype":"venue"
},
  "geometry": {"coordinates":[12.513649,51.435314],"type":"Point"}
}