{
  "type": "Feature",
  "properties": {
    "iso:country":"DE",
    "sg:address":"Altenessener Str. 392",
    "sg:city":"Essen",
    "sg:phone":"+49 201/341151",
    "sg:postcode":"45329",
    "sg:province":"Nordrhein-Westfalen",
    "wof:name":"Assindia-apotheke J\u00f6rg Werner E. K.",
    "wof:placetype":"venue"
},
  "geometry": {"coordinates":[7.008298,51.497231],"type":"Point"}
}