{
  "type": "Feature",
  "properties": {
    "iso:country":"DE",
    "sg:address":"Albtalstr. 3",
    "sg:city":"Weilheim",
    "sg:phone":"+49 7755/8167",
    "sg:postcode":"79809",
    "sg:province":"Baden-W\u00fcrttemberg",
    "wof:name":"A. Hilpert",
    "wof:placetype":"venue"
},
  "geometry": {"coordinates":[8.1557292938,47.6781654358],"type":"Point"}
}