{
  "type": "Feature",
  "properties": {
    "iso:country":"DE",
    "sg:address":"Hauptstr. 75",
    "sg:city":"Neustadt",
    "sg:phone":"+49 6321/929170",
    "sg:postcode":"67433",
    "sg:province":"Rheinland-Pfalz",
    "wof:name":"Dm-drogerie Markt Gmbh & Co. Kg",
    "wof:placetype":"venue"
},
  "geometry": {"coordinates":[8.13662,49.352894],"type":"Point"}
}