{
  "type": "Feature",
  "properties": {
    "iso:country":"DE",
    "sg:address":"Heidkantweg 199",
    "sg:city":"Haltern",
    "sg:phone":"+49 2360/10011",
    "sg:postcode":"45721",
    "sg:province":"Nordrhein-Westfalen",
    "wof:name":"A. B\u00fcning",
    "wof:placetype":"venue"
},
  "geometry": {"coordinates":[7.068779,51.708073],"type":"Point"}
}