{
  "type": "Feature",
  "properties": {
    "iso:country":"DE",
    "sg:address":"Kirchplatz 2",
    "sg:city":"Pullach",
    "sg:phone":"+49 89/7934634",
    "sg:postcode":"82049",
    "sg:province":"Bayern",
    "wof:name":"Eduard Flo\u00df Ingenieur",
    "wof:placetype":"venue"
},
  "geometry": {"coordinates":[11.523467,48.056309],"type":"Point"}
}