{
  "type": "Feature",
  "properties": {
    "iso:country":"DE",
    "sg:address":"Marktstr. 31",
    "sg:city":"Greven",
    "sg:phone":"+49 2571/2202",
    "sg:postcode":"48268",
    "sg:province":"Nordrhein-Westfalen",
    "wof:name":"A. Sch\u00fcrhaus",
    "wof:placetype":"venue"
},
  "geometry": {"coordinates":[7.611311,52.094685],"type":"Point"}
}