{
  "type": "Feature",
  "properties": {
    "iso:country":"DE",
    "sg:address":"Gartenfeldstr. 20",
    "sg:city":"Trier",
    "sg:phone":"+49 651/975370",
    "sg:postcode":"54295",
    "sg:province":"Rheinland-Pfalz",
    "wof:name":"Heiko Schichel Finanzberater",
    "wof:placetype":"venue"
},
  "geometry": {"coordinates":[6.6486649513,49.7530708313],"type":"Point"}
}