{
  "type": "Feature",
  "properties": {
    "iso:country":"DE",
    "sg:address":"Nordstr. 35",
    "sg:city":"Leipzig",
    "sg:phone":"+49 341/5648222",
    "sg:postcode":"04105",
    "sg:province":"Sachsen",
    "wof:name":"K.-k. Volkmar",
    "wof:placetype":"venue"
},
  "geometry": {"coordinates":[12.374387,51.348381],"type":"Point"}
}