{
  "type": "Feature",
  "properties": {
    "iso:country":"DE",
    "sg:address":"Hauptstr. 59",
    "sg:city":"Niederhorbach",
    "sg:phone":"+49 6343/1432",
    "sg:postcode":"76889",
    "sg:province":"Rheinland-Pfalz",
    "wof:name":"Willi Gander",
    "wof:placetype":"venue"
},
  "geometry": {"coordinates":[8.033729,49.115986],"type":"Point"}
}