{
  "type": "Feature",
  "properties": {
    "iso:country":"DE",
    "sg:address":"Hochbruckerstr. 2",
    "sg:city":"Donauw\u00f6rth",
    "sg:phone":"+49 906/8095",
    "sg:postcode":"86609",
    "sg:province":"Bayern",
    "wof:name":"Hotel Zm Deutschmeister",
    "wof:placetype":"venue"
},
  "geometry": {"coordinates":[10.7922315598,48.7349510193],"type":"Point"}
}