{
  "type": "Feature",
  "properties": {
    "iso:country":"DE",
    "sg:address":"Brahmsstr. 5",
    "sg:city":"Bargteheide",
    "sg:phone":"+49 4532/3887",
    "sg:postcode":"22941",
    "sg:province":"Schleswig-Holstein",
    "wof:name":"Handelsvertretungen A.matzdorf",
    "wof:placetype":"venue"
},
  "geometry": {"coordinates":[10.2714700699,53.7277374268],"type":"Point"}
}