{
  "type": "Feature",
  "properties": {
    "iso:country":"DE",
    "sg:address":"Bergstr. 20",
    "sg:city":"Trogen",
    "sg:phone":"+49 9281/43515",
    "sg:postcode":"95183",
    "sg:province":"Bayern",
    "wof:name":"Alfred Krau\u00df",
    "wof:placetype":"venue"
},
  "geometry": {"coordinates":[11.959572,50.361755],"type":"Point"}
}