{
  "type": "Feature",
  "properties": {
    "iso:country":"DE",
    "sg:address":"Siemensstr. 9",
    "sg:city":"Rutesheim",
    "sg:phone":"+49 7152/52117",
    "sg:postcode":"71277",
    "sg:province":"Baden-W\u00fcrttemberg",
    "wof:name":"Gerhard Stahl",
    "wof:placetype":"venue"
},
  "geometry": {"coordinates":[8.958161,48.811131],"type":"Point"}
}