{
  "type": "Feature",
  "properties": {
    "iso:country":"DE",
    "sg:address":"Kohlh\u00e4user Str. 111",
    "sg:city":"Fulda",
    "sg:postcode":"36043",
    "sg:province":"Hessen",
    "wof:name":"Sucor Kork & Holz Handelsgesellschaft Mbh",
    "wof:placetype":"venue"
},
  "geometry": {"coordinates":[9.6827077866,50.5290374756],"type":"Point"}
}