{
  "type": "Feature",
  "properties": {
    "iso:country":"DE",
    "sg:address":"Pfarrgasse 15",
    "sg:city":"Gr\u00fcndau",
    "sg:phone":"+49 6058/90030",
    "sg:postcode":"63584",
    "sg:province":"Hessen",
    "wof:name":"Seniorenpension",
    "wof:placetype":"venue"
},
  "geometry": {"coordinates":[9.142393,50.243015],"type":"Point"}
}