{
  "type": "Feature",
  "properties": {
    "iso:country":"DE",
    "sg:address":"Langgasse 70",
    "sg:city":"Dausenau",
    "sg:phone":"+49 2603/96090",
    "sg:postcode":"56132",
    "sg:province":"Rheinland-Pfalz",
    "wof:name":"Optimed Medizintechnik",
    "wof:placetype":"venue"
},
  "geometry": {"coordinates":[7.762026,50.333549],"type":"Point"}
}