{
  "type": "Feature",
  "properties": {
    "iso:country":"DE",
    "sg:address":"Friedhofstr. 9",
    "sg:city":"Hatzfeld",
    "sg:phone":"+49 6467/258",
    "sg:postcode":"35116",
    "sg:province":"Hessen",
    "wof:name":"Otto Gro\u00df",
    "wof:placetype":"venue"
},
  "geometry": {"coordinates":[8.549229,50.986038],"type":"Point"}
}