{
  "type": "Feature",
  "properties": {
    "iso:country":"DE",
    "sg:address":"Tannenstr. 1",
    "sg:city":"Weinheim",
    "sg:phone":"+49 6201/64214",
    "sg:postcode":"69469",
    "sg:province":"Baden-W\u00fcrttemberg",
    "wof:name":"F. Wolf",
    "wof:placetype":"venue"
},
  "geometry": {"coordinates":[8.674693,49.551865],"type":"Point"}
}