{
  "type": "Feature",
  "properties": {
    "iso:country":"DE",
    "sg:address":"H\u00f6ftenkamp 7",
    "sg:city":"Haren",
    "sg:phone":"+49 5932/4957",
    "sg:postcode":"49733",
    "sg:province":"Niedersachsen",
    "wof:name":"Karl Heinz Velthaus",
    "wof:placetype":"venue"
},
  "geometry": {"coordinates":[7.235077858,52.7950210571],"type":"Point"}
}