{
  "type": "Feature",
  "properties": {
    "iso:country":"DE",
    "sg:address":"Ettishofer Str. 10",
    "sg:city":"Weingarten",
    "sg:phone":"+49 751/553770",
    "sg:postcode":"88250",
    "sg:province":"Baden-W\u00fcrttemberg",
    "wof:name":"Elosoft Systemtechnik Gmbh",
    "wof:placetype":"venue"
},
  "geometry": {"coordinates":[9.632677,47.812969],"type":"Point"}
}