{
  "type": "Feature",
  "properties": {
    "iso:country":"DE",
    "sg:address":"Rotdornweg 3",
    "sg:city":"Horneburg",
    "sg:phone":"+49 4163/82074",
    "sg:postcode":"21640",
    "sg:province":"Niedersachsen",
    "wof:name":"A. Und R. Pauls",
    "wof:placetype":"venue"
},
  "geometry": {"coordinates":[9.5673732758,53.5067977905],"type":"Point"}
}