{
  "type": "Feature",
  "properties": {
    "iso:country":"DE",
    "sg:address":"Puschkinstr. 10 a",
    "sg:city":"Bad Langensalza",
    "sg:phone":"+49 3603/842858",
    "sg:postcode":"99947",
    "sg:province":"Th\u00fcringen",
    "wof:name":"Harald Stieding",
    "wof:placetype":"venue"
},
  "geometry": {"coordinates":[10.642874,51.103874],"type":"Point"}
}