{
  "type": "Feature",
  "properties": {
    "iso:country":"DE",
    "sg:address":"Lobensteiner Str. 18",
    "sg:city":"Nordhalben",
    "sg:phone":"+49 9267/640",
    "sg:postcode":"96365",
    "sg:province":"Bayern",
    "wof:name":"Heinrich P\u00f6hnlein",
    "wof:placetype":"venue"
},
  "geometry": {"coordinates":[11.5124063492,50.3749504089],"type":"Point"}
}