{
  "type": "Feature",
  "properties": {
    "iso:country":"DE",
    "sg:address":"Gro\u00dfe Brinkgasse 21-25",
    "sg:city":"K\u00f6ln",
    "sg:phone":"+49 221/2582918",
    "sg:postcode":"50672",
    "sg:province":"Nordrhein-Westfalen",
    "wof:name":"Vintage Gmbh",
    "wof:placetype":"venue"
},
  "geometry": {"coordinates":[6.9430727959,50.9375801086],"type":"Point"}
}