{
  "type": "Feature",
  "properties": {
    "iso:country":"DE",
    "sg:address":"Klausstr. 24",
    "sg:city":"Bad Hersfeld",
    "sg:postcode":"36251",
    "sg:province":"Hessen",
    "wof:name":"City-kaufhaus Verwaltungs Gmbh",
    "wof:placetype":"venue"
},
  "geometry": {"coordinates":[9.7096166611,50.869140625],"type":"Point"}
}