{
  "type": "Feature",
  "properties": {
    "iso:country":"DE",
    "sg:address":"Saseler Chaussee 205",
    "sg:city":"Hamburg",
    "sg:postcode":"22393",
    "sg:province":"Hamburg",
    "wof:name":"Restaurante Donau Inh. Djujic E. K.",
    "wof:placetype":"venue"
},
  "geometry": {"coordinates":[10.1063575745,53.6530036926],"type":"Point"}
}