{
  "type": "Feature",
  "properties": {
    "iso:country":"DE",
    "sg:address":"Wollgrasweg 41",
    "sg:city":"Stuttgart",
    "sg:phone":"+49 711/45070",
    "sg:postcode":"70599",
    "sg:province":"Baden-W\u00fcrttemberg",
    "wof:name":"Redaktion Die Gefiederte Welt Eugen Ulmer",
    "wof:placetype":"venue"
},
  "geometry": {"coordinates":[9.1994171143,48.7099456787],"type":"Point"}
}