{
  "type": "Feature",
  "properties": {
    "iso:country":"DE",
    "sg:address":"Wittekindstr. 16",
    "sg:city":"Herford",
    "sg:postcode":"32051",
    "sg:province":"Nordrhein-Westfalen",
    "wof:name":"Eurex Gmbh",
    "wof:placetype":"venue"
},
  "geometry": {"coordinates":[8.6602840424,52.1145515442],"type":"Point"}
}