{
  "type": "Feature",
  "properties": {
    "iso:country":"DE",
    "sg:address":"Burgunderstr. 3",
    "sg:city":"Murr",
    "sg:phone":"+49 7144/209368",
    "sg:postcode":"71711",
    "sg:province":"Baden-W\u00fcrttemberg",
    "wof:name":"Unger Immobilien Gmbh",
    "wof:placetype":"venue"
},
  "geometry": {"coordinates":[9.254661,48.957153],"type":"Point"}
}