{
  "type": "Feature",
  "properties": {
    "iso:country":"DE",
    "sg:address":"Ernst-Barlach-Str. 40",
    "sg:city":"Sindelfingen",
    "sg:phone":"+49 7031/870594",
    "sg:postcode":"71065",
    "sg:province":"Baden-W\u00fcrttemberg",
    "wof:name":"Naturfreundehaus",
    "wof:placetype":"venue"
},
  "geometry": {"coordinates":[9.0405797958,48.7073516846],"type":"Point"}
}