{
  "type": "Feature",
  "properties": {
    "iso:country":"DE",
    "sg:address":"Oberer Markt 16",
    "sg:city":"Hersbruck",
    "sg:phone":"+49 9151/7400",
    "sg:postcode":"91217",
    "sg:province":"Bayern",
    "wof:name":"Markt-apotheke",
    "wof:placetype":"venue"
},
  "geometry": {"coordinates":[11.429282,49.507866],"type":"Point"}
}