{
  "type": "Feature",
  "properties": {
    "iso:country":"DE",
    "sg:address":"Hofer Str. 12",
    "sg:city":"Plauen",
    "sg:phone":"+49 3741/223627",
    "sg:postcode":"08527",
    "sg:province":"Sachsen",
    "wof:name":"Weis Bauunternehmen Weba Plauen Gmbh",
    "wof:placetype":"venue"
},
  "geometry": {"coordinates":[12.1404762268,50.4905738831],"type":"Point"}
}