{
  "type": "Feature",
  "properties": {
    "iso:country":"DE",
    "sg:address":"Fischerstr. 6",
    "sg:city":"Ribnitz-Damgarten",
    "sg:phone":"+49 3821/813605",
    "sg:postcode":"18311",
    "sg:province":"Mecklenburg-Vorpommern",
    "wof:name":"Bild + Rahmen Stroh",
    "wof:placetype":"venue"
},
  "geometry": {"coordinates":[12.4302110672,54.2442474365],"type":"Point"}
}