{
  "type": "Feature",
  "properties": {
    "iso:country":"DE",
    "sg:address":"Hauptstr. 68",
    "sg:city":"Schutterwald",
    "sg:phone":"+49 4978/152982",
    "sg:postcode":"77746",
    "sg:province":"Baden-W\u00fcrttemberg",
    "wof:name":"Volksbank Offenburg Eg",
    "wof:placetype":"venue"
},
  "geometry": {"coordinates":[7.883944,48.453873],"type":"Point"}
}