{
  "type": "Feature",
  "properties": {
    "iso:country":"DE",
    "sg:address":"Pfinzingstra\u00dfe 5",
    "sg:city":"Feucht",
    "sg:postcode":"90537",
    "sg:province":"Bayern",
    "wof:name":"Reiseb\u00fcro Interplan",
    "wof:placetype":"venue"
},
  "geometry": {"coordinates":[11.212547,49.375282],"type":"Point"}
}