{
  "type": "Feature",
  "properties": {
    "iso:country":"DE",
    "sg:address":"Johann-Karg-Str. 44",
    "sg:city":"Haar",
    "sg:phone":"+49 89/4399890",
    "sg:postcode":"85540",
    "sg:province":"Bayern",
    "wof:name":"Physiotec Gmbh",
    "wof:placetype":"venue"
},
  "geometry": {"coordinates":[11.7206897736,48.1304016113],"type":"Point"}
}