{
  "type": "Feature",
  "properties": {
    "iso:country":"DE",
    "sg:address":"Ohmstr. 10",
    "sg:city":"Schwarzenfeld",
    "sg:phone":"+49 9435/3249",
    "sg:postcode":"92521",
    "sg:province":"Bayern",
    "wof:name":"Hasenkopf Maschinenbau Gmbh",
    "wof:placetype":"venue"
},
  "geometry": {"coordinates":[12.119463,49.387264],"type":"Point"}
}