{
  "type": "Feature",
  "properties": {
    "iso:country":"DE",
    "sg:address":"Josefstr. 41",
    "sg:city":"Nettetal",
    "sg:phone":"+49 2153/71519",
    "sg:postcode":"41334",
    "sg:province":"Nordrhein-Westfalen",
    "wof:name":"A. Bayraktar",
    "wof:placetype":"venue"
},
  "geometry": {"coordinates":[6.2455692291,51.2962608337],"type":"Point"}
}