{
  "type": "Feature",
  "properties": {
    "iso:country":"DE",
    "sg:address":"Fasanenweg 43",
    "sg:city":"Haar",
    "sg:phone":"+49 89/468574",
    "sg:postcode":"85540",
    "sg:province":"Bayern",
    "wof:name":"Manfred M\u00fcller",
    "wof:placetype":"venue"
},
  "geometry": {"coordinates":[11.7270421982,48.1049537659],"type":"Point"}
}