{
  "type": "Feature",
  "properties": {
    "iso:country":"DE",
    "sg:address":"Mottener Str. 64",
    "sg:city":"Lebach",
    "sg:phone":"+49 6881/2891",
    "sg:postcode":"66822",
    "sg:province":"Saarland",
    "wof:name":"Karl Kost",
    "wof:placetype":"venue"
},
  "geometry": {"coordinates":[6.9112849236,49.4108161926],"type":"Point"}
}