{
  "type": "Feature",
  "properties": {
    "iso:country":"DE",
    "sg:address":"Ziegelstr. 25 A",
    "sg:city":"L\u00fcbeck",
    "sg:phone":"+49 451/40377",
    "sg:postcode":"23556",
    "sg:province":"Schleswig-Holstein",
    "wof:name":"Praxis Freudenstein Matthie\u00dfen Und",
    "wof:placetype":"venue"
},
  "geometry": {"coordinates":[10.6636276245,53.869594574],"type":"Point"}
}