{
  "type": "Feature",
  "properties": {
    "iso:country":"DE",
    "sg:address":"Hauptstr. 43",
    "sg:city":"Hoppst\u00e4dten-Weiersbach",
    "sg:phone":"+49 6782/5322",
    "sg:postcode":"55768",
    "sg:province":"Rheinland-Pfalz",
    "wof:name":"Gregor Flick",
    "wof:placetype":"venue"
},
  "geometry": {"coordinates":[7.1973519325,49.6187896729],"type":"Point"}
}