{
  "type": "Feature",
  "properties": {
    "iso:country":"DE",
    "sg:address":"Dieburger Str. 71",
    "sg:city":"R\u00f6dermark",
    "sg:phone":"+49 6074/93693",
    "sg:postcode":"63322",
    "sg:province":"Hessen",
    "wof:name":"Video-star",
    "wof:placetype":"venue"
},
  "geometry": {"coordinates":[8.8296775818,49.9739189148],"type":"Point"}
}