{
  "type": "Feature",
  "properties": {
    "iso:country":"DE",
    "sg:address":"Mozartstr. 19 a",
    "sg:city":"R\u00fclzheim",
    "sg:phone":"+49 7272/93100",
    "sg:postcode":"76761",
    "sg:province":"Rheinland-Pfalz",
    "wof:name":"Impulse Gmbh Sondermaschinen-konstruktion",
    "wof:placetype":"venue"
},
  "geometry": {"coordinates":[8.296055,49.150383],"type":"Point"}
}