{
  "type": "Feature",
  "properties": {
    "iso:country":"DE",
    "sg:address":"Langer Kamp 2",
    "sg:city":"Braunschweig",
    "sg:phone":"+49 531/346453",
    "sg:postcode":"38106",
    "sg:province":"Niedersachsen",
    "wof:name":"Tordalk",
    "wof:placetype":"venue"
},
  "geometry": {"coordinates":[10.539011,52.275642],"type":"Point"}
}