{
  "type": "Feature",
  "properties": {
    "iso:country":"DE",
    "sg:address":"Bahnhofstr. 13",
    "sg:city":"Wustrow",
    "sg:phone":"+49 4958/43286",
    "sg:postcode":"29462",
    "sg:province":"Niedersachsen",
    "wof:name":"Kreissparkasse",
    "wof:placetype":"venue"
},
  "geometry": {"coordinates":[11.121808,52.923878],"type":"Point"}
}