{
  "type": "Feature",
  "properties": {
    "iso:country":"DE",
    "sg:address":"Robert-Koch-Str. 2",
    "sg:city":"Klingenthal",
    "sg:postcode":"08248",
    "sg:province":"Sachsen",
    "wof:name":"Musikhaus Musikschule Gmbh",
    "wof:placetype":"venue"
},
  "geometry": {"coordinates":[12.4866304398,50.3839797974],"type":"Point"}
}