{
  "type": "Feature",
  "properties": {
    "iso:country":"DE",
    "sg:address":"Br\u00fcner Landstr. 73",
    "sg:city":"Wesel",
    "sg:phone":"+49 281/53289",
    "sg:postcode":"46485",
    "sg:province":"Nordrhein-Westfalen",
    "wof:name":"K. Sardemann",
    "wof:placetype":"venue"
},
  "geometry": {"coordinates":[6.6352901459,51.6702308655],"type":"Point"}
}