{
  "type": "Feature",
  "properties": {
    "iso:country":"DE",
    "sg:address":"Hauptstr. 11",
    "sg:city":"Weilersbach",
    "sg:phone":"+49 9191/9262",
    "sg:postcode":"91365",
    "sg:province":"Bayern",
    "wof:name":"Hilmar Porzelt",
    "wof:placetype":"venue"
},
  "geometry": {"coordinates":[11.133769989,49.7445640564],"type":"Point"}
}