{
  "type": "Feature",
  "properties": {
    "iso:country":"DE",
    "sg:address":"Thaerstr. 10",
    "sg:city":"Stuttgart",
    "sg:phone":"+49 711/8874873",
    "sg:postcode":"70499",
    "sg:province":"Baden-W\u00fcrttemberg",
    "wof:name":"Julius Schindler Innenarchitekt",
    "wof:placetype":"venue"
},
  "geometry": {"coordinates":[9.111245,48.811989],"type":"Point"}
}