{
  "type": "Feature",
  "properties": {
    "iso:country":"DE",
    "sg:address":"Lohm\u00fchlstr.39",
    "sg:city":"M\u00fchldorf",
    "sg:phone":"+49 8631/990442",
    "sg:postcode":"84453",
    "sg:province":"Bayern",
    "wof:name":"Shopping-center",
    "wof:placetype":"venue"
},
  "geometry": {"coordinates":[12.535849,48.23534],"type":"Point"}
}