{
  "type": "Feature",
  "properties": {
    "iso:country":"DE",
    "sg:address":"Verena Weg 9",
    "sg:city":"Spaichingen",
    "sg:phone":"+49 7424/502533",
    "sg:postcode":"78549",
    "sg:province":"Baden-W\u00fcrttemberg",
    "wof:name":"Reichmann Kunststofftechnik Gmbh",
    "wof:placetype":"venue"
},
  "geometry": {"coordinates":[8.736572,48.068241],"type":"Point"}
}