{
  "type": "Feature",
  "properties": {
    "iso:country":"DE",
    "sg:address":"Humboldtstr. 9",
    "sg:city":"L\u00fcdenscheid",
    "sg:phone":"+49 2351/25044",
    "sg:postcode":"58511",
    "sg:province":"Nordrhein-Westfalen",
    "wof:name":"Beka Gmbh",
    "wof:placetype":"venue"
},
  "geometry": {"coordinates":[7.6324949265,51.2176742554],"type":"Point"}
}