{
  "type": "Feature",
  "properties": {
    "iso:country":"DE",
    "sg:address":"Ludwigstr. 6",
    "sg:city":"Offenbach",
    "sg:phone":"+49 69/8290070",
    "sg:postcode":"63067",
    "sg:province":"Hessen",
    "wof:name":"H. J\u00e4ger Und J. Lubrich Steuerberater",
    "wof:placetype":"venue"
},
  "geometry": {"coordinates":[8.7561187744,50.0994567871],"type":"Point"}
}