{
  "type": "Feature",
  "properties": {
    "iso:country":"DE",
    "sg:address":"Friedr.-Wilh.-Raiffeisen-Str.",
    "sg:city":"\u00dcbach-Palenberg",
    "sg:postcode":"52531",
    "sg:province":"Nordrhein-Westfalen",
    "wof:name":"Janex Vertriebsges. Mbh",
    "wof:placetype":"venue"
},
  "geometry": {"coordinates":[6.1194939613,50.9198150635],"type":"Point"}
}