{
  "type": "Feature",
  "properties": {
    "iso:country":"DE",
    "sg:address":"Eisenbahnstr. 4",
    "sg:city":"Gaggenau",
    "sg:phone":"+49 7225/983547",
    "sg:postcode":"76571",
    "sg:province":"Baden-W\u00fcrttemberg",
    "wof:name":"Geiser Holz- Und Treppenbau Gmbh",
    "wof:placetype":"venue"
},
  "geometry": {"coordinates":[8.3020792007,48.8160591125],"type":"Point"}
}