{
  "type": "Feature",
  "properties": {
    "iso:country":"DE",
    "sg:address":"Kirchplatz",
    "sg:city":"Dietmannsried",
    "sg:phone":"+49 8374/257",
    "sg:postcode":"87463",
    "sg:province":"Bayern",
    "wof:name":"Kath. \u00d6ffentliche B\u00fccherei",
    "wof:placetype":"venue"
},
  "geometry": {"coordinates":[10.289444,47.808128],"type":"Point"}
}