{
  "type": "Feature",
  "properties": {
    "iso:country":"DE",
    "sg:address":"Clemens-M\u00fcller-Str. 2",
    "sg:city":"Dresden",
    "sg:phone":"+49 351/4767872",
    "sg:postcode":"01099",
    "sg:province":"Sachsen",
    "wof:name":"S\u00e4chsische B\u00e4ckerschule Dresden-helmsdorf E. V.",
    "wof:placetype":"venue"
},
  "geometry": {"coordinates":[13.7691631317,51.0836982727],"type":"Point"}
}