{
  "type": "Feature",
  "properties": {
    "iso:country":"DE",
    "sg:address":"Karl-Marx-Str. 1",
    "sg:city":"Ruhland",
    "sg:phone":"+49 35752/96110",
    "sg:postcode":"01945",
    "sg:province":"Brandenburg",
    "wof:name":"Gerd Und Frank Hopisch",
    "wof:placetype":"venue"
},
  "geometry": {"coordinates":[13.8636837006,51.4536247253],"type":"Point"}
}