{
  "type": "Feature",
  "properties": {
    "iso:country":"DE",
    "sg:address":"Hauptstr. 8",
    "sg:city":"Recke",
    "sg:postcode":"49509",
    "sg:province":"Nordrhein-Westfalen",
    "wof:name":"Ihr Platz Drogeriemarkt",
    "wof:placetype":"venue"
},
  "geometry": {"coordinates":[7.719756,52.369415],"type":"Point"}
}