{
  "type": "Feature",
  "properties": {
    "iso:country":"DE",
    "sg:address":"Wolfgang-Dachstein-Str 28",
    "sg:city":"Offenburg",
    "sg:phone":"+49 781/34846",
    "sg:postcode":"77654",
    "sg:province":"Baden-W\u00fcrttemberg",
    "wof:name":"Michael Hummel Rechtsanwalt",
    "wof:placetype":"venue"
},
  "geometry": {"coordinates":[7.9605269432,48.4747123718],"type":"Point"}
}