{
  "type": "Feature",
  "properties": {
    "iso:country":"DE",
    "sg:address":"Kunkgang 2",
    "sg:city":"Petershagen",
    "sg:phone":"+49 5704/500",
    "sg:postcode":"32469",
    "sg:province":"Nordrhein-Westfalen",
    "wof:name":"Karl-heinz Poos",
    "wof:placetype":"venue"
},
  "geometry": {"coordinates":[8.891583,52.376324],"type":"Point"}
}