{
  "type": "Feature",
  "properties": {
    "iso:country":"DE",
    "sg:address":"Benediktinerplatz 1",
    "sg:city":"Saarwellingen",
    "sg:phone":"+49 6838/7029",
    "sg:postcode":"66793",
    "sg:province":"Saarland",
    "wof:name":"Bernd Hild",
    "wof:placetype":"venue"
},
  "geometry": {"coordinates":[6.801468,49.360283],"type":"Point"}
}