{
  "type": "Feature",
  "properties": {
    "iso:country":"DE",
    "sg:address":"Englerstr 24",
    "sg:city":"Ettlingen",
    "sg:phone":"+49 6227/52373",
    "sg:postcode":"76275",
    "sg:province":"Baden-W\u00fcrttemberg",
    "wof:name":"C.b. Elektrotechnik Gmbh",
    "wof:placetype":"venue"
},
  "geometry": {"coordinates":[8.598642,49.265911],"type":"Point"}
}