{
  "type": "Feature",
  "properties": {
    "iso:country":"DE",
    "sg:address":"Thieplatz 3",
    "sg:city":"Lienen",
    "sg:phone":"+49 5483/8132",
    "sg:postcode":"49536",
    "sg:province":"Nordrhein-Westfalen",
    "wof:name":"Dineke Kalvelage Innenarchitektin",
    "wof:placetype":"venue"
},
  "geometry": {"coordinates":[7.976243,52.14743],"type":"Point"}
}