{
  "type": "Feature",
  "properties": {
    "iso:country":"DE",
    "sg:address":"Dammstr. 36",
    "sg:city":"Jena",
    "sg:phone":"+49 3641/820877",
    "sg:postcode":"07749",
    "sg:province":"Th\u00fcringen",
    "wof:name":"Dr. Norbert Plandor Rechtsanwalt",
    "wof:placetype":"venue"
},
  "geometry": {"coordinates":[11.5979623795,50.9332313538],"type":"Point"}
}