{
  "type": "Feature",
  "properties": {
    "iso:country":"DE",
    "sg:address":"Zeesener Str. 7",
    "sg:city":"Bestensee",
    "sg:phone":"+49 33763/62211",
    "sg:postcode":"15741",
    "sg:province":"Brandenburg",
    "wof:name":"Schulz",
    "wof:placetype":"venue"
},
  "geometry": {"coordinates":[13.635840416,52.2433586121],"type":"Point"}
}