{
  "type": "Feature",
  "properties": {
    "iso:country":"DE",
    "sg:address":"Am Markt 1",
    "sg:city":"Ketzin",
    "sg:phone":"+49 33233/82302",
    "sg:postcode":"14669",
    "sg:province":"Brandenburg",
    "wof:name":"Brillen-rasch Inh. M. M\u00fcller",
    "wof:placetype":"venue"
},
  "geometry": {"coordinates":[12.842663765,52.475643158],"type":"Point"}
}