{
  "type": "Feature",
  "properties": {
    "iso:country":"DE",
    "sg:address":"Sackstr. 58 a",
    "sg:city":"Kleve",
    "sg:phone":"+49 2821/23922",
    "sg:postcode":"47533",
    "sg:province":"Nordrhein-Westfalen",
    "wof:name":"Sportklause",
    "wof:placetype":"venue"
},
  "geometry": {"coordinates":[6.1293091774,51.777797699],"type":"Point"}
}