{
  "type": "Feature",
  "properties": {
    "iso:country":"DE",
    "sg:address":"Hahnenbachstr. 28",
    "sg:city":"Hahnenbach",
    "sg:phone":"+49 6752/8295",
    "sg:postcode":"55606",
    "sg:province":"Rheinland-Pfalz",
    "wof:name":"Heled Lederwaren Ohg",
    "wof:placetype":"venue"
},
  "geometry": {"coordinates":[7.4197130203,49.8078918457],"type":"Point"}
}