{
  "type": "Feature",
  "properties": {
    "iso:country":"DE",
    "sg:address":"Friedrich-Ebert-Str. 1",
    "sg:city":"Gaggenau",
    "sg:phone":"+49 7225/76098",
    "sg:postcode":"76571",
    "sg:province":"Baden-W\u00fcrttemberg",
    "wof:name":"U. Sondermann",
    "wof:placetype":"venue"
},
  "geometry": {"coordinates":[8.319940567,48.8032608032],"type":"Point"}
}