{
  "type": "Feature",
  "properties": {
    "iso:country":"DE",
    "sg:address":"Bachfeldstr. 4",
    "sg:city":"Landsberg",
    "sg:phone":"+49 8246/1552",
    "sg:postcode":"86899",
    "sg:province":"Bayern",
    "wof:name":"H. Pointner",
    "wof:placetype":"venue"
},
  "geometry": {"coordinates":[10.835695,48.002312],"type":"Point"}
}