{
  "type": "Feature",
  "properties": {
    "iso:country":"DE",
    "sg:address":"Karlstr. 18",
    "sg:city":"Rodgau",
    "sg:phone":"+49 6106/29519",
    "sg:postcode":"63110",
    "sg:province":"Hessen",
    "wof:name":"Kiosk Zum Gem\u00fctlichen Treff",
    "wof:placetype":"venue"
},
  "geometry": {"coordinates":[8.8857812881,50.0100021362],"type":"Point"}
}