{
  "type": "Feature",
  "properties": {
    "iso:country":"DE",
    "sg:address":"Hauptstr. 33",
    "sg:city":"Werda",
    "sg:postcode":"08223",
    "sg:province":"Sachsen",
    "wof:name":"Ev.-luth. Kirche Werda",
    "wof:placetype":"venue"
},
  "geometry": {"coordinates":[12.3016700745,50.4382209778],"type":"Point"}
}