{
  "type": "Feature",
  "properties": {
    "iso:country":"DE",
    "sg:address":"Hohe Str. 45",
    "sg:city":"Pirna",
    "sg:phone":"+49 3501/781773",
    "sg:postcode":"01796",
    "sg:province":"Sachsen",
    "wof:name":"Petra Adler",
    "wof:placetype":"venue"
},
  "geometry": {"coordinates":[13.9452838898,50.9505157471],"type":"Point"}
}