{
  "type": "Feature",
  "properties": {
    "iso:country":"DE",
    "sg:address":"Burvagsweg 2",
    "sg:city":"Fintel",
    "sg:phone":"+49 4265/1210",
    "sg:postcode":"27389",
    "sg:province":"Niedersachsen",
    "wof:name":"Alfred Schulz Inh. Gerhard Buhr",
    "wof:placetype":"venue"
},
  "geometry": {"coordinates":[9.6697902679,53.1711654663],"type":"Point"}
}