{
  "type": "Feature",
  "properties": {
    "iso:country":"DE",
    "sg:address":"Zum Kratt 4",
    "sg:city":"Fockbek",
    "sg:phone":"+49 4331/66160",
    "sg:postcode":"24787",
    "sg:province":"Schleswig-Holstein",
    "wof:name":"Fliesen-hof-fockbek Gmbh",
    "wof:placetype":"venue"
},
  "geometry": {"coordinates":[9.58705616,54.3107528687],"type":"Point"}
}