{
  "type": "Feature",
  "properties": {
    "iso:country":"DE",
    "sg:address":"Eitelstr. 40",
    "sg:city":"D\u00fcsseldorf",
    "sg:postcode":"40472",
    "sg:province":"Nordrhein-Westfalen",
    "wof:name":"K\u00fchne Liegenschafts- Verwaltungen Gmbh",
    "wof:placetype":"venue"
},
  "geometry": {"coordinates":[6.8281350136,51.2702598572],"type":"Point"}
}