{
  "type": "Feature",
  "properties": {
    "iso:country":"DE",
    "sg:address":"Ditzenbacher Weg 5",
    "sg:city":"Leonberg",
    "sg:phone":"+49 7152/929506",
    "sg:postcode":"71229",
    "sg:province":"Baden-W\u00fcrttemberg",
    "wof:name":"Speed Art Tuningzubeh\u00f6r E. K.",
    "wof:placetype":"venue"
},
  "geometry": {"coordinates":[8.9962205887,48.7901382446],"type":"Point"}
}