{
  "type": "Feature",
  "properties": {
    "iso:country":"DE",
    "sg:address":"Wachtelstr. 1",
    "sg:city":"Niederkassel",
    "sg:phone":"+49 2208/1287",
    "sg:postcode":"53859",
    "sg:province":"Nordrhein-Westfalen",
    "wof:name":"K. Baderschneider Verm\u00f6gensverwaltung",
    "wof:placetype":"venue"
},
  "geometry": {"coordinates":[7.0336818695,50.8248214722],"type":"Point"}
}