{
  "type": "Feature",
  "properties": {
    "iso:country":"DE",
    "sg:address":"Asternweg 1",
    "sg:city":"Regensburg",
    "sg:phone":"+49 941/7877915",
    "sg:postcode":"93053",
    "sg:province":"Bayern",
    "wof:name":"Nidermayer Kirchentechnik",
    "wof:placetype":"venue"
},
  "geometry": {"coordinates":[12.110543,49.000374],"type":"Point"}
}