{
  "type": "Feature",
  "properties": {
    "iso:country":"DE",
    "sg:address":"Hindenburgstr 23",
    "sg:city":"Rheinau",
    "sg:phone":"+49 7227/95860",
    "sg:postcode":"77866",
    "sg:province":"Baden-W\u00fcrttemberg",
    "wof:name":"Bickel Tuning Gmbh",
    "wof:placetype":"venue"
},
  "geometry": {"coordinates":[7.972128,48.70911],"type":"Point"}
}