{
  "type": "Feature",
  "properties": {
    "iso:country":"DE",
    "sg:address":"Breite Gasse 46",
    "sg:city":"N\u00fcrnberg",
    "sg:phone":"+49 911/225122",
    "sg:postcode":"90402",
    "sg:province":"Bayern",
    "wof:name":"Stengel Beteiligungen Gmbh",
    "wof:placetype":"venue"
},
  "geometry": {"coordinates":[11.074596,49.450211],"type":"Point"}
}