{
  "type": "Feature",
  "properties": {
    "iso:country":"DE",
    "sg:address":"Beuchaer Str. 12",
    "sg:city":"Leipzig",
    "sg:phone":"+49 341/2619384",
    "sg:postcode":"04318",
    "sg:province":"Sachsen",
    "wof:name":"Werner K\u00f6pke",
    "wof:placetype":"venue"
},
  "geometry": {"coordinates":[12.4106941223,51.3358726501],"type":"Point"}
}