{
  "type": "Feature",
  "properties": {
    "iso:country":"DE",
    "sg:address":"Wagenfeldstr. 60",
    "sg:city":"Nordkirchen",
    "sg:phone":"+49 2596/1651",
    "sg:postcode":"59394",
    "sg:province":"Nordrhein-Westfalen",
    "wof:name":"Klaus Berg",
    "wof:placetype":"venue"
},
  "geometry": {"coordinates":[7.540303,51.710129],"type":"Point"}
}