{
  "type": "Feature",
  "properties": {
    "iso:country":"DE",
    "sg:address":"Bonifatiusstr. 9",
    "sg:city":"Marl",
    "sg:phone":"+49 2365/691316",
    "sg:postcode":"45768",
    "sg:province":"Nordrhein-Westfalen",
    "wof:name":"Pizzeria Bella Italia",
    "wof:placetype":"venue"
},
  "geometry": {"coordinates":[7.0862798691,51.6571731567],"type":"Point"}
}