{
  "type": "Feature",
  "properties": {
    "iso:country":"DE",
    "sg:address":"Josef-Fischhaber-Str. 39",
    "sg:city":"Starnberg",
    "sg:phone":"+49 8151/15130",
    "sg:postcode":"82319",
    "sg:province":"Bayern",
    "wof:name":"Heinz L\u00f6hr Rechtsanwalt",
    "wof:placetype":"venue"
},
  "geometry": {"coordinates":[11.342171669,47.9995918274],"type":"Point"}
}