{
  "type": "Feature",
  "properties": {
    "iso:country":"DE",
    "sg:address":"Kirchweg 39",
    "sg:city":"Kleve",
    "sg:phone":"+49 2821/25450",
    "sg:postcode":"47533",
    "sg:province":"Nordrhein-Westfalen",
    "wof:name":"Liffers & Groenewald",
    "wof:placetype":"venue"
},
  "geometry": {"coordinates":[6.116168,51.777939],"type":"Point"}
}