{
  "type": "Feature",
  "properties": {
    "iso:country":"DE",
    "sg:address":"Fuchsengarten 1",
    "sg:city":"Erlangen",
    "sg:phone":"+49 9131/29164",
    "sg:postcode":"91054",
    "sg:province":"Bayern",
    "wof:name":"H\u00fchnertod",
    "wof:placetype":"venue"
},
  "geometry": {"coordinates":[11.0012788773,49.6015892029],"type":"Point"}
}