{
  "type": "Feature",
  "properties": {
    "iso:country":"DE",
    "sg:address":"Christian-B\u00fcrkert-Str. 13 -17",
    "sg:city":"Ingelfingen",
    "sg:phone":"+49 7940/10204",
    "sg:postcode":"74653",
    "sg:province":"Baden-W\u00fcrttemberg",
    "wof:name":"B\u00fcrkert Besitz Gmbh",
    "wof:placetype":"venue"
},
  "geometry": {"coordinates":[9.653604,49.297714],"type":"Point"}
}