{
  "type": "Feature",
  "properties": {
    "iso:country":"DE",
    "sg:address":"Suebenstr. 28",
    "sg:city":"Dortmund",
    "sg:phone":"+49 231/431031",
    "sg:postcode":"44263",
    "sg:province":"Nordrhein-Westfalen",
    "wof:name":"Wilhelm Petzold",
    "wof:placetype":"venue"
},
  "geometry": {"coordinates":[7.493279,51.485985],"type":"Point"}
}