{
  "type": "Feature",
  "properties": {
    "iso:country":"DE",
    "sg:address":"Benzstr. 2",
    "sg:city":"Gelsenkirchen",
    "sg:phone":"+49 209/976120",
    "sg:postcode":"45891",
    "sg:province":"Nordrhein-Westfalen",
    "wof:name":"Creatic Concept Ges. F. Gesch\u00e4ftseinrichtungen",
    "wof:placetype":"venue"
},
  "geometry": {"coordinates":[7.075652,51.544792],"type":"Point"}
}