{
  "type": "Feature",
  "properties": {
    "iso:country":"DE",
    "sg:address":"Noltestr. 14",
    "sg:city":"L\u00fcdenscheid",
    "sg:phone":"+49 2351/12086",
    "sg:postcode":"58511",
    "sg:province":"Nordrhein-Westfalen",
    "wof:name":"R. Linnepe K\u00e4lte-klima-technik Inh. Marko Capan E. K.",
    "wof:placetype":"venue"
},
  "geometry": {"coordinates":[7.654187,51.230778],"type":"Point"}
}