{
  "type": "Feature",
  "properties": {
    "iso:country":"DE",
    "sg:address":"Hospeltstr. 35B",
    "sg:city":"K\u00f6ln",
    "sg:phone":"+49 221/9541350",
    "sg:postcode":"50825",
    "sg:province":"Nordrhein-Westfalen",
    "wof:name":"V & M Video & Monitor Filmservice Dieter Klucke",
    "wof:placetype":"venue"
},
  "geometry": {"coordinates":[6.9072041512,50.9538497925],"type":"Point"}
}