{
  "type": "Feature",
  "properties": {
    "iso:country":"DE",
    "sg:address":"Am Eisweiher 9",
    "sg:city":"Gernsbach",
    "sg:postcode":"76593",
    "sg:province":"Baden-W\u00fcrttemberg",
    "wof:name":"Man At Work Software Gmbh",
    "wof:placetype":"venue"
},
  "geometry": {"coordinates":[8.350012,48.750671],"type":"Point"}
}