{
  "type": "Feature",
  "properties": {
    "iso:country":"DE",
    "sg:address":"Braunsdorf 14",
    "sg:city":"Dittrichsh\u00fctte",
    "sg:phone":"+49 36741/42660",
    "sg:postcode":"07422",
    "sg:province":"Th\u00fcringen",
    "wof:name":"Bauernst\u00fcbl",
    "wof:placetype":"venue"
},
  "geometry": {"coordinates":[11.2431383133,50.6684608459],"type":"Point"}
}