{
  "type": "Feature",
  "properties": {
    "iso:country":"DE",
    "sg:address":"Biegenhofstr. 8",
    "sg:city":"Hallstadt",
    "sg:phone":"+49 951/9679911",
    "sg:postcode":"96103",
    "sg:province":"Bayern",
    "wof:name":"Staatliche Lotterie-einnahme Hubert Hennes",
    "wof:placetype":"venue"
},
  "geometry": {"coordinates":[10.870725,49.918179],"type":"Point"}
}