{
  "type": "Feature",
  "properties": {
    "iso:country":"DE",
    "sg:address":"Steinackerstr. 19",
    "sg:city":"Weil am Rhein",
    "sg:phone":"+49 7621/71689",
    "sg:postcode":"79576",
    "sg:province":"Baden-W\u00fcrttemberg",
    "wof:name":"Eckardt Foege",
    "wof:placetype":"venue"
},
  "geometry": {"coordinates":[7.600084,47.595722],"type":"Point"}
}