{
  "type": "Feature",
  "properties": {
    "iso:country":"DE",
    "sg:address":"Neue Str. 3",
    "sg:city":"Asbach-B\u00e4umenheim",
    "sg:phone":"+49 906/91600",
    "sg:postcode":"86663",
    "sg:province":"Bayern",
    "wof:name":"Oliver Kauffmann Verkehrsunternehmen Gmbh",
    "wof:placetype":"venue"
},
  "geometry": {"coordinates":[10.8163318634,48.6805763245],"type":"Point"}
}