{
  "type": "Feature",
  "properties": {
    "iso:country":"DE",
    "sg:address":"Drollm\u00fchle",
    "sg:city":"W\u00f6rrstadt",
    "sg:phone":"+49 6732/2334",
    "sg:postcode":"55286",
    "sg:province":"Rheinland-Pfalz",
    "wof:name":"L. Simon",
    "wof:placetype":"venue"
},
  "geometry": {"coordinates":[8.0958566666,49.8296737671],"type":"Point"}
}