{
  "type": "Feature",
  "properties": {
    "iso:country":"DE",
    "sg:address":"Uhlandstr. 16",
    "sg:city":"Maselheim",
    "sg:phone":"+49 7356/679",
    "sg:postcode":"88437",
    "sg:province":"Baden-W\u00fcrttemberg",
    "wof:name":"F. Laack",
    "wof:placetype":"venue"
},
  "geometry": {"coordinates":[9.8517389297,48.1521148682],"type":"Point"}
}