{
  "type": "Feature",
  "properties": {
    "iso:country":"DE",
    "sg:address":"Prioreierstr. 11",
    "sg:city":"Hagen",
    "sg:phone":"+49 2337",
    "sg:postcode":"58091",
    "sg:province":"Nordrhein-Westfalen",
    "wof:name":"Fr.wilh.keil Ohg",
    "wof:placetype":"venue"
},
  "geometry": {"coordinates":[7.5281271935,51.2942733765],"type":"Point"}
}