{
  "type": "Feature",
  "properties": {
    "iso:country":"DE",
    "sg:address":"Prenzlauer Allee 214",
    "sg:city":"Berlin",
    "sg:phone":"+49 30/4425924",
    "sg:postcode":"10405",
    "sg:province":"Berlin",
    "wof:name":"Prenzlauer-apotheke",
    "wof:placetype":"venue"
},
  "geometry": {"coordinates":[13.4219,52.535919],"type":"Point"}
}