{
  "type": "Feature",
  "properties": {
    "iso:country":"DE",
    "sg:address":"Zeilstr. 16",
    "sg:city":"Reutlingen",
    "sg:phone":"+49 7121/310972",
    "sg:postcode":"72768",
    "sg:province":"Baden-W\u00fcrttemberg",
    "wof:name":"Nagler",
    "wof:placetype":"venue"
},
  "geometry": {"coordinates":[9.180575,48.524994],"type":"Point"}
}