{
  "type": "Feature",
  "properties": {
    "iso:country":"DE",
    "sg:address":"Am Gro\u00dfen Wannsee 2",
    "sg:city":"Berlin",
    "sg:phone":"+49 30/8052684",
    "sg:postcode":"14109",
    "sg:province":"Berlin",
    "wof:name":"H. Schlickeisen",
    "wof:placetype":"venue"
},
  "geometry": {"coordinates":[13.167189,52.420872],"type":"Point"}
}