{
  "type": "Feature",
  "properties": {
    "iso:country":"DE",
    "sg:address":"Hagedornstr. 21",
    "sg:city":"Halver",
    "sg:phone":"+49 2353/912950",
    "sg:postcode":"58553",
    "sg:province":"Nordrhein-Westfalen",
    "wof:name":"Hans Otto Eicker Architekt",
    "wof:placetype":"venue"
},
  "geometry": {"coordinates":[7.505854,51.185619],"type":"Point"}
}