{
  "type": "Feature",
  "properties": {
    "iso:country":"DE",
    "sg:address":"Kirchenweg 2",
    "sg:city":"Sittensen",
    "sg:phone":"+49 4282/933600",
    "sg:postcode":"27419",
    "sg:province":"Niedersachsen",
    "wof:name":"Landgasthof Oehr Sittensen Tagung Tagungen Seminar",
    "wof:placetype":"venue"
},
  "geometry": {"coordinates":[9.5047559738,53.2754631042],"type":"Point"}
}