{
  "type": "Feature",
  "properties": {
    "iso:country":"DE",
    "sg:address":"Bahnhofstr. 24",
    "sg:city":"B\u00f6blingen",
    "sg:phone":"+49 7031/236272",
    "sg:postcode":"71034",
    "sg:province":"Baden-W\u00fcrttemberg",
    "wof:name":"Argus Contactlinsen Und Brillen-optic Gmbh",
    "wof:placetype":"venue"
},
  "geometry": {"coordinates":[9.007179,48.686699],"type":"Point"}
}