{
  "type": "Feature",
  "properties": {
    "iso:country":"DE",
    "sg:address":"Johann-Strau\u00df-Str. 7/1",
    "sg:city":"Filderstadt",
    "sg:phone":"+49 7158/982327",
    "sg:postcode":"70794",
    "sg:province":"Baden-W\u00fcrttemberg",
    "wof:name":"Marx-st\u00e4dteguide",
    "wof:placetype":"venue"
},
  "geometry": {"coordinates":[9.2490158081,48.6484680176],"type":"Point"}
}