{
  "type": "Feature",
  "properties": {
    "iso:country":"DE",
    "sg:address":"Hauptstr. 24",
    "sg:city":"Ettringen",
    "sg:phone":"+49 8249/562",
    "sg:postcode":"86833",
    "sg:province":"Bayern",
    "wof:name":"Sparkasse Memmingen-mindelheim",
    "wof:placetype":"venue"
},
  "geometry": {"coordinates":[10.656779,48.104874],"type":"Point"}
}