{
  "type": "Feature",
  "properties": {
    "iso:country":"DE",
    "sg:address":"Kakabellenweg 11",
    "sg:city":"Eckernf\u00f6rde",
    "sg:phone":"+49 4351/6248",
    "sg:postcode":"24340",
    "sg:province":"Schleswig-Holstein",
    "wof:name":"Der Tabak-laden",
    "wof:placetype":"venue"
},
  "geometry": {"coordinates":[9.8358421326,54.4646949768],"type":"Point"}
}