{
  "type": "Feature",
  "properties": {
    "iso:country":"DE",
    "sg:address":"Rottweiler Str. 2",
    "sg:city":"Villingendorf",
    "sg:phone":"+49 741/3485992",
    "sg:postcode":"78667",
    "sg:province":"Baden-W\u00fcrttemberg",
    "wof:name":"Gastst\u00e4tte Zur Krone",
    "wof:placetype":"venue"
},
  "geometry": {"coordinates":[8.5899810791,48.2020225525],"type":"Point"}
}