{
  "type": "Feature",
  "properties": {
    "iso:country":"DE",
    "sg:address":"L\u00e4rchenweg 37",
    "sg:city":"Berlin",
    "sg:phone":"+49 30/3021567",
    "sg:postcode":"14055",
    "sg:province":"Berlin",
    "wof:name":"Ingrid Braune Heilpraktikerin",
    "wof:placetype":"venue"
},
  "geometry": {"coordinates":[13.265130043,52.4972114563],"type":"Point"}
}