{
  "type": "Feature",
  "properties": {
    "iso:country":"DE",
    "sg:address":"Bahnhofstr 9::",
    "sg:city":"Bornheim",
    "sg:phone":"+49 6734/94110",
    "sg:postcode":"55237",
    "sg:province":"Rheinland-Pfalz",
    "wof:name":"Raiffeisenbank Alzey-land Eg",
    "wof:placetype":"venue"
},
  "geometry": {"coordinates":[8.066855,49.780987],"type":"Point"}
}