{
  "type": "Feature",
  "properties": {
    "iso:country":"DE",
    "sg:address":"Weldener Str. 4",
    "sg:city":"Kaltental",
    "sg:phone":"+49 8345/338",
    "sg:postcode":"87662",
    "sg:province":"Bayern",
    "wof:name":"Kath. Pfarramt St. Peter Und Paul",
    "wof:placetype":"venue"
},
  "geometry": {"coordinates":[10.7535705566,47.9094581604],"type":"Point"}
}