{
  "type": "Feature",
  "properties": {
    "iso:country":"DE",
    "sg:address":"Rehstr. 3",
    "sg:city":"Eppenbrunn",
    "sg:phone":"+49 6335/1463",
    "sg:postcode":"66957",
    "sg:province":"Rheinland-Pfalz",
    "wof:name":"Bernd Und Sonja Hollerith",
    "wof:placetype":"venue"
},
  "geometry": {"coordinates":[7.5637130737,49.1177635193],"type":"Point"}
}