{
  "type": "Feature",
  "properties": {
    "iso:country":"DE",
    "sg:address":"Wolfhelmstr. 20",
    "sg:city":"Pulheim",
    "sg:phone":"+49 2234/84405",
    "sg:postcode":"50259",
    "sg:province":"Nordrhein-Westfalen",
    "wof:name":"Franz Fr\u00f6mbgen",
    "wof:placetype":"venue"
},
  "geometry": {"coordinates":[6.767763,50.957886],"type":"Point"}
}