{
  "type": "Feature",
  "properties": {
    "iso:country":"DE",
    "sg:address":"Neuer Wall 49",
    "sg:city":"Hamburg",
    "sg:postcode":"20354",
    "sg:province":"Hamburg",
    "wof:name":"H.a.g. Hanseatisches Auktionshaus Hamburg Gmbh",
    "wof:placetype":"venue"
},
  "geometry": {"coordinates":[9.9895887375,53.5510597229],"type":"Point"}
}