{
  "type": "Feature",
  "properties": {
    "iso:country":"DE",
    "sg:address":"Im Schee 10",
    "sg:city":"Essen",
    "sg:phone":"+49 201/510354",
    "sg:postcode":"45276",
    "sg:province":"Nordrhein-Westfalen",
    "wof:name":"Robert Strothe",
    "wof:placetype":"venue"
},
  "geometry": {"coordinates":[7.0635929108,51.4504013062],"type":"Point"}
}