{
  "type": "Feature",
  "properties": {
    "iso:country":"DE",
    "sg:address":"Alte Landstr. 5",
    "sg:city":"Medebach",
    "sg:phone":"+49 5632/7348",
    "sg:postcode":"59964",
    "sg:province":"Nordrhein-Westfalen",
    "wof:name":"Wilh. Deimel",
    "wof:placetype":"venue"
},
  "geometry": {"coordinates":[8.680848,51.247952],"type":"Point"}
}