{
  "type": "Feature",
  "properties": {
    "iso:country":"DE",
    "sg:address":"Leopold-Krawinkel-Stra\u00dfe 5",
    "sg:city":"Bergneustadt",
    "sg:phone":"+49 2261",
    "sg:postcode":"51702",
    "sg:province":"Nordrhein-Westfalen",
    "wof:name":"News Oberberg - Die Etwas Andere Onlinezeitung",
    "wof:placetype":"venue"
},
  "geometry": {"coordinates":[7.654072,51.021324],"type":"Point"}
}