{
  "type": "Feature",
  "properties": {
    "iso:country":"DE",
    "sg:address":"Hinterfeld 26",
    "sg:city":"Kaarst",
    "sg:phone":"+49 2131/65473",
    "sg:postcode":"41564",
    "sg:province":"Nordrhein-Westfalen",
    "wof:name":"J\u00fcrgen Bitzer Ingenieur",
    "wof:placetype":"venue"
},
  "geometry": {"coordinates":[6.6196928024,51.2217521667],"type":"Point"}
}