{
  "type": "Feature",
  "properties": {
    "iso:country":"DE",
    "sg:address":"Gro\u00dfheppacher Str. 68",
    "sg:city":"Weinstadt",
    "sg:phone":"+49 7151/967030",
    "sg:postcode":"71384",
    "sg:province":"Baden-W\u00fcrttemberg",
    "wof:name":"Toom-baumarkt Sb-baustoffvertrieb Gmbh",
    "wof:placetype":"venue"
},
  "geometry": {"coordinates":[9.3768777847,48.8143424988],"type":"Point"}
}