{
  "type": "Feature",
  "properties": {
    "iso:country":"DE",
    "sg:address":"Schiftunger Str. 9",
    "sg:city":"Sinzheim",
    "sg:phone":"+49 7221/81601",
    "sg:postcode":"76547",
    "sg:province":"Baden-W\u00fcrttemberg",
    "wof:name":"Walter Greulich",
    "wof:placetype":"venue"
},
  "geometry": {"coordinates":[8.14119,48.759785],"type":"Point"}
}