{
  "type": "Feature",
  "properties": {
    "iso:country":"DE",
    "sg:address":"Elzstr 6",
    "sg:city":"Sexau",
    "sg:phone":"+49 7641/915657",
    "sg:postcode":"79350",
    "sg:province":"Baden-W\u00fcrttemberg",
    "wof:name":"Druckerei Herbstritt Gmbh",
    "wof:placetype":"venue"
},
  "geometry": {"coordinates":[7.8909568787,48.0879173279],"type":"Point"}
}