{
  "type": "Feature",
  "properties": {
    "iso:country":"DE",
    "sg:address":"Dreifaltigkeitsweg 29",
    "sg:city":"Sinzig",
    "sg:phone":"+49 2642/97780",
    "sg:postcode":"53489",
    "sg:province":"Rheinland-Pfalz",
    "wof:name":"Praxis Dr. Med. Fleischmann Und Dr. Med. Klumpp",
    "wof:placetype":"venue"
},
  "geometry": {"coordinates":[7.2525119781,50.5481300354],"type":"Point"}
}