{
  "type": "Feature",
  "properties": {
    "iso:country":"DE",
    "sg:address":"Fetscherstr. 70",
    "sg:city":"Dresden",
    "sg:phone":"+49 351/44300",
    "sg:postcode":"01307",
    "sg:province":"Sachsen",
    "wof:name":"Orthop\u00e4die Rehatechnik Dresden Gmbh",
    "wof:placetype":"venue"
},
  "geometry": {"coordinates":[13.7780036926,51.0531959534],"type":"Point"}
}