{
  "type": "Feature",
  "properties": {
    "iso:country":"DE",
    "sg:address":"Beckstr. 141",
    "sg:city":"Bottrop",
    "sg:phone":"+49 2041/32163",
    "sg:postcode":"46238",
    "sg:province":"Nordrhein-Westfalen",
    "wof:name":"Ev. Pfarramt Batenbrock",
    "wof:placetype":"venue"
},
  "geometry": {"coordinates":[6.9500222206,51.5317764282],"type":"Point"}
}