{
  "type": "Feature",
  "properties": {
    "iso:country":"DE",
    "sg:address":"Erdbr\u00fcggenstr. 109",
    "sg:city":"Gelsenkirchen",
    "sg:phone":"+49 209/871238",
    "sg:postcode":"45889",
    "sg:province":"Nordrhein-Westfalen",
    "wof:name":"Arnhelm Lux",
    "wof:placetype":"venue"
},
  "geometry": {"coordinates":[7.129208,51.525921],"type":"Point"}
}