{
  "type": "Feature",
  "properties": {
    "iso:country":"DE",
    "sg:address":"Im Steg 18",
    "sg:city":"Ladenburg",
    "sg:phone":"+49 6203/922314",
    "sg:postcode":"68526",
    "sg:province":"Baden-W\u00fcrttemberg",
    "wof:name":"Hsi Immobilien Und Bautr\u00e4ger Gmbh",
    "wof:placetype":"venue"
},
  "geometry": {"coordinates":[8.618273,49.475834],"type":"Point"}
}