{
  "type": "Feature",
  "properties": {
    "iso:country":"DE",
    "sg:address":"Corveystr. 19",
    "sg:city":"Hamburg",
    "sg:phone":"+49 40/5511660",
    "sg:postcode":"22529",
    "sg:province":"Hamburg",
    "wof:name":"Hans Zernitz Ingenieur",
    "wof:placetype":"venue"
},
  "geometry": {"coordinates":[9.9688205719,53.5979270935],"type":"Point"}
}