{
  "type": "Feature",
  "properties": {
    "iso:country":"DE",
    "sg:address":"Blumenthalstr. 27",
    "sg:city":"K\u00f6ln",
    "sg:phone":"+49 221/7201700",
    "sg:postcode":"50670",
    "sg:province":"Nordrhein-Westfalen",
    "wof:name":"W. Mai Architekt",
    "wof:placetype":"venue"
},
  "geometry": {"coordinates":[6.960649,50.955395],"type":"Point"}
}