{
  "type": "Feature",
  "properties": {
    "iso:country":"DE",
    "sg:address":"D\u00fcsternortstr. 9",
    "sg:city":"Delmenhorst",
    "sg:phone":"+49 4221/6944",
    "sg:postcode":"27755",
    "sg:province":"Niedersachsen",
    "wof:name":"Ewald Gramberg",
    "wof:placetype":"venue"
},
  "geometry": {"coordinates":[8.637331,53.040848],"type":"Point"}
}