{
  "type": "Feature",
  "properties": {
    "iso:country":"DE",
    "sg:address":"M\u00f6llner Landstr. 28",
    "sg:city":"Oststeinbek",
    "sg:phone":"+49 40/7134712",
    "sg:postcode":"22113",
    "sg:province":"Schleswig-Holstein",
    "wof:name":"U. Dzienuda",
    "wof:placetype":"venue"
},
  "geometry": {"coordinates":[10.165678,53.542004],"type":"Point"}
}