{
  "type": "Feature",
  "properties": {
    "iso:country":"DE",
    "sg:address":"K\u00f6lner Strasse 159",
    "sg:city":"Weilerswist",
    "sg:postcode":"53919",
    "sg:province":"Nordrhein-Westfalen",
    "wof:name":"Gaststaette Em Faessje",
    "wof:placetype":"venue"
},
  "geometry": {"coordinates":[6.841586113,50.7596244812],"type":"Point"}
}