{
  "type": "Feature",
  "properties": {
    "iso:country":"DE",
    "sg:address":"Dr.-Robert-Pfleger-Str. 4",
    "sg:city":"Bamberg",
    "sg:phone":"+49 951/603361",
    "sg:postcode":"96052",
    "sg:province":"Bayern",
    "wof:name":"T\u00fcren-galerie H\u00fcbner E. Kfm.",
    "wof:placetype":"venue"
},
  "geometry": {"coordinates":[10.880664,49.909054],"type":"Point"}
}