{
  "type": "Feature",
  "properties": {
    "iso:country":"DE",
    "sg:address":"Nahariyastr. 11",
    "sg:city":"Berlin",
    "sg:phone":"+49 30/7462874",
    "sg:postcode":"12309",
    "sg:province":"Berlin",
    "wof:name":"M. Billen",
    "wof:placetype":"venue"
},
  "geometry": {"coordinates":[13.420075,52.390099],"type":"Point"}
}