{
  "type": "Feature",
  "properties": {
    "iso:country":"DE",
    "sg:address":"Deutsch-Haus 2",
    "sg:city":"Gangkofen",
    "sg:phone":"+49 8722/266",
    "sg:postcode":"84140",
    "sg:province":"Bayern",
    "wof:name":"Kath. Pfarramt Mari\u00e4 Himmelfahrt",
    "wof:placetype":"venue"
},
  "geometry": {"coordinates":[12.5615644455,48.437084198],"type":"Point"}
}