{
  "type": "Feature",
  "properties": {
    "iso:country":"DE",
    "sg:address":"Condomer Str. 22",
    "sg:city":"Gr\u00fcnberg",
    "sg:phone":"+49 6401/3681",
    "sg:postcode":"35305",
    "sg:province":"Hessen",
    "wof:name":"H. Becker-kl\u00f6s",
    "wof:placetype":"venue"
},
  "geometry": {"coordinates":[8.954303,50.588947],"type":"Point"}
}