{
  "type": "Feature",
  "properties": {
    "iso:country":"DE",
    "sg:address":"Moltkestr. 50",
    "sg:city":"Berlin",
    "sg:phone":"+49 30/8342139",
    "sg:postcode":"12203",
    "sg:province":"Berlin",
    "wof:name":"Gardesch\u00fctzen-apotheke",
    "wof:placetype":"venue"
},
  "geometry": {"coordinates":[13.307218,52.446655],"type":"Point"}
}