{
  "type": "Feature",
  "properties": {
    "iso:country":"DE",
    "sg:address":"Mayerbachstr. 6 a",
    "sg:city":"Rosenheim",
    "sg:phone":"+49 8031/381043",
    "sg:postcode":"83024",
    "sg:province":"Bayern",
    "wof:name":"Hcb Warenvertrieb Bleyenheuft Ohg",
    "wof:placetype":"venue"
},
  "geometry": {"coordinates":[12.1221704483,47.8686981201],"type":"Point"}
}