{
  "type": "Feature",
  "properties": {
    "iso:country":"DE",
    "sg:address":"Schwesternhausstr. 7",
    "sg:city":"Homburg",
    "sg:phone":"+49 6841/65326",
    "sg:postcode":"66424",
    "sg:province":"Saarland",
    "wof:name":"Hans-rainer Schaller & Carmen Rumlich",
    "wof:placetype":"venue"
},
  "geometry": {"coordinates":[7.3404111862,49.3191833496],"type":"Point"}
}