{
  "type": "Feature",
  "properties": {
    "iso:country":"DE",
    "sg:address":"Jakob-Krebs-Str. 36",
    "sg:city":"Willich",
    "sg:phone":"+49 2156/2312",
    "sg:postcode":"47877",
    "sg:province":"Nordrhein-Westfalen",
    "wof:name":"K\u00e4the Schuffelen Inh. Birgit Felde",
    "wof:placetype":"venue"
},
  "geometry": {"coordinates":[6.460472,51.279354],"type":"Point"}
}