{
  "type": "Feature",
  "properties": {
    "iso:country":"DE",
    "sg:address":"Am Alten General 31-33",
    "sg:city":"Bochum",
    "sg:phone":"+49 234/492060",
    "sg:postcode":"44879",
    "sg:province":"Nordrhein-Westfalen",
    "wof:name":"Friedhelm Schmidtbauer",
    "wof:placetype":"venue"
},
  "geometry": {"coordinates":[7.1479649544,51.4289016724],"type":"Point"}
}