{
  "type": "Feature",
  "properties": {
    "iso:country":"DE",
    "sg:address":"Hofweg 25",
    "sg:city":"Hamburg",
    "sg:phone":"+49 40/222701",
    "sg:postcode":"22085",
    "sg:province":"Hamburg",
    "wof:name":"Made In Italy",
    "wof:placetype":"venue"
},
  "geometry": {"coordinates":[10.0169906616,53.5700721741],"type":"Point"}
}