{
  "type": "Feature",
  "properties": {
    "iso:country":"DE",
    "sg:address":"Am Bloch 19",
    "sg:city":"Bad M\u00fcnstereifel",
    "sg:postcode":"53902",
    "sg:province":"Nordrhein-Westfalen",
    "wof:name":"Restaurator Und Tischlermeister Kolvenbach",
    "wof:placetype":"venue"
},
  "geometry": {"coordinates":[6.7709188461,50.5828208923],"type":"Point"}
}