{
  "type": "Feature",
  "properties": {
    "iso:country":"DE",
    "sg:address":"Am Sch\u00e4ferstock 1",
    "sg:city":"Mannheim",
    "sg:phone":"+49 4962/1419160",
    "sg:postcode":"68163",
    "sg:province":"Baden-W\u00fcrttemberg",
    "wof:name":"Elex Elektronik Gmbh",
    "wof:placetype":"venue"
},
  "geometry": {"coordinates":[8.503468,49.47514],"type":"Point"}
}