{
  "type": "Feature",
  "properties": {
    "iso:country":"DE",
    "sg:address":"Salzburger Str. 7",
    "sg:city":"Wasserburg",
    "sg:phone":"+49 8071/2554",
    "sg:postcode":"83512",
    "sg:province":"Bayern",
    "wof:name":"Hans Schauer",
    "wof:placetype":"venue"
},
  "geometry": {"coordinates":[12.2312545776,48.0574913025],"type":"Point"}
}