{
  "type": "Feature",
  "properties": {
    "iso:country":"DE",
    "sg:address":"Lange Wende 43",
    "sg:city":"Soest",
    "sg:phone":"+49 2921/990",
    "sg:postcode":"59494",
    "sg:province":"Nordrhein-Westfalen",
    "wof:name":"Actebis Computer Deutschland Gmbh",
    "wof:placetype":"venue"
},
  "geometry": {"coordinates":[8.139166832,51.5539665222],"type":"Point"}
}