{
  "type": "Feature",
  "properties": {
    "iso:country":"DE",
    "sg:address":"Schwarzwaldstr. 14",
    "sg:city":"Singen",
    "sg:phone":"+49 7731/69005",
    "sg:postcode":"78224",
    "sg:province":"Baden-W\u00fcrttemberg",
    "wof:name":"Klaus Speichinger",
    "wof:placetype":"venue"
},
  "geometry": {"coordinates":[8.8391361237,47.7611427307],"type":"Point"}
}