{
  "type": "Feature",
  "properties": {
    "iso:country":"DE",
    "sg:address":"L\u00fctticher Str. 29",
    "sg:city":"K\u00f6ln",
    "sg:postcode":"50674",
    "sg:province":"Nordrhein-Westfalen",
    "wof:name":"Karbar Karg & Barske Gmbh",
    "wof:placetype":"venue"
},
  "geometry": {"coordinates":[6.9359841347,50.9373588562],"type":"Point"}
}