{
  "type": "Feature",
  "properties": {
    "iso:country":"DE",
    "sg:address":"Weimarische Str. 60",
    "sg:city":"Erfurt",
    "sg:phone":"+49 361/4233262",
    "sg:postcode":"99099",
    "sg:province":"Th\u00fcringen",
    "wof:name":"Mcdonalds Deutschland",
    "wof:placetype":"venue"
},
  "geometry": {"coordinates":[11.0622415543,50.9744796753],"type":"Point"}
}