{
  "type": "Feature",
  "properties": {
    "iso:country":"DE",
    "sg:address":"Langer Graben 7",
    "sg:city":"Lemgo",
    "sg:phone":"+49 5261/7704974",
    "sg:postcode":"32657",
    "sg:province":"Nordrhein-Westfalen",
    "wof:name":"Rwsoft Thomas Wegener + Thorsten Reineking Gbr",
    "wof:placetype":"venue"
},
  "geometry": {"coordinates":[8.917413,52.031464],"type":"Point"}
}