{
  "type": "Feature",
  "properties": {
    "iso:country":"DE",
    "sg:address":"Ringstr. 3",
    "sg:city":"G\u00f6llnitz",
    "sg:phone":"+49 34495/428",
    "sg:postcode":"04626",
    "sg:province":"Th\u00fcringen",
    "wof:name":"Alfred Wojan",
    "wof:placetype":"venue"
},
  "geometry": {"coordinates":[12.318686,50.945835],"type":"Point"}
}