{
  "type": "Feature",
  "properties": {
    "iso:country":"DE",
    "sg:address":"Gro\u00dfe Marktstr. 4",
    "sg:city":"Offenbach",
    "sg:phone":"+49 69/887822",
    "sg:postcode":"63065",
    "sg:province":"Hessen",
    "wof:name":"Punkt-apotheke Inh. Edith Kruse",
    "wof:placetype":"venue"
},
  "geometry": {"coordinates":[8.764212,50.104218],"type":"Point"}
}