{
  "type": "Feature",
  "properties": {
    "iso:country":"DE",
    "sg:address":"Untertal 37",
    "sg:city":"Schuttertal",
    "sg:phone":"+49 7823/2055",
    "sg:postcode":"77978",
    "sg:province":"Baden-W\u00fcrttemberg",
    "wof:name":"Karl F. Obert",
    "wof:placetype":"venue"
},
  "geometry": {"coordinates":[7.9554448128,48.2845687866],"type":"Point"}
}