{
  "type": "Feature",
  "properties": {
    "iso:country":"DE",
    "sg:address":"Martensdamm 1-2",
    "sg:city":"Kiel",
    "sg:phone":"+49 431/98040",
    "sg:postcode":"24103",
    "sg:province":"Schleswig-Holstein",
    "wof:name":"Bank Companie Nord Ag",
    "wof:placetype":"venue"
},
  "geometry": {"coordinates":[10.136061,54.322861],"type":"Point"}
}