{
  "type": "Feature",
  "properties": {
    "iso:country":"DE",
    "sg:address":"Hein-Heckroth-Str. 34",
    "sg:city":"Gie\u00dfen",
    "sg:phone":"+49 641/42242",
    "sg:postcode":"35394",
    "sg:province":"Hessen",
    "wof:name":"Prof. Rudolf M\u00fcller Ingenieur",
    "wof:placetype":"venue"
},
  "geometry": {"coordinates":[8.6861047745,50.5805702209],"type":"Point"}
}