{
  "type": "Feature",
  "properties": {
    "iso:country":"DE",
    "sg:address":"Reichenberger Str. 4",
    "sg:city":"Zittau",
    "sg:phone":"+49 3583/512049",
    "sg:postcode":"02763",
    "sg:province":"Sachsen",
    "wof:name":"G\u00f6bel & Wei\u00df",
    "wof:placetype":"venue"
},
  "geometry": {"coordinates":[14.808501,50.895611],"type":"Point"}
}