{
  "type": "Feature",
  "properties": {
    "iso:country":"DE",
    "sg:address":"Schalmen\u00e4ckerstr. 4",
    "sg:city":"Klettgau",
    "sg:phone":"+49 7742/92330",
    "sg:postcode":"79771",
    "sg:province":"Baden-W\u00fcrttemberg",
    "wof:name":"Mack Alu-technik Gmbh",
    "wof:placetype":"venue"
},
  "geometry": {"coordinates":[8.395268,47.619789],"type":"Point"}
}