{
  "type": "Feature",
  "properties": {
    "iso:country":"DE",
    "sg:address":"Albstr. 35",
    "sg:city":"Reutlingen",
    "sg:phone":"+49 7121/334047",
    "sg:postcode":"72764",
    "sg:province":"Baden-W\u00fcrttemberg",
    "wof:name":"Al Dente",
    "wof:placetype":"venue"
},
  "geometry": {"coordinates":[9.2192258835,48.4885253906],"type":"Point"}
}