{
  "type": "Feature",
  "properties": {
    "iso:country":"DE",
    "sg:address":"Kirchenstr. 3",
    "sg:city":"Kiebitzreihe",
    "sg:postcode":"25368",
    "sg:province":"Schleswig-Holstein",
    "wof:name":"Igb Bau- Verwaltungs- Planungs- Gmbh & Co. Kg",
    "wof:placetype":"venue"
},
  "geometry": {"coordinates":[9.607138,53.780849],"type":"Point"}
}