{
  "type": "Feature",
  "properties": {
    "iso:country":"DE",
    "sg:address":"Eppendorfer Landstr. 36",
    "sg:city":"Hamburg",
    "sg:phone":"+49 800 6600099",
    "sg:postcode":"20249",
    "sg:province":"Hamburg",
    "wof:name":"Verbraucherberatung F\u00fcr Private Kranken- Und Renten-",
    "wof:placetype":"venue"
},
  "geometry": {"coordinates":[9.9847450256,53.5871391296],"type":"Point"}
}