{
  "type": "Feature",
  "properties": {
    "iso:country":"DE",
    "sg:address":"Monheimer Str. 5",
    "sg:city":"Neuburg",
    "sg:phone":"+49 8431/49966",
    "sg:postcode":"86633",
    "sg:province":"Bayern",
    "wof:name":"G\u00fcropack Gmbh",
    "wof:placetype":"venue"
},
  "geometry": {"coordinates":[11.1794939041,48.7404708862],"type":"Point"}
}