{
  "type": "Feature",
  "properties": {
    "iso:country":"DE",
    "sg:address":"Schlo\u00dfplatz 11",
    "sg:city":"Saarwellingen",
    "sg:phone":"+49 6838/80823",
    "sg:postcode":"66793",
    "sg:province":"Saarland",
    "wof:name":"A. Pintus",
    "wof:placetype":"venue"
},
  "geometry": {"coordinates":[6.8062081337,49.3532714844],"type":"Point"}
}