{
  "type": "Feature",
  "properties": {
    "iso:country":"DE",
    "sg:address":"Bahnhofstr. 14",
    "sg:city":"Wei\u00dfenburg",
    "sg:phone":"+49 9141/86750",
    "sg:postcode":"91781",
    "sg:province":"Bayern",
    "wof:name":"Anselm Gmbh & Co.",
    "wof:placetype":"venue"
},
  "geometry": {"coordinates":[10.9721403122,49.0329589844],"type":"Point"}
}