{
  "type": "Feature",
  "properties": {
    "iso:country":"DE",
    "sg:address":"Wampen 32",
    "sg:city":"Thiersheim",
    "sg:phone":"+49 9233/6184",
    "sg:postcode":"95707",
    "sg:province":"Bayern",
    "wof:name":"Stefan Romainczyk",
    "wof:placetype":"venue"
},
  "geometry": {"coordinates":[12.1043834686,50.0625152588],"type":"Point"}
}