{
  "type": "Feature",
  "properties": {
    "iso:country":"DE",
    "sg:address":"Angerstr. 19",
    "sg:city":"Mickhausen",
    "sg:phone":"+49 8204/1464",
    "sg:postcode":"86866",
    "sg:province":"Bayern",
    "wof:name":"Martin Bindl",
    "wof:placetype":"venue"
},
  "geometry": {"coordinates":[10.615773201,48.2133140564],"type":"Point"}
}