{
  "type": "Feature",
  "properties": {
    "iso:country":"DE",
    "sg:address":"Sarnowstr. 7",
    "sg:city":"Stralsund",
    "sg:postcode":"18435",
    "sg:province":"Mecklenburg-Vorpommern",
    "wof:name":"Mv Ratgeber Radio Beteiligungs Gmbh",
    "wof:placetype":"venue"
},
  "geometry": {"coordinates":[13.087752,54.318825],"type":"Point"}
}