{
  "type": "Feature",
  "properties": {
    "iso:country":"DE",
    "sg:address":"Untere Dorfstr. 19",
    "sg:city":"L\u00f6ffingen",
    "sg:phone":"+49 7654/922143",
    "sg:postcode":"79843",
    "sg:province":"Baden-W\u00fcrttemberg",
    "wof:name":"R. Heim Produktions-gmbh",
    "wof:placetype":"venue"
},
  "geometry": {"coordinates":[8.366849,47.90218],"type":"Point"}
}