{
  "type": "Feature",
  "properties": {
    "iso:country":"DE",
    "sg:address":"Hersfelder Str. 13c",
    "sg:city":"Bebra",
    "sg:phone":"+49 6622/92190",
    "sg:postcode":"36179",
    "sg:province":"Hessen",
    "wof:name":"W. Und L. Jordan Gro\u00dfhandels Gmbh",
    "wof:placetype":"venue"
},
  "geometry": {"coordinates":[9.795353,50.965542],"type":"Point"}
}