{
  "type": "Feature",
  "properties": {
    "iso:country":"DE",
    "sg:address":"Salvador-Allende-Str. 22 b",
    "sg:city":"Magdeburg",
    "sg:postcode":"39126",
    "sg:province":"Sachsen-Anhalt",
    "wof:name":"Aldi Gmbh & Co. Kg",
    "wof:placetype":"venue"
},
  "geometry": {"coordinates":[11.6416425705,52.1711578369],"type":"Point"}
}