{
  "type": "Feature",
  "properties": {
    "iso:country":"DE",
    "sg:address":"Karl-Wander-Str. 70",
    "sg:city":"Stollberg",
    "sg:postcode":"09366",
    "sg:province":"Sachsen",
    "wof:name":"Siegfried Keller",
    "wof:placetype":"venue"
},
  "geometry": {"coordinates":[12.7733697891,50.7030601501],"type":"Point"}
}