{
  "type": "Feature",
  "properties": {
    "iso:country":"DE",
    "sg:address":"Ranoldsberg 7",
    "sg:city":"Buchbach",
    "sg:phone":"+49 8086/445",
    "sg:postcode":"84428",
    "sg:province":"Bayern",
    "wof:name":"Kath. Pfarramt Mari\u00e4 Himmelfahrt",
    "wof:placetype":"venue"
},
  "geometry": {"coordinates":[12.2734537125,48.3125],"type":"Point"}
}