{
  "type": "Feature",
  "properties": {
    "iso:country":"DE",
    "sg:address":"Sommerhalde 18",
    "sg:city":"Ludwigsburg",
    "sg:phone":"+49 7144/6226",
    "sg:postcode":"71642",
    "sg:province":"Baden-W\u00fcrttemberg",
    "wof:name":"Gert Schreiber Anlageberater",
    "wof:placetype":"venue"
},
  "geometry": {"coordinates":[9.2652158737,48.9032402039],"type":"Point"}
}