{
  "type": "Feature",
  "properties": {
    "iso:country":"DE",
    "sg:address":"K\u00f6nigstr. 206",
    "sg:city":"Minden",
    "sg:phone":"+49 571/580518",
    "sg:postcode":"32427",
    "sg:province":"Nordrhein-Westfalen",
    "wof:name":"Fleischermeister Grill",
    "wof:placetype":"venue"
},
  "geometry": {"coordinates":[8.8768587112,52.2938232422],"type":"Point"}
}