{
  "type": "Feature",
  "properties": {
    "iso:country":"DE",
    "sg:address":"Wei\u00dfiger Str. 2 a",
    "sg:city":"Kleinopitz",
    "sg:phone":"+49 35203/2115",
    "sg:postcode":"01737",
    "sg:province":"Sachsen",
    "wof:name":"Jana S\u00fc\u00df",
    "wof:placetype":"venue"
},
  "geometry": {"coordinates":[13.592241,51.003742],"type":"Point"}
}