{
  "type": "Feature",
  "properties": {
    "iso:country":"DE",
    "sg:address":"Talstr. 6",
    "sg:city":"Deutschneudorf",
    "sg:phone":"+49 37368/250",
    "sg:postcode":"09548",
    "sg:province":"Sachsen",
    "wof:name":"Volkmar Br\u00fcckner",
    "wof:placetype":"venue"
},
  "geometry": {"coordinates":[13.454833,50.605713],"type":"Point"}
}