{
  "type": "Feature",
  "properties": {
    "iso:country":"DE",
    "sg:address":"St. Petersburger Str. 15",
    "sg:city":"Dresden",
    "sg:postcode":"01069",
    "sg:province":"Sachsen",
    "wof:name":"Debeka Lebensversicherungs- Verein A.g.",
    "wof:placetype":"venue"
},
  "geometry": {"coordinates":[13.741766,51.045937],"type":"Point"}
}