{
  "type": "Feature",
  "properties": {
    "iso:country":"DE",
    "sg:address":"Schleswiger Str. 44",
    "sg:city":"Kiel",
    "sg:phone":"+49 431/680966",
    "sg:postcode":"24113",
    "sg:province":"Schleswig-Holstein",
    "wof:name":"Michael Fischer Architekt",
    "wof:placetype":"venue"
},
  "geometry": {"coordinates":[10.109597,54.303364],"type":"Point"}
}