{
  "type": "Feature",
  "properties": {
    "iso:country":"DE",
    "sg:address":"Keltenweg 3",
    "sg:city":"Starnberg",
    "sg:phone":"+49 8151/16180",
    "sg:postcode":"82319",
    "sg:province":"Bayern",
    "wof:name":"Stephanie Straa\u00df",
    "wof:placetype":"venue"
},
  "geometry": {"coordinates":[11.2737379074,47.9996795654],"type":"Point"}
}