{
  "type": "Feature",
  "properties": {
    "iso:country":"DE",
    "sg:address":"An der Kohlstatt 2",
    "sg:city":"Neuburg",
    "sg:phone":"+49 8283/603",
    "sg:postcode":"86476",
    "sg:province":"Bayern",
    "wof:name":"S. H\u00f6sle",
    "wof:placetype":"venue"
},
  "geometry": {"coordinates":[10.3773918152,48.3147315979],"type":"Point"}
}