{
  "type": "Feature",
  "properties": {
    "iso:country":"DE",
    "sg:address":"Karlstr. 12",
    "sg:city":"Rheinfelden",
    "sg:phone":"+49 7623/30004",
    "sg:postcode":"79618",
    "sg:province":"Baden-W\u00fcrttemberg",
    "wof:name":"Restaurant China-town",
    "wof:placetype":"venue"
},
  "geometry": {"coordinates":[7.7885789871,47.5598487854],"type":"Point"}
}