{
  "type": "Feature",
  "properties": {
    "iso:country":"DE",
    "sg:address":"H\u00f6lderlinstr. 55",
    "sg:city":"Bopfingen",
    "sg:phone":"+49 4907/3627392",
    "sg:postcode":"73441",
    "sg:province":"Baden-W\u00fcrttemberg",
    "wof:name":"Outdoorshop Deubler Und Sohn",
    "wof:placetype":"venue"
},
  "geometry": {"coordinates":[10.347812,48.853184],"type":"Point"}
}