{
  "type": "Feature",
  "properties": {
    "iso:country":"DE",
    "sg:address":"Anebosstr. 15",
    "sg:city":"Annweiler",
    "sg:phone":"+49 6346/7104",
    "sg:postcode":"76855",
    "sg:province":"Rheinland-Pfalz",
    "wof:name":"Zum Kurtal",
    "wof:placetype":"venue"
},
  "geometry": {"coordinates":[7.9747610092,49.191204071],"type":"Point"}
}