{
  "type": "Feature",
  "properties": {
    "iso:country":"DE",
    "sg:address":"Am R\u00f6merweg 57",
    "sg:city":"Schifferstadt",
    "sg:phone":"+49 6235/3536",
    "sg:postcode":"67105",
    "sg:province":"Rheinland-Pfalz",
    "wof:name":"Egon Heberger",
    "wof:placetype":"venue"
},
  "geometry": {"coordinates":[8.374225,49.399345],"type":"Point"}
}