{
  "type": "Feature",
  "properties": {
    "iso:country":"DE",
    "sg:city":"Gommersheim",
    "sg:phone":"+49 4963/275560",
    "sg:postcode":"67377",
    "sg:province":"Rheinland-Pfalz",
    "wof:name":"Sparkasse S\u00fcdliche Weinstra\u00dfe Land.",
    "wof:placetype":"venue"
},
  "geometry": {"coordinates":[8.267263,49.291084],"type":"Point"}
}