{
  "type": "Feature",
  "properties": {
    "iso:country":"DE",
    "sg:address":"Wei\u00dfiger Str 8",
    "sg:city":"Langebr\u00fcck",
    "sg:phone":"+49 35201/70094",
    "sg:postcode":"01465",
    "sg:province":"Sachsen",
    "wof:name":"Saxotec Gmbh & Co Kg",
    "wof:placetype":"venue"
},
  "geometry": {"coordinates":[13.8461723328,51.12707901],"type":"Point"}
}