{
  "type": "Feature",
  "properties": {
    "iso:country":"DE",
    "sg:address":"Lange Str. 55",
    "sg:city":"Bernitt",
    "sg:phone":"+49 38464/20509",
    "sg:postcode":"18249",
    "sg:province":"Mecklenburg-Vorpommern",
    "wof:name":"Franz G\u00fcrtler",
    "wof:placetype":"venue"
},
  "geometry": {"coordinates":[11.8852329254,53.7853927612],"type":"Point"}
}