{
  "type": "Feature",
  "properties": {
    "iso:country":"DE",
    "sg:address":"Hansestr. 26",
    "sg:city":"Bentwisch",
    "sg:postcode":"18182",
    "sg:province":"Mecklenburg-Vorpommern",
    "wof:name":"Fn Reparatur- Und Montagegesellschaft Mbh",
    "wof:placetype":"venue"
},
  "geometry": {"coordinates":[12.1912498474,54.1134910583],"type":"Point"}
}