{
  "type": "Feature",
  "properties": {
    "iso:country":"DE",
    "sg:address":"Grindelhof 23",
    "sg:city":"Hamburg",
    "sg:phone":"+49 40/446608",
    "sg:postcode":"20146",
    "sg:province":"Hamburg",
    "wof:name":"Studentenblitz Gmbh Fotokopier- Und",
    "wof:placetype":"venue"
},
  "geometry": {"coordinates":[9.9824237823,53.5683441162],"type":"Point"}
}