{
  "type": "Feature",
  "properties": {
    "iso:country":"DE",
    "sg:address":"Jungfernstieg 26-30",
    "sg:city":"Hamburg",
    "sg:phone":"+49 40/352218",
    "sg:postcode":"20354",
    "sg:province":"Hamburg",
    "wof:name":"Montgomery Presents Werner Albers",
    "wof:placetype":"venue"
},
  "geometry": {"coordinates":[9.9913244247,53.5538787842],"type":"Point"}
}