{
  "type": "Feature",
  "properties": {
    "iso:country":"DE",
    "sg:address":"Kraienbruch 72",
    "sg:city":"Essen",
    "sg:phone":"+49 201/665578",
    "sg:postcode":"45357",
    "sg:province":"Nordrhein-Westfalen",
    "wof:name":"Malerbetrieb H.-g. Tissen Gmbh",
    "wof:placetype":"venue"
},
  "geometry": {"coordinates":[6.940563,51.491337],"type":"Point"}
}