{
  "type": "Feature",
  "properties": {
    "iso:country":"DE",
    "sg:address":"Siemensring 4",
    "sg:city":"R\u00fclzheim",
    "sg:phone":"+49 7272/4920",
    "sg:postcode":"76761",
    "sg:province":"Rheinland-Pfalz",
    "wof:name":"Neways Noni Maximol Gef\u00e4hrliche Inhaltsstoffe",
    "wof:placetype":"venue"
},
  "geometry": {"coordinates":[8.295513,49.156193],"type":"Point"}
}