{
  "type": "Feature",
  "properties": {
    "iso:country":"DE",
    "sg:address":"Adoplf-Holst-Str. 26",
    "sg:city":"B\u00fcckeburg",
    "sg:phone":"+49 5722/23071",
    "sg:postcode":"31675",
    "sg:province":"Niedersachsen",
    "wof:name":"Internet Marketing Services",
    "wof:placetype":"venue"
},
  "geometry": {"coordinates":[9.0555677414,52.2511444092],"type":"Point"}
}