{
  "type": "Feature",
  "properties": {
    "iso:country":"DE",
    "sg:address":"Sch\u00e4fergasse 29",
    "sg:city":"Frankfurt",
    "sg:phone":"+49 69/281348",
    "sg:postcode":"60313",
    "sg:province":"Hessen",
    "wof:name":"Eldorado",
    "wof:placetype":"venue"
},
  "geometry": {"coordinates":[8.685172,50.116776],"type":"Point"}
}