{
  "type": "Feature",
  "properties": {
    "iso:country":"DE",
    "sg:address":"Friedrich-Wilhelm-Str. 18",
    "sg:city":"Voerde",
    "sg:phone":"+49 2855/6551",
    "sg:postcode":"46562",
    "sg:province":"Nordrhein-Westfalen",
    "wof:name":"Westerfeld",
    "wof:placetype":"venue"
},
  "geometry": {"coordinates":[6.6177067757,51.6097297668],"type":"Point"}
}