{
  "type": "Feature",
  "properties": {
    "iso:country":"DE",
    "sg:address":"Fr\u00f6schbacher Str. 16",
    "sg:city":"Biberach",
    "sg:phone":"+49 7835/8798",
    "sg:postcode":"77781",
    "sg:province":"Baden-W\u00fcrttemberg",
    "wof:name":"Helmut Beck Architekt",
    "wof:placetype":"venue"
},
  "geometry": {"coordinates":[8.02355,48.344845],"type":"Point"}
}