{
  "type": "Feature",
  "properties": {
    "iso:country":"DE",
    "sg:address":"Vellandstr. 14",
    "sg:city":"D\u00f6rpen",
    "sg:phone":"+49 4963/1881",
    "sg:postcode":"26892",
    "sg:province":"Niedersachsen",
    "wof:name":"Rita Schwarz Masseurin",
    "wof:placetype":"venue"
},
  "geometry": {"coordinates":[7.335195,52.963856],"type":"Point"}
}