{
  "type": "Feature",
  "properties": {
    "iso:country":"DE",
    "sg:address":"M\u00fcnchner Str. 28",
    "sg:city":"Augsburg",
    "sg:phone":"+49 821/662472",
    "sg:postcode":"86163",
    "sg:province":"Bayern",
    "wof:name":"Wolfgang Baur",
    "wof:placetype":"venue"
},
  "geometry": {"coordinates":[10.9464864731,48.3444328308],"type":"Point"}
}