{
  "type": "Feature",
  "properties": {
    "iso:country":"DE",
    "sg:address":"Stadtplatz 25",
    "sg:city":"Osterhofen",
    "sg:phone":"+49 9932/908090",
    "sg:postcode":"94486",
    "sg:province":"Bayern",
    "wof:name":"Bayerischer Hof",
    "wof:placetype":"venue"
},
  "geometry": {"coordinates":[13.0189886093,48.7023735046],"type":"Point"}
}