{
  "type": "Feature",
  "properties": {
    "iso:country":"DE",
    "sg:address":"Ferdinandstr. 41",
    "sg:city":"Hamburg",
    "sg:phone":"+49 40/337383",
    "sg:postcode":"20095",
    "sg:province":"Hamburg",
    "wof:name":"Stolte & Charlier Gmbh",
    "wof:placetype":"venue"
},
  "geometry": {"coordinates":[9.999471,53.553593],"type":"Point"}
}