{
  "type": "Feature",
  "properties": {
    "iso:country":"DE",
    "sg:address":"Hasenstr. 3",
    "sg:city":"Zirndorf",
    "sg:phone":"+49 911/604776",
    "sg:postcode":"90513",
    "sg:province":"Bayern",
    "wof:name":"G. Michalek",
    "wof:placetype":"venue"
},
  "geometry": {"coordinates":[10.947686,49.444775],"type":"Point"}
}