{
  "type": "Feature",
  "properties": {
    "iso:country":"DE",
    "sg:address":"Bullenhuser Damm 54",
    "sg:city":"Hamburg",
    "sg:phone":"+49 40/201038",
    "sg:postcode":"20539",
    "sg:province":"Hamburg",
    "wof:name":"Import Und Export Honary Inh. Henry-aqa Sayed",
    "wof:placetype":"venue"
},
  "geometry": {"coordinates":[10.0445756912,53.5424041748],"type":"Point"}
}