{
  "type": "Feature",
  "properties": {
    "iso:country":"DE",
    "sg:address":"Seligenst\u00e4dter Weg",
    "sg:city":"Prosselsheim",
    "sg:phone":"+49 9386/218",
    "sg:postcode":"97279",
    "sg:province":"Bayern",
    "wof:name":"Gitschel & Marx",
    "wof:placetype":"venue"
},
  "geometry": {"coordinates":[10.1269960403,49.8615036011],"type":"Point"}
}