{
  "type": "Feature",
  "properties": {
    "iso:country":"DE",
    "sg:address":"Ahrenloher Str. 98",
    "sg:city":"Tornesch",
    "sg:phone":"+49 4122/52327",
    "sg:postcode":"25436",
    "sg:province":"Schleswig-Holstein",
    "wof:name":"Hermann Neumann",
    "wof:placetype":"venue"
},
  "geometry": {"coordinates":[9.729486,53.703075],"type":"Point"}
}