{
  "type": "Feature",
  "properties": {
    "iso:country":"DE",
    "sg:address":"Industriering Ost 26",
    "sg:city":"Kempen",
    "sg:postcode":"47906",
    "sg:province":"Nordrhein-Westfalen",
    "wof:name":"Nothers Textilges. Mbh",
    "wof:placetype":"venue"
},
  "geometry": {"coordinates":[6.434522,51.365509],"type":"Point"}
}