{
  "type": "Feature",
  "properties": {
    "iso:country":"DE",
    "sg:address":"Hillenstr. 4",
    "sg:city":"Dillingen",
    "sg:phone":"+49 6831/73189",
    "sg:postcode":"66763",
    "sg:province":"Saarland",
    "wof:name":"Blumenhaus Philipp Inh. Katja Malter",
    "wof:placetype":"venue"
},
  "geometry": {"coordinates":[6.727245,49.350979],"type":"Point"}
}