{
  "type": "Feature",
  "properties": {
    "iso:country":"DE",
    "sg:address":"Bahnhofstr. 4",
    "sg:city":"Sindelfingen",
    "sg:phone":"+49 7031/793730",
    "sg:postcode":"71063",
    "sg:province":"Baden-W\u00fcrttemberg",
    "wof:name":"Thomas Hess & Partner Hausverwaltungs Gmbh",
    "wof:placetype":"venue"
},
  "geometry": {"coordinates":[9.0018033981,48.7073478699],"type":"Point"}
}