{
  "type": "Feature",
  "properties": {
    "iso:country":"DE",
    "sg:address":"K\u00f6nigsberger Str. 32",
    "sg:city":"Kriftel",
    "sg:phone":"+49 6192/911434",
    "sg:postcode":"65830",
    "sg:province":"Hessen",
    "wof:name":"P. Jansen Ingenieurb\u00fcro",
    "wof:placetype":"venue"
},
  "geometry": {"coordinates":[8.461632,50.087116],"type":"Point"}
}