{
  "type": "Feature",
  "properties": {
    "iso:country":"DE",
    "sg:address":"Lindenweg 4",
    "sg:city":"Ettlingen",
    "sg:phone":"+49 7243/761710",
    "sg:postcode":"76275",
    "sg:province":"Baden-W\u00fcrttemberg",
    "wof:name":"Hermann Duffner Schraubenfabrik Gmbh & Co",
    "wof:placetype":"venue"
},
  "geometry": {"coordinates":[8.385232,48.950794],"type":"Point"}
}