{
  "type": "Feature",
  "properties": {
    "iso:country":"DE",
    "sg:address":"Tannenkampweg",
    "sg:city":"Wolgast",
    "sg:phone":"+49 3836/602431",
    "sg:postcode":"17438",
    "sg:province":"Mecklenburg-Vorpommern",
    "wof:name":"Tierpark Tannenkamp Wolgast",
    "wof:placetype":"venue"
},
  "geometry": {"coordinates":[13.774815,54.066833],"type":"Point"}
}