{
  "type": "Feature",
  "properties": {
    "iso:country":"DE",
    "sg:address":"Br\u00fcckenstr. 118",
    "sg:city":"Ummerstadt",
    "sg:phone":"+49 36871/21706",
    "sg:postcode":"98663",
    "sg:province":"Th\u00fcringen",
    "wof:name":"Stadt Schleusingen Am S\u00fcdhang Des Th\u00fcringer Waldes",
    "wof:placetype":"venue"
},
  "geometry": {"coordinates":[10.807642,50.258938],"type":"Point"}
}