{
  "type": "Feature",
  "properties": {
    "iso:country":"DE",
    "sg:address":"Liebknechtstr. 26-27",
    "sg:city":"Zeitz",
    "sg:phone":"+49 3441/213185",
    "sg:postcode":"06712",
    "sg:province":"Sachsen-Anhalt",
    "wof:name":"M - S- P Wohnideen Gmbh",
    "wof:placetype":"venue"
},
  "geometry": {"coordinates":[12.1409463882,51.0479011536],"type":"Point"}
}