{
  "type": "Feature",
  "properties": {
    "iso:country":"DE",
    "sg:address":"Ernst-Th\u00e4lmann-Str. 21",
    "sg:city":"Mobschatz",
    "sg:phone":"+49 351/4537595",
    "sg:postcode":"01462",
    "wof:name":"Walter Schumann",
    "wof:placetype":"venue"
},
  "geometry": {"coordinates":[13.6450500488,51.0793304443],"type":"Point"}
}