{
  "type": "Feature",
  "properties": {
    "iso:country":"DE",
    "sg:address":"Kirchstr. 5",
    "sg:city":"Langquaid",
    "sg:postcode":"84085",
    "sg:province":"Bayern",
    "wof:name":"B\u00f6schl & Dechant Bau Gmbh",
    "wof:placetype":"venue"
},
  "geometry": {"coordinates":[12.013174057,48.787399292],"type":"Point"}
}