{
  "type": "Feature",
  "properties": {
    "iso:country":"DE",
    "sg:address":"In der Lander 37",
    "sg:city":"Bad Sassendorf",
    "sg:phone":"+49 2921/59060",
    "sg:postcode":"59505",
    "sg:province":"Nordrhein-Westfalen",
    "wof:name":"Reinhardt Delle Design Verwaltungs Gmbh",
    "wof:placetype":"venue"
},
  "geometry": {"coordinates":[8.189101,51.590458],"type":"Point"}
}