{
  "type": "Feature",
  "properties": {
    "iso:country":"DE",
    "sg:address":"Str\u00fcbelweg 14",
    "sg:city":"Alfdorf",
    "sg:phone":"+49 7172/937110",
    "sg:postcode":"73553",
    "sg:province":"Baden-W\u00fcrttemberg",
    "wof:name":"Kaleja Elektronik Gmbh",
    "wof:placetype":"venue"
},
  "geometry": {"coordinates":[9.720982,48.845509],"type":"Point"}
}