{
  "type": "Feature",
  "properties": {
    "iso:country":"DE",
    "sg:address":"Im kleinen Feld 10",
    "sg:city":"Ratingen",
    "sg:phone":"+49 2102/34218",
    "sg:postcode":"40885",
    "sg:province":"Nordrhein-Westfalen",
    "wof:name":"Monika Und Karl-heinz Wiegand Krankengymnasten",
    "wof:placetype":"venue"
},
  "geometry": {"coordinates":[6.83115,51.329121],"type":"Point"}
}