{
  "type": "Feature",
  "properties": {
    "iso:country":"DE",
    "sg:address":"Frankenweg 41",
    "sg:city":"Bochum",
    "sg:phone":"+49 2327/57115",
    "sg:postcode":"44867",
    "sg:province":"Nordrhein-Westfalen",
    "wof:name":"Helmut Hoffmann",
    "wof:placetype":"venue"
},
  "geometry": {"coordinates":[7.1521849632,51.4668426514],"type":"Point"}
}