{
  "type": "Feature",
  "properties": {
    "iso:country":"DE",
    "sg:address":"Holzkamp 7",
    "sg:city":"Korschenbroich",
    "sg:postcode":"41352",
    "sg:province":"Nordrhein-Westfalen",
    "wof:name":"Asia-therme- Wellness-spa Gmbh",
    "wof:placetype":"venue"
},
  "geometry": {"coordinates":[6.5509681702,51.1934204102],"type":"Point"}
}