{
  "type": "Feature",
  "properties": {
    "iso:country":"DE",
    "sg:address":"Christian-Klengel-Str. 5",
    "sg:city":"Kesselsdorf",
    "sg:postcode":"01723",
    "sg:province":"Sachsen",
    "wof:name":"Evangelisches Pfarramt Kesselsdorf",
    "wof:placetype":"venue"
},
  "geometry": {"coordinates":[13.5907783508,51.0312423706],"type":"Point"}
}