{
  "type": "Feature",
  "properties": {
    "iso:country":"DE",
    "sg:address":"Horrenberger Str. 9",
    "sg:city":"Zuzenhausen",
    "sg:phone":"+49 6226/8029",
    "sg:postcode":"74939",
    "sg:province":"Baden-W\u00fcrttemberg",
    "wof:name":"Fritz Kirsch",
    "wof:placetype":"venue"
},
  "geometry": {"coordinates":[8.822781,49.294746],"type":"Point"}
}