{
  "type": "Feature",
  "properties": {
    "iso:country":"DE",
    "sg:address":"Betzenm\u00fchle 2",
    "sg:city":"Schonungen",
    "sg:phone":"+49 9727/8906",
    "sg:postcode":"97453",
    "sg:province":"Bayern",
    "wof:name":"W. Brazdrum Ingenieur",
    "wof:placetype":"venue"
},
  "geometry": {"coordinates":[10.3241405487,50.0551109314],"type":"Point"}
}