{
  "type": "Feature",
  "properties": {
    "iso:country":"DE",
    "sg:address":"Amtsdamm",
    "sg:city":"Hagen",
    "sg:postcode":"27628",
    "sg:province":"Niedersachsen",
    "wof:name":"Flore & Schr\u00f6der Grundst\u00fccks- Verwaltungs Gmbh & Co. Kg",
    "wof:placetype":"venue"
},
  "geometry": {"coordinates":[8.6524782181,53.3592224121],"type":"Point"}
}