{
  "type": "Feature",
  "properties": {
    "iso:country":"DE",
    "sg:address":"Rahlandsweg 25",
    "sg:city":"Bremerv\u00f6rde",
    "sg:phone":"+49 4761/5044",
    "sg:postcode":"27432",
    "sg:province":"Niedersachsen",
    "wof:name":"Frank Und Grudrun Thiele Rechtsanw\u00e4lte Und Notare",
    "wof:placetype":"venue"
},
  "geometry": {"coordinates":[9.1437702179,53.4898109436],"type":"Point"}
}