{
  "type": "Feature",
  "properties": {
    "iso:country":"DE",
    "sg:address":"Am G\u00e4nsekamp 10",
    "sg:city":"Wolfsburg",
    "sg:postcode":"38446",
    "sg:province":"Niedersachsen",
    "wof:name":"Izv Innovationen Zur Verbrennungstechnik Gmbh",
    "wof:placetype":"venue"
},
  "geometry": {"coordinates":[10.8352270126,52.4000053406],"type":"Point"}
}