{
  "type": "Feature",
  "properties": {
    "iso:country":"DE",
    "sg:address":"Heidegartenstr. 10",
    "sg:city":"Dudenhofen",
    "sg:phone":"+49 6232/93084",
    "sg:postcode":"67373",
    "sg:province":"Rheinland-Pfalz",
    "wof:name":"Theo Bettag",
    "wof:placetype":"venue"
},
  "geometry": {"coordinates":[8.391404,49.320206],"type":"Point"}
}