{
  "type": "Feature",
  "properties": {
    "iso:country":"DE",
    "sg:address":"Industriestr. 15",
    "sg:city":"Mettingen",
    "sg:phone":"+49 5452/811",
    "sg:postcode":"49497",
    "sg:province":"Nordrhein-Westfalen",
    "wof:name":"Lothar Albers Wurst Schinken Und Feinkosthandel E. K.",
    "wof:placetype":"venue"
},
  "geometry": {"coordinates":[7.7907481194,52.3143157959],"type":"Point"}
}