{
  "type": "Feature",
  "properties": {
    "iso:country":"DE",
    "sg:address":"Hauptstr. 19",
    "sg:city":"K\u00e4mpfelbach",
    "sg:phone":"+49 4972/322443",
    "sg:postcode":"75236",
    "sg:province":"Baden-W\u00fcrttemberg",
    "wof:name":"Volksbank Stein Eg",
    "wof:placetype":"venue"
},
  "geometry": {"coordinates":[8.621156,48.948826],"type":"Point"}
}