{
  "type": "Feature",
  "properties": {
    "iso:country":"DE",
    "sg:address":"Steinknappen 43",
    "sg:city":"M\u00fclheim",
    "sg:phone":"+49 208/372162",
    "sg:postcode":"45470",
    "sg:province":"Nordrhein-Westfalen",
    "wof:name":"Dieter Wirth Ingenieur",
    "wof:placetype":"venue"
},
  "geometry": {"coordinates":[6.9042768478,51.4084358215],"type":"Point"}
}