{
  "type": "Feature",
  "properties": {
    "iso:country":"DE",
    "sg:address":"Hauptstr. 26",
    "sg:city":"Reifferscheid",
    "sg:phone":"+49 2691/1313",
    "sg:postcode":"53520",
    "sg:province":"Rheinland-Pfalz",
    "wof:name":"Kl\u00e4re Marx",
    "wof:placetype":"venue"
},
  "geometry": {"coordinates":[6.8848900795,50.4057044983],"type":"Point"}
}