{
  "type": "Feature",
  "properties": {
    "iso:country":"DE",
    "sg:address":"Heideweg 9",
    "sg:city":"Kettenkamp",
    "sg:phone":"+49 5436/354",
    "sg:postcode":"49577",
    "sg:province":"Niedersachsen",
    "wof:name":"Leonberger Bausparkasse Frank Kottmann",
    "wof:placetype":"venue"
},
  "geometry": {"coordinates":[7.826233,52.584789],"type":"Point"}
}