{
  "type": "Feature",
  "properties": {
    "iso:country":"DE",
    "sg:address":"Seeheimer Str. 26",
    "sg:city":"Pfungstadt",
    "sg:phone":"+49 6157/6455",
    "sg:postcode":"64319",
    "sg:province":"Hessen",
    "wof:name":"Emil Ro\u00dfbach Architekt",
    "wof:placetype":"venue"
},
  "geometry": {"coordinates":[8.60168,49.800289],"type":"Point"}
}