{
  "type": "Feature",
  "properties": {
    "iso:country":"DE",
    "sg:address":"Luise-Brachmann-Str. 82",
    "sg:city":"Wei\u00dfenfels",
    "sg:phone":"+49 3443/234846",
    "sg:postcode":"06667",
    "sg:province":"Sachsen-Anhalt",
    "wof:name":"Manfred M\u00fcller",
    "wof:placetype":"venue"
},
  "geometry": {"coordinates":[11.98041,51.190491],"type":"Point"}
}