{
  "type": "Feature",
  "properties": {
    "iso:country":"DE",
    "sg:address":"Schorndorfer Str. 67",
    "sg:city":"Waiblingen",
    "sg:phone":"+49 7151/1310",
    "sg:postcode":"71332",
    "sg:province":"Baden-W\u00fcrttemberg",
    "wof:name":"Stadtwerke Waiblingen Gmbh",
    "wof:placetype":"venue"
},
  "geometry": {"coordinates":[9.323011,48.827332],"type":"Point"}
}