{
  "type": "Feature",
  "properties": {
    "iso:country":"DE",
    "sg:address":"Hochstr. 35",
    "sg:city":"Gelsenkirchen",
    "sg:phone":"+49 209/930670",
    "sg:postcode":"45894",
    "sg:province":"Nordrhein-Westfalen",
    "wof:name":"Hettlage & Fischer Gmbh",
    "wof:placetype":"venue"
},
  "geometry": {"coordinates":[7.052016,51.580235],"type":"Point"}
}