{
  "type": "Feature",
  "properties": {
    "iso:country":"DE",
    "sg:address":"Woldlinie 44a",
    "sg:city":"Bad Zwischenahn",
    "sg:phone":"+49 4486/8661",
    "sg:postcode":"26160",
    "sg:province":"Niedersachsen",
    "wof:name":"A. Schr\u00f6der",
    "wof:placetype":"venue"
},
  "geometry": {"coordinates":[8.096715,53.153057],"type":"Point"}
}