{
  "type": "Feature",
  "properties": {
    "iso:country":"DE",
    "sg:address":"Schweinedeich 5",
    "sg:city":"B\u00fcsum",
    "sg:phone":"+49 4834/2295",
    "sg:postcode":"25761",
    "sg:province":"Schleswig-Holstein",
    "wof:name":"Campingplatz Perlebucht",
    "wof:placetype":"venue"
},
  "geometry": {"coordinates":[8.846291,54.135887],"type":"Point"}
}