{
  "type": "Feature",
  "properties": {
    "iso:country":"DE",
    "sg:address":"Baumschulenweg 24",
    "sg:city":"Rathenow",
    "sg:phone":"+49 3385/513158",
    "sg:postcode":"14712",
    "sg:province":"Brandenburg",
    "wof:name":"Erich Kny",
    "wof:placetype":"venue"
},
  "geometry": {"coordinates":[12.314846,52.609169],"type":"Point"}
}