{
  "type": "Feature",
  "properties": {
    "iso:country":"DE",
    "sg:address":"Dorfstrase 22",
    "sg:city":"Moers",
    "sg:phone":"+49 2841/394600",
    "sg:postcode":"47447",
    "sg:province":"Nordrhein-Westfalen",
    "wof:name":"E-w-p Technik Herbert Kallen",
    "wof:placetype":"venue"
},
  "geometry": {"coordinates":[6.650442,51.423927],"type":"Point"}
}