{
  "type": "Feature",
  "properties": {
    "iso:country":"DE",
    "sg:address":"Marienwasserstr. 85",
    "sg:city":"Goch",
    "sg:phone":"+49 2823/97010",
    "sg:postcode":"47574",
    "sg:province":"Nordrhein-Westfalen",
    "wof:name":"Rtu Heinz H\u00fcgging Revisions Treuhand- Und Unternehmens-",
    "wof:placetype":"venue"
},
  "geometry": {"coordinates":[6.1643028259,51.6687469482],"type":"Point"}
}