{
  "type": "Feature",
  "properties": {
    "iso:country":"DE",
    "sg:address":"Pl. D. Republik",
    "sg:city":"Frankfurt",
    "sg:phone":"+49 4969/744701",
    "sg:postcode":"60265",
    "sg:province":"Brandenburg",
    "wof:name":"Dz Bank Ag",
    "wof:placetype":"venue"
},
  "geometry": {"coordinates":[8.6843,50.112251],"type":"Point"}
}