{
  "type": "Feature",
  "properties": {
    "iso:country":"DE",
    "sg:address":"Herrenstr. 5",
    "sg:city":"Ratzeburg",
    "sg:phone":"+49 4541/3771",
    "sg:postcode":"23909",
    "sg:province":"Schleswig-Holstein",
    "wof:name":"Gerd Habeck",
    "wof:placetype":"venue"
},
  "geometry": {"coordinates":[10.772724,53.698936],"type":"Point"}
}