{
  "type": "Feature",
  "properties": {
    "iso:country":"DE",
    "sg:address":"Am Kranen 2",
    "sg:city":"Bamberg",
    "sg:phone":"+49 951/21788",
    "sg:postcode":"96047",
    "sg:province":"Bayern",
    "wof:name":"Johann Holland",
    "wof:placetype":"venue"
},
  "geometry": {"coordinates":[10.8873901367,49.89220047],"type":"Point"}
}