{
  "type": "Feature",
  "properties": {
    "iso:country":"DE",
    "sg:address":"Carl-Friedrich-Gau\u00df-Stra\u00dfe 12",
    "sg:city":"Kamp-Lintfort",
    "sg:phone":"+49 2842/91430",
    "sg:postcode":"47475",
    "sg:province":"Nordrhein-Westfalen",
    "wof:name":"Grateach Gmbh",
    "wof:placetype":"venue"
},
  "geometry": {"coordinates":[6.534232,51.484447],"type":"Point"}
}