{
  "type": "Feature",
  "properties": {
    "iso:country":"DE",
    "sg:address":"R1",
    "sg:city":"Mannheim",
    "sg:phone":"+49 621",
    "sg:postcode":"68161",
    "sg:province":"Baden-W\u00fcrttemberg",
    "wof:name":"Grunert Medien & Kommunikation Gmbh",
    "wof:placetype":"venue"
},
  "geometry": {"coordinates":[8.468855,49.489094],"type":"Point"}
}