{
  "type": "Feature",
  "properties": {
    "iso:country":"DE",
    "sg:address":"Ernst-Ludwig-Str. 62",
    "sg:city":"Egelsbach",
    "sg:phone":"+49 6103/49196",
    "sg:postcode":"63329",
    "sg:province":"Hessen",
    "wof:name":"Walter Kuehn Drogerie",
    "wof:placetype":"venue"
},
  "geometry": {"coordinates":[8.66767,49.969521],"type":"Point"}
}