{
  "type": "Feature",
  "properties": {
    "iso:country":"DE",
    "sg:address":"Vorderb\u00fchlweg 2",
    "sg:city":"Oppenau",
    "sg:phone":"+49 7804/524",
    "sg:postcode":"77728",
    "sg:province":"Baden-W\u00fcrttemberg",
    "wof:name":"Doll",
    "wof:placetype":"venue"
},
  "geometry": {"coordinates":[8.1627168655,48.4682235718],"type":"Point"}
}