{
  "type": "Feature",
  "properties": {
    "iso:country":"DE",
    "sg:address":"Obernheimer Str. 28",
    "sg:city":"Reichenbach",
    "sg:postcode":"78564",
    "sg:province":"Baden-W\u00fcrttemberg",
    "wof:name":"Kath. Pfarramt St. Nikolaus",
    "wof:placetype":"venue"
},
  "geometry": {"coordinates":[8.7917013168,48.1458625793],"type":"Point"}
}