{
  "type": "Feature",
  "properties": {
    "iso:country":"DE",
    "sg:address":"Gr\u00fcnefelder Str. 10 b",
    "sg:city":"Berlin",
    "sg:phone":"+49 30/3753640",
    "sg:postcode":"13589",
    "sg:province":"Berlin",
    "wof:name":"Manfred Neuenfeldt",
    "wof:placetype":"venue"
},
  "geometry": {"coordinates":[13.1811361313,52.5595321655],"type":"Point"}
}