{
  "type": "Feature",
  "properties": {
    "iso:country":"DE",
    "sg:address":"K\u00f6nigbacher Str. 15",
    "sg:city":"Ortenburg",
    "sg:phone":"+49 8542/1680",
    "sg:postcode":"94496",
    "sg:province":"Bayern",
    "wof:name":"Micro-epsilon Messtechnik Gmbh & Co Kg",
    "wof:placetype":"venue"
},
  "geometry": {"coordinates":[13.237836,48.528782],"type":"Point"}
}