{
  "type": "Feature",
  "properties": {
    "iso:country":"DE",
    "sg:address":"H\u00fcttenstr. 133-135",
    "sg:city":"Aachen",
    "sg:phone":"+49 241/551691",
    "sg:postcode":"52068",
    "sg:province":"Nordrhein-Westfalen",
    "wof:name":"Steinrath Gmbh",
    "wof:placetype":"venue"
},
  "geometry": {"coordinates":[6.140254,50.776878],"type":"Point"}
}