{
  "type": "Feature",
  "properties": {
    "iso:country":"DE",
    "sg:address":"Luitpoldplatz 5",
    "sg:city":"Sulzbach",
    "sg:phone":"+49 9661/5300",
    "sg:postcode":"92237",
    "sg:province":"Bayern",
    "wof:name":"Sparkasse Sulzbach-rosenberg",
    "wof:placetype":"venue"
},
  "geometry": {"coordinates":[11.738726,49.505112],"type":"Point"}
}