{
  "type": "Feature",
  "properties": {
    "iso:country":"DE",
    "sg:address":"Arkonaplatz 5",
    "sg:city":"Berlin",
    "sg:phone":"+49 30/44340505",
    "sg:postcode":"10435",
    "sg:province":"Berlin",
    "wof:name":"Acht Eichen G\u00fcter- Und Liegenschaftsverwaltung Gmbh",
    "wof:placetype":"venue"
},
  "geometry": {"coordinates":[13.4014787674,52.5375747681],"type":"Point"}
}