{
  "type": "Feature",
  "properties": {
    "iso:country":"DE",
    "sg:address":"Kastanienallee 6",
    "sg:city":"Leer",
    "sg:phone":"+49 491/71030",
    "sg:postcode":"26789",
    "sg:province":"Niedersachsen",
    "wof:name":"W. Siebelts",
    "wof:placetype":"venue"
},
  "geometry": {"coordinates":[7.4794511795,53.2362823486],"type":"Point"}
}