{
  "type": "Feature",
  "properties": {
    "iso:country":"DE",
    "sg:address":"Wankelstr. 9",
    "sg:city":"Moormerland",
    "sg:phone":"+49 4954/6713",
    "sg:postcode":"26802",
    "sg:province":"Niedersachsen",
    "wof:name":"Andreas Tempel Gmbh",
    "wof:placetype":"venue"
},
  "geometry": {"coordinates":[7.4658031464,53.3138275146],"type":"Point"}
}