{
  "type": "Feature",
  "properties": {
    "iso:country":"DE",
    "sg:address":"Burggasse 2",
    "sg:city":"K\u00fcnzelsau",
    "sg:phone":"+49 7940/55477",
    "sg:postcode":"74653",
    "sg:province":"Baden-W\u00fcrttemberg",
    "wof:name":"Renate M\u00fcller Krankengymnastin",
    "wof:placetype":"venue"
},
  "geometry": {"coordinates":[9.690562,49.278648],"type":"Point"}
}