{
  "type": "Feature",
  "properties": {
    "iso:country":"DE",
    "sg:address":"Ringstr. 16",
    "sg:city":"Altlandsberg",
    "sg:phone":"+49 33438/61294",
    "sg:postcode":"15345",
    "sg:province":"Brandenburg",
    "wof:name":"Christel Stepputat",
    "wof:placetype":"venue"
},
  "geometry": {"coordinates":[13.773685,52.561516],"type":"Point"}
}