{
  "type": "Feature",
  "properties": {
    "iso:country":"DE",
    "sg:address":"H\u00f6nower Str. 230",
    "sg:city":"Berlin",
    "sg:postcode":"12623",
    "sg:province":"Berlin",
    "wof:name":"Elektronik Schubert",
    "wof:placetype":"venue"
},
  "geometry": {"coordinates":[13.622442,52.525219],"type":"Point"}
}