{
  "type": "Feature",
  "properties": {
    "iso:country":"DE",
    "sg:address":"Robert-Mayer-Str. 4",
    "sg:city":"Urbach",
    "sg:phone":"+49 7181/98730",
    "sg:postcode":"73660",
    "sg:province":"Baden-W\u00fcrttemberg",
    "wof:name":"Lutz Markisen",
    "wof:placetype":"venue"
},
  "geometry": {"coordinates":[9.564949,48.810318],"type":"Point"}
}