{
  "type": "Feature",
  "properties": {
    "iso:country":"DE",
    "sg:address":"Darmst\u00e4dter Str. 5",
    "sg:city":"Bischofsheim",
    "sg:phone":"+49 6144/42661",
    "sg:postcode":"65474",
    "sg:province":"Hessen",
    "wof:name":"Backhaus",
    "wof:placetype":"venue"
},
  "geometry": {"coordinates":[8.3551778793,49.988658905],"type":"Point"}
}