{
  "type": "Feature",
  "properties": {
    "iso:country":"DE",
    "sg:address":"Dodenauer Str. 6",
    "sg:city":"Battenberg",
    "sg:phone":"+49 6452/3386",
    "sg:postcode":"35088",
    "sg:province":"Hessen",
    "wof:name":"Stefan Dreher",
    "wof:placetype":"venue"
},
  "geometry": {"coordinates":[8.6370668411,51.0134658813],"type":"Point"}
}