{
  "type": "Feature",
  "properties": {
    "iso:country":"DE",
    "sg:address":"Lichtensteinstr. 4",
    "sg:city":"Frankfurt",
    "sg:phone":"+49 69/150513",
    "sg:postcode":"60322",
    "sg:province":"Hessen",
    "wof:name":"Reuss Und Partner",
    "wof:placetype":"venue"
},
  "geometry": {"coordinates":[8.6820392609,50.1270561218],"type":"Point"}
}