{
  "type": "Feature",
  "properties": {
    "iso:country":"DE",
    "sg:address":"Rosenbergstr. 151",
    "sg:city":"Wiltingen",
    "sg:phone":"+49 6501/17360",
    "sg:postcode":"54459",
    "sg:province":"Rheinland-Pfalz",
    "wof:name":"Arnold Turbing-class",
    "wof:placetype":"venue"
},
  "geometry": {"coordinates":[6.5920190811,49.6604881287],"type":"Point"}
}