{
  "type": "Feature",
  "properties": {
    "iso:country":"DE",
    "sg:address":"Hildastr. 1",
    "sg:city":"Eppelheim",
    "sg:phone":"+49 6221/758476",
    "sg:postcode":"69214",
    "sg:province":"Baden-W\u00fcrttemberg",
    "wof:name":"Restaurant 's Pf\u00e4nnle",
    "wof:placetype":"venue"
},
  "geometry": {"coordinates":[8.6342630386,49.4010658264],"type":"Point"}
}