{
  "type": "Feature",
  "properties": {
    "iso:country":"DE",
    "sg:address":"Strandpromenade",
    "sg:city":"Timmendorfer Strand",
    "sg:phone":"+49 4503/1454",
    "sg:postcode":"23669",
    "sg:province":"Schleswig-Holstein",
    "wof:name":"R\u00fcdiger Harnisch",
    "wof:placetype":"venue"
},
  "geometry": {"coordinates":[10.805850029,53.9897842407],"type":"Point"}
}