{
  "type": "Feature",
  "properties": {
    "iso:country":"DE",
    "sg:address":"Westerwaldstr. 21",
    "sg:city":"Ehringshausen",
    "sg:phone":"+49 6449/92300",
    "sg:postcode":"35630",
    "sg:province":"Hessen",
    "wof:name":"Biosun Gmbh",
    "wof:placetype":"venue"
},
  "geometry": {"coordinates":[8.3252887726,50.6094512939],"type":"Point"}
}