{
  "type": "Feature",
  "properties": {
    "iso:country":"DE",
    "sg:address":"Hauptstr. 15",
    "sg:city":"Ettringen",
    "sg:phone":"+49 2651/6222",
    "sg:postcode":"56729",
    "sg:province":"Rheinland-Pfalz",
    "wof:name":"Restaurant Eifelperle",
    "wof:placetype":"venue"
},
  "geometry": {"coordinates":[7.2220702171,50.355506897],"type":"Point"}
}