{
  "type": "Feature",
  "properties": {
    "iso:country":"DE",
    "sg:address":"Dietesheimer Str. 2",
    "sg:city":"M\u00fchlheim",
    "sg:phone":"+49 6108/76507",
    "sg:postcode":"63165",
    "sg:province":"Hessen",
    "wof:name":"Steffie Carlsen",
    "wof:placetype":"venue"
},
  "geometry": {"coordinates":[8.832758,50.124943],"type":"Point"}
}