{
  "type": "Feature",
  "properties": {
    "iso:country":"DE",
    "sg:address":"H\u00f6seler Str. 50",
    "sg:city":"Heiligenhaus",
    "sg:phone":"+49 2056/20028",
    "sg:postcode":"42579",
    "sg:province":"Nordrhein-Westfalen",
    "wof:name":"Wkg",
    "wof:placetype":"venue"
},
  "geometry": {"coordinates":[6.945024,51.325424],"type":"Point"}
}