{
  "type": "Feature",
  "properties": {
    "iso:country":"DE",
    "sg:address":"Wullener Feld 20",
    "sg:city":"Witten",
    "sg:phone":"+49 2302/699046",
    "sg:postcode":"58454",
    "sg:province":"Nordrhein-Westfalen",
    "wof:name":"Gr\u00fcnewald Chemie Gmbh",
    "wof:placetype":"venue"
},
  "geometry": {"coordinates":[7.364331,51.457279],"type":"Point"}
}