{
  "type": "Feature",
  "properties": {
    "iso:country":"DE",
    "sg:address":"Seitenstr. 1 / 1",
    "sg:city":"Schwaikheim",
    "sg:phone":"+49 7195/51198",
    "sg:postcode":"71409",
    "sg:province":"Baden-W\u00fcrttemberg",
    "wof:name":"Walter Strobel",
    "wof:placetype":"venue"
},
  "geometry": {"coordinates":[9.352549,48.873875],"type":"Point"}
}