{
  "type": "Feature",
  "properties": {
    "iso:country":"DE",
    "sg:address":"L\u00fcneburger Str. 7",
    "sg:city":"Bremen",
    "sg:postcode":"28205",
    "sg:province":"Bremen",
    "wof:name":"Biochemischer Verein Dr. Sch\u00fc\u00dfler E. V.",
    "wof:placetype":"venue"
},
  "geometry": {"coordinates":[8.8327207565,53.0692596436],"type":"Point"}
}