{
  "type": "Feature",
  "properties": {
    "iso:country":"DE",
    "sg:address":"Berta-Morena-Weg 10",
    "sg:city":"Rottach-Egern",
    "sg:phone":"+49 8022/5384",
    "sg:postcode":"83700",
    "sg:province":"Bayern",
    "wof:name":"Josef Strohschneider Architekt",
    "wof:placetype":"venue"
},
  "geometry": {"coordinates":[11.767141,47.691204],"type":"Point"}
}