{
  "type": "Feature",
  "properties": {
    "iso:country":"DE",
    "sg:address":"Leinstr. 19",
    "sg:city":"Alfeld",
    "sg:phone":"+49 5181/26201",
    "sg:postcode":"31061",
    "sg:province":"Niedersachsen",
    "wof:name":"Rossmann Drogeriemarkt",
    "wof:placetype":"venue"
},
  "geometry": {"coordinates":[9.824324,51.984997],"type":"Point"}
}