{
  "type": "Feature",
  "properties": {
    "iso:country":"DE",
    "sg:address":"Am Br\u00fcckentor 15",
    "sg:city":"Mayen",
    "sg:phone":"+49 2651/2427",
    "sg:postcode":"56727",
    "sg:province":"Rheinland-Pfalz",
    "wof:name":"Pfaff",
    "wof:placetype":"venue"
},
  "geometry": {"coordinates":[7.2250652313,50.3300361633],"type":"Point"}
}