{
  "type": "Feature",
  "properties": {
    "iso:country":"DE",
    "sg:address":"Sjip-Wai 6",
    "sg:city":"Kampen",
    "sg:phone":"+49 4651/41780",
    "sg:postcode":"25999",
    "sg:province":"Schleswig-Holstein",
    "wof:name":"Haus Inken",
    "wof:placetype":"venue"
},
  "geometry": {"coordinates":[8.3456201553,54.9531745911],"type":"Point"}
}