{
  "type": "Feature",
  "properties": {
    "iso:country":"DE",
    "sg:address":"Englerstr. 26",
    "sg:city":"Ettlingen",
    "sg:phone":"+49 4972/4354000",
    "sg:postcode":"76275",
    "sg:province":"Baden-W\u00fcrttemberg",
    "wof:name":"Im Marketing-forum Gmbh",
    "wof:placetype":"venue"
},
  "geometry": {"coordinates":[8.379586,48.945816],"type":"Point"}
}