{
  "type": "Feature",
  "properties": {
    "iso:country":"DE",
    "sg:address":"Obere Kaiserstr. 94",
    "sg:city":"St. Ingbert",
    "sg:phone":"+49 6894/51389",
    "sg:postcode":"66386",
    "sg:province":"Saarland",
    "wof:name":"E. Haberer",
    "wof:placetype":"venue"
},
  "geometry": {"coordinates":[7.133262,49.285858],"type":"Point"}
}