{
  "type": "Feature",
  "properties": {
    "iso:country":"DE",
    "sg:address":"Simon-H\u00f6ller-Str. 4",
    "sg:city":"Straubing",
    "sg:phone":"+49 9421/22191",
    "sg:postcode":"94315",
    "sg:province":"Bayern",
    "wof:name":"Hilmer Architekturb\u00fcro",
    "wof:placetype":"venue"
},
  "geometry": {"coordinates":[12.569133,48.882797],"type":"Point"}
}