{
  "type": "Feature",
  "properties": {
    "iso:country":"DE",
    "sg:address":"Hamburger Str. 43",
    "sg:city":"L\u00fctjensee",
    "sg:phone":"+49 4154/7276",
    "sg:postcode":"22952",
    "sg:province":"Schleswig-Holstein",
    "wof:name":"Hermann M\u00fcller Gmbh",
    "wof:placetype":"venue"
},
  "geometry": {"coordinates":[10.3645610809,53.6527404785],"type":"Point"}
}