{
  "type": "Feature",
  "properties": {
    "iso:country":"DE",
    "sg:address":"Heilwigstr. 36",
    "sg:city":"Hamburg",
    "sg:postcode":"20249",
    "sg:province":"Hamburg",
    "wof:name":"Cea Beratungs-und Be- Teiligungs-gmbh",
    "wof:placetype":"venue"
},
  "geometry": {"coordinates":[9.994351,53.582447],"type":"Point"}
}