{
  "type": "Feature",
  "properties": {
    "iso:country":"DE",
    "sg:address":"Pappelweg 11",
    "sg:city":"Gerlingen",
    "sg:phone":"+49 7156/23436",
    "sg:postcode":"70839",
    "sg:province":"Baden-W\u00fcrttemberg",
    "wof:name":"Werner Franke Steuerberater",
    "wof:placetype":"venue"
},
  "geometry": {"coordinates":[9.083483696,48.8016586304],"type":"Point"}
}