{
  "type": "Feature",
  "properties": {
    "iso:country":"DE",
    "sg:address":"Saynstr. 22",
    "sg:city":"Hachenburg",
    "sg:phone":"+49 4926/6295130",
    "sg:postcode":"57627",
    "sg:province":"Rheinland-Pfalz",
    "wof:name":"Leonhard Heyden By Pelz Neu Gmbh",
    "wof:placetype":"venue"
},
  "geometry": {"coordinates":[7.814352,50.664223],"type":"Point"}
}