{
  "type": "Feature",
  "properties": {
    "iso:country":"DE",
    "sg:address":"Sch\u00fctzenstr. 109",
    "sg:city":"Hamburg",
    "sg:phone":"+49 40/8500099",
    "sg:postcode":"22761",
    "sg:province":"Hamburg",
    "wof:name":"Wrage Service Gmbh",
    "wof:placetype":"venue"
},
  "geometry": {"coordinates":[9.928468,53.568836],"type":"Point"}
}