{
  "type": "Feature",
  "properties": {
    "iso:country":"DE",
    "sg:address":"Kielmannseggstr. 78",
    "sg:city":"Hamburg",
    "sg:postcode":"22043",
    "sg:province":"Hamburg",
    "wof:name":"Zsv Zeitungs-supplements- Verlagsges. Mbh & Co. Kg",
    "wof:placetype":"venue"
},
  "geometry": {"coordinates":[10.0927333832,53.5671730042],"type":"Point"}
}