{
  "type": "Feature",
  "properties": {
    "iso:country":"DE",
    "sg:address":"Reuthstr. 9",
    "sg:city":"Oberkotzau",
    "sg:phone":"+49 9286/6212",
    "sg:postcode":"95145",
    "sg:province":"Bayern",
    "wof:name":"Friedrichsruh",
    "wof:placetype":"venue"
},
  "geometry": {"coordinates":[11.9306488037,50.2723045349],"type":"Point"}
}