{
  "type": "Feature",
  "properties": {
    "iso:country":"DE",
    "sg:address":"Hindenburgstr. 55",
    "sg:city":"Weil der Stadt",
    "sg:phone":"+49 7033/7619",
    "sg:postcode":"71263",
    "sg:province":"Baden-W\u00fcrttemberg",
    "wof:name":"Gerd Fr\u00e4nkel Architekt",
    "wof:placetype":"venue"
},
  "geometry": {"coordinates":[8.860152,48.750149],"type":"Point"}
}