{
  "type": "Feature",
  "properties": {
    "iso:country":"DE",
    "sg:address":"Rosenheimer Str. 20",
    "sg:city":"Kolbermoor",
    "sg:phone":"+49 8031/91984",
    "sg:postcode":"83059",
    "sg:province":"Bayern",
    "wof:name":"Franz Dei\u00dfer",
    "wof:placetype":"venue"
},
  "geometry": {"coordinates":[12.065307,47.850098],"type":"Point"}
}