{
  "type": "Feature",
  "properties": {
    "iso:country":"DE",
    "sg:address":"Todtnauer Str. 6",
    "sg:city":"Freiburg",
    "sg:phone":"+49 761/44900",
    "sg:postcode":"79115",
    "sg:province":"Baden-W\u00fcrttemberg",
    "wof:name":"Taxi-union E. K.",
    "wof:placetype":"venue"
},
  "geometry": {"coordinates":[7.8250870705,47.979850769],"type":"Point"}
}