{
  "type": "Feature",
  "properties": {
    "iso:country":"DE",
    "sg:address":"Pastorendamm 10 a",
    "sg:city":"Tornesch",
    "sg:phone":"+49 4122/54566",
    "sg:postcode":"25436",
    "sg:province":"Schleswig-Holstein",
    "wof:name":"Herta Bludau Inh. S. Kr\u00fcger",
    "wof:placetype":"venue"
},
  "geometry": {"coordinates":[9.7120294571,53.7069511414],"type":"Point"}
}