{
  "type": "Feature",
  "properties": {
    "iso:country":"DE",
    "sg:address":"Moritz-Werner-Str. 7",
    "sg:city":"Eschwege",
    "sg:phone":"+49 5651/5569",
    "sg:postcode":"37269",
    "sg:province":"Hessen",
    "wof:name":"St. Vinzenz",
    "wof:placetype":"venue"
},
  "geometry": {"coordinates":[10.047291,51.18729],"type":"Point"}
}