{
  "type": "Feature",
  "properties": {
    "iso:country":"DE",
    "sg:address":"Buschberger Weg 45",
    "sg:city":"Norderstedt",
    "sg:phone":"+49 40/5221635",
    "sg:postcode":"22844",
    "sg:province":"Schleswig-Holstein",
    "wof:name":"T. Metelmann",
    "wof:placetype":"venue"
},
  "geometry": {"coordinates":[10.0041742325,53.7300415039],"type":"Point"}
}