{
  "type": "Feature",
  "properties": {
    "iso:country":"DE",
    "sg:address":"Landsberger Allee 221",
    "sg:city":"Berlin",
    "sg:phone":"+49 30/97105420",
    "sg:postcode":"13055",
    "sg:province":"Berlin",
    "wof:name":"Manfred Adaszewski",
    "wof:placetype":"venue"
},
  "geometry": {"coordinates":[13.4873914719,52.5348396301],"type":"Point"}
}