{
  "type": "Feature",
  "properties": {
    "iso:country":"DE",
    "sg:address":"Langenfelder Str. 119",
    "sg:city":"Leverkusen",
    "sg:postcode":"51371",
    "sg:province":"Nordrhein-Westfalen",
    "wof:name":"Rubin Leasing Gmbh",
    "wof:placetype":"venue"
},
  "geometry": {"coordinates":[6.9257102013,51.074798584],"type":"Point"}
}