{
  "type": "Feature",
  "properties": {
    "iso:country":"DE",
    "sg:address":"Schm\u00f6llner Str. 14",
    "sg:city":"Schm\u00f6lln",
    "sg:phone":"+49 34491/80803",
    "sg:postcode":"04626",
    "sg:province":"Th\u00fcringen",
    "wof:name":"K.-h. Stroech",
    "wof:placetype":"venue"
},
  "geometry": {"coordinates":[12.3862981796,50.9203338623],"type":"Point"}
}