{
  "type": "Feature",
  "properties": {
    "iso:country":"DE",
    "sg:address":"Walther-Rathenau-Str. 87",
    "sg:city":"Ludwigsfelde",
    "sg:postcode":"14974",
    "sg:province":"Brandenburg",
    "wof:name":"Protea Gmbh",
    "wof:placetype":"venue"
},
  "geometry": {"coordinates":[13.249261,52.296192],"type":"Point"}
}