{
  "type": "Feature",
  "properties": {
    "iso:country":"DE",
    "sg:address":"Im Altengarten 9",
    "sg:city":"Gleiszellen-Gleishorbach",
    "sg:phone":"+49 6343/2331",
    "sg:postcode":"76889",
    "sg:province":"Rheinland-Pfalz",
    "wof:name":"Ernst Semar Gmbh",
    "wof:placetype":"venue"
},
  "geometry": {"coordinates":[8.004624,49.125256],"type":"Point"}
}