{
  "type": "Feature",
  "properties": {
    "iso:country":"DE",
    "sg:address":"L\u00fcbarser Str. 2 a",
    "sg:city":"Berlin",
    "sg:phone":"+49 30/40360040",
    "sg:postcode":"13435",
    "sg:province":"Berlin",
    "wof:name":"Harry Gusek Gmbh",
    "wof:placetype":"venue"
},
  "geometry": {"coordinates":[13.332467,52.599354],"type":"Point"}
}