{
  "type": "Feature",
  "properties": {
    "iso:country":"DE",
    "sg:address":"Go\u00dfholzer Str. 8",
    "sg:city":"Lindenberg",
    "sg:phone":"+49 8381/92060",
    "sg:postcode":"88161",
    "sg:province":"Bayern",
    "wof:name":"Erich Leiter Steuerbevollm\u00e4chtigter",
    "wof:placetype":"venue"
},
  "geometry": {"coordinates":[9.8950004578,47.6082496643],"type":"Point"}
}