{
  "type": "Feature",
  "properties": {
    "iso:country":"DE",
    "sg:address":"Werningshof 7",
    "sg:city":"Bielefeld",
    "sg:phone":"+49 521/934000",
    "sg:postcode":"33719",
    "sg:province":"Nordrhein-Westfalen",
    "wof:name":"Galox Gmbh",
    "wof:placetype":"venue"
},
  "geometry": {"coordinates":[8.5973072052,52.0377388],"type":"Point"}
}