{
  "type": "Feature",
  "properties": {
    "iso:country":"DE",
    "sg:address":"Am Hofgarten 1",
    "sg:city":"Freising",
    "sg:phone":"+49 8161/713200",
    "sg:postcode":"85354",
    "sg:province":"Bayern",
    "wof:name":"Sichtungsgarten Der Fach- Hochschule Weihenstephan",
    "wof:placetype":"venue"
},
  "geometry": {"coordinates":[11.731773,48.396057],"type":"Point"}
}