{
  "type": "Feature",
  "properties": {
    "iso:country":"DE",
    "sg:address":"Uhlandstr. 7",
    "sg:city":"Bad Neuenahr-Ahrweiler",
    "sg:phone":"+49 2641/27019",
    "sg:postcode":"53474",
    "sg:province":"Rheinland-Pfalz",
    "wof:name":"Jak-sport Und Freizeitanlagen Gmbh",
    "wof:placetype":"venue"
},
  "geometry": {"coordinates":[7.1240668297,50.5441665649],"type":"Point"}
}