{
  "type": "Feature",
  "properties": {
    "iso:country":"DE",
    "sg:address":"Juliuspromenade 56",
    "sg:city":"W\u00fcrzburg",
    "sg:phone":"+49 931/404490",
    "sg:postcode":"97070",
    "sg:province":"Bayern",
    "wof:name":"Mlp Finanzdienstleistungen Ag",
    "wof:placetype":"venue"
},
  "geometry": {"coordinates":[9.9299707413,49.7967224121],"type":"Point"}
}