{
  "type": "Feature",
  "properties": {
    "iso:country":"DE",
    "sg:address":"Neust\u00e4dter Str. 19",
    "sg:city":"Wunstorf",
    "sg:phone":"+49 5031/5764",
    "sg:postcode":"31515",
    "sg:province":"Niedersachsen",
    "wof:name":"E. Lange",
    "wof:placetype":"venue"
},
  "geometry": {"coordinates":[9.4288625717,52.432559967],"type":"Point"}
}