{
  "type": "Feature",
  "properties": {
    "iso:country":"DE",
    "sg:address":"Hauptstr. 31",
    "sg:city":"Ederheim",
    "sg:phone":"+49 9081/23634",
    "sg:postcode":"86739",
    "sg:province":"Bayern",
    "wof:name":"H. Geyer",
    "wof:placetype":"venue"
},
  "geometry": {"coordinates":[10.467631,48.80909],"type":"Point"}
}