{
  "type": "Feature",
  "properties": {
    "iso:country":"DE",
    "sg:address":"August-Bebel-Str. 11",
    "sg:city":"Cavertitz",
    "sg:postcode":"04758",
    "sg:province":"Sachsen",
    "wof:name":"Landhotel Zur M\u00fchle Verwaltungs Gmbh",
    "wof:placetype":"venue"
},
  "geometry": {"coordinates":[13.0383119583,51.3790245056],"type":"Point"}
}