{
  "type": "Feature",
  "properties": {
    "iso:country":"DE",
    "sg:address":"Friedrichstr. 54",
    "sg:city":"Schleswig",
    "sg:phone":"+49 4621/32739",
    "sg:postcode":"24837",
    "sg:province":"Schleswig-Holstein",
    "wof:name":"Willy Jochims",
    "wof:placetype":"venue"
},
  "geometry": {"coordinates":[9.541805,54.502506],"type":"Point"}
}