{
  "type": "Feature",
  "properties": {
    "iso:country":"DE",
    "sg:address":"Zartener Str. 42",
    "sg:city":"Kirchzarten",
    "sg:phone":"+49 7661/980296",
    "sg:postcode":"79199",
    "sg:province":"Baden-W\u00fcrttemberg",
    "wof:name":"G. U. Kappler",
    "wof:placetype":"venue"
},
  "geometry": {"coordinates":[7.9523601532,47.9689750671],"type":"Point"}
}