{
  "type": "Feature",
  "properties": {
    "iso:country":"DE",
    "sg:address":"Zehnthofstr. 56",
    "sg:city":"D\u00fcren",
    "sg:phone":"+49 2421/14172",
    "sg:postcode":"52349",
    "sg:province":"Nordrhein-Westfalen",
    "wof:name":"Carl Gottschalk",
    "wof:placetype":"venue"
},
  "geometry": {"coordinates":[6.482441,50.804352],"type":"Point"}
}