{
  "type": "Feature",
  "properties": {
    "iso:country":"DE",
    "sg:address":"Robert-Koch-Str. 37",
    "sg:city":"Norderstedt",
    "sg:phone":"+49 40/5243472",
    "sg:postcode":"22851",
    "sg:province":"Schleswig-Holstein",
    "wof:name":"Paul Jentzig",
    "wof:placetype":"venue"
},
  "geometry": {"coordinates":[10.0507316589,53.6852111816],"type":"Point"}
}