{
  "type": "Feature",
  "properties": {
    "iso:country":"DE",
    "sg:address":"Industriestr. 15",
    "sg:city":"Ergolding",
    "sg:phone":"+49 871/75170",
    "sg:postcode":"84030",
    "sg:province":"Bayern",
    "wof:name":"Heryschek Baugesch\u00e4ft Gmbh",
    "wof:placetype":"venue"
},
  "geometry": {"coordinates":[12.160842,48.562218],"type":"Point"}
}