{
  "type": "Feature",
  "properties": {
    "iso:country":"DE",
    "sg:address":"Bergstr. 3",
    "sg:city":"Reichartshausen",
    "sg:phone":"+49 6262/6712",
    "sg:postcode":"74934",
    "sg:province":"Baden-W\u00fcrttemberg",
    "wof:name":"Gerhard Schilling",
    "wof:placetype":"venue"
},
  "geometry": {"coordinates":[8.941383,49.360832],"type":"Point"}
}