{
  "type": "Feature",
  "properties": {
    "iso:country":"DE",
    "sg:address":"Blumenthaler Str. 80",
    "sg:city":"Schwanewede",
    "sg:phone":"+49 4209/93210",
    "sg:postcode":"28790",
    "sg:province":"Niedersachsen",
    "wof:name":"Senioren Zentrum Am Wifowald Gmbh",
    "wof:placetype":"venue"
},
  "geometry": {"coordinates":[8.585334,53.216278],"type":"Point"}
}