{
  "type": "Feature",
  "properties": {
    "iso:country":"DE",
    "sg:address":"Taunusstr. 44",
    "sg:city":"Wiesbaden",
    "sg:phone":"+49 611/524864",
    "sg:postcode":"65183",
    "sg:province":"Hessen",
    "wof:name":"Ad. M\u00fcller Und S\u00f6hne",
    "wof:placetype":"venue"
},
  "geometry": {"coordinates":[8.239809,50.088638],"type":"Point"}
}