{
  "type": "Feature",
  "properties": {
    "iso:country":"DE",
    "sg:address":"An der Meusdorfer H\u00f6he 15",
    "sg:city":"Leipzig",
    "sg:phone":"+49 34297/87048",
    "sg:postcode":"04288",
    "sg:province":"Sachsen",
    "wof:name":"Ingrid Arndt",
    "wof:placetype":"venue"
},
  "geometry": {"coordinates":[12.444929,51.298584],"type":"Point"}
}