{
  "type": "Feature",
  "properties": {
    "iso:country":"DE",
    "sg:address":"Boschstr. 10",
    "sg:city":"Karlsfeld",
    "sg:phone":"+49 8131/92278",
    "sg:postcode":"85757",
    "sg:province":"Bayern",
    "wof:name":"M\u00fcnchener Festzeltbetrieb Josef Brandl",
    "wof:placetype":"venue"
},
  "geometry": {"coordinates":[11.4850254059,48.2265586853],"type":"Point"}
}