{
  "type": "Feature",
  "properties": {
    "iso:country":"DE",
    "sg:address":"Arnweg 11",
    "sg:city":"M\u00fcnchen",
    "sg:phone":"+49 89/4316527",
    "sg:postcode":"81673",
    "sg:province":"Bayern",
    "wof:name":"Ing. Grad. Hans Seidel Ingenieur Und Architekt",
    "wof:placetype":"venue"
},
  "geometry": {"coordinates":[11.637607,48.129662],"type":"Point"}
}