{
  "type": "Feature",
  "properties": {
    "iso:country":"DE",
    "sg:address":"Schonstetter Str. 7",
    "sg:city":"Amerang",
    "sg:phone":"+49 8075/250",
    "sg:postcode":"83123",
    "sg:province":"Bayern",
    "wof:name":"Pfarrb\u00fccherei",
    "wof:placetype":"venue"
},
  "geometry": {"coordinates":[12.307055,47.99086],"type":"Point"}
}