{
  "type": "Feature",
  "properties": {
    "iso:country":"DE",
    "sg:address":"Bosch Str. 1",
    "sg:city":"Stadtlohn",
    "sg:phone":"+49 2563/929200",
    "sg:postcode":"48703",
    "sg:province":"Nordrhein-Westfalen",
    "wof:name":"H\u00d6tzel Rfs & Partner Gmbh",
    "wof:placetype":"venue"
},
  "geometry": {"coordinates":[6.901848793,51.9840087891],"type":"Point"}
}