{
  "type": "Feature",
  "properties": {
    "iso:country":"DE",
    "sg:address":"Altm\u00fchlweg 69",
    "sg:city":"Hamburg",
    "sg:phone":"+49 40/64940656",
    "sg:postcode":"22393",
    "sg:province":"Hamburg",
    "wof:name":"Herion-werke Gmbh & Co. Kg",
    "wof:placetype":"venue"
},
  "geometry": {"coordinates":[10.109801,53.641052],"type":"Point"}
}