{
  "type": "Feature",
  "properties": {
    "iso:country":"DE",
    "sg:address":"Helmstedter Str. 13",
    "sg:city":"Querenhorst",
    "sg:phone":"+49 5358/248",
    "sg:postcode":"38368",
    "sg:province":"Niedersachsen",
    "wof:name":"Bagge & Partner Gmbh",
    "wof:placetype":"venue"
},
  "geometry": {"coordinates":[10.9608860016,52.3374900818],"type":"Point"}
}