{
  "type": "Feature",
  "properties": {
    "iso:country":"DE",
    "sg:address":"Charlottenstr. 15",
    "sg:city":"Potsdam",
    "sg:postcode":"14467",
    "sg:province":"Brandenburg",
    "wof:name":"Universal Service Gmbh",
    "wof:placetype":"venue"
},
  "geometry": {"coordinates":[13.051237,52.398788],"type":"Point"}
}