{
  "type": "Feature",
  "properties": {
    "iso:country":"DE",
    "sg:address":"Franz-Schubert-Str. 6",
    "sg:city":"P\u00f6\u00dfneck",
    "sg:phone":"+49 3647/414832",
    "sg:postcode":"07381",
    "sg:province":"Th\u00fcringen",
    "wof:name":"Klaus Voigt",
    "wof:placetype":"venue"
},
  "geometry": {"coordinates":[11.602615,50.692265],"type":"Point"}
}