{
  "type": "Feature",
  "properties": {
    "iso:country":"DE",
    "sg:address":"Am Lahberg 11",
    "sg:city":"Burgwedel",
    "sg:postcode":"30938",
    "sg:province":"Niedersachsen",
    "wof:name":"Netlogon Gmbh & Co. Kg",
    "wof:placetype":"venue"
},
  "geometry": {"coordinates":[9.9478979111,52.5067558289],"type":"Point"}
}