{
  "type": "Feature",
  "properties": {
    "iso:country":"DE",
    "sg:address":"Bahnhofweg 13",
    "sg:city":"Oettingen",
    "sg:phone":"+49 9082/3987",
    "sg:postcode":"86732",
    "sg:province":"Bayern",
    "wof:name":"H. Li\u00dfmann Immobilienmakler",
    "wof:placetype":"venue"
},
  "geometry": {"coordinates":[10.5967798233,48.9438056946],"type":"Point"}
}