{
  "type": "Feature",
  "properties": {
    "iso:country":"DE",
    "sg:address":"Im Erlich 6",
    "sg:city":"Steinbach-Hallenberg",
    "sg:phone":"+49 5222/4131",
    "sg:postcode":"98587",
    "sg:province":"Th\u00fcringen",
    "wof:name":"Holztechnik Friedrich Klinkert Gmbh",
    "wof:placetype":"venue"
},
  "geometry": {"coordinates":[8.730607,52.087765],"type":"Point"}
}