{
  "type": "Feature",
  "properties": {
    "iso:country":"DE",
    "sg:address":"Donautalstr. 46",
    "sg:city":"Ulm",
    "sg:phone":"+49 731/41027",
    "sg:postcode":"89079",
    "sg:province":"Baden-W\u00fcrttemberg",
    "wof:name":"Apotheke Wiblingen",
    "wof:placetype":"venue"
},
  "geometry": {"coordinates":[9.984068,48.360558],"type":"Point"}
}