{
  "type": "Feature",
  "properties": {
    "iso:country":"DE",
    "sg:address":"Kirchbachstr. 185",
    "sg:city":"Bremen",
    "sg:postcode":"28211",
    "sg:province":"Bremen",
    "wof:name":"Oswin Willy Mittag",
    "wof:placetype":"venue"
},
  "geometry": {"coordinates":[8.8532495499,53.0825843811],"type":"Point"}
}