{
  "type": "Feature",
  "properties": {
    "iso:country":"DE",
    "sg:address":"Gartenkamp 208",
    "sg:city":"Westerkappeln",
    "sg:postcode":"49492",
    "sg:province":"Nordrhein-Westfalen",
    "wof:name":"Bauunternehmen S. Und T. Gmbh",
    "wof:placetype":"venue"
},
  "geometry": {"coordinates":[7.898263,52.313477],"type":"Point"}
}