{
  "type": "Feature",
  "properties": {
    "iso:country":"DE",
    "sg:address":"Tharandter Str. 10",
    "sg:city":"H\u00f6ckendorf",
    "sg:phone":"+49 35055/61289",
    "sg:postcode":"01774",
    "sg:province":"Sachsen",
    "wof:name":"Helmut K\u00f6hler",
    "wof:placetype":"venue"
},
  "geometry": {"coordinates":[13.586658,50.92907],"type":"Point"}
}