{
  "type": "Feature",
  "properties": {
    "iso:country":"DE",
    "sg:address":"Hauptstr. 71",
    "sg:city":"Albisheim",
    "sg:phone":"+49 6355/560",
    "sg:postcode":"67308",
    "sg:province":"Rheinland-Pfalz",
    "wof:name":"A. Hebbel",
    "wof:placetype":"venue"
},
  "geometry": {"coordinates":[8.092836,49.648453],"type":"Point"}
}