{
  "type": "Feature",
  "properties": {
    "iso:country":"DE",
    "sg:address":"Stillachstr. 1",
    "sg:city":"Oberstdorf",
    "sg:phone":"+49 8322/2669",
    "sg:postcode":"87561",
    "sg:province":"Bayern",
    "wof:name":"Erste Deutsche Skibob-snowbike-schule In Oberstdorhttp://www.skibob-snowbik",
    "wof:placetype":"venue"
},
  "geometry": {"coordinates":[10.263676,47.411198],"type":"Point"}
}