{
  "type": "Feature",
  "properties": {
    "iso:country":"DE",
    "sg:address":"Bachstr. 16",
    "sg:city":"Teuschnitz",
    "sg:phone":"+49 9268/9567",
    "sg:postcode":"96358",
    "sg:province":"Bayern",
    "wof:name":"A-tel Moderne Kommunikation",
    "wof:placetype":"venue"
},
  "geometry": {"coordinates":[11.3777885437,50.3794822693],"type":"Point"}
}