{
  "type": "Feature",
  "properties": {
    "iso:country":"DE",
    "sg:address":"Elsa-Br\u00e4ndstr\u00f6m-Str. 35",
    "sg:city":"Bochum",
    "sg:phone":"+49 234/43691",
    "sg:postcode":"44795",
    "sg:province":"Nordrhein-Westfalen",
    "wof:name":"Friedrich-wilhelm Struck Baugesellschaft Mbh & Co. Kg",
    "wof:placetype":"venue"
},
  "geometry": {"coordinates":[7.185203,51.453407],"type":"Point"}
}