{
  "type": "Feature",
  "properties": {
    "iso:country":"DE",
    "sg:address":"Lilienweg 10",
    "sg:city":"Markdorf",
    "sg:phone":"+49 7544/3140",
    "sg:postcode":"88677",
    "sg:province":"Baden-W\u00fcrttemberg",
    "wof:name":"Fritz O\u00dfwald",
    "wof:placetype":"venue"
},
  "geometry": {"coordinates":[9.402776,47.725105],"type":"Point"}
}