{
  "type": "Feature",
  "properties": {
    "iso:country":"DE",
    "sg:address":"Maarweg 66",
    "sg:city":"K\u00f6ln",
    "sg:postcode":"50933",
    "sg:province":"Nordrhein-Westfalen",
    "wof:name":"Sterntaxi Gmbh",
    "wof:placetype":"venue"
},
  "geometry": {"coordinates":[6.8993940353,50.9398040771],"type":"Point"}
}