{
  "type": "Feature",
  "properties": {
    "iso:country":"DE",
    "sg:address":"Putzkauer Str. 2",
    "sg:city":"Tr\u00f6bigau",
    "sg:phone":"+49 3594/713014",
    "sg:postcode":"01877",
    "sg:province":"Sachsen",
    "wof:name":"Lothar Birner",
    "wof:placetype":"venue"
},
  "geometry": {"coordinates":[14.2602777481,51.1191749573],"type":"Point"}
}