{
  "type": "Feature",
  "properties": {
    "iso:country":"DE",
    "sg:address":"Kirchenweg 9",
    "sg:city":"Baldham",
    "sg:phone":"+49 8106/358507",
    "sg:postcode":"85598",
    "sg:province":"Bayern",
    "wof:name":"Wirtschaftspr\u00fcfer Und Steuerberater",
    "wof:placetype":"venue"
},
  "geometry": {"coordinates":[11.7796020508,48.0952186584],"type":"Point"}
}