{
  "type": "Feature",
  "properties": {
    "iso:country":"DE",
    "sg:address":"Ludwig-Erhard-Allee 3",
    "sg:city":"Bielefeld",
    "sg:phone":"+49 521/20860",
    "sg:postcode":"33719",
    "sg:province":"Nordrhein-Westfalen",
    "wof:name":"Metro-eco",
    "wof:placetype":"venue"
},
  "geometry": {"coordinates":[8.6187868118,52.0054206848],"type":"Point"}
}