{
  "type": "Feature",
  "properties": {
    "iso:country":"DE",
    "sg:address":"Traunweg 27 c",
    "sg:city":"Altenmarkt",
    "sg:phone":"+49 8621/1345",
    "sg:postcode":"83352",
    "sg:province":"Bayern",
    "wof:name":"Wolfgang G\u00e4rtner Baugesch\u00e4ft Gmbh & Co. Kg",
    "wof:placetype":"venue"
},
  "geometry": {"coordinates":[12.53954,48.003868],"type":"Point"}
}