{
  "type": "Feature",
  "properties": {
    "iso:country":"DE",
    "sg:address":"Parkstr. 5",
    "sg:city":"Wiesentheid",
    "sg:phone":"+49 9383/2628",
    "sg:postcode":"97353",
    "sg:province":"Bayern",
    "wof:name":"Hildegard Town",
    "wof:placetype":"venue"
},
  "geometry": {"coordinates":[10.3410778046,49.7951583862],"type":"Point"}
}