{
  "type": "Feature",
  "properties": {
    "iso:country":"DE",
    "sg:address":"Haller Str. 17",
    "sg:city":"Paderborn",
    "sg:phone":"+49 5251/760101",
    "sg:postcode":"33106",
    "sg:province":"Nordrhein-Westfalen",
    "wof:name":"Anton Ahlen Inh. Hermann Josef Ahlen",
    "wof:placetype":"venue"
},
  "geometry": {"coordinates":[8.6848773956,51.7339286804],"type":"Point"}
}