{
  "type": "Feature",
  "properties": {
    "iso:country":"DE",
    "sg:address":"Poststr. 11",
    "sg:city":"Pleiskirchen",
    "sg:phone":"+49 8635/239",
    "sg:postcode":"84568",
    "sg:province":"Bayern",
    "wof:name":"Josef Altersberger",
    "wof:placetype":"venue"
},
  "geometry": {"coordinates":[12.598046,48.304882],"type":"Point"}
}