{
  "type": "Feature",
  "properties": {
    "iso:country":"DE",
    "sg:address":"Im Fahlenland 18",
    "sg:city":"Herzebrock-Clarholz",
    "sg:phone":"+49 5245/3868",
    "sg:postcode":"33442",
    "sg:province":"Nordrhein-Westfalen",
    "wof:name":"Christoph Hamersmeyer",
    "wof:placetype":"venue"
},
  "geometry": {"coordinates":[8.245454,51.881916],"type":"Point"}
}