{
  "type": "Feature",
  "properties": {
    "iso:country":"DE",
    "sg:address":"Am Markt 8",
    "sg:city":"Schenefeld",
    "sg:phone":"+49 4892/242",
    "sg:postcode":"25560",
    "sg:province":"Schleswig-Holstein",
    "wof:name":"Rolf Thiel",
    "wof:placetype":"venue"
},
  "geometry": {"coordinates":[9.483013,54.046284],"type":"Point"}
}