{
  "type": "Feature",
  "properties": {
    "iso:country":"DE",
    "sg:address":"Markgr\u00e4flerstr. 2",
    "sg:city":"Stuttgart",
    "sg:phone":"+49 711/65402610",
    "sg:postcode":"70329",
    "sg:province":"Baden-W\u00fcrttemberg",
    "wof:name":"A. V. E. Audio-vertriebs- Entwicklungsgesellschaft Mbh",
    "wof:placetype":"venue"
},
  "geometry": {"coordinates":[9.2745103836,48.7782211304],"type":"Point"}
}