{
  "type": "Feature",
  "properties": {
    "iso:country":"DE",
    "sg:address":"Florianweg 10",
    "sg:city":"Warburg",
    "sg:phone":"+49 5641/79040",
    "sg:postcode":"34414",
    "sg:province":"Nordrhein-Westfalen",
    "wof:name":"Nolte Hochbau Gmbh & Co. Kg",
    "wof:placetype":"venue"
},
  "geometry": {"coordinates":[9.1326913834,51.4931907654],"type":"Point"}
}