{
  "type": "Feature",
  "properties": {
    "iso:country":"DE",
    "sg:address":"Ferrariweg 56",
    "sg:city":"Paderborn",
    "sg:phone":"+49 5251/33634",
    "sg:postcode":"33102",
    "sg:province":"Nordrhein-Westfalen",
    "wof:name":"Paul Tewes Ingenieur",
    "wof:placetype":"venue"
},
  "geometry": {"coordinates":[8.746629715,51.7334098816],"type":"Point"}
}