{
  "type": "Feature",
  "properties": {
    "iso:country":"DE",
    "sg:address":"Burgstr. 11",
    "sg:city":"Pfalzgrafenweiler",
    "sg:phone":"+49 7445/2309",
    "sg:postcode":"72285",
    "sg:province":"Baden-W\u00fcrttemberg",
    "wof:name":"Fritz Steeb",
    "wof:placetype":"venue"
},
  "geometry": {"coordinates":[8.563815,48.524734],"type":"Point"}
}