{
  "type": "Feature",
  "properties": {
    "iso:country":"DE",
    "sg:address":"Wiesenstr. 22",
    "sg:city":"Karlsruhe",
    "sg:phone":"+49 721/9453090",
    "sg:postcode":"76228",
    "sg:province":"Baden-W\u00fcrttemberg",
    "wof:name":"Wolfgang Schramm",
    "wof:placetype":"venue"
},
  "geometry": {"coordinates":[8.4706659317,48.9534721375],"type":"Point"}
}