{
  "type": "Feature",
  "properties": {
    "iso:country":"DE",
    "sg:address":"Goetheplatz 2",
    "sg:city":"Bad M\u00fcnster-Ebernburg",
    "sg:phone":"+49 6708/2022",
    "sg:postcode":"55583",
    "sg:province":"Rheinland-Pfalz",
    "wof:name":"Praxis Dr. Med. Rabel",
    "wof:placetype":"venue"
},
  "geometry": {"coordinates":[7.8468518257,49.8111610413],"type":"Point"}
}