{
  "type": "Feature",
  "properties": {
    "iso:country":"DE",
    "sg:address":"Ludwigstr. 1a",
    "sg:city":"K\u00f6ln",
    "sg:postcode":"50667",
    "sg:province":"Nordrhein-Westfalen",
    "wof:name":"K\u00fcchen Forum Gmbh",
    "wof:placetype":"venue"
},
  "geometry": {"coordinates":[6.9548721313,50.938457489],"type":"Point"}
}