{
  "type": "Feature",
  "properties": {
    "iso:country":"DE",
    "sg:address":"Maarstr. 22",
    "sg:city":"Schalkenmehren",
    "sg:phone":"+49 6592/551",
    "sg:postcode":"54552",
    "sg:province":"Rheinland-Pfalz",
    "wof:name":"Camp Am Maar",
    "wof:placetype":"venue"
},
  "geometry": {"coordinates":[6.856966,50.166027],"type":"Point"}
}