{
  "type": "Feature",
  "properties": {
    "iso:country":"DE",
    "sg:address":"Nieper Str. 275",
    "sg:city":"Krefeld",
    "sg:phone":"+49 2151/564835",
    "sg:postcode":"47802",
    "sg:province":"Nordrhein-Westfalen",
    "wof:name":"Landhaus Fischerheim",
    "wof:placetype":"venue"
},
  "geometry": {"coordinates":[6.5578899384,51.387752533],"type":"Point"}
}