{
  "type": "Feature",
  "properties": {
    "iso:country":"DE",
    "sg:address":"Kelterplatz 5",
    "sg:city":"M\u00fchlacker",
    "sg:phone":"+49 7041/18329",
    "sg:postcode":"75417",
    "sg:province":"Baden-W\u00fcrttemberg",
    "wof:name":"Heimatmuseum",
    "wof:placetype":"venue"
},
  "geometry": {"coordinates":[8.841514,48.946354],"type":"Point"}
}