{
  "type": "Feature",
  "properties": {
    "iso:country":"DE",
    "sg:address":"Krahnendonk 106",
    "sg:city":"M\u00f6nchengladbach",
    "sg:phone":"+49 2161/99470",
    "sg:postcode":"41066",
    "sg:province":"Nordrhein-Westfalen",
    "wof:name":"Controlware Gmbh",
    "wof:placetype":"venue"
},
  "geometry": {"coordinates":[6.4717669487,51.2289962769],"type":"Point"}
}