{
  "type": "Feature",
  "properties": {
    "iso:country":"DE",
    "sg:address":"Freundallee 17",
    "sg:city":"Hannover",
    "sg:phone":"+49 511/818054",
    "sg:postcode":"30173",
    "sg:province":"Niedersachsen",
    "wof:name":"M & P Internationale Mess- Und Rechnertechnik Gmbh",
    "wof:placetype":"venue"
},
  "geometry": {"coordinates":[9.772687,52.365795],"type":"Point"}
}