{
  "type": "Feature",
  "properties": {
    "iso:country":"DE",
    "sg:address":"Wortherbruchstr. 50",
    "sg:city":"Hagen",
    "sg:phone":"+49 2331/303605",
    "sg:postcode":"58089",
    "sg:province":"Nordrhein-Westfalen",
    "wof:name":"Richard Lemke",
    "wof:placetype":"venue"
},
  "geometry": {"coordinates":[7.4243202209,51.3828811646],"type":"Point"}
}