{
  "type": "Feature",
  "properties": {
    "iso:country":"DE",
    "sg:address":"Wulfener Str. 16",
    "sg:city":"Dorsten",
    "sg:phone":"+49 2369/77707",
    "sg:postcode":"46286",
    "sg:province":"Nordrhein-Westfalen",
    "wof:name":"Bohle",
    "wof:placetype":"venue"
},
  "geometry": {"coordinates":[7.0036997795,51.7423477173],"type":"Point"}
}