{
  "type": "Feature",
  "properties": {
    "iso:country":"DE",
    "sg:address":"Wilhelm-Harting-Str. 2",
    "sg:city":"Espelkamp",
    "sg:phone":"+49 5772/3077",
    "sg:postcode":"32339",
    "sg:province":"Nordrhein-Westfalen",
    "wof:name":"Erwin Pianka Gmbh",
    "wof:placetype":"venue"
},
  "geometry": {"coordinates":[8.618996,52.391365],"type":"Point"}
}