{
  "type": "Feature",
  "properties": {
    "iso:country":"DE",
    "sg:address":"Rassowweg 5",
    "sg:city":"Bremen",
    "sg:phone":"+49 421/250345",
    "sg:postcode":"28355",
    "sg:province":"Bremen",
    "wof:name":"Helmut Kramer Steuerberater",
    "wof:placetype":"venue"
},
  "geometry": {"coordinates":[8.9222402573,53.0943603516],"type":"Point"}
}