{
  "type": "Feature",
  "properties": {
    "iso:country":"DE",
    "sg:address":"Belgradstr. 14",
    "sg:city":"M\u00fcnchen",
    "sg:phone":"+49 89/33019284",
    "sg:postcode":"80796",
    "sg:province":"Bayern",
    "wof:name":"Von Mellenthin'sche Beteiligungs-beratungs Gmbh",
    "wof:placetype":"venue"
},
  "geometry": {"coordinates":[11.574959,48.162308],"type":"Point"}
}