{
  "type": "Feature",
  "properties": {
    "iso:country":"DE",
    "sg:address":"Hopfenbergstr. 26",
    "sg:city":"Oberweser",
    "sg:phone":"+49 5572/7730",
    "sg:postcode":"34399",
    "sg:province":"Hessen",
    "wof:name":"Meth",
    "wof:placetype":"venue"
},
  "geometry": {"coordinates":[9.5543403625,51.5971984863],"type":"Point"}
}