{
  "type": "Feature",
  "properties": {
    "iso:country":"DE",
    "sg:address":"Dresdner Str. 52",
    "sg:city":"Nossen",
    "sg:phone":"+49 4952/227639",
    "sg:postcode":"01683",
    "sg:province":"Sachsen",
    "wof:name":"S\u00dcllwald-schuh Gmbh",
    "wof:placetype":"venue"
},
  "geometry": {"coordinates":[8.716206,52.04718],"type":"Point"}
}