{
  "type": "Feature",
  "properties": {
    "iso:country":"DE",
    "sg:address":"Aitrachstr. 28",
    "sg:city":"Straubing",
    "sg:phone":"+49 9421/61260",
    "sg:postcode":"94315",
    "sg:province":"Bayern",
    "wof:name":"Hans Wagner Baugesch\u00e4ft Gmbh",
    "wof:placetype":"venue"
},
  "geometry": {"coordinates":[12.643835,48.892628],"type":"Point"}
}