{
  "type": "Feature",
  "properties": {
    "iso:country":"DE",
    "sg:address":"Siedemeierkamp 3",
    "sg:city":"Celle",
    "sg:postcode":"29227",
    "sg:province":"Niedersachsen",
    "wof:name":"Lampe Gmbh",
    "wof:placetype":"venue"
},
  "geometry": {"coordinates":[10.1077470779,52.6010131836],"type":"Point"}
}