{
  "type": "Feature",
  "properties": {
    "iso:country":"DE",
    "sg:address":"Sternkamp 3",
    "sg:city":"L\u00fcneburg",
    "sg:phone":"+49 4131/31444",
    "sg:postcode":"21339",
    "sg:province":"Niedersachsen",
    "wof:name":"Dachdeckerei Behning Gmbh",
    "wof:placetype":"venue"
},
  "geometry": {"coordinates":[10.4093647003,53.2676696777],"type":"Point"}
}