{
  "type": "Feature",
  "properties": {
    "iso:country":"DE",
    "sg:address":"Hauptstr. 122",
    "sg:city":"B\u00f6hl-Iggelheim",
    "sg:phone":"+49 6324/76729",
    "sg:postcode":"67459",
    "sg:province":"Rheinland-Pfalz",
    "wof:name":"Kurt Rieger",
    "wof:placetype":"venue"
},
  "geometry": {"coordinates":[8.2944,49.388481],"type":"Point"}
}