{
  "type": "Feature",
  "properties": {
    "iso:country":"DE",
    "sg:address":"Delogstr. 32",
    "sg:city":"Wesel",
    "sg:postcode":"46483",
    "sg:province":"Nordrhein-Westfalen",
    "wof:name":"Flabeg Steinglas Gmbh",
    "wof:placetype":"venue"
},
  "geometry": {"coordinates":[6.6037540436,51.6613197327],"type":"Point"}
}