{
  "type": "Feature",
  "properties": {
    "iso:country":"DE",
    "sg:address":"M\u00fcnchener Str. 3",
    "sg:city":"Pullach",
    "sg:phone":"+49 89/7933830",
    "sg:postcode":"82049",
    "sg:province":"Bayern",
    "wof:name":"Juwelier Max E. K.",
    "wof:placetype":"venue"
},
  "geometry": {"coordinates":[11.523312,48.057522],"type":"Point"}
}