{
  "type": "Feature",
  "properties": {
    "iso:country":"DE",
    "sg:address":"Hopfenbachstr. 1",
    "sg:city":"Neukloster",
    "sg:phone":"+49 38422/25450",
    "sg:postcode":"23992",
    "sg:province":"Mecklenburg-Vorpommern",
    "wof:name":"Zielinski & Reimann Gbr",
    "wof:placetype":"venue"
},
  "geometry": {"coordinates":[11.691646,53.870098],"type":"Point"}
}