{
  "type": "Feature",
  "properties": {
    "iso:country":"DE",
    "sg:address":"Dornierstr. 51",
    "sg:city":"Tuttlingen",
    "sg:postcode":"78532",
    "sg:province":"Baden-W\u00fcrttemberg",
    "wof:name":"Tuttlinger Investment Management Gmbh",
    "wof:placetype":"venue"
},
  "geometry": {"coordinates":[8.785592,47.967377],"type":"Point"}
}