{
  "type": "Feature",
  "properties": {
    "iso:country":"DE",
    "sg:address":"Noltestr. 12",
    "sg:city":"L\u00fcdenscheid",
    "sg:phone":"+49 2351/929292",
    "sg:postcode":"58511",
    "sg:province":"Nordrhein-Westfalen",
    "wof:name":"Weinreich Industrie- K\u00fchlung Gmbh",
    "wof:placetype":"venue"
},
  "geometry": {"coordinates":[7.65449,51.230927],"type":"Point"}
}