{
  "type": "Feature",
  "properties": {
    "iso:country":"DE",
    "sg:address":"Ziegeleiweg 11",
    "sg:city":"Crimmitschau",
    "sg:phone":"+49 3762/95540",
    "sg:postcode":"08451",
    "sg:province":"Sachsen",
    "wof:name":"Kaminwelt Crimmitschau",
    "wof:placetype":"venue"
},
  "geometry": {"coordinates":[12.40668,50.815498],"type":"Point"}
}