{
  "type": "Feature",
  "properties": {
    "iso:country":"DE",
    "sg:address":"Isargestade 735",
    "sg:city":"Landshut",
    "sg:phone":"+49 871/22011",
    "sg:postcode":"84028",
    "sg:province":"Bayern",
    "wof:name":"Taxi Funktaxi-vereinigung Landshut E. V.",
    "wof:placetype":"venue"
},
  "geometry": {"coordinates":[12.1524953842,48.5399932861],"type":"Point"}
}