{
  "type": "Feature",
  "properties": {
    "iso:country":"DE",
    "sg:address":"Schlosstr. 11",
    "sg:city":"Berlin",
    "sg:postcode":"10323",
    "sg:province":"Berlin",
    "wof:name":"Kino Potsdam",
    "wof:placetype":"venue"
},
  "geometry": {"coordinates":[13.296019,52.516109],"type":"Point"}
}