{
  "type": "Feature",
  "properties": {
    "iso:country":"DE",
    "sg:address":"Neum\u00fchle 72",
    "sg:city":"Heiligenstadt",
    "sg:phone":"+49 9198/228",
    "sg:postcode":"91332",
    "sg:province":"Bayern",
    "wof:name":"Gasthof Hans B\u00e4chmann",
    "wof:placetype":"venue"
},
  "geometry": {"coordinates":[11.1675748825,49.8715934753],"type":"Point"}
}