{
  "type": "Feature",
  "properties": {
    "iso:country":"DE",
    "sg:address":"Hinterstr. 15",
    "sg:city":"Seelow",
    "sg:postcode":"15306",
    "sg:province":"Brandenburg",
    "wof:name":"Seelower Dachdeckerei Gmbh",
    "wof:placetype":"venue"
},
  "geometry": {"coordinates":[14.378052,52.530674],"type":"Point"}
}