{
  "type": "Feature",
  "properties": {
    "iso:country":"DE",
    "sg:address":"Muskauer Str. 13",
    "sg:city":"Niesky",
    "sg:phone":"+49 3588/200277",
    "sg:postcode":"02906",
    "sg:province":"Sachsen",
    "wof:name":"Diakonie-sozialstation Niesky",
    "wof:placetype":"venue"
},
  "geometry": {"coordinates":[14.823287,51.29459],"type":"Point"}
}