{
  "type": "Feature",
  "properties": {
    "iso:country":"DE",
    "sg:address":"R\u00f6hrborngasse 1",
    "sg:city":"Frankfurt",
    "sg:phone":"+49 6109/23600",
    "sg:postcode":"60388",
    "sg:province":"Hessen",
    "wof:name":"Norbert B\u00f6hm",
    "wof:placetype":"venue"
},
  "geometry": {"coordinates":[8.7526321411,50.1544532776],"type":"Point"}
}