{
  "type": "Feature",
  "properties": {
    "iso:country":"DE",
    "sg:address":"L\u00fcder-Wose-Str. 39",
    "sg:city":"Celle",
    "sg:phone":"+49 5141/21039",
    "sg:postcode":"29221",
    "sg:province":"Niedersachsen",
    "wof:name":"Alten- Und Pflegeheim Vera Meyer Gmbh",
    "wof:placetype":"venue"
},
  "geometry": {"coordinates":[10.097221,52.611092],"type":"Point"}
}