{
  "type": "Feature",
  "properties": {
    "iso:country":"DE",
    "sg:address":"Caesariusstr. 83 a",
    "sg:city":"Koenigswinter",
    "sg:phone":"+49 700 0767 6866",
    "sg:postcode":"53637",
    "wof:name":"Deutsche Poroton Gmbh",
    "wof:placetype":"venue"
},
  "geometry": {"coordinates":[7.182115078,50.7033500671],"type":"Point"}
}