{
  "type": "Feature",
  "properties": {
    "iso:country":"DE",
    "sg:address":"Postfach 227",
    "sg:city":"Bad Wimpfen",
    "sg:phone":"+49 7063/7952",
    "sg:postcode":"74201",
    "sg:province":"Baden-W\u00fcrttemberg",
    "wof:name":"Wolfgang Veith",
    "wof:placetype":"venue"
},
  "geometry": {"coordinates":[9.1575603485,49.2300758362],"type":"Point"}
}