{
  "type": "Feature",
  "properties": {
    "iso:country":"DE",
    "sg:address":"Von-Axen-Str. 2",
    "sg:city":"Hamburg",
    "sg:phone":"+49 40/2273104",
    "sg:postcode":"22083",
    "sg:province":"Hamburg",
    "wof:name":"Peter D\u00e4mmrich Heilpraktiker",
    "wof:placetype":"venue"
},
  "geometry": {"coordinates":[10.0251712799,53.5797576904],"type":"Point"}
}