{
  "type": "Feature",
  "properties": {
    "iso:country":"DE",
    "sg:address":"Breitscheidstr. 23",
    "sg:city":"Oschersleben",
    "sg:phone":"+49 3949/2313",
    "sg:postcode":"39387",
    "sg:province":"Sachsen-Anhalt",
    "wof:name":"K Und W Planungsges. F\u00fcr Architektur Und Ingenieur-",
    "wof:placetype":"venue"
},
  "geometry": {"coordinates":[11.227384,52.033978],"type":"Point"}
}