{
  "type": "Feature",
  "properties": {
    "iso:country":"DE",
    "sg:address":"Hofer Str. 13",
    "sg:city":"Feilitzsch",
    "sg:phone":"+49 9281/85612",
    "sg:postcode":"95183",
    "sg:province":"Bayern",
    "wof:name":"Richard R\u00f6del",
    "wof:placetype":"venue"
},
  "geometry": {"coordinates":[11.90143,50.35154],"type":"Point"}
}