{
  "type": "Feature",
  "properties": {
    "iso:country":"DE",
    "sg:address":"Obere Dorfstr. 32",
    "sg:city":"K\u00fcps",
    "sg:phone":"+49 9264/6160",
    "sg:postcode":"96328",
    "sg:province":"Bayern",
    "wof:name":"Marco Beetz Hardwarehandel",
    "wof:placetype":"venue"
},
  "geometry": {"coordinates":[11.2724781036,50.2162399292],"type":"Point"}
}