{
  "type": "Feature",
  "properties": {
    "iso:country":"DE",
    "sg:address":"Haderstr. 5",
    "sg:city":"Langenaltheim",
    "sg:phone":"+49 9145/283",
    "sg:postcode":"91799",
    "sg:province":"Bayern",
    "wof:name":"Friedrich H\u00fcbner",
    "wof:placetype":"venue"
},
  "geometry": {"coordinates":[10.925956,48.894241],"type":"Point"}
}