{
  "type": "Feature",
  "properties": {
    "iso:country":"DE",
    "sg:address":"Max-Dietrich-Str. 28",
    "sg:city":"Bremerhaven",
    "sg:phone":"+49 471/34289",
    "sg:postcode":"27570",
    "sg:province":"Bremen",
    "wof:name":"China-restaurant Ni Hao",
    "wof:placetype":"venue"
},
  "geometry": {"coordinates":[8.5909481049,53.530620575],"type":"Point"}
}