{
  "type": "Feature",
  "properties": {
    "iso:country":"DE",
    "sg:address":"Hauptstr. 53",
    "sg:city":"Ruppichteroth",
    "sg:phone":"+49 2247/4017",
    "sg:postcode":"53809",
    "sg:province":"Nordrhein-Westfalen",
    "wof:name":"Provinzial Versicherungen Robert Beer",
    "wof:placetype":"venue"
},
  "geometry": {"coordinates":[7.3653402328,50.8137283325],"type":"Point"}
}