{
  "type": "Feature",
  "properties": {
    "iso:country":"DE",
    "sg:address":"Hombrucher Weg 29",
    "sg:city":"Iserlohn",
    "sg:phone":"+49 2371/3980",
    "sg:postcode":"58638",
    "sg:province":"Nordrhein-Westfalen",
    "wof:name":"L\u00f6tters Beteiligungs Gmbh & Co. Kg",
    "wof:placetype":"venue"
},
  "geometry": {"coordinates":[7.68411,51.394226],"type":"Point"}
}