{
  "type": "Feature",
  "properties": {
    "iso:country":"DE",
    "sg:address":"Untere Krankenhausstr. 20",
    "sg:city":"Schneeberg",
    "sg:phone":"+49 3772/22614",
    "sg:postcode":"08289",
    "sg:province":"Sachsen",
    "wof:name":"F. Bauer",
    "wof:placetype":"venue"
},
  "geometry": {"coordinates":[12.637374,50.590855],"type":"Point"}
}