{
  "type": "Feature",
  "properties": {
    "iso:country":"DE",
    "sg:address":"R\u00f6merstr. 11",
    "sg:city":"Starnberg",
    "sg:phone":"+49 8151/16754",
    "sg:postcode":"82319",
    "sg:province":"Bayern",
    "wof:name":"Helga Czerney",
    "wof:placetype":"venue"
},
  "geometry": {"coordinates":[11.2724533081,48.0001296997],"type":"Point"}
}