{
  "type": "Feature",
  "properties": {
    "iso:country":"DE",
    "sg:address":"Am Rundteil 2b",
    "sg:city":"Riesa",
    "sg:phone":"+49 3525/730608",
    "sg:postcode":"01589",
    "sg:province":"Sachsen",
    "wof:name":"H. Polster Anlageberater",
    "wof:placetype":"venue"
},
  "geometry": {"coordinates":[13.3097715378,51.3038024902],"type":"Point"}
}