{
  "type": "Feature",
  "properties": {
    "iso:country":"DE",
    "sg:address":"Karl-Marx-Allee 9",
    "sg:city":"Gera",
    "sg:phone":"+49 365/810058",
    "sg:postcode":"07548",
    "sg:province":"Th\u00fcringen",
    "wof:name":"Bonnfinanz Ag",
    "wof:placetype":"venue"
},
  "geometry": {"coordinates":[12.0714044571,50.8688545227],"type":"Point"}
}