{
  "type": "Feature",
  "properties": {
    "iso:country":"DE",
    "sg:address":"Wilhelmstr. 12",
    "sg:city":"Holzwickede",
    "sg:phone":"+49 2301/12934",
    "sg:postcode":"59439",
    "sg:province":"Nordrhein-Westfalen",
    "wof:name":"Keramik & Sanit\u00e4r Handelsgesellschaft Mbh",
    "wof:placetype":"venue"
},
  "geometry": {"coordinates":[7.6220178604,51.514919281],"type":"Point"}
}