{
  "type": "Feature",
  "properties": {
    "iso:country":"DE",
    "sg:address":"Theodor-Storm-Str 13",
    "sg:city":"Dassel",
    "sg:phone":"+49 5564/96160",
    "sg:postcode":"37586",
    "sg:province":"Niedersachsen",
    "wof:name":"Creydt Fruchtsaft Gmbh",
    "wof:placetype":"venue"
},
  "geometry": {"coordinates":[9.689781,51.798794],"type":"Point"}
}