{
  "type": "Feature",
  "properties": {
    "iso:country":"DE",
    "sg:address":"Sauerbruchstr. 10",
    "sg:city":"M\u00fcnchen",
    "sg:phone":"+49 89/705521",
    "sg:postcode":"81377",
    "sg:province":"Bayern",
    "wof:name":"Christian Schmidt Kg",
    "wof:placetype":"venue"
},
  "geometry": {"coordinates":[11.4765548706,48.1136474609],"type":"Point"}
}