{
  "type": "Feature",
  "properties": {
    "iso:country":"DE",
    "sg:address":"Konradstr. 12",
    "sg:city":"Zwickau",
    "sg:phone":"+49 375/281180",
    "sg:postcode":"08056",
    "sg:province":"Sachsen",
    "wof:name":"Steffi Und Friedhelm Werthmann Rechtsanw\u00e4lte",
    "wof:placetype":"venue"
},
  "geometry": {"coordinates":[12.4864463806,50.7224617004],"type":"Point"}
}