{
  "type": "Feature",
  "properties": {
    "iso:country":"DE",
    "sg:address":"Zehnthausstr. 7",
    "sg:city":"Bernkastel-Kues",
    "sg:phone":"+49 6531/8276",
    "sg:postcode":"54470",
    "sg:province":"Rheinland-Pfalz",
    "wof:name":"Klaus Mentges",
    "wof:placetype":"venue"
},
  "geometry": {"coordinates":[7.0428371429,49.9415512085],"type":"Point"}
}