{
  "type": "Feature",
  "properties": {
    "iso:country":"DE",
    "sg:address":"Ro\u00dfbergerhof 50",
    "sg:city":"Schenkenzell",
    "sg:phone":"+49 7836/1295",
    "sg:postcode":"77773",
    "sg:province":"Baden-W\u00fcrttemberg",
    "wof:name":"Johannes G\u00f6hring",
    "wof:placetype":"venue"
},
  "geometry": {"coordinates":[8.3523206711,48.3467483521],"type":"Point"}
}