{
  "type": "Feature",
  "properties": {
    "iso:country":"DE",
    "sg:address":"Kurf\u00fcrstenstr. 3",
    "sg:city":"Essen",
    "sg:phone":"+49 201/285137",
    "sg:postcode":"45138",
    "sg:province":"Nordrhein-Westfalen",
    "wof:name":"A. Neydrowski",
    "wof:placetype":"venue"
},
  "geometry": {"coordinates":[7.0296111107,51.450881958],"type":"Point"}
}