{
  "type": "Feature",
  "properties": {
    "iso:country":"DE",
    "sg:address":"Bahnhofstr 35",
    "sg:city":"G\u00f6ppingen",
    "sg:phone":"+49 7161/6760",
    "sg:postcode":"73033",
    "sg:province":"Baden-W\u00fcrttemberg",
    "wof:name":"Staufen-pharma Gmbh & Co",
    "wof:placetype":"venue"
},
  "geometry": {"coordinates":[9.6479148865,48.7027854919],"type":"Point"}
}