{
  "type": "Feature",
  "properties": {
    "iso:country":"DE",
    "sg:address":"Marxener Str. 28",
    "sg:city":"Seevetal",
    "sg:phone":"+49 4185/3319",
    "sg:postcode":"21220",
    "sg:province":"Niedersachsen",
    "wof:name":"Willi Eddelb\u00fcttel",
    "wof:placetype":"venue"
},
  "geometry": {"coordinates":[10.017656,53.337147],"type":"Point"}
}