{
  "type": "Feature",
  "properties": {
    "iso:country":"DE",
    "sg:address":"Am Rhin 1",
    "sg:city":"Hiddenhausen",
    "sg:phone":"+49 5221/65957",
    "sg:postcode":"32120",
    "sg:province":"Nordrhein-Westfalen",
    "wof:name":"Apotheke Am Rhin",
    "wof:placetype":"venue"
},
  "geometry": {"coordinates":[8.618232,52.142006],"type":"Point"}
}