{
  "type": "Feature",
  "properties": {
    "iso:country":"DE",
    "sg:city":"Weiskirchen",
    "sg:phone":"+49 6876/366",
    "sg:postcode":"66709",
    "sg:province":"Saarland",
    "wof:name":"Schwarzw\u00e4lder Hochwald Campingplatz",
    "wof:placetype":"venue"
},
  "geometry": {"coordinates":[6.81979,49.5536],"type":"Point"}
}