{
  "type": "Feature",
  "properties": {
    "iso:country":"DE",
    "sg:address":"Neugartenstr. 77",
    "sg:city":"Prien",
    "sg:postcode":"83209",
    "sg:province":"Bayern",
    "wof:name":"Obstverwertungsgenossenschaft Prien Und Umgebung Eg",
    "wof:placetype":"venue"
},
  "geometry": {"coordinates":[12.3428373337,47.8555526733],"type":"Point"}
}