{
  "type": "Feature",
  "properties": {
    "iso:country":"DE",
    "sg:address":"Wendelstr. 4",
    "sg:city":"Wiesbaden",
    "sg:phone":"+49 611/1885696",
    "sg:postcode":"65191",
    "sg:province":"Hessen",
    "wof:name":"Heri`s Weingalerie",
    "wof:placetype":"venue"
},
  "geometry": {"coordinates":[8.277557373,50.0842628479],"type":"Point"}
}