{
  "type": "Feature",
  "properties": {
    "iso:country":"DE",
    "sg:address":"Fallingbosteler Str. 6",
    "sg:city":"Walsrode",
    "sg:phone":"+49 5161/71661",
    "sg:postcode":"29664",
    "sg:province":"Niedersachsen",
    "wof:name":"Karl-heinrich Hoops",
    "wof:placetype":"venue"
},
  "geometry": {"coordinates":[9.63168,52.832821],"type":"Point"}
}