{
  "type": "Feature",
  "properties": {
    "iso:country":"DE",
    "sg:address":"Hauptstr. 2",
    "sg:city":"Ramsen",
    "sg:phone":"+49 6351/8562",
    "sg:postcode":"67305",
    "sg:province":"Rheinland-Pfalz",
    "wof:name":"Zimmerei Und Dachdeckerei Gunther Spie\u00df Gmbh",
    "wof:placetype":"venue"
},
  "geometry": {"coordinates":[8.0168800354,49.5374603271],"type":"Point"}
}