{
  "type": "Feature",
  "properties": {
    "iso:country":"DE",
    "sg:address":"Richard-Lehmann-Str. 11",
    "sg:city":"Aschersleben",
    "sg:phone":"+49 3473/804417",
    "sg:postcode":"06449",
    "sg:province":"Sachsen-Anhalt",
    "wof:name":"Marion M\u00fcller",
    "wof:placetype":"venue"
},
  "geometry": {"coordinates":[11.450504303,51.7608642578],"type":"Point"}
}