{
  "type": "Feature",
  "properties": {
    "iso:country":"DE",
    "sg:address":"Feldbergstr. 15",
    "sg:city":"Oberursel",
    "sg:phone":"+49 6171/57590",
    "sg:postcode":"61440",
    "sg:province":"Hessen",
    "wof:name":"Dr. Ulrich Stoll Rechtsanwalt",
    "wof:placetype":"venue"
},
  "geometry": {"coordinates":[8.5854177475,50.2010536194],"type":"Point"}
}