{
  "type": "Feature",
  "properties": {
    "iso:country":"DE",
    "sg:address":"Dorotheenstr. 180a",
    "sg:city":"Hamburg",
    "sg:phone":"+49 40/2797909",
    "sg:postcode":"22299",
    "sg:province":"Hamburg",
    "wof:name":"Outdoor & Sports Pool Simon Barg Und",
    "wof:placetype":"venue"
},
  "geometry": {"coordinates":[10.002247,53.591522],"type":"Point"}
}