{
  "type": "Feature",
  "properties": {
    "iso:country":"DE",
    "sg:address":"Wattmannstr 40",
    "sg:city":"Kaarst",
    "sg:phone":"+49 2131/75850",
    "sg:postcode":"41564",
    "sg:province":"Nordrhein-Westfalen",
    "wof:name":"Christina Guth Werbeberatung Gmbh",
    "wof:placetype":"venue"
},
  "geometry": {"coordinates":[6.577065,51.21508],"type":"Point"}
}