{
  "type": "Feature",
  "properties": {
    "iso:country":"DE",
    "sg:address":"Thalm\u00fchl 1",
    "sg:city":"Warngau",
    "sg:phone":"+49 8021/1831",
    "sg:postcode":"83627",
    "sg:province":"Bayern",
    "wof:name":"Ata Akustik-trockenbau Ablassmeier Gmbh",
    "wof:placetype":"venue"
},
  "geometry": {"coordinates":[11.771368,47.777374],"type":"Point"}
}