{
  "type": "Feature",
  "properties": {
    "iso:country":"DE",
    "sg:address":"Lindenhofstr. 36",
    "sg:city":"Bremen",
    "sg:phone":"+49 421/6161402",
    "sg:postcode":"28237",
    "sg:province":"Bremen",
    "wof:name":"Gh Gebrauchtwagenhandels Gmbh",
    "wof:placetype":"venue"
},
  "geometry": {"coordinates":[8.7559986115,53.1135635376],"type":"Point"}
}