{
  "type": "Feature",
  "properties": {
    "iso:country":"DE",
    "sg:address":"Lauxweg 29",
    "sg:city":"Stuttgart",
    "sg:phone":"+49 711/4482311",
    "sg:postcode":"70619",
    "sg:province":"Baden-W\u00fcrttemberg",
    "wof:name":"Data Saldo Plus T\u00e4uber & Co Gmbh",
    "wof:placetype":"venue"
},
  "geometry": {"coordinates":[9.2383928299,48.7482223511],"type":"Point"}
}