{
  "type": "Feature",
  "properties": {
    "iso:country":"DE",
    "sg:address":"Kirchstr. 25",
    "sg:city":"Bad Liebenzell",
    "sg:phone":"+49 7052/3719",
    "sg:postcode":"75378",
    "sg:province":"Baden-W\u00fcrttemberg",
    "wof:name":"Gustav M\u00fcnster",
    "wof:placetype":"venue"
},
  "geometry": {"coordinates":[8.727799,48.775356],"type":"Point"}
}