{
  "type": "Feature",
  "properties": {
    "iso:country":"DE",
    "sg:address":"Postfach 1176",
    "sg:city":"Ruppichteroth",
    "sg:phone":"+49 2295/30041",
    "sg:postcode":"53809",
    "sg:province":"Nordrhein-Westfalen",
    "wof:name":"Software Rest- Und Sonderposten Zu Top Preisen",
    "wof:placetype":"venue"
},
  "geometry": {"coordinates":[7.485466,50.844364],"type":"Point"}
}