{
  "type": "Feature",
  "properties": {
    "iso:country":"DE",
    "sg:address":"Sch\u00fctzenstr. 64",
    "sg:city":"D\u00fcsseldorf",
    "sg:postcode":"40211",
    "sg:province":"Nordrhein-Westfalen",
    "wof:name":"Gsc Info Und Beteiligungen Ag",
    "wof:placetype":"venue"
},
  "geometry": {"coordinates":[6.7946190834,51.2264862061],"type":"Point"}
}