{
  "type": "Feature",
  "properties": {
    "iso:country":"DE",
    "sg:address":"Im Altenburger Feld 2",
    "sg:city":"Felsberg",
    "sg:phone":"+49 5662/883",
    "sg:postcode":"34587",
    "sg:province":"Hessen",
    "wof:name":"W\u00fcsteneck Anlagenbau F\u00fcr Wasser-luft- Und",
    "wof:placetype":"venue"
},
  "geometry": {"coordinates":[9.410618,51.129894],"type":"Point"}
}