{
  "type": "Feature",
  "properties": {
    "iso:country":"DE",
    "sg:address":"Grabenstr 21",
    "sg:city":"Bodelshausen",
    "sg:phone":"+49 7471/7610",
    "sg:postcode":"72411",
    "sg:province":"Baden-W\u00fcrttemberg",
    "wof:name":"Martin Eberhardt",
    "wof:placetype":"venue"
},
  "geometry": {"coordinates":[8.980961,48.388012],"type":"Point"}
}