{
  "type": "Feature",
  "properties": {
    "iso:country":"DE",
    "sg:address":"Krapfen 9",
    "sg:city":"Bayrischzell",
    "sg:phone":"+49 8023/740",
    "sg:postcode":"83735",
    "sg:province":"Bayern",
    "wof:name":"G\u00e4stehaus Willi Buschmann",
    "wof:placetype":"venue"
},
  "geometry": {"coordinates":[12.0119800568,47.6734390259],"type":"Point"}
}