{
  "type": "Feature",
  "properties": {
    "iso:country":"DE",
    "sg:address":"\u00d6rtl 5",
    "sg:city":"Obernzell",
    "sg:phone":"+49 8591/1805",
    "sg:postcode":"94130",
    "sg:province":"Bayern",
    "wof:name":"Fritz Fuchs",
    "wof:placetype":"venue"
},
  "geometry": {"coordinates":[13.634895,48.554695],"type":"Point"}
}