{
  "type": "Feature",
  "properties": {
    "iso:country":"DE",
    "sg:address":"Brodstr. 13",
    "sg:city":"M\u00fcnchen",
    "sg:phone":"+49 89/4801820",
    "sg:postcode":"81829",
    "sg:province":"Bayern",
    "wof:name":"Walter Weindl",
    "wof:placetype":"venue"
},
  "geometry": {"coordinates":[11.6671352386,48.1283683777],"type":"Point"}
}