{
  "type": "Feature",
  "properties": {
    "iso:country":"DE",
    "sg:address":"Irlbacher Str. 10",
    "sg:city":"Stephansposching",
    "sg:phone":"+49 9424/618",
    "sg:postcode":"94569",
    "sg:province":"Bayern",
    "wof:name":"Johann Petzenhauser",
    "wof:placetype":"venue"
},
  "geometry": {"coordinates":[12.768479,48.826767],"type":"Point"}
}