{
  "type": "Feature",
  "properties": {
    "iso:country":"DE",
    "sg:address":"Raiffenstr. 12",
    "sg:city":"Kusterdingen",
    "sg:phone":"+49 4970/7193920",
    "sg:postcode":"72127",
    "sg:province":"Baden-W\u00fcrttemberg",
    "wof:name":"Delfina Vertriebsges Martin Heusel Mbh",
    "wof:placetype":"venue"
},
  "geometry": {"coordinates":[9.120675,48.522022],"type":"Point"}
}