{
  "type": "Feature",
  "properties": {
    "iso:country":"DE",
    "sg:address":"Industriestr 10g",
    "sg:city":"Rellingen",
    "sg:phone":"+49 6172/9163300",
    "sg:postcode":"25462",
    "sg:province":"Schleswig-Holstein",
    "wof:name":"St Systems Gmbh",
    "wof:placetype":"venue"
},
  "geometry": {"coordinates":[8.610874176,50.2301177979],"type":"Point"}
}