{
  "type": "Feature",
  "properties": {
    "iso:country":"DE",
    "sg:address":"Ritterstr. 3",
    "sg:city":"Ditzingen",
    "sg:phone":"+49 7156/6438",
    "sg:postcode":"71254",
    "sg:province":"Baden-W\u00fcrttemberg",
    "wof:name":"E. Gommel",
    "wof:placetype":"venue"
},
  "geometry": {"coordinates":[9.0242595673,48.8444328308],"type":"Point"}
}