{
  "type": "Feature",
  "properties": {
    "iso:country":"DE",
    "sg:address":"Holstweg 24",
    "sg:city":"Berlin",
    "sg:phone":"+49 30/8026550",
    "sg:postcode":"14163",
    "sg:province":"Berlin",
    "wof:name":"Bestmaker Service Gmbh",
    "wof:placetype":"venue"
},
  "geometry": {"coordinates":[13.234619,52.428661],"type":"Point"}
}