{
  "type": "Feature",
  "properties": {
    "iso:country":"DE",
    "sg:address":"Landsberger Str. 205",
    "sg:city":"M\u00fcnchen",
    "sg:phone":"+49 89/33019490",
    "sg:postcode":"80687",
    "sg:province":"Bayern",
    "wof:name":"Ott & Kollegen Steuerberatungsges. Mbh",
    "wof:placetype":"venue"
},
  "geometry": {"coordinates":[11.5168323517,48.1413650513],"type":"Point"}
}