{
  "type": "Feature",
  "properties": {
    "iso:country":"DE",
    "sg:address":"Langeooger Str. 16",
    "sg:city":"Bremen",
    "sg:phone":"+49 421/3964198",
    "sg:postcode":"28219",
    "sg:province":"Bremen",
    "wof:name":"M. St\u00fcwe Hebamme",
    "wof:placetype":"venue"
},
  "geometry": {"coordinates":[8.781815,53.103146],"type":"Point"}
}