{
  "type": "Feature",
  "properties": {
    "iso:country":"DE",
    "sg:address":"Sch\u00e4fergasse 28",
    "sg:city":"Maintal",
    "sg:phone":"+49 6109/66616",
    "sg:postcode":"63477",
    "sg:province":"Hessen",
    "wof:name":"Trinkhalle Pl\u00e4ttenweide",
    "wof:placetype":"venue"
},
  "geometry": {"coordinates":[8.8019504547,50.1509933472],"type":"Point"}
}