{
  "type": "Feature",
  "properties": {
    "iso:country":"DE",
    "sg:address":"M\u00fchlenstr. 45",
    "sg:city":"Cloppenburg",
    "sg:phone":"+49 4471/81100",
    "sg:postcode":"49661",
    "sg:province":"Niedersachsen",
    "wof:name":"Buchhandlung Wolfgang Janssen",
    "wof:placetype":"venue"
},
  "geometry": {"coordinates":[8.0422525406,52.8478431702],"type":"Point"}
}