{
  "type": "Feature",
  "properties": {
    "iso:country":"DE",
    "sg:address":"Uneringer Str. 1",
    "sg:city":"Starnberg",
    "sg:phone":"+49 8151/12157",
    "sg:postcode":"82319",
    "sg:province":"Bayern",
    "wof:name":"Golfanlage Starnberg Beteiligungs-gmbh",
    "wof:placetype":"venue"
},
  "geometry": {"coordinates":[11.281187,48.016933],"type":"Point"}
}