{
  "type": "Feature",
  "properties": {
    "iso:country":"DE",
    "sg:address":"Ostenwalder Str. 3",
    "sg:city":"H\u00f6rstel",
    "sg:phone":"+49 5459/1093",
    "sg:postcode":"48477",
    "sg:province":"Nordrhein-Westfalen",
    "wof:name":"J. Roth",
    "wof:placetype":"venue"
},
  "geometry": {"coordinates":[7.5869250298,52.3008766174],"type":"Point"}
}