{
  "type": "Feature",
  "properties": {
    "iso:country":"DE",
    "sg:address":"Lerchenstr. 3",
    "sg:city":"Bruckm\u00fchl",
    "sg:phone":"+49 8062/6829",
    "sg:postcode":"83052",
    "sg:province":"Bayern",
    "wof:name":"Birkenst\u00fcberl",
    "wof:placetype":"venue"
},
  "geometry": {"coordinates":[11.9380321503,47.8759002686],"type":"Point"}
}