{
  "type": "Feature",
  "properties": {
    "iso:country":"DE",
    "sg:address":"Markt 1",
    "sg:city":"Schwarzenberg",
    "sg:phone":"+49 3774/15570",
    "sg:postcode":"08340",
    "sg:province":"Sachsen",
    "wof:name":"Hotel Ratskeller",
    "wof:placetype":"venue"
},
  "geometry": {"coordinates":[12.7838525772,50.5376586914],"type":"Point"}
}