{
  "type": "Feature",
  "properties": {
    "iso:country":"DE",
    "sg:address":"Feuerweg 6",
    "sg:city":"Nordholz",
    "sg:phone":"+49 4741/602340",
    "sg:postcode":"27637",
    "sg:province":"Niedersachsen",
    "wof:name":"Flughafen-betriebsgesellschaft Cuxhaven-nordholz Mbh",
    "wof:placetype":"venue"
},
  "geometry": {"coordinates":[8.5882701874,53.7738800049],"type":"Point"}
}