{
  "type": "Feature",
  "properties": {
    "iso:country":"DE",
    "sg:address":"Neuenkamp 3",
    "sg:city":"Fr\u00f6ndenberg",
    "sg:phone":"+49 2377/2176",
    "sg:postcode":"58730",
    "sg:province":"Nordrhein-Westfalen",
    "wof:name":"Heinrich Werneke",
    "wof:placetype":"venue"
},
  "geometry": {"coordinates":[7.829259,51.510296],"type":"Point"}
}