{
  "type": "Feature",
  "properties": {
    "iso:country":"DE",
    "sg:address":"Henrich-Valck-Str. 31",
    "sg:city":"Laer",
    "sg:postcode":"48366",
    "sg:province":"Nordrhein-Westfalen",
    "wof:name":"Norbert Hoppermann Ingenieur Und Architekt",
    "wof:placetype":"venue"
},
  "geometry": {"coordinates":[7.358971,52.049156],"type":"Point"}
}