{
  "type": "Feature",
  "properties": {
    "iso:country":"DE",
    "sg:address":"Sandschurrepfad 43",
    "sg:city":"Berlin",
    "sg:phone":"+49 30/6519502",
    "sg:postcode":"12557",
    "sg:province":"Berlin",
    "wof:name":"Helmut N\u00f6lte",
    "wof:placetype":"venue"
},
  "geometry": {"coordinates":[13.600626,52.431446],"type":"Point"}
}