{
  "type": "Feature",
  "properties": {
    "iso:country":"DE",
    "sg:address":"Suhring 4",
    "sg:city":"Reddelich",
    "sg:phone":"+49 38203/4320",
    "sg:postcode":"18209",
    "sg:province":"Mecklenburg-Vorpommern",
    "wof:name":"Fresand Gmbh",
    "wof:placetype":"venue"
},
  "geometry": {"coordinates":[11.842158,54.08662],"type":"Point"}
}