{
  "type": "Feature",
  "properties": {
    "iso:country":"DE",
    "sg:address":"Am Fort Gonsenheim 120",
    "sg:city":"Mainz",
    "sg:phone":"+49 6131/371830",
    "sg:postcode":"55122",
    "sg:province":"Rheinland-Pfalz",
    "wof:name":"Petra Nothnagel-filz Rechtsanw\u00e4ltin",
    "wof:placetype":"venue"
},
  "geometry": {"coordinates":[8.2451963425,50.0030937195],"type":"Point"}
}