{
  "type": "Feature",
  "properties": {
    "iso:country":"DE",
    "sg:address":"Gartenweg 5",
    "sg:city":"Nauen",
    "sg:phone":"+49 3321/48380",
    "sg:postcode":"14641",
    "sg:province":"Brandenburg",
    "wof:name":"J\u00f6rg Mahnkopf",
    "wof:placetype":"venue"
},
  "geometry": {"coordinates":[12.860856,52.610661],"type":"Point"}
}