{
  "type": "Feature",
  "properties": {
    "iso:country":"DE",
    "sg:address":"Am Falchen 60",
    "sg:city":"Lechbruck",
    "sg:phone":"+49 8862/7720",
    "sg:postcode":"86983",
    "sg:province":"Bayern",
    "wof:name":"Bergsonne Freizeitheim Des Diakonischen Werkes",
    "wof:placetype":"venue"
},
  "geometry": {"coordinates":[10.7895889282,47.6906661987],"type":"Point"}
}