{
  "type": "Feature",
  "properties": {
    "iso:country":"DE",
    "sg:address":"Fischzucht 1",
    "sg:city":"Bischofsheim",
    "sg:phone":"+49 9772/248",
    "sg:postcode":"97653",
    "sg:province":"Bayern",
    "wof:name":"Christliche Tagungsst\u00e4tte Hohe Rh\u00f6n E. V.",
    "wof:placetype":"venue"
},
  "geometry": {"coordinates":[9.9940900803,50.3865737915],"type":"Point"}
}