{
  "type": "Feature",
  "properties": {
    "iso:country":"DE",
    "sg:address":"Halligweg 7",
    "sg:city":"Schortens",
    "sg:phone":"+49 4461/80251",
    "sg:postcode":"26419",
    "sg:province":"Niedersachsen",
    "wof:name":"Fritz B\u00f6hm",
    "wof:placetype":"venue"
},
  "geometry": {"coordinates":[7.931225,53.539997],"type":"Point"}
}