{
  "type": "Feature",
  "properties": {
    "iso:country":"DE",
    "sg:address":"Kainzenweg 10",
    "sg:city":"Passau",
    "sg:phone":"+49 851/7914",
    "sg:postcode":"94036",
    "sg:province":"Bayern",
    "wof:name":"R. Tewaag",
    "wof:placetype":"venue"
},
  "geometry": {"coordinates":[13.434472084,48.5640411377],"type":"Point"}
}