{
  "type": "Feature",
  "properties": {
    "iso:country":"DE",
    "sg:address":"Ludwigstr. 16",
    "sg:city":"M\u00fcnchen",
    "sg:phone":"+49 89/28638384",
    "sg:postcode":"80539",
    "sg:province":"Bayern",
    "wof:name":"Monumenta Germaniae Historica",
    "wof:placetype":"venue"
},
  "geometry": {"coordinates":[11.5800819397,48.1475334167],"type":"Point"}
}