{
  "type": "Feature",
  "properties": {
    "iso:country":"DE",
    "sg:address":"Industriestr. 16",
    "sg:city":"Rietberg",
    "sg:phone":"+49 5244/8063",
    "sg:postcode":"33397",
    "sg:province":"Nordrhein-Westfalen",
    "wof:name":"Conrad Bussieweke M\u00f6belwerkst\u00e4tten Gmbh & Co.",
    "wof:placetype":"venue"
},
  "geometry": {"coordinates":[8.42167,51.794029],"type":"Point"}
}