{
  "type": "Feature",
  "properties": {
    "iso:country":"DE",
    "sg:address":"Wagrain",
    "sg:city":"Schleching",
    "sg:phone":"+49 8649/810",
    "sg:postcode":"83259",
    "sg:province":"Bayern",
    "wof:name":"Christa Wagner",
    "wof:placetype":"venue"
},
  "geometry": {"coordinates":[12.389222,47.709724],"type":"Point"}
}