{
  "type": "Feature",
  "properties": {
    "iso:country":"DE",
    "sg:address":"Talstr. 52",
    "sg:city":"Solingen",
    "sg:phone":"+49 212/75027",
    "sg:postcode":"42697",
    "sg:province":"Nordrhein-Westfalen",
    "wof:name":"E. Altenpohl-wehner",
    "wof:placetype":"venue"
},
  "geometry": {"coordinates":[6.996912,51.160686],"type":"Point"}
}