{
  "type": "Feature",
  "properties": {
    "iso:country":"DE",
    "sg:address":"Br\u00f6derhausener Str. 14",
    "sg:city":"H\u00fcllhorst",
    "sg:phone":"+49 5744/1201",
    "sg:postcode":"32609",
    "sg:province":"Nordrhein-Westfalen",
    "wof:name":"Wilhelm Schlinger",
    "wof:placetype":"venue"
},
  "geometry": {"coordinates":[8.70262,52.25568],"type":"Point"}
}