{
  "type": "Feature",
  "properties": {
    "iso:country":"DE",
    "sg:address":"Wodantal 106",
    "sg:city":"Hattingen",
    "sg:phone":"+49 2052/4985",
    "sg:postcode":"45529",
    "sg:province":"Nordrhein-Westfalen",
    "wof:name":"Rassegefl\u00fcgelzucht-verein Viktoria Nierenhof 1929",
    "wof:placetype":"venue"
},
  "geometry": {"coordinates":[7.1713409424,51.3753623962],"type":"Point"}
}