{
  "type": "Feature",
  "properties": {
    "iso:country":"DE",
    "sg:address":"Rektor-Wutz-Str. 34",
    "sg:city":"K\u00fcmmersbruck",
    "sg:phone":"+49 9621/82228",
    "sg:postcode":"92245",
    "sg:province":"Bayern",
    "wof:name":"Hans Heinrich",
    "wof:placetype":"venue"
},
  "geometry": {"coordinates":[11.888716,49.414364],"type":"Point"}
}