{
  "type": "Feature",
  "properties": {
    "iso:country":"DE",
    "sg:address":"Nr. 23",
    "sg:city":"Greiz",
    "sg:phone":"+49 3661/3610",
    "sg:postcode":"07973",
    "sg:province":"Th\u00fcringen",
    "wof:name":"B. Reineck Immobilienmakler",
    "wof:placetype":"venue"
},
  "geometry": {"coordinates":[12.2006196976,50.6542396545],"type":"Point"}
}