{
  "type": "Feature",
  "properties": {
    "iso:country":"DE",
    "sg:address":"Freiheitstr. 49",
    "sg:city":"Schlaitz",
    "sg:phone":"+49 34955/22423",
    "sg:postcode":"06774",
    "sg:province":"Sachsen-Anhalt",
    "wof:name":"H & H Innenausbau Schlaitz Gmbh",
    "wof:placetype":"venue"
},
  "geometry": {"coordinates":[12.431325,51.660229],"type":"Point"}
}