{
  "type": "Feature",
  "properties": {
    "iso:country":"DE",
    "sg:address":"Wirkerstr. 2",
    "sg:city":"Albstadt",
    "sg:phone":"+49 7432/21361",
    "sg:postcode":"72461",
    "sg:province":"Baden-W\u00fcrttemberg",
    "wof:name":"Frottana Textil Gmbh",
    "wof:placetype":"venue"
},
  "geometry": {"coordinates":[9.0008239746,48.2596435547],"type":"Point"}
}