{
  "type": "Feature",
  "properties": {
    "iso:country":"DE",
    "sg:address":"Hauptstr. 35",
    "sg:city":"Birkweiler",
    "sg:phone":"+49 6345/3423",
    "sg:postcode":"76831",
    "sg:province":"Rheinland-Pfalz",
    "wof:name":"Horst Dicker",
    "wof:placetype":"venue"
},
  "geometry": {"coordinates":[8.0335083008,49.2039985657],"type":"Point"}
}