{
  "type": "Feature",
  "properties": {
    "iso:country":"DE",
    "sg:address":"Bahnhofstr. 32-34",
    "sg:city":"Vilseck",
    "sg:phone":"+49 9662/40160",
    "sg:postcode":"92249",
    "sg:province":"Bayern",
    "wof:name":"Str\u00f6ll Gmbh",
    "wof:placetype":"venue"
},
  "geometry": {"coordinates":[11.80255,49.617157],"type":"Point"}
}