{
  "type": "Feature",
  "properties": {
    "iso:country":"DE",
    "sg:address":"Dreischeweg 39 B",
    "sg:city":"Hildesheim",
    "sg:phone":"+49 5121/47825",
    "sg:postcode":"31137",
    "sg:province":"Niedersachsen",
    "wof:name":"Helmut Kassner Heilpraktiker",
    "wof:placetype":"venue"
},
  "geometry": {"coordinates":[9.9121627808,52.1689453125],"type":"Point"}
}