{
  "type": "Feature",
  "properties": {
    "iso:country":"DE",
    "sg:address":"Bahnhofstr. 18",
    "sg:city":"Rheinau",
    "sg:phone":"+49 7844/868",
    "sg:postcode":"77866",
    "sg:province":"Baden-W\u00fcrttemberg",
    "wof:name":"Waldhorn",
    "wof:placetype":"venue"
},
  "geometry": {"coordinates":[7.9402427673,48.6704063416],"type":"Point"}
}