{
  "type": "Feature",
  "properties": {
    "iso:country":"DE",
    "sg:address":"Watzmannstr. 1",
    "sg:city":"Starnberg",
    "sg:phone":"+49 8151/73021",
    "sg:postcode":"82319",
    "sg:province":"Bayern",
    "wof:name":"Jaumann Alpenland Kunstwerkst\u00c4tte Ohg",
    "wof:placetype":"venue"
},
  "geometry": {"coordinates":[11.3279399872,48.0124740601],"type":"Point"}
}