{
  "type": "Feature",
  "properties": {
    "iso:country":"DE",
    "sg:address":"Hohenzollerndamm 193",
    "sg:city":"Berlin",
    "sg:phone":"+49 30/2613860",
    "sg:postcode":"10717",
    "sg:province":"Berlin",
    "wof:name":"Astrid K\u00f6hlmann",
    "wof:placetype":"venue"
},
  "geometry": {"coordinates":[13.3221950531,52.492893219],"type":"Point"}
}