{
  "type": "Feature",
  "properties": {
    "iso:country":"DE",
    "sg:address":"Hauptstr. 197",
    "sg:city":"Spaichingen",
    "sg:phone":"+49 4974/242238",
    "sg:postcode":"78549",
    "sg:province":"Baden-W\u00fcrttemberg",
    "wof:name":"Conrad Braun & Sohn Gmbh",
    "wof:placetype":"venue"
},
  "geometry": {"coordinates":[8.7324676514,48.0802345276],"type":"Point"}
}