{
  "type": "Feature",
  "properties": {
    "iso:country":"DE",
    "sg:address":"Feuersteinstr. 54",
    "sg:city":"Eggolsheim",
    "sg:phone":"+49 9545/509820",
    "sg:postcode":"91330",
    "sg:province":"Bayern",
    "wof:name":"Vsr Versicherungs- Service Richter",
    "wof:placetype":"venue"
},
  "geometry": {"coordinates":[11.1111774445,49.7940750122],"type":"Point"}
}