{
  "type": "Feature",
  "properties": {
    "iso:country":"DE",
    "sg:address":"Gewerbepark Keplerstr 26",
    "sg:city":"Gera",
    "sg:phone":"+49 365/7106890",
    "sg:postcode":"07549",
    "sg:province":"Th\u00fcringen",
    "wof:name":"Produma Maschineninstandhaltung Und Elektronik-service Gmbh",
    "wof:placetype":"venue"
},
  "geometry": {"coordinates":[12.06383,50.852928],"type":"Point"}
}