{
  "type": "Feature",
  "properties": {
    "iso:country":"DE",
    "sg:address":"Marktplatz 15",
    "sg:city":"Ahaus",
    "sg:phone":"+49 2561/98210",
    "sg:postcode":"48683",
    "sg:province":"Nordrhein-Westfalen",
    "wof:name":"Hotel J\u00e4gerhof",
    "wof:placetype":"venue"
},
  "geometry": {"coordinates":[7.0068898201,52.0756378174],"type":"Point"}
}