{
  "type": "Feature",
  "properties": {
    "iso:country":"DE",
    "sg:address":"L\u00fcdersenkamp 6",
    "sg:city":"Stadthagen",
    "sg:phone":"+49 5721/2356",
    "sg:postcode":"31655",
    "sg:province":"Niedersachsen",
    "wof:name":"F. W\u00f6bbeking",
    "wof:placetype":"venue"
},
  "geometry": {"coordinates":[9.1604423523,52.3227729797],"type":"Point"}
}