{
  "type": "Feature",
  "properties": {
    "iso:country":"DE",
    "sg:address":"Industriestr. 27",
    "sg:city":"Bad Oldesloe",
    "sg:postcode":"23843",
    "sg:province":"Schleswig-Holstein",
    "wof:name":"Otto Kolz Gmbh",
    "wof:placetype":"venue"
},
  "geometry": {"coordinates":[10.3948326111,53.8014526367],"type":"Point"}
}