{
  "type": "Feature",
  "properties": {
    "iso:country":"DE",
    "sg:address":"Kleinschwaig",
    "sg:city":"Valley",
    "sg:phone":"+49 8095/2875",
    "sg:postcode":"83626",
    "sg:province":"Bayern",
    "wof:name":"Grubich",
    "wof:placetype":"venue"
},
  "geometry": {"coordinates":[11.7611303329,47.9240188599],"type":"Point"}
}