{
  "type": "Feature",
  "properties": {
    "iso:country":"DE",
    "sg:address":"Grenzstr. 1",
    "sg:city":"Wilhelmshaven",
    "sg:phone":"+49 4421/15540",
    "sg:postcode":"26382",
    "sg:province":"Niedersachsen",
    "wof:name":"Reiseb\u00fcro Auto Fischer Gmbh Thomas Cook",
    "wof:placetype":"venue"
},
  "geometry": {"coordinates":[8.1112937927,53.5202445984],"type":"Point"}
}