{
  "type": "Feature",
  "properties": {
    "iso:country":"DE",
    "sg:address":"Niederhorbacher Str. 46",
    "sg:city":"Neunkirchen-Seelscheid",
    "sg:phone":"+49 2247/2640",
    "sg:postcode":"53819",
    "sg:province":"Nordrhein-Westfalen",
    "wof:name":"Georg Oberd\u00f6rfer",
    "wof:placetype":"venue"
},
  "geometry": {"coordinates":[7.358099,50.835983],"type":"Point"}
}