{
  "type": "Feature",
  "properties": {
    "iso:country":"DE",
    "sg:address":"Siedlung am Devener Holz 12",
    "sg:city":"Demmin",
    "sg:phone":"+49 3998/202459",
    "sg:postcode":"17109",
    "sg:province":"Mecklenburg-Vorpommern",
    "wof:name":"Wolfgang Czech",
    "wof:placetype":"venue"
},
  "geometry": {"coordinates":[13.0193653107,53.8955917358],"type":"Point"}
}