{
  "type": "Feature",
  "properties": {
    "iso:country":"DE",
    "sg:address":"Freundegrund 12",
    "sg:city":"Bad Arolsen",
    "sg:phone":"+49 5691/3716",
    "sg:postcode":"34454",
    "sg:province":"Hessen",
    "wof:name":"O. M\u00fcller",
    "wof:placetype":"venue"
},
  "geometry": {"coordinates":[8.989641,51.36272],"type":"Point"}
}