{
  "type": "Feature",
  "properties": {
    "iso:country":"DE",
    "sg:address":"Hansaring 146",
    "sg:city":"Greven",
    "sg:phone":"+49 4925/7195380",
    "sg:postcode":"48268",
    "sg:province":"Nordrhein-Westfalen",
    "wof:name":"Hillebrandt, Stahl- Und Behaelterbau Gmbh",
    "wof:placetype":"venue"
},
  "geometry": {"coordinates":[7.6147232056,52.1091880798],"type":"Point"}
}