{
  "type": "Feature",
  "properties": {
    "iso:country":"DE",
    "sg:address":"Burgsteller Weg 11",
    "sg:city":"Neustadt",
    "sg:phone":"+49 5032/62624",
    "sg:postcode":"31535",
    "sg:province":"Niedersachsen",
    "wof:name":"Treff",
    "wof:placetype":"venue"
},
  "geometry": {"coordinates":[9.4833068848,52.4679336548],"type":"Point"}
}