{
  "type": "Feature",
  "properties": {
    "iso:country":"DE",
    "sg:address":"Siegerstr.",
    "sg:city":"Kenn",
    "sg:phone":"+49 6502/9120",
    "sg:postcode":"54344",
    "sg:province":"Rheinland-Pfalz",
    "wof:name":"Quint Gmbh & Co. Kg",
    "wof:placetype":"venue"
},
  "geometry": {"coordinates":[6.7269301414,49.7998466492],"type":"Point"}
}