{
  "type": "Feature",
  "properties": {
    "iso:country":"DE",
    "sg:address":"Koppel 74",
    "sg:city":"Hamburg",
    "sg:postcode":"20099",
    "sg:province":"Hamburg",
    "wof:name":"Autohaus Wilhelm Kuhfu\u00df Gmbh",
    "wof:placetype":"venue"
},
  "geometry": {"coordinates":[10.0116815567,53.5587844849],"type":"Point"}
}