{
  "type": "Feature",
  "properties": {
    "iso:country":"DE",
    "sg:address":"Lebacher Str. 73",
    "sg:city":"Heusweiler",
    "sg:phone":"+49 6806/91890",
    "sg:postcode":"66265",
    "sg:province":"Saarland",
    "wof:name":"Els\u00e4ssische Stuben Inh. Dieter Gengenbach",
    "wof:placetype":"venue"
},
  "geometry": {"coordinates":[6.9319758415,49.3615837097],"type":"Point"}
}