{
  "type": "Feature",
  "properties": {
    "iso:country":"DE",
    "sg:address":"Jurastr. 27",
    "sg:city":"T\u00fcbingen",
    "sg:phone":"+49 7071/792225",
    "sg:postcode":"72072",
    "sg:province":"Baden-W\u00fcrttemberg",
    "wof:name":"Hirsch",
    "wof:placetype":"venue"
},
  "geometry": {"coordinates":[9.0509243011,48.5037307739],"type":"Point"}
}