{
  "type": "Feature",
  "properties": {
    "iso:country":"DE",
    "sg:address":"Hunsr\u00fcckstr. 6",
    "sg:city":"Frankfurt",
    "sg:phone":"+49 69/302581",
    "sg:postcode":"65929",
    "sg:province":"Hessen",
    "wof:name":"Reiner Wagner",
    "wof:placetype":"venue"
},
  "geometry": {"coordinates":[8.5341653824,50.1101913452],"type":"Point"}
}