{
  "type": "Feature",
  "properties": {
    "iso:country":"DE",
    "sg:address":"Marburger Str. 32",
    "sg:city":"Rabenau",
    "sg:phone":"+49 6407/1694",
    "sg:postcode":"35466",
    "sg:province":"Hessen",
    "wof:name":"H. Lich",
    "wof:placetype":"venue"
},
  "geometry": {"coordinates":[8.8584346771,50.6781730652],"type":"Point"}
}