{
  "type": "Feature",
  "properties": {
    "iso:country":"DE",
    "sg:address":"Am Bischofskreuz 11",
    "sg:city":"Freiburg",
    "sg:phone":"+49 761/87279",
    "sg:postcode":"79114",
    "sg:province":"Baden-W\u00fcrttemberg",
    "wof:name":"Kretschmar",
    "wof:placetype":"venue"
},
  "geometry": {"coordinates":[7.818704,48.005623],"type":"Point"}
}