{
  "type": "Feature",
  "properties": {
    "iso:country":"DE",
    "sg:address":"Industriestr. 24",
    "sg:city":"M\u00fclheim-K\u00e4rlich",
    "sg:phone":"+49 261/2960",
    "sg:postcode":"56218",
    "sg:province":"Rheinland-Pfalz",
    "wof:name":"Lohmeier & Partner Gmbh Spirituosen Herst.",
    "wof:placetype":"venue"
},
  "geometry": {"coordinates":[7.5274209976,50.3952980042],"type":"Point"}
}