{
  "type": "Feature",
  "properties": {
    "iso:country":"DE",
    "sg:address":"Heidecker Weg 66",
    "sg:city":"Sprotta",
    "sg:phone":"+49 3423/752100",
    "sg:postcode":"04838",
    "sg:province":"Sachsen",
    "wof:name":"Karl-heinz Hempel",
    "wof:placetype":"venue"
},
  "geometry": {"coordinates":[12.626225,51.493671],"type":"Point"}
}