{
  "type": "Feature",
  "properties": {
    "iso:country":"DE",
    "sg:address":"Dillinger Str. 33",
    "sg:city":"Burgau",
    "sg:phone":"+49 8222/410702",
    "sg:postcode":"89331",
    "sg:province":"Bayern",
    "wof:name":"Norma Gmbh & Co. Kg Lebensmittelfilialbetrieb",
    "wof:placetype":"venue"
},
  "geometry": {"coordinates":[10.4113149643,48.4380989075],"type":"Point"}
}