{
  "type": "Feature",
  "properties": {
    "iso:country":"DE",
    "sg:address":"Eckenbertstr. 75",
    "sg:city":"Worms",
    "sg:phone":"+49 6241/77110",
    "sg:postcode":"67549",
    "sg:province":"Rheinland-Pfalz",
    "wof:name":"Mathias Schwarz Bildhauer",
    "wof:placetype":"venue"
},
  "geometry": {"coordinates":[8.336791,49.643673],"type":"Point"}
}