{
  "type": "Feature",
  "properties": {
    "iso:country":"DE",
    "sg:address":"Robert-Bunsen-Str. 5",
    "sg:city":"R\u00fcsselsheim",
    "sg:phone":"+49 6142/504607",
    "sg:postcode":"65428",
    "sg:province":"Hessen",
    "wof:name":"Peters Party-service Peter Voigt",
    "wof:placetype":"venue"
},
  "geometry": {"coordinates":[8.432605,49.983707],"type":"Point"}
}