{
  "type": "Feature",
  "properties": {
    "iso:country":"DE",
    "sg:address":"Hauptstr. 2",
    "sg:city":"Mannheim",
    "sg:phone":"+49 621/7182747",
    "sg:postcode":"68259",
    "sg:province":"Baden-W\u00fcrttemberg",
    "wof:name":"Birgit Balz Rechtsanw\u00e4ltin",
    "wof:placetype":"venue"
},
  "geometry": {"coordinates":[8.5375881195,49.4857749939],"type":"Point"}
}