{
  "type": "Feature",
  "properties": {
    "iso:country":"DE",
    "sg:address":"Rosenhofer Str. 1",
    "sg:city":"Mintraching",
    "sg:phone":"+49 9406/2985",
    "sg:postcode":"93098",
    "sg:province":"Bayern",
    "wof:name":"J. Saller",
    "wof:placetype":"venue"
},
  "geometry": {"coordinates":[12.239541,48.955303],"type":"Point"}
}