{
  "type": "Feature",
  "properties": {
    "iso:country":"DE",
    "sg:address":"August-Hebenstreit-Str. 22",
    "sg:city":"M\u00fchlacker",
    "sg:phone":"+49 7041/41698",
    "sg:postcode":"75417",
    "sg:province":"Baden-W\u00fcrttemberg",
    "wof:name":"Friedrich Lachenmajer Gmbh",
    "wof:placetype":"venue"
},
  "geometry": {"coordinates":[8.8356981277,48.9422988892],"type":"Point"}
}