{
  "type": "Feature",
  "properties": {
    "iso:country":"DE",
    "sg:address":"Schwarzer Weg 23",
    "sg:city":"Espelkamp",
    "sg:phone":"+49 5743/8535",
    "sg:postcode":"32339",
    "sg:province":"Nordrhein-Westfalen",
    "wof:name":"Heinz Kracht Farben-lacke-grosshandel",
    "wof:placetype":"venue"
},
  "geometry": {"coordinates":[8.610152,52.355564],"type":"Point"}
}