{
  "type": "Feature",
  "properties": {
    "iso:country":"DE",
    "sg:address":"Martin-Luther-Str. 4",
    "sg:city":"Grafenw\u00f6hr",
    "sg:phone":"+49 9641/2218",
    "sg:postcode":"92655",
    "sg:province":"Bayern",
    "wof:name":"Ev. Luth. Pfarramt",
    "wof:placetype":"venue"
},
  "geometry": {"coordinates":[11.9041500092,49.7144165039],"type":"Point"}
}