{
  "type": "Feature",
  "properties": {
    "iso:country":"DE",
    "sg:address":"Mainaustr. 199",
    "sg:city":"Konstanz",
    "sg:phone":"+49 7531/31349",
    "sg:postcode":"78464",
    "sg:province":"Baden-W\u00fcrttemberg",
    "wof:name":"Edgar Weiss",
    "wof:placetype":"venue"
},
  "geometry": {"coordinates":[9.1936950684,47.689365387],"type":"Point"}
}