{
  "type": "Feature",
  "properties": {
    "iso:country":"DE",
    "sg:address":"Fu\u00dffallstr. 18",
    "sg:city":"K\u00f6ln",
    "sg:phone":"+49 221/9692406",
    "sg:postcode":"51109",
    "sg:province":"Nordrhein-Westfalen",
    "wof:name":"J. Kessling",
    "wof:placetype":"venue"
},
  "geometry": {"coordinates":[7.0478100777,50.9494438171],"type":"Point"}
}