{
  "type": "Feature",
  "properties": {
    "iso:country":"DE",
    "sg:address":"Sch\u00f6ne Aussicht 6",
    "sg:city":"Stadt Wehlen",
    "sg:postcode":"01829",
    "sg:province":"Sachsen",
    "wof:name":"Ferienhaus R\u00f6sler In Wehlen",
    "wof:placetype":"venue"
},
  "geometry": {"coordinates":[14.028499,50.958416],"type":"Point"}
}