{
  "type": "Feature",
  "properties": {
    "iso:country":"DE",
    "sg:address":"Siedlung 9",
    "sg:city":"Uttenreuth",
    "sg:phone":"+49 9131/54340",
    "sg:postcode":"91080",
    "sg:province":"Bayern",
    "wof:name":"Feuerwehrverein Christian Bock",
    "wof:placetype":"venue"
},
  "geometry": {"coordinates":[11.0733575821,49.5905647278],"type":"Point"}
}