{
  "type": "Feature",
  "properties": {
    "iso:country":"DE",
    "sg:address":"Senner Hellweg 489",
    "sg:city":"Bielefeld",
    "sg:phone":"+49 5205/3445",
    "sg:postcode":"33689",
    "sg:province":"Nordrhein-Westfalen",
    "wof:name":"Waldgastst\u00e4tte Fichteheim",
    "wof:placetype":"venue"
},
  "geometry": {"coordinates":[8.6339454651,51.9511375427],"type":"Point"}
}