{
  "type": "Feature",
  "properties": {
    "iso:country":"DE",
    "sg:address":"Vaalser Str. 68",
    "sg:city":"Aachen",
    "sg:phone":"+49 241/82359",
    "sg:postcode":"52064",
    "sg:province":"Nordrhein-Westfalen",
    "wof:name":"Detlef M\u00fcller",
    "wof:placetype":"venue"
},
  "geometry": {"coordinates":[6.070742,50.770222],"type":"Point"}
}