{
  "type": "Feature",
  "properties": {
    "iso:country":"DE",
    "sg:address":"Gildestr. 17",
    "sg:city":"Vechta",
    "sg:postcode":"49377",
    "sg:province":"Niedersachsen",
    "wof:name":"H. F. Grundst\u00fccks- Verwaltung Gmbh",
    "wof:placetype":"venue"
},
  "geometry": {"coordinates":[8.2866888046,52.7308998108],"type":"Point"}
}