{
  "type": "Feature",
  "properties": {
    "iso:country":"DE",
    "sg:address":"H\u00f6henweg 1",
    "sg:city":"Achern",
    "sg:postcode":"77855",
    "sg:province":"Baden-W\u00fcrttemberg",
    "wof:name":"Bauatelier K\u00f6ppel Gmbh",
    "wof:placetype":"venue"
},
  "geometry": {"coordinates":[8.067058,48.623699],"type":"Point"}
}