{
  "type": "Feature",
  "properties": {
    "iso:country":"DE",
    "sg:address":"Markt 29",
    "sg:city":"Geldern",
    "sg:phone":"+49 2831/4869",
    "sg:postcode":"47608",
    "sg:province":"Nordrhein-Westfalen",
    "wof:name":"Quick-schuh",
    "wof:placetype":"venue"
},
  "geometry": {"coordinates":[6.3225650787,51.5167579651],"type":"Point"}
}