{
  "type": "Feature",
  "properties": {
    "iso:country":"DE",
    "sg:address":"Contrescarpe 53",
    "sg:city":"Bremen",
    "sg:phone":"+49 421/326065",
    "sg:postcode":"28195",
    "sg:province":"Bremen",
    "wof:name":"Forpromote Ges. F\u00fcr Markt- Einf\u00fchrung Und Distribution",
    "wof:placetype":"venue"
},
  "geometry": {"coordinates":[8.813308,53.07782],"type":"Point"}
}