{
  "type": "Feature",
  "properties": {
    "iso:country":"DE",
    "sg:address":"Theodor-Heuss-Str. 10",
    "sg:city":"K\u00f6nigsfeld",
    "sg:phone":"+49 7725/7348",
    "sg:postcode":"78126",
    "sg:province":"Baden-W\u00fcrttemberg",
    "wof:name":"E. Herrmann",
    "wof:placetype":"venue"
},
  "geometry": {"coordinates":[8.4191455841,48.1377372742],"type":"Point"}
}