{
  "type": "Feature",
  "properties": {
    "iso:country":"DE",
    "sg:address":"Potsdamer Chaussee 34",
    "sg:city":"Berlin",
    "sg:phone":"+49 30/8031734",
    "sg:postcode":"14129",
    "sg:province":"Berlin",
    "wof:name":"G\u00fcnter Und Ulrich Grauel Bildhauerei",
    "wof:placetype":"venue"
},
  "geometry": {"coordinates":[13.2121324539,52.4270439148],"type":"Point"}
}