{
  "type": "Feature",
  "properties": {
    "iso:country":"DE",
    "sg:address":"Ulrich-von-Hutten-Str. 10",
    "sg:city":"Sinntal",
    "sg:phone":"+49 6665/247",
    "sg:postcode":"36391",
    "sg:province":"Hessen",
    "wof:name":"Heinz Fu\u00df",
    "wof:placetype":"venue"
},
  "geometry": {"coordinates":[9.6216144562,50.2529258728],"type":"Point"}
}