{
  "type": "Feature",
  "properties": {
    "iso:country":"DE",
    "sg:address":"Karl-Erb-Ring 175",
    "sg:city":"Ravensburg",
    "sg:phone":"+49 751/92619",
    "sg:postcode":"88213",
    "sg:province":"Baden-W\u00fcrttemberg",
    "wof:name":"Volker Petzold Architekt",
    "wof:placetype":"venue"
},
  "geometry": {"coordinates":[9.576305,47.781376],"type":"Point"}
}