{
  "type": "Feature",
  "properties": {
    "iso:country":"DE",
    "sg:address":"Preyerstr. 101",
    "sg:city":"Eschweiler",
    "sg:phone":"+49 2403/800667",
    "sg:postcode":"52249",
    "sg:province":"Nordrhein-Westfalen",
    "wof:name":"Messmer Grundst\u00fccks-gmbh",
    "wof:placetype":"venue"
},
  "geometry": {"coordinates":[6.275435,50.82592],"type":"Point"}
}