{
  "type": "Feature",
  "properties": {
    "iso:country":"DE",
    "sg:address":"Lindenbrunnenstr. 22",
    "sg:city":"Achern",
    "sg:phone":"+49 7841/5359",
    "sg:postcode":"77855",
    "sg:province":"Baden-W\u00fcrttemberg",
    "wof:name":"Otto Meister",
    "wof:placetype":"venue"
},
  "geometry": {"coordinates":[8.0801038742,48.6324005127],"type":"Point"}
}