{
  "type": "Feature",
  "properties": {
    "iso:country":"DE",
    "sg:address":"Ahornweg 7",
    "sg:city":"Meschede",
    "sg:phone":"+49 291/6396",
    "sg:postcode":"59872",
    "sg:province":"Nordrhein-Westfalen",
    "wof:name":"Heinz K\u00fcckelmann Ingenieur",
    "wof:placetype":"venue"
},
  "geometry": {"coordinates":[8.2900571823,51.3592796326],"type":"Point"}
}