{
  "type": "Feature",
  "properties": {
    "iso:country":"DE",
    "sg:address":"Mittelstr. 1",
    "sg:city":"Nettetal",
    "sg:phone":"+49 2153/3795",
    "sg:postcode":"41334",
    "sg:province":"Nordrhein-Westfalen",
    "wof:name":"Kurt Mainz",
    "wof:placetype":"venue"
},
  "geometry": {"coordinates":[6.2767119408,51.3130187988],"type":"Point"}
}