{
  "type": "Feature",
  "properties": {
    "iso:country":"DE",
    "sg:address":"Berliner Str. 13",
    "sg:city":"Beelitz",
    "sg:phone":"+49 33204/2821",
    "sg:postcode":"14547",
    "sg:province":"Brandenburg",
    "wof:name":"Reinicke",
    "wof:placetype":"venue"
},
  "geometry": {"coordinates":[12.9785251617,52.234462738],"type":"Point"}
}