{
  "type": "Feature",
  "properties": {
    "iso:country":"DE",
    "sg:address":"Josefstr. 1",
    "sg:city":"K\u00f6ln",
    "sg:phone":"+49 2203/52120",
    "sg:postcode":"51143",
    "sg:province":"Nordrhein-Westfalen",
    "wof:name":"Happy Snacks Diamanto Megas Und Aliki Pappas",
    "wof:placetype":"venue"
},
  "geometry": {"coordinates":[7.0573749542,50.8838806152],"type":"Point"}
}