{
  "type": "Feature",
  "properties": {
    "iso:country":"DE",
    "sg:address":"Brunsb\u00fctteler Damm 334a",
    "sg:city":"Berlin",
    "sg:phone":"+49 30/3662898",
    "sg:postcode":"13591",
    "sg:province":"Berlin",
    "wof:name":"Traditionsbus Gmbh",
    "wof:placetype":"venue"
},
  "geometry": {"coordinates":[13.1462202072,52.5335769653],"type":"Point"}
}