{
  "type": "Feature",
  "properties": {
    "iso:country":"DE",
    "sg:address":"Im Kellerfeld 39a",
    "sg:city":"Blieskastel",
    "sg:phone":"+49 6842/7847",
    "sg:postcode":"66440",
    "sg:province":"Saarland",
    "wof:name":"G. Klein",
    "wof:placetype":"venue"
},
  "geometry": {"coordinates":[7.206066,49.247692],"type":"Point"}
}