{
  "type": "Feature",
  "properties": {
    "iso:country":"DE",
    "sg:address":"Lossaustr. 6",
    "sg:city":"Coburg",
    "sg:phone":"+49 9561/772395",
    "sg:postcode":"96450",
    "sg:province":"Bayern",
    "wof:name":"Deutsche Bahn Ag",
    "wof:placetype":"venue"
},
  "geometry": {"coordinates":[10.9583215714,50.2623176575],"type":"Point"}
}