{
  "type": "Feature",
  "properties": {
    "iso:country":"DE",
    "sg:address":"Ostenstr. 18",
    "sg:city":"Ennigerloh",
    "sg:phone":"+49 2587/1059",
    "sg:postcode":"59320",
    "sg:province":"Nordrhein-Westfalen",
    "wof:name":"I. Eidhoff",
    "wof:placetype":"venue"
},
  "geometry": {"coordinates":[8.0435180664,51.8807106018],"type":"Point"}
}