{
  "type": "Feature",
  "properties": {
    "iso:country":"DE",
    "sg:address":"W\u00fcrzburger Str. 12",
    "sg:city":"Rothenburg",
    "sg:phone":"+49 9861/6745",
    "sg:postcode":"91541",
    "sg:province":"Bayern",
    "wof:name":"M\u00f6bel-k\u00f6lblin Gmbh",
    "wof:placetype":"venue"
},
  "geometry": {"coordinates":[10.185741,49.381626],"type":"Point"}
}