{
  "type": "Feature",
  "properties": {
    "iso:country":"DE",
    "sg:address":"Seebacher Stra\u00dfe 20",
    "sg:city":"Bad D\u00fcrkheim",
    "sg:phone":"+49 6322",
    "sg:postcode":"67098",
    "sg:province":"Rheinland-Pfalz",
    "wof:name":"Slashing Twilight",
    "wof:placetype":"venue"
},
  "geometry": {"coordinates":[8.168993,49.45517],"type":"Point"}
}