{
  "type": "Feature",
  "properties": {
    "iso:country":"DE",
    "sg:address":"Laubengang 10",
    "sg:city":"Wuppertal",
    "sg:phone":"+49 202/252310",
    "sg:postcode":"42279",
    "sg:province":"Nordrhein-Westfalen",
    "wof:name":"Avokal Gmbh",
    "wof:placetype":"venue"
},
  "geometry": {"coordinates":[7.210365,51.297302],"type":"Point"}
}