{
  "type": "Feature",
  "properties": {
    "iso:country":"DE",
    "sg:address":"Hauptstr. 22",
    "sg:city":"Kandern",
    "sg:phone":"+49 7626/246",
    "sg:postcode":"79400",
    "sg:province":"Baden-W\u00fcrttemberg",
    "wof:name":"Albert Schneider Inh. Helene Schneider",
    "wof:placetype":"venue"
},
  "geometry": {"coordinates":[7.6615462303,47.7142906189],"type":"Point"}
}