{
  "type": "Feature",
  "properties": {
    "iso:country":"DE",
    "sg:address":"Lange Wand 14",
    "sg:city":"Delmenhorst",
    "sg:phone":"+49 4221/809330",
    "sg:postcode":"27753",
    "sg:province":"Niedersachsen",
    "wof:name":"Westrich Gmbh",
    "wof:placetype":"venue"
},
  "geometry": {"coordinates":[8.587365,53.037594],"type":"Point"}
}