{
  "type": "Feature",
  "properties": {
    "iso:country":"DE",
    "sg:address":"Pensiner Weg 63",
    "sg:city":"Demmin",
    "sg:phone":"+49 3998/28350",
    "sg:postcode":"17109",
    "sg:province":"Mecklenburg-Vorpommern",
    "wof:name":"Wohnungsbau- Und Verwaltungsges. Demmin Mbh",
    "wof:placetype":"venue"
},
  "geometry": {"coordinates":[13.0483865738,53.9067764282],"type":"Point"}
}