{
  "type": "Feature",
  "properties": {
    "iso:country":"DE",
    "sg:address":"Dieselstr. 18",
    "sg:city":"Hiddenhausen",
    "sg:postcode":"32120",
    "sg:province":"Nordrhein-Westfalen",
    "wof:name":"Feld & Guszausky Beteiligungs Gmbh",
    "wof:placetype":"venue"
},
  "geometry": {"coordinates":[8.600959,52.167732],"type":"Point"}
}