{
  "type": "Feature",
  "properties": {
    "iso:country":"DE",
    "sg:address":"Engelsberg 6-8",
    "sg:city":"Bretten",
    "sg:phone":"+49 7252/2096",
    "sg:postcode":"75015",
    "sg:province":"Baden-W\u00fcrttemberg",
    "wof:name":"Landesbausparkasse Beratungsstelle",
    "wof:placetype":"venue"
},
  "geometry": {"coordinates":[8.706857,49.037693],"type":"Point"}
}