{
  "type": "Feature",
  "properties": {
    "iso:country":"DE",
    "sg:address":"Ringstr. 19",
    "sg:city":"Ro\u00dfdorf",
    "sg:phone":"+49 6154/800830",
    "sg:postcode":"64380",
    "sg:province":"Hessen",
    "wof:name":"Uwe Duchow Rechtsanwalt",
    "wof:placetype":"venue"
},
  "geometry": {"coordinates":[8.74974823,49.8593864441],"type":"Point"}
}