{
  "type": "Feature",
  "properties": {
    "iso:country":"DE",
    "sg:address":"Adolf-Ludwig-Ring 10a",
    "sg:city":"Pirmasens",
    "sg:phone":"+49 6331/21100",
    "sg:postcode":"66955",
    "sg:province":"Rheinland-Pfalz",
    "wof:name":"Hans Erwin Volberg Steuerberater",
    "wof:placetype":"venue"
},
  "geometry": {"coordinates":[7.6362252235,49.188747406],"type":"Point"}
}