{
  "type": "Feature",
  "properties": {
    "iso:country":"DE",
    "sg:address":"Zwickauer Str.",
    "sg:city":"G\u00f6\u00dfnitz",
    "sg:phone":"+49 34493/36513",
    "sg:postcode":"04639",
    "sg:province":"Th\u00fcringen",
    "wof:name":"Meyer",
    "wof:placetype":"venue"
},
  "geometry": {"coordinates":[12.430791,50.882668],"type":"Point"}
}