{
  "type": "Feature",
  "properties": {
    "iso:country":"DE",
    "sg:address":"Dorfstr. 7",
    "sg:city":"Naumburg",
    "sg:phone":"+49 3445/702206",
    "sg:postcode":"06618",
    "sg:province":"Sachsen-Anhalt",
    "wof:name":"G. S\u00f6ll",
    "wof:placetype":"venue"
},
  "geometry": {"coordinates":[11.790559,51.188236],"type":"Point"}
}