{
  "type": "Feature",
  "properties": {
    "iso:country":"DE",
    "sg:address":"Reichenstr. 1",
    "sg:city":"Gr\u00f6ningen",
    "sg:postcode":"39397",
    "sg:province":"Sachsen-Anhalt",
    "wof:name":"Gemeindeschwesterstation Gr\u00f6ningen",
    "wof:placetype":"venue"
},
  "geometry": {"coordinates":[11.218807,51.939751],"type":"Point"}
}