{
  "type": "Feature",
  "properties": {
    "iso:country":"DE",
    "sg:address":"Hindenburgstr. 12",
    "sg:city":"Bassum",
    "sg:phone":"+49 4241/3059",
    "sg:postcode":"27211",
    "sg:province":"Niedersachsen",
    "wof:name":"Heinrich Wessel",
    "wof:placetype":"venue"
},
  "geometry": {"coordinates":[8.720329,52.847378],"type":"Point"}
}