{
  "type": "Feature",
  "properties": {
    "iso:country":"DE",
    "sg:address":"Maurepasstr. 2 a",
    "sg:city":"Henstedt-Ulzburg",
    "sg:phone":"+49 4193/94818",
    "sg:postcode":"24558",
    "sg:province":"Schleswig-Holstein",
    "wof:name":"Marks",
    "wof:placetype":"venue"
},
  "geometry": {"coordinates":[9.981422,53.790287],"type":"Point"}
}