{
  "type": "Feature",
  "properties": {
    "iso:country":"DE",
    "sg:address":"Zur Alten M\u00fchle 1",
    "sg:city":"Stockach",
    "sg:postcode":"78333",
    "sg:province":"Baden-W\u00fcrttemberg",
    "wof:name":"R. Hans",
    "wof:placetype":"venue"
},
  "geometry": {"coordinates":[8.9656047821,47.8152122498],"type":"Point"}
}