{
  "type": "Feature",
  "properties": {
    "iso:country":"DE",
    "sg:address":"Drei\u00dfentalstr. 8",
    "sg:city":"Oberkochen",
    "sg:phone":"+49 7364/6472",
    "sg:postcode":"73447",
    "sg:province":"Baden-W\u00fcrttemberg",
    "wof:name":"Emil Vollmer",
    "wof:placetype":"venue"
},
  "geometry": {"coordinates":[10.103655,48.783344],"type":"Point"}
}