{
  "type": "Feature",
  "properties": {
    "iso:country":"DE",
    "sg:address":"Bahnhofstra\u00dfe 95",
    "sg:city":"Maintal",
    "sg:phone":"+49 6181",
    "sg:postcode":"63477",
    "sg:province":"Hessen",
    "wof:name":"Herzlich Willkommen Beim Reiseservice Maintal",
    "wof:placetype":"venue"
},
  "geometry": {"coordinates":[8.8361101151,50.142742157],"type":"Point"}
}