{
  "type": "Feature",
  "properties": {
    "iso:country":"DE",
    "sg:address":"Bullermannshof 19",
    "sg:city":"Moers",
    "sg:phone":"+49 2841/170781",
    "sg:postcode":"47441",
    "sg:province":"Nordrhein-Westfalen",
    "wof:name":"Dirtex Gmbh",
    "wof:placetype":"venue"
},
  "geometry": {"coordinates":[6.614781,51.46104],"type":"Point"}
}