{
  "type": "Feature",
  "properties": {
    "iso:country":"DE",
    "sg:address":"B\u00fcrst\u00e4dter Str. 51",
    "sg:city":"Lampertheim",
    "sg:phone":"+49 6206",
    "sg:postcode":"68623",
    "sg:province":"Hessen",
    "wof:name":"Vip Lampertheim",
    "wof:placetype":"venue"
},
  "geometry": {"coordinates":[8.4695386887,49.6007461548],"type":"Point"}
}