{
  "type": "Feature",
  "properties": {
    "iso:country":"DE",
    "sg:address":"Strobandtstr. 14",
    "sg:city":"Coesfeld",
    "sg:phone":"+49 2541/2996",
    "sg:postcode":"48653",
    "sg:province":"Nordrhein-Westfalen",
    "wof:name":"Hermann Koch",
    "wof:placetype":"venue"
},
  "geometry": {"coordinates":[7.174738,51.938927],"type":"Point"}
}