{
  "type": "Feature",
  "properties": {
    "iso:country":"DE",
    "sg:address":"K\u00f6lner Str. 10 b",
    "sg:city":"Eschborn",
    "sg:postcode":"65760",
    "sg:province":"Hessen",
    "wof:name":"T & T Bauunternehmen Gmbh",
    "wof:placetype":"venue"
},
  "geometry": {"coordinates":[8.571466,50.131935],"type":"Point"}
}