{
  "type": "Feature",
  "properties": {
    "iso:country":"DE",
    "sg:address":"Am Manger 13",
    "sg:city":"Behrungen",
    "sg:phone":"+49 36944/54840",
    "sg:postcode":"98631",
    "sg:province":"Th\u00fcringen",
    "wof:name":"Zur Henne Gasthof",
    "wof:placetype":"venue"
},
  "geometry": {"coordinates":[10.4150075912,50.4097480774],"type":"Point"}
}