{
  "type": "Feature",
  "properties": {
    "iso:country":"DE",
    "sg:address":"Nagolder Str. 27",
    "sg:city":"Herrenberg",
    "sg:phone":"+49 7032/287924",
    "sg:postcode":"71083",
    "sg:province":"Baden-W\u00fcrttemberg",
    "wof:name":"Gfs Projektentwicklungs- Gesellschaft Mbh",
    "wof:placetype":"venue"
},
  "geometry": {"coordinates":[8.8614273071,48.5956916809],"type":"Point"}
}