{
  "type": "Feature",
  "properties": {
    "iso:country":"DE",
    "sg:address":"Rochlitzer Berg",
    "sg:city":"Rochlitz",
    "sg:phone":"+49 3737/40706",
    "sg:postcode":"09306",
    "sg:province":"Sachsen",
    "wof:name":"T\u00fcrmerhaus",
    "wof:placetype":"venue"
},
  "geometry": {"coordinates":[12.7702474594,51.0247879028],"type":"Point"}
}