{
  "type": "Feature",
  "properties": {
    "iso:country":"DE",
    "sg:address":"Friedrich-Engels-Str. 17",
    "sg:city":"K\u00fchren-Burkartshain",
    "sg:phone":"+49 34261/251",
    "sg:postcode":"04808",
    "sg:province":"Sachsen",
    "wof:name":"K. Tryius Ingenieur",
    "wof:placetype":"venue"
},
  "geometry": {"coordinates":[12.7918653488,51.3923568726],"type":"Point"}
}