{
  "type": "Feature",
  "properties": {
    "iso:country":"DE",
    "sg:address":"Klosterstr. 15",
    "sg:city":"Budenheim",
    "sg:phone":"+49 6139/2173",
    "sg:postcode":"55257",
    "sg:province":"Rheinland-Pfalz",
    "wof:name":"Eduard Hellmeister",
    "wof:placetype":"venue"
},
  "geometry": {"coordinates":[8.17208004,50.027507782],"type":"Point"}
}