{
  "type": "Feature",
  "properties": {
    "iso:country":"DE",
    "sg:address":"Oberlausitzer Stra\u00dfe",
    "sg:city":"Cunewalde",
    "sg:postcode":"02733",
    "sg:province":"Sachsen",
    "wof:name":"Haus -und Hobbybrauer Cunewalder Tal E.v.",
    "wof:placetype":"venue"
},
  "geometry": {"coordinates":[14.4752702713,51.0972595215],"type":"Point"}
}