{
  "type": "Feature",
  "properties": {
    "iso:country":"DE",
    "sg:address":"L\u00f6hner Str. 221",
    "sg:city":"Hiddenhausen",
    "sg:phone":"+49 5223/2952",
    "sg:postcode":"32120",
    "sg:province":"Nordrhein-Westfalen",
    "wof:name":"Heinrich Vollmer",
    "wof:placetype":"venue"
},
  "geometry": {"coordinates":[8.619349,52.165173],"type":"Point"}
}