{
  "type": "Feature",
  "properties": {
    "iso:country":"DE",
    "sg:city":"Bad Gandersheim",
    "sg:phone":"+49 5382/8303",
    "sg:postcode":"37581",
    "sg:province":"Niedersachsen",
    "wof:name":"Boutique Michelle",
    "wof:placetype":"venue"
},
  "geometry": {"coordinates":[10.024801,51.870716],"type":"Point"}
}