{
  "type": "Feature",
  "properties": {
    "iso:country":"DE",
    "sg:address":"Regensburger Str. 15",
    "sg:city":"Schwandorf",
    "sg:phone":"+49 9431/50151",
    "sg:postcode":"92421",
    "sg:province":"Bayern",
    "wof:name":"Franz S\u00f6llner",
    "wof:placetype":"venue"
},
  "geometry": {"coordinates":[12.1068134308,49.3213996887],"type":"Point"}
}