{
  "type": "Feature",
  "properties": {
    "iso:country":"DE",
    "sg:address":"Friedrichstr. 11",
    "sg:city":"Norderney",
    "sg:phone":"+49 4932/93860",
    "sg:postcode":"26548",
    "sg:province":"Niedersachsen",
    "wof:name":"Hotel Austernfischer",
    "wof:placetype":"venue"
},
  "geometry": {"coordinates":[7.1424322128,53.7080078125],"type":"Point"}
}