{
  "type": "Feature",
  "properties": {
    "iso:country":"DE",
    "sg:address":"Walpersdorfer Str. 33-39",
    "sg:city":"Schwabach",
    "sg:phone":"+49 9122/18060",
    "sg:postcode":"91126",
    "sg:province":"Bayern",
    "wof:name":"Schmidthammer Elektrokohle Gmbh",
    "wof:placetype":"venue"
},
  "geometry": {"coordinates":[11.0344581604,49.3217468262],"type":"Point"}
}