{
  "type": "Feature",
  "properties": {
    "iso:country":"DE",
    "sg:address":"Bismarckstr. 11",
    "sg:city":"Idar-Oberstein",
    "sg:phone":"+49 6781/360535",
    "sg:postcode":"55743",
    "sg:province":"Rheinland-Pfalz",
    "wof:name":"Mdk Medizinischer Dienst Der Krankenversicherung Rhld-pfalz",
    "wof:placetype":"venue"
},
  "geometry": {"coordinates":[7.3013339043,49.7212867737],"type":"Point"}
}