{
  "type": "Feature",
  "properties": {
    "iso:country":"DE",
    "sg:address":"Elisabethenstr. 44",
    "sg:city":"Ulm",
    "sg:phone":"+49 731/37541",
    "sg:postcode":"89077",
    "sg:province":"Baden-W\u00fcrttemberg",
    "wof:name":"Roeper Ingenieur",
    "wof:placetype":"venue"
},
  "geometry": {"coordinates":[9.975153923,48.3948783875],"type":"Point"}
}