{
  "type": "Feature",
  "properties": {
    "iso:country":"DE",
    "sg:address":"Klingelp\u00fctz 12 - 14",
    "sg:city":"K\u00f6ln",
    "sg:phone":"+49 221/1652319",
    "sg:postcode":"50670",
    "sg:province":"Nordrhein-Westfalen",
    "wof:name":"S\u00fc\u00dfstoff-vertriebs-gmbh",
    "wof:placetype":"venue"
},
  "geometry": {"coordinates":[6.948193,50.943691],"type":"Point"}
}