{
  "type": "Feature",
  "properties": {
    "iso:country":"DE",
    "sg:address":"Feldstr. 6",
    "sg:city":"Vechelde",
    "sg:phone":"+49 5302/1011",
    "sg:postcode":"38159",
    "sg:province":"Niedersachsen",
    "wof:name":"Siegfried Schr\u00f6ter",
    "wof:placetype":"venue"
},
  "geometry": {"coordinates":[10.3611383438,52.260055542],"type":"Point"}
}