{
  "type": "Feature",
  "properties": {
    "iso:country":"DE",
    "sg:address":"Marktplatz 1",
    "sg:city":"Siegburg",
    "sg:phone":"+49 2241/61401",
    "sg:postcode":"53721",
    "sg:province":"Nordrhein-Westfalen",
    "wof:name":"Fritz Joachim Piehl Gmbh",
    "wof:placetype":"venue"
},
  "geometry": {"coordinates":[7.205853,50.796406],"type":"Point"}
}