{
  "type": "Feature",
  "properties": {
    "iso:country":"DE",
    "sg:address":"Pinneberger Chaussee 92",
    "sg:city":"Moorrege",
    "sg:phone":"+49 4941/2282251",
    "sg:postcode":"25436",
    "sg:province":"Schleswig-Holstein",
    "wof:name":"Herbert Halerm\u00d6ller Gmbh",
    "wof:placetype":"venue"
},
  "geometry": {"coordinates":[9.6862106323,53.6666755676],"type":"Point"}
}