{
  "type": "Feature",
  "properties": {
    "iso:country":"DE",
    "sg:address":"Bahnhofplatz 1",
    "sg:city":"Erlangen",
    "sg:phone":"+49 9131/22569",
    "sg:postcode":"91054",
    "sg:province":"Bayern",
    "wof:name":"Bahnhofsbuchhandlung Erna Werner",
    "wof:placetype":"venue"
},
  "geometry": {"coordinates":[11.0022554398,49.5959396362],"type":"Point"}
}