{
  "type": "Feature",
  "properties": {
    "iso:country":"DE",
    "sg:address":"Tylestr. 1",
    "sg:city":"Frankenberg",
    "sg:phone":"+49 6451/713634",
    "sg:postcode":"35066",
    "sg:province":"Hessen",
    "wof:name":"Gebr\u00fcder M\u00fcller Bau Gmbh",
    "wof:placetype":"venue"
},
  "geometry": {"coordinates":[8.769412,51.06847],"type":"Point"}
}