{
  "type": "Feature",
  "properties": {
    "iso:country":"DE",
    "sg:address":"Goldhammer Str. 13",
    "sg:city":"Bochum",
    "sg:phone":"+49 234/14384",
    "sg:postcode":"44793",
    "sg:province":"Nordrhein-Westfalen",
    "wof:name":"Johann J\u00e4ger",
    "wof:placetype":"venue"
},
  "geometry": {"coordinates":[7.188774,51.477119],"type":"Point"}
}