{
  "type": "Feature",
  "properties": {
    "iso:country":"DE",
    "sg:address":"Beerenweg 3",
    "sg:city":"Grafenau",
    "sg:phone":"+49 8552/895",
    "sg:postcode":"94481",
    "sg:province":"Bayern",
    "wof:name":"Pension Johann U. Luise Wolf",
    "wof:placetype":"venue"
},
  "geometry": {"coordinates":[13.3678779602,48.8507766724],"type":"Point"}
}