{
  "type": "Feature",
  "properties": {
    "iso:country":"DE",
    "sg:address":"Schubertstr. 11",
    "sg:city":"Dortmund",
    "sg:phone":"+49 231/833472",
    "sg:postcode":"44145",
    "sg:province":"Nordrhein-Westfalen",
    "wof:name":"Karl Hoffmann",
    "wof:placetype":"venue"
},
  "geometry": {"coordinates":[7.461398,51.5271],"type":"Point"}
}