{
  "type": "Feature",
  "properties": {
    "iso:country":"DE",
    "sg:address":"Kleiststr. 39",
    "sg:city":"Schildow",
    "sg:phone":"+49 33056/216",
    "sg:postcode":"16552",
    "sg:province":"Brandenburg",
    "wof:name":"Vbs Verband Der Bausachverst\u00e4ndigen E. V.",
    "wof:placetype":"venue"
},
  "geometry": {"coordinates":[13.3910799026,52.6441497803],"type":"Point"}
}