{
  "type": "Feature",
  "properties": {
    "iso:country":"DE",
    "sg:address":"Z\u00f6rbiger Str.",
    "sg:city":"Bitterfeld",
    "sg:phone":"+49 3493/7930",
    "sg:postcode":"06749",
    "sg:province":"Sachsen-Anhalt",
    "wof:name":"Sina Fahrzeug- Und F\u00f6rdertechnik Gmbh",
    "wof:placetype":"venue"
},
  "geometry": {"coordinates":[12.2975654602,51.6237792969],"type":"Point"}
}