{
  "type": "Feature",
  "properties": {
    "iso:country":"DE",
    "sg:address":"P\u00f6ppinghauser Str. 60",
    "sg:city":"Herne",
    "sg:phone":"+49 2323/981016",
    "sg:postcode":"44628",
    "sg:province":"Nordrhein-Westfalen",
    "wof:name":"Atlantis Videotheken Gmbh & Co 5 Beteiligungs Kg Poeppinghauser Str",
    "wof:placetype":"venue"
},
  "geometry": {"coordinates":[7.2343130112,51.5649261475],"type":"Point"}
}