{
  "type": "Feature",
  "properties": {
    "iso:country":"DE",
    "sg:address":"Bahnhofstr 9",
    "sg:city":"Sigmaringen",
    "sg:phone":"+49 7571/7250",
    "sg:postcode":"72488",
    "sg:province":"Baden-W\u00fcrttemberg",
    "wof:name":"Schw\u00f6rer Haus Gmbh & Co Kg",
    "wof:placetype":"venue"
},
  "geometry": {"coordinates":[9.2245283127,48.0857543945],"type":"Point"}
}