{
  "type": "Feature",
  "properties": {
    "iso:country":"DE",
    "sg:address":"Kaiserring 7",
    "sg:city":"Wesel",
    "sg:phone":"+49 281/28109",
    "sg:postcode":"46483",
    "sg:province":"Nordrhein-Westfalen",
    "wof:name":"F Und F Dv-consulting Gmbh",
    "wof:placetype":"venue"
},
  "geometry": {"coordinates":[6.6248898506,51.6569671631],"type":"Point"}
}