{
  "type": "Feature",
  "properties": {
    "iso:country":"DE",
    "sg:address":"St.-Martin-Str. 27",
    "sg:city":"Garmisch-Partenkirchen",
    "sg:phone":"+49 8821/78977",
    "sg:postcode":"82467",
    "sg:province":"Bayern",
    "wof:name":"Reinhold Kirsch",
    "wof:placetype":"venue"
},
  "geometry": {"coordinates":[11.0891389847,47.4899253845],"type":"Point"}
}