{
  "type": "Feature",
  "properties": {
    "iso:country":"DE",
    "sg:address":"Ketteldorf 24",
    "sg:city":"Heilsbronn",
    "sg:phone":"+49 9872/2694",
    "sg:postcode":"91560",
    "sg:province":"Bayern",
    "wof:name":"Horst Buchholz",
    "wof:placetype":"venue"
},
  "geometry": {"coordinates":[10.78118,49.340656],"type":"Point"}
}