{
  "type": "Feature",
  "properties": {
    "iso:country":"DE",
    "sg:address":"Gottlieb-Daimler-Str. 13",
    "sg:city":"Twistringen",
    "sg:phone":"+49 4942/433011",
    "sg:postcode":"27239",
    "sg:province":"Niedersachsen",
    "wof:name":"Eiervermarktung Wiesengold Landei Gmbh & Co. Kg",
    "wof:placetype":"venue"
},
  "geometry": {"coordinates":[8.637984,52.789261],"type":"Point"}
}