{
  "type": "Feature",
  "properties": {
    "iso:country":"DE",
    "sg:address":"Bahnhofstr. 68 a",
    "sg:city":"Linkenheim-Hochstetten",
    "sg:phone":"+49 7247/6344",
    "sg:postcode":"76351",
    "sg:province":"Baden-W\u00fcrttemberg",
    "wof:name":"Robert Ochs",
    "wof:placetype":"venue"
},
  "geometry": {"coordinates":[8.4172239304,49.122959137],"type":"Point"}
}