{
  "type": "Feature",
  "properties": {
    "iso:country":"DE",
    "sg:address":"Kr\u00f6peliner Str. 1 c",
    "sg:city":"Bad Doberan",
    "sg:phone":"+49 38203/14967",
    "sg:postcode":"18209",
    "sg:province":"Mecklenburg-Vorpommern",
    "wof:name":"Karin Br\u00fcmmer Rechtsanw\u00e4ltin",
    "wof:placetype":"venue"
},
  "geometry": {"coordinates":[11.8999500275,54.1019630432],"type":"Point"}
}