{
  "type": "Feature",
  "properties": {
    "iso:country":"DE",
    "sg:address":"Taunusstr. 3",
    "sg:city":"Mainz",
    "sg:phone":"+49 6131/604427",
    "sg:postcode":"55118",
    "sg:province":"Rheinland-Pfalz",
    "wof:name":"Joachim Heberer Rechtsanwalt",
    "wof:placetype":"venue"
},
  "geometry": {"coordinates":[8.2684087753,50.0098114014],"type":"Point"}
}