{
  "type": "Feature",
  "properties": {
    "iso:country":"DE",
    "sg:address":"Daimlerstr. 22",
    "sg:city":"Renningen",
    "sg:phone":"+49 7159/18714",
    "sg:postcode":"71272",
    "sg:province":"Baden-W\u00fcrttemberg",
    "wof:name":"Gastst\u00e4tte Freibadkiosk",
    "wof:placetype":"venue"
},
  "geometry": {"coordinates":[8.9308996201,48.7741088867],"type":"Point"}
}