{
  "type": "Feature",
  "properties": {
    "iso:country":"DE",
    "sg:address":"Leipziger Str. 26",
    "sg:city":"Delitzsch",
    "sg:phone":"+49 34202/55345",
    "sg:postcode":"04509",
    "sg:province":"Sachsen",
    "wof:name":"Afi Innovations Forum Gmbh",
    "wof:placetype":"venue"
},
  "geometry": {"coordinates":[12.3353643417,51.516708374],"type":"Point"}
}