{
  "type": "Feature",
  "properties": {
    "iso:country":"DE",
    "sg:address":"Schulstr. 5",
    "sg:city":"Deinstedt",
    "sg:phone":"+49 4284/8529",
    "sg:postcode":"27446",
    "sg:province":"Niedersachsen",
    "wof:name":"Nord-contor Handels- Und Dienstleitungs Gmbh",
    "wof:placetype":"venue"
},
  "geometry": {"coordinates":[9.2245788574,53.4069671631],"type":"Point"}
}