{
  "type": "Feature",
  "properties": {
    "iso:country":"DE",
    "sg:address":"Schopenhauerstr. 31",
    "sg:city":"Dreieich",
    "sg:phone":"+49 6103/61761",
    "sg:postcode":"63303",
    "sg:province":"Hessen",
    "wof:name":"Detlef W. Troglauer",
    "wof:placetype":"venue"
},
  "geometry": {"coordinates":[8.688776,50.026749],"type":"Point"}
}