{
  "type": "Feature",
  "properties": {
    "iso:country":"DE",
    "sg:address":"Alte Bahnhofstr. 131",
    "sg:city":"Bochum",
    "sg:phone":"+49 234/296597",
    "sg:postcode":"44892",
    "sg:province":"Nordrhein-Westfalen",
    "wof:name":"China Restaurant Lotus",
    "wof:placetype":"venue"
},
  "geometry": {"coordinates":[7.3118309975,51.473323822],"type":"Point"}
}