{
  "type": "Feature",
  "properties": {
    "iso:country":"DE",
    "sg:address":"Zollstr. 2",
    "sg:city":"S\u00f6hlde",
    "sg:phone":"+49 5129/1340",
    "sg:postcode":"31185",
    "sg:province":"Niedersachsen",
    "wof:name":"Hans-herwig Plumeyer",
    "wof:placetype":"venue"
},
  "geometry": {"coordinates":[10.231255,52.186142],"type":"Point"}
}