{
  "type": "Feature",
  "properties": {
    "iso:country":"DE",
    "sg:address":"Thiergartner Weg 6",
    "sg:city":"Plauen",
    "sg:phone":"+49 3741/229150",
    "sg:postcode":"08527",
    "sg:province":"Sachsen",
    "wof:name":"M\u00f6beltischlerei Sch\u00f6nherr",
    "wof:placetype":"venue"
},
  "geometry": {"coordinates":[12.128972,50.484619],"type":"Point"}
}