{
  "type": "Feature",
  "properties": {
    "iso:country":"DE",
    "sg:address":"Gemeinreuth 1",
    "sg:city":"Schwarzenbach a Wald",
    "sg:phone":"+49 9289/97210",
    "sg:postcode":"95131",
    "sg:province":"Bayern",
    "wof:name":"Pro-forst Consult Horst Schuberth E. K.",
    "wof:placetype":"venue"
},
  "geometry": {"coordinates":[11.573079,50.282833],"type":"Point"}
}