{
  "type": "Feature",
  "properties": {
    "iso:country":"DE",
    "sg:address":"Mainkai 35",
    "sg:city":"Frankfurt",
    "sg:postcode":"60311",
    "sg:province":"Hessen",
    "wof:name":"Astor Immobilien Gmbh",
    "wof:placetype":"venue"
},
  "geometry": {"coordinates":[8.681955,50.109177],"type":"Point"}
}