{
  "type": "Feature",
  "properties": {
    "iso:country":"DE",
    "sg:address":"F\u00f6rsterlingstr. 3",
    "sg:city":"Dresden",
    "sg:postcode":"01259",
    "sg:province":"Sachsen",
    "wof:name":"Wenzel & Glass Gmbh",
    "wof:placetype":"venue"
},
  "geometry": {"coordinates":[13.837837,51.005371],"type":"Point"}
}