{
  "type": "Feature",
  "properties": {
    "iso:country":"DE",
    "sg:address":"Gl\u00f6rstr. 1",
    "sg:city":"Schalksm\u00fchle",
    "sg:phone":"+49 2355/90910",
    "sg:postcode":"58579",
    "sg:province":"Nordrhein-Westfalen",
    "wof:name":"Axel H\u00fcttebr\u00e4ucker Steuerberater",
    "wof:placetype":"venue"
},
  "geometry": {"coordinates":[7.5042462349,51.2515563965],"type":"Point"}
}