{
  "type": "Feature",
  "properties": {
    "iso:country":"DE",
    "sg:address":"Krefelder Str. 222",
    "sg:city":"Willich",
    "sg:phone":"+49 2154/41115",
    "sg:postcode":"47877",
    "sg:province":"Nordrhein-Westfalen",
    "wof:name":"G. Kamphof",
    "wof:placetype":"venue"
},
  "geometry": {"coordinates":[6.554995,51.278175],"type":"Point"}
}