{
  "type": "Feature",
  "properties": {
    "iso:country":"DE",
    "sg:address":"Am K\u00f6llersgeh\u00e4u 50",
    "sg:city":"Zella-Mehlis",
    "sg:phone":"+49 4936/824550",
    "sg:postcode":"98544",
    "sg:province":"Th\u00fcringen",
    "wof:name":"Egs Elektro- Und Hausgeraetewerk Suhl Gmbh",
    "wof:placetype":"venue"
},
  "geometry": {"coordinates":[10.683807,50.644772],"type":"Point"}
}