{
  "type": "Feature",
  "properties": {
    "iso:country":"DE",
    "sg:address":"Spyckstr. 68",
    "sg:city":"Kleve",
    "sg:phone":"+49 2821/7160",
    "sg:postcode":"47533",
    "sg:province":"Nordrhein-Westfalen",
    "wof:name":"Franziskus-haus",
    "wof:placetype":"venue"
},
  "geometry": {"coordinates":[6.134801,51.795662],"type":"Point"}
}