{
  "type": "Feature",
  "properties": {
    "iso:country":"DE",
    "sg:address":"Waizenhof 12",
    "sg:city":"Aichstetten",
    "sg:phone":"+49 7565/91114",
    "sg:postcode":"88317",
    "sg:province":"Baden-W\u00fcrttemberg",
    "wof:name":"Euro Rastpark",
    "wof:placetype":"venue"
},
  "geometry": {"coordinates":[10.0400953293,47.8808250427],"type":"Point"}
}