{
  "type": "Feature",
  "properties": {
    "iso:country":"DE",
    "sg:address":"Adolf-Kolping-Str. 17",
    "sg:city":"M\u00fchldorf",
    "sg:phone":"+49 8631/2688",
    "sg:postcode":"84453",
    "sg:province":"Bayern",
    "wof:name":"Esv-sportgastst\u00e4tte",
    "wof:placetype":"venue"
},
  "geometry": {"coordinates":[12.5138731003,48.250667572],"type":"Point"}
}