{
  "type": "Feature",
  "properties": {
    "iso:country":"DE",
    "sg:address":"H\u00f6lkeringer Str. 20",
    "sg:city":"Pentling",
    "sg:phone":"+49 941/91070",
    "sg:postcode":"93080",
    "sg:province":"Bayern",
    "wof:name":"Real",
    "wof:placetype":"venue"
},
  "geometry": {"coordinates":[12.0642414093,48.9796524048],"type":"Point"}
}