{
  "type": "Feature",
  "properties": {
    "iso:country":"DE",
    "sg:address":"Uhlenweg 9",
    "sg:city":"Berlin",
    "sg:phone":"+49 30/9497191",
    "sg:postcode":"13125",
    "sg:province":"Berlin",
    "wof:name":"J. Stanulla Gmbh",
    "wof:placetype":"venue"
},
  "geometry": {"coordinates":[13.4997653961,52.643032074],"type":"Point"}
}