{
  "type": "Feature",
  "properties": {
    "iso:country":"DE",
    "sg:address":"Kalkweiler Steige 29",
    "sg:city":"Rottenburg",
    "sg:phone":"+49 7472/1017",
    "sg:postcode":"72108",
    "sg:province":"Baden-W\u00fcrttemberg",
    "wof:name":"Albert B\u00f6hringer Ingenieur",
    "wof:placetype":"venue"
},
  "geometry": {"coordinates":[8.9261760712,48.4738693237],"type":"Point"}
}