{
  "type": "Feature",
  "properties": {
    "iso:country":"DE",
    "sg:address":"Kriensh\u00fctte 108",
    "sg:city":"Krefeld",
    "sg:phone":"+49 2151/473387",
    "sg:postcode":"47802",
    "sg:province":"Nordrhein-Westfalen",
    "wof:name":"Josef Kreifels",
    "wof:placetype":"venue"
},
  "geometry": {"coordinates":[6.613484,51.385216],"type":"Point"}
}