{
  "type": "Feature",
  "properties": {
    "iso:country":"DE",
    "sg:address":"Sommerstr. 9",
    "sg:city":"Falkenberg",
    "sg:phone":"+49 8727/270",
    "sg:postcode":"84326",
    "sg:province":"Bayern",
    "wof:name":"Franz Schmeller",
    "wof:placetype":"venue"
},
  "geometry": {"coordinates":[12.731933,48.462357],"type":"Point"}
}