{
  "type": "Feature",
  "properties": {
    "iso:country":"DE",
    "sg:address":"Haydnstr. 8",
    "sg:city":"Nidderau",
    "sg:phone":"+49 6187/28460",
    "sg:postcode":"61130",
    "sg:province":"Hessen",
    "wof:name":"C. Zenker Immobilienmakler",
    "wof:placetype":"venue"
},
  "geometry": {"coordinates":[8.8641939163,50.2294387817],"type":"Point"}
}