{
  "type": "Feature",
  "properties": {
    "iso:country":"DE",
    "sg:address":"M\u00fcllenhoffweg 60",
    "sg:city":"Hamburg",
    "sg:phone":"+49 40/828551",
    "sg:postcode":"22607",
    "sg:province":"Hamburg",
    "wof:name":"A. Und M. Helwig Restauratoren",
    "wof:placetype":"venue"
},
  "geometry": {"coordinates":[9.8707313538,53.5616493225],"type":"Point"}
}