{
  "type": "Feature",
  "properties": {
    "iso:country":"DE",
    "sg:address":"Hofer Str. 45",
    "sg:city":"Chemnitz",
    "sg:phone":"+49 371/4010286",
    "sg:postcode":"09130",
    "sg:province":"Sachsen",
    "wof:name":"Ursula Trommler",
    "wof:placetype":"venue"
},
  "geometry": {"coordinates":[12.9479875565,50.8386993408],"type":"Point"}
}