{
  "type": "Feature",
  "properties": {
    "iso:country":"DE",
    "sg:address":"Am Bahnhof",
    "sg:city":"Rentwertshausen",
    "sg:phone":"+49 36944/225",
    "sg:postcode":"98631",
    "sg:province":"Th\u00fcringen",
    "wof:name":"Raiffeisenbank Obere\u00dffeld/r\u00f6mhild, E. G.",
    "wof:placetype":"venue"
},
  "geometry": {"coordinates":[10.437912,50.45557],"type":"Point"}
}