{
  "type": "Feature",
  "properties": {
    "iso:country":"DE",
    "sg:address":"Robert-Sterling-Rg. 1",
    "sg:city":"Kraihling",
    "sg:phone":"+49 89/893360",
    "sg:postcode":"82152",
    "sg:province":"Bayern",
    "wof:name":"Eos Gmbh",
    "wof:placetype":"venue"
},
  "geometry": {"coordinates":[11.3573169708,48.0930519104],"type":"Point"}
}