{
  "type": "Feature",
  "properties": {
    "iso:country":"DE",
    "sg:address":"M\u00fcnchner-Kindl-Weg 50",
    "sg:city":"M\u00fcnchen",
    "sg:phone":"+49 89/6908678",
    "sg:postcode":"81547",
    "sg:province":"Bayern",
    "wof:name":"Hubert Wohllaib Ingenieur",
    "wof:placetype":"venue"
},
  "geometry": {"coordinates":[11.5799713135,48.0919685364],"type":"Point"}
}