{
  "type": "Feature",
  "properties": {
    "iso:country":"DE",
    "sg:address":"L\u00f6hrstr. 13",
    "sg:city":"Haiger",
    "sg:phone":"+49 2773/913366",
    "sg:postcode":"35708",
    "sg:province":"Hessen",
    "wof:name":"Pizzeria Il Carpaccio",
    "wof:placetype":"venue"
},
  "geometry": {"coordinates":[8.2066917419,50.7417259216],"type":"Point"}
}