{
  "type": "Feature",
  "properties": {
    "iso:country":"DE",
    "sg:address":"Spitalweg 11",
    "sg:city":"Calw",
    "sg:phone":"+49 7053/8614",
    "sg:postcode":"75365",
    "sg:province":"Baden-W\u00fcrttemberg",
    "wof:name":"R. Und A. R\u00fccker",
    "wof:placetype":"venue"
},
  "geometry": {"coordinates":[8.767225,48.693405],"type":"Point"}
}