{
  "type": "Feature",
  "properties": {
    "iso:country":"DE",
    "sg:address":"Weidendamm 41",
    "sg:city":"Hannover",
    "sg:phone":"+49 511",
    "sg:postcode":"30167",
    "sg:province":"Niedersachsen",
    "wof:name":"Tms Tischtennis",
    "wof:placetype":"venue"
},
  "geometry": {"coordinates":[9.727365,52.387276],"type":"Point"}
}