{
  "type": "Feature",
  "properties": {
    "iso:country":"DE",
    "sg:address":"Flurstr. 6",
    "sg:city":"Schwindegg",
    "sg:phone":"+49 8082/94085",
    "sg:postcode":"84419",
    "sg:province":"Bayern",
    "wof:name":"Friese Gmbh",
    "wof:placetype":"venue"
},
  "geometry": {"coordinates":[12.257876,48.274197],"type":"Point"}
}