{
  "type": "Feature",
  "properties": {
    "iso:country":"DE",
    "sg:address":"Theodor-Storm-Str. 2",
    "sg:city":"Roitzsch",
    "sg:phone":"+49 34954/23000",
    "sg:postcode":"06809",
    "sg:province":"Sachsen-Anhalt",
    "wof:name":"Klaus Drosd Rechtsanwalt",
    "wof:placetype":"venue"
},
  "geometry": {"coordinates":[12.2701177597,51.5776252747],"type":"Point"}
}