{
  "type": "Feature",
  "properties": {
    "iso:country":"DE",
    "sg:address":"Drescherweg 1",
    "sg:city":"Schmatzfeld",
    "sg:phone":"+49 39451/362",
    "sg:postcode":"38855",
    "sg:province":"Sachsen-Anhalt",
    "wof:name":"Agrargenossenschaft Bundschuh Schmatzfeld Eg",
    "wof:placetype":"venue"
},
  "geometry": {"coordinates":[10.767307,51.890865],"type":"Point"}
}