{
  "type": "Feature",
  "properties": {
    "iso:country":"DE",
    "sg:address":"Gartenstr. 3a",
    "sg:city":"Leuterod",
    "sg:phone":"+49 2602/60015",
    "sg:postcode":"56244",
    "sg:province":"Rheinland-Pfalz",
    "wof:name":"Ignatz Mondorf & Sohn Inh. Peter Mondorf E. K.",
    "wof:placetype":"venue"
},
  "geometry": {"coordinates":[7.819519,50.491936],"type":"Point"}
}