{
  "type": "Feature",
  "properties": {
    "iso:country":"DE",
    "sg:address":"Eyssenechstrasse 19",
    "sg:city":"Frankfurt",
    "sg:phone":"+49 69/9596980",
    "sg:postcode":"60322",
    "sg:province":"Hessen",
    "wof:name":"Wolf",
    "wof:placetype":"venue"
},
  "geometry": {"coordinates":[8.675966,50.128365],"type":"Point"}
}