{
  "type": "Feature",
  "properties": {
    "iso:country":"DE",
    "sg:address":"M\u00f6wenstr. 109",
    "sg:city":"Wilhelmshaven",
    "sg:phone":"+49 4421/52017",
    "sg:postcode":"26388",
    "sg:province":"Niedersachsen",
    "wof:name":"Peter Klug",
    "wof:placetype":"venue"
},
  "geometry": {"coordinates":[8.100271225,53.5807571411],"type":"Point"}
}