{
  "type": "Feature",
  "properties": {
    "iso:country":"DE",
    "sg:address":"Kriegkstr. 62",
    "sg:city":"Frankfurt",
    "sg:postcode":"60326",
    "sg:province":"Hessen",
    "wof:name":"Die Einhundert - Gesellschaft F\u00fcr Verm\u00f6gensverwaltung Mbh",
    "wof:placetype":"venue"
},
  "geometry": {"coordinates":[8.6395196915,50.1053886414],"type":"Point"}
}