{
  "type": "Feature",
  "properties": {
    "iso:country":"DE",
    "sg:address":"Veilchenstr. 3",
    "sg:city":"Steinhagen",
    "sg:phone":"+49 5204/2366",
    "sg:postcode":"33803",
    "sg:province":"Nordrhein-Westfalen",
    "wof:name":"Gastst\u00e4tte Bei Janni Inh. Ioannis Voliotis",
    "wof:placetype":"venue"
},
  "geometry": {"coordinates":[8.4356899261,52.0147438049],"type":"Point"}
}