{
  "type": "Feature",
  "properties": {
    "iso:country":"DE",
    "sg:address":"Mainstr. 25",
    "sg:city":"Bad K\u00f6nig",
    "sg:phone":"+49 6063/4304",
    "sg:postcode":"64732",
    "sg:province":"Hessen",
    "wof:name":"K.f.b. Bad K\u00f6niger Finanz- Vermittlungs- U. Beteiligungs-",
    "wof:placetype":"venue"
},
  "geometry": {"coordinates":[9.012649,49.743767],"type":"Point"}
}