{
  "type": "Feature",
  "properties": {
    "iso:country":"DE",
    "sg:address":"Nibelungenstr. 34",
    "sg:city":"Lindenfels",
    "sg:phone":"+49 6255/538",
    "sg:postcode":"64678",
    "sg:province":"Hessen",
    "wof:name":"Georg Arras",
    "wof:placetype":"venue"
},
  "geometry": {"coordinates":[8.780125618,49.686252594],"type":"Point"}
}