{
  "type": "Feature",
  "properties": {
    "iso:country":"DE",
    "sg:address":"Hauptstr. 31",
    "sg:city":"Geisingen",
    "sg:phone":"+49 7704/6808",
    "sg:postcode":"78187",
    "sg:province":"Baden-W\u00fcrttemberg",
    "wof:name":"I. Gualtieri",
    "wof:placetype":"venue"
},
  "geometry": {"coordinates":[8.64658,47.922813],"type":"Point"}
}