{
  "type": "Feature",
  "properties": {
    "iso:country":"DE",
    "sg:address":"Albert-Hahn-Str. 22",
    "sg:city":"Duisburg",
    "sg:phone":"+49 203/998290",
    "sg:postcode":"47269",
    "sg:province":"Nordrhein-Westfalen",
    "wof:name":"Jakob Rosskothen Gmbh",
    "wof:placetype":"venue"
},
  "geometry": {"coordinates":[6.775660038,51.3662567139],"type":"Point"}
}