{
  "type": "Feature",
  "properties": {
    "iso:country":"DE",
    "sg:address":"Delsterner Str. 5",
    "sg:city":"Hagen",
    "sg:postcode":"58091",
    "sg:province":"Nordrhein-Westfalen",
    "wof:name":"Team-software Programmierung Und",
    "wof:placetype":"venue"
},
  "geometry": {"coordinates":[7.5043778419,51.3444862366],"type":"Point"}
}