{
  "type": "Feature",
  "properties": {
    "iso:country":"DE",
    "sg:address":"Spieser Str. 17",
    "sg:city":"St. Ingbert",
    "sg:phone":"+49 6894/5510",
    "sg:postcode":"66386",
    "sg:province":"Saarland",
    "wof:name":"K. Munkes",
    "wof:placetype":"venue"
},
  "geometry": {"coordinates":[7.162614,49.284973],"type":"Point"}
}