{
  "type": "Feature",
  "properties": {
    "iso:country":"DE",
    "sg:address":"Herrenruhmweg 31",
    "sg:city":"Trittau",
    "sg:phone":"+49 4154/2966",
    "sg:postcode":"22946",
    "sg:province":"Schleswig-Holstein",
    "wof:name":"R\u00fcdiger Haag Lebensmittel",
    "wof:placetype":"venue"
},
  "geometry": {"coordinates":[10.4061174393,53.6049842834],"type":"Point"}
}