{
  "type": "Feature",
  "properties": {
    "iso:country":"DE",
    "sg:address":"Michaelisweg 15",
    "sg:city":"Schwerte",
    "sg:phone":"+49 2304",
    "sg:postcode":"58239",
    "sg:province":"Nordrhein-Westfalen",
    "wof:name":"Masters Wieschendahl",
    "wof:placetype":"venue"
},
  "geometry": {"coordinates":[7.591824,51.401649],"type":"Point"}
}