{
  "type": "Feature",
  "properties": {
    "iso:country":"DE",
    "sg:address":"Mariahilfer Str. 37",
    "sg:city":"Eisenberg",
    "sg:phone":"+49 8364/1511",
    "sg:postcode":"87637",
    "sg:province":"Bayern",
    "wof:name":"J. K\u00f6rbl Jun.",
    "wof:placetype":"venue"
},
  "geometry": {"coordinates":[10.610044,47.610172],"type":"Point"}
}