{
  "type": "Feature",
  "properties": {
    "iso:country":"DE",
    "sg:address":"Seeleitenweg 5",
    "sg:city":"Waging",
    "sg:phone":"+49 8681/4262",
    "sg:postcode":"83329",
    "sg:province":"Bayern",
    "wof:name":"Kneidl Gmbh & Co. Handels Kg",
    "wof:placetype":"venue"
},
  "geometry": {"coordinates":[12.7500686646,47.9575843811],"type":"Point"}
}