{
  "type": "Feature",
  "properties": {
    "iso:country":"DE",
    "sg:address":"Neuelandstr. 20",
    "sg:city":"Bremerhaven",
    "sg:phone":"+49 471/52516",
    "sg:postcode":"27576",
    "sg:province":"Bremen",
    "wof:name":"Dionysos",
    "wof:placetype":"venue"
},
  "geometry": {"coordinates":[8.5887880325,53.5623779297],"type":"Point"}
}