{
  "type": "Feature",
  "properties": {
    "iso:country":"DE",
    "sg:address":"S\u00fcdliche Hauptstr. 26",
    "sg:city":"Rottach-Egern",
    "sg:phone":"+49 8022/67231",
    "sg:postcode":"83700",
    "sg:province":"Bayern",
    "wof:name":"Tremmel Gmbh",
    "wof:placetype":"venue"
},
  "geometry": {"coordinates":[11.76755,47.689133],"type":"Point"}
}