{
  "type": "Feature",
  "properties": {
    "iso:country":"DE",
    "sg:address":"Jahnstr. 48",
    "sg:city":"G\u00f6ppingen",
    "sg:phone":"+49 7161/78554",
    "sg:postcode":"73037",
    "sg:province":"Baden-W\u00fcrttemberg",
    "wof:name":"Avia Tankstelle",
    "wof:placetype":"venue"
},
  "geometry": {"coordinates":[9.6528196335,48.6988105774],"type":"Point"}
}