{
  "type": "Feature",
  "properties": {
    "iso:country":"DE",
    "sg:address":"Ahornstr. 10",
    "sg:city":"Ebenhofen",
    "sg:postcode":"87640",
    "sg:province":"Bayern",
    "wof:name":"Fieselgators Kaufbeuren E.v. - Streethockey",
    "wof:placetype":"venue"
},
  "geometry": {"coordinates":[10.619484,47.81461],"type":"Point"}
}