{
  "type": "Feature",
  "properties": {
    "iso:country":"DE",
    "sg:address":"Dientzenhoferstr. 8",
    "sg:city":"Ingolstadt",
    "sg:phone":"+49 841/483420",
    "sg:postcode":"85049",
    "sg:province":"Bayern",
    "wof:name":"Reinhard Kren Immobilienmakler",
    "wof:placetype":"venue"
},
  "geometry": {"coordinates":[11.3871259689,48.7646598816],"type":"Point"}
}