{
  "type": "Feature",
  "properties": {
    "iso:country":"DE",
    "sg:address":"Leonhardstr. 7",
    "sg:city":"H\u00fcckelhoven",
    "sg:phone":"+49 2433/42665",
    "sg:postcode":"41836",
    "sg:province":"Nordrhein-Westfalen",
    "wof:name":"Erich Emrich",
    "wof:placetype":"venue"
},
  "geometry": {"coordinates":[6.220796,51.040245],"type":"Point"}
}