{
  "type": "Feature",
  "properties": {
    "iso:country":"DE",
    "sg:address":"Blumenstr. 14",
    "sg:city":"Woltersdorf",
    "sg:phone":"+49 3362/22912",
    "sg:postcode":"15569",
    "sg:province":"Brandenburg",
    "wof:name":"Klaus Werner Ingenieur",
    "wof:placetype":"venue"
},
  "geometry": {"coordinates":[13.7622680664,52.4507331848],"type":"Point"}
}