{
  "type": "Feature",
  "properties": {
    "iso:country":"DE",
    "sg:address":"Im Specken 5",
    "sg:city":"Ahausen",
    "sg:phone":"+49 4269/5247",
    "sg:postcode":"27367",
    "sg:province":"Niedersachsen",
    "wof:name":"Heinrich K\u00f6ster",
    "wof:placetype":"venue"
},
  "geometry": {"coordinates":[9.315302,53.064396],"type":"Point"}
}