{
  "type": "Feature",
  "properties": {
    "iso:country":"DE",
    "sg:address":"Brennesstr. 3",
    "sg:city":"Lohberg",
    "sg:phone":"+49 9943/1202",
    "sg:postcode":"93470",
    "sg:province":"Bayern",
    "wof:name":"Gasthaus G. Gra\u00dfl",
    "wof:placetype":"venue"
},
  "geometry": {"coordinates":[13.1042432785,49.1752433777],"type":"Point"}
}