{
  "type": "Feature",
  "properties": {
    "iso:country":"DE",
    "sg:address":"Steinfrankenreuth 4",
    "sg:city":"Flo\u00df",
    "sg:phone":"+49 9603/2433",
    "sg:postcode":"92685",
    "sg:province":"Bayern",
    "wof:name":"Werner Riedel",
    "wof:placetype":"venue"
},
  "geometry": {"coordinates":[12.26648,49.687946],"type":"Point"}
}