{
  "type": "Feature",
  "properties": {
    "iso:country":"DE",
    "sg:address":"Guardinistr.155",
    "sg:city":"M\u00fcnchen",
    "sg:phone":"+49 170",
    "sg:postcode":"81375",
    "sg:province":"Bayern",
    "wof:name":"Fastovskij-transporte",
    "wof:placetype":"venue"
},
  "geometry": {"coordinates":[11.4833688736,48.1189155579],"type":"Point"}
}