{
  "type": "Feature",
  "properties": {
    "iso:country":"DE",
    "sg:address":"Zum Scherb\u00fcchel 14",
    "sg:city":"R\u00f6srath",
    "sg:phone":"+49 2205/6647",
    "sg:postcode":"51503",
    "sg:province":"Nordrhein-Westfalen",
    "wof:name":"Nagel Gmbh",
    "wof:placetype":"venue"
},
  "geometry": {"coordinates":[7.200709,50.902287],"type":"Point"}
}