{
  "type": "Feature",
  "properties": {
    "iso:country":"DE",
    "sg:address":"Hamberger Ring 28",
    "sg:city":"Lohne",
    "sg:phone":"+49 4442/2325",
    "sg:postcode":"49393",
    "sg:province":"Niedersachsen",
    "wof:name":"Abc Agency For Bilding Components Gmbh",
    "wof:placetype":"venue"
},
  "geometry": {"coordinates":[8.2508478165,52.6459159851],"type":"Point"}
}