{
  "type": "Feature",
  "properties": {
    "iso:country":"DE",
    "sg:address":"Friedrich-R\u00fcckert-Ring 8A",
    "sg:city":"Maroldsweisach",
    "sg:phone":"+49 9382/4444",
    "sg:postcode":"96126",
    "sg:province":"Bayern",
    "wof:name":"Wilder Mann",
    "wof:placetype":"venue"
},
  "geometry": {"coordinates":[10.6531963348,50.1987915039],"type":"Point"}
}