{
  "type": "Feature",
  "properties": {
    "iso:country":"DE",
    "sg:address":"Klewertweg 48 a",
    "sg:city":"Hemmingen",
    "sg:phone":"+49 511/9426563",
    "sg:postcode":"30966",
    "sg:province":"Niedersachsen",
    "wof:name":"Messeservice A. Kuhn Gmbh",
    "wof:placetype":"venue"
},
  "geometry": {"coordinates":[9.727679,52.329346],"type":"Point"}
}