{
  "type": "Feature",
  "properties": {
    "iso:country":"DE",
    "sg:address":"Schlo\u00dfhof",
    "sg:city":"Nebra",
    "sg:phone":"+49 34461",
    "sg:postcode":"06642",
    "sg:province":"Sachsen-Anhalt",
    "wof:name":"Hotel & Restaurant, Schlosshotel-nebra * * * *",
    "wof:placetype":"venue"
},
  "geometry": {"coordinates":[11.5453596115,51.2680587769],"type":"Point"}
}