{
  "type": "Feature",
  "properties": {
    "iso:country":"DE",
    "sg:address":"Chemnitzer Str. 48",
    "sg:city":"Gr\u00fcna",
    "sg:phone":"+49 371/851352",
    "sg:postcode":"09224",
    "sg:province":"Sachsen",
    "wof:name":"Alexander Ge\u00dfner",
    "wof:placetype":"venue"
},
  "geometry": {"coordinates":[12.7813901901,50.8105583191],"type":"Point"}
}