{
  "type": "Feature",
  "properties": {
    "iso:country":"DE",
    "sg:address":"Schulgasse 21",
    "sg:city":"Albstadt",
    "sg:phone":"+49 7432/6289",
    "sg:postcode":"72459",
    "sg:province":"Baden-W\u00fcrttemberg",
    "wof:name":"Werner Bitzer",
    "wof:placetype":"venue"
},
  "geometry": {"coordinates":[8.9639921188,48.2548522949],"type":"Point"}
}