{
  "type": "Feature",
  "properties": {
    "iso:country":"DE",
    "sg:address":"Bahnhofstr. 184",
    "sg:city":"Duisburg",
    "sg:phone":"+49 203/4791870",
    "sg:postcode":"47178",
    "sg:province":"Nordrhein-Westfalen",
    "wof:name":"Gisela Zaremba Steuerberaterin",
    "wof:placetype":"venue"
},
  "geometry": {"coordinates":[6.7269701958,51.5349349976],"type":"Point"}
}