{
  "type": "Feature",
  "properties": {
    "iso:country":"DE",
    "sg:address":"Weidmattenstr. 2",
    "sg:city":"B\u00fchl",
    "sg:phone":"+49 7223/94580",
    "sg:postcode":"77815",
    "sg:province":"Baden-W\u00fcrttemberg",
    "wof:name":"Rheintal-apotheke",
    "wof:placetype":"venue"
},
  "geometry": {"coordinates":[8.112728,48.722404],"type":"Point"}
}