{
  "type": "Feature",
  "properties": {
    "iso:country":"DE",
    "sg:address":"Auenall. 3",
    "sg:city":"Zweimen",
    "sg:phone":"+49 4934/6388180",
    "sg:postcode":"06254",
    "sg:province":"Sachsen-Anhalt",
    "wof:name":"Flowserve Essen Gmbh",
    "wof:placetype":"venue"
},
  "geometry": {"coordinates":[12.131215,51.354542],"type":"Point"}
}