{
  "type": "Feature",
  "properties": {
    "iso:country":"DE",
    "sg:address":"Schumannstr. 2",
    "sg:city":"L\u00fcdenscheid",
    "sg:phone":"+49 2351/963343",
    "sg:postcode":"58509",
    "sg:province":"Nordrhein-Westfalen",
    "wof:name":"Polydorm M\u00e4rkische Fachklinik F\u00fcr Schlafmedizin",
    "wof:placetype":"venue"
},
  "geometry": {"coordinates":[7.5989627838,51.2267990112],"type":"Point"}
}