{
  "type": "Feature",
  "properties": {
    "iso:country":"DE",
    "sg:address":"Kapellenstr. 18",
    "sg:city":"M\u00fclheim-K\u00e4rlich",
    "sg:postcode":"56218",
    "sg:province":"Rheinland-Pfalz",
    "wof:name":"Maria Vertheyen",
    "wof:placetype":"venue"
},
  "geometry": {"coordinates":[7.498001,50.386913],"type":"Point"}
}