{
  "type": "Feature",
  "properties": {
    "iso:country":"DE",
    "sg:address":"Bahnhofstr. 61",
    "sg:city":"M\u00fchlheim",
    "sg:phone":"+49 7463/7447",
    "sg:postcode":"78570",
    "sg:province":"Baden-W\u00fcrttemberg",
    "wof:name":"W. Wirth",
    "wof:placetype":"venue"
},
  "geometry": {"coordinates":[8.881376,48.026379],"type":"Point"}
}