{
  "type": "Feature",
  "properties": {
    "iso:country":"DE",
    "sg:address":"V\u00f6lklinger Str. 128",
    "sg:city":"V\u00f6lklingen",
    "sg:phone":"+49 6898/943134",
    "sg:postcode":"66333",
    "sg:province":"Saarland",
    "wof:name":"Horst Reinhard Architekt",
    "wof:placetype":"venue"
},
  "geometry": {"coordinates":[6.8068,49.22094],"type":"Point"}
}