{
  "type": "Feature",
  "properties": {
    "iso:country":"DE",
    "sg:address":"Gudesstr. 18/20",
    "sg:city":"Uelzen",
    "sg:phone":"+49 581/2777",
    "sg:postcode":"29525",
    "sg:province":"Niedersachsen",
    "wof:name":"Wilgr\u00fc Textileinzelhandel Jens Gr\u00fcnewald-steiger E. K.",
    "wof:placetype":"venue"
},
  "geometry": {"coordinates":[10.5619525909,52.9647789001],"type":"Point"}
}