{
  "type": "Feature",
  "properties": {
    "iso:country":"DE",
    "sg:address":"Senefelderstr. 109",
    "sg:city":"Stuttgart",
    "sg:postcode":"70176",
    "sg:province":"Baden-W\u00fcrttemberg",
    "wof:name":"Tk Bio-super-markt Gmbh",
    "wof:placetype":"venue"
},
  "geometry": {"coordinates":[9.1568479538,48.7807159424],"type":"Point"}
}