{
  "type": "Feature",
  "properties": {
    "iso:country":"DE",
    "sg:address":"Sandstr. 76",
    "sg:city":"Herford",
    "sg:phone":"+49 5221/70508",
    "sg:postcode":"32052",
    "sg:province":"Nordrhein-Westfalen",
    "wof:name":"Gerhard Wittenborn",
    "wof:placetype":"venue"
},
  "geometry": {"coordinates":[8.6560258865,52.0803337097],"type":"Point"}
}