{
  "type": "Feature",
  "properties": {
    "iso:country":"DE",
    "sg:address":"Elsbruch 15",
    "sg:city":"Heinsberg",
    "sg:phone":"+49 2452/7555",
    "sg:postcode":"52525",
    "sg:province":"Nordrhein-Westfalen",
    "wof:name":"Heinrich Hilgers",
    "wof:placetype":"venue"
},
  "geometry": {"coordinates":[6.099705,51.090122],"type":"Point"}
}