{
  "type": "Feature",
  "properties": {
    "iso:country":"DE",
    "sg:address":"Winzelb\u00fcrgstr. 9",
    "sg:city":"N\u00fcrnberg",
    "sg:phone":"+49 911/591543",
    "sg:postcode":"90491",
    "sg:province":"Bayern",
    "wof:name":"Rudi Vogel Architekt",
    "wof:placetype":"venue"
},
  "geometry": {"coordinates":[11.108877,49.462029],"type":"Point"}
}