{
  "type": "Feature",
  "properties": {
    "iso:country":"DE",
    "sg:address":"Hauptstr. 21",
    "sg:city":"Bergrheinfeld",
    "sg:phone":"+49 9721/90864",
    "sg:postcode":"97493",
    "sg:province":"Bayern",
    "wof:name":"Gregor Neuberth",
    "wof:placetype":"venue"
},
  "geometry": {"coordinates":[10.1778106689,50.0041999817],"type":"Point"}
}