{
  "type": "Feature",
  "properties": {
    "iso:country":"DE",
    "sg:address":"Am Steinberg 5 b",
    "sg:city":"W\u00f6rthsee",
    "sg:phone":"+49 8153/8070",
    "sg:postcode":"82237",
    "sg:province":"Bayern",
    "wof:name":"Klaus-j\u00fcrgen Ulbricht Architekt",
    "wof:placetype":"venue"
},
  "geometry": {"coordinates":[11.204164,48.064297],"type":"Point"}
}