{
  "type": "Feature",
  "properties": {
    "iso:country":"DE",
    "sg:address":"Bockskamp 14",
    "sg:city":"Kalkar",
    "sg:phone":"+49 2824/6337",
    "sg:postcode":"47546",
    "sg:province":"Nordrhein-Westfalen",
    "wof:name":"J. Wenten",
    "wof:placetype":"venue"
},
  "geometry": {"coordinates":[6.31356,51.785252],"type":"Point"}
}