{
  "type": "Feature",
  "properties": {
    "iso:country":"DE",
    "sg:address":"Hof Schrixdorf",
    "sg:city":"Mohrkirch",
    "sg:phone":"+49 4646",
    "sg:postcode":"24405",
    "sg:province":"Schleswig-Holstein",
    "wof:name":"Immobilien Mit Stil",
    "wof:placetype":"venue"
},
  "geometry": {"coordinates":[9.6925449371,54.6649131775],"type":"Point"}
}