{
  "type": "Feature",
  "properties": {
    "iso:country":"DE",
    "sg:address":"Bergstr. 49",
    "sg:city":"Bad Laasphe",
    "sg:phone":"+49 2752/6337",
    "sg:postcode":"57334",
    "sg:province":"Nordrhein-Westfalen",
    "wof:name":"Pension Elisabeth Wille",
    "wof:placetype":"venue"
},
  "geometry": {"coordinates":[8.4034509659,50.9317359924],"type":"Point"}
}