{
  "type": "Feature",
  "properties": {
    "iso:country":"DE",
    "sg:address":"Bahnhofstr. 26",
    "sg:city":"Ebersburg",
    "sg:phone":"+49 6656/1543",
    "sg:postcode":"36157",
    "sg:province":"Hessen",
    "wof:name":"S. Kleinhenz",
    "wof:placetype":"venue"
},
  "geometry": {"coordinates":[9.789607048,50.456401825],"type":"Point"}
}