{
  "type": "Feature",
  "properties": {
    "iso:country":"DE",
    "sg:address":"Maximinstr. 9",
    "sg:city":"Mehring",
    "sg:phone":"+49 6502/2788",
    "sg:postcode":"54346",
    "sg:province":"Rheinland-Pfalz",
    "wof:name":"L. Molitor Weinanbau",
    "wof:placetype":"venue"
},
  "geometry": {"coordinates":[6.82062006,49.795425415],"type":"Point"}
}