{
  "type": "Feature",
  "properties": {
    "iso:country":"DE",
    "sg:address":"Hohenzollernstr. 29",
    "sg:city":"Hannover",
    "sg:phone":"+49 511/312950",
    "sg:postcode":"30161",
    "sg:province":"Niedersachsen",
    "wof:name":"Travel 2 Fairs Gmbh",
    "wof:placetype":"venue"
},
  "geometry": {"coordinates":[9.7563056946,52.3828964233],"type":"Point"}
}