{
  "type": "Feature",
  "properties": {
    "iso:country":"DE",
    "sg:address":"Sch\u00f6nnemer Str. 28",
    "sg:city":"Erbach",
    "sg:phone":"+49 6062/3203",
    "sg:postcode":"64711",
    "sg:province":"Hessen",
    "wof:name":"Kurt Kessler",
    "wof:placetype":"venue"
},
  "geometry": {"coordinates":[8.99466,49.627277],"type":"Point"}
}