{
  "type": "Feature",
  "properties": {
    "iso:country":"DE",
    "sg:address":"Fritz-Claus-Weg 1",
    "sg:city":"Edenkoben",
    "sg:phone":"+49 6323/989333",
    "sg:postcode":"67480",
    "sg:province":"Rheinland-Pfalz",
    "wof:name":"Gerling Konzern",
    "wof:placetype":"venue"
},
  "geometry": {"coordinates":[8.1172771454,49.2803382874],"type":"Point"}
}