{
  "type": "Feature",
  "properties": {
    "iso:country":"DE",
    "sg:address":"Im Burkhardtstal 10",
    "sg:city":"Sinsheim",
    "sg:phone":"+49 7265/7202",
    "sg:postcode":"74889",
    "sg:province":"Baden-W\u00fcrttemberg",
    "wof:name":"Almon-quarzapparatebau Gmbh",
    "wof:placetype":"venue"
},
  "geometry": {"coordinates":[8.8041543961,49.2133255005],"type":"Point"}
}