{
  "type": "Feature",
  "properties": {
    "iso:country":"DE",
    "sg:address":"Leester Str. 11",
    "sg:city":"Stuhr",
    "sg:phone":"+49 421/88055",
    "sg:postcode":"28816",
    "sg:province":"Niedersachsen",
    "wof:name":"Manfred Hohenecker Rechtsanwalt Und Notar",
    "wof:placetype":"venue"
},
  "geometry": {"coordinates":[8.793718338,53.0049209595],"type":"Point"}
}