{
  "type": "Feature",
  "properties": {
    "iso:country":"DE",
    "sg:address":"Auf Rinelen 38",
    "sg:city":"Schwenningen",
    "sg:phone":"+49 7720",
    "sg:postcode":"78056",
    "sg:province":"Baden-W\u00fcrttemberg",
    "wof:name":"Vermittlungs-b\u00f6rse / Party&showservice",
    "wof:placetype":"venue"
},
  "geometry": {"coordinates":[8.5416660309,48.0734977722],"type":"Point"}
}