{
  "type": "Feature",
  "properties": {
    "iso:country":"DE",
    "sg:address":"Winkelstr. 6",
    "sg:city":"Ramstein-Miesenbach",
    "sg:phone":"+49 6371/50512",
    "sg:postcode":"66877",
    "sg:province":"Rheinland-Pfalz",
    "wof:name":"Hotel Bacchus",
    "wof:placetype":"venue"
},
  "geometry": {"coordinates":[7.5584340096,49.4435958862],"type":"Point"}
}