{
  "type": "Feature",
  "properties": {
    "iso:country":"DE",
    "sg:address":"Ludwigsburger Str. 11",
    "sg:city":"Fellbach",
    "sg:postcode":"70736",
    "sg:province":"Baden-W\u00fcrttemberg",
    "wof:name":"Deltat Me\u00dfdienst Geb\u00e4udeservice Gmbh",
    "wof:placetype":"venue"
},
  "geometry": {"coordinates":[9.267416,48.845062],"type":"Point"}
}