{
  "type": "Feature",
  "properties": {
    "iso:country":"DE",
    "sg:address":"Dernburgstr. 37",
    "sg:city":"Berlin",
    "sg:phone":"+49 30/3217509",
    "sg:postcode":"14057",
    "sg:province":"Berlin",
    "wof:name":"Berliner Parkett-kontor Inh. M. Kannenberg",
    "wof:placetype":"venue"
},
  "geometry": {"coordinates":[13.2843704224,52.5038871765],"type":"Point"}
}