{
  "type": "Feature",
  "properties": {
    "iso:country":"DE",
    "sg:address":"Hammerstr.",
    "sg:city":"Schwarzenberg",
    "sg:phone":"+49 4937/7422651",
    "sg:postcode":"08340",
    "sg:province":"Sachsen",
    "wof:name":"Pressspanfabrik Untersachsenfeld Gmbh",
    "wof:placetype":"venue"
},
  "geometry": {"coordinates":[12.7636699677,50.5573616028],"type":"Point"}
}