{
  "type": "Feature",
  "properties": {
    "iso:country":"DE",
    "sg:address":"Uissigheimer Str. 10",
    "sg:city":"K\u00fclsheim",
    "sg:phone":"+49 9345/216",
    "sg:postcode":"97900",
    "sg:province":"Baden-W\u00fcrttemberg",
    "wof:name":"Willi F\u00fcger",
    "wof:placetype":"venue"
},
  "geometry": {"coordinates":[9.5252084732,49.6710586548],"type":"Point"}
}