{
  "type": "Feature",
  "properties": {
    "iso:country":"DE",
    "sg:address":"Hauptstr. 76",
    "sg:city":"D\u00fcren",
    "sg:phone":"+49 2422/4767",
    "sg:postcode":"52355",
    "sg:province":"Nordrhein-Westfalen",
    "wof:name":"F. Kaminiarz",
    "wof:placetype":"venue"
},
  "geometry": {"coordinates":[6.476835,50.76759],"type":"Point"}
}