{
  "type": "Feature",
  "properties": {
    "iso:country":"DE",
    "sg:address":"Neubr\u00fcck 2",
    "sg:city":"Grevenbroich",
    "sg:phone":"+49 2182/2408",
    "sg:postcode":"41516",
    "sg:province":"Nordrhein-Westfalen",
    "wof:name":"Willi Kr\u00fcll",
    "wof:placetype":"venue"
},
  "geometry": {"coordinates":[6.641395,51.132759],"type":"Point"}
}