{
  "type": "Feature",
  "properties": {
    "iso:country":"DE",
    "sg:address":"R\u00f6ntgenstr. 11",
    "sg:city":"Herzogenaurach",
    "sg:postcode":"91074",
    "sg:province":"Bayern",
    "wof:name":"Tecmat Handelsgesellschaft F\u00fcr Den Maschinenbau Mbh",
    "wof:placetype":"venue"
},
  "geometry": {"coordinates":[10.889168,49.578022],"type":"Point"}
}