{
  "type": "Feature",
  "properties": {
    "iso:country":"DE",
    "sg:address":"Wahlscheider Str. 31",
    "sg:city":"Lohmar",
    "sg:phone":"+49 2206/4884",
    "sg:postcode":"53797",
    "sg:province":"Nordrhein-Westfalen",
    "wof:name":"Laden 78 Matro\u00df Gmbh",
    "wof:placetype":"venue"
},
  "geometry": {"coordinates":[7.2515821457,50.8896408081],"type":"Point"}
}