{
  "type": "Feature",
  "properties": {
    "iso:country":"DE",
    "sg:address":"Am Markt 25",
    "sg:city":"Eppelborn",
    "sg:phone":"+49 6881/7550",
    "sg:postcode":"66571",
    "sg:province":"Saarland",
    "wof:name":"Sebastians-apotheke",
    "wof:placetype":"venue"
},
  "geometry": {"coordinates":[6.967335,49.406815],"type":"Point"}
}