{
  "type": "Feature",
  "properties": {
    "iso:country":"DE",
    "sg:address":"K\u00f6lnstr. 92",
    "sg:city":"D\u00fcren",
    "sg:phone":"+49 2421/13376",
    "sg:postcode":"52351",
    "sg:province":"Nordrhein-Westfalen",
    "wof:name":"E. K\u00f6nn",
    "wof:placetype":"venue"
},
  "geometry": {"coordinates":[6.4902849197,50.8043632507],"type":"Point"}
}