{
  "type": "Feature",
  "properties": {
    "iso:country":"DE",
    "sg:address":"Industriestr. 2 a",
    "sg:city":"Fl\u00f6rsheim",
    "sg:postcode":"65439",
    "sg:province":"Hessen",
    "wof:name":"H & R Naturstein - Objektbau Gmbh",
    "wof:placetype":"venue"
},
  "geometry": {"coordinates":[8.444179,50.040379],"type":"Point"}
}