{
  "type": "Feature",
  "properties": {
    "iso:country":"DE",
    "sg:address":"Holbeinstr. 12",
    "sg:city":"M\u00fcnchen",
    "sg:phone":"+49 89/475105",
    "sg:postcode":"81679",
    "sg:province":"Bayern",
    "wof:name":"Martin Bauer Innenarchitekt",
    "wof:placetype":"venue"
},
  "geometry": {"coordinates":[11.603272,48.142544],"type":"Point"}
}