{
  "type": "Feature",
  "properties": {
    "iso:country":"DE",
    "sg:address":"Panoramastr. 18",
    "sg:city":"Sonnenb\u00fchl",
    "sg:phone":"+49 7128/2593",
    "sg:postcode":"72820",
    "sg:province":"Baden-W\u00fcrttemberg",
    "wof:name":"Kurt Walter Ingenieur",
    "wof:placetype":"venue"
},
  "geometry": {"coordinates":[9.1916189194,48.3879470825],"type":"Point"}
}