{
  "type": "Feature",
  "properties": {
    "iso:country":"DE",
    "sg:address":"Parkstr. 4",
    "sg:city":"Wittenberge",
    "sg:phone":"+49 3877/66285",
    "sg:postcode":"19322",
    "sg:province":"Brandenburg",
    "wof:name":"U. Kamenz",
    "wof:placetype":"venue"
},
  "geometry": {"coordinates":[11.748574,52.996235],"type":"Point"}
}