{
  "type": "Feature",
  "properties": {
    "iso:country":"DE",
    "sg:address":"Heideweg 13",
    "sg:city":"Filderstadt",
    "sg:phone":"+49 711/775701",
    "sg:postcode":"70794",
    "sg:province":"Baden-W\u00fcrttemberg",
    "wof:name":"Roselinde Arnold Immobilienmaklerin",
    "wof:placetype":"venue"
},
  "geometry": {"coordinates":[9.2085561752,48.6476821899],"type":"Point"}
}