{
  "type": "Feature",
  "properties": {
    "iso:country":"DE",
    "sg:address":"Detmoldstr. 5",
    "sg:city":"M\u00fcnchen",
    "sg:phone":"+49 89/3577696",
    "sg:postcode":"80935",
    "sg:province":"Bayern",
    "wof:name":"R.m.p. Umwelttechnik Gmbh",
    "wof:placetype":"venue"
},
  "geometry": {"coordinates":[11.5630178452,48.1925163269],"type":"Point"}
}