{
  "type": "Feature",
  "properties": {
    "iso:country":"DE",
    "sg:address":"Leipziger Str. 10",
    "sg:city":"Wittmar",
    "sg:phone":"+49 5337/7653",
    "sg:postcode":"38329",
    "sg:province":"Niedersachsen",
    "wof:name":"K. R\u00f6mmling",
    "wof:placetype":"venue"
},
  "geometry": {"coordinates":[10.6406450272,52.1284255981],"type":"Point"}
}