{
  "type": "Feature",
  "properties": {
    "iso:country":"DE",
    "sg:address":"Postfach 45",
    "sg:city":"Gro\u00dfbottwar",
    "sg:phone":"+49 7148/5299",
    "sg:postcode":"71721",
    "sg:province":"Baden-W\u00fcrttemberg",
    "wof:name":"Restaurant Rose",
    "wof:placetype":"venue"
},
  "geometry": {"coordinates":[9.2971420288,49.0012817383],"type":"Point"}
}