{
  "type": "Feature",
  "properties": {
    "iso:country":"DE",
    "sg:address":"D\u00fcrmerstr. 7",
    "sg:city":"Urmitz",
    "sg:phone":"+49 2630/7527",
    "sg:postcode":"56220",
    "sg:province":"Rheinland-Pfalz",
    "wof:name":"Konrad Dott",
    "wof:placetype":"venue"
},
  "geometry": {"coordinates":[7.517595,50.415619],"type":"Point"}
}