{
  "type": "Feature",
  "properties": {
    "iso:country":"DE",
    "sg:address":"Luitpoldstra\u00dfe 27",
    "sg:city":"Eichst\u00e4tt",
    "sg:phone":"+49 8421/3107",
    "sg:postcode":"85072",
    "sg:province":"Bayern",
    "wof:name":"Bizvesi - Bildungszentrum F\u00fcr Verkehrssicherheit",
    "wof:placetype":"venue"
},
  "geometry": {"coordinates":[11.1859846115,48.8936843872],"type":"Point"}
}