{
  "type": "Feature",
  "properties": {
    "iso:country":"DE",
    "sg:address":"Eschersheimer Landstr. 325",
    "sg:city":"Frankfurt",
    "sg:phone":"+49 69/563066",
    "sg:postcode":"60320",
    "sg:province":"Hessen",
    "wof:name":"Ail Anlagen Und Investitions- G\u00fcter Leasing Frankfurt Gmbh",
    "wof:placetype":"venue"
},
  "geometry": {"coordinates":[8.6691093445,50.140838623],"type":"Point"}
}