{
  "type": "Feature",
  "properties": {
    "iso:country":"DE",
    "sg:address":"Virchowstr. 57",
    "sg:city":"Hamburg",
    "sg:phone":"+49 40/3800179",
    "sg:postcode":"22767",
    "sg:province":"Hamburg",
    "wof:name":"S. Und R. Gercken",
    "wof:placetype":"venue"
},
  "geometry": {"coordinates":[9.94783,53.553699],"type":"Point"}
}