{
  "type": "Feature",
  "properties": {
    "iso:country":"DE",
    "sg:address":"Friedrichstr. 3",
    "sg:city":"K\u00f6ln",
    "sg:phone":"+49 221/2576589",
    "sg:postcode":"50676",
    "sg:province":"Nordrhein-Westfalen",
    "wof:name":"Kraemer Gmbh",
    "wof:placetype":"venue"
},
  "geometry": {"coordinates":[7.0603370667,50.8835792542],"type":"Point"}
}