{
  "type": "Feature",
  "properties": {
    "iso:country":"DE",
    "sg:address":"Koblenzer Str. 201",
    "sg:city":"Bonn",
    "sg:postcode":"53177",
    "sg:province":"Nordrhein-Westfalen",
    "wof:name":"Michael M\u00fcller Gmbh",
    "wof:placetype":"venue"
},
  "geometry": {"coordinates":[7.170837,50.676159],"type":"Point"}
}