{
  "type": "Feature",
  "properties": {
    "iso:country":"DE",
    "sg:address":"Daimlerstr. 8",
    "sg:city":"Forchheim",
    "sg:phone":"+49 9191/72160",
    "sg:postcode":"91301",
    "sg:province":"Bayern",
    "wof:name":"Dietzel & R\u00f6sch Dental Gmbh",
    "wof:placetype":"venue"
},
  "geometry": {"coordinates":[11.062459,49.703403],"type":"Point"}
}