{
  "type": "Feature",
  "properties": {
    "iso:country":"DE",
    "sg:address":"Landwehrstr. 5",
    "sg:city":"M\u00fcnchen",
    "sg:phone":"+49 89/597833",
    "sg:postcode":"80336",
    "sg:province":"Bayern",
    "wof:name":"Pension Luna",
    "wof:placetype":"venue"
},
  "geometry": {"coordinates":[11.5639152527,48.136138916],"type":"Point"}
}