{
  "type": "Feature",
  "properties": {
    "iso:country":"DE",
    "sg:address":"August-Bebel-Str. 24",
    "sg:city":"K\u00f6nigswalde",
    "sg:phone":"+49 3733/44238",
    "sg:postcode":"09471",
    "sg:province":"Sachsen",
    "wof:name":"Bau- Und M\u00f6beltischlerei Michael Br\u00e4uer",
    "wof:placetype":"venue"
},
  "geometry": {"coordinates":[13.049871,50.542213],"type":"Point"}
}