{
  "type": "Feature",
  "properties": {
    "iso:country":"DE",
    "sg:address":"Hofmark 10",
    "sg:city":"Abensberg",
    "sg:phone":"+49 9443/6441",
    "sg:postcode":"93326",
    "sg:province":"Bayern",
    "wof:name":"Michael Kiermeier",
    "wof:placetype":"venue"
},
  "geometry": {"coordinates":[11.9031381607,48.8074569702],"type":"Point"}
}