{
  "type": "Feature",
  "properties": {
    "iso:country":"DE",
    "sg:address":"Rosenstr. 28",
    "sg:city":"Heide",
    "sg:phone":"+49 481/71112",
    "sg:postcode":"25746",
    "sg:province":"Schleswig-Holstein",
    "wof:name":"Horst Eickhoff Masseur",
    "wof:placetype":"venue"
},
  "geometry": {"coordinates":[9.090969,54.196968],"type":"Point"}
}