{
  "type": "Feature",
  "properties": {
    "iso:country":"DE",
    "sg:address":"Parkstr. 47a",
    "sg:city":"Hamburg",
    "sg:postcode":"22605",
    "sg:province":"Hamburg",
    "wof:name":"Park Beteiligungs- Und Verwaltungsgesellschaft Mbh",
    "wof:placetype":"venue"
},
  "geometry": {"coordinates":[9.88017,53.551369],"type":"Point"}
}