{
  "type": "Feature",
  "properties": {
    "iso:country":"DE",
    "sg:address":"Frankenstr. 49",
    "sg:city":"Mechernich",
    "sg:phone":"+49 2443/6257",
    "sg:postcode":"53894",
    "sg:province":"Nordrhein-Westfalen",
    "wof:name":"Peter J. Merzenich",
    "wof:placetype":"venue"
},
  "geometry": {"coordinates":[6.612894,50.62701],"type":"Point"}
}