{
  "type": "Feature",
  "properties": {
    "iso:country":"DE",
    "sg:address":"An den K\u00e4mpen 56",
    "sg:city":"L\u00fcdinghausen",
    "sg:phone":"+49 2591/8541",
    "sg:postcode":"59348",
    "sg:province":"Nordrhein-Westfalen",
    "wof:name":"Katholische Arbeiter Bewegung St. Josef Seppenrade",
    "wof:placetype":"venue"
},
  "geometry": {"coordinates":[7.3864049911,51.7569084167],"type":"Point"}
}