{
  "type": "Feature",
  "properties": {
    "iso:country":"DE",
    "sg:address":"H\u00f6rster Str. 66",
    "sg:city":"Lage",
    "sg:phone":"+49 5232/71150",
    "sg:postcode":"32791",
    "sg:province":"Nordrhein-Westfalen",
    "wof:name":"H. Dreimann",
    "wof:placetype":"venue"
},
  "geometry": {"coordinates":[8.77479,51.958599],"type":"Point"}
}