{
  "type": "Feature",
  "properties": {
    "iso:country":"DE",
    "sg:address":"Am Goldbach 1",
    "sg:city":"Obermaiselstein",
    "sg:phone":"+49 8326/7754",
    "sg:postcode":"87538",
    "sg:province":"Bayern",
    "wof:name":"Duttlinger",
    "wof:placetype":"venue"
},
  "geometry": {"coordinates":[10.2442827225,47.445224762],"type":"Point"}
}