{
  "type": "Feature",
  "properties": {
    "iso:country":"DE",
    "sg:address":"Am Baderteich 11",
    "sg:city":"Bad D\u00fcben",
    "sg:phone":"+49 34243/22530",
    "sg:postcode":"04849",
    "sg:province":"Sachsen",
    "wof:name":"Sabine J\u00f6rke",
    "wof:placetype":"venue"
},
  "geometry": {"coordinates":[12.588391304,51.592716217],"type":"Point"}
}