{
  "type": "Feature",
  "properties": {
    "iso:country":"DE",
    "sg:address":"Im Stadtgarten 2",
    "sg:city":"Bottrop",
    "sg:phone":"+49 2041/9690",
    "sg:postcode":"46236",
    "sg:province":"Nordrhein-Westfalen",
    "wof:name":"Wohn- Und Pflegeheim Bottrop",
    "wof:placetype":"venue"
},
  "geometry": {"coordinates":[6.921952,51.532543],"type":"Point"}
}