{
  "type": "Feature",
  "properties": {
    "iso:country":"DE",
    "sg:address":"Hemmstr. 89",
    "sg:city":"Bremen",
    "sg:phone":"+49 421/355073",
    "sg:postcode":"28215",
    "sg:province":"Bremen",
    "wof:name":"Village",
    "wof:placetype":"venue"
},
  "geometry": {"coordinates":[8.8012008667,53.0917053223],"type":"Point"}
}