{
  "type": "Feature",
  "properties": {
    "iso:country":"DE",
    "sg:address":"Wittelsbacherallee 60",
    "sg:city":"Frankfurt",
    "sg:phone":"+49 69/446044",
    "sg:postcode":"60385",
    "sg:province":"Hessen",
    "wof:name":"Linder Presse Union Gmbh Werbeagentur",
    "wof:placetype":"venue"
},
  "geometry": {"coordinates":[8.7062444687,50.1201896667],"type":"Point"}
}