{
  "type": "Feature",
  "properties": {
    "iso:country":"DE",
    "sg:address":"Prinzregentenstr. 21",
    "sg:city":"Rodalben",
    "sg:phone":"+49 6331/17321",
    "sg:postcode":"66976",
    "sg:province":"Rheinland-Pfalz",
    "wof:name":"Josef Schehl",
    "wof:placetype":"venue"
},
  "geometry": {"coordinates":[7.636372,49.239819],"type":"Point"}
}