{
  "type": "Feature",
  "properties": {
    "iso:country":"DE",
    "sg:address":"Freiherr-vom-Stein-Str. 2",
    "sg:city":"Speyer",
    "sg:postcode":"67346",
    "sg:province":"Rheinland-Pfalz",
    "wof:name":"Forschungsinstitut F. \u00f6ffentl. Verwaltung Bei Der Hochschule",
    "wof:placetype":"venue"
},
  "geometry": {"coordinates":[8.416765213,49.3169288635],"type":"Point"}
}