{
  "type": "Feature",
  "properties": {
    "iso:country":"DE",
    "sg:address":"Rainer-Maria-Rilke-Str. 4",
    "sg:city":"Denzlingen",
    "sg:phone":"+49 7666/6538",
    "sg:postcode":"79211",
    "sg:province":"Baden-W\u00fcrttemberg",
    "wof:name":"Lascheit Und Seitz Architekten",
    "wof:placetype":"venue"
},
  "geometry": {"coordinates":[7.890776,48.072491],"type":"Point"}
}