{
  "type": "Feature",
  "properties": {
    "iso:country":"DE",
    "sg:address":"Heidestr. 44",
    "sg:city":"Hagen",
    "sg:phone":"+49 2334/45687",
    "sg:postcode":"58119",
    "sg:province":"Nordrhein-Westfalen",
    "wof:name":"Heinrich Rinke",
    "wof:placetype":"venue"
},
  "geometry": {"coordinates":[7.571436882,51.3578681946],"type":"Point"}
}