{
  "type": "Feature",
  "properties": {
    "iso:country":"DE",
    "sg:address":"Aalener Str 70",
    "sg:city":"Oberkochen",
    "sg:phone":"+49 7364/7713",
    "sg:postcode":"73447",
    "sg:province":"Baden-W\u00fcrttemberg",
    "wof:name":"Rettenmaier Schleifservice Gmbh",
    "wof:placetype":"venue"
},
  "geometry": {"coordinates":[10.1134109497,48.7859344482],"type":"Point"}
}