{
  "type": "Feature",
  "properties": {
    "iso:country":"DE",
    "sg:address":"Ferdinand-Runge-Str. 3",
    "sg:city":"Halle",
    "sg:phone":"+49 345/4443834",
    "sg:postcode":"06130",
    "sg:province":"Sachsen-Anhalt",
    "wof:name":"Werner Oehme",
    "wof:placetype":"venue"
},
  "geometry": {"coordinates":[11.9880247116,51.4494781494],"type":"Point"}
}