{
  "type": "Feature",
  "properties": {
    "iso:country":"DE",
    "sg:address":"Scharfeneckstr. 2",
    "sg:city":"Oberscheinfeld",
    "sg:phone":"+49 9167/1219",
    "sg:postcode":"91483",
    "sg:province":"Bayern",
    "wof:name":"Klingenbach Gmbh",
    "wof:placetype":"venue"
},
  "geometry": {"coordinates":[10.4382991791,49.7084655762],"type":"Point"}
}