{
  "type": "Feature",
  "properties": {
    "iso:country":"DE",
    "sg:address":"Wiesenweg 4",
    "sg:city":"Steinigtwolmsdorf",
    "sg:phone":"+49 35951/31632",
    "sg:postcode":"01904",
    "sg:province":"Sachsen",
    "wof:name":"Holger Thomas",
    "wof:placetype":"venue"
},
  "geometry": {"coordinates":[14.342376,51.059376],"type":"Point"}
}