{
  "type": "Feature",
  "properties": {
    "iso:country":"DE",
    "sg:address":"Alsbergstr. 12",
    "sg:city":"Breuna",
    "sg:phone":"+49 5693/7023",
    "sg:postcode":"34479",
    "sg:province":"Hessen",
    "wof:name":"Brunhilde Reith",
    "wof:placetype":"venue"
},
  "geometry": {"coordinates":[9.1579427719,51.4098052979],"type":"Point"}
}