{
  "type": "Feature",
  "properties": {
    "iso:country":"DE",
    "sg:address":"Darmst\u00e4dter Str. 5",
    "sg:city":"Reinheim",
    "sg:phone":"+49 6162/1736",
    "sg:postcode":"64354",
    "sg:province":"Hessen",
    "wof:name":"Wilhelm Henkel",
    "wof:placetype":"venue"
},
  "geometry": {"coordinates":[8.831173,49.826965],"type":"Point"}
}