{
  "type": "Feature",
  "properties": {
    "iso:country":"DE",
    "sg:address":"Lindenstr. 1",
    "sg:city":"Kupferberg",
    "sg:phone":"+49 9227/97166",
    "sg:postcode":"95362",
    "sg:province":"Bayern",
    "wof:name":"Alois Zeyher",
    "wof:placetype":"venue"
},
  "geometry": {"coordinates":[11.5722551346,50.1407394409],"type":"Point"}
}