{
  "type": "Feature",
  "properties": {
    "iso:country":"DE",
    "sg:address":"Dorfstr. 16",
    "sg:city":"Zehna",
    "sg:phone":"+49 38458/21926",
    "sg:postcode":"18276",
    "sg:province":"Mecklenburg-Vorpommern",
    "wof:name":"Pension P. Junge",
    "wof:placetype":"venue"
},
  "geometry": {"coordinates":[12.1397733688,53.7146110535],"type":"Point"}
}