{
  "type": "Feature",
  "properties": {
    "iso:country":"DE",
    "sg:address":"In den Siepen 30",
    "sg:city":"Wuppertal",
    "sg:phone":"+49 202/662418",
    "sg:postcode":"42109",
    "sg:province":"Nordrhein-Westfalen",
    "wof:name":"Foto Dahmen",
    "wof:placetype":"venue"
},
  "geometry": {"coordinates":[7.1553149223,51.2846717834],"type":"Point"}
}