{
  "type": "Feature",
  "properties": {
    "iso:country":"DE",
    "sg:address":"Deimenrieder Str. 31",
    "sg:city":"Huglfing",
    "sg:phone":"+49 8802/1772",
    "sg:postcode":"82386",
    "sg:province":"Bayern",
    "wof:name":"Georg Haas",
    "wof:placetype":"venue"
},
  "geometry": {"coordinates":[11.154097,47.761402],"type":"Point"}
}