{
  "type": "Feature",
  "properties": {
    "iso:country":"DE",
    "sg:address":"Helzen 13",
    "sg:city":"Waldbr\u00f6l",
    "sg:phone":"+49 2292/1666",
    "sg:postcode":"51545",
    "sg:province":"Nordrhein-Westfalen",
    "wof:name":"Friedhofsverein Helzen- Vierbuchen",
    "wof:placetype":"venue"
},
  "geometry": {"coordinates":[7.6297101974,50.8305435181],"type":"Point"}
}