{
  "type": "Feature",
  "properties": {
    "iso:country":"DE",
    "sg:address":"Neuenhofstr. 112",
    "sg:city":"Aachen",
    "sg:phone":"+49 241/928390",
    "sg:postcode":"52078",
    "sg:province":"Nordrhein-Westfalen",
    "wof:name":"Prof. Dr. H. D\u00fcllmann Ingenieur",
    "wof:placetype":"venue"
},
  "geometry": {"coordinates":[6.145401001,50.7670936584],"type":"Point"}
}