{
  "type": "Feature",
  "properties": {
    "iso:country":"DE",
    "sg:address":"M\u00fchlweg 12",
    "sg:city":"Mainz",
    "sg:phone":"+49 6131/34727",
    "sg:postcode":"55128",
    "sg:province":"Rheinland-Pfalz",
    "wof:name":"Storchen-apotheke",
    "wof:placetype":"venue"
},
  "geometry": {"coordinates":[8.246623,49.981373],"type":"Point"}
}