{
  "type": "Feature",
  "properties": {
    "iso:country":"DE",
    "sg:address":"An der B 97",
    "sg:city":"K\u00f6nigsbr\u00fcck",
    "sg:postcode":"01936",
    "sg:province":"Sachsen",
    "wof:name":"Bay Wa Bhg Bau- Und Gartenmarkt",
    "wof:placetype":"venue"
},
  "geometry": {"coordinates":[13.9250173569,51.2818603516],"type":"Point"}
}