{
  "type": "Feature",
  "properties": {
    "iso:country":"DE",
    "sg:address":"Moorhof 2 b",
    "sg:city":"Hamburg",
    "sg:phone":"+49 40/6026013",
    "sg:postcode":"22399",
    "sg:province":"Hamburg",
    "wof:name":"Klaus F. Biesterfeldt Rechtsanwalt",
    "wof:placetype":"venue"
},
  "geometry": {"coordinates":[10.0855169296,53.661403656],"type":"Point"}
}