{
  "type": "Feature",
  "properties": {
    "iso:country":"DE",
    "sg:address":"Am Bahnhof 2",
    "sg:city":"Klein Meckelsen",
    "sg:phone":"+49 4282/95228",
    "sg:postcode":"27419",
    "sg:province":"Niedersachsen",
    "wof:name":"Dreyer Raumgestaltung",
    "wof:placetype":"venue"
},
  "geometry": {"coordinates":[9.448641,53.294071],"type":"Point"}
}