{
  "type": "Feature",
  "properties": {
    "iso:country":"DE",
    "sg:address":"Am Markt 12",
    "sg:city":"Penkun",
    "sg:phone":"+49 39751/60528",
    "sg:postcode":"17328",
    "sg:province":"Mecklenburg-Vorpommern",
    "wof:name":"B. Spanngenberg",
    "wof:placetype":"venue"
},
  "geometry": {"coordinates":[14.236594,53.296677],"type":"Point"}
}