{
  "type": "Feature",
  "properties": {
    "iso:country":"DE",
    "sg:address":"Ratiborstr. 14g",
    "sg:city":"Berlin",
    "sg:phone":"+49 30/6126714",
    "sg:postcode":"10999",
    "sg:province":"Berlin",
    "wof:name":"Otto Gleich",
    "wof:placetype":"venue"
},
  "geometry": {"coordinates":[13.438465,52.491951],"type":"Point"}
}