{
  "type": "Feature",
  "properties": {
    "iso:country":"DE",
    "sg:address":"Sudetenstr. 11",
    "sg:city":"Ruhmannsfelden",
    "sg:phone":"+49 9929/1240",
    "sg:postcode":"94239",
    "sg:province":"Bayern",
    "wof:name":"Gastst\u00e4tte Casablanca",
    "wof:placetype":"venue"
},
  "geometry": {"coordinates":[12.9880390167,48.9815711975],"type":"Point"}
}