{
  "type": "Feature",
  "properties": {
    "iso:country":"DE",
    "sg:address":"Efeuweg 23",
    "sg:city":"Speyer",
    "sg:postcode":"67346",
    "sg:province":"Rheinland-Pfalz",
    "wof:name":"Fws Schmidt Gmbh",
    "wof:placetype":"venue"
},
  "geometry": {"coordinates":[8.4310073853,49.3568840027],"type":"Point"}
}