{
  "type": "Feature",
  "properties": {
    "iso:country":"DE",
    "sg:address":"Ostenallee 138",
    "sg:city":"Hamm",
    "sg:phone":"+49 2381/82440",
    "sg:postcode":"59071",
    "sg:province":"Nordrhein-Westfalen",
    "wof:name":"Manfred Wierbr\u00fcgge",
    "wof:placetype":"venue"
},
  "geometry": {"coordinates":[7.8548469543,51.6909637451],"type":"Point"}
}