{
  "type": "Feature",
  "properties": {
    "iso:country":"DE",
    "sg:address":"Scharnhorststr. 56",
    "sg:city":"D\u00fcren",
    "sg:phone":"+49 2421/392682",
    "sg:postcode":"52351",
    "sg:province":"Nordrhein-Westfalen",
    "wof:name":"Bechir Hamza-damani Import-export-gro\u00dfhandel",
    "wof:placetype":"venue"
},
  "geometry": {"coordinates":[6.4948248863,50.8090019226],"type":"Point"}
}