{
  "type": "Feature",
  "properties": {
    "iso:country":"DE",
    "sg:address":"Habbr\u00fcgger Furth 11",
    "sg:city":"Ganderkesee",
    "sg:phone":"+49 4222/6439",
    "sg:postcode":"27777",
    "sg:province":"Niedersachsen",
    "wof:name":"Terracottahof",
    "wof:placetype":"venue"
},
  "geometry": {"coordinates":[8.503495,53.045883],"type":"Point"}
}