{
  "type": "Feature",
  "properties": {
    "iso:country":"DE",
    "sg:address":"Kaiserstr. 40",
    "sg:city":"Br\u00fchl",
    "sg:phone":"+49 2232/44688",
    "sg:postcode":"50321",
    "sg:province":"Nordrhein-Westfalen",
    "wof:name":"Werner W. K\u00f6hler Heilpraktiker",
    "wof:placetype":"venue"
},
  "geometry": {"coordinates":[6.9010739326,50.8344726562],"type":"Point"}
}