{
  "type": "Feature",
  "properties": {
    "iso:country":"DE",
    "sg:address":"Heidesheimer Str. 11",
    "sg:city":"Mainz",
    "sg:phone":"+49 6131/42727",
    "sg:postcode":"55124",
    "sg:province":"Rheinland-Pfalz",
    "wof:name":"Restaurant Zum Gutenberg",
    "wof:placetype":"venue"
},
  "geometry": {"coordinates":[8.2039756775,50.0005302429],"type":"Point"}
}