{
  "type": "Feature",
  "properties": {
    "iso:country":"DE",
    "sg:address":"Breslauer Str. 1b",
    "sg:city":"Ottersberg",
    "sg:phone":"+49 4205/1794",
    "sg:postcode":"28870",
    "sg:province":"Niedersachsen",
    "wof:name":"Uwe B\u00f6sch",
    "wof:placetype":"venue"
},
  "geometry": {"coordinates":[9.160634,53.105942],"type":"Point"}
}