{
  "type": "Feature",
  "properties": {
    "iso:country":"DE",
    "sg:address":"Kiebitzdeich 154",
    "sg:city":"Hamburg",
    "sg:phone":"+49 40/7235522",
    "sg:postcode":"21037",
    "sg:province":"Hamburg",
    "wof:name":"Hermann Loest",
    "wof:placetype":"venue"
},
  "geometry": {"coordinates":[10.230259,53.414337],"type":"Point"}
}