{
  "type": "Feature",
  "properties": {
    "iso:country":"DE",
    "sg:address":"Ringstr. 2",
    "sg:city":"Zehna",
    "sg:phone":"+49 38458/20221",
    "sg:postcode":"18276",
    "sg:province":"Mecklenburg-Vorpommern",
    "wof:name":"Zehnaer Landwirtschafts- Gesellschaft Eg",
    "wof:placetype":"venue"
},
  "geometry": {"coordinates":[12.141761,53.715282],"type":"Point"}
}