{
  "type": "Feature",
  "properties": {
    "iso:country":"DE",
    "sg:address":"Hauptstr. 63",
    "sg:city":"Gro\u00df Quenstedt",
    "sg:phone":"+49 39424/5848",
    "sg:postcode":"38822",
    "sg:province":"Sachsen-Anhalt",
    "wof:name":"Kindertagesst\u00e4tte",
    "wof:placetype":"venue"
},
  "geometry": {"coordinates":[11.1111917496,51.9269752502],"type":"Point"}
}