{
  "type": "Feature",
  "properties": {
    "iso:country":"DE",
    "sg:address":"Im Bad 28",
    "sg:city":"Sankt Peter-Ording",
    "sg:phone":"+49 4863/2729",
    "sg:postcode":"25826",
    "sg:province":"Schleswig-Holstein",
    "wof:name":"G\u00e4stehaus A. Meeder",
    "wof:placetype":"venue"
},
  "geometry": {"coordinates":[8.6086101532,54.3164596558],"type":"Point"}
}