{
  "type": "Feature",
  "properties": {
    "iso:country":"DE",
    "sg:address":"Lengericher Str. 16",
    "sg:city":"Ladbergen",
    "sg:phone":"+49 5485/2166",
    "sg:postcode":"49549",
    "sg:province":"Nordrhein-Westfalen",
    "wof:name":"Hans Rocklage",
    "wof:placetype":"venue"
},
  "geometry": {"coordinates":[7.749498,52.140755],"type":"Point"}
}