{
  "type": "Feature",
  "properties": {
    "iso:country":"DE",
    "sg:address":"D\u00fcrener Str. 89",
    "sg:city":"K\u00f6ln",
    "sg:phone":"+49 221/9403808",
    "sg:postcode":"50931",
    "sg:province":"Nordrhein-Westfalen",
    "wof:name":"Akcent International Property Consulting E. K.",
    "wof:placetype":"venue"
},
  "geometry": {"coordinates":[6.921505928,50.9326438904],"type":"Point"}
}