{
  "type": "Feature",
  "properties": {
    "iso:country":"DE",
    "sg:address":"Friedrich-Gl\u00fcck-Str 20",
    "sg:city":"Schorndorf",
    "sg:phone":"+49 7181/978330",
    "sg:postcode":"73614",
    "sg:province":"Baden-W\u00fcrttemberg",
    "wof:name":"Klip Ag",
    "wof:placetype":"venue"
},
  "geometry": {"coordinates":[9.5103311539,48.8305740356],"type":"Point"}
}