{
  "type": "Feature",
  "properties": {
    "iso:country":"DE",
    "sg:address":"T\u00f6pferstr. 11",
    "sg:city":"Bautzen",
    "sg:phone":"+49 3591/47472",
    "sg:postcode":"02625",
    "sg:province":"Sachsen",
    "wof:name":"G. Drechsel",
    "wof:placetype":"venue"
},
  "geometry": {"coordinates":[14.4287128448,51.1824455261],"type":"Point"}
}