{
  "type": "Feature",
  "properties": {
    "iso:country":"DE",
    "sg:address":"Kirchheimer Str. 98",
    "sg:city":"Wernau",
    "sg:phone":"+49 7153/31719",
    "sg:postcode":"73249",
    "sg:province":"Baden-W\u00fcrttemberg",
    "wof:name":"Central-apotheke",
    "wof:placetype":"venue"
},
  "geometry": {"coordinates":[9.421002,48.689281],"type":"Point"}
}