{
  "type": "Feature",
  "properties": {
    "iso:country":"DE",
    "sg:address":"Sturmb\u00fchlstr. 37",
    "sg:city":"Villingen-Schwenningen",
    "sg:phone":"+49 7720/33409",
    "sg:postcode":"78054",
    "sg:province":"Baden-W\u00fcrttemberg",
    "wof:name":"Reinhard K\u00f6llemann Steuerberater",
    "wof:placetype":"venue"
},
  "geometry": {"coordinates":[8.5330343246,48.0665168762],"type":"Point"}
}