{
  "type": "Feature",
  "properties": {
    "iso:country":"DE",
    "sg:address":"Lindenstr. 8",
    "sg:city":"Neckarwestheim",
    "sg:phone":"+49 7133/15313",
    "sg:postcode":"74382",
    "sg:province":"Baden-W\u00fcrttemberg",
    "wof:name":"Weing\u00e4rtner Neckarwestheim Eg",
    "wof:placetype":"venue"
},
  "geometry": {"coordinates":[9.193778038,49.046169281],"type":"Point"}
}