{
  "type": "Feature",
  "properties": {
    "iso:country":"DE",
    "sg:address":"Am Haselbach 4",
    "sg:city":"Bad Sassendorf",
    "sg:phone":"+49 2945/1339",
    "sg:postcode":"59505",
    "sg:province":"Nordrhein-Westfalen",
    "wof:name":"F. Hoffmeier",
    "wof:placetype":"venue"
},
  "geometry": {"coordinates":[8.1894226074,51.6186637878],"type":"Point"}
}