{
  "type": "Feature",
  "properties": {
    "iso:country":"DE",
    "sg:address":"Fischinger Str. 3",
    "sg:city":"Binzen",
    "sg:phone":"+49 7621/665806",
    "sg:postcode":"79589",
    "sg:province":"Baden-W\u00fcrttemberg",
    "wof:name":"Tauchring Dold",
    "wof:placetype":"venue"
},
  "geometry": {"coordinates":[7.620778,47.630707],"type":"Point"}
}