{
  "type": "Feature",
  "properties": {
    "iso:country":"DE",
    "sg:address":"Josefstr. 13",
    "sg:city":"Einhausen",
    "sg:phone":"+49 6251/53766",
    "sg:postcode":"64683",
    "sg:province":"Hessen",
    "wof:name":"Hans Schumacher",
    "wof:placetype":"venue"
},
  "geometry": {"coordinates":[8.541166,49.673561],"type":"Point"}
}