{
  "type": "Feature",
  "properties": {
    "iso:country":"DE",
    "sg:address":"Beckumer Str. 58",
    "sg:city":"Lippstadt",
    "sg:phone":"+49 2941/77148",
    "sg:postcode":"59555",
    "sg:province":"Nordrhein-Westfalen",
    "wof:name":"Ernst Ewers Zum Rode",
    "wof:placetype":"venue"
},
  "geometry": {"coordinates":[8.3350915909,51.6780509949],"type":"Point"}
}