{
  "type": "Feature",
  "properties": {
    "iso:country":"DE",
    "sg:address":"Hochfelder Str. 85",
    "sg:city":"Krefeld",
    "sg:postcode":"47809",
    "sg:province":"Nordrhein-Westfalen",
    "wof:name":"Bauunternehmung Bernhard Sch\u00fcler Gmbh",
    "wof:placetype":"venue"
},
  "geometry": {"coordinates":[6.60831,51.329414],"type":"Point"}
}