{
  "type": "Feature",
  "properties": {
    "iso:country":"DE",
    "sg:address":"Wildbader Str. 35",
    "sg:city":"Enzkl\u00f6sterle",
    "sg:phone":"+49 7085/7218",
    "sg:postcode":"75337",
    "sg:province":"Baden-W\u00fcrttemberg",
    "wof:name":"Peter Gulde Kg",
    "wof:placetype":"venue"
},
  "geometry": {"coordinates":[8.4751195908,48.6700515747],"type":"Point"}
}