{
  "type": "Feature",
  "properties": {
    "iso:country":"DE",
    "sg:address":"Am Wall 184",
    "sg:city":"Bremen",
    "sg:phone":"+49 421/320623",
    "sg:postcode":"28195",
    "sg:province":"Bremen",
    "wof:name":"Nordsee-zeitung",
    "wof:placetype":"venue"
},
  "geometry": {"coordinates":[8.8122720718,53.0758323669],"type":"Point"}
}