{
  "type": "Feature",
  "properties": {
    "iso:country":"DE",
    "sg:address":"Scherlebecker Str. 229",
    "sg:city":"Herten",
    "sg:phone":"+49 2366/494541",
    "sg:postcode":"45701",
    "sg:province":"Nordrhein-Westfalen",
    "wof:name":"Petra Blaschczok",
    "wof:placetype":"venue"
},
  "geometry": {"coordinates":[7.1431498528,51.615776062],"type":"Point"}
}