{
  "type": "Feature",
  "properties": {
    "iso:country":"DE",
    "sg:address":"Industriestr. 9",
    "sg:city":"Eislingen",
    "sg:phone":"+49 7161/85050",
    "sg:postcode":"73054",
    "sg:province":"Baden-W\u00fcrttemberg",
    "wof:name":"Mtd Marketing Gmbh",
    "wof:placetype":"venue"
},
  "geometry": {"coordinates":[9.696335,48.699211],"type":"Point"}
}