{
  "type": "Feature",
  "properties": {
    "iso:country":"DE",
    "sg:address":"Hamburger Str 181",
    "sg:city":"Hamburg",
    "sg:phone":"+49 40/6969470",
    "sg:postcode":"22083",
    "sg:province":"Hamburg",
    "wof:name":"Dako Diagnostika Gmbh",
    "wof:placetype":"venue"
},
  "geometry": {"coordinates":[10.038541,53.578419],"type":"Point"}
}