{
  "type": "Feature",
  "properties": {
    "iso:country":"DE",
    "sg:address":"Buldernweg 58",
    "sg:city":"M\u00fcnster",
    "sg:phone":"+49 251/785212",
    "sg:postcode":"48163",
    "sg:province":"Nordrhein-Westfalen",
    "wof:name":"Alwa Zelte Planenbau Gmbh",
    "wof:placetype":"venue"
},
  "geometry": {"coordinates":[7.5983448029,51.9267578125],"type":"Point"}
}