{
  "type": "Feature",
  "properties": {
    "iso:country":"DE",
    "sg:address":"H\u00fclsmannstr. 96",
    "sg:city":"Essen",
    "sg:phone":"+49 201/672402",
    "sg:postcode":"45355",
    "sg:province":"Nordrhein-Westfalen",
    "wof:name":"Pothmann",
    "wof:placetype":"venue"
},
  "geometry": {"coordinates":[6.9463610649,51.480846405],"type":"Point"}
}