{
  "type": "Feature",
  "properties": {
    "iso:country":"DE",
    "sg:address":"Steinfeldstr. 6",
    "sg:city":"Vienenburg",
    "sg:phone":"+49 5324/1609",
    "sg:postcode":"38690",
    "sg:province":"Niedersachsen",
    "wof:name":"Fg 16 Vienenburgwiedelah Bernd Mei\u00dfner",
    "wof:placetype":"venue"
},
  "geometry": {"coordinates":[10.5410413742,51.9508285522],"type":"Point"}
}