{
  "type": "Feature",
  "properties": {
    "iso:country":"DE",
    "sg:address":"Burgstr. 55",
    "sg:city":"Kinheim",
    "sg:phone":"+49 6532/2381",
    "sg:postcode":"54538",
    "sg:province":"Rheinland-Pfalz",
    "wof:name":"Hans Hoffmann Strickerei Und Textilien",
    "wof:placetype":"venue"
},
  "geometry": {"coordinates":[7.0539469719,49.9737739563],"type":"Point"}
}