{
  "type": "Feature",
  "properties": {
    "iso:country":"DE",
    "sg:address":"Am Rand 6",
    "sg:city":"Heidersdorf",
    "sg:phone":"+49 37361/4466",
    "sg:postcode":"09526",
    "sg:province":"Sachsen",
    "wof:name":"Gisela Weidensd\u00f6rfer Immobilienmaklerin",
    "wof:placetype":"venue"
},
  "geometry": {"coordinates":[13.4238014221,50.6737174988],"type":"Point"}
}