{
  "type": "Feature",
  "properties": {
    "iso:country":"DE",
    "sg:address":"Professor-Frosch-Str. 11",
    "sg:city":"Arnstadt",
    "sg:phone":"+49 3628/45189",
    "sg:postcode":"99310",
    "sg:province":"Th\u00fcringen",
    "wof:name":"Edda Neud\u00f6rfl",
    "wof:placetype":"venue"
},
  "geometry": {"coordinates":[10.9562673569,50.8258857727],"type":"Point"}
}