{
  "type": "Feature",
  "properties": {
    "iso:country":"DE",
    "sg:address":"Lange Str. 122",
    "sg:city":"Delmenhorst",
    "sg:phone":"+49 7151/609261",
    "sg:postcode":"27749",
    "sg:province":"Niedersachsen",
    "wof:name":"Druckerei Verlag R. Kuppinger Gmbh",
    "wof:placetype":"venue"
},
  "geometry": {"coordinates":[9.3653850555,48.8122634888],"type":"Point"}
}