{
  "type": "Feature",
  "properties": {
    "iso:country":"DE",
    "sg:address":"Mainzer Str. 38",
    "sg:city":"Raunheim",
    "sg:phone":"+49 6142/44591",
    "sg:postcode":"65479",
    "sg:province":"Hessen",
    "wof:name":"Steffen Kahlert Architekt",
    "wof:placetype":"venue"
},
  "geometry": {"coordinates":[8.448609,50.013489],"type":"Point"}
}