{
  "type": "Feature",
  "properties": {
    "iso:country":"DE",
    "sg:address":"Auf dem Hessel 25",
    "sg:city":"Erlensee",
    "sg:phone":"+49 6183/3046",
    "sg:postcode":"63526",
    "sg:province":"Hessen",
    "wof:name":"Orga B\u00fcromaschinen Handel Und Vertrieb Gmbh",
    "wof:placetype":"venue"
},
  "geometry": {"coordinates":[8.9771680832,50.1646194458],"type":"Point"}
}