{
  "type": "Feature",
  "properties": {
    "iso:country":"DE",
    "sg:address":"Hauptstr. 106",
    "sg:city":"Oldenburg",
    "sg:phone":"+49 441/508766",
    "sg:postcode":"26131",
    "sg:province":"Niedersachsen",
    "wof:name":"Heinz-georg Wehlau Gmbh",
    "wof:placetype":"venue"
},
  "geometry": {"coordinates":[8.190451622,53.1337165833],"type":"Point"}
}