{
  "type": "Feature",
  "properties": {
    "iso:country":"DE",
    "sg:address":"Franz-Schubert-Str. 1-3",
    "sg:city":"Duisburg",
    "sg:postcode":"47226",
    "sg:province":"Nordrhein-Westfalen",
    "wof:name":"Taxi Paetz Gmbh",
    "wof:placetype":"venue"
},
  "geometry": {"coordinates":[6.7226829529,51.4023551941],"type":"Point"}
}