{
  "type": "Feature",
  "properties": {
    "iso:country":"DE",
    "sg:address":"Parkstr. 30",
    "sg:city":"Trebbin",
    "sg:phone":"+49 33731/15377",
    "sg:postcode":"14959",
    "sg:province":"Brandenburg",
    "wof:name":"J\u00fcrgen Pfaender Gmbh",
    "wof:placetype":"venue"
},
  "geometry": {"coordinates":[13.228645,52.216946],"type":"Point"}
}