{
  "type": "Feature",
  "properties": {
    "iso:country":"DE",
    "sg:address":"Julius-Leber-Str. 23",
    "sg:city":"Bremen",
    "sg:phone":"+49 421/4675028",
    "sg:postcode":"28329",
    "sg:province":"Bremen",
    "wof:name":"Damasta",
    "wof:placetype":"venue"
},
  "geometry": {"coordinates":[8.8881988525,53.07604599],"type":"Point"}
}