{
  "type": "Feature",
  "properties": {
    "iso:country":"DE",
    "sg:address":"Antonienstr. 35",
    "sg:city":"Berlin",
    "sg:phone":"+49 30/9299567",
    "sg:postcode":"13403",
    "sg:province":"Berlin",
    "wof:name":"Mhm Herrmann Malerbetrieb Gmbh",
    "wof:placetype":"venue"
},
  "geometry": {"coordinates":[13.312748,52.574478],"type":"Point"}
}