{
  "type": "Feature",
  "properties": {
    "iso:country":"DE",
    "sg:address":"Pestalozziplatz 1",
    "sg:city":"Windischleuba",
    "sg:phone":"+49 3447/834471",
    "sg:postcode":"04603",
    "sg:province":"Th\u00fcringen",
    "wof:name":"Jugendherberge Windischleuba",
    "wof:placetype":"venue"
},
  "geometry": {"coordinates":[12.4724235535,51.016418457],"type":"Point"}
}