{
  "type": "Feature",
  "properties": {
    "iso:country":"DE",
    "sg:address":"B\u00fcrgermeister-Witter-Str. 4",
    "sg:city":"Ha\u00dfmersheim",
    "sg:postcode":"74855",
    "sg:province":"Baden-W\u00fcrttemberg",
    "wof:name":"Emil Prager",
    "wof:placetype":"venue"
},
  "geometry": {"coordinates":[9.144455,49.300381],"type":"Point"}
}