{
  "type": "Feature",
  "properties": {
    "iso:country":"DE",
    "sg:address":"Amselweg 3",
    "sg:city":"Mettmann",
    "sg:phone":"+49 2104/71324",
    "sg:postcode":"40822",
    "sg:province":"Nordrhein-Westfalen",
    "wof:name":"Wolfgang Haase Dipl.-ing.",
    "wof:placetype":"venue"
},
  "geometry": {"coordinates":[6.965077877,51.2415847778],"type":"Point"}
}