{
  "type": "Feature",
  "properties": {
    "iso:country":"DE",
    "sg:address":"Gr\u00fcnstr. 15",
    "sg:city":"D\u00fcsseldorf",
    "sg:phone":"+49 211/86228180",
    "sg:postcode":"40212",
    "sg:province":"Nordrhein-Westfalen",
    "wof:name":"Olbrich Tischkult Gmbh",
    "wof:placetype":"venue"
},
  "geometry": {"coordinates":[6.7805838585,51.2213668823],"type":"Point"}
}