{
  "type": "Feature",
  "properties": {
    "iso:country":"DE",
    "sg:address":"Pellenzstr. 17",
    "sg:city":"Andernach",
    "sg:phone":"+49 2632/6182",
    "sg:postcode":"56626",
    "sg:province":"Rheinland-Pfalz",
    "wof:name":"Willi Schmidt",
    "wof:placetype":"venue"
},
  "geometry": {"coordinates":[7.4072079659,50.3970413208],"type":"Point"}
}