{
  "type": "Feature",
  "properties": {
    "iso:country":"DE",
    "sg:address":"Spadener Str. 85",
    "sg:city":"Bremerhaven",
    "sg:postcode":"27578",
    "sg:province":"Bremen",
    "wof:name":"Sven Heinsohn Gmbh",
    "wof:placetype":"venue"
},
  "geometry": {"coordinates":[8.6046171188,53.5706062317],"type":"Point"}
}