{
  "type": "Feature",
  "properties": {
    "iso:country":"DE",
    "sg:address":"Marktstr. 16",
    "sg:city":"Weinstadt",
    "sg:phone":"+49 7151/690100",
    "sg:postcode":"71384",
    "sg:province":"Baden-W\u00fcrttemberg",
    "wof:name":"Anselm",
    "wof:placetype":"venue"
},
  "geometry": {"coordinates":[9.3874549866,48.8034172058],"type":"Point"}
}