{
  "type": "Feature",
  "properties": {
    "iso:country":"DE",
    "sg:address":"Arndtstr. 7",
    "sg:city":"Gummersbach",
    "sg:phone":"+49 2261/77532",
    "sg:postcode":"51645",
    "sg:province":"Nordrhein-Westfalen",
    "wof:name":"Klaus Stranzenbach",
    "wof:placetype":"venue"
},
  "geometry": {"coordinates":[7.524131,50.981625],"type":"Point"}
}