{
  "type": "Feature",
  "properties": {
    "iso:country":"DE",
    "sg:address":"Seminarstr. 4",
    "sg:city":"Heidelberg",
    "sg:postcode":"69117",
    "sg:province":"Baden-W\u00fcrttemberg",
    "wof:name":"Seminar F\u00fcr Osteurop\u00e4ische Geschichte",
    "wof:placetype":"venue"
},
  "geometry": {"coordinates":[8.7082796097,49.4098930359],"type":"Point"}
}