{
  "type": "Feature",
  "properties": {
    "iso:country":"DE",
    "sg:address":"Verbindungsweg 49",
    "sg:city":"Edewecht",
    "sg:phone":"+49 4486/1335",
    "sg:postcode":"26188",
    "sg:province":"Niedersachsen",
    "wof:name":"Gerhard Sommerfeld",
    "wof:placetype":"venue"
},
  "geometry": {"coordinates":[8.098724,53.116821],"type":"Point"}
}