{
  "type": "Feature",
  "properties": {
    "iso:country":"DE",
    "sg:address":"Am Markt",
    "sg:city":"Mosbach",
    "sg:phone":"+49 6261/60066",
    "sg:postcode":"74821",
    "sg:province":"Baden-W\u00fcrttemberg",
    "wof:name":"Hotel-restaurant Lindenhof",
    "wof:placetype":"venue"
},
  "geometry": {"coordinates":[9.146024704,49.3520050049],"type":"Point"}
}