{
  "type": "Feature",
  "properties": {
    "iso:country":"DE",
    "sg:address":"Rollnerstr. 43",
    "sg:city":"N\u00fcrnberg",
    "sg:phone":"+49 911/359111",
    "sg:postcode":"90408",
    "sg:province":"Bayern",
    "wof:name":"H\u00fcbsch Und Ramsauer Architekten",
    "wof:placetype":"venue"
},
  "geometry": {"coordinates":[11.081962,49.463497],"type":"Point"}
}