{
  "type": "Feature",
  "properties": {
    "iso:country":"DE",
    "sg:address":"Ochtruper Str. 92",
    "sg:city":"Gronau",
    "sg:phone":"+49 2562/2896",
    "sg:postcode":"48599",
    "sg:province":"Nordrhein-Westfalen",
    "wof:name":"Eduard Strootmann Alt- Und Abfallstoffe",
    "wof:placetype":"venue"
},
  "geometry": {"coordinates":[7.038952,52.207581],"type":"Point"}
}