{
  "type": "Feature",
  "properties": {
    "iso:country":"DE",
    "sg:address":"Kaulsdorfer Weg 6",
    "sg:city":"Kamsdorf",
    "sg:phone":"+49 3671/643113",
    "sg:postcode":"07334",
    "sg:province":"Th\u00fcringen",
    "wof:name":"Robert Leichauer",
    "wof:placetype":"venue"
},
  "geometry": {"coordinates":[11.44218,50.643181],"type":"Point"}
}