{
  "type": "Feature",
  "properties": {
    "iso:country":"DE",
    "sg:address":"Neipperger Str. 1",
    "sg:city":"Schwaigern",
    "sg:phone":"+49 7138/5971",
    "sg:postcode":"74193",
    "sg:province":"Baden-W\u00fcrttemberg",
    "wof:name":"Ri D\u00f6 Ko Inh. W. Rieger W. D\u00f6rr",
    "wof:placetype":"venue"
},
  "geometry": {"coordinates":[9.0623416901,49.13829422],"type":"Point"}
}