{
  "type": "Feature",
  "properties": {
    "iso:country":"DE",
    "sg:address":"Lazarus-Mannheimer-Str. 6",
    "sg:city":"Kehl",
    "sg:postcode":"77694",
    "sg:province":"Baden-W\u00fcrttemberg",
    "wof:name":"Trois Soleis S. A. R. L. Zweigniederlassung Kehl",
    "wof:placetype":"venue"
},
  "geometry": {"coordinates":[7.834549,48.56271],"type":"Point"}
}