{
  "type": "Feature",
  "properties": {
    "iso:country":"DE",
    "sg:address":"Stader Str. 107",
    "sg:city":"Hemmoor",
    "sg:phone":"+49 4947/7165110",
    "sg:postcode":"21745",
    "sg:province":"Niedersachsen",
    "wof:name":"Helmut Fritsche Kg",
    "wof:placetype":"venue"
},
  "geometry": {"coordinates":[9.1709861755,53.6877555847],"type":"Point"}
}