{
  "type": "Feature",
  "properties": {
    "iso:country":"DE",
    "sg:address":"Langenbeckstr. 3",
    "sg:city":"Wiesbaden",
    "sg:postcode":"65189",
    "sg:province":"Hessen",
    "wof:name":"Fachverband W\u00e4rmed\u00e4mm- Verbundsysteme E. V.",
    "wof:placetype":"venue"
},
  "geometry": {"coordinates":[8.255821228,50.0748558044],"type":"Point"}
}