{
  "type": "Feature",
  "properties": {
    "iso:country":"DE",
    "sg:address":"Alte Schulstr. 24",
    "sg:city":"K\u00fcrten",
    "sg:phone":"+49 2207/6275",
    "sg:postcode":"51515",
    "sg:province":"Nordrhein-Westfalen",
    "wof:name":"H. J. Wurth",
    "wof:placetype":"venue"
},
  "geometry": {"coordinates":[7.208591,51.039742],"type":"Point"}
}