{
  "type": "Feature",
  "properties": {
    "iso:country":"DE",
    "sg:address":"Moltkestr. 22",
    "sg:city":"Hof",
    "sg:phone":"+49 9281/2683",
    "sg:postcode":"95028",
    "sg:province":"Bayern",
    "wof:name":"Horst L\u00f6rner",
    "wof:placetype":"venue"
},
  "geometry": {"coordinates":[11.9222402573,50.3112030029],"type":"Point"}
}