{
  "type": "Feature",
  "properties": {
    "iso:country":"DE",
    "sg:address":"Kampstr. 2a",
    "sg:city":"Olsberg",
    "sg:phone":"+49 2962/97500",
    "sg:postcode":"59939",
    "sg:province":"Nordrhein-Westfalen",
    "wof:name":"Dr. Rieden Steuerberatungs Gmbh",
    "wof:placetype":"venue"
},
  "geometry": {"coordinates":[8.4908390045,51.3544845581],"type":"Point"}
}