{
  "type": "Feature",
  "properties": {
    "iso:country":"DE",
    "sg:address":"M\u00fchlenweg 21",
    "sg:city":"Oberstaufen",
    "sg:phone":"+49 8325/296",
    "sg:postcode":"87534",
    "sg:province":"Bayern",
    "wof:name":"Heinrich Sch\u00f6nberger Mineral\u00f6lvertrieb",
    "wof:placetype":"venue"
},
  "geometry": {"coordinates":[10.022749,47.554211],"type":"Point"}
}