{
  "type": "Feature",
  "properties": {
    "iso:country":"DE",
    "sg:address":"An der B 277",
    "sg:city":"A\u00dflar",
    "sg:phone":"+49 6443/82610",
    "sg:postcode":"35614",
    "sg:province":"Hessen",
    "wof:name":"Betonsteinwerk Willeck Zweigniederlassung Der",
    "wof:placetype":"venue"
},
  "geometry": {"coordinates":[8.4641122818,50.5896644592],"type":"Point"}
}