{
  "type": "Feature",
  "properties": {
    "iso:country":"DE",
    "sg:address":"Gro\u00dfe Friedberger Str. 13-17",
    "sg:city":"Frankfurt",
    "sg:postcode":"60313",
    "sg:province":"Hessen",
    "wof:name":"Fishn Ships Gmbh",
    "wof:placetype":"venue"
},
  "geometry": {"coordinates":[8.6862287521,50.1153182983],"type":"Point"}
}