{
  "type": "Feature",
  "properties": {
    "iso:country":"DE",
    "sg:address":"Beesener Str. 15",
    "sg:city":"Halle",
    "sg:postcode":"06110",
    "sg:province":"Sachsen-Anhalt",
    "wof:name":"Akazienhof-gemeinn. Heimges. Der Stadt Halle Saale",
    "wof:placetype":"venue"
},
  "geometry": {"coordinates":[11.968953,51.47049],"type":"Point"}
}