{
  "type": "Feature",
  "properties": {
    "iso:country":"DE",
    "sg:address":"Bruchwiesenstr. 31",
    "sg:city":"Oberursel",
    "sg:phone":"+49 6171/54578",
    "sg:postcode":"61440",
    "sg:province":"Hessen",
    "wof:name":"Alfons Schirmer Architekt",
    "wof:placetype":"venue"
},
  "geometry": {"coordinates":[8.597466,50.202705],"type":"Point"}
}