{
  "type": "Feature",
  "properties": {
    "iso:country":"DE",
    "sg:address":"Seewiesenweg 25b",
    "sg:city":"Bad Rappenau",
    "sg:postcode":"74906",
    "sg:province":"Baden-W\u00fcrttemberg",
    "wof:name":"Isopor Kunststoff Gmbh",
    "wof:placetype":"venue"
},
  "geometry": {"coordinates":[9.0014572144,49.2272491455],"type":"Point"}
}