{
  "type": "Feature",
  "properties": {
    "iso:country":"DE",
    "sg:address":"Neuh\u00e4user Str. 20",
    "sg:city":"Derental",
    "sg:phone":"+49 5273/37600",
    "sg:postcode":"37691",
    "sg:province":"Niedersachsen",
    "wof:name":"Sollingglas Bau Und Veredlungs Verwaltungs Gmbh",
    "wof:placetype":"venue"
},
  "geometry": {"coordinates":[9.438447,51.696457],"type":"Point"}
}