{
  "type": "Feature",
  "properties": {
    "iso:country":"DE",
    "sg:address":"Postfach 9545:: 97095 W\u00fcrzburg:: Germany.^^Theaterstr 26-28::",
    "sg:city":"W\u00fcrzburg",
    "sg:phone":"+49 931/30550",
    "sg:postcode":"97070",
    "sg:province":"Bayern",
    "wof:name":"Volksbank-raiffeisenbank W\u00fcrzburg Eg",
    "wof:placetype":"venue"
},
  "geometry": {"coordinates":[9.936415,49.792793],"type":"Point"}
}