{
  "type": "Feature",
  "properties": {
    "iso:country":"DE",
    "sg:address":"Lehestener Str. 8",
    "sg:city":"Wurzbach",
    "sg:postcode":"07343",
    "sg:province":"Th\u00fcringen",
    "wof:name":"Fachgesch\u00e4ft B\u00fcrobedarf",
    "wof:placetype":"venue"
},
  "geometry": {"coordinates":[11.536222,50.463055],"type":"Point"}
}