{
  "type": "Feature",
  "properties": {
    "iso:country":"DE",
    "sg:address":"Dr.-Prior-Str. 61",
    "sg:city":"Dillingen",
    "sg:phone":"+49 6831/73454",
    "sg:postcode":"66763",
    "sg:province":"Saarland",
    "wof:name":"Dr. Kurt Faber Architekt",
    "wof:placetype":"venue"
},
  "geometry": {"coordinates":[6.725122,49.359283],"type":"Point"}
}