{
  "type": "Feature",
  "properties": {
    "iso:country":"DE",
    "sg:address":"Oberer Markt 9",
    "sg:city":"Heroldsberg",
    "sg:phone":"+49 911/5181380",
    "sg:postcode":"90562",
    "sg:province":"Bayern",
    "wof:name":"Hilde Langenberger Wettannahme",
    "wof:placetype":"venue"
},
  "geometry": {"coordinates":[11.158724,49.534649],"type":"Point"}
}