{
  "type": "Feature",
  "properties": {
    "iso:country":"DE",
    "sg:address":"Bauernstr. 5",
    "sg:city":"Gersthofen",
    "sg:phone":"+49 821/493371",
    "sg:postcode":"86368",
    "sg:province":"Bayern",
    "wof:name":"H. Ask\u00e4r",
    "wof:placetype":"venue"
},
  "geometry": {"coordinates":[10.8805646896,48.4246406555],"type":"Point"}
}