{
  "type": "Feature",
  "properties": {
    "iso:country":"DE",
    "sg:address":"Karlstr. 29",
    "sg:city":"Petershagen",
    "sg:phone":"+49 33439/7107",
    "sg:postcode":"15370",
    "sg:province":"Brandenburg",
    "wof:name":"Heinz Jankowski",
    "wof:placetype":"venue"
},
  "geometry": {"coordinates":[13.796412,52.527012],"type":"Point"}
}