{
  "type": "Feature",
  "properties": {
    "iso:country":"DE",
    "sg:address":"Mittelweg 20",
    "sg:city":"Frankfurt",
    "sg:phone":"+49 69/590641",
    "sg:postcode":"60318",
    "sg:province":"Hessen",
    "wof:name":"Peter Herrmann Rechtsanwalt",
    "wof:placetype":"venue"
},
  "geometry": {"coordinates":[8.6840267181,50.1213569641],"type":"Point"}
}