{
  "type": "Feature",
  "properties": {
    "iso:country":"DE",
    "sg:address":"Allersberger Str 86",
    "sg:city":"N\u00fcrnberg",
    "sg:phone":"+49 911/4467729",
    "sg:postcode":"90402",
    "sg:province":"Bayern",
    "wof:name":"Deutsche Bank Ag",
    "wof:placetype":"venue"
},
  "geometry": {"coordinates":[11.090028,49.440147],"type":"Point"}
}