{
  "type": "Feature",
  "properties": {
    "iso:country":"DE",
    "sg:address":"Elisabeth-Lange-Weg 35",
    "sg:city":"Hamburg",
    "sg:phone":"+49 40/76910607",
    "sg:postcode":"21079",
    "sg:province":"Hamburg",
    "wof:name":"B\u00fcko B\u00fcro Komplett J\u00fcrgen Schmidt",
    "wof:placetype":"venue"
},
  "geometry": {"coordinates":[9.9923877716,53.4316444397],"type":"Point"}
}