{
  "type": "Feature",
  "properties": {
    "iso:country":"DE",
    "sg:address":"Tegelkuhl 10",
    "sg:city":"Schwarzenbek",
    "sg:postcode":"21493",
    "sg:province":"Schleswig-Holstein",
    "wof:name":"Ktv Komposttechnik Vertriebs- Gmbh",
    "wof:placetype":"venue"
},
  "geometry": {"coordinates":[10.485391,53.495689],"type":"Point"}
}