{
  "type": "Feature",
  "properties": {
    "iso:country":"DE",
    "sg:address":"Salierstr. 6",
    "sg:city":"Karlsruhe",
    "sg:phone":"+49 721/812179",
    "sg:postcode":"76137",
    "sg:province":"Baden-W\u00fcrttemberg",
    "wof:name":"Doris Stadler Steuerberaterin",
    "wof:placetype":"venue"
},
  "geometry": {"coordinates":[8.3888711929,48.9968719482],"type":"Point"}
}