{
  "type": "Feature",
  "properties": {
    "iso:country":"DE",
    "sg:address":"Hauptstr. 47",
    "sg:city":"Pei\u00dfenberg",
    "sg:phone":"+49 8803/3746",
    "sg:postcode":"82380",
    "sg:province":"Bayern",
    "wof:name":"Erika Spanner",
    "wof:placetype":"venue"
},
  "geometry": {"coordinates":[11.0730743408,47.8006706238],"type":"Point"}
}