{
  "type": "Feature",
  "properties": {
    "iso:country":"DE",
    "sg:address":"Blumenstr. 28",
    "sg:city":"Aschersleben",
    "sg:phone":"+49 3473/808789",
    "sg:postcode":"06449",
    "sg:province":"Sachsen-Anhalt",
    "wof:name":"Rosch Und Partner",
    "wof:placetype":"venue"
},
  "geometry": {"coordinates":[11.4713497162,51.7534294128],"type":"Point"}
}