{
  "type": "Feature",
  "properties": {
    "iso:country":"DE",
    "sg:address":"Schwabenstr. 4",
    "sg:city":"Memmingen",
    "sg:phone":"+49 8331/47001",
    "sg:postcode":"87700",
    "sg:province":"Bayern",
    "wof:name":"Gisela Mayer Gmbh",
    "wof:placetype":"venue"
},
  "geometry": {"coordinates":[10.1795406342,47.9986381531],"type":"Point"}
}