{
  "type": "Feature",
  "properties": {
    "iso:country":"DE",
    "sg:address":"Krefelder Str. 450",
    "sg:city":"M\u00f6nchengladbach",
    "sg:phone":"+49 2161/821930",
    "sg:postcode":"41066",
    "sg:province":"Nordrhein-Westfalen",
    "wof:name":"Bernards Immobilien",
    "wof:placetype":"venue"
},
  "geometry": {"coordinates":[6.4769258499,51.2180252075],"type":"Point"}
}