{
  "type": "Feature",
  "properties": {
    "iso:country":"DE",
    "sg:address":"Wilhelm-Stahl-Str. 7a",
    "sg:city":"Titisee-Neustadt",
    "sg:phone":"+49 7651/7018",
    "sg:postcode":"79822",
    "sg:province":"Baden-W\u00fcrttemberg",
    "wof:name":"Wilhelm Beck",
    "wof:placetype":"venue"
},
  "geometry": {"coordinates":[8.2133026123,47.9100227356],"type":"Point"}
}