{
  "type": "Feature",
  "properties": {
    "iso:country":"DE",
    "sg:address":"Holtbarg 19",
    "sg:city":"Hamburg",
    "sg:postcode":"22589",
    "sg:province":"Hamburg",
    "wof:name":"Lars Boettger Planungssoftware",
    "wof:placetype":"venue"
},
  "geometry": {"coordinates":[9.825735,53.583614],"type":"Point"}
}