{
  "type": "Feature",
  "properties": {
    "iso:country":"DE",
    "sg:address":"Hauptstr. 58",
    "sg:city":"Herbolzheim",
    "sg:phone":"+49 7643/1043",
    "sg:postcode":"79336",
    "sg:province":"Baden-W\u00fcrttemberg",
    "wof:name":"Ringwald",
    "wof:placetype":"venue"
},
  "geometry": {"coordinates":[7.7780108452,48.2207870483],"type":"Point"}
}