{
  "type": "Feature",
  "properties": {
    "iso:country":"DE",
    "sg:address":"Im Winkel 12",
    "sg:city":"Wennigsen",
    "sg:phone":"+49 5103/2267",
    "sg:postcode":"30974",
    "sg:province":"Niedersachsen",
    "wof:name":"Hanneliese Bleischwitz",
    "wof:placetype":"venue"
},
  "geometry": {"coordinates":[9.585377,52.25956],"type":"Point"}
}