{
  "type": "Feature",
  "properties": {
    "iso:country":"DE",
    "sg:address":"Bahnhofstr. 47",
    "sg:city":"Nidda",
    "sg:phone":"+49 6043/8888",
    "sg:postcode":"63667",
    "sg:province":"Hessen",
    "wof:name":"Vis-verwaltungs-immobilien- Und Servicegesellschaft Mbh",
    "wof:placetype":"venue"
},
  "geometry": {"coordinates":[9.0035448074,50.4122238159],"type":"Point"}
}