{
  "type": "Feature",
  "properties": {
    "iso:country":"DE",
    "sg:address":"Hauptstr. 32",
    "sg:city":"Elmenhorst/Lichtenhagen",
    "sg:phone":"+49 381/7697312",
    "sg:postcode":"18107",
    "sg:province":"Mecklenburg-Vorpommern",
    "wof:name":"Grimnitz-immobilien Gmbh",
    "wof:placetype":"venue"
},
  "geometry": {"coordinates":[12.01002,54.15744],"type":"Point"}
}