{
  "type": "Feature",
  "properties": {
    "iso:country":"DE",
    "sg:address":"Ritzefeldstra\u00dfe 27",
    "sg:city":"Stolberg",
    "sg:postcode":"52222",
    "sg:province":"Nordrhein-Westfalen",
    "wof:name":"Stolberg-info - Das Internet-portal F\u00fcr Stolberg-i",
    "wof:placetype":"venue"
},
  "geometry": {"coordinates":[6.228557,50.774464],"type":"Point"}
}