{
  "type": "Feature",
  "properties": {
    "iso:country":"DE",
    "sg:address":"Sachtlebenstr. 29 a",
    "sg:city":"Berlin",
    "sg:phone":"+49 30/7455881",
    "sg:postcode":"14165",
    "sg:province":"Berlin",
    "wof:name":"Rosmaria Werland",
    "wof:placetype":"venue"
},
  "geometry": {"coordinates":[13.2517566681,52.4144172668],"type":"Point"}
}