{
  "type": "Feature",
  "properties": {
    "iso:country":"DE",
    "sg:address":"L\u00e4mmerstr. 4",
    "sg:city":"M\u00fcnchen",
    "sg:postcode":"80335",
    "sg:province":"Bayern",
    "wof:name":"City Mitwohnzentrale Veronika Tertsch",
    "wof:placetype":"venue"
},
  "geometry": {"coordinates":[11.5591268539,48.1426086426],"type":"Point"}
}