{
  "type": "Feature",
  "properties": {
    "iso:country":"DE",
    "sg:address":"Ringstr. 19",
    "sg:city":"Arberg",
    "sg:phone":"+49 9822/1223",
    "sg:postcode":"91722",
    "sg:province":"Bayern",
    "wof:name":"Sparkasse Feuchtwangen",
    "wof:placetype":"venue"
},
  "geometry": {"coordinates":[10.618458,49.145096],"type":"Point"}
}