{
  "type": "Feature",
  "properties": {
    "iso:country":"DE",
    "sg:address":"Kenzelweg 39",
    "sg:city":"Friedrichshafen",
    "sg:phone":"+49 7541/51022",
    "sg:postcode":"88045",
    "sg:province":"Baden-W\u00fcrttemberg",
    "wof:name":"Deutscher Amateur-radio- Club E. V.",
    "wof:placetype":"venue"
},
  "geometry": {"coordinates":[9.4725656509,47.669342041],"type":"Point"}
}