{
  "type": "Feature",
  "properties": {
    "iso:country":"DE",
    "sg:address":"Am Wall 2",
    "sg:city":"Nienburg",
    "sg:phone":"+49 5021/9820",
    "sg:postcode":"31582",
    "sg:province":"Niedersachsen",
    "wof:name":"Wasser- U. Bodenverband Kreisverband F\u00fcr Wasserwirts.",
    "wof:placetype":"venue"
},
  "geometry": {"coordinates":[9.2332925797,52.6569976807],"type":"Point"}
}