{
  "type": "Feature",
  "properties": {
    "iso:country":"DE",
    "sg:address":"Hindenburgstr. 16",
    "sg:city":"Schwabach",
    "sg:phone":"+49 9122/2271",
    "sg:postcode":"91126",
    "sg:province":"Bayern",
    "wof:name":"Ott Gmbh & Co. Kg",
    "wof:placetype":"venue"
},
  "geometry": {"coordinates":[11.0200080872,49.3257789612],"type":"Point"}
}