{
  "type": "Feature",
  "properties": {
    "iso:country":"DE",
    "sg:address":"\u00c4u\u00dfere Industriestr. 17",
    "sg:city":"Friedberg",
    "sg:phone":"+49 821/279780",
    "sg:postcode":"86316",
    "sg:province":"Bayern",
    "wof:name":"Gna Ges F\u00dcr Nassaufbereitungstechnik Gmbh",
    "wof:placetype":"venue"
},
  "geometry": {"coordinates":[10.954955,48.410778],"type":"Point"}
}