{
  "type": "Feature",
  "properties": {
    "iso:country":"DE",
    "sg:address":"Schulstr. 16",
    "sg:city":"Gr\u00e4felfing",
    "sg:phone":"+49 89/853865",
    "sg:postcode":"82166",
    "sg:province":"Bayern",
    "wof:name":"Aris Annemarie Riedl Immobilienmaklerin",
    "wof:placetype":"venue"
},
  "geometry": {"coordinates":[11.435790062,48.1191101074],"type":"Point"}
}