{
  "type": "Feature",
  "properties": {
    "iso:country":"DE",
    "sg:address":"Kirschbaumer Str. 90",
    "sg:city":"Solingen",
    "sg:phone":"+49 212/204789",
    "sg:postcode":"42655",
    "sg:province":"Nordrhein-Westfalen",
    "wof:name":"Robert Ventura",
    "wof:placetype":"venue"
},
  "geometry": {"coordinates":[7.0690631866,51.1693763733],"type":"Point"}
}