{
  "type": "Feature",
  "properties": {
    "iso:country":"DE",
    "sg:address":"Enneper Str. 117",
    "sg:city":"Hagen",
    "sg:phone":"+49 2331/403239",
    "sg:postcode":"58135",
    "sg:province":"Nordrhein-Westfalen",
    "wof:name":"Heinz Flinkerbusch",
    "wof:placetype":"venue"
},
  "geometry": {"coordinates":[7.3952279091,51.3391227722],"type":"Point"}
}