{
  "type": "Feature",
  "properties": {
    "iso:country":"DE",
    "sg:address":"Pasteurstr. 32",
    "sg:city":"Berlin",
    "sg:phone":"+49 30/4255284",
    "sg:postcode":"10407",
    "sg:province":"Berlin",
    "wof:name":"Bernd Lau",
    "wof:placetype":"venue"
},
  "geometry": {"coordinates":[13.435787,52.532295],"type":"Point"}
}