{
  "type": "Feature",
  "properties": {
    "iso:country":"DE",
    "sg:address":"Alte Wipperf\u00fcrther Str. 2",
    "sg:city":"K\u00f6ln",
    "sg:phone":"+49 221/694606",
    "sg:postcode":"51065",
    "sg:province":"Nordrhein-Westfalen",
    "wof:name":"Ahl Wipp",
    "wof:placetype":"venue"
},
  "geometry": {"coordinates":[7.0140252113,50.9555587769],"type":"Point"}
}