{
  "type": "Feature",
  "properties": {
    "iso:country":"DE",
    "sg:address":"Kirchweg 3",
    "sg:city":"Braunschweig",
    "sg:phone":"+49 531/36688",
    "sg:postcode":"38104",
    "sg:province":"Niedersachsen",
    "wof:name":"Horst Winkler Automatenges. Mbh",
    "wof:placetype":"venue"
},
  "geometry": {"coordinates":[10.599377,52.29266],"type":"Point"}
}