{
  "type": "Feature",
  "properties": {
    "iso:country":"DE",
    "sg:address":"Gravelottestr. 8",
    "sg:city":"M\u00fcnchen",
    "sg:phone":"+49 89/3801720",
    "sg:postcode":"81667",
    "sg:province":"Bayern",
    "wof:name":"Dr. R\u00fcdiger M\u00fcller Ingenieur",
    "wof:placetype":"venue"
},
  "geometry": {"coordinates":[11.6006984711,48.1275024414],"type":"Point"}
}