{
  "type": "Feature",
  "properties": {
    "iso:country":"DE",
    "sg:address":"Asbeckstr. 16",
    "sg:city":"Essen",
    "sg:phone":"+49 201/663216",
    "sg:postcode":"45356",
    "sg:province":"Nordrhein-Westfalen",
    "wof:name":"Albert Stumpf",
    "wof:placetype":"venue"
},
  "geometry": {"coordinates":[6.976661,51.474743],"type":"Point"}
}