{
  "type": "Feature",
  "properties": {
    "iso:country":"DE",
    "sg:address":"Bruno-Frank-Weg 4a",
    "sg:city":"M\u00fcnchen",
    "sg:phone":"+49 89/1507394",
    "sg:postcode":"80995",
    "sg:province":"Bayern",
    "wof:name":"Christl Hustiak Anlageberater",
    "wof:placetype":"venue"
},
  "geometry": {"coordinates":[11.5311203003,48.1936302185],"type":"Point"}
}