{
  "type": "Feature",
  "properties": {
    "iso:country":"DE",
    "sg:address":"Springiersbacher Str. 15",
    "sg:city":"Bengel",
    "sg:phone":"+49 6532/2238",
    "sg:postcode":"54538",
    "sg:province":"Rheinland-Pfalz",
    "wof:name":"Franz J. Greis",
    "wof:placetype":"venue"
},
  "geometry": {"coordinates":[7.069395,50.019211],"type":"Point"}
}