{
  "type": "Feature",
  "properties": {
    "iso:country":"DE",
    "sg:address":"Rh\u00f6nhallenstr. 33",
    "sg:city":"Burkardroth",
    "sg:phone":"+49 9734/1433",
    "sg:postcode":"97705",
    "sg:province":"Bayern",
    "wof:name":"Albin Ke\u00dfler",
    "wof:placetype":"venue"
},
  "geometry": {"coordinates":[9.98291,50.287785],"type":"Point"}
}