{
  "type": "Feature",
  "properties": {
    "iso:country":"DE",
    "sg:address":"Winsener Str. 6",
    "sg:city":"Hanstedt",
    "sg:postcode":"21271",
    "sg:province":"Niedersachsen",
    "wof:name":"Br\u00fcckenapotheke Dr. Elke Beckmann E. K.",
    "wof:placetype":"venue"
},
  "geometry": {"coordinates":[10.01585,53.257721],"type":"Point"}
}