{
  "type": "Feature",
  "properties": {
    "iso:country":"DE",
    "sg:address":"Ringbahnstr. 15",
    "sg:city":"Berlin",
    "sg:phone":"+49 30/8913757",
    "sg:postcode":"10711",
    "sg:province":"Berlin",
    "wof:name":"Herkules-reinigung Adolf Umlauft",
    "wof:placetype":"venue"
},
  "geometry": {"coordinates":[13.289206,52.497807],"type":"Point"}
}