{
  "type": "Feature",
  "properties": {
    "iso:country":"DE",
    "sg:address":"Lindnerstr. 20",
    "sg:city":"Duisburg",
    "sg:phone":"+49 203/5180251",
    "sg:postcode":"47167",
    "sg:province":"Nordrhein-Westfalen",
    "wof:name":"Care Fliesen Gmbh",
    "wof:placetype":"venue"
},
  "geometry": {"coordinates":[6.8204760551,51.4950523376],"type":"Point"}
}