{
  "type": "Feature",
  "properties": {
    "iso:country":"DE",
    "sg:address":"Berliner Str. 3",
    "sg:city":"Bobenheim-Roxheim",
    "sg:phone":"+49 6239/6393",
    "sg:postcode":"67240",
    "sg:province":"Rheinland-Pfalz",
    "wof:name":"Ludwig Gress Hydraulik-service Gmbh",
    "wof:placetype":"venue"
},
  "geometry": {"coordinates":[8.360987,49.582493],"type":"Point"}
}