{
  "type": "Feature",
  "properties": {
    "iso:country":"DE",
    "sg:address":"Koblenzer Str. 12",
    "sg:city":"Wandlitz",
    "sg:postcode":"16348",
    "sg:province":"Brandenburg",
    "wof:name":"Wolfgang Haberland",
    "wof:placetype":"venue"
},
  "geometry": {"coordinates":[13.470125,52.762611],"type":"Point"}
}