{
  "type": "Feature",
  "properties": {
    "iso:country":"DE",
    "sg:address":"Hahnsteig 13",
    "sg:city":"Frickenhausen",
    "sg:phone":"+49 9331/5863",
    "sg:postcode":"97252",
    "sg:province":"Bayern",
    "wof:name":"Hartmut \u00d6der",
    "wof:placetype":"venue"
},
  "geometry": {"coordinates":[10.0771064758,49.6705932617],"type":"Point"}
}