{
  "type": "Feature",
  "properties": {
    "iso:country":"DE",
    "sg:address":"Alte Dorfstra\u00dfe 16",
    "sg:city":"Steinhagen",
    "sg:postcode":"18246",
    "sg:province":"Mecklenburg-Vorpommern",
    "wof:name":"Hansen Bau Gmbh",
    "wof:placetype":"venue"
},
  "geometry": {"coordinates":[11.9311609268,53.8450775146],"type":"Point"}
}