{
  "type": "Feature",
  "properties": {
    "iso:country":"DE",
    "sg:address":"Ludwigstr. 109",
    "sg:city":"Kempten",
    "sg:phone":"+49 831/63865",
    "sg:postcode":"87437",
    "sg:province":"Bayern",
    "wof:name":"Ludolf Holzer",
    "wof:placetype":"venue"
},
  "geometry": {"coordinates":[10.322957,47.702194],"type":"Point"}
}