{
  "type": "Feature",
  "properties": {
    "iso:country":"DE",
    "sg:address":"St. Annenstr. 10",
    "sg:city":"Quakenbr\u00fcck",
    "sg:phone":"+49 5431/3541",
    "sg:postcode":"49610",
    "sg:province":"Niedersachsen",
    "wof:name":"W. Ortland",
    "wof:placetype":"venue"
},
  "geometry": {"coordinates":[7.9580049515,52.6796989441],"type":"Point"}
}