{
  "type": "Feature",
  "properties": {
    "iso:country":"DE",
    "sg:address":"Alexanderstr. 136",
    "sg:city":"Stuttgart",
    "sg:phone":"+49 711/6490546",
    "sg:postcode":"70180",
    "sg:province":"Baden-W\u00fcrttemberg",
    "wof:name":"Orthofit Krankengymnastik Stuttgart Gmbh",
    "wof:placetype":"venue"
},
  "geometry": {"coordinates":[9.180044,48.767685],"type":"Point"}
}