{
  "type": "Feature",
  "properties": {
    "iso:country":"DE",
    "sg:address":"Wundstr. 66",
    "sg:city":"Berlin",
    "sg:phone":"+49 30/32604023",
    "sg:postcode":"14057",
    "sg:province":"Berlin",
    "wof:name":"Ecl - Envirotech Corporation Ltd.",
    "wof:placetype":"venue"
},
  "geometry": {"coordinates":[13.2845754623,52.5071868896],"type":"Point"}
}