{
  "type": "Feature",
  "properties": {
    "iso:country":"DE",
    "sg:address":"H\u00fcxstr. 43",
    "sg:city":"L\u00fcbeck",
    "sg:phone":"+49 451/74468",
    "sg:postcode":"23552",
    "sg:province":"Schleswig-Holstein",
    "wof:name":"Walter Reissenauer",
    "wof:placetype":"venue"
},
  "geometry": {"coordinates":[10.6885299683,53.8660697937],"type":"Point"}
}