{
  "type": "Feature",
  "properties": {
    "iso:country":"DE",
    "sg:address":"Ziegelstr. 60",
    "sg:city":"Plettenberg",
    "sg:phone":"+49 2391/12010",
    "sg:postcode":"58840",
    "sg:province":"Nordrhein-Westfalen",
    "wof:name":"Gerd Niederhagemann",
    "wof:placetype":"venue"
},
  "geometry": {"coordinates":[7.8659081459,51.2028541565],"type":"Point"}
}