{
  "type": "Feature",
  "properties": {
    "iso:country":"DE",
    "sg:address":"Stromberger Str. 113",
    "sg:city":"Beckum",
    "sg:phone":"+49 2521/4993",
    "sg:postcode":"59269",
    "sg:province":"Nordrhein-Westfalen",
    "wof:name":"Ottens",
    "wof:placetype":"venue"
},
  "geometry": {"coordinates":[8.0593767166,51.7570343018],"type":"Point"}
}