{
  "type": "Feature",
  "properties": {
    "iso:country":"DE",
    "sg:address":"M\u00fchlenstr. 2",
    "sg:city":"Bielefeld",
    "sg:phone":"+49 521/66663",
    "sg:postcode":"33607",
    "sg:province":"Nordrhein-Westfalen",
    "wof:name":"Tangente",
    "wof:placetype":"venue"
},
  "geometry": {"coordinates":[8.5464630127,52.0202407837],"type":"Point"}
}