{
  "type": "Feature",
  "properties": {
    "iso:country":"DE",
    "sg:address":"Adlerstr. 62-68",
    "sg:city":"Rellingen",
    "sg:phone":"+49 4101/28262",
    "sg:postcode":"25462",
    "sg:province":"Schleswig-Holstein",
    "wof:name":"Tcs Trans- Und Carservice Gmbh",
    "wof:placetype":"venue"
},
  "geometry": {"coordinates":[9.882611,53.627686],"type":"Point"}
}