{
  "type": "Feature",
  "properties": {
    "iso:country":"DE",
    "sg:address":"Bamberger Str. 55",
    "sg:city":"Hallstadt",
    "sg:phone":"+49 951/71353",
    "sg:postcode":"96103",
    "sg:province":"Bayern",
    "wof:name":"V. Gasseter",
    "wof:placetype":"venue"
},
  "geometry": {"coordinates":[10.874718,49.924976],"type":"Point"}
}