{
  "type": "Feature",
  "properties": {
    "iso:country":"DE",
    "sg:address":"Stift 1",
    "sg:city":"Ochtrup",
    "sg:phone":"+49 2553/1306",
    "sg:postcode":"48607",
    "sg:province":"Nordrhein-Westfalen",
    "wof:name":"Adolf Berghaus Grundst\u00fccksvermittlung",
    "wof:placetype":"venue"
},
  "geometry": {"coordinates":[7.2377448082,52.1974372864],"type":"Point"}
}