{
  "type": "Feature",
  "properties": {
    "iso:country":"DE",
    "sg:address":"Teckstr. 5",
    "sg:city":"Ofterdingen",
    "sg:phone":"+49 7473/3974",
    "sg:postcode":"72131",
    "sg:province":"Baden-W\u00fcrttemberg",
    "wof:name":"Gertraude Gerstorfer Rechtsanw\u00e4ltin",
    "wof:placetype":"venue"
},
  "geometry": {"coordinates":[9.0313072205,48.4235801697],"type":"Point"}
}