{
  "type": "Feature",
  "properties": {
    "iso:country":"DE",
    "sg:address":"Heinrich-Hertz-Str. 6",
    "sg:city":"Kerpen",
    "sg:phone":"+49 2273/570135",
    "sg:postcode":"50170",
    "sg:province":"Nordrhein-Westfalen",
    "wof:name":"Oeb Ges. F\u00fcr Organisation Und Edv Und Beratung Mbh",
    "wof:placetype":"venue"
},
  "geometry": {"coordinates":[6.6807432175,50.8915481567],"type":"Point"}
}