{
  "type": "Feature",
  "properties": {
    "iso:country":"DE",
    "sg:address":"Garchinger Str. 34",
    "sg:city":"M\u00fcnchen",
    "sg:phone":"+49 89/363593",
    "sg:postcode":"80805",
    "sg:province":"Bayern",
    "wof:name":"Alois Brodschelm",
    "wof:placetype":"venue"
},
  "geometry": {"coordinates":[11.6004915237,48.1775054932],"type":"Point"}
}