{
  "type": "Feature",
  "properties": {
    "iso:country":"DE",
    "sg:address":"Schlo\u00dfgasse 12",
    "sg:city":"Poppenhausen",
    "sg:phone":"+49 9725/4117",
    "sg:postcode":"97490",
    "sg:province":"Bayern",
    "wof:name":"Rudolf Massel",
    "wof:placetype":"venue"
},
  "geometry": {"coordinates":[10.1455593109,50.083366394],"type":"Point"}
}