{
  "type": "Feature",
  "properties": {
    "iso:country":"DE",
    "sg:address":"Gerhart-Hauptmann-Str. 37",
    "sg:city":"H\u00f6xter",
    "sg:phone":"+49 5271/32248",
    "sg:postcode":"37671",
    "sg:province":"Nordrhein-Westfalen",
    "wof:name":"E. Karsch",
    "wof:placetype":"venue"
},
  "geometry": {"coordinates":[9.3551988602,51.7692298889],"type":"Point"}
}