{
  "type": "Feature",
  "properties": {
    "iso:country":"DE",
    "sg:address":"H\u00fcttenweg 5",
    "sg:city":"Netphen",
    "sg:phone":"+49 4927/375040",
    "sg:postcode":"57250",
    "sg:province":"Nordrhein-Westfalen",
    "wof:name":"Walzen Irle Gmbh",
    "wof:placetype":"venue"
},
  "geometry": {"coordinates":[8.148828,50.884823],"type":"Point"}
}