{
  "type": "Feature",
  "properties": {
    "iso:country":"DE",
    "sg:address":"Am Horstbusch 24",
    "sg:city":"Rastede",
    "sg:phone":"+49 4402/1385",
    "sg:postcode":"26180",
    "sg:province":"Niedersachsen",
    "wof:name":"Evang. Gemeindeb\u00fccherei",
    "wof:placetype":"venue"
},
  "geometry": {"coordinates":[8.206215,53.256939],"type":"Point"}
}