{
  "type": "Feature",
  "properties": {
    "iso:country":"DE",
    "sg:address":"Glaubitzer Str. 1",
    "sg:city":"Zeithain",
    "sg:phone":"+49 4935/25790",
    "sg:postcode":"01619",
    "sg:province":"Sachsen",
    "wof:name":"Vallourec & Mannesmann Tubes V & M Deutschland Gmbh",
    "wof:placetype":"venue"
},
  "geometry": {"coordinates":[13.33598,51.320881],"type":"Point"}
}