{
  "type": "Feature",
  "properties": {
    "iso:country":"DE",
    "sg:address":"Hauptstr. 60",
    "sg:city":"S\u00f6llingen",
    "sg:phone":"+49 5354/1018",
    "sg:postcode":"38387",
    "sg:province":"Niedersachsen",
    "wof:name":"Steiniger",
    "wof:placetype":"venue"
},
  "geometry": {"coordinates":[10.92529,52.093258],"type":"Point"}
}