{
  "type": "Feature",
  "properties": {
    "iso:country":"DE",
    "sg:address":"Paderborner Str. 2",
    "sg:city":"Bad Driburg",
    "sg:phone":"+49 5259/526",
    "sg:postcode":"33014",
    "sg:province":"Nordrhein-Westfalen",
    "wof:name":"Provinzial Versicherung J. Und M. Osburg",
    "wof:placetype":"venue"
},
  "geometry": {"coordinates":[8.9934501648,51.6759796143],"type":"Point"}
}