{
  "type": "Feature",
  "properties": {
    "iso:country":"DE",
    "sg:address":"Berliner Str. 17",
    "sg:city":"Elsterwerda",
    "sg:phone":"+49 3533/2606",
    "sg:postcode":"04910",
    "sg:province":"Brandenburg",
    "wof:name":"H. Lehmann Steuerberater",
    "wof:placetype":"venue"
},
  "geometry": {"coordinates":[13.5210866928,51.4613952637],"type":"Point"}
}