{
  "type": "Feature",
  "properties": {
    "iso:country":"DE",
    "sg:address":"Tuchmacherweg 8",
    "sg:city":"Burgdorf",
    "sg:phone":"+49 5136/85463",
    "sg:postcode":"31303",
    "sg:province":"Niedersachsen",
    "wof:name":"Bernhard Aldag Isolierungen Gmbh",
    "wof:placetype":"venue"
},
  "geometry": {"coordinates":[10.044048,52.451618],"type":"Point"}
}