{
  "type": "Feature",
  "properties": {
    "iso:country":"DE",
    "sg:address":"Annalindestr. 2",
    "sg:city":"Heilbronn",
    "sg:phone":"+49 7066/7442",
    "sg:postcode":"74078",
    "sg:province":"Baden-W\u00fcrttemberg",
    "wof:name":"Erwin Rappold",
    "wof:placetype":"venue"
},
  "geometry": {"coordinates":[9.1144914627,49.1837844849],"type":"Point"}
}