{
  "type": "Feature",
  "properties": {
    "iso:country":"DE",
    "sg:address":"Richard-Klinger-Str. 8",
    "sg:city":"Idstein",
    "sg:phone":"+49 6126/9500",
    "sg:postcode":"65510",
    "sg:province":"Hessen",
    "wof:name":"Klinger Gmbh",
    "wof:placetype":"venue"
},
  "geometry": {"coordinates":[8.2581853867,50.2039642334],"type":"Point"}
}