{
  "type": "Feature",
  "properties": {
    "iso:country":"DE",
    "sg:address":"Schulstr. 53",
    "sg:city":"Bad Lauterberg",
    "sg:phone":"+49 5524/3124",
    "sg:postcode":"37431",
    "sg:province":"Niedersachsen",
    "wof:name":"K. Kleemann",
    "wof:placetype":"venue"
},
  "geometry": {"coordinates":[10.4679260254,51.6319770813],"type":"Point"}
}