{
  "type": "Feature",
  "properties": {
    "iso:country":"DE",
    "sg:address":"W\u00fcrmtalstr. 125",
    "sg:city":"M\u00fcnchen",
    "sg:postcode":"81375",
    "sg:province":"Bayern",
    "wof:name":"Hvw Focus Filmvertriebs Gmbh",
    "wof:placetype":"venue"
},
  "geometry": {"coordinates":[11.4757242203,48.1152648926],"type":"Point"}
}