{
  "type": "Feature",
  "properties": {
    "iso:country":"DE",
    "sg:address":"Bensheimer Str. 104-105",
    "sg:city":"Lorsch",
    "sg:postcode":"64653",
    "sg:province":"Hessen",
    "wof:name":"Jakobi Entsorgung Gmbh & Co. Kg",
    "wof:placetype":"venue"
},
  "geometry": {"coordinates":[8.56366,49.658829],"type":"Point"}
}