{
  "type": "Feature",
  "properties": {
    "iso:country":"DE",
    "sg:address":"Erlanger Str. 21a",
    "sg:city":"Kalchreuth",
    "sg:phone":"+49 911/5181314",
    "sg:postcode":"90562",
    "sg:province":"Bayern",
    "wof:name":"Heinz Key Ingenieur",
    "wof:placetype":"venue"
},
  "geometry": {"coordinates":[11.1271324158,49.5565719604],"type":"Point"}
}