{
  "type": "Feature",
  "properties": {
    "iso:country":"DE",
    "sg:address":"Schlo\u00dfstr. 33",
    "sg:city":"Alsdorf",
    "sg:phone":"+49 2404/65341",
    "sg:postcode":"52477",
    "sg:province":"Nordrhein-Westfalen",
    "wof:name":"M. Herzog",
    "wof:placetype":"venue"
},
  "geometry": {"coordinates":[6.1595611572,50.8792037964],"type":"Point"}
}