{
  "type": "Feature",
  "properties": {
    "iso:country":"DE",
    "sg:address":"Burghauser Str. 3",
    "sg:city":"Alt\u00f6tting",
    "sg:phone":"+49 8671/880623",
    "sg:postcode":"84503",
    "sg:province":"Bayern",
    "wof:name":"I. Palazzo",
    "wof:placetype":"venue"
},
  "geometry": {"coordinates":[12.6778211594,48.2247772217],"type":"Point"}
}