{
  "type": "Feature",
  "properties": {
    "iso:country":"DE",
    "sg:address":"An der Gro\u00dfen Br\u00fccke 1",
    "sg:city":"Kirn",
    "sg:phone":"+49 6752/8484",
    "sg:postcode":"55606",
    "sg:province":"Rheinland-Pfalz",
    "wof:name":"Br\u00fcckenschenke",
    "wof:placetype":"venue"
},
  "geometry": {"coordinates":[7.4559779167,49.7832221985],"type":"Point"}
}