{
  "type": "Feature",
  "properties": {
    "iso:country":"DE",
    "sg:address":"Hortweg 31",
    "sg:city":"Volkmarsen",
    "sg:postcode":"34471",
    "sg:province":"Hessen",
    "wof:name":"Karl Viering",
    "wof:placetype":"venue"
},
  "geometry": {"coordinates":[9.07702,51.403229],"type":"Point"}
}