{
  "type": "Feature",
  "properties": {
    "iso:country":"DE",
    "sg:address":"Julianenweg 6",
    "sg:city":"Regensburg",
    "sg:phone":"+49 941/760811",
    "sg:postcode":"93055",
    "sg:province":"Bayern",
    "wof:name":"R. Harting Frummet",
    "wof:placetype":"venue"
},
  "geometry": {"coordinates":[12.1392221451,48.9909706116],"type":"Point"}
}