{
  "type": "Feature",
  "properties": {
    "iso:country":"DE",
    "sg:address":"Gartenstr. 51",
    "sg:city":"Heddesheim",
    "sg:phone":"+49 6203/41233",
    "sg:postcode":"68542",
    "sg:province":"Baden-W\u00fcrttemberg",
    "wof:name":"Karl Thetmeyer",
    "wof:placetype":"venue"
},
  "geometry": {"coordinates":[8.6071853638,49.5070724487],"type":"Point"}
}