{
  "type": "Feature",
  "properties": {
    "iso:country":"DE",
    "sg:address":"Am Burgacker 30-42",
    "sg:city":"Duisburg",
    "sg:phone":"+49 203/99230",
    "sg:postcode":"47051",
    "sg:province":"Nordrhein-Westfalen",
    "wof:name":"Bremer & Leguil Gmbh",
    "wof:placetype":"venue"
},
  "geometry": {"coordinates":[6.767301,51.435326],"type":"Point"}
}