{
  "type": "Feature",
  "properties": {
    "iso:country":"DE",
    "sg:address":"Sch\u00fctzenkamp 4",
    "sg:city":"R\u00fcthen",
    "sg:phone":"+49 2952/701",
    "sg:postcode":"59602",
    "sg:province":"Nordrhein-Westfalen",
    "wof:name":"M\u00f6bel Gerits Gmbh",
    "wof:placetype":"venue"
},
  "geometry": {"coordinates":[8.408669,51.525635],"type":"Point"}
}