{
  "type": "Feature",
  "properties": {
    "iso:country":"DE",
    "sg:address":"Steinhof 49",
    "sg:city":"Erkrath",
    "sg:phone":"+49 211/2450100",
    "sg:postcode":"40699",
    "sg:province":"Nordrhein-Westfalen",
    "wof:name":"S&d-siebdruck Gmbh",
    "wof:placetype":"venue"
},
  "geometry": {"coordinates":[6.8964920044,51.2195396423],"type":"Point"}
}