{
  "type": "Feature",
  "properties": {
    "iso:country":"DE",
    "sg:address":"Ernst-L\u00e4ssig-Str 5",
    "sg:city":"Hartmannsdorf",
    "sg:phone":"+49 3722/6370",
    "sg:postcode":"09232",
    "sg:province":"Sachsen",
    "wof:name":"Schaudt Mikrosa Bwf Gmbh",
    "wof:placetype":"venue"
},
  "geometry": {"coordinates":[12.792777,50.895172],"type":"Point"}
}