{
  "type": "Feature",
  "properties": {
    "iso:country":"DE",
    "sg:address":"Goffineweg 29",
    "sg:city":"K\u00f6ln",
    "sg:phone":"+49 221/606410",
    "sg:postcode":"51069",
    "sg:province":"Nordrhein-Westfalen",
    "wof:name":"Dr. Med. G\u00fcnter Struck Arzt F\u00fcr Nervenheilkunde",
    "wof:placetype":"venue"
},
  "geometry": {"coordinates":[7.0310811996,51.0042915344],"type":"Point"}
}