{
  "type": "Feature",
  "properties": {
    "iso:country":"DE",
    "sg:address":"Jahnstr 2",
    "sg:city":"Unterf\u00f6hring",
    "sg:phone":"+49 89/9959050",
    "sg:postcode":"85774",
    "sg:province":"Bayern",
    "wof:name":"Claus Heinemann Elektroanlagen Gmbh",
    "wof:placetype":"venue"
},
  "geometry": {"coordinates":[11.648926,48.192638],"type":"Point"}
}