{
  "type": "Feature",
  "properties": {
    "iso:country":"DE",
    "sg:address":"Sch\u00e4fflerbachstr. 38",
    "sg:city":"Augsburg",
    "sg:phone":"+49 821/552079",
    "sg:postcode":"86153",
    "sg:province":"Bayern",
    "wof:name":"Is Birinci Gmbh",
    "wof:placetype":"venue"
},
  "geometry": {"coordinates":[10.9156103134,48.3611679077],"type":"Point"}
}