{
  "type": "Feature",
  "properties": {
    "iso:country":"DE",
    "sg:address":"Richard-Wagner-Str. 67",
    "sg:city":"Saarbruecken",
    "sg:phone":"+49 4968/134088",
    "sg:postcode":"66111",
    "sg:province":"Saarland",
    "wof:name":"Aranoltels Hotels",
    "wof:placetype":"venue"
},
  "geometry": {"coordinates":[7.0006728172,49.2372932434],"type":"Point"}
}