{
  "type": "Feature",
  "properties": {
    "iso:country":"DE",
    "sg:address":"Gildestr. 38",
    "sg:city":"Herzebrock-Clarholz",
    "sg:phone":"+49 5245/3206",
    "sg:postcode":"33442",
    "sg:province":"Nordrhein-Westfalen",
    "wof:name":"H. Westphal Jun",
    "wof:placetype":"venue"
},
  "geometry": {"coordinates":[8.242194,51.880825],"type":"Point"}
}