{
  "type": "Feature",
  "properties": {
    "iso:country":"DE",
    "sg:address":"Kirchplatz 11",
    "sg:city":"Drensteinfurt",
    "sg:phone":"+49 2508/1016",
    "sg:postcode":"48317",
    "sg:province":"Nordrhein-Westfalen",
    "wof:name":"Franke Und Rademacher Rechtsanw\u00e4lte Und Notare",
    "wof:placetype":"venue"
},
  "geometry": {"coordinates":[7.7419781685,51.7975158691],"type":"Point"}
}