{
  "type": "Feature",
  "properties": {
    "iso:country":"DE",
    "sg:address":"Selchertstr. 19",
    "sg:city":"Kr\u00f6v",
    "sg:phone":"+49 6541/2206",
    "sg:postcode":"54536",
    "sg:province":"Rheinland-Pfalz",
    "wof:name":"Valentin R\u00f6mer",
    "wof:placetype":"venue"
},
  "geometry": {"coordinates":[7.0829057693,49.9796600342],"type":"Point"}
}