{
  "type": "Feature",
  "properties": {
    "iso:country":"DE",
    "sg:address":"Sandforter Str. 4",
    "sg:city":"Olfen",
    "sg:phone":"+49 2595/1516",
    "sg:postcode":"59399",
    "sg:province":"Nordrhein-Westfalen",
    "wof:name":"H. Forsmann",
    "wof:placetype":"venue"
},
  "geometry": {"coordinates":[7.4115519524,51.7002296448],"type":"Point"}
}