{
  "type": "Feature",
  "properties": {
    "iso:country":"DE",
    "sg:address":"Sonnenring 2",
    "sg:city":"Altdorf",
    "sg:phone":"+49 871/32252",
    "sg:postcode":"84032",
    "sg:province":"Bayern",
    "wof:name":"Berger Gmbh",
    "wof:placetype":"venue"
},
  "geometry": {"coordinates":[12.100552,48.548817],"type":"Point"}
}