{
  "type": "Feature",
  "properties": {
    "iso:country":"DE",
    "sg:address":"Evenser Dorfstr. 17",
    "sg:city":"Sehlem",
    "sg:phone":"+49 5060/533",
    "sg:postcode":"31196",
    "sg:province":"Niedersachsen",
    "wof:name":"Wilhelm Feilcke",
    "wof:placetype":"venue"
},
  "geometry": {"coordinates":[10.003331,52.005871],"type":"Point"}
}