{
  "type": "Feature",
  "properties": {
    "iso:country":"DE",
    "sg:address":"Stoschstr. 6",
    "sg:city":"Kiel",
    "sg:phone":"+49 431/76867",
    "sg:postcode":"24143",
    "sg:province":"Schleswig-Holstein",
    "wof:name":"Klaus Reffke",
    "wof:placetype":"venue"
},
  "geometry": {"coordinates":[10.1490936279,54.3112220764],"type":"Point"}
}