{
  "type": "Feature",
  "properties": {
    "iso:country":"DE",
    "sg:address":"Fluderweg 21",
    "sg:city":"Vohenstrau\u00df",
    "sg:phone":"+49 9651/1080",
    "sg:postcode":"92648",
    "sg:province":"Bayern",
    "wof:name":"Josef Schmidt Grabdenkm\u00e4ler",
    "wof:placetype":"venue"
},
  "geometry": {"coordinates":[12.3428030014,49.6254501343],"type":"Point"}
}