{
  "type": "Feature",
  "properties": {
    "iso:country":"DE",
    "sg:address":"Pettenkoferplatz 1",
    "sg:city":"Berching",
    "sg:phone":"+49 8462/905060",
    "sg:postcode":"92334",
    "sg:province":"Bayern",
    "wof:name":"Hans Willax Grundst\u00fccksverwaltungs Gmbh",
    "wof:placetype":"venue"
},
  "geometry": {"coordinates":[11.4407043457,49.1063537598],"type":"Point"}
}