{
  "type": "Feature",
  "properties": {
    "iso:country":"DE",
    "sg:address":"Saarner Str. 66",
    "sg:city":"M\u00fclheim",
    "sg:phone":"+49 4920/8422366",
    "sg:postcode":"45481",
    "sg:province":"Nordrhein-Westfalen",
    "wof:name":"Peter Bru\u00df",
    "wof:placetype":"venue"
},
  "geometry": {"coordinates":[6.862811,51.410244],"type":"Point"}
}