{
  "type": "Feature",
  "properties": {
    "iso:country":"DE",
    "sg:address":"Pommernweg 19",
    "sg:city":"Schwedeneck",
    "sg:phone":"+49 4308/422",
    "sg:postcode":"24229",
    "sg:province":"Schleswig-Holstein",
    "wof:name":"Gerhard Steffen Pension",
    "wof:placetype":"venue"
},
  "geometry": {"coordinates":[10.075051,54.473309],"type":"Point"}
}