{
  "type": "Feature",
  "properties": {
    "iso:country":"DE",
    "sg:address":"Ortsstr. 1",
    "sg:city":"Hohenfels",
    "sg:phone":"+49 7557/363",
    "sg:postcode":"78355",
    "sg:province":"Baden-W\u00fcrttemberg",
    "wof:name":"E. Moser",
    "wof:placetype":"venue"
},
  "geometry": {"coordinates":[9.109322,47.885159],"type":"Point"}
}