{
  "type": "Feature",
  "properties": {
    "iso:country":"DE",
    "sg:address":"Wessenhorst 34",
    "sg:city":"Ennigerloh",
    "sg:phone":"+49 2585/7483",
    "sg:postcode":"59320",
    "sg:province":"Nordrhein-Westfalen",
    "wof:name":"Willi Dorgeist",
    "wof:placetype":"venue"
},
  "geometry": {"coordinates":[7.8941521645,51.8595619202],"type":"Point"}
}