{
  "type": "Feature",
  "properties": {
    "iso:country":"DE",
    "sg:address":"Bahnhofstr. 11-13",
    "sg:city":"Stadtallendorf",
    "sg:phone":"+49 6428/3048",
    "sg:postcode":"35260",
    "sg:province":"Hessen",
    "wof:name":"Baustoff-m\u00fcller Handels Gmbh & Co. Kg",
    "wof:placetype":"venue"
},
  "geometry": {"coordinates":[9.015955925,50.8285522461],"type":"Point"}
}