{
  "type": "Feature",
  "properties": {
    "iso:country":"DE",
    "sg:address":"Dorfstr. 35",
    "sg:city":"Gohrau",
    "sg:phone":"+49 34905/20534",
    "sg:postcode":"06786",
    "sg:province":"Sachsen-Anhalt",
    "wof:name":"Gottfried Wildgrube",
    "wof:placetype":"venue"
},
  "geometry": {"coordinates":[12.4859714508,51.8129844666],"type":"Point"}
}