{
  "type": "Feature",
  "properties": {
    "iso:country":"DE",
    "sg:address":"Epplestr. 50",
    "sg:city":"Stuttgart",
    "sg:phone":"+49 711/8105330",
    "sg:postcode":"70597",
    "sg:province":"Baden-W\u00fcrttemberg",
    "wof:name":"Communication 2000",
    "wof:placetype":"venue"
},
  "geometry": {"coordinates":[9.1689252853,48.7451324463],"type":"Point"}
}