{
  "type": "Feature",
  "properties": {
    "iso:country":"DE",
    "sg:address":"An den Tannen 17",
    "sg:city":"Usingen",
    "sg:phone":"+49 6081/13131",
    "sg:postcode":"61250",
    "sg:province":"Hessen",
    "wof:name":"Peter Peretzki Architekt",
    "wof:placetype":"venue"
},
  "geometry": {"coordinates":[8.475368,50.351734],"type":"Point"}
}