{
  "type": "Feature",
  "properties": {
    "iso:country":"DE",
    "sg:address":"Bonner Str. 68",
    "sg:city":"Sankt Augustin",
    "sg:phone":"+49 2241/330151",
    "sg:postcode":"53757",
    "sg:province":"Nordrhein-Westfalen",
    "wof:name":"Filmri\u00df Ot M\u00fclldorf",
    "wof:placetype":"venue"
},
  "geometry": {"coordinates":[7.196304,50.784348],"type":"Point"}
}