{
  "type": "Feature",
  "properties": {
    "iso:country":"DE",
    "sg:address":"Ravensburger Str. 30",
    "sg:city":"Markdorf",
    "sg:phone":"+49 7544/71777",
    "sg:postcode":"88677",
    "sg:province":"Baden-W\u00fcrttemberg",
    "wof:name":"Kurt F. Regitz Anlageberater",
    "wof:placetype":"venue"
},
  "geometry": {"coordinates":[9.3936929703,47.7194252014],"type":"Point"}
}