{
  "type": "Feature",
  "properties": {
    "iso:country":"DE",
    "sg:address":"Oberer Sand 9",
    "sg:city":"Passau",
    "sg:phone":"+49 851/34801",
    "sg:postcode":"94032",
    "sg:province":"Bayern",
    "wof:name":"Gaby Nigl Masseurin",
    "wof:placetype":"venue"
},
  "geometry": {"coordinates":[13.462324,48.572697],"type":"Point"}
}