{
  "type": "Feature",
  "properties": {
    "iso:country":"DE",
    "sg:address":"R\u00f6ntgenweg 1",
    "sg:city":"L\u00fcdenscheid",
    "sg:phone":"+49 2351/40488",
    "sg:postcode":"58515",
    "sg:province":"Nordrhein-Westfalen",
    "wof:name":"Gerhard Beckmann Patentanwalt",
    "wof:placetype":"venue"
},
  "geometry": {"coordinates":[7.6571969986,51.2057418823],"type":"Point"}
}