{
  "type": "Feature",
  "properties": {
    "iso:country":"DE",
    "sg:address":"Hauptstr. 12",
    "sg:city":"Gohlis",
    "sg:phone":"+49 3525/760729",
    "sg:postcode":"01619",
    "sg:province":"Sachsen",
    "wof:name":"Verm\u00f6gensberatung Tietz Joachim",
    "wof:placetype":"venue"
},
  "geometry": {"coordinates":[13.3197793961,51.3439598083],"type":"Point"}
}