{
  "type": "Feature",
  "properties": {
    "iso:country":"DE",
    "sg:address":"Zur Wasserm\u00fchle 1",
    "sg:city":"S\u00fcstedt",
    "sg:phone":"+49 4240/1058",
    "sg:postcode":"27305",
    "sg:province":"Niedersachsen",
    "wof:name":"Immobilienkontor Wasserm\u00fchle Gmbh",
    "wof:placetype":"venue"
},
  "geometry": {"coordinates":[8.9167327881,52.859703064],"type":"Point"}
}