{
  "type": "Feature",
  "properties": {
    "iso:country":"DE",
    "sg:address":"Kupferdreher Str. 173",
    "sg:city":"Essen",
    "sg:phone":"+49 201/485463",
    "sg:postcode":"45257",
    "sg:province":"Nordrhein-Westfalen",
    "wof:name":"Werner Thiel Gmbh",
    "wof:placetype":"venue"
},
  "geometry": {"coordinates":[7.083038,51.390228],"type":"Point"}
}