{
  "type": "Feature",
  "properties": {
    "iso:country":"DE",
    "sg:address":"Goethestr. 12",
    "sg:city":"Gornsdorf",
    "sg:phone":"+49 3721/22481",
    "sg:postcode":"09390",
    "sg:province":"Sachsen",
    "wof:name":"G. Uhlig",
    "wof:placetype":"venue"
},
  "geometry": {"coordinates":[12.890239,50.714333],"type":"Point"}
}