{
  "type": "Feature",
  "properties": {
    "iso:country":"DE",
    "sg:address":"Kirchbergstr. 7",
    "sg:city":"Bubsheim",
    "sg:phone":"+49 7429/891",
    "sg:postcode":"78585",
    "sg:province":"Baden-W\u00fcrttemberg",
    "wof:name":"Anna Petrich",
    "wof:placetype":"venue"
},
  "geometry": {"coordinates":[8.8268823624,48.1187400818],"type":"Point"}
}