{
  "type": "Feature",
  "properties": {
    "iso:country":"DE",
    "sg:address":"Geschwister-Scholl-Platz 1",
    "sg:city":"M\u00fcnchen",
    "sg:phone":"+49 89/21802323",
    "sg:postcode":"80539",
    "sg:province":"Bayern",
    "wof:name":"Institut F\u00fcr Biblische Exgese Bibliothek",
    "wof:placetype":"venue"
},
  "geometry": {"coordinates":[11.58042,48.150776],"type":"Point"}
}