{
  "type": "Feature",
  "properties": {
    "iso:country":"DE",
    "sg:address":"Fontenay 11",
    "sg:city":"Hamburg",
    "sg:phone":"+49 40/441464",
    "sg:postcode":"20354",
    "sg:province":"Hamburg",
    "wof:name":"Ariola Eurodisc Gmbh",
    "wof:placetype":"venue"
},
  "geometry": {"coordinates":[9.9966821671,53.5647201538],"type":"Point"}
}