{
  "type": "Feature",
  "properties": {
    "iso:country":"DE",
    "sg:address":"Weilbornstr. 22",
    "sg:city":"Dreieich",
    "sg:phone":"+49 6103/322060",
    "sg:postcode":"63303",
    "sg:province":"Hessen",
    "wof:name":"Helmut Hegen",
    "wof:placetype":"venue"
},
  "geometry": {"coordinates":[8.696783,50.023342],"type":"Point"}
}