{
  "type": "Feature",
  "properties": {
    "iso:country":"DE",
    "sg:address":"Im Wiesengrund 27",
    "sg:city":"Pr\u00fcm",
    "sg:phone":"+49 6551/4435",
    "sg:postcode":"54595",
    "sg:province":"Rheinland-Pfalz",
    "wof:name":"Klaus-dieter Fuchs Gmbh",
    "wof:placetype":"venue"
},
  "geometry": {"coordinates":[6.4156951904,50.1912612915],"type":"Point"}
}