{
  "type": "Feature",
  "properties": {
    "iso:country":"DE",
    "sg:address":"Wettersteinstr. 8",
    "sg:city":"Taufkirchen",
    "sg:phone":"+49 89/6147381",
    "sg:postcode":"82024",
    "sg:province":"Bayern",
    "wof:name":"A-mazing Shop Ohg",
    "wof:placetype":"venue"
},
  "geometry": {"coordinates":[11.6095170975,48.0317420959],"type":"Point"}
}