{
  "type": "Feature",
  "properties": {
    "iso:country":"DE",
    "sg:address":"Schillerstr. 28",
    "sg:city":"Dreieich",
    "sg:phone":"+49 6103/84883",
    "sg:postcode":"63303",
    "sg:province":"Hessen",
    "wof:name":"Nikolaus Geiger",
    "wof:placetype":"venue"
},
  "geometry": {"coordinates":[8.712276,50.002396],"type":"Point"}
}