{
  "type": "Feature",
  "properties": {
    "iso:country":"DE",
    "sg:address":"herkenbuscherweg 46",
    "sg:city":"grevenbroich",
    "sg:postcode":"41515",
    "sg:province":"Nordrhein-Westfalen",
    "wof:name":"Hoppeditz",
    "wof:placetype":"venue"
},
  "geometry": {"coordinates":[6.6057300568,51.0824737549],"type":"Point"}
}