{
  "type": "Feature",
  "properties": {
    "iso:country":"DE",
    "sg:address":"Reinsdorf 64 a",
    "sg:city":"Waldheim",
    "sg:phone":"+49 34327/91225",
    "sg:postcode":"04736",
    "sg:province":"Sachsen",
    "wof:name":"H. Gr\u00fcnheid",
    "wof:placetype":"venue"
},
  "geometry": {"coordinates":[12.96649,51.062469],"type":"Point"}
}