{
  "type": "Feature",
  "properties": {
    "iso:country":"DE",
    "sg:address":"Ursprunger Str. 26",
    "sg:city":"Oberlungwitz",
    "sg:phone":"+49 3723/41980",
    "sg:postcode":"09353",
    "sg:province":"Sachsen",
    "wof:name":"Zi Kaltumformung Verwaltungs Gmbh",
    "wof:placetype":"venue"
},
  "geometry": {"coordinates":[12.7668390274,50.788028717],"type":"Point"}
}