{
  "type": "Feature",
  "properties": {
    "iso:country":"DE",
    "sg:address":"An den Siffen 34",
    "sg:city":"Duisburg",
    "sg:phone":"+49 2151/409147",
    "sg:postcode":"47239",
    "sg:province":"Nordrhein-Westfalen",
    "wof:name":"Fritz Meyer Ingenieur",
    "wof:placetype":"venue"
},
  "geometry": {"coordinates":[6.6556248665,51.4048957825],"type":"Point"}
}