{
  "type": "Feature",
  "properties": {
    "iso:country":"DE",
    "sg:address":"Breitefeld 16",
    "sg:city":"M\u00fcnster",
    "sg:phone":"+49 6071/62248",
    "sg:postcode":"64839",
    "sg:province":"Hessen",
    "wof:name":"Seebold Dacharbeiten Gmbh",
    "wof:placetype":"venue"
},
  "geometry": {"coordinates":[8.8269796371,49.9293174744],"type":"Point"}
}