{
  "type": "Feature",
  "properties": {
    "iso:country":"DE",
    "sg:address":"Kronenstr. 5",
    "sg:city":"Oberndorf",
    "sg:phone":"+49 7423/3354",
    "sg:postcode":"78727",
    "sg:province":"Baden-W\u00fcrttemberg",
    "wof:name":"Hermann Altenburger",
    "wof:placetype":"venue"
},
  "geometry": {"coordinates":[8.57076931,48.2909698486],"type":"Point"}
}