{
  "type": "Feature",
  "properties": {
    "iso:country":"DE",
    "sg:address":"Bademer Str. 1",
    "sg:city":"Bitburg",
    "sg:phone":"+49 6561/3412",
    "sg:postcode":"54634",
    "sg:province":"Rheinland-Pfalz",
    "wof:name":"Johannes Alff Detektei",
    "wof:placetype":"venue"
},
  "geometry": {"coordinates":[6.528271,49.976906],"type":"Point"}
}