{
  "type": "Feature",
  "properties": {
    "iso:country":"DE",
    "sg:address":"Potsdamer Str. 67",
    "sg:city":"Berlin",
    "sg:phone":"+49 30/2613483",
    "sg:postcode":"10785",
    "sg:province":"Berlin",
    "wof:name":"Manfred Bohner",
    "wof:placetype":"venue"
},
  "geometry": {"coordinates":[13.365979,52.503254],"type":"Point"}
}