{
  "type": "Feature",
  "properties": {
    "iso:country":"DE",
    "sg:address":"Findelsgrund 46",
    "sg:city":"Porta Westfalica",
    "sg:phone":"+49 571/7989711",
    "sg:postcode":"32457",
    "sg:province":"Nordrhein-Westfalen",
    "wof:name":"Schulze Heimtierbedarf Gmbh",
    "wof:placetype":"venue"
},
  "geometry": {"coordinates":[8.9171142578,52.2308006287],"type":"Point"}
}