{
  "type": "Feature",
  "properties": {
    "iso:country":"DE",
    "sg:address":"Pastor-Heintze-Weg 1",
    "sg:city":"Schladen",
    "sg:phone":"+49 5335/1664",
    "sg:postcode":"38315",
    "sg:province":"Niedersachsen",
    "wof:name":"Ev. Pfarramt Wehre",
    "wof:placetype":"venue"
},
  "geometry": {"coordinates":[10.4994487762,52.0046005249],"type":"Point"}
}