{
  "type": "Feature",
  "properties": {
    "iso:country":"DE",
    "sg:address":"Alte Str. 46",
    "sg:city":"Frechen",
    "sg:phone":"+49 2234/56867",
    "sg:postcode":"50226",
    "sg:province":"Nordrhein-Westfalen",
    "wof:name":"Klein Wohnbau Gmbh",
    "wof:placetype":"venue"
},
  "geometry": {"coordinates":[6.8123869896,50.9109115601],"type":"Point"}
}