{
  "type": "Feature",
  "properties": {
    "iso:country":"DE",
    "sg:address":"Schlesierstr. 6a",
    "sg:city":"Schmitten",
    "sg:phone":"+49 6084/2196",
    "sg:postcode":"61389",
    "sg:province":"Hessen",
    "wof:name":"Helmut Wietschorke Architekt",
    "wof:placetype":"venue"
},
  "geometry": {"coordinates":[8.4394,50.269909],"type":"Point"}
}