{
  "type": "Feature",
  "properties": {
    "iso:country":"DE",
    "sg:address":"Kaiserstr. 30",
    "sg:city":"Lohnsfeld",
    "sg:phone":"+49 6302/982182",
    "sg:postcode":"67727",
    "sg:province":"Rheinland-Pfalz",
    "wof:name":"Zum Kaiserhof Inh. Manfred Borchadt",
    "wof:placetype":"venue"
},
  "geometry": {"coordinates":[7.8538208008,49.5513877869],"type":"Point"}
}