{
  "type": "Feature",
  "properties": {
    "iso:country":"DE",
    "sg:address":"Bahnhofstr. 34",
    "sg:city":"Kalkar",
    "sg:phone":"+49 2824/4443",
    "sg:postcode":"47546",
    "sg:province":"Nordrhein-Westfalen",
    "wof:name":"Storck",
    "wof:placetype":"venue"
},
  "geometry": {"coordinates":[6.2910590172,51.7345352173],"type":"Point"}
}