{
  "type": "Feature",
  "properties": {
    "iso:country":"DE",
    "sg:address":"Im Schachen 996",
    "sg:city":"Wadern",
    "sg:phone":"+49 6874/7075",
    "sg:postcode":"66687",
    "sg:province":"Saarland",
    "wof:name":"Psm Objektbauten Gmbh",
    "wof:placetype":"venue"
},
  "geometry": {"coordinates":[6.83219,49.497002],"type":"Point"}
}