{
  "type": "Feature",
  "properties": {
    "iso:country":"DE",
    "sg:address":"Marienborner Str. 100",
    "sg:city":"Mainz",
    "sg:phone":"+49 6131/368178",
    "sg:postcode":"55128",
    "sg:province":"Rheinland-Pfalz",
    "wof:name":"Daimler Chrysler Bank Gmbh",
    "wof:placetype":"venue"
},
  "geometry": {"coordinates":[8.238646,49.977978],"type":"Point"}
}