{
  "type": "Feature",
  "properties": {
    "iso:country":"DE",
    "sg:address":"Zur Butterleithe 10",
    "sg:city":"Zobes",
    "sg:phone":"+49 3741/413279",
    "sg:postcode":"08541",
    "sg:province":"Sachsen",
    "wof:name":"Henry Dietrich",
    "wof:placetype":"venue"
},
  "geometry": {"coordinates":[12.252403,50.512524],"type":"Point"}
}