{
  "type": "Feature",
  "properties": {
    "iso:country":"DE",
    "sg:address":"Lindenauallee 2",
    "sg:city":"Gotha",
    "sg:phone":"+49 3621/405715",
    "sg:postcode":"99867",
    "sg:province":"Th\u00fcringen",
    "wof:name":"U. Stichling",
    "wof:placetype":"venue"
},
  "geometry": {"coordinates":[10.702477,50.946693],"type":"Point"}
}