{
  "type": "Feature",
  "properties": {
    "iso:country":"DE",
    "sg:address":"Rungestr. 25",
    "sg:city":"Berlin",
    "sg:phone":"+49 30/2785475",
    "sg:postcode":"10179",
    "sg:province":"Berlin",
    "wof:name":"G\u00fcnter Meyer Handels- Und Finanzdienstleistungen E. K.",
    "wof:placetype":"venue"
},
  "geometry": {"coordinates":[13.4180727005,52.5125160217],"type":"Point"}
}