{
  "type": "Feature",
  "properties": {
    "iso:country":"DE",
    "sg:address":"Niebelsbacher Str. 8",
    "sg:city":"Birkenfeld",
    "sg:phone":"+49 7082/7696",
    "sg:postcode":"75217",
    "sg:province":"Baden-W\u00fcrttemberg",
    "wof:name":"Heinz Franke",
    "wof:placetype":"venue"
},
  "geometry": {"coordinates":[8.581859,48.871876],"type":"Point"}
}