{
  "type": "Feature",
  "properties": {
    "iso:country":"DE",
    "sg:address":"Stieglitzstr. 32",
    "sg:city":"Leipzig",
    "sg:phone":"+49 341/4801136",
    "sg:postcode":"04229",
    "sg:province":"Sachsen",
    "wof:name":"Georg Ambros Gross Architekt",
    "wof:placetype":"venue"
},
  "geometry": {"coordinates":[12.348024,51.320278],"type":"Point"}
}