{
  "type": "Feature",
  "properties": {
    "iso:country":"DE",
    "sg:address":"Gartenweg 4",
    "sg:city":"L\u00e4hden",
    "sg:phone":"+49 5432/3465",
    "sg:postcode":"49774",
    "sg:province":"Niedersachsen",
    "wof:name":"A. B\u00f6ckelmann",
    "wof:placetype":"venue"
},
  "geometry": {"coordinates":[7.569699,52.743729],"type":"Point"}
}