{
  "type": "Feature",
  "properties": {
    "iso:country":"DE",
    "sg:address":"L\u00fcbecker Str. 73",
    "sg:city":"Bad Oldesloe",
    "sg:phone":"+49 4531/1551",
    "sg:postcode":"23843",
    "sg:province":"Schleswig-Holstein",
    "wof:name":"Hbi Hanseatic Bau- Und Immobilien Kontor Gmbh",
    "wof:placetype":"venue"
},
  "geometry": {"coordinates":[10.385392,53.812389],"type":"Point"}
}