{
  "type": "Feature",
  "properties": {
    "iso:country":"DE",
    "sg:address":"Finsterwalder Str. 14",
    "sg:city":"Berlin",
    "sg:phone":"+49 30/40769900",
    "sg:postcode":"13435",
    "sg:province":"Berlin",
    "wof:name":"Hans-heiner Fromm Steuerberater",
    "wof:placetype":"venue"
},
  "geometry": {"coordinates":[13.3393115997,52.597694397],"type":"Point"}
}