{
  "type": "Feature",
  "properties": {
    "iso:country":"DE",
    "sg:address":"Juliusstr. 44 a",
    "sg:city":"K\u00f6ln",
    "sg:phone":"+49 221/816407",
    "sg:postcode":"51063",
    "sg:province":"Nordrhein-Westfalen",
    "wof:name":"Kurt Recker Architekt",
    "wof:placetype":"venue"
},
  "geometry": {"coordinates":[6.992734,50.951698],"type":"Point"}
}