{
  "type": "Feature",
  "properties": {
    "iso:country":"DE",
    "sg:address":"Postfach 182",
    "sg:city":"Sonneberg",
    "sg:postcode":"96502",
    "sg:province":"Th\u00fcringen",
    "wof:name":"S\u00fcdth\u00fcringer Brennstoff Gmbh",
    "wof:placetype":"venue"
},
  "geometry": {"coordinates":[11.1818799973,50.3568611145],"type":"Point"}
}