{
  "type": "Feature",
  "properties": {
    "iso:country":"DE",
    "sg:address":"Hauptstr. 32",
    "sg:city":"Wermelskirchen",
    "sg:phone":"+49 2196/80216",
    "sg:postcode":"42929",
    "sg:province":"Nordrhein-Westfalen",
    "wof:name":"Restaurant Zur Post",
    "wof:placetype":"venue"
},
  "geometry": {"coordinates":[7.2569642067,51.1093444824],"type":"Point"}
}