{
  "type": "Feature",
  "properties": {
    "iso:country":"DE",
    "sg:address":"Auf'm Kl\u00f6ppchen 1",
    "sg:city":"Glanbr\u00fccken",
    "sg:phone":"+49 6387/7489",
    "sg:postcode":"66887",
    "sg:province":"Rheinland-Pfalz",
    "wof:name":"Handels-contor Kaehl Gmbh",
    "wof:placetype":"venue"
},
  "geometry": {"coordinates":[7.5268611908,49.6146430969],"type":"Point"}
}