{
  "type": "Feature",
  "properties": {
    "iso:country":"DE",
    "sg:address":"Rehornweg 11",
    "sg:city":"Rastede",
    "sg:postcode":"26180",
    "sg:province":"Niedersachsen",
    "wof:name":"Georg Koch Gmbh & Co. Kg",
    "wof:placetype":"venue"
},
  "geometry": {"coordinates":[8.1785354614,53.2676200867],"type":"Point"}
}