{
  "type": "Feature",
  "properties": {
    "iso:country":"DE",
    "sg:address":"Elly-Heuss-Knapp-Ring 139",
    "sg:city":"Hamburg",
    "sg:postcode":"21035",
    "sg:province":"Hamburg",
    "wof:name":"Das Babyland",
    "wof:placetype":"venue"
},
  "geometry": {"coordinates":[10.165792,53.479687],"type":"Point"}
}