{
  "type": "Feature",
  "properties": {
    "iso:country":"DE",
    "sg:address":"An der Krebsburg 4",
    "sg:city":"Ostercappeln",
    "sg:phone":"+49 5473/92120",
    "sg:postcode":"49179",
    "sg:province":"Niedersachsen",
    "wof:name":"Verein F\u00fcr Heilp\u00e4dagogische Hilfe E. V.",
    "wof:placetype":"venue"
},
  "geometry": {"coordinates":[8.2071971893,52.3460998535],"type":"Point"}
}