{
  "type": "Feature",
  "properties": {
    "iso:country":"DE",
    "sg:address":"Sperl-Ring 4",
    "sg:city":"Pfaffenhofen/Ilm",
    "sg:phone":"+49 8441/788810",
    "sg:postcode":"85276",
    "sg:province":"Bayern",
    "wof:name":"Scm Pc-card Gmbh",
    "wof:placetype":"venue"
},
  "geometry": {"coordinates":[11.505592,48.500454],"type":"Point"}
}