{
  "type": "Feature",
  "properties": {
    "iso:country":"DE",
    "sg:address":"Busmannstr. 34",
    "sg:city":"Kevelaer",
    "sg:phone":"+49 2832/5292",
    "sg:postcode":"47623",
    "sg:province":"Nordrhein-Westfalen",
    "wof:name":"Hahlen",
    "wof:placetype":"venue"
},
  "geometry": {"coordinates":[6.243599,51.582214],"type":"Point"}
}