{
  "type": "Feature",
  "properties": {
    "iso:country":"DE",
    "sg:address":"Dorfstr. 9",
    "sg:city":"Icking",
    "sg:phone":"+49 8171/26191",
    "sg:postcode":"82057",
    "sg:province":"Bayern",
    "wof:name":"Gfms Gesellschaft F\u00fcr Modulare Software Mbh",
    "wof:placetype":"venue"
},
  "geometry": {"coordinates":[11.4095935822,47.9377403259],"type":"Point"}
}