{
  "type": "Feature",
  "properties": {
    "iso:country":"DE",
    "sg:address":"Falkenstra\u00dfe 5 e",
    "sg:city":"Barsb\u00fcttel",
    "sg:phone":"+49 40/67078335",
    "sg:postcode":"22885",
    "sg:province":"Schleswig-Holstein",
    "wof:name":"Wicke Entertainment Corp.",
    "wof:placetype":"venue"
},
  "geometry": {"coordinates":[10.16827,53.56905],"type":"Point"}
}