{
  "type": "Feature",
  "properties": {
    "iso:country":"DE",
    "sg:address":"K\u00f6nigsberger Str. 7",
    "sg:city":"Ostfildern",
    "sg:phone":"+49 711/3430123",
    "sg:postcode":"73760",
    "sg:province":"Baden-W\u00fcrttemberg",
    "wof:name":"Klaus-dieter Locher",
    "wof:placetype":"venue"
},
  "geometry": {"coordinates":[9.2783842087,48.725479126],"type":"Point"}
}