{
  "type": "Feature",
  "properties": {
    "iso:country":"DE",
    "sg:address":"Schulenburger Landstr. 113",
    "sg:city":"Hannover",
    "sg:phone":"+49 511/3521594",
    "sg:postcode":"30165",
    "sg:province":"Niedersachsen",
    "wof:name":"Jet-tankstelle",
    "wof:placetype":"venue"
},
  "geometry": {"coordinates":[9.7099542618,52.4069061279],"type":"Point"}
}