{
  "type": "Feature",
  "properties": {
    "iso:country":"DE",
    "sg:address":"Eichenwinkel 2",
    "sg:city":"Reinstorf",
    "sg:phone":"+49 4137/810100",
    "sg:postcode":"21400",
    "sg:province":"Niedersachsen",
    "wof:name":"K. Und B. Von Manteufel Zoege",
    "wof:placetype":"venue"
},
  "geometry": {"coordinates":[10.53692,53.244846],"type":"Point"}
}