{
  "type": "Feature",
  "properties": {
    "iso:country":"DE",
    "sg:address":"Killermannstr. 46",
    "sg:city":"Regensburg",
    "sg:phone":"+49 941/32101",
    "sg:postcode":"93049",
    "sg:province":"Bayern",
    "wof:name":"Wilhelm Kehrer",
    "wof:placetype":"venue"
},
  "geometry": {"coordinates":[12.0476236343,49.0167350769],"type":"Point"}
}