{
  "type": "Feature",
  "properties": {
    "iso:country":"DE",
    "sg:address":"Lindenring 7",
    "sg:city":"Naumburg",
    "sg:postcode":"06618",
    "sg:province":"Sachsen-Anhalt",
    "wof:name":"Bausparkasse Schw\u00e4bisch Hall Ag",
    "wof:placetype":"venue"
},
  "geometry": {"coordinates":[11.806236,51.152229],"type":"Point"}
}