{
  "type": "Feature",
  "properties": {
    "iso:country":"DE",
    "sg:address":"Elisabethstr. 74",
    "sg:city":"Berlin",
    "sg:phone":"+49 30/54801340",
    "sg:postcode":"12683",
    "sg:province":"Berlin",
    "wof:name":"Holger Grahl Immobilienmakler",
    "wof:placetype":"venue"
},
  "geometry": {"coordinates":[13.5603675842,52.5339736938],"type":"Point"}
}