{
  "type": "Feature",
  "properties": {
    "iso:country":"DE",
    "sg:address":"Windm\u00fchlenstr. 31",
    "sg:city":"Leipzig",
    "sg:phone":"+49 341/2117502",
    "sg:postcode":"04107",
    "sg:province":"Sachsen",
    "wof:name":"Gv Grundst\u00fccksver- Triebs Gmbh & Co. Kg",
    "wof:placetype":"venue"
},
  "geometry": {"coordinates":[12.3793754578,51.3319702148],"type":"Point"}
}