{
  "type": "Feature",
  "properties": {
    "iso:country":"DE",
    "sg:address":"Dammstr. 38",
    "sg:city":"Salzgitter",
    "sg:phone":"+49 5341/17075",
    "sg:postcode":"38229",
    "sg:province":"Niedersachsen",
    "wof:name":"Gala Hof",
    "wof:placetype":"venue"
},
  "geometry": {"coordinates":[10.3326673508,52.136302948],"type":"Point"}
}