{
  "type": "Feature",
  "properties": {
    "iso:country":"DE",
    "sg:address":"Kirchwerder Hausdeich 406",
    "sg:city":"Hamburg",
    "sg:phone":"+49 40/7230033",
    "sg:postcode":"21037",
    "sg:province":"Hamburg",
    "wof:name":"Baustoffhandel Werner Grube Gmbh",
    "wof:placetype":"venue"
},
  "geometry": {"coordinates":[10.2062692642,53.4146080017],"type":"Point"}
}