{
  "type": "Feature",
  "properties": {
    "iso:country":"DE",
    "sg:address":"Am Trappenberg 32",
    "sg:city":"Erkrath",
    "sg:postcode":"40699",
    "sg:province":"Nordrhein-Westfalen",
    "wof:name":"Eos Gmbh",
    "wof:placetype":"venue"
},
  "geometry": {"coordinates":[6.943995,51.212849],"type":"Point"}
}