{
  "type": "Feature",
  "properties": {
    "iso:country":"DE",
    "sg:address":"Pfaustr. 10",
    "sg:city":"Augsburg",
    "sg:phone":"+49 821/889401",
    "sg:postcode":"86179",
    "sg:province":"Bayern",
    "wof:name":"Chr. Angerbauer Bildhauer",
    "wof:placetype":"venue"
},
  "geometry": {"coordinates":[10.904637,48.309772],"type":"Point"}
}