{
  "type": "Feature",
  "properties": {
    "iso:country":"DE",
    "sg:address":"Bahnhofstr. 5 b",
    "sg:city":"Gersthofen",
    "sg:phone":"+49 821/2991104",
    "sg:postcode":"86368",
    "sg:province":"Bayern",
    "wof:name":"Praxis Direkt Gmbh",
    "wof:placetype":"venue"
},
  "geometry": {"coordinates":[10.8772106171,48.4250144958],"type":"Point"}
}