{
  "type": "Feature",
  "properties": {
    "iso:country":"DE",
    "sg:address":"Platanenstr. 5",
    "sg:city":"Nienburg",
    "sg:phone":"+49 5021/2361",
    "sg:postcode":"31582",
    "sg:province":"Niedersachsen",
    "wof:name":"Fritz J\u00e4ger Wolfgang J\u00e4ger",
    "wof:placetype":"venue"
},
  "geometry": {"coordinates":[9.2236623764,52.645526886],"type":"Point"}
}