{
  "type": "Feature",
  "properties": {
    "iso:country":"DE",
    "sg:address":"Arminiusstr. 30",
    "sg:city":"Gera",
    "sg:phone":"+49 365/7104328",
    "sg:postcode":"07548",
    "sg:province":"Th\u00fcringen",
    "wof:name":"A. Fr\u00f6hlich",
    "wof:placetype":"venue"
},
  "geometry": {"coordinates":[12.0718212128,50.8628540039],"type":"Point"}
}