{
  "type": "Feature",
  "properties": {
    "iso:country":"DE",
    "sg:address":"Hauptstr. 9",
    "sg:city":"Glash\u00fctte",
    "sg:phone":"+49 35053/49720",
    "sg:postcode":"01768",
    "sg:province":"Sachsen",
    "wof:name":"Petzold Handels Gmbh",
    "wof:placetype":"venue"
},
  "geometry": {"coordinates":[13.78115,50.852028],"type":"Point"}
}