{
  "type": "Feature",
  "properties": {
    "iso:country":"DE",
    "sg:address":"Schwerinstr. 69",
    "sg:city":"D\u00fcsseldorf",
    "sg:phone":"+49 211/492336",
    "sg:postcode":"40476",
    "sg:province":"Nordrhein-Westfalen",
    "wof:name":"A. Moritz",
    "wof:placetype":"venue"
},
  "geometry": {"coordinates":[6.7749199867,51.2445373535],"type":"Point"}
}