{
  "type": "Feature",
  "properties": {
    "iso:country":"DE",
    "sg:address":"Pontstr. 111",
    "sg:city":"Aachen",
    "sg:phone":"+49 241/21966",
    "sg:postcode":"52062",
    "sg:province":"Nordrhein-Westfalen",
    "wof:name":"Pizzeria Tutta Italia",
    "wof:placetype":"venue"
},
  "geometry": {"coordinates":[6.0801010132,50.780002594],"type":"Point"}
}