{
  "type": "Feature",
  "properties": {
    "iso:country":"DE",
    "sg:address":"Rappeneckweg 5",
    "sg:city":"Hinterzarten",
    "sg:phone":"+49 7652/1465",
    "sg:postcode":"79856",
    "sg:province":"Baden-W\u00fcrttemberg",
    "wof:name":"Ellen Hahn",
    "wof:placetype":"venue"
},
  "geometry": {"coordinates":[8.0972499847,47.9076538086],"type":"Point"}
}