{
  "type": "Feature",
  "properties": {
    "iso:country":"DE",
    "sg:address":"M\u00fchlenstr. 24",
    "sg:city":"Bad Zwischenahn",
    "sg:phone":"+49 4403/2270",
    "sg:postcode":"26160",
    "sg:province":"Niedersachsen",
    "wof:name":"Dr. Med. Uwe Paul",
    "wof:placetype":"venue"
},
  "geometry": {"coordinates":[7.997713089,53.1822814941],"type":"Point"}
}