{
  "type": "Feature",
  "properties": {
    "iso:country":"DE",
    "sg:address":"S\u00e4ggasse 10",
    "sg:city":"Polsingen",
    "sg:phone":"+49 9093/1235",
    "sg:postcode":"91805",
    "sg:province":"Bayern",
    "wof:name":"Karl Niemeyer",
    "wof:placetype":"venue"
},
  "geometry": {"coordinates":[10.7153625488,48.9385375977],"type":"Point"}
}