{
  "type": "Feature",
  "properties": {
    "iso:country":"DE",
    "sg:address":"Brookdamm 2",
    "sg:city":"Stuhr",
    "sg:phone":"+49 421/890151",
    "sg:postcode":"28816",
    "sg:province":"Niedersachsen",
    "wof:name":"Georg Dierks",
    "wof:placetype":"venue"
},
  "geometry": {"coordinates":[8.7276296616,53.0070037842],"type":"Point"}
}