{
  "type": "Feature",
  "properties": {
    "iso:country":"DE",
    "sg:address":"Mettmanner Str. 61",
    "sg:city":"W\u00fclfrath",
    "sg:phone":"+49 2058/913130",
    "sg:postcode":"42489",
    "sg:province":"Nordrhein-Westfalen",
    "wof:name":"Pflegeservice Vierjahreszeiten Gmbh",
    "wof:placetype":"venue"
},
  "geometry": {"coordinates":[7.027814,51.279629],"type":"Point"}
}