{
  "type": "Feature",
  "properties": {
    "iso:country":"DE",
    "sg:address":"Ernst-Th\u00e4lmann-Str. 28",
    "sg:city":"Vetschau",
    "sg:postcode":"03226",
    "sg:province":"Brandenburg",
    "wof:name":"Katholisches Pfarramt Vetschau",
    "wof:placetype":"venue"
},
  "geometry": {"coordinates":[14.0385303497,51.8182983398],"type":"Point"}
}