{
  "type": "Feature",
  "properties": {
    "iso:country":"DE",
    "sg:address":"Im Eck 5",
    "sg:city":"K\u00f6nigstein",
    "sg:phone":"+49 6174/5320",
    "sg:postcode":"61462",
    "sg:province":"Hessen",
    "wof:name":"K. Knuttel Kunstmaler",
    "wof:placetype":"venue"
},
  "geometry": {"coordinates":[8.462189,50.183998],"type":"Point"}
}