{
  "type": "Feature",
  "properties": {
    "iso:country":"DE",
    "sg:address":"Hochdorfer Str. 35",
    "sg:city":"Notzingen",
    "sg:phone":"+49 7021/45308",
    "sg:postcode":"73274",
    "sg:province":"Baden-W\u00fcrttemberg",
    "wof:name":"Kurt Kreuser",
    "wof:placetype":"venue"
},
  "geometry": {"coordinates":[9.455312,48.672523],"type":"Point"}
}