{
  "type": "Feature",
  "properties": {
    "iso:country":"DE",
    "sg:address":"Diederichsstr. 21",
    "sg:city":"Remscheid",
    "sg:phone":"+49 2191/26800",
    "sg:postcode":"42855",
    "sg:province":"Nordrhein-Westfalen",
    "wof:name":"Dirk Kirschbaum Anlageberater",
    "wof:placetype":"venue"
},
  "geometry": {"coordinates":[7.1890869141,51.1937103271],"type":"Point"}
}