{
  "type": "Feature",
  "properties": {
    "iso:country":"DE",
    "sg:address":"Werderstr. 30",
    "sg:city":"Baden-Baden",
    "sg:phone":"+49 7221/26386",
    "sg:postcode":"76530",
    "sg:province":"Baden-W\u00fcrttemberg",
    "wof:name":"G. Uschkurat Architekt",
    "wof:placetype":"venue"
},
  "geometry": {"coordinates":[8.230042,48.758602],"type":"Point"}
}