{
  "type": "Feature",
  "properties": {
    "iso:country":"DE",
    "sg:address":"Werastr. 42",
    "sg:city":"Friedrichshafen",
    "sg:phone":"+49 7541/92030",
    "sg:postcode":"88045",
    "sg:province":"Baden-W\u00fcrttemberg",
    "wof:name":"Compumac Computerver- Vertrieb Gmbh",
    "wof:placetype":"venue"
},
  "geometry": {"coordinates":[9.4664716721,47.65442276],"type":"Point"}
}