{
  "type": "Feature",
  "properties": {
    "iso:country":"DE",
    "sg:address":"Seumestr 135",
    "sg:city":"Leipzig",
    "sg:phone":"+49 341/4283342",
    "sg:postcode":"04249",
    "sg:province":"Sachsen",
    "wof:name":"Bowe & Vaal Gmbh",
    "wof:placetype":"venue"
},
  "geometry": {"coordinates":[12.312376976,51.2746124268],"type":"Point"}
}