{
  "type": "Feature",
  "properties": {
    "iso:country":"DE",
    "sg:address":"An der Koppel 22",
    "sg:city":"Norderstedt",
    "sg:phone":"+49 40/5263976",
    "sg:postcode":"22844",
    "sg:province":"Schleswig-Holstein",
    "wof:name":"Hermann Dohse",
    "wof:placetype":"venue"
},
  "geometry": {"coordinates":[9.9983873367,53.7398490906],"type":"Point"}
}