{
  "type": "Feature",
  "properties": {
    "iso:country":"DE",
    "sg:address":"Gro\u00dfostheimer Str. 189",
    "sg:city":"Aschaffenburg",
    "sg:phone":"+49 6021/83663",
    "sg:postcode":"63741",
    "sg:province":"Bayern",
    "wof:name":"Die Hand-in-hand-werker Gmbh",
    "wof:placetype":"venue"
},
  "geometry": {"coordinates":[9.1202,49.956326],"type":"Point"}
}