{
  "type": "Feature",
  "properties": {
    "iso:country":"DE",
    "sg:address":"Wagnerstr. 10",
    "sg:city":"Pforzheim",
    "sg:phone":"+49 4972/3122052",
    "sg:postcode":"75173",
    "sg:province":"Baden-W\u00fcrttemberg",
    "wof:name":"A. Odenwald",
    "wof:placetype":"venue"
},
  "geometry": {"coordinates":[8.6941576004,48.8874855042],"type":"Point"}
}