{
  "type": "Feature",
  "properties": {
    "iso:country":"DE",
    "sg:address":"Ber\u00dfener Str. 12",
    "sg:city":"L\u00e4hden",
    "sg:phone":"+49 5964/554",
    "sg:postcode":"49774",
    "sg:province":"Niedersachsen",
    "wof:name":"Paul Freese",
    "wof:placetype":"venue"
},
  "geometry": {"coordinates":[7.559061,52.745087],"type":"Point"}
}