{
  "type": "Feature",
  "properties": {
    "iso:country":"DE",
    "sg:address":"Sp\u00fcrkerau 23",
    "sg:city":"Erftstadt",
    "sg:phone":"+49 2235/44680",
    "sg:postcode":"50374",
    "sg:province":"Nordrhein-Westfalen",
    "wof:name":"Wolfgang Koch Rechtsanwalt",
    "wof:placetype":"venue"
},
  "geometry": {"coordinates":[6.8260588646,50.8104743958],"type":"Point"}
}