{
  "type": "Feature",
  "properties": {
    "iso:country":"DE",
    "sg:address":"Ernst-Tellering-Str. 13",
    "sg:city":"Langenfeld",
    "sg:phone":"+49 2173/28050",
    "sg:postcode":"40764",
    "sg:province":"Nordrhein-Westfalen",
    "wof:name":"D\u00fccker F\u00f6rdertechnik Gmbh",
    "wof:placetype":"venue"
},
  "geometry": {"coordinates":[6.95112,51.113384],"type":"Point"}
}