{
  "type": "Feature",
  "properties": {
    "iso:country":"DE",
    "sg:address":"Thomas-M\u00fcntzer-Str. 107a",
    "sg:city":"Hesserode",
    "sg:phone":"+49 3631/900460",
    "sg:postcode":"99735",
    "sg:province":"Th\u00fcringen",
    "wof:name":"Bernhardt",
    "wof:placetype":"venue"
},
  "geometry": {"coordinates":[10.7407264709,51.4831237793],"type":"Point"}
}