{
  "type": "Feature",
  "properties": {
    "iso:country":"DE",
    "sg:address":"Werderstr. 28",
    "sg:city":"Gerstetten",
    "sg:phone":"+49 7323/919363",
    "sg:postcode":"89547",
    "sg:province":"Baden-W\u00fcrttemberg",
    "wof:name":"Integ Gmbh",
    "wof:placetype":"venue"
},
  "geometry": {"coordinates":[10.0255708694,48.6232833862],"type":"Point"}
}