{
  "type": "Feature",
  "properties": {
    "iso:country":"DE",
    "sg:address":"Birkenweg 10",
    "sg:city":"Bad F\u00fcssing",
    "sg:phone":"+49 8531/21792",
    "sg:postcode":"94072",
    "sg:province":"Bayern",
    "wof:name":"Josef Resch Masseur",
    "wof:placetype":"venue"
},
  "geometry": {"coordinates":[13.314334,48.348598],"type":"Point"}
}