{
  "type": "Feature",
  "properties": {
    "iso:country":"DE",
    "sg:address":"Obere Dorfstr. 16",
    "sg:city":"Freiberg",
    "sg:phone":"+49 7141/707707",
    "sg:postcode":"71691",
    "sg:province":"Baden-W\u00fcrttemberg",
    "wof:name":"Thomas Miess Rechtsanwalt",
    "wof:placetype":"venue"
},
  "geometry": {"coordinates":[9.1871328354,48.9298782349],"type":"Point"}
}