{
  "type": "Feature",
  "properties": {
    "iso:country":"DE",
    "sg:address":"Husumer Str. 95",
    "sg:city":"Bielefeld",
    "sg:postcode":"33729",
    "sg:province":"Nordrhein-Westfalen",
    "wof:name":"Swinger Reisen Touristik Swingerclubs Swingertreff Party",
    "wof:placetype":"venue"
},
  "geometry": {"coordinates":[8.5971517563,52.0786437988],"type":"Point"}
}