{
  "type": "Feature",
  "properties": {
    "iso:country":"DE",
    "sg:address":"Klarastr. 1a",
    "sg:city":"Berlin",
    "sg:phone":"+49 30/53790036",
    "sg:postcode":"12459",
    "sg:province":"Berlin",
    "wof:name":"Koepenick.de - Das Bezirksmagazin",
    "wof:placetype":"venue"
},
  "geometry": {"coordinates":[13.5230264664,52.4603385925],"type":"Point"}
}