{
  "type": "Feature",
  "properties": {
    "iso:country":"DE",
    "sg:address":"Buchenh\u00f6he 1",
    "sg:city":"Kerpen",
    "sg:phone":"+49 2273/4961",
    "sg:postcode":"50169",
    "sg:province":"Nordrhein-Westfalen",
    "wof:name":"Franz Stokowy Steuerberater",
    "wof:placetype":"venue"
},
  "geometry": {"coordinates":[6.7279658318,50.9151649475],"type":"Point"}
}