{
  "type": "Feature",
  "properties": {
    "iso:country":"DE",
    "sg:address":"Arnulfstr. 44",
    "sg:city":"Augsburg",
    "sg:phone":"+49 821/542789",
    "sg:postcode":"86157",
    "sg:province":"Bayern",
    "wof:name":"Business Phone E. K.",
    "wof:placetype":"venue"
},
  "geometry": {"coordinates":[10.867073,48.357803],"type":"Point"}
}