{
  "type": "Feature",
  "properties": {
    "iso:country":"DE",
    "sg:address":"Metzgerstr. 4",
    "sg:city":"Offenburg",
    "sg:phone":"+49 781/9705750",
    "sg:postcode":"77652",
    "sg:province":"Baden-W\u00fcrttemberg",
    "wof:name":"Wohnhaus Gmbh",
    "wof:placetype":"venue"
},
  "geometry": {"coordinates":[7.9435567856,48.4701385498],"type":"Point"}
}