{
  "type": "Feature",
  "properties": {
    "iso:country":"DE",
    "sg:address":"Gatherweg 94",
    "sg:city":"D\u00fcsseldorf",
    "sg:phone":"+49 211/219819",
    "sg:postcode":"40231",
    "sg:province":"Nordrhein-Westfalen",
    "wof:name":"Edeltraut Steil Ladeneinrichtung Gmbh",
    "wof:placetype":"venue"
},
  "geometry": {"coordinates":[6.83019,51.210442],"type":"Point"}
}