{
  "type": "Feature",
  "properties": {
    "iso:country":"DE",
    "sg:address":"Gretelweg 3",
    "sg:city":"Dortmund",
    "sg:phone":"+49 231/857414",
    "sg:postcode":"44339",
    "sg:province":"Nordrhein-Westfalen",
    "wof:name":"Diakonische Dienste Dortmund Eving",
    "wof:placetype":"venue"
},
  "geometry": {"coordinates":[7.484014,51.556786],"type":"Point"}
}