{
  "type": "Feature",
  "properties": {
    "iso:country":"DE",
    "sg:address":"Am Sommerberg 20",
    "sg:city":"Lohr",
    "sg:phone":"+49 9352/503460",
    "sg:postcode":"97816",
    "sg:province":"Bayern",
    "wof:name":"Lohrer Selbsthilfe Ggmbh",
    "wof:placetype":"venue"
},
  "geometry": {"coordinates":[9.570235,49.989838],"type":"Point"}
}