{
  "type": "Feature",
  "properties": {
    "iso:country":"DE",
    "sg:address":"Hauptstr. 6",
    "sg:city":"Gehrden",
    "sg:phone":"+49 39247/428",
    "sg:postcode":"39264",
    "sg:province":"Sachsen-Anhalt",
    "wof:name":"E. Konstabel",
    "wof:placetype":"venue"
},
  "geometry": {"coordinates":[11.958652,52.011044],"type":"Point"}
}