{
  "type": "Feature",
  "properties": {
    "iso:country":"DE",
    "sg:address":"K\u00f6nigseestr. 43a",
    "sg:city":"Kolbermoor",
    "sg:phone":"+49 8031/92558",
    "sg:postcode":"83059",
    "sg:province":"Bayern",
    "wof:name":"Alfred Schlarb Bau Gmbh",
    "wof:placetype":"venue"
},
  "geometry": {"coordinates":[12.047542,47.836514],"type":"Point"}
}