{
  "type": "Feature",
  "properties": {
    "iso:country":"DE",
    "sg:address":"Linsenbergstr. 29",
    "sg:city":"Rottweil",
    "sg:phone":"+49 7427/3586",
    "sg:postcode":"78628",
    "sg:province":"Baden-W\u00fcrttemberg",
    "wof:name":"Elmar Forn",
    "wof:placetype":"venue"
},
  "geometry": {"coordinates":[8.708416,48.19162],"type":"Point"}
}