{
  "type": "Feature",
  "properties": {
    "iso:country":"DE",
    "sg:address":"Schulstr. 1",
    "sg:city":"Jarplund-Weding",
    "sg:postcode":"24941",
    "sg:province":"Schleswig-Holstein",
    "wof:name":"Arch-bau Architektur Und Bauen Gmbh & Co. Kg",
    "wof:placetype":"venue"
},
  "geometry": {"coordinates":[9.43847,54.74482],"type":"Point"}
}