{
  "type": "Feature",
  "properties": {
    "iso:country":"DE",
    "sg:address":"Mennekrath 8c",
    "sg:city":"Erkelenz",
    "sg:phone":"+49 2431/76320",
    "sg:postcode":"41812",
    "sg:province":"Nordrhein-Westfalen",
    "wof:name":"B\u00f6ttcher Private Altenpflege",
    "wof:placetype":"venue"
},
  "geometry": {"coordinates":[6.339997,51.090744],"type":"Point"}
}