{
  "type": "Feature",
  "properties": {
    "iso:country":"DE",
    "sg:address":"Steinreuther Str. 14b",
    "sg:city":"Bad F\u00fcssing",
    "sg:phone":"+49 8531/24628",
    "sg:postcode":"94072",
    "sg:province":"Bayern",
    "wof:name":"J\u00fcrgen Krause Ingenieur",
    "wof:placetype":"venue"
},
  "geometry": {"coordinates":[13.3090610504,48.3486747742],"type":"Point"}
}