{
  "type": "Feature",
  "properties": {
    "iso:country":"DE",
    "sg:address":"Neuenhofer Str. 101-103",
    "sg:city":"Solingen",
    "sg:phone":"+49 212/249130",
    "sg:postcode":"42657",
    "sg:province":"Nordrhein-Westfalen",
    "wof:name":"Franz F\u00fcrst Gmbh & Co. Kg",
    "wof:placetype":"venue"
},
  "geometry": {"coordinates":[7.0714669228,51.1576423645],"type":"Point"}
}