{
  "type": "Feature",
  "properties": {
    "iso:country":"DE",
    "sg:address":"K\u00f6nigsf\u00f6rder Str. 19",
    "sg:city":"Lindau",
    "sg:phone":"+49 4346/7657",
    "sg:postcode":"24214",
    "sg:province":"Schleswig-Holstein",
    "wof:name":"Jamesway Incubator Gmbh",
    "wof:placetype":"venue"
},
  "geometry": {"coordinates":[9.932111,54.391438],"type":"Point"}
}