{
  "type": "Feature",
  "properties": {
    "iso:country":"DE",
    "sg:address":"Dallgower Str. 9",
    "sg:city":"Berlin",
    "sg:phone":"+49 30/4917872",
    "sg:postcode":"13583",
    "sg:province":"Berlin",
    "wof:name":"H. Dehning",
    "wof:placetype":"venue"
},
  "geometry": {"coordinates":[13.187647,52.537083],"type":"Point"}
}