{
  "type": "Feature",
  "properties": {
    "iso:country":"DE",
    "sg:address":"Mozartstr. 12",
    "sg:city":"Bubenreuth",
    "sg:phone":"+49 9131/24164",
    "sg:postcode":"91088",
    "sg:province":"Bayern",
    "wof:name":"Andreas Gleissner Ohg",
    "wof:placetype":"venue"
},
  "geometry": {"coordinates":[11.0056419373,49.6216278076],"type":"Point"}
}