{
  "type": "Feature",
  "properties": {
    "iso:country":"DE",
    "sg:address":"Ferdinand-Porsche-Str. 7",
    "sg:city":"Ettlingen",
    "sg:phone":"+49 7243/54731",
    "sg:postcode":"76275",
    "sg:province":"Baden-W\u00fcrttemberg",
    "wof:name":"Ksk Guided Microtunneling Technologies Gmbh",
    "wof:placetype":"venue"
},
  "geometry": {"coordinates":[8.384141,48.937218],"type":"Point"}
}