{
  "type": "Feature",
  "properties": {
    "iso:country":"DE",
    "sg:address":"M\u00fchlenbachstr. 3",
    "sg:city":"Blomberg",
    "sg:phone":"+49 5236/213",
    "sg:postcode":"32825",
    "sg:province":"Nordrhein-Westfalen",
    "wof:name":"Erhard Plogstert",
    "wof:placetype":"venue"
},
  "geometry": {"coordinates":[9.019884,51.971107],"type":"Point"}
}