{
  "type": "Feature",
  "properties": {
    "iso:country":"DE",
    "sg:address":"Karl-Marx-Str. 25",
    "sg:city":"Brieskow-Finkenheerd",
    "sg:postcode":"15295",
    "sg:province":"Brandenburg",
    "wof:name":"G. Triebler Elektro",
    "wof:placetype":"venue"
},
  "geometry": {"coordinates":[14.625205,52.206322],"type":"Point"}
}