{
  "type": "Feature",
  "properties": {
    "iso:country":"DE",
    "sg:address":"Haustenbecker Str 173",
    "sg:city":"Augustdorf",
    "sg:phone":"+49 5237/5839",
    "sg:postcode":"32832",
    "sg:province":"Nordrhein-Westfalen",
    "wof:name":"Classen",
    "wof:placetype":"venue"
},
  "geometry": {"coordinates":[8.7340631485,51.8893203735],"type":"Point"}
}