{
  "type": "Feature",
  "properties": {
    "iso:country":"DE",
    "sg:address":"Fischerort 8",
    "sg:city":"Emmerich",
    "sg:phone":"+49 2822/70639",
    "sg:postcode":"46446",
    "sg:province":"Nordrhein-Westfalen",
    "wof:name":"F. Holtfort",
    "wof:placetype":"venue"
},
  "geometry": {"coordinates":[6.2428970337,51.8300857544],"type":"Point"}
}