{
  "type": "Feature",
  "properties": {
    "iso:country":"DE",
    "sg:address":"K\u00f6rnerstr. 4",
    "sg:city":"Bochum",
    "sg:phone":"+49 234/510000",
    "sg:postcode":"44791",
    "sg:province":"Nordrhein-Westfalen",
    "wof:name":"Der Medienpool Gmbh",
    "wof:placetype":"venue"
},
  "geometry": {"coordinates":[7.219701767,51.4874305725],"type":"Point"}
}