{
  "type": "Feature",
  "properties": {
    "iso:country":"DE",
    "sg:address":"Langenbergring 172",
    "sg:city":"Konz",
    "sg:phone":"+49 6501/5964",
    "sg:postcode":"54329",
    "sg:province":"Rheinland-Pfalz",
    "wof:name":"Rolf R\u00f6mer",
    "wof:placetype":"venue"
},
  "geometry": {"coordinates":[6.5902299881,49.698135376],"type":"Point"}
}