{
  "type": "Feature",
  "properties": {
    "iso:country":"DE",
    "sg:address":"N\u00fcrnberger Str. 34 - 36",
    "sg:city":"Burghaslach",
    "sg:phone":"+49 9552/7007",
    "sg:postcode":"96152",
    "sg:province":"Bayern",
    "wof:name":"Iftner Holzverarbeitung Gmbh & Co. Kg",
    "wof:placetype":"venue"
},
  "geometry": {"coordinates":[10.6027507782,49.7308883667],"type":"Point"}
}