{
  "type": "Feature",
  "properties": {
    "iso:country":"DE",
    "sg:address":"Hauptstr. 8",
    "sg:city":"Petershagen",
    "sg:phone":"+49 5707/8688",
    "sg:postcode":"32469",
    "sg:province":"Nordrhein-Westfalen",
    "wof:name":"China Restaurant Asia Garten",
    "wof:placetype":"venue"
},
  "geometry": {"coordinates":[8.9693517685,52.3780632019],"type":"Point"}
}