{
  "type": "Feature",
  "properties": {
    "iso:country":"DE",
    "sg:address":"Breite Str. 36",
    "sg:city":"Samswegen",
    "sg:phone":"+49 39202/60334",
    "sg:postcode":"39326",
    "sg:province":"Sachsen-Anhalt",
    "wof:name":"Heinz Kunkel",
    "wof:placetype":"venue"
},
  "geometry": {"coordinates":[11.567061,52.26038],"type":"Point"}
}