{
  "type": "Feature",
  "properties": {
    "iso:country":"DE",
    "sg:address":"Weygandtsweg 3",
    "sg:city":"Hattingen",
    "sg:phone":"+49 2324/52471",
    "sg:postcode":"45525",
    "sg:province":"Nordrhein-Westfalen",
    "wof:name":"Wilh. Pollmeier Steuerberater",
    "wof:placetype":"venue"
},
  "geometry": {"coordinates":[7.1805229187,51.3959236145],"type":"Point"}
}