{
  "type": "Feature",
  "properties": {
    "iso:country":"DE",
    "sg:address":"Pastor-Schmedes-Str. 5",
    "sg:city":"Springe",
    "sg:postcode":"31832",
    "sg:province":"Niedersachsen",
    "wof:name":"Kirchenkreisamt",
    "wof:placetype":"venue"
},
  "geometry": {"coordinates":[9.5604448318,52.2092590332],"type":"Point"}
}