{
  "type": "Feature",
  "properties": {
    "iso:country":"DE",
    "sg:address":"Dreifaltigkeitsbergstr. 17",
    "sg:city":"Spaichingen",
    "sg:phone":"+49 7424/2512",
    "sg:postcode":"78549",
    "sg:province":"Baden-W\u00fcrttemberg",
    "wof:name":"Robert Fischer Grabdenkm\u00e4ler",
    "wof:placetype":"venue"
},
  "geometry": {"coordinates":[8.7450237274,48.0749473572],"type":"Point"}
}