{
  "type": "Feature",
  "properties": {
    "iso:country":"DE",
    "sg:address":"Mettmanner Str. 163-165",
    "sg:city":"Velbert",
    "sg:phone":"+49 2051/21298",
    "sg:postcode":"42549",
    "sg:province":"Nordrhein-Westfalen",
    "wof:name":"Wilhelm Rees & S\u00f6hne Ohg",
    "wof:placetype":"venue"
},
  "geometry": {"coordinates":[7.0468869209,51.3249130249],"type":"Point"}
}