{
  "type": "Feature",
  "properties": {
    "iso:country":"DE",
    "sg:address":"Platter Str. 27 B",
    "sg:city":"Niedernhausen",
    "sg:phone":"+49 6127/5800",
    "sg:postcode":"65527",
    "sg:province":"Hessen",
    "wof:name":"Wiesel Montage- Und Einrichtungs Service Gmbh",
    "wof:placetype":"venue"
},
  "geometry": {"coordinates":[8.311619,50.15834],"type":"Point"}
}