{
  "type": "Feature",
  "properties": {
    "iso:country":"DE",
    "sg:address":"Spicherer Str. 43",
    "sg:city":"Kaiserslautern",
    "sg:phone":"+49 631/3504333",
    "sg:postcode":"67663",
    "sg:province":"Rheinland-Pfalz",
    "wof:name":"Datatronic Systemhaus Gmbh",
    "wof:placetype":"venue"
},
  "geometry": {"coordinates":[7.7279491425,49.436958313],"type":"Point"}
}