{
  "type": "Feature",
  "properties": {
    "iso:country":"DE",
    "sg:address":"Am Lornsenpark 31",
    "sg:city":"Schleswig",
    "sg:phone":"+49 4621/27180",
    "sg:postcode":"24837",
    "sg:province":"Schleswig-Holstein",
    "wof:name":"Global Sun Gmbh",
    "wof:placetype":"venue"
},
  "geometry": {"coordinates":[9.56665,54.51646],"type":"Point"}
}