{
  "type": "Feature",
  "properties": {
    "iso:country":"DE",
    "sg:address":"Josefstr. 60",
    "sg:city":"Marl",
    "sg:phone":"+49 2365/400",
    "sg:postcode":"45772",
    "sg:province":"Nordrhein-Westfalen",
    "wof:name":"Mevluet Deniz",
    "wof:placetype":"venue"
},
  "geometry": {"coordinates":[7.1390228271,51.6612358093],"type":"Point"}
}