{
  "type": "Feature",
  "properties": {
    "iso:country":"DE",
    "sg:address":"Steinbach 16",
    "sg:city":"Johanngeorgenstadt",
    "sg:phone":"+49 3773/882564",
    "sg:postcode":"08349",
    "sg:province":"Sachsen",
    "wof:name":"Max Hahn",
    "wof:placetype":"venue"
},
  "geometry": {"coordinates":[12.6828508377,50.4421844482],"type":"Point"}
}