{
  "type": "Feature",
  "properties": {
    "iso:country":"DE",
    "sg:address":"Bosenheimer Str. 99",
    "sg:city":"Bad Kreuznach",
    "sg:phone":"+49 671/68651",
    "sg:postcode":"55543",
    "sg:province":"Rheinland-Pfalz",
    "wof:name":"Rudolf Fey",
    "wof:placetype":"venue"
},
  "geometry": {"coordinates":[7.8736758232,49.8438148499],"type":"Point"}
}