{
  "type": "Feature",
  "properties": {
    "iso:country":"DE",
    "sg:address":"Solmser Gewerbepark",
    "sg:city":"Solms",
    "sg:phone":"+49 6442/1364",
    "sg:postcode":"35606",
    "sg:province":"Hessen",
    "wof:name":"Holzbau- Und S\u00e4gewerk Sch\u00fctz Ohg",
    "wof:placetype":"venue"
},
  "geometry": {"coordinates":[8.4129810333,50.5432510376],"type":"Point"}
}