{
  "type": "Feature",
  "properties": {
    "iso:country":"DE",
    "sg:address":"Vockenthal 31",
    "sg:city":"Dietmannsried",
    "sg:phone":"+49 8374/1420",
    "sg:postcode":"87463",
    "sg:province":"Bayern",
    "wof:name":"Hans K\u00f6pple Architekt",
    "wof:placetype":"venue"
},
  "geometry": {"coordinates":[10.29154,47.820293],"type":"Point"}
}