{
  "type": "Feature",
  "properties": {
    "iso:country":"DE",
    "sg:address":"Zum Wasserberg 3",
    "sg:city":"Salzkotten",
    "sg:phone":"+49 2955/1550",
    "sg:postcode":"33154",
    "sg:province":"Nordrhein-Westfalen",
    "wof:name":"N\u00fcbel Metalltechnik Gmbh",
    "wof:placetype":"venue"
},
  "geometry": {"coordinates":[8.6701850891,51.6385955811],"type":"Point"}
}