{
  "type": "Feature",
  "properties": {
    "iso:country":"DE",
    "sg:address":"Darmst\u00e4dter Str. 8",
    "sg:city":"Zwingenberg",
    "sg:phone":"+49 6251/79846",
    "sg:postcode":"64673",
    "sg:province":"Hessen",
    "wof:name":"J. Trautmann",
    "wof:placetype":"venue"
},
  "geometry": {"coordinates":[8.6122207642,49.7246856689],"type":"Point"}
}