{
  "type": "Feature",
  "properties": {
    "iso:country":"DE",
    "sg:address":"Abt-D\u00fcring-Str. 2",
    "sg:city":"Staffelstein",
    "sg:phone":"+49 9573/92230",
    "sg:postcode":"96231",
    "sg:province":"Bayern",
    "wof:name":"G. Und H. D\u00f6bert",
    "wof:placetype":"venue"
},
  "geometry": {"coordinates":[10.9834184647,50.1241149902],"type":"Point"}
}