{
  "type": "Feature",
  "properties": {
    "iso:country":"DE",
    "sg:address":"Lamontstr. 32",
    "sg:city":"Uebigau",
    "sg:postcode":"04938",
    "sg:province":"Brandenburg",
    "wof:name":"Architekten Rappmannsberger Rehle Und Partner",
    "wof:placetype":"venue"
},
  "geometry": {"coordinates":[13.3027973175,51.5960960388],"type":"Point"}
}