{
  "type": "Feature",
  "properties": {
    "iso:country":"DE",
    "sg:address":"Hauptstr. 45",
    "sg:city":"N\u00f6rten-Hardenberg",
    "sg:phone":"+49 5503/2288",
    "sg:postcode":"37176",
    "sg:province":"Niedersachsen",
    "wof:name":"Hans-joachim Resebeck Alt- Und Abfallstoffe",
    "wof:placetype":"venue"
},
  "geometry": {"coordinates":[9.899472,51.614201],"type":"Point"}
}