{
  "type": "Feature",
  "properties": {
    "iso:country":"DE",
    "sg:address":"Am Galgenberg 29",
    "sg:city":"Dillingen",
    "sg:phone":"+49 9071/9922",
    "sg:postcode":"89407",
    "sg:province":"Bayern",
    "wof:name":"Barbara Schrell Steuerberaterin",
    "wof:placetype":"venue"
},
  "geometry": {"coordinates":[10.51121521,48.5844650269],"type":"Point"}
}