{
  "type": "Feature",
  "properties": {
    "iso:country":"DE",
    "sg:address":"Gartenstr. 25",
    "sg:city":"Friolzheim",
    "sg:phone":"+49 7044/954570",
    "sg:postcode":"71292",
    "sg:province":"Baden-W\u00fcrttemberg",
    "wof:name":"Camporama Marketing Gmbh",
    "wof:placetype":"venue"
},
  "geometry": {"coordinates":[8.8399181366,48.8378791809],"type":"Point"}
}