{
  "type": "Feature",
  "properties": {
    "iso:country":"DE",
    "sg:address":"R\u00fcgenstr. 9",
    "sg:city":"Neum\u00fcnster",
    "sg:phone":"+49 4321/84437",
    "sg:postcode":"24539",
    "sg:province":"Schleswig-Holstein",
    "wof:name":"F. Friedrichs E. K.",
    "wof:placetype":"venue"
},
  "geometry": {"coordinates":[9.9734201431,54.0623931885],"type":"Point"}
}