{
  "type": "Feature",
  "properties": {
    "iso:country":"DE",
    "sg:address":"Geranienweg 4",
    "sg:city":"Nettetal",
    "sg:phone":"+49 2157/3305",
    "sg:postcode":"41334",
    "sg:province":"Nordrhein-Westfalen",
    "wof:name":"Janssen Spiel- Und Unter- Haltungsautomaten Gmbh",
    "wof:placetype":"venue"
},
  "geometry": {"coordinates":[6.277780056,51.306350708],"type":"Point"}
}