{
  "type": "Feature",
  "properties": {
    "iso:country":"DE",
    "sg:address":"Am M\u00e4rchen 28",
    "sg:city":"Leverkusen",
    "sg:phone":"+49 214/501594",
    "sg:postcode":"51375",
    "sg:province":"Nordrhein-Westfalen",
    "wof:name":"W. K\u00fcrten Architekt",
    "wof:placetype":"venue"
},
  "geometry": {"coordinates":[7.052782,51.027641],"type":"Point"}
}