{
  "type": "Feature",
  "properties": {
    "iso:country":"DE",
    "sg:address":"Kreuztaler Str. 5",
    "sg:city":"Netphen",
    "sg:phone":"+49 271/7420871",
    "sg:postcode":"57250",
    "sg:province":"Nordrhein-Westfalen",
    "wof:name":"Modellbau Michael Schweidler E. K.",
    "wof:placetype":"venue"
},
  "geometry": {"coordinates":[8.0611782074,50.9172782898],"type":"Point"}
}