{
  "type": "Feature",
  "properties": {
    "iso:country":"DE",
    "sg:address":"Bachstra\u00dfe 28",
    "sg:city":"Walddorfh\u00e4slach",
    "sg:phone":"+49 7127/922560",
    "sg:postcode":"72141",
    "sg:province":"Baden-W\u00fcrttemberg",
    "wof:name":"@rtmedia Interaktive Medien Gbrmbh Walddorfh\u00e4slach",
    "wof:placetype":"venue"
},
  "geometry": {"coordinates":[9.1830854416,48.5880508423],"type":"Point"}
}