{
  "type": "Feature",
  "properties": {
    "iso:country":"DE",
    "sg:address":"Weinheimer Str. 74 a",
    "sg:city":"Viernheim",
    "sg:phone":"+49 6204/72431",
    "sg:postcode":"68519",
    "sg:province":"Hessen",
    "wof:name":"Albert Winkler",
    "wof:placetype":"venue"
},
  "geometry": {"coordinates":[8.584534,49.537643],"type":"Point"}
}