{
  "type": "Feature",
  "properties": {
    "iso:country":"DE",
    "sg:address":"Gerberweg 6",
    "sg:city":"Ziemetshausen",
    "sg:phone":"+49 8284/222",
    "sg:postcode":"86473",
    "sg:province":"Bayern",
    "wof:name":"Anton Holetschek Feinleder- Gerberei Und F\u00e4rberei Gmbh",
    "wof:placetype":"venue"
},
  "geometry": {"coordinates":[10.532791,48.290787],"type":"Point"}
}