{
  "type": "Feature",
  "properties": {
    "iso:country":"DE",
    "sg:address":"Hauptstr. 72",
    "sg:city":"Elchingen",
    "sg:phone":"+49 7308/919299",
    "sg:postcode":"89275",
    "sg:province":"Bayern",
    "wof:name":"Wersching's Cargo Trans E. K.",
    "wof:placetype":"venue"
},
  "geometry": {"coordinates":[10.1043872833,48.4626274109],"type":"Point"}
}