{
  "type": "Feature",
  "properties": {
    "iso:country":"DE",
    "sg:address":"Lindenallee 56",
    "sg:city":"Eisenh\u00fcttenstadt",
    "sg:phone":"+49 3364/44083",
    "sg:postcode":"15890",
    "sg:province":"Brandenburg",
    "wof:name":"Oder-florist Gmbh",
    "wof:placetype":"venue"
},
  "geometry": {"coordinates":[14.63292,52.1516],"type":"Point"}
}