{
  "type": "Feature",
  "properties": {
    "iso:country":"DE",
    "sg:address":"Lorenzstr. 3",
    "sg:city":"Hof",
    "sg:phone":"+49 9281/2515",
    "sg:postcode":"95028",
    "sg:province":"Bayern",
    "wof:name":"Photo-studio Rudolph",
    "wof:placetype":"venue"
},
  "geometry": {"coordinates":[11.9157028198,50.3166885376],"type":"Point"}
}