{
  "type": "Feature",
  "properties": {
    "iso:country":"DE",
    "sg:address":"Belsenstr. 9",
    "sg:city":"D\u00fcsseldorf",
    "sg:phone":"+49 211/552491",
    "sg:postcode":"40545",
    "sg:province":"Nordrhein-Westfalen",
    "wof:name":"Dahmen-garms Und Garms Rechtsanw\u00e4lte",
    "wof:placetype":"venue"
},
  "geometry": {"coordinates":[6.7461209297,51.2304725647],"type":"Point"}
}