{
  "type": "Feature",
  "properties": {
    "iso:country":"DE",
    "sg:address":"Rappenauer Str. 23",
    "sg:city":"Bad Wimpfen",
    "sg:phone":"+49 7063/426",
    "sg:postcode":"74206",
    "sg:province":"Baden-W\u00fcrttemberg",
    "wof:name":"H. Hofmann",
    "wof:placetype":"venue"
},
  "geometry": {"coordinates":[9.1560459137,49.2298622131],"type":"Point"}
}