{
  "type": "Feature",
  "properties": {
    "iso:country":"DE",
    "sg:address":"L\u00fcbbecker Str. 120",
    "sg:city":"Kirchlengern",
    "sg:phone":"+49 5223/71504",
    "sg:postcode":"32278",
    "sg:province":"Nordrhein-Westfalen",
    "wof:name":"Heinrich Brackmann",
    "wof:placetype":"venue"
},
  "geometry": {"coordinates":[8.640309,52.204586],"type":"Point"}
}