{
  "type": "Feature",
  "properties": {
    "iso:country":"DE",
    "sg:address":"Mittlere Str. 37",
    "sg:city":"L\u00fcgde",
    "sg:phone":"+49 5281/98110",
    "sg:postcode":"32676",
    "sg:province":"Nordrhein-Westfalen",
    "wof:name":"Niggemann",
    "wof:placetype":"venue"
},
  "geometry": {"coordinates":[9.2458534241,51.9570922852],"type":"Point"}
}