{
  "type": "Feature",
  "properties": {
    "iso:country":"DE",
    "sg:address":"Friedensstr. 7",
    "sg:city":"Waren",
    "sg:phone":"+49 3991/667695",
    "sg:postcode":"17192",
    "sg:province":"Mecklenburg-Vorpommern",
    "wof:name":"M\u00fcritz Immobilien Gmbh",
    "wof:placetype":"venue"
},
  "geometry": {"coordinates":[12.6360273361,53.5378570557],"type":"Point"}
}