{
  "type": "Feature",
  "properties": {
    "iso:country":"DE",
    "sg:address":"Alfdorfer Str. 34",
    "sg:city":"Mutlangen",
    "sg:phone":"+49 7171/74695",
    "sg:postcode":"73557",
    "sg:province":"Baden-W\u00fcrttemberg",
    "wof:name":"Karl Krieg",
    "wof:placetype":"venue"
},
  "geometry": {"coordinates":[9.771987,48.840137],"type":"Point"}
}