{
  "type": "Feature",
  "properties": {
    "iso:country":"DE",
    "sg:address":"Daimlerstr. 35",
    "sg:city":"Nattheim",
    "sg:phone":"+49 7321/971880",
    "sg:postcode":"89564",
    "sg:province":"Baden-W\u00fcrttemberg",
    "wof:name":"A. Beyrle Gmbh",
    "wof:placetype":"venue"
},
  "geometry": {"coordinates":[10.243261,48.705738],"type":"Point"}
}