{
  "type": "Feature",
  "properties": {
    "iso:country":"DE",
    "sg:address":"Pfarrgasse 5",
    "sg:city":"Ellwangen",
    "sg:phone":"+49 7961/2240",
    "sg:postcode":"73479",
    "sg:province":"Baden-W\u00fcrttemberg",
    "wof:name":"A. Brenner",
    "wof:placetype":"venue"
},
  "geometry": {"coordinates":[10.13093853,48.9604911804],"type":"Point"}
}