{
  "type": "Feature",
  "properties": {
    "iso:country":"DE",
    "sg:address":"W\u00f6rthstr. 7",
    "sg:city":"Kitzingen",
    "sg:phone":"+49 9321/22060",
    "sg:postcode":"97318",
    "sg:province":"Bayern",
    "wof:name":"Handelshof",
    "wof:placetype":"venue"
},
  "geometry": {"coordinates":[10.1625909805,49.7342453003],"type":"Point"}
}