{
  "type": "Feature",
  "properties": {
    "iso:country":"DE",
    "sg:address":"Mussenm\u00fchle",
    "sg:city":"Tacherting",
    "sg:phone":"+49 8621/2349",
    "sg:postcode":"83342",
    "sg:province":"Bayern",
    "wof:name":"Josef Grundner Inh. Josef Huber",
    "wof:placetype":"venue"
},
  "geometry": {"coordinates":[12.5667009354,48.0470428467],"type":"Point"}
}