{
  "type": "Feature",
  "properties": {
    "iso:country":"DE",
    "sg:address":"Eschenweg 5",
    "sg:city":"Egling",
    "sg:phone":"+49 8171/20250",
    "sg:postcode":"82544",
    "sg:province":"Bayern",
    "wof:name":"Immobilien- & Verm\u00f6gens- Verwaltung Friedrich Gmbh",
    "wof:placetype":"venue"
},
  "geometry": {"coordinates":[11.4812240601,47.9292907715],"type":"Point"}
}