{
  "type": "Feature",
  "properties": {
    "iso:country":"DE",
    "sg:address":"Wormser Str. 23",
    "sg:city":"Pfungstadt",
    "sg:phone":"+49 4961/572027",
    "sg:postcode":"64319",
    "sg:province":"Hessen",
    "wof:name":"Heinrich Liebig Stahld\u00dcbelwerke Gmbh",
    "wof:placetype":"venue"
},
  "geometry": {"coordinates":[8.590342,49.803261],"type":"Point"}
}