{
  "type": "Feature",
  "properties": {
    "iso:country":"DE",
    "sg:address":"Bernhardstr. 16",
    "sg:city":"Schalkau",
    "sg:phone":"+49 36766/20107",
    "sg:postcode":"96528",
    "sg:province":"Th\u00fcringen",
    "wof:name":"B. Seidler",
    "wof:placetype":"venue"
},
  "geometry": {"coordinates":[11.01297,50.395752],"type":"Point"}
}