{
  "type": "Feature",
  "properties": {
    "iso:country":"DE",
    "sg:address":"Am Ahltener Weg 1",
    "sg:city":"Hannover",
    "sg:phone":"+49 511/6101790",
    "sg:postcode":"30559",
    "sg:province":"Niedersachsen",
    "wof:name":"Cs Networks Gmbh",
    "wof:placetype":"venue"
},
  "geometry": {"coordinates":[9.8683919907,52.3674507141],"type":"Point"}
}