{
  "type": "Feature",
  "properties": {
    "iso:country":"DE",
    "sg:address":"Eckertsfeld",
    "sg:city":"Birgland",
    "sg:phone":"+49 9666/570",
    "sg:postcode":"92262",
    "sg:province":"Bayern",
    "wof:name":"Wilhelm Volkert",
    "wof:placetype":"venue"
},
  "geometry": {"coordinates":[11.6394100189,49.4473991394],"type":"Point"}
}