{
  "type": "Feature",
  "properties": {
    "iso:country":"DE",
    "sg:address":"Kaiserstr. 1",
    "sg:city":"Leimen",
    "sg:phone":"+49 6224/72184",
    "sg:postcode":"69181",
    "sg:province":"Baden-W\u00fcrttemberg",
    "wof:name":"Klaus Schick Steuerberater",
    "wof:placetype":"venue"
},
  "geometry": {"coordinates":[8.6876773834,49.3492507935],"type":"Point"}
}