{
  "type": "Feature",
  "properties": {
    "iso:country":"DE",
    "sg:address":"Oberndorfer Str. 6",
    "sg:city":"Schramberg",
    "sg:phone":"+49 7422/23153",
    "sg:postcode":"78713",
    "sg:province":"Baden-W\u00fcrttemberg",
    "wof:name":"Porzellanhaus Schinle Gmbh",
    "wof:placetype":"venue"
},
  "geometry": {"coordinates":[8.3857498169,48.2255363464],"type":"Point"}
}