{
  "type": "Feature",
  "properties": {
    "iso:country":"DE",
    "sg:address":"Saarlandstr. 14",
    "sg:city":"Pforzheim",
    "sg:phone":"+49 7231/79133",
    "sg:postcode":"75181",
    "sg:province":"Baden-W\u00fcrttemberg",
    "wof:name":"W. Ochner",
    "wof:placetype":"venue"
},
  "geometry": {"coordinates":[8.698967,48.852451],"type":"Point"}
}