{
  "type": "Feature",
  "properties": {
    "iso:country":"DE",
    "sg:address":"Otto-Hahn-Str. 6",
    "sg:city":"Niederwerrn",
    "sg:postcode":"97464",
    "sg:province":"Bayern",
    "wof:name":"M & S Gmbh",
    "wof:placetype":"venue"
},
  "geometry": {"coordinates":[10.187969,50.06609],"type":"Point"}
}