{
  "type": "Feature",
  "properties": {
    "iso:country":"DE",
    "sg:address":"Roteb\u00fchlstr 89/2",
    "sg:city":"Stuttgart",
    "sg:phone":"+49 711/61565440",
    "sg:postcode":"70178",
    "sg:province":"Baden-W\u00fcrttemberg",
    "wof:name":"Dundi Daniel & J\u00e4ger Gmbh",
    "wof:placetype":"venue"
},
  "geometry": {"coordinates":[9.163826,48.771915],"type":"Point"}
}