{
  "type": "Feature",
  "properties": {
    "iso:country":"DE",
    "sg:address":"Herrenstr.",
    "sg:city":"Cochem",
    "sg:postcode":"56812",
    "sg:province":"Rheinland-Pfalz",
    "wof:name":"Street One Store Camillo Geipel Gmbh & Co. Kg",
    "wof:placetype":"venue"
},
  "geometry": {"coordinates":[7.166637,50.144611],"type":"Point"}
}