{
  "type": "Feature",
  "properties": {
    "iso:country":"DE",
    "sg:address":"Merseburger Str. 378",
    "sg:city":"Halle",
    "sg:phone":"+49 345/7703860",
    "sg:postcode":"06132",
    "sg:province":"Sachsen-Anhalt",
    "wof:name":"Jelowik Und Elster Rechtsanw\u00e4lte",
    "wof:placetype":"venue"
},
  "geometry": {"coordinates":[11.9838047028,51.4353256226],"type":"Point"}
}