{
  "type": "Feature",
  "properties": {
    "iso:country":"DE",
    "sg:address":"Ivensring 19",
    "sg:city":"Kiel",
    "sg:phone":"+49 431/723682",
    "sg:postcode":"24149",
    "sg:province":"Schleswig-Holstein",
    "wof:name":"Wilfried L\u00fctgens",
    "wof:placetype":"venue"
},
  "geometry": {"coordinates":[10.190267,54.332821],"type":"Point"}
}