{
  "type": "Feature",
  "properties": {
    "iso:country":"DE",
    "sg:address":"Salzgasse 6",
    "sg:city":"Speyer",
    "sg:phone":"+49 6232/70699",
    "sg:postcode":"67346",
    "sg:province":"Rheinland-Pfalz",
    "wof:name":"Angelika Hau\u00df",
    "wof:placetype":"venue"
},
  "geometry": {"coordinates":[8.4379663467,49.3176193237],"type":"Point"}
}