{
  "type": "Feature",
  "properties": {
    "iso:country":"DE",
    "sg:address":"Ruhrorter Str. 122",
    "sg:city":"M\u00fclheim",
    "sg:phone":"+49 208/580560",
    "sg:postcode":"45478",
    "sg:province":"Nordrhein-Westfalen",
    "wof:name":"Tauch- Und Bergungsunternehmen Barthel & Sohn Gmbh",
    "wof:placetype":"venue"
},
  "geometry": {"coordinates":[6.8317251205,51.4402008057],"type":"Point"}
}