{
  "type": "Feature",
  "properties": {
    "iso:country":"DE",
    "sg:address":"Weinstr. 4",
    "sg:city":"Schweigen-Rechtenbach",
    "sg:phone":"+49 6342/7352",
    "sg:postcode":"76889",
    "sg:province":"Rheinland-Pfalz",
    "wof:name":"Restaurant Deutsches Weintor",
    "wof:placetype":"venue"
},
  "geometry": {"coordinates":[7.9565668106,49.0523071289],"type":"Point"}
}