{
  "type": "Feature",
  "properties": {
    "iso:country":"DE",
    "sg:address":"Piccoloministr. 408",
    "sg:city":"K\u00f6ln",
    "sg:phone":"+49 221/638615",
    "sg:postcode":"51067",
    "sg:province":"Nordrhein-Westfalen",
    "wof:name":"Scholl & Briller Dachdeckermeister Gmbh",
    "wof:placetype":"venue"
},
  "geometry": {"coordinates":[7.047287,50.972275],"type":"Point"}
}