{
  "type": "Feature",
  "properties": {
    "iso:country":"DE",
    "sg:address":"Bachstr.",
    "sg:city":"Oberstdorf",
    "sg:phone":"+49 8322/7778",
    "sg:postcode":"87561",
    "sg:province":"Bayern",
    "wof:name":"Sport Gerg Gmbh",
    "wof:placetype":"venue"
},
  "geometry": {"coordinates":[10.2763948441,47.4090766907],"type":"Point"}
}