{
  "type": "Feature",
  "properties": {
    "iso:country":"DE",
    "sg:address":"Am Neutor 7",
    "sg:city":"Mayen",
    "sg:phone":"+49 2651/71100",
    "sg:postcode":"56727",
    "sg:province":"Rheinland-Pfalz",
    "wof:name":"Reiseb\u00fcro Rathscheck Inh. Hiltrid Wagner",
    "wof:placetype":"venue"
},
  "geometry": {"coordinates":[7.2247738838,50.3270874023],"type":"Point"}
}