{
  "type": "Feature",
  "properties": {
    "iso:country":"DE",
    "sg:address":"Westerwaldstr. 1",
    "sg:city":"H\u00f6hr-Grenzhausen",
    "sg:phone":"+49 2624/6292",
    "sg:postcode":"56203",
    "sg:province":"Rheinland-Pfalz",
    "wof:name":"A. Hanusch Und H. Ecker Abt. Buchhandlung",
    "wof:placetype":"venue"
},
  "geometry": {"coordinates":[7.6683220863,50.4372444153],"type":"Point"}
}