{
  "type": "Feature",
  "properties": {
    "iso:country":"DE",
    "sg:address":"Hessenring 24",
    "sg:city":"B\u00fcttelborn",
    "sg:phone":"+49 6152/92360",
    "sg:postcode":"64572",
    "sg:province":"Hessen",
    "wof:name":"Polar Electro Gmbh",
    "wof:placetype":"venue"
},
  "geometry": {"coordinates":[8.526837,49.898495],"type":"Point"}
}