{
  "type": "Feature",
  "properties": {
    "iso:country":"DE",
    "sg:address":"Thermalbadstr. 18",
    "sg:city":"Bad Rodach",
    "sg:postcode":"96476",
    "sg:province":"Bayern",
    "wof:name":"Kurbetrieb Thermalbad Der Stadt Bad Rodach",
    "wof:placetype":"venue"
},
  "geometry": {"coordinates":[10.7658843994,50.3337135315],"type":"Point"}
}