{
  "type": "Feature",
  "properties": {
    "iso:country":"DE",
    "sg:address":"Bayreuther Str. 31",
    "sg:city":"Wunsiedel",
    "sg:postcode":"95632",
    "sg:province":"Bayern",
    "wof:name":"Wohnplan Markenm\u00f6bel- Vertrieb Gmbh",
    "wof:placetype":"venue"
},
  "geometry": {"coordinates":[11.9682769775,50.0250396729],"type":"Point"}
}