{
  "type": "Feature",
  "properties": {
    "iso:country":"DE",
    "sg:address":"Hauptstr. 7",
    "sg:city":"Perl",
    "sg:phone":"+49 6866/222",
    "sg:postcode":"66706",
    "sg:province":"Saarland",
    "wof:name":"Peter J\u00e4ger",
    "wof:placetype":"venue"
},
  "geometry": {"coordinates":[6.430021,49.531174],"type":"Point"}
}