{
  "type": "Feature",
  "properties": {
    "iso:country":"DE",
    "sg:address":"Am Heuberg 2",
    "sg:city":"Balingen",
    "sg:phone":"+49 7433/8284",
    "sg:postcode":"72336",
    "sg:province":"Baden-W\u00fcrttemberg",
    "wof:name":"Max Nachtmann",
    "wof:placetype":"venue"
},
  "geometry": {"coordinates":[8.8468141556,48.2734336853],"type":"Point"}
}