{
  "type": "Feature",
  "properties": {
    "iso:country":"DE",
    "sg:address":"Mal\u00dfstr. 1a",
    "sg:city":"Frankfurt",
    "sg:phone":"+49 69/561060",
    "sg:postcode":"60320",
    "sg:province":"Hessen",
    "wof:name":"Treuhand Revisions- Und Wirtschaftsberatungs Gmbh",
    "wof:placetype":"venue"
},
  "geometry": {"coordinates":[8.6697206497,50.1394729614],"type":"Point"}
}