{
  "type": "Feature",
  "properties": {
    "iso:country":"DE",
    "sg:address":"Flittarder Hauptstr. 71",
    "sg:city":"K\u00f6ln",
    "sg:phone":"+49 221/661415",
    "sg:postcode":"51061",
    "sg:province":"Nordrhein-Westfalen",
    "wof:name":"Peter Schmitz",
    "wof:placetype":"venue"
},
  "geometry": {"coordinates":[6.9768071175,51.0035743713],"type":"Point"}
}