{
  "type": "Feature",
  "properties": {
    "iso:country":"DE",
    "sg:address":"Im Boschm\u00e4ttle 13",
    "sg:city":"Offenburg",
    "sg:phone":"+49 781/25613",
    "sg:postcode":"77656",
    "sg:province":"Baden-W\u00fcrttemberg",
    "wof:name":"Kl\u00e4r Verwaltungs Gmbh",
    "wof:placetype":"venue"
},
  "geometry": {"coordinates":[7.9368181229,48.4496841431],"type":"Point"}
}