{
  "type": "Feature",
  "properties": {
    "iso:country":"DE",
    "sg:address":"Auf dem Schnee 52",
    "sg:city":"Herdecke",
    "sg:phone":"+49 2330/84670",
    "sg:postcode":"58313",
    "sg:province":"Nordrhein-Westfalen",
    "wof:name":"Reinhard L\u00fcckel",
    "wof:placetype":"venue"
},
  "geometry": {"coordinates":[7.4248900414,51.4321403503],"type":"Point"}
}