{
  "type": "Feature",
  "properties": {
    "iso:country":"DE",
    "sg:address":"Hauptstr. 38 a",
    "sg:city":"Rheinfelden",
    "sg:phone":"+49 7623/40656",
    "sg:postcode":"79618",
    "sg:province":"Baden-W\u00fcrttemberg",
    "wof:name":"Gerhard Sch\u00e4ck",
    "wof:placetype":"venue"
},
  "geometry": {"coordinates":[7.734384,47.556828],"type":"Point"}
}