{
  "type": "Feature",
  "properties": {
    "iso:country":"DE",
    "sg:address":"Geschwister-Scholl-Str. 27",
    "sg:city":"Borna",
    "sg:phone":"+49 3433/203801",
    "sg:postcode":"04552",
    "sg:province":"Sachsen",
    "wof:name":"Siegfried Stiller",
    "wof:placetype":"venue"
},
  "geometry": {"coordinates":[12.508958,51.128994],"type":"Point"}
}