{
  "type": "Feature",
  "properties": {
    "iso:country":"DE",
    "sg:address":"Blumenstr. 25",
    "sg:city":"Heidelberg",
    "sg:phone":"+49 6221/25369",
    "sg:postcode":"69115",
    "sg:province":"Baden-W\u00fcrttemberg",
    "wof:name":"Zwitscherstube",
    "wof:placetype":"venue"
},
  "geometry": {"coordinates":[8.6868057251,49.4043045044],"type":"Point"}
}