{
  "type": "Feature",
  "properties": {
    "iso:country":"DE",
    "sg:address":"Nassmuehlstr. 7",
    "sg:city":"Kahl",
    "sg:phone":"+49 4961/8891080",
    "sg:postcode":"63796",
    "sg:province":"Bayern",
    "wof:name":"Getr\u00c4nke Gathof Ohg",
    "wof:placetype":"venue"
},
  "geometry": {"coordinates":[9.001987,50.069744],"type":"Point"}
}