{
  "type": "Feature",
  "properties": {
    "iso:country":"DE",
    "sg:address":"Neusser Str. 27-29",
    "sg:city":"K\u00f6ln",
    "sg:phone":"+49 221/7200241",
    "sg:postcode":"50670",
    "sg:province":"Nordrhein-Westfalen",
    "wof:name":"Leighton & Krasnenko Integrated Communications Gmbh",
    "wof:placetype":"venue"
},
  "geometry": {"coordinates":[6.9569268227,50.9522132874],"type":"Point"}
}