{
  "type": "Feature",
  "properties": {
    "iso:country":"DE",
    "sg:address":"Dellbr\u00fccker Hauptstr. 205",
    "sg:city":"K\u00f6ln",
    "sg:phone":"+49 221/6804038",
    "sg:postcode":"51069",
    "sg:province":"Nordrhein-Westfalen",
    "wof:name":"Altes Postamt",
    "wof:placetype":"venue"
},
  "geometry": {"coordinates":[7.0685720444,50.9806098938],"type":"Point"}
}