{
  "type": "Feature",
  "properties": {
    "iso:country":"DE",
    "sg:address":"Regensburger Str. 38 a",
    "sg:city":"Burglengenfeld",
    "sg:phone":"+49 9471/70230",
    "sg:postcode":"93133",
    "sg:province":"Bayern",
    "wof:name":"Gottfried Friedberger",
    "wof:placetype":"venue"
},
  "geometry": {"coordinates":[12.0463905334,49.2034988403],"type":"Point"}
}