{
  "type": "Feature",
  "properties": {
    "iso:country":"DE",
    "sg:address":"Herderstr. 53",
    "sg:city":"Ilmenau",
    "sg:phone":"+49 3677/202061",
    "sg:postcode":"98693",
    "sg:province":"Th\u00fcringen",
    "wof:name":"Verena Laudan",
    "wof:placetype":"venue"
},
  "geometry": {"coordinates":[10.909433,50.676842],"type":"Point"}
}