{
  "type": "Feature",
  "properties": {
    "iso:country":"DE",
    "sg:address":"Lobensteiner Str. 13",
    "sg:city":"Ebersdorf",
    "sg:phone":"+49 36651/87142",
    "sg:postcode":"07368",
    "sg:province":"Th\u00fcringen",
    "wof:name":"Ruestzeitenheim Sonnenschein",
    "wof:placetype":"venue"
},
  "geometry": {"coordinates":[11.6028175354,50.5349655151],"type":"Point"}
}