{
  "type": "Feature",
  "properties": {
    "iso:country":"DE",
    "sg:address":"nelkenstr",
    "sg:city":"markhausen",
    "sg:postcode":"26169",
    "sg:province":"Niedersachsen",
    "wof:name":"Die Andere Welt",
    "wof:placetype":"venue"
},
  "geometry": {"coordinates":[7.83657,52.941116],"type":"Point"}
}