{
  "type": "Feature",
  "properties": {
    "iso:country":"DE",
    "sg:address":"Am Osterbach 2",
    "sg:city":"Cham",
    "sg:phone":"+49 9971/3970",
    "sg:postcode":"93413",
    "sg:province":"Bayern",
    "wof:name":"Aulfes Gmbh",
    "wof:placetype":"venue"
},
  "geometry": {"coordinates":[12.6998968124,49.2114906311],"type":"Point"}
}