{
  "type": "Feature",
  "properties": {
    "iso:country":"DE",
    "sg:address":"Hagener Str. 250",
    "sg:city":"Dortmund",
    "sg:phone":"+49 231/731923",
    "sg:postcode":"44229",
    "sg:province":"Nordrhein-Westfalen",
    "wof:name":"Manfred Raphael",
    "wof:placetype":"venue"
},
  "geometry": {"coordinates":[7.456355,51.458492],"type":"Point"}
}