{
  "type": "Feature",
  "properties": {
    "iso:country":"DE",
    "sg:address":"Lindenstr. 110",
    "sg:city":"Bremen",
    "sg:phone":"+49 421/6680",
    "sg:postcode":"28755",
    "sg:province":"Bremen",
    "wof:name":"Archiv Der Bremer Vulkan Werft Und Maschinenfabrik Gmbh",
    "wof:placetype":"venue"
},
  "geometry": {"coordinates":[8.595025,53.177643],"type":"Point"}
}