{
  "type": "Feature",
  "properties": {
    "iso:country":"DE",
    "sg:address":"Kirchgasse 14",
    "sg:city":"Weilrod",
    "sg:phone":"+49 6083/379",
    "sg:postcode":"61276",
    "sg:province":"Hessen",
    "wof:name":"Ev. Pfarramt Niederlauken",
    "wof:placetype":"venue"
},
  "geometry": {"coordinates":[8.4338674545,50.3433914185],"type":"Point"}
}