{
  "type": "Feature",
  "properties": {
    "iso:country":"DE",
    "sg:address":"Hofbreite 5",
    "sg:city":"Northeim",
    "sg:phone":"+49 5503/740",
    "sg:postcode":"37154",
    "sg:province":"Niedersachsen",
    "wof:name":"Volker Reinberger",
    "wof:placetype":"venue"
},
  "geometry": {"coordinates":[9.9836292267,51.6507797241],"type":"Point"}
}