{
  "type": "Feature",
  "properties": {
    "iso:country":"DE",
    "sg:address":"Schubertstr. 12 a",
    "sg:city":"Eggenstein-Leopoldshafen",
    "sg:phone":"+49 721/9702446",
    "sg:postcode":"76344",
    "sg:province":"Baden-W\u00fcrttemberg",
    "wof:name":"Daten Rausch Gmbh",
    "wof:placetype":"venue"
},
  "geometry": {"coordinates":[8.40228,49.08733],"type":"Point"}
}