{
  "type": "Feature",
  "properties": {
    "iso:country":"DE",
    "sg:address":"Weinbergstr. 6 c",
    "sg:city":"Guteborn",
    "sg:phone":"+49 35752/5240",
    "sg:postcode":"01945",
    "sg:province":"Brandenburg",
    "wof:name":"Horst Peise",
    "wof:placetype":"venue"
},
  "geometry": {"coordinates":[13.928203,51.421902],"type":"Point"}
}