{
  "type": "Feature",
  "properties": {
    "iso:country":"DE",
    "sg:address":"Marktplatz 5",
    "sg:city":"Essing",
    "sg:phone":"+49 9447/386",
    "sg:postcode":"93343",
    "sg:province":"Bayern",
    "wof:name":"Pension Holzapfel",
    "wof:placetype":"venue"
},
  "geometry": {"coordinates":[11.7881479263,48.9365081787],"type":"Point"}
}