{
  "type": "Feature",
  "properties": {
    "iso:country":"DE",
    "sg:address":"Bunsenstr. 17",
    "sg:city":"Keltern",
    "sg:phone":"+49 7236/980424",
    "sg:postcode":"75210",
    "sg:province":"Baden-W\u00fcrttemberg",
    "wof:name":"Big Sale Textil-vertriebs Gmbh",
    "wof:placetype":"venue"
},
  "geometry": {"coordinates":[8.5609560013,48.9114074707],"type":"Point"}
}