{
  "type": "Feature",
  "properties": {
    "iso:country":"DE",
    "sg:address":"Marktplatz 40",
    "sg:city":"Gunzenhausen",
    "sg:phone":"+49 9831/2465",
    "sg:postcode":"91710",
    "sg:province":"Bayern",
    "wof:name":"Gislinde Reder",
    "wof:placetype":"venue"
},
  "geometry": {"coordinates":[10.7544994354,49.1138687134],"type":"Point"}
}