{
  "type": "Feature",
  "properties": {
    "iso:country":"DE",
    "sg:address":"Wei\u00dfachaustr. 9",
    "sg:city":"Kreuth",
    "sg:phone":"+49 8029/289",
    "sg:postcode":"83708",
    "sg:province":"Bayern",
    "wof:name":"Andreas Strillinger Elektroinstallation",
    "wof:placetype":"venue"
},
  "geometry": {"coordinates":[11.747085,47.645313],"type":"Point"}
}