{
  "type": "Feature",
  "properties": {
    "iso:country":"DE",
    "sg:address":"Fetscherplatz 2 a",
    "sg:city":"Dresden",
    "sg:phone":"+49 351/449320",
    "sg:postcode":"01307",
    "sg:province":"Sachsen",
    "wof:name":"M. Baker Immobilienmakler",
    "wof:placetype":"venue"
},
  "geometry": {"coordinates":[13.7706766129,51.0467948914],"type":"Point"}
}