{
  "type": "Feature",
  "properties": {
    "iso:country":"DE",
    "sg:address":"Aachstrasse 30",
    "sg:city":"Deggenhausertal",
    "sg:phone":"+49 7555",
    "sg:postcode":"88693",
    "sg:province":"Baden-W\u00fcrttemberg",
    "wof:name":"Gasthof Rossknecht",
    "wof:placetype":"venue"
},
  "geometry": {"coordinates":[9.3912410736,47.7824707031],"type":"Point"}
}