{
  "type": "Feature",
  "properties": {
    "iso:country":"DE",
    "sg:address":"Leuthenstr. 31",
    "sg:city":"Minden",
    "sg:phone":"+49 571/63725",
    "sg:postcode":"32425",
    "sg:province":"Nordrhein-Westfalen",
    "wof:name":"R. Kaltofen",
    "wof:placetype":"venue"
},
  "geometry": {"coordinates":[8.8928546906,52.3161888123],"type":"Point"}
}