{
  "type": "Feature",
  "properties": {
    "iso:country":"DE",
    "sg:address":"Westfalenstr 17",
    "sg:city":"Kassel",
    "sg:phone":"+49 561/33133",
    "sg:postcode":"34131",
    "sg:province":"Hessen",
    "wof:name":"Cbc Component Broadcast Company",
    "wof:placetype":"venue"
},
  "geometry": {"coordinates":[9.439081,51.307869],"type":"Point"}
}