{
  "type": "Feature",
  "properties": {
    "iso:country":"DE",
    "sg:address":"Weinbergstr. 4",
    "sg:city":"R\u00fcsselsheim",
    "sg:phone":"+49 6142/65132",
    "sg:postcode":"65428",
    "sg:province":"Hessen",
    "wof:name":"Uwe Herrmann",
    "wof:placetype":"venue"
},
  "geometry": {"coordinates":[8.420189,49.997684],"type":"Point"}
}