{
  "type": "Feature",
  "properties": {
    "iso:country":"DE",
    "sg:address":"Postfach 1853",
    "sg:city":"Ahrensburg",
    "sg:phone":"+49 5109/515221",
    "sg:postcode":"22908",
    "sg:province":"Schleswig-Holstein",
    "wof:name":"W I B U - Wirtschaftsbund Soz. Einricht. Nord Gmbh",
    "wof:placetype":"venue"
},
  "geometry": {"coordinates":[10.2398,53.675709],"type":"Point"}
}