{
  "type": "Feature",
  "properties": {
    "iso:country":"DE",
    "sg:address":"Pa\u00dfstr. 105",
    "sg:city":"Aachen",
    "sg:phone":"+49 241/153584",
    "sg:postcode":"52070",
    "sg:province":"Nordrhein-Westfalen",
    "wof:name":"E. Eilert",
    "wof:placetype":"venue"
},
  "geometry": {"coordinates":[6.097096,50.784279],"type":"Point"}
}