{
  "type": "Feature",
  "properties": {
    "iso:country":"DE",
    "sg:address":"Tilsiter Str. 13",
    "sg:city":"Laudenbach",
    "sg:phone":"+49 6201/72920",
    "sg:postcode":"69514",
    "sg:province":"Baden-W\u00fcrttemberg",
    "wof:name":"Sandforth",
    "wof:placetype":"venue"
},
  "geometry": {"coordinates":[8.648831,49.613785],"type":"Point"}
}