{
  "type": "Feature",
  "properties": {
    "iso:country":"DE",
    "sg:address":"Immermannstr 8",
    "sg:city":"Witten",
    "sg:phone":"+49 2302/956780",
    "sg:postcode":"58453",
    "sg:province":"Nordrhein-Westfalen",
    "wof:name":"A.i.d.a Werbeartikel Gmbh",
    "wof:placetype":"venue"
},
  "geometry": {"coordinates":[7.369674,51.447906],"type":"Point"}
}