{
  "type": "Feature",
  "properties": {
    "iso:country":"DE",
    "sg:address":"Obersch\u00f6llenbacher Hauptstr. 7",
    "sg:city":"Eckental",
    "sg:phone":"+49 9126/8690",
    "sg:postcode":"90542",
    "sg:province":"Bayern",
    "wof:name":"Andreas Fensel",
    "wof:placetype":"venue"
},
  "geometry": {"coordinates":[11.166308,49.572449],"type":"Point"}
}