{
  "type": "Feature",
  "properties": {
    "iso:country":"DE",
    "sg:address":"Petersauracher Str. 3",
    "sg:city":"Neuendettelsau",
    "sg:phone":"+49 9872/7672",
    "sg:postcode":"91564",
    "sg:province":"Bayern",
    "wof:name":"Hans Seitzinger",
    "wof:placetype":"venue"
},
  "geometry": {"coordinates":[10.791677,49.310741],"type":"Point"}
}