{
  "type": "Feature",
  "properties": {
    "iso:country":"DE",
    "sg:address":"Otto-Schmirgal-Str. 5",
    "sg:city":"Berlin",
    "sg:phone":"+49 30/9989500",
    "sg:postcode":"10319",
    "sg:province":"Berlin",
    "wof:name":"Triade Reiseb\u00fcro Gmbh",
    "wof:placetype":"venue"
},
  "geometry": {"coordinates":[13.5225601196,52.4974021912],"type":"Point"}
}