{
  "type": "Feature",
  "properties": {
    "iso:country":"DE",
    "sg:address":"Krautpoint 23",
    "sg:city":"Hofkirchen",
    "sg:postcode":"94544",
    "sg:province":"Bayern",
    "wof:name":"A To Z Agency Eckmiller Gmbh",
    "wof:placetype":"venue"
},
  "geometry": {"coordinates":[13.1244096756,48.6762313843],"type":"Point"}
}