{
  "type": "Feature",
  "properties": {
    "iso:country":"DE",
    "sg:address":"Landgrafenstr. 37-39",
    "sg:city":"Troisdorf",
    "sg:phone":"+49 2241/406627",
    "sg:postcode":"53842",
    "sg:province":"Nordrhein-Westfalen",
    "wof:name":"Deutscher Familien- Dienst E. V.",
    "wof:placetype":"venue"
},
  "geometry": {"coordinates":[7.1380419731,50.8127212524],"type":"Point"}
}