{
  "type": "Feature",
  "properties": {
    "iso:country":"DE",
    "sg:address":"Eitelstr. 7",
    "sg:city":"D\u00fcsseldorf",
    "sg:phone":"+49 211/654331",
    "sg:postcode":"40472",
    "sg:province":"Nordrhein-Westfalen",
    "wof:name":"Isa Ingenieurb\u00fcro F\u00fcr Elektrische Steuerungen Und",
    "wof:placetype":"venue"
},
  "geometry": {"coordinates":[6.8263959885,51.2689361572],"type":"Point"}
}