{
  "type": "Feature",
  "properties": {
    "iso:country":"DE",
    "sg:address":"Oderberger Str. 39",
    "sg:city":"Bralitz",
    "sg:phone":"+49 33369/849",
    "sg:postcode":"16259",
    "sg:province":"Brandenburg",
    "wof:name":"Hartmut Jankowsky",
    "wof:placetype":"venue"
},
  "geometry": {"coordinates":[14.008034,52.837631],"type":"Point"}
}