{
  "type": "Feature",
  "properties": {
    "iso:country":"DE",
    "sg:address":"Bremers Weg 5 a",
    "sg:city":"Hamburg",
    "sg:phone":"+49 40/861310",
    "sg:postcode":"22587",
    "sg:province":"Hamburg",
    "wof:name":"Architektur-designmodelle- Schleifer",
    "wof:placetype":"venue"
},
  "geometry": {"coordinates":[9.809116,53.557915],"type":"Point"}
}