{
  "type": "Feature",
  "properties": {
    "iso:country":"DE",
    "sg:address":"H\u00e4geb\u00fcchstr. 5",
    "sg:city":"Reilingen",
    "sg:phone":"+49 6205/15663",
    "sg:postcode":"68799",
    "sg:province":"Baden-W\u00fcrttemberg",
    "wof:name":"Erich Klaus",
    "wof:placetype":"venue"
},
  "geometry": {"coordinates":[8.55909729,49.299030304],"type":"Point"}
}