{
  "type": "Feature",
  "properties": {
    "iso:country":"DE",
    "sg:address":"Ru\u00dflandweg 42",
    "sg:city":"Friedeburg",
    "sg:phone":"+49 4465/94960",
    "sg:postcode":"26446",
    "sg:province":"Niedersachsen",
    "wof:name":"Onnen-reisen",
    "wof:placetype":"venue"
},
  "geometry": {"coordinates":[7.8132801056,53.4503898621],"type":"Point"}
}