{
  "type": "Feature",
  "properties": {
    "iso:country":"DE",
    "sg:address":"Leinestr. 2",
    "sg:city":"Seelze",
    "sg:phone":"+49 5137/93353",
    "sg:postcode":"30926",
    "sg:province":"Niedersachsen",
    "wof:name":"Heinrich Reckewerth",
    "wof:placetype":"venue"
},
  "geometry": {"coordinates":[9.595328331,52.400138855],"type":"Point"}
}