{
  "type": "Feature",
  "properties": {
    "iso:country":"DE",
    "sg:address":"Gretlade 5",
    "sg:city":"Sehnde",
    "sg:phone":"+49 5132/86870",
    "sg:postcode":"31319",
    "sg:province":"Niedersachsen",
    "wof:name":"Hoffmann Dienstleistungen F\u00fcr Die Werbende Wirtschaft Gmbh",
    "wof:placetype":"venue"
},
  "geometry": {"coordinates":[9.8836956024,52.3559837341],"type":"Point"}
}