{
  "type": "Feature",
  "properties": {
    "iso:country":"DE",
    "sg:address":"Hertlingstr. 6",
    "sg:city":"Ingolstadt",
    "sg:phone":"+49 841/76271",
    "sg:postcode":"85051",
    "sg:province":"Bayern",
    "wof:name":"Schmidl Gmbh & Co. Wirtschafts Kg",
    "wof:placetype":"venue"
},
  "geometry": {"coordinates":[11.4111146927,48.7391281128],"type":"Point"}
}