{
  "type": "Feature",
  "properties": {
    "iso:country":"DE",
    "sg:address":"R\u00f6merdorf 23",
    "sg:city":"Bad Kreuznach",
    "sg:phone":"+49 671/68429",
    "sg:postcode":"55545",
    "sg:province":"Rheinland-Pfalz",
    "wof:name":"Erich Frank",
    "wof:placetype":"venue"
},
  "geometry": {"coordinates":[7.9110579491,49.8632850647],"type":"Point"}
}