{
  "type": "Feature",
  "properties": {
    "iso:country":"DE",
    "sg:address":"Amberger Str. 7",
    "sg:city":"Hersbruck",
    "sg:phone":"+49 9151/7582",
    "sg:postcode":"91217",
    "sg:province":"Bayern",
    "wof:name":"Die Kleine Kneipe",
    "wof:placetype":"venue"
},
  "geometry": {"coordinates":[11.4323711395,49.5093193054],"type":"Point"}
}