{
  "type": "Feature",
  "properties": {
    "iso:country":"DE",
    "sg:address":"Weltestr. 10",
    "sg:city":"Weingarten",
    "sg:phone":"+49 751/22665",
    "sg:postcode":"88250",
    "sg:province":"Baden-W\u00fcrttemberg",
    "wof:name":"Ckv Service Gmbh",
    "wof:placetype":"venue"
},
  "geometry": {"coordinates":[9.6302652359,47.8216934204],"type":"Point"}
}