{
  "type": "Feature",
  "properties": {
    "iso:country":"DE",
    "sg:address":"Oberweg 52",
    "sg:city":"Frankfurt",
    "sg:phone":"+49 69/9596540",
    "sg:postcode":"60318",
    "sg:province":"Hessen",
    "wof:name":"Fischer Euler Und Plottnitz Rechtsanw\u00e4lte",
    "wof:placetype":"venue"
},
  "geometry": {"coordinates":[8.6818408966,50.1224212646],"type":"Point"}
}