{
  "type": "Feature",
  "properties": {
    "iso:country":"DE",
    "sg:address":"Rudolf-Diesel-Str. 13",
    "sg:city":"Altenkirchen",
    "sg:postcode":"57610",
    "sg:province":"Rheinland-Pfalz",
    "wof:name":"Lauterbach Holzbau- Und Abbundzentrum Gmbh",
    "wof:placetype":"venue"
},
  "geometry": {"coordinates":[7.6228737831,50.6916885376],"type":"Point"}
}