{
  "type": "Feature",
  "properties": {
    "iso:country":"DE",
    "sg:address":"Hainstr 2",
    "sg:city":"K\u00f6nigsee",
    "sg:phone":"+49 36738/42328",
    "sg:postcode":"07426",
    "sg:province":"Th\u00fcringen",
    "wof:name":"Bergemann Druck",
    "wof:placetype":"venue"
},
  "geometry": {"coordinates":[11.0966901779,50.6605987549],"type":"Point"}
}