{
  "type": "Feature",
  "properties": {
    "iso:country":"DE",
    "sg:address":"Gartenstr. 14",
    "sg:city":"Wassenach",
    "sg:phone":"+49 2636/3181",
    "sg:postcode":"56653",
    "sg:province":"Rheinland-Pfalz",
    "wof:name":"Hans-gerd Biermann Architekt",
    "wof:placetype":"venue"
},
  "geometry": {"coordinates":[7.278928,50.431896],"type":"Point"}
}