{
  "type": "Feature",
  "properties": {
    "iso:country":"DE",
    "sg:address":"Philippistr. 4",
    "sg:city":"Berlin",
    "sg:phone":"+49 30/32602739",
    "sg:postcode":"14059",
    "sg:province":"Berlin",
    "wof:name":"Fanselow Elektroinstallation Und Datennetze Gmbh",
    "wof:placetype":"venue"
},
  "geometry": {"coordinates":[13.287606,52.51149],"type":"Point"}
}