{
  "type": "Feature",
  "properties": {
    "iso:country":"DE",
    "sg:address":"Obertor 23",
    "sg:city":"Rosenthal",
    "sg:phone":"+49 6458/350",
    "sg:postcode":"35119",
    "sg:province":"Hessen",
    "wof:name":"Johann Kornmann Elektromeister",
    "wof:placetype":"venue"
},
  "geometry": {"coordinates":[8.865315,50.973888],"type":"Point"}
}