{
  "type": "Feature",
  "properties": {
    "iso:country":"DE",
    "sg:address":"Langenauer Str. 1",
    "sg:city":"Siegen",
    "sg:phone":"+49 271/83045",
    "sg:postcode":"57078",
    "sg:province":"Nordrhein-Westfalen",
    "wof:name":"Hm Feinblechhandel Gmbh",
    "wof:placetype":"venue"
},
  "geometry": {"coordinates":[7.999063,50.930595],"type":"Point"}
}