{
  "type": "Feature",
  "properties": {
    "iso:country":"DE",
    "sg:address":"Hauptstr. 1",
    "sg:city":"Ribbesb\u00fcttel",
    "sg:phone":"+49 5373/330007",
    "sg:postcode":"38551",
    "sg:province":"Niedersachsen",
    "wof:name":"Adam",
    "wof:placetype":"venue"
},
  "geometry": {"coordinates":[10.485916,52.432648],"type":"Point"}
}