{
  "type": "Feature",
  "properties": {
    "iso:country":"DE",
    "sg:address":"Am Waldesrand 5",
    "sg:city":"Rothenberg",
    "sg:phone":"+49 6068/2890",
    "sg:postcode":"64757",
    "sg:province":"Hessen",
    "wof:name":"Team Haus Bautr\u00e4gergesell. Mbh",
    "wof:placetype":"venue"
},
  "geometry": {"coordinates":[8.8840417862,49.5573272705],"type":"Point"}
}