{
  "type": "Feature",
  "properties": {
    "iso:country":"DE",
    "sg:address":"R\u00f6bendiekenstr. 19",
    "sg:city":"Zetel",
    "sg:phone":"+49 4452/418",
    "sg:postcode":"26340",
    "sg:province":"Niedersachsen",
    "wof:name":"Ingo Hilbers Ingenieur",
    "wof:placetype":"venue"
},
  "geometry": {"coordinates":[7.938,53.386715],"type":"Point"}
}