{
  "type": "Feature",
  "properties": {
    "iso:country":"DE",
    "sg:address":"An der Sch\u00f6lke 18",
    "sg:city":"Salzgitter",
    "sg:phone":"+49 5341/15952",
    "sg:postcode":"38226",
    "sg:province":"Niedersachsen",
    "wof:name":"Ihv Service Gmbh",
    "wof:placetype":"venue"
},
  "geometry": {"coordinates":[10.3230085373,52.1522941589],"type":"Point"}
}