{
  "type": "Feature",
  "properties": {
    "iso:country":"DE",
    "sg:address":"Am Huckelrieder Friedhof",
    "sg:city":"Bremen",
    "sg:phone":"+49 421/215494",
    "sg:postcode":"28201",
    "sg:province":"Bremen",
    "wof:name":"Werth Und Co. Grabdenkm\u00e4ler",
    "wof:placetype":"venue"
},
  "geometry": {"coordinates":[8.8206949234,53.0604248047],"type":"Point"}
}