{
  "type": "Feature",
  "properties": {
    "iso:country":"DE",
    "sg:address":"Stadtfischergasse 5",
    "sg:city":"Ellwangen",
    "sg:phone":"+49 7961/3651",
    "sg:postcode":"73479",
    "sg:province":"Baden-W\u00fcrttemberg",
    "wof:name":"A. Wecker Bauschlosserei",
    "wof:placetype":"venue"
},
  "geometry": {"coordinates":[10.132139,48.960201],"type":"Point"}
}