{
  "type": "Feature",
  "properties": {
    "iso:country":"DE",
    "sg:address":"Sollner Str. 36",
    "sg:city":"M\u00fcnchen",
    "sg:phone":"+49 89/514150",
    "sg:postcode":"81479",
    "sg:province":"Bayern",
    "wof:name":"Profi Partner Verm\u00f6gensverwaltung Gmbh & Co.",
    "wof:placetype":"venue"
},
  "geometry": {"coordinates":[11.5257072449,48.0790061951],"type":"Point"}
}