{
  "type": "Feature",
  "properties": {
    "iso:country":"DE",
    "sg:address":"Remscheider Str. 12",
    "sg:city":"Stuttgart",
    "sg:phone":"+49 711/5490862",
    "sg:postcode":"70376",
    "sg:province":"Baden-W\u00fcrttemberg",
    "wof:name":"Restaurant Filderhof",
    "wof:placetype":"venue"
},
  "geometry": {"coordinates":[9.2124872208,48.8078422546],"type":"Point"}
}