{
  "type": "Feature",
  "properties": {
    "iso:country":"DE",
    "sg:address":"Reisholzer Str. 50",
    "sg:city":"D\u00fcsseldorf",
    "sg:phone":"+49 211/227088",
    "sg:postcode":"40231",
    "sg:province":"Nordrhein-Westfalen",
    "wof:name":"Brillenmacher Blankenburg E. K.",
    "wof:placetype":"venue"
},
  "geometry": {"coordinates":[6.8325171471,51.2066612244],"type":"Point"}
}