{
  "type": "Feature",
  "properties": {
    "iso:country":"DE",
    "sg:address":"Zum Wingertsberg 13",
    "sg:city":"Trier",
    "sg:phone":"+49 651/1700111",
    "sg:postcode":"54296",
    "sg:province":"Rheinland-Pfalz",
    "wof:name":"Kommunalentwicklung Rheinland-pfalz Gmbh",
    "wof:placetype":"venue"
},
  "geometry": {"coordinates":[6.7017397881,49.7387275696],"type":"Point"}
}