{
  "type": "Feature",
  "properties": {
    "iso:country":"DE",
    "sg:address":"Schiffweilerstr. 44",
    "sg:city":"Illingen",
    "sg:phone":"+49 6825/44024",
    "sg:postcode":"66557",
    "sg:province":"Saarland",
    "wof:name":"Bauunternehmung Strau\u00df Gmbh",
    "wof:placetype":"venue"
},
  "geometry": {"coordinates":[7.080087,49.387627],"type":"Point"}
}