{
  "type": "Feature",
  "properties": {
    "iso:country":"DE",
    "sg:address":"Markgrafenstr. 5",
    "sg:city":"Berlin",
    "sg:phone":"+49 30/2511670",
    "sg:postcode":"10969",
    "sg:province":"Berlin",
    "wof:name":"Dietmar Silber",
    "wof:placetype":"venue"
},
  "geometry": {"coordinates":[13.395049,52.504105],"type":"Point"}
}