{
  "type": "Feature",
  "properties": {
    "iso:country":"DE",
    "sg:address":"Friedrichstr. 11",
    "sg:city":"Ha\u00dfmersheim",
    "sg:phone":"+49 6266/242",
    "sg:postcode":"74855",
    "sg:province":"Baden-W\u00fcrttemberg",
    "wof:name":"Ev. Pfarramt",
    "wof:placetype":"venue"
},
  "geometry": {"coordinates":[9.1483488083,49.3003807068],"type":"Point"}
}