{
  "type": "Feature",
  "properties": {
    "iso:country":"DE",
    "sg:address":"Kirchberg 29",
    "sg:city":"Stallwang",
    "sg:phone":"+49 9964/297",
    "sg:postcode":"94375",
    "sg:province":"Bayern",
    "wof:name":"Georg Pielmeier",
    "wof:placetype":"venue"
},
  "geometry": {"coordinates":[12.6518907547,49.0543365479],"type":"Point"}
}