{
  "type": "Feature",
  "properties": {
    "iso:country":"DE",
    "sg:address":"Am Bahnhof 2",
    "sg:city":"Hammerbr\u00fccke",
    "sg:phone":"+49 37465/4400",
    "sg:postcode":"08269",
    "sg:province":"Sachsen",
    "wof:name":"Kamp Gute B\u00fcrom\u00f6bel Gmbh",
    "wof:placetype":"venue"
},
  "geometry": {"coordinates":[12.4077749252,50.4365768433],"type":"Point"}
}