{
  "type": "Feature",
  "properties": {
    "iso:country":"DE",
    "sg:address":"Talstr. 71",
    "sg:city":"Lohr",
    "sg:phone":"+49 9352/70770",
    "sg:postcode":"97816",
    "sg:province":"Bayern",
    "wof:name":"R. Reuter",
    "wof:placetype":"venue"
},
  "geometry": {"coordinates":[9.592522,49.958652],"type":"Point"}
}