{
  "type": "Feature",
  "properties": {
    "iso:country":"DE",
    "sg:address":"Krahmer Weg 1",
    "sg:city":"Much",
    "sg:phone":"+49 2245/2787",
    "sg:postcode":"53804",
    "sg:province":"Nordrhein-Westfalen",
    "wof:name":"Backwaren S\u00f6ntgerath Gmbh",
    "wof:placetype":"venue"
},
  "geometry": {"coordinates":[7.396083,50.904114],"type":"Point"}
}