{
  "type": "Feature",
  "properties": {
    "iso:country":"DE",
    "sg:address":"Otterweg 73",
    "sg:city":"Baldham",
    "sg:postcode":"85598",
    "sg:province":"Bayern",
    "wof:name":"Kfz-sachverst\u00e4ndigenb\u00fcro Wolfgang Wieduwild",
    "wof:placetype":"venue"
},
  "geometry": {"coordinates":[11.795455,48.100956],"type":"Point"}
}