{
  "type": "Feature",
  "properties": {
    "iso:country":"DE",
    "sg:address":"Hauptstr. 36",
    "sg:city":"Ahlen",
    "sg:phone":"+49 2528/8506",
    "sg:postcode":"59227",
    "sg:province":"Nordrhein-Westfalen",
    "wof:name":"Helmut D\u00fcchting",
    "wof:placetype":"venue"
},
  "geometry": {"coordinates":[7.945303,51.806545],"type":"Point"}
}