{
  "type": "Feature",
  "properties": {
    "iso:country":"DE",
    "sg:address":"Wigand-Gerstenberg-Str. 21",
    "sg:city":"Frankenberg",
    "sg:phone":"+49 6451/4675",
    "sg:postcode":"35066",
    "sg:province":"Hessen",
    "wof:name":"Leiterberg",
    "wof:placetype":"venue"
},
  "geometry": {"coordinates":[8.7835407257,51.0633125305],"type":"Point"}
}