{
  "type": "Feature",
  "properties": {
    "iso:country":"DE",
    "sg:address":"Zum F\u00f6rsternstein 4",
    "sg:city":"Immenhausen",
    "sg:phone":"+49 5673/1013",
    "sg:postcode":"34376",
    "sg:province":"Hessen",
    "wof:name":"Hans Lieberum Landwirtschaftl. Lohnbetrieb",
    "wof:placetype":"venue"
},
  "geometry": {"coordinates":[9.484669,51.426281],"type":"Point"}
}