{
  "type": "Feature",
  "properties": {
    "iso:country":"DE",
    "sg:address":"Friedrich-Wilhelm-Platz 3",
    "sg:city":"Berlin",
    "sg:phone":"+49 30/85961605",
    "sg:postcode":"12161",
    "sg:province":"Berlin",
    "wof:name":"Underground Mailorder",
    "wof:placetype":"venue"
},
  "geometry": {"coordinates":[13.3276767731,52.4728622437],"type":"Point"}
}