{
  "type": "Feature",
  "properties": {
    "iso:country":"DE",
    "sg:address":"Hoher Weg 4",
    "sg:city":"Hohne",
    "sg:phone":"+49 5083/858",
    "sg:postcode":"29362",
    "sg:province":"Niedersachsen",
    "wof:name":"Karl Heinrich Schulze",
    "wof:placetype":"venue"
},
  "geometry": {"coordinates":[10.375049,52.587029],"type":"Point"}
}