{
  "type": "Feature",
  "properties": {
    "iso:country":"DE",
    "sg:address":"Hauptstr. 72-74",
    "sg:city":"Trippstadt",
    "sg:phone":"+49 6306/993035",
    "sg:postcode":"67705",
    "sg:province":"Rheinland-Pfalz",
    "wof:name":"Ferien In Der Pfalz, Im Pf\u00e4lzerwald Und Toskana",
    "wof:placetype":"venue"
},
  "geometry": {"coordinates":[7.7735390663,49.3579368591],"type":"Point"}
}