{
  "type": "Feature",
  "properties": {
    "iso:country":"DE",
    "sg:address":"Karlstr. 45 b",
    "sg:city":"Karlsruhe",
    "sg:phone":"+49 721/912730",
    "sg:postcode":"76133",
    "sg:province":"Baden-W\u00fcrttemberg",
    "wof:name":"Werner Oestringer Architekt",
    "wof:placetype":"venue"
},
  "geometry": {"coordinates":[8.394922,49.006294],"type":"Point"}
}