{
  "type": "Feature",
  "properties": {
    "iso:country":"DE",
    "sg:address":"Rundweg 16",
    "sg:city":"R\u00f6merstein",
    "sg:phone":"+49 7382/7128",
    "sg:postcode":"72587",
    "sg:province":"Baden-W\u00fcrttemberg",
    "wof:name":"Traugott G\u00f6tz",
    "wof:placetype":"venue"
},
  "geometry": {"coordinates":[9.5492992401,48.4842948914],"type":"Point"}
}