{
  "type": "Feature",
  "properties": {
    "iso:country":"DE",
    "sg:address":"Linzgaustr. 32",
    "sg:city":"Uhldingen-M\u00fchlhofen",
    "sg:phone":"+49 7556/8830",
    "sg:postcode":"88690",
    "sg:province":"Baden-W\u00fcrttemberg",
    "wof:name":"Trattoria Salerno",
    "wof:placetype":"venue"
},
  "geometry": {"coordinates":[9.2426977158,47.7327842712],"type":"Point"}
}