{
  "type": "Feature",
  "properties": {
    "iso:country":"DE",
    "sg:address":"Raiffeisenstr. 10 a",
    "sg:city":"Grabenst\u00e4tt",
    "sg:phone":"+49 861/700780",
    "sg:postcode":"83355",
    "sg:province":"Bayern",
    "wof:name":"Hagebaumarkt Vilsbiburg Gmbh",
    "wof:placetype":"venue"
},
  "geometry": {"coordinates":[12.5881052017,47.8745079041],"type":"Point"}
}