{
  "type": "Feature",
  "properties": {
    "iso:country":"DE",
    "sg:address":"Alzweg 2",
    "sg:city":"Emmerting",
    "sg:postcode":"84547",
    "sg:province":"Bayern",
    "wof:name":"Anton Weidenspointner Inh. E. Rottenwallner",
    "wof:placetype":"venue"
},
  "geometry": {"coordinates":[12.77226,48.194904],"type":"Point"}
}