{
  "type": "Feature",
  "properties": {
    "iso:country":"DE",
    "sg:address":"Industriestr 14",
    "sg:city":"Rellingen",
    "sg:phone":"+49 4101/39070",
    "sg:postcode":"25462",
    "sg:province":"Schleswig-Holstein",
    "wof:name":"Hans Papenbroock Gmbh & Co",
    "wof:placetype":"venue"
},
  "geometry": {"coordinates":[9.887662,53.640179],"type":"Point"}
}