{
  "type": "Feature",
  "properties": {
    "iso:country":"DE",
    "sg:address":"An der Wieslauf 14",
    "sg:city":"Schorndorf",
    "sg:phone":"+49 7181/62609",
    "sg:postcode":"73614",
    "sg:province":"Baden-W\u00fcrttemberg",
    "wof:name":"Festhalle Haubersbronn Mehrzweckhalle",
    "wof:placetype":"venue"
},
  "geometry": {"coordinates":[9.548503,48.828999],"type":"Point"}
}