{
  "type": "Feature",
  "properties": {
    "iso:country":"DE",
    "sg:address":"Postfach 1548:: 32295 L\u00fcbbecke:: Germany.^^Bahnhofstr 3::",
    "sg:city":"L\u00fcbbecke",
    "sg:phone":"+49 5741/3280",
    "sg:postcode":"32312",
    "sg:province":"Nordrhein-Westfalen",
    "wof:name":"Volksbank L\u00fcbbecke Eg",
    "wof:placetype":"venue"
},
  "geometry": {"coordinates":[8.612882,52.303047],"type":"Point"}
}