{
  "type": "Feature",
  "properties": {
    "iso:country":"DE",
    "sg:address":"Vor dem Bardowicker Tore 21",
    "sg:city":"L\u00fcneburg",
    "sg:phone":"+49 4131/35075",
    "sg:postcode":"21339",
    "sg:province":"Niedersachsen",
    "wof:name":"Sixt-budget",
    "wof:placetype":"venue"
},
  "geometry": {"coordinates":[10.409771,53.255527],"type":"Point"}
}