{
  "type": "Feature",
  "properties": {
    "iso:country":"DE",
    "sg:address":"Von-R\u00f6der-Weg 2",
    "sg:city":"Schutterwald",
    "sg:phone":"+49 781/9900800",
    "sg:postcode":"77746",
    "sg:province":"Baden-W\u00fcrttemberg",
    "wof:name":"S. Doll Masseur",
    "wof:placetype":"venue"
},
  "geometry": {"coordinates":[7.882424,48.456139],"type":"Point"}
}