{
  "type": "Feature",
  "properties": {
    "iso:country":"DE",
    "sg:address":"Berliner Str. 104",
    "sg:city":"Hildesheim",
    "sg:phone":"+49 5121/54686",
    "sg:postcode":"31135",
    "sg:province":"Niedersachsen",
    "wof:name":"E. Westenius Nachf. Inh. Helmut Wittkamp",
    "wof:placetype":"venue"
},
  "geometry": {"coordinates":[9.981617,52.159111],"type":"Point"}
}