{
  "type": "Feature",
  "properties": {
    "iso:country":"DE",
    "sg:address":"Detterheide 24",
    "sg:city":"Nottuln",
    "sg:phone":"+49 2509/470",
    "sg:postcode":"48301",
    "sg:province":"Nordrhein-Westfalen",
    "wof:name":"Aloys Jostmeyer",
    "wof:placetype":"venue"
},
  "geometry": {"coordinates":[7.439498,51.932114],"type":"Point"}
}