{
  "type": "Feature",
  "properties": {
    "iso:country":"DE",
    "sg:address":"Gewerbestr. 11",
    "sg:city":"L\u00f6hne",
    "sg:phone":"+49 5731/81616",
    "sg:postcode":"32584",
    "sg:province":"Nordrhein-Westfalen",
    "wof:name":"Turkowski Gmbh",
    "wof:placetype":"venue"
},
  "geometry": {"coordinates":[8.757885,52.181664],"type":"Point"}
}