{
  "type": "Feature",
  "properties": {
    "iso:country":"DE",
    "sg:address":"Franz-Kissing-Str. 2",
    "sg:city":"Menden",
    "sg:phone":"+49 2373/392100",
    "sg:postcode":"58706",
    "sg:province":"Nordrhein-Westfalen",
    "wof:name":"Technofinish Gmbh",
    "wof:placetype":"venue"
},
  "geometry": {"coordinates":[7.79205,51.433949],"type":"Point"}
}