{
  "type": "Feature",
  "properties": {
    "iso:country":"DE",
    "sg:address":"Trollblumenweg 29",
    "sg:city":"Berlin",
    "sg:phone":"+49 30/6612051",
    "sg:postcode":"12357",
    "sg:province":"Berlin",
    "wof:name":"Hans Schoenthal",
    "wof:placetype":"venue"
},
  "geometry": {"coordinates":[13.482749939,52.4392776489],"type":"Point"}
}