{
  "type": "Feature",
  "properties": {
    "iso:country":"DE",
    "sg:address":"Werderstr. 123",
    "sg:city":"Heilbronn",
    "sg:phone":"+49 7131/82403",
    "sg:postcode":"74074",
    "sg:province":"Baden-W\u00fcrttemberg",
    "wof:name":"B. Sprem",
    "wof:placetype":"venue"
},
  "geometry": {"coordinates":[9.220949,49.133221],"type":"Point"}
}