{
  "type": "Feature",
  "properties": {
    "iso:country":"DE",
    "sg:address":"Ernst-Th\u00e4lmann-Str 28",
    "sg:city":"Osterburg",
    "sg:phone":"+49 3937/80135",
    "sg:postcode":"39606",
    "sg:province":"Sachsen-Anhalt",
    "wof:name":"Elektro Magerin Gmbh",
    "wof:placetype":"venue"
},
  "geometry": {"coordinates":[11.75236,52.791275],"type":"Point"}
}