{
  "type": "Feature",
  "properties": {
    "iso:country":"DE",
    "sg:address":"Bahnhofstr. 58",
    "sg:city":"Bruchhausen-Vilsen",
    "sg:phone":"+49 4252/92191",
    "sg:postcode":"27305",
    "sg:province":"Niedersachsen",
    "wof:name":"Seniorenpark Ganderkesee Gmbh",
    "wof:placetype":"venue"
},
  "geometry": {"coordinates":[8.985932,52.822231],"type":"Point"}
}