{
  "type": "Feature",
  "properties": {
    "iso:country":"DE",
    "sg:address":"Am Grabenberg 5",
    "sg:city":"Velbert",
    "sg:phone":"+49 2051/82328",
    "sg:postcode":"42551",
    "sg:province":"Nordrhein-Westfalen",
    "wof:name":"W. Und \u00c4. Sperzel Heissmangel",
    "wof:placetype":"venue"
},
  "geometry": {"coordinates":[7.0478019714,51.3502464294],"type":"Point"}
}