{
  "type": "Feature",
  "properties": {
    "iso:country":"DE",
    "sg:address":"Bismarckstr. 24",
    "sg:city":"M\u00fcllheim",
    "sg:phone":"+49 7631/2469",
    "sg:postcode":"79379",
    "sg:province":"Baden-W\u00fcrttemberg",
    "wof:name":"Otto Weber",
    "wof:placetype":"venue"
},
  "geometry": {"coordinates":[7.622365,47.811321],"type":"Point"}
}