{
  "type": "Feature",
  "properties": {
    "iso:country":"DE",
    "sg:address":"Moltkestr. 5",
    "sg:city":"Ehningen",
    "sg:phone":"+49 7034/4513",
    "sg:postcode":"71139",
    "sg:province":"Baden-W\u00fcrttemberg",
    "wof:name":"Simone Edwards",
    "wof:placetype":"venue"
},
  "geometry": {"coordinates":[8.945909,48.661697],"type":"Point"}
}