{
  "type": "Feature",
  "properties": {
    "iso:country":"DE",
    "sg:address":"Sensburger Str. 14",
    "sg:city":"M\u00fcnchen",
    "sg:phone":"+49 89/933201",
    "sg:postcode":"81929",
    "sg:province":"Bayern",
    "wof:name":"Dr. Gerhard Buchegger Rechtsanwalt",
    "wof:placetype":"venue"
},
  "geometry": {"coordinates":[11.6424541473,48.1473045349],"type":"Point"}
}