{
  "type": "Feature",
  "properties": {
    "iso:country":"DE",
    "sg:address":"Brackeler Hellweg 139",
    "sg:city":"Dortmund",
    "sg:phone":"+49 231/258043",
    "sg:postcode":"44309",
    "sg:province":"Nordrhein-Westfalen",
    "wof:name":"H. Wassenhoven Rechtsanwalt",
    "wof:placetype":"venue"
},
  "geometry": {"coordinates":[7.5473518372,51.5235290527],"type":"Point"}
}