{
  "type": "Feature",
  "properties": {
    "iso:country":"DE",
    "sg:address":"Stuttgarter Str. 8",
    "sg:city":"Maulbronn",
    "sg:phone":"+49 7043/6424",
    "sg:postcode":"75433",
    "sg:province":"Baden-W\u00fcrttemberg",
    "wof:name":"Bistro Cafe Bar",
    "wof:placetype":"venue"
},
  "geometry": {"coordinates":[8.812522,49.000038],"type":"Point"}
}