{
  "type": "Feature",
  "properties": {
    "iso:country":"DE",
    "sg:address":"Mittelgrund 1a",
    "sg:city":"Ostseebad Prerow",
    "sg:phone":"+49 38233/344",
    "sg:postcode":"18375",
    "sg:province":"Mecklenburg-Vorpommern",
    "wof:name":"Heinrich Noll",
    "wof:placetype":"venue"
},
  "geometry": {"coordinates":[12.580428,54.447906],"type":"Point"}
}