{
  "type": "Feature",
  "properties": {
    "iso:country":"DE",
    "sg:address":"Weingartener Str. 7",
    "sg:city":"Bruchsal",
    "sg:phone":"+49 7257/3983",
    "sg:postcode":"76646",
    "sg:province":"Baden-W\u00fcrttemberg",
    "wof:name":"Waltraut Kussmann Krankengymnastin",
    "wof:placetype":"venue"
},
  "geometry": {"coordinates":[8.552828,49.085667],"type":"Point"}
}