{
  "type": "Feature",
  "properties": {
    "iso:country":"DE",
    "sg:address":"Bahnstr. 39",
    "sg:city":"Mettmann",
    "sg:phone":"+49 2104/25010",
    "sg:postcode":"40822",
    "sg:province":"Nordrhein-Westfalen",
    "wof:name":"Teamtrakt Bau\u00fcbernahme Baubetreuung Gmbh",
    "wof:placetype":"venue"
},
  "geometry": {"coordinates":[6.981996,51.251312],"type":"Point"}
}