{
  "type": "Feature",
  "properties": {
    "iso:country":"DE",
    "sg:address":"Magistratsweg 122/a",
    "sg:city":"Berlin",
    "sg:phone":"+49 30/3679741",
    "sg:postcode":"13591",
    "sg:province":"Berlin",
    "wof:name":"Liedtke Und Hoffmann Rechtsanw\u00e4lte",
    "wof:placetype":"venue"
},
  "geometry": {"coordinates":[13.1579475403,52.5336380005],"type":"Point"}
}