{
  "type": "Feature",
  "properties": {
    "iso:country":"DE",
    "sg:address":"Bergstr. 13a",
    "sg:city":"Frankenberg",
    "sg:phone":"+49 6451/1724",
    "sg:postcode":"35066",
    "sg:province":"Hessen",
    "wof:name":"Peter Dornseif Architekt",
    "wof:placetype":"venue"
},
  "geometry": {"coordinates":[8.796588,51.058468],"type":"Point"}
}