{
  "type": "Feature",
  "properties": {
    "iso:country":"DE",
    "sg:address":"Schwabenheimer Str. 9",
    "sg:city":"Mannheim",
    "sg:phone":"+49 621/896592",
    "sg:postcode":"68219",
    "sg:province":"Baden-W\u00fcrttemberg",
    "wof:name":"Imbi\u00df Caravella",
    "wof:placetype":"venue"
},
  "geometry": {"coordinates":[8.5281143188,49.4338645935],"type":"Point"}
}