{
  "type": "Feature",
  "properties": {
    "iso:country":"DE",
    "sg:address":"Niendorfer Str. 68",
    "sg:city":"Hamburg",
    "sg:phone":"+49 40/5549100",
    "sg:postcode":"22529",
    "sg:province":"Hamburg",
    "wof:name":"Datatel Marketing Gmbh",
    "wof:placetype":"venue"
},
  "geometry": {"coordinates":[9.956693,53.606541],"type":"Point"}
}