{
  "type": "Feature",
  "properties": {
    "iso:country":"DE",
    "sg:address":"Bamberger Str. 20",
    "sg:city":"Zapfendorf",
    "sg:phone":"+49 9547/6820",
    "sg:postcode":"96199",
    "sg:province":"Bayern",
    "wof:name":"M. Schmitt",
    "wof:placetype":"venue"
},
  "geometry": {"coordinates":[10.929441,50.016006],"type":"Point"}
}