{
  "type": "Feature",
  "properties": {
    "iso:country":"DE",
    "sg:address":"F\u00fcnfhausenstr. 1",
    "sg:city":"Springe",
    "sg:phone":"+49 5041/970058",
    "sg:postcode":"31832",
    "sg:province":"Niedersachsen",
    "wof:name":"Rossmann Drogeriemarkt",
    "wof:placetype":"venue"
},
  "geometry": {"coordinates":[9.554729,52.209015],"type":"Point"}
}