{
  "type": "Feature",
  "properties": {
    "iso:country":"DE",
    "sg:address":"Raiffeisenstr. 6",
    "sg:city":"Meitingen",
    "sg:phone":"+49 8271/2981",
    "sg:postcode":"86405",
    "sg:province":"Bayern",
    "wof:name":"Bezirks-lagerhausgen. Wertingen Eg",
    "wof:placetype":"venue"
},
  "geometry": {"coordinates":[10.847485,48.543991],"type":"Point"}
}