{
  "type": "Feature",
  "properties": {
    "iso:country":"DE",
    "sg:address":"Rathenaustr. 28",
    "sg:city":"Werdau",
    "sg:phone":"+49 3761/2806",
    "sg:postcode":"08412",
    "sg:province":"Sachsen",
    "wof:name":"R. Kindel",
    "wof:placetype":"venue"
},
  "geometry": {"coordinates":[12.372902,50.725101],"type":"Point"}
}