{
  "type": "Feature",
  "properties": {
    "iso:country":"DE",
    "sg:address":"Rudolf-Diesel-Ring 4",
    "sg:city":"Holzkirchen",
    "sg:postcode":"83607",
    "sg:province":"Bayern",
    "wof:name":"Aldi Gmbh & Co. Kg",
    "wof:placetype":"venue"
},
  "geometry": {"coordinates":[11.7106733322,47.8829650879],"type":"Point"}
}