{
  "type": "Feature",
  "properties": {
    "iso:country":"DE",
    "sg:address":"Broitzemer Str. 244",
    "sg:city":"Braunschweig",
    "sg:phone":"+49 531/82834",
    "sg:postcode":"38118",
    "sg:province":"Niedersachsen",
    "wof:name":"Ev. Pfarramt Gem. St. Martinikirche",
    "wof:placetype":"venue"
},
  "geometry": {"coordinates":[10.5062255859,52.2591209412],"type":"Point"}
}