{
  "type": "Feature",
  "properties": {
    "iso:country":"DE",
    "sg:address":"Villiper Weg 1",
    "sg:city":"Wachtberg",
    "sg:phone":"+49 2225/3034",
    "sg:postcode":"53343",
    "sg:province":"Nordrhein-Westfalen",
    "wof:name":"R. Wei\u00dfweiler",
    "wof:placetype":"venue"
},
  "geometry": {"coordinates":[7.088033,50.609432],"type":"Point"}
}