{
  "type": "Feature",
  "properties": {
    "iso:country":"DE",
    "sg:address":"Paul-Gerhardt-Str. 13",
    "sg:city":"L\u00fcbben",
    "sg:phone":"+49 3546/3098",
    "sg:postcode":"15907",
    "sg:province":"Brandenburg",
    "wof:name":"Redaktion Lausitzer Rundschau",
    "wof:placetype":"venue"
},
  "geometry": {"coordinates":[13.8873615265,51.9374427795],"type":"Point"}
}