{
  "type": "Feature",
  "properties": {
    "iso:country":"DE",
    "sg:address":"Kanalstr. 71-73",
    "sg:city":"Berlin",
    "sg:postcode":"12357",
    "sg:province":"Berlin",
    "wof:name":"Frischbeton Bettels Berlin Verwaltungs- Gmbh",
    "wof:placetype":"venue"
},
  "geometry": {"coordinates":[13.50349617,52.4281311035],"type":"Point"}
}