{
  "type": "Feature",
  "properties": {
    "iso:country":"DE",
    "sg:address":"Paul-Gruner-Str. 64",
    "sg:city":"Leipzig",
    "sg:phone":"+49 341/2131863",
    "sg:postcode":"04107",
    "sg:province":"Sachsen",
    "wof:name":"Elster-apotheke",
    "wof:placetype":"venue"
},
  "geometry": {"coordinates":[12.369819,51.329193],"type":"Point"}
}