{
  "type": "Feature",
  "properties": {
    "iso:country":"DE",
    "sg:address":"Oeslauer Str. 115",
    "sg:city":"R\u00f6dental",
    "sg:phone":"+49 9563/4047",
    "sg:postcode":"96472",
    "sg:province":"Bayern",
    "wof:name":"Hugo Grosch E. K.",
    "wof:placetype":"venue"
},
  "geometry": {"coordinates":[11.029761,50.288525],"type":"Point"}
}