{
  "type": "Feature",
  "properties": {
    "iso:country":"DE",
    "sg:address":"Staufenbergstr. 10",
    "sg:city":"Fischbach",
    "sg:phone":"+49 6784/7478",
    "sg:postcode":"55743",
    "sg:province":"Rheinland-Pfalz",
    "wof:name":"U. Kohl",
    "wof:placetype":"venue"
},
  "geometry": {"coordinates":[7.3960208893,49.7429924011],"type":"Point"}
}