{
  "type": "Feature",
  "properties": {
    "iso:country":"DE",
    "sg:address":"L\u00fctzowstr. 100",
    "sg:city":"Berlin",
    "sg:phone":"+49 30/2308110",
    "sg:postcode":"10785",
    "sg:province":"Berlin",
    "wof:name":"Ccs Color Copy Service Sch\u00f6ning & Ruh Gmbh",
    "wof:placetype":"venue"
},
  "geometry": {"coordinates":[13.3680305481,52.5023727417],"type":"Point"}
}