{
  "type": "Feature",
  "properties": {
    "iso:country":"DE",
    "sg:address":"W\u00fclferoder Str. 14",
    "sg:city":"Hannover",
    "sg:phone":"+49 511/524413",
    "sg:postcode":"30539",
    "sg:province":"Niedersachsen",
    "wof:name":"Ernst Knackstedt",
    "wof:placetype":"venue"
},
  "geometry": {"coordinates":[9.830068,52.339252],"type":"Point"}
}