{
  "type": "Feature",
  "properties": {
    "iso:country":"DE",
    "sg:address":"Ehst 7",
    "sg:city":"Tating",
    "sg:phone":"+49 4862/990",
    "sg:postcode":"25881",
    "sg:province":"Schleswig-Holstein",
    "wof:name":"Horn Ingenieurbau Gmbh",
    "wof:placetype":"venue"
},
  "geometry": {"coordinates":[8.70275,54.301079],"type":"Point"}
}