{
  "type": "Feature",
  "properties": {
    "iso:country":"DE",
    "sg:address":"Freiburger Str. 38",
    "sg:city":"Weil am Rhein",
    "sg:phone":"+49 7621/63547",
    "sg:postcode":"79576",
    "sg:province":"Baden-W\u00fcrttemberg",
    "wof:name":"R. Vogel Masseur",
    "wof:placetype":"venue"
},
  "geometry": {"coordinates":[7.617068,47.608627],"type":"Point"}
}