{
  "type": "Feature",
  "properties": {
    "iso:country":"DE",
    "sg:address":"Hasestr. 11",
    "sg:city":"Quakenbr\u00fcck",
    "sg:phone":"+49 5431/2207",
    "sg:postcode":"49610",
    "sg:province":"Niedersachsen",
    "wof:name":"Oldenburger Hof",
    "wof:placetype":"venue"
},
  "geometry": {"coordinates":[7.9489030838,52.6758918762],"type":"Point"}
}