{
  "type": "Feature",
  "properties": {
    "iso:country":"DE",
    "sg:address":"Markt 6",
    "sg:city":"Heiligenhafen",
    "sg:phone":"+49 4362/5755",
    "sg:postcode":"23774",
    "sg:province":"Schleswig-Holstein",
    "wof:name":"Jaek-m\u00f6bel Gmbh & Co. Kg",
    "wof:placetype":"venue"
},
  "geometry": {"coordinates":[10.979426,54.374138],"type":"Point"}
}