{
  "type": "Feature",
  "properties": {
    "iso:country":"DE",
    "sg:address":"Rathausgasse 2",
    "sg:city":"Bad Schwartau",
    "sg:phone":"+49 451/292300",
    "sg:postcode":"23611",
    "sg:province":"Schleswig-Holstein",
    "wof:name":"Gunther Olbrich Rechtsanwalt Und Notar",
    "wof:placetype":"venue"
},
  "geometry": {"coordinates":[10.6962585449,53.9191398621],"type":"Point"}
}