{
  "type": "Feature",
  "properties": {
    "iso:country":"DE",
    "sg:address":"Dortelweiler Str. 83",
    "sg:city":"Frankfurt",
    "sg:phone":"+49 69/9451010",
    "sg:postcode":"60389",
    "sg:province":"Hessen",
    "wof:name":"W. Woller",
    "wof:placetype":"venue"
},
  "geometry": {"coordinates":[8.702818,50.135551],"type":"Point"}
}