{
  "type": "Feature",
  "properties": {
    "iso:country":"DE",
    "sg:address":"Brunnenstr. 29",
    "sg:city":"Kirchheim",
    "sg:phone":"+49 7021/55739",
    "sg:postcode":"73230",
    "sg:province":"Baden-W\u00fcrttemberg",
    "wof:name":"Elgert Gmbh",
    "wof:placetype":"venue"
},
  "geometry": {"coordinates":[9.483554,48.637337],"type":"Point"}
}