{
  "type": "Feature",
  "properties": {
    "iso:country":"DE",
    "sg:address":"Bernhardstr. 5",
    "sg:city":"Bad Driburg",
    "sg:phone":"+49 5253/2405",
    "sg:postcode":"33014",
    "sg:province":"Nordrhein-Westfalen",
    "wof:name":"Ursula Berka Lebensmittel",
    "wof:placetype":"venue"
},
  "geometry": {"coordinates":[9.0172433853,51.7271499634],"type":"Point"}
}