{
  "type": "Feature",
  "properties": {
    "iso:country":"DE",
    "sg:address":"Zum Lonnenhohl 7",
    "sg:city":"Dortmund",
    "sg:phone":"+49 231/9210350",
    "sg:postcode":"44319",
    "sg:province":"Nordrhein-Westfalen",
    "wof:name":"H. Wintscher Kg",
    "wof:placetype":"venue"
},
  "geometry": {"coordinates":[7.630378,51.532536],"type":"Point"}
}