{
  "type": "Feature",
  "properties": {
    "iso:country":"DE",
    "sg:address":"Marktplatz 14",
    "sg:city":"Schnaittach",
    "sg:phone":"+49 9153/216",
    "sg:postcode":"91220",
    "sg:province":"Bayern",
    "wof:name":"Jumbo Apotheke Und Parf\u00fcmerie Raffaela",
    "wof:placetype":"venue"
},
  "geometry": {"coordinates":[11.340756,49.559528],"type":"Point"}
}