{
  "type": "Feature",
  "properties": {
    "iso:country":"DE",
    "sg:address":"Borsigstr. 1",
    "sg:city":"Kaltenkirchen",
    "sg:phone":"+49 4191/99930",
    "sg:postcode":"24568",
    "sg:province":"Schleswig-Holstein",
    "wof:name":"Kl\u00fcver Aggregatebau Gmbh",
    "wof:placetype":"venue"
},
  "geometry": {"coordinates":[9.975449,53.82262],"type":"Point"}
}