{
  "type": "Feature",
  "properties": {
    "iso:country":"DE",
    "sg:address":"Brambauerstr. 71",
    "sg:city":"Waltrop",
    "sg:phone":"+49 2309/2593",
    "sg:postcode":"45731",
    "sg:province":"Nordrhein-Westfalen",
    "wof:name":"Norbert Westhoff",
    "wof:placetype":"venue"
},
  "geometry": {"coordinates":[7.433504,51.618225],"type":"Point"}
}