{
  "type": "Feature",
  "properties": {
    "iso:country":"DE",
    "sg:address":"Bocholter Str. 20",
    "sg:city":"Borken",
    "sg:phone":"+49 2861/5770",
    "sg:postcode":"46325",
    "sg:province":"Nordrhein-Westfalen",
    "wof:name":"Elda Bacchinin Romanello Roh- Und Lederwaren",
    "wof:placetype":"venue"
},
  "geometry": {"coordinates":[6.8524222374,51.8442993164],"type":"Point"}
}