{
  "type": "Feature",
  "properties": {
    "iso:country":"DE",
    "sg:address":"Sch\u00fctzdellerweg 10",
    "sg:city":"Essen",
    "sg:phone":"+49 201/492371",
    "sg:postcode":"45239",
    "sg:province":"Nordrhein-Westfalen",
    "wof:name":"Kurt Rothe",
    "wof:placetype":"venue"
},
  "geometry": {"coordinates":[6.9904828072,51.3845748901],"type":"Point"}
}