{
  "type": "Feature",
  "properties": {
    "iso:country":"DE",
    "sg:address":"Br\u00e4uhausgasse 9",
    "sg:city":"Erding",
    "sg:phone":"+49 8122/892340",
    "sg:postcode":"85435",
    "sg:province":"Bayern",
    "wof:name":"Siegfried Eschbaumer",
    "wof:placetype":"venue"
},
  "geometry": {"coordinates":[11.908782,48.307121],"type":"Point"}
}