{
  "type": "Feature",
  "properties": {
    "iso:country":"DE",
    "sg:address":"An der Rehwiese 65",
    "sg:city":"Bielefeld",
    "sg:postcode":"33617",
    "sg:province":"Nordrhein-Westfalen",
    "wof:name":"Sarepta-schule Gymnasium",
    "wof:placetype":"venue"
},
  "geometry": {"coordinates":[8.5222635269,52.0038261414],"type":"Point"}
}