{
  "type": "Feature",
  "properties": {
    "iso:country":"DE",
    "sg:address":"Schmittenwiese 12",
    "sg:city":"Attendorn",
    "sg:phone":"+49 2722/8122",
    "sg:postcode":"57439",
    "sg:province":"Nordrhein-Westfalen",
    "wof:name":"Franz Josef Wiese",
    "wof:placetype":"venue"
},
  "geometry": {"coordinates":[7.951998,51.119041],"type":"Point"}
}