{
  "type": "Feature",
  "properties": {
    "iso:country":"DE",
    "sg:address":"Helgol\u00e4nder Str. 15",
    "sg:city":"Wuppertal",
    "sg:phone":"+49 202/559509",
    "sg:postcode":"42287",
    "sg:province":"Nordrhein-Westfalen",
    "wof:name":"Remy Wilms",
    "wof:placetype":"venue"
},
  "geometry": {"coordinates":[7.197512,51.265945],"type":"Point"}
}