{
  "type": "Feature",
  "properties": {
    "iso:country":"DE",
    "sg:address":"Am Winzerkeller 2",
    "sg:city":"Gengenbach",
    "sg:phone":"+49 7803/96580",
    "sg:postcode":"77723",
    "sg:province":"Baden-W\u00fcrttemberg",
    "wof:name":"Gengenbacher Winzer- Genossenschaft Eg",
    "wof:placetype":"venue"
},
  "geometry": {"coordinates":[8.0113573074,48.3987541199],"type":"Point"}
}