{
  "type": "Feature",
  "properties": {
    "iso:country":"DE",
    "sg:address":"Hartenfelser Str. 9",
    "sg:city":"Maxsain",
    "sg:phone":"+49 2626/292",
    "sg:postcode":"56244",
    "sg:province":"Rheinland-Pfalz",
    "wof:name":"Walter Adelfang",
    "wof:placetype":"venue"
},
  "geometry": {"coordinates":[7.7862682343,50.5449714661],"type":"Point"}
}