{
  "type": "Feature",
  "properties": {
    "iso:country":"DE",
    "sg:address":"Frikenhop 11",
    "sg:city":"Rinteln",
    "sg:phone":"+49 5754/1308",
    "sg:postcode":"31737",
    "sg:province":"Niedersachsen",
    "wof:name":"Wilhelm Gro\u00dfkop",
    "wof:placetype":"venue"
},
  "geometry": {"coordinates":[9.13502,52.14151],"type":"Point"}
}