{
  "type": "Feature",
  "properties": {
    "iso:country":"DE",
    "sg:address":"Bergstr. 12",
    "sg:city":"Burgberg",
    "sg:phone":"+49 8321/3520",
    "sg:postcode":"87545",
    "sg:province":"Bayern",
    "wof:name":"G\u00e4stehaus Eugen Wei\u00df",
    "wof:placetype":"venue"
},
  "geometry": {"coordinates":[10.2879896164,47.5396537781],"type":"Point"}
}