{
  "type": "Feature",
  "properties": {
    "iso:country":"DE",
    "sg:address":"Wanheimer Str. 620-622",
    "sg:city":"Duisburg",
    "sg:phone":"+49 203/702256",
    "sg:postcode":"47249",
    "sg:province":"Nordrhein-Westfalen",
    "wof:name":"Die K\u00fcchenwelt Thomas Brag Gmbh",
    "wof:placetype":"venue"
},
  "geometry": {"coordinates":[6.7415728569,51.3854904175],"type":"Point"}
}