{
  "type": "Feature",
  "properties": {
    "iso:country":"DE",
    "sg:address":"Amerner Str. 4",
    "sg:city":"Schwalmtal",
    "sg:phone":"+49 2163/30389",
    "sg:postcode":"41366",
    "sg:province":"Nordrhein-Westfalen",
    "wof:name":"Rico K\u00fcpper Architekt",
    "wof:placetype":"venue"
},
  "geometry": {"coordinates":[6.267495,51.219254],"type":"Point"}
}