{
  "type": "Feature",
  "properties": {
    "iso:country":"DE",
    "sg:address":"Bromberger Str. 59",
    "sg:city":"M\u00fcnchen",
    "sg:phone":"+49 89/93940284",
    "sg:postcode":"81929",
    "sg:province":"Bayern",
    "wof:name":"Wecora Immobilien Gmbh",
    "wof:placetype":"venue"
},
  "geometry": {"coordinates":[11.6489553452,48.146320343],"type":"Point"}
}