{
  "type": "Feature",
  "properties": {
    "iso:country":"DE",
    "sg:city":"Salzhemmendorf",
    "sg:phone":"+49 5186/957140",
    "sg:postcode":"31020",
    "sg:province":"Niedersachsen",
    "wof:name":"Camping Humboldtsee",
    "wof:placetype":"venue"
},
  "geometry": {"coordinates":[9.59008,52.065578],"type":"Point"}
}