{
  "type": "Feature",
  "properties": {
    "iso:country":"DE",
    "sg:address":"Fischmarkt",
    "sg:city":"Regensburg",
    "sg:phone":"+49 941/52793",
    "sg:postcode":"93047",
    "sg:province":"Bayern",
    "wof:name":"M\u00fchlhiasl",
    "wof:placetype":"venue"
},
  "geometry": {"coordinates":[12.0948152542,49.0210762024],"type":"Point"}
}