{
  "type": "Feature",
  "properties": {
    "iso:country":"DE",
    "sg:address":"Wallufer Str. 1",
    "sg:city":"Mainz-Kostheim",
    "sg:phone":"+49 6134/25186",
    "sg:postcode":"55246",
    "sg:province":"Hessen",
    "wof:name":"Blue Box Gmbh",
    "wof:placetype":"venue"
},
  "geometry": {"coordinates":[8.2995662689,50.0074424744],"type":"Point"}
}