{
  "type": "Feature",
  "properties": {
    "iso:country":"DE",
    "sg:address":"Hugo-Sellheim-Str. 7",
    "sg:city":"Biblis",
    "sg:phone":"+49 6245/7143",
    "sg:postcode":"68647",
    "sg:province":"Hessen",
    "wof:name":"Karlheinz Fischer",
    "wof:placetype":"venue"
},
  "geometry": {"coordinates":[8.4522695541,49.6848144531],"type":"Point"}
}