{
  "type": "Feature",
  "properties": {
    "iso:country":"DE",
    "sg:address":"Hauptstr. 71",
    "sg:city":"Besigheim",
    "sg:phone":"+49 7143/33230",
    "sg:postcode":"74354",
    "sg:province":"Baden-W\u00fcrttemberg",
    "wof:name":"Tabler Gmbh",
    "wof:placetype":"venue"
},
  "geometry": {"coordinates":[9.1406564713,49.0019874573],"type":"Point"}
}