{
  "type": "Feature",
  "properties": {
    "iso:country":"DE",
    "sg:address":"Fuderbachsweg 5",
    "sg:city":"Bonn",
    "sg:phone":"+49 228/325582",
    "sg:postcode":"53177",
    "sg:province":"Nordrhein-Westfalen",
    "wof:name":"F. Walbr\u00f6l",
    "wof:placetype":"venue"
},
  "geometry": {"coordinates":[7.1326389313,50.6635932922],"type":"Point"}
}