{
  "type": "Feature",
  "properties": {
    "iso:country":"DE",
    "sg:address":"Turmgasse 11",
    "sg:city":"Langen",
    "sg:phone":"+49 6103/29127",
    "sg:postcode":"63225",
    "sg:province":"Hessen",
    "wof:name":"S. Tetzlaff",
    "wof:placetype":"venue"
},
  "geometry": {"coordinates":[8.6827278137,49.9898529053],"type":"Point"}
}