{
  "type": "Feature",
  "properties": {
    "iso:country":"DE",
    "sg:address":"Lohrer Str. 23",
    "sg:city":"Frammersbach",
    "sg:phone":"+49 9355/1224",
    "sg:postcode":"97833",
    "sg:province":"Bayern",
    "wof:name":"Josef Breitenbach",
    "wof:placetype":"venue"
},
  "geometry": {"coordinates":[9.4728288651,50.0632019043],"type":"Point"}
}