{
  "type": "Feature",
  "properties": {
    "iso:country":"DE",
    "sg:address":"Postfach 900217",
    "sg:city":"Potsdam",
    "sg:phone":"+49 331/7480485",
    "sg:postcode":"14438",
    "sg:province":"Brandenburg",
    "wof:name":"Telemat",
    "wof:placetype":"venue"
},
  "geometry": {"coordinates":[13.0398302078,52.3950691223],"type":"Point"}
}