{
  "type": "Feature",
  "properties": {
    "iso:country":"DE",
    "sg:address":"Rotkehlchenweg 16",
    "sg:city":"Viersen",
    "sg:phone":"+49 2162/6489",
    "sg:postcode":"41749",
    "sg:province":"Nordrhein-Westfalen",
    "wof:name":"H. Bolten-kleukers Architekt",
    "wof:placetype":"venue"
},
  "geometry": {"coordinates":[6.36534,51.281136],"type":"Point"}
}