{
  "type": "Feature",
  "properties": {
    "iso:country":"DE",
    "sg:address":"Heinrichsthaler Str. 1",
    "sg:city":"Heigenbr\u00fccken",
    "sg:phone":"+49 6020/1303",
    "sg:postcode":"63869",
    "sg:province":"Bayern",
    "wof:name":"Paletten-express Handels Gmbh",
    "wof:placetype":"venue"
},
  "geometry": {"coordinates":[9.360976,50.028011],"type":"Point"}
}