{
  "type": "Feature",
  "properties": {
    "iso:country":"DE",
    "sg:address":"Arnst\u00e4dter Str. 22",
    "sg:city":"Rudisleben",
    "sg:phone":"+49 3628/56780",
    "sg:postcode":"99334",
    "sg:province":"Th\u00fcringen",
    "wof:name":"Antec Solar Gmbh",
    "wof:placetype":"venue"
},
  "geometry": {"coordinates":[10.9675827026,50.8723144531],"type":"Point"}
}