{
  "type": "Feature",
  "properties": {
    "iso:country":"DE",
    "sg:address":"Anhalter Str. 4",
    "sg:city":"Dessau",
    "sg:phone":"+49 340/511632",
    "sg:postcode":"06847",
    "sg:province":"Sachsen-Anhalt",
    "wof:name":"Glasbau Frohberg",
    "wof:placetype":"venue"
},
  "geometry": {"coordinates":[12.153503418,51.8063240051],"type":"Point"}
}