{
  "type": "Feature",
  "properties": {
    "iso:country":"DE",
    "sg:address":"Stukenborg 27",
    "sg:city":"Vechta",
    "sg:phone":"+49 4441/2537",
    "sg:postcode":"49377",
    "sg:province":"Niedersachsen",
    "wof:name":"Siegfried Beuse",
    "wof:placetype":"venue"
},
  "geometry": {"coordinates":[8.261644,52.738213],"type":"Point"}
}