{
  "type": "Feature",
  "properties": {
    "iso:country":"DE",
    "sg:address":"Strandweg 9",
    "sg:city":"Allensbach",
    "sg:phone":"+49 7533/4091",
    "sg:postcode":"78476",
    "sg:province":"Baden-W\u00fcrttemberg",
    "wof:name":"Riemer-immobilien Gmbh",
    "wof:placetype":"venue"
},
  "geometry": {"coordinates":[9.070057869,47.7130088806],"type":"Point"}
}