{
  "type": "Feature",
  "properties": {
    "iso:country":"DE",
    "sg:address":"Teich 3",
    "sg:city":"G\u00fctenbach",
    "sg:phone":"+49 7723/7587",
    "sg:postcode":"78148",
    "sg:province":"Baden-W\u00fcrttemberg",
    "wof:name":"Josef Rombach Bildhauer",
    "wof:placetype":"venue"
},
  "geometry": {"coordinates":[8.133012,48.042999],"type":"Point"}
}