{
  "type": "Feature",
  "properties": {
    "iso:country":"DE",
    "sg:address":"Grenzstr. 1",
    "sg:city":"Seebad Heringsdorf",
    "sg:phone":"+49 38378/22971",
    "sg:postcode":"17424",
    "sg:province":"Mecklenburg-Vorpommern",
    "wof:name":"Hotel Hubertus",
    "wof:placetype":"venue"
},
  "geometry": {"coordinates":[14.1813087463,53.9465103149],"type":"Point"}
}