{
  "type": "Feature",
  "properties": {
    "iso:country":"DE",
    "sg:address":"An der Steige 4",
    "sg:city":"Oberaurach",
    "sg:phone":"+49 9522/310",
    "sg:postcode":"97514",
    "sg:province":"Bayern",
    "wof:name":"H. Buhl",
    "wof:placetype":"venue"
},
  "geometry": {"coordinates":[10.664604,49.924805],"type":"Point"}
}