{
  "type": "Feature",
  "properties": {
    "iso:country":"DE",
    "sg:address":"Schwalbacher Str. 6 a",
    "sg:city":"Lorch",
    "sg:phone":"+49 6726/9473",
    "sg:postcode":"65391",
    "sg:province":"Rheinland-Pfalz",
    "wof:name":"St. Martinus-apotheke",
    "wof:placetype":"venue"
},
  "geometry": {"coordinates":[7.803359,50.044918],"type":"Point"}
}