{
  "type": "Feature",
  "properties": {
    "iso:country":"DE",
    "sg:address":"Am Altenwalder Bahnhof 21a",
    "sg:city":"Cuxhaven",
    "sg:phone":"+49 4723/3292",
    "sg:postcode":"27478",
    "sg:province":"Niedersachsen",
    "wof:name":"Fluss- Und Hafentouristik Gmbh Carstensen",
    "wof:placetype":"venue"
},
  "geometry": {"coordinates":[8.67305,53.822571],"type":"Point"}
}