{
  "type": "Feature",
  "properties": {
    "iso:country":"DE",
    "sg:address":"Goetheweg 14",
    "sg:city":"Schauenburg",
    "sg:phone":"+49 5601/50029",
    "sg:postcode":"34270",
    "sg:province":"Hessen",
    "wof:name":"Jwo-bauhandelsges. Mbh",
    "wof:placetype":"venue"
},
  "geometry": {"coordinates":[9.3117,51.27821],"type":"Point"}
}