{
  "type": "Feature",
  "properties": {
    "iso:country":"DE",
    "sg:address":"Am Alten Sportplatz 7 a",
    "sg:city":"Seevetal",
    "sg:phone":"+49 4105/82831",
    "sg:postcode":"21220",
    "sg:province":"Niedersachsen",
    "wof:name":"Erhard Strek",
    "wof:placetype":"venue"
},
  "geometry": {"coordinates":[10.0343122482,53.3815078735],"type":"Point"}
}