{
  "type": "Feature",
  "properties": {
    "iso:country":"DE",
    "sg:address":"Gerhart-Hauptmann-Str. 11",
    "sg:city":"Bremen",
    "sg:phone":"+49 421/212853",
    "sg:postcode":"28213",
    "sg:province":"Bremen",
    "wof:name":"Hans-georg Budelmann Ingenieur",
    "wof:placetype":"venue"
},
  "geometry": {"coordinates":[8.8435087204,53.0930252075],"type":"Point"}
}