{
  "type": "Feature",
  "properties": {
    "iso:country":"DE",
    "sg:address":"Hauptstr. 150",
    "sg:city":"Behringen",
    "sg:phone":"+49 36254/71666",
    "sg:postcode":"99947",
    "sg:province":"Th\u00fcringen",
    "wof:name":"Egon Rockstuhl",
    "wof:placetype":"venue"
},
  "geometry": {"coordinates":[10.508551,51.020367],"type":"Point"}
}