{
  "type": "Feature",
  "properties": {
    "iso:country":"DE",
    "sg:address":"Allensteiner Str. 4",
    "sg:city":"Mettmann",
    "sg:postcode":"40822",
    "sg:province":"Nordrhein-Westfalen",
    "wof:name":"Pms Multi Store E. K.",
    "wof:placetype":"venue"
},
  "geometry": {"coordinates":[6.9690389633,51.2597236633],"type":"Point"}
}