{
  "type": "Feature",
  "properties": {
    "iso:country":"DE",
    "sg:address":"Marktplatz 1",
    "sg:city":"Bad Br\u00fcckenau",
    "sg:phone":"+49 9741/2088",
    "sg:postcode":"97769",
    "sg:province":"Bayern",
    "wof:name":"W\u00fcstenrot Gmbh Uwe Kessler",
    "wof:placetype":"venue"
},
  "geometry": {"coordinates":[9.791673,50.310383],"type":"Point"}
}