{
  "type": "Feature",
  "properties": {
    "iso:country":"DE",
    "sg:address":"Heinrich-Heine-Str. 4",
    "sg:city":"Beierfeld",
    "sg:phone":"+49 3774/61477",
    "sg:postcode":"08340",
    "sg:province":"Sachsen",
    "wof:name":"Heinz M\u00fcller",
    "wof:placetype":"venue"
},
  "geometry": {"coordinates":[12.78841,50.529518],"type":"Point"}
}