{
  "type": "Feature",
  "properties": {
    "iso:country":"DE",
    "sg:address":"Am Sportplatz",
    "sg:city":"Ichtershausen",
    "sg:phone":"+49 36200/6320",
    "sg:postcode":"99334",
    "sg:province":"Th\u00fcringen",
    "wof:name":"Wagner Treppen- Und Gel\u00e4nderbau Gmbh",
    "wof:placetype":"venue"
},
  "geometry": {"coordinates":[10.9662733078,50.8741188049],"type":"Point"}
}