{
  "type": "Feature",
  "properties": {
    "iso:country":"DE",
    "sg:address":"Obere Br\u00fcckenstr. 8",
    "sg:city":"Lohr",
    "sg:phone":"+49 9352/6955",
    "sg:postcode":"97816",
    "sg:province":"Bayern",
    "wof:name":"Time Out",
    "wof:placetype":"venue"
},
  "geometry": {"coordinates":[9.5768632889,49.9930648804],"type":"Point"}
}