{
  "type": "Feature",
  "properties": {
    "iso:country":"DE",
    "sg:address":"Kratzerstr. 2",
    "sg:city":"M\u00fcnchen",
    "sg:phone":"+49 89/156879",
    "sg:postcode":"80638",
    "sg:province":"Bayern",
    "wof:name":"Christian Schopp Rechtsanwalt",
    "wof:placetype":"venue"
},
  "geometry": {"coordinates":[11.5257129669,48.160610199],"type":"Point"}
}