{
  "type": "Feature",
  "properties": {
    "iso:country":"DE",
    "sg:address":"Borneweg 33",
    "sg:city":"Grebenstein",
    "sg:phone":"+49 5674/359",
    "sg:postcode":"34393",
    "sg:province":"Hessen",
    "wof:name":"Horst Jordan",
    "wof:placetype":"venue"
},
  "geometry": {"coordinates":[9.468975,51.460629],"type":"Point"}
}