{
  "type": "Feature",
  "properties": {
    "iso:country":"DE",
    "sg:address":"Frankenwaldstr. 32",
    "sg:city":"Teuschnitz",
    "sg:phone":"+49 9268/6290",
    "sg:postcode":"96358",
    "sg:province":"Bayern",
    "wof:name":"H. Friedlein Kg",
    "wof:placetype":"venue"
},
  "geometry": {"coordinates":[11.387606,50.400829],"type":"Point"}
}