{
  "type": "Feature",
  "properties": {
    "iso:country":"DE",
    "sg:address":"Ahornweg 21",
    "sg:city":"Boppard",
    "sg:phone":"+49 6742/2488",
    "sg:postcode":"56154",
    "sg:province":"Rheinland-Pfalz",
    "wof:name":"Fidula-verlag Holzmeister Gmbh",
    "wof:placetype":"venue"
},
  "geometry": {"coordinates":[7.6040530205,50.2143249512],"type":"Point"}
}