{
  "type": "Feature",
  "properties": {
    "iso:country":"DE",
    "sg:address":"Rheinstr. 29",
    "sg:city":"Frankfurt",
    "sg:phone":"+49 69/9758110",
    "sg:postcode":"60325",
    "sg:province":"Hessen",
    "wof:name":"Fritz Bauer Institut-studien- U. Dokumentationszentr. Z. Ge-",
    "wof:placetype":"venue"
},
  "geometry": {"coordinates":[8.6579666138,50.1118392944],"type":"Point"}
}