{
  "type": "Feature",
  "properties": {
    "iso:country":"DE",
    "sg:address":"Eulerstr. 10",
    "sg:city":"Oberkochen",
    "sg:phone":"+49 7364/5622",
    "sg:postcode":"73447",
    "sg:province":"Baden-W\u00fcrttemberg",
    "wof:name":"Gerhard Weber",
    "wof:placetype":"venue"
},
  "geometry": {"coordinates":[10.1138401031,48.7952003479],"type":"Point"}
}