{
  "type": "Feature",
  "properties": {
    "iso:country":"DE",
    "sg:address":"Kiebitzdeich 229",
    "sg:city":"Hamburg",
    "sg:phone":"+49 40/7235163",
    "sg:postcode":"21037",
    "sg:province":"Hamburg",
    "wof:name":"G\u00fcnter Kr\u00f6ger",
    "wof:placetype":"venue"
},
  "geometry": {"coordinates":[10.240844,53.409939],"type":"Point"}
}