{
  "type": "Feature",
  "properties": {
    "iso:country":"DE",
    "sg:address":"Hoheluftchaussee 30",
    "sg:city":"Hamburg",
    "sg:phone":"+49 40/4201601",
    "sg:postcode":"20253",
    "sg:province":"Hamburg",
    "wof:name":"H. Reimann",
    "wof:placetype":"venue"
},
  "geometry": {"coordinates":[9.9743709564,53.5801696777],"type":"Point"}
}