{
  "type": "Feature",
  "properties": {
    "iso:country":"DE",
    "sg:address":"Wiesenstr. 17",
    "sg:city":"Seebad Ahlbeck",
    "sg:phone":"+49 38378/28680",
    "sg:postcode":"17419",
    "sg:province":"Mecklenburg-Vorpommern",
    "wof:name":"Roland Kruse",
    "wof:placetype":"venue"
},
  "geometry": {"coordinates":[14.0651,53.886711],"type":"Point"}
}