{
  "type": "Feature",
  "properties": {
    "iso:country":"DE",
    "sg:address":"Davidisstr. 40",
    "sg:city":"Dortmund",
    "sg:phone":"+49 231/597351",
    "sg:postcode":"44143",
    "sg:province":"Nordrhein-Westfalen",
    "wof:name":"Tempo Petersen",
    "wof:placetype":"venue"
},
  "geometry": {"coordinates":[7.496653,51.513084],"type":"Point"}
}