{
  "type": "Feature",
  "properties": {
    "iso:country":"DE",
    "sg:address":"Sim-J\u00fc 4",
    "sg:city":"Werne",
    "sg:postcode":"59368",
    "sg:province":"Nordrhein-Westfalen",
    "wof:name":"Franck M. Stogbr\u00fcger Brauerei Gmbh",
    "wof:placetype":"venue"
},
  "geometry": {"coordinates":[7.64081,51.661579],"type":"Point"}
}