{
  "type": "Feature",
  "properties": {
    "iso:country":"DE",
    "sg:address":"Erbacher Str. 12",
    "sg:city":"Eltville",
    "sg:phone":"+49 6123/3453",
    "sg:postcode":"65343",
    "sg:province":"Hessen",
    "wof:name":"Willy Jamm Kameramann",
    "wof:placetype":"venue"
},
  "geometry": {"coordinates":[8.1119070053,50.02293396],"type":"Point"}
}