{
  "type": "Feature",
  "properties": {
    "iso:country":"DE",
    "sg:address":"Wallen-Lienen 16",
    "sg:city":"Tecklenburg",
    "sg:phone":"+49 5455/1266",
    "sg:postcode":"49545",
    "sg:province":"Nordrhein-Westfalen",
    "wof:name":"Hugo Helmig",
    "wof:placetype":"venue"
},
  "geometry": {"coordinates":[7.761353,52.210442],"type":"Point"}
}