{
  "type": "Feature",
  "properties": {
    "iso:country":"DE",
    "sg:address":"Richtweg 33",
    "sg:city":"Wendelstein",
    "sg:phone":"+49 9129/7328",
    "sg:postcode":"90530",
    "sg:province":"Bayern",
    "wof:name":"Siemens Ag",
    "wof:placetype":"venue"
},
  "geometry": {"coordinates":[11.1587877274,49.3527526855],"type":"Point"}
}