{
  "type": "Feature",
  "properties": {
    "iso:country":"DE",
    "sg:address":"Ludwigsplatz 36",
    "sg:city":"Straubing",
    "sg:phone":"+49 9421/82931",
    "sg:postcode":"94315",
    "sg:province":"Bayern",
    "wof:name":"Orsay",
    "wof:placetype":"venue"
},
  "geometry": {"coordinates":[12.570968,48.881836],"type":"Point"}
}