{
  "type": "Feature",
  "properties": {
    "iso:country":"DE",
    "sg:address":"Breite Gasse 76",
    "sg:city":"N\u00fcrnberg",
    "sg:phone":"+49 202/454013",
    "sg:postcode":"90402",
    "sg:province":"Bayern",
    "wof:name":"Runners Point Warenhandelsgesellschaft Mbh",
    "wof:placetype":"venue"
},
  "geometry": {"coordinates":[11.0726737976,49.4503364563],"type":"Point"}
}