{
  "type": "Feature",
  "properties": {
    "iso:country":"DE",
    "sg:address":"W\u00fcrzburg",
    "sg:city":"W\u00fcrzburg",
    "sg:phone":"+49 931/18761",
    "sg:postcode":"97070",
    "sg:province":"Bayern",
    "wof:name":"Service Bank Gmbh Von 1954",
    "wof:placetype":"venue"
},
  "geometry": {"coordinates":[9.93389,49.793701],"type":"Point"}
}