{
  "type": "Feature",
  "properties": {
    "iso:country":"DE",
    "sg:address":"Pontstr. 39",
    "sg:city":"Aachen",
    "sg:phone":"+49 241/36560",
    "sg:postcode":"52062",
    "sg:province":"Nordrhein-Westfalen",
    "wof:name":"Cafe Kittel Gastronomie Gmbh",
    "wof:placetype":"venue"
},
  "geometry": {"coordinates":[6.082065,50.778038],"type":"Point"}
}