{
  "type": "Feature",
  "properties": {
    "iso:country":"DE",
    "sg:address":"Strelitzer Str. 32",
    "sg:city":"Mirow",
    "sg:phone":"+49 39833/22222",
    "sg:postcode":"17252",
    "sg:province":"Mecklenburg-Vorpommern",
    "wof:name":"Blume & Kunst",
    "wof:placetype":"venue"
},
  "geometry": {"coordinates":[12.8160877228,53.2742233276],"type":"Point"}
}