{
  "type": "Feature",
  "properties": {
    "iso:country":"DE",
    "sg:address":"Badermelcherweg 1",
    "sg:city":"Dietramszell",
    "sg:phone":"+49 8027/539",
    "sg:postcode":"83623",
    "sg:province":"Bayern",
    "wof:name":"W. Haller Gmbh",
    "wof:placetype":"venue"
},
  "geometry": {"coordinates":[11.591269,47.852924],"type":"Point"}
}