{
  "type": "Feature",
  "properties": {
    "iso:country":"DE",
    "sg:address":"Goethestr 7",
    "sg:city":"Chemnitz",
    "sg:phone":"+49 371/3691012",
    "sg:postcode":"09119",
    "sg:province":"Sachsen",
    "wof:name":"Reha-aktiv Gmbh",
    "wof:placetype":"venue"
},
  "geometry": {"coordinates":[12.905735,50.824341],"type":"Point"}
}