{
  "type": "Feature",
  "properties": {
    "iso:country":"DE",
    "sg:address":"Vaihinger Str. 50",
    "sg:city":"Leinfelden-Echterdingen",
    "sg:phone":"+49 711/7545406",
    "sg:postcode":"70771",
    "sg:province":"Baden-W\u00fcrttemberg",
    "wof:name":"Waldheim",
    "wof:placetype":"venue"
},
  "geometry": {"coordinates":[9.1131868362,48.7057380676],"type":"Point"}
}