{
  "type": "Feature",
  "properties": {
    "iso:country":"DE",
    "sg:address":"Weidestr. 85",
    "sg:city":"Hamburg",
    "sg:phone":"+49 40/2798922",
    "sg:postcode":"22083",
    "sg:province":"Hamburg",
    "wof:name":"David Landau",
    "wof:placetype":"venue"
},
  "geometry": {"coordinates":[10.0306444168,53.5799293518],"type":"Point"}
}