{
  "type": "Feature",
  "properties": {
    "iso:country":"DE",
    "sg:address":"Clemensstr. 8",
    "sg:city":"Koblenz",
    "sg:phone":"+49 261/17797",
    "sg:postcode":"56068",
    "sg:province":"Rheinland-Pfalz",
    "wof:name":"Praxis Dr. Med. Bohner-haas Und Dr. Med. Haas",
    "wof:placetype":"venue"
},
  "geometry": {"coordinates":[7.5991840363,50.3586921692],"type":"Point"}
}