{
  "type": "Feature",
  "properties": {
    "iso:country":"DE",
    "sg:address":"Passauer Str. 6",
    "sg:city":"Obernzell",
    "sg:phone":"+49 8591/93169",
    "sg:postcode":"94130",
    "sg:province":"Bayern",
    "wof:name":"Vds Versicherungs-direkt- Service Gmbh",
    "wof:placetype":"venue"
},
  "geometry": {"coordinates":[13.631524086,48.556186676],"type":"Point"}
}