{
  "type": "Feature",
  "properties": {
    "iso:country":"DE",
    "sg:address":"Halfenstr. 5",
    "sg:city":"P\u00f6lich",
    "sg:phone":"+49 6507/993066",
    "sg:postcode":"54340",
    "sg:province":"Rheinland-Pfalz",
    "wof:name":"Seniorenresidenz St. Andreas P\u00f6lich Gmbh",
    "wof:placetype":"venue"
},
  "geometry": {"coordinates":[6.84991,49.79845],"type":"Point"}
}