{
  "type": "Feature",
  "properties": {
    "iso:country":"DE",
    "sg:address":"Karlstr. 24",
    "sg:city":"Rastatt",
    "sg:phone":"+49 7222/32260",
    "sg:postcode":"76437",
    "sg:province":"Baden-W\u00fcrttemberg",
    "wof:name":"Storchennest",
    "wof:placetype":"venue"
},
  "geometry": {"coordinates":[8.209856987,48.8525161743],"type":"Point"}
}