{
  "type": "Feature",
  "properties": {
    "iso:country":"DE",
    "sg:address":"Tiefenbachstr. 5",
    "sg:city":"Hausham",
    "sg:phone":"+49 8026/91670",
    "sg:postcode":"83734",
    "sg:province":"Bayern",
    "wof:name":"Kroha Druck Gmbh",
    "wof:placetype":"venue"
},
  "geometry": {"coordinates":[11.8270988464,47.764591217],"type":"Point"}
}