{
  "type": "Feature",
  "properties": {
    "iso:country":"DE",
    "sg:address":"Auf der H\u00f6he 45",
    "sg:city":"Stolberg",
    "sg:phone":"+49 2402/81387",
    "sg:postcode":"52223",
    "sg:province":"Nordrhein-Westfalen",
    "wof:name":"Bert Kiver Ingenieur",
    "wof:placetype":"venue"
},
  "geometry": {"coordinates":[6.2208647728,50.7533378601],"type":"Point"}
}