{
  "type": "Feature",
  "properties": {
    "iso:country":"DE",
    "sg:address":"Triftweg 20",
    "sg:city":"Birkenwerder",
    "sg:phone":"+49 3303/502935",
    "sg:postcode":"16547",
    "sg:province":"Brandenburg",
    "wof:name":"Druck Punkt Birkenwerder Gmbh",
    "wof:placetype":"venue"
},
  "geometry": {"coordinates":[13.2703313828,52.6969223022],"type":"Point"}
}