{
  "type": "Feature",
  "properties": {
    "iso:country":"DE",
    "sg:address":"Dr.-M\u00fcller-Desterro-Str. 12",
    "sg:city":"Windischholzhausen",
    "sg:phone":"+49 361/413632",
    "sg:postcode":"99102",
    "sg:province":"Th\u00fcringen",
    "wof:name":"Volker Koch",
    "wof:placetype":"venue"
},
  "geometry": {"coordinates":[11.0938625336,50.9462890625],"type":"Point"}
}