{
  "type": "Feature",
  "properties": {
    "iso:country":"DE",
    "sg:address":"Bildstocker Markt",
    "sg:city":"Friedrichsthal",
    "sg:phone":"+49 6897/8313",
    "sg:postcode":"66299",
    "sg:province":"Saarland",
    "wof:name":"Mode Reuter",
    "wof:placetype":"venue"
},
  "geometry": {"coordinates":[7.0891451836,49.3208198547],"type":"Point"}
}