{
  "type": "Feature",
  "properties": {
    "iso:country":"DE",
    "sg:address":"Am Buchenst\u00fcck 9",
    "sg:city":"Schwerte",
    "sg:phone":"+49 2304/68528",
    "sg:postcode":"58239",
    "sg:province":"Nordrhein-Westfalen",
    "wof:name":"Karl-heinz Weber Ingenieur",
    "wof:placetype":"venue"
},
  "geometry": {"coordinates":[7.5306692123,51.4262466431],"type":"Point"}
}