{
  "type": "Feature",
  "properties": {
    "iso:country":"DE",
    "sg:address":"Gro\u00dfe Elbstr. 38",
    "sg:city":"Hamburg",
    "sg:phone":"+49 40/3192046",
    "sg:postcode":"22767",
    "sg:province":"Hamburg",
    "wof:name":"Engineering Und Trading J\u00fcrgen Seyfert Gmbh",
    "wof:placetype":"venue"
},
  "geometry": {"coordinates":[9.950687,53.545029],"type":"Point"}
}