{
  "type": "Feature",
  "properties": {
    "iso:country":"DE",
    "sg:address":"Bahnhofstr. 4",
    "sg:city":"Stollberg",
    "sg:phone":"+49 37296/2105",
    "sg:postcode":"09366",
    "sg:province":"Sachsen",
    "wof:name":"Lsk Immobilien Und Bautr\u00e4ger Gmbh",
    "wof:placetype":"venue"
},
  "geometry": {"coordinates":[12.7704391479,50.7040596008],"type":"Point"}
}