{
  "type": "Feature",
  "properties": {
    "iso:country":"DE",
    "sg:address":"QUADENWEG 6a",
    "sg:city":"Wesel",
    "sg:phone":"+49 281/51485",
    "sg:postcode":"46485",
    "sg:province":"Nordrhein-Westfalen",
    "wof:name":"Von Hippel Gmbh",
    "wof:placetype":"venue"
},
  "geometry": {"coordinates":[6.631539,51.661678],"type":"Point"}
}