{
  "type": "Feature",
  "properties": {
    "iso:country":"DE",
    "sg:address":"Ahrenshooper Zeile 15",
    "sg:city":"Berlin",
    "sg:phone":"+49 30/8017103",
    "sg:postcode":"14129",
    "sg:province":"Berlin",
    "wof:name":"Dr. Med. Jantje Wessel",
    "wof:placetype":"venue"
},
  "geometry": {"coordinates":[13.2214765549,52.438999176],"type":"Point"}
}