{
  "type": "Feature",
  "properties": {
    "iso:country":"DE",
    "sg:address":"Am Heidkamp 26",
    "sg:city":"Wedemark",
    "sg:phone":"+49 5130/3444",
    "sg:postcode":"30900",
    "sg:province":"Niedersachsen",
    "wof:name":"Horst G\u00f6rries",
    "wof:placetype":"venue"
},
  "geometry": {"coordinates":[9.708688,52.594112],"type":"Point"}
}