{
  "type": "Feature",
  "properties": {
    "iso:country":"DE",
    "sg:address":"Gm\u00fcnder Str. 16",
    "sg:city":"Heubach",
    "sg:phone":"+49 7173/6731",
    "sg:postcode":"73540",
    "sg:province":"Baden-W\u00fcrttemberg",
    "wof:name":"Eiscafe Etna",
    "wof:placetype":"venue"
},
  "geometry": {"coordinates":[9.9319601059,48.7931022644],"type":"Point"}
}