{
  "type": "Feature",
  "properties": {
    "iso:country":"DE",
    "sg:address":"Blumentalstr. 134 A",
    "sg:city":"Krefeld",
    "sg:phone":"+49 2151/67311",
    "sg:postcode":"47798",
    "sg:province":"Nordrhein-Westfalen",
    "wof:name":"Grafische Werkstatt Weilandt Gmbh",
    "wof:placetype":"venue"
},
  "geometry": {"coordinates":[6.559576,51.34219],"type":"Point"}
}