{
  "type": "Feature",
  "properties": {
    "iso:country":"DE",
    "sg:address":"Am Pferdemarkt 61",
    "sg:city":"Langenhagen",
    "sg:postcode":"30853",
    "sg:province":"Niedersachsen",
    "wof:name":"Ev Electronic Gmbh",
    "wof:placetype":"venue"
},
  "geometry": {"coordinates":[9.728171,52.453671],"type":"Point"}
}