{
  "type": "Feature",
  "properties": {
    "iso:country":"DE",
    "sg:address":"Marcel-Verfaillie-Allee 14a",
    "sg:city":"M\u00fchlhausen",
    "sg:phone":"+49 36018/3020",
    "sg:postcode":"99974",
    "sg:province":"Th\u00fcringen",
    "wof:name":"Wohnungsgenossenschaft M\u00fchlhausen Eg",
    "wof:placetype":"venue"
},
  "geometry": {"coordinates":[10.440884,51.206501],"type":"Point"}
}