{
  "type": "Feature",
  "properties": {
    "iso:country":"DE",
    "sg:address":"Am G\u00e4nserain",
    "sg:city":"Gospiteroda",
    "sg:phone":"+49 3622/40240",
    "sg:postcode":"99880",
    "sg:province":"Th\u00fcringen",
    "wof:name":"Rena Recycling Und Naturstein Gmbh",
    "wof:placetype":"venue"
},
  "geometry": {"coordinates":[10.5551204681,50.8978042603],"type":"Point"}
}