{
  "type": "Feature",
  "properties": {
    "iso:country":"DE",
    "sg:address":"Bahnhofplatz 1::",
    "sg:city":"Munich",
    "sg:postcode":"80335",
    "sg:province":"Bayern",
    "wof:name":"Milpitas Beteiligungs- Gmbh",
    "wof:placetype":"venue"
},
  "geometry": {"coordinates":[8.409202,49.010376],"type":"Point"}
}