{
  "type": "Feature",
  "properties": {
    "iso:country":"DE",
    "sg:address":"Im Gewerbepark",
    "sg:city":"Espenau",
    "sg:postcode":"34314",
    "sg:province":"Hessen",
    "wof:name":"Waldeier Bau Gmbh",
    "wof:placetype":"venue"
},
  "geometry": {"coordinates":[9.45642,51.387775],"type":"Point"}
}