{
  "type": "Feature",
  "properties": {
    "iso:country":"DE",
    "sg:address":"Industriestr 26",
    "sg:city":"Sch\u00fcttorf",
    "sg:phone":"+49 5923/1475",
    "sg:postcode":"48465",
    "sg:province":"Niedersachsen",
    "wof:name":"Druckerei Zech & Co Kg",
    "wof:placetype":"venue"
},
  "geometry": {"coordinates":[7.2490429878,52.3387756348],"type":"Point"}
}