{
  "type": "Feature",
  "properties": {
    "iso:country":"DE",
    "sg:address":"Siederstr. 12",
    "sg:city":"Werl",
    "sg:phone":"+49 2922/87800",
    "sg:postcode":"59457",
    "sg:province":"Nordrhein-Westfalen",
    "wof:name":"Euroliquid Ohg",
    "wof:placetype":"venue"
},
  "geometry": {"coordinates":[7.9122200012,51.5541038513],"type":"Point"}
}