{
  "type": "Feature",
  "properties": {
    "iso:country":"DE",
    "sg:address":"Langgasse 21",
    "sg:city":"Eisenheim",
    "sg:phone":"+49 9386/285",
    "sg:postcode":"97247",
    "sg:province":"Bayern",
    "wof:name":"Hirschen",
    "wof:placetype":"venue"
},
  "geometry": {"coordinates":[10.1584978104,49.8821258545],"type":"Point"}
}