{
  "type": "Feature",
  "properties": {
    "iso:country":"DE",
    "sg:address":"Landwehrstr. 29",
    "sg:city":"Lohne",
    "sg:phone":"+49 4442/2274",
    "sg:postcode":"49393",
    "sg:province":"Niedersachsen",
    "wof:name":"Annonca-verlags- Gmbh",
    "wof:placetype":"venue"
},
  "geometry": {"coordinates":[8.2455749512,52.6618080139],"type":"Point"}
}