{
  "type": "Feature",
  "properties": {
    "iso:country":"DE",
    "sg:address":"Mausegatt 61",
    "sg:city":"Bochum",
    "sg:phone":"+49 2327/10797",
    "sg:postcode":"44866",
    "sg:province":"Nordrhein-Westfalen",
    "wof:name":"A. Rieboldt",
    "wof:placetype":"venue"
},
  "geometry": {"coordinates":[7.1638507843,51.4842414856],"type":"Point"}
}