{
  "type": "Feature",
  "properties": {
    "iso:country":"DE",
    "sg:address":"An der Krone 5",
    "sg:city":"Enkirch",
    "sg:phone":"+49 6541/1207",
    "sg:postcode":"56850",
    "sg:province":"Rheinland-Pfalz",
    "wof:name":"Hans-f. Georg",
    "wof:placetype":"venue"
},
  "geometry": {"coordinates":[7.1255512238,49.9835090637],"type":"Point"}
}