{
  "type": "Feature",
  "properties": {
    "iso:country":"DE",
    "sg:address":"Lauchst\u00e4dter Weg 33",
    "sg:city":"Berlin",
    "sg:phone":"+49 30/6611747",
    "sg:postcode":"12355",
    "sg:province":"Berlin",
    "wof:name":"Wolfgang Bullerdieck",
    "wof:placetype":"venue"
},
  "geometry": {"coordinates":[13.4811162949,52.4136123657],"type":"Point"}
}