{
  "type": "Feature",
  "properties": {
    "iso:country":"DE",
    "sg:address":"Arabellastr. 5",
    "sg:city":"M\u00fcnchen",
    "sg:phone":"+49 89/911955",
    "sg:postcode":"81925",
    "sg:province":"Bayern",
    "wof:name":"Arabella - Apotheke Wolfgang Bernhard",
    "wof:placetype":"venue"
},
  "geometry": {"coordinates":[11.618008,48.150734],"type":"Point"}
}