{
  "type": "Feature",
  "properties": {
    "iso:country":"DE",
    "sg:address":"Weidestr. 12",
    "sg:city":"Idstein",
    "sg:phone":"+49 6434/8087",
    "sg:postcode":"65510",
    "sg:province":"Hessen",
    "wof:name":"Edith Scholtes",
    "wof:placetype":"venue"
},
  "geometry": {"coordinates":[8.2789096832,50.2666893005],"type":"Point"}
}