{
  "type": "Feature",
  "properties": {
    "iso:country":"DE",
    "sg:address":"Schnittert 25",
    "sg:city":"Solingen",
    "sg:phone":"+49 212/2681874",
    "sg:postcode":"42697",
    "sg:province":"Nordrhein-Westfalen",
    "wof:name":"Outfit Marketing Gmbh",
    "wof:placetype":"venue"
},
  "geometry": {"coordinates":[7.001745224,51.1704292297],"type":"Point"}
}