{
  "type": "Feature",
  "properties": {
    "iso:country":"DE",
    "sg:address":"Bahnhofsplatz 8",
    "sg:city":"Trier",
    "sg:phone":"+49 651/25190",
    "sg:postcode":"54292",
    "sg:province":"Rheinland-Pfalz",
    "wof:name":"Usw Warenvertriebsgesellschaft Lang Gmbh",
    "wof:placetype":"venue"
},
  "geometry": {"coordinates":[6.651325,49.757439],"type":"Point"}
}