{
  "type": "Feature",
  "properties": {
    "iso:country":"DE",
    "sg:address":"Hauptstr. 49",
    "sg:city":"Durmersheim",
    "sg:phone":"+49 7245/93260",
    "sg:postcode":"76448",
    "sg:province":"Baden-W\u00fcrttemberg",
    "wof:name":"Hotel Adler",
    "wof:placetype":"venue"
},
  "geometry": {"coordinates":[8.2672843933,48.9298019409],"type":"Point"}
}