{
  "type": "Feature",
  "properties": {
    "iso:country":"DE",
    "sg:address":"Sch\u00fctzenstr. 30",
    "sg:city":"Bamberg",
    "sg:phone":"+49 951/28880",
    "sg:postcode":"96047",
    "sg:province":"Bayern",
    "wof:name":"Inside Werbung",
    "wof:placetype":"venue"
},
  "geometry": {"coordinates":[10.8953933716,49.8880882263],"type":"Point"}
}