{
  "type": "Feature",
  "properties": {
    "iso:country":"DE",
    "sg:address":"Heilbronner Str 20",
    "sg:city":"Obersulm",
    "sg:phone":"+49 5922/2314",
    "sg:postcode":"74182",
    "sg:province":"Baden-W\u00fcrttemberg",
    "wof:name":"Volksbank Obergrafschaft Eg",
    "wof:placetype":"venue"
},
  "geometry": {"coordinates":[7.11716,52.307049],"type":"Point"}
}