{
  "type": "Feature",
  "properties": {
    "iso:country":"DE",
    "sg:address":"Putzbrunner Str. 136",
    "sg:city":"Ottobrunn",
    "sg:phone":"+49 89/66002117",
    "sg:postcode":"85521",
    "sg:province":"Bayern",
    "wof:name":"Altschmied Gmbh",
    "wof:placetype":"venue"
},
  "geometry": {"coordinates":[11.6915636063,48.0726585388],"type":"Point"}
}