{
  "type": "Feature",
  "properties": {
    "iso:country":"DE",
    "sg:address":"Pionierstr. 22",
    "sg:city":"D\u00fcsseldorf",
    "sg:postcode":"40215",
    "sg:province":"Nordrhein-Westfalen",
    "wof:name":"Bemacon Im- Und Export Gmbh",
    "wof:placetype":"venue"
},
  "geometry": {"coordinates":[6.7858772278,51.2174377441],"type":"Point"}
}