{
  "type": "Feature",
  "properties": {
    "iso:country":"DE",
    "sg:address":"Leimengr\u00fcbweg 4",
    "sg:city":"Weinheim",
    "sg:phone":"+49 6201/61195",
    "sg:postcode":"69469",
    "sg:province":"Baden-W\u00fcrttemberg",
    "wof:name":"Ulrike Grether Heilpraktikerin",
    "wof:placetype":"venue"
},
  "geometry": {"coordinates":[8.6669940948,49.5377960205],"type":"Point"}
}