{
  "type": "Feature",
  "properties": {
    "iso:country":"DE",
    "sg:address":"Kirchmoor 20",
    "sg:city":"Hohenfelde",
    "sg:phone":"+49 4127/475",
    "sg:postcode":"25358",
    "sg:province":"Schleswig-Holstein",
    "wof:name":"Walter Twiesselmann",
    "wof:placetype":"venue"
},
  "geometry": {"coordinates":[9.626677,53.835758],"type":"Point"}
}