{
  "type": "Feature",
  "properties": {
    "iso:country":"DE",
    "sg:address":"Mo\u00dfkopfring 12",
    "sg:city":"Berlin",
    "sg:phone":"+49 30/6759438",
    "sg:postcode":"12527",
    "sg:province":"Berlin",
    "wof:name":"Joachim Arndt",
    "wof:placetype":"venue"
},
  "geometry": {"coordinates":[13.649698,52.342491],"type":"Point"}
}