{
  "type": "Feature",
  "properties": {
    "iso:country":"DE",
    "sg:address":"Am Gau",
    "sg:city":"Ringgau",
    "sg:postcode":"37296",
    "sg:province":"Hessen",
    "wof:name":"Ev. \u00f6ffentliche Bibliothek Modelljugendb\u00fccherei",
    "wof:placetype":"venue"
},
  "geometry": {"coordinates":[10.038115,51.081081],"type":"Point"}
}