{
  "type": "Feature",
  "properties": {
    "iso:country":"DE",
    "sg:address":"Hohenstaufenstr. 4",
    "sg:city":"D\u00fcsseldorf",
    "sg:postcode":"40547",
    "sg:province":"Nordrhein-Westfalen",
    "wof:name":"J\u00fcrgs Thomas Howell Und Kiewit",
    "wof:placetype":"venue"
},
  "geometry": {"coordinates":[6.7597942352,51.2360076904],"type":"Point"}
}