{
  "type": "Feature",
  "properties": {
    "iso:country":"DE",
    "sg:address":"Liebknechtstr. 10",
    "sg:city":"Beeskow",
    "sg:postcode":"15848",
    "sg:province":"Brandenburg",
    "wof:name":"Katholisches Pfarramt Beeskow",
    "wof:placetype":"venue"
},
  "geometry": {"coordinates":[14.2393884659,52.1708374023],"type":"Point"}
}