{
  "type": "Feature",
  "properties": {
    "iso:country":"DE",
    "sg:address":"Springenkamp 58",
    "sg:city":"Olfen",
    "sg:phone":"+49 2595/384141",
    "sg:postcode":"59399",
    "sg:province":"Nordrhein-Westfalen",
    "wof:name":"Everbrite Europe Gmbh",
    "wof:placetype":"venue"
},
  "geometry": {"coordinates":[7.371138,51.710682],"type":"Point"}
}