{
  "type": "Feature",
  "properties": {
    "iso:country":"DE",
    "sg:address":"Stra\u00dfe des Friedens 1-7",
    "sg:city":"S\u00f6mmerda",
    "sg:phone":"+49 3634/612103",
    "sg:postcode":"99610",
    "sg:province":"Th\u00fcringen",
    "wof:name":"Sonnen-apotheke",
    "wof:placetype":"venue"
},
  "geometry": {"coordinates":[11.13112,51.158501],"type":"Point"}
}