{
  "type": "Feature",
  "properties": {
    "iso:country":"DE",
    "sg:address":"Blumenthal",
    "sg:city":"Aichach",
    "sg:phone":"+49 8251/6970",
    "sg:postcode":"86551",
    "sg:province":"Bayern",
    "wof:name":"Volker Dahm Kunstmaler",
    "wof:placetype":"venue"
},
  "geometry": {"coordinates":[11.14621,48.41943],"type":"Point"}
}