{
  "type": "Feature",
  "properties": {
    "iso:country":"DE",
    "sg:address":"Fr\u00fchlingstr. 10",
    "sg:city":"Balingen",
    "sg:phone":"+49 7433/21720",
    "sg:postcode":"72336",
    "sg:province":"Baden-W\u00fcrttemberg",
    "wof:name":"K. Fuchs",
    "wof:placetype":"venue"
},
  "geometry": {"coordinates":[8.8430776596,48.2996368408],"type":"Point"}
}