{
  "type": "Feature",
  "properties": {
    "iso:country":"DE",
    "sg:address":"Bahnhofsallee 1 B",
    "sg:city":"G\u00f6ttingen",
    "sg:phone":"+49 551/3700000",
    "sg:postcode":"37081",
    "sg:province":"Niedersachsen",
    "wof:name":"Ser Net Service Network Gmbh",
    "wof:placetype":"venue"
},
  "geometry": {"coordinates":[9.9225492477,51.5354232788],"type":"Point"}
}