{
  "type": "Feature",
  "properties": {
    "iso:country":"DE",
    "sg:address":"Nicolaisteg 1",
    "sg:city":"Mei\u00dfen",
    "sg:phone":"+49 3521/454021",
    "sg:postcode":"01662",
    "sg:province":"Sachsen",
    "wof:name":"P. Seifert",
    "wof:placetype":"venue"
},
  "geometry": {"coordinates":[13.4698266983,51.1589889526],"type":"Point"}
}