{
  "type": "Feature",
  "properties": {
    "iso:country":"DE",
    "sg:address":"Azaleenweg 3",
    "sg:city":"Dresden",
    "sg:phone":"+49 351/2591927",
    "sg:postcode":"01279",
    "sg:province":"Sachsen",
    "wof:name":"Dr.pappritz, Schirmer & Partner",
    "wof:placetype":"venue"
},
  "geometry": {"coordinates":[13.8288516998,51.0240020752],"type":"Point"}
}