{
  "type": "Feature",
  "properties": {
    "iso:country":"DE",
    "sg:address":"Im Hebsack 11",
    "sg:city":"Rot",
    "sg:phone":"+49 8395/1869",
    "sg:postcode":"88430",
    "sg:province":"Baden-W\u00fcrttemberg",
    "wof:name":"Hans-dieter Schwarzbart Masseur",
    "wof:placetype":"venue"
},
  "geometry": {"coordinates":[10.027613,48.01059],"type":"Point"}
}