{
  "type": "Feature",
  "properties": {
    "iso:country":"DE",
    "sg:address":"Seebruchstr. 51a",
    "sg:city":"Vlotho",
    "sg:phone":"+49 5733/960482",
    "sg:postcode":"32602",
    "sg:province":"Nordrhein-Westfalen",
    "wof:name":"Standard Life Versicherung T. Kr\u00f6mker",
    "wof:placetype":"venue"
},
  "geometry": {"coordinates":[8.8522062302,52.1321792603],"type":"Point"}
}