{
  "type": "Feature",
  "properties": {
    "iso:country":"DE",
    "sg:address":"Markt 26",
    "sg:city":"Merseburg",
    "sg:phone":"+49 3461/200970",
    "sg:postcode":"06217",
    "sg:province":"Sachsen-Anhalt",
    "wof:name":"Hartmut Klaus Rechtsanwalt",
    "wof:placetype":"venue"
},
  "geometry": {"coordinates":[11.9985799789,51.3551292419],"type":"Point"}
}