{
  "type": "Feature",
  "properties": {
    "iso:country":"DE",
    "sg:address":"Albert-Einstein-Str. 11",
    "sg:city":"Seelze",
    "sg:phone":"+49 511/481491",
    "sg:postcode":"30926",
    "sg:province":"Niedersachsen",
    "wof:name":"Hahn Bedachungen Gmbh",
    "wof:placetype":"venue"
},
  "geometry": {"coordinates":[9.638326,52.387394],"type":"Point"}
}