{
  "type": "Feature",
  "properties": {
    "iso:country":"DE",
    "sg:address":"Schlo\u00dfberg 17",
    "sg:city":"Pforzheim",
    "sg:phone":"+49 7231/36889",
    "sg:postcode":"75175",
    "sg:province":"Baden-W\u00fcrttemberg",
    "wof:name":"P. Kurz Neuheitenvertrieb",
    "wof:placetype":"venue"
},
  "geometry": {"coordinates":[8.70271,48.892773],"type":"Point"}
}