{
  "type": "Feature",
  "properties": {
    "iso:country":"DE",
    "sg:address":"Porschestr. 9",
    "sg:city":"St.Leon-Rot",
    "sg:phone":"+49 6227",
    "sg:postcode":"68789",
    "sg:province":"Baden-W\u00fcrttemberg",
    "wof:name":"Hirt-zerspanungstechnik, St.leon-rot",
    "wof:placetype":"venue"
},
  "geometry": {"coordinates":[-98.0141296387,42.5245513916],"type":"Point"}
}