{
  "type": "Feature",
  "properties": {
    "iso:country":"DE",
    "sg:city":"Lohfelden",
    "sg:phone":"+49 561/512288",
    "sg:postcode":"34253",
    "sg:province":"Hessen",
    "wof:name":"Medicus",
    "wof:placetype":"venue"
},
  "geometry": {"coordinates":[9.552792,51.273262],"type":"Point"}
}