{
  "type": "Feature",
  "properties": {
    "iso:country":"DE",
    "sg:address":"Weierfeld 8",
    "sg:city":"Schleiden",
    "sg:phone":"+49 2485/325",
    "sg:postcode":"53937",
    "sg:province":"Nordrhein-Westfalen",
    "wof:name":"Karl-gustav Breuer",
    "wof:placetype":"venue"
},
  "geometry": {"coordinates":[6.394687,50.520126],"type":"Point"}
}