{
  "type": "Feature",
  "properties": {
    "iso:country":"DE",
    "sg:address":"Neue Str. 50",
    "sg:city":"Ludwigsburg",
    "sg:phone":"+49 7141/257114",
    "sg:postcode":"71642",
    "sg:province":"Baden-W\u00fcrttemberg",
    "wof:name":"Friedrich Gmbh",
    "wof:placetype":"venue"
},
  "geometry": {"coordinates":[9.220468,48.911327],"type":"Point"}
}