{
  "type": "Feature",
  "properties": {
    "iso:country":"DE",
    "sg:address":"Bachernstr. 3",
    "sg:city":"Kissing",
    "sg:phone":"+49 8233/60864",
    "sg:postcode":"86438",
    "sg:province":"Bayern",
    "wof:name":"Bestattungsdienst Friede Gmbh",
    "wof:placetype":"venue"
},
  "geometry": {"coordinates":[10.990003,48.297626],"type":"Point"}
}