{
  "type": "Feature",
  "properties": {
    "iso:country":"DE",
    "sg:address":"Hahnenbergstr. 20 a",
    "sg:city":"Mogendorf",
    "sg:phone":"+49 2623/970220",
    "sg:postcode":"56424",
    "sg:province":"Rheinland-Pfalz",
    "wof:name":"Friedbert Str\u00f6der Gmbh & Co. Kg",
    "wof:placetype":"venue"
},
  "geometry": {"coordinates":[7.761976,50.492931],"type":"Point"}
}