{
  "type": "Feature",
  "properties": {
    "iso:country":"DE",
    "sg:address":"Johannesstr. 35",
    "sg:city":"Elmshorn",
    "sg:postcode":"25335",
    "sg:province":"Schleswig-Holstein",
    "wof:name":"B & B Gmbh",
    "wof:placetype":"venue"
},
  "geometry": {"coordinates":[9.64836,53.756302],"type":"Point"}
}