{
  "type": "Feature",
  "properties": {
    "iso:country":"DE",
    "sg:address":"Siedlerweg 1b",
    "sg:city":"Herzfelde",
    "sg:postcode":"15378",
    "sg:province":"Brandenburg",
    "wof:name":"S. Faulhaber Gmbh",
    "wof:placetype":"venue"
},
  "geometry": {"coordinates":[13.8457107544,52.5063934326],"type":"Point"}
}