{
  "type": "Feature",
  "properties": {
    "iso:country":"DE",
    "sg:address":"Brinkstr. 14",
    "sg:city":"D\u00fclmen",
    "sg:phone":"+49 2590/536",
    "sg:postcode":"48249",
    "sg:province":"Nordrhein-Westfalen",
    "wof:name":"Str\u00e4ter Gmbh",
    "wof:placetype":"venue"
},
  "geometry": {"coordinates":[7.407537,51.835606],"type":"Point"}
}