{
  "type": "Feature",
  "properties": {
    "iso:country":"DE",
    "sg:address":"Gra\u00dfhoffstr 35",
    "sg:city":"Minden",
    "sg:phone":"+49 4957/194609",
    "sg:postcode":"32425",
    "sg:province":"Nordrhein-Westfalen",
    "wof:name":"Volksbank Holzhausen Ii Eg",
    "wof:placetype":"venue"
},
  "geometry": {"coordinates":[8.91762,52.335751],"type":"Point"}
}