{
  "type": "Feature",
  "properties": {
    "iso:country":"DE",
    "sg:address":"Alte Rottenburger Str. 20",
    "sg:city":"Ofterdingen",
    "sg:phone":"+49 7473/1094",
    "sg:postcode":"72131",
    "sg:province":"Baden-W\u00fcrttemberg",
    "wof:name":"W. R\u00f6cker",
    "wof:placetype":"venue"
},
  "geometry": {"coordinates":[9.025435,48.421803],"type":"Point"}
}