{
  "type": "Feature",
  "properties": {
    "iso:country":"DE",
    "sg:address":"Schillerstr. 9",
    "sg:city":"Dillenburg",
    "sg:phone":"+49 2771/35086",
    "sg:postcode":"35684",
    "sg:province":"Hessen",
    "wof:name":"International K.-h. Turowski",
    "wof:placetype":"venue"
},
  "geometry": {"coordinates":[8.298119,50.776325],"type":"Point"}
}