{
  "type": "Feature",
  "properties": {
    "iso:country":"DE",
    "sg:address":"Am Katzenberg 6",
    "sg:city":"Didderse",
    "sg:phone":"+49 5373",
    "sg:postcode":"38530",
    "sg:province":"Niedersachsen",
    "wof:name":"E.f. Automobile",
    "wof:placetype":"venue"
},
  "geometry": {"coordinates":[10.4127054214,52.383430481],"type":"Point"}
}