{
  "type": "Feature",
  "properties": {
    "iso:country":"DE",
    "sg:address":"Bahnhofstr. 82",
    "sg:city":"M\u00fchlacker",
    "sg:phone":"+49 7041/940679",
    "sg:postcode":"75417",
    "sg:province":"Baden-W\u00fcrttemberg",
    "wof:name":"Foto-quelle Bilderpoint Michael Berger",
    "wof:placetype":"venue"
},
  "geometry": {"coordinates":[8.842499733,48.9513015747],"type":"Point"}
}