{
  "type": "Feature",
  "properties": {
    "iso:country":"DE",
    "sg:address":"Rathausplatz 4",
    "sg:city":"Wedel",
    "sg:phone":"+49 4103/3208",
    "sg:postcode":"22880",
    "sg:province":"Schleswig-Holstein",
    "wof:name":"Da Salvatore",
    "wof:placetype":"venue"
},
  "geometry": {"coordinates":[9.7031393051,53.5810585022],"type":"Point"}
}