{
  "type": "Feature",
  "properties": {
    "iso:country":"DE",
    "sg:address":"Hebelstr. 3",
    "sg:city":"Titisee-Neustadt",
    "sg:phone":"+49 7651/7778",
    "sg:postcode":"79822",
    "sg:province":"Baden-W\u00fcrttemberg",
    "wof:name":"Rolf Beckers",
    "wof:placetype":"venue"
},
  "geometry": {"coordinates":[8.1493597031,47.9025421143],"type":"Point"}
}