{
  "type": "Feature",
  "properties": {
    "iso:country":"DE",
    "sg:address":"Kemptener Str. 12",
    "sg:city":"Bad W\u00f6rishofen",
    "sg:phone":"+49 8247/7030",
    "sg:postcode":"86825",
    "sg:province":"Bayern",
    "wof:name":"Robert K\u00f6llner Architekt",
    "wof:placetype":"venue"
},
  "geometry": {"coordinates":[10.60263,48.009628],"type":"Point"}
}