{
  "type": "Feature",
  "properties": {
    "iso:country":"DE",
    "sg:address":"Alfred-Klingele-Str. 32",
    "sg:city":"Remshalden",
    "sg:phone":"+49 7151/750400",
    "sg:postcode":"73630",
    "sg:province":"Baden-W\u00fcrttemberg",
    "wof:name":"Erga-trennwandbau Gmbh",
    "wof:placetype":"venue"
},
  "geometry": {"coordinates":[9.432247,48.808418],"type":"Point"}
}