{
  "type": "Feature",
  "properties": {
    "iso:country":"DE",
    "sg:address":"Winterleitenweg 30",
    "sg:city":"Kitzingen",
    "sg:phone":"+49 9321/5378",
    "sg:postcode":"97318",
    "sg:province":"Bayern",
    "wof:name":"R. H. Eckert",
    "wof:placetype":"venue"
},
  "geometry": {"coordinates":[10.1447763443,49.7358360291],"type":"Point"}
}