{
  "type": "Feature",
  "properties": {
    "iso:country":"DE",
    "sg:address":"Offenbachplatz 1",
    "sg:city":"K\u00f6ln",
    "sg:phone":"+49 221/2573998",
    "sg:postcode":"50667",
    "sg:province":"Nordrhein-Westfalen",
    "wof:name":"Hans Heuss Augenoptiker",
    "wof:placetype":"venue"
},
  "geometry": {"coordinates":[6.9521818161,50.9381217957],"type":"Point"}
}