{
  "type": "Feature",
  "properties": {
    "iso:country":"DE",
    "sg:address":"Eggenfeldener Str. 38",
    "sg:city":"Arnstorf",
    "sg:phone":"+49 8723/1440",
    "sg:postcode":"94424",
    "sg:province":"Bayern",
    "wof:name":"Paschal-werk G. Maier Gmbh",
    "wof:placetype":"venue"
},
  "geometry": {"coordinates":[12.80937,48.55468],"type":"Point"}
}