{
  "type": "Feature",
  "properties": {
    "iso:country":"DE",
    "sg:address":"Ernst-Renz-Str. 88",
    "sg:city":"Bruchsal",
    "sg:phone":"+49 7257/2934",
    "sg:postcode":"76646",
    "sg:province":"Baden-W\u00fcrttemberg",
    "wof:name":"Bunter Clown Kindermoden Inh. S. Pfisterer",
    "wof:placetype":"venue"
},
  "geometry": {"coordinates":[8.5532045364,49.0906677246],"type":"Point"}
}