{
  "type": "Feature",
  "properties": {
    "iso:country":"DE",
    "sg:address":"Kelterbergstr. 5",
    "sg:city":"Gernsbach",
    "sg:phone":"+49 7224/40240",
    "sg:postcode":"76593",
    "sg:province":"Baden-W\u00fcrttemberg",
    "wof:name":"M. Roth",
    "wof:placetype":"venue"
},
  "geometry": {"coordinates":[8.3419475555,48.7620201111],"type":"Point"}
}