{
  "type": "Feature",
  "properties": {
    "iso:country":"DE",
    "sg:address":"Stegwiesenstr. 6",
    "sg:city":"Bruchsal",
    "sg:phone":"+49 7251/97850",
    "sg:postcode":"76646",
    "sg:province":"Baden-W\u00fcrttemberg",
    "wof:name":"Horn-druck",
    "wof:placetype":"venue"
},
  "geometry": {"coordinates":[8.592292,49.138058],"type":"Point"}
}