{
  "type": "Feature",
  "properties": {
    "iso:country":"DE",
    "sg:address":"Marktstr. 20",
    "sg:city":"Blaubeuren",
    "sg:phone":"+49 7344/6661",
    "sg:postcode":"89143",
    "sg:province":"Baden-W\u00fcrttemberg",
    "wof:name":"Restaurant Asia-regent",
    "wof:placetype":"venue"
},
  "geometry": {"coordinates":[9.7811403275,48.4129447937],"type":"Point"}
}