{
  "type": "Feature",
  "properties": {
    "iso:country":"DE",
    "sg:address":"Im Wiesental 30",
    "sg:city":"Ehingen",
    "sg:phone":"+49 7395/364",
    "sg:postcode":"89584",
    "sg:province":"Baden-W\u00fcrttemberg",
    "wof:name":"Restaurant Talhof",
    "wof:placetype":"venue"
},
  "geometry": {"coordinates":[9.6477861404,48.2842559814],"type":"Point"}
}