{
  "type": "Feature",
  "properties": {
    "iso:country":"DE",
    "sg:address":"Klettwitzer Str. 15",
    "sg:city":"Annah\u00fctte",
    "sg:phone":"+49 35754/10628",
    "sg:postcode":"01994",
    "sg:province":"Brandenburg",
    "wof:name":"C. Auras",
    "wof:placetype":"venue"
},
  "geometry": {"coordinates":[13.8971185684,51.5582046509],"type":"Point"}
}