{
  "type": "Feature",
  "properties": {
    "iso:country":"DE",
    "sg:address":"Robert-Schade-Weg 4",
    "sg:city":"Bad Schwartau",
    "sg:phone":"+49 451/22437",
    "sg:postcode":"23611",
    "sg:province":"Schleswig-Holstein",
    "wof:name":"H. M\u00f6ller",
    "wof:placetype":"venue"
},
  "geometry": {"coordinates":[10.6914930344,53.9210510254],"type":"Point"}
}