{
  "type": "Feature",
  "properties": {
    "iso:country":"DE",
    "sg:address":"Klosterstr. 1",
    "sg:city":"Zwickau",
    "sg:phone":"+49 375/25787",
    "sg:postcode":"08056",
    "sg:province":"Sachsen",
    "wof:name":"Einkaufs- Und Liefergenossen- Schaft Des Dienstleistenden",
    "wof:placetype":"venue"
},
  "geometry": {"coordinates":[12.496329,50.715435],"type":"Point"}
}