{
  "type": "Feature",
  "properties": {
    "iso:country":"DE",
    "sg:address":"Nordgaustr. 7",
    "sg:city":"Burglengenfeld",
    "sg:phone":"+49 9471/808995",
    "sg:postcode":"93133",
    "sg:province":"Bayern",
    "wof:name":"Gerhard Kammerl",
    "wof:placetype":"venue"
},
  "geometry": {"coordinates":[12.0335702896,49.1985054016],"type":"Point"}
}