{
  "type": "Feature",
  "properties": {
    "iso:country":"DE",
    "sg:address":"Neue H\u00fclbe 2",
    "sg:city":"Wildberg",
    "sg:phone":"+49 7054/5361",
    "sg:postcode":"72218",
    "sg:province":"Baden-W\u00fcrttemberg",
    "wof:name":"Walfried Creutz",
    "wof:placetype":"venue"
},
  "geometry": {"coordinates":[8.710049,48.629581],"type":"Point"}
}