{
  "type": "Feature",
  "properties": {
    "iso:country":"DE",
    "sg:address":"Friesenstr. 44-48",
    "sg:city":"K\u00f6ln",
    "sg:phone":"+49 4922/116140",
    "sg:postcode":"50670",
    "sg:province":"Nordrhein-Westfalen",
    "wof:name":"Dorint Hotel K\u00d6ln",
    "wof:placetype":"venue"
},
  "geometry": {"coordinates":[6.943068,50.940842],"type":"Point"}
}