{
  "type": "Feature",
  "properties": {
    "iso:country":"DE",
    "sg:address":"Steubenstr. 61",
    "sg:city":"Heidelberg",
    "sg:phone":"+49 6221/471242",
    "sg:postcode":"69121",
    "sg:province":"Baden-W\u00fcrttemberg",
    "wof:name":"Hermann Fischer",
    "wof:placetype":"venue"
},
  "geometry": {"coordinates":[8.68671,49.426521],"type":"Point"}
}