{
  "type": "Feature",
  "properties": {
    "iso:country":"DE",
    "sg:address":"Peter-Koch-Str. 50",
    "sg:city":"Neustadt",
    "sg:phone":"+49 6321/66062",
    "sg:postcode":"67435",
    "sg:province":"Rheinland-Pfalz",
    "wof:name":"Kurt Mugler",
    "wof:placetype":"venue"
},
  "geometry": {"coordinates":[8.152100563,49.3765106201],"type":"Point"}
}