{
  "type": "Feature",
  "properties": {
    "iso:country":"DE",
    "sg:address":"Haubergweg 1",
    "sg:city":"Iserlohn",
    "sg:phone":"+49 2371/44443",
    "sg:postcode":"58640",
    "sg:province":"Nordrhein-Westfalen",
    "wof:name":"Hennig Gmbh",
    "wof:placetype":"venue"
},
  "geometry": {"coordinates":[7.6874279976,51.4048805237],"type":"Point"}
}