{
  "type": "Feature",
  "properties": {
    "iso:country":"DE",
    "sg:address":"Roseggerstr. 20",
    "sg:city":"D\u00fcsseldorf",
    "sg:phone":"+49 211/6413891",
    "sg:postcode":"40470",
    "sg:province":"Nordrhein-Westfalen",
    "wof:name":"Uwe Behrens",
    "wof:placetype":"venue"
},
  "geometry": {"coordinates":[6.8066158295,51.2559776306],"type":"Point"}
}