{
  "type": "Feature",
  "properties": {
    "iso:country":"DE",
    "sg:address":"Warburger Str. 134",
    "sg:city":"Paderborn",
    "sg:phone":"+49 5251/16620",
    "sg:postcode":"33100",
    "sg:province":"Nordrhein-Westfalen",
    "wof:name":"Deppe",
    "wof:placetype":"venue"
},
  "geometry": {"coordinates":[8.7780799866,51.7050323486],"type":"Point"}
}