{
  "type": "Feature",
  "properties": {
    "iso:country":"DE",
    "sg:address":"Pfarrweg 2",
    "sg:city":"Nehren",
    "sg:phone":"+49 7473/8504",
    "sg:postcode":"72147",
    "sg:province":"Baden-W\u00fcrttemberg",
    "wof:name":"Eugen Nill",
    "wof:placetype":"venue"
},
  "geometry": {"coordinates":[9.0664234161,48.4293060303],"type":"Point"}
}