{
  "type": "Feature",
  "properties": {
    "iso:country":"DE",
    "sg:address":"Holthauser H\u00f6fe 94",
    "sg:city":"M\u00fclheim",
    "sg:phone":"+49 208/370950",
    "sg:postcode":"45470",
    "sg:province":"Nordrhein-Westfalen",
    "wof:name":"Hans Klingels Stahlhandel",
    "wof:placetype":"venue"
},
  "geometry": {"coordinates":[6.91464,51.40749],"type":"Point"}
}