{
  "type": "Feature",
  "properties": {
    "iso:country":"DE",
    "sg:address":"Pestalozzistr 29",
    "sg:city":"M\u00fcnchen",
    "sg:phone":"+49 89/265312",
    "sg:postcode":"80469",
    "sg:province":"Bayern",
    "wof:name":"Pr\u00f6kel Gmbh",
    "wof:placetype":"venue"
},
  "geometry": {"coordinates":[11.5674800873,48.1290473938],"type":"Point"}
}