{
  "type": "Feature",
  "properties": {
    "iso:country":"DE",
    "sg:address":"Elexenbach 1",
    "sg:city":"Ortenburg",
    "sg:phone":"+49 8542/7605",
    "sg:postcode":"94496",
    "sg:province":"Bayern",
    "wof:name":"M\u00fcgro Gro\u00dfhandels-gmbh",
    "wof:placetype":"venue"
},
  "geometry": {"coordinates":[13.2584943771,48.5726661682],"type":"Point"}
}