{
  "type": "Feature",
  "properties": {
    "iso:country":"DE",
    "sg:address":"Hinter der Saline 13",
    "sg:city":"L\u00fcneburg",
    "sg:phone":"+49 4131424904242",
    "sg:postcode":"21339",
    "sg:province":"Niedersachsen",
    "wof:name":"Theodor Meyer Gmbh & Co. Kg Haus- Und Grundst\u00fccks-",
    "wof:placetype":"venue"
},
  "geometry": {"coordinates":[10.4004144669,53.2422294617],"type":"Point"}
}