{
  "type": "Feature",
  "properties": {
    "iso:country":"DE",
    "sg:address":"Am Kalkhaus 5",
    "sg:city":"Schwalmstadt",
    "sg:phone":"+49 6691/2945",
    "sg:postcode":"34613",
    "sg:province":"Hessen",
    "wof:name":"Treysit-presserei Inh. Inge Ermel",
    "wof:placetype":"venue"
},
  "geometry": {"coordinates":[9.19381,50.918369],"type":"Point"}
}