{
  "type": "Feature",
  "properties": {
    "iso:country":"DE",
    "sg:address":"Robert-Koch-Ring 66",
    "sg:city":"Meppen",
    "sg:phone":"+49 5931/12142",
    "sg:postcode":"49716",
    "sg:province":"Niedersachsen",
    "wof:name":"Hans Dommerque Ingenieur",
    "wof:placetype":"venue"
},
  "geometry": {"coordinates":[7.2920818329,52.6729278564],"type":"Point"}
}