{
  "type": "Feature",
  "properties": {
    "iso:country":"DE",
    "sg:address":"Edisonstr. 29 a",
    "sg:city":"Berlin",
    "sg:phone":"+49 30/5319854",
    "sg:postcode":"12459",
    "sg:province":"Berlin",
    "wof:name":"Audrey Zitscher",
    "wof:placetype":"venue"
},
  "geometry": {"coordinates":[13.513365,52.466801],"type":"Point"}
}