{
  "type": "Feature",
  "properties": {
    "iso:country":"DE",
    "sg:address":"Amtsgartenweg 1",
    "sg:city":"Badenweiler",
    "sg:phone":"+49 7632/358",
    "sg:postcode":"79410",
    "sg:province":"Baden-W\u00fcrttemberg",
    "wof:name":"Kath. Pfarramt St. Peter",
    "wof:placetype":"venue"
},
  "geometry": {"coordinates":[7.668129921,47.7986297607],"type":"Point"}
}