{
  "type": "Feature",
  "properties": {
    "iso:country":"DE",
    "sg:address":"Bismarckstr 142b",
    "sg:city":"Duisburg",
    "sg:phone":"+49 203/3062050",
    "sg:postcode":"47057",
    "sg:province":"Nordrhein-Westfalen",
    "wof:name":"Microtec Gesellschaft F\u00fcr Mikrotechnologie Mbh",
    "wof:placetype":"venue"
},
  "geometry": {"coordinates":[6.788783,51.430672],"type":"Point"}
}