{
  "type": "Feature",
  "properties": {
    "iso:country":"DE",
    "sg:address":"Puschkinstr. 10",
    "sg:city":"L\u00fcbben",
    "sg:phone":"+49 3546/8420",
    "sg:postcode":"15907",
    "sg:province":"Brandenburg",
    "wof:name":"Treffpunkt",
    "wof:placetype":"venue"
},
  "geometry": {"coordinates":[13.8904848099,51.9377403259],"type":"Point"}
}