{
  "type": "Feature",
  "properties": {
    "iso:country":"DE",
    "sg:address":"Kleineschle 16",
    "sg:city":"Burladingen",
    "sg:phone":"+49 7475/7269",
    "sg:postcode":"72393",
    "sg:province":"Baden-W\u00fcrttemberg",
    "wof:name":"M. Und A. Grieswald Mech. Werkstatt",
    "wof:placetype":"venue"
},
  "geometry": {"coordinates":[9.096062,48.293121],"type":"Point"}
}