{
  "type": "Feature",
  "properties": {
    "iso:country":"DE",
    "sg:address":"Bruchstr. 6",
    "sg:city":"Burgwedel",
    "sg:phone":"+49 5139/1645",
    "sg:postcode":"30938",
    "sg:province":"Niedersachsen",
    "wof:name":"C. Kr\u00fcger",
    "wof:placetype":"venue"
},
  "geometry": {"coordinates":[9.902312,52.494919],"type":"Point"}
}