{
  "type": "Feature",
  "properties": {
    "iso:country":"DE",
    "sg:address":"Allerstr. 46",
    "sg:city":"Berlin",
    "sg:phone":"+49 30/6212111",
    "sg:postcode":"12049",
    "sg:province":"Berlin",
    "wof:name":"Hans Bonau",
    "wof:placetype":"venue"
},
  "geometry": {"coordinates":[13.426501,52.474987],"type":"Point"}
}