{
  "type": "Feature",
  "properties": {
    "iso:country":"DE",
    "sg:address":"Mainstr. 45",
    "sg:city":"B\u00fcrstadt",
    "sg:phone":"+49 6206/79278",
    "sg:postcode":"68642",
    "sg:province":"Hessen",
    "wof:name":"T.u.u. Schumacher",
    "wof:placetype":"venue"
},
  "geometry": {"coordinates":[8.4545125961,49.6450233459],"type":"Point"}
}