{
  "type": "Feature",
  "properties": {
    "iso:country":"DE",
    "sg:address":"Eichenbirkig 16",
    "sg:city":"Waischenfeld",
    "sg:phone":"+49 9202",
    "sg:postcode":"91344",
    "sg:province":"Bayern",
    "wof:name":"Bss Baumaschinen-service-stein",
    "wof:placetype":"venue"
},
  "geometry": {"coordinates":[11.339951,49.819771],"type":"Point"}
}