{
  "type": "Feature",
  "properties": {
    "iso:country":"DE",
    "sg:address":"Apenrader Str. 1",
    "sg:city":"Oldenburg",
    "sg:phone":"+49 441/63293",
    "sg:postcode":"26127",
    "sg:province":"Niedersachsen",
    "wof:name":"Wilfried Otte",
    "wof:placetype":"venue"
},
  "geometry": {"coordinates":[8.198626,53.165455],"type":"Point"}
}