{
  "type": "Feature",
  "properties": {
    "iso:country":"DE",
    "sg:address":"Bahnhofstr. 42",
    "sg:city":"Malchow",
    "sg:phone":"+49 39932/870",
    "sg:postcode":"17213",
    "sg:province":"Mecklenburg-Vorpommern",
    "wof:name":"Edeka",
    "wof:placetype":"venue"
},
  "geometry": {"coordinates":[12.4265489578,53.4848632812],"type":"Point"}
}