{
  "type": "Feature",
  "properties": {
    "iso:country":"DE",
    "sg:address":"L\u00fcneburger Str. 24",
    "sg:city":"L\u00fcneburg",
    "sg:phone":"+49 4131/41862",
    "sg:postcode":"21335",
    "sg:province":"Niedersachsen",
    "wof:name":"Betonsteinwerk Rettmer Inh. Thomas Schr\u00f6der",
    "wof:placetype":"venue"
},
  "geometry": {"coordinates":[10.3675098419,53.2113456726],"type":"Point"}
}