{
  "type": "Feature",
  "properties": {
    "iso:country":"DE",
    "sg:address":"Im Wiesengrund",
    "sg:city":"Kirchgellersen",
    "sg:phone":"+49 4135/622",
    "sg:postcode":"21394",
    "sg:province":"Niedersachsen",
    "wof:name":"Freibad",
    "wof:placetype":"venue"
},
  "geometry": {"coordinates":[10.3017759323,53.2344512939],"type":"Point"}
}