{
  "type": "Feature",
  "properties": {
    "iso:country":"DE",
    "sg:address":"Kirchbergstr. 10",
    "sg:city":"Kandern",
    "sg:phone":"+49 7626/970998",
    "sg:postcode":"79400",
    "sg:province":"Baden-W\u00fcrttemberg",
    "wof:name":"Rorec Rohrleitungsplanung & Recyclingberatung Gmbh",
    "wof:placetype":"venue"
},
  "geometry": {"coordinates":[7.6350941658,47.7164230347],"type":"Point"}
}