{
  "type": "Feature",
  "properties": {
    "iso:country":"DE",
    "sg:address":"Frankenstr. 30",
    "sg:city":"Nordhausen",
    "sg:phone":"+49 3631/981222",
    "sg:postcode":"99734",
    "sg:province":"Th\u00fcringen",
    "wof:name":"W.-ulrich Skyba",
    "wof:placetype":"venue"
},
  "geometry": {"coordinates":[10.807970047,51.5081253052],"type":"Point"}
}