{
  "type": "Feature",
  "properties": {
    "iso:country":"DE",
    "sg:address":"Landshuter Allee 12-14",
    "sg:city":"M\u00fcnchen",
    "sg:phone":"+49 89/4556590",
    "sg:postcode":"80637",
    "sg:province":"Bayern",
    "wof:name":"Acucorp Deutschland Gmbh",
    "wof:placetype":"venue"
},
  "geometry": {"coordinates":[11.5370960236,48.1475906372],"type":"Point"}
}