{
  "type": "Feature",
  "properties": {
    "iso:country":"DE",
    "sg:address":"Harzer Str 32(2. Hof)",
    "sg:city":"Berlin",
    "sg:phone":"+49 30/6819133",
    "sg:postcode":"12059",
    "sg:province":"Berlin",
    "wof:name":"Mevo",
    "wof:placetype":"venue"
},
  "geometry": {"coordinates":[13.447674,52.485538],"type":"Point"}
}