{
  "type": "Feature",
  "properties": {
    "iso:country":"DE",
    "sg:address":"Bergstedter Chaussee 195",
    "sg:city":"Hamburg",
    "sg:phone":"+49 40/6049422",
    "sg:postcode":"22395",
    "sg:province":"Hamburg",
    "wof:name":"Claus Poggensee",
    "wof:placetype":"venue"
},
  "geometry": {"coordinates":[10.134117,53.674541],"type":"Point"}
}