{
  "type": "Feature",
  "properties": {
    "iso:country":"DE",
    "sg:address":"B\u00e4ngles\u00e4cker 1",
    "sg:city":"Schw\u00e4bisch Gm\u00fcnd",
    "sg:phone":"+49 7171/976010",
    "sg:postcode":"73527",
    "sg:province":"Baden-W\u00fcrttemberg",
    "wof:name":"Weiss-ausbausysteme Gmbh",
    "wof:placetype":"venue"
},
  "geometry": {"coordinates":[9.8216171265,48.8341827393],"type":"Point"}
}