{
  "type": "Feature",
  "properties": {
    "iso:country":"DE",
    "sg:address":"Kriegerstr. 40",
    "sg:city":"Hannover",
    "sg:postcode":"30161",
    "sg:province":"Niedersachsen",
    "wof:name":"Matthias B\u00f6hm Verwaltungs- Und Beteiligungsgesellschaft",
    "wof:placetype":"venue"
},
  "geometry": {"coordinates":[9.739988,52.388893],"type":"Point"}
}