{
  "type": "Feature",
  "properties": {
    "iso:country":"DE",
    "sg:address":"Ahornweg 2",
    "sg:city":"Nauheim",
    "sg:phone":"+49 6152/69252",
    "sg:postcode":"64569",
    "sg:province":"Hessen",
    "wof:name":"Hans Und Melitta Riedl",
    "wof:placetype":"venue"
},
  "geometry": {"coordinates":[8.4559822083,49.950012207],"type":"Point"}
}