{
  "type": "Feature",
  "properties": {
    "iso:country":"DE",
    "sg:address":"Ueckerstr. 44",
    "sg:city":"Ueckerm\u00fcnde",
    "sg:phone":"+49 39771/24521",
    "sg:postcode":"17373",
    "sg:province":"Mecklenburg-Vorpommern",
    "wof:name":"Victoria Versicherung Ag",
    "wof:placetype":"venue"
},
  "geometry": {"coordinates":[14.0403118134,53.7394790649],"type":"Point"}
}