{
  "type": "Feature",
  "properties": {
    "iso:country":"DE",
    "sg:address":"Gutwillen 30",
    "sg:city":"Kaufbeuren",
    "sg:phone":"+49 8341/2642",
    "sg:postcode":"87600",
    "sg:province":"Bayern",
    "wof:name":"Georg Winstel",
    "wof:placetype":"venue"
},
  "geometry": {"coordinates":[10.593671,47.887341],"type":"Point"}
}