{
  "type": "Feature",
  "properties": {
    "iso:country":"DE",
    "sg:address":"Rothenbaumchaussee 87",
    "sg:city":"Hamburg",
    "sg:phone":"+49 40/2781910",
    "sg:postcode":"20148",
    "sg:province":"Hamburg",
    "wof:name":"Consequence Werbung Und Kommunikation Gmbh",
    "wof:placetype":"venue"
},
  "geometry": {"coordinates":[9.988240242,53.5700798035],"type":"Point"}
}