{
  "type": "Feature",
  "properties": {
    "iso:country":"DE",
    "sg:address":"Kaiser-Wilhelm-Str. 100",
    "sg:city":"Duisburg",
    "sg:phone":"+49 203/5224359",
    "sg:postcode":"47166",
    "sg:province":"Nordrhein-Westfalen",
    "wof:name":"Arbeitsgemeinschaft Haupt- Amtlicher Werks\u00e4rzte E. V.",
    "wof:placetype":"venue"
},
  "geometry": {"coordinates":[6.742055,51.49147],"type":"Point"}
}