{
  "type": "Feature",
  "properties": {
    "iso:country":"DE",
    "sg:address":"Seestr. 7",
    "sg:city":"Ettlingen",
    "sg:phone":"+49 7243/527564",
    "sg:postcode":"76275",
    "sg:province":"Baden-W\u00fcrttemberg",
    "wof:name":"Lehnguth Und Sturm Ergotherapeutische Praxis",
    "wof:placetype":"venue"
},
  "geometry": {"coordinates":[8.382728,48.924416],"type":"Point"}
}