{
  "type": "Feature",
  "properties": {
    "iso:country":"DE",
    "sg:address":"Alter Markt 34",
    "sg:city":"Arnsberg",
    "sg:phone":"+49 2931/3011",
    "sg:postcode":"59821",
    "sg:province":"Nordrhein-Westfalen",
    "wof:name":"H. Dielitz",
    "wof:placetype":"venue"
},
  "geometry": {"coordinates":[8.06385,51.397659],"type":"Point"}
}