{
  "type": "Feature",
  "properties": {
    "iso:country":"DE",
    "sg:address":"Feilitzschstr. 7",
    "sg:city":"M\u00fcnchen",
    "sg:phone":"+49 89/344259",
    "sg:postcode":"80802",
    "sg:province":"Bayern",
    "wof:name":"Flip Munich Warenhandelsges. Mbh",
    "wof:placetype":"venue"
},
  "geometry": {"coordinates":[11.58783,48.161701],"type":"Point"}
}