{
  "type": "Feature",
  "properties": {
    "iso:country":"DE",
    "sg:address":"Waldweg 9",
    "sg:city":"Prittitz",
    "sg:phone":"+49 34445/29000",
    "sg:postcode":"06667",
    "sg:province":"Sachsen-Anhalt",
    "wof:name":"R. Siegel",
    "wof:placetype":"venue"
},
  "geometry": {"coordinates":[11.934827,51.149101],"type":"Point"}
}