{
  "type": "Feature",
  "properties": {
    "iso:country":"DE",
    "sg:address":"Brettener Str. 10",
    "sg:city":"Graben-Neudorf",
    "sg:phone":"+49 7255/2277",
    "sg:postcode":"76676",
    "sg:province":"Baden-W\u00fcrttemberg",
    "wof:name":"Herzog Immobilienmakler",
    "wof:placetype":"venue"
},
  "geometry": {"coordinates":[8.4998054504,49.1648521423],"type":"Point"}
}