{
  "type": "Feature",
  "properties": {
    "iso:country":"DE",
    "sg:address":"Industriestr. 8",
    "sg:city":"Senden",
    "sg:phone":"+49 2597/9100",
    "sg:postcode":"48308",
    "sg:province":"Nordrhein-Westfalen",
    "wof:name":"Gebr. Wiese Gmbh",
    "wof:placetype":"venue"
},
  "geometry": {"coordinates":[7.4746770859,51.8465652466],"type":"Point"}
}