{
  "type": "Feature",
  "properties": {
    "iso:country":"DE",
    "sg:address":"Am W\u00e4ldchen 9",
    "sg:city":"Ramstein-Miesenbach",
    "sg:phone":"+49 6371/50751",
    "sg:postcode":"66877",
    "sg:province":"Rheinland-Pfalz",
    "wof:name":"Alma Wack",
    "wof:placetype":"venue"
},
  "geometry": {"coordinates":[7.5601549149,49.4661903381],"type":"Point"}
}