{
  "type": "Feature",
  "properties": {
    "iso:country":"DE",
    "sg:address":"Weimarische Str. 24",
    "sg:city":"Mellingen",
    "sg:phone":"+49 36453/82244",
    "sg:postcode":"99441",
    "sg:province":"Th\u00fcringen",
    "wof:name":"Der Pc-doktor - Weimar",
    "wof:placetype":"venue"
},
  "geometry": {"coordinates":[11.393336,50.943611],"type":"Point"}
}