{
  "type": "Feature",
  "properties": {
    "iso:country":"DE",
    "sg:address":"Baintstr. 10",
    "sg:city":"Weilheim",
    "sg:phone":"+49 7023/900250",
    "sg:postcode":"73235",
    "sg:province":"Baden-W\u00fcrttemberg",
    "wof:name":"Weissinger",
    "wof:placetype":"venue"
},
  "geometry": {"coordinates":[9.534483,48.616604],"type":"Point"}
}