{
  "type": "Feature",
  "properties": {
    "iso:country":"DE",
    "sg:address":"Eilenburger Str.",
    "sg:city":"Leipzig",
    "sg:postcode":"04317",
    "sg:province":"Sachsen",
    "wof:name":"Aldi Gmbh & Co. Kg",
    "wof:placetype":"venue"
},
  "geometry": {"coordinates":[12.3981847763,51.3341636658],"type":"Point"}
}