{
  "type": "Feature",
  "properties": {
    "iso:country":"DE",
    "sg:address":"Mainzer Str. 33",
    "sg:city":"Idar-Oberstein",
    "sg:phone":"+49 6781/43978",
    "sg:postcode":"55743",
    "sg:province":"Rheinland-Pfalz",
    "wof:name":"Hans W. Lorenz",
    "wof:placetype":"venue"
},
  "geometry": {"coordinates":[7.2999181747,49.7197189331],"type":"Point"}
}