{
  "type": "Feature",
  "properties": {
    "iso:country":"DE",
    "sg:address":"Limesstr. 24",
    "sg:city":"Essingen",
    "sg:phone":"+49 7365/6878",
    "sg:postcode":"73457",
    "sg:province":"Baden-W\u00fcrttemberg",
    "wof:name":"Dieter Kosak Masseur",
    "wof:placetype":"venue"
},
  "geometry": {"coordinates":[10.027933,48.815933],"type":"Point"}
}