{
  "type": "Feature",
  "properties": {
    "iso:country":"DE",
    "sg:address":"Hauptstr. 15",
    "sg:city":"Neckargem\u00fcnd",
    "sg:phone":"+49 6223/990300",
    "sg:postcode":"69151",
    "sg:province":"Baden-W\u00fcrttemberg",
    "wof:name":"Dr. H. Lamade & Kollegen",
    "wof:placetype":"venue"
},
  "geometry": {"coordinates":[8.8000335693,49.3925170898],"type":"Point"}
}