{
  "type": "Feature",
  "properties": {
    "iso:country":"DE",
    "sg:address":"Traisaer Hohlweg 8",
    "sg:city":"M\u00fchltal",
    "sg:phone":"+49 6151/145617",
    "sg:postcode":"64367",
    "sg:province":"Hessen",
    "wof:name":"Aluxxon-bauelemente Gmbh",
    "wof:placetype":"venue"
},
  "geometry": {"coordinates":[8.701909,49.83094],"type":"Point"}
}