{
  "type": "Feature",
  "properties": {
    "iso:country":"DE",
    "sg:address":"Zschokkestr. 73",
    "sg:city":"M\u00fcnchen",
    "sg:phone":"+49 89/5471960",
    "sg:postcode":"80686",
    "sg:province":"Bayern",
    "wof:name":"Karwendel-apotheke",
    "wof:placetype":"venue"
},
  "geometry": {"coordinates":[11.509733,48.134972],"type":"Point"}
}