{
  "type": "Feature",
  "properties": {
    "iso:country":"DE",
    "sg:address":"Trierer Str. 136",
    "sg:city":"N\u00fcrnberg",
    "sg:phone":"+49 911/482406",
    "sg:postcode":"90469",
    "sg:province":"Bayern",
    "wof:name":"Erwin K\u00fchnlein Feuerl\u00f6schger\u00e4te",
    "wof:placetype":"venue"
},
  "geometry": {"coordinates":[11.106729,49.407711],"type":"Point"}
}