{
  "type": "Feature",
  "properties": {
    "iso:country":"DE",
    "sg:address":"Boleweg 14",
    "sg:city":"Soest",
    "sg:postcode":"59494",
    "sg:province":"Nordrhein-Westfalen",
    "wof:name":"Aldi Gmbh & Co. Kg",
    "wof:placetype":"venue"
},
  "geometry": {"coordinates":[8.0855712891,51.5604400635],"type":"Point"}
}