{
  "type": "Feature",
  "properties": {
    "iso:country":"DE",
    "sg:address":"Vorderstr. 3",
    "sg:city":"Stockstadt",
    "sg:phone":"+49 6158/985801",
    "sg:postcode":"64589",
    "sg:province":"Hessen",
    "wof:name":"Ilbuco",
    "wof:placetype":"venue"
},
  "geometry": {"coordinates":[8.4668102264,49.8110313416],"type":"Point"}
}