{
  "type": "Feature",
  "properties": {
    "iso:country":"DE",
    "sg:address":"Schwabm\u00fcnchner Str. 2",
    "sg:city":"Langenneufnach",
    "sg:phone":"+49 8239/7598",
    "sg:postcode":"86863",
    "sg:province":"Bayern",
    "wof:name":"Akropolis",
    "wof:placetype":"venue"
},
  "geometry": {"coordinates":[10.6007871628,48.2559356689],"type":"Point"}
}