{
  "type": "Feature",
  "properties": {
    "iso:country":"DE",
    "sg:address":"Unterstr 10",
    "sg:city":"Arzfeld",
    "sg:phone":"+49 6550/92900",
    "sg:postcode":"54687",
    "sg:province":"Rheinland-Pfalz",
    "wof:name":"Elektro Zahnen & Co Gmbh",
    "wof:placetype":"venue"
},
  "geometry": {"coordinates":[6.2723259926,50.0852890015],"type":"Point"}
}