{
  "type": "Feature",
  "properties": {
    "iso:country":"DE",
    "sg:address":"Allee 19",
    "sg:city":"Horn-Bad Meinberg",
    "sg:phone":"+49 5234/98866",
    "sg:postcode":"32805",
    "sg:province":"Nordrhein-Westfalen",
    "wof:name":"Teutonia",
    "wof:placetype":"venue"
},
  "geometry": {"coordinates":[8.9787216187,51.8947181702],"type":"Point"}
}