{
  "type": "Feature",
  "properties": {
    "iso:country":"DE",
    "sg:address":"Hauptstr. 110",
    "sg:city":"Rellingen",
    "sg:phone":"+49 4101/204018",
    "sg:postcode":"25462",
    "sg:province":"Schleswig-Holstein",
    "wof:name":"Aral-tankstelle",
    "wof:placetype":"venue"
},
  "geometry": {"coordinates":[9.8236732483,53.6547927856],"type":"Point"}
}