{
  "type": "Feature",
  "properties": {
    "iso:country":"DE",
    "sg:address":"Im Dorf 2",
    "sg:city":"Westerwalsede",
    "sg:phone":"+49 4269/1518",
    "sg:postcode":"27386",
    "sg:province":"Niedersachsen",
    "wof:name":"Rotermundt",
    "wof:placetype":"venue"
},
  "geometry": {"coordinates":[9.365061,53.003563],"type":"Point"}
}