{
  "type": "Feature",
  "properties": {
    "iso:country":"DE",
    "sg:address":"S\u00fcdbeckenstr. 8",
    "sg:city":"Karlsruhe",
    "sg:phone":"+49 721/556060",
    "sg:postcode":"76189",
    "sg:province":"Baden-W\u00fcrttemberg",
    "wof:name":"Uhg Umschlags- Und Baustoff- Handelsgesellschaft Mbh",
    "wof:placetype":"venue"
},
  "geometry": {"coordinates":[8.3388662338,49.0120697021],"type":"Point"}
}