{
  "type": "Feature",
  "properties": {
    "iso:country":"DE",
    "sg:address":"S\u00fcdwall 13",
    "sg:city":"Schwerte",
    "sg:postcode":"58239",
    "sg:province":"Nordrhein-Westfalen",
    "wof:name":"E. Schmidt Heissmangel",
    "wof:placetype":"venue"
},
  "geometry": {"coordinates":[7.5725297928,51.4401893616],"type":"Point"}
}