{
  "type": "Feature",
  "properties": {
    "iso:country":"DE",
    "sg:address":"S\u00f6st 83",
    "sg:city":"Wincheringen",
    "sg:phone":"+49 6583/542",
    "sg:postcode":"54457",
    "sg:province":"Rheinland-Pfalz",
    "wof:name":"Peter Haas",
    "wof:placetype":"venue"
},
  "geometry": {"coordinates":[6.4614200592,49.6239814758],"type":"Point"}
}