{
  "type": "Feature",
  "properties": {
    "iso:country":"DE",
    "sg:address":"Kaufbeurer Str. 44",
    "sg:city":"Germaringen",
    "sg:phone":"+49 8341/65200",
    "sg:postcode":"87656",
    "sg:province":"Bayern",
    "wof:name":"Franz Smida",
    "wof:placetype":"venue"
},
  "geometry": {"coordinates":[10.66735,47.920525],"type":"Point"}
}