{
  "type": "Feature",
  "properties": {
    "iso:country":"DE",
    "sg:address":"Belchenstr. 57",
    "sg:city":"Karlsruhe",
    "sg:phone":"+49 721/883101",
    "sg:postcode":"76199",
    "sg:province":"Baden-W\u00fcrttemberg",
    "wof:name":"Silvia Eschelbach-karl Ergotherapiepraxis",
    "wof:placetype":"venue"
},
  "geometry": {"coordinates":[8.390954,48.982071],"type":"Point"}
}