{
  "type": "Feature",
  "properties": {
    "iso:country":"DE",
    "sg:address":"Ostheimer Str. 9",
    "sg:city":"Brakel",
    "sg:phone":"+49 5272/5452",
    "sg:postcode":"33034",
    "sg:province":"Nordrhein-Westfalen",
    "wof:name":"Werbering Brakel E. V. Klaus Tensi",
    "wof:placetype":"venue"
},
  "geometry": {"coordinates":[9.1852111816,51.7163925171],"type":"Point"}
}