{
  "type": "Feature",
  "properties": {
    "iso:country":"DE",
    "sg:address":"Gro\u00dfe Str. 25",
    "sg:city":"Holdorf",
    "sg:phone":"+49 5494/220",
    "sg:postcode":"49451",
    "sg:province":"Niedersachsen",
    "wof:name":"August Borgerding Eierhandlung",
    "wof:placetype":"venue"
},
  "geometry": {"coordinates":[8.1251564026,52.5848045349],"type":"Point"}
}