{
  "type": "Feature",
  "properties": {
    "iso:country":"DE",
    "sg:address":"Amtmann-Daniel-Str. 10",
    "sg:city":"Nordwalde",
    "sg:phone":"+49 2573/3234",
    "sg:postcode":"48356",
    "sg:province":"Nordrhein-Westfalen",
    "wof:name":"Eisdiele Giacomel",
    "wof:placetype":"venue"
},
  "geometry": {"coordinates":[7.480973,52.085255],"type":"Point"}
}