{
  "type": "Feature",
  "properties": {
    "iso:country":"DE",
    "sg:city":"Flintsbach",
    "sg:phone":"+49 8034/597",
    "sg:postcode":"83126",
    "sg:province":"Bayern",
    "wof:name":"Raiffeisenbank Oberaudorf Eg",
    "wof:placetype":"venue"
},
  "geometry": {"coordinates":[12.123943,47.723953],"type":"Point"}
}