{
  "type": "Feature",
  "properties": {
    "iso:country":"DE",
    "sg:address":"Regerstr. 16",
    "sg:city":"Viechtach",
    "sg:phone":"+49 9942/8735",
    "sg:postcode":"94234",
    "sg:province":"Bayern",
    "wof:name":"Michael Kraus",
    "wof:placetype":"venue"
},
  "geometry": {"coordinates":[12.8788251877,49.0805091858],"type":"Point"}
}