{
  "type": "Feature",
  "properties": {
    "iso:country":"DE",
    "sg:address":"Schlo\u00dfstr. 32",
    "sg:city":"Herten",
    "sg:phone":"+49 2366/35493",
    "sg:postcode":"45701",
    "sg:province":"Nordrhein-Westfalen",
    "wof:name":"B. Heyse",
    "wof:placetype":"venue"
},
  "geometry": {"coordinates":[7.0915131569,51.5999488831],"type":"Point"}
}