{
  "type": "Feature",
  "properties": {
    "iso:country":"DE",
    "sg:address":"Schenkendorfstr. 1",
    "sg:city":"Wiesbaden",
    "sg:phone":"+49 611/812270",
    "sg:postcode":"65187",
    "sg:province":"Hessen",
    "wof:name":"Knoche Und Collegen Rechtsanw\u00e4lte",
    "wof:placetype":"venue"
},
  "geometry": {"coordinates":[8.2357749939,50.0716438293],"type":"Point"}
}