{
  "type": "Feature",
  "properties": {
    "iso:country":"DE",
    "sg:address":"Vegesacker Heerstr. 75",
    "sg:city":"Bremen",
    "sg:phone":"+49 421/623435",
    "sg:postcode":"28757",
    "sg:province":"Bremen",
    "wof:name":"Esso Deutschland Gmbh",
    "wof:placetype":"venue"
},
  "geometry": {"coordinates":[8.651632309,53.1741981506],"type":"Point"}
}