{
  "type": "Feature",
  "properties": {
    "iso:country":"DE",
    "sg:address":"Sendlinger Str. 25",
    "sg:city":"M\u00fcnchen",
    "sg:phone":"+49 89/26024630",
    "sg:postcode":"80331",
    "sg:province":"Bayern",
    "wof:name":"Henning Bethge Rechtsanwalt",
    "wof:placetype":"venue"
},
  "geometry": {"coordinates":[11.5703010559,48.1351280212],"type":"Point"}
}