{
  "type": "Feature",
  "properties": {
    "iso:country":"DE",
    "sg:address":"Holmer Str. 8",
    "sg:city":"S\u00fcderbrarup",
    "sg:phone":"+49 4641/91365",
    "sg:postcode":"24392",
    "sg:province":"Schleswig-Holstein",
    "wof:name":"M. Prahl Anlageberater",
    "wof:placetype":"venue"
},
  "geometry": {"coordinates":[9.7801942825,54.6325416565],"type":"Point"}
}