{
  "type": "Feature",
  "properties": {
    "iso:country":"DE",
    "sg:address":"Michaelweg 64",
    "sg:city":"M\u00fcnster",
    "sg:phone":"+49 251/868811",
    "sg:postcode":"48149",
    "sg:province":"Nordrhein-Westfalen",
    "wof:name":"Prester Produkt- Innov.-gmbh",
    "wof:placetype":"venue"
},
  "geometry": {"coordinates":[7.5819420815,51.966960907],"type":"Point"}
}