{
  "type": "Feature",
  "properties": {
    "iso:country":"DE",
    "sg:address":"St.-Annener-Str. 96",
    "sg:city":"Melle",
    "sg:phone":"+49 5428/94140",
    "sg:postcode":"49326",
    "sg:province":"Niedersachsen",
    "wof:name":"Wilh. Wittler Fleischwarenfabrik Gmbh",
    "wof:placetype":"venue"
},
  "geometry": {"coordinates":[8.4197530746,52.1550483704],"type":"Point"}
}