{
  "type": "Feature",
  "properties": {
    "iso:country":"DE",
    "sg:address":"59399",
    "sg:city":"Olfen",
    "sg:postcode":"59399",
    "sg:province":"Nordrhein-Westfalen",
    "wof:name":"Volksbank Olfen Eg",
    "wof:placetype":"venue"
},
  "geometry": {"coordinates":[7.37524,51.703659],"type":"Point"}
}