{
  "type": "Feature",
  "properties": {
    "iso:country":"DE",
    "sg:address":"Ellerbachstr. 22",
    "sg:city":"Buxheim",
    "sg:phone":"+49 8331/72253",
    "sg:postcode":"87740",
    "sg:province":"Bayern",
    "wof:name":"M. Jocham",
    "wof:placetype":"venue"
},
  "geometry": {"coordinates":[10.140454,47.995068],"type":"Point"}
}