{
  "type": "Feature",
  "properties": {
    "iso:country":"DE",
    "sg:address":"Achenbachstr. 159",
    "sg:city":"D\u00fcsseldorf",
    "sg:phone":"+49 211/671350",
    "sg:postcode":"40237",
    "sg:province":"Nordrhein-Westfalen",
    "wof:name":"Heinz Neubauer Ingenieur",
    "wof:placetype":"venue"
},
  "geometry": {"coordinates":[6.7991847992,51.2375297546],"type":"Point"}
}