{
  "type": "Feature",
  "properties": {
    "iso:country":"DE",
    "sg:address":"Lange Str. 23",
    "sg:city":"Cloppenburg",
    "sg:phone":"+49 4471/2367",
    "sg:postcode":"49661",
    "sg:province":"Niedersachsen",
    "wof:name":"Friedrich Kerckhoff",
    "wof:placetype":"venue"
},
  "geometry": {"coordinates":[8.04118,52.845276],"type":"Point"}
}