{
  "type": "Feature",
  "properties": {
    "iso:country":"DE",
    "sg:address":"M\u00fcnchner Str 80",
    "sg:city":"Unterf\u00f6hring",
    "sg:phone":"+49 89/9504928",
    "sg:postcode":"85774",
    "sg:province":"Bayern",
    "wof:name":"Raiffeisenbank M\u00fcnchen Eg",
    "wof:placetype":"venue"
},
  "geometry": {"coordinates":[11.641957,48.193909],"type":"Point"}
}