{
  "type": "Feature",
  "properties": {
    "iso:country":"DE",
    "sg:address":"Hospitalstr. 27",
    "sg:city":"G\u00f6ttingen",
    "sg:phone":"+49 551/541526",
    "sg:postcode":"37073",
    "sg:province":"Niedersachsen",
    "wof:name":"Aqua-institut F\u00fcr Angewandte Qualit\u00e4tsf\u00f6rderung U. Forsch.",
    "wof:placetype":"venue"
},
  "geometry": {"coordinates":[9.9341716766,51.5299301147],"type":"Point"}
}