{
  "type": "Feature",
  "properties": {
    "iso:country":"DE",
    "sg:address":"Lukkaer Str. 2a",
    "sg:city":"Odelzhausen",
    "sg:phone":"+49 8134/6403",
    "sg:postcode":"85235",
    "sg:province":"Bayern",
    "wof:name":"Ne We Tec Vertriebs Gmbh",
    "wof:placetype":"venue"
},
  "geometry": {"coordinates":[11.198952,48.308521],"type":"Point"}
}