{
  "type": "Feature",
  "properties": {
    "iso:country":"DE",
    "sg:address":"L\u00f6\u00dfnitzer Str. 15",
    "sg:city":"Freiberg",
    "sg:phone":"+49 3731/247214",
    "sg:postcode":"09599",
    "sg:province":"Sachsen",
    "wof:name":"Monika Zsch\u00f6rnig",
    "wof:placetype":"venue"
},
  "geometry": {"coordinates":[13.3230829239,50.9232521057],"type":"Point"}
}