{
  "type": "Feature",
  "properties": {
    "iso:country":"DE",
    "sg:address":"Sch\u00f6llersheider Str. 31",
    "sg:city":"Mettmann",
    "sg:phone":"+49 2104/924620",
    "sg:postcode":"40822",
    "sg:province":"Nordrhein-Westfalen",
    "wof:name":"Frank M\u00f6ller",
    "wof:placetype":"venue"
},
  "geometry": {"coordinates":[7.0082812309,51.2475280762],"type":"Point"}
}