{
  "type": "Feature",
  "properties": {
    "iso:country":"DE",
    "sg:address":"Bismarckring 12",
    "sg:city":"Wiesbaden",
    "sg:phone":"+49 611/449027",
    "sg:postcode":"65185",
    "sg:province":"Hessen",
    "wof:name":"Gerd M\u00fcller Gmbh",
    "wof:placetype":"venue"
},
  "geometry": {"coordinates":[8.229406,50.07925],"type":"Point"}
}