{
  "type": "Feature",
  "properties": {
    "iso:country":"DE",
    "sg:address":"Handstr. 262",
    "sg:city":"Bergisch Gladbach",
    "sg:phone":"+49 2202/57870",
    "sg:postcode":"51469",
    "sg:province":"Nordrhein-Westfalen",
    "wof:name":"Al Capriccio Restaurant Gmbh & Co. Kg",
    "wof:placetype":"venue"
},
  "geometry": {"coordinates":[7.1042609215,50.9915924072],"type":"Point"}
}