{
  "type": "Feature",
  "properties": {
    "iso:country":"DE",
    "sg:address":"Masurenallee 17 A",
    "sg:city":"Bad Wildungen",
    "sg:phone":"+49 5621/6238",
    "sg:postcode":"34537",
    "sg:province":"Hessen",
    "wof:name":"G\u00e4stehaus H. Landau",
    "wof:placetype":"venue"
},
  "geometry": {"coordinates":[9.0758371353,51.1160850525],"type":"Point"}
}