{
  "type": "Feature",
  "properties": {
    "iso:country":"DE",
    "sg:address":"Ackerwiesenstr. 30",
    "sg:city":"Waiblingen",
    "sg:phone":"+49 7151/9391930",
    "sg:postcode":"71334",
    "sg:province":"Baden-W\u00fcrttemberg",
    "wof:name":"Genotec Elektronik Gmbh",
    "wof:placetype":"venue"
},
  "geometry": {"coordinates":[9.3465900421,48.8186187744],"type":"Point"}
}