{
  "type": "Feature",
  "properties": {
    "iso:country":"DE",
    "sg:address":"Eisenbahnstr. 3",
    "sg:city":"Ravensburg",
    "sg:phone":"+49 751/33457",
    "sg:postcode":"88212",
    "sg:province":"Baden-W\u00fcrttemberg",
    "wof:name":"Sylvia Wohlfeil",
    "wof:placetype":"venue"
},
  "geometry": {"coordinates":[9.612792,47.782761],"type":"Point"}
}