{
  "type": "Feature",
  "properties": {
    "iso:country":"DE",
    "sg:address":"\u00dcssinghausen 8",
    "sg:city":"Twistringen",
    "sg:phone":"+49 4243/763",
    "sg:postcode":"27239",
    "sg:province":"Niedersachsen",
    "wof:name":"Wilhelm Alfken",
    "wof:placetype":"venue"
},
  "geometry": {"coordinates":[8.647454,52.830296],"type":"Point"}
}