{
  "type": "Feature",
  "properties": {
    "iso:country":"DE",
    "sg:address":"Norderstr. 4",
    "sg:city":"Lentf\u00f6hrden",
    "sg:phone":"+49 4192/897370",
    "sg:postcode":"24632",
    "sg:province":"Schleswig-Holstein",
    "wof:name":"Schulz-elektro Gmbh",
    "wof:placetype":"venue"
},
  "geometry": {"coordinates":[9.882285,53.881001],"type":"Point"}
}