{
  "type": "Feature",
  "properties": {
    "iso:country":"DE",
    "sg:address":"Schrobenhausener Str. 42",
    "sg:city":"Karlshuld",
    "sg:phone":"+49 8454/616",
    "sg:postcode":"86668",
    "sg:province":"Bayern",
    "wof:name":"Gottfried Jung",
    "wof:placetype":"venue"
},
  "geometry": {"coordinates":[11.266281,48.669975],"type":"Point"}
}