{
  "type": "Feature",
  "properties": {
    "iso:country":"DE",
    "sg:address":"Wittelsbacherstr. 1",
    "sg:city":"Bad Reichenhall",
    "sg:postcode":"83435",
    "sg:province":"Bayern",
    "wof:name":"Holzbau Ateka Gmbh",
    "wof:placetype":"venue"
},
  "geometry": {"coordinates":[12.8761367798,47.7265739441],"type":"Point"}
}