{
  "type": "Feature",
  "properties": {
    "iso:country":"DE",
    "sg:address":"Hauptstr. 38b",
    "sg:city":"Frankenberg",
    "sg:phone":"+49 37206/3132",
    "sg:postcode":"09669",
    "sg:province":"Sachsen",
    "wof:name":"Rolf Ranft",
    "wof:placetype":"venue"
},
  "geometry": {"coordinates":[13.0459976196,50.9492301941],"type":"Point"}
}