{
  "type": "Feature",
  "properties": {
    "iso:country":"DE",
    "sg:address":"Fliederstr. 10",
    "sg:city":"Duisburg",
    "sg:phone":"+49 203/770563",
    "sg:postcode":"47055",
    "sg:province":"Nordrhein-Westfalen",
    "wof:name":"Alex Groth",
    "wof:placetype":"venue"
},
  "geometry": {"coordinates":[6.757028,51.406151],"type":"Point"}
}