{
  "type": "Feature",
  "properties": {
    "iso:country":"DE",
    "sg:address":"Marktstr. 1",
    "sg:city":"Lathen",
    "sg:phone":"+49 5933/1311",
    "sg:postcode":"49762",
    "sg:province":"Niedersachsen",
    "wof:name":"Emsdrogerie",
    "wof:placetype":"venue"
},
  "geometry": {"coordinates":[7.315914,52.86055],"type":"Point"}
}