{
  "type": "Feature",
  "properties": {
    "iso:country":"DE",
    "sg:address":"Kreuzstr. 37",
    "sg:city":"Dortmund",
    "sg:phone":"+49 231/124050",
    "sg:postcode":"44139",
    "sg:province":"Nordrhein-Westfalen",
    "wof:name":"Fritz Torlop",
    "wof:placetype":"venue"
},
  "geometry": {"coordinates":[7.4554619789,51.5034408569],"type":"Point"}
}