{
  "type": "Feature",
  "properties": {
    "iso:country":"DE",
    "sg:address":"Hradeker Str. 18",
    "sg:city":"Hennigsdorf",
    "sg:phone":"+49 3302/220818",
    "sg:postcode":"16761",
    "sg:province":"Brandenburg",
    "wof:name":"Amw Immobilien Und Serviceb\u00fcro E. K.",
    "wof:placetype":"venue"
},
  "geometry": {"coordinates":[13.1976413727,52.6538963318],"type":"Point"}
}