{
  "type": "Feature",
  "properties": {
    "iso:country":"DE",
    "sg:address":"Kirchstr. 5",
    "sg:city":"Gelsenkirchen",
    "sg:phone":"+49 209/205989",
    "sg:postcode":"45879",
    "sg:province":"Nordrhein-Westfalen",
    "wof:name":"K. Helmke",
    "wof:placetype":"venue"
},
  "geometry": {"coordinates":[7.097232,51.50996],"type":"Point"}
}