{
  "type": "Feature",
  "properties": {
    "iso:country":"DE",
    "sg:address":"Kanalstr. Nord 231 a",
    "sg:city":"Gro\u00dfefehn",
    "sg:phone":"+49 4943/1531",
    "sg:postcode":"26629",
    "sg:province":"Niedersachsen",
    "wof:name":"Rolf Kross",
    "wof:placetype":"venue"
},
  "geometry": {"coordinates":[7.671031,53.416138],"type":"Point"}
}