{
  "type": "Feature",
  "properties": {
    "iso:country":"DE",
    "sg:address":"Auering 57",
    "sg:city":"Neu Wulmstorf",
    "sg:phone":"+49 40/70012335",
    "sg:postcode":"21629",
    "sg:province":"Niedersachsen",
    "wof:name":"Behring Edv-baratung",
    "wof:placetype":"venue"
},
  "geometry": {"coordinates":[9.795368,53.470631],"type":"Point"}
}