{
  "type": "Feature",
  "properties": {
    "iso:country":"DE",
    "sg:address":"HsNr. 50",
    "sg:city":"Hohenburg",
    "sg:postcode":"92277",
    "sg:province":"Bayern",
    "wof:name":"Omnibus Lindner Gmbh",
    "wof:placetype":"venue"
},
  "geometry": {"coordinates":[11.7997655869,49.2946166992],"type":"Point"}
}