{
  "type": "Feature",
  "properties": {
    "iso:country":"DE",
    "sg:address":"Golfstr. 1",
    "sg:city":"Gutach",
    "sg:phone":"+49 7685/22929",
    "sg:postcode":"79261",
    "sg:province":"Baden-W\u00fcrttemberg",
    "wof:name":"Friedericke Sauer",
    "wof:placetype":"venue"
},
  "geometry": {"coordinates":[-100.681099,34.47147],"type":"Point"}
}