{
  "type": "Feature",
  "properties": {
    "iso:country":"DE",
    "sg:address":"Werdenfelser Str. 25",
    "sg:city":"Farchant",
    "sg:phone":"+49 8821/61117",
    "sg:postcode":"82490",
    "sg:province":"Bayern",
    "wof:name":"Manfred Ufer Industrievertretungen",
    "wof:placetype":"venue"
},
  "geometry": {"coordinates":[11.1047897339,47.5259399414],"type":"Point"}
}