{
  "type": "Feature",
  "properties": {
    "iso:country":"DE",
    "sg:address":"Bachstr. 29",
    "sg:city":"Ettlingen",
    "sg:phone":"+49 7243/78508",
    "sg:postcode":"76275",
    "sg:province":"Baden-W\u00fcrttemberg",
    "wof:name":"Rudi Krause",
    "wof:placetype":"venue"
},
  "geometry": {"coordinates":[8.3937149048,48.9407043457],"type":"Point"}
}