{
  "type": "Feature",
  "properties": {
    "iso:country":"DE",
    "sg:address":"Edlinger Str. 5",
    "sg:city":"Scheyern",
    "sg:phone":"+49 8445/260",
    "sg:postcode":"85298",
    "sg:province":"Bayern",
    "wof:name":"Franz Greppmeier",
    "wof:placetype":"venue"
},
  "geometry": {"coordinates":[11.40736,48.511456],"type":"Point"}
}