{
  "type": "Feature",
  "properties": {
    "iso:country":"DE",
    "sg:address":"Geisaer Str. 46c",
    "sg:city":"Oechsen",
    "sg:phone":"+49 36965/64219",
    "sg:postcode":"36404",
    "sg:province":"Th\u00fcringen",
    "wof:name":"Josef Krieg",
    "wof:placetype":"venue"
},
  "geometry": {"coordinates":[10.061061,50.744072],"type":"Point"}
}