{
  "type": "Feature",
  "properties": {
    "iso:country":"DE",
    "sg:address":"Kopernikusring 9",
    "sg:city":"Eberswalde",
    "sg:phone":"+49 3334/24133",
    "sg:postcode":"16227",
    "sg:province":"Brandenburg",
    "wof:name":"Joachim Zimmermann",
    "wof:placetype":"venue"
},
  "geometry": {"coordinates":[13.746813,52.836365],"type":"Point"}
}