{
  "type": "Feature",
  "properties": {
    "iso:country":"DE",
    "sg:address":"August-Bebel-Str. 2",
    "sg:city":"Lunzenau",
    "sg:phone":"+49 37383/68234",
    "sg:postcode":"09328",
    "sg:province":"Sachsen",
    "wof:name":"Gebr. Steyer",
    "wof:placetype":"venue"
},
  "geometry": {"coordinates":[12.755119,50.965431],"type":"Point"}
}