{
  "type": "Feature",
  "properties": {
    "iso:country":"DE",
    "sg:address":"Im Rosengarten 18",
    "sg:city":"Sinntal",
    "sg:postcode":"36391",
    "sg:province":"Hessen",
    "wof:name":"Blindenwerkst\u00e4tte",
    "wof:placetype":"venue"
},
  "geometry": {"coordinates":[9.590496,50.32362],"type":"Point"}
}