{
  "type": "Feature",
  "properties": {
    "iso:country":"DE",
    "sg:address":"Uhlandplatz 4",
    "sg:city":"Bad Wildbad",
    "sg:phone":"+49 7081/3699",
    "sg:postcode":"75323",
    "sg:province":"Baden-W\u00fcrttemberg",
    "wof:name":"Antikst\u00fcble",
    "wof:placetype":"venue"
},
  "geometry": {"coordinates":[8.549262,48.750507],"type":"Point"}
}