{
  "type": "Feature",
  "properties": {
    "iso:country":"DE",
    "sg:address":"Wilhelmstr. 1",
    "sg:city":"Oberhausen",
    "sg:phone":"+49 208/669192",
    "sg:postcode":"46145",
    "sg:province":"Nordrhein-Westfalen",
    "wof:name":"Alte Mitte",
    "wof:placetype":"venue"
},
  "geometry": {"coordinates":[6.8456177711,51.5148239136],"type":"Point"}
}