{
  "type": "Feature",
  "properties": {
    "iso:country":"DE",
    "sg:address":"Muensterstrasse 25",
    "sg:city":"Versmold",
    "sg:phone":"+49 5423/43549",
    "sg:postcode":"33775",
    "sg:province":"Nordrhein-Westfalen",
    "wof:name":"Visitenkarten Links",
    "wof:placetype":"venue"
},
  "geometry": {"coordinates":[8.1508407593,52.0392837524],"type":"Point"}
}