{
  "type": "Feature",
  "properties": {
    "iso:country":"DE",
    "sg:address":"Davenstedter Str. 102",
    "sg:city":"Hannover",
    "sg:phone":"+49 511/2110810",
    "sg:postcode":"30453",
    "sg:province":"Niedersachsen",
    "wof:name":"Willi Hoppert Gmbh",
    "wof:placetype":"venue"
},
  "geometry": {"coordinates":[9.696255,52.365795],"type":"Point"}
}