{
  "type": "Feature",
  "properties": {
    "iso:country":"DE",
    "sg:address":"Karlsteiner Str. 26",
    "sg:city":"Neu Wulmstorf",
    "sg:phone":"+49 4168/911250",
    "sg:postcode":"21629",
    "sg:province":"Niedersachsen",
    "wof:name":"Comcon Computer Und Consulting Gmbh",
    "wof:placetype":"venue"
},
  "geometry": {"coordinates":[9.7809505463,53.4064941406],"type":"Point"}
}