{
  "type": "Feature",
  "properties": {
    "iso:country":"DE",
    "sg:address":"Martinsbogen 8",
    "sg:city":"Leipzig",
    "sg:phone":"+49 341/3303100",
    "sg:postcode":"04158",
    "sg:province":"Sachsen",
    "wof:name":"Dr. G\u00fcnter Albert Tierarzt",
    "wof:placetype":"venue"
},
  "geometry": {"coordinates":[12.3566236496,51.386051178],"type":"Point"}
}