{
  "type": "Feature",
  "properties": {
    "iso:country":"DE",
    "sg:address":"Amonsh\u00f6he 10",
    "sg:city":"Ha\u00dffurt",
    "sg:phone":"+49 9521/2275",
    "sg:postcode":"97437",
    "sg:province":"Bayern",
    "wof:name":"Dr. Erich Ullrich Rechtsanwalt",
    "wof:placetype":"venue"
},
  "geometry": {"coordinates":[10.5147981644,50.0415039062],"type":"Point"}
}