{
  "type": "Feature",
  "properties": {
    "iso:country":"DE",
    "sg:address":"Beerenweg 6-8",
    "sg:city":"Hamburg",
    "sg:postcode":"22761",
    "sg:province":"Hamburg",
    "wof:name":"Vgn Verlagsgesellschaft Neue Medien Mbh",
    "wof:placetype":"venue"
},
  "geometry": {"coordinates":[9.9223089218,53.5646286011],"type":"Point"}
}