{
  "type": "Feature",
  "properties": {
    "iso:country":"DE",
    "sg:address":"Bussardweg 19",
    "sg:city":"Waldenbuch",
    "sg:phone":"+49 7157/4413",
    "sg:postcode":"71111",
    "sg:province":"Baden-W\u00fcrttemberg",
    "wof:name":"J\u00fcrgen Hartmann Rep.-werkstatt",
    "wof:placetype":"venue"
},
  "geometry": {"coordinates":[9.141755,48.64563],"type":"Point"}
}