{
  "type": "Feature",
  "properties": {
    "iso:country":"DE",
    "sg:address":"Flugplatzstr. 23",
    "sg:city":"Friedrichshafen",
    "sg:phone":"+49 7541/72781",
    "sg:postcode":"88046",
    "sg:province":"Baden-W\u00fcrttemberg",
    "wof:name":"Klosterwirt",
    "wof:placetype":"venue"
},
  "geometry": {"coordinates":[9.4934177399,47.6611709595],"type":"Point"}
}