{
  "type": "Feature",
  "properties": {
    "iso:country":"DE",
    "sg:address":"Salzburger Str. 1",
    "sg:city":"Wasserburg",
    "sg:phone":"+49 8071/51663",
    "sg:postcode":"83512",
    "sg:province":"Bayern",
    "wof:name":"Bruckbr\u00e4u Zum Griechen",
    "wof:placetype":"venue"
},
  "geometry": {"coordinates":[12.2325935364,48.0583496094],"type":"Point"}
}