{
  "type": "Feature",
  "properties": {
    "iso:country":"DE",
    "sg:address":"71287",
    "sg:city":"Weissach",
    "sg:phone":"+49 7044/31310",
    "sg:postcode":"71287",
    "sg:province":"Baden-W\u00fcrttemberg",
    "wof:name":"Ev. Pfarramt",
    "wof:placetype":"venue"
},
  "geometry": {"coordinates":[8.9183998108,48.842300415],"type":"Point"}
}