{
  "type": "Feature",
  "properties": {
    "iso:country":"DE",
    "sg:address":"Rosenweg 42",
    "sg:city":"Schwarme",
    "sg:phone":"+49 4255/380",
    "sg:postcode":"27327",
    "sg:province":"Niedersachsen",
    "wof:name":"Erich Hustedt",
    "wof:placetype":"venue"
},
  "geometry": {"coordinates":[9.012362,52.891743],"type":"Point"}
}