{
  "type": "Feature",
  "properties": {
    "iso:country":"DE",
    "sg:address":"Quellenstr. 36",
    "sg:city":"Wuppertal",
    "sg:phone":"+49 202/435111",
    "sg:postcode":"42117",
    "sg:province":"Nordrhein-Westfalen",
    "wof:name":"Auto-j\u00fcnemann Gmbh",
    "wof:placetype":"venue"
},
  "geometry": {"coordinates":[7.1293029785,51.2451629639],"type":"Point"}
}