{
  "type": "Feature",
  "properties": {
    "iso:country":"DE",
    "sg:address":"K\u00f6nigswieser Str. 5",
    "sg:city":"M\u00fcnchen",
    "sg:phone":"+49 89/758409",
    "sg:postcode":"81475",
    "sg:province":"Bayern",
    "wof:name":"K\u00f6nigs-apotheke",
    "wof:placetype":"venue"
},
  "geometry": {"coordinates":[11.484941,48.083057],"type":"Point"}
}