{
  "type": "Feature",
  "properties": {
    "iso:country":"DE",
    "sg:address":"Kamillusweg 5",
    "sg:city":"M\u00fcnster",
    "sg:phone":"+49 251/143444",
    "sg:postcode":"48157",
    "sg:province":"Nordrhein-Westfalen",
    "wof:name":"Klaus Dupin",
    "wof:placetype":"venue"
},
  "geometry": {"coordinates":[7.6929101944,51.9943809509],"type":"Point"}
}