{
  "type": "Feature",
  "properties": {
    "iso:country":"DE",
    "sg:address":"Krumme Str. 22",
    "sg:city":"Syke",
    "sg:phone":"+49 4242/70967",
    "sg:postcode":"28857",
    "sg:province":"Niedersachsen",
    "wof:name":"Stickan",
    "wof:placetype":"venue"
},
  "geometry": {"coordinates":[8.8251724243,52.9109954834],"type":"Point"}
}