{
  "type": "Feature",
  "properties": {
    "iso:country":"DE",
    "sg:address":"Judengraben 20 Geh\u00fclz",
    "sg:city":"Kronach",
    "sg:phone":"+49 9261/1499",
    "sg:postcode":"96317",
    "sg:province":"Bayern",
    "wof:name":"Liftstuben",
    "wof:placetype":"venue"
},
  "geometry": {"coordinates":[11.3274345398,50.2411613464],"type":"Point"}
}