{
  "type": "Feature",
  "properties": {
    "iso:country":"DE",
    "sg:address":"Ebersbrunner Str. 1",
    "sg:city":"Sch\u00f6nfels",
    "sg:phone":"+49 37600/2587",
    "sg:postcode":"08115",
    "sg:province":"Sachsen",
    "wof:name":"Bernhard Zierke",
    "wof:placetype":"venue"
},
  "geometry": {"coordinates":[12.404786,50.675617],"type":"Point"}
}