{
  "type": "Feature",
  "properties": {
    "iso:country":"DE",
    "sg:address":"Kempener Str. 36",
    "sg:city":"Erkrath",
    "sg:phone":"+49 2104/390811",
    "sg:postcode":"40699",
    "sg:province":"Nordrhein-Westfalen",
    "wof:name":"B\u00e4cker Messebau",
    "wof:placetype":"venue"
},
  "geometry": {"coordinates":[6.942101,51.204914],"type":"Point"}
}