{
  "type": "Feature",
  "properties": {
    "iso:country":"DE",
    "sg:address":"Bismarckstr. 11",
    "sg:city":"Bruchsal",
    "sg:phone":"+49 7251/300053",
    "sg:postcode":"76646",
    "sg:province":"Baden-W\u00fcrttemberg",
    "wof:name":"Anker-apotheke",
    "wof:placetype":"venue"
},
  "geometry": {"coordinates":[8.591866,49.122318],"type":"Point"}
}