{
  "type": "Feature",
  "properties": {
    "iso:country":"DE",
    "sg:address":"M\u00fcnsterstr. 27",
    "sg:city":"\u00dcberlingen",
    "sg:phone":"+49 7551/5176",
    "sg:postcode":"88662",
    "sg:province":"Baden-W\u00fcrttemberg",
    "wof:name":"A. Zarrinbal",
    "wof:placetype":"venue"
},
  "geometry": {"coordinates":[9.1613883972,47.7664718628],"type":"Point"}
}