{
  "type": "Feature",
  "properties": {
    "iso:country":"DE",
    "sg:address":"Okerstr. 17",
    "sg:city":"Wolfenb\u00fcttel",
    "sg:postcode":"38300",
    "sg:province":"Niedersachsen",
    "wof:name":"Kaisers Markt",
    "wof:placetype":"venue"
},
  "geometry": {"coordinates":[10.537853241,52.1641235352],"type":"Point"}
}