{
  "type": "Feature",
  "properties": {
    "iso:country":"DE",
    "sg:address":"Oberh\u00fctzer Str. 13",
    "sg:city":"Remscheid",
    "sg:phone":"+49 4921/9188550",
    "sg:postcode":"42857",
    "sg:province":"Nordrhein-Westfalen",
    "wof:name":"Grund & Bunse Maschinenmesserfabrik Gmbh",
    "wof:placetype":"venue"
},
  "geometry": {"coordinates":[7.1611461639,51.1908416748],"type":"Point"}
}