{
  "type": "Feature",
  "properties": {
    "iso:country":"DE",
    "sg:address":"Himmelreichstr. 17",
    "sg:city":"Buchenbach",
    "sg:phone":"+49 7661/3383",
    "sg:postcode":"79256",
    "sg:province":"Baden-W\u00fcrttemberg",
    "wof:name":"Thomas Schweizer Gmbh",
    "wof:placetype":"venue"
},
  "geometry": {"coordinates":[7.9921040535,47.9581336975],"type":"Point"}
}