{
  "type": "Feature",
  "properties": {
    "iso:country":"DE",
    "sg:address":"Heilbronner Str. 33",
    "sg:city":"Marbach",
    "sg:phone":"+49 7144/15223",
    "sg:postcode":"71672",
    "sg:province":"Baden-W\u00fcrttemberg",
    "wof:name":"H. J. Moritz Steuerberater",
    "wof:placetype":"venue"
},
  "geometry": {"coordinates":[9.2548389435,48.9261474609],"type":"Point"}
}