{
  "type": "Feature",
  "properties": {
    "iso:country":"DE",
    "sg:address":"Wasen\u00e4ckerstr. 9",
    "sg:city":"Rottweil",
    "sg:phone":"+49 741/32149",
    "sg:postcode":"78628",
    "sg:province":"Baden-W\u00fcrttemberg",
    "wof:name":"Vereinigung Der Franz\u00f6sisch Lehrer E. V.",
    "wof:placetype":"venue"
},
  "geometry": {"coordinates":[8.5848846436,48.1455383301],"type":"Point"}
}