{
  "type": "Feature",
  "properties": {
    "iso:country":"DE",
    "sg:address":"Heinrich-von-Brentano-Str. 7",
    "sg:city":"Bad Abbach",
    "sg:postcode":"93077",
    "sg:province":"Bayern",
    "wof:name":"Christl & Partner",
    "wof:placetype":"venue"
},
  "geometry": {"coordinates":[12.0679197311,48.9375610352],"type":"Point"}
}