{
  "type": "Feature",
  "properties": {
    "iso:country":"DE",
    "sg:address":"Dorfstr. 14",
    "sg:city":"Langlingen",
    "sg:phone":"+49 5082/696",
    "sg:postcode":"29364",
    "sg:province":"Niedersachsen",
    "wof:name":"G\u00fcnther K\u00f6ther",
    "wof:placetype":"venue"
},
  "geometry": {"coordinates":[10.319913,52.554577],"type":"Point"}
}