{
  "type": "Feature",
  "properties": {
    "iso:country":"DE",
    "sg:address":"Eubigstr. 26",
    "sg:city":"Marktrodach",
    "sg:phone":"+49 9261/4367",
    "sg:postcode":"96364",
    "sg:province":"Bayern",
    "wof:name":"Gerhard Wich Bauten- Schutz Gmbh",
    "wof:placetype":"venue"
},
  "geometry": {"coordinates":[11.3962917328,50.25440979],"type":"Point"}
}