{
  "type": "Feature",
  "properties": {
    "iso:country":"DE",
    "sg:address":"Keplerstr. 2",
    "sg:city":"Schwerin",
    "sg:phone":"+49 385/2014020",
    "sg:postcode":"19063",
    "sg:province":"Mecklenburg-Vorpommern",
    "wof:name":"M. B\u00e4hne",
    "wof:placetype":"venue"
},
  "geometry": {"coordinates":[11.46765,53.591465],"type":"Point"}
}