{
  "type": "Feature",
  "properties": {
    "iso:country":"DE",
    "sg:address":"M\u00fchltal 1",
    "sg:city":"Boppard",
    "sg:phone":"+49 6742/1852",
    "sg:postcode":"56154",
    "sg:province":"Rheinland-Pfalz",
    "wof:name":"Peter Enderlein & Eddy Hohl",
    "wof:placetype":"venue"
},
  "geometry": {"coordinates":[7.5776901245,50.2349967957],"type":"Point"}
}