{
  "type": "Feature",
  "properties": {
    "iso:country":"DE",
    "sg:address":"Lorentzendamm 20",
    "sg:city":"Kiel",
    "sg:phone":"+49 431/551822",
    "sg:postcode":"24103",
    "sg:province":"Schleswig-Holstein",
    "wof:name":"Aschmoneit-l\u00fccke Und Musculus-stahnke",
    "wof:placetype":"venue"
},
  "geometry": {"coordinates":[10.1377410889,54.3265991211],"type":"Point"}
}