{
  "type": "Feature",
  "properties": {
    "iso:country":"DE",
    "sg:address":"Gro\u00dfe Friedberger Str. 23",
    "sg:city":"Frankfurt",
    "sg:phone":"+49 69/287847",
    "sg:postcode":"60313",
    "sg:province":"Hessen",
    "wof:name":"Super-top-musik Verlag Gmbh",
    "wof:placetype":"venue"
},
  "geometry": {"coordinates":[8.686084,50.115696],"type":"Point"}
}