{
  "type": "Feature",
  "properties": {
    "iso:country":"DE",
    "sg:address":"Schreinerstr. 53",
    "sg:city":"Berlin",
    "sg:phone":"+49 30",
    "sg:postcode":"10247",
    "sg:province":"Berlin",
    "wof:name":"Physioenergy Gesundheitsvorsorge Am Arbeitsplatz",
    "wof:placetype":"venue"
},
  "geometry": {"coordinates":[13.464874,52.51759],"type":"Point"}
}