{
  "type": "Feature",
  "properties": {
    "iso:country":"DE",
    "sg:address":"Sch\u00f6ppenstedter Str. 20",
    "sg:city":"Braunschweig",
    "sg:phone":"+49 531/42544",
    "sg:postcode":"38100",
    "sg:province":"Niedersachsen",
    "wof:name":"I. Rosenfeld",
    "wof:placetype":"venue"
},
  "geometry": {"coordinates":[10.5283927917,52.2677192688],"type":"Point"}
}