{
  "type": "Feature",
  "properties": {
    "iso:country":"DE",
    "sg:address":"Chateauneufstr. 14",
    "sg:city":"Alfter",
    "sg:phone":"+49 228/6420171",
    "sg:postcode":"53347",
    "sg:province":"Nordrhein-Westfalen",
    "wof:name":"M. Fuhrmann Rechtsanwalt",
    "wof:placetype":"venue"
},
  "geometry": {"coordinates":[7.0273518562,50.7213935852],"type":"Point"}
}