{
  "type": "Feature",
  "properties": {
    "iso:country":"DE",
    "sg:address":"Wewerstr. 60",
    "sg:city":"Paderborn",
    "sg:phone":"+49 5251/92638",
    "sg:postcode":"33106",
    "sg:province":"Nordrhein-Westfalen",
    "wof:name":"Bodo Spitzbarth",
    "wof:placetype":"venue"
},
  "geometry": {"coordinates":[8.697525,51.709625],"type":"Point"}
}