{
  "type": "Feature",
  "properties": {
    "iso:country":"DE",
    "sg:address":"Dorfstr. 17",
    "sg:city":"Oegeln",
    "sg:phone":"+49 3366/21693",
    "sg:postcode":"15848",
    "sg:province":"Brandenburg",
    "wof:name":"G. Langanke",
    "wof:placetype":"venue"
},
  "geometry": {"coordinates":[14.281969,52.180824],"type":"Point"}
}