{
  "type": "Feature",
  "properties": {
    "iso:country":"DE",
    "sg:address":"K\u00f6hler Str. 60",
    "sg:city":"Dorsten",
    "sg:phone":"+49 2369/4262",
    "sg:postcode":"46286",
    "sg:province":"Nordrhein-Westfalen",
    "wof:name":"Werner Kensy Inh. Johannes Ei\u00dfing",
    "wof:placetype":"venue"
},
  "geometry": {"coordinates":[7.003893,51.710903],"type":"Point"}
}