{
  "type": "Feature",
  "properties": {
    "iso:country":"DE",
    "sg:address":"Karlsruhestr. 32",
    "sg:city":"Hockenheim",
    "sg:phone":"+49 4962/0594070",
    "sg:postcode":"68766",
    "sg:province":"Baden-W\u00fcrttemberg",
    "wof:name":"Reymann Technik Gmbh",
    "wof:placetype":"venue"
},
  "geometry": {"coordinates":[8.541449,49.317585],"type":"Point"}
}