{
  "type": "Feature",
  "properties": {
    "iso:country":"DE",
    "sg:address":"Neustadtring 30 a",
    "sg:city":"Braunschweig",
    "sg:phone":"+49 531/256240",
    "sg:postcode":"38114",
    "sg:province":"Niedersachsen",
    "wof:name":"G\u00f6ttingen Hausverwaltung Gmbh",
    "wof:placetype":"venue"
},
  "geometry": {"coordinates":[10.512260437,52.2737464905],"type":"Point"}
}