{
  "type": "Feature",
  "properties": {
    "iso:country":"DE",
    "sg:address":"Hans-R\u00f6mhild-Str. 42",
    "sg:city":"Kassel",
    "sg:phone":"+49 561/887586",
    "sg:postcode":"34128",
    "sg:province":"Hessen",
    "wof:name":"Hk Immobilienmanagement F\u00fcr Handel Und Gewerbe",
    "wof:placetype":"venue"
},
  "geometry": {"coordinates":[9.4434509277,51.3465690613],"type":"Point"}
}