{
  "type": "Feature",
  "properties": {
    "iso:country":"DE",
    "sg:address":"Eintrachtstr. 9",
    "sg:city":"Solingen",
    "sg:postcode":"42655",
    "sg:province":"Nordrhein-Westfalen",
    "wof:name":"Sg-gestelltechnik Gmbh",
    "wof:placetype":"venue"
},
  "geometry": {"coordinates":[7.074382,51.177921],"type":"Point"}
}