{
  "type": "Feature",
  "properties": {
    "iso:country":"DE",
    "sg:address":"Dreherstr. 14",
    "sg:city":"Remscheid",
    "sg:phone":"+49 2191/5808",
    "sg:postcode":"42899",
    "sg:province":"Nordrhein-Westfalen",
    "wof:name":"Somborn Gmbh",
    "wof:placetype":"venue"
},
  "geometry": {"coordinates":[7.221864,51.219822],"type":"Point"}
}