{
  "type": "Feature",
  "properties": {
    "iso:country":"DE",
    "sg:address":"Helmstedter Str. 32 a",
    "sg:city":"Irxleben",
    "sg:phone":"+49 39204/60034",
    "sg:postcode":"39167",
    "sg:province":"Sachsen-Anhalt",
    "wof:name":"Installationstechnik Und Service Gmbh",
    "wof:placetype":"venue"
},
  "geometry": {"coordinates":[11.476379,52.164963],"type":"Point"}
}