{
  "type": "Feature",
  "properties": {
    "iso:country":"DE",
    "sg:address":"Jakob-Henle-Str. 1",
    "sg:city":"F\u00fcrth",
    "sg:phone":"+49 911/75800",
    "sg:postcode":"90766",
    "sg:province":"Bayern",
    "wof:name":"Klinikum F\u00fcrth",
    "wof:placetype":"venue"
},
  "geometry": {"coordinates":[10.974366,49.483597],"type":"Point"}
}