{
  "type": "Feature",
  "properties": {
    "iso:country":"DE",
    "sg:address":"P\u00fctzgesbenden 7",
    "sg:city":"D\u00fcren",
    "sg:phone":"+49 2421/950141",
    "sg:postcode":"52355",
    "sg:province":"Nordrhein-Westfalen",
    "wof:name":"Kurt Franck Steuerberater",
    "wof:placetype":"venue"
},
  "geometry": {"coordinates":[6.4810390472,50.7695198059],"type":"Point"}
}