{
  "type": "Feature",
  "properties": {
    "iso:country":"DE",
    "sg:address":"Seeweg 11",
    "sg:city":"Heinsberg",
    "sg:phone":"+49 2452/87105",
    "sg:postcode":"52525",
    "sg:province":"Nordrhein-Westfalen",
    "wof:name":"Aw-kfz Hobby-werkstatt Gmbh",
    "wof:placetype":"venue"
},
  "geometry": {"coordinates":[6.092958,51.073063],"type":"Point"}
}