{
  "type": "Feature",
  "properties": {
    "iso:country":"DE",
    "sg:address":"Bahnhofstr. 17",
    "sg:city":"Ingelheim",
    "sg:phone":"+49 6132/2231",
    "sg:postcode":"55218",
    "sg:province":"Rheinland-Pfalz",
    "wof:name":"Vogt & Schoor Gmbh",
    "wof:placetype":"venue"
},
  "geometry": {"coordinates":[8.054901123,49.9741592407],"type":"Point"}
}