{
  "type": "Feature",
  "properties": {
    "iso:country":"DE",
    "sg:address":"Auer Gasse 7",
    "sg:city":"Schmalkalden",
    "sg:postcode":"98574",
    "sg:province":"Th\u00fcringen",
    "wof:name":"Optik Schulze E. K.",
    "wof:placetype":"venue"
},
  "geometry": {"coordinates":[10.4501876831,50.7206687927],"type":"Point"}
}