{
  "type": "Feature",
  "properties": {
    "iso:country":"DE",
    "sg:address":"Rieslingweg 21",
    "sg:city":"Heppenheim",
    "sg:postcode":"64646",
    "sg:province":"Hessen",
    "wof:name":"Q & A Agency E. K.",
    "wof:placetype":"venue"
},
  "geometry": {"coordinates":[8.635682,49.653152],"type":"Point"}
}