{
  "type": "Feature",
  "properties": {
    "iso:country":"DE",
    "sg:address":"Timmersholt 12 - 14",
    "sg:city":"Sprockh\u00f6vel",
    "sg:phone":"+49 2339/7046",
    "sg:postcode":"45549",
    "sg:province":"Nordrhein-Westfalen",
    "wof:name":"Wolfgang P\u00f6rschmann Kg",
    "wof:placetype":"venue"
},
  "geometry": {"coordinates":[7.2594280243,51.3294525146],"type":"Point"}
}