{
  "type": "Feature",
  "properties": {
    "iso:country":"DE",
    "sg:address":"Auf den Stock\u00e4ckern 6",
    "sg:city":"Glauburg",
    "sg:phone":"+49 6041/4406",
    "sg:postcode":"63695",
    "sg:province":"Hessen",
    "wof:name":"Baudekoration Mogk Gmbh",
    "wof:placetype":"venue"
},
  "geometry": {"coordinates":[9.002047,50.318169],"type":"Point"}
}