{
  "type": "Feature",
  "properties": {
    "iso:country":"DE",
    "sg:address":"Gutenbergstr. 30",
    "sg:city":"Reinbek",
    "sg:phone":"+49 40/72735110",
    "sg:postcode":"21465",
    "sg:province":"Schleswig-Holstein",
    "wof:name":"Einhorn-presse Verlag Gmbh",
    "wof:placetype":"venue"
},
  "geometry": {"coordinates":[10.2366790771,53.5281829834],"type":"Point"}
}