{
  "type": "Feature",
  "properties": {
    "iso:country":"DE",
    "sg:address":"Hirschlatter Str. 15",
    "sg:city":"Friedrichshafen",
    "sg:phone":"+49 7541/53236",
    "sg:postcode":"88048",
    "sg:province":"Baden-W\u00fcrttemberg",
    "wof:name":"A. H\u00e4ggele",
    "wof:placetype":"venue"
},
  "geometry": {"coordinates":[9.4980697632,47.6890830994],"type":"Point"}
}