{
  "type": "Feature",
  "properties": {
    "iso:country":"DE",
    "sg:address":"Carl-Benz-Str. 11",
    "sg:city":"Weilheim",
    "sg:phone":"+49 7023/2233",
    "sg:postcode":"73235",
    "sg:province":"Baden-W\u00fcrttemberg",
    "wof:name":"Karl Bernauer Gmbh",
    "wof:placetype":"venue"
},
  "geometry": {"coordinates":[9.5489387512,48.6244850159],"type":"Point"}
}