{
  "type": "Feature",
  "properties": {
    "iso:country":"DE",
    "sg:address":"Kiehnlestr. 9",
    "sg:city":"Pforzheim",
    "sg:phone":"+49 7231/106619",
    "sg:postcode":"75172",
    "sg:province":"Baden-W\u00fcrttemberg",
    "wof:name":"Rudolf Pfl\u00fcger",
    "wof:placetype":"venue"
},
  "geometry": {"coordinates":[8.695463,48.893139],"type":"Point"}
}