{
  "type": "Feature",
  "properties": {
    "iso:country":"DE",
    "sg:address":"Hinterm Sportplatz 19",
    "sg:city":"S\u00fcstedt",
    "sg:phone":"+49 4240/485",
    "sg:postcode":"27305",
    "sg:province":"Niedersachsen",
    "wof:name":"K\u00f6hler-haus Gmbh",
    "wof:placetype":"venue"
},
  "geometry": {"coordinates":[8.929183,52.863392],"type":"Point"}
}