{
  "type": "Feature",
  "properties": {
    "iso:country":"DE",
    "sg:address":"Marktstr. 39",
    "sg:city":"Winnenden",
    "sg:phone":"+49 7195/2307",
    "sg:postcode":"71364",
    "sg:province":"Baden-W\u00fcrttemberg",
    "wof:name":"Apotheke Am Torturm Ingrid Hecht-hatzis",
    "wof:placetype":"venue"
},
  "geometry": {"coordinates":[9.398643,48.876453],"type":"Point"}
}