{
  "type": "Feature",
  "properties": {
    "iso:country":"DE",
    "sg:address":"Jahnstr. 2",
    "sg:city":"Ritterhude",
    "sg:phone":"+49 4292/3855",
    "sg:postcode":"27721",
    "sg:province":"Niedersachsen",
    "wof:name":"Schwimmbad",
    "wof:placetype":"venue"
},
  "geometry": {"coordinates":[8.7481174469,53.1857643127],"type":"Point"}
}