{
  "type": "Feature",
  "properties": {
    "iso:country":"DE",
    "sg:address":"Zur Dom\u00e4ne 1",
    "sg:city":"Vienenburg",
    "sg:phone":"+49 4953/2476824",
    "sg:postcode":"38690",
    "sg:province":"Niedersachsen",
    "wof:name":"Otto Breustedt Gmbh",
    "wof:placetype":"venue"
},
  "geometry": {"coordinates":[10.48908,51.973846],"type":"Point"}
}