{
  "type": "Feature",
  "properties": {
    "iso:country":"DE",
    "sg:address":"Bosestr. 10",
    "sg:city":"Bad Brambach",
    "sg:phone":"+49 37438/20280",
    "sg:postcode":"08648",
    "sg:province":"Sachsen",
    "wof:name":"Vogtland-apotheke Konstanze Haberer E. Kfr.",
    "wof:placetype":"venue"
},
  "geometry": {"coordinates":[12.312518,50.222954],"type":"Point"}
}