{
  "type": "Feature",
  "properties": {
    "iso:country":"DE",
    "sg:address":"Hauptstrasse 1",
    "sg:city":"B\u00f6nnigheim",
    "sg:phone":"+49 7143",
    "sg:postcode":"74357",
    "sg:province":"Baden-W\u00fcrttemberg",
    "wof:name":"Amann N\u00e4hgarne, B\u00f6nnigheim",
    "wof:placetype":"venue"
},
  "geometry": {"coordinates":[9.0939254761,49.0389976501],"type":"Point"}
}