{
  "type": "Feature",
  "properties": {
    "iso:country":"DE",
    "sg:address":"Konrad-Heby-Weg 11",
    "sg:city":"Bad D\u00fcrrheim",
    "sg:phone":"+49 7726/7685",
    "sg:postcode":"78073",
    "sg:province":"Baden-W\u00fcrttemberg",
    "wof:name":"Christel Els\u00e4sser",
    "wof:placetype":"venue"
},
  "geometry": {"coordinates":[8.5354375839,48.0225715637],"type":"Point"}
}