{
  "type": "Feature",
  "properties": {
    "iso:country":"DE",
    "sg:address":"Ebertstr. 60",
    "sg:city":"Karlsruhe",
    "sg:phone":"+49 721/3530",
    "sg:postcode":"76137",
    "sg:province":"Baden-W\u00fcrttemberg",
    "wof:name":"Karlsruher Beamten- Versicherung Ag",
    "wof:placetype":"venue"
},
  "geometry": {"coordinates":[8.3859300613,48.995300293],"type":"Point"}
}