{
  "type": "Feature",
  "properties": {
    "iso:country":"DE",
    "sg:address":"Am Sportplatz 17",
    "sg:city":"Braunschweig",
    "sg:phone":"+49 531/360455",
    "sg:postcode":"38104",
    "sg:province":"Niedersachsen",
    "wof:name":"Franz Dombach Ingenieur",
    "wof:placetype":"venue"
},
  "geometry": {"coordinates":[10.5967969894,52.2851409912],"type":"Point"}
}