{
  "type": "Feature",
  "properties": {
    "iso:country":"DE",
    "sg:address":"Dammstr. 11",
    "sg:city":"Hohenstein-Ernstthal",
    "sg:phone":"+49 3723/414772",
    "sg:postcode":"09337",
    "sg:province":"Sachsen",
    "wof:name":"C. W. H. Computer-wartung- Hohenstein E. K.",
    "wof:placetype":"venue"
},
  "geometry": {"coordinates":[12.742916,50.807507],"type":"Point"}
}