{
  "type": "Feature",
  "properties": {
    "iso:country":"DE",
    "sg:address":"Sprottauer Str. 51",
    "sg:city":"N\u00fcrnberg",
    "sg:postcode":"90475",
    "sg:province":"Bayern",
    "wof:name":"Bilfinger & Berger Bau- Ag Ndl. Ingenieurbau S\u00fcd",
    "wof:placetype":"venue"
},
  "geometry": {"coordinates":[11.1676,49.413883],"type":"Point"}
}