{
  "type": "Feature",
  "properties": {
    "iso:country":"DE",
    "sg:address":"Brandenburgische Str. 46",
    "sg:city":"Berlin",
    "sg:phone":"+49 30/8916193",
    "sg:postcode":"10707",
    "sg:province":"Berlin",
    "wof:name":"Envi Services Gmbh",
    "wof:placetype":"venue"
},
  "geometry": {"coordinates":[13.3080482483,52.4958953857],"type":"Point"}
}