{
  "type": "Feature",
  "properties": {
    "iso:country":"DE",
    "sg:address":"Gerleve 19",
    "sg:city":"Billerbeck",
    "sg:phone":"+49 2541/2077",
    "sg:postcode":"48727",
    "sg:province":"Nordrhein-Westfalen",
    "wof:name":"Karl Hilbert",
    "wof:placetype":"venue"
},
  "geometry": {"coordinates":[7.236774,51.942532],"type":"Point"}
}