{
  "type": "Feature",
  "properties": {
    "iso:country":"DE",
    "sg:address":"Neuhausstr. 10",
    "sg:city":"Aachen",
    "sg:phone":"+49 241/9203040",
    "sg:postcode":"52078",
    "sg:province":"Nordrhein-Westfalen",
    "wof:name":"Orth Gmbh & Co. Kg",
    "wof:placetype":"venue"
},
  "geometry": {"coordinates":[6.137105,50.759426],"type":"Point"}
}