{
  "type": "Feature",
  "properties": {
    "iso:country":"DE",
    "sg:address":"Im B\u00fcrgergarten 9",
    "sg:city":"Iserlohn",
    "sg:phone":"+49 2371/29478",
    "sg:postcode":"58636",
    "sg:province":"Nordrhein-Westfalen",
    "wof:name":"Dr. Jochen Kirchhoff Ingenieur",
    "wof:placetype":"venue"
},
  "geometry": {"coordinates":[7.7007770538,51.382648468],"type":"Point"}
}