{
  "type": "Feature",
  "properties": {
    "iso:country":"DE",
    "sg:address":"Gersweilerstr. 64",
    "sg:city":"Saarbr\u00fccken",
    "sg:phone":"+49 681/5881690",
    "sg:postcode":"66117",
    "sg:province":"Saarland",
    "wof:name":"Mewa Sagu Gmbh, Technischer Grosshandel",
    "wof:placetype":"venue"
},
  "geometry": {"coordinates":[6.96677,49.232719],"type":"Point"}
}