{
  "type": "Feature",
  "properties": {
    "iso:country":"DE",
    "sg:address":"Hesedorfer Str. 3",
    "sg:city":"Bremerv\u00f6rde",
    "sg:phone":"+49 4761/2798",
    "sg:postcode":"27432",
    "sg:province":"Niedersachsen",
    "wof:name":"Wilkens",
    "wof:placetype":"venue"
},
  "geometry": {"coordinates":[9.1764974594,53.4441184998],"type":"Point"}
}