{
  "type": "Feature",
  "properties": {
    "iso:country":"DE",
    "sg:address":"Carstensstr. 1",
    "sg:city":"Husum",
    "sg:phone":"+49 4841/62500",
    "sg:postcode":"25813",
    "sg:province":"Schleswig-Holstein",
    "wof:name":"Gudrun Sander Hebamme",
    "wof:placetype":"venue"
},
  "geometry": {"coordinates":[9.066108,54.466839],"type":"Point"}
}