{
  "type": "Feature",
  "properties": {
    "iso:country":"DE",
    "sg:address":"Charles-Dickens-Str. 16",
    "sg:city":"Halle",
    "sg:postcode":"06126",
    "sg:province":"Sachsen-Anhalt",
    "wof:name":"Dr. Med. Regina Vogel",
    "wof:placetype":"venue"
},
  "geometry": {"coordinates":[11.906533,51.484444],"type":"Point"}
}