{
  "type": "Feature",
  "properties": {
    "iso:country":"DE",
    "sg:address":"Leipziger Ring 94",
    "sg:city":"Rodgau",
    "sg:phone":"+49 6106/74365",
    "sg:postcode":"63110",
    "sg:province":"Hessen",
    "wof:name":"Christian Teichmann",
    "wof:placetype":"venue"
},
  "geometry": {"coordinates":[8.8782100677,50.0042724609],"type":"Point"}
}