{
  "type": "Feature",
  "properties": {
    "iso:country":"DE",
    "sg:address":"Mellinghofer Str. 27",
    "sg:city":"M\u00fclheim",
    "sg:phone":"+49 208/76991",
    "sg:postcode":"45473",
    "sg:province":"Nordrhein-Westfalen",
    "wof:name":"Badminton-center",
    "wof:placetype":"venue"
},
  "geometry": {"coordinates":[6.8877649307,51.4385414124],"type":"Point"}
}