{
  "type": "Feature",
  "properties": {
    "iso:country":"DE",
    "sg:address":"Paul-Ehrlich-Str. 12",
    "sg:city":"Frankfurt",
    "sg:phone":"+49 69/638797",
    "sg:postcode":"60596",
    "sg:province":"Hessen",
    "wof:name":"C. Sang-pitz Werbegeschenke",
    "wof:placetype":"venue"
},
  "geometry": {"coordinates":[8.6684570312,50.0977516174],"type":"Point"}
}