{
  "type": "Feature",
  "properties": {
    "iso:country":"DE",
    "sg:address":"Reichsstr. 84",
    "sg:city":"Berlin",
    "sg:phone":"+49 30/3053075",
    "sg:postcode":"14052",
    "sg:province":"Berlin",
    "wof:name":"Dresdner Bank",
    "wof:placetype":"venue"
},
  "geometry": {"coordinates":[13.261536,52.515514],"type":"Point"}
}