{
  "type": "Feature",
  "properties": {
    "iso:country":"DE",
    "sg:address":"Martenerstr. 525a",
    "sg:city":"Dortmund",
    "sg:phone":"+49 231/9613450",
    "sg:postcode":"44379",
    "sg:province":"Nordrhein-Westfalen",
    "wof:name":"Trippe Industrieelectronic Gmbh",
    "wof:placetype":"venue"
},
  "geometry": {"coordinates":[7.384358,51.510132],"type":"Point"}
}