{
  "type": "Feature",
  "properties": {
    "iso:country":"DE",
    "sg:address":"Borstr. 37",
    "sg:city":"Radebeul",
    "sg:phone":"+49 351/8385530",
    "sg:postcode":"01445",
    "sg:province":"Sachsen",
    "wof:name":"Dr. Andreas Stegmann Rechtsanwalt",
    "wof:placetype":"venue"
},
  "geometry": {"coordinates":[13.6462421417,51.1070365906],"type":"Point"}
}