{
  "type": "Feature",
  "properties": {
    "iso:country":"DE",
    "sg:address":"Osterstr. 4",
    "sg:city":"Kaiserslautern",
    "sg:phone":"+49 631/92178",
    "sg:postcode":"67655",
    "sg:province":"Rheinland-Pfalz",
    "wof:name":"Kehrer Spielautomaten Gmbh",
    "wof:placetype":"venue"
},
  "geometry": {"coordinates":[7.770689,49.443783],"type":"Point"}
}