{
  "type": "Feature",
  "properties": {
    "iso:country":"DE",
    "sg:address":"Bahnstr. 110",
    "sg:city":"Langen",
    "sg:postcode":"63225",
    "sg:province":"Hessen",
    "wof:name":"Wildhardt Lederwaren Ursula Schulz",
    "wof:placetype":"venue"
},
  "geometry": {"coordinates":[8.6600580215,49.9913482666],"type":"Point"}
}