{
  "type": "Feature",
  "properties": {
    "iso:country":"DE",
    "sg:address":"Kaiserplatz 1",
    "sg:city":"Bad Reichenhall",
    "sg:phone":"+49 8651/8360",
    "sg:postcode":"83435",
    "sg:province":"Bayern",
    "wof:name":"M\u00fcller",
    "wof:placetype":"venue"
},
  "geometry": {"coordinates":[12.878693,47.724644],"type":"Point"}
}