{
  "type": "Feature",
  "properties": {
    "iso:country":"DE",
    "sg:address":"Theresienplatz 32",
    "sg:city":"Straubing",
    "sg:phone":"+49 9421/81631",
    "sg:postcode":"94315",
    "sg:province":"Bayern",
    "wof:name":"Christine Troll",
    "wof:placetype":"venue"
},
  "geometry": {"coordinates":[12.567211,48.881428],"type":"Point"}
}