{
  "type": "Feature",
  "properties": {
    "iso:country":"DE",
    "sg:address":"Flach-Fengler-Str. 65",
    "sg:city":"Wesseling",
    "sg:phone":"+49 2236/49131",
    "sg:postcode":"50389",
    "sg:province":"Nordrhein-Westfalen",
    "wof:name":"Kemper Gmbh",
    "wof:placetype":"venue"
},
  "geometry": {"coordinates":[6.978338,50.822315],"type":"Point"}
}