{
  "type": "Feature",
  "properties": {
    "iso:country":"DE",
    "sg:address":"Hauptstr.",
    "sg:city":"Dahlem",
    "sg:phone":"+49 5851/9400",
    "sg:postcode":"21368",
    "sg:province":"Niedersachsen",
    "wof:name":"Karl-heinz Kruse Bauunternehmen Gmbh & Co. Kg",
    "wof:placetype":"venue"
},
  "geometry": {"coordinates":[10.744306,53.204037],"type":"Point"}
}