{
  "type": "Feature",
  "properties": {
    "iso:country":"DE",
    "sg:address":"Antoniusstr. 8",
    "sg:city":"Bochum",
    "sg:phone":"+49 234/15198",
    "sg:postcode":"44793",
    "sg:province":"Nordrhein-Westfalen",
    "wof:name":"Katholisches Pfarramt St. Antonius",
    "wof:placetype":"venue"
},
  "geometry": {"coordinates":[7.2069830894,51.4764442444],"type":"Point"}
}