{
  "type": "Feature",
  "properties": {
    "iso:country":"DE",
    "sg:address":"Kirchberg 3",
    "sg:city":"Hohenwart",
    "sg:phone":"+49 8443/1663",
    "sg:postcode":"86558",
    "sg:province":"Bayern",
    "wof:name":"Reis Metallbau Gmbh",
    "wof:placetype":"venue"
},
  "geometry": {"coordinates":[11.380188,48.593555],"type":"Point"}
}