{
  "type": "Feature",
  "properties": {
    "iso:country":"DE",
    "sg:address":"Augsburger Str. 118",
    "sg:city":"Geisenfeld",
    "sg:phone":"+49 8452/2613",
    "sg:postcode":"85290",
    "sg:province":"Bayern",
    "wof:name":"Kieswerk Lachermeier Gmbh",
    "wof:placetype":"venue"
},
  "geometry": {"coordinates":[11.6070070267,48.6837348938],"type":"Point"}
}