{
  "type": "Feature",
  "properties": {
    "iso:country":"DE",
    "sg:address":"An den Folgen 16",
    "sg:city":"Liegau-Augustusbad",
    "sg:phone":"+49 3528/447138",
    "sg:postcode":"01465",
    "sg:province":"Sachsen",
    "wof:name":"Heinz Hengstmann",
    "wof:placetype":"venue"
},
  "geometry": {"coordinates":[13.871951,51.129864],"type":"Point"}
}