{
  "type": "Feature",
  "properties": {
    "iso:country":"DE",
    "sg:address":"Talstr. 58",
    "sg:city":"Stuttgart",
    "sg:phone":"+49 711/483534",
    "sg:postcode":"70188",
    "sg:province":"Baden-W\u00fcrttemberg",
    "wof:name":"Willi Schickardt",
    "wof:placetype":"venue"
},
  "geometry": {"coordinates":[9.214136,48.784882],"type":"Point"}
}