{
  "type": "Feature",
  "properties": {
    "iso:country":"DE",
    "sg:address":"K\u00f6nigstr. 24",
    "sg:city":"Brilon",
    "sg:phone":"+49 2961/1819",
    "sg:postcode":"59929",
    "sg:province":"Nordrhein-Westfalen",
    "wof:name":"Weyers Druck Gmbh",
    "wof:placetype":"venue"
},
  "geometry": {"coordinates":[8.571291,51.395199],"type":"Point"}
}