{
  "type": "Feature",
  "properties": {
    "iso:country":"DE",
    "sg:address":"Hansering 39",
    "sg:city":"L\u00fcbeck",
    "sg:phone":"+49 451/82979",
    "sg:postcode":"23558",
    "sg:province":"Schleswig-Holstein",
    "wof:name":"Blumenk\u00f6rbchen Heidegard Wind",
    "wof:placetype":"venue"
},
  "geometry": {"coordinates":[10.663708,53.857937],"type":"Point"}
}