{
  "type": "Feature",
  "properties": {
    "iso:country":"DE",
    "sg:address":"Frankfurter Str. 146",
    "sg:city":"Fulda",
    "sg:phone":"+49 661/46755",
    "sg:postcode":"36043",
    "sg:province":"Hessen",
    "wof:name":"B. Kr\u00f6nung",
    "wof:placetype":"venue"
},
  "geometry": {"coordinates":[9.6780757904,50.5281028748],"type":"Point"}
}