{
  "type": "Feature",
  "properties": {
    "iso:country":"DE",
    "sg:address":"Aloys-Schulte-Str. 13-14",
    "sg:city":"Bonn",
    "sg:postcode":"53129",
    "sg:province":"Nordrhein-Westfalen",
    "wof:name":"D & V Netconsult Ohg",
    "wof:placetype":"venue"
},
  "geometry": {"coordinates":[7.108699,50.719627],"type":"Point"}
}