{
  "type": "Feature",
  "properties": {
    "iso:country":"DE",
    "sg:address":"Am Alten Friesoyther Kanal 7",
    "sg:city":"Friesoythe",
    "sg:phone":"+49 4497/1413",
    "sg:postcode":"26169",
    "sg:province":"Niedersachsen",
    "wof:name":"Hermann B\u00f6ckermann",
    "wof:placetype":"venue"
},
  "geometry": {"coordinates":[7.800361,53.062225],"type":"Point"}
}