{
  "type": "Feature",
  "properties": {
    "iso:country":"DE",
    "sg:address":"Adrianistr. 4",
    "sg:city":"Bochum",
    "sg:phone":"+49 234/230814",
    "sg:postcode":"44894",
    "sg:province":"Nordrhein-Westfalen",
    "wof:name":"Gerd Mange",
    "wof:placetype":"venue"
},
  "geometry": {"coordinates":[7.3040070534,51.4908485413],"type":"Point"}
}