{
  "type": "Feature",
  "properties": {
    "iso:country":"DE",
    "sg:address":"Vogelsbergstr. 13",
    "sg:city":"Glauburg",
    "sg:phone":"+49 6041/8617",
    "sg:postcode":"63695",
    "sg:province":"Hessen",
    "wof:name":"Pizzaleo",
    "wof:placetype":"venue"
},
  "geometry": {"coordinates":[9.0174598694,50.3255767822],"type":"Point"}
}