{
  "type": "Feature",
  "properties": {
    "iso:country":"DE",
    "sg:address":"Bl\u00fccherstr. 60",
    "sg:city":"Augsburg",
    "sg:phone":"+49 821/717272",
    "sg:postcode":"86165",
    "sg:province":"Bayern",
    "wof:name":"Landb\u00e4ckerei Ihle Gmbh & Co. Kg",
    "wof:placetype":"venue"
},
  "geometry": {"coordinates":[10.923594,48.377785],"type":"Point"}
}