{
  "type": "Feature",
  "properties": {
    "iso:country":"DE",
    "sg:address":"Hauptstr. 36",
    "sg:city":"Kellinghusen",
    "sg:phone":"+49 4822/2093",
    "sg:postcode":"25548",
    "sg:province":"Schleswig-Holstein",
    "wof:name":"Red. Norddeutsche Rundschau",
    "wof:placetype":"venue"
},
  "geometry": {"coordinates":[9.7221727371,53.9486732483],"type":"Point"}
}