{
  "type": "Feature",
  "properties": {
    "iso:country":"DE",
    "sg:address":"Ascherode",
    "sg:city":"Schimberg",
    "sg:postcode":"37308",
    "sg:province":"Th\u00fcringen",
    "wof:name":"W. Koch",
    "wof:placetype":"venue"
},
  "geometry": {"coordinates":[10.1924,51.299461],"type":"Point"}
}