{
  "type": "Feature",
  "properties": {
    "iso:country":"DE",
    "sg:address":"Erftstr. 7",
    "sg:city":"K\u00f6ln",
    "sg:phone":"+49 2234/709511",
    "sg:postcode":"50859",
    "sg:province":"Nordrhein-Westfalen",
    "wof:name":"Birgit Henze-ficht Heilpraktikerin",
    "wof:placetype":"venue"
},
  "geometry": {"coordinates":[6.8194627762,50.9440803528],"type":"Point"}
}