{
  "type": "Feature",
  "properties": {
    "iso:country":"DE",
    "sg:address":"Bonifatiusstr. 2",
    "sg:city":"Marl",
    "sg:phone":"+49 2365/18182",
    "sg:postcode":"45768",
    "sg:province":"Nordrhein-Westfalen",
    "wof:name":"N. Yigiter",
    "wof:placetype":"venue"
},
  "geometry": {"coordinates":[7.0859298706,51.6565856934],"type":"Point"}
}