{
  "type": "Feature",
  "properties": {
    "iso:country":"DE",
    "sg:address":"Schallenstr. 12",
    "sg:city":"Freiburg",
    "sg:phone":"+49 4779/442",
    "sg:postcode":"21729",
    "sg:province":"Niedersachsen",
    "wof:name":"Helmut Hatecke Gmbh",
    "wof:placetype":"venue"
},
  "geometry": {"coordinates":[9.292451,53.826637],"type":"Point"}
}