{
  "type": "Feature",
  "properties": {
    "iso:country":"DE",
    "sg:address":"Blumlage 64",
    "sg:city":"Celle",
    "sg:phone":"+49 5141/907079",
    "sg:postcode":"29221",
    "sg:province":"Niedersachsen",
    "wof:name":"Elses Game-shop",
    "wof:placetype":"venue"
},
  "geometry": {"coordinates":[10.0944690704,52.6171302795],"type":"Point"}
}