{
  "type": "Feature",
  "properties": {
    "iso:country":"DE",
    "sg:address":"Eppendorfer Landstr. 77",
    "sg:city":"Hamburg",
    "sg:phone":"+49 40/471080",
    "sg:postcode":"20249",
    "sg:province":"Hamburg",
    "wof:name":"Karstadt Warenhaus Ag",
    "wof:placetype":"venue"
},
  "geometry": {"coordinates":[9.986923,53.590912],"type":"Point"}
}