{
  "type": "Feature",
  "properties": {
    "iso:country":"DE",
    "sg:address":"Beethovenstr. 1",
    "sg:city":"Klosterlechfeld",
    "sg:phone":"+49 8232/2360",
    "sg:postcode":"86836",
    "sg:province":"Bayern",
    "wof:name":"Heinz Haberland Entrostungen",
    "wof:placetype":"venue"
},
  "geometry": {"coordinates":[10.828718,48.153],"type":"Point"}
}