{
  "type": "Feature",
  "properties": {
    "iso:country":"DE",
    "sg:address":"Haselnu\u00dfweg 29",
    "sg:city":"Delbr\u00fcck",
    "sg:phone":"+49 5250/6362",
    "sg:postcode":"33129",
    "sg:province":"Nordrhein-Westfalen",
    "wof:name":"J. Breinhorst",
    "wof:placetype":"venue"
},
  "geometry": {"coordinates":[8.5193481445,51.7440223694],"type":"Point"}
}