{
  "type": "Feature",
  "properties": {
    "iso:country":"DE",
    "sg:address":"Herforder Str. 128",
    "sg:city":"Bielefeld",
    "sg:phone":"+49 521/323082",
    "sg:postcode":"33609",
    "sg:province":"Nordrhein-Westfalen",
    "wof:name":"Neue Baugesellschaft Mbh",
    "wof:placetype":"venue"
},
  "geometry": {"coordinates":[8.5450878143,52.0335884094],"type":"Point"}
}