{
  "type": "Feature",
  "properties": {
    "iso:country":"DE",
    "sg:address":"Untere Rehwiese 2",
    "sg:city":"Prosselsheim",
    "sg:phone":"+49 9386/316",
    "sg:postcode":"97279",
    "sg:province":"Bayern",
    "wof:name":"Hubert Brand",
    "wof:placetype":"venue"
},
  "geometry": {"coordinates":[10.1241817474,49.8761558533],"type":"Point"}
}