{
  "type": "Feature",
  "properties": {
    "iso:country":"DE",
    "sg:address":"Bregenzer Str. 65a",
    "sg:city":"Lindau",
    "sg:phone":"+49 8382/5137",
    "sg:postcode":"88131",
    "sg:province":"Bayern",
    "wof:name":"Wagenknecht & Sohn",
    "wof:placetype":"venue"
},
  "geometry": {"coordinates":[9.663177,47.572323],"type":"Point"}
}