{
  "type": "Feature",
  "properties": {
    "iso:country":"DE",
    "sg:address":"Rheinstr. 10",
    "sg:city":"Dettenheim",
    "sg:phone":"+49 7255/9393",
    "sg:postcode":"76706",
    "sg:province":"Baden-W\u00fcrttemberg",
    "wof:name":"G. Und R. Heuser",
    "wof:placetype":"venue"
},
  "geometry": {"coordinates":[8.422501564,49.1838150024],"type":"Point"}
}