{
  "type": "Feature",
  "properties": {
    "iso:country":"DE",
    "sg:address":"M\u00fchlenstr. 1",
    "sg:city":"Dahmen",
    "sg:phone":"+49 39933/70589",
    "sg:postcode":"17166",
    "sg:province":"Mecklenburg-Vorpommern",
    "wof:name":"Eckhard Pohl Bauunternehmen Und",
    "wof:placetype":"venue"
},
  "geometry": {"coordinates":[12.543004,53.674297],"type":"Point"}
}