{
  "type": "Feature",
  "properties": {
    "iso:country":"DE",
    "sg:address":"Jahnplatz 11",
    "sg:city":"Frankenthal",
    "sg:phone":"+49 6233/349666",
    "sg:postcode":"67227",
    "sg:province":"Rheinland-Pfalz",
    "wof:name":"Sabine Bl\u00fcmel Ergotherapiepraxis",
    "wof:placetype":"venue"
},
  "geometry": {"coordinates":[8.329279,49.513309],"type":"Point"}
}