{
  "type": "Feature",
  "properties": {
    "iso:country":"DE",
    "sg:address":"Fabrikgel\u00e4nde 17",
    "sg:city":"Fraureuth",
    "sg:phone":"+49 3761/3295",
    "sg:postcode":"08427",
    "sg:province":"Sachsen",
    "wof:name":"Sanit\u00e4tshaus Techn. Rehabilitation",
    "wof:placetype":"venue"
},
  "geometry": {"coordinates":[12.355426,50.704762],"type":"Point"}
}