{
  "type": "Feature",
  "properties": {
    "iso:country":"DE",
    "sg:address":"Kirchstr. 15",
    "sg:city":"Borkum",
    "sg:phone":"+49 4922/2721",
    "sg:postcode":"26757",
    "sg:province":"Niedersachsen",
    "wof:name":"Pension Schulte",
    "wof:placetype":"venue"
},
  "geometry": {"coordinates":[6.6663918495,53.588558197],"type":"Point"}
}