{
  "type": "Feature",
  "properties": {
    "iso:country":"DE",
    "sg:address":"Beim Andreasbrunnen 8",
    "sg:city":"Hamburg",
    "sg:phone":"+49 40/479213",
    "sg:postcode":"20249",
    "sg:province":"Hamburg",
    "wof:name":"Architektur Und Kultur Lingnau Dickhaus",
    "wof:placetype":"venue"
},
  "geometry": {"coordinates":[9.985974,53.586662],"type":"Point"}
}