{
  "type": "Feature",
  "properties": {
    "iso:country":"DE",
    "sg:address":"Halberst\u00e4dter Chaussee 64",
    "sg:city":"Magdeburg",
    "sg:postcode":"39116",
    "sg:province":"Sachsen-Anhalt",
    "wof:name":"Atlas Baumaschaschinen Vertrieb Und Service Gmbh",
    "wof:placetype":"venue"
},
  "geometry": {"coordinates":[11.575088,52.098015],"type":"Point"}
}