{
  "type": "Feature",
  "properties": {
    "iso:country":"DE",
    "sg:address":"Glockenlandstr. 11",
    "sg:city":"Heinsberg",
    "sg:phone":"+49 2452/61725",
    "sg:postcode":"52525",
    "sg:province":"Nordrhein-Westfalen",
    "wof:name":"Josef Laven",
    "wof:placetype":"venue"
},
  "geometry": {"coordinates":[6.145269,51.038151],"type":"Point"}
}