{
  "type": "Feature",
  "properties": {
    "iso:country":"DE",
    "sg:address":"Am Bahnhof 72",
    "sg:city":"Mellinghausen",
    "sg:phone":"+49 4272/94133",
    "sg:postcode":"27249",
    "sg:province":"Niedersachsen",
    "wof:name":"Raiffeisen- Warengenossenschaft",
    "wof:placetype":"venue"
},
  "geometry": {"coordinates":[8.892388,52.698513],"type":"Point"}
}