{
  "type": "Feature",
  "properties": {
    "iso:country":"DE",
    "sg:address":"Lindenstr. 8",
    "sg:city":"Itzehoe",
    "sg:phone":"+49 4821/62022",
    "sg:postcode":"25524",
    "sg:province":"Schleswig-Holstein",
    "wof:name":"Horst Kunert Steuerberater",
    "wof:placetype":"venue"
},
  "geometry": {"coordinates":[9.5118923187,53.9280929565],"type":"Point"}
}