{
  "type": "Feature",
  "properties": {
    "iso:country":"DE",
    "sg:address":"Schwalbacher Str. 54 d",
    "sg:city":"Lorch",
    "sg:phone":"+49 6726/304",
    "sg:postcode":"65391",
    "sg:province":"Rheinland-Pfalz",
    "wof:name":"Bauuntern. Wittemann Gmbh",
    "wof:placetype":"venue"
},
  "geometry": {"coordinates":[7.8135690689,50.0518226624],"type":"Point"}
}