{
  "type": "Feature",
  "properties": {
    "iso:country":"DE",
    "sg:address":"Naheweinstr. 168",
    "sg:city":"Langenlonsheim",
    "sg:phone":"+49 6704/562",
    "sg:postcode":"55450",
    "sg:province":"Rheinland-Pfalz",
    "wof:name":"Lantzsch",
    "wof:placetype":"venue"
},
  "geometry": {"coordinates":[7.898329,49.89922],"type":"Point"}
}