{
  "type": "Feature",
  "properties": {
    "iso:country":"DE",
    "sg:address":"Wilckensstr 3",
    "sg:city":"Heidelberg",
    "sg:phone":"+49 6221/47670",
    "sg:postcode":"69120",
    "sg:province":"Baden-W\u00fcrttemberg",
    "wof:name":"Ifeu-institut F\u00fcr Energie- Und Umweltforschung Heidelberg Gmbh",
    "wof:placetype":"venue"
},
  "geometry": {"coordinates":[8.680206,49.414917],"type":"Point"}
}