{
  "type": "Feature",
  "properties": {
    "iso:country":"DE",
    "sg:address":"Stubbenhuk 10",
    "sg:city":"Hamburg",
    "sg:phone":"+49 40/3808170",
    "sg:postcode":"20459",
    "sg:province":"Hamburg",
    "wof:name":"Ecs Eurocargo Services Gmbh",
    "wof:placetype":"venue"
},
  "geometry": {"coordinates":[9.9808168411,53.5456542969],"type":"Point"}
}