{
  "type": "Feature",
  "properties": {
    "iso:country":"DE",
    "sg:address":"Dorfstr. 69",
    "sg:city":"Ackendorf",
    "sg:phone":"+49 39202/60437",
    "sg:postcode":"39343",
    "sg:province":"Sachsen-Anhalt",
    "wof:name":"Gastst\u00e4tte C. Plate",
    "wof:placetype":"venue"
},
  "geometry": {"coordinates":[11.4439401627,52.223400116],"type":"Point"}
}