{
  "type": "Feature",
  "properties": {
    "iso:country":"DE",
    "sg:address":"Sickingenstr. 58",
    "sg:city":"Berlin",
    "sg:phone":"+49 30/3460000",
    "sg:postcode":"10553",
    "sg:province":"Berlin",
    "wof:name":"God Guaranteed Overnight Delivery Gmbh",
    "wof:placetype":"venue"
},
  "geometry": {"coordinates":[13.317343,52.530766],"type":"Point"}
}