{
  "type": "Feature",
  "properties": {
    "iso:country":"DE",
    "sg:address":"Dachauer Str. 61",
    "sg:city":"Olching",
    "sg:phone":"+49 8142/12954",
    "sg:postcode":"82140",
    "sg:province":"Bayern",
    "wof:name":"J. Jexl",
    "wof:placetype":"venue"
},
  "geometry": {"coordinates":[11.3394975662,48.2246055603],"type":"Point"}
}