{
  "type": "Feature",
  "properties": {
    "iso:country":"DE",
    "sg:address":"Amberger Str. 37",
    "sg:city":"Neumarkt",
    "sg:phone":"+49 9181/42114",
    "sg:postcode":"92318",
    "sg:province":"Bayern",
    "wof:name":"H. Zuckschwert",
    "wof:placetype":"venue"
},
  "geometry": {"coordinates":[11.467903,49.286774],"type":"Point"}
}