{
  "type": "Feature",
  "properties": {
    "iso:country":"DE",
    "sg:address":"Halmhuberstr. 2",
    "sg:city":"Mannheim",
    "sg:phone":"+49 621/804300",
    "sg:postcode":"68219",
    "sg:province":"Baden-W\u00fcrttemberg",
    "wof:name":"Merk Reisen Gmbh",
    "wof:placetype":"venue"
},
  "geometry": {"coordinates":[8.5305652618,49.4292411804],"type":"Point"}
}