{
  "type": "Feature",
  "properties": {
    "iso:country":"DE",
    "sg:address":"Maschstr 5",
    "sg:city":"Wunstorf",
    "sg:phone":"+49 5031/949560",
    "sg:postcode":"31515",
    "sg:province":"Niedersachsen",
    "wof:name":"Hsg-hydraulik-service-gmbh",
    "wof:placetype":"venue"
},
  "geometry": {"coordinates":[9.4579219818,52.435962677],"type":"Point"}
}