{
  "type": "Feature",
  "properties": {
    "iso:country":"DE",
    "sg:address":"Vischerstr. 14",
    "sg:city":"T\u00fcbingen",
    "sg:phone":"+49 7071/33265",
    "sg:postcode":"72072",
    "sg:province":"Baden-W\u00fcrttemberg",
    "wof:name":"Dieter Kasporwicz Rechtsanwalt",
    "wof:placetype":"venue"
},
  "geometry": {"coordinates":[9.0582914352,48.5105476379],"type":"Point"}
}