{
  "type": "Feature",
  "properties": {
    "iso:country":"DE",
    "sg:address":"Raiffeisenplatz 3",
    "sg:city":"Meldorf",
    "sg:phone":"+49 4832/555560",
    "sg:postcode":"25704",
    "sg:province":"Schleswig-Holstein",
    "wof:name":"Eurospar",
    "wof:placetype":"venue"
},
  "geometry": {"coordinates":[9.0792980194,54.0897064209],"type":"Point"}
}