{
  "type": "Feature",
  "properties": {
    "iso:country":"DE",
    "sg:address":"Deichstr. 23",
    "sg:city":"Hamburg",
    "sg:phone":"+49 40/364208",
    "sg:postcode":"20459",
    "sg:province":"Hamburg",
    "wof:name":"Restaurant Deichgraf",
    "wof:placetype":"venue"
},
  "geometry": {"coordinates":[9.9874677658,53.5460853577],"type":"Point"}
}