{
  "type": "Feature",
  "properties": {
    "iso:country":"DE",
    "sg:address":"Kranichweg 27",
    "sg:city":"Heidelberg",
    "sg:phone":"+49 6221/775708",
    "sg:postcode":"69123",
    "sg:province":"Baden-W\u00fcrttemberg",
    "wof:name":"Franz Jahl",
    "wof:placetype":"venue"
},
  "geometry": {"coordinates":[8.642619133,49.3976364136],"type":"Point"}
}