{
  "type": "Feature",
  "properties": {
    "iso:country":"DE",
    "sg:address":"Maximilianstr. 100",
    "sg:city":"Speyer",
    "sg:postcode":"67346",
    "sg:province":"Rheinland-Pfalz",
    "wof:name":"Wes Wirtschaftsf\u00f6rderungs- Und Entwicklungsges.speyer Mbh",
    "wof:placetype":"venue"
},
  "geometry": {"coordinates":[8.440543,49.317394],"type":"Point"}
}