{
  "type": "Feature",
  "properties": {
    "iso:country":"DE",
    "sg:address":"Kranichstr. 9a",
    "sg:city":"Neustrelitz",
    "sg:phone":"+49 3981/443044",
    "sg:postcode":"17235",
    "sg:province":"Mecklenburg-Vorpommern",
    "wof:name":"Anika-schuhhandels Gmbh",
    "wof:placetype":"venue"
},
  "geometry": {"coordinates":[13.0699472427,53.3387985229],"type":"Point"}
}