{
  "type": "Feature",
  "properties": {
    "iso:country":"DE",
    "sg:address":"Sechzigstr. 13a",
    "sg:city":"K\u00f6ln",
    "sg:phone":"+49 221/7391027",
    "sg:postcode":"50733",
    "sg:province":"Nordrhein-Westfalen",
    "wof:name":"Remis",
    "wof:placetype":"venue"
},
  "geometry": {"coordinates":[6.9489951134,50.9598274231],"type":"Point"}
}