{
  "type": "Feature",
  "properties": {
    "iso:country":"DE",
    "sg:address":"Trivastr. 19",
    "sg:city":"M\u00fcnchen",
    "sg:phone":"+49 89/5420880",
    "sg:postcode":"80637",
    "sg:province":"Bayern",
    "wof:name":"F. G. Herrmann Heilpraktiker",
    "wof:placetype":"venue"
},
  "geometry": {"coordinates":[11.5411500931,48.1612930298],"type":"Point"}
}