{
  "type": "Feature",
  "properties": {
    "iso:country":"DE",
    "sg:address":"Gro\u00dfe-Leege-Str. 41",
    "sg:city":"Berlin",
    "sg:phone":"+49 30/9705272",
    "sg:postcode":"13055",
    "sg:province":"Berlin",
    "wof:name":"Fahrschule Michael R\u00f6per",
    "wof:placetype":"venue"
},
  "geometry": {"coordinates":[13.491268158,52.5399284363],"type":"Point"}
}