{
  "type": "Feature",
  "properties": {
    "iso:country":"DE",
    "sg:address":"Albert-Schweitzer-Strasse 1",
    "sg:city":"Elsdorf",
    "sg:phone":"+49 4901/77",
    "sg:postcode":"50189",
    "sg:province":"Nordrhein-Westfalen",
    "wof:name":"Fachinformatiker",
    "wof:placetype":"venue"
},
  "geometry": {"coordinates":[6.552795,50.936108],"type":"Point"}
}