{
  "type": "Feature",
  "properties": {
    "iso:country":"DE",
    "sg:address":"Martin-Huber-Str. 18",
    "sg:city":"Dachau",
    "sg:phone":"+49 8131/86896",
    "sg:postcode":"85221",
    "sg:province":"Bayern",
    "wof:name":"M. Scheiblhuber",
    "wof:placetype":"venue"
},
  "geometry": {"coordinates":[11.4410238266,48.2586936951],"type":"Point"}
}