{
  "type": "Feature",
  "properties": {
    "iso:country":"DE",
    "sg:address":"Sulzbacher Str. 27/31",
    "sg:city":"N\u00fcrnberg",
    "sg:postcode":"90489",
    "sg:province":"Bayern",
    "wof:name":"Noris Insurance Service Gmbh & Co. Versicherungs- Und",
    "wof:placetype":"venue"
},
  "geometry": {"coordinates":[11.0927906036,49.4580879211],"type":"Point"}
}