{
  "type": "Feature",
  "properties": {
    "iso:country":"DE",
    "sg:address":"Am Kratt 12",
    "sg:city":"Ahrensburg",
    "sg:postcode":"22926",
    "sg:province":"Schleswig-Holstein",
    "wof:name":"Fiv Fonds- Und Immobiliengesellschaft Mbh",
    "wof:placetype":"venue"
},
  "geometry": {"coordinates":[10.207901001,53.6390953064],"type":"Point"}
}