{
  "type": "Feature",
  "properties": {
    "iso:country":"DE",
    "sg:address":"Bergstr. 35",
    "sg:city":"Chamerau",
    "sg:phone":"+49 9944/428",
    "sg:postcode":"93466",
    "sg:province":"Bayern",
    "wof:name":"Pension Max Hirschberger",
    "wof:placetype":"venue"
},
  "geometry": {"coordinates":[12.7475233078,49.1936721802],"type":"Point"}
}