{
  "type": "Feature",
  "properties": {
    "iso:country":"DE",
    "sg:address":"In Venrath 44",
    "sg:city":"Erkelenz",
    "sg:phone":"+49 2431/5429",
    "sg:postcode":"41812",
    "sg:province":"Nordrhein-Westfalen",
    "wof:name":"H. Jansen",
    "wof:placetype":"venue"
},
  "geometry": {"coordinates":[6.36893,51.090729],"type":"Point"}
}