{
  "type": "Feature",
  "properties": {
    "iso:country":"DE",
    "sg:address":"Albert-Schweitzer-Str. 2",
    "sg:city":"Neustadt",
    "sg:phone":"+49 6321/6488",
    "sg:postcode":"67435",
    "sg:province":"Rheinland-Pfalz",
    "wof:name":"Gabriele Zimmermann Rechtsanw\u00e4ltin",
    "wof:placetype":"venue"
},
  "geometry": {"coordinates":[8.1770954132,49.3647384644],"type":"Point"}
}