{
  "type": "Feature",
  "properties": {
    "iso:country":"DE",
    "sg:address":"Martin-Luther-Str. 5",
    "sg:city":"Emmendingen",
    "sg:phone":"+49 7641/51942",
    "sg:postcode":"79312",
    "sg:province":"Baden-W\u00fcrttemberg",
    "wof:name":"Ulrich Weigel Rechtsanwalt",
    "wof:placetype":"venue"
},
  "geometry": {"coordinates":[7.8643379211,48.1054534912],"type":"Point"}
}