{
  "type": "Feature",
  "properties": {
    "iso:country":"DE",
    "sg:address":"Oberried 28",
    "sg:city":"Bischofsmais",
    "sg:phone":"+49 9920/1002",
    "sg:postcode":"94253",
    "sg:province":"Bayern",
    "wof:name":"Josef Achatz Eletroinstallation",
    "wof:placetype":"venue"
},
  "geometry": {"coordinates":[13.061793,48.900078],"type":"Point"}
}