{
  "type": "Feature",
  "properties": {
    "iso:country":"DE",
    "sg:address":"Trappenallee 62",
    "sg:city":"Hennigsdorf",
    "sg:phone":"+49 3302/810973",
    "sg:postcode":"16761",
    "sg:province":"Brandenburg",
    "wof:name":"Lars Waterstradt",
    "wof:placetype":"venue"
},
  "geometry": {"coordinates":[13.199873,52.619747],"type":"Point"}
}