{
  "type": "Feature",
  "properties": {
    "iso:country":"DE",
    "sg:address":"Elisabethenstr. 5",
    "sg:city":"Hochheim",
    "sg:phone":"+49 6146/5862",
    "sg:postcode":"65239",
    "sg:province":"Hessen",
    "wof:name":"E. M\u00fcller",
    "wof:placetype":"venue"
},
  "geometry": {"coordinates":[8.3534860611,50.0137481689],"type":"Point"}
}