{
  "type": "Feature",
  "properties": {
    "iso:country":"DE",
    "sg:address":"Klammstr. 12",
    "sg:city":"Garmisch-Partenkirchen",
    "sg:phone":"+49 8821/1606",
    "sg:postcode":"82467",
    "sg:province":"Bayern",
    "wof:name":"Kurtis Zugspitzbar",
    "wof:placetype":"venue"
},
  "geometry": {"coordinates":[11.089783,47.492332],"type":"Point"}
}