{
  "type": "Feature",
  "properties": {
    "iso:country":"DE",
    "sg:address":"Helstr. 60",
    "sg:city":"Bochum",
    "sg:phone":"+49 234/264348",
    "sg:postcode":"44894",
    "sg:province":"Nordrhein-Westfalen",
    "wof:name":"W. Klingelh\u00f6fer Ingenieur",
    "wof:placetype":"venue"
},
  "geometry": {"coordinates":[7.2818341255,51.4821014404],"type":"Point"}
}