{
  "type": "Feature",
  "properties": {
    "iso:country":"DE",
    "sg:address":"Am Bahndamm 11",
    "sg:city":"Nettetal",
    "sg:postcode":"41334",
    "sg:province":"Nordrhein-Westfalen",
    "wof:name":"Karl Und Willi Friedhoff Bauunternehmung Gmbh",
    "wof:placetype":"venue"
},
  "geometry": {"coordinates":[6.255061,51.287735],"type":"Point"}
}