{
  "type": "Feature",
  "properties": {
    "iso:country":"DE",
    "sg:address":"Killisfeldstr. 40 a",
    "sg:city":"Karlsruhe",
    "sg:phone":"+49 721/611064",
    "sg:postcode":"76227",
    "sg:province":"Baden-W\u00fcrttemberg",
    "wof:name":"Daebel Janssen Und Partner Ingenieur",
    "wof:placetype":"venue"
},
  "geometry": {"coordinates":[8.4525156021,48.9968070984],"type":"Point"}
}