{
  "type": "Feature",
  "properties": {
    "iso:country":"DE",
    "sg:address":"Hochmoorweg",
    "sg:city":"Heist",
    "sg:phone":"+49 4122/81291",
    "sg:postcode":"25492",
    "sg:province":"Schleswig-Holstein",
    "wof:name":"H. Scharrel",
    "wof:placetype":"venue"
},
  "geometry": {"coordinates":[9.671839,53.652199],"type":"Point"}
}