{
  "type": "Feature",
  "properties": {
    "iso:country":"DE",
    "sg:address":"Gewerbegebiet 6",
    "sg:city":"Brakel",
    "sg:phone":"+49 5648/488",
    "sg:postcode":"33034",
    "sg:province":"Nordrhein-Westfalen",
    "wof:name":"Johannes Weber Kg",
    "wof:placetype":"venue"
},
  "geometry": {"coordinates":[9.1348991394,51.6524429321],"type":"Point"}
}