{
  "type": "Feature",
  "properties": {
    "iso:country":"DE",
    "sg:address":"Beethovenstr. 5",
    "sg:city":"Waltrop",
    "sg:phone":"+49 2309/91144",
    "sg:postcode":"45731",
    "sg:province":"Nordrhein-Westfalen",
    "wof:name":"Teamwork Service Gabriel Gmbh",
    "wof:placetype":"venue"
},
  "geometry": {"coordinates":[7.3803339005,51.6274147034],"type":"Point"}
}