{
  "type": "Feature",
  "properties": {
    "iso:country":"DE",
    "sg:address":"Else-Kr\u00f6ner-Str. 1",
    "sg:city":"Bad Homburg",
    "sg:phone":"+49 6172/6080",
    "sg:postcode":"61352",
    "sg:province":"Hessen",
    "wof:name":"Fresenius Ag",
    "wof:placetype":"venue"
},
  "geometry": {"coordinates":[8.6230106354,50.2164840698],"type":"Point"}
}