{
  "type": "Feature",
  "properties": {
    "iso:country":"DE",
    "sg:address":"Im Sch\u00fcle 39",
    "sg:city":"Stuttgart",
    "sg:phone":"+49 711/2566053",
    "sg:postcode":"70192",
    "sg:province":"Baden-W\u00fcrttemberg",
    "wof:name":"Prof. Hans-d. U. Gisela Kaiser Architekten",
    "wof:placetype":"venue"
},
  "geometry": {"coordinates":[9.170859,48.792904],"type":"Point"}
}