{
  "type": "Feature",
  "properties": {
    "iso:country":"DE",
    "sg:address":"Riedling 8 a",
    "sg:city":"Oberschneiding",
    "sg:phone":"+49 9426/2225",
    "sg:postcode":"94363",
    "sg:province":"Bayern",
    "wof:name":"M. Hermann",
    "wof:placetype":"venue"
},
  "geometry": {"coordinates":[12.6052322388,48.7945556641],"type":"Point"}
}