{
  "type": "Feature",
  "properties": {
    "iso:country":"DE",
    "sg:address":"Paulistr. 1",
    "sg:city":"Bautzen",
    "sg:phone":"+49 3591/4830",
    "sg:postcode":"02625",
    "sg:province":"Sachsen",
    "wof:name":"Osts\u00e4chsische Baugesellschaft Mbh",
    "wof:placetype":"venue"
},
  "geometry": {"coordinates":[14.4411964417,51.1799964905],"type":"Point"}
}