{
  "type": "Feature",
  "properties": {
    "iso:country":"DE",
    "sg:address":"Rotdornweg 10",
    "sg:city":"Kassel",
    "sg:phone":"+49 561/9812803",
    "sg:postcode":"34125",
    "sg:province":"Hessen",
    "wof:name":"Giata Gmbh",
    "wof:placetype":"venue"
},
  "geometry": {"coordinates":[9.525702,51.333321],"type":"Point"}
}