{
  "type": "Feature",
  "properties": {
    "iso:country":"DE",
    "sg:address":"Maingaustr.13",
    "sg:city":"Obertshausen",
    "sg:phone":"+49 6104",
    "sg:postcode":"63179",
    "sg:province":"Hessen",
    "wof:name":"Mes\u00f3n Madrid",
    "wof:placetype":"venue"
},
  "geometry": {"coordinates":[8.859322,50.076157],"type":"Point"}
}