{
  "type": "Feature",
  "properties": {
    "iso:country":"DE",
    "sg:address":"Bielatalstr. 91-93",
    "sg:city":"K\u00f6nigstein",
    "sg:phone":"+49 4935/021650",
    "sg:postcode":"01824",
    "sg:province":"Sachsen",
    "wof:name":"Papierfabrik K\u00d6nigstein Gmbh",
    "wof:placetype":"venue"
},
  "geometry": {"coordinates":[14.0795536041,50.8889961243],"type":"Point"}
}