{
  "type": "Feature",
  "properties": {
    "iso:country":"DE",
    "sg:address":"Alte Dorfstr. 14",
    "sg:city":"Celle",
    "sg:phone":"+49 5141/84894",
    "sg:postcode":"29227",
    "sg:province":"Niedersachsen",
    "wof:name":"Allerkrug",
    "wof:placetype":"venue"
},
  "geometry": {"coordinates":[10.119635582,52.6050834656],"type":"Point"}
}