{
  "type": "Feature",
  "properties": {
    "iso:country":"DE",
    "sg:address":"Ratje 28",
    "sg:city":"Bergfeld",
    "sg:phone":"+49 5368/706",
    "sg:postcode":"38467",
    "sg:province":"Niedersachsen",
    "wof:name":"H. Litzenberg Immobilienmakler",
    "wof:placetype":"venue"
},
  "geometry": {"coordinates":[10.8405275345,52.5438537598],"type":"Point"}
}