{
  "type": "Feature",
  "properties": {
    "iso:country":"DE",
    "sg:address":"Festplatzstr. 3",
    "sg:city":"Ergolding",
    "sg:phone":"+49 871/975800",
    "sg:postcode":"84030",
    "sg:province":"Bayern",
    "wof:name":"Hotel-cafe Rosenhof",
    "wof:placetype":"venue"
},
  "geometry": {"coordinates":[12.1686840057,48.5627174377],"type":"Point"}
}