{
  "type": "Feature",
  "properties": {
    "iso:country":"DE",
    "sg:address":"Kapellenstr. 25",
    "sg:city":"Ahlen",
    "sg:phone":"+49 2382/8933",
    "sg:postcode":"59227",
    "sg:province":"Nordrhein-Westfalen",
    "wof:name":"Elisabeth-tombrock-haus",
    "wof:placetype":"venue"
},
  "geometry": {"coordinates":[7.878148,51.765553],"type":"Point"}
}