{
  "type": "Feature",
  "properties": {
    "iso:country":"DE",
    "sg:address":"Theaterplatz 14",
    "sg:city":"Erlangen",
    "sg:phone":"+49 9131/226000",
    "sg:postcode":"91054",
    "sg:province":"Bayern",
    "wof:name":"Appli Com Gmbh",
    "wof:placetype":"venue"
},
  "geometry": {"coordinates":[11.0057849884,49.6008338928],"type":"Point"}
}