{
  "type": "Feature",
  "properties": {
    "iso:country":"DE",
    "sg:address":"Graudenzer Str. 43",
    "sg:city":"Kehl",
    "sg:phone":"+49 7851/87050",
    "sg:postcode":"77694",
    "sg:province":"Baden-W\u00fcrttemberg",
    "wof:name":"Dold S\u00fcdwestdeutsche Sperrholzwerke Gmbh",
    "wof:placetype":"venue"
},
  "geometry": {"coordinates":[7.8227500916,48.5922203064],"type":"Point"}
}