{
  "type": "Feature",
  "properties": {
    "iso:country":"DE",
    "sg:address":"Steinweg 43",
    "sg:city":"Marburg",
    "sg:phone":"+49 6421/65741",
    "sg:postcode":"35037",
    "sg:province":"Hessen",
    "wof:name":"Das Kraml\u00e4dchen",
    "wof:placetype":"venue"
},
  "geometry": {"coordinates":[8.7690629959,50.8141860962],"type":"Point"}
}