{
  "type": "Feature",
  "properties": {
    "iso:country":"DE",
    "sg:address":"Hauptstr. 16",
    "sg:city":"Uichteritz",
    "sg:phone":"+49 3443/208232",
    "sg:postcode":"06667",
    "sg:province":"Sachsen-Anhalt",
    "wof:name":"J. Hahn",
    "wof:placetype":"venue"
},
  "geometry": {"coordinates":[11.906179,51.194984],"type":"Point"}
}