{
  "type": "Feature",
  "properties": {
    "iso:country":"DE",
    "sg:address":"Augsburger Greppe 1",
    "sg:city":"P\u00f6ttmes",
    "sg:postcode":"86554",
    "sg:province":"Bayern",
    "wof:name":"Walter Rupp Gmbh",
    "wof:placetype":"venue"
},
  "geometry": {"coordinates":[11.079632,48.578846],"type":"Point"}
}