{
  "type": "Feature",
  "properties": {
    "iso:country":"DE",
    "sg:address":"Berger Str. 12",
    "sg:city":"Homberg",
    "sg:phone":"+49 5681/2175",
    "sg:postcode":"34576",
    "sg:province":"Hessen",
    "wof:name":"Karl Bornkessel",
    "wof:placetype":"venue"
},
  "geometry": {"coordinates":[9.406095,51.03376],"type":"Point"}
}