{
  "type": "Feature",
  "properties": {
    "iso:country":"DE",
    "sg:address":"R\u00f6merbadstr. 23",
    "sg:city":"Jockgrim",
    "sg:phone":"+49 7271/51308",
    "sg:postcode":"76751",
    "sg:province":"Rheinland-Pfalz",
    "wof:name":"Josef Giglberger",
    "wof:placetype":"venue"
},
  "geometry": {"coordinates":[8.2829790115,49.0992698669],"type":"Point"}
}