{
  "type": "Feature",
  "properties": {
    "iso:country":"DE",
    "sg:address":"Schlo\u00dfstr. 5",
    "sg:city":"Schrobenhausen",
    "sg:phone":"+49 8252/7566",
    "sg:postcode":"86529",
    "sg:province":"Bayern",
    "wof:name":"Karlheinz Zimmermann Glas- Und Porzellanwaren",
    "wof:placetype":"venue"
},
  "geometry": {"coordinates":[11.2639369965,48.5626983643],"type":"Point"}
}