{
  "type": "Feature",
  "properties": {
    "iso:country":"DE",
    "sg:address":"Wilhelm-Heinrich-Str. 7",
    "sg:city":"Usingen",
    "sg:phone":"+49 6081/944550",
    "sg:postcode":"61250",
    "sg:province":"Hessen",
    "wof:name":"Immo-perfect Gmbh",
    "wof:placetype":"venue"
},
  "geometry": {"coordinates":[8.479522,50.349453],"type":"Point"}
}