{
  "type": "Feature",
  "properties": {
    "iso:country":"DE",
    "sg:address":"Schilfstr. 18",
    "sg:city":"Rastatt",
    "sg:phone":"+49 7222/69894",
    "sg:postcode":"76437",
    "sg:province":"Baden-W\u00fcrttemberg",
    "wof:name":"Rolf Gro\u00df",
    "wof:placetype":"venue"
},
  "geometry": {"coordinates":[8.1600751877,48.8600502014],"type":"Point"}
}