{
  "type": "Feature",
  "properties": {
    "iso:country":"DE",
    "sg:address":"Neustr. 18",
    "sg:city":"Mehring",
    "sg:phone":"+49 6502/5916",
    "sg:postcode":"54346",
    "sg:province":"Rheinland-Pfalz",
    "wof:name":"Hans Pfeifer-klein Weinanbau",
    "wof:placetype":"venue"
},
  "geometry": {"coordinates":[6.8276968002,49.7974319458],"type":"Point"}
}