{
  "type": "Feature",
  "properties": {
    "iso:country":"DE",
    "sg:address":"Am Bahnhof 10",
    "sg:city":"Wegberg",
    "sg:phone":"+49 2434/25948",
    "sg:postcode":"41844",
    "sg:province":"Nordrhein-Westfalen",
    "wof:name":"Toen Feyen",
    "wof:placetype":"venue"
},
  "geometry": {"coordinates":[6.283723,51.144753],"type":"Point"}
}