{
  "type": "Feature",
  "properties": {
    "iso:country":"DE",
    "sg:address":"Frank Wiesbacherstr. 8",
    "sg:city":"Ainring",
    "sg:phone":"+49 8654/50404",
    "sg:postcode":"83404",
    "sg:province":"Bayern",
    "wof:name":"Aral Ag Eschelberger Kg",
    "wof:placetype":"venue"
},
  "geometry": {"coordinates":[12.9576969147,47.8053283691],"type":"Point"}
}