{
  "type": "Feature",
  "properties": {
    "iso:country":"DE",
    "sg:address":"Obers\u00fclzer Str. 6 a",
    "sg:city":"Gr\u00fcnstadt",
    "sg:phone":"+49 6359/3472",
    "sg:postcode":"67269",
    "sg:province":"Rheinland-Pfalz",
    "wof:name":"Helmut Venter",
    "wof:placetype":"venue"
},
  "geometry": {"coordinates":[8.166435,49.562546],"type":"Point"}
}