{
  "type": "Feature",
  "properties": {
    "iso:country":"DE",
    "sg:address":"Felchenstr. 14",
    "sg:city":"Ehingen",
    "sg:phone":"+49 7391/72777",
    "sg:postcode":"89584",
    "sg:province":"Baden-W\u00fcrttemberg",
    "wof:name":"Jmb Automaten Und Gastronomiebetriebs Gmbh",
    "wof:placetype":"venue"
},
  "geometry": {"coordinates":[9.7403860092,48.2812957764],"type":"Point"}
}