{
  "type": "Feature",
  "properties": {
    "iso:country":"DE",
    "sg:address":"Osnabr\u00fccker Str. 107",
    "sg:city":"L\u00fcbbecke",
    "sg:phone":"+49 5741/298406",
    "sg:postcode":"32312",
    "sg:province":"Nordrhein-Westfalen",
    "wof:name":"Gourmet St\u00fcbchen",
    "wof:placetype":"venue"
},
  "geometry": {"coordinates":[8.5966300964,52.3023529053],"type":"Point"}
}