{
  "type": "Feature",
  "properties": {
    "iso:country":"DE",
    "sg:address":"Leopoldstr. 64",
    "sg:city":"M\u00fcnchen",
    "sg:phone":"+49 89/38889825",
    "sg:postcode":"80802",
    "sg:province":"Bayern",
    "wof:name":"E-plus Shop M\u00fcnchen 3",
    "wof:placetype":"venue"
},
  "geometry": {"coordinates":[11.5858774185,48.1596679688],"type":"Point"}
}