{
  "type": "Feature",
  "properties": {
    "iso:country":"DE",
    "sg:address":"Distelkoppel 3 A",
    "sg:city":"Hamburg",
    "sg:phone":"+49 40/595068",
    "sg:postcode":"22339",
    "sg:province":"Hamburg",
    "wof:name":"Klaus Wiskemann Rechtsanwalt",
    "wof:placetype":"venue"
},
  "geometry": {"coordinates":[10.0426139832,53.6368751526],"type":"Point"}
}