{
  "type": "Feature",
  "properties": {
    "iso:country":"DE",
    "sg:address":"Regensburger Str. 13",
    "sg:city":"Schrobenhausen",
    "sg:phone":"+49 8252/889177",
    "sg:postcode":"86529",
    "sg:province":"Bayern",
    "wof:name":"Florian Laquai",
    "wof:placetype":"venue"
},
  "geometry": {"coordinates":[11.263427,48.564854],"type":"Point"}
}