{
  "type": "Feature",
  "properties": {
    "iso:country":"DE",
    "sg:address":"Klingenburg 30",
    "sg:city":"Heinsen",
    "sg:phone":"+49 5535/685",
    "sg:postcode":"37649",
    "sg:province":"Niedersachsen",
    "wof:name":"Bridssun Gmbh & Co. Kg",
    "wof:placetype":"venue"
},
  "geometry": {"coordinates":[9.4314022064,51.8806915283],"type":"Point"}
}