{
  "type": "Feature",
  "properties": {
    "iso:country":"DE",
    "sg:address":"Mittelstr. 34",
    "sg:city":"Bamberg",
    "sg:phone":"+49 951/201618",
    "sg:postcode":"96052",
    "sg:province":"Bayern",
    "wof:name":"G\u00e4rtner Und H\u00e4ckermuseum",
    "wof:placetype":"venue"
},
  "geometry": {"coordinates":[10.89257,49.899513],"type":"Point"}
}