{
  "type": "Feature",
  "properties": {
    "iso:country":"DE",
    "sg:address":"Friedrich-Huth-Str. 2 a",
    "sg:city":"Harsefeld",
    "sg:phone":"+49 4164/6265",
    "sg:postcode":"21698",
    "sg:province":"Niedersachsen",
    "wof:name":"Ebke Spielothek Verwaltungs Gmbh",
    "wof:placetype":"venue"
},
  "geometry": {"coordinates":[9.5002470016,53.4522743225],"type":"Point"}
}