{
  "type": "Feature",
  "properties": {
    "iso:country":"DE",
    "sg:address":"Riedstr. 6",
    "sg:city":"Bad Salzschlirf",
    "sg:phone":"+49 6648/2325",
    "sg:postcode":"36364",
    "sg:province":"Hessen",
    "wof:name":"Haus Gies",
    "wof:placetype":"venue"
},
  "geometry": {"coordinates":[9.5081300735,50.622428894],"type":"Point"}
}