{
  "type": "Feature",
  "properties": {
    "iso:country":"DE",
    "sg:address":"Bergenkamp 5",
    "sg:city":"Unna",
    "sg:phone":"+49 2303/68235",
    "sg:postcode":"59425",
    "sg:province":"Nordrhein-Westfalen",
    "wof:name":"Hallenbad",
    "wof:placetype":"venue"
},
  "geometry": {"coordinates":[7.6971120834,51.545124054],"type":"Point"}
}