{
  "type": "Feature",
  "properties": {
    "iso:country":"DE",
    "sg:address":"Hessenring 50",
    "sg:city":"R\u00fcsselsheim",
    "sg:phone":"+49 6142/51101",
    "sg:postcode":"65428",
    "sg:province":"Hessen",
    "wof:name":"Aral Ag",
    "wof:placetype":"venue"
},
  "geometry": {"coordinates":[8.4481143951,49.9828872681],"type":"Point"}
}