{
  "type": "Feature",
  "properties": {
    "iso:country":"DE",
    "sg:address":"Sperlingstr. 11",
    "sg:city":"Falkensee",
    "sg:phone":"+49 3322/206041",
    "sg:postcode":"14612",
    "sg:province":"Brandenburg",
    "wof:name":"Harald Wiesner Rechtsanwalt",
    "wof:placetype":"venue"
},
  "geometry": {"coordinates":[13.0711250305,52.5516166687],"type":"Point"}
}