{
  "type": "Feature",
  "properties": {
    "iso:country":"DE",
    "sg:address":"Badener Ring 24",
    "sg:city":"Reutlingen",
    "sg:phone":"+49 7121/610961",
    "sg:postcode":"72768",
    "sg:province":"Baden-W\u00fcrttemberg",
    "wof:name":"I. Taschler",
    "wof:placetype":"venue"
},
  "geometry": {"coordinates":[9.2055168152,48.5290641785],"type":"Point"}
}