{
  "type": "Feature",
  "properties": {
    "iso:country":"DE",
    "sg:address":"Feuerhausstr. 10 a",
    "sg:city":"F\u00fcrstenfeldbruck",
    "sg:phone":"+49 8141/9647",
    "sg:postcode":"82256",
    "sg:province":"Bayern",
    "wof:name":"Brunetti Bautr\u00e4ger Gmbh",
    "wof:placetype":"venue"
},
  "geometry": {"coordinates":[11.2574930191,48.1809883118],"type":"Point"}
}