{
  "type": "Feature",
  "properties": {
    "iso:country":"DE",
    "sg:address":"K\u00f6lner Str. 3",
    "sg:city":"Gevelsberg",
    "sg:phone":"+49 2332/3835",
    "sg:postcode":"58285",
    "sg:province":"Nordrhein-Westfalen",
    "wof:name":"Hotel Zur Post",
    "wof:placetype":"venue"
},
  "geometry": {"coordinates":[7.3430438042,51.3197746277],"type":"Point"}
}