{
  "type": "Feature",
  "properties": {
    "iso:country":"DE",
    "sg:address":"Loreleiring 13",
    "sg:city":"Wiesbaden",
    "sg:phone":"+49 611/944820",
    "sg:postcode":"65197",
    "sg:province":"Hessen",
    "wof:name":"G\u00fcnter Ruppert Immobilienmakler",
    "wof:placetype":"venue"
},
  "geometry": {"coordinates":[8.2214212418,50.0762481689],"type":"Point"}
}