{
  "type": "Feature",
  "properties": {
    "iso:country":"DE",
    "sg:address":"Rudolfstr. 1",
    "sg:city":"Troisdorf",
    "sg:phone":"+49 2241/42855",
    "sg:postcode":"53842",
    "sg:province":"Nordrhein-Westfalen",
    "wof:name":"Willi Kl\u00f6fer",
    "wof:placetype":"venue"
},
  "geometry": {"coordinates":[7.1123600006,50.8298606873],"type":"Point"}
}