{
  "type": "Feature",
  "properties": {
    "iso:country":"DE",
    "sg:address":"Pettenkoferstr. 48",
    "sg:city":"M\u00fcnchen",
    "sg:phone":"+49 89/534167",
    "sg:postcode":"80336",
    "sg:province":"Bayern",
    "wof:name":"S\u00e4ngerwarte",
    "wof:placetype":"venue"
},
  "geometry": {"coordinates":[11.553650856,48.1352958679],"type":"Point"}
}