{
  "type": "Feature",
  "properties": {
    "iso:country":"DE",
    "sg:address":"Daimlerstr. 13 - 15",
    "sg:city":"Lotte",
    "sg:phone":"+49 4954/0496660",
    "sg:postcode":"49504",
    "sg:province":"Nordrhein-Westfalen",
    "wof:name":"Mkg Metall & Kunststoffverarbeitungs Gmbh",
    "wof:placetype":"venue"
},
  "geometry": {"coordinates":[7.9263510704,52.2793006897],"type":"Point"}
}