{
  "type": "Feature",
  "properties": {
    "iso:country":"DE",
    "sg:address":"Nahestr. 15",
    "sg:city":"R\u00fcdesheim",
    "sg:phone":"+49 671/40555",
    "sg:postcode":"55593",
    "sg:province":"Rheinland-Pfalz",
    "wof:name":"Welker & Emmerich",
    "wof:placetype":"venue"
},
  "geometry": {"coordinates":[7.8091201782,49.845375061],"type":"Point"}
}