{
  "type": "Feature",
  "properties": {
    "iso:country":"DE",
    "sg:address":"Scheffelstr. 18",
    "sg:city":"Frankfurt",
    "sg:phone":"+49 69/443486",
    "sg:postcode":"60318",
    "sg:province":"Hessen",
    "wof:name":"Tele-drive Softic Gmbh",
    "wof:placetype":"venue"
},
  "geometry": {"coordinates":[8.6884641647,50.1208572388],"type":"Point"}
}