{
  "type": "Feature",
  "properties": {
    "iso:country":"DE",
    "sg:address":"Genthiner Str. 6",
    "sg:city":"Bensdorf",
    "sg:postcode":"14789",
    "sg:province":"Brandenburg",
    "wof:name":"Arag Allgemeine Versicherungs- Ag",
    "wof:placetype":"venue"
},
  "geometry": {"coordinates":[12.3495254517,52.4116210938],"type":"Point"}
}