{
  "type": "Feature",
  "properties": {
    "iso:country":"DE",
    "sg:address":"Hauptstr. 34 b",
    "sg:city":"Barsb\u00fcttel",
    "sg:phone":"+49 40/6701883",
    "sg:postcode":"22885",
    "sg:province":"Schleswig-Holstein",
    "wof:name":"Dieter Maltzan",
    "wof:placetype":"venue"
},
  "geometry": {"coordinates":[10.160634,53.568554],"type":"Point"}
}