{
  "type": "Feature",
  "properties": {
    "iso:country":"DE",
    "sg:address":"Bahnstr. 85",
    "sg:city":"Langen",
    "sg:phone":"+49 6103/23021",
    "sg:postcode":"63225",
    "sg:province":"Hessen",
    "wof:name":"Mfo-drucklufttechnik Manfred U. Forster",
    "wof:placetype":"venue"
},
  "geometry": {"coordinates":[8.6639051437,49.9910163879],"type":"Point"}
}