{
  "type": "Feature",
  "properties": {
    "iso:country":"DE",
    "sg:address":"T\u00f6ngesstr. 19a",
    "sg:city":"Mainz",
    "sg:phone":"+49 6136/42985",
    "sg:postcode":"55129",
    "sg:province":"Rheinland-Pfalz",
    "wof:name":"Gerhard Herdt",
    "wof:placetype":"venue"
},
  "geometry": {"coordinates":[8.2475166321,49.9139022827],"type":"Point"}
}