{
  "type": "Feature",
  "properties": {
    "iso:country":"DE",
    "sg:address":"An der Dreik\u00f6nigskirche 10",
    "sg:city":"Dresden",
    "sg:phone":"+49 351/826440",
    "sg:postcode":"01097",
    "sg:province":"Sachsen",
    "wof:name":"Cms Hasche Rechtsanw\u00e4lte",
    "wof:placetype":"venue"
},
  "geometry": {"coordinates":[13.7430791855,51.0614204407],"type":"Point"}
}