{
  "type": "Feature",
  "properties": {
    "iso:country":"DE",
    "sg:address":"Kosberg 11",
    "sg:city":"Spangenberg",
    "sg:phone":"+49 5663/5540",
    "sg:postcode":"34286",
    "sg:province":"Hessen",
    "wof:name":"S. Elger",
    "wof:placetype":"venue"
},
  "geometry": {"coordinates":[9.646715,51.106361],"type":"Point"}
}