{
  "type": "Feature",
  "properties": {
    "iso:country":"DE",
    "sg:address":"Wolfratshauser Str. 54a",
    "sg:city":"Baierbrunn",
    "sg:phone":"+49 89/7938345",
    "sg:postcode":"82065",
    "sg:province":"Bayern",
    "wof:name":"F. R\u00f6hling Mech. Werkstatt",
    "wof:placetype":"venue"
},
  "geometry": {"coordinates":[11.486603,48.019215],"type":"Point"}
}