{
  "type": "Feature",
  "properties": {
    "iso:country":"DE",
    "sg:address":"Dommitzscher Str. 30 A",
    "sg:city":"Torgau",
    "sg:phone":"+49 3421/706770",
    "sg:postcode":"04860",
    "sg:province":"Sachsen",
    "wof:name":"Torga-immobilien Gmbh",
    "wof:placetype":"venue"
},
  "geometry": {"coordinates":[12.983295,51.562504],"type":"Point"}
}