{
  "type": "Feature",
  "properties": {
    "iso:country":"DE",
    "sg:address":"Emscherstr. 3",
    "sg:city":"Solingen",
    "sg:phone":"+49 212/72339",
    "sg:postcode":"42697",
    "sg:province":"Nordrhein-Westfalen",
    "wof:name":"Uschi Holzh\u00e4user Steuerberaterin",
    "wof:placetype":"venue"
},
  "geometry": {"coordinates":[6.9973778725,51.161655426],"type":"Point"}
}