{
  "type": "Feature",
  "properties": {
    "iso:country":"DE",
    "sg:address":"Klosterstr. 21",
    "sg:city":"Ibbenb\u00fcren",
    "sg:phone":"+49 5451/2111",
    "sg:postcode":"49477",
    "sg:province":"Nordrhein-Westfalen",
    "wof:name":"Karl Bosse Immobilienmakler",
    "wof:placetype":"venue"
},
  "geometry": {"coordinates":[7.7164320946,52.2728385925],"type":"Point"}
}