{
  "type": "Feature",
  "properties": {
    "iso:country":"DE",
    "sg:address":"Kapellenstr. 23",
    "sg:city":"Fichtenau",
    "sg:phone":"+49 7962/2928",
    "sg:postcode":"74579",
    "sg:province":"Baden-W\u00fcrttemberg",
    "wof:name":"E. Schultes",
    "wof:placetype":"venue"
},
  "geometry": {"coordinates":[10.231385,49.051353],"type":"Point"}
}