{
  "type": "Feature",
  "properties": {
    "iso:country":"DE",
    "sg:address":"Bauernstr. 6",
    "sg:city":"Jahrstedt",
    "sg:phone":"+49 39008/608",
    "sg:postcode":"38486",
    "sg:province":"Sachsen-Anhalt",
    "wof:name":"J\u00fcrgen Meyer-roschau",
    "wof:placetype":"venue"
},
  "geometry": {"coordinates":[10.9780111313,52.5607299805],"type":"Point"}
}