{
  "type": "Feature",
  "properties": {
    "iso:country":"DE",
    "sg:address":"Platanenring 144",
    "sg:city":"Bad Homburg",
    "sg:postcode":"61352",
    "sg:province":"Hessen",
    "wof:name":"Tharmac Gmbh",
    "wof:placetype":"venue"
},
  "geometry": {"coordinates":[8.680297,50.229023],"type":"Point"}
}