{
  "type": "Feature",
  "properties": {
    "iso:country":"DE",
    "sg:city":"Hof",
    "sg:phone":"+49 9281/8920",
    "sg:postcode":"95028",
    "sg:province":"Bayern",
    "wof:name":"Bayerische Hypotheken-und Wechsel-, Bank Ag",
    "wof:placetype":"venue"
},
  "geometry": {"coordinates":[11.918688,50.321609],"type":"Point"}
}