{
  "type": "Feature",
  "properties": {
    "iso:country":"DE",
    "sg:address":"Altenberger Gasse 29",
    "sg:city":"Bornheim",
    "sg:phone":"+49 2227/6702",
    "sg:postcode":"53332",
    "sg:province":"Nordrhein-Westfalen",
    "wof:name":"Heinz-peter Horst Ingenieur",
    "wof:placetype":"venue"
},
  "geometry": {"coordinates":[6.9273161888,50.7667655945],"type":"Point"}
}