{
  "type": "Feature",
  "properties": {
    "iso:country":"DE",
    "sg:address":"Sandberggasse 4",
    "sg:city":"\u00dcckeritz",
    "sg:phone":"+49 38375/862",
    "sg:postcode":"17459",
    "sg:province":"Mecklenburg-Vorpommern",
    "wof:name":"S. Bergmann",
    "wof:placetype":"venue"
},
  "geometry": {"coordinates":[14.0481901169,54.0136909485],"type":"Point"}
}