{
  "type": "Feature",
  "properties": {
    "iso:country":"DE",
    "sg:address":"Gotenstr. 10-12",
    "sg:city":"Hamburg",
    "sg:postcode":"20097",
    "sg:province":"Hamburg",
    "wof:name":"Wtb Investitionsg\u00fcter- Und Absatz-leasing",
    "wof:placetype":"venue"
},
  "geometry": {"coordinates":[10.023894,53.548996],"type":"Point"}
}