{
  "type": "Feature",
  "properties": {
    "iso:country":"DE",
    "sg:address":"Wilhelm-Heinrich-Str. 20",
    "sg:city":"Saarbr\u00fccken",
    "sg:phone":"+49 681/51551",
    "sg:postcode":"66117",
    "sg:province":"Saarland",
    "wof:name":"Kleine Tonhalle",
    "wof:placetype":"venue"
},
  "geometry": {"coordinates":[6.9906902313,49.2322425842],"type":"Point"}
}