{
  "type": "Feature",
  "properties": {
    "iso:country":"DE",
    "sg:address":"B\u00f6rchemstr. 3",
    "sg:city":"D\u00fcsseldorf",
    "sg:phone":"+49 211/716814",
    "sg:postcode":"40597",
    "sg:province":"Nordrhein-Westfalen",
    "wof:name":"Sanit\u00e4tshaus Inhoven Gmbh",
    "wof:placetype":"venue"
},
  "geometry": {"coordinates":[6.871261,51.163731],"type":"Point"}
}