{
  "type": "Feature",
  "properties": {
    "iso:country":"DE",
    "sg:address":"Welzbachstr. 33",
    "sg:city":"Appenheim",
    "sg:phone":"+49 6725/6502",
    "sg:postcode":"55437",
    "sg:province":"Rheinland-Pfalz",
    "wof:name":"Klaus Und Petra Welge",
    "wof:placetype":"venue"
},
  "geometry": {"coordinates":[8.033663,49.935032],"type":"Point"}
}