{
  "type": "Feature",
  "properties": {
    "iso:country":"DE",
    "sg:address":"Landstuhler Str. 8",
    "sg:city":"Ramstein-Miesenbach",
    "sg:phone":"+49 6371/50438",
    "sg:postcode":"66877",
    "sg:province":"Rheinland-Pfalz",
    "wof:name":"Pfarrb\u00fccherei Ramstein",
    "wof:placetype":"venue"
},
  "geometry": {"coordinates":[7.555656,49.446278],"type":"Point"}
}