{
  "type": "Feature",
  "properties": {
    "iso:country":"DE",
    "sg:address":"Postpassage",
    "sg:city":"Heilbronn",
    "sg:phone":"+49 7131/83737",
    "sg:postcode":"74072",
    "sg:province":"Baden-W\u00fcrttemberg",
    "wof:name":"Boutique Libre",
    "wof:placetype":"venue"
},
  "geometry": {"coordinates":[9.221635,49.140305],"type":"Point"}
}