{
  "type": "Feature",
  "properties": {
    "iso:country":"DE",
    "sg:address":"Im W\u00f6rth 1",
    "sg:city":"Allmendingen",
    "sg:phone":"+49 7384/6218",
    "sg:postcode":"89604",
    "sg:province":"Baden-W\u00fcrttemberg",
    "wof:name":"Werner Ruo\u00df",
    "wof:placetype":"venue"
},
  "geometry": {"coordinates":[9.662307,48.340389],"type":"Point"}
}