{
  "type": "Feature",
  "properties": {
    "iso:country":"DE",
    "sg:address":"Lukasstr. 4",
    "sg:city":"Bubenreuth",
    "sg:postcode":"91088",
    "sg:province":"Bayern",
    "wof:name":"Synapses-partitura",
    "wof:placetype":"venue"
},
  "geometry": {"coordinates":[11.0167474747,49.6239967346],"type":"Point"}
}