{
  "type": "Feature",
  "properties": {
    "iso:country":"DE",
    "sg:address":"Heubergweg 55",
    "sg:city":"Bad K\u00f6nig",
    "sg:phone":"+49 6063/3341",
    "sg:postcode":"64732",
    "sg:province":"Hessen",
    "wof:name":"Hubert Batke",
    "wof:placetype":"venue"
},
  "geometry": {"coordinates":[8.99421978,49.7157440186],"type":"Point"}
}