{
  "type": "Feature",
  "properties": {
    "iso:country":"DE",
    "sg:address":"Hausfeld 50",
    "sg:city":"Wuppertal",
    "sg:phone":"+49 202/61036",
    "sg:postcode":"42399",
    "sg:province":"Nordrhein-Westfalen",
    "wof:name":"E. W. Zingler Steuerberater",
    "wof:placetype":"venue"
},
  "geometry": {"coordinates":[7.2904448509,51.2441291809],"type":"Point"}
}