{
  "type": "Feature",
  "properties": {
    "iso:country":"DE",
    "sg:address":"Wiebelskircher Str. 10",
    "sg:city":"Neunkirchen",
    "sg:phone":"+49 6821/51489",
    "sg:postcode":"66540",
    "sg:province":"Saarland",
    "wof:name":"G. Gei\u00df",
    "wof:placetype":"venue"
},
  "geometry": {"coordinates":[7.2101621628,49.3819656372],"type":"Point"}
}