{
  "type": "Feature",
  "properties": {
    "iso:country":"DE",
    "sg:address":"Wildenhainer Str. 79",
    "sg:city":"Gro\u00dfenhain",
    "sg:postcode":"01558",
    "sg:province":"Sachsen",
    "wof:name":"Ullmann Haus Bautr\u00e4ger Gmbh",
    "wof:placetype":"venue"
},
  "geometry": {"coordinates":[13.502682,51.296188],"type":"Point"}
}