{
  "type": "Feature",
  "properties": {
    "iso:country":"DE",
    "sg:address":"Duisburger Str. 91",
    "sg:city":"D\u00fcsseldorf",
    "sg:postcode":"40479",
    "sg:province":"Nordrhein-Westfalen",
    "wof:name":"Select Gmbh",
    "wof:placetype":"venue"
},
  "geometry": {"coordinates":[6.784502,51.23341],"type":"Point"}
}