{
  "type": "Feature",
  "properties": {
    "iso:country":"DE",
    "sg:address":"Bachenauer Str. 18",
    "sg:city":"Offenau",
    "sg:phone":"+49 7136/8665",
    "sg:postcode":"74254",
    "sg:province":"Baden-W\u00fcrttemberg",
    "wof:name":"Redaktion Estrich Journal Verlag Menzel",
    "wof:placetype":"venue"
},
  "geometry": {"coordinates":[9.1641693115,49.2487716675],"type":"Point"}
}