{
  "type": "Feature",
  "properties": {
    "iso:country":"DE",
    "sg:address":"Kriegsfelder Str.",
    "sg:city":"Nieder-Wiesen",
    "sg:phone":"+49 6736/230",
    "sg:postcode":"55234",
    "sg:province":"Rheinland-Pfalz",
    "wof:name":"Ev. Pfarramt",
    "wof:placetype":"venue"
},
  "geometry": {"coordinates":[7.9777150154,49.7302055359],"type":"Point"}
}