{
  "type": "Feature",
  "properties": {
    "iso:country":"DE",
    "sg:address":"Eholfing",
    "sg:city":"Ruhstorf",
    "sg:phone":"+49 8503/776",
    "sg:postcode":"94099",
    "sg:province":"Bayern",
    "wof:name":"W. Holzer",
    "wof:placetype":"venue"
},
  "geometry": {"coordinates":[13.3191,48.465729],"type":"Point"}
}