{
  "type": "Feature",
  "properties": {
    "iso:country":"DE",
    "sg:address":"Seestr. 11 a",
    "sg:city":"Potsdam",
    "sg:phone":"+49 331/2707037",
    "sg:postcode":"14467",
    "sg:province":"Brandenburg",
    "wof:name":"Ask Arbeitsgruppe F\u00fcr Stadtplanung Und",
    "wof:placetype":"venue"
},
  "geometry": {"coordinates":[13.0761833191,52.4123840332],"type":"Point"}
}