{
  "type": "Feature",
  "properties": {
    "iso:country":"DE",
    "sg:address":"Donaustr. 13",
    "sg:city":"Stephansposching",
    "sg:phone":"+49 9935/265",
    "sg:postcode":"94569",
    "sg:province":"Bayern",
    "wof:name":"Gastst\u00e4tte Angela Kr\u00e4mer",
    "wof:placetype":"venue"
},
  "geometry": {"coordinates":[12.8029575348,48.8184204102],"type":"Point"}
}