{
  "type": "Feature",
  "properties": {
    "iso:country":"DE",
    "sg:address":"Urseler Str. 47",
    "sg:city":"Bad Homburg",
    "sg:phone":"+49 6172/690470",
    "sg:postcode":"61348",
    "sg:province":"Hessen",
    "wof:name":"Haarstudio Suchy Gmbh",
    "wof:placetype":"venue"
},
  "geometry": {"coordinates":[8.6077785492,50.2208557129],"type":"Point"}
}