{
  "type": "Feature",
  "properties": {
    "iso:country":"DE",
    "sg:address":"Asbacher Str. 42",
    "sg:city":"Linz",
    "sg:phone":"+49 2644/96020",
    "sg:postcode":"53545",
    "sg:province":"Rheinland-Pfalz",
    "wof:name":"M. Schulte S\u00f6hne",
    "wof:placetype":"venue"
},
  "geometry": {"coordinates":[7.286113,50.568741],"type":"Point"}
}