{
  "type": "Feature",
  "properties": {
    "iso:country":"DE",
    "sg:address":"Bahnhofstr. 9",
    "sg:city":"Asperg",
    "sg:phone":"+49 7141/680000",
    "sg:postcode":"71679",
    "sg:province":"Baden-W\u00fcrttemberg",
    "wof:name":"Nkd Vertriebsges. Mbh",
    "wof:placetype":"venue"
},
  "geometry": {"coordinates":[9.1366081238,48.9057846069],"type":"Point"}
}