{
  "type": "Feature",
  "properties": {
    "iso:country":"DE",
    "sg:address":"Neue Schulstr. 10",
    "sg:city":"Mudersbach",
    "sg:phone":"+49 2745/446",
    "sg:postcode":"57555",
    "sg:province":"Rheinland-Pfalz",
    "wof:name":"August Gerhardus Leder- Und Schuhmacherbed.",
    "wof:placetype":"venue"
},
  "geometry": {"coordinates":[7.9455142021,50.8270378113],"type":"Point"}
}