{
  "type": "Feature",
  "properties": {
    "iso:country":"DE",
    "sg:address":"Neustr. 11",
    "sg:city":"Westerburg",
    "sg:phone":"+49 2663/4088",
    "sg:postcode":"56457",
    "sg:province":"Rheinland-Pfalz",
    "wof:name":"Bock B\u00e4ckerei",
    "wof:placetype":"venue"
},
  "geometry": {"coordinates":[7.970531,50.563068],"type":"Point"}
}