{
  "type": "Feature",
  "properties": {
    "iso:country":"DE",
    "sg:address":"S\u00fcdstr. 39",
    "sg:city":"Ascheberg",
    "sg:phone":"+49 2599/7041",
    "sg:postcode":"59387",
    "sg:province":"Nordrhein-Westfalen",
    "wof:name":"Theodor Krampe",
    "wof:placetype":"venue"
},
  "geometry": {"coordinates":[7.663392067,51.7388267517],"type":"Point"}
}