{
  "type": "Feature",
  "properties": {
    "iso:country":"DE",
    "sg:address":"Am Bahnhof 6",
    "sg:city":"Dieburg",
    "sg:phone":"+49 6071/22074",
    "sg:postcode":"64807",
    "sg:province":"Hessen",
    "wof:name":"Wolfgang Maruschke",
    "wof:placetype":"venue"
},
  "geometry": {"coordinates":[8.8398532867,49.9035568237],"type":"Point"}
}