{
  "type": "Feature",
  "properties": {
    "iso:country":"DE",
    "sg:address":"Eichenplatz 3",
    "sg:city":"K\u00f6nigsbrunn",
    "sg:phone":"+49 8231/5770",
    "sg:postcode":"86343",
    "sg:province":"Bayern",
    "wof:name":"Helmut Wagner",
    "wof:placetype":"venue"
},
  "geometry": {"coordinates":[10.89628,48.255501],"type":"Point"}
}