{
  "type": "Feature",
  "properties": {
    "iso:country":"DE",
    "sg:address":"Dorfplatz 8",
    "sg:city":"Bad Steben/Carlsgr\u00fcn",
    "sg:phone":"+49 9288/8440",
    "sg:postcode":"95138",
    "sg:province":"Bayern",
    "wof:name":"Adelskammer Mit Adelshof - Carlsg\u00fcn Im Frankenwald",
    "wof:placetype":"venue"
},
  "geometry": {"coordinates":[11.6194629669,50.3769798279],"type":"Point"}
}