{
  "type": "Feature",
  "properties": {
    "iso:country":"DE",
    "sg:address":"Konner Pfad 5",
    "sg:city":"Mayen",
    "sg:phone":"+49 2651/48430",
    "sg:postcode":"56727",
    "sg:province":"Rheinland-Pfalz",
    "wof:name":"M\u00fcller Gmbh & Co. Kg",
    "wof:placetype":"venue"
},
  "geometry": {"coordinates":[7.2303771973,50.327041626],"type":"Point"}
}