{
  "type": "Feature",
  "properties": {
    "iso:country":"DE",
    "sg:address":"Wilhelmstr. 119",
    "sg:city":"W\u00fclfrath",
    "sg:phone":"+49 2058/5438",
    "sg:postcode":"42489",
    "sg:province":"Nordrhein-Westfalen",
    "wof:name":"Wilhelm Wenzel",
    "wof:placetype":"venue"
},
  "geometry": {"coordinates":[7.038379,51.282406],"type":"Point"}
}