{
  "type": "Feature",
  "properties": {
    "iso:country":"DE",
    "sg:address":"Bernaysstr. 6a",
    "sg:city":"M\u00fcnchen",
    "sg:phone":"+49 89/31698496",
    "sg:postcode":"80937",
    "sg:province":"Bayern",
    "wof:name":"Dila Soft Datentechnik F\u00fcr Dienstleister Gmbh",
    "wof:placetype":"venue"
},
  "geometry": {"coordinates":[11.579413414,48.2025184631],"type":"Point"}
}