{
  "type": "Feature",
  "properties": {
    "iso:country":"DE",
    "sg:address":"Gro\u00dfbuchfeld 1",
    "sg:city":"Hirschaid",
    "sg:phone":"+49 9543/7494",
    "sg:postcode":"96114",
    "sg:province":"Bayern",
    "wof:name":"Rudolf Kohlmann",
    "wof:placetype":"venue"
},
  "geometry": {"coordinates":[10.967082,49.782173],"type":"Point"}
}