{
  "type": "Feature",
  "properties": {
    "iso:country":"DE",
    "sg:address":"Kolmberger Str. 8",
    "sg:city":"Blaibach",
    "sg:phone":"+49 9941/1715",
    "sg:postcode":"93476",
    "sg:province":"Bayern",
    "wof:name":"E. Strotzer",
    "wof:placetype":"venue"
},
  "geometry": {"coordinates":[12.8072547913,49.1693229675],"type":"Point"}
}