{
  "type": "Feature",
  "properties": {
    "iso:country":"DE",
    "sg:address":"Auf der Ebest 15",
    "sg:city":"Daun",
    "sg:phone":"+49 6596/888",
    "sg:postcode":"54550",
    "sg:province":"Rheinland-Pfalz",
    "wof:name":"Hans-g\u00fcnther Brandl Architekt",
    "wof:placetype":"venue"
},
  "geometry": {"coordinates":[6.814303,50.166527],"type":"Point"}
}