{
  "type": "Feature",
  "properties": {
    "iso:country":"DE",
    "sg:address":"Dahlienweg 3a",
    "sg:city":"Bad Laer",
    "sg:phone":"+49 5424/70050",
    "sg:postcode":"49196",
    "sg:province":"Niedersachsen",
    "wof:name":"Cd-shop - Cds Und Mehr!",
    "wof:placetype":"venue"
},
  "geometry": {"coordinates":[8.0899,52.110256],"type":"Point"}
}