{
  "type": "Feature",
  "properties": {
    "iso:country":"DE",
    "sg:address":"Allerheiligenbergstr. 2",
    "sg:city":"Lahnstein",
    "sg:phone":"+49 2621/7402",
    "sg:postcode":"56112",
    "sg:province":"Rheinland-Pfalz",
    "wof:name":"Ev. Pfarramt Niederlahnstein",
    "wof:placetype":"venue"
},
  "geometry": {"coordinates":[7.609167099,50.3121757507],"type":"Point"}
}