{
  "type": "Feature",
  "properties": {
    "iso:country":"DE",
    "sg:address":"Bruchweg 11",
    "sg:city":"Babenhausen",
    "sg:phone":"+49 6073/4513",
    "sg:postcode":"64832",
    "sg:province":"Hessen",
    "wof:name":"Kath. Pfarramt St. Josef",
    "wof:placetype":"venue"
},
  "geometry": {"coordinates":[8.9537658691,49.9638748169],"type":"Point"}
}