{
  "type": "Feature",
  "properties": {
    "iso:country":"DE",
    "sg:address":"R\u00fcttenscheider Str. 86",
    "sg:city":"Essen",
    "sg:phone":"+49 201/785428",
    "sg:postcode":"45130",
    "sg:province":"Nordrhein-Westfalen",
    "wof:name":"J. H\u00f6ing",
    "wof:placetype":"venue"
},
  "geometry": {"coordinates":[7.004846096,51.4358711243],"type":"Point"}
}