{
  "type": "Feature",
  "properties": {
    "iso:country":"DE",
    "sg:address":"Neumarkt 33",
    "sg:city":"K\u00f6ln",
    "sg:phone":"+49 221/213919",
    "sg:postcode":"50667",
    "sg:province":"Nordrhein-Westfalen",
    "wof:name":"Worms Miederwaren Kg",
    "wof:placetype":"venue"
},
  "geometry": {"coordinates":[6.9473237991,50.9356040955],"type":"Point"}
}