{
  "type": "Feature",
  "properties": {
    "iso:country":"DE",
    "sg:address":"August-Becker-Str. 10",
    "sg:city":"Datteln",
    "sg:phone":"+49 2363/356903",
    "sg:postcode":"45711",
    "sg:province":"Nordrhein-Westfalen",
    "wof:name":"Verkehrs-technik Datteln Dathl- Und Maschinenbau Gmbh",
    "wof:placetype":"venue"
},
  "geometry": {"coordinates":[7.317188,51.621593],"type":"Point"}
}