{
  "type": "Feature",
  "properties": {
    "iso:country":"DE",
    "sg:address":"Hauptstrasse 28-Huetten",
    "sg:city":"Grafenwoehr",
    "sg:phone":"+49 9641",
    "sg:postcode":"92655",
    "sg:province":"Bayern",
    "wof:name":"An Die Schoensten Straende Der Tuerkei",
    "wof:placetype":"venue"
},
  "geometry": {"coordinates":[11.911775,49.717972],"type":"Point"}
}