{
  "type": "Feature",
  "properties": {
    "iso:country":"DE",
    "sg:address":"Schwanallee 31 a",
    "sg:city":"Marburg",
    "sg:phone":"+49 6421/164061",
    "sg:postcode":"35037",
    "sg:province":"Hessen",
    "wof:name":"Paisano Pizzeria",
    "wof:placetype":"venue"
},
  "geometry": {"coordinates":[8.759346962,50.8016815186],"type":"Point"}
}