{
  "type": "Feature",
  "properties": {
    "iso:country":"DE",
    "sg:address":"Memeler Str. 106",
    "sg:city":"M\u00fcnchen",
    "sg:phone":"+49 89/933031",
    "sg:postcode":"81929",
    "sg:province":"Bayern",
    "wof:name":"Karl-heinz Gruber",
    "wof:placetype":"venue"
},
  "geometry": {"coordinates":[11.6445503235,48.1529769897],"type":"Point"}
}