{
  "type": "Feature",
  "properties": {
    "iso:country":"DE",
    "sg:address":"Winterfeldtstr. 29",
    "sg:city":"Dortmund",
    "sg:phone":"+49 231/414744",
    "sg:postcode":"44141",
    "sg:province":"Nordrhein-Westfalen",
    "wof:name":"Roland Goetze Steuerberater",
    "wof:placetype":"venue"
},
  "geometry": {"coordinates":[7.4815411568,51.4991569519],"type":"Point"}
}