{
  "type": "Feature",
  "properties": {
    "iso:country":"DE",
    "sg:address":"Robert-Blum-Str. 45",
    "sg:city":"Leverkusen",
    "sg:phone":"+49 214/601864",
    "sg:postcode":"51373",
    "sg:province":"Nordrhein-Westfalen",
    "wof:name":"Layher Verwaltungs Gmbh",
    "wof:placetype":"venue"
},
  "geometry": {"coordinates":[7.0054731369,51.0512962341],"type":"Point"}
}