{
  "type": "Feature",
  "properties": {
    "iso:country":"DE",
    "sg:address":"Balduinstr. 3",
    "sg:city":"St. Wendel",
    "sg:phone":"+49 6851/2445",
    "sg:postcode":"66606",
    "sg:province":"Saarland",
    "wof:name":"Bogards",
    "wof:placetype":"venue"
},
  "geometry": {"coordinates":[7.1716799736,49.4680366516],"type":"Point"}
}