{
  "type": "Feature",
  "properties": {
    "iso:country":"DE",
    "sg:address":"Erich-M\u00fchsam-Str. 18",
    "sg:city":"Rostock",
    "sg:phone":"+49 381/82668",
    "sg:postcode":"18069",
    "sg:province":"Mecklenburg-Vorpommern",
    "wof:name":"Dr. Med. Wolfgang M\u00fcnter",
    "wof:placetype":"venue"
},
  "geometry": {"coordinates":[12.068815,54.094547],"type":"Point"}
}