{
  "type": "Feature",
  "properties": {
    "iso:country":"DE",
    "sg:address":"Bahnhofstr. 7",
    "sg:city":"Lichtenfels",
    "sg:phone":"+49 9571/71210",
    "sg:postcode":"96215",
    "sg:province":"Bayern",
    "wof:name":"Dr. Med. Joachim Hildebrandt Arzt F\u00fcr Allgemeinmedizin",
    "wof:placetype":"venue"
},
  "geometry": {"coordinates":[11.0603466034,50.1457557678],"type":"Point"}
}