{
  "type": "Feature",
  "properties": {
    "iso:country":"DE",
    "sg:address":"Zurmaiener Str. 60",
    "sg:city":"Trier",
    "sg:phone":"+49 651/41041",
    "sg:postcode":"54292",
    "sg:province":"Rheinland-Pfalz",
    "wof:name":"Esh Gitarrenkonzeption Gmbh",
    "wof:placetype":"venue"
},
  "geometry": {"coordinates":[6.636742115,49.7642860413],"type":"Point"}
}