{
  "type": "Feature",
  "properties": {
    "iso:country":"DE",
    "sg:address":"Wilhelmstr. 10",
    "sg:city":"Vienenburg",
    "sg:postcode":"38690",
    "sg:province":"Niedersachsen",
    "wof:name":"Miga Mietgarant Gmbh",
    "wof:placetype":"venue"
},
  "geometry": {"coordinates":[10.5595798492,51.9466018677],"type":"Point"}
}