{
  "type": "Feature",
  "properties": {
    "iso:country":"DE",
    "sg:address":"Burgauer Str. 21",
    "sg:city":"Kammeltal",
    "sg:phone":"+49 8223/3425",
    "sg:postcode":"89358",
    "sg:province":"Bayern",
    "wof:name":"Gastst\u00e4tte Markus Schweimeier",
    "wof:placetype":"venue"
},
  "geometry": {"coordinates":[10.3642959595,48.3792152405],"type":"Point"}
}