{
  "type": "Feature",
  "properties": {
    "iso:country":"DE",
    "sg:address":"Georg-Fischer-Str. 20",
    "sg:city":"Marktoberdorf",
    "sg:phone":"+49 8342/96060",
    "sg:postcode":"87616",
    "sg:province":"Bayern",
    "wof:name":"Wohnbau Riedler Gmbh",
    "wof:placetype":"venue"
},
  "geometry": {"coordinates":[10.6168336868,47.7782211304],"type":"Point"}
}