{
  "type": "Feature",
  "properties": {
    "iso:country":"DE",
    "sg:address":"Im Laasphetal 7",
    "sg:city":"Bad Laasphe",
    "sg:phone":"+49 2752/6158",
    "sg:postcode":"57334",
    "sg:province":"Nordrhein-Westfalen",
    "wof:name":"G\u00fcnter Hahn Elektro",
    "wof:placetype":"venue"
},
  "geometry": {"coordinates":[8.400109,50.934925],"type":"Point"}
}