{
  "type": "Feature",
  "properties": {
    "iso:country":"DE",
    "sg:address":"Frahmredder 3",
    "sg:city":"Hamburg",
    "sg:phone":"+49 40/6019594",
    "sg:postcode":"22393",
    "sg:province":"Hamburg",
    "wof:name":"S. Kr\u00fcper",
    "wof:placetype":"venue"
},
  "geometry": {"coordinates":[10.096226,53.651474],"type":"Point"}
}