{
  "type": "Feature",
  "properties": {
    "iso:country":"DE",
    "sg:address":"Redwitzstr. 83",
    "sg:city":"K\u00f6ln",
    "sg:phone":"+49 221/420550",
    "sg:postcode":"50937",
    "sg:province":"Nordrhein-Westfalen",
    "wof:name":"Id3 - Werkstatt F\u00fcr Digitale Gestaltung",
    "wof:placetype":"venue"
},
  "geometry": {"coordinates":[6.9235877991,50.9216651917],"type":"Point"}
}