{
  "type": "Feature",
  "properties": {
    "iso:country":"DE",
    "sg:address":"Goethestr. 3",
    "sg:city":"Suhl",
    "sg:phone":"+49 3681/307024",
    "sg:postcode":"98527",
    "sg:province":"Th\u00fcringen",
    "wof:name":"C. Wahl",
    "wof:placetype":"venue"
},
  "geometry": {"coordinates":[10.7038660049,50.6090545654],"type":"Point"}
}