{
  "type": "Feature",
  "properties": {
    "iso:country":"DE",
    "sg:address":"R\u00f6merstr. 95",
    "sg:city":"Castrop-Rauxel",
    "sg:phone":"+49 2305/72239",
    "sg:postcode":"44579",
    "sg:province":"Nordrhein-Westfalen",
    "wof:name":"H. Bensch Kunstmaler",
    "wof:placetype":"venue"
},
  "geometry": {"coordinates":[7.317868,51.588451],"type":"Point"}
}