{
  "type": "Feature",
  "properties": {
    "iso:country":"DE",
    "sg:address":"Kaiserstr. 21",
    "sg:city":"Lampertheim",
    "sg:phone":"+49 6206/910147",
    "sg:postcode":"68623",
    "sg:province":"Hessen",
    "wof:name":"Dm-drogerie Markt Gmbh & Co. Kg",
    "wof:placetype":"venue"
},
  "geometry": {"coordinates":[8.469705,49.595482],"type":"Point"}
}