{
  "type": "Feature",
  "properties": {
    "iso:country":"DE",
    "sg:address":"Wildbader Str. 75",
    "sg:city":"Neubulach",
    "sg:phone":"+49 7055/7068",
    "sg:postcode":"75387",
    "sg:province":"Baden-W\u00fcrttemberg",
    "wof:name":"Sonne",
    "wof:placetype":"venue"
},
  "geometry": {"coordinates":[8.6220474243,48.6384506226],"type":"Point"}
}