{
  "type": "Feature",
  "properties": {
    "iso:country":"DE",
    "sg:address":"Bahnhofstr. 60",
    "sg:city":"Peiting",
    "sg:phone":"+49 8861/25200",
    "sg:postcode":"86971",
    "sg:province":"Bayern",
    "wof:name":"H\u00f6ma Bautr\u00e4ger Und Baubetreuungs-gmbh",
    "wof:placetype":"venue"
},
  "geometry": {"coordinates":[10.941037,47.792629],"type":"Point"}
}