{
  "type": "Feature",
  "properties": {
    "iso:country":"DE",
    "sg:address":"Schlo\u00dfplatz 5",
    "sg:city":"Hof",
    "sg:phone":"+49 9281/71300",
    "sg:postcode":"95028",
    "sg:province":"Bayern",
    "wof:name":"Cds Gerd Wittig Kg",
    "wof:placetype":"venue"
},
  "geometry": {"coordinates":[11.9157457352,50.3205375671],"type":"Point"}
}