{
  "type": "Feature",
  "properties": {
    "iso:country":"DE",
    "sg:address":"Am Stie\u00dfberg 1",
    "sg:city":"Oberstaufen",
    "sg:phone":"+49 8386/7020",
    "sg:postcode":"87534",
    "sg:province":"Bayern",
    "wof:name":"Hotel Allg\u00c4u Sonne",
    "wof:placetype":"venue"
},
  "geometry": {"coordinates":[10.022749,47.554211],"type":"Point"}
}