{
  "type": "Feature",
  "properties": {
    "iso:country":"DE",
    "sg:address":"Katzhagen",
    "sg:city":"Wendeburg",
    "sg:phone":"+49 5303/2851",
    "sg:postcode":"38176",
    "sg:province":"Niedersachsen",
    "wof:name":"Bauernhaus-museum Bortfeld",
    "wof:placetype":"venue"
},
  "geometry": {"coordinates":[10.40432,52.293201],"type":"Point"}
}