{
  "type": "Feature",
  "properties": {
    "iso:country":"DE",
    "sg:address":"Twentestr. 9",
    "sg:city":"Nordhorn",
    "sg:phone":"+49 5921/80750",
    "sg:postcode":"48527",
    "sg:province":"Niedersachsen",
    "wof:name":"Monotal Schornsteinbau Gmbh",
    "wof:placetype":"venue"
},
  "geometry": {"coordinates":[7.034702,52.421772],"type":"Point"}
}