{
  "type": "Feature",
  "properties": {
    "iso:country":"DE",
    "sg:address":"Ludwigstr. 78",
    "sg:city":"Edesheim",
    "sg:phone":"+49 6323/6124",
    "sg:postcode":"67483",
    "sg:province":"Rheinland-Pfalz",
    "wof:name":"Norbert Berlenbach Weinanbau",
    "wof:placetype":"venue"
},
  "geometry": {"coordinates":[8.1245222092,49.2597122192],"type":"Point"}
}