{
  "type": "Feature",
  "properties": {
    "iso:country":"DE",
    "sg:address":"H\u00fcttenplatz 8",
    "sg:city":"Dillenburg",
    "sg:phone":"+49 2771/5709",
    "sg:postcode":"35683",
    "sg:province":"Hessen",
    "wof:name":"Horst Fackiner",
    "wof:placetype":"venue"
},
  "geometry": {"coordinates":[8.288836,50.73904],"type":"Point"}
}