{
  "type": "Feature",
  "properties": {
    "iso:country":"DE",
    "sg:address":"Im Rundteil 17",
    "sg:city":"Hagenburg",
    "sg:phone":"+49 5033/7964",
    "sg:postcode":"31558",
    "sg:province":"Niedersachsen",
    "wof:name":"Gefl\u00fcgelzuchtverein Kurt Griethe",
    "wof:placetype":"venue"
},
  "geometry": {"coordinates":[9.3089723587,52.4283332825],"type":"Point"}
}