{
  "type": "Feature",
  "properties": {
    "iso:country":"DE",
    "sg:address":"Am Ziegelfeld 4",
    "sg:city":"Bergisch Gladbach",
    "sg:phone":"+49 2204/81756",
    "sg:postcode":"51429",
    "sg:province":"Nordrhein-Westfalen",
    "wof:name":"G.i.b. Gesellschaft F\u00fcr Industrieberatung Mbh",
    "wof:placetype":"venue"
},
  "geometry": {"coordinates":[7.1911201477,50.9701194763],"type":"Point"}
}