{
  "type": "Feature",
  "properties": {
    "iso:country":"DE",
    "sg:address":"Weggenrode 4",
    "sg:city":"Bad Laer",
    "sg:phone":"+49 5424/38274",
    "sg:postcode":"49196",
    "sg:province":"Niedersachsen",
    "wof:name":"Grote & Reinhold",
    "wof:placetype":"venue"
},
  "geometry": {"coordinates":[8.115307,52.126316],"type":"Point"}
}