{
  "type": "Feature",
  "properties": {
    "iso:country":"DE",
    "sg:address":"Wielandstr. 17",
    "sg:city":"N\u00fcrnberg",
    "sg:phone":"+49 911/379862",
    "sg:postcode":"90419",
    "sg:province":"Bayern",
    "wof:name":"F. Loehr",
    "wof:placetype":"venue"
},
  "geometry": {"coordinates":[11.071056366,49.4593963623],"type":"Point"}
}