{
  "type": "Feature",
  "properties": {
    "iso:country":"DE",
    "sg:address":"Stiegelgasse 3",
    "sg:city":"Hendungen",
    "sg:phone":"+49 9764/223",
    "sg:postcode":"97640",
    "sg:province":"Bayern",
    "wof:name":"A. Other",
    "wof:placetype":"venue"
},
  "geometry": {"coordinates":[10.4073047638,50.3866081238],"type":"Point"}
}