{
  "type": "Feature",
  "properties": {
    "iso:country":"DE",
    "sg:address":"Moselstr. 121",
    "sg:city":"Troisdorf",
    "sg:phone":"+49 2241/805366",
    "sg:postcode":"53842",
    "sg:province":"Nordrhein-Westfalen",
    "wof:name":"Gertraud Kockel Steuerberater",
    "wof:placetype":"venue"
},
  "geometry": {"coordinates":[7.145840168,50.8063392639],"type":"Point"}
}