{
  "type": "Feature",
  "properties": {
    "iso:country":"DE",
    "sg:address":"Hauptstr. 35",
    "sg:city":"Spalt",
    "sg:phone":"+49 9175/1300",
    "sg:postcode":"91174",
    "sg:province":"Bayern",
    "wof:name":"Georg Kern",
    "wof:placetype":"venue"
},
  "geometry": {"coordinates":[10.9246768951,49.1760749817],"type":"Point"}
}