{
  "type": "Feature",
  "properties": {
    "iso:country":"DE",
    "sg:address":"Becker-G\u00f6ring-Str. 1",
    "sg:city":"Karlsbad",
    "sg:phone":"+49 7248/91990",
    "sg:postcode":"76307",
    "sg:province":"Baden-W\u00fcrttemberg",
    "wof:name":"Ermo Erwin Morlock Automations Gmbh",
    "wof:placetype":"venue"
},
  "geometry": {"coordinates":[8.508991,48.879017],"type":"Point"}
}