{
  "type": "Feature",
  "properties": {
    "iso:country":"DE",
    "sg:address":"H\u00fcttenstr. 7",
    "sg:city":"Inden",
    "sg:phone":"+49 2465/1233",
    "sg:postcode":"52459",
    "sg:province":"Nordrhein-Westfalen",
    "wof:name":"Ferdinand Jungbluth",
    "wof:placetype":"venue"
},
  "geometry": {"coordinates":[6.397972,50.862743],"type":"Point"}
}