{
  "type": "Feature",
  "properties": {
    "iso:country":"DE",
    "sg:address":"Waldstr. 8",
    "sg:city":"Zschirla",
    "sg:postcode":"09306",
    "sg:province":"Sachsen",
    "wof:name":"G\u00fcnter K\u00f6hler",
    "wof:placetype":"venue"
},
  "geometry": {"coordinates":[12.844958,51.131241],"type":"Point"}
}