{
  "type": "Feature",
  "properties": {
    "iso:country":"DE",
    "sg:address":"Sch\u00f6nhauser Str. 63",
    "sg:city":"Berlin",
    "sg:phone":"+49 30/4005016",
    "sg:postcode":"13127",
    "sg:province":"Berlin",
    "wof:name":"Bistro Zur Tanne",
    "wof:placetype":"venue"
},
  "geometry": {"coordinates":[13.4264955521,52.5965194702],"type":"Point"}
}