{
  "type": "Feature",
  "properties": {
    "iso:country":"DE",
    "sg:address":"B\u00e4rteichpromenade 12a",
    "sg:city":"K\u00f6then",
    "sg:postcode":"06366",
    "sg:province":"Sachsen-Anhalt",
    "wof:name":"Kinderheim Wilhelm Theuerjahr",
    "wof:placetype":"venue"
},
  "geometry": {"coordinates":[11.973594,51.749256],"type":"Point"}
}