{
  "type": "Feature",
  "properties": {
    "iso:country":"DE",
    "sg:address":"Markt 26",
    "sg:city":"M\u00f6nchengladbach",
    "sg:phone":"+49 2166/47447",
    "sg:postcode":"41236",
    "sg:province":"Nordrhein-Westfalen",
    "wof:name":"Parf\u00fcmerie Wilhelm Herschner Gmbh",
    "wof:placetype":"venue"
},
  "geometry": {"coordinates":[6.445548,51.167747],"type":"Point"}
}