{
  "type": "Feature",
  "properties": {
    "iso:country":"DE",
    "sg:address":"Augsburger Str. 45",
    "sg:city":"Straubing",
    "sg:phone":"+49 9421/6810",
    "sg:postcode":"94315",
    "sg:province":"Bayern",
    "wof:name":"Schreinerei Josef Bl\u00f6chl Inh. Helmut Kr\u00e4mer",
    "wof:placetype":"venue"
},
  "geometry": {"coordinates":[12.59336,48.8825],"type":"Point"}
}