{
  "type": "Feature",
  "properties": {
    "iso:country":"DE",
    "sg:address":"Maklerstr. 8",
    "sg:city":"Kiel",
    "sg:phone":"+49 4943/1331772",
    "sg:postcode":"24159",
    "sg:province":"Schleswig-Holstein",
    "wof:name":"Nautischer Dienst Kapit\u00c4n Stegmann",
    "wof:placetype":"venue"
},
  "geometry": {"coordinates":[10.1414070129,54.3647460938],"type":"Point"}
}