{
  "type": "Feature",
  "properties": {
    "iso:country":"DE",
    "sg:address":"Sch\u00f6nblickweg 18",
    "sg:city":"Pfronten",
    "sg:phone":"+49 8363/1241",
    "sg:postcode":"87459",
    "sg:province":"Bayern",
    "wof:name":"Scheerschmidt",
    "wof:placetype":"venue"
},
  "geometry": {"coordinates":[10.5620861053,47.594909668],"type":"Point"}
}