{
  "type": "Feature",
  "properties": {
    "iso:country":"DE",
    "sg:address":"Steubenstr. 1",
    "sg:city":"Paderborn",
    "sg:phone":"+49 5251/150960",
    "sg:postcode":"33100",
    "sg:province":"Nordrhein-Westfalen",
    "wof:name":"D\u00e4nisches Bettenlager Gmbh & Co. Kg",
    "wof:placetype":"venue"
},
  "geometry": {"coordinates":[8.7768039703,51.7365531921],"type":"Point"}
}