{
  "type": "Feature",
  "properties": {
    "iso:country":"DE",
    "sg:address":"Feldgasse 2",
    "sg:city":"R\u00f6thenbach",
    "sg:phone":"+49 911/5705033",
    "sg:postcode":"90552",
    "sg:province":"Bayern",
    "wof:name":"Die Igel-apotheke Inh. Thomas Sp\u00e4thling E. K.",
    "wof:placetype":"venue"
},
  "geometry": {"coordinates":[11.246364,49.486576],"type":"Point"}
}