{
  "type": "Feature",
  "properties": {
    "iso:country":"DE",
    "sg:address":"Schlo\u00dfstra\u00dfe 6",
    "sg:city":"Gro\u00dfenhain",
    "sg:postcode":"01558",
    "sg:province":"Sachsen",
    "wof:name":"Kaube-immobilien",
    "wof:placetype":"venue"
},
  "geometry": {"coordinates":[13.530419,51.290508],"type":"Point"}
}