{
  "type": "Feature",
  "properties": {
    "iso:country":"DE",
    "sg:address":"Torgauer Str. 42",
    "sg:city":"Eilenburg",
    "sg:phone":"+49 3423/603030",
    "sg:postcode":"04838",
    "sg:province":"Sachsen",
    "wof:name":"Falk Oettler Rechtsanwalt",
    "wof:placetype":"venue"
},
  "geometry": {"coordinates":[12.635181427,51.4605979919],"type":"Point"}
}