{
  "type": "Feature",
  "properties": {
    "iso:country":"DE",
    "sg:address":"Marienplatz 3",
    "sg:city":"Ebersberg",
    "sg:phone":"+49 8092/20489",
    "sg:postcode":"85560",
    "sg:province":"Bayern",
    "wof:name":"Gelato E Fantasia Eiscaf\u00e9",
    "wof:placetype":"venue"
},
  "geometry": {"coordinates":[11.96918,48.078419],"type":"Point"}
}