{
  "type": "Feature",
  "properties": {
    "iso:country":"DE",
    "sg:address":"Grimm 12",
    "sg:city":"Hamburg",
    "sg:phone":"+49 40/30379550",
    "sg:postcode":"20457",
    "sg:province":"Hamburg",
    "wof:name":"Aptare Personal Und Entwicklung Beratungs- Gmbh",
    "wof:placetype":"venue"
},
  "geometry": {"coordinates":[9.9932909012,53.5466461182],"type":"Point"}
}