{
  "type": "Feature",
  "properties": {
    "iso:country":"DE",
    "sg:address":"S\u00fcdendstr. 51",
    "sg:city":"Karlsruhe",
    "sg:phone":"+49 721/679229",
    "sg:postcode":"76135",
    "sg:province":"Baden-W\u00fcrttemberg",
    "wof:name":"Heinrich-hertz-schule",
    "wof:placetype":"venue"
},
  "geometry": {"coordinates":[8.384646,48.998623],"type":"Point"}
}