{
  "type": "Feature",
  "properties": {
    "iso:country":"DE",
    "sg:address":"Angergasse 110",
    "sg:city":"Ollendorf",
    "sg:phone":"+49 36203/60108",
    "sg:postcode":"99198",
    "sg:province":"Th\u00fcringen",
    "wof:name":"Elektro Eckardt E. K.",
    "wof:placetype":"venue"
},
  "geometry": {"coordinates":[11.189224,51.036102],"type":"Point"}
}