{
  "type": "Feature",
  "properties": {
    "iso:country":"DE",
    "sg:address":"Klothildenstr. 27",
    "sg:city":"M\u00fcnchen",
    "sg:phone":"+49 89/4302706",
    "sg:postcode":"81827",
    "sg:province":"Bayern",
    "wof:name":"Franz Graf Ingenieur",
    "wof:placetype":"venue"
},
  "geometry": {"coordinates":[11.6849632263,48.114906311],"type":"Point"}
}