{
  "type": "Feature",
  "properties": {
    "iso:country":"DE",
    "sg:address":"Borsigstr. 5",
    "sg:city":"Leverkusen",
    "sg:phone":"+49 2171/768588",
    "sg:postcode":"51381",
    "sg:province":"Nordrhein-Westfalen",
    "wof:name":"Kuhlmann M\u00f6bel Gmbh",
    "wof:placetype":"venue"
},
  "geometry": {"coordinates":[7.01474,51.051285],"type":"Point"}
}