{
  "type": "Feature",
  "properties": {
    "iso:country":"DE",
    "sg:address":"Langemarckstr. 12",
    "sg:city":"Bonn",
    "sg:phone":"+49 228/443008",
    "sg:postcode":"53227",
    "sg:province":"Nordrhein-Westfalen",
    "wof:name":"Helmut Schendzielorz",
    "wof:placetype":"venue"
},
  "geometry": {"coordinates":[7.18361,50.711319],"type":"Point"}
}