{
  "type": "Feature",
  "properties": {
    "iso:country":"DE",
    "sg:address":"Hauptstr. 58",
    "sg:city":"Zella-Mehlis",
    "sg:phone":"+49 3682/483353",
    "sg:postcode":"98544",
    "sg:province":"Th\u00fcringen",
    "wof:name":"G. Schmitz",
    "wof:placetype":"venue"
},
  "geometry": {"coordinates":[10.6616592407,50.6563301086],"type":"Point"}
}