{
  "type": "Feature",
  "properties": {
    "iso:country":"DE",
    "sg:address":"G\u00fcstener Str. 54",
    "sg:city":"Ilberstedt",
    "sg:phone":"+49 3471/367153",
    "sg:postcode":"06408",
    "sg:province":"Sachsen-Anhalt",
    "wof:name":"Pro Fix Reinigungsmittelwerk Gmbh",
    "wof:placetype":"venue"
},
  "geometry": {"coordinates":[11.7773303986,51.7593307495],"type":"Point"}
}