{
  "type": "Feature",
  "properties": {
    "iso:country":"DE",
    "sg:address":"Werkstr 2",
    "sg:city":"B\u00fchl",
    "sg:phone":"+49 7223/21051",
    "sg:postcode":"77815",
    "sg:province":"Baden-W\u00fcrttemberg",
    "wof:name":"Sturm-transmar Gmbh",
    "wof:placetype":"venue"
},
  "geometry": {"coordinates":[8.1202316284,48.7185821533],"type":"Point"}
}