{
  "type": "Feature",
  "properties": {
    "iso:country":"DE",
    "sg:address":"Wurzerstr. 15",
    "sg:city":"M\u00fcnchen",
    "sg:phone":"+49 89/221331",
    "sg:postcode":"80539",
    "sg:province":"Bayern",
    "wof:name":"Print & Proof Gesellschaftzum Vertrieb Graphischerprodukte Mbh",
    "wof:placetype":"venue"
},
  "geometry": {"coordinates":[11.582693,48.139317],"type":"Point"}
}