{
  "type": "Feature",
  "properties": {
    "iso:country":"DE",
    "sg:address":"Hauptstr. 10",
    "sg:city":"Breitenbrunn",
    "sg:phone":"+49 9492/5749",
    "sg:postcode":"92363",
    "sg:province":"Bayern",
    "wof:name":"Karl Tynek Rechtsanwalt",
    "wof:placetype":"venue"
},
  "geometry": {"coordinates":[11.6866340637,49.1090164185],"type":"Point"}
}