{
  "type": "Feature",
  "properties": {
    "iso:country":"DE",
    "sg:address":"Haydnstr. 2",
    "sg:city":"Buseck",
    "sg:phone":"+49 6408/90070",
    "sg:postcode":"35418",
    "sg:province":"Hessen",
    "wof:name":"J\u00fcrgen Fliege",
    "wof:placetype":"venue"
},
  "geometry": {"coordinates":[8.7982959747,50.5877113342],"type":"Point"}
}