{
  "type": "Feature",
  "properties": {
    "iso:country":"DE",
    "sg:address":"Zansham 6",
    "sg:city":"Schnaitsee",
    "sg:phone":"+49 8074/380",
    "sg:postcode":"83530",
    "sg:province":"Bayern",
    "wof:name":"G. Deibl",
    "wof:placetype":"venue"
},
  "geometry": {"coordinates":[12.343748,48.07748],"type":"Point"}
}