{
  "type": "Feature",
  "properties": {
    "iso:country":"DE",
    "sg:address":"Ma\u00dfbrucher Weg 77",
    "sg:city":"Lemgo",
    "sg:phone":"+49 5261/8129",
    "sg:postcode":"32657",
    "sg:province":"Nordrhein-Westfalen",
    "wof:name":"Albert Sch\u00fcte",
    "wof:placetype":"venue"
},
  "geometry": {"coordinates":[8.944921,52.002541],"type":"Point"}
}