{
  "type": "Feature",
  "properties": {
    "iso:country":"DE",
    "sg:address":"Gotenring 56",
    "sg:city":"Swisttal",
    "sg:phone":"+49 2255/8416",
    "sg:postcode":"53913",
    "sg:province":"Nordrhein-Westfalen",
    "wof:name":"Wolfgang Klein",
    "wof:placetype":"venue"
},
  "geometry": {"coordinates":[6.888021,50.645264],"type":"Point"}
}