{
  "type": "Feature",
  "properties": {
    "iso:country":"DE",
    "sg:address":"Anton-Seith-Platz 2",
    "sg:city":"M\u00fcnnerstadt",
    "sg:phone":"+49 9733/1282",
    "sg:postcode":"97702",
    "sg:province":"Bayern",
    "wof:name":"Guntram Back",
    "wof:placetype":"venue"
},
  "geometry": {"coordinates":[10.1536569595,50.2632026672],"type":"Point"}
}