{
  "type": "Feature",
  "properties": {
    "iso:country":"DE",
    "sg:address":"Langenhaus 47",
    "sg:city":"Wuppertal",
    "sg:phone":"+49 202/4698040",
    "sg:postcode":"42369",
    "sg:province":"Nordrhein-Westfalen",
    "wof:name":"Alfred Kratz Kunststoffprodukte Gmbh",
    "wof:placetype":"venue"
},
  "geometry": {"coordinates":[7.19631,51.227798],"type":"Point"}
}