{
  "type": "Feature",
  "properties": {
    "iso:country":"DE",
    "sg:address":"Schillerstr. 30",
    "sg:city":"M\u00fcnchen",
    "sg:phone":"+49 89/595721",
    "sg:postcode":"80336",
    "sg:province":"Bayern",
    "wof:name":"A. Yechieli",
    "wof:placetype":"venue"
},
  "geometry": {"coordinates":[11.560745,48.136524],"type":"Point"}
}