{
  "type": "Feature",
  "properties": {
    "iso:country":"DE",
    "sg:address":"Am Schattenberg 16",
    "sg:city":"Finnentrop",
    "sg:postcode":"57413",
    "sg:province":"Nordrhein-Westfalen",
    "wof:name":"Grula Lubsch & Grube Gmbh & Co.",
    "wof:placetype":"venue"
},
  "geometry": {"coordinates":[7.951072,51.152718],"type":"Point"}
}