{
  "type": "Feature",
  "properties": {
    "iso:country":"DE",
    "sg:address":"Germersheimer Str. 64",
    "sg:city":"Offenbach",
    "sg:phone":"+49 6348/380",
    "sg:postcode":"76877",
    "sg:province":"Rheinland-Pfalz",
    "wof:name":"Schnetzer Heizungsbau Gmbh",
    "wof:placetype":"venue"
},
  "geometry": {"coordinates":[8.1955699921,49.1933441162],"type":"Point"}
}