{
  "type": "Feature",
  "properties": {
    "iso:country":"DE",
    "sg:address":"Seelbacher Weg 8",
    "sg:city":"Taunusstein",
    "sg:phone":"+49 611/992390",
    "sg:postcode":"65232",
    "sg:province":"Hessen",
    "wof:name":"Synergetic Projekt - Entwicklungsges. Mbh",
    "wof:placetype":"venue"
},
  "geometry": {"coordinates":[8.188284,50.15649],"type":"Point"}
}