{
  "type": "Feature",
  "properties": {
    "iso:country":"DE",
    "sg:address":"Brabanter Str. 125",
    "sg:city":"Viersen",
    "sg:phone":"+49 2162/55733",
    "sg:postcode":"41751",
    "sg:province":"Nordrhein-Westfalen",
    "wof:name":"J. Snellen",
    "wof:placetype":"venue"
},
  "geometry": {"coordinates":[6.3404288292,51.2645835876],"type":"Point"}
}