{
  "type": "Feature",
  "properties": {
    "iso:country":"DE",
    "sg:address":"Bgm.-Hergenhan-Str.12",
    "sg:city":"Trittau",
    "sg:phone":"+49 4154/842970",
    "sg:postcode":"22946",
    "sg:province":"Schleswig-Holstein",
    "wof:name":"Five-o-one",
    "wof:placetype":"venue"
},
  "geometry": {"coordinates":[10.3924760818,53.6170539856],"type":"Point"}
}