{
  "type": "Feature",
  "properties": {
    "iso:country":"DE",
    "sg:address":"Peterstr. 25",
    "sg:city":"Bad Zwischenahn",
    "sg:phone":"+49 4403/5011",
    "sg:postcode":"26160",
    "sg:province":"Niedersachsen",
    "wof:name":"Trend Line Holzum",
    "wof:placetype":"venue"
},
  "geometry": {"coordinates":[8.006307,53.184498],"type":"Point"}
}