{
  "type": "Feature",
  "properties": {
    "iso:country":"DE",
    "sg:address":"Hoffmannstr. 28",
    "sg:city":"Chemnitz",
    "sg:postcode":"09112",
    "sg:province":"Sachsen",
    "wof:name":"Dr. Med. Dieter Korn",
    "wof:placetype":"venue"
},
  "geometry": {"coordinates":[12.897938,50.827648],"type":"Point"}
}