{
  "type": "Feature",
  "properties": {
    "iso:country":"DE",
    "sg:address":"Friedberger Str. 11",
    "sg:city":"Augsburg",
    "sg:phone":"+49 821/555015",
    "sg:postcode":"86161",
    "sg:province":"Bayern",
    "wof:name":"Leithammel Verlags-gmbh",
    "wof:placetype":"venue"
},
  "geometry": {"coordinates":[10.9097099304,48.3581542969],"type":"Point"}
}