{
  "type": "Feature",
  "properties": {
    "iso:country":"DE",
    "sg:address":"Hohentwielstr. 80",
    "sg:city":"Stuttgart",
    "sg:phone":"+49 711/6071090",
    "sg:postcode":"70199",
    "sg:province":"Baden-W\u00fcrttemberg",
    "wof:name":"J. Klusendick",
    "wof:placetype":"venue"
},
  "geometry": {"coordinates":[9.150616,48.76247],"type":"Point"}
}