{
  "type": "Feature",
  "properties": {
    "iso:country":"DE",
    "sg:address":"Bauhausstiege 2",
    "sg:city":"Dorsten",
    "sg:phone":"+49 2362/280",
    "sg:postcode":"46282",
    "sg:province":"Nordrhein-Westfalen",
    "wof:name":"Union Baustoffhandel Gmbh",
    "wof:placetype":"venue"
},
  "geometry": {"coordinates":[6.9641861916,51.6612434387],"type":"Point"}
}