{
  "type": "Feature",
  "properties": {
    "iso:country":"DE",
    "sg:address":"Leipziger Str. 34",
    "sg:city":"Magdeburg",
    "sg:phone":"+49 391/6201807",
    "sg:postcode":"39112",
    "sg:province":"Sachsen-Anhalt",
    "wof:name":"K. Bonhage",
    "wof:placetype":"venue"
},
  "geometry": {"coordinates":[11.61989,52.107597],"type":"Point"}
}