{
  "type": "Feature",
  "properties": {
    "iso:country":"DE",
    "sg:address":"Silgestr. 38",
    "sg:city":"Ludwigshafen",
    "sg:phone":"+49 621/532083",
    "sg:postcode":"67067",
    "sg:province":"Rheinland-Pfalz",
    "wof:name":"E. Scholz Heissmangel",
    "wof:placetype":"venue"
},
  "geometry": {"coordinates":[8.3746681213,49.4563941956],"type":"Point"}
}