{
  "type": "Feature",
  "properties": {
    "iso:country":"DE",
    "sg:address":"Griesweg 22",
    "sg:city":"Kirchdorf",
    "sg:phone":"+49 7354/8550",
    "sg:postcode":"88457",
    "sg:province":"Baden-W\u00fcrttemberg",
    "wof:name":"Thomas Schindler Architekt",
    "wof:placetype":"venue"
},
  "geometry": {"coordinates":[10.129135,48.078972],"type":"Point"}
}