{
  "type": "Feature",
  "properties": {
    "iso:country":"DE",
    "sg:address":"Unter den Ulmen 45",
    "sg:city":"Duisburg",
    "sg:phone":"+49 203/446617",
    "sg:postcode":"47137",
    "sg:province":"Nordrhein-Westfalen",
    "wof:name":"Home Racing",
    "wof:placetype":"venue"
},
  "geometry": {"coordinates":[6.7606468201,51.4641342163],"type":"Point"}
}