{
  "type": "Feature",
  "properties": {
    "iso:country":"DE",
    "sg:address":"Hanauer Str. 10",
    "sg:city":"R\u00f6dermark",
    "sg:phone":"+49 6074/97228",
    "sg:postcode":"63322",
    "sg:province":"Hessen",
    "wof:name":"Reinhold Wittich",
    "wof:placetype":"venue"
},
  "geometry": {"coordinates":[8.823185,49.980984],"type":"Point"}
}