{
  "type": "Feature",
  "properties": {
    "iso:country":"DE",
    "sg:address":"Armin-Knab-Str. 50",
    "sg:city":"Dittelbrunn",
    "sg:phone":"+49 9725/4644",
    "sg:postcode":"97456",
    "sg:province":"Bayern",
    "wof:name":"C.m. G\u00f6bel",
    "wof:placetype":"venue"
},
  "geometry": {"coordinates":[10.2130908966,50.1023101807],"type":"Point"}
}