{
  "type": "Feature",
  "properties": {
    "iso:country":"DE",
    "sg:address":"Am Joelper 19",
    "sg:city":"Nettersheim",
    "sg:phone":"+49 2440/284414",
    "sg:postcode":"53947",
    "sg:province":"Nordrhein-Westfalen",
    "wof:name":"K. H. Hellmeier Immobilienmakler",
    "wof:placetype":"venue"
},
  "geometry": {"coordinates":[6.7164549828,50.470905304],"type":"Point"}
}