{
  "type": "Feature",
  "properties": {
    "iso:country":"DE",
    "sg:address":"Kortenhegge 4",
    "sg:city":"Harsewinkel",
    "sg:phone":"+49 5247/2178",
    "sg:postcode":"33428",
    "sg:province":"Nordrhein-Westfalen",
    "wof:name":"Augustinus Linnemann",
    "wof:placetype":"venue"
},
  "geometry": {"coordinates":[8.184379,51.951794],"type":"Point"}
}