{
  "type": "Feature",
  "properties": {
    "iso:country":"DE",
    "sg:address":"B\u00fchlstr. 26",
    "sg:city":"Uhingen",
    "sg:phone":"+49 7161/32755",
    "sg:postcode":"73066",
    "sg:province":"Baden-W\u00fcrttemberg",
    "wof:name":"Klara Schock",
    "wof:placetype":"venue"
},
  "geometry": {"coordinates":[9.5770330429,48.6858291626],"type":"Point"}
}