{
  "type": "Feature",
  "properties": {
    "iso:country":"DE",
    "sg:address":"Ostpreu\u00dfenstr. 6",
    "sg:city":"Karlsruhe",
    "sg:phone":"+49 721/451143",
    "sg:postcode":"76228",
    "sg:province":"Baden-W\u00fcrttemberg",
    "wof:name":"D. Ouetz",
    "wof:placetype":"venue"
},
  "geometry": {"coordinates":[8.476276,48.951981],"type":"Point"}
}