{
  "type": "Feature",
  "properties": {
    "iso:country":"DE",
    "sg:address":"Briller Str. 1 d",
    "sg:city":"Wuppertal",
    "sg:phone":"+49 202/302314",
    "sg:postcode":"42103",
    "sg:province":"Nordrhein-Westfalen",
    "wof:name":"Hubert Luttermann",
    "wof:placetype":"venue"
},
  "geometry": {"coordinates":[7.1325969696,51.2535324097],"type":"Point"}
}