{
  "type": "Feature",
  "properties": {
    "iso:country":"DE",
    "sg:address":"Im Rauland 48",
    "sg:city":"Bergheim",
    "sg:phone":"+49 2271/980345",
    "sg:postcode":"50127",
    "sg:province":"Nordrhein-Westfalen",
    "wof:name":"Richard Moll",
    "wof:placetype":"venue"
},
  "geometry": {"coordinates":[6.678377,50.940086],"type":"Point"}
}