{
  "type": "Feature",
  "properties": {
    "iso:country":"DE",
    "sg:address":"Gneisenaustr. 100",
    "sg:city":"Berlin",
    "sg:postcode":"10961",
    "sg:province":"Berlin",
    "wof:name":"Guerilla Music Gmbh",
    "wof:placetype":"venue"
},
  "geometry": {"coordinates":[13.3919219971,52.492389679],"type":"Point"}
}