{
  "type": "Feature",
  "properties": {
    "iso:country":"DE",
    "sg:address":"K\u00f6nigstr. 132",
    "sg:city":"F\u00fcrth",
    "sg:phone":"+49 911/778842",
    "sg:postcode":"90762",
    "sg:province":"Bayern",
    "wof:name":"J\u00fcrgen L\u00f6del Rechtsanwalt",
    "wof:placetype":"venue"
},
  "geometry": {"coordinates":[10.9926309586,49.4734916687],"type":"Point"}
}