{
  "type": "Feature",
  "properties": {
    "iso:country":"DE",
    "sg:address":"K\u00f6nigstr. 80",
    "sg:city":"Stuttgart",
    "sg:postcode":"70173",
    "sg:province":"Baden-W\u00fcrttemberg",
    "wof:name":"Star Logistics Ag",
    "wof:placetype":"venue"
},
  "geometry": {"coordinates":[9.174484,48.773586],"type":"Point"}
}