{
  "type": "Feature",
  "properties": {
    "iso:country":"DE",
    "sg:address":"Pillenreuther Str. 41",
    "sg:city":"N\u00fcrnberg",
    "sg:postcode":"90459",
    "sg:province":"Bayern",
    "wof:name":"C Und R - Create And Realize Event Gmbh",
    "wof:placetype":"venue"
},
  "geometry": {"coordinates":[11.0820198059,49.4406433105],"type":"Point"}
}