{
  "type": "Feature",
  "properties": {
    "iso:country":"DE",
    "sg:address":"Am R\u00f6merhof 13",
    "sg:city":"Frankfurt",
    "sg:phone":"+49 69/702070",
    "sg:postcode":"60486",
    "sg:province":"Hessen",
    "wof:name":"Bowlingzentrum Rebstock",
    "wof:placetype":"venue"
},
  "geometry": {"coordinates":[8.6086053848,50.106842041],"type":"Point"}
}