{
  "type": "Feature",
  "properties": {
    "iso:country":"DE",
    "sg:address":"Viktoriastr. 8",
    "sg:city":"L\u00fcnen",
    "sg:phone":"+49 2306/22770",
    "sg:postcode":"44532",
    "sg:province":"Nordrhein-Westfalen",
    "wof:name":"Susanne Eschert",
    "wof:placetype":"venue"
},
  "geometry": {"coordinates":[7.523422,51.609245],"type":"Point"}
}