{
  "type": "Feature",
  "properties": {
    "iso:country":"DE",
    "sg:address":"Gro\u00dfe Budengasse 3",
    "sg:city":"K\u00f6ln",
    "sg:phone":"+49 221/2580390",
    "sg:postcode":"50667",
    "sg:province":"Nordrhein-Westfalen",
    "wof:name":"Koll & Werdel",
    "wof:placetype":"venue"
},
  "geometry": {"coordinates":[6.9565601349,50.9393539429],"type":"Point"}
}