{
  "type": "Feature",
  "properties": {
    "iso:country":"DE",
    "sg:address":"Hauptstr. 1",
    "sg:city":"Gars",
    "sg:phone":"+49 8073/1254",
    "sg:postcode":"83536",
    "sg:province":"Bayern",
    "wof:name":"Paul Ullrich Inh. F. Gerzer",
    "wof:placetype":"venue"
},
  "geometry": {"coordinates":[12.27659,48.152687],"type":"Point"}
}