{
  "type": "Feature",
  "properties": {
    "iso:country":"DE",
    "sg:address":"Am Scherrweiher 2",
    "sg:city":"Marktredwitz",
    "sg:phone":"+49 9231/4008",
    "sg:postcode":"95615",
    "sg:province":"Bayern",
    "wof:name":"Ebm Alfons Bauer",
    "wof:placetype":"venue"
},
  "geometry": {"coordinates":[12.0999164581,50.0124473572],"type":"Point"}
}