{
  "type": "Feature",
  "properties": {
    "iso:country":"DE",
    "sg:address":"Steinweg 3",
    "sg:city":"D\u00f6hlau",
    "sg:phone":"+49 9286/97153",
    "sg:postcode":"95182",
    "sg:province":"Bayern",
    "wof:name":"Walter S\u00f6rgel",
    "wof:placetype":"venue"
},
  "geometry": {"coordinates":[11.9465675354,50.2774047852],"type":"Point"}
}