{
  "type": "Feature",
  "properties": {
    "iso:country":"DE",
    "sg:address":"Mittelstr. 90",
    "sg:city":"Neuwied",
    "sg:phone":"+49 2631/25455",
    "sg:postcode":"56564",
    "sg:province":"Rheinland-Pfalz",
    "wof:name":"Phildar Wolle Gmbh",
    "wof:placetype":"venue"
},
  "geometry": {"coordinates":[7.46237,50.430149],"type":"Point"}
}