{
  "type": "Feature",
  "properties": {
    "iso:country":"DE",
    "sg:address":"Eichendorffstr. 24",
    "sg:city":"Renningen",
    "sg:phone":"+49 7159/2431",
    "sg:postcode":"71272",
    "sg:province":"Baden-W\u00fcrttemberg",
    "wof:name":"Longrin Heinkele Architekt",
    "wof:placetype":"venue"
},
  "geometry": {"coordinates":[8.936186,48.774517],"type":"Point"}
}