{
  "type": "Feature",
  "properties": {
    "iso:country":"DE",
    "sg:address":"Schillerstr. 10",
    "sg:city":"Selbitz",
    "sg:phone":"+49 9280/5739",
    "sg:postcode":"95152",
    "sg:province":"Bayern",
    "wof:name":"Werner Tho\u00df Kg",
    "wof:placetype":"venue"
},
  "geometry": {"coordinates":[11.750413,50.31839],"type":"Point"}
}