{
  "type": "Feature",
  "properties": {
    "iso:country":"DE",
    "sg:address":"Zur Stiege 1",
    "sg:city":"Bramsche",
    "sg:phone":"+49 5461/3531",
    "sg:postcode":"49565",
    "sg:province":"Niedersachsen",
    "wof:name":"B\u00fchrmann-st\u00fcckemann Baugesch\u00e4ft Gmbh",
    "wof:placetype":"venue"
},
  "geometry": {"coordinates":[7.9672012329,52.417350769],"type":"Point"}
}