{
  "type": "Feature",
  "properties": {
    "iso:country":"DE",
    "sg:address":"B\u00f6llerts H\u00f6fe 3",
    "sg:city":"M\u00fclheim",
    "sg:phone":"+49 208/426502",
    "sg:postcode":"45479",
    "sg:province":"Nordrhein-Westfalen",
    "wof:name":"Thomas Weimann",
    "wof:placetype":"venue"
},
  "geometry": {"coordinates":[6.8544421196,51.4165344238],"type":"Point"}
}