{
  "type": "Feature",
  "properties": {
    "iso:country":"DE",
    "sg:address":"Ruitwiesen 4",
    "sg:city":"Leonberg",
    "sg:postcode":"71229",
    "sg:province":"Baden-W\u00fcrttemberg",
    "wof:name":"Automobilforum Gmbh",
    "wof:placetype":"venue"
},
  "geometry": {"coordinates":[9.0165157318,48.7849388123],"type":"Point"}
}