{
  "type": "Feature",
  "properties": {
    "iso:country":"DE",
    "sg:address":"Kirchstr. 7",
    "sg:city":"Winterberg",
    "sg:postcode":"59955",
    "sg:province":"Nordrhein-Westfalen",
    "wof:name":"Pfarrb\u00fccherei Winterberg",
    "wof:placetype":"venue"
},
  "geometry": {"coordinates":[8.535927,51.195053],"type":"Point"}
}