{
  "type": "Feature",
  "properties": {
    "iso:country":"DE",
    "sg:address":"Tegernseer Str. 5",
    "sg:city":"Gmund",
    "sg:phone":"+49 8022/75909",
    "sg:postcode":"83703",
    "sg:province":"Bayern",
    "wof:name":"Steuerberatungsges. Oberland Gmbh",
    "wof:placetype":"venue"
},
  "geometry": {"coordinates":[11.738945961,47.7481460571],"type":"Point"}
}