{
  "type": "Feature",
  "properties": {
    "iso:country":"DE",
    "sg:address":"Lauterbacher Str. 32",
    "sg:city":"Neukirchen",
    "sg:phone":"+49 3762/3544",
    "sg:postcode":"08459",
    "sg:province":"Sachsen",
    "wof:name":"Lrz Landhandels- Und Recycling-zentrum Gmbh",
    "wof:placetype":"venue"
},
  "geometry": {"coordinates":[12.383714,50.776718],"type":"Point"}
}