{
  "type": "Feature",
  "properties": {
    "iso:country":"DE",
    "sg:address":"Baumeisterallee 33",
    "sg:city":"Zwenkau",
    "sg:phone":"+49 34203/4710",
    "sg:postcode":"04442",
    "sg:province":"Sachsen",
    "wof:name":"Siekmann Econosto Armaturen- Und Dichtungstechnik Gmbh",
    "wof:placetype":"venue"
},
  "geometry": {"coordinates":[12.334936142,51.2113304138],"type":"Point"}
}