{
  "type": "Feature",
  "properties": {
    "iso:country":"DE",
    "sg:address":"Stra\u00dfe der Einheit 152",
    "sg:city":"Gelenau",
    "sg:phone":"+49 37297/7250",
    "sg:postcode":"09423",
    "sg:province":"Sachsen",
    "wof:name":"Steigerhaus",
    "wof:placetype":"venue"
},
  "geometry": {"coordinates":[12.9626350403,50.7107543945],"type":"Point"}
}