{
  "type": "Feature",
  "properties": {
    "iso:country":"DE",
    "sg:address":"Zur Spetze 7",
    "sg:city":"Flechtingen",
    "sg:phone":"+49 39054/2279",
    "sg:postcode":"39345",
    "sg:province":"Sachsen-Anhalt",
    "wof:name":"H. Crackau",
    "wof:placetype":"venue"
},
  "geometry": {"coordinates":[11.240565,52.332554],"type":"Point"}
}