{
  "type": "Feature",
  "properties": {
    "iso:country":"DE",
    "sg:address":"Unlandstr. 101",
    "sg:city":"Rheine",
    "sg:phone":"+49 5971/40020",
    "sg:postcode":"48431",
    "sg:province":"Nordrhein-Westfalen",
    "wof:name":"Caritas Kinderheim Gmbh",
    "wof:placetype":"venue"
},
  "geometry": {"coordinates":[7.4136400223,52.2905387878],"type":"Point"}
}