{
  "type": "Feature",
  "properties": {
    "iso:country":"DE",
    "sg:address":"Nicolaistr. 5",
    "sg:city":"Glauchau",
    "sg:phone":"+49 3763/5527",
    "sg:postcode":"08371",
    "sg:province":"Sachsen",
    "wof:name":"Ju. Waner Und J. Z\u00f6llner",
    "wof:placetype":"venue"
},
  "geometry": {"coordinates":[12.5428752899,50.8183898926],"type":"Point"}
}