{
  "type": "Feature",
  "properties": {
    "iso:country":"DE",
    "sg:address":"Alt-Tempelhof 34",
    "sg:city":"Berlin",
    "sg:phone":"+49 30/76008010",
    "sg:postcode":"12103",
    "sg:province":"Berlin",
    "wof:name":"Holger Schelsky",
    "wof:placetype":"venue"
},
  "geometry": {"coordinates":[13.3829908371,52.4661178589],"type":"Point"}
}