{
  "type": "Feature",
  "properties": {
    "iso:country":"DE",
    "sg:address":"Devern 19",
    "sg:city":"Badbergen",
    "sg:phone":"+49 5433/738",
    "sg:postcode":"49635",
    "sg:province":"Niedersachsen",
    "wof:name":"J\u00fcrgen Devermann",
    "wof:placetype":"venue"
},
  "geometry": {"coordinates":[7.968677,52.626587],"type":"Point"}
}