{
  "type": "Feature",
  "properties": {
    "iso:country":"DE",
    "sg:address":"Puschkinstr. 14",
    "sg:city":"Erfurt",
    "sg:phone":"+49 361/6462633",
    "sg:postcode":"99084",
    "sg:province":"Th\u00fcringen",
    "wof:name":"Vvs Holding Vertriebs- Verwaltungs- Und Service Gmbh",
    "wof:placetype":"venue"
},
  "geometry": {"coordinates":[11.0267286301,50.9661827087],"type":"Point"}
}