{
  "type": "Feature",
  "properties": {
    "iso:country":"DE",
    "sg:address":"Kieferndorfer Weg 35",
    "sg:city":"H\u00f6chstadt",
    "sg:phone":"+49 9193/1575",
    "sg:postcode":"91315",
    "sg:province":"Bayern",
    "wof:name":"Burkholz & Partner Gmbh",
    "wof:placetype":"venue"
},
  "geometry": {"coordinates":[10.8202018738,49.7073059082],"type":"Point"}
}