{
  "type": "Feature",
  "properties": {
    "iso:country":"DE",
    "sg:address":"Gro\u00dfer Kamp 26",
    "sg:city":"Hagen",
    "sg:postcode":"58093",
    "sg:province":"Nordrhein-Westfalen",
    "wof:name":"Brock Vertriebs- Und Verwaltungs- Gmbh",
    "wof:placetype":"venue"
},
  "geometry": {"coordinates":[7.503237,51.377026],"type":"Point"}
}