{
  "type": "Feature",
  "properties": {
    "iso:country":"DE",
    "sg:address":"Auf'm Kalper 6",
    "sg:city":"Drolshagen",
    "sg:phone":"+49 2763/840909",
    "sg:postcode":"57489",
    "sg:province":"Nordrhein-Westfalen",
    "wof:name":"Kreco Klebetechnik Gmbh",
    "wof:placetype":"venue"
},
  "geometry": {"coordinates":[7.8145160675,51.0394248962],"type":"Point"}
}