{
  "type": "Feature",
  "properties": {
    "iso:country":"DE",
    "sg:address":"Albert-Mertes-Str. 11",
    "sg:city":"Bad Breisig",
    "sg:phone":"+49 2633/480710",
    "sg:postcode":"53498",
    "sg:province":"Rheinland-Pfalz",
    "wof:name":"R\u00f6mer-therme",
    "wof:placetype":"venue"
},
  "geometry": {"coordinates":[7.295125,50.51265],"type":"Point"}
}