{
  "type": "Feature",
  "properties": {
    "iso:country":"DE",
    "sg:address":"Hagenower Str. 73",
    "sg:city":"Schwerin",
    "sg:phone":"+49 385/3993109",
    "sg:postcode":"19061",
    "sg:province":"Mecklenburg-Vorpommern",
    "wof:name":"Mri Devices Daum Gmbh",
    "wof:placetype":"venue"
},
  "geometry": {"coordinates":[11.4171056747,53.6004447937],"type":"Point"}
}