{
  "type": "Feature",
  "properties": {
    "iso:country":"DE",
    "sg:address":"Bronntor 1",
    "sg:city":"Herrenberg",
    "sg:phone":"+49 7032/24958",
    "sg:postcode":"71083",
    "sg:province":"Baden-W\u00fcrttemberg",
    "wof:name":"Hosen-city Manfred Sitzler Kg",
    "wof:placetype":"venue"
},
  "geometry": {"coordinates":[8.869929,48.595989],"type":"Point"}
}