{
  "type": "Feature",
  "properties": {
    "iso:country":"DE",
    "sg:address":"Ottoweg 2b",
    "sg:city":"Coesfeld",
    "sg:phone":"+49 2541/7666",
    "sg:postcode":"48653",
    "sg:province":"Nordrhein-Westfalen",
    "wof:name":"A. Pier",
    "wof:placetype":"venue"
},
  "geometry": {"coordinates":[7.1512408257,51.9483184814],"type":"Point"}
}