{
  "type": "Feature",
  "properties": {
    "iso:country":"DE",
    "sg:address":"Karl-Marx-str.49",
    "sg:city":"Berlin",
    "sg:phone":"+49 30",
    "sg:postcode":"12043",
    "sg:province":"Berlin",
    "wof:name":"Forces Style - Online Shop",
    "wof:placetype":"venue"
},
  "geometry": {"coordinates":[13.4309654236,52.4835662842],"type":"Point"}
}