{
  "type": "Feature",
  "properties": {
    "iso:country":"DE",
    "sg:address":"Stompen 19",
    "sg:city":"Much",
    "sg:phone":"+49 2245/2172",
    "sg:postcode":"53804",
    "sg:province":"Nordrhein-Westfalen",
    "wof:name":"P. Kreuzer",
    "wof:placetype":"venue"
},
  "geometry": {"coordinates":[7.409567,50.882687],"type":"Point"}
}