{
  "type": "Feature",
  "properties": {
    "iso:country":"DE",
    "sg:address":"Niederfeldstr. 17 a",
    "sg:city":"Bielefeld",
    "sg:phone":"+49 521/82566",
    "sg:postcode":"33611",
    "sg:province":"Nordrhein-Westfalen",
    "wof:name":"Hans-j\u00f6rg Quelle",
    "wof:placetype":"venue"
},
  "geometry": {"coordinates":[8.55156,52.05402],"type":"Point"}
}