{
  "type": "Feature",
  "properties": {
    "iso:country":"DE",
    "sg:address":"Oststr. 30",
    "sg:city":"Eberstadt",
    "sg:phone":"+49 7134/4524",
    "sg:postcode":"74246",
    "sg:province":"Baden-W\u00fcrttemberg",
    "wof:name":"O. Voegele",
    "wof:placetype":"venue"
},
  "geometry": {"coordinates":[9.328205,49.179222],"type":"Point"}
}