{
  "type": "Feature",
  "properties": {
    "iso:country":"DE",
    "sg:address":"Sch\u00f6ne Aussicht 6",
    "sg:city":"Walluf",
    "sg:phone":"+49 6123/990061",
    "sg:postcode":"65396",
    "sg:province":"Hessen",
    "wof:name":"Peter Brunsbach Gmbh",
    "wof:placetype":"venue"
},
  "geometry": {"coordinates":[8.1617870331,50.0387878418],"type":"Point"}
}