{
  "type": "Feature",
  "properties": {
    "iso:country":"DE",
    "sg:address":"Ligusterweg 17",
    "sg:city":"Ditzingen",
    "sg:phone":"+49 7156/939967",
    "sg:postcode":"71254",
    "sg:province":"Baden-W\u00fcrttemberg",
    "wof:name":"Christa Wennemann",
    "wof:placetype":"venue"
},
  "geometry": {"coordinates":[9.0316886902,48.8360939026],"type":"Point"}
}