{
  "type": "Feature",
  "properties": {
    "iso:country":"DE",
    "sg:address":"Odenwaldweg 22",
    "sg:city":"Klingenberg",
    "sg:phone":"+49 9372/2141",
    "sg:postcode":"63911",
    "sg:province":"Bayern",
    "wof:name":"Bernhard Me\u00dfbacher",
    "wof:placetype":"venue"
},
  "geometry": {"coordinates":[9.172621727,49.7773284912],"type":"Point"}
}