{
  "type": "Feature",
  "properties": {
    "iso:country":"DE",
    "sg:address":"Poststr. 8",
    "sg:city":"Lohmar",
    "sg:phone":"+49 2246/7890",
    "sg:postcode":"53797",
    "sg:province":"Nordrhein-Westfalen",
    "wof:name":"G. Sch\u00f6nenbr\u00fccher Immobilienmakler",
    "wof:placetype":"venue"
},
  "geometry": {"coordinates":[7.2109642029,50.8399810791],"type":"Point"}
}