{
  "type": "Feature",
  "properties": {
    "iso:country":"DE",
    "sg:address":"Oberpfuhlstr. 3",
    "sg:city":"Lychen",
    "sg:phone":"+49 39888/2686",
    "sg:postcode":"17279",
    "sg:province":"Brandenburg",
    "wof:name":"Siegfried Glodschei",
    "wof:placetype":"venue"
},
  "geometry": {"coordinates":[13.3158721924,53.2136611938],"type":"Point"}
}