{
  "type": "Feature",
  "properties": {
    "iso:country":"DE",
    "sg:address":"Blannentalhof 1",
    "sg:city":"Weil der Stadt",
    "sg:phone":"+49 7033/32458",
    "sg:postcode":"71263",
    "sg:province":"Baden-W\u00fcrttemberg",
    "wof:name":"Werner Schindele",
    "wof:placetype":"venue"
},
  "geometry": {"coordinates":[8.861937,48.769604],"type":"Point"}
}