{
  "type": "Feature",
  "properties": {
    "iso:country":"DE",
    "sg:address":"Im L\u00f6ringhof",
    "sg:city":"Datteln",
    "sg:phone":"+49 2363/97940",
    "sg:postcode":"45711",
    "sg:province":"Nordrhein-Westfalen",
    "wof:name":"Raiffeisen Warengenossenschaft Datteln-waltrop Eg",
    "wof:placetype":"venue"
},
  "geometry": {"coordinates":[7.346126,51.637787],"type":"Point"}
}