{
  "type": "Feature",
  "properties": {
    "iso:country":"DE",
    "sg:address":"Daimlerstr. 41",
    "sg:city":"Kempten",
    "sg:phone":"+49 831/7444",
    "sg:postcode":"87437",
    "sg:province":"Bayern",
    "wof:name":"Endlos Druck Kempten Gmbh",
    "wof:placetype":"venue"
},
  "geometry": {"coordinates":[10.323216,47.763466],"type":"Point"}
}