{
  "type": "Feature",
  "properties": {
    "iso:country":"DE",
    "sg:address":"Zeppelinstr. 23a",
    "sg:city":"Herdecke",
    "sg:phone":"+49 2330/13555",
    "sg:postcode":"58313",
    "sg:province":"Nordrhein-Westfalen",
    "wof:name":"Lumpe Gesellschaft Mbh",
    "wof:placetype":"venue"
},
  "geometry": {"coordinates":[7.4373807907,51.3993453979],"type":"Point"}
}