{
  "type": "Feature",
  "properties": {
    "iso:country":"DE",
    "sg:address":"Wilhelm-Umbreit-Str. 9",
    "sg:city":"Gotha",
    "sg:postcode":"99867",
    "sg:province":"Th\u00fcringen",
    "wof:name":"Gemeindeschwesterstation",
    "wof:placetype":"venue"
},
  "geometry": {"coordinates":[10.741004,50.94437],"type":"Point"}
}