{
  "type": "Feature",
  "properties": {
    "iso:country":"DE",
    "sg:address":"Carl-Zei\u00df-Str 18",
    "sg:city":"Hemmingen",
    "sg:phone":"+49 511/47320600",
    "sg:postcode":"30966",
    "sg:province":"Niedersachsen",
    "wof:name":"Sponholtz Druckerei Gmbh",
    "wof:placetype":"venue"
},
  "geometry": {"coordinates":[9.7259750366,52.320400238],"type":"Point"}
}