{
  "type": "Feature",
  "properties": {
    "iso:country":"DE",
    "sg:address":"Springbergstr. 9",
    "sg:city":"Anr\u00f6chte",
    "sg:phone":"+49 2947/3236",
    "sg:postcode":"59609",
    "sg:province":"Nordrhein-Westfalen",
    "wof:name":"Bernhilde Borggr\u00e4fe",
    "wof:placetype":"venue"
},
  "geometry": {"coordinates":[8.2889652252,51.5697784424],"type":"Point"}
}