{
  "type": "Feature",
  "properties": {
    "iso:country":"DE",
    "sg:address":"Nordh\u00e4user Str. 8",
    "sg:city":"Ellrich",
    "sg:phone":"+49 36332/20497",
    "sg:postcode":"99755",
    "sg:province":"Th\u00fcringen",
    "wof:name":"Gebler Optik",
    "wof:placetype":"venue"
},
  "geometry": {"coordinates":[10.6652183533,51.5859260559],"type":"Point"}
}