{
  "type": "Feature",
  "properties": {
    "iso:country":"DE",
    "sg:address":"Bergfinkenweg 2",
    "sg:city":"Hamm",
    "sg:phone":"+49 2381/403074",
    "sg:postcode":"59077",
    "sg:province":"Nordrhein-Westfalen",
    "wof:name":"Kunze Gmbh",
    "wof:placetype":"venue"
},
  "geometry": {"coordinates":[7.784583,51.636196],"type":"Point"}
}