{
  "type": "Feature",
  "properties": {
    "iso:country":"DE",
    "sg:address":"Im Klauenfu\u00df 15",
    "sg:city":"Neckarsulm",
    "sg:phone":"+49 7132/2021",
    "sg:postcode":"74172",
    "sg:province":"Baden-W\u00fcrttemberg",
    "wof:name":"Gfv Immobilien- Finanzierungs- Und Versicherungsver-",
    "wof:placetype":"venue"
},
  "geometry": {"coordinates":[9.2221870422,49.1821670532],"type":"Point"}
}