{
  "type": "Feature",
  "properties": {
    "iso:country":"DE",
    "sg:address":"Friedrich-Alfred-Str. 70",
    "sg:city":"Duisburg",
    "sg:phone":"+49 2065/58833",
    "sg:postcode":"47226",
    "sg:province":"Nordrhein-Westfalen",
    "wof:name":"Baby-etage I. Thielmann Und G. Deutsch",
    "wof:placetype":"venue"
},
  "geometry": {"coordinates":[6.7158789635,51.4106788635],"type":"Point"}
}