{
  "type": "Feature",
  "properties": {
    "iso:country":"DE",
    "sg:address":"Bingstr. 4",
    "sg:city":"N\u00fcrnberg",
    "sg:phone":"+49 911/402002",
    "sg:postcode":"90480",
    "sg:province":"Bayern",
    "wof:name":"Heinz M\u00fcller Gmbh",
    "wof:placetype":"venue"
},
  "geometry": {"coordinates":[11.1287193298,49.4450645447],"type":"Point"}
}