{
  "type": "Feature",
  "properties": {
    "iso:country":"DE",
    "sg:address":"Am Markt 21",
    "sg:city":"Stadthagen",
    "sg:phone":"+49 5721/3424",
    "sg:postcode":"31655",
    "sg:province":"Niedersachsen",
    "wof:name":"Siebrecht Gmbh & Co.",
    "wof:placetype":"venue"
},
  "geometry": {"coordinates":[9.205393,52.323578],"type":"Point"}
}