{
  "type": "Feature",
  "properties": {
    "iso:country":"DE",
    "sg:address":"Mittelstr. 14",
    "sg:city":"Hagen",
    "sg:phone":"+49 2331/31483",
    "sg:postcode":"58095",
    "sg:province":"Nordrhein-Westfalen",
    "wof:name":"B\u00e4ckerei Kamm Gmbh",
    "wof:placetype":"venue"
},
  "geometry": {"coordinates":[7.475171,51.356873],"type":"Point"}
}