{
  "type": "Feature",
  "properties": {
    "iso:country":"DE",
    "sg:address":"Maingasse 12",
    "sg:city":"Sommerhausen",
    "sg:phone":"+49 9333/8158",
    "sg:postcode":"97286",
    "sg:province":"Bayern",
    "wof:name":"Weinstube Sch\u00f6nig",
    "wof:placetype":"venue"
},
  "geometry": {"coordinates":[10.0238733292,49.7051544189],"type":"Point"}
}