{
  "type": "Feature",
  "properties": {
    "iso:country":"DE",
    "sg:address":"Paschenburgstr. 68a",
    "sg:city":"Bremen",
    "sg:phone":"+49 421/445547",
    "sg:postcode":"28211",
    "sg:province":"Bremen",
    "wof:name":"Hanna Gramberg Steuerbevollm\u00e4chtigte",
    "wof:placetype":"venue"
},
  "geometry": {"coordinates":[8.8493089676,53.0784683228],"type":"Point"}
}