{
  "type": "Feature",
  "properties": {
    "iso:country":"DE",
    "sg:address":"95",
    "sg:city":"PARIS",
    "sg:postcode":"75010",
    "wof:name":"Voyance Non Stop",
    "wof:placetype":"venue"
},
  "geometry": {"coordinates":[2.354321,48.877956],"type":"Point"}
}