{
  "type": "Feature",
  "properties": {
    "iso:country":"DE",
    "sg:address":"T\u00f6pferweg 23",
    "sg:city":"Delmenhorst",
    "sg:phone":"+49 4221/808910",
    "sg:postcode":"27753",
    "sg:province":"Niedersachsen",
    "wof:name":"Jolly Deutschland Gmbh",
    "wof:placetype":"venue"
},
  "geometry": {"coordinates":[8.600244,53.058357],"type":"Point"}
}