{
  "type": "Feature",
  "properties": {
    "iso:country":"DE",
    "sg:address":"Homburger Landstr. 710",
    "sg:city":"Frankfurt",
    "sg:phone":"+49 69/5072020",
    "sg:postcode":"60437",
    "sg:province":"Hessen",
    "wof:name":"Hopf-werbung Messebau",
    "wof:placetype":"venue"
},
  "geometry": {"coordinates":[8.666647,50.188732],"type":"Point"}
}