{
  "type": "Feature",
  "properties": {
    "iso:country":"DE",
    "sg:address":"Wei\u00dfenberger Str. 1",
    "sg:city":"Hohendubrau",
    "sg:phone":"+49 35932/30751",
    "sg:postcode":"02906",
    "sg:province":"Sachsen",
    "wof:name":"Ruth Wagner",
    "wof:placetype":"venue"
},
  "geometry": {"coordinates":[14.668346,51.247822],"type":"Point"}
}