{
  "type": "Feature",
  "properties": {
    "iso:country":"DE",
    "sg:address":"Otto-Hahn-Str. 14",
    "sg:city":"Dornstetten",
    "sg:phone":"+49 4974/4396490",
    "sg:postcode":"72280",
    "sg:province":"Baden-W\u00fcrttemberg",
    "wof:name":"Eldec Schwenk Induction",
    "wof:placetype":"venue"
},
  "geometry": {"coordinates":[8.490611,48.479065],"type":"Point"}
}