{
  "type": "Feature",
  "properties": {
    "iso:country":"DE",
    "sg:address":"Hauptstr. 54",
    "sg:city":"Wiesenbach",
    "sg:phone":"+49 6223/4410",
    "sg:postcode":"69257",
    "sg:province":"Baden-W\u00fcrttemberg",
    "wof:name":"Katholisches Pfarramt St. Michael",
    "wof:placetype":"venue"
},
  "geometry": {"coordinates":[8.8082427979,49.359790802],"type":"Point"}
}