{
  "type": "Feature",
  "properties": {
    "iso:country":"DE",
    "sg:address":"Hochstr. 4",
    "sg:city":"Bad Salzuflen",
    "sg:phone":"+49 5222/59420",
    "sg:postcode":"32105",
    "sg:province":"Nordrhein-Westfalen",
    "wof:name":"Luise Bethkorsky",
    "wof:placetype":"venue"
},
  "geometry": {"coordinates":[8.7439651489,52.0850753784],"type":"Point"}
}