{
  "type": "Feature",
  "properties": {
    "iso:country":"DE",
    "sg:address":"Pellinger Str. 35",
    "sg:city":"Trier",
    "sg:phone":"+49 651/36459",
    "sg:postcode":"54294",
    "sg:province":"Rheinland-Pfalz",
    "wof:name":"E. Schreiber",
    "wof:placetype":"venue"
},
  "geometry": {"coordinates":[6.563395977,49.7421875],"type":"Point"}
}