{
  "type": "Feature",
  "properties": {
    "iso:country":"DE",
    "sg:address":"B\u00f6vinghauser Str. 62",
    "sg:city":"Dortmund",
    "sg:phone":"+49 231/691443",
    "sg:postcode":"44388",
    "sg:province":"Nordrhein-Westfalen",
    "wof:name":"Benno Dietzen",
    "wof:placetype":"venue"
},
  "geometry": {"coordinates":[7.319438,51.521458],"type":"Point"}
}