{
  "type": "Feature",
  "properties": {
    "iso:country":"DE",
    "sg:address":"B.P. 90",
    "sg:city":"MEYZIEU Cedex",
    "sg:phone":"+49 4780/41095",
    "sg:postcode":"69882",
    "wof:name":"J2r Consultants",
    "wof:placetype":"venue"
},
  "geometry": {"coordinates":[5.00365,45.766682],"type":"Point"}
}