{
  "type": "Feature",
  "properties": {
    "iso:country":"DE",
    "sg:address":"V\u00f6gnitzer Str. 5",
    "sg:city":"Sulzheim",
    "sg:phone":"+49 9382/5261",
    "sg:postcode":"97529",
    "sg:province":"Bayern",
    "wof:name":"Franz Miosga",
    "wof:placetype":"venue"
},
  "geometry": {"coordinates":[10.3681116104,49.9336357117],"type":"Point"}
}