{
  "type": "Feature",
  "properties": {
    "iso:country":"DE",
    "sg:address":"Riehler Str. 7",
    "sg:city":"K\u00f6ln",
    "sg:phone":"+49 221/7391222",
    "sg:postcode":"50668",
    "sg:province":"Nordrhein-Westfalen",
    "wof:name":"Partnerdruck Gmbh",
    "wof:placetype":"venue"
},
  "geometry": {"coordinates":[6.959325,50.951519],"type":"Point"}
}