{
  "type": "Feature",
  "properties": {
    "iso:country":"DE",
    "sg:address":"Torstr 6-8::",
    "sg:city":"Berlin",
    "sg:postcode":"10119",
    "sg:province":"Berlin",
    "wof:name":"Blb Immobilien",
    "wof:placetype":"venue"
},
  "geometry": {"coordinates":[8.804667,53.075165],"type":"Point"}
}