{
  "type": "Feature",
  "properties": {
    "iso:country":"DE",
    "sg:address":"Neusalzaer Str 32a",
    "sg:city":"Bautzen",
    "sg:phone":"+49 3591/390000",
    "sg:postcode":"02625",
    "sg:province":"Sachsen",
    "wof:name":"Alpha Lan Computer Und Netzwerke Ag",
    "wof:placetype":"venue"
},
  "geometry": {"coordinates":[14.4241123199,51.1712532043],"type":"Point"}
}