{
  "type": "Feature",
  "properties": {
    "iso:country":"DE",
    "sg:address":"Unterer Rennebaum 31",
    "sg:city":"Hofgeismar",
    "sg:phone":"+49 5671/3884",
    "sg:postcode":"34369",
    "sg:province":"Hessen",
    "wof:name":"Dr. Fritz M\u00e4hler Steuerberater",
    "wof:placetype":"venue"
},
  "geometry": {"coordinates":[9.3766536713,51.4998283386],"type":"Point"}
}