{
  "type": "Feature",
  "properties": {
    "iso:country":"DE",
    "sg:address":"Kirchplatz 5",
    "sg:city":"Arnstein",
    "sg:phone":"+49 9363/5153",
    "sg:postcode":"97450",
    "sg:province":"Bayern",
    "wof:name":"Kath. Pfarramt St. Laurentius",
    "wof:placetype":"venue"
},
  "geometry": {"coordinates":[10.0123443604,49.9668045044],"type":"Point"}
}