{
  "type": "Feature",
  "properties": {
    "iso:country":"DE",
    "sg:address":"K\u00f6lnerstr.582",
    "sg:city":"Meerbusch",
    "sg:phone":"+49 2151/301523",
    "sg:postcode":"40667",
    "sg:province":"Nordrhein-Westfalen",
    "wof:name":"Dressagehorses-agency",
    "wof:placetype":"venue"
},
  "geometry": {"coordinates":[6.691025,51.251896],"type":"Point"}
}