{
  "type": "Feature",
  "properties": {
    "iso:country":"DE",
    "sg:address":"Hauptstr. 81",
    "sg:city":"Mulda",
    "sg:phone":"+49 37320/1537",
    "sg:postcode":"09619",
    "sg:province":"Sachsen",
    "wof:name":"Joachim Kempe",
    "wof:placetype":"venue"
},
  "geometry": {"coordinates":[13.408752,50.808361],"type":"Point"}
}