{
  "type": "Feature",
  "properties": {
    "iso:country":"DE",
    "sg:address":"Feldstr. 1",
    "sg:city":"Nortrup",
    "sg:phone":"+49 5436/1808",
    "sg:postcode":"49638",
    "sg:province":"Niedersachsen",
    "wof:name":"Manfred Kahtenbrink",
    "wof:placetype":"venue"
},
  "geometry": {"coordinates":[7.853309,52.608608],"type":"Point"}
}