{
  "type": "Feature",
  "properties": {
    "iso:country":"DE",
    "sg:address":"Gewerbestr. 5",
    "sg:city":"Villingendorf",
    "sg:phone":"+49 741/33003",
    "sg:postcode":"78667",
    "sg:province":"Baden-W\u00fcrttemberg",
    "wof:name":"Sk Scheidel Kunststoffe- Glas Gmbh",
    "wof:placetype":"venue"
},
  "geometry": {"coordinates":[8.585526,48.210258],"type":"Point"}
}