{
  "type": "Feature",
  "properties": {
    "iso:country":"DE",
    "sg:address":"Beethovenstr. 14",
    "sg:city":"Hamburg",
    "sg:postcode":"22083",
    "sg:province":"Hamburg",
    "wof:name":"Dsm Interoffice Handel Gmbh",
    "wof:placetype":"venue"
},
  "geometry": {"coordinates":[10.0229415894,53.5757064819],"type":"Point"}
}