{
  "type": "Feature",
  "properties": {
    "iso:country":"DE",
    "sg:address":"Badstr. 16",
    "sg:city":"Bad Kohlgrub",
    "sg:phone":"+49 8845/9255",
    "sg:postcode":"82433",
    "sg:province":"Bayern",
    "wof:name":"Leonhard Schellinger Masseur",
    "wof:placetype":"venue"
},
  "geometry": {"coordinates":[11.043655,47.667107],"type":"Point"}
}