{
  "type": "Feature",
  "properties": {
    "iso:country":"DE",
    "sg:address":"Vorderstr. 8",
    "sg:city":"Fl\u00f6rsheim",
    "sg:phone":"+49 6145/2791",
    "sg:postcode":"65439",
    "sg:province":"Hessen",
    "wof:name":"Reinhard Allendorf",
    "wof:placetype":"venue"
},
  "geometry": {"coordinates":[8.4033460617,50.027633667],"type":"Point"}
}