{
  "type": "Feature",
  "properties": {
    "iso:country":"DE",
    "sg:address":"Sachsenbergstr. 21",
    "sg:city":"Bad Harzburg",
    "sg:phone":"+49 5322/53415",
    "sg:postcode":"38667",
    "sg:province":"Niedersachsen",
    "wof:name":"Sidney Gromnica Heilpraktiker",
    "wof:placetype":"venue"
},
  "geometry": {"coordinates":[10.5691900253,51.8821525574],"type":"Point"}
}