{
  "type": "Feature",
  "properties": {
    "iso:country":"DE",
    "sg:address":"Paddenbett 2",
    "sg:city":"Bochum",
    "sg:phone":"+49 234/332529",
    "sg:postcode":"44803",
    "sg:province":"Nordrhein-Westfalen",
    "wof:name":"Jb Jugendsparberatung Bauspar- Und Versicherungs-",
    "wof:placetype":"venue"
},
  "geometry": {"coordinates":[7.2345261574,51.4775238037],"type":"Point"}
}