{
  "type": "Feature",
  "properties": {
    "iso:country":"DE",
    "sg:address":"Neuenteich 88",
    "sg:city":"Wuppertal",
    "sg:phone":"+49 202/446066",
    "sg:postcode":"42107",
    "sg:province":"Nordrhein-Westfalen",
    "wof:name":"Christian H\u00f6rning Rechtsanwalt",
    "wof:placetype":"venue"
},
  "geometry": {"coordinates":[7.1531410217,51.2591400146],"type":"Point"}
}