{
  "type": "Feature",
  "properties": {
    "iso:country":"DE",
    "sg:address":"Hauptstr. 11",
    "sg:city":"Heidenheim",
    "sg:phone":"+49 7321/23255",
    "sg:postcode":"89522",
    "sg:province":"Baden-W\u00fcrttemberg",
    "wof:name":"K\u00f6nig Wilhelm",
    "wof:placetype":"venue"
},
  "geometry": {"coordinates":[6.570579052,49.8992156982],"type":"Point"}
}