{
  "type": "Feature",
  "properties": {
    "iso:country":"DE",
    "sg:city":"Stetten",
    "sg:phone":"+49 7573/753",
    "sg:postcode":"72510",
    "sg:province":"Baden-W\u00fcrttemberg",
    "wof:name":"Billard-cafe",
    "wof:placetype":"venue"
},
  "geometry": {"coordinates":[9.078165,48.120865],"type":"Point"}
}