{
  "type": "Feature",
  "properties": {
    "iso:country":"DE",
    "sg:address":"Chopinstr. 2",
    "sg:city":"Zittau",
    "sg:phone":"+49 3583/704119",
    "sg:postcode":"02763",
    "sg:province":"Sachsen",
    "wof:name":"Rudolf Hoffmann",
    "wof:placetype":"venue"
},
  "geometry": {"coordinates":[14.819818,50.896908],"type":"Point"}
}