{
  "type": "Feature",
  "properties": {
    "iso:country":"DE",
    "sg:address":"Niedieckstr. 16",
    "sg:city":"Nettetal",
    "sg:phone":"+49 2153/2096",
    "sg:postcode":"41334",
    "sg:province":"Nordrhein-Westfalen",
    "wof:name":"Gisela Althoff",
    "wof:placetype":"venue"
},
  "geometry": {"coordinates":[6.2764129639,51.3087730408],"type":"Point"}
}