{
  "type": "Feature",
  "properties": {
    "iso:country":"DE",
    "sg:address":"Ratsherrenstr. 91",
    "sg:city":"Melle",
    "sg:phone":"+49 5226/5132",
    "sg:postcode":"49328",
    "sg:province":"Niedersachsen",
    "wof:name":"Wilhelm Petering",
    "wof:placetype":"venue"
},
  "geometry": {"coordinates":[8.428379,52.170013],"type":"Point"}
}