{
  "type": "Feature",
  "properties": {
    "iso:country":"DE",
    "sg:address":"Prenzlauer Chaussee 132",
    "sg:city":"Wandlitz",
    "sg:phone":"+49 33397/22139",
    "sg:postcode":"16348",
    "sg:province":"Brandenburg",
    "wof:name":"Linden-apotheke E. Kfm.",
    "wof:placetype":"venue"
},
  "geometry": {"coordinates":[13.468614,52.751236],"type":"Point"}
}