{
  "type": "Feature",
  "properties": {
    "iso:country":"DE",
    "sg:address":"Horststr. 1",
    "sg:city":"Ochtrup",
    "sg:postcode":"48607",
    "sg:province":"Nordrhein-Westfalen",
    "wof:name":"E & V Gmbh",
    "wof:placetype":"venue"
},
  "geometry": {"coordinates":[7.189395,52.207329],"type":"Point"}
}