{
  "type": "Feature",
  "properties": {
    "iso:country":"DE",
    "sg:address":"Kunstgasse 11",
    "sg:city":"Altenburg",
    "sg:phone":"+49 3447/505959",
    "sg:postcode":"04600",
    "sg:province":"Th\u00fcringen",
    "wof:name":"J. Meineck Immobilienmakler",
    "wof:placetype":"venue"
},
  "geometry": {"coordinates":[12.4362392426,50.9829940796],"type":"Point"}
}