{
  "type": "Feature",
  "properties": {
    "iso:country":"DE",
    "sg:address":"Oldenburger Str. 44",
    "sg:city":"Edewecht",
    "sg:phone":"+49 4405/287",
    "sg:postcode":"26188",
    "sg:province":"Niedersachsen",
    "wof:name":"Friedrich Dierks",
    "wof:placetype":"venue"
},
  "geometry": {"coordinates":[7.9916257858,53.1255836487],"type":"Point"}
}