{
  "type": "Feature",
  "properties": {
    "iso:country":"DE",
    "sg:address":"Zw\u00f6lferweg 6",
    "sg:city":"Graben",
    "sg:postcode":"86836",
    "sg:province":"Bayern",
    "wof:name":"Eest Reisen Gmbh Reisen Und Tagungen",
    "wof:placetype":"venue"
},
  "geometry": {"coordinates":[10.8378582001,48.178855896],"type":"Point"}
}