{
  "type": "Feature",
  "properties": {
    "iso:country":"DE",
    "sg:address":"Biberacher Str.",
    "sg:city":"Oberstadion",
    "sg:postcode":"89613",
    "sg:province":"Baden-W\u00fcrttemberg",
    "wof:name":"Adler-br\u00e4u Moosbeuren Verwaltungs-gmbh",
    "wof:placetype":"venue"
},
  "geometry": {"coordinates":[9.72282,48.179966],"type":"Point"}
}