{
  "type": "Feature",
  "properties": {
    "iso:country":"DE",
    "sg:address":"Ferdinand-Lassalle-Str. 27",
    "sg:city":"Taucha",
    "sg:postcode":"04425",
    "sg:province":"Sachsen",
    "wof:name":"Dr.peter M\u00fcller",
    "wof:placetype":"venue"
},
  "geometry": {"coordinates":[12.4886274338,51.3746681213],"type":"Point"}
}