{
  "type": "Feature",
  "properties": {
    "iso:country":"DE",
    "sg:address":"Taunusstr. 75",
    "sg:city":"Wiesbaden",
    "sg:phone":"+49 611/526263",
    "sg:postcode":"65183",
    "sg:province":"Hessen",
    "wof:name":"Renate Schollmeyer Heilpraktikerin",
    "wof:placetype":"venue"
},
  "geometry": {"coordinates":[8.2379636765,50.0902023315],"type":"Point"}
}