{
  "type": "Feature",
  "properties": {
    "iso:country":"DE",
    "sg:address":"Hohe Str. 5",
    "sg:city":"Eisenberg",
    "sg:postcode":"07607",
    "sg:province":"Th\u00fcringen",
    "wof:name":"Laubenstein Decker Dachdeckermeister Gmbh",
    "wof:placetype":"venue"
},
  "geometry": {"coordinates":[11.895655,50.967499],"type":"Point"}
}