{
  "type": "Feature",
  "properties": {
    "iso:country":"DE",
    "sg:address":"Georg-Leinfelder-Str. 16",
    "sg:city":"Schrobenhausen",
    "sg:phone":"+49 8252/7124",
    "sg:postcode":"86529",
    "sg:province":"Bayern",
    "wof:name":"Stadtb\u00fccherei Hauptschule",
    "wof:placetype":"venue"
},
  "geometry": {"coordinates":[11.272053,48.558758],"type":"Point"}
}