{
  "type": "Feature",
  "properties": {
    "iso:country":"DE",
    "sg:address":"Hindenburgstr. 60",
    "sg:city":"Murr",
    "sg:postcode":"71711",
    "sg:province":"Baden-W\u00fcrttemberg",
    "wof:name":"Ortsb\u00fccherei",
    "wof:placetype":"venue"
},
  "geometry": {"coordinates":[9.258932,48.961983],"type":"Point"}
}