{
  "type": "Feature",
  "properties": {
    "iso:country":"DE",
    "sg:address":"Mei\u00dfner Landstr. 151",
    "sg:city":"Dresden",
    "sg:phone":"+49 351/4520853",
    "sg:postcode":"01157",
    "sg:province":"Sachsen",
    "wof:name":"Helmut Daniel",
    "wof:placetype":"venue"
},
  "geometry": {"coordinates":[13.656373,51.080757],"type":"Point"}
}