{
  "type": "Feature",
  "properties": {
    "iso:country":"DE",
    "sg:address":"Mommstr. 9",
    "sg:city":"St. Wendel",
    "sg:phone":"+49 6851/81359",
    "sg:postcode":"66606",
    "sg:province":"Saarland",
    "wof:name":"H. Bouillon",
    "wof:placetype":"venue"
},
  "geometry": {"coordinates":[7.1661062241,49.4675140381],"type":"Point"}
}