{
  "type": "Feature",
  "properties": {
    "iso:country":"DE",
    "sg:address":"Appelsgarten 2",
    "sg:city":"Euskirchen",
    "sg:phone":"+49 2251/181",
    "sg:postcode":"53879",
    "sg:province":"Nordrhein-Westfalen",
    "wof:name":"Fraunhofer Inst. F\u00fcr Natur- Wissensch.-techn Trendanalysen",
    "wof:placetype":"venue"
},
  "geometry": {"coordinates":[6.8064842224,50.6628913879],"type":"Point"}
}