{
  "type": "Feature",
  "properties": {
    "iso:country":"DE",
    "sg:address":"Drosselstieg 71",
    "sg:city":"Stade",
    "sg:phone":"+49 4141/86767",
    "sg:postcode":"21682",
    "sg:province":"Niedersachsen",
    "wof:name":"Bahr Baumarkt",
    "wof:placetype":"venue"
},
  "geometry": {"coordinates":[9.4231796265,53.5968360901],"type":"Point"}
}