{
  "type": "Feature",
  "properties": {
    "iso:country":"DE",
    "sg:address":"N\u00f6rdliche Ringstr. 12 a",
    "sg:city":"Schwabach",
    "sg:phone":"+49 9122/4004",
    "sg:postcode":"91126",
    "sg:province":"Bayern",
    "wof:name":"Bestattungsinstitut Denk Trauer-hilfe Gmbh",
    "wof:placetype":"venue"
},
  "geometry": {"coordinates":[11.023722,49.331715],"type":"Point"}
}