{
  "type": "Feature",
  "properties": {
    "iso:country":"DE",
    "sg:address":"Talstr. 14",
    "sg:city":"Niederaula",
    "sg:phone":"+49 6625/5842",
    "sg:postcode":"36272",
    "sg:province":"Hessen",
    "wof:name":"Hans-helmut Ochs Ingenieur",
    "wof:placetype":"venue"
},
  "geometry": {"coordinates":[9.6165370941,50.7945137024],"type":"Point"}
}