{
  "type": "Feature",
  "properties": {
    "iso:country":"DE",
    "sg:address":"Frankenstr. 17",
    "sg:city":"Maintal",
    "sg:phone":"+49 6181/82870",
    "sg:postcode":"63477",
    "sg:province":"Hessen",
    "wof:name":"Wilhelm Zell Steuerberater",
    "wof:placetype":"venue"
},
  "geometry": {"coordinates":[8.855512619,50.163269043],"type":"Point"}
}