{
  "type": "Feature",
  "properties": {
    "iso:country":"DE",
    "sg:address":"Glash\u00fctter T\u00e4le 11",
    "sg:city":"Waldenbuch",
    "sg:phone":"+49 7157/520156",
    "sg:postcode":"71111",
    "sg:province":"Baden-W\u00fcrttemberg",
    "wof:name":"Mep Me\u00df- Und Produktionstechnik Gmbh",
    "wof:placetype":"venue"
},
  "geometry": {"coordinates":[9.1531400681,48.6317443848],"type":"Point"}
}