{
  "type": "Feature",
  "properties": {
    "iso:country":"DE",
    "sg:address":"Kuseler Str. 35",
    "sg:city":"St. Wendel",
    "sg:phone":"+49 6856/233",
    "sg:postcode":"66606",
    "sg:province":"Saarland",
    "wof:name":"Georg Sollorz Elektroinstallation",
    "wof:placetype":"venue"
},
  "geometry": {"coordinates":[7.253372,49.469906],"type":"Point"}
}