{
  "type": "Feature",
  "properties": {
    "iso:country":"DE",
    "sg:address":"Bahnhofstr. 3",
    "sg:city":"Erlau",
    "sg:phone":"+49 36841/41489",
    "sg:postcode":"98553",
    "sg:province":"Th\u00fcringen",
    "wof:name":"P. Griebel Ingenieur",
    "wof:placetype":"venue"
},
  "geometry": {"coordinates":[10.7541399002,50.5430793762],"type":"Point"}
}