{
  "type": "Feature",
  "properties": {
    "iso:country":"DE",
    "sg:address":"Ballindamm 8",
    "sg:city":"Hamburg",
    "sg:phone":"+49 40/324041",
    "sg:postcode":"20095",
    "sg:province":"Hamburg",
    "wof:name":"Christoph Miller Beteiligungs- Gmbh",
    "wof:placetype":"venue"
},
  "geometry": {"coordinates":[9.999715,53.554771],"type":"Point"}
}