{
  "type": "Feature",
  "properties": {
    "iso:country":"DE",
    "sg:address":"Heddinghovener Str. 8",
    "sg:city":"Erftstadt",
    "sg:phone":"+49 2235/73040",
    "sg:postcode":"50374",
    "sg:province":"Nordrhein-Westfalen",
    "wof:name":"Werner Seybold Ingenieur",
    "wof:placetype":"venue"
},
  "geometry": {"coordinates":[6.7573437691,50.8016014099],"type":"Point"}
}