{
  "type": "Feature",
  "properties": {
    "iso:country":"DE",
    "sg:address":"Wehneltsteig 5",
    "sg:city":"Berlin",
    "sg:phone":"+49 30/3311938",
    "sg:postcode":"13629",
    "sg:province":"Berlin",
    "wof:name":"Eva Palmer",
    "wof:placetype":"venue"
},
  "geometry": {"coordinates":[13.2710313797,52.5360374451],"type":"Point"}
}