{
  "type": "Feature",
  "properties": {
    "iso:country":"DE",
    "sg:address":"Bahnhofstr. 4",
    "sg:city":"Nottuln",
    "sg:phone":"+49 2509/227",
    "sg:postcode":"48301",
    "sg:province":"Nordrhein-Westfalen",
    "wof:name":"W. H\u00fcls",
    "wof:placetype":"venue"
},
  "geometry": {"coordinates":[7.423774,51.897537],"type":"Point"}
}