{
  "type": "Feature",
  "properties": {
    "iso:country":"DE",
    "sg:address":"Tulpenweg 9",
    "sg:city":"Schwaig",
    "sg:phone":"+49 911/500497",
    "sg:postcode":"90571",
    "sg:province":"Bayern",
    "wof:name":"Herbert H\u00f6gerl",
    "wof:placetype":"venue"
},
  "geometry": {"coordinates":[11.193581,49.467987],"type":"Point"}
}