{
  "type": "Feature",
  "properties": {
    "iso:country":"DE",
    "sg:address":"Kronacher Str. 32",
    "sg:city":"Marktrodach",
    "sg:phone":"+49 9262/410",
    "sg:postcode":"96364",
    "sg:province":"Bayern",
    "wof:name":"H. Zeuhs Bauschlosserei",
    "wof:placetype":"venue"
},
  "geometry": {"coordinates":[11.407628,50.26685],"type":"Point"}
}