{
  "type": "Feature",
  "properties": {
    "iso:country":"DE",
    "sg:address":"K\u00e4the-Kollwitz-Str. 58",
    "sg:city":"Hohen Neuendorf",
    "sg:phone":"+49 3303/404271",
    "sg:postcode":"16540",
    "sg:province":"Brandenburg",
    "wof:name":"Valentina Gastst\u00e4tten Gmbh",
    "wof:placetype":"venue"
},
  "geometry": {"coordinates":[13.288704,52.669956],"type":"Point"}
}