{
  "type": "Feature",
  "properties": {
    "iso:country":"DE",
    "sg:address":"M\u00fchlstr. 15",
    "sg:city":"Leipzig",
    "sg:phone":"+49 341/2613527",
    "sg:postcode":"04317",
    "sg:province":"Sachsen",
    "wof:name":"D. Buchwald",
    "wof:placetype":"venue"
},
  "geometry": {"coordinates":[12.402885,51.330467],"type":"Point"}
}