{
  "type": "Feature",
  "properties": {
    "iso:country":"DE",
    "sg:address":"Joseph-Fraunhofer-Str. 59",
    "sg:city":"Pfaffenhofen",
    "sg:phone":"+49 8441/80870",
    "sg:postcode":"85276",
    "sg:province":"Bayern",
    "wof:name":"Loiperdinger Gmbh Mineral\u00f6l",
    "wof:placetype":"venue"
},
  "geometry": {"coordinates":[11.511174202,48.5461654663],"type":"Point"}
}