{
  "type": "Feature",
  "properties": {
    "iso:country":"DE",
    "sg:address":"M\u00f6llenstr. 34 e",
    "sg:city":"Herzfelde",
    "sg:phone":"+49 33434/71975",
    "sg:postcode":"15378",
    "sg:province":"Brandenburg",
    "wof:name":"A. Oppermann",
    "wof:placetype":"venue"
},
  "geometry": {"coordinates":[13.8457107544,52.5063934326],"type":"Point"}
}