{
  "type": "Feature",
  "properties": {
    "iso:country":"DE",
    "sg:address":"Ahauser Str. 9",
    "sg:city":"Borken",
    "sg:phone":"+49 4928/6194120",
    "sg:postcode":"46325",
    "sg:province":"Nordrhein-Westfalen",
    "wof:name":"Kolks Wilhelm Handels-gmbh",
    "wof:placetype":"venue"
},
  "geometry": {"coordinates":[6.863609,51.851048],"type":"Point"}
}