{
  "type": "Feature",
  "properties": {
    "iso:country":"DE",
    "sg:address":"Mainbr\u00fccke 7",
    "sg:city":"Altenkunstadt",
    "sg:phone":"+49 9572/3551",
    "sg:postcode":"96264",
    "sg:province":"Bayern",
    "wof:name":"Nepomuk Gmbh",
    "wof:placetype":"venue"
},
  "geometry": {"coordinates":[11.2447328568,50.1335487366],"type":"Point"}
}