{
  "type": "Feature",
  "properties": {
    "iso:country":"DE",
    "sg:address":"Blumenstr. 10 a",
    "sg:city":"Freiburg",
    "sg:phone":"+49 761/43939",
    "sg:postcode":"79111",
    "sg:province":"Baden-W\u00fcrttemberg",
    "wof:name":"Wolfgang B\u00f6hler",
    "wof:placetype":"venue"
},
  "geometry": {"coordinates":[7.8035869598,47.979549408],"type":"Point"}
}