{
  "type": "Feature",
  "properties": {
    "iso:country":"DE",
    "sg:address":"Schulstr. 6",
    "sg:city":"Schleching",
    "sg:phone":"+49 8649/275",
    "sg:postcode":"83259",
    "sg:province":"Bayern",
    "wof:name":"Michael Scheck",
    "wof:placetype":"venue"
},
  "geometry": {"coordinates":[12.393143,47.719234],"type":"Point"}
}