{
  "type": "Feature",
  "properties": {
    "iso:country":"DE",
    "sg:address":"Kaiser-Wilhelm-Ring 30",
    "sg:city":"Mainz",
    "sg:phone":"+49 6131/612100",
    "sg:postcode":"55118",
    "sg:province":"Rheinland-Pfalz",
    "wof:name":"Amp Assekuranz Management Poetini Gmbh",
    "wof:placetype":"venue"
},
  "geometry": {"coordinates":[8.2575016022,50.0042533875],"type":"Point"}
}