{
  "type": "Feature",
  "properties": {
    "iso:country":"DE",
    "sg:address":"Hochstr. 7",
    "sg:city":"Biebergem\u00fcnd",
    "sg:phone":"+49 6050/970100",
    "sg:postcode":"63599",
    "sg:province":"Hessen",
    "wof:name":"Engelbert Strau\u00df Verwaltungs Gmbh",
    "wof:placetype":"venue"
},
  "geometry": {"coordinates":[9.2832422256,50.2029190063],"type":"Point"}
}