{
  "type": "Feature",
  "properties": {
    "iso:country":"DE",
    "sg:address":"Reiherweg 71",
    "sg:city":"K\u00f6ln",
    "sg:phone":"+49 221/5802470",
    "sg:postcode":"50829",
    "sg:province":"Nordrhein-Westfalen",
    "wof:name":"S. Schneider",
    "wof:placetype":"venue"
},
  "geometry": {"coordinates":[6.8797459602,50.9594917297],"type":"Point"}
}