{
  "type": "Feature",
  "properties": {
    "iso:country":"DE",
    "sg:address":"Bahnhofstr. 38",
    "sg:city":"Hagen",
    "sg:postcode":"58095",
    "sg:province":"Nordrhein-Westfalen",
    "wof:name":"C.-j. Busatis Verwaltungs Gmbh Co Dr. Deussen",
    "wof:placetype":"venue"
},
  "geometry": {"coordinates":[7.464495,51.361034],"type":"Point"}
}