{
  "type": "Feature",
  "properties": {
    "iso:country":"DE",
    "sg:address":"Bertholdstr 7",
    "sg:city":"Teltow",
    "sg:phone":"+49 3328/300790",
    "sg:postcode":"14513",
    "sg:province":"Brandenburg",
    "wof:name":"L&c Labortechnik Gmbh",
    "wof:placetype":"venue"
},
  "geometry": {"coordinates":[13.274039,52.394581],"type":"Point"}
}