{
  "type": "Feature",
  "properties": {
    "iso:country":"DE",
    "sg:address":"Fischerei 20",
    "sg:city":"Dingolfing",
    "sg:phone":"+49 8731/4861",
    "sg:postcode":"84130",
    "sg:province":"Bayern",
    "wof:name":"M. Weniger",
    "wof:placetype":"venue"
},
  "geometry": {"coordinates":[12.495324,48.63089],"type":"Point"}
}