{
  "type": "Feature",
  "properties": {
    "iso:country":"DE",
    "sg:address":"B\u00f6ttcherkoppel 2",
    "sg:city":"Hamburg",
    "sg:phone":"+49 40",
    "sg:postcode":"21031",
    "sg:province":"Hamburg",
    "wof:name":"Dst-network - Selbst\u00e4ndige Repr\u00e4sentanz Way4me",
    "wof:placetype":"venue"
},
  "geometry": {"coordinates":[10.207026,53.498703],"type":"Point"}
}