{
  "type": "Feature",
  "properties": {
    "iso:country":"DE",
    "sg:address":"Georg-Schumann-Str. 123",
    "sg:city":"Leipzig",
    "sg:phone":"+49 341/5906067",
    "sg:postcode":"04155",
    "sg:province":"Sachsen",
    "wof:name":"R. Kulbe",
    "wof:placetype":"venue"
},
  "geometry": {"coordinates":[12.359799,51.363605],"type":"Point"}
}