{
  "type": "Feature",
  "properties": {
    "iso:country":"DE",
    "sg:address":"Gustav-Stresemann-Ring 1",
    "sg:city":"Wiesbaden",
    "sg:classifiers":[
        {
            "category":"Professional",
            "subcategory":"Computer Services",
            "type":"Services"
        }
    ],
    "sg:postcode":"65189",
    "sg:tags":[
        "network-management",
        "network-acceleration"
    ],
    "sg:website":"http://www.ipanematech.com/",
    "wof:name":"Ipanema",
    "wof:placetype":"venue"
},
  "geometry": {"coordinates":[8.246493,50.071696],"type":"Point"}
}