{
  "type": "Feature",
  "properties": {
    "iso:country":"DE",
    "sg:address":"Bahnhofplatz 1",
    "sg:city":"H\u00f6henkirchen-Siegertbrn",
    "sg:phone":"+49 8102/74280",
    "sg:postcode":"85635",
    "sg:province":"Bayern",
    "wof:name":"Guggenberger Baustoffe Gmbh",
    "wof:placetype":"venue"
},
  "geometry": {"coordinates":[11.718365,48.019176],"type":"Point"}
}