{
  "type": "Feature",
  "properties": {
    "iso:country":"DE",
    "sg:address":"Waschgrabenallee 3-5",
    "sg:city":"Neustadt",
    "sg:phone":"+49 4561/5150",
    "sg:postcode":"23730",
    "sg:province":"Schleswig-Holstein",
    "wof:name":"Deutsche Post Ag",
    "wof:placetype":"venue"
},
  "geometry": {"coordinates":[10.8850679398,54.1342926025],"type":"Point"}
}