{
  "type": "Feature",
  "properties": {
    "iso:country":"DE",
    "sg:address":"Repker Dorfstr. 3",
    "sg:city":"Dedelstorf",
    "sg:phone":"+49 5832/1894",
    "sg:postcode":"29386",
    "sg:province":"Niedersachsen",
    "wof:name":"Wilhelm Heuer",
    "wof:placetype":"venue"
},
  "geometry": {"coordinates":[10.533531,52.707645],"type":"Point"}
}