{
  "type": "Feature",
  "properties": {
    "iso:country":"DE",
    "sg:address":"Bahnhofstr. 22",
    "sg:city":"Dietmannsried",
    "sg:phone":"+49 8374/58135",
    "sg:postcode":"87463",
    "sg:province":"Bayern",
    "wof:name":"Power Control Electronic Gmbh",
    "wof:placetype":"venue"
},
  "geometry": {"coordinates":[10.2914848328,47.8121337891],"type":"Point"}
}