{
  "type": "Feature",
  "properties": {
    "iso:country":"DE",
    "sg:address":"Kirchsteigstr. 10",
    "sg:city":"Neuburg",
    "sg:phone":"+49 8283/838",
    "sg:postcode":"86476",
    "sg:province":"Bayern",
    "wof:name":"O. Schorer",
    "wof:placetype":"venue"
},
  "geometry": {"coordinates":[10.371383667,48.3118896484],"type":"Point"}
}