{
  "type": "Feature",
  "properties": {
    "iso:country":"DE",
    "sg:address":"Postfach 101452",
    "sg:city":"Neuss",
    "sg:postcode":"41414",
    "sg:province":"Nordrhein-Westfalen",
    "wof:name":"Botanischer Garten",
    "wof:placetype":"venue"
},
  "geometry": {"coordinates":[6.69528,51.198429],"type":"Point"}
}