{
  "type": "Feature",
  "properties": {
    "iso:country":"DE",
    "sg:address":"Kirchdornberger Str. 19",
    "sg:city":"Bielefeld",
    "sg:phone":"+49 521/103785",
    "sg:postcode":"33619",
    "sg:province":"Nordrhein-Westfalen",
    "wof:name":"Klaus Schwake",
    "wof:placetype":"venue"
},
  "geometry": {"coordinates":[8.440066,52.04583],"type":"Point"}
}