{
  "type": "Feature",
  "properties": {
    "iso:country":"DE",
    "sg:address":"Wertstr. 12",
    "sg:city":"Wendlingen",
    "sg:postcode":"73240",
    "sg:province":"Baden-W\u00fcrttemberg",
    "wof:name":"Grosso",
    "wof:placetype":"venue"
},
  "geometry": {"coordinates":[9.3651132584,48.6726455688],"type":"Point"}
}