{
  "type": "Feature",
  "properties": {
    "iso:country":"DE",
    "sg:address":"Ilmenauweg 9",
    "sg:city":"Seelze",
    "sg:phone":"+49 5137/3843",
    "sg:postcode":"30926",
    "sg:province":"Niedersachsen",
    "wof:name":"Alfred Hochheuser",
    "wof:placetype":"venue"
},
  "geometry": {"coordinates":[9.617545,52.376961],"type":"Point"}
}