{
  "type": "Feature",
  "properties": {
    "iso:country":"DE",
    "sg:address":"Viktoriastr. 4",
    "sg:city":"Bad Oeynhausen",
    "sg:phone":"+49 5731/22741",
    "sg:postcode":"32545",
    "sg:province":"Nordrhein-Westfalen",
    "wof:name":"Gundi Sonneck",
    "wof:placetype":"venue"
},
  "geometry": {"coordinates":[8.797109,52.203819],"type":"Point"}
}