{
  "type": "Feature",
  "properties": {
    "iso:country":"DE",
    "sg:address":"Dorotheenstr. 12",
    "sg:city":"Dresden",
    "sg:phone":"+49 351/4717737",
    "sg:postcode":"01219",
    "sg:province":"Sachsen",
    "wof:name":"Thilo Seehof",
    "wof:placetype":"venue"
},
  "geometry": {"coordinates":[13.769448,51.022804],"type":"Point"}
}