{
  "type": "Feature",
  "properties": {
    "iso:country":"DE",
    "sg:address":"Waldstr. 12",
    "sg:city":"Sengenthal",
    "sg:phone":"+49 9181/21616",
    "sg:postcode":"92369",
    "sg:province":"Bayern",
    "wof:name":"Friese Electronic Gmbh",
    "wof:placetype":"venue"
},
  "geometry": {"coordinates":[11.438126564,49.2390174866],"type":"Point"}
}