{
  "type": "Feature",
  "properties": {
    "iso:country":"DE",
    "sg:address":"Westallee 2",
    "sg:city":"Gronau",
    "sg:phone":"+49 5182/946130",
    "sg:postcode":"31028",
    "sg:province":"Niedersachsen",
    "wof:name":"D\u00f6nerstation Inh. Ahmet G\u00f6zg\u00f6ren",
    "wof:placetype":"venue"
},
  "geometry": {"coordinates":[9.7625312805,52.0839118958],"type":"Point"}
}