{
  "type": "Feature",
  "properties": {
    "iso:country":"DE",
    "sg:address":"M\u00fcnchner All 2",
    "sg:city":"Bad Reichenhall",
    "sg:phone":"+49 8651/600610",
    "sg:postcode":"83435",
    "sg:province":"Bayern",
    "wof:name":"Volksbank Eg",
    "wof:placetype":"venue"
},
  "geometry": {"coordinates":[12.883445,47.731323],"type":"Point"}
}