{
  "type": "Feature",
  "properties": {
    "iso:country":"DE",
    "sg:address":"Pappstr. 3",
    "sg:city":"Osterholz-Scharmbeck",
    "sg:phone":"+49 4791/982648",
    "sg:postcode":"27711",
    "sg:province":"Niedersachsen",
    "wof:name":"H. Staffetius",
    "wof:placetype":"venue"
},
  "geometry": {"coordinates":[8.797085762,53.2255516052],"type":"Point"}
}