{
  "type": "Feature",
  "properties": {
    "iso:country":"DE",
    "sg:address":"Ravensberger Str. 172",
    "sg:city":"Wuppertal",
    "sg:phone":"+49 202/420705",
    "sg:postcode":"42117",
    "sg:province":"Nordrhein-Westfalen",
    "wof:name":"Knetsch Gmbh",
    "wof:placetype":"venue"
},
  "geometry": {"coordinates":[7.14303,51.239342],"type":"Point"}
}