{
  "type": "Feature",
  "properties": {
    "iso:country":"DE",
    "sg:address":"Frauenrichter Str. 12",
    "sg:city":"Weiden",
    "sg:phone":"+49 961/29119",
    "sg:postcode":"92637",
    "sg:province":"Bayern",
    "wof:name":"Erich Frisch Masseur",
    "wof:placetype":"venue"
},
  "geometry": {"coordinates":[12.152919,49.673214],"type":"Point"}
}