{
  "type": "Feature",
  "properties": {
    "iso:country":"DE",
    "sg:address":"Kirchweg 1",
    "sg:city":"Sontheim",
    "sg:phone":"+49 8336/7026",
    "sg:postcode":"87776",
    "sg:province":"Bayern",
    "wof:name":"Helmut Stich",
    "wof:placetype":"venue"
},
  "geometry": {"coordinates":[10.352465,48.008736],"type":"Point"}
}