{
  "type": "Feature",
  "properties": {
    "iso:country":"DE",
    "sg:address":"Steinerne Furt 44",
    "sg:city":"Augsburg",
    "sg:postcode":"86167",
    "sg:province":"Bayern",
    "wof:name":"Carl Albani Gardinenfabrik Gmbh & Co.",
    "wof:placetype":"venue"
},
  "geometry": {"coordinates":[10.9217834473,48.39270401],"type":"Point"}
}