{
  "type": "Feature",
  "properties": {
    "iso:country":"DE",
    "sg:address":"Bahnhofstr. 11",
    "sg:city":"Emsdetten",
    "sg:phone":"+49 2572/5060",
    "sg:postcode":"48282",
    "sg:province":"Nordrhein-Westfalen",
    "wof:name":"Barbara Matzger",
    "wof:placetype":"venue"
},
  "geometry": {"coordinates":[7.530933857,52.1757583618],"type":"Point"}
}