{
  "type": "Feature",
  "properties": {
    "iso:country":"DE",
    "sg:address":"Dorstner Stra\u00dfe 29",
    "sg:city":"Herne",
    "sg:phone":"+49 4923/23",
    "sg:postcode":"44651",
    "sg:province":"Nordrhein-Westfalen",
    "wof:name":"Pms Gmbh: Electron Beam Lithography",
    "wof:placetype":"venue"
},
  "geometry": {"coordinates":[7.190261,51.514366],"type":"Point"}
}