{
  "type": "Feature",
  "properties": {
    "iso:country":"DE",
    "sg:address":"Ludwigstr. 6",
    "sg:city":"M\u00fcnchen",
    "sg:phone":"+49 89/288261",
    "sg:postcode":"80539",
    "sg:province":"Bayern",
    "wof:name":"Aeroflot Russian International",
    "wof:placetype":"venue"
},
  "geometry": {"coordinates":[11.579064,48.145439],"type":"Point"}
}