{
  "type": "Feature",
  "properties": {
    "iso:country":"DE",
    "sg:address":"M\u00fcnchener Str. 8",
    "sg:city":"Weilheim",
    "sg:phone":"+49 881/2230",
    "sg:postcode":"82362",
    "sg:province":"Bayern",
    "wof:name":"Bahnhof-apotheke",
    "wof:placetype":"venue"
},
  "geometry": {"coordinates":[11.14999,47.84267],"type":"Point"}
}