{
  "type": "Feature",
  "properties": {
    "iso:country":"DE",
    "sg:address":"Steinerstr. 2",
    "sg:city":"Waldsassen",
    "sg:phone":"+49 9632/2442",
    "sg:postcode":"95652",
    "sg:province":"Bayern",
    "wof:name":"Erwin Propst",
    "wof:placetype":"venue"
},
  "geometry": {"coordinates":[12.301767,50.003948],"type":"Point"}
}