{
  "type": "Feature",
  "properties": {
    "iso:country":"DE",
    "sg:address":"Hartmannstr. 5",
    "sg:city":"Chemnitz",
    "sg:postcode":"09111",
    "sg:province":"Sachsen",
    "wof:name":"Antares Beteiligungsges. F\u00fcr Den Mittelstand Sachsen",
    "wof:placetype":"venue"
},
  "geometry": {"coordinates":[12.917938,50.836376],"type":"Point"}
}