{
  "type": "Feature",
  "properties": {
    "iso:country":"DE",
    "sg:address":"Maimoorweg 60 B",
    "sg:city":"Hamburg",
    "sg:phone":"+49 40/6021955",
    "sg:postcode":"22179",
    "sg:province":"Hamburg",
    "wof:name":"Hwz System Consult Gesellschaft F\u00fcr Daten-",
    "wof:placetype":"venue"
},
  "geometry": {"coordinates":[10.0786104202,53.6071052551],"type":"Point"}
}