{
  "type": "Feature",
  "properties": {
    "iso:country":"DE",
    "sg:address":"Wilhelmstr. 1",
    "sg:city":"Neu-Isenburg",
    "sg:phone":"+49 6102/38574",
    "sg:postcode":"63263",
    "sg:province":"Hessen",
    "wof:name":"Neuer Haferkasten Gastronomie Gmbh",
    "wof:placetype":"venue"
},
  "geometry": {"coordinates":[8.6952199936,50.0516090393],"type":"Point"}
}