{
  "type": "Feature",
  "properties": {
    "iso:country":"DE",
    "sg:address":"S\u00fcdwestkorso 65",
    "sg:city":"Berlin",
    "sg:phone":"+49 30/8218859",
    "sg:postcode":"12161",
    "sg:province":"Berlin",
    "wof:name":"Galerie Am S\u00fcdwestkorso",
    "wof:placetype":"venue"
},
  "geometry": {"coordinates":[13.322635,52.473663],"type":"Point"}
}