{
  "type": "Feature",
  "properties": {
    "iso:country":"DE",
    "sg:address":"Siedlung 106",
    "sg:city":"Werther",
    "sg:phone":"+49 3631/600073",
    "sg:postcode":"99735",
    "sg:province":"Th\u00fcringen",
    "wof:name":"Walter Schmidt Architekt",
    "wof:placetype":"venue"
},
  "geometry": {"coordinates":[10.73873,51.47731],"type":"Point"}
}