{
  "type": "Feature",
  "properties": {
    "iso:country":"DE",
    "sg:address":"Zum Spritzenhaus 25",
    "sg:city":"Jesteburg",
    "sg:phone":"+49 4183/2101",
    "sg:postcode":"21266",
    "sg:province":"Niedersachsen",
    "wof:name":"Schreiber Transporte Gmbh & Co. Kg",
    "wof:placetype":"venue"
},
  "geometry": {"coordinates":[9.9567117691,53.3092727661],"type":"Point"}
}