{
  "type": "Feature",
  "properties": {
    "iso:country":"DE",
    "sg:address":"Kelterstr. 49",
    "sg:city":"Remseck",
    "sg:phone":"+49 7146/90513",
    "sg:postcode":"71686",
    "sg:province":"Baden-W\u00fcrttemberg",
    "wof:name":"Siegfried R\u00fctz Kameramann",
    "wof:placetype":"venue"
},
  "geometry": {"coordinates":[9.2557525635,48.8678703308],"type":"Point"}
}