{
  "type": "Feature",
  "properties": {
    "iso:country":"DE",
    "sg:address":"Wilhelm-Leuschner-Str. 35",
    "sg:city":"Ro\u00dfdorf",
    "sg:phone":"+49 6154/9507",
    "sg:postcode":"64380",
    "sg:province":"Hessen",
    "wof:name":"Fredegar Hahn",
    "wof:placetype":"venue"
},
  "geometry": {"coordinates":[8.7539577484,49.8551139832],"type":"Point"}
}