{
  "type": "Feature",
  "properties": {
    "iso:country":"DE",
    "sg:address":"Lindenstr. 4",
    "sg:city":"Vilseck",
    "sg:phone":"+49 9662/7202",
    "sg:postcode":"92249",
    "sg:province":"Bayern",
    "wof:name":"Hans-joachim Schieber",
    "wof:placetype":"venue"
},
  "geometry": {"coordinates":[11.8196754456,49.6209487915],"type":"Point"}
}