{
  "type": "Feature",
  "properties": {
    "iso:country":"DE",
    "sg:address":"Poststr. 25",
    "sg:city":"Merzig",
    "sg:phone":"+49 6861/939210",
    "sg:postcode":"66663",
    "sg:province":"Saarland",
    "wof:name":"Bayerische Hypo- Und Vereinsbank Ag",
    "wof:placetype":"venue"
},
  "geometry": {"coordinates":[6.6377339363,49.4432754517],"type":"Point"}
}