{
  "type": "Feature",
  "properties": {
    "iso:country":"DE",
    "sg:address":"Im Gewerbepark 38",
    "sg:city":"Regensburg",
    "sg:phone":"+49 941/401035",
    "sg:postcode":"93059",
    "sg:province":"Bayern",
    "wof:name":"Sixt Ag",
    "wof:placetype":"venue"
},
  "geometry": {"coordinates":[12.129535,49.032326],"type":"Point"}
}