{
  "type": "Feature",
  "properties": {
    "iso:country":"DE",
    "sg:address":"Am Markt 11",
    "sg:city":"S\u00f6gel",
    "sg:phone":"+49 5952/750",
    "sg:postcode":"49751",
    "sg:province":"Niedersachsen",
    "wof:name":"Imbi\u00df",
    "wof:placetype":"venue"
},
  "geometry": {"coordinates":[7.5213589668,52.8401260376],"type":"Point"}
}