{
  "type": "Feature",
  "properties": {
    "iso:country":"DE",
    "sg:address":"Sch\u00f6nseer Str. 8",
    "sg:city":"N\u00fcrnberg",
    "sg:phone":"+49 911/954060",
    "sg:postcode":"90482",
    "sg:province":"Bayern",
    "wof:name":"Hw Verwaltungsges. F\u00fcr Schl\u00fcsselfertigen Hochbau Mbh",
    "wof:placetype":"venue"
},
  "geometry": {"coordinates":[11.1463003159,49.4627761841],"type":"Point"}
}