{
  "type": "Feature",
  "properties": {
    "iso:country":"DE",
    "sg:address":"Wilhelm-Hauff-Str. 34",
    "sg:city":"Ha\u00dfmersheim",
    "sg:phone":"+49 6266/1353",
    "sg:postcode":"74855",
    "sg:province":"Baden-W\u00fcrttemberg",
    "wof:name":"Bosnjak Verwaltungs Gmbh",
    "wof:placetype":"venue"
},
  "geometry": {"coordinates":[9.13927,49.283833],"type":"Point"}
}