{
  "type": "Feature",
  "properties": {
    "iso:country":"DE",
    "sg:address":"Hauptstr. 19",
    "sg:city":"Aham",
    "sg:phone":"+49 8744",
    "sg:postcode":"84168",
    "sg:province":"Bayern",
    "wof:name":"Wasserinfoteam Bayern",
    "wof:placetype":"venue"
},
  "geometry": {"coordinates":[12.4669294357,48.5298461914],"type":"Point"}
}