{
  "type": "Feature",
  "properties": {
    "iso:country":"DE",
    "sg:address":"Neubergstr. 12",
    "sg:city":"Kleinwallstadt",
    "sg:phone":"+49 4960/2221333",
    "sg:postcode":"63839",
    "sg:province":"Bayern",
    "wof:name":"Axel Raab Gmbh",
    "wof:placetype":"venue"
},
  "geometry": {"coordinates":[9.1671829224,49.8736190796],"type":"Point"}
}