{
  "type": "Feature",
  "properties": {
    "iso:country":"DE",
    "sg:address":"Elsdorfer Weg 9",
    "sg:city":"K\u00f6then",
    "sg:phone":"+49 3496/554955",
    "sg:postcode":"06366",
    "sg:province":"Sachsen-Anhalt",
    "wof:name":"Rieder Gmbh",
    "wof:placetype":"venue"
},
  "geometry": {"coordinates":[11.9838066101,51.7649726868],"type":"Point"}
}