{
  "type": "Feature",
  "properties": {
    "iso:country":"DE",
    "sg:address":"G\u00f6rlitzer Str. 13",
    "sg:city":"Dresden",
    "sg:phone":"+49 351/8043585",
    "sg:postcode":"01099",
    "sg:province":"Sachsen",
    "wof:name":"Christoph Metasch",
    "wof:placetype":"venue"
},
  "geometry": {"coordinates":[13.7540493011,51.0670776367],"type":"Point"}
}