{
  "type": "Feature",
  "properties": {
    "iso:country":"DE",
    "sg:address":"Klemmestr. 46a",
    "sg:city":"Hamm",
    "sg:phone":"+49 2381/70047",
    "sg:postcode":"59075",
    "sg:province":"Nordrhein-Westfalen",
    "wof:name":"Ok-m\u00f6bel Otto Kraienhemke",
    "wof:placetype":"venue"
},
  "geometry": {"coordinates":[7.753759,51.698059],"type":"Point"}
}