{
  "type": "Feature",
  "properties": {
    "iso:country":"DE",
    "sg:address":"Oberer Thalerfeldweg 1",
    "sg:city":"Kronberg",
    "sg:phone":"+49 6173/2300",
    "sg:postcode":"61476",
    "sg:province":"Hessen",
    "wof:name":"I. Schneider Restaurator",
    "wof:placetype":"venue"
},
  "geometry": {"coordinates":[8.5066080093,50.1749420166],"type":"Point"}
}