{
  "type": "Feature",
  "properties": {
    "iso:country":"DE",
    "sg:address":"Wichernstr. 5",
    "sg:city":"Wiesbaden",
    "sg:phone":"+49 611/502841",
    "sg:postcode":"65191",
    "sg:province":"Hessen",
    "wof:name":"Fritz Baumann",
    "wof:placetype":"venue"
},
  "geometry": {"coordinates":[8.279214859,50.0812454224],"type":"Point"}
}