{
  "type": "Feature",
  "properties": {
    "iso:country":"DE",
    "sg:address":"Holzungsweg 11",
    "sg:city":"Berlin",
    "sg:phone":"+49 30/8131373",
    "sg:postcode":"14169",
    "sg:province":"Berlin",
    "wof:name":"Gudrun Gl\u00e4ser-janetzke",
    "wof:placetype":"venue"
},
  "geometry": {"coordinates":[13.2595672607,52.4528198242],"type":"Point"}
}