{
  "type": "Feature",
  "properties": {
    "iso:country":"DE",
    "sg:address":"Zehnthofgasse 1a",
    "sg:city":"Horrweiler",
    "sg:phone":"+49 6727/5442",
    "sg:postcode":"55457",
    "sg:province":"Rheinland-Pfalz",
    "wof:name":"Rainer Espenschied",
    "wof:placetype":"venue"
},
  "geometry": {"coordinates":[7.96538,49.898949],"type":"Point"}
}