{
  "type": "Feature",
  "properties": {
    "iso:country":"DE",
    "sg:address":"Am Kohlbuch 26",
    "sg:city":"T\u00e4nnesberg",
    "sg:phone":"+49 9655/391",
    "sg:postcode":"92723",
    "sg:province":"Bayern",
    "wof:name":"Erich Diermeier",
    "wof:placetype":"venue"
},
  "geometry": {"coordinates":[12.3348360062,49.5300865173],"type":"Point"}
}