{
  "type": "Feature",
  "properties": {
    "iso:country":"DE",
    "sg:address":"Irmgardstr. 15",
    "sg:city":"M\u00fcnchen",
    "sg:postcode":"81479",
    "sg:province":"Bayern",
    "wof:name":"Gvl Gesellschaft Zum Vertrieb Von Lebensmittelautomaten",
    "wof:placetype":"venue"
},
  "geometry": {"coordinates":[11.530849,48.078384],"type":"Point"}
}