{
  "type": "Feature",
  "properties": {
    "iso:country":"DE",
    "sg:address":"Cauerstr. 23",
    "sg:city":"Berlin",
    "sg:phone":"+49 30/3421903",
    "sg:postcode":"10587",
    "sg:province":"Berlin",
    "wof:name":"Sporting Langer",
    "wof:placetype":"venue"
},
  "geometry": {"coordinates":[13.3180713654,52.5186729431],"type":"Point"}
}