{
  "type": "Feature",
  "properties": {
    "iso:country":"DE",
    "sg:address":"Ernst-Kohl-Str. 19",
    "sg:city":"Weimar",
    "sg:phone":"+49 3643/903349",
    "sg:postcode":"99423",
    "sg:province":"Th\u00fcringen",
    "wof:name":"H. Dathe",
    "wof:placetype":"venue"
},
  "geometry": {"coordinates":[11.324665,50.988228],"type":"Point"}
}