{
  "type": "Feature",
  "properties": {
    "iso:country":"DE",
    "sg:address":"Auf der H\u00f6he 23",
    "sg:city":"Schwendi",
    "sg:postcode":"88477",
    "sg:province":"Baden-W\u00fcrttemberg",
    "wof:name":"Beautiful Faces Ag",
    "wof:placetype":"venue"
},
  "geometry": {"coordinates":[9.9506340027,48.1970825195],"type":"Point"}
}