{
  "type": "Feature",
  "properties": {
    "iso:country":"DE",
    "sg:address":"Schwalbensteg 30",
    "sg:city":"Schermbeck",
    "sg:phone":"+49 2853/2423",
    "sg:postcode":"46514",
    "sg:province":"Nordrhein-Westfalen",
    "wof:name":"C. Nederstigt",
    "wof:placetype":"venue"
},
  "geometry": {"coordinates":[6.79702,51.678185],"type":"Point"}
}