{
  "type": "Feature",
  "properties": {
    "iso:country":"DE",
    "sg:address":"Alte Stuttgarter Str. 4",
    "sg:city":"Stuttgart",
    "sg:phone":"+49 711/692238",
    "sg:postcode":"70195",
    "sg:province":"Baden-W\u00fcrttemberg",
    "wof:name":"Achim Sledzinski",
    "wof:placetype":"venue"
},
  "geometry": {"coordinates":[9.1249094009,48.778213501],"type":"Point"}
}