{
  "type": "Feature",
  "properties": {
    "iso:country":"DE",
    "sg:address":"Am H\u00fcnengraben 49",
    "sg:city":"Altena",
    "sg:phone":"+49 2352/260180",
    "sg:postcode":"58762",
    "sg:province":"Nordrhein-Westfalen",
    "wof:name":"Dietmar W\u00e4sche",
    "wof:placetype":"venue"
},
  "geometry": {"coordinates":[7.6632242203,51.3093338013],"type":"Point"}
}