{
  "type": "Feature",
  "properties": {
    "iso:country":"DE",
    "sg:address":"B\u00f6ken 9",
    "sg:city":"G\u00f6rmin",
    "sg:phone":"+49 39992/70224",
    "sg:postcode":"17121",
    "sg:province":"Mecklenburg-Vorpommern",
    "wof:name":"G\u00f6rminer Landwirtschafts- Betrieb Peenetal Gmbh & Co. Kg",
    "wof:placetype":"venue"
},
  "geometry": {"coordinates":[13.1282653809,53.9696807861],"type":"Point"}
}