{
  "type": "Feature",
  "properties": {
    "iso:country":"DE",
    "sg:address":"Im Kressgraben 35",
    "sg:city":"Untereisesheim",
    "sg:phone":"+49 7132/99800",
    "sg:postcode":"74257",
    "sg:province":"Baden-W\u00fcrttemberg",
    "wof:name":"Dierolf Tele-vertriebs Gmbh",
    "wof:placetype":"venue"
},
  "geometry": {"coordinates":[9.2073307037,49.2070388794],"type":"Point"}
}