{
  "type": "Feature",
  "properties": {
    "iso:country":"DE",
    "sg:address":"Haferacker 15",
    "sg:city":"Duisburg",
    "sg:phone":"+49 203/444652",
    "sg:postcode":"47137",
    "sg:province":"Nordrhein-Westfalen",
    "wof:name":"Wilhelm Wegener",
    "wof:placetype":"venue"
},
  "geometry": {"coordinates":[6.770687,51.468296],"type":"Point"}
}