{
  "type": "Feature",
  "properties": {
    "iso:country":"DE",
    "sg:address":"Rungholtstr. 4",
    "sg:city":"Westerland",
    "sg:phone":"+49 4651/24510",
    "sg:postcode":"25980",
    "sg:province":"Schleswig-Holstein",
    "wof:name":"G\u00e4stehaus Eike Eis",
    "wof:placetype":"venue"
},
  "geometry": {"coordinates":[8.3070573807,54.9034118652],"type":"Point"}
}