{
  "type": "Feature",
  "properties": {
    "iso:country":"DE",
    "sg:address":"M\u00fchlbachweg 5",
    "sg:city":"Wei\u00dfach",
    "sg:phone":"+49 8022/95056",
    "sg:postcode":"83700",
    "sg:province":"Bayern",
    "wof:name":"Adi Mayr",
    "wof:placetype":"venue"
},
  "geometry": {"coordinates":[11.7707128525,47.6932945251],"type":"Point"}
}