{
  "type": "Feature",
  "properties": {
    "iso:country":"DE",
    "sg:address":"B\u00fcchelbronn 13",
    "sg:city":"Simmozheim",
    "sg:phone":"+49 7033/2107",
    "sg:postcode":"75397",
    "sg:province":"Baden-W\u00fcrttemberg",
    "wof:name":"F. Baral",
    "wof:placetype":"venue"
},
  "geometry": {"coordinates":[8.8129329681,48.7406997681],"type":"Point"}
}