{
  "type": "Feature",
  "properties": {
    "iso:country":"DE",
    "sg:address":"Elbeallee 83",
    "sg:city":"Bielefeld",
    "sg:phone":"+49 5205/5075",
    "sg:postcode":"33689",
    "sg:province":"Nordrhein-Westfalen",
    "wof:name":"C. Kotzenberg Gmbh",
    "wof:placetype":"venue"
},
  "geometry": {"coordinates":[8.588158,51.947285],"type":"Point"}
}