{
  "type": "Feature",
  "properties": {
    "iso:country":"DE",
    "sg:address":"In den Birken 2",
    "sg:city":"Haina",
    "sg:postcode":"35114",
    "sg:province":"Hessen",
    "wof:name":"Fair-m\u00e4rkte Gmbh",
    "wof:placetype":"venue"
},
  "geometry": {"coordinates":[9.0263662338,51.0296211243],"type":"Point"}
}