{
  "type": "Feature",
  "properties": {
    "iso:country":"DE",
    "sg:address":"Hauptstr. 41",
    "sg:city":"Appenheim",
    "sg:phone":"+49 6725/95526",
    "sg:postcode":"55437",
    "sg:province":"Rheinland-Pfalz",
    "wof:name":"Andreas Neyses",
    "wof:placetype":"venue"
},
  "geometry": {"coordinates":[8.0342607498,49.928401947],"type":"Point"}
}