{
  "type": "Feature",
  "properties": {
    "iso:country":"DE",
    "sg:address":"Lagerstr. 20",
    "sg:city":"Stetten",
    "sg:phone":"+49 7573/5620",
    "sg:postcode":"72510",
    "sg:province":"Baden-W\u00fcrttemberg",
    "wof:name":"Barcarole Tanzcafe",
    "wof:placetype":"venue"
},
  "geometry": {"coordinates":[9.077852,48.124306],"type":"Point"}
}