{
  "type": "Feature",
  "properties": {
    "iso:country":"DE",
    "sg:address":"Kellenbachstr. 10",
    "sg:city":"Trossingen",
    "sg:phone":"+49 7425/5172",
    "sg:postcode":"78647",
    "sg:province":"Baden-W\u00fcrttemberg",
    "wof:name":"Gebhard Wei\u00dfhaar",
    "wof:placetype":"venue"
},
  "geometry": {"coordinates":[8.6367616653,48.05727005],"type":"Point"}
}