{
  "type": "Feature",
  "properties": {
    "iso:country":"DE",
    "sg:address":"Leuchtenbergring 20",
    "sg:city":"M\u00fcnchen",
    "sg:phone":"+49 89/4488870",
    "sg:postcode":"81677",
    "sg:province":"Bayern",
    "wof:name":"Schmidts Login Beratungsges. F\u00fcr Logistik Und Informations-",
    "wof:placetype":"venue"
},
  "geometry": {"coordinates":[11.6149578094,48.1358795166],"type":"Point"}
}