{
  "type": "Feature",
  "properties": {
    "iso:country":"DE",
    "sg:address":"Gerberstr. 7",
    "sg:city":"Achern",
    "sg:phone":"+49 7841/9495",
    "sg:postcode":"77855",
    "sg:province":"Baden-W\u00fcrttemberg",
    "wof:name":"Werner Erdrich Bauschlosserei",
    "wof:placetype":"venue"
},
  "geometry": {"coordinates":[8.0749988556,48.5974311829],"type":"Point"}
}