{
  "type": "Feature",
  "properties": {
    "iso:country":"DE",
    "sg:address":"Inselstr. 11",
    "sg:city":"Bayreuth",
    "sg:phone":"+49 921/26765",
    "sg:postcode":"95448",
    "sg:province":"Bayern",
    "wof:name":"Hans Sch\u00f6nauer",
    "wof:placetype":"venue"
},
  "geometry": {"coordinates":[11.59377,49.957077],"type":"Point"}
}