{
  "type": "Feature",
  "properties": {
    "iso:country":"DE",
    "sg:address":"Auf dem Greite 18",
    "sg:city":"G\u00f6ttingen",
    "sg:postcode":"37081",
    "sg:province":"Niedersachsen",
    "wof:name":"Dr. F. J\u00e4ger & Dr. S. Drinkuth Laborgemeinschaft Ohg",
    "wof:placetype":"venue"
},
  "geometry": {"coordinates":[9.9023160934,51.5350570679],"type":"Point"}
}