{
  "type": "Feature",
  "properties": {
    "iso:country":"DE",
    "sg:address":"Lehmgaster Str. 11",
    "sg:city":"Nortmoor",
    "sg:phone":"+49 4950/1303",
    "sg:postcode":"26845",
    "sg:province":"Niedersachsen",
    "wof:name":"Heiko Arends",
    "wof:placetype":"venue"
},
  "geometry": {"coordinates":[7.543818,53.245518],"type":"Point"}
}