{
  "type": "Feature",
  "properties": {
    "iso:country":"DE",
    "sg:address":"Leipziger Platz 1",
    "sg:city":"N\u00fcrnberg",
    "sg:phone":"+49 911/5105979",
    "sg:postcode":"90491",
    "sg:province":"Bayern",
    "wof:name":"K. Yildiz",
    "wof:placetype":"venue"
},
  "geometry": {"coordinates":[11.1030950546,49.4716796875],"type":"Point"}
}