{
  "type": "Feature",
  "properties": {
    "iso:country":"DE",
    "sg:address":"Kandelstr. 7 +9",
    "sg:city":"Sch\u00f6nwald",
    "sg:phone":"+49 7722/8665881",
    "sg:postcode":"78141",
    "sg:province":"Baden-W\u00fcrttemberg",
    "wof:name":"Hotel-restaurant An Der Sonne",
    "wof:placetype":"venue"
},
  "geometry": {"coordinates":[8.2061519623,48.1095275879],"type":"Point"}
}