{
  "type": "Feature",
  "properties": {
    "iso:country":"DE",
    "sg:address":"Friedrichstr. 14",
    "sg:city":"Rheinfelden",
    "sg:phone":"+49 7623/1074",
    "sg:postcode":"79618",
    "sg:province":"Baden-W\u00fcrttemberg",
    "wof:name":"Gerhard Hornig E. R\u00fctschle",
    "wof:placetype":"venue"
},
  "geometry": {"coordinates":[7.78962183,47.5600509644],"type":"Point"}
}