{
  "type": "Feature",
  "properties": {
    "iso:country":"DE",
    "sg:address":"M\u00fchlst\u00e4dtle 8",
    "sg:city":"Immendingen",
    "sg:phone":"+49 7462/923257",
    "sg:postcode":"78194",
    "sg:province":"Baden-W\u00fcrttemberg",
    "wof:name":"Taxi Biskup Inh. Karl Kauschinger",
    "wof:placetype":"venue"
},
  "geometry": {"coordinates":[8.7310533524,47.9438438416],"type":"Point"}
}