{
  "type": "Feature",
  "properties": {
    "iso:country":"DE",
    "sg:address":"K\u00fcchwaldring 9",
    "sg:city":"Chemnitz",
    "sg:phone":"+49 371/3302020",
    "sg:postcode":"09113",
    "sg:province":"Sachsen",
    "wof:name":"Planungsgruppe S\u00fcd Architekten Und Ingenieure Gbr",
    "wof:placetype":"venue"
},
  "geometry": {"coordinates":[12.90736866,50.8465232849],"type":"Point"}
}