{
  "type": "Feature",
  "properties": {
    "iso:country":"DE",
    "sg:address":"H\u00f6glweg 11",
    "sg:city":"Saaldorf-Surheim",
    "sg:phone":"+49 8654/670288",
    "sg:postcode":"83416",
    "sg:province":"Bayern",
    "wof:name":"Vimana Multimedia Und Musikverlag Gmbh",
    "wof:placetype":"venue"
},
  "geometry": {"coordinates":[12.9560518265,47.8736228943],"type":"Point"}
}