{
  "type": "Feature",
  "properties": {
    "iso:country":"DE",
    "sg:address":"Berger-Kreuz-Str. 25",
    "sg:city":"M\u00fcnchen",
    "sg:phone":"+49 89/494282",
    "sg:postcode":"81735",
    "sg:province":"Bayern",
    "wof:name":"Wenzel Halmel",
    "wof:placetype":"venue"
},
  "geometry": {"coordinates":[11.6259088516,48.1150398254],"type":"Point"}
}