{
  "type": "Feature",
  "properties": {
    "iso:country":"DE",
    "sg:address":"Johann-Georg-Fahr-Str. 11",
    "sg:city":"Gottmadingen",
    "sg:phone":"+49 7731/72218",
    "sg:postcode":"78244",
    "sg:province":"Baden-W\u00fcrttemberg",
    "wof:name":"Deutsche Bahn Ag",
    "wof:placetype":"venue"
},
  "geometry": {"coordinates":[8.7755498886,47.7373313904],"type":"Point"}
}