{
  "type": "Feature",
  "properties": {
    "iso:country":"DE",
    "sg:address":"Am Teichberg 7",
    "sg:city":"Hardegsen",
    "sg:phone":"+49 5505/2352",
    "sg:postcode":"37181",
    "sg:province":"Niedersachsen",
    "wof:name":"Gerd Meinecke Architekt",
    "wof:placetype":"venue"
},
  "geometry": {"coordinates":[9.826555,51.64772],"type":"Point"}
}