{
  "type": "Feature",
  "properties": {
    "iso:country":"DE",
    "sg:address":"Weizengrund 10",
    "sg:city":"Magdeburg",
    "sg:phone":"+49 391/7270235",
    "sg:postcode":"39130",
    "sg:province":"Sachsen-Anhalt",
    "wof:name":"Pension Winkelmann",
    "wof:placetype":"venue"
},
  "geometry": {"coordinates":[11.5718393326,52.1544799805],"type":"Point"}
}