{
  "type": "Feature",
  "properties": {
    "iso:country":"DE",
    "sg:address":"Im Westfeld 1",
    "sg:city":"Nienhagen",
    "sg:phone":"+49 5144/684",
    "sg:postcode":"29336",
    "sg:province":"Niedersachsen",
    "wof:name":"K\u00fcbek-betonwaren Gmbh",
    "wof:placetype":"venue"
},
  "geometry": {"coordinates":[10.0792341232,52.5606956482],"type":"Point"}
}