{
  "type": "Feature",
  "properties": {
    "iso:country":"DE",
    "sg:address":"Altenritter Str. 41",
    "sg:city":"Baunatal",
    "sg:phone":"+49 561/4913538",
    "sg:postcode":"34225",
    "sg:province":"Hessen",
    "wof:name":"Saunaland Sonnenstudio Im Freizeitbad Massage Praxis",
    "wof:placetype":"venue"
},
  "geometry": {"coordinates":[9.4051866531,51.2590560913],"type":"Point"}
}