{
  "type": "Feature",
  "properties": {
    "iso:country":"DE",
    "sg:address":"Hollerstr. 34-58",
    "sg:city":"B\u00fcdelsdorf",
    "sg:postcode":"24782",
    "sg:province":"Schleswig-Holstein",
    "wof:name":"Hallo Wochenbl\u00e4tter Gmbh",
    "wof:placetype":"venue"
},
  "geometry": {"coordinates":[9.6678190231,54.3128662109],"type":"Point"}
}