{
  "type": "Feature",
  "properties": {
    "iso:country":"DE",
    "sg:address":"Auguste-Viktoria-Str. 65",
    "sg:city":"Berlin",
    "sg:phone":"+49 30/8259055",
    "sg:postcode":"14199",
    "sg:province":"Berlin",
    "wof:name":"Astrid Lipps Rechtsanw\u00e4ltin",
    "wof:placetype":"venue"
},
  "geometry": {"coordinates":[13.288728714,52.480342865],"type":"Point"}
}