{
  "type": "Feature",
  "properties": {
    "iso:country":"DE",
    "sg:address":"Stra\u00dfe der Einheit 102",
    "sg:city":"Falkensee",
    "sg:phone":"+49 3322/237210",
    "sg:postcode":"14612",
    "sg:province":"Brandenburg",
    "wof:name":"Griechisches Restaurant Karyaktis",
    "wof:placetype":"venue"
},
  "geometry": {"coordinates":[13.0968561172,52.5530776978],"type":"Point"}
}