{
  "type": "Feature",
  "properties": {
    "iso:country":"DE",
    "sg:address":"B\u00fchlertalstr. 42",
    "sg:city":"B\u00fchl",
    "sg:phone":"+49 7223/3313",
    "sg:postcode":"77815",
    "sg:province":"Baden-W\u00fcrttemberg",
    "wof:name":"Taverna-pizzeria Saloniki",
    "wof:placetype":"venue"
},
  "geometry": {"coordinates":[8.1424455643,48.6939125061],"type":"Point"}
}