{
  "type": "Feature",
  "properties": {
    "iso:country":"DE",
    "sg:address":"Falkenweg 9",
    "sg:city":"Herbrechtingen",
    "sg:phone":"+49 7324/2213",
    "sg:postcode":"89542",
    "sg:province":"Baden-W\u00fcrttemberg",
    "wof:name":"Franz Huber",
    "wof:placetype":"venue"
},
  "geometry": {"coordinates":[10.1766738892,48.6256103516],"type":"Point"}
}