{
  "type": "Feature",
  "properties": {
    "iso:country":"DE",
    "sg:address":"Weilbrunnstr. 14",
    "sg:city":"Frankfurt",
    "sg:phone":"+49 69/549252",
    "sg:postcode":"60435",
    "sg:province":"Hessen",
    "wof:name":"Ludwig Boss Ingenieur",
    "wof:placetype":"venue"
},
  "geometry": {"coordinates":[8.6935863495,50.1546669006],"type":"Point"}
}