{
  "type": "Feature",
  "properties": {
    "iso:country":"DE",
    "sg:address":"Osnabr\u00fccker Str. 123",
    "sg:city":"Ibbenb\u00fcren",
    "sg:phone":"+49 5451/16009",
    "sg:postcode":"49477",
    "sg:province":"Nordrhein-Westfalen",
    "wof:name":"Grillmaster Kostas Karakasidis",
    "wof:placetype":"venue"
},
  "geometry": {"coordinates":[7.7314548492,52.2877807617],"type":"Point"}
}