{
  "type": "Feature",
  "properties": {
    "iso:country":"DE",
    "sg:address":"Strandweg 9",
    "sg:city":"L\u00fctjensee",
    "sg:postcode":"22952",
    "sg:province":"Schleswig-Holstein",
    "wof:name":"Alpha-ypsilon Marketing Gmbh",
    "wof:placetype":"venue"
},
  "geometry": {"coordinates":[10.3717079163,53.6353988647],"type":"Point"}
}