{
  "type": "Feature",
  "properties": {
    "iso:country":"DE",
    "sg:address":"Overwegstr. 15",
    "sg:city":"Iserlohn",
    "sg:phone":"+49 2374/15251",
    "sg:postcode":"58642",
    "sg:province":"Nordrhein-Westfalen",
    "wof:name":"M. Bussmann",
    "wof:placetype":"venue"
},
  "geometry": {"coordinates":[7.614447,51.365807],"type":"Point"}
}