{
  "type": "Feature",
  "properties": {
    "iso:country":"DE",
    "sg:address":"An der G\u00f6pelskuppe 1",
    "sg:city":"Eisenach",
    "sg:postcode":"99817",
    "sg:province":"Th\u00fcringen",
    "wof:name":"Berghotel Burschenhaus Gmbh",
    "wof:placetype":"venue"
},
  "geometry": {"coordinates":[10.3342447281,50.9664726257],"type":"Point"}
}