{
  "type": "Feature",
  "properties": {
    "iso:country":"DE",
    "sg:address":"Rohrackerstr. 283",
    "sg:city":"Stuttgart",
    "sg:phone":"+49 711/425916",
    "sg:postcode":"70329",
    "sg:province":"Baden-W\u00fcrttemberg",
    "wof:name":"Rainer Mischke",
    "wof:placetype":"venue"
},
  "geometry": {"coordinates":[9.238418,48.757973],"type":"Point"}
}