{
  "type": "Feature",
  "properties": {
    "iso:country":"DE",
    "sg:address":"Juliusplatz 1",
    "sg:city":"Aichach",
    "sg:phone":"+49 8251/9010",
    "sg:postcode":"86551",
    "sg:province":"Bayern",
    "wof:name":"Julius Zorn Gmbh",
    "wof:placetype":"venue"
},
  "geometry": {"coordinates":[11.1349506378,48.4465904236],"type":"Point"}
}