{
  "type": "Feature",
  "properties": {
    "iso:country":"DE",
    "sg:address":"R\u00f6merstr. 8",
    "sg:city":"Leiwen",
    "sg:phone":"+49 6507/3372",
    "sg:postcode":"54340",
    "sg:province":"Rheinland-Pfalz",
    "wof:name":"Theo Schweicher",
    "wof:placetype":"venue"
},
  "geometry": {"coordinates":[6.8814949989,49.8213310242],"type":"Point"}
}