{
  "type": "Feature",
  "properties": {
    "iso:country":"DE",
    "sg:address":"Im Br\u00fchl 21",
    "sg:city":"Bosenbach",
    "sg:phone":"+49 6385/6408",
    "sg:postcode":"66887",
    "sg:province":"Rheinland-Pfalz",
    "wof:name":"Erich Sch\u00fcler",
    "wof:placetype":"venue"
},
  "geometry": {"coordinates":[7.4939107895,49.5423278809],"type":"Point"}
}