{
  "type": "Feature",
  "properties": {
    "iso:country":"DE",
    "sg:address":"Auer Weg 1-4",
    "sg:city":"Schmalkalden",
    "sg:phone":"+49 3683/62230",
    "sg:postcode":"98574",
    "sg:province":"Th\u00fcringen",
    "wof:name":"Herda-lebensmitteltechnik Gmbh",
    "wof:placetype":"venue"
},
  "geometry": {"coordinates":[10.441015,50.719604],"type":"Point"}
}