{
  "type": "Feature",
  "properties": {
    "iso:country":"DE",
    "sg:address":"Cheruskerstr. 2",
    "sg:city":"Dortmund",
    "sg:phone":"+49 231/424483",
    "sg:postcode":"44263",
    "sg:province":"Nordrhein-Westfalen",
    "wof:name":"Andrea Worch Rechtsanw\u00e4ltin",
    "wof:placetype":"venue"
},
  "geometry": {"coordinates":[7.4947099686,51.4840240479],"type":"Point"}
}