{
  "type": "Feature",
  "properties": {
    "iso:country":"DE",
    "sg:address":"Talstr. 7",
    "sg:city":"Sinsheim",
    "sg:phone":"+49 7261/3821",
    "sg:postcode":"74889",
    "sg:province":"Baden-W\u00fcrttemberg",
    "wof:name":"W. Guttmann",
    "wof:placetype":"venue"
},
  "geometry": {"coordinates":[8.8361196518,49.2412261963],"type":"Point"}
}