{
  "type": "Feature",
  "properties": {
    "iso:country":"DE",
    "sg:address":"Hauptstr. 61",
    "sg:city":"Gaggenau",
    "sg:phone":"+49 7225/74803",
    "sg:postcode":"76571",
    "sg:province":"Baden-W\u00fcrttemberg",
    "wof:name":"Hvm Gmbh",
    "wof:placetype":"venue"
},
  "geometry": {"coordinates":[8.319773674,48.8033943176],"type":"Point"}
}