{
  "type": "Feature",
  "properties": {
    "iso:country":"DE",
    "sg:address":"Liedolsheimer Weg 7",
    "sg:city":"Eggenstein-Leopoldshafen",
    "sg:phone":"+49 7247/22673",
    "sg:postcode":"76344",
    "sg:province":"Baden-W\u00fcrttemberg",
    "wof:name":"Prof. Dr. Michael Friedrich",
    "wof:placetype":"venue"
},
  "geometry": {"coordinates":[8.4070606232,49.1009750366],"type":"Point"}
}