{
  "type": "Feature",
  "properties": {
    "iso:country":"DE",
    "sg:address":"Grunerstr. 26",
    "sg:city":"Idstein",
    "sg:phone":"+49 6126/53965",
    "sg:postcode":"65510",
    "sg:province":"Hessen",
    "wof:name":"D & H Tischlerei Gmbh",
    "wof:placetype":"venue"
},
  "geometry": {"coordinates":[8.267294,50.215763],"type":"Point"}
}