{
  "type": "Feature",
  "properties": {
    "iso:country":"DE",
    "sg:address":"In der Steinwiese 22",
    "sg:city":"Siegen",
    "sg:phone":"+49 271/65165",
    "sg:postcode":"57074",
    "sg:province":"Nordrhein-Westfalen",
    "wof:name":"Gellert",
    "wof:placetype":"venue"
},
  "geometry": {"coordinates":[8.0714769363,50.8689422607],"type":"Point"}
}