{
  "type": "Feature",
  "properties": {
    "iso:country":"DE",
    "sg:address":"Martinsbuch 1",
    "sg:city":"Mengkofen",
    "sg:phone":"+49 8733/790",
    "sg:postcode":"84152",
    "sg:province":"Bayern",
    "wof:name":"Kath. Pfarramt St. Martin",
    "wof:placetype":"venue"
},
  "geometry": {"coordinates":[12.4309091568,48.7652282715],"type":"Point"}
}