{
  "type": "Feature",
  "properties": {
    "iso:country":"DE",
    "sg:address":"Kapellenweg 7",
    "sg:city":"Reichshof-Sinspert",
    "sg:phone":"+49 2265/385",
    "sg:postcode":"51580",
    "sg:province":"Nordrhein-Westfalen",
    "wof:name":"Elektro Team Ohletz Inh. Thomas Woldt",
    "wof:placetype":"venue"
},
  "geometry": {"coordinates":[7.7772049904,50.9599494934],"type":"Point"}
}