{
  "type": "Feature",
  "properties": {
    "iso:country":"DE",
    "sg:address":"Neuer Markt 11",
    "sg:city":"Meckenheim",
    "sg:phone":"+49 2225/12555",
    "sg:postcode":"53340",
    "sg:province":"Nordrhein-Westfalen",
    "wof:name":"Markt-apotheke",
    "wof:placetype":"venue"
},
  "geometry": {"coordinates":[7.0397,50.625481],"type":"Point"}
}