{
  "type": "Feature",
  "properties": {
    "iso:country":"DE",
    "sg:address":"L\u00fcbbenauer Weg 48",
    "sg:city":"Berlin",
    "sg:phone":"+49 30/6758360",
    "sg:postcode":"12527",
    "sg:province":"Berlin",
    "wof:name":"Dipl.hist. Eberhard Herzog",
    "wof:placetype":"venue"
},
  "geometry": {"coordinates":[13.6310472488,52.3906517029],"type":"Point"}
}