{
  "type": "Feature",
  "properties": {
    "iso:country":"DE",
    "sg:address":"St. T\u00f6niser Str. 124",
    "sg:city":"Krefeld",
    "sg:phone":"+49 2151/980",
    "sg:postcode":"47804",
    "sg:province":"Nordrhein-Westfalen",
    "wof:name":"Swk",
    "wof:placetype":"venue"
},
  "geometry": {"coordinates":[6.538496,51.329128],"type":"Point"}
}