{
  "type": "Feature",
  "properties": {
    "iso:country":"DE",
    "sg:address":"Am Kampe 79",
    "sg:city":"Barnstorf",
    "sg:phone":"+49 5442/2101",
    "sg:postcode":"49406",
    "sg:province":"Niedersachsen",
    "wof:name":"Leo Schmidt",
    "wof:placetype":"venue"
},
  "geometry": {"coordinates":[8.523167,52.71637],"type":"Point"}
}