{
  "type": "Feature",
  "properties": {
    "iso:country":"DE",
    "sg:address":"K\u00e4rntener Str. 8",
    "sg:city":"Berlin",
    "sg:phone":"+49 30/7822803",
    "sg:postcode":"10827",
    "sg:province":"Berlin",
    "wof:name":"Neuer B\u00e4cker-verlag Gmbh",
    "wof:placetype":"venue"
},
  "geometry": {"coordinates":[13.347372,52.479301],"type":"Point"}
}