{
  "type": "Feature",
  "properties": {
    "iso:country":"DE",
    "sg:address":"Gleiwitzer Str. 4",
    "sg:city":"Ingolstadt",
    "sg:phone":"+49 841/65363",
    "sg:postcode":"85053",
    "sg:province":"Bayern",
    "wof:name":"Ing. Manfred Kahlert Architekt",
    "wof:placetype":"venue"
},
  "geometry": {"coordinates":[11.447134,48.760765],"type":"Point"}
}