{
  "type": "Feature",
  "properties": {
    "iso:country":"DE",
    "sg:address":"Akazienweg 6",
    "sg:city":"Fr\u00f6ndenberg",
    "sg:phone":"+49 2373/70177",
    "sg:postcode":"58730",
    "sg:province":"Nordrhein-Westfalen",
    "wof:name":"Weyler & Co. Inh. Lothar Kr\u00f6ll",
    "wof:placetype":"venue"
},
  "geometry": {"coordinates":[7.758975029,51.4770088196],"type":"Point"}
}