{
  "type": "Feature",
  "properties": {
    "iso:country":"DE",
    "sg:address":"Berliner Str. 3",
    "sg:city":"Bad M\u00fcnster-Ebernburg",
    "sg:phone":"+49 6708/1213",
    "sg:postcode":"55583",
    "sg:province":"Rheinland-Pfalz",
    "wof:name":"Kl\u00e4rle Schmidt",
    "wof:placetype":"venue"
},
  "geometry": {"coordinates":[7.849052906,49.8143043518],"type":"Point"}
}