{
  "type": "Feature",
  "properties": {
    "iso:country":"DE",
    "sg:address":"Poststr. 8",
    "sg:city":"S\u00f6mmerda",
    "sg:phone":"+49 3634/38438",
    "sg:postcode":"99610",
    "sg:province":"Th\u00fcringen",
    "wof:name":"S. Kanzler",
    "wof:placetype":"venue"
},
  "geometry": {"coordinates":[11.1218900681,51.1637458801],"type":"Point"}
}