{
  "type": "Feature",
  "properties": {
    "iso:country":"DE",
    "sg:address":"Freiberger Str. 55",
    "sg:city":"Frankenberg",
    "sg:phone":"+49 37206/2332",
    "sg:postcode":"09669",
    "sg:province":"Sachsen",
    "wof:name":"Bohlen Elektrow\u00e4rme",
    "wof:placetype":"venue"
},
  "geometry": {"coordinates":[13.0338907242,50.9109611511],"type":"Point"}
}