{
  "type": "Feature",
  "properties": {
    "iso:country":"DE",
    "sg:address":"Gr\u00fcntalstr. 4",
    "sg:city":"Todtmoos",
    "sg:phone":"+49 7674/8724",
    "sg:postcode":"79682",
    "sg:province":"Baden-W\u00fcrttemberg",
    "wof:name":"Gerd Thienger",
    "wof:placetype":"venue"
},
  "geometry": {"coordinates":[8.002186,47.741802],"type":"Point"}
}