{
  "type": "Feature",
  "properties": {
    "iso:country":"DE",
    "sg:address":"Zittelstr. 12",
    "sg:city":"M\u00fcnchen",
    "sg:phone":"+49 89/3006228",
    "sg:postcode":"80796",
    "sg:province":"Bayern",
    "wof:name":"Gerhard Metz Patentanwalt",
    "wof:placetype":"venue"
},
  "geometry": {"coordinates":[11.5734453201,48.1616325378],"type":"Point"}
}