{
  "type": "Feature",
  "properties": {
    "iso:country":"DE",
    "sg:address":"Gartenweg 13",
    "sg:city":"Unterkaka",
    "sg:phone":"+49 3445/76510",
    "sg:postcode":"06721",
    "sg:province":"Sachsen-Anhalt",
    "wof:name":"Lidl Niederlassung Unterkaka",
    "wof:placetype":"venue"
},
  "geometry": {"coordinates":[11.9399995804,51.0777511597],"type":"Point"}
}