{
  "type": "Feature",
  "properties": {
    "iso:country":"DE",
    "sg:address":"Leukersdorfer Str. 55",
    "sg:city":"Jahnsdorf",
    "sg:phone":"+49 3721/880037",
    "sg:postcode":"09387",
    "sg:province":"Sachsen",
    "wof:name":"S. Kunz",
    "wof:placetype":"venue"
},
  "geometry": {"coordinates":[12.8578796387,50.7566604614],"type":"Point"}
}