{
  "type": "Feature",
  "properties": {
    "iso:country":"DE",
    "sg:address":"Bankstr. 2",
    "sg:city":"D\u00fcsseldorf",
    "sg:postcode":"40476",
    "sg:province":"Nordrhein-Westfalen",
    "wof:name":"Unimex Chemisch- Technische Produkte Handelsges. Mbh",
    "wof:placetype":"venue"
},
  "geometry": {"coordinates":[6.773397,51.242683],"type":"Point"}
}