{
  "type": "Feature",
  "properties": {
    "iso:country":"DE",
    "sg:address":"Flensburger Str. 86",
    "sg:city":"Schleswig",
    "sg:phone":"+49 4621/25838",
    "sg:postcode":"24837",
    "sg:province":"Schleswig-Holstein",
    "wof:name":"Bp Tankstelle",
    "wof:placetype":"venue"
},
  "geometry": {"coordinates":[9.5426635742,54.5239753723],"type":"Point"}
}