{
  "type": "Feature",
  "properties": {
    "iso:country":"DE",
    "sg:address":"Hochstr. 16a",
    "sg:city":"Leichlingen",
    "sg:phone":"+49 2175/90251",
    "sg:postcode":"42799",
    "sg:province":"Nordrhein-Westfalen",
    "wof:name":"Egbert Mainzer Grabdenkm\u00e4ler",
    "wof:placetype":"venue"
},
  "geometry": {"coordinates":[7.0019640923,51.1074104309],"type":"Point"}
}