{
  "type": "Feature",
  "properties": {
    "iso:country":"DE",
    "sg:address":"Moerser Str. 17",
    "sg:city":"Kamp-Lintfort",
    "sg:phone":"+49 2842/2148",
    "sg:postcode":"47475",
    "sg:province":"Nordrhein-Westfalen",
    "wof:name":"Ferdinand Beck Gmbh",
    "wof:placetype":"venue"
},
  "geometry": {"coordinates":[6.52718,51.504219],"type":"Point"}
}