{
  "type": "Feature",
  "properties": {
    "iso:country":"DE",
    "sg:address":"Pfarrer-Haus-Str. 7",
    "sg:city":"Ginsheim-Gustavsburg",
    "sg:phone":"+49 6134/564872",
    "sg:postcode":"65462",
    "sg:province":"Hessen",
    "wof:name":"G\u00fcnther Schmitt",
    "wof:placetype":"venue"
},
  "geometry": {"coordinates":[8.3224868774,49.9953575134],"type":"Point"}
}