{
  "type": "Feature",
  "properties": {
    "iso:country":"DE",
    "sg:address":"Kornmarkt 1",
    "sg:city":"Osterode",
    "sg:phone":"+49 5522/920730",
    "sg:postcode":"37520",
    "sg:province":"Niedersachsen",
    "wof:name":"Weber Am Markt Gmbh & Co. Kg",
    "wof:placetype":"venue"
},
  "geometry": {"coordinates":[10.251052,51.727688],"type":"Point"}
}