{
  "type": "Feature",
  "properties": {
    "iso:country":"DE",
    "sg:address":"Glonner Str. 12",
    "sg:city":"Baiern",
    "sg:phone":"+49 8093/1442",
    "sg:postcode":"85625",
    "sg:province":"Bayern",
    "wof:name":"Katholisches Pfarramt St. Jakobus",
    "wof:placetype":"venue"
},
  "geometry": {"coordinates":[11.9142856598,47.9521942139],"type":"Point"}
}