{
  "type": "Feature",
  "properties": {
    "iso:country":"DE",
    "sg:address":"H\u00f6lker Weg 9",
    "sg:city":"B\u00f6sel",
    "sg:phone":"+49 4494/8331",
    "sg:postcode":"26219",
    "sg:province":"Niedersachsen",
    "wof:name":"H. Hempen",
    "wof:placetype":"venue"
},
  "geometry": {"coordinates":[7.9567279816,53.0039825439],"type":"Point"}
}