{
  "type": "Feature",
  "properties": {
    "iso:country":"DE",
    "sg:address":"Lilienstr. 10 a",
    "sg:city":"Oberasbach",
    "sg:phone":"+49 911/969910",
    "sg:postcode":"90522",
    "sg:province":"Bayern",
    "wof:name":"Georg Ramsteck",
    "wof:placetype":"venue"
},
  "geometry": {"coordinates":[10.984933,49.41991],"type":"Point"}
}