{
  "type": "Feature",
  "properties": {
    "iso:country":"DE",
    "sg:address":"Kornweg 7",
    "sg:city":"L\u00f6hne",
    "sg:phone":"+49 5732/12304",
    "sg:postcode":"32584",
    "sg:province":"Nordrhein-Westfalen",
    "wof:name":"J\u00fcrgen Freyer",
    "wof:placetype":"venue"
},
  "geometry": {"coordinates":[8.679842,52.207783],"type":"Point"}
}