{
  "type": "Feature",
  "properties": {
    "iso:country":"DE",
    "sg:address":"Moorstr. 20",
    "sg:city":"Walsrode",
    "sg:phone":"+49 5161/609883",
    "sg:postcode":"29664",
    "sg:province":"Niedersachsen",
    "wof:name":"Balkanrestaurant",
    "wof:placetype":"venue"
},
  "geometry": {"coordinates":[9.593919754,52.8618507385],"type":"Point"}
}