{
  "type": "Feature",
  "properties": {
    "iso:country":"DE",
    "sg:address":"Paulinstr. 63",
    "sg:city":"Trier",
    "sg:phone":"+49 651/9910420",
    "sg:postcode":"54292",
    "sg:province":"Rheinland-Pfalz",
    "wof:name":"Hobby-rc-welt",
    "wof:placetype":"venue"
},
  "geometry": {"coordinates":[6.648874,49.762562],"type":"Point"}
}