{
  "type": "Feature",
  "properties": {
    "iso:country":"DE",
    "sg:address":"Seilerbahn 2",
    "sg:city":"Hofheim",
    "sg:phone":"+49 6192/6045",
    "sg:postcode":"65719",
    "sg:province":"Hessen",
    "wof:name":"Herbert Dehler Steuerberater",
    "wof:placetype":"venue"
},
  "geometry": {"coordinates":[8.4093503952,50.094039917],"type":"Point"}
}