{
  "type": "Feature",
  "properties": {
    "iso:country":"DE",
    "sg:address":"Albblickstr. 17",
    "sg:city":"Ofterdingen",
    "sg:phone":"+49 7473/7913",
    "sg:postcode":"72131",
    "sg:province":"Baden-W\u00fcrttemberg",
    "wof:name":"J. Bieder Heilpraktiker",
    "wof:placetype":"venue"
},
  "geometry": {"coordinates":[9.0196304321,48.4225387573],"type":"Point"}
}