{
  "type": "Feature",
  "properties": {
    "iso:country":"DE",
    "sg:address":"Am Zentbuckel 11",
    "sg:city":"Lindenfels",
    "sg:phone":"+49 6255/630",
    "sg:postcode":"64678",
    "sg:province":"Hessen",
    "wof:name":"Terrassencamping Schlierbach",
    "wof:placetype":"venue"
},
  "geometry": {"coordinates":[8.769932,49.681953],"type":"Point"}
}