{
  "type": "Feature",
  "properties": {
    "iso:country":"DE",
    "sg:address":"Schulstr. 40",
    "sg:city":"Hemer",
    "sg:phone":"+49 2372/4269",
    "sg:postcode":"58675",
    "sg:province":"Nordrhein-Westfalen",
    "wof:name":"Hubert Potthoff Steuerberater",
    "wof:placetype":"venue"
},
  "geometry": {"coordinates":[7.7596588135,51.3718223572],"type":"Point"}
}