{
  "type": "Feature",
  "properties": {
    "iso:country":"DE",
    "sg:address":"Schmittmannstr. 12",
    "sg:city":"K\u00f6ln",
    "sg:postcode":"50935",
    "sg:province":"Nordrhein-Westfalen",
    "wof:name":"Kivi K\u00f6lner Institut F\u00fcr Versicherungsinformation Gmbh",
    "wof:placetype":"venue"
},
  "geometry": {"coordinates":[6.895595,50.918781],"type":"Point"}
}