{
  "type": "Feature",
  "properties": {
    "iso:country":"DE",
    "sg:address":"Dahlhausener Str. 4",
    "sg:city":"Windeck",
    "sg:phone":"+49 2292/7026",
    "sg:postcode":"51570",
    "sg:province":"Nordrhein-Westfalen",
    "wof:name":"Gerd B\u00f6cking",
    "wof:placetype":"venue"
},
  "geometry": {"coordinates":[7.5738549232,50.8108634949],"type":"Point"}
}