{
  "type": "Feature",
  "properties": {
    "iso:country":"DE",
    "sg:address":"Saarlandstr. 131",
    "sg:city":"Ludwigshafen",
    "sg:phone":"+49 621/582898",
    "sg:postcode":"67061",
    "sg:province":"Rheinland-Pfalz",
    "wof:name":"B\u00f6rner Gmbh & Co. Kg",
    "wof:placetype":"venue"
},
  "geometry": {"coordinates":[8.438842,49.471889],"type":"Point"}
}