{
  "type": "Feature",
  "properties": {
    "iso:country":"DE",
    "sg:address":"Akazienstr. 3",
    "sg:city":"Sulingen",
    "sg:phone":"+49 4271/2597",
    "sg:postcode":"27232",
    "sg:province":"Niedersachsen",
    "wof:name":"Helmut Symkenberg",
    "wof:placetype":"venue"
},
  "geometry": {"coordinates":[8.824892,52.681293],"type":"Point"}
}