{
  "type": "Feature",
  "properties": {
    "iso:country":"DE",
    "sg:address":"Sauerweg 13",
    "sg:city":"Stuttgart",
    "sg:phone":"+49 711/6787455",
    "sg:postcode":"70563",
    "sg:province":"Baden-W\u00fcrttemberg",
    "wof:name":"Sch\u00f6n Gmbh",
    "wof:placetype":"venue"
},
  "geometry": {"coordinates":[9.1035633087,48.7359390259],"type":"Point"}
}