{
  "type": "Feature",
  "properties": {
    "iso:country":"DE",
    "sg:address":"Lorenz-Stumpf-Str. 11",
    "sg:city":"Nordhalben",
    "sg:phone":"+49 9267/224",
    "sg:postcode":"96365",
    "sg:province":"Bayern",
    "wof:name":"Otto Zimmermann",
    "wof:placetype":"venue"
},
  "geometry": {"coordinates":[11.5039749146,50.3731842041],"type":"Point"}
}