{
  "type": "Feature",
  "properties": {
    "iso:country":"DE",
    "sg:address":"Bebelplatz 19",
    "sg:city":"Kiel",
    "sg:postcode":"24146",
    "sg:province":"Schleswig-Holstein",
    "wof:name":"Horst Stolley E. K.",
    "wof:placetype":"venue"
},
  "geometry": {"coordinates":[10.1856546402,54.2941589355],"type":"Point"}
}