{
  "type": "Feature",
  "properties": {
    "iso:country":"DE",
    "sg:address":"Prinz-Regent-Str. 44",
    "sg:city":"Bochum",
    "sg:phone":"+49 234/977900",
    "sg:postcode":"44795",
    "sg:province":"Nordrhein-Westfalen",
    "wof:name":"Freudenhaus Werbeagentur Gmbh & Co. Kg",
    "wof:placetype":"venue"
},
  "geometry": {"coordinates":[7.2193012238,51.4509925842],"type":"Point"}
}