{
  "type": "Feature",
  "properties": {
    "iso:country":"DE",
    "sg:address":"Schillerstr. 22",
    "sg:city":"Gardelegen",
    "sg:phone":"+49 3907/715486",
    "sg:postcode":"39638",
    "sg:province":"Sachsen-Anhalt",
    "wof:name":"Kr\u00fcper-draffehn Gbr",
    "wof:placetype":"venue"
},
  "geometry": {"coordinates":[11.400076,52.526112],"type":"Point"}
}