{
  "type": "Feature",
  "properties": {
    "iso:country":"DE",
    "sg:address":"Ferdinand-Rhode-Str. 10",
    "sg:city":"Leipzig",
    "sg:phone":"+49 341/9600659",
    "sg:postcode":"04107",
    "sg:province":"Sachsen",
    "wof:name":"Dr. Helmut Nase Rechtsanwalt",
    "wof:placetype":"venue"
},
  "geometry": {"coordinates":[12.3655557632,51.3316421509],"type":"Point"}
}