{
  "type": "Feature",
  "properties": {
    "iso:country":"DE",
    "sg:address":"Industriestr. 3",
    "sg:city":"Hausham",
    "sg:postcode":"83734",
    "sg:province":"Bayern",
    "wof:name":"Heiner Hofmann Gmbh & Co. Kg",
    "wof:placetype":"venue"
},
  "geometry": {"coordinates":[11.8385477066,47.753162384],"type":"Point"}
}