{
  "type": "Feature",
  "properties": {
    "iso:country":"DE",
    "sg:address":"Hauptstr. 20",
    "sg:city":"Radebeul",
    "sg:postcode":"01445",
    "sg:province":"Sachsen",
    "wof:name":"Kleine Galerie Radebeul",
    "wof:placetype":"venue"
},
  "geometry": {"coordinates":[13.680093,51.101345],"type":"Point"}
}