{
  "type": "Feature",
  "properties": {
    "iso:country":"DE",
    "sg:address":"Betzdorfer Str. 66",
    "sg:city":"Daaden",
    "sg:phone":"+49 2743/6581",
    "sg:postcode":"57567",
    "sg:province":"Rheinland-Pfalz",
    "wof:name":"Werner H\u00f6fer",
    "wof:placetype":"venue"
},
  "geometry": {"coordinates":[7.961582,50.744095],"type":"Point"}
}