{
  "type": "Feature",
  "properties": {
    "iso:country":"DE",
    "sg:address":"Havellandstr. 12",
    "sg:city":"Brieselang",
    "sg:phone":"+49 3321/4116",
    "sg:postcode":"14656",
    "sg:province":"Brandenburg",
    "wof:name":"Presse Vertrieb Potsdam Ohg",
    "wof:placetype":"venue"
},
  "geometry": {"coordinates":[12.97349,52.602959],"type":"Point"}
}