{
  "type": "Feature",
  "properties": {
    "iso:country":"DE",
    "sg:address":"Merkurring 46",
    "sg:city":"Hamburg",
    "sg:postcode":"22143",
    "sg:province":"Hamburg",
    "wof:name":"Huwa Lagertechnik Vertriebs- Gmbh",
    "wof:placetype":"venue"
},
  "geometry": {"coordinates":[10.186964,53.604229],"type":"Point"}
}