{
  "type": "Feature",
  "properties": {
    "iso:country":"DE",
    "sg:address":"Sternstr.",
    "sg:city":"Liebenau",
    "sg:phone":"+49 5023/4672",
    "sg:postcode":"31618",
    "sg:province":"Niedersachsen",
    "wof:name":"Haus Im Scheunenviertel Seniorenheim",
    "wof:placetype":"venue"
},
  "geometry": {"coordinates":[9.088029,52.607666],"type":"Point"}
}