{
  "type": "Feature",
  "properties": {
    "iso:country":"DE",
    "sg:address":"Elisabeth-Selbert-Str. 4a",
    "sg:city":"Langenfeld",
    "sg:phone":"+49 2173/109370",
    "sg:postcode":"40764",
    "sg:province":"Nordrhein-Westfalen",
    "wof:name":"Flos Gmbh",
    "wof:placetype":"venue"
},
  "geometry": {"coordinates":[6.934381,51.122757],"type":"Point"}
}