{
  "type": "Feature",
  "properties": {
    "iso:country":"DE",
    "sg:address":"Carl-Bosch-Str.",
    "sg:city":"Ludwigshafen",
    "sg:phone":"+49 621/599020",
    "sg:postcode":"67063",
    "sg:province":"Rheinland-Pfalz",
    "wof:name":"Gewoge Wohnungsunter - Nehmen Der Basf Gmbh",
    "wof:placetype":"venue"
},
  "geometry": {"coordinates":[8.4196395874,49.4977836609],"type":"Point"}
}