{
  "type": "Feature",
  "properties": {
    "iso:country":"DE",
    "sg:address":"Bieberer Str. 28",
    "sg:city":"Obertshausen",
    "sg:phone":"+49 6104/43961",
    "sg:postcode":"63179",
    "sg:province":"Hessen",
    "wof:name":"Gedrim Verwaltungs- Gesellschaft Mbh",
    "wof:placetype":"venue"
},
  "geometry": {"coordinates":[8.834473,50.066624],"type":"Point"}
}