{
  "type": "Feature",
  "properties": {
    "iso:country":"DE",
    "sg:address":"Am Alten Brunnen 9",
    "sg:city":"Werneck",
    "sg:phone":"+49 9722/9265",
    "sg:postcode":"97440",
    "sg:province":"Bayern",
    "wof:name":"W. Und K. Schnepf",
    "wof:placetype":"venue"
},
  "geometry": {"coordinates":[10.086612,50.030788],"type":"Point"}
}