{
  "type": "Feature",
  "properties": {
    "iso:country":"DE",
    "sg:address":"Br\u00fcckenstr. 11",
    "sg:city":"Neustadt",
    "sg:phone":"+49 5072/1359",
    "sg:postcode":"31535",
    "sg:province":"Niedersachsen",
    "wof:name":"Jk Papierverarbeitung Gmbh",
    "wof:placetype":"venue"
},
  "geometry": {"coordinates":[9.0314722061,49.8169212341],"type":"Point"}
}