{
  "type": "Feature",
  "properties": {
    "iso:country":"DE",
    "sg:address":"Balger Hauptstr. 31",
    "sg:city":"Baden-Baden",
    "sg:phone":"+49 7221/64580",
    "sg:postcode":"76532",
    "sg:province":"Baden-W\u00fcrttemberg",
    "wof:name":"Else Krause",
    "wof:placetype":"venue"
},
  "geometry": {"coordinates":[8.2224273682,48.7877578735],"type":"Point"}
}