{
  "type": "Feature",
  "properties": {
    "iso:country":"DE",
    "sg:address":"Eidelsgasse 29",
    "sg:city":"Freudenberg",
    "sg:phone":"+49 9377/1476",
    "sg:postcode":"97896",
    "sg:province":"Baden-W\u00fcrttemberg",
    "wof:name":"Vollhardt & Weis Gmbh",
    "wof:placetype":"venue"
},
  "geometry": {"coordinates":[9.386819,49.739922],"type":"Point"}
}