{
  "type": "Feature",
  "properties": {
    "iso:country":"DE",
    "sg:address":"M\u00fchlenstr. 33",
    "sg:city":"Melle",
    "sg:phone":"+49 5422/981211",
    "sg:postcode":"49324",
    "sg:province":"Niedersachsen",
    "wof:name":"Polsterforum Melle Gmbh",
    "wof:placetype":"venue"
},
  "geometry": {"coordinates":[8.3405399323,52.203918457],"type":"Point"}
}