{
  "type": "Feature",
  "properties": {
    "iso:country":"DE",
    "sg:address":"Platzer H\u00f6henweg 7",
    "sg:city":"Bergisch Gladbach",
    "sg:phone":"+49 2204/82110",
    "sg:postcode":"51429",
    "sg:province":"Nordrhein-Westfalen",
    "wof:name":"H. Giersen Ingenieur",
    "wof:placetype":"venue"
},
  "geometry": {"coordinates":[7.2214231491,50.9612121582],"type":"Point"}
}