{
  "type": "Feature",
  "properties": {
    "iso:country":"DE",
    "sg:address":"Herner Str. 348",
    "sg:city":"Bochum",
    "sg:phone":"+49 234/534426",
    "sg:postcode":"44807",
    "sg:province":"Nordrhein-Westfalen",
    "wof:name":"H\u00e4usliche Krankenpflege Cornelia Hoof",
    "wof:placetype":"venue"
},
  "geometry": {"coordinates":[7.233935,51.499763],"type":"Point"}
}