{
  "type": "Feature",
  "properties": {
    "iso:country":"DE",
    "sg:address":"Obere Gartenstr. 12",
    "sg:city":"Bad Rappenau",
    "sg:phone":"+49 7264/5344",
    "sg:postcode":"74906",
    "sg:province":"Baden-W\u00fcrttemberg",
    "wof:name":"Erika Winkler",
    "wof:placetype":"venue"
},
  "geometry": {"coordinates":[9.1486997604,49.2595176697],"type":"Point"}
}