{
  "type": "Feature",
  "properties": {
    "iso:country":"DE",
    "sg:address":"Badestube 11",
    "sg:city":"Bad Hersfeld",
    "sg:phone":"+49 6621/73590",
    "sg:postcode":"36251",
    "sg:province":"Hessen",
    "wof:name":"Kimmich Mode-versand Beteiligungs Gmbh",
    "wof:placetype":"venue"
},
  "geometry": {"coordinates":[9.71075,50.868881],"type":"Point"}
}