{
  "type": "Feature",
  "properties": {
    "iso:country":"DE",
    "sg:address":"Kirchplatz 4",
    "sg:city":"Horstmar",
    "sg:phone":"+49 2551/5282",
    "sg:postcode":"48612",
    "sg:province":"Nordrhein-Westfalen",
    "wof:name":"Katholisches Pfarramt St. Cosmas Und Damian",
    "wof:placetype":"venue"
},
  "geometry": {"coordinates":[7.2948718071,52.1139755249],"type":"Point"}
}