{
  "type": "Feature",
  "properties": {
    "iso:country":"DE",
    "sg:address":"Bahnhofstr. 39",
    "sg:city":"Bad Frankenhausen",
    "sg:postcode":"06567",
    "sg:province":"Th\u00fcringen",
    "wof:name":"Bau Und Ausbau Gmbh",
    "wof:placetype":"venue"
},
  "geometry": {"coordinates":[11.04206,51.360832],"type":"Point"}
}