{
  "type": "Feature",
  "properties": {
    "iso:country":"DE",
    "sg:address":"Pixeler Str. 29",
    "sg:city":"Rheda-Wiedenbr\u00fcck",
    "sg:phone":"+49 5242/48789",
    "sg:postcode":"33378",
    "sg:province":"Nordrhein-Westfalen",
    "wof:name":"Tanja Kramer",
    "wof:placetype":"venue"
},
  "geometry": {"coordinates":[8.294583,51.86079],"type":"Point"}
}