{
  "type": "Feature",
  "properties": {
    "iso:country":"DE",
    "sg:address":"Idenbrockplatz 24/25",
    "sg:city":"M\u00fcnster",
    "sg:postcode":"48159",
    "sg:province":"Nordrhein-Westfalen",
    "wof:name":"Aldi Gmbh & Co. Kg",
    "wof:placetype":"venue"
},
  "geometry": {"coordinates":[7.6035699844,51.9947967529],"type":"Point"}
}