{
  "type": "Feature",
  "properties": {
    "iso:country":"DE",
    "sg:address":"Ardeystra\u00dfe 67",
    "sg:city":"Dortmund",
    "sg:phone":"+49 231/1084260",
    "sg:postcode":"44139",
    "sg:province":"Nordrhein-Westfalen",
    "wof:name":"Ergonetz",
    "wof:placetype":"venue"
},
  "geometry": {"coordinates":[7.458667,51.489956],"type":"Point"}
}