{
  "type": "Feature",
  "properties": {
    "iso:country":"DE",
    "sg:address":"Bahnhofstr. 42",
    "sg:city":"Rain",
    "sg:postcode":"86641",
    "sg:province":"Bayern",
    "wof:name":"Rtg Transport Gmbh",
    "wof:placetype":"venue"
},
  "geometry": {"coordinates":[10.9250507355,48.6956176758],"type":"Point"}
}