{
  "type": "Feature",
  "properties": {
    "iso:country":"DE",
    "sg:address":"Rebweg 4",
    "sg:city":"Friedrichshafen",
    "sg:phone":"+49 7541/21685",
    "sg:postcode":"88048",
    "sg:province":"Baden-W\u00fcrttemberg",
    "wof:name":"Magnus Fotohaus Fotostudio Gmbh",
    "wof:placetype":"venue"
},
  "geometry": {"coordinates":[9.4334945679,47.6659011841],"type":"Point"}
}