{
  "type": "Feature",
  "properties": {
    "iso:country":"DE",
    "sg:address":"Bahnweg 70",
    "sg:city":"Lengdorf",
    "sg:phone":"+49 8083/282",
    "sg:postcode":"84435",
    "sg:province":"Bayern",
    "wof:name":"A. Sigl",
    "wof:placetype":"venue"
},
  "geometry": {"coordinates":[12.04786,48.260818],"type":"Point"}
}