{
  "type": "Feature",
  "properties": {
    "iso:country":"DE",
    "sg:address":"Kirchgasse 2",
    "sg:city":"Sch\u00f6mberg",
    "sg:phone":"+49 7427/8645",
    "sg:postcode":"72355",
    "sg:province":"Baden-W\u00fcrttemberg",
    "wof:name":"Bistro Kanone",
    "wof:placetype":"venue"
},
  "geometry": {"coordinates":[8.7611732483,48.2113952637],"type":"Point"}
}