{
  "type": "Feature",
  "properties": {
    "iso:country":"DE",
    "sg:address":"Prenzlauer Ch. 30",
    "sg:city":"Pasewalk",
    "sg:phone":"+49 3973/210210",
    "sg:postcode":"17309",
    "sg:province":"Mecklenburg-Vorpommern",
    "wof:name":"Elektroanlagenbau Gmbh",
    "wof:placetype":"venue"
},
  "geometry": {"coordinates":[13.983446,53.489494],"type":"Point"}
}