{
  "type": "Feature",
  "properties": {
    "iso:country":"DE",
    "sg:address":"Tinsdaler Weg 92",
    "sg:city":"Wedel",
    "sg:phone":"+49 4103/88160",
    "sg:postcode":"22880",
    "sg:province":"Schleswig-Holstein",
    "wof:name":"I. Steffens",
    "wof:placetype":"venue"
},
  "geometry": {"coordinates":[9.719162,53.574375],"type":"Point"}
}