{
  "type": "Feature",
  "properties": {
    "iso:country":"DE",
    "sg:address":"Friedrichstr. 3",
    "sg:city":"Bernkastel-Kues",
    "sg:phone":"+49 6531/3669",
    "sg:postcode":"54470",
    "sg:province":"Rheinland-Pfalz",
    "wof:name":"Paul Mehl Masseur",
    "wof:placetype":"venue"
},
  "geometry": {"coordinates":[7.068738,49.914909],"type":"Point"}
}