{
  "type": "Feature",
  "properties": {
    "iso:country":"DE",
    "sg:address":"Mindener Str. 36",
    "sg:city":"Bad Oeynhausen",
    "sg:phone":"+49 5731/18080",
    "sg:postcode":"32547",
    "sg:province":"Nordrhein-Westfalen",
    "wof:name":"Casino Gastronomie Diamond Verwaltungsgesellschaft Mbh",
    "wof:placetype":"venue"
},
  "geometry": {"coordinates":[8.8156261444,52.2140884399],"type":"Point"}
}