{
  "type": "Feature",
  "properties": {
    "iso:country":"DE",
    "sg:address":"Maybachstr. 9",
    "sg:city":"Stuttgart",
    "sg:phone":"+49 711/858902",
    "sg:postcode":"70469",
    "sg:province":"Baden-W\u00fcrttemberg",
    "wof:name":"Jet Tankstelle",
    "wof:placetype":"venue"
},
  "geometry": {"coordinates":[9.1765890121,48.80909729],"type":"Point"}
}