{
  "type": "Feature",
  "properties": {
    "iso:country":"DE",
    "sg:address":"Universit\u00e4tspark 1",
    "sg:city":"Schw\u00e4bisch Gm\u00fcnd",
    "sg:phone":"+49 7171/927530",
    "sg:postcode":"73525",
    "sg:province":"Baden-W\u00fcrttemberg",
    "wof:name":"Wirtschaftsf\u00f6rderungs Gmbh Region Ostw\u00fcrttemberg",
    "wof:placetype":"venue"
},
  "geometry": {"coordinates":[9.816334,48.800697],"type":"Point"}
}