{
  "type": "Feature",
  "properties": {
    "iso:country":"DE",
    "sg:address":"F\u00f6rsterstr. 7",
    "sg:city":"Deisenhofen",
    "sg:phone":"+49 89/6132397",
    "sg:postcode":"82041",
    "sg:province":"Bayern",
    "wof:name":"Hans-dieter Bartels Dipl.-phys.",
    "wof:placetype":"venue"
},
  "geometry": {"coordinates":[11.5876159668,48.016708374],"type":"Point"}
}