{
  "type": "Feature",
  "properties": {
    "iso:country":"DE",
    "sg:address":"Neckarweg 5",
    "sg:city":"Vellmar",
    "sg:phone":"+49 561/821630",
    "sg:postcode":"34246",
    "sg:province":"Hessen",
    "wof:name":"Frank-michael Thiel",
    "wof:placetype":"venue"
},
  "geometry": {"coordinates":[9.465274,51.356384],"type":"Point"}
}