{
  "type": "Feature",
  "properties": {
    "iso:country":"DE",
    "sg:address":"Am Sonnenhang 4",
    "sg:city":"Altenstadt",
    "sg:phone":"+49 6047/7905",
    "sg:postcode":"63674",
    "sg:province":"Hessen",
    "wof:name":"Karl Hennrich",
    "wof:placetype":"venue"
},
  "geometry": {"coordinates":[8.9416570663,50.290725708],"type":"Point"}
}