{
  "type": "Feature",
  "properties": {
    "iso:country":"DE",
    "sg:address":"Dahner Str. 15",
    "sg:city":"Lemberg",
    "sg:phone":"+49 6331/209300",
    "sg:postcode":"66969",
    "sg:province":"Rheinland-Pfalz",
    "wof:name":"R. Und M. Klemm",
    "wof:placetype":"venue"
},
  "geometry": {"coordinates":[7.6582560539,49.1707038879],"type":"Point"}
}