{
  "type": "Feature",
  "properties": {
    "iso:country":"DE",
    "sg:address":"Robert-Di\u00dfmann-Str. 18",
    "sg:city":"Frankfurt",
    "sg:phone":"+49 69/346010",
    "sg:postcode":"65936",
    "sg:province":"Hessen",
    "wof:name":"Kedo Krankenpflege D\u00f6ring",
    "wof:placetype":"venue"
},
  "geometry": {"coordinates":[8.567735,50.123367],"type":"Point"}
}