{
  "type": "Feature",
  "properties": {
    "iso:country":"DE",
    "sg:address":"Kapellenweg 6",
    "sg:city":"Winsen",
    "sg:phone":"+49 5056/1557",
    "sg:postcode":"29308",
    "sg:province":"Niedersachsen",
    "wof:name":"Ets International Gmbh",
    "wof:placetype":"venue"
},
  "geometry": {"coordinates":[9.8532419205,52.729473114],"type":"Point"}
}