{
  "type": "Feature",
  "properties": {
    "iso:country":"DE",
    "sg:address":"Am Pferdskopf 12",
    "sg:city":"Schmitten",
    "sg:phone":"+49 6084/950250",
    "sg:postcode":"61389",
    "sg:province":"Hessen",
    "wof:name":"Forexpo Vertriebs Gmbh",
    "wof:placetype":"venue"
},
  "geometry": {"coordinates":[8.436992,50.294361],"type":"Point"}
}