{
  "type": "Feature",
  "properties": {
    "iso:country":"DE",
    "sg:address":"Saarlandstr. 9",
    "sg:city":"Hamburg",
    "sg:phone":"+49 40/19295",
    "sg:postcode":"22303",
    "sg:province":"Hamburg",
    "wof:name":"Anonyme Alkoholiker Beratungsstelle",
    "wof:placetype":"venue"
},
  "geometry": {"coordinates":[10.033242,53.585995],"type":"Point"}
}