{
  "type": "Feature",
  "properties": {
    "iso:country":"DE",
    "sg:address":"Klopstockstr. 3",
    "sg:city":"Halberstadt",
    "sg:phone":"+49 3941/442341",
    "sg:postcode":"38820",
    "sg:province":"Sachsen-Anhalt",
    "wof:name":"Zur Stampe Inh. Peter K\u00e4sewieter",
    "wof:placetype":"venue"
},
  "geometry": {"coordinates":[11.0510501862,51.8831977844],"type":"Point"}
}