{
  "type": "Feature",
  "properties": {
    "iso:country":"DE",
    "sg:address":"Zum B\u00e4rental 14",
    "sg:city":"N\u00f6rvenich",
    "sg:phone":"+49 2421/75521",
    "sg:postcode":"52388",
    "sg:province":"Nordrhein-Westfalen",
    "wof:name":"J. Deller Rechtsanwalt",
    "wof:placetype":"venue"
},
  "geometry": {"coordinates":[6.5738401413,50.7919082642],"type":"Point"}
}