{
  "type": "Feature",
  "properties": {
    "iso:country":"DE",
    "sg:address":"Dorfweg 2a",
    "sg:city":"Bad Endorf",
    "sg:phone":"+49 8053/30770",
    "sg:postcode":"83093",
    "sg:province":"Bayern",
    "wof:name":"Ro Spedition Gmbh",
    "wof:placetype":"venue"
},
  "geometry": {"coordinates":[12.3357067108,47.9091415405],"type":"Point"}
}