{
  "type": "Feature",
  "properties": {
    "iso:country":"DE",
    "sg:address":"Aktienstra\u00dfe 293",
    "sg:city":"M\u00fclheim",
    "sg:phone":"+49 208",
    "sg:postcode":"45468",
    "sg:province":"Nordrhein-Westfalen",
    "wof:name":"Reinberger, Stefan",
    "wof:placetype":"venue"
},
  "geometry": {"coordinates":[6.8862500191,51.4274482727],"type":"Point"}
}