{
  "type": "Feature",
  "properties": {
    "iso:country":"DE",
    "sg:address":"Diehlenweg 1",
    "sg:city":"Gro\u00dfkampenberg",
    "sg:phone":"+49 6559/438",
    "sg:postcode":"54619",
    "sg:province":"Rheinland-Pfalz",
    "wof:name":"Peter Jakobs",
    "wof:placetype":"venue"
},
  "geometry": {"coordinates":[6.211169,50.160767],"type":"Point"}
}