{
  "type": "Feature",
  "properties": {
    "iso:country":"DE",
    "sg:address":"Westerfeld 46 a",
    "sg:city":"Herzebrock-Clarholz",
    "sg:postcode":"33442",
    "sg:province":"Nordrhein-Westfalen",
    "wof:name":"I. Borchmeier Hebamme",
    "wof:placetype":"venue"
},
  "geometry": {"coordinates":[8.298218,51.891838],"type":"Point"}
}