{
  "type": "Feature",
  "properties": {
    "iso:country":"DE",
    "sg:address":"Johanneswerkstr. 12",
    "sg:city":"Bielefeld",
    "sg:phone":"+49 521/83042",
    "sg:postcode":"33611",
    "sg:province":"Nordrhein-Westfalen",
    "wof:name":"Beratungsstelle F\u00fcr Selbstmordgef\u00e4hrdete",
    "wof:placetype":"venue"
},
  "geometry": {"coordinates":[8.539822,52.040169],"type":"Point"}
}