{
  "type": "Feature",
  "properties": {
    "iso:country":"DE",
    "sg:address":"Bahnhofstr. 54",
    "sg:city":"Ferdinandshof",
    "sg:phone":"+49 39778/20255",
    "sg:postcode":"17379",
    "sg:province":"Mecklenburg-Vorpommern",
    "wof:name":"Gertrud V\u00f6lker",
    "wof:placetype":"venue"
},
  "geometry": {"coordinates":[13.885547,53.663807],"type":"Point"}
}