{
  "type": "Feature",
  "properties": {
    "iso:country":"DE",
    "sg:address":"Soltauer Str. 8",
    "sg:city":"Berlin",
    "sg:postcode":"13509",
    "sg:province":"Berlin",
    "wof:name":"Bskv Starkstromkabel Verwaltungsgesellschaft Mbh",
    "wof:placetype":"venue"
},
  "geometry": {"coordinates":[13.3039722443,52.5796890259],"type":"Point"}
}