{
  "type": "Feature",
  "properties": {
    "iso:country":"DE",
    "sg:address":"Siegener Str. 25",
    "sg:city":"Frankenberg",
    "sg:postcode":"35066",
    "sg:province":"Hessen",
    "wof:name":"Hennings Gmbh",
    "wof:placetype":"venue"
},
  "geometry": {"coordinates":[8.78469,51.05328],"type":"Point"}
}