{
  "type": "Feature",
  "properties": {
    "iso:country":"DE",
    "sg:address":"Fuchsh\u00f6hlenweg 12a",
    "sg:city":"Menden",
    "sg:phone":"+49 2373/14447",
    "sg:postcode":"58706",
    "sg:province":"Nordrhein-Westfalen",
    "wof:name":"Mess- & Datentechnik Martin Dehen",
    "wof:placetype":"venue"
},
  "geometry": {"coordinates":[7.801612,51.439205],"type":"Point"}
}