{
  "type": "Feature",
  "properties": {
    "iso:country":"DE",
    "sg:address":"Friedhofstr. 5",
    "sg:city":"Mengen",
    "sg:postcode":"88512",
    "sg:province":"Baden-W\u00fcrttemberg",
    "wof:name":"Emhart Und Pfister Partnerschaft Freie",
    "wof:placetype":"venue"
},
  "geometry": {"coordinates":[9.3484592438,48.0690689087],"type":"Point"}
}