{
  "type": "Feature",
  "properties": {
    "iso:country":"DE",
    "sg:address":"Eichendorffstr. 44",
    "sg:city":"Neuss",
    "sg:phone":"+49 2131/43068",
    "sg:postcode":"41464",
    "sg:province":"Nordrhein-Westfalen",
    "wof:name":"Karin Winschuh",
    "wof:placetype":"venue"
},
  "geometry": {"coordinates":[6.69241,51.186218],"type":"Point"}
}