{
  "type": "Feature",
  "properties": {
    "iso:country":"DE",
    "sg:address":"Hegaustr. 7",
    "sg:city":"Radolfzell",
    "sg:phone":"+49 7732/58153",
    "sg:postcode":"78315",
    "sg:province":"Baden-W\u00fcrttemberg",
    "wof:name":"Vitalis Powerhouse Gym Fitness-studio",
    "wof:placetype":"venue"
},
  "geometry": {"coordinates":[8.9618701935,47.7453117371],"type":"Point"}
}