{
  "type": "Feature",
  "properties": {
    "iso:country":"DE",
    "sg:address":"Breitenhofstr. 110",
    "sg:city":"Neu-Ulm",
    "sg:postcode":"89233",
    "sg:province":"Bayern",
    "wof:name":"Kirchenbauverein St. Mammas Neu-ulm Finningen E. V.",
    "wof:placetype":"venue"
},
  "geometry": {"coordinates":[10.0478897095,48.3873901367],"type":"Point"}
}