{
  "type": "Feature",
  "properties": {
    "iso:country":"DE",
    "sg:address":"Appelh\u00fclsener Str. 15",
    "sg:city":"Nottuln",
    "sg:phone":"+49 2502/7044",
    "sg:postcode":"48301",
    "sg:province":"Nordrhein-Westfalen",
    "wof:name":"Wilbers Kotten",
    "wof:placetype":"venue"
},
  "geometry": {"coordinates":[7.3634738922,51.9272994995],"type":"Point"}
}