{
  "type": "Feature",
  "properties": {
    "iso:country":"DE",
    "sg:address":"Polmansstr. 50",
    "sg:city":"Schwalmtal",
    "sg:phone":"+49 2163/32280",
    "sg:postcode":"41366",
    "sg:province":"Nordrhein-Westfalen",
    "wof:name":"Kokot Gmbh",
    "wof:placetype":"venue"
},
  "geometry": {"coordinates":[6.2413301468,51.2280883789],"type":"Point"}
}