{
  "type": "Feature",
  "properties": {
    "iso:country":"DE",
    "sg:address":"Lindenstr. 8",
    "sg:city":"Rosdorf",
    "sg:phone":"+49 5509/1469",
    "sg:postcode":"37124",
    "sg:province":"Niedersachsen",
    "wof:name":"Pension Lieselotte Becker",
    "wof:placetype":"venue"
},
  "geometry": {"coordinates":[9.8725862503,51.4911270142],"type":"Point"}
}