{
  "type": "Feature",
  "properties": {
    "iso:country":"DE",
    "sg:address":"Dorfstr. 30",
    "sg:city":"Colditz",
    "sg:phone":"+49 34381/42336",
    "sg:postcode":"04680",
    "sg:province":"Sachsen",
    "wof:name":"W. Schatz",
    "wof:placetype":"venue"
},
  "geometry": {"coordinates":[12.82995224,51.0980415344],"type":"Point"}
}