{
  "type": "Feature",
  "properties": {
    "iso:country":"DE",
    "sg:address":"Hasenbanckweg 5",
    "sg:city":"Hamburg",
    "sg:phone":"+49 40/7331646",
    "sg:postcode":"22119",
    "sg:province":"Hamburg",
    "wof:name":"Baugesch\u00e4ft Joachim Schynol Ohg",
    "wof:placetype":"venue"
},
  "geometry": {"coordinates":[10.1175260544,53.5533485413],"type":"Point"}
}