{
  "type": "Feature",
  "properties": {
    "iso:country":"DE",
    "sg:address":"Seumestr. 10",
    "sg:city":"Plauen",
    "sg:postcode":"08525",
    "sg:province":"Sachsen",
    "wof:name":"H. Clau\u00df",
    "wof:placetype":"venue"
},
  "geometry": {"coordinates":[12.129098,50.50927],"type":"Point"}
}