{
  "type": "Feature",
  "properties": {
    "iso:country":"DE",
    "sg:address":"Hellweg 6",
    "sg:city":"Hamminkeln",
    "sg:phone":"+49 2852/2117",
    "sg:postcode":"46499",
    "sg:province":"Nordrhein-Westfalen",
    "wof:name":"B. Knipping",
    "wof:placetype":"venue"
},
  "geometry": {"coordinates":[6.630171,51.750286],"type":"Point"}
}