{
  "type": "Feature",
  "properties": {
    "iso:country":"DE",
    "sg:address":"Goltzstr. 20",
    "sg:city":"Berlin",
    "sg:phone":"+49 30/2151862",
    "sg:postcode":"10781",
    "sg:province":"Berlin",
    "wof:name":"Kristina Shamsi Gmbh",
    "wof:placetype":"venue"
},
  "geometry": {"coordinates":[13.354059,52.494083],"type":"Point"}
}