{
  "type": "Feature",
  "properties": {
    "iso:country":"DE",
    "sg:address":"Kurf\u00fcrstenstr. 12",
    "sg:city":"N\u00f6rvenich",
    "sg:phone":"+49 2426",
    "sg:postcode":"52388",
    "sg:province":"Nordrhein-Westfalen",
    "wof:name":"Teepee Heart Guest Ranch",
    "wof:placetype":"venue"
},
  "geometry": {"coordinates":[6.6365537643,50.7862815857],"type":"Point"}
}