{
  "type": "Feature",
  "properties": {
    "iso:country":"DE",
    "sg:address":"Rosenstr. 9",
    "sg:city":"Moosbach",
    "sg:postcode":"92709",
    "sg:province":"Bayern",
    "wof:name":"Allianz Versicherungs Ag",
    "wof:placetype":"venue"
},
  "geometry": {"coordinates":[12.4122877121,49.5873031616],"type":"Point"}
}