{
  "type": "Feature",
  "properties": {
    "iso:country":"DE",
    "sg:address":"Happoldstaffel 5",
    "sg:city":"Stuttgart",
    "sg:phone":"+49 711/853991",
    "sg:postcode":"70469",
    "sg:province":"Baden-W\u00fcrttemberg",
    "wof:name":"Erwin Schraivogel Gmbh",
    "wof:placetype":"venue"
},
  "geometry": {"coordinates":[9.161448,48.806961],"type":"Point"}
}