{
  "type": "Feature",
  "properties": {
    "iso:country":"DE",
    "sg:address":"Ro\u00dfplan 12",
    "sg:city":"Altenburg",
    "sg:phone":"+49 3447/504006",
    "sg:postcode":"04600",
    "sg:province":"Th\u00fcringen",
    "wof:name":"Ina Schreier Notarin",
    "wof:placetype":"venue"
},
  "geometry": {"coordinates":[12.4325227737,50.982875824],"type":"Point"}
}