{
  "type": "Feature",
  "properties": {
    "iso:country":"DE",
    "sg:address":"Lothringer Str. 23",
    "sg:city":"K\u00f6ln",
    "sg:postcode":"50677",
    "sg:province":"Nordrhein-Westfalen",
    "wof:name":"Permission Music Productions Gmbh",
    "wof:placetype":"venue"
},
  "geometry": {"coordinates":[6.9534420967,50.9221153259],"type":"Point"}
}