{
  "type": "Feature",
  "properties": {
    "iso:country":"DE",
    "sg:address":"Go\u00dflerstr. 11",
    "sg:city":"G\u00f6ttingen",
    "sg:phone":"+49 551/394693",
    "sg:postcode":"37073",
    "sg:province":"Niedersachsen",
    "wof:name":"Institut F\u00fcr Allgemeine Staatslehre Und Politische",
    "wof:placetype":"venue"
},
  "geometry": {"coordinates":[9.937911,51.540882],"type":"Point"}
}