{
  "type": "Feature",
  "properties": {
    "iso:country":"DE",
    "sg:address":"Hindenburgdamm 48",
    "sg:city":"Berlin",
    "sg:phone":"+49 30/8349741",
    "sg:postcode":"12203",
    "sg:province":"Berlin",
    "wof:name":"Kunst- Und Bauglaserei Werner Bode Gmbh",
    "wof:placetype":"venue"
},
  "geometry": {"coordinates":[13.3158473969,52.444732666],"type":"Point"}
}