{
  "type": "Feature",
  "properties": {
    "iso:country":"DE",
    "sg:address":"Geraer Str. 23",
    "sg:city":"Luckenwalde",
    "sg:phone":"+49 3371/620000",
    "sg:postcode":"14943",
    "sg:province":"Brandenburg",
    "wof:name":"M. Barknecht",
    "wof:placetype":"venue"
},
  "geometry": {"coordinates":[13.165643,52.09766],"type":"Point"}
}