{
  "type": "Feature",
  "properties": {
    "iso:country":"DE",
    "sg:address":"Am Fuchsheck 7",
    "sg:city":"Linkenheim-Hochstetten",
    "sg:phone":"+49 7247/87033",
    "sg:postcode":"76351",
    "sg:province":"Baden-W\u00fcrttemberg",
    "wof:name":"Gerd Bauer Architekt",
    "wof:placetype":"venue"
},
  "geometry": {"coordinates":[8.411525,49.133106],"type":"Point"}
}