{
  "type": "Feature",
  "properties": {
    "iso:country":"DE",
    "sg:address":"Brambach 29",
    "sg:city":"Schramberg",
    "sg:phone":"+49 7422/6916",
    "sg:postcode":"78713",
    "sg:province":"Baden-W\u00fcrttemberg",
    "wof:name":"Josef Fehrenbacher",
    "wof:placetype":"venue"
},
  "geometry": {"coordinates":[8.43523,48.244801],"type":"Point"}
}