{
  "type": "Feature",
  "properties": {
    "iso:country":"DE",
    "sg:address":"Hermannsfelder Str. 7",
    "sg:city":"Mellrichstadt",
    "sg:phone":"+49 9776/5862",
    "sg:postcode":"97638",
    "sg:province":"Bayern",
    "wof:name":"Theo Euring",
    "wof:placetype":"venue"
},
  "geometry": {"coordinates":[10.3185596466,50.4639587402],"type":"Point"}
}