{
  "type": "Feature",
  "properties": {
    "iso:country":"DE",
    "sg:address":"Ramskamp 37",
    "sg:city":"Elmshorn",
    "sg:phone":"+49 4121/72472",
    "sg:postcode":"25337",
    "sg:province":"Schleswig-Holstein",
    "wof:name":"Kurt Kreutzfeld",
    "wof:placetype":"venue"
},
  "geometry": {"coordinates":[9.686129,53.742241],"type":"Point"}
}