{
  "type": "Feature",
  "properties": {
    "iso:country":"DE",
    "sg:address":"Holsteiner Str. 8",
    "sg:city":"Finsterwalde",
    "sg:postcode":"03238",
    "sg:province":"Brandenburg",
    "wof:name":"Eurospar",
    "wof:placetype":"venue"
},
  "geometry": {"coordinates":[13.7039203644,51.6043510437],"type":"Point"}
}