{
  "type": "Feature",
  "properties": {
    "iso:country":"DE",
    "sg:address":"Passauer Str. 19",
    "sg:city":"Neuhaus",
    "sg:phone":"+49 8503/252",
    "sg:postcode":"94152",
    "sg:province":"Bayern",
    "wof:name":"Helmuth Barth",
    "wof:placetype":"venue"
},
  "geometry": {"coordinates":[13.419208,48.458958],"type":"Point"}
}