{
  "type": "Feature",
  "properties": {
    "iso:country":"DE",
    "sg:address":"Schwalbenstr. 16",
    "sg:city":"Winterbach",
    "sg:phone":"+49 7181/75258",
    "sg:postcode":"73650",
    "sg:province":"Baden-W\u00fcrttemberg",
    "wof:name":"N & M Natur Und Management Gmbh",
    "wof:placetype":"venue"
},
  "geometry": {"coordinates":[9.48442,48.79644],"type":"Point"}
}