{
  "type": "Feature",
  "properties": {
    "iso:country":"DE",
    "sg:city":"Stiege",
    "sg:phone":"+49 39459/316",
    "sg:postcode":"38899",
    "sg:province":"Sachsen-Anhalt",
    "wof:name":"Campingplatz Stiege",
    "wof:placetype":"venue"
},
  "geometry": {"coordinates":[10.886179,51.667679],"type":"Point"}
}