{
  "type": "Feature",
  "properties": {
    "iso:country":"DE",
    "sg:address":"R\u00f6thensteig 19",
    "sg:city":"N\u00fcrnberg",
    "sg:postcode":"90408",
    "sg:province":"Bayern",
    "wof:name":"S & G Mangement Limited Zweigniederlassung",
    "wof:placetype":"venue"
},
  "geometry": {"coordinates":[11.075117,49.470726],"type":"Point"}
}