{
  "type": "Feature",
  "properties": {
    "iso:country":"DE",
    "sg:address":"Ritterstr. 102",
    "sg:city":"Viersen",
    "sg:phone":"+49 2162/7635",
    "sg:postcode":"41749",
    "sg:province":"Nordrhein-Westfalen",
    "wof:name":"Paul Ohligs",
    "wof:placetype":"venue"
},
  "geometry": {"coordinates":[6.331282,51.305042],"type":"Point"}
}