{
  "type": "Feature",
  "properties": {
    "iso:country":"DE",
    "sg:address":"Kirchbergstr. 29",
    "sg:city":"Schwalbach",
    "sg:postcode":"66773",
    "sg:province":"Saarland",
    "wof:name":"Cosic Hochbau Gmbh",
    "wof:placetype":"venue"
},
  "geometry": {"coordinates":[6.802449,49.299747],"type":"Point"}
}