{
  "type": "Feature",
  "properties": {
    "iso:country":"DE",
    "sg:address":"Werkstrasse 7",
    "sg:city":"Enger",
    "sg:phone":"+49 4905/2231850",
    "sg:postcode":"32130",
    "sg:province":"Nordrhein-Westfalen",
    "wof:name":"Ehlebracht Ag",
    "wof:placetype":"venue"
},
  "geometry": {"coordinates":[8.5899581909,52.1674423218],"type":"Point"}
}