{
  "type": "Feature",
  "properties": {
    "iso:country":"DE",
    "sg:address":"Bruckdorfer Str. 7 a",
    "sg:city":"Sinzing",
    "sg:phone":"+49 941/31300",
    "sg:postcode":"93161",
    "sg:province":"Bayern",
    "wof:name":"Marien-apotheke Bernd Laubrock",
    "wof:placetype":"venue"
},
  "geometry": {"coordinates":[12.0329,48.990208],"type":"Point"}
}