{
  "type": "Feature",
  "properties": {
    "iso:country":"DE",
    "sg:address":"Talstr. 53",
    "sg:city":"Homburg",
    "sg:phone":"+49 6841/2259",
    "sg:postcode":"66424",
    "sg:province":"Saarland",
    "wof:name":"Sanit\u00e4tshaus Beck Inh. R. Speer",
    "wof:placetype":"venue"
},
  "geometry": {"coordinates":[7.336143,49.320137],"type":"Point"}
}