{
  "type": "Feature",
  "properties": {
    "iso:country":"DE",
    "sg:address":"Delmenhorster Str. 4",
    "sg:city":"Lemwerder",
    "sg:postcode":"27809",
    "sg:province":"Niedersachsen",
    "wof:name":"Dr. Christel Meyer Tier\u00e4rztin",
    "wof:placetype":"venue"
},
  "geometry": {"coordinates":[8.6456546783,53.1166496277],"type":"Point"}
}