{
  "type": "Feature",
  "properties": {
    "iso:country":"DE",
    "sg:address":"Kurstra\u00dfe 15",
    "sg:city":"Bad-Salzhausen",
    "sg:phone":"+49 6043/401160",
    "sg:postcode":"63667",
    "sg:province":"Hessen",
    "wof:name":"K\u00f6nig-st\u00fcbchen",
    "wof:placetype":"venue"
},
  "geometry": {"coordinates":[8.984754,50.416241],"type":"Point"}
}