{
  "type": "Feature",
  "properties": {
    "iso:country":"DE",
    "sg:address":"Brucknerallee 1",
    "sg:city":"M\u00f6nchengladbach",
    "sg:phone":"+49 2166/41641",
    "sg:postcode":"41236",
    "sg:province":"Nordrhein-Westfalen",
    "wof:name":"Carl M\u00fchlinghaus",
    "wof:placetype":"venue"
},
  "geometry": {"coordinates":[6.444948,51.168468],"type":"Point"}
}