{
  "type": "Feature",
  "properties": {
    "iso:country":"DE",
    "sg:address":"Ringbergstr. 38",
    "sg:city":"Schweinschied",
    "sg:phone":"+49 6753/94720",
    "sg:postcode":"67744",
    "sg:province":"Rheinland-Pfalz",
    "wof:name":"Gauch Gmbh",
    "wof:placetype":"venue"
},
  "geometry": {"coordinates":[7.575366,49.70166],"type":"Point"}
}