{
  "type": "Feature",
  "properties": {
    "iso:country":"DE",
    "sg:address":"Vilbeler Landstr. 41",
    "sg:city":"Frankfurt",
    "sg:phone":"+49 6109/3848",
    "sg:postcode":"60388",
    "sg:province":"Hessen",
    "wof:name":"R Und S Stanzformen Gmbh",
    "wof:placetype":"venue"
},
  "geometry": {"coordinates":[8.7573671341,50.1409454346],"type":"Point"}
}