{
  "type": "Feature",
  "properties": {
    "iso:country":"DE",
    "sg:address":"Herchener Str. 14",
    "sg:city":"Windeck",
    "sg:phone":"+49 2292/2226",
    "sg:postcode":"51570",
    "sg:province":"Nordrhein-Westfalen",
    "wof:name":"Lenz",
    "wof:placetype":"venue"
},
  "geometry": {"coordinates":[7.530129,50.797607],"type":"Point"}
}