{
  "type": "Feature",
  "properties": {
    "iso:country":"DE",
    "sg:address":"Vor der Hasenhecke 18",
    "sg:city":"Kassel",
    "sg:phone":"+49 561/818161",
    "sg:postcode":"34125",
    "sg:province":"Hessen",
    "wof:name":"Dr. Fritjof B\u00f6rner Rechtsanwalt",
    "wof:placetype":"venue"
},
  "geometry": {"coordinates":[9.5453691483,51.3389434814],"type":"Point"}
}