{
  "type": "Feature",
  "properties": {
    "iso:country":"DE",
    "sg:address":"Obertorplatz 13",
    "sg:city":"Hechingen",
    "sg:phone":"+49 4974/712934",
    "sg:postcode":"72379",
    "sg:province":"Baden-W\u00fcrttemberg",
    "wof:name":"Volksbank Hechingen",
    "wof:placetype":"venue"
},
  "geometry": {"coordinates":[8.963178,48.350632],"type":"Point"}
}