{
  "type": "Feature",
  "properties": {
    "iso:country":"DE",
    "sg:address":"Altdorfstr. 19",
    "sg:city":"Aachen",
    "sg:phone":"+49 241/65186",
    "sg:postcode":"52066",
    "sg:province":"Nordrhein-Westfalen",
    "wof:name":"Im Backhaus",
    "wof:placetype":"venue"
},
  "geometry": {"coordinates":[6.0913381577,50.7614135742],"type":"Point"}
}