{
  "type": "Feature",
  "properties": {
    "iso:country":"DE",
    "sg:address":"Egerlandstr. 23",
    "sg:city":"Geretsried",
    "sg:phone":"+49 8171/8411",
    "sg:postcode":"82538",
    "sg:province":"Bayern",
    "wof:name":"Ernst Schw\u00e4gerl",
    "wof:placetype":"venue"
},
  "geometry": {"coordinates":[11.4703979492,47.8724632263],"type":"Point"}
}