{
  "type": "Feature",
  "properties": {
    "iso:country":"DE",
    "sg:address":"Marktstr. 14",
    "sg:city":"Seubersdorf",
    "sg:phone":"+49 9497/6453",
    "sg:postcode":"92358",
    "sg:province":"Bayern",
    "wof:name":"J.schierl Jun.",
    "wof:placetype":"venue"
},
  "geometry": {"coordinates":[11.5961294174,49.1512527466],"type":"Point"}
}