{
  "type": "Feature",
  "properties": {
    "iso:country":"DE",
    "sg:address":"Karlstr.",
    "sg:city":"Ro\u00dfla",
    "sg:postcode":"06536",
    "sg:province":"Sachsen-Anhalt",
    "wof:name":"Medi-bau-und Grundst\u00fccks- Beteiligungsgesellschaft Mbh",
    "wof:placetype":"venue"
},
  "geometry": {"coordinates":[11.075715,51.462223],"type":"Point"}
}