{
  "type": "Feature",
  "properties": {
    "iso:country":"DE",
    "sg:address":"Wattenbergstr. 19",
    "sg:city":"Zierenberg",
    "sg:phone":"+49 5606/7115",
    "sg:postcode":"34289",
    "sg:province":"Hessen",
    "wof:name":"H. Schaub",
    "wof:placetype":"venue"
},
  "geometry": {"coordinates":[9.2605838776,51.3108177185],"type":"Point"}
}