{
  "type": "Feature",
  "properties": {
    "iso:country":"DE",
    "sg:address":"Martinstr. 3",
    "sg:city":"Friedberg",
    "sg:phone":"+49 821/605319",
    "sg:postcode":"86316",
    "sg:province":"Bayern",
    "wof:name":"Josef Wolf",
    "wof:placetype":"venue"
},
  "geometry": {"coordinates":[11.008442,48.332939],"type":"Point"}
}