{
  "type": "Feature",
  "properties": {
    "iso:country":"DE",
    "sg:address":"Lehmbachstr. 17",
    "sg:city":"Oberhausen",
    "sg:phone":"+49 208/651360",
    "sg:postcode":"46149",
    "sg:province":"Nordrhein-Westfalen",
    "wof:name":"Theo Overdreef",
    "wof:placetype":"venue"
},
  "geometry": {"coordinates":[6.830785,51.501099],"type":"Point"}
}