{
  "type": "Feature",
  "properties": {
    "iso:country":"DE",
    "sg:address":"Im Heggelsfeld 49",
    "sg:city":"Krefeld",
    "sg:phone":"+49 2151/560255",
    "sg:postcode":"47802",
    "sg:province":"Nordrhein-Westfalen",
    "wof:name":"Karl Golubarsch",
    "wof:placetype":"venue"
},
  "geometry": {"coordinates":[6.589758,51.373749],"type":"Point"}
}