{
  "type": "Feature",
  "properties": {
    "iso:country":"DE",
    "sg:address":"Apothekenstr. 1",
    "sg:city":"Walldorf",
    "sg:phone":"+49 6227/2652",
    "sg:postcode":"69190",
    "sg:province":"Baden-W\u00fcrttemberg",
    "wof:name":"Hans Jaklitsch",
    "wof:placetype":"venue"
},
  "geometry": {"coordinates":[8.6368656158,49.3016815186],"type":"Point"}
}