{
  "type": "Feature",
  "properties": {
    "iso:country":"DE",
    "sg:address":"Am Betzenr\u00f6der Weg 3",
    "sg:city":"Hessisch Lichtenau",
    "sg:phone":"+49 5602/700606",
    "sg:postcode":"37235",
    "sg:province":"Hessen",
    "wof:name":"Frank Reuter",
    "wof:placetype":"venue"
},
  "geometry": {"coordinates":[9.685306,51.206131],"type":"Point"}
}