{
  "type": "Feature",
  "properties": {
    "iso:country":"DE",
    "sg:address":"Rainwiesenweg 15",
    "sg:city":"Schwaig",
    "sg:postcode":"90571",
    "sg:province":"Bayern",
    "wof:name":"Ath Aufz\u00fcge Gmbh & Co. Kg",
    "wof:placetype":"venue"
},
  "geometry": {"coordinates":[11.1884117126,49.4776306152],"type":"Point"}
}