{
  "type": "Feature",
  "properties": {
    "iso:country":"DE",
    "sg:address":"Bremerhavener Str. 92",
    "sg:city":"Bremen",
    "sg:phone":"+49 421/3989190",
    "sg:postcode":"28219",
    "sg:province":"Bremen",
    "wof:name":"Zoohaus Wieding",
    "wof:placetype":"venue"
},
  "geometry": {"coordinates":[8.780025,53.098209],"type":"Point"}
}