{
  "type": "Feature",
  "properties": {
    "iso:country":"DE",
    "sg:address":"Landshuter Str. 74 f",
    "sg:city":"Regensburg",
    "sg:phone":"+49 941/7501963",
    "sg:postcode":"93053",
    "sg:province":"Bayern",
    "wof:name":"Reifen Und Autoservice F. J. Wolf Gmbh",
    "wof:placetype":"venue"
},
  "geometry": {"coordinates":[12.1030464172,48.9835700989],"type":"Point"}
}