{
  "type": "Feature",
  "properties": {
    "iso:country":"DE",
    "sg:address":"S\u00fcdlicher Rosengarten 29",
    "sg:city":"Ribnitz-Damgarten",
    "sg:phone":"+49 3821/713510",
    "sg:postcode":"18311",
    "sg:province":"Mecklenburg-Vorpommern",
    "wof:name":"Hartmut Schuldt Ingenieur",
    "wof:placetype":"venue"
},
  "geometry": {"coordinates":[12.4351911545,54.2413368225],"type":"Point"}
}