{
  "type": "Feature",
  "properties": {
    "iso:country":"DE",
    "sg:address":"Hasencleverstr. 108",
    "sg:city":"Solingen",
    "sg:phone":"+49 212/42247",
    "sg:postcode":"42659",
    "sg:province":"Nordrhein-Westfalen",
    "wof:name":"Georg Lehner",
    "wof:placetype":"venue"
},
  "geometry": {"coordinates":[7.141351,51.134666],"type":"Point"}
}