{
  "type": "Feature",
  "properties": {
    "iso:country":"DE",
    "sg:address":"H\u00fcttenstr. 1",
    "sg:city":"Goslar",
    "sg:phone":"+49 5321/33670",
    "sg:postcode":"38642",
    "sg:province":"Niedersachsen",
    "wof:name":"Electrocycling Anlagen Gmbh",
    "wof:placetype":"venue"
},
  "geometry": {"coordinates":[10.4839401245,51.9001541138],"type":"Point"}
}