{
  "type": "Feature",
  "properties": {
    "iso:country":"DE",
    "sg:address":"Klosterstr. 73",
    "sg:city":"W\u00fcrselen",
    "sg:phone":"+49 2405/5069",
    "sg:postcode":"52146",
    "sg:province":"Nordrhein-Westfalen",
    "wof:name":"Stefan Hammers Architekt",
    "wof:placetype":"venue"
},
  "geometry": {"coordinates":[6.126375,50.818348],"type":"Point"}
}