{
  "type": "Feature",
  "properties": {
    "iso:country":"DE",
    "sg:address":"Gladbacher Strasse 21",
    "sg:city":"Heinsberg",
    "sg:phone":"+49 2452/96710",
    "sg:postcode":"52525",
    "sg:province":"Nordrhein-Westfalen",
    "wof:name":"Euromat Gmbh",
    "wof:placetype":"venue"
},
  "geometry": {"coordinates":[6.1608700752,51.0455284119],"type":"Point"}
}