{
  "type": "Feature",
  "properties": {
    "iso:country":"DE",
    "sg:address":"Schulstr. 19",
    "sg:city":"Bexbach",
    "sg:phone":"+49 6826/6309",
    "sg:postcode":"66450",
    "sg:province":"Saarland",
    "wof:name":"Kath. Pfarramt St. Josef",
    "wof:placetype":"venue"
},
  "geometry": {"coordinates":[7.2580118179,49.3784942627],"type":"Point"}
}