{
  "type": "Feature",
  "properties": {
    "iso:country":"DE",
    "sg:address":"Waldstr. 142",
    "sg:city":"Wiesbaden",
    "sg:phone":"+49 611/809190",
    "sg:postcode":"65197",
    "sg:province":"Hessen",
    "wof:name":"S. Mittelst\u00e4dt Immobilienmakler",
    "wof:placetype":"venue"
},
  "geometry": {"coordinates":[8.2217493057,50.0678825378],"type":"Point"}
}