{
  "type": "Feature",
  "properties": {
    "iso:country":"DE",
    "sg:address":"Dammweg 10",
    "sg:city":"Berlin",
    "sg:phone":"+49 30/5334931",
    "sg:postcode":"12435",
    "sg:province":"Berlin",
    "wof:name":"Sabine Landschek",
    "wof:placetype":"venue"
},
  "geometry": {"coordinates":[13.482086,52.479492],"type":"Point"}
}