{
  "type": "Feature",
  "properties": {
    "iso:country":"DE",
    "sg:address":"Am Stadtwald 6",
    "sg:city":"Wickede",
    "sg:phone":"+49 2377/914914",
    "sg:postcode":"58739",
    "sg:province":"Nordrhein-Westfalen",
    "wof:name":"Severin Vertriebsgesellschaft Mbh",
    "wof:placetype":"venue"
},
  "geometry": {"coordinates":[7.877283,51.511524],"type":"Point"}
}