{
  "type": "Feature",
  "properties": {
    "iso:country":"DE",
    "sg:address":"Schweinheimer Str. 148",
    "sg:city":"Aschaffenburg",
    "sg:phone":"+49 6021/96124",
    "sg:postcode":"63743",
    "sg:province":"Bayern",
    "wof:name":"Pizzeria Abruzzo",
    "wof:placetype":"venue"
},
  "geometry": {"coordinates":[9.1643180847,49.9593658447],"type":"Point"}
}