{
  "type": "Feature",
  "properties": {
    "iso:country":"DE",
    "sg:address":"Kellenbergstr. 18",
    "sg:city":"Melle",
    "sg:phone":"+49 5427/6223",
    "sg:postcode":"49328",
    "sg:province":"Niedersachsen",
    "wof:name":"Am Gr\u00fcnen See",
    "wof:placetype":"venue"
},
  "geometry": {"coordinates":[8.4478616714,52.2571258545],"type":"Point"}
}