{
  "type": "Feature",
  "properties": {
    "iso:country":"DE",
    "sg:address":"Lu\u00dfhardtstr. 1a",
    "sg:city":"Neulu\u00dfheim",
    "sg:phone":"+49 6205/34458",
    "sg:postcode":"68809",
    "sg:province":"Baden-W\u00fcrttemberg",
    "wof:name":"Dragoljub Nanovski",
    "wof:placetype":"venue"
},
  "geometry": {"coordinates":[8.522045,49.290546],"type":"Point"}
}