{
  "type": "Feature",
  "properties": {
    "iso:country":"DE",
    "sg:address":"Gie\u00dferweg 5",
    "sg:city":"Wernigerode",
    "sg:phone":"+49 3943/628360",
    "sg:postcode":"38855",
    "sg:province":"Sachsen-Anhalt",
    "wof:name":"Aes-alternative Energie Systeme Gmbh",
    "wof:placetype":"venue"
},
  "geometry": {"coordinates":[10.768298,51.839943],"type":"Point"}
}