{
  "type": "Feature",
  "properties": {
    "iso:country":"DE",
    "sg:address":"Wasenmeisterei 3",
    "sg:city":"Wilhermsdorf",
    "sg:phone":"+49 9102/530",
    "sg:postcode":"91452",
    "sg:province":"Bayern",
    "wof:name":"Kleinert Ohg",
    "wof:placetype":"venue"
},
  "geometry": {"coordinates":[10.718567,49.488819],"type":"Point"}
}