{
  "type": "Feature",
  "properties": {
    "iso:country":"DE",
    "sg:address":"Bahnhofstr. 1",
    "sg:city":"Wettrup",
    "sg:phone":"+49 5904/1276",
    "sg:postcode":"49838",
    "sg:province":"Niedersachsen",
    "wof:name":"Raiffeisen-warengenossenschaft Bawinkel-gersten-langen Eg",
    "wof:placetype":"venue"
},
  "geometry": {"coordinates":[7.590212,52.577316],"type":"Point"}
}