{
  "type": "Feature",
  "properties": {
    "iso:country":"DE",
    "sg:address":"Rodensteinstr. 13",
    "sg:city":"Bensheim",
    "sg:phone":"+49 6251/581731",
    "sg:postcode":"64625",
    "sg:province":"Hessen",
    "wof:name":"Penny",
    "wof:placetype":"venue"
},
  "geometry": {"coordinates":[8.6193675995,49.6825866699],"type":"Point"}
}