{
  "type": "Feature",
  "properties": {
    "iso:country":"DE",
    "sg:address":"Dohlenweg 3",
    "sg:city":"Kamp-Lintfort",
    "sg:phone":"+49 2842/470342",
    "sg:postcode":"47475",
    "sg:province":"Nordrhein-Westfalen",
    "wof:name":"G\u00fcnter Kautz",
    "wof:placetype":"venue"
},
  "geometry": {"coordinates":[6.535717,51.512012],"type":"Point"}
}