{
  "type": "Feature",
  "properties": {
    "iso:country":"DE",
    "sg:address":"Feldm\u00fchlestr. 28a",
    "sg:city":"Niederkassel",
    "sg:phone":"+49 4922/088700",
    "sg:postcode":"53859",
    "sg:province":"Nordrhein-Westfalen",
    "wof:name":"Rudolf Doufrain",
    "wof:placetype":"venue"
},
  "geometry": {"coordinates":[7.025662,50.829571],"type":"Point"}
}