{
  "type": "Feature",
  "properties": {
    "iso:country":"DE",
    "sg:address":"Am Bahnhof 65",
    "sg:city":"Mellinghausen",
    "sg:phone":"+49 4272/1799",
    "sg:postcode":"27249",
    "sg:province":"Niedersachsen",
    "wof:name":"D. H\u00f6tker",
    "wof:placetype":"venue"
},
  "geometry": {"coordinates":[8.895736,52.70071],"type":"Point"}
}