{
  "type": "Feature",
  "properties": {
    "iso:country":"DE",
    "sg:address":"Kriegsstr. 39",
    "sg:city":"Karlsruhe",
    "sg:phone":"+49 721/9374114",
    "sg:postcode":"76133",
    "sg:province":"Baden-W\u00fcrttemberg",
    "wof:name":"Bauer Portrait-atelier",
    "wof:placetype":"venue"
},
  "geometry": {"coordinates":[8.396604538,49.0052108765],"type":"Point"}
}