{
  "type": "Feature",
  "properties": {
    "iso:country":"DE",
    "sg:address":"Assestr. 23",
    "sg:city":"Vahlberg",
    "sg:phone":"+49 5333/1013",
    "sg:postcode":"38170",
    "sg:province":"Niedersachsen",
    "wof:name":"Alfred Libbe",
    "wof:placetype":"venue"
},
  "geometry": {"coordinates":[10.698757,52.138672],"type":"Point"}
}