{
  "type": "Feature",
  "properties": {
    "iso:country":"DE",
    "sg:address":"Westerbleichstr. 38",
    "sg:city":"Dortmund",
    "sg:phone":"+49 231/7282564",
    "sg:postcode":"44147",
    "sg:province":"Nordrhein-Westfalen",
    "wof:name":"Pizzeria Calabria",
    "wof:placetype":"venue"
},
  "geometry": {"coordinates":[7.4562211037,51.5215492249],"type":"Point"}
}