{
  "type": "Feature",
  "properties": {
    "iso:country":"DE",
    "sg:address":"M\u00fchlestr. 6",
    "sg:city":"L\u00f6rrach",
    "sg:phone":"+49 7621/10451",
    "sg:postcode":"79539",
    "sg:province":"Baden-W\u00fcrttemberg",
    "wof:name":"Yimpas Einkauf Und Import Handels Gmbh",
    "wof:placetype":"venue"
},
  "geometry": {"coordinates":[7.6567220688,47.6269454956],"type":"Point"}
}