{
  "type": "Feature",
  "properties": {
    "iso:country":"DE",
    "sg:address":"Grasinger Weg 40",
    "sg:city":"Ingolstadt",
    "sg:phone":"+49 8450/7028",
    "sg:postcode":"85051",
    "sg:province":"Bayern",
    "wof:name":"Wesma Schwei\u00dftechnik S\u00fcd Gmbh",
    "wof:placetype":"venue"
},
  "geometry": {"coordinates":[11.4040908813,48.7075309753],"type":"Point"}
}