{
  "type": "Feature",
  "properties": {
    "iso:country":"DE",
    "sg:address":"Boltenhagener Str. 7",
    "sg:city":"Kl\u00fctz",
    "sg:phone":"+49 38825/22574",
    "sg:postcode":"23948",
    "sg:province":"Mecklenburg-Vorpommern",
    "wof:name":"Klaus M\u00f6ller",
    "wof:placetype":"venue"
},
  "geometry": {"coordinates":[11.168814,53.966331],"type":"Point"}
}