{
  "type": "Feature",
  "properties": {
    "iso:country":"DE",
    "sg:address":"Pertelgasse 1",
    "sg:city":"Saulheim",
    "sg:phone":"+49 6732/5052",
    "sg:postcode":"55291",
    "sg:province":"Rheinland-Pfalz",
    "wof:name":"Fsk Stahlbau Gmbh",
    "wof:placetype":"venue"
},
  "geometry": {"coordinates":[8.14827,49.87645],"type":"Point"}
}