{
  "type": "Feature",
  "properties": {
    "iso:country":"DE",
    "sg:address":"Kohlisstr. 27",
    "sg:city":"Berlin",
    "sg:phone":"+49 30/5676052",
    "sg:postcode":"12623",
    "sg:province":"Berlin",
    "wof:name":"Klaus F\u00f6rster",
    "wof:placetype":"venue"
},
  "geometry": {"coordinates":[13.5930366516,52.4784011841],"type":"Point"}
}