{
  "type": "Feature",
  "properties": {
    "iso:country":"DE",
    "sg:address":"Gro\u00dfbeerenstr. 64",
    "sg:city":"Berlin",
    "sg:phone":"+49 30/2516333",
    "sg:postcode":"10963",
    "sg:province":"Berlin",
    "wof:name":"Pension Kreuzberg",
    "wof:placetype":"venue"
},
  "geometry": {"coordinates":[13.3839902878,52.4943122864],"type":"Point"}
}