{
  "type": "Feature",
  "properties": {
    "iso:country":"DE",
    "sg:address":"Siegesstr. 1",
    "sg:city":"Hannover",
    "sg:phone":"+49 511/3884888",
    "sg:postcode":"30175",
    "sg:province":"Niedersachsen",
    "wof:name":"Uhambo E Africa Touristik Gmbh",
    "wof:placetype":"venue"
},
  "geometry": {"coordinates":[9.7588243484,52.3784294128],"type":"Point"}
}