{
  "type": "Feature",
  "properties": {
    "iso:country":"DE",
    "sg:address":"H\u00f6velhoferstr. 59",
    "sg:city":"Delbr\u00fcck-Ostenland",
    "sg:postcode":"33129",
    "sg:province":"Nordrhein-Westfalen",
    "wof:name":"Sts Stefan Schmitz Gmbh & Co. Kg",
    "wof:placetype":"venue"
},
  "geometry": {"coordinates":[8.6218566895,51.8140144348],"type":"Point"}
}