{
  "type": "Feature",
  "properties": {
    "iso:country":"DE",
    "sg:address":"Br\u00e4unleinsberg 3",
    "sg:city":"Ottensoos",
    "sg:postcode":"91242",
    "sg:province":"Bayern",
    "wof:name":"B\u00e4r Leatherwear Dieter B\u00e4r",
    "wof:placetype":"venue"
},
  "geometry": {"coordinates":[11.3307800293,49.5173912048],"type":"Point"}
}