{
  "type": "Feature",
  "properties": {
    "iso:country":"DE",
    "sg:address":"Dorfstr. 58",
    "sg:city":"Osch\u00e4tzchen",
    "sg:phone":"+49 35341/10254",
    "sg:postcode":"04924",
    "sg:province":"Brandenburg",
    "wof:name":"Reichels Gastst\u00e4tte",
    "wof:placetype":"venue"
},
  "geometry": {"coordinates":[13.3877716064,51.4715194702],"type":"Point"}
}