{
  "type": "Feature",
  "properties": {
    "iso:country":"DE",
    "sg:address":"Weidenstr. 3",
    "sg:city":"Huglfing",
    "sg:phone":"+49 8802/180",
    "sg:postcode":"82386",
    "sg:province":"Bayern",
    "wof:name":"Johann Listl Kies- Und Bagger- Betrieb Verwaltungs Gmbh",
    "wof:placetype":"venue"
},
  "geometry": {"coordinates":[11.161002,47.754753],"type":"Point"}
}