{
  "type": "Feature",
  "properties": {
    "iso:country":"DE",
    "sg:address":"Wilhelm-Breckow-Allee 15",
    "sg:city":"Gummersbach",
    "sg:phone":"+49 2261/21047",
    "sg:postcode":"51643",
    "sg:province":"Nordrhein-Westfalen",
    "wof:name":"Landeszentralbank In Nordrhein-westfalen",
    "wof:placetype":"venue"
},
  "geometry": {"coordinates":[7.5675549507,51.0292816162],"type":"Point"}
}