{
  "type": "Feature",
  "properties": {
    "iso:country":"DE",
    "sg:address":"M\u00fchlenkamp 58",
    "sg:city":"Barsbek",
    "sg:phone":"+49 4344/9806",
    "sg:postcode":"24217",
    "sg:province":"Schleswig-Holstein",
    "wof:name":"S. Und M. Drews",
    "wof:placetype":"venue"
},
  "geometry": {"coordinates":[10.3228816986,54.4043426514],"type":"Point"}
}