{
  "type": "Feature",
  "properties": {
    "iso:country":"DE",
    "sg:address":"Gro\u00dfe Ulrichstr. 53",
    "sg:city":"Halle",
    "sg:phone":"+49 345/2023564",
    "sg:postcode":"06108",
    "sg:province":"Sachsen-Anhalt",
    "wof:name":"Eckart Becker-j\u00fcrgen",
    "wof:placetype":"venue"
},
  "geometry": {"coordinates":[11.9690742493,51.4849586487],"type":"Point"}
}