{
  "type": "Feature",
  "properties": {
    "iso:country":"DE",
    "sg:address":"Schlo\u00dfgasse",
    "sg:city":"M\u00fchltroff",
    "sg:postcode":"07919",
    "sg:province":"Th\u00fcringen",
    "wof:name":"Katholisches Pfarramt",
    "wof:placetype":"venue"
},
  "geometry": {"coordinates":[11.9291620255,50.5405044556],"type":"Point"}
}