{
  "type": "Feature",
  "properties": {
    "iso:country":"DE",
    "sg:address":"Siegritz",
    "sg:city":"Erbendorf",
    "sg:phone":"+49 9682/1411",
    "sg:postcode":"92681",
    "sg:province":"Bayern",
    "wof:name":"M. Heimerl",
    "wof:placetype":"venue"
},
  "geometry": {"coordinates":[12.0693702698,49.8606491089],"type":"Point"}
}