{
  "type": "Feature",
  "properties": {
    "iso:country":"DE",
    "sg:address":"Utm\u00fchlenweg 5a",
    "sg:city":"Kirchlengern",
    "sg:phone":"+49 5223/78631",
    "sg:postcode":"32278",
    "sg:province":"Nordrhein-Westfalen",
    "wof:name":"Weiterbildung.de Gmbh Win.",
    "wof:placetype":"venue"
},
  "geometry": {"coordinates":[8.644821,52.198814],"type":"Point"}
}