{
  "type": "Feature",
  "properties": {
    "iso:country":"DE",
    "sg:address":"Bergseestr. 93",
    "sg:city":"Bad S\u00e4ckingen",
    "sg:phone":"+49 7761/7575",
    "sg:postcode":"79713",
    "sg:province":"Baden-W\u00fcrttemberg",
    "wof:name":"Cafe-restaurant Bergsee",
    "wof:placetype":"venue"
},
  "geometry": {"coordinates":[7.9414181709,47.5626869202],"type":"Point"}
}