{
  "type": "Feature",
  "properties": {
    "iso:country":"DE",
    "sg:address":"Am S\u00f6hlberg 6",
    "sg:city":"Denkte",
    "sg:phone":"+49 5331/906103",
    "sg:postcode":"38321",
    "sg:province":"Niedersachsen",
    "wof:name":"Johannesson Ingenieur",
    "wof:placetype":"venue"
},
  "geometry": {"coordinates":[10.607878685,52.1470222473],"type":"Point"}
}