{
  "type": "Feature",
  "properties": {
    "iso:country":"DE",
    "sg:address":"Faktoreistrasse 4",
    "sg:city":"Saarbr\u00fccken",
    "sg:phone":"+49 4968/140010",
    "sg:postcode":"66111",
    "sg:province":"Saarland",
    "wof:name":"Credit Lyonnais Portugal",
    "wof:placetype":"venue"
},
  "geometry": {"coordinates":[6.989399,49.238125],"type":"Point"}
}