{
  "type": "Feature",
  "properties": {
    "iso:country":"DE",
    "sg:address":"Webergasse 8",
    "sg:city":"Aschaffenburg",
    "sg:phone":"+49 6021/26544",
    "sg:postcode":"63739",
    "sg:province":"Bayern",
    "wof:name":"Winstub",
    "wof:placetype":"venue"
},
  "geometry": {"coordinates":[9.1429290771,49.9739227295],"type":"Point"}
}