{
  "type": "Feature",
  "properties": {
    "iso:country":"DE",
    "sg:address":"Lehwaldstr. 27-29",
    "sg:city":"M\u00f6nchengladbach",
    "sg:phone":"+49 2166/62960",
    "sg:postcode":"41236",
    "sg:province":"Nordrhein-Westfalen",
    "wof:name":"Hotel Rheydter Residenz",
    "wof:placetype":"venue"
},
  "geometry": {"coordinates":[6.4526228905,51.1644210815],"type":"Point"}
}