{
  "type": "Feature",
  "properties": {
    "iso:country":"DE",
    "sg:address":"Westenhellweg 17",
    "sg:city":"Dortmund",
    "sg:phone":"+49 231/553880",
    "sg:postcode":"44137",
    "sg:province":"Nordrhein-Westfalen",
    "wof:name":"Czeratzkj Gmbh",
    "wof:placetype":"venue"
},
  "geometry": {"coordinates":[7.465004921,51.5144042969],"type":"Point"}
}