{
  "type": "Feature",
  "properties": {
    "iso:country":"DE",
    "sg:address":"Grabenstr. 66",
    "sg:city":"Niederzier",
    "sg:phone":"+49 2428/8042",
    "sg:postcode":"52382",
    "sg:province":"Nordrhein-Westfalen",
    "wof:name":"Dtg Gmbh",
    "wof:placetype":"venue"
},
  "geometry": {"coordinates":[6.4535050392,50.8470458984],"type":"Point"}
}