{
  "type": "Feature",
  "properties": {
    "iso:country":"DE",
    "sg:address":"R\u00f6diger Str. 99",
    "sg:city":"Wuppertal",
    "sg:phone":"+49 202/596043",
    "sg:postcode":"42283",
    "sg:province":"Nordrhein-Westfalen",
    "wof:name":"F. Gruse",
    "wof:placetype":"venue"
},
  "geometry": {"coordinates":[7.1863160133,51.2747001648],"type":"Point"}
}