{
  "type": "Feature",
  "properties": {
    "iso:country":"DE",
    "sg:address":"Werner-von-Siemens-Str. 19",
    "sg:city":"Forst",
    "sg:postcode":"76694",
    "sg:province":"Baden-W\u00fcrttemberg",
    "wof:name":"Roundliner Gesellschaft F\u00fcr Umweltfreundliche",
    "wof:placetype":"venue"
},
  "geometry": {"coordinates":[8.572296,49.160137],"type":"Point"}
}