{
  "type": "Feature",
  "properties": {
    "iso:country":"DE",
    "sg:address":"Nierenhofer Str. 45",
    "sg:city":"Hattingen",
    "sg:phone":"+49 2324/593099",
    "sg:postcode":"45529",
    "sg:province":"Nordrhein-Westfalen",
    "wof:name":"Restaurant Olympic Flame",
    "wof:placetype":"venue"
},
  "geometry": {"coordinates":[7.1697697639,51.3868789673],"type":"Point"}
}