{
  "type": "Feature",
  "properties": {
    "iso:country":"DE",
    "sg:address":"Elisenstr. 31",
    "sg:city":"Aschaffenburg",
    "sg:postcode":"63739",
    "sg:province":"Bayern",
    "wof:name":"August Wei\u00df Tabakwarengro\u00dfhandlung Ohg",
    "wof:placetype":"venue"
},
  "geometry": {"coordinates":[9.1456098557,49.9796638489],"type":"Point"}
}