{
  "type": "Feature",
  "properties": {
    "iso:country":"DE",
    "sg:address":"Freiherren-von-Friesen-Str. 02",
    "sg:city":"R\u00f6tha",
    "sg:phone":"+49 34206/6170",
    "sg:postcode":"04571",
    "sg:province":"Sachsen",
    "wof:name":"Ww Team Plan Gmbh",
    "wof:placetype":"venue"
},
  "geometry": {"coordinates":[12.428518,51.19846],"type":"Point"}
}