{
  "type": "Feature",
  "properties": {
    "iso:country":"DE",
    "sg:address":"Kleinalbershof",
    "sg:city":"Edelsfeld",
    "sg:phone":"+49 9665/498",
    "sg:postcode":"92265",
    "sg:province":"Bayern",
    "wof:name":"D. Woisczyk",
    "wof:placetype":"venue"
},
  "geometry": {"coordinates":[11.69537,49.596779],"type":"Point"}
}