{
  "type": "Feature",
  "properties": {
    "iso:country":"DE",
    "sg:address":"Dorfstr. 42",
    "sg:city":"Flintbek",
    "sg:phone":"+49 4347/9722",
    "sg:postcode":"24220",
    "sg:province":"Schleswig-Holstein",
    "wof:name":"U. Goossen",
    "wof:placetype":"venue"
},
  "geometry": {"coordinates":[10.074898,54.240166],"type":"Point"}
}