{
  "type": "Feature",
  "properties": {
    "iso:country":"DE",
    "sg:address":"L\u00f6wenmarkt 5",
    "sg:city":"Stuttgart",
    "sg:phone":"+49 711/881078",
    "sg:postcode":"70499",
    "sg:province":"Baden-W\u00fcrttemberg",
    "wof:name":"Hanle Und Partner",
    "wof:placetype":"venue"
},
  "geometry": {"coordinates":[9.1133089066,48.8142089844],"type":"Point"}
}