{
  "type": "Feature",
  "properties": {
    "iso:country":"DE",
    "sg:address":"Hermann-L\u00f6ns-Str. 20-22",
    "sg:city":"Munster",
    "sg:phone":"+49 5192/2510",
    "sg:postcode":"29633",
    "sg:province":"Niedersachsen",
    "wof:name":"Maess Inh. U. Korn",
    "wof:placetype":"venue"
},
  "geometry": {"coordinates":[10.080905,52.992485],"type":"Point"}
}