{
  "type": "Feature",
  "properties": {
    "iso:country":"DE",
    "sg:address":"Reimsbacher Str. 59",
    "sg:city":"Beckingen",
    "sg:phone":"+49 6832/91245",
    "sg:postcode":"66701",
    "sg:province":"Saarland",
    "wof:name":"Pizza Saloon-pizza Und Flamm- Kuchen Vom Holzfeuer Gmbh",
    "wof:placetype":"venue"
},
  "geometry": {"coordinates":[6.7674798965,49.4509277344],"type":"Point"}
}