{
  "type": "Feature",
  "properties": {
    "iso:country":"DE",
    "sg:address":"Bayreuther Str. 3",
    "sg:city":"Marktredwitz",
    "sg:phone":"+49 9231/82448",
    "sg:postcode":"95615",
    "sg:province":"Bayern",
    "wof:name":"G. Schiffl-solarien Und Saunas E. K.",
    "wof:placetype":"venue"
},
  "geometry": {"coordinates":[12.0767507553,50.0035438538],"type":"Point"}
}