{
  "type": "Feature",
  "properties": {
    "iso:country":"DE",
    "sg:address":"Alt-Friedrichsfelde 62 a",
    "sg:city":"Berlin",
    "sg:postcode":"10315",
    "sg:province":"Berlin",
    "wof:name":"Kaiser & Kaiser Fahrzeugtechnik Gmbh",
    "wof:placetype":"venue"
},
  "geometry": {"coordinates":[13.5219926834,52.5103378296],"type":"Point"}
}