{
  "type": "Feature",
  "properties": {
    "iso:country":"DE",
    "sg:address":"Pingsdorfer Str. 145",
    "sg:city":"Br\u00fchl",
    "sg:phone":"+49 2232/43462",
    "sg:postcode":"50321",
    "sg:province":"Nordrhein-Westfalen",
    "wof:name":"L. Beils",
    "wof:placetype":"venue"
},
  "geometry": {"coordinates":[6.8938140869,50.8187484741],"type":"Point"}
}