{
  "type": "Feature",
  "properties": {
    "iso:country":"DE",
    "sg:address":"Harnischstr. 12",
    "sg:city":"Hannover",
    "sg:postcode":"30163",
    "sg:province":"Niedersachsen",
    "wof:name":"S. Trhal",
    "wof:placetype":"venue"
},
  "geometry": {"coordinates":[9.7449426651,52.3896713257],"type":"Point"}
}