{
  "type": "Feature",
  "properties": {
    "iso:country":"DE",
    "sg:address":"Leuschnerstr. 91",
    "sg:city":"Hamburg",
    "sg:postcode":"21031",
    "sg:province":"Hamburg",
    "wof:name":"Ordinariat F\u00fcr Weltforstwirtschaft",
    "wof:placetype":"venue"
},
  "geometry": {"coordinates":[10.2030677795,53.5047721863],"type":"Point"}
}