{
  "type": "Feature",
  "properties": {
    "iso:country":"DE",
    "sg:address":"Morsbachallee 4-10",
    "sg:city":"Bad Oeynhausen",
    "sg:phone":"+49 5731/3937",
    "sg:postcode":"32545",
    "sg:province":"Nordrhein-Westfalen",
    "wof:name":"Maklerkontor Brand & Co. Versicherungsmakler Kg",
    "wof:placetype":"venue"
},
  "geometry": {"coordinates":[8.7982730865,52.1980743408],"type":"Point"}
}