{
  "type": "Feature",
  "properties": {
    "iso:country":"DE",
    "sg:address":"Kufsteiner Str. 7 b",
    "sg:city":"Riemerling",
    "sg:phone":"+49 89/6084404",
    "sg:postcode":"85521",
    "sg:province":"Bayern",
    "wof:name":"Serfolco Filter- Und Pumpen- Handels Gmbh",
    "wof:placetype":"venue"
},
  "geometry": {"coordinates":[11.671712,48.059555],"type":"Point"}
}