{
  "type": "Feature",
  "properties": {
    "iso:country":"DE",
    "sg:address":"Kantnersleite 2",
    "sg:city":"Neudrossenfeld",
    "sg:phone":"+49 9203/97252",
    "sg:postcode":"95512",
    "sg:province":"Bayern",
    "wof:name":"Hans Hofstetter",
    "wof:placetype":"venue"
},
  "geometry": {"coordinates":[11.4974308014,50.0174942017],"type":"Point"}
}