{
  "type": "Feature",
  "properties": {
    "iso:country":"DE",
    "sg:address":"Gartenstr.",
    "sg:city":"Augustusburg",
    "sg:phone":"+49 37291/20542",
    "sg:postcode":"09573",
    "sg:province":"Sachsen",
    "wof:name":"H\u00f6ckericht",
    "wof:placetype":"venue"
},
  "geometry": {"coordinates":[13.0681581497,50.8197059631],"type":"Point"}
}