{
  "type": "Feature",
  "properties": {
    "iso:country":"DE",
    "sg:address":"Sievekingsallee 105",
    "sg:city":"Hamburg",
    "sg:phone":"+49 40/212776",
    "sg:postcode":"20535",
    "sg:province":"Hamburg",
    "wof:name":"G\u00fcnter Hanisch Ohg",
    "wof:placetype":"venue"
},
  "geometry": {"coordinates":[10.0644350052,53.5600776672],"type":"Point"}
}