{
  "type": "Feature",
  "properties": {
    "iso:country":"DE",
    "sg:address":"N\u00fcrnberger Str. 186",
    "sg:city":"Regensburg",
    "sg:phone":"+49 941/84261",
    "sg:postcode":"93059",
    "sg:province":"Bayern",
    "wof:name":"Glockner Baugesch\u00e4ft Gmbh",
    "wof:placetype":"venue"
},
  "geometry": {"coordinates":[12.06964,49.031845],"type":"Point"}
}