{
  "type": "Feature",
  "properties": {
    "iso:country":"DE",
    "sg:address":"St.-Sebastianus-Str 20",
    "sg:city":"Merzenich",
    "sg:phone":"+49 2275/911042",
    "sg:postcode":"52399",
    "sg:province":"Nordrhein-Westfalen",
    "wof:name":"Bibu",
    "wof:placetype":"venue"
},
  "geometry": {"coordinates":[6.5251898766,50.8293495178],"type":"Point"}
}