{
  "type": "Feature",
  "properties": {
    "iso:country":"DE",
    "sg:address":"Rosa-Luxemburg-Str. 7",
    "sg:city":"Rostock",
    "sg:phone":"+49 381/4908888",
    "sg:postcode":"18055",
    "sg:province":"Mecklenburg-Vorpommern",
    "wof:name":"Nokia City Shop",
    "wof:placetype":"venue"
},
  "geometry": {"coordinates":[12.1371107101,54.0802116394],"type":"Point"}
}