{
  "type": "Feature",
  "properties": {
    "iso:country":"DE",
    "sg:address":"Ro\u00dfbachh\u00f6he 13",
    "sg:city":"Taunusstein",
    "sg:phone":"+49 6128/43225",
    "sg:postcode":"65232",
    "sg:province":"Hessen",
    "wof:name":"Af Service- Und Montage Gmbh Energie-spar-heizsysteme",
    "wof:placetype":"venue"
},
  "geometry": {"coordinates":[8.128837,50.130478],"type":"Point"}
}