{
  "type": "Feature",
  "properties": {
    "iso:country":"DE",
    "sg:address":"Dorfstr. 8-10",
    "sg:city":"Tangstedt",
    "sg:phone":"+49 4109/9357",
    "sg:postcode":"22889",
    "sg:province":"Schleswig-Holstein",
    "wof:name":"Alten- Und Pflegeheim Sommer Gmbh",
    "wof:placetype":"venue"
},
  "geometry": {"coordinates":[10.085116,53.73304],"type":"Point"}
}