{
  "type": "Feature",
  "properties": {
    "iso:country":"DE",
    "sg:address":"Jenfelder Stra\u00dfe 132",
    "sg:city":"Hamburg",
    "sg:phone":"+49 451/690510",
    "sg:postcode":"22045",
    "sg:province":"Hamburg",
    "wof:name":"Deutscher Wun Hop Kuen Do Verband E.v.",
    "wof:placetype":"venue"
},
  "geometry": {"coordinates":[10.1179113388,53.5742530823],"type":"Point"}
}