{
  "type": "Feature",
  "properties": {
    "iso:country":"DE",
    "sg:address":"Petersburger Str. 45",
    "sg:city":"Berlin",
    "sg:phone":"+49 30/42010428",
    "sg:postcode":"10249",
    "sg:province":"Berlin",
    "wof:name":"Fvh - Foto-video-handel Gmbh",
    "wof:placetype":"venue"
},
  "geometry": {"coordinates":[13.450922966,52.5222473145],"type":"Point"}
}