{
  "type": "Feature",
  "properties": {
    "iso:country":"DE",
    "sg:address":"Haldenweg 2",
    "sg:city":"St. Peter",
    "sg:phone":"+49 7660/307",
    "sg:postcode":"79271",
    "sg:province":"Baden-W\u00fcrttemberg",
    "wof:name":"Waldcafe",
    "wof:placetype":"venue"
},
  "geometry": {"coordinates":[8.03517,48.023434],"type":"Point"}
}