{
  "type": "Feature",
  "properties": {
    "iso:country":"DE",
    "sg:address":"Br\u00fcnnsteinstr. 48",
    "sg:city":"Erding",
    "sg:phone":"+49 8122/892112",
    "sg:postcode":"85435",
    "sg:province":"Bayern",
    "wof:name":"A. Poethe",
    "wof:placetype":"venue"
},
  "geometry": {"coordinates":[11.9058113098,48.2871322632],"type":"Point"}
}