{
  "type": "Feature",
  "properties": {
    "iso:country":"DE",
    "sg:address":"Hallerh\u00f6lzlweg 55",
    "sg:city":"Traitsching",
    "sg:phone":"+49 9974/671",
    "sg:postcode":"93455",
    "sg:province":"Bayern",
    "wof:name":"Gabi Wanninger",
    "wof:placetype":"venue"
},
  "geometry": {"coordinates":[12.635254,49.164528],"type":"Point"}
}