{
  "type": "Feature",
  "properties": {
    "iso:country":"DE",
    "sg:address":"An Der Leite",
    "sg:city":"K\u00f6nigsberg",
    "sg:phone":"+49 9525/92250",
    "sg:postcode":"97486",
    "sg:province":"Bayern",
    "wof:name":"Benkert - Benke",
    "wof:placetype":"venue"
},
  "geometry": {"coordinates":[10.5928058624,50.0621948242],"type":"Point"}
}