{
  "type": "Feature",
  "properties": {
    "iso:country":"DE",
    "sg:address":"Otto-Ohl-Weg 20",
    "sg:city":"W\u00fclfrath",
    "sg:phone":"+49 202/2729340",
    "sg:postcode":"42489",
    "sg:province":"Nordrhein-Westfalen",
    "wof:name":"Haus-otto-ohl Seniorenheim",
    "wof:placetype":"venue"
},
  "geometry": {"coordinates":[7.09096,51.28466],"type":"Point"}
}