{
  "type": "Feature",
  "properties": {
    "iso:country":"DE",
    "sg:address":"Konsul-Lindner-Str.",
    "sg:city":"Markt Erlbach",
    "sg:phone":"+49 9106/802",
    "sg:postcode":"91459",
    "sg:province":"Bayern",
    "wof:name":"Ev. Pfarramt Ii Gem. Markt Erlbach",
    "wof:placetype":"venue"
},
  "geometry": {"coordinates":[10.6513004303,49.4902458191],"type":"Point"}
}