{
  "type": "Feature",
  "properties": {
    "iso:country":"DE",
    "sg:address":"Querstr. 25",
    "sg:city":"Sulzbach",
    "sg:phone":"+49 6897/87417",
    "sg:postcode":"66280",
    "sg:province":"Saarland",
    "wof:name":"Edmund Voltz",
    "wof:placetype":"venue"
},
  "geometry": {"coordinates":[7.07859,49.307224],"type":"Point"}
}