{
  "type": "Feature",
  "properties": {
    "iso:country":"DE",
    "sg:address":"Waldstr.",
    "sg:city":"Biberach",
    "sg:postcode":"77781",
    "sg:province":"Baden-W\u00fcrttemberg",
    "wof:name":"Kaisers Markt",
    "wof:placetype":"venue"
},
  "geometry": {"coordinates":[8.0378484726,48.3396492004],"type":"Point"}
}