{
  "type": "Feature",
  "properties": {
    "iso:country":"DE",
    "sg:address":"Poststr. 47a",
    "sg:city":"W\u00e4chtersbach",
    "sg:phone":"+49 6053/1649",
    "sg:postcode":"63607",
    "sg:province":"Hessen",
    "wof:name":"Marie Hartz Inh. Gisela Wilhelm",
    "wof:placetype":"venue"
},
  "geometry": {"coordinates":[9.294507,50.255028],"type":"Point"}
}