{
  "type": "Feature",
  "properties": {
    "iso:country":"DE",
    "sg:address":"Neuer Markt 9",
    "sg:city":"Rechlin",
    "sg:phone":"+49 39823/21261",
    "sg:postcode":"17248",
    "sg:province":"Mecklenburg-Vorpommern",
    "wof:name":"Tourismus-f\u00f6rderungsges. Rechlin Mbh",
    "wof:placetype":"venue"
},
  "geometry": {"coordinates":[12.7222146988,53.3299636841],"type":"Point"}
}