{
  "type": "Feature",
  "properties": {
    "iso:country":"DE",
    "sg:address":"Gartenstr. 2",
    "sg:city":"H\u00fcpstedt",
    "sg:phone":"+49 36076/44428",
    "sg:postcode":"99976",
    "sg:province":"Th\u00fcringen",
    "wof:name":"Gisela Kost",
    "wof:placetype":"venue"
},
  "geometry": {"coordinates":[10.440459,51.325069],"type":"Point"}
}