{
  "type": "Feature",
  "properties": {
    "iso:country":"DE",
    "sg:address":"Schlosserstr. 9",
    "sg:city":"Remscheid",
    "sg:phone":"+49 4921/9155207",
    "sg:postcode":"42899",
    "sg:province":"Nordrhein-Westfalen",
    "wof:name":"Womaco Gmbh",
    "wof:placetype":"venue"
},
  "geometry": {"coordinates":[7.233039,51.220322],"type":"Point"}
}