{
  "type": "Feature",
  "properties": {
    "iso:country":"DE",
    "sg:address":"Chemnitzer Str. 15",
    "sg:city":"Penig",
    "sg:phone":"+49 37381/5118",
    "sg:postcode":"09322",
    "sg:province":"Sachsen",
    "wof:name":"L. Frauenheim",
    "wof:placetype":"venue"
},
  "geometry": {"coordinates":[12.706239,50.931591],"type":"Point"}
}