{
  "type": "Feature",
  "properties": {
    "iso:country":"DE",
    "sg:address":"Wei\u00dfenbrunner Str. 7",
    "sg:city":"Untersiemau",
    "sg:phone":"+49 9565/2595",
    "sg:postcode":"96253",
    "sg:province":"Bayern",
    "wof:name":"B. Senger",
    "wof:placetype":"venue"
},
  "geometry": {"coordinates":[10.9788360596,50.196559906],"type":"Point"}
}