{
  "type": "Feature",
  "properties": {
    "iso:country":"DE",
    "sg:address":"Gewerbering 26",
    "sg:city":"Niederkr\u00fcchten",
    "sg:phone":"+49 2163",
    "sg:postcode":"41372",
    "sg:province":"Nordrhein-Westfalen",
    "wof:name":"Www.hallenspielplatz.de",
    "wof:placetype":"venue"
},
  "geometry": {"coordinates":[6.1813201904,51.2090988159],"type":"Point"}
}