{
  "type": "Feature",
  "properties": {
    "iso:country":"DE",
    "sg:address":"Dachauer Str. 26",
    "sg:city":"F\u00fcrstenfeldbruck",
    "sg:phone":"+49 8141/63137",
    "sg:postcode":"82256",
    "sg:province":"Bayern",
    "wof:name":"Bestattungsinstitut Hanrieder Gmbh",
    "wof:placetype":"venue"
},
  "geometry": {"coordinates":[11.258393,48.179966],"type":"Point"}
}