{
  "type": "Feature",
  "properties": {
    "iso:country":"DE",
    "sg:address":"Auf der Ilberg 22",
    "sg:city":"Gevelsberg",
    "sg:phone":"+49 2332/50711",
    "sg:postcode":"58285",
    "sg:province":"Nordrhein-Westfalen",
    "wof:name":"Heinrich Echterhoff",
    "wof:placetype":"venue"
},
  "geometry": {"coordinates":[7.32394,51.354855],"type":"Point"}
}