{
  "type": "Feature",
  "properties": {
    "iso:country":"DE",
    "sg:address":"Gertrudenstr. 10",
    "sg:city":"Lohne",
    "sg:phone":"+49 4442/1387",
    "sg:postcode":"49393",
    "sg:province":"Niedersachsen",
    "wof:name":"Alfred Weghof",
    "wof:placetype":"venue"
},
  "geometry": {"coordinates":[8.2373,52.663673],"type":"Point"}
}