{
  "type": "Feature",
  "properties": {
    "iso:country":"DE",
    "sg:address":"Hauptstr. 22",
    "sg:city":"Sehestedt",
    "sg:phone":"+49 4357/1070",
    "sg:postcode":"24814",
    "sg:province":"Schleswig-Holstein",
    "wof:name":"Landhaus Sehestedt",
    "wof:placetype":"venue"
},
  "geometry": {"coordinates":[9.8184146881,54.365814209],"type":"Point"}
}