{
  "type": "Feature",
  "properties": {
    "iso:country":"DE",
    "sg:address":"In der Kirchtanne 33",
    "sg:city":"Darmstadt",
    "sg:phone":"+49 6151/591199",
    "sg:postcode":"64297",
    "sg:province":"Hessen",
    "wof:name":"Rauchfang",
    "wof:placetype":"venue"
},
  "geometry": {"coordinates":[8.6434583664,49.8063163757],"type":"Point"}
}