{
  "type": "Feature",
  "properties": {
    "iso:country":"DE",
    "sg:address":"Amselstr. 44",
    "sg:city":"Lampertheim",
    "sg:phone":"+49 621/785621",
    "sg:postcode":"68623",
    "sg:province":"Hessen",
    "wof:name":"Siri B\u00fcroservice E. K.",
    "wof:placetype":"venue"
},
  "geometry": {"coordinates":[8.487579,49.593586],"type":"Point"}
}