{
  "type": "Feature",
  "properties": {
    "iso:country":"DE",
    "sg:address":"Durchstr. 88",
    "sg:city":"Dortmund",
    "sg:phone":"+49 4923/1467999",
    "sg:postcode":"44265",
    "sg:province":"Nordrhein-Westfalen",
    "wof:name":"Dz-stahl Gmbh",
    "wof:placetype":"venue"
},
  "geometry": {"coordinates":[7.491523,51.464111],"type":"Point"}
}