{
  "type": "Feature",
  "properties": {
    "iso:country":"DE",
    "sg:address":"Wolfhagener Str. 71",
    "sg:city":"Wermelskirchen",
    "sg:phone":"+49 2196831974025",
    "sg:postcode":"42929",
    "sg:province":"Nordrhein-Westfalen",
    "wof:name":"Watte- Und Verbandstoffe Verwaltungsgesellschaft Mbh",
    "wof:placetype":"venue"
},
  "geometry": {"coordinates":[7.2081007957,51.1477661133],"type":"Point"}
}