{
  "type": "Feature",
  "properties": {
    "iso:country":"DE",
    "sg:address":"Krummer Weg 2",
    "sg:city":"Gronau",
    "sg:phone":"+49 2562/21218",
    "sg:postcode":"48599",
    "sg:province":"Nordrhein-Westfalen",
    "wof:name":"Vereinigte Filmtheater 1",
    "wof:placetype":"venue"
},
  "geometry": {"coordinates":[7.0493159294,52.2261543274],"type":"Point"}
}