{
  "type": "Feature",
  "properties": {
    "iso:country":"DE",
    "sg:address":"W\u00f6rthstr. 39",
    "sg:city":"Kiel",
    "sg:phone":"+49 431/14382",
    "sg:postcode":"24116",
    "sg:province":"Schleswig-Holstein",
    "wof:name":"Sommerfeld \u00b4s Cartoons",
    "wof:placetype":"venue"
},
  "geometry": {"coordinates":[10.115348,54.325596],"type":"Point"}
}