{
  "type": "Feature",
  "properties": {
    "iso:country":"DE",
    "sg:address":"Wilhelmstr. 11",
    "sg:city":"Frankenberg",
    "sg:phone":"+49 4964/514211",
    "sg:postcode":"35066",
    "sg:province":"Hessen",
    "wof:name":"Bhw",
    "wof:placetype":"venue"
},
  "geometry": {"coordinates":[8.799778,51.062988],"type":"Point"}
}