{
  "type": "Feature",
  "properties": {
    "iso:country":"DE",
    "sg:address":"Wolframstr. 12",
    "sg:city":"Untereisesheim",
    "sg:phone":"+49 7132/42581",
    "sg:postcode":"74257",
    "sg:province":"Baden-W\u00fcrttemberg",
    "wof:name":"Heinz W\u00f6hr Architekt Gmbh",
    "wof:placetype":"venue"
},
  "geometry": {"coordinates":[9.2039747238,49.2082557678],"type":"Point"}
}