{
  "type": "Feature",
  "properties": {
    "iso:country":"DE",
    "sg:address":"Silberdistelstr. 51",
    "sg:city":"M\u00fcnchen",
    "sg:postcode":"80689",
    "sg:province":"Bayern",
    "wof:name":"Olympiapark Hotel Gmbh & Co. Kg",
    "wof:placetype":"venue"
},
  "geometry": {"coordinates":[11.4786081314,48.1288871765],"type":"Point"}
}