{
  "type": "Feature",
  "properties": {
    "iso:country":"DE",
    "sg:address":"Am Thie 4",
    "sg:city":"Hehlen",
    "sg:phone":"+49 5533/2850",
    "sg:postcode":"37619",
    "sg:province":"Niedersachsen",
    "wof:name":"Ev. Pfarramt Hehlen",
    "wof:placetype":"venue"
},
  "geometry": {"coordinates":[9.4697628021,51.9839935303],"type":"Point"}
}