{
  "type": "Feature",
  "properties": {
    "iso:country":"DE",
    "sg:address":"35 rue Santos Dumont",
    "sg:city":"Paris",
    "sg:phone":"+49 156361543",
    "sg:postcode":"75015",
    "sg:province":"Baden-W\u00fcrttemberg",
    "wof:name":"Viriville, Un Village De Charme En France",
    "wof:placetype":"venue"
},
  "geometry": {"coordinates":[2.304548,48.832642],"type":"Point"}
}