{
  "type": "Feature",
  "properties": {
    "iso:country":"DE",
    "sg:address":"Friedrich-Seele-Str 10",
    "sg:city":"Braunschweig",
    "sg:phone":"+49 531/809010",
    "sg:postcode":"38122",
    "sg:province":"Niedersachsen",
    "wof:name":"Spedition Lagerpusch Gmbh",
    "wof:placetype":"venue"
},
  "geometry": {"coordinates":[10.5031442642,52.2408332825],"type":"Point"}
}