{
  "type": "Feature",
  "properties": {
    "iso:country":"DE",
    "sg:address":"Vluyner S\u00fcdring 94",
    "sg:city":"Neukirchen-Vluyn",
    "sg:phone":"+49 2845/21177",
    "sg:postcode":"47506",
    "sg:province":"Nordrhein-Westfalen",
    "wof:name":"H. Wagner",
    "wof:placetype":"venue"
},
  "geometry": {"coordinates":[6.5292978287,51.4360237122],"type":"Point"}
}