{
  "type": "Feature",
  "properties": {
    "iso:country":"DE",
    "sg:address":"Donaustr. 7",
    "sg:city":"Saarwellingen",
    "sg:phone":"+49 6838/2334",
    "sg:postcode":"66793",
    "sg:province":"Saarland",
    "wof:name":"Dietmar Andre",
    "wof:placetype":"venue"
},
  "geometry": {"coordinates":[6.812444,49.352676],"type":"Point"}
}