{
  "type": "Feature",
  "properties": {
    "iso:country":"DE",
    "sg:address":"Bahnhofstr. 19",
    "sg:city":"Hauzenberg",
    "sg:phone":"+49 8586/918678",
    "sg:postcode":"94051",
    "sg:province":"Bayern",
    "wof:name":"Matthias Bauer & Sohn",
    "wof:placetype":"venue"
},
  "geometry": {"coordinates":[13.6286258698,48.6469612122],"type":"Point"}
}