{
  "type": "Feature",
  "properties": {
    "iso:country":"DE",
    "sg:address":"Lichtenauer Str. 5",
    "sg:city":"Petersaurach",
    "sg:phone":"+49 172 8105808",
    "sg:postcode":"91580",
    "sg:province":"Bayern",
    "wof:name":"Hans Keim",
    "wof:placetype":"venue"
},
  "geometry": {"coordinates":[10.701615,49.3144],"type":"Point"}
}