{
  "type": "Feature",
  "properties": {
    "iso:country":"DE",
    "sg:address":"Rotfuchsweg 4",
    "sg:city":"M\u00fcnchen",
    "sg:postcode":"81827",
    "sg:province":"Bayern",
    "wof:name":"Cinedigit*.exe Willkommen",
    "wof:placetype":"venue"
},
  "geometry": {"coordinates":[11.696232,48.112705],"type":"Point"}
}