{
  "type": "Feature",
  "properties": {
    "iso:country":"DE",
    "sg:address":"Unkenstein 2",
    "sg:city":"Plein",
    "sg:phone":"+49 6571/8118",
    "sg:postcode":"54518",
    "sg:province":"Rheinland-Pfalz",
    "wof:name":"G. Koller",
    "wof:placetype":"venue"
},
  "geometry": {"coordinates":[6.957391,49.920593],"type":"Point"}
}