{
  "type": "Feature",
  "properties": {
    "iso:country":"DE",
    "sg:address":"An der Mangfall 3",
    "sg:city":"Rosenheim",
    "sg:phone":"+49 8031/95444",
    "sg:postcode":"83026",
    "sg:province":"Bayern",
    "wof:name":"G Und W Gewerbe- Und Wohnbau Gmbh",
    "wof:placetype":"venue"
},
  "geometry": {"coordinates":[12.085878,47.844238],"type":"Point"}
}