{
  "type": "Feature",
  "properties": {
    "iso:country":"DE",
    "sg:address":"Hauptstr. 46",
    "sg:city":"Buxheim",
    "sg:phone":"+49 7393/4828",
    "sg:postcode":"87740",
    "sg:province":"Bayern",
    "wof:name":"Ingo Schroeder Anlageberater",
    "wof:placetype":"venue"
},
  "geometry": {"coordinates":[10.1314992905,48.001083374],"type":"Point"}
}