{
  "type": "Feature",
  "properties": {
    "iso:country":"DE",
    "sg:address":"Hindenburgstr. 96",
    "sg:city":"Borkum",
    "sg:phone":"+49 4922/2426",
    "sg:postcode":"26757",
    "sg:province":"Niedersachsen",
    "wof:name":"Pension D. Dykmann",
    "wof:placetype":"venue"
},
  "geometry": {"coordinates":[6.6719141006,53.592502594],"type":"Point"}
}