{
  "type": "Feature",
  "properties": {
    "iso:country":"DE",
    "sg:address":"Germanenstra\u00dfe 25",
    "sg:city":"Niederkassel",
    "sg:phone":"+49 179 2922136",
    "sg:postcode":"53895",
    "sg:province":"Nordrhein-Westfalen",
    "wof:name":"Tobias Hahn Presseagentur",
    "wof:placetype":"venue"
},
  "geometry": {"coordinates":[7.0548968315,50.7842826843],"type":"Point"}
}