{
  "type": "Feature",
  "properties": {
    "iso:country":"DE",
    "sg:address":"Hegestr. 12",
    "sg:city":"Hamburg",
    "sg:phone":"+49 40/482092",
    "sg:postcode":"20251",
    "sg:province":"Hamburg",
    "wof:name":"Heinz K\u00fcster Schneiderei",
    "wof:placetype":"venue"
},
  "geometry": {"coordinates":[9.9808511734,53.5824279785],"type":"Point"}
}