{
  "type": "Feature",
  "properties": {
    "iso:country":"DE",
    "sg:address":"Lindenweg 10",
    "sg:city":"Arnschwang",
    "sg:phone":"+49 9977/8480",
    "sg:postcode":"93473",
    "sg:province":"Bayern",
    "wof:name":"K. Seitz",
    "wof:placetype":"venue"
},
  "geometry": {"coordinates":[12.8200817108,49.2795677185],"type":"Point"}
}