{
  "type": "Feature",
  "properties": {
    "iso:country":"DE",
    "sg:address":"Am Kohlenmeiler 10",
    "sg:city":"Wuppertal",
    "sg:phone":"+49 202/604285",
    "sg:postcode":"42389",
    "sg:province":"Nordrhein-Westfalen",
    "wof:name":"N. Schmidt",
    "wof:placetype":"venue"
},
  "geometry": {"coordinates":[7.241672039,51.2657737732],"type":"Point"}
}