{
  "type": "Feature",
  "properties": {
    "iso:country":"DE",
    "sg:address":"Paul-Robeson-Str. 35",
    "sg:city":"Berlin",
    "sg:phone":"+49 30/4499696",
    "sg:postcode":"10439",
    "sg:province":"Berlin",
    "wof:name":"Werner Zahn",
    "wof:placetype":"venue"
},
  "geometry": {"coordinates":[13.407195,52.552547],"type":"Point"}
}