{
  "type": "Feature",
  "properties": {
    "iso:country":"DE",
    "sg:address":"Am Klafelder Markt 12",
    "sg:city":"Siegen",
    "sg:phone":"+49 271/86299",
    "sg:postcode":"57078",
    "sg:province":"Nordrhein-Westfalen",
    "wof:name":"W. N\u00f6ll",
    "wof:placetype":"venue"
},
  "geometry": {"coordinates":[8.0093803406,50.9145202637],"type":"Point"}
}