{
  "type": "Feature",
  "properties": {
    "iso:country":"DE",
    "sg:address":"Klarastr.12",
    "sg:city":"Heilbronn",
    "sg:phone":"+49 4971/3178100",
    "sg:postcode":"74072",
    "sg:province":"Baden-W\u00fcrttemberg",
    "wof:name":"Globes Elektronik Gmbh & Co. Kg",
    "wof:placetype":"venue"
},
  "geometry": {"coordinates":[9.220771,49.140091],"type":"Point"}
}