{
  "type": "Feature",
  "properties": {
    "iso:country":"DE",
    "sg:address":"Donnersbergstr. 120 a",
    "sg:city":"Kaiserslautern",
    "sg:phone":"+49 631/42015",
    "sg:postcode":"67657",
    "sg:province":"Rheinland-Pfalz",
    "wof:name":"Hls Gmbh & Co. Kg",
    "wof:placetype":"venue"
},
  "geometry": {"coordinates":[7.7986388206,49.4493331909],"type":"Point"}
}