{
  "type": "Feature",
  "properties": {
    "iso:country":"DE",
    "sg:address":"Schulstr. 9",
    "sg:city":"Oberdreis",
    "sg:phone":"+49 2684/7327",
    "sg:postcode":"57639",
    "sg:province":"Rheinland-Pfalz",
    "wof:name":"M. Ohlenschl\u00e4ger",
    "wof:placetype":"venue"
},
  "geometry": {"coordinates":[7.6640400887,50.6440391541],"type":"Point"}
}