{
  "type": "Feature",
  "properties": {
    "iso:country":"DE",
    "sg:address":"Leopoldstr. 2",
    "sg:city":"Kuppenheim",
    "sg:phone":"+49 7222/4434",
    "sg:postcode":"76456",
    "sg:province":"Baden-W\u00fcrttemberg",
    "wof:name":"Walter P\u00fctz",
    "wof:placetype":"venue"
},
  "geometry": {"coordinates":[8.252505,48.827011],"type":"Point"}
}