{
  "type": "Feature",
  "properties": {
    "iso:country":"DE",
    "sg:address":"Landshuter Str. 8",
    "sg:city":"Wallersdorf",
    "sg:phone":"+49 9933/8108",
    "sg:postcode":"94522",
    "sg:province":"Bayern",
    "wof:name":"Erich Zschumpelt",
    "wof:placetype":"venue"
},
  "geometry": {"coordinates":[12.744481,48.736732],"type":"Point"}
}