{
  "type": "Feature",
  "properties": {
    "iso:country":"DE",
    "sg:address":"Haydnstr. 9",
    "sg:city":"Hilden",
    "sg:phone":"+49 2103/40150",
    "sg:postcode":"40724",
    "sg:province":"Nordrhein-Westfalen",
    "wof:name":"Willi Eichholz Ingenieur",
    "wof:placetype":"venue"
},
  "geometry": {"coordinates":[6.936439991,51.1798706055],"type":"Point"}
}