{
  "type": "Feature",
  "properties": {
    "iso:country":"DE",
    "sg:address":"Brausestr. 10",
    "sg:city":"Iserlohn",
    "sg:phone":"+49 2371/6591",
    "sg:postcode":"58636",
    "sg:province":"Nordrhein-Westfalen",
    "wof:name":"Neuhaus Gmbh Werkzeuge",
    "wof:placetype":"venue"
},
  "geometry": {"coordinates":[7.709162,51.373745],"type":"Point"}
}