{
  "type": "Feature",
  "properties": {
    "iso:country":"DE",
    "sg:address":"Heidelberger Str. 41",
    "sg:city":"Zwingenberg",
    "sg:phone":"+49 6251/78110",
    "sg:postcode":"64673",
    "sg:province":"Hessen",
    "wof:name":"Sylvia Menzel Krankengymnastin",
    "wof:placetype":"venue"
},
  "geometry": {"coordinates":[8.6135053635,49.7169570923],"type":"Point"}
}