{
  "type": "Feature",
  "properties": {
    "iso:country":"DE",
    "sg:address":"Nordbrocker Str.",
    "sg:city":"Hamminkeln",
    "sg:phone":"+49 2856/493",
    "sg:postcode":"46499",
    "sg:province":"Nordrhein-Westfalen",
    "wof:name":"Unter Den Linden",
    "wof:placetype":"venue"
},
  "geometry": {"coordinates":[6.6233301163,51.7668952942],"type":"Point"}
}