{
  "type": "Feature",
  "properties": {
    "iso:country":"DE",
    "sg:address":"Nr. 110",
    "sg:city":"Dittersdorf",
    "sg:postcode":"07907",
    "sg:province":"Th\u00fcringen",
    "wof:name":"Werner Schneider",
    "wof:placetype":"venue"
},
  "geometry": {"coordinates":[11.81709,50.592869],"type":"Point"}
}