{
  "type": "Feature",
  "properties": {
    "iso:country":"DE",
    "sg:address":"M\u00fchlenstr. 28",
    "sg:city":"B\u00fchl",
    "sg:phone":"+49 7223/22139",
    "sg:postcode":"77815",
    "sg:province":"Baden-W\u00fcrttemberg",
    "wof:name":"Reinhold Scherer",
    "wof:placetype":"venue"
},
  "geometry": {"coordinates":[8.1410665512,48.6957015991],"type":"Point"}
}