{
  "type": "Feature",
  "properties": {
    "iso:country":"DE",
    "sg:address":"Ofener Str. 44",
    "sg:city":"Oldenburg",
    "sg:phone":"+49 441/76544",
    "sg:postcode":"26121",
    "sg:province":"Niedersachsen",
    "wof:name":"Paracelsus Apotheke",
    "wof:placetype":"venue"
},
  "geometry": {"coordinates":[8.193894,53.142918],"type":"Point"}
}