{
  "type": "Feature",
  "properties": {
    "iso:country":"DE",
    "sg:address":"B. P. 65",
    "sg:city":"CHARENTON - LE - PONT CEDEX",
    "sg:postcode":"94220",
    "wof:name":"Invention . Europe",
    "wof:placetype":"venue"
},
  "geometry": {"coordinates":[2.41364,48.821571],"type":"Point"}
}