{
  "type": "Feature",
  "properties": {
    "iso:country":"DE",
    "sg:address":"Bodanstr. 16",
    "sg:city":"Konstanz",
    "sg:phone":"+49 7531/23616",
    "sg:postcode":"78462",
    "sg:province":"Baden-W\u00fcrttemberg",
    "wof:name":"K\u00fcchen-studio Harder Kg",
    "wof:placetype":"venue"
},
  "geometry": {"coordinates":[9.1745834351,47.6581230164],"type":"Point"}
}