{
  "type": "Feature",
  "properties": {
    "iso:country":"DE",
    "sg:address":"Solitudestr. 44",
    "sg:city":"Ludwigsburg",
    "sg:phone":"+49 7141/925386",
    "sg:postcode":"71638",
    "sg:province":"Baden-W\u00fcrttemberg",
    "wof:name":"Jung Gmbh",
    "wof:placetype":"venue"
},
  "geometry": {"coordinates":[9.1883993149,48.8908843994],"type":"Point"}
}