{
  "type": "Feature",
  "properties": {
    "iso:country":"DE",
    "sg:address":"Am Wilhelmschacht",
    "sg:city":"Borna",
    "sg:postcode":"04552",
    "sg:province":"Sachsen",
    "wof:name":"Apotheke Im Kaufland Borna",
    "wof:placetype":"venue"
},
  "geometry": {"coordinates":[12.48587,51.115501],"type":"Point"}
}