{
  "type": "Feature",
  "properties": {
    "iso:country":"DE",
    "sg:address":"K\u00f6nigstr. 119",
    "sg:city":"F\u00fcrth",
    "sg:phone":"+49 911/9718863",
    "sg:postcode":"90762",
    "sg:province":"Bayern",
    "wof:name":"Allcurat Unternehmensdienste Verwaltungs Gmbh",
    "wof:placetype":"venue"
},
  "geometry": {"coordinates":[10.99193,49.47509],"type":"Point"}
}