{
  "type": "Feature",
  "properties": {
    "iso:country":"DE",
    "sg:address":"Wasserstr 9",
    "sg:city":"Steinfurt",
    "sg:phone":"+49 2551/919300",
    "sg:postcode":"48565",
    "sg:province":"Nordrhein-Westfalen",
    "wof:name":"Regioconnect Gmbh",
    "wof:placetype":"venue"
},
  "geometry": {"coordinates":[7.3394379616,52.1483650208],"type":"Point"}
}