{
  "type": "Feature",
  "properties": {
    "iso:country":"DE",
    "sg:address":"Greisbacher Str. 6",
    "sg:city":"Burgau",
    "sg:phone":"+49 8222/7076",
    "sg:postcode":"89331",
    "sg:province":"Bayern",
    "wof:name":"Grossag Elektro- Hausger\u00e4te Gmbh",
    "wof:placetype":"venue"
},
  "geometry": {"coordinates":[10.384748,48.435589],"type":"Point"}
}