{
  "type": "Feature",
  "properties": {
    "iso:country":"DE",
    "sg:address":"Thuner Str. 75 c",
    "sg:city":"Stade",
    "sg:phone":"+49 4141/64515",
    "sg:postcode":"21680",
    "sg:province":"Niedersachsen",
    "wof:name":"Seifenhaus Horst Neubauer Inh. Bernd Nadstazik E. Kfm.",
    "wof:placetype":"venue"
},
  "geometry": {"coordinates":[9.46311,53.587341],"type":"Point"}
}