{
  "type": "Feature",
  "properties": {
    "iso:country":"DE",
    "sg:address":"Lindenmaierstr. 61",
    "sg:city":"Laupheim (Usu)",
    "sg:phone":"+49 7392/5768",
    "sg:postcode":"88471",
    "sg:province":"Baden-W\u00fcrttemberg",
    "wof:name":"Maschinenbau Eiberle",
    "wof:placetype":"venue"
},
  "geometry": {"coordinates":[9.8344154358,48.2285881042],"type":"Point"}
}