{
  "type": "Feature",
  "properties": {
    "iso:country":"DE",
    "sg:address":"Etzstr. 45",
    "sg:city":"Ergolding",
    "sg:phone":"+49 871/72102",
    "sg:postcode":"84030",
    "sg:province":"Bayern",
    "wof:name":"Bautest Ges. F\u00fcr Forschung Und Materialpr\u00fcf. Im Bauwesen Mbh",
    "wof:placetype":"venue"
},
  "geometry": {"coordinates":[12.1741313934,48.5646247864],"type":"Point"}
}