{
  "type": "Feature",
  "properties": {
    "iso:country":"DE",
    "sg:address":"Walburgisstr. 10 a",
    "sg:city":"Werl",
    "sg:phone":"+49 2922/2190",
    "sg:postcode":"59457",
    "sg:province":"Nordrhein-Westfalen",
    "wof:name":"Blumen-risse Gmbh & Co. Kg",
    "wof:placetype":"venue"
},
  "geometry": {"coordinates":[7.912426,51.555443],"type":"Point"}
}