{
  "type": "Feature",
  "properties": {
    "iso:country":"DE",
    "sg:address":"K\u00fcmperweg 9",
    "sg:city":"Ibbenb\u00fcren",
    "sg:phone":"+49 5451/88536",
    "sg:postcode":"49479",
    "sg:province":"Nordrhein-Westfalen",
    "wof:name":"Geesmann Tief- U. Stra\u00dfenbau Gmbh",
    "wof:placetype":"venue"
},
  "geometry": {"coordinates":[7.77416,52.276218],"type":"Point"}
}