{
  "type": "Feature",
  "properties": {
    "iso:country":"DE",
    "sg:address":"Laichanger 38",
    "sg:city":"P\u00f6ttmes",
    "sg:postcode":"86554",
    "sg:province":"Bayern",
    "wof:name":"Versicherungsvermittlung Karl Jehm\u00fcller Kg",
    "wof:placetype":"venue"
},
  "geometry": {"coordinates":[11.0980796814,48.5818710327],"type":"Point"}
}