{
  "type": "Feature",
  "properties": {
    "iso:country":"DE",
    "sg:address":"Kirchstr. 19",
    "sg:city":"Grafenau",
    "sg:phone":"+49 7033/43217",
    "sg:postcode":"71120",
    "sg:province":"Baden-W\u00fcrttemberg",
    "wof:name":"Paul Gau\u00df",
    "wof:placetype":"venue"
},
  "geometry": {"coordinates":[8.888714,48.717075],"type":"Point"}
}