{
  "type": "Feature",
  "properties": {
    "iso:country":"DE",
    "sg:address":"S\u00fcdring 3",
    "sg:city":"Scheinfeld",
    "sg:phone":"+49 9162/7708",
    "sg:postcode":"91443",
    "sg:province":"Bayern",
    "wof:name":"Renate Klein",
    "wof:placetype":"venue"
},
  "geometry": {"coordinates":[10.466188,49.665455],"type":"Point"}
}