{
  "type": "Feature",
  "properties": {
    "iso:country":"DE",
    "sg:address":"Freiligrathstr. 28",
    "sg:city":"Zeitz",
    "sg:phone":"+49 3441/212084",
    "sg:postcode":"06712",
    "sg:province":"Sachsen-Anhalt",
    "wof:name":"Schwimmhalle",
    "wof:placetype":"venue"
},
  "geometry": {"coordinates":[12.1460781097,51.0544395447],"type":"Point"}
}