{
  "type": "Feature",
  "properties": {
    "iso:country":"DE",
    "sg:address":"D\u00fchlfeld 2",
    "sg:city":"Sachsenhagen",
    "sg:phone":"+49 5725/337",
    "sg:postcode":"31553",
    "sg:province":"Niedersachsen",
    "wof:name":"L. Lampe",
    "wof:placetype":"venue"
},
  "geometry": {"coordinates":[9.2690086365,52.3930091858],"type":"Point"}
}