{
  "type": "Feature",
  "properties": {
    "iso:country":"DE",
    "sg:address":"Nevigeser Str. 272-282",
    "sg:city":"Velbert",
    "sg:phone":"+49 2053/98100",
    "sg:postcode":"42553",
    "sg:province":"Nordrhein-Westfalen",
    "wof:name":"Eichenauer Umformtechnik Verwaltungs Gmbh",
    "wof:placetype":"venue"
},
  "geometry": {"coordinates":[7.064687,51.31525],"type":"Point"}
}