{
  "type": "Feature",
  "properties": {
    "iso:country":"DE",
    "sg:address":"M\u00f6wenstr. 16",
    "sg:city":"Molfsee",
    "sg:phone":"+49 4347/4395",
    "sg:postcode":"24113",
    "sg:province":"Schleswig-Holstein",
    "wof:name":"Bj\u00f6rn Und Myrna Bergfeld Architekten",
    "wof:placetype":"venue"
},
  "geometry": {"coordinates":[10.060137,54.260273],"type":"Point"}
}