{
  "type": "Feature",
  "properties": {
    "iso:country":"DE",
    "sg:address":"Nobelstr. 49-55",
    "sg:city":"Berlin",
    "sg:phone":"+49 30/68970822",
    "sg:postcode":"12057",
    "sg:province":"Berlin",
    "wof:name":"I & P Bautechnik Vertriebs Gmbh",
    "wof:placetype":"venue"
},
  "geometry": {"coordinates":[13.4620885849,52.4605407715],"type":"Point"}
}