{
  "type": "Feature",
  "properties": {
    "iso:country":"DE",
    "sg:address":"Tegeler Str. 23",
    "sg:city":"Bad Salzuflen",
    "sg:phone":"+49 5221/972960",
    "sg:postcode":"32107",
    "sg:province":"Nordrhein-Westfalen",
    "wof:name":"Bake - Pro Gmbh Backwarenvertrieb",
    "wof:placetype":"venue"
},
  "geometry": {"coordinates":[8.68626,52.087955],"type":"Point"}
}