{
  "type": "Feature",
  "properties": {
    "iso:country":"DE",
    "sg:address":"M\u00fchlenstr. 8",
    "sg:city":"G\u00fcstrow",
    "sg:postcode":"18273",
    "sg:province":"Mecklenburg-Vorpommern",
    "wof:name":"Geno-immobilien G\u00fcstrow Gmbh",
    "wof:placetype":"venue"
},
  "geometry": {"coordinates":[12.1779327393,53.7940940857],"type":"Point"}
}