{
  "type": "Feature",
  "properties": {
    "iso:country":"DE",
    "sg:address":"Bahnhofstr. 4",
    "sg:city":"Pegau",
    "sg:phone":"+49 177 2720334",
    "sg:postcode":"04523",
    "sg:province":"Sachsen",
    "wof:name":"Montageservice Steven Horch",
    "wof:placetype":"venue"
},
  "geometry": {"coordinates":[12.2470140457,51.165813446],"type":"Point"}
}