{
  "type": "Feature",
  "properties": {
    "iso:country":"DE",
    "sg:address":"Blankenheimer Str. 15",
    "sg:city":"Ohlenhard",
    "sg:phone":"+49 2694/710",
    "sg:postcode":"53520",
    "sg:province":"Rheinland-Pfalz",
    "wof:name":"Ernst Kaspers",
    "wof:placetype":"venue"
},
  "geometry": {"coordinates":[6.768833,50.442871],"type":"Point"}
}