{
  "type": "Feature",
  "properties": {
    "iso:country":"DE",
    "sg:address":"Beim Weidige 21",
    "sg:city":"Apolda",
    "sg:postcode":"99510",
    "sg:province":"Th\u00fcringen",
    "wof:name":"Gr-verwaltungsgesellschaft Mbh",
    "wof:placetype":"venue"
},
  "geometry": {"coordinates":[11.4719781876,51.0112457275],"type":"Point"}
}