{
  "type": "Feature",
  "properties": {
    "iso:country":"DE",
    "sg:address":"Weiltinger Str. 30",
    "sg:city":"N\u00fcrnberg",
    "sg:phone":"+49 911/682617",
    "sg:postcode":"90449",
    "sg:province":"Bayern",
    "wof:name":"Elfriede Schuster Steuerberaterin",
    "wof:placetype":"venue"
},
  "geometry": {"coordinates":[11.0224256516,49.4225120544],"type":"Point"}
}