{
  "type": "Feature",
  "properties": {
    "iso:country":"DE",
    "sg:address":"Herstallstr. 18",
    "sg:city":"Aschaffenburg",
    "sg:phone":"+49 6021/30890",
    "sg:postcode":"63739",
    "sg:province":"Bayern",
    "wof:name":"Uhren Vogl Gmbh",
    "wof:placetype":"venue"
},
  "geometry": {"coordinates":[9.1471662521,49.9752464294],"type":"Point"}
}