{
  "type": "Feature",
  "properties": {
    "iso:country":"DE",
    "sg:address":"Schindelberg 12",
    "sg:city":"Oberrstaufen-Steibis",
    "sg:phone":"+49 8386",
    "sg:postcode":"87534",
    "sg:province":"Bayern",
    "wof:name":"Willkommen In Schindelberg Bei Steibis Im Allg\u00e4u",
    "wof:placetype":"venue"
},
  "geometry": {"coordinates":[10.008738,47.532379],"type":"Point"}
}