{
  "type": "Feature",
  "properties": {
    "iso:country":"DE",
    "sg:address":"Hackenberger Str. 41",
    "sg:city":"Remscheid",
    "sg:phone":"+49 2191/62635",
    "sg:postcode":"42897",
    "sg:province":"Nordrhein-Westfalen",
    "wof:name":"Blumen Karl Lendermann Inh. Helge Lendermann E. K.",
    "wof:placetype":"venue"
},
  "geometry": {"coordinates":[7.26717,51.195675],"type":"Point"}
}