{
  "type": "Feature",
  "properties": {
    "iso:country":"DE",
    "sg:address":"Langenzenner Str. 9",
    "sg:city":"Seukendorf",
    "sg:phone":"+49 171 3064181",
    "sg:postcode":"90556",
    "sg:province":"Bayern",
    "wof:name":"Werner Tiefel",
    "wof:placetype":"venue"
},
  "geometry": {"coordinates":[10.877028,49.48703],"type":"Point"}
}