{
  "type": "Feature",
  "properties": {
    "iso:country":"DE",
    "sg:address":"Am Knippchen 23",
    "sg:city":"Bonn",
    "sg:phone":"+49 228/482489",
    "sg:postcode":"53229",
    "sg:province":"Nordrhein-Westfalen",
    "wof:name":"Dieter Hitzig",
    "wof:placetype":"venue"
},
  "geometry": {"coordinates":[7.1486740112,50.7385520935],"type":"Point"}
}