{
  "type": "Feature",
  "properties": {
    "iso:country":"DE",
    "sg:address":"Mandlstr. 11",
    "sg:city":"Buchbach",
    "sg:phone":"+49 8086/567",
    "sg:postcode":"84428",
    "sg:province":"Bayern",
    "wof:name":"Max Schechtl Gmbh",
    "wof:placetype":"venue"
},
  "geometry": {"coordinates":[12.2645330429,48.3076515198],"type":"Point"}
}