{
  "type": "Feature",
  "properties": {
    "iso:country":"DE",
    "sg:address":"Poststr. 14",
    "sg:city":"Duisburg",
    "sg:phone":"+49 203/2808943",
    "sg:postcode":"47051",
    "sg:province":"Nordrhein-Westfalen",
    "wof:name":"Britta Ruiters Rechtsanw\u00e4ltin",
    "wof:placetype":"venue"
},
  "geometry": {"coordinates":[6.7625098228,51.4342918396],"type":"Point"}
}