{
  "type": "Feature",
  "properties": {
    "iso:country":"DE",
    "sg:address":"Keltenstr. 19",
    "sg:city":"Gersheim",
    "sg:phone":"+49 6843/8324",
    "sg:postcode":"66453",
    "sg:province":"Saarland",
    "wof:name":"Gasthaus Schwarz",
    "wof:placetype":"venue"
},
  "geometry": {"coordinates":[7.1819162369,49.1366081238],"type":"Point"}
}