{
  "type": "Feature",
  "properties": {
    "iso:country":"DE",
    "sg:address":"Backhausstr. 3",
    "sg:city":"Ehingen",
    "sg:phone":"+49 7386/351",
    "sg:postcode":"89584",
    "sg:province":"Baden-W\u00fcrttemberg",
    "wof:name":"Wilfried Sch\u00e4nzle",
    "wof:placetype":"venue"
},
  "geometry": {"coordinates":[9.540603,48.279633],"type":"Point"}
}