{
  "type": "Feature",
  "properties": {
    "iso:country":"DE",
    "sg:address":"Bucher Hauptstr. 54",
    "sg:city":"N\u00fcrnberg",
    "sg:phone":"+49 911/381333",
    "sg:postcode":"90427",
    "sg:province":"Bayern",
    "wof:name":"Konrad H\u00fcbner",
    "wof:placetype":"venue"
},
  "geometry": {"coordinates":[11.0502033234,49.4930534363],"type":"Point"}
}