{
  "type": "Feature",
  "properties": {
    "iso:country":"DE",
    "sg:address":"Kanonenstr. 16",
    "sg:city":"Schmitten",
    "sg:phone":"+49 6084/2619",
    "sg:postcode":"61389",
    "sg:province":"Hessen",
    "wof:name":"Heinz Hartmann",
    "wof:placetype":"venue"
},
  "geometry": {"coordinates":[8.4461174011,50.2688407898],"type":"Point"}
}