{
  "type": "Feature",
  "properties": {
    "iso:country":"DE",
    "sg:address":"Heerstr. 16",
    "sg:city":"Aldingen",
    "sg:phone":"+49 7424/98140",
    "sg:postcode":"78554",
    "sg:province":"Baden-W\u00fcrttemberg",
    "wof:name":"Ais Gmbh",
    "wof:placetype":"venue"
},
  "geometry": {"coordinates":[8.688844,48.095287],"type":"Point"}
}