{
  "type": "Feature",
  "properties": {
    "iso:country":"DE",
    "sg:address":"R\u00f6merstr. 80",
    "sg:city":"Bad Ems",
    "sg:phone":"+49 2603/944544",
    "sg:postcode":"56130",
    "sg:province":"Rheinland-Pfalz",
    "wof:name":"Dadder Pharma Konzepte Beratungsgesellschaft Mbh",
    "wof:placetype":"venue"
},
  "geometry": {"coordinates":[7.7148981094,50.3342056274],"type":"Point"}
}