{
  "type": "Feature",
  "properties": {
    "iso:country":"DE",
    "sg:address":"Bismarckstr. 18",
    "sg:city":"Marburg",
    "sg:phone":"+49 6421/162780",
    "sg:postcode":"35037",
    "sg:province":"Hessen",
    "wof:name":"Ursula Engel Rechtsanw\u00e4ltin",
    "wof:placetype":"venue"
},
  "geometry": {"coordinates":[8.7634572983,50.8043785095],"type":"Point"}
}