{
  "type": "Feature",
  "properties": {
    "iso:country":"DE",
    "sg:address":"Lauchringer Str. 21",
    "sg:city":"Wut\u00f6schingen",
    "sg:phone":"+49 7746/5259",
    "sg:postcode":"79793",
    "sg:province":"Baden-W\u00fcrttemberg",
    "wof:name":"Siegfried Vollmann",
    "wof:placetype":"venue"
},
  "geometry": {"coordinates":[8.3560218811,47.655456543],"type":"Point"}
}