{
  "type": "Feature",
  "properties": {
    "iso:country":"DE",
    "sg:address":"M\u00fchlenstr. 2",
    "sg:city":"Algermissen",
    "sg:phone":"+49 5126/2379",
    "sg:postcode":"31191",
    "sg:province":"Niedersachsen",
    "wof:name":"Thomas Wucherpfennig",
    "wof:placetype":"venue"
},
  "geometry": {"coordinates":[9.963406,52.251274],"type":"Point"}
}