{
  "type": "Feature",
  "properties": {
    "iso:country":"DE",
    "sg:address":"Nonnenwaldstr. 15",
    "sg:city":"Stuttgart",
    "sg:postcode":"70186",
    "sg:province":"Baden-W\u00fcrttemberg",
    "wof:name":"Fetzer Projekt- Und Baumanagement Gmbh",
    "wof:placetype":"venue"
},
  "geometry": {"coordinates":[9.212311,48.778351],"type":"Point"}
}