{
  "type": "Feature",
  "properties": {
    "iso:country":"DE",
    "sg:address":"Schillingstr. 37 - 39",
    "sg:city":"K\u00f6ln",
    "sg:phone":"+49 221/772020",
    "sg:postcode":"50670",
    "sg:province":"Nordrhein-Westfalen",
    "wof:name":"Rhein-beton Gmbh",
    "wof:placetype":"venue"
},
  "geometry": {"coordinates":[6.9587612152,50.9521865845],"type":"Point"}
}