{
  "type": "Feature",
  "properties": {
    "iso:country":"DE",
    "sg:address":"Dachsgang 27",
    "sg:city":"Langg\u00f6ns",
    "sg:phone":"+49 6085/988700",
    "sg:postcode":"35428",
    "sg:province":"Hessen",
    "wof:name":"Cronidesoft Ag",
    "wof:placetype":"venue"
},
  "geometry": {"coordinates":[8.558049,50.441677],"type":"Point"}
}