{
  "type": "Feature",
  "properties": {
    "iso:country":"DE",
    "sg:address":"Raiffeisenstr. 1",
    "sg:city":"Radevormwald",
    "sg:phone":"+49 2195/4523",
    "sg:postcode":"42477",
    "sg:province":"Nordrhein-Westfalen",
    "wof:name":"Helmut Gutberlett Gmbh",
    "wof:placetype":"venue"
},
  "geometry": {"coordinates":[7.382811,51.203785],"type":"Point"}
}