{
  "type": "Feature",
  "properties": {
    "iso:country":"DE",
    "sg:address":"Annastr. 21",
    "sg:city":"Kevelaer",
    "sg:phone":"+49 2832/6755",
    "sg:postcode":"47623",
    "sg:province":"Nordrhein-Westfalen",
    "wof:name":"Ferrari-vonk",
    "wof:placetype":"venue"
},
  "geometry": {"coordinates":[6.2451457977,51.5820503235],"type":"Point"}
}