{
  "type": "Feature",
  "properties": {
    "iso:country":"DE",
    "sg:address":"Roggenkamp 14",
    "sg:city":"Damme",
    "sg:phone":"+49 5491/96660",
    "sg:postcode":"49401",
    "sg:province":"Niedersachsen",
    "wof:name":"Hermann Trimpe-bruns Steuerberater",
    "wof:placetype":"venue"
},
  "geometry": {"coordinates":[8.1901884079,52.5264472961],"type":"Point"}
}