{
  "type": "Feature",
  "properties": {
    "iso:country":"DE",
    "sg:address":"Im Wiesengrund 10",
    "sg:city":"Marienheide",
    "sg:phone":"+49 4922/646410",
    "sg:postcode":"51709",
    "sg:province":"Nordrhein-Westfalen",
    "wof:name":"Risse Gmbh",
    "wof:placetype":"venue"
},
  "geometry": {"coordinates":[7.52221,51.073551],"type":"Point"}
}