{
  "type": "Feature",
  "properties": {
    "iso:country":"DE",
    "sg:address":"Am M\u00fchlenberg 17",
    "sg:city":"Bahrdorf",
    "sg:phone":"+49 5364/9490",
    "sg:postcode":"38459",
    "sg:province":"Niedersachsen",
    "wof:name":"Wilfried Kuhn Ingenieur",
    "wof:placetype":"venue"
},
  "geometry": {"coordinates":[11.0052042007,52.388885498],"type":"Point"}
}