{
  "type": "Feature",
  "properties": {
    "iso:country":"DE",
    "sg:address":"Gro\u00dfenhainer Str. 102",
    "sg:city":"Dresden",
    "sg:phone":"+49 351/8489847",
    "sg:postcode":"01127",
    "sg:province":"Sachsen",
    "wof:name":"Buschs",
    "wof:placetype":"venue"
},
  "geometry": {"coordinates":[13.7289228439,51.0837974548],"type":"Point"}
}