{
  "type": "Feature",
  "properties": {
    "iso:country":"DE",
    "sg:address":"Oerlinghauser Str.118",
    "sg:city":"Detmold",
    "sg:phone":"+49 7009327678",
    "sg:postcode":"32758",
    "sg:province":"Nordrhein-Westfalen",
    "wof:name":"Webport@: Das Tor Zu Ihrer Internetpr\u00e4senz",
    "wof:placetype":"venue"
},
  "geometry": {"coordinates":[8.785435,51.944607],"type":"Point"}
}