{
  "type": "Feature",
  "properties": {
    "iso:country":"DE",
    "sg:address":"Wied 13",
    "sg:city":"Neustadt/Wied",
    "sg:phone":"+49 2683",
    "sg:postcode":"53577",
    "sg:province":"Rheinland-Pfalz",
    "wof:name":"Immobilien Fischer",
    "wof:placetype":"venue"
},
  "geometry": {"coordinates":[7.3943052292,50.6131744385],"type":"Point"}
}