{
  "type": "Feature",
  "properties": {
    "iso:country":"DE",
    "sg:address":"L\u00fcbbecker Str. 221",
    "sg:city":"Hille",
    "sg:postcode":"32479",
    "sg:province":"Nordrhein-Westfalen",
    "wof:name":"H\u00fcbel Verwaltungs Gmbh",
    "wof:placetype":"venue"
},
  "geometry": {"coordinates":[8.769796,52.297615],"type":"Point"}
}