{
  "type": "Feature",
  "properties": {
    "iso:country":"DE",
    "sg:address":"Feldstr. 1",
    "sg:city":"Angern",
    "sg:phone":"+49 39363/291",
    "sg:postcode":"39326",
    "sg:province":"Sachsen-Anhalt",
    "wof:name":"Klaus Matzdorf",
    "wof:placetype":"venue"
},
  "geometry": {"coordinates":[11.746761322,52.357635498],"type":"Point"}
}