{
  "type": "Feature",
  "properties": {
    "iso:country":"DE",
    "sg:address":"Main-Neckar-Bahn-Str. 19",
    "sg:city":"Mannheim",
    "sg:phone":"+49 621/473531",
    "sg:postcode":"68229",
    "sg:province":"Baden-W\u00fcrttemberg",
    "wof:name":"Stadt Saloniki",
    "wof:placetype":"venue"
},
  "geometry": {"coordinates":[8.5776996613,49.4433860779],"type":"Point"}
}