{
  "type": "Feature",
  "properties": {
    "iso:country":"DE",
    "sg:address":"K-Marx Str. 32",
    "sg:city":"Hartha",
    "sg:phone":"+49 34328/2302",
    "sg:postcode":"04746",
    "sg:province":"Sachsen",
    "wof:name":"Kreissparkasse D\u00f6beln",
    "wof:placetype":"venue"
},
  "geometry": {"coordinates":[12.972009,51.097992],"type":"Point"}
}