{
  "type": "Feature",
  "properties": {
    "iso:country":"DE",
    "sg:address":"Westendstr. 24",
    "sg:city":"Frankfurt",
    "sg:phone":"+49 69/9714970",
    "sg:postcode":"60325",
    "sg:province":"Hessen",
    "wof:name":"Deutsche Structured Finance Gmbh & Co. Virgo Kg",
    "wof:placetype":"venue"
},
  "geometry": {"coordinates":[8.662374,50.112499],"type":"Point"}
}