{
  "type": "Feature",
  "properties": {
    "iso:country":"DE",
    "sg:address":"Kasseler Str. 53",
    "sg:city":"Niedenstein",
    "sg:phone":"+49 5624/6290",
    "sg:postcode":"34305",
    "sg:province":"Hessen",
    "wof:name":"Gasthaus Zur Dicken Eiche",
    "wof:placetype":"venue"
},
  "geometry": {"coordinates":[9.313659668,51.2340888977],"type":"Point"}
}