{
  "type": "Feature",
  "properties": {
    "iso:country":"DE",
    "sg:address":"Lange Str. 38",
    "sg:city":"Bockhorn",
    "sg:phone":"+49 4453/72711",
    "sg:postcode":"26345",
    "sg:province":"Niedersachsen",
    "wof:name":"Quelle-sch\u00f6pflin-agentur",
    "wof:placetype":"venue"
},
  "geometry": {"coordinates":[8.0197868347,53.3936653137],"type":"Point"}
}