{
  "type": "Feature",
  "properties": {
    "iso:country":"DE",
    "sg:address":"S\u00fcdstr. 6",
    "sg:city":"Ludwigsh\u00f6he",
    "sg:phone":"+49 6249/1565",
    "sg:postcode":"55278",
    "sg:province":"Rheinland-Pfalz",
    "wof:name":"Siegfried Best",
    "wof:placetype":"venue"
},
  "geometry": {"coordinates":[8.3488807678,49.8156318665],"type":"Point"}
}