{
  "type": "Feature",
  "properties": {
    "iso:country":"DE",
    "sg:address":"Meyenburger Str. 1",
    "sg:city":"Putlitz",
    "sg:postcode":"16949",
    "sg:province":"Brandenburg",
    "wof:name":"Horst Mellmann",
    "wof:placetype":"venue"
},
  "geometry": {"coordinates":[12.043417,53.24987],"type":"Point"}
}