{
  "type": "Feature",
  "properties": {
    "iso:country":"DE",
    "sg:address":"Palmstr. 23",
    "sg:city":"L\u00f6rrach",
    "sg:phone":"+49 7621/47163",
    "sg:postcode":"79539",
    "sg:province":"Baden-W\u00fcrttemberg",
    "wof:name":"P. Kessler Stoffgrosshandel",
    "wof:placetype":"venue"
},
  "geometry": {"coordinates":[7.663343,47.613907],"type":"Point"}
}