{
  "type": "Feature",
  "properties": {
    "iso:country":"DE",
    "sg:address":"Steinbacher Str. 9",
    "sg:city":"Dannenfels",
    "sg:phone":"+49 6357/332",
    "sg:postcode":"67814",
    "sg:province":"Rheinland-Pfalz",
    "wof:name":"E. Raab",
    "wof:placetype":"venue"
},
  "geometry": {"coordinates":[7.9463157654,49.6246566772],"type":"Point"}
}