{
  "type": "Feature",
  "properties": {
    "iso:country":"DE",
    "sg:address":"Hauptstr. 113",
    "sg:city":"Langenhagen",
    "sg:postcode":"30855",
    "sg:province":"Niedersachsen",
    "wof:name":"Btb Gewerbe- Und Klimak\u00e4lte Gmbh",
    "wof:placetype":"venue"
},
  "geometry": {"coordinates":[9.7067928314,52.4337425232],"type":"Point"}
}