{
  "type": "Feature",
  "properties": {
    "iso:country":"DE",
    "sg:address":"Hellegraben 33",
    "sg:city":"Warendorf",
    "sg:phone":"+49 2581/1604",
    "sg:postcode":"48231",
    "sg:province":"Nordrhein-Westfalen",
    "wof:name":"Georg Witte",
    "wof:placetype":"venue"
},
  "geometry": {"coordinates":[7.97126,51.955502],"type":"Point"}
}