{
  "type": "Feature",
  "properties": {
    "iso:country":"DE",
    "sg:address":"Rahlau 60",
    "sg:city":"Hamburg",
    "sg:phone":"+49 40/666313",
    "sg:postcode":"22045",
    "sg:province":"Hamburg",
    "wof:name":"Kurt Siggelow & Sohn Gmbh",
    "wof:placetype":"venue"
},
  "geometry": {"coordinates":[10.1181240082,53.5811195374],"type":"Point"}
}