{
  "type": "Feature",
  "properties": {
    "iso:country":"DE",
    "sg:address":"Scheidter Hof",
    "sg:city":"Kobern-Gondorf",
    "sg:phone":"+49 2607/6607",
    "sg:postcode":"56330",
    "sg:province":"Rheinland-Pfalz",
    "wof:name":"Ewald H\u00e4hn",
    "wof:placetype":"venue"
},
  "geometry": {"coordinates":[7.435589,50.30526],"type":"Point"}
}