{
  "type": "Feature",
  "properties": {
    "iso:country":"DE",
    "sg:address":"Grevener Str. 27",
    "sg:city":"Telgte",
    "sg:phone":"+49 2504/88719",
    "sg:postcode":"48291",
    "sg:province":"Nordrhein-Westfalen",
    "wof:name":"F. Muhmann",
    "wof:placetype":"venue"
},
  "geometry": {"coordinates":[7.7999110222,52.0489807129],"type":"Point"}
}