{
  "type": "Feature",
  "properties": {
    "iso:country":"DE",
    "sg:address":"Stargarder Str. 39",
    "sg:city":"Berlin",
    "sg:phone":"+49 30/4455190",
    "sg:postcode":"10437",
    "sg:province":"Berlin",
    "wof:name":"Willi Hollatz",
    "wof:placetype":"venue"
},
  "geometry": {"coordinates":[13.425473,52.543205],"type":"Point"}
}