{
  "type": "Feature",
  "properties": {
    "iso:country":"DE",
    "sg:address":"B\u00f6nnier Str. 28",
    "sg:city":"Bockenem",
    "sg:phone":"+49 5067/1666",
    "sg:postcode":"31167",
    "sg:province":"Niedersachsen",
    "wof:name":"Ambergau-apotheke",
    "wof:placetype":"venue"
},
  "geometry": {"coordinates":[10.126695,52.009575],"type":"Point"}
}