{
  "type": "Feature",
  "properties": {
    "iso:country":"DE",
    "sg:address":"Bahnhofstr. 19",
    "sg:city":"Emsb\u00fcren",
    "sg:phone":"+49 5903/93610",
    "sg:postcode":"48488",
    "sg:province":"Niedersachsen",
    "wof:name":"Hotel Garni Plagge",
    "wof:placetype":"venue"
},
  "geometry": {"coordinates":[7.2945890427,52.3939285278],"type":"Point"}
}