{
  "type": "Feature",
  "properties": {
    "iso:country":"DE",
    "sg:address":"Im Kloster 11",
    "sg:city":"Bad Herrenalb",
    "sg:phone":"+49 7083/2195",
    "sg:postcode":"76332",
    "sg:province":"Baden-W\u00fcrttemberg",
    "wof:name":"Krankenpflegeverein Bad Herrenalb Dobel E. V.",
    "wof:placetype":"venue"
},
  "geometry": {"coordinates":[8.43619,48.79652],"type":"Point"}
}