{
  "type": "Feature",
  "properties": {
    "iso:country":"DE",
    "sg:address":"Dohrweg 30",
    "sg:city":"M\u00f6nchengladbach",
    "sg:postcode":"41066",
    "sg:province":"Nordrhein-Westfalen",
    "wof:name":"Autopark 2002 Verwaltungs Gmbh",
    "wof:placetype":"venue"
},
  "geometry": {"coordinates":[6.4752001762,51.213809967],"type":"Point"}
}