{
  "type": "Feature",
  "properties": {
    "iso:country":"DE",
    "sg:address":"\u00d6lweg 21",
    "sg:city":"Osnabr\u00fcck",
    "sg:phone":"+49 541/77566",
    "sg:postcode":"49084",
    "sg:province":"Niedersachsen",
    "wof:name":"Ev. Pfarramt Jakobusgemeinde",
    "wof:placetype":"venue"
},
  "geometry": {"coordinates":[8.1007175446,52.2784805298],"type":"Point"}
}