{
  "type": "Feature",
  "properties": {
    "iso:country":"DE",
    "sg:address":"Stadtwaldpark 10",
    "sg:city":"Melsungen",
    "sg:phone":"+49 4956/6173440",
    "sg:postcode":"34212",
    "sg:province":"Hessen",
    "wof:name":"Bibliomed - Med. Verlags Gmbh",
    "wof:placetype":"venue"
},
  "geometry": {"coordinates":[9.5700531006,51.1185951233],"type":"Point"}
}