{
  "type": "Feature",
  "properties": {
    "iso:country":"DE",
    "sg:address":"Hindenburgstr. 22",
    "sg:city":"F\u00fcrstenfeldbruck",
    "sg:phone":"+49 8141/42362",
    "sg:postcode":"82256",
    "sg:province":"Bayern",
    "wof:name":"Engelbert Reiter Ingenieur",
    "wof:placetype":"venue"
},
  "geometry": {"coordinates":[11.256986618,48.183883667],"type":"Point"}
}