{
  "type": "Feature",
  "properties": {
    "iso:country":"DE",
    "sg:address":"Lautensackstr. 2 a",
    "sg:city":"M\u00fcnchen",
    "sg:phone":"+49 89/576522",
    "sg:postcode":"80687",
    "sg:province":"Bayern",
    "wof:name":"K. Hitzelsperger",
    "wof:placetype":"venue"
},
  "geometry": {"coordinates":[11.517988,48.139809],"type":"Point"}
}