{
  "type": "Feature",
  "properties": {
    "iso:country":"DE",
    "sg:address":"Beethovenstr. 12",
    "sg:city":"Bergisch Gladbach",
    "sg:phone":"+49 2204/63676",
    "sg:postcode":"51427",
    "sg:province":"Nordrhein-Westfalen",
    "wof:name":"Doris Gomoll Steuerberaterin",
    "wof:placetype":"venue"
},
  "geometry": {"coordinates":[7.1368618011,50.9530296326],"type":"Point"}
}