{
  "type": "Feature",
  "properties": {
    "iso:country":"DE",
    "sg:address":"Frankenplatz 3",
    "sg:city":"Wuppertal",
    "sg:phone":"+49 202/453978",
    "sg:postcode":"42107",
    "sg:province":"Nordrhein-Westfalen",
    "wof:name":"Wilhelm Benninghoven",
    "wof:placetype":"venue"
},
  "geometry": {"coordinates":[7.1604471207,51.2656669617],"type":"Point"}
}