{
  "type": "Feature",
  "properties": {
    "iso:country":"DE",
    "sg:address":"Ludwigstra\u00dfe 116",
    "sg:city":"Waldsee / Pfalz",
    "sg:phone":"+49 6236/40",
    "sg:postcode":"67165",
    "sg:province":"Rheinland-Pfalz",
    "wof:name":"Dornick Dienstleistungen",
    "wof:placetype":"venue"
},
  "geometry": {"coordinates":[8.438206,49.387955],"type":"Point"}
}