{
  "type": "Feature",
  "properties": {
    "iso:country":"DE",
    "sg:address":"Eisertstr. 21",
    "sg:city":"Goldbach",
    "sg:phone":"+49 6021/53652",
    "sg:postcode":"63773",
    "sg:province":"Bayern",
    "wof:name":"Juliane B\u00fcttner Krankengymnastin",
    "wof:placetype":"venue"
},
  "geometry": {"coordinates":[9.173672,50.000114],"type":"Point"}
}