{
  "type": "Feature",
  "properties": {
    "iso:country":"DE",
    "sg:address":"Vaihinger Str. 1",
    "sg:city":"Eberdingen",
    "sg:phone":"+49 7042/5415",
    "sg:postcode":"71735",
    "sg:province":"Baden-W\u00fcrttemberg",
    "wof:name":"Lamm",
    "wof:placetype":"venue"
},
  "geometry": {"coordinates":[8.9395427704,48.8951416016],"type":"Point"}
}