{
  "type": "Feature",
  "properties": {
    "iso:country":"DE",
    "sg:address":"Gute \u00c4nger 11",
    "sg:city":"Freising",
    "sg:postcode":"85356",
    "sg:province":"Bayern",
    "wof:name":"Schmidt Spiel Und Freizeit Gmbh",
    "wof:placetype":"venue"
},
  "geometry": {"coordinates":[11.7580528259,48.3889083862],"type":"Point"}
}