{
  "type": "Feature",
  "properties": {
    "iso:country":"DE",
    "sg:address":"Storchenweg 14",
    "sg:city":"Seevetal",
    "sg:phone":"+49 40/7691610",
    "sg:postcode":"21217",
    "sg:province":"Niedersachsen",
    "wof:name":"Dachdecker-einkauf L\u00fcbeck Eg",
    "wof:placetype":"venue"
},
  "geometry": {"coordinates":[10.038124,53.428017],"type":"Point"}
}