{
  "type": "Feature",
  "properties": {
    "iso:country":"DE",
    "sg:address":"Uhleneike 7",
    "sg:city":"Hann. M\u00fcnden",
    "sg:phone":"+49 5541/906644",
    "sg:postcode":"34346",
    "sg:province":"Niedersachsen",
    "wof:name":"Haus Werrablick Heidi Granica-eckelmann",
    "wof:placetype":"venue"
},
  "geometry": {"coordinates":[9.7150964737,51.4002227783],"type":"Point"}
}