{
  "type": "Feature",
  "properties": {
    "iso:country":"DE",
    "sg:address":"Flurstr. 40",
    "sg:city":"Gauting",
    "sg:postcode":"82131",
    "sg:province":"Bayern",
    "wof:name":"Bp Oil Deutschland Gmbh",
    "wof:placetype":"venue"
},
  "geometry": {"coordinates":[11.3923959732,48.0646095276],"type":"Point"}
}