{
  "type": "Feature",
  "properties": {
    "iso:country":"DE",
    "sg:address":"Kranichstr. 7",
    "sg:city":"Ingolstadt",
    "sg:phone":"+49 841/72050",
    "sg:postcode":"85051",
    "sg:province":"Bayern",
    "wof:name":"Erich Maier",
    "wof:placetype":"venue"
},
  "geometry": {"coordinates":[11.4356956482,48.7299880981],"type":"Point"}
}