{
  "type": "Feature",
  "properties": {
    "iso:country":"DE",
    "sg:address":"Georg-Haar-Str. 7",
    "sg:city":"Weimar",
    "sg:phone":"+49 3643/202496",
    "sg:postcode":"99427",
    "sg:province":"Th\u00fcringen",
    "wof:name":"Stahlbau M\u00fcller Gmbh",
    "wof:placetype":"venue"
},
  "geometry": {"coordinates":[11.30322,50.982265],"type":"Point"}
}