{
  "type": "Feature",
  "properties": {
    "iso:country":"DE",
    "sg:address":"Richard-Byrd-Str.",
    "sg:city":"K\u00f6ln",
    "sg:phone":"+49 221/594481",
    "sg:postcode":"50829",
    "sg:province":"Nordrhein-Westfalen",
    "wof:name":"Mmc Entertainment Gmbh",
    "wof:placetype":"venue"
},
  "geometry": {"coordinates":[6.885395,50.986584],"type":"Point"}
}