{
  "type": "Feature",
  "properties": {
    "iso:country":"DE",
    "sg:address":"Altenbergstr. 16",
    "sg:city":"Auenwald",
    "sg:phone":"+49 7191/52224",
    "sg:postcode":"71549",
    "sg:province":"Baden-W\u00fcrttemberg",
    "wof:name":"Burkert Beteiligungs-gmbh",
    "wof:placetype":"venue"
},
  "geometry": {"coordinates":[9.503589,48.955902],"type":"Point"}
}