{
  "type": "Feature",
  "properties": {
    "iso:country":"DE",
    "sg:address":"Warmensteinacher Str. 53",
    "sg:city":"Berlin",
    "sg:phone":"+49 30/7425091",
    "sg:postcode":"12349",
    "sg:province":"Berlin",
    "wof:name":"Siegfried Gregor Dachdeckerei Gmbh",
    "wof:placetype":"venue"
},
  "geometry": {"coordinates":[13.425252,52.415432],"type":"Point"}
}