{
  "type": "Feature",
  "properties": {
    "iso:country":"DE",
    "sg:address":"Hangerg. 80",
    "sg:city":"Me\u00dfstetten",
    "sg:phone":"+49 4974/3196220",
    "sg:postcode":"72469",
    "sg:province":"Baden-W\u00fcrttemberg",
    "wof:name":"Axel G\u00d6tting Gmbh",
    "wof:placetype":"venue"
},
  "geometry": {"coordinates":[8.97025,48.178619],"type":"Point"}
}