{
  "type": "Feature",
  "properties": {
    "iso:country":"DE",
    "sg:address":"Heusingerstr. 76",
    "sg:city":"Frankfurt",
    "sg:phone":"+49 69/38999329",
    "sg:postcode":"65934",
    "sg:province":"Hessen",
    "wof:name":"La Belle",
    "wof:placetype":"venue"
},
  "geometry": {"coordinates":[8.57819,50.106525],"type":"Point"}
}