{
  "type": "Feature",
  "properties": {
    "iso:country":"DE",
    "sg:address":"Straetener Weg 15",
    "sg:city":"Heinsberg",
    "sg:phone":"+49 2452/4455",
    "sg:postcode":"52525",
    "sg:province":"Nordrhein-Westfalen",
    "wof:name":"Brigitte G\u00f6rres",
    "wof:placetype":"venue"
},
  "geometry": {"coordinates":[6.07837677,51.0131492615],"type":"Point"}
}