{
  "type": "Feature",
  "properties": {
    "iso:country":"DE",
    "sg:address":"Amalienburgstr. 13",
    "sg:city":"M\u00fcnchen",
    "sg:phone":"+49 89/8110586",
    "sg:postcode":"81247",
    "sg:province":"Bayern",
    "wof:name":"Maskot",
    "wof:placetype":"venue"
},
  "geometry": {"coordinates":[11.489603,48.16431],"type":"Point"}
}