{
  "type": "Feature",
  "properties": {
    "iso:country":"DE",
    "sg:address":"Kientenstr. 50",
    "sg:city":"Albstadt",
    "sg:phone":"+49 7431/13450",
    "sg:postcode":"72458",
    "sg:province":"Baden-W\u00fcrttemberg",
    "wof:name":"Haas & Alber Elektrohaus Gmbh",
    "wof:placetype":"venue"
},
  "geometry": {"coordinates":[8.9941625595,48.2112197876],"type":"Point"}
}