{
  "type": "Feature",
  "properties": {
    "iso:country":"DE",
    "sg:address":"Kaiser-Wilhelm-Str. 296",
    "sg:city":"Duisburg",
    "sg:phone":"+49 203/405281",
    "sg:postcode":"47169",
    "sg:province":"Nordrhein-Westfalen",
    "wof:name":"Olaf Ellermann Masseur",
    "wof:placetype":"venue"
},
  "geometry": {"coordinates":[6.756249,51.501522],"type":"Point"}
}