{
  "type": "Feature",
  "properties": {
    "iso:country":"DE",
    "sg:address":"Schlehenstr. 7",
    "sg:city":"Langenzenn",
    "sg:phone":"+49 9101/7576",
    "sg:postcode":"90579",
    "sg:province":"Bayern",
    "wof:name":"Ahg Agrarhandelsgesell- Schaft Mbh + Co Warenver-",
    "wof:placetype":"venue"
},
  "geometry": {"coordinates":[10.789573,49.497345],"type":"Point"}
}