{
  "type": "Feature",
  "properties": {
    "iso:country":"DE",
    "sg:address":"Industriestr. 2",
    "sg:city":"K\u00f6ln",
    "sg:phone":"+49 221/7122094",
    "sg:postcode":"50735",
    "sg:province":"Nordrhein-Westfalen",
    "wof:name":"Schaumprodukte J. Reif E. K. Inh. Sieglinde Kr\u00e4mer",
    "wof:placetype":"venue"
},
  "geometry": {"coordinates":[6.9477720261,50.9967460632],"type":"Point"}
}