{
  "type": "Feature",
  "properties": {
    "iso:country":"DE",
    "sg:address":"Bergtorstr. 21",
    "sg:city":"Isny",
    "sg:phone":"+49 7562/91066",
    "sg:postcode":"88316",
    "sg:province":"Baden-W\u00fcrttemberg",
    "wof:name":"Elektro-aigner & Schwarz Gmbh",
    "wof:placetype":"venue"
},
  "geometry": {"coordinates":[10.0411167145,47.6916503906],"type":"Point"}
}