{
  "type": "Feature",
  "properties": {
    "iso:country":"DE",
    "sg:address":"Poststr. 31",
    "sg:city":"Mainz",
    "sg:phone":"+49 6131/479413",
    "sg:postcode":"55126",
    "sg:province":"Rheinland-Pfalz",
    "wof:name":"Herbert Weil",
    "wof:placetype":"venue"
},
  "geometry": {"coordinates":[8.1747350693,49.9852104187],"type":"Point"}
}