{
  "type": "Feature",
  "properties": {
    "iso:country":"DE",
    "sg:address":"Katzenhagen 13",
    "sg:city":"Gifhorn",
    "sg:phone":"+49 5371/52913",
    "sg:postcode":"38518",
    "sg:province":"Niedersachsen",
    "wof:name":"Otto Genz",
    "wof:placetype":"venue"
},
  "geometry": {"coordinates":[10.477171,52.492813],"type":"Point"}
}