{
  "type": "Feature",
  "properties": {
    "iso:country":"DE",
    "sg:address":"Stanigplatz 11",
    "sg:city":"M\u00fcnchen",
    "sg:phone":"+49 89/3132659",
    "sg:postcode":"80933",
    "sg:province":"Bayern",
    "wof:name":"Ev. Pfarramt Evangeliumskirche",
    "wof:placetype":"venue"
},
  "geometry": {"coordinates":[11.5535869598,48.2167892456],"type":"Point"}
}