{
  "type": "Feature",
  "properties": {
    "iso:country":"DE",
    "sg:address":"Rieheweg 3",
    "sg:city":"Seelze",
    "sg:phone":"+49 5031/972328",
    "sg:postcode":"30926",
    "sg:province":"Niedersachsen",
    "wof:name":"Helisol",
    "wof:placetype":"venue"
},
  "geometry": {"coordinates":[9.5135278702,52.4069747925],"type":"Point"}
}