{
  "type": "Feature",
  "properties": {
    "iso:country":"DE",
    "sg:address":"Marienburger Str. 4",
    "sg:city":"Gelsenkirchen",
    "sg:phone":"+49 209/9592014",
    "sg:postcode":"45897",
    "sg:province":"Nordrhein-Westfalen",
    "wof:name":"Image House - Ges. F\u00fcr Elektronische",
    "wof:placetype":"venue"
},
  "geometry": {"coordinates":[7.0408658981,51.5736846924],"type":"Point"}
}