{
  "type": "Feature",
  "properties": {
    "iso:country":"DE",
    "sg:address":"Boelckestr. 165 B",
    "sg:city":"Mainz-Kastel",
    "sg:phone":"+49 4961/3418500",
    "sg:postcode":"55252",
    "sg:province":"Hessen",
    "wof:name":"Expo Partner Gmbh Ausstellungssysteme",
    "wof:placetype":"venue"
},
  "geometry": {"coordinates":[8.293273,50.02969],"type":"Point"}
}