{
  "type": "Feature",
  "properties": {
    "iso:country":"DE",
    "sg:address":"Hauptstr. 4",
    "sg:city":"Hohentengen",
    "sg:phone":"+49 7742/3178",
    "sg:postcode":"79801",
    "sg:province":"Baden-W\u00fcrttemberg",
    "wof:name":"Rheinblick",
    "wof:placetype":"venue"
},
  "geometry": {"coordinates":[9.3789072037,48.0289802551],"type":"Point"}
}