{
  "type": "Feature",
  "properties": {
    "iso:country":"DE",
    "sg:address":"Weusthoffstr. 46",
    "sg:city":"Hamburg",
    "sg:phone":"+49 40/7929855",
    "sg:postcode":"21075",
    "sg:province":"Hamburg",
    "wof:name":"M. B\u00f6tjer Immobilienmakler",
    "wof:placetype":"venue"
},
  "geometry": {"coordinates":[9.9568653107,53.4580497742],"type":"Point"}
}