{
  "type": "Feature",
  "properties": {
    "iso:country":"DE",
    "sg:address":"Besterfeld 7",
    "sg:city":"Telgte",
    "sg:phone":"+49 2504/4428",
    "sg:postcode":"48291",
    "sg:province":"Nordrhein-Westfalen",
    "wof:name":"Anna Vennefrohne",
    "wof:placetype":"venue"
},
  "geometry": {"coordinates":[7.8343749046,51.9548492432],"type":"Point"}
}