{
  "type": "Feature",
  "properties": {
    "iso:country":"DE",
    "sg:address":"Wilhelm-Tenhagen-Str. 12",
    "sg:city":"Bottrop",
    "sg:phone":"+49 2041/475060",
    "sg:postcode":"46240",
    "sg:province":"Nordrhein-Westfalen",
    "wof:name":"Heib Non Food Service Manfred Heib & S\u00f6hne Ohg",
    "wof:placetype":"venue"
},
  "geometry": {"coordinates":[6.977671,51.532955],"type":"Point"}
}