{
  "type": "Feature",
  "properties": {
    "iso:country":"DE",
    "sg:address":"Goldgasse 10",
    "sg:city":"Ravensburg",
    "sg:phone":"+49 751/33332",
    "sg:postcode":"88212",
    "sg:province":"Baden-W\u00fcrttemberg",
    "wof:name":"Hannelore Weissmann",
    "wof:placetype":"venue"
},
  "geometry": {"coordinates":[9.6107912064,47.7816314697],"type":"Point"}
}