{
  "type": "Feature",
  "properties": {
    "iso:country":"DE",
    "sg:address":"Unterstr. 73",
    "sg:city":"Grevenbroich",
    "sg:phone":"+49 2181/74727",
    "sg:postcode":"41516",
    "sg:province":"Nordrhein-Westfalen",
    "wof:name":"Veronika Coenen",
    "wof:placetype":"venue"
},
  "geometry": {"coordinates":[6.621242,51.107906],"type":"Point"}
}