{
  "type": "Feature",
  "properties": {
    "iso:country":"DE",
    "sg:address":"Im Dorf 6 a",
    "sg:city":"Handeloh",
    "sg:postcode":"21256",
    "sg:province":"Niedersachsen",
    "wof:name":"Heide- Und Hanse Luftfahrt Gmbh",
    "wof:placetype":"venue"
},
  "geometry": {"coordinates":[9.8628425598,53.261505127],"type":"Point"}
}