{
  "type": "Feature",
  "properties": {
    "iso:country":"DE",
    "sg:address":"Kolpingstr. 6",
    "sg:city":"Wolfenb\u00fcttel",
    "sg:phone":"+49 5331/32132",
    "sg:postcode":"38302",
    "sg:province":"Niedersachsen",
    "wof:name":"Heinz Riepold",
    "wof:placetype":"venue"
},
  "geometry": {"coordinates":[10.5385866165,52.1691970825],"type":"Point"}
}