{
  "type": "Feature",
  "properties": {
    "iso:country":"DE",
    "sg:address":"Dilborner Str. 99",
    "sg:city":"Niederkr\u00fcchten",
    "sg:phone":"+49 2163/990480",
    "sg:postcode":"41372",
    "sg:province":"Nordrhein-Westfalen",
    "wof:name":"Tecnon Gmbh",
    "wof:placetype":"venue"
},
  "geometry": {"coordinates":[6.161693,51.230106],"type":"Point"}
}