{
  "type": "Feature",
  "properties": {
    "iso:country":"DE",
    "sg:address":"Tietmecker Weg 8",
    "sg:city":"L\u00fcdenscheid",
    "sg:postcode":"58513",
    "sg:province":"Nordrhein-Westfalen",
    "wof:name":"Sorange Gmbh",
    "wof:placetype":"venue"
},
  "geometry": {"coordinates":[7.599369,51.246235],"type":"Point"}
}