{
  "type": "Feature",
  "properties": {
    "iso:country":"DE",
    "sg:address":"Unterlindau 31",
    "sg:city":"Frankfurt",
    "sg:phone":"+49 69/726196",
    "sg:postcode":"60323",
    "sg:province":"Hessen",
    "wof:name":"Hanns Schalast Rechtsanwalt",
    "wof:placetype":"venue"
},
  "geometry": {"coordinates":[8.6679849625,50.1187057495],"type":"Point"}
}