{
  "type": "Feature",
  "properties": {
    "iso:country":"DE",
    "sg:address":"An der Neuen Niers 14 a",
    "sg:city":"M\u00f6nchengladbach",
    "sg:phone":"+49 2161/663664",
    "sg:postcode":"41066",
    "sg:province":"Nordrhein-Westfalen",
    "wof:name":"Hermann J. Huppertz Ingenieur",
    "wof:placetype":"venue"
},
  "geometry": {"coordinates":[6.4834651947,51.2335205078],"type":"Point"}
}