{
  "type": "Feature",
  "properties": {
    "iso:country":"DE",
    "sg:address":"Ingolst\u00e4dter Str. 23",
    "sg:city":"Brunnen",
    "sg:phone":"+49 8454/3260",
    "sg:postcode":"86564",
    "sg:province":"Bayern",
    "wof:name":"Willi Schmidmair",
    "wof:placetype":"venue"
},
  "geometry": {"coordinates":[11.310621,48.630051],"type":"Point"}
}