{
  "type": "Feature",
  "properties": {
    "iso:country":"DE",
    "sg:address":"Poststr. 1",
    "sg:city":"Bad Schandau",
    "sg:phone":"+49 35022/42815",
    "sg:postcode":"01814",
    "sg:province":"Sachsen",
    "wof:name":"Ilona Kaulfu\u00df",
    "wof:placetype":"venue"
},
  "geometry": {"coordinates":[14.1543292999,50.9181976318],"type":"Point"}
}