{
  "type": "Feature",
  "properties": {
    "iso:country":"DE",
    "sg:address":"Dorfstr. 23",
    "sg:city":"R\u00fcthen",
    "sg:phone":"+49 2954/305",
    "sg:postcode":"59602",
    "sg:province":"Nordrhein-Westfalen",
    "wof:name":"Gastst\u00e4tte A. Klegraf",
    "wof:placetype":"venue"
},
  "geometry": {"coordinates":[8.4057788849,51.570350647],"type":"Point"}
}