{
  "type": "Feature",
  "properties": {
    "iso:country":"DE",
    "sg:address":"Dr.-Max-Picard-Platz 5",
    "sg:city":"Schopfheim",
    "sg:phone":"+49 7622/6980",
    "sg:postcode":"79650",
    "sg:province":"Baden-W\u00fcrttemberg",
    "wof:name":"Senioren-pflegestift Im Bifig",
    "wof:placetype":"venue"
},
  "geometry": {"coordinates":[7.818439,47.649467],"type":"Point"}
}