{
  "type": "Feature",
  "properties": {
    "iso:country":"DE",
    "sg:address":"Rauschbergstr. 1",
    "sg:city":"Ruhpolding",
    "sg:phone":"+49 8663/1705",
    "sg:postcode":"83324",
    "sg:province":"Bayern",
    "wof:name":"Fischerwirt",
    "wof:placetype":"venue"
},
  "geometry": {"coordinates":[12.6632299423,47.752822876],"type":"Point"}
}