{
  "type": "Feature",
  "properties": {
    "iso:country":"DE",
    "sg:address":"Lugaufstr. 21",
    "sg:city":"Freiberg",
    "sg:phone":"+49 7141/73684",
    "sg:postcode":"71691",
    "sg:province":"Baden-W\u00fcrttemberg",
    "wof:name":"Spar-markt",
    "wof:placetype":"venue"
},
  "geometry": {"coordinates":[9.1825323105,48.9353866577],"type":"Point"}
}