{
  "type": "Feature",
  "properties": {
    "iso:country":"DE",
    "sg:address":"Holbeinstr. 5",
    "sg:city":"Bonn",
    "sg:phone":"+49 228/371930",
    "sg:postcode":"53175",
    "sg:province":"Nordrhein-Westfalen",
    "wof:name":"Dieter Von K\u00f6nig",
    "wof:placetype":"venue"
},
  "geometry": {"coordinates":[7.1386198997,50.7018432617],"type":"Point"}
}