{
  "type": "Feature",
  "properties": {
    "iso:country":"DE",
    "sg:address":"Im Triesch 1",
    "sg:city":"Ederm\u00fcnde",
    "sg:phone":"+49 5665",
    "sg:postcode":"34295",
    "sg:province":"Hessen",
    "wof:name":"Urlaub Einfach Online Buchen",
    "wof:placetype":"venue"
},
  "geometry": {"coordinates":[9.42411,51.215801],"type":"Point"}
}