{
  "type": "Feature",
  "properties": {
    "iso:country":"DE",
    "sg:address":"Lehrerstr. 46",
    "sg:city":"Duisburg",
    "sg:phone":"+49 203/586390",
    "sg:postcode":"47167",
    "sg:province":"Nordrhein-Westfalen",
    "wof:name":"Massage Lehrerstr.",
    "wof:placetype":"venue"
},
  "geometry": {"coordinates":[6.805269,51.496578],"type":"Point"}
}