{
  "type": "Feature",
  "properties": {
    "iso:country":"DE",
    "sg:address":"Neue Spreestr 7",
    "sg:city":"F\u00fcrstenwalde",
    "sg:phone":"+49 3361/37430",
    "sg:postcode":"15517",
    "sg:province":"Brandenburg",
    "wof:name":"Microplast Gmbh",
    "wof:placetype":"venue"
},
  "geometry": {"coordinates":[14.0767621994,52.3504943848],"type":"Point"}
}