{
  "type": "Feature",
  "properties": {
    "iso:country":"DE",
    "sg:address":"Raiffeisenstr. 11",
    "sg:city":"Winnenden",
    "sg:phone":"+49 7151/54007",
    "sg:postcode":"71364",
    "sg:province":"Baden-W\u00fcrttemberg",
    "wof:name":"Arcom Gmbh",
    "wof:placetype":"venue"
},
  "geometry": {"coordinates":[9.4196186066,48.8904380798],"type":"Point"}
}