{
  "type": "Feature",
  "properties": {
    "iso:country":"DE",
    "sg:address":"Schweinfurthstr. 29",
    "sg:city":"Berlin",
    "sg:phone":"+49 30/8324635",
    "sg:postcode":"14195",
    "sg:province":"Berlin",
    "wof:name":"Dr. Ernst-michael Ehrenk\u00f6nig Rechtsanwalt Und Notar",
    "wof:placetype":"venue"
},
  "geometry": {"coordinates":[13.294968605,52.4675445557],"type":"Point"}
}