{
  "type": "Feature",
  "properties": {
    "iso:country":"DE",
    "sg:address":"Kardinal-Wendel-Str. 3",
    "sg:city":"Maikammer",
    "sg:phone":"+49 6321/5219",
    "sg:postcode":"67487",
    "sg:province":"Rheinland-Pfalz",
    "wof:name":"Kurt Nitzsche Masseur",
    "wof:placetype":"venue"
},
  "geometry": {"coordinates":[8.127346,49.309647],"type":"Point"}
}