{
  "type": "Feature",
  "properties": {
    "iso:country":"DE",
    "sg:address":"R\u00fcgnerstr. 27",
    "sg:city":"Pfungstadt",
    "sg:phone":"+49 6157/2708",
    "sg:postcode":"64319",
    "sg:province":"Hessen",
    "wof:name":"H. Rothmann",
    "wof:placetype":"venue"
},
  "geometry": {"coordinates":[8.5991640091,49.8049812317],"type":"Point"}
}