{
  "type": "Feature",
  "properties": {
    "iso:country":"DE",
    "sg:address":"Kiarwai 1",
    "sg:city":"Sylt-Ost",
    "sg:phone":"+49 4651/3488",
    "sg:postcode":"25980",
    "sg:province":"Schleswig-Holstein",
    "wof:name":"Mattern",
    "wof:placetype":"venue"
},
  "geometry": {"coordinates":[8.3280849457,54.9022254944],"type":"Point"}
}