{
  "type": "Feature",
  "properties": {
    "iso:country":"DE",
    "sg:address":"Hindenburgstr. 17",
    "sg:city":"M\u00fchlacker",
    "sg:phone":"+49 7041/6150",
    "sg:postcode":"75417",
    "sg:province":"Baden-W\u00fcrttemberg",
    "wof:name":"Rudolf Eberhardt",
    "wof:placetype":"venue"
},
  "geometry": {"coordinates":[8.84098,48.947659],"type":"Point"}
}