{
  "type": "Feature",
  "properties": {
    "iso:country":"DE",
    "sg:address":"Posthalterweg 2",
    "sg:city":"Oldenburg",
    "sg:phone":"+49 441/97110",
    "sg:postcode":"26129",
    "sg:province":"Niedersachsen",
    "wof:name":"B\u00e4ko Weser-ems B\u00e4cker- Und Konditorengenossenschaft Eg",
    "wof:placetype":"venue"
},
  "geometry": {"coordinates":[8.1702680588,53.1606712341],"type":"Point"}
}