{
  "type": "Feature",
  "properties": {
    "iso:country":"DE",
    "sg:address":"Waldferiendorf 2",
    "sg:city":"Regen",
    "sg:phone":"+49 9921",
    "sg:postcode":"94209",
    "sg:province":"Bayern",
    "wof:name":"Willkommen Im Waldferiendorf Regen",
    "wof:placetype":"venue"
},
  "geometry": {"coordinates":[13.126935,48.958706],"type":"Point"}
}