{
  "type": "Feature",
  "properties": {
    "iso:country":"DE",
    "sg:address":"Am Fronhof 6",
    "sg:city":"Gro\u00dfenl\u00fcder",
    "sg:phone":"+49 6648/7541",
    "sg:postcode":"36137",
    "sg:province":"Hessen",
    "wof:name":"Winfried Schlitzer",
    "wof:placetype":"venue"
},
  "geometry": {"coordinates":[9.541743,50.587627],"type":"Point"}
}