{
  "type": "Feature",
  "properties": {
    "iso:country":"DE",
    "sg:address":"f.-Ebert-Str. 33",
    "sg:city":"Altenburg",
    "sg:phone":"+49 3447",
    "sg:postcode":"04600",
    "sg:province":"Th\u00fcringen",
    "wof:name":"Awa E.v.",
    "wof:placetype":"venue"
},
  "geometry": {"coordinates":[12.43496,50.984699],"type":"Point"}
}