{
  "type": "Feature",
  "properties": {
    "iso:country":"DE",
    "sg:address":"Giesenbach 34",
    "sg:city":"Kranzberg",
    "sg:postcode":"85402",
    "sg:province":"Bayern",
    "wof:name":"Euroil 2000 Gmbh",
    "wof:placetype":"venue"
},
  "geometry": {"coordinates":[11.614566,48.384911],"type":"Point"}
}