{
  "type": "Feature",
  "properties": {
    "iso:country":"DE",
    "sg:address":"Kreyssigstr. 6",
    "sg:city":"Brandenburg",
    "sg:phone":"+49 3381/300504",
    "sg:postcode":"14770",
    "sg:province":"Brandenburg",
    "wof:name":"Eva-maria Reichelt",
    "wof:placetype":"venue"
},
  "geometry": {"coordinates":[12.538576,52.421547],"type":"Point"}
}