{
  "type": "Feature",
  "properties": {
    "iso:country":"DE",
    "sg:address":"Industriestr 32",
    "sg:city":"Bochum",
    "sg:phone":"+49 234/922130",
    "sg:postcode":"44894",
    "sg:province":"Nordrhein-Westfalen",
    "wof:name":"K\u00f6nneker Gmbh & Co Kg",
    "wof:placetype":"venue"
},
  "geometry": {"coordinates":[7.2938899994,51.4732055664],"type":"Point"}
}