{
  "type": "Feature",
  "properties": {
    "iso:country":"DE",
    "sg:address":"Vechteaue 2",
    "sg:city":"Nordhorn",
    "sg:phone":"+49 5921/990801",
    "sg:postcode":"48529",
    "sg:province":"Niedersachsen",
    "wof:name":"Kultur- Und Tourismuszentrum Alte Weberei Nordhorn",
    "wof:placetype":"venue"
},
  "geometry": {"coordinates":[7.0754499435,52.4332809448],"type":"Point"}
}