{
  "type": "Feature",
  "properties": {
    "iso:country":"DE",
    "sg:address":"Vogelsangstr. 5",
    "sg:city":"Weil im Sch\u00f6nbuch",
    "sg:phone":"+49 7157/62235",
    "sg:postcode":"71093",
    "sg:province":"Baden-W\u00fcrttemberg",
    "wof:name":"Wilhelmine Jockers Hebamme",
    "wof:placetype":"venue"
},
  "geometry": {"coordinates":[9.059117,48.626522],"type":"Point"}
}