{
  "type": "Feature",
  "properties": {
    "iso:country":"DE",
    "sg:address":"Dahlener Str. 515",
    "sg:city":"M\u00f6nchengladbach",
    "sg:phone":"+49 2166/124959",
    "sg:postcode":"41239",
    "sg:province":"Nordrhein-Westfalen",
    "wof:name":"Kaiserschnitt Andrea Bruckschen Gmbh",
    "wof:placetype":"venue"
},
  "geometry": {"coordinates":[6.4160017967,51.159576416],"type":"Point"}
}