{
  "type": "Feature",
  "properties": {
    "iso:country":"DE",
    "sg:address":"Augustenstr. 15",
    "sg:city":"Stuttgart",
    "sg:phone":"+49 4971/1629020",
    "sg:postcode":"70178",
    "sg:province":"Baden-W\u00fcrttemberg",
    "wof:name":"Bank F\u00fcr Sozialwirtschaft Gmbh",
    "wof:placetype":"venue"
},
  "geometry": {"coordinates":[9.168645,48.772121],"type":"Point"}
}