{
  "type": "Feature",
  "properties": {
    "iso:country":"DE",
    "sg:address":"Heinrichstr. 6",
    "sg:city":"Leipzig",
    "sg:phone":"+49 341/649210",
    "sg:postcode":"04317",
    "sg:province":"Sachsen",
    "wof:name":"Filmtheaterbetriebe Leipzig Gmbh",
    "wof:placetype":"venue"
},
  "geometry": {"coordinates":[12.4016876221,51.3386611938],"type":"Point"}
}