{
  "type": "Feature",
  "properties": {
    "iso:country":"DE",
    "sg:address":"Igelweg 3",
    "sg:city":"Adendorf",
    "sg:postcode":"21365",
    "sg:province":"Niedersachsen",
    "wof:name":"Kaiser Datentechnik",
    "wof:placetype":"venue"
},
  "geometry": {"coordinates":[10.460015,53.283176],"type":"Point"}
}