{
  "type": "Feature",
  "properties": {
    "iso:country":"DE",
    "sg:address":"Kirchgasse 2",
    "sg:city":"Bayreuth",
    "sg:phone":"+49 921/23652",
    "sg:postcode":"95444",
    "sg:province":"Bayern",
    "wof:name":"Richard Renner Kg B\u00fcrobedarf",
    "wof:placetype":"venue"
},
  "geometry": {"coordinates":[11.573972,49.944481],"type":"Point"}
}