{
  "type": "Feature",
  "properties": {
    "iso:country":"DE",
    "sg:address":"Hallesche Str. 27",
    "sg:city":"Schkopau",
    "sg:postcode":"06258",
    "sg:province":"Sachsen-Anhalt",
    "wof:name":"Rmh-polymers L\u00f6sungen Mitr Polymeren Gmbh & Co. Kg",
    "wof:placetype":"venue"
},
  "geometry": {"coordinates":[11.978597641,51.3987121582],"type":"Point"}
}