{
  "type": "Feature",
  "properties": {
    "iso:country":"DE",
    "sg:address":"Stollberger Str. 13",
    "sg:city":"Jahnsdorf",
    "sg:postcode":"09387",
    "sg:province":"Sachsen",
    "wof:name":"Deutex Handelsgesellschaft Mbh",
    "wof:placetype":"venue"
},
  "geometry": {"coordinates":[12.847413063,50.7388114929],"type":"Point"}
}