{
  "type": "Feature",
  "properties": {
    "iso:country":"DE",
    "sg:address":"Hallesche Str. 3",
    "sg:city":"Falkensee",
    "sg:phone":"+49 3322/201049",
    "sg:postcode":"14612",
    "sg:province":"Brandenburg",
    "wof:name":"Heemann Ohg",
    "wof:placetype":"venue"
},
  "geometry": {"coordinates":[13.1039390564,52.5518531799],"type":"Point"}
}