{
  "type": "Feature",
  "properties": {
    "iso:country":"DE",
    "sg:address":"Juteweg 2",
    "sg:city":"Vechelde",
    "sg:phone":"+49 5302/902928",
    "sg:postcode":"38159",
    "sg:province":"Niedersachsen",
    "wof:name":"Stephan Jungeblut Architekt",
    "wof:placetype":"venue"
},
  "geometry": {"coordinates":[10.376512,52.259232],"type":"Point"}
}