{
  "type": "Feature",
  "properties": {
    "iso:country":"DE",
    "sg:address":"Frankfurter Str. 55",
    "sg:city":"Limburg",
    "sg:phone":"+49 6431/41640",
    "sg:postcode":"65549",
    "sg:province":"Hessen",
    "wof:name":"Aral Ag",
    "wof:placetype":"venue"
},
  "geometry": {"coordinates":[8.0697822571,50.3842697144],"type":"Point"}
}