{
  "type": "Feature",
  "properties": {
    "iso:country":"DE",
    "sg:address":"Seegraben 3",
    "sg:city":"Aschersleben",
    "sg:phone":"+49 3473/806861",
    "sg:postcode":"06449",
    "sg:province":"Sachsen-Anhalt",
    "wof:name":"Manfred Ansorge",
    "wof:placetype":"venue"
},
  "geometry": {"coordinates":[11.459956,51.759785],"type":"Point"}
}