{
  "type": "Feature",
  "properties": {
    "iso:country":"DE",
    "sg:address":"Goslarer Str. 6 A",
    "sg:city":"Osterwieck",
    "sg:phone":"+49 39421/73740",
    "sg:postcode":"38835",
    "sg:province":"Sachsen-Anhalt",
    "wof:name":"Udo Reuer Polsterm\u00f6belreparatur",
    "wof:placetype":"venue"
},
  "geometry": {"coordinates":[10.7042064667,51.9716491699],"type":"Point"}
}