{
  "type": "Feature",
  "properties": {
    "iso:country":"DE",
    "sg:address":"Bahnhofstr. 99",
    "sg:city":"Schuld",
    "sg:phone":"+49 2695/271",
    "sg:postcode":"53520",
    "sg:province":"Rheinland-Pfalz",
    "wof:name":"Hans Schug Gmbh",
    "wof:placetype":"venue"
},
  "geometry": {"coordinates":[6.87699,50.44643],"type":"Point"}
}