{
  "type": "Feature",
  "properties": {
    "iso:country":"DE",
    "sg:address":"Aulhauser Str. 16a",
    "sg:city":"R\u00fcdesheim am Rhein",
    "sg:phone":"+49 6722/3916",
    "sg:postcode":"65385",
    "sg:province":"Hessen",
    "wof:name":"Dieter Wagner",
    "wof:placetype":"venue"
},
  "geometry": {"coordinates":[7.87692,49.992031],"type":"Point"}
}