{
  "type": "Feature",
  "properties": {
    "iso:country":"DE",
    "sg:address":"Bahnhofstr. 9",
    "sg:city":"Lauter",
    "sg:postcode":"08312",
    "sg:province":"Sachsen",
    "wof:name":"Ideal-bau-lauter Bautr\u00e4ger Gmbh & Co. Kg",
    "wof:placetype":"venue"
},
  "geometry": {"coordinates":[12.749114,50.565117],"type":"Point"}
}