{
  "type": "Feature",
  "properties": {
    "iso:country":"DE",
    "sg:address":"Woltmershauser Str. 174",
    "sg:city":"Bremen",
    "sg:phone":"+49 421/541102",
    "sg:postcode":"28197",
    "sg:province":"Bremen",
    "wof:name":"Heinz Meyer Gmbh Metallverarbeitung",
    "wof:placetype":"venue"
},
  "geometry": {"coordinates":[8.7781,53.078918],"type":"Point"}
}