{
  "type": "Feature",
  "properties": {
    "iso:country":"DE",
    "sg:address":"Sonneckstr. 31",
    "sg:city":"Weitnau",
    "sg:phone":"+49 8375/1466",
    "sg:postcode":"87480",
    "sg:province":"Bayern",
    "wof:name":"Toni Nessler",
    "wof:placetype":"venue"
},
  "geometry": {"coordinates":[10.1000442505,47.6641159058],"type":"Point"}
}