{
  "type": "Feature",
  "properties": {
    "iso:country":"DE",
    "sg:address":"Fuhlrottstr. 40",
    "sg:city":"Erkrath",
    "sg:phone":"+49 2104/45346",
    "sg:postcode":"40699",
    "sg:province":"Nordrhein-Westfalen",
    "wof:name":"Waltraud R\u00f6se Steuerberaterin",
    "wof:placetype":"venue"
},
  "geometry": {"coordinates":[6.9529452324,51.2143630981],"type":"Point"}
}