{
  "type": "Feature",
  "properties": {
    "iso:country":"DE",
    "sg:address":"Waldparkdamm 2",
    "sg:city":"Mannheim",
    "sg:phone":"+49 621/8321697",
    "sg:postcode":"68163",
    "sg:province":"Baden-W\u00fcrttemberg",
    "wof:name":"Wolfgang Haas Steuerberater",
    "wof:placetype":"venue"
},
  "geometry": {"coordinates":[8.4672393799,49.4696235657],"type":"Point"}
}