{
  "type": "Feature",
  "properties": {
    "iso:country":"DE",
    "sg:address":"Hindenburgstr. 16a",
    "sg:city":"Bassum",
    "sg:phone":"+49 4241/2429",
    "sg:postcode":"27211",
    "sg:province":"Niedersachsen",
    "wof:name":"Wolfgang Schmidt Bedachungen Gmbh",
    "wof:placetype":"venue"
},
  "geometry": {"coordinates":[8.719656,52.847984],"type":"Point"}
}