{
  "type": "Feature",
  "properties": {
    "iso:country":"DE",
    "sg:address":"M\u00fchlenstr. 16-20",
    "sg:city":"Hamburg",
    "sg:phone":"+49 40/3984120",
    "sg:postcode":"22049",
    "sg:province":"Hamburg",
    "wof:name":"Lawaetz Stiftung",
    "wof:placetype":"venue"
},
  "geometry": {"coordinates":[10.067435,53.582787],"type":"Point"}
}