{
  "type": "Feature",
  "properties": {
    "iso:country":"DE",
    "sg:address":"Hoher Weg 1",
    "sg:city":"Augsburg",
    "sg:phone":"+49 4975/815060",
    "sg:postcode":"86152",
    "sg:province":"Bayern",
    "wof:name":"Stadtwerke Bad Saulgau",
    "wof:placetype":"venue"
},
  "geometry": {"coordinates":[9.496383,48.021622],"type":"Point"}
}