{
  "type": "Feature",
  "properties": {
    "iso:country":"DE",
    "sg:address":"Hohfuhrstr. 3",
    "sg:city":"L\u00fcdenscheid",
    "sg:phone":"+49 2351/363061",
    "sg:postcode":"58509",
    "sg:province":"Nordrhein-Westfalen",
    "wof:name":"Kaufpark",
    "wof:placetype":"venue"
},
  "geometry": {"coordinates":[7.627974987,51.2152633667],"type":"Point"}
}