{
  "type": "Feature",
  "properties": {
    "iso:country":"DE",
    "sg:address":"Albecker Steige 79",
    "sg:city":"Ulm",
    "sg:phone":"+49 731/23245",
    "sg:postcode":"89075",
    "sg:province":"Baden-W\u00fcrttemberg",
    "wof:name":"Pierre Policard Architekt",
    "wof:placetype":"venue"
},
  "geometry": {"coordinates":[9.999896,48.41431],"type":"Point"}
}