{
  "type": "Feature",
  "properties": {
    "iso:country":"DE",
    "sg:address":"Hauptstr. 16",
    "sg:city":"Adenb\u00fcttel",
    "sg:phone":"+49 5304/2388",
    "sg:postcode":"38528",
    "sg:province":"Niedersachsen",
    "wof:name":"Udo Bosse",
    "wof:placetype":"venue"
},
  "geometry": {"coordinates":[10.451087,52.379463],"type":"Point"}
}