{
  "type": "Feature",
  "properties": {
    "iso:country":"DE",
    "sg:address":"Albertusstr. 13",
    "sg:city":"Amerdingen",
    "sg:phone":"+49 9089/313",
    "sg:postcode":"86735",
    "sg:province":"Bayern",
    "wof:name":"Bernhard Schildenberger",
    "wof:placetype":"venue"
},
  "geometry": {"coordinates":[10.5037603378,48.7542877197],"type":"Point"}
}