{
  "type": "Feature",
  "properties": {
    "iso:country":"DE",
    "sg:address":"Seestr. 43",
    "sg:city":"Radolfzell",
    "sg:phone":"+49 7732/57477",
    "sg:postcode":"78315",
    "sg:province":"Baden-W\u00fcrttemberg",
    "wof:name":"Karin Brose",
    "wof:placetype":"venue"
},
  "geometry": {"coordinates":[8.968414,47.736904],"type":"Point"}
}