{
  "type": "Feature",
  "properties": {
    "iso:country":"DE",
    "sg:address":"Thalenhorststr. 18",
    "sg:city":"Bremen",
    "sg:phone":"+49 421/4841025",
    "sg:postcode":"28307",
    "sg:province":"Bremen",
    "wof:name":"Stefan Buben",
    "wof:placetype":"venue"
},
  "geometry": {"coordinates":[8.959378,53.037601],"type":"Point"}
}