{
  "type": "Feature",
  "properties": {
    "iso:country":"DE",
    "sg:address":"Schulweg 7",
    "sg:city":"Rinteln",
    "sg:postcode":"31737",
    "sg:province":"Niedersachsen",
    "wof:name":"Mehrzweckhalle Engern",
    "wof:placetype":"venue"
},
  "geometry": {"coordinates":[9.08369,52.186451],"type":"Point"}
}