{
  "type": "Feature",
  "properties": {
    "iso:country":"DE",
    "sg:address":"Sandhaasstr. 12",
    "sg:city":"Haslach",
    "sg:phone":"+49 7832/96788",
    "sg:postcode":"77716",
    "sg:province":"Baden-W\u00fcrttemberg",
    "wof:name":"Gr\u00fcner Baum",
    "wof:placetype":"venue"
},
  "geometry": {"coordinates":[8.1109752655,48.287071228],"type":"Point"}
}