{
  "type": "Feature",
  "properties": {
    "iso:country":"DE",
    "sg:address":"Rochlitzer Str. 58",
    "sg:city":"Colditz",
    "sg:phone":"+49 34381/42581",
    "sg:postcode":"04680",
    "sg:province":"Sachsen",
    "wof:name":"Thomas Klemm",
    "wof:placetype":"venue"
},
  "geometry": {"coordinates":[12.7979440689,51.1260681152],"type":"Point"}
}