{
  "type": "Feature",
  "properties": {
    "iso:country":"DE",
    "sg:address":"Crellenhain",
    "sg:city":"M\u00fcgeln",
    "sg:phone":"+49 34362/32404",
    "sg:postcode":"04769",
    "sg:province":"Sachsen",
    "wof:name":"Stadtbad",
    "wof:placetype":"venue"
},
  "geometry": {"coordinates":[13.0494499207,51.2359085083],"type":"Point"}
}