{
  "type": "Feature",
  "properties": {
    "iso:country":"DE",
    "sg:address":"Bahnhofstr. 2",
    "sg:city":"Butzbach",
    "sg:phone":"+49 6033/4041",
    "sg:postcode":"35510",
    "sg:province":"Hessen",
    "wof:name":"Wallbott Und Partner Rechtsanw\u00e4lte Und Notare",
    "wof:placetype":"venue"
},
  "geometry": {"coordinates":[8.6706514359,50.4314842224],"type":"Point"}
}