{
  "type": "Feature",
  "properties": {
    "iso:country":"DE",
    "sg:address":"Bei der Osterkirche 13",
    "sg:city":"Hamburg",
    "sg:phone":"+49 40/3909570",
    "sg:postcode":"22765",
    "sg:province":"Hamburg",
    "wof:name":"Ev. Pfarramt Osterkirche",
    "wof:placetype":"venue"
},
  "geometry": {"coordinates":[9.9323453903,53.555305481],"type":"Point"}
}