{
  "type": "Feature",
  "properties": {
    "iso:country":"DE",
    "sg:address":"Sudetenstr. 23",
    "sg:city":"Gersfeld",
    "sg:phone":"+49 6654/334",
    "sg:postcode":"36129",
    "sg:province":"Hessen",
    "wof:name":"Willi Sturm Kg",
    "wof:placetype":"venue"
},
  "geometry": {"coordinates":[9.9264802933,50.454914093],"type":"Point"}
}