{
  "type": "Feature",
  "properties": {
    "iso:country":"DE",
    "sg:address":"Hamannplatz 2",
    "sg:city":"M\u00fcnster",
    "sg:phone":"+49 251/247219",
    "sg:postcode":"48157",
    "sg:province":"Nordrhein-Westfalen",
    "wof:name":"A. Und F. Rotthove Ohg",
    "wof:placetype":"venue"
},
  "geometry": {"coordinates":[7.6483578682,51.9930343628],"type":"Point"}
}