{
  "type": "Feature",
  "properties": {
    "iso:country":"DE",
    "sg:address":"Stadtgarten 3",
    "sg:city":"Krefeld",
    "sg:phone":"+49 2151/771044",
    "sg:postcode":"47798",
    "sg:province":"Nordrhein-Westfalen",
    "wof:name":"Dr. Hubertus Plattenteich Rechtsanwalt",
    "wof:placetype":"venue"
},
  "geometry": {"coordinates":[6.5525360107,51.3321876526],"type":"Point"}
}