{
  "type": "Feature",
  "properties": {
    "iso:country":"DE",
    "sg:address":"M\u00f6nchstr. 6/7",
    "sg:city":"Stralsund",
    "sg:phone":"+49 3831/28750",
    "sg:postcode":"18439",
    "sg:province":"Mecklenburg-Vorpommern",
    "wof:name":"Friesenhahn Und Kr\u00fcger-kleinschmidt",
    "wof:placetype":"venue"
},
  "geometry": {"coordinates":[13.0886077881,54.3150482178],"type":"Point"}
}