{
  "type": "Feature",
  "properties": {
    "iso:country":"DE",
    "sg:address":"Bruchstr. 11",
    "sg:city":"Achim",
    "sg:phone":"+49 4202/4912",
    "sg:postcode":"28832",
    "sg:province":"Niedersachsen",
    "wof:name":"Uwe Ganske",
    "wof:placetype":"venue"
},
  "geometry": {"coordinates":[9.018543,53.017712],"type":"Point"}
}