{
  "type": "Feature",
  "properties": {
    "iso:country":"DE",
    "sg:address":"Marktplatz 4",
    "sg:city":"Butzbach",
    "sg:phone":"+49 6033/65147",
    "sg:postcode":"35510",
    "sg:province":"Hessen",
    "wof:name":"H. Und E. Volkmann",
    "wof:placetype":"venue"
},
  "geometry": {"coordinates":[8.671646,50.434353],"type":"Point"}
}