{
  "type": "Feature",
  "properties": {
    "iso:country":"DE",
    "sg:address":"Leopoldstr. 3",
    "sg:city":"Detmold",
    "sg:phone":"+49 5231/93860",
    "sg:postcode":"32756",
    "sg:province":"Nordrhein-Westfalen",
    "wof:name":"Acs Advanced Communication Systems Data Gmbh",
    "wof:placetype":"venue"
},
  "geometry": {"coordinates":[8.8808269501,51.9321289062],"type":"Point"}
}