{
  "type": "Feature",
  "properties": {
    "iso:country":"DE",
    "sg:address":"Heideweg 1",
    "sg:city":"Heist",
    "sg:phone":"+49 4122/82544",
    "sg:postcode":"25492",
    "sg:province":"Schleswig-Holstein",
    "wof:name":"Lydia Heppner Architektin",
    "wof:placetype":"venue"
},
  "geometry": {"coordinates":[9.669555,53.654392],"type":"Point"}
}