{
  "type": "Feature",
  "properties": {
    "iso:country":"DE",
    "sg:address":"Fuggerstr. 10",
    "sg:city":"Roth",
    "sg:phone":"+49 9171/9550",
    "sg:postcode":"91154",
    "sg:province":"Bayern",
    "wof:name":"O. Lux Gmbh & Co.",
    "wof:placetype":"venue"
},
  "geometry": {"coordinates":[11.1093769073,49.2496452332],"type":"Point"}
}