{
  "type": "Feature",
  "properties": {
    "iso:country":"DE",
    "sg:address":"Landgraf-Karl-Stra\u00dfe 2",
    "sg:city":"Kassel",
    "sg:phone":"+49 561",
    "sg:postcode":"34131",
    "sg:province":"Hessen",
    "wof:name":"Agp E.v. Arbeitsgemeinschaft Partnerschaft In Der Wirtschaft",
    "wof:placetype":"venue"
},
  "geometry": {"coordinates":[9.4438943863,51.3132171631],"type":"Point"}
}