{
  "type": "Feature",
  "properties": {
    "iso:country":"DE",
    "sg:address":"Gudensberger Str. 13",
    "sg:city":"Kaufungen",
    "sg:phone":"+49 5605/3933",
    "sg:postcode":"34260",
    "sg:province":"Hessen",
    "wof:name":"Klaus Friedrich Ergotherapiepraxis",
    "wof:placetype":"venue"
},
  "geometry": {"coordinates":[9.615465,51.280937],"type":"Point"}
}