{
  "type": "Feature",
  "properties": {
    "iso:country":"DE",
    "sg:address":"Elfershausener Str. 18",
    "sg:city":"Hammelburg",
    "sg:phone":"+49 9732/7556",
    "sg:postcode":"97762",
    "sg:province":"Bayern",
    "wof:name":"O. Besler",
    "wof:placetype":"venue"
},
  "geometry": {"coordinates":[9.9373941422,50.1230545044],"type":"Point"}
}