{
  "type": "Feature",
  "properties": {
    "iso:country":"DE",
    "sg:address":"Bahnhofstr. 5",
    "sg:city":"Walddrehna",
    "sg:phone":"+49 35455/443",
    "sg:postcode":"15926",
    "sg:province":"Brandenburg",
    "wof:name":"W. Schulze",
    "wof:placetype":"venue"
},
  "geometry": {"coordinates":[13.618493,51.775394],"type":"Point"}
}