{
  "type": "Feature",
  "properties": {
    "iso:country":"DE",
    "sg:address":"Bergstr. 60/1",
    "sg:city":"Weinheim",
    "sg:phone":"+49 6201/185227",
    "sg:postcode":"69469",
    "sg:province":"Baden-W\u00fcrttemberg",
    "wof:name":"Ohrmundt Versicherungsmakler Gmbh",
    "wof:placetype":"venue"
},
  "geometry": {"coordinates":[8.669462204,49.559211731],"type":"Point"}
}