{
  "type": "Feature",
  "properties": {
    "iso:country":"DE",
    "sg:address":"Freitagsgasse 13",
    "sg:city":"Sinsheim",
    "sg:phone":"+49 7261/979784",
    "sg:postcode":"74889",
    "sg:province":"Baden-W\u00fcrttemberg",
    "wof:name":"Klaus Fa\u00dfrainer",
    "wof:placetype":"venue"
},
  "geometry": {"coordinates":[8.8794002533,49.2519683838],"type":"Point"}
}