{
  "type": "Feature",
  "properties": {
    "iso:country":"DE",
    "sg:address":"Heuerweg 4",
    "sg:city":"Rheine",
    "sg:phone":"+49 5971/65517",
    "sg:postcode":"48429",
    "sg:province":"Nordrhein-Westfalen",
    "wof:name":"Rheiner Schiffsmodellbau- Club E. V.",
    "wof:placetype":"venue"
},
  "geometry": {"coordinates":[7.4523382187,52.2946281433],"type":"Point"}
}