{
  "type": "Feature",
  "properties": {
    "iso:country":"DE",
    "sg:address":"Neuweg 4",
    "sg:city":"Ladenburg",
    "sg:phone":"+49 6203/16514",
    "sg:postcode":"68526",
    "sg:province":"Baden-W\u00fcrttemberg",
    "wof:name":"K. Pieper",
    "wof:placetype":"venue"
},
  "geometry": {"coordinates":[8.609149,49.471859],"type":"Point"}
}