{
  "type": "Feature",
  "properties": {
    "iso:country":"DE",
    "sg:address":"In Der Braike 21",
    "sg:city":"Owen",
    "sg:phone":"+49 7021/980300",
    "sg:postcode":"73277",
    "sg:province":"Baden-W\u00fcrttemberg",
    "wof:name":"Idupa Sch\u00dcbelin Gmbh",
    "wof:placetype":"venue"
},
  "geometry": {"coordinates":[9.4475870132,48.581577301],"type":"Point"}
}