{
  "type": "Feature",
  "properties": {
    "iso:country":"DE",
    "sg:address":"Wilhelmstr. 31",
    "sg:city":"Verl",
    "sg:phone":"+49 5246/5767",
    "sg:postcode":"33415",
    "sg:province":"Nordrhein-Westfalen",
    "wof:name":"Shah",
    "wof:placetype":"venue"
},
  "geometry": {"coordinates":[8.5065631866,51.8823432922],"type":"Point"}
}