{
  "type": "Feature",
  "properties": {
    "iso:country":"DE",
    "sg:address":"Bahnhofstr. 44",
    "sg:city":"Schmallenberg",
    "sg:phone":"+49 2972/5401",
    "sg:postcode":"57392",
    "sg:province":"Nordrhein-Westfalen",
    "wof:name":"Tapetenhaus Vollmert",
    "wof:placetype":"venue"
},
  "geometry": {"coordinates":[8.292715,51.158405],"type":"Point"}
}