{
  "type": "Feature",
  "properties": {
    "iso:country":"DE",
    "sg:address":"Barkholt 63",
    "sg:city":"Gro\u00dfhansdorf",
    "sg:postcode":"22927",
    "sg:province":"Schleswig-Holstein",
    "wof:name":"Bittner \u00dcberseehandel Gmbh",
    "wof:placetype":"venue"
},
  "geometry": {"coordinates":[10.2812433243,53.6531028748],"type":"Point"}
}