{
  "type": "Feature",
  "properties": {
    "iso:country":"DE",
    "sg:address":"Georg-August-Zinn-Str. 36",
    "sg:city":"Gro\u00df-Umstadt",
    "sg:phone":"+49 6078/3576",
    "sg:postcode":"64823",
    "sg:province":"Hessen",
    "wof:name":"Heinrich Frie\u00df",
    "wof:placetype":"venue"
},
  "geometry": {"coordinates":[8.927151,49.867496],"type":"Point"}
}