{
  "type": "Feature",
  "properties": {
    "iso:country":"DE",
    "sg:address":"Bamberger Str. 27",
    "sg:city":"Neustadt",
    "sg:phone":"+49 9161/62936",
    "sg:postcode":"91413",
    "sg:province":"Bayern",
    "wof:name":"W. Pflug",
    "wof:placetype":"venue"
},
  "geometry": {"coordinates":[10.61055,49.582039],"type":"Point"}
}