{
  "type": "Feature",
  "properties": {
    "iso:country":"DE",
    "sg:address":"Eilenburger Str. 4",
    "sg:city":"Paschwitz",
    "sg:postcode":"04838",
    "sg:province":"Sachsen",
    "wof:name":"Erika Hellmuth",
    "wof:placetype":"venue"
},
  "geometry": {"coordinates":[12.7199287415,51.4665184021],"type":"Point"}
}