{
  "type": "Feature",
  "properties": {
    "iso:country":"DE",
    "sg:address":"Kohlteichstr. 7",
    "sg:city":"Gutenzell-H\u00fcrbel",
    "sg:postcode":"88484",
    "sg:province":"Baden-W\u00fcrttemberg",
    "wof:name":"Siweco Gmbh",
    "wof:placetype":"venue"
},
  "geometry": {"coordinates":[10.0029668808,48.1198768616],"type":"Point"}
}