{
  "type": "Feature",
  "properties": {
    "iso:country":"DE",
    "sg:address":"Kirchstr. 19",
    "sg:city":"Bad Ditzenbach",
    "sg:phone":"+49 7334/5273",
    "sg:postcode":"73342",
    "sg:province":"Baden-W\u00fcrttemberg",
    "wof:name":"Ev. Pfarramt Auendorf",
    "wof:placetype":"venue"
},
  "geometry": {"coordinates":[9.7046298981,48.5888671875],"type":"Point"}
}