{
  "type": "Feature",
  "properties": {
    "iso:country":"DE",
    "sg:address":"Veilchenweg 10",
    "sg:city":"Buchen",
    "sg:phone":"+49 6281/3741",
    "sg:postcode":"74722",
    "sg:province":"Baden-W\u00fcrttemberg",
    "wof:name":"Manfred Busch Steuerbevollm\u00e4chtigter",
    "wof:placetype":"venue"
},
  "geometry": {"coordinates":[9.3258543015,49.5329627991],"type":"Point"}
}