{
  "type": "Feature",
  "properties": {
    "iso:country":"DE",
    "sg:address":"Eugen-Bolz-Str. 6",
    "sg:city":"Ravensburg",
    "sg:phone":"+49 751/31801",
    "sg:postcode":"88212",
    "sg:province":"Baden-W\u00fcrttemberg",
    "wof:name":"Roland Labidi",
    "wof:placetype":"venue"
},
  "geometry": {"coordinates":[9.6251163483,47.7918739319],"type":"Point"}
}