{
  "type": "Feature",
  "properties": {
    "iso:country":"DE",
    "sg:address":"Hauptstr. 28",
    "sg:city":"Medelby",
    "sg:phone":"+49 4605/189476",
    "sg:postcode":"24994",
    "sg:province":"Schleswig-Holstein",
    "wof:name":"Gastst\u00e4tte Kl\u00f6nstuv",
    "wof:placetype":"venue"
},
  "geometry": {"coordinates":[9.1721973419,54.8128738403],"type":"Point"}
}