{
  "type": "Feature",
  "properties": {
    "iso:country":"DE",
    "sg:address":"Irmintrudisstr. 1",
    "sg:city":"Bonn",
    "sg:phone":"+49 228/639475",
    "sg:postcode":"53111",
    "sg:province":"Nordrhein-Westfalen",
    "wof:name":"Cassius Forum Bonn E. V.",
    "wof:placetype":"venue"
},
  "geometry": {"coordinates":[7.094895,50.743248],"type":"Point"}
}