{
  "type": "Feature",
  "properties": {
    "iso:country":"DE",
    "sg:city":"Baiern",
    "sg:phone":"+49 8093/5011",
    "sg:postcode":"85625",
    "sg:province":"Bayern",
    "wof:name":"Raiffeisenbank Glonn Eg",
    "wof:placetype":"venue"
},
  "geometry": {"coordinates":[11.91695,47.979271],"type":"Point"}
}