{
  "type": "Feature",
  "properties": {
    "iso:country":"DE",
    "sg:address":"Birkenallee 57",
    "sg:city":"Hockenheim",
    "sg:phone":"+49 6205/94160",
    "sg:postcode":"68766",
    "sg:province":"Baden-W\u00fcrttemberg",
    "wof:name":"Schneider Hausverwaltung Gmbh",
    "wof:placetype":"venue"
},
  "geometry": {"coordinates":[8.5556659698,49.3260536194],"type":"Point"}
}