{
  "type": "Feature",
  "properties": {
    "iso:country":"DE",
    "sg:address":"K\u00f6nigstr. 32",
    "sg:city":"Marne",
    "sg:phone":"+49 4851/566",
    "sg:postcode":"25709",
    "sg:province":"Schleswig-Holstein",
    "wof:name":"Paul Gnekow Steinmetzbetrieb",
    "wof:placetype":"venue"
},
  "geometry": {"coordinates":[9.0087633133,53.9546318054],"type":"Point"}
}