{
  "type": "Feature",
  "properties": {
    "iso:country":"DE",
    "sg:address":"Europastr. 12",
    "sg:city":"Spaichingen",
    "sg:phone":"+49 7424/4933",
    "sg:postcode":"78549",
    "sg:province":"Baden-W\u00fcrttemberg",
    "wof:name":"Minimal",
    "wof:placetype":"venue"
},
  "geometry": {"coordinates":[8.7327156067,48.0783157349],"type":"Point"}
}