{
  "type": "Feature",
  "properties": {
    "iso:country":"DE",
    "sg:address":"Lohbr\u00fcgger Landstr. 23",
    "sg:city":"Hamburg",
    "sg:phone":"+49 40/7219495",
    "sg:postcode":"21031",
    "sg:province":"Hamburg",
    "wof:name":"Norzel & Wucherpfennig Ergotherapiepraxis",
    "wof:placetype":"venue"
},
  "geometry": {"coordinates":[10.204159,53.496544],"type":"Point"}
}