{
  "type": "Feature",
  "properties": {
    "iso:country":"DE",
    "sg:address":"Tullastr. 15",
    "sg:city":"Mannheim",
    "sg:postcode":"68161",
    "sg:province":"Baden-W\u00fcrttemberg",
    "wof:name":"S\u00fcdwest-grund Mannheim Bautr\u00e4ger Und Immobilien Gmbh",
    "wof:placetype":"venue"
},
  "geometry": {"coordinates":[8.47728,49.485958],"type":"Point"}
}