{
  "type": "Feature",
  "properties": {
    "iso:country":"DE",
    "sg:address":"Th\u00e4lmannstr. 8",
    "sg:city":"M\u00f6ser",
    "sg:phone":"+49 39222/2911",
    "sg:postcode":"39291",
    "sg:province":"Sachsen-Anhalt",
    "wof:name":"Pension Sonnenschein",
    "wof:placetype":"venue"
},
  "geometry": {"coordinates":[11.7930421829,52.217250824],"type":"Point"}
}