{
  "type": "Feature",
  "properties": {
    "iso:country":"DE",
    "sg:address":"Tummelhaus 5",
    "sg:city":"Pfullendorf",
    "sg:phone":"+49 7552/408131",
    "sg:postcode":"88630",
    "sg:province":"Baden-W\u00fcrttemberg",
    "wof:name":"Erstellung Von Websites",
    "wof:placetype":"venue"
},
  "geometry": {"coordinates":[9.26107,47.928314],"type":"Point"}
}