{
  "type": "Feature",
  "properties": {
    "iso:country":"DE",
    "sg:address":"Hauptstr. 27",
    "sg:city":"Igersheim",
    "sg:phone":"+49 7931/8923",
    "sg:postcode":"97999",
    "sg:province":"Baden-W\u00fcrttemberg",
    "wof:name":"Alois Landwehr",
    "wof:placetype":"venue"
},
  "geometry": {"coordinates":[9.847986,49.533279],"type":"Point"}
}