{
  "type": "Feature",
  "properties": {
    "iso:country":"DE",
    "sg:address":"Hauptstr. 59",
    "sg:city":"Garmisch-Partenkirchen",
    "sg:phone":"+49 8821/71899",
    "sg:postcode":"82467",
    "sg:province":"Bayern",
    "wof:name":"Ampezzan",
    "wof:placetype":"venue"
},
  "geometry": {"coordinates":[11.104725,47.494926],"type":"Point"}
}