{
  "type": "Feature",
  "properties": {
    "iso:country":"DE",
    "sg:address":"Lange Fuhr 23",
    "sg:city":"Dortmund",
    "sg:phone":"+49 231/175341",
    "sg:postcode":"44149",
    "sg:province":"Nordrhein-Westfalen",
    "wof:name":"M. Haufe",
    "wof:placetype":"venue"
},
  "geometry": {"coordinates":[7.409673,51.501587],"type":"Point"}
}