{
  "type": "Feature",
  "properties": {
    "iso:country":"DE",
    "sg:city":"Leisel",
    "sg:phone":"+49 6787/8787",
    "sg:postcode":"55767",
    "sg:province":"Rheinland-Pfalz",
    "wof:name":"C. Bauer",
    "wof:placetype":"venue"
},
  "geometry": {"coordinates":[7.203985,49.718967],"type":"Point"}
}