{
  "type": "Feature",
  "properties": {
    "iso:country":"DE",
    "sg:address":"M\u00fchlgasse 3",
    "sg:city":"Amberg",
    "sg:phone":"+49 9621/470098",
    "sg:postcode":"92224",
    "sg:province":"Bayern",
    "wof:name":"Rockdomizil",
    "wof:placetype":"venue"
},
  "geometry": {"coordinates":[11.8548402786,49.446395874],"type":"Point"}
}