{
  "type": "Feature",
  "properties": {
    "iso:country":"DE",
    "sg:address":"Niedernstr. 25",
    "sg:city":"L\u00fcbbecke",
    "sg:phone":"+49 5741/40834",
    "sg:postcode":"32312",
    "sg:province":"Nordrhein-Westfalen",
    "wof:name":"Lady-line",
    "wof:placetype":"venue"
},
  "geometry": {"coordinates":[8.6172447205,52.3045730591],"type":"Point"}
}