{
  "type": "Feature",
  "properties": {
    "iso:country":"DE",
    "sg:address":"Schneewittchenstr. 22",
    "sg:city":"Bayreuth",
    "sg:phone":"+49 921/31064",
    "sg:postcode":"95447",
    "sg:province":"Bayern",
    "wof:name":"Richard Gabriel Zeltverleih",
    "wof:placetype":"venue"
},
  "geometry": {"coordinates":[11.5347261429,49.9372711182],"type":"Point"}
}