{
  "type": "Feature",
  "properties": {
    "iso:country":"DE",
    "sg:address":"Werner-von-Siemens-Str. 21",
    "sg:city":"Singen",
    "sg:phone":"+49 7731/12343",
    "sg:postcode":"78224",
    "sg:province":"Baden-W\u00fcrttemberg",
    "wof:name":"Sultanimbiss",
    "wof:placetype":"venue"
},
  "geometry": {"coordinates":[8.8868579865,47.753036499],"type":"Point"}
}