{
  "type": "Feature",
  "properties": {
    "iso:country":"DE",
    "sg:address":"Birkenweg 2",
    "sg:city":"Velpke",
    "sg:phone":"+49 5364/4867",
    "sg:postcode":"38458",
    "sg:province":"Niedersachsen",
    "wof:name":"Derby",
    "wof:placetype":"venue"
},
  "geometry": {"coordinates":[10.9491567612,52.4042282104],"type":"Point"}
}