{
  "type": "Feature",
  "properties": {
    "iso:country":"DE",
    "sg:address":"Feldstr. 47",
    "sg:city":"Kiel",
    "sg:phone":"+49 431/561076",
    "sg:postcode":"24105",
    "sg:province":"Schleswig-Holstein",
    "wof:name":"Deutsche Seebestattungs- Genossenschaft Im Bundesverb.",
    "wof:placetype":"venue"
},
  "geometry": {"coordinates":[10.139736,54.336044],"type":"Point"}
}