{
  "type": "Feature",
  "properties": {
    "iso:country":"DE",
    "sg:address":"Simon-Breu-Str. 27",
    "sg:city":"Simbach/Inn",
    "sg:phone":"+49 8571/921375",
    "sg:postcode":"84359",
    "sg:province":"Bayern",
    "wof:name":"Vermessungsingenieur Br\u00fcckner-bardroff",
    "wof:placetype":"venue"
},
  "geometry": {"coordinates":[13.020975,48.268768],"type":"Point"}
}