{
  "type": "Feature",
  "properties": {
    "iso:country":"DE",
    "sg:address":"Lengenbach 16",
    "sg:city":"Deining",
    "sg:phone":"+49 9184/1676",
    "sg:postcode":"92364",
    "sg:province":"Bayern",
    "wof:name":"Gastst\u00e4tte Hans Krau\u00df",
    "wof:placetype":"venue"
},
  "geometry": {"coordinates":[11.5320100784,49.2614097595],"type":"Point"}
}