{
  "type": "Feature",
  "properties": {
    "iso:country":"DE",
    "sg:address":"Havelberger Str. 17",
    "sg:city":"Berlin",
    "sg:phone":"+49 30/3961115",
    "sg:postcode":"10559",
    "sg:province":"Berlin",
    "wof:name":"Verlag Erich Scheer Gmbh",
    "wof:placetype":"venue"
},
  "geometry": {"coordinates":[13.3468952179,52.5345993042],"type":"Point"}
}