{
  "type": "Feature",
  "properties": {
    "iso:country":"DE",
    "sg:address":"Leipziger Str. 4",
    "sg:city":"Zwickau",
    "sg:phone":"+49 375/212244",
    "sg:postcode":"08056",
    "sg:province":"Sachsen",
    "wof:name":"Vita Trauerhilfe Gmbh",
    "wof:placetype":"venue"
},
  "geometry": {"coordinates":[12.495525,50.721695],"type":"Point"}
}