{
  "type": "Feature",
  "properties": {
    "iso:country":"DE",
    "sg:address":"Hemdener Weg 169",
    "sg:city":"Bocholt",
    "sg:phone":"+49 2871/30177",
    "sg:postcode":"46399",
    "sg:province":"Nordrhein-Westfalen",
    "wof:name":"Bahia-restaurant",
    "wof:placetype":"venue"
},
  "geometry": {"coordinates":[6.6119318008,51.8601799011],"type":"Point"}
}