{
  "type": "Feature",
  "properties": {
    "iso:country":"DE",
    "sg:address":"Gottfried-Resl-Weg 10",
    "sg:city":"Oberstaufen",
    "sg:phone":"+49 8386/7479",
    "sg:postcode":"87534",
    "sg:province":"Bayern",
    "wof:name":"Sport Hohaus",
    "wof:placetype":"venue"
},
  "geometry": {"coordinates":[10.027259,47.554508],"type":"Point"}
}