{
  "type": "Feature",
  "properties": {
    "iso:country":"DE",
    "sg:address":"Rathausstr. 14",
    "sg:city":"V\u00f6lklingen",
    "sg:phone":"+49 6898/22337",
    "sg:postcode":"66333",
    "sg:province":"Saarland",
    "wof:name":"Anwaltskanzlei Dr. Kausch & Diete",
    "wof:placetype":"venue"
},
  "geometry": {"coordinates":[6.854233,49.249378],"type":"Point"}
}