{
  "type": "Feature",
  "properties": {
    "iso:country":"DE",
    "sg:address":"K\u00f6lner Landstr. 297",
    "sg:city":"D\u00fcsseldorf",
    "sg:phone":"+49 211/750686",
    "sg:postcode":"40589",
    "sg:province":"Nordrhein-Westfalen",
    "wof:name":"Aral Tankstelle",
    "wof:placetype":"venue"
},
  "geometry": {"coordinates":[6.8228149414,51.1825447083],"type":"Point"}
}