{
  "type": "Feature",
  "properties": {
    "iso:country":"DE",
    "sg:address":"Hansestr. 29",
    "sg:city":"Salzwedel",
    "sg:postcode":"29410",
    "sg:province":"Sachsen-Anhalt",
    "wof:name":"Bodo Chappuis",
    "wof:placetype":"venue"
},
  "geometry": {"coordinates":[11.173023,52.84338],"type":"Point"}
}