{
  "type": "Feature",
  "properties": {
    "iso:country":"DE",
    "sg:address":"Luitpoldstr. 4",
    "sg:city":"Dinkelsb\u00fchl",
    "sg:phone":"+49 9851/3058",
    "sg:postcode":"91550",
    "sg:province":"Bayern",
    "wof:name":"Rolf Sch\u00e4fer Rechtsanwalt",
    "wof:placetype":"venue"
},
  "geometry": {"coordinates":[10.3246774673,49.0699501038],"type":"Point"}
}