{
  "type": "Feature",
  "properties": {
    "iso:country":"DE",
    "sg:address":"Dorfstr. 5",
    "sg:city":"Pemfling",
    "sg:phone":"+49 9971/1541",
    "sg:postcode":"93482",
    "sg:province":"Bayern",
    "wof:name":"Georg Weber",
    "wof:placetype":"venue"
},
  "geometry": {"coordinates":[12.604278,49.250042],"type":"Point"}
}