{
  "type": "Feature",
  "properties": {
    "iso:country":"DE",
    "sg:address":"Feldstr. 34a",
    "sg:city":"Delmenhorst",
    "sg:phone":"+49 4221/978057",
    "sg:postcode":"27751",
    "sg:province":"Niedersachsen",
    "wof:name":"R. H\u00fclsemeyer",
    "wof:placetype":"venue"
},
  "geometry": {"coordinates":[8.668504,53.050251],"type":"Point"}
}