{
  "type": "Feature",
  "properties": {
    "iso:country":"DE",
    "sg:address":"Corveystr. 24",
    "sg:city":"L\u00f6ningen",
    "sg:phone":"+49 5432/3211",
    "sg:postcode":"49624",
    "sg:province":"Niedersachsen",
    "wof:name":"Heinz Siemer",
    "wof:placetype":"venue"
},
  "geometry": {"coordinates":[7.7472391129,52.7437973022],"type":"Point"}
}