{
  "type": "Feature",
  "properties": {
    "iso:country":"DE",
    "sg:address":"Hauptstr. 26",
    "sg:city":"Buchholz",
    "sg:phone":"+49 3395/302025",
    "sg:postcode":"16928",
    "sg:province":"Brandenburg",
    "wof:name":"Horst Ramin",
    "wof:placetype":"venue"
},
  "geometry": {"coordinates":[11.787661,52.538525],"type":"Point"}
}