{
  "type": "Feature",
  "properties": {
    "iso:country":"DE",
    "sg:address":"Polsumer Str. 1",
    "sg:city":"Gelsenkirchen",
    "sg:phone":"+49 209/394262",
    "sg:postcode":"45894",
    "sg:province":"Nordrhein-Westfalen",
    "wof:name":"Jacques Wein Depot Wein- Einzelhandel",
    "wof:placetype":"venue"
},
  "geometry": {"coordinates":[7.0500478745,51.5885505676],"type":"Point"}
}