{
  "type": "Feature",
  "properties": {
    "iso:country":"DE",
    "sg:address":"Ludwig-Thoma-Str. 3",
    "sg:city":"Geiselh\u00f6ring",
    "sg:phone":"+49 9423/2350",
    "sg:postcode":"94333",
    "sg:province":"Bayern",
    "wof:name":"Xaver Brunner Gmbh",
    "wof:placetype":"venue"
},
  "geometry": {"coordinates":[12.403803,48.828228],"type":"Point"}
}