{
  "type": "Feature",
  "properties": {
    "iso:country":"DE",
    "sg:address":"Heppen 27",
    "sg:city":"Bad Sassendorf",
    "sg:postcode":"59505",
    "sg:province":"Nordrhein-Westfalen",
    "wof:name":"R. I. E. Mpp Innovative Systeml\u00f6sungen Gmbh",
    "wof:placetype":"venue"
},
  "geometry": {"coordinates":[8.169922,51.585163],"type":"Point"}
}