{
  "type": "Feature",
  "properties": {
    "iso:country":"DE",
    "sg:address":"Bachstr. 4",
    "sg:city":"Piesport",
    "sg:phone":"+49 6507/2361",
    "sg:postcode":"54498",
    "sg:province":"Rheinland-Pfalz",
    "wof:name":"Josef Veit",
    "wof:placetype":"venue"
},
  "geometry": {"coordinates":[6.9160051346,49.8867721558],"type":"Point"}
}