{
  "type": "Feature",
  "properties": {
    "iso:country":"DE",
    "sg:address":"Orber Stra\u00dfe 13",
    "sg:city":"Frammersbach",
    "sg:phone":"+49 9355",
    "sg:postcode":"97833",
    "sg:province":"Bayern",
    "wof:name":"Spessarter Holzkunst",
    "wof:placetype":"venue"
},
  "geometry": {"coordinates":[9.4694652557,50.0638694763],"type":"Point"}
}