{
  "type": "Feature",
  "properties": {
    "iso:country":"DE",
    "sg:address":"Saterlandstr. 2",
    "sg:city":"Apen",
    "sg:phone":"+49 4489/92850",
    "sg:postcode":"26689",
    "sg:province":"Niedersachsen",
    "wof:name":"Georg Borchers Gmbh",
    "wof:placetype":"venue"
},
  "geometry": {"coordinates":[7.76171,53.21508],"type":"Point"}
}