{
  "type": "Feature",
  "properties": {
    "iso:country":"DE",
    "sg:address":"Rotthauser Str. 3",
    "sg:city":"Gelsenkirchen",
    "sg:phone":"+49 209/140670",
    "sg:postcode":"45879",
    "sg:province":"Nordrhein-Westfalen",
    "wof:name":"Pizzeria La Tombola",
    "wof:placetype":"venue"
},
  "geometry": {"coordinates":[7.0946002007,51.5070648193],"type":"Point"}
}