{
  "type": "Feature",
  "properties": {
    "iso:country":"DE",
    "sg:address":"St.-Martin-Str. 44",
    "sg:city":"Werneck",
    "sg:postcode":"97440",
    "sg:province":"Bayern",
    "wof:name":"Katholisches Pfarramt St. Martin",
    "wof:placetype":"venue"
},
  "geometry": {"coordinates":[10.0482244492,49.9618186951],"type":"Point"}
}