{
  "type": "Feature",
  "properties": {
    "iso:country":"DE",
    "sg:address":"Bangertstr. 8",
    "sg:city":"Hanau",
    "sg:phone":"+49 6181/24265",
    "sg:postcode":"63450",
    "sg:province":"Hessen",
    "wof:name":"Friedrich Beilstein Inh. Wilfried Porth E. K.",
    "wof:placetype":"venue"
},
  "geometry": {"coordinates":[8.916324,50.1362],"type":"Point"}
}