{
  "type": "Feature",
  "properties": {
    "iso:country":"DE",
    "sg:address":"Am Bommersbacher Hof 28",
    "sg:city":"Bous",
    "sg:phone":"+49 6834/2720",
    "sg:postcode":"66359",
    "sg:province":"Saarland",
    "wof:name":"N. Glasen",
    "wof:placetype":"venue"
},
  "geometry": {"coordinates":[6.7915802002,49.2840614319],"type":"Point"}
}