{
  "type": "Feature",
  "properties": {
    "iso:country":"DE",
    "sg:address":"Ambrosius-Heim-Str 29",
    "sg:city":"Burladingen",
    "sg:phone":"+49 7475/95240",
    "sg:postcode":"72393",
    "sg:province":"Baden-W\u00fcrttemberg",
    "wof:name":"G\u00f6ckel Druck Und Grafik Gmbh",
    "wof:placetype":"venue"
},
  "geometry": {"coordinates":[9.1102905273,48.2923622131],"type":"Point"}
}