{
  "type": "Feature",
  "properties": {
    "iso:country":"DE",
    "sg:address":"Klinikumallee 11",
    "sg:city":"Bayreuth",
    "sg:phone":"+49 921/43600",
    "sg:postcode":"95445",
    "sg:province":"Bayern",
    "wof:name":"B\u00fccher Gmbh",
    "wof:placetype":"venue"
},
  "geometry": {"coordinates":[11.5426063538,49.9430541992],"type":"Point"}
}