{
  "type": "Feature",
  "properties": {
    "iso:country":"DE",
    "sg:address":"W\u00fchlestr. 28",
    "sg:city":"G\u00f6ppingen",
    "sg:phone":"+49 7161/72033",
    "sg:postcode":"73033",
    "sg:province":"Baden-W\u00fcrttemberg",
    "wof:name":"Wilhelm G\u00f6sele",
    "wof:placetype":"venue"
},
  "geometry": {"coordinates":[9.650963,48.702557],"type":"Point"}
}