{
  "type": "Feature",
  "properties": {
    "iso:country":"DE",
    "sg:address":"Kirchstr. 5",
    "sg:city":"Oberrod",
    "sg:postcode":"56479",
    "sg:province":"Rheinland-Pfalz",
    "wof:name":"Ege Bau Gmbh",
    "wof:placetype":"venue"
},
  "geometry": {"coordinates":[8.126071,50.584305],"type":"Point"}
}