{
  "type": "Feature",
  "properties": {
    "iso:country":"DE",
    "sg:address":"H\u00f6ckhstr. 1",
    "sg:city":"Bad T\u00f6lz",
    "sg:phone":"+49 8041/3625",
    "sg:postcode":"83646",
    "sg:province":"Bayern",
    "wof:name":"G\u00e4stehaus Anneliese",
    "wof:placetype":"venue"
},
  "geometry": {"coordinates":[11.5474939346,47.7626800537],"type":"Point"}
}