{
  "type": "Feature",
  "properties": {
    "iso:country":"DE",
    "sg:address":"Bismarckstr. 13",
    "sg:city":"Hof",
    "sg:phone":"+49 9281/85800",
    "sg:postcode":"95028",
    "sg:province":"Bayern",
    "wof:name":"Bismarck-apotheke Leonard Wiedemann",
    "wof:placetype":"venue"
},
  "geometry": {"coordinates":[11.915426,50.315536],"type":"Point"}
}