{
  "type": "Feature",
  "properties": {
    "iso:country":"DE",
    "sg:address":"Am Kronenhof 10",
    "sg:city":"Esslingen",
    "sg:phone":"+49 7141/643400",
    "sg:postcode":"73728",
    "sg:province":"Baden-W\u00fcrttemberg",
    "wof:name":"Bay Kessel Systeme Gmbh + Co. Kg",
    "wof:placetype":"venue"
},
  "geometry": {"coordinates":[9.2033052444,48.9287948608],"type":"Point"}
}