{
  "type": "Feature",
  "properties": {
    "iso:country":"DE",
    "sg:address":"Raiffeisenstr. 5",
    "sg:city":"Bad Krozingen",
    "sg:phone":"+49 7633/12788",
    "sg:postcode":"79189",
    "sg:province":"Baden-W\u00fcrttemberg",
    "wof:name":"Josef Bleile",
    "wof:placetype":"venue"
},
  "geometry": {"coordinates":[7.690233,47.939289],"type":"Point"}
}