{
  "type": "Feature",
  "properties": {
    "iso:country":"DE",
    "sg:address":"B\u00fcrgerm.-Neff-Str. 4",
    "sg:city":"Viernheim",
    "sg:phone":"+49 6206/98010",
    "sg:postcode":"68519",
    "sg:province":"Hessen",
    "wof:name":"Data Plan Gmbh",
    "wof:placetype":"venue"
},
  "geometry": {"coordinates":[8.571422,49.527931],"type":"Point"}
}