{
  "type": "Feature",
  "properties": {
    "iso:country":"DE",
    "sg:address":"Neufelder Weg 1",
    "sg:city":"Schiffdorf",
    "sg:postcode":"27619",
    "sg:province":"Niedersachsen",
    "wof:name":"Erste Pick-pack Gmbh",
    "wof:placetype":"venue"
},
  "geometry": {"coordinates":[8.628241,53.581169],"type":"Point"}
}