{
  "type": "Feature",
  "properties": {
    "iso:country":"DE",
    "sg:address":"Pappelallee 13",
    "sg:city":"Ribnitz-Damgarten",
    "sg:phone":"+49 3821/813322",
    "sg:postcode":"18311",
    "sg:province":"Mecklenburg-Vorpommern",
    "wof:name":"Ferienhof Henning",
    "wof:placetype":"venue"
},
  "geometry": {"coordinates":[12.4005565643,54.2239761353],"type":"Point"}
}