{
  "type": "Feature",
  "properties": {
    "iso:country":"DE",
    "sg:address":"Holzgartenstr. 36",
    "sg:city":"Pforzheim",
    "sg:phone":"+49 7231/61012",
    "sg:postcode":"75175",
    "sg:province":"Baden-W\u00fcrttemberg",
    "wof:name":"Fachhochschule Pforzheim Hochschule F\u00fcr Gestaltung",
    "wof:placetype":"venue"
},
  "geometry": {"coordinates":[8.707853,48.887997],"type":"Point"}
}