{
  "type": "Feature",
  "properties": {
    "iso:country":"DE",
    "sg:address":"Chattenweg 3",
    "sg:city":"Biedenkopf",
    "sg:phone":"+49 6461/5277",
    "sg:postcode":"35216",
    "sg:province":"Hessen",
    "wof:name":"Inerle & Weber",
    "wof:placetype":"venue"
},
  "geometry": {"coordinates":[8.602039,50.925175],"type":"Point"}
}