{
  "type": "Feature",
  "properties": {
    "iso:country":"DE",
    "sg:address":"Mergenthalerallee 79-81",
    "sg:city":"Eschborn",
    "sg:phone":"+49 6196/96040",
    "sg:postcode":"65760",
    "sg:province":"Hessen",
    "wof:name":"Bt Telecom Deutschland Gmbh",
    "wof:placetype":"venue"
},
  "geometry": {"coordinates":[8.571453,50.135445],"type":"Point"}
}