{
  "type": "Feature",
  "properties": {
    "iso:country":"DE",
    "sg:address":"Klosterlohne 14",
    "sg:city":"Hage",
    "sg:phone":"+49 4931/974060",
    "sg:postcode":"26524",
    "sg:province":"Niedersachsen",
    "wof:name":"Korinnas Fotostudio",
    "wof:placetype":"venue"
},
  "geometry": {"coordinates":[7.2862071991,53.601524353],"type":"Point"}
}