{
  "type": "Feature",
  "properties": {
    "iso:country":"DE",
    "sg:address":"Rebenweg 5",
    "sg:city":"Hettstedt",
    "sg:phone":"+49 3476/811055",
    "sg:postcode":"06333",
    "sg:province":"Sachsen-Anhalt",
    "wof:name":"Frankes Bierstube",
    "wof:placetype":"venue"
},
  "geometry": {"coordinates":[11.500834465,51.6428947449],"type":"Point"}
}