{
  "type": "Feature",
  "properties": {
    "iso:country":"DE",
    "sg:address":"Anton-Vogt-Str. 6",
    "sg:city":"Oberkirch",
    "sg:phone":"+49 7802/50204",
    "sg:postcode":"77704",
    "sg:province":"Baden-W\u00fcrttemberg",
    "wof:name":"K. K\u00f6nig",
    "wof:placetype":"venue"
},
  "geometry": {"coordinates":[8.0405,48.557091],"type":"Point"}
}