{
  "type": "Feature",
  "properties": {
    "iso:country":"DE",
    "sg:address":"Amselstr. 9",
    "sg:city":"Garmisch-Partenkirchen",
    "sg:postcode":"82467",
    "sg:province":"Bayern",
    "wof:name":"E-center",
    "wof:placetype":"venue"
},
  "geometry": {"coordinates":[11.0979328156,47.504322052],"type":"Point"}
}