{
  "type": "Feature",
  "properties": {
    "iso:country":"DE",
    "sg:address":"Dr.-Julius-Str. 9",
    "sg:city":"Marktoberdorf",
    "sg:phone":"+49 8342/42832",
    "sg:postcode":"87616",
    "sg:province":"Bayern",
    "wof:name":"Gerhard Eiselt",
    "wof:placetype":"venue"
},
  "geometry": {"coordinates":[10.623799324,47.7787857056],"type":"Point"}
}