{
  "type": "Feature",
  "properties": {
    "iso:country":"DE",
    "sg:address":"Kaiser-Otto-Platz 6",
    "sg:city":"Meschede",
    "sg:phone":"+49 291/6214",
    "sg:postcode":"59872",
    "sg:province":"Nordrhein-Westfalen",
    "wof:name":"Linden-theater",
    "wof:placetype":"venue"
},
  "geometry": {"coordinates":[8.28352,51.345871],"type":"Point"}
}