{
  "type": "Feature",
  "properties": {
    "iso:country":"DE",
    "sg:address":"Karolingerstr. 23",
    "sg:city":"Aachen",
    "sg:phone":"+49 241/154674",
    "sg:postcode":"52070",
    "sg:province":"Nordrhein-Westfalen",
    "wof:name":"Liberales Jugendwerk Aachen E. V.",
    "wof:placetype":"venue"
},
  "geometry": {"coordinates":[6.0911130905,50.7885627747],"type":"Point"}
}