{
  "type": "Feature",
  "properties": {
    "iso:country":"DE",
    "sg:address":"\u00dcberkinger Str. 20",
    "sg:city":"Bad \u00dcberkingen",
    "sg:phone":"+49 7334/8228",
    "sg:postcode":"73337",
    "sg:province":"Baden-W\u00fcrttemberg",
    "wof:name":"E. Kr\u00f6ner Mech. Werkstatt",
    "wof:placetype":"venue"
},
  "geometry": {"coordinates":[9.766424,48.60743],"type":"Point"}
}