{
  "type": "Feature",
  "properties": {
    "iso:country":"DE",
    "sg:address":"Schlo\u00dfstr. 32",
    "sg:city":"Metzingen",
    "sg:phone":"+49 7123/1201",
    "sg:postcode":"72555",
    "sg:province":"Baden-W\u00fcrttemberg",
    "wof:name":"Wohnbau Roland Bitterlich Baubetreuungs Gmbh",
    "wof:placetype":"venue"
},
  "geometry": {"coordinates":[9.284938,48.536724],"type":"Point"}
}