{
  "type": "Feature",
  "properties": {
    "iso:country":"DE",
    "sg:address":"Platz 24",
    "sg:city":"Remscheid",
    "sg:phone":"+49 2191/88490",
    "sg:postcode":"42855",
    "sg:province":"Nordrhein-Westfalen",
    "wof:name":"Ing.-b\u00fcro H. Dieter Hoch Gmbh",
    "wof:placetype":"venue"
},
  "geometry": {"coordinates":[7.173746109,51.2040214539],"type":"Point"}
}