{
  "type": "Feature",
  "properties": {
    "iso:country":"DE",
    "sg:address":"Hauptstr. 20",
    "sg:city":"S\u00fcderl\u00fcgum",
    "sg:phone":"+49 4663/1220",
    "sg:postcode":"25923",
    "sg:province":"Schleswig-Holstein",
    "wof:name":"Grenz-apotheke",
    "wof:placetype":"venue"
},
  "geometry": {"coordinates":[8.907136,54.871418],"type":"Point"}
}