{
  "type": "Feature",
  "properties": {
    "iso:country":"DE",
    "sg:address":"Hammerstr. 22-24",
    "sg:city":"Mettmann",
    "sg:phone":"+49 2104/924900",
    "sg:postcode":"40822",
    "sg:province":"Nordrhein-Westfalen",
    "wof:name":"Josef Noll",
    "wof:placetype":"venue"
},
  "geometry": {"coordinates":[6.9791798592,51.2542381287],"type":"Point"}
}