{
  "type": "Feature",
  "properties": {
    "iso:country":"DE",
    "sg:address":"Laufener Str. 19",
    "sg:city":"Albstadt",
    "sg:phone":"+49 7431/73340",
    "sg:postcode":"72459",
    "sg:province":"Baden-W\u00fcrttemberg",
    "wof:name":"Krone",
    "wof:placetype":"venue"
},
  "geometry": {"coordinates":[8.9570026398,48.2154960632],"type":"Point"}
}