{
  "type": "Feature",
  "properties": {
    "iso:country":"DE",
    "sg:address":"Ballindamm 36",
    "sg:city":"Hamburg",
    "sg:postcode":"20095",
    "sg:province":"Hamburg",
    "wof:name":"Seefahrt Und Transport Interessen-gesellschaft Mbh",
    "wof:placetype":"venue"
},
  "geometry": {"coordinates":[9.99549,53.552097],"type":"Point"}
}