{
  "type": "Feature",
  "properties": {
    "iso:country":"DE",
    "sg:address":"Spardorfer Str. 19",
    "sg:city":"Erlangen",
    "sg:phone":"+49 9131/26024",
    "sg:postcode":"91054",
    "sg:province":"Bayern",
    "wof:name":"M\u00f6nius Finanz-marketing Gmbh",
    "wof:placetype":"venue"
},
  "geometry": {"coordinates":[11.0116300583,49.6060447693],"type":"Point"}
}