{
  "type": "Feature",
  "properties": {
    "iso:country":"DE",
    "sg:address":"Albert-Einstein-Ring 6",
    "sg:city":"Hamburg",
    "sg:phone":"+49 40/899720",
    "sg:postcode":"22761",
    "sg:province":"Hamburg",
    "wof:name":"Hdb - Hagenuk Schiffstechnik Gmbh",
    "wof:placetype":"venue"
},
  "geometry": {"coordinates":[9.888729,53.575008],"type":"Point"}
}