{
  "type": "Feature",
  "properties": {
    "iso:country":"DE",
    "sg:address":"Krumme Str. 18",
    "sg:city":"Welsleben",
    "sg:phone":"+49 39296/20309",
    "sg:postcode":"39221",
    "sg:province":"Sachsen-Anhalt",
    "wof:name":"Fleischerei Gei\u00dfner Gmbh",
    "wof:placetype":"venue"
},
  "geometry": {"coordinates":[11.6364574432,52.004573822],"type":"Point"}
}