{
  "type": "Feature",
  "properties": {
    "iso:country":"DE",
    "sg:address":"Unterm-Heilig-Kreuz 6",
    "sg:city":"Fulda",
    "sg:phone":"+49 661/9709060",
    "sg:postcode":"36037",
    "sg:province":"Hessen",
    "wof:name":"Eduscho Gmbh & Co. Kg",
    "wof:placetype":"venue"
},
  "geometry": {"coordinates":[9.676281929,50.5521392822],"type":"Point"}
}