{
  "type": "Feature",
  "properties": {
    "iso:country":"DE",
    "sg:address":"Hohwachter Weg 15",
    "sg:city":"Hamburg",
    "sg:phone":"+49 40/6684971",
    "sg:postcode":"22143",
    "sg:province":"Hamburg",
    "wof:name":"Ingenieurb\u00fcro J. Schr\u00f6der Gmbh",
    "wof:placetype":"venue"
},
  "geometry": {"coordinates":[10.16606,53.607536],"type":"Point"}
}