{
  "type": "Feature",
  "properties": {
    "iso:country":"DE",
    "sg:address":"Pivitsheider Str. 154",
    "sg:city":"Augustdorf",
    "sg:phone":"+49 5237/7763",
    "sg:postcode":"32832",
    "sg:province":"Nordrhein-Westfalen",
    "wof:name":"Katholisches Pfarramt Maria",
    "wof:placetype":"venue"
},
  "geometry": {"coordinates":[8.7626399994,51.9196166992],"type":"Point"}
}