{
  "type": "Feature",
  "properties": {
    "iso:country":"DE",
    "sg:address":"Lilienthalstr 17",
    "sg:city":"Rohrbach",
    "sg:phone":"+49 8442/96780",
    "sg:postcode":"85296",
    "sg:province":"Bayern",
    "wof:name":"Adverma Advertising & Marketing Gmbh",
    "wof:placetype":"venue"
},
  "geometry": {"coordinates":[11.579174,48.607594],"type":"Point"}
}