{
  "type": "Feature",
  "properties": {
    "iso:country":"DE",
    "sg:address":"Frankenweg 45",
    "sg:city":"Burgen",
    "sg:phone":"+49 2605/8829",
    "sg:postcode":"56332",
    "sg:province":"Rheinland-Pfalz",
    "wof:name":"B. Klas",
    "wof:placetype":"venue"
},
  "geometry": {"coordinates":[7.3840370178,50.2063026428],"type":"Point"}
}