{
  "type": "Feature",
  "properties": {
    "iso:country":"DE",
    "sg:address":"Auf'm Brinke 16",
    "sg:city":"Meschede",
    "sg:phone":"+49 291/99620",
    "sg:postcode":"59872",
    "sg:province":"Nordrhein-Westfalen",
    "wof:name":"Ith Gmbh Industrie-technische",
    "wof:placetype":"venue"
},
  "geometry": {"coordinates":[8.27208,51.356194],"type":"Point"}
}