{
  "type": "Feature",
  "properties": {
    "iso:country":"DE",
    "sg:address":"S\u00fcntelstr. 75b",
    "sg:city":"Hamburg",
    "sg:phone":"+49 40/5592028",
    "sg:postcode":"22457",
    "sg:province":"Hamburg",
    "wof:name":"Prof. Dr. Wolf-joachim H\u00f6ltje Zahnarzt F\u00fcr Mund- Und",
    "wof:placetype":"venue"
},
  "geometry": {"coordinates":[9.8947143555,53.6307601929],"type":"Point"}
}