{
  "type": "Feature",
  "properties": {
    "iso:country":"DE",
    "sg:address":"Jahnstr. 1",
    "sg:city":"Egelsbach",
    "sg:phone":"+49 6103/481830",
    "sg:postcode":"63329",
    "sg:province":"Hessen",
    "wof:name":"Protec-service Gmbh",
    "wof:placetype":"venue"
},
  "geometry": {"coordinates":[8.671373,49.966419],"type":"Point"}
}