{
  "type": "Feature",
  "properties": {
    "iso:country":"DE",
    "sg:address":"Gutenbergstr 23",
    "sg:city":"Metzingen",
    "sg:phone":"+49 7123/169560",
    "sg:postcode":"72555",
    "sg:province":"Baden-W\u00fcrttemberg",
    "wof:name":"Karl Steidinger Gmbh & Co Kg",
    "wof:placetype":"venue"
},
  "geometry": {"coordinates":[9.2746572495,48.545337677],"type":"Point"}
}