{
  "type": "Feature",
  "properties": {
    "iso:country":"DE",
    "sg:address":"Auer-Schulstr.13",
    "sg:city":"Wuppertal",
    "sg:phone":"+49 202/305044",
    "sg:postcode":"42103",
    "sg:province":"Nordrhein-Westfalen",
    "wof:name":"Das Katholische Wuppertal",
    "wof:placetype":"venue"
},
  "geometry": {"coordinates":[7.139965,51.255436],"type":"Point"}
}