{
  "type": "Feature",
  "properties": {
    "iso:country":"DE",
    "sg:address":"Kallenbergstr. 72",
    "sg:city":"Korntal-M\u00fcnchingen",
    "sg:phone":"+49 711/801690",
    "sg:postcode":"70825",
    "sg:province":"Baden-W\u00fcrttemberg",
    "wof:name":"Ev. Pfarramt Kallenberg",
    "wof:placetype":"venue"
},
  "geometry": {"coordinates":[9.1300086975,48.8500556946],"type":"Point"}
}