{
  "type": "Feature",
  "properties": {
    "iso:country":"DE",
    "sg:address":"An der Wietze 15",
    "sg:city":"Wietzendorf",
    "sg:phone":"+49 5196/535",
    "sg:postcode":"29649",
    "sg:province":"Niedersachsen",
    "wof:name":"Albert Schnorr Elektromeister",
    "wof:placetype":"venue"
},
  "geometry": {"coordinates":[9.979844,52.918854],"type":"Point"}
}