{
  "type": "Feature",
  "properties": {
    "iso:country":"DE",
    "sg:address":"Tassilostr. 5",
    "sg:city":"Donaustauf",
    "sg:phone":"+49 9403/961550",
    "sg:postcode":"93093",
    "sg:province":"Bayern",
    "wof:name":"H. Holler",
    "wof:placetype":"venue"
},
  "geometry": {"coordinates":[12.1991987228,49.0301361084],"type":"Point"}
}