{
  "type": "Feature",
  "properties": {
    "iso:country":"DE",
    "sg:address":"Graudenzer Str. 11",
    "sg:city":"Dortmund",
    "sg:phone":"+49 231/423155",
    "sg:postcode":"44263",
    "sg:province":"Nordrhein-Westfalen",
    "wof:name":"S\u00fcdanzeiger",
    "wof:placetype":"venue"
},
  "geometry": {"coordinates":[7.4957199097,51.4853019714],"type":"Point"}
}