{
  "type": "Feature",
  "properties": {
    "iso:country":"DE",
    "sg:address":"Magdeburger Str. 8",
    "sg:city":"Grasleben",
    "sg:phone":"+49 5357/254",
    "sg:postcode":"38368",
    "sg:province":"Niedersachsen",
    "wof:name":"Hans-hermann Risse",
    "wof:placetype":"venue"
},
  "geometry": {"coordinates":[11.018986702,52.3076324463],"type":"Point"}
}