{
  "type": "Feature",
  "properties": {
    "iso:country":"DE",
    "sg:address":"Falltorstr. 30",
    "sg:city":"Bergisch Gladbach",
    "sg:phone":"+49 2204/52716",
    "sg:postcode":"51429",
    "sg:province":"Nordrhein-Westfalen",
    "wof:name":"Heinz Bohn Architekt",
    "wof:placetype":"venue"
},
  "geometry": {"coordinates":[7.157931,50.963535],"type":"Point"}
}