{
  "type": "Feature",
  "properties": {
    "iso:country":"DE",
    "sg:address":"Sternstr. 2",
    "sg:city":"Liebenau",
    "sg:phone":"+49 5023/633",
    "sg:postcode":"31618",
    "sg:province":"Niedersachsen",
    "wof:name":"A. Bargemann",
    "wof:placetype":"venue"
},
  "geometry": {"coordinates":[9.0906066895,52.6065330505],"type":"Point"}
}