{
  "type": "Feature",
  "properties": {
    "iso:country":"DE",
    "sg:address":"Flurstr. 5",
    "sg:city":"Becherbach",
    "sg:phone":"+49 6757/218",
    "sg:postcode":"55608",
    "sg:province":"Rheinland-Pfalz",
    "wof:name":"Ev. Pfarramt",
    "wof:placetype":"venue"
},
  "geometry": {"coordinates":[7.4128608704,49.7802085876],"type":"Point"}
}