{
  "type": "Feature",
  "properties": {
    "iso:country":"DE",
    "sg:address":"Hermine-Maierheuser-Str. 20",
    "sg:city":"Linkenheim-Hochstetten",
    "sg:phone":"+49 7247/4547",
    "sg:postcode":"76351",
    "sg:province":"Baden-W\u00fcrttemberg",
    "wof:name":"Samuel Bayer",
    "wof:placetype":"venue"
},
  "geometry": {"coordinates":[8.4087524414,49.1297645569],"type":"Point"}
}