{
  "type": "Feature",
  "properties": {
    "iso:country":"DE",
    "sg:address":"Weidelsburgstr. 7",
    "sg:city":"Kassel",
    "sg:postcode":"34132",
    "sg:province":"Hessen",
    "wof:name":"Weidelsburg Verlag",
    "wof:placetype":"venue"
},
  "geometry": {"coordinates":[9.4482297897,51.2725639343],"type":"Point"}
}