{
  "type": "Feature",
  "properties": {
    "iso:country":"DE",
    "sg:address":"Kolpingstr. 10",
    "sg:city":"Kaufering",
    "sg:postcode":"86916",
    "sg:province":"Bayern",
    "wof:name":"Massa Ag",
    "wof:placetype":"venue"
},
  "geometry": {"coordinates":[10.856003,48.090729],"type":"Point"}
}