{
  "type": "Feature",
  "properties": {
    "iso:country":"DE",
    "sg:address":"Eduard-Adler-Str. 23b",
    "sg:city":"Kiel",
    "sg:phone":"+49 431/334381",
    "sg:postcode":"24106",
    "sg:province":"Schleswig-Holstein",
    "wof:name":"Ev. Pfarramt Ii Osterkirchengemeinde",
    "wof:placetype":"venue"
},
  "geometry": {"coordinates":[10.12840271,54.3466567993],"type":"Point"}
}