{
  "type": "Feature",
  "properties": {
    "iso:country":"DE",
    "sg:address":"S\u00fcderende 11 a",
    "sg:city":"Westerland",
    "sg:phone":"+49 4651/5185",
    "sg:postcode":"25980",
    "sg:province":"Schleswig-Holstein",
    "wof:name":"Franz Schreiber",
    "wof:placetype":"venue"
},
  "geometry": {"coordinates":[8.305941,54.896084],"type":"Point"}
}