{
  "type": "Feature",
  "properties": {
    "iso:country":"DE",
    "sg:address":"Wiesenstr. 9",
    "sg:city":"R\u00fcckeroth",
    "sg:phone":"+49 2626/140241",
    "sg:postcode":"56244",
    "sg:province":"Rheinland-Pfalz",
    "wof:name":"C\u00e4sar",
    "wof:placetype":"venue"
},
  "geometry": {"coordinates":[7.7431120872,50.5577125549],"type":"Point"}
}