{
  "type": "Feature",
  "properties": {
    "iso:country":"DE",
    "sg:address":"Skarbinastr. 80",
    "sg:city":"Berlin",
    "sg:postcode":"12309",
    "sg:province":"Berlin",
    "wof:name":"Logisco Dienstleistungs- Gesellschaft Mbh",
    "wof:placetype":"venue"
},
  "geometry": {"coordinates":[13.4225311279,52.3934288025],"type":"Point"}
}