{
  "type": "Feature",
  "properties": {
    "iso:country":"DE",
    "sg:address":"Br\u00fcckenstr. 29",
    "sg:city":"Tuttlingen",
    "sg:phone":"+49 7461/78677",
    "sg:postcode":"78532",
    "sg:province":"Baden-W\u00fcrttemberg",
    "wof:name":"Richard E. Koepf Heilpraktiker",
    "wof:placetype":"venue"
},
  "geometry": {"coordinates":[8.8145675659,47.9897232056],"type":"Point"}
}