{
  "type": "Feature",
  "properties": {
    "iso:country":"DE",
    "sg:address":"Schliemannstr. 11a",
    "sg:city":"Erkrath",
    "sg:phone":"+49 2104/44711",
    "sg:postcode":"40699",
    "sg:province":"Nordrhein-Westfalen",
    "wof:name":"Beratungsstelle F\u00fcr Lebensfragen Des Drk",
    "wof:placetype":"venue"
},
  "geometry": {"coordinates":[6.958471,51.214348],"type":"Point"}
}