{
  "type": "Feature",
  "properties": {
    "iso:country":"DE",
    "sg:address":"Haarbr\u00fccker Str. 18",
    "sg:city":"Neustadt",
    "sg:phone":"+49 9568/87789",
    "sg:postcode":"96465",
    "sg:province":"Bayern",
    "wof:name":"Roland Gundermann",
    "wof:placetype":"venue"
},
  "geometry": {"coordinates":[11.102638,50.316105],"type":"Point"}
}