{
  "type": "Feature",
  "properties": {
    "iso:country":"DE",
    "sg:address":"Semperstrasse 8",
    "sg:city":"Hamburg",
    "sg:phone":"+49 40/41350497",
    "sg:postcode":"21303",
    "sg:province":"Hamburg",
    "wof:name":"Macconnell",
    "wof:placetype":"venue"
},
  "geometry": {"coordinates":[10.0114107132,53.5840492249],"type":"Point"}
}