{
  "type": "Feature",
  "properties": {
    "iso:country":"DE",
    "sg:address":"Ulmenallee 5",
    "sg:city":"Visselh\u00f6vede",
    "sg:phone":"+49 4262/4444",
    "sg:postcode":"27374",
    "sg:province":"Niedersachsen",
    "wof:name":"Heiko Wedemeyer Fitness-studio",
    "wof:placetype":"venue"
},
  "geometry": {"coordinates":[9.5172996521,52.9676704407],"type":"Point"}
}