{
  "type": "Feature",
  "properties": {
    "iso:country":"DE",
    "sg:address":"Heusingerstr. 3",
    "sg:city":"Frankfurt",
    "sg:phone":"+49 69/392413",
    "sg:postcode":"65934",
    "sg:province":"Hessen",
    "wof:name":"Ev. Pfarramt Apostelgemeinde",
    "wof:placetype":"venue"
},
  "geometry": {"coordinates":[8.5808572769,50.1076278687],"type":"Point"}
}