{
  "type": "Feature",
  "properties": {
    "iso:country":"DE",
    "sg:address":"Treibgasse 19",
    "sg:city":"Aschaffenburg",
    "sg:postcode":"63739",
    "sg:province":"Bayern",
    "wof:name":"Morgenwelt Event Gmbh",
    "wof:placetype":"venue"
},
  "geometry": {"coordinates":[9.143294,49.976933],"type":"Point"}
}