{
  "type": "Feature",
  "properties": {
    "iso:country":"DE",
    "sg:address":"Gutenbergstr. 1",
    "sg:city":"Henstedt-Ulzburg",
    "sg:phone":"+49 4193/1810",
    "sg:postcode":"24558",
    "sg:province":"Schleswig-Holstein",
    "wof:name":"Minipreis-m\u00f6belmarkt",
    "wof:placetype":"venue"
},
  "geometry": {"coordinates":[9.982767,53.804054],"type":"Point"}
}