{
  "type": "Feature",
  "properties": {
    "iso:country":"DE",
    "sg:address":"Wallensteinstr. 28",
    "sg:city":"Ingolstadt",
    "sg:phone":"+49 841/973650",
    "sg:postcode":"85051",
    "sg:province":"Bayern",
    "wof:name":"Erich Sutner Steuerberatungsges. Mbh",
    "wof:placetype":"venue"
},
  "geometry": {"coordinates":[11.4276990891,48.7393341064],"type":"Point"}
}