{
  "type": "Feature",
  "properties": {
    "iso:country":"DE",
    "sg:address":"Taddigsh\u00f6rn 200",
    "sg:city":"Esens",
    "sg:phone":"+49 4971/4767",
    "sg:postcode":"26427",
    "sg:province":"Niedersachsen",
    "wof:name":"Meentz",
    "wof:placetype":"venue"
},
  "geometry": {"coordinates":[7.57389,53.671638],"type":"Point"}
}