{
  "type": "Feature",
  "properties": {
    "iso:country":"DE",
    "sg:address":"Industriestr. 5",
    "sg:city":"Bad Neustadt",
    "sg:phone":"+49 9771/3959",
    "sg:postcode":"97616",
    "sg:province":"Bayern",
    "wof:name":"Stefan Hein",
    "wof:placetype":"venue"
},
  "geometry": {"coordinates":[10.2218160629,50.3338241577],"type":"Point"}
}