{
  "type": "Feature",
  "properties": {
    "iso:country":"DE",
    "sg:address":"Dorfstr. 44 a",
    "sg:city":"Meerbusch",
    "sg:postcode":"40667",
    "sg:province":"Nordrhein-Westfalen",
    "wof:name":"Ballettschule Gemma",
    "wof:placetype":"venue"
},
  "geometry": {"coordinates":[6.6962537766,51.2535171509],"type":"Point"}
}