{
  "type": "Feature",
  "properties": {
    "iso:country":"DE",
    "sg:address":"B\u00fccklersstr. 15",
    "sg:city":"D\u00fcren",
    "sg:phone":"+49 2421/17379",
    "sg:postcode":"52351",
    "sg:province":"Nordrhein-Westfalen",
    "wof:name":"W. M\u00fcller Ergotherapiepraxis",
    "wof:placetype":"venue"
},
  "geometry": {"coordinates":[6.48408,50.807739],"type":"Point"}
}