{
  "type": "Feature",
  "properties": {
    "iso:country":"DE",
    "sg:address":"Hauptstr. 48",
    "sg:city":"Barsb\u00fcttel",
    "sg:phone":"+49 40/6703204",
    "sg:postcode":"22885",
    "sg:province":"Schleswig-Holstein",
    "wof:name":"Alfred Schreiber",
    "wof:placetype":"venue"
},
  "geometry": {"coordinates":[10.1680860519,53.5689582825],"type":"Point"}
}