{
  "type": "Feature",
  "properties": {
    "iso:country":"DE",
    "sg:address":"Mannheimer Str. 3",
    "sg:city":"Br\u00fchl",
    "sg:phone":"+49 6202/77959",
    "sg:postcode":"68782",
    "sg:province":"Baden-W\u00fcrttemberg",
    "wof:name":"Chinaresraurant Asia",
    "wof:placetype":"venue"
},
  "geometry": {"coordinates":[8.5342445374,49.3956336975],"type":"Point"}
}