{
  "type": "Feature",
  "properties": {
    "iso:country":"DE",
    "sg:address":"Eisenbahnstr. 4",
    "sg:city":"Frankenthal",
    "sg:phone":"+49 4962/3325061",
    "sg:postcode":"67227",
    "sg:province":"Rheinland-Pfalz",
    "wof:name":"Kreissparkasse Gr\u00fcnstadt",
    "wof:placetype":"venue"
},
  "geometry": {"coordinates":[8.350608,49.535637],"type":"Point"}
}