{
  "type": "Feature",
  "properties": {
    "iso:country":"DE",
    "sg:address":"Hauptstr. 4",
    "sg:city":"Rees",
    "sg:phone":"+49 2851/6537",
    "sg:postcode":"46459",
    "sg:province":"Nordrhein-Westfalen",
    "wof:name":"Bernhard Landers",
    "wof:placetype":"venue"
},
  "geometry": {"coordinates":[6.3939919472,51.809173584],"type":"Point"}
}