{
  "type": "Feature",
  "properties": {
    "iso:country":"DE",
    "sg:address":"Moislinger Allee 42",
    "sg:city":"L\u00fcbeck",
    "sg:phone":"+49 451/81649",
    "sg:postcode":"23558",
    "sg:province":"Schleswig-Holstein",
    "wof:name":"R. Schauseil",
    "wof:placetype":"venue"
},
  "geometry": {"coordinates":[10.671922,53.85976],"type":"Point"}
}