{
  "type": "Feature",
  "properties": {
    "iso:country":"DE",
    "sg:address":"Hauptstr. 36",
    "sg:city":"Butzbach",
    "sg:phone":"+49 6447/6524",
    "sg:postcode":"35510",
    "sg:province":"Hessen",
    "wof:name":"Biozentrum Butzbach Gmbh",
    "wof:placetype":"venue"
},
  "geometry": {"coordinates":[8.60804,50.45266],"type":"Point"}
}