{
  "type": "Feature",
  "properties": {
    "iso:country":"DE",
    "sg:address":"Nauheimer Str 40",
    "sg:city":"Stuttgart",
    "sg:phone":"+49 711/5092503",
    "sg:postcode":"70372",
    "sg:province":"Baden-W\u00fcrttemberg",
    "wof:name":"Heinz Industrial Design",
    "wof:placetype":"venue"
},
  "geometry": {"coordinates":[9.221455574,48.8070068359],"type":"Point"}
}