{
  "type": "Feature",
  "properties": {
    "iso:country":"DE",
    "sg:address":"Neuburger Str. 30",
    "sg:city":"Passau",
    "sg:phone":"+49 851/6543",
    "sg:postcode":"94032",
    "sg:province":"Bayern",
    "wof:name":"Centa Schuster",
    "wof:placetype":"venue"
},
  "geometry": {"coordinates":[13.4523124695,48.5717926025],"type":"Point"}
}