{
  "type": "Feature",
  "properties": {
    "iso:country":"DE",
    "sg:address":"Satower Str. 55 a",
    "sg:city":"Rostock",
    "sg:phone":"+49 381/4000168",
    "sg:postcode":"18059",
    "sg:province":"Mecklenburg-Vorpommern",
    "wof:name":"Medata Steuerberatungs Gmbh",
    "wof:placetype":"venue"
},
  "geometry": {"coordinates":[12.0787172318,54.0684318542],"type":"Point"}
}