{
  "type": "Feature",
  "properties": {
    "iso:country":"DE",
    "sg:address":"H\u00f6fchensweg 38",
    "sg:city":"Aachen",
    "sg:phone":"+49 241/65252",
    "sg:postcode":"52076",
    "sg:province":"Nordrhein-Westfalen",
    "wof:name":"Dr. Ing. Trapp Ingenieurs Gmbh",
    "wof:placetype":"venue"
},
  "geometry": {"coordinates":[6.0807352066,50.7501792908],"type":"Point"}
}