{
  "type": "Feature",
  "properties": {
    "iso:country":"DE",
    "sg:address":"Lindenstr. 38",
    "sg:city":"Bad Essen",
    "sg:phone":"+49 5472/5669",
    "sg:postcode":"49152",
    "sg:province":"Niedersachsen",
    "wof:name":"Dorka",
    "wof:placetype":"venue"
},
  "geometry": {"coordinates":[8.3429327011,52.3195381165],"type":"Point"}
}