{
  "type": "Feature",
  "properties": {
    "iso:country":"DE",
    "sg:address":"Zur Kapelle 1",
    "sg:city":"Ensdorf",
    "sg:phone":"+49 9624/2425",
    "sg:postcode":"92266",
    "sg:province":"Bayern",
    "wof:name":"H. T\u00f6lke-g\u00f6\u00dfl",
    "wof:placetype":"venue"
},
  "geometry": {"coordinates":[11.9416017532,49.3396148682],"type":"Point"}
}