{
  "type": "Feature",
  "properties": {
    "iso:country":"DE",
    "sg:address":"Zabenstedter Str. 42",
    "sg:city":"Gerbstedt",
    "sg:phone":"+49 34783/2470",
    "sg:postcode":"06347",
    "sg:province":"Sachsen-Anhalt",
    "wof:name":"Druckhaus Mansfelder Land Gmbh",
    "wof:placetype":"venue"
},
  "geometry": {"coordinates":[11.6366472244,51.6286735535],"type":"Point"}
}