{
  "type": "Feature",
  "properties": {
    "iso:country":"DE",
    "sg:address":"Bogenstr. 8",
    "sg:city":"Solingen",
    "sg:phone":"+49 212/267020",
    "sg:postcode":"42697",
    "sg:province":"Nordrhein-Westfalen",
    "wof:name":"Hermann-josef L\u00fcrwer Immobilien Gmbh",
    "wof:placetype":"venue"
},
  "geometry": {"coordinates":[6.9936718941,51.1630897522],"type":"Point"}
}