{
  "type": "Feature",
  "properties": {
    "iso:country":"DE",
    "sg:address":"Horst 15",
    "sg:city":"Rosendahl",
    "sg:phone":"+49 2547/934250",
    "sg:postcode":"48720",
    "sg:province":"Nordrhein-Westfalen",
    "wof:name":"Leuters-bau- Gmbh",
    "wof:placetype":"venue"
},
  "geometry": {"coordinates":[7.162084,52.029442],"type":"Point"}
}