{
  "type": "Feature",
  "properties": {
    "iso:country":"DE",
    "sg:address":"Ostpreu\u00dfenstr. 28",
    "sg:city":"Flieden",
    "sg:postcode":"36103",
    "sg:province":"Hessen",
    "wof:name":"Drimalski Beteiligungsges. Mbh",
    "wof:placetype":"venue"
},
  "geometry": {"coordinates":[9.564057,50.425747],"type":"Point"}
}