{
  "type": "Feature",
  "properties": {
    "iso:country":"DE",
    "sg:address":"Anzinger Str. 2",
    "sg:city":"Zorneding",
    "sg:phone":"+49 8106/29249",
    "sg:postcode":"85604",
    "sg:province":"Bayern",
    "wof:name":"Angela Stadler",
    "wof:placetype":"venue"
},
  "geometry": {"coordinates":[11.830786705,48.0901870728],"type":"Point"}
}