{
  "type": "Feature",
  "properties": {
    "iso:country":"DE",
    "sg:address":"M\u00fchlenweg 2",
    "sg:city":"Bad Salzschlirf",
    "sg:phone":"+49 6648/2658",
    "sg:postcode":"36364",
    "sg:province":"Hessen",
    "wof:name":"Haus Wiesenruh",
    "wof:placetype":"venue"
},
  "geometry": {"coordinates":[9.5029840469,50.6197738647],"type":"Point"}
}