{
  "type": "Feature",
  "properties": {
    "iso:country":"DE",
    "sg:address":"Nordstr. 1",
    "sg:city":"Crimmitschau",
    "sg:phone":"+49 3762/5431",
    "sg:postcode":"08451",
    "sg:province":"Sachsen",
    "wof:name":"Alfred Birnstein",
    "wof:placetype":"venue"
},
  "geometry": {"coordinates":[12.394812,50.824287],"type":"Point"}
}