{
  "type": "Feature",
  "properties": {
    "iso:country":"DE",
    "sg:address":"Alter Weg 14",
    "sg:city":"Dillenburg",
    "sg:phone":"+49 2771/829041",
    "sg:postcode":"35687",
    "sg:province":"Hessen",
    "wof:name":"P & W Reinigungssysteme Gmbh",
    "wof:placetype":"venue"
},
  "geometry": {"coordinates":[8.314009,50.723877],"type":"Point"}
}