{
  "type": "Feature",
  "properties": {
    "iso:country":"DE",
    "sg:address":"An der Schleuse",
    "sg:city":"Stahnsdorf",
    "sg:postcode":"14532",
    "sg:province":"Brandenburg",
    "wof:name":"Kaisers Verbrauchermarkt",
    "wof:placetype":"venue"
},
  "geometry": {"coordinates":[13.2216596603,52.3919143677],"type":"Point"}
}