{
  "type": "Feature",
  "properties": {
    "iso:country":"DE",
    "sg:address":"Moselstr. 18",
    "sg:city":"Burg",
    "sg:phone":"+49 6541/9214",
    "sg:postcode":"56843",
    "sg:province":"Rheinland-Pfalz",
    "wof:name":"Hotel Zur Post",
    "wof:placetype":"venue"
},
  "geometry": {"coordinates":[7.1869010925,49.9244499207],"type":"Point"}
}