{
  "type": "Feature",
  "properties": {
    "iso:country":"DE",
    "sg:address":"Inrather Str. 291",
    "sg:city":"Krefeld",
    "sg:phone":"+49 2151/753943",
    "sg:postcode":"47803",
    "sg:province":"Nordrhein-Westfalen",
    "wof:name":"Peter Brossen",
    "wof:placetype":"venue"
},
  "geometry": {"coordinates":[6.5468931198,51.3484687805],"type":"Point"}
}