{
  "type": "Feature",
  "properties": {
    "iso:country":"DE",
    "sg:address":"Hansestr. 24",
    "sg:city":"M\u00fcnster",
    "sg:phone":"+49 2501/44960",
    "sg:postcode":"48165",
    "sg:province":"Nordrhein-Westfalen",
    "wof:name":"Edc Embedded Design Center Gesellschaft Zur Entwicklung",
    "wof:placetype":"venue"
},
  "geometry": {"coordinates":[7.63374,51.893581],"type":"Point"}
}