{
  "type": "Feature",
  "properties": {
    "iso:country":"DE",
    "sg:address":"Schlo\u00dfstr. 10",
    "sg:city":"Schrozberg",
    "sg:phone":"+49 7936/990577",
    "sg:postcode":"74575",
    "sg:province":"Baden-W\u00fcrttemberg",
    "wof:name":"Eberhard Hofmann",
    "wof:placetype":"venue"
},
  "geometry": {"coordinates":[9.980195,49.34584],"type":"Point"}
}