{
  "type": "Feature",
  "properties": {
    "iso:country":"DE",
    "sg:address":"Im Dorf 26",
    "sg:city":"Erwitte",
    "sg:phone":"+49 2945/2424",
    "sg:postcode":"59597",
    "sg:province":"Nordrhein-Westfalen",
    "wof:name":"Heinrich Tochtrop",
    "wof:placetype":"venue"
},
  "geometry": {"coordinates":[8.272236,51.618279],"type":"Point"}
}