{
  "type": "Feature",
  "properties": {
    "iso:country":"DE",
    "sg:address":"Birkenweg 14",
    "sg:city":"Schl\u00fcchtern",
    "sg:phone":"+49 6661/919103",
    "sg:postcode":"36381",
    "sg:province":"Hessen",
    "wof:name":"Dr. J\u00fcrgen Stock Nachf.",
    "wof:placetype":"venue"
},
  "geometry": {"coordinates":[9.514987,50.347767],"type":"Point"}
}