{
  "type": "Feature",
  "properties": {
    "iso:country":"DE",
    "sg:address":"Freunder Landstr. 33-",
    "sg:city":"Aachen",
    "sg:postcode":"52078",
    "sg:province":"Nordrhein-Westfalen",
    "wof:name":"Herbert Plingen Gmbh",
    "wof:placetype":"venue"
},
  "geometry": {"coordinates":[6.19115,50.751629],"type":"Point"}
}