{
  "type": "Feature",
  "properties": {
    "iso:country":"DE",
    "sg:address":"Hansastr. 5",
    "sg:city":"M\u00fcnchen",
    "sg:phone":"+49 89/51739590",
    "sg:postcode":"80686",
    "sg:province":"Bayern",
    "wof:name":"Redlukas Gesellschaft Zur Veranstaltung Von Internet-",
    "wof:placetype":"venue"
},
  "geometry": {"coordinates":[11.525135994,48.1354370117],"type":"Point"}
}