{
  "type": "Feature",
  "properties": {
    "iso:country":"DE",
    "sg:address":"Lengefeldstr. 4",
    "sg:city":"Rudolstadt",
    "sg:phone":"+49 3672/412923",
    "sg:postcode":"07407",
    "sg:province":"Th\u00fcringen",
    "wof:name":"H. Christ",
    "wof:placetype":"venue"
},
  "geometry": {"coordinates":[11.3425035477,50.7229576111],"type":"Point"}
}