{
  "type": "Feature",
  "properties": {
    "iso:country":"DE",
    "sg:address":"Friedrich-Ebert-Str. 134",
    "sg:city":"Bottrop",
    "sg:phone":"+49 2041/62615",
    "sg:postcode":"46236",
    "sg:province":"Nordrhein-Westfalen",
    "wof:name":"K.-h. Keller Grabdenkm\u00e4ler",
    "wof:placetype":"venue"
},
  "geometry": {"coordinates":[6.9305567741,51.5233955383],"type":"Point"}
}