{
  "type": "Feature",
  "properties": {
    "iso:country":"DE",
    "sg:address":"Lammersdorfer Str. 69",
    "sg:city":"Roetgen",
    "sg:postcode":"52159",
    "sg:province":"Nordrhein-Westfalen",
    "wof:name":"Db Bausanierung Gmbh",
    "wof:placetype":"venue"
},
  "geometry": {"coordinates":[6.2240538597,50.6807975769],"type":"Point"}
}