{
  "type": "Feature",
  "properties": {
    "iso:country":"DE",
    "sg:address":"Rimbachweg 87",
    "sg:city":"Freudenstadt",
    "sg:phone":"+49 7442/3873",
    "sg:postcode":"72250",
    "sg:province":"Baden-W\u00fcrttemberg",
    "wof:name":"A. Welle",
    "wof:placetype":"venue"
},
  "geometry": {"coordinates":[8.3080701828,48.4661026001],"type":"Point"}
}