{
  "type": "Feature",
  "properties": {
    "iso:country":"DE",
    "sg:address":"H\u00fcnefeldzeile 6",
    "sg:city":"Berlin",
    "sg:phone":"+49 30/7747642",
    "sg:postcode":"12247",
    "sg:province":"Berlin",
    "wof:name":"Prof. Dr. Horst Eick",
    "wof:placetype":"venue"
},
  "geometry": {"coordinates":[13.3561105728,52.4472122192],"type":"Point"}
}