{
  "type": "Feature",
  "properties": {
    "iso:country":"DE",
    "sg:address":"Wilhelm-Schussen-Str. 1",
    "sg:city":"Bad Schussenried",
    "sg:phone":"+49 7583/2257",
    "sg:postcode":"88427",
    "sg:province":"Baden-W\u00fcrttemberg",
    "wof:name":"Cafe Walser",
    "wof:placetype":"venue"
},
  "geometry": {"coordinates":[9.6583852768,48.0032653809],"type":"Point"}
}