{
  "type": "Feature",
  "properties": {
    "iso:country":"DE",
    "sg:address":"Kreuzweg 25",
    "sg:city":"L\u00fcbbecke",
    "sg:phone":"+49 5741/9956",
    "sg:postcode":"32312",
    "sg:province":"Nordrhein-Westfalen",
    "wof:name":"Herbert Borchard",
    "wof:placetype":"venue"
},
  "geometry": {"coordinates":[8.5718402863,52.3153915405],"type":"Point"}
}