{
  "type": "Feature",
  "properties": {
    "iso:country":"DE",
    "sg:address":"Raiffeisenstr 7",
    "sg:city":"Ovelg\u00f6nne",
    "sg:phone":"+49 4483/1272",
    "sg:postcode":"26939",
    "sg:province":"Niedersachsen",
    "wof:name":"Raiffeisenbank Berne-moorriem Eg",
    "wof:placetype":"venue"
},
  "geometry": {"coordinates":[8.3125,53.263821],"type":"Point"}
}