{
  "type": "Feature",
  "properties": {
    "iso:country":"DE",
    "sg:address":"Kapellenstr. 5",
    "sg:city":"Telgte",
    "sg:phone":"+49 2504/4555",
    "sg:postcode":"48291",
    "sg:province":"Nordrhein-Westfalen",
    "wof:name":"W. Kaub",
    "wof:placetype":"venue"
},
  "geometry": {"coordinates":[7.7856249809,51.9847602844],"type":"Point"}
}