{
  "type": "Feature",
  "properties": {
    "iso:country":"DE",
    "sg:address":"Feldweg 21",
    "sg:city":"Herdorf",
    "sg:phone":"+49 2744/930318",
    "sg:postcode":"57562",
    "sg:province":"Rheinland-Pfalz",
    "wof:name":"Peter Christian",
    "wof:placetype":"venue"
},
  "geometry": {"coordinates":[7.959843,50.776478],"type":"Point"}
}