{
  "type": "Feature",
  "properties": {
    "iso:country":"DE",
    "sg:address":"Auf Dorheck 25",
    "sg:city":"Trier",
    "sg:phone":"+49 651/10693",
    "sg:postcode":"54292",
    "sg:province":"Rheinland-Pfalz",
    "wof:name":"Peter Zimmer",
    "wof:placetype":"venue"
},
  "geometry": {"coordinates":[6.7204818726,49.7875480652],"type":"Point"}
}