{
  "type": "Feature",
  "properties": {
    "iso:country":"DE",
    "sg:address":"Weseler Weg 32",
    "sg:city":"H\u00fcnxe",
    "sg:phone":"+49 2856/2516",
    "sg:postcode":"46569",
    "sg:province":"Nordrhein-Westfalen",
    "wof:name":"H. Hillesheim",
    "wof:placetype":"venue"
},
  "geometry": {"coordinates":[6.731653,51.696991],"type":"Point"}
}