{
  "type": "Feature",
  "properties": {
    "iso:country":"DE",
    "sg:address":"L\u00fctticher Str. 51",
    "sg:city":"K\u00f6ln",
    "sg:phone":"+49 221/523302",
    "sg:postcode":"50674",
    "sg:province":"Nordrhein-Westfalen",
    "wof:name":"Ottokar Stiasny",
    "wof:placetype":"venue"
},
  "geometry": {"coordinates":[6.934194,50.937305],"type":"Point"}
}