{
  "type": "Feature",
  "properties": {
    "iso:country":"DE",
    "sg:address":"Graf-von-Bray-Str. 14",
    "sg:city":"Irlbach",
    "sg:phone":"+49 9424/94030",
    "sg:postcode":"94342",
    "sg:province":"Bayern",
    "wof:name":"Freiherr Von Poschinger Braysche Schlo\u00dfbrauerei",
    "wof:placetype":"venue"
},
  "geometry": {"coordinates":[12.747395,48.844505],"type":"Point"}
}