{
  "type": "Feature",
  "properties": {
    "iso:country":"DE",
    "sg:address":"Gl\u00e4serstr. 25",
    "sg:city":"Weimar",
    "sg:phone":"+49 3643/83170",
    "sg:postcode":"99423",
    "sg:province":"Th\u00fcringen",
    "wof:name":"Fischer-elektro-montagen Weimar Gmbh",
    "wof:placetype":"venue"
},
  "geometry": {"coordinates":[11.332476,50.990238],"type":"Point"}
}