{
  "type": "Feature",
  "properties": {
    "iso:country":"DE",
    "sg:address":"Limburger Str. 5A",
    "sg:city":"K\u00f6nigstein",
    "sg:phone":"+49 6174/29340",
    "sg:postcode":"61462",
    "sg:province":"Hessen",
    "wof:name":"Menge & Menge Versicherungsagenturen Gbr",
    "wof:placetype":"venue"
},
  "geometry": {"coordinates":[8.4666690826,50.1849784851],"type":"Point"}
}