{
  "type": "Feature",
  "properties": {
    "iso:country":"DE",
    "sg:address":"Lindenstr. 24",
    "sg:city":"Reichenberg",
    "sg:phone":"+49 9366/451",
    "sg:postcode":"97234",
    "sg:province":"Bayern",
    "wof:name":"Richard Schmidt",
    "wof:placetype":"venue"
},
  "geometry": {"coordinates":[9.929043,49.710617],"type":"Point"}
}