{
  "type": "Feature",
  "properties": {
    "iso:country":"DE",
    "sg:address":"Oehleckerring 6a",
    "sg:city":"Hamburg",
    "sg:phone":"+49 40/5314081",
    "sg:postcode":"22419",
    "sg:province":"Hamburg",
    "wof:name":"Ees J\u00fcrgen Scholz Gmbh",
    "wof:placetype":"venue"
},
  "geometry": {"coordinates":[10.0059499741,53.660785675],"type":"Point"}
}