{
  "type": "Feature",
  "properties": {
    "iso:country":"DE",
    "sg:address":"Gluckstr. 53 a",
    "sg:city":"Hamburg",
    "sg:postcode":"22081",
    "sg:province":"Hamburg",
    "wof:name":"Uthbronee Industriefu\u00dfb\u00f6den Gmbh",
    "wof:placetype":"venue"
},
  "geometry": {"coordinates":[10.0458469391,53.5739097595],"type":"Point"}
}