{
  "type": "Feature",
  "properties": {
    "iso:country":"DE",
    "sg:address":"Johanna-Kirchner-Str. 2",
    "sg:city":"Hildesheim",
    "sg:phone":"+49 5121/44846",
    "sg:postcode":"31139",
    "sg:province":"Niedersachsen",
    "wof:name":"Wolfgang Brunotte Architekt",
    "wof:placetype":"venue"
},
  "geometry": {"coordinates":[9.919413,52.141068],"type":"Point"}
}