{
  "type": "Feature",
  "properties": {
    "iso:country":"DE",
    "sg:address":"Muschelquellenweg 4",
    "sg:city":"Wiesenttal",
    "sg:phone":"+49 9196/232",
    "sg:postcode":"91346",
    "sg:province":"Bayern",
    "wof:name":"Ev. Luth. Pfarramt",
    "wof:placetype":"venue"
},
  "geometry": {"coordinates":[11.2227010727,49.8123550415],"type":"Point"}
}