{
  "type": "Feature",
  "properties": {
    "iso:country":"DE",
    "sg:address":"Albanusstr. 7",
    "sg:city":"Frankfurt",
    "sg:phone":"+49 69/333208",
    "sg:postcode":"65929",
    "sg:province":"Hessen",
    "wof:name":"Gastst\u00e4tte Stadt Limburg",
    "wof:placetype":"venue"
},
  "geometry": {"coordinates":[8.5477190018,50.0999794006],"type":"Point"}
}