{
  "type": "Feature",
  "properties": {
    "iso:country":"DE",
    "sg:address":"Willi-Bleicher-Str. 2",
    "sg:city":"D\u00fcren",
    "sg:postcode":"52353",
    "sg:province":"Nordrhein-Westfalen",
    "wof:name":"Sak\u00f6 Produkt Gmbh",
    "wof:placetype":"venue"
},
  "geometry": {"coordinates":[6.472199,50.831657],"type":"Point"}
}