{
  "type": "Feature",
  "properties": {
    "iso:country":"DE",
    "sg:address":"Fischem\u00e4kerstr. 9",
    "sg:city":"Goslar",
    "sg:phone":"+49 5321/1202",
    "sg:postcode":"38640",
    "sg:province":"Niedersachsen",
    "wof:name":"Recai Karadeniz",
    "wof:placetype":"venue"
},
  "geometry": {"coordinates":[10.427986145,51.9072990417],"type":"Point"}
}