{
  "type": "Feature",
  "properties": {
    "iso:country":"DE",
    "sg:address":"Bergh\u00e4user Str. 12",
    "sg:city":"Recklinghausen",
    "sg:postcode":"45659",
    "sg:province":"Nordrhein-Westfalen",
    "wof:name":"Centuri Automatenaufstellungs- Und",
    "wof:placetype":"venue"
},
  "geometry": {"coordinates":[7.2291898727,51.5907516479],"type":"Point"}
}