{
  "type": "Feature",
  "properties": {
    "iso:country":"DE",
    "sg:address":"Marschner Str. 14",
    "sg:city":"Berlin",
    "sg:phone":"+49 4930/7911041",
    "sg:postcode":"12203",
    "sg:province":"Berlin",
    "wof:name":"Funkturm Verlag Musik Service Gmbh",
    "wof:placetype":"venue"
},
  "geometry": {"coordinates":[13.3167419434,52.4460487366],"type":"Point"}
}