{
  "type": "Feature",
  "properties": {
    "iso:country":"DE",
    "sg:address":"S\u00fcrther Str. 76",
    "sg:city":"K\u00f6ln",
    "sg:phone":"+49 221/353224",
    "sg:postcode":"50996",
    "sg:province":"Nordrhein-Westfalen",
    "wof:name":"Ferdl R\u00f6der",
    "wof:placetype":"venue"
},
  "geometry": {"coordinates":[6.99834,50.885101],"type":"Point"}
}