{
  "type": "Feature",
  "properties": {
    "iso:country":"DE",
    "sg:address":"Bestenseer Str. 1",
    "sg:city":"Gallun",
    "sg:phone":"+49 33764/22260",
    "sg:postcode":"15749",
    "sg:province":"Brandenburg",
    "wof:name":"Eckert & Wellmann Anlagentechnik Gmbh",
    "wof:placetype":"venue"
},
  "geometry": {"coordinates":[13.565564,52.247829],"type":"Point"}
}