{
  "type": "Feature",
  "properties": {
    "iso:country":"DE",
    "sg:address":"Donauw\u00f6rther Str. 42",
    "sg:city":"Augsburg",
    "sg:phone":"+49 821/414076",
    "sg:postcode":"86154",
    "sg:province":"Bayern",
    "wof:name":"Dr. Cramers Apotheke",
    "wof:placetype":"venue"
},
  "geometry": {"coordinates":[10.880625,48.383377],"type":"Point"}
}