{
  "type": "Feature",
  "properties": {
    "iso:country":"DE",
    "sg:address":"Gr\u00fcnwalder Str. 257",
    "sg:city":"M\u00fcnchen",
    "sg:phone":"+49 89/645888",
    "sg:postcode":"81545",
    "sg:province":"Bayern",
    "wof:name":"Helmut Meyer Kameramann",
    "wof:placetype":"venue"
},
  "geometry": {"coordinates":[11.5576410294,48.0905342102],"type":"Point"}
}