{
  "type": "Feature",
  "properties": {
    "iso:country":"DE",
    "sg:address":"Malchiner Str. 7",
    "sg:city":"Berlin",
    "sg:phone":"+49 30/6078510",
    "sg:postcode":"12359",
    "sg:province":"Berlin",
    "wof:name":"Bruno Fiedler",
    "wof:placetype":"venue"
},
  "geometry": {"coordinates":[13.452838,52.447659],"type":"Point"}
}