{
  "type": "Feature",
  "properties": {
    "iso:country":"DE",
    "sg:address":"Heilberg 5",
    "sg:city":"B\u00fchlerzell",
    "sg:phone":"+49 7974/367",
    "sg:postcode":"74426",
    "sg:province":"Baden-W\u00fcrttemberg",
    "wof:name":"Hans Siller",
    "wof:placetype":"venue"
},
  "geometry": {"coordinates":[9.918802,49.002441],"type":"Point"}
}