{
  "type": "Feature",
  "properties": {
    "iso:country":"DE",
    "sg:address":"Georgstr. 13",
    "sg:city":"Ravensburg",
    "sg:phone":"+49 751/25289",
    "sg:postcode":"88214",
    "sg:province":"Baden-W\u00fcrttemberg",
    "wof:name":"Esso Deutschland Gmbh",
    "wof:placetype":"venue"
},
  "geometry": {"coordinates":[9.6066799164,47.7827072144],"type":"Point"}
}