{
  "type": "Feature",
  "properties": {
    "iso:country":"DE",
    "sg:address":"J\u00fclicher Str. 66",
    "sg:city":"Aachen",
    "sg:phone":"+49 241/508332",
    "sg:postcode":"52070",
    "sg:province":"Nordrhein-Westfalen",
    "wof:name":"Jakob Gerets",
    "wof:placetype":"venue"
},
  "geometry": {"coordinates":[6.100022,50.779549],"type":"Point"}
}