{
  "type": "Feature",
  "properties": {
    "iso:country":"DE",
    "sg:address":"Boschstr. 3",
    "sg:city":"Ober-M\u00f6rlen",
    "sg:phone":"+49 6002/91100",
    "sg:postcode":"61239",
    "sg:province":"Hessen",
    "wof:name":"P.s.d. Recon Power Storage",
    "wof:placetype":"venue"
},
  "geometry": {"coordinates":[8.6878023148,50.3651428223],"type":"Point"}
}