{
  "type": "Feature",
  "properties": {
    "iso:country":"DE",
    "sg:address":"Schlo\u00dfgasse 5",
    "sg:city":"Waiblingen",
    "sg:phone":"+49 7146/43203",
    "sg:postcode":"71336",
    "sg:province":"Baden-W\u00fcrttemberg",
    "wof:name":"Jochen Jordan Masseur",
    "wof:placetype":"venue"
},
  "geometry": {"coordinates":[9.313991,48.889626],"type":"Point"}
}