{
  "type": "Feature",
  "properties": {
    "iso:country":"DE",
    "sg:address":"Meppener Str. 19",
    "sg:city":"Geeste",
    "sg:phone":"+49 5907/8295",
    "sg:postcode":"49744",
    "sg:province":"Niedersachsen",
    "wof:name":"Weser-ems Union Eg",
    "wof:placetype":"venue"
},
  "geometry": {"coordinates":[7.234206,52.594414],"type":"Point"}
}