{
  "type": "Feature",
  "properties": {
    "iso:country":"DE",
    "sg:address":"Johannettental",
    "sg:city":"Detmold",
    "sg:postcode":"32760",
    "sg:province":"Nordrhein-Westfalen",
    "wof:name":"Behindertenwerkstatt",
    "wof:placetype":"venue"
},
  "geometry": {"coordinates":[8.890685,51.927029],"type":"Point"}
}