{
  "type": "Feature",
  "properties": {
    "iso:country":"DE",
    "sg:address":"Gro\u00dfe Str. 10",
    "sg:city":"F\u00fcrstenau",
    "sg:phone":"+49 5901/2171",
    "sg:postcode":"49584",
    "sg:province":"Niedersachsen",
    "wof:name":"M. Kohkemper",
    "wof:placetype":"venue"
},
  "geometry": {"coordinates":[7.675547,52.516762],"type":"Point"}
}