{
  "type": "Feature",
  "properties": {
    "iso:country":"DE",
    "sg:address":"Im Meckelesch 2",
    "sg:city":"Bissendorf",
    "sg:postcode":"49143",
    "sg:province":"Niedersachsen",
    "wof:name":"Gustav Meyer Zu Ortbergen",
    "wof:placetype":"venue"
},
  "geometry": {"coordinates":[8.184472,52.275463],"type":"Point"}
}