{
  "type": "Feature",
  "properties": {
    "iso:country":"DE",
    "sg:address":"Marienstr. 30",
    "sg:city":"R\u00f6fingen",
    "sg:phone":"+49 8222/6123",
    "sg:postcode":"89365",
    "sg:province":"Bayern",
    "wof:name":"Gerhard Winkler Steuerberater",
    "wof:placetype":"venue"
},
  "geometry": {"coordinates":[10.4463396072,48.4219741821],"type":"Point"}
}