{
  "type": "Feature",
  "properties": {
    "iso:country":"DE",
    "sg:address":"Fasanenweg 7",
    "sg:city":"Oberboihingen",
    "sg:phone":"+49 7022/62477",
    "sg:postcode":"72644",
    "sg:province":"Baden-W\u00fcrttemberg",
    "wof:name":"G\u00fcnther Schmitt Ingenieurb\u00fcro",
    "wof:placetype":"venue"
},
  "geometry": {"coordinates":[9.3678178787,48.6567001343],"type":"Point"}
}