{
  "type": "Feature",
  "properties": {
    "iso:country":"DE",
    "sg:address":"Lindenstr. 39b",
    "sg:city":"Borgsdorf",
    "sg:phone":"+49 3303/505756",
    "sg:postcode":"16556",
    "sg:province":"Brandenburg",
    "wof:name":"Iba Lift Components Gmbh",
    "wof:placetype":"venue"
},
  "geometry": {"coordinates":[13.2582015991,52.7082595825],"type":"Point"}
}