{
  "type": "Feature",
  "properties": {
    "iso:country":"DE",
    "sg:address":"M\u00fcnchberger Str. 8",
    "sg:city":"Regensburg",
    "sg:phone":"+49 941/63793",
    "sg:postcode":"93057",
    "sg:province":"Bayern",
    "wof:name":"Dhd Donau Holz & Draht Gmbh",
    "wof:placetype":"venue"
},
  "geometry": {"coordinates":[12.128977,49.058239],"type":"Point"}
}