{
  "type": "Feature",
  "properties": {
    "iso:country":"DE",
    "sg:address":"Rieter Str. 26",
    "sg:city":"Vaihingen",
    "sg:phone":"+49 7042/14706",
    "sg:postcode":"71665",
    "sg:province":"Baden-W\u00fcrttemberg",
    "wof:name":"Roland Flurer",
    "wof:placetype":"venue"
},
  "geometry": {"coordinates":[8.9821996689,48.9166946411],"type":"Point"}
}