{
  "type": "Feature",
  "properties": {
    "iso:country":"DE",
    "sg:address":"Fritz-Wendt-Str. 5",
    "sg:city":"Meerbusch",
    "sg:phone":"+49 2159/96800",
    "sg:postcode":"40670",
    "sg:province":"Nordrhein-Westfalen",
    "wof:name":"Ssl - Support Service Logistik Gmbh",
    "wof:placetype":"venue"
},
  "geometry": {"coordinates":[6.643272,51.283775],"type":"Point"}
}