{
  "type": "Feature",
  "properties": {
    "iso:country":"DE",
    "sg:address":"Herrenm\u00fchlenstr. 32",
    "sg:city":"Eisenach",
    "sg:postcode":"99817",
    "sg:province":"Th\u00fcringen",
    "wof:name":"Unitec Dr. Militzer Maschinenbau Gmbh & Co.",
    "wof:placetype":"venue"
},
  "geometry": {"coordinates":[10.30139,50.98143],"type":"Point"}
}