{
  "type": "Feature",
  "properties": {
    "iso:country":"DE",
    "sg:address":"Bebelstr. 47",
    "sg:city":"G\u00f6ttingen",
    "sg:phone":"+49 551/68136",
    "sg:postcode":"37081",
    "sg:province":"Niedersachsen",
    "wof:name":"Callios - Call Internet Operation Systems",
    "wof:placetype":"venue"
},
  "geometry": {"coordinates":[9.91391,51.53997],"type":"Point"}
}