{
  "type": "Feature",
  "properties": {
    "iso:country":"DE",
    "sg:address":"Shadow 2",
    "sg:city":"Hunters",
    "sg:postcode":"54668",
    "sg:province":"Rheinland-Pfalz",
    "wof:name":"Shadow Hunters",
    "wof:placetype":"venue"
},
  "geometry": {"coordinates":[-74.039688,42.203674],"type":"Point"}
}