{
  "type": "Feature",
  "properties": {
    "iso:country":"DE",
    "sg:address":"Finkenweg 6",
    "sg:city":"G\u00f6ttingen",
    "sg:phone":"+49 551/91015",
    "sg:postcode":"37081",
    "sg:province":"Niedersachsen",
    "wof:name":"Online-shop Kreativparadies",
    "wof:placetype":"venue"
},
  "geometry": {"coordinates":[9.89983,51.536274],"type":"Point"}
}