{
  "type": "Feature",
  "properties": {
    "iso:country":"DE",
    "sg:address":"Bismarckstr. 12a",
    "sg:city":"Weinheim",
    "sg:phone":"+49 6201/961005",
    "sg:postcode":"69469",
    "sg:province":"Baden-W\u00fcrttemberg",
    "wof:name":"Arta Bautr\u00e4ger- Und Entwicklungsgesellschaft Mbh",
    "wof:placetype":"venue"
},
  "geometry": {"coordinates":[8.670563,49.552425],"type":"Point"}
}