{
  "type": "Feature",
  "properties": {
    "iso:country":"DE",
    "sg:address":"Leitenstr. 40",
    "sg:city":"Geretsried",
    "sg:phone":"+49 8171/909535",
    "sg:postcode":"82538",
    "sg:province":"Bayern",
    "wof:name":"Hartmut P\u00f6stges",
    "wof:placetype":"venue"
},
  "geometry": {"coordinates":[11.4395256042,47.8887557983],"type":"Point"}
}