{
  "type": "Feature",
  "properties": {
    "iso:country":"DE",
    "sg:address":"L\u00fcneburger Str. 3",
    "sg:city":"Laatzen",
    "sg:postcode":"30880",
    "sg:province":"Niedersachsen",
    "wof:name":"Metro",
    "wof:placetype":"venue"
},
  "geometry": {"coordinates":[9.8256120682,52.2965545654],"type":"Point"}
}