{
  "type": "Feature",
  "properties": {
    "iso:country":"DE",
    "sg:address":"Friesische Str. 54",
    "sg:city":"Flensburg",
    "sg:phone":"+49 461/57857",
    "sg:postcode":"24937",
    "sg:province":"Schleswig-Holstein",
    "wof:name":"Hanna Juhrke",
    "wof:placetype":"venue"
},
  "geometry": {"coordinates":[9.4285230637,54.7816963196],"type":"Point"}
}