{
  "type": "Feature",
  "properties": {
    "iso:country":"DE",
    "sg:address":"Sch\u00f6nauer Bach 15",
    "sg:city":"Aachen",
    "sg:phone":"+49 241/876610",
    "sg:postcode":"52072",
    "sg:province":"Nordrhein-Westfalen",
    "wof:name":"Eis Gesellschaft F\u00fcr Information Consultung",
    "wof:placetype":"venue"
},
  "geometry": {"coordinates":[6.0658578873,50.8136291504],"type":"Point"}
}