{
  "type": "Feature",
  "properties": {
    "iso:country":"DE",
    "sg:address":"Eisenbahnstr. 38",
    "sg:city":"Saarbr\u00fccken",
    "sg:phone":"+49 681/55580",
    "sg:postcode":"66117",
    "sg:province":"Saarland",
    "wof:name":"M\u00fcller-bruverius Rechtsanw\u00e4lte",
    "wof:placetype":"venue"
},
  "geometry": {"coordinates":[6.9888348579,49.2341308594],"type":"Point"}
}