{
  "type": "Feature",
  "properties": {
    "iso:country":"DE",
    "sg:address":"Weilburger Str. 1 a",
    "sg:city":"Driedorf",
    "sg:phone":"+49 2775/7665",
    "sg:postcode":"35759",
    "sg:province":"Hessen",
    "wof:name":"Angela Mederer",
    "wof:placetype":"venue"
},
  "geometry": {"coordinates":[8.1864757538,50.6336212158],"type":"Point"}
}