{
  "type": "Feature",
  "properties": {
    "iso:country":"DE",
    "sg:address":"Eberle-K\u00f6gl-Str. 16",
    "sg:city":"Marktoberdorf",
    "sg:phone":"+49 8342/2201",
    "sg:postcode":"87616",
    "sg:province":"Bayern",
    "wof:name":"Schlo\u00df-apotheke",
    "wof:placetype":"venue"
},
  "geometry": {"coordinates":[10.620563,47.7785],"type":"Point"}
}