{
  "type": "Feature",
  "properties": {
    "iso:country":"DE",
    "sg:address":"Tegelbusch 21 a",
    "sg:city":"Rastede",
    "sg:phone":"+49 4402/2358",
    "sg:postcode":"26180",
    "sg:province":"Niedersachsen",
    "wof:name":"Walter L\u00fcbs",
    "wof:placetype":"venue"
},
  "geometry": {"coordinates":[8.199124,53.256207],"type":"Point"}
}