{
  "type": "Feature",
  "properties": {
    "iso:country":"DE",
    "sg:address":"Franziskanergasse 3",
    "sg:city":"Esslingen",
    "sg:phone":"+49 711/3995110",
    "sg:postcode":"73728",
    "sg:province":"Baden-W\u00fcrttemberg",
    "wof:name":"Landesgirokasse \u00f6ffentliche Bank",
    "wof:placetype":"venue"
},
  "geometry": {"coordinates":[9.310778,48.741173],"type":"Point"}
}