{
  "type": "Feature",
  "properties": {
    "iso:country":"DE",
    "sg:address":"Wellingsb\u00fcttler Weg 21",
    "sg:city":"Hamburg",
    "sg:postcode":"22391",
    "sg:province":"Hamburg",
    "wof:name":"Aqua Blue Bereederung Verwaltungsges. Mbh",
    "wof:placetype":"venue"
},
  "geometry": {"coordinates":[10.061372,53.63792],"type":"Point"}
}