{
  "type": "Feature",
  "properties": {
    "iso:country":"DE",
    "sg:address":"Gwinnerstr. 27",
    "sg:city":"Frankfurt",
    "sg:phone":"+49 69/40110",
    "sg:postcode":"60388",
    "sg:province":"Hessen",
    "wof:name":"Lurgi Gmbh Forschungslaboratorium",
    "wof:placetype":"venue"
},
  "geometry": {"coordinates":[8.7364730835,50.1390762329],"type":"Point"}
}