{
  "type": "Feature",
  "properties": {
    "iso:country":"DE",
    "sg:address":"Liebigstr. 1",
    "sg:city":"Karlsfeld",
    "sg:postcode":"85757",
    "sg:province":"Bayern",
    "wof:name":"Fkr Friedhelm Kreuels Regel- Technik Verwaltungs Gmbh",
    "wof:placetype":"venue"
},
  "geometry": {"coordinates":[11.4841213226,48.2297019958],"type":"Point"}
}