{
  "type": "Feature",
  "properties": {
    "iso:country":"DE",
    "sg:address":"Rathausplatz 9",
    "sg:city":"Hohenahr",
    "sg:phone":"+49 6446/597",
    "sg:postcode":"35644",
    "sg:province":"Hessen",
    "wof:name":"Eugen Herrmann Kg Tischlerei",
    "wof:placetype":"venue"
},
  "geometry": {"coordinates":[8.524982,50.674568],"type":"Point"}
}