{
  "type": "Feature",
  "properties": {
    "iso:country":"DE",
    "sg:address":"Albstr. 9",
    "sg:city":"Reutlingen",
    "sg:phone":"+49 7121/337801",
    "sg:postcode":"72764",
    "sg:province":"Baden-W\u00fcrttemberg",
    "wof:name":"Kunsthaus Waimer",
    "wof:placetype":"venue"
},
  "geometry": {"coordinates":[9.217374,48.489964],"type":"Point"}
}