{
  "type": "Feature",
  "properties": {
    "iso:country":"DE",
    "sg:address":"Bahnhofstr. 22",
    "sg:city":"Beverungen",
    "sg:phone":"+49 5273/35666",
    "sg:postcode":"37688",
    "sg:province":"Nordrhein-Westfalen",
    "wof:name":"Elmar Kanand Elektroinstallation",
    "wof:placetype":"venue"
},
  "geometry": {"coordinates":[9.374831,51.668152],"type":"Point"}
}