{
  "type": "Feature",
  "properties": {
    "iso:country":"DE",
    "sg:address":"Kappenberger Damm 8",
    "sg:city":"M\u00fcnster",
    "sg:phone":"+49 251/73925",
    "sg:postcode":"48151",
    "sg:province":"Nordrhein-Westfalen",
    "wof:name":"Kappenberg-apotheke",
    "wof:placetype":"venue"
},
  "geometry": {"coordinates":[7.609487,51.940434],"type":"Point"}
}