{
  "type": "Feature",
  "properties": {
    "iso:country":"DE",
    "sg:address":"Stra\u00dfe der Gemeinschaft 12",
    "sg:city":"Kamenz",
    "sg:phone":"+49 35783/04596",
    "sg:postcode":"01917",
    "sg:province":"Sachsen",
    "wof:name":"Thomas Hahne",
    "wof:placetype":"venue"
},
  "geometry": {"coordinates":[14.1177148819,51.2548789978],"type":"Point"}
}