{
  "type": "Feature",
  "properties": {
    "iso:country":"DE",
    "sg:address":"Speyerer Str. 52",
    "sg:city":"Frankenthal",
    "sg:phone":"+49 6233/20126",
    "sg:postcode":"67227",
    "sg:province":"Rheinland-Pfalz",
    "wof:name":"Klatsch",
    "wof:placetype":"venue"
},
  "geometry": {"coordinates":[8.3539333344,49.532245636],"type":"Point"}
}