{
  "type": "Feature",
  "properties": {
    "iso:country":"DE",
    "sg:address":"Schulstr. 20",
    "sg:city":"Weil der Stadt",
    "sg:phone":"+49 7033/31359",
    "sg:postcode":"71263",
    "sg:province":"Baden-W\u00fcrttemberg",
    "wof:name":"Heinz Wahl Architekt",
    "wof:placetype":"venue"
},
  "geometry": {"coordinates":[8.81556,48.776318],"type":"Point"}
}