{
  "type": "Feature",
  "properties": {
    "iso:country":"DE",
    "sg:address":"Friedrichsdorfer Landstr. 8/1",
    "sg:city":"Eberbach",
    "sg:phone":"+49 6271/1219",
    "sg:postcode":"69412",
    "sg:province":"Baden-W\u00fcrttemberg",
    "wof:name":"Wilfried Erban Grabdenkm\u00e4ler",
    "wof:placetype":"venue"
},
  "geometry": {"coordinates":[8.9907131195,49.46717453],"type":"Point"}
}