{
  "type": "Feature",
  "properties": {
    "iso:country":"DE",
    "sg:address":"Waxweiler Str. 28",
    "sg:city":"Rittersdorf",
    "sg:phone":"+49 6561/5386",
    "sg:postcode":"54636",
    "sg:province":"Rheinland-Pfalz",
    "wof:name":"Nik. Hommertgen",
    "wof:placetype":"venue"
},
  "geometry": {"coordinates":[6.491134,49.999947],"type":"Point"}
}