{
  "type": "Feature",
  "properties": {
    "iso:country":"DE",
    "sg:address":"Blumenstr. 10",
    "sg:city":"Kirchheim",
    "sg:phone":"+49 7021/58271",
    "sg:postcode":"73230",
    "sg:province":"Baden-W\u00fcrttemberg",
    "wof:name":"G. K\u00fcstermann",
    "wof:placetype":"venue"
},
  "geometry": {"coordinates":[12.7780780792,48.045009613],"type":"Point"}
}