{
  "type": "Feature",
  "properties": {
    "iso:country":"DE",
    "sg:address":"Eggerstalstr. 9",
    "sg:city":"Otterbach",
    "sg:phone":"+49 6301/33213",
    "sg:postcode":"67731",
    "sg:province":"Rheinland-Pfalz",
    "wof:name":"G\u00fcnter Brandst\u00e4dter Architekt",
    "wof:placetype":"venue"
},
  "geometry": {"coordinates":[7.735262,49.4809],"type":"Point"}
}