{
  "type": "Feature",
  "properties": {
    "iso:country":"DE",
    "sg:address":"Kiesseestr. 2",
    "sg:city":"Neubrandenburg",
    "sg:postcode":"17036",
    "sg:province":"Mecklenburg-Vorpommern",
    "wof:name":"Ingenieurb\u00fcro F\u00fcr Bauplanung",
    "wof:placetype":"venue"
},
  "geometry": {"coordinates":[13.3157444,53.5366287231],"type":"Point"}
}