{
  "type": "Feature",
  "properties": {
    "iso:country":"DE",
    "sg:address":"Mittelstr. 3",
    "sg:city":"B\u00fcsum",
    "sg:phone":"+49 4834/1315",
    "sg:postcode":"25761",
    "sg:province":"Schleswig-Holstein",
    "wof:name":"Hans-hermann L\u00fcth",
    "wof:placetype":"venue"
},
  "geometry": {"coordinates":[8.859735,54.128963],"type":"Point"}
}