{
  "type": "Feature",
  "properties": {
    "iso:country":"DE",
    "sg:city":"Prutting",
    "sg:phone":"+49 8036/2362",
    "sg:postcode":"83134",
    "sg:province":"Bayern",
    "wof:name":"M\u00e4chl",
    "wof:placetype":"venue"
},
  "geometry": {"coordinates":[12.201728,47.89267],"type":"Point"}
}