{
  "type": "Feature",
  "properties": {
    "iso:country":"DE",
    "sg:address":"Untere Vorstadtstr. 6",
    "sg:city":"Walld\u00fcrn",
    "sg:phone":"+49 6282/304",
    "sg:postcode":"74731",
    "sg:province":"Baden-W\u00fcrttemberg",
    "wof:name":"H. Paul",
    "wof:placetype":"venue"
},
  "geometry": {"coordinates":[9.368703,49.58231],"type":"Point"}
}