{
  "type": "Feature",
  "properties": {
    "iso:country":"DE",
    "sg:address":"Liebigstr. 19",
    "sg:city":"D\u00fcsseldorf",
    "sg:phone":"+49 211/441244",
    "sg:postcode":"40479",
    "sg:province":"Nordrhein-Westfalen",
    "wof:name":"Johannes Haines Architekt",
    "wof:placetype":"venue"
},
  "geometry": {"coordinates":[6.792198,51.23703],"type":"Point"}
}