{
  "type": "Feature",
  "properties": {
    "iso:country":"DE",
    "sg:address":"Schulstr. 2",
    "sg:city":"Donaueschingen",
    "sg:phone":"+49 771/5199",
    "sg:postcode":"78166",
    "sg:province":"Baden-W\u00fcrttemberg",
    "wof:name":"Danubia Revisions- Treuhand Gmbh",
    "wof:placetype":"venue"
},
  "geometry": {"coordinates":[8.4994478226,47.953540802],"type":"Point"}
}