{
  "type": "Feature",
  "properties": {
    "iso:country":"DE",
    "sg:address":"Ruhlaer Str. 128",
    "sg:city":"Wutha-Farnroda",
    "sg:postcode":"99848",
    "sg:province":"Th\u00fcringen",
    "wof:name":"Elektrodienst",
    "wof:placetype":"venue"
},
  "geometry": {"coordinates":[10.39157,50.941132],"type":"Point"}
}