{
  "type": "Feature",
  "properties": {
    "iso:country":"DE",
    "sg:address":"Adolf-Scholz-Allee 10",
    "sg:city":"Bad W\u00f6rishofen",
    "sg:phone":"+49 8247/30520",
    "sg:postcode":"86825",
    "sg:province":"Bayern",
    "wof:name":"We Eigenheim Gmbh Wohnbau Kg",
    "wof:placetype":"venue"
},
  "geometry": {"coordinates":[10.590836,48.008717],"type":"Point"}
}