{
  "type": "Feature",
  "properties": {
    "iso:country":"DE",
    "sg:address":"\u00d6lspielstr. 19",
    "sg:city":"Sommerhausen",
    "sg:phone":"+49 9333/1258",
    "sg:postcode":"97286",
    "sg:province":"Bayern",
    "wof:name":"Pension N. Und L. Ruckert",
    "wof:placetype":"venue"
},
  "geometry": {"coordinates":[10.0276002884,49.7059364319],"type":"Point"}
}