{
  "type": "Feature",
  "properties": {
    "iso:country":"DE",
    "sg:address":"Florastr. 19",
    "sg:city":"Berlin",
    "sg:phone":"+49 30/7923096",
    "sg:postcode":"12163",
    "sg:province":"Berlin",
    "wof:name":"Voigtl\u00e4nder Av B\u00fcromaschinen Alfred Voigtl\u00e4nder",
    "wof:placetype":"venue"
},
  "geometry": {"coordinates":[13.3265743256,52.4615402222],"type":"Point"}
}