{
  "type": "Feature",
  "properties": {
    "iso:country":"DE",
    "sg:address":"Kiebitzdeich 196",
    "sg:city":"Hamburg",
    "sg:phone":"+49 40/7235412",
    "sg:postcode":"21037",
    "sg:province":"Hamburg",
    "wof:name":"Hermann Gutstein",
    "wof:placetype":"venue"
},
  "geometry": {"coordinates":[10.234207,53.411503],"type":"Point"}
}