{
  "type": "Feature",
  "properties": {
    "iso:country":"DE",
    "sg:address":"Bruecksief 9",
    "sg:city":"Schleiden",
    "sg:postcode":"53937",
    "sg:province":"Nordrhein-Westfalen",
    "wof:name":"Geruestbau Fedder !",
    "wof:placetype":"venue"
},
  "geometry": {"coordinates":[6.4626917839,50.5559463501],"type":"Point"}
}