{
  "type": "Feature",
  "properties": {
    "iso:country":"DE",
    "sg:address":"Wolmirstedter Str. 6",
    "sg:city":"Glindenberg",
    "sg:phone":"+49 39201/22888",
    "sg:postcode":"39326",
    "sg:province":"Sachsen-Anhalt",
    "wof:name":"Mhd Meinhardt Hausbau Gmbh",
    "wof:placetype":"venue"
},
  "geometry": {"coordinates":[11.675778,52.24369],"type":"Point"}
}