{
  "type": "Feature",
  "properties": {
    "iso:country":"DE",
    "sg:address":"Ottostr. 71",
    "sg:city":"Ottobrunn",
    "sg:phone":"+49 89/6083420",
    "sg:postcode":"85521",
    "sg:province":"Bayern",
    "wof:name":"Ld Gmbh",
    "wof:placetype":"venue"
},
  "geometry": {"coordinates":[11.676664,48.06218],"type":"Point"}
}