{
  "type": "Feature",
  "properties": {
    "iso:country":"DE",
    "sg:address":"Geschwister-Scholl-Str. 26",
    "sg:city":"Sulingen",
    "sg:phone":"+49 4271/952857",
    "sg:postcode":"27232",
    "sg:province":"Niedersachsen",
    "wof:name":"Ingenieurbau Gnuschke Gmbh",
    "wof:placetype":"venue"
},
  "geometry": {"coordinates":[8.8158779144,52.6766395569],"type":"Point"}
}