{
  "type": "Feature",
  "properties": {
    "iso:country":"DE",
    "sg:address":"Goschenstr. 37",
    "sg:city":"Hildesheim",
    "sg:phone":"+49 5121/17990",
    "sg:postcode":"31134",
    "sg:province":"Niedersachsen",
    "wof:name":"Jolo Data",
    "wof:placetype":"venue"
},
  "geometry": {"coordinates":[9.9590358734,52.1468582153],"type":"Point"}
}