{
  "type": "Feature",
  "properties": {
    "iso:country":"DE",
    "sg:address":"Osdorfer Landstr. 15",
    "sg:city":"Hamburg",
    "sg:phone":"+49 40/823057",
    "sg:postcode":"22607",
    "sg:province":"Hamburg",
    "wof:name":"J\u00fcrgen Kagerah Steuerberater",
    "wof:placetype":"venue"
},
  "geometry": {"coordinates":[9.8733758926,53.5709114075],"type":"Point"}
}