{
  "type": "Feature",
  "properties": {
    "iso:country":"DE",
    "sg:address":"Leibstr. 9",
    "sg:city":"Haar",
    "sg:phone":"+49 89/469011",
    "sg:postcode":"85540",
    "sg:province":"Bayern",
    "wof:name":"F. Und L. Fischbach",
    "wof:placetype":"venue"
},
  "geometry": {"coordinates":[11.7319517136,48.1084785461],"type":"Point"}
}