{
  "type": "Feature",
  "properties": {
    "iso:country":"DE",
    "sg:address":"Am Hoheloh 11",
    "sg:city":"Suhl",
    "sg:phone":"+49 3681/721056",
    "sg:postcode":"98527",
    "sg:province":"Th\u00fcringen",
    "wof:name":"H. He\u00dfler",
    "wof:placetype":"venue"
},
  "geometry": {"coordinates":[10.702673,50.60334],"type":"Point"}
}