{
  "type": "Feature",
  "properties": {
    "iso:country":"DE",
    "sg:address":"Birkenstr. 7",
    "sg:city":"Seeheim-Jugenheim",
    "sg:phone":"+49 6257/7670",
    "sg:postcode":"64342",
    "sg:province":"Hessen",
    "wof:name":"J. Becker Finanzberater",
    "wof:placetype":"venue"
},
  "geometry": {"coordinates":[8.6287612915,49.7529563904],"type":"Point"}
}