{
  "type": "Feature",
  "properties": {
    "iso:country":"DE",
    "sg:address":"Altenburger Chaussee 1",
    "sg:city":"Bernburg",
    "sg:phone":"+49 3471/35630",
    "sg:postcode":"06406",
    "sg:province":"Sachsen-Anhalt",
    "wof:name":"Wieden & Partner Gmbh",
    "wof:placetype":"venue"
},
  "geometry": {"coordinates":[11.7378177643,51.8074035645],"type":"Point"}
}