{
  "type": "Feature",
  "properties": {
    "iso:country":"DE",
    "sg:address":"theresienthaler str. 22",
    "sg:city":"zwiesel",
    "sg:phone":"+49 9922/609344",
    "sg:postcode":"94227",
    "sg:province":"Bayern",
    "wof:name":"Finanzmakler, Aktienfonds, Immobilienfonds",
    "wof:placetype":"venue"
},
  "geometry": {"coordinates":[13.231073,49.021603],"type":"Point"}
}