{
  "type": "Feature",
  "properties": {
    "iso:country":"DE",
    "sg:address":"Siemensstr. 9",
    "sg:city":"Reiskirchen",
    "sg:phone":"+49 6408/965030",
    "sg:postcode":"35447",
    "sg:province":"Hessen",
    "wof:name":"Manfred Feick Architekt",
    "wof:placetype":"venue"
},
  "geometry": {"coordinates":[8.818951,50.599777],"type":"Point"}
}