{
  "type": "Feature",
  "properties": {
    "iso:country":"DE",
    "sg:address":"Nieh\u00f6rsterstr. 33",
    "sg:city":"Paderborn",
    "sg:postcode":"33104",
    "sg:province":"Nordrhein-Westfalen",
    "wof:name":"Casada Gmbh",
    "wof:placetype":"venue"
},
  "geometry": {"coordinates":[8.717157,51.785862],"type":"Point"}
}