{
  "type": "Feature",
  "properties": {
    "iso:country":"DE",
    "sg:address":"L\u00fcckerather Str. 22",
    "sg:city":"Kall",
    "sg:phone":"+49 2441/6122",
    "sg:postcode":"53925",
    "sg:province":"Nordrhein-Westfalen",
    "wof:name":"Peter Thelen",
    "wof:placetype":"venue"
},
  "geometry": {"coordinates":[6.580035,50.567238],"type":"Point"}
}