{
  "type": "Feature",
  "properties": {
    "iso:country":"DE",
    "sg:address":"Freiburger Str. 1",
    "sg:city":"Lenzkirch",
    "sg:phone":"+49 7653/9305",
    "sg:postcode":"79853",
    "sg:province":"Baden-W\u00fcrttemberg",
    "wof:name":"Bierhals",
    "wof:placetype":"venue"
},
  "geometry": {"coordinates":[8.2013187408,47.8685951233],"type":"Point"}
}