{
  "type": "Feature",
  "properties": {
    "iso:country":"DE",
    "sg:address":"Ruhrstr. 23",
    "sg:city":"Mettmann",
    "sg:phone":"+49 2104/71544",
    "sg:postcode":"40822",
    "sg:province":"Nordrhein-Westfalen",
    "wof:name":"Hans-peter Koch",
    "wof:placetype":"venue"
},
  "geometry": {"coordinates":[6.9622907639,51.2469444275],"type":"Point"}
}