{
  "type": "Feature",
  "properties": {
    "iso:country":"DE",
    "sg:address":"Theresienstr. 4",
    "sg:city":"Berg",
    "sg:phone":"+49 7273/1298",
    "sg:postcode":"76768",
    "sg:province":"Rheinland-Pfalz",
    "wof:name":"Josef Roitsch Inh. Horst Roitsch",
    "wof:placetype":"venue"
},
  "geometry": {"coordinates":[8.2047109604,48.9829597473],"type":"Point"}
}