{
  "type": "Feature",
  "properties": {
    "iso:country":"DE",
    "sg:address":"Am L\u00f6bauer Wasser 2",
    "sg:city":"Kittlitz",
    "sg:phone":"+49 3585",
    "sg:postcode":"02708",
    "sg:province":"Sachsen",
    "wof:name":"Automaten-service Locke In L\u00f6bau / Georgewitz",
    "wof:placetype":"venue"
},
  "geometry": {"coordinates":[14.676127,51.12933],"type":"Point"}
}