{
  "type": "Feature",
  "properties": {
    "iso:country":"DE",
    "sg:address":"Postfach 102",
    "sg:city":"Morbach",
    "sg:postcode":"54494",
    "sg:province":"Rheinland-Pfalz",
    "wof:name":"Kath. Pfarrb\u00fccherei Morbach",
    "wof:placetype":"venue"
},
  "geometry": {"coordinates":[7.121416,49.808575],"type":"Point"}
}