{
  "type": "Feature",
  "properties": {
    "iso:country":"DE",
    "sg:address":"Rastb\u00fcchlstr. 41",
    "sg:city":"Breitenberg",
    "sg:phone":"+49 8584/1833",
    "sg:postcode":"94139",
    "sg:province":"Bayern",
    "wof:name":"Josef Thaler",
    "wof:placetype":"venue"
},
  "geometry": {"coordinates":[13.7563800812,48.700302124],"type":"Point"}
}