{
  "type": "Feature",
  "properties": {
    "iso:country":"DE",
    "sg:address":"Rh\u00f6nstr. 105",
    "sg:city":"Frankfurt",
    "sg:phone":"+49 69/491429",
    "sg:postcode":"60385",
    "sg:province":"Hessen",
    "wof:name":"Moderna Reinigungs-zentrum Gmbh",
    "wof:placetype":"venue"
},
  "geometry": {"coordinates":[8.710127,50.118435],"type":"Point"}
}