{
  "type": "Feature",
  "properties": {
    "iso:country":"DE",
    "sg:address":"Immermannstr. 34",
    "sg:city":"K\u00f6ln",
    "sg:phone":"+49 221/409792",
    "sg:postcode":"50931",
    "sg:province":"Nordrhein-Westfalen",
    "wof:name":"Eichel Dachbau Gmbh",
    "wof:placetype":"venue"
},
  "geometry": {"coordinates":[6.9182481766,50.9299697876],"type":"Point"}
}