{
  "type": "Feature",
  "properties": {
    "iso:country":"DE",
    "sg:address":"Neutorstr. 63",
    "sg:city":"Salzwedel",
    "sg:phone":"+49 3901/422228",
    "sg:postcode":"29410",
    "sg:province":"Sachsen-Anhalt",
    "wof:name":"Bhg",
    "wof:placetype":"venue"
},
  "geometry": {"coordinates":[11.152023,52.845165],"type":"Point"}
}