{
  "type": "Feature",
  "properties": {
    "iso:country":"DE",
    "sg:address":"Bothmerstr. 14",
    "sg:city":"M\u00fcnchen",
    "sg:phone":"+49 89/165615",
    "sg:postcode":"80634",
    "sg:province":"Bayern",
    "wof:name":"Allmann Sattler Und Wappner Architekten",
    "wof:placetype":"venue"
},
  "geometry": {"coordinates":[11.533761,48.156185],"type":"Point"}
}