{
  "type": "Feature",
  "properties": {
    "iso:country":"DE",
    "sg:address":"Neue Str. 15",
    "sg:city":"J\u00f6rdenstorf",
    "sg:phone":"+49 39977/2541",
    "sg:postcode":"17168",
    "sg:province":"Mecklenburg-Vorpommern",
    "wof:name":"G. H\u00fcckst\u00e4dt Masseur",
    "wof:placetype":"venue"
},
  "geometry": {"coordinates":[12.488532,53.909344],"type":"Point"}
}