{
  "type": "Feature",
  "properties": {
    "iso:country":"DE",
    "sg:address":"H\u00f6lderlinstr. 3",
    "sg:city":"Wendlingen",
    "sg:phone":"+49 7024/7278",
    "sg:postcode":"73240",
    "sg:province":"Baden-W\u00fcrttemberg",
    "wof:name":"Stogatex Stoff & Gardinenland Gmbh",
    "wof:placetype":"venue"
},
  "geometry": {"coordinates":[9.3819417953,48.6752128601],"type":"Point"}
}