{
  "type": "Feature",
  "properties": {
    "iso:country":"DE",
    "sg:address":"Schaaphusen 2",
    "sg:city":"Hamburg",
    "sg:phone":"+49 40/7960135",
    "sg:postcode":"21147",
    "sg:province":"Hamburg",
    "wof:name":"Fds Technik Gmbh",
    "wof:placetype":"venue"
},
  "geometry": {"coordinates":[9.8900747299,53.4745674133],"type":"Point"}
}