{
  "type": "Feature",
  "properties": {
    "iso:country":"DE",
    "sg:address":"Uferallee 39a",
    "sg:city":"Zeltingen-Rachtig",
    "sg:phone":"+49 6532/2515",
    "sg:postcode":"54492",
    "sg:province":"Rheinland-Pfalz",
    "wof:name":"M. M. Grill",
    "wof:placetype":"venue"
},
  "geometry": {"coordinates":[7.0091152191,49.9552230835],"type":"Point"}
}