{
  "type": "Feature",
  "properties": {
    "iso:country":"DE",
    "sg:address":"Gschwenderstr. 7 A",
    "sg:city":"Marktoberdorf",
    "sg:phone":"+49 8342/2656",
    "sg:postcode":"87616",
    "sg:province":"Bayern",
    "wof:name":"Filmburg",
    "wof:placetype":"venue"
},
  "geometry": {"coordinates":[10.617173,47.779903],"type":"Point"}
}