{
  "type": "Feature",
  "properties": {
    "iso:country":"DE",
    "sg:address":"Elbstr. 18",
    "sg:city":"Pretzsch",
    "sg:phone":"+49 34926/57205",
    "sg:postcode":"06909",
    "sg:province":"Sachsen-Anhalt",
    "wof:name":"Manfred Murche",
    "wof:placetype":"venue"
},
  "geometry": {"coordinates":[12.8069038391,51.7136764526],"type":"Point"}
}