{
  "type": "Feature",
  "properties": {
    "iso:country":"DE",
    "sg:address":"Hauptstr. 14",
    "sg:city":"Herrischried",
    "sg:phone":"+49 7764/210",
    "sg:postcode":"79737",
    "sg:province":"Baden-W\u00fcrttemberg",
    "wof:name":"Metzgerei Pension Ochsen",
    "wof:placetype":"venue"
},
  "geometry": {"coordinates":[8.0006742477,47.6669082642],"type":"Point"}
}