{
  "type": "Feature",
  "properties": {
    "iso:country":"DE",
    "sg:address":"Bahnhofstr. 40",
    "sg:city":"Burg",
    "sg:phone":"+49 4825/700",
    "sg:postcode":"25712",
    "sg:province":"Schleswig-Holstein",
    "wof:name":"Deutsches Rotes Kreuz Kreisverband Dithmarschen",
    "wof:placetype":"venue"
},
  "geometry": {"coordinates":[9.257634,54.0009],"type":"Point"}
}