{
  "type": "Feature",
  "properties": {
    "iso:country":"DE",
    "sg:address":"\u00d6tzstr. 3",
    "sg:city":"Fischbachau",
    "sg:phone":"+49 8028/497",
    "sg:postcode":"83730",
    "sg:province":"Bayern",
    "wof:name":"Konrad Astner",
    "wof:placetype":"venue"
},
  "geometry": {"coordinates":[11.949852,47.742592],"type":"Point"}
}