{
  "type": "Feature",
  "properties": {
    "iso:country":"DE",
    "sg:address":"Rathausstr. 11",
    "sg:city":"Bodolz",
    "sg:phone":"+49 8382/946797",
    "sg:postcode":"88131",
    "sg:province":"Bayern",
    "wof:name":"Dagmar Scharf",
    "wof:placetype":"venue"
},
  "geometry": {"coordinates":[9.6621189117,47.571811676],"type":"Point"}
}