{
  "type": "Feature",
  "properties": {
    "iso:country":"DE",
    "sg:address":"Herner Str. 39a",
    "sg:city":"Recklinghausen",
    "sg:phone":"+49 2361/654797",
    "sg:postcode":"45657",
    "sg:province":"Nordrhein-Westfalen",
    "wof:name":"Tiffany Glaskunst Recklinghausen",
    "wof:placetype":"venue"
},
  "geometry": {"coordinates":[7.198539,51.60849],"type":"Point"}
}