{
  "type": "Feature",
  "properties": {
    "iso:country":"DE",
    "sg:address":"Gr\u00e4festr. 18",
    "sg:city":"Kassel",
    "sg:phone":"+49 561/23646",
    "sg:postcode":"34121",
    "sg:province":"Hessen",
    "wof:name":"Farben-thomas- August Thomas Gmbh",
    "wof:placetype":"venue"
},
  "geometry": {"coordinates":[9.4691648483,51.3109855652],"type":"Point"}
}