{
  "type": "Feature",
  "properties": {
    "iso:country":"DE",
    "sg:address":"F\u00e4rberstr. 43",
    "sg:city":"Rosenheim",
    "sg:phone":"+49 8031/33358",
    "sg:postcode":"83022",
    "sg:province":"Bayern",
    "wof:name":"Hekro Design Harald Hemberger Kg",
    "wof:placetype":"venue"
},
  "geometry": {"coordinates":[12.1328458786,47.8561477661],"type":"Point"}
}