{
  "type": "Feature",
  "properties": {
    "iso:country":"DE",
    "sg:address":"An der Stadtkirche 18",
    "sg:city":"Aalen",
    "sg:phone":"+49 7361/9550050",
    "sg:postcode":"73430",
    "sg:province":"Baden-W\u00fcrttemberg",
    "wof:name":"Modehaus Ratspassage",
    "wof:placetype":"venue"
},
  "geometry": {"coordinates":[10.0942678452,48.8366661072],"type":"Point"}
}