{
  "type": "Feature",
  "properties": {
    "iso:country":"DE",
    "sg:address":"Grunigerstr. 17",
    "sg:city":"Paderborn",
    "sg:phone":"+49 5251/32612",
    "sg:postcode":"33102",
    "sg:province":"Nordrhein-Westfalen",
    "wof:name":"M\u00f6llmann-oberbach Tanzschule",
    "wof:placetype":"venue"
},
  "geometry": {"coordinates":[8.7412090302,51.7156219482],"type":"Point"}
}