{
  "type": "Feature",
  "properties": {
    "iso:country":"DE",
    "sg:address":"An der Zollbr\u00fccke 8",
    "sg:city":"Ulm",
    "sg:phone":"+49 7305/7595",
    "sg:postcode":"89079",
    "sg:province":"Baden-W\u00fcrttemberg",
    "wof:name":"Anton Wegerer",
    "wof:placetype":"venue"
},
  "geometry": {"coordinates":[9.94271,48.344898],"type":"Point"}
}