{
  "type": "Feature",
  "properties": {
    "iso:country":"DE",
    "sg:address":"Kanalweg 11",
    "sg:city":"Geldern",
    "sg:phone":"+49 2831/8118",
    "sg:postcode":"47608",
    "sg:province":"Nordrhein-Westfalen",
    "wof:name":"Gerling Konzern Gki",
    "wof:placetype":"venue"
},
  "geometry": {"coordinates":[6.3151760101,51.5195541382],"type":"Point"}
}