{
  "type": "Feature",
  "properties": {
    "iso:country":"DE",
    "sg:address":"Urfersheim 14",
    "sg:city":"Illesheim",
    "sg:phone":"+49 9841/8868",
    "sg:postcode":"91471",
    "sg:province":"Bayern",
    "wof:name":"Hans Fischer",
    "wof:placetype":"venue"
},
  "geometry": {"coordinates":[10.391484,49.47094],"type":"Point"}
}