{
  "type": "Feature",
  "properties": {
    "iso:country":"DE",
    "sg:address":"Ostwall 15a",
    "sg:city":"Menden",
    "sg:phone":"+49 2373/12377",
    "sg:postcode":"58706",
    "sg:province":"Nordrhein-Westfalen",
    "wof:name":"Am Kamin",
    "wof:placetype":"venue"
},
  "geometry": {"coordinates":[7.7973828316,51.4386749268],"type":"Point"}
}