{
  "type": "Feature",
  "properties": {
    "iso:country":"DE",
    "sg:address":"Dr.-Theodor-Neubauer-Str. 13",
    "sg:city":"Apolda",
    "sg:phone":"+49 3644/553043",
    "sg:postcode":"99510",
    "sg:province":"Th\u00fcringen",
    "wof:name":"Egbert Knopf Immobilienmakler",
    "wof:placetype":"venue"
},
  "geometry": {"coordinates":[11.5085105896,51.0242271423],"type":"Point"}
}