{
  "type": "Feature",
  "properties": {
    "iso:country":"DE",
    "sg:address":"Wiesbadener Str. 38",
    "sg:city":"K\u00f6nigstein",
    "sg:phone":"+49 6174/5029",
    "sg:postcode":"61462",
    "sg:province":"Hessen",
    "wof:name":"Hofra-trading Gmbh",
    "wof:placetype":"venue"
},
  "geometry": {"coordinates":[8.469461441,50.1793365479],"type":"Point"}
}