{
  "type": "Feature",
  "properties": {
    "iso:country":"DE",
    "sg:address":"Str\u00fcth",
    "sg:city":"R\u00f6ttingen",
    "sg:phone":"+49 9338/360",
    "sg:postcode":"97285",
    "sg:province":"Bayern",
    "wof:name":"B. Gunz",
    "wof:placetype":"venue"
},
  "geometry": {"coordinates":[9.964769,49.51543],"type":"Point"}
}