{
  "type": "Feature",
  "properties": {
    "iso:country":"DE",
    "sg:address":"Hubertusstr. 15",
    "sg:city":"Baden-Baden",
    "sg:postcode":"76532",
    "sg:province":"Baden-W\u00fcrttemberg",
    "wof:name":"Ap Computer Und Netzwerke E. K.",
    "wof:placetype":"venue"
},
  "geometry": {"coordinates":[8.2039308548,48.7816505432],"type":"Point"}
}