{
  "type": "Feature",
  "properties": {
    "iso:country":"DE",
    "sg:address":"Trinkbornstr. 21",
    "sg:city":"D\u00f6rth",
    "sg:phone":"+49 6747/93090",
    "sg:postcode":"56281",
    "sg:province":"Rheinland-Pfalz",
    "wof:name":"Sonntag Holding Gesch\u00e4ftsf\u00fchrungs Gmbh",
    "wof:placetype":"venue"
},
  "geometry": {"coordinates":[7.591207,50.162666],"type":"Point"}
}