{
  "type": "Feature",
  "properties": {
    "iso:country":"DE",
    "sg:address":"Sudetenstr. 9",
    "sg:city":"Menden",
    "sg:phone":"+49 2373/95900",
    "sg:postcode":"58708",
    "sg:province":"Nordrhein-Westfalen",
    "wof:name":"Friedrich Freek Gmbh",
    "wof:placetype":"venue"
},
  "geometry": {"coordinates":[7.7747550011,51.4371376038],"type":"Point"}
}