{
  "type": "Feature",
  "properties": {
    "iso:country":"DE",
    "sg:address":"Veneterstr. 2a",
    "sg:city":"Aachen",
    "sg:postcode":"52074",
    "sg:province":"Nordrhein-Westfalen",
    "wof:name":"Rehanova Gesellschaft F\u00fcr Innovative Rehabilitation Mbh",
    "wof:placetype":"venue"
},
  "geometry": {"coordinates":[6.039951,50.766026],"type":"Point"}
}