{
  "type": "Feature",
  "properties": {
    "iso:country":"DE",
    "sg:address":"Hauptstr. 52",
    "sg:city":"Alerheim",
    "sg:phone":"+49 9085/243",
    "sg:postcode":"86733",
    "sg:province":"Bayern",
    "wof:name":"Brauereigastst\u00e4tte",
    "wof:placetype":"venue"
},
  "geometry": {"coordinates":[10.6165761948,48.8464164734],"type":"Point"}
}