{
  "type": "Feature",
  "properties": {
    "iso:country":"DE",
    "sg:address":"Marktplatz",
    "sg:city":"Seligenstadt",
    "sg:phone":"+49 6182/937119",
    "sg:postcode":"63500",
    "sg:province":"Hessen",
    "wof:name":"Online-kurier",
    "wof:placetype":"venue"
},
  "geometry": {"coordinates":[8.97542,50.044395],"type":"Point"}
}