{
  "type": "Feature",
  "properties": {
    "iso:country":"DE",
    "sg:address":"Gartenstr. 24",
    "sg:city":"Gro\u00dfp\u00f6sna",
    "sg:phone":"+49 34297/40643",
    "sg:postcode":"04463",
    "sg:province":"Sachsen",
    "wof:name":"Prof. Dr. G\u00fcnter Heller",
    "wof:placetype":"venue"
},
  "geometry": {"coordinates":[12.5083398819,51.2821311951],"type":"Point"}
}