{
  "type": "Feature",
  "properties": {
    "iso:country":"DE",
    "sg:address":"Werkstr. 13",
    "sg:city":"Handewitt",
    "sg:phone":"+49 4608/458",
    "sg:postcode":"24983",
    "sg:province":"Schleswig-Holstein",
    "wof:name":"Beraldi Grundst\u00fccks- Gesellschaft Mbh & Co. Kg",
    "wof:placetype":"venue"
},
  "geometry": {"coordinates":[9.3197450638,54.7682723999],"type":"Point"}
}