{
  "type": "Feature",
  "properties": {
    "iso:country":"DE",
    "sg:address":"Karl-Marx-Str. 56",
    "sg:city":"Neuruppin",
    "sg:phone":"+49 3391/2202",
    "sg:postcode":"16816",
    "sg:province":"Brandenburg",
    "wof:name":"Unicum",
    "wof:placetype":"venue"
},
  "geometry": {"coordinates":[12.8019828796,52.9225540161],"type":"Point"}
}