{
  "type": "Feature",
  "properties": {
    "iso:country":"DE",
    "sg:address":"Postfach 28",
    "sg:city":"M\u00f6nchberg",
    "sg:postcode":"63933",
    "sg:province":"Bayern",
    "wof:name":"Bibliothek Im Alten Rathaus",
    "wof:placetype":"venue"
},
  "geometry": {"coordinates":[9.266589,49.792446],"type":"Point"}
}