{
  "type": "Feature",
  "properties": {
    "iso:country":"DE",
    "sg:address":"Saalburgallee 2",
    "sg:city":"Frankfurt",
    "sg:phone":"+49 69/94415032",
    "sg:postcode":"60385",
    "sg:province":"Hessen",
    "wof:name":"Heidenfelder Service Gmbh",
    "wof:placetype":"venue"
},
  "geometry": {"coordinates":[8.7101106644,50.1252937317],"type":"Point"}
}