{
  "type": "Feature",
  "properties": {
    "iso:country":"DE",
    "sg:address":"Bahnhofstr. 3",
    "sg:city":"M\u00f6rfelden-Walldorf",
    "sg:phone":"+49 6105/72863",
    "sg:postcode":"64546",
    "sg:province":"Hessen",
    "wof:name":"Stadtb\u00fccherei M\u00f6rfelden",
    "wof:placetype":"venue"
},
  "geometry": {"coordinates":[8.567721,49.976372],"type":"Point"}
}