{
  "type": "Feature",
  "properties": {
    "iso:country":"DE",
    "sg:address":"Blankenburger Str. 21c",
    "sg:city":"Bramsche",
    "sg:phone":"+49 5461/4747",
    "sg:postcode":"49565",
    "sg:province":"Niedersachsen",
    "wof:name":"F. H\u00fcrdler Ingenieur",
    "wof:placetype":"venue"
},
  "geometry": {"coordinates":[7.9927148819,52.4219818115],"type":"Point"}
}