{
  "type": "Feature",
  "properties": {
    "iso:country":"DE",
    "sg:address":"Bahnhofstrasse",
    "sg:city":"Ebersburg",
    "sg:phone":"+49 6656/253",
    "sg:postcode":"36157",
    "sg:province":"Hessen",
    "wof:name":"Tafeln Und Mehr",
    "wof:placetype":"venue"
},
  "geometry": {"coordinates":[9.781221,50.457119],"type":"Point"}
}