{
  "type": "Feature",
  "properties": {
    "iso:country":"DE",
    "sg:address":"Auerbergstr. 26",
    "sg:city":"Hausham",
    "sg:phone":"+49 8026/58885",
    "sg:postcode":"83734",
    "sg:province":"Bayern",
    "wof:name":"Josef R\u00f6sler Elektroinstallation",
    "wof:placetype":"venue"
},
  "geometry": {"coordinates":[11.823181,47.749104],"type":"Point"}
}