{
  "type": "Feature",
  "properties": {
    "iso:country":"DE",
    "sg:address":"Langhansstr. 85",
    "sg:city":"Berlin",
    "sg:phone":"+49 30/47300666",
    "sg:postcode":"13086",
    "sg:province":"Berlin",
    "wof:name":"Wagner Tischlerei Gmbh",
    "wof:placetype":"venue"
},
  "geometry": {"coordinates":[13.43267,52.554092],"type":"Point"}
}