{
  "type": "Feature",
  "properties": {
    "iso:country":"DE",
    "sg:address":"Von-Harsch-Str. 18",
    "sg:city":"Reute",
    "sg:phone":"+49 7641/48585",
    "sg:postcode":"79276",
    "sg:province":"Baden-W\u00fcrttemberg",
    "wof:name":"A. Lindenau Ingenieur",
    "wof:placetype":"venue"
},
  "geometry": {"coordinates":[7.828772068,48.0841941833],"type":"Point"}
}