{
  "type": "Feature",
  "properties": {
    "iso:country":"DE",
    "sg:address":"Seitenhalde 55",
    "sg:city":"Pfullingen",
    "sg:phone":"+49 7121/790239",
    "sg:postcode":"72793",
    "sg:province":"Baden-W\u00fcrttemberg",
    "wof:name":"Finckh Consult Gmbh",
    "wof:placetype":"venue"
},
  "geometry": {"coordinates":[9.2175540924,48.4577674866],"type":"Point"}
}