{
  "type": "Feature",
  "properties": {
    "iso:country":"DE",
    "sg:address":"Filderbahnstr. 2",
    "sg:city":"Stuttgart",
    "sg:phone":"+49 711/9977166",
    "sg:postcode":"70567",
    "sg:province":"Baden-W\u00fcrttemberg",
    "wof:name":"Restaurant Momentos",
    "wof:placetype":"venue"
},
  "geometry": {"coordinates":[9.1454381943,48.7262687683],"type":"Point"}
}