{
  "type": "Feature",
  "properties": {
    "iso:country":"DE",
    "sg:address":"Barbarastr. 37",
    "sg:city":"Liebenburg",
    "sg:phone":"+49 5346/4136",
    "sg:postcode":"38704",
    "sg:province":"Niedersachsen",
    "wof:name":"W. Dinter",
    "wof:placetype":"venue"
},
  "geometry": {"coordinates":[10.3836898804,52.0092086792],"type":"Point"}
}