{
  "type": "Feature",
  "properties": {
    "iso:country":"DE",
    "sg:address":"Deipenbrock 15",
    "sg:city":"Legden",
    "sg:phone":"+49 2566/96555",
    "sg:postcode":"48739",
    "sg:province":"Nordrhein-Westfalen",
    "wof:name":"Franz Harmeling",
    "wof:placetype":"venue"
},
  "geometry": {"coordinates":[7.115029,52.047005],"type":"Point"}
}