{
  "type": "Feature",
  "properties": {
    "iso:country":"DE",
    "sg:address":"Brahmsstr. 51",
    "sg:city":"Meckenheim",
    "sg:phone":"+49 2225/14609",
    "sg:postcode":"53340",
    "sg:province":"Nordrhein-Westfalen",
    "wof:name":"H. Rauschning Rid Reprotechnik Gmbh",
    "wof:placetype":"venue"
},
  "geometry": {"coordinates":[7.0466470718,50.6259803772],"type":"Point"}
}