{
  "type": "Feature",
  "properties": {
    "iso:country":"DE",
    "sg:address":"Kapellenstr. 3 a",
    "sg:city":"Unterhaching",
    "sg:phone":"+49 89/6111086",
    "sg:postcode":"82008",
    "sg:province":"Bayern",
    "wof:name":"B. Ellinger",
    "wof:placetype":"venue"
},
  "geometry": {"coordinates":[11.618785,48.066742],"type":"Point"}
}