{
  "type": "Feature",
  "properties": {
    "iso:country":"DE",
    "sg:address":"Widayweg 4",
    "sg:city":"Arnsberg",
    "sg:postcode":"59823",
    "sg:province":"Nordrhein-Westfalen",
    "wof:name":"Aldi Gmbh & Co. Kg",
    "wof:placetype":"venue"
},
  "geometry": {"coordinates":[8.1342868805,51.3957519531],"type":"Point"}
}