{
  "type": "Feature",
  "properties": {
    "iso:country":"DE",
    "sg:address":"Birkenweg 2",
    "sg:city":"Wei\u00dfenstadt",
    "sg:phone":"+49 9253/1363",
    "sg:postcode":"95163",
    "sg:province":"Bayern",
    "wof:name":"Blumen Pietschka",
    "wof:placetype":"venue"
},
  "geometry": {"coordinates":[11.890177,50.096432],"type":"Point"}
}