{
  "type": "Feature",
  "properties": {
    "iso:country":"DE",
    "sg:address":"Robert-Bosch-Str 11",
    "sg:city":"Dachau",
    "sg:phone":"+49 8131/2960",
    "sg:postcode":"85221",
    "sg:province":"Bayern",
    "wof:name":"Euras Elektro-forschungs- Und Produktionsgesellschaft Mbh",
    "wof:placetype":"venue"
},
  "geometry": {"coordinates":[11.475904,48.264893],"type":"Point"}
}