{
  "type": "Feature",
  "properties": {
    "iso:country":"DE",
    "sg:address":"M\u00fchlenstr. 22",
    "sg:city":"Siegburg",
    "sg:phone":"+49 2241/58107",
    "sg:postcode":"53721",
    "sg:province":"Nordrhein-Westfalen",
    "wof:name":"Petra Siek",
    "wof:placetype":"venue"
},
  "geometry": {"coordinates":[7.208086,50.795341],"type":"Point"}
}