{
  "type": "Feature",
  "properties": {
    "iso:country":"DE",
    "sg:address":"Heinzengartenstr. 4",
    "sg:city":"Sch\u00f6nbrunn",
    "sg:phone":"+49 6272/2313",
    "sg:postcode":"69436",
    "sg:province":"Baden-W\u00fcrttemberg",
    "wof:name":"Otto Boch Bildhauer",
    "wof:placetype":"venue"
},
  "geometry": {"coordinates":[8.927622,49.412285],"type":"Point"}
}