{
  "type": "Feature",
  "properties": {
    "iso:country":"DE",
    "sg:address":"Kaiserslauterer Str. 19",
    "sg:city":"Saarbr\u00fccken",
    "sg:phone":"+49 681/35749",
    "sg:postcode":"66123",
    "sg:province":"Saarland",
    "wof:name":"Wolfgang Schweizer Masseur",
    "wof:placetype":"venue"
},
  "geometry": {"coordinates":[7.018167,49.238846],"type":"Point"}
}