{
  "type": "Feature",
  "properties": {
    "iso:country":"DE",
    "sg:address":"Marienstr 6-8",
    "sg:city":"Kevelaer",
    "sg:phone":"+49 2832/50022",
    "sg:postcode":"47623",
    "sg:province":"Nordrhein-Westfalen",
    "wof:name":"Bercker",
    "wof:placetype":"venue"
},
  "geometry": {"coordinates":[6.2481489182,51.5837440491],"type":"Point"}
}