{
  "type": "Feature",
  "properties": {
    "iso:country":"DE",
    "sg:address":"Hausackerweg 22",
    "sg:city":"Heidelberg",
    "sg:phone":"+49 6221/182509",
    "sg:postcode":"69118",
    "sg:province":"Baden-W\u00fcrttemberg",
    "wof:name":"J. P. Ackermann Rechtsanwalt",
    "wof:placetype":"venue"
},
  "geometry": {"coordinates":[8.7300786972,49.4165534973],"type":"Point"}
}