{
  "type": "Feature",
  "properties": {
    "iso:country":"DE",
    "sg:address":"Hauptstr. 108",
    "sg:city":"Achern",
    "sg:phone":"+49 7841/3992",
    "sg:postcode":"77855",
    "sg:province":"Baden-W\u00fcrttemberg",
    "wof:name":"Bieber",
    "wof:placetype":"venue"
},
  "geometry": {"coordinates":[8.07668,48.62904],"type":"Point"}
}