{
  "type": "Feature",
  "properties": {
    "iso:country":"DE",
    "sg:address":"Luisenstr. 6",
    "sg:city":"Bad Oeynhausen",
    "sg:phone":"+49 5731/28681",
    "sg:postcode":"32545",
    "sg:province":"Nordrhein-Westfalen",
    "wof:name":"Haus Holstein",
    "wof:placetype":"venue"
},
  "geometry": {"coordinates":[8.7909622192,52.1986083984],"type":"Point"}
}