{
  "type": "Feature",
  "properties": {
    "iso:country":"DE",
    "sg:address":"Dr.-Tusch-Str. 8",
    "sg:city":"Frechen",
    "sg:phone":"+49 2234/23794",
    "sg:postcode":"50226",
    "sg:province":"Nordrhein-Westfalen",
    "wof:name":"Peter Puszta",
    "wof:placetype":"venue"
},
  "geometry": {"coordinates":[6.809613,50.903671],"type":"Point"}
}