{
  "type": "Feature",
  "properties": {
    "iso:country":"DE",
    "sg:address":"K\u00f6lner Str. 52 a",
    "sg:city":"Hagen",
    "sg:phone":"+49 2331/406061",
    "sg:postcode":"58135",
    "sg:province":"Nordrhein-Westfalen",
    "wof:name":"Geitner-reisen Reiseb\u00fcro",
    "wof:placetype":"venue"
},
  "geometry": {"coordinates":[7.4165420532,51.3456192017],"type":"Point"}
}