{
  "type": "Feature",
  "properties": {
    "iso:country":"DE",
    "sg:address":"Eichenweg 2",
    "sg:city":"Hirschau",
    "sg:phone":"+49 9622/2731",
    "sg:postcode":"92242",
    "sg:province":"Bayern",
    "wof:name":"Edwin Hauk",
    "wof:placetype":"venue"
},
  "geometry": {"coordinates":[11.937964,49.541607],"type":"Point"}
}