{
  "type": "Feature",
  "properties": {
    "iso:country":"DE",
    "sg:address":"H\u00fcttenstr. 139",
    "sg:city":"Bendorf",
    "sg:phone":"+49 2622/3563",
    "sg:postcode":"56170",
    "sg:province":"Rheinland-Pfalz",
    "wof:name":"Hans D\u00fcyster",
    "wof:placetype":"venue"
},
  "geometry": {"coordinates":[7.5578970909,50.4241981506],"type":"Point"}
}