{
  "type": "Feature",
  "properties": {
    "iso:country":"DE",
    "sg:address":"Waldtorstr. 5",
    "sg:city":"Waldshut-Tiengen",
    "sg:postcode":"79761",
    "sg:province":"Baden-W\u00fcrttemberg",
    "wof:name":"Dekanat Hochrhein",
    "wof:placetype":"venue"
},
  "geometry": {"coordinates":[8.2127103806,47.6245040894],"type":"Point"}
}