{
  "type": "Feature",
  "properties": {
    "iso:country":"DE",
    "sg:address":"Sch\u00fcrholzer Str. 1",
    "sg:city":"Drolshagen",
    "sg:phone":"+49 2763/6137",
    "sg:postcode":"57489",
    "sg:province":"Nordrhein-Westfalen",
    "wof:name":"Robert Ackerschott",
    "wof:placetype":"venue"
},
  "geometry": {"coordinates":[7.776194,51.070023],"type":"Point"}
}