{
  "type": "Feature",
  "properties": {
    "iso:country":"DE",
    "sg:address":"In den Schelmen\u00e4ckern 1",
    "sg:city":"Hechingen",
    "sg:phone":"+49 7471/2535",
    "sg:postcode":"72379",
    "sg:province":"Baden-W\u00fcrttemberg",
    "wof:name":"Hermann Str\u00f6bele",
    "wof:placetype":"venue"
},
  "geometry": {"coordinates":[8.97249,48.352444],"type":"Point"}
}