{
  "type": "Feature",
  "properties": {
    "iso:country":"DE",
    "sg:address":"Goethestr. 11c",
    "sg:city":"Visselh\u00f6vede",
    "sg:phone":"+49 4262/4383",
    "sg:postcode":"27374",
    "sg:province":"Niedersachsen",
    "wof:name":"Ambulanter Kranken- Und Pflegedienst Mit Niveau Gbr",
    "wof:placetype":"venue"
},
  "geometry": {"coordinates":[9.579004,52.984722],"type":"Point"}
}