{
  "type": "Feature",
  "properties": {
    "iso:country":"DE",
    "sg:address":"Blossersberg 26",
    "sg:city":"Viechtach",
    "sg:phone":"+49 9942/1342",
    "sg:postcode":"94234",
    "sg:province":"Bayern",
    "wof:name":"Rlk Reisinger Ges. F\u00fcr L\u00fcftungs- Und Klimatechnik Mbh",
    "wof:placetype":"venue"
},
  "geometry": {"coordinates":[12.9034776688,49.084487915],"type":"Point"}
}