{
  "type": "Feature",
  "properties": {
    "iso:country":"DE",
    "sg:address":"Bonifatiusplatz 10",
    "sg:city":"M\u00fcnnerstadt",
    "sg:phone":"+49 9766/272",
    "sg:postcode":"97702",
    "sg:province":"Bayern",
    "wof:name":"Metzgerei J\u00fcrgen Trost Gmbh",
    "wof:placetype":"venue"
},
  "geometry": {"coordinates":[10.3131504059,50.2570457458],"type":"Point"}
}