{
  "type": "Feature",
  "properties": {
    "iso:country":"DE",
    "sg:address":"Hintere Str. 36",
    "sg:city":"M\u00fchlheim",
    "sg:phone":"+49 7463/990082",
    "sg:postcode":"78570",
    "sg:province":"Baden-W\u00fcrttemberg",
    "wof:name":"Rainer Schad Rechtsanwalt",
    "wof:placetype":"venue"
},
  "geometry": {"coordinates":[8.8902997971,48.0247497559],"type":"Point"}
}