{
  "type": "Feature",
  "properties": {
    "iso:country":"DE",
    "sg:address":"Friedrich-Olbricht-Damm 68",
    "sg:city":"Berlin",
    "sg:postcode":"13627",
    "sg:province":"Berlin",
    "wof:name":"Brauhaus Karlsburg Gmbh",
    "wof:placetype":"venue"
},
  "geometry": {"coordinates":[13.312649,52.545502],"type":"Point"}
}