{
  "type": "Feature",
  "properties": {
    "iso:country":"DE",
    "sg:address":"Deisterstr. 44",
    "sg:city":"Hameln",
    "sg:phone":"+49 5151/29256",
    "sg:postcode":"31785",
    "sg:province":"Niedersachsen",
    "wof:name":"Dionisos-grill",
    "wof:placetype":"venue"
},
  "geometry": {"coordinates":[9.3693981171,52.1038284302],"type":"Point"}
}