{
  "type": "Feature",
  "properties": {
    "iso:country":"DE",
    "sg:address":"Dachsring 27",
    "sg:city":"Ratingen",
    "sg:phone":"+49 2102/60818",
    "sg:postcode":"40883",
    "sg:province":"Nordrhein-Westfalen",
    "wof:name":"Prof. Anton Miller Architekt",
    "wof:placetype":"venue"
},
  "geometry": {"coordinates":[6.903962,51.324989],"type":"Point"}
}