{
  "type": "Feature",
  "properties": {
    "iso:country":"DE",
    "sg:address":"Udersche Str. 11",
    "sg:city":"Thalwenden",
    "sg:phone":"+49 36083/2178",
    "sg:postcode":"37318",
    "sg:province":"Th\u00fcringen",
    "wof:name":"Prodeco Gmbh",
    "wof:placetype":"venue"
},
  "geometry": {"coordinates":[10.041962,51.355244],"type":"Point"}
}