{
  "type": "Feature",
  "properties": {
    "iso:country":"DE",
    "sg:address":"Kalbsburger Str. 9",
    "sg:city":"Borken",
    "sg:phone":"+49 5682/2105",
    "sg:postcode":"34582",
    "sg:province":"Hessen",
    "wof:name":"H. Lohr",
    "wof:placetype":"venue"
},
  "geometry": {"coordinates":[9.2750778198,51.0786056519],"type":"Point"}
}