{
  "type": "Feature",
  "properties": {
    "iso:country":"DE",
    "sg:address":"Hauptstr. 62B",
    "sg:city":"Emmerthal",
    "sg:phone":"+49 5155/8096",
    "sg:postcode":"31860",
    "sg:province":"Niedersachsen",
    "wof:name":"Sch\u00e4fers Brot- Und Kuchen- Spezialit\u00e4ten Gmbh",
    "wof:placetype":"venue"
},
  "geometry": {"coordinates":[9.383542,52.048504],"type":"Point"}
}