{
  "type": "Feature",
  "properties": {
    "iso:country":"DE",
    "sg:address":"Bunsenstr. 15",
    "sg:city":"M\u00fclheim",
    "sg:phone":"+49 208/33459",
    "sg:postcode":"45470",
    "sg:province":"Nordrhein-Westfalen",
    "wof:name":"Uniled Leder- Vertriebsgesellschaft Mbh",
    "wof:placetype":"venue"
},
  "geometry": {"coordinates":[6.8831682205,51.4160346985],"type":"Point"}
}