{
  "type": "Feature",
  "properties": {
    "iso:country":"DE",
    "sg:address":"Rosenbuschstr. 18",
    "sg:city":"Sinzing",
    "sg:phone":"+49 9404/6387",
    "sg:postcode":"93161",
    "sg:province":"Bayern",
    "wof:name":"Franz-xaver Listl",
    "wof:placetype":"venue"
},
  "geometry": {"coordinates":[11.959948,48.97887],"type":"Point"}
}