{
  "type": "Feature",
  "properties": {
    "iso:country":"DE",
    "sg:city":"Pforzheim",
    "sg:phone":"+49 7231",
    "sg:postcode":"75172",
    "sg:province":"Baden-W\u00fcrttemberg",
    "wof:name":"Druckerei Schr\u00f6ter Gmbh",
    "wof:placetype":"venue"
},
  "geometry": {"coordinates":[8.700255,48.890137],"type":"Point"}
}