{
  "type": "Feature",
  "properties": {
    "iso:country":"DE",
    "sg:address":"Bugginger Str. 14",
    "sg:city":"Neuenburg",
    "sg:phone":"+49 7634/2324",
    "sg:postcode":"79395",
    "sg:province":"Baden-W\u00fcrttemberg",
    "wof:name":"Hans-joachim Exner",
    "wof:placetype":"venue"
},
  "geometry": {"coordinates":[7.591524,47.873749],"type":"Point"}
}