{
  "type": "Feature",
  "properties": {
    "iso:country":"DE",
    "sg:address":"Alfred-Neumann-Anger 12",
    "sg:city":"M\u00fcnchen",
    "sg:phone":"+49 89/674518",
    "sg:postcode":"81737",
    "sg:province":"Bayern",
    "wof:name":"Dieter Matzka Kameramann",
    "wof:placetype":"venue"
},
  "geometry": {"coordinates":[11.6519594193,48.0950889587],"type":"Point"}
}