{
  "type": "Feature",
  "properties": {
    "iso:country":"DE",
    "sg:address":"Saarlouiser Str. 61",
    "sg:city":"Eisenh\u00fcttenstadt",
    "sg:phone":"+49 3364/44115",
    "sg:postcode":"15890",
    "sg:province":"Brandenburg",
    "wof:name":"Gastst\u00e4tte Br\u00e4ust\u00fcbel",
    "wof:placetype":"venue"
},
  "geometry": {"coordinates":[14.6236448288,52.1463508606],"type":"Point"}
}