{
  "type": "Feature",
  "properties": {
    "iso:country":"DE",
    "sg:address":"K\u00f6lner Str. 85",
    "sg:city":"Kierspe",
    "sg:postcode":"58566",
    "sg:province":"Nordrhein-Westfalen",
    "wof:name":"Dugro Kunststoff-vertrieb Gmbh",
    "wof:placetype":"venue"
},
  "geometry": {"coordinates":[7.6120328903,51.1253166199],"type":"Point"}
}