{
  "type": "Feature",
  "properties": {
    "iso:country":"DE",
    "sg:address":"Lessau 22",
    "sg:city":"Weidenberg",
    "sg:phone":"+49 9278/9940",
    "sg:postcode":"95466",
    "sg:province":"Bayern",
    "wof:name":"Seifried Bauten Und Einrichtungen Gmbh",
    "wof:placetype":"venue"
},
  "geometry": {"coordinates":[11.696724,49.917725],"type":"Point"}
}