{
  "type": "Feature",
  "properties": {
    "iso:country":"DE",
    "sg:address":"Sondermayerstr. 6",
    "sg:city":"Weilheim",
    "sg:phone":"+49 881/64946",
    "sg:postcode":"82362",
    "sg:province":"Bayern",
    "wof:name":"Evelyn Huber Top-sun",
    "wof:placetype":"venue"
},
  "geometry": {"coordinates":[11.1493930817,47.83984375],"type":"Point"}
}