{
  "type": "Feature",
  "properties": {
    "iso:country":"DE",
    "sg:address":"Pinkertweg 1",
    "sg:city":"Hamburg",
    "sg:phone":"+49 40/7332060",
    "sg:postcode":"22113",
    "sg:province":"Schleswig-Holstein",
    "wof:name":"Dobbertin Drahthandel Gmbh",
    "wof:placetype":"venue"
},
  "geometry": {"coordinates":[10.0816297531,53.5273933411],"type":"Point"}
}