{
  "type": "Feature",
  "properties": {
    "iso:country":"DE",
    "sg:address":"Treptower Weg 11",
    "sg:city":"Meckenheim",
    "sg:phone":"+49 2225/6698",
    "sg:postcode":"53340",
    "sg:province":"Nordrhein-Westfalen",
    "wof:name":"M. Leupold Makler",
    "wof:placetype":"venue"
},
  "geometry": {"coordinates":[7.0387721062,50.6210136414],"type":"Point"}
}