{
  "type": "Feature",
  "properties": {
    "iso:country":"DE",
    "sg:address":"Fr\u00fchlingstr. 3",
    "sg:city":"Schechen",
    "sg:phone":"+49 8031/85864",
    "sg:postcode":"83135",
    "sg:province":"Bayern",
    "wof:name":"Ush Utility Software Hallbauer Gmbh",
    "wof:placetype":"venue"
},
  "geometry": {"coordinates":[12.120009,47.886597],"type":"Point"}
}