{
  "type": "Feature",
  "properties": {
    "iso:country":"DE",
    "sg:address":"Karl-Friedrich-Str. 3",
    "sg:city":"Emmendingen",
    "sg:phone":"+49 7641/7315",
    "sg:postcode":"79312",
    "sg:province":"Baden-W\u00fcrttemberg",
    "wof:name":"Psycho-soz. Beratungsstelle D. Bad. Landesverbandes",
    "wof:placetype":"venue"
},
  "geometry": {"coordinates":[7.847375,48.12183],"type":"Point"}
}