{
  "type": "Feature",
  "properties": {
    "iso:country":"DE",
    "sg:address":"An der Turnhalle 20",
    "sg:city":"Mainz",
    "sg:phone":"+49 6131/85197",
    "sg:postcode":"55130",
    "sg:province":"Rheinland-Pfalz",
    "wof:name":"Karl R\u00f6sch",
    "wof:placetype":"venue"
},
  "geometry": {"coordinates":[8.2991542816,49.9806098938],"type":"Point"}
}