{
  "type": "Feature",
  "properties": {
    "iso:country":"DE",
    "sg:address":"Marktplatz 11",
    "sg:city":"W\u00e4chtersbach",
    "sg:phone":"+49 6053/1610",
    "sg:postcode":"63607",
    "sg:province":"Hessen",
    "wof:name":"Raumtexstudio Stein & Lieder Gmbh",
    "wof:placetype":"venue"
},
  "geometry": {"coordinates":[9.2869243622,50.2580718994],"type":"Point"}
}