{
  "type": "Feature",
  "properties": {
    "iso:country":"DE",
    "sg:address":"Deutzener Str 73",
    "sg:city":"Borna",
    "sg:phone":"+49 3433/205107",
    "sg:postcode":"04552",
    "sg:province":"Sachsen",
    "wof:name":"Rrb-rekultivierung Und Recycling Borna Gmbh",
    "wof:placetype":"venue"
},
  "geometry": {"coordinates":[12.464073,51.122684],"type":"Point"}
}