{
  "type": "Feature",
  "properties": {
    "iso:country":"DE",
    "sg:address":"Auf der Horst 65-67",
    "sg:city":"Garbsen",
    "sg:phone":"+49 5137/8890",
    "sg:postcode":"30823",
    "sg:province":"Niedersachsen",
    "wof:name":"Karstadt Warenhaus Ag",
    "wof:placetype":"venue"
},
  "geometry": {"coordinates":[9.597424,52.420654],"type":"Point"}
}