{
  "type": "Feature",
  "properties": {
    "iso:country":"DE",
    "sg:address":"Pferseer Str. 23",
    "sg:city":"Augsburg",
    "sg:phone":"+49 821/541367",
    "sg:postcode":"86150",
    "sg:province":"Bayern",
    "wof:name":"Matratzen- Concord Verwaltung S\u00dcd Gmbh",
    "wof:placetype":"venue"
},
  "geometry": {"coordinates":[10.8799800873,48.3652000427],"type":"Point"}
}