{
  "type": "Feature",
  "properties": {
    "iso:country":"DE",
    "sg:address":"Hauptstr. 2",
    "sg:city":"\u00dchlingen-Birkendorf",
    "sg:phone":"+49 7743/1596",
    "sg:postcode":"79777",
    "sg:province":"Baden-W\u00fcrttemberg",
    "wof:name":"Waldemar D\u00fcrr",
    "wof:placetype":"venue"
},
  "geometry": {"coordinates":[8.3183002472,47.722026825],"type":"Point"}
}