{
  "type": "Feature",
  "properties": {
    "iso:country":"DE",
    "sg:address":"Goethestr. 4",
    "sg:city":"Pulsnitz",
    "sg:phone":"+49 35955/72974",
    "sg:postcode":"01896",
    "sg:province":"Sachsen",
    "wof:name":"Lincke Leonhardt & Kollegen Steuerberatungsges. Mbh",
    "wof:placetype":"venue"
},
  "geometry": {"coordinates":[14.0141448975,51.1830062866],"type":"Point"}
}