{
  "type": "Feature",
  "properties": {
    "iso:country":"DE",
    "sg:address":"Brahmsallee 77",
    "sg:city":"Hamburg",
    "sg:phone":"+49 40/4208629",
    "sg:postcode":"20144",
    "sg:province":"Hamburg",
    "wof:name":"Wolf-hinrich Groeneveld Journalist",
    "wof:placetype":"venue"
},
  "geometry": {"coordinates":[9.9813308716,53.5778656006],"type":"Point"}
}