{
  "type": "Feature",
  "properties": {
    "iso:country":"DE",
    "sg:address":"Hauptstr. 22",
    "sg:city":"Winterbach",
    "sg:phone":"+49 7181/481645",
    "sg:postcode":"73650",
    "sg:province":"Baden-W\u00fcrttemberg",
    "wof:name":"Bierb\u00f6rse",
    "wof:placetype":"venue"
},
  "geometry": {"coordinates":[9.4797315598,48.8017425537],"type":"Point"}
}