{
  "type": "Feature",
  "properties": {
    "iso:country":"DE",
    "sg:address":"Schillerstr. 16",
    "sg:city":"Kronberg",
    "sg:phone":"+49 6173/79516",
    "sg:postcode":"61476",
    "sg:province":"Hessen",
    "wof:name":"Hans-dieter Heeb Steuerberater",
    "wof:placetype":"venue"
},
  "geometry": {"coordinates":[8.5164728165,50.1824989319],"type":"Point"}
}