{
  "type": "Feature",
  "properties": {
    "iso:country":"DE",
    "sg:address":"Friedhofstr. 37",
    "sg:city":"Osburg",
    "sg:phone":"+49 6500/7279",
    "sg:postcode":"54317",
    "sg:province":"Rheinland-Pfalz",
    "wof:name":"Michael Rosenkr\u00e4nzer",
    "wof:placetype":"venue"
},
  "geometry": {"coordinates":[6.793235,49.714046],"type":"Point"}
}