{
  "type": "Feature",
  "properties": {
    "iso:country":"DE",
    "sg:address":"Rote-Kreuz-Str. 6-8",
    "sg:city":"Hammelburg",
    "sg:phone":"+49 9732/4063",
    "sg:postcode":"97762",
    "sg:province":"Bayern",
    "wof:name":"Brauerei Salch Gmbh",
    "wof:placetype":"venue"
},
  "geometry": {"coordinates":[9.893588,50.11655],"type":"Point"}
}