{
  "type": "Feature",
  "properties": {
    "iso:country":"DE",
    "sg:address":"Elisenstr. 64",
    "sg:city":"K\u00f6ln",
    "sg:phone":"+49 2203/13444",
    "sg:postcode":"51149",
    "sg:province":"Nordrhein-Westfalen",
    "wof:name":"Christoph Schmitz Architekt",
    "wof:placetype":"venue"
},
  "geometry": {"coordinates":[7.033347,50.900562],"type":"Point"}
}