{
  "type": "Feature",
  "properties": {
    "iso:country":"DE",
    "sg:address":"Theoderichstr. 34",
    "sg:city":"Neuffen",
    "sg:phone":"+49 7025/7441",
    "sg:postcode":"72639",
    "sg:province":"Baden-W\u00fcrttemberg",
    "wof:name":"Z. Yildirim",
    "wof:placetype":"venue"
},
  "geometry": {"coordinates":[9.3770465851,48.5593948364],"type":"Point"}
}