{
  "type": "Feature",
  "properties": {
    "iso:country":"DE",
    "sg:address":"Hauptstr. 29",
    "sg:city":"Ronnenberg",
    "sg:phone":"+49 5109/2062",
    "sg:postcode":"30952",
    "sg:province":"Niedersachsen",
    "wof:name":"Fritz Ehlers",
    "wof:placetype":"venue"
},
  "geometry": {"coordinates":[9.63323,52.29023],"type":"Point"}
}