{
  "type": "Feature",
  "properties": {
    "iso:country":"DE",
    "sg:address":"Korallusstr. 3 b",
    "sg:city":"Hamburg",
    "sg:phone":"+49 40/7545258",
    "sg:postcode":"21109",
    "sg:province":"Hamburg",
    "wof:name":"Britta Beck Massagepraxis",
    "wof:placetype":"venue"
},
  "geometry": {"coordinates":[10.010878,53.502312],"type":"Point"}
}