{
  "type": "Feature",
  "properties": {
    "iso:country":"DE",
    "sg:address":"Barbarossastr. 1",
    "sg:city":"Wiesbaden",
    "sg:phone":"+49 611/718077",
    "sg:postcode":"65205",
    "sg:province":"Hessen",
    "wof:name":"Immobilien Erbenheim Eg",
    "wof:placetype":"venue"
},
  "geometry": {"coordinates":[8.30436,50.053139],"type":"Point"}
}