{
  "type": "Feature",
  "properties": {
    "iso:country":"DE",
    "sg:address":"Dr. R-Friedrichs-Str 4",
    "sg:city":"Radeberg",
    "sg:phone":"+49 3528/441110",
    "sg:postcode":"01454",
    "sg:province":"Sachsen",
    "wof:name":"Autofit Kfz Werkstatt Gabel Automobile Gmbh",
    "wof:placetype":"venue"
},
  "geometry": {"coordinates":[13.9141483307,51.1254959106],"type":"Point"}
}