{
  "type": "Feature",
  "properties": {
    "iso:country":"DE",
    "sg:address":"Rigwinstr. 33",
    "sg:city":"Dortmund",
    "sg:phone":"+49 231/528637",
    "sg:postcode":"44359",
    "sg:province":"Nordrhein-Westfalen",
    "wof:name":"Restaurant Pizzeria Vallo Del Cigno",
    "wof:placetype":"venue"
},
  "geometry": {"coordinates":[7.3827748299,51.5706748962],"type":"Point"}
}