{
  "type": "Feature",
  "properties": {
    "iso:country":"DE",
    "sg:address":"Stettiner Str. 1",
    "sg:city":"Neuburg",
    "sg:phone":"+49 8431/8695",
    "sg:postcode":"86633",
    "sg:province":"Bayern",
    "wof:name":"Anton Schmaus",
    "wof:placetype":"venue"
},
  "geometry": {"coordinates":[8.2621965408,48.9655723572],"type":"Point"}
}