{
  "type": "Feature",
  "properties": {
    "iso:country":"DE",
    "sg:address":"Burgstall 11",
    "sg:city":"Hochstadt",
    "sg:phone":"+49 9574/1383",
    "sg:postcode":"96272",
    "sg:province":"Bayern",
    "wof:name":"Hans Leikeim",
    "wof:placetype":"venue"
},
  "geometry": {"coordinates":[11.197906,50.148769],"type":"Point"}
}