{
  "type": "Feature",
  "properties": {
    "iso:country":"DE",
    "sg:address":"Hauptstr. 23",
    "sg:city":"Gol\u00dfen",
    "sg:phone":"+49 35452/739",
    "sg:postcode":"15938",
    "sg:province":"Brandenburg",
    "wof:name":"Walter Winter",
    "wof:placetype":"venue"
},
  "geometry": {"coordinates":[13.606088,51.970131],"type":"Point"}
}