{
  "type": "Feature",
  "properties": {
    "iso:country":"DE",
    "sg:address":"Bitscher Str.",
    "sg:city":"Hornbach",
    "sg:phone":"+49 6338/1264",
    "sg:postcode":"66500",
    "sg:province":"Rheinland-Pfalz",
    "wof:name":"Hermann K\u00fchn",
    "wof:placetype":"venue"
},
  "geometry": {"coordinates":[7.369629,49.182735],"type":"Point"}
}