{
  "type": "Feature",
  "properties": {
    "iso:country":"DE",
    "sg:address":"Stra\u00dfe der Einheit 9",
    "sg:city":"Bad Langensalza",
    "sg:phone":"+49 3603/842249",
    "sg:postcode":"99947",
    "sg:province":"Th\u00fcringen",
    "wof:name":"Christel Galek",
    "wof:placetype":"venue"
},
  "geometry": {"coordinates":[10.630649,51.101688],"type":"Point"}
}