{
  "type": "Feature",
  "properties": {
    "iso:country":"DE",
    "sg:address":"Bonifaciusstr. 236",
    "sg:city":"Essen",
    "sg:phone":"+49 201",
    "sg:postcode":"45309",
    "sg:province":"Nordrhein-Westfalen",
    "wof:name":"Babytraeume-\u00f6kologisch,nat\u00fcrlich,sch\u00f6n",
    "wof:placetype":"venue"
},
  "geometry": {"coordinates":[7.0811681747,51.4750518799],"type":"Point"}
}