{
  "type": "Feature",
  "properties": {
    "iso:country":"DE",
    "sg:address":"Marktpl. 6",
    "sg:city":"Reutlingen",
    "sg:phone":"+49 4971/213310",
    "sg:postcode":"72764",
    "sg:province":"Baden-W\u00fcrttemberg",
    "wof:name":"Kreissparkasse Reutlingen",
    "wof:placetype":"venue"
},
  "geometry": {"coordinates":[9.211144,48.49202],"type":"Point"}
}