{
  "type": "Feature",
  "properties": {
    "iso:country":"DE",
    "sg:address":"Frankreichstr. 5",
    "sg:city":"Merzig",
    "sg:phone":"+49 6861/6373",
    "sg:postcode":"66663",
    "sg:province":"Saarland",
    "wof:name":"Manfred Enkirch Architekt",
    "wof:placetype":"venue"
},
  "geometry": {"coordinates":[6.611834,49.433361],"type":"Point"}
}