{
  "type": "Feature",
  "properties": {
    "iso:country":"DE",
    "sg:city":"Kaarst/B\u00fcttgen",
    "sg:postcode":"41564",
    "sg:province":"Nordrhein-Westfalen",
    "wof:name":"Thinius Yachtcharter",
    "wof:placetype":"venue"
},
  "geometry": {"coordinates":[6.61709,51.230385],"type":"Point"}
}