{
  "type": "Feature",
  "properties": {
    "iso:country":"DE",
    "sg:address":"N\u00fcrnberger Str. 15",
    "sg:city":"Frankenthal",
    "sg:phone":"+49 6233/21784",
    "sg:postcode":"67227",
    "sg:province":"Rheinland-Pfalz",
    "wof:name":"Lothar Wittmann Gmbh",
    "wof:placetype":"venue"
},
  "geometry": {"coordinates":[8.3574800491,49.5346336365],"type":"Point"}
}