{
  "type": "Feature",
  "properties": {
    "iso:country":"DE",
    "sg:address":"Niederm\u00fcnchsdorf",
    "sg:city":"Osterhofen",
    "sg:phone":"+49 9932/4679",
    "sg:postcode":"94486",
    "sg:province":"Bayern",
    "wof:name":"J. Eckl",
    "wof:placetype":"venue"
},
  "geometry": {"coordinates":[13.0003681183,48.7171096802],"type":"Point"}
}