{
  "type": "Feature",
  "properties": {
    "iso:country":"DE",
    "sg:address":"Burgstr. 2",
    "sg:city":"Sankt Augustin",
    "sg:phone":"+49 2241/313142",
    "sg:postcode":"53757",
    "sg:province":"Nordrhein-Westfalen",
    "wof:name":"K. W. Seeberger",
    "wof:placetype":"venue"
},
  "geometry": {"coordinates":[7.165407,50.789982],"type":"Point"}
}