{
  "type": "Feature",
  "properties": {
    "iso:country":"DE",
    "sg:address":"Berliner Ring 40",
    "sg:city":"Rastatt",
    "sg:phone":"+49 7222/53005",
    "sg:postcode":"76437",
    "sg:province":"Baden-W\u00fcrttemberg",
    "wof:name":"Kastner-praxisbedarf Gmbh",
    "wof:placetype":"venue"
},
  "geometry": {"coordinates":[8.229699,48.859528],"type":"Point"}
}