{
  "type": "Feature",
  "properties": {
    "iso:country":"DE",
    "sg:address":"Grunewaldstr. 11",
    "sg:city":"Berlin",
    "sg:postcode":"12165",
    "sg:province":"Berlin",
    "wof:name":"W & S Dorfaue Vehlefanz Gmbh & Co. Kg",
    "wof:placetype":"venue"
},
  "geometry": {"coordinates":[13.316103,52.458748],"type":"Point"}
}