{
  "type": "Feature",
  "properties": {
    "iso:country":"DE",
    "sg:address":"Langer Weg 25",
    "sg:city":"G\u00fctersloh",
    "sg:phone":"+49 5241/13004",
    "sg:postcode":"33332",
    "sg:province":"Nordrhein-Westfalen",
    "wof:name":"Deutsche Bahn Ag",
    "wof:placetype":"venue"
},
  "geometry": {"coordinates":[8.3913650513,51.9095306396],"type":"Point"}
}