{
  "type": "Feature",
  "properties": {
    "iso:country":"DE",
    "sg:address":"Hofwiesenweg 17",
    "sg:city":"Alsfeld",
    "sg:phone":"+49 6631/2506",
    "sg:postcode":"36304",
    "sg:province":"Hessen",
    "wof:name":"Otto Halfter",
    "wof:placetype":"venue"
},
  "geometry": {"coordinates":[9.274348259,50.7479324341],"type":"Point"}
}