{
  "type": "Feature",
  "properties": {
    "iso:country":"DE",
    "sg:address":"Leipziger Str. 40",
    "sg:city":"B\u00f6hlen",
    "sg:phone":"+49 34206/54080",
    "sg:postcode":"04564",
    "sg:province":"Sachsen",
    "wof:name":"Kulturraumorchester Leipziger Raum Ggmbh",
    "wof:placetype":"venue"
},
  "geometry": {"coordinates":[12.3858251572,51.2093276978],"type":"Point"}
}