{
  "type": "Feature",
  "properties": {
    "iso:country":"DE",
    "sg:address":"Hauptstr. 18",
    "sg:city":"Wieseth",
    "sg:phone":"+49 9822/7411",
    "sg:postcode":"91632",
    "sg:province":"Bayern",
    "wof:name":"Brauerei Fischer Gmbh & Co. Kg",
    "wof:placetype":"venue"
},
  "geometry": {"coordinates":[10.484451,49.16272],"type":"Point"}
}