{
  "type": "Feature",
  "properties": {
    "iso:country":"DE",
    "sg:address":"Auf den Erlen 75",
    "sg:city":"Wiesbaden",
    "sg:phone":"+49 6127/66671",
    "sg:postcode":"65207",
    "sg:province":"Hessen",
    "wof:name":"Ralf Baumann Ingenieur",
    "wof:placetype":"venue"
},
  "geometry": {"coordinates":[8.3304023743,50.1186676025],"type":"Point"}
}