{
  "type": "Feature",
  "properties": {
    "iso:country":"DE",
    "sg:address":"Hauptstr. 6",
    "sg:city":"Neu Zauche",
    "sg:phone":"+49 35475/686",
    "sg:postcode":"15913",
    "sg:province":"Brandenburg",
    "wof:name":"Hans-joachim Janetzki",
    "wof:placetype":"venue"
},
  "geometry": {"coordinates":[14.089616,51.925873],"type":"Point"}
}