{
  "type": "Feature",
  "properties": {
    "iso:country":"DE",
    "sg:address":"Im Grunde 6",
    "sg:city":"Barsinghausen",
    "sg:phone":"+49 5105/4620",
    "sg:postcode":"30890",
    "sg:province":"Niedersachsen",
    "wof:name":"F. B\u00f6deker",
    "wof:placetype":"venue"
},
  "geometry": {"coordinates":[9.4317684174,52.316028595],"type":"Point"}
}