{
  "type": "Feature",
  "properties": {
    "iso:country":"DE",
    "sg:address":"Harthauser Str. 31",
    "sg:city":"Veringenstadt",
    "sg:phone":"+49 7577/3218",
    "sg:postcode":"72519",
    "sg:province":"Baden-W\u00fcrttemberg",
    "wof:name":"Josef Fink",
    "wof:placetype":"venue"
},
  "geometry": {"coordinates":[9.206062,48.181767],"type":"Point"}
}