{
  "type": "Feature",
  "properties": {
    "iso:country":"DE",
    "sg:address":"Wilhelm-Maybach-Str. 6",
    "sg:city":"Ellwangen",
    "sg:phone":"+49 7961/566105",
    "sg:postcode":"73479",
    "sg:province":"Baden-W\u00fcrttemberg",
    "wof:name":"Zink-technik Besitz Gmbh",
    "wof:placetype":"venue"
},
  "geometry": {"coordinates":[10.178195,48.957684],"type":"Point"}
}