{
  "type": "Feature",
  "properties": {
    "iso:country":"DE",
    "sg:address":"Trobischstr. 10",
    "sg:city":"Dresden",
    "sg:postcode":"01129",
    "sg:province":"Sachsen",
    "wof:name":"Dr. Med. Walter Hornig",
    "wof:placetype":"venue"
},
  "geometry": {"coordinates":[13.709481,51.093773],"type":"Point"}
}