{
  "type": "Feature",
  "properties": {
    "iso:country":"DE",
    "sg:address":"Saarlandstr. 64",
    "sg:city":"Bingen",
    "sg:phone":"+49 6721/2876",
    "sg:postcode":"55411",
    "sg:province":"Rheinland-Pfalz",
    "wof:name":"Lutec Grastronomie Service R. D. Lutz",
    "wof:placetype":"venue"
},
  "geometry": {"coordinates":[7.899753,49.953659],"type":"Point"}
}