{
  "type": "Feature",
  "properties": {
    "iso:country":"DE",
    "sg:address":"Ingeborg-Bachmann-Str. 15",
    "sg:city":"Beckum",
    "sg:phone":"+49 2521/823130",
    "sg:postcode":"59269",
    "sg:province":"Nordrhein-Westfalen",
    "wof:name":"Mallorca-finca-service.de",
    "wof:placetype":"venue"
},
  "geometry": {"coordinates":[8.059526,51.748016],"type":"Point"}
}