{
  "type": "Feature",
  "properties": {
    "iso:country":"DE",
    "sg:address":"Hauptstr.",
    "sg:city":"Meckenbach",
    "sg:phone":"+49 6752/2781",
    "sg:postcode":"55606",
    "sg:province":"Rheinland-Pfalz",
    "wof:name":"Ev. Pfarramt Meckenbach",
    "wof:placetype":"venue"
},
  "geometry": {"coordinates":[7.506480217,49.7779045105],"type":"Point"}
}