{
  "type": "Feature",
  "properties": {
    "iso:country":"DE",
    "sg:address":"Rechbergweg 14/1",
    "sg:city":"Dettingen",
    "sg:postcode":"88451",
    "sg:province":"Baden-W\u00fcrttemberg",
    "wof:name":"Thomas Rabenstein Ingenieurb\u00fcro",
    "wof:placetype":"venue"
},
  "geometry": {"coordinates":[10.11046,48.102509],"type":"Point"}
}