{
  "type": "Feature",
  "properties": {
    "iso:country":"DE",
    "sg:address":"Gottschalkstr. 10",
    "sg:city":"Kassel",
    "sg:phone":"+49 561/84068",
    "sg:postcode":"34127",
    "sg:province":"Hessen",
    "wof:name":"Winfried Hauffe",
    "wof:placetype":"venue"
},
  "geometry": {"coordinates":[9.503827095,51.3235168457],"type":"Point"}
}