{
  "type": "Feature",
  "properties": {
    "iso:country":"DE",
    "sg:address":"Kurf\u00fcrstenstr. 73",
    "sg:city":"Bocholt",
    "sg:phone":"+49 2871/222908",
    "sg:postcode":"46399",
    "sg:province":"Nordrhein-Westfalen",
    "wof:name":"Willkommen Bei Eiting Computer",
    "wof:placetype":"venue"
},
  "geometry": {"coordinates":[6.605306,51.840714],"type":"Point"}
}