{
  "type": "Feature",
  "properties": {
    "iso:country":"DE",
    "sg:address":"Flurstr. 32",
    "sg:city":"Freiburg",
    "sg:phone":"+49 761/84923",
    "sg:postcode":"79114",
    "sg:province":"Baden-W\u00fcrttemberg",
    "wof:name":"Bella-club Freiburg I. Br. Heinz Acker",
    "wof:placetype":"venue"
},
  "geometry": {"coordinates":[7.8227319717,48.0058135986],"type":"Point"}
}