{
  "type": "Feature",
  "properties": {
    "iso:country":"DE",
    "sg:address":"B\u00fcchnerweg 4",
    "sg:city":"Friedberg",
    "sg:phone":"+49 6031/13900",
    "sg:postcode":"61169",
    "sg:province":"Hessen",
    "wof:name":"Edgar Jost Steuerberater",
    "wof:placetype":"venue"
},
  "geometry": {"coordinates":[8.7409582138,50.3326301575],"type":"Point"}
}