{
  "type": "Feature",
  "properties": {
    "iso:country":"DE",
    "sg:address":"An der Schule 12",
    "sg:city":"R\u00fchen",
    "sg:phone":"+49 5367/1869",
    "sg:postcode":"38471",
    "sg:province":"Niedersachsen",
    "wof:name":"Helmut M\u00fcller",
    "wof:placetype":"venue"
},
  "geometry": {"coordinates":[10.891187,52.486626],"type":"Point"}
}