{
  "type": "Feature",
  "properties": {
    "iso:country":"DE",
    "sg:address":"Leite 64",
    "sg:city":"Kleinmachnow",
    "sg:phone":"+49 3329/612161",
    "sg:postcode":"14532",
    "sg:province":"Brandenburg",
    "wof:name":"Mp Treuhand Steuerberatungs Gmbh",
    "wof:placetype":"venue"
},
  "geometry": {"coordinates":[13.2090778351,52.4012565613],"type":"Point"}
}