{
  "type": "Feature",
  "properties": {
    "iso:country":"DE",
    "sg:address":"Moosstr. 14",
    "sg:city":"Tussenhausen",
    "sg:phone":"+49 8268/406",
    "sg:postcode":"86874",
    "sg:province":"Bayern",
    "wof:name":"Karl Immerz",
    "wof:placetype":"venue"
},
  "geometry": {"coordinates":[10.540936,48.09177],"type":"Point"}
}