{
  "type": "Feature",
  "properties": {
    "iso:country":"DE",
    "sg:address":"Rankestr. 7",
    "sg:city":"Berlin",
    "sg:postcode":"10789",
    "sg:province":"Berlin",
    "wof:name":"Gcbs German Contakt Und Business Service Gmbh",
    "wof:placetype":"venue"
},
  "geometry": {"coordinates":[13.333518,52.502537],"type":"Point"}
}