{
  "type": "Feature",
  "properties": {
    "iso:country":"DE",
    "sg:address":"K\u00f6lnstr. 147",
    "sg:city":"Bonn",
    "sg:phone":"+49 228/637214",
    "sg:postcode":"53111",
    "sg:province":"Nordrhein-Westfalen",
    "wof:name":"Willi Kratz",
    "wof:placetype":"venue"
},
  "geometry": {"coordinates":[7.093818,50.742352],"type":"Point"}
}