{
  "type": "Feature",
  "properties": {
    "iso:country":"DE",
    "sg:address":"Am Markt 8",
    "sg:city":"Wittmund",
    "sg:phone":"+49 4462/4015",
    "sg:postcode":"26409",
    "sg:province":"Niedersachsen",
    "wof:name":"Gisela Gottwald-bruns Krankengymnastin",
    "wof:placetype":"venue"
},
  "geometry": {"coordinates":[7.783395,53.575195],"type":"Point"}
}