{
  "type": "Feature",
  "properties": {
    "iso:country":"DE",
    "sg:address":"Dorfstr. 37",
    "sg:city":"Hartmannsdorf",
    "sg:phone":"+49 37602/6357",
    "sg:postcode":"08107",
    "sg:province":"Sachsen",
    "wof:name":"Pension Christian Flechsig",
    "wof:placetype":"venue"
},
  "geometry": {"coordinates":[12.5454063416,50.5984573364],"type":"Point"}
}