{
  "type": "Feature",
  "properties": {
    "iso:country":"DE",
    "sg:address":"Im Geiger 65",
    "sg:city":"Stuttgart",
    "sg:phone":"+49 711/524376",
    "sg:postcode":"70374",
    "sg:province":"Baden-W\u00fcrttemberg",
    "wof:name":"Frank Joos Architekt",
    "wof:placetype":"venue"
},
  "geometry": {"coordinates":[9.244534,48.807182],"type":"Point"}
}