{
  "type": "Feature",
  "properties": {
    "iso:country":"DE",
    "sg:address":"Postfach 10 28 20:: 69018 Heidelberg:: Germany.^^Kurfuerstenanlage 8::",
    "sg:city":"Heidelberg",
    "sg:phone":"+49 7321/20148",
    "sg:postcode":"69115",
    "sg:province":"Baden-W\u00fcrttemberg",
    "wof:name":"Heidenheimer Treuhand Gmbh",
    "wof:placetype":"venue"
},
  "geometry": {"coordinates":[10.152089,48.679138],"type":"Point"}
}