{
  "type": "Feature",
  "properties": {
    "iso:country":"DE",
    "sg:address":"Uferstr. 6",
    "sg:city":"Halle",
    "sg:phone":"+49 345/5511930",
    "sg:postcode":"06120",
    "sg:province":"Sachsen-Anhalt",
    "wof:name":"Reiterhof Schurig",
    "wof:placetype":"venue"
},
  "geometry": {"coordinates":[11.9087638855,51.5280685425],"type":"Point"}
}