{
  "type": "Feature",
  "properties": {
    "iso:country":"DE",
    "sg:address":"Br\u00fcckenauer Str. 50",
    "sg:city":"Schondra",
    "sg:phone":"+49 9747/888",
    "sg:postcode":"97795",
    "sg:province":"Bayern",
    "wof:name":"Karl M\u00fcller Kranvermietung Gmbh",
    "wof:placetype":"venue"
},
  "geometry": {"coordinates":[9.8575601578,50.2691307068],"type":"Point"}
}