{
  "type": "Feature",
  "properties": {
    "iso:country":"DE",
    "sg:address":"Dorfstrasse 13",
    "sg:city":"Aachen",
    "sg:phone":"+49 2408/59213",
    "sg:postcode":"52076",
    "sg:province":"Nordrhein-Westfalen",
    "wof:name":"Tintenpatronen Und Mehr, Www.gagacomp.de",
    "wof:placetype":"venue"
},
  "geometry": {"coordinates":[6.19847,50.709782],"type":"Point"}
}