{
  "type": "Feature",
  "properties": {
    "iso:country":"DE",
    "sg:address":"Gartnischer Weg 170",
    "sg:city":"Halle",
    "sg:phone":"+49 5201/87120",
    "sg:postcode":"33790",
    "sg:province":"Nordrhein-Westfalen",
    "wof:name":"Raiffeisen Warenhandel Gmbh & Co. Kg",
    "wof:placetype":"venue"
},
  "geometry": {"coordinates":[8.379991,52.043304],"type":"Point"}
}