{
  "type": "Feature",
  "properties": {
    "iso:country":"DE",
    "sg:address":"Leopoldstr. 81",
    "sg:city":"M\u00fcnchen",
    "sg:phone":"+49 89/347047",
    "sg:postcode":"80802",
    "sg:province":"Bayern",
    "wof:name":"Dr. Nierhaus Und Partner Gmbh",
    "wof:placetype":"venue"
},
  "geometry": {"coordinates":[11.5860691071,48.1631622314],"type":"Point"}
}