{
  "type": "Feature",
  "properties": {
    "iso:country":"DE",
    "sg:address":"Eichendorffstr. 30",
    "sg:city":"N\u00fcrnberg",
    "sg:phone":"+49 911/593740",
    "sg:postcode":"90491",
    "sg:province":"Bayern",
    "wof:name":"G\u00fcnter E. Schneider Immobilienmakler",
    "wof:placetype":"venue"
},
  "geometry": {"coordinates":[11.1310930252,49.4736595154],"type":"Point"}
}