{
  "type": "Feature",
  "properties": {
    "iso:country":"DE",
    "sg:address":"Hauptstr. 23",
    "sg:city":"Binzen",
    "sg:phone":"+49 7621/64790",
    "sg:postcode":"79589",
    "sg:province":"Baden-W\u00fcrttemberg",
    "wof:name":"Dieter Schweigler",
    "wof:placetype":"venue"
},
  "geometry": {"coordinates":[7.6222419739,47.631111145],"type":"Point"}
}