{
  "type": "Feature",
  "properties": {
    "iso:country":"DE",
    "sg:address":"Travem\u00fcnder Landstr. 304",
    "sg:city":"L\u00fcbeck",
    "sg:phone":"+49 4502/5051",
    "sg:postcode":"23570",
    "sg:province":"Schleswig-Holstein",
    "wof:name":"B\u00f6bs-werft Gmbh",
    "wof:placetype":"venue"
},
  "geometry": {"coordinates":[10.8338127136,53.932144165],"type":"Point"}
}