{
  "type": "Feature",
  "properties": {
    "iso:country":"DE",
    "sg:address":"Joachimstaler Str. 1",
    "sg:city":"Berlin",
    "sg:phone":"+49 30/8815520",
    "sg:postcode":"10623",
    "sg:province":"Berlin",
    "wof:name":"Hans-joachim Hau\u00dfner",
    "wof:placetype":"venue"
},
  "geometry": {"coordinates":[13.331861,52.506065],"type":"Point"}
}