{
  "type": "Feature",
  "properties": {
    "iso:country":"DE",
    "sg:address":"Rathausstr. 21",
    "sg:city":"Idstein",
    "sg:phone":"+49 6126/70656",
    "sg:postcode":"65510",
    "sg:province":"Hessen",
    "wof:name":"Gerhard Heil",
    "wof:placetype":"venue"
},
  "geometry": {"coordinates":[8.2410182953,50.1892127991],"type":"Point"}
}