{
  "type": "Feature",
  "properties": {
    "iso:country":"DE",
    "sg:address":"Arsterdamm 100A",
    "sg:city":"Bremen",
    "sg:phone":"+49 421/873514",
    "sg:postcode":"28277",
    "sg:province":"Bremen",
    "wof:name":"Arster-spedition German Bollmann Gmbh",
    "wof:placetype":"venue"
},
  "geometry": {"coordinates":[8.8319272995,53.0406455994],"type":"Point"}
}