{
  "type": "Feature",
  "properties": {
    "iso:country":"DE",
    "sg:address":"Weiner 291",
    "sg:city":"Ochtrup",
    "sg:phone":"+49 2553/98620",
    "sg:postcode":"48607",
    "sg:province":"Nordrhein-Westfalen",
    "wof:name":"M. H\u00f6lscher-b\u00f6king Obstanbau",
    "wof:placetype":"venue"
},
  "geometry": {"coordinates":[7.1593980789,52.2040138245],"type":"Point"}
}