{
  "type": "Feature",
  "properties": {
    "iso:country":"DE",
    "sg:address":"Parsevalstr. 4",
    "sg:city":"Hamm",
    "sg:phone":"+49 2381/599369",
    "sg:postcode":"59075",
    "sg:province":"Nordrhein-Westfalen",
    "wof:name":"Manuela Und Danny Lubawinski",
    "wof:placetype":"venue"
},
  "geometry": {"coordinates":[7.75409,51.689617],"type":"Point"}
}