{
  "type": "Feature",
  "properties": {
    "iso:country":"DE",
    "sg:address":"Hanauer Str. 12",
    "sg:city":"Rodalben",
    "sg:phone":"+49 6331/10522",
    "sg:postcode":"66976",
    "sg:province":"Rheinland-Pfalz",
    "wof:name":"Hilmar Haas Architekt",
    "wof:placetype":"venue"
},
  "geometry": {"coordinates":[7.66275,49.230511],"type":"Point"}
}