{
  "type": "Feature",
  "properties": {
    "iso:country":"DE",
    "sg:address":"Altmarkstr. 35",
    "sg:city":"Braunschweig",
    "sg:phone":"+49 5307/6815",
    "sg:postcode":"38110",
    "sg:province":"Niedersachsen",
    "wof:name":"Edith May",
    "wof:placetype":"venue"
},
  "geometry": {"coordinates":[10.526664,52.318054],"type":"Point"}
}