{
  "type": "Feature",
  "properties": {
    "iso:country":"DE",
    "sg:address":"M\u00fcllheimer Str. 31",
    "sg:city":"Neuenburg",
    "sg:phone":"+49 7631/72487",
    "sg:postcode":"79395",
    "sg:province":"Baden-W\u00fcrttemberg",
    "wof:name":"Urban Saurer",
    "wof:placetype":"venue"
},
  "geometry": {"coordinates":[7.567932,47.812378],"type":"Point"}
}