{
  "type": "Feature",
  "properties": {
    "iso:country":"DE",
    "sg:address":"Schubertstr. 27",
    "sg:city":"Frankfurt",
    "sg:postcode":"60325",
    "sg:province":"Hessen",
    "wof:name":"Hpm Beteiligungsges. Mbh",
    "wof:placetype":"venue"
},
  "geometry": {"coordinates":[8.656819,50.11779],"type":"Point"}
}