{
  "type": "Feature",
  "properties": {
    "iso:country":"DE",
    "sg:address":"Am Wasserberg 11",
    "sg:city":"Zusmarshausen",
    "sg:phone":"+49 8291/18960",
    "sg:postcode":"86441",
    "sg:province":"Bayern",
    "wof:name":"Goldham Pharma Gmbh",
    "wof:placetype":"venue"
},
  "geometry": {"coordinates":[10.6048078537,48.4042015076],"type":"Point"}
}