{
  "type": "Feature",
  "properties": {
    "iso:country":"DE",
    "sg:address":"L\u00fcneburger Str.",
    "sg:city":"Winsen",
    "sg:phone":"+49 4171/73890",
    "sg:postcode":"21423",
    "sg:province":"Niedersachsen",
    "wof:name":"Rundt",
    "wof:placetype":"venue"
},
  "geometry": {"coordinates":[10.209155,53.355499],"type":"Point"}
}