{
  "type": "Feature",
  "properties": {
    "iso:country":"DE",
    "sg:address":"Veer\u00dfer Str. 64",
    "sg:city":"Uelzen",
    "sg:phone":"+49 581/14445",
    "sg:postcode":"29525",
    "sg:province":"Niedersachsen",
    "wof:name":"Ernst-peter K\u00f6ster Rechtsanwalt",
    "wof:placetype":"venue"
},
  "geometry": {"coordinates":[10.5561704636,52.9608573914],"type":"Point"}
}