{
  "type": "Feature",
  "properties": {
    "iso:country":"DE",
    "sg:address":"Alte Pallinger Str. 10",
    "sg:city":"Trostberg",
    "sg:phone":"+49 8621/7870",
    "sg:postcode":"83308",
    "sg:province":"Bayern",
    "wof:name":"Waldbesitzervereinigung Traunstein E. V.",
    "wof:placetype":"venue"
},
  "geometry": {"coordinates":[12.5594358444,48.0251541138],"type":"Point"}
}