{
  "type": "Feature",
  "properties": {
    "iso:country":"DE",
    "sg:address":"N\u00f6rdlinger Str. 6",
    "sg:city":"Heilbronn",
    "sg:phone":"+49 7131/173455",
    "sg:postcode":"74074",
    "sg:province":"Baden-W\u00fcrttemberg",
    "wof:name":"Hans Russ Architekt",
    "wof:placetype":"venue"
},
  "geometry": {"coordinates":[9.236548,49.130974],"type":"Point"}
}