{
  "type": "Feature",
  "properties": {
    "iso:country":"DE",
    "sg:address":"Hauptstr. 15",
    "sg:city":"Bokel",
    "sg:phone":"+49 4748/2276",
    "sg:postcode":"27616",
    "sg:province":"Niedersachsen",
    "wof:name":"Lutz Fels",
    "wof:placetype":"venue"
},
  "geometry": {"coordinates":[8.774974823,53.4016418457],"type":"Point"}
}