{
  "type": "Feature",
  "properties": {
    "iso:country":"DE",
    "sg:address":"Im Heidenfeld 55",
    "sg:city":"Frankfurt",
    "sg:postcode":"60439",
    "sg:province":"Hessen",
    "wof:name":"Malamut Handels-, Werbe- Und",
    "wof:placetype":"venue"
},
  "geometry": {"coordinates":[8.6420469284,50.1539802551],"type":"Point"}
}