{
  "type": "Feature",
  "properties": {
    "iso:country":"DE",
    "sg:address":"Hauptstr. 61",
    "sg:city":"Ebensfeld",
    "sg:phone":"+49 9573/5120",
    "sg:postcode":"96250",
    "sg:province":"Bayern",
    "wof:name":"Georg Jung",
    "wof:placetype":"venue"
},
  "geometry": {"coordinates":[10.959546,50.067703],"type":"Point"}
}