{
  "type": "Feature",
  "properties": {
    "iso:country":"DE",
    "sg:address":"Frankenstr. 36 a",
    "sg:city":"Birkenwerder",
    "sg:phone":"+49 3303/29370",
    "sg:postcode":"16547",
    "sg:province":"Brandenburg",
    "wof:name":"Ebk Haus Gmbh",
    "wof:placetype":"venue"
},
  "geometry": {"coordinates":[13.270924,52.692974],"type":"Point"}
}