{
  "type": "Feature",
  "properties": {
    "iso:country":"DE",
    "sg:address":"Sonnengasse 6",
    "sg:city":"Heilbronn",
    "sg:phone":"+49 7131/81973",
    "sg:postcode":"74072",
    "sg:province":"Baden-W\u00fcrttemberg",
    "wof:name":"Eisenwaren Waidelich Eisenwaren-beschl\u00e4ge",
    "wof:placetype":"venue"
},
  "geometry": {"coordinates":[9.2213287354,49.1437568665],"type":"Point"}
}