{
  "type": "Feature",
  "properties": {
    "iso:country":"DE",
    "sg:address":"Greschbachstr.",
    "sg:city":"Karlsruhe",
    "sg:phone":"+49 721/612051",
    "sg:postcode":"76229",
    "sg:province":"Baden-W\u00fcrttemberg",
    "wof:name":"Franzels",
    "wof:placetype":"venue"
},
  "geometry": {"coordinates":[8.4744129181,49.03282547],"type":"Point"}
}