{
  "type": "Feature",
  "properties": {
    "iso:country":"DE",
    "sg:address":"Butjadinger Str. 49",
    "sg:city":"Bremen",
    "sg:phone":"+49 421/542127",
    "sg:postcode":"28197",
    "sg:province":"Bremen",
    "wof:name":"Ursula Bauer",
    "wof:placetype":"venue"
},
  "geometry": {"coordinates":[8.764446,53.080856],"type":"Point"}
}