{
  "type": "Feature",
  "properties": {
    "iso:country":"DE",
    "sg:address":"Werdohler Landstr. 350",
    "sg:city":"L\u00fcdenscheid",
    "sg:phone":"+49 2351/12061",
    "sg:postcode":"58513",
    "sg:province":"Nordrhein-Westfalen",
    "wof:name":"Hesmer Gmbh",
    "wof:placetype":"venue"
},
  "geometry": {"coordinates":[7.7165789604,51.2417182922],"type":"Point"}
}