{
  "type": "Feature",
  "properties": {
    "iso:country":"DE",
    "sg:address":"Reinholdstr. 5",
    "sg:city":"Hamburg",
    "sg:postcode":"21073",
    "sg:province":"Hamburg",
    "wof:name":"Pit - Planung & Design Gmbh",
    "wof:placetype":"venue"
},
  "geometry": {"coordinates":[9.986575,53.454498],"type":"Point"}
}