{
  "type": "Feature",
  "properties": {
    "iso:country":"DE",
    "sg:address":"M\u00f6westr. 24",
    "sg:city":"M\u00fcnchen",
    "sg:phone":"+49 89/4306200",
    "sg:postcode":"81827",
    "sg:province":"Bayern",
    "wof:name":"Josef Bischof Architekt",
    "wof:placetype":"venue"
},
  "geometry": {"coordinates":[11.707115,48.102459],"type":"Point"}
}