{
  "type": "Feature",
  "properties": {
    "iso:country":"DE",
    "sg:address":"K\u00e4ferstr. 18",
    "sg:city":"Donaueschingen",
    "sg:phone":"+49 771/80990",
    "sg:postcode":"78166",
    "sg:province":"Baden-W\u00fcrttemberg",
    "wof:name":"Hotel-restaurant Ochsel E. Und A. Kuttrutt",
    "wof:placetype":"venue"
},
  "geometry": {"coordinates":[8.4935035706,47.9519042969],"type":"Point"}
}