{
  "type": "Feature",
  "properties": {
    "iso:country":"DE",
    "sg:address":"Am Alten Kirchenpfad 17",
    "sg:city":"St. Ingbert",
    "sg:phone":"+49 6894/57991",
    "sg:postcode":"66386",
    "sg:province":"Saarland",
    "wof:name":"Hrs Kessler Gmbh",
    "wof:placetype":"venue"
},
  "geometry": {"coordinates":[7.15435,49.284645],"type":"Point"}
}