{
  "type": "Feature",
  "properties": {
    "iso:country":"DE",
    "sg:address":"Marktstr. 8",
    "sg:city":"Neuwied",
    "sg:phone":"+49 2631/27861",
    "sg:postcode":"56564",
    "sg:province":"Rheinland-Pfalz",
    "wof:name":"G. Boy",
    "wof:placetype":"venue"
},
  "geometry": {"coordinates":[7.4569292068,50.4268989563],"type":"Point"}
}