{
  "type": "Feature",
  "properties": {
    "iso:country":"DE",
    "sg:address":"Gutenbergstr. 33-35",
    "sg:city":"Reinbek",
    "sg:phone":"+49 40/728300",
    "sg:postcode":"21465",
    "sg:province":"Schleswig-Holstein",
    "wof:name":"Gebr\u00fcder Wollenhaupt Gmbh",
    "wof:placetype":"venue"
},
  "geometry": {"coordinates":[10.23693,53.528969],"type":"Point"}
}