{
  "type": "Feature",
  "properties": {
    "iso:country":"DE",
    "sg:address":"Kurt-Schumacher-Damm 12",
    "sg:city":"Osnabr\u00fcck",
    "sg:phone":"+49 541/49367",
    "sg:postcode":"49078",
    "sg:province":"Niedersachsen",
    "wof:name":"Aral Auto-center Susanne Pabst",
    "wof:placetype":"venue"
},
  "geometry": {"coordinates":[8.025018,52.270687],"type":"Point"}
}