{
  "type": "Feature",
  "properties": {
    "iso:country":"DE",
    "sg:address":"Waldemardamm 15a",
    "sg:city":"Nauen",
    "sg:postcode":"14641",
    "sg:province":"Brandenburg",
    "wof:name":"Hsg Heizung Sanit\u00e4r Gasanlagen Gmbh",
    "wof:placetype":"venue"
},
  "geometry": {"coordinates":[12.8862991333,52.6109352112],"type":"Point"}
}