{
  "type": "Feature",
  "properties": {
    "iso:country":"DE",
    "sg:address":"Anzengruberstr. 14",
    "sg:city":"Hamburg",
    "sg:postcode":"21079",
    "sg:province":"Hamburg",
    "wof:name":"Bauconsult Bahl Gmbh",
    "wof:placetype":"venue"
},
  "geometry": {"coordinates":[9.989718,53.449806],"type":"Point"}
}