{
  "type": "Feature",
  "properties": {
    "iso:country":"DE",
    "sg:address":"Himbeerweg 2",
    "sg:city":"Bochum",
    "sg:phone":"+49 234/47755",
    "sg:postcode":"44879",
    "sg:province":"Nordrhein-Westfalen",
    "wof:name":"H. H. Und I. Weitzel Steuerberater",
    "wof:placetype":"venue"
},
  "geometry": {"coordinates":[7.1864490509,51.4340553284],"type":"Point"}
}