{
  "type": "Feature",
  "properties": {
    "iso:country":"DE",
    "sg:address":"Wannen\u00e4ckerstr. 57",
    "sg:city":"Heilbronn",
    "sg:phone":"+49 4971/3122616",
    "sg:postcode":"74078",
    "sg:province":"Baden-W\u00fcrttemberg",
    "wof:name":"Seidler Speditions Gmbh",
    "wof:placetype":"venue"
},
  "geometry": {"coordinates":[9.173538208,49.1842689514],"type":"Point"}
}