{
  "type": "Feature",
  "properties": {
    "iso:country":"DE",
    "sg:address":"P\u00fctzgasse 8",
    "sg:city":"Remagen",
    "sg:phone":"+49 2228/271",
    "sg:postcode":"53424",
    "sg:province":"Rheinland-Pfalz",
    "wof:name":"Paul Schneider",
    "wof:placetype":"venue"
},
  "geometry": {"coordinates":[7.2065701485,50.6155700684],"type":"Point"}
}