{
  "type": "Feature",
  "properties": {
    "iso:country":"DE",
    "sg:address":"Wilhelm-Mauser-Str. 41-43",
    "sg:city":"K\u00f6ln",
    "sg:postcode":"50827",
    "sg:province":"Nordrhein-Westfalen",
    "wof:name":"Wonschik Immobilien E. K.",
    "wof:placetype":"venue"
},
  "geometry": {"coordinates":[6.893643856,50.9564399719],"type":"Point"}
}