{
  "type": "Feature",
  "properties": {
    "iso:country":"DE",
    "sg:address":"Im Stock 13",
    "sg:city":"Winsen",
    "sg:phone":"+49 4171/76608",
    "sg:postcode":"21423",
    "sg:province":"Niedersachsen",
    "wof:name":"Wilhelm Meyer",
    "wof:placetype":"venue"
},
  "geometry": {"coordinates":[10.204494,53.358658],"type":"Point"}
}