{
  "type": "Feature",
  "properties": {
    "iso:country":"DE",
    "sg:address":"Zehnthofstr. 10",
    "sg:city":"D\u00fcren",
    "sg:phone":"+49 2421/13692",
    "sg:postcode":"52349",
    "sg:province":"Nordrhein-Westfalen",
    "wof:name":"Optik Lothar Rommelsheim",
    "wof:placetype":"venue"
},
  "geometry": {"coordinates":[6.483189106,50.8032722473],"type":"Point"}
}