{
  "type": "Feature",
  "properties": {
    "iso:country":"DE",
    "sg:address":"Pulvermaarstr. 4",
    "sg:city":"Gillenfeld",
    "sg:phone":"+49 6573/9233",
    "sg:postcode":"54558",
    "sg:province":"Rheinland-Pfalz",
    "wof:name":"H.-peter Riemann",
    "wof:placetype":"venue"
},
  "geometry": {"coordinates":[6.904856,50.127525],"type":"Point"}
}