{
  "type": "Feature",
  "properties": {
    "iso:country":"DE",
    "sg:address":"Vogesenstr. 12",
    "sg:city":"Mannheim",
    "sg:phone":"+49 621/478596",
    "sg:postcode":"68229",
    "sg:province":"Baden-W\u00fcrttemberg",
    "wof:name":"Volker Ziegler",
    "wof:placetype":"venue"
},
  "geometry": {"coordinates":[8.5786819458,49.4420623779],"type":"Point"}
}