{
  "type": "Feature",
  "properties": {
    "iso:country":"DE",
    "sg:address":"Brauersdorfer Str. 16 a",
    "sg:city":"Netphen",
    "sg:phone":"+49 2738/2358",
    "sg:postcode":"57250",
    "sg:province":"Nordrhein-Westfalen",
    "wof:name":"Bernd H. Meyer",
    "wof:placetype":"venue"
},
  "geometry": {"coordinates":[8.111737,50.912006],"type":"Point"}
}