{
  "type": "Feature",
  "properties": {
    "iso:country":"DE",
    "sg:address":"Gottlieb-Daimler-Str. 1",
    "sg:city":"Laudenbach",
    "sg:phone":"+49 6201/71343",
    "sg:postcode":"69514",
    "sg:province":"Baden-W\u00fcrttemberg",
    "wof:name":"Psi Pool Of Scientific Instruments",
    "wof:placetype":"venue"
},
  "geometry": {"coordinates":[8.638151,49.609406],"type":"Point"}
}