{
  "type": "Feature",
  "properties": {
    "iso:country":"DE",
    "sg:address":"Birkenstr. 26",
    "sg:city":"Rottenburg",
    "sg:phone":"+49 7457/8363",
    "sg:postcode":"72108",
    "sg:province":"Baden-W\u00fcrttemberg",
    "wof:name":"Schenker Ag",
    "wof:placetype":"venue"
},
  "geometry": {"coordinates":[8.8700208664,48.5060462952],"type":"Point"}
}