{
  "type": "Feature",
  "properties": {
    "iso:country":"DE",
    "sg:address":"Kirchplatz 6",
    "sg:city":"Bernau",
    "sg:phone":"+49 8051/7352",
    "sg:postcode":"83233",
    "sg:province":"Bayern",
    "wof:name":"St. Laurentius-apotheke",
    "wof:placetype":"venue"
},
  "geometry": {"coordinates":[12.373138,47.812073],"type":"Point"}
}