{
  "type": "Feature",
  "properties": {
    "iso:country":"DE",
    "sg:address":"Bahnhofstr. 2",
    "sg:city":"Bad Wildungen",
    "sg:phone":"+49 5621/3939",
    "sg:postcode":"34537",
    "sg:province":"Hessen",
    "wof:name":"Rosenschl\u00f6\u00dfchen",
    "wof:placetype":"venue"
},
  "geometry": {"coordinates":[9.1273622513,51.1206283569],"type":"Point"}
}