{
  "type": "Feature",
  "properties": {
    "iso:country":"DE",
    "sg:address":"Kurstr. 2",
    "sg:city":"Nidda",
    "sg:phone":"+49 6043/40917",
    "sg:postcode":"63667",
    "sg:province":"Hessen",
    "wof:name":"Restaurant Salinenstube",
    "wof:placetype":"venue"
},
  "geometry": {"coordinates":[8.9819898605,50.4154090881],"type":"Point"}
}