{
  "type": "Feature",
  "properties": {
    "iso:country":"DE",
    "sg:address":"Steinstra\u00dfe 8",
    "sg:city":"Dierdorf",
    "sg:phone":"+49 2689/1003",
    "sg:postcode":"56269",
    "sg:province":"Rheinland-Pfalz",
    "wof:name":"B\u00f6sche-online",
    "wof:placetype":"venue"
},
  "geometry": {"coordinates":[7.6424250603,50.5590553284],"type":"Point"}
}