{
  "type": "Feature",
  "properties": {
    "iso:country":"DE",
    "sg:address":"Gie\u00dfener Str. 45",
    "sg:city":"Lollar",
    "sg:phone":"+49 6406/3347",
    "sg:postcode":"35457",
    "sg:province":"Hessen",
    "wof:name":"R. Gr\u00f6hl-wagner",
    "wof:placetype":"venue"
},
  "geometry": {"coordinates":[8.703182,50.645622],"type":"Point"}
}