{
  "type": "Feature",
  "properties": {
    "iso:country":"DE",
    "sg:address":"Jahnstr. 2",
    "sg:city":"Neunkirchen",
    "sg:phone":"+49 6821/23535",
    "sg:postcode":"66538",
    "sg:province":"Saarland",
    "wof:name":"Vereinslokal Schlo\u00dfbr\u00e4ueck",
    "wof:placetype":"venue"
},
  "geometry": {"coordinates":[7.1939921379,49.3480110168],"type":"Point"}
}