{
  "type": "Feature",
  "properties": {
    "iso:country":"DE",
    "sg:address":"Salinstr. 6",
    "sg:city":"Rosenheim",
    "sg:phone":"+49 8031/32041",
    "sg:postcode":"83022",
    "sg:province":"Bayern",
    "wof:name":"Real-finanzservice- Vermittlungs Gmbh",
    "wof:placetype":"venue"
},
  "geometry": {"coordinates":[12.1230096817,47.8526153564],"type":"Point"}
}