{
  "type": "Feature",
  "properties": {
    "iso:country":"DE",
    "sg:address":"F\u00f6hrenheide",
    "sg:city":"Farchant",
    "sg:phone":"+49 8821/6566",
    "sg:postcode":"82490",
    "sg:province":"Bayern",
    "wof:name":"Sportzentrum-schwimmbad",
    "wof:placetype":"venue"
},
  "geometry": {"coordinates":[11.1200847626,47.5331535339],"type":"Point"}
}