{
  "type": "Feature",
  "properties": {
    "iso:country":"DE",
    "sg:address":"Mahdentalstr. 44",
    "sg:city":"Sindelfingen",
    "sg:phone":"+49 4970/3186770",
    "sg:postcode":"71065",
    "sg:province":"Baden-W\u00fcrttemberg",
    "wof:name":"Kobold Messring Gmbh Werk 2",
    "wof:placetype":"venue"
},
  "geometry": {"coordinates":[9.017181,48.707836],"type":"Point"}
}