{
  "type": "Feature",
  "properties": {
    "iso:country":"DE",
    "sg:address":"Eiswerderstr. 19",
    "sg:city":"Berlin",
    "sg:phone":"+49 30/3355028",
    "sg:postcode":"13585",
    "sg:province":"Berlin",
    "wof:name":"Kl 2000 Klima- Und L\u00fcftungstechnik Gmbh",
    "wof:placetype":"venue"
},
  "geometry": {"coordinates":[13.2200622559,52.5493431091],"type":"Point"}
}