{
  "type": "Feature",
  "properties": {
    "iso:country":"DE",
    "sg:address":"Gie\u00dfener Str. 11",
    "sg:city":"Hungen",
    "sg:phone":"+49 6402/7335",
    "sg:postcode":"35410",
    "sg:province":"Hessen",
    "wof:name":"Anneli Gra\u00df Masseurin",
    "wof:placetype":"venue"
},
  "geometry": {"coordinates":[8.891971,50.476734],"type":"Point"}
}