{
  "type": "Feature",
  "properties": {
    "iso:country":"DE",
    "sg:address":"Eichelsbacher Str. 15",
    "sg:city":"Kleinwallstadt",
    "sg:phone":"+49 6022/21367",
    "sg:postcode":"63839",
    "sg:province":"Bayern",
    "wof:name":"Gemeindeb\u00fccherei Im Ot Hofstetten",
    "wof:placetype":"venue"
},
  "geometry": {"coordinates":[9.167183,49.873619],"type":"Point"}
}