{
  "type": "Feature",
  "properties": {
    "iso:country":"DE",
    "sg:address":"Gewerbestr. 4",
    "sg:city":"Ilsede",
    "sg:phone":"+49 5172/7329",
    "sg:postcode":"31241",
    "sg:province":"Niedersachsen",
    "wof:name":"Herbel Montagen Gmbh",
    "wof:placetype":"venue"
},
  "geometry": {"coordinates":[10.219293,52.273354],"type":"Point"}
}