{
  "type": "Feature",
  "properties": {
    "iso:country":"DE",
    "sg:address":"Schachenmeierstr. 40",
    "sg:city":"M\u00fcnchen",
    "sg:phone":"+49 89/1291780",
    "sg:postcode":"80636",
    "sg:province":"Bayern",
    "wof:name":"M. P\u00f6ringer Immobilienmakler",
    "wof:placetype":"venue"
},
  "geometry": {"coordinates":[11.5457706451,48.1539573669],"type":"Point"}
}