{
  "type": "Feature",
  "properties": {
    "iso:country":"DE",
    "sg:address":"Landshuter Str. 18",
    "sg:city":"W\u00f6rth",
    "sg:phone":"+49 8702/94020",
    "sg:postcode":"84109",
    "sg:province":"Bayern",
    "wof:name":"Kagerer Gmbh & Co. Bau Kg",
    "wof:placetype":"venue"
},
  "geometry": {"coordinates":[12.3343238831,48.6227760315],"type":"Point"}
}