{
  "type": "Feature",
  "properties": {
    "iso:country":"DE",
    "sg:address":"Seilerstr. 19",
    "sg:city":"Norderney",
    "sg:phone":"+49 4932/81033",
    "sg:postcode":"26548",
    "sg:province":"Niedersachsen",
    "wof:name":"G\u00e4stehaus E. Und G. Krohn",
    "wof:placetype":"venue"
},
  "geometry": {"coordinates":[7.1454181671,53.7081489563],"type":"Point"}
}