{
  "type": "Feature",
  "properties": {
    "iso:country":"DE",
    "sg:address":"Buxtehuder Str. 50",
    "sg:city":"Apensen",
    "sg:phone":"+49 4167/234",
    "sg:postcode":"21641",
    "sg:province":"Niedersachsen",
    "wof:name":"Malereibetrieb Horst Thomas Inh. Stefan Thomas",
    "wof:placetype":"venue"
},
  "geometry": {"coordinates":[9.623194,53.437996],"type":"Point"}
}