{
  "type": "Feature",
  "properties": {
    "iso:country":"DE",
    "sg:address":"Prinzregentenstr. 5",
    "sg:city":"Rosenheim",
    "sg:phone":"+49 8031/12296",
    "sg:postcode":"83022",
    "sg:province":"Bayern",
    "wof:name":"Cafe Tscherl",
    "wof:placetype":"venue"
},
  "geometry": {"coordinates":[12.125083,47.855396],"type":"Point"}
}