{
  "type": "Feature",
  "properties": {
    "iso:country":"DE",
    "sg:address":"Riedlinger Str. 22",
    "sg:city":"Altheim",
    "sg:phone":"+49 7371/8642",
    "sg:postcode":"88499",
    "sg:province":"Baden-W\u00fcrttemberg",
    "wof:name":"M. Rhein",
    "wof:placetype":"venue"
},
  "geometry": {"coordinates":[9.453267,48.145306],"type":"Point"}
}