{
  "type": "Feature",
  "properties": {
    "iso:country":"DE",
    "sg:address":"Unterer Kirchbergweg 160",
    "sg:city":"W\u00fcrzburg",
    "sg:postcode":"97084",
    "sg:province":"Bayern",
    "wof:name":"Schulz Gmbh",
    "wof:placetype":"venue"
},
  "geometry": {"coordinates":[9.9712753296,49.7547836304],"type":"Point"}
}