{
  "type": "Feature",
  "properties": {
    "iso:country":"DE",
    "sg:address":"Hauptstr. 7",
    "sg:city":"Aidhausen",
    "sg:phone":"+49 9523/1331",
    "sg:postcode":"97491",
    "sg:province":"Bayern",
    "wof:name":"Christl Gr\u00fcnewald",
    "wof:placetype":"venue"
},
  "geometry": {"coordinates":[10.4677238464,50.1632728577],"type":"Point"}
}