{
  "type": "Feature",
  "properties": {
    "iso:country":"DE",
    "sg:address":"Am Krausenbaum 54",
    "sg:city":"Neuss",
    "sg:postcode":"41464",
    "sg:province":"Nordrhein-Westfalen",
    "wof:name":"J\u00fcrgen Gro\u00dfe-wilde Gmbh",
    "wof:placetype":"venue"
},
  "geometry": {"coordinates":[6.683087,51.185776],"type":"Point"}
}