{
  "type": "Feature",
  "properties": {
    "iso:country":"DE",
    "sg:address":"Auf der Hill 6",
    "sg:city":"Trier",
    "sg:phone":"+49 651/33131",
    "sg:postcode":"54295",
    "sg:province":"Rheinland-Pfalz",
    "wof:name":"Engel Gipsbergbau Gmbh",
    "wof:placetype":"venue"
},
  "geometry": {"coordinates":[6.6580328941,49.7419013977],"type":"Point"}
}