{
  "type": "Feature",
  "properties": {
    "iso:country":"DE",
    "sg:address":"Ohlweg 10",
    "sg:city":"Barsb\u00fcttel",
    "sg:phone":"+49 40/6702627",
    "sg:postcode":"22885",
    "sg:province":"Schleswig-Holstein",
    "wof:name":"Promat Gmbh",
    "wof:placetype":"venue"
},
  "geometry": {"coordinates":[10.1904201508,53.5702552795],"type":"Point"}
}