{
  "type": "Feature",
  "properties": {
    "iso:country":"DE",
    "sg:address":"Sturmb\u00fchlstr. 30 b",
    "sg:city":"Villingen-Schwenningen",
    "sg:phone":"+49 7720/34188",
    "sg:postcode":"78054",
    "sg:province":"Baden-W\u00fcrttemberg",
    "wof:name":"Prodif Raumdesign Gmbh",
    "wof:placetype":"venue"
},
  "geometry": {"coordinates":[8.5335321426,48.0667991638],"type":"Point"}
}