{
  "type": "Feature",
  "properties": {
    "iso:country":"DE",
    "sg:address":"Grafenberger Allee 100",
    "sg:city":"D\u00fcsseldorf",
    "sg:phone":"+49 211/7496930",
    "sg:postcode":"40237",
    "sg:province":"Nordrhein-Westfalen",
    "wof:name":"Human-i Euro Rscg Gmbh",
    "wof:placetype":"venue"
},
  "geometry": {"coordinates":[6.804057,51.231121],"type":"Point"}
}