{
  "type": "Feature",
  "properties": {
    "iso:country":"DE",
    "sg:address":"Kaplaneistr. 11",
    "sg:city":"Rheurdt",
    "sg:phone":"+49 2845/6485",
    "sg:postcode":"47509",
    "sg:province":"Nordrhein-Westfalen",
    "wof:name":"G. M\u00fcller",
    "wof:placetype":"venue"
},
  "geometry": {"coordinates":[6.4704008102,51.4710235596],"type":"Point"}
}