{
  "type": "Feature",
  "properties": {
    "iso:country":"DE",
    "sg:address":"Langenforther Str. 105",
    "sg:city":"Hannover",
    "sg:phone":"+49 511/6042945",
    "sg:postcode":"30657",
    "sg:province":"Niedersachsen",
    "wof:name":"Deutsche Shell Ag",
    "wof:placetype":"venue"
},
  "geometry": {"coordinates":[9.782336235,52.4244804382],"type":"Point"}
}