{
  "type": "Feature",
  "properties": {
    "iso:country":"DE",
    "sg:address":"Bahnhofstr. 2",
    "sg:city":"Sickte",
    "sg:phone":"+49 5305/3879",
    "sg:postcode":"38173",
    "sg:province":"Niedersachsen",
    "wof:name":"Uwe Bartels",
    "wof:placetype":"venue"
},
  "geometry": {"coordinates":[10.637788,52.214432],"type":"Point"}
}