{
  "type": "Feature",
  "properties": {
    "iso:country":"DE",
    "sg:address":"Friedrich-Engels-Str. 12",
    "sg:city":"Ichtershausen",
    "sg:phone":"+49 4936/2875763",
    "sg:postcode":"99334",
    "sg:province":"Th\u00fcringen",
    "wof:name":"M. K. Juchheim Gmbh & Co.",
    "wof:placetype":"venue"
},
  "geometry": {"coordinates":[10.96877,50.876305],"type":"Point"}
}