{
  "type": "Feature",
  "properties": {
    "iso:country":"DE",
    "sg:address":"Oskar-Messter-Str. 24",
    "sg:city":"Ismaning",
    "sg:phone":"+49 89/9624550",
    "sg:postcode":"85737",
    "sg:province":"Bayern",
    "wof:name":"Linear Technology Gmbh",
    "wof:placetype":"venue"
},
  "geometry": {"coordinates":[11.681139,48.234993],"type":"Point"}
}