{
  "type": "Feature",
  "properties": {
    "iso:country":"DE",
    "sg:address":"Friedrich-Engels-Str. 62",
    "sg:city":"Erfurt",
    "sg:phone":"+49 361/6461842",
    "sg:postcode":"99086",
    "sg:province":"Th\u00fcringen",
    "wof:name":"Erfurt Touristik Service",
    "wof:placetype":"venue"
},
  "geometry": {"coordinates":[11.035695076,50.987827301],"type":"Point"}
}