{
  "type": "Feature",
  "properties": {
    "iso:country":"DE",
    "sg:address":"Zu den Fuhren 5",
    "sg:city":"Ganderkesee",
    "sg:phone":"+49 4221/987010",
    "sg:postcode":"27777",
    "sg:province":"Niedersachsen",
    "wof:name":"Hagen M\u00f6ller",
    "wof:placetype":"venue"
},
  "geometry": {"coordinates":[8.57355,53.074959],"type":"Point"}
}