{
  "type": "Feature",
  "properties": {
    "iso:country":"DE",
    "sg:address":"Technologiepark 13",
    "sg:city":"Paderborn",
    "sg:phone":"+49 5251/16630",
    "sg:postcode":"33100",
    "sg:province":"Nordrhein-Westfalen",
    "wof:name":"\u00d6zel Agentur F\u00fcr Design Und Marketing Gmbh",
    "wof:placetype":"venue"
},
  "geometry": {"coordinates":[8.7632541656,51.7013168335],"type":"Point"}
}