{
  "type": "Feature",
  "properties": {
    "iso:country":"DE",
    "sg:address":"Eisenacher Str. 61",
    "sg:city":"Eisenach",
    "sg:phone":"+49 3691/72937",
    "sg:postcode":"99817",
    "sg:province":"Th\u00fcringen",
    "wof:name":"U. Schlamm Gmbh",
    "wof:placetype":"venue"
},
  "geometry": {"coordinates":[10.3616733551,51.0086174011],"type":"Point"}
}