{
  "type": "Feature",
  "properties": {
    "iso:country":"DE",
    "sg:address":"Dammtorstr. 31",
    "sg:city":"Hamburg",
    "sg:phone":"+49 40/35710180",
    "sg:postcode":"20354",
    "sg:province":"Hamburg",
    "wof:name":"Mh Architekten Mondino Hinrichsen",
    "wof:placetype":"venue"
},
  "geometry": {"coordinates":[9.988103,53.556198],"type":"Point"}
}