{
  "type": "Feature",
  "properties": {
    "iso:country":"DE",
    "sg:address":"Gottlieb-Daimler-Str. 6",
    "sg:city":"Gemmingen",
    "sg:phone":"+49 4972/6791270",
    "sg:postcode":"75050",
    "sg:province":"Baden-W\u00fcrttemberg",
    "wof:name":"Artur B\u00c4r Maschinenbau Gmbh",
    "wof:placetype":"venue"
},
  "geometry": {"coordinates":[8.981426,49.148865],"type":"Point"}
}