{
  "type": "Feature",
  "properties": {
    "iso:country":"DE",
    "sg:address":"Baroper Str. 239c",
    "sg:city":"Dortmund",
    "sg:phone":"+49 231/7275600",
    "sg:postcode":"44227",
    "sg:province":"Nordrhein-Westfalen",
    "wof:name":"B. Sch\u00e4fer Und G. Wallach Steuerberater",
    "wof:placetype":"venue"
},
  "geometry": {"coordinates":[7.4195461273,51.4872131348],"type":"Point"}
}