{
  "type": "Feature",
  "properties": {
    "iso:country":"DE",
    "sg:address":"Werderstr. 27",
    "sg:city":"Berlin",
    "sg:phone":"+49 30/7513398",
    "sg:postcode":"12103",
    "sg:province":"Berlin",
    "wof:name":"Ruth Krone Steuerberaterin",
    "wof:placetype":"venue"
},
  "geometry": {"coordinates":[13.38169384,52.4578056335],"type":"Point"}
}