{
  "type": "Feature",
  "properties": {
    "iso:country":"DE",
    "sg:address":"Hegerm\u00fchlenstr 58",
    "sg:city":"Strausberg",
    "sg:phone":"+49 3341/3820",
    "sg:postcode":"15344",
    "sg:province":"Brandenburg",
    "wof:name":"Ewe Ag",
    "wof:placetype":"venue"
},
  "geometry": {"coordinates":[13.8826856613,52.575340271],"type":"Point"}
}