{
  "type": "Feature",
  "properties": {
    "iso:country":"DE",
    "sg:address":"Nikischstr. 5",
    "sg:city":"B\u00f6hlitz-Ehrenberg",
    "sg:phone":"+49 341/4410022",
    "sg:postcode":"04430",
    "wof:name":"Frank Pfeiffer",
    "wof:placetype":"venue"
},
  "geometry": {"coordinates":[12.294386,51.355732],"type":"Point"}
}