{
  "type": "Feature",
  "properties": {
    "iso:country":"DE",
    "sg:address":"Carl-Stolcke-Str. 1",
    "sg:city":"Osnabr\u00fcck",
    "sg:phone":"+49 541/1950",
    "sg:postcode":"49090",
    "sg:province":"Niedersachsen",
    "wof:name":"Montepur Chemie Deutschland Gmbh",
    "wof:placetype":"venue"
},
  "geometry": {"coordinates":[8.008754,52.303719],"type":"Point"}
}