{
  "type": "Feature",
  "properties": {
    "iso:country":"DE",
    "sg:city":"Hasenmoor",
    "sg:phone":"+49 4195/99770",
    "sg:postcode":"24640",
    "sg:province":"Schleswig-Holstein",
    "wof:name":"Albatros -- M Y - S K Y W O R L D . D E --",
    "wof:placetype":"venue"
},
  "geometry": {"coordinates":[9.996304,53.900841],"type":"Point"}
}