{
  "type": "Feature",
  "properties": {
    "iso:country":"DE",
    "sg:address":"Elbe-EKZ",
    "sg:city":"Hamburg",
    "sg:postcode":"20095",
    "sg:province":"Hamburg",
    "wof:name":"Thalia-buchhandlung Erich K\u00f6nnecke Gmbh & Co. Kg",
    "wof:placetype":"venue"
},
  "geometry": {"coordinates":[9.9984846115,53.5498847961],"type":"Point"}
}