{
  "type": "Feature",
  "properties": {
    "iso:country":"DE",
    "sg:address":"Im Dorfe 7",
    "sg:city":"Gelmeroda",
    "sg:postcode":"99428",
    "sg:province":"Th\u00fcringen",
    "wof:name":"Guarnera Pflasterbau Gmbh",
    "wof:placetype":"venue"
},
  "geometry": {"coordinates":[11.3018503189,50.9502258301],"type":"Point"}
}