{
  "type": "Feature",
  "properties": {
    "iso:country":"DE",
    "sg:address":"Sonnborner Str. 95",
    "sg:city":"Wuppertal",
    "sg:postcode":"42327",
    "sg:province":"Nordrhein-Westfalen",
    "wof:name":"Cxc Commercial Communications Gmbh",
    "wof:placetype":"venue"
},
  "geometry": {"coordinates":[7.095984,51.237915],"type":"Point"}
}