{
  "type": "Feature",
  "properties": {
    "iso:country":"DE",
    "sg:address":"G\u00e4nsemarkt 5",
    "sg:city":"Herford",
    "sg:phone":"+49 5221/54477",
    "sg:postcode":"32052",
    "sg:province":"Nordrhein-Westfalen",
    "wof:name":"Die Brille Inh. Lutz Breder",
    "wof:placetype":"venue"
},
  "geometry": {"coordinates":[8.6652803421,52.1154556274],"type":"Point"}
}