{
  "type": "Feature",
  "properties": {
    "iso:country":"DE",
    "sg:address":"G\u00e4nsheidestr. 15a",
    "sg:city":"Stuttgart",
    "sg:phone":"+49 711/240880",
    "sg:postcode":"70184",
    "sg:province":"Baden-W\u00fcrttemberg",
    "wof:name":"Peter Kaltschmidt Architekt",
    "wof:placetype":"venue"
},
  "geometry": {"coordinates":[9.195228,48.776371],"type":"Point"}
}