{
  "type": "Feature",
  "properties": {
    "iso:country":"DE",
    "sg:address":"Pfaffenpf\u00e4dchen 28",
    "sg:city":"K\u00f6ln",
    "sg:phone":"+49 2203/39878",
    "sg:postcode":"51145",
    "sg:province":"Nordrhein-Westfalen",
    "wof:name":"Horst Salomon Steuerberater",
    "wof:placetype":"venue"
},
  "geometry": {"coordinates":[7.077682972,50.8955078125],"type":"Point"}
}