{
  "type": "Feature",
  "properties": {
    "iso:country":"DE",
    "sg:address":"In der Bredde 18",
    "sg:city":"Iserlohn",
    "sg:phone":"+49 2371/6566",
    "sg:postcode":"58636",
    "sg:province":"Nordrhein-Westfalen",
    "wof:name":"Tanzschule F\u00fcr Sie M. Wirth",
    "wof:placetype":"venue"
},
  "geometry": {"coordinates":[7.7135300636,51.3768997192],"type":"Point"}
}