{
  "type": "Feature",
  "properties": {
    "iso:country":"DE",
    "sg:address":"Lange Str. 46",
    "sg:city":"Castrop-Rauxel",
    "sg:phone":"+49 2305/85520",
    "sg:postcode":"44579",
    "sg:province":"Nordrhein-Westfalen",
    "wof:name":"Olympic",
    "wof:placetype":"venue"
},
  "geometry": {"coordinates":[7.3110837936,51.5841751099],"type":"Point"}
}