{
  "type": "Feature",
  "properties": {
    "iso:country":"DE",
    "sg:address":"Parsevalstrasse 41",
    "sg:city":"Wuppertal",
    "sg:phone":"+49 202",
    "sg:postcode":"42285",
    "sg:province":"Nordrhein-Westfalen",
    "wof:name":"Geschenk-service-rode",
    "wof:placetype":"venue"
},
  "geometry": {"coordinates":[7.1760149002,51.2684936523],"type":"Point"}
}