{
  "type": "Feature",
  "properties": {
    "iso:country":"DE",
    "sg:address":"Rhinstrasse 84",
    "sg:city":"Berlin Marzahn",
    "sg:phone":"+49 30/54984414",
    "sg:postcode":"12681",
    "sg:province":"Berlin",
    "wof:name":"Aphrodite Reisen",
    "wof:placetype":"venue"
},
  "geometry": {"coordinates":[13.5198945999,52.526424408],"type":"Point"}
}