{
  "type": "Feature",
  "properties": {
    "iso:country":"DE",
    "sg:address":"R\u00f6merstr. 8 1-2",
    "sg:city":"Lampertheim",
    "sg:phone":"+49 6206/12565",
    "sg:postcode":"68623",
    "sg:province":"Hessen",
    "wof:name":"Werner Barvels",
    "wof:placetype":"venue"
},
  "geometry": {"coordinates":[8.4659252167,49.5948143005],"type":"Point"}
}