{
  "type": "Feature",
  "properties": {
    "iso:country":"DE",
    "sg:address":"Bergheimer Str. 134 a",
    "sg:city":"Heidelberg",
    "sg:phone":"+49 6221/181071",
    "sg:postcode":"69115",
    "sg:province":"Baden-W\u00fcrttemberg",
    "wof:name":"Dr. Med. Monika Bachmayer Arzt F\u00fcr Allgemeinmedizin",
    "wof:placetype":"venue"
},
  "geometry": {"coordinates":[8.6731672287,49.4081497192],"type":"Point"}
}