{
  "type": "Feature",
  "properties": {
    "iso:country":"DE",
    "sg:address":"Neustadter Str. 3",
    "sg:city":"Hochstadt",
    "sg:postcode":"76879",
    "sg:province":"Rheinland-Pfalz",
    "wof:name":"Helmut Klatt E. K.",
    "wof:placetype":"venue"
},
  "geometry": {"coordinates":[8.222144,49.240078],"type":"Point"}
}