{
  "type": "Feature",
  "properties": {
    "iso:country":"DE",
    "sg:address":"V\u00f6gelestr. 1",
    "sg:city":"Fischach",
    "sg:phone":"+49 8236/1446",
    "sg:postcode":"86850",
    "sg:province":"Bayern",
    "wof:name":"V\u00f6gele",
    "wof:placetype":"venue"
},
  "geometry": {"coordinates":[10.6734809875,48.2697296143],"type":"Point"}
}