{
  "type": "Feature",
  "properties": {
    "iso:country":"DE",
    "sg:address":"Gro\u00dfe Rurstr. 15",
    "sg:city":"J\u00fclich",
    "sg:phone":"+49 2461/97980",
    "sg:postcode":"52428",
    "sg:province":"Nordrhein-Westfalen",
    "wof:name":"Dolfus Immobilien",
    "wof:placetype":"venue"
},
  "geometry": {"coordinates":[6.3635950089,50.9223518372],"type":"Point"}
}