{
  "type": "Feature",
  "properties": {
    "iso:country":"DE",
    "sg:address":"Bonner Talweg 77",
    "sg:city":"Bonn",
    "sg:phone":"+49 228/212705",
    "sg:postcode":"53113",
    "sg:province":"Nordrhein-Westfalen",
    "wof:name":"Cavatine",
    "wof:placetype":"venue"
},
  "geometry": {"coordinates":[7.1039910316,50.7233734131],"type":"Point"}
}