{
  "type": "Feature",
  "properties": {
    "iso:country":"DE",
    "sg:address":"Schillerstr. 6",
    "sg:city":"\u00dcberlingen",
    "sg:phone":"+49 7551/2232",
    "sg:postcode":"88662",
    "sg:province":"Baden-W\u00fcrttemberg",
    "wof:name":"H. J. Beck Kunstmaler",
    "wof:placetype":"venue"
},
  "geometry": {"coordinates":[9.170991,47.765217],"type":"Point"}
}