{
  "type": "Feature",
  "properties": {
    "iso:country":"DE",
    "sg:address":"Gertrudenstr. 39",
    "sg:city":"Datteln",
    "sg:phone":"+49 2363/91144",
    "sg:postcode":"45711",
    "sg:province":"Nordrhein-Westfalen",
    "wof:name":"Gwr Sanit\u00e4r - Heizung - L\u00fcftung-klima-service Gmbh",
    "wof:placetype":"venue"
},
  "geometry": {"coordinates":[7.344289,51.649502],"type":"Point"}
}