{
  "type": "Feature",
  "properties": {
    "iso:country":"DE",
    "sg:address":"Lerchenkamp",
    "sg:city":"Hildesheim",
    "sg:phone":"+49 5121/58514",
    "sg:postcode":"31137",
    "sg:province":"Niedersachsen",
    "wof:name":"Hundert Morgen",
    "wof:placetype":"venue"
},
  "geometry": {"coordinates":[9.9514398575,52.1738815308],"type":"Point"}
}