{
  "type": "Feature",
  "properties": {
    "iso:country":"DE",
    "sg:address":"An der M\u00fchle 21",
    "sg:city":"Bremerhaven",
    "sg:phone":"+49 471/305252",
    "sg:postcode":"27570",
    "sg:province":"Bremen",
    "wof:name":"Etna Inh. Orazio Andronaco",
    "wof:placetype":"venue"
},
  "geometry": {"coordinates":[8.5911865234,53.5297393799],"type":"Point"}
}