{
  "type": "Feature",
  "properties": {
    "iso:country":"DE",
    "sg:address":"Bundesstr. 464",
    "sg:city":"Holzgerlingen",
    "sg:phone":"+49 7031/602193",
    "sg:postcode":"71088",
    "sg:province":"Baden-W\u00fcrttemberg",
    "wof:name":"Jet Tankstelle",
    "wof:placetype":"venue"
},
  "geometry": {"coordinates":[9.0117950439,48.6366653442],"type":"Point"}
}