{
  "type": "Feature",
  "properties": {
    "iso:country":"DE",
    "sg:address":"Desinger\u00f6der Str. 38",
    "sg:city":"Duderstadt",
    "sg:phone":"+49 5527/8884",
    "sg:postcode":"37115",
    "sg:province":"Niedersachsen",
    "wof:name":"Kath. Pfarramt St. Mauritius",
    "wof:placetype":"venue"
},
  "geometry": {"coordinates":[10.1812801361,51.5254058838],"type":"Point"}
}