{
  "type": "Feature",
  "properties": {
    "iso:country":"DE",
    "sg:address":"Ulmenstr. 86",
    "sg:city":"D\u00fcsseldorf",
    "sg:phone":"+49 211/465970",
    "sg:postcode":"40476",
    "sg:province":"Nordrhein-Westfalen",
    "wof:name":"Dziatzko",
    "wof:placetype":"venue"
},
  "geometry": {"coordinates":[6.783147,51.247833],"type":"Point"}
}