{
  "type": "Feature",
  "properties": {
    "iso:country":"DE",
    "sg:address":"Berchemstr. 13",
    "sg:city":"M\u00fcnchen",
    "sg:phone":"+49 89/560580",
    "sg:postcode":"80686",
    "sg:province":"Bayern",
    "wof:name":"R. Lauterbach Ingenieur",
    "wof:placetype":"venue"
},
  "geometry": {"coordinates":[11.5068492889,48.1350288391],"type":"Point"}
}