{
  "type": "Feature",
  "properties": {
    "iso:country":"DE",
    "sg:address":"Hellweg 3",
    "sg:city":"Weitefeld",
    "sg:phone":"+49 2743/2714",
    "sg:postcode":"57586",
    "sg:province":"Rheinland-Pfalz",
    "wof:name":"Imbi\u00df G. H\u00f6fer",
    "wof:placetype":"venue"
},
  "geometry": {"coordinates":[7.9283161163,50.7262268066],"type":"Point"}
}