{
  "type": "Feature",
  "properties": {
    "iso:country":"DE",
    "sg:address":"Tituscorso 6",
    "sg:city":"Frankfurt",
    "sg:phone":"+49 69/588455",
    "sg:postcode":"60439",
    "sg:province":"Hessen",
    "wof:name":"Heiko Rupprecht",
    "wof:placetype":"venue"
},
  "geometry": {"coordinates":[8.6346054077,50.1579246521],"type":"Point"}
}