{
  "type": "Feature",
  "properties": {
    "iso:country":"DE",
    "sg:address":"Marktplatz 6",
    "sg:city":"Calw",
    "sg:phone":"+49 7051/92570",
    "sg:postcode":"75365",
    "sg:province":"Baden-W\u00fcrttemberg",
    "wof:name":"Mode Schaber Gmbh",
    "wof:placetype":"venue"
},
  "geometry": {"coordinates":[8.7393007278,48.7141723633],"type":"Point"}
}