{
  "type": "Feature",
  "properties": {
    "iso:country":"DE",
    "sg:address":"Franconvilleplatz 2",
    "sg:city":"Viernheim",
    "sg:phone":"+49 6204/8994",
    "sg:postcode":"68519",
    "sg:province":"Hessen",
    "wof:name":"Erich Bugert Gmbh",
    "wof:placetype":"venue"
},
  "geometry": {"coordinates":[8.590048,49.5415],"type":"Point"}
}