{
  "type": "Feature",
  "properties": {
    "iso:country":"DE",
    "sg:address":"Wittkuller Str. 51",
    "sg:city":"Solingen",
    "sg:phone":"+49 212/38070",
    "sg:postcode":"42719",
    "sg:province":"Nordrhein-Westfalen",
    "wof:name":"Ern Zweite Beteiligungsges. Mbh",
    "wof:placetype":"venue"
},
  "geometry": {"coordinates":[7.034863,51.186359],"type":"Point"}
}