{
  "type": "Feature",
  "properties": {
    "iso:country":"DE",
    "sg:address":"Baltrumer Platz 2",
    "sg:city":"Gifhorn",
    "sg:phone":"+49 5371/58187",
    "sg:postcode":"38518",
    "sg:province":"Niedersachsen",
    "wof:name":"Manfred Pr\u00fcfer Finanzberater",
    "wof:placetype":"venue"
},
  "geometry": {"coordinates":[10.5660257339,52.466594696],"type":"Point"}
}