{
  "type": "Feature",
  "properties": {
    "iso:country":"DE",
    "sg:address":"Marktplatz 7",
    "sg:city":"Braunsbach",
    "sg:phone":"+49 4979/06588",
    "sg:postcode":"74542",
    "sg:province":"Baden-W\u00fcrttemberg",
    "wof:name":"Volksbank Schw\u00e4bisch Hall Eg",
    "wof:placetype":"venue"
},
  "geometry": {"coordinates":[9.79208,49.199268],"type":"Point"}
}