{
  "type": "Feature",
  "properties": {
    "iso:country":"DE",
    "sg:address":"Seitzenbachstr. 18",
    "sg:city":"Donzdorf",
    "sg:phone":"+49 7162/29204",
    "sg:postcode":"73072",
    "sg:province":"Baden-W\u00fcrttemberg",
    "wof:name":"Kurt Saur",
    "wof:placetype":"venue"
},
  "geometry": {"coordinates":[9.814044,48.683342],"type":"Point"}
}