{
  "type": "Feature",
  "properties": {
    "iso:country":"DE",
    "sg:address":"Schulenburger Landstr. 152",
    "sg:city":"Hannover",
    "sg:phone":"+49 511/639977",
    "sg:postcode":"30165",
    "sg:province":"Niedersachsen",
    "wof:name":"Industrie-hydraulik Horst M\u00fcller Gmbh",
    "wof:placetype":"venue"
},
  "geometry": {"coordinates":[9.708227,52.409817],"type":"Point"}
}