{
  "type": "Feature",
  "properties": {
    "iso:country":"DE",
    "sg:address":"Grossflecken 50",
    "sg:city":"Neum\u00fcnster",
    "sg:phone":"+49 4321/410516",
    "sg:postcode":"24534",
    "sg:province":"Schleswig-Holstein",
    "wof:name":"Conrads Die B\u00fcro-entwicklung",
    "wof:placetype":"venue"
},
  "geometry": {"coordinates":[9.9874019623,54.0704917908],"type":"Point"}
}