{
  "type": "Feature",
  "properties": {
    "iso:country":"DE",
    "sg:address":"Westerstr. 26",
    "sg:city":"Elmshorn",
    "sg:phone":"+49 4121/62465",
    "sg:postcode":"25336",
    "sg:province":"Schleswig-Holstein",
    "wof:name":"Frachtkontor E. K\u00f6lln Gmbh",
    "wof:placetype":"venue"
},
  "geometry": {"coordinates":[9.6527519226,53.7493209839],"type":"Point"}
}