{
  "type": "Feature",
  "properties": {
    "iso:country":"DE",
    "sg:address":"Dorfstr. 18",
    "sg:city":"Filsum",
    "sg:postcode":"26849",
    "sg:province":"Niedersachsen",
    "wof:name":"Kkm Gesellschaft F\u00fcr Handel Und Kommerz Mbh",
    "wof:placetype":"venue"
},
  "geometry": {"coordinates":[7.6676969528,53.2443618774],"type":"Point"}
}