{
  "type": "Feature",
  "properties": {
    "iso:country":"DE",
    "sg:address":"Waldwinkel 7",
    "sg:city":"H\u00fcnxe",
    "sg:phone":"+49 2858/7484",
    "sg:postcode":"46569",
    "sg:province":"Nordrhein-Westfalen",
    "wof:name":"Arntz Kg",
    "wof:placetype":"venue"
},
  "geometry": {"coordinates":[6.7399997711,51.6586761475],"type":"Point"}
}