{
  "type": "Feature",
  "properties": {
    "iso:country":"DE",
    "sg:address":"Westerm\u00fchlstrasse 25",
    "sg:city":"M\u00fcnchen",
    "sg:postcode":"80469",
    "sg:province":"Bayern",
    "wof:name":"Caraudiodiscount",
    "wof:placetype":"venue"
},
  "geometry": {"coordinates":[11.5713891983,48.1279335022],"type":"Point"}
}