{
  "type": "Feature",
  "properties": {
    "iso:country":"DE",
    "sg:address":"Rudolf-Breitscheid-Str. 8",
    "sg:city":"Scheibenberg",
    "sg:phone":"+49 37349/7025",
    "sg:postcode":"09481",
    "sg:province":"Sachsen",
    "wof:name":"Trt S & A Ingenieurb\u00fcro Gmbh",
    "wof:placetype":"venue"
},
  "geometry": {"coordinates":[12.9147520065,50.5413589478],"type":"Point"}
}