{
  "type": "Feature",
  "properties": {
    "iso:country":"DE",
    "sg:address":"Kolonie 36",
    "sg:city":"Abtsgm\u00fcnd",
    "sg:phone":"+49 7975/207",
    "sg:postcode":"73453",
    "sg:province":"Baden-W\u00fcrttemberg",
    "wof:name":"I. Stieb",
    "wof:placetype":"venue"
},
  "geometry": {"coordinates":[9.8901987076,48.9137535095],"type":"Point"}
}