{
  "type": "Feature",
  "properties": {
    "iso:country":"DE",
    "sg:address":"Kardinal-Wendel-Str. 8",
    "sg:city":"Blieskastel",
    "sg:phone":"+49 6842/4565",
    "sg:postcode":"66440",
    "sg:province":"Saarland",
    "wof:name":"Hut-und Pelzhaus Bartholus Inh. Ernst Horbach",
    "wof:placetype":"venue"
},
  "geometry": {"coordinates":[7.257912159,49.2368507385],"type":"Point"}
}