{
  "type": "Feature",
  "properties": {
    "iso:country":"DE",
    "sg:address":"Hohewardstr. 345",
    "sg:city":"Herten",
    "sg:postcode":"45699",
    "sg:province":"Nordrhein-Westfalen",
    "wof:name":"Abat Handels- Und Verm\u00f6gens- Verwaltungs Gmbh",
    "wof:placetype":"venue"
},
  "geometry": {"coordinates":[7.157057,51.554054],"type":"Point"}
}