{
  "type": "Feature",
  "properties": {
    "iso:country":"DE",
    "sg:address":"Reitzenhainer Str. 51",
    "sg:city":"Penig",
    "sg:phone":"+49 37381/82092",
    "sg:postcode":"09322",
    "sg:province":"Sachsen",
    "wof:name":"Dr. Med. Heidemarie Schinke",
    "wof:placetype":"venue"
},
  "geometry": {"coordinates":[12.7119112015,50.9278030396],"type":"Point"}
}