{
  "type": "Feature",
  "properties": {
    "iso:country":"DE",
    "sg:address":"Neuastenberger Str. 50",
    "sg:city":"Winterberg",
    "sg:postcode":"59955",
    "sg:province":"Nordrhein-Westfalen",
    "wof:name":"Postwiesen-liftges. Mbh",
    "wof:placetype":"venue"
},
  "geometry": {"coordinates":[8.4852132797,51.1638793945],"type":"Point"}
}