{
  "type": "Feature",
  "properties": {
    "iso:country":"DE",
    "sg:address":"Br\u00fcder-Grimm-Str. 7",
    "sg:city":"Linden",
    "sg:phone":"+49 6403/71145",
    "sg:postcode":"35440",
    "sg:province":"Hessen",
    "wof:name":"Klaus M\u00fcller",
    "wof:placetype":"venue"
},
  "geometry": {"coordinates":[8.6596002579,50.5247840881],"type":"Point"}
}