{
  "type": "Feature",
  "properties": {
    "iso:country":"DE",
    "sg:address":"Burger Str. 13",
    "sg:city":"Wermelskirchen",
    "sg:phone":"+49 2196/91511",
    "sg:postcode":"42929",
    "sg:province":"Nordrhein-Westfalen",
    "wof:name":"Reiner Hackl\u00e4nder",
    "wof:placetype":"venue"
},
  "geometry": {"coordinates":[7.20302,51.135571],"type":"Point"}
}