{
  "type": "Feature",
  "properties": {
    "iso:country":"DE",
    "sg:address":"Thalkirchner Str. 130",
    "sg:city":"M\u00fcnchen",
    "sg:phone":"+49 89/763709",
    "sg:postcode":"81371",
    "sg:province":"Bayern",
    "wof:name":"Wilhelmi",
    "wof:placetype":"venue"
},
  "geometry": {"coordinates":[11.5508041382,48.1184234619],"type":"Point"}
}