{
  "type": "Feature",
  "properties": {
    "iso:country":"DE",
    "sg:address":"Damperhofstr. 10",
    "sg:city":"Kiel",
    "sg:postcode":"24103",
    "sg:province":"Schleswig-Holstein",
    "wof:name":"Kieler W\u00e4getechnik Gmbh",
    "wof:placetype":"venue"
},
  "geometry": {"coordinates":[10.126353,54.324791],"type":"Point"}
}