{
  "type": "Feature",
  "properties": {
    "iso:country":"DE",
    "sg:address":"Prignitzstr. 92",
    "sg:city":"Berlin",
    "sg:phone":"+49 30/5405443",
    "sg:postcode":"12683",
    "sg:province":"Berlin",
    "wof:name":"Heinz Wosch",
    "wof:placetype":"venue"
},
  "geometry": {"coordinates":[13.551013,52.522415],"type":"Point"}
}