{
  "type": "Feature",
  "properties": {
    "iso:country":"DE",
    "sg:address":"Hardtstr. 1-3",
    "sg:city":"R\u00fcthen",
    "sg:phone":"+49 2952/3811",
    "sg:postcode":"59602",
    "sg:province":"Nordrhein-Westfalen",
    "wof:name":"Tele Tec Brechtl Telekommunikation E. K.",
    "wof:placetype":"venue"
},
  "geometry": {"coordinates":[8.4072666168,51.4949913025],"type":"Point"}
}