{
  "type": "Feature",
  "properties": {
    "iso:country":"DE",
    "sg:address":"Salzstr. 1",
    "sg:city":"Freiburg",
    "sg:phone":"+49 761/34646",
    "sg:postcode":"79098",
    "sg:province":"Baden-W\u00fcrttemberg",
    "wof:name":"Alphaflor F. St\u00fcber",
    "wof:placetype":"venue"
},
  "geometry": {"coordinates":[7.850085,47.994835],"type":"Point"}
}