{
  "type": "Feature",
  "properties": {
    "iso:country":"DE",
    "sg:address":"Triftstr. 2",
    "sg:city":"Durmersheim",
    "sg:phone":"+49 7245/92400",
    "sg:postcode":"76448",
    "sg:province":"Baden-W\u00fcrttemberg",
    "wof:name":"Mappes & Riedlinger Ohg",
    "wof:placetype":"venue"
},
  "geometry": {"coordinates":[8.2739553452,48.9384727478],"type":"Point"}
}