{
  "type": "Feature",
  "properties": {
    "iso:country":"DE",
    "sg:address":"Webershohl 11",
    "sg:city":"Dortmund",
    "sg:phone":"+49 231/270002",
    "sg:postcode":"44319",
    "sg:province":"Nordrhein-Westfalen",
    "wof:name":"Reparatur Werkstatt Harlos",
    "wof:placetype":"venue"
},
  "geometry": {"coordinates":[7.590043,51.526806],"type":"Point"}
}