{
  "type": "Feature",
  "properties": {
    "iso:country":"DE",
    "sg:address":"Wilhelm-Leithe-Weg 12-14",
    "sg:city":"Bochum",
    "sg:phone":"+49 2327/94850",
    "sg:postcode":"44867",
    "sg:province":"Nordrhein-Westfalen",
    "wof:name":"Hans B\u00fccker Gmbh",
    "wof:placetype":"venue"
},
  "geometry": {"coordinates":[7.1444549561,51.4715156555],"type":"Point"}
}