{
  "type": "Feature",
  "properties": {
    "iso:country":"DE",
    "sg:address":"Savignystr. 77",
    "sg:city":"Frankfurt",
    "sg:phone":"+49 69/558820",
    "sg:postcode":"60325",
    "sg:province":"Hessen",
    "wof:name":"Conrec Gesellschaft F\u00fcr Container- Recycling- Und",
    "wof:placetype":"venue"
},
  "geometry": {"coordinates":[8.6574707031,50.1144828796],"type":"Point"}
}