{
  "type": "Feature",
  "properties": {
    "iso:country":"DE",
    "sg:address":"Gerhart-Hauptmann-Str. 17",
    "sg:city":"Sinsheim",
    "sg:phone":"+49 7261/2134",
    "sg:postcode":"74889",
    "sg:province":"Baden-W\u00fcrttemberg",
    "wof:name":"Walter Kleinbach Architekt",
    "wof:placetype":"venue"
},
  "geometry": {"coordinates":[8.872708,49.260555],"type":"Point"}
}