{
  "type": "Feature",
  "properties": {
    "iso:country":"DE",
    "sg:address":"Angerweg 20",
    "sg:city":"Lich",
    "sg:phone":"+49 6404/7410",
    "sg:postcode":"35423",
    "sg:province":"Hessen",
    "wof:name":"Sieglinde Pr\u00fcss",
    "wof:placetype":"venue"
},
  "geometry": {"coordinates":[8.8825836182,50.5400276184],"type":"Point"}
}