{
  "type": "Feature",
  "properties": {
    "iso:country":"DE",
    "sg:address":"Kissingerstra\u00dfe 47",
    "sg:city":"Duesseldorf",
    "sg:postcode":"40229",
    "sg:province":"Nordrhein-Westfalen",
    "wof:name":"Waeschseite.de Alles Fuer Waeschliebhaber",
    "wof:placetype":"venue"
},
  "geometry": {"coordinates":[6.840476,51.194256],"type":"Point"}
}