{
  "type": "Feature",
  "properties": {
    "iso:country":"DE",
    "sg:address":"Riedstr. 7",
    "sg:city":"Alfdorf",
    "sg:phone":"+49 7172/31191",
    "sg:postcode":"73553",
    "sg:province":"Baden-W\u00fcrttemberg",
    "wof:name":"Silvia Semler Heilpraktikerin",
    "wof:placetype":"venue"
},
  "geometry": {"coordinates":[9.6831798553,48.8352432251],"type":"Point"}
}