{
  "type": "Feature",
  "properties": {
    "iso:country":"DE",
    "sg:address":"Stegerstr. 15",
    "sg:city":"Stadtlohn",
    "sg:phone":"+49 2563/1238",
    "sg:postcode":"48703",
    "sg:province":"Nordrhein-Westfalen",
    "wof:name":"B. Van B\u00f6mmel-s\u00fcsken",
    "wof:placetype":"venue"
},
  "geometry": {"coordinates":[6.9182581902,51.9914245605],"type":"Point"}
}