{
  "type": "Feature",
  "properties": {
    "iso:country":"DE",
    "sg:address":"Alois-Schenk-Str. 4",
    "sg:city":"Baunach",
    "sg:phone":"+49 9544/1302",
    "sg:postcode":"96148",
    "sg:province":"Bayern",
    "wof:name":"Gerhard Postler Architekt",
    "wof:placetype":"venue"
},
  "geometry": {"coordinates":[10.844445,49.985802],"type":"Point"}
}