{
  "type": "Feature",
  "properties": {
    "iso:country":"DE",
    "sg:address":"Freudenst\u00e4dter Str. 60",
    "sg:city":"Baiersbronn",
    "sg:phone":"+49 7442/3320",
    "sg:postcode":"72270",
    "sg:province":"Baden-W\u00fcrttemberg",
    "wof:name":"Manfred Vetter Statiker",
    "wof:placetype":"venue"
},
  "geometry": {"coordinates":[8.3769073486,48.4967498779],"type":"Point"}
}