{
  "type": "Feature",
  "properties": {
    "iso:country":"DE",
    "sg:address":"Sch\u00f6nbergstr. 63",
    "sg:city":"Ebringen",
    "sg:phone":"+49 7664/60976",
    "sg:postcode":"79285",
    "sg:province":"Baden-W\u00fcrttemberg",
    "wof:name":"F. Ziegler Und B. Zippenfennig",
    "wof:placetype":"venue"
},
  "geometry": {"coordinates":[7.7789959908,47.9577980042],"type":"Point"}
}