{
  "type": "Feature",
  "properties": {
    "iso:country":"DE",
    "sg:address":"Feigenberg 2",
    "sg:city":"Hatzenb\u00fchl",
    "sg:phone":"+49 7275/1358",
    "sg:postcode":"76770",
    "sg:province":"Rheinland-Pfalz",
    "wof:name":"Albert Henigin",
    "wof:placetype":"venue"
},
  "geometry": {"coordinates":[8.2436,49.10976],"type":"Point"}
}