{
  "type": "Feature",
  "properties": {
    "iso:country":"DE",
    "sg:address":"Elzestr. 59",
    "sg:city":"Morschen",
    "sg:phone":"+49 5664/333",
    "sg:postcode":"34326",
    "sg:province":"Hessen",
    "wof:name":"A. Wohlgemut",
    "wof:placetype":"venue"
},
  "geometry": {"coordinates":[9.617443,51.072041],"type":"Point"}
}