{
  "type": "Feature",
  "properties": {
    "iso:country":"DE",
    "sg:address":"Kinzigheimer Hof",
    "sg:city":"Bruchk\u00f6bel",
    "sg:phone":"+49 6181/976760",
    "sg:postcode":"63486",
    "sg:province":"Hessen",
    "wof:name":"Dr. Christian Kaiser",
    "wof:placetype":"venue"
},
  "geometry": {"coordinates":[8.9102468491,50.1674118042],"type":"Point"}
}