{
  "type": "Feature",
  "properties": {
    "iso:country":"DE",
    "sg:address":"Hohe Str. 1",
    "sg:city":"Montabaur",
    "sg:phone":"+49 2602/5224",
    "sg:postcode":"56410",
    "sg:province":"Rheinland-Pfalz",
    "wof:name":"Capri Tanzgrotte",
    "wof:placetype":"venue"
},
  "geometry": {"coordinates":[7.826106,50.441734],"type":"Point"}
}