{
  "type": "Feature",
  "properties": {
    "iso:country":"DE",
    "sg:address":"Stader Landstrasse 1",
    "sg:city":"Osterholz-Schambeck",
    "sg:phone":"+49 4791/13262",
    "sg:postcode":"27711",
    "sg:province":"Niedersachsen",
    "wof:name":"Willkommen Auf Torsten Gellrichs Website",
    "wof:placetype":"venue"
},
  "geometry": {"coordinates":[8.79298,53.235462],"type":"Point"}
}