{
  "type": "Feature",
  "properties": {
    "iso:country":"DE",
    "sg:address":"W\u00f6rschhauser Str. 29",
    "sg:city":"Egling",
    "sg:phone":"+49 8176/282",
    "sg:postcode":"82544",
    "sg:province":"Bayern",
    "wof:name":"Karl H\u00fcmmer",
    "wof:placetype":"venue"
},
  "geometry": {"coordinates":[11.5523996353,47.9254417419],"type":"Point"}
}