{
  "type": "Feature",
  "properties": {
    "iso:country":"DE",
    "sg:address":"Lange Wende 12",
    "sg:city":"Arnsberg",
    "sg:phone":"+49 2932/26116",
    "sg:postcode":"59755",
    "sg:province":"Nordrhein-Westfalen",
    "wof:name":"S. Sch\u00fctz",
    "wof:placetype":"venue"
},
  "geometry": {"coordinates":[7.964712,51.449394],"type":"Point"}
}