{
  "type": "Feature",
  "properties": {
    "iso:country":"DE",
    "sg:address":"Bachstr. 23",
    "sg:city":"Karlsruhe",
    "sg:phone":"+49 721/844066",
    "sg:postcode":"76185",
    "sg:province":"Baden-W\u00fcrttemberg",
    "wof:name":"Gerling E & L Lebensversicherungs Ag",
    "wof:placetype":"venue"
},
  "geometry": {"coordinates":[8.3693790436,49.0120429993],"type":"Point"}
}