{
  "type": "Feature",
  "properties": {
    "iso:country":"DE",
    "sg:address":"Scharbacher Str.",
    "sg:city":"Grasellenbach",
    "sg:phone":"+49 6207/6770",
    "sg:postcode":"64689",
    "sg:province":"Hessen",
    "wof:name":"Pension H. Helferich",
    "wof:placetype":"venue"
},
  "geometry": {"coordinates":[8.8325119019,49.6194496155],"type":"Point"}
}