{
  "type": "Feature",
  "properties": {
    "iso:country":"DE",
    "sg:address":"Lembergstr. 54",
    "sg:city":"Reutlingen",
    "sg:postcode":"72766",
    "sg:province":"Baden-W\u00fcrttemberg",
    "wof:name":"Kauffmann Gmbh",
    "wof:placetype":"venue"
},
  "geometry": {"coordinates":[9.218673,48.514561],"type":"Point"}
}