{
  "type": "Feature",
  "properties": {
    "iso:country":"DE",
    "sg:address":"Sperberstr. 5",
    "sg:city":"Essenbach",
    "sg:phone":"+49 8703/91908",
    "sg:postcode":"84051",
    "sg:province":"Bayern",
    "wof:name":"H. Schedletzki",
    "wof:placetype":"venue"
},
  "geometry": {"coordinates":[12.2410821915,48.6267089844],"type":"Point"}
}