{
  "type": "Feature",
  "properties": {
    "iso:country":"DE",
    "sg:address":"Kemnater Str. 85",
    "sg:city":"Stuttgart",
    "sg:phone":"+49 711/444666",
    "sg:postcode":"70619",
    "sg:province":"Baden-W\u00fcrttemberg",
    "wof:name":"Jet Promotion",
    "wof:placetype":"venue"
},
  "geometry": {"coordinates":[9.2248077393,48.735874176],"type":"Point"}
}