{
  "type": "Feature",
  "properties": {
    "iso:country":"DE",
    "sg:address":"Schillerstr. 26",
    "sg:city":"Langenbrettach",
    "sg:phone":"+49 7139/7109",
    "sg:postcode":"74243",
    "sg:province":"Baden-W\u00fcrttemberg",
    "wof:name":"Erwin Mack",
    "wof:placetype":"venue"
},
  "geometry": {"coordinates":[9.383337,49.223797],"type":"Point"}
}