{
  "type": "Feature",
  "properties": {
    "iso:country":"DE",
    "sg:address":"Hauptstr. 16",
    "sg:city":"Neuenhagen",
    "sg:phone":"+49 3342/200063",
    "sg:postcode":"15366",
    "sg:province":"Brandenburg",
    "wof:name":"G. Schloms",
    "wof:placetype":"venue"
},
  "geometry": {"coordinates":[13.7026329041,52.5221748352],"type":"Point"}
}