{
  "type": "Feature",
  "properties": {
    "iso:country":"DE",
    "sg:address":"Sch\u00e4ffnerstr. 22",
    "sg:city":"Regensburg",
    "sg:phone":"+49 941/52489",
    "sg:postcode":"93047",
    "sg:province":"Bayern",
    "wof:name":"Phase Two Textilhandels Gmbh",
    "wof:placetype":"venue"
},
  "geometry": {"coordinates":[12.098883,49.016014],"type":"Point"}
}