{
  "type": "Feature",
  "properties": {
    "iso:country":"DE",
    "sg:address":"Dr.-Wilhelm-K\u00fclz-Str. 7",
    "sg:city":"Bad Wilsnack",
    "sg:phone":"+49 38791/2024",
    "sg:postcode":"19336",
    "sg:province":"Brandenburg",
    "wof:name":"Elektro-lausmann",
    "wof:placetype":"venue"
},
  "geometry": {"coordinates":[11.954092,52.961658],"type":"Point"}
}