{
  "type": "Feature",
  "properties": {
    "iso:country":"DE",
    "sg:address":"Abelweg 15",
    "sg:city":"Kronshagen",
    "sg:phone":"+49 431/542812",
    "sg:postcode":"24119",
    "sg:province":"Schleswig-Holstein",
    "wof:name":"Erhard Bartels Wirtschaftspr\u00fcfer",
    "wof:placetype":"venue"
},
  "geometry": {"coordinates":[10.0905008316,54.3392868042],"type":"Point"}
}