{
  "type": "Feature",
  "properties": {
    "iso:country":"DE",
    "sg:address":"Dresdner Str. 331",
    "sg:city":"Freital",
    "sg:phone":"+49 351/6491319",
    "sg:postcode":"01705",
    "sg:province":"Sachsen",
    "wof:name":"Fischer Elektrowerkst\u00e4tten",
    "wof:placetype":"venue"
},
  "geometry": {"coordinates":[13.636707,50.985977],"type":"Point"}
}