{
  "type": "Feature",
  "properties": {
    "iso:country":"DE",
    "sg:address":"Bahnhofstr. 21 -29",
    "sg:city":"Frankenthal",
    "sg:phone":"+49 6233/31840",
    "sg:postcode":"67227",
    "sg:province":"Rheinland-Pfalz",
    "wof:name":"Helmut Barth Und Dirk Scheerer",
    "wof:placetype":"venue"
},
  "geometry": {"coordinates":[8.3525562286,49.5351982117],"type":"Point"}
}