{
  "type": "Feature",
  "properties": {
    "iso:country":"DE",
    "sg:address":"Industriestr. 60",
    "sg:city":"Bochum",
    "sg:phone":"+49 234/288760",
    "sg:postcode":"44894",
    "sg:province":"Nordrhein-Westfalen",
    "wof:name":"Herbert W\u00fcstrich Bedachungen Gmbh",
    "wof:placetype":"venue"
},
  "geometry": {"coordinates":[7.287967,51.476227],"type":"Point"}
}