{
  "type": "Feature",
  "properties": {
    "iso:country":"DE",
    "sg:address":"Altk\u00f6tzschenbroda 59",
    "sg:city":"Radebeul",
    "sg:postcode":"01445",
    "sg:province":"Sachsen",
    "wof:name":"Sachsenwein Kache Ebert Ohg",
    "wof:placetype":"venue"
},
  "geometry": {"coordinates":[13.6318807602,51.1044197083],"type":"Point"}
}