{
  "type": "Feature",
  "properties": {
    "iso:country":"DE",
    "sg:address":"Dortmunder Str. 18",
    "sg:city":"Bremen",
    "sg:phone":"+49 421/513006",
    "sg:postcode":"28199",
    "sg:province":"Bremen",
    "wof:name":"Thermo Technik Ivs Ind. Versorgungssysteme Gmbh",
    "wof:placetype":"venue"
},
  "geometry": {"coordinates":[8.7805318832,53.0597496033],"type":"Point"}
}