{
  "type": "Feature",
  "properties": {
    "iso:country":"DE",
    "sg:address":"Am Dreschschopf 4b",
    "sg:city":"Freiburg",
    "sg:phone":"+49 7664/2049",
    "sg:postcode":"79112",
    "sg:province":"Baden-W\u00fcrttemberg",
    "wof:name":"Werner Gerteisen",
    "wof:placetype":"venue"
},
  "geometry": {"coordinates":[7.7132377625,47.9991874695],"type":"Point"}
}