{
  "type": "Feature",
  "properties": {
    "iso:country":"DE",
    "sg:address":"Gerhardstr. 3",
    "sg:city":"Rendsburg",
    "sg:phone":"+49 4331/787678",
    "sg:postcode":"24768",
    "sg:province":"Schleswig-Holstein",
    "wof:name":"Nord-apotheke",
    "wof:placetype":"venue"
},
  "geometry": {"coordinates":[9.656959,54.309765],"type":"Point"}
}