{
  "type": "Feature",
  "properties": {
    "iso:country":"DE",
    "sg:address":"Rh\u00f6nstr. 3",
    "sg:city":"Lohfelden",
    "sg:phone":"+49 5608/1470",
    "sg:postcode":"34253",
    "sg:province":"Hessen",
    "wof:name":"Bernd Schulze Elektroinstallation",
    "wof:placetype":"venue"
},
  "geometry": {"coordinates":[9.562675,51.2561],"type":"Point"}
}