{
  "type": "Feature",
  "properties": {
    "iso:country":"DE",
    "sg:address":"Ritzenb\u00fctteler Str. 104",
    "sg:city":"Lemwerder",
    "sg:phone":"+49 421/67645",
    "sg:postcode":"27809",
    "sg:province":"Niedersachsen",
    "wof:name":"Heinrich Kasimiers",
    "wof:placetype":"venue"
},
  "geometry": {"coordinates":[8.5822143555,53.1669158936],"type":"Point"}
}