{
  "type": "Feature",
  "properties": {
    "iso:country":"DE",
    "sg:address":"Steinb\u00fchlstr. 22",
    "sg:city":"Seesen",
    "sg:phone":"+49 5381/46580",
    "sg:postcode":"38723",
    "sg:province":"Niedersachsen",
    "wof:name":"Betten-markt Wedeg\u00e4rtner-verwaltungs Gmbh",
    "wof:placetype":"venue"
},
  "geometry": {"coordinates":[10.190613,51.89373],"type":"Point"}
}