{
  "type": "Feature",
  "properties": {
    "iso:country":"DE",
    "sg:address":"Borgmannshof 4",
    "sg:city":"Gelsenkirchen",
    "sg:phone":"+49 209/871087",
    "sg:postcode":"45888",
    "sg:province":"Nordrhein-Westfalen",
    "wof:name":"Carl-textilvertriebs Gmbh",
    "wof:placetype":"venue"
},
  "geometry": {"coordinates":[7.1176748276,51.522480011],"type":"Point"}
}