{
  "type": "Feature",
  "properties": {
    "iso:country":"DE",
    "sg:address":"Hofbieberer Str. 14",
    "sg:city":"N\u00fcsttal",
    "sg:phone":"+49 6684/374",
    "sg:postcode":"36167",
    "sg:province":"Hessen",
    "wof:name":"T. Gatterdamm",
    "wof:placetype":"venue"
},
  "geometry": {"coordinates":[9.8475408554,50.628112793],"type":"Point"}
}