{
  "type": "Feature",
  "properties": {
    "iso:country":"DE",
    "sg:address":"Industriestr. 7",
    "sg:city":"Haibach",
    "sg:phone":"+49 6021/69559",
    "sg:postcode":"63808",
    "sg:province":"Bayern",
    "wof:name":"Helmut Schnatz",
    "wof:placetype":"venue"
},
  "geometry": {"coordinates":[9.192222,49.963646],"type":"Point"}
}