{
  "type": "Feature",
  "properties": {
    "iso:country":"DE",
    "sg:address":"Hasslebener Str. 32",
    "sg:city":"Gerswalde",
    "sg:phone":"+49 4939/8876060",
    "sg:postcode":"17268",
    "sg:province":"Brandenburg",
    "wof:name":"Gasthaus & Pension Zum Schwarzen Adler",
    "wof:placetype":"venue"
},
  "geometry": {"coordinates":[13.748735,53.170818],"type":"Point"}
}