{
  "type": "Feature",
  "properties": {
    "iso:country":"DE",
    "sg:address":"Heinrichstr 6",
    "sg:city":"Spremberg",
    "sg:phone":"+49 3563/2197",
    "sg:postcode":"03130",
    "sg:province":"Brandenburg",
    "wof:name":"W\u00e4scherei Spremberg Gmbh",
    "wof:placetype":"venue"
},
  "geometry": {"coordinates":[14.376063,51.567364],"type":"Point"}
}