{
  "type": "Feature",
  "properties": {
    "iso:country":"DE",
    "sg:address":"Alte Twiete 7",
    "sg:city":"Hamburg",
    "sg:phone":"+49 40/7230268",
    "sg:postcode":"21037",
    "sg:province":"Hamburg",
    "wof:name":"August Sch\u00e4fer",
    "wof:placetype":"venue"
},
  "geometry": {"coordinates":[10.2004470825,53.4184951782],"type":"Point"}
}