{
  "type": "Feature",
  "properties": {
    "iso:country":"DE",
    "sg:address":"Schlo\u00dfplatz 7",
    "sg:city":"Wittlich",
    "sg:phone":"+49 6571/8424",
    "sg:postcode":"54516",
    "sg:province":"Rheinland-Pfalz",
    "wof:name":"Franz-josef Kr\u00e4mer",
    "wof:placetype":"venue"
},
  "geometry": {"coordinates":[6.890063,49.985439],"type":"Point"}
}