{
  "type": "Feature",
  "properties": {
    "iso:country":"DE",
    "sg:address":"Heinrich-Hammer-Str. 6",
    "sg:city":"Erbach",
    "sg:phone":"+49 7305/932630",
    "sg:postcode":"89155",
    "sg:province":"Baden-W\u00fcrttemberg",
    "wof:name":"Movilite Intelligente Projektionssysteme Gmbh",
    "wof:placetype":"venue"
},
  "geometry": {"coordinates":[9.8978595734,48.3276367188],"type":"Point"}
}