{
  "type": "Feature",
  "properties": {
    "iso:country":"DE",
    "sg:address":"Seining 3",
    "sg:city":"Tiefenbach",
    "sg:phone":"+49 8546/2261",
    "sg:postcode":"94113",
    "sg:province":"Bayern",
    "wof:name":"Eduard Schopf",
    "wof:placetype":"venue"
},
  "geometry": {"coordinates":[13.326385,48.653584],"type":"Point"}
}