{
  "type": "Feature",
  "properties": {
    "iso:country":"DE",
    "sg:address":"Friedhofstr. 3",
    "sg:city":"Dermbach",
    "sg:phone":"+49 36964/81990",
    "sg:postcode":"36466",
    "sg:province":"Th\u00fcringen",
    "wof:name":"Elektro-kynast",
    "wof:placetype":"venue"
},
  "geometry": {"coordinates":[10.122307,50.716507],"type":"Point"}
}