{
  "type": "Feature",
  "properties": {
    "iso:country":"DE",
    "sg:address":"Scharrerstr. 3",
    "sg:city":"Grafenau",
    "sg:phone":"+49 8552/2143",
    "sg:postcode":"94481",
    "sg:province":"Bayern",
    "wof:name":"Georg Loibl Ingenieur",
    "wof:placetype":"venue"
},
  "geometry": {"coordinates":[13.3957386017,48.8550949097],"type":"Point"}
}