{
  "type": "Feature",
  "properties": {
    "iso:country":"DE",
    "sg:address":"Salmannsweilergasse 7-11",
    "sg:city":"Konstanz",
    "sg:phone":"+49 7531/23571",
    "sg:postcode":"78462",
    "sg:province":"Baden-W\u00fcrttemberg",
    "wof:name":"Bruno Fritz Gmbh & Co. Kg",
    "wof:placetype":"venue"
},
  "geometry": {"coordinates":[9.1758089066,47.6613540649],"type":"Point"}
}