{
  "type": "Feature",
  "properties": {
    "iso:country":"DE",
    "sg:address":"Krayer Str. 234",
    "sg:city":"Essen",
    "sg:phone":"+49 201/550580",
    "sg:postcode":"45307",
    "sg:province":"Nordrhein-Westfalen",
    "wof:name":"Krayer Therapiezentrum Praxis F\u00fcr Krankengymnastik,",
    "wof:placetype":"venue"
},
  "geometry": {"coordinates":[7.080624,51.466824],"type":"Point"}
}