{
  "type": "Feature",
  "properties": {
    "iso:country":"DE",
    "sg:address":"Linzhausenstr. 20a",
    "sg:city":"Linz",
    "sg:postcode":"53545",
    "sg:province":"Rheinland-Pfalz",
    "wof:name":"R. A. P. Rhein-asphalt Gmbh",
    "wof:placetype":"venue"
},
  "geometry": {"coordinates":[7.2747168541,50.569229126],"type":"Point"}
}