{
  "type": "Feature",
  "properties": {
    "iso:country":"DE",
    "sg:address":"Auf den \u00c4ckern 8",
    "sg:city":"Neustadt",
    "sg:phone":"+49 5032/7528",
    "sg:postcode":"31535",
    "sg:province":"Niedersachsen",
    "wof:name":"Heinrich Fedler",
    "wof:placetype":"venue"
},
  "geometry": {"coordinates":[9.536592,52.562401],"type":"Point"}
}