{
  "type": "Feature",
  "properties": {
    "iso:country":"DE",
    "sg:address":"Gerberstr. 27",
    "sg:city":"Villingen-Schwenningen",
    "sg:phone":"+49 7721/30942",
    "sg:postcode":"78050",
    "sg:province":"Baden-W\u00fcrttemberg",
    "wof:name":"Stiftskeller",
    "wof:placetype":"venue"
},
  "geometry": {"coordinates":[8.461769104,48.0581626892],"type":"Point"}
}