{
  "type": "Feature",
  "properties": {
    "iso:country":"DE",
    "sg:address":"Einsteinweg 3",
    "sg:city":"Plochingen",
    "sg:phone":"+49 7153/24694",
    "sg:postcode":"73207",
    "sg:province":"Baden-W\u00fcrttemberg",
    "wof:name":"Karlheinz Lau",
    "wof:placetype":"venue"
},
  "geometry": {"coordinates":[9.4289712906,48.7079811096],"type":"Point"}
}