{
  "type": "Feature",
  "properties": {
    "iso:country":"DE",
    "sg:address":"Stresemannstr. 27",
    "sg:city":"D\u00fcren",
    "sg:phone":"+49 2421/505990",
    "sg:postcode":"52349",
    "sg:province":"Nordrhein-Westfalen",
    "wof:name":"K3 Innovationen Gmbh",
    "wof:placetype":"venue"
},
  "geometry": {"coordinates":[6.496025,50.787193],"type":"Point"}
}