{
  "type": "Feature",
  "properties": {
    "iso:country":"DE",
    "sg:address":"Am Alten Spritzenhaus 4",
    "sg:city":"Schweringen",
    "sg:phone":"+49 4257/273",
    "sg:postcode":"27333",
    "sg:province":"Niedersachsen",
    "wof:name":"Hermann Stuwe",
    "wof:placetype":"venue"
},
  "geometry": {"coordinates":[9.182274,52.746525],"type":"Point"}
}