{
  "type": "Feature",
  "properties": {
    "iso:country":"DE",
    "sg:address":"Kupferstr. 2",
    "sg:city":"Annaberg-Buchholz",
    "sg:postcode":"09456",
    "sg:province":"Sachsen",
    "wof:name":"Peter Heinz",
    "wof:placetype":"venue"
},
  "geometry": {"coordinates":[13.0024232864,50.5787963867],"type":"Point"}
}