{
  "type": "Feature",
  "properties": {
    "iso:country":"DE",
    "sg:address":"Austr. 25",
    "sg:city":"Idar-Oberstein",
    "sg:phone":"+49 6781/45243",
    "sg:postcode":"55743",
    "sg:province":"Rheinland-Pfalz",
    "wof:name":"Parkhaus B\u00f6rse",
    "wof:placetype":"venue"
},
  "geometry": {"coordinates":[7.326154232,49.7028465271],"type":"Point"}
}