{
  "type": "Feature",
  "properties": {
    "iso:country":"DE",
    "sg:address":"Finkenweg 17",
    "sg:city":"Harsewinkel",
    "sg:phone":"+49 2588/605",
    "sg:postcode":"33428",
    "sg:province":"Nordrhein-Westfalen",
    "wof:name":"Friedel Menebr\u00f6cker",
    "wof:placetype":"venue"
},
  "geometry": {"coordinates":[8.14914,51.972385],"type":"Point"}
}