{
  "type": "Feature",
  "properties": {
    "iso:country":"DE",
    "sg:address":"Im Eschbacher Pfad 38",
    "sg:city":"Heitersheim",
    "sg:phone":"+49 7634/519110",
    "sg:postcode":"79423",
    "sg:province":"Baden-W\u00fcrttemberg",
    "wof:name":"Elektro Beratung S\u00fcd-west Fritz Teichmann Gmbh",
    "wof:placetype":"venue"
},
  "geometry": {"coordinates":[7.6559648514,47.8773231506],"type":"Point"}
}