{
  "type": "Feature",
  "properties": {
    "iso:country":"DE",
    "sg:address":"Daldorfer Str. 15",
    "sg:city":"Rickling",
    "sg:phone":"+49 4328/208",
    "sg:postcode":"24635",
    "sg:province":"Schleswig-Holstein",
    "wof:name":"Redaktion Med. Dent. Magazin",
    "wof:placetype":"venue"
},
  "geometry": {"coordinates":[10.1744832993,54.0003318787],"type":"Point"}
}