{
  "type": "Feature",
  "properties": {
    "iso:country":"DE",
    "sg:address":"Becksfelder Weg 9 a",
    "sg:city":"Appel",
    "sg:postcode":"21279",
    "sg:province":"Niedersachsen",
    "wof:name":"Pbi Grund Und Boden Gmbh",
    "wof:placetype":"venue"
},
  "geometry": {"coordinates":[9.752355,53.389828],"type":"Point"}
}