{
  "type": "Feature",
  "properties": {
    "iso:country":"DE",
    "sg:address":"W\u00fclpensand 1",
    "sg:city":"Hamburg",
    "sg:phone":"+49 40/817997",
    "sg:postcode":"22559",
    "sg:province":"Hamburg",
    "wof:name":"G\u00fcnther Gamperl",
    "wof:placetype":"venue"
},
  "geometry": {"coordinates":[9.749095,53.579189],"type":"Point"}
}