{
  "type": "Feature",
  "properties": {
    "iso:country":"DE",
    "sg:address":"Kreittmayrstr. 4",
    "sg:city":"Abensberg",
    "sg:phone":"+49 9443/6448",
    "sg:postcode":"93326",
    "sg:province":"Bayern",
    "wof:name":"C. Rottauscher",
    "wof:placetype":"venue"
},
  "geometry": {"coordinates":[11.8975553513,48.8086891174],"type":"Point"}
}