{
  "type": "Feature",
  "properties": {
    "iso:country":"DE",
    "sg:address":"Birkenwei\u00dfbuch",
    "sg:city":"Berglen",
    "sg:postcode":"73663",
    "sg:province":"Baden-W\u00fcrttemberg",
    "wof:name":"Homepage Des Musikverein Wei\u00dfbuch E.v.",
    "wof:placetype":"venue"
},
  "geometry": {"coordinates":[9.469328,48.861183],"type":"Point"}
}