{
  "type": "Feature",
  "properties": {
    "iso:country":"DE",
    "sg:address":"Wendelsteinstr. 5",
    "sg:city":"Vaterstetten",
    "sg:phone":"+49 8106/7375",
    "sg:postcode":"85591",
    "sg:province":"Bayern",
    "wof:name":"Angela Adelsberger",
    "wof:placetype":"venue"
},
  "geometry": {"coordinates":[11.769737,48.105419],"type":"Point"}
}