{
  "type": "Feature",
  "properties": {
    "iso:country":"DE",
    "sg:address":"Saturnstr. 8",
    "sg:city":"L\u00fcbeck",
    "sg:phone":"+49 451/501395",
    "sg:postcode":"23562",
    "sg:province":"Schleswig-Holstein",
    "wof:name":"Kurt Mai Architekt",
    "wof:placetype":"venue"
},
  "geometry": {"coordinates":[10.713944,53.829281],"type":"Point"}
}