{
  "type": "Feature",
  "properties": {
    "iso:country":"DE",
    "sg:address":"Wulfspark 54",
    "sg:city":"Hannover",
    "sg:postcode":"30559",
    "sg:province":"Niedersachsen",
    "wof:name":"\u00d6katau Gmbh",
    "wof:placetype":"venue"
},
  "geometry": {"coordinates":[9.8241701126,52.3612670898],"type":"Point"}
}