{
  "type": "Feature",
  "properties": {
    "iso:country":"DE",
    "sg:address":"Teufelsseestr. 3 D",
    "sg:city":"Berlin",
    "sg:phone":"+49 30/3047221",
    "sg:postcode":"14055",
    "sg:province":"Berlin",
    "wof:name":"San-trockenbau Gmbh",
    "wof:placetype":"venue"
},
  "geometry": {"coordinates":[13.256764,52.507515],"type":"Point"}
}