{
  "type": "Feature",
  "properties": {
    "iso:country":"DE",
    "sg:address":"Innsbrucker Str. 15",
    "sg:city":"Freiburg",
    "sg:phone":"+49 761/474787",
    "sg:postcode":"79111",
    "sg:province":"Baden-W\u00fcrttemberg",
    "wof:name":"Eberhard Cless Ingenieur",
    "wof:placetype":"venue"
},
  "geometry": {"coordinates":[7.8162379265,47.9752159119],"type":"Point"}
}