{
  "type": "Feature",
  "properties": {
    "iso:country":"DE",
    "sg:address":"Norderoog 4",
    "sg:city":"Bremen",
    "sg:phone":"+49 4976/6094110",
    "sg:postcode":"28259",
    "sg:province":"Bremen",
    "wof:name":"Willtec Messtechnik E.k.",
    "wof:placetype":"venue"
},
  "geometry": {"coordinates":[8.037459,48.021801],"type":"Point"}
}