{
  "type": "Feature",
  "properties": {
    "iso:country":"DE",
    "sg:address":"Kirchstr. 2-4",
    "sg:city":"Achern",
    "sg:phone":"+49 7841/628440",
    "sg:postcode":"77855",
    "sg:province":"Baden-W\u00fcrttemberg",
    "wof:name":"Scheck Bau Gmbh",
    "wof:placetype":"venue"
},
  "geometry": {"coordinates":[8.072013,48.629971],"type":"Point"}
}