{
  "type": "Feature",
  "properties": {
    "iso:country":"DE",
    "sg:address":"Braunschweiger Str. 22",
    "sg:city":"Burgdorf",
    "sg:phone":"+49 5136/83539",
    "sg:postcode":"31303",
    "sg:province":"Niedersachsen",
    "wof:name":"Peter Fritz",
    "wof:placetype":"venue"
},
  "geometry": {"coordinates":[10.0095758438,52.4447174072],"type":"Point"}
}