{
  "type": "Feature",
  "properties": {
    "iso:country":"DE",
    "sg:address":"Halberst\u00e4dter Str. 84",
    "sg:city":"Oschersleben",
    "sg:phone":"+49 3949/96297",
    "sg:postcode":"39387",
    "sg:province":"Sachsen-Anhalt",
    "wof:name":"Schau Mal Rein",
    "wof:placetype":"venue"
},
  "geometry": {"coordinates":[11.226305,52.025078],"type":"Point"}
}