{
  "type": "Feature",
  "properties": {
    "iso:country":"DE",
    "sg:address":"Hauptstr. 56",
    "sg:city":"Unterw\u00f6ssen",
    "sg:phone":"+49 8641/8243",
    "sg:postcode":"83246",
    "sg:province":"Bayern",
    "wof:name":"Franz Steiner",
    "wof:placetype":"venue"
},
  "geometry": {"coordinates":[12.4563932419,47.7362518311],"type":"Point"}
}