{
  "type": "Feature",
  "properties": {
    "iso:country":"DE",
    "sg:address":"Mannheimer Landstr. 36",
    "sg:city":"Brensbach",
    "sg:phone":"+49 6161/2882",
    "sg:postcode":"64395",
    "sg:province":"Hessen",
    "wof:name":"Stahlbau G\u00f6tz Kg",
    "wof:placetype":"venue"
},
  "geometry": {"coordinates":[8.8774547577,49.7505149841],"type":"Point"}
}