{
  "type": "Feature",
  "properties": {
    "iso:country":"DE",
    "sg:address":"Mierendorfstr.8",
    "sg:city":"Frankfurt am Main",
    "sg:phone":"+49 69/21235332",
    "sg:postcode":"60320",
    "sg:province":"Hessen",
    "wof:name":"Schule-grundschule-bildung-schule_haupt",
    "wof:placetype":"venue"
},
  "geometry": {"coordinates":[8.666815,50.145584],"type":"Point"}
}