{
  "type": "Feature",
  "properties": {
    "iso:country":"DE",
    "sg:address":"Hellweg 13",
    "sg:city":"Erwitte",
    "sg:phone":"+49 2943/2946",
    "sg:postcode":"59597",
    "sg:province":"Nordrhein-Westfalen",
    "wof:name":"Gabriel",
    "wof:placetype":"venue"
},
  "geometry": {"coordinates":[8.339595,51.612007],"type":"Point"}
}