{
  "type": "Feature",
  "properties": {
    "iso:country":"DE",
    "sg:address":"Kreuzbreite 3",
    "sg:city":"Bissendorf",
    "sg:phone":"+49 5402/7222",
    "sg:postcode":"49143",
    "sg:province":"Niedersachsen",
    "wof:name":"M. Lonzer",
    "wof:placetype":"venue"
},
  "geometry": {"coordinates":[8.250855,52.28587],"type":"Point"}
}