{
  "type": "Feature",
  "properties": {
    "iso:country":"DE",
    "sg:address":"Flehgasse 10",
    "sg:city":"Rinchnach",
    "sg:phone":"+49 9921/807833",
    "sg:postcode":"94269",
    "sg:province":"Bayern",
    "wof:name":"Digital Art. Multimedia. Werbung. Design. Gmbh",
    "wof:placetype":"venue"
},
  "geometry": {"coordinates":[13.201507,48.950146],"type":"Point"}
}