{
  "type": "Feature",
  "properties": {
    "iso:country":"DE",
    "sg:address":"Birkenfelder Weg 30",
    "sg:city":"Maroldsweisach",
    "sg:phone":"+49 9532/1300",
    "sg:postcode":"96126",
    "sg:province":"Bayern",
    "wof:name":"Wilfried Wolfsberger Gmbh",
    "wof:placetype":"venue"
},
  "geometry": {"coordinates":[10.652147,50.19566],"type":"Point"}
}