{
  "type": "Feature",
  "properties": {
    "iso:country":"DE",
    "sg:address":"Heinrichstr.",
    "sg:city":"Aschersleben",
    "sg:phone":"+49 3473/814368",
    "sg:postcode":"06449",
    "sg:province":"Sachsen-Anhalt",
    "wof:name":"Anni Lohmann",
    "wof:placetype":"venue"
},
  "geometry": {"coordinates":[11.466485,51.755219],"type":"Point"}
}