{
  "type": "Feature",
  "properties": {
    "iso:country":"DE",
    "sg:address":"Rohrkamp 10",
    "sg:city":"Braunschweig",
    "sg:phone":"+49 531/63670",
    "sg:postcode":"38126",
    "sg:province":"Niedersachsen",
    "wof:name":"Malermeister Peter Otte Gmbh",
    "wof:placetype":"venue"
},
  "geometry": {"coordinates":[10.570218,52.225986],"type":"Point"}
}