{
  "type": "Feature",
  "properties": {
    "iso:country":"DE",
    "sg:address":"Leimitzer Str. 20",
    "sg:city":"Hof",
    "sg:phone":"+49 9281/41048",
    "sg:postcode":"95028",
    "sg:province":"Bayern",
    "wof:name":"Gambrinusstuben",
    "wof:placetype":"venue"
},
  "geometry": {"coordinates":[11.9250354767,50.3157081604],"type":"Point"}
}