{
  "type": "Feature",
  "properties": {
    "iso:country":"DE",
    "sg:address":"Burgstr. 62",
    "sg:city":"Stuttgart",
    "sg:phone":"+49 711/6873196",
    "sg:postcode":"70569",
    "sg:province":"Baden-W\u00fcrttemberg",
    "wof:name":"Alfred Kurz Heissmangel",
    "wof:placetype":"venue"
},
  "geometry": {"coordinates":[9.1334753036,48.7417831421],"type":"Point"}
}