{
  "type": "Feature",
  "properties": {
    "iso:country":"DE",
    "sg:address":"Schlo\u00dfstr. 1 a",
    "sg:city":"Rimbach",
    "sg:phone":"+49 6253/7379",
    "sg:postcode":"64668",
    "sg:province":"Hessen",
    "wof:name":"Marlin Gmbh",
    "wof:placetype":"venue"
},
  "geometry": {"coordinates":[8.7584533691,49.6224861145],"type":"Point"}
}