{
  "type": "Feature",
  "properties": {
    "iso:country":"DE",
    "sg:address":"Theodor-Klippel-Str. 7",
    "sg:city":"Erlangen",
    "sg:phone":"+49 9131/127120",
    "sg:postcode":"91052",
    "sg:province":"Bayern",
    "wof:name":"Geromed Gmbh",
    "wof:placetype":"venue"
},
  "geometry": {"coordinates":[11.0112218857,49.5830230713],"type":"Point"}
}