{
  "type": "Feature",
  "properties": {
    "iso:country":"DE",
    "sg:address":"Vehlager Str. 36",
    "sg:city":"Espelkamp",
    "sg:phone":"+49 5743/722",
    "sg:postcode":"32339",
    "sg:province":"Nordrhein-Westfalen",
    "wof:name":"Heinz-dieter H\u00fclsmann",
    "wof:placetype":"venue"
},
  "geometry": {"coordinates":[8.555717,52.362682],"type":"Point"}
}