{
  "type": "Feature",
  "properties": {
    "iso:country":"DE",
    "sg:address":"Hellenstr. 18",
    "sg:city":"Rockenberg",
    "sg:phone":"+49 6033/66818",
    "sg:postcode":"35519",
    "sg:province":"Hessen",
    "wof:name":"Paul Hartmann",
    "wof:placetype":"venue"
},
  "geometry": {"coordinates":[8.7353792191,50.4347953796],"type":"Point"}
}