{
  "type": "Feature",
  "properties": {
    "iso:country":"DE",
    "sg:address":"Bornaische Str. 180",
    "sg:city":"Leipzig",
    "sg:phone":"+49 341/3385194",
    "sg:postcode":"04279",
    "sg:province":"Sachsen",
    "wof:name":"S. Dietze",
    "wof:placetype":"venue"
},
  "geometry": {"coordinates":[12.391993,51.288502],"type":"Point"}
}