{
  "type": "Feature",
  "properties": {
    "iso:country":"DE",
    "sg:address":"Auf dem Loh 12",
    "sg:city":"Hannover",
    "sg:phone":"+49 511/702129",
    "sg:postcode":"30167",
    "sg:province":"Niedersachsen",
    "wof:name":"Ackermann-bauer",
    "wof:placetype":"venue"
},
  "geometry": {"coordinates":[9.717249,52.393097],"type":"Point"}
}