{
  "type": "Feature",
  "properties": {
    "iso:country":"DE",
    "sg:address":"Gartenstr. 21",
    "sg:city":"Dernau",
    "sg:phone":"+49 2643/1382",
    "sg:postcode":"53507",
    "sg:province":"Rheinland-Pfalz",
    "wof:name":"Karl Kreuzberg",
    "wof:placetype":"venue"
},
  "geometry": {"coordinates":[7.0442099571,50.534324646],"type":"Point"}
}