{
  "type": "Feature",
  "properties": {
    "iso:country":"DE",
    "sg:address":"Frankfurter Str. 41",
    "sg:city":"Gr\u00e4venwiesbach",
    "sg:phone":"+49 6086/275",
    "sg:postcode":"61279",
    "sg:province":"Hessen",
    "wof:name":"Tkv Tankcontainer & Kessel- Wagenvermietung Gmbh",
    "wof:placetype":"venue"
},
  "geometry": {"coordinates":[8.4567337036,50.3861732483],"type":"Point"}
}