{
  "type": "Feature",
  "properties": {
    "iso:country":"DE",
    "sg:address":"Hof Heydstadt 1",
    "sg:city":"Ederm\u00fcnde",
    "sg:phone":"+49 5665/7887",
    "sg:postcode":"34295",
    "sg:province":"Hessen",
    "wof:name":"R. Nachbar Ingenieur",
    "wof:placetype":"venue"
},
  "geometry": {"coordinates":[9.4415035248,51.2134017944],"type":"Point"}
}