{
  "type": "Feature",
  "properties": {
    "iso:country":"DE",
    "sg:address":"Buchenhofener Str 23",
    "sg:city":"Wuppertal",
    "sg:phone":"+49 202/271540",
    "sg:postcode":"42329",
    "sg:province":"Nordrhein-Westfalen",
    "wof:name":"Karl Gottaut Gmbh",
    "wof:placetype":"venue"
},
  "geometry": {"coordinates":[7.10849,51.226772],"type":"Point"}
}