{
  "type": "Feature",
  "properties": {
    "iso:country":"DE",
    "sg:address":"Forststr. 9",
    "sg:city":"Leipzig",
    "sg:postcode":"04229",
    "sg:province":"Sachsen",
    "wof:name":"Acivo Prozessfinanzierungs Ag",
    "wof:placetype":"venue"
},
  "geometry": {"coordinates":[12.329903,51.320213],"type":"Point"}
}