{
  "type": "Feature",
  "properties": {
    "iso:country":"DE",
    "sg:address":"Langer Kornweg 10",
    "sg:city":"Kelsterbach",
    "sg:postcode":"65451",
    "sg:province":"Hessen",
    "wof:name":"Aldi Gmbh & Co. Kg",
    "wof:placetype":"venue"
},
  "geometry": {"coordinates":[8.5164327621,50.0534286499],"type":"Point"}
}