{
  "type": "Feature",
  "properties": {
    "iso:country":"DE",
    "sg:address":"Steinbergstr. 1",
    "sg:city":"Wangen",
    "sg:phone":"+49 7506/225",
    "sg:postcode":"88239",
    "sg:province":"Baden-W\u00fcrttemberg",
    "wof:name":"Allg\u00e4uer Emmentalerk\u00e4serei Leupold Eg",
    "wof:placetype":"venue"
},
  "geometry": {"coordinates":[9.8253011703,47.7473182678],"type":"Point"}
}