{
  "type": "Feature",
  "properties": {
    "iso:country":"DE",
    "sg:address":"Martinstr. 21",
    "sg:city":"Eberdingen",
    "sg:phone":"+49 7042/5665",
    "sg:postcode":"71735",
    "sg:province":"Baden-W\u00fcrttemberg",
    "wof:name":"Joachim Karok",
    "wof:placetype":"venue"
},
  "geometry": {"coordinates":[8.93945,48.89262],"type":"Point"}
}