{
  "type": "Feature",
  "properties": {
    "iso:country":"DE",
    "sg:address":"Breite Str. 12",
    "sg:city":"Brake",
    "sg:phone":"+49 4401/4888",
    "sg:postcode":"26919",
    "sg:province":"Niedersachsen",
    "wof:name":"Tinama",
    "wof:placetype":"venue"
},
  "geometry": {"coordinates":[8.47855,53.326321],"type":"Point"}
}