{
  "type": "Feature",
  "properties": {
    "iso:country":"DE",
    "sg:address":"Siegener Str. 21",
    "sg:city":"Frankenberg",
    "sg:postcode":"35066",
    "sg:province":"Hessen",
    "wof:name":"Heinrich M\u00fctze Bauunternehmen Gmbh & Co. Kg",
    "wof:placetype":"venue"
},
  "geometry": {"coordinates":[8.785423,51.053715],"type":"Point"}
}