{
  "type": "Feature",
  "properties": {
    "iso:country":"DE",
    "sg:address":"Kirchheimer Str. 31",
    "sg:city":"Notzingen",
    "sg:phone":"+49 7021/483941",
    "sg:postcode":"73274",
    "sg:province":"Baden-W\u00fcrttemberg",
    "wof:name":"Herbert Maier",
    "wof:placetype":"venue"
},
  "geometry": {"coordinates":[9.4584188461,48.6679229736],"type":"Point"}
}