{
  "type": "Feature",
  "properties": {
    "iso:country":"DE",
    "sg:address":"Hartenfelsweg 2",
    "sg:city":"K\u00f6ln",
    "sg:postcode":"50767",
    "sg:province":"Nordrhein-Westfalen",
    "wof:name":"Spedition Gessner Gmbh",
    "wof:placetype":"venue"
},
  "geometry": {"coordinates":[6.8851838112,51.0048217773],"type":"Point"}
}