{
  "type": "Feature",
  "properties": {
    "iso:country":"DE",
    "sg:address":"Im Alten Dorfe 11",
    "sg:city":"G\u00f6ttingen",
    "sg:phone":"+49 551/61158",
    "sg:postcode":"37079",
    "sg:province":"Niedersachsen",
    "wof:name":"Armin Mecke",
    "wof:placetype":"venue"
},
  "geometry": {"coordinates":[9.889914,51.563057],"type":"Point"}
}