{
  "type": "Feature",
  "properties": {
    "iso:country":"DE",
    "sg:address":"Unterster Weg 44",
    "sg:city":"Wetzlar",
    "sg:phone":"+49 641/21041",
    "sg:postcode":"35582",
    "sg:province":"Hessen",
    "wof:name":"Rudolf Mehl Gmbh",
    "wof:placetype":"venue"
},
  "geometry": {"coordinates":[8.5965499878,50.5561714172],"type":"Point"}
}