{
  "type": "Feature",
  "properties": {
    "iso:country":"DE",
    "sg:address":"Mittelstr. 12",
    "sg:city":"Magdeburg",
    "sg:phone":"+49 391/59220",
    "sg:postcode":"39114",
    "sg:province":"Sachsen-Anhalt",
    "wof:name":"Bsu Bewachungs- Und Sicherheitsunternehmen Gmbh",
    "wof:placetype":"venue"
},
  "geometry": {"coordinates":[11.6515598297,52.1303482056],"type":"Point"}
}