{
  "type": "Feature",
  "properties": {
    "iso:country":"DE",
    "sg:address":"Ingolst\u00e4dter Str. 100",
    "sg:city":"Manching",
    "sg:phone":"+49 8459/6536",
    "sg:postcode":"85077",
    "sg:province":"Bayern",
    "wof:name":"Hallenbad Manching",
    "wof:placetype":"venue"
},
  "geometry": {"coordinates":[11.4715709686,48.7162780762],"type":"Point"}
}