{
  "type": "Feature",
  "properties": {
    "iso:country":"DE",
    "sg:address":"Gahmener Str. 217",
    "sg:city":"L\u00fcnen",
    "sg:postcode":"44532",
    "sg:province":"Nordrhein-Westfalen",
    "wof:name":"D. Ludwig Schl\u00fcsseldienst",
    "wof:placetype":"venue"
},
  "geometry": {"coordinates":[7.505179882,51.5799407959],"type":"Point"}
}