{
  "type": "Feature",
  "properties": {
    "iso:country":"DE",
    "sg:address":"Am Dorneywald 17",
    "sg:city":"Witten",
    "sg:phone":"+49 2302/48629",
    "sg:postcode":"58454",
    "sg:province":"Nordrhein-Westfalen",
    "wof:name":"R. Breimann",
    "wof:placetype":"venue"
},
  "geometry": {"coordinates":[7.3706679344,51.4812164307],"type":"Point"}
}