{
  "type": "Feature",
  "properties": {
    "iso:country":"DE",
    "sg:address":"Sandstr. 3",
    "sg:city":"Freiburg",
    "sg:phone":"+49 761/552260",
    "sg:postcode":"79104",
    "sg:province":"Baden-W\u00fcrttemberg",
    "wof:name":"Hansj\u00f6rg Merkle",
    "wof:placetype":"venue"
},
  "geometry": {"coordinates":[7.8633198738,48.0075683594],"type":"Point"}
}