{
  "type": "Feature",
  "properties": {
    "iso:country":"DE",
    "sg:address":"Albert-Lortzing-Str. 32",
    "sg:city":"Polch",
    "sg:phone":"+49 2654/6151",
    "sg:postcode":"56751",
    "sg:province":"Rheinland-Pfalz",
    "wof:name":"Anneliese M\u00fcller",
    "wof:placetype":"venue"
},
  "geometry": {"coordinates":[7.304825,50.293491],"type":"Point"}
}