{
  "type": "Feature",
  "properties": {
    "iso:country":"DE",
    "sg:address":"An der Lohm\u00fchle",
    "sg:city":"M\u00f6nchengladbach",
    "sg:phone":"+49 2166/915275",
    "sg:postcode":"41189",
    "sg:province":"Nordrhein-Westfalen",
    "wof:name":"Jochen Lingen",
    "wof:placetype":"venue"
},
  "geometry": {"coordinates":[6.4144001007,51.101436615],"type":"Point"}
}