{
  "type": "Feature",
  "properties": {
    "iso:country":"DE",
    "sg:address":"Kalzhofen 48",
    "sg:city":"Oberstaufen",
    "sg:phone":"+49 8386/2115",
    "sg:postcode":"87534",
    "sg:province":"Bayern",
    "wof:name":"G\u00e4stehaus Tannenalp",
    "wof:placetype":"venue"
},
  "geometry": {"coordinates":[10.0227489471,47.5542106628],"type":"Point"}
}