{
  "type": "Feature",
  "properties": {
    "iso:country":"DE",
    "sg:address":"Am Kurscheidshof 1",
    "sg:city":"Niederkassel",
    "sg:phone":"+49 2208/4342",
    "sg:postcode":"53859",
    "sg:province":"Nordrhein-Westfalen",
    "wof:name":"Schmitt",
    "wof:placetype":"venue"
},
  "geometry": {"coordinates":[7.0527682304,50.7837371826],"type":"Point"}
}