{
  "type": "Feature",
  "properties": {
    "iso:country":"DE",
    "sg:address":"Am Festungsgraben 45",
    "sg:city":"Oldenburg",
    "sg:phone":"+49 441/2331",
    "sg:postcode":"26135",
    "sg:province":"Niedersachsen",
    "wof:name":"Vertrauens\u00e4rztlicher-dienst D. Lva Oldenburg-bremen",
    "wof:placetype":"venue"
},
  "geometry": {"coordinates":[8.2205276489,53.1373710632],"type":"Point"}
}