{
  "type": "Feature",
  "properties": {
    "iso:country":"DE",
    "sg:address":"Kupferdreher Markt 9",
    "sg:city":"Essen",
    "sg:postcode":"45257",
    "sg:province":"Nordrhein-Westfalen",
    "wof:name":"Bagus Und Kampmann H\u00f6rger\u00e4teakustik Gmbh",
    "wof:placetype":"venue"
},
  "geometry": {"coordinates":[7.0818891525,51.3907699585],"type":"Point"}
}