{
  "type": "Feature",
  "properties": {
    "iso:country":"DE",
    "sg:address":"Puschkinstr. 61-63",
    "sg:city":"Schwerin",
    "sg:postcode":"19055",
    "sg:province":"Mecklenburg-Vorpommern",
    "wof:name":"Apotheke Am Markt Susanne Hallier E. K.",
    "wof:placetype":"venue"
},
  "geometry": {"coordinates":[11.414908,53.62822],"type":"Point"}
}