{
  "type": "Feature",
  "properties": {
    "iso:country":"DE",
    "sg:address":"Am H\u00fcttenpfad 33",
    "sg:city":"Balve",
    "sg:postcode":"58802",
    "sg:province":"Nordrhein-Westfalen",
    "wof:name":"Dieter Kannengie\u00dfer Gmbh",
    "wof:placetype":"venue"
},
  "geometry": {"coordinates":[7.8656311035,51.335735321],"type":"Point"}
}