{
  "type": "Feature",
  "properties": {
    "iso:country":"DE",
    "sg:address":"Haid 1",
    "sg:city":"Straubing",
    "sg:phone":"+49 9421/740140",
    "sg:postcode":"94315",
    "sg:province":"Bayern",
    "wof:name":"Straubinger Konserven- Und Sauerkrautfabrik A. Buchner",
    "wof:placetype":"venue"
},
  "geometry": {"coordinates":[12.573706,48.881397],"type":"Point"}
}