{
  "type": "Feature",
  "properties": {
    "iso:country":"DE",
    "sg:address":"Panoramastr. 4",
    "sg:city":"Utting",
    "sg:phone":"+49 8806/95342",
    "sg:postcode":"86919",
    "sg:province":"Bayern",
    "wof:name":"Ampersand Gmbh Informatik",
    "wof:placetype":"venue"
},
  "geometry": {"coordinates":[11.0843706131,48.0198631287],"type":"Point"}
}