{
  "type": "Feature",
  "properties": {
    "iso:country":"DE",
    "sg:address":"Saarlandstr. 4",
    "sg:city":"Ludwigshafen",
    "sg:phone":"+49 621/574372",
    "sg:postcode":"67061",
    "sg:province":"Rheinland-Pfalz",
    "wof:name":"Gerd Janka",
    "wof:placetype":"venue"
},
  "geometry": {"coordinates":[8.4388198853,49.4713516235],"type":"Point"}
}