{
  "type": "Feature",
  "properties": {
    "iso:country":"DE",
    "sg:address":"Am G\u00fcterbahnhof",
    "sg:city":"Bad Aibling",
    "sg:postcode":"83043",
    "sg:province":"Bayern",
    "wof:name":"Hermann Kuntz",
    "wof:placetype":"venue"
},
  "geometry": {"coordinates":[12.004947,47.861122],"type":"Point"}
}