{
  "type": "Feature",
  "properties": {
    "iso:country":"DE",
    "sg:address":"Jacobsenweg 6-8",
    "sg:city":"Hamburg",
    "sg:phone":"+49 40",
    "sg:postcode":"22525",
    "sg:province":"Hamburg",
    "wof:name":"Axro Distribution Partner Gmbh",
    "wof:placetype":"venue"
},
  "geometry": {"coordinates":[9.9129085541,53.5950012207],"type":"Point"}
}