{
  "type": "Feature",
  "properties": {
    "iso:country":"DE",
    "sg:address":"Voltastr. 7",
    "sg:city":"Dietzenbach",
    "sg:phone":"+49 6074/44031",
    "sg:postcode":"63128",
    "sg:province":"Hessen",
    "wof:name":"Prodel Montagesysteme Gmbh",
    "wof:placetype":"venue"
},
  "geometry": {"coordinates":[8.792608,50.003826],"type":"Point"}
}