{
  "type": "Feature",
  "properties": {
    "iso:country":"DE",
    "sg:address":"Bredenstr. 3",
    "sg:city":"Celle",
    "sg:phone":"+49 5141/43084",
    "sg:postcode":"29225",
    "sg:province":"Niedersachsen",
    "wof:name":"Heinz Lenzing Kg",
    "wof:placetype":"venue"
},
  "geometry": {"coordinates":[10.058298,52.618992],"type":"Point"}
}