{
  "type": "Feature",
  "properties": {
    "iso:country":"DE",
    "sg:address":"Kortumstr. 110",
    "sg:city":"Bochum",
    "sg:phone":"+49 234/685882",
    "sg:postcode":"44787",
    "sg:province":"Nordrhein-Westfalen",
    "wof:name":"Heyermann B\u00e4ckerei Gmbh",
    "wof:placetype":"venue"
},
  "geometry": {"coordinates":[7.217498,51.48328],"type":"Point"}
}