{
  "type": "Feature",
  "properties": {
    "iso:country":"DE",
    "sg:address":"Bahnhofstr. 9",
    "sg:city":"Ellrich",
    "sg:phone":"+49 36332/20201",
    "sg:postcode":"99755",
    "sg:province":"Th\u00fcringen",
    "wof:name":"Fritz Kellner",
    "wof:placetype":"venue"
},
  "geometry": {"coordinates":[10.667785,51.581841],"type":"Point"}
}