{
  "type": "Feature",
  "properties": {
    "iso:country":"DE",
    "sg:address":"Siemensstr. 10",
    "sg:city":"Ha\u00dfloch",
    "sg:phone":"+49 6324/4829",
    "sg:postcode":"67454",
    "sg:province":"Rheinland-Pfalz",
    "wof:name":"K. Scholl",
    "wof:placetype":"venue"
},
  "geometry": {"coordinates":[8.236197,49.344902],"type":"Point"}
}