{
  "type": "Feature",
  "properties": {
    "iso:country":"DE",
    "sg:address":"Hermann-Seger Str. 18",
    "sg:city":"Frechen",
    "sg:phone":"+49 9973/1365",
    "sg:postcode":"50226",
    "sg:province":"Nordrhein-Westfalen",
    "wof:name":"Tragl-textil-gmbh",
    "wof:placetype":"venue"
},
  "geometry": {"coordinates":[12.844004,49.304855],"type":"Point"}
}