{
  "type": "Feature",
  "properties": {
    "iso:country":"DE",
    "sg:address":"Herzog-Friedrich-Str. 45",
    "sg:city":"Kiel",
    "sg:postcode":"24103",
    "sg:province":"Schleswig-Holstein",
    "wof:name":"Diakoniewerk Es Castellot Gmbh",
    "wof:placetype":"venue"
},
  "geometry": {"coordinates":[10.1294803619,54.3178443909],"type":"Point"}
}