{
  "type": "Feature",
  "properties": {
    "iso:country":"DE",
    "sg:address":"Ostpreu\u00dfendamm 44",
    "sg:city":"Berlin",
    "sg:phone":"+49 30/7729032",
    "sg:postcode":"12207",
    "sg:province":"Berlin",
    "wof:name":"Plura Grundst\u00fccks Gmbh",
    "wof:placetype":"venue"
},
  "geometry": {"coordinates":[13.3174962997,52.428237915],"type":"Point"}
}