{
  "type": "Feature",
  "properties": {
    "iso:country":"DE",
    "sg:address":"An Der Freiheit 2",
    "sg:city":"Tann",
    "sg:phone":"+49 4966/828726",
    "sg:postcode":"36142",
    "sg:province":"Hessen",
    "wof:name":"Lothar G\u00d6pfert Kg",
    "wof:placetype":"venue"
},
  "geometry": {"coordinates":[10.0025053024,50.6624603271],"type":"Point"}
}