{
  "type": "Feature",
  "properties": {
    "iso:country":"DE",
    "sg:address":"Breitenbacher Str. 40",
    "sg:city":"Schl\u00fcchtern",
    "sg:phone":"+49 6661/96830",
    "sg:postcode":"36381",
    "sg:province":"Hessen",
    "wof:name":"Zf-technik Gmbh",
    "wof:placetype":"venue"
},
  "geometry": {"coordinates":[9.523305,50.347664],"type":"Point"}
}