{
  "type": "Feature",
  "properties": {
    "iso:country":"DE",
    "sg:address":"Fischbrunnenplatz 12",
    "sg:city":"Eggenfelden",
    "sg:phone":"+49 8721/1853",
    "sg:postcode":"84307",
    "sg:province":"Bayern",
    "wof:name":"Buchner",
    "wof:placetype":"venue"
},
  "geometry": {"coordinates":[12.761438,48.403858],"type":"Point"}
}