{
  "type": "Feature",
  "properties": {
    "iso:country":"DE",
    "sg:address":"Langendorfer Berg",
    "sg:city":"Stralsund",
    "sg:postcode":"18437",
    "sg:province":"Mecklenburg-Vorpommern",
    "wof:name":"Tief- Und Verkehrsbau Stralsund Gmbh",
    "wof:placetype":"venue"
},
  "geometry": {"coordinates":[13.0244846344,54.3013038635],"type":"Point"}
}