{
  "type": "Feature",
  "properties": {
    "iso:country":"DE",
    "sg:address":"Wiesenstr. 2",
    "sg:city":"Bad Br\u00fcckenau",
    "sg:postcode":"97769",
    "sg:province":"Bayern",
    "wof:name":"Bau Betriebs- Und Dienstleistungsges. Stadt",
    "wof:placetype":"venue"
},
  "geometry": {"coordinates":[9.7705192566,50.3228569031],"type":"Point"}
}