{
  "type": "Feature",
  "properties": {
    "iso:country":"DE",
    "sg:address":"G\u00e4rtnerstr. 85",
    "sg:city":"Scharbeutz",
    "sg:phone":"+49 4524/517",
    "sg:postcode":"23684",
    "sg:province":"Schleswig-Holstein",
    "wof:name":"Alten- Und Pflegeheim J\u00f6rg Hein",
    "wof:placetype":"venue"
},
  "geometry": {"coordinates":[10.710369,54.018017],"type":"Point"}
}