{
  "type": "Feature",
  "properties": {
    "iso:country":"DE",
    "sg:address":"Saladin-Schmitt-Str. 54",
    "sg:city":"Bochum",
    "sg:phone":"+49 234/301274",
    "sg:postcode":"44789",
    "sg:province":"Nordrhein-Westfalen",
    "wof:name":"R\u00fcdiger Wandschneider Ingenieur",
    "wof:placetype":"venue"
},
  "geometry": {"coordinates":[7.2220039368,51.4702148438],"type":"Point"}
}