{
  "type": "Feature",
  "properties": {
    "iso:country":"DE",
    "sg:address":"Hauptstr. 21",
    "sg:city":"Neunkirchen-Seelscheid",
    "sg:phone":"+49 2247/2361",
    "sg:postcode":"53819",
    "sg:province":"Nordrhein-Westfalen",
    "wof:name":"Heribert V\u00f6ller",
    "wof:placetype":"venue"
},
  "geometry": {"coordinates":[7.333321,50.839218],"type":"Point"}
}