{
  "type": "Feature",
  "properties": {
    "iso:country":"DE",
    "sg:address":"Marktstr. 19",
    "sg:city":"Stadland",
    "sg:phone":"+49 4732/8139",
    "sg:postcode":"26935",
    "sg:province":"Niedersachsen",
    "wof:name":"Sigward Meier",
    "wof:placetype":"venue"
},
  "geometry": {"coordinates":[8.451571,53.39629],"type":"Point"}
}