{
  "type": "Feature",
  "properties": {
    "iso:country":"DE",
    "sg:address":"Robert-Koch-Str. 22",
    "sg:city":"Kaufungen",
    "sg:phone":"+49 5605/2786",
    "sg:postcode":"34260",
    "sg:province":"Hessen",
    "wof:name":"Heinrich Braun Elektroinstallation",
    "wof:placetype":"venue"
},
  "geometry": {"coordinates":[9.643312,51.281612],"type":"Point"}
}