{
  "type": "Feature",
  "properties": {
    "iso:country":"DE",
    "sg:address":"Heinrich-Mann-Str. 11",
    "sg:city":"Zittau",
    "sg:phone":"+49 3583/709710",
    "sg:postcode":"02763",
    "sg:province":"Sachsen",
    "wof:name":"Anlagentechnik Gmbh",
    "wof:placetype":"venue"
},
  "geometry": {"coordinates":[14.7919197083,50.9005317688],"type":"Point"}
}