{
  "type": "Feature",
  "properties": {
    "iso:country":"DE",
    "sg:address":"Koblenzer Str. 11",
    "sg:city":"Bonn",
    "sg:phone":"+49 228/357066",
    "sg:postcode":"53173",
    "sg:province":"Nordrhein-Westfalen",
    "wof:name":"Reiseb\u00fcro Kr\u00f6ger Inh. Wolfgang Kr\u00f6ger",
    "wof:placetype":"venue"
},
  "geometry": {"coordinates":[7.1536269188,50.6857872009],"type":"Point"}
}