{
  "type": "Feature",
  "properties": {
    "iso:country":"DE",
    "sg:address":"Ronsdorfer Str. 172-174",
    "sg:city":"Remscheid",
    "sg:phone":"+49 4921/914350",
    "sg:postcode":"42855",
    "sg:province":"Nordrhein-Westfalen",
    "wof:name":"Grimm Edelstahl-werke Gmbh & Co Kg",
    "wof:placetype":"venue"
},
  "geometry": {"coordinates":[7.195816,51.199135],"type":"Point"}
}