{
  "type": "Feature",
  "properties": {
    "iso:country":"DE",
    "sg:address":"Bachstr. 12",
    "sg:city":"Bad F\u00fcssing",
    "sg:phone":"+49 8531/24483",
    "sg:postcode":"94072",
    "sg:province":"Bayern",
    "wof:name":"Franz Kellermann Masseur",
    "wof:placetype":"venue"
},
  "geometry": {"coordinates":[13.3095197678,48.3457298279],"type":"Point"}
}