{
  "type": "Feature",
  "properties": {
    "iso:country":"DE",
    "sg:address":"Irenenstr. 82",
    "sg:city":"D\u00fcsseldorf",
    "sg:phone":"+49 211/4220113",
    "sg:postcode":"40468",
    "sg:province":"Nordrhein-Westfalen",
    "wof:name":"Bernhard J\u00f6sten",
    "wof:placetype":"venue"
},
  "geometry": {"coordinates":[6.77806,51.268257],"type":"Point"}
}