{
  "type": "Feature",
  "properties": {
    "iso:country":"DE",
    "sg:city":"N\u00fcmbrecht",
    "sg:phone":"+49 2293/909534",
    "sg:postcode":"51588",
    "sg:province":"Nordrhein-Westfalen",
    "wof:name":"Arbeitskreis Werbe-, Mode- Industriefotografie Awi E.v.",
    "wof:placetype":"venue"
},
  "geometry": {"coordinates":[7.542751,50.905434],"type":"Point"}
}