{
  "type": "Feature",
  "properties": {
    "iso:country":"DE",
    "sg:address":"Jungstr. 8",
    "sg:city":"Erlangen",
    "sg:phone":"+49 9131/51589",
    "sg:postcode":"91054",
    "sg:province":"Bayern",
    "wof:name":"Dr. Jutta Neiss Tier\u00e4rztin",
    "wof:placetype":"venue"
},
  "geometry": {"coordinates":[11.0321779251,49.6024360657],"type":"Point"}
}