{
  "type": "Feature",
  "properties": {
    "iso:country":"DE",
    "sg:address":"Teschendorfer Chaussee 20a",
    "sg:city":"Burg Stargard",
    "sg:phone":"+49 39603/20296",
    "sg:postcode":"17094",
    "sg:province":"Mecklenburg-Vorpommern",
    "wof:name":"Dieter Niemann",
    "wof:placetype":"venue"
},
  "geometry": {"coordinates":[13.321639,53.493252],"type":"Point"}
}