{
  "type": "Feature",
  "properties": {
    "iso:country":"DE",
    "sg:address":"Wei\u00dfer Weg 1",
    "sg:city":"Marktgraitz",
    "sg:phone":"+49 9574/4732",
    "sg:postcode":"96257",
    "sg:province":"Bayern",
    "wof:name":"B. Und M. Schm\u00f6lzing",
    "wof:placetype":"venue"
},
  "geometry": {"coordinates":[11.193798,50.188198],"type":"Point"}
}