{
  "type": "Feature",
  "properties": {
    "iso:country":"DE",
    "sg:address":"Wilhelmstr. 46",
    "sg:city":"Filderstadt",
    "sg:phone":"+49 7158/2691",
    "sg:postcode":"70794",
    "sg:province":"Baden-W\u00fcrttemberg",
    "wof:name":"Walter H\u00f6hn Heissmangel",
    "wof:placetype":"venue"
},
  "geometry": {"coordinates":[9.2414226532,48.6738891602],"type":"Point"}
}