{
  "type": "Feature",
  "properties": {
    "iso:country":"DE",
    "sg:address":"Beethovenstr. 55",
    "sg:city":"J\u00fcterbog",
    "sg:phone":"+49 3372/406027",
    "sg:postcode":"14913",
    "sg:province":"Brandenburg",
    "wof:name":"Helmut Lindner Steuerberater",
    "wof:placetype":"venue"
},
  "geometry": {"coordinates":[13.0590467453,51.9972267151],"type":"Point"}
}