{
  "type": "Feature",
  "properties": {
    "iso:country":"DE",
    "sg:address":"Untere Pforte 32",
    "sg:city":"Gau-Weinheim",
    "sg:phone":"+49 6732/1001",
    "sg:postcode":"55578",
    "sg:province":"Rheinland-Pfalz",
    "wof:name":"Lothar Mann",
    "wof:placetype":"venue"
},
  "geometry": {"coordinates":[8.0498476028,49.842830658],"type":"Point"}
}