{
  "type": "Feature",
  "properties": {
    "iso:country":"DE",
    "sg:address":"Hauptstr. 57",
    "sg:city":"Liebenstein",
    "sg:phone":"+49 36205/95051",
    "sg:postcode":"99330",
    "sg:province":"Th\u00fcringen",
    "wof:name":"Langbein",
    "wof:placetype":"venue"
},
  "geometry": {"coordinates":[10.854719162,50.768913269],"type":"Point"}
}