{
  "type": "Feature",
  "properties": {
    "iso:country":"DE",
    "sg:address":"Freisenbergstr. 20",
    "sg:city":"L\u00fcdenscheid",
    "sg:phone":"+49 2351/79807",
    "sg:postcode":"58513",
    "sg:province":"Nordrhein-Westfalen",
    "wof:name":"Helmut Binczyk Gmbh & Co. Kg",
    "wof:placetype":"venue"
},
  "geometry": {"coordinates":[7.603616,51.24567],"type":"Point"}
}