{
  "type": "Feature",
  "properties": {
    "iso:country":"DE",
    "sg:address":"Bassenheimer Str. 31",
    "sg:city":"Kettig",
    "sg:phone":"+49 2637/600998",
    "sg:postcode":"56220",
    "sg:province":"Rheinland-Pfalz",
    "wof:name":"Gro\u00df",
    "wof:placetype":"venue"
},
  "geometry": {"coordinates":[7.4591178894,50.3896331787],"type":"Point"}
}