{
  "type": "Feature",
  "properties": {
    "iso:country":"DE",
    "sg:address":"F\u00fcrther Freiheit 6",
    "sg:city":"F\u00fcrth",
    "sg:phone":"+49 911/772211",
    "sg:postcode":"90762",
    "sg:province":"Bayern",
    "wof:name":"Ammon & Schnatzky Inh. Ingomar Schnatzky",
    "wof:placetype":"venue"
},
  "geometry": {"coordinates":[10.9911184311,49.4720573425],"type":"Point"}
}