{
  "type": "Feature",
  "properties": {
    "iso:country":"DE",
    "sg:address":"Antoniusstr. 8",
    "sg:city":"Beckum",
    "sg:phone":"+49 2521/5763",
    "sg:postcode":"59269",
    "sg:province":"Nordrhein-Westfalen",
    "wof:name":"M\u00fctterzentrum",
    "wof:placetype":"venue"
},
  "geometry": {"coordinates":[8.042909,51.758137],"type":"Point"}
}