{
  "type": "Feature",
  "properties": {
    "iso:country":"DE",
    "sg:address":"Westliche Ringstr. 18",
    "sg:city":"B\u00f6hmfeld",
    "sg:phone":"+49 8406/92910",
    "sg:postcode":"85113",
    "sg:province":"Bayern",
    "wof:name":"Lst Landwirtsch. Anlagen Und Stalleinrichtungen Vertriebs-gmbh",
    "wof:placetype":"venue"
},
  "geometry": {"coordinates":[11.36184,48.861378],"type":"Point"}
}