{
  "type": "Feature",
  "properties": {
    "iso:country":"DE",
    "sg:address":"Kampweg 6",
    "sg:city":"Rosdorf",
    "sg:phone":"+49 551/500670",
    "sg:postcode":"37124",
    "sg:province":"Niedersachsen",
    "wof:name":"Transfair Umzugs- Und Transport Gmbh",
    "wof:placetype":"venue"
},
  "geometry": {"coordinates":[9.8910293579,51.5099868774],"type":"Point"}
}