{
  "type": "Feature",
  "properties": {
    "iso:country":"DE",
    "sg:address":"Wiesenstr. 64",
    "sg:city":"Tamm",
    "sg:phone":"+49 711/631474",
    "sg:postcode":"71732",
    "sg:province":"Baden-W\u00fcrttemberg",
    "wof:name":"Heinrich M\u00fcmmler",
    "wof:placetype":"venue"
},
  "geometry": {"coordinates":[9.138007,48.922077],"type":"Point"}
}