{
  "type": "Feature",
  "properties": {
    "iso:country":"DE",
    "sg:address":"Bergstr. 26",
    "sg:city":"Hamburg",
    "sg:phone":"+49 40/326864",
    "sg:postcode":"20095",
    "sg:province":"Hamburg",
    "wof:name":"Internatioanl Sports Equipment & Trading",
    "wof:placetype":"venue"
},
  "geometry": {"coordinates":[9.995023,53.551441],"type":"Point"}
}