{
  "type": "Feature",
  "properties": {
    "iso:country":"DE",
    "sg:address":"Heidelberger Str. 32",
    "sg:city":"Schriesheim",
    "sg:postcode":"69198",
    "sg:province":"Baden-W\u00fcrttemberg",
    "wof:name":"Billard Pro-service Und Shop",
    "wof:placetype":"venue"
},
  "geometry": {"coordinates":[8.6646699905,49.4740943909],"type":"Point"}
}