{
  "type": "Feature",
  "properties": {
    "iso:country":"DE",
    "sg:address":"Bahnhofstr. 26",
    "sg:city":"Wedemark",
    "sg:phone":"+49 5130/7400",
    "sg:postcode":"30900",
    "sg:province":"Niedersachsen",
    "wof:name":"Gildestuben",
    "wof:placetype":"venue"
},
  "geometry": {"coordinates":[9.7488021851,52.5227584839],"type":"Point"}
}