{
  "type": "Feature",
  "properties": {
    "iso:country":"DE",
    "sg:address":"Schillerstr. 7",
    "sg:city":"Stockach",
    "sg:phone":"+49 7771/2445",
    "sg:postcode":"78333",
    "sg:province":"Baden-W\u00fcrttemberg",
    "wof:name":"M. Grunenberg",
    "wof:placetype":"venue"
},
  "geometry": {"coordinates":[9.007686615,47.8500061035],"type":"Point"}
}