{
  "type": "Feature",
  "properties": {
    "iso:country":"DE",
    "sg:address":"Kaiser-Joseph-Str. 222",
    "sg:city":"Freiburg",
    "sg:phone":"+49 761/381101",
    "sg:postcode":"79098",
    "sg:province":"Baden-W\u00fcrttemberg",
    "wof:name":"Friedrich Freytag Gmbh",
    "wof:placetype":"venue"
},
  "geometry": {"coordinates":[7.8498058319,47.9949417114],"type":"Point"}
}