{
  "type": "Feature",
  "properties": {
    "iso:country":"DE",
    "sg:address":"Unterer Dammweg 12",
    "sg:city":"Karlsruhe",
    "sg:phone":"+49 721/978930",
    "sg:postcode":"76149",
    "sg:province":"Baden-W\u00fcrttemberg",
    "wof:name":"Rolf Althuon Laborbedarf",
    "wof:placetype":"venue"
},
  "geometry": {"coordinates":[8.369193,49.06461],"type":"Point"}
}