{
  "type": "Feature",
  "properties": {
    "iso:country":"DE",
    "sg:address":"Am S\u00fcdfriedhof 17",
    "sg:city":"Bonn",
    "sg:phone":"+49 228/950410",
    "sg:postcode":"53175",
    "sg:province":"Nordrhein-Westfalen",
    "wof:name":"Kreutz Werkzeuge Gmbh & Co Kg",
    "wof:placetype":"venue"
},
  "geometry": {"coordinates":[7.126938,50.701767],"type":"Point"}
}