{
  "type": "Feature",
  "properties": {
    "iso:country":"DE",
    "sg:address":"Tulpenweg 6",
    "sg:city":"Gro\u00df Kreutz",
    "sg:phone":"+49 33207/32204",
    "sg:postcode":"14550",
    "sg:province":"Brandenburg",
    "wof:name":"Hochbau Kurt Till",
    "wof:placetype":"venue"
},
  "geometry": {"coordinates":[12.783895,52.400398],"type":"Point"}
}