{
  "type": "Feature",
  "properties": {
    "iso:country":"DE",
    "sg:address":"Weidkamp 124",
    "sg:city":"Essen",
    "sg:phone":"+49 201/661386",
    "sg:postcode":"45355",
    "sg:province":"Nordrhein-Westfalen",
    "wof:name":"Friedhelm Barnscheidt",
    "wof:placetype":"venue"
},
  "geometry": {"coordinates":[6.9482750893,51.4814376831],"type":"Point"}
}