{
  "type": "Feature",
  "properties": {
    "iso:country":"DE",
    "sg:address":"Hochstr. 53",
    "sg:city":"Frankfurt",
    "sg:phone":"+49 69/281845",
    "sg:postcode":"60313",
    "sg:province":"Hessen",
    "wof:name":"Pizza-hut",
    "wof:placetype":"venue"
},
  "geometry": {"coordinates":[8.6731081009,50.1150245667],"type":"Point"}
}