{
  "type": "Feature",
  "properties": {
    "iso:country":"DE",
    "sg:address":"Marktstr. 3",
    "sg:city":"Neuhausen",
    "sg:phone":"+49 7158/67000",
    "sg:postcode":"73765",
    "sg:province":"Baden-W\u00fcrttemberg",
    "wof:name":"Kronen-apotheke",
    "wof:placetype":"venue"
},
  "geometry": {"coordinates":[9.279229,48.684471],"type":"Point"}
}