{
  "type": "Feature",
  "properties": {
    "iso:country":"DE",
    "sg:address":"Aufh\u00e4userstr. 25",
    "sg:city":"Hannover",
    "sg:phone":"+49 511/431955",
    "sg:postcode":"30457",
    "sg:province":"Niedersachsen",
    "wof:name":"Wis Wettberger-immobilien Service Gmbh",
    "wof:placetype":"venue"
},
  "geometry": {"coordinates":[9.684605,52.334587],"type":"Point"}
}