{
  "type": "Feature",
  "properties": {
    "iso:country":"DE",
    "sg:address":"St.-Wendeler-Str. 58a",
    "sg:city":"Bruchm\u00fchlbach-Miesau",
    "sg:phone":"+49 6372/8727",
    "sg:postcode":"66892",
    "sg:province":"Rheinland-Pfalz",
    "wof:name":"Ecker & Partner Gmbh",
    "wof:placetype":"venue"
},
  "geometry": {"coordinates":[7.4295349121,49.4080657959],"type":"Point"}
}