{
  "type": "Feature",
  "properties": {
    "iso:country":"DE",
    "sg:address":"Mittelstr. 118",
    "sg:city":"Lemgo",
    "sg:phone":"+49 5261/2384",
    "sg:postcode":"32657",
    "sg:province":"Nordrhein-Westfalen",
    "wof:name":"Albert Engbers Gmbh",
    "wof:placetype":"venue"
},
  "geometry": {"coordinates":[8.896267,52.028568],"type":"Point"}
}