{
  "type": "Feature",
  "properties": {
    "iso:country":"DE",
    "sg:address":"An der Steinleiten 7",
    "sg:city":"Bruckberg",
    "sg:phone":"+49 9824/58270",
    "sg:postcode":"91590",
    "sg:province":"Bayern",
    "wof:name":"Werkstatt F\u00fcr Behinderte Bruckberger Heime",
    "wof:placetype":"venue"
},
  "geometry": {"coordinates":[10.69932,49.364517],"type":"Point"}
}