{
  "type": "Feature",
  "properties": {
    "iso:country":"DE",
    "sg:address":"Sch\u00e4keln 8",
    "sg:city":"Varrel",
    "sg:phone":"+49 4274/380",
    "sg:postcode":"27259",
    "sg:province":"Niedersachsen",
    "wof:name":"Erich Sander",
    "wof:placetype":"venue"
},
  "geometry": {"coordinates":[8.764115,52.639618],"type":"Point"}
}