{
  "type": "Feature",
  "properties": {
    "iso:country":"DE",
    "sg:address":"Gottlieb-Daimler-Str 32",
    "sg:city":"Sulz",
    "sg:phone":"+49 7454/9966910",
    "sg:postcode":"72172",
    "sg:province":"Baden-W\u00fcrttemberg",
    "wof:name":"5-p Kg",
    "wof:placetype":"venue"
},
  "geometry": {"coordinates":[8.639909,48.355042],"type":"Point"}
}