{
  "type": "Feature",
  "properties": {
    "iso:country":"DE",
    "sg:address":"Kellerstr. 4",
    "sg:city":"Bad M\u00fcnder",
    "sg:phone":"+49 5042/952577",
    "sg:postcode":"31848",
    "sg:province":"Niedersachsen",
    "wof:name":"A. Grieger",
    "wof:placetype":"venue"
},
  "geometry": {"coordinates":[9.46322155,52.1987915039],"type":"Point"}
}