{
  "type": "Feature",
  "properties": {
    "iso:country":"DE",
    "sg:address":"Baumstr. 4",
    "sg:city":"Bad Liebenzell",
    "sg:phone":"+49 7052/2623",
    "sg:postcode":"75378",
    "sg:province":"Baden-W\u00fcrttemberg",
    "wof:name":"K. Bodamer",
    "wof:placetype":"venue"
},
  "geometry": {"coordinates":[8.7304420471,48.7742424011],"type":"Point"}
}