{
  "type": "Feature",
  "properties": {
    "iso:country":"DE",
    "sg:address":"Markt 2a",
    "sg:city":"Schwanebeck",
    "sg:phone":"+49 39424/367",
    "sg:postcode":"39397",
    "sg:province":"Sachsen-Anhalt",
    "wof:name":"Eiscafe Schmidt",
    "wof:placetype":"venue"
},
  "geometry": {"coordinates":[11.120028,51.967922],"type":"Point"}
}