{
  "type": "Feature",
  "properties": {
    "iso:country":"DE",
    "sg:address":"Sophienstr. 2b",
    "sg:city":"Leipzig",
    "sg:phone":"+49 341/4617382",
    "sg:postcode":"04158",
    "sg:province":"Sachsen",
    "wof:name":"U. Demmler Franke",
    "wof:placetype":"venue"
},
  "geometry": {"coordinates":[12.3229627609,51.3915672302],"type":"Point"}
}