{
  "type": "Feature",
  "properties": {
    "iso:country":"DE",
    "sg:address":"Brinkstr. 5",
    "sg:city":"Bremen",
    "sg:phone":"+49 421/3967359",
    "sg:postcode":"28219",
    "sg:province":"Bremen",
    "wof:name":"Care",
    "wof:placetype":"venue"
},
  "geometry": {"coordinates":[8.786168,53.104641],"type":"Point"}
}