{
  "type": "Feature",
  "properties": {
    "iso:country":"DE",
    "sg:address":"Tucholskystr. 30",
    "sg:city":"Frankfurt",
    "sg:postcode":"60598",
    "sg:province":"Hessen",
    "wof:name":"Fracon Unternehmens- Beratung Gmbh",
    "wof:placetype":"venue"
},
  "geometry": {"coordinates":[8.6874475479,50.0957756042],"type":"Point"}
}