{
  "type": "Feature",
  "properties": {
    "iso:country":"DE",
    "sg:address":"Steinbo\u00dfweg 15",
    "sg:city":"Eslarn",
    "sg:phone":"+49 9653/224",
    "sg:postcode":"92693",
    "sg:province":"Bayern",
    "wof:name":"Karl Forster",
    "wof:placetype":"venue"
},
  "geometry": {"coordinates":[12.52021,49.588047],"type":"Point"}
}