{
  "type": "Feature",
  "properties": {
    "iso:country":"DE",
    "sg:address":"Bilholtstr. 23",
    "sg:city":"Olfen",
    "sg:phone":"+49 2595/1003",
    "sg:postcode":"59399",
    "sg:province":"Nordrhein-Westfalen",
    "wof:name":"Pielemeier & Klingenstein",
    "wof:placetype":"venue"
},
  "geometry": {"coordinates":[7.379592,51.709122],"type":"Point"}
}