{
  "type": "Feature",
  "properties": {
    "iso:country":"DE",
    "sg:address":"Pierer Str. 64",
    "sg:city":"Inden",
    "sg:phone":"+49 2465/2344",
    "sg:postcode":"52459",
    "sg:province":"Nordrhein-Westfalen",
    "wof:name":"Stephan Fergen",
    "wof:placetype":"venue"
},
  "geometry": {"coordinates":[6.397277832,50.8612976074],"type":"Point"}
}