{
  "type": "Feature",
  "properties": {
    "iso:country":"DE",
    "sg:address":"Brunnenstr. 125",
    "sg:city":"Berlin",
    "sg:phone":"+49 30/4634692",
    "sg:postcode":"13355",
    "sg:province":"Berlin",
    "wof:name":"Monika Luft",
    "wof:placetype":"venue"
},
  "geometry": {"coordinates":[13.394279,52.540066],"type":"Point"}
}