{
  "type": "Feature",
  "properties": {
    "iso:country":"DE",
    "sg:address":"Altdorferweg 2",
    "sg:city":"Leipzig",
    "sg:phone":"+49 341/8774773",
    "sg:postcode":"04289",
    "sg:province":"Sachsen",
    "wof:name":"Robert K\u00f6hler",
    "wof:placetype":"venue"
},
  "geometry": {"coordinates":[12.4423036575,51.2848548889],"type":"Point"}
}