{
  "type": "Feature",
  "properties": {
    "iso:country":"DE",
    "sg:address":"Oberf\u00f6hringer Str. 186",
    "sg:city":"M\u00fcnchen",
    "sg:postcode":"81925",
    "sg:province":"Bayern",
    "wof:name":"Scan Werk Gmbh",
    "wof:placetype":"venue"
},
  "geometry": {"coordinates":[11.6255636215,48.1689758301],"type":"Point"}
}