{
  "type": "Feature",
  "properties": {
    "iso:country":"DE",
    "sg:address":"Friedrich-Gau\u00df-Str. 4",
    "sg:city":"Schweinfurt",
    "sg:phone":"+49 9721/77110",
    "sg:postcode":"97424",
    "sg:province":"Bayern",
    "wof:name":"Seuferts Backhaus Willi Seufert Gmbh",
    "wof:placetype":"venue"
},
  "geometry": {"coordinates":[10.236707,50.031704],"type":"Point"}
}