{
  "type": "Feature",
  "properties": {
    "iso:country":"DE",
    "sg:address":"Dorfstr. 36",
    "sg:city":"Blankenhain",
    "sg:phone":"+49 36459/42033",
    "sg:postcode":"99444",
    "sg:province":"Th\u00fcringen",
    "wof:name":"Sven Hauspurg",
    "wof:placetype":"venue"
},
  "geometry": {"coordinates":[11.2825565338,50.8467102051],"type":"Point"}
}