{
  "type": "Feature",
  "properties": {
    "iso:country":"DE",
    "sg:address":"Bahnhofstr. 12",
    "sg:city":"K\u00f6nigs Wusterhausen",
    "sg:phone":"+49 3375",
    "sg:postcode":"15711",
    "sg:province":"Brandenburg",
    "wof:name":"Sparkasse Dahme Spreewald",
    "wof:placetype":"venue"
},
  "geometry": {"coordinates":[13.7205400467,52.2974128723],"type":"Point"}
}