{
  "type": "Feature",
  "properties": {
    "iso:country":"DE",
    "sg:address":"Lister Meile 71",
    "sg:city":"Hannover",
    "sg:phone":"+49 511/393083",
    "sg:postcode":"30161",
    "sg:province":"Niedersachsen",
    "wof:name":"Musikus",
    "wof:placetype":"venue"
},
  "geometry": {"coordinates":[9.748374939,52.3868141174],"type":"Point"}
}