{
  "type": "Feature",
  "properties": {
    "iso:country":"DE",
    "sg:address":"Auweg 6",
    "sg:city":"Neu-Ulm",
    "sg:postcode":"89233",
    "sg:province":"Bayern",
    "wof:name":"Bm-leasing- Vertriebsges. Mbh",
    "wof:placetype":"venue"
},
  "geometry": {"coordinates":[10.0710048676,48.3641548157],"type":"Point"}
}