{
  "type": "Feature",
  "properties": {
    "iso:country":"DE",
    "sg:address":"Karlstr. 20",
    "sg:city":"Penzberg",
    "sg:phone":"+49 8856/2888",
    "sg:postcode":"82377",
    "sg:province":"Bayern",
    "wof:name":"Herbert Leistle Ingenieur",
    "wof:placetype":"venue"
},
  "geometry": {"coordinates":[11.3772993088,47.7514266968],"type":"Point"}
}