{
  "type": "Feature",
  "properties": {
    "iso:country":"DE",
    "sg:address":"Bahnhofstr. 25",
    "sg:city":"St. Ingbert",
    "sg:phone":"+49 6894/5556",
    "sg:postcode":"66386",
    "sg:province":"Saarland",
    "wof:name":"Hans Wagner",
    "wof:placetype":"venue"
},
  "geometry": {"coordinates":[7.161154,49.281895],"type":"Point"}
}