{
  "type": "Feature",
  "properties": {
    "iso:country":"DE",
    "sg:address":"Kaiserstr. 1 d",
    "sg:city":"Kirkel",
    "sg:phone":"+49 6849/541",
    "sg:postcode":"66459",
    "sg:province":"Saarland",
    "wof:name":"Gastst\u00e4tte Georg Ohg",
    "wof:placetype":"venue"
},
  "geometry": {"coordinates":[7.2393841743,49.2902259827],"type":"Point"}
}