{
  "type": "Feature",
  "properties": {
    "iso:country":"DE",
    "sg:address":"Waschleither Str. 22",
    "sg:city":"Beierfeld",
    "sg:phone":"+49 3774/61131",
    "sg:postcode":"08340",
    "sg:province":"Sachsen",
    "wof:name":"Sven Ehmer Architekt",
    "wof:placetype":"venue"
},
  "geometry": {"coordinates":[12.793014,50.562618],"type":"Point"}
}