{
  "type": "Feature",
  "properties": {
    "iso:country":"DE",
    "sg:address":"Talsiedlung 3",
    "sg:city":"K\u00fclsheim",
    "sg:phone":"+49 9345/415",
    "sg:postcode":"97900",
    "sg:province":"Baden-W\u00fcrttemberg",
    "wof:name":"Karl Ballweg",
    "wof:placetype":"venue"
},
  "geometry": {"coordinates":[9.469642,49.694416],"type":"Point"}
}