{
  "type": "Feature",
  "properties": {
    "iso:country":"DE",
    "sg:address":"L\u00f6bdergraben 24",
    "sg:city":"Jena",
    "sg:phone":"+49 3641/441533",
    "sg:postcode":"07743",
    "sg:province":"Th\u00fcringen",
    "wof:name":"Hans Kemter",
    "wof:placetype":"venue"
},
  "geometry": {"coordinates":[11.590598,50.927746],"type":"Point"}
}