{
  "type": "Feature",
  "properties": {
    "iso:country":"DE",
    "sg:address":"August-Bebel-Str. 3",
    "sg:city":"Hohenstein-Ernstthal",
    "sg:postcode":"09337",
    "sg:province":"Sachsen",
    "wof:name":"Taf Industrie-service Kg",
    "wof:placetype":"venue"
},
  "geometry": {"coordinates":[12.7100334167,50.7966041565],"type":"Point"}
}