{
  "type": "Feature",
  "properties": {
    "iso:country":"DE",
    "sg:address":"Rotenberg 6",
    "sg:city":"Marburg",
    "sg:phone":"+49 6421/162573",
    "sg:postcode":"35037",
    "sg:province":"Hessen",
    "wof:name":"Websolution Gbr - Internet Publishing",
    "wof:placetype":"venue"
},
  "geometry": {"coordinates":[8.7601251602,50.8064308167],"type":"Point"}
}