{
  "type": "Feature",
  "properties": {
    "iso:country":"DE",
    "sg:address":"Wilhelmsstr. 19",
    "sg:city":"Kassel",
    "sg:phone":"+49 561/14788",
    "sg:postcode":"34117",
    "sg:province":"Hessen",
    "wof:name":"K.-h. Quentin",
    "wof:placetype":"venue"
},
  "geometry": {"coordinates":[9.4924182892,51.3134269714],"type":"Point"}
}