{
  "type": "Feature",
  "properties": {
    "iso:country":"DE",
    "sg:address":"Distelbeck 21",
    "sg:city":"Wuppertal",
    "sg:phone":"+49 202/432965",
    "sg:postcode":"42119",
    "sg:province":"Nordrhein-Westfalen",
    "wof:name":"Falko Weber",
    "wof:placetype":"venue"
},
  "geometry": {"coordinates":[7.152012825,51.2532958984],"type":"Point"}
}