{
  "type": "Feature",
  "properties": {
    "iso:country":"DE",
    "sg:address":"Dellwiger Str. 17",
    "sg:city":"Essen",
    "sg:phone":"+49 201/698801",
    "sg:postcode":"45357",
    "sg:province":"Nordrhein-Westfalen",
    "wof:name":"Alfred Jost",
    "wof:placetype":"venue"
},
  "geometry": {"coordinates":[6.920958,51.487537],"type":"Point"}
}