{
  "type": "Feature",
  "properties": {
    "iso:country":"DE",
    "sg:address":"Aschaffstr. 21",
    "sg:city":"Waldaschaff",
    "sg:phone":"+49 6021/560855",
    "sg:postcode":"63857",
    "sg:province":"Bayern",
    "wof:name":"A. Fitschen",
    "wof:placetype":"venue"
},
  "geometry": {"coordinates":[9.30221,49.97121],"type":"Point"}
}