{
  "type": "Feature",
  "properties": {
    "iso:country":"DE",
    "sg:address":"Im Krummen Arm 3D",
    "sg:city":"Lilienthal",
    "sg:phone":"+49 4298/4890",
    "sg:postcode":"28865",
    "sg:province":"Niedersachsen",
    "wof:name":"J\u00fcrgen Tiemann Architekt",
    "wof:placetype":"venue"
},
  "geometry": {"coordinates":[8.941599,53.157749],"type":"Point"}
}