{
  "type": "Feature",
  "properties": {
    "iso:country":"DE",
    "sg:address":"Potsdamer Str. 100",
    "sg:city":"Ludwigsfelde",
    "sg:phone":"+49 3378/879557",
    "sg:postcode":"14974",
    "sg:province":"Brandenburg",
    "wof:name":"Ristorante Casa-romana",
    "wof:placetype":"venue"
},
  "geometry": {"coordinates":[13.250538826,52.3067588806],"type":"Point"}
}