{
  "type": "Feature",
  "properties": {
    "iso:country":"DE",
    "sg:address":"Heidenb\u00fchl 2",
    "sg:city":"Aldingen",
    "sg:phone":"+49 7424/86179",
    "sg:postcode":"78554",
    "sg:province":"Baden-W\u00fcrttemberg",
    "wof:name":"Horst Scharf",
    "wof:placetype":"venue"
},
  "geometry": {"coordinates":[8.670911,48.101082],"type":"Point"}
}