{
  "type": "Feature",
  "properties": {
    "iso:country":"DE",
    "sg:address":"Blumenstr. 25",
    "sg:city":"Heusweiler",
    "sg:phone":"+49 6806/8945",
    "sg:postcode":"66265",
    "sg:province":"Saarland",
    "wof:name":"R. Gro\u00df",
    "wof:placetype":"venue"
},
  "geometry": {"coordinates":[6.989835,49.326054],"type":"Point"}
}