{
  "type": "Feature",
  "properties": {
    "iso:country":"DE",
    "sg:address":"Rathausplatz 3",
    "sg:city":"Asbach-B\u00e4umenheim",
    "sg:phone":"+49 906/91881",
    "sg:postcode":"86663",
    "sg:province":"Bayern",
    "wof:name":"Roko Gmbh",
    "wof:placetype":"venue"
},
  "geometry": {"coordinates":[10.815617,48.681065],"type":"Point"}
}