{
  "type": "Feature",
  "properties": {
    "iso:country":"DE",
    "sg:address":"Auf der Hude 66-70",
    "sg:city":"L\u00fcneburg",
    "sg:phone":"+49 4131/37046",
    "sg:postcode":"21339",
    "sg:province":"Niedersachsen",
    "wof:name":"Siemens Ag",
    "wof:placetype":"venue"
},
  "geometry": {"coordinates":[10.4135665894,53.2580451965],"type":"Point"}
}