{
  "type": "Feature",
  "properties": {
    "iso:country":"DE",
    "sg:address":"Max-Planck-Str. 10",
    "sg:city":"Vreden",
    "sg:phone":"+49 2564/93360",
    "sg:postcode":"48691",
    "sg:province":"Nordrhein-Westfalen",
    "wof:name":"Ventana Deutschland Verwaltungsges. Mbh",
    "wof:placetype":"venue"
},
  "geometry": {"coordinates":[6.7970972061,52.0204811096],"type":"Point"}
}