{
  "type": "Feature",
  "properties": {
    "iso:country":"DE",
    "sg:address":"Welle 4",
    "sg:city":"Bielefeld",
    "sg:phone":"+49 521/69126",
    "sg:postcode":"33602",
    "sg:province":"Nordrhein-Westfalen",
    "wof:name":"Jochen Adler",
    "wof:placetype":"venue"
},
  "geometry": {"coordinates":[8.531978,52.019722],"type":"Point"}
}