{
  "type": "Feature",
  "properties": {
    "iso:country":"DE",
    "sg:address":"Tennenbacherstr. 8",
    "sg:city":"Neuenburg",
    "sg:phone":"+49 7631/72636",
    "sg:postcode":"79395",
    "sg:province":"Baden-W\u00fcrttemberg",
    "wof:name":"Egon Furler",
    "wof:placetype":"venue"
},
  "geometry": {"coordinates":[7.564568,47.816349],"type":"Point"}
}