{
  "type": "Feature",
  "properties": {
    "iso:country":"DE",
    "sg:address":"\u00d6scheiderwg. 25",
    "sg:city":"Solingen",
    "sg:phone":"+49 4921/2262090",
    "sg:postcode":"42699",
    "sg:province":"Nordrhein-Westfalen",
    "wof:name":"Metallveredlung Gmbh & Co Kg",
    "wof:placetype":"venue"
},
  "geometry": {"coordinates":[7.025834,51.148678],"type":"Point"}
}