{
  "type": "Feature",
  "properties": {
    "iso:country":"DE",
    "sg:address":"Kinzigheimer Weg 37",
    "sg:city":"Bruchk\u00f6bel",
    "sg:phone":"+49 6181",
    "sg:postcode":"63486",
    "sg:province":"Hessen",
    "wof:name":"Nice Price 4 You Handyzubeh\u00f6r, Handys, Kartenvertr\u00e4ge,uhren",
    "wof:placetype":"venue"
},
  "geometry": {"coordinates":[8.9232788086,50.1712188721],"type":"Point"}
}