{
  "type": "Feature",
  "properties": {
    "iso:country":"DE",
    "sg:address":"Charlottenburger Str. 9",
    "sg:city":"Geesthacht",
    "sg:phone":"+49 4941/5280920",
    "sg:postcode":"21502",
    "sg:province":"Schleswig-Holstein",
    "wof:name":"Hanse Chemie Ag",
    "wof:placetype":"venue"
},
  "geometry": {"coordinates":[10.346125,53.438042],"type":"Point"}
}