{
  "type": "Feature",
  "properties": {
    "iso:country":"DE",
    "sg:address":"Stromberger Str. 6",
    "sg:city":"Bingen",
    "sg:phone":"+49 6721/33106",
    "sg:postcode":"55411",
    "sg:province":"Rheinland-Pfalz",
    "wof:name":"Helmut Hertz",
    "wof:placetype":"venue"
},
  "geometry": {"coordinates":[7.888959,49.964108],"type":"Point"}
}