{
  "type": "Feature",
  "properties": {
    "iso:country":"DE",
    "sg:address":"Kirchstr. 20",
    "sg:city":"Hilders",
    "sg:phone":"+49 6681/285",
    "sg:postcode":"36115",
    "sg:province":"Hessen",
    "wof:name":"Kath. Pfarramt St. Bartholom\u00e4us",
    "wof:placetype":"venue"
},
  "geometry": {"coordinates":[10.0032253265,50.5735244751],"type":"Point"}
}