{
  "type": "Feature",
  "properties": {
    "iso:country":"DE",
    "sg:address":"Dr. Friedrichs Ring. 51",
    "sg:city":"Zwickau",
    "sg:phone":"+49 4937/5212581",
    "sg:postcode":"08056",
    "sg:province":"Sachsen",
    "wof:name":"Prickner Systembuero Gmbh",
    "wof:placetype":"venue"
},
  "geometry": {"coordinates":[12.4963340759,50.721786499],"type":"Point"}
}