{
  "type": "Feature",
  "properties": {
    "iso:country":"DE",
    "sg:address":"Hasenheide 9",
    "sg:city":"Bosau",
    "sg:phone":"+49 4527/264",
    "sg:postcode":"23715",
    "sg:province":"Schleswig-Holstein",
    "wof:name":"Helga Jeche",
    "wof:placetype":"venue"
},
  "geometry": {"coordinates":[10.4319972992,54.1026878357],"type":"Point"}
}