{
  "type": "Feature",
  "properties": {
    "iso:country":"DE",
    "sg:address":"Am G\u00e4nsemarkt 8",
    "sg:city":"Lunden",
    "sg:phone":"+49 4882/843",
    "sg:postcode":"25774",
    "sg:province":"Schleswig-Holstein",
    "wof:name":"Hotel-restaurant Dithmarscher Hof",
    "wof:placetype":"venue"
},
  "geometry": {"coordinates":[9.0257463455,54.3304595947],"type":"Point"}
}