{
  "type": "Feature",
  "properties": {
    "iso:country":"DE",
    "sg:address":"Von-Trotha-Str. 9a",
    "sg:city":"M\u00fcnchen",
    "sg:phone":"+49 89/4303339",
    "sg:postcode":"81827",
    "sg:province":"Bayern",
    "wof:name":"Aribert Meyer Modeagentur",
    "wof:placetype":"venue"
},
  "geometry": {"coordinates":[11.6892595291,48.1072387695],"type":"Point"}
}