{
  "type": "Feature",
  "properties": {
    "iso:country":"DE",
    "sg:address":"Wilhelmistr. 5",
    "sg:city":"Hamburg",
    "sg:phone":"+49 40/824451",
    "sg:postcode":"22605",
    "sg:province":"Hamburg",
    "wof:name":"Agentpol Jasper Siems Gmbh",
    "wof:placetype":"venue"
},
  "geometry": {"coordinates":[9.8690032959,53.5582275391],"type":"Point"}
}