{
  "type": "Feature",
  "properties": {
    "iso:country":"DE",
    "sg:address":"Emsstr. 24",
    "sg:city":"Emsdetten",
    "sg:phone":"+49 2572/80664",
    "sg:postcode":"48282",
    "sg:province":"Nordrhein-Westfalen",
    "wof:name":"Heinz-g\u00fcnter Schmitz",
    "wof:placetype":"venue"
},
  "geometry": {"coordinates":[7.5290870667,52.1757698059],"type":"Point"}
}