{
  "type": "Feature",
  "properties": {
    "iso:country":"DE",
    "sg:address":"Heinrich-Gr\u00fcber-Str. 4",
    "sg:city":"Berlin",
    "sg:phone":"+49 30/5627054",
    "sg:postcode":"12621",
    "sg:province":"Berlin",
    "wof:name":"Simone Mandel",
    "wof:placetype":"venue"
},
  "geometry": {"coordinates":[13.5879392624,52.5121383667],"type":"Point"}
}