{
  "type": "Feature",
  "properties": {
    "iso:country":"DE",
    "sg:address":"Frankfurter Allee 195",
    "sg:city":"Berlin",
    "sg:phone":"+49 30/5599619",
    "sg:postcode":"10365",
    "sg:province":"Berlin",
    "wof:name":"Klaus-peter Str\u00f6hl",
    "wof:placetype":"venue"
},
  "geometry": {"coordinates":[13.490118,52.512337],"type":"Point"}
}