{
  "type": "Feature",
  "properties": {
    "iso:country":"DE",
    "sg:address":"Ludwigstr. 38",
    "sg:city":"Lingen",
    "sg:phone":"+49 591/58093",
    "sg:postcode":"49809",
    "sg:province":"Niedersachsen",
    "wof:name":"S. Stancic",
    "wof:placetype":"venue"
},
  "geometry": {"coordinates":[7.3334460258,52.5198059082],"type":"Point"}
}