{
  "type": "Feature",
  "properties": {
    "iso:country":"DE",
    "sg:address":"Eckgartenstr. 18",
    "sg:city":"Remseck",
    "sg:phone":"+49 7146/891026",
    "sg:postcode":"71686",
    "sg:province":"Baden-W\u00fcrttemberg",
    "wof:name":"Klaus Vogel",
    "wof:placetype":"venue"
},
  "geometry": {"coordinates":[9.248208046,48.8645515442],"type":"Point"}
}