{
  "type": "Feature",
  "properties": {
    "iso:country":"DE",
    "sg:address":"Obere M\u00fchle 17",
    "sg:city":"Bad Rappenau",
    "sg:phone":"+49 7066/994410",
    "sg:postcode":"74906",
    "sg:province":"Baden-W\u00fcrttemberg",
    "wof:name":"Mogler-kassen Gmbh",
    "wof:placetype":"venue"
},
  "geometry": {"coordinates":[9.1038131714,49.2098121643],"type":"Point"}
}