{
  "type": "Feature",
  "properties": {
    "iso:country":"DE",
    "sg:address":"Goldsbergstr. 16",
    "sg:city":"Wesel",
    "sg:phone":"+49 2803/1844",
    "sg:postcode":"46487",
    "sg:province":"Nordrhein-Westfalen",
    "wof:name":"Britta Ingenleuf Rechtsanw\u00e4ltin",
    "wof:placetype":"venue"
},
  "geometry": {"coordinates":[6.5731110573,51.6277160645],"type":"Point"}
}