{
  "type": "Feature",
  "properties": {
    "iso:country":"DE",
    "sg:address":"Rheinstr. 33",
    "sg:city":"Dreieich",
    "sg:phone":"+49 6103/81541",
    "sg:postcode":"63303",
    "sg:province":"Hessen",
    "wof:name":"Ev. Pfarramt G\u00f6tzenhain",
    "wof:placetype":"venue"
},
  "geometry": {"coordinates":[8.7358617783,49.9952964783],"type":"Point"}
}