{
  "type": "Feature",
  "properties": {
    "iso:country":"DE",
    "sg:address":"Breslauer Str.1",
    "sg:city":"Herzlake",
    "sg:postcode":"49770",
    "sg:province":"Niedersachsen",
    "wof:name":"Eushop",
    "wof:placetype":"venue"
},
  "geometry": {"coordinates":[7.60838,52.682018],"type":"Point"}
}