{
  "type": "Feature",
  "properties": {
    "iso:country":"DE",
    "sg:address":"Elbstr. 4",
    "sg:city":"Mei\u00dfen",
    "sg:phone":"+49 3521/404575",
    "sg:postcode":"01662",
    "sg:province":"Sachsen",
    "wof:name":"U-k-a-verwaltungs Gmbh",
    "wof:placetype":"venue"
},
  "geometry": {"coordinates":[13.472296,51.163517],"type":"Point"}
}