{
  "type": "Feature",
  "properties": {
    "iso:country":"DE",
    "sg:address":"Dingesweg 8",
    "sg:city":"Kelkheim",
    "sg:phone":"+49 6195/62906",
    "sg:postcode":"65779",
    "sg:province":"Hessen",
    "wof:name":"E. H. Hellwig",
    "wof:placetype":"venue"
},
  "geometry": {"coordinates":[8.4482746124,50.1406517029],"type":"Point"}
}