{
  "type": "Feature",
  "properties": {
    "iso:country":"DE",
    "sg:address":"Im Schrimmlingen 13",
    "sg:city":"Kleinblittersdorf",
    "sg:phone":"+49 6805/1354",
    "sg:postcode":"66271",
    "sg:province":"Saarland",
    "wof:name":"P. Becker",
    "wof:placetype":"venue"
},
  "geometry": {"coordinates":[7.0416898727,49.1582260132],"type":"Point"}
}