{
  "type": "Feature",
  "properties": {
    "iso:country":"DE",
    "sg:address":"Florastr. 1",
    "sg:city":"D\u00fcsseldorf",
    "sg:phone":"+49 211/376655",
    "sg:postcode":"40217",
    "sg:province":"Nordrhein-Westfalen",
    "wof:name":"T. Biereder Steuerberater",
    "wof:placetype":"venue"
},
  "geometry": {"coordinates":[6.7728791237,51.2156181335],"type":"Point"}
}