{
  "type": "Feature",
  "properties": {
    "iso:country":"DE",
    "sg:address":"Ispringer Str. 14",
    "sg:city":"Pforzheim",
    "sg:phone":"+49 7231/351237",
    "sg:postcode":"75179",
    "sg:province":"Baden-W\u00fcrttemberg",
    "wof:name":"Horst Pietack Elektroinstallation",
    "wof:placetype":"venue"
},
  "geometry": {"coordinates":[8.672219,48.901512],"type":"Point"}
}