{
  "type": "Feature",
  "properties": {
    "iso:country":"DE",
    "sg:address":"Kirchgasse 21",
    "sg:city":"Schorndorf",
    "sg:phone":"+49 7181/62894",
    "sg:postcode":"73614",
    "sg:province":"Baden-W\u00fcrttemberg",
    "wof:name":"Schuhhaus Kurt Noller Inh. Wilfried Noller",
    "wof:placetype":"venue"
},
  "geometry": {"coordinates":[9.526258,48.806423],"type":"Point"}
}