{
  "type": "Feature",
  "properties": {
    "iso:country":"DE",
    "sg:address":"Hasestr. 8",
    "sg:city":"Hasel\u00fcnne",
    "sg:phone":"+49 5961/5304",
    "sg:postcode":"49740",
    "sg:province":"Niedersachsen",
    "wof:name":"Franz Kladde",
    "wof:placetype":"venue"
},
  "geometry": {"coordinates":[7.486972,52.672836],"type":"Point"}
}