{
  "type": "Feature",
  "properties": {
    "iso:country":"DE",
    "sg:address":"Adalbertsteinweg 271",
    "sg:city":"Aachen",
    "sg:phone":"+49 241/537317",
    "sg:postcode":"52066",
    "sg:province":"Nordrhein-Westfalen",
    "wof:name":"N. Mir Mohammadi",
    "wof:placetype":"venue"
},
  "geometry": {"coordinates":[6.1158299446,50.7710952759],"type":"Point"}
}