{
  "type": "Feature",
  "properties": {
    "iso:country":"DE",
    "sg:address":"Hinter der Halle 8",
    "sg:city":"Emden",
    "sg:phone":"+49 4921/25184",
    "sg:postcode":"26725",
    "sg:province":"Niedersachsen",
    "wof:name":"Thiele & Freese Gmbh & Co. Kg",
    "wof:placetype":"venue"
},
  "geometry": {"coordinates":[7.2093501091,53.3665046692],"type":"Point"}
}