{
  "type": "Feature",
  "properties": {
    "iso:country":"DE",
    "sg:address":"Milchgrund 41",
    "sg:city":"Hamburg",
    "sg:phone":"+49 40/7905309",
    "sg:postcode":"21075",
    "sg:province":"Hamburg",
    "wof:name":"J. Pollmann Steuerberater",
    "wof:placetype":"venue"
},
  "geometry": {"coordinates":[9.9519662857,53.4671707153],"type":"Point"}
}