{
  "type": "Feature",
  "properties": {
    "iso:country":"DE",
    "sg:address":"B\u00e4renstr. 5",
    "sg:city":"Herbrechtingen",
    "sg:phone":"+49 7324/2250",
    "sg:postcode":"89542",
    "sg:province":"Baden-W\u00fcrttemberg",
    "wof:name":"F.-o. Habenicht",
    "wof:placetype":"venue"
},
  "geometry": {"coordinates":[10.1504983902,48.6304359436],"type":"Point"}
}