{
  "type": "Feature",
  "properties": {
    "iso:country":"DE",
    "sg:address":"Roderburgm\u00fchle 10",
    "sg:city":"Stolberg",
    "sg:phone":"+49 2402/91730",
    "sg:postcode":"52222",
    "sg:province":"Nordrhein-Westfalen",
    "wof:name":"Karadeniz",
    "wof:placetype":"venue"
},
  "geometry": {"coordinates":[6.2228498459,50.7769241333],"type":"Point"}
}