{
  "type": "Feature",
  "properties": {
    "iso:country":"DE",
    "sg:address":"Hauptstr. 89",
    "sg:city":"Huglfing",
    "sg:phone":"+49 8802/90210",
    "sg:postcode":"82386",
    "sg:province":"Bayern",
    "wof:name":"Za Gmbh",
    "wof:placetype":"venue"
},
  "geometry": {"coordinates":[11.149596,47.772331],"type":"Point"}
}