{
  "type": "Feature",
  "properties": {
    "iso:country":"DE",
    "sg:address":"Brunnader Str. 9",
    "sg:city":"Bad Birnbach",
    "sg:phone":"+49 8563/96160",
    "sg:postcode":"84364",
    "sg:province":"Bayern",
    "wof:name":"Hotel-appartementhaus Rappenberg Garni",
    "wof:placetype":"venue"
},
  "geometry": {"coordinates":[13.0806732178,48.4412078857],"type":"Point"}
}