{
  "type": "Feature",
  "properties": {
    "iso:country":"DE",
    "sg:address":"Stuhrsallee 35",
    "sg:city":"Flensburg",
    "sg:postcode":"24937",
    "sg:province":"Schleswig-Holstein",
    "wof:name":"Kiessling & Partner Dachdecker Gmbh",
    "wof:placetype":"venue"
},
  "geometry": {"coordinates":[9.428999,54.784924],"type":"Point"}
}