{
  "type": "Feature",
  "properties": {
    "iso:country":"DE",
    "sg:address":"Marktstr. 60",
    "sg:city":"Remagen",
    "sg:phone":"+49 2642/21757",
    "sg:postcode":"53424",
    "sg:province":"Rheinland-Pfalz",
    "wof:name":"G\u00fcttes",
    "wof:placetype":"venue"
},
  "geometry": {"coordinates":[7.231298,50.578613],"type":"Point"}
}