{
  "type": "Feature",
  "properties": {
    "iso:country":"DE",
    "sg:address":"Am Hirschgraben 11",
    "sg:city":"Ludwigsburg",
    "sg:phone":"+49 7141/855134",
    "sg:postcode":"71640",
    "sg:province":"Baden-W\u00fcrttemberg",
    "wof:name":"Etiko-haftetiketten",
    "wof:placetype":"venue"
},
  "geometry": {"coordinates":[9.228729,48.890221],"type":"Point"}
}