{
  "type": "Feature",
  "properties": {
    "iso:country":"DE",
    "sg:address":"Seebacher Str. 110",
    "sg:city":"Bad D\u00fcrkheim",
    "sg:phone":"+49 6322/5359",
    "sg:postcode":"67098",
    "sg:province":"Rheinland-Pfalz",
    "wof:name":"Kurt Leckron",
    "wof:placetype":"venue"
},
  "geometry": {"coordinates":[8.158673,49.451496],"type":"Point"}
}