{
  "type": "Feature",
  "properties": {
    "iso:country":"DE",
    "sg:address":"Sch\u00f6nheider Str. 7",
    "sg:city":"St\u00fctzengr\u00fcn",
    "sg:phone":"+49 37462/3641",
    "sg:postcode":"08328",
    "sg:province":"Sachsen",
    "wof:name":"Dieter Streit",
    "wof:placetype":"venue"
},
  "geometry": {"coordinates":[12.525272,50.533199],"type":"Point"}
}