{
  "type": "Feature",
  "properties": {
    "iso:country":"DE",
    "sg:address":"Rosenstr. 34",
    "sg:city":"Eislingen",
    "sg:phone":"+49 7161",
    "sg:postcode":"73054",
    "sg:province":"Baden-W\u00fcrttemberg",
    "wof:name":"Sps Feriendomizile",
    "wof:placetype":"venue"
},
  "geometry": {"coordinates":[9.7088346481,48.6944389343],"type":"Point"}
}