{
  "type": "Feature",
  "properties": {
    "iso:country":"DE",
    "sg:address":"Ortshof 21",
    "sg:city":"M\u00f6nchengladbach",
    "sg:phone":"+49 2161/631812",
    "sg:postcode":"41066",
    "sg:province":"Nordrhein-Westfalen",
    "wof:name":"Hubert Hoinkis",
    "wof:placetype":"venue"
},
  "geometry": {"coordinates":[6.454643,51.219112],"type":"Point"}
}