{
  "type": "Feature",
  "properties": {
    "iso:country":"DE",
    "sg:address":"Wilhelmstr. 7",
    "sg:city":"Salach",
    "sg:phone":"+49 7162/40930",
    "sg:postcode":"73084",
    "sg:province":"Baden-W\u00fcrttemberg",
    "wof:name":"Heldele Gmbh",
    "wof:placetype":"venue"
},
  "geometry": {"coordinates":[9.7390460968,48.6904983521],"type":"Point"}
}