{
  "type": "Feature",
  "properties": {
    "iso:country":"DE",
    "sg:address":"Stralsunder Str. 43",
    "sg:city":"Leipzig",
    "sg:postcode":"04357",
    "sg:province":"Sachsen",
    "wof:name":"Wolfgang Kupfer Ingenieurwesen",
    "wof:placetype":"venue"
},
  "geometry": {"coordinates":[12.419707,51.383919],"type":"Point"}
}