{
  "type": "Feature",
  "properties": {
    "iso:country":"DE",
    "sg:address":"Kelterstr. 49",
    "sg:city":"M\u00fchlacker",
    "sg:phone":"+49 7041/96760",
    "sg:postcode":"75417",
    "sg:province":"Baden-W\u00fcrttemberg",
    "wof:name":"Seiter Gmbh",
    "wof:placetype":"venue"
},
  "geometry": {"coordinates":[8.848827,48.947754],"type":"Point"}
}