{
  "type": "Feature",
  "properties": {
    "iso:country":"DE",
    "sg:address":"H\u00e4ndelstr. 25",
    "sg:city":"Mettmann",
    "sg:phone":"+49 2104/13419",
    "sg:postcode":"40822",
    "sg:province":"Nordrhein-Westfalen",
    "wof:name":"Arnold Schumacher",
    "wof:placetype":"venue"
},
  "geometry": {"coordinates":[6.9780550003,51.2412338257],"type":"Point"}
}