{
  "type": "Feature",
  "properties": {
    "iso:country":"DE",
    "sg:address":"M\u00fchlener Torweg 23",
    "sg:city":"Horb",
    "sg:phone":"+49 7451/623258",
    "sg:postcode":"72160",
    "sg:province":"Baden-W\u00fcrttemberg",
    "wof:name":"Haid Werbeagentur Gmbh",
    "wof:placetype":"venue"
},
  "geometry": {"coordinates":[8.6954545975,48.446018219],"type":"Point"}
}