{
  "type": "Feature",
  "properties": {
    "iso:country":"DE",
    "sg:address":"Hallenweg 81",
    "sg:city":"Mannheim",
    "sg:phone":"+49 831/540270",
    "sg:postcode":"68219",
    "sg:province":"Baden-W\u00fcrttemberg",
    "wof:name":"Rab Rohr- & Anlagenbau Gmbh",
    "wof:placetype":"venue"
},
  "geometry": {"coordinates":[10.311271,47.722561],"type":"Point"}
}