{
  "type": "Feature",
  "properties": {
    "iso:country":"DE",
    "sg:address":"Neue Str. 7",
    "sg:city":"Wietzendorf",
    "sg:postcode":"29649",
    "sg:province":"Niedersachsen",
    "wof:name":"De Boer Verwaltungs- Und Beteiligungs Gmbh",
    "wof:placetype":"venue"
},
  "geometry": {"coordinates":[9.983365,52.920235],"type":"Point"}
}