{
  "type": "Feature",
  "properties": {
    "iso:country":"DE",
    "sg:address":"Zehntgrafstr. 6",
    "sg:city":"H\u00f6hn",
    "sg:phone":"+49 2661/8550",
    "sg:postcode":"56462",
    "sg:province":"Rheinland-Pfalz",
    "wof:name":"Rolf K\u00fcnkler",
    "wof:placetype":"venue"
},
  "geometry": {"coordinates":[7.983731,50.617577],"type":"Point"}
}