{
  "type": "Feature",
  "properties": {
    "iso:country":"DE",
    "sg:address":"H\u00f6ckelheimer Str. 3",
    "sg:city":"Northeim",
    "sg:phone":"+49 5551/3191",
    "sg:postcode":"37154",
    "sg:province":"Niedersachsen",
    "wof:name":"Rosenhang",
    "wof:placetype":"venue"
},
  "geometry": {"coordinates":[9.9505710602,51.68699646],"type":"Point"}
}