{
  "type": "Feature",
  "properties": {
    "iso:country":"DE",
    "sg:address":"Amsterdamer Str. 33",
    "sg:city":"Kevelaer",
    "sg:phone":"+49 2832/5140",
    "sg:postcode":"47623",
    "sg:province":"Nordrhein-Westfalen",
    "wof:name":"Wilhelm Girmes",
    "wof:placetype":"venue"
},
  "geometry": {"coordinates":[6.2413191795,51.5853233337],"type":"Point"}
}