{
  "type": "Feature",
  "properties": {
    "iso:country":"DE",
    "sg:address":"An der Untertrave 100",
    "sg:city":"L\u00fcbeck",
    "sg:phone":"+49 451/72424",
    "sg:postcode":"23552",
    "sg:province":"Schleswig-Holstein",
    "wof:name":"Mobiliar Licht + Raum Gmbh",
    "wof:placetype":"venue"
},
  "geometry": {"coordinates":[10.6806850433,53.8680229187],"type":"Point"}
}