{
  "type": "Feature",
  "properties": {
    "iso:country":"DE",
    "sg:address":"Heeper Str. 189",
    "sg:city":"Bielefeld",
    "sg:phone":"+49 521/932500",
    "sg:postcode":"33607",
    "sg:province":"Nordrhein-Westfalen",
    "wof:name":"Hansa-apotheke Wilfried Volmer E. K.",
    "wof:placetype":"venue"
},
  "geometry": {"coordinates":[8.564342,52.023972],"type":"Point"}
}