{
  "type": "Feature",
  "properties": {
    "iso:country":"DE",
    "sg:address":"Walter-Kolb-Str. 5-7",
    "sg:city":"Frankfurt",
    "sg:phone":"+49 69/24277001",
    "sg:postcode":"60594",
    "sg:province":"Hessen",
    "wof:name":"Dywidag-service-gmbh",
    "wof:placetype":"venue"
},
  "geometry": {"coordinates":[8.6864061356,50.1056976318],"type":"Point"}
}