{
  "type": "Feature",
  "properties": {
    "iso:country":"DE",
    "sg:address":"Glottertalstr. 3",
    "sg:city":"Heuweiler",
    "sg:postcode":"79194",
    "sg:province":"Baden-W\u00fcrttemberg",
    "wof:name":"Gasthof Gr\u00fcner Baum Hans Bank E. K.",
    "wof:placetype":"venue"
},
  "geometry": {"coordinates":[7.9074602127,48.0557937622],"type":"Point"}
}