{
  "type": "Feature",
  "properties": {
    "iso:country":"DE",
    "sg:address":"Kuller Str. 43",
    "sg:city":"Solingen",
    "sg:phone":"+49 212/53832",
    "sg:postcode":"42651",
    "sg:province":"Nordrhein-Westfalen",
    "wof:name":"Psa Sicherheitstechnik Gmbh",
    "wof:placetype":"venue"
},
  "geometry": {"coordinates":[7.084224,51.182266],"type":"Point"}
}