{
  "type": "Feature",
  "properties": {
    "iso:country":"DE",
    "sg:address":"Grafinger Str. 6",
    "sg:city":"M\u00fcnchen",
    "sg:phone":"+49 89/4506920",
    "sg:postcode":"81671",
    "sg:province":"Bayern",
    "wof:name":"Kunstpark Ost Vermietungs Gmbh",
    "wof:placetype":"venue"
},
  "geometry": {"coordinates":[11.606347,48.125652],"type":"Point"}
}