{
  "type": "Feature",
  "properties": {
    "iso:country":"DE",
    "sg:address":"B\u00e4ckerstr. 18",
    "sg:city":"Lengede",
    "sg:phone":"+49 5344/7047",
    "sg:postcode":"38268",
    "sg:province":"Niedersachsen",
    "wof:name":"Ev. Pfarramt Lengede",
    "wof:placetype":"venue"
},
  "geometry": {"coordinates":[10.3054924011,52.2023544312],"type":"Point"}
}