{
  "type": "Feature",
  "properties": {
    "iso:country":"DE",
    "sg:address":"Bauernstr 47",
    "sg:city":"Stadtbergen",
    "sg:phone":"+49 821/437472",
    "sg:postcode":"86391",
    "sg:province":"Bayern",
    "wof:name":"Raiffeisenbank-volksbank Augsburg E",
    "wof:placetype":"venue"
},
  "geometry": {"coordinates":[10.845761,48.367599],"type":"Point"}
}