{
  "type": "Feature",
  "properties": {
    "iso:country":"DE",
    "sg:address":"Lise-Meitner-Str. 10",
    "sg:city":"Winnenden",
    "sg:phone":"+49 7195/92680",
    "sg:postcode":"71364",
    "sg:province":"Baden-W\u00fcrttemberg",
    "wof:name":"Sadex-zuckerwarenfabrik Gmbh",
    "wof:placetype":"venue"
},
  "geometry": {"coordinates":[9.4193315506,48.8892288208],"type":"Point"}
}