{
  "type": "Feature",
  "properties": {
    "iso:country":"DE",
    "sg:address":"Freiburger Str. 59",
    "sg:city":"Hohberg",
    "sg:phone":"+49 7808/84141",
    "sg:postcode":"77749",
    "sg:province":"Baden-W\u00fcrttemberg",
    "wof:name":"A. Hofmann Und H.-p. Gross",
    "wof:placetype":"venue"
},
  "geometry": {"coordinates":[7.9054498672,48.4223365784],"type":"Point"}
}