{
  "type": "Feature",
  "properties": {
    "iso:country":"DE",
    "sg:address":"Spitzbergenweg 25",
    "sg:city":"Hamburg",
    "sg:phone":"+49 40/6792048",
    "sg:postcode":"22145",
    "sg:province":"Hamburg",
    "wof:name":"Bay Dolmetscher",
    "wof:placetype":"venue"
},
  "geometry": {"coordinates":[10.167605,53.627178],"type":"Point"}
}