{
  "type": "Feature",
  "properties": {
    "iso:country":"DE",
    "sg:address":"Wiesharder Markt 2",
    "sg:city":"Handewitt",
    "sg:phone":"+49 4608/1044",
    "sg:postcode":"24983",
    "sg:province":"Schleswig-Holstein",
    "wof:name":"Apotheke Handewitt Inh. Volker Andresen",
    "wof:placetype":"venue"
},
  "geometry": {"coordinates":[9.3225,54.7701],"type":"Point"}
}