{
  "type": "Feature",
  "properties": {
    "iso:country":"DE",
    "sg:address":"Schlo\u00dfplatz 35774::",
    "sg:city":"Karlsruhe",
    "sg:phone":"+49 4972/11500",
    "sg:postcode":"76112",
    "sg:province":"Baden-W\u00fcrttemberg",
    "wof:name":"Landeskreditbank Baden W\u00dcrttemberg",
    "wof:placetype":"venue"
},
  "geometry": {"coordinates":[8.405297,49.010712],"type":"Point"}
}