{
  "type": "Feature",
  "properties": {
    "iso:country":"DE",
    "sg:address":"Zindelstr 12",
    "sg:city":"Essen",
    "sg:phone":"+49 201/872280",
    "sg:postcode":"45128",
    "sg:province":"Nordrhein-Westfalen",
    "wof:name":"Image Transfer Gmbh",
    "wof:placetype":"venue"
},
  "geometry": {"coordinates":[7.0075588226,51.4481506348],"type":"Point"}
}