{
  "type": "Feature",
  "properties": {
    "iso:country":"DE",
    "sg:address":"Gilgenstr. 5",
    "sg:city":"Speyer",
    "sg:phone":"+49 4962/3275029",
    "sg:postcode":"67346",
    "sg:province":"Rheinland-Pfalz",
    "wof:name":"Sparda Bank Mainz Eg",
    "wof:placetype":"venue"
},
  "geometry": {"coordinates":[8.431024,49.317116],"type":"Point"}
}