{
  "type": "Feature",
  "properties": {
    "iso:country":"DE",
    "sg:address":"Kaufhof 3",
    "sg:city":"Wolfsburg",
    "sg:phone":"+49 5361/25111",
    "sg:postcode":"38440",
    "sg:province":"Niedersachsen",
    "wof:name":"Nablus",
    "wof:placetype":"venue"
},
  "geometry": {"coordinates":[10.7852706909,52.4234542847],"type":"Point"}
}