{
  "type": "Feature",
  "properties": {
    "iso:country":"DE",
    "sg:address":"Hutschdorf 80",
    "sg:city":"Thurnau",
    "sg:phone":"+49 9228/5415",
    "sg:postcode":"95349",
    "sg:province":"Bayern",
    "wof:name":"Detlef Sesselmann",
    "wof:placetype":"venue"
},
  "geometry": {"coordinates":[11.4191703796,50.0406532288],"type":"Point"}
}