{
  "type": "Feature",
  "properties": {
    "iso:country":"DE",
    "sg:address":"Immermannstr. 35",
    "sg:city":"Dortmund",
    "sg:phone":"+49 231",
    "sg:postcode":"44147",
    "sg:province":"Nordrhein-Westfalen",
    "wof:name":"Skifreunde Dortmund E. V.",
    "wof:placetype":"venue"
},
  "geometry": {"coordinates":[7.4523887634,51.5326881409],"type":"Point"}
}