{
  "type": "Feature",
  "properties": {
    "iso:country":"DE",
    "sg:address":"Golzheimer Str. 104",
    "sg:city":"D\u00fcsseldorf",
    "sg:phone":"+49 211/483912",
    "sg:postcode":"40476",
    "sg:province":"Nordrhein-Westfalen",
    "wof:name":"Peter Henseler",
    "wof:placetype":"venue"
},
  "geometry": {"coordinates":[6.78024,51.24596],"type":"Point"}
}