{
  "type": "Feature",
  "properties": {
    "iso:country":"DE",
    "sg:address":"Robert-Bosch-Str. 25",
    "sg:city":"Odelzhausen",
    "sg:phone":"+49 8134/5819",
    "sg:postcode":"85235",
    "sg:province":"Bayern",
    "wof:name":"Top Transport Organisations Gmbh",
    "wof:placetype":"venue"
},
  "geometry": {"coordinates":[11.2102336884,48.3026542664],"type":"Point"}
}