{
  "type": "Feature",
  "properties": {
    "iso:country":"DE",
    "sg:address":"Bernsdorfer Str 89",
    "sg:city":"Chemnitz",
    "sg:phone":"+49 371/5905436",
    "sg:postcode":"09126",
    "sg:province":"Sachsen",
    "wof:name":"Elektro-uhlig",
    "wof:placetype":"venue"
},
  "geometry": {"coordinates":[12.938956,50.81815],"type":"Point"}
}