{
  "type": "Feature",
  "properties": {
    "iso:country":"DE",
    "sg:address":"Landwehr 59",
    "sg:city":"Solingen",
    "sg:phone":"+49 212/61135",
    "sg:postcode":"42697",
    "sg:province":"Nordrhein-Westfalen",
    "wof:name":"Hans Herbst",
    "wof:placetype":"venue"
},
  "geometry": {"coordinates":[6.993834,51.126244],"type":"Point"}
}