{
  "type": "Feature",
  "properties": {
    "iso:country":"DE",
    "sg:address":"Engelthaler Str. 7",
    "sg:city":"Frankfurt",
    "sg:phone":"+49 69/545469",
    "sg:postcode":"60435",
    "sg:province":"Hessen",
    "wof:name":"Piet\u00e4t W. Schmidt & Partner",
    "wof:placetype":"venue"
},
  "geometry": {"coordinates":[8.681387,50.14959],"type":"Point"}
}