{
  "type": "Feature",
  "properties": {
    "iso:country":"DE",
    "sg:address":"Im D\u00fcmpel 4 a",
    "sg:city":"H\u00fcrtgenwald",
    "sg:phone":"+49 2429/7248",
    "sg:postcode":"52393",
    "sg:province":"Nordrhein-Westfalen",
    "wof:name":"K\u00f6rner",
    "wof:placetype":"venue"
},
  "geometry": {"coordinates":[6.376319,50.711086],"type":"Point"}
}