{
  "type": "Feature",
  "properties": {
    "iso:country":"DE",
    "sg:address":"Carl-Benz-Str. 9",
    "sg:city":"Weilheim",
    "sg:phone":"+49 7023/900120",
    "sg:postcode":"73235",
    "sg:province":"Baden-W\u00fcrttemberg",
    "wof:name":"Friedrich Schnitzler",
    "wof:placetype":"venue"
},
  "geometry": {"coordinates":[9.546924,48.624321],"type":"Point"}
}