{
  "type": "Feature",
  "properties": {
    "iso:country":"DE",
    "sg:address":"Goerdelerstrasse 32",
    "sg:city":"Unterhaching",
    "sg:phone":"+49 89/6251145",
    "sg:postcode":"82008",
    "sg:province":"Bayern",
    "wof:name":"Gesellschaft F. Internationale Jugendkontakte E.v. Muenchen",
    "wof:placetype":"venue"
},
  "geometry": {"coordinates":[11.623214,48.061844],"type":"Point"}
}