{
  "type": "Feature",
  "properties": {
    "iso:country":"DE",
    "sg:address":"W\u00fcrttembergstr. 34",
    "sg:city":"Oberhausen",
    "sg:postcode":"46149",
    "sg:province":"Nordrhein-Westfalen",
    "wof:name":"Ibs Brakmann Gmbh",
    "wof:placetype":"venue"
},
  "geometry": {"coordinates":[6.836744,51.50824],"type":"Point"}
}