{
  "type": "Feature",
  "properties": {
    "iso:country":"DE",
    "sg:address":"Eduard-Grunow-Str. 24",
    "sg:city":"Bremen",
    "sg:phone":"+49 421/791990",
    "sg:postcode":"28203",
    "sg:province":"Bremen",
    "wof:name":"Parit\u00e4tischer Wohlfahrts- Verband- Landesverband",
    "wof:placetype":"venue"
},
  "geometry": {"coordinates":[8.821073,53.077305],"type":"Point"}
}