{
  "type": "Feature",
  "properties": {
    "iso:country":"DE",
    "sg:address":"Eisenberger Str. 38",
    "sg:city":"Wei\u00dfenborn",
    "sg:phone":"+49 36601/83548",
    "sg:postcode":"07639",
    "sg:province":"Th\u00fcringen",
    "wof:name":"Fritz Kurze",
    "wof:placetype":"venue"
},
  "geometry": {"coordinates":[11.878048,50.926102],"type":"Point"}
}