{
  "type": "Feature",
  "properties": {
    "iso:country":"DE",
    "sg:address":"Lahnstr. 1",
    "sg:city":"Dautphetal",
    "sg:phone":"+49 6466/310",
    "sg:postcode":"35232",
    "sg:province":"Hessen",
    "wof:name":"L. Ortm\u00fcller",
    "wof:placetype":"venue"
},
  "geometry": {"coordinates":[8.5496063232,50.8698883057],"type":"Point"}
}