{
  "type": "Feature",
  "properties": {
    "iso:country":"DE",
    "sg:address":"Bremer Str. 115",
    "sg:city":"Hamburg",
    "sg:phone":"+49 40/7654201",
    "sg:postcode":"21073",
    "sg:province":"Hamburg",
    "wof:name":"Malereibetrieb K.-h. Grob Gmbh",
    "wof:placetype":"venue"
},
  "geometry": {"coordinates":[9.972375,53.451794],"type":"Point"}
}