{
  "type": "Feature",
  "properties": {
    "iso:country":"DE",
    "sg:address":"Mollerstr. 12a",
    "sg:city":"Hamburg",
    "sg:phone":"+49 40/451142",
    "sg:postcode":"20148",
    "sg:province":"Hamburg",
    "wof:name":"W. Pullich",
    "wof:placetype":"venue"
},
  "geometry": {"coordinates":[9.9914608002,53.5700035095],"type":"Point"}
}