{
  "type": "Feature",
  "properties": {
    "iso:country":"DE",
    "sg:address":"Pestalozzistr. 17",
    "sg:city":"Kerpen",
    "sg:phone":"+49 2237/52112",
    "sg:postcode":"50171",
    "sg:province":"Nordrhein-Westfalen",
    "wof:name":"H. J. Mein Architekt",
    "wof:placetype":"venue"
},
  "geometry": {"coordinates":[6.70075,50.865639],"type":"Point"}
}