{
  "type": "Feature",
  "properties": {
    "iso:country":"DE",
    "sg:address":"Altendorfer Str. 360",
    "sg:city":"Essen",
    "sg:phone":"+49 201/622844",
    "sg:postcode":"45143",
    "sg:province":"Nordrhein-Westfalen",
    "wof:name":"Surbach-dental Gmbh",
    "wof:placetype":"venue"
},
  "geometry": {"coordinates":[6.9712262154,51.461643219],"type":"Point"}
}