{
  "type": "Feature",
  "properties": {
    "iso:country":"DE",
    "sg:address":"Kurparkstr. 12",
    "sg:city":"M\u00fcnchen",
    "sg:phone":"+49 89/7145526",
    "sg:postcode":"81375",
    "sg:province":"Bayern",
    "wof:name":"Iv-beratung Und Direkt- Marketingservice M\u00fcller Gmbh",
    "wof:placetype":"venue"
},
  "geometry": {"coordinates":[11.50089,48.124271],"type":"Point"}
}