{
  "type": "Feature",
  "properties": {
    "iso:country":"DE",
    "sg:address":"Parkstr. 7",
    "sg:city":"Falkenstein",
    "sg:phone":"+49 9462/170",
    "sg:postcode":"93167",
    "sg:province":"Bayern",
    "wof:name":"Pressol Gmbh & Co. Kg",
    "wof:placetype":"venue"
},
  "geometry": {"coordinates":[12.4888601303,49.102191925],"type":"Point"}
}