{
  "type": "Feature",
  "properties": {
    "iso:country":"DE",
    "sg:address":"Bischofswerdaer Str 101",
    "sg:city":"Gro\u00dfr\u00f6hrsdorf",
    "sg:phone":"+49 35952/3470",
    "sg:postcode":"01900",
    "sg:province":"Sachsen",
    "wof:name":"Holthaus Meditex Gmbh",
    "wof:placetype":"venue"
},
  "geometry": {"coordinates":[14.036952,51.142735],"type":"Point"}
}