{
  "type": "Feature",
  "properties": {
    "iso:country":"DE",
    "sg:address":"Blumenstr. 33",
    "sg:city":"Oedheim",
    "sg:phone":"+49 7136/910155",
    "sg:postcode":"74229",
    "sg:province":"Baden-W\u00fcrttemberg",
    "wof:name":"Rita Nutz",
    "wof:placetype":"venue"
},
  "geometry": {"coordinates":[9.266035,49.24387],"type":"Point"}
}