{
  "type": "Feature",
  "properties": {
    "iso:country":"DE",
    "sg:address":"Nieder-Breidenbacher-Str. 18",
    "sg:city":"Romrod",
    "sg:phone":"+49 6636/1395",
    "sg:postcode":"36329",
    "sg:province":"Hessen",
    "wof:name":"J. G\u00f6ttlicher",
    "wof:placetype":"venue"
},
  "geometry": {"coordinates":[9.229702,50.680138],"type":"Point"}
}