{
  "type": "Feature",
  "properties": {
    "iso:country":"DE",
    "sg:address":"Karlstr. 2",
    "sg:city":"Herne",
    "sg:phone":"+49 2325/74429",
    "sg:postcode":"44649",
    "sg:province":"Nordrhein-Westfalen",
    "wof:name":"Kosmetik Janine",
    "wof:placetype":"venue"
},
  "geometry": {"coordinates":[7.155072,51.5373],"type":"Point"}
}