{
  "type": "Feature",
  "properties": {
    "iso:country":"DE",
    "sg:address":"Uhlandstr. 1 a",
    "sg:city":"Heitersheim",
    "sg:postcode":"79423",
    "sg:province":"Baden-W\u00fcrttemberg",
    "wof:name":"Steinle Wassertechnik Gmbh",
    "wof:placetype":"venue"
},
  "geometry": {"coordinates":[7.6452379227,47.8757629395],"type":"Point"}
}