{
  "type": "Feature",
  "properties": {
    "iso:country":"DE",
    "sg:address":"Industriestr. 27",
    "sg:city":"D\u00fclmen",
    "sg:phone":"+49 2594/760",
    "sg:postcode":"48249",
    "sg:province":"Nordrhein-Westfalen",
    "wof:name":"Estelit Baustoffwerke Gmbh & Co. Kg",
    "wof:placetype":"venue"
},
  "geometry": {"coordinates":[7.30224,51.822262],"type":"Point"}
}