{
  "type": "Feature",
  "properties": {
    "iso:country":"DE",
    "sg:address":"Bahnhofstr. 84",
    "sg:city":"Geislingen",
    "sg:phone":"+49 7331/64331",
    "sg:postcode":"73312",
    "sg:province":"Baden-W\u00fcrttemberg",
    "wof:name":"Herbert J\u00e4kel",
    "wof:placetype":"venue"
},
  "geometry": {"coordinates":[9.8362760544,48.6230506897],"type":"Point"}
}