{
  "type": "Feature",
  "properties": {
    "iso:country":"DE",
    "sg:address":"Herforder Str. 191",
    "sg:city":"Bielefeld",
    "sg:phone":"+49 521/320214",
    "sg:postcode":"33609",
    "sg:province":"Nordrhein-Westfalen",
    "wof:name":"Mobilcom Shop",
    "wof:placetype":"venue"
},
  "geometry": {"coordinates":[8.5536842346,52.035987854],"type":"Point"}
}