{
  "type": "Feature",
  "properties": {
    "iso:country":"DE",
    "sg:address":"Am Steinbergel 13",
    "sg:city":"Epfenbach",
    "sg:phone":"+49 7263/4860",
    "sg:postcode":"74925",
    "sg:province":"Baden-W\u00fcrttemberg",
    "wof:name":"Mke Metall- Und Apparatebau Gmbh",
    "wof:placetype":"venue"
},
  "geometry": {"coordinates":[8.918158,49.334583],"type":"Point"}
}