{
  "type": "Feature",
  "properties": {
    "iso:country":"DE",
    "sg:address":"Alte Heerstr. 24",
    "sg:city":"Hildesheim",
    "sg:phone":"+49 5121/510449",
    "sg:postcode":"31135",
    "sg:province":"Niedersachsen",
    "wof:name":"Notka Gmbh",
    "wof:placetype":"venue"
},
  "geometry": {"coordinates":[10.016625,52.161072],"type":"Point"}
}