{
  "type": "Feature",
  "properties": {
    "iso:country":"DE",
    "sg:address":"Brabandstr. 5",
    "sg:city":"Hamburg",
    "sg:phone":"+49 40/48001510",
    "sg:postcode":"22297",
    "sg:province":"Hamburg",
    "wof:name":"Upcare Handels-und Produktentwicklungs Gmbh",
    "wof:placetype":"venue"
},
  "geometry": {"coordinates":[10.0022172928,53.6126899719],"type":"Point"}
}