{
  "type": "Feature",
  "properties": {
    "iso:country":"DE",
    "sg:address":"Herzogstr. 4",
    "sg:city":"F\u00fcssen",
    "sg:phone":"+49 8362/7766",
    "sg:postcode":"87629",
    "sg:province":"Bayern",
    "wof:name":"H. M\u00fcller",
    "wof:placetype":"venue"
},
  "geometry": {"coordinates":[10.684536,47.573906],"type":"Point"}
}