{
  "type": "Feature",
  "properties": {
    "iso:country":"DE",
    "sg:address":"D\u00fcsseldorfer Str. 127",
    "sg:city":"Duisburg",
    "sg:phone":"+49 2151/409281",
    "sg:postcode":"47051",
    "sg:province":"Nordrhein-Westfalen",
    "wof:name":"Kath. \u00f6ffentliche Bibliothek St. Klara",
    "wof:placetype":"venue"
},
  "geometry": {"coordinates":[6.765169,51.426811],"type":"Point"}
}