{
  "type": "Feature",
  "properties": {
    "iso:country":"DE",
    "sg:address":"Rosenhagenstr. 2",
    "sg:city":"Hamburg",
    "sg:phone":"+49 40/895632",
    "sg:postcode":"22607",
    "sg:province":"Hamburg",
    "wof:name":"Horst Becker Rechtsanwalt",
    "wof:placetype":"venue"
},
  "geometry": {"coordinates":[9.8888139725,53.5597496033],"type":"Point"}
}