{
  "type": "Feature",
  "properties": {
    "iso:country":"DE",
    "sg:address":"Nansenstr. 46",
    "sg:city":"Kempen",
    "sg:phone":"+49 2152/2564",
    "sg:postcode":"47906",
    "sg:province":"Nordrhein-Westfalen",
    "wof:name":"Expert-krawatten Inh. Manfred Bieda",
    "wof:placetype":"venue"
},
  "geometry": {"coordinates":[6.409695,51.36945],"type":"Point"}
}