{
  "type": "Feature",
  "properties": {
    "iso:country":"DE",
    "sg:address":"An der Stephanuskirche 7",
    "sg:city":"Hamm",
    "sg:phone":"+49 2381/306988",
    "sg:postcode":"59073",
    "sg:province":"Nordrhein-Westfalen",
    "wof:name":"Bilkom Gmbh",
    "wof:placetype":"venue"
},
  "geometry": {"coordinates":[7.845833,51.704693],"type":"Point"}
}