{
  "type": "Feature",
  "properties": {
    "iso:country":"DE",
    "sg:address":"Schachert 1 b",
    "sg:city":"Hauzenberg",
    "sg:postcode":"94051",
    "sg:province":"Bayern",
    "wof:name":"Unisecur Wertschutzschr\u00e4nke Gmbh",
    "wof:placetype":"venue"
},
  "geometry": {"coordinates":[13.6802835464,48.6270484924],"type":"Point"}
}