{
  "type": "Feature",
  "properties": {
    "iso:country":"DE",
    "sg:address":"Aubinger Str. 32",
    "sg:city":"Gr\u00e4felfing",
    "sg:phone":"+49 89/875026",
    "sg:postcode":"82166",
    "sg:province":"Bayern",
    "wof:name":"J. Bremerich",
    "wof:placetype":"venue"
},
  "geometry": {"coordinates":[11.429869,48.133713],"type":"Point"}
}