{
  "type": "Feature",
  "properties": {
    "iso:country":"DE",
    "sg:address":"In Der Wart 6",
    "sg:city":"Talheim",
    "sg:phone":"+49 4971/3312690",
    "sg:postcode":"74388",
    "sg:province":"Baden-W\u00fcrttemberg",
    "wof:name":"Jung Gmbh",
    "wof:placetype":"venue"
},
  "geometry": {"coordinates":[9.1915855408,49.0780525208],"type":"Point"}
}