{
  "type": "Feature",
  "properties": {
    "iso:country":"DE",
    "sg:address":"Kapellenweg 7",
    "sg:city":"Breisach",
    "sg:phone":"+49 7664/4506",
    "sg:postcode":"79206",
    "sg:province":"Baden-W\u00fcrttemberg",
    "wof:name":"Hermann Weismann",
    "wof:placetype":"venue"
},
  "geometry": {"coordinates":[7.6630029678,47.9767684937],"type":"Point"}
}