{
  "type": "Feature",
  "properties": {
    "iso:country":"DE",
    "sg:address":"Waldbachstr. 41",
    "sg:city":"Gernsbach",
    "sg:phone":"+49 7224/3435",
    "sg:postcode":"76593",
    "sg:province":"Baden-W\u00fcrttemberg",
    "wof:name":"Waldbachsch\u00e4nke",
    "wof:placetype":"venue"
},
  "geometry": {"coordinates":[8.332818985,48.7628326416],"type":"Point"}
}