{
  "type": "Feature",
  "properties": {
    "iso:country":"DE",
    "sg:address":"Weender Landstr. 23",
    "sg:city":"G\u00f6ttingen",
    "sg:phone":"+49 551/5311339",
    "sg:postcode":"37073",
    "sg:province":"Niedersachsen",
    "wof:name":"Restaurant La Hacienda",
    "wof:placetype":"venue"
},
  "geometry": {"coordinates":[9.9327201843,51.5412635803],"type":"Point"}
}