{
  "type": "Feature",
  "properties": {
    "iso:country":"DE",
    "sg:address":"Seligenthaler Str. 33",
    "sg:city":"Landshut",
    "sg:postcode":"84034",
    "sg:province":"Bayern",
    "wof:name":"Hh Haus- Und Grundst\u00fccks- Verwertungs- Gmbh",
    "wof:placetype":"venue"
},
  "geometry": {"coordinates":[12.14215,48.545193],"type":"Point"}
}