{
  "type": "Feature",
  "properties": {
    "iso:country":"DE",
    "sg:address":"Wellenstr. 15",
    "sg:city":"Siegburg",
    "sg:phone":"+49 2241/590732",
    "sg:postcode":"53721",
    "sg:province":"Nordrhein-Westfalen",
    "wof:name":"Monika Mentges Heilpraktikerin",
    "wof:placetype":"venue"
},
  "geometry": {"coordinates":[7.2112717628,50.8003921509],"type":"Point"}
}