{
  "type": "Feature",
  "properties": {
    "iso:country":"DE",
    "sg:address":"Langen-Bergheimer Str. 4",
    "sg:city":"Hanau",
    "sg:phone":"+49 6181/82308",
    "sg:postcode":"63452",
    "sg:province":"Hessen",
    "wof:name":"Horst Bruckmann",
    "wof:placetype":"venue"
},
  "geometry": {"coordinates":[8.9129686356,50.1464691162],"type":"Point"}
}