{
  "type": "Feature",
  "properties": {
    "iso:country":"DE",
    "sg:address":"Karlstr. 35",
    "sg:city":"Rheinsberg",
    "sg:phone":"+49 33931/2629",
    "sg:postcode":"16831",
    "sg:province":"Brandenburg",
    "wof:name":"Peter Puschmann",
    "wof:placetype":"venue"
},
  "geometry": {"coordinates":[12.8977193832,53.0977935791],"type":"Point"}
}