{
  "type": "Feature",
  "properties": {
    "iso:country":"DE",
    "sg:address":"Friedrichstr. 44",
    "sg:city":"Westerland",
    "sg:phone":"+49 4651/24933",
    "sg:postcode":"25980",
    "sg:province":"Schleswig-Holstein",
    "wof:name":"Althoff Der Herrenausstatter Nachf. Inh. Klaus Hartmann",
    "wof:placetype":"venue"
},
  "geometry": {"coordinates":[8.300198555,54.9077835083],"type":"Point"}
}