{
  "type": "Feature",
  "properties": {
    "iso:country":"DE",
    "sg:address":"Limburger Stra\u00dfe 76",
    "sg:city":"Limburg-Offheim",
    "sg:phone":"+49 6431",
    "sg:postcode":"65555",
    "sg:province":"Hessen",
    "wof:name":"Spedition Antl",
    "wof:placetype":"venue"
},
  "geometry": {"coordinates":[8.0620803833,50.4054069519],"type":"Point"}
}