{
  "type": "Feature",
  "properties": {
    "iso:country":"DE",
    "sg:address":"Stintzingstr. 31",
    "sg:city":"Erlangen",
    "sg:phone":"+49 9131/31085",
    "sg:postcode":"91052",
    "sg:province":"Bayern",
    "wof:name":"Baustoffe Schlemmer Gmbh & Co. Kg",
    "wof:placetype":"venue"
},
  "geometry": {"coordinates":[11.003655,49.580627],"type":"Point"}
}