{
  "type": "Feature",
  "properties": {
    "iso:country":"DE",
    "sg:address":"Scheibenstr. 12",
    "sg:city":"Traunstein",
    "sg:phone":"+49 861/6794",
    "sg:postcode":"83278",
    "sg:province":"Bayern",
    "wof:name":"Richard Hilscher",
    "wof:placetype":"venue"
},
  "geometry": {"coordinates":[12.651869,47.869652],"type":"Point"}
}