{
  "type": "Feature",
  "properties": {
    "iso:country":"DE",
    "sg:address":"Billstedter Hauptstr. 71",
    "sg:city":"Hamburg",
    "sg:phone":"+49 40/7310630",
    "sg:postcode":"22111",
    "sg:province":"Hamburg",
    "wof:name":"Cord-w. Hellinger Steuerberater",
    "wof:placetype":"venue"
},
  "geometry": {"coordinates":[10.106092453,53.5384216309],"type":"Point"}
}