{
  "type": "Feature",
  "properties": {
    "iso:country":"DE",
    "sg:address":"Hunnenswarf",
    "sg:city":"Langene\u00df",
    "sg:phone":"+49 4684/224",
    "sg:postcode":"25863",
    "sg:province":"Schleswig-Holstein",
    "wof:name":"A. Boysen",
    "wof:placetype":"venue"
},
  "geometry": {"coordinates":[8.640137,54.648464],"type":"Point"}
}