{
  "type": "Feature",
  "properties": {
    "iso:country":"DE",
    "sg:address":"Drachenfelsstr. 16",
    "sg:city":"Lohmar",
    "sg:phone":"+49 2205/4209",
    "sg:postcode":"53797",
    "sg:province":"Nordrhein-Westfalen",
    "wof:name":"Wolfgang Beck",
    "wof:placetype":"venue"
},
  "geometry": {"coordinates":[7.241557,50.905094],"type":"Point"}
}