{
  "type": "Feature",
  "properties": {
    "iso:country":"DE",
    "sg:address":"\u00c4u\u00dfere N\u00fcrnberger Str. 8",
    "sg:city":"Thalm\u00e4ssing",
    "sg:phone":"+49 9173/266",
    "sg:postcode":"91177",
    "sg:province":"Bayern",
    "wof:name":"Peter Schmehling Gmbh",
    "wof:placetype":"venue"
},
  "geometry": {"coordinates":[11.2096500397,49.0923843384],"type":"Point"}
}