{
  "type": "Feature",
  "properties": {
    "iso:country":"DE",
    "sg:address":"Am Feybach 5",
    "sg:city":"Mechernich",
    "sg:phone":"+49 2484/1458",
    "sg:postcode":"53894",
    "sg:province":"Nordrhein-Westfalen",
    "wof:name":"Michael Sistig",
    "wof:placetype":"venue"
},
  "geometry": {"coordinates":[6.6547179222,50.555393219],"type":"Point"}
}