{
  "type": "Feature",
  "properties": {
    "iso:country":"DE",
    "sg:address":"Bosauer Str. 4",
    "sg:city":"Seedorf",
    "sg:phone":"+49 4555/823",
    "sg:postcode":"23823",
    "sg:province":"Schleswig-Holstein",
    "wof:name":"Herbert Bargholz",
    "wof:placetype":"venue"
},
  "geometry": {"coordinates":[10.429369,54.051807],"type":"Point"}
}