{
  "type": "Feature",
  "properties": {
    "iso:country":"DE",
    "sg:address":"Herforder Str. 155 A",
    "sg:city":"Bielefeld",
    "sg:phone":"+49 4952/1932310",
    "sg:postcode":"33609",
    "sg:province":"Nordrhein-Westfalen",
    "wof:name":"Cesoft Softwareentwicklung Gmbh",
    "wof:placetype":"venue"
},
  "geometry": {"coordinates":[8.548787117,52.0348014832],"type":"Point"}
}