{
  "type": "Feature",
  "properties": {
    "iso:country":"DE",
    "sg:address":"Hauptstr. 46",
    "sg:city":"Linnich",
    "sg:phone":"+49 2462/8392",
    "sg:postcode":"52441",
    "sg:province":"Nordrhein-Westfalen",
    "wof:name":"Gastst\u00e4tte H. Leuchter",
    "wof:placetype":"venue"
},
  "geometry": {"coordinates":[6.2806038857,51.0019798279],"type":"Point"}
}