{
  "type": "Feature",
  "properties": {
    "iso:country":"DE",
    "sg:address":"Grosjeanstr. 2",
    "sg:city":"M\u00fcnchen",
    "sg:postcode":"81925",
    "sg:province":"Bayern",
    "wof:name":"Bender Records Gmbh",
    "wof:placetype":"venue"
},
  "geometry": {"coordinates":[11.6132946014,48.1549835205],"type":"Point"}
}