{
  "type": "Feature",
  "properties": {
    "iso:country":"DE",
    "sg:address":"Hansestr. 2",
    "sg:city":"Roth",
    "sg:phone":"+49 9171/4634",
    "sg:postcode":"91154",
    "sg:province":"Bayern",
    "wof:name":"Gerhard Blank Gmbh",
    "wof:placetype":"venue"
},
  "geometry": {"coordinates":[11.106156,49.250717],"type":"Point"}
}