{
  "type": "Feature",
  "properties": {
    "iso:country":"DE",
    "sg:address":"Gr\u00fcner Kamp 5",
    "sg:city":"Pinneberg",
    "sg:phone":"+49 4101/61974",
    "sg:postcode":"25421",
    "sg:province":"Schleswig-Holstein",
    "wof:name":"Richard K\u00f6hler Ingenieur",
    "wof:placetype":"venue"
},
  "geometry": {"coordinates":[9.7819499969,53.6497154236],"type":"Point"}
}