{
  "type": "Feature",
  "properties": {
    "iso:country":"DE",
    "sg:address":"Am Hohenmoor 36",
    "sg:city":"Kaltenkirchen",
    "sg:phone":"+49 4191/6108",
    "sg:postcode":"24568",
    "sg:province":"Schleswig-Holstein",
    "wof:name":"K. Stolper Garten- Und",
    "wof:placetype":"venue"
},
  "geometry": {"coordinates":[9.947583,53.829838],"type":"Point"}
}