{
  "type": "Feature",
  "properties": {
    "iso:country":"DE",
    "sg:address":"Borsteler Str. 41",
    "sg:city":"Neustadt",
    "sg:phone":"+49 5034/4122",
    "sg:postcode":"31535",
    "sg:province":"Niedersachsen",
    "wof:name":"Heinrich Dangers",
    "wof:placetype":"venue"
},
  "geometry": {"coordinates":[9.3832454681,52.5863838196],"type":"Point"}
}