{
  "type": "Feature",
  "properties": {
    "iso:country":"DE",
    "sg:address":"Xantener Str 22",
    "sg:city":"Berlin",
    "sg:phone":"+49 30/8933514",
    "sg:postcode":"10707",
    "sg:province":"Berlin",
    "wof:name":"Ion Industrial Design Berlin Fleckenstein & G\u00f6tz Gbr",
    "wof:placetype":"venue"
},
  "geometry": {"coordinates":[13.30878,52.499161],"type":"Point"}
}