{
  "type": "Feature",
  "properties": {
    "iso:country":"DE",
    "sg:address":"B\u00fclt 52",
    "sg:city":"Heek",
    "sg:postcode":"48619",
    "sg:province":"Nordrhein-Westfalen",
    "wof:name":"Gala-bau Vortkamp Verwaltungs- Und Beteiligungsges. Mbh",
    "wof:placetype":"venue"
},
  "geometry": {"coordinates":[7.121485,52.120869],"type":"Point"}
}