{
  "type": "Feature",
  "properties": {
    "iso:country":"DE",
    "sg:address":"Friemersheimer Str. 27",
    "sg:city":"Duisburg",
    "sg:postcode":"47229",
    "sg:province":"Nordrhein-Westfalen",
    "wof:name":"Ev. Pfarramt I Friemersheim",
    "wof:placetype":"venue"
},
  "geometry": {"coordinates":[6.7019681931,51.3819274902],"type":"Point"}
}