{
  "type": "Feature",
  "properties": {
    "iso:country":"DE",
    "sg:address":"Am Seegraben 17b",
    "sg:city":"Gro\u00df Gaglow",
    "sg:phone":"+49 355/5842650",
    "sg:postcode":"03058",
    "sg:province":"Brandenburg",
    "wof:name":"Dr. G. Pahn",
    "wof:placetype":"venue"
},
  "geometry": {"coordinates":[14.3113956451,51.7180862427],"type":"Point"}
}