{
  "type": "Feature",
  "properties": {
    "iso:country":"DE",
    "sg:address":"Burgstr. 13",
    "sg:city":"Windischeschenbach",
    "sg:phone":"+49 9681/8147",
    "sg:postcode":"92670",
    "sg:province":"Bayern",
    "wof:name":"Waldnaabtal-museum Burg Neuhaus",
    "wof:placetype":"venue"
},
  "geometry": {"coordinates":[12.153886,49.804081],"type":"Point"}
}