{
  "type": "Feature",
  "properties": {
    "iso:country":"DE",
    "sg:address":"Obermausbach 1",
    "sg:city":"Wipperf\u00fcrth",
    "sg:phone":"+49 2268/1560",
    "sg:postcode":"51688",
    "sg:province":"Nordrhein-Westfalen",
    "wof:name":"W. Philipps",
    "wof:placetype":"venue"
},
  "geometry": {"coordinates":[7.3179731369,51.0952110291],"type":"Point"}
}