{
  "type": "Feature",
  "properties": {
    "iso:country":"DE",
    "sg:address":"Mozartstr. 33",
    "sg:city":"Notzingen",
    "sg:phone":"+49 7021/41053",
    "sg:postcode":"73274",
    "sg:province":"Baden-W\u00fcrttemberg",
    "wof:name":"Marianne Berger",
    "wof:placetype":"venue"
},
  "geometry": {"coordinates":[9.470582,48.67474],"type":"Point"}
}