{
  "type": "Feature",
  "properties": {
    "iso:country":"DE",
    "sg:address":"Adelheidstr. 8",
    "sg:city":"Worms",
    "sg:phone":"+49 6241/75784",
    "sg:postcode":"67549",
    "sg:province":"Rheinland-Pfalz",
    "wof:name":"G\u00fcnter Stelkens Lehr- Und Lernmittel Gmbh",
    "wof:placetype":"venue"
},
  "geometry": {"coordinates":[8.323531,49.638042],"type":"Point"}
}