{
  "type": "Feature",
  "properties": {
    "iso:country":"DE",
    "sg:address":"Neue Str. 6",
    "sg:city":"Creglingen",
    "sg:phone":"+49 7933/20106",
    "sg:postcode":"97993",
    "sg:province":"Baden-W\u00fcrttemberg",
    "wof:name":"Erich Pfannkuch Und H. Pieler",
    "wof:placetype":"venue"
},
  "geometry": {"coordinates":[10.0314540863,49.4689483643],"type":"Point"}
}