{
  "type": "Feature",
  "properties": {
    "iso:country":"DE",
    "sg:address":"Sonnhalde 3",
    "sg:city":"Stockach",
    "sg:phone":"+49 7771/921464",
    "sg:postcode":"78333",
    "sg:province":"Baden-W\u00fcrttemberg",
    "wof:name":"Verein Freie Waldorfschule Wahlwies",
    "wof:placetype":"venue"
},
  "geometry": {"coordinates":[8.9659748077,47.8114433289],"type":"Point"}
}