{
  "type": "Feature",
  "properties": {
    "iso:country":"DE",
    "sg:address":"Trasham 59",
    "sg:city":"Ruderting",
    "sg:phone":"+49 8509/2841",
    "sg:postcode":"94161",
    "sg:province":"Bayern",
    "wof:name":"Mjr Service & Vertriebs Gmbh",
    "wof:placetype":"venue"
},
  "geometry": {"coordinates":[13.395911,48.667927],"type":"Point"}
}