{
  "type": "Feature",
  "properties": {
    "iso:country":"DE",
    "sg:address":"Alte Landstr. 33",
    "sg:city":"Drolshagen",
    "sg:phone":"+49 2761/71760",
    "sg:postcode":"57489",
    "sg:province":"Nordrhein-Westfalen",
    "wof:name":"Ursula Blum",
    "wof:placetype":"venue"
},
  "geometry": {"coordinates":[7.785932,51.018669],"type":"Point"}
}