{
  "type": "Feature",
  "properties": {
    "iso:country":"DE",
    "sg:address":"H\u00fcltzstr. 6-8",
    "sg:city":"K\u00f6ln",
    "sg:phone":"+49 221/400890",
    "sg:postcode":"50933",
    "sg:province":"Nordrhein-Westfalen",
    "wof:name":"Rolf Hennies Steuerberater",
    "wof:placetype":"venue"
},
  "geometry": {"coordinates":[6.9071497917,50.9365463257],"type":"Point"}
}