{
  "type": "Feature",
  "properties": {
    "iso:country":"DE",
    "sg:address":"Seestr. 50",
    "sg:city":"Dahme",
    "sg:phone":"+49 4364/312",
    "sg:postcode":"23747",
    "sg:province":"Schleswig-Holstein",
    "wof:name":"Helmut Schr\u00f6der",
    "wof:placetype":"venue"
},
  "geometry": {"coordinates":[11.0881252289,54.2197151184],"type":"Point"}
}