{
  "type": "Feature",
  "properties": {
    "iso:country":"DE",
    "sg:address":"Arfelder Hauptstr. 45",
    "sg:city":"Bad Berleburg",
    "sg:phone":"+49 2755/711",
    "sg:postcode":"57319",
    "sg:province":"Nordrhein-Westfalen",
    "wof:name":"Hermann Afflerbach",
    "wof:placetype":"venue"
},
  "geometry": {"coordinates":[8.438319,51.015015],"type":"Point"}
}