{
  "type": "Feature",
  "properties": {
    "iso:country":"DE",
    "sg:address":"Lindenstr. 7",
    "sg:city":"Bad Langensalza",
    "sg:phone":"+49 3603/813370",
    "sg:postcode":"99947",
    "sg:province":"Th\u00fcringen",
    "wof:name":"M\u00f6bel Gmbh",
    "wof:placetype":"venue"
},
  "geometry": {"coordinates":[10.63289,51.102039],"type":"Point"}
}