{
  "type": "Feature",
  "properties": {
    "iso:country":"DE",
    "sg:address":"Schillerstr. 14",
    "sg:city":"M\u00fcnchen",
    "sg:phone":"+49 89/593877",
    "sg:postcode":"80336",
    "sg:province":"Bayern",
    "wof:name":"Dolema Aussenhandel Inh. Ivo Tikvic",
    "wof:placetype":"venue"
},
  "geometry": {"coordinates":[11.5608587265,48.1378479004],"type":"Point"}
}