{
  "type": "Feature",
  "properties": {
    "iso:country":"DE",
    "sg:address":"Donaustaufer Str. 164 a",
    "sg:city":"Regensburg",
    "sg:postcode":"93059",
    "sg:province":"Bayern",
    "wof:name":"R. E. U. T.-regensburger Energie- Und Umwelttechnik Ohg",
    "wof:placetype":"venue"
},
  "geometry": {"coordinates":[12.126486,49.028931],"type":"Point"}
}