{
  "type": "Feature",
  "properties": {
    "iso:country":"DE",
    "sg:address":"Moltkestr. 1",
    "sg:city":"G\u00fctersloh",
    "sg:phone":"+49 5241/92430",
    "sg:postcode":"33330",
    "sg:province":"Nordrhein-Westfalen",
    "wof:name":"Foto Schorcht Rainer Schorcht",
    "wof:placetype":"venue"
},
  "geometry": {"coordinates":[8.3776063919,51.9070243835],"type":"Point"}
}