{
  "type": "Feature",
  "properties": {
    "iso:country":"DE",
    "sg:address":"Am Baggerteich 2",
    "sg:city":"Coswig",
    "sg:phone":"+49 3523/71918",
    "sg:postcode":"01640",
    "sg:province":"Sachsen",
    "wof:name":"Hermann Hald Baumaschinen Gmbh & Co.",
    "wof:placetype":"venue"
},
  "geometry": {"coordinates":[13.565437,51.131302],"type":"Point"}
}