{
  "type": "Feature",
  "properties": {
    "iso:country":"DE",
    "sg:address":"Debberoder Str. 1",
    "sg:city":"Hannover",
    "sg:phone":"+49 511/528253",
    "sg:postcode":"30539",
    "sg:province":"Niedersachsen",
    "wof:name":"Wilhelm Breustedt",
    "wof:placetype":"venue"
},
  "geometry": {"coordinates":[9.834646225,52.3101577759],"type":"Point"}
}