{
  "type": "Feature",
  "properties": {
    "iso:country":"DE",
    "sg:address":"Wiesenstr 9",
    "sg:city":"Uffenheim",
    "sg:phone":"+49 9842/97977",
    "sg:postcode":"97215",
    "sg:province":"Bayern",
    "wof:name":"Helmut Veeh Gmbh",
    "wof:placetype":"venue"
},
  "geometry": {"coordinates":[10.2326698303,49.5479316711],"type":"Point"}
}