{
  "type": "Feature",
  "properties": {
    "iso:country":"DE",
    "sg:address":"Boltzmannstr. 3",
    "sg:city":"Berlin",
    "sg:postcode":"14195",
    "sg:province":"Berlin",
    "wof:name":"Institut F. Grundlagen Und Grenzgeb. D. Rechts Fachricht.",
    "wof:placetype":"venue"
},
  "geometry": {"coordinates":[13.2801866531,52.4483757019],"type":"Point"}
}