{
  "type": "Feature",
  "properties": {
    "iso:country":"DE",
    "sg:address":"R\u00fcstersieler Str. 35",
    "sg:city":"Wilhelmshaven",
    "sg:phone":"+49 4421/61658",
    "sg:postcode":"26386",
    "sg:province":"Niedersachsen",
    "wof:name":"Jacobs Malereibetrieb Gmbh",
    "wof:placetype":"venue"
},
  "geometry": {"coordinates":[8.10506,53.55537],"type":"Point"}
}