{
  "type": "Feature",
  "properties": {
    "iso:country":"DE",
    "sg:address":"Gersthofer Str. 3",
    "sg:city":"Frankfurt",
    "sg:phone":"+49 69/313166",
    "sg:postcode":"65929",
    "sg:province":"Hessen",
    "wof:name":"Joachim Christ Bauschlosserei",
    "wof:placetype":"venue"
},
  "geometry": {"coordinates":[8.5424127579,50.1006851196],"type":"Point"}
}