{
  "type": "Feature",
  "properties": {
    "iso:country":"DE",
    "sg:address":"Gutenbergstr. 26",
    "sg:city":"Dei\u00dflingen",
    "sg:phone":"+49 7420/1606",
    "sg:postcode":"78652",
    "sg:province":"Baden-W\u00fcrttemberg",
    "wof:name":"Detlef Skandy",
    "wof:placetype":"venue"
},
  "geometry": {"coordinates":[8.6059513092,48.1087608337],"type":"Point"}
}