{
  "type": "Feature",
  "properties": {
    "iso:country":"DE",
    "sg:address":"Am Hulsberg 19",
    "sg:city":"Bremen",
    "sg:phone":"+49 421/449072",
    "sg:postcode":"28205",
    "sg:province":"Bremen",
    "wof:name":"Brinkmann-immobilien",
    "wof:placetype":"venue"
},
  "geometry": {"coordinates":[8.8441171646,53.0718765259],"type":"Point"}
}