{
  "type": "Feature",
  "properties": {
    "iso:country":"DE",
    "sg:address":"Werdener Str. 25",
    "sg:city":"Velbert",
    "sg:phone":"+49 2051/82464",
    "sg:postcode":"42551",
    "sg:province":"Nordrhein-Westfalen",
    "wof:name":"Auto-trading Fuhrmann Gmbh",
    "wof:placetype":"venue"
},
  "geometry": {"coordinates":[7.0304031372,51.3463897705],"type":"Point"}
}