{
  "type": "Feature",
  "properties": {
    "iso:country":"DE",
    "sg:address":"Uhlandstr. 41",
    "sg:city":"Bad S\u00e4ckingen",
    "sg:phone":"+49 7761/6720",
    "sg:postcode":"79713",
    "sg:province":"Baden-W\u00fcrttemberg",
    "wof:name":"Erich J\u00e4ger Architekt",
    "wof:placetype":"venue"
},
  "geometry": {"coordinates":[7.931859,47.559429],"type":"Point"}
}