{
  "type": "Feature",
  "properties": {
    "iso:country":"DE",
    "sg:address":"Emser Str. 27",
    "sg:city":"Becheln",
    "sg:phone":"+49 2603/2634",
    "sg:postcode":"56132",
    "sg:province":"Rheinland-Pfalz",
    "wof:name":"Gernot Wagner",
    "wof:placetype":"venue"
},
  "geometry": {"coordinates":[7.717863,50.293255],"type":"Point"}
}