{
  "type": "Feature",
  "properties": {
    "iso:country":"DE",
    "sg:address":"Turnstr. 31",
    "sg:city":"Ispringen",
    "sg:phone":"+49 4972/318030",
    "sg:postcode":"75228",
    "sg:province":"Baden-W\u00fcrttemberg",
    "wof:name":"Tiolox Implants Gmbh",
    "wof:placetype":"venue"
},
  "geometry": {"coordinates":[8.6642780304,48.9131278992],"type":"Point"}
}