{
  "type": "Feature",
  "properties": {
    "iso:country":"DE",
    "sg:address":"Zum Turm 16",
    "sg:city":"Wippingen",
    "sg:postcode":"26892",
    "sg:province":"Niedersachsen",
    "wof:name":"Raiffeisen-zentral- Genossenschaft Eg",
    "wof:placetype":"venue"
},
  "geometry": {"coordinates":[7.409154,52.921837],"type":"Point"}
}