{
  "type": "Feature",
  "properties": {
    "iso:country":"DE",
    "sg:address":"Benzenbergweg 31",
    "sg:city":"Br\u00fcggen",
    "sg:phone":"+49 2163/953533",
    "sg:postcode":"41379",
    "sg:province":"Nordrhein-Westfalen",
    "wof:name":"Gmv Gesellschaft F. Marketing Und Vertrieb Mbh",
    "wof:placetype":"venue"
},
  "geometry": {"coordinates":[6.1869077682,51.248249054],"type":"Point"}
}