{
  "type": "Feature",
  "properties": {
    "iso:country":"DE",
    "sg:address":"Hauptstr. 341",
    "sg:city":"K\u00f6nigswinter",
    "sg:phone":"+49 2223/21268",
    "sg:postcode":"53639",
    "sg:province":"Nordrhein-Westfalen",
    "wof:name":"Bei Henry",
    "wof:placetype":"venue"
},
  "geometry": {"coordinates":[7.1911277771,50.6774330139],"type":"Point"}
}