{
  "type": "Feature",
  "properties": {
    "iso:country":"DE",
    "sg:address":"Mohlstr. 65",
    "sg:city":"Tuttlingen",
    "sg:phone":"+49 7461/3452",
    "sg:postcode":"78532",
    "sg:province":"Baden-W\u00fcrttemberg",
    "wof:name":"Anita Hennis",
    "wof:placetype":"venue"
},
  "geometry": {"coordinates":[8.812289,47.988766],"type":"Point"}
}