{
  "type": "Feature",
  "properties": {
    "iso:country":"DE",
    "sg:address":"Schrannengasse 13",
    "sg:city":"F\u00fcssen",
    "sg:phone":"+49 8362/4467",
    "sg:postcode":"87629",
    "sg:province":"Bayern",
    "wof:name":"Reiseb\u00fcro Gueffroy",
    "wof:placetype":"venue"
},
  "geometry": {"coordinates":[10.7009000778,47.568611145],"type":"Point"}
}