{
  "type": "Feature",
  "properties": {
    "iso:country":"DE",
    "sg:address":"Hauptbahnhofstr. 18",
    "sg:city":"Schweinfurt",
    "sg:phone":"+49 9721/802511",
    "sg:postcode":"97424",
    "sg:province":"Bayern",
    "wof:name":"Adolf Mai",
    "wof:placetype":"venue"
},
  "geometry": {"coordinates":[10.215027,50.036671],"type":"Point"}
}