{
  "type": "Feature",
  "properties": {
    "iso:country":"DE",
    "sg:address":"Kantstr. 1",
    "sg:city":"Mainz",
    "sg:phone":"+49 4961/313030",
    "sg:postcode":"55122",
    "sg:province":"Rheinland-Pfalz",
    "wof:name":"Bausparkasse Mainz Ag",
    "wof:placetype":"venue"
},
  "geometry": {"coordinates":[8.23816,49.99538],"type":"Point"}
}