{
  "type": "Feature",
  "properties": {
    "iso:country":"DE",
    "sg:address":"Haubachstr. 4",
    "sg:city":"Hamburg",
    "sg:phone":"+49 40/38619665",
    "sg:postcode":"22765",
    "sg:province":"Hamburg",
    "wof:name":"B\u00fcch Mulitmedia Kg",
    "wof:placetype":"venue"
},
  "geometry": {"coordinates":[9.9373207092,53.5560569763],"type":"Point"}
}