{
  "type": "Feature",
  "properties": {
    "iso:country":"DE",
    "sg:address":"Industriestr. 22",
    "sg:city":"Schkeuditz",
    "sg:phone":"+49 34204/66219",
    "sg:postcode":"04435",
    "sg:province":"Sachsen",
    "wof:name":"A. Kaufmann",
    "wof:placetype":"venue"
},
  "geometry": {"coordinates":[12.2164506912,51.403755188],"type":"Point"}
}