{
  "type": "Feature",
  "properties": {
    "iso:country":"DE",
    "sg:address":"Friederweg 6",
    "sg:city":"Grainau",
    "sg:phone":"+49 8821/988098",
    "sg:postcode":"82491",
    "sg:province":"Bayern",
    "wof:name":"Efd Zinkl Gmbh",
    "wof:placetype":"venue"
},
  "geometry": {"coordinates":[11.0409088135,47.4814453125],"type":"Point"}
}