{
  "type": "Feature",
  "properties": {
    "iso:country":"DE",
    "sg:address":"Rainweg 30",
    "sg:city":"Heidelberg",
    "sg:phone":"+49 6221/800229",
    "sg:postcode":"69118",
    "sg:province":"Baden-W\u00fcrttemberg",
    "wof:name":"Karl Brunner",
    "wof:placetype":"venue"
},
  "geometry": {"coordinates":[8.748344,49.425766],"type":"Point"}
}