{
  "type": "Feature",
  "properties": {
    "iso:country":"DE",
    "sg:address":"Wartenburger Str. 61",
    "sg:city":"Globig-Bleddin",
    "sg:phone":"+49 34927/20770",
    "sg:postcode":"06901",
    "sg:province":"Sachsen-Anhalt",
    "wof:name":"F. Lohmann",
    "wof:placetype":"venue"
},
  "geometry": {"coordinates":[12.744192,51.790237],"type":"Point"}
}