{
  "type": "Feature",
  "properties": {
    "iso:country":"DE",
    "sg:address":"Kelterstr. 4",
    "sg:city":"Kirchheim",
    "sg:phone":"+49 7021/51081",
    "sg:postcode":"73230",
    "sg:province":"Baden-W\u00fcrttemberg",
    "wof:name":"Naberner Seefreunde E. V. Werner Bressmer",
    "wof:placetype":"venue"
},
  "geometry": {"coordinates":[9.4810018539,48.617313385],"type":"Point"}
}