{
  "type": "Feature",
  "properties": {
    "iso:country":"DE",
    "sg:address":"Syassen Strasse 13",
    "sg:city":"Brake",
    "sg:phone":"+49 4401/936000",
    "sg:postcode":"26916",
    "sg:province":"Niedersachsen",
    "wof:name":"Dt Datentechnik Toenjes Gmbh",
    "wof:placetype":"venue"
},
  "geometry": {"coordinates":[-101.3000030518,27.9167003632],"type":"Point"}
}