{
  "type": "Feature",
  "properties": {
    "iso:country":"DE",
    "sg:address":"Kastellstr. 9",
    "sg:city":"Erlensee",
    "sg:phone":"+49 6183/6623",
    "sg:postcode":"63526",
    "sg:province":"Hessen",
    "wof:name":"Ergin Aysal",
    "wof:placetype":"venue"
},
  "geometry": {"coordinates":[8.978729,50.16325],"type":"Point"}
}