{
  "type": "Feature",
  "properties": {
    "iso:country":"DE",
    "sg:address":"Hessenring 4",
    "sg:city":"M\u00f6rfelden-Walldorf",
    "sg:postcode":"64546",
    "sg:province":"Hessen",
    "wof:name":"Fabrikverkauf Direkt Ag",
    "wof:placetype":"venue"
},
  "geometry": {"coordinates":[8.581081,49.980957],"type":"Point"}
}