{
  "type": "Feature",
  "properties": {
    "iso:country":"DE",
    "sg:address":"D\u00f6rpkestieg 1",
    "sg:city":"Goslar",
    "sg:phone":"+49 5321/34750",
    "sg:postcode":"38640",
    "sg:province":"Niedersachsen",
    "wof:name":"Hans-joachim-tessner-stiftung",
    "wof:placetype":"venue"
},
  "geometry": {"coordinates":[10.4423427582,51.9026947021],"type":"Point"}
}