{
  "type": "Feature",
  "properties": {
    "iso:country":"DE",
    "sg:address":"Edinger Riedweg 45 -47",
    "sg:city":"Mannheim",
    "sg:phone":"+49 621/891343",
    "sg:postcode":"68219",
    "sg:province":"Baden-W\u00fcrttemberg",
    "wof:name":"Gmd G. M. Dankewitz Thermoplast Gmbh",
    "wof:placetype":"venue"
},
  "geometry": {"coordinates":[8.53176,49.421669],"type":"Point"}
}