{
  "type": "Feature",
  "properties": {
    "iso:country":"DE",
    "sg:address":"Sennehof 25",
    "sg:city":"Bielefeld",
    "sg:phone":"+49 521/492222",
    "sg:postcode":"33659",
    "sg:province":"Nordrhein-Westfalen",
    "wof:name":"Cv Marketing Gmbh",
    "wof:placetype":"venue"
},
  "geometry": {"coordinates":[8.5393323898,51.9746856689],"type":"Point"}
}