{
  "type": "Feature",
  "properties": {
    "iso:country":"DE",
    "sg:address":"Nordstr. 10",
    "sg:city":"Oldenburg",
    "sg:postcode":"26135",
    "sg:province":"Niedersachsen",
    "wof:name":"Treuhand Und Verm\u00f6gens- Verwaltung Peter Kawalla E.k.",
    "wof:placetype":"venue"
},
  "geometry": {"coordinates":[8.226008,53.13723],"type":"Point"}
}