{
  "type": "Feature",
  "properties": {
    "iso:country":"DE",
    "sg:address":"Bremker Str. 3",
    "sg:city":"Extertal",
    "sg:phone":"+49 5754/1564",
    "sg:postcode":"32699",
    "sg:province":"Nordrhein-Westfalen",
    "wof:name":"Erwin Schmidtke",
    "wof:placetype":"venue"
},
  "geometry": {"coordinates":[9.10557,52.126831],"type":"Point"}
}