{
  "type": "Feature",
  "properties": {
    "iso:country":"DE",
    "sg:address":"W\u00fcrzburger Str. 5",
    "sg:city":"Reichenberg",
    "sg:phone":"+49 931/661030",
    "sg:postcode":"97234",
    "sg:province":"Bayern",
    "wof:name":"Marien-apotheke E. K.",
    "wof:placetype":"venue"
},
  "geometry": {"coordinates":[9.9168,49.732632],"type":"Point"}
}