{
  "type": "Feature",
  "properties": {
    "iso:country":"DE",
    "sg:address":"Alsterufer 26",
    "sg:city":"Hamburg",
    "sg:phone":"+49 40/3891770",
    "sg:postcode":"20354",
    "sg:province":"Hamburg",
    "wof:name":"Verwaltung Rickmers Schiffs- Beteiligungs Gmbh",
    "wof:placetype":"venue"
},
  "geometry": {"coordinates":[9.9971199036,53.562122345],"type":"Point"}
}