{
  "type": "Feature",
  "properties": {
    "iso:country":"DE",
    "sg:address":"Petersburg 2",
    "sg:city":"Gronau",
    "sg:phone":"+49 2565/4232",
    "sg:postcode":"48599",
    "sg:province":"Nordrhein-Westfalen",
    "wof:name":"Tropex Markisenbau Gmbh",
    "wof:placetype":"venue"
},
  "geometry": {"coordinates":[7.024683,52.190762],"type":"Point"}
}