{
  "type": "Feature",
  "properties": {
    "iso:country":"DE",
    "sg:address":"Baierstr. 59",
    "sg:city":"B\u00f6hmenkirch",
    "sg:phone":"+49 7332/3911",
    "sg:postcode":"89558",
    "sg:province":"Baden-W\u00fcrttemberg",
    "wof:name":"Joachim Ziller",
    "wof:placetype":"venue"
},
  "geometry": {"coordinates":[9.940034,48.688457],"type":"Point"}
}