{
  "type": "Feature",
  "properties": {
    "iso:country":"DE",
    "sg:address":"Pl\u00fcggentiner Stra\u00dfe 18",
    "sg:city":"Samtens / R\u00fcgen",
    "sg:phone":"+49 38306/21020",
    "sg:postcode":"18573",
    "sg:province":"Mecklenburg-Vorpommern",
    "wof:name":"Freizeitzentrum \u00b4r\u00fcgen - Tiet Un Wiel\u00b4",
    "wof:placetype":"venue"
},
  "geometry": {"coordinates":[13.1287498474,54.3291397095],"type":"Point"}
}