{
  "type": "Feature",
  "properties": {
    "iso:country":"DE",
    "sg:address":"Herzogstr. 116",
    "sg:city":"M\u00fcnchen",
    "sg:phone":"+49 89/3009048",
    "sg:postcode":"80796",
    "sg:province":"Bayern",
    "wof:name":"A. Komma-p\u00f6llath Immobilienmakler",
    "wof:placetype":"venue"
},
  "geometry": {"coordinates":[11.5667457581,48.1634750366],"type":"Point"}
}