{
  "type": "Feature",
  "properties": {
    "iso:country":"DE",
    "sg:address":"Uppenbornstr 19a",
    "sg:city":"Moosburg",
    "sg:phone":"+49 8761/72540",
    "sg:postcode":"85368",
    "sg:province":"Bayern",
    "wof:name":"M-system Elektronik Gmbh",
    "wof:placetype":"venue"
},
  "geometry": {"coordinates":[11.936375,48.49445],"type":"Point"}
}