{
  "type": "Feature",
  "properties": {
    "iso:country":"DE",
    "sg:address":"Kremenholler Str. 5",
    "sg:city":"Remscheid",
    "sg:phone":"+49 2191/40249",
    "sg:postcode":"42857",
    "sg:province":"Nordrhein-Westfalen",
    "wof:name":"S. D\u00f6rpfeld",
    "wof:placetype":"venue"
},
  "geometry": {"coordinates":[7.184076786,51.1766738892],"type":"Point"}
}