{
  "type": "Feature",
  "properties": {
    "iso:country":"DE",
    "sg:address":"Bunzlauer Weg 23",
    "sg:city":"D\u00fcsseldorf",
    "sg:phone":"+49 211/278202",
    "sg:postcode":"40627",
    "sg:province":"Nordrhein-Westfalen",
    "wof:name":"Sass Gmbh",
    "wof:placetype":"venue"
},
  "geometry": {"coordinates":[6.8443617821,51.2160148621],"type":"Point"}
}