{
  "type": "Feature",
  "properties": {
    "iso:country":"DE",
    "sg:address":"Siegstr.",
    "sg:city":"Betzdorf",
    "sg:phone":"+49 2741/22551",
    "sg:postcode":"57518",
    "sg:province":"Rheinland-Pfalz",
    "wof:name":"Bauer",
    "wof:placetype":"venue"
},
  "geometry": {"coordinates":[7.8761329651,50.7915458679],"type":"Point"}
}