{
  "type": "Feature",
  "properties": {
    "iso:country":"DE",
    "sg:address":"Walramsneustr. 7",
    "sg:city":"Trier",
    "sg:phone":"+49 651/948030",
    "sg:postcode":"54290",
    "sg:province":"Rheinland-Pfalz",
    "wof:name":"Dr. S. Schatz Und Theo Bomm Rechtsanw\u00e4lte",
    "wof:placetype":"venue"
},
  "geometry": {"coordinates":[6.6383118629,49.758354187],"type":"Point"}
}