{
  "type": "Feature",
  "properties": {
    "iso:country":"DE",
    "sg:address":"An der Eie 6",
    "sg:city":"Drolshagen",
    "sg:phone":"+49 2763/214843",
    "sg:postcode":"57489",
    "sg:province":"Nordrhein-Westfalen",
    "wof:name":"Id-acc.",
    "wof:placetype":"venue"
},
  "geometry": {"coordinates":[7.720192,51.056885],"type":"Point"}
}