{
  "type": "Feature",
  "properties": {
    "iso:country":"DE",
    "sg:address":"Everndorf 34",
    "sg:city":"Ganderkesee",
    "sg:phone":"+49 4222/8267",
    "sg:postcode":"27777",
    "sg:province":"Niedersachsen",
    "wof:name":"Heino Hohnholt",
    "wof:placetype":"venue"
},
  "geometry": {"coordinates":[8.457262,53.021679],"type":"Point"}
}