{
  "type": "Feature",
  "properties": {
    "iso:country":"DE",
    "sg:address":"Steinmetzenweg 4",
    "sg:city":"Bremen",
    "sg:phone":"+49 421/451836",
    "sg:postcode":"28309",
    "sg:province":"Bremen",
    "wof:name":"Walter Achtmann",
    "wof:placetype":"venue"
},
  "geometry": {"coordinates":[8.915338,53.060509],"type":"Point"}
}