{
  "type": "Feature",
  "properties": {
    "iso:country":"DE",
    "sg:address":"Kaiserstrasse 4 c",
    "sg:city":"Saarbr\u00fccken",
    "sg:phone":"+49 681",
    "sg:postcode":"66133",
    "sg:province":"Saarland",
    "wof:name":"Hifi-garage; Saarbr\u00fccken",
    "wof:placetype":"venue"
},
  "geometry": {"coordinates":[7.0741500854,49.2560691833],"type":"Point"}
}