{
  "type": "Feature",
  "properties": {
    "iso:country":"DE",
    "sg:address":"K\u00f6hlerwiese 1a",
    "sg:city":"Brotterode",
    "sg:phone":"+49 36840/31033",
    "sg:postcode":"98599",
    "sg:province":"Th\u00fcringen",
    "wof:name":"Ing. M. Lachmund Ingenieur",
    "wof:placetype":"venue"
},
  "geometry": {"coordinates":[10.4486608505,50.8248634338],"type":"Point"}
}