{
  "type": "Feature",
  "properties": {
    "iso:country":"DE",
    "sg:address":"Kaufhof 25",
    "sg:city":"Wolfsburg",
    "sg:phone":"+49 5361/16825",
    "sg:postcode":"38440",
    "sg:province":"Niedersachsen",
    "wof:name":"Herzels",
    "wof:placetype":"venue"
},
  "geometry": {"coordinates":[10.784084,52.423576],"type":"Point"}
}