{
  "type": "Feature",
  "properties": {
    "iso:country":"DE",
    "sg:address":"Geibelstr. 24",
    "sg:city":"Emden",
    "sg:phone":"+49 4921/21038",
    "sg:postcode":"26721",
    "sg:province":"Niedersachsen",
    "wof:name":"Comet",
    "wof:placetype":"venue"
},
  "geometry": {"coordinates":[7.213602066,53.3805427551],"type":"Point"}
}