{
  "type": "Feature",
  "properties": {
    "iso:country":"DE",
    "sg:address":"Rostocker Chaussee 28 a",
    "sg:city":"Stralsund",
    "sg:phone":"+49 3831/498310",
    "sg:postcode":"18437",
    "sg:province":"Mecklenburg-Vorpommern",
    "wof:name":"Pension Im Gr\u00fcnen Inh. Christa Gr\u00e4ff",
    "wof:placetype":"venue"
},
  "geometry": {"coordinates":[13.0573482513,54.3053741455],"type":"Point"}
}