{
  "type": "Feature",
  "properties": {
    "iso:country":"DE",
    "sg:address":"Ehlentruper Weg 2",
    "sg:city":"Bielefeld",
    "sg:phone":"+49 521/68458",
    "sg:postcode":"33604",
    "sg:province":"Nordrhein-Westfalen",
    "wof:name":"Ulrich Kaldewey Architekt",
    "wof:placetype":"venue"
},
  "geometry": {"coordinates":[8.5399,52.013927],"type":"Point"}
}