{
  "type": "Feature",
  "properties": {
    "iso:country":"DE",
    "sg:address":"In den Fuhren 1",
    "sg:city":"Bispingen",
    "sg:phone":"+49 5194/1271",
    "sg:postcode":"29646",
    "sg:province":"Niedersachsen",
    "wof:name":"J\u00f6rn Schmarje Innenarchitekt",
    "wof:placetype":"venue"
},
  "geometry": {"coordinates":[10.005004,53.087173],"type":"Point"}
}