{
  "type": "Feature",
  "properties": {
    "iso:country":"DE",
    "sg:address":"Seefeld 30",
    "sg:city":"Bad Oldesloe",
    "sg:phone":"+49 4531/6167",
    "sg:postcode":"23843",
    "sg:province":"Schleswig-Holstein",
    "wof:name":"G\u00fcnter Und Ruth Ullrich",
    "wof:placetype":"venue"
},
  "geometry": {"coordinates":[10.37077,53.848843],"type":"Point"}
}