{
  "type": "Feature",
  "properties": {
    "iso:country":"DE",
    "sg:address":"Im Altenschemel 50",
    "sg:city":"Neustadt",
    "sg:phone":"+49 6327/3332",
    "sg:postcode":"67435",
    "sg:province":"Rheinland-Pfalz",
    "wof:name":"W. Und E. Mahler",
    "wof:placetype":"venue"
},
  "geometry": {"coordinates":[8.221915,49.333408],"type":"Point"}
}