{
  "type": "Feature",
  "properties": {
    "iso:country":"DE",
    "sg:address":"Ahrstr. 65",
    "sg:city":"Blankenheim",
    "sg:phone":"+49 2449/1006",
    "sg:postcode":"53945",
    "sg:province":"Nordrhein-Westfalen",
    "wof:name":"Anneliese G\u00f6rgens",
    "wof:placetype":"venue"
},
  "geometry": {"coordinates":[6.6502580643,50.4366645813],"type":"Point"}
}