{
  "type": "Feature",
  "properties": {
    "iso:country":"DE",
    "sg:address":"Eisfelder Str. 7",
    "sg:city":"Schalkau",
    "sg:phone":"+49 36766/22241",
    "sg:postcode":"96528",
    "sg:province":"Th\u00fcringen",
    "wof:name":"Siegfried Grabner",
    "wof:placetype":"venue"
},
  "geometry": {"coordinates":[11.001332,50.399174],"type":"Point"}
}