{
  "type": "Feature",
  "properties": {
    "iso:country":"DE",
    "sg:address":"Bahnhofstr. 15",
    "sg:city":"Thannhausen",
    "sg:phone":"+49 8281/3424",
    "sg:postcode":"86470",
    "sg:province":"Bayern",
    "wof:name":"Renate A. Ziche",
    "wof:placetype":"venue"
},
  "geometry": {"coordinates":[10.4694156647,48.2835464478],"type":"Point"}
}