{
  "type": "Feature",
  "properties": {
    "iso:country":"DE",
    "sg:address":"Hirtenstr. 24",
    "sg:city":"M\u00fcnchen",
    "sg:phone":"+49 89/551640",
    "sg:postcode":"80335",
    "sg:province":"Bayern",
    "wof:name":"Regionalverkehr Oberbayern Gmbh",
    "wof:placetype":"venue"
},
  "geometry": {"coordinates":[11.5570716858,48.1426010132],"type":"Point"}
}