{
  "type": "Feature",
  "properties": {
    "iso:country":"DE",
    "sg:address":"Ostpreu\u00dfendamm 137-138",
    "sg:city":"Berlin",
    "sg:phone":"+49 30/779940",
    "sg:postcode":"12207",
    "sg:province":"Berlin",
    "wof:name":"Riccius & Seibt Regelungs- Technik Und Geb\u00e4ude-",
    "wof:placetype":"venue"
},
  "geometry": {"coordinates":[13.312989,52.422546],"type":"Point"}
}