{
  "type": "Feature",
  "properties": {
    "iso:country":"DE",
    "sg:address":"Kulmbacher Str. 13",
    "sg:city":"Marktleugast",
    "sg:phone":"+49 9255/1245",
    "sg:postcode":"95352",
    "sg:province":"Bayern",
    "wof:name":"Weberei Egid R\u00f6del Inh. Ambros R\u00f6del E. K.",
    "wof:placetype":"venue"
},
  "geometry": {"coordinates":[11.6338424683,50.1689071655],"type":"Point"}
}