{
  "type": "Feature",
  "properties": {
    "iso:country":"DE",
    "sg:address":"Konkordiastr. 1",
    "sg:city":"Hagen",
    "sg:phone":"+49 2331/13577",
    "sg:postcode":"58095",
    "sg:province":"Nordrhein-Westfalen",
    "wof:name":"Shop Shop",
    "wof:placetype":"venue"
},
  "geometry": {"coordinates":[7.467544,51.358814],"type":"Point"}
}