{
  "type": "Feature",
  "properties": {
    "iso:country":"DE",
    "sg:address":"Hochstr. 137",
    "sg:city":"Sonsbeck",
    "sg:phone":"+49 2838/2065",
    "sg:postcode":"47665",
    "sg:province":"Nordrhein-Westfalen",
    "wof:name":"Van Huet & Weber Gmbh",
    "wof:placetype":"venue"
},
  "geometry": {"coordinates":[6.3781599998,51.6032600403],"type":"Point"}
}