{
  "type": "Feature",
  "properties": {
    "iso:country":"DE",
    "sg:address":"Brauersgasse 3",
    "sg:city":"Z\u00fclpich",
    "sg:phone":"+49 2252/2740",
    "sg:postcode":"53909",
    "sg:province":"Nordrhein-Westfalen",
    "wof:name":"Heinz Spanier Elektro-k\u00e4lte-inst.",
    "wof:placetype":"venue"
},
  "geometry": {"coordinates":[6.64981,50.690201],"type":"Point"}
}