{
  "type": "Feature",
  "properties": {
    "iso:country":"DE",
    "sg:address":"M\u00fchlenstr. 20",
    "sg:city":"Donaueschingen",
    "sg:phone":"+49 771/832650",
    "sg:postcode":"78166",
    "sg:province":"Baden-W\u00fcrttemberg",
    "wof:name":"Neue Heimat Gemeinn. Siedlungs-",
    "wof:placetype":"venue"
},
  "geometry": {"coordinates":[8.4907894135,47.9550361633],"type":"Point"}
}