{
  "type": "Feature",
  "properties": {
    "iso:country":"DE",
    "sg:address":"Brahmsstr. 24a",
    "sg:city":"M\u00fcnchen",
    "sg:phone":"+49 89/41600721",
    "sg:postcode":"81677",
    "sg:province":"Bayern",
    "wof:name":"Deutscher Bundesverband F\u00fcr Steuer-, Finanz- Und",
    "wof:placetype":"venue"
},
  "geometry": {"coordinates":[11.613857,48.141296],"type":"Point"}
}