{
  "type": "Feature",
  "properties": {
    "iso:country":"DE",
    "sg:address":"Julius-Rolle-Str. 2",
    "sg:city":"Ostritz",
    "sg:phone":"+49 35823/86365",
    "sg:postcode":"02899",
    "sg:province":"Sachsen",
    "wof:name":"Brigitte Klose",
    "wof:placetype":"venue"
},
  "geometry": {"coordinates":[14.932469368,51.0143356323],"type":"Point"}
}