{
  "type": "Feature",
  "properties": {
    "iso:country":"DE",
    "sg:address":"Garstedter Weg 33",
    "sg:city":"Hamburg",
    "sg:postcode":"22453",
    "sg:province":"Hamburg",
    "wof:name":"Illustration Und Graphik Forster Gmbh",
    "wof:placetype":"venue"
},
  "geometry": {"coordinates":[9.956261,53.625645],"type":"Point"}
}