{
  "type": "Feature",
  "properties": {
    "iso:country":"DE",
    "sg:address":"Gr\u00fcner Weg 40",
    "sg:city":"Lippstadt",
    "sg:phone":"+49 2941/80207",
    "sg:postcode":"59556",
    "sg:province":"Nordrhein-Westfalen",
    "wof:name":"H.-d. K\u00f6tter Wirtschaftsberatungs- Und",
    "wof:placetype":"venue"
},
  "geometry": {"coordinates":[8.348110199,51.7124595642],"type":"Point"}
}