{
  "type": "Feature",
  "properties": {
    "iso:country":"DE",
    "sg:address":"L\u00fchlingsgasse 3",
    "sg:city":"Unkel",
    "sg:phone":"+49 2224/75965",
    "sg:postcode":"53572",
    "sg:province":"Rheinland-Pfalz",
    "wof:name":"E. Dolanay",
    "wof:placetype":"venue"
},
  "geometry": {"coordinates":[7.2156257629,50.5999984741],"type":"Point"}
}