{
  "type": "Feature",
  "properties": {
    "iso:country":"DE",
    "sg:address":"Paul-R\u00fcttchen-Str. 17",
    "sg:city":"Erkelenz",
    "sg:phone":"+49 4924/312022",
    "sg:postcode":"41812",
    "sg:province":"Nordrhein-Westfalen",
    "wof:name":"Ultra Gartenzentrumgmbh & Co. Kg",
    "wof:placetype":"venue"
},
  "geometry": {"coordinates":[6.3048110008,51.0755310059],"type":"Point"}
}