{
  "type": "Feature",
  "properties": {
    "iso:country":"DE",
    "sg:address":"Noeggerathstr. 4-8",
    "sg:city":"Bonn",
    "sg:phone":"+49 228/72570",
    "sg:postcode":"53111",
    "sg:province":"Nordrhein-Westfalen",
    "wof:name":"Altenheim Marienhaus",
    "wof:placetype":"venue"
},
  "geometry": {"coordinates":[7.094078,50.734531],"type":"Point"}
}