{
  "type": "Feature",
  "properties": {
    "iso:country":"DE",
    "sg:address":"Am Butterbusch 7",
    "sg:city":"Braunschweig",
    "sg:phone":"+49 531/611314",
    "sg:postcode":"38124",
    "sg:province":"Niedersachsen",
    "wof:name":"Hans-otto Kurz Architekt",
    "wof:placetype":"venue"
},
  "geometry": {"coordinates":[10.527283,52.210533],"type":"Point"}
}