{
  "type": "Feature",
  "properties": {
    "iso:country":"DE",
    "sg:address":"Ambergstr. 6",
    "sg:city":"Neuburg",
    "sg:phone":"+49 8431/7782",
    "sg:postcode":"86633",
    "sg:province":"Bayern",
    "wof:name":"Kuznia Gmbh",
    "wof:placetype":"venue"
},
  "geometry": {"coordinates":[11.1905460358,48.7229118347],"type":"Point"}
}