{
  "type": "Feature",
  "properties": {
    "iso:country":"DE",
    "sg:address":"Ostpreu\u00dfenstr. 4",
    "sg:city":"K\u00f6nigsberg",
    "sg:phone":"+49 9525/366",
    "sg:postcode":"97486",
    "sg:province":"Bayern",
    "wof:name":"Erwin Blank Rechtsanwalt",
    "wof:placetype":"venue"
},
  "geometry": {"coordinates":[10.5684013367,50.0757446289],"type":"Point"}
}