{
  "type": "Feature",
  "properties": {
    "iso:country":"DE",
    "sg:address":"Meisenweg 6",
    "sg:city":"Langen",
    "sg:phone":"+49 6103/71892",
    "sg:postcode":"63225",
    "sg:province":"Hessen",
    "wof:name":"Horst Minden Architekt",
    "wof:placetype":"venue"
},
  "geometry": {"coordinates":[8.642414,49.986809],"type":"Point"}
}