{
  "type": "Feature",
  "properties": {
    "iso:country":"DE",
    "sg:address":"Erbsegasse 9",
    "sg:city":"Gelnhausen",
    "sg:postcode":"63571",
    "sg:province":"Hessen",
    "wof:name":"Gst Schleifmittel-handels Gmbh",
    "wof:placetype":"venue"
},
  "geometry": {"coordinates":[9.139367,50.184471],"type":"Point"}
}