{
  "type": "Feature",
  "properties": {
    "iso:country":"DE",
    "sg:address":"Hauptstr. 60",
    "sg:city":"Herdorf",
    "sg:phone":"+49 2744/1644",
    "sg:postcode":"57562",
    "sg:province":"Rheinland-Pfalz",
    "wof:name":"Olympus Grill",
    "wof:placetype":"venue"
},
  "geometry": {"coordinates":[7.9519600868,50.7788734436],"type":"Point"}
}