{
  "type": "Feature",
  "properties": {
    "iso:country":"DE",
    "sg:address":"Zeppelinstr. 5",
    "sg:city":"Hagenbach",
    "sg:phone":"+49 7273/2530",
    "sg:postcode":"76767",
    "sg:province":"Rheinland-Pfalz",
    "wof:name":"Hermann Kollofrath",
    "wof:placetype":"venue"
},
  "geometry": {"coordinates":[8.2503156662,49.0236968994],"type":"Point"}
}