{
  "type": "Feature",
  "properties": {
    "iso:country":"DE",
    "sg:address":"Lindenstr. 8",
    "sg:city":"Emskirchen",
    "sg:phone":"+49 9104/548",
    "sg:postcode":"91448",
    "sg:province":"Bayern",
    "wof:name":"Manfred Ohst",
    "wof:placetype":"venue"
},
  "geometry": {"coordinates":[10.70033741,49.5469322205],"type":"Point"}
}