{
  "type": "Feature",
  "properties": {
    "iso:country":"DE",
    "sg:address":"Alter Heerweg 95",
    "sg:city":"Bonn",
    "sg:phone":"+49 228/647823",
    "sg:postcode":"53123",
    "sg:province":"Nordrhein-Westfalen",
    "wof:name":"Rich. Schwedhelm & S\u00f6hne Gmbh",
    "wof:placetype":"venue"
},
  "geometry": {"coordinates":[7.0480809212,50.7225952148],"type":"Point"}
}