{
  "type": "Feature",
  "properties": {
    "iso:country":"DE",
    "sg:address":"Hauptstr. 183",
    "sg:city":"Bellheim",
    "sg:phone":"+49 7272/760766",
    "sg:postcode":"76756",
    "sg:province":"Rheinland-Pfalz",
    "wof:name":"J\u00fcrgen M\u00fcnch",
    "wof:placetype":"venue"
},
  "geometry": {"coordinates":[8.2881994247,49.1905136108],"type":"Point"}
}