{
  "type": "Feature",
  "properties": {
    "iso:country":"DE",
    "sg:address":"Kienbergstr. 53",
    "sg:city":"Pfronten",
    "sg:phone":"+49 8363/314",
    "sg:postcode":"87459",
    "sg:province":"Bayern",
    "wof:name":"Pension Hermann Ego",
    "wof:placetype":"venue"
},
  "geometry": {"coordinates":[10.55210495,47.5701408386],"type":"Point"}
}