{
  "type": "Feature",
  "properties": {
    "iso:country":"DE",
    "sg:address":"Schlo\u00dfallee 63",
    "sg:city":"Bedburg",
    "sg:phone":"+49 2272/3383",
    "sg:postcode":"50181",
    "sg:province":"Nordrhein-Westfalen",
    "wof:name":"Herbert Holatzek",
    "wof:placetype":"venue"
},
  "geometry": {"coordinates":[6.5551099777,51.0005569458],"type":"Point"}
}