{
  "type": "Feature",
  "properties": {
    "iso:country":"DE",
    "sg:address":"Rangaustr. 3",
    "sg:city":"Oberasbach",
    "sg:phone":"+49 911/692891",
    "sg:postcode":"90522",
    "sg:province":"Bayern",
    "wof:name":"W. Frauenknecht",
    "wof:placetype":"venue"
},
  "geometry": {"coordinates":[10.9736118317,49.434677124],"type":"Point"}
}