{
  "type": "Feature",
  "properties": {
    "iso:country":"DE",
    "sg:address":"Unter Taschenmacher 18",
    "sg:city":"K\u00f6ln",
    "sg:phone":"+49 221/2580724",
    "sg:postcode":"50667",
    "sg:province":"Nordrhein-Westfalen",
    "wof:name":"Hotel Am Museum",
    "wof:placetype":"venue"
},
  "geometry": {"coordinates":[6.9597191811,50.9396438599],"type":"Point"}
}