{
  "type": "Feature",
  "properties": {
    "iso:country":"DE",
    "sg:address":"Waitzinger Wiese 10",
    "sg:city":"Landsberg",
    "sg:phone":"+49 8191/5369",
    "sg:postcode":"86899",
    "sg:province":"Bayern",
    "wof:name":"Walter D\u00fcrrstein",
    "wof:placetype":"venue"
},
  "geometry": {"coordinates":[10.871178627,48.0564651489],"type":"Point"}
}