{
  "type": "Feature",
  "properties": {
    "iso:country":"DE",
    "sg:address":"L\u00f6bauer Str. 60",
    "sg:city":"Bautzen",
    "sg:postcode":"02625",
    "sg:province":"Sachsen",
    "wof:name":"Edeka C & C",
    "wof:placetype":"venue"
},
  "geometry": {"coordinates":[14.4526472092,51.1783981323],"type":"Point"}
}