{
  "type": "Feature",
  "properties": {
    "iso:country":"DE",
    "sg:address":"Am Neuen Markt 26",
    "sg:city":"Rotenburg",
    "sg:phone":"+49 4261/3154",
    "sg:postcode":"27356",
    "sg:province":"Niedersachsen",
    "wof:name":"Elke Zukunft-damenmoden-gmbh",
    "wof:placetype":"venue"
},
  "geometry": {"coordinates":[9.4095067978,53.1114730835],"type":"Point"}
}