{
  "type": "Feature",
  "properties": {
    "iso:country":"DE",
    "sg:address":"Ru\u00dfkamp 4",
    "sg:city":"Minden",
    "sg:phone":"+49 571/31218",
    "sg:postcode":"32423",
    "sg:province":"Nordrhein-Westfalen",
    "wof:name":"Eckhard Stegmann",
    "wof:placetype":"venue"
},
  "geometry": {"coordinates":[8.958407,52.3153],"type":"Point"}
}