{
  "type": "Feature",
  "properties": {
    "iso:country":"DE",
    "sg:address":"Willibaldstr. 8a",
    "sg:city":"M\u00fcnchen",
    "sg:phone":"+49 89/5808782",
    "sg:postcode":"80687",
    "sg:province":"Bayern",
    "wof:name":"Stephan Lintner Architekt",
    "wof:placetype":"venue"
},
  "geometry": {"coordinates":[11.489174,48.143459],"type":"Point"}
}