{
  "type": "Feature",
  "properties": {
    "iso:country":"DE",
    "sg:address":"Gewerbestr 6",
    "sg:city":"Otterberg",
    "sg:phone":"+49 6301/710856",
    "sg:postcode":"67697",
    "sg:province":"Rheinland-Pfalz",
    "wof:name":"Otterberger Betonwerk Gmbh",
    "wof:placetype":"venue"
},
  "geometry": {"coordinates":[7.766506,49.494999],"type":"Point"}
}