{
  "type": "Feature",
  "properties": {
    "iso:country":"DE",
    "sg:address":"Kastanienallee 29/30",
    "sg:city":"Berlin",
    "sg:phone":"+49 30/42105180",
    "sg:postcode":"10435",
    "sg:province":"Berlin",
    "wof:name":"Niggas Fr\u00e4sen Gmbh",
    "wof:placetype":"venue"
},
  "geometry": {"coordinates":[13.407836,52.537033],"type":"Point"}
}