{
  "type": "Feature",
  "properties": {
    "iso:country":"DE",
    "sg:address":"Hindenburgstr. 18",
    "sg:city":"H\u00f6fen",
    "sg:phone":"+49 7081/953083",
    "sg:postcode":"75339",
    "sg:province":"Baden-W\u00fcrttemberg",
    "wof:name":"Volker Gengenbach",
    "wof:placetype":"venue"
},
  "geometry": {"coordinates":[8.5836133957,48.8035049438],"type":"Point"}
}