{
  "type": "Feature",
  "properties": {
    "iso:country":"DE",
    "sg:address":"Am Walde 5",
    "sg:city":"Lahr",
    "sg:phone":"+49 7821/76348",
    "sg:postcode":"77933",
    "sg:province":"Baden-W\u00fcrttemberg",
    "wof:name":"Dr. Albert Hexges",
    "wof:placetype":"venue"
},
  "geometry": {"coordinates":[7.9034938812,48.341506958],"type":"Point"}
}