{
  "type": "Feature",
  "properties": {
    "iso:country":"DE",
    "sg:address":"Auf dem H\u00f6chsten 18",
    "sg:city":"Wiehl",
    "sg:phone":"+49 2262/701373",
    "sg:postcode":"51674",
    "sg:province":"Nordrhein-Westfalen",
    "wof:name":"B. Heiden-debus",
    "wof:placetype":"venue"
},
  "geometry": {"coordinates":[7.5124540329,50.9656562805],"type":"Point"}
}