{
  "type": "Feature",
  "properties": {
    "iso:country":"DE",
    "sg:address":"Talstr. 22",
    "sg:city":"Ettlingen",
    "sg:phone":"+49 7243/29129",
    "sg:postcode":"76275",
    "sg:province":"Baden-W\u00fcrttemberg",
    "wof:name":"Kath. Pfarramt St. Anton",
    "wof:placetype":"venue"
},
  "geometry": {"coordinates":[8.4349527359,48.9142532349],"type":"Point"}
}