{
  "type": "Feature",
  "properties": {
    "iso:country":"DE",
    "sg:address":"Hauptstr. 178",
    "sg:city":"Krefeld",
    "sg:phone":"+49 2151/544161",
    "sg:postcode":"47809",
    "sg:province":"Nordrhein-Westfalen",
    "wof:name":"Oppumer Krug",
    "wof:placetype":"venue"
},
  "geometry": {"coordinates":[6.627767086,51.3183670044],"type":"Point"}
}