{
  "type": "Feature",
  "properties": {
    "iso:country":"DE",
    "sg:address":"Langbaurghstr. 19",
    "sg:city":"Troisdorf",
    "sg:phone":"+49 2241/951970",
    "sg:postcode":"53842",
    "sg:province":"Nordrhein-Westfalen",
    "wof:name":"Ssg Sicherheits Service Gmbh",
    "wof:placetype":"venue"
},
  "geometry": {"coordinates":[7.1095452309,50.8221168518],"type":"Point"}
}