{
  "type": "Feature",
  "properties": {
    "iso:country":"DE",
    "sg:address":"Mail\u00e4nder Str. 7",
    "sg:city":"Frankfurt",
    "sg:phone":"+49 69/682279",
    "sg:postcode":"60598",
    "sg:province":"Hessen",
    "wof:name":"Dario G. C. Querini International Co-editions",
    "wof:placetype":"venue"
},
  "geometry": {"coordinates":[8.6900949478,50.0915641785],"type":"Point"}
}