{
  "type": "Feature",
  "properties": {
    "iso:country":"DE",
    "sg:address":"Bechthal",
    "sg:city":"Raitenbuch",
    "sg:phone":"+49 9147/223",
    "sg:postcode":"91790",
    "sg:province":"Bayern",
    "wof:name":"Georg Schreiner",
    "wof:placetype":"venue"
},
  "geometry": {"coordinates":[11.1736879349,49.0231208801],"type":"Point"}
}