{
  "type": "Feature",
  "properties": {
    "iso:country":"DE",
    "sg:address":"Hangstr. 24",
    "sg:city":"Obersulm",
    "sg:phone":"+49 7130/8814",
    "sg:postcode":"74182",
    "sg:province":"Baden-W\u00fcrttemberg",
    "wof:name":"R\u00fcdiger Und Simone Wagner",
    "wof:placetype":"venue"
},
  "geometry": {"coordinates":[9.3696975708,49.1320381165],"type":"Point"}
}