{
  "type": "Feature",
  "properties": {
    "iso:country":"DE",
    "sg:address":"K\u00f6nigsberger Str. 8",
    "sg:city":"Northeim",
    "sg:phone":"+49 5551/7030",
    "sg:postcode":"37154",
    "sg:province":"Niedersachsen",
    "wof:name":"Thimm Display Management Gmbh",
    "wof:placetype":"venue"
},
  "geometry": {"coordinates":[9.9874601364,51.6978492737],"type":"Point"}
}