{
  "type": "Feature",
  "properties": {
    "iso:country":"DE",
    "sg:address":"Chausseestr. 34",
    "sg:city":"Klostermansfeld",
    "sg:phone":"+49 34772/25367",
    "sg:postcode":"06308",
    "sg:province":"Sachsen-Anhalt",
    "wof:name":"D. Glorius",
    "wof:placetype":"venue"
},
  "geometry": {"coordinates":[11.4942054749,51.5844688416],"type":"Point"}
}