{
  "type": "Feature",
  "properties": {
    "iso:country":"DE",
    "sg:address":"Alte Dorfstr. 19",
    "sg:city":"Zwingenberg",
    "sg:phone":"+49 6263/256",
    "sg:postcode":"69439",
    "sg:province":"Baden-W\u00fcrttemberg",
    "wof:name":"Hedwig Greis",
    "wof:placetype":"venue"
},
  "geometry": {"coordinates":[9.0358018875,49.4210243225],"type":"Point"}
}