{
  "type": "Feature",
  "properties": {
    "iso:country":"DE",
    "sg:address":"Ferdinand-Freiligrath-Str. 14",
    "sg:city":"Weimar",
    "sg:phone":"+49 3643/850680",
    "sg:postcode":"99423",
    "sg:province":"Th\u00fcringen",
    "wof:name":"H\u00f6rger\u00e4te Isma Gmbh & Co. Kg",
    "wof:placetype":"venue"
},
  "geometry": {"coordinates":[11.3297472,50.9836997986],"type":"Point"}
}