{
  "type": "Feature",
  "properties": {
    "iso:country":"DE",
    "sg:address":"Bredeneyerstr. 94",
    "sg:city":"Essen",
    "sg:postcode":"45133",
    "sg:province":"Nordrhein-Westfalen",
    "wof:name":"Www.frauenmitbart.de",
    "wof:placetype":"venue"
},
  "geometry": {"coordinates":[6.989327,51.402508],"type":"Point"}
}