{
  "type": "Feature",
  "properties": {
    "iso:country":"DE",
    "sg:address":"Egenstr. 49",
    "sg:city":"Breckerfeld",
    "sg:phone":"+49 2338/785",
    "sg:postcode":"58339",
    "sg:province":"Nordrhein-Westfalen",
    "wof:name":"Kardonas Ikonen Gmbh",
    "wof:placetype":"venue"
},
  "geometry": {"coordinates":[7.4651350975,51.2673110962],"type":"Point"}
}