{
  "type": "Feature",
  "properties": {
    "iso:country":"DE",
    "sg:address":"Ludwigsburg 4",
    "sg:city":"Rodewisch",
    "sg:phone":"+49 3744/34284",
    "sg:postcode":"08228",
    "sg:province":"Sachsen",
    "wof:name":"Ludwigsburg",
    "wof:placetype":"venue"
},
  "geometry": {"coordinates":[12.4159297943,50.539150238],"type":"Point"}
}