{
  "type": "Feature",
  "properties": {
    "iso:country":"DE",
    "sg:address":"Gebr\u00fcder-Hofmann-Ring 3",
    "sg:city":"Eibelstadt",
    "sg:phone":"+49 9303/2126",
    "sg:postcode":"97246",
    "sg:province":"Bayern",
    "wof:name":"Fitness-studio Spartakus Schenk Und Schr\u00f6der",
    "wof:placetype":"venue"
},
  "geometry": {"coordinates":[10.0014276505,49.7223739624],"type":"Point"}
}