{
  "type": "Feature",
  "properties": {
    "iso:country":"DE",
    "sg:address":"Goethestr. 21",
    "sg:city":"M\u00fcnchen",
    "sg:postcode":"80336",
    "sg:province":"Bayern",
    "wof:name":"Redaktion Katastrophenschutz Aktuell",
    "wof:placetype":"venue"
},
  "geometry": {"coordinates":[11.55879879,48.1360626221],"type":"Point"}
}