{
  "type": "Feature",
  "properties": {
    "iso:country":"DE",
    "sg:address":"Krebsstr. 24",
    "sg:city":"Aachen",
    "sg:postcode":"52080",
    "sg:province":"Nordrhein-Westfalen",
    "wof:name":"Acron-tufting Produktions- Gmbh",
    "wof:placetype":"venue"
},
  "geometry": {"coordinates":[6.147543,50.773922],"type":"Point"}
}