{
  "type": "Feature",
  "properties": {
    "iso:country":"DE",
    "sg:address":"Sommerstr. 27",
    "sg:city":"Erndtebr\u00fcck",
    "sg:phone":"+49 2753/60620",
    "sg:postcode":"57339",
    "sg:province":"Nordrhein-Westfalen",
    "wof:name":"Sparkasse Wittgenstein",
    "wof:placetype":"venue"
},
  "geometry": {"coordinates":[8.272074,51.01556],"type":"Point"}
}