{
  "type": "Feature",
  "properties": {
    "iso:country":"DE",
    "sg:address":"Dransfelder Stra\u00dfe 3",
    "sg:city":"G\u00f6ttingen",
    "sg:phone":"+49 551/90010",
    "sg:postcode":"37079",
    "sg:province":"Niedersachsen",
    "wof:name":"Hotel Freizeit In",
    "wof:placetype":"venue"
},
  "geometry": {"coordinates":[9.871894,51.523003],"type":"Point"}
}