{
  "type": "Feature",
  "properties": {
    "iso:country":"DE",
    "sg:address":"R\u00f6hre 17",
    "sg:city":"Sundern",
    "sg:phone":"+49 2933/2417",
    "sg:postcode":"59846",
    "sg:province":"Nordrhein-Westfalen",
    "wof:name":"Theo Rammrath",
    "wof:placetype":"venue"
},
  "geometry": {"coordinates":[8.0091571808,51.3167076111],"type":"Point"}
}