{
  "type": "Feature",
  "properties": {
    "iso:country":"DE",
    "sg:address":"Holder\u00e4ckerstr. 4",
    "sg:city":"Gerlingen",
    "sg:phone":"+49 7156/25785",
    "sg:postcode":"70839",
    "sg:province":"Baden-W\u00fcrttemberg",
    "wof:name":"L\u00f6ffler Verwaltungsgesellschaft Mbh",
    "wof:placetype":"venue"
},
  "geometry": {"coordinates":[9.055348,48.801029],"type":"Point"}
}