{
  "type": "Feature",
  "properties": {
    "iso:country":"DE",
    "sg:address":"Klemmertstr. 27",
    "sg:city":"Holzgerlingen",
    "sg:phone":"+49 7031/605631",
    "sg:postcode":"71088",
    "sg:province":"Baden-W\u00fcrttemberg",
    "wof:name":"Friedrich Dannecker",
    "wof:placetype":"venue"
},
  "geometry": {"coordinates":[9.014257,48.639648],"type":"Point"}
}