{
  "type": "Feature",
  "properties": {
    "iso:country":"DE",
    "sg:address":"Mohnweg 3",
    "sg:city":"Oberasbach",
    "sg:phone":"+49 911/693078",
    "sg:postcode":"90522",
    "sg:province":"Bayern",
    "wof:name":"J. Schmidt",
    "wof:placetype":"venue"
},
  "geometry": {"coordinates":[10.9883832932,49.4138870239],"type":"Point"}
}