{
  "type": "Feature",
  "properties": {
    "iso:country":"DE",
    "sg:address":"Dorfstr. 40",
    "sg:city":"Weiskirchen",
    "sg:phone":"+49 6874/869",
    "sg:postcode":"66709",
    "sg:province":"Saarland",
    "wof:name":"Peter Barth",
    "wof:placetype":"venue"
},
  "geometry": {"coordinates":[6.816122,49.522987],"type":"Point"}
}