{
  "type": "Feature",
  "properties": {
    "iso:country":"DE",
    "sg:address":"Hofer Str. 22",
    "sg:city":"Oelsnitz",
    "sg:phone":"+49 37421/28579",
    "sg:postcode":"08606",
    "sg:province":"Sachsen",
    "wof:name":"Wohnbedarf Handels- Und Produktions Gmbh",
    "wof:placetype":"venue"
},
  "geometry": {"coordinates":[12.1569929123,50.4059562683],"type":"Point"}
}