{
  "type": "Feature",
  "properties": {
    "iso:country":"DE",
    "sg:address":"Niedersorpe 32",
    "sg:city":"Schmallenberg",
    "sg:phone":"+49 2975/1235",
    "sg:postcode":"57392",
    "sg:province":"Nordrhein-Westfalen",
    "wof:name":"Josef H\u00fctten",
    "wof:placetype":"venue"
},
  "geometry": {"coordinates":[8.365966,51.169804],"type":"Point"}
}