{
  "type": "Feature",
  "properties": {
    "iso:country":"DE",
    "sg:address":"Bruchstr. 1",
    "sg:city":"Bad Harzburg",
    "sg:phone":"+49 5322/8816",
    "sg:postcode":"38667",
    "sg:province":"Niedersachsen",
    "wof:name":"W. Fricke",
    "wof:placetype":"venue"
},
  "geometry": {"coordinates":[10.529258728,51.9030990601],"type":"Point"}
}