{
  "type": "Feature",
  "properties": {
    "iso:country":"DE",
    "sg:address":"Br\u00e4uhausstr. 2",
    "sg:city":"Haigerloch",
    "sg:phone":"+49 7474/2240",
    "sg:postcode":"72401",
    "sg:province":"Baden-W\u00fcrttemberg",
    "wof:name":"Holz Pur G.f. Schwarz",
    "wof:placetype":"venue"
},
  "geometry": {"coordinates":[8.775642,48.343163],"type":"Point"}
}