{
  "type": "Feature",
  "properties": {
    "iso:country":"DE",
    "sg:address":"N\u00fcrnberger Str. 11",
    "sg:city":"N\u00f6rdlingen",
    "sg:phone":"+49 9081/96089",
    "sg:postcode":"86720",
    "sg:province":"Bayern",
    "wof:name":"Top-bau Center",
    "wof:placetype":"venue"
},
  "geometry": {"coordinates":[10.4954805374,48.8571166992],"type":"Point"}
}