{
  "type": "Feature",
  "properties": {
    "iso:country":"DE",
    "sg:address":"Langenmantelstr. 4",
    "sg:city":"Augsburg",
    "sg:phone":"+49 821/152563",
    "sg:postcode":"86153",
    "sg:province":"Bayern",
    "wof:name":"Famex Handels Gmbh",
    "wof:placetype":"venue"
},
  "geometry": {"coordinates":[10.883852005,48.3746986389],"type":"Point"}
}