{
  "type": "Feature",
  "properties": {
    "iso:country":"DE",
    "sg:address":"An der Alster 1",
    "sg:city":"Hamburg",
    "sg:phone":"+49 40/2272250",
    "sg:postcode":"20099",
    "sg:province":"Hamburg",
    "wof:name":"R\u00fcdiger Ritschel Verlagsservice",
    "wof:placetype":"venue"
},
  "geometry": {"coordinates":[10.014345,53.561783],"type":"Point"}
}