{
  "type": "Feature",
  "properties": {
    "iso:country":"DE",
    "sg:address":"M\u00fchlendamm 39",
    "sg:city":"Haren",
    "sg:phone":"+49 5932/2403",
    "sg:postcode":"49733",
    "sg:province":"Niedersachsen",
    "wof:name":"Bernhard Lohmann Kapit\u00e4n Ms Stephan",
    "wof:placetype":"venue"
},
  "geometry": {"coordinates":[7.246388,52.79356],"type":"Point"}
}