{
  "type": "Feature",
  "properties": {
    "iso:country":"DE",
    "sg:address":"Zifling-Bierl 43",
    "sg:city":"Willmering",
    "sg:phone":"+49 9971/7029",
    "sg:postcode":"93497",
    "sg:province":"Bayern",
    "wof:name":"Bernhard D\u00fcrichen Architekt",
    "wof:placetype":"venue"
},
  "geometry": {"coordinates":[12.67576,49.242188],"type":"Point"}
}