{
  "type": "Feature",
  "properties": {
    "iso:country":"DE",
    "sg:address":"M\u00fchlweg 5",
    "sg:city":"Birstein",
    "sg:phone":"+49 6054/2091",
    "sg:postcode":"63633",
    "sg:province":"Hessen",
    "wof:name":"G\u00f6tz & Sohn Kg",
    "wof:placetype":"venue"
},
  "geometry": {"coordinates":[9.304644,50.352856],"type":"Point"}
}