{
  "type": "Feature",
  "properties": {
    "iso:country":"DE",
    "sg:address":"An der Parthenaue 4",
    "sg:city":"Borsdorf",
    "sg:phone":"+49 34291/88813",
    "sg:postcode":"04451",
    "sg:province":"Sachsen",
    "wof:name":"Terrawert Bautr\u00e4ger Gmbh",
    "wof:placetype":"venue"
},
  "geometry": {"coordinates":[12.53395,51.35059],"type":"Point"}
}