{
  "type": "Feature",
  "properties": {
    "iso:country":"DE",
    "sg:address":"Rh\u00f6nstr. 20",
    "sg:city":"Eichenzell",
    "sg:phone":"+49 6656/377",
    "sg:postcode":"36124",
    "sg:province":"Hessen",
    "wof:name":"Rehberg",
    "wof:placetype":"venue"
},
  "geometry": {"coordinates":[9.7557649612,50.4773979187],"type":"Point"}
}