{
  "type": "Feature",
  "properties": {
    "iso:country":"DE",
    "sg:address":"Hohler Graben 14",
    "sg:city":"Hann. M\u00fcnden",
    "sg:phone":"+49 5546/91001",
    "sg:postcode":"34346",
    "sg:province":"Niedersachsen",
    "wof:name":"Udo Meyer",
    "wof:placetype":"venue"
},
  "geometry": {"coordinates":[9.7013158798,51.4552192688],"type":"Point"}
}