{
  "type": "Feature",
  "properties": {
    "iso:country":"DE",
    "sg:address":"Gottfried-Keller-Str. 32",
    "sg:city":"Dresden",
    "sg:phone":"+49 351/4215462",
    "sg:postcode":"01157",
    "sg:province":"Sachsen",
    "wof:name":"Volkhard Scholz",
    "wof:placetype":"venue"
},
  "geometry": {"coordinates":[13.677315,51.059155],"type":"Point"}
}