{
  "type": "Feature",
  "properties": {
    "iso:country":"DE",
    "sg:address":"Jenaer Str. 52",
    "sg:city":"Weimar",
    "sg:phone":"+49 3643/24320",
    "sg:postcode":"99425",
    "sg:province":"Th\u00fcringen",
    "wof:name":"Kroll Gmbh",
    "wof:placetype":"venue"
},
  "geometry": {"coordinates":[11.343314,50.979362],"type":"Point"}
}