{
  "type": "Feature",
  "properties": {
    "iso:country":"DE",
    "sg:address":"Feldstr. 3",
    "sg:city":"Bramsche",
    "sg:phone":"+49 5461/3469",
    "sg:postcode":"49565",
    "sg:province":"Niedersachsen",
    "wof:name":"W. Legler",
    "wof:placetype":"venue"
},
  "geometry": {"coordinates":[7.9866871834,52.40102005],"type":"Point"}
}