{
  "type": "Feature",
  "properties": {
    "iso:country":"DE",
    "sg:address":"Wilhelm-K\u00fclz-Stra\u00dfe 16",
    "sg:city":"Cottbus",
    "sg:phone":"+49 4935/533582",
    "sg:postcode":"03046",
    "sg:province":"Brandenburg",
    "wof:name":"Deutsche Chopin-gesellschaft E.v.",
    "wof:placetype":"venue"
},
  "geometry": {"coordinates":[14.325155,51.753906],"type":"Point"}
}