{
  "type": "Feature",
  "properties": {
    "iso:country":"DE",
    "sg:address":"Niedersachsenstr. 84 E",
    "sg:city":"Winsen",
    "sg:phone":"+49 4171/652145",
    "sg:postcode":"21423",
    "sg:province":"Niedersachsen",
    "wof:name":"Dipl.-ing. Siegmund Richert Industrieapparate Ingenieur-",
    "wof:placetype":"venue"
},
  "geometry": {"coordinates":[10.207904,53.364349],"type":"Point"}
}