{
  "type": "Feature",
  "properties": {
    "iso:country":"DE",
    "sg:address":"Gildestr. 33",
    "sg:city":"Herzebrock-Clarholz",
    "sg:phone":"+49 5245/3830",
    "sg:postcode":"33442",
    "sg:province":"Nordrhein-Westfalen",
    "wof:name":"Bernhard Pumpe Taxi Gmbh",
    "wof:placetype":"venue"
},
  "geometry": {"coordinates":[8.2428789139,51.8810997009],"type":"Point"}
}