{
  "type": "Feature",
  "properties": {
    "iso:country":"DE",
    "sg:address":"Landwehrdamm 33",
    "sg:city":"Bremerv\u00f6rde",
    "sg:phone":"+49 4761/3500",
    "sg:postcode":"27432",
    "sg:province":"Niedersachsen",
    "wof:name":"Johann H. Burfeindt",
    "wof:placetype":"venue"
},
  "geometry": {"coordinates":[9.186811,53.469307],"type":"Point"}
}