{
  "type": "Feature",
  "properties": {
    "iso:country":"DE",
    "sg:address":"Albertsthaler Str. 17",
    "sg:city":"Glauchau",
    "sg:phone":"+49 3763/3096",
    "sg:postcode":"08371",
    "sg:province":"Sachsen",
    "wof:name":"Gr\u00fcner Baum",
    "wof:placetype":"venue"
},
  "geometry": {"coordinates":[12.5357046127,50.810295105],"type":"Point"}
}