{
  "type": "Feature",
  "properties": {
    "iso:country":"DE",
    "sg:address":"Im Bergerfeld 3",
    "sg:city":"Neunkirchen-Seelscheid",
    "sg:phone":"+49 2247/69080",
    "sg:postcode":"53819",
    "sg:province":"Nordrhein-Westfalen",
    "wof:name":"Reinhard Heinrich",
    "wof:placetype":"venue"
},
  "geometry": {"coordinates":[7.32279,50.875393],"type":"Point"}
}