{
  "type": "Feature",
  "properties": {
    "iso:country":"DE",
    "sg:address":"Schildergasse 86-88",
    "sg:city":"K\u00f6ln",
    "sg:phone":"+49 221/213917",
    "sg:postcode":"50667",
    "sg:province":"Nordrhein-Westfalen",
    "wof:name":"Madelli Leder Exquisit Gmbh & Co. Kg",
    "wof:placetype":"venue"
},
  "geometry": {"coordinates":[6.951451,50.936596],"type":"Point"}
}