{
  "type": "Feature",
  "properties": {
    "iso:country":"DE",
    "sg:address":"Pichelsdorfer Str. 101",
    "sg:city":"Berlin",
    "sg:phone":"+49 30/3315892",
    "sg:postcode":"13595",
    "sg:province":"Berlin",
    "wof:name":"Dr. Med. Christine Neubart",
    "wof:placetype":"venue"
},
  "geometry": {"coordinates":[13.1973266602,52.5240478516],"type":"Point"}
}