{
  "type": "Feature",
  "properties": {
    "iso:country":"DE",
    "sg:address":"Im Rosenhagen 9",
    "sg:city":"Bad Salzuflen",
    "sg:phone":"+49 5222/70229",
    "sg:postcode":"32107",
    "sg:province":"Nordrhein-Westfalen",
    "wof:name":"Cord Lukowski Dachdeckerei Gmbh",
    "wof:placetype":"venue"
},
  "geometry": {"coordinates":[8.729895,52.064533],"type":"Point"}
}