{
  "type": "Feature",
  "properties": {
    "iso:country":"DE",
    "sg:address":"Bahrensdorfer Str.",
    "sg:city":"Beeskow",
    "sg:phone":"+49 33672/215",
    "sg:postcode":"15848",
    "sg:province":"Brandenburg",
    "wof:name":"S. Liebscher",
    "wof:placetype":"venue"
},
  "geometry": {"coordinates":[14.257084,52.165577],"type":"Point"}
}