{
  "type": "Feature",
  "properties": {
    "iso:country":"DE",
    "sg:address":"Andreaestr. 25",
    "sg:city":"Frankfurt",
    "sg:phone":"+49 69/453438",
    "sg:postcode":"60385",
    "sg:province":"Hessen",
    "wof:name":"Helmut Tietjen",
    "wof:placetype":"venue"
},
  "geometry": {"coordinates":[8.711438,50.127235],"type":"Point"}
}