{
  "type": "Feature",
  "properties": {
    "iso:country":"DE",
    "sg:address":"Saalstr. 7",
    "sg:city":"Saalfeld",
    "sg:phone":"+49 3671/511905",
    "sg:postcode":"07318",
    "sg:province":"Th\u00fcringen",
    "wof:name":"Relax",
    "wof:placetype":"venue"
},
  "geometry": {"coordinates":[11.361457,50.64864],"type":"Point"}
}