{
  "type": "Feature",
  "properties": {
    "iso:country":"DE",
    "sg:address":"Kuhlertstr. 60",
    "sg:city":"Heinsberg",
    "sg:phone":"+49 2452/939007",
    "sg:postcode":"52525",
    "sg:province":"Nordrhein-Westfalen",
    "wof:name":"M. Kraechter",
    "wof:placetype":"venue"
},
  "geometry": {"coordinates":[6.1132969856,51.0538635254],"type":"Point"}
}