{
  "type": "Feature",
  "properties": {
    "iso:country":"DE",
    "sg:city":"H\u00f6slwang",
    "sg:phone":"+49 8055/8292",
    "sg:postcode":"83129",
    "sg:province":"Bayern",
    "wof:name":"P. Mayer",
    "wof:placetype":"venue"
},
  "geometry": {"coordinates":[12.328883,47.955524],"type":"Point"}
}