{
  "type": "Feature",
  "properties": {
    "iso:country":"DE",
    "sg:address":"Goethestr. 21",
    "sg:city":"Erfurt",
    "sg:phone":"+49 361/340660",
    "sg:postcode":"99096",
    "sg:province":"Th\u00fcringen",
    "wof:name":"Ilona Ruschel Steuerberaterin",
    "wof:placetype":"venue"
},
  "geometry": {"coordinates":[11.0227136612,50.9644546509],"type":"Point"}
}