{
  "type": "Feature",
  "properties": {
    "iso:country":"DE",
    "sg:address":"Troppauer Str. 5",
    "sg:city":"Kornwestheim",
    "sg:phone":"+49 7154/23046",
    "sg:postcode":"70806",
    "sg:province":"Baden-W\u00fcrttemberg",
    "wof:name":"G. C. Etzel",
    "wof:placetype":"venue"
},
  "geometry": {"coordinates":[9.1930046082,48.8552856445],"type":"Point"}
}