{
  "type": "Feature",
  "properties": {
    "iso:country":"DE",
    "sg:address":"Ziegeleistr. 52",
    "sg:city":"Tengen",
    "sg:phone":"+49 7736/97030",
    "sg:postcode":"78250",
    "sg:province":"Baden-W\u00fcrttemberg",
    "wof:name":"Zimmermann",
    "wof:placetype":"venue"
},
  "geometry": {"coordinates":[8.6545505524,47.8185081482],"type":"Point"}
}