{
  "type": "Feature",
  "properties": {
    "iso:country":"DE",
    "sg:address":"Roggendorfer Str. 2",
    "sg:city":"Mechernich",
    "sg:phone":"+49 2443/48581",
    "sg:postcode":"53894",
    "sg:province":"Nordrhein-Westfalen",
    "wof:name":"Frings Transporte Gmbh",
    "wof:placetype":"venue"
},
  "geometry": {"coordinates":[6.6165118217,50.5872650146],"type":"Point"}
}