{
  "type": "Feature",
  "properties": {
    "iso:country":"DE",
    "sg:address":"Spittastr. 4",
    "sg:city":"Stuttgart",
    "sg:phone":"+49 711/639525",
    "sg:postcode":"70193",
    "sg:province":"Baden-W\u00fcrttemberg",
    "wof:name":"H\u00fcseyin Demir",
    "wof:placetype":"venue"
},
  "geometry": {"coordinates":[9.1514444351,48.7752723694],"type":"Point"}
}