{
  "type": "Feature",
  "properties": {
    "iso:country":"DE",
    "sg:address":"Lindenweg 1",
    "sg:city":"Patersdorf",
    "sg:phone":"+49 9923/504",
    "sg:postcode":"94265",
    "sg:province":"Bayern",
    "wof:name":"Georg Apfl Gmbh",
    "wof:placetype":"venue"
},
  "geometry": {"coordinates":[12.979428,49.018307],"type":"Point"}
}