{
  "type": "Feature",
  "properties": {
    "iso:country":"DE",
    "sg:address":"Grabenstr. 13",
    "sg:city":"G\u00f6ppingen",
    "sg:phone":"+49 7161/73642",
    "sg:postcode":"73033",
    "sg:province":"Baden-W\u00fcrttemberg",
    "wof:name":"Cafe Luipold Cafe Und Konditorei",
    "wof:placetype":"venue"
},
  "geometry": {"coordinates":[9.6537008286,48.7020950317],"type":"Point"}
}