{
  "type": "Feature",
  "properties": {
    "iso:country":"DE",
    "sg:address":"Brunnerstr. 11",
    "sg:city":"Haar",
    "sg:phone":"+49 89/4603035",
    "sg:postcode":"85540",
    "sg:province":"Bayern",
    "wof:name":"Peter M\u00fcller Ingenieur",
    "wof:placetype":"venue"
},
  "geometry": {"coordinates":[11.7348146439,48.1075782776],"type":"Point"}
}