{
  "type": "Feature",
  "properties": {
    "iso:country":"DE",
    "sg:address":"Werdener Str. 166",
    "sg:city":"Velbert",
    "sg:phone":"+49 2051/81318",
    "sg:postcode":"42549",
    "sg:province":"Nordrhein-Westfalen",
    "wof:name":"Lothar Engel Gmbh",
    "wof:placetype":"venue"
},
  "geometry": {"coordinates":[7.021312,51.354633],"type":"Point"}
}