{
  "type": "Feature",
  "properties": {
    "iso:country":"DE",
    "sg:address":"Friesenweg 47",
    "sg:city":"Jever",
    "sg:phone":"+49 4461/2933",
    "sg:postcode":"26441",
    "sg:province":"Niedersachsen",
    "wof:name":"Clemens Husmann",
    "wof:placetype":"venue"
},
  "geometry": {"coordinates":[7.9080471992,53.5648918152],"type":"Point"}
}