{
  "type": "Feature",
  "properties": {
    "iso:country":"DE",
    "sg:address":"G\u00f6rlitzerstr. 2",
    "sg:city":"Neuss",
    "sg:postcode":"41460",
    "sg:province":"Nordrhein-Westfalen",
    "wof:name":"Dimi\u00b4s Impressions",
    "wof:placetype":"venue"
},
  "geometry": {"coordinates":[6.720733,51.202042],"type":"Point"}
}