{
  "type": "Feature",
  "properties": {
    "iso:country":"DE",
    "sg:address":"Schadowstr. 40",
    "sg:city":"Essen",
    "sg:phone":"+49 201/702211",
    "sg:postcode":"45147",
    "sg:province":"Nordrhein-Westfalen",
    "wof:name":"Hausbauplanung Und Bautr\u00e4ger Gmbh",
    "wof:placetype":"venue"
},
  "geometry": {"coordinates":[6.9822340012,51.4404296875],"type":"Point"}
}