{
  "type": "Feature",
  "properties": {
    "iso:country":"DE",
    "sg:address":"Lehmweg 3",
    "sg:city":"Aurich",
    "sg:phone":"+49 4941/8306",
    "sg:postcode":"26607",
    "sg:province":"Niedersachsen",
    "wof:name":"Christian Graalfs",
    "wof:placetype":"venue"
},
  "geometry": {"coordinates":[7.457531,53.485985],"type":"Point"}
}