{
  "type": "Feature",
  "properties": {
    "iso:country":"DE",
    "sg:address":"Innstr. 40",
    "sg:city":"Simbach",
    "sg:phone":"+49 8571/3010",
    "sg:postcode":"84359",
    "sg:province":"Bayern",
    "wof:name":"Dr. Ferdinand Geitner Ingenieur",
    "wof:placetype":"venue"
},
  "geometry": {"coordinates":[13.032018,48.263138],"type":"Point"}
}