{
  "type": "Feature",
  "properties": {
    "iso:country":"DE",
    "sg:address":"Ahornstr. 55",
    "sg:city":"Aachen",
    "sg:phone":"+49 241/807280",
    "sg:postcode":"52074",
    "sg:province":"Nordrhein-Westfalen",
    "wof:name":"Lehrstuhl F. Informatik Iiirwth Aachen",
    "wof:placetype":"venue"
},
  "geometry": {"coordinates":[6.0593729019,50.7797279358],"type":"Point"}
}