{
  "type": "Feature",
  "properties": {
    "iso:country":"DE",
    "sg:address":"F\u00fcrstenwalder Allee 27",
    "sg:city":"Berlin",
    "sg:phone":"+49 30/6481474",
    "sg:postcode":"12589",
    "sg:province":"Berlin",
    "wof:name":"Horst Schade",
    "wof:placetype":"venue"
},
  "geometry": {"coordinates":[13.686058,52.442806],"type":"Point"}
}