{
  "type": "Feature",
  "properties": {
    "iso:country":"DE",
    "sg:address":"Haitzinger Str. 64",
    "sg:city":"Passau",
    "sg:phone":"+49 851/8402",
    "sg:postcode":"94036",
    "sg:province":"Bayern",
    "wof:name":"Schmidter Gmbh",
    "wof:placetype":"venue"
},
  "geometry": {"coordinates":[13.415675,48.572639],"type":"Point"}
}