{
  "type": "Feature",
  "properties": {
    "iso:country":"DE",
    "sg:address":"Hinter den Teichen 4",
    "sg:city":"Vienenburg",
    "sg:phone":"+49 5324/2968",
    "sg:postcode":"38690",
    "sg:province":"Niedersachsen",
    "wof:name":"Riefling Gmbh",
    "wof:placetype":"venue"
},
  "geometry": {"coordinates":[10.5680408478,51.9469261169],"type":"Point"}
}