{
  "type": "Feature",
  "properties": {
    "iso:country":"DE",
    "sg:address":"Theodor-Heuss-Str. 10a",
    "sg:city":"Waldkirch",
    "sg:phone":"+49 7681/6497",
    "sg:postcode":"79183",
    "sg:province":"Baden-W\u00fcrttemberg",
    "wof:name":"Elzt\u00e4ler Frischei-service Tobias Bayer E. K.",
    "wof:placetype":"venue"
},
  "geometry": {"coordinates":[7.9661960602,48.0966033936],"type":"Point"}
}