{
  "type": "Feature",
  "properties": {
    "iso:country":"DE",
    "sg:address":"Lotharstr. 156",
    "sg:city":"Bonn",
    "sg:phone":"+49 228/232129",
    "sg:postcode":"53115",
    "sg:province":"Nordrhein-Westfalen",
    "wof:name":"Kurt Baumann",
    "wof:placetype":"venue"
},
  "geometry": {"coordinates":[7.1037540436,50.7155342102],"type":"Point"}
}