{
  "type": "Feature",
  "properties": {
    "iso:country":"DE",
    "sg:address":"Stadtlanggasse 43",
    "sg:city":"Rottenburg",
    "sg:phone":"+49 7472/21404",
    "sg:postcode":"72108",
    "sg:province":"Baden-W\u00fcrttemberg",
    "wof:name":"H. Neu",
    "wof:placetype":"venue"
},
  "geometry": {"coordinates":[8.9362974167,48.4759941101],"type":"Point"}
}