{
  "type": "Feature",
  "properties": {
    "iso:country":"DE",
    "sg:address":"Hermannstr. 23",
    "sg:city":"Peine",
    "sg:phone":"+49 5171/21253",
    "sg:postcode":"31228",
    "sg:province":"Niedersachsen",
    "wof:name":"Wolfgang Oldenburg",
    "wof:placetype":"venue"
},
  "geometry": {"coordinates":[10.206668,52.32584],"type":"Point"}
}