{
  "type": "Feature",
  "properties": {
    "iso:country":"DE",
    "sg:address":"Rodewald",
    "sg:city":"Rodewald",
    "sg:phone":"+49 4950/741067",
    "sg:postcode":"31637",
    "sg:province":"Niedersachsen",
    "wof:name":"Volksbank Rodewald",
    "wof:placetype":"venue"
},
  "geometry": {"coordinates":[9.481993,52.660049],"type":"Point"}
}