{
  "type": "Feature",
  "properties": {
    "iso:country":"DE",
    "sg:address":"Windshofen 12",
    "sg:city":"Aurach",
    "sg:phone":"+49 9804/913376",
    "sg:postcode":"91589",
    "sg:province":"Bayern",
    "wof:name":"Nitzschke Dachdeckerei E. Kfm.",
    "wof:placetype":"venue"
},
  "geometry": {"coordinates":[10.383445,49.216049],"type":"Point"}
}