{
  "type": "Feature",
  "properties": {
    "iso:country":"DE",
    "sg:address":"Uferpromenade 27",
    "sg:city":"Meersburg",
    "sg:phone":"+49 7532/6057",
    "sg:postcode":"88709",
    "sg:province":"Baden-W\u00fcrttemberg",
    "wof:name":"Ev. Pfarramt",
    "wof:placetype":"venue"
},
  "geometry": {"coordinates":[9.2788076401,47.6901741028],"type":"Point"}
}