{
  "type": "Feature",
  "properties": {
    "iso:country":"DE",
    "sg:address":"Lange Str. 56",
    "sg:city":"Hessisch Oldendorf",
    "sg:phone":"+49 5152/1382",
    "sg:postcode":"31840",
    "sg:province":"Niedersachsen",
    "wof:name":"Dieter Ilchmann",
    "wof:placetype":"venue"
},
  "geometry": {"coordinates":[9.2478246689,52.1685218811],"type":"Point"}
}