{
  "type": "Feature",
  "properties": {
    "iso:country":"DE",
    "sg:address":"Haberstr. 30",
    "sg:city":"Neum\u00fcnster",
    "sg:phone":"+49 4321/569690",
    "sg:postcode":"24537",
    "sg:province":"Schleswig-Holstein",
    "wof:name":"B\u00e4cker Andresen & Sohn Ohg",
    "wof:placetype":"venue"
},
  "geometry": {"coordinates":[9.970363,54.104691],"type":"Point"}
}