{
  "type": "Feature",
  "properties": {
    "iso:country":"DE",
    "sg:address":"Ziegel\u00e4ckerweg 1",
    "sg:city":"Schriesheim",
    "sg:phone":"+49 6221/473282",
    "sg:postcode":"69198",
    "sg:province":"Baden-W\u00fcrttemberg",
    "wof:name":"Dr. W. Schwartz",
    "wof:placetype":"venue"
},
  "geometry": {"coordinates":[8.653386116,49.4702148438],"type":"Point"}
}