{
  "type": "Feature",
  "properties": {
    "iso:country":"DE",
    "sg:address":"Westerfilder Str. 29",
    "sg:city":"Dortmund",
    "sg:phone":"+49 231/370124",
    "sg:postcode":"44357",
    "sg:province":"Nordrhein-Westfalen",
    "wof:name":"Plus",
    "wof:placetype":"venue"
},
  "geometry": {"coordinates":[7.3754739761,51.5453224182],"type":"Point"}
}