{
  "type": "Feature",
  "properties": {
    "iso:country":"DE",
    "sg:address":"Holzhofstr. 8",
    "sg:city":"Weilheim",
    "sg:phone":"+49 881/5964",
    "sg:postcode":"82362",
    "sg:province":"Bayern",
    "wof:name":"Franz Buck",
    "wof:placetype":"venue"
},
  "geometry": {"coordinates":[11.128169,47.834114],"type":"Point"}
}