{
  "type": "Feature",
  "properties": {
    "iso:country":"DE",
    "sg:address":"Schweizerwiese 9",
    "sg:city":"Bad Herrenalb",
    "sg:postcode":"76332",
    "sg:province":"Baden-W\u00fcrttemberg",
    "wof:name":"Therme Bad Herrenalb Gmbh",
    "wof:placetype":"venue"
},
  "geometry": {"coordinates":[8.4406433105,48.8032112122],"type":"Point"}
}