{
  "type": "Feature",
  "properties": {
    "iso:country":"DE",
    "sg:address":"Wilramstr. 31",
    "sg:city":"M\u00fcnchen",
    "sg:phone":"+49 89/49000059",
    "sg:postcode":"81669",
    "sg:province":"Bayern",
    "wof:name":"C. Henkel",
    "wof:placetype":"venue"
},
  "geometry": {"coordinates":[11.6079807281,48.1154594421],"type":"Point"}
}