{
  "type": "Feature",
  "properties": {
    "iso:country":"DE",
    "sg:address":"Bergerplatz 2",
    "sg:city":"Grefrath",
    "sg:phone":"+49 2158/911963",
    "sg:postcode":"47929",
    "sg:province":"Nordrhein-Westfalen",
    "wof:name":"Wilfried Grehl",
    "wof:placetype":"venue"
},
  "geometry": {"coordinates":[6.3438200951,51.3372993469],"type":"Point"}
}