{
  "type": "Feature",
  "properties": {
    "iso:country":"DE",
    "sg:address":"Hauptstr. 23",
    "sg:city":"G\u00f6llingen",
    "sg:phone":"+49 34671/78622",
    "sg:postcode":"06567",
    "sg:province":"Th\u00fcringen",
    "wof:name":"E. Hoffmann",
    "wof:placetype":"venue"
},
  "geometry": {"coordinates":[11.0131492615,51.343624115],"type":"Point"}
}