{
  "type": "Feature",
  "properties": {
    "iso:country":"DE",
    "sg:address":"Hammerwasen",
    "sg:city":"Rottenburg",
    "sg:phone":"+49 7472/160254",
    "sg:postcode":"72108",
    "sg:province":"Baden-W\u00fcrttemberg",
    "wof:name":"St\u00e4dt. Freibad",
    "wof:placetype":"venue"
},
  "geometry": {"coordinates":[8.9190216064,48.4671134949],"type":"Point"}
}