{
  "type": "Feature",
  "properties": {
    "iso:country":"DE",
    "sg:address":"Industriestr. 20",
    "sg:city":"Alfdorf",
    "sg:phone":"+49 7172/3020",
    "sg:postcode":"73553",
    "sg:province":"Baden-W\u00fcrttemberg",
    "wof:name":"Trw Occupant Restraint Systems Gmbh & Co. Kg",
    "wof:placetype":"venue"
},
  "geometry": {"coordinates":[9.737596,48.845539],"type":"Point"}
}