{
  "type": "Feature",
  "properties": {
    "iso:country":"DE",
    "sg:address":"Birkenwaldstr. 213 a",
    "sg:city":"Stuttgart",
    "sg:phone":"+49 711/251966",
    "sg:postcode":"70191",
    "sg:province":"Baden-W\u00fcrttemberg",
    "wof:name":"Apotheke Am Killesberg",
    "wof:placetype":"venue"
},
  "geometry": {"coordinates":[9.175329,48.799107],"type":"Point"}
}