{
  "type": "Feature",
  "properties": {
    "iso:country":"DE",
    "sg:address":"Nienburger Str.12",
    "sg:city":"Husum",
    "sg:phone":"+49 5027/902408",
    "sg:postcode":"31632",
    "sg:province":"Niedersachsen",
    "wof:name":"Fickwunder",
    "wof:placetype":"venue"
},
  "geometry": {"coordinates":[9.265286,52.585678],"type":"Point"}
}