{
  "type": "Feature",
  "properties": {
    "iso:country":"DE",
    "sg:address":"Lilienthalstr 8-10",
    "sg:city":"Viernheim",
    "sg:phone":"+49 6204/70030",
    "sg:postcode":"68519",
    "sg:province":"Hessen",
    "wof:name":"Pfenning Logistik Gmbh",
    "wof:placetype":"venue"
},
  "geometry": {"coordinates":[8.595193,49.54631],"type":"Point"}
}