{
  "type": "Feature",
  "properties": {
    "iso:country":"DE",
    "sg:address":"Wahld 5",
    "sg:city":"Hellenthal",
    "sg:phone":"+49 2448/336",
    "sg:postcode":"53940",
    "sg:province":"Nordrhein-Westfalen",
    "wof:name":"Karl-josef Klein",
    "wof:placetype":"venue"
},
  "geometry": {"coordinates":[6.453758,50.454155],"type":"Point"}
}