{
  "type": "Feature",
  "properties": {
    "iso:country":"DE",
    "sg:address":"Moosburger Str. 8",
    "sg:city":"H\u00f6rgertshausen",
    "sg:phone":"+49 8764/479",
    "sg:postcode":"85413",
    "sg:province":"Bayern",
    "wof:name":"Josef Lutz Gmbh",
    "wof:placetype":"venue"
},
  "geometry": {"coordinates":[11.8649187088,48.5483283997],"type":"Point"}
}