{
  "type": "Feature",
  "properties": {
    "iso:country":"DE",
    "sg:address":"Birkhuhnstr. 6",
    "sg:city":"Bar\u00dfel",
    "sg:phone":"+49 4499/1729",
    "sg:postcode":"26676",
    "sg:province":"Niedersachsen",
    "wof:name":"Georg Benkens",
    "wof:placetype":"venue"
},
  "geometry": {"coordinates":[7.7428870201,53.1195373535],"type":"Point"}
}