{
  "type": "Feature",
  "properties": {
    "iso:country":"DE",
    "sg:address":"Marktplatz 7",
    "sg:city":"Kirchberg",
    "sg:phone":"+49 6763/3266",
    "sg:postcode":"55481",
    "sg:province":"Rheinland-Pfalz",
    "wof:name":"Ausonius",
    "wof:placetype":"venue"
},
  "geometry": {"coordinates":[7.4062662125,49.9429626465],"type":"Point"}
}