{
  "type": "Feature",
  "properties": {
    "iso:country":"DE",
    "sg:address":"Bolandenstr. 14",
    "sg:city":"Ludwigshafen",
    "sg:phone":"+49 621/543203",
    "sg:postcode":"67067",
    "sg:province":"Rheinland-Pfalz",
    "wof:name":"Hans-j\u00fcrgen Birkholz",
    "wof:placetype":"venue"
},
  "geometry": {"coordinates":[8.417468,49.449303],"type":"Point"}
}