{
  "type": "Feature",
  "properties": {
    "iso:country":"DE",
    "sg:address":"Jahnstr. 15",
    "sg:city":"Baienfurt",
    "sg:phone":"+49 751/44859",
    "sg:postcode":"88255",
    "sg:province":"Baden-W\u00fcrttemberg",
    "wof:name":"Monika Schuster",
    "wof:placetype":"venue"
},
  "geometry": {"coordinates":[9.651632,47.829315],"type":"Point"}
}