{
  "type": "Feature",
  "properties": {
    "iso:country":"DE",
    "sg:address":"Dreifelderstr. 26",
    "sg:city":"Stuttgart",
    "sg:phone":"+49 4971/1454848",
    "sg:postcode":"70599",
    "sg:province":"Baden-W\u00fcrttemberg",
    "wof:name":"Oskar Baumann Fleischerei-maschinenbau Gmbh & Co.",
    "wof:placetype":"venue"
},
  "geometry": {"coordinates":[9.219909668,48.7025680542],"type":"Point"}
}