{
  "type": "Feature",
  "properties": {
    "iso:country":"DE",
    "sg:address":"Dorfstr. 21",
    "sg:city":"Gro\u00dfkrausnik",
    "sg:postcode":"03249",
    "sg:province":"Brandenburg",
    "wof:name":"Lott Elektrik",
    "wof:placetype":"venue"
},
  "geometry": {"coordinates":[13.696533,51.706276],"type":"Point"}
}