{
  "type": "Feature",
  "properties": {
    "iso:country":"DE",
    "sg:address":"Sanarystr. 20",
    "sg:city":"Bad S\u00e4ckingen",
    "sg:phone":"+49 7761/50277",
    "sg:postcode":"79713",
    "sg:province":"Baden-W\u00fcrttemberg",
    "wof:name":"Barbara Sabas",
    "wof:placetype":"venue"
},
  "geometry": {"coordinates":[7.949284,47.561546],"type":"Point"}
}