{
  "type": "Feature",
  "properties": {
    "iso:country":"DE",
    "sg:address":"Hauptstr. 10",
    "sg:city":"Gaggenau",
    "sg:phone":"+49 7225/76746",
    "sg:postcode":"76571",
    "sg:province":"Baden-W\u00fcrttemberg",
    "wof:name":"Pfiff",
    "wof:placetype":"venue"
},
  "geometry": {"coordinates":[8.318181,48.805534],"type":"Point"}
}