{
  "type": "Feature",
  "properties": {
    "iso:country":"DE",
    "sg:address":"K\u00f6lner Str. 54",
    "sg:city":"M\u00fclheim",
    "sg:phone":"+49 208/489709",
    "sg:postcode":"45481",
    "sg:province":"Nordrhein-Westfalen",
    "wof:name":"Jet Tankstelle",
    "wof:placetype":"venue"
},
  "geometry": {"coordinates":[6.8756008148,51.3987426758],"type":"Point"}
}