{
  "type": "Feature",
  "properties": {
    "iso:country":"DE",
    "sg:address":"Am Plackmorgen 1",
    "sg:city":"Einbeck",
    "sg:phone":"+49 5561/81234",
    "sg:postcode":"37574",
    "sg:province":"Niedersachsen",
    "wof:name":"Walter Hesse",
    "wof:placetype":"venue"
},
  "geometry": {"coordinates":[9.897206,51.753777],"type":"Point"}
}