{
  "type": "Feature",
  "properties": {
    "iso:country":"DE",
    "sg:address":"Marktstr. 10",
    "sg:city":"Karlsruhe",
    "sg:postcode":"76185",
    "sg:province":"Baden-W\u00fcrttemberg",
    "wof:name":"Manuelas Bistro Und Backshop Gmbh",
    "wof:placetype":"venue"
},
  "geometry": {"coordinates":[8.359641,49.012257],"type":"Point"}
}