{
  "type": "Feature",
  "properties": {
    "iso:country":"DE",
    "sg:address":"Auf Den B\u00fclten 40",
    "sg:city":"Stemshorn",
    "sg:phone":"+49 4954/4399320",
    "sg:postcode":"49448",
    "sg:province":"Niedersachsen",
    "wof:name":"Raiffeisenmarkt Stemweder Berg Gmbh",
    "wof:placetype":"venue"
},
  "geometry": {"coordinates":[8.361543,52.456917],"type":"Point"}
}