{
  "type": "Feature",
  "properties": {
    "iso:country":"DE",
    "sg:address":"Hintere Marktstr. 48",
    "sg:city":"N\u00fcrnberg",
    "sg:phone":"+49 911/666878",
    "sg:postcode":"90441",
    "sg:province":"Bayern",
    "wof:name":"Ristorante Dal Gatto Rosso",
    "wof:placetype":"venue"
},
  "geometry": {"coordinates":[11.050280571,49.4331626892],"type":"Point"}
}