{
  "type": "Feature",
  "properties": {
    "iso:country":"DE",
    "sg:address":"Marschall 27",
    "sg:city":"Holzkirchen",
    "sg:postcode":"83607",
    "sg:province":"Bayern",
    "wof:name":"Dipl.-ing. Fh Klaus Nolte Elektronik E. Kfm.",
    "wof:placetype":"venue"
},
  "geometry": {"coordinates":[11.7119455338,47.8691139221],"type":"Point"}
}