{
  "type": "Feature",
  "properties": {
    "iso:country":"DE",
    "sg:address":"Adlerstr. 14",
    "sg:city":"Kronberg",
    "sg:phone":"+49 6173/78403",
    "sg:postcode":"61476",
    "sg:province":"Hessen",
    "wof:name":"Walter Litzinger",
    "wof:placetype":"venue"
},
  "geometry": {"coordinates":[8.5097332001,50.1789016724],"type":"Point"}
}