{
  "type": "Feature",
  "properties": {
    "iso:country":"DE",
    "sg:address":"Feldafinger Str. 61",
    "sg:city":"P\u00f6cking",
    "sg:phone":"+49 8157/4045",
    "sg:postcode":"82343",
    "sg:province":"Bayern",
    "wof:name":"Tretter Gmbh",
    "wof:placetype":"venue"
},
  "geometry": {"coordinates":[11.298009,47.957165],"type":"Point"}
}