{
  "type": "Feature",
  "properties": {
    "iso:country":"DE",
    "sg:address":"Dorfwiesenstr. 18",
    "sg:city":"Kornwestheim",
    "sg:phone":"+49 7154/21984",
    "sg:postcode":"70806",
    "sg:province":"Baden-W\u00fcrttemberg",
    "wof:name":"Eugen G\u00fcrr",
    "wof:placetype":"venue"
},
  "geometry": {"coordinates":[9.18928,48.864201],"type":"Point"}
}