{
  "type": "Feature",
  "properties": {
    "iso:country":"DE",
    "sg:address":"Werkstr. 7",
    "sg:city":"Aachen",
    "sg:phone":"+49 4924/082034",
    "sg:postcode":"52076",
    "sg:province":"Nordrhein-Westfalen",
    "wof:name":"Josef Hickertz Handels- Gmbh & Co. Kg",
    "wof:placetype":"venue"
},
  "geometry": {"coordinates":[6.137896,50.712685],"type":"Point"}
}