{
  "type": "Feature",
  "properties": {
    "iso:country":"DE",
    "sg:address":"Heinrich-Heine-Str. 8",
    "sg:city":"Gro\u00dfenhain",
    "sg:postcode":"01558",
    "sg:province":"Sachsen",
    "wof:name":"Institut F\u00fcr Lehrerbildung K\u00e4te Duncker",
    "wof:placetype":"venue"
},
  "geometry": {"coordinates":[13.530511,51.289948],"type":"Point"}
}