{
  "type": "Feature",
  "properties": {
    "iso:country":"DE",
    "sg:address":"Klammstr. 18",
    "sg:city":"Garmisch-Partenkirchen",
    "sg:phone":"+49 8821/2810",
    "sg:postcode":"82467",
    "sg:province":"Bayern",
    "wof:name":"G\u00e4stehaus J\u00f6rgl Hauterer",
    "wof:placetype":"venue"
},
  "geometry": {"coordinates":[11.0905189514,47.4913520813],"type":"Point"}
}