{
  "type": "Feature",
  "properties": {
    "iso:country":"DE",
    "sg:address":"Hofackerstr. 12",
    "sg:city":"Glatten",
    "sg:phone":"+49 7443/8224",
    "sg:postcode":"72293",
    "sg:province":"Baden-W\u00fcrttemberg",
    "wof:name":"G\u00fcnther Kress Steuerberater",
    "wof:placetype":"venue"
},
  "geometry": {"coordinates":[8.5134048462,48.4459991455],"type":"Point"}
}