{
  "type": "Feature",
  "properties": {
    "iso:country":"DE",
    "sg:address":"Industriestr. 13",
    "sg:city":"Kronach",
    "sg:phone":"+49 9261/60250",
    "sg:postcode":"96317",
    "sg:province":"Bayern",
    "wof:name":"Rebhan Metallwerkst\u00e4tten Gmbh",
    "wof:placetype":"venue"
},
  "geometry": {"coordinates":[11.341101,50.232018],"type":"Point"}
}