{
  "type": "Feature",
  "properties": {
    "iso:country":"DE",
    "sg:address":"U-Bhf Schlesisches Tor",
    "sg:city":"Berlin",
    "sg:phone":"+49 30/6112339",
    "sg:postcode":"10997",
    "sg:province":"Berlin",
    "wof:name":"Kato Kulturbahnhof Kreuzberg Betriebs Gmbh",
    "wof:placetype":"venue"
},
  "geometry": {"coordinates":[13.4418888092,52.5007476807],"type":"Point"}
}