{
  "type": "Feature",
  "properties": {
    "iso:country":"DE",
    "sg:address":"Ludwigstr. 8",
    "sg:city":"Buxtehude",
    "sg:phone":"+49 4161/61580",
    "sg:postcode":"21614",
    "sg:province":"Niedersachsen",
    "wof:name":"Rudolf Aldag",
    "wof:placetype":"venue"
},
  "geometry": {"coordinates":[9.70807,53.47665],"type":"Point"}
}