{
  "type": "Feature",
  "properties": {
    "iso:country":"DE",
    "sg:address":"Fuhrberger Landstr. 30",
    "sg:city":"Celle",
    "sg:phone":"+49 5141/46444",
    "sg:postcode":"29225",
    "sg:province":"Niedersachsen",
    "wof:name":"Gloria",
    "wof:placetype":"venue"
},
  "geometry": {"coordinates":[10.0209083557,52.6052017212],"type":"Point"}
}