{
  "type": "Feature",
  "properties": {
    "iso:country":"DE",
    "sg:address":"Kopernikusstr. 8",
    "sg:city":"Vechta",
    "sg:phone":"+49 4441/911230",
    "sg:postcode":"49377",
    "sg:province":"Niedersachsen",
    "wof:name":"Ls-autoverwertung E. Kfm.",
    "wof:placetype":"venue"
},
  "geometry": {"coordinates":[8.278459549,52.7476043701],"type":"Point"}
}