{
  "type": "Feature",
  "properties": {
    "iso:country":"DE",
    "sg:address":"Pfarrgasse 29",
    "sg:city":"Ha\u00dfloch",
    "sg:phone":"+49 6324/59507",
    "sg:postcode":"67454",
    "sg:province":"Rheinland-Pfalz",
    "wof:name":"R. Daggulu",
    "wof:placetype":"venue"
},
  "geometry": {"coordinates":[8.2652101517,49.3626747131],"type":"Point"}
}