{
  "type": "Feature",
  "properties": {
    "iso:country":"DE",
    "sg:address":"Obere Str. 18/1",
    "sg:city":"Altdorf",
    "sg:phone":"+49 7031/602140",
    "sg:postcode":"71155",
    "sg:province":"Baden-W\u00fcrttemberg",
    "wof:name":"Barth Reutlinger Rousek Und Schatz",
    "wof:placetype":"venue"
},
  "geometry": {"coordinates":[8.9963350296,48.6288261414],"type":"Point"}
}