{
  "type": "Feature",
  "properties": {
    "iso:country":"DE",
    "sg:address":"Am Zachow 8",
    "sg:city":"Malchin",
    "sg:phone":"+49 3994/227251",
    "sg:postcode":"17139",
    "sg:province":"Mecklenburg-Vorpommern",
    "wof:name":"Gerhard Emberger",
    "wof:placetype":"venue"
},
  "geometry": {"coordinates":[12.764051,53.742561],"type":"Point"}
}