{
  "type": "Feature",
  "properties": {
    "iso:country":"DE",
    "sg:address":"Hochsauerlandstr. 10 POSTFACH 2306",
    "sg:city":"Winterberg",
    "sg:phone":"+49 4929/8397100",
    "sg:postcode":"59947",
    "sg:province":"Bayern",
    "wof:name":"Kr\u00c4ling Office Gmbh",
    "wof:placetype":"venue"
},
  "geometry": {"coordinates":[8.4719467163,51.2526359558],"type":"Point"}
}