{
  "type": "Feature",
  "properties": {
    "iso:country":"DE",
    "sg:city":"Putzbrunn",
    "sg:phone":"+49 89/6013542",
    "sg:postcode":"85640",
    "sg:province":"Bayern",
    "wof:name":"Anna Sch\u00fc\u00dfler",
    "wof:placetype":"venue"
},
  "geometry": {"coordinates":[11.715634,48.076046],"type":"Point"}
}