{
  "type": "Feature",
  "properties": {
    "iso:country":"DE",
    "sg:address":"Sch\u00f6nhauser Allee 71",
    "sg:city":"Berlin",
    "sg:phone":"+49 30/4458407",
    "sg:postcode":"10437",
    "sg:province":"Berlin",
    "wof:name":"C. Gampe Und M. Vorreiter",
    "wof:placetype":"venue"
},
  "geometry": {"coordinates":[13.413835,52.548161],"type":"Point"}
}