{
  "type": "Feature",
  "properties": {
    "iso:country":"DE",
    "sg:address":"Viersener Str. 17",
    "sg:city":"Willich",
    "sg:phone":"+49 2156/911315",
    "sg:postcode":"47877",
    "sg:province":"Nordrhein-Westfalen",
    "wof:name":"Michael Malterer",
    "wof:placetype":"venue"
},
  "geometry": {"coordinates":[6.4568300247,51.2754707336],"type":"Point"}
}