{
  "type": "Feature",
  "properties": {
    "iso:country":"DE",
    "sg:address":"F\u00fcllscheuerweg 1",
    "sg:city":"Andernach",
    "sg:phone":"+49 4933/393427",
    "sg:postcode":"56626",
    "sg:province":"Rheinland-Pfalz",
    "wof:name":"Leistenwerk Schorfheide Gmbh",
    "wof:placetype":"venue"
},
  "geometry": {"coordinates":[13.4726142883,52.7550354004],"type":"Point"}
}