{
  "type": "Feature",
  "properties": {
    "iso:country":"DE",
    "sg:address":"Karl-Marx-Platz 12",
    "sg:city":"Berlin",
    "sg:phone":"+49 30/6817644",
    "sg:postcode":"12043",
    "sg:province":"Berlin",
    "wof:name":"Brigitte Frank",
    "wof:placetype":"venue"
},
  "geometry": {"coordinates":[13.4421272278,52.473651886],"type":"Point"}
}