{
  "type": "Feature",
  "properties": {
    "iso:country":"DE",
    "sg:address":"Bahnhofstr. 47",
    "sg:city":"Aalen",
    "sg:phone":"+49 7361/6347",
    "sg:postcode":"73430",
    "sg:province":"Baden-W\u00fcrttemberg",
    "wof:name":"Herbert M\u00e4urer Rechtsanwalt",
    "wof:placetype":"venue"
},
  "geometry": {"coordinates":[10.0944166183,48.8422775269],"type":"Point"}
}