{
  "type": "Feature",
  "properties": {
    "iso:country":"DE",
    "sg:address":"Dorfstr. 42",
    "sg:city":"Abtsgm\u00fcnd",
    "sg:phone":"+49 7366/6026",
    "sg:postcode":"73453",
    "sg:province":"Baden-W\u00fcrttemberg",
    "wof:name":"Theodor Lang",
    "wof:placetype":"venue"
},
  "geometry": {"coordinates":[9.9903278351,48.880771637],"type":"Point"}
}