{
  "type": "Feature",
  "properties": {
    "iso:country":"DE",
    "sg:address":"Greefsallee 49 POSTFACH 100561",
    "sg:city":"Viersen",
    "sg:phone":"+49 4921/623740",
    "sg:postcode":"41705",
    "sg:province":"Nordrhein-Westfalen",
    "wof:name":"Groschoop Ag Drive & More",
    "wof:placetype":"venue"
},
  "geometry": {"coordinates":[6.398786,51.247002],"type":"Point"}
}