{
  "type": "Feature",
  "properties": {
    "iso:country":"DE",
    "sg:address":"Ottensener Str. 150",
    "sg:city":"Hamburg",
    "sg:postcode":"22525",
    "sg:province":"Hamburg",
    "wof:name":"Nohr & Jakobsen Verwaltungsges. Mbh",
    "wof:placetype":"venue"
},
  "geometry": {"coordinates":[9.907258,53.586765],"type":"Point"}
}