{
  "type": "Feature",
  "properties": {
    "iso:country":"DE",
    "sg:address":"Martin-Luther-Str. 6",
    "sg:city":"Kr\u00f6lpa",
    "sg:postcode":"07387",
    "sg:province":"Th\u00fcringen",
    "wof:name":"Ev.-luth. Kirche Kr\u00f6lpa",
    "wof:placetype":"venue"
},
  "geometry": {"coordinates":[11.5325107574,50.6777572632],"type":"Point"}
}