{
  "type": "Feature",
  "properties": {
    "iso:country":"DE",
    "sg:address":"N\u00f6schenr\u00f6der Str. 10",
    "sg:city":"Wernigerode",
    "sg:phone":"+49 3943/43030",
    "sg:postcode":"38855",
    "sg:province":"Sachsen-Anhalt",
    "wof:name":"Volker Felgendreff",
    "wof:placetype":"venue"
},
  "geometry": {"coordinates":[10.7906455994,51.830280304],"type":"Point"}
}