{
  "type": "Feature",
  "properties": {
    "iso:country":"DE",
    "sg:address":"Barbarastr. 47-49",
    "sg:city":"K\u00f6ln",
    "sg:phone":"+49 221/392960",
    "sg:postcode":"50996",
    "sg:province":"Nordrhein-Westfalen",
    "wof:name":"Rodenkirchener Partyservice",
    "wof:placetype":"venue"
},
  "geometry": {"coordinates":[6.997437,50.8936],"type":"Point"}
}