{
  "type": "Feature",
  "properties": {
    "iso:country":"DE",
    "sg:address":"Sternbuschweg 136",
    "sg:city":"Duisburg",
    "sg:phone":"+49 203/351251",
    "sg:postcode":"47057",
    "sg:province":"Nordrhein-Westfalen",
    "wof:name":"G\u00fcnter Pauli Versandgesch\u00e4ft",
    "wof:placetype":"venue"
},
  "geometry": {"coordinates":[6.789563179,51.4255714417],"type":"Point"}
}