{
  "type": "Feature",
  "properties": {
    "iso:country":"DE",
    "sg:address":"Rudower Str. 17",
    "sg:city":"Berlin",
    "sg:phone":"+49 30/6519428",
    "sg:postcode":"12557",
    "sg:province":"Berlin",
    "wof:name":"M\u00fcnzel Bestattungs Gmbh",
    "wof:placetype":"venue"
},
  "geometry": {"coordinates":[13.566763,52.444004],"type":"Point"}
}