{
  "type": "Feature",
  "properties": {
    "iso:country":"DE",
    "sg:address":"Am Cr\u00f6stener Weg 11a",
    "sg:city":"Saalfeld",
    "sg:phone":"+49 3671/513342",
    "sg:postcode":"07318",
    "sg:province":"Th\u00fcringen",
    "wof:name":"Radl Eck Bikes & Sports Gmbh",
    "wof:placetype":"venue"
},
  "geometry": {"coordinates":[11.3467283249,50.6542129517],"type":"Point"}
}