{
  "type": "Feature",
  "properties": {
    "iso:country":"DE",
    "sg:city":"Sonstige ges. Deutschland",
    "sg:phone":"+49 190824903",
    "sg:postcode":"99999",
    "wof:name":"Firma U.k",
    "wof:placetype":"venue"
},
  "geometry": {"coordinates":[10.45424,51.090839],"type":"Point"}
}