{
  "type": "Feature",
  "properties": {
    "iso:country":"DE",
    "sg:address":"Osterheider Str. 4",
    "sg:city":"Espelkamp",
    "sg:phone":"+49 5743/8528",
    "sg:postcode":"32339",
    "sg:province":"Nordrhein-Westfalen",
    "wof:name":"Heinrich L\u00f6mker Bildhauer",
    "wof:placetype":"venue"
},
  "geometry": {"coordinates":[8.6843,52.365528],"type":"Point"}
}