{
  "type": "Feature",
  "properties": {
    "iso:country":"DE",
    "sg:address":"Weststr. 43",
    "sg:city":"Chemnitz",
    "sg:phone":"+49 371/517273",
    "sg:postcode":"09112",
    "sg:province":"Sachsen",
    "wof:name":"Malerwerkst\u00e4tten Zeuner Gmbh",
    "wof:placetype":"venue"
},
  "geometry": {"coordinates":[12.901317,50.831978],"type":"Point"}
}