{
  "type": "Feature",
  "properties": {
    "iso:country":"DE",
    "sg:address":"M\u00fchlenweg 27",
    "sg:city":"Bocholt",
    "sg:phone":"+49 2871/23163",
    "sg:postcode":"46395",
    "sg:province":"Nordrhein-Westfalen",
    "wof:name":"Fildeken-apotheke Mechthild M\u00fcssener",
    "wof:placetype":"venue"
},
  "geometry": {"coordinates":[6.623195,51.830597],"type":"Point"}
}