{
  "type": "Feature",
  "properties": {
    "iso:country":"DE",
    "sg:address":"Horbacher Str. 52",
    "sg:city":"Aachen",
    "sg:phone":"+49 241/12353",
    "sg:postcode":"52072",
    "sg:province":"Nordrhein-Westfalen",
    "wof:name":"Kath. Pfarramt St. Martin",
    "wof:placetype":"venue"
},
  "geometry": {"coordinates":[6.0587620735,50.814540863],"type":"Point"}
}