{
  "type": "Feature",
  "properties": {
    "iso:country":"DE",
    "sg:address":"Rhodel\u00e4nderweg 106",
    "sg:city":"Berlin",
    "sg:phone":"+49 30/6635876",
    "sg:postcode":"12355",
    "sg:province":"Berlin",
    "wof:name":"Dr. Hartmut Bartel Ingenieur",
    "wof:placetype":"venue"
},
  "geometry": {"coordinates":[13.4830694199,52.40284729],"type":"Point"}
}