{
  "type": "Feature",
  "properties": {
    "iso:country":"DE",
    "sg:address":"Sch\u00f6tmarsche Str. 21",
    "sg:city":"Bad Salzuflen",
    "sg:phone":"+49 5222/70178",
    "sg:postcode":"32107",
    "sg:province":"Nordrhein-Westfalen",
    "wof:name":"Helmut W\u00f6hler",
    "wof:placetype":"venue"
},
  "geometry": {"coordinates":[8.70065,52.064541],"type":"Point"}
}