{
  "type": "Feature",
  "properties": {
    "iso:country":"DE",
    "sg:address":"Alte Augsburger Str. 4",
    "sg:city":"Donauw\u00f6rth",
    "sg:postcode":"86609",
    "sg:province":"Bayern",
    "wof:name":"Innova Tuning Und Design Gmbh",
    "wof:placetype":"venue"
},
  "geometry": {"coordinates":[10.7857055664,48.7097892761],"type":"Point"}
}