{
  "type": "Feature",
  "properties": {
    "iso:country":"DE",
    "sg:address":"Bernsteinweg 3",
    "sg:city":"Darmstadt",
    "sg:phone":"+49 6151",
    "sg:postcode":"64297",
    "sg:province":"Hessen",
    "wof:name":"Meurer-landkartenvertrieb",
    "wof:placetype":"venue"
},
  "geometry": {"coordinates":[8.62478,49.820156],"type":"Point"}
}