{
  "type": "Feature",
  "properties": {
    "iso:country":"DE",
    "sg:address":"Hehler 172",
    "sg:city":"Schwalmtal",
    "sg:phone":"+49 2163/32343",
    "sg:postcode":"41366",
    "sg:province":"Nordrhein-Westfalen",
    "wof:name":"Haus Gather",
    "wof:placetype":"venue"
},
  "geometry": {"coordinates":[6.3082470894,51.2016143799],"type":"Point"}
}