{
  "type": "Feature",
  "properties": {
    "iso:country":"DE",
    "sg:address":"Ullsteinstr. 146",
    "sg:city":"Berlin",
    "sg:phone":"+49 30/7055153",
    "sg:postcode":"12105",
    "sg:province":"Berlin",
    "wof:name":"Wolfgang G\u00f6ritz Ingenieur",
    "wof:placetype":"venue"
},
  "geometry": {"coordinates":[13.3837327957,52.4528007507],"type":"Point"}
}