{
  "type": "Feature",
  "properties": {
    "iso:country":"DE",
    "sg:address":"Dreihornm\u00fchlgasse 48",
    "sg:city":"Worms",
    "sg:phone":"+49 6241/78495",
    "sg:postcode":"67549",
    "sg:province":"Rheinland-Pfalz",
    "wof:name":"A. Schl\u00e4fer Ingenieur",
    "wof:placetype":"venue"
},
  "geometry": {"coordinates":[8.3409004211,49.6390914917],"type":"Point"}
}