{
  "type": "Feature",
  "properties": {
    "iso:country":"DE",
    "sg:address":"Schustergasse 1",
    "sg:city":"Ochsenfurt",
    "sg:phone":"+49 9331/2133",
    "sg:postcode":"97199",
    "sg:province":"Bayern",
    "wof:name":"Ev. Pfarramt Erlach",
    "wof:placetype":"venue"
},
  "geometry": {"coordinates":[10.080242157,49.7059288025],"type":"Point"}
}