{
  "type": "Feature",
  "properties": {
    "iso:country":"DE",
    "sg:address":"Isarstra\u00dfe 34",
    "sg:city":"N\u00fcrnberg",
    "sg:phone":"+49 911/641860",
    "sg:postcode":"90451",
    "sg:province":"Bayern",
    "wof:name":"Thomas Sippel",
    "wof:placetype":"venue"
},
  "geometry": {"coordinates":[11.056230545,49.4082145691],"type":"Point"}
}