{
  "type": "Feature",
  "properties": {
    "iso:country":"DE",
    "sg:address":"Kirchenplatz 6",
    "sg:city":"Mettenheim",
    "sg:phone":"+49 8631/7245",
    "sg:postcode":"84562",
    "sg:province":"Bayern",
    "wof:name":"Kath. \u00d6ffentliche Bibliothek Kath. Pfarramt",
    "wof:placetype":"venue"
},
  "geometry": {"coordinates":[12.465199,48.266319],"type":"Point"}
}