{
  "type": "Feature",
  "properties": {
    "iso:country":"DE",
    "sg:address":"L\u00fctgendortmunder Str. 120",
    "sg:city":"Dortmund",
    "sg:phone":"+49 231/6992290",
    "sg:postcode":"44388",
    "sg:province":"Nordrhein-Westfalen",
    "wof:name":"Bau Tec Wohnbau Gmbh",
    "wof:placetype":"venue"
},
  "geometry": {"coordinates":[7.34009,51.499249],"type":"Point"}
}