{
  "type": "Feature",
  "properties": {
    "iso:country":"DE",
    "sg:address":"Waldstr. 10",
    "sg:city":"Geislingen",
    "sg:phone":"+49 7433/276365",
    "sg:postcode":"72351",
    "sg:province":"Baden-W\u00fcrttemberg",
    "wof:name":"Albrecht Brobeil Masseur",
    "wof:placetype":"venue"
},
  "geometry": {"coordinates":[8.814014,48.286617],"type":"Point"}
}