{
  "type": "Feature",
  "properties": {
    "iso:country":"DE",
    "sg:address":"Sachsentor 48",
    "sg:city":"Hamburg",
    "sg:phone":"+49 40/7211051",
    "sg:postcode":"21029",
    "sg:province":"Hamburg",
    "wof:name":"Dr. Klaus D. Partecke Rechtsanwalt",
    "wof:placetype":"venue"
},
  "geometry": {"coordinates":[10.214263916,53.4868774414],"type":"Point"}
}