{
  "type": "Feature",
  "properties": {
    "iso:country":"DE",
    "sg:address":"Hubmannstr. 6",
    "sg:city":"Aichach",
    "sg:phone":"+49 8251/1080",
    "sg:postcode":"86551",
    "sg:province":"Bayern",
    "wof:name":"Beck & Aidelsburger Gesch\u00e4ftsf\u00fchrungs Gmbh",
    "wof:placetype":"venue"
},
  "geometry": {"coordinates":[11.130538,48.459442],"type":"Point"}
}