{
  "type": "Feature",
  "properties": {
    "iso:country":"DE",
    "sg:address":"Kesselschmiedstr. 8",
    "sg:city":"Freising",
    "sg:phone":"+49 8161/41429",
    "sg:postcode":"85354",
    "sg:province":"Bayern",
    "wof:name":"Michael Rittscher Finanzberater",
    "wof:placetype":"venue"
},
  "geometry": {"coordinates":[11.740521431,48.3945846558],"type":"Point"}
}