{
  "type": "Feature",
  "properties": {
    "iso:country":"DE",
    "sg:address":"H\u00f6llgehau 55",
    "sg:city":"Krumbach",
    "sg:phone":"+49 8282/9080",
    "sg:postcode":"86381",
    "sg:province":"Bayern",
    "wof:name":"Bay Wa Ag",
    "wof:placetype":"venue"
},
  "geometry": {"coordinates":[10.351284,48.252075],"type":"Point"}
}