{
  "type": "Feature",
  "properties": {
    "iso:country":"DE",
    "sg:address":"Kurt-Schumacher-Str. 7",
    "sg:city":"Weinheim",
    "sg:phone":"+49 6201/65697",
    "sg:postcode":"69469",
    "sg:province":"Baden-W\u00fcrttemberg",
    "wof:name":"T. Pavlik",
    "wof:placetype":"venue"
},
  "geometry": {"coordinates":[8.637013,49.544403],"type":"Point"}
}