{
  "type": "Feature",
  "properties": {
    "iso:country":"DE",
    "sg:address":"Am Falltor 13",
    "sg:city":"Bensheim",
    "sg:phone":"+49 6251/79792",
    "sg:postcode":"64625",
    "sg:province":"Hessen",
    "wof:name":"Roth",
    "wof:placetype":"venue"
},
  "geometry": {"coordinates":[8.5721607208,49.6969718933],"type":"Point"}
}