{
  "type": "Feature",
  "properties": {
    "iso:country":"DE",
    "sg:address":"M\u00fcssenkoppel 8 b",
    "sg:city":"Hamburg",
    "sg:phone":"+49 40/64940303",
    "sg:postcode":"22399",
    "sg:province":"Hamburg",
    "wof:name":"Cec Confident Export Consult Gmbh",
    "wof:placetype":"venue"
},
  "geometry": {"coordinates":[10.0714120865,53.6526832581],"type":"Point"}
}