{
  "type": "Feature",
  "properties": {
    "iso:country":"DE",
    "sg:address":"S\u00fcdgeorgsfehner Str. 5",
    "sg:city":"Apen",
    "sg:phone":"+49 4489/1326",
    "sg:postcode":"26689",
    "sg:province":"Niedersachsen",
    "wof:name":"Carl Hinrichs Gro\u00df- Und Einzelhandel Eisenwaren",
    "wof:placetype":"venue"
},
  "geometry": {"coordinates":[7.74191,53.229649],"type":"Point"}
}