{
  "type": "Feature",
  "properties": {
    "iso:country":"DE",
    "sg:address":"Freiburger Str. 23",
    "sg:city":"Weinheim",
    "sg:phone":"+49 6201/12003",
    "sg:postcode":"69469",
    "sg:province":"Baden-W\u00fcrttemberg",
    "wof:name":"Martin & Karch",
    "wof:placetype":"venue"
},
  "geometry": {"coordinates":[8.6324453354,49.5484237671],"type":"Point"}
}