{
  "type": "Feature",
  "properties": {
    "iso:country":"DE",
    "sg:address":"Hubertusstrasse 19",
    "sg:city":"Kevelaer",
    "sg:phone":"+49 2832/6328",
    "sg:postcode":"47623",
    "sg:province":"Nordrhein-Westfalen",
    "wof:name":"Krippen Und Devotionalien",
    "wof:placetype":"venue"
},
  "geometry": {"coordinates":[6.239671,51.585773],"type":"Point"}
}