{
  "type": "Feature",
  "properties": {
    "iso:country":"DE",
    "sg:address":"Alexander-Fleming-Str. 39",
    "sg:city":"Mainz",
    "sg:phone":"+49 6131/882471",
    "sg:postcode":"55130",
    "sg:province":"Rheinland-Pfalz",
    "wof:name":"Robert Sommer",
    "wof:placetype":"venue"
},
  "geometry": {"coordinates":[8.320615,49.960979],"type":"Point"}
}