{
  "type": "Feature",
  "properties": {
    "iso:country":"DE",
    "sg:address":"Th\u00fcngersheimer Str. 78",
    "sg:city":"G\u00fcntersleben",
    "sg:phone":"+49 9365/897020",
    "sg:postcode":"97261",
    "sg:province":"Bayern",
    "wof:name":"Ingenieurb\u00fcro \u00d6hrlein Gmbh & Co. Kg",
    "wof:placetype":"venue"
},
  "geometry": {"coordinates":[9.8966808319,49.8723754883],"type":"Point"}
}