{
  "type": "Feature",
  "properties": {
    "iso:country":"DE",
    "sg:address":"Baltenstr. 26",
    "sg:city":"Stuttgart",
    "sg:phone":"+49 711/532394",
    "sg:postcode":"70378",
    "sg:province":"Baden-W\u00fcrttemberg",
    "wof:name":"Karl Haisch",
    "wof:placetype":"venue"
},
  "geometry": {"coordinates":[9.22726,48.84214],"type":"Point"}
}