{
  "type": "Feature",
  "properties": {
    "iso:country":"DE",
    "sg:address":"Solmsstr. 27",
    "sg:city":"Berlin",
    "sg:phone":"+49 30/6925815",
    "sg:postcode":"10961",
    "sg:province":"Berlin",
    "wof:name":"Klaus-j\u00fcrgen B\u00fcttner Angelger\u00e4te",
    "wof:placetype":"venue"
},
  "geometry": {"coordinates":[13.391858,52.489731],"type":"Point"}
}