{
  "type": "Feature",
  "properties": {
    "iso:country":"DE",
    "sg:address":"Landshuter Str. 65",
    "sg:city":"Ergolding",
    "sg:phone":"+49 871/7040",
    "sg:postcode":"84030",
    "sg:province":"Bayern",
    "wof:name":"Rwe Solutions Ag",
    "wof:placetype":"venue"
},
  "geometry": {"coordinates":[12.161357,48.564686],"type":"Point"}
}