{
  "type": "Feature",
  "properties": {
    "iso:country":"DE",
    "sg:address":"Karlsbader Stra\u00dfe 42",
    "sg:city":"STUTTGART",
    "sg:phone":"+49 711/568224",
    "sg:postcode":"70372",
    "sg:province":"Baden-W\u00fcrttemberg",
    "wof:name":"Erpu Verlag",
    "wof:placetype":"venue"
},
  "geometry": {"coordinates":[9.22676,48.801197],"type":"Point"}
}