{
  "type": "Feature",
  "properties": {
    "iso:country":"DE",
    "sg:address":"Weimarer Weg 18",
    "sg:city":"Stuhr",
    "sg:phone":"+49 421/898570",
    "sg:postcode":"28816",
    "sg:province":"Niedersachsen",
    "wof:name":"Senioren Wohnpark Weser Gmbh",
    "wof:placetype":"venue"
},
  "geometry": {"coordinates":[8.779729,53.015308],"type":"Point"}
}