{
  "type": "Feature",
  "properties": {
    "iso:country":"DE",
    "sg:address":"Trajanstr. 21",
    "sg:city":"Xanten",
    "sg:phone":"+49 2801/2097",
    "sg:postcode":"46509",
    "sg:province":"Nordrhein-Westfalen",
    "wof:name":"Ernst Kiwitz",
    "wof:placetype":"venue"
},
  "geometry": {"coordinates":[6.431414,51.659069],"type":"Point"}
}