{
  "type": "Feature",
  "properties": {
    "iso:country":"DE",
    "sg:address":"Dannenwalder Weg 142",
    "sg:city":"Berlin",
    "sg:phone":"+49 30/4155506",
    "sg:postcode":"13439",
    "sg:province":"Berlin",
    "wof:name":"Manfred Gurschke Masseur",
    "wof:placetype":"venue"
},
  "geometry": {"coordinates":[13.356371,52.592335],"type":"Point"}
}