{
  "type": "Feature",
  "properties": {
    "iso:country":"DE",
    "sg:address":"Freisinger Str. 11 a",
    "sg:city":"Erding",
    "sg:phone":"+49 8122/1638",
    "sg:postcode":"85435",
    "sg:province":"Bayern",
    "wof:name":"Ingenieurb\u00fcro Dipl.-ing. Peter Ke\u00dfler",
    "wof:placetype":"venue"
},
  "geometry": {"coordinates":[11.9066534042,48.3096046448],"type":"Point"}
}