{
  "type": "Feature",
  "properties": {
    "iso:country":"DE",
    "sg:address":"Hochstr. 14",
    "sg:city":"Ettringen",
    "sg:phone":"+49 8249/573",
    "sg:postcode":"86833",
    "sg:province":"Bayern",
    "wof:name":"Hubert Lang",
    "wof:placetype":"venue"
},
  "geometry": {"coordinates":[10.656862,48.102375],"type":"Point"}
}