{
  "type": "Feature",
  "properties": {
    "iso:country":"DE",
    "sg:address":"Collegienstr. 3",
    "sg:city":"Lutherstadt Wittenberg",
    "sg:phone":"+49 3491/401039",
    "sg:postcode":"06886",
    "sg:province":"Sachsen-Anhalt",
    "wof:name":"Schwab",
    "wof:placetype":"venue"
},
  "geometry": {"coordinates":[12.644502,51.866127],"type":"Point"}
}