{
  "type": "Feature",
  "properties": {
    "iso:country":"DE",
    "sg:address":"M\u00fcnchhof 10",
    "sg:city":"Burghaslach",
    "sg:phone":"+49 9552/7937",
    "sg:postcode":"96152",
    "sg:province":"Bayern",
    "wof:name":"Siegfried Link",
    "wof:placetype":"venue"
},
  "geometry": {"coordinates":[10.544561,49.742241],"type":"Point"}
}