{
  "type": "Feature",
  "properties": {
    "iso:country":"DE",
    "sg:address":"D\u00fcsseldorfer Str. 32",
    "sg:city":"M\u00fclheim",
    "sg:phone":"+49 208/487227",
    "sg:postcode":"45481",
    "sg:province":"Nordrhein-Westfalen",
    "wof:name":"Wilfried Olfs Und Heike Immand Gbr",
    "wof:placetype":"venue"
},
  "geometry": {"coordinates":[6.8770489693,51.4039497375],"type":"Point"}
}