{
  "type": "Feature",
  "properties": {
    "iso:country":"DE",
    "sg:address":"Dorfstr. 19",
    "sg:city":"Traunstein",
    "sg:phone":"+49 861/2715",
    "sg:postcode":"83278",
    "sg:province":"Bayern",
    "wof:name":"Karl-heinz Brenninger Architekt",
    "wof:placetype":"venue"
},
  "geometry": {"coordinates":[12.607836,47.880398],"type":"Point"}
}