{
  "type": "Feature",
  "properties": {
    "iso:country":"DE",
    "sg:address":"Am Grafenfeld 5 b",
    "sg:city":"Oettingen",
    "sg:phone":"+49 9082/2585",
    "sg:postcode":"86732",
    "sg:province":"Bayern",
    "wof:name":"R. Vo\u00df",
    "wof:placetype":"venue"
},
  "geometry": {"coordinates":[10.5990066528,48.9462585449],"type":"Point"}
}