{
  "type": "Feature",
  "properties": {
    "iso:country":"DE",
    "sg:address":"Essener Str. 15",
    "sg:city":"Stuttgart",
    "sg:phone":"+49 711/543320",
    "sg:postcode":"70376",
    "sg:province":"Baden-W\u00fcrttemberg",
    "wof:name":"Satilmis \u00d6zdemir",
    "wof:placetype":"venue"
},
  "geometry": {"coordinates":[9.2087211609,48.8153305054],"type":"Point"}
}