{
  "type": "Feature",
  "properties": {
    "iso:country":"DE",
    "sg:address":"Bangertsbuckel 25",
    "sg:city":"M\u00f6rlenbach",
    "sg:phone":"+49 4962/095530",
    "sg:postcode":"69509",
    "sg:province":"Hessen",
    "wof:name":"D\u00dcma Maschinenbau & W\u00c4rmetechnik Gmbh",
    "wof:placetype":"venue"
},
  "geometry": {"coordinates":[8.754541,49.577286],"type":"Point"}
}