{
  "type": "Feature",
  "properties": {
    "iso:country":"DE",
    "sg:address":"Reichartshausen 23",
    "sg:city":"Amorbach",
    "sg:phone":"+49 9373/698",
    "sg:postcode":"63916",
    "sg:province":"Bayern",
    "wof:name":"Heinrich M\u00fcnig",
    "wof:placetype":"venue"
},
  "geometry": {"coordinates":[9.279969,49.659172],"type":"Point"}
}