{
  "type": "Feature",
  "properties": {
    "iso:country":"DE",
    "sg:address":"Untergasse 32",
    "sg:city":"Gudensberg",
    "sg:phone":"+49 5603/3540",
    "sg:postcode":"34281",
    "sg:province":"Hessen",
    "wof:name":"Christine Schauml\u00f6ffel",
    "wof:placetype":"venue"
},
  "geometry": {"coordinates":[9.36782,51.177505],"type":"Point"}
}