{
  "type": "Feature",
  "properties": {
    "iso:country":"DE",
    "sg:address":"Friedrichstr. 57",
    "sg:city":"Kronberg",
    "sg:phone":"+49 6173/703217",
    "sg:postcode":"61476",
    "sg:province":"Hessen",
    "wof:name":"Taunushalle Sch\u00f6nberg",
    "wof:placetype":"venue"
},
  "geometry": {"coordinates":[8.517806,50.183327],"type":"Point"}
}