{
  "type": "Feature",
  "properties": {
    "iso:country":"DE",
    "sg:address":"P\u00f6hlauer Str. 81",
    "sg:city":"Zwickau",
    "sg:phone":"+49 375/212027",
    "sg:postcode":"08066",
    "sg:province":"Sachsen",
    "wof:name":"G\u00fcnther Reinhold",
    "wof:placetype":"venue"
},
  "geometry": {"coordinates":[12.542818,50.717567],"type":"Point"}
}