{
  "type": "Feature",
  "properties": {
    "iso:country":"DE",
    "sg:city":"Lohme",
    "sg:phone":"+49 38302/9204",
    "sg:postcode":"18551",
    "sg:province":"Mecklenburg-Vorpommern",
    "wof:name":"Erholungs- Und R\u00fcstzeitheim",
    "wof:placetype":"venue"
},
  "geometry": {"coordinates":[13.610193,54.582821],"type":"Point"}
}