{
  "type": "Feature",
  "properties": {
    "iso:country":"DE",
    "sg:address":"Poststr. 17",
    "sg:city":"Augsburg",
    "sg:phone":"+49 821/8155909",
    "sg:postcode":"86179",
    "sg:province":"Bayern",
    "wof:name":"Erich Frank",
    "wof:placetype":"venue"
},
  "geometry": {"coordinates":[10.9096441269,48.3106231689],"type":"Point"}
}