{
  "type": "Feature",
  "properties": {
    "iso:country":"DE",
    "sg:address":"Ged\u00e4chtnisstr. 12",
    "sg:city":"Koblenz",
    "sg:phone":"+49 261/27538",
    "sg:postcode":"56072",
    "sg:province":"Rheinland-Pfalz",
    "wof:name":"Alfred Ackermann",
    "wof:placetype":"venue"
},
  "geometry": {"coordinates":[7.517076,50.368923],"type":"Point"}
}