{
  "type": "Feature",
  "properties": {
    "iso:country":"DE",
    "sg:address":"Schloenbachstr. 18 a",
    "sg:city":"Bad Rothenfelde",
    "sg:phone":"+49 561/812091",
    "sg:postcode":"49214",
    "sg:province":"Niedersachsen",
    "wof:name":"F. Homann Gmbh & Co. Kg",
    "wof:placetype":"venue"
},
  "geometry": {"coordinates":[8.1692237854,52.1110191345],"type":"Point"}
}