{
  "type": "Feature",
  "properties": {
    "iso:country":"DE",
    "sg:city":"Bad Soden",
    "sg:postcode":"65812",
    "sg:province":"Hessen",
    "wof:name":"Minimoneyart",
    "wof:placetype":"venue"
},
  "geometry": {"coordinates":[9.213757,49.924606],"type":"Point"}
}