{
  "type": "Feature",
  "properties": {
    "iso:country":"DE",
    "sg:address":"Dorfstr. 11",
    "sg:city":"Langen",
    "sg:phone":"+49 4707/1300",
    "sg:postcode":"27607",
    "sg:province":"Niedersachsen",
    "wof:name":"Wilhelm Handelmann",
    "wof:placetype":"venue"
},
  "geometry": {"coordinates":[8.68543,53.676777],"type":"Point"}
}