{
  "type": "Feature",
  "properties": {
    "iso:country":"DE",
    "sg:address":"St\u00f6rwiesen 18",
    "sg:city":"Neum\u00fcnster",
    "sg:phone":"+49 4321/81960",
    "sg:postcode":"24539",
    "sg:province":"Schleswig-Holstein",
    "wof:name":"G\u00fcnter Kersten",
    "wof:placetype":"venue"
},
  "geometry": {"coordinates":[9.982163,54.055237],"type":"Point"}
}