{
  "type": "Feature",
  "properties": {
    "iso:country":"DE",
    "sg:address":"Blumenstr. 14",
    "sg:city":"Leiblfing",
    "sg:phone":"+49 9427/1227",
    "sg:postcode":"94339",
    "sg:province":"Bayern",
    "wof:name":"Wolfgang Radecker",
    "wof:placetype":"venue"
},
  "geometry": {"coordinates":[12.5113153458,48.7700157166],"type":"Point"}
}