{
  "type": "Feature",
  "properties": {
    "iso:country":"DE",
    "sg:address":"Sudetenstr. 19",
    "sg:city":"Allersberg",
    "sg:phone":"+49 9176/7600",
    "sg:postcode":"90584",
    "sg:province":"Bayern",
    "wof:name":"Max Fickert Architekt",
    "wof:placetype":"venue"
},
  "geometry": {"coordinates":[11.239788,49.257641],"type":"Point"}
}