{
  "type": "Feature",
  "properties": {
    "iso:country":"DE",
    "sg:address":"Lichtenrader Damm 95",
    "sg:city":"Berlin",
    "sg:phone":"+49 30/7451131",
    "sg:postcode":"12305",
    "sg:province":"Berlin",
    "wof:name":"Spallek",
    "wof:placetype":"venue"
},
  "geometry": {"coordinates":[13.4067611694,52.4051017761],"type":"Point"}
}