{
  "type": "Feature",
  "properties": {
    "iso:country":"DE",
    "sg:address":"Rosenstr. 20",
    "sg:city":"Geseke",
    "sg:phone":"+49 2942/1351",
    "sg:postcode":"59590",
    "sg:province":"Nordrhein-Westfalen",
    "wof:name":"Joh. Vorderw\u00fclbecke",
    "wof:placetype":"venue"
},
  "geometry": {"coordinates":[8.513317,51.637306],"type":"Point"}
}