{
  "type": "Feature",
  "properties": {
    "iso:country":"DE",
    "sg:address":"Kirselfeld 16",
    "sg:city":"Uedem",
    "sg:phone":"+49 2825/90350",
    "sg:postcode":"47589",
    "sg:province":"Nordrhein-Westfalen",
    "wof:name":"Hans Scharfschwerdt",
    "wof:placetype":"venue"
},
  "geometry": {"coordinates":[6.2845811844,51.6742324829],"type":"Point"}
}