{
  "type": "Feature",
  "properties": {
    "iso:country":"DE",
    "sg:address":"Max-Planck-Str. 11",
    "sg:city":"Kerpen",
    "sg:phone":"+49 2237/53200",
    "sg:postcode":"50171",
    "sg:province":"Nordrhein-Westfalen",
    "wof:name":"H. Sch\u00e4fers",
    "wof:placetype":"venue"
},
  "geometry": {"coordinates":[6.674098,50.881161],"type":"Point"}
}