{
  "type": "Feature",
  "properties": {
    "iso:country":"DE",
    "sg:address":"Narzissenstr. 26",
    "sg:city":"F\u00fcrth",
    "sg:phone":"+49 911/751186",
    "sg:postcode":"90768",
    "sg:province":"Bayern",
    "wof:name":"Dachsel & Co.",
    "wof:placetype":"venue"
},
  "geometry": {"coordinates":[10.9122571945,49.4913215637],"type":"Point"}
}