{
  "type": "Feature",
  "properties": {
    "iso:country":"DE",
    "sg:address":"Friedrich-Engels-Allee 275b",
    "sg:city":"Wuppertal",
    "sg:phone":"+49 202/87521",
    "sg:postcode":"42285",
    "sg:province":"Nordrhein-Westfalen",
    "wof:name":"W. Dieter Himmelmann Gmbh",
    "wof:placetype":"venue"
},
  "geometry": {"coordinates":[7.18024683,51.264087677],"type":"Point"}
}