{
  "type": "Feature",
  "properties": {
    "iso:country":"DE",
    "sg:address":"Fischersteige 1",
    "sg:city":"Kempten",
    "sg:phone":"+49 831/17459",
    "sg:postcode":"87435",
    "sg:province":"Bayern",
    "wof:name":"Optik Am Rathaus J. & G. Stachel Gmbh",
    "wof:placetype":"venue"
},
  "geometry": {"coordinates":[10.315459,47.725548],"type":"Point"}
}