{
  "type": "Feature",
  "properties": {
    "iso:country":"DE",
    "sg:address":"Postfach 11 03 64:: D-64218 Darmstadt:: Germany.^^Huegelstrasse 8-20::",
    "sg:city":"Darmstadt",
    "sg:phone":"+49 6151/1570",
    "sg:postcode":"64218",
    "sg:province":"Hessen",
    "wof:name":"Volksbank Darmstadt Eg",
    "wof:placetype":"venue"
},
  "geometry": {"coordinates":[8.65478,49.87458],"type":"Point"}
}