{
  "type": "Feature",
  "properties": {
    "iso:country":"DE",
    "sg:address":"Am Stadtrand 15",
    "sg:city":"Sassnitz",
    "sg:phone":"+49 38392/32211",
    "sg:postcode":"18546",
    "sg:province":"Mecklenburg-Vorpommern",
    "wof:name":"Waldemar Sch\u00f6n",
    "wof:placetype":"venue"
},
  "geometry": {"coordinates":[13.60881,54.516193],"type":"Point"}
}