{
  "type": "Feature",
  "properties": {
    "iso:country":"DE",
    "sg:address":"Friedrich-von-Spee-Str. 44",
    "sg:city":"D\u00fcsseldorf",
    "sg:phone":"+49 211/940050",
    "sg:postcode":"40489",
    "sg:province":"Nordrhein-Westfalen",
    "wof:name":"Hotel Ambrosius",
    "wof:placetype":"venue"
},
  "geometry": {"coordinates":[6.7355771065,51.2995872498],"type":"Point"}
}