{
  "type": "Feature",
  "properties": {
    "iso:country":"DE",
    "sg:address":"Angerstr. 6",
    "sg:city":"Goldkronach",
    "sg:phone":"+49 9208/8856",
    "sg:postcode":"95497",
    "sg:province":"Bayern",
    "wof:name":"Heinrich B\u00f6hner",
    "wof:placetype":"venue"
},
  "geometry": {"coordinates":[11.660491,49.994316],"type":"Point"}
}