{
  "type": "Feature",
  "properties": {
    "iso:country":"DE",
    "sg:address":"Henschelstr. 4",
    "sg:city":"B\u00fcnde",
    "sg:phone":"+49 5223/699080",
    "sg:postcode":"32257",
    "sg:province":"Nordrhein-Westfalen",
    "wof:name":"Futterkrippe",
    "wof:placetype":"venue"
},
  "geometry": {"coordinates":[8.5796699524,52.1968193054],"type":"Point"}
}