{
  "type": "Feature",
  "properties": {
    "iso:country":"DE",
    "sg:address":"Fichtenstr 11",
    "sg:city":"Kutzenhausen",
    "sg:phone":"+49 8238/959970",
    "sg:postcode":"86500",
    "sg:province":"Bayern",
    "wof:name":"M\u00fcller",
    "wof:placetype":"venue"
},
  "geometry": {"coordinates":[10.694332,48.33786],"type":"Point"}
}