{
  "type": "Feature",
  "properties": {
    "iso:country":"DE",
    "sg:address":"Leipziger Str. 13",
    "sg:city":"Brandis",
    "sg:phone":"+49 34292/3776",
    "sg:postcode":"04821",
    "sg:province":"Sachsen",
    "wof:name":"K. Dressel Masseur",
    "wof:placetype":"venue"
},
  "geometry": {"coordinates":[12.610657,51.336411],"type":"Point"}
}