{
  "type": "Feature",
  "properties": {
    "iso:country":"DE",
    "sg:address":"Hauptstr. 37",
    "sg:city":"Ramsthal",
    "sg:phone":"+49 9704/1435",
    "sg:postcode":"97729",
    "sg:province":"Bayern",
    "wof:name":"Heinrich Warmuth",
    "wof:placetype":"venue"
},
  "geometry": {"coordinates":[10.0697240829,50.1396942139],"type":"Point"}
}