{
  "type": "Feature",
  "properties": {
    "iso:country":"DE",
    "sg:address":"Rosenberger Str 1",
    "sg:city":"Osterburken",
    "sg:phone":"+49 6291/64460",
    "sg:postcode":"74706",
    "sg:province":"Baden-W\u00fcrttemberg",
    "wof:name":"G\u00fcdel Gmbh",
    "wof:placetype":"venue"
},
  "geometry": {"coordinates":[9.427154,49.428932],"type":"Point"}
}