{
  "type": "Feature",
  "properties": {
    "iso:country":"DE",
    "sg:address":"Grover Str. 32",
    "sg:city":"Rodenberg",
    "sg:phone":"+49 5723/913486",
    "sg:postcode":"31552",
    "sg:province":"Niedersachsen",
    "wof:name":"Ev. Pfarramt",
    "wof:placetype":"venue"
},
  "geometry": {"coordinates":[9.359670639,52.3136711121],"type":"Point"}
}