{
  "type": "Feature",
  "properties": {
    "iso:country":"DE",
    "sg:address":"Oskar-Kiefer-Str. 12",
    "sg:city":"Ettlingen",
    "sg:phone":"+49 7243/91933",
    "sg:postcode":"76275",
    "sg:province":"Baden-W\u00fcrttemberg",
    "wof:name":"Max B\u00fchler Architekt",
    "wof:placetype":"venue"
},
  "geometry": {"coordinates":[8.390417,48.926136],"type":"Point"}
}