{
  "type": "Feature",
  "properties": {
    "iso:country":"DE",
    "sg:address":"H\u00e4\u00dflerstr. 4",
    "sg:city":"Erfurt",
    "sg:phone":"+49 361/3460104",
    "sg:postcode":"99096",
    "sg:province":"Th\u00fcringen",
    "wof:name":"Bistro Sunshine",
    "wof:placetype":"venue"
},
  "geometry": {"coordinates":[11.0416889191,50.9648475647],"type":"Point"}
}