{
  "type": "Feature",
  "properties": {
    "iso:country":"DE",
    "sg:address":"Siemensstr. 9",
    "sg:city":"N\u00fcrtingen",
    "sg:phone":"+49 7022/969712",
    "sg:postcode":"72622",
    "sg:province":"Baden-W\u00fcrttemberg",
    "wof:name":"Sanib\u00e4r F\u00fcr Heizung Bad Und Vieles Mehr",
    "wof:placetype":"venue"
},
  "geometry": {"coordinates":[9.352588,48.644398],"type":"Point"}
}