{
  "type": "Feature",
  "properties": {
    "iso:country":"DE",
    "sg:address":"Reichenbacher Str. 8",
    "sg:city":"Aalen",
    "sg:phone":"+49 7366/5678",
    "sg:postcode":"73434",
    "sg:province":"Baden-W\u00fcrttemberg",
    "wof:name":"M\u00fcller Gmbh Drogerie",
    "wof:placetype":"venue"
},
  "geometry": {"coordinates":[10.021242,48.870949],"type":"Point"}
}