{
  "type": "Feature",
  "properties": {
    "iso:country":"DE",
    "sg:address":"Gau\u00dfstr 2-4",
    "sg:city":"Lehrte",
    "sg:phone":"+49 5132/20060",
    "sg:postcode":"31275",
    "sg:province":"Niedersachsen",
    "wof:name":"Michalek Gmbh",
    "wof:placetype":"venue"
},
  "geometry": {"coordinates":[9.9912900925,52.3727798462],"type":"Point"}
}