{
  "type": "Feature",
  "properties": {
    "iso:country":"DE",
    "sg:address":"Hauptstr. 1",
    "sg:city":"Sulzbach",
    "sg:phone":"+49 6544/1307",
    "sg:postcode":"55758",
    "sg:province":"Rheinland-Pfalz",
    "wof:name":"Otto Jung",
    "wof:placetype":"venue"
},
  "geometry": {"coordinates":[7.335743,49.837132],"type":"Point"}
}