{
  "type": "Feature",
  "properties": {
    "iso:country":"DE",
    "sg:address":"Brennerstr. 13",
    "sg:city":"Rosenheim",
    "sg:phone":"+49 8031/41155",
    "sg:postcode":"83024",
    "sg:province":"Bayern",
    "wof:name":"Highlander",
    "wof:placetype":"venue"
},
  "geometry": {"coordinates":[12.101769,47.86132],"type":"Point"}
}