{
  "type": "Feature",
  "properties": {
    "iso:country":"DE",
    "sg:address":"Am Wiesengrund 2",
    "sg:city":"Deisenhausen",
    "sg:phone":"+49 8282/3176",
    "sg:postcode":"86489",
    "sg:province":"Bayern",
    "wof:name":"Josef Dreier",
    "wof:placetype":"venue"
},
  "geometry": {"coordinates":[10.3324403763,48.2547264099],"type":"Point"}
}