{
  "type": "Feature",
  "properties": {
    "iso:country":"DE",
    "sg:address":"Wackersdorfer Str. 84",
    "sg:city":"Schwandorf",
    "sg:phone":"+49 9431/8686",
    "sg:postcode":"92421",
    "sg:province":"Bayern",
    "wof:name":"S. Dornhauser",
    "wof:placetype":"venue"
},
  "geometry": {"coordinates":[12.1290197372,49.3220405579],"type":"Point"}
}