{
  "type": "Feature",
  "properties": {
    "iso:country":"DE",
    "sg:address":"Messe-Allee 2",
    "sg:city":"Leipzig",
    "sg:phone":"+49 341/6003731",
    "sg:postcode":"04356",
    "sg:province":"Sachsen",
    "wof:name":"K & R Internationale Handelsgesellschaft Kg",
    "wof:placetype":"venue"
},
  "geometry": {"coordinates":[12.395957,51.394341],"type":"Point"}
}