{
  "type": "Feature",
  "properties": {
    "iso:country":"DE",
    "sg:address":"Hauptstr. 160",
    "sg:city":"Reilingen",
    "sg:phone":"+49 6205/4725",
    "sg:postcode":"68799",
    "sg:province":"Baden-W\u00fcrttemberg",
    "wof:name":"R\u00f6tls",
    "wof:placetype":"venue"
},
  "geometry": {"coordinates":[8.565121,49.290848],"type":"Point"}
}