{
  "type": "Feature",
  "properties": {
    "iso:country":"DE",
    "sg:address":"Hauptstr. 63",
    "sg:city":"B\u00fchl",
    "sg:phone":"+49 7223/98280",
    "sg:postcode":"77815",
    "sg:province":"Baden-W\u00fcrttemberg",
    "wof:name":"R\u00fcdiger Schmith Und Eckhard Sch\u00fctt",
    "wof:placetype":"venue"
},
  "geometry": {"coordinates":[8.1365203857,48.6967048645],"type":"Point"}
}