{
  "type": "Feature",
  "properties": {
    "iso:country":"DE",
    "sg:address":"Bahnhofstr. 45",
    "sg:city":"Beverungen",
    "sg:phone":"+49 5273/1248",
    "sg:postcode":"37688",
    "sg:province":"Nordrhein-Westfalen",
    "wof:name":"Jos. Nolte & Sohn",
    "wof:placetype":"venue"
},
  "geometry": {"coordinates":[9.374787,51.670715],"type":"Point"}
}