{
  "type": "Feature",
  "properties": {
    "iso:country":"DE",
    "sg:address":"Ahnatalstr. 162",
    "sg:city":"Kassel",
    "sg:phone":"+49 561/62056",
    "sg:postcode":"34128",
    "sg:province":"Hessen",
    "wof:name":"Sonnenhang-seniorenheime",
    "wof:placetype":"venue"
},
  "geometry": {"coordinates":[9.416747,51.335453],"type":"Point"}
}