{
  "type": "Feature",
  "properties": {
    "iso:country":"DE",
    "sg:address":"Friedrich-Ludwig-Jahn-Str. 51",
    "sg:city":"Lenzen",
    "sg:phone":"+49 38792/7646",
    "sg:postcode":"19309",
    "sg:province":"Brandenburg",
    "wof:name":"Manfred Werner",
    "wof:placetype":"venue"
},
  "geometry": {"coordinates":[11.4747076035,53.0905914307],"type":"Point"}
}