{
  "type": "Feature",
  "properties": {
    "iso:country":"DE",
    "sg:address":"Ostertor 1",
    "sg:city":"Lemgo",
    "sg:phone":"+49 5261/16447",
    "sg:postcode":"32657",
    "sg:province":"Nordrhein-Westfalen",
    "wof:name":"Bistro Pulverturm",
    "wof:placetype":"venue"
},
  "geometry": {"coordinates":[8.9069862366,52.0277442932],"type":"Point"}
}