{
  "type": "Feature",
  "properties": {
    "iso:country":"DE",
    "sg:address":"Tr\u00f6bitzer Str. 74",
    "sg:city":"Prie\u00dfen",
    "sg:phone":"+49 35327/340",
    "sg:postcode":"03253",
    "sg:province":"Brandenburg",
    "wof:name":"Axel G\u00fcnther",
    "wof:placetype":"venue"
},
  "geometry": {"coordinates":[13.436715126,51.6572418213],"type":"Point"}
}