{
  "type": "Feature",
  "properties": {
    "iso:country":"DE",
    "sg:address":"Beusselstra\u00dfe 64",
    "sg:city":"Berlin",
    "sg:phone":"+49 30/3918318",
    "sg:postcode":"10553",
    "sg:province":"Berlin",
    "wof:name":"Nix Gmbh",
    "wof:placetype":"venue"
},
  "geometry": {"coordinates":[13.328403,52.529156],"type":"Point"}
}