{
  "type": "Feature",
  "properties": {
    "iso:country":"DE",
    "sg:address":"Gro\u00dfbottwarer Str. 25",
    "sg:city":"Oberstenfeld",
    "sg:phone":"+49 7062/21917",
    "sg:postcode":"71720",
    "sg:province":"Baden-W\u00fcrttemberg",
    "wof:name":"Gasthof Kupferd\u00e4chle",
    "wof:placetype":"venue"
},
  "geometry": {"coordinates":[9.3194046021,49.023727417],"type":"Point"}
}