{
  "type": "Feature",
  "properties": {
    "iso:country":"DE",
    "sg:address":"Kreuzstr. 8",
    "sg:city":"Ingolstadt",
    "sg:phone":"+49 841/910744",
    "sg:postcode":"85049",
    "sg:province":"Bayern",
    "wof:name":"Bernd M\u00f6ding",
    "wof:placetype":"venue"
},
  "geometry": {"coordinates":[11.419839859,48.7638244629],"type":"Point"}
}