{
  "type": "Feature",
  "properties": {
    "iso:country":"DE",
    "sg:address":"Bergstr. 11",
    "sg:city":"Ottensoos",
    "sg:phone":"+49 9123/4674",
    "sg:postcode":"91242",
    "sg:province":"Bayern",
    "wof:name":"W. B\u00e4r Architekt",
    "wof:placetype":"venue"
},
  "geometry": {"coordinates":[11.337128,49.50658],"type":"Point"}
}