{
  "type": "Feature",
  "properties": {
    "iso:country":"DE",
    "sg:address":"Hochemmericher Str. 56",
    "sg:city":"Duisburg",
    "sg:phone":"+49 2065/58533",
    "sg:postcode":"47226",
    "sg:province":"Nordrhein-Westfalen",
    "wof:name":"Rudolf Kr\u00e4mer Eisenwaren Gmbh",
    "wof:placetype":"venue"
},
  "geometry": {"coordinates":[6.718139,51.411366],"type":"Point"}
}