{
  "type": "Feature",
  "properties": {
    "iso:country":"DE",
    "sg:address":"Pf\u00e4lzer Str. 58",
    "sg:city":"K\u00f6ln",
    "sg:postcode":"50677",
    "sg:province":"Nordrhein-Westfalen",
    "wof:name":"Massiv K\u00fcchen & Mehr Gmbh",
    "wof:placetype":"venue"
},
  "geometry": {"coordinates":[6.9420862198,50.9273834229],"type":"Point"}
}