{
  "type": "Feature",
  "properties": {
    "iso:country":"DE",
    "sg:address":"L\u00fcnener Str. 128",
    "sg:city":"Hamm",
    "sg:phone":"+49 2381/998810",
    "sg:postcode":"59077",
    "sg:province":"Nordrhein-Westfalen",
    "wof:name":"G\u00fcnter Krause Architekt",
    "wof:placetype":"venue"
},
  "geometry": {"coordinates":[7.738192,51.67202],"type":"Point"}
}