{
  "type": "Feature",
  "properties": {
    "iso:country":"DE",
    "sg:address":"Unterer Markt 30",
    "sg:city":"Auerbach",
    "sg:phone":"+49 9643/91185",
    "sg:postcode":"91275",
    "sg:province":"Bayern",
    "wof:name":"Karl Trenz",
    "wof:placetype":"venue"
},
  "geometry": {"coordinates":[11.6291179657,49.6933708191],"type":"Point"}
}