{
  "type": "Feature",
  "properties": {
    "iso:country":"DE",
    "sg:address":"Buntenskamp 10",
    "sg:city":"Geesthacht",
    "sg:phone":"+49 4152/841222",
    "sg:postcode":"21502",
    "sg:province":"Schleswig-Holstein",
    "wof:name":"Hueseyin Celik",
    "wof:placetype":"venue"
},
  "geometry": {"coordinates":[10.3731794357,53.4340324402],"type":"Point"}
}