{
  "type": "Feature",
  "properties": {
    "iso:country":"DE",
    "sg:address":"Bernstadt",
    "sg:city":"Bernstadt",
    "sg:phone":"+49 4973/485454",
    "sg:postcode":"89182",
    "sg:province":"Baden-W\u00fcrttemberg",
    "wof:name":"Langenauer Bank Eg",
    "wof:placetype":"venue"
},
  "geometry": {"coordinates":[10.02676,48.499352],"type":"Point"}
}