{
  "type": "Feature",
  "properties": {
    "iso:country":"DE",
    "sg:address":"Rader Str. 48",
    "sg:city":"Remscheid",
    "sg:phone":"+49 2191/62034",
    "sg:postcode":"42897",
    "sg:province":"Nordrhein-Westfalen",
    "wof:name":"Hoffmann",
    "wof:placetype":"venue"
},
  "geometry": {"coordinates":[7.277589798,51.1901702881],"type":"Point"}
}