{
  "type": "Feature",
  "properties": {
    "iso:country":"DE",
    "sg:address":"Langenpreisinger Str. 46",
    "sg:city":"M\u00fcnchen",
    "sg:phone":"+49 89/31215945",
    "sg:postcode":"80995",
    "sg:province":"Bayern",
    "wof:name":"Wkt Kunststofftechnologie - Rechteverwertungs Gmbh",
    "wof:placetype":"venue"
},
  "geometry": {"coordinates":[11.5468711853,48.2121047974],"type":"Point"}
}