{
  "type": "Feature",
  "properties": {
    "iso:country":"DE",
    "sg:address":"Brunnenweg 3",
    "sg:city":"Lo\u00dfburg",
    "sg:phone":"+49 7446/1830",
    "sg:postcode":"72290",
    "sg:province":"Baden-W\u00fcrttemberg",
    "wof:name":"Heimatmuseum Lo\u00dfburg",
    "wof:placetype":"venue"
},
  "geometry": {"coordinates":[8.453866,48.411877],"type":"Point"}
}