{
  "type": "Feature",
  "properties": {
    "iso:country":"DE",
    "sg:address":"Zeiss-Stra\u00dfe 13",
    "sg:city":"Velbert",
    "sg:phone":"+49 2051/28930",
    "sg:postcode":"42551",
    "sg:province":"Nordrhein-Westfalen",
    "wof:name":"Dahms Gmbh - Mess-, Regel-, Steuer- & Anzeigegr\u00e4te",
    "wof:placetype":"venue"
},
  "geometry": {"coordinates":[7.07906,51.35191],"type":"Point"}
}