{
  "type": "Feature",
  "properties": {
    "iso:country":"DE",
    "sg:address":"Friedensstr. 20",
    "sg:city":"Obertshausen",
    "sg:phone":"+49 6104/98080",
    "sg:postcode":"63179",
    "sg:province":"Hessen",
    "wof:name":"Cas Gmbh",
    "wof:placetype":"venue"
},
  "geometry": {"coordinates":[8.8614940643,50.076877594],"type":"Point"}
}