{
  "type": "Feature",
  "properties": {
    "iso:country":"DE",
    "sg:address":"Schlo\u00dfstr. 5",
    "sg:city":"Meitingen",
    "sg:phone":"+49 8271/6021",
    "sg:postcode":"86405",
    "sg:province":"Bayern",
    "wof:name":"Hans-joachim Pl\u00f6ssel Masseur",
    "wof:placetype":"venue"
},
  "geometry": {"coordinates":[10.85363,48.541718],"type":"Point"}
}