{
  "type": "Feature",
  "properties": {
    "iso:country":"DE",
    "sg:address":"Hauptstr. 21",
    "sg:city":"Ro\u00dfhaupten",
    "sg:phone":"+49 8367/349",
    "sg:postcode":"87672",
    "sg:province":"Bayern",
    "wof:name":"Heidrun Hartmann",
    "wof:placetype":"venue"
},
  "geometry": {"coordinates":[10.7185115814,47.6525726318],"type":"Point"}
}