{
  "type": "Feature",
  "properties": {
    "iso:country":"DE",
    "sg:address":"Platzhoffstr. 19",
    "sg:city":"Wuppertal",
    "sg:phone":"+49 202/313260",
    "sg:postcode":"42115",
    "sg:province":"Nordrhein-Westfalen",
    "wof:name":"Bruno Und Manfred K\u00f6pchen",
    "wof:placetype":"venue"
},
  "geometry": {"coordinates":[7.1302700043,51.2561454773],"type":"Point"}
}