{
  "type": "Feature",
  "properties": {
    "iso:country":"DE",
    "sg:address":"Schulgasse 2",
    "sg:city":"Tann",
    "sg:phone":"+49 8572/8564",
    "sg:postcode":"84367",
    "sg:province":"Bayern",
    "wof:name":"Hedwig Ortmaier",
    "wof:placetype":"venue"
},
  "geometry": {"coordinates":[12.891822,48.314556],"type":"Point"}
}