{
  "type": "Feature",
  "properties": {
    "iso:country":"DE",
    "sg:address":"S\u00fcdring 39",
    "sg:city":"Raesfeld",
    "sg:phone":"+49 2865/7553",
    "sg:postcode":"46348",
    "sg:province":"Nordrhein-Westfalen",
    "wof:name":"Karl-heinz Beck",
    "wof:placetype":"venue"
},
  "geometry": {"coordinates":[6.8402099609,51.765663147],"type":"Point"}
}