{
  "type": "Feature",
  "properties": {
    "iso:country":"DE",
    "sg:address":"Pferdekamp 3",
    "sg:city":"Hamm",
    "sg:phone":"+49 2381/972020",
    "sg:postcode":"59075",
    "sg:province":"Nordrhein-Westfalen",
    "wof:name":"Wenthaus Baugesellschaft Mbh",
    "wof:placetype":"venue"
},
  "geometry": {"coordinates":[7.773489,51.698383],"type":"Point"}
}