{
  "type": "Feature",
  "properties": {
    "iso:country":"DE",
    "sg:address":"Isarstr. 8",
    "sg:city":"Baierbrunn",
    "sg:phone":"+49 89/7933637",
    "sg:postcode":"82065",
    "sg:province":"Bayern",
    "wof:name":"Christine G\u00f6nnheimer",
    "wof:placetype":"venue"
},
  "geometry": {"coordinates":[11.4933538437,48.0278625488],"type":"Point"}
}