{
  "type": "Feature",
  "properties": {
    "iso:country":"DE",
    "sg:address":"Grassinger Str. 29",
    "sg:city":"Bad Aibling",
    "sg:phone":"+49 8061/4160",
    "sg:postcode":"83043",
    "sg:province":"Bayern",
    "wof:name":"Balthasar Stacheder",
    "wof:placetype":"venue"
},
  "geometry": {"coordinates":[11.995538,47.870754],"type":"Point"}
}