{
  "type": "Feature",
  "properties": {
    "iso:country":"DE",
    "sg:address":"Klingelbergstr. 5",
    "sg:city":"Gaggenau",
    "sg:phone":"+49 7224/1719",
    "sg:postcode":"76571",
    "sg:province":"Baden-W\u00fcrttemberg",
    "wof:name":"R. Kast",
    "wof:placetype":"venue"
},
  "geometry": {"coordinates":[8.3445,48.781166],"type":"Point"}
}