{
  "type": "Feature",
  "properties": {
    "iso:country":"DE",
    "sg:address":"Tammichstr. 40",
    "sg:city":"Tambach-Dietharz",
    "sg:phone":"+49 36252/36731",
    "sg:postcode":"99897",
    "sg:province":"Th\u00fcringen",
    "wof:name":"Restaurant Lutherst\u00fcbchen",
    "wof:placetype":"venue"
},
  "geometry": {"coordinates":[10.6031103134,50.7865486145],"type":"Point"}
}