{
  "type": "Feature",
  "properties": {
    "iso:country":"DE",
    "sg:address":"Ophovener Str. 48",
    "sg:city":"Leverkusen",
    "sg:phone":"+49 214/59341",
    "sg:postcode":"51375",
    "sg:province":"Nordrhein-Westfalen",
    "wof:name":"Elektro Eckardt Gmbh",
    "wof:placetype":"venue"
},
  "geometry": {"coordinates":[7.057346,51.042877],"type":"Point"}
}