{
  "type": "Feature",
  "properties": {
    "iso:country":"DE",
    "sg:address":"Kokenm\u00fchlenstr. 15",
    "sg:city":"Nordhorn",
    "sg:phone":"+49 5921/80190",
    "sg:postcode":"48529",
    "sg:province":"Niedersachsen",
    "wof:name":"Dr. Hewig Und St\u00fcrmann Rechtsanw\u00e4lte Und Notare",
    "wof:placetype":"venue"
},
  "geometry": {"coordinates":[7.0720911026,52.4335594177],"type":"Point"}
}