{
  "type": "Feature",
  "properties": {
    "iso:country":"DE",
    "sg:address":"Im Ziegelhaus 14",
    "sg:city":"Gelnhausen",
    "sg:phone":"+49 6051/17137",
    "sg:postcode":"63571",
    "sg:province":"Hessen",
    "wof:name":"Idea Die Gr\u00fcne Drogerie Gmbh",
    "wof:placetype":"venue"
},
  "geometry": {"coordinates":[9.190679,50.198483],"type":"Point"}
}