{
  "type": "Feature",
  "properties": {
    "iso:country":"DE",
    "sg:address":"Wilmsmannstr. 14a",
    "sg:city":"Dortmund",
    "sg:phone":"+49 231/2008010",
    "sg:postcode":"44269",
    "sg:province":"Nordrhein-Westfalen",
    "wof:name":"Sk Kurier",
    "wof:placetype":"venue"
},
  "geometry": {"coordinates":[7.521821,51.476891],"type":"Point"}
}