{
  "type": "Feature",
  "properties": {
    "iso:country":"DE",
    "sg:address":"Im Steingew\u00e4nde 11",
    "sg:city":"Magdeburg",
    "sg:phone":"+49 391/289490",
    "sg:postcode":"39126",
    "sg:province":"Sachsen-Anhalt",
    "wof:name":"Oheim K\u00fchlraumbau Gmbh",
    "wof:placetype":"venue"
},
  "geometry": {"coordinates":[11.639886,52.169502],"type":"Point"}
}