{
  "type": "Feature",
  "properties": {
    "iso:country":"DE",
    "sg:address":"Pasewalker Allee 23",
    "sg:city":"Anklam",
    "sg:postcode":"17389",
    "sg:province":"Mecklenburg-Vorpommern",
    "wof:name":"A. Tschoppe Architekt",
    "wof:placetype":"venue"
},
  "geometry": {"coordinates":[13.703931,53.852097],"type":"Point"}
}