{
  "type": "Feature",
  "properties": {
    "iso:country":"DE",
    "sg:address":"Beukenbergstr. 12-14",
    "sg:city":"Dortmund",
    "sg:postcode":"44263",
    "sg:province":"Nordrhein-Westfalen",
    "wof:name":"Grundst\u00fccksgesellschaft Altwickeder",
    "wof:placetype":"venue"
},
  "geometry": {"coordinates":[7.4960408211,51.4876174927],"type":"Point"}
}