{
  "type": "Feature",
  "properties": {
    "iso:country":"DE",
    "sg:address":"Schlipperhaus 3",
    "sg:city":"Ratingen",
    "sg:phone":"+49 2102/67639",
    "sg:postcode":"40883",
    "sg:province":"Nordrhein-Westfalen",
    "wof:name":"Gp Grundbesitz Gmbh",
    "wof:placetype":"venue"
},
  "geometry": {"coordinates":[6.903768,51.328274],"type":"Point"}
}