{
  "type": "Feature",
  "properties": {
    "iso:country":"DE",
    "sg:address":"Achtstr 4",
    "sg:city":"M\u00f6rschied",
    "sg:phone":"+49 6785/286",
    "sg:postcode":"55758",
    "sg:province":"Rheinland-Pfalz",
    "wof:name":"Albert Grimm",
    "wof:placetype":"venue"
},
  "geometry": {"coordinates":[7.311360836,49.7895965576],"type":"Point"}
}