{
  "type": "Feature",
  "properties": {
    "iso:country":"DE",
    "sg:address":"Wilhelm-Maigatter-Weg 1",
    "sg:city":"Dachau",
    "sg:phone":"+49 8131/56590",
    "sg:postcode":"85221",
    "sg:province":"Bayern",
    "wof:name":"Edition Aum Gmbh",
    "wof:placetype":"venue"
},
  "geometry": {"coordinates":[11.4229898453,48.2465515137],"type":"Point"}
}