{
  "type": "Feature",
  "properties": {
    "iso:country":"DE",
    "sg:address":"Werner-Petzold-Str. 27",
    "sg:city":"Gera",
    "sg:phone":"+49 365/35169",
    "sg:postcode":"07549",
    "sg:province":"Th\u00fcringen",
    "wof:name":"Claudia Walter Masseurin",
    "wof:placetype":"venue"
},
  "geometry": {"coordinates":[12.061305,50.84016],"type":"Point"}
}