{
  "type": "Feature",
  "properties": {
    "iso:country":"DE",
    "sg:address":"Goethestr. 2",
    "sg:city":"Aldingen",
    "sg:phone":"+49 7424/1513",
    "sg:postcode":"78554",
    "sg:province":"Baden-W\u00fcrttemberg",
    "wof:name":"Albert Mauch",
    "wof:placetype":"venue"
},
  "geometry": {"coordinates":[8.6693429947,48.108379364],"type":"Point"}
}