{
  "type": "Feature",
  "properties": {
    "iso:country":"DE",
    "sg:address":"Vo\u00dfstr. 125-127",
    "sg:city":"Sarstedt",
    "sg:phone":"+49 5066/98160",
    "sg:postcode":"31157",
    "sg:province":"Niedersachsen",
    "wof:name":"Spedition P\u00f6nsgen Gmbh Zweigniederlassung Sarstedt",
    "wof:placetype":"venue"
},
  "geometry": {"coordinates":[9.8396120071,52.2221031189],"type":"Point"}
}