{
  "type": "Feature",
  "properties": {
    "iso:country":"DE",
    "sg:address":"Damwildsteig 45",
    "sg:city":"Berlin",
    "sg:phone":"+49 30/4318833",
    "sg:postcode":"13503",
    "sg:province":"Berlin",
    "wof:name":"K. Parlar Ingenieur",
    "wof:placetype":"venue"
},
  "geometry": {"coordinates":[13.2395439148,52.6007919312],"type":"Point"}
}