{
  "type": "Feature",
  "properties": {
    "iso:country":"DE",
    "sg:address":"K\u00f6rtlinghausen",
    "sg:city":"R\u00fcthen",
    "sg:phone":"+49 2902/57366",
    "sg:postcode":"59602",
    "sg:province":"Nordrhein-Westfalen",
    "wof:name":"Biohof Gyso Von Bonin",
    "wof:placetype":"venue"
},
  "geometry": {"coordinates":[8.409093,51.462124],"type":"Point"}
}