{
  "type": "Feature",
  "properties": {
    "iso:country":"DE",
    "sg:address":"Schillerplatz 1",
    "sg:city":"Saarbr\u00fccken",
    "sg:phone":"+49 681/30920",
    "sg:postcode":"66111",
    "sg:province":"Saarland",
    "wof:name":"Saarl\u00e4ndisches Staatstheater Gmbh",
    "wof:placetype":"venue"
},
  "geometry": {"coordinates":[6.9964189529,49.2311935425],"type":"Point"}
}