{
  "type": "Feature",
  "properties": {
    "iso:country":"DE",
    "sg:address":"Zum Greffling 5",
    "sg:city":"Finnentrop",
    "sg:phone":"+49 2721/70654",
    "sg:postcode":"57413",
    "sg:province":"Nordrhein-Westfalen",
    "wof:name":"Franz Vogt & Sohn Inh. Franz Bernhard Vogt",
    "wof:placetype":"venue"
},
  "geometry": {"coordinates":[8.012219,51.191288],"type":"Point"}
}