{
  "type": "Feature",
  "properties": {
    "iso:country":"DE",
    "sg:address":"Kunigundenstr. 14",
    "sg:city":"Baiersdorf",
    "sg:phone":"+49 9133/600751",
    "sg:postcode":"91083",
    "sg:province":"Bayern",
    "wof:name":"Volkskunst Und Informationen Aus Der Mongolei",
    "wof:placetype":"venue"
},
  "geometry": {"coordinates":[11.036951,49.660305],"type":"Point"}
}