{
  "type": "Feature",
  "properties": {
    "iso:country":"DE",
    "sg:address":"Charlottenstr. 53",
    "sg:city":"Essen",
    "sg:phone":"+49 201/570191",
    "sg:postcode":"45289",
    "sg:province":"Nordrhein-Westfalen",
    "wof:name":"Aloys Schmidt",
    "wof:placetype":"venue"
},
  "geometry": {"coordinates":[7.101274,51.423702],"type":"Point"}
}