{
  "type": "Feature",
  "properties": {
    "iso:country":"DE",
    "sg:address":"Am Sparrenberg 5",
    "sg:city":"Bielefeld",
    "sg:phone":"+49 521/967530",
    "sg:postcode":"33602",
    "sg:province":"Nordrhein-Westfalen",
    "wof:name":"Schweizerische Ag",
    "wof:placetype":"venue"
},
  "geometry": {"coordinates":[8.5262699127,52.0169181824],"type":"Point"}
}