{
  "type": "Feature",
  "properties": {
    "iso:country":"DE",
    "sg:address":"Unter den Eichen 16",
    "sg:city":"Bad Marienberg",
    "sg:phone":"+49 2661/62630",
    "sg:postcode":"56470",
    "sg:province":"Rheinland-Pfalz",
    "wof:name":"Schmehmann Rohrschlangenwerk Gmbh",
    "wof:placetype":"venue"
},
  "geometry": {"coordinates":[7.9516,50.656746],"type":"Point"}
}