{
  "type": "Feature",
  "properties": {
    "iso:country":"DE",
    "sg:address":"Fernewaldstr. 363",
    "sg:city":"Bottrop",
    "sg:phone":"+49 2041/93224",
    "sg:postcode":"46242",
    "sg:province":"Nordrhein-Westfalen",
    "wof:name":"Neue Arbeit Bottrop Dorsten Gladbeck Gemeinn. Ges. Z. Be-",
    "wof:placetype":"venue"
},
  "geometry": {"coordinates":[6.8867001534,51.5428733826],"type":"Point"}
}