{
  "type": "Feature",
  "properties": {
    "iso:country":"DE",
    "sg:address":"Vilbeler Landstr. 55",
    "sg:city":"Frankfurt",
    "sg:phone":"+49 6109/73460",
    "sg:postcode":"60388",
    "sg:province":"Hessen",
    "wof:name":"Hotel Klein Gmbh",
    "wof:placetype":"venue"
},
  "geometry": {"coordinates":[8.753657341,50.1436195374],"type":"Point"}
}