{
  "type": "Feature",
  "properties": {
    "iso:country":"DE",
    "sg:address":"Rathausplatz 4",
    "sg:city":"Waldstetten",
    "sg:phone":"+49 8223/3966",
    "sg:postcode":"89367",
    "sg:province":"Bayern",
    "wof:name":"Rudolf Steib",
    "wof:placetype":"venue"
},
  "geometry": {"coordinates":[10.2921180725,48.3479270935],"type":"Point"}
}