{
  "type": "Feature",
  "properties": {
    "iso:country":"DE",
    "sg:address":"Veilchenstr. 18",
    "sg:city":"Linkenheim-Hochstetten",
    "sg:phone":"+49 7247/4806",
    "sg:postcode":"76351",
    "sg:province":"Baden-W\u00fcrttemberg",
    "wof:name":"J\u00fcrgen Tennert",
    "wof:placetype":"venue"
},
  "geometry": {"coordinates":[8.414229,49.115685],"type":"Point"}
}