{
  "type": "Feature",
  "properties": {
    "iso:country":"DE",
    "sg:address":"Mainstr. 35",
    "sg:city":"M\u00fchlheim",
    "sg:phone":"+49 6108/76165",
    "sg:postcode":"63165",
    "sg:province":"Hessen",
    "wof:name":"Emil Heberer",
    "wof:placetype":"venue"
},
  "geometry": {"coordinates":[8.828159,50.129143],"type":"Point"}
}