{
  "type": "Feature",
  "properties": {
    "iso:country":"DE",
    "sg:address":"Hinter der Post 4-8",
    "sg:city":"Leipheim",
    "sg:postcode":"89340",
    "sg:province":"Bayern",
    "wof:name":"Br\u00fcder Siegel Gmbh",
    "wof:placetype":"venue"
},
  "geometry": {"coordinates":[10.2188501358,48.4515342712],"type":"Point"}
}