{
  "type": "Feature",
  "properties": {
    "iso:country":"DE",
    "sg:address":"Rosenstr. 61",
    "sg:city":"Bad Bramstedt",
    "sg:phone":"+49 4192/3168",
    "sg:postcode":"24576",
    "sg:province":"Schleswig-Holstein",
    "wof:name":"Dr. Med. Jens Alnor",
    "wof:placetype":"venue"
},
  "geometry": {"coordinates":[9.8854341507,53.9223594666],"type":"Point"}
}