{
  "type": "Feature",
  "properties": {
    "iso:country":"DE",
    "sg:address":"Graudenzstr. 1-3",
    "sg:city":"K\u00f6ln",
    "sg:phone":"+49 2203/35437",
    "sg:postcode":"51145",
    "sg:province":"Nordrhein-Westfalen",
    "wof:name":"B\u00fcroservice Gabriele Koch",
    "wof:placetype":"venue"
},
  "geometry": {"coordinates":[7.068466,50.894989],"type":"Point"}
}