{
  "type": "Feature",
  "properties": {
    "iso:country":"DE",
    "sg:address":"Lettow-Vorbeck-Str. 2",
    "sg:city":"M\u00f6nchengladbach",
    "sg:phone":"+49 2161/26992",
    "sg:postcode":"41063",
    "sg:province":"Nordrhein-Westfalen",
    "wof:name":"Peter Wolff",
    "wof:placetype":"venue"
},
  "geometry": {"coordinates":[6.436797,51.202007],"type":"Point"}
}