{
  "type": "Feature",
  "properties": {
    "iso:country":"DE",
    "sg:address":"Atlasstr. 6",
    "sg:city":"Ganderkesee",
    "sg:phone":"+49 4222/9540",
    "sg:postcode":"27777",
    "sg:province":"Niedersachsen",
    "wof:name":"Atlas Weyhausen Gmbh",
    "wof:placetype":"venue"
},
  "geometry": {"coordinates":[8.538399,53.033436],"type":"Point"}
}