{
  "type": "Feature",
  "properties": {
    "iso:country":"DE",
    "sg:address":"Am Neunm\u00fchlental 2",
    "sg:city":"Oelsnitz",
    "sg:phone":"+49 37421/22159",
    "sg:postcode":"08606",
    "sg:province":"Sachsen",
    "wof:name":"Siegmar Steinm\u00fcller Raumausstatter",
    "wof:placetype":"venue"
},
  "geometry": {"coordinates":[12.1997356415,50.4015922546],"type":"Point"}
}