{
  "type": "Feature",
  "properties": {
    "iso:country":"DE",
    "sg:address":"Friedberger Landstr. 54",
    "sg:city":"Frankfurt",
    "sg:phone":"+49 69/434372",
    "sg:postcode":"60316",
    "sg:province":"Hessen",
    "wof:name":"Schreinerei Friedrich Gmbh",
    "wof:placetype":"venue"
},
  "geometry": {"coordinates":[8.691125,50.121647],"type":"Point"}
}