{
  "type": "Feature",
  "properties": {
    "iso:country":"DE",
    "sg:address":"Magdeburger Str. 21",
    "sg:city":"Leipzig",
    "sg:postcode":"04155",
    "sg:province":"Sachsen",
    "wof:name":"Ramses Dienstleistungs Gmbh",
    "wof:placetype":"venue"
},
  "geometry": {"coordinates":[12.362794,51.365231],"type":"Point"}
}