{
  "type": "Feature",
  "properties": {
    "iso:country":"DE",
    "sg:address":"Edelsheimstra\u00dfe 7",
    "sg:city":"Karlsruhe",
    "sg:phone":"+49 721",
    "sg:postcode":"76131",
    "sg:province":"Baden-W\u00fcrttemberg",
    "wof:name":"Gorgy Timing Gmbh",
    "wof:placetype":"venue"
},
  "geometry": {"coordinates":[8.4240083694,49.0135307312],"type":"Point"}
}