{
  "type": "Feature",
  "properties": {
    "iso:country":"DE",
    "sg:address":"Am Reichswald 7",
    "sg:city":"Altdorf",
    "sg:phone":"+49 9187/1474",
    "sg:postcode":"90518",
    "sg:province":"Bayern",
    "wof:name":"A.-r. Gaidies Heilpraktiker",
    "wof:placetype":"venue"
},
  "geometry": {"coordinates":[11.3374042511,49.4039955139],"type":"Point"}
}