{
  "type": "Feature",
  "properties": {
    "iso:country":"DE",
    "sg:address":"Schlesierstr 2",
    "sg:city":"Guxhagen",
    "sg:phone":"+49 5665/404990",
    "sg:postcode":"34302",
    "sg:province":"Hessen",
    "wof:name":"Dj Hep",
    "wof:placetype":"venue"
},
  "geometry": {"coordinates":[9.484389,51.201469],"type":"Point"}
}