{
  "type": "Feature",
  "properties": {
    "iso:country":"DE",
    "sg:address":"B\u00f6rgerstr. 17",
    "sg:city":"Neub\u00f6rger",
    "sg:phone":"+49 4966/656",
    "sg:postcode":"26909",
    "sg:province":"Niedersachsen",
    "wof:name":"Thekla \u00dcmken",
    "wof:placetype":"venue"
},
  "geometry": {"coordinates":[7.450498,52.946697],"type":"Point"}
}