{
  "type": "Feature",
  "properties": {
    "iso:country":"DE",
    "sg:address":"Weberstr. 44",
    "sg:city":"Gelsenkirchen",
    "sg:phone":"+49 209/274586",
    "sg:postcode":"45879",
    "sg:province":"Nordrhein-Westfalen",
    "wof:name":"E. Santos-diaz",
    "wof:placetype":"venue"
},
  "geometry": {"coordinates":[7.100062,51.508953],"type":"Point"}
}