{
  "type": "Feature",
  "properties": {
    "iso:country":"DE",
    "sg:address":"Engelbergweg 27",
    "sg:city":"Gro\u00dfheubach",
    "sg:phone":"+49 9371/80028",
    "sg:postcode":"63920",
    "sg:province":"Bayern",
    "wof:name":"Marietta Brand Steuerberaterin",
    "wof:placetype":"venue"
},
  "geometry": {"coordinates":[9.2287368774,49.723575592],"type":"Point"}
}