{
  "type": "Feature",
  "properties": {
    "iso:country":"DE",
    "sg:address":"K\u00f6thener Str 1",
    "sg:city":"Wei\u00dfandt-G\u00f6lzau",
    "sg:phone":"+49 34978/30510",
    "sg:postcode":"06369",
    "sg:province":"Sachsen-Anhalt",
    "wof:name":"Vta Gesellschaft F\u00fcr Verfahrenstechnik Und Apparatebau Mbh",
    "wof:placetype":"venue"
},
  "geometry": {"coordinates":[12.077068,51.670895],"type":"Point"}
}