{
  "type": "Feature",
  "properties": {
    "iso:country":"DE",
    "sg:address":"Friesenplatz 5",
    "sg:city":"K\u00f6ln",
    "sg:phone":"+49 221/2574828",
    "sg:postcode":"50672",
    "sg:province":"Nordrhein-Westfalen",
    "wof:name":"American-stock",
    "wof:placetype":"venue"
},
  "geometry": {"coordinates":[6.939019,50.940548],"type":"Point"}
}