{
  "type": "Feature",
  "properties": {
    "iso:country":"DE",
    "sg:address":"Nahering 3",
    "sg:city":"Ingelheim",
    "sg:phone":"+49 6132/897070",
    "sg:postcode":"55218",
    "sg:province":"Rheinland-Pfalz",
    "wof:name":"Reisecenter Alltours",
    "wof:placetype":"venue"
},
  "geometry": {"coordinates":[8.0303249359,49.9808616638],"type":"Point"}
}