{
  "type": "Feature",
  "properties": {
    "iso:country":"DE",
    "sg:address":"Steinweg 13",
    "sg:city":"Gifhorn",
    "sg:phone":"+49 5371/13143",
    "sg:postcode":"38518",
    "sg:province":"Niedersachsen",
    "wof:name":"M. Briegel",
    "wof:placetype":"venue"
},
  "geometry": {"coordinates":[10.546668,52.487015],"type":"Point"}
}