{
  "type": "Feature",
  "properties": {
    "iso:country":"DE",
    "sg:address":"Egonstr. 3",
    "sg:city":"Freiburg",
    "sg:phone":"+49 761/387080",
    "sg:postcode":"79106",
    "sg:province":"Baden-W\u00fcrttemberg",
    "wof:name":"Ifb - Klotz & Partner Ingenieurgesellschaft F\u00fcr Bau-",
    "wof:placetype":"venue"
},
  "geometry": {"coordinates":[7.8408069611,47.998840332],"type":"Point"}
}