{
  "type": "Feature",
  "properties": {
    "iso:country":"DE",
    "sg:address":"Elisabethenstr. 24",
    "sg:city":"Edingen-Neckarhausen",
    "sg:phone":"+49 6203/5081",
    "sg:postcode":"68535",
    "sg:province":"Baden-W\u00fcrttemberg",
    "wof:name":"Peter Sartorius Patentanwalt",
    "wof:placetype":"venue"
},
  "geometry": {"coordinates":[8.5970888138,49.4641685486],"type":"Point"}
}