{
  "type": "Feature",
  "properties": {
    "iso:country":"DE",
    "sg:address":"Am Schie\u00dfhaus 1",
    "sg:city":"Bayreuth",
    "sg:phone":"+49 921/20479",
    "sg:postcode":"95445",
    "sg:province":"Bayern",
    "wof:name":"Heinz Koob",
    "wof:placetype":"venue"
},
  "geometry": {"coordinates":[11.5852909088,49.9632301331],"type":"Point"}
}