{
  "type": "Feature",
  "properties": {
    "iso:country":"DE",
    "sg:address":"Torcystr. 2",
    "sg:city":"Lingenfeld",
    "sg:phone":"+49 6344/507659",
    "sg:postcode":"67360",
    "sg:province":"Rheinland-Pfalz",
    "wof:name":"Wk Bauplanung Gmbh",
    "wof:placetype":"venue"
},
  "geometry": {"coordinates":[8.339748,49.24308],"type":"Point"}
}