{
  "type": "Feature",
  "properties": {
    "iso:country":"DE",
    "sg:address":"Vitusstr. 55",
    "sg:city":"M\u00f6nchengladbach",
    "sg:phone":"+49 2161/13544",
    "sg:postcode":"41061",
    "sg:province":"Nordrhein-Westfalen",
    "wof:name":"Heinz Henneke",
    "wof:placetype":"venue"
},
  "geometry": {"coordinates":[6.4324688911,51.187789917],"type":"Point"}
}