{
  "type": "Feature",
  "properties": {
    "iso:country":"DE",
    "sg:address":"B\u00f6hringer Str. 28",
    "sg:city":"Grabenstetten",
    "sg:phone":"+49 7382/937210",
    "sg:postcode":"72582",
    "sg:province":"Baden-W\u00fcrttemberg",
    "wof:name":"Wolfgang Ostertag Ingenieur",
    "wof:placetype":"venue"
},
  "geometry": {"coordinates":[9.4615068436,48.5214996338],"type":"Point"}
}