{
  "type": "Feature",
  "properties": {
    "iso:country":"DE",
    "sg:address":"Forstweg 47",
    "sg:city":"Jena",
    "sg:phone":"+49 3641/615224",
    "sg:postcode":"07745",
    "sg:province":"Th\u00fcringen",
    "wof:name":"Prof. Dr. Rosemarie Albrecht",
    "wof:placetype":"venue"
},
  "geometry": {"coordinates":[11.573306,50.926132],"type":"Point"}
}