{
  "type": "Feature",
  "properties": {
    "iso:country":"DE",
    "sg:address":"S\u00f6hringer Str. 1",
    "sg:city":"Badow",
    "sg:phone":"+49 38874/22002",
    "sg:postcode":"19209",
    "sg:province":"Mecklenburg-Vorpommern",
    "wof:name":"Schlo\u00df Badow Kg",
    "wof:placetype":"venue"
},
  "geometry": {"coordinates":[11.1355676651,53.5989723206],"type":"Point"}
}