{
  "type": "Feature",
  "properties": {
    "iso:country":"DE",
    "sg:address":"Neunburger Str. 4",
    "sg:city":"Nabburg",
    "sg:phone":"+49 9433/1704",
    "sg:postcode":"92507",
    "sg:province":"Bayern",
    "wof:name":"Restaurant Jade",
    "wof:placetype":"venue"
},
  "geometry": {"coordinates":[12.1871557236,49.4530105591],"type":"Point"}
}