{
  "type": "Feature",
  "properties": {
    "iso:country":"DE",
    "sg:address":"Kattenstr. 8",
    "sg:city":"Hanau",
    "sg:phone":"+49 6181/82019",
    "sg:postcode":"63452",
    "sg:province":"Hessen",
    "wof:name":"Bolz Und Oehsen Rechtsanw\u00e4lte",
    "wof:placetype":"venue"
},
  "geometry": {"coordinates":[8.9030866623,50.1408996582],"type":"Point"}
}