{
  "type": "Feature",
  "properties": {
    "iso:country":"DE",
    "sg:address":"Lerchenstr. 17",
    "sg:city":"Schwerin",
    "sg:phone":"+49 385/719321",
    "sg:postcode":"19057",
    "sg:province":"Mecklenburg-Vorpommern",
    "wof:name":"Detlef Barz",
    "wof:placetype":"venue"
},
  "geometry": {"coordinates":[11.3736352921,53.6343765259],"type":"Point"}
}