{
  "type": "Feature",
  "properties": {
    "iso:country":"DE",
    "sg:address":"Stadtdeich 27",
    "sg:city":"Hamburg",
    "sg:phone":"+49 40/327553",
    "sg:postcode":"20097",
    "sg:province":"Hamburg",
    "wof:name":"Johann Heinsohn",
    "wof:placetype":"venue"
},
  "geometry": {"coordinates":[10.0094861984,53.5450325012],"type":"Point"}
}