{
  "type": "Feature",
  "properties": {
    "iso:country":"DE",
    "sg:address":"Ernst-Th\u00e4lmann-Platz 11",
    "sg:city":"Niedersachswerfen",
    "sg:phone":"+49 36331/42063",
    "sg:postcode":"99762",
    "sg:province":"Th\u00fcringen",
    "wof:name":"Max K\u00f6hn Drogerie",
    "wof:placetype":"venue"
},
  "geometry": {"coordinates":[10.766699,51.552765],"type":"Point"}
}