{
  "type": "Feature",
  "properties": {
    "iso:country":"DE",
    "sg:address":"Auf dem Kamp 1-11",
    "sg:city":"Osterholz-Scharmbeck",
    "sg:phone":"+49 4791/92210",
    "sg:postcode":"27711",
    "sg:province":"Niedersachsen",
    "wof:name":"Life Wertstoffhandel Entsorgung Und Umwelt-",
    "wof:placetype":"venue"
},
  "geometry": {"coordinates":[8.7949991226,53.2208900452],"type":"Point"}
}