{
  "type": "Feature",
  "properties": {
    "iso:country":"DE",
    "sg:address":"Postfach",
    "sg:city":"Monheim am Rhein",
    "sg:postcode":"40789",
    "sg:province":"Nordrhein-Westfalen",
    "wof:name":"Werbegemeinschaft Treffpunkt Monheim Am Rhein E.v.",
    "wof:placetype":"venue"
},
  "geometry": {"coordinates":[6.8895130157,51.0911903381],"type":"Point"}
}