{
  "type": "Feature",
  "properties": {
    "iso:country":"DE",
    "sg:address":"Werner-Von-Siemens-Str.",
    "sg:city":"Saarwellingen",
    "sg:phone":"+49 4934/756573",
    "sg:postcode":"66793",
    "sg:province":"Saarland",
    "wof:name":"Resa Industrietechnik Gmbh",
    "wof:placetype":"venue"
},
  "geometry": {"coordinates":[11.588521,51.506046],"type":"Point"}
}