{
  "type": "Feature",
  "properties": {
    "iso:country":"DE",
    "sg:address":"Gr\u00fcner Weg 1",
    "sg:city":"Bad W\u00fcnnenberg",
    "sg:phone":"+49 2957/1062",
    "sg:postcode":"33181",
    "sg:province":"Nordrhein-Westfalen",
    "wof:name":"Johannes Und Werner K\u00fcnsting",
    "wof:placetype":"venue"
},
  "geometry": {"coordinates":[8.7247400284,51.5620536804],"type":"Point"}
}