{
  "type": "Feature",
  "properties": {
    "iso:country":"DE",
    "sg:address":"Stra\u00dfe der OdF 3a",
    "sg:city":"Halle",
    "sg:phone":"+49 345/2022513",
    "sg:postcode":"06112",
    "sg:province":"Sachsen-Anhalt",
    "wof:name":"Wolfgang Leipold Architekt",
    "wof:placetype":"venue"
},
  "geometry": {"coordinates":[11.99424,51.478352],"type":"Point"}
}