{
  "type": "Feature",
  "properties": {
    "iso:country":"DE",
    "sg:address":"Brockhausstra\u00dfe 13",
    "sg:city":"Leipzig",
    "sg:phone":"+49 341",
    "sg:postcode":"04229",
    "sg:province":"Sachsen",
    "wof:name":"Dokservice Andrea Ruthenberg",
    "wof:placetype":"venue"
},
  "geometry": {"coordinates":[12.343038,51.325352],"type":"Point"}
}