{
  "type": "Feature",
  "properties": {
    "iso:country":"DE",
    "sg:address":"M\u00fchlweg 1",
    "sg:city":"Schuttertal",
    "sg:phone":"+49 7826/213",
    "sg:postcode":"77978",
    "sg:province":"Baden-W\u00fcrttemberg",
    "wof:name":"Engel",
    "wof:placetype":"venue"
},
  "geometry": {"coordinates":[7.9458861351,48.2186431885],"type":"Point"}
}