{
  "type": "Feature",
  "properties": {
    "iso:country":"DE",
    "sg:address":"Jahnstr. 39",
    "sg:city":"Quickborn",
    "sg:phone":"+49 4106/3808",
    "sg:postcode":"25451",
    "sg:province":"Schleswig-Holstein",
    "wof:name":"Dr. Franz Josef Degenhardt Komponist",
    "wof:placetype":"venue"
},
  "geometry": {"coordinates":[9.9174089432,53.731338501],"type":"Point"}
}