{
  "type": "Feature",
  "properties": {
    "iso:country":"DE",
    "sg:address":"Lindenallee 1",
    "sg:city":"Malente",
    "sg:phone":"+49 4523/2255",
    "sg:postcode":"23714",
    "sg:province":"Schleswig-Holstein",
    "wof:name":"Kurhotel Am Kurpark Petris Ohg",
    "wof:placetype":"venue"
},
  "geometry": {"coordinates":[10.5552330017,54.1693191528],"type":"Point"}
}