{
  "type": "Feature",
  "properties": {
    "iso:country":"DE",
    "sg:address":"Aidlinger Str. 2",
    "sg:city":"B\u00f6blingen",
    "sg:phone":"+49 7031/672223",
    "sg:postcode":"71034",
    "sg:province":"Baden-W\u00fcrttemberg",
    "wof:name":"E. Bauer B\u00e4ckerei",
    "wof:placetype":"venue"
},
  "geometry": {"coordinates":[8.950568,48.691776],"type":"Point"}
}