{
  "type": "Feature",
  "properties": {
    "iso:country":"DE",
    "sg:address":"Humboldtstr. 10",
    "sg:city":"Glinde",
    "sg:phone":"+49 40/72810910",
    "sg:postcode":"21509",
    "sg:province":"Schleswig-Holstein",
    "wof:name":"Reincke Bau Gmbh",
    "wof:placetype":"venue"
},
  "geometry": {"coordinates":[10.23265,53.529339],"type":"Point"}
}