{
  "type": "Feature",
  "properties": {
    "iso:country":"DE",
    "sg:address":"Im Winkel 67",
    "sg:city":"Rheinberg",
    "sg:phone":"+49 2843/2735",
    "sg:postcode":"47495",
    "sg:province":"Nordrhein-Westfalen",
    "wof:name":"Maas Bau- Und Rekultivierungs Gmbh",
    "wof:placetype":"venue"
},
  "geometry": {"coordinates":[6.609401226,51.5215072632],"type":"Point"}
}