{
  "type": "Feature",
  "properties": {
    "iso:country":"DE",
    "sg:address":"Stargarder Tor 4",
    "sg:city":"Neubrandenburg",
    "sg:phone":"+49 395/5442843",
    "sg:postcode":"17033",
    "sg:province":"Mecklenburg-Vorpommern",
    "wof:name":"Zur Lohm\u00fchle Inh. Klonau-schleicher",
    "wof:placetype":"venue"
},
  "geometry": {"coordinates":[13.2611494064,53.5540771484],"type":"Point"}
}