{
  "type": "Feature",
  "properties": {
    "iso:country":"DE",
    "sg:address":"Rosa-Luxemburg-Str. 13",
    "sg:city":"Zittau",
    "sg:phone":"+49 3583/707236",
    "sg:postcode":"02763",
    "sg:province":"Sachsen",
    "wof:name":"Matthias H\u00e4hnel",
    "wof:placetype":"venue"
},
  "geometry": {"coordinates":[14.813737,50.897873],"type":"Point"}
}