{
  "type": "Feature",
  "properties": {
    "iso:country":"DE",
    "sg:address":"Nohner Str. 10",
    "sg:city":"Mettlach",
    "sg:phone":"+49 6868/93024",
    "sg:postcode":"66693",
    "sg:province":"Saarland",
    "wof:name":"Pimi Privates Institut F\u00fcr Marketing In Der",
    "wof:placetype":"venue"
},
  "geometry": {"coordinates":[6.568266,49.485645],"type":"Point"}
}