{
  "type": "Feature",
  "properties": {
    "iso:country":"DE",
    "sg:address":"Sandstr. 40",
    "sg:city":"Pfullingen",
    "sg:phone":"+49 7121/790930",
    "sg:postcode":"72793",
    "sg:province":"Baden-W\u00fcrttemberg",
    "wof:name":"Tilmann Geiselhart Architekt",
    "wof:placetype":"venue"
},
  "geometry": {"coordinates":[9.222023,48.458031],"type":"Point"}
}