{
  "type": "Feature",
  "properties": {
    "iso:country":"DE",
    "sg:address":"Oskar-von-Miller-Str. 24",
    "sg:city":"Miesbach",
    "sg:phone":"+49 8025/6553",
    "sg:postcode":"83714",
    "sg:province":"Bayern",
    "wof:name":"Walter Rau",
    "wof:placetype":"venue"
},
  "geometry": {"coordinates":[11.835288,47.797516],"type":"Point"}
}