{
  "type": "Feature",
  "properties": {
    "iso:country":"DE",
    "sg:address":"Friedhofstr. 12",
    "sg:city":"Illertissen",
    "sg:phone":"+49 7303/42555",
    "sg:postcode":"89257",
    "sg:province":"Bayern",
    "wof:name":"Pili",
    "wof:placetype":"venue"
},
  "geometry": {"coordinates":[10.1077098846,48.225769043],"type":"Point"}
}