{
  "type": "Feature",
  "properties": {
    "iso:country":"DE",
    "sg:address":"Landauer Str. 61",
    "sg:city":"Plattling",
    "sg:postcode":"94447",
    "sg:province":"Bayern",
    "wof:name":"Minimal",
    "wof:placetype":"venue"
},
  "geometry": {"coordinates":[12.8650178909,48.7743225098],"type":"Point"}
}