{
  "type": "Feature",
  "properties": {
    "iso:country":"DE",
    "sg:address":"Hoher Weg 22",
    "sg:city":"Augsburg",
    "sg:phone":"+49 821/15999093",
    "sg:postcode":"86152",
    "sg:province":"Bayern",
    "wof:name":"Rudolf Repgen Rechtsanwalt",
    "wof:placetype":"venue"
},
  "geometry": {"coordinates":[10.8974542618,48.3727035522],"type":"Point"}
}