{
  "type": "Feature",
  "properties": {
    "iso:country":"DE",
    "sg:address":"Robert-Franck-Allee 49",
    "sg:city":"Ludwigsburg",
    "sg:phone":"+49 7141/904745",
    "sg:postcode":"71638",
    "sg:province":"Baden-W\u00fcrttemberg",
    "wof:name":"Dr. Guzman Gmbh",
    "wof:placetype":"venue"
},
  "geometry": {"coordinates":[9.2009830475,48.8874397278],"type":"Point"}
}