{
  "type": "Feature",
  "properties": {
    "iso:country":"DE",
    "sg:address":"B\u00fc\u00dflinger Str. 25",
    "sg:city":"Hilzingen",
    "sg:phone":"+49 4977/3992960",
    "sg:postcode":"78247",
    "sg:province":"Baden-W\u00fcrttemberg",
    "wof:name":"Gebr. J\u00c4ckle Gmbh",
    "wof:placetype":"venue"
},
  "geometry": {"coordinates":[8.69957,47.770615],"type":"Point"}
}