{
  "type": "Feature",
  "properties": {
    "iso:country":"DE",
    "sg:address":"Favoritepark 5",
    "sg:city":"Ludwigsburg",
    "sg:phone":"+49 7141/926637",
    "sg:postcode":"71634",
    "sg:province":"Baden-W\u00fcrttemberg",
    "wof:name":"Favoritenpark",
    "wof:placetype":"venue"
},
  "geometry": {"coordinates":[9.1911783218,48.9074249268],"type":"Point"}
}