{
  "type": "Feature",
  "properties": {
    "iso:country":"DE",
    "sg:address":"Oberdorfstr. 28",
    "sg:city":"Nierstein",
    "sg:phone":"+49 6133/58541",
    "sg:postcode":"55283",
    "sg:province":"Rheinland-Pfalz",
    "wof:name":"F. J. Sandersches Weingut",
    "wof:placetype":"venue"
},
  "geometry": {"coordinates":[8.3344421387,49.8727378845],"type":"Point"}
}