{
  "type": "Feature",
  "properties": {
    "iso:country":"DE",
    "sg:address":"Max-Planck-Str. 4",
    "sg:city":"Rodgau",
    "sg:phone":"+49 6106/22855",
    "sg:postcode":"63110",
    "sg:province":"Hessen",
    "wof:name":"Gerhard Knapp",
    "wof:placetype":"venue"
},
  "geometry": {"coordinates":[8.883825,49.997986],"type":"Point"}
}