{
  "type": "Feature",
  "properties": {
    "iso:country":"DE",
    "sg:address":"Heutorstr. 1",
    "sg:city":"Blomberg",
    "sg:postcode":"32825",
    "sg:province":"Nordrhein-Westfalen",
    "wof:name":"H\u00f6lscher Computerservice Gmbh",
    "wof:placetype":"venue"
},
  "geometry": {"coordinates":[9.0938405991,51.9432106018],"type":"Point"}
}