{
  "type": "Feature",
  "properties": {
    "iso:country":"DE",
    "sg:address":"Ostenhellweg 42-48",
    "sg:city":"Dortmund",
    "sg:phone":"+49 231/5569550",
    "sg:postcode":"44135",
    "sg:province":"Nordrhein-Westfalen",
    "wof:name":"Acc Agentur F\u00fcr Creative Communikation Gmbh",
    "wof:placetype":"venue"
},
  "geometry": {"coordinates":[7.4710650444,51.5145263672],"type":"Point"}
}