{
  "type": "Feature",
  "properties": {
    "iso:country":"DE",
    "sg:address":"Albert-Schweitzer-Str. 1",
    "sg:city":"Wartenberg",
    "sg:phone":"+49 6641/3310",
    "sg:postcode":"36367",
    "sg:province":"Hessen",
    "wof:name":"E. Fuchs",
    "wof:placetype":"venue"
},
  "geometry": {"coordinates":[9.445075,50.627735],"type":"Point"}
}