{
  "type": "Feature",
  "properties": {
    "iso:country":"DE",
    "sg:address":"Liebschwitzer Str. 109",
    "sg:city":"Gera",
    "sg:phone":"+49 365/737880",
    "sg:postcode":"07551",
    "sg:province":"Th\u00fcringen",
    "wof:name":"Fliesen-lindner",
    "wof:placetype":"venue"
},
  "geometry": {"coordinates":[12.0867853165,50.8474006653],"type":"Point"}
}