{
  "type": "Feature",
  "properties": {
    "iso:country":"DE",
    "sg:address":"M\u00f6hnestr. 20",
    "sg:city":"Hanau",
    "sg:phone":"+49 6181/14462",
    "sg:postcode":"63452",
    "sg:province":"Hessen",
    "wof:name":"R. Koch Maschinen",
    "wof:placetype":"venue"
},
  "geometry": {"coordinates":[8.940038,50.146103],"type":"Point"}
}