{
  "type": "Feature",
  "properties": {
    "iso:country":"DE",
    "sg:address":"Horster Str. 345",
    "sg:city":"Bottrop",
    "sg:phone":"+49 2041/74700",
    "sg:postcode":"46238",
    "sg:province":"Nordrhein-Westfalen",
    "wof:name":"Klemencic Und Doussier-klemencic",
    "wof:placetype":"venue"
},
  "geometry": {"coordinates":[6.963915,51.534962],"type":"Point"}
}