{
  "type": "Feature",
  "properties": {
    "iso:country":"DE",
    "sg:address":"Am Marktrasen 8",
    "sg:city":"Krauthausen",
    "sg:phone":"+49 3691/610937",
    "sg:postcode":"99819",
    "sg:province":"Th\u00fcringen",
    "wof:name":"Teco Schr\u00f6der Manfred E. K.",
    "wof:placetype":"venue"
},
  "geometry": {"coordinates":[10.2629756927,51.0078582764],"type":"Point"}
}