{
  "type": "Feature",
  "properties": {
    "iso:country":"DE",
    "sg:address":"Remscheider Str. 1-3",
    "sg:city":"Wermelskirchen",
    "sg:phone":"+49 2196/973737",
    "sg:postcode":"42929",
    "sg:province":"Nordrhein-Westfalen",
    "wof:name":"Bike & Ride Radsportgro\u00df- Handel Jochen Vranic",
    "wof:placetype":"venue"
},
  "geometry": {"coordinates":[7.2158551216,51.1425895691],"type":"Point"}
}