{
  "type": "Feature",
  "properties": {
    "iso:country":"DE",
    "sg:address":"Leipziger Str. 17",
    "sg:city":"Reuden",
    "sg:phone":"+49 34424/21550",
    "sg:postcode":"06725",
    "sg:province":"Sachsen-Anhalt",
    "wof:name":"Gasthof Drei Linden",
    "wof:placetype":"venue"
},
  "geometry": {"coordinates":[12.1941165924,51.1115226746],"type":"Point"}
}