{
  "type": "Feature",
  "properties": {
    "iso:country":"DE",
    "sg:address":"G\u00f6rzhainer Weg 1",
    "sg:city":"Ottrau",
    "sg:phone":"+49 6628/92190",
    "sg:postcode":"34633",
    "sg:province":"Hessen",
    "wof:name":"Fr\u00f6hlich Landmaschinen- Handels Gmbh",
    "wof:placetype":"venue"
},
  "geometry": {"coordinates":[9.41204,50.833614],"type":"Point"}
}