{
  "type": "Feature",
  "properties": {
    "iso:country":"DE",
    "sg:address":"Neumarkter Str.",
    "sg:city":"Altdorf",
    "sg:phone":"+49 9187/7260",
    "sg:postcode":"90518",
    "sg:province":"Bayern",
    "wof:name":"N\u00e4der Gartenbau",
    "wof:placetype":"venue"
},
  "geometry": {"coordinates":[11.360708,49.385021],"type":"Point"}
}