{
  "type": "Feature",
  "properties": {
    "iso:country":"DE",
    "sg:address":"Nr. 86b",
    "sg:city":"Rammenau",
    "sg:phone":"+49 3594/6844",
    "sg:postcode":"01877",
    "sg:province":"Sachsen",
    "wof:name":"Walter Dre\u00dfler",
    "wof:placetype":"venue"
},
  "geometry": {"coordinates":[14.21106,51.129002],"type":"Point"}
}