{
  "type": "Feature",
  "properties": {
    "iso:country":"DE",
    "sg:address":"Schwarzenbacher Ring 2",
    "sg:city":"H\u00f6chstadt",
    "sg:phone":"+49 9193/2893",
    "sg:postcode":"91315",
    "sg:province":"Bayern",
    "wof:name":"E. Roth",
    "wof:placetype":"venue"
},
  "geometry": {"coordinates":[10.802024,49.69416],"type":"Point"}
}