{
  "type": "Feature",
  "properties": {
    "iso:country":"DE",
    "sg:address":"Gewerbeparkring 29",
    "sg:city":"F\u00fcrstenwalde",
    "sg:phone":"+49 3361/50207",
    "sg:postcode":"15517",
    "sg:province":"Brandenburg",
    "wof:name":"Entwicklung Und Produktion Innovativer Kunststoffteile",
    "wof:placetype":"venue"
},
  "geometry": {"coordinates":[14.099978,52.353348],"type":"Point"}
}