{
  "type": "Feature",
  "properties": {
    "iso:country":"DE",
    "sg:address":"Mottelerstr. 8",
    "sg:city":"Leipzig",
    "sg:phone":"+49 341/5662838",
    "sg:postcode":"04155",
    "sg:province":"Sachsen",
    "wof:name":"Scs Treuhand Gmbh",
    "wof:placetype":"venue"
},
  "geometry": {"coordinates":[12.3565368652,51.3631858826],"type":"Point"}
}