{
  "type": "Feature",
  "properties": {
    "iso:country":"DE",
    "sg:address":"Berliner Str. 91",
    "sg:city":"Bielefeld",
    "sg:phone":"+49 521/449829",
    "sg:postcode":"33647",
    "sg:province":"Nordrhein-Westfalen",
    "wof:name":"Akt Ges. F\u00fcr Akustik Und Trockenbau Gmbh",
    "wof:placetype":"venue"
},
  "geometry": {"coordinates":[8.501904,51.982166],"type":"Point"}
}