{
  "type": "Feature",
  "properties": {
    "iso:country":"DE",
    "sg:address":"Burscheider Str. 384",
    "sg:city":"Leverkusen",
    "sg:phone":"+49 2171/33001",
    "sg:postcode":"51381",
    "sg:province":"Nordrhein-Westfalen",
    "wof:name":"Varia Bauplanung Hausbau Und Immobilien-",
    "wof:placetype":"venue"
},
  "geometry": {"coordinates":[7.052541,51.091183],"type":"Point"}
}