{
  "type": "Feature",
  "properties": {
    "iso:country":"DE",
    "sg:address":"Limmerstr. 42",
    "sg:city":"Hannover",
    "sg:phone":"+49 511/456055",
    "sg:postcode":"30451",
    "sg:province":"Niedersachsen",
    "wof:name":"Wilh.-friedr. Strau\u00df Immobilienmakler",
    "wof:placetype":"venue"
},
  "geometry": {"coordinates":[9.7079429626,52.3734550476],"type":"Point"}
}