{
  "type": "Feature",
  "properties": {
    "iso:country":"DE",
    "sg:address":"Weinstr. 28",
    "sg:city":"Deidesheim",
    "sg:phone":"+49 6326/8730",
    "sg:postcode":"67146",
    "sg:province":"Rheinland-Pfalz",
    "wof:name":"M. Schmitt",
    "wof:placetype":"venue"
},
  "geometry": {"coordinates":[8.186653,49.408978],"type":"Point"}
}