{
  "type": "Feature",
  "properties": {
    "iso:country":"DE",
    "sg:address":"L\u00f6rracher Str. 37",
    "sg:city":"R\u00fcmmingen",
    "sg:phone":"+49 7623/1220",
    "sg:postcode":"79595",
    "sg:province":"Baden-W\u00fcrttemberg",
    "wof:name":"Adolf Morr Architekt",
    "wof:placetype":"venue"
},
  "geometry": {"coordinates":[7.641835,47.637775],"type":"Point"}
}