{
  "type": "Feature",
  "properties": {
    "iso:country":"DE",
    "sg:address":"Glottertalstr. 2",
    "sg:city":"St. Peter",
    "sg:phone":"+49 7660/257",
    "sg:postcode":"79271",
    "sg:province":"Baden-W\u00fcrttemberg",
    "wof:name":"Erle",
    "wof:placetype":"venue"
},
  "geometry": {"coordinates":[8.032623291,48.0183639526],"type":"Point"}
}