{
  "type": "Feature",
  "properties": {
    "iso:country":"DE",
    "sg:address":"Lenbachplatz 2 a",
    "sg:city":"M\u00fcnchen",
    "sg:phone":"+49 89/225925",
    "sg:postcode":"80333",
    "sg:province":"Bayern",
    "wof:name":"Nymphenburger Verm\u00f6gensanlage- Und Beteiligungsges. Mbh",
    "wof:placetype":"venue"
},
  "geometry": {"coordinates":[11.567298,48.140694],"type":"Point"}
}