{
  "type": "Feature",
  "properties": {
    "iso:country":"DE",
    "sg:address":"Im Vogelsang 47",
    "sg:city":"Mosbach",
    "sg:phone":"+49 6261/5227",
    "sg:postcode":"74821",
    "sg:province":"Baden-W\u00fcrttemberg",
    "wof:name":"G. Wiemann Und C. Plass-wiemann",
    "wof:placetype":"venue"
},
  "geometry": {"coordinates":[9.1372232437,49.3710823059],"type":"Point"}
}