{
  "type": "Feature",
  "properties": {
    "iso:country":"DE",
    "sg:address":"Gerberweg 2",
    "sg:city":"Ruhmannsfelden",
    "sg:phone":"+49 9929/1284",
    "sg:postcode":"94239",
    "sg:province":"Bayern",
    "wof:name":"Rudolf Hofbrucker",
    "wof:placetype":"venue"
},
  "geometry": {"coordinates":[12.982796,48.979786],"type":"Point"}
}