{
  "type": "Feature",
  "properties": {
    "iso:country":"DE",
    "sg:address":"Chemnitzer Str. 10",
    "sg:city":"Geithain",
    "sg:phone":"+49 34341/42631",
    "sg:postcode":"04643",
    "sg:province":"Sachsen",
    "wof:name":"D. Feig",
    "wof:placetype":"venue"
},
  "geometry": {"coordinates":[12.6952371597,51.0538406372],"type":"Point"}
}