{
  "type": "Feature",
  "properties": {
    "iso:country":"DE",
    "sg:address":"Von-Galen-Str. 15",
    "sg:city":"H\u00f6rstel",
    "sg:phone":"+49 5459/8222",
    "sg:postcode":"48477",
    "sg:province":"Nordrhein-Westfalen",
    "wof:name":"Josef Thiemann",
    "wof:placetype":"venue"
},
  "geometry": {"coordinates":[7.586697,52.27327],"type":"Point"}
}