{
  "type": "Feature",
  "properties": {
    "iso:country":"DE",
    "sg:address":"Schwabstr. 20",
    "sg:city":"Weinsberg",
    "sg:phone":"+49 7134/7180",
    "sg:postcode":"74189",
    "sg:province":"Baden-W\u00fcrttemberg",
    "wof:name":"Redaktion Rebe & Wein Jahrbuch-verlag",
    "wof:placetype":"venue"
},
  "geometry": {"coordinates":[9.2898073196,49.1481399536],"type":"Point"}
}