{
  "type": "Feature",
  "properties": {
    "iso:country":"DE",
    "sg:address":"Postfach 4140",
    "sg:city":"Mainz",
    "sg:postcode":"55031",
    "wof:name":"Deutsche Talentb\u00f6rse Mainzer Talentb\u00f6rse",
    "wof:placetype":"venue"
},
  "geometry": {"coordinates":[8.26785,49.997879],"type":"Point"}
}