{
  "type": "Feature",
  "properties": {
    "iso:country":"DE",
    "sg:address":"Lehmweg 10",
    "sg:city":"Hamburg",
    "sg:phone":"+49 40/4221121",
    "sg:postcode":"20251",
    "sg:province":"Hamburg",
    "wof:name":"Marwitz Gmbh & Co. Kg",
    "wof:placetype":"venue"
},
  "geometry": {"coordinates":[9.977124,53.579884],"type":"Point"}
}