{
  "type": "Feature",
  "properties": {
    "iso:country":"DE",
    "sg:address":"H\u00fchnerkamp 12",
    "sg:city":"Achim",
    "sg:phone":"+49 4202/3999",
    "sg:postcode":"28832",
    "sg:province":"Niedersachsen",
    "wof:name":"Dieter Schemmel",
    "wof:placetype":"venue"
},
  "geometry": {"coordinates":[9.028983,53.033329],"type":"Point"}
}