{
  "type": "Feature",
  "properties": {
    "iso:country":"DE",
    "sg:address":"Leipziger Str. 57",
    "sg:city":"Eilenburg",
    "sg:phone":"+49 3423/600780",
    "sg:postcode":"04838",
    "sg:province":"Sachsen",
    "wof:name":"Reiseb\u00fcro Schwarz-bieligk Gmbh",
    "wof:placetype":"venue"
},
  "geometry": {"coordinates":[12.6294803619,51.4589576721],"type":"Point"}
}