{
  "type": "Feature",
  "properties": {
    "iso:country":"DE",
    "sg:address":"Geschwister-Scholl-Platz 4-6",
    "sg:city":"F\u00fcrstenfeldbruck",
    "sg:phone":"+49 8141/12264",
    "sg:postcode":"82256",
    "sg:province":"Bayern",
    "wof:name":"Avg Allgemeine Immobilien- Vertriebs Gmbh",
    "wof:placetype":"venue"
},
  "geometry": {"coordinates":[11.2253446579,48.1613616943],"type":"Point"}
}