{
  "type": "Feature",
  "properties": {
    "iso:country":"DE",
    "sg:address":"Penzing",
    "sg:city":"Lengdorf",
    "sg:phone":"+49 8083/53060",
    "sg:postcode":"84435",
    "sg:province":"Bayern",
    "wof:name":"O. Heller",
    "wof:placetype":"venue"
},
  "geometry": {"coordinates":[12.042235,48.231781],"type":"Point"}
}