{
  "type": "Feature",
  "properties": {
    "iso:country":"DE",
    "sg:address":"Hofstr. 25",
    "sg:city":"Gescher",
    "sg:phone":"+49 2542/7747",
    "sg:postcode":"48712",
    "sg:province":"Nordrhein-Westfalen",
    "wof:name":"Thomas Lanfer",
    "wof:placetype":"venue"
},
  "geometry": {"coordinates":[7.006004,51.954716],"type":"Point"}
}