{
  "type": "Feature",
  "properties": {
    "iso:country":"DE",
    "sg:address":"Mechower Str. 13",
    "sg:city":"Ratzeburg",
    "sg:phone":"+49 4541/80013",
    "sg:postcode":"23909",
    "sg:province":"Schleswig-Holstein",
    "wof:name":"Volksbank Ratzeburg E.g.",
    "wof:placetype":"venue"
},
  "geometry": {"coordinates":[10.768997,53.699306],"type":"Point"}
}