{
  "type": "Feature",
  "properties": {
    "iso:country":"DE",
    "sg:address":"Ziegeleistr. 1",
    "sg:city":"Waltershausen",
    "sg:phone":"+49 3622/67707",
    "sg:postcode":"99880",
    "sg:province":"Th\u00fcringen",
    "wof:name":"Neumann Gmbh",
    "wof:placetype":"venue"
},
  "geometry": {"coordinates":[10.5559558868,50.9163093567],"type":"Point"}
}