{
  "type": "Feature",
  "properties": {
    "iso:country":"DE",
    "sg:address":"Parkstr. 31",
    "sg:city":"Freising",
    "sg:phone":"+49 8161/61055",
    "sg:postcode":"85356",
    "sg:province":"Bayern",
    "wof:name":"Csf Medienproduktion Gmbh",
    "wof:placetype":"venue"
},
  "geometry": {"coordinates":[11.7614822388,48.4049606323],"type":"Point"}
}