{
  "type": "Feature",
  "properties": {
    "iso:country":"DE",
    "sg:address":"L\u00f6nsstr. 8",
    "sg:city":"Ilsede",
    "sg:phone":"+49 5172/93127",
    "sg:postcode":"31241",
    "sg:province":"Niedersachsen",
    "wof:name":"Klaus Leitner",
    "wof:placetype":"venue"
},
  "geometry": {"coordinates":[10.19490242,52.2777328491],"type":"Point"}
}