{
  "type": "Feature",
  "properties": {
    "iso:country":"DE",
    "sg:address":"Barbarossastr. 86",
    "sg:city":"Chemnitz",
    "sg:phone":"+49 371/305471",
    "sg:postcode":"09112",
    "sg:province":"Sachsen",
    "wof:name":"Nad Gmbh",
    "wof:placetype":"venue"
},
  "geometry": {"coordinates":[12.900692,50.837315],"type":"Point"}
}