{
  "type": "Feature",
  "properties": {
    "iso:country":"DE",
    "sg:address":"Jahnstr. 6",
    "sg:city":"Dierdorf",
    "sg:phone":"+49 2689/3637",
    "sg:postcode":"56269",
    "sg:province":"Rheinland-Pfalz",
    "wof:name":"Georg Scherf",
    "wof:placetype":"venue"
},
  "geometry": {"coordinates":[7.6485061646,50.5469284058],"type":"Point"}
}