{
  "type": "Feature",
  "properties": {
    "iso:country":"DE",
    "sg:address":"Christian-Blank-Str. 4-6",
    "sg:city":"Duderstadt",
    "sg:phone":"+49 4955/2798720",
    "sg:postcode":"37115",
    "sg:province":"Niedersachsen",
    "wof:name":"Mitschke Sportartikel Gmbh",
    "wof:placetype":"venue"
},
  "geometry": {"coordinates":[10.2568006516,51.5143737793],"type":"Point"}
}