{
  "type": "Feature",
  "properties": {
    "iso:country":"DE",
    "sg:address":"Vereinsstr. 354",
    "sg:city":"Gronau",
    "sg:phone":"+49 2562/5135",
    "sg:postcode":"48599",
    "sg:province":"Nordrhein-Westfalen",
    "wof:name":"H. V\u00f6lker Immobilienmakler",
    "wof:placetype":"venue"
},
  "geometry": {"coordinates":[7.0423669815,52.2209472656],"type":"Point"}
}