{
  "type": "Feature",
  "properties": {
    "iso:country":"DE",
    "sg:address":"Gewerbestr. 17",
    "sg:city":"Rheinfelden",
    "sg:postcode":"79618",
    "sg:province":"Baden-W\u00fcrttemberg",
    "wof:name":"Av Video Promotion Aveco-vidas Gmbh",
    "wof:placetype":"venue"
},
  "geometry": {"coordinates":[7.734789,47.547539],"type":"Point"}
}