{
  "type": "Feature",
  "properties": {
    "iso:country":"DE",
    "sg:address":"Hauptstr. 1",
    "sg:city":"Hitzacker",
    "sg:phone":"+49 5862/8707",
    "sg:postcode":"29456",
    "sg:province":"Niedersachsen",
    "wof:name":"Restaurant Plaka",
    "wof:placetype":"venue"
},
  "geometry": {"coordinates":[11.0469465256,53.1516647339],"type":"Point"}
}