{
  "type": "Feature",
  "properties": {
    "iso:country":"DE",
    "sg:address":"Markgrafstr. 7",
    "sg:city":"Pfaffenhausen",
    "sg:phone":"+49 8265/485",
    "sg:postcode":"87772",
    "sg:province":"Bayern",
    "wof:name":"Michael Probst",
    "wof:placetype":"venue"
},
  "geometry": {"coordinates":[10.4541864395,48.1205215454],"type":"Point"}
}