{
  "type": "Feature",
  "properties": {
    "iso:country":"DE",
    "sg:address":"Unterstadt 25",
    "sg:city":"Lich",
    "sg:phone":"+49 6404/2259",
    "sg:postcode":"35423",
    "sg:province":"Hessen",
    "wof:name":"Privileg Hof-apotheke",
    "wof:placetype":"venue"
},
  "geometry": {"coordinates":[8.818999,50.518871],"type":"Point"}
}