{
  "type": "Feature",
  "properties": {
    "iso:country":"DE",
    "sg:address":"Alte Dorfstr. 17",
    "sg:city":"Heeslingen",
    "sg:phone":"+49 4287/564",
    "sg:postcode":"27404",
    "sg:province":"Niedersachsen",
    "wof:name":"Bernd Martens",
    "wof:placetype":"venue"
},
  "geometry": {"coordinates":[9.364185,53.356461],"type":"Point"}
}