{
  "type": "Feature",
  "properties": {
    "iso:country":"DE",
    "sg:address":"Stemmer Landstr. 158",
    "sg:city":"Minden",
    "sg:phone":"+49 571/41507",
    "sg:postcode":"32425",
    "sg:province":"Nordrhein-Westfalen",
    "wof:name":"Heinrich Kruse",
    "wof:placetype":"venue"
},
  "geometry": {"coordinates":[8.867827,52.341534],"type":"Point"}
}