{
  "type": "Feature",
  "properties": {
    "iso:country":"DE",
    "sg:address":"Schaffhauser Str. 15",
    "sg:city":"Tuttlingen",
    "sg:phone":"+49 7461/15812",
    "sg:postcode":"78532",
    "sg:province":"Baden-W\u00fcrttemberg",
    "wof:name":"Venus-film-bar",
    "wof:placetype":"venue"
},
  "geometry": {"coordinates":[8.817504,47.981087],"type":"Point"}
}