{
  "type": "Feature",
  "properties": {
    "iso:country":"DE",
    "sg:address":"Adolf-Kolping-Str. 34",
    "sg:city":"Ludwigshafen",
    "sg:phone":"+49 621/679071",
    "sg:postcode":"67071",
    "sg:province":"Rheinland-Pfalz",
    "wof:name":"Treuverm\u00f6gen Verwaltungsges. F\u00fcr Haus- Und Grundbesitz Mbh",
    "wof:placetype":"venue"
},
  "geometry": {"coordinates":[8.3588609695,49.4932785034],"type":"Point"}
}