{
  "type": "Feature",
  "properties": {
    "iso:country":"DE",
    "sg:address":"Vogesenstr. 42",
    "sg:city":"M\u00fcnchen",
    "sg:phone":"+49 89/4309327",
    "sg:postcode":"81825",
    "sg:province":"Bayern",
    "wof:name":"Erwin Heut Architekt",
    "wof:placetype":"venue"
},
  "geometry": {"coordinates":[11.6709,48.109692],"type":"Point"}
}