{
  "type": "Feature",
  "properties": {
    "iso:country":"DE",
    "sg:address":"Birlenbacher H\u00fctte 2",
    "sg:city":"Siegen",
    "sg:phone":"+49 271/81395",
    "sg:postcode":"57078",
    "sg:province":"Nordrhein-Westfalen",
    "wof:name":"Kurt Beier Gmbh",
    "wof:placetype":"venue"
},
  "geometry": {"coordinates":[8.0102405548,50.9071006775],"type":"Point"}
}