{
  "type": "Feature",
  "properties": {
    "iso:country":"DE",
    "sg:address":"Clever Str. 1",
    "sg:city":"K\u00f6ln",
    "sg:phone":"+49 221/124362",
    "sg:postcode":"50668",
    "sg:province":"Nordrhein-Westfalen",
    "wof:name":"Jris Oelsner",
    "wof:placetype":"venue"
},
  "geometry": {"coordinates":[6.961871,50.949432],"type":"Point"}
}