{
  "type": "Feature",
  "properties": {
    "iso:country":"DE",
    "sg:address":"Eichelsweg 7",
    "sg:city":"Brombachtal",
    "sg:phone":"+49 6063/601",
    "sg:postcode":"64753",
    "sg:province":"Hessen",
    "wof:name":"Werner Scholl",
    "wof:placetype":"venue"
},
  "geometry": {"coordinates":[8.955756,49.734375],"type":"Point"}
}