{
  "type": "Feature",
  "properties": {
    "iso:country":"DE",
    "sg:address":"Sachsentor 26",
    "sg:city":"Hamburg",
    "sg:phone":"+49 40/7244574",
    "sg:postcode":"21029",
    "sg:province":"Hamburg",
    "wof:name":"Alligator Lederwaren Gmbh",
    "wof:placetype":"venue"
},
  "geometry": {"coordinates":[10.213062,53.487728],"type":"Point"}
}