{
  "type": "Feature",
  "properties": {
    "iso:country":"DE",
    "sg:address":"Rheingoldstr. 10",
    "sg:city":"Boppard",
    "sg:phone":"+49 6742/93010",
    "sg:postcode":"56154",
    "sg:province":"Rheinland-Pfalz",
    "wof:name":"Frost Import Gmbh",
    "wof:placetype":"venue"
},
  "geometry": {"coordinates":[7.5996918678,50.1843948364],"type":"Point"}
}