{
  "type": "Feature",
  "properties": {
    "iso:country":"DE",
    "sg:address":"Gewerbegebiet Hollsteitzergrund/ Industriering 15",
    "sg:city":"D\u00f6schwitz",
    "sg:phone":"+49 4934/4254100",
    "sg:postcode":"06712",
    "sg:province":"Sachsen-Anhalt",
    "wof:name":"Owa Vertrieb S\u00dcd Gmbh",
    "wof:placetype":"venue"
},
  "geometry": {"coordinates":[12.1360702515,51.0350189209],"type":"Point"}
}