{
  "type": "Feature",
  "properties": {
    "iso:country":"DE",
    "sg:address":"Schulthei\u00df-Kiefer-Str. 2",
    "sg:city":"Karlsruhe",
    "sg:phone":"+49 721/481414",
    "sg:postcode":"76229",
    "sg:province":"Baden-W\u00fcrttemberg",
    "wof:name":"H. Giegeling Wettannahme",
    "wof:placetype":"venue"
},
  "geometry": {"coordinates":[8.496298,49.007198],"type":"Point"}
}