{
  "type": "Feature",
  "properties": {
    "iso:country":"DE",
    "sg:address":"Siemensstr. 21",
    "sg:city":"Koserow",
    "sg:phone":"+49 38375/910",
    "sg:postcode":"17459",
    "sg:province":"Mecklenburg-Vorpommern",
    "wof:name":"Senioren- Und Pflegeheim",
    "wof:placetype":"venue"
},
  "geometry": {"coordinates":[14.016423,54.048004],"type":"Point"}
}