{
  "type": "Feature",
  "properties": {
    "iso:country":"DE",
    "sg:address":"Stockweg 9e",
    "sg:city":"Berlin",
    "sg:phone":"+49 30/8336496",
    "sg:postcode":"12203",
    "sg:province":"Berlin",
    "wof:name":"Astrid Grube-becker Heilpraktikerin",
    "wof:placetype":"venue"
},
  "geometry": {"coordinates":[13.3135461807,52.4382591248],"type":"Point"}
}