{
  "type": "Feature",
  "properties": {
    "iso:country":"DE",
    "sg:address":"Birkenweg 12",
    "sg:city":"Rottenacker",
    "sg:phone":"+49 7393/1784",
    "sg:postcode":"89616",
    "sg:province":"Baden-W\u00fcrttemberg",
    "wof:name":"Helene Und Werner Walter",
    "wof:placetype":"venue"
},
  "geometry": {"coordinates":[9.6855297089,48.2373695374],"type":"Point"}
}