{
  "type": "Feature",
  "properties": {
    "iso:country":"DE",
    "sg:address":"Niehler Str. 167",
    "sg:city":"K\u00f6ln",
    "sg:phone":"+49 221/764007",
    "sg:postcode":"50733",
    "sg:province":"Nordrhein-Westfalen",
    "wof:name":"Lessur Glaserei Gmbh",
    "wof:placetype":"venue"
},
  "geometry": {"coordinates":[6.958732,50.967861],"type":"Point"}
}