{
  "type": "Feature",
  "properties": {
    "iso:country":"DE",
    "sg:address":"Buschriege 70",
    "sg:city":"H\u00f6velhof",
    "sg:phone":"+49 5257/4410",
    "sg:postcode":"33161",
    "sg:province":"Nordrhein-Westfalen",
    "wof:name":"Rudolf B\u00fcscher",
    "wof:placetype":"venue"
},
  "geometry": {"coordinates":[8.693486,51.82959],"type":"Point"}
}