{
  "type": "Feature",
  "properties": {
    "iso:country":"DE",
    "sg:address":"Max-Planck-Str. 1",
    "sg:city":"Erftstadt",
    "sg:phone":"+49 2235/45791",
    "sg:postcode":"50374",
    "sg:province":"Nordrhein-Westfalen",
    "wof:name":"Ville Express",
    "wof:placetype":"venue"
},
  "geometry": {"coordinates":[6.8205828667,50.8173408508],"type":"Point"}
}