{
  "type": "Feature",
  "properties": {
    "iso:country":"DE",
    "sg:address":"\u00c4u\u00dfere Lengenfelder Str. 12",
    "sg:city":"Rodewisch",
    "sg:phone":"+49 3744/48631",
    "sg:postcode":"08228",
    "sg:province":"Sachsen",
    "wof:name":"Vogtland Holzrecycling Gmbh",
    "wof:placetype":"venue"
},
  "geometry": {"coordinates":[12.3859128952,50.5462608337],"type":"Point"}
}