{
  "type": "Feature",
  "properties": {
    "iso:country":"DE",
    "sg:address":"91359",
    "sg:city":"Leutenbach",
    "sg:postcode":"91359",
    "sg:province":"Bayern",
    "wof:name":"Raiffeisenbank Mittelehrenbach Eg",
    "wof:placetype":"venue"
},
  "geometry": {"coordinates":[11.170197,49.708775],"type":"Point"}
}