{
  "type": "Feature",
  "properties": {
    "iso:country":"DE",
    "sg:address":"K\u00fchgasse 3",
    "sg:city":"Hindelang",
    "sg:postcode":"87541",
    "sg:province":"Bayern",
    "wof:name":"Alpinschule Hindelang",
    "wof:placetype":"venue"
},
  "geometry": {"coordinates":[10.3856115341,47.5038146973],"type":"Point"}
}