{
  "type": "Feature",
  "properties": {
    "iso:country":"DE",
    "sg:address":"Aachener Str. 1h",
    "sg:city":"\u00dcbach-Palenberg",
    "sg:phone":"+49 2451/909010",
    "sg:postcode":"52531",
    "sg:province":"Nordrhein-Westfalen",
    "wof:name":"V. Hoffmann",
    "wof:placetype":"venue"
},
  "geometry": {"coordinates":[6.101129055,50.9206047058],"type":"Point"}
}