{
  "type": "Feature",
  "properties": {
    "iso:country":"DE",
    "sg:address":"Ricklinger Stadtweg 120",
    "sg:city":"Hannover",
    "sg:phone":"+49 511/4503159",
    "sg:postcode":"30459",
    "sg:province":"Niedersachsen",
    "wof:name":"Zentral Und Bereischsbibl. Elektronik Und Maschinenbau",
    "wof:placetype":"venue"
},
  "geometry": {"coordinates":[9.722204,52.353661],"type":"Point"}
}