{
  "type": "Feature",
  "properties": {
    "iso:country":"DE",
    "sg:address":"Hermann-M\u00fcller-Str. 1",
    "sg:city":"Schladen",
    "sg:phone":"+49 4953/3592820",
    "sg:postcode":"38315",
    "sg:province":"Niedersachsen",
    "wof:name":"Alstab Oberfl\u00c4chentechnik Gmbh",
    "wof:placetype":"venue"
},
  "geometry": {"coordinates":[10.550284,52.021049],"type":"Point"}
}