{
  "type": "Feature",
  "properties": {
    "iso:country":"DE",
    "sg:address":"\u00dcmminger Str. 11",
    "sg:city":"Bochum",
    "sg:postcode":"44892",
    "sg:province":"Nordrhein-Westfalen",
    "wof:name":"Inova-bau- Gmbh",
    "wof:placetype":"venue"
},
  "geometry": {"coordinates":[7.301468,51.476875],"type":"Point"}
}