{
  "type": "Feature",
  "properties": {
    "iso:country":"DE",
    "sg:address":"Efeuweg 21",
    "sg:city":"Berlin",
    "sg:phone":"+49 30/6618784",
    "sg:postcode":"12357",
    "sg:province":"Berlin",
    "wof:name":"Klaus J. Wa\u00dfmann Ingenieur",
    "wof:placetype":"venue"
},
  "geometry": {"coordinates":[13.474552,52.428192],"type":"Point"}
}