{
  "type": "Feature",
  "properties": {
    "iso:country":"DE",
    "sg:address":"Am Wahlebach 3",
    "sg:city":"Lohfelden",
    "sg:phone":"+49 561/513607",
    "sg:postcode":"34253",
    "sg:province":"Hessen",
    "wof:name":"Zur Wahlebach-klause",
    "wof:placetype":"venue"
},
  "geometry": {"coordinates":[9.5496387482,51.2798194885],"type":"Point"}
}