{
  "type": "Feature",
  "properties": {
    "iso:country":"DE",
    "sg:address":"Baumgartnerstr. 171/2",
    "sg:city":"Augsburg",
    "sg:phone":"+49 821/551362",
    "sg:postcode":"86161",
    "sg:province":"Bayern",
    "wof:name":"Helmut Keller",
    "wof:placetype":"venue"
},
  "geometry": {"coordinates":[10.90822,48.35503],"type":"Point"}
}