{
  "type": "Feature",
  "properties": {
    "iso:country":"DE",
    "sg:address":"Am Unteren Rain 34",
    "sg:city":"Mittenwald",
    "sg:phone":"+49 8823/5536",
    "sg:postcode":"82481",
    "sg:province":"Bayern",
    "wof:name":"Josef Zwerger Architekt",
    "wof:placetype":"venue"
},
  "geometry": {"coordinates":[11.274168,47.448154],"type":"Point"}
}