{
  "type": "Feature",
  "properties": {
    "iso:country":"DE",
    "sg:address":"Gro\u00dfer Stellweg 23",
    "sg:city":"Viernheim",
    "sg:phone":"+49 6204/60610",
    "sg:postcode":"68519",
    "sg:province":"Hessen",
    "wof:name":"Koch-glitsch Gmbh",
    "wof:placetype":"venue"
},
  "geometry": {"coordinates":[8.579721,49.5481],"type":"Point"}
}