{
  "type": "Feature",
  "properties": {
    "iso:country":"DE",
    "sg:address":"Lisa-Meitner-Str. 9",
    "sg:city":"Mainz",
    "sg:phone":"+49 4961/319910",
    "sg:postcode":"55129",
    "sg:province":"Rheinland-Pfalz",
    "wof:name":"Zdf Enterprises Gmbh",
    "wof:placetype":"venue"
},
  "geometry": {"coordinates":[8.260521,49.964211],"type":"Point"}
}