{
  "type": "Feature",
  "properties": {
    "iso:country":"DE",
    "sg:address":"Reichenberger Str. 12",
    "sg:city":"R\u00fcckmarsdorf",
    "sg:phone":"+49 341/9410215",
    "sg:postcode":"04430",
    "wof:name":"Reinhard Morenz",
    "wof:placetype":"venue"
},
  "geometry": {"coordinates":[12.2544651031,51.3398132324],"type":"Point"}
}