{
  "type": "Feature",
  "properties": {
    "iso:country":"DE",
    "sg:address":"Sandweg 6",
    "sg:city":"Frankfurt",
    "sg:phone":"+49 69/7392727",
    "sg:postcode":"60316",
    "sg:province":"Hessen",
    "wof:name":"Musictrust Musikverlags- Und Produktions- Gmbh",
    "wof:placetype":"venue"
},
  "geometry": {"coordinates":[8.695684433,50.1162528992],"type":"Point"}
}