{
  "type": "Feature",
  "properties": {
    "iso:country":"DE",
    "sg:address":"Oranienstr. 32",
    "sg:city":"Berlin",
    "sg:phone":"+49 30/6147318",
    "sg:postcode":"10999",
    "sg:province":"Berlin",
    "wof:name":"Brillenwerkstatt Berlin",
    "wof:placetype":"venue"
},
  "geometry": {"coordinates":[13.418726,52.501579],"type":"Point"}
}