{
  "type": "Feature",
  "properties": {
    "iso:country":"DE",
    "sg:address":"Kauler Feld 54",
    "sg:city":"Bergisch Gladbach",
    "sg:phone":"+49 2207/1376",
    "sg:postcode":"51429",
    "sg:province":"Nordrhein-Westfalen",
    "wof:name":"Josef Biermann",
    "wof:placetype":"venue"
},
  "geometry": {"coordinates":[7.234373,50.970394],"type":"Point"}
}