{
  "type": "Feature",
  "properties": {
    "iso:country":"DE",
    "sg:address":"Potsdamer Str. 109",
    "sg:city":"Berlin",
    "sg:phone":"+49 30/2540960",
    "sg:postcode":"10785",
    "sg:province":"Berlin",
    "wof:name":"Aurell Company Consulting Gmbh",
    "wof:placetype":"venue"
},
  "geometry": {"coordinates":[13.3630437851,52.4998130798],"type":"Point"}
}