{
  "type": "Feature",
  "properties": {
    "iso:country":"DE",
    "sg:address":"Neue Reihe 22",
    "sg:city":"Cuxhaven",
    "sg:phone":"+49 4721/36457",
    "sg:postcode":"27472",
    "sg:province":"Niedersachsen",
    "wof:name":"Horst Kemme Masseur",
    "wof:placetype":"venue"
},
  "geometry": {"coordinates":[8.701305,53.871338],"type":"Point"}
}