{
  "type": "Feature",
  "properties": {
    "iso:country":"DE",
    "sg:address":"Finkenweg 7",
    "sg:city":"Drachselsried",
    "sg:phone":"+49 9945/2475",
    "sg:postcode":"94256",
    "sg:province":"Bayern",
    "wof:name":"Pension Josef K\u00f6ppl",
    "wof:placetype":"venue"
},
  "geometry": {"coordinates":[13.0120611191,49.1073684692],"type":"Point"}
}