{
  "type": "Feature",
  "properties": {
    "iso:country":"DE",
    "sg:address":"Bovermannstr. 15",
    "sg:city":"Dortmund",
    "sg:phone":"+49 231/9520680",
    "sg:postcode":"44141",
    "sg:province":"Nordrhein-Westfalen",
    "wof:name":"Dr. Karl-w. B\u00f6kenkamp Steuerberater Und",
    "wof:placetype":"venue"
},
  "geometry": {"coordinates":[7.488740921,51.5036735535],"type":"Point"}
}