{
  "type": "Feature",
  "properties": {
    "iso:country":"DE",
    "sg:address":"Allersberger Str. 39",
    "sg:city":"Roth",
    "sg:phone":"+49 9171/61805",
    "sg:postcode":"91154",
    "sg:province":"Bayern",
    "wof:name":"Norma Lebensmittelfilial- Betrieb Gmbh & Co. Kg",
    "wof:placetype":"venue"
},
  "geometry": {"coordinates":[11.0973854065,49.2493133545],"type":"Point"}
}