{
  "type": "Feature",
  "properties": {
    "iso:country":"DE",
    "sg:address":"Leopoldstr. 3",
    "sg:city":"Braunschweig",
    "sg:phone":"+49 531/15805",
    "sg:postcode":"38100",
    "sg:province":"Niedersachsen",
    "wof:name":"\u00dcnal",
    "wof:placetype":"venue"
},
  "geometry": {"coordinates":[10.5228643417,52.2610321045],"type":"Point"}
}