{
  "type": "Feature",
  "properties": {
    "iso:country":"DE",
    "sg:address":"Mackensenstr. 1 a",
    "sg:city":"Regensburg",
    "sg:phone":"+49 941/75717",
    "sg:postcode":"93053",
    "sg:province":"Bayern",
    "wof:name":"Christo Drandarevski",
    "wof:placetype":"venue"
},
  "geometry": {"coordinates":[12.112080574,49.0060539246],"type":"Point"}
}