{
  "type": "Feature",
  "properties": {
    "iso:country":"DE",
    "sg:address":"Am Leitgraben 3",
    "sg:city":"Uelversheim",
    "sg:phone":"+49 6249/8138",
    "sg:postcode":"55278",
    "sg:province":"Rheinland-Pfalz",
    "wof:name":"E. Scholtz Heilpraktiker",
    "wof:placetype":"venue"
},
  "geometry": {"coordinates":[8.285451889,49.8081169128],"type":"Point"}
}