{
  "type": "Feature",
  "properties": {
    "iso:country":"DE",
    "sg:address":"Kjeirstr. 16",
    "sg:city":"Westerland",
    "sg:phone":"+49 4651/201706",
    "sg:postcode":"25980",
    "sg:province":"Schleswig-Holstein",
    "wof:name":"Incosa Gmbh",
    "wof:placetype":"venue"
},
  "geometry": {"coordinates":[8.3104,54.909767],"type":"Point"}
}