{
  "type": "Feature",
  "properties": {
    "iso:country":"DE",
    "sg:address":"Hevelingstr. 238",
    "sg:city":"Goch",
    "sg:phone":"+49 2823/2250",
    "sg:postcode":"47574",
    "sg:province":"Nordrhein-Westfalen",
    "wof:name":"Hotel K. Tophofen",
    "wof:placetype":"venue"
},
  "geometry": {"coordinates":[6.1658658981,51.7176055908],"type":"Point"}
}