{
  "type": "Feature",
  "properties": {
    "iso:country":"DE",
    "sg:address":"Feldstr. 19",
    "sg:city":"L\u00fcneburg",
    "sg:postcode":"21335",
    "sg:province":"Niedersachsen",
    "wof:name":"Hermann Woltmann E. K.",
    "wof:placetype":"venue"
},
  "geometry": {"coordinates":[10.4085254669,53.242603302],"type":"Point"}
}