{
  "type": "Feature",
  "properties": {
    "iso:country":"DE",
    "sg:address":"Rombachstr. 34",
    "sg:city":"Vilsbiburg",
    "sg:postcode":"84137",
    "sg:province":"Bayern",
    "wof:name":"Czink Franz Versicherungs- Vermittlungs Kg",
    "wof:placetype":"venue"
},
  "geometry": {"coordinates":[12.3440952301,48.4585418701],"type":"Point"}
}