{
  "type": "Feature",
  "properties": {
    "iso:country":"DE",
    "sg:address":"Neue Anlage",
    "sg:city":"Ladenburg",
    "sg:phone":"+49 6203/3136",
    "sg:postcode":"68526",
    "sg:province":"Baden-W\u00fcrttemberg",
    "wof:name":"Aral Tankstelle",
    "wof:placetype":"venue"
},
  "geometry": {"coordinates":[8.609254837,49.474571228],"type":"Point"}
}