{
  "type": "Feature",
  "properties": {
    "iso:country":"DE",
    "sg:address":"Karlsruher Str. 67",
    "sg:city":"Pforzheim",
    "sg:postcode":"75179",
    "sg:province":"Baden-W\u00fcrttemberg",
    "wof:name":"Immobilienfonds M\u00fchlehof M\u00fchlacker E. Veigel Kg",
    "wof:placetype":"venue"
},
  "geometry": {"coordinates":[8.6597166061,48.9021263123],"type":"Point"}
}