{
  "type": "Feature",
  "properties": {
    "iso:country":"DE",
    "sg:address":"Berdumer Hammrich 1",
    "sg:city":"Wittmund",
    "sg:phone":"+49 4467/206",
    "sg:postcode":"26409",
    "sg:province":"Niedersachsen",
    "wof:name":"Ihno Remmers",
    "wof:placetype":"venue"
},
  "geometry": {"coordinates":[7.81289,53.606201],"type":"Point"}
}