{
  "type": "Feature",
  "properties": {
    "iso:country":"DE",
    "sg:address":"Hirten\u00e4cker 10",
    "sg:city":"Frankenhardt",
    "sg:phone":"+49 7959/768",
    "sg:postcode":"74586",
    "sg:province":"Baden-W\u00fcrttemberg",
    "wof:name":"Nonnenmacher Fahrzeugbau Gmbh",
    "wof:placetype":"venue"
},
  "geometry": {"coordinates":[10.023732,49.072018],"type":"Point"}
}