{
  "type": "Feature",
  "properties": {
    "iso:country":"DE",
    "sg:address":"Bahnhofstr 21b",
    "sg:city":"Neu Wulmstorf",
    "sg:phone":"+49 40/7008054",
    "sg:postcode":"21629",
    "sg:province":"Niedersachsen",
    "wof:name":"Kreissparkasse Harburg",
    "wof:placetype":"venue"
},
  "geometry": {"coordinates":[9.793397,53.465775],"type":"Point"}
}