{
  "type": "Feature",
  "properties": {
    "iso:country":"DE",
    "sg:address":"Schellbergstr. 24",
    "sg:city":"H\u00fcckelhoven",
    "sg:phone":"+49 2433/918830",
    "sg:postcode":"41836",
    "sg:province":"Nordrhein-Westfalen",
    "wof:name":"Contex Dienstleistung Und Beratung F\u00fcr Abfallverwertung",
    "wof:placetype":"venue"
},
  "geometry": {"coordinates":[6.2308001518,51.0828514099],"type":"Point"}
}