{
  "type": "Feature",
  "properties": {
    "iso:country":"DE",
    "sg:address":"Zum Finkenberg 2",
    "sg:city":"Estorf",
    "sg:phone":"+49 5025/98050",
    "sg:postcode":"31629",
    "sg:province":"Niedersachsen",
    "wof:name":"Manfred Kunze Omnibusbetrieb",
    "wof:placetype":"venue"
},
  "geometry": {"coordinates":[9.1531076431,52.5905838013],"type":"Point"}
}