{
  "type": "Feature",
  "properties": {
    "iso:country":"DE",
    "sg:address":"Pillauer Str. 16",
    "sg:city":"Stuhr",
    "sg:phone":"+49 421/560720",
    "sg:postcode":"28816",
    "sg:province":"Niedersachsen",
    "wof:name":"Hans J. Behrens Handelsvertretungen",
    "wof:placetype":"venue"
},
  "geometry": {"coordinates":[8.7307481766,53.0273933411],"type":"Point"}
}