{
  "type": "Feature",
  "properties": {
    "iso:country":"DE",
    "sg:address":"Jahnstr. 33",
    "sg:city":"Berlin",
    "sg:phone":"+49 30/6850090",
    "sg:postcode":"12347",
    "sg:province":"Berlin",
    "wof:name":"Fkr Friedhelm Kreuels Regeltechnik Gmbh Fachgro\u00df-",
    "wof:placetype":"venue"
},
  "geometry": {"coordinates":[13.442278862,52.460811615],"type":"Point"}
}