{
  "type": "Feature",
  "properties": {
    "iso:country":"DE",
    "sg:address":"Dr.-Dinkler-Allee 9",
    "sg:city":"K\u00f6nigsee",
    "sg:phone":"+49 36738/42203",
    "sg:postcode":"07426",
    "sg:province":"Th\u00fcringen",
    "wof:name":"A. K\u00fchn",
    "wof:placetype":"venue"
},
  "geometry": {"coordinates":[11.095717,50.66568],"type":"Point"}
}