{
  "type": "Feature",
  "properties": {
    "iso:country":"DE",
    "sg:address":"Marktstr. 51",
    "sg:city":"Bad Salzdetfurth",
    "sg:phone":"+49 5063/960262",
    "sg:postcode":"31162",
    "sg:province":"Niedersachsen",
    "wof:name":"Restaurant Delphi",
    "wof:placetype":"venue"
},
  "geometry": {"coordinates":[10.0083398819,52.0646057129],"type":"Point"}
}