{
  "type": "Feature",
  "properties": {
    "iso:country":"DE",
    "sg:address":"Ziegeleistr. 1",
    "sg:city":"Bad Wurzach",
    "sg:phone":"+49 7524/2021",
    "sg:postcode":"88410",
    "sg:province":"Baden-W\u00fcrttemberg",
    "wof:name":"Ziegelwerk Arnach J. Schmid Gmbh & Co. Kg",
    "wof:placetype":"venue"
},
  "geometry": {"coordinates":[9.8899564743,47.8580589294],"type":"Point"}
}