{
  "type": "Feature",
  "properties": {
    "iso:country":"DE",
    "sg:address":"T\u00fctersburg 37",
    "sg:city":"Wuppertal",
    "sg:phone":"+49 202/523052",
    "sg:postcode":"42277",
    "sg:province":"Nordrhein-Westfalen",
    "wof:name":"Aba-moden Angelika Bark Kg",
    "wof:placetype":"venue"
},
  "geometry": {"coordinates":[7.2142081261,51.2852783203],"type":"Point"}
}