{
  "type": "Feature",
  "properties": {
    "iso:country":"DE",
    "sg:address":"Hauptstr. 3",
    "sg:city":"P\u00fcttlingen",
    "sg:phone":"+49 6806/920099",
    "sg:postcode":"66346",
    "sg:province":"Saarland",
    "wof:name":"Reiseb\u00fcro Ames Gmbh",
    "wof:placetype":"venue"
},
  "geometry": {"coordinates":[6.8983469009,49.3009719849],"type":"Point"}
}