{
  "type": "Feature",
  "properties": {
    "iso:country":"DE",
    "sg:address":"Hellbrookstr. 71",
    "sg:city":"Hamburg",
    "sg:phone":"+49 40/613984",
    "sg:postcode":"22305",
    "sg:province":"Hamburg",
    "wof:name":"Kurbad Hellbrook",
    "wof:placetype":"venue"
},
  "geometry": {"coordinates":[10.047149,53.591694],"type":"Point"}
}