{
  "type": "Feature",
  "properties": {
    "iso:country":"DE",
    "sg:address":"Overbergstr. 31 a",
    "sg:city":"Recklinghausen",
    "sg:phone":"+49 2361/7822",
    "sg:postcode":"45663",
    "sg:province":"Nordrhein-Westfalen",
    "wof:name":"Rosen Apotheke Frank Gretenkord E. K.",
    "wof:placetype":"venue"
},
  "geometry": {"coordinates":[7.229632,51.586681],"type":"Point"}
}