{
  "type": "Feature",
  "properties": {
    "iso:country":"DE",
    "sg:address":"Berliner Platz 2",
    "sg:city":"Bocholt",
    "sg:phone":"+49 2871/17958",
    "sg:postcode":"46395",
    "sg:province":"Nordrhein-Westfalen",
    "wof:name":"Kind Und Hobby R\u00fcdiger Gmbh",
    "wof:placetype":"venue"
},
  "geometry": {"coordinates":[6.6110811234,51.8355941772],"type":"Point"}
}