{
  "type": "Feature",
  "properties": {
    "iso:country":"DE",
    "sg:address":"Casinowall 17",
    "sg:city":"Bocholt",
    "sg:phone":"+49 2871/180991",
    "sg:postcode":"46399",
    "sg:province":"Nordrhein-Westfalen",
    "wof:name":"Heide Ratering",
    "wof:placetype":"venue"
},
  "geometry": {"coordinates":[6.6135392189,51.836517334],"type":"Point"}
}