{
  "type": "Feature",
  "properties": {
    "iso:country":"DE",
    "sg:address":"Goethestr. 41",
    "sg:city":"Weinheim",
    "sg:phone":"+49 6201/71958",
    "sg:postcode":"69469",
    "sg:province":"Baden-W\u00fcrttemberg",
    "wof:name":"Alfons Schachner",
    "wof:placetype":"venue"
},
  "geometry": {"coordinates":[8.656698,49.580807],"type":"Point"}
}