{
  "type": "Feature",
  "properties": {
    "iso:country":"DE",
    "sg:city":"Alfeld",
    "sg:phone":"+49 5181/2921",
    "sg:postcode":"31061",
    "sg:province":"Niedersachsen",
    "wof:name":"Handy-scout",
    "wof:placetype":"venue"
},
  "geometry": {"coordinates":[9.871855,51.958954],"type":"Point"}
}