{
  "type": "Feature",
  "properties": {
    "iso:country":"DE",
    "sg:address":"D\u00fcnenweg",
    "sg:city":"Grabow",
    "sg:postcode":"19300",
    "sg:province":"Mecklenburg-Vorpommern",
    "wof:name":"Hadecosped Warenveredelung- Verpackungs-u. Umschlagges.mbh",
    "wof:placetype":"venue"
},
  "geometry": {"coordinates":[11.535055,53.276745],"type":"Point"}
}