{
  "type": "Feature",
  "properties": {
    "iso:country":"DE",
    "sg:address":"Wilhelmplatz 1",
    "sg:city":"Bonn",
    "sg:phone":"+49 228/651941",
    "sg:postcode":"53111",
    "sg:province":"Nordrhein-Westfalen",
    "wof:name":"Abbass Farahani",
    "wof:placetype":"venue"
},
  "geometry": {"coordinates":[7.098803997,50.7403564453],"type":"Point"}
}