{
  "type": "Feature",
  "properties": {
    "iso:country":"DE",
    "sg:address":"Frankfurter Allee 94a",
    "sg:city":"Berlin",
    "sg:phone":"+49 30/5890129",
    "sg:postcode":"10247",
    "sg:province":"Berlin",
    "wof:name":"Ralf Rau Feldservice",
    "wof:placetype":"venue"
},
  "geometry": {"coordinates":[13.472018,52.513783],"type":"Point"}
}