{
  "type": "Feature",
  "properties": {
    "iso:country":"DE",
    "sg:address":"F\u00e4hrstr. 8",
    "sg:city":"Zeltingen-Rachtig",
    "sg:phone":"+49 6532/2451",
    "sg:postcode":"54492",
    "sg:province":"Rheinland-Pfalz",
    "wof:name":"Pension Liesel Ehlen",
    "wof:placetype":"venue"
},
  "geometry": {"coordinates":[7.0156478882,49.952922821],"type":"Point"}
}