{
  "type": "Feature",
  "properties": {
    "iso:country":"DE",
    "sg:address":"Palmstr. 4",
    "sg:city":"L\u00f6rrach",
    "sg:phone":"+49 7621/8552",
    "sg:postcode":"79539",
    "sg:province":"Baden-W\u00fcrttemberg",
    "wof:name":"Becker Planen Und Einrichten Gmbh",
    "wof:placetype":"venue"
},
  "geometry": {"coordinates":[7.661361,47.614281],"type":"Point"}
}