{
  "type": "Feature",
  "properties": {
    "iso:country":"DE",
    "sg:address":"Erfurter Strasse 1",
    "sg:city":"Arnstadt",
    "sg:phone":"+49 4936/2848277",
    "sg:postcode":"99310",
    "sg:province":"Th\u00fcringen",
    "wof:name":"Schwimmbadtechnik Scheliga",
    "wof:placetype":"venue"
},
  "geometry": {"coordinates":[10.9472703934,50.8338661194],"type":"Point"}
}