{
  "type": "Feature",
  "properties": {
    "iso:country":"DE",
    "sg:address":"Alzeyer Str. 134",
    "sg:city":"Fl\u00f6rsheim-Dalsheim",
    "sg:phone":"+49 6243/908070",
    "sg:postcode":"67592",
    "sg:province":"Rheinland-Pfalz",
    "wof:name":"Sekthaus Mobile Sektkellerei Raumland Gmbh",
    "wof:placetype":"venue"
},
  "geometry": {"coordinates":[8.2036857605,49.6607208252],"type":"Point"}
}