{
  "type": "Feature",
  "properties": {
    "iso:country":"DE",
    "sg:address":"Bubenhauser Str. 8",
    "sg:city":"Zweibr\u00fccken",
    "sg:phone":"+49 6332/3738",
    "sg:postcode":"66482",
    "sg:province":"Rheinland-Pfalz",
    "wof:name":"May Und Diehl Rechtsanw\u00e4lte",
    "wof:placetype":"venue"
},
  "geometry": {"coordinates":[7.3624048233,49.2450752258],"type":"Point"}
}