{
  "type": "Feature",
  "properties": {
    "iso:country":"DE",
    "sg:address":"K\u00f6lner Str. 388a",
    "sg:city":"M\u00fclheim",
    "sg:phone":"+49 208/481135",
    "sg:postcode":"45481",
    "sg:province":"Nordrhein-Westfalen",
    "wof:name":"Holbeck S\u00f6hne Gmbh",
    "wof:placetype":"venue"
},
  "geometry": {"coordinates":[6.863074,51.368111],"type":"Point"}
}