{
  "type": "Feature",
  "properties": {
    "iso:country":"DE",
    "sg:address":"Fleher Str. 106",
    "sg:city":"D\u00fcsseldorf",
    "sg:postcode":"40223",
    "sg:province":"Nordrhein-Westfalen",
    "wof:name":"Omnisoft Ag",
    "wof:placetype":"venue"
},
  "geometry": {"coordinates":[6.7668218613,51.20079422],"type":"Point"}
}