{
  "type": "Feature",
  "properties": {
    "iso:country":"DE",
    "sg:address":"Bleichstr. 20",
    "sg:city":"Wiesbaden",
    "sg:phone":"+49 611/301154",
    "sg:postcode":"65183",
    "sg:province":"Hessen",
    "wof:name":"Braust\u00fcbl",
    "wof:placetype":"venue"
},
  "geometry": {"coordinates":[8.233332634,50.0805969238],"type":"Point"}
}