{
  "type": "Feature",
  "properties": {
    "iso:country":"DE",
    "sg:address":"Industriestr. 12",
    "sg:city":"Niederfischbach",
    "sg:phone":"+49 2734/5090",
    "sg:postcode":"57572",
    "sg:province":"Rheinland-Pfalz",
    "wof:name":"F. A. T. F\u00f6rder- Und Anlagentechnik Gmbh",
    "wof:placetype":"venue"
},
  "geometry": {"coordinates":[7.859165,50.846794],"type":"Point"}
}