{
  "type": "Feature",
  "properties": {
    "iso:country":"DE",
    "sg:address":"Schmallenberger Str. 30",
    "sg:city":"Lennestadt",
    "sg:phone":"+49 2723/80193",
    "sg:postcode":"57368",
    "sg:province":"Nordrhein-Westfalen",
    "wof:name":"Alfons Tigges",
    "wof:placetype":"venue"
},
  "geometry": {"coordinates":[8.1025104523,51.110458374],"type":"Point"}
}