{
  "type": "Feature",
  "properties": {
    "iso:country":"DE",
    "sg:address":"Wannen\u00e4ckerstr. 29-2",
    "sg:city":"Heilbronn",
    "sg:phone":"+49 7131/21010",
    "sg:postcode":"74078",
    "sg:province":"Baden-W\u00fcrttemberg",
    "wof:name":"R & S Wohn- Und Gewerbebau Gmbh",
    "wof:placetype":"venue"
},
  "geometry": {"coordinates":[9.182281,49.184704],"type":"Point"}
}