{
  "type": "Feature",
  "properties": {
    "iso:country":"DE",
    "sg:address":"Honsberger Str. 39",
    "sg:city":"Remscheid",
    "sg:phone":"+49 2191/349045",
    "sg:postcode":"42857",
    "sg:province":"Nordrhein-Westfalen",
    "wof:name":"Wilh. Wege",
    "wof:placetype":"venue"
},
  "geometry": {"coordinates":[7.1860938072,51.1737213135],"type":"Point"}
}