{
  "type": "Feature",
  "properties": {
    "iso:country":"DE",
    "sg:address":"Schr\u00f6derplatz 2",
    "sg:city":"Kassel",
    "sg:phone":"+49 561/512682",
    "sg:postcode":"34123",
    "sg:province":"Hessen",
    "wof:name":"Helmut Bechstein",
    "wof:placetype":"venue"
},
  "geometry": {"coordinates":[9.5344219208,51.2919425964],"type":"Point"}
}