{
  "type": "Feature",
  "properties": {
    "iso:country":"DE",
    "sg:address":"Wellesweilerstr. 135",
    "sg:city":"Neunkirchen",
    "sg:postcode":"66538",
    "sg:province":"Saarland",
    "wof:name":"C. M\u00fcller",
    "wof:placetype":"venue"
},
  "geometry": {"coordinates":[7.2084608078,49.3533744812],"type":"Point"}
}