{
  "type": "Feature",
  "properties": {
    "iso:country":"DE",
    "sg:address":"Kruckenburgstr. 38",
    "sg:city":"M\u00fcnchen",
    "sg:phone":"+49 89/7143351",
    "sg:postcode":"81375",
    "sg:province":"Bayern",
    "wof:name":"Josef Kirmair",
    "wof:placetype":"venue"
},
  "geometry": {"coordinates":[11.485446,48.116207],"type":"Point"}
}