{
  "type": "Feature",
  "properties": {
    "iso:country":"DE",
    "sg:address":"Unter den Weiden 19",
    "sg:city":"Mannheim",
    "sg:phone":"+49 621/8620183",
    "sg:postcode":"68199",
    "sg:province":"Baden-W\u00fcrttemberg",
    "wof:name":"Hartmut Krahn Architekt",
    "wof:placetype":"venue"
},
  "geometry": {"coordinates":[8.473734,49.450035],"type":"Point"}
}