{
  "type": "Feature",
  "properties": {
    "iso:country":"DE",
    "sg:address":"Raiffeisenstr. 29",
    "sg:city":"Schw\u00e4bisch Hall",
    "sg:phone":"+49 791/2655",
    "sg:postcode":"74523",
    "sg:province":"Baden-W\u00fcrttemberg",
    "wof:name":"Karosseriefachbetrieb Harry Strohmeier Gmbh",
    "wof:placetype":"venue"
},
  "geometry": {"coordinates":[9.7924470901,49.1104660034],"type":"Point"}
}