{
  "type": "Feature",
  "properties": {
    "iso:country":"DE",
    "sg:address":"Kreisstr. 2",
    "sg:city":"Kalbach",
    "sg:phone":"+49 9742/273",
    "sg:postcode":"36148",
    "sg:province":"Hessen",
    "wof:name":"E. Lotz",
    "wof:placetype":"venue"
},
  "geometry": {"coordinates":[9.650560379,50.3949890137],"type":"Point"}
}