{
  "type": "Feature",
  "properties": {
    "iso:country":"DE",
    "sg:address":"Gro\u00dfe Str. 49",
    "sg:city":"Kranenburg",
    "sg:phone":"+49 2826/455",
    "sg:postcode":"47559",
    "sg:province":"Nordrhein-Westfalen",
    "wof:name":"A. Starke",
    "wof:placetype":"venue"
},
  "geometry": {"coordinates":[6.0068411827,51.7898178101],"type":"Point"}
}