{
  "type": "Feature",
  "properties": {
    "iso:country":"DE",
    "sg:address":"Zeisselstrasse 22",
    "sg:city":"Frankfurt am Main",
    "sg:phone":"+49 69/5973714",
    "sg:postcode":"60318",
    "sg:province":"Hessen",
    "wof:name":"Edv Berater Mit Langj\u00e4hrige Erfahrung.",
    "wof:placetype":"venue"
},
  "geometry": {"coordinates":[8.689878,50.124275],"type":"Point"}
}