{
  "type": "Feature",
  "properties": {
    "iso:country":"DE",
    "sg:address":"H\u00f6nerfeld 8",
    "sg:city":"B\u00f6nningstedt",
    "sg:phone":"+49 40/5567065",
    "sg:postcode":"25474",
    "sg:province":"Schleswig-Holstein",
    "wof:name":"Meyntz Gmbh",
    "wof:placetype":"venue"
},
  "geometry": {"coordinates":[9.90789,53.659779],"type":"Point"}
}