{
  "type": "Feature",
  "properties": {
    "iso:country":"DE",
    "sg:address":"Am Kurgarten 100",
    "sg:city":"L\u00fcbeck",
    "sg:phone":"+49 4502/3959",
    "sg:postcode":"23570",
    "sg:province":"Schleswig-Holstein",
    "wof:name":"Karin Freter",
    "wof:placetype":"venue"
},
  "geometry": {"coordinates":[10.8713769913,53.9584884644],"type":"Point"}
}