{
  "type": "Feature",
  "properties": {
    "iso:country":"DE",
    "sg:address":"Alte Coburger Str. 40",
    "sg:city":"Lichtenfels",
    "sg:phone":"+49 9571/3545",
    "sg:postcode":"96215",
    "sg:province":"Bayern",
    "wof:name":"Pizzeria Maintalterrasse",
    "wof:placetype":"venue"
},
  "geometry": {"coordinates":[11.0562009811,50.1576690674],"type":"Point"}
}