{
  "type": "Feature",
  "properties": {
    "iso:country":"DE",
    "sg:address":"Hainleinstr. 176",
    "sg:city":"Niederwerrn",
    "sg:phone":"+49 9721/49378",
    "sg:postcode":"97464",
    "sg:province":"Bayern",
    "wof:name":"Francesco Canu",
    "wof:placetype":"venue"
},
  "geometry": {"coordinates":[10.1925058365,50.0644378662],"type":"Point"}
}