{
  "type": "Feature",
  "properties": {
    "iso:country":"DE",
    "sg:address":"Lindenstr. 27",
    "sg:city":"Lohne",
    "sg:phone":"+49 4442/73350",
    "sg:postcode":"49393",
    "sg:province":"Niedersachsen",
    "wof:name":"Kontor",
    "wof:placetype":"venue"
},
  "geometry": {"coordinates":[8.2405433655,52.6670570374],"type":"Point"}
}