{
  "type": "Feature",
  "properties": {
    "iso:country":"DE",
    "sg:address":"Frauental 31",
    "sg:city":"Creglingen",
    "sg:phone":"+49 7933/398",
    "sg:postcode":"97993",
    "sg:province":"Baden-W\u00fcrttemberg",
    "wof:name":"Ernst Mack",
    "wof:placetype":"venue"
},
  "geometry": {"coordinates":[10.090344,49.496544],"type":"Point"}
}