{
  "type": "Feature",
  "properties": {
    "iso:country":"DE",
    "sg:address":"Alte Dorfstr. 7b",
    "sg:city":"Liebenburg",
    "sg:phone":"+49 5346/99080",
    "sg:postcode":"38704",
    "sg:province":"Niedersachsen",
    "wof:name":"Noack Bautr\u00e4ger- Und Immobilien Gmbh",
    "wof:placetype":"venue"
},
  "geometry": {"coordinates":[10.401266,51.974625],"type":"Point"}
}