{
  "type": "Feature",
  "properties": {
    "iso:country":"DE",
    "sg:address":"Bahnhofstr. 44",
    "sg:city":"Weiterstadt",
    "sg:phone":"+49 6150/2515",
    "sg:postcode":"64331",
    "sg:province":"Hessen",
    "wof:name":"Elektro G\u00f6rich Gmbh",
    "wof:placetype":"venue"
},
  "geometry": {"coordinates":[8.579573,49.905945],"type":"Point"}
}