{
  "type": "Feature",
  "properties": {
    "iso:country":"DE",
    "sg:address":"Nimsch\u00fctzer Str. 6 b",
    "sg:city":"Bautzen",
    "sg:phone":"+49 3591/209938",
    "sg:postcode":"02625",
    "sg:province":"Sachsen",
    "wof:name":"E. Sprigade",
    "wof:placetype":"venue"
},
  "geometry": {"coordinates":[14.4612493515,51.1984443665],"type":"Point"}
}