{
  "type": "Feature",
  "properties": {
    "iso:country":"DE",
    "sg:address":"Magdeburger Str. 8",
    "sg:city":"St. Wendel",
    "sg:phone":"+49 6851/905310",
    "sg:postcode":"66606",
    "sg:province":"Saarland",
    "wof:name":"Stamer Musikanlagen Gmbh",
    "wof:placetype":"venue"
},
  "geometry": {"coordinates":[7.1510801315,49.4627532959],"type":"Point"}
}