{
  "type": "Feature",
  "properties": {
    "iso:country":"DE",
    "sg:address":"Antonstr. 23",
    "sg:city":"G\u00f6rlitz",
    "sg:phone":"+49 3581/302162",
    "sg:postcode":"02828",
    "sg:province":"Sachsen",
    "wof:name":"Michael Furchner",
    "wof:placetype":"venue"
},
  "geometry": {"coordinates":[14.981605,51.163895],"type":"Point"}
}