{
  "type": "Feature",
  "properties": {
    "iso:country":"DE",
    "sg:address":"Chemnitzer Str. 15",
    "sg:city":"M\u00fchlau",
    "sg:phone":"+49 3722/80752",
    "sg:postcode":"09241",
    "sg:province":"Sachsen",
    "wof:name":"P. W. Br\u00e4uer",
    "wof:placetype":"venue"
},
  "geometry": {"coordinates":[12.7624206543,50.8997955322],"type":"Point"}
}