{
  "type": "Feature",
  "properties": {
    "iso:country":"DE",
    "sg:address":"Behringstrasse 8",
    "sg:city":"Ludwigshafen",
    "sg:phone":"+49 621/6339791",
    "sg:postcode":"67063",
    "sg:province":"Rheinland-Pfalz",
    "wof:name":"Webspace Und Domainen - Webjanssen",
    "wof:placetype":"venue"
},
  "geometry": {"coordinates":[8.418016,49.495968],"type":"Point"}
}