{
  "type": "Feature",
  "properties": {
    "iso:country":"DE",
    "sg:address":"Hauptstr. 56",
    "sg:city":"Bad Sch\u00f6nborn",
    "sg:phone":"+49 7253/32223",
    "sg:postcode":"76669",
    "sg:province":"Baden-W\u00fcrttemberg",
    "wof:name":"Rats-apotheke",
    "wof:placetype":"venue"
},
  "geometry": {"coordinates":[8.647217,49.203503],"type":"Point"}
}