{
  "type": "Feature",
  "properties": {
    "iso:country":"DE",
    "sg:address":"Am Gelskamp 14",
    "sg:city":"Detmold",
    "sg:postcode":"32758",
    "sg:province":"Nordrhein-Westfalen",
    "wof:name":"Western-riding",
    "wof:placetype":"venue"
},
  "geometry": {"coordinates":[8.857476,51.948906],"type":"Point"}
}