{
  "type": "Feature",
  "properties": {
    "iso:country":"DE",
    "sg:address":"Geesthofer Weg 1",
    "sg:city":"Hechthausen",
    "sg:phone":"+49 4774/272",
    "sg:postcode":"21755",
    "sg:province":"Niedersachsen",
    "wof:name":"Ernst Tiedemann",
    "wof:placetype":"venue"
},
  "geometry": {"coordinates":[9.20839,53.631142],"type":"Point"}
}