{
  "type": "Feature",
  "properties": {
    "iso:country":"DE",
    "sg:address":"Mellendorfer Kirchweg 43",
    "sg:city":"Wedemark",
    "sg:phone":"+49 4951/303400",
    "sg:postcode":"30900",
    "sg:province":"Niedersachsen",
    "wof:name":"Butenhoff Gmbh Baustoffhandel Transporte",
    "wof:placetype":"venue"
},
  "geometry": {"coordinates":[9.7293739319,52.5575256348],"type":"Point"}
}