{
  "type": "Feature",
  "properties": {
    "iso:country":"DE",
    "sg:address":"Eversbuschstr. 33",
    "sg:city":"M\u00fcnchen",
    "sg:phone":"+49 89/8120120",
    "sg:postcode":"80999",
    "sg:province":"Bayern",
    "wof:name":"A. Morlok",
    "wof:placetype":"venue"
},
  "geometry": {"coordinates":[11.4603996277,48.1834907532],"type":"Point"}
}