{
  "type": "Feature",
  "properties": {
    "iso:country":"DE",
    "sg:address":"Immenst\u00e4dter Str 79a",
    "sg:city":"Kempten",
    "sg:phone":"+49 831/2528210",
    "sg:postcode":"87435",
    "sg:province":"Bayern",
    "wof:name":"Zak Energie Gmbh",
    "wof:placetype":"venue"
},
  "geometry": {"coordinates":[10.311486,47.713718],"type":"Point"}
}