{
  "type": "Feature",
  "properties": {
    "iso:country":"DE",
    "sg:address":"Schillerstr. 4",
    "sg:city":"Edingen-Neckarhausen",
    "sg:phone":"+49 6203/85410",
    "sg:postcode":"68535",
    "sg:province":"Baden-W\u00fcrttemberg",
    "wof:name":"T. S. P. Gesellschaft F\u00fcr Informationssysteme Mbh",
    "wof:placetype":"venue"
},
  "geometry": {"coordinates":[8.6158351898,49.4415206909],"type":"Point"}
}