{
  "type": "Feature",
  "properties": {
    "iso:country":"DE",
    "sg:address":"Eckerder Str. 5",
    "sg:city":"Barsinghausen",
    "sg:phone":"+49 5105/2282",
    "sg:postcode":"30890",
    "sg:province":"Niedersachsen",
    "wof:name":"Friedrich Tatje",
    "wof:placetype":"venue"
},
  "geometry": {"coordinates":[9.503184,52.330605],"type":"Point"}
}