{
  "type": "Feature",
  "properties": {
    "iso:country":"DE",
    "sg:address":"Dorfstr. 19",
    "sg:city":"Travenhorst",
    "sg:phone":"+49 4556/547",
    "sg:postcode":"23827",
    "sg:province":"Schleswig-Holstein",
    "wof:name":"Thomas Br\u00e4mer",
    "wof:placetype":"venue"
},
  "geometry": {"coordinates":[10.4541120529,54.0192184448],"type":"Point"}
}