{
  "type": "Feature",
  "properties": {
    "iso:country":"DE",
    "sg:address":"Schlo\u00dfstr. 1",
    "sg:city":"Uffenheim",
    "sg:phone":"+49 9842/8182",
    "sg:postcode":"97215",
    "sg:province":"Bayern",
    "wof:name":"W. Pehl",
    "wof:placetype":"venue"
},
  "geometry": {"coordinates":[10.228799,49.545059],"type":"Point"}
}