{
  "type": "Feature",
  "properties": {
    "iso:country":"DE",
    "sg:address":"R\u00f6merstr. 7",
    "sg:city":"Ellwangen",
    "sg:phone":"+49 7965/2651",
    "sg:postcode":"73479",
    "sg:province":"Baden-W\u00fcrttemberg",
    "wof:name":"J. Schiebel",
    "wof:placetype":"venue"
},
  "geometry": {"coordinates":[10.258307,48.961777],"type":"Point"}
}