{
  "type": "Feature",
  "properties": {
    "iso:country":"DE",
    "sg:address":"Hospitalstr. 1",
    "sg:city":"Wallerfangen",
    "sg:postcode":"66798",
    "sg:province":"Saarland",
    "wof:name":"Accord",
    "wof:placetype":"venue"
},
  "geometry": {"coordinates":[6.7160382271,49.3294258118],"type":"Point"}
}