{
  "type": "Feature",
  "properties": {
    "iso:country":"DE",
    "sg:address":"Wallstr. 34",
    "sg:city":"Aachen",
    "sg:phone":"+49 241/20676",
    "sg:postcode":"52064",
    "sg:province":"Nordrhein-Westfalen",
    "wof:name":"Marien-apotheke Helmut Koch Inh. Hermann-josef Kleine",
    "wof:placetype":"venue"
},
  "geometry": {"coordinates":[6.089286,50.769768],"type":"Point"}
}