{
  "type": "Feature",
  "properties": {
    "iso:country":"DE",
    "sg:address":"Bergheimer Str. 39",
    "sg:city":"Heidelberg",
    "sg:phone":"+49 6221/184069",
    "sg:postcode":"69115",
    "sg:province":"Baden-W\u00fcrttemberg",
    "wof:name":"H. Gayer",
    "wof:placetype":"venue"
},
  "geometry": {"coordinates":[8.6889019012,49.4083747864],"type":"Point"}
}