{
  "type": "Feature",
  "properties": {
    "iso:country":"DE",
    "sg:address":"Poststr. 6",
    "sg:city":"Bad Friedrichshall",
    "sg:phone":"+49 7136/7461",
    "sg:postcode":"74177",
    "sg:province":"Baden-W\u00fcrttemberg",
    "wof:name":"China-restaurant Asien",
    "wof:placetype":"venue"
},
  "geometry": {"coordinates":[9.1955947876,49.2332038879],"type":"Point"}
}