{
  "type": "Feature",
  "properties": {
    "iso:country":"DE",
    "sg:address":"Winnender Str. 6",
    "sg:city":"Backnang",
    "sg:phone":"+49 7191/953228",
    "sg:postcode":"71522",
    "sg:province":"Baden-W\u00fcrttemberg",
    "wof:name":"33er St\u00fcble",
    "wof:placetype":"venue"
},
  "geometry": {"coordinates":[9.4387741089,48.9346389771],"type":"Point"}
}