{
  "type": "Feature",
  "properties": {
    "iso:country":"DE",
    "sg:address":"Pestalozzistr. 23",
    "sg:city":"K\u00f6ln",
    "sg:phone":"+49 221/5907041",
    "sg:postcode":"50858",
    "sg:province":"Nordrhein-Westfalen",
    "wof:name":"Richard Kille",
    "wof:placetype":"venue"
},
  "geometry": {"coordinates":[6.8461298943,50.9366493225],"type":"Point"}
}