{
  "type": "Feature",
  "properties": {
    "iso:country":"DE",
    "sg:address":"N\u00fcdlinger Str. 11",
    "sg:city":"Bad Kissingen",
    "sg:phone":"+49 971/62861",
    "sg:postcode":"97688",
    "sg:province":"Bayern",
    "wof:name":"Helmut Reu\u00df",
    "wof:placetype":"venue"
},
  "geometry": {"coordinates":[10.072567,50.22982],"type":"Point"}
}