{
  "type": "Feature",
  "properties": {
    "iso:country":"DE",
    "sg:address":"Westendstr 3-4",
    "sg:city":"Schmalkalden",
    "sg:phone":"+49 3683/6860",
    "sg:postcode":"98574",
    "sg:province":"Th\u00fcringen",
    "wof:name":"Kbs Kran- Und Stahlbau B\u00e4r Gmbh",
    "wof:placetype":"venue"
},
  "geometry": {"coordinates":[10.442032814,50.7209320068],"type":"Point"}
}