{
  "type": "Feature",
  "properties": {
    "iso:country":"DE",
    "sg:address":"Br\u00fcckenstr. 6",
    "sg:city":"Ha\u00dffurt",
    "sg:phone":"+49 9521/8266",
    "sg:postcode":"97437",
    "sg:province":"Bayern",
    "wof:name":"Norbert Burkard",
    "wof:placetype":"venue"
},
  "geometry": {"coordinates":[10.506606102,50.0310630798],"type":"Point"}
}