{
  "type": "Feature",
  "properties": {
    "iso:country":"DE",
    "sg:address":"Kauperstr. 38",
    "sg:city":"Cottbus",
    "sg:phone":"+49 355/821088",
    "sg:postcode":"03044",
    "sg:province":"Brandenburg",
    "wof:name":"Thomas Ramisch Arzt F\u00fcr Allgemeinmedizin",
    "wof:placetype":"venue"
},
  "geometry": {"coordinates":[14.3491830826,51.7845687866],"type":"Point"}
}