{
  "type": "Feature",
  "properties": {
    "iso:country":"DE",
    "sg:address":"Goedeke-Michel-Str. 39",
    "sg:city":"Wangerland",
    "sg:phone":"+49 4425/1810",
    "sg:postcode":"26434",
    "sg:province":"Niedersachsen",
    "wof:name":"K. Richter",
    "wof:placetype":"venue"
},
  "geometry": {"coordinates":[8.024303,53.633366],"type":"Point"}
}