{
  "type": "Feature",
  "properties": {
    "iso:country":"DE",
    "sg:address":"Wildunger Str. 64a",
    "sg:city":"Stuttgart",
    "sg:phone":"+49 711/565054",
    "sg:postcode":"70372",
    "sg:province":"Baden-W\u00fcrttemberg",
    "wof:name":"Hans Haller Architekt",
    "wof:placetype":"venue"
},
  "geometry": {"coordinates":[9.227566,48.803368],"type":"Point"}
}