{
  "type": "Feature",
  "properties": {
    "iso:country":"DE",
    "sg:address":"Velberter Str. 154",
    "sg:city":"Heiligenhaus",
    "sg:postcode":"42579",
    "sg:province":"Nordrhein-Westfalen",
    "wof:name":"Hoops Und M\u00fcller Ger\u00fcstbau",
    "wof:placetype":"venue"
},
  "geometry": {"coordinates":[6.9989480972,51.3295478821],"type":"Point"}
}