{
  "type": "Feature",
  "properties": {
    "iso:country":"DE",
    "sg:address":"Steinbrunner Weg 20",
    "sg:city":"Battenberg",
    "sg:phone":"+49 6359/5925",
    "sg:postcode":"67271",
    "sg:province":"Rheinland-Pfalz",
    "wof:name":"Prof. Gerd V. Heene Architekt",
    "wof:placetype":"venue"
},
  "geometry": {"coordinates":[8.138875,49.535542],"type":"Point"}
}