{
  "type": "Feature",
  "properties": {
    "iso:country":"DE",
    "sg:address":"Wagnerstr. 7",
    "sg:city":"Lage",
    "sg:phone":"+49 5232/5507",
    "sg:postcode":"32791",
    "sg:province":"Nordrhein-Westfalen",
    "wof:name":"Friedbert Witte",
    "wof:placetype":"venue"
},
  "geometry": {"coordinates":[8.796543,51.999229],"type":"Point"}
}