{
  "type": "Feature",
  "properties": {
    "iso:country":"DE",
    "sg:address":"Zur Hohen Eich 6",
    "sg:city":"Kirchhain",
    "sg:phone":"+49 6422/1797",
    "sg:postcode":"35274",
    "sg:province":"Hessen",
    "wof:name":"Heinrich Birkenstock",
    "wof:placetype":"venue"
},
  "geometry": {"coordinates":[8.962618,50.829723],"type":"Point"}
}