{
  "type": "Feature",
  "properties": {
    "iso:country":"DE",
    "sg:address":"Raiffeisenstr. 28",
    "sg:city":"Bottrop",
    "sg:phone":"+49 2045/2627",
    "sg:postcode":"46244",
    "sg:province":"Nordrhein-Westfalen",
    "wof:name":"Automobile Marpe",
    "wof:placetype":"venue"
},
  "geometry": {"coordinates":[6.930273056,51.6119651794],"type":"Point"}
}