{
  "type": "Feature",
  "properties": {
    "iso:country":"DE",
    "sg:address":"Schreinerweg 10",
    "sg:city":"Lindlar",
    "sg:phone":"+49 2266/47400",
    "sg:postcode":"51789",
    "sg:province":"Nordrhein-Westfalen",
    "wof:name":"Kambium M\u00f6belwerkst\u00e4tte Gmbh",
    "wof:placetype":"venue"
},
  "geometry": {"coordinates":[7.4133820534,51.0259895325],"type":"Point"}
}