{
  "type": "Feature",
  "properties": {
    "iso:country":"DE",
    "sg:address":"B\u00fcrgerstr. 45",
    "sg:city":"Dresden",
    "sg:phone":"+49 351/8489417",
    "sg:postcode":"01127",
    "sg:province":"Sachsen",
    "wof:name":"Charlotte Engelhardt",
    "wof:placetype":"venue"
},
  "geometry": {"coordinates":[13.724264,51.077011],"type":"Point"}
}