{
  "type": "Feature",
  "properties": {
    "iso:country":"DE",
    "sg:address":"Hanauer Landstr. 6",
    "sg:city":"Kahl",
    "sg:phone":"+49 6188/2672",
    "sg:postcode":"63796",
    "sg:province":"Bayern",
    "wof:name":"Kurt Dresel",
    "wof:placetype":"venue"
},
  "geometry": {"coordinates":[9.005577,50.069866],"type":"Point"}
}