{
  "type": "Feature",
  "properties": {
    "iso:country":"DE",
    "sg:address":"Lindnerstra\u00dfe 4",
    "sg:city":"Oberhausen",
    "sg:phone":"+49 208/25815",
    "sg:postcode":"46149",
    "sg:province":"Nordrhein-Westfalen",
    "wof:name":"Kanuabteilung Tc69 - Kanuverein In Oberhausen",
    "wof:placetype":"venue"
},
  "geometry": {"coordinates":[6.857243,51.494694],"type":"Point"}
}