{
  "type": "Feature",
  "properties": {
    "iso:country":"DE",
    "sg:address":"Bahnhofstr. 18",
    "sg:city":"Horn-Bad Meinberg",
    "sg:phone":"+49 5234/2213",
    "sg:postcode":"32805",
    "sg:province":"Nordrhein-Westfalen",
    "wof:name":"Sch\u00f6nlau",
    "wof:placetype":"venue"
},
  "geometry": {"coordinates":[8.952287674,51.8748283386],"type":"Point"}
}