{
  "type": "Feature",
  "properties": {
    "iso:country":"DE",
    "sg:address":"Auf dem Sommerfeld 7",
    "sg:city":"Bergisch Gladbach",
    "sg:phone":"+49 2204/810865",
    "sg:postcode":"51429",
    "sg:province":"Nordrhein-Westfalen",
    "wof:name":"Wein-galerie-online",
    "wof:placetype":"venue"
},
  "geometry": {"coordinates":[7.1885299683,50.9814300537],"type":"Point"}
}