{
  "type": "Feature",
  "properties": {
    "iso:country":"DE",
    "sg:address":"Holstent\u00f6rn 9",
    "sg:city":"Kiel",
    "sg:phone":"+49 431/5051",
    "sg:postcode":"24149",
    "sg:province":"Schleswig-Holstein",
    "wof:name":"Lornsenschule Schleswig (gymnasium)",
    "wof:placetype":"venue"
},
  "geometry": {"coordinates":[10.189395,54.334698],"type":"Point"}
}