{
  "type": "Feature",
  "properties": {
    "iso:country":"DE",
    "sg:address":"Asamstr. 10a",
    "sg:city":"Ingolstadt",
    "sg:phone":"+49 841/64833",
    "sg:postcode":"85053",
    "sg:province":"Bayern",
    "wof:name":"Impuls Fitness Gmbh",
    "wof:placetype":"venue"
},
  "geometry": {"coordinates":[11.4391832352,48.7552566528],"type":"Point"}
}