{
  "type": "Feature",
  "properties": {
    "iso:country":"DE",
    "sg:address":"Am Gut Wolf 19-21",
    "sg:city":"Aachen",
    "sg:phone":"+49 241/9109100",
    "sg:postcode":"52070",
    "sg:province":"Nordrhein-Westfalen",
    "wof:name":"Stemmler Presse-vertrieb Gmbh & Co. Kg",
    "wof:placetype":"venue"
},
  "geometry": {"coordinates":[6.103453,50.788708],"type":"Point"}
}