{
  "type": "Feature",
  "properties": {
    "iso:country":"DE",
    "sg:address":"Wittbr\u00e4ucker Str. 374",
    "sg:city":"Dortmund",
    "sg:phone":"+49 231/481742",
    "sg:postcode":"44267",
    "sg:province":"Nordrhein-Westfalen",
    "wof:name":"C. Scholz",
    "wof:placetype":"venue"
},
  "geometry": {"coordinates":[7.5241308212,51.4640579224],"type":"Point"}
}