{
  "type": "Feature",
  "properties": {
    "iso:country":"DE",
    "sg:address":"Hauptstr 22",
    "sg:city":"Donzdorf",
    "sg:phone":"+49 7162/21021",
    "sg:postcode":"73072",
    "sg:province":"Baden-W\u00fcrttemberg",
    "wof:name":"Peppino Dress Gmbh & Co Kg",
    "wof:placetype":"venue"
},
  "geometry": {"coordinates":[9.804601,48.685955],"type":"Point"}
}