{
  "type": "Feature",
  "properties": {
    "iso:country":"DE",
    "sg:address":"M\u00e4rkische Str. 8",
    "sg:city":"Dortmund",
    "sg:phone":"+49 231/5760",
    "sg:postcode":"44135",
    "sg:province":"Nordrhein-Westfalen",
    "wof:name":"Siemens Ag Zwgndlg. Ruhr",
    "wof:placetype":"venue"
},
  "geometry": {"coordinates":[7.4689788818,51.5087585449],"type":"Point"}
}