{
  "type": "Feature",
  "properties": {
    "iso:country":"DE",
    "sg:address":"Lange Str. 22",
    "sg:city":"Badersleben",
    "sg:phone":"+49 39422/61450",
    "sg:postcode":"38836",
    "sg:province":"Sachsen-Anhalt",
    "wof:name":"Aschenbrenner Metallbau",
    "wof:placetype":"venue"
},
  "geometry": {"coordinates":[10.8871603012,51.98462677],"type":"Point"}
}