{
  "type": "Feature",
  "properties": {
    "iso:country":"DE",
    "sg:address":"Gneisenaustr. 17",
    "sg:city":"Mannheim",
    "sg:phone":"+49 621/795234",
    "sg:postcode":"68259",
    "sg:province":"Baden-W\u00fcrttemberg",
    "wof:name":"Bauer Marktanalyse",
    "wof:placetype":"venue"
},
  "geometry": {"coordinates":[8.523061,49.491283],"type":"Point"}
}