{
  "type": "Feature",
  "properties": {
    "iso:country":"DE",
    "sg:address":"\u00c4u\u00dfere Sulzfelder Str. 2",
    "sg:city":"Kitzingen",
    "sg:phone":"+49 9321/22693",
    "sg:postcode":"97318",
    "sg:province":"Bayern",
    "wof:name":"G. Pardo Inh. Gaspare Pardo",
    "wof:placetype":"venue"
},
  "geometry": {"coordinates":[10.1568403244,49.7286987305],"type":"Point"}
}