{
  "type": "Feature",
  "properties": {
    "iso:country":"DE",
    "sg:address":"Dr.-Leo-Ritter-Str. 47",
    "sg:city":"Regensburg",
    "sg:postcode":"93049",
    "sg:province":"Bayern",
    "wof:name":"Gk-systemtechnik Gmbh K\u00f6ck",
    "wof:placetype":"venue"
},
  "geometry": {"coordinates":[12.0553684235,49.0169715881],"type":"Point"}
}