{
  "type": "Feature",
  "properties": {
    "iso:country":"DE",
    "sg:address":"Weseler Str. 131",
    "sg:city":"Geldern",
    "sg:phone":"+49 2831/2506",
    "sg:postcode":"47608",
    "sg:province":"Nordrhein-Westfalen",
    "wof:name":"B & B Autoglas Und Reifenservice Gmbh",
    "wof:placetype":"venue"
},
  "geometry": {"coordinates":[6.3466801643,51.5225715637],"type":"Point"}
}