{
  "type": "Feature",
  "properties": {
    "iso:country":"DE",
    "sg:address":"Am Kaninchenberg 31",
    "sg:city":"Saarbr\u00fccken",
    "sg:phone":"+49 681/65482",
    "sg:postcode":"66123",
    "sg:province":"Saarland",
    "wof:name":"Gabriele Koebnick Rechtsanw\u00e4ltin",
    "wof:placetype":"venue"
},
  "geometry": {"coordinates":[7.0216288567,49.2301635742],"type":"Point"}
}