{
  "type": "Feature",
  "properties": {
    "iso:country":"DE",
    "sg:address":"Maulbeerallee",
    "sg:city":"Potsdam",
    "sg:phone":"+49 331/5053808",
    "sg:postcode":"14469",
    "sg:province":"Brandenburg",
    "wof:name":"Restaurant Cafe Drachenhaus",
    "wof:placetype":"venue"
},
  "geometry": {"coordinates":[13.0264644623,52.4040908813],"type":"Point"}
}