{
  "type": "Feature",
  "properties": {
    "iso:country":"DE",
    "sg:address":"Timmendorfer Str. 81",
    "sg:city":"Hamburg",
    "sg:phone":"+49 40/64789574",
    "sg:postcode":"22147",
    "sg:province":"Hamburg",
    "wof:name":"Josef Puers",
    "wof:placetype":"venue"
},
  "geometry": {"coordinates":[10.1316337585,53.603263855],"type":"Point"}
}