{
  "type": "Feature",
  "properties": {
    "iso:country":"DE",
    "sg:address":"Sch\u00f6nbornstr. 13",
    "sg:city":"Wiesentheid",
    "sg:phone":"+49 9383/336",
    "sg:postcode":"97353",
    "sg:province":"Bayern",
    "wof:name":"Blumenhaus Laudenbach",
    "wof:placetype":"venue"
},
  "geometry": {"coordinates":[10.345095,49.792526],"type":"Point"}
}