{
  "type": "Feature",
  "properties": {
    "iso:country":"DE",
    "sg:address":"Eibensteinstr. 16",
    "sg:city":"Thanstein",
    "sg:postcode":"92554",
    "sg:province":"Bayern",
    "wof:name":"Katholisches Pfarramt St. Josef",
    "wof:placetype":"venue"
},
  "geometry": {"coordinates":[12.4718532562,49.379032135],"type":"Point"}
}