{
  "type": "Feature",
  "properties": {
    "iso:country":"DE",
    "sg:address":"K\u00f6nigstrasse 17",
    "sg:city":"Kaiserslautern",
    "sg:phone":"+49 631/13900",
    "sg:postcode":"67655",
    "sg:province":"Rheinland-Pfalz",
    "wof:name":"Pandora Bildagentur",
    "wof:placetype":"venue"
},
  "geometry": {"coordinates":[7.764423,49.443195],"type":"Point"}
}