{
  "type": "Feature",
  "properties": {
    "iso:country":"DE",
    "sg:address":"Friedrich-Ludwig-Jahn-Str. 47",
    "sg:city":"Wittstock",
    "sg:phone":"+49 3394/712230",
    "sg:postcode":"16909",
    "sg:province":"Brandenburg",
    "wof:name":"T. Beck",
    "wof:placetype":"venue"
},
  "geometry": {"coordinates":[12.4965867996,53.1745605469],"type":"Point"}
}