{
  "type": "Feature",
  "properties": {
    "iso:country":"DE",
    "sg:address":"Werlte 2",
    "sg:city":"Nottuln",
    "sg:phone":"+49 2509/8481",
    "sg:postcode":"48301",
    "sg:province":"Nordrhein-Westfalen",
    "wof:name":"Ludger Bahrenberg",
    "wof:placetype":"venue"
},
  "geometry": {"coordinates":[7.427841,51.884212],"type":"Point"}
}