{
  "type": "Feature",
  "properties": {
    "iso:country":"DE",
    "sg:address":"Gartenstr. 52",
    "sg:city":"Niedererbach",
    "sg:phone":"+49 6485/911774",
    "sg:postcode":"56412",
    "sg:province":"Rheinland-Pfalz",
    "wof:name":"Praxis F\u00fcr Ambulante Dienste C. Ester",
    "wof:placetype":"venue"
},
  "geometry": {"coordinates":[7.96892,50.424011],"type":"Point"}
}