{
  "type": "Feature",
  "properties": {
    "iso:country":"DE",
    "sg:address":"Neugasse 1a",
    "sg:city":"Koblenz",
    "sg:phone":"+49 261",
    "sg:postcode":"56072",
    "sg:province":"Rheinland-Pfalz",
    "wof:name":"Computer-service Koblenz",
    "wof:placetype":"venue"
},
  "geometry": {"coordinates":[7.550128,50.364075],"type":"Point"}
}