{
  "type": "Feature",
  "properties": {
    "iso:country":"DE",
    "sg:address":"Hohenzollernstr 16",
    "sg:city":"Pforzheim",
    "sg:phone":"+49 7231/316478",
    "sg:postcode":"75177",
    "sg:province":"Baden-W\u00fcrttemberg",
    "wof:name":"Abnoba Heilmittel Gmbh",
    "wof:placetype":"venue"
},
  "geometry": {"coordinates":[8.708844,48.897003],"type":"Point"}
}