{
  "type": "Feature",
  "properties": {
    "iso:country":"DE",
    "sg:address":"Luikenweg 12",
    "sg:city":"Waiblingen",
    "sg:phone":"+49 7151/908393",
    "sg:postcode":"71334",
    "sg:province":"Baden-W\u00fcrttemberg",
    "wof:name":"Arcus Bauplanungs Gmbh",
    "wof:placetype":"venue"
},
  "geometry": {"coordinates":[9.322538,48.839886],"type":"Point"}
}