{
  "type": "Feature",
  "properties": {
    "iso:country":"DE",
    "sg:address":"Junkerstr. 62",
    "sg:city":"B\u00fcsingen",
    "sg:phone":"+49 7734/931487",
    "sg:postcode":"78266",
    "sg:province":"Baden-W\u00fcrttemberg",
    "wof:name":"K. Zeiler",
    "wof:placetype":"venue"
},
  "geometry": {"coordinates":[8.6900291443,47.6969070435],"type":"Point"}
}