{
  "type": "Feature",
  "properties": {
    "iso:country":"DE",
    "sg:address":"Kaiserstr. 4",
    "sg:city":"W\u00fcrzburg",
    "sg:phone":"+49 931/50764",
    "sg:postcode":"97070",
    "sg:province":"Bayern",
    "wof:name":"Vhv Versicherung",
    "wof:placetype":"venue"
},
  "geometry": {"coordinates":[9.9336938858,49.7978019714],"type":"Point"}
}