{
  "type": "Feature",
  "properties": {
    "iso:country":"DE",
    "sg:address":"strasse",
    "sg:city":"stadt",
    "sg:phone":"+49 0",
    "sg:postcode":"12345",
    "wof:name":"The 52 Studios",
    "wof:placetype":"venue"
},
  "geometry": {"coordinates":[-103.706192,48.727791],"type":"Point"}
}