{
  "type": "Feature",
  "properties": {
    "iso:country":"DE",
    "sg:address":"Bahnhofstr. 48",
    "sg:city":"Ostseebad Binz",
    "sg:phone":"+49 38393/32758",
    "sg:postcode":"18609",
    "sg:province":"Mecklenburg-Vorpommern",
    "wof:name":"Jens Tietb\u00f6hl Gmbh",
    "wof:placetype":"venue"
},
  "geometry": {"coordinates":[13.6081418991,54.3939971924],"type":"Point"}
}