{
  "type": "Feature",
  "properties": {
    "iso:country":"DE",
    "sg:address":"Postfach 1154:: 64854 Eppertshausen:: Germany.^^Bahnhofstr 13::",
    "sg:city":"Eppertshausen",
    "sg:phone":"+49 6071/30050",
    "sg:postcode":"64859",
    "sg:province":"Hessen",
    "wof:name":"Volksbank Eg Eppertshausen",
    "wof:placetype":"venue"
},
  "geometry": {"coordinates":[8.843413,49.946659],"type":"Point"}
}