{
  "type": "Feature",
  "properties": {
    "iso:country":"DE",
    "sg:address":"Hauptstr. 31",
    "sg:city":"G\u00e4ufelden",
    "sg:phone":"+49 7032/73371",
    "sg:postcode":"71126",
    "sg:province":"Baden-W\u00fcrttemberg",
    "wof:name":"Ev. Pfarramt Tailfingem",
    "wof:placetype":"venue"
},
  "geometry": {"coordinates":[8.8664493561,48.5497016907],"type":"Point"}
}