{
  "type": "Feature",
  "properties": {
    "iso:country":"DE",
    "sg:address":"Unterer Dornbusch 16",
    "sg:city":"Dautphetal",
    "sg:phone":"+49 6466/91053",
    "sg:postcode":"35232",
    "sg:province":"Hessen",
    "wof:name":"Pfeiffer Und Partner",
    "wof:placetype":"venue"
},
  "geometry": {"coordinates":[8.569217,50.852226],"type":"Point"}
}