{
  "type": "Feature",
  "properties": {
    "iso:country":"DE",
    "sg:address":"Burgstr. 2 A",
    "sg:city":"Sankt Augustin",
    "sg:phone":"+49 2241/315841",
    "sg:postcode":"53757",
    "sg:province":"Nordrhein-Westfalen",
    "wof:name":"Josef Braschos",
    "wof:placetype":"venue"
},
  "geometry": {"coordinates":[7.165407,50.789982],"type":"Point"}
}