{
  "type": "Feature",
  "properties": {
    "iso:country":"DE",
    "sg:address":"Sieker Landstr. 41",
    "sg:city":"Hamburg",
    "sg:phone":"+49 40/67510",
    "sg:postcode":"22143",
    "sg:province":"Hamburg",
    "wof:name":"Atlantik Film Kopierwerk Gmbh",
    "wof:placetype":"venue"
},
  "geometry": {"coordinates":[10.176264,53.607048],"type":"Point"}
}