{
  "type": "Feature",
  "properties": {
    "iso:country":"DE",
    "sg:address":"Blumenstr. 13",
    "sg:city":"F\u00fcrth",
    "sg:phone":"+49 911/770909",
    "sg:postcode":"90762",
    "sg:province":"Bayern",
    "wof:name":"G\u00fcnter E. Wich",
    "wof:placetype":"venue"
},
  "geometry": {"coordinates":[10.986836,49.475174],"type":"Point"}
}