{
  "type": "Feature",
  "properties": {
    "iso:country":"DE",
    "sg:address":"Am Kurpark 2",
    "sg:city":"Bad Hersfeld",
    "sg:phone":"+49 6621/919160",
    "sg:postcode":"36251",
    "sg:province":"Hessen",
    "wof:name":"Joachim Spangenberg",
    "wof:placetype":"venue"
},
  "geometry": {"coordinates":[9.7021980286,50.8643836975],"type":"Point"}
}