{
  "type": "Feature",
  "properties": {
    "iso:country":"DE",
    "sg:address":"Wetzendorfer Str. 270",
    "sg:city":"N\u00fcrnberg",
    "sg:phone":"+49 911/333269",
    "sg:postcode":"90427",
    "sg:province":"Bayern",
    "wof:name":"Konrad H\u00f6fler",
    "wof:placetype":"venue"
},
  "geometry": {"coordinates":[11.038069,49.471256],"type":"Point"}
}