{
  "type": "Feature",
  "properties": {
    "iso:country":"DE",
    "sg:address":"Kiesstr. 8",
    "sg:city":"Esslingen",
    "sg:phone":"+49 711/355515",
    "sg:postcode":"73728",
    "sg:province":"Baden-W\u00fcrttemberg",
    "wof:name":"Boutique Pia",
    "wof:placetype":"venue"
},
  "geometry": {"coordinates":[9.3119115829,48.7392196655],"type":"Point"}
}