{
  "type": "Feature",
  "properties": {
    "iso:country":"DE",
    "sg:address":"Neue Reihe 1",
    "sg:city":"Holdenstedt",
    "sg:phone":"+49 34659/60320",
    "sg:postcode":"06528",
    "sg:province":"Sachsen-Anhalt",
    "wof:name":"S. Goymann",
    "wof:placetype":"venue"
},
  "geometry": {"coordinates":[11.446148,51.475346],"type":"Point"}
}