{
  "type": "Feature",
  "properties": {
    "iso:country":"DE",
    "sg:address":"Dorfstr. 13A",
    "sg:city":"Eicklingen",
    "sg:phone":"+49 5144/5200",
    "sg:postcode":"29358",
    "sg:province":"Niedersachsen",
    "wof:name":"Fineline Atelier",
    "wof:placetype":"venue"
},
  "geometry": {"coordinates":[10.179145813,52.5518608093],"type":"Point"}
}