{
  "type": "Feature",
  "properties": {
    "iso:country":"DE",
    "sg:address":"Kiskerstr. 1",
    "sg:city":"Halle",
    "sg:phone":"+49 4952/0181170",
    "sg:postcode":"33790",
    "sg:province":"Nordrhein-Westfalen",
    "wof:name":"Baum-kisker Zum F\u00dcrstenhof Wilhelm Kisker Gmbh",
    "wof:placetype":"venue"
},
  "geometry": {"coordinates":[8.363803,52.061237],"type":"Point"}
}