{
  "type": "Feature",
  "properties": {
    "iso:country":"DE",
    "sg:address":"Bahnhofstr. 12",
    "sg:city":"Binsfeld",
    "sg:phone":"+49 6575/950500",
    "sg:postcode":"54518",
    "sg:province":"Rheinland-Pfalz",
    "wof:name":"M. Schommer & Sohn M\u00f6bel Und Innenausbau Gmbh",
    "wof:placetype":"venue"
},
  "geometry": {"coordinates":[6.70263,49.962833],"type":"Point"}
}