{
  "type": "Feature",
  "properties": {
    "iso:country":"DE",
    "sg:address":"Hermann-Buck-Weg 11-13",
    "sg:city":"Hamburg",
    "sg:phone":"+49 40/2201676",
    "sg:postcode":"22309",
    "sg:province":"Hamburg",
    "wof:name":"Theodor Rothe Gmbh",
    "wof:placetype":"venue"
},
  "geometry": {"coordinates":[10.051651001,53.606174469],"type":"Point"}
}