{
  "type": "Feature",
  "properties": {
    "iso:country":"DE",
    "sg:address":"Kehmstedter Weg 47",
    "sg:city":"Bleicherode",
    "sg:postcode":"99752",
    "sg:province":"Th\u00fcringen",
    "wof:name":"Future Health Care- Sales And Marketing",
    "wof:placetype":"venue"
},
  "geometry": {"coordinates":[10.5989017487,51.4557914734],"type":"Point"}
}