{
  "type": "Feature",
  "properties": {
    "iso:country":"DE",
    "sg:address":"Waldstr. 21",
    "sg:city":"Ellrich",
    "sg:postcode":"99755",
    "sg:province":"Th\u00fcringen",
    "wof:name":"Green Valley Ranch Ellrich",
    "wof:placetype":"venue"
},
  "geometry": {"coordinates":[10.6654071808,51.5961685181],"type":"Point"}
}