{
  "type": "Feature",
  "properties": {
    "iso:country":"DE",
    "sg:address":"Gozbertstr. 6",
    "sg:city":"M\u00fcnchen",
    "sg:phone":"+49 89/6923156",
    "sg:postcode":"81547",
    "sg:province":"Bayern",
    "wof:name":"A. Huber Immobilienmakler",
    "wof:placetype":"venue"
},
  "geometry": {"coordinates":[11.5771923065,48.1095046997],"type":"Point"}
}