{
  "type": "Feature",
  "properties": {
    "iso:country":"DE",
    "sg:address":"Am Brangenberg 4",
    "sg:city":"Velbert",
    "sg:phone":"+49 2051/23403",
    "sg:postcode":"42551",
    "sg:province":"Nordrhein-Westfalen",
    "wof:name":"Heiner Beninga",
    "wof:placetype":"venue"
},
  "geometry": {"coordinates":[7.0698,51.338734],"type":"Point"}
}