{
  "type": "Feature",
  "properties": {
    "iso:country":"DE",
    "sg:address":"Schulstr. 23",
    "sg:city":"Ferdinandshof",
    "sg:phone":"+49 39778/20342",
    "sg:postcode":"17379",
    "sg:province":"Mecklenburg-Vorpommern",
    "wof:name":"G. G\u00fcrtler",
    "wof:placetype":"venue"
},
  "geometry": {"coordinates":[13.886583,53.663761],"type":"Point"}
}