{
  "type": "Feature",
  "properties": {
    "iso:country":"DE",
    "sg:address":"Industriestr. 3-5",
    "sg:city":"Gladenbach",
    "sg:phone":"+49 4964/622060",
    "sg:postcode":"35075",
    "sg:province":"Hessen",
    "wof:name":"Kempkes Druckerei Offset + Buchdruck Gmbh",
    "wof:placetype":"venue"
},
  "geometry": {"coordinates":[8.5879154205,50.7700195312],"type":"Point"}
}