{
  "type": "Feature",
  "properties": {
    "iso:country":"DE",
    "sg:address":"Sulzbacher Str. 65",
    "sg:city":"Backnang",
    "sg:phone":"+49 7191/60666",
    "sg:postcode":"71522",
    "sg:province":"Baden-W\u00fcrttemberg",
    "wof:name":"R. Millen Anlageberater",
    "wof:placetype":"venue"
},
  "geometry": {"coordinates":[9.4347400665,48.9504585266],"type":"Point"}
}