{
  "type": "Feature",
  "properties": {
    "iso:country":"DE",
    "sg:address":"Ahlefelder Str. 31",
    "sg:city":"Gummersbach",
    "sg:phone":"+49 2261/98410",
    "sg:postcode":"51645",
    "sg:province":"Nordrhein-Westfalen",
    "wof:name":"Fercad Elektronikgesellschaft Mbh",
    "wof:placetype":"venue"
},
  "geometry": {"coordinates":[7.566533,51.002033],"type":"Point"}
}