{
  "type": "Feature",
  "properties": {
    "iso:country":"DE",
    "sg:address":"Lange Stra\u00dfe 9",
    "sg:city":"Stuttgart",
    "sg:phone":"+49 4971/1227480",
    "sg:postcode":"70173",
    "sg:province":"Baden-W\u00fcrttemberg",
    "wof:name":"Schweizerischer Bankverein, Repr\u00e4sentanz Stuttgart",
    "wof:placetype":"venue"
},
  "geometry": {"coordinates":[9.17383,48.775703],"type":"Point"}
}