{
  "type": "Feature",
  "properties": {
    "iso:country":"DE",
    "sg:address":"Kunstm\u00fchlestrasse 43",
    "sg:city":"Reutlingen-Pfullingen",
    "sg:phone":"+49 7121/99140",
    "sg:postcode":"72793",
    "sg:province":"Baden-W\u00fcrttemberg",
    "wof:name":"Klass&gessmann Spezialist Feiner Handarbeitsger\u00e4te",
    "wof:placetype":"venue"
},
  "geometry": {"coordinates":[9.22694,48.46574],"type":"Point"}
}