{
  "type": "Feature",
  "properties": {
    "iso:country":"DE",
    "sg:address":"Werner-von-Siemens-Str. 13",
    "sg:city":"Meitingen",
    "sg:phone":"+49 8271/2338",
    "sg:postcode":"86405",
    "sg:province":"Bayern",
    "wof:name":"Valentin Riebel",
    "wof:placetype":"venue"
},
  "geometry": {"coordinates":[10.855821,48.551243],"type":"Point"}
}