{
  "type": "Feature",
  "properties": {
    "iso:country":"DE",
    "sg:address":"Grasweg 50",
    "sg:city":"Buseck",
    "sg:phone":"+49 6408/92333",
    "sg:postcode":"35418",
    "sg:province":"Hessen",
    "wof:name":"Klaus Henning",
    "wof:placetype":"venue"
},
  "geometry": {"coordinates":[8.760974884,50.6122550964],"type":"Point"}
}