{
  "type": "Feature",
  "properties": {
    "iso:country":"DE",
    "sg:address":"Zum Jagdhaus 7",
    "sg:city":"Kaiserslautern",
    "sg:phone":"+49 631/357190",
    "sg:postcode":"67661",
    "sg:province":"Rheinland-Pfalz",
    "wof:name":"Josef Sp\u00f6tzl",
    "wof:placetype":"venue"
},
  "geometry": {"coordinates":[7.7134308815,49.3984947205],"type":"Point"}
}