{
  "type": "Feature",
  "properties": {
    "iso:country":"DE",
    "sg:address":"Rudolfstr. 12",
    "sg:city":"Durmersheim",
    "sg:phone":"+49 7245/937780",
    "sg:postcode":"76448",
    "sg:province":"Baden-W\u00fcrttemberg",
    "wof:name":"Twk-kastner Gmbh & Co. Kg",
    "wof:placetype":"venue"
},
  "geometry": {"coordinates":[8.266786,48.930958],"type":"Point"}
}