{
  "type": "Feature",
  "properties": {
    "iso:country":"DE",
    "sg:address":"Haingasse 11",
    "sg:city":"Frankfurt",
    "sg:phone":"+49 6109/22297",
    "sg:postcode":"60388",
    "sg:province":"Hessen",
    "wof:name":"Karl Schaller",
    "wof:placetype":"venue"
},
  "geometry": {"coordinates":[8.756175,50.157341],"type":"Point"}
}