{
  "type": "Feature",
  "properties": {
    "iso:country":"DE",
    "sg:address":"Zum Rundling 5",
    "sg:city":"Zethlingen",
    "sg:phone":"+49 3901/37439",
    "sg:postcode":"39624",
    "sg:province":"Sachsen-Anhalt",
    "wof:name":"Jens Pl\u00f6nnigs",
    "wof:placetype":"venue"
},
  "geometry": {"coordinates":[11.2537202835,52.7048568726],"type":"Point"}
}