{
  "type": "Feature",
  "properties": {
    "iso:country":"DE",
    "sg:address":"Feldstr. 1",
    "sg:city":"Bremerhaven",
    "sg:phone":"+49 471/301950",
    "sg:postcode":"27574",
    "sg:province":"Bremen",
    "wof:name":"Bund F\u00fcr Umwelt Und Naturschutz Deutschland",
    "wof:placetype":"venue"
},
  "geometry": {"coordinates":[8.6018800735,53.5297584534],"type":"Point"}
}