{
  "type": "Feature",
  "properties": {
    "iso:country":"DE",
    "sg:address":"Strangenh\u00e4uschen 18",
    "sg:city":"Aachen",
    "sg:phone":"+49 241/918010",
    "sg:postcode":"52070",
    "sg:province":"Nordrhein-Westfalen",
    "wof:name":"Fest- Und Partyzeltverleih Alwin Fiebus Gmbh",
    "wof:placetype":"venue"
},
  "geometry": {"coordinates":[6.112816,50.801006],"type":"Point"}
}