{
  "type": "Feature",
  "properties": {
    "iso:country":"DE",
    "sg:address":"Deichstr. 27",
    "sg:city":"Stendal",
    "sg:phone":"+49 3931/213137",
    "sg:postcode":"39576",
    "sg:province":"Sachsen-Anhalt",
    "wof:name":"Hinze",
    "wof:placetype":"venue"
},
  "geometry": {"coordinates":[11.859335,52.60358],"type":"Point"}
}