{
  "type": "Feature",
  "properties": {
    "iso:country":"DE",
    "sg:address":"Hochweg 69",
    "sg:city":"Regensburg",
    "sg:phone":"+49 941/22458",
    "sg:postcode":"93049",
    "sg:province":"Bayern",
    "wof:name":"Paulin Werkst\u00e4tten Gmbh & Co. Kg",
    "wof:placetype":"venue"
},
  "geometry": {"coordinates":[12.0643177032,49.0208625793],"type":"Point"}
}