{
  "type": "Feature",
  "properties": {
    "iso:country":"DE",
    "sg:address":"Alberodaer Str. 143",
    "sg:city":"Aue",
    "sg:phone":"+49 3771/55710",
    "sg:postcode":"08280",
    "sg:province":"Sachsen",
    "wof:name":"Walter M\u00fcller",
    "wof:placetype":"venue"
},
  "geometry": {"coordinates":[12.70879,50.614853],"type":"Point"}
}