{
  "type": "Feature",
  "properties": {
    "iso:country":"DE",
    "sg:address":"Isenacker 10",
    "sg:city":"Soest",
    "sg:phone":"+49 2921/2144",
    "sg:postcode":"59494",
    "sg:province":"Nordrhein-Westfalen",
    "wof:name":"Architekturb\u00fcro Rosskothen Inh. Dipl. Ing. Gerd Kordes",
    "wof:placetype":"venue"
},
  "geometry": {"coordinates":[8.10737,51.570114],"type":"Point"}
}