{
  "type": "Feature",
  "properties": {
    "iso:country":"DE",
    "sg:address":"Neuengammer Hausdeich 260",
    "sg:city":"Hamburg",
    "sg:phone":"+49 40/7231363",
    "sg:postcode":"21039",
    "sg:province":"Hamburg",
    "wof:name":"R. Wulff & Sohn",
    "wof:placetype":"venue"
},
  "geometry": {"coordinates":[10.2201299667,53.4465904236],"type":"Point"}
}