{
  "type": "Feature",
  "properties": {
    "iso:country":"DE",
    "sg:address":"Asperger Str. 46",
    "sg:city":"Ludwigsburg",
    "sg:phone":"+49 7141/927998",
    "sg:postcode":"71634",
    "sg:province":"Baden-W\u00fcrttemberg",
    "wof:name":"R.-f. Erhard",
    "wof:placetype":"venue"
},
  "geometry": {"coordinates":[9.18399,48.897419],"type":"Point"}
}