{
  "type": "Feature",
  "properties": {
    "iso:country":"DE",
    "sg:address":"Neue Steinmetzstr. 6",
    "sg:city":"Berlin",
    "sg:phone":"+49 30/7875146",
    "sg:postcode":"10827",
    "sg:province":"Berlin",
    "wof:name":"Claudia Schweitzer",
    "wof:placetype":"venue"
},
  "geometry": {"coordinates":[13.3624763489,52.4912261963],"type":"Point"}
}