{
  "type": "Feature",
  "properties": {
    "iso:country":"DE",
    "sg:address":"Wilhelmstr. 14",
    "sg:city":"Siegburg",
    "sg:phone":"+49 2241/64874",
    "sg:postcode":"53721",
    "sg:province":"Nordrhein-Westfalen",
    "wof:name":"Vhv-versicherungen Uwe Rohoff",
    "wof:placetype":"venue"
},
  "geometry": {"coordinates":[7.2054810524,50.7934074402],"type":"Point"}
}