{
  "type": "Feature",
  "properties": {
    "iso:country":"DE",
    "sg:address":"Neuer Weg 12",
    "sg:city":"Altenburg",
    "sg:phone":"+49 3447/830601",
    "sg:postcode":"04600",
    "sg:province":"Th\u00fcringen",
    "wof:name":"Werner Kraft Patentanwalt",
    "wof:placetype":"venue"
},
  "geometry": {"coordinates":[12.4413833618,51.0094604492],"type":"Point"}
}