{
  "type": "Feature",
  "properties": {
    "iso:country":"DE",
    "sg:address":"Dorfstr. 30a",
    "sg:city":"Lohm",
    "sg:phone":"+49 33973/52297",
    "sg:postcode":"16845",
    "sg:province":"Brandenburg",
    "wof:name":"W. Bork",
    "wof:placetype":"venue"
},
  "geometry": {"coordinates":[12.314818,52.862743],"type":"Point"}
}