{
  "type": "Feature",
  "properties": {
    "iso:country":"DE",
    "sg:address":"Im Rheinblick 21",
    "sg:city":"Weitersburg",
    "sg:phone":"+49 2622/4405",
    "sg:postcode":"56191",
    "sg:province":"Rheinland-Pfalz",
    "wof:name":"Ludwig Korell Steuerberater",
    "wof:placetype":"venue"
},
  "geometry": {"coordinates":[7.592315197,50.4129180908],"type":"Point"}
}