{
  "type": "Feature",
  "properties": {
    "iso:country":"DE",
    "sg:address":"Moosweg 4",
    "sg:city":"Hohberg",
    "sg:phone":"+49 7808/636",
    "sg:postcode":"77749",
    "sg:province":"Baden-W\u00fcrttemberg",
    "wof:name":"J\u00f6rg Runge Masseur",
    "wof:placetype":"venue"
},
  "geometry": {"coordinates":[7.916789,48.423809],"type":"Point"}
}