{
  "type": "Feature",
  "properties": {
    "iso:country":"DE",
    "sg:address":"Holzhofall. 19",
    "sg:city":"Darmstadt",
    "sg:phone":"+49 4961/5136210",
    "sg:postcode":"64295",
    "sg:province":"Hessen",
    "wof:name":"Newport Gmbh",
    "wof:placetype":"venue"
},
  "geometry": {"coordinates":[8.6413173676,49.8650474548],"type":"Point"}
}