{
  "type": "Feature",
  "properties": {
    "iso:country":"DE",
    "sg:address":"Fuhrmannweg 4",
    "sg:city":"Bad Zwischenahn",
    "sg:phone":"+49 4403/8742",
    "sg:postcode":"26160",
    "sg:province":"Niedersachsen",
    "wof:name":"Wolf Haye",
    "wof:placetype":"venue"
},
  "geometry": {"coordinates":[8.040688,53.248554],"type":"Point"}
}