{
  "type": "Feature",
  "properties": {
    "iso:country":"DE",
    "sg:address":"Friedrichstr. 17",
    "sg:city":"Wittlich",
    "sg:phone":"+49 6571/7202",
    "sg:postcode":"54516",
    "sg:province":"Rheinland-Pfalz",
    "wof:name":"China-restaurant Dong-fong",
    "wof:placetype":"venue"
},
  "geometry": {"coordinates":[6.8936839104,49.9876174927],"type":"Point"}
}