{
  "type": "Feature",
  "properties": {
    "iso:country":"DE",
    "sg:address":"Hagener Str. 257",
    "sg:city":"Dortmund",
    "sg:phone":"+49 231/733675",
    "sg:postcode":"44229",
    "sg:province":"Nordrhein-Westfalen",
    "wof:name":"K. Holle",
    "wof:placetype":"venue"
},
  "geometry": {"coordinates":[7.455831,51.459148],"type":"Point"}
}