{
  "type": "Feature",
  "properties": {
    "iso:country":"DE",
    "sg:address":"Stockweg 4",
    "sg:city":"Inzigkofen",
    "sg:phone":"+49 7575/5231",
    "sg:postcode":"72514",
    "sg:province":"Baden-W\u00fcrttemberg",
    "wof:name":"H. Bayram",
    "wof:placetype":"venue"
},
  "geometry": {"coordinates":[9.130301,48.039669],"type":"Point"}
}