{
  "type": "Feature",
  "properties": {
    "iso:country":"DE",
    "sg:address":"Auguststr. 58",
    "sg:city":"K\u00f6ln",
    "sg:postcode":"50733",
    "sg:province":"Nordrhein-Westfalen",
    "wof:name":"Kath. \u00d6ffentliche Bibliothek St. Marien",
    "wof:placetype":"venue"
},
  "geometry": {"coordinates":[6.951699,50.963863],"type":"Point"}
}