{
  "type": "Feature",
  "properties": {
    "iso:country":"DE",
    "sg:address":"Neust\u00e4dter Str. 61",
    "sg:city":"Titisee-Neustadt",
    "sg:phone":"+49 7651/8219",
    "sg:postcode":"79822",
    "sg:province":"Baden-W\u00fcrttemberg",
    "wof:name":"Paulina Und Rudolf Kaltenbach",
    "wof:placetype":"venue"
},
  "geometry": {"coordinates":[8.1574430466,47.9064292908],"type":"Point"}
}