{
  "type": "Feature",
  "properties": {
    "iso:country":"DE",
    "sg:address":"Alte Krefelder Str. 5",
    "sg:city":"Krefeld",
    "sg:phone":"+49 2151/483843",
    "sg:postcode":"47829",
    "sg:province":"Nordrhein-Westfalen",
    "wof:name":"M. Wieland",
    "wof:placetype":"venue"
},
  "geometry": {"coordinates":[6.649224,51.353619],"type":"Point"}
}