{
  "type": "Feature",
  "properties": {
    "iso:country":"DE",
    "sg:address":"Dittenberger Str. 8",
    "sg:city":"Halle",
    "sg:phone":"+49 345/501083",
    "sg:postcode":"06114",
    "sg:province":"Sachsen-Anhalt",
    "wof:name":"Gabriele Mehlhose",
    "wof:placetype":"venue"
},
  "geometry": {"coordinates":[11.9791812897,51.4913253784],"type":"Point"}
}