{
  "type": "Feature",
  "properties": {
    "iso:country":"DE",
    "sg:address":"Industriestr. 10",
    "sg:city":"Schlangen",
    "sg:phone":"+49 5252/8008",
    "sg:postcode":"33189",
    "sg:province":"Nordrhein-Westfalen",
    "wof:name":"F. Kohlwes Schausteller",
    "wof:placetype":"venue"
},
  "geometry": {"coordinates":[8.829862,51.800926],"type":"Point"}
}