{
  "type": "Feature",
  "properties": {
    "iso:country":"DE",
    "sg:address":"Nordstr 48",
    "sg:city":"Grefrath",
    "sg:phone":"+49 2158/911606",
    "sg:postcode":"47929",
    "sg:province":"Nordrhein-Westfalen",
    "wof:name":"Cada Deko- Und Heimtextilien Gmbh",
    "wof:placetype":"venue"
},
  "geometry": {"coordinates":[6.3374009132,51.339679718],"type":"Point"}
}