{
  "type": "Feature",
  "properties": {
    "iso:country":"DE",
    "sg:address":"K\u00e4sb\u00fchlstr. 1-2",
    "sg:city":"Allmersbach",
    "sg:phone":"+49 7191/5040",
    "sg:postcode":"71573",
    "sg:province":"Baden-W\u00fcrttemberg",
    "wof:name":"Hotel-restaurant L\u00f6wen",
    "wof:placetype":"venue"
},
  "geometry": {"coordinates":[9.4852657318,48.9081268311],"type":"Point"}
}