{
  "type": "Feature",
  "properties": {
    "iso:country":"DE",
    "sg:address":"Industriestr. 7",
    "sg:city":"Altenbeken",
    "sg:phone":"+49 5255/930871",
    "sg:postcode":"33184",
    "sg:province":"Nordrhein-Westfalen",
    "wof:name":"Natursteinzentrum Buke Gmbh",
    "wof:placetype":"venue"
},
  "geometry": {"coordinates":[8.9474344254,51.7302436829],"type":"Point"}
}