{
  "type": "Feature",
  "properties": {
    "iso:country":"DE",
    "sg:address":"S\u00fcderstr. 36",
    "sg:city":"J\u00fcbek",
    "sg:postcode":"24855",
    "sg:province":"Schleswig-Holstein",
    "wof:name":"Ampere Geest Windpark Gmbh & Co. Kg",
    "wof:placetype":"venue"
},
  "geometry": {"coordinates":[9.404062,54.55513],"type":"Point"}
}