{
  "type": "Feature",
  "properties": {
    "iso:country":"DE",
    "sg:address":"Asternweg 4",
    "sg:city":"Walluf",
    "sg:phone":"+49 6123/71572",
    "sg:postcode":"65396",
    "sg:province":"Hessen",
    "wof:name":"Htb Eigenheimbau Gmbh",
    "wof:placetype":"venue"
},
  "geometry": {"coordinates":[8.1563453674,50.0422401428],"type":"Point"}
}