{
  "type": "Feature",
  "properties": {
    "iso:country":"DE",
    "sg:address":"Hohentorstr. 22",
    "sg:city":"Lassan",
    "sg:phone":"+49 38374/80255",
    "sg:postcode":"17440",
    "sg:province":"Mecklenburg-Vorpommern",
    "wof:name":"Ch. Lehmann",
    "wof:placetype":"venue"
},
  "geometry": {"coordinates":[13.8477516174,53.9469184875],"type":"Point"}
}