{
  "type": "Feature",
  "properties": {
    "iso:country":"DE",
    "sg:address":"Behringstr. 15",
    "sg:city":"Eckental",
    "sg:phone":"+49 9126/4701",
    "sg:postcode":"90542",
    "sg:province":"Bayern",
    "wof:name":"Novisport Maier & Persch",
    "wof:placetype":"venue"
},
  "geometry": {"coordinates":[11.219766,49.588753],"type":"Point"}
}