{
  "type": "Feature",
  "properties": {
    "iso:country":"DE",
    "sg:address":"Querstr. 8",
    "sg:city":"Ebeleben",
    "sg:phone":"+49 36020/875",
    "sg:postcode":"99713",
    "sg:province":"Th\u00fcringen",
    "wof:name":"Teag Th\u00fcringer Energie Ag",
    "wof:placetype":"venue"
},
  "geometry": {"coordinates":[10.735286,51.286018],"type":"Point"}
}