{
  "type": "Feature",
  "properties": {
    "iso:country":"DE",
    "sg:address":"Hundseckstr. 24",
    "sg:city":"Forbach",
    "sg:phone":"+49 7220/272",
    "sg:postcode":"76596",
    "sg:province":"Baden-W\u00fcrttemberg",
    "wof:name":"Hotel Feiner Schnabel",
    "wof:placetype":"venue"
},
  "geometry": {"coordinates":[8.2692451477,48.6211738586],"type":"Point"}
}