{
  "type": "Feature",
  "properties": {
    "iso:country":"DE",
    "sg:address":"Aachener Str. 98",
    "sg:city":"Herzogenrath",
    "sg:phone":"+49 2406/4253",
    "sg:postcode":"52134",
    "sg:province":"Nordrhein-Westfalen",
    "wof:name":"T. Peters",
    "wof:placetype":"venue"
},
  "geometry": {"coordinates":[6.081,50.862579],"type":"Point"}
}