{
  "type": "Feature",
  "properties": {
    "iso:country":"DE",
    "sg:address":"Hauptstr. 25",
    "sg:city":"Kinding",
    "sg:phone":"+49 8467/321",
    "sg:postcode":"85125",
    "sg:province":"Bayern",
    "wof:name":"Hotel-restaurant Heckl",
    "wof:placetype":"venue"
},
  "geometry": {"coordinates":[11.3649568558,48.9929504395],"type":"Point"}
}