{
  "type": "Feature",
  "properties": {
    "iso:country":"DE",
    "sg:address":"Wilhelmshavener Str. 2",
    "sg:city":"Berlin",
    "sg:phone":"+49 30/2510064",
    "sg:postcode":"10551",
    "sg:province":"Berlin",
    "wof:name":"Marianne Porep",
    "wof:placetype":"venue"
},
  "geometry": {"coordinates":[13.341559,52.527142],"type":"Point"}
}