{
  "type": "Feature",
  "properties": {
    "iso:country":"DE",
    "sg:address":"Gartenstra\u00dfe 31",
    "sg:city":"G\u00f6ppingen",
    "sg:phone":"+49 7161",
    "sg:postcode":"73033",
    "sg:province":"Baden-W\u00fcrttemberg",
    "wof:name":"Rettungshundestaffel Juh G\u00f6ppingen",
    "wof:placetype":"venue"
},
  "geometry": {"coordinates":[9.655416,48.700508],"type":"Point"}
}