{
  "type": "Feature",
  "properties": {
    "iso:country":"DE",
    "sg:address":"Kobellstr. 4",
    "sg:city":"M\u00fcnchen",
    "sg:phone":"+49 89/5446770",
    "sg:postcode":"80336",
    "sg:province":"Bayern",
    "wof:name":"Bbv Computer-dienst Gmbh",
    "wof:placetype":"venue"
},
  "geometry": {"coordinates":[11.5542802811,48.1291313171],"type":"Point"}
}