{
  "type": "Feature",
  "properties": {
    "iso:country":"DE",
    "sg:address":"Akazienweg 1",
    "sg:city":"Aspach",
    "sg:phone":"+49 7191/366050",
    "sg:postcode":"71546",
    "sg:province":"Baden-W\u00fcrttemberg",
    "wof:name":"H & B Servicegesellschaft F\u00fcr B\u00fcro Organisation",
    "wof:placetype":"venue"
},
  "geometry": {"coordinates":[9.40712,48.99205],"type":"Point"}
}