{
  "type": "Feature",
  "properties": {
    "iso:country":"DE",
    "sg:address":"Mirbachstr. 2 a",
    "sg:city":"Bonn",
    "sg:phone":"+49 228/357626",
    "sg:postcode":"53173",
    "sg:province":"Nordrhein-Westfalen",
    "wof:name":"Hotel Patricia",
    "wof:placetype":"venue"
},
  "geometry": {"coordinates":[7.1653981209,50.6867027283],"type":"Point"}
}