{
  "type": "Feature",
  "properties": {
    "iso:country":"DE",
    "sg:address":"Am Steinsgraben 1",
    "sg:city":"Friedland",
    "sg:phone":"+49 5592/1234",
    "sg:postcode":"37133",
    "sg:province":"Niedersachsen",
    "wof:name":"Karl Hecke",
    "wof:placetype":"venue"
},
  "geometry": {"coordinates":[10.009745,51.425781],"type":"Point"}
}