{
  "type": "Feature",
  "properties": {
    "iso:country":"DE",
    "sg:address":"Ziegeleistr 18",
    "sg:city":"Gemmingen",
    "sg:phone":"+49 7267/911094",
    "sg:postcode":"75050",
    "sg:province":"Baden-W\u00fcrttemberg",
    "wof:name":"Hans Joch Maschinenbau",
    "wof:placetype":"venue"
},
  "geometry": {"coordinates":[8.98165,49.149586],"type":"Point"}
}