{
  "type": "Feature",
  "properties": {
    "iso:country":"DE",
    "sg:address":"Auf der Bleiche 42",
    "sg:city":"Freiburg",
    "sg:phone":"+49 761/82144",
    "sg:postcode":"79110",
    "sg:province":"Baden-W\u00fcrttemberg",
    "wof:name":"Ki Technik Gesellschaft F\u00fcr",
    "wof:placetype":"venue"
},
  "geometry": {"coordinates":[7.8087658882,48.0160598755],"type":"Point"}
}