{
  "type": "Feature",
  "properties": {
    "iso:country":"DE",
    "sg:address":"Stadtplatz 4",
    "sg:city":"Hemau",
    "sg:phone":"+49 9491/1021",
    "sg:postcode":"93155",
    "sg:province":"Bayern",
    "wof:name":"Stadtwerke Hemau",
    "wof:placetype":"venue"
},
  "geometry": {"coordinates":[11.782222,49.051933],"type":"Point"}
}