{
  "type": "Feature",
  "properties": {
    "iso:country":"DE",
    "sg:address":"Schraplauer Str. 32b",
    "sg:city":"R\u00f6blingen am See",
    "sg:postcode":"06317",
    "sg:province":"Sachsen-Anhalt",
    "wof:name":"Mas Ketzenberg Gmbh",
    "wof:placetype":"venue"
},
  "geometry": {"coordinates":[11.6715106964,51.4575538635],"type":"Point"}
}