{
  "type": "Feature",
  "properties": {
    "iso:country":"DE",
    "sg:address":"Wulferhooks Weg 33",
    "sg:city":"Coesfeld",
    "sg:phone":"+49 2546/275",
    "sg:postcode":"48653",
    "sg:province":"Nordrhein-Westfalen",
    "wof:name":"B\u00e4uerliche Bezugs- Und Absatzgenossenschaft Eg",
    "wof:placetype":"venue"
},
  "geometry": {"coordinates":[7.190143,51.890198],"type":"Point"}
}