{
  "type": "Feature",
  "properties": {
    "iso:country":"DE",
    "sg:address":"Dahlener Str. 25",
    "sg:city":"Schildau",
    "sg:phone":"+49 34221/50341",
    "sg:postcode":"04889",
    "sg:province":"Sachsen",
    "wof:name":"J\u00f6rg Rentsch",
    "wof:placetype":"venue"
},
  "geometry": {"coordinates":[12.9728899002,51.4813194275],"type":"Point"}
}