{
  "type": "Feature",
  "properties": {
    "iso:country":"DE",
    "sg:address":"Talstr. 2a",
    "sg:city":"Bergneustadt",
    "sg:phone":"+49 2261/47506",
    "sg:postcode":"51702",
    "sg:province":"Nordrhein-Westfalen",
    "wof:name":"Reiseb\u00fcro Marina Ruckes",
    "wof:placetype":"venue"
},
  "geometry": {"coordinates":[7.6528902054,51.0206985474],"type":"Point"}
}