{
  "type": "Feature",
  "properties": {
    "iso:country":"DE",
    "sg:address":"Gartenstr. 14",
    "sg:city":"Elze",
    "sg:phone":"+49 5068/2622",
    "sg:postcode":"31008",
    "sg:province":"Niedersachsen",
    "wof:name":"Bauverein Elze Eg",
    "wof:placetype":"venue"
},
  "geometry": {"coordinates":[9.7331409454,52.1135063171],"type":"Point"}
}