{
  "type": "Feature",
  "properties": {
    "iso:country":"DE",
    "sg:address":"Kreuzbergstr. 57",
    "sg:city":"Sandberg",
    "sg:phone":"+49 9701/207",
    "sg:postcode":"97657",
    "sg:province":"Bayern",
    "wof:name":"Sparkasse",
    "wof:placetype":"venue"
},
  "geometry": {"coordinates":[10.006848,50.348782],"type":"Point"}
}