{
  "type": "Feature",
  "properties": {
    "iso:country":"DE",
    "sg:address":"Am Weiher 24",
    "sg:city":"Elsdorf",
    "sg:phone":"+49 2271/767488",
    "sg:postcode":"50189",
    "sg:province":"Nordrhein-Westfalen",
    "wof:name":"Richter & Sohn Gmbh",
    "wof:placetype":"venue"
},
  "geometry": {"coordinates":[6.6315732002,50.9114303589],"type":"Point"}
}