{
  "type": "Feature",
  "properties": {
    "iso:country":"DE",
    "sg:address":"Staufener Str. 11",
    "sg:city":"Freiburg",
    "sg:phone":"+49 761/494494",
    "sg:postcode":"79115",
    "sg:province":"Baden-W\u00fcrttemberg",
    "wof:name":"Brigitte H\u00fcbner Reprotechnik",
    "wof:placetype":"venue"
},
  "geometry": {"coordinates":[7.8208670616,47.991645813],"type":"Point"}
}