{
  "type": "Feature",
  "properties": {
    "iso:country":"DE",
    "sg:address":"Marchandstr. 6",
    "sg:city":"Berlin",
    "sg:phone":"+49 30/7679140",
    "sg:postcode":"12249",
    "sg:province":"Berlin",
    "wof:name":"Bav Berg Audio Vertriebs Gmbh",
    "wof:placetype":"venue"
},
  "geometry": {"coordinates":[13.3542404175,52.4203834534],"type":"Point"}
}