{
  "type": "Feature",
  "properties": {
    "iso:country":"DE",
    "sg:address":"Gindericher Str. 10",
    "sg:city":"Wesel",
    "sg:phone":"+49 2803/247",
    "sg:postcode":"46487",
    "sg:province":"Nordrhein-Westfalen",
    "wof:name":"Lindenhof",
    "wof:placetype":"venue"
},
  "geometry": {"coordinates":[6.5648641586,51.6313171387],"type":"Point"}
}