{
  "type": "Feature",
  "properties": {
    "iso:country":"DE",
    "sg:address":"Waldstra\u00dfe 14",
    "sg:city":"Linden",
    "sg:phone":"+49 2666/95140",
    "sg:postcode":"57629",
    "sg:province":"Rheinland-Pfalz",
    "wof:name":"Sch\u00e4fer Maschinenbau & Freizeittechnik",
    "wof:placetype":"venue"
},
  "geometry": {"coordinates":[7.851580143,50.600151062],"type":"Point"}
}