{
  "type": "Feature",
  "properties": {
    "iso:country":"DE",
    "sg:address":"Rodach",
    "sg:city":"Rodach",
    "sg:phone":"+49 9564/1404",
    "sg:postcode":"96476",
    "sg:province":"Bayern",
    "wof:name":"Raiffeisenbank Gro\u00dfwalbur-wiesenf.",
    "wof:placetype":"venue"
},
  "geometry": {"coordinates":[10.8013,50.337078],"type":"Point"}
}