{
  "type": "Feature",
  "properties": {
    "iso:country":"DE",
    "sg:address":"Auf der H\u00f6he 9",
    "sg:city":"Neustadt",
    "sg:phone":"+49 9161/4758",
    "sg:postcode":"91413",
    "sg:province":"Bayern",
    "wof:name":"Peter Gabor",
    "wof:placetype":"venue"
},
  "geometry": {"coordinates":[10.6270780563,49.5816688538],"type":"Point"}
}