{
  "type": "Feature",
  "properties": {
    "iso:country":"DE",
    "sg:address":"M\u00f6rikestr. 11",
    "sg:city":"Deggingen",
    "sg:phone":"+49 7334/920439",
    "sg:postcode":"73326",
    "sg:province":"Baden-W\u00fcrttemberg",
    "wof:name":"Bwb Betriebswirtschaftliche Beratungsgesellschaft Mbh",
    "wof:placetype":"venue"
},
  "geometry": {"coordinates":[9.717893,48.599297],"type":"Point"}
}