{
  "type": "Feature",
  "properties": {
    "iso:country":"DE",
    "sg:address":"Weiherweg 2",
    "sg:city":"Langenzenn",
    "sg:postcode":"90579",
    "sg:province":"Bayern",
    "wof:name":"Gft Glas Und Fassaden- Technik Gmbh",
    "wof:placetype":"venue"
},
  "geometry": {"coordinates":[10.7551412582,49.4897918701],"type":"Point"}
}