{
  "type": "Feature",
  "properties": {
    "iso:country":"DE",
    "sg:address":"Gartenheimsteg 3",
    "sg:city":"Dresden",
    "sg:phone":"+49 351/2513154",
    "sg:postcode":"01277",
    "sg:province":"Sachsen",
    "wof:name":"Netbuilder Netzwerktechnik Gmbh",
    "wof:placetype":"venue"
},
  "geometry": {"coordinates":[13.7906980515,51.0349349976],"type":"Point"}
}