{
  "type": "Feature",
  "properties": {
    "iso:country":"DE",
    "sg:address":"Seiferitzer Allee 29",
    "sg:city":"Meerane",
    "sg:phone":"+49 3764/47205",
    "sg:postcode":"08393",
    "sg:province":"Sachsen",
    "wof:name":"Schmidt Autolack Gmbh Leitgrossh\u00e4ndler",
    "wof:placetype":"venue"
},
  "geometry": {"coordinates":[12.458718,50.828514],"type":"Point"}
}