{
  "type": "Feature",
  "properties": {
    "iso:country":"DE",
    "sg:address":"Oldesloer Str. 23",
    "sg:city":"Bad Segeberg",
    "sg:phone":"+49 4551/944477",
    "sg:postcode":"23795",
    "sg:province":"Schleswig-Holstein",
    "wof:name":"Armin Stadter Rechtsanwalt",
    "wof:placetype":"venue"
},
  "geometry": {"coordinates":[10.3109769821,53.9351387024],"type":"Point"}
}