{
  "type": "Feature",
  "properties": {
    "iso:country":"DE",
    "sg:address":"Neuh\u00e4user Str. 19",
    "sg:city":"Dettingen",
    "sg:phone":"+49 7123/97960",
    "sg:postcode":"72581",
    "sg:province":"Baden-W\u00fcrttemberg",
    "wof:name":"R\u00fcdt Gmbh",
    "wof:placetype":"venue"
},
  "geometry": {"coordinates":[9.3325147629,48.5330047607],"type":"Point"}
}