{
  "type": "Feature",
  "properties": {
    "iso:country":"DE",
    "sg:address":"Brunnenstr. 4",
    "sg:city":"Sachsenheim",
    "sg:phone":"+49 7147/921000",
    "sg:postcode":"74343",
    "sg:province":"Baden-W\u00fcrttemberg",
    "wof:name":"B\u00e4ckerei Clement Gmbh",
    "wof:placetype":"venue"
},
  "geometry": {"coordinates":[9.065434,48.959602],"type":"Point"}
}