{
  "type": "Feature",
  "properties": {
    "iso:country":"DE",
    "sg:address":"Lutherplatz 2",
    "sg:city":"Markneukirchen",
    "sg:phone":"+49 37422/2744",
    "sg:postcode":"08258",
    "sg:province":"Sachsen",
    "wof:name":"Hermann Schmidt",
    "wof:placetype":"venue"
},
  "geometry": {"coordinates":[12.325668335,50.3116836548],"type":"Point"}
}