{
  "type": "Feature",
  "properties": {
    "iso:country":"DE",
    "sg:address":"Heinrich-von-Kleist-Str. 12",
    "sg:city":"Mosbach",
    "sg:phone":"+49 6261/915181",
    "sg:postcode":"74821",
    "sg:province":"Baden-W\u00fcrttemberg",
    "wof:name":"Heinz Arnold",
    "wof:placetype":"venue"
},
  "geometry": {"coordinates":[9.1339130402,49.3434753418],"type":"Point"}
}