{
  "type": "Feature",
  "properties": {
    "iso:country":"DE",
    "sg:address":"Rheinstr. 113-115",
    "sg:city":"Osnabr\u00fcck",
    "sg:phone":"+49 541/6690523",
    "sg:postcode":"49090",
    "sg:province":"Niedersachsen",
    "wof:name":"Henneb\u00f6hl & Tasch Gmbh",
    "wof:placetype":"venue"
},
  "geometry": {"coordinates":[8.0258150101,52.2929954529],"type":"Point"}
}