{
  "type": "Feature",
  "properties": {
    "iso:country":"DE",
    "sg:address":"In den Weiherg\u00e4rten 20",
    "sg:city":"Saarbr\u00fccken",
    "sg:phone":"+49 681/791700",
    "sg:postcode":"66115",
    "sg:province":"Saarland",
    "wof:name":"Peter Neumann",
    "wof:placetype":"venue"
},
  "geometry": {"coordinates":[6.9451670647,49.2426071167],"type":"Point"}
}