{
  "type": "Feature",
  "properties": {
    "iso:country":"DE",
    "sg:address":"Steinmetzstr 3",
    "sg:city":"L\u00fcbeck",
    "sg:phone":"+49 451/873600",
    "sg:postcode":"23556",
    "sg:province":"Schleswig-Holstein",
    "wof:name":"Jessenlenz Computerentwicklungs- Und Vertriebs-gmbh",
    "wof:placetype":"venue"
},
  "geometry": {"coordinates":[10.617518,53.863388],"type":"Point"}
}