{
  "type": "Feature",
  "properties": {
    "iso:country":"DE",
    "sg:address":"Kehler Str. 25",
    "sg:city":"Freiburg",
    "sg:phone":"+49 761/500766",
    "sg:postcode":"79108",
    "sg:province":"Baden-W\u00fcrttemberg",
    "wof:name":"Wilhelm Flad",
    "wof:placetype":"venue"
},
  "geometry": {"coordinates":[7.8525128365,48.0179862976],"type":"Point"}
}