{
  "type": "Feature",
  "properties": {
    "iso:country":"DE",
    "sg:address":"Klingerstr. 13",
    "sg:city":"Marktredwitz",
    "sg:phone":"+49 9231/62839",
    "sg:postcode":"95615",
    "sg:province":"Bayern",
    "wof:name":"Schrott",
    "wof:placetype":"venue"
},
  "geometry": {"coordinates":[12.0807828903,50.0008354187],"type":"Point"}
}