{
  "type": "Feature",
  "properties": {
    "iso:country":"DE",
    "sg:address":"Erich-Dieckhoff-Str. 44a",
    "sg:city":"Neuruppin",
    "sg:phone":"+49 3391/84110",
    "sg:postcode":"16816",
    "sg:province":"Brandenburg",
    "wof:name":"H. Vogler Gmbh",
    "wof:placetype":"venue"
},
  "geometry": {"coordinates":[12.806296,52.890663],"type":"Point"}
}