{
  "type": "Feature",
  "properties": {
    "iso:country":"DE",
    "sg:address":"Industriestr. 21",
    "sg:city":"Beverungen",
    "sg:phone":"+49 5273/905200",
    "sg:postcode":"37688",
    "sg:province":"Nordrhein-Westfalen",
    "wof:name":"Lewag Holding Ag",
    "wof:placetype":"venue"
},
  "geometry": {"coordinates":[9.380891,51.681641],"type":"Point"}
}