{
  "type": "Feature",
  "properties": {
    "iso:country":"DE",
    "sg:address":"Unterrather Str. 163",
    "sg:city":"D\u00fcsseldorf",
    "sg:phone":"+49 211/4201007",
    "sg:postcode":"40001",
    "sg:province":"Nordrhein-Westfalen",
    "wof:name":"D\u00fcsseldorf Online Hotel Reservierung",
    "wof:placetype":"venue"
},
  "geometry": {"coordinates":[6.776753,51.272175],"type":"Point"}
}