{
  "type": "Feature",
  "properties": {
    "iso:country":"DE",
    "sg:address":"Werler Str 28",
    "sg:city":"Ense",
    "sg:phone":"+49 2938/1316",
    "sg:postcode":"59469",
    "sg:province":"Nordrhein-Westfalen",
    "wof:name":"A. Stamen Ohg",
    "wof:placetype":"venue"
},
  "geometry": {"coordinates":[7.9639849663,51.5045547485],"type":"Point"}
}