{
  "type": "Feature",
  "properties": {
    "iso:country":"DE",
    "sg:address":"Burgschmietstr. 25",
    "sg:city":"N\u00fcrnberg",
    "sg:phone":"+49 911/335220",
    "sg:postcode":"90419",
    "sg:province":"Bayern",
    "wof:name":"D. J\u00e4gerhuber",
    "wof:placetype":"venue"
},
  "geometry": {"coordinates":[11.0691604614,49.4577217102],"type":"Point"}
}