{
  "type": "Feature",
  "properties": {
    "iso:country":"DE",
    "sg:address":"Kaufbeurer Str. 2",
    "sg:city":"Germaringen",
    "sg:phone":"+49 8341/66297",
    "sg:postcode":"87656",
    "sg:province":"Bayern",
    "wof:name":"Andreas Dopfer",
    "wof:placetype":"venue"
},
  "geometry": {"coordinates":[10.671565,47.928764],"type":"Point"}
}