{
  "type": "Feature",
  "properties": {
    "iso:country":"DE",
    "sg:address":"Komotauer Str. 4",
    "sg:city":"Lauf",
    "sg:postcode":"91207",
    "sg:province":"Bayern",
    "wof:name":"Inmar International Marketing & Export",
    "wof:placetype":"venue"
},
  "geometry": {"coordinates":[11.2525777817,49.5235519409],"type":"Point"}
}