{
  "type": "Feature",
  "properties": {
    "iso:country":"DE",
    "sg:address":"Kastanienallee 12",
    "sg:city":"Kreiensen",
    "sg:phone":"+49 5563/6901",
    "sg:postcode":"37547",
    "sg:province":"Niedersachsen",
    "wof:name":"O. Bohnsack & Sohn M\u00fchlen- Speicher- U. Heizungsbau",
    "wof:placetype":"venue"
},
  "geometry": {"coordinates":[9.961131,51.85091],"type":"Point"}
}