{
  "type": "Feature",
  "properties": {
    "iso:country":"DE",
    "sg:address":"Lange Str. 10",
    "sg:city":"Moringen",
    "sg:phone":"+49 5554/8223",
    "sg:postcode":"37186",
    "sg:province":"Niedersachsen",
    "wof:name":"Gerhard Weigel",
    "wof:placetype":"venue"
},
  "geometry": {"coordinates":[9.8706283569,51.6993904114],"type":"Point"}
}