{
  "type": "Feature",
  "properties": {
    "iso:country":"DE",
    "sg:address":"Waldstr. 18",
    "sg:city":"Wachtberg",
    "sg:phone":"+49 228/321633",
    "sg:postcode":"53343",
    "sg:province":"Nordrhein-Westfalen",
    "wof:name":"E. He\u00dfler",
    "wof:placetype":"venue"
},
  "geometry": {"coordinates":[7.0832500458,50.6431808472],"type":"Point"}
}