{
  "type": "Feature",
  "properties": {
    "iso:country":"DE",
    "sg:address":"Hauptstr. 119",
    "sg:city":"Obersch\u00f6nau",
    "sg:phone":"+49 36847/30334",
    "sg:postcode":"98587",
    "sg:province":"Th\u00fcringen",
    "wof:name":"A. Kaiser",
    "wof:placetype":"venue"
},
  "geometry": {"coordinates":[10.6162204742,50.7123451233],"type":"Point"}
}