{
  "type": "Feature",
  "properties": {
    "iso:country":"DE",
    "sg:address":"M\u00fcnchener Stra\u00dfe 119",
    "sg:city":"Ingolstadt",
    "sg:postcode":"85051",
    "sg:province":"Bayern",
    "wof:name":"Internet-cafe Ingolstadt",
    "wof:placetype":"venue"
},
  "geometry": {"coordinates":[11.4353189468,48.7411766052],"type":"Point"}
}