{
  "type": "Feature",
  "properties": {
    "iso:country":"DE",
    "sg:address":"F\u00fcrstenrieder Str. 35",
    "sg:city":"M\u00fcnchen",
    "sg:phone":"+49 89/58979374",
    "sg:postcode":"80686",
    "sg:province":"Bayern",
    "wof:name":"S\u00fcddeutsche Assekuranz Vermittlungsgesellschaft Mbh",
    "wof:placetype":"venue"
},
  "geometry": {"coordinates":[11.5033473969,48.1389198303],"type":"Point"}
}