{
  "type": "Feature",
  "properties": {
    "iso:country":"DE",
    "sg:address":"Am Angerbach 18",
    "sg:city":"Pfronten",
    "sg:phone":"+49 8363/927645",
    "sg:postcode":"87459",
    "sg:province":"Bayern",
    "wof:name":"Ngt New Generationtools Gmbh & Co. Kg",
    "wof:placetype":"venue"
},
  "geometry": {"coordinates":[10.553516,47.582794],"type":"Point"}
}