{
  "type": "Feature",
  "properties": {
    "iso:country":"DE",
    "sg:address":"Tempelsweg 1",
    "sg:city":"T\u00f6nisvorst",
    "sg:postcode":"47918",
    "sg:province":"Nordrhein-Westfalen",
    "wof:name":"Schr\u00f6er Verwaltungs-gmbh",
    "wof:placetype":"venue"
},
  "geometry": {"coordinates":[6.4708280563,51.3179168701],"type":"Point"}
}