{
  "type": "Feature",
  "properties": {
    "iso:country":"DE",
    "sg:address":"Zusamstr. 6",
    "sg:city":"Augsburg",
    "sg:phone":"+49 821/713819",
    "sg:postcode":"86165",
    "sg:province":"Bayern",
    "wof:name":"Sadeh-siebdruck Gmbh",
    "wof:placetype":"venue"
},
  "geometry": {"coordinates":[10.935965538,48.376991272],"type":"Point"}
}