{
  "type": "Feature",
  "properties": {
    "iso:country":"DE",
    "sg:address":"Braubachstr. 14-16",
    "sg:city":"Frankfurt",
    "sg:postcode":"60311",
    "sg:province":"Hessen",
    "wof:name":"Schwarz & Dibbern Kg",
    "wof:placetype":"venue"
},
  "geometry": {"coordinates":[8.683866,50.111534],"type":"Point"}
}