{
  "type": "Feature",
  "properties": {
    "iso:country":"DE",
    "sg:address":"Gaisenrain 5",
    "sg:city":"Singen",
    "sg:phone":"+49 7731/68044",
    "sg:postcode":"78224",
    "sg:province":"Baden-W\u00fcrttemberg",
    "wof:name":"Einkaufsgen. D. Gipser- Und Stukkateurmeister S\u00fcdwest-",
    "wof:placetype":"venue"
},
  "geometry": {"coordinates":[8.868368,47.757023],"type":"Point"}
}