{
  "type": "Feature",
  "properties": {
    "iso:country":"DE",
    "sg:address":"M\u00fchlenstr. 38",
    "sg:city":"Negenharrie",
    "sg:phone":"+49 4322/9433",
    "sg:postcode":"24625",
    "sg:province":"Schleswig-Holstein",
    "wof:name":"Uwe Rieper",
    "wof:placetype":"venue"
},
  "geometry": {"coordinates":[10.076885,54.139107],"type":"Point"}
}