{
  "type": "Feature",
  "properties": {
    "iso:country":"DE",
    "sg:address":"Anton-Franznick-Weg 2",
    "sg:city":"Bollschweil",
    "sg:phone":"+49 7633/5317",
    "sg:postcode":"79283",
    "sg:province":"Baden-W\u00fcrttemberg",
    "wof:name":"Kath. Pfarramt St. Hilarius",
    "wof:placetype":"venue"
},
  "geometry": {"coordinates":[7.7881669998,47.920173645],"type":"Point"}
}