{
  "type": "Feature",
  "properties": {
    "iso:country":"DE",
    "sg:address":"Strelitzer Str. 54",
    "sg:city":"Neustrelitz",
    "sg:phone":"+49 3981/205185",
    "sg:postcode":"17235",
    "sg:province":"Mecklenburg-Vorpommern",
    "wof:name":"Heiko Gau",
    "wof:placetype":"venue"
},
  "geometry": {"coordinates":[13.063558,53.362137],"type":"Point"}
}