{
  "type": "Feature",
  "properties": {
    "iso:country":"DE",
    "sg:address":"Richtweg 1",
    "sg:city":"Bremen",
    "sg:phone":"+49 421/363000",
    "sg:postcode":"28195",
    "sg:province":"Bremen",
    "wof:name":"Jantzen-emde-tjarks Wirtschaftspr\u00fcfungsges.",
    "wof:placetype":"venue"
},
  "geometry": {"coordinates":[8.8147373199,53.0776176453],"type":"Point"}
}