{
  "type": "Feature",
  "properties": {
    "iso:country":"DE",
    "sg:address":"Schwaaner Str. 35",
    "sg:city":"G\u00fcstrow",
    "sg:phone":"+49 3843/212507",
    "sg:postcode":"18273",
    "sg:province":"Mecklenburg-Vorpommern",
    "wof:name":"Bar Klein Paris",
    "wof:placetype":"venue"
},
  "geometry": {"coordinates":[12.171865,53.807926],"type":"Point"}
}