{
  "type": "Feature",
  "properties": {
    "iso:country":"DE",
    "sg:address":"Lindenstr. 44",
    "sg:city":"Appen",
    "sg:phone":"+49 4101/553063",
    "sg:postcode":"25482",
    "sg:province":"Schleswig-Holstein",
    "wof:name":"D. Lindner Steuerberater",
    "wof:placetype":"venue"
},
  "geometry": {"coordinates":[9.732088089,53.6612052917],"type":"Point"}
}