{
  "type": "Feature",
  "properties": {
    "iso:country":"DE",
    "sg:address":"M\u00fchlgrabenweg 5",
    "sg:city":"Gernsbach",
    "sg:phone":"+49 7224/2428",
    "sg:postcode":"76593",
    "sg:province":"Baden-W\u00fcrttemberg",
    "wof:name":"Eduard Billian",
    "wof:placetype":"venue"
},
  "geometry": {"coordinates":[8.3358383179,48.7638015747],"type":"Point"}
}