{
  "type": "Feature",
  "properties": {
    "iso:country":"DE",
    "sg:address":"Sollner Str. 45",
    "sg:city":"M\u00fcnchen",
    "sg:phone":"+49 89/7499123",
    "sg:postcode":"81479",
    "sg:province":"Bayern",
    "wof:name":"Der W\u00fcrfel Qualit\u00e4tsspielwaren Und",
    "wof:placetype":"venue"
},
  "geometry": {"coordinates":[11.5262079239,48.0801277161],"type":"Point"}
}