{
  "type": "Feature",
  "properties": {
    "iso:country":"DE",
    "sg:address":"Hessenheide 9",
    "sg:city":"G\u00fctersloh",
    "sg:phone":"+49 5241/56773",
    "sg:postcode":"33334",
    "sg:province":"Nordrhein-Westfalen",
    "wof:name":"Hans Gausemeier",
    "wof:placetype":"venue"
},
  "geometry": {"coordinates":[8.357319,51.892487],"type":"Point"}
}