{
  "type": "Feature",
  "properties": {
    "iso:country":"DE",
    "sg:address":"Braunschweiger Str. 25 - 26",
    "sg:city":"Burgdorf",
    "sg:phone":"+49 5136/4435",
    "sg:postcode":"31303",
    "sg:province":"Niedersachsen",
    "wof:name":"G.w. M\u00fcller Inh. Dirk M\u00fcller",
    "wof:placetype":"venue"
},
  "geometry": {"coordinates":[10.0092878342,52.4451026917],"type":"Point"}
}