{
  "type": "Feature",
  "properties": {
    "iso:country":"DE",
    "sg:address":"Alte Chaussee 8",
    "sg:city":"Meiningen",
    "sg:phone":"+49 3693/931225",
    "sg:postcode":"98617",
    "sg:province":"Th\u00fcringen",
    "wof:name":"Werner Kellner",
    "wof:placetype":"venue"
},
  "geometry": {"coordinates":[10.388703,50.558743],"type":"Point"}
}