{
  "type": "Feature",
  "properties": {
    "iso:country":"DE",
    "sg:address":"Westenhellweg 98",
    "sg:city":"Dortmund",
    "sg:phone":"+49 231/423678",
    "sg:postcode":"44137",
    "sg:province":"Nordrhein-Westfalen",
    "wof:name":"Anton Schlecker",
    "wof:placetype":"venue"
},
  "geometry": {"coordinates":[7.459164,51.513988],"type":"Point"}
}