{
  "type": "Feature",
  "properties": {
    "iso:country":"DE",
    "sg:address":"Stra\u00dfe der Chemiearbeiter 45",
    "sg:city":"Wolfen",
    "sg:phone":"+49 3494/25198",
    "sg:postcode":"06766",
    "sg:province":"Sachsen-Anhalt",
    "wof:name":"Frank Keller",
    "wof:placetype":"venue"
},
  "geometry": {"coordinates":[12.258480072,51.68309021],"type":"Point"}
}