{
  "type": "Feature",
  "properties": {
    "iso:country":"DE",
    "sg:address":"Am Ortberg 7",
    "sg:city":"Halbe",
    "sg:phone":"+49 172 9486140",
    "sg:postcode":"15757",
    "sg:province":"Brandenburg",
    "wof:name":"Car-clean-centre",
    "wof:placetype":"venue"
},
  "geometry": {"coordinates":[13.714302,52.086967],"type":"Point"}
}