{
  "type": "Feature",
  "properties": {
    "iso:country":"DE",
    "sg:address":"Stehfelder Weg 6",
    "sg:city":"Nidda",
    "sg:phone":"+49 6043/96600",
    "sg:postcode":"63667",
    "sg:province":"Hessen",
    "wof:name":"Rg-treuhand Ringel & Partner Gmbh & Co.",
    "wof:placetype":"venue"
},
  "geometry": {"coordinates":[9.0105466843,50.4060325623],"type":"Point"}
}