{
  "type": "Feature",
  "properties": {
    "iso:country":"DE",
    "sg:address":"Domziegelhof 14",
    "sg:city":"Schleswig",
    "sg:phone":"+49 4621/25836",
    "sg:postcode":"24837",
    "sg:province":"Schleswig-Holstein",
    "wof:name":"Hotel Deutscher Hof",
    "wof:placetype":"venue"
},
  "geometry": {"coordinates":[9.5560426712,54.5144348145],"type":"Point"}
}