{
  "type": "Feature",
  "properties": {
    "iso:country":"DE",
    "sg:address":"Victoriastr. 20",
    "sg:city":"K\u00f6ln",
    "sg:phone":"+49 221/9128260",
    "sg:postcode":"50670",
    "sg:province":"Nordrhein-Westfalen",
    "wof:name":"Herbert M\u00f6rs Finanzberater",
    "wof:placetype":"venue"
},
  "geometry": {"coordinates":[6.951777935,50.9453010559],"type":"Point"}
}