{
  "type": "Feature",
  "properties": {
    "iso:country":"DE",
    "sg:address":"Ricarda-Huch-Str. 14",
    "sg:city":"Freiburg",
    "sg:phone":"+49 761/891017",
    "sg:postcode":"79114",
    "sg:province":"Baden-W\u00fcrttemberg",
    "wof:name":"Bernhard Spiess",
    "wof:placetype":"venue"
},
  "geometry": {"coordinates":[7.8121800423,48.0049743652],"type":"Point"}
}