{
  "type": "Feature",
  "properties": {
    "iso:country":"DE",
    "sg:address":"Auf Der H\u00f6he 28",
    "sg:city":"Duisburg",
    "sg:phone":"+49 4920/3312038",
    "sg:postcode":"47059",
    "sg:province":"Nordrhein-Westfalen",
    "wof:name":"Blech- U. Eisenverarbeitung Gr\u00d6sgen Gmbh + Co Kg",
    "wof:placetype":"venue"
},
  "geometry": {"coordinates":[6.757209,51.441193],"type":"Point"}
}