{
  "type": "Feature",
  "properties": {
    "iso:country":"DE",
    "sg:address":"Pescher Str. 156",
    "sg:city":"M\u00f6nchengladbach",
    "sg:phone":"+49 2161/481854",
    "sg:postcode":"41065",
    "sg:province":"Nordrhein-Westfalen",
    "wof:name":"Heinz Aretz Architekt",
    "wof:placetype":"venue"
},
  "geometry": {"coordinates":[6.453022,51.193687],"type":"Point"}
}