{
  "type": "Feature",
  "properties": {
    "iso:country":"DE",
    "sg:address":"Bohlander Str. 14",
    "sg:city":"Albbruck",
    "sg:phone":"+49 7753/706",
    "sg:postcode":"79774",
    "sg:province":"Baden-W\u00fcrttemberg",
    "wof:name":"P. Klahn",
    "wof:placetype":"venue"
},
  "geometry": {"coordinates":[8.1604375839,47.6274681091],"type":"Point"}
}