{
  "type": "Feature",
  "properties": {
    "iso:country":"DE",
    "sg:address":"Pleistalstr. 64",
    "sg:city":"Hennef",
    "sg:phone":"+49 2242/5102",
    "sg:postcode":"53773",
    "sg:province":"Nordrhein-Westfalen",
    "wof:name":"Hans Peter Siegberg Handelsgesellschaft Mbh",
    "wof:placetype":"venue"
},
  "geometry": {"coordinates":[7.238316,50.748089],"type":"Point"}
}