{
  "type": "Feature",
  "properties": {
    "iso:country":"DE",
    "sg:address":"Puschkinstr. 25",
    "sg:city":"Br\u00fcssow",
    "sg:postcode":"17326",
    "sg:province":"Brandenburg",
    "wof:name":"Goldener Stern Inh. P. Quandt",
    "wof:placetype":"venue"
},
  "geometry": {"coordinates":[14.1312427521,53.401927948],"type":"Point"}
}