{
  "type": "Feature",
  "properties": {
    "iso:country":"DE",
    "sg:address":"Am M\u00fchlenberg 26",
    "sg:city":"Kalkhorst",
    "sg:postcode":"23942",
    "sg:province":"Mecklenburg-Vorpommern",
    "wof:name":"Ts Holding Gmbh",
    "wof:placetype":"venue"
},
  "geometry": {"coordinates":[11.044473,53.965603],"type":"Point"}
}