{
  "type": "Feature",
  "properties": {
    "iso:country":"DE",
    "sg:address":"Wilhelmstr. 24",
    "sg:city":"M\u00fclheim",
    "sg:phone":"+49 208/36128",
    "sg:postcode":"45468",
    "sg:province":"Nordrhein-Westfalen",
    "wof:name":"Friedrich Kurtz Buch- U. Zeitschriftenhandlung",
    "wof:placetype":"venue"
},
  "geometry": {"coordinates":[6.879708,51.421654],"type":"Point"}
}