{
  "type": "Feature",
  "properties": {
    "iso:country":"DE",
    "sg:address":"Waldtruderinger Str. 67",
    "sg:city":"M\u00fcnchen",
    "sg:phone":"+49 89/4308381",
    "sg:postcode":"81827",
    "sg:province":"Bayern",
    "wof:name":"Sch\u00f6nreiter Baustoffe",
    "wof:placetype":"venue"
},
  "geometry": {"coordinates":[11.7008228302,48.1130714417],"type":"Point"}
}