{
  "type": "Feature",
  "properties": {
    "iso:country":"DE",
    "sg:address":"Schwalinger Str. 4",
    "sg:city":"Neuenkirchen",
    "sg:phone":"+49 5195/1382",
    "sg:postcode":"29643",
    "sg:province":"Niedersachsen",
    "wof:name":"Heinfried Witte",
    "wof:placetype":"venue"
},
  "geometry": {"coordinates":[9.669132,53.06731],"type":"Point"}
}