{
  "type": "Feature",
  "properties": {
    "iso:country":"DE",
    "sg:address":"Mainzer Landstra\u00dfe 46",
    "sg:city":"Frankfurt am Main",
    "sg:phone":"+49 4969/9714400",
    "sg:postcode":"60325",
    "sg:province":"Hessen",
    "wof:name":"Gmb",
    "wof:placetype":"venue"
},
  "geometry": {"coordinates":[8.663898468,50.1109809875],"type":"Point"}
}