{
  "type": "Feature",
  "properties": {
    "iso:country":"DE",
    "sg:address":"Rolandstr. 7",
    "sg:city":"Bonn",
    "sg:phone":"+49 228/366272",
    "sg:postcode":"53179",
    "sg:province":"Nordrhein-Westfalen",
    "wof:name":"Mail-log Versandlogistik Consulting Und Service Gmbh",
    "wof:placetype":"venue"
},
  "geometry": {"coordinates":[7.1725940704,50.6837844849],"type":"Point"}
}