{
  "type": "Feature",
  "properties": {
    "iso:country":"DE",
    "sg:address":"Am Spitzberg 8a",
    "sg:city":"Possendorf",
    "sg:phone":"+49 8247/34340",
    "sg:postcode":"01728",
    "sg:province":"Sachsen",
    "wof:name":"Af Druckform Amon Gmbh",
    "wof:placetype":"venue"
},
  "geometry": {"coordinates":[10.5964136124,48.0196533203],"type":"Point"}
}