{
  "type": "Feature",
  "properties": {
    "iso:country":"DE",
    "sg:address":"Am Elbberg 3",
    "sg:city":"Boizenburg",
    "sg:postcode":"19258",
    "sg:province":"Mecklenburg-Vorpommern",
    "wof:name":"Dp Druck + Pack Service Hamburg Gmbh Filiale Boizenb.",
    "wof:placetype":"venue"
},
  "geometry": {"coordinates":[10.694836,53.374153],"type":"Point"}
}