{
  "type": "Feature",
  "properties": {
    "iso:country":"DE",
    "sg:address":"Gewerbegebiet",
    "sg:city":"Geismar",
    "sg:postcode":"37308",
    "sg:province":"Th\u00fcringen",
    "wof:name":"Replag- Replastifizierungs-gmbh",
    "wof:placetype":"venue"
},
  "geometry": {"coordinates":[10.136575,51.376862],"type":"Point"}
}