{
  "type": "Feature",
  "properties": {
    "iso:country":"DE",
    "sg:address":"Hansastr. 17",
    "sg:city":"Ahlen",
    "sg:phone":"+49 2382/73613",
    "sg:postcode":"59229",
    "sg:province":"Nordrhein-Westfalen",
    "wof:name":"F. Crabus Gmbh",
    "wof:placetype":"venue"
},
  "geometry": {"coordinates":[7.9088511467,51.7583465576],"type":"Point"}
}