{
  "type": "Feature",
  "properties": {
    "iso:country":"DE",
    "sg:address":"Morgensternstr. 35",
    "sg:city":"Leipzig",
    "sg:phone":"+49 341/4805025",
    "sg:postcode":"04179",
    "sg:province":"Sachsen",
    "wof:name":"Wolfgang Petzold Ingenieur",
    "wof:placetype":"venue"
},
  "geometry": {"coordinates":[12.3105125427,51.3331565857],"type":"Point"}
}