{
  "type": "Feature",
  "properties": {
    "iso:country":"DE",
    "sg:address":"Heimst\u00e4ttenstr. 16",
    "sg:city":"Jena",
    "sg:phone":"+49 3641/336551",
    "sg:postcode":"07749",
    "sg:province":"Th\u00fcringen",
    "wof:name":"D. Rodewald Immobilienmakler",
    "wof:placetype":"venue"
},
  "geometry": {"coordinates":[11.5999288559,50.9212799072],"type":"Point"}
}