{
  "type": "Feature",
  "properties": {
    "iso:country":"DE",
    "sg:address":"Bahnhofstr. 1",
    "sg:city":"Burgkirchen",
    "sg:phone":"+49 8679/1331",
    "sg:postcode":"84508",
    "sg:province":"Bayern",
    "wof:name":"Dr. Med. Helmut Weber Arzt F\u00fcr Allgemeinmedizin",
    "wof:placetype":"venue"
},
  "geometry": {"coordinates":[12.7271680832,48.1662445068],"type":"Point"}
}