{
  "type": "Feature",
  "properties": {
    "iso:country":"DE",
    "sg:address":"Merkurring 108",
    "sg:city":"Hamburg",
    "sg:phone":"+49 40/67561500",
    "sg:postcode":"22143",
    "sg:province":"Hamburg",
    "wof:name":"Auto Und Technik Tim Jahnke Gmbh",
    "wof:placetype":"venue"
},
  "geometry": {"coordinates":[10.1922559738,53.6070289612],"type":"Point"}
}