{
  "type": "Feature",
  "properties": {
    "iso:country":"DE",
    "sg:address":"Potsdamer Str. 45",
    "sg:city":"Potsdam",
    "sg:phone":"+49 331/50540049",
    "sg:postcode":"14469",
    "sg:province":"Brandenburg",
    "wof:name":"Erhard Leider",
    "wof:placetype":"venue"
},
  "geometry": {"coordinates":[13.016046,52.418453],"type":"Point"}
}