{
  "type": "Feature",
  "properties": {
    "iso:country":"DE",
    "sg:address":"Gottlieb-Daimler-Str. 22",
    "sg:city":"G\u00fctersloh",
    "sg:phone":"+49 5241/96760",
    "sg:postcode":"33334",
    "sg:province":"Nordrhein-Westfalen",
    "wof:name":"Zimmermann Transport- Und Chemiehandels Gmbh & Co.",
    "wof:placetype":"venue"
},
  "geometry": {"coordinates":[8.4280195236,51.940864563],"type":"Point"}
}