{
  "type": "Feature",
  "properties": {
    "iso:country":"DE",
    "sg:address":"Konkordiastr. 103",
    "sg:city":"D\u00fcsseldorf",
    "sg:phone":"+49 211/305243",
    "sg:postcode":"40219",
    "sg:province":"Nordrhein-Westfalen",
    "wof:name":"Dr. Michael Libertus Rechtsanwalt",
    "wof:placetype":"venue"
},
  "geometry": {"coordinates":[6.7656941414,51.2118415833],"type":"Point"}
}