{
  "type": "Feature",
  "properties": {
    "iso:country":"DE",
    "sg:address":"Im Weizen 11",
    "sg:city":"Braunfels",
    "sg:phone":"+49 6472/8787",
    "sg:postcode":"35619",
    "sg:province":"Hessen",
    "wof:name":"Dwm Toczek Und Co. Ohg",
    "wof:placetype":"venue"
},
  "geometry": {"coordinates":[8.3998193741,50.4685630798],"type":"Point"}
}