{
  "type": "Feature",
  "properties": {
    "iso:country":"DE",
    "sg:address":"Am Seestern 24",
    "sg:city":"D\u00fcsseldorf",
    "sg:phone":"+49 211/596058",
    "sg:postcode":"40547",
    "sg:province":"Nordrhein-Westfalen",
    "wof:name":"Biotec Medizintechnik Gmbh",
    "wof:placetype":"venue"
},
  "geometry": {"coordinates":[6.74055,51.243122],"type":"Point"}
}