{
  "type": "Feature",
  "properties": {
    "iso:country":"DE",
    "sg:address":"Dorfstr. 30a",
    "sg:city":"Willmersdorf",
    "sg:phone":"+49 4933/3987311",
    "sg:postcode":"16356",
    "sg:province":"Brandenburg",
    "wof:name":"Jens Dahler",
    "wof:placetype":"venue"
},
  "geometry": {"coordinates":[14.3804388046,51.801776886],"type":"Point"}
}