{
  "type": "Feature",
  "properties": {
    "iso:country":"DE",
    "sg:address":"Hauptstr. 29",
    "sg:city":"Heidelberg",
    "sg:phone":"+49 6221/21416",
    "sg:postcode":"69117",
    "sg:province":"Baden-W\u00fcrttemberg",
    "wof:name":"Janssen-kaffee Gmbh",
    "wof:placetype":"venue"
},
  "geometry": {"coordinates":[8.6959104538,49.4103164673],"type":"Point"}
}