{
  "type": "Feature",
  "properties": {
    "iso:country":"DE",
    "sg:address":"Kirchstr. 8",
    "sg:city":"Flemlingen",
    "sg:phone":"+49 6323/1669",
    "sg:postcode":"76835",
    "sg:province":"Rheinland-Pfalz",
    "wof:name":"Paul Beck",
    "wof:placetype":"venue"
},
  "geometry": {"coordinates":[8.0978078842,49.2436256409],"type":"Point"}
}