{
  "type": "Feature",
  "properties": {
    "iso:country":"DE",
    "sg:address":"Textorstr. 17",
    "sg:city":"W\u00fcrzburg",
    "sg:phone":"+49 931/322770",
    "sg:postcode":"97070",
    "sg:province":"Bayern",
    "wof:name":"Hotel-restaurant Poppular",
    "wof:placetype":"venue"
},
  "geometry": {"coordinates":[9.9347858429,49.7975120544],"type":"Point"}
}