{
  "type": "Feature",
  "properties": {
    "iso:country":"DE",
    "sg:address":"Grabenstr. 22",
    "sg:city":"Arnstein",
    "sg:phone":"+49 9363/5234",
    "sg:postcode":"97450",
    "sg:province":"Bayern",
    "wof:name":"Rosemarie Weippert",
    "wof:placetype":"venue"
},
  "geometry": {"coordinates":[9.967097,49.97797],"type":"Point"}
}