{
  "type": "Feature",
  "properties": {
    "iso:country":"DE",
    "sg:address":"Heinz-Luhnen-Str. 10",
    "sg:city":"Viersen",
    "sg:phone":"+49 2162/51018",
    "sg:postcode":"41751",
    "sg:province":"Nordrhein-Westfalen",
    "wof:name":"G\u00fcnter Houben Steuerberater",
    "wof:placetype":"venue"
},
  "geometry": {"coordinates":[6.3369188309,51.2551345825],"type":"Point"}
}