{
  "type": "Feature",
  "properties": {
    "iso:country":"DE",
    "sg:address":"Cloppenburger Str. 39",
    "sg:city":"Oldenburg",
    "sg:phone":"+49 441/2488409",
    "sg:postcode":"26135",
    "sg:province":"Niedersachsen",
    "wof:name":"China-imbi\u00df Konfuzius",
    "wof:placetype":"venue"
},
  "geometry": {"coordinates":[8.2215490341,53.1290397644],"type":"Point"}
}