{
  "type": "Feature",
  "properties": {
    "iso:country":"DE",
    "sg:address":"Bergische Landstr. 47",
    "sg:city":"Leverkusen",
    "sg:phone":"+49 214/505979",
    "sg:postcode":"51375",
    "sg:province":"Nordrhein-Westfalen",
    "wof:name":"Peppys E. K.",
    "wof:placetype":"venue"
},
  "geometry": {"coordinates":[7.050435,51.034698],"type":"Point"}
}