{
  "type": "Feature",
  "properties": {
    "iso:country":"DE",
    "sg:address":"Strahlenberger Weg 10",
    "sg:city":"Frankfurt",
    "sg:postcode":"60599",
    "sg:province":"Hessen",
    "wof:name":"Lukas Thurner Bauunternehmung Gmbh",
    "wof:placetype":"venue"
},
  "geometry": {"coordinates":[8.701333,50.103306],"type":"Point"}
}