{
  "type": "Feature",
  "properties": {
    "iso:country":"DE",
    "sg:address":"Weinstr. 37",
    "sg:city":"Herxheim am Berg",
    "sg:phone":"+49 6353/1820",
    "sg:postcode":"67273",
    "sg:province":"Rheinland-Pfalz",
    "wof:name":"Karl Schwenk Weinanbau",
    "wof:placetype":"venue"
},
  "geometry": {"coordinates":[8.1795101166,49.5105476379],"type":"Point"}
}