{
  "type": "Feature",
  "properties": {
    "iso:country":"DE",
    "sg:address":"K\u00f6nigswall 5",
    "sg:city":"Minden",
    "sg:phone":"+49 571/27974",
    "sg:postcode":"32423",
    "sg:province":"Nordrhein-Westfalen",
    "wof:name":"Bernd Vogt",
    "wof:placetype":"venue"
},
  "geometry": {"coordinates":[8.9135961533,52.2911224365],"type":"Point"}
}