{
  "type": "Feature",
  "properties": {
    "iso:country":"DE",
    "sg:address":"Steinpleiser Weg 19",
    "sg:city":"Werdau",
    "sg:phone":"+49 3761/73971",
    "sg:postcode":"08412",
    "sg:province":"Sachsen",
    "wof:name":"Monika Macht Heilpraktikerin",
    "wof:placetype":"venue"
},
  "geometry": {"coordinates":[12.3869857788,50.7238426208],"type":"Point"}
}