{
  "type": "Feature",
  "properties": {
    "iso:country":"DE",
    "sg:address":"Lingener Str. 1",
    "sg:city":"Meppen",
    "sg:phone":"+49 5931/89548",
    "sg:postcode":"49716",
    "sg:province":"Niedersachsen",
    "wof:name":"Roland Engler Rechtsanwalt Und Notar",
    "wof:placetype":"venue"
},
  "geometry": {"coordinates":[7.2911200523,52.687538147],"type":"Point"}
}