{
  "type": "Feature",
  "properties": {
    "iso:country":"DE",
    "sg:address":"Hauptstr. 21 a",
    "sg:city":"Aitrach",
    "sg:phone":"+49 7565/5433",
    "sg:postcode":"88319",
    "sg:province":"Baden-W\u00fcrttemberg",
    "wof:name":"Restaurant Hirsch",
    "wof:placetype":"venue"
},
  "geometry": {"coordinates":[10.0868997574,47.940612793],"type":"Point"}
}