{
  "type": "Feature",
  "properties": {
    "iso:country":"DE",
    "sg:address":"Hindenburgallee 3",
    "sg:city":"Gehrden",
    "sg:phone":"+49 5108/4041",
    "sg:postcode":"30989",
    "sg:province":"Niedersachsen",
    "wof:name":"Keilhack Gmbh",
    "wof:placetype":"venue"
},
  "geometry": {"coordinates":[9.5995197296,52.3092651367],"type":"Point"}
}