{
  "type": "Feature",
  "properties": {
    "iso:country":"DE",
    "sg:address":"Max-Hueber-Str. 8",
    "sg:city":"Ismaning",
    "sg:postcode":"85737",
    "sg:province":"Bayern",
    "wof:name":"Tonstudio Langer Verwaltungs Gmbh",
    "wof:placetype":"venue"
},
  "geometry": {"coordinates":[11.6653585434,48.2171859741],"type":"Point"}
}