{
  "type": "Feature",
  "properties": {
    "iso:country":"DE",
    "sg:address":"Schlachthofstr. 106",
    "sg:city":"Koblenz",
    "sg:phone":"+49 261/43111",
    "sg:postcode":"56073",
    "sg:province":"Rheinland-Pfalz",
    "wof:name":"Deutsche Shell Ag",
    "wof:placetype":"venue"
},
  "geometry": {"coordinates":[7.5710940361,50.3623008728],"type":"Point"}
}