{
  "type": "Feature",
  "properties": {
    "iso:country":"DE",
    "sg:address":"Reeperbahn 18",
    "sg:city":"Elmshorn",
    "sg:phone":"+49 4121/2624860",
    "sg:postcode":"25335",
    "sg:province":"Schleswig-Holstein",
    "wof:name":"Einkaufsshop",
    "wof:placetype":"venue"
},
  "geometry": {"coordinates":[9.645848,53.755257],"type":"Point"}
}