{
  "type": "Feature",
  "properties": {
    "iso:country":"DE",
    "sg:address":"R\u00fcttenscheider Str. 16",
    "sg:city":"Essen",
    "sg:phone":"+49 201/772830",
    "sg:postcode":"45128",
    "sg:province":"Nordrhein-Westfalen",
    "wof:name":"Christiane Luftmann",
    "wof:placetype":"venue"
},
  "geometry": {"coordinates":[7.0066590309,51.4422912598],"type":"Point"}
}