{
  "type": "Feature",
  "properties": {
    "iso:country":"DE",
    "sg:address":"Engerstr. 10",
    "sg:city":"Herford",
    "sg:phone":"+49 5221/91480",
    "sg:postcode":"32051",
    "sg:province":"Nordrhein-Westfalen",
    "wof:name":"Haus Birkenkamp",
    "wof:placetype":"venue"
},
  "geometry": {"coordinates":[8.659506,52.118515],"type":"Point"}
}