{
  "type": "Feature",
  "properties": {
    "iso:country":"DE",
    "sg:address":"Breitenfelder Str. 90",
    "sg:city":"Hamburg",
    "sg:phone":"+49 40/4801374",
    "sg:postcode":"20251",
    "sg:province":"Hamburg",
    "wof:name":"Wilfried Schwartz",
    "wof:placetype":"venue"
},
  "geometry": {"coordinates":[9.982252121,53.5894165039],"type":"Point"}
}