{
  "type": "Feature",
  "properties": {
    "iso:country":"DE",
    "sg:address":"Stra\u00dfe der Republik 17",
    "sg:city":"Wiesbaden",
    "sg:phone":"+49 611/607131",
    "sg:postcode":"65203",
    "sg:province":"Hessen",
    "wof:name":"Michaela Weigel Praxis F\u00fcr Krankengymnastik",
    "wof:placetype":"venue"
},
  "geometry": {"coordinates":[8.241397,50.043236],"type":"Point"}
}