{
  "type": "Feature",
  "properties": {
    "iso:country":"DE",
    "sg:address":"Hauptstr. 169",
    "sg:city":"Rodalben",
    "sg:phone":"+49 6331/18337",
    "sg:postcode":"66976",
    "sg:province":"Rheinland-Pfalz",
    "wof:name":"Gabriele Und Andreas Doro",
    "wof:placetype":"venue"
},
  "geometry": {"coordinates":[7.634274,49.239918],"type":"Point"}
}