{
  "type": "Feature",
  "properties": {
    "iso:country":"DE",
    "sg:address":"Peter-Moll-Weg 6",
    "sg:city":"K\u00f6nigswinter",
    "sg:phone":"+49 2244/915006",
    "sg:postcode":"53639",
    "sg:province":"Nordrhein-Westfalen",
    "wof:name":"Lingua Video Medien Gmbh",
    "wof:placetype":"venue"
},
  "geometry": {"coordinates":[7.2353100777,50.6912193298],"type":"Point"}
}