{
  "type": "Feature",
  "properties": {
    "iso:country":"DE",
    "sg:address":"Lise-Meitner-Str. 6",
    "sg:city":"Ratingen",
    "sg:phone":"+49 2102/46320",
    "sg:postcode":"40878",
    "sg:province":"Nordrhein-Westfalen",
    "wof:name":"Mc Donalds Deutschland Inc",
    "wof:placetype":"venue"
},
  "geometry": {"coordinates":[6.8310852051,51.2976036072],"type":"Point"}
}