{
  "type": "Feature",
  "properties": {
    "iso:country":"DE",
    "sg:address":"Schlo\u00dfstra\u00dfe 70a",
    "sg:city":"Bergisch Gladbach",
    "sg:phone":"+49 2204/483714",
    "sg:postcode":"51429",
    "sg:province":"Nordrhein-Westfalen",
    "wof:name":"Unternehmens- Und Einzelberatung",
    "wof:placetype":"venue"
},
  "geometry": {"coordinates":[7.160615,50.965298],"type":"Point"}
}