{
  "type": "Feature",
  "properties": {
    "iso:country":"DE",
    "sg:address":"Carl-Franke-Str. 2",
    "sg:city":"Bad Blankenburg",
    "sg:phone":"+49 36741/2365",
    "sg:postcode":"07422",
    "sg:province":"Th\u00fcringen",
    "wof:name":"E. J\u00f6rdens Masseur",
    "wof:placetype":"venue"
},
  "geometry": {"coordinates":[11.277278,50.677437],"type":"Point"}
}