{
  "type": "Feature",
  "properties": {
    "iso:country":"DE",
    "sg:address":"Schwedenwinkel 14",
    "sg:city":"Neukirch",
    "sg:phone":"+49 35951/31696",
    "sg:postcode":"01904",
    "sg:province":"Sachsen",
    "wof:name":"Schindler & Thomas",
    "wof:placetype":"venue"
},
  "geometry": {"coordinates":[14.314239,51.094734],"type":"Point"}
}