{
  "type": "Feature",
  "properties": {
    "iso:country":"DE",
    "sg:address":"Schrobenhausener Str. 7",
    "sg:city":"Aichach",
    "sg:phone":"+49 8251/52922",
    "sg:postcode":"86551",
    "sg:province":"Bayern",
    "wof:name":"P. Kathuria",
    "wof:placetype":"venue"
},
  "geometry": {"coordinates":[11.13408,48.461945],"type":"Point"}
}