{
  "type": "Feature",
  "properties": {
    "iso:country":"DE",
    "sg:address":"Luidolfstr. 3",
    "sg:city":"Ro\u00dftal",
    "sg:phone":"+49 9127/901661",
    "sg:postcode":"90574",
    "sg:province":"Bayern",
    "wof:name":"Rudi Lauchs Steuerberater",
    "wof:placetype":"venue"
},
  "geometry": {"coordinates":[10.8958120346,49.3958053589],"type":"Point"}
}