{
  "type": "Feature",
  "properties": {
    "iso:country":"DE",
    "sg:address":"Karlstr. 43",
    "sg:city":"Dettenhausen",
    "sg:phone":"+49 7157/56470",
    "sg:postcode":"72135",
    "sg:province":"Baden-W\u00fcrttemberg",
    "wof:name":"Roland Ekle",
    "wof:placetype":"venue"
},
  "geometry": {"coordinates":[9.1048898697,48.6091995239],"type":"Point"}
}