{
  "type": "Feature",
  "properties": {
    "iso:country":"DE",
    "sg:address":"Kalkhorster Str. 25",
    "sg:city":"Hohen Sch\u00f6nberg",
    "sg:postcode":"23948",
    "sg:province":"Mecklenburg-Vorpommern",
    "wof:name":"Alter Hof",
    "wof:placetype":"venue"
},
  "geometry": {"coordinates":[11.0816287994,53.9788475037],"type":"Point"}
}