{
  "type": "Feature",
  "properties": {
    "iso:country":"DE",
    "sg:address":"Deggendorfer Str. 6",
    "sg:city":"Wallersdorf",
    "sg:phone":"+49 9933/375",
    "sg:postcode":"94522",
    "sg:province":"Bayern",
    "wof:name":"Hans Steindl",
    "wof:placetype":"venue"
},
  "geometry": {"coordinates":[12.7469701767,48.7402305603],"type":"Point"}
}