{
  "type": "Feature",
  "properties": {
    "iso:country":"DE",
    "sg:address":"Landstr. 22",
    "sg:city":"Geilenkirchen",
    "sg:phone":"+49 2451/2648",
    "sg:postcode":"52511",
    "sg:province":"Nordrhein-Westfalen",
    "wof:name":"Josef Ramacher",
    "wof:placetype":"venue"
},
  "geometry": {"coordinates":[6.119436,50.99641],"type":"Point"}
}