{
  "type": "Feature",
  "properties": {
    "iso:country":"DE",
    "sg:address":"Frankfurter Str. 145",
    "sg:city":"Gie\u00dfen",
    "sg:phone":"+49 641/21064",
    "sg:postcode":"35392",
    "sg:province":"Hessen",
    "wof:name":"Hotel Arnst\u00e4dter Hof",
    "wof:placetype":"venue"
},
  "geometry": {"coordinates":[8.6565885544,50.5702857971],"type":"Point"}
}