{
  "type": "Feature",
  "properties": {
    "iso:country":"DE",
    "sg:address":"Berliner Allee 4",
    "sg:city":"D\u00fcsseldorf",
    "sg:phone":"+49 211/356664",
    "sg:postcode":"40212",
    "sg:province":"Nordrhein-Westfalen",
    "wof:name":"G\u00fcnther Petzel Masseur",
    "wof:placetype":"venue"
},
  "geometry": {"coordinates":[6.783594,51.226212],"type":"Point"}
}