{
  "type": "Feature",
  "properties": {
    "iso:country":"DE",
    "sg:address":"Ahrenburger Str. 152-154",
    "sg:city":"Hamburg",
    "sg:phone":"+49 40/6686220",
    "sg:postcode":"22045",
    "sg:province":"Hamburg",
    "wof:name":"Ahlrep Elektrogrosshandel Ag",
    "wof:placetype":"venue"
},
  "geometry": {"coordinates":[10.108044,53.581612],"type":"Point"}
}