{
  "type": "Feature",
  "properties": {
    "iso:country":"DE",
    "sg:address":"Casinostr. 48",
    "sg:city":"Koblenz",
    "sg:phone":"+49 261/915540",
    "sg:postcode":"56068",
    "sg:province":"Rheinland-Pfalz",
    "wof:name":"King Fisher Reisen",
    "wof:placetype":"venue"
},
  "geometry": {"coordinates":[7.5965800285,50.3564605713],"type":"Point"}
}