{
  "type": "Feature",
  "properties": {
    "iso:country":"DE",
    "sg:address":"Kiebitzhof 9",
    "sg:city":"Hamburg",
    "sg:phone":"+49 40/4600660",
    "sg:postcode":"22089",
    "sg:province":"Hamburg",
    "wof:name":"Rmm Marketing Research International Gmbh",
    "wof:placetype":"venue"
},
  "geometry": {"coordinates":[10.036642,53.563416],"type":"Point"}
}