{
  "type": "Feature",
  "properties": {
    "iso:country":"DE",
    "sg:address":"Hohenzollernstr. 22",
    "sg:city":"Berlin",
    "sg:phone":"+49 30",
    "sg:postcode":"12307",
    "sg:province":"Berlin",
    "wof:name":"Ebs-einbaustaubsauger Vertrieb Berlin, H.g. May",
    "wof:placetype":"venue"
},
  "geometry": {"coordinates":[13.3937654495,52.3841209412],"type":"Point"}
}