{
  "type": "Feature",
  "properties": {
    "iso:country":"DE",
    "sg:address":"Upheider Weg 77",
    "sg:city":"Steinhagen",
    "sg:phone":"+49 5204/89112",
    "sg:postcode":"33803",
    "sg:province":"Nordrhein-Westfalen",
    "wof:name":"J\u00fcrgen Edler",
    "wof:placetype":"venue"
},
  "geometry": {"coordinates":[8.4080495834,52.0180511475],"type":"Point"}
}