{
  "type": "Feature",
  "properties": {
    "iso:country":"DE",
    "sg:address":"Salomon-Idler-Str. 2",
    "sg:city":"Augsburg",
    "sg:phone":"+49 821/575025",
    "sg:postcode":"86159",
    "sg:province":"Bayern",
    "wof:name":"Staatsarchiv Augsburg",
    "wof:placetype":"venue"
},
  "geometry": {"coordinates":[10.8993768692,48.3346977234],"type":"Point"}
}