{
  "type": "Feature",
  "properties": {
    "iso:country":"DE",
    "sg:address":"Obertorstr. 15-19",
    "sg:city":"Hungen",
    "sg:phone":"+49 6402/6953",
    "sg:postcode":"35410",
    "sg:province":"Hessen",
    "wof:name":"Elektrohaus Emmerich Gmbh & Co. Kg",
    "wof:placetype":"venue"
},
  "geometry": {"coordinates":[8.8999996185,50.4752998352],"type":"Point"}
}