{
  "type": "Feature",
  "properties": {
    "iso:country":"DE",
    "sg:address":"Lange Str. 1a",
    "sg:city":"Ottersheim",
    "sg:phone":"+49 6348/7527",
    "sg:postcode":"76879",
    "sg:province":"Rheinland-Pfalz",
    "wof:name":"Herbert Merdian",
    "wof:placetype":"venue"
},
  "geometry": {"coordinates":[8.1742477417,49.2365684509],"type":"Point"}
}