{
  "type": "Feature",
  "properties": {
    "iso:country":"DE",
    "sg:address":"Gollacker 7",
    "sg:city":"Haiger",
    "sg:phone":"+49 2773/2911",
    "sg:postcode":"35708",
    "sg:province":"Hessen",
    "wof:name":"Edith H\u00fcttner",
    "wof:placetype":"venue"
},
  "geometry": {"coordinates":[8.21969,50.73988],"type":"Point"}
}