{
  "type": "Feature",
  "properties": {
    "iso:country":"DE",
    "sg:address":"Am Reichshof 5",
    "sg:city":"Illertissen",
    "sg:phone":"+49 7303/43792",
    "sg:postcode":"89257",
    "sg:province":"Bayern",
    "wof:name":"Matthias Hauf",
    "wof:placetype":"venue"
},
  "geometry": {"coordinates":[10.107325,48.22366],"type":"Point"}
}