{
  "type": "Feature",
  "properties": {
    "iso:country":"DE",
    "sg:address":"Beunestr. 20-22",
    "sg:city":"Frankfurt",
    "sg:phone":"+49 69/387599",
    "sg:postcode":"65934",
    "sg:province":"Hessen",
    "wof:name":"Peter Riedel",
    "wof:placetype":"venue"
},
  "geometry": {"coordinates":[8.567053,50.099735],"type":"Point"}
}