{
  "type": "Feature",
  "properties": {
    "iso:country":"DE",
    "sg:address":"B\u00fchlmatte 18",
    "sg:city":"Durbach",
    "sg:phone":"+49 781/41656",
    "sg:postcode":"77770",
    "sg:province":"Baden-W\u00fcrttemberg",
    "wof:name":"Werner B\u00e4chle",
    "wof:placetype":"venue"
},
  "geometry": {"coordinates":[8.0031967163,48.4941825867],"type":"Point"}
}