{
  "type": "Feature",
  "properties": {
    "iso:country":"DE",
    "sg:address":"Schlo\u00dfstr. 10",
    "sg:city":"Kirchberg",
    "sg:phone":"+49 7954/98010",
    "sg:postcode":"74592",
    "sg:province":"Baden-W\u00fcrttemberg",
    "wof:name":"Stadt- Und Sch\u00fclerb\u00fccherei Stadtverwaltung",
    "wof:placetype":"venue"
},
  "geometry": {"coordinates":[9.982088,49.20507],"type":"Point"}
}