{
  "type": "Feature",
  "properties": {
    "iso:country":"DE",
    "sg:address":"Im Flecken 16",
    "sg:city":"Geisenheim",
    "sg:phone":"+49 6722/8887",
    "sg:postcode":"65366",
    "sg:province":"Hessen",
    "wof:name":"R. Und G. Dormann",
    "wof:placetype":"venue"
},
  "geometry": {"coordinates":[7.9803118706,50.0026702881],"type":"Point"}
}