{
  "type": "Feature",
  "properties": {
    "iso:country":"DE",
    "sg:address":"Saydaer Str 21",
    "sg:city":"Chemnitz",
    "sg:phone":"+49 371/512002",
    "sg:postcode":"09125",
    "sg:province":"Sachsen",
    "wof:name":"Fachgro\u00dfhandel Industrielle Elektrotechnik-elektronik Rast",
    "wof:placetype":"venue"
},
  "geometry": {"coordinates":[12.934388,50.797745],"type":"Point"}
}