{
  "type": "Feature",
  "properties": {
    "iso:country":"DE",
    "sg:address":"Mohrengarten 65",
    "sg:city":"Mettmann",
    "sg:phone":"+49 2104/53662",
    "sg:postcode":"40822",
    "sg:province":"Nordrhein-Westfalen",
    "wof:name":"Wolfgang Pik",
    "wof:placetype":"venue"
},
  "geometry": {"coordinates":[6.9597730637,51.2695655823],"type":"Point"}
}