{
  "type": "Feature",
  "properties": {
    "iso:country":"DE",
    "sg:address":"Zuffenhauser Str. 93",
    "sg:city":"Korntal-M\u00fcnchingen",
    "sg:postcode":"70825",
    "sg:province":"Baden-W\u00fcrttemberg",
    "wof:name":"Pistor & Maier Verwaltungs- Gmbh",
    "wof:placetype":"venue"
},
  "geometry": {"coordinates":[9.1348657608,48.8307228088],"type":"Point"}
}