{
  "type": "Feature",
  "properties": {
    "iso:country":"DE",
    "sg:address":"Schlo\u00dfstr. 11",
    "sg:city":"Klingenthal",
    "sg:postcode":"08248",
    "sg:province":"Sachsen",
    "wof:name":"Akkordeon Centrum",
    "wof:placetype":"venue"
},
  "geometry": {"coordinates":[12.4670009613,50.3567314148],"type":"Point"}
}