{
  "type": "Feature",
  "properties": {
    "iso:country":"DE",
    "sg:address":"Lena-Christ-Str. 8",
    "sg:city":"Unterhaching",
    "sg:phone":"+49 89/617799",
    "sg:postcode":"82008",
    "sg:province":"Bayern",
    "wof:name":"Ursula Wollinger Krankengymnastin",
    "wof:placetype":"venue"
},
  "geometry": {"coordinates":[11.626817,48.064362],"type":"Point"}
}