{
  "type": "Feature",
  "properties": {
    "iso:country":"DE",
    "sg:address":"Buchenstr. 10",
    "sg:city":"Duisburg",
    "sg:phone":"+49 2065/76006",
    "sg:postcode":"47228",
    "sg:province":"Nordrhein-Westfalen",
    "wof:name":"Rolf Kube",
    "wof:placetype":"venue"
},
  "geometry": {"coordinates":[6.6901249886,51.4065322876],"type":"Point"}
}