{
  "type": "Feature",
  "properties": {
    "iso:country":"DE",
    "sg:address":"Wei\u00dfkirchener Weg 83",
    "sg:city":"Frankfurt",
    "sg:phone":"+49 69/581539",
    "sg:postcode":"60439",
    "sg:province":"Hessen",
    "wof:name":"Rolladenbau Keller E. K.",
    "wof:placetype":"venue"
},
  "geometry": {"coordinates":[8.616705,50.16769],"type":"Point"}
}