{
  "type": "Feature",
  "properties": {
    "iso:country":"DE",
    "sg:address":"Am Hasenbiel 18 a",
    "sg:city":"Stutensee",
    "sg:postcode":"76297",
    "sg:province":"Baden-W\u00fcrttemberg",
    "wof:name":"Ibeas Gmbh",
    "wof:placetype":"venue"
},
  "geometry": {"coordinates":[8.4667825699,49.0795135498],"type":"Point"}
}