{
  "type": "Feature",
  "properties": {
    "iso:country":"DE",
    "sg:address":"Kroge",
    "sg:city":"Lohne",
    "sg:phone":"+49 4442/3545",
    "sg:postcode":"49393",
    "sg:province":"Niedersachsen",
    "wof:name":"Willi Haskamp",
    "wof:placetype":"venue"
},
  "geometry": {"coordinates":[8.253624,52.608021],"type":"Point"}
}