{
  "type": "Feature",
  "properties": {
    "iso:country":"DE",
    "sg:address":"Kurt-Schumacher-Ring 13",
    "sg:city":"Limburg",
    "sg:postcode":"65550",
    "sg:province":"Hessen",
    "wof:name":"Reflexzonentafeln & Reflexzonenspiele",
    "wof:placetype":"venue"
},
  "geometry": {"coordinates":[8.09848,50.369919],"type":"Point"}
}