{
  "type": "Feature",
  "properties": {
    "iso:country":"DE",
    "sg:address":"Hungerberg 9",
    "sg:city":"Bodelshausen",
    "sg:phone":"+49 7471/73236",
    "sg:postcode":"72411",
    "sg:province":"Baden-W\u00fcrttemberg",
    "wof:name":"W. Rieker",
    "wof:placetype":"venue"
},
  "geometry": {"coordinates":[8.973714,48.386372],"type":"Point"}
}