{
  "type": "Feature",
  "properties": {
    "iso:country":"DE",
    "sg:address":"Am Thie 6",
    "sg:city":"Glandorf",
    "sg:phone":"+49 5426/4062",
    "sg:postcode":"49219",
    "sg:province":"Niedersachsen",
    "wof:name":"Paul Gerding Drogerie",
    "wof:placetype":"venue"
},
  "geometry": {"coordinates":[8.00139,52.081528],"type":"Point"}
}