{
  "type": "Feature",
  "properties": {
    "iso:country":"DE",
    "sg:address":"Brahmsallee 18",
    "sg:city":"Hamburg",
    "sg:phone":"+49 40/455142",
    "sg:postcode":"20144",
    "sg:province":"Hamburg",
    "wof:name":"Gloker & Vogel",
    "wof:placetype":"venue"
},
  "geometry": {"coordinates":[9.982085,53.574112],"type":"Point"}
}