{
  "type": "Feature",
  "properties": {
    "iso:country":"DE",
    "sg:address":"Edisonstr. 43",
    "sg:city":"Berlin",
    "sg:phone":"+49 30/5353333",
    "sg:postcode":"12459",
    "sg:province":"Berlin",
    "wof:name":"Cochius Metallbau Gmbh",
    "wof:placetype":"venue"
},
  "geometry": {"coordinates":[13.513083,52.466022],"type":"Point"}
}