{
  "type": "Feature",
  "properties": {
    "iso:country":"DE",
    "sg:address":"Drochterser Str. 4",
    "sg:city":"Drochtersen",
    "sg:phone":"+49 4143/7108",
    "sg:postcode":"21706",
    "sg:province":"Niedersachsen",
    "wof:name":"Eiscafe Capri",
    "wof:placetype":"venue"
},
  "geometry": {"coordinates":[9.388,53.708057],"type":"Point"}
}