{
  "type": "Feature",
  "properties": {
    "iso:country":"DE",
    "sg:address":"Karl-Liebknecht-Str. 11",
    "sg:city":"Dortmund",
    "sg:phone":"+49 231/140004",
    "sg:postcode":"44141",
    "sg:province":"Nordrhein-Westfalen",
    "wof:name":"Dieter Sommer",
    "wof:placetype":"venue"
},
  "geometry": {"coordinates":[7.487302,51.500168],"type":"Point"}
}