{
  "type": "Feature",
  "properties": {
    "iso:country":"DE",
    "sg:address":"B\u00f6blinger Str. 1",
    "sg:city":"B\u00f6blingen",
    "sg:phone":"+49 7031/675122",
    "sg:postcode":"71034",
    "sg:province":"Baden-W\u00fcrttemberg",
    "wof:name":"Gastst\u00e4tte Schlapph\u00fcadle",
    "wof:placetype":"venue"
},
  "geometry": {"coordinates":[8.9526309967,48.6903991699],"type":"Point"}
}