{
  "type": "Feature",
  "properties": {
    "iso:country":"DE",
    "sg:address":"Karl-Marx-Str. 10",
    "sg:city":"Vetschau",
    "sg:phone":"+49 35433/2367",
    "sg:postcode":"03226",
    "sg:province":"Brandenburg",
    "wof:name":"Franz Schanze",
    "wof:placetype":"venue"
},
  "geometry": {"coordinates":[14.0747823715,51.7854270935],"type":"Point"}
}