{
  "type": "Feature",
  "properties": {
    "iso:country":"DE",
    "sg:address":"Dinkelsb\u00fchler Str. 21",
    "sg:city":"Neuendettelsau",
    "sg:phone":"+49 9874/79124",
    "sg:postcode":"91564",
    "sg:province":"Bayern",
    "wof:name":"Deutsches Pinsel- Und B\u00fcrsten-museum",
    "wof:placetype":"venue"
},
  "geometry": {"coordinates":[10.787855,49.286777],"type":"Point"}
}