{
  "type": "Feature",
  "properties": {
    "iso:country":"DE",
    "sg:address":"Teterower Str. 62",
    "sg:city":"J\u00f6rdenstorf",
    "sg:phone":"+49 39977/30286",
    "sg:postcode":"17168",
    "sg:province":"Mecklenburg-Vorpommern",
    "wof:name":"Verwaltungsgesellschaft Sternberg Baumaschinen Gmbh",
    "wof:placetype":"venue"
},
  "geometry": {"coordinates":[12.618481636,53.8822135925],"type":"Point"}
}