{
  "type": "Feature",
  "properties": {
    "iso:country":"DE",
    "sg:address":"Hauptstr. 60",
    "sg:city":"Tremsb\u00fcttel",
    "sg:postcode":"22967",
    "sg:province":"Schleswig-Holstein",
    "wof:name":"Gie\u00dfe",
    "wof:placetype":"venue"
},
  "geometry": {"coordinates":[10.3065443039,53.7396392822],"type":"Point"}
}