{
  "type": "Feature",
  "properties": {
    "iso:country":"DE",
    "sg:address":"W\u00fcrttemberger Str. 12",
    "sg:city":"Schwalbach",
    "sg:phone":"+49 6196/950990",
    "sg:postcode":"65824",
    "sg:province":"Hessen",
    "wof:name":"Dr. Siegfried Traub Rechtsanwalt",
    "wof:placetype":"venue"
},
  "geometry": {"coordinates":[8.5236301422,50.1598472595],"type":"Point"}
}