{
  "type": "Feature",
  "properties": {
    "iso:country":"DE",
    "sg:address":"H\u00fcttengrundstr. 13a",
    "sg:city":"Hohenstein-Ernstthal",
    "sg:phone":"+49 3723/44510",
    "sg:postcode":"09337",
    "sg:province":"Sachsen",
    "wof:name":"Wolfgang Hallmann",
    "wof:placetype":"venue"
},
  "geometry": {"coordinates":[12.6988754272,50.80078125],"type":"Point"}
}