{
  "type": "Feature",
  "properties": {
    "iso:country":"DE",
    "sg:address":"Flurweg 11",
    "sg:city":"Porta Westfalica",
    "sg:phone":"+49 571/58470",
    "sg:postcode":"32457",
    "sg:province":"Nordrhein-Westfalen",
    "wof:name":"Porta Garten-center Gmbh",
    "wof:placetype":"venue"
},
  "geometry": {"coordinates":[8.900314,52.260391],"type":"Point"}
}