{
  "type": "Feature",
  "properties": {
    "iso:country":"DE",
    "sg:address":"Brunnensteige 15",
    "sg:city":"Zwiefalten",
    "sg:phone":"+49 7373/92010",
    "sg:postcode":"88529",
    "sg:province":"Baden-W\u00fcrttemberg",
    "wof:name":"Dr. Med. Fridolin Gerhardt",
    "wof:placetype":"venue"
},
  "geometry": {"coordinates":[9.4676122665,48.2324676514],"type":"Point"}
}