{
  "type": "Feature",
  "properties": {
    "iso:country":"DE",
    "sg:address":"Lohstr. 13",
    "sg:city":"Marktredwitz",
    "sg:phone":"+49 9231/3048",
    "sg:postcode":"95615",
    "sg:province":"Bayern",
    "wof:name":"Hickfang Edelsteinfasser Werkst\u00e4tte Gmbh",
    "wof:placetype":"venue"
},
  "geometry": {"coordinates":[12.100998,50.023392],"type":"Point"}
}