{
  "type": "Feature",
  "properties": {
    "iso:country":"DE",
    "sg:address":"Hellenbach 22",
    "sg:city":"Dinkelsb\u00fchl",
    "sg:phone":"+49 9851/2416",
    "sg:postcode":"91550",
    "sg:province":"Bayern",
    "wof:name":"E. Karl",
    "wof:placetype":"venue"
},
  "geometry": {"coordinates":[10.3197078705,49.0943946838],"type":"Point"}
}