{
  "type": "Feature",
  "properties": {
    "iso:country":"DE",
    "sg:address":"Demminer Str. 30",
    "sg:city":"Erfurt",
    "sg:phone":"+49 361/7466922",
    "sg:postcode":"99091",
    "sg:province":"Th\u00fcringen",
    "wof:name":"Sieben Severi-verwaltungs- Verwaltungsgesellschaft Mbh",
    "wof:placetype":"venue"
},
  "geometry": {"coordinates":[10.9895563126,51.0129356384],"type":"Point"}
}