{
  "type": "Feature",
  "properties": {
    "iso:country":"DE",
    "sg:address":"Krautgartenweg 10",
    "sg:city":"Augsburg",
    "sg:phone":"+49 821/96799",
    "sg:postcode":"86199",
    "sg:province":"Bayern",
    "wof:name":"Harpaintner & Sohn Gmbh",
    "wof:placetype":"venue"
},
  "geometry": {"coordinates":[10.861657,48.334576],"type":"Point"}
}