{
  "type": "Feature",
  "properties": {
    "iso:country":"DE",
    "sg:address":"Ittlinger Str. 51",
    "sg:city":"Straubing",
    "sg:phone":"+49 9421/71364",
    "sg:postcode":"94315",
    "sg:province":"Bayern",
    "wof:name":"Richard Schwaiger Brennstoffe",
    "wof:placetype":"venue"
},
  "geometry": {"coordinates":[12.595084,48.884346],"type":"Point"}
}