{
  "type": "Feature",
  "properties": {
    "iso:country":"DE",
    "sg:address":"Am Bierweg 11",
    "sg:city":"Schwanstetten",
    "sg:phone":"+49 9170/1061",
    "sg:postcode":"90596",
    "sg:province":"Bayern",
    "wof:name":"Concertb\u00fcro H\u00e4nsel Gmbh",
    "wof:placetype":"venue"
},
  "geometry": {"coordinates":[11.1267995834,49.3118400574],"type":"Point"}
}