{
  "type": "Feature",
  "properties": {
    "iso:country":"DE",
    "sg:address":"Niederkleiner Str. 47",
    "sg:city":"Stadtallendorf",
    "sg:phone":"+49 6428/1423",
    "sg:postcode":"35260",
    "sg:province":"Hessen",
    "wof:name":"City-treff",
    "wof:placetype":"venue"
},
  "geometry": {"coordinates":[9.0136604309,50.8185997009],"type":"Point"}
}