{
  "type": "Feature",
  "properties": {
    "iso:country":"DE",
    "sg:address":"Botenheimer Str.",
    "sg:city":"Brackenheim",
    "sg:phone":"+49 7135/3820",
    "sg:postcode":"74336",
    "sg:province":"Baden-W\u00fcrttemberg",
    "wof:name":"Vereinsgastst\u00e4tte Tsv Botenheim E. V.",
    "wof:placetype":"venue"
},
  "geometry": {"coordinates":[9.083568573,49.0626945496],"type":"Point"}
}