{
  "type": "Feature",
  "properties": {
    "iso:country":"DE",
    "sg:address":"Eickelstr. 15",
    "sg:city":"Rheda-Wiedenbr\u00fcck",
    "sg:phone":"+49 5242/8968",
    "sg:postcode":"33378",
    "sg:province":"Nordrhein-Westfalen",
    "wof:name":"Eustermann Ohg Nachf. Josef Eustermann",
    "wof:placetype":"venue"
},
  "geometry": {"coordinates":[8.321125,51.836796],"type":"Point"}
}