{
  "type": "Feature",
  "properties": {
    "iso:country":"DE",
    "sg:address":"Gro\u00dfbberenstr.122",
    "sg:city":"Potsdam",
    "sg:phone":"+49 331/715319",
    "sg:postcode":"14482",
    "sg:province":"Brandenburg",
    "wof:name":"Segler.online.de - Webmaster Seite",
    "wof:placetype":"venue"
},
  "geometry": {"coordinates":[13.108104,52.38625],"type":"Point"}
}