{
  "type": "Feature",
  "properties": {
    "iso:country":"DE",
    "sg:address":"Kienhainweg 3",
    "sg:city":"Dinkelsb\u00fchl",
    "sg:postcode":"91550",
    "sg:province":"Bayern",
    "wof:name":"M\u00f6sch Steuerberatungsges. Mbh",
    "wof:placetype":"venue"
},
  "geometry": {"coordinates":[10.3239202499,49.0639038086],"type":"Point"}
}