{
  "type": "Feature",
  "properties": {
    "iso:country":"DE",
    "sg:address":"Soerser Weg 165",
    "sg:city":"Aachen",
    "sg:phone":"+49 241/151462",
    "sg:postcode":"52070",
    "sg:province":"Nordrhein-Westfalen",
    "wof:name":"Josef Cornetz",
    "wof:placetype":"venue"
},
  "geometry": {"coordinates":[6.092701,50.798935],"type":"Point"}
}