{
  "type": "Feature",
  "properties": {
    "iso:country":"DE",
    "sg:address":"Gr\u00fcntenseestr. 17",
    "sg:city":"Wertach",
    "sg:phone":"+49 8365/576",
    "sg:postcode":"87497",
    "sg:province":"Bayern",
    "wof:name":"Christa J\u00f6rg-dahlhaus",
    "wof:placetype":"venue"
},
  "geometry": {"coordinates":[10.4137620926,47.6024131775],"type":"Point"}
}