{
  "type": "Feature",
  "properties": {
    "iso:country":"DE",
    "sg:address":"Feldstr. 2",
    "sg:city":"Glash\u00fctten",
    "sg:phone":"+49 6082/931030",
    "sg:postcode":"61479",
    "sg:province":"Hessen",
    "wof:name":"Stefan J\u00c4ger",
    "wof:placetype":"venue"
},
  "geometry": {"coordinates":[8.40034,50.237221],"type":"Point"}
}