{
  "type": "Feature",
  "properties": {
    "iso:country":"DE",
    "sg:address":"Hermannstr. 52",
    "sg:city":"Dortmund",
    "sg:phone":"+49 231/433973",
    "sg:postcode":"44263",
    "sg:province":"Nordrhein-Westfalen",
    "wof:name":"Alte Apotheke Dr. F. Brauch Inh. Hans-hermann Brauch",
    "wof:placetype":"venue"
},
  "geometry": {"coordinates":[7.502129,51.489475],"type":"Point"}
}