{
  "type": "Feature",
  "properties": {
    "iso:country":"DE",
    "sg:address":"Wittumstr. 10",
    "sg:city":"Hambr\u00fccken",
    "sg:phone":"+49 7255/20244",
    "sg:postcode":"76707",
    "sg:province":"Baden-W\u00fcrttemberg",
    "wof:name":"Kr\u00e4mer & Sauer-schmidt",
    "wof:placetype":"venue"
},
  "geometry": {"coordinates":[8.553549,49.188358],"type":"Point"}
}