{
  "type": "Feature",
  "properties": {
    "iso:country":"DE",
    "sg:address":"Max-Planck-Str. 87",
    "sg:city":"Mannheim",
    "sg:phone":"+49 621/315566",
    "sg:postcode":"68169",
    "sg:province":"Baden-W\u00fcrttemberg",
    "wof:name":"Richard Dehus Fischerei",
    "wof:placetype":"venue"
},
  "geometry": {"coordinates":[8.4354381561,49.5345420837],"type":"Point"}
}