{
  "type": "Feature",
  "properties": {
    "iso:country":"DE",
    "sg:address":"Rathausstr. 5",
    "sg:city":"Staufenberg",
    "sg:phone":"+49 6406/908837",
    "sg:postcode":"35460",
    "sg:province":"Hessen",
    "wof:name":"Corplink Sales & Market Solution Gmbh",
    "wof:placetype":"venue"
},
  "geometry": {"coordinates":[8.73757267,50.6587371826],"type":"Point"}
}