{
  "type": "Feature",
  "properties": {
    "iso:country":"DE",
    "sg:address":"Hauptstr. 17",
    "sg:city":"Gochsheim",
    "sg:phone":"+49 9721/62208",
    "sg:postcode":"97469",
    "sg:province":"Bayern",
    "wof:name":"Gasthaus Zur Krone",
    "wof:placetype":"venue"
},
  "geometry": {"coordinates":[10.3157892227,50.0225601196],"type":"Point"}
}