{
  "type": "Feature",
  "properties": {
    "iso:country":"DE",
    "sg:address":"Holzhauser Str. 2",
    "sg:city":"Rheinau",
    "sg:phone":"+49 7853/1449",
    "sg:postcode":"77866",
    "sg:province":"Baden-W\u00fcrttemberg",
    "wof:name":"Joachim Metzen Architekt",
    "wof:placetype":"venue"
},
  "geometry": {"coordinates":[7.893055,48.623405],"type":"Point"}
}