{
  "type": "Feature",
  "properties": {
    "iso:country":"DE",
    "sg:address":"Foltzring 1",
    "sg:city":"Frankenthal",
    "sg:phone":"+49 6233/27420",
    "sg:postcode":"67227",
    "sg:province":"Rheinland-Pfalz",
    "wof:name":"Hirsch-apotheke Am Wormser Tor Hans-dieter Roth",
    "wof:placetype":"venue"
},
  "geometry": {"coordinates":[8.354098,49.538212],"type":"Point"}
}