{
  "type": "Feature",
  "properties": {
    "iso:country":"DE",
    "sg:address":"Op den St\u00fcben 42",
    "sg:city":"Reinbek",
    "sg:phone":"+49 40/7105138",
    "sg:postcode":"21465",
    "sg:province":"Schleswig-Holstein",
    "wof:name":"Heinrich Dierking Garten- Und",
    "wof:placetype":"venue"
},
  "geometry": {"coordinates":[10.242485,53.546749],"type":"Point"}
}