{
  "type": "Feature",
  "properties": {
    "iso:country":"DE",
    "sg:address":"Dorfstr. 4",
    "sg:city":"Traitsching",
    "sg:phone":"+49 9974/902033",
    "sg:postcode":"93455",
    "sg:province":"Bayern",
    "wof:name":"Hans Venus",
    "wof:placetype":"venue"
},
  "geometry": {"coordinates":[12.661117,49.165493],"type":"Point"}
}