{
  "type": "Feature",
  "properties": {
    "iso:country":"DE",
    "sg:address":"Bonner Str. 29",
    "sg:city":"D\u00fcsseldorf",
    "sg:phone":"+49 211/9886594",
    "sg:postcode":"40589",
    "sg:province":"Nordrhein-Westfalen",
    "wof:name":"Deutsche Postbank Ag",
    "wof:placetype":"venue"
},
  "geometry": {"coordinates":[6.8356251717,51.174659729],"type":"Point"}
}