{
  "type": "Feature",
  "properties": {
    "iso:country":"DE",
    "sg:address":"Maybachstr. 15",
    "sg:city":"Neu-Ulm",
    "sg:phone":"+49 731/979600",
    "sg:postcode":"89233",
    "sg:province":"Bayern",
    "wof:name":"E. Raiss Gmbh & Co.",
    "wof:placetype":"venue"
},
  "geometry": {"coordinates":[10.0681219101,48.4224472046],"type":"Point"}
}