{
  "type": "Feature",
  "properties": {
    "iso:country":"DE",
    "sg:address":"Osianderstr. 5",
    "sg:city":"Stuttgart",
    "sg:phone":"+49 711/603166",
    "sg:postcode":"70197",
    "sg:province":"Baden-W\u00fcrttemberg",
    "wof:name":"Aspirator Gesellschaft F\u00fcr Entstaubungstechnik Mbh",
    "wof:placetype":"venue"
},
  "geometry": {"coordinates":[9.149021,48.766628],"type":"Point"}
}