{
  "type": "Feature",
  "properties": {
    "iso:country":"DE",
    "sg:address":"Wehlitzer Str. 2",
    "sg:city":"Schkeuditz",
    "sg:phone":"+49 34204/7180",
    "sg:postcode":"04435",
    "sg:province":"Sachsen",
    "wof:name":"Mauser-office Gmbh",
    "wof:placetype":"venue"
},
  "geometry": {"coordinates":[12.194872,51.398952],"type":"Point"}
}