{
  "type": "Feature",
  "properties": {
    "iso:country":"DE",
    "sg:address":"Eitorferstr. 3",
    "sg:city":"Windeck",
    "sg:phone":"+49 4922/432493",
    "sg:postcode":"51570",
    "sg:province":"Nordrhein-Westfalen",
    "wof:name":"Franz Druck Gmbh",
    "wof:placetype":"venue"
},
  "geometry": {"coordinates":[7.519671917,50.7598266602],"type":"Point"}
}