{
  "type": "Feature",
  "properties": {
    "iso:country":"DE",
    "sg:address":"Zur Auheide 6",
    "sg:city":"Hilter",
    "sg:phone":"+49 5409/1786",
    "sg:postcode":"49176",
    "sg:province":"Niedersachsen",
    "wof:name":"Wilfried Grewe",
    "wof:placetype":"venue"
},
  "geometry": {"coordinates":[8.186652,52.174038],"type":"Point"}
}