{
  "type": "Feature",
  "properties": {
    "iso:country":"DE",
    "sg:address":"Bergheim 15",
    "sg:city":"Markdorf",
    "sg:phone":"+49 7544/3726",
    "sg:postcode":"88677",
    "sg:province":"Baden-W\u00fcrttemberg",
    "wof:name":"W. Bernhardt",
    "wof:placetype":"venue"
},
  "geometry": {"coordinates":[9.3893356323,47.7208862305],"type":"Point"}
}