{
  "type": "Feature",
  "properties": {
    "iso:country":"DE",
    "sg:address":"Obernstr. 36",
    "sg:city":"Stadthagen",
    "sg:phone":"+49 5721/2172",
    "sg:postcode":"31655",
    "sg:province":"Niedersachsen",
    "wof:name":"Restaurant Harran",
    "wof:placetype":"venue"
},
  "geometry": {"coordinates":[9.2052316666,52.3216781616],"type":"Point"}
}