{
  "type": "Feature",
  "properties": {
    "iso:country":"DE",
    "sg:address":"Am Sch\u00fctzenhaus 2",
    "sg:city":"Butzbach",
    "sg:phone":"+49 6033/970804",
    "sg:postcode":"35510",
    "sg:province":"Hessen",
    "wof:name":"Verleger & K\u00f6hler",
    "wof:placetype":"venue"
},
  "geometry": {"coordinates":[8.6546468735,50.4374198914],"type":"Point"}
}