{
  "type": "Feature",
  "properties": {
    "iso:country":"DE",
    "sg:address":"Halterner Str. 299",
    "sg:city":"D\u00fclmen",
    "sg:phone":"+49 2594/2631",
    "sg:postcode":"48249",
    "sg:province":"Nordrhein-Westfalen",
    "wof:name":"Heinrich Unterberg",
    "wof:placetype":"venue"
},
  "geometry": {"coordinates":[7.246534,51.809795],"type":"Point"}
}