{
  "type": "Feature",
  "properties": {
    "iso:country":"DE",
    "sg:address":"Carthausplatz 1",
    "sg:city":"Frankfurt",
    "sg:phone":"+49 335/556470",
    "sg:postcode":"15230",
    "sg:province":"Brandenburg",
    "wof:name":"Victoria Versicherungen",
    "wof:placetype":"venue"
},
  "geometry": {"coordinates":[14.5530147552,52.3335380554],"type":"Point"}
}