{
  "type": "Feature",
  "properties": {
    "iso:country":"DE",
    "sg:address":"K\u00fchnerstr. 3",
    "sg:city":"Viernheim",
    "sg:phone":"+49 6204/5681",
    "sg:postcode":"68519",
    "sg:province":"Hessen",
    "wof:name":"Willi Jakob",
    "wof:placetype":"venue"
},
  "geometry": {"coordinates":[8.574552536,49.5402870178],"type":"Point"}
}