{
  "type": "Feature",
  "properties": {
    "iso:country":"DE",
    "sg:address":"Pr\u00e4toriusweg 16",
    "sg:city":"Hamburg",
    "sg:postcode":"20255",
    "sg:province":"Hamburg",
    "wof:name":"Ruschin Gmbh",
    "wof:placetype":"venue"
},
  "geometry": {"coordinates":[9.953303,53.580643],"type":"Point"}
}