{
  "type": "Feature",
  "properties": {
    "iso:country":"DE",
    "sg:address":"G\u00e4rtnerstr. 38",
    "sg:city":"Zeitz",
    "sg:phone":"+49 3441/5468",
    "sg:postcode":"06712",
    "sg:province":"Sachsen-Anhalt",
    "wof:name":"O. Doleschal",
    "wof:placetype":"venue"
},
  "geometry": {"coordinates":[12.1244182587,51.0606117249],"type":"Point"}
}