{
  "type": "Feature",
  "properties": {
    "iso:country":"DE",
    "sg:address":"Nonnendammallee 86",
    "sg:city":"Berlin",
    "sg:phone":"+49 30/3828038",
    "sg:postcode":"13629",
    "sg:province":"Berlin",
    "wof:name":"Ristows-apotheke Inh. Margarete Sparkowsky",
    "wof:placetype":"venue"
},
  "geometry": {"coordinates":[13.270582,52.536358],"type":"Point"}
}