{
  "type": "Feature",
  "properties": {
    "iso:country":"DE",
    "sg:address":"Robert-Bosch-Str. 7",
    "sg:city":"Elchingen",
    "sg:phone":"+49 7308/6006",
    "sg:postcode":"89275",
    "sg:province":"Bayern",
    "wof:name":"Eap Wolfgang Lachnit Gmbh",
    "wof:placetype":"venue"
},
  "geometry": {"coordinates":[10.1029481888,48.4524154663],"type":"Point"}
}