{
  "type": "Feature",
  "properties": {
    "iso:country":"DE",
    "sg:address":"Gadumerstr. 61",
    "sg:city":"Unna",
    "sg:phone":"+49 2303/68102",
    "sg:postcode":"59425",
    "sg:province":"Nordrhein-Westfalen",
    "wof:name":"Karlheinz Br\u00e4ckelmann",
    "wof:placetype":"venue"
},
  "geometry": {"coordinates":[7.672907,51.558369],"type":"Point"}
}