{
  "type": "Feature",
  "properties": {
    "iso:country":"DE",
    "sg:address":"M\u00fchltorstr. 4",
    "sg:city":"Bad Wurzach",
    "sg:phone":"+49 7564/1478",
    "sg:postcode":"88410",
    "sg:province":"Baden-W\u00fcrttemberg",
    "wof:name":"M. Sugg",
    "wof:placetype":"venue"
},
  "geometry": {"coordinates":[9.896197,47.907364],"type":"Point"}
}