{
  "type": "Feature",
  "properties": {
    "iso:country":"DE",
    "sg:address":"Albert-Schweitzer-Str 12",
    "sg:city":"Stuhr",
    "sg:phone":"+49 421/894080",
    "sg:postcode":"28816",
    "sg:province":"Niedersachsen",
    "wof:name":"Ingenieurb\u00fcro Prof. Dipl.-ing. J. Dittrich",
    "wof:placetype":"venue"
},
  "geometry": {"coordinates":[8.78728,53.004402],"type":"Point"}
}