{
  "type": "Feature",
  "properties": {
    "iso:country":"DE",
    "sg:address":"Nordstr. 4",
    "sg:city":"Hadamar",
    "sg:phone":"+49 6433/3611",
    "sg:postcode":"65589",
    "sg:province":"Hessen",
    "wof:name":"Hedwig Menier",
    "wof:placetype":"venue"
},
  "geometry": {"coordinates":[8.0611953735,50.4757499695],"type":"Point"}
}