{
  "type": "Feature",
  "properties": {
    "iso:country":"DE",
    "sg:address":"Postfach 1144:: 02901 Niesky:: Germany.^^G\u00f6rlitzer Str 12::",
    "sg:city":"Niesky",
    "sg:postcode":"02906",
    "sg:province":"Sachsen",
    "wof:name":"Raiffeisenbank-volksbank Niesky-weisswasser Eg",
    "wof:placetype":"venue"
},
  "geometry": {"coordinates":[14.735344,51.288494],"type":"Point"}
}