{
  "type": "Feature",
  "properties": {
    "iso:country":"DE",
    "sg:address":"Richthausener Str. 14",
    "sg:city":"Winkelhaid",
    "sg:phone":"+49 9187/4741",
    "sg:postcode":"90610",
    "sg:province":"Bayern",
    "wof:name":"Wolfgang Abraham",
    "wof:placetype":"venue"
},
  "geometry": {"coordinates":[11.306307,49.388298],"type":"Point"}
}