{
  "type": "Feature",
  "properties": {
    "iso:country":"DE",
    "sg:address":"Oberpforte 10",
    "sg:city":"Bad Nauheim",
    "sg:phone":"+49 6032/81669",
    "sg:postcode":"61231",
    "sg:province":"Hessen",
    "wof:name":"Philipp Huber Inh. Hermann Huber",
    "wof:placetype":"venue"
},
  "geometry": {"coordinates":[8.74672,50.400723],"type":"Point"}
}