{
  "type": "Feature",
  "properties": {
    "iso:country":"DE",
    "sg:address":"Postfach 100687",
    "sg:city":"Solingen",
    "sg:postcode":"42606",
    "sg:province":"Nordrhein-Westfalen",
    "wof:name":"Karstadt Warenhaus Ag",
    "wof:placetype":"venue"
},
  "geometry": {"coordinates":[7.08352,51.172451],"type":"Point"}
}