{
  "type": "Feature",
  "properties": {
    "iso:country":"DE",
    "sg:address":"Oberfeld 9",
    "sg:city":"Seefeld",
    "sg:phone":"+49 8152/76284",
    "sg:postcode":"82229",
    "sg:province":"Bayern",
    "wof:name":"Blecha Entwicklungen Gmbh",
    "wof:placetype":"venue"
},
  "geometry": {"coordinates":[11.182775,48.034061],"type":"Point"}
}