{
  "type": "Feature",
  "properties": {
    "iso:country":"DE",
    "sg:address":"Schillerstr. 4g",
    "sg:city":"Dresden",
    "sg:postcode":"01326",
    "sg:province":"Sachsen",
    "wof:name":"Deutsch-polnische Gesell. F\u00fcr S\u00e4chsisch-polnische Zusammen-",
    "wof:placetype":"venue"
},
  "geometry": {"coordinates":[13.8134536743,51.0572967529],"type":"Point"}
}