{
  "type": "Feature",
  "properties": {
    "iso:country":"DE",
    "sg:address":"Dewitzer Chaussee 7",
    "sg:city":"Burg Stargard",
    "sg:postcode":"17094",
    "sg:province":"Mecklenburg-Vorpommern",
    "wof:name":"Jugendherberge Neubrandenburg",
    "wof:placetype":"venue"
},
  "geometry": {"coordinates":[13.3198423386,53.4943733215],"type":"Point"}
}