{
  "type": "Feature",
  "properties": {
    "iso:country":"DE",
    "sg:address":"Handstr. 34",
    "sg:city":"Bergisch Gladbach",
    "sg:phone":"+49 2202/57214",
    "sg:postcode":"51469",
    "sg:province":"Nordrhein-Westfalen",
    "wof:name":"Brigitte Sawatzki Steuerbevollm\u00e4chtigte",
    "wof:placetype":"venue"
},
  "geometry": {"coordinates":[7.0900621414,50.9880638123],"type":"Point"}
}