{
  "type": "Feature",
  "properties": {
    "iso:country":"DE",
    "sg:address":"Salzer-Str. 18b",
    "sg:city":"Sch\u00f6nebeck",
    "sg:phone":"+49 3928/2208",
    "sg:postcode":"39218",
    "sg:province":"Sachsen-Anhalt",
    "wof:name":"Commerzbank Ag",
    "wof:placetype":"venue"
},
  "geometry": {"coordinates":[11.742085,52.019646],"type":"Point"}
}