{
  "type": "Feature",
  "properties": {
    "iso:country":"DE",
    "sg:address":"Heinrich-B\u00f6ll-Str 38",
    "sg:city":"L\u00fcneburg",
    "sg:phone":"+49 4131/24270",
    "sg:postcode":"21335",
    "sg:province":"Niedersachsen",
    "wof:name":"G.v.k. First Unit Staples & Jeske Kg",
    "wof:placetype":"venue"
},
  "geometry": {"coordinates":[10.40455,53.226688],"type":"Point"}
}