{
  "type": "Feature",
  "properties": {
    "iso:country":"DE",
    "sg:address":"Aarstr. 218",
    "sg:city":"Taunusstein",
    "sg:phone":"+49 6128/6624",
    "sg:postcode":"65232",
    "sg:province":"Hessen",
    "wof:name":"Willi Schrank",
    "wof:placetype":"venue"
},
  "geometry": {"coordinates":[8.172033,50.146595],"type":"Point"}
}