{
  "type": "Feature",
  "properties": {
    "iso:country":"DE",
    "sg:address":"Kapuzinergraben 26",
    "sg:city":"Aachen",
    "sg:phone":"+49 241/407475",
    "sg:postcode":"52062",
    "sg:province":"Nordrhein-Westfalen",
    "wof:name":"Pr\u00e4senta Orient-teppiche Inh. Shahab Ebrahimi",
    "wof:placetype":"venue"
},
  "geometry": {"coordinates":[6.0856871605,50.7725563049],"type":"Point"}
}