{
  "type": "Feature",
  "properties": {
    "iso:country":"DE",
    "sg:address":"T\u00f6pferstr. 94",
    "sg:city":"Joachimsthal",
    "sg:phone":"+49 33361/592",
    "sg:postcode":"16247",
    "sg:province":"Brandenburg",
    "wof:name":"Artur Krupski",
    "wof:placetype":"venue"
},
  "geometry": {"coordinates":[13.754524,52.972897],"type":"Point"}
}