{
  "type": "Feature",
  "properties": {
    "iso:country":"DE",
    "sg:address":"Kleindeinbacher Str. 1",
    "sg:city":"Schw\u00e4bisch Gm\u00fcnd",
    "sg:phone":"+49 7171/73659",
    "sg:postcode":"73527",
    "sg:province":"Baden-W\u00fcrttemberg",
    "wof:name":"Franz Lang",
    "wof:placetype":"venue"
},
  "geometry": {"coordinates":[9.7532949448,48.8120346069],"type":"Point"}
}