{
  "type": "Feature",
  "properties": {
    "iso:country":"DE",
    "sg:address":"Neckarstr. 25",
    "sg:city":"Solingen",
    "sg:phone":"+49 4921/2203843",
    "sg:postcode":"42655",
    "sg:province":"Nordrhein-Westfalen",
    "wof:name":"Wilhelm Freese",
    "wof:placetype":"venue"
},
  "geometry": {"coordinates":[7.0745072365,51.1679039001],"type":"Point"}
}