{
  "type": "Feature",
  "properties": {
    "iso:country":"DE",
    "sg:address":"Keltergasse 17",
    "sg:city":"K\u00fcnzelsau",
    "sg:phone":"+49 7940/4500",
    "sg:postcode":"74653",
    "sg:province":"Baden-W\u00fcrttemberg",
    "wof:name":"Hornung Und Hermann Immobilienmakler",
    "wof:placetype":"venue"
},
  "geometry": {"coordinates":[9.6881771088,49.2779541016],"type":"Point"}
}