{
  "type": "Feature",
  "properties": {
    "iso:country":"DE",
    "sg:address":"Lengmoos 19",
    "sg:city":"Gars",
    "sg:phone":"+49 8072/8898",
    "sg:postcode":"83536",
    "sg:province":"Bayern",
    "wof:name":"Landgasthaus Berger",
    "wof:placetype":"venue"
},
  "geometry": {"coordinates":[12.2198858261,48.1413955688],"type":"Point"}
}