{
  "type": "Feature",
  "properties": {
    "iso:country":"DE",
    "sg:address":"Landsberger Str 80",
    "sg:city":"Essen",
    "sg:phone":"+49 2054/130",
    "sg:postcode":"45219",
    "sg:province":"Nordrhein-Westfalen",
    "wof:name":"Classen-convertronics Gmbh",
    "wof:placetype":"venue"
},
  "geometry": {"coordinates":[6.920238,51.361477],"type":"Point"}
}