{
  "type": "Feature",
  "properties": {
    "iso:country":"DE",
    "sg:address":"Drehergasse 6",
    "sg:city":"Karlsbad",
    "sg:phone":"+49 7248/8679",
    "sg:postcode":"76307",
    "sg:province":"Baden-W\u00fcrttemberg",
    "wof:name":"Erwin Huber",
    "wof:placetype":"venue"
},
  "geometry": {"coordinates":[8.505594,48.866879],"type":"Point"}
}