{
  "type": "Feature",
  "properties": {
    "iso:country":"DE",
    "sg:address":"Georgenstr. 34",
    "sg:city":"Mindelheim",
    "sg:postcode":"87719",
    "sg:province":"Bayern",
    "wof:name":"Dr. H. Haisch Tierarzt",
    "wof:placetype":"venue"
},
  "geometry": {"coordinates":[10.4864501953,48.0424804688],"type":"Point"}
}