{
  "type": "Feature",
  "properties": {
    "iso:country":"DE",
    "sg:address":"Schwanthalerstr. 77",
    "sg:city":"M\u00fcnchen",
    "sg:postcode":"80336",
    "sg:province":"Bayern",
    "wof:name":"Schaum-stoffe Meyer Inh. Axel Meyer",
    "wof:placetype":"venue"
},
  "geometry": {"coordinates":[11.554401,48.137379],"type":"Point"}
}