{
  "type": "Feature",
  "properties": {
    "iso:country":"DE",
    "sg:address":"Untertraubenbach 43",
    "sg:city":"Cham",
    "sg:phone":"+49 9461/1525",
    "sg:postcode":"93413",
    "sg:province":"Bayern",
    "wof:name":"J. Holzer",
    "wof:placetype":"venue"
},
  "geometry": {"coordinates":[12.5808019638,49.2135810852],"type":"Point"}
}