{
  "type": "Feature",
  "properties": {
    "iso:country":"DE",
    "sg:address":"K.-Hofmann-Str. 10",
    "sg:city":"Boxberg",
    "sg:phone":"+49 7930/6788",
    "sg:postcode":"97944",
    "sg:province":"Baden-W\u00fcrttemberg",
    "wof:name":"Dr. Ulshoefer Internet Werbung",
    "wof:placetype":"venue"
},
  "geometry": {"coordinates":[9.6379985809,49.4792098999],"type":"Point"}
}