{
  "type": "Feature",
  "properties": {
    "iso:country":"DE",
    "sg:address":"Kaldekirche 24a",
    "sg:city":"Essen",
    "sg:phone":"+49 201/301190",
    "sg:postcode":"45309",
    "sg:province":"Nordrhein-Westfalen",
    "wof:name":"Joachim Dersken Elektrotechnik",
    "wof:placetype":"venue"
},
  "geometry": {"coordinates":[7.049955,51.486546],"type":"Point"}
}