{
  "type": "Feature",
  "properties": {
    "iso:country":"DE",
    "sg:address":"Mozartstr. 2",
    "sg:city":"Ulm",
    "sg:phone":"+49 731/152111",
    "sg:postcode":"89075",
    "sg:province":"Baden-W\u00fcrttemberg",
    "wof:name":"Dr. Bertele Verwaltungs Gmbh",
    "wof:placetype":"venue"
},
  "geometry": {"coordinates":[9.9870510101,48.4077224731],"type":"Point"}
}