{
  "type": "Feature",
  "properties": {
    "iso:country":"DE",
    "sg:address":"Lange Gasse 7",
    "sg:city":"K\u00fcnzelsau",
    "sg:phone":"+49 7940/6670",
    "sg:postcode":"74653",
    "sg:province":"Baden-W\u00fcrttemberg",
    "wof:name":"Hirsch",
    "wof:placetype":"venue"
},
  "geometry": {"coordinates":[9.724861145,49.2732200623],"type":"Point"}
}