{
  "type": "Feature",
  "properties": {
    "iso:country":"DE",
    "sg:address":"Hofaue 41",
    "sg:city":"Wuppertal",
    "sg:postcode":"42103",
    "sg:province":"Nordrhein-Westfalen",
    "wof:name":"Benvenuto Mode F\u00fcr M\u00e4nner Gmbh",
    "wof:placetype":"venue"
},
  "geometry": {"coordinates":[7.15317,51.257198],"type":"Point"}
}