{
  "type": "Feature",
  "properties": {
    "iso:country":"DE",
    "sg:address":"Alter Rehmer Weg 128",
    "sg:city":"Bad Oeynhausen",
    "sg:phone":"+49 5731/22225",
    "sg:postcode":"32547",
    "sg:province":"Nordrhein-Westfalen",
    "wof:name":"Karl-heinz Kaase",
    "wof:placetype":"venue"
},
  "geometry": {"coordinates":[8.8256244659,52.2139663696],"type":"Point"}
}