{
  "type": "Feature",
  "properties": {
    "iso:country":"DE",
    "sg:address":"Windeichenweg 26",
    "sg:city":"Cuxhaven",
    "sg:phone":"+49 4721/22626",
    "sg:postcode":"27476",
    "sg:province":"Niedersachsen",
    "wof:name":"Pension Appelt",
    "wof:placetype":"venue"
},
  "geometry": {"coordinates":[8.6516418457,53.8776397705],"type":"Point"}
}