{
  "type": "Feature",
  "properties": {
    "iso:country":"DE",
    "sg:address":"Lange Gewanne 78",
    "sg:city":"Augsburg",
    "sg:phone":"+49 821/462516",
    "sg:postcode":"86156",
    "sg:province":"Bayern",
    "wof:name":"Hermann Seiler",
    "wof:placetype":"venue"
},
  "geometry": {"coordinates":[10.8481006622,48.398525238],"type":"Point"}
}