{
  "type": "Feature",
  "properties": {
    "iso:country":"DE",
    "sg:address":"Baumstr. 71",
    "sg:city":"D\u00fcsseldorf",
    "sg:phone":"+49 211/425143",
    "sg:postcode":"40468",
    "sg:province":"Nordrhein-Westfalen",
    "wof:name":"Hannelore Schulten Steuerberaterin",
    "wof:placetype":"venue"
},
  "geometry": {"coordinates":[6.7817149162,51.255153656],"type":"Point"}
}