{
  "type": "Feature",
  "properties": {
    "iso:country":"DE",
    "sg:address":"Bahnhofstr. 11",
    "sg:city":"Bad Bentheim",
    "sg:phone":"+49 5922/2889",
    "sg:postcode":"48455",
    "sg:province":"Niedersachsen",
    "wof:name":"K\u00fcno",
    "wof:placetype":"venue"
},
  "geometry": {"coordinates":[7.159986,52.304874],"type":"Point"}
}