{
  "type": "Feature",
  "properties": {
    "iso:country":"DE",
    "sg:address":"Olof-Palme-Str. 35",
    "sg:city":"Frankfurt",
    "sg:postcode":"60439",
    "sg:province":"Hessen",
    "wof:name":"Brugola Oeb Industrial Deutschland Gmbh",
    "wof:placetype":"venue"
},
  "geometry": {"coordinates":[8.641134,50.173512],"type":"Point"}
}