{
  "type": "Feature",
  "properties": {
    "iso:country":"DE",
    "sg:address":"Wiesharder Markt 10",
    "sg:city":"Handewitt",
    "sg:phone":"+49 4608/970337",
    "sg:postcode":"24983",
    "sg:province":"Schleswig-Holstein",
    "wof:name":"Gastst\u00e4tte Poseidon",
    "wof:placetype":"venue"
},
  "geometry": {"coordinates":[9.3228282928,54.7708282471],"type":"Point"}
}