{
  "type": "Feature",
  "properties": {
    "iso:country":"DE",
    "sg:address":"Liebigstr. 12",
    "sg:city":"Dieburg",
    "sg:phone":"+49 6071/820073",
    "sg:postcode":"64807",
    "sg:province":"Hessen",
    "wof:name":"Weber Textilhandels Gmbh",
    "wof:placetype":"venue"
},
  "geometry": {"coordinates":[8.854287,49.914249],"type":"Point"}
}