{
  "type": "Feature",
  "properties": {
    "iso:country":"DE",
    "sg:address":"Nollbrink 6",
    "sg:city":"Borgholzhausen",
    "sg:phone":"+49 5425/5184",
    "sg:postcode":"33829",
    "sg:province":"Nordrhein-Westfalen",
    "wof:name":"Willi Johannb\u00f6ke",
    "wof:placetype":"venue"
},
  "geometry": {"coordinates":[8.278272,52.094357],"type":"Point"}
}