{
  "type": "Feature",
  "properties": {
    "iso:country":"DE",
    "sg:address":"Friedrichstra\u00dfe 165",
    "sg:city":"Berlin",
    "sg:phone":"+49 30/2041080",
    "sg:postcode":"10172",
    "sg:province":"Berlin",
    "wof:name":"Neues Forum",
    "wof:placetype":"venue"
},
  "geometry": {"coordinates":[13.3888893127,52.5154762268],"type":"Point"}
}