{
  "type": "Feature",
  "properties": {
    "iso:country":"DE",
    "sg:address":"\u00d6lwiesenweg 7",
    "sg:city":"Kahla",
    "sg:phone":"+49 36424/23156",
    "sg:postcode":"07768",
    "sg:province":"Th\u00fcringen",
    "wof:name":"Vfm-vieh- Und Fleischmarketing Gmbh",
    "wof:placetype":"venue"
},
  "geometry": {"coordinates":[11.5898103714,50.8089904785],"type":"Point"}
}