{
  "type": "Feature",
  "properties": {
    "iso:country":"DE",
    "sg:address":"In den H\u00e4feles\u00e4ckern 32",
    "sg:city":"Mainhardt",
    "sg:phone":"+49 7903/2051",
    "sg:postcode":"74535",
    "sg:province":"Baden-W\u00fcrttemberg",
    "wof:name":"Ernst Frey",
    "wof:placetype":"venue"
},
  "geometry": {"coordinates":[9.574104,49.098312],"type":"Point"}
}