{
  "type": "Feature",
  "properties": {
    "iso:country":"DE",
    "sg:address":"Kleine Hamburger Str. 2",
    "sg:city":"Berlin",
    "sg:phone":"+49 30/2808088",
    "sg:postcode":"10115",
    "sg:province":"Berlin",
    "wof:name":"Falken-jugendfahrten",
    "wof:placetype":"venue"
},
  "geometry": {"coordinates":[13.3942213058,52.528175354],"type":"Point"}
}