{
  "type": "Feature",
  "properties": {
    "iso:country":"DE",
    "sg:address":"Entenpfuhler Weg 11",
    "sg:city":"Aachen",
    "sg:phone":"+49 241/71393",
    "sg:postcode":"52074",
    "sg:province":"Nordrhein-Westfalen",
    "wof:name":"Gut Entenpfuhl",
    "wof:placetype":"venue"
},
  "geometry": {"coordinates":[6.0571899414,50.735874176],"type":"Point"}
}