{
  "type": "Feature",
  "properties": {
    "iso:country":"DE",
    "sg:address":"Karl-B\u00fccher-Str. 7",
    "sg:city":"Bremen",
    "sg:phone":"+49 421/4841204",
    "sg:postcode":"28307",
    "sg:province":"Bremen",
    "wof:name":"K-tec Konstruktion Werk- Zeug- Und Maschinenbau Gmbh",
    "wof:placetype":"venue"
},
  "geometry": {"coordinates":[8.960414,53.037491],"type":"Point"}
}