{
  "type": "Feature",
  "properties": {
    "iso:country":"DE",
    "sg:address":"Im Belli 20",
    "sg:city":"Brigachtal",
    "sg:postcode":"78086",
    "sg:province":"Baden-W\u00fcrttemberg",
    "wof:name":"Raimond Kammerer Briefmarkenversand",
    "wof:placetype":"venue"
},
  "geometry": {"coordinates":[8.4520158768,48.0145339966],"type":"Point"}
}