{
  "type": "Feature",
  "properties": {
    "iso:country":"DE",
    "sg:address":"Nobelstr. 6",
    "sg:city":"Fulda",
    "sg:phone":"+49 4966/183010",
    "sg:postcode":"36041",
    "sg:province":"Hessen",
    "wof:name":"Teclac Werner Gmbh",
    "wof:placetype":"venue"
},
  "geometry": {"coordinates":[9.6020708084,50.5630455017],"type":"Point"}
}