{
  "type": "Feature",
  "properties": {
    "iso:country":"DE",
    "sg:address":"Altdorfer Str. 3",
    "sg:city":"Geithain",
    "sg:phone":"+49 34341/43412",
    "sg:postcode":"04643",
    "sg:province":"Sachsen",
    "wof:name":"Fliesen-handel-geithain Gmbh",
    "wof:placetype":"venue"
},
  "geometry": {"coordinates":[12.6814699173,51.0541191101],"type":"Point"}
}