{
  "type": "Feature",
  "properties": {
    "iso:country":"DE",
    "sg:address":"Frankfurter Str 22b",
    "sg:city":"Hennef",
    "sg:phone":"+49 2242/4579",
    "sg:postcode":"53773",
    "sg:province":"Nordrhein-Westfalen",
    "wof:name":"Labc-labortechnik M\u00fcller & Zillger Gbr",
    "wof:placetype":"venue"
},
  "geometry": {"coordinates":[7.29688,50.770267],"type":"Point"}
}