{
  "type": "Feature",
  "properties": {
    "iso:country":"DE",
    "sg:address":"Wolfener Str. 32-34",
    "sg:city":"Berlin",
    "sg:phone":"+49 30/4445466",
    "sg:postcode":"12681",
    "sg:province":"Berlin",
    "wof:name":"Ava Gmbh",
    "wof:placetype":"venue"
},
  "geometry": {"coordinates":[13.551414,52.560623],"type":"Point"}
}