{
  "type": "Feature",
  "properties": {
    "iso:country":"DE",
    "sg:address":"Eckstr. 14",
    "sg:city":"Oberhausen",
    "sg:phone":"+49 208/866600",
    "sg:postcode":"46045",
    "sg:province":"Nordrhein-Westfalen",
    "wof:name":"Hans Strietholt Steuerberater",
    "wof:placetype":"venue"
},
  "geometry": {"coordinates":[6.8649158478,51.4648208618],"type":"Point"}
}