{
  "type": "Feature",
  "properties": {
    "iso:country":"DE",
    "sg:address":"Zirkelstr. 31",
    "sg:city":"Bielefeld",
    "sg:phone":"+49 521/391043",
    "sg:postcode":"33729",
    "sg:province":"Nordrhein-Westfalen",
    "wof:name":"G\u00fcnter Klemme Verwaltungs Gmbh",
    "wof:placetype":"venue"
},
  "geometry": {"coordinates":[8.633333,52.042606],"type":"Point"}
}