{
  "type": "Feature",
  "properties": {
    "iso:country":"DE",
    "sg:address":"Hohenstaufenstr. 2",
    "sg:city":"Filderstadt",
    "sg:phone":"+49 711/706337",
    "sg:postcode":"70794",
    "sg:province":"Baden-W\u00fcrttemberg",
    "wof:name":"Rodewalds Kurierdienst",
    "wof:placetype":"venue"
},
  "geometry": {"coordinates":[9.221316,48.681934],"type":"Point"}
}