{
  "type": "Feature",
  "properties": {
    "iso:country":"DE",
    "sg:address":"Im Kurpark 3",
    "sg:city":"Schieder-Schwalenberg",
    "sg:phone":"+49 5282/8274",
    "sg:postcode":"32816",
    "sg:province":"Nordrhein-Westfalen",
    "wof:name":"Kurmittelhaus",
    "wof:placetype":"venue"
},
  "geometry": {"coordinates":[9.150095,51.918621],"type":"Point"}
}