{
  "type": "Feature",
  "properties": {
    "iso:country":"DE",
    "sg:address":"Obere Hauptstr. 1",
    "sg:city":"Lustadt",
    "sg:phone":"+49 6347/8807",
    "sg:postcode":"67363",
    "sg:province":"Rheinland-Pfalz",
    "wof:name":"C. Und R. Hellmann",
    "wof:placetype":"venue"
},
  "geometry": {"coordinates":[8.2872838974,49.2465019226],"type":"Point"}
}