{
  "type": "Feature",
  "properties": {
    "iso:country":"DE",
    "sg:address":"Rheinstr. 94",
    "sg:city":"Darmstadt",
    "sg:phone":"+49 6151/319141",
    "sg:postcode":"64295",
    "sg:province":"Hessen",
    "wof:name":"Didacta Ausstellungs- Und Verlags-gmbh",
    "wof:placetype":"venue"
},
  "geometry": {"coordinates":[8.6345815659,49.8703193665],"type":"Point"}
}