{
  "type": "Feature",
  "properties": {
    "iso:country":"DE",
    "sg:address":"Karlstr. 14",
    "sg:city":"Babenhausen",
    "sg:phone":"+49 6073/2714",
    "sg:postcode":"64832",
    "sg:province":"Hessen",
    "wof:name":"Harry Jans",
    "wof:placetype":"venue"
},
  "geometry": {"coordinates":[8.9443664551,49.9645729065],"type":"Point"}
}