{
  "type": "Feature",
  "properties": {
    "iso:country":"DE",
    "sg:address":"Alzenbacher Str. 137",
    "sg:city":"Eitorf",
    "sg:postcode":"53783",
    "sg:province":"Nordrhein-Westfalen",
    "wof:name":"Lechmann Industriemontage Gmbh",
    "wof:placetype":"venue"
},
  "geometry": {"coordinates":[7.48226,50.755821],"type":"Point"}
}