{
  "type": "Feature",
  "properties": {
    "iso:country":"DE",
    "sg:address":"Hindenburgstr. 8",
    "sg:city":"Itzehoe",
    "sg:phone":"+49 4821/3619",
    "sg:postcode":"25524",
    "sg:province":"Schleswig-Holstein",
    "wof:name":"Wolfgang Freund",
    "wof:placetype":"venue"
},
  "geometry": {"coordinates":[9.5227832794,53.9222373962],"type":"Point"}
}