{
  "type": "Feature",
  "properties": {
    "iso:country":"DE",
    "sg:address":"Schlo\u00dfgasse 1",
    "sg:city":"Neuhausen",
    "sg:phone":"+49 37361/45659",
    "sg:postcode":"09544",
    "sg:province":"Sachsen",
    "wof:name":"Walter Schmieder",
    "wof:placetype":"venue"
},
  "geometry": {"coordinates":[13.4691905975,50.6795654297],"type":"Point"}
}