{
  "type": "Feature",
  "properties": {
    "iso:country":"DE",
    "sg:address":"F\u00f6hrenstr 9",
    "sg:city":"Tuttlingen",
    "sg:phone":"+49 7461/3697",
    "sg:postcode":"78532",
    "sg:province":"Baden-W\u00fcrttemberg",
    "wof:name":"Dufner Instrumente Gmbh",
    "wof:placetype":"venue"
},
  "geometry": {"coordinates":[8.8389368057,47.973274231],"type":"Point"}
}