{
  "type": "Feature",
  "properties": {
    "iso:country":"DE",
    "sg:address":"Rudolf-Diener-Str. 18",
    "sg:city":"Gera",
    "sg:phone":"+49 365/8321161",
    "sg:postcode":"07545",
    "sg:province":"Th\u00fcringen",
    "wof:name":"Betten-br\u00e4uner",
    "wof:placetype":"venue"
},
  "geometry": {"coordinates":[12.0836181641,50.879196167],"type":"Point"}
}