{
  "type": "Feature",
  "properties": {
    "iso:country":"DE",
    "sg:address":"Sonnenallee 94",
    "sg:city":"Berlin",
    "sg:phone":"+49 30/6876017",
    "sg:postcode":"12045",
    "sg:province":"Berlin",
    "wof:name":"Brandi Moden",
    "wof:placetype":"venue"
},
  "geometry": {"coordinates":[13.438352,52.482246],"type":"Point"}
}