{
  "type": "Feature",
  "properties": {
    "iso:country":"DE",
    "sg:address":"Quintusstr. 133",
    "sg:city":"Walsrode",
    "sg:phone":"+49 4938/2937771",
    "sg:postcode":"29664",
    "sg:province":"Niedersachsen",
    "wof:name":"Kruth Ohg",
    "wof:placetype":"venue"
},
  "geometry": {"coordinates":[11.7444601059,54.1248893738],"type":"Point"}
}