{
  "type": "Feature",
  "properties": {
    "iso:country":"DE",
    "sg:address":"Va\u00dfmerstr. 7",
    "sg:city":"Buxtehude",
    "sg:phone":"+49 4161/54712",
    "sg:postcode":"21614",
    "sg:province":"Niedersachsen",
    "wof:name":"Heidrun Kr\u00e4mer Steuerberaterin",
    "wof:placetype":"venue"
},
  "geometry": {"coordinates":[9.6914539337,53.4734687805],"type":"Point"}
}