{
  "type": "Feature",
  "properties": {
    "iso:country":"DE",
    "sg:address":"Hauptstr. 64",
    "sg:city":"Endingen",
    "sg:phone":"+49 7642/8061",
    "sg:postcode":"79346",
    "sg:province":"Baden-W\u00fcrttemberg",
    "wof:name":"Dieter Griesbaum",
    "wof:placetype":"venue"
},
  "geometry": {"coordinates":[9.173674,48.39006],"type":"Point"}
}