{
  "type": "Feature",
  "properties": {
    "iso:country":"DE",
    "sg:address":"Tannenweg 1",
    "sg:city":"Stavenhagen",
    "sg:phone":"+49 39954/21609",
    "sg:postcode":"17153",
    "sg:province":"Mecklenburg-Vorpommern",
    "wof:name":"W. J\u00f6rend",
    "wof:placetype":"venue"
},
  "geometry": {"coordinates":[12.907034,53.692886],"type":"Point"}
}