{
  "type": "Feature",
  "properties": {
    "iso:country":"DE",
    "sg:address":"Am Sande 29",
    "sg:city":"L\u00fcneburg",
    "sg:phone":"+49 4131/42119",
    "sg:postcode":"21335",
    "sg:province":"Niedersachsen",
    "wof:name":"Klaus Schwaak",
    "wof:placetype":"venue"
},
  "geometry": {"coordinates":[10.384884,53.227989],"type":"Point"}
}