{
  "type": "Feature",
  "properties": {
    "iso:country":"DE",
    "sg:address":"Kirschallee 18",
    "sg:city":"Z\u00fctzen",
    "sg:phone":"+49 3332/510696",
    "sg:postcode":"16306",
    "sg:province":"Brandenburg",
    "wof:name":"Olf Benick",
    "wof:placetype":"venue"
},
  "geometry": {"coordinates":[14.2109642029,53.210559845],"type":"Point"}
}