{
  "type": "Feature",
  "properties": {
    "iso:country":"DE",
    "sg:address":"Postfach 1160:: 50301 Br\u00fchl:: Germany.^^Tiergartenstr 1-7::",
    "sg:city":"Br\u00fchl",
    "sg:phone":"+49 2232/70740",
    "sg:postcode":"50321",
    "sg:province":"Nordrhein-Westfalen",
    "wof:name":"Br\u00fchler Kreditbank Eg",
    "wof:placetype":"venue"
},
  "geometry": {"coordinates":[6.90557,50.830399],"type":"Point"}
}