{
  "type": "Feature",
  "properties": {
    "iso:country":"DE",
    "sg:address":"Weststr. 6",
    "sg:city":"Dessau",
    "sg:phone":"+49 340/530010",
    "sg:postcode":"06847",
    "sg:province":"Sachsen-Anhalt",
    "wof:name":"M\u00f6bius",
    "wof:placetype":"venue"
},
  "geometry": {"coordinates":[12.2220773697,51.8212432861],"type":"Point"}
}