{
  "type": "Feature",
  "properties": {
    "iso:country":"DE",
    "sg:address":"Molkereiweg 8",
    "sg:city":"Erkheim",
    "sg:phone":"+49 8336/7914",
    "sg:postcode":"87746",
    "sg:province":"Bayern",
    "wof:name":"W. Steinhauser",
    "wof:placetype":"venue"
},
  "geometry": {"coordinates":[10.336804,48.038139],"type":"Point"}
}