{
  "type": "Feature",
  "properties": {
    "iso:country":"DE",
    "sg:address":"Katharinenstr. 14",
    "sg:city":"Freiburg",
    "sg:phone":"+49 761/276505",
    "sg:postcode":"79104",
    "sg:province":"Baden-W\u00fcrttemberg",
    "wof:name":"Uhlenpress Verlag E. K.",
    "wof:placetype":"venue"
},
  "geometry": {"coordinates":[7.8490400314,48.000453949],"type":"Point"}
}