{
  "type": "Feature",
  "properties": {
    "iso:country":"DE",
    "sg:address":"Nordstr. 10",
    "sg:city":"Markranst\u00e4dt",
    "sg:phone":"+49 34205/87353",
    "sg:postcode":"04420",
    "sg:province":"Sachsen",
    "wof:name":"Henry Schuster",
    "wof:placetype":"venue"
},
  "geometry": {"coordinates":[12.2270212173,51.3102073669],"type":"Point"}
}