{
  "type": "Feature",
  "properties": {
    "iso:country":"DE",
    "sg:address":"Markt 40",
    "sg:city":"Rudolstadt",
    "sg:postcode":"07407",
    "sg:province":"Th\u00fcringen",
    "wof:name":"M. Dehnhardt Gmbh & Co. Forst Holz Jagd Handels-",
    "wof:placetype":"venue"
},
  "geometry": {"coordinates":[11.3408670425,50.7204284668],"type":"Point"}
}