{
  "type": "Feature",
  "properties": {
    "iso:country":"DE",
    "sg:address":"Mittelweg 99",
    "sg:city":"Oelde",
    "sg:phone":"+49 4925/2293090",
    "sg:postcode":"59302",
    "sg:province":"Nordrhein-Westfalen",
    "wof:name":"Caramasov Textil-mode-design-gmbh",
    "wof:placetype":"venue"
},
  "geometry": {"coordinates":[8.14326,51.849636],"type":"Point"}
}