{
  "type": "Feature",
  "properties": {
    "iso:country":"DE",
    "sg:address":"Kalkarer Str. 77",
    "sg:city":"Kleve",
    "sg:phone":"+49 2821/77730",
    "sg:postcode":"47533",
    "sg:province":"Nordrhein-Westfalen",
    "wof:name":"Praktiker Bau- Und Heimwerkermarkt",
    "wof:placetype":"venue"
},
  "geometry": {"coordinates":[6.1513528824,51.7831077576],"type":"Point"}
}