{
  "type": "Feature",
  "properties": {
    "iso:country":"DE",
    "sg:address":"Hochfeldstr. 9",
    "sg:city":"Grafing",
    "sg:phone":"+49 8092/1633",
    "sg:postcode":"85567",
    "sg:province":"Bayern",
    "wof:name":"W. Fahner",
    "wof:placetype":"venue"
},
  "geometry": {"coordinates":[11.9073457718,48.0207824707],"type":"Point"}
}