{
  "type": "Feature",
  "properties": {
    "iso:country":"DE",
    "sg:address":"Brucknerstr. 32",
    "sg:city":"Steinhagen",
    "sg:phone":"+49 5204/6600",
    "sg:postcode":"33803",
    "sg:province":"Nordrhein-Westfalen",
    "wof:name":"Gert U. Petra Wellnitz",
    "wof:placetype":"venue"
},
  "geometry": {"coordinates":[8.4252758026,52.0030899048],"type":"Point"}
}