{
  "type": "Feature",
  "properties": {
    "iso:country":"DE",
    "sg:address":"Gr\u00e4fstr. 78",
    "sg:city":"M\u00fcnchen",
    "sg:phone":"+49 89/89669986",
    "sg:postcode":"81241",
    "sg:province":"Bayern",
    "wof:name":"Nis Bauunternehmen Gmbh & Co. Kg",
    "wof:placetype":"venue"
},
  "geometry": {"coordinates":[11.459189,48.142639],"type":"Point"}
}