{
  "type": "Feature",
  "properties": {
    "iso:country":"DE",
    "sg:address":"B\u00fcrgerm.-Mahr-Str. 4",
    "sg:city":"Obertshausen",
    "sg:postcode":"63179",
    "sg:province":"Hessen",
    "wof:name":"Reifen-service Karakus Gmbh",
    "wof:placetype":"venue"
},
  "geometry": {"coordinates":[8.8725538254,50.0791397095],"type":"Point"}
}