{
  "type": "Feature",
  "properties": {
    "iso:country":"DE",
    "sg:address":"Jakob-Sigle-Platz 3",
    "sg:city":"Kornwestheim",
    "sg:phone":"+49 7154/22448",
    "sg:postcode":"70806",
    "sg:province":"Baden-W\u00fcrttemberg",
    "wof:name":"Wanner Ohnesorg Und Schmidt",
    "wof:placetype":"venue"
},
  "geometry": {"coordinates":[9.1851968765,48.8591537476],"type":"Point"}
}