{
  "type": "Feature",
  "properties": {
    "iso:country":"DE",
    "sg:address":"Schillerstr. 10",
    "sg:city":"Stutensee",
    "sg:phone":"+49 7249/6623",
    "sg:postcode":"76297",
    "sg:province":"Baden-W\u00fcrttemberg",
    "wof:name":"S. Und B. Bernhardt",
    "wof:placetype":"venue"
},
  "geometry": {"coordinates":[8.476,49.105843],"type":"Point"}
}