{
  "type": "Feature",
  "properties": {
    "iso:country":"DE",
    "sg:address":"Mettinger Str. 135",
    "sg:city":"Recke",
    "sg:phone":"+49 5453/93050",
    "sg:postcode":"49509",
    "sg:province":"Nordrhein-Westfalen",
    "wof:name":"Recker Ziegelwerk Berentelg & Hebrok",
    "wof:placetype":"venue"
},
  "geometry": {"coordinates":[7.7344059944,52.34425354],"type":"Point"}
}