{
  "type": "Feature",
  "properties": {
    "iso:country":"DE",
    "sg:address":"Eggeweg 2",
    "sg:city":"Bielefeld",
    "sg:phone":"+49 521/141494",
    "sg:postcode":"33617",
    "sg:province":"Nordrhein-Westfalen",
    "wof:name":"B. Kortmann",
    "wof:placetype":"venue"
},
  "geometry": {"coordinates":[8.5100431442,52.0051345825],"type":"Point"}
}