{
  "type": "Feature",
  "properties": {
    "iso:country":"DE",
    "sg:address":"Baaderstr 56c",
    "sg:city":"M\u00fcnchen",
    "sg:phone":"+49 89/2025300",
    "sg:postcode":"80469",
    "sg:province":"Bayern",
    "wof:name":"Pantos Werbeagentur Gwa Gmbh",
    "wof:placetype":"venue"
},
  "geometry": {"coordinates":[11.57718,48.129665],"type":"Point"}
}