{
  "type": "Feature",
  "properties": {
    "iso:country":"DE",
    "sg:address":"Waasemstr. 9",
    "sg:city":"Bornheim",
    "sg:phone":"+49 2227/1659",
    "sg:postcode":"53332",
    "sg:province":"Nordrhein-Westfalen",
    "wof:name":"E. Schmitz & P. Wolber Gmbh",
    "wof:placetype":"venue"
},
  "geometry": {"coordinates":[6.9277911186,50.7605628967],"type":"Point"}
}