{
  "type": "Feature",
  "properties": {
    "iso:country":"DE",
    "sg:address":"Nordh\u00e4user Str. 7",
    "sg:city":"Erfurt",
    "sg:phone":"+49 361/2112561",
    "sg:postcode":"99089",
    "sg:province":"Th\u00fcringen",
    "wof:name":"Heinemann Gmbh",
    "wof:placetype":"venue"
},
  "geometry": {"coordinates":[11.018989,50.983917],"type":"Point"}
}