{
  "type": "Feature",
  "properties": {
    "iso:country":"DE",
    "sg:address":"Grie\u00dferstr. 2",
    "sg:city":"Ering",
    "sg:phone":"+49 8573/787",
    "sg:postcode":"94140",
    "sg:province":"Bayern",
    "wof:name":"F. Kainzlbauer",
    "wof:placetype":"venue"
},
  "geometry": {"coordinates":[13.1441278458,48.2993164062],"type":"Point"}
}