{
  "type": "Feature",
  "properties": {
    "iso:country":"DE",
    "sg:address":"Siemensstr. 12",
    "sg:city":"Freiburg",
    "sg:phone":"+49 761/5009662",
    "sg:postcode":"79108",
    "sg:province":"Baden-W\u00fcrttemberg",
    "wof:name":"E. Dubois",
    "wof:placetype":"venue"
},
  "geometry": {"coordinates":[7.8482079506,48.0186576843],"type":"Point"}
}