{
  "type": "Feature",
  "properties": {
    "iso:country":"DE",
    "sg:address":"Grimmstr. 3",
    "sg:city":"M\u00fcnchen",
    "sg:phone":"+49 89/3000780",
    "sg:postcode":"80336",
    "sg:province":"Bayern",
    "wof:name":"Bluelane W\u00e4chter & W\u00e4chter Interactive Gmbh",
    "wof:placetype":"venue"
},
  "geometry": {"coordinates":[11.5498151779,48.1260871887],"type":"Point"}
}