{
  "type": "Feature",
  "properties": {
    "iso:country":"DE",
    "sg:address":"Conradstr. 35",
    "sg:city":"Gera",
    "sg:postcode":"07548",
    "sg:province":"Th\u00fcringen",
    "wof:name":"Bauconsult Rt Gmbh",
    "wof:placetype":"venue"
},
  "geometry": {"coordinates":[12.062724,50.889004],"type":"Point"}
}