{
  "type": "Feature",
  "properties": {
    "iso:country":"DE",
    "sg:address":"Seestr. 10",
    "sg:city":"Utting",
    "sg:phone":"+49 8806/517",
    "sg:postcode":"86919",
    "sg:province":"Bayern",
    "wof:name":"Seerestaurant",
    "wof:placetype":"venue"
},
  "geometry": {"coordinates":[11.0965795517,48.0230712891],"type":"Point"}
}