{
  "type": "Feature",
  "properties": {
    "iso:country":"DE",
    "sg:address":"Wondreb 2",
    "sg:city":"Tirschenreuth",
    "sg:phone":"+49 9631/2211",
    "sg:postcode":"95643",
    "sg:province":"Bayern",
    "wof:name":"Kath. Pfarramt St. Maria",
    "wof:placetype":"venue"
},
  "geometry": {"coordinates":[12.3855800629,49.9095344543],"type":"Point"}
}