{
  "type": "Feature",
  "properties": {
    "iso:country":"DE",
    "sg:address":"St.-Martin-Str. 5",
    "sg:city":"Aichach",
    "sg:phone":"+49 8251/3432",
    "sg:postcode":"86551",
    "sg:province":"Bayern",
    "wof:name":"A. Reichhold",
    "wof:placetype":"venue"
},
  "geometry": {"coordinates":[11.183821,48.442776],"type":"Point"}
}