{
  "type": "Feature",
  "properties": {
    "iso:country":"DE",
    "sg:address":"Landshuter Str. 51",
    "sg:city":"Ergolding",
    "sg:phone":"+49 871/770246",
    "sg:postcode":"84030",
    "sg:province":"Bayern",
    "wof:name":"J. Klotz",
    "wof:placetype":"venue"
},
  "geometry": {"coordinates":[12.1618423462,48.5679664612],"type":"Point"}
}