{
  "type": "Feature",
  "properties": {
    "iso:country":"DE",
    "sg:address":"Schulstr. 14",
    "sg:city":"O\u00dfling",
    "sg:phone":"+49 35792/50502",
    "sg:postcode":"01920",
    "sg:province":"Sachsen",
    "wof:name":"G\u00fcnter Feist",
    "wof:placetype":"venue"
},
  "geometry": {"coordinates":[14.1679096222,51.3604011536],"type":"Point"}
}