{
  "type": "Feature",
  "properties": {
    "iso:country":"DE",
    "sg:address":"Narzissenstr. 33",
    "sg:city":"F\u00fcrth",
    "sg:phone":"+49 911/7530697",
    "sg:postcode":"90768",
    "sg:province":"Bayern",
    "wof:name":"Peter Enzmann",
    "wof:placetype":"venue"
},
  "geometry": {"coordinates":[10.9120206833,49.4919242859],"type":"Point"}
}