{
  "type": "Feature",
  "properties": {
    "iso:country":"DE",
    "sg:address":"Maximilianstr. 3",
    "sg:city":"Mindelheim",
    "sg:phone":"+49 8261/20212",
    "sg:postcode":"87719",
    "sg:province":"Bayern",
    "wof:name":"Cafe L\u00f6rcher",
    "wof:placetype":"venue"
},
  "geometry": {"coordinates":[10.490333,48.046753],"type":"Point"}
}