{
  "type": "Feature",
  "properties": {
    "iso:country":"DE",
    "sg:address":"Belvederestr. 65",
    "sg:city":"K\u00f6ln",
    "sg:postcode":"50933",
    "sg:province":"Nordrhein-Westfalen",
    "wof:name":"Rechtsanw\u00e4lte Kamp & M\u00fcting",
    "wof:placetype":"venue"
},
  "geometry": {"coordinates":[6.8737969398,50.9434928894],"type":"Point"}
}