{
  "type": "Feature",
  "properties": {
    "iso:country":"DE",
    "sg:address":"Heilbronner Str. 100",
    "sg:city":"Schw\u00e4bisch Hall",
    "sg:postcode":"74523",
    "sg:province":"Baden-W\u00fcrttemberg",
    "wof:name":"Ev. \u00d6ffentliche Bibliothek Diakonissenanstalt",
    "wof:placetype":"venue"
},
  "geometry": {"coordinates":[9.73713,49.120171],"type":"Point"}
}