{
  "type": "Feature",
  "properties": {
    "iso:country":"DE",
    "sg:address":"Plochinger Str. 37",
    "sg:city":"K\u00f6ngen",
    "sg:phone":"+49 7024/989941",
    "sg:postcode":"73257",
    "sg:province":"Baden-W\u00fcrttemberg",
    "wof:name":"Dr. P. Kreutzer Heilpraktiker",
    "wof:placetype":"venue"
},
  "geometry": {"coordinates":[9.3711509705,48.6837348938],"type":"Point"}
}