{
  "type": "Feature",
  "properties": {
    "iso:country":"DE",
    "sg:address":"Neusser Str. 20",
    "sg:city":"K\u00f6ln",
    "sg:phone":"+49 221/775440",
    "sg:postcode":"50670",
    "sg:province":"Nordrhein-Westfalen",
    "wof:name":"W\u00f6hlermann Lorenz Und Partner Rechtsanw\u00e4lte",
    "wof:placetype":"venue"
},
  "geometry": {"coordinates":[6.9581661224,50.9553222656],"type":"Point"}
}