{
  "type": "Feature",
  "properties": {
    "iso:country":"DE",
    "sg:address":"Tischbeinstr. 4",
    "sg:city":"Leipzig",
    "sg:postcode":"04229",
    "sg:province":"Sachsen",
    "wof:name":"\u00d6koplan Bauplanungs- Und Grundst\u00fccksverwaltungs Gmbh",
    "wof:placetype":"venue"
},
  "geometry": {"coordinates":[12.3451957703,51.3171463013],"type":"Point"}
}