{
  "type": "Feature",
  "properties": {
    "iso:country":"DE",
    "sg:address":"Parchetwiesen 45a",
    "sg:city":"Weilheim",
    "sg:phone":"+49 881/69988",
    "sg:postcode":"82362",
    "sg:province":"Bayern",
    "wof:name":"Weeke Werkzeugmaschinen Gmbh",
    "wof:placetype":"venue"
},
  "geometry": {"coordinates":[11.12568,47.844421],"type":"Point"}
}