{
  "type": "Feature",
  "properties": {
    "iso:country":"DE",
    "sg:address":"Pestalozzistr. 26c",
    "sg:city":"S\u00f6mmerda",
    "sg:phone":"+49 3634/601244",
    "sg:postcode":"99610",
    "sg:province":"Th\u00fcringen",
    "wof:name":"E. Gans",
    "wof:placetype":"venue"
},
  "geometry": {"coordinates":[11.1208238602,51.1554718018],"type":"Point"}
}