{
  "type": "Feature",
  "properties": {
    "iso:country":"DE",
    "sg:address":"Mittelstr. 51",
    "sg:city":"Beselich",
    "sg:phone":"+49 6484/6574",
    "sg:postcode":"65614",
    "sg:province":"Hessen",
    "wof:name":"H. Kramer",
    "wof:placetype":"venue"
},
  "geometry": {"coordinates":[8.1688079834,50.4538459778],"type":"Point"}
}