{
  "type": "Feature",
  "properties": {
    "iso:country":"DE",
    "sg:address":"Im Grund 11",
    "sg:city":"Aach",
    "sg:phone":"+49 7774/6747",
    "sg:postcode":"78267",
    "sg:province":"Baden-W\u00fcrttemberg",
    "wof:name":"Z. Stojilikovic Immobilienmakler",
    "wof:placetype":"venue"
},
  "geometry": {"coordinates":[8.8507432938,47.8392944336],"type":"Point"}
}