{
  "type": "Feature",
  "properties": {
    "iso:country":"DE",
    "sg:address":"Briloner Str. 34",
    "sg:city":"Winterberg",
    "sg:phone":"+49 2983/326",
    "sg:postcode":"59955",
    "sg:province":"Nordrhein-Westfalen",
    "wof:name":"Heinrich Ratte",
    "wof:placetype":"venue"
},
  "geometry": {"coordinates":[8.472394,51.25671],"type":"Point"}
}