{
  "type": "Feature",
  "properties": {
    "iso:country":"DE",
    "sg:address":"Siedlungsweg 8 a",
    "sg:city":"Hildesheim",
    "sg:phone":"+49 5121/53690",
    "sg:postcode":"31135",
    "sg:province":"Niedersachsen",
    "wof:name":"Hans-friedrich Krancke",
    "wof:placetype":"venue"
},
  "geometry": {"coordinates":[9.979932785,52.1604270935],"type":"Point"}
}