{
  "type": "Feature",
  "properties": {
    "iso:country":"DE",
    "sg:address":"Am Alten Bahnhof 4-8",
    "sg:city":"Brensbach",
    "sg:phone":"+49 6161/523",
    "sg:postcode":"64395",
    "sg:province":"Hessen",
    "wof:name":"Georg Steinmetz Gmbh & Co. Kg",
    "wof:placetype":"venue"
},
  "geometry": {"coordinates":[8.8762655258,49.773399353],"type":"Point"}
}