{
  "type": "Feature",
  "properties": {
    "iso:country":"DE",
    "sg:address":"Hilariusstr. 8",
    "sg:city":"Bad S\u00e4ckingen",
    "sg:phone":"+49 7761/2690",
    "sg:postcode":"79713",
    "sg:province":"Baden-W\u00fcrttemberg",
    "wof:name":"Werner Frank Architekt",
    "wof:placetype":"venue"
},
  "geometry": {"coordinates":[7.939864,47.555393],"type":"Point"}
}