{
  "type": "Feature",
  "properties": {
    "iso:country":"DE",
    "sg:address":"Hirschstr. 121",
    "sg:city":"Laichingen",
    "sg:phone":"+49 7333/6895",
    "sg:postcode":"89150",
    "sg:province":"Baden-W\u00fcrttemberg",
    "wof:name":"Hans Frank",
    "wof:placetype":"venue"
},
  "geometry": {"coordinates":[9.69936,48.493351],"type":"Point"}
}