{
  "type": "Feature",
  "properties": {
    "iso:country":"DE",
    "sg:address":"Kastanienallee 9 B",
    "sg:city":"Iserlohn",
    "sg:postcode":"58638",
    "sg:province":"Nordrhein-Westfalen",
    "wof:name":"Imb Automaten Gmbh",
    "wof:placetype":"venue"
},
  "geometry": {"coordinates":[7.689102,51.3969],"type":"Point"}
}