{
  "type": "Feature",
  "properties": {
    "iso:country":"DE",
    "sg:address":"Kranichstr. 8",
    "sg:city":"N\u00fcrnberg",
    "sg:phone":"+49 911/939880",
    "sg:postcode":"90427",
    "sg:province":"Bayern",
    "wof:name":"Mc Byte Edv Service- Und Vertriebsgesellschaft Mbh",
    "wof:placetype":"venue"
},
  "geometry": {"coordinates":[11.0254850388,49.4694976807],"type":"Point"}
}