{
  "type": "Feature",
  "properties": {
    "iso:country":"DE",
    "sg:address":"Kirchstr. 120",
    "sg:city":"Goch",
    "sg:phone":"+49 2823/2410",
    "sg:postcode":"47574",
    "sg:province":"Nordrhein-Westfalen",
    "wof:name":"Rickes Gmbh",
    "wof:placetype":"venue"
},
  "geometry": {"coordinates":[6.191146,51.720802],"type":"Point"}
}