{
  "type": "Feature",
  "properties": {
    "iso:country":"DE",
    "sg:address":"Winzerstr. 1",
    "sg:city":"Kolitzheim",
    "sg:postcode":"97509",
    "sg:province":"Bayern",
    "wof:name":"B & S Bauservice Gmbh",
    "wof:placetype":"venue"
},
  "geometry": {"coordinates":[10.19388,49.90498],"type":"Point"}
}