{
  "type": "Feature",
  "properties": {
    "iso:country":"DE",
    "sg:address":"Alsterberg 18",
    "sg:city":"Hamburg",
    "sg:phone":"+49 40/503301",
    "sg:postcode":"22335",
    "sg:province":"Hamburg",
    "wof:name":"Rainer Ullrich",
    "wof:placetype":"venue"
},
  "geometry": {"coordinates":[10.0122423172,53.6193351746],"type":"Point"}
}