{
  "type": "Feature",
  "properties": {
    "iso:country":"DE",
    "sg:address":"Eggm\u00fchler Str. 36",
    "sg:city":"Schierling",
    "sg:phone":"+49 9451/3647",
    "sg:postcode":"84069",
    "sg:province":"Bayern",
    "wof:name":"Bauzentrum Weingart Kg",
    "wof:placetype":"venue"
},
  "geometry": {"coordinates":[12.1451320648,48.8331298828],"type":"Point"}
}