{
  "type": "Feature",
  "properties": {
    "iso:country":"DE",
    "sg:address":"Industriestr 7",
    "sg:city":"Werl",
    "sg:phone":"+49 2922/861590",
    "sg:postcode":"59457",
    "sg:province":"Nordrhein-Westfalen",
    "wof:name":"Elmo Elektromotoren U. Maschinen Gmbh",
    "wof:placetype":"venue"
},
  "geometry": {"coordinates":[7.923500061,51.5596809387],"type":"Point"}
}