{
  "type": "Feature",
  "properties": {
    "iso:country":"DE",
    "sg:address":"Augsburger Str. 7",
    "sg:city":"Karlshuld",
    "sg:phone":"+49 8454/2553",
    "sg:postcode":"86668",
    "sg:province":"Bayern",
    "wof:name":"Johann Eubel",
    "wof:placetype":"venue"
},
  "geometry": {"coordinates":[11.284719,48.681515],"type":"Point"}
}