{
  "type": "Feature",
  "properties": {
    "iso:country":"DE",
    "sg:address":"Wilhelm-Kobelt-Str. 31",
    "sg:city":"Magdeburg",
    "sg:phone":"+49 391/7316550",
    "sg:postcode":"39108",
    "sg:province":"Sachsen-Anhalt",
    "wof:name":"Rs-m\u00f6bel Gmbh",
    "wof:placetype":"venue"
},
  "geometry": {"coordinates":[11.6075620651,52.1221389771],"type":"Point"}
}