{
  "type": "Feature",
  "properties": {
    "iso:country":"DE",
    "sg:address":"Mittlere Ortsstr. 66",
    "sg:city":"R\u00fclzheim",
    "sg:phone":"+49 7272/71029",
    "sg:postcode":"76761",
    "sg:province":"Rheinland-Pfalz",
    "wof:name":"J. Bohsung Lotto Und Toto",
    "wof:placetype":"venue"
},
  "geometry": {"coordinates":[8.29281,49.157265],"type":"Point"}
}