{
  "type": "Feature",
  "properties": {
    "iso:country":"DE",
    "sg:address":"Langestr. 5",
    "sg:city":"Altenhagen",
    "sg:phone":"+49 3961/8831",
    "sg:postcode":"17091",
    "sg:province":"Mecklenburg-Vorpommern",
    "wof:name":"Harald Range",
    "wof:placetype":"venue"
},
  "geometry": {"coordinates":[13.1050109863,53.7653312683],"type":"Point"}
}