{
  "type": "Feature",
  "properties": {
    "iso:country":"DE",
    "sg:address":"S\u00f6brigener Str. 44 b",
    "sg:city":"Pirna",
    "sg:phone":"+49 3501/523327",
    "sg:postcode":"01796",
    "sg:province":"Sachsen",
    "wof:name":"Otto Meinhardt & Sohn",
    "wof:placetype":"venue"
},
  "geometry": {"coordinates":[13.886233,50.982784],"type":"Point"}
}