{
  "type": "Feature",
  "properties": {
    "iso:country":"DE",
    "sg:address":"Gartenstr. 5",
    "sg:city":"Metzingen",
    "sg:phone":"+49 7123/20111",
    "sg:postcode":"72555",
    "sg:province":"Baden-W\u00fcrttemberg",
    "wof:name":"Pizzeria Express L'isola",
    "wof:placetype":"venue"
},
  "geometry": {"coordinates":[9.2851819992,48.5385169983],"type":"Point"}
}