{
  "type": "Feature",
  "properties": {
    "iso:country":"DE",
    "sg:address":"Jakob-Sch\u00fcle-Str. 42",
    "sg:city":"Pl\u00fcderhausen",
    "sg:phone":"+49 7181/84630",
    "sg:postcode":"73655",
    "sg:province":"Baden-W\u00fcrttemberg",
    "wof:name":"H. Und W. Schaaf",
    "wof:placetype":"venue"
},
  "geometry": {"coordinates":[9.5936632156,48.8003463745],"type":"Point"}
}