{
  "type": "Feature",
  "properties": {
    "iso:country":"DE",
    "sg:address":"Uhlandstr. 2",
    "sg:city":"Tiefenbronn",
    "sg:phone":"+49 7234/95550",
    "sg:postcode":"75233",
    "sg:province":"Baden-W\u00fcrttemberg",
    "wof:name":"Delux Schmuckwarenhandels Gmbh",
    "wof:placetype":"venue"
},
  "geometry": {"coordinates":[8.7929582596,48.8216094971],"type":"Point"}
}