{
  "type": "Feature",
  "properties": {
    "iso:country":"DE",
    "sg:address":"Wiesenthalstr. 6",
    "sg:city":"Freising",
    "sg:phone":"+49 8161/67837",
    "sg:postcode":"85356",
    "sg:province":"Bayern",
    "wof:name":"Cafe Brause",
    "wof:placetype":"venue"
},
  "geometry": {"coordinates":[11.758981,48.407784],"type":"Point"}
}