{
  "type": "Feature",
  "properties": {
    "iso:country":"DE",
    "sg:address":"G\u00fcnselstieg 7",
    "sg:city":"Hamburg",
    "sg:phone":"+49 40/6424043",
    "sg:postcode":"22177",
    "sg:province":"Hamburg",
    "wof:name":"Hbt Hamburger Bautechnik Mbh",
    "wof:placetype":"venue"
},
  "geometry": {"coordinates":[10.070556,53.61425],"type":"Point"}
}