{
  "type": "Feature",
  "properties": {
    "iso:country":"DE",
    "sg:address":"Wasserberg 3",
    "sg:city":"Trendelburg",
    "sg:phone":"+49 5675/433",
    "sg:postcode":"34388",
    "sg:province":"Hessen",
    "wof:name":"Udo Sch\u00f6nhut Masseur",
    "wof:placetype":"venue"
},
  "geometry": {"coordinates":[9.416059,51.572941],"type":"Point"}
}