{
  "type": "Feature",
  "properties": {
    "iso:country":"DE",
    "sg:address":"Karl-Liebknecht-Str. 14",
    "sg:city":"Hennigsdorf",
    "sg:phone":"+49 3302/225689",
    "sg:postcode":"16761",
    "sg:province":"Brandenburg",
    "wof:name":"Hesa Gmbh",
    "wof:placetype":"venue"
},
  "geometry": {"coordinates":[13.19051,52.6334],"type":"Point"}
}