{
  "type": "Feature",
  "properties": {
    "iso:country":"DE",
    "sg:address":"Schulstr. 12",
    "sg:city":"Wollin",
    "sg:phone":"+49 33833/70263",
    "sg:postcode":"14778",
    "sg:province":"Brandenburg",
    "wof:name":"Manfred Kirstein",
    "wof:placetype":"venue"
},
  "geometry": {"coordinates":[12.472187,52.279045],"type":"Point"}
}