{
  "type": "Feature",
  "properties": {
    "iso:country":"DE",
    "sg:address":"Reisingerstr. 8",
    "sg:city":"Ismaning",
    "sg:postcode":"85737",
    "sg:province":"Bayern",
    "wof:name":"Karl-h. Strasser",
    "wof:placetype":"venue"
},
  "geometry": {"coordinates":[11.6699771881,48.2223434448],"type":"Point"}
}