{
  "type": "Feature",
  "properties": {
    "iso:country":"DE",
    "sg:address":"Hinterm Hof 12",
    "sg:city":"Sinzheim",
    "sg:phone":"+49 7221/81115",
    "sg:postcode":"76547",
    "sg:province":"Baden-W\u00fcrttemberg",
    "wof:name":"Dieter Schechinger Gmbh & Co. Kg",
    "wof:placetype":"venue"
},
  "geometry": {"coordinates":[8.141801,48.760845],"type":"Point"}
}