{
  "type": "Feature",
  "properties": {
    "iso:country":"DE",
    "sg:address":"Stuttgarter Str. 91",
    "sg:city":"Calw",
    "sg:phone":"+49 7051/20580",
    "sg:postcode":"75365",
    "sg:province":"Baden-W\u00fcrttemberg",
    "wof:name":"V. Giaccone",
    "wof:placetype":"venue"
},
  "geometry": {"coordinates":[8.757389,48.710808],"type":"Point"}
}