{
  "type": "Feature",
  "properties": {
    "iso:country":"DE",
    "sg:address":"Sch\u00e4ftlarnstr. 2",
    "sg:city":"M\u00fcnchen",
    "sg:phone":"+49 89/774740",
    "sg:postcode":"81371",
    "sg:province":"Bayern",
    "wof:name":"Blumenland Alfons Stammermann",
    "wof:placetype":"venue"
},
  "geometry": {"coordinates":[11.557916,48.118271],"type":"Point"}
}