{
  "type": "Feature",
  "properties": {
    "iso:country":"DE",
    "sg:address":"Bahnhofstr. 32",
    "sg:city":"Piesport",
    "sg:phone":"+49 6507/92500",
    "sg:postcode":"54498",
    "sg:province":"Rheinland-Pfalz",
    "wof:name":"Carl Hoffmann Landmaschinenfachbetrieb Gmbh",
    "wof:placetype":"venue"
},
  "geometry": {"coordinates":[6.922414,49.881138],"type":"Point"}
}