{
  "type": "Feature",
  "properties": {
    "iso:country":"DE",
    "sg:address":"Wendorf 4",
    "sg:city":"Garz",
    "sg:phone":"+49 38304/290",
    "sg:postcode":"18574",
    "sg:province":"Mecklenburg-Vorpommern",
    "wof:name":"Landgaststst\u00e4tte",
    "wof:placetype":"venue"
},
  "geometry": {"coordinates":[13.2749252319,54.2978363037],"type":"Point"}
}