{
  "type": "Feature",
  "properties": {
    "iso:country":"DE",
    "sg:address":"Eichenstr. 10",
    "sg:city":"P\u00e4hl",
    "sg:phone":"+49 89/7460644",
    "sg:postcode":"82396",
    "sg:province":"Bayern",
    "wof:name":"Christian Hammerl",
    "wof:placetype":"venue"
},
  "geometry": {"coordinates":[11.1579418182,47.9247970581],"type":"Point"}
}