{
  "type": "Feature",
  "properties": {
    "iso:country":"DE",
    "sg:address":"In den Zehnteng\u00e4rten 2",
    "sg:city":"Efringen-Kirchen",
    "sg:postcode":"79588",
    "sg:province":"Baden-W\u00fcrttemberg",
    "wof:name":"Hxk Software Gmbh",
    "wof:placetype":"venue"
},
  "geometry": {"coordinates":[7.5417208672,47.6902236938],"type":"Point"}
}