{
  "type": "Feature",
  "properties": {
    "iso:country":"DE",
    "sg:address":"Stampfm\u00fcllerstr. 27",
    "sg:city":"Rostock",
    "sg:phone":"+49 381/4922651",
    "sg:postcode":"18057",
    "sg:province":"Mecklenburg-Vorpommern",
    "wof:name":"Schr\u00f6der-immobilien- Management",
    "wof:placetype":"venue"
},
  "geometry": {"coordinates":[12.1240940094,54.0863494873],"type":"Point"}
}