{
  "type": "Feature",
  "properties": {
    "iso:country":"DE",
    "sg:address":"Erlenstr 8",
    "sg:city":"Maitenbeth",
    "sg:phone":"+49 8076/1617",
    "sg:postcode":"83558",
    "sg:province":"Bayern",
    "wof:name":"Sprachendienst Russisch Elena Hotze",
    "wof:placetype":"venue"
},
  "geometry": {"coordinates":[12.0914506912,48.1491394043],"type":"Point"}
}