{
  "type": "Feature",
  "properties": {
    "iso:country":"DE",
    "sg:address":"Gardelegener Str. 46",
    "sg:city":"Salzwedel",
    "sg:phone":"+49 3901/82424",
    "sg:postcode":"29410",
    "sg:province":"Sachsen-Anhalt",
    "wof:name":"Manfred Wellkisch",
    "wof:placetype":"venue"
},
  "geometry": {"coordinates":[11.166074,52.840134],"type":"Point"}
}