{
  "type": "Feature",
  "properties": {
    "iso:country":"DE",
    "sg:address":"Wendelinusstr. 47",
    "sg:city":"H\u00fcrth",
    "sg:phone":"+49 2233/33422",
    "sg:postcode":"50354",
    "sg:province":"Nordrhein-Westfalen",
    "wof:name":"Th. Jansen & S. Wilden",
    "wof:placetype":"venue"
},
  "geometry": {"coordinates":[6.8145251274,50.8743972778],"type":"Point"}
}