{
  "type": "Feature",
  "properties": {
    "iso:country":"DE",
    "sg:address":"Relaisstr. 71-73",
    "sg:city":"Mannheim",
    "sg:phone":"+49 621/891651",
    "sg:postcode":"68219",
    "sg:province":"Baden-W\u00fcrttemberg",
    "wof:name":"Optik Heinrich Faust Brillen Und Kontaklinsen",
    "wof:placetype":"venue"
},
  "geometry": {"coordinates":[8.5374584198,49.4239387512],"type":"Point"}
}