{
  "type": "Feature",
  "properties": {
    "iso:country":"DE",
    "sg:address":"Donnerstr. 22",
    "sg:city":"Essen",
    "sg:phone":"+49 201/667825",
    "sg:postcode":"45355",
    "sg:province":"Nordrhein-Westfalen",
    "wof:name":"Werner K\u00f6hler",
    "wof:placetype":"venue"
},
  "geometry": {"coordinates":[6.9467492104,51.4827537537],"type":"Point"}
}