{
  "type": "Feature",
  "properties": {
    "iso:country":"DE",
    "sg:address":"Bergwerksring 1",
    "sg:city":"Nidda",
    "sg:phone":"+49 6043/401530",
    "sg:postcode":"63667",
    "sg:province":"Hessen",
    "wof:name":"Klaus J. Bl\u00e4sner",
    "wof:placetype":"venue"
},
  "geometry": {"coordinates":[8.9728679657,50.4089164734],"type":"Point"}
}