{
  "type": "Feature",
  "properties": {
    "iso:country":"DE",
    "sg:address":"Leuschnerstr. 18a",
    "sg:city":"Ludwigshafen",
    "sg:phone":"+49 621/524856",
    "sg:postcode":"67063",
    "sg:province":"Rheinland-Pfalz",
    "wof:name":"S. Hartelt-janssen \u00dcbersetzungsb\u00fcro",
    "wof:placetype":"venue"
},
  "geometry": {"coordinates":[8.429302,49.491447],"type":"Point"}
}