{
  "type": "Feature",
  "properties": {
    "iso:country":"DE",
    "sg:address":"Am Weidenring 1",
    "sg:city":"Biederitz",
    "sg:postcode":"39175",
    "sg:province":"Sachsen-Anhalt",
    "wof:name":"Aldi Gmbh & Co. Kg",
    "wof:placetype":"venue"
},
  "geometry": {"coordinates":[11.7242698669,52.1463317871],"type":"Point"}
}