{
  "type": "Feature",
  "properties": {
    "iso:country":"DE",
    "sg:address":"Schulgasse 13",
    "sg:city":"Idstein",
    "sg:phone":"+49 6126/91919",
    "sg:postcode":"65510",
    "sg:province":"Hessen",
    "wof:name":"Walter Scheid",
    "wof:placetype":"venue"
},
  "geometry": {"coordinates":[8.2681760788,50.2222213745],"type":"Point"}
}