{
  "type": "Feature",
  "properties": {
    "iso:country":"DE",
    "sg:address":"Salzburger Str. 12 a",
    "sg:city":"Wasserburg",
    "sg:phone":"+49 8071/5954",
    "sg:postcode":"83512",
    "sg:province":"Bayern",
    "wof:name":"Rupert Weiherer Rechtsanwalt",
    "wof:placetype":"venue"
},
  "geometry": {"coordinates":[12.2304992676,48.0564651489],"type":"Point"}
}