{
  "type": "Feature",
  "properties": {
    "iso:country":"DE",
    "sg:address":"Wiesbadener Str. 59 c",
    "sg:city":"Berlin",
    "sg:phone":"+49 30/2164740",
    "sg:postcode":"14197",
    "sg:province":"Berlin",
    "wof:name":"Edelgard Dietz",
    "wof:placetype":"venue"
},
  "geometry": {"coordinates":[13.30717659,52.47240448],"type":"Point"}
}