{
  "type": "Feature",
  "properties": {
    "iso:country":"DE",
    "sg:address":"Friedrichsbr\u00fccker Str. 1",
    "sg:city":"Kassel",
    "sg:phone":"+49 561/9893946",
    "sg:postcode":"34127",
    "sg:province":"Hessen",
    "wof:name":"Roswitha Wendel-schwigon",
    "wof:placetype":"venue"
},
  "geometry": {"coordinates":[9.5006380081,51.3366584778],"type":"Point"}
}