{
  "type": "Feature",
  "properties": {
    "iso:country":"DE",
    "sg:address":"Am Damm 15",
    "sg:city":"Hamburg",
    "sg:phone":"+49 40/6402242",
    "sg:postcode":"22175",
    "sg:province":"Hamburg",
    "wof:name":"Arthur Benedickt",
    "wof:placetype":"venue"
},
  "geometry": {"coordinates":[10.091619,53.631332],"type":"Point"}
}