{
  "type": "Feature",
  "properties": {
    "iso:country":"DE",
    "sg:address":"Neubauernstr. 1",
    "sg:city":"Eulau",
    "sg:phone":"+49 3445/701363",
    "sg:postcode":"06618",
    "sg:province":"Sachsen-Anhalt",
    "wof:name":"J\u00f6rg Hecht",
    "wof:placetype":"venue"
},
  "geometry": {"coordinates":[11.8509216309,51.1783294678],"type":"Point"}
}