{
  "type": "Feature",
  "properties": {
    "iso:country":"DE",
    "sg:address":"Geismarkter Str. 3",
    "sg:city":"Aletshausen",
    "sg:phone":"+49 8263/428",
    "sg:postcode":"86480",
    "sg:province":"Bayern",
    "wof:name":"Wiedemann Gro\u00df- U. Einzel- Handel Gmbh Parkettboden",
    "wof:placetype":"venue"
},
  "geometry": {"coordinates":[10.4160614014,48.2014465332],"type":"Point"}
}