{
  "type": "Feature",
  "properties": {
    "iso:country":"DE",
    "sg:address":"K\u00f6lner Str. 540",
    "sg:city":"Krefeld",
    "sg:phone":"+49 2151/301550",
    "sg:postcode":"47807",
    "sg:province":"Nordrhein-Westfalen",
    "wof:name":"Bellissima Str\u00fcmpfe Und Mode E. K.",
    "wof:placetype":"venue"
},
  "geometry": {"coordinates":[6.588106,51.304863],"type":"Point"}
}