{
  "type": "Feature",
  "properties": {
    "iso:country":"DE",
    "sg:address":"Regenstr. 7",
    "sg:city":"Erkrath",
    "sg:phone":"+49 2104/41674",
    "sg:postcode":"40699",
    "sg:province":"Nordrhein-Westfalen",
    "wof:name":"H.-m. Wirtz Architekt",
    "wof:placetype":"venue"
},
  "geometry": {"coordinates":[6.976014,51.210632],"type":"Point"}
}