{
  "type": "Feature",
  "properties": {
    "iso:country":"DE",
    "sg:address":"Gro\u00dfberghausen",
    "sg:city":"H\u00fcckeswagen",
    "sg:phone":"+49 2192/83389",
    "sg:postcode":"42499",
    "sg:province":"Nordrhein-Westfalen",
    "wof:name":"Friedel Wickesberg",
    "wof:placetype":"venue"
},
  "geometry": {"coordinates":[7.359844,51.145851],"type":"Point"}
}