{
  "type": "Feature",
  "properties": {
    "iso:country":"DE",
    "sg:address":"Ellernbrook 9a",
    "sg:city":"Kiel",
    "sg:phone":"+49 431/2059033",
    "sg:postcode":"24149",
    "sg:province":"Schleswig-Holstein",
    "wof:name":"Peter Dittmann Gmbh",
    "wof:placetype":"venue"
},
  "geometry": {"coordinates":[10.209287,54.322536],"type":"Point"}
}