{
  "type": "Feature",
  "properties": {
    "iso:country":"DE",
    "sg:city":"Schlieben",
    "sg:phone":"+49 35361/80940",
    "sg:postcode":"04936",
    "sg:province":"Brandenburg",
    "wof:name":"W. Friese",
    "wof:placetype":"venue"
},
  "geometry": {"coordinates":[13.384825,51.721947],"type":"Point"}
}