{
  "type": "Feature",
  "properties": {
    "iso:country":"DE",
    "sg:address":"Auf dem Schilde 4",
    "sg:city":"Steinfurt",
    "sg:phone":"+49 2552/2109",
    "sg:postcode":"48565",
    "sg:province":"Nordrhein-Westfalen",
    "wof:name":"Hans Wilbrand",
    "wof:placetype":"venue"
},
  "geometry": {"coordinates":[7.3942651749,52.1235198975],"type":"Point"}
}