{
  "type": "Feature",
  "properties": {
    "iso:country":"DE",
    "sg:address":"Magdeburger Str. 28e",
    "sg:city":"Wolmirstedt",
    "sg:postcode":"39326",
    "sg:province":"Sachsen-Anhalt",
    "wof:name":"Max Und Moritz Inh. Regina Moritz",
    "wof:placetype":"venue"
},
  "geometry": {"coordinates":[11.6201343536,52.2421112061],"type":"Point"}
}