{
  "type": "Feature",
  "properties": {
    "iso:country":"DE",
    "sg:address":"Grabenstr. 22",
    "sg:city":"Bad Ems",
    "sg:phone":"+49 2603/2975",
    "sg:postcode":"56130",
    "sg:province":"Rheinland-Pfalz",
    "wof:name":"Pension Else Oeser",
    "wof:placetype":"venue"
},
  "geometry": {"coordinates":[7.7315211296,50.3306655884],"type":"Point"}
}