{
  "type": "Feature",
  "properties": {
    "iso:country":"DE",
    "sg:address":"Breslauer Str. 9",
    "sg:city":"Haiterbach",
    "sg:phone":"+49 7456/250",
    "sg:postcode":"72221",
    "sg:province":"Baden-W\u00fcrttemberg",
    "wof:name":"A. Haizmann",
    "wof:placetype":"venue"
},
  "geometry": {"coordinates":[8.643352,48.520817],"type":"Point"}
}