{
  "type": "Feature",
  "properties": {
    "iso:country":"DE",
    "sg:address":"Kappenh\u00f6he 17a",
    "sg:city":"Salzgitter",
    "sg:phone":"+49 5341/71321",
    "sg:postcode":"38229",
    "sg:province":"Niedersachsen",
    "wof:name":"Dieter Thun Masseur",
    "wof:placetype":"venue"
},
  "geometry": {"coordinates":[10.344817,52.107971],"type":"Point"}
}