{
  "type": "Feature",
  "properties": {
    "iso:country":"DE",
    "sg:address":"Gro\u00dfenhainer Str. 8",
    "sg:city":"Thiendorf",
    "sg:phone":"+49 35240/7180",
    "sg:postcode":"01561",
    "sg:province":"Sachsen",
    "wof:name":"Boco Gmbh & Co.",
    "wof:placetype":"venue"
},
  "geometry": {"coordinates":[13.789024353,51.2849006653],"type":"Point"}
}