{
  "type": "Feature",
  "properties": {
    "iso:country":"DE",
    "sg:address":"Haydnstr. 16",
    "sg:city":"Krefeld",
    "sg:phone":"+49 2151/590059",
    "sg:postcode":"47800",
    "sg:province":"Nordrhein-Westfalen",
    "wof:name":"Hufnagel Und Heiden Rechtsanw\u00e4lte",
    "wof:placetype":"venue"
},
  "geometry": {"coordinates":[6.5855731964,51.3439445496],"type":"Point"}
}