{
  "type": "Feature",
  "properties": {
    "iso:country":"DE",
    "sg:address":"Holitzberg 78",
    "sg:city":"Hamburg",
    "sg:phone":"+49 40/5373991",
    "sg:postcode":"22417",
    "sg:province":"Hamburg",
    "wof:name":"Hans Hartig Ingenieur",
    "wof:placetype":"venue"
},
  "geometry": {"coordinates":[10.0247383118,53.6722145081],"type":"Point"}
}