{
  "type": "Feature",
  "properties": {
    "iso:country":"DE",
    "sg:address":"Sch\u00fctzenholzstr. 18",
    "sg:city":"Clenze",
    "sg:phone":"+49 5844/1344",
    "sg:postcode":"29459",
    "sg:province":"Niedersachsen",
    "wof:name":"Wilhelm Janiesch",
    "wof:placetype":"venue"
},
  "geometry": {"coordinates":[10.957746,52.936264],"type":"Point"}
}