{
  "type": "Feature",
  "properties": {
    "iso:country":"DE",
    "sg:address":"Haferweg 26",
    "sg:city":"Hamburg",
    "sg:phone":"+49 40/851810",
    "sg:postcode":"22769",
    "sg:province":"Hamburg",
    "wof:name":"Mediamatic 24.de Gmbh",
    "wof:placetype":"venue"
},
  "geometry": {"coordinates":[9.9405698776,53.5719566345],"type":"Point"}
}