{
  "type": "Feature",
  "properties": {
    "iso:country":"DE",
    "sg:address":"Marlistra\u00dfe 124",
    "sg:city":"L\u00fcbeck",
    "sg:phone":"+49 451/606818",
    "sg:postcode":"23566",
    "sg:province":"Schleswig-Holstein",
    "wof:name":"Angelsport Widerhaken",
    "wof:placetype":"venue"
},
  "geometry": {"coordinates":[10.7209815979,53.8635177612],"type":"Point"}
}