{
  "type": "Feature",
  "properties": {
    "iso:country":"DE",
    "sg:address":"Maximilianstr. 10",
    "sg:city":"Regensburg",
    "sg:phone":"+49 941/53537",
    "sg:postcode":"93047",
    "sg:province":"Bayern",
    "wof:name":"Hans-thomas Raith Und Alexander Wieland",
    "wof:placetype":"venue"
},
  "geometry": {"coordinates":[12.1002969742,49.0170097351],"type":"Point"}
}