{
  "type": "Feature",
  "properties": {
    "iso:country":"DE",
    "sg:address":"Schmidtstedter Str. 12-13",
    "sg:city":"Erfurt",
    "sg:phone":"+49 361/5613913",
    "sg:postcode":"99084",
    "sg:province":"Th\u00fcringen",
    "wof:name":"Michael H\u00f6seler Rechtsanwalt",
    "wof:placetype":"venue"
},
  "geometry": {"coordinates":[11.0375022888,50.9742431641],"type":"Point"}
}