{
  "type": "Feature",
  "properties": {
    "iso:country":"DE",
    "sg:address":"Belchenstr. 1",
    "sg:city":"Aitern",
    "sg:phone":"+49 7673/8763",
    "sg:postcode":"79677",
    "sg:province":"Baden-W\u00fcrttemberg",
    "wof:name":"Isabella Herling Heilpraktikerin",
    "wof:placetype":"venue"
},
  "geometry": {"coordinates":[7.8986577988,47.8018455505],"type":"Point"}
}