{
  "type": "Feature",
  "properties": {
    "iso:country":"DE",
    "sg:address":"Au\u00dferhalb",
    "sg:city":"Saulheim",
    "sg:phone":"+49 6732/5236",
    "sg:postcode":"55291",
    "sg:province":"Rheinland-Pfalz",
    "wof:name":"W. Freitag",
    "wof:placetype":"venue"
},
  "geometry": {"coordinates":[8.1538591385,49.8844871521],"type":"Point"}
}