{
  "type": "Feature",
  "properties": {
    "iso:country":"DE",
    "sg:address":"Liebfrauenstr. 51",
    "sg:city":"M\u00f6nchengladbach",
    "sg:phone":"+49 2161/994420",
    "sg:postcode":"41066",
    "sg:province":"Nordrhein-Westfalen",
    "wof:name":"Optik Schr\u00f6mges Gmbh",
    "wof:placetype":"venue"
},
  "geometry": {"coordinates":[6.4683208466,51.2243232727],"type":"Point"}
}