{
  "type": "Feature",
  "properties": {
    "iso:country":"DE",
    "sg:address":"Sandgasse 51",
    "sg:city":"Aschaffenburg",
    "sg:phone":"+49 6021/24740",
    "sg:postcode":"63739",
    "sg:province":"Bayern",
    "wof:name":"Sport Team Willig Gmbh",
    "wof:placetype":"venue"
},
  "geometry": {"coordinates":[9.150222,49.974407],"type":"Point"}
}