{
  "type": "Feature",
  "properties": {
    "iso:country":"DE",
    "sg:address":"Riedblickweg 1",
    "sg:city":"Ertingen",
    "sg:phone":"+49 7371/6502",
    "sg:postcode":"88521",
    "sg:province":"Baden-W\u00fcrttemberg",
    "wof:name":"Herbert Binder",
    "wof:placetype":"venue"
},
  "geometry": {"coordinates":[9.466615,48.102036],"type":"Point"}
}