{
  "type": "Feature",
  "properties": {
    "iso:country":"DE",
    "sg:address":"Am Kr\u00e4henberg 30",
    "sg:city":"Lennestadt",
    "sg:phone":"+49 2721/989277",
    "sg:postcode":"57368",
    "sg:province":"Nordrhein-Westfalen",
    "wof:name":"Elektro Rauchheld Gmbh",
    "wof:placetype":"venue"
},
  "geometry": {"coordinates":[8.0267705917,51.0915985107],"type":"Point"}
}