{
  "type": "Feature",
  "properties": {
    "iso:country":"DE",
    "sg:address":"Kardinal-von-Galen-Str. 22",
    "sg:city":"Mettingen",
    "sg:phone":"+49 5452/1812",
    "sg:postcode":"49497",
    "sg:province":"Nordrhein-Westfalen",
    "wof:name":"Photo Ursula Maletz Gmbh",
    "wof:placetype":"venue"
},
  "geometry": {"coordinates":[7.7787051201,52.3141326904],"type":"Point"}
}