{
  "type": "Feature",
  "properties": {
    "iso:country":"DE",
    "sg:address":"Kirchenplatz 9",
    "sg:city":"Rostock",
    "sg:postcode":"18119",
    "sg:province":"Mecklenburg-Vorpommern",
    "wof:name":"Reinhard Bast",
    "wof:placetype":"venue"
},
  "geometry": {"coordinates":[12.083984,54.17701],"type":"Point"}
}