{
  "type": "Feature",
  "properties": {
    "iso:country":"DE",
    "sg:address":"Zum Ra\u00dfberg 4",
    "sg:city":"Rotenburg",
    "sg:phone":"+49 6623/7164",
    "sg:postcode":"36199",
    "sg:province":"Hessen",
    "wof:name":"Erich Schwarze Kg",
    "wof:placetype":"venue"
},
  "geometry": {"coordinates":[9.68894,50.989361],"type":"Point"}
}