{
  "type": "Feature",
  "properties": {
    "iso:country":"DE",
    "sg:address":"Feldstr. 13",
    "sg:city":"Kerpen",
    "sg:phone":"+49 2237/2679",
    "sg:postcode":"50171",
    "sg:province":"Nordrhein-Westfalen",
    "wof:name":"Reiner Effertz",
    "wof:placetype":"venue"
},
  "geometry": {"coordinates":[6.695808,50.866894],"type":"Point"}
}