{
  "type": "Feature",
  "properties": {
    "iso:country":"DE",
    "sg:address":"Scheidter Str. 16",
    "sg:city":"Saarbr\u00fccken",
    "sg:phone":"+49 6897/765544",
    "sg:postcode":"66125",
    "sg:province":"Saarland",
    "wof:name":"E. Doppler",
    "wof:placetype":"venue"
},
  "geometry": {"coordinates":[7.0367231369,49.2761535645],"type":"Point"}
}