{
  "type": "Feature",
  "properties": {
    "iso:country":"DE",
    "sg:address":"Waldauenweg 2",
    "sg:city":"Hohenbocka",
    "sg:phone":"+49 35756/60931",
    "sg:postcode":"01945",
    "sg:province":"Brandenburg",
    "wof:name":"Liesk Baustoffhandel Gmbh",
    "wof:placetype":"venue"
},
  "geometry": {"coordinates":[14.0146923065,51.4328918457],"type":"Point"}
}