{
  "type": "Feature",
  "properties": {
    "iso:country":"DE",
    "sg:address":"Tegernseer Landstr. 61",
    "sg:city":"Taufkirchen",
    "sg:phone":"+49 89/6127091",
    "sg:postcode":"82024",
    "sg:province":"Bayern",
    "wof:name":"Josef Hiebler",
    "wof:placetype":"venue"
},
  "geometry": {"coordinates":[11.63043,48.043797],"type":"Point"}
}