{
  "type": "Feature",
  "properties": {
    "iso:country":"DE",
    "sg:address":"Sch\u00fctzenweg 1",
    "sg:city":"L\u00f6ffingen",
    "sg:phone":"+49 7654/8558",
    "sg:postcode":"79843",
    "sg:province":"Baden-W\u00fcrttemberg",
    "wof:name":"Oskar Winterhalder",
    "wof:placetype":"venue"
},
  "geometry": {"coordinates":[8.303694,47.85965],"type":"Point"}
}