{
  "type": "Feature",
  "properties": {
    "iso:country":"DE",
    "sg:address":"Brinkerstr. 49",
    "sg:city":"Sprockh\u00f6vel",
    "sg:postcode":"45549",
    "sg:province":"Nordrhein-Westfalen",
    "wof:name":"Bcs Gmbh",
    "wof:placetype":"venue"
},
  "geometry": {"coordinates":[7.239643,51.365334],"type":"Point"}
}