{
  "type": "Feature",
  "properties": {
    "iso:country":"DE",
    "sg:address":"Kullbeeksweg 9a",
    "sg:city":"Ratingen",
    "sg:phone":"+49 2102/18164",
    "sg:postcode":"40885",
    "sg:province":"Nordrhein-Westfalen",
    "wof:name":"Blumendeco Enk Gmbh",
    "wof:placetype":"venue"
},
  "geometry": {"coordinates":[6.852165,51.337009],"type":"Point"}
}