{
  "type": "Feature",
  "properties": {
    "iso:country":"DE",
    "sg:address":"Elisabethenstr. 2",
    "sg:city":"Ulm",
    "sg:phone":"+49 731/33563",
    "sg:postcode":"89077",
    "sg:province":"Baden-W\u00fcrttemberg",
    "wof:name":"Lina Jourdan",
    "wof:placetype":"venue"
},
  "geometry": {"coordinates":[9.9752311707,48.391040802],"type":"Point"}
}