{
  "type": "Feature",
  "properties": {
    "iso:country":"DE",
    "sg:address":"Finkenstr. 1a",
    "sg:city":"Feldkirchen",
    "sg:postcode":"85622",
    "sg:province":"Bayern",
    "wof:name":"Alpha Verm\u00f6gensverwaltungs- Und Beteiligungsmanagement",
    "wof:placetype":"venue"
},
  "geometry": {"coordinates":[11.7395534515,48.145362854],"type":"Point"}
}