{
  "type": "Feature",
  "properties": {
    "iso:country":"DE",
    "sg:address":"Markt 6",
    "sg:city":"Naumburg",
    "sg:phone":"+49 3445/202250",
    "sg:postcode":"06618",
    "sg:province":"Sachsen-Anhalt",
    "wof:name":"Stadt- Und Kreisbibliothek Louis F\u00fcrnberg",
    "wof:placetype":"venue"
},
  "geometry": {"coordinates":[11.809704,51.152267],"type":"Point"}
}