{
  "type": "Feature",
  "properties": {
    "iso:country":"DE",
    "sg:address":"Bubsheimer Str. 5",
    "sg:city":"Spaichingen",
    "sg:phone":"+49 7424/6268",
    "sg:postcode":"78549",
    "sg:province":"Baden-W\u00fcrttemberg",
    "wof:name":"Reinhold B\u00fchler",
    "wof:placetype":"venue"
},
  "geometry": {"coordinates":[8.743628,48.079437],"type":"Point"}
}