{
  "type": "Feature",
  "properties": {
    "iso:country":"DE",
    "sg:address":"Kasarmen 2",
    "sg:city":"Bad Wurzach",
    "sg:phone":"+49 7568/1256",
    "sg:postcode":"88410",
    "sg:province":"Baden-W\u00fcrttemberg",
    "wof:name":"Hans J\u00e4ger",
    "wof:placetype":"venue"
},
  "geometry": {"coordinates":[9.9850587845,47.9484786987],"type":"Point"}
}