{
  "type": "Feature",
  "properties": {
    "iso:country":"DE",
    "sg:address":"In der Schliem 3",
    "sg:city":"Gro\u00df-Umstadt",
    "sg:phone":"+49 6078/5110",
    "sg:postcode":"64823",
    "sg:province":"Hessen",
    "wof:name":"Kurt R\u00f6delsperger",
    "wof:placetype":"venue"
},
  "geometry": {"coordinates":[8.945348,49.844505],"type":"Point"}
}