{
  "type": "Feature",
  "properties": {
    "iso:country":"DE",
    "sg:address":"Kantstr. 46",
    "sg:city":"Waldesruh",
    "sg:phone":"+49 30/5660404",
    "sg:postcode":"12625",
    "sg:province":"Berlin",
    "wof:name":"B & S Bau- Und Sanierungs Gmbh",
    "wof:placetype":"venue"
},
  "geometry": {"coordinates":[13.6198406219,52.4793052673],"type":"Point"}
}