{
  "type": "Feature",
  "properties": {
    "iso:country":"DE",
    "sg:address":"Am Schnurrenacker 5",
    "sg:city":"Windischeschenbach",
    "sg:postcode":"92670",
    "sg:province":"Bayern",
    "wof:name":"Insieme Vertriebs Gmbh",
    "wof:placetype":"venue"
},
  "geometry": {"coordinates":[12.1506052017,49.8050308228],"type":"Point"}
}