{
  "type": "Feature",
  "properties": {
    "iso:country":"DE",
    "sg:address":"Honings 18",
    "sg:city":"Hetzles",
    "sg:postcode":"91077",
    "sg:province":"Bayern",
    "wof:name":"Rs Spedition Gmbh",
    "wof:placetype":"venue"
},
  "geometry": {"coordinates":[11.1018667221,49.638835907],"type":"Point"}
}