{
  "type": "Feature",
  "properties": {
    "iso:country":"DE",
    "sg:address":"Unterfeld 11",
    "sg:city":"Gerstungen",
    "sg:phone":"+49 36922/2650",
    "sg:postcode":"99834",
    "sg:province":"Th\u00fcringen",
    "wof:name":"Ae Druckgu\u00df Gmbh & Co. Kg",
    "wof:placetype":"venue"
},
  "geometry": {"coordinates":[10.0837287903,50.9719734192],"type":"Point"}
}