{
  "type": "Feature",
  "properties": {
    "iso:country":"DE",
    "sg:address":"Wiesbadener Str. 78",
    "sg:city":"Idstein",
    "sg:phone":"+49 6126/99790",
    "sg:postcode":"65510",
    "sg:province":"Hessen",
    "wof:name":"Technik Shop Idstein Stefan Schmitt",
    "wof:placetype":"venue"
},
  "geometry": {"coordinates":[8.2599592209,50.2174835205],"type":"Point"}
}