{
  "type": "Feature",
  "properties": {
    "iso:country":"DE",
    "sg:address":"Buchenstr. 4",
    "sg:city":"Heimsheim",
    "sg:phone":"+49 7033/3844",
    "sg:postcode":"71296",
    "sg:province":"Baden-W\u00fcrttemberg",
    "wof:name":"M. Kohn Gmbh",
    "wof:placetype":"venue"
},
  "geometry": {"coordinates":[8.871326,48.806938],"type":"Point"}
}