{
  "type": "Feature",
  "properties": {
    "iso:country":"DE",
    "sg:address":"Cautiusstr. 46",
    "sg:city":"Berlin",
    "sg:phone":"+49 30/3355866",
    "sg:postcode":"13587",
    "sg:province":"Berlin",
    "wof:name":"Katja Knelke",
    "wof:placetype":"venue"
},
  "geometry": {"coordinates":[13.207206,52.561943],"type":"Point"}
}