{
  "type": "Feature",
  "properties": {
    "iso:country":"DE",
    "sg:address":"Gutachstr 1a",
    "sg:city":"Sch\u00f6nwald",
    "sg:phone":"+49 7722/86920",
    "sg:postcode":"78141",
    "sg:province":"Baden-W\u00fcrttemberg",
    "wof:name":"Burger Design Pen Ag",
    "wof:placetype":"venue"
},
  "geometry": {"coordinates":[8.210487,48.105602],"type":"Point"}
}