{
  "type": "Feature",
  "properties": {
    "iso:country":"DE",
    "sg:address":"Bad Oberdorfer Str. 18",
    "sg:city":"Hindelang",
    "sg:phone":"+49 8324/2153",
    "sg:postcode":"87541",
    "sg:province":"Bayern",
    "wof:name":"G\u00e4stehaus Theresia K\u00f6gel",
    "wof:placetype":"venue"
},
  "geometry": {"coordinates":[10.3764829636,47.5054244995],"type":"Point"}
}