{
  "type": "Feature",
  "properties": {
    "iso:country":"DE",
    "sg:address":"Walkertshofener Str. 14",
    "sg:city":"Erdweg",
    "sg:phone":"+49 8138/1225",
    "sg:postcode":"85253",
    "sg:province":"Bayern",
    "wof:name":"Heimatmuseum Gro\u00dfberghofen",
    "wof:placetype":"venue"
},
  "geometry": {"coordinates":[11.312416,48.32122],"type":"Point"}
}