{
  "type": "Feature",
  "properties": {
    "iso:country":"DE",
    "sg:address":"Husumer Str. 167",
    "sg:city":"Bielefeld",
    "sg:phone":"+49 521/762223",
    "sg:postcode":"33729",
    "sg:province":"Nordrhein-Westfalen",
    "wof:name":"E.-m. Requardt Praxis F\u00fcr Krankengymnastik",
    "wof:placetype":"venue"
},
  "geometry": {"coordinates":[8.606551,52.080711],"type":"Point"}
}