{
  "type": "Feature",
  "properties": {
    "iso:country":"DE",
    "sg:address":"Sandstr. 16",
    "sg:city":"S\u00fcptitz",
    "sg:postcode":"04860",
    "sg:province":"Sachsen",
    "wof:name":"Popp - Historische Bauteile Gmbh",
    "wof:placetype":"venue"
},
  "geometry": {"coordinates":[12.925394,51.562126],"type":"Point"}
}