{
  "type": "Feature",
  "properties": {
    "iso:country":"DE",
    "sg:address":"Wilhelmstr. 36",
    "sg:city":"Winningen",
    "sg:phone":"+49 2606/763",
    "sg:postcode":"56333",
    "sg:province":"Rheinland-Pfalz",
    "wof:name":"Rudolf Harmant Weinanbau",
    "wof:placetype":"venue"
},
  "geometry": {"coordinates":[7.515226841,50.3133544922],"type":"Point"}
}