{
  "type": "Feature",
  "properties": {
    "iso:country":"DE",
    "sg:address":"Hauptstr. 71",
    "sg:city":"Birkenfeld",
    "sg:phone":"+49 7231/471707",
    "sg:postcode":"75217",
    "sg:province":"Baden-W\u00fcrttemberg",
    "wof:name":"R\u00f6ssle",
    "wof:placetype":"venue"
},
  "geometry": {"coordinates":[8.63539505,48.8698768616],"type":"Point"}
}