{
  "type": "Feature",
  "properties": {
    "iso:country":"DE",
    "sg:address":"Grubenstr. 2",
    "sg:city":"Hagenow",
    "sg:phone":"+49 3883/62000",
    "sg:postcode":"19230",
    "sg:province":"Mecklenburg-Vorpommern",
    "wof:name":"Reiseland Gmbh",
    "wof:placetype":"venue"
},
  "geometry": {"coordinates":[11.1929731369,53.4316749573],"type":"Point"}
}