{
  "type": "Feature",
  "properties": {
    "iso:country":"DE",
    "sg:address":"Ro\u00dftrappenstr. 10/11",
    "sg:city":"Thale",
    "sg:phone":"+49 3947/66818",
    "sg:postcode":"06502",
    "sg:province":"Sachsen-Anhalt",
    "wof:name":"Gr\u00fcne Tanne Inh. Marion Leonhardt",
    "wof:placetype":"venue"
},
  "geometry": {"coordinates":[11.0394878387,51.7547454834],"type":"Point"}
}