{
  "type": "Feature",
  "properties": {
    "iso:country":"DE",
    "sg:address":"Hoferstr. 30",
    "sg:city":"Ludwigsburg",
    "sg:phone":"+49 7141/9590",
    "sg:postcode":"71636",
    "sg:province":"Baden-W\u00fcrttemberg",
    "wof:name":"Neckarwerke Stuttgart Ag",
    "wof:placetype":"venue"
},
  "geometry": {"coordinates":[9.178769,48.893497],"type":"Point"}
}