{
  "type": "Feature",
  "properties": {
    "iso:country":"DE",
    "sg:address":"Vesaliusstr. 10",
    "sg:city":"M\u00fcnchen",
    "sg:phone":"+49 89/8128285",
    "sg:postcode":"80999",
    "sg:province":"Bayern",
    "wof:name":"Kelys Dessousshop E. K.",
    "wof:placetype":"venue"
},
  "geometry": {"coordinates":[11.4652347565,48.1896858215],"type":"Point"}
}