{
  "type": "Feature",
  "properties": {
    "iso:country":"DE",
    "sg:address":"Hauptstr. 87",
    "sg:city":"Warstein",
    "sg:phone":"+49 2902/2644",
    "sg:postcode":"59581",
    "sg:province":"Nordrhein-Westfalen",
    "wof:name":"Ihr Platz Seifen- Und Waschmittel",
    "wof:placetype":"venue"
},
  "geometry": {"coordinates":[8.353795,51.443352],"type":"Point"}
}