{
  "type": "Feature",
  "properties": {
    "iso:country":"DE",
    "sg:address":"Karlsplatz 6",
    "sg:city":"Karlstein",
    "sg:phone":"+49 6188/5689",
    "sg:postcode":"63791",
    "sg:province":"Bayern",
    "wof:name":"G\u00fcnther Hain Bauschlosserei",
    "wof:placetype":"venue"
},
  "geometry": {"coordinates":[9.036203,50.039768],"type":"Point"}
}