{
  "type": "Feature",
  "properties": {
    "iso:country":"DE",
    "sg:address":"Lindenstr. 3",
    "sg:city":"Quappendorf",
    "sg:phone":"+49 33476/50191",
    "sg:postcode":"15320",
    "sg:province":"Brandenburg",
    "wof:name":"Hans-ulrich Dorn",
    "wof:placetype":"venue"
},
  "geometry": {"coordinates":[14.26499,52.6194],"type":"Point"}
}