{
  "type": "Feature",
  "properties": {
    "iso:country":"DE",
    "sg:address":"Colditzstr. 21-23",
    "sg:city":"Berlin",
    "sg:phone":"+49 30/7514036",
    "sg:postcode":"12099",
    "sg:province":"Berlin",
    "wof:name":"Hico-kraftfahrzeug-kontrollger\u00e4te Gmbh",
    "wof:placetype":"venue"
},
  "geometry": {"coordinates":[13.3937311172,52.4577674866],"type":"Point"}
}