{
  "type": "Feature",
  "properties": {
    "iso:country":"DE",
    "sg:address":"Brachwitzer Str. 2",
    "sg:city":"Salzm\u00fcnde/Schiepzig",
    "sg:phone":"+49 345/5511567",
    "sg:postcode":"06198",
    "sg:province":"Sachsen-Anhalt",
    "wof:name":"Brukoma Bauen, Dach Und Wand Gmbh",
    "wof:placetype":"venue"
},
  "geometry": {"coordinates":[11.8319816589,51.565826416],"type":"Point"}
}