{
  "type": "Feature",
  "properties": {
    "iso:country":"DE",
    "sg:address":"Untere Masch Str. 21",
    "sg:city":"G\u00f6ttingen",
    "sg:phone":"+49 551/531034",
    "sg:postcode":"37073",
    "sg:province":"Niedersachsen",
    "wof:name":"Aktionsgruppe Babynahrung Agb E. V.",
    "wof:placetype":"venue"
},
  "geometry": {"coordinates":[9.9305820465,51.5351333618],"type":"Point"}
}