{
  "type": "Feature",
  "properties": {
    "iso:country":"DE",
    "sg:address":"Karl-Marx-Str. 15",
    "sg:city":"Letschin",
    "sg:postcode":"15324",
    "sg:province":"Brandenburg",
    "wof:name":"Elektro-rieke",
    "wof:placetype":"venue"
},
  "geometry": {"coordinates":[14.360295,52.642513],"type":"Point"}
}