{
  "type": "Feature",
  "properties": {
    "iso:country":"DE",
    "sg:address":"Dammstr. 27",
    "sg:city":"Siegburg",
    "sg:phone":"+49 2241/66826",
    "sg:postcode":"53721",
    "sg:province":"Nordrhein-Westfalen",
    "wof:name":"Gk Ingenieur- Gmbh",
    "wof:placetype":"venue"
},
  "geometry": {"coordinates":[7.2243161201,50.794342041],"type":"Point"}
}