{
  "type": "Feature",
  "properties": {
    "iso:country":"DE",
    "sg:address":"Washingtonallee 92",
    "sg:city":"Hamburg",
    "sg:phone":"+49 40/7313238",
    "sg:postcode":"22111",
    "sg:province":"Hamburg",
    "wof:name":"Washington-apotheke Karl Kl\u00fcssendorff",
    "wof:placetype":"venue"
},
  "geometry": {"coordinates":[10.092704,53.546196],"type":"Point"}
}