{
  "type": "Feature",
  "properties": {
    "iso:country":"DE",
    "sg:address":"Bergstr. 5",
    "sg:city":"Erndtebr\u00fcck",
    "sg:phone":"+49 2753/2230",
    "sg:postcode":"57339",
    "sg:province":"Nordrhein-Westfalen",
    "wof:name":"Wilhelm Birkelbach",
    "wof:placetype":"venue"
},
  "geometry": {"coordinates":[8.256076,50.988121],"type":"Point"}
}