{
  "type": "Feature",
  "properties": {
    "iso:country":"DE",
    "sg:address":"Hauptstr. 24",
    "sg:city":"Alsbach-H\u00e4hnlein",
    "sg:phone":"+49 6257/64258",
    "sg:postcode":"64665",
    "sg:province":"Hessen",
    "wof:name":"Friedrich Seeger",
    "wof:placetype":"venue"
},
  "geometry": {"coordinates":[8.6253175735,49.7419013977],"type":"Point"}
}