{
  "type": "Feature",
  "properties": {
    "iso:country":"DE",
    "sg:address":"Rastdorfer Str. 230",
    "sg:city":"Vrees",
    "sg:phone":"+49 5956/280",
    "sg:postcode":"49757",
    "sg:province":"Niedersachsen",
    "wof:name":"Heinz Wilken",
    "wof:placetype":"venue"
},
  "geometry": {"coordinates":[7.74349,52.89592],"type":"Point"}
}