{
  "type": "Feature",
  "properties": {
    "iso:country":"DE",
    "sg:address":"Albisried 2",
    "sg:city":"Lengenwang",
    "sg:phone":"+49 8364/306",
    "sg:postcode":"87663",
    "sg:province":"Bayern",
    "wof:name":"Anton Hitzelberger",
    "wof:placetype":"venue"
},
  "geometry": {"coordinates":[10.584825,47.698154],"type":"Point"}
}