{
  "type": "Feature",
  "properties": {
    "iso:country":"DE",
    "sg:address":"Wiedenbusk 32",
    "sg:city":"Drensteinfurt",
    "sg:phone":"+49 2387/92090",
    "sg:postcode":"48317",
    "sg:province":"Nordrhein-Westfalen",
    "wof:name":"Alkoplan Fassadengestaltungs- Und Konstruktions-",
    "wof:placetype":"venue"
},
  "geometry": {"coordinates":[7.7889318466,51.7642593384],"type":"Point"}
}