{
  "type": "Feature",
  "properties": {
    "iso:country":"DE",
    "sg:address":"M\u00fclheimer Str. 206",
    "sg:city":"Bergisch Gladbach",
    "sg:phone":"+49 2202/51979",
    "sg:postcode":"51469",
    "sg:province":"Nordrhein-Westfalen",
    "wof:name":"Angelika Nu\u00dfbaumer",
    "wof:placetype":"venue"
},
  "geometry": {"coordinates":[7.112923,50.984062],"type":"Point"}
}