{
  "type": "Feature",
  "properties": {
    "iso:country":"DE",
    "sg:address":"Chausseestr. 28e",
    "sg:city":"Krielow",
    "sg:phone":"+49 33207/71689",
    "sg:postcode":"14550",
    "sg:province":"Brandenburg",
    "wof:name":"Frank Lorenz",
    "wof:placetype":"venue"
},
  "geometry": {"coordinates":[12.790787,52.416916],"type":"Point"}
}