{
  "type": "Feature",
  "properties": {
    "iso:country":"DE",
    "sg:address":"Deichstr. 17",
    "sg:city":"St.-Peter-Ording",
    "sg:phone":"+49 4863/9100",
    "sg:postcode":"25826",
    "sg:province":"Schleswig-Holstein",
    "wof:name":"Burghardt\u00b4s Individual Touristik & Pauschalreise Agentur",
    "wof:placetype":"venue"
},
  "geometry": {"coordinates":[8.6307315826,54.3038520813],"type":"Point"}
}