{
  "type": "Feature",
  "properties": {
    "iso:country":"DE",
    "sg:address":"S\u00e4gem\u00fchlenstr. 49",
    "sg:city":"Leer",
    "sg:phone":"+49 491/9290280",
    "sg:postcode":"26789",
    "sg:province":"Niedersachsen",
    "wof:name":"Regalit Gmbh",
    "wof:placetype":"venue"
},
  "geometry": {"coordinates":[7.4608511925,53.2215919495],"type":"Point"}
}