{
  "type": "Feature",
  "properties": {
    "iso:country":"DE",
    "sg:address":"Am Markt 5",
    "sg:city":"B\u00fccken",
    "sg:phone":"+49 4251/3481",
    "sg:postcode":"27333",
    "sg:province":"Niedersachsen",
    "wof:name":"Ursula Freiwald",
    "wof:placetype":"venue"
},
  "geometry": {"coordinates":[9.130792,52.779228],"type":"Point"}
}