{
  "type": "Feature",
  "properties": {
    "iso:country":"DE",
    "sg:address":"Bahnhofstr. 10",
    "sg:city":"H\u00f6chst\u00e4dt",
    "sg:phone":"+49 9074/440",
    "sg:postcode":"89420",
    "sg:province":"Bayern",
    "wof:name":"Stadtarchiv",
    "wof:placetype":"venue"
},
  "geometry": {"coordinates":[10.56714,48.616943],"type":"Point"}
}