{
  "type": "Feature",
  "properties": {
    "iso:country":"DE",
    "sg:address":"Tappeweg 1",
    "sg:city":"Soest",
    "sg:phone":"+49 2921/80899",
    "sg:postcode":"59494",
    "sg:province":"Nordrhein-Westfalen",
    "wof:name":"Dr. H. J. Baumgarten Tierarzt",
    "wof:placetype":"venue"
},
  "geometry": {"coordinates":[8.1073541641,51.580329895],"type":"Point"}
}