{
  "type": "Feature",
  "properties": {
    "iso:country":"DE",
    "sg:address":"Hauptstr. 5",
    "sg:city":"Weickelsdorf",
    "sg:postcode":"06722",
    "sg:province":"Sachsen-Anhalt",
    "wof:name":"R & L Spezialbau Gmbh",
    "wof:placetype":"venue"
},
  "geometry": {"coordinates":[11.9597702026,51.0495567322],"type":"Point"}
}