{
  "type": "Feature",
  "properties": {
    "iso:country":"DE",
    "sg:address":"Rennweg 25",
    "sg:city":"Andernach",
    "sg:phone":"+49 2632/92680",
    "sg:postcode":"56626",
    "sg:province":"Rheinland-Pfalz",
    "wof:name":"Birgit Remy Steuerberater",
    "wof:placetype":"venue"
},
  "geometry": {"coordinates":[7.3950247765,50.4260673523],"type":"Point"}
}