{
  "type": "Feature",
  "properties": {
    "iso:country":"DE",
    "sg:address":"Robert-Perthel-Str. 74-78",
    "sg:city":"K\u00f6ln",
    "sg:phone":"+49 221/5992064",
    "sg:postcode":"50739",
    "sg:province":"Nordrhein-Westfalen",
    "wof:name":"Wilhelm Pfeiffer Verwaltungs- Und Immobiliengesellschaft Mbh",
    "wof:placetype":"venue"
},
  "geometry": {"coordinates":[6.9088258743,50.988899231],"type":"Point"}
}