{
  "type": "Feature",
  "properties": {
    "iso:country":"DE",
    "sg:address":"Dieselstr. 6a",
    "sg:city":"Kamen",
    "sg:postcode":"59174",
    "sg:province":"Nordrhein-Westfalen",
    "wof:name":"Agentur Sch\u00f6nfeld Gmbh",
    "wof:placetype":"venue"
},
  "geometry": {"coordinates":[7.7093057632,51.5710525513],"type":"Point"}
}