{
  "type": "Feature",
  "properties": {
    "iso:country":"DE",
    "sg:address":"Industriestr. 55",
    "sg:city":"Stolberg",
    "sg:phone":"+49 2402/978197",
    "sg:postcode":"52224",
    "sg:province":"Nordrhein-Westfalen",
    "wof:name":"Rosenbaum Omnibusreisen Gmbh & Co. Kg",
    "wof:placetype":"venue"
},
  "geometry": {"coordinates":[6.276256,50.767452],"type":"Point"}
}