{
  "type": "Feature",
  "properties": {
    "iso:country":"DE",
    "sg:address":"Nu\u00dfbaumgasse 1",
    "sg:city":"Landau",
    "sg:phone":"+49 6341/82757",
    "sg:postcode":"76829",
    "sg:province":"Rheinland-Pfalz",
    "wof:name":"Helmut Hiestand",
    "wof:placetype":"venue"
},
  "geometry": {"coordinates":[8.1109733582,49.1966018677],"type":"Point"}
}