{
  "type": "Feature",
  "properties": {
    "iso:country":"DE",
    "sg:address":"Am Zingel 8 b",
    "sg:city":"Brandenburg",
    "sg:phone":"+49 3381/228283",
    "sg:postcode":"14776",
    "sg:province":"Brandenburg",
    "wof:name":"B\u00e4rbels Inn",
    "wof:placetype":"venue"
},
  "geometry": {"coordinates":[12.5878410339,52.3895874023],"type":"Point"}
}