{
  "type": "Feature",
  "properties": {
    "iso:country":"DE",
    "sg:address":"Hans-Sachs-Str. 4",
    "sg:city":"Augsburg",
    "sg:phone":"+49 821/415717",
    "sg:postcode":"86154",
    "sg:province":"Bayern",
    "wof:name":"Albert Herzgsell",
    "wof:placetype":"venue"
},
  "geometry": {"coordinates":[10.874162,48.384941],"type":"Point"}
}