{
  "type": "Feature",
  "properties": {
    "iso:country":"DE",
    "sg:address":"Aachener Str. 113",
    "sg:city":"D\u00fcsseldorf",
    "sg:phone":"+49 211/334805",
    "sg:postcode":"40223",
    "sg:province":"Nordrhein-Westfalen",
    "wof:name":"Dagmar Kr\u00f6lls Heilpraktikerin",
    "wof:placetype":"venue"
},
  "geometry": {"coordinates":[6.7706990242,51.2013893127],"type":"Point"}
}