{
  "type": "Feature",
  "properties": {
    "iso:country":"DE",
    "sg:address":"Kronenstr. 12-14",
    "sg:city":"Pirmasens",
    "sg:phone":"+49 6331/75125",
    "sg:postcode":"66955",
    "sg:province":"Rheinland-Pfalz",
    "wof:name":"Dr. Med. Peter Kirchner",
    "wof:placetype":"venue"
},
  "geometry": {"coordinates":[7.6057782173,49.1929016113],"type":"Point"}
}