{
  "type": "Feature",
  "properties": {
    "iso:country":"DE",
    "sg:address":"Korfiz-Holm-Str. 25",
    "sg:city":"M\u00fcnchen",
    "sg:phone":"+49 89/89162198",
    "sg:postcode":"81245",
    "sg:province":"Bayern",
    "wof:name":"B & S Fliesenfachbetrieb Gmbh",
    "wof:placetype":"venue"
},
  "geometry": {"coordinates":[11.4445905685,48.1630249023],"type":"Point"}
}