{
  "type": "Feature",
  "properties": {
    "iso:country":"DE",
    "sg:address":"Graf-von-Werdenberg-Str. 20",
    "sg:city":"Aislingen",
    "sg:phone":"+49 9075/268",
    "sg:postcode":"89344",
    "sg:province":"Bayern",
    "wof:name":"Gastst\u00e4tte Xaver Bunk",
    "wof:placetype":"venue"
},
  "geometry": {"coordinates":[10.4564380646,48.5063591003],"type":"Point"}
}