{
  "type": "Feature",
  "properties": {
    "iso:country":"DE",
    "sg:address":"Transitstr. 3",
    "sg:city":"Gelbensande",
    "sg:phone":"+49 38201/247",
    "sg:postcode":"18182",
    "sg:province":"Mecklenburg-Vorpommern",
    "wof:name":"Landkrug Immenhof",
    "wof:placetype":"venue"
},
  "geometry": {"coordinates":[12.3073940277,54.2001037598],"type":"Point"}
}