{
  "type": "Feature",
  "properties": {
    "iso:country":"DE",
    "sg:address":"An der Kirche 2",
    "sg:city":"Hannover",
    "sg:phone":"+49 511/468408",
    "sg:postcode":"30457",
    "sg:province":"Niedersachsen",
    "wof:name":"Becker Gmbh",
    "wof:placetype":"venue"
},
  "geometry": {"coordinates":[9.691242218,52.3291091919],"type":"Point"}
}