{
  "type": "Feature",
  "properties": {
    "iso:country":"DE",
    "sg:address":"Griesstr. 7",
    "sg:city":"Garmisch-Partenkirchen",
    "sg:phone":"+49 8821/2061",
    "sg:postcode":"82467",
    "sg:province":"Bayern",
    "wof:name":"H. Hibler Lebensmittel",
    "wof:placetype":"venue"
},
  "geometry": {"coordinates":[10.9431324005,47.477596283],"type":"Point"}
}