{
  "type": "Feature",
  "properties": {
    "iso:country":"DE",
    "sg:address":"Martin-Luther-Str. 29",
    "sg:city":"Mainz",
    "sg:phone":"+49 6131/55993",
    "sg:postcode":"55131",
    "sg:province":"Rheinland-Pfalz",
    "wof:name":"Karl Heinz Hofmann Achitekt Und Ingenieur",
    "wof:placetype":"venue"
},
  "geometry": {"coordinates":[8.277859,49.983109],"type":"Point"}
}