{
  "type": "Feature",
  "properties": {
    "iso:country":"DE",
    "sg:address":"Ostertorsteinweg 105",
    "sg:city":"Bremen",
    "sg:phone":"+49 421/700914",
    "sg:postcode":"28203",
    "sg:province":"Bremen",
    "wof:name":"Settje Kg Cinema Ostertor",
    "wof:placetype":"venue"
},
  "geometry": {"coordinates":[8.8229160309,53.0727882385],"type":"Point"}
}