{
  "type": "Feature",
  "properties": {
    "iso:country":"DE",
    "sg:address":"W\u00fcrzburgerstr. 59",
    "sg:city":"K\u00f6ln",
    "sg:phone":"+49 221/878628",
    "sg:postcode":"51103",
    "sg:province":"Nordrhein-Westfalen",
    "wof:name":"Rbv Touristik",
    "wof:placetype":"venue"
},
  "geometry": {"coordinates":[7.00997,50.939175],"type":"Point"}
}