{
  "type": "Feature",
  "properties": {
    "iso:country":"DE",
    "sg:address":"M\u00fchlenstr. 39",
    "sg:city":"Emden",
    "sg:phone":"+49 4921/25446",
    "sg:postcode":"26725",
    "sg:province":"Niedersachsen",
    "wof:name":"Werner Mietz Antiquit\u00e4ten",
    "wof:placetype":"venue"
},
  "geometry": {"coordinates":[7.21259,53.365681],"type":"Point"}
}