{
  "type": "Feature",
  "properties": {
    "iso:country":"DE",
    "sg:address":"Werner-Bockelmann-Str. 78",
    "sg:city":"Frankfurt",
    "sg:phone":"+49 69/399140",
    "sg:postcode":"65934",
    "sg:province":"Hessen",
    "wof:name":"Dr. Joachim Hartle Rechtsanwalt",
    "wof:placetype":"venue"
},
  "geometry": {"coordinates":[8.5809364319,50.1033782959],"type":"Point"}
}