{
  "type": "Feature",
  "properties": {
    "iso:country":"DE",
    "sg:address":"Hindenburgstr. 7",
    "sg:city":"Donauw\u00f6rth",
    "sg:phone":"+49 906/21019",
    "sg:postcode":"86609",
    "sg:province":"Bayern",
    "wof:name":"Klaus Gr\u00e4f Rechtsanwalt",
    "wof:placetype":"venue"
},
  "geometry": {"coordinates":[10.7790327072,48.7170066833],"type":"Point"}
}