{
  "type": "Feature",
  "properties": {
    "iso:country":"DE",
    "sg:address":"Friedrich-Ebert-Str. 73",
    "sg:city":"Kassel",
    "sg:phone":"+49 561/13008",
    "sg:postcode":"34119",
    "sg:province":"Hessen",
    "wof:name":"Bernd Nelle",
    "wof:placetype":"venue"
},
  "geometry": {"coordinates":[9.479171,51.315197],"type":"Point"}
}