{
  "type": "Feature",
  "properties": {
    "iso:country":"DE",
    "sg:address":"Daimlerstr. 18",
    "sg:city":"Wernberg-K\u00f6blitz",
    "sg:postcode":"92533",
    "sg:province":"Bayern",
    "wof:name":"Tennisversand Sport- Achim E. K.",
    "wof:placetype":"venue"
},
  "geometry": {"coordinates":[12.145082,49.527073],"type":"Point"}
}