{
  "type": "Feature",
  "properties": {
    "iso:country":"DE",
    "sg:address":"S\u00fclzburgstr. 160",
    "sg:city":"K\u00f6ln",
    "sg:phone":"+49 221/445993",
    "sg:postcode":"50937",
    "sg:province":"Nordrhein-Westfalen",
    "wof:name":"Welz",
    "wof:placetype":"venue"
},
  "geometry": {"coordinates":[6.920709,50.919662],"type":"Point"}
}