{
  "type": "Feature",
  "properties": {
    "iso:country":"DE",
    "sg:address":"Ausr\u00fcstung 1-20",
    "sg:city":"Wangen",
    "sg:postcode":"88239",
    "sg:province":"Baden-W\u00fcrttemberg",
    "wof:name":"Melchior Textil Gmbh",
    "wof:placetype":"venue"
},
  "geometry": {"coordinates":[9.8458166122,47.6821250916],"type":"Point"}
}