{
  "type": "Feature",
  "properties": {
    "iso:country":"DE",
    "sg:address":"Ortsstr. 140",
    "sg:city":"B\u00f6hlen",
    "sg:phone":"+49 36781/9938",
    "sg:postcode":"98701",
    "sg:province":"Th\u00fcringen",
    "wof:name":"Hotel Zur L\u00e4rche",
    "wof:placetype":"venue"
},
  "geometry": {"coordinates":[11.0369138718,50.5865211487],"type":"Point"}
}