{
  "type": "Feature",
  "properties": {
    "iso:country":"DE",
    "sg:address":"Werler Str. 381",
    "sg:city":"Hamm",
    "sg:phone":"+49 2385/1599",
    "sg:postcode":"59069",
    "sg:province":"Nordrhein-Westfalen",
    "wof:name":"Deutsche Shell Ag",
    "wof:placetype":"venue"
},
  "geometry": {"coordinates":[7.8441648483,51.6431770325],"type":"Point"}
}