{
  "type": "Feature",
  "properties": {
    "iso:country":"DE",
    "sg:address":"Homburger Str. 8",
    "sg:city":"Karben",
    "sg:phone":"+49 6039/2421",
    "sg:postcode":"61184",
    "sg:province":"Hessen",
    "wof:name":"Peter-geibel-apotheke",
    "wof:placetype":"venue"
},
  "geometry": {"coordinates":[8.773302,50.227757],"type":"Point"}
}