{
  "type": "Feature",
  "properties": {
    "iso:country":"DE",
    "sg:address":"Berliner Str. 15-16",
    "sg:city":"Cottbus",
    "sg:postcode":"03046",
    "sg:province":"Brandenburg",
    "wof:name":"Dieter Gerlich",
    "wof:placetype":"venue"
},
  "geometry": {"coordinates":[14.3265724182,51.7612075806],"type":"Point"}
}