{
  "type": "Feature",
  "properties": {
    "iso:country":"DE",
    "sg:address":"Bahnhofstr. 22a",
    "sg:city":"Mahlow",
    "sg:phone":"+49 3379/39913",
    "sg:postcode":"15831",
    "sg:province":"Brandenburg",
    "wof:name":"Men\u00fc-service Uwe Heinrich Gmbh",
    "wof:placetype":"venue"
},
  "geometry": {"coordinates":[13.4139003754,52.3608703613],"type":"Point"}
}