{
  "type": "Feature",
  "properties": {
    "iso:country":"DE",
    "sg:address":"Elsa-Brandstr\u00f6m-Str. 15-17",
    "sg:city":"Hemer",
    "sg:phone":"+49 2372/12110",
    "sg:postcode":"58675",
    "sg:province":"Nordrhein-Westfalen",
    "wof:name":"C. D. H\u00fccking Sicht- Und Sonnenschutz",
    "wof:placetype":"venue"
},
  "geometry": {"coordinates":[7.768298,51.383453],"type":"Point"}
}