{
  "type": "Feature",
  "properties": {
    "iso:country":"DE",
    "sg:address":"Graf-Adolf-Str. 63",
    "sg:city":"D\u00fcsseldorf",
    "sg:phone":"+49 211/38980",
    "sg:postcode":"40210",
    "sg:province":"Nordrhein-Westfalen",
    "wof:name":"W\u00fcrttembergische Versicherung Ag",
    "wof:placetype":"venue"
},
  "geometry": {"coordinates":[6.7864117622,51.2188911438],"type":"Point"}
}