{
  "type": "Feature",
  "properties": {
    "iso:country":"DE",
    "sg:address":"R\u00f6merstr. 10",
    "sg:city":"Xanten",
    "sg:phone":"+49 2801/1477",
    "sg:postcode":"46509",
    "sg:province":"Nordrhein-Westfalen",
    "wof:name":"Kath. Pfarramt St. Viktor",
    "wof:placetype":"venue"
},
  "geometry": {"coordinates":[6.4734768867,51.6383857727],"type":"Point"}
}