{
  "type": "Feature",
  "properties": {
    "iso:country":"DE",
    "sg:address":"Dorfstr. 15",
    "sg:city":"Kiel",
    "sg:phone":"+49 431/785165",
    "sg:postcode":"24146",
    "sg:province":"Schleswig-Holstein",
    "wof:name":"Heinrich Nommensen Eisenwaren",
    "wof:placetype":"venue"
},
  "geometry": {"coordinates":[10.1742639542,54.2950744629],"type":"Point"}
}