{
  "type": "Feature",
  "properties": {
    "iso:country":"DE",
    "sg:address":"Berner Stra\u00dfe",
    "sg:city":"Frankfurt am Main",
    "sg:postcode":"60437",
    "sg:province":"Hessen",
    "wof:name":"Supergate.de B\u00fccher",
    "wof:placetype":"venue"
},
  "geometry": {"coordinates":[8.6635828018,50.194103241],"type":"Point"}
}