{
  "type": "Feature",
  "properties": {
    "iso:country":"DE",
    "sg:address":"Wintgensstr. 118",
    "sg:city":"Duisburg",
    "sg:phone":"+49 203/331750",
    "sg:postcode":"47058",
    "sg:province":"Nordrhein-Westfalen",
    "wof:name":"Klaus Holtschneider Gmbh",
    "wof:placetype":"venue"
},
  "geometry": {"coordinates":[6.792647,51.442581],"type":"Point"}
}