{
  "type": "Feature",
  "properties": {
    "iso:country":"DE",
    "sg:address":"Lorenzstr 6",
    "sg:city":"Stutensee",
    "sg:phone":"+49 7244/7470",
    "sg:postcode":"76297",
    "sg:province":"Baden-W\u00fcrttemberg",
    "wof:name":"Iwka Pacunion Gmbh",
    "wof:placetype":"venue"
},
  "geometry": {"coordinates":[8.458106,49.075417],"type":"Point"}
}