{
  "type": "Feature",
  "properties": {
    "iso:country":"DE",
    "sg:address":"Kirchplatz 6 a",
    "sg:city":"Frankfurt",
    "sg:phone":"+49 69/7074232",
    "sg:postcode":"60487",
    "sg:province":"Hessen",
    "wof:name":"Souk",
    "wof:placetype":"venue"
},
  "geometry": {"coordinates":[8.6376399994,50.125289917],"type":"Point"}
}