{
  "type": "Feature",
  "properties": {
    "iso:country":"DE",
    "sg:address":"Unterm Warenberg 2",
    "sg:city":"Brilon",
    "sg:phone":"+49 2961/3036",
    "sg:postcode":"59929",
    "sg:province":"Nordrhein-Westfalen",
    "wof:name":"Briloner Vertriebs Gmbh & Co. Kg",
    "wof:placetype":"venue"
},
  "geometry": {"coordinates":[8.5098743439,51.3860206604],"type":"Point"}
}