{
  "type": "Feature",
  "properties": {
    "iso:country":"DE",
    "sg:address":"Am Gallborn 17",
    "sg:city":"Worms",
    "sg:phone":"+49 6241/90180",
    "sg:postcode":"67547",
    "sg:province":"Rheinland-Pfalz",
    "wof:name":"Hammer Fachm\u00e4rkte F\u00fcr Heim- Ausstattung Gmbh & Co.",
    "wof:placetype":"venue"
},
  "geometry": {"coordinates":[8.3561553955,49.6566009521],"type":"Point"}
}