{
  "type": "Feature",
  "properties": {
    "iso:country":"DE",
    "sg:address":"Hauptstr. 60",
    "sg:city":"Sulzburg",
    "sg:phone":"+49 7634/8934",
    "sg:postcode":"79295",
    "sg:province":"Baden-W\u00fcrttemberg",
    "wof:name":"Kranken- Und Altenpflegeverein Gertrude Rumpp",
    "wof:placetype":"venue"
},
  "geometry": {"coordinates":[7.7071609497,47.8411140442],"type":"Point"}
}