{
  "type": "Feature",
  "properties": {
    "iso:country":"DE",
    "sg:address":"Am Hungerbach 1",
    "sg:city":"Mindelheim",
    "sg:phone":"+49 8261/9675",
    "sg:postcode":"87719",
    "sg:province":"Bayern",
    "wof:name":"Steiner",
    "wof:placetype":"venue"
},
  "geometry": {"coordinates":[10.4951114655,48.0397872925],"type":"Point"}
}