{
  "type": "Feature",
  "properties": {
    "iso:country":"DE",
    "sg:address":"Am Galgenberg 1",
    "sg:city":"Annaberg-Buchholz",
    "sg:phone":"+49 3733/65483",
    "sg:postcode":"09456",
    "sg:province":"Sachsen",
    "wof:name":"Gunter Sch\u00f6niger",
    "wof:placetype":"venue"
},
  "geometry": {"coordinates":[12.988207,50.564739],"type":"Point"}
}