{
  "type": "Feature",
  "properties": {
    "iso:country":"DE",
    "sg:address":"Bahnhofstr. 171a",
    "sg:city":"Maintal",
    "sg:phone":"+49 6181/431302",
    "sg:postcode":"63477",
    "sg:province":"Hessen",
    "wof:name":"Ursula Ullmann Praxis F\u00fcr Krankengymnastik",
    "wof:placetype":"venue"
},
  "geometry": {"coordinates":[8.83622,50.146961],"type":"Point"}
}