{
  "type": "Feature",
  "properties": {
    "iso:country":"DE",
    "sg:address":"Tulpenweg 53",
    "sg:city":"Ro\u00dflau",
    "sg:phone":"+49 34901/93138",
    "sg:postcode":"06862",
    "sg:province":"Sachsen-Anhalt",
    "wof:name":"M\u00f6bius",
    "wof:placetype":"venue"
},
  "geometry": {"coordinates":[12.2536811829,51.9069976807],"type":"Point"}
}