{
  "type": "Feature",
  "properties": {
    "iso:country":"DE",
    "sg:address":"Siebertstr",
    "sg:city":"Eppelborn",
    "sg:phone":"+49 6806/9800",
    "sg:postcode":"66571",
    "sg:province":"Saarland",
    "wof:name":"Siebert Industrieelektronik Gmbh",
    "wof:placetype":"venue"
},
  "geometry": {"coordinates":[6.991775,49.372723],"type":"Point"}
}