{
  "type": "Feature",
  "properties": {
    "iso:country":"DE",
    "sg:address":"Neuenzinnen 1",
    "sg:city":"Burg",
    "sg:phone":"+49 3921/2403",
    "sg:postcode":"39288",
    "sg:province":"Sachsen-Anhalt",
    "wof:name":"August Mittendorf",
    "wof:placetype":"venue"
},
  "geometry": {"coordinates":[11.867595,52.274929],"type":"Point"}
}