{
  "type": "Feature",
  "properties": {
    "iso:country":"DE",
    "sg:address":"Tieenbrink 2",
    "sg:city":"Attendorn",
    "sg:phone":"+49 2722/70246",
    "sg:postcode":"57439",
    "sg:province":"Nordrhein-Westfalen",
    "wof:name":"Werner Happ",
    "wof:placetype":"venue"
},
  "geometry": {"coordinates":[7.86547,51.110615],"type":"Point"}
}