{
  "type": "Feature",
  "properties": {
    "iso:country":"DE",
    "sg:address":"Obringhauser Str. 4",
    "sg:city":"Schmallenberg",
    "sg:phone":"+49 2972/1672",
    "sg:postcode":"57392",
    "sg:province":"Nordrhein-Westfalen",
    "wof:name":"St. Valentin-apotheke",
    "wof:placetype":"venue"
},
  "geometry": {"coordinates":[8.284418,51.153671],"type":"Point"}
}