{
  "type": "Feature",
  "properties": {
    "iso:country":"DE",
    "sg:address":"Hauptstr. 8",
    "sg:city":"Eschbach",
    "sg:phone":"+49 4976/342310",
    "sg:postcode":"79427",
    "sg:province":"Baden-W\u00fcrttemberg",
    "wof:name":"Sparkasse Staufen",
    "wof:placetype":"venue"
},
  "geometry": {"coordinates":[7.652901,47.890797],"type":"Point"}
}