{
  "type": "Feature",
  "properties": {
    "iso:country":"DE",
    "sg:address":"Hauptstr. 217",
    "sg:city":"Heiligenhaus",
    "sg:phone":"+49 2056/20760",
    "sg:postcode":"42579",
    "sg:province":"Nordrhein-Westfalen",
    "wof:name":"Ute Schreiner",
    "wof:placetype":"venue"
},
  "geometry": {"coordinates":[6.965894,51.325375],"type":"Point"}
}