{
  "type": "Feature",
  "properties": {
    "iso:country":"DE",
    "sg:address":"Zum Ordenswald 22",
    "sg:city":"Neustadt",
    "sg:phone":"+49 6321/69381",
    "sg:postcode":"67435",
    "sg:province":"Rheinland-Pfalz",
    "wof:name":"Artemis",
    "wof:placetype":"venue"
},
  "geometry": {"coordinates":[8.1732416153,49.3677062988],"type":"Point"}
}