{
  "type": "Feature",
  "properties": {
    "iso:country":"DE",
    "sg:address":"Niederfeldstr. 18",
    "sg:city":"B\u00fcnde",
    "sg:phone":"+49 5223/60189",
    "sg:postcode":"32257",
    "sg:province":"Nordrhein-Westfalen",
    "wof:name":"Werner Darm\u00f6ller",
    "wof:placetype":"venue"
},
  "geometry": {"coordinates":[8.551009,52.201908],"type":"Point"}
}