{
  "type": "Feature",
  "properties": {
    "iso:country":"DE",
    "sg:address":"Hansastr. 1",
    "sg:city":"Bottrop",
    "sg:phone":"+49 2041/22894",
    "sg:postcode":"46236",
    "sg:province":"Nordrhein-Westfalen",
    "wof:name":"Christa Sandforth Vorm Robert Broch",
    "wof:placetype":"venue"
},
  "geometry": {"coordinates":[6.9252967834,51.5212173462],"type":"Point"}
}