{
  "type": "Feature",
  "properties": {
    "iso:country":"DE",
    "sg:address":"Carl-Zuckmayer-Str. 20",
    "sg:city":"Erkrath",
    "sg:postcode":"40699",
    "sg:province":"Nordrhein-Westfalen",
    "wof:name":"Andab Gesellschaft F\u00fcr Angewandte Datenverarbeitung",
    "wof:placetype":"venue"
},
  "geometry": {"coordinates":[6.920952,51.204819],"type":"Point"}
}