{
  "type": "Feature",
  "properties": {
    "iso:country":"DE",
    "sg:address":"krillin strasse 6",
    "sg:city":"satan city",
    "sg:phone":"+49 4587/46409697",
    "sg:postcode":"88752",
    "wof:name":"Dragon Ball The Legend",
    "wof:placetype":"venue"
},
  "geometry": {"coordinates":[-98.28103637700001,26.0719509125],"type":"Point"}
}