{
  "type": "Feature",
  "properties": {
    "iso:country":"DE",
    "sg:address":"Bamberger Str. 4",
    "sg:city":"Burgebrach",
    "sg:phone":"+49 9546/1787",
    "sg:postcode":"96138",
    "sg:province":"Bayern",
    "wof:name":"Giess",
    "wof:placetype":"venue"
},
  "geometry": {"coordinates":[10.744235,49.826691],"type":"Point"}
}