{
  "type": "Feature",
  "properties": {
    "iso:country":"DE",
    "sg:address":"M\u00f6llner Str. 51a",
    "sg:city":"Hagenow",
    "sg:phone":"+49 3883/61700",
    "sg:postcode":"19230",
    "sg:province":"Mecklenburg-Vorpommern",
    "wof:name":"Amtsgericht Hagenow",
    "wof:placetype":"venue"
},
  "geometry": {"coordinates":[11.1964530945,53.4322090149],"type":"Point"}
}