{
  "type": "Feature",
  "properties": {
    "iso:country":"DE",
    "sg:address":"Dunlopstr. 18",
    "sg:city":"Bielefeld",
    "sg:phone":"+49 5205/967980",
    "sg:postcode":"33689",
    "sg:province":"Nordrhein-Westfalen",
    "wof:name":"Esch-fahrzeugtechnik Gmbh",
    "wof:placetype":"venue"
},
  "geometry": {"coordinates":[8.5599184036,51.9409713745],"type":"Point"}
}