{
  "type": "Feature",
  "properties": {
    "iso:country":"DE",
    "sg:address":"Deroystr. 3 -5",
    "sg:city":"M\u00fcnchen",
    "sg:phone":"+49 89/4904110",
    "sg:postcode":"80335",
    "sg:province":"Bayern",
    "wof:name":"Kms. Team Werbeagentur Gmbh",
    "wof:placetype":"venue"
},
  "geometry": {"coordinates":[11.5459594727,48.1449966431],"type":"Point"}
}