{
  "type": "Feature",
  "properties": {
    "iso:country":"DE",
    "sg:address":"Kettwiger Str. 27",
    "sg:city":"Essen",
    "sg:postcode":"45127",
    "sg:province":"Nordrhein-Westfalen",
    "wof:name":"Gesamtverband D.dt.brenn- Stoff-u. Mineral\u00f6lhandels",
    "wof:placetype":"venue"
},
  "geometry": {"coordinates":[7.0127010345,51.4547653198],"type":"Point"}
}