{
  "type": "Feature",
  "properties": {
    "iso:country":"DE",
    "sg:address":"Bruno-Frank-Str. 34",
    "sg:city":"Stuttgart",
    "sg:phone":"+49 711/441380",
    "sg:postcode":"70619",
    "sg:province":"Baden-W\u00fcrttemberg",
    "wof:name":"Hanspeter Knoll",
    "wof:placetype":"venue"
},
  "geometry": {"coordinates":[9.2314567566,48.7472267151],"type":"Point"}
}