{
  "type": "Feature",
  "properties": {
    "iso:country":"DE",
    "sg:address":"Boysenstr. 3",
    "sg:city":"Westerland",
    "sg:phone":"+49 4651/24071",
    "sg:postcode":"25980",
    "sg:province":"Schleswig-Holstein",
    "wof:name":"Sebastian Strohmeier Rechtsanwalt Und Notar",
    "wof:placetype":"venue"
},
  "geometry": {"coordinates":[8.3046569824,54.9074401855],"type":"Point"}
}