{
  "type": "Feature",
  "properties": {
    "iso:country":"DE",
    "sg:address":"Krokusstra\u00dfe 7a/9",
    "sg:city":"Berlin",
    "sg:phone":"+49 30",
    "sg:postcode":"12357",
    "sg:province":"Berlin",
    "wof:name":"Georg Ebell Dachdeckerei Gmgh & Co. Kg",
    "wof:placetype":"venue"
},
  "geometry": {"coordinates":[13.4944810867,52.4298019409],"type":"Point"}
}