{
  "type": "Feature",
  "properties": {
    "iso:country":"DE",
    "sg:address":"Sonnenstr. 24",
    "sg:city":"Dortmund",
    "sg:phone":"+49 231/136100",
    "sg:postcode":"44139",
    "sg:province":"Nordrhein-Westfalen",
    "wof:name":"Erika Nau-harmel",
    "wof:placetype":"venue"
},
  "geometry": {"coordinates":[7.464489,51.506821],"type":"Point"}
}