{
  "type": "Feature",
  "properties": {
    "iso:country":"DE",
    "sg:address":"Michaelisstr. 8",
    "sg:city":"Eberswalde",
    "sg:phone":"+49 3334/23186",
    "sg:postcode":"16225",
    "sg:province":"Brandenburg",
    "wof:name":"Praxis Dr. Prass",
    "wof:placetype":"venue"
},
  "geometry": {"coordinates":[13.8175697327,52.8335418701],"type":"Point"}
}