{
  "type": "Feature",
  "properties": {
    "iso:country":"DE",
    "sg:address":"Joseph-K\u00f6nig-Str. 33",
    "sg:city":"M\u00fcnster",
    "sg:phone":"+49 251/30271",
    "sg:postcode":"48147",
    "sg:province":"Nordrhein-Westfalen",
    "wof:name":"Franz Heinrich Bauer- Beteiligungsges. Mbh",
    "wof:placetype":"venue"
},
  "geometry": {"coordinates":[7.63501,51.984066],"type":"Point"}
}