{
  "type": "Feature",
  "properties": {
    "iso:country":"DE",
    "sg:address":"Amselweg 27",
    "sg:city":"Stolberg",
    "sg:phone":"+49 2402/29109",
    "sg:postcode":"52223",
    "sg:province":"Nordrhein-Westfalen",
    "wof:name":"Restaurant Liester Keller",
    "wof:placetype":"venue"
},
  "geometry": {"coordinates":[6.2181692123,50.7639312744],"type":"Point"}
}