{
  "type": "Feature",
  "properties": {
    "iso:country":"DE",
    "sg:address":"Triebenbachstr. 17",
    "sg:city":"Ramsau",
    "sg:phone":"+49 8657/1247",
    "sg:postcode":"83486",
    "sg:province":"Bayern",
    "wof:name":"Johanna Stutz",
    "wof:placetype":"venue"
},
  "geometry": {"coordinates":[12.8687467575,47.6136550903],"type":"Point"}
}