{
  "type": "Feature",
  "properties": {
    "iso:country":"DE",
    "sg:address":"Osterholder Allee 2",
    "sg:city":"Pinneberg",
    "sg:phone":"+49 4101/54930",
    "sg:postcode":"25421",
    "sg:province":"Schleswig-Holstein",
    "wof:name":"Wekatrans Internationale Spedition Gmbh",
    "wof:placetype":"venue"
},
  "geometry": {"coordinates":[9.7987766266,53.6534767151],"type":"Point"}
}