{
  "type": "Feature",
  "properties": {
    "iso:country":"DE",
    "sg:address":"Johann-G.-Gutenberg-Str 19a",
    "sg:city":"Olching",
    "sg:phone":"+49 8142/488747",
    "sg:postcode":"82140",
    "sg:province":"Bayern",
    "wof:name":"Batec Sicherheitsanlagen Gmbh & Co Kg",
    "wof:placetype":"venue"
},
  "geometry": {"coordinates":[11.3316192627,48.1979637146],"type":"Point"}
}