{
  "type": "Feature",
  "properties": {
    "iso:country":"DE",
    "sg:address":"Am Iberg 3",
    "sg:city":"Willingen",
    "sg:phone":"+49 5632/6192",
    "sg:postcode":"34508",
    "sg:province":"Hessen",
    "wof:name":"G\u00e4stehaus Kesper-schneiders",
    "wof:placetype":"venue"
},
  "geometry": {"coordinates":[8.6156148911,51.2936973572],"type":"Point"}
}