{
  "type": "Feature",
  "properties": {
    "iso:country":"DE",
    "sg:address":"Hallesche Str 29",
    "sg:city":"Zorbau",
    "sg:phone":"+49 34441/9790",
    "sg:postcode":"06679",
    "sg:province":"Sachsen-Anhalt",
    "wof:name":"Seifert Spedition-logistik Gmbh",
    "wof:placetype":"venue"
},
  "geometry": {"coordinates":[12.0101957321,51.1822052002],"type":"Point"}
}