{
  "type": "Feature",
  "properties": {
    "iso:country":"DE",
    "sg:address":"Wertinger Str. 94",
    "sg:city":"Augsburg",
    "sg:phone":"+49 821/461815",
    "sg:postcode":"86156",
    "sg:province":"Bayern",
    "wof:name":"Hl-markt",
    "wof:placetype":"venue"
},
  "geometry": {"coordinates":[10.8605108261,48.3954696655],"type":"Point"}
}