{
  "type": "Feature",
  "properties": {
    "iso:country":"DE",
    "sg:address":"Hafenweg 44 b",
    "sg:city":"Schaprode",
    "sg:phone":"+49 38309/1209",
    "sg:postcode":"18569",
    "sg:province":"Mecklenburg-Vorpommern",
    "wof:name":"R\u00fcgener Hafen- Und Touristik Gmbh",
    "wof:placetype":"venue"
},
  "geometry": {"coordinates":[13.1641283035,54.5134124756],"type":"Point"}
}