{
  "type": "Feature",
  "properties": {
    "iso:country":"DE",
    "sg:address":"Bahrenfelder Str. 97",
    "sg:city":"Hamburg",
    "sg:phone":"+49 40/3903833",
    "sg:postcode":"22765",
    "sg:province":"Hamburg",
    "wof:name":"Rosa Rosa",
    "wof:placetype":"venue"
},
  "geometry": {"coordinates":[9.929794,53.552601],"type":"Point"}
}