{
  "type": "Feature",
  "properties": {
    "iso:country":"DE",
    "sg:address":"Rennbachstr. 21",
    "sg:city":"Bad Wildbad",
    "sg:phone":"+49 7081/3356",
    "sg:postcode":"75323",
    "sg:province":"Baden-W\u00fcrttemberg",
    "wof:name":"Heinz Und Wolfgang Bott Gmbh",
    "wof:placetype":"venue"
},
  "geometry": {"coordinates":[8.548398,48.754585],"type":"Point"}
}