{
  "type": "Feature",
  "properties": {
    "iso:country":"DE",
    "sg:address":"Hauptstr 62",
    "sg:city":"Waldbr\u00f6l",
    "sg:phone":"+49 2291/2739",
    "sg:postcode":"51545",
    "sg:province":"Nordrhein-Westfalen",
    "wof:name":"Kreissparkasse K\u00f6ln",
    "wof:placetype":"venue"
},
  "geometry": {"coordinates":[7.65422,50.894291],"type":"Point"}
}