{
  "type": "Feature",
  "properties": {
    "iso:country":"DE",
    "sg:address":"Wasserstr. 219",
    "sg:city":"Bochum",
    "sg:phone":"+49 4961/0152470",
    "sg:postcode":"44799",
    "sg:province":"Nordrhein-Westfalen",
    "wof:name":"Winterthur Software Gmbh",
    "wof:placetype":"venue"
},
  "geometry": {"coordinates":[8.7451276779,50.1926841736],"type":"Point"}
}