{
  "type": "Feature",
  "properties": {
    "iso:country":"DE",
    "sg:address":"Schalksburgstr. 2",
    "sg:city":"Porta Westfalica",
    "sg:phone":"+49 571/74780",
    "sg:postcode":"32457",
    "sg:province":"Nordrhein-Westfalen",
    "wof:name":"Petra",
    "wof:placetype":"venue"
},
  "geometry": {"coordinates":[8.921767,52.239334],"type":"Point"}
}