{
  "type": "Feature",
  "properties": {
    "iso:country":"DE",
    "sg:address":"Schlo\u00dfstr. 110",
    "sg:city":"Dinslaken",
    "sg:phone":"+49 2064/71283",
    "sg:postcode":"46535",
    "sg:province":"Nordrhein-Westfalen",
    "wof:name":"Autoren Team Spezialisten F\u00fcr",
    "wof:placetype":"venue"
},
  "geometry": {"coordinates":[6.7402639389,51.5512390137],"type":"Point"}
}