{
  "type": "Feature",
  "properties": {
    "iso:country":"DE",
    "sg:address":"Br\u00fchlstr. 10",
    "sg:city":"Ettringen",
    "sg:phone":"+49 8249/1441",
    "sg:postcode":"86833",
    "sg:province":"Bayern",
    "wof:name":"A. Seitz",
    "wof:placetype":"venue"
},
  "geometry": {"coordinates":[10.656064,48.106823],"type":"Point"}
}