{
  "type": "Feature",
  "properties": {
    "iso:country":"DE",
    "sg:address":"Schulstr. 5",
    "sg:city":"Salach",
    "sg:postcode":"73084",
    "sg:province":"Baden-W\u00fcrttemberg",
    "wof:name":"Tele-verwaltung Gmbh",
    "wof:placetype":"venue"
},
  "geometry": {"coordinates":[9.7391881943,48.6907615662],"type":"Point"}
}