{
  "type": "Feature",
  "properties": {
    "iso:country":"DE",
    "sg:address":"Schillerstr. 5",
    "sg:city":"Erfurt",
    "sg:postcode":"99096",
    "sg:province":"Th\u00fcringen",
    "wof:name":"Katholisches Pfarramt St. Wigbert",
    "wof:placetype":"venue"
},
  "geometry": {"coordinates":[11.0349340439,50.9692192078],"type":"Point"}
}