{
  "type": "Feature",
  "properties": {
    "iso:country":"DE",
    "sg:address":"Behringstr. 6",
    "sg:city":"Burgwald",
    "sg:phone":"+49 4964/573156",
    "sg:postcode":"35099",
    "sg:province":"Hessen",
    "wof:name":"Raiffeisenbank Eg",
    "wof:placetype":"venue"
},
  "geometry": {"coordinates":[8.746934,51.008579],"type":"Point"}
}