{
  "type": "Feature",
  "properties": {
    "iso:country":"DE",
    "sg:address":"Jahnstr. 6",
    "sg:city":"Monheim",
    "sg:phone":"+49 9091/3663",
    "sg:postcode":"86653",
    "sg:province":"Bayern",
    "wof:name":"Albert Brendle",
    "wof:placetype":"venue"
},
  "geometry": {"coordinates":[10.8553113937,48.8420791626],"type":"Point"}
}