{
  "type": "Feature",
  "properties": {
    "iso:country":"DE",
    "sg:address":"Morsbacher Str. 56",
    "sg:city":"W\u00fcrselen",
    "sg:phone":"+49 2405/808010",
    "sg:postcode":"52146",
    "sg:province":"Nordrhein-Westfalen",
    "wof:name":"Franz P\u00fctz Gmbh & Co. Kg",
    "wof:placetype":"venue"
},
  "geometry": {"coordinates":[6.1246881485,50.8300323486],"type":"Point"}
}