{
  "type": "Feature",
  "properties": {
    "iso:country":"DE",
    "sg:city":"Dresden",
    "sg:phone":"+49 351/4902746",
    "sg:postcode":"01141",
    "sg:province":"Sachsen",
    "wof:name":"Eisenbahnverlag",
    "wof:placetype":"venue"
},
  "geometry": {"coordinates":[13.73361,51.05085],"type":"Point"}
}