{
  "type": "Feature",
  "properties": {
    "iso:country":"DE",
    "sg:address":"Amsterdamer Str. 31",
    "sg:city":"B\u00f6blingen",
    "sg:phone":"+49 7031/276148",
    "sg:postcode":"71034",
    "sg:province":"Baden-W\u00fcrttemberg",
    "wof:name":"W. Bohne",
    "wof:placetype":"venue"
},
  "geometry": {"coordinates":[8.9948005676,48.6738967896],"type":"Point"}
}