{
  "type": "Feature",
  "properties": {
    "iso:country":"DE",
    "sg:address":"Im R\u00fcckenborn 5",
    "sg:city":"Piesport",
    "sg:phone":"+49 6507/2336",
    "sg:postcode":"54498",
    "sg:province":"Rheinland-Pfalz",
    "wof:name":"Erz Betonwerkstein- Herstellungs Gmbh",
    "wof:placetype":"venue"
},
  "geometry": {"coordinates":[6.924304,49.878307],"type":"Point"}
}