{
  "type": "Feature",
  "properties": {
    "iso:country":"DE",
    "sg:address":"Axtbachtal 8",
    "sg:city":"Beelen",
    "sg:phone":"+49 2586/1795",
    "sg:postcode":"48361",
    "sg:province":"Nordrhein-Westfalen",
    "wof:name":"Getr\u00e4nke-blienert Waltraud Blienert",
    "wof:placetype":"venue"
},
  "geometry": {"coordinates":[8.109951,51.929909],"type":"Point"}
}