{
  "type": "Feature",
  "properties": {
    "iso:country":"DE",
    "sg:address":"Biedermannstr. 36",
    "sg:city":"Leipzig",
    "sg:phone":"+49 341/3913398",
    "sg:postcode":"04277",
    "sg:province":"Sachsen",
    "wof:name":"Hans Zsch\u00f6ttche",
    "wof:placetype":"venue"
},
  "geometry": {"coordinates":[12.375828,51.307472],"type":"Point"}
}