{
  "type": "Feature",
  "properties": {
    "iso:country":"DE",
    "sg:address":"G\u00e4ustr. 98",
    "sg:city":"Neustadt",
    "sg:phone":"+49 6327/649",
    "sg:postcode":"67435",
    "sg:province":"Rheinland-Pfalz",
    "wof:name":"E. U. C. Sturm",
    "wof:placetype":"venue"
},
  "geometry": {"coordinates":[8.2562379837,49.3049468994],"type":"Point"}
}