{
  "type": "Feature",
  "properties": {
    "iso:country":"DE",
    "sg:address":"Holthausen 68",
    "sg:city":"Steinfeld",
    "sg:phone":"+49 5492/1251",
    "sg:postcode":"49439",
    "sg:province":"Niedersachsen",
    "wof:name":"Landwirtschaft Und K\u00e4lbermast Holthausen Gmbh",
    "wof:placetype":"venue"
},
  "geometry": {"coordinates":[8.2459697723,52.5976600647],"type":"Point"}
}