{
  "type": "Feature",
  "properties": {
    "iso:country":"DE",
    "sg:address":"L\u00f6chgauer Str. 2",
    "sg:city":"Bietigheim-Bissingen",
    "sg:phone":"+49 7142/44432",
    "sg:postcode":"74321",
    "sg:province":"Baden-W\u00fcrttemberg",
    "wof:name":"K. N\u00e4gele",
    "wof:placetype":"venue"
},
  "geometry": {"coordinates":[9.1287279129,48.9610137939],"type":"Point"}
}