{
  "type": "Feature",
  "properties": {
    "iso:country":"DE",
    "sg:address":"Auf dem Quellberg 10",
    "sg:city":"D\u00fclmen",
    "sg:phone":"+49 2594/782280",
    "sg:postcode":"48249",
    "sg:province":"Nordrhein-Westfalen",
    "wof:name":"M. S. Design Shop Gmbh",
    "wof:placetype":"venue"
},
  "geometry": {"coordinates":[7.2936348915,51.8412094116],"type":"Point"}
}