{
  "type": "Feature",
  "properties": {
    "iso:country":"DE",
    "sg:address":"Cyrener Hof 31",
    "sg:city":"H\u00fcnxe",
    "sg:phone":"+49 2858/1445",
    "sg:postcode":"46569",
    "sg:province":"Nordrhein-Westfalen",
    "wof:name":"Akh Aluminium-kunststoffbau Handels- Und",
    "wof:placetype":"venue"
},
  "geometry": {"coordinates":[6.769256115,51.6398582458],"type":"Point"}
}