{
  "type": "Feature",
  "properties": {
    "iso:country":"DE",
    "sg:address":"Bahnhofstr. 1",
    "sg:city":"Nordholz",
    "sg:phone":"+49 4741/8070",
    "sg:postcode":"27637",
    "sg:province":"Niedersachsen",
    "wof:name":"Gastst\u00e4tte Zur Rampe",
    "wof:placetype":"venue"
},
  "geometry": {"coordinates":[8.6198711395,53.77759552],"type":"Point"}
}