{
  "type": "Feature",
  "properties": {
    "iso:country":"DE",
    "sg:address":"Gartenstr. 13",
    "sg:city":"M\u00fclheim",
    "sg:phone":"+49 6534/512",
    "sg:postcode":"54486",
    "sg:province":"Rheinland-Pfalz",
    "wof:name":"Erich Pauly",
    "wof:placetype":"venue"
},
  "geometry": {"coordinates":[7.01171,49.911034],"type":"Point"}
}