{
  "type": "Feature",
  "properties": {
    "iso:country":"DE",
    "sg:address":"Hauptstr. 3",
    "sg:city":"Starnberg",
    "sg:phone":"+49 8151/36200",
    "sg:postcode":"82319",
    "sg:province":"Bayern",
    "wof:name":"Ic & F Innovative Cosmetics Und Fragrances Gmbh",
    "wof:placetype":"venue"
},
  "geometry": {"coordinates":[11.342436,47.999718],"type":"Point"}
}