{
  "type": "Feature",
  "properties": {
    "iso:country":"DE",
    "sg:address":"Kronenstr. 5",
    "sg:city":"K\u00fcrnbach",
    "sg:phone":"+49 7258/7435",
    "sg:postcode":"75057",
    "sg:province":"Baden-W\u00fcrttemberg",
    "wof:name":"Gerhard Lutz",
    "wof:placetype":"venue"
},
  "geometry": {"coordinates":[8.844644,49.077595],"type":"Point"}
}