{
  "type": "Feature",
  "properties": {
    "iso:country":"DE",
    "sg:address":"K\u00f6nigstr. 11",
    "sg:city":"Asperg",
    "sg:phone":"+49 7141/2690",
    "sg:postcode":"71679",
    "sg:province":"Baden-W\u00fcrttemberg",
    "wof:name":"Stadtwerke Asperg",
    "wof:placetype":"venue"
},
  "geometry": {"coordinates":[9.135108,48.905823],"type":"Point"}
}