{
  "type": "Feature",
  "properties": {
    "iso:country":"DE",
    "sg:address":"Bergstr. 2",
    "sg:city":"Oschersleben",
    "sg:phone":"+49 3949/97022",
    "sg:postcode":"39387",
    "sg:province":"Sachsen-Anhalt",
    "wof:name":"Otto Rohr Gmbh Zweigniederlsg. Oschersleben",
    "wof:placetype":"venue"
},
  "geometry": {"coordinates":[11.225549,52.02282],"type":"Point"}
}