{
  "type": "Feature",
  "properties": {
    "iso:country":"DE",
    "sg:address":"An der Hasel 147",
    "sg:city":"Suhl",
    "sg:phone":"+49 3681/721213",
    "sg:postcode":"98527",
    "sg:province":"Th\u00fcringen",
    "wof:name":"Karl Wienke Landschaftsarchitekt",
    "wof:placetype":"venue"
},
  "geometry": {"coordinates":[10.688375,50.595898],"type":"Point"}
}