{
  "type": "Feature",
  "properties": {
    "iso:country":"DE",
    "sg:address":"Bergstr. 3",
    "sg:city":"St. Ingbert",
    "sg:phone":"+49 6894/35423",
    "sg:postcode":"66386",
    "sg:province":"Saarland",
    "wof:name":"Judith Hepp-eich",
    "wof:placetype":"venue"
},
  "geometry": {"coordinates":[7.123665,49.276691],"type":"Point"}
}