{
  "type": "Feature",
  "properties": {
    "iso:country":"DE",
    "sg:address":"Sch\u00fcbargredder 1",
    "sg:city":"Ammersbek",
    "sg:phone":"+49 40/6052632",
    "sg:postcode":"22949",
    "sg:province":"Schleswig-Holstein",
    "wof:name":"Wilfried Trunsch",
    "wof:placetype":"venue"
},
  "geometry": {"coordinates":[10.170349,53.68877],"type":"Point"}
}