{
  "type": "Feature",
  "properties": {
    "iso:country":"DE",
    "sg:address":"Finkenweg 6",
    "sg:city":"Pfalzgrafenweiler",
    "sg:phone":"+49 7445/2819",
    "sg:postcode":"72285",
    "sg:province":"Baden-W\u00fcrttemberg",
    "wof:name":"R. F\u00f6rster",
    "wof:placetype":"venue"
},
  "geometry": {"coordinates":[8.6026029587,48.5374908447],"type":"Point"}
}