{
  "type": "Feature",
  "properties": {
    "iso:country":"DE",
    "sg:address":"An der Eschollm\u00fchle 28",
    "sg:city":"Darmstadt",
    "sg:phone":"+49 6151/94480",
    "sg:postcode":"64297",
    "sg:province":"Hessen",
    "wof:name":"Igm Ingenieurgesellschaft F\u00fcr Wasserwirtschafl. Me\u00dfdaten Mbh",
    "wof:placetype":"venue"
},
  "geometry": {"coordinates":[8.6417036057,49.8157806396],"type":"Point"}
}