{
  "type": "Feature",
  "properties": {
    "iso:country":"DE",
    "sg:address":"Schwarzer Weg 34",
    "sg:city":"Bardowick",
    "sg:phone":"+49 4131/12330",
    "sg:postcode":"21357",
    "sg:province":"Niedersachsen",
    "wof:name":"Spedition Harms E. K.",
    "wof:placetype":"venue"
},
  "geometry": {"coordinates":[10.3961229324,53.2881698608],"type":"Point"}
}