{
  "type": "Feature",
  "properties": {
    "iso:country":"DE",
    "sg:address":"Schwickartsh\u00e4user Str. 11",
    "sg:city":"Nidda",
    "sg:phone":"+49 6043/8157",
    "sg:postcode":"63667",
    "sg:province":"Hessen",
    "wof:name":"Heinz Brack",
    "wof:placetype":"venue"
},
  "geometry": {"coordinates":[9.0628814697,50.4031982422],"type":"Point"}
}