{
  "type": "Feature",
  "properties": {
    "iso:country":"DE",
    "sg:address":"D\u00fcrerstr. 7",
    "sg:city":"Gelsenkirchen",
    "sg:phone":"+49 209/41077",
    "sg:postcode":"45883",
    "sg:province":"Nordrhein-Westfalen",
    "wof:name":"Gelsentrade Mineral\u00f6l-handels-gmbh",
    "wof:placetype":"venue"
},
  "geometry": {"coordinates":[7.0843901634,51.5073242188],"type":"Point"}
}