{
  "type": "Feature",
  "properties": {
    "iso:country":"DE",
    "sg:address":"Friedensplatz 1",
    "sg:city":"Barnst\u00e4dt",
    "sg:postcode":"06268",
    "sg:province":"Sachsen-Anhalt",
    "wof:name":"Gebr\u00fcder Hlady Kg",
    "wof:placetype":"venue"
},
  "geometry": {"coordinates":[11.641757,51.344822],"type":"Point"}
}