{
  "type": "Feature",
  "properties": {
    "iso:country":"DE",
    "sg:address":"Marktstr. 2",
    "sg:city":"Owen",
    "sg:phone":"+49 7021/864735",
    "sg:postcode":"73277",
    "sg:province":"Baden-W\u00fcrttemberg",
    "wof:name":"Cafe-restaurant Gw\u00f6lbe",
    "wof:placetype":"venue"
},
  "geometry": {"coordinates":[9.4530706406,48.5882835388],"type":"Point"}
}