{
  "type": "Feature",
  "properties": {
    "iso:country":"DE",
    "sg:address":"Tegernau 1-10",
    "sg:city":"Wasserburg",
    "sg:phone":"+49 8071/1090",
    "sg:postcode":"83512",
    "sg:province":"Bayern",
    "wof:name":"Josef Bauer Kg",
    "wof:placetype":"venue"
},
  "geometry": {"coordinates":[12.2203798294,48.0483894348],"type":"Point"}
}