{
  "type": "Feature",
  "properties": {
    "iso:country":"DE",
    "sg:address":"Luitpoldstr. 38",
    "sg:city":"Ottobeuren",
    "sg:phone":"+49 8332/7778",
    "sg:postcode":"87724",
    "sg:province":"Bayern",
    "wof:name":"Josef Heiler",
    "wof:placetype":"venue"
},
  "geometry": {"coordinates":[10.300479,47.938747],"type":"Point"}
}