{
  "type": "Feature",
  "properties": {
    "iso:country":"DE",
    "sg:address":"Helgolandstr. 9",
    "sg:city":"Dresden",
    "sg:phone":"+49 351/8047680",
    "sg:postcode":"01097",
    "sg:province":"Sachsen",
    "wof:name":"Ccs Dresden Gmbh",
    "wof:placetype":"venue"
},
  "geometry": {"coordinates":[13.742919,51.072632],"type":"Point"}
}