{
  "type": "Feature",
  "properties": {
    "iso:country":"DE",
    "sg:address":"Mei\u00dfener Dorfstr. 66",
    "sg:city":"Minden",
    "sg:phone":"+49 571/31494",
    "sg:postcode":"32423",
    "sg:province":"Nordrhein-Westfalen",
    "wof:name":"Ev. Pfarramt Ev. Luth. Kirchengemeinde",
    "wof:placetype":"venue"
},
  "geometry": {"coordinates":[8.9570703506,52.2708015442],"type":"Point"}
}