{
  "type": "Feature",
  "properties": {
    "iso:country":"DE",
    "sg:address":"Karl-Benz-Str. 12",
    "sg:city":"Bad W\u00f6rishofen",
    "sg:phone":"+49 8247/96300",
    "sg:postcode":"86825",
    "sg:province":"Bayern",
    "wof:name":"Holz-kreuzer Gmbh",
    "wof:placetype":"venue"
},
  "geometry": {"coordinates":[10.601893425,48.0225219727],"type":"Point"}
}