{
  "type": "Feature",
  "properties": {
    "iso:country":"DE",
    "sg:address":"Am Walde 14",
    "sg:city":"Haverlah",
    "sg:phone":"+49 5341/331886",
    "sg:postcode":"38275",
    "sg:province":"Niedersachsen",
    "wof:name":"Claus-dieter Wiesner Gmbh",
    "wof:placetype":"venue"
},
  "geometry": {"coordinates":[10.3323287964,52.0756072998],"type":"Point"}
}