{
  "type": "Feature",
  "properties": {
    "iso:country":"DE",
    "sg:address":"An der Walkm\u00fchle 7",
    "sg:city":"Hammelburg",
    "sg:phone":"+49 9732/4406",
    "sg:postcode":"97762",
    "sg:province":"Bayern",
    "wof:name":"Elektro-eilingsfeld Verwaltungs Gmbh",
    "wof:placetype":"venue"
},
  "geometry": {"coordinates":[9.8995819092,50.1150665283],"type":"Point"}
}