{
  "type": "Feature",
  "properties": {
    "iso:country":"DE",
    "sg:address":"Zeunerstr. 66",
    "sg:city":"Dresden",
    "sg:phone":"+49 351/4714996",
    "sg:postcode":"01069",
    "sg:province":"Sachsen",
    "wof:name":"Spina Bifida Und Hydrocephalus E. V.",
    "wof:placetype":"venue"
},
  "geometry": {"coordinates":[13.732334137,51.026676178],"type":"Point"}
}