{
  "type": "Feature",
  "properties": {
    "iso:country":"DE",
    "sg:address":"Renterei 4",
    "sg:city":"Altersbach",
    "sg:phone":"+49 36847/31208",
    "sg:postcode":"98587",
    "sg:province":"Th\u00fcringen",
    "wof:name":"B. Hellmann",
    "wof:placetype":"venue"
},
  "geometry": {"coordinates":[10.545214653,50.7038841248],"type":"Point"}
}