{
  "type": "Feature",
  "properties": {
    "iso:country":"DE",
    "sg:address":"Am M\u00fchlgraben 8",
    "sg:city":"Bad K\u00f6stritz",
    "sg:phone":"+49 36605/84232",
    "sg:postcode":"07586",
    "sg:province":"Th\u00fcringen",
    "wof:name":"Pension Kaiser",
    "wof:placetype":"venue"
},
  "geometry": {"coordinates":[12.0158157349,50.931388855],"type":"Point"}
}