{
  "type": "Feature",
  "properties": {
    "iso:country":"DE",
    "sg:address":"Schlo\u00dfgarten 5",
    "sg:city":"Erlangen",
    "sg:phone":"+49 9131/852615",
    "sg:postcode":"91054",
    "sg:province":"Bayern",
    "wof:name":"Geologische Sammlungen Des Institus F\u00fcr Geologie",
    "wof:placetype":"venue"
},
  "geometry": {"coordinates":[11.0044412613,49.5981063843],"type":"Point"}
}