{
  "type": "Feature",
  "properties": {
    "iso:country":"DE",
    "sg:address":"Schillerstr. 60",
    "sg:city":"Arnsberg",
    "sg:postcode":"59755",
    "sg:province":"Nordrhein-Westfalen",
    "wof:name":"Stima Verm\u00f6gensverwaltungs- Und Holding Ag",
    "wof:placetype":"venue"
},
  "geometry": {"coordinates":[7.960876,51.444038],"type":"Point"}
}