{
  "type": "Feature",
  "properties": {
    "iso:country":"DE",
    "sg:address":"Dreik\u00f6nigsstr. 6",
    "sg:city":"Wenden",
    "sg:phone":"+49 2762/8242",
    "sg:postcode":"57482",
    "sg:province":"Nordrhein-Westfalen",
    "wof:name":"L. Und D. Heupel",
    "wof:placetype":"venue"
},
  "geometry": {"coordinates":[7.890616,50.939117],"type":"Point"}
}