{
  "type": "Feature",
  "properties": {
    "iso:country":"DE",
    "sg:address":"Gei\u00dfbergstr. 5",
    "sg:city":"Eningen",
    "sg:phone":"+49 7121/81516",
    "sg:postcode":"72800",
    "sg:province":"Baden-W\u00fcrttemberg",
    "wof:name":"Robert Reinhardt",
    "wof:placetype":"venue"
},
  "geometry": {"coordinates":[9.2610712051,48.4878234863],"type":"Point"}
}