{
  "type": "Feature",
  "properties": {
    "iso:country":"DE",
    "sg:address":"Dielingerstr. 23",
    "sg:city":"Osnabr\u00fcck",
    "sg:phone":"+49 541/29564",
    "sg:postcode":"49074",
    "sg:province":"Niedersachsen",
    "wof:name":"Altstadt-friseur",
    "wof:placetype":"venue"
},
  "geometry": {"coordinates":[8.0404348373,52.2753753662],"type":"Point"}
}