{
  "type": "Feature",
  "properties": {
    "iso:country":"DE",
    "sg:address":"Wiesenstr. 20-23",
    "sg:city":"Berlin",
    "sg:phone":"+49 30/4659056",
    "sg:postcode":"13357",
    "sg:province":"Berlin",
    "wof:name":"Friedrich Wei\u00df Gmbh",
    "wof:placetype":"venue"
},
  "geometry": {"coordinates":[13.3736829758,52.5479354858],"type":"Point"}
}