{
  "type": "Feature",
  "properties": {
    "iso:country":"DE",
    "sg:address":"Rheinstr. 62",
    "sg:city":"M\u00fcnster-Sarmsheim",
    "sg:phone":"+49 6721/46370",
    "sg:postcode":"55424",
    "sg:province":"Rheinland-Pfalz",
    "wof:name":"Gastst\u00e4tte U 9",
    "wof:placetype":"venue"
},
  "geometry": {"coordinates":[7.8965940475,49.9456596375],"type":"Point"}
}