{
  "type": "Feature",
  "properties": {
    "iso:country":"DE",
    "sg:address":"Gro\u00dfe Str. 97",
    "sg:city":"Aschendorf",
    "sg:phone":"+49 4962/472",
    "sg:postcode":"26871",
    "sg:province":"Niedersachsen",
    "wof:name":"B. Hinrichs",
    "wof:placetype":"venue"
},
  "geometry": {"coordinates":[7.33057,53.049675],"type":"Point"}
}