{
  "type": "Feature",
  "properties": {
    "iso:country":"DE",
    "sg:address":"Hauptstr. 14",
    "sg:city":"Dernbach",
    "sg:phone":"+49 2689/2429",
    "sg:postcode":"56307",
    "sg:province":"Rheinland-Pfalz",
    "wof:name":"Bistro Vis-a-vis",
    "wof:placetype":"venue"
},
  "geometry": {"coordinates":[7.5978560448,50.5434989929],"type":"Point"}
}