{
  "type": "Feature",
  "properties": {
    "iso:country":"DE",
    "sg:address":"Beunegasse 17",
    "sg:city":"Schaafheim",
    "sg:phone":"+49 6073/9396",
    "sg:postcode":"64850",
    "sg:province":"Hessen",
    "wof:name":"M. Schimpf & S\u00f6hne",
    "wof:placetype":"venue"
},
  "geometry": {"coordinates":[9.0019922256,49.9209251404],"type":"Point"}
}