{
  "type": "Feature",
  "properties": {
    "iso:country":"DE",
    "sg:address":"Paul-M\u00fcnch-Str. 8",
    "sg:city":"Limburgerhof",
    "sg:phone":"+49 6236/60702",
    "sg:postcode":"67117",
    "sg:province":"Rheinland-Pfalz",
    "wof:name":"Michael Klipphahn",
    "wof:placetype":"venue"
},
  "geometry": {"coordinates":[8.3905544281,49.4252433777],"type":"Point"}
}