{
  "type": "Feature",
  "properties": {
    "iso:country":"DE",
    "sg:address":"Merkurweg 7",
    "sg:city":"Ronnenberg",
    "sg:phone":"+49 511/466463",
    "sg:postcode":"30952",
    "sg:province":"Niedersachsen",
    "wof:name":"Klaus Scheumann Architekt",
    "wof:placetype":"venue"
},
  "geometry": {"coordinates":[9.660837,52.343033],"type":"Point"}
}