{
  "type": "Feature",
  "properties": {
    "iso:country":"DE",
    "sg:address":"Altenkamp 37",
    "sg:city":"Ratingen",
    "sg:phone":"+49 2102/93390",
    "sg:postcode":"40885",
    "sg:province":"Nordrhein-Westfalen",
    "wof:name":"Lang Software Gmbh",
    "wof:placetype":"venue"
},
  "geometry": {"coordinates":[6.8315877914,51.3453903198],"type":"Point"}
}