{
  "type": "Feature",
  "properties": {
    "iso:country":"DE",
    "sg:address":"Hammerweg 2",
    "sg:city":"Annaberg-Buchholz",
    "sg:phone":"+49 3733/22388",
    "sg:postcode":"09456",
    "sg:province":"Sachsen",
    "wof:name":"M. Teucher",
    "wof:placetype":"venue"
},
  "geometry": {"coordinates":[12.993694,50.58139],"type":"Point"}
}