{
  "type": "Feature",
  "properties": {
    "iso:country":"DE",
    "sg:address":"Mauerschell",
    "sg:city":"Hilders",
    "sg:phone":"+49 6681/450",
    "sg:postcode":"36115",
    "sg:province":"Hessen",
    "wof:name":"Eduard Reinhardt",
    "wof:placetype":"venue"
},
  "geometry": {"coordinates":[9.9434,50.577648],"type":"Point"}
}