{
  "type": "Feature",
  "properties": {
    "iso:country":"DE",
    "sg:address":"Schmiljanstr. 12",
    "sg:city":"Berlin",
    "sg:phone":"+49 30/8519858",
    "sg:postcode":"12161",
    "sg:province":"Berlin",
    "wof:name":"Top-copy Kopiercenter",
    "wof:placetype":"venue"
},
  "geometry": {"coordinates":[13.3314275742,52.4694976807],"type":"Point"}
}