{
  "type": "Feature",
  "properties": {
    "iso:country":"DE",
    "sg:address":"Zur Dorfeiche 26",
    "sg:city":"Undeloh",
    "sg:phone":"+49 4189/351",
    "sg:postcode":"21274",
    "sg:province":"Niedersachsen",
    "wof:name":"Pension Drews",
    "wof:placetype":"venue"
},
  "geometry": {"coordinates":[9.9823274612,53.1986618042],"type":"Point"}
}