{
  "type": "Feature",
  "properties": {
    "iso:country":"DE",
    "sg:address":"B\u00fcnder Landweg 56",
    "sg:city":"Hiddenhausen",
    "sg:postcode":"32120",
    "sg:province":"Nordrhein-Westfalen",
    "wof:name":"Santerra Gmbh",
    "wof:placetype":"venue"
},
  "geometry": {"coordinates":[8.6552019119,52.1409797668],"type":"Point"}
}