{
  "type": "Feature",
  "properties": {
    "iso:country":"DE",
    "sg:address":"Kirchheimer Str. 66",
    "sg:city":"Dettingen",
    "sg:phone":"+49 7021/81388",
    "sg:postcode":"73265",
    "sg:province":"Baden-W\u00fcrttemberg",
    "wof:name":"Wero Immobilienmakler",
    "wof:placetype":"venue"
},
  "geometry": {"coordinates":[9.4523267746,48.6158828735],"type":"Point"}
}