{
  "type": "Feature",
  "properties": {
    "iso:country":"DE",
    "sg:address":"Industriepark 26",
    "sg:city":"Gro\u00dfkoschen",
    "sg:phone":"+49 3573/81581",
    "sg:postcode":"01968",
    "sg:province":"Brandenburg",
    "wof:name":"Wile Rolladen Und Jalousien Gmbh",
    "wof:placetype":"venue"
},
  "geometry": {"coordinates":[14.00963,51.515202],"type":"Point"}
}