{
  "type": "Feature",
  "properties": {
    "iso:country":"DE",
    "sg:address":"Neue Mainzer Str. 24",
    "sg:city":"Frankfurt",
    "sg:phone":"+49 69/253790",
    "sg:postcode":"60311",
    "sg:province":"Hessen",
    "wof:name":"Medius-keller",
    "wof:placetype":"venue"
},
  "geometry": {"coordinates":[8.674446106,50.1098213196],"type":"Point"}
}