{
  "type": "Feature",
  "properties": {
    "iso:country":"DE",
    "sg:address":"Kuhlenstr. 64",
    "sg:city":"M\u00fclheim",
    "sg:phone":"+49 208/471710",
    "sg:postcode":"45468",
    "sg:province":"Nordrhein-Westfalen",
    "wof:name":"Karlheinz Bosly Steuerberater",
    "wof:placetype":"venue"
},
  "geometry": {"coordinates":[6.8943929672,51.4392089844],"type":"Point"}
}