{
  "type": "Feature",
  "properties": {
    "iso:country":"DE",
    "sg:address":"Nauwerckstr. 1",
    "sg:city":"Chemnitz",
    "sg:phone":"+49 371/855166",
    "sg:postcode":"09116",
    "sg:province":"Sachsen",
    "wof:name":"Msr Elektro- Und Anlagen- Bau Gmbh",
    "wof:placetype":"venue"
},
  "geometry": {"coordinates":[12.8716249466,50.816280365],"type":"Point"}
}