{
  "type": "Feature",
  "properties": {
    "iso:country":"DE",
    "sg:address":"Kaiser-Wilhelm-Platz 4",
    "sg:city":"Lorsch",
    "sg:phone":"+49 6251/96380",
    "sg:postcode":"64653",
    "sg:province":"Hessen",
    "wof:name":"Klaus Klinger Und Br\u00fcckmann Architekten",
    "wof:placetype":"venue"
},
  "geometry": {"coordinates":[8.566756,49.651592],"type":"Point"}
}