{
  "type": "Feature",
  "properties": {
    "iso:country":"DE",
    "sg:address":"Tiroler Str. 7",
    "sg:city":"V\u00f6hringen",
    "sg:phone":"+49 7306/6091",
    "sg:postcode":"89269",
    "sg:province":"Bayern",
    "wof:name":"Rinker Bau Gmbh & Co. Kg",
    "wof:placetype":"venue"
},
  "geometry": {"coordinates":[10.0787248611,48.2724266052],"type":"Point"}
}