{
  "type": "Feature",
  "properties": {
    "iso:country":"DE",
    "sg:address":"Deidesheimer Str. 24",
    "sg:city":"Berlin",
    "sg:phone":"+49 4930/7879200",
    "sg:postcode":"14197",
    "sg:province":"Berlin",
    "wof:name":"Aachen Bis Berlin Umzugsspedition Gmbh",
    "wof:placetype":"venue"
},
  "geometry": {"coordinates":[13.3196935654,52.4742622375],"type":"Point"}
}