{
  "type": "Feature",
  "properties": {
    "iso:country":"DE",
    "sg:address":"Auf den Kuhlen 3",
    "sg:city":"Syke",
    "sg:phone":"+49 4242/7457",
    "sg:postcode":"28857",
    "sg:province":"Niedersachsen",
    "wof:name":"Heinrich St\u00f6ver",
    "wof:placetype":"venue"
},
  "geometry": {"coordinates":[8.755631,52.931572],"type":"Point"}
}