{
  "type": "Feature",
  "properties": {
    "iso:country":"DE",
    "sg:address":"Saarstra\u00dfe 2",
    "sg:city":"Trier",
    "sg:phone":"+49 651/42425",
    "sg:postcode":"54290",
    "sg:province":"Rheinland-Pfalz",
    "wof:name":"Ars Antikenfestspiele Gmbh",
    "wof:placetype":"venue"
},
  "geometry": {"coordinates":[6.6367111206,49.7495727539],"type":"Point"}
}