{
  "type": "Feature",
  "properties": {
    "iso:country":"DE",
    "sg:address":"Halskestr. 56 a",
    "sg:city":"Hamburg",
    "sg:phone":"+49 40/781651",
    "sg:postcode":"22113",
    "sg:province":"Schleswig-Holstein",
    "wof:name":"Billtrans-billbrooker Transporte Gmbh",
    "wof:placetype":"venue"
},
  "geometry": {"coordinates":[10.0868806839,53.5187034607],"type":"Point"}
}