{
  "type": "Feature",
  "properties": {
    "iso:country":"DE",
    "sg:address":"Im Kloster 1",
    "sg:city":"Welver",
    "sg:phone":"+49 2527/569",
    "sg:postcode":"59514",
    "sg:province":"Nordrhein-Westfalen",
    "wof:name":"Willi Haverkamp Tischlerei Inh. W. Oeing",
    "wof:placetype":"venue"
},
  "geometry": {"coordinates":[8.04928,51.624348],"type":"Point"}
}