{
  "type": "Feature",
  "properties": {
    "iso:country":"DE",
    "sg:address":"Zum Lingeshof 3n",
    "sg:city":"Eichenzell",
    "sg:phone":"+49 6659/987940",
    "sg:postcode":"36124",
    "sg:province":"Hessen",
    "wof:name":"Walcher Kraftwerks- Kommunikationstechnik",
    "wof:placetype":"venue"
},
  "geometry": {"coordinates":[9.718651,50.485008],"type":"Point"}
}