{
  "type": "Feature",
  "properties": {
    "iso:country":"DE",
    "sg:address":"Von-Stauffenberg-Str. 1",
    "sg:city":"J\u00fcchen",
    "sg:phone":"+49 2181/44734",
    "sg:postcode":"41363",
    "sg:province":"Nordrhein-Westfalen",
    "wof:name":"Hans Zinner",
    "wof:placetype":"venue"
},
  "geometry": {"coordinates":[6.5436081886,51.1094055176],"type":"Point"}
}