{
  "type": "Feature",
  "properties": {
    "iso:country":"DE",
    "sg:address":"Bergfeine 34",
    "sg:city":"Damme",
    "sg:phone":"+49 5491/8017",
    "sg:postcode":"49401",
    "sg:province":"Niedersachsen",
    "wof:name":"Heinrich Hellebusch",
    "wof:placetype":"venue"
},
  "geometry": {"coordinates":[8.256891,52.5481],"type":"Point"}
}