{
  "type": "Feature",
  "properties": {
    "iso:country":"DE",
    "sg:address":"Hauptstr. 121",
    "sg:city":"Freudenberg",
    "sg:phone":"+49 9375/242",
    "sg:postcode":"97896",
    "sg:province":"Baden-W\u00fcrttemberg",
    "wof:name":"Sparkasse Freudenberg",
    "wof:placetype":"venue"
},
  "geometry": {"coordinates":[9.323238,49.741905],"type":"Point"}
}