{
  "type": "Feature",
  "properties": {
    "iso:country":"DE",
    "sg:address":"Vogt-Flaig-Str. 23",
    "sg:city":"M\u00f6nchweiler",
    "sg:postcode":"78087",
    "sg:province":"Baden-W\u00fcrttemberg",
    "wof:name":"Wolfgang Joh. Kaiser",
    "wof:placetype":"venue"
},
  "geometry": {"coordinates":[8.4262599945,48.1015739441],"type":"Point"}
}