{
  "type": "Feature",
  "properties": {
    "iso:country":"DE",
    "sg:address":"Sierstorpffstr. 20",
    "sg:city":"Heidesheim",
    "sg:phone":"+49 6132/58621",
    "sg:postcode":"55262",
    "sg:province":"Rheinland-Pfalz",
    "wof:name":"Alice Rose",
    "wof:placetype":"venue"
},
  "geometry": {"coordinates":[8.1232061386,49.9993858337],"type":"Point"}
}