{
  "type": "Feature",
  "properties": {
    "iso:country":"DE",
    "sg:address":"An der Bahn 20",
    "sg:city":"Karlsruhe",
    "sg:phone":"+49 721/681940",
    "sg:postcode":"76139",
    "sg:province":"Baden-W\u00fcrttemberg",
    "wof:name":"Lothar Holdorf",
    "wof:placetype":"venue"
},
  "geometry": {"coordinates":[8.455368,49.030964],"type":"Point"}
}