{
  "type": "Feature",
  "properties": {
    "iso:country":"DE",
    "sg:address":"Hertigswalde 64",
    "sg:city":"Sebnitz",
    "sg:phone":"+49 35971/3713",
    "sg:postcode":"01855",
    "sg:province":"Sachsen",
    "wof:name":"Manfred Montag",
    "wof:placetype":"venue"
},
  "geometry": {"coordinates":[14.2733659744,50.965839386],"type":"Point"}
}