{
  "type": "Feature",
  "properties": {
    "iso:country":"DE",
    "sg:address":"Rheinstr. 28",
    "sg:city":"Montabaur",
    "sg:phone":"+49 2602/90250",
    "sg:postcode":"56410",
    "sg:province":"Rheinland-Pfalz",
    "wof:name":"Norbert Sch\u00fctz Steuerberater",
    "wof:placetype":"venue"
},
  "geometry": {"coordinates":[7.8234119415,50.4350662231],"type":"Point"}
}