{
  "type": "Feature",
  "properties": {
    "iso:country":"DE",
    "sg:address":"Teckstr. 12",
    "sg:city":"Esslingen",
    "sg:phone":"+49 711/3450269",
    "sg:postcode":"73734",
    "sg:province":"Baden-W\u00fcrttemberg",
    "wof:name":"Rainer Edele Messtechnik",
    "wof:placetype":"venue"
},
  "geometry": {"coordinates":[9.325923,48.716457],"type":"Point"}
}