{
  "type": "Feature",
  "properties": {
    "iso:country":"DE",
    "sg:address":"Waldkirchener Str. 11 POSTFACH 3137",
    "sg:city":"Landshut",
    "sg:phone":"+49 871/70030",
    "sg:postcode":"84037",
    "sg:province":"Bayern",
    "wof:name":"Klann Verpackungen Gmbh + Co.",
    "wof:placetype":"venue"
},
  "geometry": {"coordinates":[12.1518297195,48.5388183594],"type":"Point"}
}