{
  "type": "Feature",
  "properties": {
    "iso:country":"DE",
    "sg:address":"Fraunhoferstr. 23i",
    "sg:city":"M\u00fcnchen",
    "sg:phone":"+49 89/20239501",
    "sg:postcode":"80469",
    "sg:province":"Bayern",
    "wof:name":"Reinert & Partner",
    "wof:placetype":"venue"
},
  "geometry": {"coordinates":[11.574067,48.129665],"type":"Point"}
}