{
  "type": "Feature",
  "properties": {
    "iso:country":"DE",
    "sg:address":"Zum Taubenbr\u00fcnnlein 2",
    "sg:city":"Feuchtwangen",
    "sg:phone":"+49 9852/9184",
    "sg:postcode":"91555",
    "sg:province":"Bayern",
    "wof:name":"Ev. Luth. Pfarramt Ii",
    "wof:placetype":"venue"
},
  "geometry": {"coordinates":[10.3305387497,49.1679725647],"type":"Point"}
}