{
  "type": "Feature",
  "properties": {
    "iso:country":"DE",
    "sg:address":"Behringstr. 17",
    "sg:city":"Herrenberg",
    "sg:phone":"+49 4970/3272152",
    "sg:postcode":"71083",
    "sg:province":"Baden-W\u00fcrttemberg",
    "wof:name":"Huppert Gmbh",
    "wof:placetype":"venue"
},
  "geometry": {"coordinates":[8.885405,48.577702],"type":"Point"}
}