{
  "type": "Feature",
  "properties": {
    "iso:country":"DE",
    "sg:address":"Hauptstr. 241",
    "sg:city":"Herne",
    "sg:phone":"+49 2325/92880",
    "sg:postcode":"44649",
    "sg:province":"Nordrhein-Westfalen",
    "wof:name":"Peter N\u00e4rdemann Rechtsanwalt",
    "wof:placetype":"venue"
},
  "geometry": {"coordinates":[7.1588711739,51.530796051],"type":"Point"}
}