{
  "type": "Feature",
  "properties": {
    "iso:country":"DE",
    "sg:address":"Ossietzkystr 37-38",
    "sg:city":"Mei\u00dfen",
    "sg:phone":"+49 3521/46450",
    "sg:postcode":"01662",
    "sg:province":"Sachsen",
    "wof:name":"Rath Gmbh",
    "wof:placetype":"venue"
},
  "geometry": {"coordinates":[13.45952,51.136463],"type":"Point"}
}