{
  "type": "Feature",
  "properties": {
    "iso:country":"DE",
    "sg:address":"P\u00e4hlerstra\u00dfe",
    "sg:city":"Raisting",
    "sg:postcode":"82399",
    "sg:province":"Bayern",
    "wof:name":"Zimmerei Grenzebach",
    "wof:placetype":"venue"
},
  "geometry": {"coordinates":[11.109385,47.910679],"type":"Point"}
}