{
  "type": "Feature",
  "properties": {
    "iso:country":"DE",
    "sg:address":"Hochfeldstr. 51",
    "sg:city":"Langerringen",
    "sg:phone":"+49 8232/4950",
    "sg:postcode":"86853",
    "sg:province":"Bayern",
    "wof:name":"Erwin Schmach",
    "wof:placetype":"venue"
},
  "geometry": {"coordinates":[10.7587652206,48.15417099],"type":"Point"}
}