{
  "type": "Feature",
  "properties": {
    "iso:country":"DE",
    "sg:address":"Hindenburgstr. 15",
    "sg:city":"Konstanz",
    "sg:phone":"+49 7531/8921690",
    "sg:postcode":"78467",
    "sg:province":"Baden-W\u00fcrttemberg",
    "wof:name":"Sv Servicecenter",
    "wof:placetype":"venue"
},
  "geometry": {"coordinates":[9.1711349487,47.6721343994],"type":"Point"}
}