{
  "type": "Feature",
  "properties": {
    "iso:country":"DE",
    "sg:address":"Renoisstr. 1",
    "sg:city":"Bonn",
    "sg:phone":"+49 228/216780",
    "sg:postcode":"53129",
    "sg:province":"Nordrhein-Westfalen",
    "wof:name":"Lisa-reisen Gmbh",
    "wof:placetype":"venue"
},
  "geometry": {"coordinates":[7.1001000404,50.7209739685],"type":"Point"}
}