{
  "type": "Feature",
  "properties": {
    "iso:country":"DE",
    "sg:address":"Hengersberger Str. 8",
    "sg:city":"Niederalteich",
    "sg:phone":"+49 9901/2845",
    "sg:postcode":"94557",
    "sg:province":"Bayern",
    "wof:name":"Josef Voggenreiter",
    "wof:placetype":"venue"
},
  "geometry": {"coordinates":[13.026107,48.766312],"type":"Point"}
}