{
  "type": "Feature",
  "properties": {
    "iso:country":"DE",
    "sg:address":"Sandbergstr. 54",
    "sg:city":"Puchheim",
    "sg:phone":"+49 89/801587",
    "sg:postcode":"82178",
    "sg:province":"Bayern",
    "wof:name":"Wolfgang Gruschwitz",
    "wof:placetype":"venue"
},
  "geometry": {"coordinates":[11.349635,48.146442],"type":"Point"}
}