{
  "type": "Feature",
  "properties": {
    "iso:country":"DE",
    "sg:address":"Wilhelmstr. 48",
    "sg:city":"Muggensturm",
    "sg:phone":"+49 7222",
    "sg:postcode":"76461",
    "sg:province":"Baden-W\u00fcrttemberg",
    "wof:name":"Betonsteinwerk-knapp",
    "wof:placetype":"venue"
},
  "geometry": {"coordinates":[8.2882289886,48.8723564148],"type":"Point"}
}