{
  "type": "Feature",
  "properties": {
    "iso:country":"DE",
    "sg:address":"Ostbahnstr. 27",
    "sg:city":"Hersbruck",
    "sg:phone":"+49 9151/5023",
    "sg:postcode":"91217",
    "sg:province":"Bayern",
    "wof:name":"I. Morawetz",
    "wof:placetype":"venue"
},
  "geometry": {"coordinates":[11.437071,49.504627],"type":"Point"}
}