{
  "type": "Feature",
  "properties": {
    "iso:country":"DE",
    "sg:address":"Bahnhofstr. 50",
    "sg:city":"Michelstadt",
    "sg:phone":"+49 6061/70030",
    "sg:postcode":"64720",
    "sg:province":"Hessen",
    "wof:name":"H. Weber Bauunternehmen Gmbh",
    "wof:placetype":"venue"
},
  "geometry": {"coordinates":[9.001683,49.682789],"type":"Point"}
}