{
  "type": "Feature",
  "properties": {
    "iso:country":"DE",
    "sg:address":"Moltkestra\u00dfe 38",
    "sg:city":"Ahlen",
    "sg:phone":"+49 2382/8540",
    "sg:postcode":"59229",
    "sg:province":"Nordrhein-Westfalen",
    "wof:name":"Sparkasse Ahlen",
    "wof:placetype":"venue"
},
  "geometry": {"coordinates":[7.8972549438,51.7633552551],"type":"Point"}
}