{
  "type": "Feature",
  "properties": {
    "iso:country":"DE",
    "sg:address":"Am Dickopsbach 3",
    "sg:city":"Wesseling",
    "sg:phone":"+49 2236/947610",
    "sg:postcode":"50389",
    "sg:province":"Nordrhein-Westfalen",
    "wof:name":"Reinhard Konda Rechtsanwalt",
    "wof:placetype":"venue"
},
  "geometry": {"coordinates":[6.9642100334,50.8139801025],"type":"Point"}
}