{
  "type": "Feature",
  "properties": {
    "iso:country":"DE",
    "sg:address":"Oesterstr. 81",
    "sg:city":"Marsberg",
    "sg:phone":"+49 2992/8371",
    "sg:postcode":"34431",
    "sg:province":"Nordrhein-Westfalen",
    "wof:name":"Hubert Westermann",
    "wof:placetype":"venue"
},
  "geometry": {"coordinates":[8.864730835,51.4578437805],"type":"Point"}
}