{
  "type": "Feature",
  "properties": {
    "iso:country":"DE",
    "sg:address":"Husarenstr. 16-1",
    "sg:city":"Heidelberg",
    "sg:phone":"+49 6221/45820",
    "sg:postcode":"69121",
    "sg:province":"Baden-W\u00fcrttemberg",
    "wof:name":"G\u00fcnther Klier Steuerberater",
    "wof:placetype":"venue"
},
  "geometry": {"coordinates":[8.6798067093,49.429233551],"type":"Point"}
}