{
  "type": "Feature",
  "properties": {
    "iso:country":"DE",
    "sg:address":"Auf der H\u00f6he 13",
    "sg:city":"Rinteln",
    "sg:phone":"+49 5751/5435",
    "sg:postcode":"31737",
    "sg:province":"Niedersachsen",
    "wof:name":"Heinrich Meier",
    "wof:placetype":"venue"
},
  "geometry": {"coordinates":[9.083358,52.201519],"type":"Point"}
}