{
  "type": "Feature",
  "properties": {
    "iso:country":"DE",
    "sg:address":"Bauernpfad 1",
    "sg:city":"Langenhagen",
    "sg:phone":"+49 511/633001",
    "sg:postcode":"30855",
    "sg:province":"Niedersachsen",
    "wof:name":"Haustech",
    "wof:placetype":"venue"
},
  "geometry": {"coordinates":[9.7362661362,52.4656333923],"type":"Point"}
}