{
  "type": "Feature",
  "properties": {
    "iso:country":"DE",
    "sg:address":"Regiomontanusstr. 165",
    "sg:city":"K\u00f6nigsberg",
    "sg:phone":"+49 9525/223",
    "sg:postcode":"97486",
    "sg:province":"Bayern",
    "wof:name":"Schwarzer B\u00e4r",
    "wof:placetype":"venue"
},
  "geometry": {"coordinates":[10.5683403015,50.0838394165],"type":"Point"}
}