{
  "type": "Feature",
  "properties": {
    "iso:country":"DE",
    "sg:address":"Schilderstr. 46",
    "sg:city":"Goslar",
    "sg:phone":"+49 5321/22671",
    "sg:postcode":"38640",
    "sg:province":"Niedersachsen",
    "wof:name":"Heinrich Grope",
    "wof:placetype":"venue"
},
  "geometry": {"coordinates":[10.4240856171,51.9073791504],"type":"Point"}
}