{
  "type": "Feature",
  "properties": {
    "iso:country":"DE",
    "sg:address":"Am Kessberg 5",
    "sg:city":"Salzkotten",
    "sg:phone":"+49 2955/1072",
    "sg:postcode":"33154",
    "sg:province":"Nordrhein-Westfalen",
    "wof:name":"Fristein Vertrieb",
    "wof:placetype":"venue"
},
  "geometry": {"coordinates":[8.67442,51.631481],"type":"Point"}
}