{
  "type": "Feature",
  "properties": {
    "iso:country":"DE",
    "sg:address":"Bertolt-Brecht-Str. 19",
    "sg:city":"Rostock",
    "sg:phone":"+49 381/7620239",
    "sg:postcode":"18106",
    "sg:province":"Mecklenburg-Vorpommern",
    "wof:name":"Modefrisur Gmbh",
    "wof:placetype":"venue"
},
  "geometry": {"coordinates":[12.058045,54.123356],"type":"Point"}
}