{
  "type": "Feature",
  "properties": {
    "iso:country":"DE",
    "sg:address":"Malas 8- 16",
    "sg:city":"Oberstaufen",
    "sg:phone":"+49 8386/7000",
    "sg:postcode":"87534",
    "sg:province":"Bayern",
    "wof:name":"Metro Ferienclub",
    "wof:placetype":"venue"
},
  "geometry": {"coordinates":[10.0147161484,47.5478935242],"type":"Point"}
}