{
  "type": "Feature",
  "properties": {
    "iso:country":"DE",
    "sg:address":"Hauptstr. 44",
    "sg:city":"Ruhpolding",
    "sg:phone":"+49 8663/5024",
    "sg:postcode":"83324",
    "sg:province":"Bayern",
    "wof:name":"Maria Craatz",
    "wof:placetype":"venue"
},
  "geometry": {"coordinates":[12.64603,47.762932],"type":"Point"}
}