{
  "type": "Feature",
  "properties": {
    "iso:country":"DE",
    "sg:address":"Gie\u00dfener Str. 18-28",
    "sg:city":"Bad Vilbel",
    "sg:phone":"+49 6101/4030",
    "sg:postcode":"61118",
    "sg:province":"Hessen",
    "wof:name":"Wilhelm Reuschling Gmbh",
    "wof:placetype":"venue"
},
  "geometry": {"coordinates":[8.7445402145,50.1888999939],"type":"Point"}
}