{
  "type": "Feature",
  "properties": {
    "iso:country":"DE",
    "sg:address":"Schubertstr. 1",
    "sg:city":"Castrop-Rauxel",
    "sg:phone":"+49 2305/13812",
    "sg:postcode":"44575",
    "sg:province":"Nordrhein-Westfalen",
    "wof:name":"Erwin Sawatzki Architekt",
    "wof:placetype":"venue"
},
  "geometry": {"coordinates":[7.30943,51.554352],"type":"Point"}
}