{
  "type": "Feature",
  "properties": {
    "iso:country":"DE",
    "sg:address":"Zum Pier 60A",
    "sg:city":"L\u00fcnen",
    "sg:phone":"+49 231/9873030",
    "sg:postcode":"44536",
    "sg:province":"Nordrhein-Westfalen",
    "wof:name":"Trace Tec Begleitheizungstechnik Gmbh",
    "wof:placetype":"venue"
},
  "geometry": {"coordinates":[7.459279,51.603443],"type":"Point"}
}