{
  "type": "Feature",
  "properties": {
    "iso:country":"DE",
    "sg:address":"Kernenweg 36",
    "sg:city":"Esslingen",
    "sg:phone":"+49 711/9371551",
    "sg:postcode":"73732",
    "sg:province":"Baden-W\u00fcrttemberg",
    "wof:name":"Dr. Med. Claudia De Laporte",
    "wof:placetype":"venue"
},
  "geometry": {"coordinates":[9.316160202,48.7556381226],"type":"Point"}
}