{
  "type": "Feature",
  "properties": {
    "iso:country":"DE",
    "sg:address":"Fresenbergstr. 37",
    "sg:city":"Bremen",
    "sg:phone":"+49 421/601540",
    "sg:postcode":"28779",
    "sg:province":"Bremen",
    "wof:name":"Karl-heinz Eichler",
    "wof:placetype":"venue"
},
  "geometry": {"coordinates":[8.5726642609,53.1838569641],"type":"Point"}
}