{
  "type": "Feature",
  "properties": {
    "iso:country":"DE",
    "sg:address":"Ziegelstr. 3",
    "sg:city":"G\u00f6ppingen",
    "sg:phone":"+49 7161/686285",
    "sg:postcode":"73033",
    "sg:province":"Baden-W\u00fcrttemberg",
    "wof:name":"Friedrich Rauschnabel",
    "wof:placetype":"venue"
},
  "geometry": {"coordinates":[9.65685,48.705677],"type":"Point"}
}