{
  "type": "Feature",
  "properties": {
    "iso:country":"DE",
    "sg:address":"Schwarzwaldstr. 3",
    "sg:city":"Singen",
    "sg:phone":"+49 7731/61755",
    "sg:postcode":"78224",
    "sg:province":"Baden-W\u00fcrttemberg",
    "wof:name":"Schwarzwald-apotheke",
    "wof:placetype":"venue"
},
  "geometry": {"coordinates":[8.837891,47.760971],"type":"Point"}
}