{
  "type": "Feature",
  "properties": {
    "iso:country":"DE",
    "sg:address":"Am B\u00e4ckeranger 6",
    "sg:city":"Marzling",
    "sg:phone":"+49 8161/61781",
    "sg:postcode":"85417",
    "sg:province":"Bayern",
    "wof:name":"Dinko Dolic Ingenieur",
    "wof:placetype":"venue"
},
  "geometry": {"coordinates":[11.7913856506,48.4094200134],"type":"Point"}
}