{
  "type": "Feature",
  "properties": {
    "iso:country":"DE",
    "sg:address":"Sigefridwall 25",
    "sg:city":"Soest",
    "sg:postcode":"59494",
    "sg:province":"Nordrhein-Westfalen",
    "wof:name":"Hanlen Hauser Kg",
    "wof:placetype":"venue"
},
  "geometry": {"coordinates":[8.11859,51.57222],"type":"Point"}
}