{
  "type": "Feature",
  "properties": {
    "iso:country":"DE",
    "sg:address":"Kohlh\u00e4user Str. 71",
    "sg:city":"Fulda",
    "sg:phone":"+49 661/42882",
    "sg:postcode":"36043",
    "sg:province":"Hessen",
    "wof:name":"Pentagast Marketing Und Dienstleistungsges. Mbh",
    "wof:placetype":"venue"
},
  "geometry": {"coordinates":[9.6834306717,50.5313568115],"type":"Point"}
}