{
  "type": "Feature",
  "properties": {
    "iso:country":"DE",
    "sg:address":"Riepackerstr. 7",
    "sg:city":"Helpsen",
    "sg:phone":"+49 5724/98405",
    "sg:postcode":"31691",
    "sg:province":"Niedersachsen",
    "wof:name":"Michael Roehner",
    "wof:placetype":"venue"
},
  "geometry": {"coordinates":[9.1173419952,52.3129005432],"type":"Point"}
}