{
  "type": "Feature",
  "properties": {
    "iso:country":"DE",
    "sg:address":"Martinstr. 4",
    "sg:city":"Blaustein",
    "sg:phone":"+49 7304/96140",
    "sg:postcode":"89134",
    "sg:province":"Baden-W\u00fcrttemberg",
    "wof:name":"Otto Braunm\u00fcller Architekt",
    "wof:placetype":"venue"
},
  "geometry": {"coordinates":[9.921016,48.416035],"type":"Point"}
}