{
  "type": "Feature",
  "properties": {
    "iso:country":"DE",
    "sg:address":"Kirchweg 145",
    "sg:city":"Henstedt-Ulzburg",
    "sg:phone":"+49 4193/5274",
    "sg:postcode":"24558",
    "sg:province":"Schleswig-Holstein",
    "wof:name":"Karl-heinz Breunle",
    "wof:placetype":"venue"
},
  "geometry": {"coordinates":[9.9773492813,53.8080062866],"type":"Point"}
}