{
  "type": "Feature",
  "properties": {
    "iso:country":"DE",
    "sg:address":"Blankeneser Bahnhofstr 27",
    "sg:city":"Hamburg",
    "sg:phone":"+49 40/86663978",
    "sg:postcode":"22587",
    "sg:province":"Hamburg",
    "wof:name":"B\u00e4rbel Rottmann Rechtsanw\u00e4ltin",
    "wof:placetype":"venue"
},
  "geometry": {"coordinates":[9.8122854233,53.5628013611],"type":"Point"}
}