{
  "type": "Feature",
  "properties": {
    "iso:country":"DE",
    "sg:address":"Bruckhauser Str. 84",
    "sg:city":"Duisburg",
    "sg:phone":"+49 203/463943",
    "sg:postcode":"47139",
    "sg:province":"Nordrhein-Westfalen",
    "wof:name":"Kessemeier K\u00e4lte- Und Klimatechnik Gmbh",
    "wof:placetype":"venue"
},
  "geometry": {"coordinates":[6.7385678291,51.4793739319],"type":"Point"}
}