{
  "type": "Feature",
  "properties": {
    "iso:country":"DE",
    "sg:address":"Lessingweg 41",
    "sg:city":"Wiesbaden",
    "sg:phone":"+49 6122/941747",
    "sg:postcode":"65205",
    "sg:province":"Hessen",
    "wof:name":"B. Noll Finanzberater",
    "wof:placetype":"venue"
},
  "geometry": {"coordinates":[8.337600708,50.0622673035],"type":"Point"}
}