{
  "type": "Feature",
  "properties": {
    "iso:country":"DE",
    "sg:address":"Flandernstr. 74",
    "sg:city":"Winterlingen",
    "sg:phone":"+49 7434/1003",
    "sg:postcode":"72474",
    "sg:province":"Baden-W\u00fcrttemberg",
    "wof:name":"Eva B. Bitzer Gmbh",
    "wof:placetype":"venue"
},
  "geometry": {"coordinates":[9.111381,48.182217],"type":"Point"}
}