{
  "type": "Feature",
  "properties": {
    "iso:country":"DE",
    "sg:address":"Heiligenweg 21",
    "sg:city":"Koblenz",
    "sg:phone":"+49 261/947000",
    "sg:postcode":"56073",
    "sg:province":"Rheinland-Pfalz",
    "wof:name":"Alfons M\u00fcller Gmbh",
    "wof:placetype":"venue"
},
  "geometry": {"coordinates":[7.562912941,50.3524131775],"type":"Point"}
}