{
  "type": "Feature",
  "properties": {
    "iso:country":"DE",
    "sg:address":"Marientaler Str.",
    "sg:city":"Helmstedt",
    "sg:postcode":"38350",
    "sg:province":"Niedersachsen",
    "wof:name":"D\u00f6hring Grundst\u00fccks- Erschlie\u00dfungs Gmbh & Co. Kg",
    "wof:placetype":"venue"
},
  "geometry": {"coordinates":[10.9981498718,52.2437744141],"type":"Point"}
}