{
  "type": "Feature",
  "properties": {
    "iso:country":"DE",
    "sg:address":"Ballindamm 13",
    "sg:city":"Hamburg",
    "sg:phone":"+49 40/354142",
    "sg:postcode":"20095",
    "sg:province":"Hamburg",
    "wof:name":"Rocco-schallplatten Gbr F. Eitze Und H. Pickardt",
    "wof:placetype":"venue"
},
  "geometry": {"coordinates":[9.9990272522,53.5542373657],"type":"Point"}
}