{
  "type": "Feature",
  "properties": {
    "iso:country":"DE",
    "sg:address":"Hubert-M\u00fcller-Str. 109",
    "sg:city":"Saarbr\u00fccken",
    "sg:phone":"+49 681/792299",
    "sg:postcode":"66115",
    "sg:province":"Saarland",
    "wof:name":"Stibbi",
    "wof:placetype":"venue"
},
  "geometry": {"coordinates":[6.9514369965,49.2445755005],"type":"Point"}
}