{
  "type": "Feature",
  "properties": {
    "iso:country":"DE",
    "sg:address":"Renzel 1",
    "sg:city":"Varrel",
    "sg:phone":"+49 4274/621",
    "sg:postcode":"27259",
    "sg:province":"Niedersachsen",
    "wof:name":"Hartmut Ehm",
    "wof:placetype":"venue"
},
  "geometry": {"coordinates":[8.727452,52.577496],"type":"Point"}
}