{
  "type": "Feature",
  "properties": {
    "iso:country":"DE",
    "sg:address":"Burgstr. 22",
    "sg:city":"Rochlitz",
    "sg:phone":"+49 3737/41693",
    "sg:postcode":"09306",
    "sg:province":"Sachsen",
    "wof:name":"Eiscafe",
    "wof:placetype":"venue"
},
  "geometry": {"coordinates":[12.796487,51.045708],"type":"Point"}
}