{
  "type": "Feature",
  "properties": {
    "iso:country":"DE",
    "sg:address":"Am Langen Graben 33",
    "sg:city":"D\u00fcren",
    "sg:phone":"+49 2421/91470",
    "sg:postcode":"52353",
    "sg:province":"Nordrhein-Westfalen",
    "wof:name":"Juro Tore-bauelemente Gmbh",
    "wof:placetype":"venue"
},
  "geometry": {"coordinates":[6.467417,50.831913],"type":"Point"}
}