{
  "type": "Feature",
  "properties": {
    "iso:country":"DE",
    "sg:address":"Frauenstr. 26",
    "sg:city":"Pfaffenhofen",
    "sg:phone":"+49 8441/803234",
    "sg:postcode":"85276",
    "sg:province":"Bayern",
    "wof:name":"Bekleidungshaus Andreas Krieglmeier",
    "wof:placetype":"venue"
},
  "geometry": {"coordinates":[11.509292,48.530396],"type":"Point"}
}