{
  "type": "Feature",
  "properties": {
    "iso:country":"DE",
    "sg:address":"Lindwurmstr. 1",
    "sg:city":"M\u00fcnchen",
    "sg:phone":"+49 89/2609523",
    "sg:postcode":"80337",
    "sg:province":"Bayern",
    "wof:name":"Pianohaus Carl Hirsch",
    "wof:placetype":"venue"
},
  "geometry": {"coordinates":[11.5659809113,48.1329460144],"type":"Point"}
}