{
  "type": "Feature",
  "properties": {
    "iso:country":"DE",
    "sg:address":"Erasmusstr 14",
    "sg:city":"Essen",
    "sg:postcode":"45279",
    "sg:province":"Nordrhein-Westfalen",
    "wof:name":"Eileen Privat - Sex, Erotic, Erotik, Ficken, Bumse",
    "wof:placetype":"venue"
},
  "geometry": {"coordinates":[7.106452,51.447433],"type":"Point"}
}