{
  "type": "Feature",
  "properties": {
    "iso:country":"DE",
    "sg:address":"Saarbr\u00fccker Str. 131",
    "sg:city":"Bous",
    "sg:postcode":"66359",
    "sg:province":"Saarland",
    "wof:name":"Spi Haustechnik Gmbh",
    "wof:placetype":"venue"
},
  "geometry": {"coordinates":[6.7910079956,49.2782821655],"type":"Point"}
}