{
  "type": "Feature",
  "properties": {
    "iso:country":"DE",
    "sg:address":"Am Schneller 66",
    "sg:city":"Erkelenz",
    "sg:phone":"+49 2431/72820",
    "sg:postcode":"41812",
    "sg:province":"Nordrhein-Westfalen",
    "wof:name":"Energietechnik Evertz Erkelenz Gmbh",
    "wof:placetype":"venue"
},
  "geometry": {"coordinates":[6.3075151443,51.0702896118],"type":"Point"}
}