{
  "type": "Feature",
  "properties": {
    "iso:country":"DE",
    "sg:address":"Leerbachstr. 115",
    "sg:city":"Frankfurt",
    "sg:phone":"+49 69/2740290",
    "sg:postcode":"60322",
    "sg:province":"Hessen",
    "wof:name":"Christel Koch Immobilien E. K.",
    "wof:placetype":"venue"
},
  "geometry": {"coordinates":[8.6714839935,50.1241874695],"type":"Point"}
}