{
  "type": "Feature",
  "properties": {
    "iso:country":"DE",
    "sg:address":"Ludwigstr. 2",
    "sg:city":"Oberstdorf",
    "sg:phone":"+49 8322/5229",
    "sg:postcode":"87561",
    "sg:province":"Bayern",
    "wof:name":"Paula Schnell Gmbh Damenmoden",
    "wof:placetype":"venue"
},
  "geometry": {"coordinates":[10.279133,47.406113],"type":"Point"}
}