{
  "type": "Feature",
  "properties": {
    "iso:country":"DE",
    "sg:address":"Wartburg 8",
    "sg:city":"Lengefeld",
    "sg:phone":"+49 37367/82310",
    "sg:postcode":"09514",
    "sg:province":"Sachsen",
    "wof:name":"Wartburg Im Fl\u00f6hatal",
    "wof:placetype":"venue"
},
  "geometry": {"coordinates":[13.1944799423,50.7411804199],"type":"Point"}
}