{
  "type": "Feature",
  "properties": {
    "iso:country":"DE",
    "sg:address":"Altenburger Str. 1",
    "sg:city":"Haselbach",
    "sg:phone":"+49 34343/52638",
    "sg:postcode":"04617",
    "sg:province":"Th\u00fcringen",
    "wof:name":"Elremo Gmbh",
    "wof:placetype":"venue"
},
  "geometry": {"coordinates":[12.436986,51.067154],"type":"Point"}
}