{
  "type": "Feature",
  "properties": {
    "iso:country":"DE",
    "sg:address":"Ruhrstr. 5",
    "sg:city":"Mannheim",
    "sg:phone":"+49 621/333933",
    "sg:postcode":"68167",
    "sg:province":"Baden-W\u00fcrttemberg",
    "wof:name":"Roswitha Henz-best Rechtsanw\u00e4ltin",
    "wof:placetype":"venue"
},
  "geometry": {"coordinates":[8.4869499207,49.4989433289],"type":"Point"}
}