{
  "type": "Feature",
  "properties": {
    "iso:country":"DE",
    "sg:address":"Allmendstr. 10",
    "sg:city":"Ettlingen",
    "sg:phone":"+49 7243/52000",
    "sg:postcode":"76275",
    "sg:province":"Baden-W\u00fcrttemberg",
    "wof:name":"H\u00e4ffner Gmbh",
    "wof:placetype":"venue"
},
  "geometry": {"coordinates":[8.4323568344,48.9065093994],"type":"Point"}
}