{
  "type": "Feature",
  "properties": {
    "iso:country":"DE",
    "sg:address":"Ernst-Th\u00e4lmann-Str. 21",
    "sg:city":"P\u00f6\u00dfneck",
    "sg:phone":"+49 3647",
    "sg:postcode":"07381",
    "sg:province":"Th\u00fcringen",
    "wof:name":"Webagentur Sokline",
    "wof:placetype":"venue"
},
  "geometry": {"coordinates":[11.593812,50.697247],"type":"Point"}
}