{
  "type": "Feature",
  "properties": {
    "iso:country":"DE",
    "sg:address":"Gartenstr. 5",
    "sg:city":"Gro\u00dferlach",
    "sg:phone":"+49 7903/2587",
    "sg:postcode":"71577",
    "sg:province":"Baden-W\u00fcrttemberg",
    "wof:name":"Roland Weber",
    "wof:placetype":"venue"
},
  "geometry": {"coordinates":[9.517708,49.054115],"type":"Point"}
}