{
  "type": "Feature",
  "properties": {
    "iso:country":"DE",
    "sg:address":"Frankfurter Ring 227",
    "sg:city":"M\u00fcnchen",
    "sg:phone":"+49 89/381801",
    "sg:postcode":"80807",
    "sg:province":"Bayern",
    "wof:name":"Bayerisches Leichtmetallwerk Graf Bl\u00fccher Von Wahlstatt",
    "wof:placetype":"venue"
},
  "geometry": {"coordinates":[11.6034908295,48.186958313],"type":"Point"}
}