{
  "type": "Feature",
  "properties": {
    "iso:country":"DE",
    "sg:address":"Aschaffenburger Str. 17 B",
    "sg:city":"Goldbach",
    "sg:phone":"+49 6021/53081",
    "sg:postcode":"63773",
    "sg:province":"Bayern",
    "wof:name":"Dft Deutsche Fl\u00e4chen-technik Latexfalt Gmbh",
    "wof:placetype":"venue"
},
  "geometry": {"coordinates":[9.1761198044,49.9950866699],"type":"Point"}
}