{
  "type": "Feature",
  "properties": {
    "iso:country":"DE",
    "sg:address":"Am Heidenstock 8",
    "sg:city":"Mainaschaff",
    "sg:phone":"+49 6021/780662",
    "sg:postcode":"63814",
    "sg:province":"Bayern",
    "wof:name":"Dirk D\u00e4fler",
    "wof:placetype":"venue"
},
  "geometry": {"coordinates":[9.0881795883,49.9846916199],"type":"Point"}
}