{
  "type": "Feature",
  "properties": {
    "iso:country":"DE",
    "sg:address":"Beekscher Weg 37",
    "sg:city":"Xanten",
    "sg:phone":"+49 2801/1754",
    "sg:postcode":"46509",
    "sg:province":"Nordrhein-Westfalen",
    "wof:name":"Alois Hungerkamp",
    "wof:placetype":"venue"
},
  "geometry": {"coordinates":[6.438256,51.682281],"type":"Point"}
}