{
  "type": "Feature",
  "properties": {
    "iso:country":"DE",
    "sg:address":"Kirchenort 30",
    "sg:city":"Ostseebad Prerow",
    "sg:postcode":"18375",
    "sg:province":"Mecklenburg-Vorpommern",
    "wof:name":"Ev.-luth. Kirche",
    "wof:placetype":"venue"
},
  "geometry": {"coordinates":[12.5870580673,54.448589325],"type":"Point"}
}