{
  "type": "Feature",
  "properties": {
    "iso:country":"DE",
    "sg:address":"Bischof-Wedekin-Str. 5",
    "sg:city":"Bad Salzdetfurth",
    "sg:phone":"+49 5064/1258",
    "sg:postcode":"31162",
    "sg:province":"Niedersachsen",
    "wof:name":"Dieter Severit",
    "wof:placetype":"venue"
},
  "geometry": {"coordinates":[10.0224847794,52.0940246582],"type":"Point"}
}