{
  "type": "Feature",
  "properties": {
    "iso:country":"DE",
    "sg:address":"Marie-Curie-Str. 6 Send",
    "sg:city":"Gro\u00df-Umstadt",
    "sg:phone":"+49 4960/7873396",
    "sg:postcode":"64823",
    "sg:province":"Hessen",
    "wof:name":"Joachim Kemmer",
    "wof:placetype":"venue"
},
  "geometry": {"coordinates":[8.9303026199,49.8650665283],"type":"Point"}
}