{
  "type": "Feature",
  "properties": {
    "iso:country":"DE",
    "sg:address":"Ludwig-Behr-Str. 16",
    "sg:city":"Tutzing",
    "sg:phone":"+49 8158/6239",
    "sg:postcode":"82327",
    "sg:province":"Bayern",
    "wof:name":"Peter Br\u00e4uninger Ingenieur",
    "wof:placetype":"venue"
},
  "geometry": {"coordinates":[11.2800340652,47.9179611206],"type":"Point"}
}