{
  "type": "Feature",
  "properties": {
    "iso:country":"DE",
    "sg:address":"Angerstr. 1",
    "sg:city":"Zwiesel",
    "sg:postcode":"94227",
    "sg:province":"Bayern",
    "wof:name":"Bavaria Projekt Gmbh & Co. Kg",
    "wof:placetype":"venue"
},
  "geometry": {"coordinates":[13.22737,49.012589],"type":"Point"}
}