{
  "type": "Feature",
  "properties": {
    "iso:country":"DE",
    "sg:address":"Blumenstr. 4a",
    "sg:city":"Hohberg",
    "sg:postcode":"77749",
    "sg:province":"Baden-W\u00fcrttemberg",
    "wof:name":"Boservice - Der Ortenauer Edv-dienstleister",
    "wof:placetype":"venue"
},
  "geometry": {"coordinates":[7.897236,48.411568],"type":"Point"}
}