{
  "type": "Feature",
  "properties": {
    "iso:country":"DE",
    "sg:address":"Karlsruher Str. 87A",
    "sg:city":"Pforzheim",
    "sg:postcode":"75179",
    "sg:province":"Baden-W\u00fcrttemberg",
    "wof:name":"F. Lawall",
    "wof:placetype":"venue"
},
  "geometry": {"coordinates":[8.654831,48.904041],"type":"Point"}
}