{
  "type": "Feature",
  "properties": {
    "iso:country":"DE",
    "sg:address":"Fichtestr. 1 a",
    "sg:city":"Bautzen",
    "sg:postcode":"02625",
    "sg:province":"Sachsen",
    "wof:name":"Professional Multimedia Network Systems Gmbh",
    "wof:placetype":"venue"
},
  "geometry": {"coordinates":[14.4409751892,51.1807441711],"type":"Point"}
}