{
  "type": "Feature",
  "properties": {
    "iso:country":"DE",
    "sg:address":"Sternbuschweg 252",
    "sg:city":"Duisburg",
    "sg:phone":"+49 203/377133",
    "sg:postcode":"47057",
    "sg:province":"Nordrhein-Westfalen",
    "wof:name":"F. Schr\u00f6der",
    "wof:placetype":"venue"
},
  "geometry": {"coordinates":[6.782807827,51.4199867249],"type":"Point"}
}