{
  "type": "Feature",
  "properties": {
    "iso:country":"DE",
    "sg:address":"Am Stadtgarten 9",
    "sg:city":"Castrop-Rauxel",
    "sg:phone":"+49 2305/544487",
    "sg:postcode":"44575",
    "sg:province":"Nordrhein-Westfalen",
    "wof:name":"A.heimann Rechtsanw\u00e4ltin",
    "wof:placetype":"venue"
},
  "geometry": {"coordinates":[7.3140358925,51.5442466736],"type":"Point"}
}