{
  "type": "Feature",
  "properties": {
    "iso:country":"DE",
    "sg:address":"Rosenstr. 25",
    "sg:city":"Lohfelden",
    "sg:phone":"+49 561/513726",
    "sg:postcode":"34253",
    "sg:province":"Hessen",
    "wof:name":"Herbert Brede",
    "wof:placetype":"venue"
},
  "geometry": {"coordinates":[9.527467,51.263847],"type":"Point"}
}