{
  "type": "Feature",
  "properties": {
    "iso:country":"DE",
    "sg:address":"Siemensstr. 7",
    "sg:city":"Bad Pyrmont",
    "sg:phone":"+49 5281/9450",
    "sg:postcode":"31812",
    "sg:province":"Niedersachsen",
    "wof:name":"Kurt Neumann Gmbh & Co.",
    "wof:placetype":"venue"
},
  "geometry": {"coordinates":[9.2797002792,51.9753417969],"type":"Point"}
}