{
  "type": "Feature",
  "properties": {
    "iso:country":"DE",
    "sg:address":"Gabelsbergerstr. 3",
    "sg:city":"N\u00fcrnberg",
    "sg:phone":"+49 911/447393",
    "sg:postcode":"90459",
    "sg:province":"Bayern",
    "wof:name":"A. Kircher",
    "wof:placetype":"venue"
},
  "geometry": {"coordinates":[11.078729,49.439651],"type":"Point"}
}