{
  "type": "Feature",
  "properties": {
    "iso:country":"DE",
    "sg:address":"Drinhausen 20 a",
    "sg:city":"Asbach",
    "sg:postcode":"53567",
    "sg:province":"Rheinland-Pfalz",
    "wof:name":"Itc International Trade Consulting",
    "wof:placetype":"venue"
},
  "geometry": {"coordinates":[7.4118189812,50.6616363525],"type":"Point"}
}