{
  "type": "Feature",
  "properties": {
    "iso:country":"DE",
    "sg:address":"Tr\u00e4nkweg 17",
    "sg:city":"Bonn",
    "sg:phone":"+49 228/482307",
    "sg:postcode":"53229",
    "sg:province":"Nordrhein-Westfalen",
    "wof:name":"Hans Sch\u00fcttler",
    "wof:placetype":"venue"
},
  "geometry": {"coordinates":[7.1839141846,50.7353477478],"type":"Point"}
}