{
  "type": "Feature",
  "properties": {
    "iso:country":"DE",
    "sg:address":"Eppichmauergasse 6",
    "sg:city":"Mainz",
    "sg:phone":"+49 6131/613234",
    "sg:postcode":"55116",
    "sg:province":"Rheinland-Pfalz",
    "wof:name":"Sanit\u00e4tshaus Conrad Gmbh",
    "wof:placetype":"venue"
},
  "geometry": {"coordinates":[8.2706613541,49.9971237183],"type":"Point"}
}