{
  "type": "Feature",
  "properties": {
    "iso:country":"DE",
    "sg:address":"Z\u00f6llerstr. 22",
    "sg:city":"Dexheim",
    "sg:phone":"+49 6133/58953",
    "sg:postcode":"55278",
    "sg:province":"Rheinland-Pfalz",
    "wof:name":"Fritz Dahlem",
    "wof:placetype":"venue"
},
  "geometry": {"coordinates":[8.314789772,49.8472557068],"type":"Point"}
}