{
  "type": "Feature",
  "properties": {
    "iso:country":"DE",
    "sg:address":"Chemieparkstr",
    "sg:city":"Bitterfeld",
    "sg:phone":"+49 3493/76284",
    "sg:postcode":"06749",
    "sg:province":"Sachsen-Anhalt",
    "wof:name":"Unit Handels- U. Servicegesellschaft Mbh",
    "wof:placetype":"venue"
},
  "geometry": {"coordinates":[12.3073101044,51.6256408691],"type":"Point"}
}