{
  "type": "Feature",
  "properties": {
    "iso:country":"DE",
    "sg:address":"G\u00f6thener Str. 9",
    "sg:city":"Bahrenborstel",
    "sg:phone":"+49 4273/1434",
    "sg:postcode":"27245",
    "sg:province":"Niedersachsen",
    "wof:name":"Erwin Scholz Schwei\u00dftechnik Gmbh",
    "wof:placetype":"venue"
},
  "geometry": {"coordinates":[8.8154420853,52.5685501099],"type":"Point"}
}