{
  "type": "Feature",
  "properties": {
    "iso:country":"DE",
    "sg:address":"Detmolder Str. 249",
    "sg:city":"Lage",
    "sg:phone":"+49 5232/3881",
    "sg:postcode":"32791",
    "sg:province":"Nordrhein-Westfalen",
    "wof:name":"Lothar Pott Zimmerei Und Bautischlerei Gmbh",
    "wof:placetype":"venue"
},
  "geometry": {"coordinates":[8.8099098206,51.9821395874],"type":"Point"}
}