{
  "type": "Feature",
  "properties": {
    "iso:country":"DE",
    "sg:address":"Untere K\u00f6nigsstr. 86",
    "sg:city":"Kassel",
    "sg:phone":"+49 561/780770",
    "sg:postcode":"34117",
    "sg:province":"Hessen",
    "wof:name":"Camp Und Tramp Inh. Rainer Feltz",
    "wof:placetype":"venue"
},
  "geometry": {"coordinates":[9.502083,51.320225],"type":"Point"}
}