{
  "type": "Feature",
  "properties": {
    "iso:country":"DE",
    "sg:address":"Riedemannweg 16",
    "sg:city":"Berlin",
    "sg:phone":"+49 30/3449039",
    "sg:postcode":"13627",
    "sg:province":"Berlin",
    "wof:name":"Ingenieurb\u00fcro Stoll & Partner Gmbh",
    "wof:placetype":"venue"
},
  "geometry": {"coordinates":[13.3150691986,52.5465087891],"type":"Point"}
}