{
  "type": "Feature",
  "properties": {
    "iso:country":"DE",
    "sg:address":"Hermstedter Str. 105",
    "sg:city":"Apolda",
    "sg:phone":"+49 3644/562366",
    "sg:postcode":"99510",
    "sg:province":"Th\u00fcringen",
    "wof:name":"Kurt Weyh",
    "wof:placetype":"venue"
},
  "geometry": {"coordinates":[11.522805,51.017475],"type":"Point"}
}