{
  "type": "Feature",
  "properties": {
    "iso:country":"DE",
    "sg:address":"Waldseer Str. 92b",
    "sg:city":"Schifferstadt",
    "sg:phone":"+49 6235/5298",
    "sg:postcode":"67105",
    "sg:province":"Rheinland-Pfalz",
    "wof:name":"Blumenecke Schwind",
    "wof:placetype":"venue"
},
  "geometry": {"coordinates":[8.388331,49.384155],"type":"Point"}
}