{
  "type": "Feature",
  "properties": {
    "iso:country":"DE",
    "sg:city":"Epfendorf",
    "sg:phone":"+49 4974/04607",
    "sg:postcode":"78736",
    "sg:province":"Baden-W\u00fcrttemberg",
    "wof:name":"Kreissparkasse Rottweil",
    "wof:placetype":"venue"
},
  "geometry": {"coordinates":[8.597735,48.248371],"type":"Point"}
}