{
  "type": "Feature",
  "properties": {
    "iso:country":"DE",
    "sg:address":"Julius Ertel Str. 26",
    "sg:city":"Hamburg",
    "sg:phone":"+49 40/74200441",
    "sg:postcode":"21107",
    "sg:province":"Hamburg",
    "wof:name":"Fuegoflamenco",
    "wof:placetype":"venue"
},
  "geometry": {"coordinates":[9.983455658,53.5175552368],"type":"Point"}
}