{
  "type": "Feature",
  "properties": {
    "iso:country":"DE",
    "sg:address":"Lichtensteinstr. 40",
    "sg:city":"Villingen-Schwenningen",
    "sg:phone":"+49 7720/7065",
    "sg:postcode":"78056",
    "sg:province":"Baden-W\u00fcrttemberg",
    "wof:name":"Ludwig Schaible Kg",
    "wof:placetype":"venue"
},
  "geometry": {"coordinates":[8.5507297516,48.0624504089],"type":"Point"}
}