{
  "type": "Feature",
  "properties": {
    "iso:country":"DE",
    "sg:address":"Flughafenallee 26",
    "sg:city":"Bremen",
    "sg:postcode":"28199",
    "sg:province":"Bremen",
    "wof:name":"Systemchemie Gmbh",
    "wof:placetype":"venue"
},
  "geometry": {"coordinates":[8.787684,53.05212],"type":"Point"}
}