{
  "type": "Feature",
  "properties": {
    "iso:country":"DE",
    "sg:address":"Schlo\u00dfplatz 6 a",
    "sg:city":"Celle",
    "sg:phone":"+49 4951/417066",
    "sg:postcode":"29221",
    "sg:province":"Niedersachsen",
    "wof:name":"Norddeutsche Hypotheken-, Und Wechselbank Ag",
    "wof:placetype":"venue"
},
  "geometry": {"coordinates":[10.079363,52.623905],"type":"Point"}
}