{
  "type": "Feature",
  "properties": {
    "iso:country":"DE",
    "sg:address":"Scheffelstr. 23-31",
    "sg:city":"K\u00f6ln",
    "sg:phone":"+49 221/433729",
    "sg:postcode":"50935",
    "sg:province":"Nordrhein-Westfalen",
    "wof:name":"Alten- Und Pflegeheim Viktor-scheffel-haus",
    "wof:placetype":"venue"
},
  "geometry": {"coordinates":[6.909348,50.924892],"type":"Point"}
}