{
  "type": "Feature",
  "properties": {
    "iso:country":"DE",
    "sg:address":"Hauptstr. 26",
    "sg:city":"Impflingen",
    "sg:phone":"+49 6341/86529",
    "sg:postcode":"76831",
    "sg:province":"Rheinland-Pfalz",
    "wof:name":"Horst Petzoldt",
    "wof:placetype":"venue"
},
  "geometry": {"coordinates":[8.1122655869,49.1610183716],"type":"Point"}
}