{
  "type": "Feature",
  "properties": {
    "iso:country":"DE",
    "sg:address":"Br\u00fchlstr. 31",
    "sg:city":"Heubach",
    "sg:phone":"+49 7173/12255",
    "sg:postcode":"73540",
    "sg:province":"Baden-W\u00fcrttemberg",
    "wof:name":"Martin Koppold Heilpraktiker",
    "wof:placetype":"venue"
},
  "geometry": {"coordinates":[9.9316596985,48.7854576111],"type":"Point"}
}