{
  "type": "Feature",
  "properties": {
    "iso:country":"DE",
    "sg:address":"D\u00f6hlener Str. 25",
    "sg:city":"Dresden",
    "sg:phone":"+49 351/4218398",
    "sg:postcode":"01159",
    "sg:province":"Sachsen",
    "wof:name":"Ute Krumbiegel",
    "wof:placetype":"venue"
},
  "geometry": {"coordinates":[13.702703,51.040695],"type":"Point"}
}