{
  "type": "Feature",
  "properties": {
    "iso:country":"DE",
    "sg:address":"Altneudorfer Str. 49",
    "sg:city":"Sch\u00f6nau",
    "sg:phone":"+49 6228/8208",
    "sg:postcode":"69250",
    "sg:province":"Baden-W\u00fcrttemberg",
    "wof:name":"Willi J\u00f6rder",
    "wof:placetype":"venue"
},
  "geometry": {"coordinates":[8.8032569885,49.4663238525],"type":"Point"}
}