{
  "type": "Feature",
  "properties": {
    "iso:country":"DE",
    "sg:address":"Mendener Str 159",
    "sg:city":"Iserlohn",
    "sg:phone":"+49 2371/23909",
    "sg:postcode":"58636",
    "sg:province":"Nordrhein-Westfalen",
    "wof:name":"Bergfeld & Graumann",
    "wof:placetype":"venue"
},
  "geometry": {"coordinates":[7.714675,51.379059],"type":"Point"}
}