{
  "type": "Feature",
  "properties": {
    "iso:country":"DE",
    "sg:address":"Dachsweg 17",
    "sg:city":"K\u00f6ln",
    "sg:phone":"+49 221/501057",
    "sg:postcode":"50859",
    "sg:province":"Nordrhein-Westfalen",
    "wof:name":"Langer & Weber Inh. Hans-j\u00fcrgen Weber",
    "wof:placetype":"venue"
},
  "geometry": {"coordinates":[6.8252182007,50.9674377441],"type":"Point"}
}