{
  "type": "Feature",
  "properties": {
    "iso:country":"DE",
    "sg:address":"Rudolf-Breitscheid-Str. 7",
    "sg:city":"Weimar",
    "sg:phone":"+49 3643/401496",
    "sg:postcode":"99423",
    "sg:province":"Th\u00fcringen",
    "wof:name":"Dr. Thiele Hausverwaltung Gmbh",
    "wof:placetype":"venue"
},
  "geometry": {"coordinates":[11.3276109695,50.9737739563],"type":"Point"}
}