{
  "type": "Feature",
  "properties": {
    "iso:country":"DE",
    "sg:address":"Zum Eisenhammer 18a",
    "sg:city":"Oberhausen",
    "sg:phone":"+49 208/202050",
    "sg:postcode":"46049",
    "sg:province":"Nordrhein-Westfalen",
    "wof:name":"Koch-fenstertechnik",
    "wof:placetype":"venue"
},
  "geometry": {"coordinates":[6.847129,51.483772],"type":"Point"}
}