{
  "type": "Feature",
  "properties": {
    "iso:country":"DE",
    "sg:address":"Zum Erlenbusch 4",
    "sg:city":"M\u00fcnster",
    "sg:phone":"+49 251/616456",
    "sg:postcode":"48167",
    "sg:province":"Nordrhein-Westfalen",
    "wof:name":"Elisabeth Lachmann Masseurin",
    "wof:placetype":"venue"
},
  "geometry": {"coordinates":[7.674219,51.925705],"type":"Point"}
}