{
  "type": "Feature",
  "properties": {
    "iso:country":"DE",
    "sg:address":"Ligastr. 50",
    "sg:city":"Regensburg",
    "sg:phone":"+49 941/35147",
    "sg:postcode":"93049",
    "sg:province":"Bayern",
    "wof:name":"Motion Events Gmbh",
    "wof:placetype":"venue"
},
  "geometry": {"coordinates":[12.0463466644,49.0176239014],"type":"Point"}
}