{
  "type": "Feature",
  "properties": {
    "iso:country":"DE",
    "sg:address":"Industriestr.",
    "sg:city":"Lorsch",
    "sg:postcode":"64653",
    "sg:province":"Hessen",
    "wof:name":"Drei K Office Furniture Distribution Gmbh",
    "wof:placetype":"venue"
},
  "geometry": {"coordinates":[8.571427,49.639576],"type":"Point"}
}