{
  "type": "Feature",
  "properties": {
    "iso:country":"DE",
    "sg:address":"Kirschenallee 39",
    "sg:city":"Grimmen",
    "sg:phone":"+49 38326/80311",
    "sg:postcode":"18507",
    "sg:province":"Mecklenburg-Vorpommern",
    "wof:name":"Heinz Kleemann",
    "wof:placetype":"venue"
},
  "geometry": {"coordinates":[13.0303,54.113243],"type":"Point"}
}