{
  "type": "Feature",
  "properties": {
    "iso:country":"DE",
    "sg:address":"Happinger-Au-Str. 21",
    "sg:city":"Rosenheim",
    "sg:phone":"+49 8031/62552",
    "sg:postcode":"83026",
    "sg:province":"Bayern",
    "wof:name":"Kurt M\u00fcller Ingenieur",
    "wof:placetype":"venue"
},
  "geometry": {"coordinates":[12.135764122,47.8343963623],"type":"Point"}
}