{
  "type": "Feature",
  "properties": {
    "iso:country":"DE",
    "sg:address":"Lange Str. 41",
    "sg:city":"Uslar",
    "sg:phone":"+49 5571/2455",
    "sg:postcode":"37170",
    "sg:province":"Niedersachsen",
    "wof:name":"Karlheinz Schreiber Elektroinstallation",
    "wof:placetype":"venue"
},
  "geometry": {"coordinates":[9.637496,51.659527],"type":"Point"}
}