{
  "type": "Feature",
  "properties": {
    "iso:country":"DE",
    "sg:address":"Falkenweg 6",
    "sg:city":"Taunusstein",
    "sg:phone":"+49 6128/945307",
    "sg:postcode":"65232",
    "sg:province":"Hessen",
    "wof:name":"Georg Kircher Heilpraktiker",
    "wof:placetype":"venue"
},
  "geometry": {"coordinates":[8.1462745667,50.1312065125],"type":"Point"}
}