{
  "type": "Feature",
  "properties": {
    "iso:country":"DE",
    "sg:address":"Schlo\u00dfstr. 2",
    "sg:city":"Marienheide",
    "sg:phone":"+49 2264/7468",
    "sg:postcode":"51709",
    "sg:province":"Nordrhein-Westfalen",
    "wof:name":"Raymund G\u00fcnther",
    "wof:placetype":"venue"
},
  "geometry": {"coordinates":[7.4713478088,51.053352356],"type":"Point"}
}