{
  "type": "Feature",
  "properties": {
    "iso:country":"DE",
    "sg:address":"Reichsstr. 9",
    "sg:city":"Donauw\u00f6rth",
    "sg:phone":"+49 906/3480",
    "sg:postcode":"86609",
    "sg:province":"Bayern",
    "wof:name":"Paco-dropart-parf\u00fcmerie- Cooperations-vertriebs- Und",
    "wof:placetype":"venue"
},
  "geometry": {"coordinates":[10.7801,48.718243],"type":"Point"}
}