{
  "type": "Feature",
  "properties": {
    "iso:country":"DE",
    "sg:address":"Fichtestr. 46",
    "sg:city":"Brieselang",
    "sg:phone":"+49 33232/36413",
    "sg:postcode":"14656",
    "sg:province":"Brandenburg",
    "wof:name":"Pension Letz",
    "wof:placetype":"venue"
},
  "geometry": {"coordinates":[12.9845991135,52.5926742554],"type":"Point"}
}