{
  "type": "Feature",
  "properties": {
    "iso:country":"DE",
    "sg:address":"Schlo\u00dfpark Wilhelmsh\u00f6he 15",
    "sg:city":"Kassel",
    "sg:phone":"+49 561/312460",
    "sg:postcode":"34131",
    "sg:province":"Hessen",
    "wof:name":"Cafe-restaurant Am Herkules Inh. R. Rahni\u00df",
    "wof:placetype":"venue"
},
  "geometry": {"coordinates":[9.4122562408,51.3204078674],"type":"Point"}
}