{
  "type": "Feature",
  "properties": {
    "iso:country":"DE",
    "sg:address":"Admiralit\u00e4tstr. 55",
    "sg:city":"Hamburg",
    "sg:phone":"+49 40/370040",
    "sg:postcode":"20459",
    "sg:province":"Hamburg",
    "wof:name":"Mabanaft Nordwest-europa Gmbh",
    "wof:placetype":"venue"
},
  "geometry": {"coordinates":[9.982731,53.546227],"type":"Point"}
}