{
  "type": "Feature",
  "properties": {
    "iso:country":"DE",
    "sg:address":"M\u00fchlenstr. 6",
    "sg:city":"Lippstadt",
    "sg:phone":"+49 2941/4377",
    "sg:postcode":"59555",
    "sg:province":"Nordrhein-Westfalen",
    "wof:name":"Parkhaus Lippstadt Gmbh",
    "wof:placetype":"venue"
},
  "geometry": {"coordinates":[8.3444004059,51.6768722534],"type":"Point"}
}