{
  "type": "Feature",
  "properties": {
    "iso:country":"DE",
    "sg:address":"Birkenweg 9i",
    "sg:city":"Barsb\u00fcttel",
    "sg:phone":"+49 40/67081555",
    "sg:postcode":"22885",
    "sg:province":"Schleswig-Holstein",
    "wof:name":"G\u00fcnter Ahrens",
    "wof:placetype":"venue"
},
  "geometry": {"coordinates":[10.1654109955,53.5721206665],"type":"Point"}
}