{
  "type": "Feature",
  "properties": {
    "iso:country":"DE",
    "sg:address":"Am Riedfeld 6",
    "sg:city":"Altom\u00fcnster",
    "sg:phone":"+49 8254/458",
    "sg:postcode":"85250",
    "sg:province":"Bayern",
    "wof:name":"Gasthaus Josef Koppold",
    "wof:placetype":"venue"
},
  "geometry": {"coordinates":[11.1912784576,48.3693237305],"type":"Point"}
}