{
  "type": "Feature",
  "properties": {
    "iso:country":"DE",
    "sg:address":"Erichstr. 1",
    "sg:city":"Hameln",
    "sg:phone":"+49 5151/7007",
    "sg:postcode":"31785",
    "sg:province":"Niedersachsen",
    "wof:name":"Haus & Grund Immobilien- Service Gmbh",
    "wof:placetype":"venue"
},
  "geometry": {"coordinates":[9.36632061,52.1000213623],"type":"Point"}
}