{
  "type": "Feature",
  "properties": {
    "iso:country":"DE",
    "sg:address":"Austr. 20",
    "sg:city":"Gottenheim",
    "sg:phone":"+49 7665/6526",
    "sg:postcode":"79288",
    "sg:province":"Baden-W\u00fcrttemberg",
    "wof:name":"Manfred Simon",
    "wof:placetype":"venue"
},
  "geometry": {"coordinates":[7.7357559204,48.050365448],"type":"Point"}
}