{
  "type": "Feature",
  "properties": {
    "iso:country":"DE",
    "sg:address":"Bruchweg 48",
    "sg:city":"Lemgo",
    "sg:phone":"+49 5261/4776",
    "sg:postcode":"32657",
    "sg:province":"Nordrhein-Westfalen",
    "wof:name":"Helmut Schal\u00fcck Tankstellen Gmbh",
    "wof:placetype":"venue"
},
  "geometry": {"coordinates":[8.9058923721,52.0314254761],"type":"Point"}
}