{
  "type": "Feature",
  "properties": {
    "iso:country":"DE",
    "sg:address":"Mettnaublick 12",
    "sg:city":"Singen",
    "sg:phone":"+49 7731/22486",
    "sg:postcode":"78224",
    "sg:province":"Baden-W\u00fcrttemberg",
    "wof:name":"Leo Prutscher Ingenieur",
    "wof:placetype":"venue"
},
  "geometry": {"coordinates":[8.9007024765,47.7242126465],"type":"Point"}
}