{
  "type": "Feature",
  "properties": {
    "iso:country":"DE",
    "sg:address":"Blumenthalstr. 85",
    "sg:city":"K\u00f6ln",
    "sg:phone":"+49 221/739495",
    "sg:postcode":"50668",
    "sg:province":"Nordrhein-Westfalen",
    "wof:name":"Hartmut Herbers",
    "wof:placetype":"venue"
},
  "geometry": {"coordinates":[6.9646539688,50.9553222656],"type":"Point"}
}