{
  "type": "Feature",
  "properties": {
    "iso:country":"DE",
    "sg:address":"Carl-Hertel-Str. 15",
    "sg:city":"Chemnitz",
    "sg:postcode":"09116",
    "sg:province":"Sachsen",
    "wof:name":"Landrock Fliesenleger Gmbh",
    "wof:placetype":"venue"
},
  "geometry": {"coordinates":[12.8729000092,50.8183250427],"type":"Point"}
}