{
  "type": "Feature",
  "properties": {
    "iso:country":"DE",
    "sg:address":"Rubensstr. 14",
    "sg:city":"M\u00fcnchen",
    "sg:phone":"+49 89/888219",
    "sg:postcode":"81245",
    "sg:province":"Bayern",
    "wof:name":"Dr. Anne K\u00f6hler",
    "wof:placetype":"venue"
},
  "geometry": {"coordinates":[11.447492,48.1572],"type":"Point"}
}