{
  "type": "Feature",
  "properties": {
    "iso:country":"DE",
    "sg:address":"Neue Anlage 34",
    "sg:city":"Schriesheim-Altenbach",
    "sg:phone":"+49 6220/6231",
    "sg:postcode":"69198",
    "sg:province":"Baden-W\u00fcrttemberg",
    "wof:name":"Klug Seminare F\u00fcr Edv In Schriesheim Bei Hd",
    "wof:placetype":"venue"
},
  "geometry": {"coordinates":[8.741951,49.488346],"type":"Point"}
}