{
  "type": "Feature",
  "properties": {
    "iso:country":"DE",
    "sg:address":"Wildunger Str. 4",
    "sg:city":"Waldeck",
    "sg:phone":"+49 5634/389",
    "sg:postcode":"34513",
    "sg:province":"Hessen",
    "wof:name":"Fritz Heinemann",
    "wof:placetype":"venue"
},
  "geometry": {"coordinates":[9.01787,51.240959],"type":"Point"}
}