{
  "type": "Feature",
  "properties": {
    "iso:country":"DE",
    "sg:address":"Lindenweg 1 a",
    "sg:city":"Oranienbaum",
    "sg:postcode":"06785",
    "sg:province":"Sachsen-Anhalt",
    "wof:name":"K. Vorwerk",
    "wof:placetype":"venue"
},
  "geometry": {"coordinates":[12.409348,51.803589],"type":"Point"}
}