{
  "type": "Feature",
  "properties": {
    "iso:country":"DE",
    "sg:address":"wen 13",
    "sg:city":"Brau",
    "sg:postcode":"38110",
    "sg:province":"Niedersachsen",
    "wof:name":"Ilse-soft Alles Was Man Braucht",
    "wof:placetype":"venue"
},
  "geometry": {"coordinates":[-90.048943,35.14962],"type":"Point"}
}