{
  "type": "Feature",
  "properties": {
    "iso:country":"DE",
    "sg:address":"Am Aspenhaag 2",
    "sg:city":"Kelsterbach",
    "sg:phone":"+49 6107/759986",
    "sg:postcode":"65451",
    "sg:province":"Hessen",
    "wof:name":"T. Henrich Kg Inh. Wolf J\u00fcrgen Kohaut",
    "wof:placetype":"venue"
},
  "geometry": {"coordinates":[8.544526,50.051041],"type":"Point"}
}