{
  "type": "Feature",
  "properties": {
    "iso:country":"DE",
    "sg:address":"Ulrich-Otto-Str. 5",
    "sg:city":"Plauen",
    "sg:phone":"+49 3741/709957",
    "sg:postcode":"08523",
    "sg:province":"Sachsen",
    "wof:name":"W\u00fcst & Six",
    "wof:placetype":"venue"
},
  "geometry": {"coordinates":[12.11585,50.497181],"type":"Point"}
}