{
  "type": "Feature",
  "properties": {
    "iso:country":"DE",
    "sg:address":"Marstall 6",
    "sg:city":"Ludwigsburg",
    "sg:postcode":"71634",
    "sg:province":"Baden-W\u00fcrttemberg",
    "wof:name":"First Class-eis Handelsges. F\u00fcr Speiseeisprodukte Mbh",
    "wof:placetype":"venue"
},
  "geometry": {"coordinates":[9.1920499802,48.9000892639],"type":"Point"}
}