{
  "type": "Feature",
  "properties": {
    "iso:country":"DE",
    "sg:address":"M\u00fchlweg 41",
    "sg:city":"H\u00f6rdt",
    "sg:phone":"+49 7272/2074",
    "sg:postcode":"76771",
    "sg:province":"Rheinland-Pfalz",
    "wof:name":"Alois B\u00f6hm",
    "wof:placetype":"venue"
},
  "geometry": {"coordinates":[8.31871,49.164719],"type":"Point"}
}