{
  "type": "Feature",
  "properties": {
    "iso:country":"DE",
    "sg:address":"An der Hasenbahn 3",
    "sg:city":"Celle",
    "sg:phone":"+49 5141/217225",
    "sg:postcode":"29225",
    "sg:province":"Niedersachsen",
    "wof:name":"Geber Intertabaco Gmbh",
    "wof:placetype":"venue"
},
  "geometry": {"coordinates":[10.0576820374,52.6083450317],"type":"Point"}
}