{
  "type": "Feature",
  "properties": {
    "iso:country":"DE",
    "sg:address":"Iddensener Dorfstr. 4",
    "sg:city":"Rosengarten",
    "sg:phone":"+49 4108/7198",
    "sg:postcode":"21224",
    "sg:province":"Niedersachsen",
    "wof:name":"Wilhelm Stemmann",
    "wof:placetype":"venue"
},
  "geometry": {"coordinates":[9.9118375778,53.3902320862],"type":"Point"}
}