{
  "type": "Feature",
  "properties": {
    "iso:country":"DE",
    "sg:address":"Keltenstr.",
    "sg:city":"Kall",
    "sg:phone":"+49 2441/6640",
    "sg:postcode":"53925",
    "sg:province":"Nordrhein-Westfalen",
    "wof:name":"M\u00f6bel Brucker Gmbh & Co. Kg",
    "wof:placetype":"venue"
},
  "geometry": {"coordinates":[6.5688052177,50.542098999],"type":"Point"}
}