{
  "type": "Feature",
  "properties": {
    "iso:country":"DE",
    "sg:address":"Im Eselsberg 60",
    "sg:city":"Schwaigern",
    "sg:phone":"+49 7138/7120",
    "sg:postcode":"74193",
    "sg:province":"Baden-W\u00fcrttemberg",
    "wof:name":"J. De Ponte",
    "wof:placetype":"venue"
},
  "geometry": {"coordinates":[9.0541172028,49.1480255127],"type":"Point"}
}