{
  "type": "Feature",
  "properties": {
    "iso:country":"DE",
    "sg:address":"Zentrall\u00e4ndstr. 40",
    "sg:city":"M\u00fcnchen",
    "sg:phone":"+49 89/7241616",
    "sg:postcode":"81379",
    "sg:province":"Bayern",
    "wof:name":"Golf U. Modeshop Flu\u00df Gmbh",
    "wof:placetype":"venue"
},
  "geometry": {"coordinates":[11.543264389,48.0921516418],"type":"Point"}
}