{
  "type": "Feature",
  "properties": {
    "iso:country":"DE",
    "sg:address":"Kaiserstr. 18",
    "sg:city":"Siegburg",
    "sg:phone":"+49 2241/52455",
    "sg:postcode":"53721",
    "sg:province":"Nordrhein-Westfalen",
    "wof:name":"Casa-blanca Textil Gmbh",
    "wof:placetype":"venue"
},
  "geometry": {"coordinates":[7.2080149651,50.7982559204],"type":"Point"}
}