{
  "type": "Feature",
  "properties": {
    "iso:country":"DE",
    "sg:address":"Baumkamp 24",
    "sg:city":"Hamburg",
    "sg:phone":"+49 40/5111031",
    "sg:postcode":"22299",
    "sg:province":"Hamburg",
    "wof:name":"Sotra Europa Transport Gmbh",
    "wof:placetype":"venue"
},
  "geometry": {"coordinates":[9.9985923767,53.5991325378],"type":"Point"}
}