{
  "type": "Feature",
  "properties": {
    "iso:country":"DE",
    "sg:address":"Markneukirchner Str. 100",
    "sg:city":"Klingenthal",
    "sg:phone":"+49 37467/23023",
    "sg:postcode":"08248",
    "sg:province":"Sachsen",
    "wof:name":"Reinhold M\u00fcller",
    "wof:placetype":"venue"
},
  "geometry": {"coordinates":[12.451678,50.355598],"type":"Point"}
}