{
  "type": "Feature",
  "properties": {
    "iso:country":"DE",
    "sg:address":"Vacher Str. 81",
    "sg:city":"F\u00fcrth",
    "sg:phone":"+49 911/731592",
    "sg:postcode":"90766",
    "sg:province":"Bayern",
    "wof:name":"Gerhard Wenzel",
    "wof:placetype":"venue"
},
  "geometry": {"coordinates":[10.979019,49.486431],"type":"Point"}
}