{
  "type": "Feature",
  "properties": {
    "iso:country":"DE",
    "sg:address":"Calbescher Weg 1",
    "sg:city":"Atzendorf",
    "sg:phone":"+49 39266/76060",
    "sg:postcode":"39443",
    "sg:province":"Sachsen-Anhalt",
    "wof:name":"Sprung Ost Gmbh",
    "wof:placetype":"venue"
},
  "geometry": {"coordinates":[11.634299,51.897224],"type":"Point"}
}