{
  "type": "Feature",
  "properties": {
    "iso:country":"DE",
    "sg:address":"Markt 9",
    "sg:city":"Sch\u00f6ningen",
    "sg:phone":"+49 5352/50954",
    "sg:postcode":"38364",
    "sg:province":"Niedersachsen",
    "wof:name":"Fernau & Sohn",
    "wof:placetype":"venue"
},
  "geometry": {"coordinates":[10.9677066803,52.1394615173],"type":"Point"}
}