{
  "type": "Feature",
  "properties": {
    "iso:country":"DE",
    "sg:address":"Hauptstr. 55",
    "sg:city":"Helbra",
    "sg:phone":"+49 34772/27150",
    "sg:postcode":"06311",
    "sg:province":"Sachsen-Anhalt",
    "wof:name":"Rolf Przybilla",
    "wof:placetype":"venue"
},
  "geometry": {"coordinates":[11.487651825,51.5528373718],"type":"Point"}
}