{
  "type": "Feature",
  "properties": {
    "iso:country":"DE",
    "sg:address":"K\u00f6nigsteiner Str. 17",
    "sg:city":"Frankfurt",
    "sg:postcode":"65929",
    "sg:province":"Hessen",
    "wof:name":"Deutsche Telekom Ag",
    "wof:placetype":"venue"
},
  "geometry": {"coordinates":[8.5478105545,50.1021995544],"type":"Point"}
}