{
  "type": "Feature",
  "properties": {
    "iso:country":"DE",
    "sg:address":"Am Kugelberg 13",
    "sg:city":"Wei\u00dfenfels",
    "sg:postcode":"06667",
    "sg:province":"Sachsen-Anhalt",
    "wof:name":"Bisantech-bm Beteiligungs- Und Managementgesellschaft Mbh",
    "wof:placetype":"venue"
},
  "geometry": {"coordinates":[11.972194,51.19339],"type":"Point"}
}