{
  "type": "Feature",
  "properties": {
    "iso:country":"DE",
    "sg:address":"Vor der Reihe 4",
    "sg:city":"Petershagen",
    "sg:phone":"+49 5702/4161",
    "sg:postcode":"32469",
    "sg:province":"Nordrhein-Westfalen",
    "wof:name":"L. Fehse",
    "wof:placetype":"venue"
},
  "geometry": {"coordinates":[8.991671,52.370396],"type":"Point"}
}