{
  "type": "Feature",
  "properties": {
    "iso:country":"DE",
    "sg:address":"Kampstr. 12",
    "sg:city":"Oststeinbek",
    "sg:phone":"+49 40/7148900",
    "sg:postcode":"22113",
    "sg:province":"Schleswig-Holstein",
    "wof:name":"Van Merhagen & Seager Gmbh",
    "wof:placetype":"venue"
},
  "geometry": {"coordinates":[10.1772880554,53.5441246033],"type":"Point"}
}