{
  "type": "Feature",
  "properties": {
    "iso:country":"DE",
    "sg:city":"Brehme",
    "sg:postcode":"37339",
    "sg:province":"Th\u00fcringen",
    "wof:name":"Gemeindeschwesterstation Brehme",
    "wof:placetype":"venue"
},
  "geometry": {"coordinates":[10.361798,51.492596],"type":"Point"}
}