{
  "type": "Feature",
  "properties": {
    "iso:country":"DE",
    "sg:address":"H\u00f6chte 2",
    "sg:city":"Lippstadt",
    "sg:phone":"+49 2941/10345",
    "sg:postcode":"59558",
    "sg:province":"Nordrhein-Westfalen",
    "wof:name":"Robert Henkemeier",
    "wof:placetype":"venue"
},
  "geometry": {"coordinates":[8.401515007,51.6653823853],"type":"Point"}
}