{
  "type": "Feature",
  "properties": {
    "iso:country":"DE",
    "sg:address":"Atzelbergstr. 100",
    "sg:city":"Frankfurt",
    "sg:phone":"+49 69/474908",
    "sg:postcode":"60389",
    "sg:province":"Hessen",
    "wof:name":"Altenwohnanlage",
    "wof:placetype":"venue"
},
  "geometry": {"coordinates":[8.723259,50.141773],"type":"Point"}
}