{
  "type": "Feature",
  "properties": {
    "iso:country":"DE",
    "sg:address":"St. Lambertiplatz",
    "sg:city":"L\u00fcneburg",
    "sg:phone":"+49 4131/761076",
    "sg:postcode":"21335",
    "sg:province":"Niedersachsen",
    "wof:name":"Heiko K\u00f6hler",
    "wof:placetype":"venue"
},
  "geometry": {"coordinates":[10.4025382996,53.2459220886],"type":"Point"}
}