{
  "type": "Feature",
  "properties": {
    "iso:country":"DE",
    "sg:address":"Sagasfeld 1",
    "sg:city":"G\u00f6hrde",
    "sg:postcode":"29473",
    "sg:province":"Niedersachsen",
    "wof:name":"Ayurveda-zentrum Deutschland Azd Rundlingsdorf",
    "wof:placetype":"venue"
},
  "geometry": {"coordinates":[10.9661750793,53.1307220459],"type":"Point"}
}