{
  "type": "Feature",
  "properties": {
    "iso:country":"DE",
    "sg:address":"Am Berge 4",
    "sg:city":"L\u00fcneburg",
    "sg:phone":"+49 4131/31666",
    "sg:postcode":"21335",
    "sg:province":"Niedersachsen",
    "wof:name":"Musik-cafe New York",
    "wof:placetype":"venue"
},
  "geometry": {"coordinates":[10.4109983444,53.2491188049],"type":"Point"}
}