{
  "type": "Feature",
  "properties": {
    "iso:country":"DE",
    "sg:address":"Bellinzonastr. 1",
    "sg:city":"M\u00fcnchen",
    "sg:phone":"+49 89/753680",
    "sg:postcode":"81475",
    "sg:province":"Bayern",
    "wof:name":"Dr. Hermann Mosbauer",
    "wof:placetype":"venue"
},
  "geometry": {"coordinates":[11.48071,48.093689],"type":"Point"}
}