{
  "type": "Feature",
  "properties": {
    "iso:country":"DE",
    "sg:address":"Gauliser Str. 13",
    "sg:city":"B\u00f6hlen",
    "sg:postcode":"04564",
    "sg:province":"Sachsen",
    "wof:name":"Hartmut Flemming",
    "wof:placetype":"venue"
},
  "geometry": {"coordinates":[12.3860902786,51.208820343],"type":"Point"}
}