{
  "type": "Feature",
  "properties": {
    "iso:country":"DE",
    "sg:address":"Au\u00dfenliegend",
    "sg:city":"Sch\u00f6neck",
    "sg:phone":"+49 6187/7444",
    "sg:postcode":"61137",
    "sg:province":"Hessen",
    "wof:name":"Frank Und Claudia Bleckwehl",
    "wof:placetype":"venue"
},
  "geometry": {"coordinates":[8.854323,50.20092],"type":"Point"}
}