{
  "type": "Feature",
  "properties": {
    "iso:country":"DE",
    "sg:address":"Max-Spenger-Str. 6",
    "sg:city":"Mainburg",
    "sg:phone":"+49 8751/1666",
    "sg:postcode":"84048",
    "sg:province":"Bayern",
    "wof:name":"Josef Bauer",
    "wof:placetype":"venue"
},
  "geometry": {"coordinates":[11.78004,48.64122],"type":"Point"}
}