{
  "type": "Feature",
  "properties": {
    "iso:country":"DE",
    "sg:address":"Waidmannsring 13",
    "sg:city":"Overath",
    "sg:phone":"+49 2206/5481",
    "sg:postcode":"51491",
    "sg:province":"Nordrhein-Westfalen",
    "wof:name":"M. Hauer",
    "wof:placetype":"venue"
},
  "geometry": {"coordinates":[7.306934,50.956352],"type":"Point"}
}