{
  "type": "Feature",
  "properties": {
    "iso:country":"DE",
    "sg:address":"Brabeckstr. 127",
    "sg:city":"Hannover",
    "sg:phone":"+49 511/520395",
    "sg:postcode":"30539",
    "sg:province":"Niedersachsen",
    "wof:name":"Orth",
    "wof:placetype":"venue"
},
  "geometry": {"coordinates":[9.8274040222,52.3479423523],"type":"Point"}
}