{
  "type": "Feature",
  "properties": {
    "iso:country":"DE",
    "sg:address":"Fasanenweg 2",
    "sg:city":"Brandis",
    "sg:postcode":"04821",
    "sg:province":"Sachsen",
    "wof:name":"Manfred Burkart",
    "wof:placetype":"venue"
},
  "geometry": {"coordinates":[12.5872716904,51.3184661865],"type":"Point"}
}