{
  "type": "Feature",
  "properties": {
    "iso:country":"DE",
    "sg:address":"Arndtstr. 29",
    "sg:city":"Heidenheim",
    "sg:phone":"+49 7321/44258",
    "sg:postcode":"89518",
    "sg:province":"Baden-W\u00fcrttemberg",
    "wof:name":"Karl Krack Dipl.- Ingenieur",
    "wof:placetype":"venue"
},
  "geometry": {"coordinates":[10.137662,48.679962],"type":"Point"}
}