{
  "type": "Feature",
  "properties": {
    "iso:country":"DE",
    "sg:address":"St.-Johannes-Str. 203",
    "sg:city":"Wassenberg",
    "sg:phone":"+49 2432/6773",
    "sg:postcode":"41849",
    "sg:province":"Nordrhein-Westfalen",
    "wof:name":"Kath. Pfarramt St. Johann Baptist",
    "wof:placetype":"venue"
},
  "geometry": {"coordinates":[6.1931052208,51.0987052917],"type":"Point"}
}