{
  "type": "Feature",
  "properties": {
    "iso:country":"DE",
    "sg:address":"Schwimmbadstr. 3",
    "sg:city":"Reichelsheim",
    "sg:phone":"+49 6164/2231",
    "sg:postcode":"64385",
    "sg:province":"Hessen",
    "wof:name":"Wilhelm Eberhard Ohg",
    "wof:placetype":"venue"
},
  "geometry": {"coordinates":[8.864486,49.721405],"type":"Point"}
}