{
  "type": "Feature",
  "properties": {
    "iso:country":"DE",
    "sg:address":"S\u00f6mmeringstr. 32",
    "sg:city":"Berlin",
    "sg:phone":"+49 30/3444054",
    "sg:postcode":"10589",
    "sg:province":"Berlin",
    "wof:name":"Wolfgang Bergmann Ingenieur",
    "wof:placetype":"venue"
},
  "geometry": {"coordinates":[13.3063802719,52.5242576599],"type":"Point"}
}