{
  "type": "Feature",
  "properties": {
    "iso:country":"DE",
    "sg:address":"Hauptstr. 19",
    "sg:city":"Hundsh\u00fcbel",
    "sg:phone":"+49 37462/3672",
    "sg:postcode":"08318",
    "wof:name":"Goldener Hirsch Inh. Gottfried Unger",
    "wof:placetype":"venue"
},
  "geometry": {"coordinates":[12.5687036514,50.5439682007],"type":"Point"}
}