{
  "type": "Feature",
  "properties": {
    "iso:country":"DE",
    "sg:address":"Bahnhofstr. 2",
    "sg:city":"Ohrdruf",
    "sg:phone":"+49 3624/402452",
    "sg:postcode":"99885",
    "sg:province":"Th\u00fcringen",
    "wof:name":"Marina N\u00f6thlich",
    "wof:placetype":"venue"
},
  "geometry": {"coordinates":[10.730612,50.827499],"type":"Point"}
}