{
  "type": "Feature",
  "properties": {
    "iso:country":"DE",
    "sg:address":"V\u00fcrfelser Kaule 29",
    "sg:city":"Bergisch Gladbach",
    "sg:phone":"+49 2204/66255",
    "sg:postcode":"51427",
    "sg:province":"Nordrhein-Westfalen",
    "wof:name":"Geiger Bdt Gmbh",
    "wof:placetype":"venue"
},
  "geometry": {"coordinates":[7.1159157753,50.953086853],"type":"Point"}
}