{
  "type": "Feature",
  "properties": {
    "iso:country":"DE",
    "sg:address":"G\u00e4ns\u00e4cker 24",
    "sg:city":"Tuttlingen",
    "sg:phone":"+49 7462/94540",
    "sg:postcode":"78532",
    "sg:province":"Baden-W\u00fcrttemberg",
    "wof:name":"Axel Gentner Gmbh",
    "wof:placetype":"venue"
},
  "geometry": {"coordinates":[8.78343,47.957924],"type":"Point"}
}