{
  "type": "Feature",
  "properties": {
    "iso:country":"DE",
    "sg:address":"Huertgener Str. 3 B",
    "sg:city":"Neuss",
    "sg:phone":"+49 2131/29880",
    "sg:postcode":"41464",
    "sg:province":"Nordrhein-Westfalen",
    "wof:name":"Citybill",
    "wof:placetype":"venue"
},
  "geometry": {"coordinates":[6.681293,51.186508],"type":"Point"}
}