{
  "type": "Feature",
  "properties": {
    "iso:country":"DE",
    "sg:address":"Bahnhofsplatz 3",
    "sg:city":"Eberbach",
    "sg:phone":"+49 6271/9410",
    "sg:postcode":"69412",
    "sg:province":"Baden-W\u00fcrttemberg",
    "wof:name":"Odenwald Treuhand Gmbh",
    "wof:placetype":"venue"
},
  "geometry": {"coordinates":[8.9834108353,49.465385437],"type":"Point"}
}