{
  "type": "Feature",
  "properties": {
    "iso:country":"DE",
    "sg:address":"Am Bahnhof 3",
    "sg:city":"Lugau",
    "sg:phone":"+49 37295/2733",
    "sg:postcode":"09385",
    "sg:province":"Sachsen",
    "wof:name":"Werner Engelhardt",
    "wof:placetype":"venue"
},
  "geometry": {"coordinates":[12.7466936111,50.7610778809],"type":"Point"}
}