{
  "type": "Feature",
  "properties": {
    "iso:country":"DE",
    "sg:address":"Augustusburger Str. 15",
    "sg:city":"Chemnitz",
    "sg:phone":"+49 371/6761533",
    "sg:postcode":"09111",
    "sg:province":"Sachsen",
    "wof:name":"Reimer Fotos Inh. Carl Reimer",
    "wof:placetype":"venue"
},
  "geometry": {"coordinates":[12.9287252426,50.8329048157],"type":"Point"}
}