{
  "type": "Feature",
  "properties": {
    "iso:country":"DE",
    "sg:address":"Hurlebuschweg 11",
    "sg:city":"Hannover",
    "sg:phone":"+49 511/2102780",
    "sg:postcode":"30453",
    "sg:province":"Niedersachsen",
    "wof:name":"Herta Schmalstieg",
    "wof:placetype":"venue"
},
  "geometry": {"coordinates":[9.6931915283,52.3714141846],"type":"Point"}
}