{
  "type": "Feature",
  "properties": {
    "iso:country":"DE",
    "sg:address":"Calbesche Str. 19",
    "sg:city":"F\u00f6rderstedt",
    "sg:postcode":"39443",
    "sg:province":"Sachsen-Anhalt",
    "wof:name":"F\u00f6rder-gastro Gmbh",
    "wof:placetype":"venue"
},
  "geometry": {"coordinates":[11.6384210587,51.896736145],"type":"Point"}
}