{
  "type": "Feature",
  "properties": {
    "iso:country":"DE",
    "sg:address":"In der Heuluss 28",
    "sg:city":"M\u00fcnchen",
    "sg:phone":"+49 89/341156",
    "sg:postcode":"81827",
    "sg:province":"Bayern",
    "wof:name":"B. Wolf",
    "wof:placetype":"venue"
},
  "geometry": {"coordinates":[11.702388,48.104748],"type":"Point"}
}