{
  "type": "Feature",
  "properties": {
    "iso:country":"DE",
    "sg:address":"Brachth\u00e4userstr. 15",
    "sg:city":"Herzogenrath",
    "sg:postcode":"52134",
    "sg:province":"Nordrhein-Westfalen",
    "wof:name":"Bauausf\u00fchrung Johann Gro\u00df Gmbh",
    "wof:placetype":"venue"
},
  "geometry": {"coordinates":[6.093577,50.8675],"type":"Point"}
}