{
  "type": "Feature",
  "properties": {
    "iso:country":"DE",
    "sg:address":"Karl-Marx-Str. 57",
    "sg:city":"Berlin",
    "sg:postcode":"12043",
    "sg:province":"Berlin",
    "wof:name":"Canvas Holding Gmbh",
    "wof:placetype":"venue"
},
  "geometry": {"coordinates":[13.432169,52.483032],"type":"Point"}
}