{
  "type": "Feature",
  "properties": {
    "iso:country":"DE",
    "sg:address":"Rektor-Esser-Str. 5",
    "sg:city":"M\u00f6nchengladbach",
    "sg:phone":"+49 2161/52474",
    "sg:postcode":"41068",
    "sg:province":"Nordrhein-Westfalen",
    "wof:name":"Wilhelm Lingen",
    "wof:placetype":"venue"
},
  "geometry": {"coordinates":[6.389766,51.204117],"type":"Point"}
}