{
  "type": "Feature",
  "properties": {
    "iso:country":"DE",
    "sg:address":"M\u00fcnsterstr. 220a",
    "sg:city":"Aachen",
    "sg:phone":"+49 241/526989",
    "sg:postcode":"52076",
    "sg:province":"Nordrhein-Westfalen",
    "wof:name":"Ernst Klein",
    "wof:placetype":"venue"
},
  "geometry": {"coordinates":[6.15886,50.740276],"type":"Point"}
}