{
  "type": "Feature",
  "properties": {
    "iso:country":"DE",
    "sg:address":"Maistr. 21",
    "sg:city":"Weiden",
    "sg:phone":"+49 961/22003",
    "sg:postcode":"92637",
    "sg:province":"Bayern",
    "wof:name":"Awo-seniorenheim",
    "wof:placetype":"venue"
},
  "geometry": {"coordinates":[12.149857,49.671925],"type":"Point"}
}