{
  "type": "Feature",
  "properties": {
    "iso:country":"DE",
    "sg:address":"Wendalinusstr. 6",
    "sg:city":"St. Wendel",
    "sg:phone":"+49 6851/2800",
    "sg:postcode":"66606",
    "sg:province":"Saarland",
    "wof:name":"Th. Munkes-theobald Hebamme",
    "wof:placetype":"venue"
},
  "geometry": {"coordinates":[7.170187,49.466743],"type":"Point"}
}