{
  "type": "Feature",
  "properties": {
    "iso:country":"DE",
    "sg:address":"Hannoversche Str. 28",
    "sg:city":"Wolfsburg",
    "sg:phone":"+49 5361/61458",
    "sg:postcode":"38448",
    "sg:province":"Niedersachsen",
    "wof:name":"Axel Bolze",
    "wof:placetype":"venue"
},
  "geometry": {"coordinates":[10.746096,52.457897],"type":"Point"}
}