{
  "type": "Feature",
  "properties": {
    "iso:country":"DE",
    "sg:address":"Sauerstr. 2",
    "sg:city":"Ingolstadt",
    "sg:phone":"+49 841/33552",
    "sg:postcode":"86980",
    "sg:province":"Bayern",
    "wof:name":"Wkv-bank Gmbh",
    "wof:placetype":"venue"
},
  "geometry": {"coordinates":[11.424473,48.76265],"type":"Point"}
}