{
  "type": "Feature",
  "properties": {
    "iso:country":"DE",
    "sg:address":"Saarstr. 4",
    "sg:city":"Bornheim",
    "sg:phone":"+49 2222/82351",
    "sg:postcode":"53332",
    "sg:province":"Nordrhein-Westfalen",
    "wof:name":"Bettina Hobmeier Hebamme",
    "wof:placetype":"venue"
},
  "geometry": {"coordinates":[7.042032,50.772022],"type":"Point"}
}