{
  "type": "Feature",
  "properties": {
    "iso:country":"DE",
    "sg:address":"Spitzhausstr. 74",
    "sg:city":"Dresden",
    "sg:postcode":"01139",
    "sg:province":"Sachsen",
    "wof:name":"Pape Beteiligungs- Gesellschaft Mbh",
    "wof:placetype":"venue"
},
  "geometry": {"coordinates":[13.674356,51.092709],"type":"Point"}
}