{
  "type": "Feature",
  "properties": {
    "iso:country":"DE",
    "sg:address":"Kolpingstr. 34",
    "sg:city":"Betzdorf",
    "sg:phone":"+49 2741/23398",
    "sg:postcode":"57518",
    "sg:province":"Rheinland-Pfalz",
    "wof:name":"Erster Deutscher Altenschutzbund",
    "wof:placetype":"venue"
},
  "geometry": {"coordinates":[7.8590521812,50.7881851196],"type":"Point"}
}