{
  "type": "Feature",
  "properties": {
    "iso:country":"DE",
    "sg:address":"Hauptstr. 28",
    "sg:city":"Kindenheim",
    "sg:phone":"+49 6359/40370",
    "sg:postcode":"67271",
    "sg:province":"Rheinland-Pfalz",
    "wof:name":"R. Elsesser",
    "wof:placetype":"venue"
},
  "geometry": {"coordinates":[8.165716,49.61161],"type":"Point"}
}