{
  "type": "Feature",
  "properties": {
    "iso:country":"DE",
    "sg:address":"Schm\u00f6llnsche Str. 7",
    "sg:city":"Altenburg",
    "sg:phone":"+49 3447/504207",
    "sg:postcode":"04600",
    "sg:province":"Th\u00fcringen",
    "wof:name":"P. M\u00fcller",
    "wof:placetype":"venue"
},
  "geometry": {"coordinates":[12.43099,50.983807],"type":"Point"}
}