{
  "type": "Feature",
  "properties": {
    "iso:country":"DE",
    "sg:address":"Speyerer Str. 5",
    "sg:city":"Hockenheim",
    "sg:phone":"+49 6205/220",
    "sg:postcode":"68766",
    "sg:province":"Baden-W\u00fcrttemberg",
    "wof:name":"S\u00fcba Intertrade Ges. F\u00fcr Internationalen Bauhandel Mbh",
    "wof:placetype":"venue"
},
  "geometry": {"coordinates":[8.5320682526,49.3332557678],"type":"Point"}
}