{
  "type": "Feature",
  "properties": {
    "iso:country":"DE",
    "sg:address":"Arensdorfer Weg 2",
    "sg:city":"K\u00f6then",
    "sg:phone":"+49 3496/40550",
    "sg:postcode":"06366",
    "sg:province":"Sachsen-Anhalt",
    "wof:name":"K & K Immobilien Gmbh",
    "wof:placetype":"venue"
},
  "geometry": {"coordinates":[12.0058202744,51.7372207642],"type":"Point"}
}