{
  "type": "Feature",
  "properties": {
    "iso:country":"DE",
    "sg:address":"Raiffeisenstr 6",
    "sg:city":"Zimmern",
    "sg:phone":"+49 741/3488380",
    "sg:postcode":"78658",
    "sg:province":"Baden-W\u00fcrttemberg",
    "wof:name":"Jakubowski",
    "wof:placetype":"venue"
},
  "geometry": {"coordinates":[8.574892,48.171501],"type":"Point"}
}