{
  "type": "Feature",
  "properties": {
    "iso:country":"DE",
    "sg:address":"Els\u00e4sser Str. 78",
    "sg:city":"Freiburg",
    "sg:phone":"+49 761/85157",
    "sg:postcode":"79110",
    "sg:province":"Baden-W\u00fcrttemberg",
    "wof:name":"Restaurant Villa Thai",
    "wof:placetype":"venue"
},
  "geometry": {"coordinates":[7.8174629211,48.0185089111],"type":"Point"}
}