{
  "type": "Feature",
  "properties": {
    "iso:country":"DE",
    "sg:address":"Hitzelerstr. 97b",
    "sg:city":"K\u00f6ln",
    "sg:postcode":"50968",
    "sg:province":"Nordrhein-Westfalen",
    "wof:name":"Transsonio Gmbh",
    "wof:placetype":"venue"
},
  "geometry": {"coordinates":[6.9545960426,50.8972015381],"type":"Point"}
}