{
  "type": "Feature",
  "properties": {
    "iso:country":"DE",
    "sg:address":"Tuttlinger Str. 53",
    "sg:city":"Rottweil",
    "sg:phone":"+49 741/21561",
    "sg:postcode":"78628",
    "sg:province":"Baden-W\u00fcrttemberg",
    "wof:name":"Emil Slongo Gmbh",
    "wof:placetype":"venue"
},
  "geometry": {"coordinates":[8.639958,48.151878],"type":"Point"}
}