{
  "type": "Feature",
  "properties": {
    "iso:country":"DE",
    "sg:address":"Das Alte Feld 24",
    "sg:city":"Eiterfeld",
    "sg:phone":"+49 6672/7845",
    "sg:postcode":"36132",
    "sg:province":"Hessen",
    "wof:name":"Ellen Schneider-schabel",
    "wof:placetype":"venue"
},
  "geometry": {"coordinates":[9.8075895309,50.7607803345],"type":"Point"}
}