{
  "type": "Feature",
  "properties": {
    "iso:country":"DE",
    "sg:address":"Heimfelderstr. 29b",
    "sg:city":"Hamburg",
    "sg:phone":"+49 40/614680",
    "sg:postcode":"21075",
    "sg:province":"Hamburg",
    "wof:name":"Simmet Offsetdruckerei",
    "wof:placetype":"venue"
},
  "geometry": {"coordinates":[9.9624967575,53.4652557373],"type":"Point"}
}