{
  "type": "Feature",
  "properties": {
    "iso:country":"DE",
    "sg:address":"Weidauer Str. 10",
    "sg:city":"Schwarzenberg",
    "sg:phone":"+49 3774/24301",
    "sg:postcode":"08340",
    "sg:province":"Sachsen",
    "wof:name":"Naundorffs Fleisch Und Wurst- Spezialit\u00e4ten Fachgeschaft",
    "wof:placetype":"venue"
},
  "geometry": {"coordinates":[12.7895364761,50.5460662842],"type":"Point"}
}