{
  "type": "Feature",
  "properties": {
    "iso:country":"DE",
    "sg:address":"Eduard-M\u00fcller-Str. 2",
    "sg:city":"Hagen",
    "sg:phone":"+49 2331/98960",
    "sg:postcode":"58097",
    "sg:province":"Nordrhein-Westfalen",
    "wof:name":"Gothaer Versicherungsbank Vvag",
    "wof:placetype":"venue"
},
  "geometry": {"coordinates":[7.4773201942,51.3662528992],"type":"Point"}
}