{
  "type": "Feature",
  "properties": {
    "iso:country":"DE",
    "sg:address":"Windausstr. 18",
    "sg:city":"Dortmund",
    "sg:phone":"+49 231/67838",
    "sg:postcode":"44369",
    "sg:province":"Nordrhein-Westfalen",
    "wof:name":"Fritz Nussbaum Textilien",
    "wof:placetype":"venue"
},
  "geometry": {"coordinates":[7.3820500374,51.5296669006],"type":"Point"}
}