{
  "type": "Feature",
  "properties": {
    "iso:country":"DE",
    "sg:address":"Friedrich-List-Weg 1",
    "sg:city":"Vaihingen",
    "sg:phone":"+49 7042/960386",
    "sg:postcode":"71665",
    "sg:province":"Baden-W\u00fcrttemberg",
    "wof:name":"Veluvine Gmbh",
    "wof:placetype":"venue"
},
  "geometry": {"coordinates":[8.9600467682,48.9481201172],"type":"Point"}
}