{
  "type": "Feature",
  "properties": {
    "iso:country":"DE",
    "sg:address":"Friedrich-Ebert-Str. 52",
    "sg:city":"Seeheim-Jugenheim",
    "sg:phone":"+49 6257/81317",
    "sg:postcode":"64342",
    "sg:province":"Hessen",
    "wof:name":"A.h.d.-wohnpark Gmbh",
    "wof:placetype":"venue"
},
  "geometry": {"coordinates":[8.639015,49.773331],"type":"Point"}
}