{
  "type": "Feature",
  "properties": {
    "iso:country":"DE",
    "sg:address":"Niedersachsenstr. 20",
    "sg:city":"Ludwigsburg",
    "sg:phone":"+49 7141/862312",
    "sg:postcode":"71640",
    "sg:province":"Baden-W\u00fcrttemberg",
    "wof:name":"Pc-schule-ludwig",
    "wof:placetype":"venue"
},
  "geometry": {"coordinates":[9.2229089737,48.8925437927],"type":"Point"}
}