{
  "type": "Feature",
  "properties": {
    "iso:country":"DE",
    "sg:address":"Geibelstr. 2",
    "sg:city":"Bottrop",
    "sg:phone":"+49 2041/57261",
    "sg:postcode":"46242",
    "sg:province":"Nordrhein-Westfalen",
    "wof:name":"Theo Alkemper Ingenieur",
    "wof:placetype":"venue"
},
  "geometry": {"coordinates":[6.8978199959,51.5189056396],"type":"Point"}
}