{
  "type": "Feature",
  "properties": {
    "iso:country":"DE",
    "sg:address":"Ro\u00dfmarktstr. 18",
    "sg:city":"Bad Neustadt",
    "sg:phone":"+49 9771/2791",
    "sg:postcode":"97616",
    "sg:province":"Bayern",
    "wof:name":"Helmut Ru\u00df",
    "wof:placetype":"venue"
},
  "geometry": {"coordinates":[10.217077,50.321636],"type":"Point"}
}