{
  "type": "Feature",
  "properties": {
    "iso:country":"DE",
    "sg:address":"Untere Dorfstr. 12",
    "sg:city":"Schwarzach",
    "sg:phone":"+49 9675/461",
    "sg:postcode":"92548",
    "sg:province":"Bayern",
    "wof:name":"Josef Scheuerer",
    "wof:placetype":"venue"
},
  "geometry": {"coordinates":[12.227893,49.408657],"type":"Point"}
}