{
  "type": "Feature",
  "properties": {
    "iso:country":"DE",
    "sg:address":"Am Torney 2a",
    "sg:city":"Wismar",
    "sg:phone":"+49 3841/210079",
    "sg:postcode":"23970",
    "sg:province":"Mecklenburg-Vorpommern",
    "wof:name":"Borchers & Speer Baumaschinen- Vertriebs Gmbh",
    "wof:placetype":"venue"
},
  "geometry": {"coordinates":[11.469662,53.90469],"type":"Point"}
}