{
  "type": "Feature",
  "properties": {
    "iso:country":"DE",
    "sg:address":"Mittelstr. 17",
    "sg:city":"Espenau",
    "sg:phone":"+49 5673/2874",
    "sg:postcode":"34314",
    "sg:province":"Hessen",
    "wof:name":"Werner Schwarz Anlageberater",
    "wof:placetype":"venue"
},
  "geometry": {"coordinates":[9.4604501724,51.3958282471],"type":"Point"}
}