{
  "type": "Feature",
  "properties": {
    "iso:country":"DE",
    "sg:address":"Burgbergring 58",
    "sg:city":"\u00dcberlingen",
    "sg:phone":"+49 7551/5111",
    "sg:postcode":"88662",
    "sg:province":"Baden-W\u00fcrttemberg",
    "wof:name":"Rolf Dengler",
    "wof:placetype":"venue"
},
  "geometry": {"coordinates":[9.1804161072,47.7712631226],"type":"Point"}
}