{
  "type": "Feature",
  "properties": {
    "iso:country":"DE",
    "sg:address":"Kirchstr. 18",
    "sg:city":"Bad Pyrmont",
    "sg:phone":"+49 4952/813041",
    "sg:postcode":"31812",
    "sg:province":"Niedersachsen",
    "wof:name":"Deutsche Bank Ag",
    "wof:placetype":"venue"
},
  "geometry": {"coordinates":[9.254737,51.985489],"type":"Point"}
}