{
  "type": "Feature",
  "properties": {
    "iso:country":"DE",
    "sg:address":"Betzenriedweg 41",
    "sg:city":"Eningen",
    "sg:phone":"+49 7121/88490",
    "sg:postcode":"72800",
    "sg:province":"Baden-W\u00fcrttemberg",
    "wof:name":"J. Geiger",
    "wof:placetype":"venue"
},
  "geometry": {"coordinates":[9.244782,48.484928],"type":"Point"}
}