{
  "type": "Feature",
  "properties": {
    "iso:country":"DE",
    "sg:address":"Charlottenstr. 81",
    "sg:city":"Hannover",
    "sg:postcode":"30449",
    "sg:province":"Niedersachsen",
    "wof:name":"Brandt Innenausbau Gmbh",
    "wof:placetype":"venue"
},
  "geometry": {"coordinates":[9.718709,52.357895],"type":"Point"}
}