{
  "type": "Feature",
  "properties": {
    "iso:country":"DE",
    "sg:address":"Roonstr. 6",
    "sg:city":"Herne",
    "sg:phone":"+49 2323/13369",
    "sg:postcode":"44629",
    "sg:province":"Nordrhein-Westfalen",
    "wof:name":"R. G\u00f6bel",
    "wof:placetype":"venue"
},
  "geometry": {"coordinates":[7.2177329063,51.5489196777],"type":"Point"}
}