{
  "type": "Feature",
  "properties": {
    "iso:country":"DE",
    "sg:address":"Alte Str. 2",
    "sg:city":"Dogern",
    "sg:phone":"+49 7751/2590",
    "sg:postcode":"79804",
    "sg:province":"Baden-W\u00fcrttemberg",
    "wof:name":"Albert Br\u00f6dlin",
    "wof:placetype":"venue"
},
  "geometry": {"coordinates":[8.1658763885,47.6110572815],"type":"Point"}
}