{
  "type": "Feature",
  "properties": {
    "iso:country":"DE",
    "sg:address":"Schlierseestr. 77",
    "sg:city":"M\u00fcnchen",
    "sg:phone":"+49 89/694911",
    "sg:postcode":"81539",
    "sg:province":"Bayern",
    "wof:name":"Sch\u00f6nweitz Optic Betreibs Gmbh",
    "wof:placetype":"venue"
},
  "geometry": {"coordinates":[11.5937299728,48.1120223999],"type":"Point"}
}