{
  "type": "Feature",
  "properties": {
    "iso:country":"DE",
    "sg:address":"Siemensstr. 3",
    "sg:city":"Sottrum",
    "sg:phone":"+49 4264/83250",
    "sg:postcode":"27367",
    "sg:province":"Niedersachsen",
    "wof:name":"Beco Metallteile Handelsges. Mbh",
    "wof:placetype":"venue"
},
  "geometry": {"coordinates":[9.2020568848,53.1014137268],"type":"Point"}
}