{
  "type": "Feature",
  "properties": {
    "iso:country":"DE",
    "sg:address":"Dorfstr. 15",
    "sg:city":"Parey",
    "sg:postcode":"14715",
    "sg:province":"Brandenburg",
    "wof:name":"Biohof Holger Staudler",
    "wof:placetype":"venue"
},
  "geometry": {"coordinates":[12.244052,52.678612],"type":"Point"}
}