{
  "type": "Feature",
  "properties": {
    "iso:country":"DE",
    "sg:address":"Bahnhofstr. 15",
    "sg:city":"Wolfratshausen",
    "sg:phone":"+49 8171/43300",
    "sg:postcode":"82515",
    "sg:province":"Bayern",
    "wof:name":"Albert G. Brunnhuber Und Ulrike Riedl-zwink",
    "wof:placetype":"venue"
},
  "geometry": {"coordinates":[11.4235754013,47.9153862],"type":"Point"}
}