{
  "type": "Feature",
  "properties": {
    "iso:country":"DE",
    "sg:address":"Buchenallee 1",
    "sg:city":"Mariental",
    "sg:phone":"+49 5356/91800",
    "sg:postcode":"38368",
    "sg:province":"Niedersachsen",
    "wof:name":"Deutsches Rotes Kreuz Pflegeheim Mariental-horst",
    "wof:placetype":"venue"
},
  "geometry": {"coordinates":[10.993325,52.290989],"type":"Point"}
}