{
  "type": "Feature",
  "properties": {
    "iso:country":"DE",
    "sg:address":"Buttergasse 9 a",
    "sg:city":"Leipzig",
    "sg:phone":"+49 341/4796839",
    "sg:postcode":"04249",
    "sg:province":"Sachsen",
    "wof:name":"Van Eupen Speditionsges. . Mbh & Co. Kg",
    "wof:placetype":"venue"
},
  "geometry": {"coordinates":[12.3303852081,51.3028297424],"type":"Point"}
}