{
  "type": "Feature",
  "properties": {
    "iso:country":"DE",
    "sg:address":"Saarlandstr. 86",
    "sg:city":"Dortmund",
    "sg:phone":"+49 231/124747",
    "sg:postcode":"44139",
    "sg:province":"Nordrhein-Westfalen",
    "wof:name":"B\u00e4ren-apotheke",
    "wof:placetype":"venue"
},
  "geometry": {"coordinates":[7.464391,51.504787],"type":"Point"}
}