{
  "type": "Feature",
  "properties": {
    "iso:country":"DE",
    "sg:address":"Friedrich-Hagemann-Str. 8",
    "sg:city":"Bielefeld",
    "sg:phone":"+49 521/9282235",
    "sg:postcode":"33719",
    "sg:province":"Nordrhein-Westfalen",
    "wof:name":"Asb-pflegedienste",
    "wof:placetype":"venue"
},
  "geometry": {"coordinates":[8.581341,52.017765],"type":"Point"}
}