{
  "type": "Feature",
  "properties": {
    "iso:country":"DE",
    "sg:address":"Am Horber Wald 21",
    "sg:city":"Neuhausen",
    "sg:phone":"+49 7158/4782",
    "sg:postcode":"73765",
    "sg:province":"Baden-W\u00fcrttemberg",
    "wof:name":"Michael L\u00f6rz Und Emil Baumann",
    "wof:placetype":"venue"
},
  "geometry": {"coordinates":[9.2740545273,48.6743469238],"type":"Point"}
}