{
  "type": "Feature",
  "properties": {
    "iso:country":"DE",
    "sg:address":"Esseler Str. 163",
    "sg:city":"Oer-Erkenschwick",
    "sg:phone":"+49 2368/56196",
    "sg:postcode":"45739",
    "sg:province":"Nordrhein-Westfalen",
    "wof:name":"Josef Storm",
    "wof:placetype":"venue"
},
  "geometry": {"coordinates":[7.24255,51.634792],"type":"Point"}
}