{
  "type": "Feature",
  "properties": {
    "iso:country":"DE",
    "sg:address":"Am Zollstock 48",
    "sg:city":"Attendorn",
    "sg:phone":"+49 2722/3266",
    "sg:postcode":"57439",
    "sg:province":"Nordrhein-Westfalen",
    "wof:name":"Udo Greitemann",
    "wof:placetype":"venue"
},
  "geometry": {"coordinates":[7.9024062157,51.1225013733],"type":"Point"}
}