{
  "type": "Feature",
  "properties": {
    "iso:country":"DE",
    "sg:address":"Pernauerstr. 67",
    "sg:city":"Rosenheim",
    "sg:phone":"+49 8031/86141",
    "sg:postcode":"83024",
    "sg:province":"Bayern",
    "wof:name":"Erlenau",
    "wof:placetype":"venue"
},
  "geometry": {"coordinates":[12.129781723,47.8681907654],"type":"Point"}
}