{
  "type": "Feature",
  "properties": {
    "iso:country":"DE",
    "sg:address":"Hohlstr. 21",
    "sg:city":"Stolberg",
    "sg:phone":"+49 2409/1211",
    "sg:postcode":"52224",
    "sg:province":"Nordrhein-Westfalen",
    "wof:name":"Helmut Wrede Immobilienmakler",
    "wof:placetype":"venue"
},
  "geometry": {"coordinates":[6.3241901398,50.7679214478],"type":"Point"}
}