{
  "type": "Feature",
  "properties": {
    "iso:country":"DE",
    "sg:address":"Repitzer Weg 1",
    "sg:city":"Torgau",
    "sg:phone":"+49 3475/74580",
    "sg:postcode":"04860",
    "sg:province":"Sachsen",
    "wof:name":"Technologie- Und Gr\u00fcnderzentrum Mansfelder Land Gmbh",
    "wof:placetype":"venue"
},
  "geometry": {"coordinates":[11.5491285324,51.5200157166],"type":"Point"}
}