{
  "type": "Feature",
  "properties": {
    "iso:country":"DE",
    "sg:address":"Unter den Ulmen 96-98",
    "sg:city":"K\u00f6ln",
    "sg:phone":"+49 221/9373802",
    "sg:postcode":"50968",
    "sg:province":"Nordrhein-Westfalen",
    "wof:name":"Centrale F\u00fcr Mediation Verwaltungsges. Mbh",
    "wof:placetype":"venue"
},
  "geometry": {"coordinates":[6.973469,50.904774],"type":"Point"}
}