{
  "type": "Feature",
  "properties": {
    "iso:country":"DE",
    "sg:address":"Albert-Schweitzer-Str. 16",
    "sg:city":"Hochheim",
    "sg:phone":"+49 6146/4166",
    "sg:postcode":"65239",
    "sg:province":"Hessen",
    "wof:name":"Hans-j\u00f6rg Bucksch",
    "wof:placetype":"venue"
},
  "geometry": {"coordinates":[8.3499345779,50.0184898376],"type":"Point"}
}