{
  "type": "Feature",
  "properties": {
    "iso:country":"DE",
    "sg:address":"Borngasse 1",
    "sg:city":"Dreieich",
    "sg:postcode":"63303",
    "sg:province":"Hessen",
    "wof:name":"B\u00fcgel-fix Gmbh",
    "wof:placetype":"venue"
},
  "geometry": {"coordinates":[8.7157621384,50.0012054443],"type":"Point"}
}