{
  "type": "Feature",
  "properties": {
    "iso:country":"DE",
    "sg:address":"Sandbochumer Weg 10",
    "sg:city":"Bergkamen",
    "sg:phone":"+49 2389/2549",
    "sg:postcode":"59192",
    "sg:province":"Nordrhein-Westfalen",
    "wof:name":"Milder Gmbh",
    "wof:placetype":"venue"
},
  "geometry": {"coordinates":[7.6736469269,51.6496925354],"type":"Point"}
}