{
  "type": "Feature",
  "properties": {
    "iso:country":"DE",
    "sg:address":"N\u00e4geleshofstr. 80",
    "sg:city":"Aalen",
    "sg:phone":"+49 4973/6144099",
    "sg:postcode":"73434",
    "sg:province":"Baden-W\u00fcrttemberg",
    "wof:name":"Mba Maschinenbau Abele Gmbh",
    "wof:placetype":"venue"
},
  "geometry": {"coordinates":[10.06226,48.828201],"type":"Point"}
}