{
  "type": "Feature",
  "properties": {
    "iso:country":"DE",
    "sg:address":"B\u00fcrgerstr 70/72",
    "sg:city":"Berlin",
    "sg:phone":"+49 30/6258014",
    "sg:postcode":"12347",
    "sg:province":"Berlin",
    "wof:name":"A. Nielsen Sandstrahltechnik Gmbh",
    "wof:placetype":"venue"
},
  "geometry": {"coordinates":[13.43675,52.461647],"type":"Point"}
}