{
  "type": "Feature",
  "properties": {
    "iso:country":"DE",
    "sg:address":"Vogesenstr. 5",
    "sg:city":"Binzen",
    "sg:phone":"+49 4976/2194220",
    "sg:postcode":"79589",
    "sg:province":"Baden-W\u00fcrttemberg",
    "wof:name":"Munz Ag Kunststofftechnik",
    "wof:placetype":"venue"
},
  "geometry": {"coordinates":[7.6191859245,47.6283721924],"type":"Point"}
}