{
  "type": "Feature",
  "properties": {
    "iso:country":"DE",
    "sg:address":"Auwaldstr. 7",
    "sg:city":"Freiburg",
    "sg:phone":"+49 761/16909",
    "sg:postcode":"79110",
    "sg:province":"Baden-W\u00fcrttemberg",
    "wof:name":"W. Pfundstein",
    "wof:placetype":"venue"
},
  "geometry": {"coordinates":[7.808159,48.02787],"type":"Point"}
}