{
  "type": "Feature",
  "properties": {
    "iso:country":"DE",
    "sg:address":"Auf Stein 6",
    "sg:city":"Weilm\u00fcnster",
    "sg:phone":"+49 6472/911130",
    "sg:postcode":"35789",
    "sg:province":"Hessen",
    "wof:name":"Energie & Sparcenter Klein Gmbh",
    "wof:placetype":"venue"
},
  "geometry": {"coordinates":[8.382171,50.440434],"type":"Point"}
}