{
  "type": "Feature",
  "properties": {
    "iso:country":"DE",
    "sg:address":"Birkenstr. 41",
    "sg:city":"D\u00fcsseldorf",
    "sg:postcode":"40233",
    "sg:province":"Nordrhein-Westfalen",
    "wof:name":"Peter Sch\u00f6nauer Gmbh",
    "wof:placetype":"venue"
},
  "geometry": {"coordinates":[6.8018631935,51.2272338867],"type":"Point"}
}