{
  "type": "Feature",
  "properties": {
    "iso:country":"DE",
    "sg:address":"T\u00e4schnerstr. 4",
    "sg:city":"Leipzig",
    "sg:phone":"+49 341/8628615",
    "sg:postcode":"04289",
    "sg:province":"Sachsen",
    "wof:name":"Dietmar Beyer",
    "wof:placetype":"venue"
},
  "geometry": {"coordinates":[12.430489,51.306976],"type":"Point"}
}