{
  "type": "Feature",
  "properties": {
    "iso:country":"DE",
    "sg:address":"Mainzer Str. 8",
    "sg:city":"Boppard",
    "sg:phone":"+49 6742/87470",
    "sg:postcode":"56154",
    "sg:province":"Rheinland-Pfalz",
    "wof:name":"Stiftung Bethseda-st.-martin",
    "wof:placetype":"venue"
},
  "geometry": {"coordinates":[7.6037521362,50.2297172546],"type":"Point"}
}