{
  "type": "Feature",
  "properties": {
    "iso:country":"DE",
    "sg:address":"Hogelied 19",
    "sg:city":"Hude",
    "sg:phone":"+49 4408/7337",
    "sg:postcode":"27798",
    "sg:province":"Niedersachsen",
    "wof:name":"U. Und E. Tessendorf",
    "wof:placetype":"venue"
},
  "geometry": {"coordinates":[8.467925,53.097874],"type":"Point"}
}