{
  "type": "Feature",
  "properties": {
    "iso:country":"DE",
    "sg:address":"Reutlingen S\u00fcd",
    "sg:city":"Pfullingen",
    "sg:postcode":"72793",
    "sg:province":"Baden-W\u00fcrttemberg",
    "wof:name":"Arbach Maschinenfabrik G. Gr\u00f6zinger",
    "wof:placetype":"venue"
},
  "geometry": {"coordinates":[9.226949,48.465744],"type":"Point"}
}