{
  "type": "Feature",
  "properties": {
    "iso:country":"DE",
    "sg:address":"Godaser Str. 5",
    "sg:city":"Kemnath",
    "sg:phone":"+49 9642/638",
    "sg:postcode":"95478",
    "sg:province":"Bayern",
    "wof:name":"A. K\u00f6nig",
    "wof:placetype":"venue"
},
  "geometry": {"coordinates":[11.9499368668,49.8686065674],"type":"Point"}
}