{
  "type": "Feature",
  "properties": {
    "iso:country":"DE",
    "sg:address":"Hauptstr. 105",
    "sg:city":"Freudenberg",
    "sg:phone":"+49 9375/1350",
    "sg:postcode":"97896",
    "sg:province":"Baden-W\u00fcrttemberg",
    "wof:name":"Bernhard",
    "wof:placetype":"venue"
},
  "geometry": {"coordinates":[9.3224868774,49.7414283752],"type":"Point"}
}