{
  "type": "Feature",
  "properties": {
    "iso:country":"DE",
    "sg:address":"Frankfurter Str. 23",
    "sg:city":"Guben",
    "sg:postcode":"03172",
    "sg:province":"Brandenburg",
    "wof:name":"R. Hentzschel",
    "wof:placetype":"venue"
},
  "geometry": {"coordinates":[14.7176437378,51.9514961243],"type":"Point"}
}