{
  "type": "Feature",
  "properties": {
    "iso:country":"DE",
    "sg:address":"Frommhagenstr. 8A",
    "sg:city":"Stendal",
    "sg:phone":"+49 3931/712268",
    "sg:postcode":"39576",
    "sg:province":"Sachsen-Anhalt",
    "wof:name":"Rossmann Drogeriemarkt",
    "wof:placetype":"venue"
},
  "geometry": {"coordinates":[11.857204,52.597252],"type":"Point"}
}