{
  "type": "Feature",
  "properties": {
    "iso:country":"DE",
    "sg:address":"Schimmelmannstr. 164",
    "sg:city":"Hamburg",
    "sg:phone":"+49 40/65390571",
    "sg:postcode":"22043",
    "sg:province":"Hamburg",
    "wof:name":"Frank Dawideit",
    "wof:placetype":"venue"
},
  "geometry": {"coordinates":[10.1137428284,53.5762825012],"type":"Point"}
}