{
  "type": "Feature",
  "properties": {
    "iso:country":"DE",
    "sg:address":"Talstr. 49",
    "sg:city":"Frankfurt",
    "sg:phone":"+49 69/501655",
    "sg:postcode":"60437",
    "sg:province":"Hessen",
    "wof:name":"Druckerei M\u00fcnker & Schmidt Gmbh",
    "wof:placetype":"venue"
},
  "geometry": {"coordinates":[8.6437768936,50.1870956421],"type":"Point"}
}