{
  "type": "Feature",
  "properties": {
    "iso:country":"DE",
    "sg:address":"Osenauer Str. 16a",
    "sg:city":"Odenthal",
    "sg:phone":"+49 2202/708708",
    "sg:postcode":"51519",
    "sg:province":"Nordrhein-Westfalen",
    "wof:name":"Realring Gmbh",
    "wof:placetype":"venue"
},
  "geometry": {"coordinates":[7.10342,51.031288],"type":"Point"}
}