{
  "type": "Feature",
  "properties": {
    "iso:country":"DE",
    "sg:address":"T\u00f6lzer Str. 153",
    "sg:city":"Gmund",
    "sg:phone":"+49 8022/76259",
    "sg:postcode":"83703",
    "sg:province":"Bayern",
    "wof:name":"Mathes B\u00fcroservice Gmbh",
    "wof:placetype":"venue"
},
  "geometry": {"coordinates":[11.715131,47.754318],"type":"Point"}
}