{
  "type": "Feature",
  "properties": {
    "iso:country":"DE",
    "sg:address":"Visbeker Str. 35",
    "sg:city":"Wildeshausen",
    "sg:phone":"+49 4431/9810",
    "sg:postcode":"27793",
    "sg:province":"Niedersachsen",
    "wof:name":"F. Weyhausen Gmbh & Co. Kg",
    "wof:placetype":"venue"
},
  "geometry": {"coordinates":[8.4231863022,52.8887863159],"type":"Point"}
}