{
  "type": "Feature",
  "properties": {
    "iso:country":"DE",
    "sg:address":"Herderstr. 10",
    "sg:city":"Bad Aibling",
    "sg:phone":"+49 8061/6336",
    "sg:postcode":"83043",
    "sg:province":"Bayern",
    "wof:name":"Dr. Med. Reiner Keller Arzt F\u00fcr Allgemeinmedizin",
    "wof:placetype":"venue"
},
  "geometry": {"coordinates":[11.9944429398,47.8618011475],"type":"Point"}
}