{
  "type": "Feature",
  "properties": {
    "iso:country":"DE",
    "sg:address":"Feldromer Str. 16",
    "sg:city":"Horn-Bad Meinberg",
    "sg:phone":"+49 5234/2200",
    "sg:postcode":"32805",
    "sg:province":"Nordrhein-Westfalen",
    "wof:name":"Theodor Haase",
    "wof:placetype":"venue"
},
  "geometry": {"coordinates":[8.941911,51.824951],"type":"Point"}
}