{
  "type": "Feature",
  "properties": {
    "iso:country":"DE",
    "sg:address":"Wilhelmstr. 29",
    "sg:city":"Westerburg",
    "sg:phone":"+49 2663/4114",
    "sg:postcode":"56457",
    "sg:province":"Rheinland-Pfalz",
    "wof:name":"Spielwaren Hof",
    "wof:placetype":"venue"
},
  "geometry": {"coordinates":[7.9746432304,50.5665206909],"type":"Point"}
}