{
  "type": "Feature",
  "properties": {
    "iso:country":"DE",
    "sg:address":"Am Hochholz 7",
    "sg:city":"Karben",
    "sg:phone":"+49 6034/930180",
    "sg:postcode":"61184",
    "sg:province":"Hessen",
    "wof:name":"Technoma Entwicklung Und Vertrieb Von Computer",
    "wof:placetype":"venue"
},
  "geometry": {"coordinates":[8.7969112396,50.2564086914],"type":"Point"}
}