{
  "type": "Feature",
  "properties": {
    "iso:country":"DE",
    "sg:address":"Georg-Bitter-Str. 24",
    "sg:city":"Bremen",
    "sg:phone":"+49 421/439400",
    "sg:postcode":"28205",
    "sg:province":"Bremen",
    "wof:name":"Alfred W. L\u00f6ffler Gmbh",
    "wof:placetype":"venue"
},
  "geometry": {"coordinates":[8.855706,53.069122],"type":"Point"}
}