{
  "type": "Feature",
  "properties": {
    "iso:country":"DE",
    "sg:address":"Karlstr. 9-13",
    "sg:city":"Ispringen",
    "sg:phone":"+49 4972/3189182",
    "sg:postcode":"75228",
    "sg:province":"Baden-W\u00fcrttemberg",
    "wof:name":"Bethge Gmbh",
    "wof:placetype":"venue"
},
  "geometry": {"coordinates":[8.6762609482,48.9136886597],"type":"Point"}
}