{
  "type": "Feature",
  "properties": {
    "iso:country":"DE",
    "sg:address":"In den Peilen 4",
    "sg:city":"Lennestadt",
    "sg:phone":"+49 2723/8347",
    "sg:postcode":"57368",
    "sg:province":"Nordrhein-Westfalen",
    "wof:name":"Dorfsch\u00e4nke",
    "wof:placetype":"venue"
},
  "geometry": {"coordinates":[8.1654033661,51.1164932251],"type":"Point"}
}