{
  "type": "Feature",
  "properties": {
    "iso:country":"DE",
    "sg:address":"Gluckensteinweg 140",
    "sg:city":"Bad Homburg",
    "sg:phone":"+49 6172/33851",
    "sg:postcode":"61350",
    "sg:province":"Hessen",
    "wof:name":"Helmut Heuss Schl\u00fcsseldienst",
    "wof:placetype":"venue"
},
  "geometry": {"coordinates":[8.5959291458,50.2399024963],"type":"Point"}
}