{
  "type": "Feature",
  "properties": {
    "iso:country":"DE",
    "sg:address":"Tulpenweg 30",
    "sg:city":"Parkstein",
    "sg:postcode":"92711",
    "sg:province":"Bayern",
    "wof:name":"Fil Forschungsinstitut Logistik Gmbh",
    "wof:placetype":"venue"
},
  "geometry": {"coordinates":[12.0749473572,49.7308921814],"type":"Point"}
}