{
  "type": "Feature",
  "properties": {
    "iso:country":"DE",
    "sg:address":"In den Wiesen 1",
    "sg:city":"Altenmedingen",
    "sg:phone":"+49 5807/390",
    "sg:postcode":"29575",
    "sg:province":"Niedersachsen",
    "wof:name":"Bernd-friedrich R\u00f6ber",
    "wof:placetype":"venue"
},
  "geometry": {"coordinates":[10.617297,53.143257],"type":"Point"}
}