{
  "type": "Feature",
  "properties": {
    "iso:country":"DE",
    "sg:address":"R\u00f6gen 3",
    "sg:city":"Nienwohld",
    "sg:phone":"+49 4537/7107",
    "sg:postcode":"23863",
    "sg:province":"Schleswig-Holstein",
    "wof:name":"Eckhard Reiche",
    "wof:placetype":"venue"
},
  "geometry": {"coordinates":[10.216972,53.779076],"type":"Point"}
}