{
  "type": "Feature",
  "properties": {
    "iso:country":"DE",
    "sg:address":"Inselstr. 11",
    "sg:city":"F\u00fcrth",
    "sg:phone":"+49 6253/4595",
    "sg:postcode":"64658",
    "sg:province":"Hessen",
    "wof:name":"Georg Fabian",
    "wof:placetype":"venue"
},
  "geometry": {"coordinates":[8.775276,49.649071],"type":"Point"}
}