{
  "type": "Feature",
  "properties": {
    "iso:country":"DE",
    "sg:address":"Bahnhofstr. 7",
    "sg:city":"Pl\u00fcderhausen",
    "sg:phone":"+49 7181/81368",
    "sg:postcode":"73655",
    "sg:province":"Baden-W\u00fcrttemberg",
    "wof:name":"Weinstube",
    "wof:placetype":"venue"
},
  "geometry": {"coordinates":[9.5968503952,48.7970046997],"type":"Point"}
}