{
  "type": "Feature",
  "properties": {
    "iso:country":"DE",
    "sg:address":"Walter-Preh-Str. 37",
    "sg:city":"Bad Neustadt",
    "sg:phone":"+49 9771/991393",
    "sg:postcode":"97616",
    "sg:province":"Bayern",
    "wof:name":"Bernd W. Und Elfi Papke Finanzberater",
    "wof:placetype":"venue"
},
  "geometry": {"coordinates":[10.1879587173,50.326007843],"type":"Point"}
}