{
  "type": "Feature",
  "properties": {
    "iso:country":"DE",
    "sg:address":"Torgauer Str. 20",
    "sg:city":"Bad D\u00fcben",
    "sg:phone":"+49 34243/23294",
    "sg:postcode":"04849",
    "sg:province":"Sachsen",
    "wof:name":"Dieter Br\u00e4utigam",
    "wof:placetype":"venue"
},
  "geometry": {"coordinates":[12.5902280807,51.5912208557],"type":"Point"}
}