{
  "type": "Feature",
  "properties": {
    "iso:country":"DE",
    "sg:address":"Auf der Heide 16",
    "sg:city":"Grafenau",
    "sg:phone":"+49 7033/43996",
    "sg:postcode":"71120",
    "sg:province":"Baden-W\u00fcrttemberg",
    "wof:name":"Ernst Hartmann Bildhauer",
    "wof:placetype":"venue"
},
  "geometry": {"coordinates":[8.920528,48.705379],"type":"Point"}
}