{
  "type": "Feature",
  "properties": {
    "iso:country":"DE",
    "sg:address":"Friedenstr. 8/2",
    "sg:city":"Wilhelmsdorf",
    "sg:phone":"+49 7503/91471",
    "sg:postcode":"88271",
    "sg:province":"Baden-W\u00fcrttemberg",
    "wof:name":"M. Solbach",
    "wof:placetype":"venue"
},
  "geometry": {"coordinates":[9.4312858582,47.865196228],"type":"Point"}
}