{
  "type": "Feature",
  "properties": {
    "iso:country":"DE",
    "sg:address":"Mackestr. 53",
    "sg:city":"Bonn",
    "sg:phone":"+49 228/671586",
    "sg:postcode":"53119",
    "sg:province":"Nordrhein-Westfalen",
    "wof:name":"Andheri-hilfe Bonn E. V.",
    "wof:placetype":"venue"
},
  "geometry": {"coordinates":[7.0769791603,50.7467727661],"type":"Point"}
}