{
  "type": "Feature",
  "properties": {
    "iso:country":"DE",
    "sg:address":"Am K\u00f6pfchen 7",
    "sg:city":"Bad Berleburg",
    "sg:phone":"+49 2759/1255",
    "sg:postcode":"57319",
    "sg:province":"Nordrhein-Westfalen",
    "wof:name":"Klaus Hannebaum Finanzberater",
    "wof:placetype":"venue"
},
  "geometry": {"coordinates":[8.2928781509,51.0694923401],"type":"Point"}
}