{
  "type": "Feature",
  "properties": {
    "iso:country":"DE",
    "sg:address":"Sonnenb\u00fchl 1",
    "sg:city":"Sonnenb\u00fchl",
    "sg:phone":"+49 7128/696",
    "sg:postcode":"72820",
    "sg:province":"Baden-W\u00fcrttemberg",
    "wof:name":"Reiseb\u00fcro B\u00e4renh\u00f6hle",
    "wof:placetype":"venue"
},
  "geometry": {"coordinates":[9.1844329834,48.3868637085],"type":"Point"}
}