{
  "type": "Feature",
  "properties": {
    "iso:country":"DE",
    "sg:address":"Mathildenstr. 9::",
    "sg:city":"F\u00fcrth",
    "sg:phone":"+49 911/977730",
    "sg:postcode":"90762",
    "sg:province":"Bayern",
    "wof:name":"Finanz Team Sued, Beratungs- U. Vermittlungsges. Fuer Finanzdienstleistu Mbh",
    "wof:placetype":"venue"
},
  "geometry": {"coordinates":[10.985865,49.47443],"type":"Point"}
}