{
  "type": "Feature",
  "properties": {
    "iso:country":"DE",
    "sg:address":"Haaler Str. 95",
    "sg:city":"W\u00fcrselen",
    "sg:phone":"+49 2405/91368",
    "sg:postcode":"52146",
    "sg:province":"Nordrhein-Westfalen",
    "wof:name":"Josef Ritzen",
    "wof:placetype":"venue"
},
  "geometry": {"coordinates":[6.132258,50.81115],"type":"Point"}
}