{
  "type": "Feature",
  "properties": {
    "iso:country":"DE",
    "sg:address":"Lothringer Str. 1",
    "sg:city":"N\u00fcrnberg",
    "sg:phone":"+49 911/4395006",
    "sg:postcode":"90461",
    "sg:province":"Bayern",
    "wof:name":"Franconia Frankiermasch. Gmbh",
    "wof:placetype":"venue"
},
  "geometry": {"coordinates":[11.081531,49.430794],"type":"Point"}
}