{
  "type": "Feature",
  "properties": {
    "iso:country":"DE",
    "sg:address":"Tangstedter Chaussee 52",
    "sg:city":"Rellingen",
    "sg:phone":"+49 4101/24797",
    "sg:postcode":"25462",
    "sg:province":"Schleswig-Holstein",
    "wof:name":"Walter Anders",
    "wof:placetype":"venue"
},
  "geometry": {"coordinates":[9.834609,53.65871],"type":"Point"}
}