{
  "type": "Feature",
  "properties": {
    "iso:country":"DE",
    "sg:address":"Bergedorfer Str. 136",
    "sg:city":"Hamburg",
    "sg:phone":"+49 40/7247301",
    "sg:postcode":"21029",
    "sg:province":"Hamburg",
    "wof:name":"Tontarra Gmbh",
    "wof:placetype":"venue"
},
  "geometry": {"coordinates":[10.2128400803,53.4864006042],"type":"Point"}
}