{
  "type": "Feature",
  "properties": {
    "iso:country":"DE",
    "sg:address":"Odenwaldring 10",
    "sg:city":"Offenbach",
    "sg:phone":"+49 69/9840200",
    "sg:postcode":"63069",
    "sg:province":"Hessen",
    "wof:name":"Uvg Vermietungs Gmbh",
    "wof:placetype":"venue"
},
  "geometry": {"coordinates":[8.7689399719,50.089805603],"type":"Point"}
}