{
  "type": "Feature",
  "properties": {
    "iso:country":"DE",
    "sg:address":"Neuer Weg 23",
    "sg:city":"Arnsberg",
    "sg:phone":"+49 2932/35293",
    "sg:postcode":"59757",
    "sg:province":"Nordrhein-Westfalen",
    "wof:name":"Theodor Theine",
    "wof:placetype":"venue"
},
  "geometry": {"coordinates":[7.961356163,51.4223480225],"type":"Point"}
}