{
  "type": "Feature",
  "properties": {
    "iso:country":"DE",
    "sg:address":"Konrad-Celtis-Str 81",
    "sg:city":"M\u00fcnchen",
    "sg:phone":"+49 89/7413520",
    "sg:postcode":"81369",
    "sg:province":"Bayern",
    "wof:name":"Plantina Biologische Arzneimittel Ag",
    "wof:placetype":"venue"
},
  "geometry": {"coordinates":[11.522187,48.110516],"type":"Point"}
}