{
  "type": "Feature",
  "properties": {
    "iso:country":"DE",
    "sg:address":"Quergasse 21",
    "sg:city":"Ettlingen",
    "sg:phone":"+49 7243/31665",
    "sg:postcode":"76275",
    "sg:province":"Baden-W\u00fcrttemberg",
    "wof:name":"H. H. K\u00e4stner",
    "wof:placetype":"venue"
},
  "geometry": {"coordinates":[8.4082098007,48.9429283142],"type":"Point"}
}