{
  "type": "Feature",
  "properties": {
    "iso:country":"DE",
    "sg:address":"Tulpenweg 19",
    "sg:city":"Schwarme",
    "sg:phone":"+49 4258/203",
    "sg:postcode":"27327",
    "sg:province":"Niedersachsen",
    "wof:name":"Bodo Erdmann",
    "wof:placetype":"venue"
},
  "geometry": {"coordinates":[9.05035,52.901627],"type":"Point"}
}