{
  "type": "Feature",
  "properties": {
    "iso:country":"DE",
    "sg:address":"S\u00fcdstadtring 90",
    "sg:city":"Halle",
    "sg:phone":"+49 345/1219158",
    "sg:postcode":"06128",
    "sg:province":"Sachsen-Anhalt",
    "wof:name":"Ingenieurgesellschaft Nts",
    "wof:placetype":"venue"
},
  "geometry": {"coordinates":[11.9560546875,51.4488296509],"type":"Point"}
}