{
  "type": "Feature",
  "properties": {
    "iso:country":"DE",
    "sg:address":"Schindelberg 12",
    "sg:city":"Oberstaufen",
    "sg:phone":"+49 8386/8148",
    "sg:postcode":"87534",
    "sg:province":"Bayern",
    "wof:name":"Pension A. Und C. Zinth",
    "wof:placetype":"venue"
},
  "geometry": {"coordinates":[10.0087375641,47.5323791504],"type":"Point"}
}