{
  "type": "Feature",
  "properties": {
    "iso:country":"DE",
    "sg:address":"Himpfelshofstr. 6",
    "sg:city":"N\u00fcrnberg",
    "sg:phone":"+49 911/268466",
    "sg:postcode":"90429",
    "sg:province":"Bayern",
    "wof:name":"Silvia Gerlach Praxis F\u00fcr Krankengymnastik",
    "wof:placetype":"venue"
},
  "geometry": {"coordinates":[11.0621147156,49.4516220093],"type":"Point"}
}