{
  "type": "Feature",
  "properties": {
    "iso:country":"DE",
    "sg:address":"Klausdorfer Str. 84",
    "sg:city":"Altenholz",
    "sg:phone":"+49 431/321476",
    "sg:postcode":"24161",
    "sg:province":"Schleswig-Holstein",
    "wof:name":"Grundst\u00fccksgesellschaft Surendorf Verwaltungsges. Mbh",
    "wof:placetype":"venue"
},
  "geometry": {"coordinates":[10.118984,54.401913],"type":"Point"}
}