{
  "type": "Feature",
  "properties": {
    "iso:country":"DE",
    "sg:address":"Armenruhstr.11",
    "sg:city":"Wiesbaden",
    "sg:phone":"+49 4961/2167085",
    "sg:postcode":"65203",
    "sg:province":"Hessen",
    "wof:name":"Dresdner Bank",
    "wof:placetype":"venue"
},
  "geometry": {"coordinates":[8.239081,50.03978],"type":"Point"}
}