{
  "type": "Feature",
  "properties": {
    "iso:country":"DE",
    "sg:address":"Am Block 1",
    "sg:city":"Ense",
    "sg:phone":"+49 2928/234",
    "sg:postcode":"59469",
    "sg:province":"Nordrhein-Westfalen",
    "wof:name":"Horst N\u00f6cker",
    "wof:placetype":"venue"
},
  "geometry": {"coordinates":[8.014796,51.532669],"type":"Point"}
}