{
  "type": "Feature",
  "properties": {
    "iso:country":"DE",
    "sg:address":"Teltower Damm 47",
    "sg:city":"Berlin",
    "sg:phone":"+49 30/8156018",
    "sg:postcode":"14167",
    "sg:province":"Berlin",
    "wof:name":"Rex Tier-freund",
    "wof:placetype":"venue"
},
  "geometry": {"coordinates":[13.259952,52.429752],"type":"Point"}
}