{
  "type": "Feature",
  "properties": {
    "iso:country":"DE",
    "sg:address":"Lindenstockstr. 31",
    "sg:city":"Gummersbach",
    "sg:phone":"+49 2261/560151",
    "sg:postcode":"51647",
    "sg:province":"Nordrhein-Westfalen",
    "wof:name":"Traude Rothstein",
    "wof:placetype":"venue"
},
  "geometry": {"coordinates":[7.586857,51.022873],"type":"Point"}
}