{
  "type": "Feature",
  "properties": {
    "iso:country":"DE",
    "sg:address":"Altenberger Str. 13",
    "sg:city":"Havixbeck",
    "sg:phone":"+49 2507/2083",
    "sg:postcode":"48329",
    "sg:province":"Nordrhein-Westfalen",
    "wof:name":"Ottavios Bistro",
    "wof:placetype":"venue"
},
  "geometry": {"coordinates":[7.412460804,51.9767837524],"type":"Point"}
}