{
  "type": "Feature",
  "properties": {
    "iso:country":"DE",
    "sg:address":"Bahnhofstr. 38",
    "sg:city":"Dinklage",
    "sg:phone":"+49 4443/96290",
    "sg:postcode":"49413",
    "sg:province":"Niedersachsen",
    "wof:name":"Autohaus Calvelage Beteiligungs Gmbh",
    "wof:placetype":"venue"
},
  "geometry": {"coordinates":[8.1190652847,52.6645088196],"type":"Point"}
}