{
  "type": "Feature",
  "properties": {
    "iso:country":"DE",
    "sg:address":"Obere Hauptstr. 8",
    "sg:city":"Au",
    "sg:phone":"+49 8752/1610",
    "sg:postcode":"84072",
    "sg:province":"Bayern",
    "wof:name":"Alois Faltermeier",
    "wof:placetype":"venue"
},
  "geometry": {"coordinates":[11.7433834076,48.5572319031],"type":"Point"}
}