{
  "type": "Feature",
  "properties": {
    "iso:country":"DE",
    "sg:address":"Flaesheimer Str. 52",
    "sg:city":"Haltern",
    "sg:phone":"+49 2364/12232",
    "sg:postcode":"45721",
    "sg:province":"Nordrhein-Westfalen",
    "wof:name":"Werner Vollmer",
    "wof:placetype":"venue"
},
  "geometry": {"coordinates":[7.1931219101,51.727596283],"type":"Point"}
}