{
  "type": "Feature",
  "properties": {
    "iso:country":"DE",
    "sg:address":"Karl-Benz-Str. 1",
    "sg:city":"Weil im Sch\u00f6nbuch",
    "sg:phone":"+49 7157/66099",
    "sg:postcode":"71093",
    "sg:province":"Baden-W\u00fcrttemberg",
    "wof:name":"Schmitt Wohnmobile",
    "wof:placetype":"venue"
},
  "geometry": {"coordinates":[9.041229248,48.6197776794],"type":"Point"}
}