{
  "type": "Feature",
  "properties": {
    "iso:country":"DE",
    "sg:address":"Lichtenweg 20",
    "sg:city":"Bergisch Gladbach",
    "sg:phone":"+49 2202/35555",
    "sg:postcode":"51465",
    "sg:province":"Nordrhein-Westfalen",
    "wof:name":"Ch. Schultz Steuerberater",
    "wof:placetype":"venue"
},
  "geometry": {"coordinates":[7.151966095,50.9857368469],"type":"Point"}
}