{
  "type": "Feature",
  "properties": {
    "iso:country":"DE",
    "sg:address":"Birkenwaldstr. 44",
    "sg:city":"Stuttgart",
    "sg:phone":"+49 711/25820",
    "sg:postcode":"70191",
    "sg:province":"Baden-W\u00fcrttemberg",
    "wof:name":"Wissenschaftliche Verlags- Gesellschaft Mbh",
    "wof:placetype":"venue"
},
  "geometry": {"coordinates":[9.1771411896,48.7877845764],"type":"Point"}
}