{
  "type": "Feature",
  "properties": {
    "iso:country":"DE",
    "sg:address":"W\u00f6hrhofweg 1",
    "sg:city":"Regenstauf",
    "sg:phone":"+49 9402/2888",
    "sg:postcode":"93128",
    "sg:province":"Bayern",
    "wof:name":"K. Kolbeck",
    "wof:placetype":"venue"
},
  "geometry": {"coordinates":[12.135629,49.133492],"type":"Point"}
}