{
  "type": "Feature",
  "properties": {
    "iso:country":"DE",
    "sg:address":"August-Bebel-Str. 7",
    "sg:city":"Ludwigshafen",
    "sg:phone":"+49 621/653934",
    "sg:postcode":"67069",
    "sg:province":"Rheinland-Pfalz",
    "wof:name":"Renate Blumhardt",
    "wof:placetype":"venue"
},
  "geometry": {"coordinates":[8.402680397,49.5216140747],"type":"Point"}
}