{
  "type": "Feature",
  "properties": {
    "iso:country":"DE",
    "sg:address":"Philipp-M\u00fcller-Str. 19",
    "sg:city":"Dessau",
    "sg:phone":"+49 340/521203",
    "sg:postcode":"06847",
    "sg:province":"Sachsen-Anhalt",
    "wof:name":"Fangmann - Ording",
    "wof:placetype":"venue"
},
  "geometry": {"coordinates":[12.1563367844,51.8074684143],"type":"Point"}
}