{
  "type": "Feature",
  "properties": {
    "iso:country":"DE",
    "sg:address":"Geibelstr. 54",
    "sg:city":"Hamburg",
    "sg:phone":"+49 40/2700627",
    "sg:postcode":"22303",
    "sg:province":"Hamburg",
    "wof:name":"Martina Urban Fotografie",
    "wof:placetype":"venue"
},
  "geometry": {"coordinates":[10.0155038834,53.5849227905],"type":"Point"}
}