{
  "type": "Feature",
  "properties": {
    "iso:country":"DE",
    "sg:address":"Gress-Str. 13",
    "sg:city":"Weinstadt",
    "sg:phone":"+49 7151/609093",
    "sg:postcode":"71384",
    "sg:province":"Baden-W\u00fcrttemberg",
    "wof:name":"S. Zimmermann",
    "wof:placetype":"venue"
},
  "geometry": {"coordinates":[9.3569,48.811886],"type":"Point"}
}