{
  "type": "Feature",
  "properties": {
    "iso:country":"DE",
    "sg:address":"Appener Str. 21",
    "sg:city":"Appen",
    "sg:postcode":"25482",
    "sg:province":"Schleswig-Holstein",
    "wof:name":"Rs Logistik Gmbh",
    "wof:placetype":"venue"
},
  "geometry": {"coordinates":[9.7605438232,53.6397399902],"type":"Point"}
}