{
  "type": "Feature",
  "properties": {
    "iso:country":"DE",
    "sg:address":"Michael-Vogel-Strasse 3",
    "sg:city":"Erlangen",
    "sg:postcode":"91052",
    "sg:province":"Bayern",
    "wof:name":"Region N\u00fcrnberg E.v.",
    "wof:placetype":"venue"
},
  "geometry": {"coordinates":[11.000123,49.588348],"type":"Point"}
}