{
  "type": "Feature",
  "properties": {
    "iso:country":"DE",
    "sg:address":"Industriestr. 29",
    "sg:city":"Walldorf",
    "sg:phone":"+49 6227/63818",
    "sg:postcode":"69190",
    "sg:province":"Baden-W\u00fcrttemberg",
    "wof:name":"Karins Sb M\u00f6belhalle",
    "wof:placetype":"venue"
},
  "geometry": {"coordinates":[8.646176,49.294384],"type":"Point"}
}