{
  "type": "Feature",
  "properties": {
    "iso:country":"DE",
    "sg:address":"Selterser Str.",
    "sg:city":"Weilburg",
    "sg:phone":"+49 6471/30429",
    "sg:postcode":"35781",
    "sg:province":"Hessen",
    "wof:name":"Karl Bock",
    "wof:placetype":"venue"
},
  "geometry": {"coordinates":[8.272228,50.495857],"type":"Point"}
}