{
  "type": "Feature",
  "properties": {
    "iso:country":"DE",
    "sg:address":"Aufeldweg I 3",
    "sg:city":"Mannheim",
    "sg:phone":"+49 621/856462",
    "sg:postcode":"68199",
    "sg:province":"Baden-W\u00fcrttemberg",
    "wof:name":"Hallenbad Neckarau",
    "wof:placetype":"venue"
},
  "geometry": {"coordinates":[8.4828872681,49.4516792297],"type":"Point"}
}