{
  "type": "Feature",
  "properties": {
    "iso:country":"DE",
    "sg:address":"Sternenberg 66",
    "sg:city":"Wuppertal",
    "sg:phone":"+49 202/521769",
    "sg:postcode":"42279",
    "sg:province":"Nordrhein-Westfalen",
    "wof:name":"Walter Schmidt",
    "wof:placetype":"venue"
},
  "geometry": {"coordinates":[7.2167110443,51.3016204834],"type":"Point"}
}