{
  "type": "Feature",
  "properties": {
    "iso:country":"DE",
    "sg:address":"Schie\u00dfst\u00e4ttstr. 94",
    "sg:city":"Wolfratshausen",
    "sg:phone":"+49 8171/29083",
    "sg:postcode":"82515",
    "sg:province":"Bayern",
    "wof:name":"Eiscafe Roma",
    "wof:placetype":"venue"
},
  "geometry": {"coordinates":[11.431069,47.908295],"type":"Point"}
}