{
  "type": "Feature",
  "properties": {
    "iso:country":"DE",
    "sg:address":"Am Rabenstein 48",
    "sg:city":"Bad Homburg",
    "sg:phone":"+49 6172/81482",
    "sg:postcode":"61350",
    "sg:province":"Hessen",
    "wof:name":"Dr. Christian Knahn Rechtsanwalt",
    "wof:placetype":"venue"
},
  "geometry": {"coordinates":[8.6167573929,50.2453689575],"type":"Point"}
}