{
  "type": "Feature",
  "properties": {
    "iso:country":"DE",
    "sg:address":"Sausenthalstr. 1",
    "sg:city":"Wiesenbach",
    "sg:phone":"+49 8283/339",
    "sg:postcode":"86519",
    "sg:province":"Bayern",
    "wof:name":"Schebesta Heizungsbau Beteiligungs- Gmbh",
    "wof:placetype":"venue"
},
  "geometry": {"coordinates":[10.3148794174,48.3075523376],"type":"Point"}
}