{
  "type": "Feature",
  "properties": {
    "iso:country":"DE",
    "sg:address":"Rahlstedter Str. 150 h",
    "sg:city":"Hamburg",
    "sg:phone":"+49 40/6773670",
    "sg:postcode":"22143",
    "sg:province":"Hamburg",
    "wof:name":"Bernhard G\u00e4tke",
    "wof:placetype":"venue"
},
  "geometry": {"coordinates":[10.157995,53.602654],"type":"Point"}
}