{
  "type": "Feature",
  "properties": {
    "iso:country":"DE",
    "sg:address":"Prinz-Heinrich-Weg 2",
    "sg:city":"Minden",
    "sg:phone":"+49 571/62713",
    "sg:postcode":"32425",
    "sg:province":"Nordrhein-Westfalen",
    "wof:name":"Europal Gmbh",
    "wof:placetype":"venue"
},
  "geometry": {"coordinates":[8.893399,52.3148],"type":"Point"}
}