{
  "type": "Feature",
  "properties": {
    "iso:country":"DE",
    "sg:address":"Schickardstr. 25",
    "sg:city":"B\u00f6blingen",
    "sg:phone":"+49 4970/31180",
    "sg:postcode":"71034",
    "sg:province":"Baden-W\u00fcrttemberg",
    "wof:name":"Philips Semiconductors Gmbh",
    "wof:placetype":"venue"
},
  "geometry": {"coordinates":[8.971862,48.676079],"type":"Point"}
}