{
  "type": "Feature",
  "properties": {
    "iso:country":"DE",
    "sg:address":"Bilker Allee 163",
    "sg:city":"D\u00fcsseldorf",
    "sg:phone":"+49 211/316944",
    "sg:postcode":"40217",
    "sg:province":"Nordrhein-Westfalen",
    "wof:name":"Paulus Klause",
    "wof:placetype":"venue"
},
  "geometry": {"coordinates":[6.7754969597,51.2105712891],"type":"Point"}
}