{
  "type": "Feature",
  "properties": {
    "iso:country":"DE",
    "sg:address":"Mahlerstr. 17",
    "sg:city":"Berlin",
    "sg:postcode":"13088",
    "sg:province":"Berlin",
    "wof:name":"Christoph Meyer",
    "wof:placetype":"venue"
},
  "geometry": {"coordinates":[13.453764,52.547314],"type":"Point"}
}