{
  "type": "Feature",
  "properties": {
    "iso:country":"DE",
    "sg:address":"Gr\u00f6pelinger Heerstr. 256",
    "sg:city":"Bremen",
    "sg:phone":"+49 421/6167171",
    "sg:postcode":"28237",
    "sg:province":"Bremen",
    "wof:name":"Pl\u00f6tz Schuh-express",
    "wof:placetype":"venue"
},
  "geometry": {"coordinates":[8.7550516129,53.1190757751],"type":"Point"}
}