{
  "type": "Feature",
  "properties": {
    "iso:country":"DE",
    "sg:address":"Willy-Brandt-Weg 41",
    "sg:city":"M\u00fcnster",
    "sg:phone":"+49 251/2856100",
    "sg:postcode":"48155",
    "sg:province":"Nordrhein-Westfalen",
    "wof:name":"Vectron Systems Ag",
    "wof:placetype":"venue"
},
  "geometry": {"coordinates":[7.64636,51.934566],"type":"Point"}
}