{
  "type": "Feature",
  "properties": {
    "iso:country":"DE",
    "sg:address":"Obere Paulusstr. 105",
    "sg:city":"Stuttgart",
    "sg:phone":"+49 711/654391",
    "sg:postcode":"70197",
    "sg:province":"Baden-W\u00fcrttemberg",
    "wof:name":"W. Fichtner",
    "wof:placetype":"venue"
},
  "geometry": {"coordinates":[9.1431293488,48.7708091736],"type":"Point"}
}