{
  "type": "Feature",
  "properties": {
    "iso:country":"DE",
    "sg:address":"Lindwurmstr. 76",
    "sg:city":"M\u00fcnchen",
    "sg:phone":"+49 89/7252015",
    "sg:postcode":"80337",
    "sg:province":"Bayern",
    "wof:name":"Kare Landhaus",
    "wof:placetype":"venue"
},
  "geometry": {"coordinates":[11.55115,48.126068],"type":"Point"}
}