{
  "type": "Feature",
  "properties": {
    "iso:country":"DE",
    "sg:address":"Hauptstr. 26",
    "sg:city":"Hornberg",
    "sg:phone":"+49 7833/7772",
    "sg:postcode":"78132",
    "sg:province":"Baden-W\u00fcrttemberg",
    "wof:name":"Bahnh\u00f6fle",
    "wof:placetype":"venue"
},
  "geometry": {"coordinates":[8.2266263962,48.2146072388],"type":"Point"}
}