{
  "type": "Feature",
  "properties": {
    "iso:country":"DE",
    "sg:address":"G\u00f6dersweg 9",
    "sg:city":"Waldesch",
    "sg:phone":"+49 2628/8988",
    "sg:postcode":"56323",
    "sg:province":"Rheinland-Pfalz",
    "wof:name":"Paul Reitemeyer Masseur",
    "wof:placetype":"venue"
},
  "geometry": {"coordinates":[7.547386,50.279175],"type":"Point"}
}