{
  "type": "Feature",
  "properties": {
    "iso:country":"DE",
    "sg:address":"Am Feriengebiet 1",
    "sg:city":"Uelsen",
    "sg:phone":"+49 5942/92220",
    "sg:postcode":"49843",
    "sg:province":"Niedersachsen",
    "wof:name":"Gesundheitszentrum Aquarius Betriebs- Und Verwaltungs Gmbh",
    "wof:placetype":"venue"
},
  "geometry": {"coordinates":[6.880466938,52.4888763428],"type":"Point"}
}