{
  "type": "Feature",
  "properties": {
    "iso:country":"DE",
    "sg:address":"G\u00f6rlitzer Str. 2",
    "sg:city":"Freilassing",
    "sg:phone":"+49 8654/61888",
    "sg:postcode":"83395",
    "sg:province":"Bayern",
    "wof:name":"Franz Pfeffer Kunst- Und Bauschlosserei",
    "wof:placetype":"venue"
},
  "geometry": {"coordinates":[12.9618396759,47.8540802002],"type":"Point"}
}