{
  "type": "Feature",
  "properties": {
    "iso:country":"DE",
    "sg:address":"Im Breitspiel 17",
    "sg:city":"Heidelberg",
    "sg:postcode":"69126",
    "sg:province":"Baden-W\u00fcrttemberg",
    "wof:name":"Pke Beteiligungs- Und Verwaltungs- Gmbh",
    "wof:placetype":"venue"
},
  "geometry": {"coordinates":[8.687252,49.361179],"type":"Point"}
}