{
  "type": "Feature",
  "properties": {
    "iso:country":"DE",
    "sg:address":"R\u00f6merstr. 5",
    "sg:city":"Mainz",
    "sg:phone":"+49 6136/42341",
    "sg:postcode":"55129",
    "sg:province":"Rheinland-Pfalz",
    "wof:name":"Fremdenzimmer-gastst\u00e4tte Darmst\u00e4dter Hof",
    "wof:placetype":"venue"
},
  "geometry": {"coordinates":[8.2450399399,49.9137535095],"type":"Point"}
}