{
  "type": "Feature",
  "properties": {
    "iso:country":"DE",
    "sg:address":"Schnatgang 16",
    "sg:city":"Osnabr\u00fcck",
    "sg:phone":"+49 541/431813",
    "sg:postcode":"49080",
    "sg:province":"Niedersachsen",
    "wof:name":"Korte Nachf. Ingenieurgemeinschaft",
    "wof:placetype":"venue"
},
  "geometry": {"coordinates":[8.0370254517,52.2703323364],"type":"Point"}
}