{
  "type": "Feature",
  "properties": {
    "iso:country":"DE",
    "sg:address":"Oberschlesische Str. 10",
    "sg:city":"M\u00fcnchen",
    "sg:phone":"+49 89/931360",
    "sg:postcode":"81929",
    "sg:province":"Bayern",
    "wof:name":"Egon Ebenberk Transporte Gmbh",
    "wof:placetype":"venue"
},
  "geometry": {"coordinates":[11.6522092819,48.148223877],"type":"Point"}
}