{
  "type": "Feature",
  "properties": {
    "iso:country":"DE",
    "sg:address":"Sebachstr. 23",
    "sg:city":"Neunkirchen",
    "sg:phone":"+49 6821/93010",
    "sg:postcode":"66539",
    "sg:province":"Saarland",
    "wof:name":"Ratzky Gmbh",
    "wof:placetype":"venue"
},
  "geometry": {"coordinates":[7.228128,49.325253],"type":"Point"}
}