{
  "type": "Feature",
  "properties": {
    "iso:country":"DE",
    "sg:address":"Ludwig-Marum-Str. 13",
    "sg:city":"Karlsruhe",
    "sg:phone":"+49 721/984420",
    "sg:postcode":"76185",
    "sg:province":"Baden-W\u00fcrttemberg",
    "wof:name":"Rechtsanw\u00e4lte Honold Und Partner",
    "wof:placetype":"venue"
},
  "geometry": {"coordinates":[8.3715286255,49.0133972168],"type":"Point"}
}