{
  "type": "Feature",
  "properties": {
    "iso:country":"DE",
    "sg:address":"Schaan 39",
    "sg:city":"J\u00fcchen",
    "sg:phone":"+49 2165/375",
    "sg:postcode":"41363",
    "sg:province":"Nordrhein-Westfalen",
    "wof:name":"Theo Deweth Alt- Und Abfallstoffe",
    "wof:placetype":"venue"
},
  "geometry": {"coordinates":[6.487267,51.112251],"type":"Point"}
}