{
  "type": "Feature",
  "properties": {
    "iso:country":"DE",
    "sg:address":"Neustr. 19",
    "sg:city":"Selfkant",
    "sg:phone":"+49 2456/504070",
    "sg:postcode":"52538",
    "sg:province":"Nordrhein-Westfalen",
    "wof:name":"Willi Und Doris Ruers",
    "wof:placetype":"venue"
},
  "geometry": {"coordinates":[5.89618,51.013344],"type":"Point"}
}