{
  "type": "Feature",
  "properties": {
    "iso:country":"DE",
    "sg:address":"Wei\u00dfensteinerhof 1",
    "sg:city":"Busenberg",
    "sg:phone":"+49 6394/3559",
    "sg:postcode":"76891",
    "sg:province":"Rheinland-Pfalz",
    "wof:name":"M. M\u00fcller",
    "wof:placetype":"venue"
},
  "geometry": {"coordinates":[7.8385257721,49.1219139099],"type":"Point"}
}