{
  "type": "Feature",
  "properties": {
    "iso:country":"DE",
    "sg:address":"Hindenburgstr. 176",
    "sg:city":"Gingen",
    "sg:phone":"+49 7162/8310",
    "sg:postcode":"73333",
    "sg:province":"Baden-W\u00fcrttemberg",
    "wof:name":"Heinz Sauer Ingenieurb\u00fcro",
    "wof:placetype":"venue"
},
  "geometry": {"coordinates":[9.7821998596,48.6536483765],"type":"Point"}
}