{
  "type": "Feature",
  "properties": {
    "iso:country":"DE",
    "sg:address":"Zum Bussen 31",
    "sg:city":"Uttenweiler",
    "sg:phone":"+49 7374/353",
    "sg:postcode":"88524",
    "sg:province":"Baden-W\u00fcrttemberg",
    "wof:name":"A. Und E. Kegel",
    "wof:placetype":"venue"
},
  "geometry": {"coordinates":[9.5554504395,48.1600799561],"type":"Point"}
}