{
  "type": "Feature",
  "properties": {
    "iso:country":"DE",
    "sg:address":"Burgkirchener Str. 10",
    "sg:city":"T\u00fc\u00dfling",
    "sg:phone":"+49 8633/1285",
    "sg:postcode":"84577",
    "sg:province":"Bayern",
    "wof:name":"Sportgastst\u00e4tte",
    "wof:placetype":"venue"
},
  "geometry": {"coordinates":[12.5971813202,48.2126121521],"type":"Point"}
}