{
  "type": "Feature",
  "properties": {
    "iso:country":"DE",
    "sg:address":"Watzlikstr. 32",
    "sg:city":"Lappersdorf",
    "sg:phone":"+49 941/83845",
    "sg:postcode":"93138",
    "sg:province":"Bayern",
    "wof:name":"Speck Pumpen",
    "wof:placetype":"venue"
},
  "geometry": {"coordinates":[12.07268,49.051048],"type":"Point"}
}