{
  "type": "Feature",
  "properties": {
    "iso:country":"DE",
    "sg:address":"Scheffelstr. 1",
    "sg:city":"K\u00f6ln",
    "sg:phone":"+49 221/434575",
    "sg:postcode":"50935",
    "sg:province":"Nordrhein-Westfalen",
    "wof:name":"Lindenthaler Fleischmarkt",
    "wof:placetype":"venue"
},
  "geometry": {"coordinates":[6.9108262062,50.9252281189],"type":"Point"}
}