{
  "type": "Feature",
  "properties": {
    "iso:country":"DE",
    "sg:address":"Reuschstr 58",
    "sg:city":"Heiningen",
    "sg:phone":"+49 7161/40390",
    "sg:postcode":"73092",
    "sg:province":"Baden-W\u00fcrttemberg",
    "wof:name":"Smc Siegfried Mayer Gmbh & Co",
    "wof:placetype":"venue"
},
  "geometry": {"coordinates":[9.6424245834,48.6549377441],"type":"Point"}
}