{
  "type": "Feature",
  "properties": {
    "iso:country":"DE",
    "sg:address":"S\u00e4gestr.37",
    "sg:city":"Herrischried",
    "sg:phone":"+49 7764/1026",
    "sg:postcode":"79737",
    "sg:province":"Baden-W\u00fcrttemberg",
    "wof:name":"Divyanand-foundation",
    "wof:placetype":"venue"
},
  "geometry": {"coordinates":[7.988562,47.662125],"type":"Point"}
}