{
  "type": "Feature",
  "properties": {
    "iso:country":"DE",
    "sg:address":"K\u00f6nigstr. 12",
    "sg:city":"Wetter",
    "sg:phone":"+49 2335/3257",
    "sg:postcode":"58300",
    "sg:province":"Nordrhein-Westfalen",
    "wof:name":"U. Lipphardt Haus- Und K\u00fcchenger\u00e4te",
    "wof:placetype":"venue"
},
  "geometry": {"coordinates":[7.3965082169,51.3882331848],"type":"Point"}
}