{
  "type": "Feature",
  "properties": {
    "iso:country":"DE",
    "sg:address":"Stefan-George-Ring 19",
    "sg:city":"M\u00fcnchen",
    "sg:phone":"+49 89/9930920",
    "sg:postcode":"81929",
    "sg:province":"Bayern",
    "wof:name":"Axel Schnitzspahn Rechtsanwalt",
    "wof:placetype":"venue"
},
  "geometry": {"coordinates":[11.6477766037,48.1410446167],"type":"Point"}
}