{
  "type": "Feature",
  "properties": {
    "iso:country":"DE",
    "sg:address":"Hauptstr. 34d",
    "sg:city":"Offenburg",
    "sg:phone":"+49 781/91750",
    "sg:postcode":"77652",
    "sg:province":"Baden-W\u00fcrttemberg",
    "wof:name":"Landeszentralbank In Baden-w\u00fcrttemberg",
    "wof:placetype":"venue"
},
  "geometry": {"coordinates":[7.9444799423,48.4743499756],"type":"Point"}
}