{
  "type": "Feature",
  "properties": {
    "iso:country":"DE",
    "sg:address":"Olgastr. 2",
    "sg:city":"Friedrichshafen",
    "sg:phone":"+49 7541/35214",
    "sg:postcode":"88045",
    "sg:province":"Baden-W\u00fcrttemberg",
    "wof:name":"P. Niepel Kg",
    "wof:placetype":"venue"
},
  "geometry": {"coordinates":[9.467134,47.649849],"type":"Point"}
}