{
  "type": "Feature",
  "properties": {
    "iso:country":"DE",
    "sg:address":"Hauptstr. 22",
    "sg:city":"B\u00fcren",
    "sg:phone":"+49 2951/4492",
    "sg:postcode":"33142",
    "sg:province":"Nordrhein-Westfalen",
    "wof:name":"Johannes Kramps",
    "wof:placetype":"venue"
},
  "geometry": {"coordinates":[8.629446,51.529472],"type":"Point"}
}