{
  "type": "Feature",
  "properties": {
    "iso:country":"DE",
    "sg:address":"59602",
    "sg:city":"R\u00fcthen",
    "sg:phone":"+49 2952/1651",
    "sg:postcode":"59602",
    "sg:province":"Nordrhein-Westfalen",
    "wof:name":"Fernleitungs-betriebsges. Mbh",
    "wof:placetype":"venue"
},
  "geometry": {"coordinates":[8.4502601624,51.5019302368],"type":"Point"}
}