{
  "type": "Feature",
  "properties": {
    "iso:country":"DE",
    "sg:address":"Bornhardtstr. 10",
    "sg:city":"Goslar",
    "sg:phone":"+49 5321/388454",
    "sg:postcode":"38644",
    "sg:province":"Niedersachsen",
    "wof:name":"Ursula Tietz Verwaltungs-gmbh",
    "wof:placetype":"venue"
},
  "geometry": {"coordinates":[10.4191207886,51.9243049622],"type":"Point"}
}