{
  "type": "Feature",
  "properties": {
    "iso:country":"DE",
    "sg:address":"Heidestr. 283a",
    "sg:city":"Dessau",
    "sg:phone":"+49 340/800390",
    "sg:postcode":"06849",
    "sg:province":"Sachsen-Anhalt",
    "wof:name":"Tv Dessau Fernsehgesellschaft Mbh",
    "wof:placetype":"venue"
},
  "geometry": {"coordinates":[12.2413797379,51.8017616272],"type":"Point"}
}