{
  "type": "Feature",
  "properties": {
    "iso:country":"DE",
    "sg:address":"Bahnhofstr. 19",
    "sg:city":"Hainichen",
    "sg:phone":"+49 37207/2672",
    "sg:postcode":"09661",
    "sg:province":"Sachsen",
    "wof:name":"Harald Becker",
    "wof:placetype":"venue"
},
  "geometry": {"coordinates":[13.1199979782,50.9702301025],"type":"Point"}
}