{
  "type": "Feature",
  "properties": {
    "iso:country":"DE",
    "sg:address":"Buchenfeldstr. 2",
    "sg:city":"Stutensee",
    "sg:phone":"+49 7249/7222",
    "sg:postcode":"76297",
    "sg:province":"Baden-W\u00fcrttemberg",
    "wof:name":"Marion Liebsch Immobilien Gmbh",
    "wof:placetype":"venue"
},
  "geometry": {"coordinates":[8.4780902863,49.1010780334],"type":"Point"}
}