{
  "type": "Feature",
  "properties": {
    "iso:country":"DE",
    "sg:address":"Herzog-Wilhelm-Str. 48",
    "sg:city":"Bad Harzburg",
    "sg:phone":"+49 5322/50364",
    "sg:postcode":"38667",
    "sg:province":"Niedersachsen",
    "wof:name":"Mythos Gastst\u00e4tten Gmbh",
    "wof:placetype":"venue"
},
  "geometry": {"coordinates":[10.5589675903,51.8826675415],"type":"Point"}
}