{
  "type": "Feature",
  "properties": {
    "iso:country":"DE",
    "sg:address":"Reichenberger Str. 52",
    "sg:city":"Waldkraiburg",
    "sg:phone":"+49 8638/4841",
    "sg:postcode":"84478",
    "sg:province":"Bayern",
    "wof:name":"Heinz Wachter Elektroinstallation",
    "wof:placetype":"venue"
},
  "geometry": {"coordinates":[12.401975,48.200882],"type":"Point"}
}