{
  "type": "Feature",
  "properties": {
    "iso:country":"DE",
    "sg:address":"Reichenaustr. 210",
    "sg:city":"Konstanz",
    "sg:phone":"+49 7531/58060",
    "sg:postcode":"78467",
    "sg:province":"Baden-W\u00fcrttemberg",
    "wof:name":"Spirax Sarco Gmbh",
    "wof:placetype":"venue"
},
  "geometry": {"coordinates":[9.1567668915,47.6738624573],"type":"Point"}
}