{
  "type": "Feature",
  "properties": {
    "iso:country":"DE",
    "sg:address":"Au\u00dferhalb 999",
    "sg:city":"St Johann",
    "sg:phone":"+49 6701/8326",
    "sg:postcode":"55578",
    "sg:province":"Rheinland-Pfalz",
    "wof:name":"Golfshop Des Golfclubs Rhein- Hessen-hofgut Wi\u00dfberg",
    "wof:placetype":"venue"
},
  "geometry": {"coordinates":[8.028375,49.851501],"type":"Point"}
}