{
  "type": "Feature",
  "properties": {
    "iso:country":"DE",
    "sg:address":"Glogauer Str. 23",
    "sg:city":"Saarbr\u00fccken",
    "sg:phone":"+49 681/71011",
    "sg:postcode":"66121",
    "sg:province":"Saarland",
    "wof:name":"Horst Uhl Gmbh",
    "wof:placetype":"venue"
},
  "geometry": {"coordinates":[7.0469942093,49.2312545776],"type":"Point"}
}