{
  "type": "Feature",
  "properties": {
    "iso:country":"DE",
    "sg:address":"K\u00f6nigsgarten 7",
    "sg:city":"Weidenbach",
    "sg:phone":"+49 6599/251",
    "sg:postcode":"54570",
    "sg:province":"Rheinland-Pfalz",
    "wof:name":"Herbert Zwilling",
    "wof:placetype":"venue"
},
  "geometry": {"coordinates":[6.707323,50.12841],"type":"Point"}
}