{
  "type": "Feature",
  "properties": {
    "iso:country":"DE",
    "sg:address":"Reichswaldstr. 30",
    "sg:city":"Kaiserslautern",
    "sg:phone":"+49 631/74385",
    "sg:postcode":"67663",
    "sg:province":"Rheinland-Pfalz",
    "wof:name":"Kath. Pfarramt St. Konrad",
    "wof:placetype":"venue"
},
  "geometry": {"coordinates":[7.7428798676,49.4419403076],"type":"Point"}
}