{
  "type": "Feature",
  "properties": {
    "iso:country":"DE",
    "sg:address":"Hauptstr 13a",
    "sg:city":"Berlin",
    "sg:phone":"+49 30/4740090",
    "sg:postcode":"13127",
    "sg:province":"Berlin",
    "wof:name":"S.s.e. Trade & B\u00fcroservice Gmbh",
    "wof:placetype":"venue"
},
  "geometry": {"coordinates":[13.4323215485,52.6051254272],"type":"Point"}
}