{
  "type": "Feature",
  "properties": {
    "iso:country":"DE",
    "sg:address":"Am Pichelssee 50",
    "sg:city":"Berlin",
    "sg:phone":"+49 30/3612084",
    "sg:postcode":"13595",
    "sg:province":"Berlin",
    "wof:name":"Bootsst\u00e4nde G\u00fcnter Angermann & Co.",
    "wof:placetype":"venue"
},
  "geometry": {"coordinates":[13.1997003555,52.5097618103],"type":"Point"}
}