{
  "type": "Feature",
  "properties": {
    "iso:country":"DE",
    "sg:address":"Brandlberger Str. 77",
    "sg:city":"Regensburg",
    "sg:phone":"+49 941/48305",
    "sg:postcode":"93057",
    "sg:province":"Bayern",
    "wof:name":"Helga Schrepfer",
    "wof:placetype":"venue"
},
  "geometry": {"coordinates":[12.1167078018,49.0350532532],"type":"Point"}
}