{
  "type": "Feature",
  "properties": {
    "iso:country":"DE",
    "sg:address":"Hugenottenstr. 22",
    "sg:city":"Friedrichsdorf",
    "sg:phone":"+49 6172/75136",
    "sg:postcode":"61381",
    "sg:province":"Hessen",
    "wof:name":"Rainer Hild",
    "wof:placetype":"venue"
},
  "geometry": {"coordinates":[8.6359224319,50.2539176941],"type":"Point"}
}