{
  "type": "Feature",
  "properties": {
    "iso:country":"DE",
    "sg:address":"Annaturmstr. 25",
    "sg:city":"Euskirchen",
    "sg:phone":"+49 2251/95000",
    "sg:postcode":"53879",
    "sg:province":"Nordrhein-Westfalen",
    "wof:name":"Theo Embgenbroich Steuerberater",
    "wof:placetype":"venue"
},
  "geometry": {"coordinates":[6.7856688499,50.6623840332],"type":"Point"}
}