{
  "type": "Feature",
  "properties": {
    "iso:country":"DE",
    "sg:address":"B\u00f6hringer Str. 42 /1",
    "sg:city":"Grabenstetten",
    "sg:phone":"+49 7382/5362",
    "sg:postcode":"72582",
    "sg:province":"Baden-W\u00fcrttemberg",
    "wof:name":"Biona Bettenvertrieb S. Jarkovsky Gmbh",
    "wof:placetype":"venue"
},
  "geometry": {"coordinates":[9.4611082077,48.5206489563],"type":"Point"}
}