{
  "type": "Feature",
  "properties": {
    "iso:country":"DE",
    "sg:address":"Regenstr. 1",
    "sg:city":"Herrenberg",
    "sg:phone":"+49 7032/31338",
    "sg:postcode":"71083",
    "sg:province":"Baden-W\u00fcrttemberg",
    "wof:name":"R. Tretschok",
    "wof:placetype":"venue"
},
  "geometry": {"coordinates":[8.8306283951,48.6233711243],"type":"Point"}
}