{
  "type": "Feature",
  "properties": {
    "iso:country":"DE",
    "sg:address":"Im Westerwinkel 6",
    "sg:city":"Espelkamp",
    "sg:phone":"+49 5743/8575",
    "sg:postcode":"32339",
    "sg:province":"Nordrhein-Westfalen",
    "wof:name":"Wilfried Daniel Architekt",
    "wof:placetype":"venue"
},
  "geometry": {"coordinates":[8.615884,52.350815],"type":"Point"}
}