{
  "type": "Feature",
  "properties": {
    "iso:country":"DE",
    "sg:address":"Taubenstr. 7",
    "sg:city":"Moosburg",
    "sg:phone":"+49 8761/4779",
    "sg:postcode":"85368",
    "sg:province":"Bayern",
    "wof:name":"Adolf Grindl Architekt",
    "wof:placetype":"venue"
},
  "geometry": {"coordinates":[11.936375,48.49445],"type":"Point"}
}