{
  "type": "Feature",
  "properties": {
    "iso:country":"DE",
    "sg:address":"Schildhornstr. 72",
    "sg:city":"Berlin",
    "sg:phone":"+49 30/7911097",
    "sg:postcode":"12163",
    "sg:province":"Berlin",
    "wof:name":"Mako Heribert Klein Gmbh",
    "wof:placetype":"venue"
},
  "geometry": {"coordinates":[13.316931,52.46402],"type":"Point"}
}