{
  "type": "Feature",
  "properties": {
    "iso:country":"DE",
    "sg:address":"Sandolfstr. 10",
    "sg:city":"Mainburg",
    "sg:phone":"+49 8751/1509",
    "sg:postcode":"84048",
    "sg:province":"Bayern",
    "wof:name":"Kath. Pfarramt St. Jakobus",
    "wof:placetype":"venue"
},
  "geometry": {"coordinates":[11.7922210693,48.6252632141],"type":"Point"}
}