{
  "type": "Feature",
  "properties": {
    "iso:country":"DE",
    "sg:address":"Stockumer Str. 38",
    "sg:city":"Sundern",
    "sg:phone":"+49 2933/1085",
    "sg:postcode":"59846",
    "sg:province":"Nordrhein-Westfalen",
    "wof:name":"Helmut Krengel",
    "wof:placetype":"venue"
},
  "geometry": {"coordinates":[7.9892711639,51.28698349],"type":"Point"}
}