{
  "type": "Feature",
  "properties": {
    "iso:country":"DE",
    "sg:address":"Wilh-Theo-R\u00f6mheld-Str 30",
    "sg:city":"Mainz",
    "sg:postcode":"55130",
    "sg:province":"Rheinland-Pfalz",
    "wof:name":"Makimono Grundst\u00fccksver- Waltungsgesellschaft Mbh",
    "wof:placetype":"venue"
},
  "geometry": {"coordinates":[8.289598465,49.9821052551],"type":"Point"}
}