{
  "type": "Feature",
  "properties": {
    "iso:country":"DE",
    "sg:address":"Tauernallee 11",
    "sg:city":"Berlin",
    "sg:phone":"+49 4930/3990106",
    "sg:postcode":"12107",
    "sg:province":"Berlin",
    "wof:name":"Wichmann K\u00c4lte- & Klimatechnik Gmbh",
    "wof:placetype":"venue"
},
  "geometry": {"coordinates":[13.397622,52.424309],"type":"Point"}
}