{
  "type": "Feature",
  "properties": {
    "iso:country":"DE",
    "sg:address":"Birkenweg 1",
    "sg:city":"Forstern",
    "sg:postcode":"85659",
    "sg:province":"Bayern",
    "wof:name":"Belos Gesellschaft F\u00fcr Projektentwicklung Und",
    "wof:placetype":"venue"
},
  "geometry": {"coordinates":[11.9762849808,48.1814651489],"type":"Point"}
}