{
  "type": "Feature",
  "properties": {
    "iso:country":"DE",
    "sg:address":"Uhlandstr. 8",
    "sg:city":"Mutterstadt",
    "sg:phone":"+49 6234/929923",
    "sg:postcode":"67112",
    "sg:province":"Rheinland-Pfalz",
    "wof:name":"H\u00fcbner",
    "wof:placetype":"venue"
},
  "geometry": {"coordinates":[8.34981,49.440144],"type":"Point"}
}