{
  "type": "Feature",
  "properties": {
    "iso:country":"DE",
    "sg:address":"W\u00fchn 32",
    "sg:city":"Grafling",
    "sg:phone":"+49 991/2708761",
    "sg:postcode":"94539",
    "sg:province":"Bayern",
    "wof:name":"Baubetreuung-bodensysteme Gmbh",
    "wof:placetype":"venue"
},
  "geometry": {"coordinates":[12.97293,48.8806],"type":"Point"}
}