{
  "type": "Feature",
  "properties": {
    "iso:country":"DE",
    "sg:address":"Eibenstocker Str. 14",
    "sg:city":"Zschorlau",
    "sg:phone":"+49 3771/458341",
    "sg:postcode":"08321",
    "sg:province":"Sachsen",
    "wof:name":"Jens Reinhold",
    "wof:placetype":"venue"
},
  "geometry": {"coordinates":[12.639589,50.561493],"type":"Point"}
}