{
  "type": "Feature",
  "properties": {
    "iso:country":"DE",
    "sg:address":"Jocketaer Str. 99",
    "sg:city":"Plauen",
    "sg:phone":"+49 3741/133523",
    "sg:postcode":"08525",
    "sg:province":"Sachsen",
    "wof:name":"Ofen- Und Fliesenfachgesch\u00e4ft V\u00f6lker Gmbh",
    "wof:placetype":"venue"
},
  "geometry": {"coordinates":[12.1493425369,50.5272254944],"type":"Point"}
}