{
  "type": "Feature",
  "properties": {
    "iso:country":"DE",
    "sg:address":"Georg-Wilhelm-Stra\u00dfe",
    "sg:city":"Hamburg",
    "sg:phone":"+49 40/7524890",
    "sg:postcode":"21107",
    "sg:province":"Hamburg",
    "wof:name":"Bauverein Reiherstieg Eg",
    "wof:placetype":"venue"
},
  "geometry": {"coordinates":[9.9933395386,53.5158195496],"type":"Point"}
}