{
  "type": "Feature",
  "properties": {
    "iso:country":"DE",
    "sg:address":"Marburger Str. 58",
    "sg:city":"Gie\u00dfen",
    "sg:phone":"+49 641/31434",
    "sg:postcode":"35396",
    "sg:province":"Hessen",
    "wof:name":"Na Und",
    "wof:placetype":"venue"
},
  "geometry": {"coordinates":[8.682094574,50.5948410034],"type":"Point"}
}