{
  "type": "Feature",
  "properties": {
    "iso:country":"DE",
    "sg:address":"Marzahner Promenade 17",
    "sg:city":"Berlin",
    "sg:phone":"+49 30/9309820",
    "sg:postcode":"12679",
    "sg:province":"Berlin",
    "wof:name":"Jahresringe E. V.",
    "wof:placetype":"venue"
},
  "geometry": {"coordinates":[13.5462903976,52.5424804688],"type":"Point"}
}