{
  "type": "Feature",
  "properties": {
    "iso:country":"DE",
    "sg:address":"Peckeloh",
    "sg:city":"Versmold",
    "sg:phone":"+49 5423/8229",
    "sg:postcode":"33775",
    "sg:province":"Nordrhein-Westfalen",
    "wof:name":"Heinrich Hoff",
    "wof:placetype":"venue"
},
  "geometry": {"coordinates":[8.1237201691,52.0204353333],"type":"Point"}
}