{
  "type": "Feature",
  "properties": {
    "iso:country":"DE",
    "sg:address":"Bahnhofstr. 26",
    "sg:city":"Obrigheim",
    "sg:phone":"+49 6359/84490",
    "sg:postcode":"67283",
    "sg:province":"Rheinland-Pfalz",
    "wof:name":"Gerhard Demel Gmbh",
    "wof:placetype":"venue"
},
  "geometry": {"coordinates":[8.1792526245,49.5803794861],"type":"Point"}
}