{
  "type": "Feature",
  "properties": {
    "iso:country":"DE",
    "sg:address":"Kohlmarkt 1",
    "sg:city":"Braunschweig",
    "sg:phone":"+49 531/400695",
    "sg:postcode":"38100",
    "sg:province":"Niedersachsen",
    "wof:name":"Bijou Brigitte Modische Accessoires Ag",
    "wof:placetype":"venue"
},
  "geometry": {"coordinates":[10.520162,52.26263],"type":"Point"}
}