{
  "type": "Feature",
  "properties": {
    "iso:country":"DE",
    "sg:address":"Deichreihe 1",
    "sg:city":"Kollmar",
    "sg:phone":"+49 4128/221",
    "sg:postcode":"25377",
    "sg:province":"Schleswig-Holstein",
    "wof:name":"Ernst-hermann M\u00f6ller",
    "wof:placetype":"venue"
},
  "geometry": {"coordinates":[9.46409,53.732368],"type":"Point"}
}