{
  "type": "Feature",
  "properties": {
    "iso:country":"DE",
    "sg:address":"Friedrichstr. 41",
    "sg:city":"Dresden",
    "sg:postcode":"01067",
    "sg:province":"Sachsen",
    "wof:name":"Marcolinipalais",
    "wof:placetype":"venue"
},
  "geometry": {"coordinates":[13.717444,51.059956],"type":"Point"}
}