{
  "type": "Feature",
  "properties": {
    "iso:country":"DE",
    "sg:address":"Goethestr. 13",
    "sg:city":"Oberderdingen",
    "sg:phone":"+49 7045/8939",
    "sg:postcode":"75038",
    "sg:province":"Baden-W\u00fcrttemberg",
    "wof:name":"Johann Feijao Masseur",
    "wof:placetype":"venue"
},
  "geometry": {"coordinates":[8.797088,49.065697],"type":"Point"}
}