{
  "type": "Feature",
  "properties": {
    "iso:country":"DE",
    "sg:address":"Hauptstr. 53",
    "sg:city":"Gro\u00df Gr\u00f6nau",
    "sg:phone":"+49 4509/2772",
    "sg:postcode":"23627",
    "sg:province":"Schleswig-Holstein",
    "wof:name":"Wabo Steuerberatungs Gmbh",
    "wof:placetype":"venue"
},
  "geometry": {"coordinates":[10.7498588562,53.8053817749],"type":"Point"}
}