{
  "type": "Feature",
  "properties": {
    "iso:country":"DE",
    "sg:address":"Zehlendorfer Weg 15 a",
    "sg:city":"Weitendorf",
    "sg:postcode":"18299",
    "sg:province":"Mecklenburg-Vorpommern",
    "wof:name":"Sako Gmbh",
    "wof:placetype":"venue"
},
  "geometry": {"coordinates":[12.3469247818,53.9287796021],"type":"Point"}
}