{
  "type": "Feature",
  "properties": {
    "iso:country":"DE",
    "sg:address":"Pichelsdorfer Str. 91",
    "sg:city":"Berlin",
    "sg:phone":"+49 30/3311428",
    "sg:postcode":"13595",
    "sg:province":"Berlin",
    "wof:name":"Wolfgang Mandelkow",
    "wof:placetype":"venue"
},
  "geometry": {"coordinates":[13.1975193024,52.523109436],"type":"Point"}
}