{
  "type": "Feature",
  "properties": {
    "iso:country":"DE",
    "sg:address":"Sudetendeutsche Str. 3 a",
    "sg:city":"Straubing",
    "sg:phone":"+49 9421/6780",
    "sg:postcode":"94315",
    "sg:province":"Bayern",
    "wof:name":"Heinrich Kraus",
    "wof:placetype":"venue"
},
  "geometry": {"coordinates":[12.5999507904,48.8886146545],"type":"Point"}
}