{
  "type": "Feature",
  "properties": {
    "iso:country":"DE",
    "sg:address":"Feldstr. 41",
    "sg:city":"Saarlouis",
    "sg:phone":"+49 6831/42495",
    "sg:postcode":"66740",
    "sg:province":"Saarland",
    "wof:name":"Mathias M\u00fcller",
    "wof:placetype":"venue"
},
  "geometry": {"coordinates":[6.7596158981,49.304019928],"type":"Point"}
}