{
  "type": "Feature",
  "properties": {
    "iso:country":"DE",
    "sg:address":"Helmstedter Str. 163",
    "sg:city":"Braunschweig",
    "sg:phone":"+49 531/791798",
    "sg:postcode":"38102",
    "sg:province":"Niedersachsen",
    "wof:name":"Pilgrim-translations",
    "wof:placetype":"venue"
},
  "geometry": {"coordinates":[10.537609,52.262302],"type":"Point"}
}