{
  "type": "Feature",
  "properties": {
    "iso:country":"DE",
    "sg:address":"Braker Weg 44",
    "sg:city":"Lemgo",
    "sg:phone":"+49 5261/71581",
    "sg:postcode":"32657",
    "sg:province":"Nordrhein-Westfalen",
    "wof:name":"Christian Tasche Spedition Gmbh",
    "wof:placetype":"venue"
},
  "geometry": {"coordinates":[8.90584,52.021942],"type":"Point"}
}