{
  "type": "Feature",
  "properties": {
    "iso:country":"DE",
    "sg:address":"Schierenbeckstr. 20",
    "sg:city":"Bremen",
    "sg:phone":"+49 421/831255",
    "sg:postcode":"28279",
    "sg:province":"Bremen",
    "wof:name":"Hanns-peter Karl Architekt",
    "wof:placetype":"venue"
},
  "geometry": {"coordinates":[8.853807,53.051434],"type":"Point"}
}