{
  "type": "Feature",
  "properties": {
    "iso:country":"DE",
    "sg:address":"Verbindungsstr. 24 a",
    "sg:city":"Langenfeld",
    "sg:phone":"+49 212/60840",
    "sg:postcode":"40764",
    "sg:province":"Nordrhein-Westfalen",
    "wof:name":"Gisela Hofbeck Steuerberaterin",
    "wof:placetype":"venue"
},
  "geometry": {"coordinates":[6.9935832024,51.1345901489],"type":"Point"}
}