{
  "type": "Feature",
  "properties": {
    "iso:country":"DE",
    "sg:address":"Graf-Ulrich-Str. 7",
    "sg:city":"Leonberg",
    "sg:phone":"+49 7152/94730",
    "sg:postcode":"71229",
    "sg:province":"Baden-W\u00fcrttemberg",
    "wof:name":"Karl Ziegler Gmbh",
    "wof:placetype":"venue"
},
  "geometry": {"coordinates":[9.0160894394,48.8022499084],"type":"Point"}
}