{
  "type": "Feature",
  "properties": {
    "iso:country":"DE",
    "sg:address":"Daimlerstr. 2",
    "sg:city":"Hilpoltstein",
    "sg:postcode":"91161",
    "sg:province":"Bayern",
    "wof:name":"Spr\u00fcgel Hometex Gmbh",
    "wof:placetype":"venue"
},
  "geometry": {"coordinates":[11.1791706085,49.1817169189],"type":"Point"}
}