{
  "type": "Feature",
  "properties": {
    "iso:country":"DE",
    "sg:address":"Im Grunde 12",
    "sg:city":"Baunatal",
    "sg:phone":"+49 561/497770",
    "sg:postcode":"34225",
    "sg:province":"Hessen",
    "wof:name":"Rosemarie Gibhardt Steuerberaterin",
    "wof:placetype":"venue"
},
  "geometry": {"coordinates":[9.4569988251,51.2551765442],"type":"Point"}
}