{
  "type": "Feature",
  "properties": {
    "iso:country":"DE",
    "sg:address":"Schlo\u00dfbergstr. 22",
    "sg:city":"Starnberg",
    "sg:phone":"+49 8151/16242",
    "sg:postcode":"82319",
    "sg:province":"Bayern",
    "wof:name":"Wilhelm P. Ruhdorfer Architekt",
    "wof:placetype":"venue"
},
  "geometry": {"coordinates":[11.33761,47.997578],"type":"Point"}
}