{
  "type": "Feature",
  "properties": {
    "iso:country":"DE",
    "sg:address":"Silberstr. 4",
    "sg:city":"L\u00fcnen",
    "sg:phone":"+49 2306/257474",
    "sg:postcode":"44532",
    "sg:province":"Nordrhein-Westfalen",
    "wof:name":"Anette Weber",
    "wof:placetype":"venue"
},
  "geometry": {"coordinates":[7.5225458145,51.6122360229],"type":"Point"}
}