{
  "type": "Feature",
  "properties": {
    "iso:country":"DE",
    "sg:address":"Hauptstr. 49",
    "sg:city":"Laumersheim",
    "sg:phone":"+49 6238/742",
    "sg:postcode":"67229",
    "sg:province":"Rheinland-Pfalz",
    "wof:name":"Knipser Weingut Johannishof",
    "wof:placetype":"venue"
},
  "geometry": {"coordinates":[8.2375869751,49.5522460938],"type":"Point"}
}