{
  "type": "Feature",
  "properties": {
    "iso:country":"DE",
    "sg:address":"Herner Str. 103",
    "sg:city":"Bochum",
    "sg:phone":"+49 234/582909",
    "sg:postcode":"44791",
    "sg:province":"Nordrhein-Westfalen",
    "wof:name":"Dusza",
    "wof:placetype":"venue"
},
  "geometry": {"coordinates":[7.2130718231,51.4918556213],"type":"Point"}
}