{
  "type": "Feature",
  "properties": {
    "iso:country":"DE",
    "sg:address":"Bochumer Str. 34",
    "sg:city":"Dorsten",
    "sg:phone":"+49 2362/22389",
    "sg:postcode":"46282",
    "sg:province":"Nordrhein-Westfalen",
    "wof:name":"Willi Geismann",
    "wof:placetype":"venue"
},
  "geometry": {"coordinates":[6.97431,51.657696],"type":"Point"}
}