{
  "type": "Feature",
  "properties": {
    "iso:country":"DE",
    "sg:address":"Fremersdorfer Str. 12",
    "sg:city":"Merzig",
    "sg:phone":"+49 6861/791046",
    "sg:postcode":"66663",
    "sg:province":"Saarland",
    "wof:name":"Richtig Geld Verdienen Nur Mit Dem Pc",
    "wof:placetype":"venue"
},
  "geometry": {"coordinates":[6.629705,49.418911],"type":"Point"}
}