{
  "type": "Feature",
  "properties": {
    "iso:country":"DE",
    "sg:address":"Schulweg 6",
    "sg:city":"Ennigerloh",
    "sg:phone":"+49 2524/5756",
    "sg:postcode":"59320",
    "sg:province":"Nordrhein-Westfalen",
    "wof:name":"Ev. Pfarramt Vers\u00f6hnungskirche",
    "wof:placetype":"venue"
},
  "geometry": {"coordinates":[8.025894165,51.8337211609],"type":"Point"}
}