{
  "type": "Feature",
  "properties": {
    "iso:country":"DE",
    "sg:address":"Forstweg 30",
    "sg:city":"Brieselang",
    "sg:phone":"+49 33232/1333",
    "sg:postcode":"14656",
    "sg:province":"Brandenburg",
    "wof:name":"T. Markuse",
    "wof:placetype":"venue"
},
  "geometry": {"coordinates":[12.9868221283,52.5840377808],"type":"Point"}
}