{
  "type": "Feature",
  "properties": {
    "iso:country":"DE",
    "sg:address":"Marktstr. 15 - 17",
    "sg:city":"Kaiserslautern",
    "sg:phone":"+49 4963/124077",
    "sg:postcode":"67655",
    "sg:province":"Rheinland-Pfalz",
    "wof:name":"Noris Bank Gmbh",
    "wof:placetype":"venue"
},
  "geometry": {"coordinates":[7.770522,49.44426],"type":"Point"}
}