{
  "type": "Feature",
  "properties": {
    "iso:country":"DE",
    "sg:address":"Grabenstr. 13",
    "sg:city":"Bad Krozingen",
    "sg:phone":"+49 7633/12328",
    "sg:postcode":"79189",
    "sg:province":"Baden-W\u00fcrttemberg",
    "wof:name":"G. Wei\u00df",
    "wof:placetype":"venue"
},
  "geometry": {"coordinates":[7.701594,47.915432],"type":"Point"}
}