{
  "type": "Feature",
  "properties": {
    "iso:country":"DE",
    "sg:address":"An der Heiden 7",
    "sg:city":"Niederkr\u00fcchten",
    "sg:phone":"+49 2163/83470",
    "sg:postcode":"41372",
    "sg:province":"Nordrhein-Westfalen",
    "wof:name":"Alt Overhetfeld",
    "wof:placetype":"venue"
},
  "geometry": {"coordinates":[6.1591119766,51.2319946289],"type":"Point"}
}