{
  "type": "Feature",
  "properties": {
    "iso:country":"DE",
    "sg:address":"Liebigstr. 39",
    "sg:city":"M\u00fcnchen",
    "sg:phone":"+49 89/224475",
    "sg:postcode":"80538",
    "sg:province":"Bayern",
    "wof:name":"Klaus Waldschmidt Rechtsanwalt",
    "wof:placetype":"venue"
},
  "geometry": {"coordinates":[11.5921859741,48.1407661438],"type":"Point"}
}