{
  "type": "Feature",
  "properties": {
    "iso:country":"DE",
    "sg:address":"H\u00fcserstr. 47",
    "sg:city":"Hamm",
    "sg:postcode":"59075",
    "sg:province":"Nordrhein-Westfalen",
    "wof:name":"Jonas-computer Rainer Niehues",
    "wof:placetype":"venue"
},
  "geometry": {"coordinates":[7.7765679359,51.6865272522],"type":"Point"}
}