{
  "type": "Feature",
  "properties": {
    "iso:country":"DE",
    "sg:address":"L\u00fcbsche Str. 158",
    "sg:city":"Wismar",
    "sg:phone":"+49 3841/734941",
    "sg:postcode":"23966",
    "sg:province":"Mecklenburg-Vorpommern",
    "wof:name":"Kerstin Schott",
    "wof:placetype":"venue"
},
  "geometry": {"coordinates":[11.436924,53.894009],"type":"Point"}
}