{
  "type": "Feature",
  "properties": {
    "iso:country":"DE",
    "sg:address":"Uhdestr. 36",
    "sg:city":"Dresden",
    "sg:phone":"+49 351/4723163",
    "sg:postcode":"01219",
    "sg:province":"Sachsen",
    "wof:name":"S. Strau\u00df",
    "wof:placetype":"venue"
},
  "geometry": {"coordinates":[13.766066,51.016846],"type":"Point"}
}