{
  "type": "Feature",
  "properties": {
    "iso:country":"DE",
    "sg:address":"Lorettostr. 13",
    "sg:city":"Rohr",
    "sg:phone":"+49 8783/91105",
    "sg:postcode":"93352",
    "sg:province":"Bayern",
    "wof:name":"Ludwig Kammermeier",
    "wof:placetype":"venue"
},
  "geometry": {"coordinates":[11.969246,48.765072],"type":"Point"}
}