{
  "type": "Feature",
  "properties": {
    "iso:country":"DE",
    "sg:address":"Gartenstr. 6",
    "sg:city":"Sennfeld",
    "sg:phone":"+49 9721/776060",
    "sg:postcode":"97526",
    "sg:province":"Bayern",
    "wof:name":"Franken-apotheke",
    "wof:placetype":"venue"
},
  "geometry": {"coordinates":[10.25616,50.038692],"type":"Point"}
}