{
  "type": "Feature",
  "properties": {
    "iso:country":"DE",
    "sg:address":"Neue Str. 19",
    "sg:city":"Hagen",
    "sg:phone":"+49 2331/94810",
    "sg:postcode":"58135",
    "sg:province":"Nordrhein-Westfalen",
    "wof:name":"Bamberger Verwaltungs Gmbh",
    "wof:placetype":"venue"
},
  "geometry": {"coordinates":[7.3986091614,51.3377037048],"type":"Point"}
}