{
  "type": "Feature",
  "properties": {
    "iso:country":"DE",
    "sg:address":"Fredersdorfer Str. 31",
    "sg:city":"Bruchm\u00fchle",
    "sg:phone":"+49 33439/6251",
    "sg:postcode":"15370",
    "sg:province":"Brandenburg",
    "wof:name":"Quadriga Bautr\u00e4ger Gmbh",
    "wof:placetype":"venue"
},
  "geometry": {"coordinates":[13.747107,52.54229],"type":"Point"}
}