{
  "type": "Feature",
  "properties": {
    "iso:country":"DE",
    "sg:address":"Rheinstr. 21",
    "sg:city":"Ottersweier",
    "sg:phone":"+49 7223/26586",
    "sg:postcode":"77833",
    "sg:province":"Baden-W\u00fcrttemberg",
    "wof:name":"Hubert Burkart",
    "wof:placetype":"venue"
},
  "geometry": {"coordinates":[8.052429,48.686958],"type":"Point"}
}