{
  "type": "Feature",
  "properties": {
    "iso:country":"DE",
    "sg:address":"Franzberg 4",
    "sg:city":"Iserlohn",
    "sg:phone":"+49 2371/40573",
    "sg:postcode":"58640",
    "sg:province":"Nordrhein-Westfalen",
    "wof:name":"Hans Walter Beielstein",
    "wof:placetype":"venue"
},
  "geometry": {"coordinates":[7.6994228363,51.4052772522],"type":"Point"}
}