{
  "type": "Feature",
  "properties": {
    "iso:country":"DE",
    "sg:address":"Wilhelmstr. 137",
    "sg:city":"W\u00fclfrath",
    "sg:phone":"+49 2058/5113",
    "sg:postcode":"42489",
    "sg:province":"Nordrhein-Westfalen",
    "wof:name":"Inge Klingenburg",
    "wof:placetype":"venue"
},
  "geometry": {"coordinates":[7.036679,51.281906],"type":"Point"}
}