{
  "type": "Feature",
  "properties": {
    "iso:country":"DE",
    "sg:address":"Waldsassener Str. 16",
    "sg:city":"Mitterteich",
    "sg:phone":"+49 9633/526",
    "sg:postcode":"95666",
    "sg:province":"Bayern",
    "wof:name":"H. Brandl",
    "wof:placetype":"venue"
},
  "geometry": {"coordinates":[12.248862,49.953934],"type":"Point"}
}