{
  "type": "Feature",
  "properties": {
    "iso:country":"DE",
    "sg:address":"Arnsberger Weg 5",
    "sg:city":"Holzwickede",
    "sg:phone":"+49 2301/7499",
    "sg:postcode":"59439",
    "sg:province":"Nordrhein-Westfalen",
    "wof:name":"Wolfgang Trennberg",
    "wof:placetype":"venue"
},
  "geometry": {"coordinates":[7.622566,51.500885],"type":"Point"}
}