{
  "type": "Feature",
  "properties": {
    "iso:country":"DE",
    "sg:address":"Holzbacher Str. 5",
    "sg:city":"F\u00fcrstenzell",
    "sg:phone":"+49 8502/1011",
    "sg:postcode":"94081",
    "sg:province":"Bayern",
    "wof:name":"Franz Kitzbichler",
    "wof:placetype":"venue"
},
  "geometry": {"coordinates":[13.3171672821,48.5234909058],"type":"Point"}
}