{
  "type": "Feature",
  "properties": {
    "iso:country":"DE",
    "sg:address":"Westendstr. 13",
    "sg:city":"Freilassing",
    "sg:phone":"+49 8654/62939",
    "sg:postcode":"83395",
    "sg:province":"Bayern",
    "wof:name":"J. W. Filz Datenverarbeitungsanlagen",
    "wof:placetype":"venue"
},
  "geometry": {"coordinates":[12.9626941681,47.838394165],"type":"Point"}
}