{
  "type": "Feature",
  "properties": {
    "iso:country":"DE",
    "sg:address":"Bretzfelder Str. 30",
    "sg:city":"Bretzfeld",
    "sg:phone":"+49 7946/2055",
    "sg:postcode":"74626",
    "sg:province":"Baden-W\u00fcrttemberg",
    "wof:name":"R. Peuker",
    "wof:placetype":"venue"
},
  "geometry": {"coordinates":[9.444523,49.165867],"type":"Point"}
}