{
  "type": "Feature",
  "properties": {
    "iso:country":"DE",
    "sg:address":"Siegener Str. 43",
    "sg:city":"Dillenburg",
    "sg:phone":"+49 2771/34043",
    "sg:postcode":"35683",
    "sg:province":"Hessen",
    "wof:name":"Lei Gesundheit, Fitness, Freizeit Gmbh",
    "wof:placetype":"venue"
},
  "geometry": {"coordinates":[8.2741765976,50.7411727905],"type":"Point"}
}