{
  "type": "Feature",
  "properties": {
    "iso:country":"DE",
    "sg:address":"Isenburger Str. 20",
    "sg:city":"Heusenstamm",
    "sg:phone":"+49 6104/5123",
    "sg:postcode":"63150",
    "sg:province":"Hessen",
    "wof:name":"Aral Ag",
    "wof:placetype":"venue"
},
  "geometry": {"coordinates":[8.7874889374,50.0587463379],"type":"Point"}
}