{
  "type": "Feature",
  "properties": {
    "iso:country":"DE",
    "sg:address":"Innungstr. 27 a",
    "sg:city":"H\u00fcrth",
    "sg:phone":"+49 2233/32520",
    "sg:postcode":"50354",
    "sg:province":"Nordrhein-Westfalen",
    "wof:name":"Scheuer Gmbh",
    "wof:placetype":"venue"
},
  "geometry": {"coordinates":[6.842097,50.893745],"type":"Point"}
}