{
  "type": "Feature",
  "properties": {
    "iso:country":"DE",
    "sg:address":"Im Fuchshau 4",
    "sg:city":"Rudersberg",
    "sg:phone":"+49 7183/938780",
    "sg:postcode":"73635",
    "sg:province":"Baden-W\u00fcrttemberg",
    "wof:name":"Sm-k\u00fcchenstudio Gmbh",
    "wof:placetype":"venue"
},
  "geometry": {"coordinates":[9.5290670395,48.8789176941],"type":"Point"}
}