{
  "type": "Feature",
  "properties": {
    "iso:country":"DE",
    "sg:address":"Paradiesweg 2",
    "sg:city":"Aach",
    "sg:phone":"+49 7774/7182",
    "sg:postcode":"78267",
    "sg:province":"Baden-W\u00fcrttemberg",
    "wof:name":"G\u00e4stehaus Manfred Gogolin",
    "wof:placetype":"venue"
},
  "geometry": {"coordinates":[8.8548650742,47.8418884277],"type":"Point"}
}