{
  "type": "Feature",
  "properties": {
    "iso:country":"DE",
    "sg:address":"Weiherstr. 35",
    "sg:city":"Esslingen",
    "sg:phone":"+49 711/3161914",
    "sg:postcode":"73730",
    "sg:province":"Baden-W\u00fcrttemberg",
    "wof:name":"Diakonie-und Sozialstation Ost Oberesslingen",
    "wof:placetype":"venue"
},
  "geometry": {"coordinates":[9.337067,48.72963],"type":"Point"}
}