{
  "type": "Feature",
  "properties": {
    "iso:country":"DE",
    "sg:address":"Brockhagener Str. 17",
    "sg:city":"Steinhagen",
    "sg:phone":"+49 5204/2148",
    "sg:postcode":"33803",
    "sg:province":"Nordrhein-Westfalen",
    "wof:name":"P. Geisenhansl\u00fcke",
    "wof:placetype":"venue"
},
  "geometry": {"coordinates":[8.408413887,52.0013084412],"type":"Point"}
}