{
  "type": "Feature",
  "properties": {
    "iso:country":"DE",
    "sg:address":"Chemnitzer Str. 13A",
    "sg:city":"Thalheim",
    "sg:phone":"+49 3721/86216",
    "sg:postcode":"09380",
    "sg:province":"Sachsen",
    "wof:name":"M. Ehrenberg & Olaf Steiger Gbr",
    "wof:placetype":"venue"
},
  "geometry": {"coordinates":[12.856794,50.705685],"type":"Point"}
}