{
  "type": "Feature",
  "properties": {
    "iso:country":"DE",
    "sg:address":"Turmstr. 8",
    "sg:city":"Heilbronn",
    "sg:phone":"+49 7131/87174",
    "sg:postcode":"74072",
    "sg:province":"Baden-W\u00fcrttemberg",
    "wof:name":"Manfred Setzer",
    "wof:placetype":"venue"
},
  "geometry": {"coordinates":[9.2191123962,49.1455764771],"type":"Point"}
}