{
  "type": "Feature",
  "properties": {
    "iso:country":"DE",
    "sg:address":"Gro\u00dfe Str. 14",
    "sg:city":"Rotenburg",
    "sg:phone":"+49 4261/4081",
    "sg:postcode":"27356",
    "sg:province":"Niedersachsen",
    "wof:name":"Interforge Klee Gmbh",
    "wof:placetype":"venue"
},
  "geometry": {"coordinates":[9.401761055,53.1098442078],"type":"Point"}
}