{
  "type": "Feature",
  "properties": {
    "iso:country":"DE",
    "sg:address":"Bohnenweg 25",
    "sg:city":"Salzgitter",
    "sg:phone":"+49 5341/44656",
    "sg:postcode":"38226",
    "sg:province":"Niedersachsen",
    "wof:name":"Hans-joachim B\u00f6ttcher",
    "wof:placetype":"venue"
},
  "geometry": {"coordinates":[10.3337202072,52.1429138184],"type":"Point"}
}