{
  "type": "Feature",
  "properties": {
    "iso:country":"DE",
    "sg:address":"Rheinstr. 8",
    "sg:city":"Bischofsheim",
    "sg:phone":"+49 6144/42652",
    "sg:postcode":"65474",
    "sg:province":"Hessen",
    "wof:name":"Isabella Engert-steffens Rechtsanw\u00e4ltin",
    "wof:placetype":"venue"
},
  "geometry": {"coordinates":[8.360961,49.988686],"type":"Point"}
}