{
  "type": "Feature",
  "properties": {
    "iso:country":"DE",
    "sg:address":"Rahlstedter Str. 158",
    "sg:city":"Hamburg",
    "sg:phone":"+49 40/6771030",
    "sg:postcode":"22143",
    "sg:province":"Hamburg",
    "wof:name":"Repro L\u00fcdke Fotokopier- Und",
    "wof:placetype":"venue"
},
  "geometry": {"coordinates":[10.1611337662,53.6045188904],"type":"Point"}
}