{
  "type": "Feature",
  "properties": {
    "iso:country":"DE",
    "sg:address":"Tackweg 51",
    "sg:city":"T\u00f6nisvorst",
    "sg:phone":"+49 2151/701463",
    "sg:postcode":"47918",
    "sg:province":"Nordrhein-Westfalen",
    "wof:name":"Helmut Witt Gmbh",
    "wof:placetype":"venue"
},
  "geometry": {"coordinates":[6.467725,51.320381],"type":"Point"}
}