{
  "type": "Feature",
  "properties": {
    "iso:country":"DE",
    "sg:address":"Hinterlandstr. 16",
    "sg:city":"Eschwege",
    "sg:phone":"+49 5651/13712",
    "sg:postcode":"37269",
    "sg:province":"Hessen",
    "wof:name":"Manfred Sch\u00fclbe",
    "wof:placetype":"venue"
},
  "geometry": {"coordinates":[10.007759,51.186432],"type":"Point"}
}