{
  "type": "Feature",
  "properties": {
    "iso:country":"DE",
    "sg:address":"Salzbr\u00fccke 4",
    "sg:city":"Schmalkalden",
    "sg:phone":"+49 3683/606447",
    "sg:postcode":"98574",
    "sg:province":"Th\u00fcringen",
    "wof:name":"K-haus Gmbh",
    "wof:placetype":"venue"
},
  "geometry": {"coordinates":[10.451852,50.722061],"type":"Point"}
}