{
  "type": "Feature",
  "properties": {
    "iso:country":"DE",
    "sg:address":"Hallesche Str. 9",
    "sg:city":"Zorbau",
    "sg:phone":"+49 34441/93042",
    "sg:postcode":"06679",
    "sg:province":"Sachsen-Anhalt",
    "wof:name":"Dachdecker-einkauf-ost Eg",
    "wof:placetype":"venue"
},
  "geometry": {"coordinates":[12.016978,51.190044],"type":"Point"}
}