{
  "type": "Feature",
  "properties": {
    "iso:country":"DE",
    "sg:address":"Jean-Paul-Str. 5",
    "sg:city":"Marktredwitz",
    "sg:phone":"+49 9231/8581",
    "sg:postcode":"95615",
    "sg:province":"Bayern",
    "wof:name":"Ritter",
    "wof:placetype":"venue"
},
  "geometry": {"coordinates":[12.075772,50.002525],"type":"Point"}
}