{
  "type": "Feature",
  "properties": {
    "iso:country":"DE",
    "sg:address":"Dr.-Wilhelm-K\u00fclz-Str. 18",
    "sg:city":"Prenzlau",
    "sg:postcode":"17291",
    "sg:province":"Brandenburg",
    "wof:name":"Rema Gmbh & Co. Technologie Kg",
    "wof:placetype":"venue"
},
  "geometry": {"coordinates":[13.8593864441,53.3170852661],"type":"Point"}
}