{
  "type": "Feature",
  "properties": {
    "iso:country":"DE",
    "sg:address":"Burg-Gr\u00e4fenr\u00f6der-Str. 8",
    "sg:city":"Karben",
    "sg:phone":"+49 6039/3581",
    "sg:postcode":"61184",
    "sg:province":"Hessen",
    "wof:name":"Ev. Pfarramt Gross Karben",
    "wof:placetype":"venue"
},
  "geometry": {"coordinates":[8.7712211609,50.2386169434],"type":"Point"}
}