{
  "type": "Feature",
  "properties": {
    "iso:country":"DE",
    "sg:address":"Dollenweg 5",
    "sg:city":"Sch\u00fcttorf",
    "sg:phone":"+49 4959/238020",
    "sg:postcode":"48465",
    "sg:province":"Niedersachsen",
    "wof:name":"Tulip Food Company",
    "wof:placetype":"venue"
},
  "geometry": {"coordinates":[7.2268252373,52.3156814575],"type":"Point"}
}