{
  "type": "Feature",
  "properties": {
    "iso:country":"DE",
    "sg:address":"In der Theusen 10",
    "sg:city":"Heiligenhaus",
    "sg:phone":"+49 2054/80493",
    "sg:postcode":"42579",
    "sg:province":"Nordrhein-Westfalen",
    "wof:name":"Sch\u00f6nborn-fernschild Architekten",
    "wof:placetype":"venue"
},
  "geometry": {"coordinates":[6.941023,51.337662],"type":"Point"}
}