{
  "type": "Feature",
  "properties": {
    "iso:country":"DE",
    "sg:address":"Twielenfleth Am Deich 51",
    "sg:city":"Hollern-Twielenfleth",
    "sg:phone":"+49 4141/76831",
    "sg:postcode":"21723",
    "sg:province":"Niedersachsen",
    "wof:name":"Wilhelm Eckhoff",
    "wof:placetype":"venue"
},
  "geometry": {"coordinates":[9.5507183075,53.6071510315],"type":"Point"}
}