{
  "type": "Feature",
  "properties": {
    "iso:country":"DE",
    "sg:address":"Rudolfstr. 8",
    "sg:city":"Wuppertal",
    "sg:phone":"+49 202/4970",
    "sg:postcode":"42285",
    "sg:province":"Nordrhein-Westfalen",
    "wof:name":"Siemens Ag",
    "wof:placetype":"venue"
},
  "geometry": {"coordinates":[7.1625580788,51.2676086426],"type":"Point"}
}