{
  "type": "Feature",
  "properties": {
    "iso:country":"DE",
    "sg:address":"Rottendorfer Str. 35a",
    "sg:city":"W\u00fcrzburg",
    "sg:phone":"+49 931/883980",
    "sg:postcode":"97074",
    "sg:province":"Bayern",
    "wof:name":"Agency Horst",
    "wof:placetype":"venue"
},
  "geometry": {"coordinates":[9.9550609589,49.7914237976],"type":"Point"}
}