{
  "type": "Feature",
  "properties": {
    "iso:country":"DE",
    "sg:address":"Am Schulgarten 11",
    "sg:city":"Burgwedel",
    "sg:phone":"+49 5139/8189",
    "sg:postcode":"30938",
    "sg:province":"Niedersachsen",
    "wof:name":"Grillmaster Kaluza Gmbh",
    "wof:placetype":"venue"
},
  "geometry": {"coordinates":[9.8966159821,52.4957962036],"type":"Point"}
}