{
  "type": "Feature",
  "properties": {
    "iso:country":"DE",
    "sg:address":"Lindenstr. 82",
    "sg:city":"Kriftel",
    "sg:phone":"+49 6192/44638",
    "sg:postcode":"65830",
    "sg:province":"Hessen",
    "wof:name":"Albert D\u00f6rr",
    "wof:placetype":"venue"
},
  "geometry": {"coordinates":[8.4594459534,50.0872077942],"type":"Point"}
}