{
  "type": "Feature",
  "properties": {
    "iso:country":"DE",
    "sg:address":"L\u00f6bauer Str. 113",
    "sg:city":"Leipzig",
    "sg:phone":"+49 341/2313725",
    "sg:postcode":"04347",
    "sg:province":"Sachsen",
    "wof:name":"Peter Klinge Ingenieur",
    "wof:placetype":"venue"
},
  "geometry": {"coordinates":[12.4272346497,51.3576126099],"type":"Point"}
}