{
  "type": "Feature",
  "properties": {
    "iso:country":"DE",
    "sg:address":"Altstadt 25",
    "sg:city":"Landshut",
    "sg:postcode":"84034",
    "sg:province":"Bayern",
    "wof:name":"Ck Tr@ding Bank Gmbh",
    "wof:placetype":"venue"
},
  "geometry": {"coordinates":[8.67835,50.114079],"type":"Point"}
}