{
  "type": "Feature",
  "properties": {
    "iso:country":"DE",
    "sg:address":"Dreik\u00f6niggasse 18",
    "sg:city":"Ulm",
    "sg:phone":"+49 731/64099",
    "sg:postcode":"89073",
    "sg:province":"Baden-W\u00fcrttemberg",
    "wof:name":"Sporthaus Kraus Gmbh & Co. Kg",
    "wof:placetype":"venue"
},
  "geometry": {"coordinates":[9.9899539948,48.4001693726],"type":"Point"}
}