{
  "type": "Feature",
  "properties": {
    "iso:country":"DE",
    "sg:address":"Zur Eschenau 8",
    "sg:city":"F\u00fcrth",
    "sg:phone":"+49 911/721480",
    "sg:postcode":"90768",
    "sg:province":"Bayern",
    "wof:name":"O. Burger",
    "wof:placetype":"venue"
},
  "geometry": {"coordinates":[10.9615497589,49.4597396851],"type":"Point"}
}