{
  "type": "Feature",
  "properties": {
    "iso:country":"DE",
    "sg:address":"Wasserstr. 1",
    "sg:city":"Steinfurt",
    "sg:phone":"+49 2551/2082",
    "sg:postcode":"48565",
    "sg:province":"Nordrhein-Westfalen",
    "wof:name":"Pizzeria Perino",
    "wof:placetype":"venue"
},
  "geometry": {"coordinates":[7.3393611908,52.1480636597],"type":"Point"}
}