{
  "type": "Feature",
  "properties": {
    "iso:country":"DE",
    "sg:address":"Ringstr. 85",
    "sg:city":"Lampertheim",
    "sg:phone":"+49 6206/52552",
    "sg:postcode":"68623",
    "sg:province":"Hessen",
    "wof:name":"Ernst Becker",
    "wof:placetype":"venue"
},
  "geometry": {"coordinates":[8.4693384171,49.6056671143],"type":"Point"}
}