{
  "type": "Feature",
  "properties": {
    "iso:country":"DE",
    "sg:address":"Teichstr. 33",
    "sg:city":"Stadthagen",
    "sg:phone":"+49 5721/79050",
    "sg:postcode":"31655",
    "sg:province":"Niedersachsen",
    "wof:name":"Georg Wolff",
    "wof:placetype":"venue"
},
  "geometry": {"coordinates":[9.2103643417,52.3312034607],"type":"Point"}
}