{
  "type": "Feature",
  "properties": {
    "iso:country":"DE",
    "sg:address":"Hochgernweg 30",
    "sg:city":"\u00dcbersee",
    "sg:phone":"+49 8642/6650",
    "sg:postcode":"83236",
    "sg:province":"Bayern",
    "wof:name":"J. Van Gorkom",
    "wof:placetype":"venue"
},
  "geometry": {"coordinates":[12.4874277115,47.8274116516],"type":"Point"}
}