{
  "type": "Feature",
  "properties": {
    "iso:country":"DE",
    "sg:address":"Buchsweilerstr. 38",
    "sg:city":"Pirmasens",
    "sg:phone":"+49 6331/75031",
    "sg:postcode":"66953",
    "sg:province":"Rheinland-Pfalz",
    "wof:name":"Immobilien Lippert",
    "wof:placetype":"venue"
},
  "geometry": {"coordinates":[7.614221096,49.1948547363],"type":"Point"}
}