{
  "type": "Feature",
  "properties": {
    "iso:country":"DE",
    "sg:address":"Stolzenhagener Str. 5",
    "sg:city":"Klosterfelde",
    "sg:phone":"+49 33396/482",
    "sg:postcode":"16348",
    "sg:province":"Brandenburg",
    "wof:name":"Lutz Friedenberger",
    "wof:placetype":"venue"
},
  "geometry": {"coordinates":[13.47934,52.789085],"type":"Point"}
}