{
  "type": "Feature",
  "properties": {
    "iso:country":"DE",
    "sg:address":"Lietzenburger Str. 98",
    "sg:city":"Berlin",
    "sg:phone":"+49 30/8818529",
    "sg:postcode":"10719",
    "sg:province":"Berlin",
    "wof:name":"Stephan Y. Dietrich Architekt",
    "wof:placetype":"venue"
},
  "geometry": {"coordinates":[13.319424,52.499828],"type":"Point"}
}