{
  "type": "Feature",
  "properties": {
    "iso:country":"DE",
    "sg:address":"Otto-Hahn-Str. 9",
    "sg:city":"Paderborn",
    "sg:phone":"+49 5254/4499",
    "sg:postcode":"33104",
    "sg:province":"Nordrhein-Westfalen",
    "wof:name":"K. Griffiths",
    "wof:placetype":"venue"
},
  "geometry": {"coordinates":[8.707774,51.769638],"type":"Point"}
}