{
  "type": "Feature",
  "properties": {
    "iso:country":"DE",
    "sg:address":"Dorfstr. 97",
    "sg:city":"Kakerbeck",
    "sg:phone":"+49 39081/291",
    "sg:postcode":"39624",
    "sg:province":"Sachsen-Anhalt",
    "wof:name":"Rolf-ingo Dahm",
    "wof:placetype":"venue"
},
  "geometry": {"coordinates":[11.250289917,52.6528701782],"type":"Point"}
}