{
  "type": "Feature",
  "properties": {
    "iso:country":"DE",
    "sg:address":"Neue Str. 12",
    "sg:city":"Flensburg",
    "sg:postcode":"24939",
    "sg:province":"Schleswig-Holstein",
    "wof:name":"Fun-shop J\u00f6rg Stange E. K.",
    "wof:placetype":"venue"
},
  "geometry": {"coordinates":[9.433323,54.790585],"type":"Point"}
}