{
  "type": "Feature",
  "properties": {
    "iso:country":"DE",
    "sg:address":"Mariendorfer Weg 21",
    "sg:city":"Berlin",
    "sg:phone":"+49 30/6258027",
    "sg:postcode":"12051",
    "sg:province":"Berlin",
    "wof:name":"Seniorenheim",
    "wof:placetype":"venue"
},
  "geometry": {"coordinates":[13.42789,52.464138],"type":"Point"}
}