{
  "type": "Feature",
  "properties": {
    "iso:country":"DE",
    "sg:address":"Ch\u00fcdenstr. 19",
    "sg:city":"Salzwedel",
    "sg:postcode":"29410",
    "sg:province":"Sachsen-Anhalt",
    "wof:name":"Kurt Branski",
    "wof:placetype":"venue"
},
  "geometry": {"coordinates":[11.154866,52.849117],"type":"Point"}
}