{
  "type": "Feature",
  "properties": {
    "iso:country":"DE",
    "sg:address":"Weiler Halde",
    "sg:city":"Berg",
    "sg:phone":"+49 751/59738",
    "sg:postcode":"88276",
    "sg:province":"Baden-W\u00fcrttemberg",
    "wof:name":"Hermann Kaiser",
    "wof:placetype":"venue"
},
  "geometry": {"coordinates":[9.594199,47.833576],"type":"Point"}
}