{
  "type": "Feature",
  "properties": {
    "iso:country":"DE",
    "sg:address":"Reepschl\u00e4gerstr. 26",
    "sg:city":"L\u00fcbeck",
    "sg:phone":"+49 451/890080",
    "sg:postcode":"23556",
    "sg:province":"Schleswig-Holstein",
    "wof:name":"Friedrich W. Beck",
    "wof:placetype":"venue"
},
  "geometry": {"coordinates":[10.6133775711,53.862323761],"type":"Point"}
}