{
  "type": "Feature",
  "properties": {
    "iso:country":"DE",
    "sg:address":"Huttenstr. 2",
    "sg:city":"Bad Sch\u00f6nborn",
    "sg:phone":"+49 7253/6014",
    "sg:postcode":"76669",
    "sg:province":"Baden-W\u00fcrttemberg",
    "wof:name":"Hotel Drei K\u00f6nige",
    "wof:placetype":"venue"
},
  "geometry": {"coordinates":[8.6467418671,49.2030715942],"type":"Point"}
}