{
  "type": "Feature",
  "properties": {
    "iso:country":"DE",
    "sg:address":"Bartholom\u00e4usweg 13",
    "sg:city":"G\u00fctersloh",
    "sg:phone":"+49 5241/49044",
    "sg:postcode":"33334",
    "sg:province":"Nordrhein-Westfalen",
    "wof:name":"H. Kleinelanghorst Gmbh Dreherei",
    "wof:placetype":"venue"
},
  "geometry": {"coordinates":[8.44901,51.88179],"type":"Point"}
}