{
  "type": "Feature",
  "properties": {
    "iso:country":"DE",
    "sg:address":"K\u00f6nigstr. 237",
    "sg:city":"Minden",
    "sg:phone":"+49 571/52569",
    "sg:postcode":"32427",
    "sg:province":"Nordrhein-Westfalen",
    "wof:name":"Staas",
    "wof:placetype":"venue"
},
  "geometry": {"coordinates":[8.870211,52.295288],"type":"Point"}
}