{
  "type": "Feature",
  "properties": {
    "iso:country":"DE",
    "sg:address":"Wolfstein 20",
    "sg:city":"Offenberg",
    "sg:phone":"+49 9906/789",
    "sg:postcode":"94560",
    "sg:province":"Bayern",
    "wof:name":"K. Baumgartner",
    "wof:placetype":"venue"
},
  "geometry": {"coordinates":[12.871723,48.86652],"type":"Point"}
}