{
  "type": "Feature",
  "properties": {
    "iso:country":"DE",
    "sg:address":"Ochtruper Str. 153",
    "sg:city":"Gronau",
    "sg:postcode":"48599",
    "sg:province":"Nordrhein-Westfalen",
    "wof:name":"Meckelenkamp Gmbh",
    "wof:placetype":"venue"
},
  "geometry": {"coordinates":[7.054855,52.204285],"type":"Point"}
}