{
  "type": "Feature",
  "properties": {
    "iso:country":"DE",
    "sg:address":"L\u00e4rchenstr. 30",
    "sg:city":"F\u00fcrstenfeldbruck",
    "sg:phone":"+49 8141/20554",
    "sg:postcode":"82256",
    "sg:province":"Bayern",
    "wof:name":"Josef Murr",
    "wof:placetype":"venue"
},
  "geometry": {"coordinates":[11.2226314545,48.1584777832],"type":"Point"}
}