{
  "type": "Feature",
  "properties": {
    "iso:country":"DE",
    "sg:address":"Rinnenberg 10",
    "sg:city":"Westhausen",
    "sg:phone":"+49 7363/5242",
    "sg:postcode":"73463",
    "sg:province":"Baden-W\u00fcrttemberg",
    "wof:name":"J. Sch\u00f6nherr Kohlenhandlung",
    "wof:placetype":"venue"
},
  "geometry": {"coordinates":[10.189119,48.881783],"type":"Point"}
}