{
  "type": "Feature",
  "properties": {
    "iso:country":"DE",
    "sg:address":"Daisendorfer Str. 14a",
    "sg:city":"Meersburg",
    "sg:postcode":"88709",
    "sg:province":"Baden-W\u00fcrttemberg",
    "wof:name":"Wohnbaugesellschaft Markdorf Mbh",
    "wof:placetype":"venue"
},
  "geometry": {"coordinates":[9.271059,47.697372],"type":"Point"}
}