{
  "type": "Feature",
  "properties": {
    "iso:country":"DE",
    "sg:address":"Weg beim J\u00e4ger 214",
    "sg:city":"Hamburg",
    "sg:phone":"+49 40/591010",
    "sg:postcode":"22335",
    "sg:province":"Hamburg",
    "wof:name":"Declimed Zweigniederlassung Desitin Arzneimittel Gmbh",
    "wof:placetype":"venue"
},
  "geometry": {"coordinates":[10.0076084137,53.6230316162],"type":"Point"}
}