{
  "type": "Feature",
  "properties": {
    "iso:country":"DE",
    "sg:address":"Buttlarer Str. 2",
    "sg:city":"Geisa",
    "sg:phone":"+49 36967/71555",
    "sg:postcode":"36419",
    "sg:province":"Th\u00fcringen",
    "wof:name":"D. Kammandel",
    "wof:placetype":"venue"
},
  "geometry": {"coordinates":[9.9481077194,50.7183685303],"type":"Point"}
}