{
  "type": "Feature",
  "properties": {
    "iso:country":"DE",
    "sg:address":"Saarlandstr. 25",
    "sg:city":"Gersheim",
    "sg:phone":"+49 6843/8268",
    "sg:postcode":"66453",
    "sg:province":"Saarland",
    "wof:name":"Karl Jost",
    "wof:placetype":"venue"
},
  "geometry": {"coordinates":[7.182457,49.138096],"type":"Point"}
}