{
  "type": "Feature",
  "properties": {
    "iso:country":"DE",
    "sg:address":"Im Wiesengrund 10",
    "sg:city":"Arnsberg",
    "sg:phone":"+49 2937/6483",
    "sg:postcode":"59823",
    "sg:province":"Nordrhein-Westfalen",
    "wof:name":"Josef Wrede Inh. Joachim Wrede",
    "wof:placetype":"venue"
},
  "geometry": {"coordinates":[8.1476583481,51.3957443237],"type":"Point"}
}