{
  "type": "Feature",
  "properties": {
    "iso:country":"DE",
    "sg:address":"Matthias-Kahlke-Promenade 20",
    "sg:city":"Elmshorn",
    "sg:phone":"+49 4121/25211",
    "sg:postcode":"25335",
    "sg:province":"Schleswig-Holstein",
    "wof:name":"Zur Friesenstube",
    "wof:placetype":"venue"
},
  "geometry": {"coordinates":[9.656058,53.757946],"type":"Point"}
}