{
  "type": "Feature",
  "properties": {
    "iso:country":"DE",
    "sg:address":"Steintorstr. 6",
    "sg:city":"Duderstadt",
    "sg:phone":"+49 5527/4116",
    "sg:postcode":"37115",
    "sg:province":"Niedersachsen",
    "wof:name":"Rainer Ziesing",
    "wof:placetype":"venue"
},
  "geometry": {"coordinates":[10.2594957352,51.5107917786],"type":"Point"}
}