{
  "type": "Feature",
  "properties": {
    "iso:country":"DE",
    "sg:address":"Rieshorner Weg 33",
    "sg:city":"Heidm\u00fchlen",
    "sg:phone":"+49 4320/1028",
    "sg:postcode":"24598",
    "sg:province":"Schleswig-Holstein",
    "wof:name":"Hinrich Gli\u00dfmann",
    "wof:placetype":"venue"
},
  "geometry": {"coordinates":[10.07395,53.970322],"type":"Point"}
}