{
  "type": "Feature",
  "properties": {
    "iso:country":"DE",
    "sg:address":"Marktplatz 10",
    "sg:city":"Kirchenlamitz",
    "sg:phone":"+49 9285/91203",
    "sg:postcode":"95158",
    "sg:province":"Bayern",
    "wof:name":"Nkd Gmbh",
    "wof:placetype":"venue"
},
  "geometry": {"coordinates":[11.950065,50.151466],"type":"Point"}
}