{
  "type": "Feature",
  "properties": {
    "iso:country":"DE",
    "sg:address":"Untere Au 3",
    "sg:city":"Oberthulba",
    "sg:phone":"+49 9736/4726",
    "sg:postcode":"97723",
    "sg:province":"Bayern",
    "wof:name":"T. Golla",
    "wof:placetype":"venue"
},
  "geometry": {"coordinates":[9.923514,50.175701],"type":"Point"}
}