{
  "type": "Feature",
  "properties": {
    "iso:country":"DE",
    "sg:address":"Hauptstr. 143 a",
    "sg:city":"Durmersheim",
    "sg:phone":"+49 7245/4731",
    "sg:postcode":"76448",
    "sg:province":"Baden-W\u00fcrttemberg",
    "wof:name":"Pilgerheim",
    "wof:placetype":"venue"
},
  "geometry": {"coordinates":[8.2724838257,48.9379272461],"type":"Point"}
}