{
  "type": "Feature",
  "properties": {
    "iso:country":"DE",
    "sg:address":"Waldsassener Str. 42",
    "sg:city":"Berlin",
    "sg:phone":"+49 30/7114131",
    "sg:postcode":"12279",
    "sg:province":"Berlin",
    "wof:name":"Elisabeth Haupts",
    "wof:placetype":"venue"
},
  "geometry": {"coordinates":[13.3503665924,52.4087562561],"type":"Point"}
}