{
  "type": "Feature",
  "properties": {
    "iso:country":"DE",
    "sg:address":"Kramerstr. 18",
    "sg:city":"Hannover",
    "sg:phone":"+49 511/306565",
    "sg:postcode":"30159",
    "sg:province":"Niedersachsen",
    "wof:name":"Leithold",
    "wof:placetype":"venue"
},
  "geometry": {"coordinates":[9.733469,52.371559],"type":"Point"}
}