{
  "type": "Feature",
  "properties": {
    "iso:country":"DE",
    "sg:address":"Wiesenbach",
    "sg:city":"Oberrot",
    "sg:phone":"+49 7977/8118",
    "sg:postcode":"74420",
    "sg:province":"Baden-W\u00fcrttemberg",
    "wof:name":"M. Wolf-thiessat Hebamme",
    "wof:placetype":"venue"
},
  "geometry": {"coordinates":[9.66211,49.000721],"type":"Point"}
}