{
  "type": "Feature",
  "properties": {
    "iso:country":"DE",
    "sg:address":"Franz-Dietze-Str. 4",
    "sg:city":"Hohenthurm",
    "sg:phone":"+49 34602/50577",
    "sg:postcode":"06188",
    "sg:province":"Sachsen-Anhalt",
    "wof:name":"J\u00fcrgen Stachelrodt",
    "wof:placetype":"venue"
},
  "geometry": {"coordinates":[12.098958,51.514645],"type":"Point"}
}