{
  "type": "Feature",
  "properties": {
    "iso:country":"DE",
    "sg:address":"T\u00fcbinger Str. 6",
    "sg:city":"Berlin",
    "sg:phone":"+49 30/8532973",
    "sg:postcode":"10715",
    "sg:province":"Berlin",
    "wof:name":"Hakan Sen Immobilienmakler",
    "wof:placetype":"venue"
},
  "geometry": {"coordinates":[13.3297777176,52.4800872803],"type":"Point"}
}