{
  "type": "Feature",
  "properties": {
    "iso:country":"DE",
    "sg:address":"Am Alten Gaswerk 2",
    "sg:city":"Jena",
    "sg:phone":"+49 3641/63780",
    "sg:postcode":"07743",
    "sg:province":"Th\u00fcringen",
    "wof:name":"Mps E Com Gmbh",
    "wof:placetype":"venue"
},
  "geometry": {"coordinates":[11.5923404694,50.938911438],"type":"Point"}
}