{
  "type": "Feature",
  "properties": {
    "iso:country":"DE",
    "sg:address":"Mittelrheinstr. 23",
    "sg:city":"Worms",
    "sg:phone":"+49 6242/90200",
    "sg:postcode":"67550",
    "sg:province":"Rheinland-Pfalz",
    "wof:name":"Zentrale Handelsges.zhg Mbh",
    "wof:placetype":"venue"
},
  "geometry": {"coordinates":[8.3457136154,49.6921463013],"type":"Point"}
}