{
  "type": "Feature",
  "properties": {
    "iso:country":"DE",
    "sg:address":"Werdauer Weg 25",
    "sg:city":"Berlin",
    "sg:phone":"+49 30/788020",
    "sg:postcode":"10829",
    "sg:province":"Berlin",
    "wof:name":"Kapella Gmbh & Co. Kg",
    "wof:placetype":"venue"
},
  "geometry": {"coordinates":[13.3484983444,52.4749832153],"type":"Point"}
}