{
  "type": "Feature",
  "properties": {
    "iso:country":"DE",
    "sg:address":"Lange Str. 4",
    "sg:city":"M\u00f6ssingen",
    "sg:phone":"+49 7473/272643",
    "sg:postcode":"72116",
    "sg:province":"Baden-W\u00fcrttemberg",
    "wof:name":"Friedrich Jung",
    "wof:placetype":"venue"
},
  "geometry": {"coordinates":[9.062548,48.409058],"type":"Point"}
}