{
  "type": "Feature",
  "properties": {
    "iso:country":"DE",
    "sg:address":"Im Wacholder 12",
    "sg:city":"Allmersbach",
    "sg:phone":"+49 7191/58763",
    "sg:postcode":"71573",
    "sg:province":"Baden-W\u00fcrttemberg",
    "wof:name":"Dieter Wagner Masseur",
    "wof:placetype":"venue"
},
  "geometry": {"coordinates":[9.472398,48.907631],"type":"Point"}
}