{
  "type": "Feature",
  "properties": {
    "iso:country":"DE",
    "sg:address":"Burgstr. 20",
    "sg:city":"Geislingen",
    "sg:postcode":"73312",
    "sg:province":"Baden-W\u00fcrttemberg",
    "wof:name":"H. A. H. N. Montageservice Gmbh",
    "wof:placetype":"venue"
},
  "geometry": {"coordinates":[9.836423,48.624031],"type":"Point"}
}