{
  "type": "Feature",
  "properties": {
    "iso:country":"DE",
    "sg:address":"Dr.-Schirmer-Str. 4",
    "sg:city":"G\u00f6cklingen",
    "sg:phone":"+49 6349/929357",
    "sg:postcode":"76831",
    "sg:province":"Rheinland-Pfalz",
    "wof:name":"Sozialtherapeutische Kette Ggmbh",
    "wof:placetype":"venue"
},
  "geometry": {"coordinates":[8.044234,49.161476],"type":"Point"}
}