{
  "type": "Feature",
  "properties": {
    "iso:country":"DE",
    "sg:address":"Reinsburgstr. 188",
    "sg:city":"Stuttgart",
    "sg:phone":"+49 711/6587976",
    "sg:postcode":"70197",
    "sg:province":"Baden-W\u00fcrttemberg",
    "wof:name":"Rainer Oxenknecht",
    "wof:placetype":"venue"
},
  "geometry": {"coordinates":[9.148314,48.769276],"type":"Point"}
}