{
  "type": "Feature",
  "properties": {
    "iso:country":"DE",
    "sg:address":"Hildesheimer Str. 75",
    "sg:city":"Alfeld",
    "sg:postcode":"31061",
    "sg:province":"Niedersachsen",
    "wof:name":"Fredo Busse Versicherungen E. K.",
    "wof:placetype":"venue"
},
  "geometry": {"coordinates":[9.8282155991,51.9904098511],"type":"Point"}
}