{
  "type": "Feature",
  "properties": {
    "iso:country":"DE",
    "sg:address":"Alt Bartelsdorfer Str. 18",
    "sg:city":"Rostock",
    "sg:phone":"+49 381/6865247",
    "sg:postcode":"18146",
    "sg:province":"Mecklenburg-Vorpommern",
    "wof:name":"Hans Ackermann",
    "wof:placetype":"venue"
},
  "geometry": {"coordinates":[12.175938,54.098038],"type":"Point"}
}