{
  "type": "Feature",
  "properties": {
    "iso:country":"DE",
    "sg:address":"Dalbigsbergstr. 54",
    "sg:city":"Oberursel",
    "sg:phone":"+49 6171/57778",
    "sg:postcode":"61440",
    "sg:province":"Hessen",
    "wof:name":"Gabriele Wilhelm",
    "wof:placetype":"venue"
},
  "geometry": {"coordinates":[8.5867786407,50.2057876587],"type":"Point"}
}