{
  "type": "Feature",
  "properties": {
    "iso:country":"DE",
    "sg:address":"Sch\u00f6nbornstr. 1b",
    "sg:city":"M\u00fchlhausen",
    "sg:postcode":"69242",
    "sg:province":"Baden-W\u00fcrttemberg",
    "wof:name":"Linder Und Sauer Werkzeug- Und Formenbau Gmbh",
    "wof:placetype":"venue"
},
  "geometry": {"coordinates":[8.6938886642,49.2358131409],"type":"Point"}
}