{
  "type": "Feature",
  "properties": {
    "iso:country":"DE",
    "sg:address":"Albert-Einstein-Str 3",
    "sg:city":"Kornwestheim",
    "sg:phone":"+49 7154/82190",
    "sg:postcode":"70806",
    "sg:province":"Baden-W\u00fcrttemberg",
    "wof:name":"R\u00f6hren-handelsgesellschaft T\u00f6dtmann & Birk Gmbh",
    "wof:placetype":"venue"
},
  "geometry": {"coordinates":[9.1850252151,48.8592948914],"type":"Point"}
}