{
  "type": "Feature",
  "properties": {
    "iso:country":"DE",
    "sg:address":"B\u00fcrgerfelder Str. 1",
    "sg:city":"Oldenburg",
    "sg:postcode":"26127",
    "sg:province":"Niedersachsen",
    "wof:name":"Potsdam Konsumhof Grundst\u00fccksverwaltungsges.",
    "wof:placetype":"venue"
},
  "geometry": {"coordinates":[8.203512,53.163738],"type":"Point"}
}