{
  "type": "Feature",
  "properties": {
    "iso:country":"DE",
    "sg:address":"Reutherstr. 7",
    "sg:city":"Hennef",
    "sg:phone":"+49 4922/4292340",
    "sg:postcode":"53773",
    "sg:province":"Nordrhein-Westfalen",
    "wof:name":"Westdeutsche Carl Wolf Gmbh",
    "wof:placetype":"venue"
},
  "geometry": {"coordinates":[7.257912,50.780624],"type":"Point"}
}