{
  "type": "Feature",
  "properties": {
    "iso:country":"DE",
    "sg:address":"Moelscherweg 140",
    "sg:city":"Goch",
    "sg:phone":"+49 2827/5147",
    "sg:postcode":"47574",
    "sg:province":"Nordrhein-Westfalen",
    "wof:name":"Tuxhorn Gmbh",
    "wof:placetype":"venue"
},
  "geometry": {"coordinates":[6.0423331261,51.6715660095],"type":"Point"}
}