{
  "type": "Feature",
  "properties": {
    "iso:country":"DE",
    "sg:address":"Mainzer Allee 38",
    "sg:city":"Taunusstein",
    "sg:phone":"+49 6128/6640",
    "sg:postcode":"65232",
    "sg:province":"Hessen",
    "wof:name":"Kath. Pfarramt Herz Jesu",
    "wof:placetype":"venue"
},
  "geometry": {"coordinates":[8.1862506866,50.1508255005],"type":"Point"}
}