{
  "type": "Feature",
  "properties": {
    "iso:country":"DE",
    "sg:address":"R\u00f6merstr. 43",
    "sg:city":"Nast\u00e4tten",
    "sg:phone":"+49 6772/5865",
    "sg:postcode":"56355",
    "sg:province":"Rheinland-Pfalz",
    "wof:name":"E. Spiess",
    "wof:placetype":"venue"
},
  "geometry": {"coordinates":[7.856732,50.200066],"type":"Point"}
}