{
  "type": "Feature",
  "properties": {
    "iso:country":"DE",
    "sg:address":"C\u00f6rmannstr. 21",
    "sg:city":"Witten",
    "sg:postcode":"58455",
    "sg:province":"Nordrhein-Westfalen",
    "wof:name":"P & S Handelsgesellschaft Mbh",
    "wof:placetype":"venue"
},
  "geometry": {"coordinates":[7.3192939758,51.4447593689],"type":"Point"}
}