{
  "type": "Feature",
  "properties": {
    "iso:country":"DE",
    "sg:address":"Dornr\u00f6schenweg 102",
    "sg:city":"Stuttgart",
    "sg:phone":"+49 711/4414964",
    "sg:postcode":"70567",
    "sg:province":"Baden-W\u00fcrttemberg",
    "wof:name":"Sonja Seidenspinner",
    "wof:placetype":"venue"
},
  "geometry": {"coordinates":[9.155022,48.718105],"type":"Point"}
}