{
  "type": "Feature",
  "properties": {
    "iso:country":"DE",
    "sg:address":"Oberweiler 1",
    "sg:city":"Ostrach",
    "sg:postcode":"88356",
    "sg:province":"Baden-W\u00fcrttemberg",
    "wof:name":"Evergr\u00fcn Pflanzenhandels- Und Marketing Gmbh",
    "wof:placetype":"venue"
},
  "geometry": {"coordinates":[9.4184761047,47.9419975281],"type":"Point"}
}