{
  "type": "Feature",
  "properties": {
    "iso:country":"DE",
    "sg:address":"Bruckgasse 102",
    "sg:city":"Burghausen",
    "sg:phone":"+49 8677/967690",
    "sg:postcode":"84489",
    "sg:province":"Bayern",
    "wof:name":"Wirtschaftsf\u00f6rderungsges. Burghausen Mbh",
    "wof:placetype":"venue"
},
  "geometry": {"coordinates":[12.833319664,48.1588363647],"type":"Point"}
}