{
  "type": "Feature",
  "properties": {
    "iso:country":"DE",
    "sg:address":"Mozartstr. 17",
    "sg:city":"Siegen",
    "sg:phone":"+49 271/311511",
    "sg:postcode":"57080",
    "sg:province":"Nordrhein-Westfalen",
    "wof:name":"Amalie Hartmann",
    "wof:placetype":"venue"
},
  "geometry": {"coordinates":[7.9905428886,50.8544006348],"type":"Point"}
}