{
  "type": "Feature",
  "properties": {
    "iso:country":"DE",
    "sg:address":"Wulf-Isebrand-Str. 17",
    "sg:city":"Marne",
    "sg:phone":"+49 4851/3185",
    "sg:postcode":"25709",
    "sg:province":"Schleswig-Holstein",
    "wof:name":"Bosch-dienst K\u00f6lln Gmbh",
    "wof:placetype":"venue"
},
  "geometry": {"coordinates":[9.01313591,53.9559326172],"type":"Point"}
}