{
  "type": "Feature",
  "properties": {
    "iso:country":"DE",
    "sg:address":"Gerberstr. 33",
    "sg:city":"Rehau",
    "sg:phone":"+49 9283/1490",
    "sg:postcode":"95111",
    "sg:province":"Bayern",
    "wof:name":"Christian Sammet Lebensmittelgro\u00dfhandlung",
    "wof:placetype":"venue"
},
  "geometry": {"coordinates":[12.0274419785,50.2458648682],"type":"Point"}
}