{
  "type": "Feature",
  "properties": {
    "iso:country":"DE",
    "sg:address":"Bernstorffstr. 100",
    "sg:city":"Hamburg",
    "sg:phone":"+49 40/438484",
    "sg:postcode":"22767",
    "sg:province":"Hamburg",
    "wof:name":"Georg Weinhold Inh. Hans-j. Kroll",
    "wof:placetype":"venue"
},
  "geometry": {"coordinates":[9.958661,53.557178],"type":"Point"}
}