{
  "type": "Feature",
  "properties": {
    "iso:country":"DE",
    "sg:address":"Hauptstr. 6",
    "sg:city":"Pfofeld",
    "sg:phone":"+49 9834/292",
    "sg:postcode":"91738",
    "sg:province":"Bayern",
    "wof:name":"Karl Goppelt",
    "wof:placetype":"venue"
},
  "geometry": {"coordinates":[10.8380727768,49.1048812866],"type":"Point"}
}