{
  "type": "Feature",
  "properties": {
    "iso:country":"DE",
    "sg:address":"Lerchenweg 1",
    "sg:city":"Elchingen",
    "sg:phone":"+49 731/268837",
    "sg:postcode":"89275",
    "sg:province":"Bayern",
    "wof:name":"A.b. Design",
    "wof:placetype":"venue"
},
  "geometry": {"coordinates":[10.0489473343,48.4435310364],"type":"Point"}
}