{
  "type": "Feature",
  "properties": {
    "iso:country":"DE",
    "sg:address":"Kanzlerstr. 9",
    "sg:city":"Dortmund",
    "sg:phone":"+49 231/413220",
    "sg:postcode":"44263",
    "sg:province":"Nordrhein-Westfalen",
    "wof:name":"Belident-zahntechnik Gmbh",
    "wof:placetype":"venue"
},
  "geometry": {"coordinates":[7.499197,51.489616],"type":"Point"}
}