{
  "type": "Feature",
  "properties": {
    "iso:country":"DE",
    "sg:address":"Bahnhofstr. 1a",
    "sg:city":"Straubing",
    "sg:phone":"+49 9421/84070",
    "sg:postcode":"94315",
    "sg:province":"Bayern",
    "wof:name":"Marianne Hollauer Steuerberaterin",
    "wof:placetype":"venue"
},
  "geometry": {"coordinates":[12.5704898834,48.8799667358],"type":"Point"}
}