{
  "type": "Feature",
  "properties": {
    "iso:country":"DE",
    "sg:address":"Halkettstr. 42",
    "sg:city":"Hannover",
    "sg:phone":"+49 511/3504925",
    "sg:postcode":"30165",
    "sg:province":"Niedersachsen",
    "wof:name":"G\u00fcnter Lange",
    "wof:placetype":"venue"
},
  "geometry": {"coordinates":[9.727804,52.393372],"type":"Point"}
}