{
  "type": "Feature",
  "properties": {
    "iso:country":"DE",
    "sg:address":"Dreiecksplatz 5",
    "sg:city":"Kiel",
    "sg:phone":"+49 431/566195",
    "sg:postcode":"24105",
    "sg:province":"Schleswig-Holstein",
    "wof:name":"Arthur Rubin Inh. Michael Wienroth E. Kfm.",
    "wof:placetype":"venue"
},
  "geometry": {"coordinates":[10.1340723038,54.3287620544],"type":"Point"}
}