{
  "type": "Feature",
  "properties": {
    "iso:country":"DE",
    "sg:address":"M\u00fchlbergstr. 5",
    "sg:city":"Hungen",
    "sg:phone":"+49 6402/505960",
    "sg:postcode":"35410",
    "sg:province":"Hessen",
    "wof:name":"Versicherungsb\u00fcro Haibach",
    "wof:placetype":"venue"
},
  "geometry": {"coordinates":[8.9076986313,50.4757575989],"type":"Point"}
}