{
  "type": "Feature",
  "properties": {
    "iso:country":"DE",
    "sg:address":"Beethovenstr. 2a",
    "sg:city":"Frankfurt",
    "sg:phone":"+49 69/752013",
    "sg:postcode":"60325",
    "sg:province":"Hessen",
    "wof:name":"Klaus Plewe Steuerberater",
    "wof:placetype":"venue"
},
  "geometry": {"coordinates":[8.6574850082,50.1116943359],"type":"Point"}
}