{
  "type": "Feature",
  "properties": {
    "iso:country":"DE",
    "sg:address":"Frankfurter Tor 8a",
    "sg:city":"Berlin",
    "sg:phone":"+49 30/2947884",
    "sg:postcode":"10243",
    "sg:province":"Berlin",
    "wof:name":"Cubana Fluggesellschaft",
    "wof:placetype":"venue"
},
  "geometry": {"coordinates":[13.453456,52.515453],"type":"Point"}
}