{
  "type": "Feature",
  "properties": {
    "iso:country":"DE",
    "sg:address":"Alter Schulweg 1",
    "sg:city":"Emstek",
    "sg:phone":"+49 4944/7394880",
    "sg:postcode":"49685",
    "sg:province":"Niedersachsen",
    "wof:name":"Spedition H\u00dcsing Gmbh",
    "wof:placetype":"venue"
},
  "geometry": {"coordinates":[8.2214803696,52.8376960754],"type":"Point"}
}