{
  "type": "Feature",
  "properties": {
    "iso:country":"DE",
    "sg:address":"Schumannstr 15",
    "sg:city":"Halberstadt",
    "sg:phone":"+49 3941/610880",
    "sg:postcode":"38820",
    "sg:province":"Sachsen-Anhalt",
    "wof:name":"City-aufz\u00fcge Gmbh",
    "wof:placetype":"venue"
},
  "geometry": {"coordinates":[11.040678,51.884808],"type":"Point"}
}