{
  "type": "Feature",
  "properties": {
    "iso:country":"DE",
    "sg:address":"Hohe Linden 4",
    "sg:city":"Hameln",
    "sg:phone":"+49 5151/98680",
    "sg:postcode":"31789",
    "sg:province":"Niedersachsen",
    "wof:name":"H. Bartels",
    "wof:placetype":"venue"
},
  "geometry": {"coordinates":[9.337792,52.077755],"type":"Point"}
}