{
  "type": "Feature",
  "properties": {
    "iso:country":"DE",
    "sg:address":"Holzkamp 7",
    "sg:city":"Lippetal",
    "sg:phone":"+49 2527/9199019",
    "sg:postcode":"59510",
    "sg:province":"Nordrhein-Westfalen",
    "wof:name":"Clever Call Inh. Iris H\u00f6ner",
    "wof:placetype":"venue"
},
  "geometry": {"coordinates":[8.04762,51.66592],"type":"Point"}
}