{
  "type": "Feature",
  "properties": {
    "iso:country":"DE",
    "sg:address":"Dorfstr. 52",
    "sg:city":"Wohlde",
    "sg:phone":"+49 4885/902041",
    "sg:postcode":"24899",
    "sg:province":"Schleswig-Holstein",
    "wof:name":"Northtronics Web Design",
    "wof:placetype":"venue"
},
  "geometry": {"coordinates":[9.2948617935,54.4041519165],"type":"Point"}
}