{
  "type": "Feature",
  "properties": {
    "iso:country":"DE",
    "sg:address":"Enzenspergerweg 5e",
    "sg:city":"Oberstdorf",
    "sg:phone":"+49 8322/1096",
    "sg:postcode":"87561",
    "sg:province":"Bayern",
    "wof:name":"Allianz Geiger & Walther",
    "wof:placetype":"venue"
},
  "geometry": {"coordinates":[10.285656929,47.4090614319],"type":"Point"}
}