{
  "type": "Feature",
  "properties": {
    "iso:country":"DE",
    "sg:address":"Lohm\u00fchle 10",
    "sg:city":"Eppingen",
    "sg:phone":"+49 7262/924850",
    "sg:postcode":"75031",
    "sg:province":"Baden-W\u00fcrttemberg",
    "wof:name":"Sibru-druck Und Media Gmbh",
    "wof:placetype":"venue"
},
  "geometry": {"coordinates":[8.8928442001,49.1325035095],"type":"Point"}
}