{
  "type": "Feature",
  "properties": {
    "iso:country":"DE",
    "sg:address":"Kolpingstr 18",
    "sg:city":"Mannheim",
    "sg:phone":"+49 621/418840",
    "sg:postcode":"68165",
    "sg:province":"Baden-W\u00fcrttemberg",
    "wof:name":"Cpr Copy-, Plot- U. Reproservice Gmbh",
    "wof:placetype":"venue"
},
  "geometry": {"coordinates":[8.486826,49.484901],"type":"Point"}
}