{
  "type": "Feature",
  "properties": {
    "iso:country":"DE",
    "sg:address":"Paul-Kosmalla-Str. 3",
    "sg:city":"M\u00fclheim",
    "sg:phone":"+49 208/434707",
    "sg:postcode":"45472",
    "sg:province":"Nordrhein-Westfalen",
    "wof:name":"Horst Stemmer",
    "wof:placetype":"venue"
},
  "geometry": {"coordinates":[6.9253959656,51.4331054688],"type":"Point"}
}