{
  "type": "Feature",
  "properties": {
    "iso:country":"DE",
    "sg:address":"Westwall 1",
    "sg:city":"Schwerte",
    "sg:phone":"+49 2304/18718",
    "sg:postcode":"58239",
    "sg:province":"Nordrhein-Westfalen",
    "wof:name":"Rosita Roters",
    "wof:placetype":"venue"
},
  "geometry": {"coordinates":[7.565899,51.440594],"type":"Point"}
}