{
  "type": "Feature",
  "properties": {
    "iso:country":"DE",
    "sg:address":"Sch\u00f6nborner Str. 33",
    "sg:city":"Triptis",
    "sg:phone":"+49 36482/32532",
    "sg:postcode":"07819",
    "sg:province":"Th\u00fcringen",
    "wof:name":"Karl-heinz Prochnow",
    "wof:placetype":"venue"
},
  "geometry": {"coordinates":[11.861339,50.740555],"type":"Point"}
}