{
  "type": "Feature",
  "properties": {
    "iso:country":"DE",
    "sg:address":"\u00c4nne-Schulte-Str. 8",
    "sg:city":"K\u00f6ln",
    "sg:postcode":"51109",
    "sg:province":"Nordrhein-Westfalen",
    "wof:name":"Profil Warenhandels Gmbh",
    "wof:placetype":"venue"
},
  "geometry": {"coordinates":[7.0561208725,50.9447631836],"type":"Point"}
}