{
  "type": "Feature",
  "properties": {
    "iso:country":"DE",
    "sg:address":"Paderborner Str. 331",
    "sg:city":"Bielefeld",
    "sg:phone":"+49 5205/70118",
    "sg:postcode":"33689",
    "sg:province":"Nordrhein-Westfalen",
    "wof:name":"Buschhof",
    "wof:placetype":"venue"
},
  "geometry": {"coordinates":[8.6035804749,51.9333992004],"type":"Point"}
}