{
  "type": "Feature",
  "properties": {
    "iso:country":"DE",
    "sg:address":"Birkendorf",
    "sg:city":"\u00dchlingen-Birkendorf",
    "sg:phone":"+49 7743/392",
    "sg:postcode":"79777",
    "sg:province":"Baden-W\u00fcrttemberg",
    "wof:name":"Waldschwimmbad",
    "wof:placetype":"venue"
},
  "geometry": {"coordinates":[8.3184499741,47.7201004028],"type":"Point"}
}