{
  "type": "Feature",
  "properties": {
    "iso:country":"DE",
    "sg:address":"St.-T\u00f6nnis-Str. 71",
    "sg:city":"K\u00f6ln",
    "sg:phone":"+49 221/782684",
    "sg:postcode":"50769",
    "sg:province":"Nordrhein-Westfalen",
    "wof:name":"Knopp-steven Augenoptiker",
    "wof:placetype":"venue"
},
  "geometry": {"coordinates":[6.8625149727,51.0626983643],"type":"Point"}
}