{
  "type": "Feature",
  "properties": {
    "iso:country":"DE",
    "sg:address":"Weinstr. 45",
    "sg:city":"Bad Bergzabern",
    "sg:phone":"+49 6343/939423",
    "sg:postcode":"76887",
    "sg:province":"Rheinland-Pfalz",
    "wof:name":"Mayer",
    "wof:placetype":"venue"
},
  "geometry": {"coordinates":[7.998263,49.100468],"type":"Point"}
}