{
  "type": "Feature",
  "properties": {
    "iso:country":"DE",
    "sg:address":"An der Alexish\u00fctte 11",
    "sg:city":"Wietmarschen",
    "sg:phone":"+49 5925/99703",
    "sg:postcode":"49835",
    "sg:province":"Niedersachsen",
    "wof:name":"N. Rakel",
    "wof:placetype":"venue"
},
  "geometry": {"coordinates":[7.1349048615,52.504650116],"type":"Point"}
}