{
  "type": "Feature",
  "properties": {
    "iso:country":"DE",
    "sg:address":"Wildemannsgasse 14",
    "sg:city":"Kassel",
    "sg:phone":"+49 561/700010",
    "sg:postcode":"34117",
    "sg:province":"Hessen",
    "wof:name":"Gemeinn\u00fctzige Wohnungsbau- Ges. Der Stadt Kassel Mbh",
    "wof:placetype":"venue"
},
  "geometry": {"coordinates":[9.5039300919,51.3157958984],"type":"Point"}
}