{
  "type": "Feature",
  "properties": {
    "iso:country":"DE",
    "sg:address":"Heinrich-Heine-Str. 47",
    "sg:city":"Emsdetten",
    "sg:phone":"+49 2572/81455",
    "sg:postcode":"48282",
    "sg:province":"Nordrhein-Westfalen",
    "wof:name":"Gerhard Limbrock Architekt",
    "wof:placetype":"venue"
},
  "geometry": {"coordinates":[7.521823,52.165081],"type":"Point"}
}