{
  "type": "Feature",
  "properties": {
    "iso:country":"DE",
    "sg:address":"Ottendorf Dorfstr. 81 a",
    "sg:city":"Ottendorf",
    "sg:phone":"+49 36426/207",
    "sg:postcode":"07646",
    "sg:province":"Th\u00fcringen",
    "wof:name":"Raiffeisenbank Hermsdorf",
    "wof:placetype":"venue"
},
  "geometry": {"coordinates":[11.75468,50.847301],"type":"Point"}
}