{
  "type": "Feature",
  "properties": {
    "iso:country":"DE",
    "sg:address":"Alaunstr. 21",
    "sg:city":"Dresden",
    "sg:phone":"+49 351/8026504",
    "sg:postcode":"01099",
    "sg:province":"Sachsen",
    "wof:name":"Konsum",
    "wof:placetype":"venue"
},
  "geometry": {"coordinates":[13.7494602203,51.0650215149],"type":"Point"}
}