{
  "type": "Feature",
  "properties": {
    "iso:country":"DE",
    "sg:address":"Goetheweg 1",
    "sg:city":"Rinteln",
    "sg:phone":"+49 5751/6565",
    "sg:postcode":"31737",
    "sg:province":"Niedersachsen",
    "wof:name":"Herz",
    "wof:placetype":"venue"
},
  "geometry": {"coordinates":[9.0879096985,52.2056045532],"type":"Point"}
}