{
  "type": "Feature",
  "properties": {
    "iso:country":"DE",
    "sg:address":"Alte Dorfstr. 37",
    "sg:city":"Meddewade",
    "sg:phone":"+49 4531/88385",
    "sg:postcode":"23847",
    "sg:province":"Schleswig-Holstein",
    "wof:name":"N & H Kleidermarkt Gmbh",
    "wof:placetype":"venue"
},
  "geometry": {"coordinates":[10.440281,53.810089],"type":"Point"}
}