{
  "type": "Feature",
  "properties": {
    "iso:country":"DE",
    "sg:address":"Zwickauer Str. 22",
    "sg:city":"Schneeberg",
    "sg:phone":"+49 3772/20738",
    "sg:postcode":"08289",
    "sg:province":"Sachsen",
    "wof:name":"Stefan R. Neukirchner Rechtsanwalt",
    "wof:placetype":"venue"
},
  "geometry": {"coordinates":[12.6377191544,50.5951805115],"type":"Point"}
}