{
  "type": "Feature",
  "properties": {
    "iso:country":"DE",
    "sg:address":"Birkenweg 22",
    "sg:city":"Schwarzenbach",
    "sg:phone":"+49 9644/1302",
    "sg:postcode":"92720",
    "sg:province":"Bayern",
    "wof:name":"Horst Greim",
    "wof:placetype":"venue"
},
  "geometry": {"coordinates":[11.9981060028,49.715221405],"type":"Point"}
}