{
  "type": "Feature",
  "properties": {
    "iso:country":"DE",
    "sg:address":"Rodener Str. 5",
    "sg:city":"Urspringen",
    "sg:postcode":"97857",
    "sg:province":"Bayern",
    "wof:name":"Raiffeisenkasse Wechingen-holzkirchen Eg",
    "wof:placetype":"venue"
},
  "geometry": {"coordinates":[10.612525,48.89299],"type":"Point"}
}