{
  "type": "Feature",
  "properties": {
    "iso:country":"DE",
    "sg:address":"Antoniusstr. 11",
    "sg:city":"Herten",
    "sg:phone":"+49 2366/35145",
    "sg:postcode":"45699",
    "sg:province":"Nordrhein-Westfalen",
    "wof:name":"Ernst Pollmann Ohg",
    "wof:placetype":"venue"
},
  "geometry": {"coordinates":[7.1377391815,51.5933952332],"type":"Point"}
}