{
  "type": "Feature",
  "properties": {
    "iso:country":"DE",
    "sg:address":"Ostpreu\u00dfenweg 11",
    "sg:city":"Osterode",
    "sg:phone":"+49 5522/2351",
    "sg:postcode":"37520",
    "sg:province":"Niedersachsen",
    "wof:name":"Hubert Hartel",
    "wof:placetype":"venue"
},
  "geometry": {"coordinates":[10.2400550842,51.7356452942],"type":"Point"}
}