{
  "type": "Feature",
  "properties": {
    "iso:country":"DE",
    "sg:address":"Yorckstr. 73",
    "sg:city":"Delmenhorst",
    "sg:phone":"+49 4221/21594",
    "sg:postcode":"27755",
    "sg:province":"Niedersachsen",
    "wof:name":"Toni Kreis",
    "wof:placetype":"venue"
},
  "geometry": {"coordinates":[8.625743866,53.0212669373],"type":"Point"}
}