{
  "type": "Feature",
  "properties": {
    "iso:country":"DE",
    "sg:address":"Hoyerswerdaer Str. 51",
    "sg:city":"Spremberg",
    "sg:phone":"+49 3563/4809",
    "sg:postcode":"03130",
    "sg:province":"Brandenburg",
    "wof:name":"Frank Henschel",
    "wof:placetype":"venue"
},
  "geometry": {"coordinates":[14.3617219925,51.563419342],"type":"Point"}
}