{
  "type": "Feature",
  "properties": {
    "iso:country":"DE",
    "sg:address":"Ohlendorfer Str. 40",
    "sg:city":"Seevetal",
    "sg:phone":"+49 4185/792600",
    "sg:postcode":"21220",
    "sg:province":"Niedersachsen",
    "wof:name":"Dvs-computer Service Gmbh",
    "wof:placetype":"venue"
},
  "geometry": {"coordinates":[10.0366725922,53.3430671692],"type":"Point"}
}