{
  "type": "Feature",
  "properties": {
    "iso:country":"DE",
    "sg:address":"Obere Schlo\u00dfstr. 24",
    "sg:city":"Alfdorf",
    "sg:postcode":"73553",
    "sg:province":"Baden-W\u00fcrttemberg",
    "wof:name":"Gma Beteiligungs Gmbh",
    "wof:placetype":"venue"
},
  "geometry": {"coordinates":[9.720865,48.8442],"type":"Point"}
}