{
  "type": "Feature",
  "properties": {
    "iso:country":"DE",
    "sg:address":"Schillerstr. 4",
    "sg:city":"Roth",
    "sg:phone":"+49 9171/892175",
    "sg:postcode":"91154",
    "sg:province":"Bayern",
    "wof:name":"Erich Rottler",
    "wof:placetype":"venue"
},
  "geometry": {"coordinates":[11.0973386765,49.2512779236],"type":"Point"}
}