{
  "type": "Feature",
  "properties": {
    "iso:country":"DE",
    "sg:address":"Feldstedter Weg 26",
    "sg:city":"Berlin",
    "sg:phone":"+49 30/7424986",
    "sg:postcode":"12305",
    "sg:province":"Berlin",
    "wof:name":"Tschirpke Hans J\u00fcrgen",
    "wof:placetype":"venue"
},
  "geometry": {"coordinates":[13.3974046707,52.4109725952],"type":"Point"}
}