{
  "type": "Feature",
  "properties": {
    "iso:country":"DE",
    "sg:address":"Henschelstr. 26",
    "sg:city":"Frankfurt",
    "sg:postcode":"60314",
    "sg:province":"Hessen",
    "wof:name":"Urbania Grundst\u00fccksgesellschaft Mbh",
    "wof:placetype":"venue"
},
  "geometry": {"coordinates":[8.70903,50.114403],"type":"Point"}
}