{
  "type": "Feature",
  "properties": {
    "iso:country":"DE",
    "sg:address":"Kurt-Schumacher-Str. 378",
    "sg:city":"Gelsenkirchen",
    "sg:phone":"+49 209/930980",
    "sg:postcode":"45897",
    "sg:province":"Nordrhein-Westfalen",
    "wof:name":"Color-partner Gmbh",
    "wof:placetype":"venue"
},
  "geometry": {"coordinates":[7.0579738617,51.5742721558],"type":"Point"}
}