{
  "type": "Feature",
  "properties": {
    "iso:country":"DE",
    "sg:address":"Treuenbrietzener Str. 17",
    "sg:city":"Beelitz",
    "sg:phone":"+49 33204/35531",
    "sg:postcode":"14547",
    "sg:province":"Brandenburg",
    "wof:name":"Optimal Gmbh",
    "wof:placetype":"venue"
},
  "geometry": {"coordinates":[12.972109,52.224636],"type":"Point"}
}