{
  "type": "Feature",
  "properties": {
    "iso:country":"DE",
    "sg:address":"Waldstr. 32",
    "sg:city":"Pforzheim",
    "sg:phone":"+49 7231/79055",
    "sg:postcode":"75181",
    "sg:province":"Baden-W\u00fcrttemberg",
    "wof:name":"Bau Haag Gmbh",
    "wof:placetype":"venue"
},
  "geometry": {"coordinates":[8.73955,48.855957],"type":"Point"}
}