{
  "type": "Feature",
  "properties": {
    "iso:country":"DE",
    "sg:address":"Lomske 52",
    "sg:city":"Neschwitz",
    "sg:phone":"+49 35934/6357",
    "sg:postcode":"02699",
    "sg:province":"Sachsen",
    "wof:name":"Manfred Pohlan",
    "wof:placetype":"venue"
},
  "geometry": {"coordinates":[14.298901,51.26749],"type":"Point"}
}