{
  "type": "Feature",
  "properties": {
    "iso:country":"DE",
    "sg:address":"Vinninger Str. 2",
    "sg:city":"Bottenbach",
    "sg:phone":"+49 6339/1439",
    "sg:postcode":"66504",
    "sg:province":"Rheinland-Pfalz",
    "wof:name":"Uwe Reiser",
    "wof:placetype":"venue"
},
  "geometry": {"coordinates":[7.49585,49.181999],"type":"Point"}
}