{
  "type": "Feature",
  "properties": {
    "iso:country":"DE",
    "sg:address":"Breite Str. 76",
    "sg:city":"Andernach",
    "sg:phone":"+49 2632/45215",
    "sg:postcode":"56626",
    "sg:province":"Rheinland-Pfalz",
    "wof:name":"Post-apotheke Hans-heinrich Van Boemmel E.k.",
    "wof:placetype":"venue"
},
  "geometry": {"coordinates":[7.402529,50.434528],"type":"Point"}
}