{
  "type": "Feature",
  "properties": {
    "iso:country":"DE",
    "sg:address":"Thomas-Mann-Str. 4",
    "sg:city":"Mittweida",
    "sg:phone":"+49 3727/3098",
    "sg:postcode":"09648",
    "sg:province":"Sachsen",
    "wof:name":"E. Hampel",
    "wof:placetype":"venue"
},
  "geometry": {"coordinates":[12.9639949799,50.9928512573],"type":"Point"}
}