{
  "type": "Feature",
  "properties": {
    "iso:country":"DE",
    "sg:address":"Obertorstr. 14",
    "sg:city":"Giengen",
    "sg:phone":"+49 7322/919367",
    "sg:postcode":"89537",
    "sg:province":"Baden-W\u00fcrttemberg",
    "wof:name":"Wolfgang Klenk",
    "wof:placetype":"venue"
},
  "geometry": {"coordinates":[10.243639946,48.621963501],"type":"Point"}
}