{
  "type": "Feature",
  "properties": {
    "iso:country":"DE",
    "sg:address":"Mausegatt 12",
    "sg:city":"Duisburg",
    "sg:phone":"+49 4920/6599740",
    "sg:postcode":"47228",
    "sg:province":"Nordrhein-Westfalen",
    "wof:name":"Werkstoffpr\u00dcfung Peters Gmbh",
    "wof:placetype":"venue"
},
  "geometry": {"coordinates":[6.69335,51.421017],"type":"Point"}
}