{
  "type": "Feature",
  "properties": {
    "iso:country":"DE",
    "sg:address":"Hauptstr. 40",
    "sg:city":"M\u00fcden",
    "sg:phone":"+49 5375/2584",
    "sg:postcode":"38539",
    "sg:province":"Niedersachsen",
    "wof:name":"U. Harder",
    "wof:placetype":"venue"
},
  "geometry": {"coordinates":[10.3659067154,52.524143219],"type":"Point"}
}