{
  "type": "Feature",
  "properties": {
    "iso:country":"DE",
    "sg:address":"Am M\u00fchlenberg 3",
    "sg:city":"Schweringen",
    "sg:phone":"+49 4257/462",
    "sg:postcode":"27333",
    "sg:province":"Niedersachsen",
    "wof:name":"I. M\u00fcller",
    "wof:placetype":"venue"
},
  "geometry": {"coordinates":[9.178074,52.743977],"type":"Point"}
}