{
  "type": "Feature",
  "properties": {
    "iso:country":"DE",
    "sg:address":"Am Steinbruch 5",
    "sg:city":"V\u00f6hl",
    "sg:phone":"+49 5631/60433",
    "sg:postcode":"34516",
    "sg:province":"Hessen",
    "wof:name":"Heinrich Bauch Gmbh",
    "wof:placetype":"venue"
},
  "geometry": {"coordinates":[8.8957195282,51.230381012],"type":"Point"}
}