{
  "type": "Feature",
  "properties": {
    "iso:country":"DE",
    "sg:address":"Bredeneyer Str. 12",
    "sg:city":"Essen",
    "sg:phone":"+49 201/422435",
    "sg:postcode":"45133",
    "sg:province":"Nordrhein-Westfalen",
    "wof:name":"Seibert",
    "wof:placetype":"venue"
},
  "geometry": {"coordinates":[7.000563,51.421291],"type":"Point"}
}