{
  "type": "Feature",
  "properties": {
    "iso:country":"DE",
    "sg:address":"Rotter Bruch 17",
    "sg:city":"Aachen",
    "sg:phone":"+49 241/51970",
    "sg:postcode":"52068",
    "sg:province":"Nordrhein-Westfalen",
    "wof:name":"Wehmeyer Gmbh & Co. Kg",
    "wof:placetype":"venue"
},
  "geometry": {"coordinates":[6.127856,50.780567],"type":"Point"}
}