{
  "type": "Feature",
  "properties": {
    "iso:country":"DE",
    "sg:address":"Merowingerstr. 5-7",
    "sg:city":"K\u00f6ln",
    "sg:postcode":"50677",
    "sg:province":"Nordrhein-Westfalen",
    "wof:name":"Peg-gewotec Bau-projekt- Entwicklungs Gmbh",
    "wof:placetype":"venue"
},
  "geometry": {"coordinates":[6.9588360786,50.920841217],"type":"Point"}
}