{
  "type": "Feature",
  "properties": {
    "iso:country":"DE",
    "sg:address":"Wittoverstiege 30",
    "sg:city":"M\u00fcnster",
    "sg:phone":"+49 2534/7906",
    "sg:postcode":"48161",
    "sg:province":"Nordrhein-Westfalen",
    "wof:name":"Zimmerei Fehmer Gmbh",
    "wof:placetype":"venue"
},
  "geometry": {"coordinates":[7.5368118286,51.9759140015],"type":"Point"}
}