{
  "type": "Feature",
  "properties": {
    "iso:country":"DE",
    "sg:address":"Schillerstr. 18-18a",
    "sg:city":"Altenstadt",
    "sg:phone":"+49 8337/72950",
    "sg:postcode":"89281",
    "sg:province":"Bayern",
    "wof:name":"Kiebler Haus Und Grund Ag",
    "wof:placetype":"venue"
},
  "geometry": {"coordinates":[10.111609,48.159145],"type":"Point"}
}