{
  "type": "Feature",
  "properties": {
    "iso:country":"DE",
    "sg:address":"Kemmannstr 104/106",
    "sg:city":"Wuppertal",
    "sg:phone":"+49 202/2474580",
    "sg:postcode":"42349",
    "sg:province":"Nordrhein-Westfalen",
    "wof:name":"Gustav Christians Gmbh + Co Kg Vorrichtungen-r\u00e4umwerkzeuge",
    "wof:placetype":"venue"
},
  "geometry": {"coordinates":[7.14213,51.203671],"type":"Point"}
}