{
  "type": "Feature",
  "properties": {
    "iso:country":"DE",
    "sg:address":"Nachtwaidstr. 10",
    "sg:city":"B\u00f6tzingen",
    "sg:phone":"+49 7684/9204",
    "sg:postcode":"79268",
    "sg:province":"Baden-W\u00fcrttemberg",
    "wof:name":"H. Rehbein Garten- Und",
    "wof:placetype":"venue"
},
  "geometry": {"coordinates":[7.716497,48.069344],"type":"Point"}
}