{
  "type": "Feature",
  "properties": {
    "iso:country":"DE",
    "sg:address":"Z\u00fclpicher Str. 304",
    "sg:city":"K\u00f6ln",
    "sg:phone":"+49 221/413101",
    "sg:postcode":"50937",
    "sg:province":"Nordrhein-Westfalen",
    "wof:name":"Erich Lanser",
    "wof:placetype":"venue"
},
  "geometry": {"coordinates":[6.920179,50.921864],"type":"Point"}
}