{
  "type": "Feature",
  "properties": {
    "iso:country":"DE",
    "sg:address":"Julius-Echter-Str. 31",
    "sg:city":"Werneck",
    "sg:phone":"+49 9722/7490",
    "sg:postcode":"97440",
    "sg:province":"Bayern",
    "wof:name":"Hans Paul Wirth Architekt",
    "wof:placetype":"venue"
},
  "geometry": {"coordinates":[10.094804,49.982956],"type":"Point"}
}