{
  "type": "Feature",
  "properties": {
    "iso:country":"DE",
    "sg:address":"Bgm.-Smidt-Str. 42",
    "sg:city":"Bremerhaven",
    "sg:phone":"+49 471/44141",
    "sg:postcode":"27568",
    "sg:province":"Bremen",
    "wof:name":"Urologe Dr.s.fritz-jelden",
    "wof:placetype":"venue"
},
  "geometry": {"coordinates":[8.582082,53.544289],"type":"Point"}
}