{
  "type": "Feature",
  "properties": {
    "iso:country":"DE",
    "sg:address":"Untermarkt 11",
    "sg:city":"Gau-Odernheim",
    "sg:phone":"+49 6733/230",
    "sg:postcode":"55239",
    "sg:province":"Rheinland-Pfalz",
    "wof:name":"St. Urban-apotheke",
    "wof:placetype":"venue"
},
  "geometry": {"coordinates":[8.193765,49.784538],"type":"Point"}
}