{
  "type": "Feature",
  "properties": {
    "iso:country":"DE",
    "sg:address":"Grambeker Weg 157",
    "sg:city":"M\u00f6lln",
    "sg:phone":"+49 4542/820200",
    "sg:postcode":"23879",
    "sg:province":"Schleswig-Holstein",
    "wof:name":"Tmv Telefonmarketing Und Vertriebsges. Mbh",
    "wof:placetype":"venue"
},
  "geometry": {"coordinates":[10.6771335602,53.6060371399],"type":"Point"}
}