{
  "type": "Feature",
  "properties": {
    "iso:country":"DE",
    "sg:address":"Klint 3",
    "sg:city":"Kneitlingen",
    "sg:phone":"+49 5332/4040",
    "sg:postcode":"38170",
    "sg:province":"Niedersachsen",
    "wof:name":"Eilumer Plan-bau Gmbh",
    "wof:placetype":"venue"
},
  "geometry": {"coordinates":[10.723900795,52.1626777649],"type":"Point"}
}