{
  "type": "Feature",
  "properties": {
    "iso:country":"DE",
    "sg:address":"Allensteiner Str. 24",
    "sg:city":"Duisburg",
    "sg:phone":"+49 2151/405430",
    "sg:postcode":"47239",
    "sg:province":"Nordrhein-Westfalen",
    "wof:name":"A. Von Weschpfennig",
    "wof:placetype":"venue"
},
  "geometry": {"coordinates":[6.681019783,51.3942146301],"type":"Point"}
}