{
  "type": "Feature",
  "properties": {
    "iso:country":"DE",
    "sg:address":"Kandern",
    "sg:city":"Kandern",
    "sg:phone":"+49 7626/8077",
    "sg:postcode":"79400",
    "sg:province":"Baden-W\u00fcrttemberg",
    "wof:name":"Sparkasse L\u00f6rrach-rheinfelden",
    "wof:placetype":"venue"
},
  "geometry": {"coordinates":[7.64394,47.703098],"type":"Point"}
}