{
  "type": "Feature",
  "properties": {
    "iso:country":"DE",
    "sg:address":"Buchenstr. 2",
    "sg:city":"W\u00f6rth",
    "sg:phone":"+49 8122/54383",
    "sg:postcode":"85457",
    "sg:province":"Bayern",
    "wof:name":"Angelika Stempel Heilpraktikerin",
    "wof:placetype":"venue"
},
  "geometry": {"coordinates":[11.9369363785,48.2443733215],"type":"Point"}
}