{
  "type": "Feature",
  "properties": {
    "iso:country":"DE",
    "sg:address":"Gutenbergstr. 5",
    "sg:city":"Lorsch",
    "sg:phone":"+49 6251/52428",
    "sg:postcode":"64653",
    "sg:province":"Hessen",
    "wof:name":"Helmut Kaltwasser",
    "wof:placetype":"venue"
},
  "geometry": {"coordinates":[8.5608110428,49.6476593018],"type":"Point"}
}