{
  "type": "Feature",
  "properties": {
    "iso:country":"DE",
    "sg:address":"Augsburger Str. 568",
    "sg:city":"Stuttgart",
    "sg:postcode":"70329",
    "sg:province":"Baden-W\u00fcrttemberg",
    "wof:name":"Proplan Projektentwicklungs- Und Planungsgesellschaft Mbh",
    "wof:placetype":"venue"
},
  "geometry": {"coordinates":[9.263322,48.769138],"type":"Point"}
}