{
  "type": "Feature",
  "properties": {
    "iso:country":"DE",
    "sg:address":"Haselnu\u00dfweg 6",
    "sg:city":"Waiblingen",
    "sg:phone":"+49 7151/507881",
    "sg:postcode":"71334",
    "sg:province":"Baden-W\u00fcrttemberg",
    "wof:name":"Otto Harrandt Verwaltungs Gmbh",
    "wof:placetype":"venue"
},
  "geometry": {"coordinates":[9.3006181717,48.8649215698],"type":"Point"}
}