{
  "type": "Feature",
  "properties": {
    "iso:country":"DE",
    "sg:address":"Lippoldsruh 8",
    "sg:city":"M\u00fclsen",
    "sg:phone":"+49 375/274380",
    "sg:postcode":"08132",
    "sg:province":"Sachsen",
    "wof:name":"Dyckerhoff Transportbeton Sachsen-th\u00fcringen Gmbh & Co Kg",
    "wof:placetype":"venue"
},
  "geometry": {"coordinates":[12.576789856,50.7390899658],"type":"Point"}
}