{
  "type": "Feature",
  "properties": {
    "iso:country":"DE",
    "sg:address":"Zellerhornstr. 79",
    "sg:city":"Albstadt",
    "sg:phone":"+49 7432/21285",
    "sg:postcode":"72461",
    "sg:province":"Baden-W\u00fcrttemberg",
    "wof:name":"Dietmar Keinath",
    "wof:placetype":"venue"
},
  "geometry": {"coordinates":[9.003382,48.289677],"type":"Point"}
}