{
  "type": "Feature",
  "properties": {
    "iso:country":"DE",
    "sg:address":"Gerstenweg 12",
    "sg:city":"Schlangenbad",
    "sg:phone":"+49 6129/2432",
    "sg:postcode":"65388",
    "sg:province":"Hessen",
    "wof:name":"Dr. Wolfgang Westenberger Rechtsanwalt Und Notar",
    "wof:placetype":"venue"
},
  "geometry": {"coordinates":[8.1194677353,50.0859451294],"type":"Point"}
}