{
  "type": "Feature",
  "properties": {
    "iso:country":"DE",
    "sg:address":"Alt-Buch 45-51",
    "sg:city":"Berlin",
    "sg:phone":"+49 30/9493003",
    "sg:postcode":"13125",
    "sg:province":"Berlin",
    "wof:name":"B\u00fcro F\u00fcr Architekturbezogene Kunst Berlin",
    "wof:placetype":"venue"
},
  "geometry": {"coordinates":[13.499711,52.635544],"type":"Point"}
}