{
  "type": "Feature",
  "properties": {
    "iso:country":"DE",
    "sg:address":"Erlanger Str. 95a",
    "sg:city":"F\u00fcrth",
    "sg:phone":"+49 911/7906791",
    "sg:postcode":"90765",
    "sg:province":"Bayern",
    "wof:name":"Werner Heid",
    "wof:placetype":"venue"
},
  "geometry": {"coordinates":[10.996631,49.484673],"type":"Point"}
}