{
  "type": "Feature",
  "properties": {
    "iso:country":"DE",
    "sg:address":"Rablstr. 42",
    "sg:city":"M\u00fcnchen",
    "sg:phone":"+49 89/4801371",
    "sg:postcode":"81669",
    "sg:province":"Bayern",
    "wof:name":"Ing. Grad. Dieter Schenkl Hochbauarchitekt",
    "wof:placetype":"venue"
},
  "geometry": {"coordinates":[11.593874,48.126675],"type":"Point"}
}