{
  "type": "Feature",
  "properties": {
    "iso:country":"DE",
    "sg:address":"Frankfurter Stra\u00dfe 30",
    "sg:city":"Marburg",
    "sg:phone":"+49 6421/924778",
    "sg:postcode":"35037",
    "sg:province":"Hessen",
    "wof:name":"Koch Mcgovern Dienstleistungen F\u00fcr Den F\u00fchrungsalltag",
    "wof:placetype":"venue"
},
  "geometry": {"coordinates":[8.7651987076,50.8011894226],"type":"Point"}
}