{
  "type": "Feature",
  "properties": {
    "iso:country":"DE",
    "sg:address":"Allg\u00e4uer Str. 23",
    "sg:city":"Pfronten",
    "sg:phone":"+49 8363/8221",
    "sg:postcode":"87459",
    "sg:province":"Bayern",
    "wof:name":"Pfrontner Kinderstube Inh. Paula Ortmeier",
    "wof:placetype":"venue"
},
  "geometry": {"coordinates":[10.5596542358,47.5829963684],"type":"Point"}
}