{
  "type": "Feature",
  "properties": {
    "iso:country":"DE",
    "sg:address":"Ansbacher Str. 15",
    "sg:city":"Rothenburg",
    "sg:phone":"+49 9861/3656",
    "sg:postcode":"91541",
    "sg:province":"Bayern",
    "wof:name":"Toppler-apotheke",
    "wof:placetype":"venue"
},
  "geometry": {"coordinates":[10.1847,49.376686],"type":"Point"}
}