{
  "type": "Feature",
  "properties": {
    "iso:country":"DE",
    "sg:address":"Mettenberger Str. 14",
    "sg:city":"Maselheim",
    "sg:phone":"+49 7351/12028",
    "sg:postcode":"88437",
    "sg:province":"Baden-W\u00fcrttemberg",
    "wof:name":"Franz Pf\u00e4nder",
    "wof:placetype":"venue"
},
  "geometry": {"coordinates":[9.8632059097,48.1206321716],"type":"Point"}
}