{
  "type": "Feature",
  "properties": {
    "iso:country":"DE",
    "sg:address":"Hans-B\u00f6ckler-Str. 9",
    "sg:city":"Trautskirchen",
    "sg:phone":"+49 651/7120",
    "sg:postcode":"90619",
    "sg:province":"Bayern",
    "wof:name":"Sparkasse Trier",
    "wof:placetype":"venue"
},
  "geometry": {"coordinates":[6.636521,49.757256],"type":"Point"}
}