{
  "type": "Feature",
  "properties": {
    "iso:country":"DE",
    "sg:address":"N\u00e4gelsbachstra\u00dfe 26",
    "sg:city":"Erlangen",
    "sg:phone":"+49 9131/74480",
    "sg:postcode":"91052",
    "sg:province":"Bayern",
    "wof:name":"T3 Medien Gmbh",
    "wof:placetype":"venue"
},
  "geometry": {"coordinates":[11.0050058365,49.590423584],"type":"Point"}
}