{
  "type": "Feature",
  "properties": {
    "iso:country":"DE",
    "sg:address":"Nienhagen",
    "sg:city":"Nienhagen",
    "sg:phone":"+49 5144/2045",
    "sg:postcode":"29336",
    "sg:province":"Niedersachsen",
    "wof:name":"Volksbank Wathlingen Eg",
    "wof:placetype":"venue"
},
  "geometry": {"coordinates":[10.09651,52.538441],"type":"Point"}
}