{
  "type": "Feature",
  "properties": {
    "iso:country":"DE",
    "sg:address":"Dr.-Herbert-Iann-Str. 6",
    "sg:city":"Baunach",
    "sg:phone":"+49 9544/680",
    "sg:postcode":"96148",
    "sg:province":"Bayern",
    "wof:name":"Seba-dynatronic Industrie- Elektronic Gmbh & Co. Kg",
    "wof:placetype":"venue"
},
  "geometry": {"coordinates":[10.85438,49.990501],"type":"Point"}
}