{
  "type": "Feature",
  "properties": {
    "iso:country":"DE",
    "sg:address":"Hotherstr. 20",
    "sg:city":"G\u00f6rlitz",
    "sg:phone":"+49 3581/406661",
    "sg:postcode":"02826",
    "sg:province":"Sachsen",
    "wof:name":"Cafe-restaurant-bar Vierradenm\u00fchle",
    "wof:placetype":"venue"
},
  "geometry": {"coordinates":[14.9933233261,51.1579437256],"type":"Point"}
}