{
  "type": "Feature",
  "properties": {
    "iso:country":"DE",
    "sg:address":"M\u00fchlweg 1",
    "sg:city":"Eppingen",
    "sg:phone":"+49 7262/2221",
    "sg:postcode":"75031",
    "sg:province":"Baden-W\u00fcrttemberg",
    "wof:name":"Horst Lerch Heilpraktiker",
    "wof:placetype":"venue"
},
  "geometry": {"coordinates":[8.9132404327,49.1388397217],"type":"Point"}
}