{
  "type": "Feature",
  "properties": {
    "iso:country":"DE",
    "sg:address":"Herzog-Heinrich-Str. 10",
    "sg:city":"Rosenheim",
    "sg:phone":"+49 8031/17001",
    "sg:postcode":"83022",
    "sg:province":"Bayern",
    "wof:name":"Redaktion Echo Pons Aeni Verlag",
    "wof:placetype":"venue"
},
  "geometry": {"coordinates":[12.1227025986,47.8555450439],"type":"Point"}
}