{
  "type": "Feature",
  "properties": {
    "iso:country":"DE",
    "sg:address":"Kirchplatz 1",
    "sg:city":"Hoyerswerda",
    "sg:postcode":"02977",
    "sg:province":"Sachsen",
    "wof:name":"Ev. Kirche",
    "wof:placetype":"venue"
},
  "geometry": {"coordinates":[14.2423582077,51.4377326965],"type":"Point"}
}