{
  "type": "Feature",
  "properties": {
    "iso:country":"DE",
    "sg:address":"Weberweg 4",
    "sg:city":"Bad Wurzach",
    "sg:phone":"+49 7564/3434",
    "sg:postcode":"88410",
    "sg:province":"Baden-W\u00fcrttemberg",
    "wof:name":"Karl Schmid Bildhauer",
    "wof:placetype":"venue"
},
  "geometry": {"coordinates":[9.894329,47.907192],"type":"Point"}
}