{
  "type": "Feature",
  "properties": {
    "iso:country":"DE",
    "sg:address":"Harburger Ring 20",
    "sg:city":"Hamburg",
    "sg:phone":"+49 40/776696",
    "sg:postcode":"21073",
    "sg:province":"Hamburg",
    "wof:name":"Reiseb\u00fcro Erich Hartmann Gmbh",
    "wof:placetype":"venue"
},
  "geometry": {"coordinates":[9.9812316895,53.4607162476],"type":"Point"}
}