{
  "type": "Feature",
  "properties": {
    "iso:country":"DE",
    "sg:address":"Auf der Kappel 11",
    "sg:city":"Merklingen",
    "sg:phone":"+49 7337/451",
    "sg:postcode":"89188",
    "sg:province":"Baden-W\u00fcrttemberg",
    "wof:name":"Georg Bunz",
    "wof:placetype":"venue"
},
  "geometry": {"coordinates":[9.751161,48.511166],"type":"Point"}
}