{
  "type": "Feature",
  "properties": {
    "iso:country":"DE",
    "sg:address":"Marsstr. 16-18",
    "sg:city":"Xanten",
    "sg:phone":"+49 2801/4011",
    "sg:postcode":"46509",
    "sg:province":"Nordrhein-Westfalen",
    "wof:name":"Xantener-reiseb\u00fcro Ohg",
    "wof:placetype":"venue"
},
  "geometry": {"coordinates":[6.4549269676,51.6605949402],"type":"Point"}
}