{
  "type": "Feature",
  "properties": {
    "iso:country":"DE",
    "sg:address":"Dorfstr. 65",
    "sg:city":"Reupzig",
    "sg:postcode":"06369",
    "sg:province":"Sachsen-Anhalt",
    "wof:name":"Christiane Fr\u00f6mmigen",
    "wof:placetype":"venue"
},
  "geometry": {"coordinates":[12.070078,51.736057],"type":"Point"}
}