{
  "type": "Feature",
  "properties": {
    "iso:country":"DE",
    "sg:address":"R\u00f6lscheider Str. 23",
    "sg:city":"Solingen",
    "sg:phone":"+49 212/819159",
    "sg:postcode":"42657",
    "sg:province":"Nordrhein-Westfalen",
    "wof:name":"K\u00f6nig Gmbh",
    "wof:placetype":"venue"
},
  "geometry": {"coordinates":[7.0690689087,51.1374931335],"type":"Point"}
}