{
  "type": "Feature",
  "properties": {
    "iso:country":"DE",
    "sg:address":"Bernhard-Uhde-Str. 10",
    "sg:city":"Hildesheim",
    "sg:phone":"+49 5121/41818",
    "sg:postcode":"31137",
    "sg:province":"Niedersachsen",
    "wof:name":"Eberhard H\u00fcser",
    "wof:placetype":"venue"
},
  "geometry": {"coordinates":[9.904178,52.167393],"type":"Point"}
}