{
  "type": "Feature",
  "properties": {
    "iso:country":"DE",
    "sg:address":"Heithemstr. 17",
    "sg:city":"L\u00f6rrach",
    "sg:phone":"+49 7621/3829",
    "sg:postcode":"79539",
    "sg:province":"Baden-W\u00fcrttemberg",
    "wof:name":"R\u00f6ttelnblick",
    "wof:placetype":"venue"
},
  "geometry": {"coordinates":[7.6641860008,47.6225318909],"type":"Point"}
}