{
  "type": "Feature",
  "properties": {
    "iso:country":"DE",
    "sg:address":"Ernst-Heinkel-Str. 20",
    "sg:city":"Nordhorn",
    "sg:phone":"+49 5921/307151",
    "sg:postcode":"48531",
    "sg:province":"Niedersachsen",
    "wof:name":"T. C. Metallbau Klausheide Gmbh",
    "wof:placetype":"venue"
},
  "geometry": {"coordinates":[7.1675100327,52.4612922668],"type":"Point"}
}