{
  "type": "Feature",
  "properties": {
    "iso:country":"DE",
    "sg:address":"Pastoratstr. 3",
    "sg:city":"Viersen",
    "sg:postcode":"41751",
    "sg:province":"Nordrhein-Westfalen",
    "wof:name":"Kath. \u00f6ffentliche Bibliothek St. Peter",
    "wof:placetype":"venue"
},
  "geometry": {"coordinates":[6.269762,51.270496],"type":"Point"}
}