{
  "type": "Feature",
  "properties": {
    "iso:country":"DE",
    "sg:address":"Bahnhofstr. 9",
    "sg:city":"Siegen",
    "sg:phone":"+49 271/55215",
    "sg:postcode":"57072",
    "sg:province":"Nordrhein-Westfalen",
    "wof:name":"Pizzeria City",
    "wof:placetype":"venue"
},
  "geometry": {"coordinates":[8.0181770325,50.8746261597],"type":"Point"}
}