{
  "type": "Feature",
  "properties": {
    "iso:country":"DE",
    "sg:address":"Reichenberger Str. 4",
    "sg:city":"Augsburg",
    "sg:phone":"+49 821/468842",
    "sg:postcode":"86161",
    "sg:province":"Bayern",
    "wof:name":"Kurt Schachtner Rechtsanwalt",
    "wof:placetype":"venue"
},
  "geometry": {"coordinates":[10.9167881012,48.3618965149],"type":"Point"}
}