{
  "type": "Feature",
  "properties": {
    "iso:country":"DE",
    "sg:address":"Kurze Str. 4",
    "sg:city":"Bad Emstal",
    "sg:phone":"+49 5624/925500",
    "sg:postcode":"34308",
    "sg:province":"Hessen",
    "wof:name":"X-sat Systeme Vertriebsgesellschaft Mbh",
    "wof:placetype":"venue"
},
  "geometry": {"coordinates":[9.2605352402,51.2437858582],"type":"Point"}
}