{
  "type": "Feature",
  "properties": {
    "iso:country":"DE",
    "sg:address":"Meisenweg 2",
    "sg:city":"Seligenstadt",
    "sg:phone":"+49 6182/24704",
    "sg:postcode":"63500",
    "sg:province":"Hessen",
    "wof:name":"H.-p. Und K. Friedrich",
    "wof:placetype":"venue"
},
  "geometry": {"coordinates":[8.9563989639,50.0432624817],"type":"Point"}
}