{
  "type": "Feature",
  "properties": {
    "iso:country":"DE",
    "sg:address":"Robert-Koch-Str. 164",
    "sg:city":"Burghausen",
    "sg:phone":"+49 8677/4154",
    "sg:postcode":"84489",
    "sg:province":"Bayern",
    "wof:name":"Heinrich Senden",
    "wof:placetype":"venue"
},
  "geometry": {"coordinates":[12.8178920746,48.1613349915],"type":"Point"}
}