{
  "type": "Feature",
  "properties": {
    "iso:country":"DE",
    "sg:address":"Schwarze Str. 80",
    "sg:city":"Essen",
    "sg:phone":"+49 201/356413",
    "sg:postcode":"45326",
    "sg:province":"Nordrhein-Westfalen",
    "wof:name":"Bernhard Rupieper",
    "wof:placetype":"venue"
},
  "geometry": {"coordinates":[7.020941,51.494171],"type":"Point"}
}