{
  "type": "Feature",
  "properties": {
    "iso:country":"DE",
    "sg:address":"Weender Str. 84",
    "sg:city":"G\u00f6ttingen",
    "sg:phone":"+49 551/57020",
    "sg:postcode":"37073",
    "sg:province":"Niedersachsen",
    "wof:name":"Alfred Ewert",
    "wof:placetype":"venue"
},
  "geometry": {"coordinates":[9.9346313477,51.5367622375],"type":"Point"}
}