{
  "type": "Feature",
  "properties": {
    "iso:country":"DE",
    "sg:address":"Sch\u00f6ttlstr. 9",
    "sg:city":"M\u00fcnchen",
    "sg:phone":"+49 89/7244850",
    "sg:postcode":"81369",
    "sg:province":"Bayern",
    "wof:name":"Synitech Informationstechnolog Uwe Hewig E. K.",
    "wof:placetype":"venue"
},
  "geometry": {"coordinates":[11.5373392105,48.1089553833],"type":"Point"}
}