{
  "type": "Feature",
  "properties": {
    "iso:country":"DE",
    "sg:address":"Im Zwinger 8",
    "sg:city":"Markgr\u00f6ningen",
    "sg:phone":"+49 7145/4679",
    "sg:postcode":"71706",
    "sg:province":"Baden-W\u00fcrttemberg",
    "wof:name":"Otto Vetter",
    "wof:placetype":"venue"
},
  "geometry": {"coordinates":[9.079042,48.906029],"type":"Point"}
}