{
  "type": "Feature",
  "properties": {
    "iso:country":"DE",
    "sg:address":"Fl\u00f6\u00dfergasse 11",
    "sg:city":"M\u00fcnchen",
    "sg:phone":"+49 89/7231019",
    "sg:postcode":"81369",
    "sg:province":"Bayern",
    "wof:name":"Fl\u00f6sser-sauna",
    "wof:placetype":"venue"
},
  "geometry": {"coordinates":[11.538258,48.104328],"type":"Point"}
}