{
  "type": "Feature",
  "properties": {
    "iso:country":"DE",
    "sg:address":"Katzensteige 17",
    "sg:city":"Amstetten",
    "sg:phone":"+49 7331/41151",
    "sg:postcode":"73340",
    "sg:province":"Baden-W\u00fcrttemberg",
    "wof:name":"Hermann Osswald Architekt",
    "wof:placetype":"venue"
},
  "geometry": {"coordinates":[9.914203,48.593456],"type":"Point"}
}