{
  "type": "Feature",
  "properties": {
    "iso:country":"DE",
    "sg:address":"Maybachstr. 4",
    "sg:city":"Konstanz",
    "sg:phone":"+49 7531/65605",
    "sg:postcode":"78467",
    "sg:province":"Baden-W\u00fcrttemberg",
    "wof:name":"Malerwerkst\u00e4tte K. Zahn",
    "wof:placetype":"venue"
},
  "geometry": {"coordinates":[9.152925,47.677006],"type":"Point"}
}