{
  "type": "Feature",
  "properties": {
    "iso:country":"DE",
    "sg:address":"Eisenacher Str. 12",
    "sg:city":"Wiesbaden",
    "sg:phone":"+49 611/500113",
    "sg:postcode":"65191",
    "sg:province":"Hessen",
    "wof:name":"P. J. Butler Commercial Trade Agency Kg",
    "wof:placetype":"venue"
},
  "geometry": {"coordinates":[8.2849979401,50.0910491943],"type":"Point"}
}