{
  "type": "Feature",
  "properties": {
    "iso:country":"DE",
    "sg:address":"Bergstr. 7a",
    "sg:city":"Bamberg",
    "sg:phone":"+49 951/61676",
    "sg:postcode":"96049",
    "sg:province":"Bayern",
    "wof:name":"Herbert Kr\u00f6ner",
    "wof:placetype":"venue"
},
  "geometry": {"coordinates":[10.85939,49.903915],"type":"Point"}
}