{
  "type": "Feature",
  "properties": {
    "iso:country":"DE",
    "sg:address":"Moltkestr. 15",
    "sg:city":"Bad Salzuflen",
    "sg:phone":"+49 5222/10487",
    "sg:postcode":"32105",
    "sg:province":"Nordrhein-Westfalen",
    "wof:name":"Pension Haus K\u00f6nigin Luise",
    "wof:placetype":"venue"
},
  "geometry": {"coordinates":[8.7439470291,52.0889701843],"type":"Point"}
}