{
  "type": "Feature",
  "properties": {
    "iso:country":"DE",
    "sg:address":"H\u00f6ftenweg 26",
    "sg:city":"Haren",
    "sg:phone":"+49 5932/2461",
    "sg:postcode":"49733",
    "sg:province":"Niedersachsen",
    "wof:name":"Bernhard Rohling Ms Maro",
    "wof:placetype":"venue"
},
  "geometry": {"coordinates":[7.236146,52.794724],"type":"Point"}
}