{
  "type": "Feature",
  "properties": {
    "iso:country":"DE",
    "sg:address":"Klingelp\u00fctz 33-35",
    "sg:city":"K\u00f6ln",
    "sg:postcode":"50670",
    "sg:province":"Nordrhein-Westfalen",
    "wof:name":"Fabian & Schr\u00f6der Gmbh",
    "wof:placetype":"venue"
},
  "geometry": {"coordinates":[6.949174,50.944511],"type":"Point"}
}