{
  "type": "Feature",
  "properties": {
    "iso:country":"DE",
    "sg:address":"Hauptstr. 60",
    "sg:city":"Tennenbronn",
    "sg:phone":"+49 7729/212",
    "sg:postcode":"78144",
    "sg:province":"Baden-W\u00fcrttemberg",
    "wof:name":"Adler",
    "wof:placetype":"venue"
},
  "geometry": {"coordinates":[8.3536281586,48.1908798218],"type":"Point"}
}