{
  "type": "Feature",
  "properties": {
    "iso:country":"DE",
    "sg:address":"Bernsteinweg 2",
    "sg:city":"Ostseebad Prerow",
    "sg:phone":"+49 38233/282",
    "sg:postcode":"18375",
    "sg:province":"Mecklenburg-Vorpommern",
    "wof:name":"Wielandhaus Norddeutsche B\u00fccher- Und Kunstgewerbehandel",
    "wof:placetype":"venue"
},
  "geometry": {"coordinates":[12.5563669205,54.4480857849],"type":"Point"}
}