{
  "type": "Feature",
  "properties": {
    "iso:country":"DE",
    "sg:address":"Schopfheimer Str. 10",
    "sg:city":"L\u00f6rrach",
    "sg:phone":"+49 7621/55999",
    "sg:postcode":"79541",
    "sg:province":"Baden-W\u00fcrttemberg",
    "wof:name":"Armin Weber",
    "wof:placetype":"venue"
},
  "geometry": {"coordinates":[7.693669796,47.6352539062],"type":"Point"}
}