{
  "type": "Feature",
  "properties": {
    "iso:country":"DE",
    "sg:address":"Schwarzwaldstr. 17",
    "sg:city":"Gernsbach",
    "sg:phone":"+49 7224/2603",
    "sg:postcode":"76593",
    "sg:province":"Baden-W\u00fcrttemberg",
    "wof:name":"Wagner Gmbh",
    "wof:placetype":"venue"
},
  "geometry": {"coordinates":[8.3376626968,48.7696266174],"type":"Point"}
}