{
  "type": "Feature",
  "properties": {
    "iso:country":"DE",
    "sg:address":"An den Steinen 1",
    "sg:city":"Lohmar",
    "sg:phone":"+49 2246/300215",
    "sg:postcode":"53797",
    "sg:province":"Nordrhein-Westfalen",
    "wof:name":"Msl Wohnbau Gmbh",
    "wof:placetype":"venue"
},
  "geometry": {"coordinates":[7.21626,50.848698],"type":"Point"}
}