{
  "type": "Feature",
  "properties": {
    "iso:country":"DE",
    "sg:address":"Emil-Werner-Weg 96",
    "sg:city":"Gelenau",
    "sg:postcode":"09423",
    "sg:province":"Sachsen",
    "wof:name":"Verkaufshaus Trikot Gmbh",
    "wof:placetype":"venue"
},
  "geometry": {"coordinates":[12.999442,50.710777],"type":"Point"}
}