{
  "type": "Feature",
  "properties": {
    "iso:country":"DE",
    "sg:address":"Zeppelinstr. 26",
    "sg:city":"Holzminden",
    "sg:phone":"+49 5531/2666",
    "sg:postcode":"37603",
    "sg:province":"Niedersachsen",
    "wof:name":"Michael Tylla Fitnesscenter",
    "wof:placetype":"venue"
},
  "geometry": {"coordinates":[9.4678344727,51.8425979614],"type":"Point"}
}