{
  "type": "Feature",
  "properties": {
    "iso:country":"DE",
    "sg:address":"Gie\u00dfener Str. 1",
    "sg:city":"Fritzlar",
    "sg:phone":"+49 5622/4646",
    "sg:postcode":"34560",
    "sg:province":"Hessen",
    "wof:name":"Meltemi-reisen Inh. Adolf H. K\u00f6hler",
    "wof:placetype":"venue"
},
  "geometry": {"coordinates":[9.2752561569,51.1317100525],"type":"Point"}
}