{
  "type": "Feature",
  "properties": {
    "iso:country":"DE",
    "sg:address":"Bildst\u00f6ckleweg 40",
    "sg:city":"Baiersbronn",
    "sg:phone":"+49 7442/5533",
    "sg:postcode":"72270",
    "sg:province":"Baden-W\u00fcrttemberg",
    "wof:name":"Hans W\u00fcrth",
    "wof:placetype":"venue"
},
  "geometry": {"coordinates":[8.3648309708,48.5087471008],"type":"Point"}
}