{
  "type": "Feature",
  "properties": {
    "iso:country":"DE",
    "sg:address":"Delvenauweg 6",
    "sg:city":"M\u00f6lln",
    "sg:postcode":"23879",
    "sg:province":"Schleswig-Holstein",
    "wof:name":"R & P Elektronik Usv Anlagen Gmbh",
    "wof:placetype":"venue"
},
  "geometry": {"coordinates":[10.674784,53.613335],"type":"Point"}
}