{
  "type": "Feature",
  "properties": {
    "iso:country":"DE",
    "sg:address":"Buschower Weg 60",
    "sg:city":"Berlin",
    "sg:phone":"+49 30/3633799",
    "sg:postcode":"13591",
    "sg:province":"Berlin",
    "wof:name":"Klaus Eickemeyer Architekt",
    "wof:placetype":"venue"
},
  "geometry": {"coordinates":[13.132173,52.521469],"type":"Point"}
}