{
  "type": "Feature",
  "properties": {
    "iso:country":"DE",
    "sg:address":"Gau\u00dfstr 6",
    "sg:city":"Herford",
    "sg:phone":"+49 5221/70788",
    "sg:postcode":"32052",
    "sg:province":"Nordrhein-Westfalen",
    "wof:name":"Gebr. Landwehr",
    "wof:placetype":"venue"
},
  "geometry": {"coordinates":[8.6822099686,52.1033973694],"type":"Point"}
}