{
  "type": "Feature",
  "properties": {
    "iso:country":"DE",
    "sg:address":"Linckestr. 26",
    "sg:city":"Berglen",
    "sg:phone":"+49 7195/71254",
    "sg:postcode":"73663",
    "sg:province":"Baden-W\u00fcrttemberg",
    "wof:name":"Annelore Wieland Licht- Und Fotopausen",
    "wof:placetype":"venue"
},
  "geometry": {"coordinates":[9.4653253555,48.8603172302],"type":"Point"}
}