{
  "type": "Feature",
  "properties": {
    "iso:country":"DE",
    "sg:address":"Am Stadtgraben 3",
    "sg:city":"Pottenstein",
    "sg:phone":"+49 9243/92440",
    "sg:postcode":"91278",
    "sg:province":"Bayern",
    "wof:name":"Wagner-br\u00e4u Bruckmayer Ohg",
    "wof:placetype":"venue"
},
  "geometry": {"coordinates":[11.407079,49.771465],"type":"Point"}
}