{
  "type": "Feature",
  "properties": {
    "iso:country":"DE",
    "sg:address":"Bahnhofstr. 7",
    "sg:city":"Herzogenrath",
    "sg:postcode":"52134",
    "sg:province":"Nordrhein-Westfalen",
    "wof:name":"Sl Ingenieurbau Gmbh",
    "wof:placetype":"venue"
},
  "geometry": {"coordinates":[6.0940799713,50.8688583374],"type":"Point"}
}