{
  "type": "Feature",
  "properties": {
    "iso:country":"DE",
    "sg:address":"Hauptstr. 26",
    "sg:city":"Gelnhausen",
    "sg:phone":"+49 6051/74166",
    "sg:postcode":"63571",
    "sg:province":"Hessen",
    "wof:name":"Ferdinand Ruppel",
    "wof:placetype":"venue"
},
  "geometry": {"coordinates":[9.19051,50.202965],"type":"Point"}
}