{
  "type": "Feature",
  "properties": {
    "iso:country":"DE",
    "sg:address":"Zeppelinstr. 29",
    "sg:city":"Vaihingen",
    "sg:phone":"+49 7042/5338",
    "sg:postcode":"71665",
    "sg:province":"Baden-W\u00fcrttemberg",
    "wof:name":"Ev. Pfarramt Ii",
    "wof:placetype":"venue"
},
  "geometry": {"coordinates":[8.9687099457,48.9522018433],"type":"Point"}
}