{
  "type": "Feature",
  "properties": {
    "iso:country":"DE",
    "sg:address":"Birkenstr. 15",
    "sg:city":"Gr\u00f6benzell",
    "sg:phone":"+49 8142",
    "sg:postcode":"82194",
    "sg:province":"Bayern",
    "wof:name":"Klaus M\u00fcller Technisches B\u00fcro",
    "wof:placetype":"venue"
},
  "geometry": {"coordinates":[11.3696136475,48.2002792358],"type":"Point"}
}