{
  "type": "Feature",
  "properties": {
    "iso:country":"DE",
    "sg:address":"Hindenburgstr. 44",
    "sg:city":"Riedlingen",
    "sg:phone":"+49 7371/930010",
    "sg:postcode":"88499",
    "sg:province":"Baden-W\u00fcrttemberg",
    "wof:name":"Karl-heinz Hindelang",
    "wof:placetype":"venue"
},
  "geometry": {"coordinates":[9.4816989899,48.149394989],"type":"Point"}
}