{
  "type": "Feature",
  "properties": {
    "iso:country":"DE",
    "sg:address":"Max-Lang-Strasse 62",
    "sg:city":"Leinfelden Echterdingen",
    "sg:postcode":"70771",
    "sg:province":"Baden-W\u00fcrttemberg",
    "wof:name":"Rieker Druckveredelung Gmbh & Co. Kg",
    "wof:placetype":"venue"
},
  "geometry": {"coordinates":[9.142836,48.70179],"type":"Point"}
}