{
  "type": "Feature",
  "properties": {
    "iso:country":"DE",
    "sg:address":"Feldweg 7",
    "sg:city":"Zarrendorf",
    "sg:phone":"+49 38327/80026",
    "sg:postcode":"18510",
    "sg:province":"Mecklenburg-Vorpommern",
    "wof:name":"Burkhard Behrendt",
    "wof:placetype":"venue"
},
  "geometry": {"coordinates":[13.0815830231,54.2380981445],"type":"Point"}
}