{
  "type": "Feature",
  "properties": {
    "iso:country":"DE",
    "sg:address":"Spann 19",
    "sg:city":"Norderstedt",
    "sg:phone":"+49 40/5231819",
    "sg:postcode":"22848",
    "sg:province":"Schleswig-Holstein",
    "wof:name":"Hermann Timm",
    "wof:placetype":"venue"
},
  "geometry": {"coordinates":[9.95783,53.676971],"type":"Point"}
}