{
  "type": "Feature",
  "properties": {
    "iso:country":"DE",
    "sg:address":"Zedeliusstr. 35 + 37",
    "sg:city":"Wangerooge",
    "sg:phone":"+49 4469/315",
    "sg:postcode":"26486",
    "sg:province":"Niedersachsen",
    "wof:name":"Ingeborg Von Ahn & Sohn Porzellan- Und",
    "wof:placetype":"venue"
},
  "geometry": {"coordinates":[7.8999609947,53.7917442322],"type":"Point"}
}