{
  "type": "Feature",
  "properties": {
    "iso:country":"DE",
    "sg:address":"Schwaiger Str. 59a",
    "sg:city":"Dingolfing",
    "sg:phone":"+49 8731/71021",
    "sg:postcode":"84130",
    "sg:province":"Bayern",
    "wof:name":"Andreas Fischer Kunst- Und Bauschlosserei",
    "wof:placetype":"venue"
},
  "geometry": {"coordinates":[12.4818305969,48.6404571533],"type":"Point"}
}