{
  "type": "Feature",
  "properties": {
    "iso:country":"DE",
    "sg:address":"Eisenacher Str. 47",
    "sg:city":"Berlin",
    "sg:phone":"+49 30/78707070",
    "sg:postcode":"10823",
    "sg:province":"Berlin",
    "wof:name":"Metropolitan Media Kg",
    "wof:placetype":"venue"
},
  "geometry": {"coordinates":[13.3492126465,52.4880485535],"type":"Point"}
}