{
  "type": "Feature",
  "properties": {
    "iso:country":"DE",
    "sg:address":"Sonnenstr. 30",
    "sg:city":"Sonnenb\u00fchl",
    "sg:phone":"+49 7128/2487",
    "sg:postcode":"72820",
    "sg:province":"Baden-W\u00fcrttemberg",
    "wof:name":"B. Walser",
    "wof:placetype":"venue"
},
  "geometry": {"coordinates":[9.191963,48.388405],"type":"Point"}
}