{
  "type": "Feature",
  "properties": {
    "iso:country":"DE",
    "sg:address":"Breul 13",
    "sg:city":"M\u00fcnster",
    "sg:phone":"+49 251/45887",
    "sg:postcode":"48143",
    "sg:province":"Nordrhein-Westfalen",
    "wof:name":"Heinz-dieter Sch\u00e4fer",
    "wof:placetype":"venue"
},
  "geometry": {"coordinates":[7.6277527809,51.9671592712],"type":"Point"}
}