{
  "type": "Feature",
  "properties": {
    "iso:country":"DE",
    "sg:address":"Weserm\u00fcnder Str. 221",
    "sg:city":"Bremerv\u00f6rde",
    "sg:phone":"+49 4761/2343",
    "sg:postcode":"27432",
    "sg:province":"Niedersachsen",
    "wof:name":"Ernst-august Haase",
    "wof:placetype":"venue"
},
  "geometry": {"coordinates":[9.100728035,53.4975814819],"type":"Point"}
}