{
  "type": "Feature",
  "properties": {
    "iso:country":"DE",
    "sg:address":"Gelbe-B\u00fcrg-Str. 24",
    "sg:city":"Dittenheim",
    "sg:phone":"+49 9834/544",
    "sg:postcode":"91723",
    "sg:province":"Bayern",
    "wof:name":"Karl Schmidt Bau Gmbh",
    "wof:placetype":"venue"
},
  "geometry": {"coordinates":[10.786131,49.051991],"type":"Point"}
}