{
  "type": "Feature",
  "properties": {
    "iso:country":"DE",
    "sg:address":"K\u00e4thnerort 30",
    "sg:city":"Hamburg",
    "sg:postcode":"22083",
    "sg:province":"Hamburg",
    "wof:name":"New Town Music E. K.",
    "wof:placetype":"venue"
},
  "geometry": {"coordinates":[10.037841,53.581539],"type":"Point"}
}