{
  "type": "Feature",
  "properties": {
    "iso:country":"DE",
    "sg:address":"Landfurt 61",
    "sg:city":"Warburg",
    "sg:phone":"+49 5641/743411",
    "sg:postcode":"34414",
    "sg:province":"Nordrhein-Westfalen",
    "wof:name":"Hofstetter Und Ehrhardt Ergotherapeutische Praxis",
    "wof:placetype":"venue"
},
  "geometry": {"coordinates":[9.15583,51.49345],"type":"Point"}
}