{
  "type": "Feature",
  "properties": {
    "iso:country":"DE",
    "sg:address":"Hauptstr. 28",
    "sg:city":"Briedel",
    "sg:phone":"+49 6542/4842",
    "sg:postcode":"56867",
    "sg:province":"Rheinland-Pfalz",
    "wof:name":"M. Rees",
    "wof:placetype":"venue"
},
  "geometry": {"coordinates":[7.151159,50.019718],"type":"Point"}
}