{
  "type": "Feature",
  "properties": {
    "iso:country":"DE",
    "sg:address":"Grasstr. 11",
    "sg:city":"Essen",
    "sg:phone":"+49 201/668613",
    "sg:postcode":"45356",
    "sg:province":"Nordrhein-Westfalen",
    "wof:name":"Aquametasil Wasseraufbereitung Gmbh",
    "wof:placetype":"venue"
},
  "geometry": {"coordinates":[6.9528369904,51.4864273071],"type":"Point"}
}