{
  "type": "Feature",
  "properties": {
    "iso:country":"DE",
    "sg:address":"Kolberger Str. 30",
    "sg:city":"Garbsen",
    "sg:phone":"+49 5131/2137",
    "sg:postcode":"30826",
    "sg:province":"Niedersachsen",
    "wof:name":"Uta Grill Heilpraktikerin",
    "wof:placetype":"venue"
},
  "geometry": {"coordinates":[9.5492277145,52.4571914673],"type":"Point"}
}