{
  "type": "Feature",
  "properties": {
    "iso:country":"DE",
    "sg:address":"Wischhofstr. 1-3",
    "sg:city":"Kiel",
    "sg:postcode":"24148",
    "sg:province":"Schleswig-Holstein",
    "wof:name":"Mbt - Meerestechnisches B\u00fcro Turla Gmbh",
    "wof:placetype":"venue"
},
  "geometry": {"coordinates":[10.176913,54.327656],"type":"Point"}
}