{
  "type": "Feature",
  "properties": {
    "iso:country":"DE",
    "sg:address":"Rigwinstr. 36",
    "sg:city":"Dortmund",
    "sg:phone":"+49 231/335118",
    "sg:postcode":"44359",
    "sg:province":"Nordrhein-Westfalen",
    "wof:name":"Gastst\u00e4tte Busbahnhof",
    "wof:placetype":"venue"
},
  "geometry": {"coordinates":[7.3834400177,51.5708999634],"type":"Point"}
}