{
  "type": "Feature",
  "properties": {
    "iso:country":"DE",
    "sg:address":"Duisburger Str. 46",
    "sg:city":"Ratingen",
    "sg:phone":"+49 2102/703014",
    "sg:postcode":"40885",
    "sg:province":"Nordrhein-Westfalen",
    "wof:name":"Reinhold Lang Innenarchitekt",
    "wof:placetype":"venue"
},
  "geometry": {"coordinates":[6.824349,51.347046],"type":"Point"}
}