{
  "type": "Feature",
  "properties": {
    "iso:country":"DE",
    "sg:address":"Saaleblick 17",
    "sg:city":"Hohenroth",
    "sg:phone":"+49 9771/2702",
    "sg:postcode":"97618",
    "sg:province":"Bayern",
    "wof:name":"W. Rossmann",
    "wof:placetype":"venue"
},
  "geometry": {"coordinates":[10.1815509796,50.3114547729],"type":"Point"}
}