{
  "type": "Feature",
  "properties": {
    "iso:country":"DE",
    "sg:address":"Tittmoninger Str. 14",
    "sg:city":"Trostberg",
    "sg:postcode":"83308",
    "sg:province":"Bayern",
    "wof:name":"Tm Bau Gmbh",
    "wof:placetype":"venue"
},
  "geometry": {"coordinates":[12.5624103546,48.029384613],"type":"Point"}
}