{
  "type": "Feature",
  "properties": {
    "iso:country":"DE",
    "sg:address":"H\u00fcller Str. 92",
    "sg:city":"Bochum",
    "sg:phone":"+49 2327/82131",
    "sg:postcode":"44866",
    "sg:province":"Nordrhein-Westfalen",
    "wof:name":"Hubertus-apotheke",
    "wof:placetype":"venue"
},
  "geometry": {"coordinates":[7.138794,51.489307],"type":"Point"}
}