{
  "type": "Feature",
  "properties": {
    "iso:country":"DE",
    "sg:address":"Waldstr. 1",
    "sg:city":"Schotten",
    "sg:postcode":"63679",
    "sg:province":"Hessen",
    "wof:name":"Trapp Kg",
    "wof:placetype":"venue"
},
  "geometry": {"coordinates":[9.217041,50.497761],"type":"Point"}
}