{
  "type": "Feature",
  "properties": {
    "iso:country":"DE",
    "sg:address":"Am St\u00e4rzenbach 1",
    "sg:city":"moosham",
    "sg:phone":"+49 9406/90540",
    "sg:postcode":"93098",
    "sg:province":"Bayern",
    "wof:name":"Willkommen Bei Panatta Deutschland - Fitnessger\u00e4te",
    "wof:placetype":"venue"
},
  "geometry": {"coordinates":[12.269823,48.927036],"type":"Point"}
}