{
  "type": "Feature",
  "properties": {
    "iso:country":"DE",
    "sg:address":"Friedrich-Ebert-Damm 143",
    "sg:city":"Hamburg",
    "sg:phone":"+49 40/6961081",
    "sg:postcode":"22047",
    "sg:province":"Hamburg",
    "wof:name":"Msw Marketing Service Und Werbemittel Th. Forster",
    "wof:placetype":"venue"
},
  "geometry": {"coordinates":[10.098159,53.588966],"type":"Point"}
}