{
  "type": "Feature",
  "properties": {
    "iso:country":"DE",
    "sg:address":"Ortsstr. 12",
    "sg:city":"Gaggenau",
    "sg:phone":"+49 7222/48581",
    "sg:postcode":"76571",
    "sg:province":"Baden-W\u00fcrttemberg",
    "wof:name":"Kreuz",
    "wof:placetype":"venue"
},
  "geometry": {"coordinates":[8.3101577759,48.8481063843],"type":"Point"}
}