{
  "type": "Feature",
  "properties": {
    "iso:country":"DE",
    "sg:address":"Eversbuschstr. 111",
    "sg:city":"M\u00fcnchen",
    "sg:postcode":"80999",
    "sg:province":"Bayern",
    "wof:name":"G. E. M. Computer Company Gmbh",
    "wof:placetype":"venue"
},
  "geometry": {"coordinates":[11.4597272873,48.1906166077],"type":"Point"}
}