{
  "type": "Feature",
  "properties": {
    "iso:country":"DE",
    "sg:address":"Sprengelstr. 28",
    "sg:city":"Burgdorf",
    "sg:phone":"+49 5136/83720",
    "sg:postcode":"31303",
    "sg:province":"Niedersachsen",
    "wof:name":"Heldt & Stra\u00dfner Gmbh",
    "wof:placetype":"venue"
},
  "geometry": {"coordinates":[9.9744195938,52.4669799805],"type":"Point"}
}