{
  "type": "Feature",
  "properties": {
    "iso:country":"DE",
    "sg:address":"Am Steinh\u00e4usle 2 a",
    "sg:city":"Karlsruhe",
    "sg:phone":"+49 721/450255",
    "sg:postcode":"76228",
    "sg:province":"Baden-W\u00fcrttemberg",
    "wof:name":"B\u00e4ckerei F\u00fctterer Gmbh",
    "wof:placetype":"venue"
},
  "geometry": {"coordinates":[8.466386,48.957722],"type":"Point"}
}