{
  "type": "Feature",
  "properties": {
    "iso:country":"DE",
    "sg:address":"K\u00f6lner Str. 224",
    "sg:city":"Bergneustadt",
    "sg:phone":"+49 2261/47711",
    "sg:postcode":"51702",
    "sg:province":"Nordrhein-Westfalen",
    "wof:name":"H. Zeider Gmbh",
    "wof:placetype":"venue"
},
  "geometry": {"coordinates":[7.6491441727,51.0203857422],"type":"Point"}
}