{
  "type": "Feature",
  "properties": {
    "iso:country":"DE",
    "sg:address":"Bahnhofstr. 96",
    "sg:city":"Gr\u00e4felfing",
    "sg:phone":"+49 89/7145618",
    "sg:postcode":"82166",
    "sg:province":"Bayern",
    "wof:name":"Bergmann Gmbh",
    "wof:placetype":"venue"
},
  "geometry": {"coordinates":[11.429352,48.118713],"type":"Point"}
}