{
  "type": "Feature",
  "properties": {
    "iso:country":"DE",
    "sg:address":"Borgholzhauser Str. 27",
    "sg:city":"Versmold",
    "sg:phone":"+49 5423/41611",
    "sg:postcode":"33775",
    "sg:province":"Nordrhein-Westfalen",
    "wof:name":"Kml Werbeagentur Gmbh",
    "wof:placetype":"venue"
},
  "geometry": {"coordinates":[8.1958227158,52.0612449646],"type":"Point"}
}