{
  "type": "Feature",
  "properties": {
    "iso:country":"DE",
    "sg:address":"Roggensteiner Allee 104",
    "sg:city":"Eichenau",
    "sg:phone":"+49 8141/818504",
    "sg:postcode":"82223",
    "sg:province":"Bayern",
    "wof:name":"Peter Kreilach",
    "wof:placetype":"venue"
},
  "geometry": {"coordinates":[11.3186321259,48.1687088013],"type":"Point"}
}