{
  "type": "Feature",
  "properties": {
    "iso:country":"DE",
    "sg:address":"Langobardenweg 18b",
    "sg:city":"Hamburg",
    "sg:postcode":"22455",
    "sg:province":"Hamburg",
    "wof:name":"Kerstin Zemke Handelsvertretungen E. K.",
    "wof:placetype":"venue"
},
  "geometry": {"coordinates":[9.962997,53.636169],"type":"Point"}
}