{
  "type": "Feature",
  "properties": {
    "iso:country":"DE",
    "sg:address":"Lehbrinksweg 72",
    "sg:city":"Lemgo",
    "sg:phone":"+49 4952/6166230",
    "sg:postcode":"32657",
    "sg:province":"Nordrhein-Westfalen",
    "wof:name":"Hegra Maschinenbau Gmbh",
    "wof:placetype":"venue"
},
  "geometry": {"coordinates":[8.83812,52.034241],"type":"Point"}
}