{
  "type": "Feature",
  "properties": {
    "iso:country":"DE",
    "sg:address":"Zollerstr. 7",
    "sg:city":"Fischach",
    "sg:phone":"+49 8236/570",
    "sg:postcode":"86850",
    "sg:province":"Bayern",
    "wof:name":"M\u00fcller Gmbh",
    "wof:placetype":"venue"
},
  "geometry": {"coordinates":[10.653933,48.309093],"type":"Point"}
}