{
  "type": "Feature",
  "properties": {
    "iso:country":"DE",
    "sg:address":"Schillerstr. 20",
    "sg:city":"Deilingen",
    "sg:phone":"+49 7426/8157",
    "sg:postcode":"78586",
    "sg:province":"Baden-W\u00fcrttemberg",
    "wof:name":"Raimund Volz Gmbh",
    "wof:placetype":"venue"
},
  "geometry": {"coordinates":[8.787399292,48.1758422852],"type":"Point"}
}