{
  "type": "Feature",
  "properties": {
    "iso:country":"DE",
    "sg:address":"H\u00f6henweg 18 c",
    "sg:city":"Dortmund",
    "sg:phone":"+49 2304/983130",
    "sg:postcode":"44265",
    "sg:province":"Nordrhein-Westfalen",
    "wof:name":"Pretschold Gartenbedarf Gmbh",
    "wof:placetype":"venue"
},
  "geometry": {"coordinates":[7.500619,51.447094],"type":"Point"}
}