{
  "type": "Feature",
  "properties": {
    "iso:country":"DE",
    "sg:address":"Carstennstr. 41a",
    "sg:city":"Berlin",
    "sg:phone":"+49 30/8174655",
    "sg:postcode":"12205",
    "sg:province":"Berlin",
    "wof:name":"Ralf Gleisenstein",
    "wof:placetype":"venue"
},
  "geometry": {"coordinates":[13.292503,52.424221],"type":"Point"}
}