{
  "type": "Feature",
  "properties": {
    "iso:country":"DE",
    "sg:address":"Osterweder Str. 7",
    "sg:city":"Worpswede",
    "sg:phone":"+49 4792/1203",
    "sg:postcode":"27726",
    "sg:province":"Niedersachsen",
    "wof:name":"Hans Behrens",
    "wof:placetype":"venue"
},
  "geometry": {"coordinates":[8.930076,53.22683],"type":"Point"}
}