{
  "type": "Feature",
  "properties": {
    "iso:country":"DE",
    "sg:address":"Friedrich-Ebert-Str. 16",
    "sg:city":"Duisburg",
    "sg:phone":"+49 203/400655",
    "sg:postcode":"47179",
    "sg:province":"Nordrhein-Westfalen",
    "wof:name":"Apotheke Mattenklotz",
    "wof:placetype":"venue"
},
  "geometry": {"coordinates":[6.741092,51.516834],"type":"Point"}
}