{
  "type": "Feature",
  "properties": {
    "iso:country":"DE",
    "sg:address":"Kanalstr. 16",
    "sg:city":"Marienwerder",
    "sg:phone":"+49 3335/7170",
    "sg:postcode":"16348",
    "sg:province":"Brandenburg",
    "wof:name":"Werner Hellwig",
    "wof:placetype":"venue"
},
  "geometry": {"coordinates":[13.595205307,52.8399505615],"type":"Point"}
}