{
  "type": "Feature",
  "properties": {
    "iso:country":"DE",
    "sg:address":"Kieler Str. 72",
    "sg:city":"Eckernf\u00f6rde",
    "sg:phone":"+49 4351/5912",
    "sg:postcode":"24340",
    "sg:province":"Schleswig-Holstein",
    "wof:name":"Buchhandlung Eugenie Goerke Inh. Norbert Iwersen",
    "wof:placetype":"venue"
},
  "geometry": {"coordinates":[9.837138176,54.468952179],"type":"Point"}
}