{
  "type": "Feature",
  "properties": {
    "iso:country":"DE",
    "sg:address":"Johanniterallee 6",
    "sg:city":"Neuenburg",
    "sg:phone":"+49 7635/581",
    "sg:postcode":"79395",
    "sg:province":"Baden-W\u00fcrttemberg",
    "wof:name":"Hans Winkler",
    "wof:placetype":"venue"
},
  "geometry": {"coordinates":[7.560558,47.774948],"type":"Point"}
}