{
  "type": "Feature",
  "properties": {
    "iso:country":"DE",
    "sg:address":"Bahnhofstr. 26",
    "sg:city":"Trier",
    "sg:phone":"+49 651/25230",
    "sg:postcode":"54292",
    "sg:province":"Rheinland-Pfalz",
    "wof:name":"B\u00e4ckerei Fischer",
    "wof:placetype":"venue"
},
  "geometry": {"coordinates":[6.650679,49.757645],"type":"Point"}
}