{
  "type": "Feature",
  "properties": {
    "iso:country":"DE",
    "sg:address":"Hauptstr. 150",
    "sg:city":"M\u00f6nchengladbach",
    "sg:phone":"+49 2166/47778",
    "sg:postcode":"41236",
    "sg:province":"Nordrhein-Westfalen",
    "wof:name":"Ralf Heidemeyer",
    "wof:placetype":"venue"
},
  "geometry": {"coordinates":[6.449388,51.168533],"type":"Point"}
}