{
  "type": "Feature",
  "properties": {
    "iso:country":"DE",
    "sg:address":"Falkensteinstr. 212",
    "sg:city":"Oberhausen",
    "sg:phone":"+49 208/869235",
    "sg:postcode":"46047",
    "sg:province":"Nordrhein-Westfalen",
    "wof:name":"Rolf Thomae",
    "wof:placetype":"venue"
},
  "geometry": {"coordinates":[6.8773407936,51.4752311707],"type":"Point"}
}