{
  "type": "Feature",
  "properties": {
    "iso:country":"DE",
    "sg:address":"Osterstr. 28",
    "sg:city":"Hameln",
    "sg:phone":"+49 5151/3888",
    "sg:postcode":"31785",
    "sg:province":"Niedersachsen",
    "wof:name":"Rattenf\u00e4ngerhaus",
    "wof:placetype":"venue"
},
  "geometry": {"coordinates":[9.3608760834,52.1041412354],"type":"Point"}
}