{
  "type": "Feature",
  "properties": {
    "iso:country":"DE",
    "sg:address":"Paulinenstr. 66",
    "sg:city":"Essen",
    "sg:phone":"+49 201/775293",
    "sg:postcode":"45131",
    "sg:province":"Nordrhein-Westfalen",
    "wof:name":"Marg. Beeken",
    "wof:placetype":"venue"
},
  "geometry": {"coordinates":[7.0114841461,51.4328460693],"type":"Point"}
}