{
  "type": "Feature",
  "properties": {
    "iso:country":"DE",
    "sg:address":"Bahnhofstr. 25",
    "sg:city":"Auerbach",
    "sg:phone":"+49 3744/216276",
    "sg:postcode":"08209",
    "sg:province":"Sachsen",
    "wof:name":"Pils Pub N\u00e4chterle",
    "wof:placetype":"venue"
},
  "geometry": {"coordinates":[12.3948783875,50.5141143799],"type":"Point"}
}