{
  "type": "Feature",
  "properties": {
    "iso:country":"DE",
    "sg:address":"Hauptstr. 4",
    "sg:city":"Zwingenberg",
    "sg:phone":"+49 6251/74923",
    "sg:postcode":"64673",
    "sg:province":"Hessen",
    "wof:name":"Karl Schweickert",
    "wof:placetype":"venue"
},
  "geometry": {"coordinates":[8.579495,49.718719],"type":"Point"}
}