{
  "type": "Feature",
  "properties": {
    "iso:country":"DE",
    "sg:address":"Annastr. 58",
    "sg:city":"Essen",
    "sg:phone":"+49 201/8775315",
    "sg:postcode":"45130",
    "sg:province":"Nordrhein-Westfalen",
    "wof:name":"Blanke",
    "wof:placetype":"venue"
},
  "geometry": {"coordinates":[7.010764122,51.4401893616],"type":"Point"}
}