{
  "type": "Feature",
  "properties": {
    "iso:country":"DE",
    "sg:address":"Schulstr 15",
    "sg:city":"Zirndorf",
    "sg:phone":"+49 911/960750",
    "sg:postcode":"90513",
    "sg:province":"Bayern",
    "wof:name":"Schlosserei Ott Metallbau -und Schl\u00fcsseldienst Gmbh",
    "wof:placetype":"venue"
},
  "geometry": {"coordinates":[10.955821,49.442879],"type":"Point"}
}