{
  "type": "Feature",
  "properties": {
    "iso:country":"DE",
    "sg:address":"Ringstr. 21",
    "sg:city":"Schneeberg",
    "sg:phone":"+49 9373/8330",
    "sg:postcode":"63936",
    "sg:province":"Bayern",
    "wof:name":"Sparkasse Miltenberg-obernburg",
    "wof:placetype":"venue"
},
  "geometry": {"coordinates":[9.248434,49.639252],"type":"Point"}
}