{
  "type": "Feature",
  "properties": {
    "iso:country":"DE",
    "sg:address":"Helenenstr. 1",
    "sg:city":"Essen",
    "sg:phone":"+49 201/620088",
    "sg:postcode":"45143",
    "sg:province":"Nordrhein-Westfalen",
    "wof:name":"Ute K\u00fcpper Steuerberaterin",
    "wof:placetype":"venue"
},
  "geometry": {"coordinates":[6.9800720215,51.4609413147],"type":"Point"}
}