{
  "type": "Feature",
  "properties": {
    "iso:country":"DE",
    "sg:address":"Irring",
    "sg:city":"Tiefenbach",
    "sg:phone":"+49 8546/633",
    "sg:postcode":"94113",
    "sg:province":"Bayern",
    "wof:name":"Dreifl\u00fcsse-camping",
    "wof:placetype":"venue"
},
  "geometry": {"coordinates":[13.36556,48.637592],"type":"Point"}
}