{
  "type": "Feature",
  "properties": {
    "iso:country":"DE",
    "sg:address":"Am Niddatal 33",
    "sg:city":"Frankfurt",
    "sg:phone":"+49 69/763705",
    "sg:postcode":"60488",
    "sg:province":"Hessen",
    "wof:name":"E. W. Ziegler",
    "wof:placetype":"venue"
},
  "geometry": {"coordinates":[8.618958,50.140015],"type":"Point"}
}