{
  "type": "Feature",
  "properties": {
    "iso:country":"DE",
    "sg:address":"Bahnhofstr. 17",
    "sg:city":"Nottuln",
    "sg:phone":"+49 2509/994484",
    "sg:postcode":"48301",
    "sg:province":"Nordrhein-Westfalen",
    "wof:name":"Asien Tropic",
    "wof:placetype":"venue"
},
  "geometry": {"coordinates":[7.4250340462,51.8966407776],"type":"Point"}
}