{
  "type": "Feature",
  "properties": {
    "iso:country":"DE",
    "sg:address":"Asbacher Str. 17 c",
    "sg:city":"Schmalkalden",
    "sg:phone":"+49 3683/781173",
    "sg:postcode":"98574",
    "sg:province":"Th\u00fcringen",
    "wof:name":"Silvia Bernhart",
    "wof:placetype":"venue"
},
  "geometry": {"coordinates":[10.4746770859,50.7203521729],"type":"Point"}
}