{
  "type": "Feature",
  "properties": {
    "iso:country":"DE",
    "sg:address":"Bitscher Str. 86",
    "sg:city":"Pirmasens",
    "sg:phone":"+49 6331/24740",
    "sg:postcode":"66955",
    "sg:province":"Rheinland-Pfalz",
    "wof:name":"Rolf Gl\u00f6ckner",
    "wof:placetype":"venue"
},
  "geometry": {"coordinates":[7.6098418236,49.1906471252],"type":"Point"}
}