{
  "type": "Feature",
  "properties": {
    "iso:country":"DE",
    "sg:address":"Weinstr. 7",
    "sg:city":"Sulzburg",
    "sg:phone":"+49 7634/8014",
    "sg:postcode":"79295",
    "sg:province":"Baden-W\u00fcrttemberg",
    "wof:name":"Restaurant La Vigna",
    "wof:placetype":"venue"
},
  "geometry": {"coordinates":[7.6841139793,47.8422737122],"type":"Point"}
}