{
  "type": "Feature",
  "properties": {
    "iso:country":"DE",
    "sg:address":"Winnender Str. 24",
    "sg:city":"Backnang",
    "sg:phone":"+49 7191/61061",
    "sg:postcode":"71522",
    "sg:province":"Baden-W\u00fcrttemberg",
    "wof:name":"Merchandiser Factory Gmbh",
    "wof:placetype":"venue"
},
  "geometry": {"coordinates":[9.4434700012,48.9349517822],"type":"Point"}
}