{
  "type": "Feature",
  "properties": {
    "iso:country":"DE",
    "sg:address":"Schneewittchenweg 12",
    "sg:city":"D\u00fcsseldorf",
    "sg:phone":"+49 211/236780",
    "sg:postcode":"40235",
    "sg:province":"Nordrhein-Westfalen",
    "wof:name":"Jutta Krzikalla",
    "wof:placetype":"venue"
},
  "geometry": {"coordinates":[6.831841,51.228558],"type":"Point"}
}