{
  "type": "Feature",
  "properties": {
    "iso:country":"DE",
    "sg:address":"Heinsestr. 32-36",
    "sg:city":"Berlin",
    "sg:phone":"+49 30/4042224",
    "sg:postcode":"13467",
    "sg:province":"Berlin",
    "wof:name":"Brillenb\u00e4r K\u00fcbler Ohg",
    "wof:placetype":"venue"
},
  "geometry": {"coordinates":[13.307195,52.616867],"type":"Point"}
}