{
  "type": "Feature",
  "properties": {
    "iso:country":"DE",
    "sg:address":"Wilhelm-Staab-Str. 8",
    "sg:city":"Potsdam",
    "sg:phone":"+49 331/291879",
    "sg:postcode":"14467",
    "sg:province":"Brandenburg",
    "wof:name":"Christian B\u00e4umer",
    "wof:placetype":"venue"
},
  "geometry": {"coordinates":[13.055815,52.398327],"type":"Point"}
}