{
  "type": "Feature",
  "properties": {
    "iso:country":"DE",
    "sg:address":"Gr\u00e4fensteinstr. 3 b",
    "sg:city":"Hagenbach",
    "sg:phone":"+49 7273/1006",
    "sg:postcode":"76767",
    "sg:province":"Rheinland-Pfalz",
    "wof:name":"Transexpress Transport Gmbh",
    "wof:placetype":"venue"
},
  "geometry": {"coordinates":[8.2474765778,49.0242996216],"type":"Point"}
}