{
  "type": "Feature",
  "properties": {
    "iso:country":"DE",
    "sg:address":"Hauptstr. 30a",
    "sg:city":"Sauensiek",
    "sg:phone":"+49 4169/413",
    "sg:postcode":"21644",
    "sg:province":"Niedersachsen",
    "wof:name":"Rolf Gru\u00dfendorf",
    "wof:placetype":"venue"
},
  "geometry": {"coordinates":[9.598273,53.383698],"type":"Point"}
}