{
  "type": "Feature",
  "properties": {
    "iso:country":"DE",
    "sg:address":"Zum Eckernbaum 28",
    "sg:city":"Adenau",
    "sg:postcode":"53518",
    "sg:province":"Rheinland-Pfalz",
    "wof:name":"Usinger Dienstleistungs Gmbh",
    "wof:placetype":"venue"
},
  "geometry": {"coordinates":[6.936121,50.379696],"type":"Point"}
}