{
  "type": "Feature",
  "properties": {
    "iso:country":"DE",
    "sg:address":"Sonnenstr. 10",
    "sg:city":"Holzg\u00fcnz",
    "sg:phone":"+49 8393/268",
    "sg:postcode":"87752",
    "sg:province":"Bayern",
    "wof:name":"Josef Kraus",
    "wof:placetype":"venue"
},
  "geometry": {"coordinates":[10.243905,48.015362],"type":"Point"}
}