{
  "type": "Feature",
  "properties": {
    "iso:country":"DE",
    "sg:address":"Pariser Str. 61",
    "sg:city":"Kaiserslautern",
    "sg:phone":"+49 631/23129",
    "sg:postcode":"67655",
    "sg:province":"Rheinland-Pfalz",
    "wof:name":"Birgit Platz",
    "wof:placetype":"venue"
},
  "geometry": {"coordinates":[7.757595,49.443459],"type":"Point"}
}