{
  "type": "Feature",
  "properties": {
    "iso:country":"DE",
    "sg:address":"Bremer Str. 40",
    "sg:city":"Delmenhorst",
    "sg:phone":"+49 4221/18916",
    "sg:postcode":"27749",
    "sg:province":"Niedersachsen",
    "wof:name":"Johannes Mittag Herstellung Gro\u00dfhandel Und",
    "wof:placetype":"venue"
},
  "geometry": {"coordinates":[8.641119957,53.0524711609],"type":"Point"}
}