{
  "type": "Feature",
  "properties": {
    "iso:country":"DE",
    "sg:address":"Alte Celler Heerstr. 27",
    "sg:city":"Winsen",
    "sg:phone":"+49 5143/6266",
    "sg:postcode":"29308",
    "sg:province":"Niedersachsen",
    "wof:name":"Heinz-wilhelm Dierksen",
    "wof:placetype":"venue"
},
  "geometry": {"coordinates":[9.91617,52.682446],"type":"Point"}
}