{
  "type": "Feature",
  "properties": {
    "iso:country":"DE",
    "sg:address":"Rh\u00f6nstr. 8",
    "sg:city":"Wuppertal",
    "sg:phone":"+49 202/401481",
    "sg:postcode":"42349",
    "sg:province":"Nordrhein-Westfalen",
    "wof:name":"Gebr. Fleuss Inh. Ernst Fleuss",
    "wof:placetype":"venue"
},
  "geometry": {"coordinates":[7.1341090202,51.2298545837],"type":"Point"}
}