{
  "type": "Feature",
  "properties": {
    "iso:country":"DE",
    "sg:address":"Amlayerhof 14",
    "sg:city":"Mayen",
    "sg:phone":"+49 4926/5180010",
    "sg:postcode":"56727",
    "sg:province":"Rheinland-Pfalz",
    "wof:name":"Bikoma Ag Spezielmaschinen",
    "wof:placetype":"venue"
},
  "geometry": {"coordinates":[7.242064,50.332001],"type":"Point"}
}