{
  "type": "Feature",
  "properties": {
    "iso:country":"DE",
    "sg:address":"Fettpottstr. 32",
    "sg:city":"Leopoldsh\u00f6he",
    "sg:phone":"+49 5202/1071",
    "sg:postcode":"33818",
    "sg:province":"Nordrhein-Westfalen",
    "wof:name":"Begemanns Mietlift Gmbh",
    "wof:placetype":"venue"
},
  "geometry": {"coordinates":[8.7087593079,51.9832000732],"type":"Point"}
}