{
  "type": "Feature",
  "properties": {
    "iso:country":"DE",
    "sg:address":"Wiesenweg 9",
    "sg:city":"Steinbach-Hallenberg",
    "sg:phone":"+49 36847/30280",
    "sg:postcode":"98587",
    "sg:province":"Th\u00fcringen",
    "wof:name":"W. Prei\u00df",
    "wof:placetype":"venue"
},
  "geometry": {"coordinates":[10.556584,50.679813],"type":"Point"}
}