{
  "type": "Feature",
  "properties": {
    "iso:country":"DE",
    "sg:address":"Frankfurter Str. 27",
    "sg:city":"Heusenstamm",
    "sg:phone":"+49 6104/63695",
    "sg:postcode":"63150",
    "sg:province":"Hessen",
    "wof:name":"Sch\u00f6nert Optik Gmbh",
    "wof:placetype":"venue"
},
  "geometry": {"coordinates":[8.80633,50.059414],"type":"Point"}
}