{
  "type": "Feature",
  "properties": {
    "iso:country":"DE",
    "sg:address":"Langhansstr. 127",
    "sg:city":"Berlin",
    "sg:phone":"+49 30/9254411",
    "sg:postcode":"13086",
    "sg:province":"Berlin",
    "wof:name":"Froitzheim & Rudert Gmbh",
    "wof:placetype":"venue"
},
  "geometry": {"coordinates":[13.4438829422,52.5505828857],"type":"Point"}
}