{
  "type": "Feature",
  "properties": {
    "iso:country":"DE",
    "sg:address":"Siemensstr. 6",
    "sg:city":"L\u00fcbbecke",
    "sg:phone":"+49 5741/40254",
    "sg:postcode":"32312",
    "sg:province":"Nordrhein-Westfalen",
    "wof:name":"G\u00fcnter Grote Gmbh",
    "wof:placetype":"venue"
},
  "geometry": {"coordinates":[8.62840271,52.3243865967],"type":"Point"}
}