{
  "type": "Feature",
  "properties": {
    "iso:country":"DE",
    "sg:address":"Waldfriedhofstr. 68",
    "sg:city":"M\u00fcnchen",
    "sg:phone":"+49 89/7149551",
    "sg:postcode":"81377",
    "sg:province":"Bayern",
    "wof:name":"Horst G\u00fcnter Probst Gmbh",
    "wof:placetype":"venue"
},
  "geometry": {"coordinates":[11.5075483322,48.1126747131],"type":"Point"}
}