{
  "type": "Feature",
  "properties": {
    "iso:country":"DE",
    "sg:address":"D\u00fcnnwalder Grenzweg a",
    "sg:city":"Leverkusen",
    "sg:postcode":"51375",
    "sg:province":"Nordrhein-Westfalen",
    "wof:name":"Erotikbilder,dessous,nacktfotos Mit Niveau",
    "wof:placetype":"venue"
},
  "geometry": {"coordinates":[7.041635,51.021015],"type":"Point"}
}