{
  "type": "Feature",
  "properties": {
    "iso:country":"DE",
    "sg:address":"Im Sande 1",
    "sg:city":"S\u00f6gel",
    "sg:phone":"+49 5952/1081",
    "sg:postcode":"49751",
    "sg:province":"Niedersachsen",
    "wof:name":"M\u00f6bel Kleymann Gmbh",
    "wof:placetype":"venue"
},
  "geometry": {"coordinates":[7.506858,52.830948],"type":"Point"}
}