{
  "type": "Feature",
  "properties": {
    "iso:country":"DE",
    "sg:address":"Battenberger Str. 32-32b",
    "sg:city":"Frankenberg",
    "sg:phone":"+49 6451/1542",
    "sg:postcode":"35066",
    "sg:province":"Hessen",
    "wof:name":"Bauunternehmen Hess Gmbh",
    "wof:placetype":"venue"
},
  "geometry": {"coordinates":[8.74707,51.044971],"type":"Point"}
}