{
  "type": "Feature",
  "properties": {
    "iso:country":"DE",
    "sg:address":"Lloydstr. 13",
    "sg:city":"Bremerv\u00f6rde",
    "sg:phone":"+49 4761/1289",
    "sg:postcode":"27432",
    "sg:province":"Niedersachsen",
    "wof:name":"J. M. Dammann",
    "wof:placetype":"venue"
},
  "geometry": {"coordinates":[9.115812,53.49081],"type":"Point"}
}