{
  "type": "Feature",
  "properties": {
    "iso:country":"DE",
    "sg:address":"Pointstr. 2",
    "sg:city":"Strullendorf",
    "sg:phone":"+49 9543/4490",
    "sg:postcode":"96129",
    "sg:province":"Bayern",
    "wof:name":"Steba Elektroger\u00c4te Gmbh & Co Kg",
    "wof:placetype":"venue"
},
  "geometry": {"coordinates":[10.960026,49.844818],"type":"Point"}
}