{
  "type": "Feature",
  "properties": {
    "iso:country":"DE",
    "sg:address":"S\u00fcdring 8",
    "sg:city":"Coesfeld",
    "sg:phone":"+49 2541/72984",
    "sg:postcode":"48653",
    "sg:province":"Nordrhein-Westfalen",
    "wof:name":"Paul Joachim M\u00fcller Architekt",
    "wof:placetype":"venue"
},
  "geometry": {"coordinates":[7.168371,51.942257],"type":"Point"}
}