{
  "type": "Feature",
  "properties": {
    "iso:country":"DE",
    "sg:address":"Erftweg 48",
    "sg:city":"Bielefeld",
    "sg:phone":"+49 5205/5316",
    "sg:postcode":"33689",
    "sg:province":"Nordrhein-Westfalen",
    "wof:name":"G. China",
    "wof:placetype":"venue"
},
  "geometry": {"coordinates":[8.587388,51.95731],"type":"Point"}
}