{
  "type": "Feature",
  "properties": {
    "iso:country":"DE",
    "sg:address":"Verbindungsweg 17",
    "sg:city":"Eichst\u00e4dt",
    "sg:phone":"+49 3304/501744",
    "sg:postcode":"16727",
    "sg:province":"Brandenburg",
    "wof:name":"Schlemmer-rolle Fleisch- Und Wurstwarenhandels Gmbh",
    "wof:placetype":"venue"
},
  "geometry": {"coordinates":[13.1176300049,52.695438385],"type":"Point"}
}