{
  "type": "Feature",
  "properties": {
    "iso:country":"DE",
    "sg:address":"Haidelweg 22c",
    "sg:city":"M\u00fcnchen",
    "sg:phone":"+49 89/885284",
    "sg:postcode":"81241",
    "sg:province":"Bayern",
    "wof:name":"Casinogesellschaft Heinz Wilhelm Schoof Ohg",
    "wof:placetype":"venue"
},
  "geometry": {"coordinates":[11.4567012787,48.1365814209],"type":"Point"}
}