{
  "type": "Feature",
  "properties": {
    "iso:country":"DE",
    "sg:address":"Landsberger Str. 392",
    "sg:city":"M\u00fcnchen",
    "sg:phone":"+49 89/566060",
    "sg:postcode":"81241",
    "sg:province":"Bayern",
    "wof:name":"Handy World",
    "wof:placetype":"venue"
},
  "geometry": {"coordinates":[11.4842271805,48.145072937],"type":"Point"}
}