{
  "type": "Feature",
  "properties": {
    "iso:country":"DE",
    "sg:address":"Gringsstr. 2",
    "sg:city":"Bonn",
    "sg:phone":"+49 228/330317",
    "sg:postcode":"53177",
    "sg:province":"Nordrhein-Westfalen",
    "wof:name":"Richard Folwaczny",
    "wof:placetype":"venue"
},
  "geometry": {"coordinates":[7.160033,50.672218],"type":"Point"}
}