{
  "type": "Feature",
  "properties": {
    "iso:country":"DE",
    "sg:address":"Struppener Str.",
    "sg:city":"Pirna",
    "sg:phone":"+49 3501/784946",
    "sg:postcode":"01796",
    "sg:province":"Sachsen",
    "wof:name":"Fotopoint Im Kaufland",
    "wof:placetype":"venue"
},
  "geometry": {"coordinates":[13.9558200836,50.9567184448],"type":"Point"}
}