{
  "type": "Feature",
  "properties": {
    "iso:country":"DE",
    "sg:address":"Walder Str. 90",
    "sg:city":"Hilden",
    "sg:phone":"+49 2103/88983",
    "sg:postcode":"40724",
    "sg:province":"Nordrhein-Westfalen",
    "wof:name":"Siegfried Laube Architekt",
    "wof:placetype":"venue"
},
  "geometry": {"coordinates":[6.9505,51.168064],"type":"Point"}
}