{
  "type": "Feature",
  "properties": {
    "iso:country":"DE",
    "sg:address":"L\u00f6bauer Str. 8",
    "sg:city":"Bautzen",
    "sg:phone":"+49 3591/42430",
    "sg:postcode":"02625",
    "sg:province":"Sachsen",
    "wof:name":"Hr Steinmetz Bautzen Gmbh",
    "wof:placetype":"venue"
},
  "geometry": {"coordinates":[14.4367713928,51.180934906],"type":"Point"}
}