{
  "type": "Feature",
  "properties": {
    "iso:country":"DE",
    "sg:address":"Poststr. 19",
    "sg:city":"Mettmann",
    "sg:phone":"+49 2104/22907",
    "sg:postcode":"40822",
    "sg:province":"Nordrhein-Westfalen",
    "wof:name":"K.-h. Daum",
    "wof:placetype":"venue"
},
  "geometry": {"coordinates":[6.9809279442,51.2508659363],"type":"Point"}
}