{
  "type": "Feature",
  "properties": {
    "iso:country":"DE",
    "sg:address":"Spenglerstr. 6",
    "sg:city":"Hamm",
    "sg:phone":"+49 2381/41548",
    "sg:postcode":"59067",
    "sg:province":"Nordrhein-Westfalen",
    "wof:name":"Eickhoff",
    "wof:placetype":"venue"
},
  "geometry": {"coordinates":[7.7678661346,51.6667671204],"type":"Point"}
}