{
  "type": "Feature",
  "properties": {
    "iso:country":"DE",
    "sg:address":"Hauptstr. 61",
    "sg:city":"Offenburg",
    "sg:postcode":"77652",
    "sg:province":"Baden-W\u00fcrttemberg",
    "wof:name":"Zampolli Grundst\u00fccks- Verwaltung- Und",
    "wof:placetype":"venue"
},
  "geometry": {"coordinates":[7.9431219101,48.4701728821],"type":"Point"}
}