{
  "type": "Feature",
  "properties": {
    "iso:country":"DE",
    "sg:address":"Universit\u00e4tsstr. 10",
    "sg:city":"Konstanz",
    "sg:postcode":"78464",
    "sg:province":"Baden-W\u00fcrttemberg",
    "wof:name":"Arbeitsgruppe Physiologische Chemie",
    "wof:placetype":"venue"
},
  "geometry": {"coordinates":[9.1864185333,47.6898956299],"type":"Point"}
}