{
  "type": "Feature",
  "properties": {
    "iso:country":"DE",
    "sg:address":"Kirchhecke 2",
    "sg:city":"Newel",
    "sg:phone":"+49 6505/8681",
    "sg:postcode":"54309",
    "sg:province":"Rheinland-Pfalz",
    "wof:name":"Manfred M\u00fcller Architekt",
    "wof:placetype":"venue"
},
  "geometry": {"coordinates":[6.618327,49.814655],"type":"Point"}
}