{
  "type": "Feature",
  "properties": {
    "iso:country":"DE",
    "sg:address":"Quellendorfer Str. 5",
    "sg:city":"K\u00f6then",
    "sg:phone":"+49 3496/40360",
    "sg:postcode":"06366",
    "sg:province":"Sachsen-Anhalt",
    "wof:name":"Hagebau Centrum K\u00f6then Gmbh & Co. Kg",
    "wof:placetype":"venue"
},
  "geometry": {"coordinates":[11.999977,51.746773],"type":"Point"}
}