{
  "type": "Feature",
  "properties": {
    "iso:country":"DE",
    "sg:address":"Ebersbrunner Str. 11",
    "sg:city":"Sch\u00f6nfels",
    "sg:phone":"+49 37600/2042",
    "sg:postcode":"08115",
    "sg:province":"Sachsen",
    "wof:name":"Gerhard L\u00f6ffler",
    "wof:placetype":"venue"
},
  "geometry": {"coordinates":[12.405965,50.673981],"type":"Point"}
}