{
  "type": "Feature",
  "properties": {
    "iso:country":"DE",
    "sg:address":"J\u00fcngststr. 6",
    "sg:city":"Bielefeld",
    "sg:phone":"+49 521/176050",
    "sg:postcode":"33602",
    "sg:province":"Nordrhein-Westfalen",
    "wof:name":"Fischer & Co. Vermietung Und Verpackung",
    "wof:placetype":"venue"
},
  "geometry": {"coordinates":[8.5356416702,52.0156784058],"type":"Point"}
}