{
  "type": "Feature",
  "properties": {
    "iso:country":"DE",
    "sg:address":"Ganghoferstr. 4",
    "sg:city":"Bad W\u00f6rishofen",
    "sg:phone":"+49 8247/6593",
    "sg:postcode":"86825",
    "sg:province":"Bayern",
    "wof:name":"M. Lederer",
    "wof:placetype":"venue"
},
  "geometry": {"coordinates":[10.6000871658,48.0021858215],"type":"Point"}
}