{
  "type": "Feature",
  "properties": {
    "iso:country":"DE",
    "sg:address":"Marburger Str. 112",
    "sg:city":"Gie\u00dfen",
    "sg:phone":"+49 641/33747",
    "sg:postcode":"35396",
    "sg:province":"Hessen",
    "wof:name":"Kings Club",
    "wof:placetype":"venue"
},
  "geometry": {"coordinates":[8.685442,50.598633],"type":"Point"}
}