{
  "type": "Feature",
  "properties": {
    "iso:country":"DE",
    "sg:address":"Am G\u00fcterbahnhof",
    "sg:city":"L\u00fcbben",
    "sg:phone":"+49 3546/7393",
    "sg:postcode":"15907",
    "sg:province":"Brandenburg",
    "wof:name":"Heinrich & H\u00f6rning Gmbh",
    "wof:placetype":"venue"
},
  "geometry": {"coordinates":[13.8778095245,51.9385986328],"type":"Point"}
}