{
  "type": "Feature",
  "properties": {
    "iso:country":"DE",
    "sg:address":"Rosenheimer Str. 65",
    "sg:city":"Bad Aibling",
    "sg:phone":"+49 8061/30953",
    "sg:postcode":"83043",
    "sg:province":"Bayern",
    "wof:name":"R. Weber Und M. Drescher",
    "wof:placetype":"venue"
},
  "geometry": {"coordinates":[12.015785,47.856277],"type":"Point"}
}