{
  "type": "Feature",
  "properties": {
    "iso:country":"DE",
    "sg:address":"Dorfstr. 37",
    "sg:city":"Neu Kosenow",
    "sg:postcode":"17398",
    "sg:province":"Mecklenburg-Vorpommern",
    "wof:name":"Anklamer Fruchtmarkt Eg",
    "wof:placetype":"venue"
},
  "geometry": {"coordinates":[13.752958,53.792843],"type":"Point"}
}