{
  "type": "Feature",
  "properties": {
    "iso:country":"DE",
    "sg:address":"Florastr. 9",
    "sg:city":"Rees",
    "sg:phone":"+49 2851/1564",
    "sg:postcode":"46459",
    "sg:province":"Nordrhein-Westfalen",
    "wof:name":"Suchsland Und Becker Rechtsanw\u00e4lte",
    "wof:placetype":"venue"
},
  "geometry": {"coordinates":[6.3979067802,51.7624320984],"type":"Point"}
}