{
  "type": "Feature",
  "properties": {
    "iso:country":"DE",
    "sg:address":"Hauptstr. 47/1",
    "sg:city":"Hardthausen",
    "sg:phone":"+49 7139/1289",
    "sg:postcode":"74239",
    "sg:province":"Baden-W\u00fcrttemberg",
    "wof:name":"H. Endre\u00df",
    "wof:placetype":"venue"
},
  "geometry": {"coordinates":[9.3618917465,49.2394561768],"type":"Point"}
}