{
  "type": "Feature",
  "properties": {
    "iso:country":"DE",
    "sg:address":"Heideweg 18",
    "sg:city":"Hallenberg",
    "sg:phone":"+49 2984/8445",
    "sg:postcode":"59969",
    "sg:province":"Nordrhein-Westfalen",
    "wof:name":"Franz-j. Paffe Gmbh & Co. Kg",
    "wof:placetype":"venue"
},
  "geometry": {"coordinates":[8.6141195297,51.1127929688],"type":"Point"}
}