{
  "type": "Feature",
  "properties": {
    "iso:country":"DE",
    "sg:address":"Silberh\u00f6lle 45",
    "sg:city":"Bruchsal",
    "sg:phone":"+49 721/948680",
    "sg:postcode":"76646",
    "sg:province":"Baden-W\u00fcrttemberg",
    "wof:name":"Constanza Gmbh & Co. Kg",
    "wof:placetype":"venue"
},
  "geometry": {"coordinates":[8.595774,49.117512],"type":"Point"}
}