{
  "type": "Feature",
  "properties": {
    "iso:country":"DE",
    "sg:address":"Marktgasse 1",
    "sg:city":"T\u00fcbingen",
    "sg:phone":"+49 7071/252856",
    "sg:postcode":"72070",
    "sg:province":"Baden-W\u00fcrttemberg",
    "wof:name":"La Piazza E. K.",
    "wof:placetype":"venue"
},
  "geometry": {"coordinates":[9.0532569885,48.5206794739],"type":"Point"}
}