{
  "type": "Feature",
  "properties": {
    "iso:country":"DE",
    "sg:address":"F\u00f6rderstedter Str. 6 b",
    "sg:city":"Sta\u00dffurt",
    "sg:postcode":"39418",
    "sg:province":"Sachsen-Anhalt",
    "wof:name":"Adam Villa Revitalisierungs Gmbh",
    "wof:placetype":"venue"
},
  "geometry": {"coordinates":[11.5992250443,51.8649482727],"type":"Point"}
}