{
  "type": "Feature",
  "properties": {
    "iso:country":"DE",
    "sg:address":"jahnstrassse 21",
    "sg:city":"warstein",
    "sg:postcode":"58581",
    "sg:province":"Nordrhein-Westfalen",
    "wof:name":"Deutsche Kultur Der Region Altai In Russland",
    "wof:placetype":"venue"
},
  "geometry": {"coordinates":[-99.775726,46.04995],"type":"Point"}
}