{
  "type": "Feature",
  "properties": {
    "iso:country":"DE",
    "sg:address":"Akazienstr. 15",
    "sg:city":"Gelsenkirchen",
    "sg:phone":"+49 209/32272",
    "sg:postcode":"45894",
    "sg:province":"Nordrhein-Westfalen",
    "wof:name":"Gemeinn. Bau- Und Sparverein Eigenheim Eg",
    "wof:placetype":"venue"
},
  "geometry": {"coordinates":[7.0546998978,51.5831604004],"type":"Point"}
}