{
  "type": "Feature",
  "properties": {
    "iso:country":"DE",
    "sg:address":"Geiersgraben 6",
    "sg:city":"Gem\u00fcnden",
    "sg:phone":"+49 9354/1030",
    "sg:postcode":"97737",
    "sg:province":"Bayern",
    "wof:name":"Karl-heinz Joekel",
    "wof:placetype":"venue"
},
  "geometry": {"coordinates":[9.6638860703,50.0817871094],"type":"Point"}
}