{
  "type": "Feature",
  "properties": {
    "iso:country":"DE",
    "sg:address":"Lingener Str. 20",
    "sg:city":"Meppen",
    "sg:phone":"+49 5931/98160",
    "sg:postcode":"49716",
    "sg:province":"Niedersachsen",
    "wof:name":"Hellmich Ahlers Und Ahrens Rechtsanw\u00e4lte Und Notare",
    "wof:placetype":"venue"
},
  "geometry": {"coordinates":[7.2910838127,52.6865768433],"type":"Point"}
}