{
  "type": "Feature",
  "properties": {
    "iso:country":"DE",
    "sg:address":"Hechinger Str. 49",
    "sg:city":"Hirrlingen",
    "sg:phone":"+49 7478/497",
    "sg:postcode":"72145",
    "sg:province":"Baden-W\u00fcrttemberg",
    "wof:name":"Bernhard Stumpp",
    "wof:placetype":"venue"
},
  "geometry": {"coordinates":[8.8837490082,48.4053573608],"type":"Point"}
}