{
  "type": "Feature",
  "properties": {
    "iso:country":"DE",
    "sg:address":"Albachtstr. 2",
    "sg:city":"Greven",
    "sg:phone":"+49 2571/6738",
    "sg:postcode":"48268",
    "sg:province":"Nordrhein-Westfalen",
    "wof:name":"G. Mennemann",
    "wof:placetype":"venue"
},
  "geometry": {"coordinates":[7.6171197891,52.0922813416],"type":"Point"}
}