{
  "type": "Feature",
  "properties": {
    "iso:country":"DE",
    "sg:address":"Buchenb\u00fchler Weg 44",
    "sg:city":"N\u00fcrnberg",
    "sg:phone":"+49 911/522348",
    "sg:postcode":"90411",
    "sg:province":"Bayern",
    "wof:name":"Sportgastst\u00e4tte Hgn",
    "wof:placetype":"venue"
},
  "geometry": {"coordinates":[11.1160058975,49.4939155579],"type":"Point"}
}