{
  "type": "Feature",
  "properties": {
    "iso:country":"DE",
    "sg:address":"Krambergweg 4",
    "sg:city":"Helmstadt",
    "sg:phone":"+49 9369/90760",
    "sg:postcode":"97264",
    "sg:province":"Bayern",
    "wof:name":"Lux Fenster Und T\u00fcren Gmbh",
    "wof:placetype":"venue"
},
  "geometry": {"coordinates":[9.711482,49.759392],"type":"Point"}
}