{
  "type": "Feature",
  "properties": {
    "iso:country":"DE",
    "sg:address":"Ploon 10",
    "sg:city":"Bornheim",
    "sg:phone":"+49 2222/1526",
    "sg:postcode":"53332",
    "sg:province":"Nordrhein-Westfalen",
    "wof:name":"Hubertusklausee",
    "wof:placetype":"venue"
},
  "geometry": {"coordinates":[6.9728498459,50.7555084229],"type":"Point"}
}