{
  "type": "Feature",
  "properties": {
    "iso:country":"DE",
    "sg:address":"Saarburger Ring 38",
    "sg:city":"Mannheim",
    "sg:phone":"+49 621/476461",
    "sg:postcode":"68229",
    "sg:province":"Baden-W\u00fcrttemberg",
    "wof:name":"Lat Strecken- Und Gleisbau Gmbh",
    "wof:placetype":"venue"
},
  "geometry": {"coordinates":[8.570372,49.4426],"type":"Point"}
}