{
  "type": "Feature",
  "properties": {
    "iso:country":"DE",
    "sg:address":"Auf dem Kamp 20",
    "sg:city":"Witten",
    "sg:phone":"+49 2302/55428",
    "sg:postcode":"58455",
    "sg:province":"Nordrhein-Westfalen",
    "wof:name":"Malereibetrieb Lothar Ferber Inh. J\u00f6rg Dobrunz",
    "wof:placetype":"venue"
},
  "geometry": {"coordinates":[7.3365268707,51.4522743225],"type":"Point"}
}