{
  "type": "Feature",
  "properties": {
    "iso:country":"DE",
    "sg:address":"Br\u00fcckenstr. 5",
    "sg:city":"Wehringen",
    "sg:phone":"+49 8234/2443",
    "sg:postcode":"86517",
    "sg:province":"Bayern",
    "wof:name":"Ulrich Egger",
    "wof:placetype":"venue"
},
  "geometry": {"coordinates":[10.799986,48.246696],"type":"Point"}
}