{
  "type": "Feature",
  "properties": {
    "iso:country":"DE",
    "sg:address":"54669",
    "sg:city":"Bollendorf",
    "sg:phone":"+49 6526/234",
    "sg:postcode":"54669",
    "sg:province":"Rheinland-Pfalz",
    "wof:name":"Hotel Zur Post",
    "wof:placetype":"venue"
},
  "geometry": {"coordinates":[6.3587698936,49.8513336182],"type":"Point"}
}