{
  "type": "Feature",
  "properties": {
    "iso:country":"DE",
    "sg:address":"Friedhofsweg 11",
    "sg:city":"Ennepetal",
    "sg:phone":"+49 2333/2977",
    "sg:postcode":"58256",
    "sg:province":"Nordrhein-Westfalen",
    "wof:name":"Ev. Pfarramt Ennepetal-voerde",
    "wof:placetype":"venue"
},
  "geometry": {"coordinates":[7.3882079124,51.3075752258],"type":"Point"}
}