{
  "type": "Feature",
  "properties": {
    "iso:country":"DE",
    "sg:address":"Am Altenhof 26",
    "sg:city":"Ratingen",
    "sg:phone":"+49 2102/67820",
    "sg:postcode":"40883",
    "sg:province":"Nordrhein-Westfalen",
    "wof:name":"B. Wagener",
    "wof:placetype":"venue"
},
  "geometry": {"coordinates":[6.907556057,51.3325996399],"type":"Point"}
}