{
  "type": "Feature",
  "properties": {
    "iso:country":"DE",
    "sg:address":"Oberdorfstr. 15",
    "sg:city":"Bruchk\u00f6bel",
    "sg:phone":"+49 6181/72252",
    "sg:postcode":"63486",
    "sg:province":"Hessen",
    "wof:name":"Heinrich Vulpius",
    "wof:placetype":"venue"
},
  "geometry": {"coordinates":[8.908577,50.198757],"type":"Point"}
}