{
  "type": "Feature",
  "properties": {
    "iso:country":"DE",
    "sg:address":"Landesstr. 22 a",
    "sg:city":"Nordstemmen",
    "sg:phone":"+49 5066/7889",
    "sg:postcode":"31171",
    "sg:province":"Niedersachsen",
    "wof:name":"Erich Putzer",
    "wof:placetype":"venue"
},
  "geometry": {"coordinates":[9.816308,52.201366],"type":"Point"}
}