{
  "type": "Feature",
  "properties": {
    "iso:country":"DE",
    "sg:address":"Brucknerstr. 4",
    "sg:city":"Rees",
    "sg:phone":"+49 2850/7317",
    "sg:postcode":"46459",
    "sg:province":"Nordrhein-Westfalen",
    "wof:name":"Paul Simmes",
    "wof:placetype":"venue"
},
  "geometry": {"coordinates":[6.465218,51.770321],"type":"Point"}
}