{
  "type": "Feature",
  "properties": {
    "iso:country":"DE",
    "sg:address":"Corinthstr. 4",
    "sg:city":"Dresden",
    "sg:postcode":"01219",
    "sg:province":"Sachsen",
    "wof:name":"Stadbibliothek S\u00fcd Zweigbibliothek Strehlen",
    "wof:placetype":"venue"
},
  "geometry": {"coordinates":[13.763642,51.021111],"type":"Point"}
}