{
  "type": "Feature",
  "properties": {
    "iso:country":"DE",
    "sg:address":"Herzogstr. 35",
    "sg:city":"Grevenbroich",
    "sg:phone":"+49 2182/60669",
    "sg:postcode":"41516",
    "sg:province":"Nordrhein-Westfalen",
    "wof:name":"W. Strauch",
    "wof:placetype":"venue"
},
  "geometry": {"coordinates":[6.6641640663,51.1223754883],"type":"Point"}
}