{
  "type": "Feature",
  "properties": {
    "iso:country":"DE",
    "sg:address":"Brettener Str. 8",
    "sg:city":"Kraichtal",
    "sg:phone":"+49 7250/454",
    "sg:postcode":"76703",
    "sg:province":"Baden-W\u00fcrttemberg",
    "wof:name":"M. Pfeiffer",
    "wof:placetype":"venue"
},
  "geometry": {"coordinates":[8.713338,49.107094],"type":"Point"}
}