{
  "type": "Feature",
  "properties": {
    "iso:country":"DE",
    "sg:address":"Zollhausstr. 40",
    "sg:city":"Iserlohn",
    "sg:phone":"+49 2371/43450",
    "sg:postcode":"58640",
    "sg:province":"Nordrhein-Westfalen",
    "wof:name":"Peter Klauke Verwaltungsges. Mbh",
    "wof:placetype":"venue"
},
  "geometry": {"coordinates":[7.6809,51.421749],"type":"Point"}
}