{
  "type": "Feature",
  "properties": {
    "iso:country":"DE",
    "sg:address":"Hauptstr. 39",
    "sg:city":"Reinsberg",
    "sg:phone":"+49 37324/7349",
    "sg:postcode":"09629",
    "sg:province":"Sachsen",
    "wof:name":"W. Rost",
    "wof:placetype":"venue"
},
  "geometry": {"coordinates":[13.3718738556,51.0074806213],"type":"Point"}
}