{
  "type": "Feature",
  "properties": {
    "iso:country":"DE",
    "sg:address":"Seibersdorf 46",
    "sg:city":"Hohenwart",
    "sg:phone":"+49 8443/251",
    "sg:postcode":"86558",
    "sg:province":"Bayern",
    "wof:name":"Gasthaus Ludwig Schr\u00f6dl",
    "wof:placetype":"venue"
},
  "geometry": {"coordinates":[11.4007663727,48.5705757141],"type":"Point"}
}