{
  "type": "Feature",
  "properties": {
    "iso:country":"DE",
    "sg:address":"Jahnstr. 2",
    "sg:city":"Bietigheim-Bissingen",
    "sg:phone":"+49 7142/33755",
    "sg:postcode":"74321",
    "sg:province":"Baden-W\u00fcrttemberg",
    "wof:name":"Rings Ingenieur",
    "wof:placetype":"venue"
},
  "geometry": {"coordinates":[9.0989379883,48.9471473694],"type":"Point"}
}