{
  "type": "Feature",
  "properties": {
    "iso:country":"DE",
    "sg:address":"Clausthaler Str. 36",
    "sg:city":"Bad Grund",
    "sg:phone":"+49 5327/1216",
    "sg:postcode":"37539",
    "sg:province":"Niedersachsen",
    "wof:name":"Willi Rotte",
    "wof:placetype":"venue"
},
  "geometry": {"coordinates":[10.239278,51.809978],"type":"Point"}
}