{
  "type": "Feature",
  "properties": {
    "iso:country":"DE",
    "sg:address":"Am Ballplatz 10-16",
    "sg:city":"Hanau",
    "sg:phone":"+49 6181/22255",
    "sg:postcode":"63450",
    "sg:province":"Hessen",
    "wof:name":"Mollie-moden Textilhandel B\u00f6rner-appel Gmbh",
    "wof:placetype":"venue"
},
  "geometry": {"coordinates":[8.920734,50.131748],"type":"Point"}
}