{
  "type": "Feature",
  "properties": {
    "iso:country":"DE",
    "sg:address":"Karl-Halbig-Str. 2",
    "sg:city":"Gr\u00e4fenhain",
    "sg:phone":"+49 3624/402697",
    "sg:postcode":"99887",
    "sg:province":"Th\u00fcringen",
    "wof:name":"Gastst\u00e4tte Th\u00fcringer Wald",
    "wof:placetype":"venue"
},
  "geometry": {"coordinates":[10.7029104233,50.8195304871],"type":"Point"}
}