{
  "type": "Feature",
  "properties": {
    "iso:country":"DE",
    "sg:address":"Apothekerstr. 11",
    "sg:city":"Illertissen",
    "sg:phone":"+49 7303/7107",
    "sg:postcode":"89257",
    "sg:province":"Bayern",
    "wof:name":"Franz Hummel",
    "wof:placetype":"venue"
},
  "geometry": {"coordinates":[10.104056,48.220955],"type":"Point"}
}