{
  "type": "Feature",
  "properties": {
    "iso:country":"DE",
    "sg:address":"Schlauditz 1",
    "sg:city":"Monstab",
    "sg:phone":"+49 34498/40905",
    "sg:postcode":"04617",
    "sg:province":"Th\u00fcringen",
    "wof:name":"Josef Hrdina",
    "wof:placetype":"venue"
},
  "geometry": {"coordinates":[12.359747,50.985779],"type":"Point"}
}