{
  "type": "Feature",
  "properties": {
    "iso:country":"DE",
    "sg:address":"Attilastr. 5",
    "sg:city":"Gro\u00dfziethen",
    "sg:phone":"+49 3379/449231",
    "sg:postcode":"15831",
    "sg:province":"Brandenburg",
    "wof:name":"Kotthaus Immobilien Verwaltungsgesellschaft Mbh",
    "wof:placetype":"venue"
},
  "geometry": {"coordinates":[13.4403181076,52.4071922302],"type":"Point"}
}