{
  "type": "Feature",
  "properties": {
    "iso:country":"DE",
    "sg:address":"Z\u00fcttlinger Str. 27",
    "sg:city":"Stuttgart",
    "sg:phone":"+49 711/8489840",
    "sg:postcode":"70437",
    "sg:province":"Baden-W\u00fcrttemberg",
    "wof:name":"Hagen Jost Architekt",
    "wof:placetype":"venue"
},
  "geometry": {"coordinates":[9.199994,48.834789],"type":"Point"}
}