{
  "type": "Feature",
  "properties": {
    "iso:country":"DE",
    "sg:address":"Demianiplatz 28",
    "sg:city":"G\u00f6rlitz",
    "sg:phone":"+49 3581/405454",
    "sg:postcode":"02826",
    "sg:province":"Sachsen",
    "wof:name":"Neubauer Dental Handelsges. Mbh & Co.",
    "wof:placetype":"venue"
},
  "geometry": {"coordinates":[14.9854898453,51.1533050537],"type":"Point"}
}