{
  "type": "Feature",
  "properties": {
    "iso:country":"DE",
    "sg:address":"Rudolf-Diesel-Str. 7",
    "sg:city":"Uetze",
    "sg:phone":"+49 5173/6207",
    "sg:postcode":"31311",
    "sg:province":"Niedersachsen",
    "wof:name":"H. Kr\u00fcger",
    "wof:placetype":"venue"
},
  "geometry": {"coordinates":[10.22093,52.470886],"type":"Point"}
}