{
  "type": "Feature",
  "properties": {
    "iso:country":"DE",
    "sg:address":"Nienstedter Hauptstr. 3",
    "sg:city":"Despetal",
    "sg:phone":"+49 5065/9244",
    "sg:postcode":"31035",
    "sg:province":"Niedersachsen",
    "wof:name":"O. Ding Jun.",
    "wof:placetype":"venue"
},
  "geometry": {"coordinates":[9.8649988174,52.0769424438],"type":"Point"}
}