{
  "type": "Feature",
  "properties": {
    "iso:country":"DE",
    "sg:address":"Wiesseer Str. 8",
    "sg:city":"Gmund",
    "sg:phone":"+49 8022/74619",
    "sg:postcode":"83703",
    "sg:province":"Bayern",
    "wof:name":"Weinstube Gmunder Stubn",
    "wof:placetype":"venue"
},
  "geometry": {"coordinates":[11.735499382,47.7502822876],"type":"Point"}
}