{
  "type": "Feature",
  "properties": {
    "iso:country":"DE",
    "sg:address":"Am Buchschlag 3 Reute",
    "sg:city":"Meckenbeuren",
    "sg:phone":"+49 4975/4294290",
    "sg:postcode":"88074",
    "sg:province":"Baden-W\u00fcrttemberg",
    "wof:name":"Plattenhardt + Wirth Gmbh",
    "wof:placetype":"venue"
},
  "geometry": {"coordinates":[9.562686,47.699963],"type":"Point"}
}