{
  "type": "Feature",
  "properties": {
    "iso:country":"DE",
    "sg:address":"Kabelkamp 2",
    "sg:city":"Hannover",
    "sg:phone":"+49 511/674950",
    "sg:postcode":"30179",
    "sg:province":"Niedersachsen",
    "wof:name":"M\u00e4rtens Communication Verwaltungs Gmbh",
    "wof:placetype":"venue"
},
  "geometry": {"coordinates":[9.732775,52.412502],"type":"Point"}
}