{
  "type": "Feature",
  "properties": {
    "iso:country":"DE",
    "sg:address":"Industriestr. 7",
    "sg:city":"Mudersbach",
    "sg:phone":"+49 2745/930330",
    "sg:postcode":"57555",
    "sg:province":"Rheinland-Pfalz",
    "wof:name":"Proas Profilbearbeitung Antonius Solbach E. K.",
    "wof:placetype":"venue"
},
  "geometry": {"coordinates":[7.945852,50.822674],"type":"Point"}
}