{
  "type": "Feature",
  "properties": {
    "iso:country":"DE",
    "sg:address":"Metzgergasse 3",
    "sg:city":"Niddatal",
    "sg:phone":"+49 6034/930068",
    "sg:postcode":"61194",
    "sg:province":"Hessen",
    "wof:name":"Hanne Hirnickel",
    "wof:placetype":"venue"
},
  "geometry": {"coordinates":[8.813771,50.2995],"type":"Point"}
}