{
  "type": "Feature",
  "properties": {
    "iso:country":"DE",
    "sg:address":"Fahrstr. 1",
    "sg:city":"Trier",
    "sg:postcode":"54290",
    "sg:province":"Rheinland-Pfalz",
    "wof:name":"Das Tapfere Schneiderlein Angelika Hirschler E. Kfr.",
    "wof:placetype":"venue"
},
  "geometry": {"coordinates":[6.639225,49.753342],"type":"Point"}
}