{
  "type": "Feature",
  "properties": {
    "iso:country":"DE",
    "sg:address":"Hambrink 5",
    "sg:city":"Lotte",
    "sg:phone":"+49 5404/1361",
    "sg:postcode":"49504",
    "sg:province":"Nordrhein-Westfalen",
    "wof:name":"Pollo Industriesysteme",
    "wof:placetype":"venue"
},
  "geometry": {"coordinates":[7.918739,52.272984],"type":"Point"}
}