{
  "type": "Feature",
  "properties": {
    "iso:country":"DE",
    "sg:address":"Ersh\u00e4user Str. 4",
    "sg:city":"Geismar",
    "sg:phone":"+49 36082/470",
    "sg:postcode":"37308",
    "sg:province":"Th\u00fcringen",
    "wof:name":"Con-pearl Leichtplatten Gmbh",
    "wof:placetype":"venue"
},
  "geometry": {"coordinates":[10.1573600769,51.2363433838],"type":"Point"}
}