{
  "type": "Feature",
  "properties": {
    "iso:country":"DE",
    "sg:address":"Tizianstr. 3",
    "sg:city":"M\u00fcnchen",
    "sg:phone":"+49 89/152966",
    "sg:postcode":"80638",
    "sg:province":"Bayern",
    "wof:name":"Hansj\u00fcrg Triebel",
    "wof:placetype":"venue"
},
  "geometry": {"coordinates":[11.517513,48.159836],"type":"Point"}
}