{
  "type": "Feature",
  "properties": {
    "iso:country":"DE",
    "sg:address":"Hornissenweg 4",
    "sg:city":"Apen",
    "sg:phone":"+49 4489/5298",
    "sg:postcode":"26689",
    "sg:province":"Niedersachsen",
    "wof:name":"W. Mundt",
    "wof:placetype":"venue"
},
  "geometry": {"coordinates":[7.811241,53.218357],"type":"Point"}
}