{
  "type": "Feature",
  "properties": {
    "iso:country":"DE",
    "sg:address":"Untere Marktstr. 16",
    "sg:city":"K\u00f6sching",
    "sg:phone":"+49 8456/8495",
    "sg:postcode":"85092",
    "sg:province":"Bayern",
    "wof:name":"Oliver Leidel",
    "wof:placetype":"venue"
},
  "geometry": {"coordinates":[11.5031242371,48.811164856],"type":"Point"}
}