{
  "type": "Feature",
  "properties": {
    "iso:country":"DE",
    "sg:address":"Maria-Hilf-Str. 64",
    "sg:city":"Berching",
    "sg:phone":"+49 8462/1450",
    "sg:postcode":"92334",
    "sg:province":"Bayern",
    "wof:name":"Karl Lieblein",
    "wof:placetype":"venue"
},
  "geometry": {"coordinates":[11.4458703995,49.0944519043],"type":"Point"}
}