{
  "type": "Feature",
  "properties": {
    "iso:country":"DE",
    "sg:address":"Elisabethstr. 51",
    "sg:city":"D\u00fcsseldorf",
    "sg:phone":"+49 211/442464",
    "sg:postcode":"40217",
    "sg:province":"Nordrhein-Westfalen",
    "wof:name":"D\u00fcbag D\u00fcsseldorfer Beteiligungen Ag",
    "wof:placetype":"venue"
},
  "geometry": {"coordinates":[6.77505,51.21442],"type":"Point"}
}