{
  "type": "Feature",
  "properties": {
    "iso:country":"DE",
    "sg:address":"Ernst-Reuter-Str. 26",
    "sg:city":"Hof",
    "sg:phone":"+49 9281/92342",
    "sg:postcode":"95032",
    "sg:province":"Bayern",
    "wof:name":"A. Hader",
    "wof:placetype":"venue"
},
  "geometry": {"coordinates":[11.913867,50.306889],"type":"Point"}
}