{
  "type": "Feature",
  "properties": {
    "iso:country":"DE",
    "sg:address":"K\u00f6nigsberger Str. 7",
    "sg:city":"Aachen",
    "sg:phone":"+49 241/528448",
    "sg:postcode":"52078",
    "sg:province":"Nordrhein-Westfalen",
    "wof:name":"Verein Offene T\u00fcr Driescher Hof E. V.",
    "wof:placetype":"venue"
},
  "geometry": {"coordinates":[6.1447491646,50.7561187744],"type":"Point"}
}