{
  "type": "Feature",
  "properties": {
    "iso:country":"DE",
    "sg:address":"Kanalstr. 23",
    "sg:city":"Fulda",
    "sg:phone":"+49 661/21730",
    "sg:postcode":"36037",
    "sg:province":"Hessen",
    "wof:name":"Hans-joachim Glebe",
    "wof:placetype":"venue"
},
  "geometry": {"coordinates":[9.6749591827,50.5509529114],"type":"Point"}
}