{
  "type": "Feature",
  "properties": {
    "iso:country":"DE",
    "sg:address":"Im Sacke 2",
    "sg:city":"Ronnenberg",
    "sg:phone":"+49 5109/7689",
    "sg:postcode":"30952",
    "sg:province":"Niedersachsen",
    "wof:name":"Friedrich-wilhelm Homann",
    "wof:placetype":"venue"
},
  "geometry": {"coordinates":[9.656905,52.319515],"type":"Point"}
}