{
  "type": "Feature",
  "properties": {
    "iso:country":"DE",
    "sg:address":"Maximilianstr. 26",
    "sg:city":"Memmingen",
    "sg:phone":"+49 8331/3536",
    "sg:postcode":"87700",
    "sg:province":"Bayern",
    "wof:name":"Athen",
    "wof:placetype":"venue"
},
  "geometry": {"coordinates":[10.1854362488,47.9854927063],"type":"Point"}
}