{
  "type": "Feature",
  "properties": {
    "iso:country":"DE",
    "sg:address":"Schlo\u00dfstr. 31a",
    "sg:city":"Kl\u00fctz",
    "sg:phone":"+49 38825/29614",
    "sg:postcode":"23948",
    "sg:province":"Mecklenburg-Vorpommern",
    "wof:name":"Klawitter",
    "wof:placetype":"venue"
},
  "geometry": {"coordinates":[11.1634645462,53.964466095],"type":"Point"}
}