{
  "type": "Feature",
  "properties": {
    "iso:country":"DE",
    "sg:address":"Lothringer Str. 20",
    "sg:city":"Bremerhaven",
    "sg:phone":"+49 471/35226",
    "sg:postcode":"27570",
    "sg:province":"Bremen",
    "wof:name":"Hinrich Wendte Fische",
    "wof:placetype":"venue"
},
  "geometry": {"coordinates":[8.594669342,53.5320205688],"type":"Point"}
}