{
  "type": "Feature",
  "properties": {
    "iso:country":"DE",
    "sg:address":"Zum Gro\u00dfen Stein 1",
    "sg:city":"Spangenberg",
    "sg:phone":"+49 5663/224",
    "sg:postcode":"34286",
    "sg:province":"Hessen",
    "wof:name":"K\u00e4the Wollenhaupt Hebamme",
    "wof:placetype":"venue"
},
  "geometry": {"coordinates":[9.667609,51.120457],"type":"Point"}
}