{
  "type": "Feature",
  "properties": {
    "iso:country":"DE",
    "sg:address":"Baruther Ch. 6",
    "sg:city":"J\u00fcterbog",
    "sg:phone":"+49 3372/404954",
    "sg:postcode":"14913",
    "sg:province":"Brandenburg",
    "wof:name":"Jag J\u00dcterboger Agrargen.",
    "wof:placetype":"venue"
},
  "geometry": {"coordinates":[13.104443,51.983887],"type":"Point"}
}