{
  "type": "Feature",
  "properties": {
    "iso:country":"DE",
    "sg:address":"Kaiser-Friedrich-Ring 32",
    "sg:city":"D\u00fcsseldorf",
    "sg:phone":"+49 211/552901",
    "sg:postcode":"40545",
    "sg:province":"Nordrhein-Westfalen",
    "wof:name":"T. Lirsch",
    "wof:placetype":"venue"
},
  "geometry": {"coordinates":[6.761359,51.234863],"type":"Point"}
}