{
  "type": "Feature",
  "properties": {
    "iso:country":"DE",
    "sg:address":"Raiffeisenstra\u00dfe 4-6",
    "sg:city":"Baunatal",
    "sg:postcode":"34225",
    "sg:province":"Hessen",
    "wof:name":"Rechtsanw\u00e4lte Gutzeit U. Pistorius",
    "wof:placetype":"venue"
},
  "geometry": {"coordinates":[9.38838,51.250431],"type":"Point"}
}