{
  "type": "Feature",
  "properties": {
    "iso:country":"DE",
    "sg:address":"Elisabethenstr. 17",
    "sg:city":"Darmstadt",
    "sg:phone":"+49 6151/17825",
    "sg:postcode":"64283",
    "sg:province":"Hessen",
    "wof:name":"Sauer Und Kollegen Rechtsanw\u00e4lte Und Notare",
    "wof:placetype":"venue"
},
  "geometry": {"coordinates":[8.6512031555,49.8703422546],"type":"Point"}
}