{
  "type": "Feature",
  "properties": {
    "iso:country":"DE",
    "sg:address":"Amselweg 7",
    "sg:city":"Tamm",
    "sg:phone":"+49 7141/605560",
    "sg:postcode":"71732",
    "sg:province":"Baden-W\u00fcrttemberg",
    "wof:name":"Heinrich Diezel Gmbh",
    "wof:placetype":"venue"
},
  "geometry": {"coordinates":[9.1375932693,48.9202537537],"type":"Point"}
}