{
  "type": "Feature",
  "properties": {
    "iso:country":"DE",
    "sg:address":"Lange Str. 22",
    "sg:city":"Osten",
    "sg:phone":"+49 4771/2371",
    "sg:postcode":"21756",
    "sg:province":"Niedersachsen",
    "wof:name":"Gerichtsklause",
    "wof:placetype":"venue"
},
  "geometry": {"coordinates":[9.1897220612,53.6948394775],"type":"Point"}
}