{
  "type": "Feature",
  "properties": {
    "iso:country":"DE",
    "sg:address":"Alsterdorfer Str. 2 a",
    "sg:city":"Hamburg",
    "sg:phone":"+49 40/488066",
    "sg:postcode":"22299",
    "sg:province":"Hamburg",
    "wof:name":"Heldt Gmbh",
    "wof:placetype":"venue"
},
  "geometry": {"coordinates":[9.998712,53.595139],"type":"Point"}
}