{
  "type": "Feature",
  "properties": {
    "iso:country":"DE",
    "sg:address":"Petuelring 130",
    "sg:city":"M\u00fcnchen",
    "sg:phone":"+49 89/35009412",
    "sg:postcode":"80809",
    "sg:province":"Bayern",
    "wof:name":"Bmw Intec Beteiligungs-gmbh",
    "wof:placetype":"venue"
},
  "geometry": {"coordinates":[11.560648,48.176727],"type":"Point"}
}