{
  "type": "Feature",
  "properties": {
    "iso:country":"DE",
    "sg:address":"August-Bebel-Str. 24",
    "sg:city":"Scharfenstein",
    "sg:phone":"+49 3725/70750",
    "sg:postcode":"09435",
    "sg:province":"Sachsen",
    "wof:name":"Sfb-schl\u00fcssel-fertiges- Bauen Gmbh",
    "wof:placetype":"venue"
},
  "geometry": {"coordinates":[13.049326,50.702271],"type":"Point"}
}