{
  "type": "Feature",
  "properties": {
    "iso:country":"DE",
    "sg:address":"Br\u00fchlmatten 9",
    "sg:city":"Sulzburg",
    "sg:postcode":"79295",
    "sg:province":"Baden-W\u00fcrttemberg",
    "wof:name":"Securiton Beteiligungs Gmbh",
    "wof:placetype":"venue"
},
  "geometry": {"coordinates":[7.70084,47.84763],"type":"Point"}
}