{
  "type": "Feature",
  "properties": {
    "iso:country":"DE",
    "sg:address":"Lehmkuhlenweg 16",
    "sg:city":"Hattstedt",
    "sg:phone":"+49 4846/750",
    "sg:postcode":"25856",
    "sg:province":"Schleswig-Holstein",
    "wof:name":"Michael Hansen-metallbau Gmbh",
    "wof:placetype":"venue"
},
  "geometry": {"coordinates":[9.031123,54.524582],"type":"Point"}
}