{
  "type": "Feature",
  "properties": {
    "iso:country":"DE",
    "sg:address":"Zehntstr. 25",
    "sg:city":"Deizisau",
    "sg:phone":"+49 7153/27511",
    "sg:postcode":"73779",
    "sg:province":"Baden-W\u00fcrttemberg",
    "wof:name":"Neckar-apotheke",
    "wof:placetype":"venue"
},
  "geometry": {"coordinates":[9.389066,48.713676],"type":"Point"}
}