{
  "type": "Feature",
  "properties": {
    "iso:country":"DE",
    "sg:address":"Heideweg 14",
    "sg:city":"Neuhof",
    "sg:phone":"+49 6655/4638",
    "sg:postcode":"36119",
    "sg:province":"Hessen",
    "wof:name":"Helmut We\u00df Steuerberater",
    "wof:placetype":"venue"
},
  "geometry": {"coordinates":[9.5739402771,50.4522209167],"type":"Point"}
}