{
  "type": "Feature",
  "properties": {
    "iso:country":"DE",
    "sg:address":"Nu\u00dfbaumerstr. 32",
    "sg:city":"Traunstein",
    "sg:phone":"+49 861/55549",
    "sg:postcode":"83278",
    "sg:province":"Bayern",
    "wof:name":"Ausbildungsst\u00e4tte Fernmeldeamt Traunstein Mit",
    "wof:placetype":"venue"
},
  "geometry": {"coordinates":[12.6281604767,47.8809165955],"type":"Point"}
}