{
  "type": "Feature",
  "properties": {
    "iso:country":"DE",
    "sg:address":"Friedrich-Rodehorst-Str. 39",
    "sg:city":"Hemmingen",
    "sg:phone":"+49 511/943950",
    "sg:postcode":"30966",
    "sg:province":"Niedersachsen",
    "wof:name":"Schuhbedarf-vertriebsges. Mbh",
    "wof:placetype":"venue"
},
  "geometry": {"coordinates":[9.733174,52.322296],"type":"Point"}
}