{
  "type": "Feature",
  "properties": {
    "iso:country":"DE",
    "sg:address":"88512",
    "sg:city":"Mengen",
    "sg:phone":"+49 7572/60721",
    "sg:postcode":"88512",
    "sg:province":"Baden-W\u00fcrttemberg",
    "wof:name":"Stadtarchiv Stadtverwaltung",
    "wof:placetype":"venue"
},
  "geometry": {"coordinates":[9.32414,48.045658],"type":"Point"}
}