{
  "type": "Feature",
  "properties": {
    "iso:country":"DE",
    "sg:address":"Am Wasserfall 1",
    "sg:city":"Velbert",
    "sg:phone":"+49 2051/81742",
    "sg:postcode":"42551",
    "sg:province":"Nordrhein-Westfalen",
    "wof:name":"Das Blumenparadies Winfried Hoffmann",
    "wof:placetype":"venue"
},
  "geometry": {"coordinates":[7.02942,51.350456],"type":"Point"}
}