{
  "type": "Feature",
  "properties": {
    "iso:country":"DE",
    "sg:address":"Burgackerweg 10",
    "sg:city":"Freiburg",
    "sg:phone":"+49 761/5563155",
    "sg:postcode":"79104",
    "sg:province":"Baden-W\u00fcrttemberg",
    "wof:name":"Trade Concept Handel Und Versand Gmbh",
    "wof:placetype":"venue"
},
  "geometry": {"coordinates":[7.8680877686,48.0249824524],"type":"Point"}
}