{
  "type": "Feature",
  "properties": {
    "iso:country":"DE",
    "sg:address":"Krefelder Str. 170",
    "sg:city":"T\u00f6nisvorst",
    "sg:phone":"+49 2151",
    "sg:postcode":"47918",
    "sg:province":"Nordrhein-Westfalen",
    "wof:name":"Voigt Edv-systeme Software-entwicklung",
    "wof:placetype":"venue"
},
  "geometry": {"coordinates":[6.509119,51.323566],"type":"Point"}
}