{
  "type": "Feature",
  "properties": {
    "iso:country":"DE",
    "sg:address":"Ulzburger Str. 8",
    "sg:city":"Norderstedt",
    "sg:phone":"+49 40/5236464",
    "sg:postcode":"22850",
    "sg:province":"Schleswig-Holstein",
    "wof:name":"Wolfgang Malchow",
    "wof:placetype":"venue"
},
  "geometry": {"coordinates":[9.9983758926,53.6835365295],"type":"Point"}
}