{
  "type": "Feature",
  "properties": {
    "iso:country":"DE",
    "sg:address":"Hauptstr. 127",
    "sg:city":"Bernstadt",
    "sg:phone":"+49 35874/4263",
    "sg:postcode":"02748",
    "sg:province":"Sachsen",
    "wof:name":"Gastst\u00e4tte Kretscham",
    "wof:placetype":"venue"
},
  "geometry": {"coordinates":[14.7766218185,51.0711212158],"type":"Point"}
}