{
  "type": "Feature",
  "properties": {
    "iso:country":"DE",
    "sg:address":"Frankenweg 59",
    "sg:city":"Burgen",
    "sg:phone":"+49 2605/732",
    "sg:postcode":"56332",
    "sg:province":"Rheinland-Pfalz",
    "wof:name":"Pension M. Nebinger",
    "wof:placetype":"venue"
},
  "geometry": {"coordinates":[7.3834710121,50.2055931091],"type":"Point"}
}