{
  "type": "Feature",
  "properties": {
    "iso:country":"DE",
    "sg:address":"Holzwiesenweg 10",
    "sg:city":"Rudersberg",
    "sg:phone":"+49 7183/939190",
    "sg:postcode":"73635",
    "sg:province":"Baden-W\u00fcrttemberg",
    "wof:name":"Dai\u00df & Partner",
    "wof:placetype":"venue"
},
  "geometry": {"coordinates":[9.54813,48.85416],"type":"Point"}
}