{
  "type": "Feature",
  "properties": {
    "iso:country":"DE",
    "sg:address":"Kiefernweg 3",
    "sg:city":"Marburg",
    "sg:phone":"+49 6424/70210",
    "sg:postcode":"35043",
    "sg:province":"Hessen",
    "wof:name":"Heidrun Schuh",
    "wof:placetype":"venue"
},
  "geometry": {"coordinates":[8.820312,50.771652],"type":"Point"}
}