{
  "type": "Feature",
  "properties": {
    "iso:country":"DE",
    "sg:address":"Hauptstr. 25",
    "sg:city":"Olching",
    "sg:phone":"+49 8142/18477",
    "sg:postcode":"82140",
    "sg:province":"Bayern",
    "wof:name":"Kfz-reparatur Anton Rauscher Gmbh",
    "wof:placetype":"venue"
},
  "geometry": {"coordinates":[11.3302268982,48.2084884644],"type":"Point"}
}