{
  "type": "Feature",
  "properties": {
    "iso:country":"DE",
    "sg:address":"Breite Str. 6",
    "sg:city":"Glauchau",
    "sg:phone":"+49 3763/5504",
    "sg:postcode":"08371",
    "sg:province":"Sachsen",
    "wof:name":"Werner Hennig",
    "wof:placetype":"venue"
},
  "geometry": {"coordinates":[12.539045,50.818619],"type":"Point"}
}