{
  "type": "Feature",
  "properties": {
    "iso:country":"DE",
    "sg:address":"Tannenweg 12",
    "sg:city":"Aidlingen",
    "sg:phone":"+49 7034/71134",
    "sg:postcode":"71134",
    "sg:province":"Baden-W\u00fcrttemberg",
    "wof:name":"Raiffeisen Markt",
    "wof:placetype":"venue"
},
  "geometry": {"coordinates":[8.884345,48.677208],"type":"Point"}
}