{
  "type": "Feature",
  "properties": {
    "iso:country":"DE",
    "sg:address":"Lindhorstweg 53",
    "sg:city":"Berlin",
    "sg:phone":"+49 30/6310716",
    "sg:postcode":"12487",
    "sg:province":"Berlin",
    "wof:name":"J\u00fcrgen Strauch & Sohn Gmbh",
    "wof:placetype":"venue"
},
  "geometry": {"coordinates":[13.500742,52.440826],"type":"Point"}
}