{
  "type": "Feature",
  "properties": {
    "iso:country":"DE",
    "sg:address":"Gallusstr. 11",
    "sg:city":"Bonn",
    "sg:phone":"+49 228/442269",
    "sg:postcode":"53227",
    "sg:province":"Nordrhein-Westfalen",
    "wof:name":"Kath. \u00d6ffentliche Bibliothek St. Gallus",
    "wof:placetype":"venue"
},
  "geometry": {"coordinates":[7.149713,50.72868],"type":"Point"}
}