{
  "type": "Feature",
  "properties": {
    "iso:country":"DE",
    "sg:address":"Uhlandstr. 14",
    "sg:city":"Ettlingen",
    "sg:phone":"+49 7243/91807",
    "sg:postcode":"76275",
    "sg:province":"Baden-W\u00fcrttemberg",
    "wof:name":"Jens Hartz Architekten",
    "wof:placetype":"venue"
},
  "geometry": {"coordinates":[8.366145,48.931362],"type":"Point"}
}