{
  "type": "Feature",
  "properties": {
    "iso:country":"DE",
    "sg:address":"Eckgasse 5",
    "sg:city":"Bad D\u00fcrrheim",
    "sg:phone":"+49 7706/287",
    "sg:postcode":"78073",
    "sg:province":"Baden-W\u00fcrttemberg",
    "wof:name":"Adolf W\u00f6lfle",
    "wof:placetype":"venue"
},
  "geometry": {"coordinates":[8.6389665604,47.9913330078],"type":"Point"}
}