{
  "type": "Feature",
  "properties": {
    "iso:country":"DE",
    "sg:address":"Beckers Kamp 9",
    "sg:city":"Melle",
    "sg:phone":"+49 5429/444",
    "sg:postcode":"49326",
    "sg:province":"Niedersachsen",
    "wof:name":"Dr. Josef Thiemann Tierarzt",
    "wof:placetype":"venue"
},
  "geometry": {"coordinates":[8.2705535889,52.1571044922],"type":"Point"}
}