{
  "type": "Feature",
  "properties": {
    "iso:country":"DE",
    "sg:address":"Am Rustebach 7",
    "sg:city":"Rustenfelde",
    "sg:postcode":"37318",
    "sg:province":"Th\u00fcringen",
    "wof:name":"Gemeindeschwesterstation Ingrid Ringleb",
    "wof:placetype":"venue"
},
  "geometry": {"coordinates":[10.004559,51.394314],"type":"Point"}
}