{
  "type": "Feature",
  "properties": {
    "iso:country":"DE",
    "sg:address":"Friedrichstr. 1",
    "sg:city":"Pleidelsheim",
    "sg:postcode":"74385",
    "sg:province":"Baden-W\u00fcrttemberg",
    "wof:name":"Cool-clean-tec Gmbh",
    "wof:placetype":"venue"
},
  "geometry": {"coordinates":[9.20573,48.960373],"type":"Point"}
}