{
  "type": "Feature",
  "properties": {
    "iso:country":"DE",
    "sg:address":"Am Reislebach 12",
    "sg:city":"Albstadt",
    "sg:phone":"+49 7432/3707",
    "sg:postcode":"72461",
    "sg:province":"Baden-W\u00fcrttemberg",
    "wof:name":"Hartmut Ott Elektroinstallation",
    "wof:placetype":"venue"
},
  "geometry": {"coordinates":[9.025446,48.240269],"type":"Point"}
}