{
  "type": "Feature",
  "properties": {
    "iso:country":"DE",
    "sg:address":"Vorstadtstr. 14",
    "sg:city":"Saarwellingen",
    "sg:phone":"+49 6838/4440",
    "sg:postcode":"66793",
    "sg:province":"Saarland",
    "wof:name":"Restaurant Vorstadtkneipe",
    "wof:placetype":"venue"
},
  "geometry": {"coordinates":[6.8048849106,49.352104187],"type":"Point"}
}