{
  "type": "Feature",
  "properties": {
    "iso:country":"DE",
    "sg:address":"Bahnhofstr. 18",
    "sg:city":"B\u00fcsum",
    "sg:phone":"+49 4834/1007",
    "sg:postcode":"25761",
    "sg:province":"Schleswig-Holstein",
    "wof:name":"S\u00f6nke Martensen Architekt",
    "wof:placetype":"venue"
},
  "geometry": {"coordinates":[8.862793,54.132084],"type":"Point"}
}