{
  "type": "Feature",
  "properties": {
    "iso:country":"DE",
    "sg:address":"B\u00fcchel 5",
    "sg:city":"Aachen",
    "sg:phone":"+49 241/48393",
    "sg:postcode":"52062",
    "sg:province":"Nordrhein-Westfalen",
    "wof:name":"Hotel Drei K\u00f6nige",
    "wof:placetype":"venue"
},
  "geometry": {"coordinates":[6.0851650238,50.7763175964],"type":"Point"}
}