{
  "type": "Feature",
  "properties": {
    "iso:country":"DE",
    "sg:address":"Lindenstr. 17",
    "sg:city":"R\u00f6dental",
    "sg:phone":"+49 9563/6260",
    "sg:postcode":"96472",
    "sg:province":"Bayern",
    "wof:name":"G. Hofmann",
    "wof:placetype":"venue"
},
  "geometry": {"coordinates":[11.056433,50.298115],"type":"Point"}
}