{
  "type": "Feature",
  "properties": {
    "iso:country":"DE",
    "sg:address":"Bettikumer Dorfstr. 11",
    "sg:city":"Neuss",
    "sg:phone":"+49 2137/952364",
    "sg:postcode":"41470",
    "sg:province":"Nordrhein-Westfalen",
    "wof:name":"Peter Holtermann",
    "wof:placetype":"venue"
},
  "geometry": {"coordinates":[6.7144389153,51.1453857422],"type":"Point"}
}