{
  "type": "Feature",
  "properties": {
    "iso:country":"DE",
    "sg:address":"M\u00fcnzgasse 6",
    "sg:city":"Annaberg-Buchholz",
    "sg:phone":"+49 3733/22286",
    "sg:postcode":"09456",
    "sg:province":"Sachsen",
    "wof:name":"Herms Schmidt",
    "wof:placetype":"venue"
},
  "geometry": {"coordinates":[13.0012531281,50.5805587769],"type":"Point"}
}