{
  "type": "Feature",
  "properties": {
    "iso:country":"DE",
    "sg:address":"Am Porthspick 3",
    "sg:city":"Krefeld",
    "sg:phone":"+49 2151/735084",
    "sg:postcode":"47839",
    "sg:province":"Nordrhein-Westfalen",
    "wof:name":"R. Stahl",
    "wof:placetype":"venue"
},
  "geometry": {"coordinates":[6.506653,51.381279],"type":"Point"}
}