{
  "type": "Feature",
  "properties": {
    "iso:country":"DE",
    "sg:address":"Pilsenseeweg 22",
    "sg:city":"Gr\u00f6benzell",
    "sg:phone":"+49 8142/9277",
    "sg:postcode":"82194",
    "sg:province":"Bayern",
    "wof:name":"Karl Werner",
    "wof:placetype":"venue"
},
  "geometry": {"coordinates":[11.374362,48.189896],"type":"Point"}
}