{
  "type": "Feature",
  "properties": {
    "iso:country":"DE",
    "sg:address":"Go\u00dfmannsdorf 125 1/2",
    "sg:city":"Hofheim",
    "sg:phone":"+49 9523/1501",
    "sg:postcode":"97461",
    "sg:province":"Bayern",
    "wof:name":"Schramm-frie\u00dflich",
    "wof:placetype":"venue"
},
  "geometry": {"coordinates":[10.5223703384,50.1371421814],"type":"Point"}
}