{
  "type": "Feature",
  "properties": {
    "iso:country":"DE",
    "sg:address":"Kirchstr. 2a",
    "sg:city":"Steinen",
    "sg:phone":"+49 7627/2577",
    "sg:postcode":"79585",
    "sg:province":"Baden-W\u00fcrttemberg",
    "wof:name":"Foto-studio-k\u00f6pfer Gmbh",
    "wof:placetype":"venue"
},
  "geometry": {"coordinates":[7.7395191193,47.643989563],"type":"Point"}
}