{
  "type": "Feature",
  "properties": {
    "iso:country":"DE",
    "sg:address":"Kreulshof 12 A",
    "sg:city":"Bottrop",
    "sg:phone":"+49 2041/43209",
    "sg:postcode":"46240",
    "sg:province":"Nordrhein-Westfalen",
    "wof:name":"M. Nordick",
    "wof:placetype":"venue"
},
  "geometry": {"coordinates":[6.9700031281,51.5318374634],"type":"Point"}
}