{
  "type": "Feature",
  "properties": {
    "iso:country":"DE",
    "sg:address":"Weiherstr. 3",
    "sg:city":"Netphen",
    "sg:phone":"+49 2737/1241",
    "sg:postcode":"57250",
    "sg:province":"Nordrhein-Westfalen",
    "wof:name":"Hubertushof Solbach",
    "wof:placetype":"venue"
},
  "geometry": {"coordinates":[8.1640501022,50.9508094788],"type":"Point"}
}