{
  "type": "Feature",
  "properties": {
    "iso:country":"DE",
    "sg:address":"Bachstr. 42",
    "sg:city":"M\u00fcnsing",
    "sg:phone":"+49 8177/354",
    "sg:postcode":"82541",
    "sg:province":"Bayern",
    "wof:name":"Franz Eckart",
    "wof:placetype":"venue"
},
  "geometry": {"coordinates":[11.378158,47.902451],"type":"Point"}
}