{
  "type": "Feature",
  "properties": {
    "iso:country":"DE",
    "sg:address":"Rathausstr. 67",
    "sg:city":"Rheurdt",
    "sg:phone":"+49 2845/6234",
    "sg:postcode":"47509",
    "sg:province":"Nordrhein-Westfalen",
    "wof:name":"Werner Arts",
    "wof:placetype":"venue"
},
  "geometry": {"coordinates":[6.4680409431,51.4700126648],"type":"Point"}
}