{
  "type": "Feature",
  "properties": {
    "iso:country":"DE",
    "sg:address":"Pallaswiesenstr. 63",
    "sg:city":"Darmstadt",
    "sg:phone":"+49 6151/893537",
    "sg:postcode":"64293",
    "sg:province":"Hessen",
    "wof:name":"Verband Evangelische Gemeindeb\u00fcchereien",
    "wof:placetype":"venue"
},
  "geometry": {"coordinates":[8.645453,49.882133],"type":"Point"}
}