{
  "type": "Feature",
  "properties": {
    "iso:country":"DE",
    "sg:address":"Ispringer Str. 6",
    "sg:city":"Pforzheim",
    "sg:phone":"+49 7231/91890",
    "sg:postcode":"75179",
    "sg:province":"Baden-W\u00fcrttemberg",
    "wof:name":"Cde Software Und Systems Gmbh",
    "wof:placetype":"venue"
},
  "geometry": {"coordinates":[8.693247,48.898815],"type":"Point"}
}