{
  "type": "Feature",
  "properties": {
    "iso:country":"DE",
    "sg:address":"Hauptstr. 25",
    "sg:city":"Osterhausen",
    "sg:phone":"+49 34776/20468",
    "sg:postcode":"06295",
    "sg:province":"Sachsen-Anhalt",
    "wof:name":"Klaus-dieter Kopper",
    "wof:placetype":"venue"
},
  "geometry": {"coordinates":[11.503044,51.454094],"type":"Point"}
}