{
  "type": "Feature",
  "properties": {
    "iso:country":"DE",
    "sg:address":"Kirchstr. 65",
    "sg:city":"Tangerm\u00fcnde",
    "sg:phone":"+49 4939/3222039",
    "sg:postcode":"39590",
    "sg:province":"Sachsen-Anhalt",
    "wof:name":"Buch-u Offsetdruckerei",
    "wof:placetype":"venue"
},
  "geometry": {"coordinates":[11.9700450897,52.5404510498],"type":"Point"}
}