{
  "type": "Feature",
  "properties": {
    "iso:country":"DE",
    "sg:address":"Bergstr. 14",
    "sg:city":"Seesen",
    "sg:phone":"+49 5381/2950",
    "sg:postcode":"38723",
    "sg:province":"Niedersachsen",
    "wof:name":"Gundula Hilliger Krankengymnastin",
    "wof:placetype":"venue"
},
  "geometry": {"coordinates":[10.179586,51.885822],"type":"Point"}
}