{
  "type": "Feature",
  "properties": {
    "iso:country":"DE",
    "sg:address":"Bahnhofstr. 13",
    "sg:city":"K\u00f6lleda",
    "sg:phone":"+49 3635/400965",
    "sg:postcode":"99625",
    "sg:province":"Th\u00fcringen",
    "wof:name":"Birgit Dittmar Masseur",
    "wof:placetype":"venue"
},
  "geometry": {"coordinates":[11.2461,51.188316],"type":"Point"}
}