{
  "type": "Feature",
  "properties": {
    "iso:country":"DE",
    "sg:address":"Starnberger Str. 22",
    "sg:city":"Gauting",
    "sg:phone":"+49 89/8931680",
    "sg:postcode":"82131",
    "sg:province":"Bayern",
    "wof:name":"Ingenieurb\u00fcro Gregoritsch Techn. Geb\u00e4udeausr\u00fcstung. Mbh",
    "wof:placetype":"venue"
},
  "geometry": {"coordinates":[11.3783321381,48.064655304],"type":"Point"}
}