{
  "type": "Feature",
  "properties": {
    "iso:country":"DE",
    "sg:address":"Eisfelder Str. 12",
    "sg:city":"Neuhaus",
    "sg:phone":"+49 3679/720757",
    "sg:postcode":"98724",
    "sg:province":"Th\u00fcringen",
    "wof:name":"F. Ritter",
    "wof:placetype":"venue"
},
  "geometry": {"coordinates":[11.1373214722,50.5094718933],"type":"Point"}
}