{
  "type": "Feature",
  "properties": {
    "iso:country":"DE",
    "sg:address":"Kurzstr. 2",
    "sg:city":"M\u00fcnchen",
    "sg:phone":"+49 89/64258157",
    "sg:postcode":"81547",
    "sg:province":"Bayern",
    "wof:name":"Bayerische Landesschule F\u00fcr K\u00f6rperbehinderte",
    "wof:placetype":"venue"
},
  "geometry": {"coordinates":[11.568110466,48.105255127],"type":"Point"}
}