{
  "type": "Feature",
  "properties": {
    "iso:country":"DE",
    "sg:address":"Steinstr. 8",
    "sg:city":"Reken",
    "sg:phone":"+49 2864/1304",
    "sg:postcode":"48734",
    "sg:province":"Nordrhein-Westfalen",
    "wof:name":"Hubert Schulte Architekt",
    "wof:placetype":"venue"
},
  "geometry": {"coordinates":[7.043439,51.83305],"type":"Point"}
}