{
  "type": "Feature",
  "properties": {
    "iso:country":"DE",
    "sg:address":"Molkereistra\u00dfe 6",
    "sg:city":"Elsdorf",
    "sg:phone":"+49 4286/930062",
    "sg:postcode":"27404",
    "sg:province":"Niedersachsen",
    "wof:name":"Milchberatung, Milchleistungspr\u00fcfung, Und Pr\u00fcfung",
    "wof:placetype":"venue"
},
  "geometry": {"coordinates":[9.350028038,53.2389793396],"type":"Point"}
}