{
  "type": "Feature",
  "properties": {
    "iso:country":"DE",
    "sg:address":"Wandhofener Str. 2",
    "sg:city":"Hagen",
    "sg:phone":"+49 2331/36000",
    "sg:postcode":"58099",
    "sg:province":"Nordrhein-Westfalen",
    "wof:name":"Ernst-apparatebau Gmbh & Co.",
    "wof:placetype":"venue"
},
  "geometry": {"coordinates":[7.4835271835,51.4045791626],"type":"Point"}
}