{
  "type": "Feature",
  "properties": {
    "iso:country":"DE",
    "sg:address":"Am Tiefen Stein 3",
    "sg:city":"H\u00f6chstadt",
    "sg:phone":"+49 9193/3772",
    "sg:postcode":"91315",
    "sg:province":"Bayern",
    "wof:name":"Saha-sack-handels- Gmbh",
    "wof:placetype":"venue"
},
  "geometry": {"coordinates":[10.8186721802,49.7184028625],"type":"Point"}
}