{
  "type": "Feature",
  "properties": {
    "iso:country":"DE",
    "sg:address":"Stra\u00dfe 10 5",
    "sg:city":"Berlin",
    "sg:phone":"+49 30/9208165",
    "sg:postcode":"13059",
    "sg:province":"Berlin",
    "wof:name":"Bic Bau-instandhaltungs- Consult Ingenieurges. Mbh",
    "wof:placetype":"venue"
},
  "geometry": {"coordinates":[13.516625,52.579884],"type":"Point"}
}