{
  "type": "Feature",
  "properties": {
    "iso:country":"DE",
    "sg:address":"Kurf\u00fcrstenallee 28",
    "sg:city":"Bremen",
    "sg:phone":"+49 421/434370",
    "sg:postcode":"28211",
    "sg:province":"Bremen",
    "wof:name":"Hahndorf & Wucherpfenning Gmbh & Co.",
    "wof:placetype":"venue"
},
  "geometry": {"coordinates":[8.845599,53.081257],"type":"Point"}
}