{
  "type": "Feature",
  "properties": {
    "iso:country":"DE",
    "sg:address":"Georg-Kohl-Str. 14",
    "sg:city":"Brackenheim",
    "sg:phone":"+49 7135/960883",
    "sg:postcode":"74336",
    "sg:province":"Baden-W\u00fcrttemberg",
    "wof:name":"Crt Transport Beteiligungsgesellschaft Mbh",
    "wof:placetype":"venue"
},
  "geometry": {"coordinates":[9.06657,49.074535],"type":"Point"}
}