{
  "type": "Feature",
  "properties": {
    "iso:country":"DE",
    "sg:address":"Am Massenberger Kamp 49",
    "sg:city":"D\u00fcsseldorf",
    "sg:phone":"+49 211/751701",
    "sg:postcode":"40589",
    "sg:province":"Nordrhein-Westfalen",
    "wof:name":"H. Deis",
    "wof:placetype":"venue"
},
  "geometry": {"coordinates":[6.8208341599,51.1809196472],"type":"Point"}
}