{
  "type": "Feature",
  "properties": {
    "iso:country":"DE",
    "sg:address":"Buchholzer Landstr. 66 a",
    "sg:city":"Buchholz",
    "sg:phone":"+49 4187/6956",
    "sg:postcode":"21244",
    "sg:province":"Niedersachsen",
    "wof:name":"G. Lorenz",
    "wof:placetype":"venue"
},
  "geometry": {"coordinates":[9.8708648682,53.2863731384],"type":"Point"}
}