{
  "type": "Feature",
  "properties": {
    "iso:country":"DE",
    "sg:address":"Dorfstr. 49",
    "sg:city":"Osterr\u00f6nfeld",
    "sg:phone":"+49 4331/80085",
    "sg:postcode":"24783",
    "sg:province":"Schleswig-Holstein",
    "wof:name":"Handelsagentur Klaus-peter Heit E. Kfm.",
    "wof:placetype":"venue"
},
  "geometry": {"coordinates":[9.696393013,54.2911376953],"type":"Point"}
}