{
  "type": "Feature",
  "properties": {
    "iso:country":"DE",
    "sg:address":"Moosm\u00fchlweg 9",
    "sg:city":"Pfronten",
    "sg:phone":"+49 8363/6437",
    "sg:postcode":"87459",
    "sg:province":"Bayern",
    "wof:name":"T. Wolfart",
    "wof:placetype":"venue"
},
  "geometry": {"coordinates":[10.557114,47.606014],"type":"Point"}
}