{
  "type": "Feature",
  "properties": {
    "iso:country":"DE",
    "sg:address":"Carl-Benz-Str. 29",
    "sg:city":"Singen",
    "sg:postcode":"78224",
    "sg:province":"Baden-W\u00fcrttemberg",
    "wof:name":"Wohnbau Sk Gmbh",
    "wof:placetype":"venue"
},
  "geometry": {"coordinates":[8.870593071,47.754524231],"type":"Point"}
}