{
  "type": "Feature",
  "properties": {
    "iso:country":"DE",
    "sg:address":"Linder Weg 100",
    "sg:city":"K\u00f6ln",
    "sg:phone":"+49 221/7901472",
    "sg:postcode":"51147",
    "sg:province":"Nordrhein-Westfalen",
    "wof:name":"Itg-baugesellschaft Mbh",
    "wof:placetype":"venue"
},
  "geometry": {"coordinates":[7.103664,50.851624],"type":"Point"}
}