{
  "type": "Feature",
  "properties": {
    "iso:country":"DE",
    "sg:address":"Theresienstr. 3",
    "sg:city":"Aschaffenburg",
    "sg:phone":"+49 6021/424886",
    "sg:postcode":"63741",
    "sg:province":"Bayern",
    "wof:name":"Gebhard Eich Steuerberater",
    "wof:placetype":"venue"
},
  "geometry": {"coordinates":[9.1391420364,49.9825325012],"type":"Point"}
}