{
  "type": "Feature",
  "properties": {
    "iso:country":"DE",
    "sg:address":"Stra\u00dfe des Friedens 40",
    "sg:city":"Teuchern",
    "sg:phone":"+49 34443/21484",
    "sg:postcode":"06682",
    "sg:province":"Sachsen-Anhalt",
    "wof:name":"Mecklenburgische Versicherungsgruppe",
    "wof:placetype":"venue"
},
  "geometry": {"coordinates":[12.0216522217,51.1186332703],"type":"Point"}
}