{
  "type": "Feature",
  "properties": {
    "iso:country":"DE",
    "sg:address":"Karl-Schurz-Str. 6",
    "sg:city":"Troisdorf",
    "sg:phone":"+49 2241/73677",
    "sg:postcode":"53840",
    "sg:province":"Nordrhein-Westfalen",
    "wof:name":"G. Dorndorf",
    "wof:placetype":"venue"
},
  "geometry": {"coordinates":[7.163989,50.808723],"type":"Point"}
}