{
  "type": "Feature",
  "properties": {
    "iso:country":"DE",
    "sg:address":"Blumenheideweg 8",
    "sg:city":"Kevelaer",
    "sg:phone":"+49 2832/951320",
    "sg:postcode":"47625",
    "sg:province":"Nordrhein-Westfalen",
    "wof:name":"Tsn Topfpflanzenservice Niederrhein Gmbh",
    "wof:placetype":"venue"
},
  "geometry": {"coordinates":[6.254475,51.553772],"type":"Point"}
}