{
  "type": "Feature",
  "properties": {
    "iso:country":"DE",
    "sg:address":"Augsburger Str. 62",
    "sg:city":"Schongau",
    "sg:phone":"+49 8861/7373",
    "sg:postcode":"86956",
    "sg:province":"Bayern",
    "wof:name":"Blumenschule Engler & Friesch Gbr",
    "wof:placetype":"venue"
},
  "geometry": {"coordinates":[10.899651,47.815166],"type":"Point"}
}