{
  "type": "Feature",
  "properties": {
    "iso:country":"DE",
    "sg:address":"Lobeckstr. 18",
    "sg:city":"Berlin",
    "sg:phone":"+49 30/7850022",
    "sg:postcode":"10969",
    "sg:province":"Berlin",
    "wof:name":"Wilbur Im- Und Export Gmbh",
    "wof:placetype":"venue"
},
  "geometry": {"coordinates":[13.4054775238,52.5010910034],"type":"Point"}
}