{
  "type": "Feature",
  "properties": {
    "iso:country":"DE",
    "sg:address":"Falterstr.",
    "sg:city":"Kitzingen",
    "sg:phone":"+49 9321/4686",
    "sg:postcode":"97318",
    "sg:province":"Bayern",
    "wof:name":"Deutsches Fastnachtmuseum",
    "wof:placetype":"venue"
},
  "geometry": {"coordinates":[10.159213,49.736191],"type":"Point"}
}