{
  "type": "Feature",
  "properties": {
    "iso:country":"DE",
    "sg:address":"Im Dosenwald 3",
    "sg:city":"Dossenheim",
    "sg:phone":"+49 6221/866608",
    "sg:postcode":"69221",
    "sg:province":"Baden-W\u00fcrttemberg",
    "wof:name":"Herbert Schr\u00f6der",
    "wof:placetype":"venue"
},
  "geometry": {"coordinates":[8.649426,49.457909],"type":"Point"}
}