{
  "type": "Feature",
  "properties": {
    "iso:country":"DE",
    "sg:address":"Lilistr. 83b",
    "sg:city":"Offenbach",
    "sg:phone":"+49 69/8007760",
    "sg:postcode":"63067",
    "sg:province":"Hessen",
    "wof:name":"D\u00f6tsch & Reith Konzept Pro Raum Gmbh",
    "wof:placetype":"venue"
},
  "geometry": {"coordinates":[8.7460050583,50.1117897034],"type":"Point"}
}