{
  "type": "Feature",
  "properties": {
    "iso:country":"DE",
    "sg:address":"Tongrubenweg 4",
    "sg:city":"Neustadt",
    "sg:phone":"+49 9161/60851",
    "sg:postcode":"91413",
    "sg:province":"Bayern",
    "wof:name":"Manfred Beyer",
    "wof:placetype":"venue"
},
  "geometry": {"coordinates":[10.593797,49.572052],"type":"Point"}
}