{
  "type": "Feature",
  "properties": {
    "iso:country":"DE",
    "sg:address":"Birkenweg 7",
    "sg:city":"Kirchberg",
    "sg:phone":"+49 7354/569",
    "sg:postcode":"88486",
    "sg:province":"Baden-W\u00fcrttemberg",
    "wof:name":"E. Schedel Gmbh Bautischlerei",
    "wof:placetype":"venue"
},
  "geometry": {"coordinates":[6.349405,50.897125],"type":"Point"}
}