{
  "type": "Feature",
  "properties": {
    "iso:country":"DE",
    "sg:address":"Schortentalstr. 24",
    "sg:city":"Heideland",
    "sg:phone":"+49 36691/7220",
    "sg:postcode":"07613",
    "sg:province":"Th\u00fcringen",
    "wof:name":"Bauelemente Gmbh F. J. Linzmeier",
    "wof:placetype":"venue"
},
  "geometry": {"coordinates":[11.90781,50.990898],"type":"Point"}
}