{
  "type": "Feature",
  "properties": {
    "iso:country":"DE",
    "sg:address":"Donaustr. 116",
    "sg:city":"Berlin",
    "sg:phone":"+49 30/6245728",
    "sg:postcode":"12043",
    "sg:province":"Berlin",
    "wof:name":"Todzi Und Schult Partnerschaftsgesellschaft",
    "wof:placetype":"venue"
},
  "geometry": {"coordinates":[13.4333820343,52.4836273193],"type":"Point"}
}