{
  "type": "Feature",
  "properties": {
    "iso:country":"DE",
    "sg:address":"Flacken 2",
    "sg:city":"Nordrach",
    "sg:phone":"+49 7838/334",
    "sg:postcode":"77787",
    "sg:province":"Baden-W\u00fcrttemberg",
    "wof:name":"Georg Bruder",
    "wof:placetype":"venue"
},
  "geometry": {"coordinates":[8.099031,48.390656],"type":"Point"}
}