{
  "type": "Feature",
  "properties": {
    "iso:country":"DE",
    "sg:address":"Kirchwerder Elbdeich 38",
    "sg:city":"Hamburg",
    "sg:phone":"+49 40/7230302",
    "sg:postcode":"21037",
    "sg:province":"Hamburg",
    "wof:name":"Hermann Busch",
    "wof:placetype":"venue"
},
  "geometry": {"coordinates":[10.177501,53.400364],"type":"Point"}
}