{
  "type": "Feature",
  "properties": {
    "iso:country":"DE",
    "sg:address":"Sepp-Stra\u00dfberger-Str. 16",
    "sg:city":"Kolbermoor",
    "sg:phone":"+49 8031/94629",
    "sg:postcode":"83059",
    "sg:province":"Bayern",
    "wof:name":"Stefan Kosek",
    "wof:placetype":"venue"
},
  "geometry": {"coordinates":[12.0515594482,47.8400497437],"type":"Point"}
}