{
  "type": "Feature",
  "properties": {
    "iso:country":"DE",
    "sg:address":"Am Jungbornpark 196a",
    "sg:city":"Moers",
    "sg:phone":"+49 2841/76074",
    "sg:postcode":"47445",
    "sg:province":"Nordrhein-Westfalen",
    "wof:name":"F. P. Bleckmann",
    "wof:placetype":"venue"
},
  "geometry": {"coordinates":[6.606845,51.486202],"type":"Point"}
}