{
  "type": "Feature",
  "properties": {
    "iso:country":"DE",
    "sg:address":"Oberneul 1",
    "sg:city":"Aichach",
    "sg:phone":"+49 8251/895961",
    "sg:postcode":"86551",
    "sg:province":"Bayern",
    "wof:name":"Tecpro Kg",
    "wof:placetype":"venue"
},
  "geometry": {"coordinates":[11.0865850449,48.4086990356],"type":"Point"}
}