{
  "type": "Feature",
  "properties": {
    "iso:country":"DE",
    "sg:address":"G\u00f6ttinger Landstr. 4 - 6",
    "sg:city":"Hann. M\u00fcnden",
    "sg:phone":"+49 5541/98220",
    "sg:postcode":"34346",
    "sg:province":"Niedersachsen",
    "wof:name":"Wmu Weser Metall- Umformtechnik Gmbh",
    "wof:placetype":"venue"
},
  "geometry": {"coordinates":[9.64531,51.424759],"type":"Point"}
}