{
  "type": "Feature",
  "properties": {
    "iso:country":"DE",
    "sg:address":"Im Gr\u00fcnen Winkel 13",
    "sg:city":"H\u00fcllhorst",
    "sg:phone":"+49 5744/2145",
    "sg:postcode":"32609",
    "sg:province":"Nordrhein-Westfalen",
    "wof:name":"Ernst Wudke",
    "wof:placetype":"venue"
},
  "geometry": {"coordinates":[8.677717,52.291264],"type":"Point"}
}