{
  "type": "Feature",
  "properties": {
    "iso:country":"DE",
    "sg:address":"Sonnenbergstr. 13",
    "sg:city":"Fr\u00f6ndenberg",
    "sg:phone":"+49 2378/2289",
    "sg:postcode":"58730",
    "sg:province":"Nordrhein-Westfalen",
    "wof:name":"Hans-dieter Babusch",
    "wof:placetype":"venue"
},
  "geometry": {"coordinates":[7.715777874,51.4750099182],"type":"Point"}
}