{
  "type": "Feature",
  "properties": {
    "iso:country":"DE",
    "sg:address":"Am Wemholz 2",
    "sg:city":"Berchtesgaden",
    "sg:phone":"+49 8652/5429",
    "sg:postcode":"83471",
    "sg:province":"Bayern",
    "wof:name":"Hotel Binderh\u00e4usl Inh. Anton Lenz",
    "wof:placetype":"venue"
},
  "geometry": {"coordinates":[13.0001821518,47.6227149963],"type":"Point"}
}