{
  "type": "Feature",
  "properties": {
    "iso:country":"DE",
    "sg:address":"Am Strauch 41",
    "sg:city":"Hilden",
    "sg:phone":"+49 2103/64867",
    "sg:postcode":"40723",
    "sg:province":"Nordrhein-Westfalen",
    "wof:name":"Lutz Bellack",
    "wof:placetype":"venue"
},
  "geometry": {"coordinates":[6.9475631714,51.1555976868],"type":"Point"}
}