{
  "type": "Feature",
  "properties": {
    "iso:country":"DE",
    "sg:address":"Franzensbader Str. 41",
    "sg:city":"Kaufbeuren",
    "sg:phone":"+49 8341/64317",
    "sg:postcode":"87600",
    "sg:province":"Bayern",
    "wof:name":"K. Schlumps Steuerberater",
    "wof:placetype":"venue"
},
  "geometry": {"coordinates":[10.6333856583,47.9109916687],"type":"Point"}
}