{
  "type": "Feature",
  "properties": {
    "iso:country":"DE",
    "sg:address":"Niederdorfstr. 10",
    "sg:city":"Sch\u00f6nbach",
    "sg:postcode":"02708",
    "sg:province":"Sachsen",
    "wof:name":"Evangelisches Pfarramt",
    "wof:placetype":"venue"
},
  "geometry": {"coordinates":[14.5750331879,51.0612030029],"type":"Point"}
}