{
  "type": "Feature",
  "properties": {
    "iso:country":"DE",
    "sg:address":"Brandenburgische Str. 38",
    "sg:city":"Berlin",
    "sg:phone":"+49 30/8916706",
    "sg:postcode":"10707",
    "sg:province":"Berlin",
    "wof:name":"Wulf Eichst\u00e4dt Architekt",
    "wof:placetype":"venue"
},
  "geometry": {"coordinates":[13.307314,52.497913],"type":"Point"}
}