{
  "type": "Feature",
  "properties": {
    "iso:country":"DE",
    "sg:address":"Hellsberg",
    "sg:city":"Niedertaufkirchen",
    "sg:phone":"+49 8724/8727",
    "sg:postcode":"84494",
    "sg:province":"Bayern",
    "wof:name":"Anton Heizinger",
    "wof:placetype":"venue"
},
  "geometry": {"coordinates":[12.591517,48.383068],"type":"Point"}
}