{
  "type": "Feature",
  "properties": {
    "iso:country":"DE",
    "sg:address":"Dorfplatz 7",
    "sg:city":"Bad Wiessee",
    "sg:phone":"+49 8022/81146",
    "sg:postcode":"83707",
    "sg:province":"Bayern",
    "wof:name":"G\u00e4stehaus Josef Beil",
    "wof:placetype":"venue"
},
  "geometry": {"coordinates":[11.7322731018,47.7090950012],"type":"Point"}
}