{
  "type": "Feature",
  "properties": {
    "iso:country":"DE",
    "sg:address":"Achalmstr. 31",
    "sg:city":"Nagold",
    "sg:phone":"+49 7459/605",
    "sg:postcode":"72202",
    "sg:province":"Baden-W\u00fcrttemberg",
    "wof:name":"Wilhelm Katz",
    "wof:placetype":"venue"
},
  "geometry": {"coordinates":[8.7256202698,48.4994735718],"type":"Point"}
}