{
  "type": "Feature",
  "properties": {
    "iso:country":"DE",
    "sg:address":"Blumental 26",
    "sg:city":"K\u00f6ln",
    "sg:phone":"+49 2233/22946",
    "sg:postcode":"50997",
    "sg:province":"Nordrhein-Westfalen",
    "wof:name":"Hoeschler Kg",
    "wof:placetype":"venue"
},
  "geometry": {"coordinates":[6.966766,50.879173],"type":"Point"}
}