{
  "type": "Feature",
  "properties": {
    "iso:country":"DE",
    "sg:address":"Immermannstr. 9",
    "sg:city":"D\u00fcsseldorf",
    "sg:postcode":"40210",
    "sg:province":"Nordrhein-Westfalen",
    "wof:name":"S\u00fcddeutsche Bodencreditbank Ag",
    "wof:placetype":"venue"
},
  "geometry": {"coordinates":[11.572275,48.143456],"type":"Point"}
}