{
  "type": "Feature",
  "properties": {
    "iso:country":"DE",
    "sg:address":"Mozartstr. 9",
    "sg:city":"Starnberg",
    "sg:phone":"+49 8151/12796",
    "sg:postcode":"82319",
    "sg:province":"Bayern",
    "wof:name":"Erika Schalper Architektin",
    "wof:placetype":"venue"
},
  "geometry": {"coordinates":[11.319019,47.991787],"type":"Point"}
}