{
  "type": "Feature",
  "properties": {
    "iso:country":"DE",
    "sg:address":"Schleswiger Str. 5",
    "sg:city":"S\u00f6rup",
    "sg:phone":"+49 4635/2270",
    "sg:postcode":"24966",
    "sg:province":"Schleswig-Holstein",
    "wof:name":"Manfred Ketelsen",
    "wof:placetype":"venue"
},
  "geometry": {"coordinates":[9.6695756912,54.7143821716],"type":"Point"}
}