{
  "type": "Feature",
  "properties": {
    "iso:country":"DE",
    "sg:address":"07937",
    "sg:city":"Zeulenroda",
    "sg:postcode":"07937",
    "sg:province":"Th\u00fcringen",
    "wof:name":"Raiffeisenbank Auma-zeulenroda Eg",
    "wof:placetype":"venue"
},
  "geometry": {"coordinates":[11.9908,50.631458],"type":"Point"}
}