{
  "type": "Feature",
  "properties": {
    "iso:country":"DE",
    "sg:address":"Bockenheimer Landstr. 23",
    "sg:city":"Frankfurt",
    "sg:postcode":"60325",
    "sg:province":"Hessen",
    "wof:name":"Dubai Commerce And Tourism Promotion Board",
    "wof:placetype":"venue"
},
  "geometry": {"coordinates":[8.668003,50.116047],"type":"Point"}
}