{
  "type": "Feature",
  "properties": {
    "iso:country":"DE",
    "sg:address":"Daimlerstr. 10",
    "sg:city":"\u00dcbach-Palenberg",
    "sg:phone":"+49 2451/41430",
    "sg:postcode":"52531",
    "sg:province":"Nordrhein-Westfalen",
    "wof:name":"J. Wilbrand",
    "wof:placetype":"venue"
},
  "geometry": {"coordinates":[6.1310977936,50.918182373],"type":"Point"}
}