{
  "type": "Feature",
  "properties": {
    "iso:country":"DE",
    "sg:address":"Thomas-M\u00fcntzer-Str.",
    "sg:city":"Lobst\u00e4dt",
    "sg:phone":"+49 3433/4818",
    "sg:postcode":"04552",
    "sg:province":"Sachsen",
    "wof:name":"Wolfgang Marx",
    "wof:placetype":"venue"
},
  "geometry": {"coordinates":[12.4355382919,51.1576919556],"type":"Point"}
}