{
  "type": "Feature",
  "properties": {
    "iso:country":"DE",
    "sg:address":"Neuhof 2",
    "sg:city":"Wernshausen",
    "sg:phone":"+49 36848/80757",
    "sg:postcode":"98590",
    "sg:province":"Th\u00fcringen",
    "wof:name":"T. Kassel",
    "wof:placetype":"venue"
},
  "geometry": {"coordinates":[10.352546,50.723503],"type":"Point"}
}