{
  "type": "Feature",
  "properties": {
    "iso:country":"DE",
    "sg:address":"Zerbster Chaussee 10",
    "sg:city":"Burg",
    "sg:phone":"+49 3921/93070",
    "sg:postcode":"39288",
    "sg:province":"Sachsen-Anhalt",
    "wof:name":"Agrarhof Gmbh",
    "wof:placetype":"venue"
},
  "geometry": {"coordinates":[11.8656673431,52.2580108643],"type":"Point"}
}