{
  "type": "Feature",
  "properties": {
    "iso:country":"DE",
    "sg:address":"Bahnhofstr. 13",
    "sg:city":"Altd\u00f6bern",
    "sg:phone":"+49 35434/207",
    "sg:postcode":"03229",
    "sg:province":"Brandenburg",
    "wof:name":"Rainer Fuchs",
    "wof:placetype":"venue"
},
  "geometry": {"coordinates":[14.016579,51.652145],"type":"Point"}
}