{
  "type": "Feature",
  "properties": {
    "iso:country":"DE",
    "sg:address":"Alsstr. 264",
    "sg:city":"M\u00f6nchengladbach",
    "sg:phone":"+49 2161/13096",
    "sg:postcode":"41063",
    "sg:province":"Nordrhein-Westfalen",
    "wof:name":"Sh Verwaltungs Gmbh",
    "wof:placetype":"venue"
},
  "geometry": {"coordinates":[6.45975,51.209202],"type":"Point"}
}