{
  "type": "Feature",
  "properties": {
    "iso:country":"DE",
    "sg:address":"Venloer Str. 42",
    "sg:city":"Straelen",
    "sg:phone":"+49 2834/8427",
    "sg:postcode":"47638",
    "sg:province":"Nordrhein-Westfalen",
    "wof:name":"Vendelse Poort",
    "wof:placetype":"venue"
},
  "geometry": {"coordinates":[6.2652249336,51.4422988892],"type":"Point"}
}