{
  "type": "Feature",
  "properties": {
    "iso:country":"DE",
    "sg:address":"Saarstr. 21 A",
    "sg:city":"Niederkirchen",
    "sg:phone":"+49 6326/6397",
    "sg:postcode":"67150",
    "sg:province":"Rheinland-Pfalz",
    "wof:name":"Antonius Und Ingeborg Andres",
    "wof:placetype":"venue"
},
  "geometry": {"coordinates":[8.2090797424,49.413318634],"type":"Point"}
}