{
  "type": "Feature",
  "properties": {
    "iso:country":"DE",
    "sg:address":"Gertrudenstr. 21",
    "sg:city":"K\u00f6ln",
    "sg:postcode":"50667",
    "sg:province":"Nordrhein-Westfalen",
    "wof:name":"Bpc Bau- Und Planungs- Consulting Gmbh",
    "wof:placetype":"venue"
},
  "geometry": {"coordinates":[6.9454388618,50.9375],"type":"Point"}
}