{
  "type": "Feature",
  "properties": {
    "iso:country":"DE",
    "sg:address":"Werneweg 95",
    "sg:city":"M\u00fcnster",
    "sg:phone":"+49 251/785655",
    "sg:postcode":"48163",
    "sg:province":"Nordrhein-Westfalen",
    "wof:name":"Gerhard Popp Heissmangel",
    "wof:placetype":"venue"
},
  "geometry": {"coordinates":[7.5998210907,51.924987793],"type":"Point"}
}