{
  "type": "Feature",
  "properties": {
    "iso:country":"DE",
    "sg:address":"Oberbachstr. 22",
    "sg:city":"Cochem",
    "sg:phone":"+49 2671/7224",
    "sg:postcode":"56812",
    "sg:province":"Rheinland-Pfalz",
    "wof:name":"M. Becker",
    "wof:placetype":"venue"
},
  "geometry": {"coordinates":[7.164658,50.145214],"type":"Point"}
}