{
  "type": "Feature",
  "properties": {
    "iso:country":"DE",
    "sg:address":"Pappelallee 29",
    "sg:city":"Seddiner See",
    "sg:phone":"+49 33205/7190",
    "sg:postcode":"14554",
    "sg:province":"Brandenburg",
    "wof:name":"Fun City Gmbh",
    "wof:placetype":"venue"
},
  "geometry": {"coordinates":[13.003037,52.287167],"type":"Point"}
}