{
  "type": "Feature",
  "properties": {
    "iso:country":"DE",
    "sg:address":"Am Stra\u00dfbach 5",
    "sg:city":"Friedberg",
    "sg:phone":"+49 6031/71220",
    "sg:postcode":"61169",
    "sg:province":"Hessen",
    "wof:name":"Expo-werbe-group Gmbh",
    "wof:placetype":"venue"
},
  "geometry": {"coordinates":[8.748298645,50.319065094],"type":"Point"}
}