{
  "type": "Feature",
  "properties": {
    "iso:country":"DE",
    "sg:address":"Kinzigstr. 11",
    "sg:city":"Langenselbold",
    "sg:postcode":"63505",
    "sg:province":"Hessen",
    "wof:name":"Tsb Tanzschulen Betriebs Gmbh",
    "wof:placetype":"venue"
},
  "geometry": {"coordinates":[9.0450305939,50.1741333008],"type":"Point"}
}