{
  "type": "Feature",
  "properties": {
    "iso:country":"DE",
    "sg:address":"Am Musebieter 34",
    "sg:city":"Attendorn",
    "sg:phone":"+49 2722/5642",
    "sg:postcode":"57439",
    "sg:province":"Nordrhein-Westfalen",
    "wof:name":"Alfred Bruse",
    "wof:placetype":"venue"
},
  "geometry": {"coordinates":[7.8935599327,51.1298980713],"type":"Point"}
}