{
  "type": "Feature",
  "properties": {
    "iso:country":"DE",
    "sg:address":"Zum Kap 2",
    "sg:city":"Dautphetal",
    "sg:phone":"+49 6468/261",
    "sg:postcode":"35232",
    "sg:province":"Hessen",
    "wof:name":"Manfred Wege",
    "wof:placetype":"venue"
},
  "geometry": {"coordinates":[8.507434,50.846447],"type":"Point"}
}