{
  "type": "Feature",
  "properties": {
    "iso:country":"DE",
    "sg:address":"Dresdener Str. 21 a",
    "sg:city":"Luckau",
    "sg:postcode":"15926",
    "sg:province":"Brandenburg",
    "wof:name":"M\u00f6bel Michaelis Gmbh & Co. Kg",
    "wof:placetype":"venue"
},
  "geometry": {"coordinates":[13.6979236603,51.8441886902],"type":"Point"}
}