{
  "type": "Feature",
  "properties": {
    "iso:country":"DE",
    "sg:address":"Friedrichstrasse 200",
    "sg:city":"Berlin",
    "sg:phone":"+49 30/22334451",
    "sg:postcode":"10117",
    "sg:province":"Berlin",
    "wof:name":"Stefan A. Kosche Seminare Kommunikation & Vertriebsberatung",
    "wof:placetype":"venue"
},
  "geometry": {"coordinates":[13.389925,52.508999],"type":"Point"}
}