{
  "type": "Feature",
  "properties": {
    "iso:country":"DE",
    "sg:address":"Buchklinger Str. 12",
    "sg:city":"Birkenau",
    "sg:phone":"+49 6201/24234",
    "sg:postcode":"69488",
    "sg:province":"Hessen",
    "wof:name":"Am Metallbau Gmbh",
    "wof:placetype":"venue"
},
  "geometry": {"coordinates":[8.74752,49.546211],"type":"Point"}
}