{
  "type": "Feature",
  "properties": {
    "iso:country":"DE",
    "sg:address":"Heimkehr 18",
    "sg:city":"Dresden",
    "sg:postcode":"01169",
    "sg:province":"Sachsen",
    "wof:name":"Dr. Med. Norbert Grosche",
    "wof:placetype":"venue"
},
  "geometry": {"coordinates":[13.671943,51.037449],"type":"Point"}
}