{
  "type": "Feature",
  "properties": {
    "iso:country":"DE",
    "sg:address":"Bahnhofstr. 28",
    "sg:city":"Weinsberg",
    "sg:phone":"+49 7134/6500",
    "sg:postcode":"74189",
    "sg:province":"Baden-W\u00fcrttemberg",
    "wof:name":"R\u00f6mer-apotheke",
    "wof:placetype":"venue"
},
  "geometry": {"coordinates":[9.287752,49.149624],"type":"Point"}
}