{
  "type": "Feature",
  "properties": {
    "iso:country":"DE",
    "sg:address":"Finkenweg 13",
    "sg:city":"Salem",
    "sg:phone":"+49 7554/8701",
    "sg:postcode":"88682",
    "sg:province":"Baden-W\u00fcrttemberg",
    "wof:name":"Wilfried Matthias Krankengymnast",
    "wof:placetype":"venue"
},
  "geometry": {"coordinates":[9.325423,47.799278],"type":"Point"}
}