{
  "type": "Feature",
  "properties": {
    "iso:country":"DE",
    "sg:address":"Am Anger 6",
    "sg:city":"Gro\u00dfm\u00fchlingen",
    "sg:phone":"+49 39297/20336",
    "sg:postcode":"39221",
    "sg:province":"Sachsen-Anhalt",
    "wof:name":"Bernd Ebeling",
    "wof:placetype":"venue"
},
  "geometry": {"coordinates":[11.705811,51.955845],"type":"Point"}
}