{
  "type": "Feature",
  "properties": {
    "iso:country":"DE",
    "sg:address":"Josephsplatz 14-16",
    "sg:city":"N\u00fcrnberg",
    "sg:phone":"+49 911/243104",
    "sg:postcode":"90403",
    "sg:province":"Bayern",
    "wof:name":"Delphi-palast",
    "wof:placetype":"venue"
},
  "geometry": {"coordinates":[11.073446,49.451614],"type":"Point"}
}