{
  "type": "Feature",
  "properties": {
    "iso:country":"DE",
    "sg:address":"Steinbruchstr. 7",
    "sg:city":"Rammelsbach",
    "sg:phone":"+49 6381/2104",
    "sg:postcode":"66887",
    "sg:province":"Rheinland-Pfalz",
    "wof:name":"Friedhelm Bangert",
    "wof:placetype":"venue"
},
  "geometry": {"coordinates":[7.4463248253,49.5425796509],"type":"Point"}
}