{
  "type": "Feature",
  "properties": {
    "iso:country":"DE",
    "sg:address":"Karl-Arnold-Str. 8",
    "sg:city":"Willich",
    "sg:phone":"+49 2154/92260",
    "sg:postcode":"47877",
    "sg:province":"Nordrhein-Westfalen",
    "wof:name":"Great Plains Deutschland Gmbh & Co. Kg",
    "wof:placetype":"venue"
},
  "geometry": {"coordinates":[6.5201869011,51.2755775452],"type":"Point"}
}