{
  "type": "Feature",
  "properties": {
    "iso:country":"DE",
    "sg:address":"Buchbergstr. 36",
    "sg:city":"R\u00fcckersdorf",
    "sg:postcode":"90607",
    "sg:province":"Bayern",
    "wof:name":"Abc Wertstoffrecycling Gmbh",
    "wof:placetype":"venue"
},
  "geometry": {"coordinates":[11.2465400696,49.4999313354],"type":"Point"}
}