{
  "type": "Feature",
  "properties": {
    "iso:country":"DE",
    "sg:address":"Hansastr. 73",
    "sg:city":"R\u00f6dinghausen",
    "sg:phone":"+49 5746/8141",
    "sg:postcode":"32289",
    "sg:province":"Nordrhein-Westfalen",
    "wof:name":"E. Bauer",
    "wof:placetype":"venue"
},
  "geometry": {"coordinates":[8.535526,52.23774],"type":"Point"}
}