{
  "type": "Feature",
  "properties": {
    "iso:country":"DE",
    "sg:address":"Hallerbacher Str. 23",
    "sg:city":"Windhagen",
    "sg:postcode":"53578",
    "sg:province":"Rheinland-Pfalz",
    "wof:name":"Fair To Fair Harald Basczok E. K.",
    "wof:placetype":"venue"
},
  "geometry": {"coordinates":[7.34281,50.63118],"type":"Point"}
}