{
  "type": "Feature",
  "properties": {
    "iso:country":"DE",
    "sg:address":"Olbernhauer Str. 55",
    "sg:city":"Freiberg",
    "sg:phone":"+49 3731/798930",
    "sg:postcode":"09599",
    "sg:province":"Sachsen",
    "wof:name":"Starkstromanlagenbaufreiberg Gmbh",
    "wof:placetype":"venue"
},
  "geometry": {"coordinates":[13.336958,50.906693],"type":"Point"}
}