{
  "type": "Feature",
  "properties": {
    "iso:country":"DE",
    "sg:address":"Kortumstr. 23",
    "sg:city":"Bochum",
    "sg:phone":"+49 234/961420",
    "sg:postcode":"44787",
    "sg:province":"Nordrhein-Westfalen",
    "wof:name":"Foto Hamer Verwaltungs Gmbh",
    "wof:placetype":"venue"
},
  "geometry": {"coordinates":[7.216563,51.477608],"type":"Point"}
}