{
  "type": "Feature",
  "properties": {
    "iso:country":"DE",
    "sg:address":"Uferstr. 32",
    "sg:city":"Gaienhofen",
    "sg:phone":"+49 7735/3431",
    "sg:postcode":"78343",
    "sg:province":"Baden-W\u00fcrttemberg",
    "wof:name":"Andy's Paradies Cafe Bistro",
    "wof:placetype":"venue"
},
  "geometry": {"coordinates":[8.970615,47.672291],"type":"Point"}
}