{
  "type": "Feature",
  "properties": {
    "iso:country":"DE",
    "sg:address":"Bahnhofstr.",
    "sg:city":"Marsberg",
    "sg:phone":"+49 2992/725",
    "sg:postcode":"34431",
    "sg:province":"Nordrhein-Westfalen",
    "wof:name":"Raiffeisen-marsberg Eg",
    "wof:placetype":"venue"
},
  "geometry": {"coordinates":[8.85662,51.462929],"type":"Point"}
}