{
  "type": "Feature",
  "properties": {
    "iso:country":"DE",
    "sg:address":"Markt 19",
    "sg:city":"Teuchern",
    "sg:phone":"+49 34443/6080",
    "sg:postcode":"06682",
    "sg:province":"Sachsen-Anhalt",
    "wof:name":"Gesa Proze\u00dfautomation Gmbh",
    "wof:placetype":"venue"
},
  "geometry": {"coordinates":[12.021783,51.120087],"type":"Point"}
}