{
  "type": "Feature",
  "properties": {
    "iso:country":"DE",
    "sg:address":"Joseph-Haas-Weg 6",
    "sg:city":"N\u00f6rdlingen",
    "sg:postcode":"86720",
    "sg:province":"Bayern",
    "wof:name":"Kino N\u00f6rdlingen",
    "wof:placetype":"venue"
},
  "geometry": {"coordinates":[10.495168,48.848206],"type":"Point"}
}