{
  "type": "Feature",
  "properties": {
    "iso:country":"DE",
    "sg:address":"Gleinaer Str. 44",
    "sg:city":"Zeitz",
    "sg:phone":"+49 3441/769030",
    "sg:postcode":"06712",
    "sg:province":"Sachsen-Anhalt",
    "wof:name":"Blumen-pitzschler Inh. Edwin Pitzschler",
    "wof:placetype":"venue"
},
  "geometry": {"coordinates":[12.14777,51.045448],"type":"Point"}
}