{
  "type": "Feature",
  "properties": {
    "iso:country":"DE",
    "sg:address":"Asternstr. 6",
    "sg:city":"Garbsen",
    "sg:phone":"+49 5131/7411",
    "sg:postcode":"30827",
    "sg:province":"Niedersachsen",
    "wof:name":"K. H. Linsel",
    "wof:placetype":"venue"
},
  "geometry": {"coordinates":[9.600112,52.436432],"type":"Point"}
}