{
  "type": "Feature",
  "properties": {
    "iso:country":"DE",
    "sg:address":"D\u00f6rfles 7",
    "sg:city":"Kronach",
    "sg:phone":"+49 9261/64869",
    "sg:postcode":"96317",
    "sg:province":"Bayern",
    "wof:name":"Wagner Entsorgung Und Recycling Gmbh",
    "wof:placetype":"venue"
},
  "geometry": {"coordinates":[11.3476295471,50.2590103149],"type":"Point"}
}