{
  "type": "Feature",
  "properties": {
    "iso:country":"DE",
    "sg:address":"Stiftstr. 7",
    "sg:city":"Lorsch",
    "sg:phone":"+49 6251/55822",
    "sg:postcode":"64653",
    "sg:province":"Hessen",
    "wof:name":"Stiftsch\u00e4nke",
    "wof:placetype":"venue"
},
  "geometry": {"coordinates":[8.5655994415,49.6522598267],"type":"Point"}
}