{
  "type": "Feature",
  "properties": {
    "iso:country":"DE",
    "sg:address":"Inneboltstr. 118",
    "sg:city":"Neukirchen-Vluyn",
    "sg:phone":"+49 2845/91430",
    "sg:postcode":"47506",
    "sg:province":"Nordrhein-Westfalen",
    "wof:name":"D. I. E. Reisen Veranstaltungs-gmbh",
    "wof:placetype":"venue"
},
  "geometry": {"coordinates":[6.543088,51.432899],"type":"Point"}
}