{
  "type": "Feature",
  "properties": {
    "iso:country":"DE",
    "sg:address":"Bussardstr. 8",
    "sg:city":"Gr\u00e4felfing",
    "sg:phone":"+49 89/8980700",
    "sg:postcode":"82166",
    "sg:province":"Bayern",
    "wof:name":"J\u00fcrgen Doerner Industrievertretungen Gmbh",
    "wof:placetype":"venue"
},
  "geometry": {"coordinates":[11.445640564,48.1171112061],"type":"Point"}
}