{
  "type": "Feature",
  "properties": {
    "iso:country":"DE",
    "sg:address":"Hermeskeiler Str. 21",
    "sg:city":"Wadern",
    "sg:phone":"+49 6871/8100",
    "sg:postcode":"66687",
    "sg:province":"Saarland",
    "wof:name":"F. Nickels",
    "wof:placetype":"venue"
},
  "geometry": {"coordinates":[6.890119,49.583267],"type":"Point"}
}