{
  "type": "Feature",
  "properties": {
    "iso:country":"DE",
    "sg:address":"Groten Heesen 40",
    "sg:city":"Hamburg",
    "sg:phone":"+49 40/7302668",
    "sg:postcode":"21033",
    "sg:province":"Hamburg",
    "wof:name":"Rainer Sylvester Gmbh",
    "wof:placetype":"venue"
},
  "geometry": {"coordinates":[10.1736268997,53.5095939636],"type":"Point"}
}