{
  "type": "Feature",
  "properties": {
    "iso:country":"DE",
    "sg:address":"Sichartstr. 5 - 25",
    "sg:city":"Lauf a.d. Pegnitz",
    "sg:phone":"+49 9123/184118",
    "sg:postcode":"91207",
    "sg:province":"Bayern",
    "wof:name":"Industriemuseum Lauf A.d. Pegnitz",
    "wof:placetype":"venue"
},
  "geometry": {"coordinates":[11.277961,49.509785],"type":"Point"}
}