{
  "type": "Feature",
  "properties": {
    "iso:country":"DE",
    "sg:address":"Asamstr. 6",
    "sg:city":"M\u00fcnchen",
    "sg:phone":"+49 89/21579100",
    "sg:postcode":"81541",
    "sg:province":"Bayern",
    "wof:name":"Food Solutions Knophius Gmbh",
    "wof:placetype":"venue"
},
  "geometry": {"coordinates":[11.5784158707,48.1253356934],"type":"Point"}
}