{
  "type": "Feature",
  "properties": {
    "iso:country":"DE",
    "sg:address":"Albert-Schweitzer-Str. 6",
    "sg:city":"Tuttlingen",
    "sg:phone":"+49 7461/2781",
    "sg:postcode":"78532",
    "sg:province":"Baden-W\u00fcrttemberg",
    "wof:name":"Chr. Teufel Sohn Gmbh",
    "wof:placetype":"venue"
},
  "geometry": {"coordinates":[8.8299531937,47.9800758362],"type":"Point"}
}