{
  "type": "Feature",
  "properties": {
    "iso:country":"DE",
    "sg:address":"Langenstr. 57",
    "sg:city":"Stralsund",
    "sg:phone":"+49 3831/280254",
    "sg:postcode":"18439",
    "sg:province":"Mecklenburg-Vorpommern",
    "wof:name":"Max Schmidt",
    "wof:placetype":"venue"
},
  "geometry": {"coordinates":[13.0926952362,54.3126754761],"type":"Point"}
}