{
  "type": "Feature",
  "properties": {
    "iso:country":"DE",
    "sg:address":"Talstr. 13/2",
    "sg:city":"Kirchheim",
    "sg:postcode":"74366",
    "sg:province":"Baden-W\u00fcrttemberg",
    "wof:name":"K\u00f6rner Blattert Und Partner Freie Architeketen",
    "wof:placetype":"venue"
},
  "geometry": {"coordinates":[9.139559,49.04232],"type":"Point"}
}