{
  "type": "Feature",
  "properties": {
    "iso:country":"DE",
    "sg:address":"Fivchtenweg 4",
    "sg:city":"Lichtenstein",
    "sg:phone":"+49 7122/9359",
    "sg:postcode":"72805",
    "sg:province":"Baden-W\u00fcrttemberg",
    "wof:name":"Ltv- Disco- Und Showtechnik",
    "wof:placetype":"venue"
},
  "geometry": {"coordinates":[9.25546,48.433559],"type":"Point"}
}