{
  "type": "Feature",
  "properties": {
    "iso:country":"DE",
    "sg:address":"Kampenwandstr. 21",
    "sg:city":"Schleching",
    "sg:phone":"+49 8649/651",
    "sg:postcode":"83259",
    "sg:province":"Bayern",
    "wof:name":"Hans Aigner Gmbh",
    "wof:placetype":"venue"
},
  "geometry": {"coordinates":[12.4066123962,47.7267913818],"type":"Point"}
}