{
  "type": "Feature",
  "properties": {
    "iso:country":"DE",
    "sg:address":"Oberdorf 1 a",
    "sg:city":"Bad Sachsa",
    "sg:phone":"+49 5523/93135",
    "sg:postcode":"37441",
    "sg:province":"Niedersachsen",
    "wof:name":"Manfred Schubert",
    "wof:placetype":"venue"
},
  "geometry": {"coordinates":[10.515282,51.595001],"type":"Point"}
}