{
  "type": "Feature",
  "properties": {
    "iso:country":"DE",
    "sg:address":"Rheinauer Str. 19",
    "sg:city":"Br\u00fchl",
    "sg:phone":"+49 6202/71362",
    "sg:postcode":"68782",
    "sg:province":"Baden-W\u00fcrttemberg",
    "wof:name":"Gerda Sauer",
    "wof:placetype":"venue"
},
  "geometry": {"coordinates":[8.522291,49.410599],"type":"Point"}
}