{
  "type": "Feature",
  "properties": {
    "iso:country":"DE",
    "sg:address":"Baumstr. 1",
    "sg:city":"R\u00f6tsweiler-Nockenthal",
    "sg:phone":"+49 6787/1647",
    "sg:postcode":"55767",
    "sg:province":"Rheinland-Pfalz",
    "wof:name":"Herbert Collingro Heilpraktiker",
    "wof:placetype":"venue"
},
  "geometry": {"coordinates":[7.2489061356,49.7139167786],"type":"Point"}
}