{
  "type": "Feature",
  "properties": {
    "iso:country":"DE",
    "sg:address":"Industriestr. 46",
    "sg:city":"F\u00fcrth",
    "sg:postcode":"90765",
    "sg:province":"Bayern",
    "wof:name":"Friedrich-baur- Beteiligungs- Gmbh",
    "wof:placetype":"venue"
},
  "geometry": {"coordinates":[11.003945,49.509769],"type":"Point"}
}