{
  "type": "Feature",
  "properties": {
    "iso:country":"DE",
    "sg:address":"Weingarten 18",
    "sg:city":"Kunreuth",
    "sg:phone":"+49 9199/217",
    "sg:postcode":"91358",
    "sg:province":"Bayern",
    "wof:name":"Fliesen Derbfu\u00df Gmbh",
    "wof:placetype":"venue"
},
  "geometry": {"coordinates":[11.1430664062,49.6838989258],"type":"Point"}
}