{
  "type": "Feature",
  "properties": {
    "iso:country":"DE",
    "sg:address":"Sch\u00fctzenstr. 14",
    "sg:city":"Marktoberdorf",
    "sg:phone":"+49 8342/7979",
    "sg:postcode":"87616",
    "sg:province":"Bayern",
    "wof:name":"G\u00fcnther Schindlbeck Ingenieur",
    "wof:placetype":"venue"
},
  "geometry": {"coordinates":[10.6183309555,47.7758560181],"type":"Point"}
}