{
  "type": "Feature",
  "properties": {
    "iso:country":"DE",
    "sg:address":"Seidelbastweg 133",
    "sg:city":"Berlin",
    "sg:phone":"+49 30/660990",
    "sg:postcode":"12357",
    "sg:province":"Berlin",
    "wof:name":"Stahlhandel Peine-salzgitter Gmbh",
    "wof:placetype":"venue"
},
  "geometry": {"coordinates":[13.492515,52.433094],"type":"Point"}
}