{
  "type": "Feature",
  "properties": {
    "iso:country":"DE",
    "sg:address":"Habichtstr. 25",
    "sg:city":"Lennestadt",
    "sg:phone":"+49 2723/80398",
    "sg:postcode":"57368",
    "sg:province":"Nordrhein-Westfalen",
    "wof:name":"P & S Gmbh",
    "wof:placetype":"venue"
},
  "geometry": {"coordinates":[8.173147,51.125],"type":"Point"}
}