{
  "type": "Feature",
  "properties": {
    "iso:country":"DE",
    "sg:address":"Hochstr. 23",
    "sg:city":"R\u00fcthen",
    "sg:phone":"+49 2952/1634",
    "sg:postcode":"59602",
    "sg:province":"Nordrhein-Westfalen",
    "wof:name":"Monika Lindenau",
    "wof:placetype":"venue"
},
  "geometry": {"coordinates":[8.4334087372,51.489364624],"type":"Point"}
}