{
  "type": "Feature",
  "properties": {
    "iso:country":"DE",
    "sg:address":"Galbrinkstr. 2",
    "sg:city":"Melle",
    "sg:phone":"+49 5428/1324",
    "sg:postcode":"49326",
    "sg:province":"Niedersachsen",
    "wof:name":"Otto Ebert",
    "wof:placetype":"venue"
},
  "geometry": {"coordinates":[8.347314,52.134628],"type":"Point"}
}