{
  "type": "Feature",
  "properties": {
    "iso:country":"DE",
    "sg:address":"Rohrbronner Str. 27",
    "sg:city":"Remshalden",
    "sg:phone":"+49 7181/72092",
    "sg:postcode":"73630",
    "sg:province":"Baden-W\u00fcrttemberg",
    "wof:name":"Lilo Kuhn",
    "wof:placetype":"venue"
},
  "geometry": {"coordinates":[9.4589681625,48.8100585938],"type":"Point"}
}