{
  "type": "Feature",
  "properties": {
    "iso:country":"DE",
    "sg:address":"Kr\u00e4henweg 28b",
    "sg:city":"Hamburg",
    "sg:phone":"+49 40/5520503",
    "sg:postcode":"22459",
    "sg:province":"Hamburg",
    "wof:name":"Greens Plus",
    "wof:placetype":"venue"
},
  "geometry": {"coordinates":[9.958388,53.631969],"type":"Point"}
}