{
  "type": "Feature",
  "properties": {
    "iso:country":"DE",
    "sg:address":"Rotachstr. 63",
    "sg:city":"St\u00f6dtlen",
    "sg:phone":"+49 7964/2291",
    "sg:postcode":"73495",
    "sg:province":"Baden-W\u00fcrttemberg",
    "wof:name":"Friedrich Sindel",
    "wof:placetype":"venue"
},
  "geometry": {"coordinates":[10.34217,49.022869],"type":"Point"}
}