{
  "type": "Feature",
  "properties": {
    "iso:country":"DE",
    "sg:address":"\u00dcberseering 25",
    "sg:city":"Hamburg",
    "sg:phone":"+49 40/6314615",
    "sg:postcode":"22297",
    "sg:province":"Hamburg",
    "wof:name":"Tanzschule Die 2",
    "wof:placetype":"venue"
},
  "geometry": {"coordinates":[10.0247192383,53.6048202515],"type":"Point"}
}