{
  "type": "Feature",
  "properties": {
    "iso:country":"DE",
    "sg:address":"Bundesstr. 79",
    "sg:city":"Friesoythe",
    "sg:phone":"+49 4405/205",
    "sg:postcode":"26169",
    "sg:province":"Niedersachsen",
    "wof:name":"Gerd Wittje",
    "wof:placetype":"venue"
},
  "geometry": {"coordinates":[7.802255,53.056423],"type":"Point"}
}