{
  "type": "Feature",
  "properties": {
    "iso:country":"DE",
    "sg:address":"Siemensstr. 31",
    "sg:city":"Kleve",
    "sg:postcode":"47533",
    "sg:province":"Nordrhein-Westfalen",
    "wof:name":"Inodes Gmbh",
    "wof:placetype":"venue"
},
  "geometry": {"coordinates":[6.137961,51.812122],"type":"Point"}
}