{
  "type": "Feature",
  "properties": {
    "iso:country":"DE",
    "sg:address":"Krischanweg 21",
    "sg:city":"Rostock",
    "sg:phone":"+49 381/8000059",
    "sg:postcode":"18069",
    "sg:province":"Mecklenburg-Vorpommern",
    "wof:name":"Objekteinrichtungen Jaunich & Jaunich Ohg",
    "wof:placetype":"venue"
},
  "geometry": {"coordinates":[12.0751533508,54.1054611206],"type":"Point"}
}