{
  "type": "Feature",
  "properties": {
    "iso:country":"DE",
    "sg:address":"Sulzaer Str. 1",
    "sg:city":"Eckolst\u00e4dt",
    "sg:phone":"+49 36421/22255",
    "sg:postcode":"99510",
    "sg:province":"Th\u00fcringen",
    "wof:name":"D + T Brennstoffe Und Handels Gmbh",
    "wof:placetype":"venue"
},
  "geometry": {"coordinates":[11.509604454,51.0231628418],"type":"Point"}
}