{
  "type": "Feature",
  "properties": {
    "iso:country":"DE",
    "sg:address":"An der Aspe",
    "sg:city":"Gro\u00dfenl\u00fcder",
    "sg:phone":"+49 6648/7403",
    "sg:postcode":"36137",
    "sg:province":"Hessen",
    "wof:name":"N. Ascher",
    "wof:placetype":"venue"
},
  "geometry": {"coordinates":[9.541834,50.583694],"type":"Point"}
}