{
  "type": "Feature",
  "properties": {
    "iso:country":"DE",
    "sg:address":"Pienersallee 54a",
    "sg:city":"M\u00fcnster",
    "sg:phone":"+49 4925/341067",
    "sg:postcode":"48161",
    "sg:province":"Nordrhein-Westfalen",
    "wof:name":"Anton Leuvering E.k.",
    "wof:placetype":"venue"
},
  "geometry": {"coordinates":[7.527625,51.948849],"type":"Point"}
}