{
  "type": "Feature",
  "properties": {
    "iso:country":"DE",
    "sg:address":"Lilienthalstr. 17",
    "sg:city":"Bielefeld",
    "sg:phone":"+49 5205/20738",
    "sg:postcode":"33689",
    "sg:province":"Nordrhein-Westfalen",
    "wof:name":"Taktec Tapezier-anstrich- Und Kunststofftechnik Gmbh",
    "wof:placetype":"venue"
},
  "geometry": {"coordinates":[8.583831,51.957104],"type":"Point"}
}