{
  "type": "Feature",
  "properties": {
    "iso:country":"DE",
    "sg:address":"Waldseestr. 34",
    "sg:city":"Bruchk\u00f6bel",
    "sg:phone":"+49 6181/97720",
    "sg:postcode":"63486",
    "sg:province":"Hessen",
    "wof:name":"Hl-markt",
    "wof:placetype":"venue"
},
  "geometry": {"coordinates":[8.9287881851,50.1770210266],"type":"Point"}
}