{
  "type": "Feature",
  "properties": {
    "iso:country":"DE",
    "sg:address":"Auf dem Brenneick 3 A",
    "sg:city":"Seevetal",
    "sg:postcode":"21220",
    "sg:province":"Niedersachsen",
    "wof:name":"Dr. Hein & Partner Zahn\u00e4rztliche Abrechnungs-",
    "wof:placetype":"venue"
},
  "geometry": {"coordinates":[10.0366945267,53.3377609253],"type":"Point"}
}