{
  "type": "Feature",
  "properties": {
    "iso:country":"DE",
    "sg:address":"Spitalstr. 16",
    "sg:city":"Dieburg",
    "sg:phone":"+49 6071/81252",
    "sg:postcode":"64807",
    "sg:province":"Hessen",
    "wof:name":"Jakob Franz Krimm Orthop\u00e4dieschuhmachermeister",
    "wof:placetype":"venue"
},
  "geometry": {"coordinates":[8.8415117264,49.899143219],"type":"Point"}
}