{
  "type": "Feature",
  "properties": {
    "iso:country":"DE",
    "sg:address":"Hochstr. 57",
    "sg:city":"T\u00f6nisvorst",
    "sg:phone":"+49 2151/970267",
    "sg:postcode":"47918",
    "sg:province":"Nordrhein-Westfalen",
    "wof:name":"Karl Heinz Lessenich",
    "wof:placetype":"venue"
},
  "geometry": {"coordinates":[6.49202,51.322155],"type":"Point"}
}