{
  "type": "Feature",
  "properties": {
    "iso:country":"DE",
    "sg:address":"Industriestr.2",
    "sg:city":"Biebertal-Fellingshausen",
    "sg:phone":"+49 6409/1818",
    "sg:postcode":"35444",
    "sg:province":"Hessen",
    "wof:name":"Freiwillige Feuererwehr Fellingshausen",
    "wof:placetype":"venue"
},
  "geometry": {"coordinates":[8.60032,50.645367],"type":"Point"}
}