{
  "type": "Feature",
  "properties": {
    "iso:country":"DE",
    "sg:address":"Untertor 10",
    "sg:city":"W\u00e4chtersbach",
    "sg:phone":"+49 6053/601432",
    "sg:postcode":"63607",
    "sg:province":"Hessen",
    "wof:name":"Altstadt",
    "wof:placetype":"venue"
},
  "geometry": {"coordinates":[9.2876052856,50.2581634521],"type":"Point"}
}