{
  "type": "Feature",
  "properties": {
    "iso:country":"DE",
    "sg:address":"Bergstr. 59",
    "sg:city":"Trier",
    "sg:phone":"+49 651/47500",
    "sg:postcode":"54295",
    "sg:province":"Rheinland-Pfalz",
    "wof:name":"Karl-heinz Schmitt",
    "wof:placetype":"venue"
},
  "geometry": {"coordinates":[6.650386,49.751385],"type":"Point"}
}