{
  "type": "Feature",
  "properties": {
    "iso:country":"DE",
    "sg:address":"Im Maisel 6",
    "sg:city":"Taunusstein",
    "sg:phone":"+49 6128/972275",
    "sg:postcode":"65232",
    "sg:province":"Hessen",
    "wof:name":"Matithor-internationale Lebensmittel-",
    "wof:placetype":"venue"
},
  "geometry": {"coordinates":[8.2208242416,50.1775093079],"type":"Point"}
}