{
  "type": "Feature",
  "properties": {
    "iso:country":"DE",
    "sg:address":"Pfarrer-Bayer-Str. 8",
    "sg:city":"Eslarn",
    "sg:phone":"+49 9653/267",
    "sg:postcode":"92693",
    "sg:province":"Bayern",
    "wof:name":"Josef H\u00f6lz",
    "wof:placetype":"venue"
},
  "geometry": {"coordinates":[12.522619,49.582996],"type":"Point"}
}