{
  "type": "Feature",
  "properties": {
    "iso:country":"DE",
    "sg:address":"Bremer Landstr. 40",
    "sg:city":"Ritterhude",
    "sg:phone":"+49 4292/2171",
    "sg:postcode":"27721",
    "sg:province":"Niedersachsen",
    "wof:name":"Waltraud Wattenberg",
    "wof:placetype":"venue"
},
  "geometry": {"coordinates":[8.7356090546,53.1827354431],"type":"Point"}
}