{
  "type": "Feature",
  "properties": {
    "iso:country":"DE",
    "sg:address":"Gr\u00fcntal 57",
    "sg:city":"Stadtroda",
    "sg:phone":"+49 36428/60143",
    "sg:postcode":"07646",
    "sg:province":"Th\u00fcringen",
    "wof:name":"Michael Schmidt Rechtsanwalt",
    "wof:placetype":"venue"
},
  "geometry": {"coordinates":[11.7105426788,50.8554115295],"type":"Point"}
}