{
  "type": "Feature",
  "properties": {
    "iso:country":"DE",
    "sg:address":"Am Iberg 2",
    "sg:city":"Willingen",
    "sg:phone":"+49 5632/6381",
    "sg:postcode":"34508",
    "sg:province":"Hessen",
    "wof:name":"Pension Erika Otto-tr\u00f6geler",
    "wof:placetype":"venue"
},
  "geometry": {"coordinates":[8.6159505844,51.2935409546],"type":"Point"}
}