{
  "type": "Feature",
  "properties": {
    "iso:country":"DE",
    "sg:address":"Mozartstr. 15",
    "sg:city":"Geiselh\u00f6ring",
    "sg:phone":"+49 9423/1267",
    "sg:postcode":"94333",
    "sg:province":"Bayern",
    "wof:name":"B. R\u00e4uschl",
    "wof:placetype":"venue"
},
  "geometry": {"coordinates":[12.3853282928,48.8219337463],"type":"Point"}
}