{
  "type": "Feature",
  "properties": {
    "iso:country":"DE",
    "sg:address":"Kurze Geismarstr. 1",
    "sg:city":"G\u00f6ttingen",
    "sg:phone":"+49 551/395072",
    "sg:postcode":"37073",
    "sg:province":"Niedersachsen",
    "wof:name":"Musikwissenschaftl. Seminar",
    "wof:placetype":"venue"
},
  "geometry": {"coordinates":[9.9382762909,51.5300865173],"type":"Point"}
}