{
  "type": "Feature",
  "properties": {
    "iso:country":"DE",
    "sg:address":"Bahnhofstr. 24",
    "sg:city":"Traunstein",
    "sg:postcode":"83278",
    "sg:province":"Bayern",
    "wof:name":"Theodor Bittner",
    "wof:placetype":"venue"
},
  "geometry": {"coordinates":[12.6418895721,47.869392395],"type":"Point"}
}