{
  "type": "Feature",
  "properties": {
    "iso:country":"DE",
    "sg:address":"Feld-Forstmann-Str. 7",
    "sg:city":"Bendorf",
    "sg:phone":"+49 2622/6604",
    "sg:postcode":"56170",
    "sg:province":"Rheinland-Pfalz",
    "wof:name":"H\u00f6fer Gmbh K\u00e4lte- Und Klimatechnik",
    "wof:placetype":"venue"
},
  "geometry": {"coordinates":[7.5674262047,50.4276695251],"type":"Point"}
}