{
  "type": "Feature",
  "properties": {
    "iso:country":"DE",
    "sg:address":"Diebesweg 39",
    "sg:city":"M\u00f6nchengladbach",
    "sg:phone":"+49 2161/96960",
    "sg:postcode":"41065",
    "sg:province":"Nordrhein-Westfalen",
    "wof:name":"Telefonbau Kalth\u00f6fer Gmbh & Co.",
    "wof:placetype":"venue"
},
  "geometry": {"coordinates":[6.4674639702,51.208366394],"type":"Point"}
}