{
  "type": "Feature",
  "properties": {
    "iso:country":"DE",
    "sg:address":"Goethestr. 15-17",
    "sg:city":"Gro\u00dfkrotzenburg",
    "sg:phone":"+49 6186/912200",
    "sg:postcode":"63538",
    "sg:province":"Hessen",
    "wof:name":"Ambulanter Pflegedienst Wanetzky",
    "wof:placetype":"venue"
},
  "geometry": {"coordinates":[8.987209,50.079437],"type":"Point"}
}