{
  "type": "Feature",
  "properties": {
    "iso:country":"DE",
    "sg:address":"Bahnhofstr. 13",
    "sg:city":"Dasing",
    "sg:phone":"+49 8205/7459",
    "sg:postcode":"86453",
    "sg:province":"Bayern",
    "wof:name":"Hildes Blumen- U. Geschenkst\u00fcberl",
    "wof:placetype":"venue"
},
  "geometry": {"coordinates":[11.050279,48.384888],"type":"Point"}
}