{
  "type": "Feature",
  "properties": {
    "iso:country":"DE",
    "sg:address":"Sternenweg 7",
    "sg:city":"Nesselwang",
    "sg:phone":"+49 8361/751",
    "sg:postcode":"87484",
    "sg:province":"Bayern",
    "wof:name":"Pension Sch\u00f6nblick",
    "wof:placetype":"venue"
},
  "geometry": {"coordinates":[10.4973125458,47.6252746582],"type":"Point"}
}