{
  "type": "Feature",
  "properties": {
    "iso:country":"DE",
    "sg:address":"Dr.-Rudolf-Eberle-Str. 3",
    "sg:city":"H\u00f6chenschwand",
    "sg:phone":"+49 7755/8414",
    "sg:postcode":"79862",
    "sg:province":"Baden-W\u00fcrttemberg",
    "wof:name":"Tennishalle H\u00f6chenschwand Betriebs Gmbh",
    "wof:placetype":"venue"
},
  "geometry": {"coordinates":[8.1659412384,47.7366065979],"type":"Point"}
}