{
  "type": "Feature",
  "properties": {
    "iso:country":"DE",
    "sg:address":"An der Eselshaut 61",
    "sg:city":"Neustadt",
    "sg:phone":"+49 6321/68486",
    "sg:postcode":"67435",
    "sg:province":"Rheinland-Pfalz",
    "wof:name":"Horst Rothfuchs Masseur",
    "wof:placetype":"venue"
},
  "geometry": {"coordinates":[8.173221,49.369598],"type":"Point"}
}