{
  "type": "Feature",
  "properties": {
    "iso:country":"DE",
    "sg:address":"Tunnelstr. 2",
    "sg:city":"Pforzheim",
    "sg:phone":"+49 7231/358677",
    "sg:postcode":"75172",
    "sg:province":"Baden-W\u00fcrttemberg",
    "wof:name":"J. Kr\u00e4mer Steuerberater",
    "wof:placetype":"venue"
},
  "geometry": {"coordinates":[8.696814537,48.8939285278],"type":"Point"}
}