{
  "type": "Feature",
  "properties": {
    "iso:country":"DE",
    "sg:address":"Hauptstr. 94",
    "sg:city":"Unterw\u00f6ssen",
    "sg:phone":"+49 8641/61126",
    "sg:postcode":"83246",
    "sg:province":"Bayern",
    "wof:name":"G. Drexl",
    "wof:placetype":"venue"
},
  "geometry": {"coordinates":[12.46179,47.731426],"type":"Point"}
}