{
  "type": "Feature",
  "properties": {
    "iso:country":"DE",
    "sg:address":"Fr.-Ebert-Str. 2a",
    "sg:city":"Speyer",
    "sg:phone":"+49 6323/31810",
    "sg:postcode":"67346",
    "sg:province":"Rheinland-Pfalz",
    "wof:name":"Schulz Bibliothekstechnik Gmbh",
    "wof:placetype":"venue"
},
  "geometry": {"coordinates":[8.4249839783,49.3268890381],"type":"Point"}
}