{
  "type": "Feature",
  "properties": {
    "iso:country":"DE",
    "sg:address":"Friedensstr 8",
    "sg:city":"Burgwerben",
    "sg:phone":"+49 3443/200120",
    "sg:postcode":"06667",
    "sg:province":"Sachsen-Anhalt",
    "wof:name":"Bre Brand- Und Rauchschutzelemente Gmbh",
    "wof:placetype":"venue"
},
  "geometry": {"coordinates":[11.9853858948,51.2222518921],"type":"Point"}
}