{
  "type": "Feature",
  "properties": {
    "iso:country":"DE",
    "sg:address":"Hauptstr. 44",
    "sg:city":"Hilkenbrook",
    "sg:postcode":"26897",
    "sg:province":"Niedersachsen",
    "wof:name":"Windpark Hilkenbrook Verwaltungsges. Mbh",
    "wof:placetype":"venue"
},
  "geometry": {"coordinates":[7.704767,52.988701],"type":"Point"}
}