{
  "type": "Feature",
  "properties": {
    "iso:country":"DE",
    "sg:address":"L\u00fcneburger Str. 4-10",
    "sg:city":"Uelzen",
    "sg:phone":"+49 581/978850",
    "sg:postcode":"29525",
    "sg:province":"Niedersachsen",
    "wof:name":"Creditreform Uelzen Styra Kg",
    "wof:placetype":"venue"
},
  "geometry": {"coordinates":[10.560789,52.965305],"type":"Point"}
}