{
  "type": "Feature",
  "properties": {
    "iso:country":"DE",
    "sg:address":"Russenstr. 29",
    "sg:city":"Leipzig",
    "sg:phone":"+49 341/6994912",
    "sg:postcode":"04289",
    "sg:province":"Sachsen",
    "wof:name":"Gebr. Strauss",
    "wof:placetype":"venue"
},
  "geometry": {"coordinates":[12.440165,51.304508],"type":"Point"}
}