{
  "type": "Feature",
  "properties": {
    "iso:country":"DE",
    "sg:address":"Dorfstr. 11",
    "sg:city":"Betzendorf",
    "sg:phone":"+49 4138/474",
    "sg:postcode":"21386",
    "sg:province":"Niedersachsen",
    "wof:name":"Bernd Radke",
    "wof:placetype":"venue"
},
  "geometry": {"coordinates":[10.311278,53.137005],"type":"Point"}
}