{
  "type": "Feature",
  "properties": {
    "iso:country":"DE",
    "sg:address":"Schenkenseestr. 26",
    "sg:city":"Schw\u00e4bisch Hall",
    "sg:phone":"+49 791/492999",
    "sg:postcode":"74523",
    "sg:province":"Baden-W\u00fcrttemberg",
    "wof:name":"Christiane Mehlis Heilpraktikerin",
    "wof:placetype":"venue"
},
  "geometry": {"coordinates":[9.7504310608,49.1160583496],"type":"Point"}
}