{
  "type": "Feature",
  "properties": {
    "iso:country":"DE",
    "sg:address":"Gr\u00f6nholm 13",
    "sg:city":"Wees",
    "sg:phone":"+49 4631/2885",
    "sg:postcode":"24999",
    "sg:province":"Schleswig-Holstein",
    "wof:name":"Verwaltung Sanipro Handel Gmbh",
    "wof:placetype":"venue"
},
  "geometry": {"coordinates":[9.5102615356,54.8022956848],"type":"Point"}
}