{
  "type": "Feature",
  "properties": {
    "iso:country":"DE",
    "sg:address":"Frankfurter Str.",
    "sg:city":"Kassel",
    "sg:postcode":"34134",
    "sg:province":"Hessen",
    "wof:name":"Reiseb\u00fcro Globetrotter",
    "wof:placetype":"venue"
},
  "geometry": {"coordinates":[9.473415,51.290867],"type":"Point"}
}