{
  "type": "Feature",
  "properties": {
    "iso:country":"DE",
    "sg:address":"Friedrich-Ebert-Str. 46",
    "sg:city":"Hainburg",
    "sg:phone":"+49 6182/4170",
    "sg:postcode":"63512",
    "sg:province":"Hessen",
    "wof:name":"Karl-heinz Klein",
    "wof:placetype":"venue"
},
  "geometry": {"coordinates":[8.9681034088,50.0755577087],"type":"Point"}
}