{
  "type": "Feature",
  "properties": {
    "iso:country":"DE",
    "sg:address":"Friedberger Landstr. 77",
    "sg:city":"Frankfurt",
    "sg:postcode":"60318",
    "sg:province":"Hessen",
    "wof:name":"G\u00e4rtner Michel E. K.",
    "wof:placetype":"venue"
},
  "geometry": {"coordinates":[8.69175,50.125198],"type":"Point"}
}