{
  "type": "Feature",
  "properties": {
    "iso:country":"DE",
    "sg:address":"Leonhard-Hausmann-Str. 9",
    "sg:city":"Augsburg",
    "sg:phone":"+49 821/544948",
    "sg:postcode":"86157",
    "sg:province":"Bayern",
    "wof:name":"Stefan Sonntag",
    "wof:placetype":"venue"
},
  "geometry": {"coordinates":[10.8731451035,48.3652496338],"type":"Point"}
}