{
  "type": "Feature",
  "properties": {
    "iso:country":"DE",
    "sg:address":"Kirchweg 19",
    "sg:city":"Boxberg",
    "sg:phone":"+49 7930/739",
    "sg:postcode":"97944",
    "sg:province":"Baden-W\u00fcrttemberg",
    "wof:name":"Manfred Wernado Masseur",
    "wof:placetype":"venue"
},
  "geometry": {"coordinates":[9.634221,49.483097],"type":"Point"}
}