{
  "type": "Feature",
  "properties": {
    "iso:country":"DE",
    "sg:address":"Friedensstr 7",
    "sg:city":"Bitterfeld",
    "sg:phone":"+49 3493/22588",
    "sg:postcode":"06749",
    "sg:province":"Sachsen-Anhalt",
    "wof:name":"Bitterfelder Entsorgungs-gmbh",
    "wof:placetype":"venue"
},
  "geometry": {"coordinates":[12.3297948837,51.6277885437],"type":"Point"}
}