{
  "type": "Feature",
  "properties": {
    "iso:country":"DE",
    "sg:address":"M\u00fcnsterstr. 427",
    "sg:city":"D\u00fcsseldorf",
    "sg:postcode":"40470",
    "sg:province":"Nordrhein-Westfalen",
    "wof:name":"M\u00f6rsenbroicher Apotheke Inh. Nicola Quante E. K.",
    "wof:placetype":"venue"
},
  "geometry": {"coordinates":[6.805571,51.257061],"type":"Point"}
}