{
  "type": "Feature",
  "properties": {
    "iso:country":"DE",
    "sg:address":"S\u00f6sepromenade 14",
    "sg:city":"Osterode",
    "sg:postcode":"37520",
    "sg:province":"Niedersachsen",
    "wof:name":"Volksbank Osterode-westharz Eg",
    "wof:placetype":"venue"
},
  "geometry": {"coordinates":[10.28459,51.72871],"type":"Point"}
}