{
  "type": "Feature",
  "properties": {
    "iso:country":"DE",
    "sg:address":"Schmittstr. 20",
    "sg:city":"Bingen",
    "sg:phone":"+49 6721/17622",
    "sg:postcode":"55411",
    "sg:province":"Rheinland-Pfalz",
    "wof:name":"Pitti Nicole",
    "wof:placetype":"venue"
},
  "geometry": {"coordinates":[7.8943228722,49.9667205811],"type":"Point"}
}