{
  "type": "Feature",
  "properties": {
    "iso:country":"DE",
    "sg:address":"Rudolf-Diesel-Weg 4",
    "sg:city":"Hohenlockstedt",
    "sg:phone":"+49 4826/5393",
    "sg:postcode":"25551",
    "sg:province":"Schleswig-Holstein",
    "wof:name":"H. Klein",
    "wof:placetype":"venue"
},
  "geometry": {"coordinates":[9.620373,53.982471],"type":"Point"}
}