{
  "type": "Feature",
  "properties": {
    "iso:country":"DE",
    "sg:address":"Rugoweg 6",
    "sg:city":"Hasbergen",
    "sg:postcode":"49205",
    "sg:province":"Niedersachsen",
    "wof:name":"Urich & Plogmann Trading Ohg",
    "wof:placetype":"venue"
},
  "geometry": {"coordinates":[7.9579701424,52.2595787048],"type":"Point"}
}