{
  "type": "Feature",
  "properties": {
    "iso:country":"DE",
    "sg:address":"Boltenhagener Str. 20",
    "sg:city":"Dresden",
    "sg:phone":"+49 351/585848",
    "sg:postcode":"01109",
    "sg:province":"Sachsen",
    "wof:name":"B. Gothe Architekt",
    "wof:placetype":"venue"
},
  "geometry": {"coordinates":[13.782685,51.116192],"type":"Point"}
}