{
  "type": "Feature",
  "properties": {
    "iso:country":"DE",
    "sg:address":"Andersenweg 8",
    "sg:city":"Heiligenhaus",
    "sg:phone":"+49 2056/69332",
    "sg:postcode":"42579",
    "sg:province":"Nordrhein-Westfalen",
    "wof:name":"R. Und J. Stelzmann",
    "wof:placetype":"venue"
},
  "geometry": {"coordinates":[7.0034909248,51.3271446228],"type":"Point"}
}