{
  "type": "Feature",
  "properties": {
    "iso:country":"DE",
    "sg:address":"Quellenstr.",
    "sg:city":"Wertheim",
    "sg:phone":"+49 9342/59988",
    "sg:postcode":"97877",
    "sg:province":"Baden-W\u00fcrttemberg",
    "wof:name":"Vereinsgastst\u00e4tte Sport-club Gr\u00fcnenw\u00f6rt E. V.",
    "wof:placetype":"venue"
},
  "geometry": {"coordinates":[9.4682130814,49.7689743042],"type":"Point"}
}