{
  "type": "Feature",
  "properties": {
    "iso:country":"DE",
    "sg:address":"Wallstr. 13",
    "sg:city":"Neustadt",
    "sg:phone":"+49 5032/64174",
    "sg:postcode":"31535",
    "sg:province":"Niedersachsen",
    "wof:name":"Martha Hageb\u00f6ck Heilpraktikerin",
    "wof:placetype":"venue"
},
  "geometry": {"coordinates":[9.459692955,52.5055732727],"type":"Point"}
}