{
  "type": "Feature",
  "properties": {
    "iso:country":"DE",
    "sg:address":"Hessenring 21",
    "sg:city":"Bad Homburg",
    "sg:postcode":"61348",
    "sg:province":"Hessen",
    "wof:name":"Nvs Automotive Cargo Gmbh",
    "wof:placetype":"venue"
},
  "geometry": {"coordinates":[8.6163444519,50.2235603333],"type":"Point"}
}