{
  "type": "Feature",
  "properties": {
    "iso:country":"DE",
    "sg:address":"Satruper Str. 2",
    "sg:city":"S\u00f6rup",
    "sg:phone":"+49 4635/29140",
    "sg:postcode":"24966",
    "sg:province":"Schleswig-Holstein",
    "wof:name":"Haus S\u00fcdensee",
    "wof:placetype":"venue"
},
  "geometry": {"coordinates":[9.670291,54.709751],"type":"Point"}
}