{
  "type": "Feature",
  "properties": {
    "iso:country":"DE",
    "sg:address":"Poststr. 8",
    "sg:city":"Velbert",
    "sg:phone":"+49 2051/50023",
    "sg:postcode":"42551",
    "sg:province":"Nordrhein-Westfalen",
    "wof:name":"M. Schmald",
    "wof:placetype":"venue"
},
  "geometry": {"coordinates":[7.042901,51.340778],"type":"Point"}
}