{
  "type": "Feature",
  "properties": {
    "iso:country":"DE",
    "sg:address":"Kaiser-Wilhelm-Ring 24",
    "sg:city":"D\u00fcsseldorf",
    "sg:phone":"+49 211/594982",
    "sg:postcode":"40545",
    "sg:province":"Nordrhein-Westfalen",
    "wof:name":"Ikp Immobilien- Beratungsgesellschaft Mbh",
    "wof:placetype":"venue"
},
  "geometry": {"coordinates":[6.7618432045,51.2290992737],"type":"Point"}
}