{
  "type": "Feature",
  "properties": {
    "iso:country":"DE",
    "sg:address":"Im Hasenbach 4",
    "sg:city":"Frankenau",
    "sg:phone":"+49 4964/55661",
    "sg:postcode":"35110",
    "sg:province":"Hessen",
    "wof:name":"Raiffeisenbank Vierm\u00fcnden Altenlot-, Heim Eg",
    "wof:placetype":"venue"
},
  "geometry": {"coordinates":[8.920272,51.128555],"type":"Point"}
}