{
  "type": "Feature",
  "properties": {
    "iso:country":"DE",
    "sg:address":"Homburger Landstr. 148",
    "sg:city":"Frankfurt",
    "sg:phone":"+49 69/95430221",
    "sg:postcode":"60435",
    "sg:province":"Hessen",
    "wof:name":"Decotec Gmbh & Co. Handels- Und Produktions Kg",
    "wof:placetype":"venue"
},
  "geometry": {"coordinates":[8.6912231445,50.1524543762],"type":"Point"}
}