{
  "type": "Feature",
  "properties": {
    "iso:country":"DE",
    "sg:address":"Torstr. 7",
    "sg:city":"Lichtenberg",
    "sg:phone":"+49 9288/8209",
    "sg:postcode":"95192",
    "sg:province":"Bayern",
    "wof:name":"G\u00fcnther Beyer",
    "wof:placetype":"venue"
},
  "geometry": {"coordinates":[11.6759662628,50.383731842],"type":"Point"}
}