{
  "type": "Feature",
  "properties": {
    "iso:country":"DE",
    "sg:address":"Trosdorfer Hauptstr. 50A",
    "sg:city":"Bischberg",
    "sg:phone":"+49 9503/7026",
    "sg:postcode":"96120",
    "sg:province":"Bayern",
    "wof:name":"Werner H\u00f6rr",
    "wof:placetype":"venue"
},
  "geometry": {"coordinates":[10.8053236008,49.9127464294],"type":"Point"}
}