{
  "type": "Feature",
  "properties": {
    "iso:country":"DE",
    "sg:address":"Fr\u00fchlingstr. 12",
    "sg:city":"Karlsbad",
    "sg:phone":"+49 7202/40145",
    "sg:postcode":"76307",
    "sg:province":"Baden-W\u00fcrttemberg",
    "wof:name":"R. Reinke",
    "wof:placetype":"venue"
},
  "geometry": {"coordinates":[8.536611557,48.9349784851],"type":"Point"}
}