{
  "type": "Feature",
  "properties": {
    "iso:country":"DE",
    "sg:address":"Obere Feldstr. 2",
    "sg:city":"Freilassing",
    "sg:postcode":"83395",
    "sg:province":"Bayern",
    "wof:name":"Fahrschule Schweiger Gmbh",
    "wof:placetype":"venue"
},
  "geometry": {"coordinates":[12.9728088379,47.8432044983],"type":"Point"}
}