{
  "type": "Feature",
  "properties": {
    "iso:country":"DE",
    "sg:address":"Zitherstr. 30",
    "sg:city":"Berlin",
    "sg:postcode":"13127",
    "sg:province":"Berlin",
    "wof:name":"Siap Schulz Immobilien Anlagen Planung Gmbh",
    "wof:placetype":"venue"
},
  "geometry": {"coordinates":[13.4258623123,52.5935592651],"type":"Point"}
}