{
  "type": "Feature",
  "properties": {
    "iso:country":"DE",
    "sg:address":"Weststr. 14",
    "sg:city":"Mittweida",
    "sg:phone":"+49 3727/92718",
    "sg:postcode":"09648",
    "sg:province":"Sachsen",
    "wof:name":"Andreas D\u00f6rfer",
    "wof:placetype":"venue"
},
  "geometry": {"coordinates":[12.9706888199,50.9870376587],"type":"Point"}
}