{
  "type": "Feature",
  "properties": {
    "iso:country":"DE",
    "sg:address":"Eichenb\u00fchler Str. 11",
    "sg:city":"Neunkirchen",
    "sg:phone":"+49 9378/777",
    "sg:postcode":"63930",
    "sg:province":"Bayern",
    "wof:name":"Franz Zeller Kg Natursteinwerke",
    "wof:placetype":"venue"
},
  "geometry": {"coordinates":[9.4029684067,49.7083015442],"type":"Point"}
}