{
  "type": "Feature",
  "properties": {
    "iso:country":"DE",
    "sg:address":"Schweppermannstr. 25",
    "sg:city":"N\u00fcrnberg",
    "sg:phone":"+49 911/367265",
    "sg:postcode":"90408",
    "sg:province":"Bayern",
    "wof:name":"Dirty Mind",
    "wof:placetype":"venue"
},
  "geometry": {"coordinates":[11.0744543076,49.4633827209],"type":"Point"}
}