{
  "type": "Feature",
  "properties": {
    "iso:country":"DE",
    "sg:address":"M\u00fchlenstr. 11",
    "sg:city":"Reinhardshagen",
    "sg:phone":"+49 5544/574",
    "sg:postcode":"34359",
    "sg:province":"Hessen",
    "wof:name":"W. Drubel",
    "wof:placetype":"venue"
},
  "geometry": {"coordinates":[9.598918,51.494209],"type":"Point"}
}