{
  "type": "Feature",
  "properties": {
    "iso:country":"DE",
    "sg:address":"Kr\u00f6\u00dfwehrstr. 52",
    "sg:city":"Lichtenfels",
    "sg:phone":"+49 9571/71729",
    "sg:postcode":"96215",
    "sg:province":"Bayern",
    "wof:name":"Maincamping",
    "wof:placetype":"venue"
},
  "geometry": {"coordinates":[11.086693,50.155956],"type":"Point"}
}