{
  "type": "Feature",
  "properties": {
    "iso:country":"DE",
    "sg:address":"Bergstr 12",
    "sg:city":"Frechen",
    "sg:phone":"+49 2234/61741",
    "sg:postcode":"50226",
    "sg:province":"Nordrhein-Westfalen",
    "wof:name":"Zirener",
    "wof:placetype":"venue"
},
  "geometry": {"coordinates":[6.7817158699,50.9390716553],"type":"Point"}
}