{
  "type": "Feature",
  "properties": {
    "iso:country":"DE",
    "sg:address":"Reisewitzer Str. 22",
    "sg:city":"Dresden",
    "sg:postcode":"01159",
    "sg:province":"Sachsen",
    "wof:name":"Gornys Boutique",
    "wof:placetype":"venue"
},
  "geometry": {"coordinates":[13.70091,51.042728],"type":"Point"}
}