{
  "type": "Feature",
  "properties": {
    "iso:country":"DE",
    "sg:address":"Karlstr. 13",
    "sg:city":"Ratingen",
    "sg:phone":"+49 2102/449895",
    "sg:postcode":"40880",
    "sg:province":"Nordrhein-Westfalen",
    "wof:name":"Krause Travel Und Adventure Gmbh",
    "wof:placetype":"venue"
},
  "geometry": {"coordinates":[6.8257279396,51.3127098083],"type":"Point"}
}