{
  "type": "Feature",
  "properties": {
    "iso:country":"DE",
    "sg:address":"Reimerweg 9",
    "sg:city":"Berlin",
    "sg:phone":"+49 30/3655701",
    "sg:postcode":"13593",
    "sg:province":"Berlin",
    "wof:name":"J\u00f6rg Jahnke Gmbh",
    "wof:placetype":"venue"
},
  "geometry": {"coordinates":[13.1525611877,52.5207252502],"type":"Point"}
}