{
  "type": "Feature",
  "properties": {
    "iso:country":"DE",
    "sg:address":"Pariser Platz 4",
    "sg:city":"M\u00fcnchen",
    "sg:phone":"+49 89/4485940",
    "sg:postcode":"81667",
    "sg:province":"Bayern",
    "wof:name":"Dr. Med. Britta Knoll",
    "wof:placetype":"venue"
},
  "geometry": {"coordinates":[11.5997543335,48.1282920837],"type":"Point"}
}