{
  "type": "Feature",
  "properties": {
    "iso:country":"DE",
    "sg:address":"Schulstr. 1",
    "sg:city":"Berlin",
    "sg:phone":"+49 30/7745133",
    "sg:postcode":"12247",
    "sg:province":"Berlin",
    "wof:name":"Elke Weber",
    "wof:placetype":"venue"
},
  "geometry": {"coordinates":[13.346802,52.436115],"type":"Point"}
}