{
  "type": "Feature",
  "properties": {
    "iso:country":"DE",
    "sg:address":"Am M\u00fchlenberg 13",
    "sg:city":"D\u00fcppenweiler",
    "sg:phone":"+49 6832/91247",
    "sg:postcode":"66701",
    "sg:province":"Saarland",
    "wof:name":"D\u00fcppenweiler",
    "wof:placetype":"venue"
},
  "geometry": {"coordinates":[6.767376,49.415184],"type":"Point"}
}