{
  "type": "Feature",
  "properties": {
    "iso:country":"DE",
    "sg:address":"Schlo\u00dfstr. 8",
    "sg:city":"Marxheim",
    "sg:postcode":"86688",
    "sg:province":"Bayern",
    "wof:name":"Donau-lech-werkst\u00e4tten Stiftung",
    "wof:placetype":"venue"
},
  "geometry": {"coordinates":[10.950797081,48.7527885437],"type":"Point"}
}