{
  "type": "Feature",
  "properties": {
    "iso:country":"DE",
    "sg:address":"Zeller Str. 4",
    "sg:city":"Weilheim",
    "sg:phone":"+49 7023/6186",
    "sg:postcode":"73235",
    "sg:province":"Baden-W\u00fcrttemberg",
    "wof:name":"W. Heilemann",
    "wof:placetype":"venue"
},
  "geometry": {"coordinates":[9.5401763916,48.6189231873],"type":"Point"}
}