{
  "type": "Feature",
  "properties": {
    "iso:country":"DE",
    "sg:address":"Stresemannstr. 232 - 238",
    "sg:city":"Hamburg",
    "sg:phone":"+49 40/856055",
    "sg:postcode":"22769",
    "sg:province":"Hamburg",
    "wof:name":"Futonia Gmbh",
    "wof:placetype":"venue"
},
  "geometry": {"coordinates":[9.941162,53.563457],"type":"Point"}
}