{
  "type": "Feature",
  "properties": {
    "iso:country":"DE",
    "sg:address":"Unterer Eickeshagen 8",
    "sg:city":"Velbert",
    "sg:phone":"+49 2052/7015",
    "sg:postcode":"42555",
    "sg:province":"Nordrhein-Westfalen",
    "wof:name":"S\u00fc\u00dfwarenagentur H. J. Siefert Ohg",
    "wof:placetype":"venue"
},
  "geometry": {"coordinates":[7.1162309647,51.3478927612],"type":"Point"}
}