{
  "type": "Feature",
  "properties": {
    "iso:country":"DE",
    "sg:address":"Schweinfurter Str. 34",
    "sg:city":"Euerdorf",
    "sg:phone":"+49 9704/5698",
    "sg:postcode":"97717",
    "sg:province":"Bayern",
    "wof:name":"Kontra-markt",
    "wof:placetype":"venue"
},
  "geometry": {"coordinates":[10.0241594315,50.1450691223],"type":"Point"}
}