{
  "type": "Feature",
  "properties": {
    "iso:country":"DE",
    "sg:address":"K\u00fchnlenzhof 2",
    "sg:city":"Kronach",
    "sg:phone":"+49 9261/60540",
    "sg:postcode":"96317",
    "sg:province":"Bayern",
    "wof:name":"Wagler Anwalts Gmbh",
    "wof:placetype":"venue"
},
  "geometry": {"coordinates":[11.3230018616,50.2384223938],"type":"Point"}
}