{
  "type": "Feature",
  "properties": {
    "iso:country":"DE",
    "sg:address":"Marktstr. 4",
    "sg:city":"Wiesmoor",
    "sg:phone":"+49 4944/7709",
    "sg:postcode":"26639",
    "sg:province":"Niedersachsen",
    "wof:name":"Biggis Fotomarkt Gmbh",
    "wof:placetype":"venue"
},
  "geometry": {"coordinates":[7.7355928421,53.413143158],"type":"Point"}
}