{
  "type": "Feature",
  "properties": {
    "iso:country":"DE",
    "sg:address":"Breitlenstr. 5",
    "sg:city":"B\u00fcsingen",
    "sg:phone":"+49 7734/6306",
    "sg:postcode":"78266",
    "sg:province":"Baden-W\u00fcrttemberg",
    "wof:name":"Helmut Heller",
    "wof:placetype":"venue"
},
  "geometry": {"coordinates":[8.696927,47.696762],"type":"Point"}
}