{
  "type": "Feature",
  "properties": {
    "iso:country":"DE",
    "sg:address":"Hinter der Wohrte 12",
    "sg:city":"Broock",
    "sg:postcode":"19386",
    "sg:province":"Mecklenburg-Vorpommern",
    "wof:name":"Dr. Med. Olaf Mews",
    "wof:placetype":"venue"
},
  "geometry": {"coordinates":[12.107006,53.464432],"type":"Point"}
}