{
  "type": "Feature",
  "properties": {
    "iso:country":"DE",
    "sg:address":"Hauptstr. 32",
    "sg:city":"Bottrop",
    "sg:phone":"+49 2045/3972",
    "sg:postcode":"46244",
    "sg:province":"Nordrhein-Westfalen",
    "wof:name":"Dickmann-kessler",
    "wof:placetype":"venue"
},
  "geometry": {"coordinates":[6.9197788239,51.603553772],"type":"Point"}
}