{
  "type": "Feature",
  "properties": {
    "iso:country":"DE",
    "sg:address":"Freytagstr. 26",
    "sg:city":"Ahlen",
    "sg:phone":"+49 2382/83188",
    "sg:postcode":"59227",
    "sg:province":"Nordrhein-Westfalen",
    "wof:name":"Helmut Holtrup",
    "wof:placetype":"venue"
},
  "geometry": {"coordinates":[7.8817949295,51.7595252991],"type":"Point"}
}