{
  "type": "Feature",
  "properties": {
    "iso:country":"DE",
    "sg:address":"Stadtgraben 7",
    "sg:city":"Wurzen",
    "sg:phone":"+49 3425/926698",
    "sg:postcode":"04808",
    "sg:province":"Sachsen",
    "wof:name":"Ambiente",
    "wof:placetype":"venue"
},
  "geometry": {"coordinates":[12.7365503311,51.3708610535],"type":"Point"}
}