{
  "type": "Feature",
  "properties": {
    "iso:country":"DE",
    "sg:address":"Robert-Havemann-Str. 9",
    "sg:city":"Frankfurt",
    "sg:phone":"+49 335/528680",
    "sg:postcode":"15236",
    "sg:province":"Brandenburg",
    "wof:name":"Monika Horn",
    "wof:placetype":"venue"
},
  "geometry": {"coordinates":[14.532966,52.32975],"type":"Point"}
}