{
  "type": "Feature",
  "properties": {
    "iso:country":"DE",
    "sg:address":"Fleischgasse 22",
    "sg:city":"Limburg",
    "sg:phone":"+49 6431/8985",
    "sg:postcode":"65549",
    "sg:province":"Hessen",
    "wof:name":"Antiquit\u00e4ten K\u00fcster Inh. J. Arweiler Schmitt E. K.",
    "wof:placetype":"venue"
},
  "geometry": {"coordinates":[8.064711,50.387436],"type":"Point"}
}