{
  "type": "Feature",
  "properties": {
    "iso:country":"DE",
    "sg:address":"Steinkampberg 29",
    "sg:city":"Laboe",
    "sg:phone":"+49 4343/7124",
    "sg:postcode":"24235",
    "sg:province":"Schleswig-Holstein",
    "wof:name":"Bachler",
    "wof:placetype":"venue"
},
  "geometry": {"coordinates":[10.224076,54.401962],"type":"Point"}
}