{
  "type": "Feature",
  "properties": {
    "iso:country":"DE",
    "sg:address":"Hauptstr. 35",
    "sg:city":"Kirchseeon",
    "sg:phone":"+49 8091/9458",
    "sg:postcode":"85614",
    "sg:province":"Bayern",
    "wof:name":"Josef Reich",
    "wof:placetype":"venue"
},
  "geometry": {"coordinates":[11.862354,48.08115],"type":"Point"}
}