{
  "type": "Feature",
  "properties": {
    "iso:country":"DE",
    "sg:address":"Wattenheimer Str. 2",
    "sg:city":"Biblis",
    "sg:phone":"+49 6245/7224",
    "sg:postcode":"68647",
    "sg:province":"Hessen",
    "wof:name":"B. Und R. Schindler",
    "wof:placetype":"venue"
},
  "geometry": {"coordinates":[8.4504556656,49.6828613281],"type":"Point"}
}