{
  "type": "Feature",
  "properties": {
    "iso:country":"DE",
    "sg:address":"Lerchenstr. 19b",
    "sg:city":"Delmenhorst",
    "sg:phone":"+49 4221/56752",
    "sg:postcode":"27749",
    "sg:province":"Niedersachsen",
    "wof:name":"Michael Steinel",
    "wof:placetype":"venue"
},
  "geometry": {"coordinates":[8.6350421906,53.0607566833],"type":"Point"}
}