{
  "type": "Feature",
  "properties": {
    "iso:country":"DE",
    "sg:address":"Malmsgel\u00e4nge 2",
    "sg:city":"P\u00f6\u00dfneck",
    "sg:phone":"+49 3647/443822",
    "sg:postcode":"07381",
    "sg:province":"Th\u00fcringen",
    "wof:name":"Center-apotheke E. K.",
    "wof:placetype":"venue"
},
  "geometry": {"coordinates":[11.617907,50.698002],"type":"Point"}
}