{
  "type": "Feature",
  "properties": {
    "iso:country":"DE",
    "sg:address":"Am Sportplatz 1",
    "sg:city":"Brietlingen",
    "sg:phone":"+49 4133/3211",
    "sg:postcode":"21382",
    "sg:province":"Niedersachsen",
    "wof:name":"K. Pursche Altenheim",
    "wof:placetype":"venue"
},
  "geometry": {"coordinates":[10.435297,53.318409],"type":"Point"}
}