{
  "type": "Feature",
  "properties": {
    "iso:country":"DE",
    "sg:address":"Marktwaldstr. 25",
    "sg:city":"Bexbach",
    "sg:phone":"+49 6826/80929",
    "sg:postcode":"66450",
    "sg:province":"Saarland",
    "wof:name":"Rrc Computer Cooperation",
    "wof:placetype":"venue"
},
  "geometry": {"coordinates":[7.260269165,49.3788032532],"type":"Point"}
}