{
  "type": "Feature",
  "properties": {
    "iso:country":"DE",
    "sg:address":"Lerchenfeld 50",
    "sg:city":"Eutin",
    "sg:phone":"+49 4521/3060",
    "sg:postcode":"23701",
    "sg:province":"Schleswig-Holstein",
    "wof:name":"Elsedora Passon",
    "wof:placetype":"venue"
},
  "geometry": {"coordinates":[10.6146678925,54.1230163574],"type":"Point"}
}