{
  "type": "Feature",
  "properties": {
    "iso:country":"DE",
    "sg:address":"Konradin-Kreutzer-Str. 35",
    "sg:city":"Me\u00dfkirch",
    "sg:phone":"+49 4975/7520980",
    "sg:postcode":"88605",
    "sg:province":"Baden-W\u00fcrttemberg",
    "wof:name":"Schako Ferdinand Schad Kg",
    "wof:placetype":"venue"
},
  "geometry": {"coordinates":[9.115662,47.997162],"type":"Point"}
}