{
  "type": "Feature",
  "properties": {
    "iso:country":"DE",
    "sg:address":"Buchenstr. 20",
    "sg:city":"Bad Rappenau",
    "sg:phone":"+49 7264/7474",
    "sg:postcode":"74906",
    "sg:province":"Baden-W\u00fcrttemberg",
    "wof:name":"Elmar Kloos Notar",
    "wof:placetype":"venue"
},
  "geometry": {"coordinates":[9.0902967453,49.2428092957],"type":"Point"}
}