{
  "type": "Feature",
  "properties": {
    "iso:country":"DE",
    "sg:address":"Berliner Str. 13",
    "sg:city":"Ronnenberg",
    "sg:phone":"+49 511/438060",
    "sg:postcode":"30952",
    "sg:province":"Niedersachsen",
    "wof:name":"Cc Erfrischungsgetr\u00e4nke S\u00fcd-niedersachsen Hannover",
    "wof:placetype":"venue"
},
  "geometry": {"coordinates":[9.668718338,52.3442993164],"type":"Point"}
}