{
  "type": "Feature",
  "properties": {
    "iso:country":"DE",
    "sg:address":"Gronauer Str. 163",
    "sg:city":"Gronau",
    "sg:phone":"+49 2565/2879",
    "sg:postcode":"48599",
    "sg:province":"Nordrhein-Westfalen",
    "wof:name":"Erich B\u00f6ggemann Grabdenkm\u00e4ler",
    "wof:placetype":"venue"
},
  "geometry": {"coordinates":[7.0289411545,52.1921348572],"type":"Point"}
}