{
  "type": "Feature",
  "properties": {
    "iso:country":"DE",
    "sg:address":"Hauptstr. 18",
    "sg:city":"Dietfurt",
    "sg:phone":"+49 8464/327",
    "sg:postcode":"92345",
    "sg:province":"Bayern",
    "wof:name":"X. Leidl Jun.",
    "wof:placetype":"venue"
},
  "geometry": {"coordinates":[11.5869455338,49.0350837708],"type":"Point"}
}