{
  "type": "Feature",
  "properties": {
    "iso:country":"DE",
    "sg:address":"Untere Hauptstr. 14",
    "sg:city":"Brunnen",
    "sg:phone":"+49 8454/3257",
    "sg:postcode":"86564",
    "sg:province":"Bayern",
    "wof:name":"Anton Kurzhals",
    "wof:placetype":"venue"
},
  "geometry": {"coordinates":[11.353996,48.632954],"type":"Point"}
}