{
  "type": "Feature",
  "properties": {
    "iso:country":"DE",
    "sg:city":"Welschneudorf",
    "sg:postcode":"56412",
    "sg:province":"Rheinland-Pfalz",
    "wof:name":"Carsten Wolter Dienstleistungs Gmbh",
    "wof:placetype":"venue"
},
  "geometry": {"coordinates":[7.79778,50.371559],"type":"Point"}
}