{
  "type": "Feature",
  "properties": {
    "iso:country":"DE",
    "sg:address":"Heinz-Brunner-Weg 1",
    "sg:city":"Fichtelberg",
    "sg:phone":"+49 9272/96093",
    "sg:postcode":"95686",
    "sg:province":"Bayern",
    "wof:name":"Bleamlalm Wirtshaus",
    "wof:placetype":"venue"
},
  "geometry": {"coordinates":[11.8386936188,50.0115394592],"type":"Point"}
}