{
  "type": "Feature",
  "properties": {
    "iso:country":"DE",
    "sg:address":"Rudolf-Diesel-Str 1",
    "sg:city":"Hofheim",
    "sg:phone":"+49 6122/7004284",
    "sg:postcode":"65719",
    "sg:province":"Hessen",
    "wof:name":"Aereco Gmbh",
    "wof:placetype":"venue"
},
  "geometry": {"coordinates":[8.3853816986,50.0682182312],"type":"Point"}
}