{
  "type": "Feature",
  "properties": {
    "iso:country":"DE",
    "sg:address":"He\u00dfstr. 102a",
    "sg:city":"M\u00fcnchen",
    "sg:phone":"+49 89/186865",
    "sg:postcode":"80797",
    "sg:province":"Bayern",
    "wof:name":"Eberhard Rach Kunstmaler",
    "wof:placetype":"venue"
},
  "geometry": {"coordinates":[11.558757,48.154152],"type":"Point"}
}