{
  "type": "Feature",
  "properties": {
    "iso:country":"DE",
    "sg:address":"Maarweg 34",
    "sg:city":"Rheinbreitbach",
    "sg:phone":"+49 2224/4060",
    "sg:postcode":"53619",
    "sg:province":"Rheinland-Pfalz",
    "wof:name":"Klaus Bertram & Ulrich Cabione Bedachungs- Kg",
    "wof:placetype":"venue"
},
  "geometry": {"coordinates":[7.2207069397,50.6225013733],"type":"Point"}
}