{
  "type": "Feature",
  "properties": {
    "iso:country":"DE",
    "sg:address":"Kirchstr. 21",
    "sg:city":"Schwarmstedt",
    "sg:phone":"+49 5071/1233",
    "sg:postcode":"29690",
    "sg:province":"Niedersachsen",
    "wof:name":"Grillst\u00fcbchen",
    "wof:placetype":"venue"
},
  "geometry": {"coordinates":[9.6186542511,52.6797904968],"type":"Point"}
}