{
  "type": "Feature",
  "properties": {
    "iso:country":"DE",
    "sg:address":"Asangstr. 127",
    "sg:city":"Stuttgart",
    "sg:phone":"+49 711/323304",
    "sg:postcode":"70329",
    "sg:province":"Baden-W\u00fcrttemberg",
    "wof:name":"Stanislav Horvat",
    "wof:placetype":"venue"
},
  "geometry": {"coordinates":[9.2724685669,48.7692642212],"type":"Point"}
}