{
  "type": "Feature",
  "properties": {
    "iso:country":"DE",
    "sg:address":"Bochumer Str. 1-3",
    "sg:city":"Schwetzingen",
    "sg:phone":"+49 6202/20980",
    "sg:postcode":"68723",
    "sg:province":"Baden-W\u00fcrttemberg",
    "wof:name":"Telena Fernmelde- Und Datentechnik",
    "wof:placetype":"venue"
},
  "geometry": {"coordinates":[8.5585727692,49.3978004456],"type":"Point"}
}