{
  "type": "Feature",
  "properties": {
    "iso:country":"DE",
    "sg:address":"Karl-Benz-Stra\u00dfe 15",
    "sg:city":"Gie\u00dfen",
    "sg:phone":"+49 4964/1962250",
    "sg:postcode":"35398",
    "sg:province":"Hessen",
    "wof:name":"E. Kreiling Gie\u00dfen Wir Bewegen Mit System",
    "wof:placetype":"venue"
},
  "geometry": {"coordinates":[8.64556,50.583305],"type":"Point"}
}