{
  "type": "Feature",
  "properties": {
    "iso:country":"DE",
    "sg:address":"Bahnhofstr. 16",
    "sg:city":"Meuselwitz",
    "sg:phone":"+49 3448/751733",
    "sg:postcode":"04610",
    "sg:province":"Th\u00fcringen",
    "wof:name":"Ei\u00dfner Und Kuhfu\u00df Rechtsanw\u00e4lte",
    "wof:placetype":"venue"
},
  "geometry": {"coordinates":[12.2965803146,51.0420188904],"type":"Point"}
}