{
  "type": "Feature",
  "properties": {
    "iso:country":"DE",
    "sg:address":"Rechenacker 62",
    "sg:city":"Oberhausen",
    "sg:postcode":"46045",
    "sg:province":"Nordrhein-Westfalen",
    "wof:name":"Rot-weiss Oberhausen Homepage",
    "wof:placetype":"venue"
},
  "geometry": {"coordinates":[6.843902,51.457737],"type":"Point"}
}