{
  "type": "Feature",
  "properties": {
    "iso:country":"DE",
    "sg:address":"Gutachweg 3",
    "sg:city":"St. Georgen",
    "sg:phone":"+49 7724/7404",
    "sg:postcode":"78112",
    "sg:province":"Baden-W\u00fcrttemberg",
    "wof:name":"Dieter Zuckschwerdt",
    "wof:placetype":"venue"
},
  "geometry": {"coordinates":[8.3426475525,48.1338577271],"type":"Point"}
}