{
  "type": "Feature",
  "properties": {
    "iso:country":"DE",
    "sg:address":"Eschweilerstr. 1",
    "sg:city":"Alsdorf",
    "sg:phone":"+49 2404/63293",
    "sg:postcode":"52477",
    "sg:province":"Nordrhein-Westfalen",
    "wof:name":"Evelyn Dujardin",
    "wof:placetype":"venue"
},
  "geometry": {"coordinates":[6.1857800484,50.8654899597],"type":"Point"}
}