{
  "type": "Feature",
  "properties": {
    "iso:country":"DE",
    "sg:address":"K\u00f6nigsborner Str. 35",
    "sg:city":"Biederitz",
    "sg:phone":"+49 39292/7500",
    "sg:postcode":"39175",
    "sg:province":"Sachsen-Anhalt",
    "wof:name":"Braas Dach Systeme",
    "wof:placetype":"venue"
},
  "geometry": {"coordinates":[11.746425,52.136784],"type":"Point"}
}