{
  "type": "Feature",
  "properties": {
    "iso:country":"DE",
    "sg:address":"Celler Str. 22",
    "sg:city":"Celle",
    "sg:phone":"+49 5141/54445",
    "sg:postcode":"29229",
    "sg:province":"Niedersachsen",
    "wof:name":"Grillstation I\u00df Was",
    "wof:placetype":"venue"
},
  "geometry": {"coordinates":[10.0624885559,52.6538276672],"type":"Point"}
}