{
  "type": "Feature",
  "properties": {
    "iso:country":"DE",
    "sg:address":"L\u00fcllauer Str. 27",
    "sg:city":"Jesteburg",
    "sg:phone":"+49 4183/3047",
    "sg:postcode":"21266",
    "sg:province":"Niedersachsen",
    "wof:name":"Devisio Steuerberatungsges. Mbh",
    "wof:placetype":"venue"
},
  "geometry": {"coordinates":[9.9492397308,53.3058280945],"type":"Point"}
}