{
  "type": "Feature",
  "properties": {
    "iso:country":"DE",
    "sg:address":"Kieselweg 19",
    "sg:city":"Verl",
    "sg:phone":"+49 5246/4964",
    "sg:postcode":"33415",
    "sg:province":"Nordrhein-Westfalen",
    "wof:name":"Graute & Richter Bau-vertriebs-gmbh",
    "wof:placetype":"venue"
},
  "geometry": {"coordinates":[8.5557384491,51.9043502808],"type":"Point"}
}