{
  "type": "Feature",
  "properties": {
    "iso:country":"DE",
    "sg:address":"Lange Str. 61",
    "sg:city":"Wittingen",
    "sg:phone":"+49 5831/7335",
    "sg:postcode":"29378",
    "sg:province":"Niedersachsen",
    "wof:name":"H\u00e4rchens Bierpub",
    "wof:placetype":"venue"
},
  "geometry": {"coordinates":[10.7431144714,52.7276077271],"type":"Point"}
}