{
  "type": "Feature",
  "properties": {
    "iso:country":"DE",
    "sg:address":"Meisenweg 5",
    "sg:city":"\u00d6lbronn-D\u00fcrrn",
    "sg:phone":"+49 7043/920230",
    "sg:postcode":"75248",
    "sg:province":"Baden-W\u00fcrttemberg",
    "wof:name":"Doris K\u00f6nig",
    "wof:placetype":"venue"
},
  "geometry": {"coordinates":[8.756709,48.980942],"type":"Point"}
}