{
  "type": "Feature",
  "properties": {
    "iso:country":"DE",
    "sg:address":"Josefstr. 7",
    "sg:city":"K\u00f6ln",
    "sg:phone":"+49 2203/53513",
    "sg:postcode":"51143",
    "sg:province":"Nordrhein-Westfalen",
    "wof:name":"M\u00e4ling",
    "wof:placetype":"venue"
},
  "geometry": {"coordinates":[7.057447,50.884212],"type":"Point"}
}