{
  "type": "Feature",
  "properties": {
    "iso:country":"DE",
    "sg:address":"Br\u00e4uhausstr. 26",
    "sg:city":"Neu\u00f6tting",
    "sg:phone":"+49 8671/979980",
    "sg:postcode":"84524",
    "sg:province":"Bayern",
    "wof:name":"Gerlinde Putz Steuerberaterin",
    "wof:placetype":"venue"
},
  "geometry": {"coordinates":[12.6870059967,48.2427139282],"type":"Point"}
}