{
  "type": "Feature",
  "properties": {
    "iso:country":"DE",
    "sg:address":"Marktplatz 4",
    "sg:city":"Homburg",
    "sg:phone":"+49 6841/61087",
    "sg:postcode":"66424",
    "sg:province":"Saarland",
    "wof:name":"C. Krauter",
    "wof:placetype":"venue"
},
  "geometry": {"coordinates":[7.34095,49.321239],"type":"Point"}
}