{
  "type": "Feature",
  "properties": {
    "iso:country":"DE",
    "sg:address":"Koburger Str. 45",
    "sg:city":"Markkleeberg",
    "sg:phone":"+49 341/3587725",
    "sg:postcode":"04416",
    "sg:province":"Sachsen",
    "wof:name":"H. Wiebelitz",
    "wof:placetype":"venue"
},
  "geometry": {"coordinates":[12.364376,51.283657],"type":"Point"}
}