{
  "type": "Feature",
  "properties": {
    "iso:country":"DE",
    "sg:address":"Schulstr.",
    "sg:city":"Liebenau",
    "sg:phone":"+49 5023/441",
    "sg:postcode":"31618",
    "sg:province":"Niedersachsen",
    "wof:name":"Gemeindeb\u00fccherei",
    "wof:placetype":"venue"
},
  "geometry": {"coordinates":[9.089846,52.602737],"type":"Point"}
}