{
  "type": "Feature",
  "properties": {
    "iso:country":"DE",
    "sg:address":"Backhausstr. 25",
    "sg:city":"Heilbronn",
    "sg:phone":"+49 7131/484791",
    "sg:postcode":"74078",
    "sg:province":"Baden-W\u00fcrttemberg",
    "wof:name":"T. Weiss",
    "wof:placetype":"venue"
},
  "geometry": {"coordinates":[9.170535,49.158096],"type":"Point"}
}