{
  "type": "Feature",
  "properties": {
    "iso:country":"DE",
    "sg:address":"Kaiserin-Augusta-Allee 90",
    "sg:city":"Berlin",
    "sg:phone":"+49 30/3441162",
    "sg:postcode":"10589",
    "sg:province":"Berlin",
    "wof:name":"Rudolf K\u00f6nig",
    "wof:placetype":"venue"
},
  "geometry": {"coordinates":[13.3103322983,52.5256118774],"type":"Point"}
}