{
  "type": "Feature",
  "properties": {
    "iso:country":"DE",
    "sg:address":"Schadowstr. 72",
    "sg:city":"D\u00fcsseldorf",
    "sg:phone":"+49 211/369055",
    "sg:postcode":"40212",
    "sg:province":"Nordrhein-Westfalen",
    "wof:name":"Dirk Bachmann Rechtsanwalt",
    "wof:placetype":"venue"
},
  "geometry": {"coordinates":[6.7823300362,51.2262382507],"type":"Point"}
}