{
  "type": "Feature",
  "properties": {
    "iso:country":"DE",
    "sg:address":"Feuerwehrstr. 5",
    "sg:city":"Singen",
    "sg:phone":"+49 7731/41147",
    "sg:postcode":"78224",
    "sg:province":"Baden-W\u00fcrttemberg",
    "wof:name":"Rolf Wick Rechtsanwalt",
    "wof:placetype":"venue"
},
  "geometry": {"coordinates":[8.8354291916,47.7630004883],"type":"Point"}
}