{
  "type": "Feature",
  "properties": {
    "iso:country":"DE",
    "sg:address":"Hauptstr. 6",
    "sg:city":"H\u00f6chstadt",
    "sg:phone":"+49 9193/5611",
    "sg:postcode":"91315",
    "sg:province":"Bayern",
    "wof:name":"M. Kramer",
    "wof:placetype":"venue"
},
  "geometry": {"coordinates":[10.8049564362,49.7032051086],"type":"Point"}
}