{
  "type": "Feature",
  "properties": {
    "iso:country":"DE",
    "sg:address":"Illerstr. 57",
    "sg:city":"Braunschweig",
    "sg:postcode":"38120",
    "sg:province":"Niedersachsen",
    "wof:name":"Arbeitsgemeinschaft Broitzemer Vereine E. V.",
    "wof:placetype":"venue"
},
  "geometry": {"coordinates":[10.480632782,52.2415390015],"type":"Point"}
}