{
  "type": "Feature",
  "properties": {
    "iso:country":"DE",
    "sg:address":"Kerkener Str. 25",
    "sg:city":"Kempen",
    "sg:phone":"+49 2152/50440",
    "sg:postcode":"47906",
    "sg:province":"Nordrhein-Westfalen",
    "wof:name":"Wachdienst Grenzland Wilhelm Smerz Kg",
    "wof:placetype":"venue"
},
  "geometry": {"coordinates":[6.4163308144,51.368434906],"type":"Point"}
}