{
  "type": "Feature",
  "properties": {
    "iso:country":"DE",
    "sg:address":"Selbachstr. 27",
    "sg:city":"Euskirchen",
    "sg:phone":"+49 2251/61470",
    "sg:postcode":"53879",
    "sg:province":"Nordrhein-Westfalen",
    "wof:name":"Ralf Morschh\u00e4user Tennislehrer",
    "wof:placetype":"venue"
},
  "geometry": {"coordinates":[6.7849531174,50.6470336914],"type":"Point"}
}