{
  "type": "Feature",
  "properties": {
    "iso:country":"DE",
    "sg:address":"Stadtplatz 24",
    "sg:city":"Geiselh\u00f6ring",
    "sg:phone":"+49 9423/1475",
    "sg:postcode":"94333",
    "sg:province":"Bayern",
    "wof:name":"Raiffeisenbank Geiselh\u00f6ring Eg",
    "wof:placetype":"venue"
},
  "geometry": {"coordinates":[12.393951,48.826225],"type":"Point"}
}