{
  "type": "Feature",
  "properties": {
    "iso:country":"DE",
    "sg:address":"Ottostra\u00dfe 8",
    "sg:city":"Hofolding",
    "sg:phone":"+49 8104",
    "sg:postcode":"85649",
    "sg:province":"Bayern",
    "wof:name":"Cotec - Pap Vertrieb E.k.",
    "wof:placetype":"venue"
},
  "geometry": {"coordinates":[11.70771,47.984417],"type":"Point"}
}