{
  "type": "Feature",
  "properties": {
    "iso:country":"DE",
    "sg:address":"Niedernfeldweg 56",
    "sg:city":"Detmold",
    "sg:phone":"+49 5231/68704",
    "sg:postcode":"32758",
    "sg:province":"Nordrhein-Westfalen",
    "wof:name":"Eva Gwiasda Korbwaren",
    "wof:placetype":"venue"
},
  "geometry": {"coordinates":[8.8430833817,51.9519195557],"type":"Point"}
}