{
  "type": "Feature",
  "properties": {
    "iso:country":"DE",
    "sg:address":"Herzog-Wilhelm-Str. 68",
    "sg:city":"Bad Harzburg",
    "sg:phone":"+49 5322/2652",
    "sg:postcode":"38667",
    "sg:province":"Niedersachsen",
    "wof:name":"Wohnoase Wohnungs- Und Siedlungsbau",
    "wof:placetype":"venue"
},
  "geometry": {"coordinates":[10.5598306656,51.8806533813],"type":"Point"}
}