{
  "type": "Feature",
  "properties": {
    "iso:country":"DE",
    "sg:address":"Rathausstr. 18",
    "sg:city":"Gro\u00dfostheim",
    "sg:phone":"+49 6026/4677",
    "sg:postcode":"63762",
    "sg:province":"Bayern",
    "wof:name":"Edgar Peter",
    "wof:placetype":"venue"
},
  "geometry": {"coordinates":[9.059267,49.908653],"type":"Point"}
}