{
  "type": "Feature",
  "properties": {
    "iso:country":"DE",
    "sg:address":"Ostring 44",
    "sg:city":"G\u00f6rlitz",
    "sg:phone":"+49 3581/314691",
    "sg:postcode":"02828",
    "sg:province":"Sachsen",
    "wof:name":"Christian Jurke",
    "wof:placetype":"venue"
},
  "geometry": {"coordinates":[14.98175,51.172825],"type":"Point"}
}