{
  "type": "Feature",
  "properties": {
    "iso:country":"DE",
    "sg:address":"K\u00f6llertalstr. 66 A",
    "sg:city":"Heusweiler",
    "sg:postcode":"66265",
    "sg:province":"Saarland",
    "wof:name":"Weyrich & Partner Gmbh",
    "wof:placetype":"venue"
},
  "geometry": {"coordinates":[7.0093111992,49.3577804565],"type":"Point"}
}