{
  "type": "Feature",
  "properties": {
    "iso:country":"DE",
    "sg:address":"Kirchhofstr. 32",
    "sg:city":"Hilden",
    "sg:phone":"+49 2103/66820",
    "sg:postcode":"40721",
    "sg:province":"Nordrhein-Westfalen",
    "wof:name":"R. Gutsch Immobilienmakler",
    "wof:placetype":"venue"
},
  "geometry": {"coordinates":[6.9390511513,51.1661109924],"type":"Point"}
}