{
  "type": "Feature",
  "properties": {
    "iso:country":"DE",
    "sg:address":"Turmstr. 1",
    "sg:city":"Gro\u00dfostheim",
    "sg:phone":"+49 6026/993160",
    "sg:postcode":"63762",
    "sg:province":"Bayern",
    "wof:name":"Restaurant Paparazzi",
    "wof:placetype":"venue"
},
  "geometry": {"coordinates":[9.0747785568,49.9176940918],"type":"Point"}
}