{
  "type": "Feature",
  "properties": {
    "iso:country":"DE",
    "sg:address":"Am Wittenkamp 6",
    "sg:city":"Weyhe",
    "sg:postcode":"28844",
    "sg:province":"Niedersachsen",
    "wof:name":"Holl\u00e4ndische Nu\u00dfbar Gmbh",
    "wof:placetype":"venue"
},
  "geometry": {"coordinates":[8.8007354736,52.998500824],"type":"Point"}
}