{
  "type": "Feature",
  "properties": {
    "iso:country":"DE",
    "sg:address":"Brakeler Str. 20",
    "sg:city":"Bad Driburg",
    "sg:postcode":"33014",
    "sg:province":"Nordrhein-Westfalen",
    "wof:name":"Burkhard Saabel Gmbh",
    "wof:placetype":"venue"
},
  "geometry": {"coordinates":[9.032286,51.729801],"type":"Point"}
}