{
  "type": "Feature",
  "properties": {
    "iso:country":"DE",
    "sg:address":"Bergstr. 7",
    "sg:city":"Langenberg",
    "sg:phone":"+49 5248/609573",
    "sg:postcode":"33449",
    "sg:province":"Nordrhein-Westfalen",
    "wof:name":"Alfons H\u00f6lscher",
    "wof:placetype":"venue"
},
  "geometry": {"coordinates":[8.307049,51.757233],"type":"Point"}
}