{
  "type": "Feature",
  "properties": {
    "iso:country":"DE",
    "sg:address":"Hauptstr. 12",
    "sg:city":"Stra\u00dfberg",
    "sg:phone":"+49 7434/608",
    "sg:postcode":"72479",
    "sg:province":"Baden-W\u00fcrttemberg",
    "wof:name":"Anton B\u00f6hringer",
    "wof:placetype":"venue"
},
  "geometry": {"coordinates":[9.096283,48.159405],"type":"Point"}
}