{
  "type": "Feature",
  "properties": {
    "iso:country":"DE",
    "sg:address":"Friedrich-Ebert-Platz 2",
    "sg:city":"M\u00fcnster",
    "sg:phone":"+49 251/521059",
    "sg:postcode":"48153",
    "sg:province":"Nordrhein-Westfalen",
    "wof:name":"Mediteam Laboratorien Verwaltungsgesellschaft Mbh",
    "wof:placetype":"venue"
},
  "geometry": {"coordinates":[7.6315951347,51.9515190125],"type":"Point"}
}