{
  "type": "Feature",
  "properties": {
    "iso:country":"DE",
    "sg:address":"Landstr. 38",
    "sg:city":"Barsinghausen",
    "sg:postcode":"30890",
    "sg:province":"Niedersachsen",
    "wof:name":"As Tief- Und Rohrleitungsbau Gmbh",
    "wof:placetype":"venue"
},
  "geometry": {"coordinates":[9.50502491,52.2998428345],"type":"Point"}
}