{
  "type": "Feature",
  "properties": {
    "iso:country":"DE",
    "sg:address":"Elbuferstr. 141",
    "sg:city":"Neu Darchau",
    "sg:phone":"+49 5853/1822",
    "sg:postcode":"29490",
    "sg:province":"Niedersachsen",
    "wof:name":"Gastst\u00e4tte Zum G\u00f6pel",
    "wof:placetype":"venue"
},
  "geometry": {"coordinates":[10.8978996277,53.2284011841],"type":"Point"}
}