{
  "type": "Feature",
  "properties": {
    "iso:country":"DE",
    "sg:address":"Schifferstr. 10",
    "sg:city":"K\u00f6ln",
    "sg:phone":"+49 221/9711082",
    "sg:postcode":"50735",
    "sg:province":"Nordrhein-Westfalen",
    "wof:name":"Jorda Gmbh",
    "wof:placetype":"venue"
},
  "geometry": {"coordinates":[6.9623022079,50.9896812439],"type":"Point"}
}