{
  "type": "Feature",
  "properties": {
    "iso:country":"DE",
    "sg:address":"Zum Katharinentor 4",
    "sg:city":"Hennef",
    "sg:phone":"+49 2248/2694",
    "sg:postcode":"53773",
    "sg:province":"Nordrhein-Westfalen",
    "wof:name":"Schlosserei St\u00f6cker Gmbh",
    "wof:placetype":"venue"
},
  "geometry": {"coordinates":[7.386303,50.748501],"type":"Point"}
}