{
  "type": "Feature",
  "properties": {
    "iso:country":"DE",
    "sg:address":"Feldkircher Str. 100",
    "sg:city":"Neuwied",
    "sg:phone":"+49 2631/9700",
    "sg:postcode":"56567",
    "sg:province":"Rheinland-Pfalz",
    "wof:name":"Landesheim Und Schule F\u00fcr Blinde Und Sehbehinderte",
    "wof:placetype":"venue"
},
  "geometry": {"coordinates":[7.4299,50.451389],"type":"Point"}
}