{
  "type": "Feature",
  "properties": {
    "iso:country":"DE",
    "sg:address":"Hochstr. 12",
    "sg:city":"Andernach",
    "sg:phone":"+49 2632/48111",
    "sg:postcode":"56626",
    "sg:province":"Rheinland-Pfalz",
    "wof:name":"Hans Werner Boers",
    "wof:placetype":"venue"
},
  "geometry": {"coordinates":[7.3969931602,50.4399604797],"type":"Point"}
}