{
  "type": "Feature",
  "properties": {
    "iso:country":"DE",
    "sg:address":"Freiheitsstr. 3",
    "sg:city":"Selb",
    "sg:phone":"+49 9287/87102",
    "sg:postcode":"95100",
    "sg:province":"Bayern",
    "wof:name":"Irene Pohl",
    "wof:placetype":"venue"
},
  "geometry": {"coordinates":[12.132216,50.163933],"type":"Point"}
}