{
  "type": "Feature",
  "properties": {
    "iso:country":"DE",
    "sg:address":"Springstr. 24",
    "sg:city":"G\u00f6ttingen",
    "sg:phone":"+49 551/32180",
    "sg:postcode":"37077",
    "sg:province":"Niedersachsen",
    "wof:name":"G\u00fcnter Waldmann",
    "wof:placetype":"venue"
},
  "geometry": {"coordinates":[9.93736,51.564003],"type":"Point"}
}