{
  "type": "Feature",
  "properties": {
    "iso:country":"DE",
    "sg:address":"Schleinkoferstr 16",
    "sg:city":"Ettlingen",
    "sg:phone":"+49 7243/304810",
    "sg:postcode":"76275",
    "sg:province":"Baden-W\u00fcrttemberg",
    "wof:name":"B\u00fcro Prochazka Agentur F\u00fcr Direktmarketing Gmbh",
    "wof:placetype":"venue"
},
  "geometry": {"coordinates":[8.39634,48.9394],"type":"Point"}
}