{
  "type": "Feature",
  "properties": {
    "iso:country":"DE",
    "sg:address":"Osningstr. 18",
    "sg:city":"G\u00fctersloh",
    "sg:phone":"+49 5241/4234",
    "sg:postcode":"33332",
    "sg:province":"Nordrhein-Westfalen",
    "wof:name":"Werner Kieke",
    "wof:placetype":"venue"
},
  "geometry": {"coordinates":[8.3913698196,51.879447937],"type":"Point"}
}