{
  "type": "Feature",
  "properties": {
    "iso:country":"DE",
    "sg:address":"K\u00f6pfelweg 41",
    "sg:city":"Heidelberg",
    "sg:phone":"+49 6221/803009",
    "sg:postcode":"69118",
    "sg:province":"Baden-W\u00fcrttemberg",
    "wof:name":"J. Ziegler Malerfachbetrieb Gmbh",
    "wof:placetype":"venue"
},
  "geometry": {"coordinates":[8.744869,49.423431],"type":"Point"}
}