{
  "type": "Feature",
  "properties": {
    "iso:country":"DE",
    "sg:address":"Adelbylund 11",
    "sg:city":"Flensburg",
    "sg:phone":"+49 461/670370",
    "sg:postcode":"24943",
    "sg:province":"Schleswig-Holstein",
    "wof:name":"Frank Singhofen Rosemarie Gergen",
    "wof:placetype":"venue"
},
  "geometry": {"coordinates":[9.4519271851,54.7818145752],"type":"Point"}
}