{
  "type": "Feature",
  "properties": {
    "iso:country":"DE",
    "sg:address":"Hundslohweg 11",
    "sg:city":"Unterschneidheim",
    "sg:phone":"+49 7966/442",
    "sg:postcode":"73485",
    "sg:province":"Baden-W\u00fcrttemberg",
    "wof:name":"Wilhelm Pflanz",
    "wof:placetype":"venue"
},
  "geometry": {"coordinates":[10.324989,48.94112],"type":"Point"}
}