{
  "type": "Feature",
  "properties": {
    "iso:country":"DE",
    "sg:address":"Rechts am G\u00e4\u00dfchen 1",
    "sg:city":"Bolanden",
    "sg:postcode":"67295",
    "sg:province":"Rheinland-Pfalz",
    "wof:name":"Bau-form Gmbh",
    "wof:placetype":"venue"
},
  "geometry": {"coordinates":[8.005519,49.638813],"type":"Point"}
}