{
  "type": "Feature",
  "properties": {
    "iso:country":"DE",
    "sg:address":"Eisenbahnstr. 30 /1",
    "sg:city":"Ravensburg",
    "sg:phone":"+49 751/15052",
    "sg:postcode":"88212",
    "sg:province":"Baden-W\u00fcrttemberg",
    "wof:name":"Barbara Hahne Ergotherapie",
    "wof:placetype":"venue"
},
  "geometry": {"coordinates":[9.608655,47.78373],"type":"Point"}
}