{
  "type": "Feature",
  "properties": {
    "iso:country":"DE",
    "sg:address":"Friedrich-Wilhelm-Str. 45",
    "sg:city":"Duisburg",
    "sg:phone":"+49 203/27879",
    "sg:postcode":"47051",
    "sg:province":"Nordrhein-Westfalen",
    "wof:name":"Park-apotheke Marco Balzert",
    "wof:placetype":"venue"
},
  "geometry": {"coordinates":[6.765884,51.431347],"type":"Point"}
}