{
  "type": "Feature",
  "properties": {
    "iso:country":"DE",
    "sg:address":"Lippweg 9",
    "sg:city":"Beckum",
    "sg:phone":"+49 2521/3103",
    "sg:postcode":"59269",
    "sg:province":"Nordrhein-Westfalen",
    "wof:name":"Herbert Bl\u00f6meke",
    "wof:placetype":"venue"
},
  "geometry": {"coordinates":[8.047581,51.753857],"type":"Point"}
}