{
  "type": "Feature",
  "properties": {
    "iso:country":"DE",
    "sg:address":"M\u00fchlheimer Str. 63",
    "sg:city":"Empfingen",
    "sg:phone":"+49 7485/234",
    "sg:postcode":"72186",
    "sg:province":"Baden-W\u00fcrttemberg",
    "wof:name":"B\u00fcrgerst\u00fcble",
    "wof:placetype":"venue"
},
  "geometry": {"coordinates":[8.707365036,48.3911743164],"type":"Point"}
}