{
  "type": "Feature",
  "properties": {
    "iso:country":"DE",
    "sg:address":"Hauptstr. 28",
    "sg:city":"Malschwitz",
    "sg:phone":"+49 35932/552",
    "sg:postcode":"02694",
    "sg:province":"Sachsen",
    "wof:name":"E. M\u00f6nnich",
    "wof:placetype":"venue"
},
  "geometry": {"coordinates":[14.588658,51.234413],"type":"Point"}
}