{
  "type": "Feature",
  "properties": {
    "iso:country":"DE",
    "sg:address":"Fischenbergstr. 8",
    "sg:city":"Witten",
    "sg:phone":"+49 2302/21534",
    "sg:postcode":"58455",
    "sg:province":"Nordrhein-Westfalen",
    "wof:name":"Lahrs\u00f6 Psychoingenieurb\u00fcro G\u00fcnther Lahr",
    "wof:placetype":"venue"
},
  "geometry": {"coordinates":[7.3177747726,51.4376907349],"type":"Point"}
}