{
  "type": "Feature",
  "properties": {
    "iso:country":"DE",
    "sg:address":"Butzheimer Str. 12",
    "sg:city":"K\u00f6ln",
    "sg:phone":"+49 221/799544",
    "sg:postcode":"50767",
    "sg:province":"Nordrhein-Westfalen",
    "wof:name":"K. Steinhauer",
    "wof:placetype":"venue"
},
  "geometry": {"coordinates":[6.896199,51.016083],"type":"Point"}
}