{
  "type": "Feature",
  "properties": {
    "iso:country":"DE",
    "sg:address":"Heerstr. 32",
    "sg:city":"Stuttgart",
    "sg:postcode":"70563",
    "sg:province":"Baden-W\u00fcrttemberg",
    "wof:name":"M. Schmid Gmbh",
    "wof:placetype":"venue"
},
  "geometry": {"coordinates":[9.1008338928,48.732624054],"type":"Point"}
}