{
  "type": "Feature",
  "properties": {
    "iso:country":"DE",
    "sg:address":"Goethestr. 3",
    "sg:city":"Langendorf",
    "sg:phone":"+49 3443/232235",
    "sg:postcode":"06667",
    "sg:province":"Sachsen-Anhalt",
    "wof:name":"Wolf Gmbh",
    "wof:placetype":"venue"
},
  "geometry": {"coordinates":[11.9606990814,51.1824798584],"type":"Point"}
}