{
  "type": "Feature",
  "properties": {
    "iso:country":"DE",
    "sg:address":"Celler Str. 2 a",
    "sg:city":"Schwarmstedt",
    "sg:phone":"+49 5071/8201",
    "sg:postcode":"29690",
    "sg:province":"Niedersachsen",
    "wof:name":"Roseanne",
    "wof:placetype":"venue"
},
  "geometry": {"coordinates":[9.62884,52.680065],"type":"Point"}
}