{
  "type": "Feature",
  "properties": {
    "iso:country":"DE",
    "sg:address":"Charlottenstr. 10",
    "sg:city":"Ansbach",
    "sg:phone":"+49 981/3981",
    "sg:postcode":"91522",
    "sg:province":"Bayern",
    "wof:name":"Dieter Scholz Architekt",
    "wof:placetype":"venue"
},
  "geometry": {"coordinates":[10.587595,49.302624],"type":"Point"}
}