{
  "type": "Feature",
  "properties": {
    "iso:country":"DE",
    "sg:address":"Oberboshasel 5",
    "sg:city":"Heiligenberg",
    "sg:phone":"+49 7554/98051",
    "sg:postcode":"88633",
    "sg:province":"Baden-W\u00fcrttemberg",
    "wof:name":"S. Lappas",
    "wof:placetype":"venue"
},
  "geometry": {"coordinates":[9.340612,47.852585],"type":"Point"}
}