{
  "type": "Feature",
  "properties": {
    "iso:country":"DE",
    "sg:address":"Westerwaldstr.",
    "sg:city":"Herborn",
    "sg:postcode":"35745",
    "sg:province":"Hessen",
    "wof:name":"Ticket Shop In Lahn Dill Kreis",
    "wof:placetype":"venue"
},
  "geometry": {"coordinates":[8.300103,50.677284],"type":"Point"}
}