{
  "type": "Feature",
  "properties": {
    "iso:country":"DE",
    "sg:address":"Ziegelbrenner Str. 19",
    "sg:city":"Sarstedt",
    "sg:phone":"+49 4950/667583",
    "sg:postcode":"31157",
    "sg:province":"Niedersachsen",
    "wof:name":"Gummiwarenfabrik Tex Gmbh",
    "wof:placetype":"venue"
},
  "geometry": {"coordinates":[9.8463220596,52.2341804504],"type":"Point"}
}