{
  "type": "Feature",
  "properties": {
    "iso:country":"DE",
    "sg:address":"Ostwall 20",
    "sg:city":"Bocholt",
    "sg:phone":"+49 2871/13360",
    "sg:postcode":"46397",
    "sg:province":"Nordrhein-Westfalen",
    "wof:name":"Dr. Wilhelm Van Aalten Rechtsanwalt",
    "wof:placetype":"venue"
},
  "geometry": {"coordinates":[6.6182341576,51.8414611816],"type":"Point"}
}