{
  "type": "Feature",
  "properties": {
    "iso:country":"DE",
    "sg:address":"Marktstr. 29",
    "sg:city":"Blankenburg",
    "sg:phone":"+49 3944/2182",
    "sg:postcode":"38889",
    "sg:province":"Sachsen-Anhalt",
    "wof:name":"Blankenburger Beschlaghandel Gmbh",
    "wof:placetype":"venue"
},
  "geometry": {"coordinates":[10.957242,51.788811],"type":"Point"}
}