{
  "type": "Feature",
  "properties": {
    "iso:country":"DE",
    "sg:address":"Schulthei\u00dfstr. 20",
    "sg:city":"Br\u00fchl",
    "sg:phone":"+49 2232/23912",
    "sg:postcode":"50321",
    "sg:province":"Nordrhein-Westfalen",
    "wof:name":"Br\u00fchler Skatfreunde 76 Kurt Pobanz",
    "wof:placetype":"venue"
},
  "geometry": {"coordinates":[6.8948950768,50.8421592712],"type":"Point"}
}