{
  "type": "Feature",
  "properties": {
    "iso:country":"DE",
    "sg:address":"Olsdorfer Str. 13",
    "sg:city":"Sankt Peter-Ording",
    "sg:phone":"+49 4863/2500",
    "sg:postcode":"25826",
    "sg:province":"Schleswig-Holstein",
    "wof:name":"Olsdorfer Krug",
    "wof:placetype":"venue"
},
  "geometry": {"coordinates":[8.6382761002,54.3053359985],"type":"Point"}
}