{
  "type": "Feature",
  "properties": {
    "iso:country":"DE",
    "sg:address":"Zwickauer Damm 5",
    "sg:city":"Berlin",
    "sg:postcode":"12353",
    "sg:province":"Berlin",
    "wof:name":"Aldi Gmbh & Co. Kg",
    "wof:placetype":"venue"
},
  "geometry": {"coordinates":[13.4848098755,52.4232788086],"type":"Point"}
}