{
  "type": "Feature",
  "properties": {
    "iso:country":"DE",
    "sg:address":"Forstweg 6",
    "sg:city":"Dr\u00fcbeck",
    "sg:phone":"+49 39452/2743",
    "sg:postcode":"38871",
    "sg:province":"Sachsen-Anhalt",
    "wof:name":"Wilfried B\u00fcldt",
    "wof:placetype":"venue"
},
  "geometry": {"coordinates":[10.72094,51.856075],"type":"Point"}
}