{
  "type": "Feature",
  "properties": {
    "iso:country":"DE",
    "sg:address":"Kaiserstr. 81",
    "sg:city":"Hauptstuhl",
    "sg:phone":"+49 6372/92720",
    "sg:postcode":"66851",
    "sg:province":"Rheinland-Pfalz",
    "wof:name":"Emb Gesellschaft F\u00fcr Hoch - Und Ingenieurbau Mbh",
    "wof:placetype":"venue"
},
  "geometry": {"coordinates":[7.483324,49.400112],"type":"Point"}
}