{
  "type": "Feature",
  "properties": {
    "iso:country":"DE",
    "sg:address":"Dolleschelstr. 11",
    "sg:city":"M\u00fcnchen",
    "sg:phone":"+49 89/3137569",
    "sg:postcode":"80937",
    "sg:province":"Bayern",
    "wof:name":"Ernst Gei\u00dfert",
    "wof:placetype":"venue"
},
  "geometry": {"coordinates":[11.565497,48.208778],"type":"Point"}
}