{
  "type": "Feature",
  "properties": {
    "iso:country":"DE",
    "sg:address":"Heinrich-Heine-Str. 19",
    "sg:city":"Wurzbach",
    "sg:phone":"+49 36652/23014",
    "sg:postcode":"07343",
    "sg:province":"Th\u00fcringen",
    "wof:name":"I. Dittmar",
    "wof:placetype":"venue"
},
  "geometry": {"coordinates":[11.545208,50.465637],"type":"Point"}
}