{
  "type": "Feature",
  "properties": {
    "iso:country":"DE",
    "sg:address":"S\u00fclldorfer Landstr. 58",
    "sg:city":"Hamburg",
    "sg:phone":"+49 40/871816",
    "sg:postcode":"22589",
    "sg:province":"Hamburg",
    "wof:name":"Restaurant Aalreuse",
    "wof:placetype":"venue"
},
  "geometry": {"coordinates":[9.8139343262,53.5781173706],"type":"Point"}
}