{
  "type": "Feature",
  "properties": {
    "iso:country":"DE",
    "sg:address":"Kleinwolmsdorfer Str. 3",
    "sg:city":"Arnsdorf",
    "sg:phone":"+49 35200/24275",
    "sg:postcode":"01477",
    "sg:province":"Sachsen",
    "wof:name":"K. Und E. G\u00fcnther",
    "wof:placetype":"venue"
},
  "geometry": {"coordinates":[13.983432,51.091454],"type":"Point"}
}