{
  "type": "Feature",
  "properties": {
    "iso:country":"DE",
    "sg:address":"Menzelstr. 3",
    "sg:city":"Potsdam",
    "sg:phone":"+49 331/2803979",
    "sg:postcode":"14467",
    "sg:province":"Brandenburg",
    "wof:name":"Intelligenz System Transfer Potsdam Ges. F\u00fcr Entw. Und",
    "wof:placetype":"venue"
},
  "geometry": {"coordinates":[13.0845947266,52.4134101868],"type":"Point"}
}