{
  "type": "Feature",
  "properties": {
    "iso:country":"DE",
    "sg:address":"Moehlenweg 3",
    "sg:city":"Klein Kussewitz",
    "sg:phone":"+49 38202/29854",
    "sg:postcode":"18184",
    "sg:province":"Mecklenburg-Vorpommern",
    "wof:name":"Mvu Umwelt Technologie Gmbh",
    "wof:placetype":"venue"
},
  "geometry": {"coordinates":[12.2561578751,54.1580123901],"type":"Point"}
}