{
  "type": "Feature",
  "properties": {
    "iso:country":"DE",
    "sg:address":"Malkastenstr. 3",
    "sg:city":"D\u00fcsseldorf",
    "sg:phone":"+49 211/176940",
    "sg:postcode":"40211",
    "sg:province":"Nordrhein-Westfalen",
    "wof:name":"Sartid Stahl Gmbh",
    "wof:placetype":"venue"
},
  "geometry": {"coordinates":[6.788012,51.23048],"type":"Point"}
}