{
  "type": "Feature",
  "properties": {
    "iso:country":"DE",
    "sg:address":"Tulpenweg 18",
    "sg:city":"Magstadt",
    "sg:phone":"+49 7159/41857",
    "sg:postcode":"71106",
    "sg:province":"Baden-W\u00fcrttemberg",
    "wof:name":"Maximilian Wallerer Steuerberater",
    "wof:placetype":"venue"
},
  "geometry": {"coordinates":[8.9704799652,48.7470207214],"type":"Point"}
}