{
  "type": "Feature",
  "properties": {
    "iso:country":"DE",
    "sg:address":"Bahnhofstr. 18",
    "sg:city":"Radebeul",
    "sg:phone":"+49 351/8305737",
    "sg:postcode":"01445",
    "sg:province":"Sachsen",
    "wof:name":"R. Strau\u00df",
    "wof:placetype":"venue"
},
  "geometry": {"coordinates":[13.629378,51.106281],"type":"Point"}
}