{
  "type": "Feature",
  "properties": {
    "iso:country":"DE",
    "sg:address":"Pfingstanger 8",
    "sg:city":"Herzberg / Harz",
    "sg:phone":"+49 5521/72626",
    "sg:postcode":"37412",
    "sg:province":"Niedersachsen",
    "wof:name":"K\u00fcke & Lisson",
    "wof:placetype":"venue"
},
  "geometry": {"coordinates":[10.3308067322,51.6568107605],"type":"Point"}
}