{
  "type": "Feature",
  "properties": {
    "iso:country":"DE",
    "sg:address":"Burkhartstr. 13",
    "sg:city":"Mallersdorf-Pfaffenberg",
    "sg:phone":"+49 8772/915238",
    "sg:postcode":"84066",
    "sg:province":"Bayern",
    "wof:name":"Michael Ziegler",
    "wof:placetype":"venue"
},
  "geometry": {"coordinates":[12.235426,48.77422],"type":"Point"}
}