{
  "type": "Feature",
  "properties": {
    "iso:country":"DE",
    "sg:address":"Schwatlostr. 8",
    "sg:city":"Berlin",
    "sg:phone":"+49 30/7124993",
    "sg:postcode":"12207",
    "sg:province":"Berlin",
    "wof:name":"Pfannstiels Logibyte Beteiligungs Gmbh",
    "wof:placetype":"venue"
},
  "geometry": {"coordinates":[13.309489,52.418842],"type":"Point"}
}