{
  "type": "Feature",
  "properties": {
    "iso:country":"DE",
    "sg:address":"Oberurseler Str.77",
    "sg:city":"Kronberg",
    "sg:postcode":"61476",
    "sg:province":"Hessen",
    "wof:name":"Altenpflege-software",
    "wof:placetype":"venue"
},
  "geometry": {"coordinates":[8.549474,50.185158],"type":"Point"}
}