{
  "type": "Feature",
  "properties": {
    "iso:country":"DE",
    "sg:address":"Torgasse 1",
    "sg:city":"M\u00fcnchberg",
    "sg:phone":"+49 9251/99220",
    "sg:postcode":"95213",
    "sg:province":"Bayern",
    "wof:name":"Hans-j\u00fcrgen M\u00fcller Rechtsanwalt",
    "wof:placetype":"venue"
},
  "geometry": {"coordinates":[11.7884702682,50.1916618347],"type":"Point"}
}