{
  "type": "Feature",
  "properties": {
    "iso:country":"DE",
    "sg:address":"Dorfstr. 45",
    "sg:city":"Wolkenburg-Kaufungen",
    "sg:phone":"+49 37609/5259",
    "sg:postcode":"08399",
    "wof:name":"Gyula Hosszu Gmbh",
    "wof:placetype":"venue"
},
  "geometry": {"coordinates":[12.66942,50.900372],"type":"Point"}
}