{
  "type": "Feature",
  "properties": {
    "iso:country":"DE",
    "sg:address":"Am Anger 3",
    "sg:city":"Zerbst",
    "sg:phone":"+49 3923/61882",
    "sg:postcode":"39261",
    "sg:province":"Sachsen-Anhalt",
    "wof:name":"Siegfried Taube",
    "wof:placetype":"venue"
},
  "geometry": {"coordinates":[12.088835,51.973213],"type":"Point"}
}