{
  "type": "Feature",
  "properties": {
    "iso:country":"DE",
    "sg:address":"Sutthauser Str. 81",
    "sg:city":"Georgsmarienh\u00fctte",
    "sg:phone":"+49 5401/2900",
    "sg:postcode":"49124",
    "sg:province":"Niedersachsen",
    "wof:name":"Ludger Meyer",
    "wof:placetype":"venue"
},
  "geometry": {"coordinates":[8.015306,52.229488],"type":"Point"}
}