{
  "type": "Feature",
  "properties": {
    "iso:country":"DE",
    "sg:address":"Aarstr.8",
    "sg:city":"Hohenstein",
    "sg:phone":"+49 451/5859493",
    "sg:postcode":"65329",
    "sg:province":"Hessen",
    "wof:name":"Potentielles) Motorrad-paradies Zu Verkaufen!",
    "wof:placetype":"venue"
},
  "geometry": {"coordinates":[8.0574102402,50.196559906],"type":"Point"}
}