{
  "type": "Feature",
  "properties": {
    "iso:country":"DE",
    "sg:address":"R\u00fcbezahlstr. 1",
    "sg:city":"Augsburg",
    "sg:phone":"+49 821/34618",
    "sg:postcode":"86179",
    "sg:province":"Bayern",
    "wof:name":"Ev. Luth. Pfarramt",
    "wof:placetype":"venue"
},
  "geometry": {"coordinates":[10.900261879,48.309135437],"type":"Point"}
}