{
  "type": "Feature",
  "properties": {
    "iso:country":"DE",
    "sg:address":"M\u00fchlenstr. 51",
    "sg:city":"Jever",
    "sg:phone":"+49 4461/3182",
    "sg:postcode":"26441",
    "sg:province":"Niedersachsen",
    "wof:name":"M. Dering-janssen",
    "wof:placetype":"venue"
},
  "geometry": {"coordinates":[7.9080471992,53.5702056885],"type":"Point"}
}