{
  "type": "Feature",
  "properties": {
    "iso:country":"DE",
    "sg:address":"Albrecht-D\u00fcrer-Str. 4",
    "sg:city":"Obertshausen",
    "sg:phone":"+49 6104/41415",
    "sg:postcode":"63179",
    "sg:province":"Hessen",
    "wof:name":"Martin Schreiner",
    "wof:placetype":"venue"
},
  "geometry": {"coordinates":[8.8562908173,50.070526123],"type":"Point"}
}