{
  "type": "Feature",
  "properties": {
    "iso:country":"DE",
    "sg:address":"Nibelungenring 7a",
    "sg:city":"Mannheim",
    "sg:phone":"+49 621/8620090",
    "sg:postcode":"68199",
    "sg:province":"Baden-W\u00fcrttemberg",
    "wof:name":"Kleeblatt - Textilpflege- Und Dienstleistungs Gmbh",
    "wof:placetype":"venue"
},
  "geometry": {"coordinates":[8.474987,49.450539],"type":"Point"}
}