{
  "type": "Feature",
  "properties": {
    "iso:country":"DE",
    "sg:address":"Hauptstr. 13",
    "sg:city":"Heuchelheim",
    "sg:phone":"+49 641/62350",
    "sg:postcode":"35452",
    "sg:province":"Hessen",
    "wof:name":"Kurt Dann",
    "wof:placetype":"venue"
},
  "geometry": {"coordinates":[8.612675,50.589733],"type":"Point"}
}