{
  "type": "Feature",
  "properties": {
    "iso:country":"DE",
    "sg:address":"Ludwigstr. 26",
    "sg:city":"St. Ingbert",
    "sg:phone":"+49 6894/385710",
    "sg:postcode":"66386",
    "sg:province":"Saarland",
    "wof:name":"Wagner Und Krempel Rechtanw\u00e4lte",
    "wof:placetype":"venue"
},
  "geometry": {"coordinates":[7.1165041924,49.2806625366],"type":"Point"}
}