{
  "type": "Feature",
  "properties": {
    "iso:country":"DE",
    "sg:address":"Birkerfeld 4",
    "sg:city":"Bergisch Gladbach",
    "sg:phone":"+49 2204/81728",
    "sg:postcode":"51429",
    "sg:province":"Nordrhein-Westfalen",
    "wof:name":"Anita Wachendorff",
    "wof:placetype":"venue"
},
  "geometry": {"coordinates":[7.190801,50.967953],"type":"Point"}
}