{
  "type": "Feature",
  "properties": {
    "iso:country":"DE",
    "sg:address":"Nikolausstr. 37a",
    "sg:city":"Vettwei\u00df",
    "sg:phone":"+49 2424/94000",
    "sg:postcode":"52391",
    "sg:province":"Nordrhein-Westfalen",
    "wof:name":"Pahrmann Edv-partner Gmbh",
    "wof:placetype":"venue"
},
  "geometry": {"coordinates":[6.6319408417,50.7726135254],"type":"Point"}
}