{
  "type": "Feature",
  "properties": {
    "iso:country":"DE",
    "sg:address":"Glash\u00fctter Damm 192",
    "sg:city":"Norderstedt",
    "sg:phone":"+49 40/5291992",
    "sg:postcode":"22851",
    "sg:province":"Schleswig-Holstein",
    "wof:name":"A. K\u00f6nigsbaum",
    "wof:placetype":"venue"
},
  "geometry": {"coordinates":[10.0262956619,53.6927871704],"type":"Point"}
}