{
  "type": "Feature",
  "properties": {
    "iso:country":"DE",
    "sg:address":"Karl-Schneider-Str. 10",
    "sg:city":"Gladbeck",
    "sg:phone":"+49 2043/46246",
    "sg:postcode":"45966",
    "sg:province":"Nordrhein-Westfalen",
    "wof:name":"K. Feldkamp",
    "wof:placetype":"venue"
},
  "geometry": {"coordinates":[6.968189,51.572296],"type":"Point"}
}