{
  "type": "Feature",
  "properties": {
    "iso:country":"DE",
    "sg:address":"Raiffeisenstr. 1",
    "sg:city":"Prosselsheim",
    "sg:phone":"+49 9386/99909",
    "sg:postcode":"97279",
    "sg:province":"Bayern",
    "wof:name":"Event Tec Winfried Karl Gmbh",
    "wof:placetype":"venue"
},
  "geometry": {"coordinates":[10.1275596619,49.8647918701],"type":"Point"}
}