{
  "type": "Feature",
  "properties": {
    "iso:country":"DE",
    "sg:address":"Bernhard-Adelung-Str. 49",
    "sg:city":"R\u00fcsselsheim",
    "sg:phone":"+49 6142/62221",
    "sg:postcode":"65428",
    "sg:province":"Hessen",
    "wof:name":"Chemie Consult Dr. R. Stenner Gmbh",
    "wof:placetype":"venue"
},
  "geometry": {"coordinates":[8.4167165756,49.9848709106],"type":"Point"}
}