{
  "type": "Feature",
  "properties": {
    "iso:country":"DE",
    "sg:address":"Hauptstr. 22",
    "sg:city":"Urbach",
    "sg:phone":"+49 7181/81274",
    "sg:postcode":"73660",
    "sg:province":"Baden-W\u00fcrttemberg",
    "wof:name":"Hirsch",
    "wof:placetype":"venue"
},
  "geometry": {"coordinates":[9.5784330368,48.8093070984],"type":"Point"}
}