{
  "type": "Feature",
  "properties": {
    "iso:country":"DE",
    "sg:address":"Unterer Engen 10C",
    "sg:city":"Bobritzsch",
    "sg:phone":"+49 37325/92345",
    "sg:postcode":"09627",
    "sg:province":"Sachsen",
    "wof:name":"Friedrich Ernst Engelmann",
    "wof:placetype":"venue"
},
  "geometry": {"coordinates":[13.4211320877,50.9359588623],"type":"Point"}
}