{
  "type": "Feature",
  "properties": {
    "iso:country":"DE",
    "sg:address":"B\u00f6nnier Str. 20",
    "sg:city":"Bockenem",
    "sg:phone":"+49 5067/698039",
    "sg:postcode":"31167",
    "sg:province":"Niedersachsen",
    "wof:name":"G\u00fcnther Berndt Elektromeister Gmbh",
    "wof:placetype":"venue"
},
  "geometry": {"coordinates":[10.128176,52.009789],"type":"Point"}
}