{
  "type": "Feature",
  "properties": {
    "iso:country":"DE",
    "sg:address":"Rohlsdorfer Beek 3",
    "sg:city":"Sarkwitz",
    "sg:phone":"+49 4504/4873",
    "sg:postcode":"23629",
    "sg:province":"Schleswig-Holstein",
    "wof:name":"Lang & Co. Bau- Und Projektgesellschaft Mbh",
    "wof:placetype":"venue"
},
  "geometry": {"coordinates":[10.66904,53.99033],"type":"Point"}
}