{
  "type": "Feature",
  "properties": {
    "iso:country":"DE",
    "sg:address":"Pestalozzistr. 16",
    "sg:city":"Stuhr",
    "sg:phone":"+49 421/891135",
    "sg:postcode":"28816",
    "sg:province":"Niedersachsen",
    "wof:name":"Friedrich Wilhelm Rotermund Architekt",
    "wof:placetype":"venue"
},
  "geometry": {"coordinates":[8.786252,53.00293],"type":"Point"}
}