{
  "type": "Feature",
  "properties": {
    "iso:country":"DE",
    "sg:address":"Warnstedtstr. 57",
    "sg:city":"Hamburg",
    "sg:phone":"+49 40/54744100",
    "sg:postcode":"22525",
    "sg:province":"Hamburg",
    "wof:name":"Elektonische Bauelemente",
    "wof:placetype":"venue"
},
  "geometry": {"coordinates":[9.928092,53.587364],"type":"Point"}
}