{
  "type": "Feature",
  "properties": {
    "iso:country":"DE",
    "sg:address":"A\u00dflarer Str. 22",
    "sg:city":"Wetzlar",
    "sg:phone":"+49 6441/32200",
    "sg:postcode":"35586",
    "sg:province":"Hessen",
    "wof:name":"Henninger Eck",
    "wof:placetype":"venue"
},
  "geometry": {"coordinates":[8.4878807068,50.5809135437],"type":"Point"}
}