{
  "type": "Feature",
  "properties": {
    "iso:country":"DE",
    "sg:address":"Weinsteiger Str. 7",
    "sg:city":"Haag",
    "sg:phone":"+49 8072/91850",
    "sg:postcode":"83527",
    "sg:province":"Bayern",
    "wof:name":"B\u00fcrgerheim",
    "wof:placetype":"venue"
},
  "geometry": {"coordinates":[12.187219,48.159462],"type":"Point"}
}