{
  "type": "Feature",
  "properties": {
    "iso:country":"DE",
    "sg:address":"Kottbusser Damm 73",
    "sg:city":"Berlin",
    "sg:phone":"+49 30/6938345",
    "sg:postcode":"10967",
    "sg:province":"Berlin",
    "wof:name":"Dieter W. Schneider Architekt",
    "wof:placetype":"venue"
},
  "geometry": {"coordinates":[13.424176,52.49012],"type":"Point"}
}