{
  "type": "Feature",
  "properties": {
    "iso:country":"DE",
    "sg:address":"Dahlienweg 8",
    "sg:city":"Dresden",
    "sg:phone":"+49 351/4113918",
    "sg:postcode":"01159",
    "sg:province":"Sachsen",
    "wof:name":"Ralf Zimmer",
    "wof:placetype":"venue"
},
  "geometry": {"coordinates":[13.6814985275,51.0456809998],"type":"Point"}
}