{
  "type": "Feature",
  "properties": {
    "iso:country":"DE",
    "sg:address":"Adelsf\u00f6rsterpfad 6",
    "sg:city":"Wiesloch",
    "sg:phone":"+49 6222/52450",
    "sg:postcode":"69168",
    "sg:province":"Baden-W\u00fcrttemberg",
    "wof:name":"Kessler",
    "wof:placetype":"venue"
},
  "geometry": {"coordinates":[8.666682,49.294895],"type":"Point"}
}