{
  "type": "Feature",
  "properties": {
    "iso:country":"DE",
    "sg:address":"Zur Neum\u00fchle 28",
    "sg:city":"Weiden",
    "sg:phone":"+49 961/34139",
    "sg:postcode":"92637",
    "sg:province":"Bayern",
    "wof:name":"Ludwig H\u00f6ning",
    "wof:placetype":"venue"
},
  "geometry": {"coordinates":[12.1846752167,49.6809806824],"type":"Point"}
}