{
  "type": "Feature",
  "properties": {
    "iso:country":"DE",
    "sg:address":"Bergstr. 3",
    "sg:city":"Pfeffelbach",
    "sg:phone":"+49 6384/1609",
    "sg:postcode":"66871",
    "sg:province":"Rheinland-Pfalz",
    "wof:name":"Hans M\u00fcller",
    "wof:placetype":"venue"
},
  "geometry": {"coordinates":[7.327559,49.541306],"type":"Point"}
}