{
  "type": "Feature",
  "properties": {
    "iso:country":"DE",
    "sg:address":"Rechelsberg 24",
    "sg:city":"Marpingen",
    "sg:phone":"+49 6853/3585",
    "sg:postcode":"66646",
    "sg:province":"Saarland",
    "wof:name":"Ludwig Sebastian Architekt",
    "wof:placetype":"venue"
},
  "geometry": {"coordinates":[7.067545,49.475708],"type":"Point"}
}