{
  "type": "Feature",
  "properties": {
    "iso:country":"DE",
    "sg:address":"Droste-H\u00fclshoff-Str. 34",
    "sg:city":"Bonn",
    "sg:postcode":"53129",
    "sg:province":"Nordrhein-Westfalen",
    "wof:name":"Gollmann Gmbh",
    "wof:placetype":"venue"
},
  "geometry": {"coordinates":[7.117228,50.70145],"type":"Point"}
}