{
  "type": "Feature",
  "properties": {
    "iso:country":"DE",
    "sg:address":"Rottbitzer Str. 17",
    "sg:city":"Bad Honnef",
    "sg:phone":"+49 2224/82175",
    "sg:postcode":"53604",
    "sg:province":"Nordrhein-Westfalen",
    "wof:name":"China-restaurant Lotus",
    "wof:placetype":"venue"
},
  "geometry": {"coordinates":[7.3279829025,50.6501159668],"type":"Point"}
}