{
  "type": "Feature",
  "properties": {
    "iso:country":"DE",
    "sg:address":"Gr\u00fcne Str. 127 A",
    "sg:city":"Westerhausen",
    "sg:phone":"+49 3946/6315",
    "sg:postcode":"06484",
    "sg:province":"Sachsen-Anhalt",
    "wof:name":"H. Koch",
    "wof:placetype":"venue"
},
  "geometry": {"coordinates":[11.059146,51.805267],"type":"Point"}
}