{
  "type": "Feature",
  "properties": {
    "iso:country":"DE",
    "sg:address":"Liliencronstr. 64",
    "sg:city":"D\u00fcsseldorf",
    "sg:phone":"+49 4921/196530",
    "sg:postcode":"40472",
    "sg:province":"Nordrhein-Westfalen",
    "wof:name":"Keller & Bohacek Gmbh & Co Kg",
    "wof:placetype":"venue"
},
  "geometry": {"coordinates":[6.823874,51.270828],"type":"Point"}
}