{
  "type": "Feature",
  "properties": {
    "iso:country":"DE",
    "sg:address":"Dreihausweg 4",
    "sg:city":"Kronberg",
    "sg:phone":"+49 6173/68154",
    "sg:postcode":"61476",
    "sg:province":"Hessen",
    "wof:name":"Dr. B\u00f6rnecke Industrieservice Isb-gmbh",
    "wof:placetype":"venue"
},
  "geometry": {"coordinates":[8.535612,50.19109],"type":"Point"}
}