{
  "type": "Feature",
  "properties": {
    "iso:country":"DE",
    "sg:address":"Kleiberstr. 1",
    "sg:city":"Kelheim",
    "sg:phone":"+49 9441/5111",
    "sg:postcode":"93309",
    "sg:province":"Bayern",
    "wof:name":"Jakob Mayer",
    "wof:placetype":"venue"
},
  "geometry": {"coordinates":[11.8959951401,48.9170455933],"type":"Point"}
}