{
  "type": "Feature",
  "properties": {
    "iso:country":"DE",
    "sg:address":"Schneider\u00e4ckerstr 6",
    "sg:city":"Aalen",
    "sg:phone":"+49 7361/73031",
    "sg:postcode":"73433",
    "sg:province":"Baden-W\u00fcrttemberg",
    "wof:name":"Bauer",
    "wof:placetype":"venue"
},
  "geometry": {"coordinates":[10.056877,48.874519],"type":"Point"}
}