{
  "type": "Feature",
  "properties": {
    "iso:country":"DE",
    "sg:address":"W\u00fcrzburger Str. 36",
    "sg:city":"Erlabrunn",
    "sg:phone":"+49 9364/1384",
    "sg:postcode":"97250",
    "sg:province":"Bayern",
    "wof:name":"Raiffeisenbank Margetsh\u00f6chheim Und, Umgebung Eg",
    "wof:placetype":"venue"
},
  "geometry": {"coordinates":[9.845577,49.858162],"type":"Point"}
}