{
  "type": "Feature",
  "properties": {
    "iso:country":"DE",
    "sg:address":"Vereinsstr. 1",
    "sg:city":"Bochum",
    "sg:phone":"+49 234/13228",
    "sg:postcode":"44793",
    "sg:province":"Nordrhein-Westfalen",
    "wof:name":"C. V\u00f6hler Schulbedarf Tabakwaren",
    "wof:placetype":"venue"
},
  "geometry": {"coordinates":[7.1928830147,51.4798049927],"type":"Point"}
}