{
  "type": "Feature",
  "properties": {
    "iso:country":"DE",
    "sg:address":"Lange Str. 26-30",
    "sg:city":"Cloppenburg",
    "sg:phone":"+49 4471/94290",
    "sg:postcode":"49661",
    "sg:province":"Niedersachsen",
    "wof:name":"Kaufhalle Ag",
    "wof:placetype":"venue"
},
  "geometry": {"coordinates":[8.0402736664,52.8452835083],"type":"Point"}
}