{
  "type": "Feature",
  "properties": {
    "iso:country":"DE",
    "sg:address":"Theodor-Storm-Str. 3 c",
    "sg:city":"Bad Homburg",
    "sg:phone":"+49 6172/86248",
    "sg:postcode":"61350",
    "sg:province":"Hessen",
    "wof:name":"Dr. Hellmuth Louis Rechtsanwalt Und Notar",
    "wof:placetype":"venue"
},
  "geometry": {"coordinates":[8.6181230545,50.2374305725],"type":"Point"}
}