{
  "type": "Feature",
  "properties": {
    "iso:country":"DE",
    "sg:address":"Rathausplatz 4",
    "sg:city":"Paderborn",
    "sg:phone":"+49 5251/22409",
    "sg:postcode":"33098",
    "sg:province":"Nordrhein-Westfalen",
    "wof:name":"Rathaus-apotheke",
    "wof:placetype":"venue"
},
  "geometry": {"coordinates":[8.753881,51.71759],"type":"Point"}
}