{
  "type": "Feature",
  "properties": {
    "iso:country":"DE",
    "sg:address":"Zum Hullen 43",
    "sg:city":"Westerstede",
    "sg:phone":"+49 4488/3322",
    "sg:postcode":"26655",
    "sg:province":"Niedersachsen",
    "wof:name":"Waltraud Bahns Heilpraktikerin",
    "wof:placetype":"venue"
},
  "geometry": {"coordinates":[7.9809598923,53.2827796936],"type":"Point"}
}