{
  "type": "Feature",
  "properties": {
    "iso:country":"DE",
    "sg:address":"Lengmoos 62",
    "sg:city":"Gars",
    "sg:phone":"+49 8054/259",
    "sg:postcode":"83536",
    "sg:province":"Bayern",
    "wof:name":"Gasthaus Zur Post Inh. Kurt Schmalwieser",
    "wof:placetype":"venue"
},
  "geometry": {"coordinates":[12.2178201675,48.1412353516],"type":"Point"}
}