{
  "type": "Feature",
  "properties": {
    "iso:country":"DE",
    "sg:address":"Ellwangerstr. 47",
    "sg:city":"Frontenhausen",
    "sg:phone":"+49 8732/452",
    "sg:postcode":"84160",
    "sg:province":"Bayern",
    "wof:name":"Josef Neumeier",
    "wof:placetype":"venue"
},
  "geometry": {"coordinates":[12.523302,48.545433],"type":"Point"}
}