{
  "type": "Feature",
  "properties": {
    "iso:country":"DE",
    "sg:address":"Flurstr. 11",
    "sg:city":"Gaildorf",
    "sg:phone":"+49 7971/6674",
    "sg:postcode":"74405",
    "sg:province":"Baden-W\u00fcrttemberg",
    "wof:name":"Fensterbau H\u00e4gele Inh. Karl H\u00e4gele",
    "wof:placetype":"venue"
},
  "geometry": {"coordinates":[9.752846,48.968685],"type":"Point"}
}