{
  "type": "Feature",
  "properties": {
    "iso:country":"DE",
    "sg:address":"Hagener Str. 16",
    "sg:city":"Iserlohn",
    "sg:phone":"+49 2374/166699",
    "sg:postcode":"58642",
    "sg:province":"Nordrhein-Westfalen",
    "wof:name":"Mohammed S. Akhtar",
    "wof:placetype":"venue"
},
  "geometry": {"coordinates":[7.6166448593,51.3652267456],"type":"Point"}
}