{
  "type": "Feature",
  "properties": {
    "iso:country":"DE",
    "sg:address":"Bei der Kirche 21",
    "sg:city":"Ellerbek",
    "sg:phone":"+49 4101/34899",
    "sg:postcode":"25474",
    "sg:province":"Schleswig-Holstein",
    "wof:name":"Wolfgang Bremer",
    "wof:placetype":"venue"
},
  "geometry": {"coordinates":[9.870606,53.657589],"type":"Point"}
}