{
  "type": "Feature",
  "properties": {
    "iso:country":"DE",
    "sg:address":"Arndtplatz 3",
    "sg:city":"Osnabr\u00fcck",
    "sg:phone":"+49 541/41049",
    "sg:postcode":"49080",
    "sg:province":"Niedersachsen",
    "wof:name":"Eisenmenger Architekten Und Ingenieure Gmbh",
    "wof:placetype":"venue"
},
  "geometry": {"coordinates":[8.037348,52.271549],"type":"Point"}
}