{
  "type": "Feature",
  "properties": {
    "iso:country":"DE",
    "sg:address":"M\u00fchlenstr. 2",
    "sg:city":"Lieberose",
    "sg:phone":"+49 33671/2241",
    "sg:postcode":"15868",
    "sg:province":"Brandenburg",
    "wof:name":"B. Dahlheim",
    "wof:placetype":"venue"
},
  "geometry": {"coordinates":[14.300881,51.988735],"type":"Point"}
}