{
  "type": "Feature",
  "properties": {
    "iso:country":"DE",
    "sg:address":"Rothenburger Str. 28 g",
    "sg:city":"G\u00f6rlitz",
    "sg:phone":"+49 3581/47110",
    "sg:postcode":"02828",
    "sg:province":"Sachsen",
    "wof:name":"G\u00f6rlitzer Hochbau Gmbh",
    "wof:placetype":"venue"
},
  "geometry": {"coordinates":[14.9806995392,51.1814804077],"type":"Point"}
}