{
  "type": "Feature",
  "properties": {
    "iso:country":"DE",
    "sg:address":"Hofstattstr. 8",
    "sg:city":"Aschheim",
    "sg:phone":"+49 89/9035107",
    "sg:postcode":"85609",
    "sg:province":"Bayern",
    "wof:name":"Ita Ingenieurb\u00fcro F\u00fcr Tragwerksplanung Gmbh",
    "wof:placetype":"venue"
},
  "geometry": {"coordinates":[11.7127914429,48.1701011658],"type":"Point"}
}