{
  "type": "Feature",
  "properties": {
    "iso:country":"DE",
    "sg:address":"Rollnerstr. 97",
    "sg:city":"Nuernberg",
    "sg:phone":"+49 911/3509417",
    "sg:postcode":"40408",
    "wof:name":"Cotrain Beratung Schulung",
    "wof:placetype":"venue"
},
  "geometry": {"coordinates":[11.0813426971,49.467830658],"type":"Point"}
}