{
  "type": "Feature",
  "properties": {
    "iso:country":"DE",
    "sg:address":"Schumacherring 96",
    "sg:city":"Kempten",
    "sg:phone":"+49 831/75510",
    "sg:postcode":"87437",
    "sg:province":"Bayern",
    "wof:name":"Agip Service-station Echter Gmbh",
    "wof:placetype":"venue"
},
  "geometry": {"coordinates":[10.3275499344,47.7308425903],"type":"Point"}
}