{
  "type": "Feature",
  "properties": {
    "iso:country":"DE",
    "sg:address":"Kirchstr. 10",
    "sg:city":"V\u00f6hringen",
    "sg:phone":"+49 7454/2278",
    "sg:postcode":"72189",
    "sg:province":"Baden-W\u00fcrttemberg",
    "wof:name":"Ev. Pfarramt Wittershausen",
    "wof:placetype":"venue"
},
  "geometry": {"coordinates":[8.6371107101,48.3168716431],"type":"Point"}
}