{
  "type": "Feature",
  "properties": {
    "iso:country":"DE",
    "sg:address":"Osterfeld 38",
    "sg:city":"Brokstedt",
    "sg:postcode":"24616",
    "sg:province":"Schleswig-Holstein",
    "wof:name":"Heinrich Diemke Gmbh",
    "wof:placetype":"venue"
},
  "geometry": {"coordinates":[9.8283052444,53.9863929749],"type":"Point"}
}