{
  "type": "Feature",
  "properties": {
    "iso:country":"DE",
    "sg:address":"Usastr. 26",
    "sg:city":"Neu-Anspach",
    "sg:phone":"+49 6081/8289",
    "sg:postcode":"61267",
    "sg:province":"Hessen",
    "wof:name":"Gardinenhaus Becker Inh. Elke Maruhn",
    "wof:placetype":"venue"
},
  "geometry": {"coordinates":[8.5073537827,50.2908363342],"type":"Point"}
}