{
  "type": "Feature",
  "properties": {
    "iso:country":"DE",
    "sg:address":"Judenb\u00fchlweg 23",
    "sg:city":"W\u00fcrzburg",
    "sg:phone":"+49 931/73548",
    "sg:postcode":"97082",
    "sg:province":"Bayern",
    "wof:name":"Dr. Werner H\u00f6hne Steuerberater Und Wirtschafts-",
    "wof:placetype":"venue"
},
  "geometry": {"coordinates":[9.9239797592,49.7755355835],"type":"Point"}
}