{
  "type": "Feature",
  "properties": {
    "iso:country":"DE",
    "sg:address":"Rudolf-Diesel-Str.",
    "sg:city":"Sonthofen",
    "sg:phone":"+49 8321/9722",
    "sg:postcode":"87527",
    "sg:province":"Bayern",
    "wof:name":"Tebo",
    "wof:placetype":"venue"
},
  "geometry": {"coordinates":[10.2695817947,47.5215492249],"type":"Point"}
}