{
  "type": "Feature",
  "properties": {
    "iso:country":"DE",
    "sg:address":"Uhlandstr. 11",
    "sg:city":"Weilerswist",
    "sg:phone":"+49 2254/5549",
    "sg:postcode":"53919",
    "sg:province":"Nordrhein-Westfalen",
    "wof:name":"Paul Latz",
    "wof:placetype":"venue"
},
  "geometry": {"coordinates":[6.840719223,50.7453460693],"type":"Point"}
}