{
  "type": "Feature",
  "properties": {
    "iso:country":"DE",
    "sg:address":"Venloer Str. 719",
    "sg:city":"K\u00f6ln",
    "sg:phone":"+49 221/581432",
    "sg:postcode":"50827",
    "sg:province":"Nordrhein-Westfalen",
    "wof:name":"Hans T. Ziegler",
    "wof:placetype":"venue"
},
  "geometry": {"coordinates":[6.896364,50.959274],"type":"Point"}
}