{
  "type": "Feature",
  "properties": {
    "iso:country":"DE",
    "sg:address":"Winsener Str. 41",
    "sg:city":"Hamburg",
    "sg:phone":"+49 40/7633541",
    "sg:postcode":"21077",
    "sg:province":"Hamburg",
    "wof:name":"Intei Industriebeteiligungs- Gmbh",
    "wof:placetype":"venue"
},
  "geometry": {"coordinates":[9.989048,53.448391],"type":"Point"}
}