{
  "type": "Feature",
  "properties": {
    "iso:country":"DE",
    "sg:address":"H\u00e4genstr. 4",
    "sg:city":"Hannover",
    "sg:phone":"+49 511/958750",
    "sg:postcode":"30559",
    "sg:province":"Niedersachsen",
    "wof:name":"Gille-hermann-jenssen & Kemna Baustoffe Gmbh",
    "wof:placetype":"venue"
},
  "geometry": {"coordinates":[9.867944,52.362736],"type":"Point"}
}