{
  "type": "Feature",
  "properties": {
    "iso:country":"DE",
    "sg:address":"Boos-Fremery-Str. 3",
    "sg:city":"Heinsberg",
    "sg:phone":"+49 2452/61298",
    "sg:postcode":"52525",
    "sg:province":"Nordrhein-Westfalen",
    "wof:name":"Kath. Pfarramt St. Aloysius",
    "wof:placetype":"venue"
},
  "geometry": {"coordinates":[6.1463479996,51.0607795715],"type":"Point"}
}