{
  "type": "Feature",
  "properties": {
    "iso:country":"DE",
    "sg:address":"Billstr. 217",
    "sg:city":"Hamburg",
    "sg:phone":"+49 40/7890286",
    "sg:postcode":"20539",
    "sg:province":"Hamburg",
    "wof:name":"Teuber Verwaltungs Gmbh",
    "wof:placetype":"venue"
},
  "geometry": {"coordinates":[10.0606660843,53.5353507996],"type":"Point"}
}