{
  "type": "Feature",
  "properties": {
    "iso:country":"DE",
    "sg:address":"Im Pastoratsbusch 9",
    "sg:city":"Bochum",
    "sg:phone":"+49 234/799849",
    "sg:postcode":"44797",
    "sg:province":"Nordrhein-Westfalen",
    "wof:name":"Wolfgang Ehlenbruch",
    "wof:placetype":"venue"
},
  "geometry": {"coordinates":[7.2323598862,51.4270095825],"type":"Point"}
}