{
  "type": "Feature",
  "properties": {
    "iso:country":"DE",
    "sg:address":"Domhof 15-21",
    "sg:city":"Ahaus",
    "sg:phone":"+49 2561/67606",
    "sg:postcode":"48683",
    "sg:province":"Nordrhein-Westfalen",
    "wof:name":"Barbara Hoffmann",
    "wof:placetype":"venue"
},
  "geometry": {"coordinates":[7.0088658333,52.0764427185],"type":"Point"}
}