{
  "type": "Feature",
  "properties": {
    "iso:country":"DE",
    "sg:address":"Rudolfstr. 10",
    "sg:city":"Aachen",
    "sg:phone":"+49 241/538916",
    "sg:postcode":"52070",
    "sg:province":"Nordrhein-Westfalen",
    "wof:name":"Andreas Korn Architekt",
    "wof:placetype":"venue"
},
  "geometry": {"coordinates":[6.097491,50.778332],"type":"Point"}
}