{
  "type": "Feature",
  "properties": {
    "iso:country":"DE",
    "sg:address":"Am Moos 11",
    "sg:city":"Neustadt",
    "sg:phone":"+49 9568/5797",
    "sg:postcode":"96465",
    "sg:province":"Bayern",
    "wof:name":"Hugo Heubach Kg",
    "wof:placetype":"venue"
},
  "geometry": {"coordinates":[11.1154279709,50.3333930969],"type":"Point"}
}