{
  "type": "Feature",
  "properties": {
    "iso:country":"DE",
    "sg:address":"Wiesenstr. 3",
    "sg:city":"Meinhard",
    "sg:phone":"+49 5651/60408",
    "sg:postcode":"37276",
    "sg:province":"Hessen",
    "wof:name":"Peter Riese Masseur",
    "wof:placetype":"venue"
},
  "geometry": {"coordinates":[10.10418,51.198608],"type":"Point"}
}