{
  "type": "Feature",
  "properties": {
    "iso:country":"DE",
    "sg:address":"Im Schleifrad 10",
    "sg:city":"Leutkirch",
    "sg:phone":"+49 7561/9790",
    "sg:postcode":"88299",
    "sg:province":"Baden-W\u00fcrttemberg",
    "wof:name":"Deutsche Telekom T-punkt",
    "wof:placetype":"venue"
},
  "geometry": {"coordinates":[10.0167922974,47.8279495239],"type":"Point"}
}