{
  "type": "Feature",
  "properties": {
    "iso:country":"DE",
    "sg:address":"Baumholderstr. 1",
    "sg:city":"Freisen",
    "sg:phone":"+49 6855/250",
    "sg:postcode":"66629",
    "sg:province":"Saarland",
    "wof:name":"Alois Becker",
    "wof:placetype":"venue"
},
  "geometry": {"coordinates":[7.2488508224,49.55260849],"type":"Point"}
}