{
  "type": "Feature",
  "properties": {
    "iso:country":"DE",
    "sg:address":"Dorfstr. 24",
    "sg:city":"Regen",
    "sg:phone":"+49 9921/2336",
    "sg:postcode":"94209",
    "sg:province":"Bayern",
    "wof:name":"Pichler Gmbh",
    "wof:placetype":"venue"
},
  "geometry": {"coordinates":[13.17766,48.986198],"type":"Point"}
}