{
  "type": "Feature",
  "properties": {
    "iso:country":"DE",
    "sg:address":"Richard-Wagner-Str. 4",
    "sg:city":"Magdeburg",
    "sg:phone":"+49 391/5313278",
    "sg:postcode":"39106",
    "sg:province":"Sachsen-Anhalt",
    "wof:name":"Dialog Gmbh",
    "wof:placetype":"venue"
},
  "geometry": {"coordinates":[11.6379642487,52.1411399841],"type":"Point"}
}