{
  "type": "Feature",
  "properties": {
    "iso:country":"DE",
    "sg:address":"D\u00f6belner Str. 27",
    "sg:city":"M\u00fcgeln",
    "sg:phone":"+49 34362/30550",
    "sg:postcode":"04769",
    "sg:province":"Sachsen",
    "wof:name":"L\u00e4ssig Gmbh",
    "wof:placetype":"venue"
},
  "geometry": {"coordinates":[13.0494499207,51.2359085083],"type":"Point"}
}