{
  "type": "Feature",
  "properties": {
    "iso:country":"DE",
    "sg:address":"Bahnhof Jeggeleben S\u00fcd",
    "sg:city":"Jeggeleben",
    "sg:phone":"+49 39009/220",
    "sg:postcode":"29416",
    "sg:province":"Sachsen-Anhalt",
    "wof:name":"Ausflugsgastst\u00e4tte Feine Sache",
    "wof:placetype":"venue"
},
  "geometry": {"coordinates":[11.2995796204,52.7491226196],"type":"Point"}
}