{
  "type": "Feature",
  "properties": {
    "iso:country":"DE",
    "sg:address":"Moelscherweg 106",
    "sg:city":"Goch",
    "sg:phone":"+49 2827/5780",
    "sg:postcode":"47574",
    "sg:province":"Nordrhein-Westfalen",
    "wof:name":"Borasterie",
    "wof:placetype":"venue"
},
  "geometry": {"coordinates":[6.0366911888,51.6730651855],"type":"Point"}
}