{
  "type": "Feature",
  "properties": {
    "iso:country":"DE",
    "sg:address":"Marienstr. 30",
    "sg:city":"Hamburg",
    "sg:postcode":"21073",
    "sg:province":"Hamburg",
    "wof:name":"Hendrik Mellahn Beteiligungs Gmbh",
    "wof:placetype":"venue"
},
  "geometry": {"coordinates":[9.9757604599,53.4584999084],"type":"Point"}
}