{
  "type": "Feature",
  "properties": {
    "iso:country":"DE",
    "sg:address":"Kolonnadenstr. 29",
    "sg:city":"Leipzig",
    "sg:phone":"+49 341/9606894",
    "sg:postcode":"04109",
    "sg:province":"Sachsen",
    "wof:name":"G\u00fcnther Prengel Rechtsanwalt",
    "wof:placetype":"venue"
},
  "geometry": {"coordinates":[12.3646202087,51.3378181458],"type":"Point"}
}