{
  "type": "Feature",
  "properties": {
    "iso:country":"DE",
    "sg:address":"Ernst-Th\u00e4lmann-Str. 30",
    "sg:city":"Liebenwalde",
    "sg:phone":"+49 33054/60260",
    "sg:postcode":"16559",
    "sg:province":"Brandenburg",
    "wof:name":"Brandenburgische Konsumgenossenschaft",
    "wof:placetype":"venue"
},
  "geometry": {"coordinates":[13.39414,52.871521],"type":"Point"}
}