{
  "type": "Feature",
  "properties": {
    "iso:country":"DE",
    "sg:address":"Klostergasse 7",
    "sg:city":"D\u00fcren",
    "sg:phone":"+49 2421/87904",
    "sg:postcode":"52353",
    "sg:province":"Nordrhein-Westfalen",
    "wof:name":"Kath. Pfarramt St. Maria-himmelfahrt",
    "wof:placetype":"venue"
},
  "geometry": {"coordinates":[6.4462242126,50.8145141602],"type":"Point"}
}