{
  "type": "Feature",
  "properties": {
    "iso:country":"DE",
    "sg:address":"Marktplatz 2",
    "sg:city":"Steinach",
    "sg:phone":"+49 36762/32359",
    "sg:postcode":"96523",
    "sg:province":"Th\u00fcringen",
    "wof:name":"Vogel & Apitz",
    "wof:placetype":"venue"
},
  "geometry": {"coordinates":[11.156655,50.431702],"type":"Point"}
}