{
  "type": "Feature",
  "properties": {
    "iso:country":"DE",
    "sg:address":"Adalbertstr. 55",
    "sg:city":"M\u00fcnchen",
    "sg:phone":"+49 89/2723125",
    "sg:postcode":"80799",
    "sg:province":"Bayern",
    "wof:name":"Richard Dietrich Architekt",
    "wof:placetype":"venue"
},
  "geometry": {"coordinates":[11.572892,48.153671],"type":"Point"}
}