{
  "type": "Feature",
  "properties": {
    "iso:country":"DE",
    "sg:address":"Opfenrieder Str. 10",
    "sg:city":"Wassertr\u00fcdingen",
    "sg:phone":"+49 9832/67834",
    "sg:postcode":"91717",
    "sg:province":"Bayern",
    "wof:name":"Klenk & Ott Kg",
    "wof:placetype":"venue"
},
  "geometry": {"coordinates":[10.5889005661,49.0444107056],"type":"Point"}
}