{
  "type": "Feature",
  "properties": {
    "iso:country":"DE",
    "sg:address":"K\u00f6llmer Str. 24",
    "sg:city":"Bennstedt",
    "sg:phone":"+49 34601/24895",
    "sg:postcode":"06179",
    "sg:province":"Sachsen-Anhalt",
    "wof:name":"Martina Meisner",
    "wof:placetype":"venue"
},
  "geometry": {"coordinates":[11.8239049911,51.4856491089],"type":"Point"}
}