{
  "type": "Feature",
  "properties": {
    "iso:country":"DE",
    "sg:address":"Im Bilskamp 5",
    "sg:city":"M\u00fcnster",
    "sg:phone":"+49 2506/1280",
    "sg:postcode":"48167",
    "sg:province":"Nordrhein-Westfalen",
    "wof:name":"H. Thale",
    "wof:placetype":"venue"
},
  "geometry": {"coordinates":[7.7408518791,51.9180603027],"type":"Point"}
}