{
  "type": "Feature",
  "properties": {
    "iso:country":"DE",
    "sg:address":"Pivitsheide 110",
    "sg:city":"G\u00fctersloh",
    "sg:phone":"+49 5241/37123",
    "sg:postcode":"33334",
    "sg:province":"Nordrhein-Westfalen",
    "wof:name":"Hans Muntau Elektroinstallation",
    "wof:placetype":"venue"
},
  "geometry": {"coordinates":[8.364013,51.949448],"type":"Point"}
}