{
  "type": "Feature",
  "properties": {
    "iso:country":"DE",
    "sg:address":"Am Lindenbaum 35",
    "sg:city":"Frankfurt",
    "sg:phone":"+49 69/511832",
    "sg:postcode":"60433",
    "sg:province":"Hessen",
    "wof:name":"F. Walter Haller Architekt",
    "wof:placetype":"venue"
},
  "geometry": {"coordinates":[8.663187,50.15414],"type":"Point"}
}