{
  "type": "Feature",
  "properties": {
    "iso:country":"DE",
    "sg:address":"Alleestr. 4",
    "sg:city":"Fr\u00f6ndenberg",
    "sg:postcode":"58730",
    "sg:province":"Nordrhein-Westfalen",
    "wof:name":"Pizzeria Milano",
    "wof:placetype":"venue"
},
  "geometry": {"coordinates":[7.7679491043,51.4732971191],"type":"Point"}
}