{
  "type": "Feature",
  "properties": {
    "iso:country":"DE",
    "sg:address":"Hohe Geest 172 a",
    "sg:city":"M\u00fcnster",
    "sg:phone":"+49 2501/16200",
    "sg:postcode":"48165",
    "sg:province":"Nordrhein-Westfalen",
    "wof:name":"Hans Heithoff Inh. Dieter Borgschulze",
    "wof:placetype":"venue"
},
  "geometry": {"coordinates":[7.63514,51.915821],"type":"Point"}
}