{
  "type": "Feature",
  "properties": {
    "iso:country":"DE",
    "sg:address":"Rockelstr. 3",
    "sg:city":"Schwanau",
    "sg:phone":"+49 7824/66929",
    "sg:postcode":"77963",
    "sg:province":"Baden-W\u00fcrttemberg",
    "wof:name":"Werner Rieth",
    "wof:placetype":"venue"
},
  "geometry": {"coordinates":[7.761821,48.38588],"type":"Point"}
}