{
  "type": "Feature",
  "properties": {
    "iso:country":"DE",
    "sg:address":"Weststr. 11",
    "sg:city":"Limbach-Oberfrohna",
    "sg:phone":"+49 3722/816503",
    "sg:postcode":"09212",
    "sg:province":"Sachsen",
    "wof:name":"Detemobil Gmbh",
    "wof:placetype":"venue"
},
  "geometry": {"coordinates":[12.7635850906,50.8574905396],"type":"Point"}
}