{
  "type": "Feature",
  "properties": {
    "iso:country":"DE",
    "sg:address":"Schwarzfeldstr. 60",
    "sg:city":"Aalen",
    "sg:phone":"+49 7366/2233",
    "sg:postcode":"73434",
    "sg:province":"Baden-W\u00fcrttemberg",
    "wof:name":"Uwe K\u00f6lbl Heilpraktiker",
    "wof:placetype":"venue"
},
  "geometry": {"coordinates":[10.0307207108,48.8682403564],"type":"Point"}
}