{
  "type": "Feature",
  "properties": {
    "iso:country":"DE",
    "sg:address":"Industriestr 17",
    "sg:city":"Rodenbach",
    "sg:phone":"+49 6184/598206",
    "sg:postcode":"63517",
    "sg:province":"Hessen",
    "wof:name":"De Nora Deutschland Gmbh",
    "wof:placetype":"venue"
},
  "geometry": {"coordinates":[9.00614,50.147141],"type":"Point"}
}