{
  "type": "Feature",
  "properties": {
    "iso:country":"DE",
    "sg:address":"Hofer Str. 75",
    "sg:city":"Mittelbach",
    "sg:phone":"+49 371/2672107",
    "sg:postcode":"09224",
    "sg:province":"Sachsen",
    "wof:name":"Citysirs Gmbh",
    "wof:placetype":"venue"
},
  "geometry": {"coordinates":[12.79828,50.799133],"type":"Point"}
}