{
  "type": "Feature",
  "properties": {
    "iso:country":"DE",
    "sg:address":"Auf dem Groben 1",
    "sg:city":"Siegen",
    "sg:phone":"+49 271/390547",
    "sg:postcode":"57080",
    "sg:province":"Nordrhein-Westfalen",
    "wof:name":"Ev. Pfarramt Siegen-eisern",
    "wof:placetype":"venue"
},
  "geometry": {"coordinates":[8.0419340134,50.8296318054],"type":"Point"}
}