{
  "type": "Feature",
  "properties": {
    "iso:country":"DE",
    "sg:address":"Sternstr. 15",
    "sg:city":"Kiel",
    "sg:phone":"+49 431/93781",
    "sg:postcode":"24103",
    "sg:province":"Schleswig-Holstein",
    "wof:name":"Bj\u00f6rn Sick",
    "wof:placetype":"venue"
},
  "geometry": {"coordinates":[10.123287,54.324062],"type":"Point"}
}