{
  "type": "Feature",
  "properties": {
    "iso:country":"DE",
    "sg:address":"Im Geisengraben 2",
    "sg:city":"H\u00fcnstetten",
    "sg:phone":"+49 6438/921865",
    "sg:postcode":"65510",
    "sg:province":"Hessen",
    "wof:name":"Gerhard M\u00fcller",
    "wof:placetype":"venue"
},
  "geometry": {"coordinates":[8.1907567978,50.2740478516],"type":"Point"}
}