{
  "type": "Feature",
  "properties": {
    "iso:country":"DE",
    "sg:address":"Hardtstr. 9",
    "sg:city":"Schw\u00e4bisch Hall",
    "sg:phone":"+49 7977/89012",
    "sg:postcode":"74523",
    "sg:province":"Baden-W\u00fcrttemberg",
    "wof:name":"Harald Reich",
    "wof:placetype":"venue"
},
  "geometry": {"coordinates":[9.6465597153,49.0582695007],"type":"Point"}
}