{
  "type": "Feature",
  "properties": {
    "iso:country":"DE",
    "sg:address":"Dickesbacher Str. 21",
    "sg:city":"Idar-Oberstein",
    "sg:phone":"+49 6784/7676",
    "sg:postcode":"55743",
    "sg:province":"Rheinland-Pfalz",
    "wof:name":"Zum Maikrug",
    "wof:placetype":"venue"
},
  "geometry": {"coordinates":[7.4065508842,49.7369422913],"type":"Point"}
}