{
  "type": "Feature",
  "properties": {
    "iso:country":"DE",
    "sg:address":"Hauptstr. 114",
    "sg:city":"Elzach",
    "sg:phone":"+49 7682/8840",
    "sg:postcode":"79215",
    "sg:province":"Baden-W\u00fcrttemberg",
    "wof:name":"Ernst Dilberger",
    "wof:placetype":"venue"
},
  "geometry": {"coordinates":[8.0728797913,48.1772384644],"type":"Point"}
}