{
  "type": "Feature",
  "properties": {
    "iso:country":"DE",
    "sg:address":"Uracher Str. 33",
    "sg:city":"Metzingen",
    "sg:phone":"+49 7123/61861",
    "sg:postcode":"72555",
    "sg:province":"Baden-W\u00fcrttemberg",
    "wof:name":"Minimal",
    "wof:placetype":"venue"
},
  "geometry": {"coordinates":[9.3079786301,48.5294914246],"type":"Point"}
}