{
  "type": "Feature",
  "properties": {
    "iso:country":"DE",
    "sg:address":"Heinz-B\u00e4cker-Str. 28 - 30",
    "sg:city":"Essen",
    "sg:phone":"+49 201/661025",
    "sg:postcode":"45356",
    "sg:province":"Nordrhein-Westfalen",
    "wof:name":"Lothar Schwieten Gmbh",
    "wof:placetype":"venue"
},
  "geometry": {"coordinates":[6.9447,51.494984],"type":"Point"}
}