{
  "type": "Feature",
  "properties": {
    "iso:country":"DE",
    "sg:address":"Beckerstr. 35",
    "sg:city":"Herford",
    "sg:phone":"+49 4952/2153007",
    "sg:postcode":"32052",
    "sg:province":"Nordrhein-Westfalen",
    "wof:name":"Zethadeem Kleiderfabrik Ohg",
    "wof:placetype":"venue"
},
  "geometry": {"coordinates":[8.670924,52.11377],"type":"Point"}
}