{
  "type": "Feature",
  "properties": {
    "iso:country":"DE",
    "sg:address":"Max-Planck-Str. 5",
    "sg:city":"Verden",
    "sg:postcode":"27283",
    "sg:province":"Niedersachsen",
    "wof:name":"Msg Maintenance Service Gmbh & Co. Kg",
    "wof:placetype":"venue"
},
  "geometry": {"coordinates":[9.2565517426,52.9127807617],"type":"Point"}
}