{
  "type": "Feature",
  "properties": {
    "iso:country":"DE",
    "sg:address":"Geibelstr. 4a",
    "sg:city":"Bad Salzuflen",
    "sg:phone":"+49 5222/13975",
    "sg:postcode":"32105",
    "sg:province":"Nordrhein-Westfalen",
    "wof:name":"Willi Eckardt Ingenieur",
    "wof:placetype":"venue"
},
  "geometry": {"coordinates":[8.7448997498,52.0928764343],"type":"Point"}
}