{
  "type": "Feature",
  "properties": {
    "iso:country":"DE",
    "sg:address":"Am S\u00f6drath 50",
    "sg:city":"Ratingen",
    "sg:phone":"+49 2054/3439",
    "sg:postcode":"40885",
    "sg:province":"Nordrhein-Westfalen",
    "wof:name":"Gerritzen Und Fenten Kanal-und Strassenbau Gmbh",
    "wof:placetype":"venue"
},
  "geometry": {"coordinates":[6.8845210075,51.363193512],"type":"Point"}
}