{
  "type": "Feature",
  "properties": {
    "iso:country":"DE",
    "sg:address":"Br\u00fcckenstr. 7",
    "sg:city":"Remshalden",
    "sg:postcode":"73630",
    "sg:province":"Baden-W\u00fcrttemberg",
    "wof:name":"Peter Kaczinski Ingenieur",
    "wof:placetype":"venue"
},
  "geometry": {"coordinates":[9.4141397476,48.8086509705],"type":"Point"}
}