{
  "type": "Feature",
  "properties": {
    "iso:country":"DE",
    "sg:address":"Weyerstr. 4-6",
    "sg:city":"Solingen",
    "sg:phone":"+49 212/337639",
    "sg:postcode":"42697",
    "sg:province":"Nordrhein-Westfalen",
    "wof:name":"Family Fitness",
    "wof:placetype":"venue"
},
  "geometry": {"coordinates":[7.0064258575,51.1678237915],"type":"Point"}
}