{
  "type": "Feature",
  "properties": {
    "iso:country":"DE",
    "sg:address":"Hasenstr. 2",
    "sg:city":"Monheim",
    "sg:phone":"+49 2173/53003",
    "sg:postcode":"40789",
    "sg:province":"Nordrhein-Westfalen",
    "wof:name":"Tecnomatix Atmd Advanced Technology Medical",
    "wof:placetype":"venue"
},
  "geometry": {"coordinates":[6.89625,51.098049],"type":"Point"}
}