{
  "type": "Feature",
  "properties": {
    "iso:country":"DE",
    "sg:address":"Eschenweg 4",
    "sg:city":"Cottbus",
    "sg:phone":"+49 355/871845",
    "sg:postcode":"03055",
    "sg:province":"Brandenburg",
    "wof:name":"Bautischlerei Schulerowitz Gmbh",
    "wof:placetype":"venue"
},
  "geometry": {"coordinates":[14.310601,51.792133],"type":"Point"}
}