{
  "type": "Feature",
  "properties": {
    "iso:country":"DE",
    "sg:address":"Alter Kirchweg 29",
    "sg:city":"Scharnhorst",
    "sg:phone":"+49 5142/1235",
    "sg:postcode":"29348",
    "sg:province":"Niedersachsen",
    "wof:name":"Rudolf Kaiser",
    "wof:placetype":"venue"
},
  "geometry": {"coordinates":[10.26782,52.726841],"type":"Point"}
}