{
  "type": "Feature",
  "properties": {
    "iso:country":"DE",
    "sg:address":"Walfischgasse 7",
    "sg:city":"Ulm",
    "sg:phone":"+49 731/65228",
    "sg:postcode":"89073",
    "sg:province":"Baden-W\u00fcrttemberg",
    "wof:name":"P. B\u00fcttner",
    "wof:placetype":"venue"
},
  "geometry": {"coordinates":[9.9890203476,48.3993797302],"type":"Point"}
}