{
  "type": "Feature",
  "properties": {
    "iso:country":"DE",
    "sg:address":"Liebfrauenstr. 3",
    "sg:city":"Werl",
    "sg:phone":"+49 2922/2425",
    "sg:postcode":"59457",
    "sg:province":"Nordrhein-Westfalen",
    "wof:name":"Breer Haarstudio",
    "wof:placetype":"venue"
},
  "geometry": {"coordinates":[7.9093980789,51.5531768799],"type":"Point"}
}