{
  "type": "Feature",
  "properties": {
    "iso:country":"DE",
    "sg:address":"Eiderstedter Weg 26",
    "sg:city":"Berlin",
    "sg:phone":"+49 30/8013406",
    "sg:postcode":"14129",
    "sg:province":"Berlin",
    "wof:name":"Gerhard Utzt Architekt",
    "wof:placetype":"venue"
},
  "geometry": {"coordinates":[13.220532,52.433681],"type":"Point"}
}