{
  "type": "Feature",
  "properties": {
    "iso:country":"DE",
    "sg:address":"Pflegelberg 6",
    "sg:city":"Wangen",
    "sg:phone":"+49 7528/2366",
    "sg:postcode":"88239",
    "sg:province":"Baden-W\u00fcrttemberg",
    "wof:name":"Gerhard Sauter",
    "wof:placetype":"venue"
},
  "geometry": {"coordinates":[9.7423706055,47.6593704224],"type":"Point"}
}