{
  "type": "Feature",
  "properties": {
    "iso:country":"DE",
    "sg:address":"Sanddornweg 33",
    "sg:city":"Sankt Augustin",
    "sg:phone":"+49 2241/335483",
    "sg:postcode":"53757",
    "sg:province":"Nordrhein-Westfalen",
    "wof:name":"Kdt Handelsagentur Gmbh",
    "wof:placetype":"venue"
},
  "geometry": {"coordinates":[7.2026338577,50.7744445801],"type":"Point"}
}