{
  "type": "Feature",
  "properties": {
    "iso:country":"DE",
    "sg:address":"Knospstr. 9",
    "sg:city":"Stuttgart",
    "sg:phone":"+49 711/625240",
    "sg:postcode":"70178",
    "sg:province":"Baden-W\u00fcrttemberg",
    "wof:name":"Dr. Steffen Fortun Rechtsanwalt",
    "wof:placetype":"venue"
},
  "geometry": {"coordinates":[9.1632347107,48.7709579468],"type":"Point"}
}