{
  "type": "Feature",
  "properties": {
    "iso:country":"DE",
    "sg:address":"Cuxhavener Str. 484",
    "sg:city":"Hamburg",
    "sg:phone":"+49 40/7028870",
    "sg:postcode":"21149",
    "sg:province":"Hamburg",
    "wof:name":"Metin Araci",
    "wof:placetype":"venue"
},
  "geometry": {"coordinates":[9.8215398788,53.470489502],"type":"Point"}
}