{
  "type": "Feature",
  "properties": {
    "iso:country":"DE",
    "sg:address":"K\u00fchnemannstr. 24-26",
    "sg:city":"Berlin",
    "sg:postcode":"13409",
    "sg:province":"Berlin",
    "wof:name":"Spree-kurier Expre\u00dfdienste Gmbh",
    "wof:placetype":"venue"
},
  "geometry": {"coordinates":[13.381594,52.566334],"type":"Point"}
}