{
  "type": "Feature",
  "properties": {
    "iso:country":"DE",
    "sg:address":"Emsstr. 16",
    "sg:city":"Rheine",
    "sg:phone":"+49 5971/2680",
    "sg:postcode":"48431",
    "sg:province":"Nordrhein-Westfalen",
    "wof:name":"Franz Scholh\u00f6lter",
    "wof:placetype":"venue"
},
  "geometry": {"coordinates":[7.4391298294,52.2780799866],"type":"Point"}
}