{
  "type": "Feature",
  "properties": {
    "iso:country":"DE",
    "sg:address":"Iggensbacher Str. 1",
    "sg:city":"Sch\u00f6llnach-Iggensbach",
    "sg:phone":"+49 9903/417",
    "sg:postcode":"94532",
    "sg:province":"Bayern",
    "wof:name":"Raiffeisenbank Sch\u00f6llnach Eg",
    "wof:placetype":"venue"
},
  "geometry": {"coordinates":[13.20633,48.724792],"type":"Point"}
}