{
  "type": "Feature",
  "properties": {
    "iso:country":"DE",
    "sg:address":"Flachsmeerstr. 14",
    "sg:city":"Papenburg",
    "sg:phone":"+49 4961/974220",
    "sg:postcode":"26871",
    "sg:province":"Niedersachsen",
    "wof:name":"Sozialer Hilfsdienst",
    "wof:placetype":"venue"
},
  "geometry": {"coordinates":[7.431248,53.082684],"type":"Point"}
}