{
  "type": "Feature",
  "properties": {
    "iso:country":"DE",
    "sg:address":"Altk\u00f6nigstr. 124",
    "sg:city":"Oberursel",
    "sg:phone":"+49 6171/910491",
    "sg:postcode":"61440",
    "sg:province":"Hessen",
    "wof:name":"Prof. Walter Weiss Ingenieur",
    "wof:placetype":"venue"
},
  "geometry": {"coordinates":[8.5607242584,50.2101974487],"type":"Point"}
}