{
  "type": "Feature",
  "properties": {
    "iso:country":"DE",
    "sg:address":"Hintermayrstr. 32",
    "sg:city":"N\u00fcrnberg",
    "sg:phone":"+49 911/331105",
    "sg:postcode":"90409",
    "sg:province":"Bayern",
    "wof:name":"E. Bauscher Verleihbetrieb",
    "wof:placetype":"venue"
},
  "geometry": {"coordinates":[11.095457077,49.4697723389],"type":"Point"}
}