{
  "type": "Feature",
  "properties": {
    "iso:country":"DE",
    "sg:address":"Wei\u00dfachstr. 19",
    "sg:city":"Oberstaufen",
    "sg:phone":"+49 8386/7266",
    "sg:postcode":"87534",
    "sg:province":"Bayern",
    "wof:name":"Restaurant Pius",
    "wof:placetype":"venue"
},
  "geometry": {"coordinates":[10.0214004517,47.5490531921],"type":"Point"}
}