{
  "type": "Feature",
  "properties": {
    "iso:country":"DE",
    "sg:address":"Aussiedlerhof 1",
    "sg:city":"Ostfildern",
    "sg:phone":"+49 711/3482462",
    "sg:postcode":"73760",
    "sg:province":"Baden-W\u00fcrttemberg",
    "wof:name":"Wilhelm Kaiser",
    "wof:placetype":"venue"
},
  "geometry": {"coordinates":[9.28235,48.71122],"type":"Point"}
}