{
  "type": "Feature",
  "properties": {
    "iso:country":"DE",
    "sg:address":"Stausberg",
    "sg:city":"Friesenhagen",
    "sg:phone":"+49 2734/7215",
    "sg:postcode":"51598",
    "sg:province":"Rheinland-Pfalz",
    "wof:name":"Norbert Klein",
    "wof:placetype":"venue"
},
  "geometry": {"coordinates":[7.811466,50.877407],"type":"Point"}
}