{
  "type": "Feature",
  "properties": {
    "iso:country":"DE",
    "sg:address":"Antoniusplatz 10",
    "sg:city":"Cloppenburg",
    "sg:phone":"+49 4471/4252",
    "sg:postcode":"49661",
    "sg:province":"Niedersachsen",
    "wof:name":"Marpla Gmbh",
    "wof:placetype":"venue"
},
  "geometry": {"coordinates":[8.0420503616,52.8485908508],"type":"Point"}
}