{
  "type": "Feature",
  "properties": {
    "iso:country":"DE",
    "sg:address":"Beekenende 9",
    "sg:city":"Achim",
    "sg:postcode":"28832",
    "sg:province":"Niedersachsen",
    "wof:name":"Yildirim Gmbh",
    "wof:placetype":"venue"
},
  "geometry": {"coordinates":[9.0140419006,53.0335426331],"type":"Point"}
}