{
  "type": "Feature",
  "properties": {
    "iso:country":"DE",
    "sg:address":"Malzgasse 4",
    "sg:city":"Neustadt",
    "sg:postcode":"01844",
    "sg:province":"Sachsen",
    "wof:name":"Ekkehard Schulze",
    "wof:placetype":"venue"
},
  "geometry": {"coordinates":[14.215615,51.026482],"type":"Point"}
}