{
  "type": "Feature",
  "properties": {
    "iso:country":"DE",
    "sg:address":"Ottostr. 12",
    "sg:city":"Marktredwitz",
    "sg:phone":"+49 9231/2739",
    "sg:postcode":"95615",
    "sg:province":"Bayern",
    "wof:name":"E.l. Vogel Gmbh",
    "wof:placetype":"venue"
},
  "geometry": {"coordinates":[12.0856704712,49.9999885559],"type":"Point"}
}