{
  "type": "Feature",
  "properties": {
    "iso:country":"DE",
    "sg:address":"Theresienstr. 3",
    "sg:city":"F\u00fcrth",
    "sg:phone":"+49 911/749050",
    "sg:postcode":"90762",
    "sg:province":"Bayern",
    "wof:name":"Sin-a-matic Handels Gmbh",
    "wof:placetype":"venue"
},
  "geometry": {"coordinates":[10.9868307114,49.4711380005],"type":"Point"}
}