{
  "type": "Feature",
  "properties": {
    "iso:country":"DE",
    "sg:address":"Robert-Koch-Str. 53",
    "sg:city":"Burghausen",
    "sg:phone":"+49 8677/3377",
    "sg:postcode":"84489",
    "sg:province":"Bayern",
    "wof:name":"G\u00fcnther Bruckmeier",
    "wof:placetype":"venue"
},
  "geometry": {"coordinates":[12.82533,48.169903],"type":"Point"}
}