{
  "type": "Feature",
  "properties": {
    "iso:country":"DE",
    "sg:address":"Sudetenstr. 7",
    "sg:city":"Speichersdorf",
    "sg:phone":"+49 9275/572",
    "sg:postcode":"95469",
    "sg:province":"Bayern",
    "wof:name":"Manfred Gillich",
    "wof:placetype":"venue"
},
  "geometry": {"coordinates":[11.772023201,49.8668327332],"type":"Point"}
}