{
  "type": "Feature",
  "properties": {
    "iso:country":"DE",
    "sg:address":"Wiesethbruck 1",
    "sg:city":"Bechhofen",
    "sg:phone":"+49 9822/605404",
    "sg:postcode":"91572",
    "sg:province":"Bayern",
    "wof:name":"Max Heumann",
    "wof:placetype":"venue"
},
  "geometry": {"coordinates":[10.6063508987,49.1616744995],"type":"Point"}
}