{
  "type": "Feature",
  "properties": {
    "iso:country":"DE",
    "sg:address":"Ebendorfer Str. 19",
    "sg:city":"Magdeburg",
    "sg:phone":"+49 391/7311838",
    "sg:postcode":"39108",
    "sg:province":"Sachsen-Anhalt",
    "wof:name":"Opti Unternehmungs- Beteiligungs- Und Ver-",
    "wof:placetype":"venue"
},
  "geometry": {"coordinates":[11.614614,52.138561],"type":"Point"}
}