{
  "type": "Feature",
  "properties": {
    "iso:country":"DE",
    "sg:address":"Friedrich-von-Teck-Str. 5",
    "sg:city":"H\u00f6chst\u00e4dt",
    "sg:phone":"+49 9074/4020",
    "sg:postcode":"89420",
    "sg:province":"Bayern",
    "wof:name":"Franz Steckeler Papier- Und Schreibwaren",
    "wof:placetype":"venue"
},
  "geometry": {"coordinates":[10.567078,48.611961],"type":"Point"}
}