{
  "type": "Feature",
  "properties": {
    "iso:country":"DE",
    "sg:address":"Kreuzstr. 5-6",
    "sg:city":"M\u00fcnster",
    "sg:postcode":"48143",
    "sg:province":"Nordrhein-Westfalen",
    "wof:name":"Hl Deutscher Supermarkt",
    "wof:placetype":"venue"
},
  "geometry": {"coordinates":[7.62150383,51.9656677246],"type":"Point"}
}