{
  "type": "Feature",
  "properties": {
    "iso:country":"DE",
    "sg:address":"Bautzener Str.",
    "sg:city":"Wei\u00dfwasser",
    "sg:phone":"+49 3576/242005",
    "sg:postcode":"02943",
    "sg:province":"Sachsen",
    "wof:name":"Volksschwimmhalle",
    "wof:placetype":"venue"
},
  "geometry": {"coordinates":[14.6410083771,51.5041656494],"type":"Point"}
}