{
  "type": "Feature",
  "properties": {
    "iso:country":"DE",
    "sg:address":"Lundweg 3",
    "sg:city":"Sankelmark",
    "sg:phone":"+49 4602/1398",
    "sg:postcode":"24988",
    "sg:province":"Schleswig-Holstein",
    "wof:name":"Baugesch\u00e4ft H. J. Schultze Gmbh",
    "wof:placetype":"venue"
},
  "geometry": {"coordinates":[9.429771,54.700863],"type":"Point"}
}