{
  "type": "Feature",
  "properties": {
    "iso:country":"DE",
    "sg:address":"Venloer Str. 1499",
    "sg:city":"Pulheim",
    "sg:phone":"+49 2238/57969",
    "sg:postcode":"50259",
    "sg:province":"Nordrhein-Westfalen",
    "wof:name":"Friedrich Pirkowski Kfz-verwertungsuntern.",
    "wof:placetype":"venue"
},
  "geometry": {"coordinates":[6.8318090439,50.9863395691],"type":"Point"}
}