{
  "type": "Feature",
  "properties": {
    "iso:country":"DE",
    "sg:address":"Unter den Eichen 28",
    "sg:city":"Oldenburg",
    "sg:phone":"+49 441/71176",
    "sg:postcode":"26122",
    "sg:province":"Niedersachsen",
    "wof:name":"Hans-peter Stoessel Immobilien Gmbh",
    "wof:placetype":"venue"
},
  "geometry": {"coordinates":[8.1996994019,53.1377906799],"type":"Point"}
}