{
  "type": "Feature",
  "properties": {
    "iso:country":"DE",
    "sg:address":"Palanterstr. 14",
    "sg:city":"K\u00f6ln",
    "sg:phone":"+49 221/443323",
    "sg:postcode":"50937",
    "sg:province":"Nordrhein-Westfalen",
    "wof:name":"Fake Film-construction Gmbh",
    "wof:placetype":"venue"
},
  "geometry": {"coordinates":[6.924427,50.922073],"type":"Point"}
}