{
  "type": "Feature",
  "properties": {
    "iso:country":"DE",
    "sg:address":"Helmholtzstr. 7",
    "sg:city":"Stutensee",
    "sg:phone":"+49 7244/73610",
    "sg:postcode":"76297",
    "sg:province":"Baden-W\u00fcrttemberg",
    "wof:name":"Hotel-restaurant Stutensee",
    "wof:placetype":"venue"
},
  "geometry": {"coordinates":[8.4528970718,49.0733680725],"type":"Point"}
}