{
  "type": "Feature",
  "properties": {
    "iso:country":"DE",
    "sg:address":"Artur-Sommer-Str. 8",
    "sg:city":"Remscheid",
    "sg:phone":"+49 2191/667024",
    "sg:postcode":"42897",
    "sg:province":"Nordrhein-Westfalen",
    "wof:name":"H. Gerhards",
    "wof:placetype":"venue"
},
  "geometry": {"coordinates":[7.2727918625,51.1830291748],"type":"Point"}
}