{
  "type": "Feature",
  "properties": {
    "iso:country":"DE",
    "sg:address":"Markt 6",
    "sg:city":"Torgau",
    "sg:phone":"+49 3421/73213",
    "sg:postcode":"04860",
    "sg:province":"Sachsen",
    "wof:name":"Hotel Goldener Anker",
    "wof:placetype":"venue"
},
  "geometry": {"coordinates":[12.9748573303,51.5575485229],"type":"Point"}
}