{
  "type": "Feature",
  "properties": {
    "iso:country":"DE",
    "sg:address":"Westerlandstr. 14",
    "sg:city":"Wenningstedt",
    "sg:phone":"+49 4651/42001",
    "sg:postcode":"25996",
    "sg:province":"Schleswig-Holstein",
    "wof:name":"Hotel Westend",
    "wof:placetype":"venue"
},
  "geometry": {"coordinates":[8.3221521378,54.9348335266],"type":"Point"}
}