{
  "type": "Feature",
  "properties": {
    "iso:country":"DE",
    "sg:address":"Bartelsstr. 8",
    "sg:city":"Hamburg",
    "sg:phone":"+49 40/42106954",
    "sg:postcode":"20357",
    "sg:province":"Hamburg",
    "wof:name":"010101www.shifteins.de",
    "wof:placetype":"venue"
},
  "geometry": {"coordinates":[9.9652824402,53.5617446899],"type":"Point"}
}