{
  "type": "Feature",
  "properties": {
    "iso:country":"DE",
    "sg:address":"Ederstr 18",
    "sg:city":"Erndtebr\u00fcck",
    "sg:phone":"+49 2753/609101",
    "sg:postcode":"57339",
    "sg:province":"Nordrhein-Westfalen",
    "wof:name":"Spezial-edelstahl-verarbeitung Gmbh",
    "wof:placetype":"venue"
},
  "geometry": {"coordinates":[8.2358283997,50.9825363159],"type":"Point"}
}