{
  "type": "Feature",
  "properties": {
    "iso:country":"DE",
    "sg:address":"Im Klein Feld 8",
    "sg:city":"Karlsdorf-Neuthard",
    "sg:postcode":"76689",
    "sg:province":"Baden-W\u00fcrttemberg",
    "wof:name":"Startweb.de - Ihr Start Ins Internet",
    "wof:placetype":"venue"
},
  "geometry": {"coordinates":[8.523326,49.134953],"type":"Point"}
}