{
  "type": "Feature",
  "properties": {
    "iso:country":"DE",
    "sg:address":"Kolpingstr. 9",
    "sg:city":"Wenzenbach",
    "sg:phone":"+49 9407/90623",
    "sg:postcode":"93173",
    "sg:province":"Bayern",
    "wof:name":"Richard Bienia Ingenieur",
    "wof:placetype":"venue"
},
  "geometry": {"coordinates":[12.1929588318,49.0713119507],"type":"Point"}
}