{
  "type": "Feature",
  "properties": {
    "iso:country":"DE",
    "sg:address":"Wachmannstr. 107",
    "sg:city":"Bremen",
    "sg:phone":"+49 421/342015",
    "sg:postcode":"28209",
    "sg:province":"Bremen",
    "wof:name":"Mitzscherlich Verwaltungs Gmbh",
    "wof:placetype":"venue"
},
  "geometry": {"coordinates":[8.834173,53.086445],"type":"Point"}
}