{
  "type": "Feature",
  "properties": {
    "iso:country":"DE",
    "sg:address":"Schwarzenberger Str. 40",
    "sg:city":"Johanngeorgenstadt",
    "sg:phone":"+49 3773/882851",
    "sg:postcode":"08349",
    "sg:province":"Sachsen",
    "wof:name":"J. Kraus",
    "wof:placetype":"venue"
},
  "geometry": {"coordinates":[12.7257099152,50.4493408203],"type":"Point"}
}