{
  "type": "Feature",
  "properties": {
    "iso:country":"DE",
    "sg:address":"Schnarsleber Str. 11",
    "sg:city":"Niederndodeleben",
    "sg:phone":"+49 39204/82427",
    "sg:postcode":"39167",
    "sg:province":"Sachsen-Anhalt",
    "wof:name":"Moritz-apotheke Inh. B\u00e4rbel Schiller E. K.",
    "wof:placetype":"venue"
},
  "geometry": {"coordinates":[11.501161,52.136555],"type":"Point"}
}