{
  "type": "Feature",
  "properties": {
    "iso:country":"DE",
    "sg:address":"Betrieb Insel Oberau",
    "sg:city":"Fachbach",
    "sg:phone":"+49 4926/0313023",
    "sg:postcode":"56133",
    "sg:province":"Rheinland-Pfalz",
    "wof:name":"Comco-plastic Gmbh",
    "wof:placetype":"venue"
},
  "geometry": {"coordinates":[7.6902451515,50.3380241394],"type":"Point"}
}