{
  "type": "Feature",
  "properties": {
    "iso:country":"DE",
    "sg:address":"Rieder Tal 4",
    "sg:city":"Dollnstein",
    "sg:phone":"+49 8422/1313",
    "sg:postcode":"91795",
    "sg:province":"Bayern",
    "wof:name":"Alfons Kruck Jun.",
    "wof:placetype":"venue"
},
  "geometry": {"coordinates":[11.075383,48.864628],"type":"Point"}
}