{
  "type": "Feature",
  "properties": {
    "iso:country":"DE",
    "sg:address":"Binger Str. 53",
    "sg:city":"Ingelheim",
    "sg:phone":"+49 6132/3272",
    "sg:postcode":"55218",
    "sg:province":"Rheinland-Pfalz",
    "wof:name":"R. E. Gottschalk Obstanbau",
    "wof:placetype":"venue"
},
  "geometry": {"coordinates":[8.0591392517,49.9750137329],"type":"Point"}
}