{
  "type": "Feature",
  "properties": {
    "iso:country":"DE",
    "sg:address":"Im Holzweg 10",
    "sg:city":"Spiesheim",
    "sg:phone":"+49 6732/8804",
    "sg:postcode":"55288",
    "sg:province":"Rheinland-Pfalz",
    "wof:name":"Tra Systembau Schmidt Gmbh",
    "wof:placetype":"venue"
},
  "geometry": {"coordinates":[8.130197,49.807041],"type":"Point"}
}