{
  "type": "Feature",
  "properties": {
    "iso:country":"DE",
    "sg:address":"Marktplatz 13",
    "sg:city":"Postbauer-Heng",
    "sg:phone":"+49 9188/1075",
    "sg:postcode":"92353",
    "sg:province":"Bayern",
    "wof:name":"Rats-apotheke",
    "wof:placetype":"venue"
},
  "geometry": {"coordinates":[11.353769,49.303532],"type":"Point"}
}