{
  "type": "Feature",
  "properties": {
    "iso:country":"DE",
    "sg:address":"Bahnhofstr. 1",
    "sg:city":"Gr\u00f6benzell",
    "sg:phone":"+49 8142/54465",
    "sg:postcode":"82194",
    "sg:province":"Bayern",
    "wof:name":"Bistro Il Paradiso",
    "wof:placetype":"venue"
},
  "geometry": {"coordinates":[11.3729505539,48.1959915161],"type":"Point"}
}