{
  "type": "Feature",
  "properties": {
    "iso:country":"DE",
    "sg:address":"Gartenstr. 21",
    "sg:city":"Kamp-Lintfort",
    "sg:phone":"+49 2842/8789",
    "sg:postcode":"47475",
    "sg:province":"Nordrhein-Westfalen",
    "wof:name":"Malermeister W. Und H. Kleinbongardt Gmbh",
    "wof:placetype":"venue"
},
  "geometry": {"coordinates":[6.53406,51.49865],"type":"Point"}
}