{
  "type": "Feature",
  "properties": {
    "iso:country":"DE",
    "sg:address":"T\u00f6pferstr. 6",
    "sg:city":"R\u00f6dermark",
    "sg:postcode":"63322",
    "sg:province":"Hessen",
    "wof:name":"Palio Erlebnis- Spielst\u00e4tten Gmbh",
    "wof:placetype":"venue"
},
  "geometry": {"coordinates":[8.7965965271,49.9698638916],"type":"Point"}
}