{
  "type": "Feature",
  "properties": {
    "iso:country":"DE",
    "sg:address":"R\u00f6merstr. 31",
    "sg:city":"Saarwellingen",
    "sg:phone":"+49 6838/1688",
    "sg:postcode":"66793",
    "sg:province":"Saarland",
    "wof:name":"Georgette Masloh",
    "wof:placetype":"venue"
},
  "geometry": {"coordinates":[6.797618,49.357536],"type":"Point"}
}