{
  "type": "Feature",
  "properties": {
    "iso:country":"DE",
    "sg:address":"Annastr. 31",
    "sg:city":"Niederkr\u00fcchten",
    "sg:phone":"+49 2163/80328",
    "sg:postcode":"41372",
    "sg:province":"Nordrhein-Westfalen",
    "wof:name":"Hans-josef Cox",
    "wof:placetype":"venue"
},
  "geometry": {"coordinates":[6.201341,51.207359],"type":"Point"}
}