{
  "type": "Feature",
  "properties": {
    "iso:country":"DE",
    "sg:address":"Schlitzer Str. 87",
    "sg:city":"Fulda",
    "sg:phone":"+49 661/9529111",
    "sg:postcode":"36039",
    "sg:province":"Hessen",
    "wof:name":"Orchideenapotheke",
    "wof:placetype":"venue"
},
  "geometry": {"coordinates":[9.658759,50.565022],"type":"Point"}
}