{
  "type": "Feature",
  "properties": {
    "iso:country":"DE",
    "sg:address":"Kalkreute 15",
    "sg:city":"Ostrach",
    "sg:postcode":"88356",
    "sg:province":"Baden-W\u00fcrttemberg",
    "wof:name":"Ips - Innovative Parksysteme Gmbh",
    "wof:placetype":"venue"
},
  "geometry": {"coordinates":[9.3799953461,47.9528961182],"type":"Point"}
}