{
  "type": "Feature",
  "properties": {
    "iso:country":"DE",
    "sg:address":"Universit\u00e4tsallee 3",
    "sg:city":"Bremen",
    "sg:phone":"+49 421/201280",
    "sg:postcode":"28359",
    "sg:province":"Bremen",
    "wof:name":"Tagesklinik Universit\u00e4ts- Allee Gmbh",
    "wof:placetype":"venue"
},
  "geometry": {"coordinates":[8.852708,53.104279],"type":"Point"}
}