{
  "type": "Feature",
  "properties": {
    "iso:country":"DE",
    "sg:address":"Bahnhofstr. 17",
    "sg:city":"K\u00f6nigsbach-Stein",
    "sg:phone":"+49 7232/9888",
    "sg:postcode":"75203",
    "sg:province":"Baden-W\u00fcrttemberg",
    "wof:name":"Fiess-optik Gmbh",
    "wof:placetype":"venue"
},
  "geometry": {"coordinates":[8.6123056412,48.9644393921],"type":"Point"}
}