{
  "type": "Feature",
  "properties": {
    "iso:country":"DE",
    "sg:address":"Hinter dem Dorfe 21",
    "sg:city":"Vechelde",
    "sg:phone":"+49 5302/2222",
    "sg:postcode":"38159",
    "sg:province":"Niedersachsen",
    "wof:name":"Josef Blahnik",
    "wof:placetype":"venue"
},
  "geometry": {"coordinates":[10.3278417587,52.273059845],"type":"Point"}
}