{
  "type": "Feature",
  "properties": {
    "iso:country":"DE",
    "sg:address":"Klosterweg 13",
    "sg:city":"Dornstetten",
    "sg:phone":"+49 7443/6321",
    "sg:postcode":"72280",
    "sg:province":"Baden-W\u00fcrttemberg",
    "wof:name":"Hans Eisenbeis",
    "wof:placetype":"venue"
},
  "geometry": {"coordinates":[8.4993543625,48.4863739014],"type":"Point"}
}