{
  "type": "Feature",
  "properties": {
    "iso:country":"DE",
    "sg:address":"Robert-Perthel-Str. 10",
    "sg:city":"K\u00f6ln",
    "sg:phone":"+49 221/173001",
    "sg:postcode":"50739",
    "sg:province":"Nordrhein-Westfalen",
    "wof:name":"Bwg Baugrund Und Boden Gmbh",
    "wof:placetype":"venue"
},
  "geometry": {"coordinates":[6.921836853,50.9788970947],"type":"Point"}
}