{
  "type": "Feature",
  "properties": {
    "iso:country":"DE",
    "sg:address":"Karlstr. 5",
    "sg:city":"Augsburg",
    "sg:phone":"+49 821/312184",
    "sg:postcode":"86150",
    "sg:province":"Bayern",
    "wof:name":"Mal Was Anderes",
    "wof:placetype":"venue"
},
  "geometry": {"coordinates":[10.8972616196,48.3702888489],"type":"Point"}
}