{
  "type": "Feature",
  "properties": {
    "iso:country":"DE",
    "sg:address":"Rheinzollstr. 10",
    "sg:city":"Koblenz",
    "sg:phone":"+49 261/38985",
    "sg:postcode":"56068",
    "sg:province":"Rheinland-Pfalz",
    "wof:name":"Garten Eden",
    "wof:placetype":"venue"
},
  "geometry": {"coordinates":[7.6042299271,50.3609924316],"type":"Point"}
}