{
  "type": "Feature",
  "properties": {
    "iso:country":"DE",
    "sg:address":"Flaspoete 38",
    "sg:city":"Dortmund",
    "sg:phone":"+49 231/601636",
    "sg:postcode":"44388",
    "sg:province":"Nordrhein-Westfalen",
    "wof:name":"Artemis-grill",
    "wof:placetype":"venue"
},
  "geometry": {"coordinates":[7.342012,51.49773],"type":"Point"}
}