{
  "type": "Feature",
  "properties": {
    "iso:country":"DE",
    "sg:address":"August-Spindler-Str. 1",
    "sg:city":"G\u00f6ttingen",
    "sg:postcode":"37079",
    "sg:province":"Niedersachsen",
    "wof:name":"Deutsche Post Ag",
    "wof:placetype":"venue"
},
  "geometry": {"coordinates":[9.8924846649,51.5494613647],"type":"Point"}
}