{
  "type": "Feature",
  "properties": {
    "iso:country":"DE",
    "sg:address":"Metzinger Str. 68",
    "sg:city":"Filderstadt",
    "sg:postcode":"70794",
    "sg:province":"Baden-W\u00fcrttemberg",
    "wof:name":"Kubus Verm\u00f6gensverwaltung Gmbh",
    "wof:placetype":"venue"
},
  "geometry": {"coordinates":[9.224157,48.650471],"type":"Point"}
}