{
  "type": "Feature",
  "properties": {
    "iso:country":"DE",
    "sg:address":"Hohenzollernstr. 73",
    "sg:city":"Ludwigshafen",
    "sg:phone":"+49 621/6376003",
    "sg:postcode":"67063",
    "sg:province":"Rheinland-Pfalz",
    "wof:name":"R. He\u00dfler",
    "wof:placetype":"venue"
},
  "geometry": {"coordinates":[8.4197769165,49.4923667908],"type":"Point"}
}