{
  "type": "Feature",
  "properties": {
    "iso:country":"DE",
    "sg:address":"Dresdner Str. 136",
    "sg:city":"Sayda",
    "sg:phone":"+49 37365/1290",
    "sg:postcode":"09619",
    "sg:province":"Sachsen",
    "wof:name":"Otto Trautsch",
    "wof:placetype":"venue"
},
  "geometry": {"coordinates":[13.443152,50.717377],"type":"Point"}
}