{
  "type": "Feature",
  "properties": {
    "iso:country":"DE",
    "sg:address":"Am Obstgarten 12a",
    "sg:city":"Kriftel",
    "sg:phone":"+49 6192/41809",
    "sg:postcode":"65830",
    "sg:province":"Hessen",
    "wof:name":"I. Gommolla",
    "wof:placetype":"venue"
},
  "geometry": {"coordinates":[8.4739551544,50.0806503296],"type":"Point"}
}