{
  "type": "Feature",
  "properties": {
    "iso:country":"DE",
    "sg:address":"Hirschgasse 1",
    "sg:city":"B\u00fcdingen",
    "sg:phone":"+49 6048/3904",
    "sg:postcode":"63654",
    "sg:province":"Hessen",
    "wof:name":"Rudi Gerth",
    "wof:placetype":"venue"
},
  "geometry": {"coordinates":[9.025032,50.255535],"type":"Point"}
}