{
  "type": "Feature",
  "properties": {
    "iso:country":"DE",
    "sg:address":"Boisheimer Str. 16",
    "sg:city":"Schwalmtal",
    "sg:phone":"+49 2163/2962",
    "sg:postcode":"41366",
    "sg:province":"Nordrhein-Westfalen",
    "wof:name":"P. Opstals",
    "wof:placetype":"venue"
},
  "geometry": {"coordinates":[6.260865,51.248333],"type":"Point"}
}