{
  "type": "Feature",
  "properties": {
    "iso:country":"DE",
    "sg:address":"Sternbuschweg 40",
    "sg:city":"Duisburg",
    "sg:phone":"+49 203/333338",
    "sg:postcode":"47057",
    "sg:province":"Nordrhein-Westfalen",
    "wof:name":"Ahd Edv-handels- Und Dienstleistungs-gmbh",
    "wof:placetype":"venue"
},
  "geometry": {"coordinates":[6.794762,51.431007],"type":"Point"}
}