{
  "type": "Feature",
  "properties": {
    "iso:country":"DE",
    "sg:address":"Zwerchallee 1",
    "sg:city":"Mainz",
    "sg:phone":"+49 6131/687077",
    "sg:postcode":"55120",
    "sg:province":"Rheinland-Pfalz",
    "wof:name":"Clever Rent Gmbh",
    "wof:placetype":"venue"
},
  "geometry": {"coordinates":[8.239828,50.016468],"type":"Point"}
}