{
  "type": "Feature",
  "properties": {
    "iso:country":"DE",
    "sg:address":"Falkenweg 41",
    "sg:city":"Schwelm",
    "sg:phone":"+49 2336/3954",
    "sg:postcode":"58332",
    "sg:province":"Nordrhein-Westfalen",
    "wof:name":"Axel Bonacker",
    "wof:placetype":"venue"
},
  "geometry": {"coordinates":[7.2788128853,51.276676178],"type":"Point"}
}