{
  "type": "Feature",
  "properties": {
    "iso:country":"DE",
    "sg:address":"Schloss Bruchsal",
    "sg:city":"Bruchsal",
    "sg:phone":"+49 7251/742661",
    "sg:postcode":"76646",
    "sg:province":"Baden-W\u00fcrttemberg",
    "wof:name":"Museum Mechanischer Musik- Instrumente",
    "wof:placetype":"venue"
},
  "geometry": {"coordinates":[8.59706,49.127281],"type":"Point"}
}