{
  "type": "Feature",
  "properties": {
    "iso:country":"DE",
    "sg:address":"Kleinenberger Weg 16b",
    "sg:city":"Paderborn",
    "sg:phone":"+49 5251/64200",
    "sg:postcode":"33100",
    "sg:province":"Nordrhein-Westfalen",
    "wof:name":"Ifk Institut F\u00fcr Kybernetik Der Ais Deutschland E.v.",
    "wof:placetype":"venue"
},
  "geometry": {"coordinates":[8.788599968,51.7094573975],"type":"Point"}
}