{
  "type": "Feature",
  "properties": {
    "iso:country":"DE",
    "sg:address":"Pfarrstr. 10",
    "sg:city":"Oberstdorf",
    "sg:phone":"+49 8322/4567",
    "sg:postcode":"87561",
    "sg:province":"Bayern",
    "wof:name":"Cafe Allg\u00e4u",
    "wof:placetype":"venue"
},
  "geometry": {"coordinates":[10.279594,47.408607],"type":"Point"}
}