{
  "type": "Feature",
  "properties": {
    "iso:country":"DE",
    "sg:address":"Burggrafenstr. 5 a",
    "sg:city":"D\u00fcsseldorf",
    "sg:phone":"+49 211/5586940",
    "sg:postcode":"40545",
    "sg:province":"Nordrhein-Westfalen",
    "wof:name":"G\u00f6bbels & Partner Gmbh",
    "wof:placetype":"venue"
},
  "geometry": {"coordinates":[6.759512,51.232452],"type":"Point"}
}