{
  "type": "Feature",
  "properties": {
    "iso:country":"DE",
    "sg:address":"Hauptstr. 8",
    "sg:city":"Bohmte",
    "sg:phone":"+49 5475/264",
    "sg:postcode":"49163",
    "sg:province":"Niedersachsen",
    "wof:name":"Ev. Pfarramt Hunteburg",
    "wof:placetype":"venue"
},
  "geometry": {"coordinates":[8.2756147385,52.4373626709],"type":"Point"}
}