{
  "type": "Feature",
  "properties": {
    "iso:country":"DE",
    "sg:address":"Sandweg 4",
    "sg:city":"Uetersen",
    "sg:phone":"+49 4122/47071",
    "sg:postcode":"25436",
    "sg:province":"Schleswig-Holstein",
    "wof:name":"Bolz Hydraulik Gmbh",
    "wof:placetype":"venue"
},
  "geometry": {"coordinates":[9.677554,53.680637],"type":"Point"}
}