{
  "type": "Feature",
  "properties": {
    "iso:country":"DE",
    "sg:address":"Viertelchen 13",
    "sg:city":"N\u00fcmbrecht",
    "sg:phone":"+49 2293/3606",
    "sg:postcode":"51588",
    "sg:province":"Nordrhein-Westfalen",
    "wof:name":"Universal Color Fachbetrieb F\u00fcr",
    "wof:placetype":"venue"
},
  "geometry": {"coordinates":[7.601195,50.904202],"type":"Point"}
}