{
  "type": "Feature",
  "properties": {
    "iso:country":"DE",
    "sg:address":"Bahnhofstr. 57",
    "sg:city":"Kempten",
    "sg:postcode":"87435",
    "sg:province":"Bayern",
    "wof:name":"Emg Dextitor Grundst\u00fccksver- Wertungsgesellschaft Mbh",
    "wof:placetype":"venue"
},
  "geometry": {"coordinates":[10.3139734268,47.7169456482],"type":"Point"}
}