{
  "type": "Feature",
  "properties": {
    "iso:country":"DE",
    "sg:address":"Hermannstr. 7",
    "sg:city":"Heppenheim",
    "sg:phone":"+49 6252/69666",
    "sg:postcode":"64646",
    "sg:province":"Hessen",
    "wof:name":"Gugenberger Immobilien",
    "wof:placetype":"venue"
},
  "geometry": {"coordinates":[8.6423254013,49.6440925598],"type":"Point"}
}