{
  "type": "Feature",
  "properties": {
    "iso:country":"DE",
    "sg:address":"Hof\u00e4ckerstr. 7",
    "sg:city":"Oy-Mittelberg",
    "sg:phone":"+49 8366/320",
    "sg:postcode":"87466",
    "sg:province":"Bayern",
    "wof:name":"Oyer Stuben",
    "wof:placetype":"venue"
},
  "geometry": {"coordinates":[10.4507598877,47.6461601257],"type":"Point"}
}