{
  "type": "Feature",
  "properties": {
    "iso:country":"DE",
    "sg:address":"Sierichstr. 126",
    "sg:city":"Hamburg",
    "sg:phone":"+49 40/46072660",
    "sg:postcode":"22299",
    "sg:province":"Hamburg",
    "wof:name":"Hanseatische Ges. Hamburg Costa Blanca Immobilien-verm.",
    "wof:placetype":"venue"
},
  "geometry": {"coordinates":[10.0005931854,53.5903129578],"type":"Point"}
}