{
  "type": "Feature",
  "properties": {
    "iso:country":"DE",
    "sg:address":"Am Stollen 10",
    "sg:city":"Chemnitz",
    "sg:phone":"+49 371/512307",
    "sg:postcode":"09125",
    "sg:province":"Sachsen",
    "wof:name":"B. Borck",
    "wof:placetype":"venue"
},
  "geometry": {"coordinates":[12.944227,50.800037],"type":"Point"}
}