{
  "type": "Feature",
  "properties": {
    "iso:country":"DE",
    "sg:address":"B\u00fcrgst\u00e4dter Str. 3",
    "sg:city":"Miltenberg",
    "sg:phone":"+49 9371/3304",
    "sg:postcode":"63897",
    "sg:province":"Bayern",
    "wof:name":"J. Schmitt",
    "wof:placetype":"venue"
},
  "geometry": {"coordinates":[9.2611351013,49.7037086487],"type":"Point"}
}