{
  "type": "Feature",
  "properties": {
    "iso:country":"DE",
    "sg:address":"Teichstr. 34",
    "sg:city":"Neundorf",
    "sg:phone":"+49 3741/131817",
    "sg:postcode":"08527",
    "sg:province":"Sachsen",
    "wof:name":"Werner Oberst",
    "wof:placetype":"venue"
},
  "geometry": {"coordinates":[12.088716,50.492882],"type":"Point"}
}