{
  "type": "Feature",
  "properties": {
    "iso:country":"DE",
    "sg:address":"Am Markt 2a",
    "sg:city":"Wismar",
    "sg:phone":"+49 3841/282112",
    "sg:postcode":"23966",
    "sg:province":"Mecklenburg-Vorpommern",
    "wof:name":"Rats-apotheke Inh. Karen Schoof",
    "wof:placetype":"venue"
},
  "geometry": {"coordinates":[11.466283,53.891899],"type":"Point"}
}