{
  "type": "Feature",
  "properties": {
    "iso:country":"DE",
    "sg:address":"Finkenweg 12",
    "sg:city":"Ratingen",
    "sg:phone":"+49 2102/963113",
    "sg:postcode":"40883",
    "sg:province":"Nordrhein-Westfalen",
    "wof:name":"Haus- Und Grundbesitzverwalt. Brigitte B\u00fcrgers E.k.",
    "wof:placetype":"venue"
},
  "geometry": {"coordinates":[6.9155302048,51.3374595642],"type":"Point"}
}