{
  "type": "Feature",
  "properties": {
    "iso:country":"DE",
    "sg:address":"Mittelstr. 7",
    "sg:city":"Litzendorf",
    "sg:phone":"+49 9505/1646",
    "sg:postcode":"96123",
    "sg:province":"Bayern",
    "wof:name":"Herbst",
    "wof:placetype":"venue"
},
  "geometry": {"coordinates":[11.002537,49.909176],"type":"Point"}
}