{
  "type": "Feature",
  "properties": {
    "iso:country":"DE",
    "sg:address":"Viktoriastr. 66",
    "sg:city":"Bochum",
    "sg:phone":"+49 234/12012",
    "sg:postcode":"44787",
    "sg:province":"Nordrhein-Westfalen",
    "wof:name":"Barrio Brothers",
    "wof:placetype":"venue"
},
  "geometry": {"coordinates":[7.2150058746,51.4763221741],"type":"Point"}
}