{
  "type": "Feature",
  "properties": {
    "iso:country":"DE",
    "sg:address":"Engelsweg 17",
    "sg:city":"Schl\u00fcchtern",
    "sg:phone":"+49 6661/1417",
    "sg:postcode":"36381",
    "sg:province":"Hessen",
    "wof:name":"Josef Faust",
    "wof:placetype":"venue"
},
  "geometry": {"coordinates":[9.560612,50.344315],"type":"Point"}
}