{
  "type": "Feature",
  "properties": {
    "iso:country":"DE",
    "sg:address":"Marktstr. 12",
    "sg:city":"Heeslingen",
    "sg:phone":"+49 4281/3716",
    "sg:postcode":"27404",
    "sg:province":"Niedersachsen",
    "wof:name":"Dietrich Meyer",
    "wof:placetype":"venue"
},
  "geometry": {"coordinates":[9.336822,53.317135],"type":"Point"}
}