{
  "type": "Feature",
  "properties": {
    "iso:country":"DE",
    "sg:address":"Dorfstr. 12",
    "sg:city":"Lemgow",
    "sg:phone":"+49 5883/270",
    "sg:postcode":"29485",
    "sg:province":"Niedersachsen",
    "wof:name":"Josef Lange",
    "wof:placetype":"venue"
},
  "geometry": {"coordinates":[11.359944,52.919075],"type":"Point"}
}