{
  "type": "Feature",
  "properties": {
    "iso:country":"DE",
    "sg:address":"Freilandstr. 22",
    "sg:city":"Gr\u00f6benzell",
    "sg:phone":"+49 8142/60877",
    "sg:postcode":"82194",
    "sg:province":"Bayern",
    "wof:name":"Hsm Management",
    "wof:placetype":"venue"
},
  "geometry": {"coordinates":[11.368752,48.20071],"type":"Point"}
}