{
  "type": "Feature",
  "properties": {
    "iso:country":"DE",
    "sg:address":"Gartenstr. 51",
    "sg:city":"Bensheim",
    "sg:phone":"+49 6251/2212",
    "sg:postcode":"64625",
    "sg:province":"Hessen",
    "wof:name":"Paul Hammes",
    "wof:placetype":"venue"
},
  "geometry": {"coordinates":[8.6120061874,49.6824150085],"type":"Point"}
}