{
  "type": "Feature",
  "properties": {
    "iso:country":"DE",
    "sg:address":"Salzufler Str. 81",
    "sg:city":"Herford",
    "sg:phone":"+49 5221/981676",
    "sg:postcode":"32052",
    "sg:province":"Nordrhein-Westfalen",
    "wof:name":"Ralf Biermann",
    "wof:placetype":"venue"
},
  "geometry": {"coordinates":[8.6883420944,52.1091880798],"type":"Point"}
}