{
  "type": "Feature",
  "properties": {
    "iso:country":"DE",
    "sg:address":"Chaukenweg 12",
    "sg:city":"Wilhelmshaven",
    "sg:phone":"+49 4423/1235",
    "sg:postcode":"26388",
    "sg:province":"Niedersachsen",
    "wof:name":"Biss Gesellschaft F\u00fcr B\u00fcroinformationssysteme Mbh",
    "wof:placetype":"venue"
},
  "geometry": {"coordinates":[8.0503501892,53.592792511],"type":"Point"}
}