{
  "type": "Feature",
  "properties": {
    "iso:country":"DE",
    "sg:address":"Postfach 1264::",
    "sg:city":"Bremerv\u00f6rde",
    "sg:phone":"+49 4761/840",
    "sg:postcode":"27432",
    "sg:province":"Niedersachsen",
    "wof:name":"Sparkasse Rotenburg-bremerv\u00f6rde",
    "wof:placetype":"venue"
},
  "geometry": {"coordinates":[9.157817,53.48307],"type":"Point"}
}