{
  "type": "Feature",
  "properties": {
    "iso:country":"DE",
    "sg:address":"An der Reling 4",
    "sg:city":"Dornumersiel",
    "sg:phone":"+49 2431/71850",
    "sg:postcode":"26553",
    "sg:province":"Niedersachsen",
    "wof:name":"Ferienhaus Nordsee In Ostfriesland, Nordsee K\u00fcste",
    "wof:placetype":"venue"
},
  "geometry": {"coordinates":[7.473902,53.674889],"type":"Point"}
}