{
  "type": "Feature",
  "properties": {
    "iso:country":"DE",
    "sg:address":"Berghausener Str. 15",
    "sg:city":"Neubukow",
    "sg:phone":"+49 38294/12774",
    "sg:postcode":"18233",
    "sg:province":"Mecklenburg-Vorpommern",
    "wof:name":"K\u00fcchenhaus Giese Gmbh",
    "wof:placetype":"venue"
},
  "geometry": {"coordinates":[11.685754776,54.0384216309],"type":"Point"}
}