{
  "type": "Feature",
  "properties": {
    "iso:country":"DE",
    "sg:address":"Schimmelwiesenstr. 18",
    "sg:city":"Leinfelden-Echterdingen",
    "sg:phone":"+49 711/791089",
    "sg:postcode":"70771",
    "sg:province":"Baden-W\u00fcrttemberg",
    "wof:name":"N. Stein Masseur",
    "wof:placetype":"venue"
},
  "geometry": {"coordinates":[9.156497,48.688072],"type":"Point"}
}