{
  "type": "Feature",
  "properties": {
    "iso:country":"DE",
    "sg:address":"Geltinger Str. 1",
    "sg:city":"Wolfratshausen",
    "sg:phone":"+49 8171/76831",
    "sg:postcode":"82515",
    "sg:province":"Bayern",
    "wof:name":"Glash\u00fctte",
    "wof:placetype":"venue"
},
  "geometry": {"coordinates":[11.4221410751,47.9100570679],"type":"Point"}
}