{
  "type": "Feature",
  "properties": {
    "iso:country":"DE",
    "sg:address":"Konrad-Adenauer-Str. 11",
    "sg:city":"Herzebrock-Clarholz",
    "sg:phone":"+49 5245/3051",
    "sg:postcode":"33442",
    "sg:province":"Nordrhein-Westfalen",
    "wof:name":"R. Wittkowski",
    "wof:placetype":"venue"
},
  "geometry": {"coordinates":[8.241788,51.881538],"type":"Point"}
}