{
  "type": "Feature",
  "properties": {
    "iso:country":"DE",
    "sg:address":"Landwehrstr. 88",
    "sg:city":"Darmstadt",
    "sg:phone":"+49 6151/894307",
    "sg:postcode":"64293",
    "sg:province":"Hessen",
    "wof:name":"Wmd Kn\u00f6\u00df & Anthes Gmbh",
    "wof:placetype":"venue"
},
  "geometry": {"coordinates":[8.631251,49.879578],"type":"Point"}
}