{
  "type": "Feature",
  "properties": {
    "iso:country":"DE",
    "sg:address":"Memminger Str. 39",
    "sg:city":"Altenstadt",
    "sg:phone":"+49 8337/293",
    "sg:postcode":"89281",
    "sg:province":"Bayern",
    "wof:name":"Sparkasse Illertissen",
    "wof:placetype":"venue"
},
  "geometry": {"coordinates":[10.112863,48.162975],"type":"Point"}
}