{
  "type": "Feature",
  "properties": {
    "iso:country":"DE",
    "sg:address":"Hugo-Hesse-Str. 12",
    "sg:city":"Kulmbach",
    "sg:phone":"+49 9221/81513",
    "sg:postcode":"95326",
    "sg:province":"Bayern",
    "wof:name":"Richard Eisold",
    "wof:placetype":"venue"
},
  "geometry": {"coordinates":[11.462264061,50.1152076721],"type":"Point"}
}