{
  "type": "Feature",
  "properties": {
    "iso:country":"DE",
    "sg:address":"Obere Felbenstr. 10",
    "sg:city":"Aldingen",
    "sg:postcode":"78554",
    "sg:province":"Baden-W\u00fcrttemberg",
    "wof:name":"Josef Derichs Architekt",
    "wof:placetype":"venue"
},
  "geometry": {"coordinates":[8.695094,48.091885],"type":"Point"}
}