{
  "type": "Feature",
  "properties": {
    "iso:country":"DE",
    "sg:address":"Herderstr. 11",
    "sg:city":"Hilden",
    "sg:phone":"+49 2103/907970",
    "sg:postcode":"40721",
    "sg:province":"Nordrhein-Westfalen",
    "wof:name":"Ronkenstein Keramik",
    "wof:placetype":"venue"
},
  "geometry": {"coordinates":[6.9240088463,51.1742172241],"type":"Point"}
}