{
  "type": "Feature",
  "properties": {
    "iso:country":"DE",
    "sg:address":"Im Steinger\u00fcst 7",
    "sg:city":"Rastatt",
    "sg:postcode":"76437",
    "sg:province":"Baden-W\u00fcrttemberg",
    "wof:name":"Renschler-rudloff Grabmale Gmbh",
    "wof:placetype":"venue"
},
  "geometry": {"coordinates":[8.2236156464,48.8619766235],"type":"Point"}
}