{
  "type": "Feature",
  "properties": {
    "iso:country":"DE",
    "sg:address":"Regenstr. 1",
    "sg:city":"Walderbach",
    "sg:phone":"+49 9464/371",
    "sg:postcode":"93194",
    "sg:province":"Bayern",
    "wof:name":"Josef Schwarzfischer",
    "wof:placetype":"venue"
},
  "geometry": {"coordinates":[12.3851251602,49.1846122742],"type":"Point"}
}