{
  "type": "Feature",
  "properties": {
    "iso:country":"DE",
    "sg:address":"Tuchinger Str. 24",
    "sg:city":"Freising",
    "sg:phone":"+49 8161/21077",
    "sg:postcode":"85356",
    "sg:province":"Bayern",
    "wof:name":"Domo Tv Telekommunikations- Betriebsgesellschaft Mbh",
    "wof:placetype":"venue"
},
  "geometry": {"coordinates":[11.7709589005,48.4091873169],"type":"Point"}
}