{
  "type": "Feature",
  "properties": {
    "iso:country":"DE",
    "sg:address":"G\u00f6tzinger Str. 3",
    "sg:city":"Kirchansch\u00f6ring",
    "sg:phone":"+49 8685/229",
    "sg:postcode":"83417",
    "sg:province":"Bayern",
    "wof:name":"Birner Elektro Gmbh",
    "wof:placetype":"venue"
},
  "geometry": {"coordinates":[12.833776474,47.9536972046],"type":"Point"}
}