{
  "type": "Feature",
  "properties": {
    "iso:country":"DE",
    "sg:address":"Stettiner Str. 46",
    "sg:city":"Bielefeld",
    "sg:phone":"+49 521/201334",
    "sg:postcode":"33605",
    "sg:province":"Nordrhein-Westfalen",
    "wof:name":"Harald H\u00f6ner",
    "wof:placetype":"venue"
},
  "geometry": {"coordinates":[8.5944414139,52.0010147095],"type":"Point"}
}