{
  "type": "Feature",
  "properties": {
    "iso:country":"DE",
    "sg:address":"Lenaustr. 12",
    "sg:city":"Weimar",
    "sg:phone":"+49 3643/202828",
    "sg:postcode":"99425",
    "sg:province":"Th\u00fcringen",
    "wof:name":"H. Stolze",
    "wof:placetype":"venue"
},
  "geometry": {"coordinates":[11.3469333649,50.9710960388],"type":"Point"}
}