{
  "type": "Feature",
  "properties": {
    "iso:country":"DE",
    "sg:address":"Ringstr. 3",
    "sg:city":"Schauerberg",
    "sg:phone":"+49 6375/304",
    "sg:postcode":"66919",
    "sg:province":"Rheinland-Pfalz",
    "wof:name":"Hans P. Ke\u00dfler",
    "wof:placetype":"venue"
},
  "geometry": {"coordinates":[7.576132,49.31506],"type":"Point"}
}