{
  "type": "Feature",
  "properties": {
    "iso:country":"DE",
    "sg:address":"Neutorstr. 8",
    "sg:city":"Usingen",
    "sg:phone":"+49 6081/13051",
    "sg:postcode":"61250",
    "sg:province":"Hessen",
    "wof:name":"Billard Bistro",
    "wof:placetype":"venue"
},
  "geometry": {"coordinates":[8.5321464539,50.3358650208],"type":"Point"}
}