{
  "type": "Feature",
  "properties": {
    "iso:country":"DE",
    "sg:address":"Dunlopstr. 2 POSTFACH 2251",
    "sg:city":"Hanau",
    "sg:phone":"+49 4934/916590",
    "sg:postcode":"63412",
    "sg:province":"Hessen",
    "wof:name":"Polymer-technik Elbe Gmbh",
    "wof:placetype":"venue"
},
  "geometry": {"coordinates":[12.6318702698,51.878578186],"type":"Point"}
}