{
  "type": "Feature",
  "properties": {
    "iso:country":"DE",
    "sg:address":"Markenweg 10",
    "sg:city":"Olfen",
    "sg:postcode":"59399",
    "sg:province":"Nordrhein-Westfalen",
    "wof:name":"W & H Werbe Und Handel Gmbh",
    "wof:placetype":"venue"
},
  "geometry": {"coordinates":[7.3939938545,51.6986732483],"type":"Point"}
}