{
  "type": "Feature",
  "properties": {
    "iso:country":"DE",
    "sg:address":"Isolde-Kurz-Str. 32",
    "sg:city":"Stuttgart",
    "sg:phone":"+49 711/474282",
    "sg:postcode":"70619",
    "sg:province":"Baden-W\u00fcrttemberg",
    "wof:name":"M. Und S. Rabsteyn",
    "wof:placetype":"venue"
},
  "geometry": {"coordinates":[9.213117,48.737694],"type":"Point"}
}