{
  "type": "Feature",
  "properties": {
    "iso:country":"DE",
    "sg:address":"Wiesenstr. 24",
    "sg:city":"Wuppertal",
    "sg:phone":"+49 202/444381",
    "sg:postcode":"42105",
    "sg:province":"Nordrhein-Westfalen",
    "wof:name":"Horst Speicher",
    "wof:placetype":"venue"
},
  "geometry": {"coordinates":[7.1452379227,51.2649993896],"type":"Point"}
}