{
  "type": "Feature",
  "properties": {
    "iso:country":"DE",
    "sg:address":"Klosterweg 22",
    "sg:city":"Obernzell",
    "sg:phone":"+49 8591/91180",
    "sg:postcode":"94130",
    "sg:province":"Bayern",
    "wof:name":"Fritz Bischof",
    "wof:placetype":"venue"
},
  "geometry": {"coordinates":[13.6387071609,48.5570297241],"type":"Point"}
}