{
  "type": "Feature",
  "properties": {
    "iso:country":"DE",
    "sg:address":"H\u00fctter Str. 12",
    "sg:city":"Hattert",
    "sg:phone":"+49 2662/7263",
    "sg:postcode":"57644",
    "sg:province":"Rheinland-Pfalz",
    "wof:name":"Ev. Pfarramt Altstadt Ii",
    "wof:placetype":"venue"
},
  "geometry": {"coordinates":[7.7639389038,50.6605758667],"type":"Point"}
}