{
  "type": "Feature",
  "properties": {
    "iso:country":"DE",
    "sg:address":"Flughafendamm 49",
    "sg:city":"Bremen",
    "sg:postcode":"28199",
    "sg:province":"Bremen",
    "wof:name":"Lsg Sky Chefs Deutschland Gmbh",
    "wof:placetype":"venue"
},
  "geometry": {"coordinates":[8.7896,53.050571],"type":"Point"}
}