{
  "type": "Feature",
  "properties": {
    "iso:country":"DE",
    "sg:address":"Koschendorfer Str. 34",
    "sg:city":"Kolkwitz",
    "sg:postcode":"03099",
    "sg:province":"Brandenburg",
    "wof:name":"G\u00f6te Klimacomfort-haus Gmbh",
    "wof:placetype":"venue"
},
  "geometry": {"coordinates":[14.248871,51.737068],"type":"Point"}
}