{
  "type": "Feature",
  "properties": {
    "iso:country":"DE",
    "sg:address":"Hinterer Giersb\u00fchlweg 2",
    "sg:city":"Schluchsee",
    "sg:phone":"+49 7656/1693",
    "sg:postcode":"79859",
    "sg:province":"Baden-W\u00fcrttemberg",
    "wof:name":"Friedrich Staub",
    "wof:placetype":"venue"
},
  "geometry": {"coordinates":[8.184504,47.821644],"type":"Point"}
}