{
  "type": "Feature",
  "properties": {
    "iso:country":"DE",
    "sg:address":"Postfach 1258",
    "sg:city":"Edewecht",
    "sg:postcode":"26182",
    "sg:province":"Niedersachsen",
    "wof:name":"Pro Meat Connection Fleisch Wurst Und Schinken",
    "wof:placetype":"venue"
},
  "geometry": {"coordinates":[7.9784598351,53.1226501465],"type":"Point"}
}