{
  "type": "Feature",
  "properties": {
    "iso:country":"DE",
    "sg:address":"Hauptstr. 4",
    "sg:city":"Wetzlar",
    "sg:phone":"+49 6441/23761",
    "sg:postcode":"35579",
    "sg:province":"Hessen",
    "wof:name":"Kurt Schmidt",
    "wof:placetype":"venue"
},
  "geometry": {"coordinates":[8.458759,50.548698],"type":"Point"}
}