{
  "type": "Feature",
  "properties": {
    "iso:country":"DE",
    "sg:address":"Marktplatz 3 -7",
    "sg:city":"Halle",
    "sg:phone":"+49 345/292960",
    "sg:postcode":"06108",
    "sg:province":"Sachsen-Anhalt",
    "wof:name":"W\u00f6hrl Das Haus Der Markenkleidung Gmbh & Co. Kg",
    "wof:placetype":"venue"
},
  "geometry": {"coordinates":[11.969595,51.482048],"type":"Point"}
}