{
  "type": "Feature",
  "properties": {
    "iso:country":"DE",
    "sg:address":"Ulmer Str. 185",
    "sg:city":"Augsburg",
    "sg:phone":"+49 821/4444974",
    "sg:postcode":"86156",
    "sg:province":"Bayern",
    "wof:name":"Susi Informationsdienst",
    "wof:placetype":"venue"
},
  "geometry": {"coordinates":[10.8537559509,48.3797302246],"type":"Point"}
}