{
  "type": "Feature",
  "properties": {
    "iso:country":"DE",
    "sg:address":"Immenweg 2",
    "sg:city":"Binnen",
    "sg:phone":"+49 5023/517",
    "sg:postcode":"31619",
    "sg:province":"Niedersachsen",
    "wof:name":"Shv Systemhallen Vertriebs Gmbh",
    "wof:placetype":"venue"
},
  "geometry": {"coordinates":[9.133919,52.628384],"type":"Point"}
}