{
  "type": "Feature",
  "properties": {
    "iso:country":"DE",
    "sg:address":"Dorfstr. 24",
    "sg:city":"Niestetal",
    "sg:phone":"+49 561/522997",
    "sg:postcode":"34266",
    "sg:province":"Hessen",
    "wof:name":"Herbert Goldmann",
    "wof:placetype":"venue"
},
  "geometry": {"coordinates":[9.5781879425,51.3073806763],"type":"Point"}
}