{
  "type": "Feature",
  "properties": {
    "iso:country":"DE",
    "sg:address":"Eigenheimstr. 14",
    "sg:city":"R\u00f6thenbach",
    "sg:phone":"+49 911/577601",
    "sg:postcode":"90552",
    "sg:province":"Bayern",
    "wof:name":"W. Walter",
    "wof:placetype":"venue"
},
  "geometry": {"coordinates":[11.2439489365,49.4809265137],"type":"Point"}
}