{
  "type": "Feature",
  "properties": {
    "iso:country":"DE",
    "sg:address":"Brunnhaldeweg 2",
    "sg:city":"Geislingen",
    "sg:phone":"+49 7331/41079",
    "sg:postcode":"73312",
    "sg:province":"Baden-W\u00fcrttemberg",
    "wof:name":"Clau\u00df Maschinenbau Gmbh & Co.",
    "wof:placetype":"venue"
},
  "geometry": {"coordinates":[9.806611,48.588989],"type":"Point"}
}