{
  "type": "Feature",
  "properties": {
    "iso:country":"DE",
    "sg:address":"Hartmattenstr. 17",
    "sg:city":"L\u00f6rrach",
    "sg:phone":"+49 7621/3356",
    "sg:postcode":"79539",
    "sg:province":"Baden-W\u00fcrttemberg",
    "wof:name":"Theodor Schwander",
    "wof:placetype":"venue"
},
  "geometry": {"coordinates":[7.674472,47.620464],"type":"Point"}
}