{
  "type": "Feature",
  "properties": {
    "iso:country":"DE",
    "sg:address":"Eschstr. 42-44",
    "sg:city":"Cloppenburg",
    "sg:phone":"+49 4471/4411",
    "sg:postcode":"49661",
    "sg:province":"Niedersachsen",
    "wof:name":"Ralf G\u00f6hre E. K.",
    "wof:placetype":"venue"
},
  "geometry": {"coordinates":[8.0381669998,52.8433074951],"type":"Point"}
}