{
  "type": "Feature",
  "properties": {
    "iso:country":"DE",
    "sg:address":"Kaltenbrunn 1",
    "sg:city":"Garmisch-Partenkirchen",
    "sg:phone":"+49 8821/52588",
    "sg:postcode":"82467",
    "sg:province":"Bayern",
    "wof:name":"Anton Frischmann",
    "wof:placetype":"venue"
},
  "geometry": {"coordinates":[11.1753454208,47.4890365601],"type":"Point"}
}