{
  "type": "Feature",
  "properties": {
    "iso:country":"DE",
    "sg:address":"Herzog-Georg-Str. 9",
    "sg:city":"Altom\u00fcnster",
    "sg:phone":"+49 8254/8511",
    "sg:postcode":"85250",
    "sg:province":"Bayern",
    "wof:name":"Markus-apotheke Apothekerin B. Lauer E. K.",
    "wof:placetype":"venue"
},
  "geometry": {"coordinates":[11.255325,48.388447],"type":"Point"}
}