{
  "type": "Feature",
  "properties": {
    "iso:country":"DE",
    "sg:address":"Hussitenstr. 54",
    "sg:city":"Berlin",
    "sg:phone":"+49 30/4633801",
    "sg:postcode":"13355",
    "sg:province":"Berlin",
    "wof:name":"Manfred Feiertag",
    "wof:placetype":"venue"
},
  "geometry": {"coordinates":[13.3863391876,52.5385093689],"type":"Point"}
}