{
  "type": "Feature",
  "properties": {
    "iso:country":"DE",
    "sg:address":"Ihlestr. 7",
    "sg:city":"N\u00fcrnberg",
    "sg:phone":"+49 911/512282",
    "sg:postcode":"90427",
    "sg:province":"Bayern",
    "wof:name":"Kp Neuendorf Handelsvertretungen Gmbh",
    "wof:placetype":"venue"
},
  "geometry": {"coordinates":[11.0571432114,49.5090408325],"type":"Point"}
}