{
  "type": "Feature",
  "properties": {
    "iso:country":"DE",
    "sg:address":"Schlo\u00dfstr. 2",
    "sg:city":"Hannover",
    "sg:phone":"+49 511/326070",
    "sg:postcode":"30159",
    "sg:province":"Niedersachsen",
    "wof:name":"Pawlowski",
    "wof:placetype":"venue"
},
  "geometry": {"coordinates":[9.732357,52.371307],"type":"Point"}
}