{
  "type": "Feature",
  "properties": {
    "iso:country":"DE",
    "sg:address":"Kaiser-Friedrich-Promenade 15",
    "sg:city":"Bad Homburg",
    "sg:phone":"+49 6172/21105",
    "sg:postcode":"61348",
    "sg:province":"Hessen",
    "wof:name":"Klaus Henius Heilpraktiker",
    "wof:placetype":"venue"
},
  "geometry": {"coordinates":[8.6150808334,50.2298583984],"type":"Point"}
}