{
  "type": "Feature",
  "properties": {
    "iso:country":"DE",
    "sg:address":"Bei der Grodener Kirche 4",
    "sg:city":"Cuxhaven",
    "sg:postcode":"27472",
    "sg:province":"Niedersachsen",
    "wof:name":"Ev.-luth. Kirchengemeinde Cuxhaven-groden",
    "wof:placetype":"venue"
},
  "geometry": {"coordinates":[8.7297115326,53.8500099182],"type":"Point"}
}