{
  "type": "Feature",
  "properties": {
    "iso:country":"DE",
    "sg:city":"Ebringen",
    "sg:postcode":"79285",
    "sg:province":"Baden-W\u00fcrttemberg",
    "wof:name":"Signature - Agentur F\u00fcr Imageprofile",
    "wof:placetype":"venue"
},
  "geometry": {"coordinates":[7.779815,47.957615],"type":"Point"}
}