{
  "type": "Feature",
  "properties": {
    "iso:country":"DE",
    "sg:address":"Saarhausen 12",
    "sg:city":"Taben-Rodt",
    "sg:phone":"+49 6582/91460",
    "sg:postcode":"54441",
    "sg:province":"Rheinland-Pfalz",
    "wof:name":"Johann D\u00fcro Gmbh & Co. Kg",
    "wof:placetype":"venue"
},
  "geometry": {"coordinates":[6.5985279083,49.5422210693],"type":"Point"}
}