{
  "type": "Feature",
  "properties": {
    "iso:country":"DE",
    "sg:address":"Emmerichstr. 68",
    "sg:city":"G\u00f6rlitz",
    "sg:phone":"+49 3581/406554",
    "sg:postcode":"02826",
    "sg:province":"Sachsen",
    "wof:name":"B. Hawelky",
    "wof:placetype":"venue"
},
  "geometry": {"coordinates":[14.992593,51.14682],"type":"Point"}
}