{
  "type": "Feature",
  "properties": {
    "iso:country":"DE",
    "sg:address":"Fuhlendorfer Weg 33",
    "sg:city":"Wiemersdorf",
    "sg:phone":"+49 4192/897060",
    "sg:postcode":"24649",
    "sg:province":"Schleswig-Holstein",
    "wof:name":"Stefan H\u00fcttenberger",
    "wof:placetype":"venue"
},
  "geometry": {"coordinates":[9.89592,53.947472],"type":"Point"}
}