{
  "type": "Feature",
  "properties": {
    "iso:country":"DE",
    "sg:address":"K\u00f6niginstr. 28",
    "sg:city":"M\u00fcnchen",
    "sg:postcode":"80802",
    "sg:province":"Bayern",
    "wof:name":"Stella Automobil- Beteiligungs-gmbh",
    "wof:placetype":"venue"
},
  "geometry": {"coordinates":[11.588061,48.153629],"type":"Point"}
}