{
  "type": "Feature",
  "properties": {
    "iso:country":"DE",
    "sg:address":"Benediktusgarten 5",
    "sg:city":"Bingen",
    "sg:phone":"+49 6721/36394",
    "sg:postcode":"55411",
    "sg:province":"Rheinland-Pfalz",
    "wof:name":"S. Ehrhardt",
    "wof:placetype":"venue"
},
  "geometry": {"coordinates":[7.889166,49.965126],"type":"Point"}
}