{
  "type": "Feature",
  "properties": {
    "iso:country":"DE",
    "sg:address":"Berliner Str 4",
    "sg:city":"Glinde",
    "sg:phone":"+49 40/7103082",
    "sg:postcode":"21509",
    "sg:province":"Schleswig-Holstein",
    "wof:name":"Optima Pressformen Gmbh & Co Kg",
    "wof:placetype":"venue"
},
  "geometry": {"coordinates":[10.233196,53.54594],"type":"Point"}
}