{
  "type": "Feature",
  "properties": {
    "iso:country":"DE",
    "sg:address":"Schulgasse 8-10",
    "sg:city":"Schw\u00e4bisch Hall",
    "sg:phone":"+49 791/855400",
    "sg:postcode":"74523",
    "sg:province":"Baden-W\u00fcrttemberg",
    "wof:name":"Spiel Und Freizeit Gmbh",
    "wof:placetype":"venue"
},
  "geometry": {"coordinates":[9.7352714539,49.1126823425],"type":"Point"}
}