{
  "type": "Feature",
  "properties": {
    "iso:country":"DE",
    "sg:address":"Kantstr. 15",
    "sg:city":"N\u00fcrtingen",
    "sg:postcode":"72622",
    "sg:province":"Baden-W\u00fcrttemberg",
    "wof:name":"Wolfgang Etter Gmbh",
    "wof:placetype":"venue"
},
  "geometry": {"coordinates":[9.35394,48.618664],"type":"Point"}
}