{
  "type": "Feature",
  "properties": {
    "iso:country":"DE",
    "sg:address":"Aidenbacher Str. 1",
    "sg:city":"Vilshofen",
    "sg:phone":"+49 8541/5035",
    "sg:postcode":"94474",
    "sg:province":"Bayern",
    "wof:name":"Bayerische Vereinsbank Ag",
    "wof:placetype":"venue"
},
  "geometry": {"coordinates":[13.194676,48.593548],"type":"Point"}
}