{
  "type": "Feature",
  "properties": {
    "iso:country":"DE",
    "sg:address":"Albert-Einstein-Ring 1",
    "sg:city":"Kleinmachnow",
    "sg:phone":"+49 33203/50100",
    "sg:postcode":"14532",
    "sg:province":"Brandenburg",
    "wof:name":"Europarc Service Gmbh",
    "wof:placetype":"venue"
},
  "geometry": {"coordinates":[13.1857175827,52.4065513611],"type":"Point"}
}