{
  "type": "Feature",
  "properties": {
    "iso:country":"DE",
    "sg:address":"Dornholzh\u00e4user Str. 12",
    "sg:city":"Oberursel",
    "sg:phone":"+49 6172/36285",
    "sg:postcode":"61440",
    "sg:province":"Hessen",
    "wof:name":"Hans-georg Nalazek Rechtsanwalt",
    "wof:placetype":"venue"
},
  "geometry": {"coordinates":[8.5801286697,50.228515625],"type":"Point"}
}