{
  "type": "Feature",
  "properties": {
    "iso:country":"DE",
    "sg:address":"Alte Chaussee 33",
    "sg:city":"Hadamar",
    "sg:phone":"+49 6433/3001",
    "sg:postcode":"65589",
    "sg:province":"Hessen",
    "wof:name":"Raphael Grohganz Steuerbevollm\u00e4chtigter",
    "wof:placetype":"venue"
},
  "geometry": {"coordinates":[8.0414743423,50.444934845],"type":"Point"}
}