{
  "type": "Feature",
  "properties": {
    "iso:country":"DE",
    "sg:address":"Kleiststr. 12",
    "sg:city":"Fuldatal",
    "sg:phone":"+49 5607/1025",
    "sg:postcode":"34233",
    "sg:province":"Hessen",
    "wof:name":"Knut Warmuth Architekt",
    "wof:placetype":"venue"
},
  "geometry": {"coordinates":[9.525155,51.389118],"type":"Point"}
}