{
  "type": "Feature",
  "properties": {
    "iso:country":"DE",
    "sg:address":"Halmer Weg 5",
    "sg:city":"Kirn",
    "sg:phone":"+49 6752/93980",
    "sg:postcode":"55606",
    "sg:province":"Rheinland-Pfalz",
    "wof:name":"Sch\u00e4fer Textil-service Gmbh",
    "wof:placetype":"venue"
},
  "geometry": {"coordinates":[7.462927,49.786545],"type":"Point"}
}