{
  "type": "Feature",
  "properties": {
    "iso:country":"DE",
    "sg:address":"Pfarrer-Kenntemich-Platz 16",
    "sg:city":"Troisdorf",
    "sg:phone":"+49 2241/809021",
    "sg:postcode":"53840",
    "sg:province":"Nordrhein-Westfalen",
    "wof:name":"Iris Bayer",
    "wof:placetype":"venue"
},
  "geometry": {"coordinates":[7.1598601341,50.8134422302],"type":"Point"}
}