{
  "type": "Feature",
  "properties": {
    "iso:country":"DE",
    "sg:address":"Von-Harff-Str. 62",
    "sg:city":"Krefeld",
    "sg:phone":"+49 2151/735143",
    "sg:postcode":"47839",
    "sg:province":"Nordrhein-Westfalen",
    "wof:name":"Arno Piper",
    "wof:placetype":"venue"
},
  "geometry": {"coordinates":[6.520494,51.369576],"type":"Point"}
}