{
  "type": "Feature",
  "properties": {
    "iso:country":"DE",
    "sg:address":"Stuttgarter Str. 35",
    "sg:city":"Bad Liebenzell",
    "sg:phone":"+49 7052/1288",
    "sg:postcode":"75378",
    "sg:province":"Baden-W\u00fcrttemberg",
    "wof:name":"Schwanen",
    "wof:placetype":"venue"
},
  "geometry": {"coordinates":[8.7569169998,48.7675704956],"type":"Point"}
}