{
  "type": "Feature",
  "properties": {
    "iso:country":"DE",
    "sg:address":"Stockacher Str. 9",
    "sg:city":"M\u00fcnchen",
    "sg:phone":"+49 89/82915301",
    "sg:postcode":"81243",
    "sg:province":"Bayern",
    "wof:name":"Intertape Gmbh Klebebandvertrieb",
    "wof:placetype":"venue"
},
  "geometry": {"coordinates":[11.442093,48.149513],"type":"Point"}
}