{
  "type": "Feature",
  "properties": {
    "iso:country":"DE",
    "sg:address":"Im Neudeck 2",
    "sg:city":"Speyer",
    "sg:phone":"+49 6232/34944",
    "sg:postcode":"67346",
    "sg:province":"Rheinland-Pfalz",
    "wof:name":"Peter Demmerle Grabdenkm\u00e4ler",
    "wof:placetype":"venue"
},
  "geometry": {"coordinates":[8.4310646057,49.3353691101],"type":"Point"}
}