{
  "type": "Feature",
  "properties": {
    "iso:country":"DE",
    "sg:address":"Lise-Meitner-Str. 7",
    "sg:city":"Maisach",
    "sg:postcode":"82216",
    "sg:province":"Bayern",
    "wof:name":"S\u00fcddeutsche Societ\u00e4ts- Druckerei Gmbh",
    "wof:placetype":"venue"
},
  "geometry": {"coordinates":[11.28908,48.215096],"type":"Point"}
}