{
  "type": "Feature",
  "properties": {
    "iso:country":"DE",
    "sg:address":"Hindenburgstr. 26",
    "sg:city":"Itzehoe",
    "sg:postcode":"25524",
    "sg:province":"Schleswig-Holstein",
    "wof:name":"Kath.\u00d6ffentliche Bibliothek St. Angar",
    "wof:placetype":"venue"
},
  "geometry": {"coordinates":[9.524239,53.923492],"type":"Point"}
}