{
  "type": "Feature",
  "properties": {
    "iso:country":"DE",
    "sg:address":"Im Esch 16",
    "sg:city":"Enger",
    "sg:phone":"+49 5224/978571",
    "sg:postcode":"32130",
    "sg:province":"Nordrhein-Westfalen",
    "wof:name":"Hermann G\u00f6hner Gmbh & Co. Vermietungs Kg",
    "wof:placetype":"venue"
},
  "geometry": {"coordinates":[8.519326,52.135143],"type":"Point"}
}