{
  "type": "Feature",
  "properties": {
    "iso:country":"DE",
    "sg:address":"Kaplanei 10",
    "sg:city":"Quedlinburg",
    "sg:postcode":"06484",
    "sg:province":"Sachsen-Anhalt",
    "wof:name":"Evangelisches Pfarramt I St. Nikolai",
    "wof:placetype":"venue"
},
  "geometry": {"coordinates":[11.1491718292,51.7889442444],"type":"Point"}
}