{
  "type": "Feature",
  "properties": {
    "iso:country":"DE",
    "sg:address":"Fritschestr. 26",
    "sg:city":"Berlin",
    "sg:phone":"+49 30/3416001",
    "sg:postcode":"10585",
    "sg:province":"Berlin",
    "wof:name":"Happatz Und Raschka Architekten",
    "wof:placetype":"venue"
},
  "geometry": {"coordinates":[13.2994413376,52.5124206543],"type":"Point"}
}