{
  "type": "Feature",
  "properties": {
    "iso:country":"DE",
    "sg:address":"Neustadt 30",
    "sg:city":"Eisenach",
    "sg:phone":"+49 3691/742744",
    "sg:postcode":"99817",
    "sg:province":"Th\u00fcringen",
    "wof:name":"Pension Haus Mahret",
    "wof:placetype":"venue"
},
  "geometry": {"coordinates":[10.3125734329,50.9755706787],"type":"Point"}
}