{
  "type": "Feature",
  "properties": {
    "iso:country":"DE",
    "sg:address":"Schillerstr. 58",
    "sg:city":"Stein",
    "sg:phone":"+49 911/685522",
    "sg:postcode":"90547",
    "sg:province":"Bayern",
    "wof:name":"Willi Pisarski Rechtsanwalt",
    "wof:placetype":"venue"
},
  "geometry": {"coordinates":[11.0160045624,49.4003868103],"type":"Point"}
}