{
  "type": "Feature",
  "properties": {
    "iso:country":"DE",
    "sg:address":"Kreuzgasse 17",
    "sg:city":"B\u00fcrgel",
    "sg:phone":"+49 36692/22498",
    "sg:postcode":"07616",
    "sg:province":"Th\u00fcringen",
    "wof:name":"Oskar Fr\u00f6mel Architekt",
    "wof:placetype":"venue"
},
  "geometry": {"coordinates":[11.755899,50.940739],"type":"Point"}
}