{
  "type": "Feature",
  "properties": {
    "iso:country":"DE",
    "sg:address":"Am Markt 17",
    "sg:city":"Templin",
    "sg:phone":"+49 3987/2528",
    "sg:postcode":"17268",
    "sg:province":"Brandenburg",
    "wof:name":"Buddelei-mode",
    "wof:placetype":"venue"
},
  "geometry": {"coordinates":[13.49969,53.119354],"type":"Point"}
}