{
  "type": "Feature",
  "properties": {
    "iso:country":"DE",
    "sg:address":"R\u00f6merstr. 40",
    "sg:city":"Treis-Karden",
    "sg:phone":"+49 2672/7104",
    "sg:postcode":"56253",
    "sg:province":"Rheinland-Pfalz",
    "wof:name":"Dieter Rumpenhorst Innenarchitekt",
    "wof:placetype":"venue"
},
  "geometry": {"coordinates":[7.296799,50.177513],"type":"Point"}
}