{
  "type": "Feature",
  "properties": {
    "iso:country":"DE",
    "sg:address":"Lindenstr. 66",
    "sg:city":"Neuwied",
    "sg:phone":"+49 2622/80372",
    "sg:postcode":"56566",
    "sg:province":"Rheinland-Pfalz",
    "wof:name":"Mechthild Schumacher",
    "wof:placetype":"venue"
},
  "geometry": {"coordinates":[7.538881,50.448837],"type":"Point"}
}