{
  "type": "Feature",
  "properties": {
    "iso:country":"DE",
    "sg:address":"Untere Brettachtalstr. 27",
    "sg:city":"Bretzfeld",
    "sg:phone":"+49 7945/91210",
    "sg:postcode":"74626",
    "sg:province":"Baden-W\u00fcrttemberg",
    "wof:name":"U. W\u00f6hrl Produktion Gmbh",
    "wof:placetype":"venue"
},
  "geometry": {"coordinates":[9.5025062561,49.1413269043],"type":"Point"}
}