{
  "type": "Feature",
  "properties": {
    "iso:country":"DE",
    "sg:address":"27432",
    "sg:city":"Bremerv\u00f6rde",
    "sg:phone":"+49 4761/3969",
    "sg:postcode":"27432",
    "sg:province":"Niedersachsen",
    "wof:name":"Bahnhofsgastst\u00e4tte",
    "wof:placetype":"venue"
},
  "geometry": {"coordinates":[9.0889797211,53.500629425],"type":"Point"}
}