{
  "type": "Feature",
  "properties": {
    "iso:country":"DE",
    "sg:address":"Lilienweg 24",
    "sg:city":"Stolberg",
    "sg:phone":"+49 2402/82827",
    "sg:postcode":"52222",
    "sg:province":"Nordrhein-Westfalen",
    "wof:name":"J\u00fcrgen Sch\u00fcmmer",
    "wof:placetype":"venue"
},
  "geometry": {"coordinates":[6.2471780777,50.7844276428],"type":"Point"}
}