{
  "type": "Feature",
  "properties": {
    "iso:country":"DE",
    "sg:address":"Karl-Marx-Str. 24",
    "sg:city":"Putlitz",
    "sg:phone":"+49 33981/80242",
    "sg:postcode":"16949",
    "sg:province":"Brandenburg",
    "wof:name":"Albert Eisermann",
    "wof:placetype":"venue"
},
  "geometry": {"coordinates":[12.044678,53.24696],"type":"Point"}
}