{
  "type": "Feature",
  "properties": {
    "iso:country":"DE",
    "sg:address":"K\u00f6lner Str. 99",
    "sg:city":"Solingen",
    "sg:phone":"+49 212/205970",
    "sg:postcode":"42651",
    "sg:province":"Nordrhein-Westfalen",
    "wof:name":"K\u00f6nig Ludwig Salon",
    "wof:placetype":"venue"
},
  "geometry": {"coordinates":[7.0827269554,51.1714668274],"type":"Point"}
}