{
  "type": "Feature",
  "properties": {
    "iso:country":"DE",
    "sg:address":"Dietmannsried",
    "sg:city":"Dietmannsried",
    "sg:phone":"+49 8374/8074",
    "sg:postcode":"87463",
    "sg:province":"Bayern",
    "wof:name":"Raiffeisenbank Dietmannsried Eg",
    "wof:placetype":"venue"
},
  "geometry": {"coordinates":[10.26948,47.826851],"type":"Point"}
}