{
  "type": "Feature",
  "properties": {
    "iso:country":"DE",
    "sg:address":"Sterkrader Str. 75",
    "sg:city":"Bottrop",
    "sg:phone":"+49 2041/183080",
    "sg:postcode":"46236",
    "sg:province":"Nordrhein-Westfalen",
    "wof:name":"New Pr\u00e4sent Gmbh",
    "wof:placetype":"venue"
},
  "geometry": {"coordinates":[6.9126300812,51.5199890137],"type":"Point"}
}