{
  "type": "Feature",
  "properties": {
    "iso:country":"DE",
    "sg:address":"Nelkenstr. 18",
    "sg:city":"Breuberg",
    "sg:phone":"+49 6163/82246",
    "sg:postcode":"64747",
    "sg:province":"Hessen",
    "wof:name":"Heusel-wohnbau Gmbh",
    "wof:placetype":"venue"
},
  "geometry": {"coordinates":[9.01792,49.82151],"type":"Point"}
}