{
  "type": "Feature",
  "properties": {
    "iso:country":"DE",
    "sg:address":"Schafhofstr. 3",
    "sg:city":"W\u00fcrzburg",
    "sg:phone":"+49 931/94795",
    "sg:postcode":"97080",
    "sg:province":"Bayern",
    "wof:name":"Reinhard R\u00fcgemer",
    "wof:placetype":"venue"
},
  "geometry": {"coordinates":[9.9226951599,49.8262710571],"type":"Point"}
}