{
  "type": "Feature",
  "properties": {
    "iso:country":"DE",
    "sg:address":"Rheinische Str. 36",
    "sg:city":"Haan",
    "sg:phone":"+49 212/993420",
    "sg:postcode":"42781",
    "sg:province":"Nordrhein-Westfalen",
    "wof:name":"Verder Lab-tec Beteiligungsgesellschaft Mbh",
    "wof:placetype":"venue"
},
  "geometry": {"coordinates":[7.038097,51.2047],"type":"Point"}
}