{
  "type": "Feature",
  "properties": {
    "iso:country":"DE",
    "sg:address":"Brunneng\u00e4\u00dfchen 1",
    "sg:city":"Blieskastel",
    "sg:phone":"+49 6842/1221",
    "sg:postcode":"66440",
    "sg:province":"Saarland",
    "wof:name":"Im Hinnereck",
    "wof:placetype":"venue"
},
  "geometry": {"coordinates":[7.2582249641,49.238243103],"type":"Point"}
}