{
  "type": "Feature",
  "properties": {
    "iso:country":"DE",
    "sg:address":"Schwarzwaldstr. 12",
    "sg:city":"Oberwolfach",
    "sg:phone":"+49 7834/584",
    "sg:postcode":"77709",
    "sg:province":"Baden-W\u00fcrttemberg",
    "wof:name":"Manfred Holzer",
    "wof:placetype":"venue"
},
  "geometry": {"coordinates":[8.2250175476,48.3435745239],"type":"Point"}
}