{
  "type": "Feature",
  "properties": {
    "iso:country":"DE",
    "sg:address":"Memelstr. 49",
    "sg:city":"Essen",
    "sg:phone":"+49 201/460048",
    "sg:postcode":"45259",
    "sg:province":"Nordrhein-Westfalen",
    "wof:name":"Awater Gmbh",
    "wof:placetype":"venue"
},
  "geometry": {"coordinates":[7.0693688393,51.4086647034],"type":"Point"}
}