{
  "type": "Feature",
  "properties": {
    "iso:country":"DE",
    "sg:address":"Dorfstr. 15",
    "sg:city":"Steinh\u00f6ring",
    "sg:phone":"+49 8094/8003",
    "sg:postcode":"85643",
    "sg:province":"Bayern",
    "wof:name":"Ficht Engineering Gmbh",
    "wof:placetype":"venue"
},
  "geometry": {"coordinates":[12.0582742691,48.0823898315],"type":"Point"}
}