{
  "type": "Feature",
  "properties": {
    "iso:country":"DE",
    "sg:address":"Hauptstr. 7",
    "sg:city":"Breidenbach",
    "sg:phone":"+49 6465/4303",
    "sg:postcode":"35236",
    "sg:province":"Hessen",
    "wof:name":"Willi Eberbach Kg",
    "wof:placetype":"venue"
},
  "geometry": {"coordinates":[8.454867,50.883099],"type":"Point"}
}