{
  "type": "Feature",
  "properties": {
    "iso:country":"DE",
    "sg:address":"Goethestr. 5",
    "sg:city":"Schuttertal",
    "sg:phone":"+49 7826/364",
    "sg:postcode":"77978",
    "sg:province":"Baden-W\u00fcrttemberg",
    "wof:name":"Adolf Frey",
    "wof:placetype":"venue"
},
  "geometry": {"coordinates":[7.9671487808,48.2211151123],"type":"Point"}
}