{
  "type": "Feature",
  "properties": {
    "iso:country":"DE",
    "sg:address":"Funkenstr. 4",
    "sg:city":"Bad M\u00fcnstereifel",
    "sg:postcode":"53902",
    "sg:province":"Nordrhein-Westfalen",
    "wof:name":"Responsum It Gmbh",
    "wof:placetype":"venue"
},
  "geometry": {"coordinates":[6.8568358421,50.4660682678],"type":"Point"}
}