{
  "type": "Feature",
  "properties": {
    "iso:country":"DE",
    "sg:address":"Bandelstr. 1",
    "sg:city":"Berlin",
    "sg:phone":"+49 30/3945626",
    "sg:postcode":"10559",
    "sg:province":"Berlin",
    "wof:name":"Asum Arbeitsgruppe F\u00fcr Sozialplanung Und Mieter-",
    "wof:placetype":"venue"
},
  "geometry": {"coordinates":[13.350101,52.527954],"type":"Point"}
}