{
  "type": "Feature",
  "properties": {
    "iso:country":"DE",
    "sg:address":"Max-Planck-Str. 6",
    "sg:city":"Dreieich",
    "sg:postcode":"63303",
    "sg:province":"Hessen",
    "wof:name":"Insuranceclick Ag",
    "wof:placetype":"venue"
},
  "geometry": {"coordinates":[8.7049798965,50.0273094177],"type":"Point"}
}