{
  "type": "Feature",
  "properties": {
    "iso:country":"DE",
    "sg:address":"Dachsgang 11",
    "sg:city":"Rinteln",
    "sg:phone":"+49 5751/41501",
    "sg:postcode":"31737",
    "sg:province":"Niedersachsen",
    "wof:name":"Fahrenkamp Und Reese Gbr",
    "wof:placetype":"venue"
},
  "geometry": {"coordinates":[9.079789,52.150131],"type":"Point"}
}