{
  "type": "Feature",
  "properties": {
    "iso:country":"DE",
    "sg:address":"Landstr. 35a",
    "sg:city":"Bad Endbach",
    "sg:postcode":"35080",
    "sg:province":"Hessen",
    "wof:name":"Orthop\u00e4die-schuhtechnik M\u00fcller Inh. J\u00fcrgen Uhlig E. K.",
    "wof:placetype":"venue"
},
  "geometry": {"coordinates":[8.493768692,50.7532272339],"type":"Point"}
}