{
  "type": "Feature",
  "properties": {
    "iso:country":"DE",
    "sg:address":"Drift 2b",
    "sg:city":"Barsb\u00fcttel",
    "sg:phone":"+49 40/7105864",
    "sg:postcode":"22885",
    "sg:province":"Schleswig-Holstein",
    "wof:name":"Bernd Faulhammer Gmbh",
    "wof:placetype":"venue"
},
  "geometry": {"coordinates":[10.199508,53.560364],"type":"Point"}
}