{
  "type": "Feature",
  "properties": {
    "iso:country":"DE",
    "sg:address":"Am Gipsbruch 1",
    "sg:city":"Garmisch-Partenkirchen",
    "sg:phone":"+49 8821/1323",
    "sg:postcode":"82467",
    "sg:province":"Bayern",
    "wof:name":"Marion Brandl",
    "wof:placetype":"venue"
},
  "geometry": {"coordinates":[11.1155395508,47.4956016541],"type":"Point"}
}