{
  "type": "Feature",
  "properties": {
    "iso:country":"DE",
    "sg:address":"Am Deich 14",
    "sg:city":"Bekm\u00fcnde",
    "sg:phone":"+49 4821/75108",
    "sg:postcode":"25524",
    "sg:province":"Schleswig-Holstein",
    "wof:name":"Baugesch\u00e4ft G. Borchardt Gmbh",
    "wof:placetype":"venue"
},
  "geometry": {"coordinates":[9.46222,53.927231],"type":"Point"}
}