{
  "type": "Feature",
  "properties": {
    "iso:country":"DE",
    "sg:address":"Hauptstr. 33",
    "sg:city":"Oberreute",
    "sg:phone":"+49 8387/3119",
    "sg:postcode":"88179",
    "sg:province":"Bayern",
    "wof:name":"Freibad",
    "wof:placetype":"venue"
},
  "geometry": {"coordinates":[9.9428606033,47.5626296997],"type":"Point"}
}