{
  "type": "Feature",
  "properties": {
    "iso:country":"DE",
    "sg:address":"Entenweiherstr.",
    "sg:city":"Homburg",
    "sg:phone":"+49 6841/101533",
    "sg:postcode":"66424",
    "sg:province":"Saarland",
    "wof:name":"Hallenbad",
    "wof:placetype":"venue"
},
  "geometry": {"coordinates":[7.3354158401,49.3178405762],"type":"Point"}
}