{
  "type": "Feature",
  "properties": {
    "iso:country":"DE",
    "sg:address":"Vogelsbergstr. 47",
    "sg:city":"Altenstadt",
    "sg:phone":"+49 6047/951436",
    "sg:postcode":"63674",
    "sg:province":"Hessen",
    "wof:name":"Eiscaf\u00e9 Dolomiti",
    "wof:placetype":"venue"
},
  "geometry": {"coordinates":[8.946586,50.285946],"type":"Point"}
}