{
  "type": "Feature",
  "properties": {
    "iso:country":"DE",
    "sg:address":"Wertachbrucker-Tor-Str. 6",
    "sg:city":"Augsburg",
    "sg:phone":"+49 821/39172",
    "sg:postcode":"86152",
    "sg:province":"Bayern",
    "wof:name":"Fritz Weber",
    "wof:placetype":"venue"
},
  "geometry": {"coordinates":[10.889434,48.37616],"type":"Point"}
}