{
  "type": "Feature",
  "properties": {
    "iso:country":"DE",
    "sg:address":"Regensburger Str. 54",
    "sg:city":"Schwandorf",
    "sg:phone":"+49 9431/74760",
    "sg:postcode":"92421",
    "sg:province":"Bayern",
    "wof:name":"Johann Huber Und Dr. Bernd Karlsbach",
    "wof:placetype":"venue"
},
  "geometry": {"coordinates":[12.1028490067,49.3173522949],"type":"Point"}
}