{
  "type": "Feature",
  "properties": {
    "iso:country":"DE",
    "sg:address":"Heilmanns Kamp 4",
    "sg:city":"Havixbeck",
    "sg:phone":"+49 2507/1695",
    "sg:postcode":"48329",
    "sg:province":"Nordrhein-Westfalen",
    "wof:name":"M. Branse Steuerberater",
    "wof:placetype":"venue"
},
  "geometry": {"coordinates":[7.4101290703,51.9797935486],"type":"Point"}
}