{
  "type": "Feature",
  "properties": {
    "iso:country":"DE",
    "sg:address":"Wandlhamerstr. 20",
    "sg:city":"Gr\u00e4felfing",
    "sg:phone":"+49 89/838382",
    "sg:postcode":"82166",
    "sg:province":"Bayern",
    "wof:name":"Alfred Dransfield",
    "wof:placetype":"venue"
},
  "geometry": {"coordinates":[11.438964,48.12167],"type":"Point"}
}