{
  "type": "Feature",
  "properties": {
    "iso:country":"DE",
    "sg:address":"Postfach 1",
    "sg:city":"Neumagen-Dhron",
    "sg:phone":"+49 6507/2230",
    "sg:postcode":"54347",
    "sg:province":"Rheinland-Pfalz",
    "wof:name":"Carl Schloeder Weinanbau",
    "wof:placetype":"venue"
},
  "geometry": {"coordinates":[6.8939981461,49.8494720459],"type":"Point"}
}