{
  "type": "Feature",
  "properties": {
    "iso:country":"DE",
    "sg:address":"Am Rosengarten 27",
    "sg:city":"Wolfhagen",
    "sg:phone":"+49 5692/8647",
    "sg:postcode":"34466",
    "sg:province":"Hessen",
    "wof:name":"Beate Schorsch",
    "wof:placetype":"venue"
},
  "geometry": {"coordinates":[9.1806173325,51.3211402893],"type":"Point"}
}