{
  "type": "Feature",
  "properties": {
    "iso:country":"DE",
    "sg:address":"Mittelstr. 8",
    "sg:city":"Eggersdorf",
    "sg:postcode":"15345",
    "sg:province":"Brandenburg",
    "wof:name":"Eggersdorfer Verwaltungs- Und Vertriebsgesellschaft Mbh",
    "wof:placetype":"venue"
},
  "geometry": {"coordinates":[13.826606,52.542717],"type":"Point"}
}