{
  "type": "Feature",
  "properties": {
    "iso:country":"DE",
    "sg:address":"Sinninger Str. 46",
    "sg:city":"Emsdetten",
    "sg:postcode":"48282",
    "sg:province":"Nordrhein-Westfalen",
    "wof:name":"Studio 3001 Gmbh",
    "wof:placetype":"venue"
},
  "geometry": {"coordinates":[7.5421600342,52.1836853027],"type":"Point"}
}