{
  "type": "Feature",
  "properties": {
    "iso:country":"DE",
    "sg:address":"Lindberghstr. 11",
    "sg:city":"Stolberg",
    "sg:phone":"+49 2402/7893",
    "sg:postcode":"52224",
    "sg:province":"Nordrhein-Westfalen",
    "wof:name":"Hubert Schr\u00f6der",
    "wof:placetype":"venue"
},
  "geometry": {"coordinates":[6.272697,50.764309],"type":"Point"}
}