{
  "type": "Feature",
  "properties": {
    "iso:country":"DE",
    "sg:address":"Am Sportplatz 1",
    "sg:city":"Schmidgaden",
    "sg:phone":"+49 9438/4263",
    "sg:postcode":"92546",
    "sg:province":"Bayern",
    "wof:name":"Andreas Deichl",
    "wof:placetype":"venue"
},
  "geometry": {"coordinates":[12.08868,49.419411],"type":"Point"}
}