{
  "type": "Feature",
  "properties": {
    "iso:country":"DE",
    "sg:address":"Domagkstr. 24",
    "sg:city":"M\u00fcnchen",
    "sg:phone":"+49 89/360940",
    "sg:postcode":"80807",
    "sg:province":"Bayern",
    "wof:name":"Strasser Verwaltungsgesellschaft Mbh",
    "wof:placetype":"venue"
},
  "geometry": {"coordinates":[11.5922937393,48.1838378906],"type":"Point"}
}