{
  "type": "Feature",
  "properties": {
    "iso:country":"DE",
    "sg:address":"Kappenberger Damm 15",
    "sg:city":"M\u00fcnster",
    "sg:phone":"+49 251/72861",
    "sg:postcode":"48151",
    "sg:province":"Nordrhein-Westfalen",
    "wof:name":"Uwe Leusing",
    "wof:placetype":"venue"
},
  "geometry": {"coordinates":[7.61018,51.939461],"type":"Point"}
}