{
  "type": "Feature",
  "properties": {
    "iso:country":"DE",
    "sg:address":"Max-von-Laue-Str. 7",
    "sg:city":"Karlsruhe",
    "sg:phone":"+49 721/617956",
    "sg:postcode":"76228",
    "sg:province":"Baden-W\u00fcrttemberg",
    "wof:name":"Fliesen- Und Fussboden-technik E. Unger Gmbh",
    "wof:placetype":"venue"
},
  "geometry": {"coordinates":[8.4622430801,48.9783477783],"type":"Point"}
}