{
  "type": "Feature",
  "properties": {
    "iso:country":"DE",
    "sg:address":"Zwickauer Str. 467",
    "sg:city":"Chemnitz",
    "sg:phone":"+49 371/852780",
    "sg:postcode":"09117",
    "sg:province":"Sachsen",
    "wof:name":"Walter Haustein",
    "wof:placetype":"venue"
},
  "geometry": {"coordinates":[12.8311576843,50.8127555847],"type":"Point"}
}