{
  "type": "Feature",
  "properties": {
    "iso:country":"DE",
    "sg:address":"Stadionstr. 65",
    "sg:city":"V\u00f6lklingen",
    "sg:phone":"+49 6898/295075",
    "sg:postcode":"66333",
    "sg:province":"Saarland",
    "wof:name":"Tennisschule Match Point Gmbh",
    "wof:placetype":"venue"
},
  "geometry": {"coordinates":[6.8692631721,49.2592926025],"type":"Point"}
}