{
  "type": "Feature",
  "properties": {
    "iso:country":"DE",
    "sg:address":"Am Ehrenmal 10",
    "sg:city":"Kinheim",
    "sg:phone":"+49 6532/2495",
    "sg:postcode":"54538",
    "sg:province":"Rheinland-Pfalz",
    "wof:name":"Willi Molitor Weinbau",
    "wof:placetype":"venue"
},
  "geometry": {"coordinates":[7.0581598282,49.9727516174],"type":"Point"}
}