{
  "type": "Feature",
  "properties": {
    "iso:country":"DE",
    "sg:address":"Waldstr. 2",
    "sg:city":"Sch\u00f6nberg",
    "sg:phone":"+49 8637/830",
    "sg:postcode":"84573",
    "sg:province":"Bayern",
    "wof:name":"Michael Aimer",
    "wof:placetype":"venue"
},
  "geometry": {"coordinates":[12.441518,48.34222],"type":"Point"}
}