{
  "type": "Feature",
  "properties": {
    "iso:country":"DE",
    "sg:address":"Obere Hauptstr. 4",
    "sg:city":"Herxheim",
    "sg:phone":"+49 7276/7173",
    "sg:postcode":"76863",
    "sg:province":"Rheinland-Pfalz",
    "wof:name":"Ratskeller",
    "wof:placetype":"venue"
},
  "geometry": {"coordinates":[8.2152309418,49.1463775635],"type":"Point"}
}