{
  "type": "Feature",
  "properties": {
    "iso:country":"DE",
    "sg:address":"Carl-Schurz-Str. 42",
    "sg:city":"Pforzheim",
    "sg:phone":"+49 7231/71574",
    "sg:postcode":"75180",
    "sg:province":"Baden-W\u00fcrttemberg",
    "wof:name":"Kurt Griesinger Heilpraktiker",
    "wof:placetype":"venue"
},
  "geometry": {"coordinates":[8.668548584,48.8709564209],"type":"Point"}
}