{
  "type": "Feature",
  "properties": {
    "iso:country":"DE",
    "sg:address":"Schwaigerner Str. 5",
    "sg:city":"Gemmingen",
    "sg:phone":"+49 4972/67228",
    "sg:postcode":"75050",
    "sg:province":"Baden-W\u00fcrttemberg",
    "wof:name":"Bezirkssparkasse Eppingen",
    "wof:placetype":"venue"
},
  "geometry": {"coordinates":[8.983653,49.156338],"type":"Point"}
}