{
  "type": "Feature",
  "properties": {
    "iso:country":"DE",
    "sg:address":"Bergstr. 6",
    "sg:city":"Oelde",
    "sg:phone":"+49 2522/2722",
    "sg:postcode":"59302",
    "sg:province":"Nordrhein-Westfalen",
    "wof:name":"Willi Guthoff Innenarchitekt",
    "wof:placetype":"venue"
},
  "geometry": {"coordinates":[8.147592,51.83123],"type":"Point"}
}