{
  "type": "Feature",
  "properties": {
    "iso:country":"DE",
    "sg:address":"Braunschweiger Str. 40",
    "sg:city":"Peine",
    "sg:phone":"+49 5171/57687",
    "sg:postcode":"31226",
    "sg:province":"Niedersachsen",
    "wof:name":"Side Imbi\u00df",
    "wof:placetype":"venue"
},
  "geometry": {"coordinates":[10.234875679,52.3171920776],"type":"Point"}
}