{
  "type": "Feature",
  "properties": {
    "iso:country":"DE",
    "sg:address":"Bahnhofstr. 15",
    "sg:city":"Sylt-Ost",
    "sg:postcode":"25980",
    "sg:province":"Schleswig-Holstein",
    "wof:name":"Raiffeisen-immobilien Sylt Gmbh",
    "wof:placetype":"venue"
},
  "geometry": {"coordinates":[8.3702354431,54.8931808472],"type":"Point"}
}