{
  "type": "Feature",
  "properties": {
    "iso:country":"DE",
    "sg:address":"Zeppelinstr. 9",
    "sg:city":"Herbertingen",
    "sg:phone":"+49 7586/5025",
    "sg:postcode":"88518",
    "sg:province":"Baden-W\u00fcrttemberg",
    "wof:name":"Johann Franz Weidinger",
    "wof:placetype":"venue"
},
  "geometry": {"coordinates":[9.436368,48.054031],"type":"Point"}
}