{
  "type": "Feature",
  "properties": {
    "iso:country":"DE",
    "sg:address":"Lohestr. 2",
    "sg:city":"Unterhaching",
    "sg:postcode":"82008",
    "sg:province":"Bayern",
    "wof:name":"Usr Generalbau Gmbh",
    "wof:placetype":"venue"
},
  "geometry": {"coordinates":[11.60704,48.072887],"type":"Point"}
}