{
  "type": "Feature",
  "properties": {
    "iso:country":"DE",
    "sg:address":"Pulverwiesen 11",
    "sg:city":"Beuren",
    "sg:phone":"+49 711/39022350",
    "sg:postcode":"72660",
    "sg:province":"Baden-W\u00fcrttemberg",
    "wof:name":"Freilichtmusuem Beuren",
    "wof:placetype":"venue"
},
  "geometry": {"coordinates":[9.403865,48.569366],"type":"Point"}
}