{
  "type": "Feature",
  "properties": {
    "iso:country":"DE",
    "sg:address":"Langgasse 8",
    "sg:city":"W\u00e4chtersbach",
    "sg:postcode":"63607",
    "sg:province":"Hessen",
    "wof:name":"Shw-sanit\u00e4r-heizung- W\u00e4rmetechnische-handels-gmbh",
    "wof:placetype":"venue"
},
  "geometry": {"coordinates":[9.2633171082,50.2866477966],"type":"Point"}
}