{
  "type": "Feature",
  "properties": {
    "iso:country":"DE",
    "sg:address":"Bullmannaue 11",
    "sg:city":"Essen",
    "sg:phone":"+49 201/830124",
    "sg:postcode":"45327",
    "sg:province":"Nordrhein-Westfalen",
    "wof:name":"Blue Chip Agentur F\u00fcr Public Relations Und",
    "wof:placetype":"venue"
},
  "geometry": {"coordinates":[7.0467591286,51.4913139343],"type":"Point"}
}