{
  "type": "Feature",
  "properties": {
    "iso:country":"DE",
    "sg:address":"Beim Alten Sch\u00fctzenhof 10-14",
    "sg:city":"Hamburg",
    "sg:phone":"+49 40/2201681",
    "sg:postcode":"22083",
    "sg:province":"Hamburg",
    "wof:name":"Ernst K\u00e4hler",
    "wof:placetype":"venue"
},
  "geometry": {"coordinates":[10.0281095505,53.575302124],"type":"Point"}
}