{
  "type": "Feature",
  "properties": {
    "iso:country":"DE",
    "sg:address":"Wilhelmsh\u00f6her Allee 106",
    "sg:city":"Kassel",
    "sg:phone":"+49 561/18031",
    "sg:postcode":"34119",
    "sg:province":"Hessen",
    "wof:name":"Reiseb\u00fcro Ikarus",
    "wof:placetype":"venue"
},
  "geometry": {"coordinates":[9.4686136246,51.3126411438],"type":"Point"}
}