{
  "type": "Feature",
  "properties": {
    "iso:country":"DE",
    "sg:address":"Bayer Weg 1-3",
    "sg:city":"Leiningen",
    "sg:phone":"+49 6746/9416863",
    "sg:postcode":"56291",
    "sg:province":"Rheinland-Pfalz",
    "wof:name":"Hsu Unternehmens- Und Informatik-beratung Gmbh",
    "wof:placetype":"venue"
},
  "geometry": {"coordinates":[7.5686388016,50.1312332153],"type":"Point"}
}