{
  "type": "Feature",
  "properties": {
    "iso:country":"DE",
    "sg:address":"Krautgartenstr. 1 a",
    "sg:city":"Hebertshausen",
    "sg:phone":"+49 8131/25168",
    "sg:postcode":"85241",
    "sg:province":"Bayern",
    "wof:name":"Pizzeria Domenico Zoccali",
    "wof:placetype":"venue"
},
  "geometry": {"coordinates":[11.4706144333,48.2885665894],"type":"Point"}
}