{
  "type": "Feature",
  "properties": {
    "iso:country":"DE",
    "sg:address":"Im Heidkampe 14",
    "sg:city":"Hannover",
    "sg:phone":"+49 511/648081",
    "sg:postcode":"30659",
    "sg:province":"Niedersachsen",
    "wof:name":"Tegtmeyer Gmbh & Co.",
    "wof:placetype":"venue"
},
  "geometry": {"coordinates":[9.8051233292,52.4094657898],"type":"Point"}
}