{
  "type": "Feature",
  "properties": {
    "iso:country":"DE",
    "sg:address":"Lucas-Cranach-Str. 6",
    "sg:city":"L\u00fcnen",
    "sg:phone":"+49 2306/25048",
    "sg:postcode":"44532",
    "sg:province":"Nordrhein-Westfalen",
    "wof:name":"Rainer Kampmann Bau Gmbh",
    "wof:placetype":"venue"
},
  "geometry": {"coordinates":[7.5213079453,51.6060295105],"type":"Point"}
}