{
  "type": "Feature",
  "properties": {
    "iso:country":"DE",
    "sg:address":"Merseburger Str. 92",
    "sg:city":"Leipzig",
    "sg:phone":"+49 341/4803035",
    "sg:postcode":"04177",
    "sg:province":"Sachsen",
    "wof:name":"Flora-apotheke Ohg",
    "wof:placetype":"venue"
},
  "geometry": {"coordinates":[12.327326,51.337471],"type":"Point"}
}