{
  "type": "Feature",
  "properties": {
    "iso:country":"DE",
    "sg:address":"Habichthorst 34-36",
    "sg:city":"Hamburg",
    "sg:postcode":"22459",
    "sg:province":"Hamburg",
    "wof:name":"Verwaltungs Rs Habicht Beteiligungsgesellschaft Mbh",
    "wof:placetype":"venue"
},
  "geometry": {"coordinates":[9.9573812485,53.6310844421],"type":"Point"}
}