{
  "type": "Feature",
  "properties": {
    "iso:country":"DE",
    "sg:address":"Hauptstr. 49",
    "sg:city":"Zeiskam",
    "sg:phone":"+49 4963/47344",
    "sg:postcode":"67378",
    "sg:province":"Rheinland-Pfalz",
    "wof:name":"Sparkasse Germersheim-kandel",
    "wof:placetype":"venue"
},
  "geometry": {"coordinates":[8.24901,49.229881],"type":"Point"}
}