{
  "type": "Feature",
  "properties": {
    "iso:country":"DE",
    "sg:address":"Le-Chambon-Str. 3",
    "sg:city":"Herzebrock-Clarholz",
    "sg:phone":"+49 5245/4941",
    "sg:postcode":"33442",
    "sg:province":"Nordrhein-Westfalen",
    "wof:name":"H. Reker",
    "wof:placetype":"venue"
},
  "geometry": {"coordinates":[8.240469,51.881199],"type":"Point"}
}