{
  "type": "Feature",
  "properties": {
    "iso:country":"DE",
    "sg:address":"Dresdner Platz 4",
    "sg:city":"Reutlingen",
    "sg:phone":"+49 7121/630226",
    "sg:postcode":"72760",
    "sg:province":"Baden-W\u00fcrttemberg",
    "wof:name":"Stadtb\u00fccherei",
    "wof:placetype":"venue"
},
  "geometry": {"coordinates":[9.208331,48.520248],"type":"Point"}
}