{
  "type": "Feature",
  "properties": {
    "iso:country":"DE",
    "sg:address":"Schleifm\u00fchlenweg 1",
    "sg:city":"Schwerin",
    "sg:phone":"+49 385/562751",
    "sg:postcode":"19061",
    "sg:province":"Mecklenburg-Vorpommern",
    "wof:name":"Schweriner Schleifm\u00fchle",
    "wof:placetype":"venue"
},
  "geometry": {"coordinates":[11.432596,53.610023],"type":"Point"}
}