{
  "type": "Feature",
  "properties": {
    "iso:country":"DE",
    "sg:address":"Nymphenburger Str. 103",
    "sg:city":"M\u00fcnchen",
    "sg:phone":"+49 89/1293255",
    "sg:postcode":"80636",
    "sg:province":"Bayern",
    "wof:name":"Karl-heinz Schulze",
    "wof:placetype":"venue"
},
  "geometry": {"coordinates":[11.5421762466,48.1505889893],"type":"Point"}
}