{
  "type": "Feature",
  "properties": {
    "iso:country":"DE",
    "sg:address":"K\u00f6nigsheimer Str. 4",
    "sg:city":"Gosheim",
    "sg:phone":"+49 7426/1350",
    "sg:postcode":"78559",
    "sg:province":"Baden-W\u00fcrttemberg",
    "wof:name":"Robert Weber Glas- Und Prozellanwaren",
    "wof:placetype":"venue"
},
  "geometry": {"coordinates":[8.765964,48.131165],"type":"Point"}
}