{
  "type": "Feature",
  "properties": {
    "iso:country":"DE",
    "sg:address":"Kronberger Str. 34",
    "sg:city":"Frankfurt",
    "sg:phone":"+49 69/684542",
    "sg:postcode":"60323",
    "sg:province":"Hessen",
    "wof:name":"Meg Maschinen & Elektro- Ger\u00e4te Handels Gmbh",
    "wof:placetype":"venue"
},
  "geometry": {"coordinates":[8.6667613983,50.119808197],"type":"Point"}
}