{
  "type": "Feature",
  "properties": {
    "iso:country":"DE",
    "sg:address":"Schnellerstr. 60",
    "sg:city":"Berlin",
    "sg:phone":"+49 30/6716474",
    "sg:postcode":"12439",
    "sg:province":"Berlin",
    "wof:name":"Bio-lein Gmbh",
    "wof:placetype":"venue"
},
  "geometry": {"coordinates":[13.5244178772,52.4528846741],"type":"Point"}
}