{
  "type": "Feature",
  "properties": {
    "iso:country":"DE",
    "sg:address":"Augustusburger Str. 106",
    "sg:city":"Fl\u00f6ha",
    "sg:phone":"+49 3726/2053",
    "sg:postcode":"09557",
    "sg:province":"Sachsen",
    "wof:name":"E. Eulitz",
    "wof:placetype":"venue"
},
  "geometry": {"coordinates":[13.079572,50.847202],"type":"Point"}
}