{
  "type": "Feature",
  "properties": {
    "iso:country":"DE",
    "sg:address":"Carl-Heydemann-Ring 128",
    "sg:city":"Stralsund",
    "sg:phone":"+49 3831/280652",
    "sg:postcode":"18437",
    "sg:province":"Mecklenburg-Vorpommern",
    "wof:name":"Fahrschule Nordland Gbr",
    "wof:placetype":"venue"
},
  "geometry": {"coordinates":[13.0704555511,54.3057060242],"type":"Point"}
}