{
  "type": "Feature",
  "properties": {
    "iso:country":"DE",
    "sg:address":"Drosselstr. 7",
    "sg:city":"Garmisch-Partenkirchen",
    "sg:phone":"+49 8821/93330",
    "sg:postcode":"82467",
    "sg:province":"Bayern",
    "wof:name":"Fotoverlag Huber Inh. Hans-peter Huber",
    "wof:placetype":"venue"
},
  "geometry": {"coordinates":[11.0992536545,47.5031433105],"type":"Point"}
}