{
  "type": "Feature",
  "properties": {
    "iso:country":"DE",
    "sg:address":"Wilhelm-Leuschner-Str. 15",
    "sg:city":"Neu-Isenburg",
    "sg:phone":"+49 6102/27470",
    "sg:postcode":"63263",
    "sg:province":"Hessen",
    "wof:name":"Neil Financial Consulting Gmbh",
    "wof:placetype":"venue"
},
  "geometry": {"coordinates":[8.6828603745,50.0570411682],"type":"Point"}
}