{
  "type": "Feature",
  "properties": {
    "iso:country":"DE",
    "sg:address":"L\u00f6psinger Str. 31",
    "sg:city":"N\u00f6rdlingen",
    "sg:phone":"+49 9081/86177",
    "sg:postcode":"86720",
    "sg:province":"Bayern",
    "wof:name":"Zoobedarf Ehrentreich Gmbh",
    "wof:placetype":"venue"
},
  "geometry": {"coordinates":[10.4804706573,48.8618431091],"type":"Point"}
}