{
  "type": "Feature",
  "properties": {
    "iso:country":"DE",
    "sg:address":"Am Storrenacker 14",
    "sg:city":"Karlsruhe",
    "sg:phone":"+49 721/625040",
    "sg:postcode":"76139",
    "sg:province":"Baden-W\u00fcrttemberg",
    "wof:name":"Jegle Gmbh",
    "wof:placetype":"venue"
},
  "geometry": {"coordinates":[8.467613,49.019688],"type":"Point"}
}