{
  "type": "Feature",
  "properties": {
    "iso:country":"DE",
    "sg:address":"In der Stockwiese",
    "sg:city":"Bad Laasphe",
    "sg:phone":"+49 2752/2155",
    "sg:postcode":"57334",
    "sg:province":"Nordrhein-Westfalen",
    "wof:name":"Lidl Gmbh & Co. Kg",
    "wof:placetype":"venue"
},
  "geometry": {"coordinates":[8.4232282639,50.9281005859],"type":"Point"}
}