{
  "type": "Feature",
  "properties": {
    "iso:country":"DE",
    "sg:address":"Harz 50",
    "sg:city":"Halle",
    "sg:phone":"+49 345/2175500",
    "sg:postcode":"06108",
    "sg:province":"Sachsen-Anhalt",
    "wof:name":"Geiger Starfinger Falter Und Kollegen",
    "wof:placetype":"venue"
},
  "geometry": {"coordinates":[11.9674396515,51.4884681702],"type":"Point"}
}