{
  "type": "Feature",
  "properties": {
    "iso:country":"DE",
    "sg:address":"Am Heuweg 43/1",
    "sg:city":"Rutesheim",
    "sg:phone":"+49 7152/52958",
    "sg:postcode":"71277",
    "sg:province":"Baden-W\u00fcrttemberg",
    "wof:name":"Berthold L\u00f6chel Architekt",
    "wof:placetype":"venue"
},
  "geometry": {"coordinates":[8.959287,48.79298],"type":"Point"}
}