{
  "type": "Feature",
  "properties": {
    "iso:country":"DE",
    "sg:address":"Hohnstr. 17",
    "sg:city":"Bad Neustadt",
    "sg:phone":"+49 9771/2847",
    "sg:postcode":"97616",
    "sg:province":"Bayern",
    "wof:name":"Reinhilde Suckf\u00fcll",
    "wof:placetype":"venue"
},
  "geometry": {"coordinates":[10.2151260376,50.3214035034],"type":"Point"}
}