{
  "type": "Feature",
  "properties": {
    "iso:country":"DE",
    "sg:address":"Gartenstr. 3",
    "sg:city":"Nauendorf",
    "sg:phone":"+49 34603/20205",
    "sg:postcode":"06193",
    "sg:province":"Sachsen-Anhalt",
    "wof:name":"R. Kambach",
    "wof:placetype":"venue"
},
  "geometry": {"coordinates":[11.888479,51.60268],"type":"Point"}
}