{
  "type": "Feature",
  "properties": {
    "iso:country":"DE",
    "sg:address":"Pfarrweg 1",
    "sg:city":"Ottenhofen",
    "sg:phone":"+49 8121/3382",
    "sg:postcode":"85570",
    "sg:province":"Bayern",
    "wof:name":"Katholisches Pfarramt St. Katharina",
    "wof:placetype":"venue"
},
  "geometry": {"coordinates":[11.8817920685,48.216342926],"type":"Point"}
}