{
  "type": "Feature",
  "properties": {
    "iso:country":"DE",
    "sg:address":"Zum Kirschenhof 2",
    "sg:city":"Schwerin",
    "sg:phone":"+49 385/484540",
    "sg:postcode":"19057",
    "sg:province":"Mecklenburg-Vorpommern",
    "wof:name":"Gust\u00e4vel Gmbh & Co. Kg",
    "wof:placetype":"venue"
},
  "geometry": {"coordinates":[11.34512043,53.6644592285],"type":"Point"}
}