{
  "type": "Feature",
  "properties": {
    "iso:country":"DE",
    "sg:address":"Rhein-Mosel-Str. 63",
    "sg:city":"Emmelshausen",
    "sg:phone":"+49 6747/93040",
    "sg:postcode":"56281",
    "sg:province":"Rheinland-Pfalz",
    "wof:name":"Rosen-apotheke Ulrich Francke E. K.",
    "wof:placetype":"venue"
},
  "geometry": {"coordinates":[7.552929,50.155647],"type":"Point"}
}