{
  "type": "Feature",
  "properties": {
    "iso:country":"DE",
    "sg:address":"Karl-Lehr-Str. 34",
    "sg:city":"Wiesbaden",
    "sg:phone":"+49 611/261656",
    "sg:postcode":"65201",
    "sg:province":"Hessen",
    "wof:name":"Richard Abt",
    "wof:placetype":"venue"
},
  "geometry": {"coordinates":[8.1994085312,50.0460205078],"type":"Point"}
}