{
  "type": "Feature",
  "properties": {
    "iso:country":"DE",
    "sg:address":"Pr\u00e4sidentenstr. 24",
    "sg:city":"Bergkamen",
    "sg:postcode":"59192",
    "sg:province":"Nordrhein-Westfalen",
    "wof:name":"All-dach Gmbh",
    "wof:placetype":"venue"
},
  "geometry": {"coordinates":[7.640432,51.618481],"type":"Point"}
}