{
  "type": "Feature",
  "properties": {
    "iso:country":"DE",
    "sg:address":"Hirschbergstr. 20",
    "sg:city":"Lenting",
    "sg:phone":"+49 8456/5342",
    "sg:postcode":"85101",
    "sg:province":"Bayern",
    "wof:name":"Sparkasse Ingolstadt",
    "wof:placetype":"venue"
},
  "geometry": {"coordinates":[11.456974,48.80838],"type":"Point"}
}