{
  "type": "Feature",
  "properties": {
    "iso:country":"DE",
    "sg:address":"Hauptstr. 1",
    "sg:city":"Gerabronn",
    "sg:phone":"+49 7952/925085",
    "sg:postcode":"74582",
    "sg:province":"Baden-W\u00fcrttemberg",
    "wof:name":"Detlev Pfisterer",
    "wof:placetype":"venue"
},
  "geometry": {"coordinates":[9.922783,49.249123],"type":"Point"}
}