{
  "type": "Feature",
  "properties": {
    "iso:country":"DE",
    "sg:address":"Gildebrede 11",
    "sg:city":"M\u00f6lln",
    "sg:phone":"+49 4542/88588",
    "sg:postcode":"23879",
    "sg:province":"Schleswig-Holstein",
    "wof:name":"Ulrich Leppek Ingenieur",
    "wof:placetype":"venue"
},
  "geometry": {"coordinates":[10.698677063,53.6006965637],"type":"Point"}
}