{
  "type": "Feature",
  "properties": {
    "iso:country":"DE",
    "sg:address":"Fr\u00fchlingstr. 17",
    "sg:city":"\u00dcchtelhausen",
    "sg:phone":"+49 9720/1287",
    "sg:postcode":"97532",
    "sg:province":"Bayern",
    "wof:name":"L. Schmitt",
    "wof:placetype":"venue"
},
  "geometry": {"coordinates":[10.3231687546,50.1102027893],"type":"Point"}
}