{
  "type": "Feature",
  "properties": {
    "iso:country":"DE",
    "sg:address":"Kleine M\u00e4rkerstr. 1",
    "sg:city":"Halle",
    "sg:postcode":"06108",
    "sg:province":"Sachsen-Anhalt",
    "wof:name":"Evangelische Beratungsstelle",
    "wof:placetype":"venue"
},
  "geometry": {"coordinates":[11.972233,51.481197],"type":"Point"}
}