{
  "type": "Feature",
  "properties": {
    "iso:country":"DE",
    "sg:address":"Bergstr. 228",
    "sg:city":"Marl",
    "sg:phone":"+49 2365/17483",
    "sg:postcode":"45768",
    "sg:province":"Nordrhein-Westfalen",
    "wof:name":"Verbraucher-zentrale Nrw E. V.",
    "wof:placetype":"venue"
},
  "geometry": {"coordinates":[7.1004400253,51.6556015015],"type":"Point"}
}