{
  "type": "Feature",
  "properties": {
    "iso:country":"DE",
    "sg:address":"Warmbacher Str. 22",
    "sg:city":"Rheinfelden",
    "sg:phone":"+49 7623/62826",
    "sg:postcode":"79618",
    "sg:province":"Baden-W\u00fcrttemberg",
    "wof:name":"L. Bludau",
    "wof:placetype":"venue"
},
  "geometry": {"coordinates":[7.7765898705,47.554309845],"type":"Point"}
}