{
  "type": "Feature",
  "properties": {
    "iso:country":"DE",
    "sg:address":"An der Insel 2",
    "sg:city":"Kronsgaard",
    "sg:phone":"+49 4643/991",
    "sg:postcode":"24395",
    "sg:province":"Schleswig-Holstein",
    "wof:name":"Carl-friedrich Cordsen",
    "wof:placetype":"venue"
},
  "geometry": {"coordinates":[9.967281,54.735741],"type":"Point"}
}