{
  "type": "Feature",
  "properties": {
    "iso:country":"DE",
    "sg:address":"Berthin-Bleeg-Str. 4",
    "sg:city":"Wenningstedt",
    "sg:phone":"+49 4651/43468",
    "sg:postcode":"25996",
    "sg:province":"Schleswig-Holstein",
    "wof:name":"Gisela Missal",
    "wof:placetype":"venue"
},
  "geometry": {"coordinates":[8.323493,54.937504],"type":"Point"}
}