{
  "type": "Feature",
  "properties": {
    "iso:country":"DE",
    "sg:address":"Klosterstr. 9",
    "sg:city":"Germersheim",
    "sg:phone":"+49 7274/8627",
    "sg:postcode":"76726",
    "sg:province":"Rheinland-Pfalz",
    "wof:name":"Germania",
    "wof:placetype":"venue"
},
  "geometry": {"coordinates":[8.3700838089,49.2196998596],"type":"Point"}
}