{
  "type": "Feature",
  "properties": {
    "iso:country":"DE",
    "sg:address":"Schwarzwaldstr. 19",
    "sg:city":"Gernsbach",
    "sg:phone":"+49 7224/2662",
    "sg:postcode":"76593",
    "sg:province":"Baden-W\u00fcrttemberg",
    "wof:name":"Kurt Klink",
    "wof:placetype":"venue"
},
  "geometry": {"coordinates":[8.3379478455,48.7701530457],"type":"Point"}
}