{
  "type": "Feature",
  "properties": {
    "iso:country":"DE",
    "sg:address":"J\u00fcdenstr. 2",
    "sg:city":"Duderstadt",
    "sg:phone":"+49 5527/2806",
    "sg:postcode":"37115",
    "sg:province":"Niedersachsen",
    "wof:name":"Ingbert Block",
    "wof:placetype":"venue"
},
  "geometry": {"coordinates":[10.261166,51.512501],"type":"Point"}
}