{
  "type": "Feature",
  "properties": {
    "iso:country":"DE",
    "sg:address":"Dorfstr. 26",
    "sg:city":"Moosinning",
    "sg:phone":"+49 8123/928870",
    "sg:postcode":"85452",
    "sg:province":"Bayern",
    "wof:name":"A. Und M. Scharlach",
    "wof:placetype":"venue"
},
  "geometry": {"coordinates":[11.843069,48.274273],"type":"Point"}
}