{
  "type": "Feature",
  "properties": {
    "iso:country":"DE",
    "sg:address":"Windsch\u00e4ufelnstr. 7",
    "sg:city":"Garmisch-Partenkirchen",
    "sg:phone":"+49 8821/71263",
    "sg:postcode":"82467",
    "sg:province":"Bayern",
    "wof:name":"Arndt & Co. Gmbh",
    "wof:placetype":"venue"
},
  "geometry": {"coordinates":[11.0858001709,47.4870452881],"type":"Point"}
}