{
  "type": "Feature",
  "properties": {
    "iso:country":"DE",
    "sg:address":"Horner Weg 192",
    "sg:city":"Hamburg",
    "sg:phone":"+49 40/6518250",
    "sg:postcode":"22111",
    "sg:province":"Hamburg",
    "wof:name":"Kg Meisterb\u00e4cker Springer Gmbh & Co.",
    "wof:placetype":"venue"
},
  "geometry": {"coordinates":[10.074524,53.554756],"type":"Point"}
}