{
  "type": "Feature",
  "properties": {
    "iso:country":"DE",
    "sg:address":"Luisenstr. 8",
    "sg:city":"Weil der Stadt",
    "sg:phone":"+49 7033/31758",
    "sg:postcode":"71263",
    "sg:province":"Baden-W\u00fcrttemberg",
    "wof:name":"Ernst Weik",
    "wof:placetype":"venue"
},
  "geometry": {"coordinates":[8.8495111465,48.7684555054],"type":"Point"}
}