{
  "type": "Feature",
  "properties": {
    "iso:country":"DE",
    "sg:address":"Ludwigstra\u00dfe 26",
    "sg:city":"Albstadt",
    "sg:postcode":"72461",
    "sg:province":"Baden-W\u00fcrttemberg",
    "wof:name":"Etiketten-service Conzelmann Kg",
    "wof:placetype":"venue"
},
  "geometry": {"coordinates":[9.013224,48.25436],"type":"Point"}
}