{
  "type": "Feature",
  "properties": {
    "iso:country":"DE",
    "sg:address":"Bahnhofstr. 18",
    "sg:city":"\u00d6tisheim",
    "sg:phone":"+49 7041/3028",
    "sg:postcode":"75443",
    "sg:province":"Baden-W\u00fcrttemberg",
    "wof:name":"Albert Heugel",
    "wof:placetype":"venue"
},
  "geometry": {"coordinates":[8.8080415726,48.9638214111],"type":"Point"}
}