{
  "type": "Feature",
  "properties": {
    "iso:country":"DE",
    "sg:address":"Hainfelder Str. 7",
    "sg:city":"Flemlingen",
    "sg:phone":"+49 6323/2757",
    "sg:postcode":"76835",
    "sg:province":"Rheinland-Pfalz",
    "wof:name":"Hainfelder Druckerei Gmbh",
    "wof:placetype":"venue"
},
  "geometry": {"coordinates":[8.096065,49.245178],"type":"Point"}
}