{
  "type": "Feature",
  "properties": {
    "iso:country":"DE",
    "sg:address":"Engerser Str. 97",
    "sg:city":"Neuwied",
    "sg:phone":"+49 2631/32948",
    "sg:postcode":"56564",
    "sg:province":"Rheinland-Pfalz",
    "wof:name":"Werkst\u00e4tten Josef Und Paul G\u00fcnther",
    "wof:placetype":"venue"
},
  "geometry": {"coordinates":[7.4619760513,50.4243125916],"type":"Point"}
}