{
  "type": "Feature",
  "properties": {
    "iso:country":"DE",
    "sg:address":"Adelhartstr. 55",
    "sg:city":"Bad Homburg",
    "sg:phone":"+49 6172/451815",
    "sg:postcode":"61352",
    "sg:province":"Hessen",
    "wof:name":"Aale Eschb\u00e4chere E. V. Reinhold Neumann",
    "wof:placetype":"venue"
},
  "geometry": {"coordinates":[8.647974968,50.2160949707],"type":"Point"}
}