{
  "type": "Feature",
  "properties": {
    "iso:country":"DE",
    "sg:address":"Stadelbergstr. 10",
    "sg:city":"M\u00fcnchen",
    "sg:phone":"+49 89/6909674",
    "sg:postcode":"81547",
    "sg:province":"Bayern",
    "wof:name":"Werner Schr\u00e4gle Gmbh",
    "wof:placetype":"venue"
},
  "geometry": {"coordinates":[11.583607,48.094208],"type":"Point"}
}