{
  "type": "Feature",
  "properties": {
    "iso:country":"DE",
    "sg:address":"Crottorfer Str. 34",
    "sg:city":"Reichshof",
    "sg:phone":"+49 2297/902790",
    "sg:postcode":"51580",
    "sg:province":"Nordrhein-Westfalen",
    "wof:name":"Manfred Mackenthun E. K.",
    "wof:placetype":"venue"
},
  "geometry": {"coordinates":[7.7517371178,50.9354934692],"type":"Point"}
}