{
  "type": "Feature",
  "properties": {
    "iso:country":"DE",
    "sg:address":"Reinstorfweg 10a",
    "sg:city":"Hamburg",
    "sg:phone":"+49 40/75662525",
    "sg:postcode":"21107",
    "sg:province":"Hamburg",
    "wof:name":"Rechtsanw\u00e4ltin Martina Sch\u00e4fer",
    "wof:placetype":"venue"
},
  "geometry": {"coordinates":[9.9935750961,53.5005455017],"type":"Point"}
}