{
  "type": "Feature",
  "properties": {
    "iso:country":"DE",
    "sg:address":"Zweinaundorfer Str. 9",
    "sg:city":"Leipzig",
    "sg:phone":"+49 341/6881901",
    "sg:postcode":"04318",
    "sg:province":"Sachsen",
    "wof:name":"R. Hachmeister",
    "wof:placetype":"venue"
},
  "geometry": {"coordinates":[12.409581,51.335331],"type":"Point"}
}