{
  "type": "Feature",
  "properties": {
    "iso:country":"DE",
    "sg:address":"Poststr. 18 - 20",
    "sg:city":"Sprockhoevel",
    "sg:phone":"+49 2339",
    "sg:postcode":"45549",
    "sg:province":"Nordrhein-Westfalen",
    "wof:name":"Gebr. Oesterling Kg",
    "wof:placetype":"venue"
},
  "geometry": {"coordinates":[7.278069973,51.3353385925],"type":"Point"}
}