{
  "type": "Feature",
  "properties": {
    "iso:country":"DE",
    "sg:address":"Friedrich-Vo\u00df-Str. 11",
    "sg:city":"Rendsburg",
    "sg:phone":"+49 4943/315960",
    "sg:postcode":"24768",
    "sg:province":"Schleswig-Holstein",
    "wof:name":"Getreide Ag",
    "wof:placetype":"venue"
},
  "geometry": {"coordinates":[9.674343,54.294533],"type":"Point"}
}