{
  "type": "Feature",
  "properties": {
    "iso:country":"DE",
    "sg:address":"Josef-Z\u00e4hringer-Str. 103",
    "sg:city":"Furtwangen",
    "sg:phone":"+49 4977/2391940",
    "sg:postcode":"78120",
    "sg:province":"Baden-W\u00fcrttemberg",
    "wof:name":"Ams-uhrenfabrik A. Mayer Gmbh",
    "wof:placetype":"venue"
},
  "geometry": {"coordinates":[8.2524404526,48.0485687256],"type":"Point"}
}