{
  "type": "Feature",
  "properties": {
    "iso:country":"DE",
    "sg:address":"M\u00fcllerstr. 114 a",
    "sg:city":"Berlin",
    "sg:phone":"+49 30/4517846",
    "sg:postcode":"13349",
    "sg:province":"Berlin",
    "wof:name":"G\u00fcnter Kannenberg",
    "wof:placetype":"venue"
},
  "geometry": {"coordinates":[13.342765,52.555447],"type":"Point"}
}