{
  "type": "Feature",
  "properties": {
    "iso:country":"DE",
    "sg:address":"Brunnenweg 1",
    "sg:city":"Heiligenstadt",
    "sg:phone":"+49 9198/1550",
    "sg:postcode":"91332",
    "sg:province":"Bayern",
    "wof:name":"Dfm-hofmann Verwaltungsges. Mbh",
    "wof:placetype":"venue"
},
  "geometry": {"coordinates":[11.174256,49.863113],"type":"Point"}
}