{
  "type": "Feature",
  "properties": {
    "iso:country":"DE",
    "sg:address":"Werner von Siemens Stra\u00dfe 1-3",
    "sg:city":"Berlin-Sch\u00f6neiche",
    "sg:phone":"+49 30/64903250",
    "sg:postcode":"15566",
    "sg:province":"Brandenburg",
    "wof:name":"Oktabau Ag",
    "wof:placetype":"venue"
},
  "geometry": {"coordinates":[13.705612,52.498009],"type":"Point"}
}