{
  "type": "Feature",
  "properties": {
    "iso:country":"DE",
    "sg:address":"Webereistr. 15",
    "sg:city":"Durach",
    "sg:postcode":"87471",
    "sg:province":"Bayern",
    "wof:name":"Domino Wohnbau- Und Patent-verwertungs Gmbh",
    "wof:placetype":"venue"
},
  "geometry": {"coordinates":[10.325562,47.700703],"type":"Point"}
}