{
  "type": "Feature",
  "properties": {
    "iso:country":"DE",
    "sg:address":"Gotenstr. 84 a",
    "sg:city":"Bonn",
    "sg:phone":"+49 228/81950",
    "sg:postcode":"53175",
    "sg:province":"Nordrhein-Westfalen",
    "wof:name":"Cbt Wohnhaus Emmaus",
    "wof:placetype":"venue"
},
  "geometry": {"coordinates":[7.152211,50.696907],"type":"Point"}
}