{
  "type": "Feature",
  "properties": {
    "iso:country":"DE",
    "sg:address":"Brauweg 12",
    "sg:city":"G\u00f6ttingen",
    "sg:phone":"+49 551/705291",
    "sg:postcode":"37073",
    "sg:province":"Niedersachsen",
    "wof:name":"Constantin-brunner-stiftung",
    "wof:placetype":"venue"
},
  "geometry": {"coordinates":[9.9259557724,51.5276832581],"type":"Point"}
}