{
  "type": "Feature",
  "properties": {
    "iso:country":"DE",
    "sg:address":"Kirchstr. 26",
    "sg:city":"Bullay",
    "sg:postcode":"56859",
    "sg:province":"Rheinland-Pfalz",
    "wof:name":"Pfarrb\u00fccherei Bullay",
    "wof:placetype":"venue"
},
  "geometry": {"coordinates":[7.132795,50.056877],"type":"Point"}
}