{
  "type": "Feature",
  "properties": {
    "iso:country":"DE",
    "sg:address":"Tauberzell",
    "sg:city":"Adelshofen",
    "sg:phone":"+49 9865/718",
    "sg:postcode":"91587",
    "sg:province":"Bayern",
    "wof:name":"Hirtenscheune",
    "wof:placetype":"venue"
},
  "geometry": {"coordinates":[10.1211919785,49.446849823],"type":"Point"}
}