{
  "type": "Feature",
  "properties": {
    "iso:country":"DE",
    "sg:address":"Om Knupp 27",
    "sg:city":"K\u00fcrten",
    "sg:phone":"+49 2268/906384",
    "sg:postcode":"51515",
    "sg:province":"Nordrhein-Westfalen",
    "wof:name":"Thomas Quabach",
    "wof:placetype":"venue"
},
  "geometry": {"coordinates":[7.25672,51.050659],"type":"Point"}
}