{
  "type": "Feature",
  "properties": {
    "iso:country":"DE",
    "sg:address":"Demminer Str. 23",
    "sg:city":"Anklam",
    "sg:phone":"+49 3971/831358",
    "sg:postcode":"17389",
    "sg:province":"Mecklenburg-Vorpommern",
    "wof:name":"S. Gro\u00dfjohann",
    "wof:placetype":"venue"
},
  "geometry": {"coordinates":[13.676895,53.853069],"type":"Point"}
}