{
  "type": "Feature",
  "properties": {
    "iso:country":"DE",
    "sg:address":"Karlsruher Str. 34",
    "sg:city":"Laatzen",
    "sg:phone":"+49 511/876252",
    "sg:postcode":"30880",
    "sg:province":"Niedersachsen",
    "wof:name":"Olympia-fitness",
    "wof:placetype":"venue"
},
  "geometry": {"coordinates":[9.7967910767,52.3139686584],"type":"Point"}
}