{
  "type": "Feature",
  "properties": {
    "iso:country":"DE",
    "sg:address":"Krokusstr. 80",
    "sg:city":"Berlin",
    "sg:phone":"+49 30/6620395",
    "sg:postcode":"12357",
    "sg:province":"Berlin",
    "wof:name":"Casa Montella",
    "wof:placetype":"venue"
},
  "geometry": {"coordinates":[13.4945764542,52.4215507507],"type":"Point"}
}