{
  "type": "Feature",
  "properties": {
    "iso:country":"DE",
    "sg:address":"Sommerberg 40",
    "sg:city":"Reutlingen",
    "sg:phone":"+49 7121/63126",
    "sg:postcode":"72768",
    "sg:province":"Baden-W\u00fcrttemberg",
    "wof:name":"Hofmayer Und Schaal Gesch\u00e4ftsf\u00fchrungs-gmbh",
    "wof:placetype":"venue"
},
  "geometry": {"coordinates":[9.1951255798,48.5337333679],"type":"Point"}
}