{
  "type": "Feature",
  "properties": {
    "iso:country":"DE",
    "sg:address":"Dorfstr. 47",
    "sg:city":"Sch\u00f6neck",
    "sg:phone":"+49 37464/88844",
    "sg:postcode":"08261",
    "sg:province":"Sachsen",
    "wof:name":"Sieglinde Schmidt",
    "wof:placetype":"venue"
},
  "geometry": {"coordinates":[12.277527,50.409142],"type":"Point"}
}