{
  "type": "Feature",
  "properties": {
    "iso:country":"DE",
    "sg:address":"Gartenstr. 2",
    "sg:city":"Holzwei\u00dfig",
    "sg:phone":"+49 3493/69174",
    "sg:postcode":"06808",
    "sg:province":"Sachsen-Anhalt",
    "wof:name":"Horst Zimmermann",
    "wof:placetype":"venue"
},
  "geometry": {"coordinates":[12.315392,51.603432],"type":"Point"}
}