{
  "type": "Feature",
  "properties": {
    "iso:country":"DE",
    "sg:address":"Meisenstr. 4",
    "sg:city":"Neu-Isenburg",
    "sg:phone":"+49 6102/53135",
    "sg:postcode":"63263",
    "sg:province":"Hessen",
    "wof:name":"Christian Schlempp Architekt",
    "wof:placetype":"venue"
},
  "geometry": {"coordinates":[8.753442,50.058903],"type":"Point"}
}