{
  "type": "Feature",
  "properties": {
    "iso:country":"DE",
    "sg:address":"Kirchhofstr. 20",
    "sg:city":"M\u00f6nchengladbach",
    "sg:phone":"+49 2166/603559",
    "sg:postcode":"41199",
    "sg:province":"Nordrhein-Westfalen",
    "wof:name":"Fassbender & Co. Inh. Hildegard Kirschner",
    "wof:placetype":"venue"
},
  "geometry": {"coordinates":[6.455608,51.134399],"type":"Point"}
}