{
  "type": "Feature",
  "properties": {
    "iso:country":"DE",
    "sg:address":"Laacher Str. 12b",
    "sg:city":"Bergheim",
    "sg:phone":"+49 2271/91985",
    "sg:postcode":"50127",
    "sg:province":"Nordrhein-Westfalen",
    "wof:name":"Changs H. D. S. Drogerie Und Geschenkboutique Gmbh",
    "wof:placetype":"venue"
},
  "geometry": {"coordinates":[6.6572751999,50.9274711609],"type":"Point"}
}