{
  "type": "Feature",
  "properties": {
    "iso:country":"DE",
    "sg:address":"Am Brunnen 1",
    "sg:city":"Leipzig",
    "sg:postcode":"04159",
    "sg:province":"Sachsen",
    "wof:name":"Roman Dieter",
    "wof:placetype":"venue"
},
  "geometry": {"coordinates":[12.272803,51.384384],"type":"Point"}
}