{
  "type": "Feature",
  "properties": {
    "iso:country":"DE",
    "sg:address":"Volmestr. 65",
    "sg:city":"L\u00fcdenscheid",
    "sg:phone":"+49 2351/97850",
    "sg:postcode":"58515",
    "sg:province":"Nordrhein-Westfalen",
    "wof:name":"Otto Eichhoff Gmbh & Co. Kg",
    "wof:placetype":"venue"
},
  "geometry": {"coordinates":[7.573153,51.208469],"type":"Point"}
}