{
  "type": "Feature",
  "properties": {
    "iso:country":"DE",
    "sg:address":"Josefstaler Str. 30",
    "sg:city":"Schliersee",
    "sg:phone":"+49 8026/71506",
    "sg:postcode":"83727",
    "sg:province":"Bayern",
    "wof:name":"G\u00e4stehaus Josefsthal",
    "wof:placetype":"venue"
},
  "geometry": {"coordinates":[11.8842229843,47.6883964539],"type":"Point"}
}