{
  "type": "Feature",
  "properties": {
    "iso:country":"DE",
    "sg:address":"Marienstr. 1",
    "sg:city":"Sch\u00f6nwald",
    "sg:phone":"+49 9287/50166",
    "sg:postcode":"95173",
    "sg:province":"Bayern",
    "wof:name":"Hans Schr\u00f6gel",
    "wof:placetype":"venue"
},
  "geometry": {"coordinates":[12.0857400894,50.2002296448],"type":"Point"}
}