{
  "type": "Feature",
  "properties": {
    "iso:country":"DE",
    "sg:address":"Innere Wiener Str. 11",
    "sg:city":"M\u00fcnchen",
    "sg:postcode":"81667",
    "sg:province":"Bayern",
    "wof:name":"Cap-group Gmbh",
    "wof:placetype":"venue"
},
  "geometry": {"coordinates":[11.593468,48.133598],"type":"Point"}
}