{
  "type": "Feature",
  "properties": {
    "iso:country":"DE",
    "sg:address":"Lemberger Str. 41",
    "sg:city":"Pirmasens",
    "sg:phone":"+49 6331/876380",
    "sg:postcode":"66955",
    "sg:province":"Rheinland-Pfalz",
    "wof:name":"Plub Pirmasenser Luft- Und Badepark Gmbh",
    "wof:placetype":"venue"
},
  "geometry": {"coordinates":[7.6162657738,49.1907844543],"type":"Point"}
}