{
  "type": "Feature",
  "properties": {
    "iso:country":"DE",
    "sg:address":"Z\u00e4unweg 8",
    "sg:city":"Weinbach",
    "sg:phone":"+49 6471/94310",
    "sg:postcode":"35796",
    "sg:province":"Hessen",
    "wof:name":"Hti Bau- Und Industrie- Dienstleistungs Gmbh",
    "wof:placetype":"venue"
},
  "geometry": {"coordinates":[8.2909212112,50.4390678406],"type":"Point"}
}