{
  "type": "Feature",
  "properties": {
    "iso:country":"DE",
    "sg:address":"Erhardstr. 30",
    "sg:city":"Bad Kissingen",
    "sg:phone":"+49 971/3325",
    "sg:postcode":"97688",
    "sg:province":"Bayern",
    "wof:name":"E. Klein",
    "wof:placetype":"venue"
},
  "geometry": {"coordinates":[10.0851354599,50.2035369873],"type":"Point"}
}