{
  "type": "Feature",
  "properties": {
    "iso:country":"DE",
    "sg:address":"B\u00e4keweg 14 a",
    "sg:city":"Schmachtenhagen",
    "sg:postcode":"16515",
    "sg:province":"Brandenburg",
    "wof:name":"C. Wanzki Gmbh",
    "wof:placetype":"venue"
},
  "geometry": {"coordinates":[13.32095,52.770996],"type":"Point"}
}