{
  "type": "Feature",
  "properties": {
    "iso:country":"DE",
    "sg:address":"Dieselstr. 9",
    "sg:city":"Metzingen",
    "sg:phone":"+49 7123/96490",
    "sg:postcode":"72555",
    "sg:province":"Baden-W\u00fcrttemberg",
    "wof:name":"J. Wurster & T. Schletterer",
    "wof:placetype":"venue"
},
  "geometry": {"coordinates":[9.2707548141,48.5454711914],"type":"Point"}
}