{
  "type": "Feature",
  "properties": {
    "iso:country":"DE",
    "sg:address":"Haberl\u00e4nderstr. 1",
    "sg:city":"Altmannstein",
    "sg:phone":"+49 9446/360",
    "sg:postcode":"93336",
    "sg:province":"Bayern",
    "wof:name":"Katholisches Pfarramt St. Martinus",
    "wof:placetype":"venue"
},
  "geometry": {"coordinates":[11.6719379425,48.8802070618],"type":"Point"}
}