{
  "type": "Feature",
  "properties": {
    "iso:country":"DE",
    "sg:address":"Isselhorster Str. 374",
    "sg:city":"G\u00fctersloh",
    "sg:phone":"+49 5241/688660",
    "sg:postcode":"33334",
    "sg:province":"Nordrhein-Westfalen",
    "wof:name":"Design Markus T. Gmbh",
    "wof:placetype":"venue"
},
  "geometry": {"coordinates":[8.4217376709,51.9449958801],"type":"Point"}
}