{
  "type": "Feature",
  "properties": {
    "iso:country":"DE",
    "sg:address":"Marktstr. 10 - 14",
    "sg:city":"R\u00fcsselsheim",
    "sg:phone":"+49 4961/4224198",
    "sg:postcode":"65428",
    "sg:province":"Hessen",
    "wof:name":"Bank F\u00fcr Gemeinwirtschaft",
    "wof:placetype":"venue"
},
  "geometry": {"coordinates":[8.412224,49.994492],"type":"Point"}
}