{
  "type": "Feature",
  "properties": {
    "iso:country":"DE",
    "sg:address":"Parsevalstr. 7b",
    "sg:city":"D\u00fcsseldorf",
    "sg:phone":"+49 211/941551",
    "sg:postcode":"40468",
    "sg:province":"Nordrhein-Westfalen",
    "wof:name":"Jahn Reisen Gmbh",
    "wof:placetype":"venue"
},
  "geometry": {"coordinates":[6.7869858742,51.2773208618],"type":"Point"}
}