{
  "type": "Feature",
  "properties": {
    "iso:country":"DE",
    "sg:address":"Hallenberger Str. 19",
    "sg:city":"Medebach",
    "sg:phone":"+49 2982/41998",
    "sg:postcode":"59964",
    "sg:province":"Nordrhein-Westfalen",
    "wof:name":"Joes Bistro",
    "wof:placetype":"venue"
},
  "geometry": {"coordinates":[8.706987381,51.1943130493],"type":"Point"}
}