{
  "type": "Feature",
  "properties": {
    "iso:country":"DE",
    "sg:address":"Gottfried-Niermann-Str. 2",
    "sg:city":"Rheda-Wiedenbr\u00fcck",
    "sg:phone":"+49 5242/36222",
    "sg:postcode":"33378",
    "sg:province":"Nordrhein-Westfalen",
    "wof:name":"Inter Concept Franz Stohlmeyer Gmbh",
    "wof:placetype":"venue"
},
  "geometry": {"coordinates":[8.279291,51.821861],"type":"Point"}
}