{
  "type": "Feature",
  "properties": {
    "iso:country":"DE",
    "sg:address":"Eyller Str. 147",
    "sg:city":"Kerken",
    "sg:phone":"+49 2833/2201",
    "sg:postcode":"47647",
    "sg:province":"Nordrhein-Westfalen",
    "wof:name":"Alois Willmen",
    "wof:placetype":"venue"
},
  "geometry": {"coordinates":[6.373739,51.456554],"type":"Point"}
}