{
  "type": "Feature",
  "properties": {
    "iso:country":"DE",
    "sg:address":"Kapuzinergasse 29",
    "sg:city":"Breisach",
    "sg:phone":"+49 7667/93770",
    "sg:postcode":"79206",
    "sg:province":"Baden-W\u00fcrttemberg",
    "wof:name":"Pension-hotel Schlo\u00dfberg Fam. Tschugg",
    "wof:placetype":"venue"
},
  "geometry": {"coordinates":[7.5780200958,48.0323410034],"type":"Point"}
}