{
  "type": "Feature",
  "properties": {
    "iso:country":"DE",
    "sg:address":"K\u00f6stritzer Str. 13",
    "sg:city":"Bad Klosterlausnitz",
    "sg:phone":"+49 36601/41123",
    "sg:postcode":"07639",
    "sg:province":"Th\u00fcringen",
    "wof:name":"Hotel-restaurant Zu Den 3 Schw\u00e4nen",
    "wof:placetype":"venue"
},
  "geometry": {"coordinates":[11.8696908951,50.9140968323],"type":"Point"}
}