{
  "type": "Feature",
  "properties": {
    "iso:country":"DE",
    "sg:address":"Hospeltstr. 39",
    "sg:city":"K\u00f6ln",
    "sg:phone":"+49 221/9541532",
    "sg:postcode":"50825",
    "sg:province":"Nordrhein-Westfalen",
    "wof:name":"Cutup Gmbh",
    "wof:placetype":"venue"
},
  "geometry": {"coordinates":[6.9069461823,50.9538002014],"type":"Point"}
}