{
  "type": "Feature",
  "properties": {
    "iso:country":"DE",
    "sg:address":"G\u00e4rtnersberg 7",
    "sg:city":"Pfullendorf",
    "sg:phone":"+49 7552/8918",
    "sg:postcode":"88630",
    "sg:province":"Baden-W\u00fcrttemberg",
    "wof:name":"R. Und C. Weig Masseure",
    "wof:placetype":"venue"
},
  "geometry": {"coordinates":[9.261688,47.921276],"type":"Point"}
}