{
  "type": "Feature",
  "properties": {
    "iso:country":"DE",
    "sg:address":"Am S\u00fcdpark 7",
    "sg:city":"Neuburg",
    "sg:phone":"+49 8431/38184",
    "sg:postcode":"86633",
    "sg:province":"Bayern",
    "wof:name":"D2 Shop Neuburg",
    "wof:placetype":"venue"
},
  "geometry": {"coordinates":[11.1681108475,48.7216072083],"type":"Point"}
}