{
  "type": "Feature",
  "properties": {
    "iso:country":"DE",
    "sg:address":"Heerweg 108",
    "sg:city":"Monheim",
    "sg:phone":"+49 2173/30347",
    "sg:postcode":"40789",
    "sg:province":"Nordrhein-Westfalen",
    "wof:name":"Bodo Mischker",
    "wof:placetype":"venue"
},
  "geometry": {"coordinates":[6.890413,51.078575],"type":"Point"}
}