{
  "type": "Feature",
  "properties": {
    "iso:country":"DE",
    "sg:address":"Jobplatz 7",
    "sg:city":"Neunburg",
    "sg:phone":"+49 9672/836",
    "sg:postcode":"92431",
    "sg:province":"Bayern",
    "wof:name":"Heinz Becher Bekleidung",
    "wof:placetype":"venue"
},
  "geometry": {"coordinates":[12.381893158,49.3488502502],"type":"Point"}
}