{
  "type": "Feature",
  "properties": {
    "iso:country":"DE",
    "sg:address":"Schweriner Str. 43",
    "sg:city":"Rostock",
    "sg:phone":"+49 381/83908",
    "sg:postcode":"18069",
    "sg:province":"Mecklenburg-Vorpommern",
    "wof:name":"Maler- Und Korrosionsschutz Bunte Palette Gmbh",
    "wof:placetype":"venue"
},
  "geometry": {"coordinates":[12.094307,54.096661],"type":"Point"}
}