{
  "type": "Feature",
  "properties": {
    "iso:country":"DE",
    "sg:address":"Kirburger Weg 123 a",
    "sg:city":"K\u00f6ln",
    "sg:phone":"+49 221/798919",
    "sg:postcode":"50767",
    "sg:province":"Nordrhein-Westfalen",
    "wof:name":"Bettina Sahm-schneider Masseurin",
    "wof:placetype":"venue"
},
  "geometry": {"coordinates":[6.884946,51.004501],"type":"Point"}
}