{
  "type": "Feature",
  "properties": {
    "iso:country":"DE",
    "sg:address":"Freiheitstr. 12",
    "sg:city":"Wuppertal",
    "sg:phone":"+49 202/641136",
    "sg:postcode":"42277",
    "sg:province":"Nordrhein-Westfalen",
    "wof:name":"Horst M\u00f6llers Ingenieur",
    "wof:placetype":"venue"
},
  "geometry": {"coordinates":[7.2209849358,51.2791976929],"type":"Point"}
}