{
  "type": "Feature",
  "properties": {
    "iso:country":"DE",
    "sg:address":"Sommerstr. 10",
    "sg:city":"Lohr",
    "sg:phone":"+49 9352/2897",
    "sg:postcode":"97816",
    "sg:province":"Bayern",
    "wof:name":"Grete M\u00fcnz",
    "wof:placetype":"venue"
},
  "geometry": {"coordinates":[9.5877971649,49.993888855],"type":"Point"}
}