{
  "type": "Feature",
  "properties": {
    "iso:country":"DE",
    "sg:address":"Theaterstr. 1",
    "sg:city":"Halberstadt",
    "sg:phone":"+49 3941/27605",
    "sg:postcode":"38820",
    "sg:province":"Sachsen-Anhalt",
    "wof:name":"K. Schupra\u00df",
    "wof:placetype":"venue"
},
  "geometry": {"coordinates":[11.062112,51.895],"type":"Point"}
}