{
  "type": "Feature",
  "properties": {
    "iso:country":"DE",
    "sg:address":"Lutherstr. 60",
    "sg:city":"Geldern",
    "sg:phone":"+49 2831/88876",
    "sg:postcode":"47608",
    "sg:province":"Nordrhein-Westfalen",
    "wof:name":"J\u00fcrgen Bousardt Masseur",
    "wof:placetype":"venue"
},
  "geometry": {"coordinates":[6.345075,51.515331],"type":"Point"}
}