{
  "type": "Feature",
  "properties": {
    "iso:country":"DE",
    "sg:address":"Max-Baermann-Str. 2",
    "sg:city":"Bergisch Gladbach",
    "sg:postcode":"51429",
    "sg:province":"Nordrhein-Westfalen",
    "wof:name":"Bettenstudio Rubin Gmbh",
    "wof:placetype":"venue"
},
  "geometry": {"coordinates":[7.1928181648,50.9673919678],"type":"Point"}
}