{
  "type": "Feature",
  "properties": {
    "iso:country":"DE",
    "sg:address":"Beselerstr. 32a",
    "sg:city":"Hamburg",
    "sg:postcode":"22607",
    "sg:province":"Hamburg",
    "wof:name":"J\u00f6rn Becker Immobilien Immobilienmakler",
    "wof:placetype":"venue"
},
  "geometry": {"coordinates":[9.8819570541,53.5631103516],"type":"Point"}
}