{
  "type": "Feature",
  "properties": {
    "iso:country":"DE",
    "sg:address":"\u00dcber dem Hagen 17",
    "sg:city":"Salzhemmendorf",
    "sg:phone":"+49 5186/957007",
    "sg:postcode":"31020",
    "sg:province":"Niedersachsen",
    "wof:name":"H. Pommerening",
    "wof:placetype":"venue"
},
  "geometry": {"coordinates":[9.6215305328,52.0151023865],"type":"Point"}
}