{
  "type": "Feature",
  "properties": {
    "iso:country":"DE",
    "sg:address":"Amselweg 6",
    "sg:city":"Pahlen",
    "sg:phone":"+49 4803/6111",
    "sg:postcode":"25794",
    "sg:province":"Schleswig-Holstein",
    "wof:name":"Norbert M\u00f6ller Fenster Roll\u00e4den T\u00fcren E. K.",
    "wof:placetype":"venue"
},
  "geometry": {"coordinates":[9.298331,54.266457],"type":"Point"}
}