{
  "type": "Feature",
  "properties": {
    "iso:country":"DE",
    "sg:address":"Am Spik 19",
    "sg:city":"Bochum",
    "sg:phone":"+49 234/381469",
    "sg:postcode":"44803",
    "sg:province":"Nordrhein-Westfalen",
    "wof:name":"Kurt Schmitz",
    "wof:placetype":"venue"
},
  "geometry": {"coordinates":[7.2357859612,51.4651298523],"type":"Point"}
}