{
  "type": "Feature",
  "properties": {
    "iso:country":"DE",
    "sg:address":"Hemmstr. 350",
    "sg:city":"Bremen",
    "sg:phone":"+49 421/252448",
    "sg:postcode":"28215",
    "sg:province":"Bremen",
    "wof:name":"Max Klohse Inh. Lutz Peter R\u00f6lle",
    "wof:placetype":"venue"
},
  "geometry": {"coordinates":[8.815202713,53.1027030945],"type":"Point"}
}