{
  "type": "Feature",
  "properties": {
    "iso:country":"DE",
    "sg:address":"Am Schilde 12",
    "sg:city":"Osterode",
    "sg:phone":"+49 5522/3311",
    "sg:postcode":"37520",
    "sg:province":"Niedersachsen",
    "wof:name":"Werner Kaminski Inh. B. Lehner",
    "wof:placetype":"venue"
},
  "geometry": {"coordinates":[10.2533283234,51.7273902893],"type":"Point"}
}