{
  "type": "Feature",
  "properties": {
    "iso:country":"DE",
    "sg:address":"Unter Lehr 12",
    "sg:city":"Bad D\u00fcrrheim",
    "sg:phone":"+49 7726/6407",
    "sg:postcode":"78073",
    "sg:province":"Baden-W\u00fcrttemberg",
    "wof:name":"Arno Winkler",
    "wof:placetype":"venue"
},
  "geometry": {"coordinates":[8.5380516052,48.0219650269],"type":"Point"}
}