{
  "type": "Feature",
  "properties": {
    "iso:country":"DE",
    "sg:address":"Gathe 50",
    "sg:city":"Wuppertal",
    "sg:phone":"+49 202/451930",
    "sg:postcode":"42107",
    "sg:province":"Nordrhein-Westfalen",
    "wof:name":"Disco Must",
    "wof:placetype":"venue"
},
  "geometry": {"coordinates":[7.147465,51.262066],"type":"Point"}
}