{
  "type": "Feature",
  "properties": {
    "iso:country":"DE",
    "sg:address":"Horster Str. 2",
    "sg:city":"L\u00fcbbecke",
    "sg:phone":"+49 5741/6487",
    "sg:postcode":"32312",
    "sg:province":"Nordrhein-Westfalen",
    "wof:name":"Christels Cafe-stube",
    "wof:placetype":"venue"
},
  "geometry": {"coordinates":[8.707552,52.314075],"type":"Point"}
}