{
  "type": "Feature",
  "properties": {
    "iso:country":"DE",
    "sg:address":"Eichendorffstr. 23 a",
    "sg:city":"Braunlage",
    "sg:phone":"+49 5520/1303",
    "sg:postcode":"38700",
    "sg:province":"Niedersachsen",
    "wof:name":"Wolf E. Franke",
    "wof:placetype":"venue"
},
  "geometry": {"coordinates":[10.6061134338,51.7226333618],"type":"Point"}
}