{
  "type": "Feature",
  "properties": {
    "iso:country":"DE",
    "sg:address":"Prager Str. 17",
    "sg:city":"Leipzig",
    "sg:phone":"+49 341/9903843",
    "sg:postcode":"04103",
    "sg:province":"Sachsen",
    "wof:name":"Epas Ressourcenscho- Nende Produkte Gmbh",
    "wof:placetype":"venue"
},
  "geometry": {"coordinates":[12.393509,51.333626],"type":"Point"}
}