{
  "type": "Feature",
  "properties": {
    "iso:country":"DE",
    "sg:address":"Ziegenhainer Str. 24",
    "sg:city":"Wabern",
    "sg:phone":"+49 5683/457",
    "sg:postcode":"34590",
    "sg:province":"Hessen",
    "wof:name":"B. F\u00f6rster Gmbh",
    "wof:placetype":"venue"
},
  "geometry": {"coordinates":[9.349111557,51.1000137329],"type":"Point"}
}