{
  "type": "Feature",
  "properties": {
    "iso:country":"DE",
    "sg:address":"Drosselweg 1",
    "sg:city":"Wiefelstede",
    "sg:phone":"+49 4402/961915",
    "sg:postcode":"26215",
    "sg:province":"Niedersachsen",
    "wof:name":"Sonnencollector",
    "wof:placetype":"venue"
},
  "geometry": {"coordinates":[8.110839,53.252361],"type":"Point"}
}