{
  "type": "Feature",
  "properties": {
    "iso:country":"DE",
    "sg:address":"Im Reuter 3",
    "sg:city":"Sinsheim",
    "sg:phone":"+49 7261/12748",
    "sg:postcode":"74889",
    "sg:province":"Baden-W\u00fcrttemberg",
    "wof:name":"Musik- Und Klavierhaus Weitz",
    "wof:placetype":"venue"
},
  "geometry": {"coordinates":[8.881321907,49.264213562],"type":"Point"}
}