{
  "type": "Feature",
  "properties": {
    "iso:country":"DE",
    "sg:address":"Fuchsweg 9",
    "sg:city":"J\u00fclich",
    "sg:phone":"+49 2461/55156",
    "sg:postcode":"52428",
    "sg:province":"Nordrhein-Westfalen",
    "wof:name":"R. Van Kann Ingenieur",
    "wof:placetype":"venue"
},
  "geometry": {"coordinates":[6.3299808502,50.9290084839],"type":"Point"}
}