{
  "type": "Feature",
  "properties": {
    "iso:country":"DE",
    "sg:address":"Innere Laufer Gasse 14",
    "sg:city":"N\u00fcrnberg",
    "sg:phone":"+49 911/227848",
    "sg:postcode":"90403",
    "sg:province":"Bayern",
    "wof:name":"Rolf-dieter Eiben Heilpraktiker",
    "wof:placetype":"venue"
},
  "geometry": {"coordinates":[11.0822067261,49.4556884766],"type":"Point"}
}