{
  "type": "Feature",
  "properties": {
    "iso:country":"DE",
    "sg:address":"Am Farrnbach 17",
    "sg:city":"Cadolzburg",
    "sg:phone":"+49 9103/1476",
    "sg:postcode":"90556",
    "sg:province":"Bayern",
    "wof:name":"Georg-ammon- Bauunternehmung- Ohg",
    "wof:placetype":"venue"
},
  "geometry": {"coordinates":[10.86813,49.476624],"type":"Point"}
}