{
  "type": "Feature",
  "properties": {
    "iso:country":"DE",
    "sg:address":"Alt-Wittenau 39",
    "sg:city":"Berlin",
    "sg:phone":"+49 30/4113550",
    "sg:postcode":"13437",
    "sg:province":"Berlin",
    "wof:name":"Padme Naturkosmetik Manfred Riemer",
    "wof:placetype":"venue"
},
  "geometry": {"coordinates":[13.3241949081,52.5929946899],"type":"Point"}
}