{
  "type": "Feature",
  "properties": {
    "iso:country":"DE",
    "sg:address":"Titiseestr. 3",
    "sg:city":"Berlin",
    "sg:phone":"+49 30/4023377",
    "sg:postcode":"13469",
    "sg:province":"Berlin",
    "wof:name":"Renate Priebe",
    "wof:placetype":"venue"
},
  "geometry": {"coordinates":[13.334945,52.609787],"type":"Point"}
}