{
  "type": "Feature",
  "properties": {
    "iso:country":"DE",
    "sg:address":"Elchesheimer Str. 25",
    "sg:city":"Steinmauern",
    "sg:phone":"+49 7222/23976",
    "sg:postcode":"76479",
    "sg:province":"Baden-W\u00fcrttemberg",
    "wof:name":"Wolfgang Werle",
    "wof:placetype":"venue"
},
  "geometry": {"coordinates":[8.196582,48.902912],"type":"Point"}
}