{
  "type": "Feature",
  "properties": {
    "iso:country":"DE",
    "sg:address":"Hermannstr. 1",
    "sg:city":"Baden-Baden",
    "sg:phone":"+49 4972/2125882",
    "sg:postcode":"76530",
    "sg:province":"Baden-W\u00fcrttemberg",
    "wof:name":"Deko-dienst Mathey Gmbh",
    "wof:placetype":"venue"
},
  "geometry": {"coordinates":[8.22783,48.771122],"type":"Point"}
}