{
  "type": "Feature",
  "properties": {
    "iso:country":"DE",
    "sg:address":"Hochstr. 23",
    "sg:city":"Saarlouis",
    "sg:phone":"+49 6831/80840",
    "sg:postcode":"66740",
    "sg:province":"Saarland",
    "wof:name":"Ms Immobilien Gmbh",
    "wof:placetype":"venue"
},
  "geometry": {"coordinates":[6.750089,49.335682],"type":"Point"}
}