{
  "type": "Feature",
  "properties": {
    "iso:country":"DE",
    "sg:address":"Kr\u00f6peliner Str. 8",
    "sg:city":"Rostock",
    "sg:phone":"+49 381/685875",
    "sg:postcode":"18055",
    "sg:province":"Mecklenburg-Vorpommern",
    "wof:name":"Mobikom Dahncke Gmbh & Co. Kg",
    "wof:placetype":"venue"
},
  "geometry": {"coordinates":[12.138413,54.088654],"type":"Point"}
}