{
  "type": "Feature",
  "properties": {
    "iso:country":"DE",
    "sg:address":"Fuldatalstr. 185",
    "sg:city":"Kassel",
    "sg:phone":"+49 561/876280",
    "sg:postcode":"34125",
    "sg:province":"Hessen",
    "wof:name":"Spiske Baugesellschaft Mbh",
    "wof:placetype":"venue"
},
  "geometry": {"coordinates":[9.544667,51.329128],"type":"Point"}
}