{
  "type": "Feature",
  "properties": {
    "iso:country":"DE",
    "sg:address":"Erlengrund 36",
    "sg:city":"Barmstedt",
    "sg:phone":"+49 4123/6964",
    "sg:postcode":"25355",
    "sg:province":"Schleswig-Holstein",
    "wof:name":"Raimund Bre\u00dflein Ingenieur",
    "wof:placetype":"venue"
},
  "geometry": {"coordinates":[9.7616491318,53.7946128845],"type":"Point"}
}