{
  "type": "Feature",
  "properties": {
    "iso:country":"DE",
    "sg:address":"Hauptstr. 73",
    "sg:city":"Crossen",
    "sg:phone":"+49 3727/2492",
    "sg:postcode":"09306",
    "sg:province":"Sachsen",
    "wof:name":"Klaus Kern",
    "wof:placetype":"venue"
},
  "geometry": {"coordinates":[12.826762,51.027431],"type":"Point"}
}