{
  "type": "Feature",
  "properties": {
    "iso:country":"DE",
    "sg:address":"Stuttgarter Str. 13",
    "sg:city":"Lorch",
    "sg:phone":"+49 7172/914081",
    "sg:postcode":"73547",
    "sg:province":"Baden-W\u00fcrttemberg",
    "wof:name":"Jo-pippos Pizzaexpress",
    "wof:placetype":"venue"
},
  "geometry": {"coordinates":[9.6866436005,48.7971115112],"type":"Point"}
}