{
  "type": "Feature",
  "properties": {
    "iso:country":"DE",
    "sg:address":"Bedernauer Str. 18",
    "sg:city":"Breitenbrunn",
    "sg:phone":"+49 8263/1035",
    "sg:postcode":"87739",
    "sg:province":"Bayern",
    "wof:name":"J. M\u00fcller",
    "wof:placetype":"venue"
},
  "geometry": {"coordinates":[10.400494,48.134697],"type":"Point"}
}