{
  "type": "Feature",
  "properties": {
    "iso:country":"DE",
    "sg:address":"Kaiserstr. 22a",
    "sg:city":"Bruchsal",
    "sg:phone":"+49 7251/14877",
    "sg:postcode":"76646",
    "sg:province":"Baden-W\u00fcrttemberg",
    "wof:name":"J. Wallner",
    "wof:placetype":"venue"
},
  "geometry": {"coordinates":[8.5959730148,49.1260108948],"type":"Point"}
}