{
  "type": "Feature",
  "properties": {
    "iso:country":"DE",
    "sg:address":"Nonnenweg 3",
    "sg:city":"Flein",
    "sg:phone":"+49 7131/570597",
    "sg:postcode":"74223",
    "sg:province":"Baden-W\u00fcrttemberg",
    "wof:name":"Kleintierzuchtverein Z 47 Manfred M\u00f6hle",
    "wof:placetype":"venue"
},
  "geometry": {"coordinates":[9.2089147568,49.1038665771],"type":"Point"}
}