{
  "type": "Feature",
  "properties": {
    "iso:country":"DE",
    "sg:address":"Provinzstr. 56",
    "sg:city":"Grevenbroich",
    "sg:phone":"+49 2181/44917",
    "sg:postcode":"41517",
    "sg:province":"Nordrhein-Westfalen",
    "wof:name":"Interproof Hoster Gmbh",
    "wof:placetype":"venue"
},
  "geometry": {"coordinates":[6.565151,51.069195],"type":"Point"}
}