{
  "type": "Feature",
  "properties": {
    "iso:country":"DE",
    "sg:address":"B\u00e4ckerweg 33",
    "sg:city":"Mannheim",
    "sg:phone":"+49 621/738747",
    "sg:postcode":"68309",
    "sg:province":"Baden-W\u00fcrttemberg",
    "wof:name":"Heinrich Schrauth",
    "wof:placetype":"venue"
},
  "geometry": {"coordinates":[8.5095386505,49.5031471252],"type":"Point"}
}