{
  "type": "Feature",
  "properties": {
    "iso:country":"DE",
    "sg:address":"Enggasse 5",
    "sg:city":"Mainz",
    "sg:phone":"+49 6136/42971",
    "sg:postcode":"55129",
    "sg:province":"Rheinland-Pfalz",
    "wof:name":"E. Kantner",
    "wof:placetype":"venue"
},
  "geometry": {"coordinates":[8.2451944351,49.9129066467],"type":"Point"}
}