{
  "type": "Feature",
  "properties": {
    "iso:country":"DE",
    "sg:address":"Hebelstra\u00dfe 28",
    "sg:city":"Hausen i.W.",
    "sg:phone":"+49 8722/4311",
    "sg:postcode":"79688",
    "sg:province":"Baden-W\u00fcrttemberg",
    "wof:name":"Grund- Und Hauptschule Hausen Im Wiesental",
    "wof:placetype":"venue"
},
  "geometry": {"coordinates":[7.84213,47.682777],"type":"Point"}
}