{
  "type": "Feature",
  "properties": {
    "iso:country":"DE",
    "sg:address":"Kreienhoopsberg 18 a",
    "sg:city":"Hamburg",
    "sg:phone":"+49 40/6116660",
    "sg:postcode":"22399",
    "sg:province":"Hamburg",
    "wof:name":"Accento Handelsges. Mbh",
    "wof:placetype":"venue"
},
  "geometry": {"coordinates":[10.070064,53.67585],"type":"Point"}
}