{
  "type": "Feature",
  "properties": {
    "iso:country":"DE",
    "sg:address":"Am Lindenhof 40",
    "sg:city":"Schm\u00f6lln",
    "sg:phone":"+49 4934/491310",
    "sg:postcode":"04626",
    "sg:province":"Th\u00fcringen",
    "wof:name":"Wolf Gmbh",
    "wof:placetype":"venue"
},
  "geometry": {"coordinates":[12.3496389389,50.8784675598],"type":"Point"}
}