{
  "type": "Feature",
  "properties": {
    "iso:country":"DE",
    "sg:address":"Hauptstr. 17",
    "sg:city":"Heldrungen",
    "sg:phone":"+49 34673/91255",
    "sg:postcode":"06577",
    "sg:province":"Th\u00fcringen",
    "wof:name":"Wilhelm-mei\u00dfner-apotheke Inh. Siegfried Breuhauer",
    "wof:placetype":"venue"
},
  "geometry": {"coordinates":[11.21793,51.301453],"type":"Point"}
}