{
  "type": "Feature",
  "properties": {
    "iso:country":"DE",
    "sg:address":"Johann-Peter-Hebel-Str. 5",
    "sg:city":"Endingen",
    "sg:phone":"+49 7642/6439",
    "sg:postcode":"79346",
    "sg:province":"Baden-W\u00fcrttemberg",
    "wof:name":"G. Str\u00fctt",
    "wof:placetype":"venue"
},
  "geometry": {"coordinates":[7.7043018341,48.1479949951],"type":"Point"}
}