{
  "type": "Feature",
  "properties": {
    "iso:country":"DE",
    "sg:address":"Siegfriedstr. 384",
    "sg:city":"Heppenheim",
    "sg:phone":"+49 6252/4263",
    "sg:postcode":"64646",
    "sg:province":"Hessen",
    "wof:name":"Hans Unger",
    "wof:placetype":"venue"
},
  "geometry": {"coordinates":[8.690111,49.646435],"type":"Point"}
}