{
  "type": "Feature",
  "properties": {
    "iso:country":"DE",
    "sg:address":"Buchenstr. 7",
    "sg:city":"Eschau",
    "sg:phone":"+49 9374/7327",
    "sg:postcode":"63863",
    "sg:province":"Bayern",
    "wof:name":"Pe-tex Gmbh",
    "wof:placetype":"venue"
},
  "geometry": {"coordinates":[9.261663,49.816933],"type":"Point"}
}