{
  "type": "Feature",
  "properties": {
    "iso:country":"DE",
    "sg:address":"Saarbr\u00fccker Str. 120",
    "sg:city":"Sch\u00f6nenberg-K\u00fcbelberg",
    "sg:postcode":"66901",
    "sg:province":"Rheinland-Pfalz",
    "wof:name":"Buser-erbach Gmbh",
    "wof:placetype":"venue"
},
  "geometry": {"coordinates":[7.370431,49.409031],"type":"Point"}
}