{
  "type": "Feature",
  "properties": {
    "iso:country":"DE",
    "sg:address":"Hilgesdorfer Str. 4",
    "sg:city":"Flechtingen",
    "sg:phone":"+49 39054/27207",
    "sg:postcode":"39345",
    "sg:province":"Sachsen-Anhalt",
    "wof:name":"Metallbau Andreas Bartsch Kg",
    "wof:placetype":"venue"
},
  "geometry": {"coordinates":[11.22544384,52.3265266418],"type":"Point"}
}