{
  "type": "Feature",
  "properties": {
    "iso:country":"DE",
    "sg:address":"Gutenbergstr 5",
    "sg:city":"Hemmingen",
    "sg:phone":"+49 511/4102950",
    "sg:postcode":"30966",
    "sg:province":"Niedersachsen",
    "wof:name":"Sauer Walzenfabriken Gmbh & Co Kg",
    "wof:placetype":"venue"
},
  "geometry": {"coordinates":[9.7231988907,52.3221588135],"type":"Point"}
}