{
  "type": "Feature",
  "properties": {
    "iso:country":"DE",
    "sg:address":"M\u00fcssenweg 19",
    "sg:city":"Voerde",
    "sg:phone":"+49 2855/82508",
    "sg:postcode":"46562",
    "sg:province":"Nordrhein-Westfalen",
    "wof:name":"E. Van H\u00fcth",
    "wof:placetype":"venue"
},
  "geometry": {"coordinates":[6.620443,51.60218],"type":"Point"}
}