{
  "type": "Feature",
  "properties": {
    "iso:country":"DE",
    "sg:address":"Weinbergstr. 2",
    "sg:city":"Linnich",
    "sg:phone":"+49 2462/6691",
    "sg:postcode":"52441",
    "sg:province":"Nordrhein-Westfalen",
    "wof:name":"Andreas M\u00fcller",
    "wof:placetype":"venue"
},
  "geometry": {"coordinates":[6.328415,50.970085],"type":"Point"}
}