{
  "type": "Feature",
  "properties": {
    "iso:country":"DE",
    "sg:address":"Hinter den H\u00f6fen 351",
    "sg:city":"Geisleden",
    "sg:phone":"+49 36084/80028",
    "sg:postcode":"37308",
    "sg:province":"Th\u00fcringen",
    "wof:name":"M. Hartung",
    "wof:placetype":"venue"
},
  "geometry": {"coordinates":[10.193064,51.350098],"type":"Point"}
}