{
  "type": "Feature",
  "properties": {
    "iso:country":"DE",
    "sg:address":"Langer Kamp 14",
    "sg:city":"Hildesheim",
    "sg:phone":"+49 5121",
    "sg:postcode":"31139",
    "sg:province":"Niedersachsen",
    "wof:name":"Bau Tec Hausbau Hildesheim Massivhaus Holzhaus",
    "wof:placetype":"venue"
},
  "geometry": {"coordinates":[9.9600849152,52.1621437073],"type":"Point"}
}