{
  "type": "Feature",
  "properties": {
    "iso:country":"DE",
    "sg:address":"Braugasse 11",
    "sg:city":"Lich",
    "sg:phone":"+49 6404/2227",
    "sg:postcode":"35423",
    "sg:province":"Hessen",
    "wof:name":"Rudolf Jung",
    "wof:placetype":"venue"
},
  "geometry": {"coordinates":[8.8186645508,50.519657135],"type":"Point"}
}