{
  "type": "Feature",
  "properties": {
    "iso:country":"DE",
    "sg:address":"Rennweg 163",
    "sg:city":"Landshut",
    "sg:phone":"+49 871/61218",
    "sg:postcode":"84034",
    "sg:province":"Bayern",
    "wof:name":"Glas Judenhofer Gmbh",
    "wof:placetype":"venue"
},
  "geometry": {"coordinates":[12.1186800003,48.5388298035],"type":"Point"}
}