{
  "type": "Feature",
  "properties": {
    "iso:country":"DE",
    "sg:address":"Kellerstr. 69",
    "sg:city":"Rellingen",
    "sg:phone":"+49 4101/31138",
    "sg:postcode":"25462",
    "sg:province":"Schleswig-Holstein",
    "wof:name":"Adolf M\u00e4necke",
    "wof:placetype":"venue"
},
  "geometry": {"coordinates":[9.87241,53.633888],"type":"Point"}
}