{
  "type": "Feature",
  "properties": {
    "iso:country":"DE",
    "sg:address":"Innere M\u00fcnchener Str. 36",
    "sg:city":"Landshut",
    "sg:postcode":"84036",
    "sg:province":"Bayern",
    "wof:name":"Alois Harlander Gmbh & Co. Kg",
    "wof:placetype":"venue"
},
  "geometry": {"coordinates":[12.1451301575,48.5293235779],"type":"Point"}
}