{
  "type": "Feature",
  "properties": {
    "iso:country":"DE",
    "sg:address":"Kienbachstr. 7",
    "sg:city":"Herrsching",
    "sg:phone":"+49 8152/1237",
    "sg:postcode":"82211",
    "sg:province":"Bayern",
    "wof:name":"Fritz Sievers",
    "wof:placetype":"venue"
},
  "geometry": {"coordinates":[11.1740274429,47.9977912903],"type":"Point"}
}