{
  "type": "Feature",
  "properties": {
    "iso:country":"DE",
    "sg:address":"Zwischen Landwehr 23",
    "sg:city":"Bad Laasphe",
    "sg:phone":"+49 2752/1418",
    "sg:postcode":"57334",
    "sg:province":"Nordrhein-Westfalen",
    "wof:name":"Rassegefl\u00fcgelz\u00fcchterverein 1906 E. V. Bad Laasphe",
    "wof:placetype":"venue"
},
  "geometry": {"coordinates":[8.4221124649,50.9317359924],"type":"Point"}
}