{
  "type": "Feature",
  "properties": {
    "iso:country":"DE",
    "sg:address":"Ehrensteiner Str. 13",
    "sg:city":"Neustadt",
    "sg:phone":"+49 2683/31060",
    "sg:postcode":"53577",
    "sg:province":"Rheinland-Pfalz",
    "wof:name":"Franz Etscheid",
    "wof:placetype":"venue"
},
  "geometry": {"coordinates":[7.440012,50.618034],"type":"Point"}
}