{
  "type": "Feature",
  "properties": {
    "iso:country":"DE",
    "sg:address":"Franckstr. 2",
    "sg:city":"Vaihingen",
    "sg:phone":"+49 7042/943030",
    "sg:postcode":"71665",
    "sg:province":"Baden-W\u00fcrttemberg",
    "wof:name":"B.m.g. Raum-design Gmbh",
    "wof:placetype":"venue"
},
  "geometry": {"coordinates":[8.9598264694,48.9305686951],"type":"Point"}
}