{
  "type": "Feature",
  "properties": {
    "iso:country":"DE",
    "sg:address":"T\u00f6pferstr. 80",
    "sg:city":"Altenstadt",
    "sg:phone":"+49 6047/7056",
    "sg:postcode":"63674",
    "sg:province":"Hessen",
    "wof:name":"Heil Import Gmbh",
    "wof:placetype":"venue"
},
  "geometry": {"coordinates":[8.95186,50.271118],"type":"Point"}
}