{
  "type": "Feature",
  "properties": {
    "iso:country":"DE",
    "sg:address":"Rathausstr. 30",
    "sg:city":"Lauda-K\u00f6nigshofen",
    "sg:phone":"+49 9343/1030",
    "sg:postcode":"97922",
    "sg:province":"Baden-W\u00fcrttemberg",
    "wof:name":"Dieter Braun",
    "wof:placetype":"venue"
},
  "geometry": {"coordinates":[9.701893,49.570312],"type":"Point"}
}