{
  "type": "Feature",
  "properties": {
    "iso:country":"DE",
    "sg:address":"Gr\u00fcnlandweg 10",
    "sg:city":"Iserlohn",
    "sg:phone":"+49 2371/94800",
    "sg:postcode":"58640",
    "sg:province":"Nordrhein-Westfalen",
    "wof:name":"Oras Gmbh & Co. Kg",
    "wof:placetype":"venue"
},
  "geometry": {"coordinates":[7.712237,51.419468],"type":"Point"}
}