{
  "type": "Feature",
  "properties": {
    "iso:country":"DE",
    "sg:address":"Spandauer Str. 12",
    "sg:city":"Bovenden",
    "sg:phone":"+49 5593/999880",
    "sg:postcode":"37120",
    "sg:province":"Niedersachsen",
    "wof:name":"Paulsen & Zinkel Gmbh",
    "wof:placetype":"venue"
},
  "geometry": {"coordinates":[9.8740434647,51.5881843567],"type":"Point"}
}