{
  "type": "Feature",
  "properties": {
    "iso:country":"DE",
    "sg:address":"Boschstr. 2",
    "sg:city":"Malsch",
    "sg:phone":"+49 4972/467040",
    "sg:postcode":"76316",
    "sg:province":"Baden-W\u00fcrttemberg",
    "wof:name":"Volta Gmbh",
    "wof:placetype":"venue"
},
  "geometry": {"coordinates":[8.3191785812,48.8907699585],"type":"Point"}
}