{
  "type": "Feature",
  "properties": {
    "iso:country":"DE",
    "sg:address":"Am G\u00e4nsberg 16 a",
    "sg:city":"Wiesbaden",
    "sg:phone":"+49 611/541336",
    "sg:postcode":"65207",
    "sg:province":"Hessen",
    "wof:name":"E. Kruse",
    "wof:placetype":"venue"
},
  "geometry": {"coordinates":[8.27476,50.111568],"type":"Point"}
}