{
  "type": "Feature",
  "properties": {
    "iso:country":"DE",
    "sg:address":"Kirchstr. 12",
    "sg:city":"Langenbach",
    "sg:phone":"+49 8761/2548",
    "sg:postcode":"85416",
    "sg:province":"Bayern",
    "wof:name":"K. Wiest",
    "wof:placetype":"venue"
},
  "geometry": {"coordinates":[11.8751802444,48.4273338318],"type":"Point"}
}