{
  "type": "Feature",
  "properties": {
    "iso:country":"DE",
    "sg:address":"Kleine Flurstr. 8",
    "sg:city":"Remscheid",
    "sg:phone":"+49 2191/30685",
    "sg:postcode":"42859",
    "sg:province":"Nordrhein-Westfalen",
    "wof:name":"Rudi Harms U. Peter Pfeifer",
    "wof:placetype":"venue"
},
  "geometry": {"coordinates":[7.1913890839,51.1656494141],"type":"Point"}
}