{
  "type": "Feature",
  "properties": {
    "iso:country":"DE",
    "sg:address":"Weilerstrasse 16-18",
    "sg:city":"Lenningen/Hochwang",
    "sg:phone":"+49 7026",
    "sg:postcode":"73268",
    "sg:province":"Baden-W\u00fcrttemberg",
    "wof:name":"Dieterich-feine-backwaren U. Weihnachtsb\u00e4ckerei C",
    "wof:placetype":"venue"
},
  "geometry": {"coordinates":[9.432737,48.557598],"type":"Point"}
}