{
  "type": "Feature",
  "properties": {
    "iso:country":"DE",
    "sg:address":"Augustenstr. 80",
    "sg:city":"M\u00fcnchen",
    "sg:phone":"+49 89/5236166",
    "sg:postcode":"80333",
    "sg:province":"Bayern",
    "wof:name":"Anne-dore Coiffeur",
    "wof:placetype":"venue"
},
  "geometry": {"coordinates":[11.5640850067,48.1505661011],"type":"Point"}
}