{
  "type": "Feature",
  "properties": {
    "iso:country":"DE",
    "sg:address":"Langenauer Weg 17",
    "sg:city":"Neenstetten",
    "sg:postcode":"89189",
    "sg:province":"Baden-W\u00fcrttemberg",
    "wof:name":"Holzbau Bunz Gmbh",
    "wof:placetype":"venue"
},
  "geometry": {"coordinates":[10.0226783752,48.5429840088],"type":"Point"}
}