{
  "type": "Feature",
  "properties": {
    "iso:country":"DE",
    "sg:address":"Siemsstr. 4",
    "sg:city":"Braunschweig",
    "sg:phone":"+49 5307/2796",
    "sg:postcode":"38110",
    "sg:province":"Niedersachsen",
    "wof:name":"Bernd Heidorn",
    "wof:placetype":"venue"
},
  "geometry": {"coordinates":[10.516551,52.320717],"type":"Point"}
}