{
  "type": "Feature",
  "properties": {
    "iso:country":"DE",
    "sg:address":"Steingasse 22",
    "sg:city":"Buseck",
    "sg:phone":"+49 6408/2865",
    "sg:postcode":"35418",
    "sg:province":"Hessen",
    "wof:name":"T. Kr\u00e4mer",
    "wof:placetype":"venue"
},
  "geometry": {"coordinates":[8.750947,50.620743],"type":"Point"}
}