{
  "type": "Feature",
  "properties": {
    "iso:country":"DE",
    "sg:address":"Sandstr. 1a",
    "sg:city":"N\u00fcrnberg",
    "sg:phone":"+49 911/222005",
    "sg:postcode":"90443",
    "sg:province":"Bayern",
    "wof:name":"Faulpelz",
    "wof:placetype":"venue"
},
  "geometry": {"coordinates":[11.0684633255,49.4469413757],"type":"Point"}
}