{
  "type": "Feature",
  "properties": {
    "iso:country":"DE",
    "sg:address":"Eisenbahnstr. 139",
    "sg:city":"F\u00fcrstenwalde",
    "sg:phone":"+49 3361/2732",
    "sg:postcode":"15517",
    "sg:province":"Brandenburg",
    "wof:name":"Robert F\u00fcnfhaus",
    "wof:placetype":"venue"
},
  "geometry": {"coordinates":[14.061641,52.362598],"type":"Point"}
}