{
  "type": "Feature",
  "properties": {
    "iso:country":"DE",
    "sg:address":"Finkenweg 30",
    "sg:city":"Rheinbach",
    "sg:phone":"+49 2226/918975",
    "sg:postcode":"53359",
    "sg:province":"Nordrhein-Westfalen",
    "wof:name":"Webdesign4all.de B\u00fcro F\u00fcr It-technik",
    "wof:placetype":"venue"
},
  "geometry": {"coordinates":[6.926707,50.601929],"type":"Point"}
}