{
  "type": "Feature",
  "properties": {
    "iso:country":"DE",
    "sg:address":"K\u00fcstersweg 38",
    "sg:city":"Hamburg",
    "sg:postcode":"21079",
    "sg:province":"Hamburg",
    "wof:name":"Heim-plan Dienstleistungs Gmbh & Co. Kg",
    "wof:placetype":"venue"
},
  "geometry": {"coordinates":[10.000852,53.436115],"type":"Point"}
}