{
  "type": "Feature",
  "properties": {
    "iso:country":"DE",
    "sg:address":"Schmitzbauerstr. 9",
    "sg:city":"M\u00fclheim",
    "sg:postcode":"45473",
    "sg:province":"Nordrhein-Westfalen",
    "wof:name":"Behindertenwerkstatt",
    "wof:placetype":"venue"
},
  "geometry": {"coordinates":[6.901868,51.444698],"type":"Point"}
}