{
  "type": "Feature",
  "properties": {
    "iso:country":"DE",
    "sg:address":"Friedhofsweg 6",
    "sg:city":"Oerlinghausen",
    "sg:phone":"+49 5202/5997",
    "sg:postcode":"33813",
    "sg:province":"Nordrhein-Westfalen",
    "wof:name":"W. Laube",
    "wof:placetype":"venue"
},
  "geometry": {"coordinates":[8.713308,51.968983],"type":"Point"}
}