{
  "type": "Feature",
  "properties": {
    "iso:country":"DE",
    "sg:address":"Prinzenstr. 16",
    "sg:city":"Friedrichstadt",
    "sg:phone":"+49 4881/1658",
    "sg:postcode":"25840",
    "sg:province":"Schleswig-Holstein",
    "wof:name":"R. Ludwig",
    "wof:placetype":"venue"
},
  "geometry": {"coordinates":[9.0869569778,54.374835968],"type":"Point"}
}