{
  "type": "Feature",
  "properties": {
    "iso:country":"DE",
    "sg:address":"Industriestr. 11",
    "sg:city":"Neunburg",
    "sg:phone":"+49 9672/460",
    "sg:postcode":"92431",
    "sg:province":"Bayern",
    "wof:name":"The Lorenz Bahlsen Snack-world Production",
    "wof:placetype":"venue"
},
  "geometry": {"coordinates":[12.4032497406,49.3373374939],"type":"Point"}
}