{
  "type": "Feature",
  "properties": {
    "iso:country":"DE",
    "sg:address":"Cloppenburger Str. 311",
    "sg:city":"Oldenburg",
    "sg:phone":"+49 441/42811",
    "sg:postcode":"26133",
    "sg:province":"Niedersachsen",
    "wof:name":"L. Urbaniak Vergn\u00fcgungsst\u00e4tte",
    "wof:placetype":"venue"
},
  "geometry": {"coordinates":[8.211471,53.112564],"type":"Point"}
}