{
  "type": "Feature",
  "properties": {
    "iso:country":"DE",
    "sg:address":"Kleinhaderner Str. 2",
    "sg:city":"M\u00fcnchen",
    "sg:phone":"+49 89/74009360",
    "sg:postcode":"80689",
    "sg:province":"Bayern",
    "wof:name":"Weko Komplettl\u00f6sungen F\u00fcr Computer- Und In-",
    "wof:placetype":"venue"
},
  "geometry": {"coordinates":[11.4835596085,48.1246337891],"type":"Point"}
}