{
  "type": "Feature",
  "properties": {
    "iso:country":"DE",
    "sg:address":"Bussardweg 32",
    "sg:city":"Essen",
    "sg:phone":"+49 201/4309721",
    "sg:postcode":"45134",
    "sg:province":"Nordrhein-Westfalen",
    "wof:name":"Holz Perali Gmbh",
    "wof:placetype":"venue"
},
  "geometry": {"coordinates":[7.0321497917,51.4269218445],"type":"Point"}
}