{
  "type": "Feature",
  "properties": {
    "iso:country":"DE",
    "sg:address":"Erlenstr. 14",
    "sg:city":"Roschbach",
    "sg:phone":"+49 6323/6223",
    "sg:postcode":"76835",
    "sg:province":"Rheinland-Pfalz",
    "wof:name":"Egbert Weigel Rechtsanwalt",
    "wof:placetype":"venue"
},
  "geometry": {"coordinates":[8.1166639328,49.2450370789],"type":"Point"}
}