{
  "type": "Feature",
  "properties": {
    "iso:country":"DE",
    "sg:address":"Ernst-Moritz-Arndt-Str. 28",
    "sg:city":"Dinslaken",
    "sg:phone":"+49 2064/15361",
    "sg:postcode":"46537",
    "sg:province":"Nordrhein-Westfalen",
    "wof:name":"Hagen-apotheke",
    "wof:placetype":"venue"
},
  "geometry": {"coordinates":[6.72183,51.570644],"type":"Point"}
}