{
  "type": "Feature",
  "properties": {
    "iso:country":"DE",
    "sg:address":"Gr\u00fcnthaler Str. 16",
    "sg:city":"Olbernhau",
    "sg:phone":"+49 37360/72522",
    "sg:postcode":"09526",
    "sg:province":"Sachsen",
    "wof:name":"Herz-apotheke Inh. Ursula Grie\u00dfbach",
    "wof:placetype":"venue"
},
  "geometry": {"coordinates":[13.338445,50.6604],"type":"Point"}
}