{
  "type": "Feature",
  "properties": {
    "iso:country":"DE",
    "sg:address":"Austr. 8",
    "sg:city":"\u00d6hringen",
    "sg:phone":"+49 7941/34291",
    "sg:postcode":"74613",
    "sg:province":"Baden-W\u00fcrttemberg",
    "wof:name":"Scp-fahrzeugpflege Gmbh",
    "wof:placetype":"venue"
},
  "geometry": {"coordinates":[9.489627,49.203983],"type":"Point"}
}