{
  "type": "Feature",
  "properties": {
    "iso:country":"DE",
    "sg:address":"Sternbuschweg 244",
    "sg:city":"Duisburg",
    "sg:phone":"+49 203/353959",
    "sg:postcode":"47057",
    "sg:province":"Nordrhein-Westfalen",
    "wof:name":"Cornelia Seidel",
    "wof:placetype":"venue"
},
  "geometry": {"coordinates":[6.7833638191,51.420463562],"type":"Point"}
}