{
  "type": "Feature",
  "properties": {
    "iso:country":"DE",
    "sg:address":"Boschstr 5",
    "sg:city":"Parkstetten",
    "sg:phone":"+49 9421/84340",
    "sg:postcode":"94365",
    "sg:province":"Bayern",
    "wof:name":"Peter Rosenlehner Gmbh",
    "wof:placetype":"venue"
},
  "geometry": {"coordinates":[12.61007,48.919804],"type":"Point"}
}