{
  "type": "Feature",
  "properties": {
    "iso:country":"DE",
    "sg:address":"Heilig-Kreuz-Str. 19",
    "sg:city":"Donauw\u00f6rth",
    "sg:phone":"+49 906/5069",
    "sg:postcode":"86609",
    "sg:province":"Bayern",
    "wof:name":"Katholisches Pfarramt Hl. Kreuz",
    "wof:placetype":"venue"
},
  "geometry": {"coordinates":[10.7746391296,48.7193069458],"type":"Point"}
}