{
  "type": "Feature",
  "properties": {
    "iso:country":"DE",
    "sg:address":"Beethovenstra\u00dfe 24",
    "sg:city":"Weissach im Tal",
    "sg:phone":"+49 7191/300488",
    "sg:postcode":"71554",
    "sg:province":"Baden-W\u00fcrttemberg",
    "wof:name":"Copy-print Express",
    "wof:placetype":"venue"
},
  "geometry": {"coordinates":[9.467703,48.929871],"type":"Point"}
}