{
  "type": "Feature",
  "properties": {
    "iso:country":"DE",
    "sg:address":"Holmredder 52",
    "sg:city":"Kiel",
    "sg:postcode":"24107",
    "sg:province":"Schleswig-Holstein",
    "wof:name":"Holger Franke Verwaltungs Gmbh",
    "wof:placetype":"venue"
},
  "geometry": {"coordinates":[10.078745842,54.3507766724],"type":"Point"}
}