{
  "type": "Feature",
  "properties": {
    "iso:country":"DE",
    "sg:address":"S\u00fcdermoor 41",
    "sg:city":"Harrislee",
    "sg:phone":"+49 461/73808",
    "sg:postcode":"24955",
    "sg:province":"Schleswig-Holstein",
    "wof:name":"Hans H. Baum",
    "wof:placetype":"venue"
},
  "geometry": {"coordinates":[9.390987,54.803734],"type":"Point"}
}