{
  "type": "Feature",
  "properties": {
    "iso:country":"DE",
    "sg:address":"Lindenstr. 60",
    "sg:city":"Bramsche",
    "sg:phone":"+49 5461/72460",
    "sg:postcode":"49565",
    "sg:province":"Niedersachsen",
    "wof:name":"Michael Werries",
    "wof:placetype":"venue"
},
  "geometry": {"coordinates":[7.975479126,52.4170608521],"type":"Point"}
}