{
  "type": "Feature",
  "properties": {
    "iso:country":"DE",
    "sg:address":"Falkenweg 30",
    "sg:city":"Dillenburg",
    "sg:phone":"+49 2771/6408",
    "sg:postcode":"35683",
    "sg:province":"Hessen",
    "wof:name":"Gerhard Halwe",
    "wof:placetype":"venue"
},
  "geometry": {"coordinates":[8.2794532776,50.7335281372],"type":"Point"}
}