{
  "type": "Feature",
  "properties": {
    "iso:country":"DE",
    "sg:address":"Kammerrathsfeldstr. 3",
    "sg:city":"D\u00fcsseldorf",
    "sg:phone":"+49 211/712304",
    "sg:postcode":"40593",
    "sg:province":"Nordrhein-Westfalen",
    "wof:name":"Rolf Weiler",
    "wof:placetype":"venue"
},
  "geometry": {"coordinates":[6.8701119423,51.1481933594],"type":"Point"}
}