{
  "type": "Feature",
  "properties": {
    "iso:country":"DE",
    "sg:address":"K\u00f6chlingstr.28",
    "sg:city":"Rheda-Wiedenbr\u00fcck",
    "sg:phone":"+49 5242/577882",
    "sg:postcode":"33378",
    "sg:province":"Nordrhein-Westfalen",
    "wof:name":"Schmidt Galabau",
    "wof:placetype":"venue"
},
  "geometry": {"coordinates":[8.3245191574,51.8398323059],"type":"Point"}
}