{
  "type": "Feature",
  "properties": {
    "iso:country":"DE",
    "sg:address":"67112",
    "sg:city":"Mutterstadt",
    "sg:postcode":"67112",
    "sg:province":"Rheinland-Pfalz",
    "wof:name":"Raiffeisenbank Schwerin Eg",
    "wof:placetype":"venue"
},
  "geometry": {"coordinates":[8.34822,49.441631],"type":"Point"}
}