{
  "type": "Feature",
  "properties": {
    "iso:country":"DE",
    "sg:address":"Stolpm\u00fcnder Str. 1",
    "sg:city":"Hamburg",
    "sg:phone":"+49 40/6725595",
    "sg:postcode":"22147",
    "sg:province":"Hamburg",
    "wof:name":"Michael Kusch",
    "wof:placetype":"venue"
},
  "geometry": {"coordinates":[10.138277,53.617634],"type":"Point"}
}