{
  "type": "Feature",
  "properties": {
    "iso:country":"DE",
    "sg:address":"Nelkenstr. 18",
    "sg:city":"Schaafheim",
    "sg:phone":"+49 6073/89103",
    "sg:postcode":"64850",
    "sg:province":"Hessen",
    "wof:name":"Knecht Immobilienmakler",
    "wof:placetype":"venue"
},
  "geometry": {"coordinates":[9.0315599442,49.8941230774],"type":"Point"}
}