{
  "type": "Feature",
  "properties": {
    "iso:country":"DE",
    "sg:address":"Lorcher Str. 5",
    "sg:city":"R\u00fcdesheim am Rhein",
    "sg:phone":"+49 6722/2766",
    "sg:postcode":"65385",
    "sg:province":"Hessen",
    "wof:name":"Hotel-restaurant Eger Delfter Stube",
    "wof:placetype":"venue"
},
  "geometry": {"coordinates":[7.8662648201,49.9884567261],"type":"Point"}
}