{
  "type": "Feature",
  "properties": {
    "iso:country":"DE",
    "sg:address":"Auf dem Hohen Stein 8",
    "sg:city":"Ruppichteroth",
    "sg:phone":"+49 2247/4052",
    "sg:postcode":"53809",
    "sg:province":"Nordrhein-Westfalen",
    "wof:name":"Siegfried Schneider",
    "wof:placetype":"venue"
},
  "geometry": {"coordinates":[7.368106,50.813484],"type":"Point"}
}