{
  "type": "Feature",
  "properties": {
    "iso:country":"DE",
    "sg:address":"Bahnhofstr. 84",
    "sg:city":"Sulz",
    "sg:phone":"+49 7454/96170",
    "sg:postcode":"72172",
    "sg:province":"Baden-W\u00fcrttemberg",
    "wof:name":"Steeb-industriek\u00fchler Inh. Albert Haugg",
    "wof:placetype":"venue"
},
  "geometry": {"coordinates":[8.64544,48.370651],"type":"Point"}
}