{
  "type": "Feature",
  "properties": {
    "iso:country":"DE",
    "sg:address":"Am Heilbrunnen 140",
    "sg:city":"Reutlingen",
    "sg:phone":"+49 7121/492043",
    "sg:postcode":"72766",
    "sg:province":"Baden-W\u00fcrttemberg",
    "wof:name":"Zawischka Apparatebau Zva Gmbh",
    "wof:placetype":"venue"
},
  "geometry": {"coordinates":[9.222485,48.507633],"type":"Point"}
}