{
  "type": "Feature",
  "properties": {
    "iso:country":"DE",
    "sg:address":"Lessingstr. 56",
    "sg:city":"Saarbr\u00fccken",
    "sg:phone":"+49 681/62986",
    "sg:postcode":"66121",
    "sg:province":"Saarland",
    "wof:name":"Maas Immobilienmakler",
    "wof:placetype":"venue"
},
  "geometry": {"coordinates":[7.0109081268,49.2308807373],"type":"Point"}
}