{
  "type": "Feature",
  "properties": {
    "iso:country":"DE",
    "sg:address":"Hauptstr. 29",
    "sg:city":"Kreuzebra",
    "sg:phone":"+49 36075/31247",
    "sg:postcode":"37351",
    "sg:province":"Th\u00fcringen",
    "wof:name":"Eichsfelder Baumarkt Gmbh",
    "wof:placetype":"venue"
},
  "geometry": {"coordinates":[10.255313,51.34166],"type":"Point"}
}