{
  "type": "Feature",
  "properties": {
    "iso:country":"DE",
    "sg:address":"Bahnhofstr. 13",
    "sg:city":"Ferdinandshof",
    "sg:phone":"+49 39778/21919",
    "sg:postcode":"17379",
    "sg:province":"Mecklenburg-Vorpommern",
    "wof:name":"Cornelia Braesel",
    "wof:placetype":"venue"
},
  "geometry": {"coordinates":[13.8838043213,53.6608543396],"type":"Point"}
}