{
  "type": "Feature",
  "properties": {
    "iso:country":"DE",
    "sg:address":"Sedlitzer Weg 2",
    "sg:city":"Dohna",
    "sg:phone":"+49 3529/522530",
    "sg:postcode":"01809",
    "sg:province":"Sachsen",
    "wof:name":"Elke Paul Architektin",
    "wof:placetype":"venue"
},
  "geometry": {"coordinates":[13.866893,50.962429],"type":"Point"}
}