{
  "type": "Feature",
  "properties": {
    "iso:country":"DE",
    "sg:address":"Chattenstr. 18",
    "sg:city":"Niedenstein",
    "sg:phone":"+49 5624/780",
    "sg:postcode":"34305",
    "sg:province":"Hessen",
    "wof:name":"Gastst\u00e4tte Helga Esche",
    "wof:placetype":"venue"
},
  "geometry": {"coordinates":[9.3007173538,51.2271194458],"type":"Point"}
}