{
  "type": "Feature",
  "properties": {
    "iso:country":"DE",
    "sg:address":"Am Hasenberg 52",
    "sg:city":"Emmerich",
    "sg:phone":"+49 2822/68846",
    "sg:postcode":"46446",
    "sg:province":"Nordrhein-Westfalen",
    "wof:name":"Wecovi Gmbh",
    "wof:placetype":"venue"
},
  "geometry": {"coordinates":[6.257316,51.842636],"type":"Point"}
}