{
  "type": "Feature",
  "properties": {
    "iso:country":"DE",
    "sg:address":"Wagnerstr. 1",
    "sg:city":"Frechen",
    "sg:phone":"+49 2234/31462",
    "sg:postcode":"50226",
    "sg:province":"Nordrhein-Westfalen",
    "wof:name":"Petra-ute K\u00f6llen",
    "wof:placetype":"venue"
},
  "geometry": {"coordinates":[6.746373,50.913002],"type":"Point"}
}