{
  "type": "Feature",
  "properties": {
    "iso:country":"DE",
    "sg:address":"79848",
    "sg:city":"Bonndorf",
    "sg:phone":"+49 7703/93800",
    "sg:postcode":"79848",
    "sg:province":"Baden-W\u00fcrttemberg",
    "wof:name":"Stadtb\u00fccherei Rathaus",
    "wof:placetype":"venue"
},
  "geometry": {"coordinates":[8.32268,47.80999],"type":"Point"}
}