{
  "type": "Feature",
  "properties": {
    "iso:country":"DE",
    "sg:address":"Jahnweg",
    "sg:city":"Kleinwallstadt",
    "sg:phone":"+49 6022/21678",
    "sg:postcode":"63839",
    "sg:province":"Bayern",
    "wof:name":"Vereinsgastst\u00e4tte Fu\u00dfballclub 1920",
    "wof:placetype":"venue"
},
  "geometry": {"coordinates":[9.1632385254,49.8640365601],"type":"Point"}
}