{
  "type": "Feature",
  "properties": {
    "iso:country":"DE",
    "sg:address":"Nockwinkel 98",
    "sg:city":"Essen",
    "sg:phone":"+49 201/589596",
    "sg:postcode":"45277",
    "sg:province":"Nordrhein-Westfalen",
    "wof:name":"Medion Unterhaltungsmedien Handelsgesellschaft",
    "wof:placetype":"venue"
},
  "geometry": {"coordinates":[7.0779838562,51.4287872314],"type":"Point"}
}