{
  "type": "Feature",
  "properties": {
    "iso:country":"DE",
    "sg:address":"Ehndorfer Str. 36",
    "sg:city":"Neum\u00fcnster",
    "sg:phone":"+49 4321/63733",
    "sg:postcode":"24537",
    "sg:province":"Schleswig-Holstein",
    "wof:name":"Ruth Angri",
    "wof:placetype":"venue"
},
  "geometry": {"coordinates":[9.970465,54.066929],"type":"Point"}
}