{
  "type": "Feature",
  "properties": {
    "iso:country":"DE",
    "sg:address":"Siemensstr. 6",
    "sg:city":"Bad Homburg",
    "sg:postcode":"61352",
    "sg:province":"Hessen",
    "wof:name":"Vereinigte Verlags- Beteiligungs Ohg",
    "wof:placetype":"venue"
},
  "geometry": {"coordinates":[8.616565,50.217884],"type":"Point"}
}