{
  "type": "Feature",
  "properties": {
    "iso:country":"DE",
    "sg:address":"Lange Str. 195",
    "sg:city":"Achern",
    "sg:phone":"+49 7841/1497",
    "sg:postcode":"77855",
    "sg:province":"Baden-W\u00fcrttemberg",
    "wof:name":"Klaus Huber",
    "wof:placetype":"venue"
},
  "geometry": {"coordinates":[8.06364,48.628712],"type":"Point"}
}