{
  "type": "Feature",
  "properties": {
    "iso:country":"DE",
    "sg:address":"Bergsiedlung 10",
    "sg:city":"Schefflenz",
    "sg:phone":"+49 6293/692",
    "sg:postcode":"74850",
    "sg:province":"Baden-W\u00fcrttemberg",
    "wof:name":"Herold",
    "wof:placetype":"venue"
},
  "geometry": {"coordinates":[9.289133,49.415195],"type":"Point"}
}