{
  "type": "Feature",
  "properties": {
    "iso:country":"DE",
    "sg:address":"Bergstr. 77",
    "sg:city":"Zwickau",
    "sg:phone":"+49 375/780483",
    "sg:postcode":"08064",
    "sg:province":"Sachsen",
    "wof:name":"Frank M\u00f6ckel",
    "wof:placetype":"venue"
},
  "geometry": {"coordinates":[12.479866,50.671158],"type":"Point"}
}