{
  "type": "Feature",
  "properties": {
    "iso:country":"DE",
    "sg:address":"An den Eichen 18",
    "sg:city":"Nideggen",
    "sg:phone":"+49 2427/6092",
    "sg:postcode":"52385",
    "sg:province":"Nordrhein-Westfalen",
    "wof:name":"Herbert M\u00fcller",
    "wof:placetype":"venue"
},
  "geometry": {"coordinates":[6.468547821,50.7023735046],"type":"Point"}
}