{
  "type": "Feature",
  "properties": {
    "iso:country":"DE",
    "sg:address":"H\u00f6henstr 29",
    "sg:city":"Viersen",
    "sg:phone":"+49 2162/77374",
    "sg:postcode":"41749",
    "sg:province":"Nordrhein-Westfalen",
    "wof:name":"Drahtseile Gebr. Henschel Gmbh",
    "wof:placetype":"venue"
},
  "geometry": {"coordinates":[6.370112896,51.2787284851],"type":"Point"}
}