{
  "type": "Feature",
  "properties": {
    "iso:country":"DE",
    "sg:address":"Hauptstr. 4",
    "sg:city":"Dillenburg",
    "sg:phone":"+49 2771/261540",
    "sg:postcode":"35687",
    "sg:province":"Hessen",
    "wof:name":"Pizzeria Bellamia",
    "wof:placetype":"venue"
},
  "geometry": {"coordinates":[8.3030662537,50.7184562683],"type":"Point"}
}