{
  "type": "Feature",
  "properties": {
    "iso:country":"DE",
    "sg:address":"Carl-Herz-Ufer 31",
    "sg:city":"Berlin",
    "sg:postcode":"10961",
    "sg:province":"Berlin",
    "wof:name":"Verein Z. F\u00f6rderung Der St\u00e4dtepartnerschaft Ber-",
    "wof:placetype":"venue"
},
  "geometry": {"coordinates":[13.401055336,52.4963035583],"type":"Point"}
}