{
  "type": "Feature",
  "properties": {
    "iso:country":"DE",
    "sg:address":"Fischmarkt 11",
    "sg:city":"Regensburg",
    "sg:phone":"+49 941/57280",
    "sg:postcode":"93047",
    "sg:province":"Bayern",
    "wof:name":"C. Bauer",
    "wof:placetype":"venue"
},
  "geometry": {"coordinates":[12.094655,49.021004],"type":"Point"}
}