{
  "type": "Feature",
  "properties": {
    "iso:country":"DE",
    "sg:address":"Hauptstr. 63",
    "sg:city":"Bad Waldsee",
    "sg:phone":"+49 7524/1297",
    "sg:postcode":"88339",
    "sg:province":"Baden-W\u00fcrttemberg",
    "wof:name":"M. Albrecht",
    "wof:placetype":"venue"
},
  "geometry": {"coordinates":[9.752086,47.921192],"type":"Point"}
}