{
  "type": "Feature",
  "properties": {
    "iso:country":"DE",
    "sg:address":"Zeiskamerstr. 20",
    "sg:city":"Bellheim",
    "sg:phone":"+49 7272",
    "sg:postcode":"76756",
    "sg:province":"Rheinland-Pfalz",
    "wof:name":"Das Ristorante-pizzeria Ischia Im Bellheim/pfalz",
    "wof:placetype":"venue"
},
  "geometry": {"coordinates":[8.279546,49.193466],"type":"Point"}
}