{
  "type": "Feature",
  "properties": {
    "iso:country":"DE",
    "sg:address":"Kurt-B\u00fcrger-Str. 19",
    "sg:city":"Besitz",
    "sg:phone":"+49 38844/21421",
    "sg:postcode":"19258",
    "sg:province":"Mecklenburg-Vorpommern",
    "wof:name":"Erich August Degenhardt",
    "wof:placetype":"venue"
},
  "geometry": {"coordinates":[10.856207,53.343056],"type":"Point"}
}