{
  "type": "Feature",
  "properties": {
    "iso:country":"DE",
    "sg:address":"Friedrich-Schiller-Str. 2b",
    "sg:city":"Guben",
    "sg:phone":"+49 3561/55540",
    "sg:postcode":"03172",
    "sg:province":"Brandenburg",
    "wof:name":"Hoffmann M\u00f6bel Gmbh",
    "wof:placetype":"venue"
},
  "geometry": {"coordinates":[14.6767454147,51.9548454285],"type":"Point"}
}