{
  "type": "Feature",
  "properties": {
    "iso:country":"DE",
    "sg:address":"Alfener Weg 14",
    "sg:city":"Saarbr\u00fccken",
    "sg:phone":"+49 681/72127",
    "sg:postcode":"66113",
    "sg:province":"Saarland",
    "wof:name":"G\u00fcnther Backhaus Architekt",
    "wof:placetype":"venue"
},
  "geometry": {"coordinates":[6.964201,49.25544],"type":"Point"}
}