{
  "type": "Feature",
  "properties": {
    "iso:country":"DE",
    "sg:address":"Gro\u00dfe Ga\u00df 7",
    "sg:city":"Weil am Rhein",
    "sg:phone":"+49 7621/62631",
    "sg:postcode":"79576",
    "sg:province":"Baden-W\u00fcrttemberg",
    "wof:name":"Soder",
    "wof:placetype":"venue"
},
  "geometry": {"coordinates":[7.6168532372,47.6153793335],"type":"Point"}
}