{
  "type": "Feature",
  "properties": {
    "iso:country":"DE",
    "sg:address":"Von-Waldthausen-Str. 8",
    "sg:city":"Neuss",
    "sg:phone":"+49 2137/4367",
    "sg:postcode":"41469",
    "sg:province":"Nordrhein-Westfalen",
    "wof:name":"J\u00fcrgen Brune",
    "wof:placetype":"venue"
},
  "geometry": {"coordinates":[6.718523,51.154514],"type":"Point"}
}