{
  "type": "Feature",
  "properties": {
    "iso:country":"DE",
    "sg:address":"WOLFGANGSTRA\u00dfE 30",
    "sg:city":"Dessau",
    "sg:postcode":"06844",
    "sg:province":"Sachsen-Anhalt",
    "wof:name":"Die Wohnunggesellschaft Dessau E. G.",
    "wof:placetype":"venue"
},
  "geometry": {"coordinates":[12.242002,51.840187],"type":"Point"}
}