{
  "type": "Feature",
  "properties": {
    "iso:country":"DE",
    "sg:address":"Marienburger Str. 54",
    "sg:city":"Balingen",
    "sg:phone":"+49 7433/15838",
    "sg:postcode":"72336",
    "sg:province":"Baden-W\u00fcrttemberg",
    "wof:name":"Dr. Ulf Uecker Tierarzt",
    "wof:placetype":"venue"
},
  "geometry": {"coordinates":[8.8562726974,48.2904777527],"type":"Point"}
}