{
  "type": "Feature",
  "properties": {
    "iso:country":"DE",
    "sg:address":"Heerdter Lohweg 53-55",
    "sg:city":"D\u00fcsseldorf",
    "sg:phone":"+49 4921/159660",
    "sg:postcode":"40549",
    "sg:province":"Nordrhein-Westfalen",
    "wof:name":"Invenses Systems Gmbh",
    "wof:placetype":"venue"
},
  "geometry": {"coordinates":[6.727277,51.23835],"type":"Point"}
}