{
  "type": "Feature",
  "properties": {
    "iso:country":"DE",
    "sg:address":"H\u00fcnegr\u00e4ben 10",
    "sg:city":"Schmallenberg",
    "sg:postcode":"57392",
    "sg:province":"Nordrhein-Westfalen",
    "wof:name":"Br\u00e4utigam Ideen Druck & Service Gmbh",
    "wof:placetype":"venue"
},
  "geometry": {"coordinates":[8.305327,51.157516],"type":"Point"}
}