{
  "type": "Feature",
  "properties": {
    "iso:country":"DE",
    "sg:address":"Ewaldstr. 43",
    "sg:city":"Herten",
    "sg:phone":"+49 2366/37654",
    "sg:postcode":"45699",
    "sg:province":"Nordrhein-Westfalen",
    "wof:name":"Ledi",
    "wof:placetype":"venue"
},
  "geometry": {"coordinates":[7.1418380737,51.5909118652],"type":"Point"}
}