{
  "type": "Feature",
  "properties": {
    "iso:country":"DE",
    "sg:address":"Weiterst\u00e4dter Landstr 13",
    "sg:city":"Darmstadt",
    "sg:phone":"+49 6151/35080",
    "sg:postcode":"64291",
    "sg:province":"Hessen",
    "wof:name":"Jumo Gmbh & Co Kg",
    "wof:placetype":"venue"
},
  "geometry": {"coordinates":[8.63086,49.91526],"type":"Point"}
}