{
  "type": "Feature",
  "properties": {
    "iso:country":"DE",
    "sg:address":"Stresemannstr. 36",
    "sg:city":"Ludwigsburg",
    "sg:postcode":"71634",
    "sg:province":"Baden-W\u00fcrttemberg",
    "wof:name":"W\u00fcrtt. Wurftaubenclub Stuttgart",
    "wof:placetype":"venue"
},
  "geometry": {"coordinates":[9.1810865402,48.9020004272],"type":"Point"}
}