{
  "type": "Feature",
  "properties": {
    "iso:country":"DE",
    "sg:address":"Weinbergstr 1",
    "sg:city":"Lychen",
    "sg:phone":"+49 39888/2308",
    "sg:postcode":"17279",
    "sg:province":"Brandenburg",
    "wof:name":"Maschinenbaumechanik Lychen Gmbh",
    "wof:placetype":"venue"
},
  "geometry": {"coordinates":[13.315235,53.210377],"type":"Point"}
}