{
  "type": "Feature",
  "properties": {
    "iso:country":"DE",
    "sg:address":"Oberdorf 2",
    "sg:city":"K\u00fcssaberg",
    "sg:phone":"+49 7741/4596",
    "sg:postcode":"79790",
    "sg:province":"Baden-W\u00fcrttemberg",
    "wof:name":"Otmar Spitznagel",
    "wof:placetype":"venue"
},
  "geometry": {"coordinates":[8.29598,47.608318],"type":"Point"}
}