{
  "type": "Feature",
  "properties": {
    "iso:country":"DE",
    "sg:address":"Marktstr. 15",
    "sg:city":"Schelklingen",
    "sg:phone":"+49 7394/2480",
    "sg:postcode":"89601",
    "sg:province":"Baden-W\u00fcrttemberg",
    "wof:name":"Heimatmuseum Der Stadt Schelklingen",
    "wof:placetype":"venue"
},
  "geometry": {"coordinates":[9.733679,48.375271],"type":"Point"}
}