{
  "type": "Feature",
  "properties": {
    "iso:country":"DE",
    "sg:address":"Behringstr. 21-25",
    "sg:city":"Berlin",
    "sg:postcode":"12437",
    "sg:province":"Berlin",
    "wof:name":"Mehaguno Gmbh",
    "wof:placetype":"venue"
},
  "geometry": {"coordinates":[13.4900665283,52.4659805298],"type":"Point"}
}