{
  "type": "Feature",
  "properties": {
    "iso:country":"DE",
    "sg:address":"Maxgasse 2",
    "sg:city":"Hof",
    "sg:phone":"+49 9281/3168",
    "sg:postcode":"95028",
    "sg:province":"Bayern",
    "wof:name":"F. Conrad Elektro Gesch\u00e4ft",
    "wof:placetype":"venue"
},
  "geometry": {"coordinates":[11.919387,50.322842],"type":"Point"}
}