{
  "type": "Feature",
  "properties": {
    "iso:country":"DE",
    "sg:address":"Marktplatz 11",
    "sg:city":"Wadern",
    "sg:phone":"+49 6871/7992",
    "sg:postcode":"66687",
    "sg:province":"Saarland",
    "wof:name":"Sanit\u00e4tshaus Prinz & Co. Gmbh",
    "wof:placetype":"venue"
},
  "geometry": {"coordinates":[6.889603138,49.5398101807],"type":"Point"}
}