{
  "type": "Feature",
  "properties": {
    "iso:country":"DE",
    "sg:address":"Br\u00f6kelner Str. 6",
    "sg:city":"Bodenwerder",
    "sg:phone":"+49 5533/97160",
    "sg:postcode":"37619",
    "sg:province":"Niedersachsen",
    "wof:name":"L\u00fccke Dach Und Wand Gmbh",
    "wof:placetype":"venue"
},
  "geometry": {"coordinates":[9.516417,51.97414],"type":"Point"}
}