{
  "type": "Feature",
  "properties": {
    "iso:country":"DE",
    "sg:address":"Fallstr. 23",
    "sg:city":"Rees",
    "sg:phone":"+49 2851/1200",
    "sg:postcode":"46459",
    "sg:province":"Nordrhein-Westfalen",
    "wof:name":"Restaurant Alt Rees",
    "wof:placetype":"venue"
},
  "geometry": {"coordinates":[6.3985681534,51.7589797974],"type":"Point"}
}