{
  "type": "Feature",
  "properties": {
    "iso:country":"DE",
    "sg:address":"Gabrielstr. 21",
    "sg:city":"Dormagen",
    "sg:phone":"+49 2133/70677",
    "sg:postcode":"41542",
    "sg:province":"Nordrhein-Westfalen",
    "wof:name":"Herbert Dick Gmbh",
    "wof:placetype":"venue"
},
  "geometry": {"coordinates":[6.784293,51.127941],"type":"Point"}
}