{
  "type": "Feature",
  "properties": {
    "iso:country":"DE",
    "sg:address":"Tannenwaldallee 72",
    "sg:city":"Bad Homburg",
    "sg:phone":"+49 6172/937176",
    "sg:postcode":"61348",
    "sg:province":"Hessen",
    "wof:name":"Ifu Diffusions- Und Umwelttechnik Gmbh",
    "wof:placetype":"venue"
},
  "geometry": {"coordinates":[8.5915813446,50.2310523987],"type":"Point"}
}