{
  "type": "Feature",
  "properties": {
    "iso:country":"DE",
    "sg:address":"Herrenbreite",
    "sg:city":"Bad Schussenried",
    "sg:phone":"+49 7525/1445",
    "sg:postcode":"88427",
    "sg:province":"Baden-W\u00fcrttemberg",
    "wof:name":"Festhalle Otterswang",
    "wof:placetype":"venue"
},
  "geometry": {"coordinates":[9.64283,47.979309],"type":"Point"}
}