{
  "type": "Feature",
  "properties": {
    "iso:country":"DE",
    "sg:address":"Sudenhofer Str. 1",
    "sg:city":"Hagenow",
    "sg:postcode":"19230",
    "sg:province":"Mecklenburg-Vorpommern",
    "wof:name":"Mwt Handel Und Service Von Massenwerbungstechnik Gmbh",
    "wof:placetype":"venue"
},
  "geometry": {"coordinates":[11.190071106,53.4312744141],"type":"Point"}
}