{
  "type": "Feature",
  "properties": {
    "iso:country":"DE",
    "sg:address":"Talstr 3",
    "sg:city":"Beckingen",
    "sg:phone":"+49 6835/590",
    "sg:postcode":"66701",
    "sg:province":"Saarland",
    "wof:name":"Textron Verbindungstechnik Gmbh & Co Ohg",
    "wof:placetype":"venue"
},
  "geometry": {"coordinates":[6.694519,49.389038],"type":"Point"}
}