{
  "type": "Feature",
  "properties": {
    "iso:country":"DE",
    "sg:address":"Tannenstr. 13",
    "sg:city":"D\u00fcsseldorf",
    "sg:postcode":"40476",
    "sg:province":"Nordrhein-Westfalen",
    "wof:name":"Hospitality Incentive Gmbh",
    "wof:placetype":"venue"
},
  "geometry": {"coordinates":[6.778565,51.2505],"type":"Point"}
}