{
  "type": "Feature",
  "properties": {
    "iso:country":"DE",
    "sg:address":"Raiffeisenstr. 2",
    "sg:city":"Rosbach",
    "sg:phone":"+49 4960/0391809",
    "sg:postcode":"61191",
    "sg:province":"Hessen",
    "wof:name":"Haase Gmbh",
    "wof:placetype":"venue"
},
  "geometry": {"coordinates":[7.6064009666,50.8000564575],"type":"Point"}
}