{
  "type": "Feature",
  "properties": {
    "iso:country":"DE",
    "sg:address":"Markstiege 33",
    "sg:city":"Meppen",
    "sg:phone":"+49 5931/12562",
    "sg:postcode":"49716",
    "sg:province":"Niedersachsen",
    "wof:name":"G\u00fcnter R\u00f6sner Steinmetzbetrieb",
    "wof:placetype":"venue"
},
  "geometry": {"coordinates":[7.2883009911,52.6866073608],"type":"Point"}
}