{
  "type": "Feature",
  "properties": {
    "iso:country":"DE",
    "sg:address":"Merkureck 16",
    "sg:city":"M\u00fcnster",
    "sg:phone":"+49 2501/6660",
    "sg:postcode":"48165",
    "sg:province":"Nordrhein-Westfalen",
    "wof:name":"Holtrup Gmbh & Co. Kg",
    "wof:placetype":"venue"
},
  "geometry": {"coordinates":[7.6356291771,51.9133338928],"type":"Point"}
}