{
  "type": "Feature",
  "properties": {
    "iso:country":"DE",
    "sg:address":"Adalbertsteinweg 18",
    "sg:city":"Aachen",
    "sg:phone":"+49 241/532525",
    "sg:postcode":"52070",
    "sg:province":"Nordrhein-Westfalen",
    "wof:name":"K\u00fcchen Gier Gmbh",
    "wof:placetype":"venue"
},
  "geometry": {"coordinates":[6.0988550186,50.7744140625],"type":"Point"}
}