{
  "type": "Feature",
  "properties": {
    "iso:country":"DE",
    "sg:address":"Zinzinger Str. 9",
    "sg:city":"Saarbr\u00fccken",
    "sg:phone":"+49 681/58630",
    "sg:postcode":"66117",
    "sg:province":"Saarland",
    "wof:name":"Hotel Novotel",
    "wof:placetype":"venue"
},
  "geometry": {"coordinates":[6.9662342072,49.2099647522],"type":"Point"}
}