{
  "type": "Feature",
  "properties": {
    "iso:country":"DE",
    "sg:address":"Volmerswerther Str 53",
    "sg:city":"D\u00fcsseldorf",
    "sg:phone":"+49 211/30065400",
    "sg:postcode":"40221",
    "sg:province":"Nordrhein-Westfalen",
    "wof:name":"Textb\u00f6rse Gmbh",
    "wof:placetype":"venue"
},
  "geometry": {"coordinates":[6.76059,51.208153],"type":"Point"}
}