{
  "type": "Feature",
  "properties": {
    "iso:country":"DE",
    "sg:address":"Kolbenzeil 18",
    "sg:city":"Heidelberg",
    "sg:phone":"+49 6221/300430",
    "sg:postcode":"69126",
    "sg:province":"Baden-W\u00fcrttemberg",
    "wof:name":"A. Speiser Dipl.-\u00dcbersetzerin",
    "wof:placetype":"venue"
},
  "geometry": {"coordinates":[8.682381,49.374561],"type":"Point"}
}