{
  "type": "Feature",
  "properties": {
    "iso:country":"DE",
    "sg:address":"Graupaer Str. 15",
    "sg:city":"Dresden",
    "sg:phone":"+49 351/2610937",
    "sg:postcode":"01326",
    "sg:province":"Sachsen",
    "wof:name":"Klaus Felsner",
    "wof:placetype":"venue"
},
  "geometry": {"coordinates":[13.901786,51.001461],"type":"Point"}
}