{
  "type": "Feature",
  "properties": {
    "iso:country":"DE",
    "sg:address":"Rheinstr. 11",
    "sg:city":"Neuenburg",
    "sg:phone":"+49 7634/3327",
    "sg:postcode":"79395",
    "sg:province":"Baden-W\u00fcrttemberg",
    "wof:name":"Willi Reimann",
    "wof:placetype":"venue"
},
  "geometry": {"coordinates":[7.590111,47.875523],"type":"Point"}
}