{
  "type": "Feature",
  "properties": {
    "iso:country":"DE",
    "sg:address":"Dorfplatz 5",
    "sg:city":"Lenzkirch",
    "sg:phone":"+49 7653/751",
    "sg:postcode":"79853",
    "sg:province":"Baden-W\u00fcrttemberg",
    "wof:name":"Hotel Hochfirst Saig",
    "wof:placetype":"venue"
},
  "geometry": {"coordinates":[8.1781387329,47.8929405212],"type":"Point"}
}