{
  "type": "Feature",
  "properties": {
    "iso:country":"DE",
    "sg:address":"Himmelsberger Str. 13",
    "sg:city":"Schernberg",
    "sg:phone":"+49 36020/72880",
    "sg:postcode":"99713",
    "sg:province":"Th\u00fcringen",
    "wof:name":"R. Hayne",
    "wof:placetype":"venue"
},
  "geometry": {"coordinates":[10.763781,51.330048],"type":"Point"}
}