{
  "type": "Feature",
  "properties": {
    "iso:country":"DE",
    "sg:address":"Werderstr. 13",
    "sg:city":"Rheinfelden",
    "sg:phone":"+49 7623/72110",
    "sg:postcode":"79618",
    "sg:province":"Baden-W\u00fcrttemberg",
    "wof:name":"Hotel Garni Oberrhein Gmbh",
    "wof:placetype":"venue"
},
  "geometry": {"coordinates":[7.783000946,47.5585365295],"type":"Point"}
}