{
  "type": "Feature",
  "properties": {
    "iso:country":"DE",
    "sg:address":"Sudetenstr. 4",
    "sg:city":"Lippstadt",
    "sg:phone":"+49 2941/80191",
    "sg:postcode":"59558",
    "sg:province":"Nordrhein-Westfalen",
    "wof:name":"H. Wagner",
    "wof:placetype":"venue"
},
  "geometry": {"coordinates":[8.366229,51.716148],"type":"Point"}
}