{
  "type": "Feature",
  "properties": {
    "iso:country":"DE",
    "sg:address":"Bruchhausener Str. 11-15",
    "sg:city":"Unkel",
    "sg:phone":"+49 4922/2494910",
    "sg:postcode":"53572",
    "sg:province":"Rheinland-Pfalz",
    "wof:name":"Hans Simon Kg",
    "wof:placetype":"venue"
},
  "geometry": {"coordinates":[7.218277,50.599476],"type":"Point"}
}