{
  "type": "Feature",
  "properties": {
    "iso:country":"DE",
    "sg:address":"Metzinger Str. 80",
    "sg:city":"Dettingen",
    "sg:phone":"+49 7123/7018",
    "sg:postcode":"72581",
    "sg:province":"Baden-W\u00fcrttemberg",
    "wof:name":"Ebk Evangelische Bruderschaft Kecharismai E.v.",
    "wof:placetype":"venue"
},
  "geometry": {"coordinates":[9.338972,48.530266],"type":"Point"}
}