{
  "type": "Feature",
  "properties": {
    "iso:country":"DE",
    "sg:address":"Neue Mainzer Str 26",
    "sg:city":"Frankfurt",
    "sg:phone":"+49 4969/235536",
    "sg:postcode":"60311",
    "sg:province":"Hessen",
    "wof:name":"Monte Dei Paschi Di Siena",
    "wof:placetype":"venue"
},
  "geometry": {"coordinates":[8.674289,50.109997],"type":"Point"}
}