{
  "type": "Feature",
  "properties": {
    "iso:country":"DE",
    "sg:address":"Weinstr. 25",
    "sg:city":"Bad D\u00fcrkheim",
    "sg:phone":"+49 6322/989436",
    "sg:postcode":"67098",
    "sg:province":"Rheinland-Pfalz",
    "wof:name":"Gerald Masching",
    "wof:placetype":"venue"
},
  "geometry": {"coordinates":[8.1777410507,49.4767875671],"type":"Point"}
}