{
  "type": "Feature",
  "properties": {
    "iso:country":"DE",
    "sg:address":"Liptinger Str. 27",
    "sg:city":"Tuttlingen",
    "sg:phone":"+49 7461/92020",
    "sg:postcode":"78532",
    "sg:province":"Baden-W\u00fcrttemberg",
    "wof:name":"Hausbau Gmbh",
    "wof:placetype":"venue"
},
  "geometry": {"coordinates":[8.8202800751,47.9794616699],"type":"Point"}
}