{
  "type": "Feature",
  "properties": {
    "iso:country":"DE",
    "sg:address":"Friedhofstr.",
    "sg:city":"Ha\u00dfloch",
    "sg:phone":"+49 6324/76767",
    "sg:postcode":"67454",
    "sg:province":"Rheinland-Pfalz",
    "wof:name":"Josef Gatti",
    "wof:placetype":"venue"
},
  "geometry": {"coordinates":[8.2503,49.3643],"type":"Point"}
}