{
  "type": "Feature",
  "properties": {
    "iso:country":"DE",
    "sg:address":"Schliggenstr. 22",
    "sg:city":"Hagen",
    "sg:phone":"+49 2337/8319",
    "sg:postcode":"58091",
    "sg:province":"Nordrhein-Westfalen",
    "wof:name":"Adolf Wehberg",
    "wof:placetype":"venue"
},
  "geometry": {"coordinates":[7.5310978889,51.3009681702],"type":"Point"}
}