{
  "type": "Feature",
  "properties": {
    "iso:country":"DE",
    "sg:address":"L\u00e4rchenweg 1",
    "sg:city":"Titisee-Neustadt",
    "sg:phone":"+49 7651/2070",
    "sg:postcode":"79822",
    "sg:province":"Baden-W\u00fcrttemberg",
    "wof:name":"J. Landgraf Konzert- Direktion Eurostudio Kg",
    "wof:placetype":"venue"
},
  "geometry": {"coordinates":[8.2199840546,47.9136734009],"type":"Point"}
}