{
  "type": "Feature",
  "properties": {
    "iso:country":"DE",
    "sg:address":"Bremer Str. 68",
    "sg:city":"Delmenhorst",
    "sg:phone":"+49 4221/16810",
    "sg:postcode":"27749",
    "sg:province":"Niedersachsen",
    "wof:name":"C. Lehmann",
    "wof:placetype":"venue"
},
  "geometry": {"coordinates":[8.644913,53.053074],"type":"Point"}
}