{
  "type": "Feature",
  "properties": {
    "iso:country":"DE",
    "sg:address":"Hebbelstr. 1",
    "sg:city":"Frechen",
    "sg:phone":"+49 2234/31071",
    "sg:postcode":"50226",
    "sg:province":"Nordrhein-Westfalen",
    "wof:name":"Redaktion Industrie- Und Handelsrevue",
    "wof:placetype":"venue"
},
  "geometry": {"coordinates":[6.7481040955,50.9149513245],"type":"Point"}
}