{
  "type": "Feature",
  "properties": {
    "iso:country":"DE",
    "sg:address":"Liegnitzer Str. 35",
    "sg:city":"Berlin",
    "sg:phone":"+49 30/2640424",
    "sg:postcode":"10999",
    "sg:province":"Berlin",
    "wof:name":"Knott-seewald-gbr Agentur F\u00fcr Geschichtsrecherche",
    "wof:placetype":"venue"
},
  "geometry": {"coordinates":[13.435783,52.494404],"type":"Point"}
}