{
  "type": "Feature",
  "properties": {
    "iso:country":"DE",
    "sg:address":"Rosenweg 4",
    "sg:city":"K\u00f6nigswinter",
    "sg:postcode":"53639",
    "sg:province":"Nordrhein-Westfalen",
    "wof:name":"Ibs Ingenieurgesell. F\u00fcr Die Bewertung Und Sanierung Von",
    "wof:placetype":"venue"
},
  "geometry": {"coordinates":[7.261931,50.677677],"type":"Point"}
}