{
  "type": "Feature",
  "properties": {
    "iso:country":"DE",
    "sg:address":"Bahnhofstr. 47",
    "sg:city":"Wirges",
    "sg:phone":"+49 2602/69090",
    "sg:postcode":"56422",
    "sg:province":"Rheinland-Pfalz",
    "wof:name":"Bernd Henrici",
    "wof:placetype":"venue"
},
  "geometry": {"coordinates":[7.7939739227,50.4706077576],"type":"Point"}
}