{
  "type": "Feature",
  "properties": {
    "iso:country":"DE",
    "sg:address":"Plauener Str. 14",
    "sg:city":"Dortmund",
    "sg:postcode":"44139",
    "sg:province":"Nordrhein-Westfalen",
    "wof:name":"Stracke Gmbh",
    "wof:placetype":"venue"
},
  "geometry": {"coordinates":[7.462989,51.503944],"type":"Point"}
}