{
  "type": "Feature",
  "properties": {
    "iso:country":"DE",
    "sg:address":"Petersbergstr. 46",
    "sg:city":"Bad Honnef",
    "sg:phone":"+49 2224/70495",
    "sg:postcode":"53604",
    "sg:province":"Nordrhein-Westfalen",
    "wof:name":"Wiv-wohnwert-immobilien- Verwaltungs Gmbh",
    "wof:placetype":"venue"
},
  "geometry": {"coordinates":[7.2193608284,50.6547737122],"type":"Point"}
}