{
  "type": "Feature",
  "properties": {
    "iso:country":"DE",
    "sg:address":"Erlenweg 2",
    "sg:city":"Grebenstein",
    "sg:phone":"+49 5674/4365",
    "sg:postcode":"34393",
    "sg:province":"Hessen",
    "wof:name":"Ev. Pfarramt Grebenstein S\u00fcd Und",
    "wof:placetype":"venue"
},
  "geometry": {"coordinates":[9.4033098221,51.4445877075],"type":"Point"}
}