{
  "type": "Feature",
  "properties": {
    "iso:country":"DE",
    "sg:address":"Geniner Str. 82",
    "sg:city":"L\u00fcbeck",
    "sg:phone":"+49 451/583200",
    "sg:postcode":"23560",
    "sg:province":"Schleswig-Holstein",
    "wof:name":"Event & Production Design Gmbh",
    "wof:placetype":"venue"
},
  "geometry": {"coordinates":[10.670597,53.847511],"type":"Point"}
}