{
  "type": "Feature",
  "properties": {
    "iso:country":"DE",
    "sg:address":"Auf Dem Luxemberg 7 Breidt",
    "sg:city":"Lohmar",
    "sg:phone":"+49 4922/464447",
    "sg:postcode":"53797",
    "sg:province":"Nordrhein-Westfalen",
    "wof:name":"Elektro Johannes Schmitz Gmbh",
    "wof:placetype":"venue"
},
  "geometry": {"coordinates":[7.211563,50.840904],"type":"Point"}
}