{
  "type": "Feature",
  "properties": {
    "iso:country":"DE",
    "sg:address":"Bauerngasse 28",
    "sg:city":"Schweinfurt",
    "sg:phone":"+49 9721/21157",
    "sg:postcode":"97421",
    "sg:province":"Bayern",
    "wof:name":"Hubert Heusinger",
    "wof:placetype":"venue"
},
  "geometry": {"coordinates":[10.2311239243,50.0467262268],"type":"Point"}
}