{
  "type": "Feature",
  "properties": {
    "iso:country":"DE",
    "sg:address":"Bergheimer Str. 19",
    "sg:city":"Heidelberg",
    "sg:phone":"+49 6221/22234",
    "sg:postcode":"69115",
    "sg:province":"Baden-W\u00fcrttemberg",
    "wof:name":"Julius M\u00fcnzenmayer",
    "wof:placetype":"venue"
},
  "geometry": {"coordinates":[8.6904325485,49.4086303711],"type":"Point"}
}