{
  "type": "Feature",
  "properties": {
    "iso:country":"DE",
    "sg:address":"Medinger Str. 10",
    "sg:city":"Bad Bevensen",
    "sg:phone":"+49 5821/2415",
    "sg:postcode":"29549",
    "sg:province":"Niedersachsen",
    "wof:name":"H. Ziegler",
    "wof:placetype":"venue"
},
  "geometry": {"coordinates":[10.575972,53.079803],"type":"Point"}
}