{
  "type": "Feature",
  "properties": {
    "iso:country":"DE",
    "sg:address":"L\u00e4rchenstr. 13",
    "sg:city":"Taufkirchen",
    "sg:phone":"+49 8084/3122",
    "sg:postcode":"84416",
    "sg:province":"Bayern",
    "wof:name":"B. Prediger",
    "wof:placetype":"venue"
},
  "geometry": {"coordinates":[12.1174573898,48.3475456238],"type":"Point"}
}