{
  "type": "Feature",
  "properties": {
    "iso:country":"DE",
    "sg:address":"Talstr. 36",
    "sg:city":"Simonswald",
    "sg:phone":"+49 7683/258",
    "sg:postcode":"79263",
    "sg:province":"Baden-W\u00fcrttemberg",
    "wof:name":"E. Beier",
    "wof:placetype":"venue"
},
  "geometry": {"coordinates":[8.0608243942,48.0974349976],"type":"Point"}
}