{
  "type": "Feature",
  "properties": {
    "iso:country":"DE",
    "sg:address":"Richard-Wagner-Str. 67",
    "sg:city":"Kehl",
    "sg:phone":"+49 7851/2643",
    "sg:postcode":"77694",
    "sg:province":"Baden-W\u00fcrttemberg",
    "wof:name":"Martin Maurer Heilpraktiker",
    "wof:placetype":"venue"
},
  "geometry": {"coordinates":[7.8257169724,48.5636672974],"type":"Point"}
}