{
  "type": "Feature",
  "properties": {
    "iso:country":"DE",
    "sg:address":"Marktstr. 1",
    "sg:city":"Gr\u00e4fenhainichen",
    "sg:phone":"+49 34953/21434",
    "sg:postcode":"06773",
    "sg:province":"Sachsen-Anhalt",
    "wof:name":"Nipos Angelshop Gmbh",
    "wof:placetype":"venue"
},
  "geometry": {"coordinates":[12.45966,51.73204],"type":"Point"}
}