{
  "type": "Feature",
  "properties": {
    "iso:country":"DE",
    "sg:address":"Ludwig-Lepper-Str. 31",
    "sg:city":"Bielefeld",
    "sg:phone":"+49 521/22760",
    "sg:postcode":"33604",
    "sg:province":"Nordrhein-Westfalen",
    "wof:name":"Hans-e. Schirrmann Ingenieur",
    "wof:placetype":"venue"
},
  "geometry": {"coordinates":[8.5419912338,52.0096817017],"type":"Point"}
}