{
  "type": "Feature",
  "properties": {
    "iso:country":"DE",
    "sg:address":"Regensburger Str. 49",
    "sg:city":"Seubersdorf",
    "sg:phone":"+49 9497/6532",
    "sg:postcode":"92358",
    "sg:province":"Bayern",
    "wof:name":"R. Wittmann",
    "wof:placetype":"venue"
},
  "geometry": {"coordinates":[11.6299114227,49.1587944031],"type":"Point"}
}