{
  "type": "Feature",
  "properties": {
    "iso:country":"DE",
    "sg:address":"Steinfeldstr. 5",
    "sg:city":"Meitingen",
    "sg:phone":"+49 8271/2352",
    "sg:postcode":"86405",
    "sg:province":"Bayern",
    "wof:name":"Johannes Schulz Architekt",
    "wof:placetype":"venue"
},
  "geometry": {"coordinates":[10.861547,48.541004],"type":"Point"}
}