{
  "type": "Feature",
  "properties": {
    "iso:country":"DE",
    "sg:address":"Lehmschlenke 101",
    "sg:city":"Bottrop",
    "sg:phone":"+49 2045/7402",
    "sg:postcode":"46244",
    "sg:province":"Nordrhein-Westfalen",
    "wof:name":"Theo Igelb\u00fcscher Architekt",
    "wof:placetype":"venue"
},
  "geometry": {"coordinates":[6.895895,51.589306],"type":"Point"}
}