{
  "type": "Feature",
  "properties": {
    "iso:country":"DE",
    "sg:address":"Laufener Str. 59",
    "sg:city":"Freilassing",
    "sg:phone":"+49 8654/9479",
    "sg:postcode":"83395",
    "sg:province":"Bayern",
    "wof:name":"Hermine Schauppner Schlosserei Metallbau",
    "wof:placetype":"venue"
},
  "geometry": {"coordinates":[12.986018,47.84708],"type":"Point"}
}