{
  "type": "Feature",
  "properties": {
    "iso:country":"DE",
    "sg:address":"Bachstr. 15",
    "sg:city":"Bad Homburg",
    "sg:phone":"+49 6172/985121",
    "sg:postcode":"61350",
    "sg:province":"Hessen",
    "wof:name":"Nicole Stephan",
    "wof:placetype":"venue"
},
  "geometry": {"coordinates":[8.6100883484,50.2397880554],"type":"Point"}
}