{
  "type": "Feature",
  "properties": {
    "iso:country":"DE",
    "sg:address":"Ludgeristr. 113",
    "sg:city":"M\u00fcnster",
    "sg:phone":"+49 251/834343",
    "sg:postcode":"48143",
    "sg:province":"Nordrhein-Westfalen",
    "wof:name":"Seminar F\u00fcr Byzantinistik Bibliothek",
    "wof:placetype":"venue"
},
  "geometry": {"coordinates":[7.627564,51.960663],"type":"Point"}
}