{
  "type": "Feature",
  "properties": {
    "iso:country":"DE",
    "sg:address":"Wendezeller Ring 11b",
    "sg:city":"Wendeburg",
    "sg:phone":"+49 5303/91040",
    "sg:postcode":"38176",
    "sg:province":"Niedersachsen",
    "wof:name":"Hornig Ingenieur",
    "wof:placetype":"venue"
},
  "geometry": {"coordinates":[10.3936157227,52.3217277527],"type":"Point"}
}