{
  "type": "Feature",
  "properties": {
    "iso:country":"DE",
    "sg:address":"Dr.-Salvadore-Allende-Str. 19",
    "sg:city":"Weimar",
    "sg:phone":"+49 3643/59126",
    "sg:postcode":"99425",
    "sg:province":"Th\u00fcringen",
    "wof:name":"Helga Barthel",
    "wof:placetype":"venue"
},
  "geometry": {"coordinates":[11.3106975555,50.9750900269],"type":"Point"}
}