{
  "type": "Feature",
  "properties": {
    "iso:country":"DE",
    "sg:address":"Gerhart-Hauptmann-Str. 7",
    "sg:city":"Wiek",
    "sg:phone":"+49 38391/70508",
    "sg:postcode":"18556",
    "sg:province":"Mecklenburg-Vorpommern",
    "wof:name":"Svantevit Immobilienverwal- Tungsgesellschaft Mbh",
    "wof:placetype":"venue"
},
  "geometry": {"coordinates":[13.2946138382,54.6214904785],"type":"Point"}
}