{
  "type": "Feature",
  "properties": {
    "iso:country":"DE",
    "sg:address":"Gr\u00fcndelsteig 14",
    "sg:city":"Dresden",
    "sg:phone":"+49 351/2686851",
    "sg:postcode":"01324",
    "sg:province":"Sachsen",
    "wof:name":"Peter Renner Anlageberater",
    "wof:placetype":"venue"
},
  "geometry": {"coordinates":[13.8417806625,51.0576324463],"type":"Point"}
}