{
  "type": "Feature",
  "properties": {
    "iso:country":"DE",
    "sg:address":"Parkstr. 13",
    "sg:city":"Wiesbaden",
    "sg:postcode":"65189",
    "sg:province":"Hessen",
    "wof:name":"Redaktion Far East Trade Inwed Informations- Und",
    "wof:placetype":"venue"
},
  "geometry": {"coordinates":[8.2534227371,50.0837211609],"type":"Point"}
}