{
  "type": "Feature",
  "properties": {
    "iso:country":"DE",
    "sg:address":"Markgrafenstr. 39",
    "sg:city":"Berlin",
    "sg:phone":"+49 30/2044369",
    "sg:postcode":"10117",
    "sg:province":"Berlin",
    "wof:name":"Adolf Niggemeier Rechtsanwalt",
    "wof:placetype":"venue"
},
  "geometry": {"coordinates":[13.3933534622,52.514251709],"type":"Point"}
}