{
  "type": "Feature",
  "properties": {
    "iso:country":"DE",
    "sg:address":"Am Waldhof 8",
    "sg:city":"Kisdorf",
    "sg:phone":"+49 4194/555",
    "sg:postcode":"24629",
    "sg:province":"Schleswig-Holstein",
    "wof:name":"Bernhard Kr\u00f6ger",
    "wof:placetype":"venue"
},
  "geometry": {"coordinates":[10.0931,53.81448],"type":"Point"}
}