{
  "type": "Feature",
  "properties": {
    "iso:country":"DE",
    "sg:address":"Urgasse 20",
    "sg:city":"Linsengericht",
    "sg:phone":"+49 6051/71342",
    "sg:postcode":"63589",
    "sg:province":"Hessen",
    "wof:name":"Karl Bohlender",
    "wof:placetype":"venue"
},
  "geometry": {"coordinates":[9.238781,50.177814],"type":"Point"}
}