{
  "type": "Feature",
  "properties": {
    "iso:country":"DE",
    "sg:address":"Marktstr. 7",
    "sg:city":"Soltau",
    "sg:phone":"+49 5191/72107",
    "sg:postcode":"29614",
    "sg:province":"Niedersachsen",
    "wof:name":"Eiscafe Venezia",
    "wof:placetype":"venue"
},
  "geometry": {"coordinates":[9.839708,52.985939],"type":"Point"}
}