{
  "type": "Feature",
  "properties": {
    "iso:country":"DE",
    "sg:address":"Westenmauer 39",
    "sg:city":"Kamen",
    "sg:phone":"+49 4923/0710214",
    "sg:postcode":"59174",
    "sg:province":"Nordrhein-Westfalen",
    "wof:name":"Werner Lang",
    "wof:placetype":"venue"
},
  "geometry": {"coordinates":[7.6578431129,51.5937271118],"type":"Point"}
}