{
  "type": "Feature",
  "properties": {
    "iso:country":"DE",
    "sg:address":"Ehestorfer Heuweg 14",
    "sg:city":"Hamburg",
    "sg:phone":"+49 40/7962015",
    "sg:postcode":"21149",
    "sg:province":"Hamburg",
    "wof:name":"Restaurant Landhaus J\u00e4gerhof Soltau Gmbh",
    "wof:placetype":"venue"
},
  "geometry": {"coordinates":[9.8918399811,53.4628791809],"type":"Point"}
}