{
  "type": "Feature",
  "properties": {
    "iso:country":"DE",
    "sg:address":"Hamburger Str. 49",
    "sg:city":"Ammersbek",
    "sg:phone":"+49 40/6051922",
    "sg:postcode":"22949",
    "sg:province":"Schleswig-Holstein",
    "wof:name":"Uwe Kramp",
    "wof:placetype":"venue"
},
  "geometry": {"coordinates":[10.1589736938,53.68542099],"type":"Point"}
}