{
  "type": "Feature",
  "properties": {
    "iso:country":"DE",
    "sg:address":"H\u00f6heweg 9",
    "sg:city":"Obernkirchen",
    "sg:phone":"+49 5724/4506",
    "sg:postcode":"31683",
    "sg:province":"Niedersachsen",
    "wof:name":"M. Becker",
    "wof:placetype":"venue"
},
  "geometry": {"coordinates":[9.135625,52.270737],"type":"Point"}
}