{
  "type": "Feature",
  "properties": {
    "iso:country":"DE",
    "sg:address":"An der Martinskirche 19 a",
    "sg:city":"Osnabr\u00fcck",
    "sg:phone":"+49 541/442828",
    "sg:postcode":"49078",
    "sg:province":"Niedersachsen",
    "wof:name":"Horst G. Altmann \u00dcbersetzungsb\u00fcro",
    "wof:placetype":"venue"
},
  "geometry": {"coordinates":[7.988267,52.262428],"type":"Point"}
}