{
  "type": "Feature",
  "properties": {
    "iso:country":"DE",
    "sg:address":"Malchinger Str.",
    "sg:city":"Maisach",
    "sg:phone":"+49 8141/93181",
    "sg:postcode":"82216",
    "sg:province":"Bayern",
    "wof:name":"Kraus",
    "wof:placetype":"venue"
},
  "geometry": {"coordinates":[11.251247,48.21487],"type":"Point"}
}