{
  "type": "Feature",
  "properties": {
    "iso:country":"DE",
    "sg:address":"Kammweg 1",
    "sg:city":"Merzenich",
    "sg:phone":"+49 2421/35668",
    "sg:postcode":"52399",
    "sg:province":"Nordrhein-Westfalen",
    "wof:name":"Schall Gmbh",
    "wof:placetype":"venue"
},
  "geometry": {"coordinates":[6.523895,50.825066],"type":"Point"}
}