{
  "type": "Feature",
  "properties": {
    "iso:country":"DE",
    "sg:address":"Sternstr. 15",
    "sg:city":"Hanau",
    "sg:phone":"+49 6181/2556511",
    "sg:postcode":"63450",
    "sg:province":"Hessen",
    "wof:name":"Video-traumland",
    "wof:placetype":"venue"
},
  "geometry": {"coordinates":[8.9144773483,50.134349823],"type":"Point"}
}