{
  "type": "Feature",
  "properties": {
    "iso:country":"DE",
    "sg:address":"Ernst-Grote-Str. 42",
    "sg:city":"Isernhagen",
    "sg:phone":"+49 511/612653",
    "sg:postcode":"30916",
    "sg:province":"Niedersachsen",
    "wof:name":"Astrid Krau\u00df",
    "wof:placetype":"venue"
},
  "geometry": {"coordinates":[9.8376750946,52.4317588806],"type":"Point"}
}