{
  "type": "Feature",
  "properties": {
    "iso:country":"DE",
    "sg:address":"K\u00f6lner Str. 1",
    "sg:city":"Eschborn",
    "sg:postcode":"65760",
    "sg:province":"Hessen",
    "wof:name":"Euro 2000 Gmbh",
    "wof:placetype":"venue"
},
  "geometry": {"coordinates":[8.5705223083,50.1329154968],"type":"Point"}
}