{
  "type": "Feature",
  "properties": {
    "iso:country":"DE",
    "sg:address":"Leveringhauser Str. 96",
    "sg:city":"Castrop-Rauxel",
    "sg:phone":"+49 2305/86523",
    "sg:postcode":"44581",
    "sg:province":"Nordrhein-Westfalen",
    "wof:name":"Reginas Stuben",
    "wof:placetype":"venue"
},
  "geometry": {"coordinates":[7.3532338142,51.596408844],"type":"Point"}
}