{
  "type": "Feature",
  "properties": {
    "iso:country":"DE",
    "sg:address":"H\u00f6henweg 20",
    "sg:city":"Hagen",
    "sg:phone":"+49 5401/89110",
    "sg:postcode":"49170",
    "sg:province":"Niedersachsen",
    "wof:name":"Loose Wassertechnik",
    "wof:placetype":"venue"
},
  "geometry": {"coordinates":[7.9901337624,52.1982307434],"type":"Point"}
}