{
  "type": "Feature",
  "properties": {
    "iso:country":"DE",
    "sg:address":"Riehler Str. 59",
    "sg:city":"K\u00f6ln",
    "sg:phone":"+49 221/2400060",
    "sg:postcode":"50668",
    "sg:province":"Nordrhein-Westfalen",
    "wof:name":"P.kom Agentur F\u00fcr Kommunikation Gmbh",
    "wof:placetype":"venue"
},
  "geometry": {"coordinates":[6.964717865,50.9544487],"type":"Point"}
}