{
  "type": "Feature",
  "properties": {
    "iso:country":"DE",
    "sg:address":"M\u00f6nchebergstr. 41-43",
    "sg:city":"Kassel",
    "sg:phone":"+49 561/9800",
    "sg:postcode":"34125",
    "sg:province":"Hessen",
    "wof:name":"Krankenhausvollapotheke In Den St\u00e4dt. Kliniken",
    "wof:placetype":"venue"
},
  "geometry": {"coordinates":[9.509461,51.327061],"type":"Point"}
}