{
  "type": "Feature",
  "properties": {
    "iso:country":"DE",
    "sg:address":"Berliner Str. 98",
    "sg:city":"Berlin",
    "sg:phone":"+49 30/4334051",
    "sg:postcode":"13507",
    "sg:province":"Berlin",
    "wof:name":"Restaurant Arcino",
    "wof:placetype":"venue"
},
  "geometry": {"coordinates":[13.2843961716,52.589263916],"type":"Point"}
}