{
  "type": "Feature",
  "properties": {
    "iso:country":"DE",
    "sg:address":"Josefstaler Str. 264",
    "sg:city":"St. Ingbert",
    "sg:phone":"+49 6894/4720",
    "sg:postcode":"66386",
    "sg:province":"Saarland",
    "wof:name":"M. Singer",
    "wof:placetype":"venue"
},
  "geometry": {"coordinates":[7.0987448692,49.2886390686],"type":"Point"}
}