{
  "type": "Feature",
  "properties": {
    "iso:country":"DE",
    "sg:address":"F\u00e4hrstr.",
    "sg:city":"Eisenh\u00fcttenstadt",
    "sg:phone":"+49 3364/61058",
    "sg:postcode":"15890",
    "sg:province":"Brandenburg",
    "wof:name":"Emb Bautechnik Handels- Gesellschaft Mbh",
    "wof:placetype":"venue"
},
  "geometry": {"coordinates":[14.646271,52.143635],"type":"Point"}
}