{
  "type": "Feature",
  "properties": {
    "iso:country":"DE",
    "sg:address":"Hattinger Str. 52",
    "sg:city":"Bochum",
    "sg:phone":"+49 234/37041",
    "sg:postcode":"44789",
    "sg:province":"Nordrhein-Westfalen",
    "wof:name":"Heinrich Sternemann",
    "wof:placetype":"venue"
},
  "geometry": {"coordinates":[7.212729,51.471581],"type":"Point"}
}