{
  "type": "Feature",
  "properties": {
    "iso:country":"DE",
    "sg:address":"\u00dcberruhrstr. 51 a",
    "sg:city":"Essen",
    "sg:phone":"+49 201/582140",
    "sg:postcode":"45277",
    "sg:province":"Nordrhein-Westfalen",
    "wof:name":"Heinrich Faber Rechtsanwalt",
    "wof:placetype":"venue"
},
  "geometry": {"coordinates":[7.0778579712,51.4349861145],"type":"Point"}
}