{
  "type": "Feature",
  "properties": {
    "iso:country":"DE",
    "sg:address":"Leonhardistr. 10",
    "sg:city":"Hebertsfelden",
    "sg:postcode":"84332",
    "sg:province":"Bayern",
    "wof:name":"Rudolf Wimmer",
    "wof:placetype":"venue"
},
  "geometry": {"coordinates":[12.80915,48.465721],"type":"Point"}
}