{
  "type": "Feature",
  "properties": {
    "iso:country":"DE",
    "sg:address":"Mozartstr. 20",
    "sg:city":"Mandelbachtal",
    "sg:phone":"+49 6893/2632",
    "sg:postcode":"66399",
    "sg:province":"Saarland",
    "wof:name":"Kai Braeuer",
    "wof:placetype":"venue"
},
  "geometry": {"coordinates":[7.1462430954,49.1939430237],"type":"Point"}
}