{
  "type": "Feature",
  "properties": {
    "iso:country":"DE",
    "sg:address":"Luisenstr. 2",
    "sg:city":"Wolfach",
    "sg:phone":"+49 7834/83850",
    "sg:postcode":"77709",
    "sg:province":"Baden-W\u00fcrttemberg",
    "wof:name":"Johannes-brenz-heim Ev. Alten- Und",
    "wof:placetype":"venue"
},
  "geometry": {"coordinates":[8.226162,48.299828],"type":"Point"}
}