{
  "type": "Feature",
  "properties": {
    "iso:country":"DE",
    "sg:address":"Weinreihe 15",
    "sg:city":"Bad Sooden-Allendorf",
    "sg:phone":"+49 5652/2469",
    "sg:postcode":"37242",
    "sg:province":"Hessen",
    "wof:name":"Buchhandlung Goldmann Inh. Ursula Vogeley E. K.",
    "wof:placetype":"venue"
},
  "geometry": {"coordinates":[9.9632024765,51.2691078186],"type":"Point"}
}