{
  "type": "Feature",
  "properties": {
    "iso:country":"DE",
    "sg:address":"Borsigstr. 41",
    "sg:city":"Wolfsburg",
    "sg:phone":"+49 5361/52866",
    "sg:postcode":"38446",
    "sg:province":"Niedersachsen",
    "wof:name":"Fliesenparadies",
    "wof:placetype":"venue"
},
  "geometry": {"coordinates":[10.8214626312,52.4283294678],"type":"Point"}
}