{
  "type": "Feature",
  "properties": {
    "iso:country":"DE",
    "sg:address":"Achterstr. 2b",
    "sg:city":"Heiligenhafen",
    "sg:phone":"+49 4362/1021",
    "sg:postcode":"23774",
    "sg:province":"Schleswig-Holstein",
    "wof:name":"Robin Yacht-charter Gmbh",
    "wof:placetype":"venue"
},
  "geometry": {"coordinates":[10.975635,54.372501],"type":"Point"}
}