{
  "type": "Feature",
  "properties": {
    "iso:country":"DE",
    "sg:address":"Kapellenstr. 26",
    "sg:city":"Bamberg",
    "sg:phone":"+49 951/916400",
    "sg:postcode":"96050",
    "sg:province":"Bayern",
    "wof:name":"Hotel Alt Wunderburg",
    "wof:placetype":"venue"
},
  "geometry": {"coordinates":[10.909743309,49.8898658752],"type":"Point"}
}