{
  "type": "Feature",
  "properties": {
    "iso:country":"DE",
    "sg:address":"Schillerstr. 57",
    "sg:city":"Cuxhaven",
    "sg:phone":"+49 4721/554144",
    "sg:postcode":"27472",
    "sg:province":"Niedersachsen",
    "wof:name":"Hans-dieter Bauer",
    "wof:placetype":"venue"
},
  "geometry": {"coordinates":[8.6989030838,53.8705749512],"type":"Point"}
}