{
  "type": "Feature",
  "properties": {
    "iso:country":"DE",
    "sg:address":"Sachsenstr. 70",
    "sg:city":"Marl",
    "sg:phone":"+49 2365/933552",
    "sg:postcode":"45770",
    "sg:province":"Nordrhein-Westfalen",
    "wof:name":"Pc - Doktoren Computer Service Gmbh",
    "wof:placetype":"venue"
},
  "geometry": {"coordinates":[7.1132631302,51.6525726318],"type":"Point"}
}