{
  "type": "Feature",
  "properties": {
    "iso:country":"DE",
    "sg:address":"Falkenseer Chaussee 50",
    "sg:city":"Berlin",
    "sg:phone":"+49 30/3721452",
    "sg:postcode":"13583",
    "sg:province":"Berlin",
    "wof:name":"Esso Deutschland Gmbh",
    "wof:placetype":"venue"
},
  "geometry": {"coordinates":[13.1787443161,52.5488777161],"type":"Point"}
}