{
  "type": "Feature",
  "properties": {
    "iso:country":"DE",
    "sg:address":"Glash\u00fctte 2",
    "sg:city":"Witzenhausen",
    "sg:phone":"+49 5545/560",
    "sg:postcode":"37217",
    "sg:province":"Hessen",
    "wof:name":"Pension Fricke",
    "wof:placetype":"venue"
},
  "geometry": {"coordinates":[9.7409801483,51.3634300232],"type":"Point"}
}