{
  "type": "Feature",
  "properties": {
    "iso:country":"DE",
    "sg:address":"V\u00f6lklinger Str. 45",
    "sg:city":"V\u00f6lklingen",
    "sg:phone":"+49 6898/42220",
    "sg:postcode":"66333",
    "sg:province":"Saarland",
    "wof:name":"Pizza Expre\u00df Taranto",
    "wof:placetype":"venue"
},
  "geometry": {"coordinates":[6.809876,49.222702],"type":"Point"}
}