{
  "type": "Feature",
  "properties": {
    "iso:country":"DE",
    "sg:address":"Van-Ronzelen-Str.",
    "sg:city":"Bremerhaven",
    "sg:phone":"+49 471/4820722",
    "sg:postcode":"27568",
    "sg:province":"Bremen",
    "wof:name":"Deutsches Schiffahrtmuseum Bibliothek",
    "wof:placetype":"venue"
},
  "geometry": {"coordinates":[8.57993,53.538555],"type":"Point"}
}