{
  "type": "Feature",
  "properties": {
    "iso:country":"DE",
    "sg:address":"Altenberger Weg 1",
    "sg:city":"Billerbeck",
    "sg:phone":"+49 2543/6285",
    "sg:postcode":"48727",
    "sg:province":"Nordrhein-Westfalen",
    "wof:name":"Gievert",
    "wof:placetype":"venue"
},
  "geometry": {"coordinates":[7.295324,51.979855],"type":"Point"}
}