{
  "type": "Feature",
  "properties": {
    "iso:country":"DE",
    "sg:address":"86492",
    "sg:city":"Egling",
    "sg:phone":"+49 8206/246",
    "sg:postcode":"86492",
    "sg:province":"Bayern",
    "wof:name":"Deutsche Bahn Ag",
    "wof:placetype":"venue"
},
  "geometry": {"coordinates":[10.9825801849,48.1873817444],"type":"Point"}
}