{
  "type": "Feature",
  "properties": {
    "iso:country":"DE",
    "sg:address":"Vor der Bahn 2",
    "sg:city":"Estorf",
    "sg:phone":"+49 5025/226",
    "sg:postcode":"31629",
    "sg:province":"Niedersachsen",
    "wof:name":"Deutsche Bahn Ag",
    "wof:placetype":"venue"
},
  "geometry": {"coordinates":[9.1539888382,52.5899543762],"type":"Point"}
}