{
  "type": "Feature",
  "properties": {
    "iso:country":"DE",
    "sg:address":"Bahnhofstr. 5",
    "sg:city":"Lindau",
    "sg:phone":"+49 39246/7163",
    "sg:postcode":"39264",
    "sg:province":"Sachsen-Anhalt",
    "wof:name":"Bahnhofgastst\u00e4tte Anne",
    "wof:placetype":"venue"
},
  "geometry": {"coordinates":[12.1056232452,52.0356750488],"type":"Point"}
}