{
  "type": "Feature",
  "properties": {
    "iso:country":"DE",
    "sg:address":"Kestnerstr. 1",
    "sg:city":"Detmold",
    "sg:postcode":"32756",
    "sg:province":"Nordrhein-Westfalen",
    "wof:name":"Mikla Warenhandels Gmbh",
    "wof:placetype":"venue"
},
  "geometry": {"coordinates":[8.8851270676,51.9262542725],"type":"Point"}
}