{
  "type": "Feature",
  "properties": {
    "iso:country":"DE",
    "sg:address":"Langgruben 1",
    "sg:city":"Wolpertshausen",
    "sg:phone":"+49 7904/97900",
    "sg:postcode":"74549",
    "sg:province":"Baden-W\u00fcrttemberg",
    "wof:name":"Charrier Gmbh",
    "wof:placetype":"venue"
},
  "geometry": {"coordinates":[9.8814353943,49.1776542664],"type":"Point"}
}