{
  "type": "Feature",
  "properties": {
    "iso:country":"DE",
    "sg:address":"Im Klingelrech 2",
    "sg:city":"Kirn",
    "sg:phone":"+49 6752/3933",
    "sg:postcode":"55606",
    "sg:province":"Rheinland-Pfalz",
    "wof:name":"Horst Traut",
    "wof:placetype":"venue"
},
  "geometry": {"coordinates":[7.4611048698,49.7851600647],"type":"Point"}
}