{
  "type": "Feature",
  "properties": {
    "iso:country":"DE",
    "sg:address":"Hauptstr 2",
    "sg:city":"Ruderatshofen",
    "sg:phone":"+49 8343/92390",
    "sg:postcode":"87674",
    "sg:province":"Bayern",
    "wof:name":"Feink\u00e4serei Stich Gmbh & Co Kg",
    "wof:placetype":"venue"
},
  "geometry": {"coordinates":[10.592534,47.819256],"type":"Point"}
}