{
  "type": "Feature",
  "properties": {
    "iso:country":"DE",
    "sg:address":"Wilhelmstr. 6",
    "sg:city":"Hofheim",
    "sg:phone":"+49 6192/22071",
    "sg:postcode":"65719",
    "sg:province":"Hessen",
    "wof:name":"Maria Theresia Tausend Heilpraktikerin",
    "wof:placetype":"venue"
},
  "geometry": {"coordinates":[8.4423427582,50.0860328674],"type":"Point"}
}