{
  "type": "Feature",
  "properties": {
    "iso:country":"DE",
    "sg:address":"Pforzheimer Str. 62",
    "sg:city":"Bretten",
    "sg:phone":"+49 7252/975630",
    "sg:postcode":"75015",
    "sg:province":"Baden-W\u00fcrttemberg",
    "wof:name":"D\u00f6hler & Gerweck Entwicklungs- Und Montagetechnik Gmbh",
    "wof:placetype":"venue"
},
  "geometry": {"coordinates":[8.7039680481,49.0298957825],"type":"Point"}
}