{
  "type": "Feature",
  "properties": {
    "iso:country":"DE",
    "sg:address":"Dietrichstr. 11",
    "sg:city":"Karlsruhe",
    "sg:phone":"+49 721/41892",
    "sg:postcode":"76227",
    "sg:province":"Baden-W\u00fcrttemberg",
    "wof:name":"Kurt Kraus",
    "wof:placetype":"venue"
},
  "geometry": {"coordinates":[8.4580631256,48.9958724976],"type":"Point"}
}