{
  "type": "Feature",
  "properties": {
    "iso:country":"DE",
    "sg:address":"Halbigstr. 1",
    "sg:city":"M\u00fcnchen",
    "sg:phone":"+49 89/650478",
    "sg:postcode":"81543",
    "sg:province":"Bayern",
    "wof:name":"H. Waldhauser Kunstmaler",
    "wof:placetype":"venue"
},
  "geometry": {"coordinates":[11.566749,48.108799],"type":"Point"}
}