{
  "type": "Feature",
  "properties": {
    "iso:country":"DE",
    "sg:address":"Im Steinbruch",
    "sg:city":"Beilngries",
    "sg:postcode":"92339",
    "sg:province":"Bayern",
    "wof:name":"Altm\u00fchl-kalkstein Gmbh & Co. Kg",
    "wof:placetype":"venue"
},
  "geometry": {"coordinates":[11.4949073792,48.9718894958],"type":"Point"}
}