{
  "type": "Feature",
  "properties": {
    "iso:country":"DE",
    "sg:address":"Nordlandweg 45",
    "sg:city":"Hamburg",
    "sg:phone":"+49 40/67941662",
    "sg:postcode":"22145",
    "sg:province":"Hamburg",
    "wof:name":"Pro Plan Vertriebsb\u00fcro E. K.",
    "wof:placetype":"venue"
},
  "geometry": {"coordinates":[10.1681032181,53.6302947998],"type":"Point"}
}