{
  "type": "Feature",
  "properties": {
    "iso:country":"DE",
    "sg:address":"Westerbachstr. 45",
    "sg:city":"Frankfurt",
    "sg:phone":"+49 69/78060",
    "sg:postcode":"60489",
    "sg:province":"Hessen",
    "wof:name":"Poly-clip System Verwaltungs Gmbh",
    "wof:placetype":"venue"
},
  "geometry": {"coordinates":[8.602191,50.122437],"type":"Point"}
}