{
  "type": "Feature",
  "properties": {
    "iso:country":"DE",
    "sg:address":"Niederkasseler Lohweg 191",
    "sg:city":"D\u00fcsseldorf",
    "sg:phone":"+49 211/5066690",
    "sg:postcode":"40547",
    "sg:province":"Nordrhein-Westfalen",
    "wof:name":"Emerson Energy Systems Gmbh",
    "wof:placetype":"venue"
},
  "geometry": {"coordinates":[6.7347989082,51.2408294678],"type":"Point"}
}