{
  "type": "Feature",
  "properties": {
    "iso:country":"DE",
    "sg:address":"Seehausweg 21",
    "sg:city":"Maulbronn",
    "sg:phone":"+49 7043/2659",
    "sg:postcode":"75433",
    "sg:province":"Baden-W\u00fcrttemberg",
    "wof:name":"J\u00f6rg Ritter",
    "wof:placetype":"venue"
},
  "geometry": {"coordinates":[8.7980604172,48.9978713989],"type":"Point"}
}