{
  "type": "Feature",
  "properties": {
    "iso:country":"DE",
    "sg:address":"Kuhbergweg 5",
    "sg:city":"Zwickau",
    "sg:phone":"+49 375/525370",
    "sg:postcode":"08058",
    "sg:province":"Sachsen",
    "wof:name":"Joachim Kre\u00df",
    "wof:placetype":"venue"
},
  "geometry": {"coordinates":[12.4689626694,50.7409439087],"type":"Point"}
}