{
  "type": "Feature",
  "properties": {
    "iso:country":"DE",
    "sg:address":"Hauptstr. 55",
    "sg:city":"Helmeroth",
    "sg:phone":"+49 2682/4749",
    "sg:postcode":"57612",
    "sg:province":"Rheinland-Pfalz",
    "wof:name":"G. U. G. S\u00e4lzer",
    "wof:placetype":"venue"
},
  "geometry": {"coordinates":[7.7393279076,50.7403945923],"type":"Point"}
}