{
  "type": "Feature",
  "properties": {
    "iso:country":"DE",
    "sg:address":"Kohlerstr. 1",
    "sg:city":"Calw",
    "sg:phone":"+49 7051/50712",
    "sg:postcode":"75365",
    "sg:province":"Baden-W\u00fcrttemberg",
    "wof:name":"Georg Rentschler",
    "wof:placetype":"venue"
},
  "geometry": {"coordinates":[8.704705,48.713116],"type":"Point"}
}