{
  "type": "Feature",
  "properties": {
    "iso:country":"DE",
    "sg:address":"Hohe Eiche 15",
    "sg:city":"Bochum",
    "sg:phone":"+49 234/294097",
    "sg:postcode":"44892",
    "sg:province":"Nordrhein-Westfalen",
    "wof:name":"O. Lohkamp",
    "wof:placetype":"venue"
},
  "geometry": {"coordinates":[7.3052210808,51.4754562378],"type":"Point"}
}