{
  "type": "Feature",
  "properties": {
    "iso:country":"DE",
    "sg:address":"Gro\u00dfe Gasse 43",
    "sg:city":"Gierst\u00e4dt",
    "sg:phone":"+49 36206/23255",
    "sg:postcode":"99100",
    "sg:province":"Th\u00fcringen",
    "wof:name":"Heinz K\u00fchnhausen",
    "wof:placetype":"venue"
},
  "geometry": {"coordinates":[10.823147,51.042355],"type":"Point"}
}