{
  "type": "Feature",
  "properties": {
    "iso:country":"DE",
    "sg:address":"Promenadenstr. 24",
    "sg:city":"Bensheim",
    "sg:phone":"+49 6251/65313",
    "sg:postcode":"64625",
    "sg:province":"Hessen",
    "wof:name":"Gastro-g.w. Gmbh",
    "wof:placetype":"venue"
},
  "geometry": {"coordinates":[8.6194868088,49.681968689],"type":"Point"}
}