{
  "type": "Feature",
  "properties": {
    "iso:country":"DE",
    "sg:address":"Knobelsdorffstr. 95",
    "sg:city":"Berlin",
    "sg:phone":"+49 30/3069020",
    "sg:postcode":"14050",
    "sg:province":"Berlin",
    "wof:name":"Gemeinn\u00fctzige Heimst\u00e4ttenbau Der Bvg Gmbh",
    "wof:placetype":"venue"
},
  "geometry": {"coordinates":[13.280522,52.512642],"type":"Point"}
}