{
  "type": "Feature",
  "properties": {
    "iso:country":"DE",
    "sg:address":"Zum Limmer 17",
    "sg:city":"Visselh\u00f6vede",
    "sg:phone":"+49 4262/573",
    "sg:postcode":"27374",
    "sg:province":"Niedersachsen",
    "wof:name":"Klaus Hoffmann",
    "wof:placetype":"venue"
},
  "geometry": {"coordinates":[9.573701,52.97781],"type":"Point"}
}