{
  "type": "Feature",
  "properties": {
    "iso:country":"DE",
    "sg:address":"R\u00fcckershagener Str. 8",
    "sg:city":"Gerabronn",
    "sg:phone":"+49 4979/5296140",
    "sg:postcode":"74582",
    "sg:province":"Baden-W\u00fcrttemberg",
    "wof:name":"Ekm Maschinenbau Gmbh",
    "wof:placetype":"venue"
},
  "geometry": {"coordinates":[9.931163,49.249153],"type":"Point"}
}