{
  "type": "Feature",
  "properties": {
    "iso:country":"DE",
    "sg:address":"Hennigesstr. 17",
    "sg:city":"Iserlohn",
    "sg:postcode":"58640",
    "sg:province":"Nordrhein-Westfalen",
    "wof:name":"Dr. Bartels Immobilien Verwaltungs- Gmbh",
    "wof:placetype":"venue"
},
  "geometry": {"coordinates":[7.655967,51.438198],"type":"Point"}
}