{
  "type": "Feature",
  "properties": {
    "iso:country":"DE",
    "sg:address":"Westpreu\u00dfenstr. 85",
    "sg:city":"Essen",
    "sg:phone":"+49 201/464900",
    "sg:postcode":"45259",
    "sg:province":"Nordrhein-Westfalen",
    "wof:name":"Anna B\u00f6gershausen Steuerberaterin",
    "wof:placetype":"venue"
},
  "geometry": {"coordinates":[7.0550317764,51.4024543762],"type":"Point"}
}