{
  "type": "Feature",
  "properties": {
    "iso:country":"DE",
    "sg:address":"Steinberger Str. 5",
    "sg:city":"Remscheid",
    "sg:phone":"+49 2191/927751",
    "sg:postcode":"42855",
    "sg:province":"Nordrhein-Westfalen",
    "wof:name":"Stanzmesserfabrik Heinrich Janssen Jr.",
    "wof:placetype":"venue"
},
  "geometry": {"coordinates":[7.1912808418,51.1866722107],"type":"Point"}
}