{
  "type": "Feature",
  "properties": {
    "iso:country":"DE",
    "sg:address":"Nothberger Str. 83",
    "sg:city":"Eschweiler",
    "sg:phone":"+49 2403/26091",
    "sg:postcode":"52249",
    "sg:province":"Nordrhein-Westfalen",
    "wof:name":"Glasmacher Stahl- Und Metallbau",
    "wof:placetype":"venue"
},
  "geometry": {"coordinates":[6.280116,50.813248],"type":"Point"}
}