{
  "type": "Feature",
  "properties": {
    "iso:country":"DE",
    "sg:address":"Marktplatz 14",
    "sg:city":"Monheim",
    "sg:phone":"+49 9091/5945",
    "sg:postcode":"86653",
    "sg:province":"Bayern",
    "wof:name":"Roland Ferber",
    "wof:placetype":"venue"
},
  "geometry": {"coordinates":[10.856669426,48.8423995972],"type":"Point"}
}