{
  "type": "Feature",
  "properties": {
    "iso:country":"DE",
    "sg:address":"Friedrichstr. 176-179",
    "sg:city":"Berlin",
    "sg:phone":"+49 30/2010111",
    "sg:postcode":"10117",
    "sg:province":"Berlin",
    "wof:name":"Art Dynamics Werbe- Und Veranstaltungsagentur Gmbh",
    "wof:placetype":"venue"
},
  "geometry": {"coordinates":[13.38914,52.513691],"type":"Point"}
}