{
  "type": "Feature",
  "properties": {
    "iso:country":"DE",
    "sg:address":"Hohenackerstr. 5",
    "sg:city":"Fellbach",
    "sg:phone":"+49 711/512620",
    "sg:postcode":"70736",
    "sg:province":"Baden-W\u00fcrttemberg",
    "wof:name":"Andreas B\u00fcrkle Ingenieur",
    "wof:placetype":"venue"
},
  "geometry": {"coordinates":[9.2696485519,48.8356132507],"type":"Point"}
}