{
  "type": "Feature",
  "properties": {
    "iso:country":"DE",
    "sg:address":"Licher Str. 21",
    "sg:city":"Gie\u00dfen",
    "sg:phone":"+49 641/46716",
    "sg:postcode":"35394",
    "sg:province":"Hessen",
    "wof:name":"Ingo Pfeiffer",
    "wof:placetype":"venue"
},
  "geometry": {"coordinates":[8.6877584457,50.5834960938],"type":"Point"}
}