{
  "type": "Feature",
  "properties": {
    "iso:country":"DE",
    "sg:address":"Bahnhofstr. 16",
    "sg:city":"Maisach",
    "sg:phone":"+49 8141/94957",
    "sg:postcode":"82216",
    "sg:province":"Bayern",
    "wof:name":"Eiscafe Alberto",
    "wof:placetype":"venue"
},
  "geometry": {"coordinates":[11.257706,48.215477],"type":"Point"}
}