{
  "type": "Feature",
  "properties": {
    "iso:country":"DE",
    "sg:address":"Herrnsdorferstrasse",
    "sg:city":"Wolkenburg",
    "sg:postcode":"08399",
    "wof:name":"Bauernhof Zum Silberbergwerk",
    "wof:placetype":"venue"
},
  "geometry": {"coordinates":[12.6645317078,50.8984680176],"type":"Point"}
}