{
  "type": "Feature",
  "properties": {
    "iso:country":"DE",
    "sg:address":"Kesselweg 12",
    "sg:city":"Waldachtal",
    "sg:phone":"+49 7486/618",
    "sg:postcode":"72178",
    "sg:province":"Baden-W\u00fcrttemberg",
    "wof:name":"Willy Kohlmus",
    "wof:placetype":"venue"
},
  "geometry": {"coordinates":[8.610713,48.483601],"type":"Point"}
}