{
  "type": "Feature",
  "properties": {
    "iso:country":"DE",
    "sg:address":"Fichtestr. 24",
    "sg:city":"Ingolstadt",
    "sg:phone":"+49 841/956377",
    "sg:postcode":"85055",
    "sg:province":"Bayern",
    "wof:name":"Regler Verlagswesen",
    "wof:placetype":"venue"
},
  "geometry": {"coordinates":[11.4424753189,48.7824859619],"type":"Point"}
}