{
  "type": "Feature",
  "properties": {
    "iso:country":"DE",
    "sg:address":"Haydnstr. 9",
    "sg:city":"Pf\u00f6rring",
    "sg:phone":"+49 8403/450",
    "sg:postcode":"85104",
    "sg:province":"Bayern",
    "wof:name":"Gottfried Vent",
    "wof:placetype":"venue"
},
  "geometry": {"coordinates":[11.680729866,48.8089790344],"type":"Point"}
}