{
  "type": "Feature",
  "properties": {
    "iso:country":"DE",
    "sg:address":"Hauptstr. 15",
    "sg:city":"Bockhorn",
    "sg:phone":"+49 4452/7777",
    "sg:postcode":"26345",
    "sg:province":"Niedersachsen",
    "wof:name":"Udo Lammers",
    "wof:placetype":"venue"
},
  "geometry": {"coordinates":[8.0033740997,53.3780555725],"type":"Point"}
}