{
  "type": "Feature",
  "properties": {
    "iso:country":"DE",
    "sg:address":"Feldstr. 24",
    "sg:city":"Salzwedel",
    "sg:phone":"+49 3901/422450",
    "sg:postcode":"29410",
    "sg:province":"Sachsen-Anhalt",
    "wof:name":"Udo Tiedge",
    "wof:placetype":"venue"
},
  "geometry": {"coordinates":[11.155542,52.862907],"type":"Point"}
}