{
  "type": "Feature",
  "properties": {
    "iso:country":"DE",
    "sg:address":"Kirchstr. 37",
    "sg:city":"Schwarme",
    "sg:phone":"+49 4258/280",
    "sg:postcode":"27327",
    "sg:province":"Niedersachsen",
    "wof:name":"Heinz Rosenhagen",
    "wof:placetype":"venue"
},
  "geometry": {"coordinates":[9.019516,52.902542],"type":"Point"}
}