{
  "type": "Feature",
  "properties": {
    "iso:country":"DE",
    "sg:address":"Westerwieher Str. 196",
    "sg:city":"Rietberg",
    "sg:postcode":"33397",
    "sg:province":"Nordrhein-Westfalen",
    "wof:name":"F & I Putz Gmbh",
    "wof:placetype":"venue"
},
  "geometry": {"coordinates":[8.47632,51.811169],"type":"Point"}
}