{
  "type": "Feature",
  "properties": {
    "iso:country":"DE",
    "sg:address":"Ackerstr. 75",
    "sg:city":"D\u00fcsseldorf",
    "sg:phone":"+49 4921/1674360",
    "sg:postcode":"40233",
    "sg:province":"Nordrhein-Westfalen",
    "wof:name":"Gentz Schl\u00dcsseldienst",
    "wof:placetype":"venue"
},
  "geometry": {"coordinates":[6.801774025,51.2275466919],"type":"Point"}
}