{
  "type": "Feature",
  "properties": {
    "iso:country":"DE",
    "sg:address":"Gro\u00dfeibstadt",
    "sg:city":"Gro\u00dfeibstadt",
    "sg:phone":"+49 9761/340",
    "sg:postcode":"97633",
    "sg:province":"Bayern",
    "wof:name":"Raiffeisenbank Gro\u00df-bardorf-klein-, Eibstadt Eg",
    "wof:placetype":"venue"
},
  "geometry": {"coordinates":[10.413753,50.301052],"type":"Point"}
}