{
  "type": "Feature",
  "properties": {
    "iso:country":"DE",
    "sg:address":"Karl-Liebknecht-Str. 66",
    "sg:city":"Jerichow",
    "sg:phone":"+49 39343/255",
    "sg:postcode":"39319",
    "sg:province":"Sachsen-Anhalt",
    "wof:name":"Merl\u00e4nders Eiscafe Inh. Rosemarie Und Sabine Merr",
    "wof:placetype":"venue"
},
  "geometry": {"coordinates":[12.025592,52.49744],"type":"Point"}
}