{
  "type": "Feature",
  "properties": {
    "iso:country":"DE",
    "sg:address":"Braker Mitte 52",
    "sg:city":"Lemgo",
    "sg:phone":"+49 5261/89713",
    "sg:postcode":"32657",
    "sg:province":"Nordrhein-Westfalen",
    "wof:name":"Braker Betten- Und Matratzenstudio",
    "wof:placetype":"venue"
},
  "geometry": {"coordinates":[8.9165439606,52.0180664062],"type":"Point"}
}