{
  "type": "Feature",
  "properties": {
    "iso:country":"DE",
    "sg:address":"Paul-S\u00e4ttele-Weg 2",
    "sg:city":"Efringen-Kirchen",
    "sg:phone":"+49 7628/357",
    "sg:postcode":"79588",
    "sg:province":"Baden-W\u00fcrttemberg",
    "wof:name":"Kath. Pfarramt St. Michael",
    "wof:placetype":"venue"
},
  "geometry": {"coordinates":[7.5389971733,47.6613235474],"type":"Point"}
}