{
  "type": "Feature",
  "properties": {
    "iso:country":"DE",
    "sg:address":"Badenweilerstr. 2",
    "sg:city":"Freiburg",
    "sg:phone":"+49 761/484440",
    "sg:postcode":"79115",
    "sg:province":"Baden-W\u00fcrttemberg",
    "wof:name":"Uwe Wehrle",
    "wof:placetype":"venue"
},
  "geometry": {"coordinates":[7.817486763,47.9978370667],"type":"Point"}
}