{
  "type": "Feature",
  "properties": {
    "iso:country":"DE",
    "sg:address":"Pfarrstr. 2",
    "sg:city":"Scheibenberg",
    "sg:phone":"+49 37349/76895",
    "sg:postcode":"09481",
    "sg:province":"Sachsen",
    "wof:name":"Baugesch\u00e4ft Meyer Gmbh",
    "wof:placetype":"venue"
},
  "geometry": {"coordinates":[12.9145898819,50.5407295227],"type":"Point"}
}