{
  "type": "Feature",
  "properties": {
    "iso:country":"DE",
    "sg:address":"Sonnenstr. 3",
    "sg:city":"Juist",
    "sg:phone":"+49 4935/914818",
    "sg:postcode":"26571",
    "sg:province":"Niedersachsen",
    "wof:name":"Herzlich Willkommen Auf Der Nordsee Insel Juist",
    "wof:placetype":"venue"
},
  "geometry": {"coordinates":[6.9897270203,53.677116394],"type":"Point"}
}