{
  "type": "Feature",
  "properties": {
    "iso:country":"DE",
    "sg:address":"Bothmerstr. 25",
    "sg:city":"Hannover",
    "sg:phone":"+49 511/834963",
    "sg:postcode":"30519",
    "sg:province":"Niedersachsen",
    "wof:name":"Gilde-br\u00e4u-st\u00fcbchen",
    "wof:placetype":"venue"
},
  "geometry": {"coordinates":[9.7695388794,52.3317527771],"type":"Point"}
}