{
  "type": "Feature",
  "properties": {
    "iso:country":"DE",
    "sg:address":"Wessendorfer Str. 8",
    "sg:city":"Vreden",
    "sg:phone":"+49 2564/3080",
    "sg:postcode":"48691",
    "sg:province":"Nordrhein-Westfalen",
    "wof:name":"Sparkasse",
    "wof:placetype":"venue"
},
  "geometry": {"coordinates":[6.824175,52.036545],"type":"Point"}
}