{
  "type": "Feature",
  "properties": {
    "iso:country":"DE",
    "sg:address":"Mainbernheimer Str. 37",
    "sg:city":"Kitzingen",
    "sg:phone":"+49 9321/37186",
    "sg:postcode":"97318",
    "sg:province":"Bayern",
    "wof:name":"Adana Kebajo",
    "wof:placetype":"venue"
},
  "geometry": {"coordinates":[10.1691551208,49.7401008606],"type":"Point"}
}