{
  "type": "Feature",
  "properties": {
    "iso:country":"DE",
    "sg:address":"Schulstr. 2",
    "sg:city":"Buchholz",
    "sg:phone":"+49 4181/34341",
    "sg:postcode":"21244",
    "sg:province":"Niedersachsen",
    "wof:name":"G\u00fcnther St\u00f6ver",
    "wof:placetype":"venue"
},
  "geometry": {"coordinates":[9.87083,53.367016],"type":"Point"}
}