{
  "type": "Feature",
  "properties": {
    "iso:country":"DE",
    "sg:address":"Hauptstr. 143",
    "sg:city":"Dorfchemnitz",
    "sg:phone":"+49 37320/8620",
    "sg:postcode":"09619",
    "sg:province":"Sachsen",
    "wof:name":"Beka-m\u00f6bel Gmbh",
    "wof:placetype":"venue"
},
  "geometry": {"coordinates":[13.4465122223,50.7547531128],"type":"Point"}
}