{
  "type": "Feature",
  "properties": {
    "iso:country":"DE",
    "sg:address":"Wilhelm-Busch-Str. 20",
    "sg:city":"Hemsbach",
    "sg:postcode":"69502",
    "sg:province":"Baden-W\u00fcrttemberg",
    "wof:name":"Von Elm Logistik Und Marketing Gmbh",
    "wof:placetype":"venue"
},
  "geometry": {"coordinates":[8.657257,49.586903],"type":"Point"}
}