{
  "type": "Feature",
  "properties": {
    "iso:country":"DE",
    "sg:address":"Eduard-M\u00f6rike-Weg 4",
    "sg:city":"Eppelheim",
    "sg:postcode":"69214",
    "sg:province":"Baden-W\u00fcrttemberg",
    "wof:name":"H + S Mitzkewitsch Gmbh",
    "wof:placetype":"venue"
},
  "geometry": {"coordinates":[8.6272706985,49.3946762085],"type":"Point"}
}