{
  "type": "Feature",
  "properties": {
    "iso:country":"DE",
    "sg:address":"Hei\u00dfener Str. 22",
    "sg:city":"M\u00fclheim",
    "sg:phone":"+49 208/476622",
    "sg:postcode":"45468",
    "sg:province":"Nordrhein-Westfalen",
    "wof:name":"Apotheke Am Ring",
    "wof:placetype":"venue"
},
  "geometry": {"coordinates":[6.888404,51.433334],"type":"Point"}
}