{
  "type": "Feature",
  "properties": {
    "iso:country":"DE",
    "sg:address":"Schillerstr. 22",
    "sg:city":"Titz",
    "sg:phone":"+49 2463/1021",
    "sg:postcode":"52445",
    "sg:province":"Nordrhein-Westfalen",
    "wof:name":"Bmvv-baumaschinen Vermiet- Und Vertriebs Gmbh",
    "wof:placetype":"venue"
},
  "geometry": {"coordinates":[6.424656868,50.9995498657],"type":"Point"}
}