{
  "type": "Feature",
  "properties": {
    "iso:country":"DE",
    "sg:address":"Dreekamp 23",
    "sg:city":"Aurich",
    "sg:postcode":"26605",
    "sg:province":"Niedersachsen",
    "wof:name":"Eurospar",
    "wof:placetype":"venue"
},
  "geometry": {"coordinates":[7.4601302147,53.4684791565],"type":"Point"}
}