{
  "type": "Feature",
  "properties": {
    "iso:country":"DE",
    "sg:address":"Am Magnusplatz 23",
    "sg:city":"Everswinkel",
    "sg:phone":"+49 2582/257",
    "sg:postcode":"48351",
    "sg:province":"Nordrhein-Westfalen",
    "wof:name":"B\u00e4ckerei-konditorei-lebens- Mittel Wiesk\u00f6tter",
    "wof:placetype":"venue"
},
  "geometry": {"coordinates":[7.846228,51.92675],"type":"Point"}
}