{
  "type": "Feature",
  "properties": {
    "iso:country":"DE",
    "sg:address":"Wuhlestr.31",
    "sg:city":"Berlin",
    "sg:phone":"+49 30/56498224",
    "sg:postcode":"12683",
    "sg:province":"Berlin",
    "wof:name":"Pecon Consult Rainer H\u00fctel",
    "wof:placetype":"venue"
},
  "geometry": {"coordinates":[13.568656,52.527878],"type":"Point"}
}