{
  "type": "Feature",
  "properties": {
    "iso:country":"DE",
    "sg:address":"Balthasar-Neumann-Str. 9a",
    "sg:city":"Bruchsal",
    "sg:phone":"+49 7251/300243",
    "sg:postcode":"76646",
    "sg:province":"Baden-W\u00fcrttemberg",
    "wof:name":"G. Braun",
    "wof:placetype":"venue"
},
  "geometry": {"coordinates":[8.595658,49.131912],"type":"Point"}
}