{
  "type": "Feature",
  "properties": {
    "iso:country":"DE",
    "sg:address":"Am Eisenberg 7",
    "sg:city":"M\u00fccke",
    "sg:phone":"+49 6400/5363",
    "sg:postcode":"35325",
    "sg:province":"Hessen",
    "wof:name":"H\u00f6lzer Gmbh & Co. Kg",
    "wof:placetype":"venue"
},
  "geometry": {"coordinates":[9.0253753662,50.6105270386],"type":"Point"}
}