{
  "type": "Feature",
  "properties": {
    "iso:country":"DE",
    "sg:address":"Warwischer Hinterdeich 122",
    "sg:city":"Hamburg",
    "sg:postcode":"21037",
    "sg:province":"Hamburg",
    "wof:name":"Afr Multimedia Gmbh",
    "wof:placetype":"venue"
},
  "geometry": {"coordinates":[10.117263,53.429722],"type":"Point"}
}