{
  "type": "Feature",
  "properties": {
    "iso:country":"DE",
    "sg:address":"Hauptstr. 4",
    "sg:city":"Betzenstein",
    "sg:phone":"+49 9244/636",
    "sg:postcode":"91282",
    "sg:province":"Bayern",
    "wof:name":"Franz Remberger Elektrogesch\u00e4ft",
    "wof:placetype":"venue"
},
  "geometry": {"coordinates":[11.420061,49.684448],"type":"Point"}
}