{
  "type": "Feature",
  "properties": {
    "iso:country":"DE",
    "sg:address":"Hauptstr. 21",
    "sg:city":"Forbach",
    "sg:phone":"+49 7228/2188",
    "sg:postcode":"76596",
    "sg:province":"Baden-W\u00fcrttemberg",
    "wof:name":"Andreas Weiler",
    "wof:placetype":"venue"
},
  "geometry": {"coordinates":[8.359353,48.677734],"type":"Point"}
}