{
  "type": "Feature",
  "properties": {
    "iso:country":"DE",
    "sg:address":"Pirolweg 5",
    "sg:city":"Aachen",
    "sg:phone":"+49 2408/58820",
    "sg:postcode":"52076",
    "sg:province":"Nordrhein-Westfalen",
    "wof:name":"Beauty-concept Beratungsgesellschaft Mbh",
    "wof:placetype":"venue"
},
  "geometry": {"coordinates":[6.1691632271,50.7030448914],"type":"Point"}
}