{
  "type": "Feature",
  "properties": {
    "iso:country":"DE",
    "sg:address":"Winkelstra\u00dfe 7",
    "sg:city":"Harsum",
    "sg:phone":"+49 5127",
    "sg:postcode":"31177",
    "sg:province":"Niedersachsen",
    "wof:name":"Caravan Welp",
    "wof:placetype":"venue"
},
  "geometry": {"coordinates":[9.9667663574,52.1955833435],"type":"Point"}
}