{
  "type": "Feature",
  "properties": {
    "iso:country":"DE",
    "sg:address":"Schanzenstra\u00dfe 10",
    "sg:city":"Dinslaken",
    "sg:postcode":"46535",
    "sg:province":"Nordrhein-Westfalen",
    "wof:name":"Gerwi-online: Die Dienstleistungsprofis!",
    "wof:placetype":"venue"
},
  "geometry": {"coordinates":[6.716742,51.566944],"type":"Point"}
}