{
  "type": "Feature",
  "properties": {
    "iso:country":"DE",
    "sg:address":"M\u00fchlenstr. 11",
    "sg:city":"Gundelfingen",
    "sg:phone":"+49 761/580590",
    "sg:postcode":"79194",
    "sg:province":"Baden-W\u00fcrttemberg",
    "wof:name":"G\u00fcnther Jurzinski",
    "wof:placetype":"venue"
},
  "geometry": {"coordinates":[7.8617229462,48.045249939],"type":"Point"}
}