{
  "type": "Feature",
  "properties": {
    "iso:country":"DE",
    "sg:address":"Germaniastr. 231",
    "sg:city":"Essen",
    "sg:phone":"+49 2054/83811",
    "sg:postcode":"45355",
    "sg:province":"Nordrhein-Westfalen",
    "wof:name":"Peter Attin Rechtsanwalt",
    "wof:placetype":"venue"
},
  "geometry": {"coordinates":[6.955824852,51.4740753174],"type":"Point"}
}