{
  "type": "Feature",
  "properties": {
    "iso:country":"DE",
    "sg:address":"Teichplan 16",
    "sg:city":"Altenburg",
    "sg:postcode":"04600",
    "sg:province":"Th\u00fcringen",
    "wof:name":"Capitol",
    "wof:placetype":"venue"
},
  "geometry": {"coordinates":[12.436056,50.982105],"type":"Point"}
}