{
  "type": "Feature",
  "properties": {
    "iso:country":"DE",
    "sg:address":"Reeperbahn 64",
    "sg:city":"Eckernf\u00f6rde",
    "sg:phone":"+49 4351/6115",
    "sg:postcode":"24340",
    "sg:province":"Schleswig-Holstein",
    "wof:name":"Restaurant Kim",
    "wof:placetype":"venue"
},
  "geometry": {"coordinates":[9.837729454,54.4646568298],"type":"Point"}
}