{
  "type": "Feature",
  "properties": {
    "iso:country":"DE",
    "sg:address":"Schulstr. 20",
    "sg:city":"Wiesbaum",
    "sg:phone":"+49 6593/8277",
    "sg:postcode":"54578",
    "sg:province":"Rheinland-Pfalz",
    "wof:name":"Josef Meyer",
    "wof:placetype":"venue"
},
  "geometry": {"coordinates":[6.676241,50.357876],"type":"Point"}
}