{
  "type": "Feature",
  "properties": {
    "iso:country":"DE",
    "sg:address":"Pulverberg 8",
    "sg:city":"Bremen",
    "sg:phone":"+49 421/649040",
    "sg:postcode":"28239",
    "sg:province":"Bremen",
    "wof:name":"Wayss & Freytag Ingenieurbau Ag",
    "wof:placetype":"venue"
},
  "geometry": {"coordinates":[8.72559,53.134575],"type":"Point"}
}