{
  "type": "Feature",
  "properties": {
    "iso:country":"DE",
    "sg:address":"Schnackenburgallee 177",
    "sg:city":"Hamburg",
    "sg:phone":"+49 40/5407431",
    "sg:postcode":"22525",
    "sg:province":"Hamburg",
    "wof:name":"Hildebrandt & Co.",
    "wof:placetype":"venue"
},
  "geometry": {"coordinates":[9.9038562775,53.5926055908],"type":"Point"}
}