{
  "type": "Feature",
  "properties": {
    "iso:country":"DE",
    "sg:address":"Schinkestr. 22",
    "sg:city":"Berlin",
    "sg:phone":"+49 30/6942443",
    "sg:postcode":"12047",
    "sg:province":"Berlin",
    "wof:name":"Enver Tazeg\u00fcl",
    "wof:placetype":"venue"
},
  "geometry": {"coordinates":[13.422416687,52.4943161011],"type":"Point"}
}