{
  "type": "Feature",
  "properties": {
    "iso:country":"DE",
    "sg:address":"Im Bremmen 28",
    "sg:city":"Hamm",
    "sg:phone":"+49 2381/405760",
    "sg:postcode":"59077",
    "sg:province":"Nordrhein-Westfalen",
    "wof:name":"Stefan Evers",
    "wof:placetype":"venue"
},
  "geometry": {"coordinates":[7.736188,51.62804],"type":"Point"}
}