{
  "type": "Feature",
  "properties": {
    "iso:country":"DE",
    "sg:address":"Brunnenstr. 17",
    "sg:city":"Riesb\u00fcrg",
    "sg:phone":"+49 9081/3754",
    "sg:postcode":"73469",
    "sg:province":"Baden-W\u00fcrttemberg",
    "wof:name":"Alban Herrling",
    "wof:placetype":"venue"
},
  "geometry": {"coordinates":[10.4396247864,48.8281593323],"type":"Point"}
}