{
  "type": "Feature",
  "properties": {
    "iso:country":"DE",
    "sg:address":"Jakobistr. 2",
    "sg:city":"Hannover",
    "sg:phone":"+49 511/628128",
    "sg:postcode":"30163",
    "sg:province":"Niedersachsen",
    "wof:name":"Rumpelkammer",
    "wof:placetype":"venue"
},
  "geometry": {"coordinates":[9.7499914169,52.3887786865],"type":"Point"}
}