{
  "type": "Feature",
  "properties": {
    "iso:country":"DE",
    "sg:address":"Quarzbichl",
    "sg:city":"Eurasburg",
    "sg:phone":"+49 8179/9330",
    "sg:postcode":"82547",
    "sg:province":"Bayern",
    "wof:name":"Wgv-recycling-wertstoff- Gewinnungs- Und",
    "wof:placetype":"venue"
},
  "geometry": {"coordinates":[11.4030179977,47.8005065918],"type":"Point"}
}