{
  "type": "Feature",
  "properties": {
    "iso:country":"DE",
    "sg:address":"Hackweg 10",
    "sg:city":"Kalletal",
    "sg:phone":"+49 5755/699",
    "sg:postcode":"32689",
    "sg:province":"Nordrhein-Westfalen",
    "wof:name":"M\u00fchlenbau Zwingelberg Gmbh",
    "wof:placetype":"venue"
},
  "geometry": {"coordinates":[8.995064,52.170883],"type":"Point"}
}