{
  "type": "Feature",
  "properties": {
    "iso:country":"DE",
    "sg:address":"Oberschleems 8",
    "sg:city":"Hamburg",
    "sg:postcode":"22117",
    "sg:province":"Hamburg",
    "wof:name":"Schwartzmann Import - Export Gmbh",
    "wof:placetype":"venue"
},
  "geometry": {"coordinates":[10.1190471649,53.5378837585],"type":"Point"}
}