{
  "type": "Feature",
  "properties": {
    "iso:country":"DE",
    "sg:address":"Georgshof",
    "sg:city":"Neukirchen",
    "sg:postcode":"23779",
    "sg:province":"Schleswig-Holstein",
    "wof:name":"Windkraft Neukirchen Gmbh & Co. Kg",
    "wof:placetype":"venue"
},
  "geometry": {"coordinates":[11.003254,54.32309],"type":"Point"}
}