{
  "type": "Feature",
  "properties": {
    "iso:country":"DE",
    "sg:address":"Gartenwinkel 44",
    "sg:city":"Leipzig",
    "sg:postcode":"04158",
    "sg:province":"Sachsen",
    "wof:name":"Schuthie Eisen-u.schrottspezi Altransport U.rohstoffhand.mbh",
    "wof:placetype":"venue"
},
  "geometry": {"coordinates":[12.337343,51.392876],"type":"Point"}
}