{
  "type": "Feature",
  "properties": {
    "iso:country":"DE",
    "sg:address":"S\u00fcdrg. 11",
    "sg:city":"Angerm\u00fcnde",
    "sg:phone":"+49 4933/3126750",
    "sg:postcode":"16278",
    "sg:province":"Brandenburg",
    "wof:name":"Preussen Email Gmbh",
    "wof:placetype":"venue"
},
  "geometry": {"coordinates":[14.00091,52.999973],"type":"Point"}
}