{
  "type": "Feature",
  "properties": {
    "iso:country":"DE",
    "sg:address":"Hans-Ackermann-Str. 5",
    "sg:city":"Gr\u00e4fenberg",
    "sg:phone":"+49 9192/509",
    "sg:postcode":"91322",
    "sg:province":"Bayern",
    "wof:name":"Karl-otto Zeier Notar",
    "wof:placetype":"venue"
},
  "geometry": {"coordinates":[11.2398338318,49.6429138184],"type":"Point"}
}