{
  "type": "Feature",
  "properties": {
    "iso:country":"DE",
    "sg:address":"Thomas-Mann-Str. 6",
    "sg:city":"Frankfurt",
    "sg:phone":"+49 69/570214",
    "sg:postcode":"60439",
    "sg:province":"Hessen",
    "wof:name":"Nordwest-apotheke",
    "wof:placetype":"venue"
},
  "geometry": {"coordinates":[8.61963,50.163418],"type":"Point"}
}