{
  "type": "Feature",
  "properties": {
    "iso:country":"DE",
    "sg:address":"Hannes-Meyer-Platz 27",
    "sg:city":"Rostock",
    "sg:phone":"+49 381/609350",
    "sg:postcode":"18146",
    "sg:province":"Mecklenburg-Vorpommern",
    "wof:name":"Goliath Show & Promotion Gmbh",
    "wof:placetype":"venue"
},
  "geometry": {"coordinates":[12.157059,54.098282],"type":"Point"}
}