{
  "type": "Feature",
  "properties": {
    "iso:country":"DE",
    "sg:address":"Raiffeisenstr. 18",
    "sg:city":"Theilenhofen",
    "sg:phone":"+49 9834/375",
    "sg:postcode":"91741",
    "sg:province":"Bayern",
    "wof:name":"Erich Heckel Lebensmittel",
    "wof:placetype":"venue"
},
  "geometry": {"coordinates":[10.8556928635,49.0826187134],"type":"Point"}
}