{
  "type": "Feature",
  "properties": {
    "iso:country":"DE",
    "sg:address":"Hermann-Heyen-Str. 12",
    "sg:city":"Papenburg",
    "sg:phone":"+49 4961/997756",
    "sg:postcode":"26871",
    "sg:province":"Niedersachsen",
    "wof:name":"Siegfried Schmitz",
    "wof:placetype":"venue"
},
  "geometry": {"coordinates":[7.40163517,53.078540802],"type":"Point"}
}