{
  "type": "Feature",
  "properties": {
    "iso:country":"DE",
    "sg:address":"Sprendlinger Landstr. 178",
    "sg:city":"Offenbach",
    "sg:phone":"+49 69/8307320",
    "sg:postcode":"63069",
    "sg:province":"Hessen",
    "wof:name":"Ips Industrieanlagenplanung Schwarzfurtner & Co.",
    "wof:placetype":"venue"
},
  "geometry": {"coordinates":[8.7458372116,50.0844688416],"type":"Point"}
}