{
  "type": "Feature",
  "properties": {
    "iso:country":"DE",
    "sg:city":"Stelle-Wittenwurth",
    "sg:phone":"+49 4837/715",
    "sg:postcode":"25795",
    "sg:province":"Schleswig-Holstein",
    "wof:name":"Hans Clau\u00dfen",
    "wof:placetype":"venue"
},
  "geometry": {"coordinates":[9.047063,54.271317],"type":"Point"}
}