{
  "type": "Feature",
  "properties": {
    "iso:country":"DE",
    "sg:address":"Ahornweg 4",
    "sg:city":"Fuchstal",
    "sg:phone":"+49 8243/783",
    "sg:postcode":"86925",
    "sg:province":"Bayern",
    "wof:name":"Dr. Herbert Ackermann Tierarzt",
    "wof:placetype":"venue"
},
  "geometry": {"coordinates":[10.8296546936,47.9317855835],"type":"Point"}
}