{
  "type": "Feature",
  "properties": {
    "iso:country":"DE",
    "sg:address":"Am H\u00fchnerort 44",
    "sg:city":"Moers",
    "sg:phone":"+49 2841/507811",
    "sg:postcode":"47441",
    "sg:province":"Nordrhein-Westfalen",
    "wof:name":"Th. Heemskerk Tiefbauunternehmen Gmbh",
    "wof:placetype":"venue"
},
  "geometry": {"coordinates":[6.66848,51.438004],"type":"Point"}
}