{
  "type": "Feature",
  "properties": {
    "iso:country":"DE",
    "sg:address":"Wambeler Str. 3",
    "sg:city":"Dortmund",
    "sg:phone":"+49 4923/1811131",
    "sg:postcode":"44145",
    "sg:province":"Nordrhein-Westfalen",
    "wof:name":"Druckerei R\u00d6hr Ohg",
    "wof:placetype":"venue"
},
  "geometry": {"coordinates":[7.4826798439,51.5237121582],"type":"Point"}
}