{
  "type": "Feature",
  "properties": {
    "iso:country":"DE",
    "sg:address":"Rolandsweg 10",
    "sg:city":"Stuvenborn",
    "sg:phone":"+49 4194/1801",
    "sg:postcode":"24641",
    "sg:province":"Schleswig-Holstein",
    "wof:name":"Erhard Und Thomas Puls Bauunternehmung Gmbh",
    "wof:placetype":"venue"
},
  "geometry": {"coordinates":[10.12323,53.853271],"type":"Point"}
}