{
  "type": "Feature",
  "properties": {
    "iso:country":"DE",
    "sg:address":"R\u00f6merstr. 2",
    "sg:city":"M\u00fcnzenberg",
    "sg:phone":"+49 6004/92008",
    "sg:postcode":"35516",
    "sg:province":"Hessen",
    "wof:name":"Gottfried Jenisch",
    "wof:placetype":"venue"
},
  "geometry": {"coordinates":[8.7891778946,50.4658050537],"type":"Point"}
}