{
  "type": "Feature",
  "properties": {
    "iso:country":"DE",
    "sg:address":"Max-Adrion-Str. 12",
    "sg:city":"Neubrandenburg",
    "sg:postcode":"17034",
    "sg:province":"Mecklenburg-Vorpommern",
    "wof:name":"Fr\u00e4drich & Diekow Handels- Gmbh",
    "wof:placetype":"venue"
},
  "geometry": {"coordinates":[13.277849,53.574963],"type":"Point"}
}