{
  "type": "Feature",
  "properties": {
    "iso:country":"DE",
    "sg:address":"Mehlbydiek 6",
    "sg:city":"Kappeln",
    "sg:phone":"+49 4642/4342",
    "sg:postcode":"24376",
    "sg:province":"Schleswig-Holstein",
    "wof:name":"Tennis-treff",
    "wof:placetype":"venue"
},
  "geometry": {"coordinates":[9.9236392975,54.6680259705],"type":"Point"}
}