{
  "type": "Feature",
  "properties": {
    "iso:country":"DE",
    "sg:address":"Berliner Platz 3 c",
    "sg:city":"Bad Bramstedt",
    "sg:phone":"+49 4192/2366",
    "sg:postcode":"24576",
    "sg:province":"Schleswig-Holstein",
    "wof:name":"Gloves",
    "wof:placetype":"venue"
},
  "geometry": {"coordinates":[9.889156,53.92654],"type":"Point"}
}