{
  "type": "Feature",
  "properties": {
    "iso:country":"DE",
    "sg:address":"M\u00f6schwitzer Str. 29",
    "sg:city":"Plauen",
    "sg:phone":"+49 3741/471659",
    "sg:postcode":"08529",
    "sg:province":"Sachsen",
    "wof:name":"Broilerbar Tho\u00df",
    "wof:placetype":"venue"
},
  "geometry": {"coordinates":[12.1571207047,50.509147644],"type":"Point"}
}