{
  "type": "Feature",
  "properties": {
    "iso:country":"DE",
    "sg:address":"Engelblecker Str. 33",
    "sg:city":"M\u00f6nchengladbach",
    "sg:phone":"+49 2161/20140",
    "sg:postcode":"41066",
    "sg:province":"Nordrhein-Westfalen",
    "wof:name":"Krieger Beteiligungsges. Mbh",
    "wof:placetype":"venue"
},
  "geometry": {"coordinates":[6.462879,51.211823],"type":"Point"}
}