{
  "type": "Feature",
  "properties": {
    "iso:country":"DE",
    "sg:address":"Rothenberge 42",
    "sg:city":"Wettringen",
    "sg:phone":"+49 2557/318",
    "sg:postcode":"48493",
    "sg:province":"Nordrhein-Westfalen",
    "wof:name":"Hermann Wiecher",
    "wof:placetype":"venue"
},
  "geometry": {"coordinates":[7.278459,52.229191],"type":"Point"}
}