{
  "type": "Feature",
  "properties": {
    "iso:country":"DE",
    "sg:address":"Biberacher Str. 19",
    "sg:city":"Eberhardzell",
    "sg:phone":"+49 4973/589600",
    "sg:postcode":"88436",
    "sg:province":"Baden-W\u00fcrttemberg",
    "wof:name":"Holzbau Gr\u00d6ber Gmbh",
    "wof:placetype":"venue"
},
  "geometry": {"coordinates":[9.8892507553,48.0011863708],"type":"Point"}
}