{
  "type": "Feature",
  "properties": {
    "iso:country":"DE",
    "sg:address":"Liviastr. 6",
    "sg:city":"Leiwen",
    "sg:phone":"+49 6507/3557",
    "sg:postcode":"54340",
    "sg:province":"Rheinland-Pfalz",
    "wof:name":"Rainer Marunde Heilpraktiker",
    "wof:placetype":"venue"
},
  "geometry": {"coordinates":[6.882311821,49.8174171448],"type":"Point"}
}