{
  "type": "Feature",
  "properties": {
    "iso:country":"DE",
    "sg:address":"Trollingerstr. 30",
    "sg:city":"Zaberfeld",
    "sg:phone":"+49 7046/7555",
    "sg:postcode":"74374",
    "sg:province":"Baden-W\u00fcrttemberg",
    "wof:name":"Uwe Freitag Massagepraxis",
    "wof:placetype":"venue"
},
  "geometry": {"coordinates":[8.93192,49.061226],"type":"Point"}
}