{
  "type": "Feature",
  "properties": {
    "iso:country":"DE",
    "sg:address":"Brunnenallee 42a",
    "sg:city":"Bad Wildungen",
    "sg:phone":"+49 5621/798300",
    "sg:postcode":"34537",
    "sg:province":"Hessen",
    "wof:name":"Hotel Isabel",
    "wof:placetype":"venue"
},
  "geometry": {"coordinates":[9.1126203537,51.1154289246],"type":"Point"}
}