{
  "type": "Feature",
  "properties": {
    "iso:country":"DE",
    "sg:address":"Forststr. 18",
    "sg:city":"Bad Endorf",
    "sg:phone":"+49 8051/999930",
    "sg:postcode":"83093",
    "sg:province":"Bayern",
    "wof:name":"Ehrko Seniorenheim Gmbh",
    "wof:placetype":"venue"
},
  "geometry": {"coordinates":[12.300391,47.91391],"type":"Point"}
}