{
  "type": "Feature",
  "properties": {
    "iso:country":"DE",
    "sg:address":"An der Schleifm\u00fchle 25",
    "sg:city":"Darmstadt",
    "sg:phone":"+49 6151/716116",
    "sg:postcode":"64289",
    "sg:province":"Hessen",
    "wof:name":"Hans-joachim Wuttke Ingenieur",
    "wof:placetype":"venue"
},
  "geometry": {"coordinates":[8.680811882,49.9051361084],"type":"Point"}
}