{
  "type": "Feature",
  "properties": {
    "iso:country":"DE",
    "sg:address":"Buersche Str. 67",
    "sg:city":"Osnabr\u00fcck",
    "sg:phone":"+49 541/24170",
    "sg:postcode":"49084",
    "sg:province":"Niedersachsen",
    "wof:name":"Gastst\u00e4tte Ost-quelle",
    "wof:placetype":"venue"
},
  "geometry": {"coordinates":[8.0651426315,52.2758102417],"type":"Point"}
}