{
  "type": "Feature",
  "properties": {
    "iso:country":"DE",
    "sg:address":"Augsburger Str. 43",
    "sg:city":"Langerringen",
    "sg:phone":"+49 8232/2372",
    "sg:postcode":"86853",
    "sg:province":"Bayern",
    "wof:name":"Johann Bihler",
    "wof:placetype":"venue"
},
  "geometry": {"coordinates":[10.757619,48.154816],"type":"Point"}
}