{
  "type": "Feature",
  "properties": {
    "iso:country":"DE",
    "sg:address":"Einharding",
    "sg:city":"Bruck",
    "sg:postcode":"85567",
    "sg:province":"Bayern",
    "wof:name":"L. Kirmair Elektroinstallation",
    "wof:placetype":"venue"
},
  "geometry": {"coordinates":[11.888269,48.012459],"type":"Point"}
}