{
  "type": "Feature",
  "properties": {
    "iso:country":"DE",
    "sg:address":"Alpenplatz 1",
    "sg:city":"M\u00fcnchen",
    "sg:phone":"+49 89/6514147",
    "sg:postcode":"81541",
    "sg:province":"Bayern",
    "wof:name":"Hanig",
    "wof:placetype":"venue"
},
  "geometry": {"coordinates":[11.581462,48.117958],"type":"Point"}
}