{
  "type": "Feature",
  "properties": {
    "iso:country":"DE",
    "sg:address":"Sonnenhalde 50",
    "sg:city":"Elztal",
    "sg:phone":"+49 6293/667",
    "sg:postcode":"74834",
    "sg:province":"Baden-W\u00fcrttemberg",
    "wof:name":"Petra Strau\u00df Masseur",
    "wof:placetype":"venue"
},
  "geometry": {"coordinates":[9.216841,49.403603],"type":"Point"}
}