{
  "type": "Feature",
  "properties": {
    "iso:country":"DE",
    "sg:address":"Heimsang 95",
    "sg:city":"Ratingen",
    "sg:postcode":"40883",
    "sg:province":"Nordrhein-Westfalen",
    "wof:name":"Espitte Gmbh",
    "wof:placetype":"venue"
},
  "geometry": {"coordinates":[6.9033517838,51.3229217529],"type":"Point"}
}