{
  "type": "Feature",
  "properties": {
    "iso:country":"DE",
    "sg:address":"Braugasse 4",
    "sg:city":"Oberlungwitz",
    "sg:postcode":"09353",
    "sg:province":"Sachsen",
    "wof:name":"Matrix Verwaltungs- Und Beteiligungs Gmbh",
    "wof:placetype":"venue"
},
  "geometry": {"coordinates":[12.725215,50.786503],"type":"Point"}
}