{
  "type": "Feature",
  "properties": {
    "iso:country":"DE",
    "sg:address":"F\u00f6rtschendorfer Str. 14",
    "sg:city":"Teuschnitz",
    "sg:phone":"+49 9268/231",
    "sg:postcode":"96358",
    "sg:province":"Bayern",
    "wof:name":"Katholisches Pfarramt Rosenkranzk\u00f6nigin",
    "wof:placetype":"venue"
},
  "geometry": {"coordinates":[11.3753652573,50.3791732788],"type":"Point"}
}