{
  "type": "Feature",
  "properties": {
    "iso:country":"DE",
    "sg:address":"Frankenstr. 75",
    "sg:city":"Lautertal",
    "sg:phone":"+49 9561/55440",
    "sg:postcode":"96486",
    "sg:province":"Bayern",
    "wof:name":"Fischland Lautertal Inh. Kurt Werner Humann E. K.",
    "wof:placetype":"venue"
},
  "geometry": {"coordinates":[10.9728527069,50.3197555542],"type":"Point"}
}