{
  "type": "Feature",
  "properties": {
    "iso:country":"DE",
    "sg:address":"Universit\u00e4tsstr. 52",
    "sg:city":"Marburg",
    "sg:phone":"+49 6421/25011",
    "sg:postcode":"35037",
    "sg:province":"Hessen",
    "wof:name":"Heinz Und Axel Ludwig Rechtsanw\u00e4lte Und Notare",
    "wof:placetype":"venue"
},
  "geometry": {"coordinates":[8.7613554001,50.8056526184],"type":"Point"}
}