{
  "type": "Feature",
  "properties": {
    "iso:country":"DE",
    "sg:address":"Alt-R\u00fchlertwist 18",
    "sg:city":"Twist",
    "sg:phone":"+49 5936/416",
    "sg:postcode":"49767",
    "sg:province":"Niedersachsen",
    "wof:name":"Theodor Koers",
    "wof:placetype":"venue"
},
  "geometry": {"coordinates":[7.077966,52.647892],"type":"Point"}
}