{
  "type": "Feature",
  "properties": {
    "iso:country":"DE",
    "sg:address":"In der Lust 3",
    "sg:city":"Bad Bevensen",
    "sg:phone":"+49 5821/3217",
    "sg:postcode":"29549",
    "sg:province":"Niedersachsen",
    "wof:name":"Hans-georg Wiesner Rechtsanwalt",
    "wof:placetype":"venue"
},
  "geometry": {"coordinates":[10.5977296829,53.0480155945],"type":"Point"}
}