{
  "type": "Feature",
  "properties": {
    "iso:country":"DE",
    "sg:address":"Hinter Hoben 129-149",
    "sg:city":"Bonn",
    "sg:postcode":"53129",
    "sg:province":"Nordrhein-Westfalen",
    "wof:name":"Infoland Verlags- Und Vertriebsgesellschaft Mbh",
    "wof:placetype":"venue"
},
  "geometry": {"coordinates":[7.1143097878,50.7070083618],"type":"Point"}
}