{
  "type": "Feature",
  "properties": {
    "iso:country":"DE",
    "sg:address":"Hahnhofstr. 53",
    "sg:city":"Baden-Baden",
    "sg:phone":"+49 7221/271090",
    "sg:postcode":"76530",
    "sg:province":"Baden-W\u00fcrttemberg",
    "wof:name":"Wohnbaugesellschaft Baden-baden Mbh",
    "wof:placetype":"venue"
},
  "geometry": {"coordinates":[8.251554,48.755054],"type":"Point"}
}