{
  "type": "Feature",
  "properties": {
    "iso:country":"DE",
    "sg:address":"Waldmattstr. 15",
    "sg:city":"B\u00fchl",
    "sg:postcode":"77815",
    "sg:province":"Baden-W\u00fcrttemberg",
    "wof:name":"H\u00e4ussler & Boileau Bau Gmbh",
    "wof:placetype":"venue"
},
  "geometry": {"coordinates":[8.1492862701,48.6680755615],"type":"Point"}
}