{
  "type": "Feature",
  "properties": {
    "iso:country":"DE",
    "sg:address":"Wildestr. 1",
    "sg:city":"Emlichheim",
    "sg:postcode":"49824",
    "sg:province":"Niedersachsen",
    "wof:name":"Bergslot Text- Und Bilderwerbungs Gmbh",
    "wof:placetype":"venue"
},
  "geometry": {"coordinates":[6.843907,52.605396],"type":"Point"}
}