{
  "type": "Feature",
  "properties": {
    "iso:country":"DE",
    "sg:address":"Franz-Joseph-Str. 21",
    "sg:city":"M\u00fcnchen",
    "sg:phone":"+49 89/3810050",
    "sg:postcode":"80801",
    "sg:province":"Bayern",
    "wof:name":"Natascha Muellerschoen Couture Gmbh",
    "wof:placetype":"venue"
},
  "geometry": {"coordinates":[11.580693,48.157688],"type":"Point"}
}