{
  "type": "Feature",
  "properties": {
    "iso:country":"DE",
    "sg:address":"Zugspitzstr. 21",
    "sg:city":"Gilching",
    "sg:phone":"+49 8105/24455",
    "sg:postcode":"82205",
    "sg:province":"Bayern",
    "wof:name":"Braun",
    "wof:placetype":"venue"
},
  "geometry": {"coordinates":[11.286768,48.113743],"type":"Point"}
}