{
  "type": "Feature",
  "properties": {
    "iso:country":"DE",
    "sg:address":"Lohstr. 26",
    "sg:city":"Uedem",
    "sg:phone":"+49 2825/1408",
    "sg:postcode":"47589",
    "sg:province":"Nordrhein-Westfalen",
    "wof:name":"Hotel Zum Bremerhafen",
    "wof:placetype":"venue"
},
  "geometry": {"coordinates":[6.2739009857,51.6676177979],"type":"Point"}
}