{
  "type": "Feature",
  "properties": {
    "iso:country":"DE",
    "sg:address":"Vor dem Sauerwassertor 7",
    "sg:city":"Koblenz",
    "sg:phone":"+49 261/76833",
    "sg:postcode":"56077",
    "sg:province":"Rheinland-Pfalz",
    "wof:name":"Peter Welter",
    "wof:placetype":"venue"
},
  "geometry": {"coordinates":[7.616354,50.362488],"type":"Point"}
}