{
  "type": "Feature",
  "properties": {
    "iso:country":"DE",
    "sg:address":"Br\u00fcckenauer Str. 29",
    "sg:city":"Schl\u00fcchtern",
    "sg:postcode":"36381",
    "sg:province":"Hessen",
    "wof:name":"Ideal-rent Pkw Inh. Carsten Kulbe",
    "wof:placetype":"venue"
},
  "geometry": {"coordinates":[9.53926,50.349361],"type":"Point"}
}