{
  "type": "Feature",
  "properties": {
    "iso:country":"DE",
    "sg:address":"Mainzer Str. 31",
    "sg:city":"R\u00fcsselsheim",
    "sg:phone":"+49 6142/63061",
    "sg:postcode":"65428",
    "sg:province":"Hessen",
    "wof:name":"Daniela Auteri",
    "wof:placetype":"venue"
},
  "geometry": {"coordinates":[8.408782959,49.9945487976],"type":"Point"}
}