{
  "type": "Feature",
  "properties": {
    "iso:country":"DE",
    "sg:address":"M\u00fcnchener Freiheit 16",
    "sg:city":"M\u00fcnchen",
    "sg:phone":"+49 89/341331",
    "sg:postcode":"80802",
    "sg:province":"Bayern",
    "wof:name":"Dr. Karl H. Pressler",
    "wof:placetype":"venue"
},
  "geometry": {"coordinates":[11.5874176025,48.1628417969],"type":"Point"}
}