{
  "type": "Feature",
  "properties": {
    "iso:country":"DE",
    "sg:address":"Stein\u00e4ckerstr. 20",
    "sg:city":"Ettlingen",
    "sg:phone":"+49 7243/21069",
    "sg:postcode":"76275",
    "sg:province":"Baden-W\u00fcrttemberg",
    "wof:name":"Dlf Axel Friedrich E. K.",
    "wof:placetype":"venue"
},
  "geometry": {"coordinates":[8.433719,48.910835],"type":"Point"}
}