{
  "type": "Feature",
  "properties": {
    "iso:country":"DE",
    "sg:address":"Robert-Bosch-Str. 2",
    "sg:city":"Diez",
    "sg:phone":"+49 6432/61532",
    "sg:postcode":"65582",
    "sg:province":"Rheinland-Pfalz",
    "wof:name":"Lisuma Gmbh & Co. Kg",
    "wof:placetype":"venue"
},
  "geometry": {"coordinates":[8.0467605591,50.3700828552],"type":"Point"}
}