{
  "type": "Feature",
  "properties": {
    "iso:country":"DE",
    "sg:address":"Bayerwaldstr. 1",
    "sg:city":"Ruderting",
    "sg:phone":"+49 8509/1219",
    "sg:postcode":"94161",
    "sg:province":"Bayern",
    "wof:name":"Josef H\u00f6ltl",
    "wof:placetype":"venue"
},
  "geometry": {"coordinates":[13.409685,48.653477],"type":"Point"}
}