{
  "type": "Feature",
  "properties": {
    "iso:country":"DE",
    "sg:address":"Wiesbadener Weg 2",
    "sg:city":"Bad Soden",
    "sg:phone":"+49 6196/56050",
    "sg:postcode":"65812",
    "sg:province":"Hessen",
    "wof:name":"Tricom Wohnstudio",
    "wof:placetype":"venue"
},
  "geometry": {"coordinates":[8.496832,50.1479],"type":"Point"}
}