{
  "type": "Feature",
  "properties": {
    "iso:country":"DE",
    "sg:address":"B\u00fcnder Str. 18",
    "sg:city":"L\u00f6hne",
    "sg:phone":"+49 5732/4591",
    "sg:postcode":"32584",
    "sg:province":"Nordrhein-Westfalen",
    "wof:name":"Imbi\u00df Antalya Grill",
    "wof:placetype":"venue"
},
  "geometry": {"coordinates":[8.7148132324,52.1979370117],"type":"Point"}
}