{
  "type": "Feature",
  "properties": {
    "iso:country":"DE",
    "sg:address":"Deutenbacher Str. 16-24",
    "sg:city":"Stein",
    "sg:phone":"+49 40/7004000",
    "sg:postcode":"90547",
    "sg:province":"Bayern",
    "wof:name":"M\u00d6bel Meyn Gmbh",
    "wof:placetype":"venue"
},
  "geometry": {"coordinates":[9.7861747742,53.4596824646],"type":"Point"}
}