{
  "type": "Feature",
  "properties": {
    "iso:country":"DE",
    "sg:address":"Kleine Spillingsgasse 10",
    "sg:city":"Frankfurt",
    "sg:phone":"+49 69/453608",
    "sg:postcode":"60385",
    "sg:province":"Hessen",
    "wof:name":"Restaurant-g\u00e4stehaus Schm\u00e4rrnche",
    "wof:placetype":"venue"
},
  "geometry": {"coordinates":[8.7120923996,50.1310920715],"type":"Point"}
}