{
  "type": "Feature",
  "properties": {
    "iso:country":"DE",
    "sg:address":"Spechtritzer Str. 1",
    "sg:city":"Rabenau",
    "sg:phone":"+49 351/6446786",
    "sg:postcode":"01734",
    "sg:province":"Sachsen",
    "wof:name":"Gebr. Herzog",
    "wof:placetype":"venue"
},
  "geometry": {"coordinates":[13.658601,50.953705],"type":"Point"}
}