{
  "type": "Feature",
  "properties": {
    "iso:country":"DE",
    "sg:address":"Harderhook 15 PF 1214",
    "sg:city":"Bocholt",
    "sg:phone":"+49 4928/7125050",
    "sg:postcode":"46395",
    "sg:province":"Nordrhein-Westfalen",
    "wof:name":"Sinnack Backspezialit\u00c4ten Gmbh & Co. Kg",
    "wof:placetype":"venue"
},
  "geometry": {"coordinates":[6.617612,51.834663],"type":"Point"}
}