{
  "type": "Feature",
  "properties": {
    "iso:country":"DE",
    "sg:address":"Hedwigstr.9",
    "sg:city":"M\u00fcnchen",
    "sg:phone":"+49 89/18979787",
    "sg:postcode":"80636",
    "sg:province":"Bayern",
    "wof:name":"Gatesbox.com - Unofficial Microsoft Xbox Videogame",
    "wof:placetype":"venue"
},
  "geometry": {"coordinates":[11.539974,48.15263],"type":"Point"}
}