{
  "type": "Feature",
  "properties": {
    "iso:country":"DE",
    "sg:address":"Borngasse 5a",
    "sg:city":"Obernhof",
    "sg:phone":"+49 2604/7563",
    "sg:postcode":"56379",
    "sg:province":"Rheinland-Pfalz",
    "wof:name":"Norbert Massengeil-beck",
    "wof:placetype":"venue"
},
  "geometry": {"coordinates":[7.8524880409,50.3178100586],"type":"Point"}
}