{
  "type": "Feature",
  "properties": {
    "iso:country":"DE",
    "sg:address":"Hauptstr. 56",
    "sg:city":"Pressig",
    "sg:phone":"+49 9265/8522",
    "sg:postcode":"96332",
    "sg:province":"Bayern",
    "wof:name":"Volksbank Ludwigsstadt-kronach Eg",
    "wof:placetype":"venue"
},
  "geometry": {"coordinates":[11.313376,50.349129],"type":"Point"}
}