{
  "type": "Feature",
  "properties": {
    "iso:country":"DE",
    "sg:address":"Hauptstr. 13",
    "sg:city":"Hallenberg",
    "sg:phone":"+49 2984/8267",
    "sg:postcode":"59969",
    "sg:province":"Nordrhein-Westfalen",
    "wof:name":"Peter Vogt Jun.",
    "wof:placetype":"venue"
},
  "geometry": {"coordinates":[8.625745,51.147694],"type":"Point"}
}