{
  "type": "Feature",
  "properties": {
    "iso:country":"DE",
    "sg:address":"Alexanderstr. 158",
    "sg:city":"Stuttgart",
    "sg:phone":"+49 711/6012319",
    "sg:postcode":"70180",
    "sg:province":"Baden-W\u00fcrttemberg",
    "wof:name":"Bewas Consulting Gmbh & Co. Kg",
    "wof:placetype":"venue"
},
  "geometry": {"coordinates":[9.1781902313,48.7655906677],"type":"Point"}
}