{
  "type": "Feature",
  "properties": {
    "iso:country":"DE",
    "sg:address":"Julius-Lichtenstein-Str 15",
    "sg:city":"Babenhausen",
    "sg:phone":"+49 6073/8314",
    "sg:postcode":"64832",
    "sg:province":"Hessen",
    "wof:name":"Greiner Vollelektronische Quarzuhren Gmbh",
    "wof:placetype":"venue"
},
  "geometry": {"coordinates":[8.9542150497,49.9622459412],"type":"Point"}
}