{
  "type": "Feature",
  "properties": {
    "iso:country":"DE",
    "sg:address":"Im Stadtfelde 3",
    "sg:city":"Wunstorf",
    "sg:phone":"+49 5031/76698",
    "sg:postcode":"31515",
    "sg:province":"Niedersachsen",
    "wof:name":"Extra",
    "wof:placetype":"venue"
},
  "geometry": {"coordinates":[9.4540691376,52.4233665466],"type":"Point"}
}