{
  "type": "Feature",
  "properties": {
    "iso:country":"DE",
    "sg:address":"Rutschbahn 17",
    "sg:city":"Hamburg",
    "sg:phone":"+49 40/41352744",
    "sg:postcode":"20146",
    "sg:province":"Hamburg",
    "wof:name":"Cafe Solo Gmbh",
    "wof:placetype":"venue"
},
  "geometry": {"coordinates":[9.981379,53.571186],"type":"Point"}
}