{
  "type": "Feature",
  "properties": {
    "iso:country":"DE",
    "sg:address":"Torgauer Str. 18",
    "sg:city":"Berlin",
    "sg:phone":"+49 4930/7849660",
    "sg:postcode":"10829",
    "sg:province":"Berlin",
    "wof:name":"B. Flickinger Kfz-lackiererei Gmbh",
    "wof:placetype":"venue"
},
  "geometry": {"coordinates":[13.356803,52.480087],"type":"Point"}
}