{
  "type": "Feature",
  "properties": {
    "iso:country":"DE",
    "sg:address":"Wilhelm-Zangen-Str. 6",
    "sg:city":"Hausach",
    "sg:phone":"+49 7831/6857",
    "sg:postcode":"77756",
    "sg:province":"Baden-W\u00fcrttemberg",
    "wof:name":"Milieu",
    "wof:placetype":"venue"
},
  "geometry": {"coordinates":[8.186578,48.283634],"type":"Point"}
}