{
  "type": "Feature",
  "properties": {
    "iso:country":"DE",
    "sg:address":"Alte Rabenstr. 12 b",
    "sg:city":"Hamburg",
    "sg:postcode":"20148",
    "sg:province":"Hamburg",
    "wof:name":"Bellini Logistik Gmbh",
    "wof:placetype":"venue"
},
  "geometry": {"coordinates":[9.99688,53.566742],"type":"Point"}
}