{
  "type": "Feature",
  "properties": {
    "iso:country":"DE",
    "sg:address":"Friedenstr. 8",
    "sg:city":"Offenburg",
    "sg:phone":"+49 781/39898",
    "sg:postcode":"77654",
    "sg:province":"Baden-W\u00fcrttemberg",
    "wof:name":"Dr. Med. Rainer Voigt",
    "wof:placetype":"venue"
},
  "geometry": {"coordinates":[7.9485330582,48.4702301025],"type":"Point"}
}