{
  "type": "Feature",
  "properties": {
    "iso:country":"DE",
    "sg:address":"Blarerstr. 56",
    "sg:city":"Konstanz",
    "sg:phone":"+49 7531",
    "sg:postcode":"78467",
    "sg:province":"Baden-W\u00fcrttemberg",
    "wof:name":"Steuerungstechnik Bew\u00e4sserung Und Klimatisierung",
    "wof:placetype":"venue"
},
  "geometry": {"coordinates":[9.166408,47.658848],"type":"Point"}
}