{
  "type": "Feature",
  "properties": {
    "iso:country":"DE",
    "sg:address":"Dorfstr. 15",
    "sg:city":"Gro\u00dfrinderfeld",
    "sg:phone":"+49 9344/285",
    "sg:postcode":"97950",
    "sg:province":"Baden-W\u00fcrttemberg",
    "wof:name":"Herkra-hemm & Krapf Automaten Gmbh",
    "wof:placetype":"venue"
},
  "geometry": {"coordinates":[9.8011522293,49.6747131348],"type":"Point"}
}