{
  "type": "Feature",
  "properties": {
    "iso:country":"DE",
    "sg:address":"Georg-August-Zinn-Str. 29",
    "sg:city":"Gro\u00df-Umstadt",
    "sg:phone":"+49 6078/2231",
    "sg:postcode":"64823",
    "sg:province":"Hessen",
    "wof:name":"Paracelsus-apotheke",
    "wof:placetype":"venue"
},
  "geometry": {"coordinates":[8.926113,49.867809],"type":"Point"}
}