{
  "type": "Feature",
  "properties": {
    "iso:country":"DE",
    "sg:address":"Erfurter Str. 2",
    "sg:city":"Arnstadt",
    "sg:phone":"+49 3628/600606",
    "sg:postcode":"99310",
    "sg:province":"Th\u00fcringen",
    "wof:name":"Schnitzelhaus",
    "wof:placetype":"venue"
},
  "geometry": {"coordinates":[10.9470691681,50.8339233398],"type":"Point"}
}