{
  "type": "Feature",
  "properties": {
    "iso:country":"DE",
    "sg:address":"Leimbachstr. 244 A",
    "sg:city":"Siegen",
    "sg:postcode":"57074",
    "sg:province":"Nordrhein-Westfalen",
    "wof:name":"H & S Infatec Gmbh",
    "wof:placetype":"venue"
},
  "geometry": {"coordinates":[8.023157,50.852768],"type":"Point"}
}