{
  "type": "Feature",
  "properties": {
    "iso:country":"DE",
    "sg:address":"Geitau 24",
    "sg:city":"Bayrischzell",
    "sg:postcode":"83735",
    "sg:province":"Bayern",
    "wof:name":"Dr. Med. H. Graatz Arzt F. Dermatologie",
    "wof:placetype":"venue"
},
  "geometry": {"coordinates":[11.9604740143,47.6874465942],"type":"Point"}
}