{
  "type": "Feature",
  "properties": {
    "iso:country":"DE",
    "sg:address":"Kierberger Str. 94",
    "sg:city":"Br\u00fchl",
    "sg:phone":"+49 2232/27650",
    "sg:postcode":"50321",
    "sg:province":"Nordrhein-Westfalen",
    "wof:name":"Heinz Fl\u00fcgel Steuerberater",
    "wof:placetype":"venue"
},
  "geometry": {"coordinates":[6.8920350075,50.8400535583],"type":"Point"}
}