{
  "type": "Feature",
  "properties": {
    "iso:country":"DE",
    "sg:address":"Wellingholzhausener Str. 122",
    "sg:city":"Melle",
    "sg:phone":"+49 5429/921740",
    "sg:postcode":"49326",
    "sg:province":"Niedersachsen",
    "wof:name":"B\u00fccherstube Peter Echelmeyer",
    "wof:placetype":"venue"
},
  "geometry": {"coordinates":[8.265408,52.16032],"type":"Point"}
}