{
  "type": "Feature",
  "properties": {
    "iso:country":"DE",
    "sg:address":"Hoyerswerdaer Str. 46",
    "sg:city":"Kamenz",
    "sg:phone":"+49 35783/00129",
    "sg:postcode":"01917",
    "sg:province":"Sachsen",
    "wof:name":"Winfried Ritscher",
    "wof:placetype":"venue"
},
  "geometry": {"coordinates":[14.1019048691,51.2770576477],"type":"Point"}
}