{
  "type": "Feature",
  "properties": {
    "iso:country":"DE",
    "sg:address":"F\u00fcrstenfeldbrucker Str. 14",
    "sg:city":"Moorenweis",
    "sg:phone":"+49 8146/7978",
    "sg:postcode":"82272",
    "sg:province":"Bayern",
    "wof:name":"Ulrichs-apotheke",
    "wof:placetype":"venue"
},
  "geometry": {"coordinates":[11.081688,48.15469],"type":"Point"}
}