{
  "type": "Feature",
  "properties": {
    "iso:country":"DE",
    "sg:address":"Elisenh\u00f6he 53",
    "sg:city":"Bingen",
    "sg:phone":"+49 6721/32011",
    "sg:postcode":"55411",
    "sg:province":"Rheinland-Pfalz",
    "wof:name":"G\u00fcnter Hartmann Architekt",
    "wof:placetype":"venue"
},
  "geometry": {"coordinates":[7.876047,49.964939],"type":"Point"}
}