{
  "type": "Feature",
  "properties": {
    "iso:country":"DE",
    "sg:address":"Friedrichsfehner Str. 32",
    "sg:city":"Edewecht",
    "sg:phone":"+49 4486/2015",
    "sg:postcode":"26188",
    "sg:province":"Niedersachsen",
    "wof:name":"Landhaus Friedrichsfehn",
    "wof:placetype":"venue"
},
  "geometry": {"coordinates":[8.0944337845,53.1246528625],"type":"Point"}
}