{
  "type": "Feature",
  "properties": {
    "iso:country":"DE",
    "sg:address":"M\u00fchlstr. 8",
    "sg:city":"Wilhermsdorf",
    "sg:phone":"+49 9102/362",
    "sg:postcode":"91452",
    "sg:province":"Bayern",
    "wof:name":"Walter Loos",
    "wof:placetype":"venue"
},
  "geometry": {"coordinates":[10.715061,49.483376],"type":"Point"}
}