{
  "type": "Feature",
  "properties": {
    "iso:country":"DE",
    "sg:address":"Kurzer Hagen 21",
    "sg:city":"Hildesheim",
    "sg:phone":"+49 5121/34073",
    "sg:postcode":"31134",
    "sg:province":"Niedersachsen",
    "wof:name":"Franz Schafhausen Nachfolger Inhaber Peter Hahn E. K.",
    "wof:placetype":"venue"
},
  "geometry": {"coordinates":[9.9501399994,52.1532096863],"type":"Point"}
}