{
  "type": "Feature",
  "properties": {
    "iso:country":"DE",
    "sg:address":"Haus-Horl-Str. 73",
    "sg:city":"Essen",
    "sg:phone":"+49 201/665951",
    "sg:postcode":"45357",
    "sg:province":"Nordrhein-Westfalen",
    "wof:name":"St. Michael-apotheke",
    "wof:placetype":"venue"
},
  "geometry": {"coordinates":[6.948006,51.493534],"type":"Point"}
}