{
  "type": "Feature",
  "properties": {
    "iso:country":"DE",
    "sg:address":"Friedenstr. 39",
    "sg:city":"Waldbronn",
    "sg:phone":"+49 7243/61018",
    "sg:postcode":"76337",
    "sg:province":"Baden-W\u00fcrttemberg",
    "wof:name":"Club Der Monmouth- Freunde E. V.",
    "wof:placetype":"venue"
},
  "geometry": {"coordinates":[8.480307579,48.9250450134],"type":"Point"}
}