{
  "type": "Feature",
  "properties": {
    "iso:country":"DE",
    "sg:address":"Carl-Zeiss-Str. 4",
    "sg:city":"Eppelheim",
    "sg:phone":"+49 6221/67700",
    "sg:postcode":"69214",
    "sg:province":"Baden-W\u00fcrttemberg",
    "wof:name":"Orth Recycling Gmbh",
    "wof:placetype":"venue"
},
  "geometry": {"coordinates":[8.6274747849,49.4110565186],"type":"Point"}
}