{
  "type": "Feature",
  "properties": {
    "iso:country":"DE",
    "sg:address":"Schweinshaupten 79",
    "sg:city":"Bundorf",
    "sg:phone":"+49 9763/1246",
    "sg:postcode":"97494",
    "sg:province":"Bayern",
    "wof:name":"Waffen Schmitt",
    "wof:placetype":"venue"
},
  "geometry": {"coordinates":[10.5745248795,50.1864738464],"type":"Point"}
}