{
  "type": "Feature",
  "properties": {
    "iso:country":"DE",
    "sg:address":"Grimmer Landstr. 3",
    "sg:city":"Greifswald",
    "sg:phone":"+49 3834/505050",
    "sg:postcode":"17489",
    "sg:province":"Mecklenburg-Vorpommern",
    "wof:name":"Martin Schmidt",
    "wof:placetype":"venue"
},
  "geometry": {"coordinates":[13.3548927307,54.0918922424],"type":"Point"}
}