{
  "type": "Feature",
  "properties": {
    "iso:country":"DE",
    "sg:address":"Elektronstr 60",
    "sg:city":"Frankfurt",
    "sg:phone":"+49 69/394939",
    "sg:postcode":"65933",
    "sg:province":"Hessen",
    "wof:name":"Duffner Gmbh",
    "wof:placetype":"venue"
},
  "geometry": {"coordinates":[8.59879,50.095833],"type":"Point"}
}