{
  "type": "Feature",
  "properties": {
    "iso:country":"DE",
    "sg:address":"Inselstr. 4",
    "sg:city":"Stade",
    "sg:phone":"+49 4141/46565",
    "sg:postcode":"21682",
    "sg:province":"Niedersachsen",
    "wof:name":"Petra Selle-tiedemann",
    "wof:placetype":"venue"
},
  "geometry": {"coordinates":[9.473629,53.599915],"type":"Point"}
}