{
  "type": "Feature",
  "properties": {
    "iso:country":"DE",
    "sg:address":"Werkstattstr 10",
    "sg:city":"Wolfen",
    "sg:phone":"+49 3494/636900",
    "sg:postcode":"06766",
    "sg:province":"Sachsen-Anhalt",
    "wof:name":"Synthon Chemicals Gmbh & Co Kg",
    "wof:placetype":"venue"
},
  "geometry": {"coordinates":[12.26328,51.653439],"type":"Point"}
}