{
  "type": "Feature",
  "properties": {
    "iso:country":"DE",
    "sg:address":"Seilerweg 14",
    "sg:city":"Walzbachtal",
    "sg:phone":"+49 4972/0391360",
    "sg:postcode":"75045",
    "sg:province":"Baden-W\u00fcrttemberg",
    "wof:name":"Huber Plastic Gmbh & Co Kg",
    "wof:placetype":"venue"
},
  "geometry": {"coordinates":[8.61411,49.012527],"type":"Point"}
}