{
  "type": "Feature",
  "properties": {
    "iso:country":"DE",
    "sg:address":"Prenzlauer Allee 195",
    "sg:city":"Berlin",
    "sg:phone":"+49 30/4417406",
    "sg:postcode":"10405",
    "sg:province":"Berlin",
    "wof:name":"Khleifs",
    "wof:placetype":"venue"
},
  "geometry": {"coordinates":[13.424081,52.539612],"type":"Point"}
}