{
  "type": "Feature",
  "properties": {
    "iso:country":"DE",
    "sg:address":"K\u00f6nigsberger Str. 3",
    "sg:city":"Kaufbeuren",
    "sg:phone":"+49 8341/2314",
    "sg:postcode":"87600",
    "sg:province":"Bayern",
    "wof:name":"Dardania-grill",
    "wof:placetype":"venue"
},
  "geometry": {"coordinates":[10.6380319595,47.8869781494],"type":"Point"}
}