{
  "type": "Feature",
  "properties": {
    "iso:country":"DE",
    "sg:address":"Kaiserstr. 100",
    "sg:city":"Dortmund",
    "sg:phone":"+49 231/573897",
    "sg:postcode":"44135",
    "sg:province":"Nordrhein-Westfalen",
    "wof:name":"W. Schulte",
    "wof:placetype":"venue"
},
  "geometry": {"coordinates":[7.4830908775,51.5131645203],"type":"Point"}
}