{
  "type": "Feature",
  "properties": {
    "iso:country":"DE",
    "sg:address":"Herrnstr. 10-12",
    "sg:city":"Kitzingen",
    "sg:phone":"+49 9321/13900",
    "sg:postcode":"97318",
    "sg:province":"Bayern",
    "wof:name":"Lang & Partner Treuhand-gmbh",
    "wof:placetype":"venue"
},
  "geometry": {"coordinates":[10.161356926,49.7377586365],"type":"Point"}
}