{
  "type": "Feature",
  "properties": {
    "iso:country":"DE",
    "sg:address":"Gippe 12",
    "sg:city":"Elsterberg",
    "sg:phone":"+49 36621/20370",
    "sg:postcode":"07985",
    "sg:province":"Th\u00fcringen",
    "wof:name":"Drk Altenpflegeheim",
    "wof:placetype":"venue"
},
  "geometry": {"coordinates":[12.160086,50.596516],"type":"Point"}
}