{
  "type": "Feature",
  "properties": {
    "iso:country":"DE",
    "sg:address":"Waldschulstr.",
    "sg:city":"Schwerin",
    "sg:phone":"+49 385/213200",
    "sg:postcode":"19061",
    "sg:province":"Mecklenburg-Vorpommern",
    "wof:name":"B\u00e4renschenke",
    "wof:placetype":"venue"
},
  "geometry": {"coordinates":[11.4360790253,53.6113471985],"type":"Point"}
}