{
  "type": "Feature",
  "properties": {
    "iso:country":"DE",
    "sg:address":"Sch\u00f6ppenstedter Str. 43",
    "sg:city":"Braunschweig",
    "sg:phone":"+49 531/45650",
    "sg:postcode":"38100",
    "sg:province":"Niedersachsen",
    "wof:name":"Klaus Gerwien",
    "wof:placetype":"venue"
},
  "geometry": {"coordinates":[10.529662,52.265991],"type":"Point"}
}