{
  "type": "Feature",
  "properties": {
    "iso:country":"DE",
    "sg:address":"Stadtgrabenstr. 25",
    "sg:city":"Bruchsal",
    "sg:phone":"+49 7251/89246",
    "sg:postcode":"76646",
    "sg:province":"Baden-W\u00fcrttemberg",
    "wof:name":"Caritasverband E. V.",
    "wof:placetype":"venue"
},
  "geometry": {"coordinates":[8.595893,49.122856],"type":"Point"}
}