{
  "type": "Feature",
  "properties": {
    "iso:country":"DE",
    "sg:address":"Haarweg 44",
    "sg:city":"Neuenkirchen",
    "sg:phone":"+49 5973/600144",
    "sg:postcode":"48485",
    "sg:province":"Nordrhein-Westfalen",
    "wof:name":"Restaurant Tennispark",
    "wof:placetype":"venue"
},
  "geometry": {"coordinates":[7.3626861572,52.2294387817],"type":"Point"}
}