{
  "type": "Feature",
  "properties": {
    "iso:country":"DE",
    "sg:address":"Am Bach 3",
    "sg:city":"Kappelrodeck",
    "sg:phone":"+49 7842/2010",
    "sg:postcode":"77876",
    "sg:province":"Baden-W\u00fcrttemberg",
    "wof:name":"Euro-tours Hugo Pfeifer",
    "wof:placetype":"venue"
},
  "geometry": {"coordinates":[8.1036529541,48.5898742676],"type":"Point"}
}