{
  "type": "Feature",
  "properties": {
    "iso:country":"DE",
    "sg:address":"Hermann-L\u00f6ns-Weg 50",
    "sg:city":"Bammental",
    "sg:phone":"+49 6223/95060",
    "sg:postcode":"69245",
    "sg:province":"Baden-W\u00fcrttemberg",
    "wof:name":"F\u00f6hrenbach Seniorenheim Gmbh",
    "wof:placetype":"venue"
},
  "geometry": {"coordinates":[8.777028,49.365967],"type":"Point"}
}