{
  "type": "Feature",
  "properties": {
    "iso:country":"DE",
    "sg:address":"Am K\u00f6hlerort 30",
    "sg:city":"Hamb\u00fchren",
    "sg:phone":"+49 5143/471",
    "sg:postcode":"29313",
    "sg:province":"Niedersachsen",
    "wof:name":"Reinhard Unger",
    "wof:placetype":"venue"
},
  "geometry": {"coordinates":[9.933457,52.651642],"type":"Point"}
}