{
  "type": "Feature",
  "properties": {
    "iso:country":"DE",
    "sg:address":"Raschdorffstr. 1",
    "sg:city":"K\u00f6ln",
    "sg:phone":"+49 221/495554",
    "sg:postcode":"50933",
    "sg:province":"Nordrhein-Westfalen",
    "wof:name":"Carl Seher",
    "wof:placetype":"venue"
},
  "geometry": {"coordinates":[6.8912611008,50.9347648621],"type":"Point"}
}