{
  "type": "Feature",
  "properties": {
    "iso:country":"DE",
    "sg:address":"Flensburger Str. 9",
    "sg:city":"Berlin",
    "sg:phone":"+49 30/3914963",
    "sg:postcode":"10557",
    "sg:province":"Berlin",
    "wof:name":"W. Von Herder Architekt",
    "wof:placetype":"venue"
},
  "geometry": {"coordinates":[13.344235,52.52029],"type":"Point"}
}