{
  "type": "Feature",
  "properties": {
    "iso:country":"DE",
    "sg:address":"Petritorwall 9",
    "sg:city":"Braunschweig",
    "sg:phone":"+49 531/400733",
    "sg:postcode":"38118",
    "sg:province":"Niedersachsen",
    "wof:name":"Burghard M\u00fchlenberg",
    "wof:placetype":"venue"
},
  "geometry": {"coordinates":[10.5126800537,52.2666816711],"type":"Point"}
}