{
  "type": "Feature",
  "properties": {
    "iso:country":"DE",
    "sg:address":"Maximilianstr. 18",
    "sg:city":"M\u00fcnchen",
    "sg:phone":"+49 89/222731",
    "sg:postcode":"80539",
    "sg:province":"Bayern",
    "wof:name":"Fraternitas Beteiligungen Gmbh",
    "wof:placetype":"venue"
},
  "geometry": {"coordinates":[11.581368,48.138775],"type":"Point"}
}