{
  "type": "Feature",
  "properties": {
    "iso:country":"DE",
    "sg:address":"Albertalstr. 2",
    "sg:city":"Dillingen",
    "sg:phone":"+49 9071/4033",
    "sg:postcode":"89407",
    "sg:province":"Bayern",
    "wof:name":"W. G\u00fcntner Immobilienmakler",
    "wof:placetype":"venue"
},
  "geometry": {"coordinates":[10.4989299774,48.5817604065],"type":"Point"}
}