{
  "type": "Feature",
  "properties": {
    "iso:country":"DE",
    "sg:address":"Bergstedter Chaussee 176",
    "sg:city":"Hamburg",
    "sg:phone":"+49 40/6048157",
    "sg:postcode":"22395",
    "sg:province":"Hamburg",
    "wof:name":"S. Taubenheim",
    "wof:placetype":"venue"
},
  "geometry": {"coordinates":[10.13224,53.673618],"type":"Point"}
}