{
  "type": "Feature",
  "properties": {
    "iso:country":"DE",
    "sg:address":"Elfringhauser Str. 29",
    "sg:city":"Hattingen",
    "sg:phone":"+49 2324/22191",
    "sg:postcode":"45527",
    "sg:province":"Nordrhein-Westfalen",
    "wof:name":"Rainer Kilfitt",
    "wof:placetype":"venue"
},
  "geometry": {"coordinates":[7.1969,51.374321],"type":"Point"}
}