{
  "type": "Feature",
  "properties": {
    "iso:country":"DE",
    "sg:address":"Paul-Ehrlich-Weg 9",
    "sg:city":"M\u00fcnchen",
    "sg:postcode":"80999",
    "sg:province":"Bayern",
    "wof:name":"Ecs Enterprise Consulting Solution M\u00fcnchen Gmbh",
    "wof:placetype":"venue"
},
  "geometry": {"coordinates":[11.455276,48.194283],"type":"Point"}
}