{
  "type": "Feature",
  "properties": {
    "iso:country":"DE",
    "sg:address":"Tunibergstr. 2",
    "sg:city":"Bad Krozingen",
    "sg:phone":"+49 7633/14592",
    "sg:postcode":"79189",
    "sg:province":"Baden-W\u00fcrttemberg",
    "wof:name":"Georg Faller",
    "wof:placetype":"venue"
},
  "geometry": {"coordinates":[7.6695017815,47.9534187317],"type":"Point"}
}