{
  "type": "Feature",
  "properties": {
    "iso:country":"DE",
    "sg:address":"K\u00f6nig-Rudolf-Str. 25",
    "sg:city":"Kaufbeuren",
    "sg:phone":"+49 8341/4960",
    "sg:postcode":"87600",
    "sg:province":"Bayern",
    "wof:name":"Ottmar Seiband Gashandlung",
    "wof:placetype":"venue"
},
  "geometry": {"coordinates":[10.6255226135,47.8904495239],"type":"Point"}
}