{
  "type": "Feature",
  "properties": {
    "iso:country":"DE",
    "sg:address":"Hermuehlheimer Str. 10",
    "sg:city":"Bruehl",
    "sg:phone":"+49 2232/18960",
    "sg:postcode":"50321",
    "sg:province":"Nordrhein-Westfalen",
    "wof:name":"Tuev-rheinland",
    "wof:placetype":"venue"
},
  "geometry": {"coordinates":[6.905728,50.84499],"type":"Point"}
}