{
  "type": "Feature",
  "properties": {
    "iso:country":"DE",
    "sg:address":"Stader Str. 32",
    "sg:city":"Buxtehude",
    "sg:phone":"+49 4161/82088",
    "sg:postcode":"21614",
    "sg:province":"Niedersachsen",
    "wof:name":"Wiehler",
    "wof:placetype":"venue"
},
  "geometry": {"coordinates":[9.682954,53.469124],"type":"Point"}
}