{
  "type": "Feature",
  "properties": {
    "iso:country":"DE",
    "sg:address":"Demianiplatz 1",
    "sg:city":"G\u00f6rlitz",
    "sg:phone":"+49 3581/671351",
    "sg:postcode":"02826",
    "sg:province":"Sachsen",
    "wof:name":"St\u00e4dtische Kunstsammlung",
    "wof:placetype":"venue"
},
  "geometry": {"coordinates":[14.985379,51.154816],"type":"Point"}
}