{
  "type": "Feature",
  "properties": {
    "iso:country":"DE",
    "sg:address":"Steinbruchstr.",
    "sg:city":"Spardorf",
    "sg:phone":"+49 9131/59796",
    "sg:postcode":"91080",
    "sg:province":"Bayern",
    "wof:name":"Hallenschwimmbad",
    "wof:placetype":"venue"
},
  "geometry": {"coordinates":[11.0534496307,49.5989189148],"type":"Point"}
}