{
  "type": "Feature",
  "properties": {
    "iso:country":"DE",
    "sg:address":"Tersteegenstr. 11",
    "sg:city":"Bielefeld",
    "sg:phone":"+49 521/331846",
    "sg:postcode":"33719",
    "sg:province":"Nordrhein-Westfalen",
    "wof:name":"G\u00fcnther Aussieker Architekt",
    "wof:placetype":"venue"
},
  "geometry": {"coordinates":[8.604538,52.035046],"type":"Point"}
}