{
  "type": "Feature",
  "properties": {
    "iso:country":"DE",
    "sg:address":"Landshuter Str. 11",
    "sg:city":"Ergolding",
    "sg:phone":"+49 871/74001",
    "sg:postcode":"84030",
    "sg:province":"Bayern",
    "wof:name":"Heim & Huber Gmbh",
    "wof:placetype":"venue"
},
  "geometry": {"coordinates":[12.162281,48.57201],"type":"Point"}
}