{
  "type": "Feature",
  "properties": {
    "iso:country":"DE",
    "sg:address":"Kirchenstr. 10",
    "sg:city":"Fridolfing",
    "sg:postcode":"83413",
    "sg:province":"Bayern",
    "wof:name":"Lederland-ghaus Gmbh",
    "wof:placetype":"venue"
},
  "geometry": {"coordinates":[12.797328949,48.0160636902],"type":"Point"}
}