{
  "type": "Feature",
  "properties": {
    "iso:country":"DE",
    "sg:address":"Nachtigallenweg 2",
    "sg:city":"Erdmannhausen",
    "sg:phone":"+49 7144/6278",
    "sg:postcode":"71729",
    "sg:province":"Baden-W\u00fcrttemberg",
    "wof:name":"Klaus Schoske Ingenieur",
    "wof:placetype":"venue"
},
  "geometry": {"coordinates":[9.3018131256,48.9452133179],"type":"Point"}
}