{
  "type": "Feature",
  "properties": {
    "iso:country":"DE",
    "sg:address":"Grabenfeld 2",
    "sg:city":"Barsinghausen",
    "sg:postcode":"30890",
    "sg:province":"Niedersachsen",
    "wof:name":"Tb Planbau Gmbh",
    "wof:placetype":"venue"
},
  "geometry": {"coordinates":[9.492431,52.336605],"type":"Point"}
}