{
  "type": "Feature",
  "properties": {
    "iso:country":"DE",
    "sg:address":"Keilbergstr. 24",
    "sg:city":"B\u00f6blingen",
    "sg:phone":"+49 7031/226460",
    "sg:postcode":"71032",
    "sg:province":"Baden-W\u00fcrttemberg",
    "wof:name":"P. Wende",
    "wof:placetype":"venue"
},
  "geometry": {"coordinates":[9.0292739868,48.6813621521],"type":"Point"}
}