{
  "type": "Feature",
  "properties": {
    "iso:country":"DE",
    "sg:address":"Offenbacher Landstr. 325",
    "sg:city":"Frankfurt",
    "sg:phone":"+49 69/651996",
    "sg:postcode":"60599",
    "sg:province":"Hessen",
    "wof:name":"R. Juchems",
    "wof:placetype":"venue"
},
  "geometry": {"coordinates":[8.722325325,50.1006317139],"type":"Point"}
}