{
  "type": "Feature",
  "properties": {
    "iso:country":"DE",
    "sg:address":"Keilbecker Str. 49",
    "sg:city":"Radevormwald",
    "sg:phone":"+49 2191/63202",
    "sg:postcode":"42477",
    "sg:province":"Nordrhein-Westfalen",
    "wof:name":"Margret Wisotzki",
    "wof:placetype":"venue"
},
  "geometry": {"coordinates":[7.311934,51.218822],"type":"Point"}
}