{
  "type": "Feature",
  "properties": {
    "iso:country":"DE",
    "sg:address":"Nansenstr. 10",
    "sg:city":"Bremerhaven",
    "sg:phone":"+49 471/28091",
    "sg:postcode":"27572",
    "sg:province":"Bremen",
    "wof:name":"Dr. T\u00f6dter Und Dr. Schamberger",
    "wof:placetype":"venue"
},
  "geometry": {"coordinates":[8.5893182755,53.5254364014],"type":"Point"}
}