{
  "type": "Feature",
  "properties": {
    "iso:country":"DE",
    "sg:address":"Blumenstr. 8",
    "sg:city":"Riegelsberg",
    "sg:postcode":"66292",
    "sg:province":"Saarland",
    "wof:name":"Ruth.marie Scholl-holzer Rechtsanw\u00e4ltin",
    "wof:placetype":"venue"
},
  "geometry": {"coordinates":[6.9186019897,49.3259391785],"type":"Point"}
}