{
  "type": "Feature",
  "properties": {
    "iso:country":"DE",
    "sg:address":"K\u00f6nig-Karl-Str. 34 b",
    "sg:city":"Stuttgart",
    "sg:phone":"+49 711/567784",
    "sg:postcode":"70372",
    "sg:province":"Baden-W\u00fcrttemberg",
    "wof:name":"Scarab\u00e4us-apotheke",
    "wof:placetype":"venue"
},
  "geometry": {"coordinates":[9.218646,48.805103],"type":"Point"}
}