{
  "type": "Feature",
  "properties": {
    "iso:country":"DE",
    "sg:address":"Ortliebs 9",
    "sg:city":"Weingarten",
    "sg:phone":"+49 751/561840",
    "sg:postcode":"88250",
    "sg:province":"Baden-W\u00fcrttemberg",
    "wof:name":"Georg Reisch Gmbh & Co. Kg",
    "wof:placetype":"venue"
},
  "geometry": {"coordinates":[9.62912,47.822582],"type":"Point"}
}