{
  "type": "Feature",
  "properties": {
    "iso:country":"DE",
    "sg:address":"Spessartstr 4",
    "sg:city":"Balingen",
    "sg:phone":"+49 5731/55781",
    "sg:postcode":"72336",
    "sg:province":"Baden-W\u00fcrttemberg",
    "wof:name":"Medizintechnik Frank Guder",
    "wof:placetype":"venue"
},
  "geometry": {"coordinates":[8.81207,52.231564],"type":"Point"}
}