{
  "type": "Feature",
  "properties": {
    "iso:country":"DE",
    "sg:address":"Emil-von-Behring-Str. 76",
    "sg:city":"Marburg",
    "sg:postcode":"35041",
    "sg:province":"Hessen",
    "wof:name":"Medinnova Ges. F. Medizinische Innovationen Aus Akademischer",
    "wof:placetype":"venue"
},
  "geometry": {"coordinates":[8.747372,50.820995],"type":"Point"}
}