{
  "type": "Feature",
  "properties": {
    "iso:country":"DE",
    "sg:address":"Graf-Eberstein-Str. 10",
    "sg:city":"Krautheim",
    "sg:phone":"+49 6294/45220",
    "sg:postcode":"74238",
    "sg:province":"Baden-W\u00fcrttemberg",
    "wof:name":"Pflege Zuhause Christiane Weyrosta",
    "wof:placetype":"venue"
},
  "geometry": {"coordinates":[9.638801,49.389645],"type":"Point"}
}