{
  "type": "Feature",
  "properties": {
    "iso:country":"DE",
    "sg:address":"Markt 4",
    "sg:city":"Glash\u00fctte",
    "sg:phone":"+49 35053/2449",
    "sg:postcode":"01768",
    "sg:province":"Sachsen",
    "wof:name":"Volksbank Dresden E. G.",
    "wof:placetype":"venue"
},
  "geometry": {"coordinates":[13.778216,50.852333],"type":"Point"}
}