{
  "type": "Feature",
  "properties": {
    "iso:country":"DE",
    "sg:address":"Feldmochinger Str. 7",
    "sg:city":"M\u00fcnchen",
    "sg:phone":"+49 89/780210",
    "sg:postcode":"80992",
    "sg:province":"Bayern",
    "wof:name":"Ada-das Systemhaus Gmbh",
    "wof:placetype":"venue"
},
  "geometry": {"coordinates":[11.5210886002,48.1779823303],"type":"Point"}
}