{
  "type": "Feature",
  "properties": {
    "iso:country":"DE",
    "sg:address":"Jahnstr. 23",
    "sg:city":"Bretzfeld",
    "sg:phone":"+49 7946/529",
    "sg:postcode":"74626",
    "sg:province":"Baden-W\u00fcrttemberg",
    "wof:name":"Erwin Barske Ingenieur",
    "wof:placetype":"venue"
},
  "geometry": {"coordinates":[9.4366922379,49.1640167236],"type":"Point"}
}