{
  "type": "Feature",
  "properties": {
    "iso:country":"DE",
    "sg:address":"Bleichstr. 72",
    "sg:city":"Bielefeld",
    "sg:phone":"+49 521/321446",
    "sg:postcode":"33607",
    "sg:province":"Nordrhein-Westfalen",
    "wof:name":"Herbert Pelz",
    "wof:placetype":"venue"
},
  "geometry": {"coordinates":[8.561939,52.026932],"type":"Point"}
}