{
  "type": "Feature",
  "properties": {
    "iso:country":"DE",
    "sg:address":"Gewerbepark 17",
    "sg:city":"Hamm",
    "sg:phone":"+49 2385/432",
    "sg:postcode":"59069",
    "sg:province":"Nordrhein-Westfalen",
    "wof:name":"Saabel Handelsgesellschaft Mbh",
    "wof:placetype":"venue"
},
  "geometry": {"coordinates":[7.850536,51.623222],"type":"Point"}
}