{
  "type": "Feature",
  "properties": {
    "iso:country":"DE",
    "sg:address":"Steinweg 37",
    "sg:city":"Volkmarsen",
    "sg:phone":"+49 5693/443",
    "sg:postcode":"34471",
    "sg:province":"Hessen",
    "wof:name":"E. Und K. Legel",
    "wof:placetype":"venue"
},
  "geometry": {"coordinates":[9.1143512726,51.4133338928],"type":"Point"}
}