{
  "type": "Feature",
  "properties": {
    "iso:country":"DE",
    "sg:address":"Liebherrstr 5",
    "sg:city":"M\u00fcnchen",
    "sg:phone":"+49 89/2429270",
    "sg:postcode":"80538",
    "sg:province":"Bayern",
    "wof:name":"Agentur 2 Gmbh",
    "wof:placetype":"venue"
},
  "geometry": {"coordinates":[11.585128,48.13459],"type":"Point"}
}