{
  "type": "Feature",
  "properties": {
    "iso:country":"DE",
    "sg:address":"Ebernhahner Str. 67",
    "sg:city":"Dernbach",
    "sg:postcode":"56428",
    "sg:province":"Rheinland-Pfalz",
    "wof:name":"Herbst-touristik Gmbh",
    "wof:placetype":"venue"
},
  "geometry": {"coordinates":[7.7917399406,50.4559898376],"type":"Point"}
}