{
  "type": "Feature",
  "properties": {
    "iso:country":"DE",
    "sg:address":"Milchgrundstr. 32",
    "sg:city":"Michelbach an der Bilz",
    "sg:postcode":"74544",
    "sg:province":"Baden-W\u00fcrttemberg",
    "wof:name":"Then Maschinen- Und Apparatebau Gmbh",
    "wof:placetype":"venue"
},
  "geometry": {"coordinates":[9.7578010559,49.0910606384],"type":"Point"}
}