{
  "type": "Feature",
  "properties": {
    "iso:country":"DE",
    "sg:address":"Zum Bahnhof 20",
    "sg:city":"Gronau",
    "sg:phone":"+49 2565/6423",
    "sg:postcode":"48599",
    "sg:province":"Nordrhein-Westfalen",
    "wof:name":"Indoor - Kart - Gmbh",
    "wof:placetype":"venue"
},
  "geometry": {"coordinates":[7.032255,52.182674],"type":"Point"}
}