{
  "type": "Feature",
  "properties": {
    "iso:country":"DE",
    "sg:address":"Knooper Weg 170",
    "sg:city":"Kiel",
    "sg:phone":"+49 431/563982",
    "sg:postcode":"24105",
    "sg:province":"Schleswig-Holstein",
    "wof:name":"Deutsche Shell Ag",
    "wof:placetype":"venue"
},
  "geometry": {"coordinates":[10.1314325333,54.3363304138],"type":"Point"}
}