{
  "type": "Feature",
  "properties": {
    "iso:country":"DE",
    "sg:address":"N\u00f6rdlinger Str. 90",
    "sg:city":"K\u00f6nigsbrunn",
    "sg:phone":"+49 8231/4559",
    "sg:postcode":"86343",
    "sg:province":"Bayern",
    "wof:name":"Hugo Fischer Architekt",
    "wof:placetype":"venue"
},
  "geometry": {"coordinates":[10.8893232346,48.2795333862],"type":"Point"}
}