{
  "type": "Feature",
  "properties": {
    "iso:country":"DE",
    "sg:address":"Waldstr. 18",
    "sg:city":"Bad Schwartau",
    "sg:phone":"+49 451/22104",
    "sg:postcode":"23611",
    "sg:province":"Schleswig-Holstein",
    "wof:name":"Hans Evers Ingenieur",
    "wof:placetype":"venue"
},
  "geometry": {"coordinates":[10.6771936417,53.9081497192],"type":"Point"}
}