{
  "type": "Feature",
  "properties": {
    "iso:country":"DE",
    "sg:address":"Am Bug 11",
    "sg:city":"Scharbeutz",
    "sg:phone":"+49 4563/1686",
    "sg:postcode":"23683",
    "sg:province":"Schleswig-Holstein",
    "wof:name":"Steinfeld Handels Gmbh",
    "wof:placetype":"venue"
},
  "geometry": {"coordinates":[10.7482748032,54.0477561951],"type":"Point"}
}