{
  "type": "Feature",
  "properties": {
    "iso:country":"DE",
    "sg:address":"Puschkinallee 15",
    "sg:city":"Angerm\u00fcnde",
    "sg:phone":"+49 3331/24058",
    "sg:postcode":"16278",
    "sg:province":"Brandenburg",
    "wof:name":"Bewicon-angerm\u00fcnder Holzbearbeitungsges. Mbh",
    "wof:placetype":"venue"
},
  "geometry": {"coordinates":[13.9906139374,53.0061302185],"type":"Point"}
}