{
  "type": "Feature",
  "properties": {
    "iso:country":"DE",
    "sg:address":"Rupprechtstr. 14",
    "sg:city":"M\u00fcnchen",
    "sg:phone":"+49 89/182278",
    "sg:postcode":"80636",
    "sg:province":"Bayern",
    "wof:name":"Manfred Abeska",
    "wof:placetype":"venue"
},
  "geometry": {"coordinates":[11.5415410995,48.148399353],"type":"Point"}
}