{
  "type": "Feature",
  "properties": {
    "iso:country":"DE",
    "sg:address":"F\u00fcrstenbrunner Wg. 54-60",
    "sg:city":"Berlin",
    "sg:phone":"+49 4930/3021943",
    "sg:postcode":"14059",
    "sg:province":"Berlin",
    "wof:name":"Schicht Fuhrunternehmen Gmbh & Co, Johann",
    "wof:placetype":"venue"
},
  "geometry": {"coordinates":[13.2796106339,52.5237579346],"type":"Point"}
}