{
  "type": "Feature",
  "properties": {
    "iso:country":"DE",
    "sg:address":"Lange Str. 129 a",
    "sg:city":"Vlotho",
    "sg:phone":"+49 5733/10222",
    "sg:postcode":"32602",
    "sg:province":"Nordrhein-Westfalen",
    "wof:name":"Parf\u00fcmerie Am Markt",
    "wof:placetype":"venue"
},
  "geometry": {"coordinates":[8.86021,52.16687],"type":"Point"}
}