{
  "type": "Feature",
  "properties": {
    "iso:country":"DE",
    "sg:address":"Gewerbering 5",
    "sg:city":"Dorfen",
    "sg:phone":"+49 8081/603",
    "sg:postcode":"84405",
    "sg:province":"Bayern",
    "wof:name":"Waschstr. Und Reifenservice Dorfen Stimmer & Sill Gmbh",
    "wof:placetype":"venue"
},
  "geometry": {"coordinates":[12.1592302322,48.2783813477],"type":"Point"}
}