{
  "type": "Feature",
  "properties": {
    "iso:country":"DE",
    "sg:address":"Bahnhofstr. 19",
    "sg:city":"Kamen",
    "sg:phone":"+49 2307/71707",
    "sg:postcode":"59174",
    "sg:province":"Nordrhein-Westfalen",
    "wof:name":"Rolf Stendenbach",
    "wof:placetype":"venue"
},
  "geometry": {"coordinates":[7.6628518105,51.5889282227],"type":"Point"}
}