{
  "type": "Feature",
  "properties": {
    "iso:country":"DE",
    "sg:address":"Auf dem Stein 12",
    "sg:city":"Selfkant",
    "sg:phone":"+49 2456/1241",
    "sg:postcode":"52538",
    "sg:province":"Nordrhein-Westfalen",
    "wof:name":"Th. Houben",
    "wof:placetype":"venue"
},
  "geometry": {"coordinates":[5.923845,51.031715],"type":"Point"}
}