{
  "type": "Feature",
  "properties": {
    "iso:country":"DE",
    "sg:address":"Emdener Str. 150",
    "sg:city":"Aschendorf",
    "sg:phone":"+49 4962/91150",
    "sg:postcode":"26871",
    "sg:province":"Niedersachsen",
    "wof:name":"Ludger Edelkamp",
    "wof:placetype":"venue"
},
  "geometry": {"coordinates":[7.363641,53.064552],"type":"Point"}
}