{
  "type": "Feature",
  "properties": {
    "iso:country":"DE",
    "sg:address":"Oldendorfer Str. 32",
    "sg:city":"Melle",
    "sg:phone":"+49 5422/5781",
    "sg:postcode":"49324",
    "sg:province":"Niedersachsen",
    "wof:name":"Heinrich Stefener Gmbh",
    "wof:placetype":"venue"
},
  "geometry": {"coordinates":[8.3359575272,52.2093391418],"type":"Point"}
}