{
  "type": "Feature",
  "properties": {
    "iso:country":"DE",
    "sg:address":"Ahauser Hof 4",
    "sg:city":"Nordhorn",
    "sg:phone":"+49 5921/4021",
    "sg:postcode":"48527",
    "sg:province":"Niedersachsen",
    "wof:name":"Feinkost-lange Gmbh & Co. Kg",
    "wof:placetype":"venue"
},
  "geometry": {"coordinates":[7.0477409363,52.4167327881],"type":"Point"}
}