{
  "type": "Feature",
  "properties": {
    "iso:country":"DE",
    "sg:address":"Feldm\u00fchlenstr 51",
    "sg:city":"Hagen",
    "sg:phone":"+49 2331/63400",
    "sg:postcode":"58093",
    "sg:province":"Nordrhein-Westfalen",
    "wof:name":"Edv Institut Oventrop Hagen Gmbh",
    "wof:placetype":"venue"
},
  "geometry": {"coordinates":[7.4984149933,51.3927383423],"type":"Point"}
}