{
  "type": "Feature",
  "properties": {
    "iso:country":"DE",
    "sg:address":"R\u00f6ttgener Str. 23 a",
    "sg:city":"Bonn",
    "sg:phone":"+49 228/281467",
    "sg:postcode":"53127",
    "sg:province":"Nordrhein-Westfalen",
    "wof:name":"Paul Waasen K\u00fcchenchef",
    "wof:placetype":"venue"
},
  "geometry": {"coordinates":[7.081183,50.702328],"type":"Point"}
}