{
  "type": "Feature",
  "properties": {
    "iso:country":"DE",
    "sg:address":"Obere Weingartenstr. 123",
    "sg:city":"Ernst",
    "sg:phone":"+49 2671/7561",
    "sg:postcode":"56814",
    "sg:province":"Rheinland-Pfalz",
    "wof:name":"Winzergenossenschaft Des Kreises Cochem Egmbh",
    "wof:placetype":"venue"
},
  "geometry": {"coordinates":[7.231135,50.133148],"type":"Point"}
}