{
  "type": "Feature",
  "properties": {
    "iso:country":"DE",
    "sg:address":"Hindenburgstr. 28",
    "sg:city":"Langenzenn",
    "sg:phone":"+49 9101/8254",
    "sg:postcode":"90579",
    "sg:province":"Bayern",
    "wof:name":"Martin Wiegel Haus- Und K\u00fcchenger\u00e4te",
    "wof:placetype":"venue"
},
  "geometry": {"coordinates":[10.7916069031,49.4940185547],"type":"Point"}
}