{
  "type": "Feature",
  "properties": {
    "iso:country":"DE",
    "sg:address":"Otto-von-Puchberg-Str. 8",
    "sg:city":"Cham",
    "sg:phone":"+49 9971/7422",
    "sg:postcode":"93413",
    "sg:province":"Bayern",
    "wof:name":"M. Roider",
    "wof:placetype":"venue"
},
  "geometry": {"coordinates":[12.709553,49.238899],"type":"Point"}
}