{
  "type": "Feature",
  "properties": {
    "iso:country":"DE",
    "sg:address":"Prinz-Handjery-Str. 70 b",
    "sg:city":"Berlin",
    "sg:phone":"+49 30/8155561",
    "sg:postcode":"14167",
    "sg:province":"Berlin",
    "wof:name":"Fmd Facility Management Dienstleistungen Gmbh",
    "wof:placetype":"venue"
},
  "geometry": {"coordinates":[13.263584137,52.4292793274],"type":"Point"}
}