{
  "type": "Feature",
  "properties": {
    "iso:country":"DE",
    "sg:address":"Barnackufer 22 a",
    "sg:city":"Berlin",
    "sg:phone":"+49 30/7724844",
    "sg:postcode":"12207",
    "sg:province":"Berlin",
    "wof:name":"Rausch & Raschmeyer Gmbh",
    "wof:placetype":"venue"
},
  "geometry": {"coordinates":[13.3117399216,52.4286193848],"type":"Point"}
}