{
  "type": "Feature",
  "properties": {
    "iso:country":"DE",
    "sg:address":"Max-Planck-Str. 13",
    "sg:city":"H\u00f6chberg",
    "sg:phone":"+49 931/406910",
    "sg:postcode":"97204",
    "sg:province":"Bayern",
    "wof:name":"Cypress Gmbh",
    "wof:placetype":"venue"
},
  "geometry": {"coordinates":[9.8712797165,49.7705841064],"type":"Point"}
}