{
  "type": "Feature",
  "properties": {
    "iso:country":"DE",
    "sg:address":"Herbert-Hellmann-Allee 20",
    "sg:city":"Bad Krozingen",
    "sg:phone":"+49 7633/12714",
    "sg:postcode":"79189",
    "sg:province":"Baden-W\u00fcrttemberg",
    "wof:name":"Sigrid Pusch",
    "wof:placetype":"venue"
},
  "geometry": {"coordinates":[7.690343,47.919724],"type":"Point"}
}