{
  "type": "Feature",
  "properties": {
    "iso:country":"DE",
    "sg:address":"Marienplatz 6",
    "sg:city":"Katlenburg-Lindau",
    "sg:phone":"+49 5556/4395",
    "sg:postcode":"37191",
    "sg:province":"Niedersachsen",
    "wof:name":"Franz Henniges",
    "wof:placetype":"venue"
},
  "geometry": {"coordinates":[10.1191082001,51.6537284851],"type":"Point"}
}