{
  "type": "Feature",
  "properties": {
    "iso:country":"DE",
    "sg:address":"Buchensee 1",
    "sg:city":"Tutzing",
    "sg:phone":"+49 8158/2560",
    "sg:postcode":"82327",
    "sg:province":"Bayern",
    "wof:name":"Akademie F\u00fcr Politische Bildung",
    "wof:placetype":"venue"
},
  "geometry": {"coordinates":[11.2867326736,47.9181861877],"type":"Point"}
}