{
  "type": "Feature",
  "properties": {
    "iso:country":"DE",
    "sg:address":"Bahnhofstr. 18-18 a",
    "sg:city":"Maulbronn",
    "sg:phone":"+49 7043/1020",
    "sg:postcode":"75433",
    "sg:province":"Baden-W\u00fcrttemberg",
    "wof:name":"Schmid & Wezel Gmbh & Co.",
    "wof:placetype":"venue"
},
  "geometry": {"coordinates":[8.804233,48.997444],"type":"Point"}
}