{
  "type": "Feature",
  "properties": {
    "iso:country":"DE",
    "sg:address":"Gartenstr. 27",
    "sg:city":"Niedersch\u00f6nenfeld",
    "sg:postcode":"86694",
    "sg:province":"Bayern",
    "wof:name":"Franz R. Anger",
    "wof:placetype":"venue"
},
  "geometry": {"coordinates":[10.91416,48.709557],"type":"Point"}
}