{
  "type": "Feature",
  "properties": {
    "iso:country":"DE",
    "sg:address":"Ottostr. 23",
    "sg:city":"Marktredwitz",
    "sg:phone":"+49 9231/61565",
    "sg:postcode":"95615",
    "sg:province":"Bayern",
    "wof:name":"Uschis Kinderladen",
    "wof:placetype":"venue"
},
  "geometry": {"coordinates":[12.0860013962,49.9999198914],"type":"Point"}
}