{
  "type": "Feature",
  "properties": {
    "iso:country":"DE",
    "sg:address":"Josef-Schregel-Strasse 38",
    "sg:city":"D\u00fcren",
    "sg:postcode":"52349",
    "sg:province":"Nordrhein-Westfalen",
    "wof:name":"Proverbraucher",
    "wof:placetype":"venue"
},
  "geometry": {"coordinates":[6.481619,50.806957],"type":"Point"}
}