{
  "type": "Feature",
  "properties": {
    "iso:country":"DE",
    "sg:address":"Am Deyekamp 15",
    "sg:city":"Edewecht",
    "sg:postcode":"26188",
    "sg:province":"Niedersachsen",
    "wof:name":"Bestattungen Nagl E. K.",
    "wof:placetype":"venue"
},
  "geometry": {"coordinates":[7.981938,53.119553],"type":"Point"}
}