{
  "type": "Feature",
  "properties": {
    "iso:country":"DE",
    "sg:address":"Eichsfelder Str. 16",
    "sg:city":"Gieboldehausen",
    "sg:phone":"+49 5528/3216",
    "sg:postcode":"37434",
    "sg:province":"Niedersachsen",
    "wof:name":"Gebr. Rohde Gbr",
    "wof:placetype":"venue"
},
  "geometry": {"coordinates":[10.220561,51.604008],"type":"Point"}
}