{
  "type": "Feature",
  "properties": {
    "iso:country":"DE",
    "sg:address":"Am Hammersee 9",
    "sg:city":"Bodenw\u00f6hr",
    "sg:phone":"+49 9434/1260",
    "sg:postcode":"92439",
    "sg:province":"Bayern",
    "wof:name":"Fritz Kaiser Gmbh",
    "wof:placetype":"venue"
},
  "geometry": {"coordinates":[12.314387,49.272896],"type":"Point"}
}