{
  "type": "Feature",
  "properties": {
    "iso:country":"DE",
    "sg:address":"Spiessfeldstrasse",
    "sg:city":"Friedrichsdorf",
    "sg:phone":"+49 6175/940276",
    "sg:postcode":"61381",
    "sg:province":"Hessen",
    "wof:name":"Bdk-hessen",
    "wof:placetype":"venue"
},
  "geometry": {"coordinates":[8.65192,50.272205],"type":"Point"}
}