{
  "type": "Feature",
  "properties": {
    "iso:country":"DE",
    "sg:address":"Ackerstr. 6",
    "sg:city":"Bonn",
    "sg:phone":"+49 228/347246",
    "sg:postcode":"53179",
    "sg:province":"Nordrhein-Westfalen",
    "wof:name":"H. W. Meyer",
    "wof:placetype":"venue"
},
  "geometry": {"coordinates":[7.190319,50.662331],"type":"Point"}
}