{
  "type": "Feature",
  "properties": {
    "iso:country":"DE",
    "sg:address":"Gustav-Hummel-Str. 4",
    "sg:city":"Schwetzingen",
    "sg:phone":"+49 6202/18777",
    "sg:postcode":"68723",
    "sg:province":"Baden-W\u00fcrttemberg",
    "wof:name":"Markt-stube",
    "wof:placetype":"venue"
},
  "geometry": {"coordinates":[8.5774068832,49.3858909607],"type":"Point"}
}