{
  "type": "Feature",
  "properties": {
    "iso:country":"DE",
    "sg:address":"Kyllweg 1",
    "sg:city":"Gerolstein",
    "sg:postcode":"54568",
    "sg:province":"Rheinland-Pfalz",
    "wof:name":"Tw Gerolsteiner Land-touristik Und Wirtschaftsf\u00f6rderung Gmbh",
    "wof:placetype":"venue"
},
  "geometry": {"coordinates":[6.656158,50.222305],"type":"Point"}
}