{
  "type": "Feature",
  "properties": {
    "iso:country":"DE",
    "sg:address":"Rheinsberger Str. 2",
    "sg:city":"Lindow",
    "sg:phone":"+49 33933/70371",
    "sg:postcode":"16835",
    "sg:province":"Brandenburg",
    "wof:name":"H. Gehrmann",
    "wof:placetype":"venue"
},
  "geometry": {"coordinates":[12.986059,52.976044],"type":"Point"}
}