{
  "type": "Feature",
  "properties": {
    "iso:country":"DE",
    "sg:address":"B\u00f6ttgerstr. 40",
    "sg:city":"Weiden",
    "sg:phone":"+49 961/43489",
    "sg:postcode":"92637",
    "sg:province":"Bayern",
    "wof:name":"Blb-steuerberatungsgesell- Schaft Mbh",
    "wof:placetype":"venue"
},
  "geometry": {"coordinates":[12.154419899,49.663608551],"type":"Point"}
}