{
  "type": "Feature",
  "properties": {
    "iso:country":"DE",
    "sg:address":"Birkenweg 9",
    "sg:city":"Gelnhausen",
    "sg:phone":"+49 6051/4449",
    "sg:postcode":"63571",
    "sg:province":"Hessen",
    "wof:name":"Angelika Zenker",
    "wof:placetype":"venue"
},
  "geometry": {"coordinates":[9.14685,50.18293],"type":"Point"}
}