{
  "type": "Feature",
  "properties": {
    "iso:country":"DE",
    "sg:address":"Grimmestr. 4",
    "sg:city":"Bochum",
    "sg:phone":"+49 234/352070",
    "sg:postcode":"44803",
    "sg:province":"Nordrhein-Westfalen",
    "wof:name":"Gerhard Ayasse Rechtsanwalt",
    "wof:placetype":"venue"
},
  "geometry": {"coordinates":[7.2674078941,51.472038269],"type":"Point"}
}