{
  "type": "Feature",
  "properties": {
    "iso:country":"DE",
    "sg:address":"Lambertstr. 2",
    "sg:city":"Essen",
    "sg:phone":"+49 201/410877",
    "sg:postcode":"45131",
    "sg:province":"Nordrhein-Westfalen",
    "wof:name":"Renate Linden Heilpraktikerin",
    "wof:placetype":"venue"
},
  "geometry": {"coordinates":[7.0013790131,51.424785614],"type":"Point"}
}