{
  "type": "Feature",
  "properties": {
    "iso:country":"DE",
    "sg:address":"Hahnen\u00e4cker 23",
    "sg:city":"M\u00f6ckm\u00fchl",
    "sg:phone":"+49 6298/4530",
    "sg:postcode":"74219",
    "sg:province":"Baden-W\u00fcrttemberg",
    "wof:name":"Prezisa Wohnbau Gmbh",
    "wof:placetype":"venue"
},
  "geometry": {"coordinates":[9.34976,49.324615],"type":"Point"}
}