{
  "type": "Feature",
  "properties": {
    "iso:country":"DE",
    "sg:address":"Von-Humboldt-Weg 14",
    "sg:city":"Norderstedt",
    "sg:phone":"+49 40/5223249",
    "sg:postcode":"22846",
    "sg:province":"Schleswig-Holstein",
    "wof:name":"Kiesow Betriebs-verwaltungs Gmbh & Co.",
    "wof:placetype":"venue"
},
  "geometry": {"coordinates":[9.9831876755,53.7180404663],"type":"Point"}
}