{
  "type": "Feature",
  "properties": {
    "iso:country":"DE",
    "sg:address":"Seeberg 4 a",
    "sg:city":"Haag",
    "sg:phone":"+49 8764/1675",
    "sg:postcode":"85410",
    "sg:province":"Bayern",
    "wof:name":"Simon Reiter Gmbh",
    "wof:placetype":"venue"
},
  "geometry": {"coordinates":[11.845795,48.482849],"type":"Point"}
}