{
  "type": "Feature",
  "properties": {
    "iso:country":"DE",
    "sg:address":"Simonshofer Str. 16",
    "sg:city":"Lauf",
    "sg:phone":"+49 9123/96820",
    "sg:postcode":"91207",
    "sg:province":"Bayern",
    "wof:name":"Werner M\u00fcller Steuerberater Und",
    "wof:placetype":"venue"
},
  "geometry": {"coordinates":[11.2826662064,49.5156745911],"type":"Point"}
}