{
  "type": "Feature",
  "properties": {
    "iso:country":"DE",
    "sg:address":"Alter Sielweg 65",
    "sg:city":"Norden",
    "sg:phone":"+49 4926/494",
    "sg:postcode":"26506",
    "sg:province":"Niedersachsen",
    "wof:name":"Jakob Harms",
    "wof:placetype":"venue"
},
  "geometry": {"coordinates":[7.147967,53.510544],"type":"Point"}
}