{
  "type": "Feature",
  "properties": {
    "iso:country":"DE",
    "sg:address":"Am Heidepark 46",
    "sg:city":"Klein Schulzendorf",
    "sg:phone":"+49 33731/17471",
    "sg:postcode":"14959",
    "sg:province":"Brandenburg",
    "wof:name":"Reinhardt Ausbau Gmbh",
    "wof:placetype":"venue"
},
  "geometry": {"coordinates":[13.23931,52.194469],"type":"Point"}
}