{
  "type": "Feature",
  "properties": {
    "iso:country":"DE",
    "sg:address":"Flosser Str 19",
    "sg:city":"St\u00f6rnstein",
    "sg:phone":"+49 9602/94130",
    "sg:postcode":"92721",
    "sg:province":"Bayern",
    "wof:name":"Rofitec Maschinen Und Anlagenbau Gmbh",
    "wof:placetype":"venue"
},
  "geometry": {"coordinates":[12.207991,49.731991],"type":"Point"}
}