{
  "type": "Feature",
  "properties": {
    "iso:country":"DE",
    "sg:address":"Hilgerstr. 20",
    "sg:city":"Essen",
    "sg:phone":"+49 4927/767332",
    "sg:postcode":"45141",
    "sg:province":"Nordrhein-Westfalen",
    "wof:name":"Schaumstoff Center Gerhard Schumerus Gmbh & Co Kg",
    "wof:placetype":"venue"
},
  "geometry": {"coordinates":[8.4994401932,50.7628326416],"type":"Point"}
}