{
  "type": "Feature",
  "properties": {
    "iso:country":"DE",
    "sg:address":"Hofmark 20",
    "sg:city":"Bad Birnbach",
    "sg:phone":"+49 8563/3935",
    "sg:postcode":"84364",
    "sg:province":"Bayern",
    "wof:name":"Hofmark-apotheke",
    "wof:placetype":"venue"
},
  "geometry": {"coordinates":[13.092451,48.444077],"type":"Point"}
}