{
  "type": "Feature",
  "properties": {
    "iso:country":"DE",
    "sg:address":"Ochtruper Str. 83",
    "sg:city":"Gronau",
    "sg:phone":"+49 2562/3369",
    "sg:postcode":"48599",
    "sg:province":"Nordrhein-Westfalen",
    "wof:name":"Sch\u00fctzenhof",
    "wof:placetype":"venue"
},
  "geometry": {"coordinates":[7.0394377708,52.2077484131],"type":"Point"}
}