{
  "type": "Feature",
  "properties": {
    "iso:country":"DE",
    "sg:address":"Wiesentalstr. 41",
    "sg:city":"Rheinfelden",
    "sg:phone":"+49 7623/5805",
    "sg:postcode":"79618",
    "sg:province":"Baden-W\u00fcrttemberg",
    "wof:name":"Josef Brugger",
    "wof:placetype":"venue"
},
  "geometry": {"coordinates":[7.790535,47.604347],"type":"Point"}
}