{
  "type": "Feature",
  "properties": {
    "iso:country":"DE",
    "sg:address":"Engelstr. 1",
    "sg:city":"Merzig",
    "sg:phone":"+49 6861/88028",
    "sg:postcode":"66663",
    "sg:province":"Saarland",
    "wof:name":"Josef Zenner",
    "wof:placetype":"venue"
},
  "geometry": {"coordinates":[6.630735,49.418922],"type":"Point"}
}