{
  "type": "Feature",
  "properties": {
    "iso:country":"DE",
    "sg:address":"L\u00e4rchenstr. 20",
    "sg:city":"Schopfloch",
    "sg:phone":"+49 9857/9611",
    "sg:postcode":"91626",
    "sg:province":"Bayern",
    "wof:name":"Margit Sch\u00e4fer Gmbh",
    "wof:placetype":"venue"
},
  "geometry": {"coordinates":[10.307519,49.127827],"type":"Point"}
}