{
  "type": "Feature",
  "properties": {
    "iso:country":"DE",
    "sg:address":"Possenheim",
    "sg:city":"P\u00f6cking",
    "sg:phone":"+49 8157/8653",
    "sg:postcode":"82343",
    "sg:province":"Bayern",
    "wof:name":"T. Glas Bootshandlung",
    "wof:placetype":"venue"
},
  "geometry": {"coordinates":[11.30188,47.968456],"type":"Point"}
}