{
  "type": "Feature",
  "properties": {
    "iso:country":"DE",
    "sg:address":"Gartenstr. 24",
    "sg:city":"Reutlingen",
    "sg:phone":"+49 7121/346637",
    "sg:postcode":"72764",
    "sg:province":"Baden-W\u00fcrttemberg",
    "wof:name":"Nusser & Co. Gmbh",
    "wof:placetype":"venue"
},
  "geometry": {"coordinates":[9.213104,48.493156],"type":"Point"}
}