{
  "type": "Feature",
  "properties": {
    "iso:country":"DE",
    "sg:address":"M\u00fchlenstr. 36b",
    "sg:city":"Schee\u00dfel",
    "sg:phone":"+49 4263/1377",
    "sg:postcode":"27383",
    "sg:province":"Niedersachsen",
    "wof:name":"Fritz Wiesmueller Drogerie",
    "wof:placetype":"venue"
},
  "geometry": {"coordinates":[9.473856,53.16576],"type":"Point"}
}