{
  "type": "Feature",
  "properties": {
    "iso:country":"DE",
    "sg:address":"Kirchweg 29",
    "sg:city":"Kassel",
    "sg:postcode":"34121",
    "sg:province":"Hessen",
    "wof:name":"Pm Service Schuhreparatur- Und Schl\u00fcsselbetriebe Gmbh",
    "wof:placetype":"venue"
},
  "geometry": {"coordinates":[9.466173172,51.3113937378],"type":"Point"}
}