{
  "type": "Feature",
  "properties": {
    "iso:country":"DE",
    "sg:address":"Tulbeckstr. 1",
    "sg:city":"M\u00fcnchen",
    "sg:phone":"+49 89/5026727",
    "sg:postcode":"80339",
    "sg:province":"Bayern",
    "wof:name":"Adria-bau Gmbh",
    "wof:placetype":"venue"
},
  "geometry": {"coordinates":[11.543739,48.136692],"type":"Point"}
}