{
  "type": "Feature",
  "properties": {
    "iso:country":"DE",
    "sg:address":"H\u00f6tensleber Str 29",
    "sg:city":"Sch\u00f6ningen",
    "sg:phone":"+49 5352/94500",
    "sg:postcode":"38364",
    "sg:province":"Niedersachsen",
    "wof:name":"M\u00f6lle-bau Gmbh",
    "wof:placetype":"venue"
},
  "geometry": {"coordinates":[10.981416,52.13649],"type":"Point"}
}