{
  "type": "Feature",
  "properties": {
    "iso:country":"DE",
    "sg:address":"M\u00fchlenbeker Str. 4",
    "sg:city":"Kellinghusen",
    "sg:postcode":"25548",
    "sg:province":"Schleswig-Holstein",
    "wof:name":"Manfred Schenk",
    "wof:placetype":"venue"
},
  "geometry": {"coordinates":[9.7292394638,53.943321228],"type":"Point"}
}