{
  "type": "Feature",
  "properties": {
    "iso:country":"DE",
    "sg:address":"Westendstr. 160",
    "sg:city":"M\u00fcnchen",
    "sg:phone":"+49 89/5409540",
    "sg:postcode":"80339",
    "sg:province":"Bayern",
    "wof:name":"Falk U. Partner Gmbh & Co. Kg",
    "wof:placetype":"venue"
},
  "geometry": {"coordinates":[11.5274629593,48.1372718811],"type":"Point"}
}