{
  "type": "Feature",
  "properties": {
    "iso:country":"DE",
    "sg:address":"Krautgartenstr. 36",
    "sg:city":"Hebertshausen",
    "sg:phone":"+49 8131/2940",
    "sg:postcode":"85241",
    "sg:province":"Bayern",
    "wof:name":"Feinpappenwerk Gebr. Schuster Gmbh & Co. Kg",
    "wof:placetype":"venue"
},
  "geometry": {"coordinates":[11.4712028503,48.2871055603],"type":"Point"}
}