{
  "type": "Feature",
  "properties": {
    "iso:country":"DE",
    "sg:address":"Schlo\u00dfstr. 1",
    "sg:city":"Arnstadt",
    "sg:phone":"+49 3628/602381",
    "sg:postcode":"99310",
    "sg:province":"Th\u00fcringen",
    "wof:name":"Jutta R\u00f6hn Notarin",
    "wof:placetype":"venue"
},
  "geometry": {"coordinates":[10.9490871429,50.8335762024],"type":"Point"}
}