{
  "type": "Feature",
  "properties": {
    "iso:country":"DE",
    "sg:address":"Albrecht-D\u00fcrer-Str. 16",
    "sg:city":"N\u00fcrnberg",
    "sg:phone":"+49 4909/1122852",
    "sg:postcode":"90403",
    "sg:province":"Bayern",
    "wof:name":"Niena - Zinnfiguren Aus St. Petersburg",
    "wof:placetype":"venue"
},
  "geometry": {"coordinates":[11.074345,49.456627],"type":"Point"}
}