{
  "type": "Feature",
  "properties": {
    "iso:country":"DE",
    "sg:address":"Steinweg 6",
    "sg:city":"Neustadt",
    "sg:phone":"+49 36481/51245",
    "sg:postcode":"07806",
    "sg:province":"Th\u00fcringen",
    "wof:name":"Rosemarie Jahn",
    "wof:placetype":"venue"
},
  "geometry": {"coordinates":[9.982409,53.550983],"type":"Point"}
}