{
  "type": "Feature",
  "properties": {
    "iso:country":"DE",
    "sg:address":"Am R\u00f6hnsbusch 4",
    "sg:city":"Altenkrempe",
    "sg:phone":"+49 4564/1073",
    "sg:postcode":"23730",
    "sg:province":"Schleswig-Holstein",
    "wof:name":"Max Bonde",
    "wof:placetype":"venue"
},
  "geometry": {"coordinates":[10.831887,54.151199],"type":"Point"}
}