{
  "type": "Feature",
  "properties": {
    "iso:country":"DE",
    "sg:address":"Raiffeisenstr 3",
    "sg:city":"D\u00fcren",
    "sg:phone":"+49 6056/91900",
    "sg:postcode":"52353",
    "sg:province":"Nordrhein-Westfalen",
    "wof:name":"Wfg Wellpappen-freigericht Gmbh",
    "wof:placetype":"venue"
},
  "geometry": {"coordinates":[9.361702,50.266674],"type":"Point"}
}