{
  "type": "Feature",
  "properties": {
    "iso:country":"DE",
    "sg:address":"An der B 91",
    "sg:city":"Merseburg",
    "sg:postcode":"06217",
    "sg:province":"Sachsen-Anhalt",
    "wof:name":"Buchen-umweltservice Merseburg Verwaltungs Gmbh",
    "wof:placetype":"venue"
},
  "geometry": {"coordinates":[11.979041,51.350147],"type":"Point"}
}