{
  "type": "Feature",
  "properties": {
    "iso:country":"DE",
    "sg:address":"Im Obrock 85",
    "sg:city":"Kirchlengern",
    "sg:phone":"+49 5223/79815",
    "sg:postcode":"32278",
    "sg:province":"Nordrhein-Westfalen",
    "wof:name":"Lsk Lederer Sondermaschinenbau Kirchlengern Gmbh",
    "wof:placetype":"venue"
},
  "geometry": {"coordinates":[8.629176,52.199593],"type":"Point"}
}