{
  "type": "Feature",
  "properties": {
    "iso:country":"DE",
    "sg:address":"Hornauer Str. 49",
    "sg:city":"Kelkheim",
    "sg:phone":"+49 6195/65666",
    "sg:postcode":"65779",
    "sg:province":"Hessen",
    "wof:name":"Gundula Herr's Papierladen Gmbh",
    "wof:placetype":"venue"
},
  "geometry": {"coordinates":[8.4501771927,50.1426696777],"type":"Point"}
}