{
  "type": "Feature",
  "properties": {
    "iso:country":"DE",
    "sg:address":"Berliner Str. 20",
    "sg:city":"G\u00fctersloh",
    "sg:phone":"+49 5241/237988",
    "sg:postcode":"33330",
    "sg:province":"Nordrhein-Westfalen",
    "wof:name":"E-plus Shop",
    "wof:placetype":"venue"
},
  "geometry": {"coordinates":[8.3781995773,51.9057807922],"type":"Point"}
}