{
  "type": "Feature",
  "properties": {
    "iso:country":"DE",
    "sg:address":"Friedlandstr. 2",
    "sg:city":"Amberg",
    "sg:phone":"+49 9621/14081",
    "sg:postcode":"92224",
    "sg:province":"Bayern",
    "wof:name":"Caritas-altenheim",
    "wof:placetype":"venue"
},
  "geometry": {"coordinates":[11.885118,49.448662],"type":"Point"}
}