{
  "type": "Feature",
  "properties": {
    "iso:country":"DE",
    "sg:address":"Dorfstr. 6",
    "sg:city":"Windeby",
    "sg:phone":"+49 4351/45411",
    "sg:postcode":"24340",
    "sg:province":"Schleswig-Holstein",
    "wof:name":"Wolf-dietrich Zander",
    "wof:placetype":"venue"
},
  "geometry": {"coordinates":[9.772759,54.474888],"type":"Point"}
}