{
  "type": "Feature",
  "properties": {
    "iso:country":"DE",
    "sg:address":"Zum Obersten Hof 4-6",
    "sg:city":"Reichshof",
    "sg:phone":"+49 2296/722",
    "sg:postcode":"51580",
    "sg:province":"Nordrhein-Westfalen",
    "wof:name":"Mkv Metallbau Klein Gmbh",
    "wof:placetype":"venue"
},
  "geometry": {"coordinates":[7.631048,50.961586],"type":"Point"}
}