{
  "type": "Feature",
  "properties": {
    "iso:country":"DE",
    "sg:address":"Siegburger Str. 506",
    "sg:city":"K\u00f6ln",
    "sg:phone":"+49 221/836790",
    "sg:postcode":"51105",
    "sg:province":"Nordrhein-Westfalen",
    "wof:name":"Dieter Pellegrini",
    "wof:placetype":"venue"
},
  "geometry": {"coordinates":[6.9989237785,50.9126091003],"type":"Point"}
}