{
  "type": "Feature",
  "properties": {
    "iso:country":"DE",
    "sg:address":"Marktplatz 9",
    "sg:city":"Ochsenhausen",
    "sg:phone":"+49 7352/3223",
    "sg:postcode":"88416",
    "sg:province":"Baden-W\u00fcrttemberg",
    "wof:name":"Hotel Bohrturm",
    "wof:placetype":"venue"
},
  "geometry": {"coordinates":[9.9514808655,48.0720291138],"type":"Point"}
}