{
  "type": "Feature",
  "properties": {
    "iso:country":"DE",
    "sg:address":"Bahnstr. 44",
    "sg:city":"L\u00fcnen",
    "sg:phone":"+49 2306/40197",
    "sg:postcode":"44532",
    "sg:province":"Nordrhein-Westfalen",
    "wof:name":"Helmut Shcmidt Steinmetzbetrieb",
    "wof:placetype":"venue"
},
  "geometry": {"coordinates":[7.5243039131,51.5908889771],"type":"Point"}
}