{
  "type": "Feature",
  "properties": {
    "iso:country":"DE",
    "sg:address":"Hasenweiler 16",
    "sg:city":"Horgenzell",
    "sg:phone":"+49 7504/441",
    "sg:postcode":"88263",
    "sg:province":"Baden-W\u00fcrttemberg",
    "wof:name":"W. Hagg",
    "wof:placetype":"venue"
},
  "geometry": {"coordinates":[9.46311,47.832108],"type":"Point"}
}