{
  "type": "Feature",
  "properties": {
    "iso:country":"DE",
    "sg:address":"Hauptstr. 38",
    "sg:city":"Niefern-\u00d6schelbronn",
    "sg:phone":"+49 7233/4370",
    "sg:postcode":"75223",
    "sg:province":"Baden-W\u00fcrttemberg",
    "wof:name":"Eis-bistro",
    "wof:placetype":"venue"
},
  "geometry": {"coordinates":[8.789986,48.906593],"type":"Point"}
}