{
  "type": "Feature",
  "properties": {
    "iso:country":"DE",
    "sg:address":"Heidestr. 17",
    "sg:city":"Recklinghausen",
    "sg:postcode":"45659",
    "sg:province":"Nordrhein-Westfalen",
    "wof:name":"Kath. \u00f6ffentliche Bibliothek St. Gertrud",
    "wof:placetype":"venue"
},
  "geometry": {"coordinates":[7.2123,51.5919],"type":"Point"}
}