{
  "type": "Feature",
  "properties": {
    "iso:country":"DE",
    "sg:address":"Blaicher Str. 69 c",
    "sg:city":"Kulmbach",
    "sg:phone":"+49 9221/4949",
    "sg:postcode":"95326",
    "sg:province":"Bayern",
    "wof:name":"Roland G\u00f6tz",
    "wof:placetype":"venue"
},
  "geometry": {"coordinates":[11.4596767426,50.1161613464],"type":"Point"}
}