{
  "type": "Feature",
  "properties": {
    "iso:country":"DE",
    "sg:address":"Heerstr. 6",
    "sg:city":"Sulzbach-Laufen",
    "sg:phone":"+49 7976/205",
    "sg:postcode":"74429",
    "sg:province":"Baden-W\u00fcrttemberg",
    "wof:name":"Karl Bauer",
    "wof:placetype":"venue"
},
  "geometry": {"coordinates":[9.857202,48.94799],"type":"Point"}
}