{
  "type": "Feature",
  "properties": {
    "iso:country":"DE",
    "sg:address":"Hauptstr. 22",
    "sg:city":"Einhausen",
    "sg:phone":"+49 6251/51120",
    "sg:postcode":"64683",
    "sg:province":"Hessen",
    "wof:name":"Robert Rothermel",
    "wof:placetype":"venue"
},
  "geometry": {"coordinates":[8.5472784042,49.6739425659],"type":"Point"}
}