{
  "type": "Feature",
  "properties": {
    "iso:country":"DE",
    "sg:address":"Hermannstr. 6 - 8",
    "sg:city":"Wetzlar",
    "sg:phone":"+49 6441/51835",
    "sg:postcode":"35576",
    "sg:province":"Hessen",
    "wof:name":"Julius Csordas & Co. E. K.",
    "wof:placetype":"venue"
},
  "geometry": {"coordinates":[8.4823665619,50.5615730286],"type":"Point"}
}