{
  "type": "Feature",
  "properties": {
    "iso:country":"DE",
    "sg:address":"Am Schellberg 19",
    "sg:city":"Grevenbroich",
    "sg:phone":"+49 2182/825143",
    "sg:postcode":"41516",
    "sg:province":"Nordrhein-Westfalen",
    "wof:name":"P & M Maschinenschutzver- Kleidung Metallbau Gmbh",
    "wof:placetype":"venue"
},
  "geometry": {"coordinates":[6.6199851036,51.1346321106],"type":"Point"}
}