{
  "type": "Feature",
  "properties": {
    "iso:country":"DE",
    "sg:address":"Wildbader Str. 21",
    "sg:city":"Sindelfingen",
    "sg:phone":"+49 7031/382509",
    "sg:postcode":"71069",
    "sg:province":"Baden-W\u00fcrttemberg",
    "wof:name":"Walter Frohnmayer Rechtsanwalt",
    "wof:placetype":"venue"
},
  "geometry": {"coordinates":[8.9591264725,48.7151908875],"type":"Point"}
}