{
  "type": "Feature",
  "properties": {
    "iso:country":"DE",
    "sg:address":"Merzlicher Str. 8",
    "sg:city":"Konz",
    "sg:phone":"+49 6501/92960",
    "sg:postcode":"54329",
    "sg:province":"Rheinland-Pfalz",
    "wof:name":"Hotel-restaurant Schons Gmbh",
    "wof:placetype":"venue"
},
  "geometry": {"coordinates":[6.5961098671,49.7109909058],"type":"Point"}
}