{
  "type": "Feature",
  "properties": {
    "iso:country":"DE",
    "sg:address":"Schornbaumstr. 6",
    "sg:city":"Erlangen",
    "sg:phone":"+49 9131/33447",
    "sg:postcode":"91052",
    "sg:province":"Bayern",
    "wof:name":"Gunde Brand",
    "wof:placetype":"venue"
},
  "geometry": {"coordinates":[11.003953,49.57938],"type":"Point"}
}