{
  "type": "Feature",
  "properties": {
    "iso:country":"DE",
    "sg:address":"Jan-Joest-Str. 48",
    "sg:city":"Kalkar",
    "sg:phone":"+49 2824/2398",
    "sg:postcode":"47546",
    "sg:province":"Nordrhein-Westfalen",
    "wof:name":"B\u00fcltjes & Sohn Gmbh",
    "wof:placetype":"venue"
},
  "geometry": {"coordinates":[6.293585,51.73579],"type":"Point"}
}