{
  "type": "Feature",
  "properties": {
    "iso:country":"DE",
    "sg:address":"Hauptstra\u00dfe 18",
    "sg:city":"D\u00fcrrwangen",
    "sg:postcode":"91602",
    "sg:province":"Bayern",
    "wof:name":"St.-sebastian-apotheke",
    "wof:placetype":"venue"
},
  "geometry": {"coordinates":[10.3883152008,49.1100921631],"type":"Point"}
}