{
  "type": "Feature",
  "properties": {
    "iso:country":"DE",
    "sg:address":"August-Bebel-Allee 58",
    "sg:city":"Bremen",
    "sg:phone":"+49 421/462155",
    "sg:postcode":"28329",
    "sg:province":"Bremen",
    "wof:name":"Ohlsen",
    "wof:placetype":"venue"
},
  "geometry": {"coordinates":[8.879741,53.08601],"type":"Point"}
}