{
  "type": "Feature",
  "properties": {
    "iso:country":"DE",
    "sg:address":"Merxm\u00fchle 1",
    "sg:city":"Hohenwart",
    "sg:phone":"+49 8443/1008",
    "sg:postcode":"86558",
    "sg:province":"Bayern",
    "wof:name":"Alois Schmidt",
    "wof:placetype":"venue"
},
  "geometry": {"coordinates":[11.401689,48.595573],"type":"Point"}
}