{
  "type": "Feature",
  "properties": {
    "iso:country":"DE",
    "sg:address":"L\u00fclsfelder Weg 31",
    "sg:city":"Gerolzhofen",
    "sg:phone":"+49 9382/1380",
    "sg:postcode":"97447",
    "sg:province":"Bayern",
    "wof:name":"K. Roth Ingenieur",
    "wof:placetype":"venue"
},
  "geometry": {"coordinates":[10.3476343155,49.8974685669],"type":"Point"}
}