{
  "type": "Feature",
  "properties": {
    "iso:country":"DE",
    "sg:address":"Oberes Dorf",
    "sg:city":"Beidenfleth",
    "sg:phone":"+49 4829/259",
    "sg:postcode":"25573",
    "sg:province":"Schleswig-Holstein",
    "wof:name":"K. Rohde",
    "wof:placetype":"venue"
},
  "geometry": {"coordinates":[9.415092,53.878998],"type":"Point"}
}