{
  "type": "Feature",
  "properties": {
    "iso:country":"DE",
    "sg:address":"Am H\u00e4usel 171",
    "sg:city":"Pirmasens",
    "sg:postcode":"66953",
    "sg:province":"Rheinland-Pfalz",
    "wof:name":"Ksh Sanit\u00e4r-heizung Handel E. K.",
    "wof:placetype":"venue"
},
  "geometry": {"coordinates":[7.6277480125,49.2208786011],"type":"Point"}
}