{
  "type": "Feature",
  "properties": {
    "iso:country":"DE",
    "sg:address":"Zeltplatz Trassenheide 3",
    "sg:city":"Trassenheide",
    "sg:phone":"+49 38371/28196",
    "sg:postcode":"17449",
    "sg:province":"Mecklenburg-Vorpommern",
    "wof:name":"Feriensiedlung Zum Kraftwerker",
    "wof:placetype":"venue"
},
  "geometry": {"coordinates":[13.8349752426,54.1126365662],"type":"Point"}
}