{
  "type": "Feature",
  "properties": {
    "iso:country":"DE",
    "sg:address":"Weinstr. 21",
    "sg:city":"Oberderdingen",
    "sg:phone":"+49 7045/2558",
    "sg:postcode":"75038",
    "sg:province":"Baden-W\u00fcrttemberg",
    "wof:name":"Ernst K\u00f6gel",
    "wof:placetype":"venue"
},
  "geometry": {"coordinates":[8.808839,49.069004],"type":"Point"}
}