{
  "type": "Feature",
  "properties": {
    "iso:country":"DE",
    "sg:address":"Tersteegenstr. 29",
    "sg:city":"Moers",
    "sg:phone":"+49 2841/23453",
    "sg:postcode":"47441",
    "sg:province":"Nordrhein-Westfalen",
    "wof:name":"Versicherungsvermittlungs- Kontor Schneider Gmbh",
    "wof:placetype":"venue"
},
  "geometry": {"coordinates":[6.6355910301,51.4486236572],"type":"Point"}
}