{
  "type": "Feature",
  "properties": {
    "iso:country":"DE",
    "sg:address":"Feldstr. 21-23",
    "sg:city":"Wuppertal",
    "sg:phone":"+49 4920/2555774",
    "sg:postcode":"42275",
    "sg:province":"Nordrhein-Westfalen",
    "wof:name":"Neon Hoppe Gmbh Werbetechnik",
    "wof:placetype":"venue"
},
  "geometry": {"coordinates":[7.2097840309,51.277557373],"type":"Point"}
}