{
  "type": "Feature",
  "properties": {
    "iso:country":"DE",
    "sg:address":"Zerzabelshofer Hauptstr. 28",
    "sg:city":"N\u00fcrnberg",
    "sg:phone":"+49 911/407078",
    "sg:postcode":"90480",
    "sg:province":"Bayern",
    "wof:name":"Zabo-linde",
    "wof:placetype":"venue"
},
  "geometry": {"coordinates":[11.125091,49.443375],"type":"Point"}
}