{
  "type": "Feature",
  "properties": {
    "iso:country":"DE",
    "sg:address":"Schmiedestr. 5",
    "sg:city":"Rahden",
    "sg:phone":"+49 5776/494",
    "sg:postcode":"32369",
    "sg:province":"Nordrhein-Westfalen",
    "wof:name":"Wilhelm Reimers",
    "wof:placetype":"venue"
},
  "geometry": {"coordinates":[8.627346,52.509815],"type":"Point"}
}