{
  "type": "Feature",
  "properties": {
    "iso:country":"DE",
    "sg:city":"Borkum",
    "sg:phone":"+49 4921/89920",
    "sg:postcode":"26757",
    "sg:province":"Niedersachsen",
    "wof:name":"Habich & Goth Gmbh",
    "wof:placetype":"venue"
},
  "geometry": {"coordinates":[6.669821,53.588196],"type":"Point"}
}