{
  "type": "Feature",
  "properties": {
    "iso:country":"DE",
    "sg:address":"Bachstr. 18",
    "sg:city":"Geseke",
    "sg:phone":"+49 2942/1219",
    "sg:postcode":"59590",
    "sg:province":"Nordrhein-Westfalen",
    "wof:name":"Josef M\u00fcller",
    "wof:placetype":"venue"
},
  "geometry": {"coordinates":[8.51,51.640469],"type":"Point"}
}