{
  "type": "Feature",
  "properties": {
    "iso:country":"DE",
    "sg:address":"Goethestr. 23",
    "sg:city":"Dietenheim",
    "sg:phone":"+49 7347/2266",
    "sg:postcode":"89165",
    "sg:province":"Baden-W\u00fcrttemberg",
    "wof:name":"Alois H\u00f6gerle",
    "wof:placetype":"venue"
},
  "geometry": {"coordinates":[10.055768,48.247261],"type":"Point"}
}