{
  "type": "Feature",
  "properties": {
    "iso:country":"DE",
    "sg:address":"Flurweg 14",
    "sg:city":"Osthofen",
    "sg:phone":"+49 6242/4549",
    "sg:postcode":"67574",
    "sg:province":"Rheinland-Pfalz",
    "wof:name":"Umpack Gesellschaft F\u00fcr Konfektionierung Und Lagerung Mbh",
    "wof:placetype":"venue"
},
  "geometry": {"coordinates":[8.3281030655,49.7002677917],"type":"Point"}
}