{
  "type": "Feature",
  "properties": {
    "iso:country":"DE",
    "sg:address":"Berliner Str. 5a",
    "sg:city":"Berlin",
    "sg:phone":"+49 30/4339936",
    "sg:postcode":"13507",
    "sg:province":"Berlin",
    "wof:name":"Pa Bekleidung Ajzen Gmbh",
    "wof:placetype":"venue"
},
  "geometry": {"coordinates":[13.283993,52.588875],"type":"Point"}
}