{
  "type": "Feature",
  "properties": {
    "iso:country":"DE",
    "sg:address":"Quellenstr. 13",
    "sg:city":"Edertal",
    "sg:phone":"+49 5623/2087",
    "sg:postcode":"34549",
    "sg:province":"Hessen",
    "wof:name":"G\u00e4stehaus K. Albus",
    "wof:placetype":"venue"
},
  "geometry": {"coordinates":[9.0646705627,51.1408500671],"type":"Point"}
}