{
  "type": "Feature",
  "properties": {
    "iso:country":"DE",
    "sg:address":"Am Egelpfuhl 4",
    "sg:city":"Templin",
    "sg:postcode":"17268",
    "sg:province":"Brandenburg",
    "wof:name":"Doris D\u00f6hring",
    "wof:placetype":"venue"
},
  "geometry": {"coordinates":[13.505034,53.112762],"type":"Point"}
}