{
  "type": "Feature",
  "properties": {
    "iso:country":"DE",
    "sg:address":"Peter-Henlein-Str. 75",
    "sg:city":"N\u00fcrnberg",
    "sg:phone":"+49 911/443083",
    "sg:postcode":"90459",
    "sg:province":"Bayern",
    "wof:name":"Heimtierzentrale Inh. Margonna Mevissen",
    "wof:placetype":"venue"
},
  "geometry": {"coordinates":[11.080932,49.442444],"type":"Point"}
}