{
  "type": "Feature",
  "properties": {
    "iso:country":"DE",
    "sg:address":"Gertrudenstr. 4",
    "sg:city":"Wuppertal",
    "sg:phone":"+49 202/3702210",
    "sg:postcode":"42105",
    "sg:province":"Nordrhein-Westfalen",
    "wof:name":"Doris Baumann-frank Rechtsanw\u00e4ltin",
    "wof:placetype":"venue"
},
  "geometry": {"coordinates":[7.1365861893,51.2586326599],"type":"Point"}
}