{
  "type": "Feature",
  "properties": {
    "iso:country":"DE",
    "sg:address":"Langenbochumer Str. 455",
    "sg:city":"Herten",
    "sg:phone":"+49 209/35528",
    "sg:postcode":"45701",
    "sg:province":"Nordrhein-Westfalen",
    "wof:name":"Wilhelm Lensmann",
    "wof:placetype":"venue"
},
  "geometry": {"coordinates":[7.092286,51.601292],"type":"Point"}
}