{
  "type": "Feature",
  "properties": {
    "iso:country":"DE",
    "sg:address":"Hofackerstr. 8",
    "sg:city":"Augsburg",
    "sg:phone":"+49 821/813687",
    "sg:postcode":"86179",
    "sg:province":"Bayern",
    "wof:name":"Wilh. Leimer",
    "wof:placetype":"venue"
},
  "geometry": {"coordinates":[10.9071826935,48.3117179871],"type":"Point"}
}