{
  "type": "Feature",
  "properties": {
    "iso:country":"DE",
    "sg:address":"Friedrichstr. 8",
    "sg:city":"Kronberg",
    "sg:phone":"+49 69/737203",
    "sg:postcode":"61476",
    "sg:province":"Hessen",
    "wof:name":"Alexander Haltmeier Ingenieur",
    "wof:placetype":"venue"
},
  "geometry": {"coordinates":[8.5269651413,50.1820411682],"type":"Point"}
}