{
  "type": "Feature",
  "properties": {
    "iso:country":"DE",
    "sg:address":"Daimlerstra\u00dfe 10",
    "sg:city":"Nehren",
    "sg:phone":"+49 7473/24151",
    "sg:postcode":"72147",
    "sg:province":"Baden-W\u00fcrttemberg",
    "wof:name":"Hipp + Strassenburg Gmbh",
    "wof:placetype":"venue"
},
  "geometry": {"coordinates":[9.078291,48.433285],"type":"Point"}
}