{
  "type": "Feature",
  "properties": {
    "iso:country":"DE",
    "sg:address":"Friedrich-Ebert-Str.31",
    "sg:city":"Schwandorf",
    "sg:phone":"+49 9431/8466",
    "sg:postcode":"92421",
    "sg:province":"Bayern",
    "wof:name":"Dresdner Bank",
    "wof:placetype":"venue"
},
  "geometry": {"coordinates":[12.108588,49.327869],"type":"Point"}
}