{
  "type": "Feature",
  "properties": {
    "iso:country":"DE",
    "sg:address":"Grubstr. 1",
    "sg:city":"Gottmadingen",
    "sg:postcode":"78244",
    "sg:province":"Baden-W\u00fcrttemberg",
    "wof:name":"Roman Toth",
    "wof:placetype":"venue"
},
  "geometry": {"coordinates":[8.737583,47.738155],"type":"Point"}
}