{
  "type": "Feature",
  "properties": {
    "iso:country":"DE",
    "sg:address":"Blezinger Weg 4",
    "sg:city":"Crailsheim",
    "sg:postcode":"74564",
    "sg:province":"Baden-W\u00fcrttemberg",
    "wof:name":"Mt Maschinenteile Gmbh",
    "wof:placetype":"venue"
},
  "geometry": {"coordinates":[10.0779428482,49.1442146301],"type":"Point"}
}