{
  "type": "Feature",
  "properties": {
    "iso:country":"DE",
    "sg:address":"Franz-Schubert-Str. 10",
    "sg:city":"Dornhan",
    "sg:phone":"+49 7455/93930",
    "sg:postcode":"72175",
    "sg:province":"Baden-W\u00fcrttemberg",
    "wof:name":"Paul Herbstreuter Steuerberater",
    "wof:placetype":"venue"
},
  "geometry": {"coordinates":[8.5037765503,48.3470497131],"type":"Point"}
}