{
  "type": "Feature",
  "properties": {
    "iso:country":"DE",
    "sg:address":"Ochsenkamp 1",
    "sg:city":"Wetter",
    "sg:phone":"+49 2335/69823",
    "sg:postcode":"58300",
    "sg:province":"Nordrhein-Westfalen",
    "wof:name":"Anis Imbi\u00df-restaurant",
    "wof:placetype":"venue"
},
  "geometry": {"coordinates":[7.3798379898,51.3583068848],"type":"Point"}
}