{
  "type": "Feature",
  "properties": {
    "iso:country":"DE",
    "sg:address":"Burbacher Str. 161",
    "sg:city":"Bonn",
    "sg:phone":"+49 228/238223",
    "sg:postcode":"53129",
    "sg:province":"Nordrhein-Westfalen",
    "wof:name":"H.-p. Pesch",
    "wof:placetype":"venue"
},
  "geometry": {"coordinates":[7.109894,50.713737],"type":"Point"}
}