{
  "type": "Feature",
  "properties": {
    "iso:country":"DE",
    "sg:address":"Kirchstr. 41",
    "sg:city":"Ellwangen",
    "sg:phone":"+49 7965/800205",
    "sg:postcode":"73479",
    "sg:province":"Baden-W\u00fcrttemberg",
    "wof:name":"Anton Rief",
    "wof:placetype":"venue"
},
  "geometry": {"coordinates":[10.22342,48.939571],"type":"Point"}
}