{
  "type": "Feature",
  "properties": {
    "iso:country":"DE",
    "sg:address":"Obernhagen 2",
    "sg:city":"Hessisch Oldendorf",
    "sg:postcode":"31840",
    "sg:province":"Niedersachsen",
    "wof:name":"Wilh. Ossenkopp Maschinenbau Inh. Wilhelm Ossenkopp E. K.",
    "wof:placetype":"venue"
},
  "geometry": {"coordinates":[9.19358,52.172119],"type":"Point"}
}