{
  "type": "Feature",
  "properties": {
    "iso:country":"DE",
    "sg:address":"Hebbelstr. 23",
    "sg:city":"Lippstadt",
    "sg:phone":"+49 2941/657113",
    "sg:postcode":"59555",
    "sg:province":"Nordrhein-Westfalen",
    "wof:name":"Elmar L\u00f6ppenberg Und Friedhelm Schneider",
    "wof:placetype":"venue"
},
  "geometry": {"coordinates":[8.358710289,51.6836967468],"type":"Point"}
}