{
  "type": "Feature",
  "properties": {
    "iso:country":"DE",
    "sg:address":"Jakob-Weinheimer-Str. 21",
    "sg:city":"Langebr\u00fcck",
    "sg:phone":"+49 35201/893",
    "sg:postcode":"01465",
    "sg:province":"Sachsen",
    "wof:name":"Peter Ernstissold",
    "wof:placetype":"venue"
},
  "geometry": {"coordinates":[13.8359699249,51.1222991943],"type":"Point"}
}