{
  "type": "Feature",
  "properties": {
    "iso:country":"DE",
    "sg:address":"Geistkircher Hof 1",
    "sg:city":"St. Ingbert",
    "sg:phone":"+49 6894/51104",
    "sg:postcode":"66386",
    "sg:province":"Saarland",
    "wof:name":"Geistkircherhof",
    "wof:placetype":"venue"
},
  "geometry": {"coordinates":[7.1880130768,49.2767066956],"type":"Point"}
}