{
  "type": "Feature",
  "properties": {
    "iso:country":"DE",
    "sg:address":"Danziger Str. 20",
    "sg:city":"Hiddenhausen",
    "sg:phone":"+49 5223/8130",
    "sg:postcode":"32120",
    "sg:province":"Nordrhein-Westfalen",
    "wof:name":"J\u00fcrgen Kampschulte Ingenieur",
    "wof:placetype":"venue"
},
  "geometry": {"coordinates":[8.6360740662,52.1714553833],"type":"Point"}
}