{
  "type": "Feature",
  "properties": {
    "iso:country":"DE",
    "sg:address":"Schulstr. 9",
    "sg:city":"Wesseling",
    "sg:phone":"+49 2236/49672",
    "sg:postcode":"50389",
    "sg:province":"Nordrhein-Westfalen",
    "wof:name":"Maler Und Lackierer Meister",
    "wof:placetype":"venue"
},
  "geometry": {"coordinates":[6.970478,50.811398],"type":"Point"}
}