{
  "type": "Feature",
  "properties": {
    "iso:country":"DE",
    "sg:address":"Lohmehlenring 116",
    "sg:city":"Tuttlingen",
    "sg:phone":"+49 7461/3672",
    "sg:postcode":"78532",
    "sg:province":"Baden-W\u00fcrttemberg",
    "wof:name":"M. Boettler Chirug. Instrumente",
    "wof:placetype":"venue"
},
  "geometry": {"coordinates":[8.846897,47.978642],"type":"Point"}
}