{
  "type": "Feature",
  "properties": {
    "iso:country":"DE",
    "sg:address":"Hauptstr. 16",
    "sg:city":"M\u00fclheim",
    "sg:phone":"+49 6534/650",
    "sg:postcode":"54486",
    "sg:province":"Rheinland-Pfalz",
    "wof:name":"Schiller-pelzer",
    "wof:placetype":"venue"
},
  "geometry": {"coordinates":[7.0072751045,49.9115715027],"type":"Point"}
}