{
  "type": "Feature",
  "properties": {
    "iso:country":"DE",
    "sg:address":"Kohlhaufm\u00fchle 1",
    "sg:city":"Brannenburg",
    "sg:phone":"+49 8034/3387",
    "sg:postcode":"83098",
    "sg:province":"Bayern",
    "wof:name":"Josef Nagl",
    "wof:placetype":"venue"
},
  "geometry": {"coordinates":[12.0957689285,47.7256774902],"type":"Point"}
}