{
  "type": "Feature",
  "properties": {
    "iso:country":"DE",
    "sg:address":"Carl-Kerber-Str. 22",
    "sg:city":"B\u00fcchlberg",
    "sg:phone":"+49 8505/2069",
    "sg:postcode":"94124",
    "sg:province":"Bayern",
    "wof:name":"Alois Reichart",
    "wof:placetype":"venue"
},
  "geometry": {"coordinates":[13.51491,48.669521],"type":"Point"}
}