{
  "type": "Feature",
  "properties": {
    "iso:country":"DE",
    "sg:address":"Augsburger Str. 31/3",
    "sg:city":"F\u00fcssen",
    "sg:phone":"+49 8362/7623",
    "sg:postcode":"87629",
    "sg:province":"Bayern",
    "wof:name":"E. Neuber",
    "wof:placetype":"venue"
},
  "geometry": {"coordinates":[10.7043447495,47.576915741],"type":"Point"}
}