{
  "type": "Feature",
  "properties": {
    "iso:country":"DE",
    "sg:address":"Osnabr\u00fccker Str. 2",
    "sg:city":"Glandorf",
    "sg:phone":"+49 5426/3360",
    "sg:postcode":"49219",
    "sg:province":"Niedersachsen",
    "wof:name":"Kath. Pfarramt St. Johannes D. T\u00e4ufer",
    "wof:placetype":"venue"
},
  "geometry": {"coordinates":[8.0021657944,52.0819740295],"type":"Point"}
}