{
  "type": "Feature",
  "properties": {
    "iso:country":"DE",
    "sg:address":"Engberdingdamm 27",
    "sg:city":"Greven",
    "sg:phone":"+49 2575/614",
    "sg:postcode":"48268",
    "sg:province":"Nordrhein-Westfalen",
    "wof:name":"M. Focke",
    "wof:placetype":"venue"
},
  "geometry": {"coordinates":[7.578899,52.140705],"type":"Point"}
}