{
  "type": "Feature",
  "properties": {
    "iso:country":"DE",
    "sg:address":"Deutschherrenstr. 178",
    "sg:city":"Bonn",
    "sg:phone":"+49 228/344112",
    "sg:postcode":"53179",
    "sg:province":"Nordrhein-Westfalen",
    "wof:name":"W. Und H. Trimborn",
    "wof:placetype":"venue"
},
  "geometry": {"coordinates":[7.1697540283,50.6661605835],"type":"Point"}
}