{
  "type": "Feature",
  "properties": {
    "iso:country":"DE",
    "sg:address":"Jagdstr. 16",
    "sg:city":"Freising",
    "sg:phone":"+49 8161/980040",
    "sg:postcode":"85356",
    "sg:province":"Bayern",
    "wof:name":"Elektronik Fischer Gmbh",
    "wof:placetype":"venue"
},
  "geometry": {"coordinates":[11.770206,48.392326],"type":"Point"}
}