{
  "type": "Feature",
  "properties": {
    "iso:country":"DE",
    "sg:address":"Limpurger Platz",
    "sg:city":"Schw\u00e4bisch Hall",
    "sg:phone":"+49 791/2590",
    "sg:postcode":"74523",
    "sg:province":"Baden-W\u00fcrttemberg",
    "wof:name":"H\u00f6hencafe",
    "wof:placetype":"venue"
},
  "geometry": {"coordinates":[9.75138,49.115429],"type":"Point"}
}