{
  "type": "Feature",
  "properties": {
    "iso:country":"DE",
    "sg:address":"Zum Bruche 6",
    "sg:city":"Springe",
    "sg:phone":"+49 5044/98052",
    "sg:postcode":"31832",
    "sg:province":"Niedersachsen",
    "wof:name":"Manfred Hanelik",
    "wof:placetype":"venue"
},
  "geometry": {"coordinates":[9.6912078857,52.1506652832],"type":"Point"}
}