{
  "type": "Feature",
  "properties": {
    "iso:country":"DE",
    "sg:address":"Bahnhofstr.",
    "sg:city":"Wei\u00dfenberg",
    "sg:phone":"+49 35876/42293",
    "sg:postcode":"02627",
    "sg:province":"Sachsen",
    "wof:name":"Eckhard Kuhnen",
    "wof:placetype":"venue"
},
  "geometry": {"coordinates":[14.654031,51.193733],"type":"Point"}
}