{
  "type": "Feature",
  "properties": {
    "iso:country":"DE",
    "sg:address":"Willst\u00e4tterstr. 73",
    "sg:city":"N\u00fcrnberg",
    "sg:phone":"+49 911/967140",
    "sg:postcode":"90449",
    "sg:province":"Bayern",
    "wof:name":"Krauss Formenbau Und Kunststofftechnik Gmbh",
    "wof:placetype":"venue"
},
  "geometry": {"coordinates":[11.014193,49.425385],"type":"Point"}
}