{
  "type": "Feature",
  "properties": {
    "iso:country":"DE",
    "sg:address":"Seestr. 78a",
    "sg:city":"Seefeld",
    "sg:phone":"+49 8152/98440",
    "sg:postcode":"82229",
    "sg:province":"Bayern",
    "wof:name":"Strand Ausstellungs- Realisation Gmbh",
    "wof:placetype":"venue"
},
  "geometry": {"coordinates":[11.1856241226,48.0294876099],"type":"Point"}
}