{
  "type": "Feature",
  "properties": {
    "iso:country":"DE",
    "sg:address":"L\u00fcbecker Str. 11",
    "sg:city":"K\u00f6ln",
    "sg:phone":"+49 2234/497143",
    "sg:postcode":"50858",
    "sg:province":"Nordrhein-Westfalen",
    "wof:name":"Somit Gmbh",
    "wof:placetype":"venue"
},
  "geometry": {"coordinates":[6.835632,50.934742],"type":"Point"}
}