{
  "type": "Feature",
  "properties": {
    "iso:country":"DE",
    "sg:address":"Neue Str. 15",
    "sg:city":"Niepars",
    "sg:phone":"+49 38321/427",
    "sg:postcode":"18442",
    "sg:province":"Mecklenburg-Vorpommern",
    "wof:name":"Harald Roggow",
    "wof:placetype":"venue"
},
  "geometry": {"coordinates":[12.979525,54.224548],"type":"Point"}
}