{
  "type": "Feature",
  "properties": {
    "iso:country":"DE",
    "sg:address":"Schlo\u00dfweg 16",
    "sg:city":"Waal",
    "sg:phone":"+49 8246/346",
    "sg:postcode":"86875",
    "sg:province":"Bayern",
    "wof:name":"Sabine Wutzig-bohn Heilpraktikerin",
    "wof:placetype":"venue"
},
  "geometry": {"coordinates":[10.8029251099,47.9967269897],"type":"Point"}
}