{
  "type": "Feature",
  "properties": {
    "iso:country":"DE",
    "sg:address":"Dorfstr. 1",
    "sg:city":"St. Goar",
    "sg:postcode":"56329",
    "sg:province":"Rheinland-Pfalz",
    "wof:name":"Ha Ge Be-dienstleistungs Gmbh",
    "wof:placetype":"venue"
},
  "geometry": {"coordinates":[7.708672,50.146938],"type":"Point"}
}