{
  "type": "Feature",
  "properties": {
    "iso:country":"DE",
    "sg:address":"Soldnerstr. 13",
    "sg:city":"Mannheim",
    "sg:phone":"+49 4962/1873030",
    "sg:postcode":"68219",
    "sg:province":"Baden-W\u00fcrttemberg",
    "wof:name":"Kurier-botendienst Wilde Gmbh",
    "wof:placetype":"venue"
},
  "geometry": {"coordinates":[8.5181493759,49.450958252],"type":"Point"}
}