{
  "type": "Feature",
  "properties": {
    "iso:country":"DE",
    "sg:address":"Industriestr.",
    "sg:city":"Wilhelmshaven",
    "sg:postcode":"26389",
    "sg:province":"Niedersachsen",
    "wof:name":"Grove Worldwide Holdings Germany Gmbh",
    "wof:placetype":"venue"
},
  "geometry": {"coordinates":[8.084366,53.510143],"type":"Point"}
}