{
  "type": "Feature",
  "properties": {
    "iso:country":"DE",
    "sg:address":"Scherrweg 29",
    "sg:city":"Dortmund",
    "sg:phone":"+49 231/258379",
    "sg:postcode":"44309",
    "sg:province":"Nordrhein-Westfalen",
    "wof:name":"Karl-heinz Br\u00fcggemann Ingenieur",
    "wof:placetype":"venue"
},
  "geometry": {"coordinates":[7.5333909988,51.5249519348],"type":"Point"}
}