{
  "type": "Feature",
  "properties": {
    "iso:country":"DE",
    "sg:address":"K\u00f6nigsberger Str. 16",
    "sg:city":"B\u00f6blingen",
    "sg:phone":"+49 7031/221301",
    "sg:postcode":"71034",
    "sg:province":"Baden-W\u00fcrttemberg",
    "wof:name":"Gastst\u00e4tte Billardpalast",
    "wof:placetype":"venue"
},
  "geometry": {"coordinates":[9.0022830963,48.6823425293],"type":"Point"}
}