{
  "type": "Feature",
  "properties": {
    "iso:country":"DE",
    "sg:address":"Altenceller Schneede 39",
    "sg:city":"Celle",
    "sg:phone":"+49 5141/82492",
    "sg:postcode":"29221",
    "sg:province":"Niedersachsen",
    "wof:name":"Edeltraud Soukup Plakatanschlagsinstitut",
    "wof:placetype":"venue"
},
  "geometry": {"coordinates":[10.0976762772,52.6072387695],"type":"Point"}
}