{
  "type": "Feature",
  "properties": {
    "iso:country":"DE",
    "sg:address":"Kirchenstr. 10",
    "sg:city":"Buchholz",
    "sg:phone":"+49 4181/210860",
    "sg:postcode":"21244",
    "sg:province":"Niedersachsen",
    "wof:name":"Limberg Und Limberg Rechtsanw\u00e4lte",
    "wof:placetype":"venue"
},
  "geometry": {"coordinates":[9.882352829,53.3279151917],"type":"Point"}
}