{
  "type": "Feature",
  "properties": {
    "iso:country":"DE",
    "sg:address":"Wellie 68",
    "sg:city":"Steyerberg",
    "sg:phone":"+49 5023/1097",
    "sg:postcode":"31595",
    "sg:province":"Niedersachsen",
    "wof:name":"Ernst Dreeke",
    "wof:placetype":"venue"
},
  "geometry": {"coordinates":[9.080197,52.577717],"type":"Point"}
}