{
  "type": "Feature",
  "properties": {
    "iso:country":"DE",
    "sg:address":"Karlstr. 9",
    "sg:city":"Koserow",
    "sg:phone":"+49 38375/20458",
    "sg:postcode":"17459",
    "sg:province":"Mecklenburg-Vorpommern",
    "wof:name":"Kelchs Fisch- Und Steakrestaurant",
    "wof:placetype":"venue"
},
  "geometry": {"coordinates":[14.0000581741,54.0563011169],"type":"Point"}
}