{
  "type": "Feature",
  "properties": {
    "iso:country":"DE",
    "sg:address":"71364",
    "sg:city":"Winnenden",
    "sg:phone":"+49 7195/63942",
    "sg:postcode":"71364",
    "sg:province":"Baden-W\u00fcrttemberg",
    "wof:name":"Stadthalle",
    "wof:placetype":"venue"
},
  "geometry": {"coordinates":[9.412320137,48.8729705811],"type":"Point"}
}