{
  "type": "Feature",
  "properties": {
    "iso:country":"DE",
    "sg:address":"Im Weidetal 3",
    "sg:city":"Seulingen",
    "sg:phone":"+49 5507/7861",
    "sg:postcode":"37136",
    "sg:province":"Niedersachsen",
    "wof:name":"Sport-gasthaus Sula Quelle",
    "wof:placetype":"venue"
},
  "geometry": {"coordinates":[10.1656141281,51.5377388],"type":"Point"}
}