{
  "type": "Feature",
  "properties": {
    "iso:country":"DE",
    "sg:address":"Am Hirtsberg 9",
    "sg:city":"Eichenzell",
    "sg:phone":"+49 6656/1264",
    "sg:postcode":"36124",
    "sg:province":"Hessen",
    "wof:name":"Hugo Kress",
    "wof:placetype":"venue"
},
  "geometry": {"coordinates":[9.708571,50.434338],"type":"Point"}
}