{
  "type": "Feature",
  "properties": {
    "iso:country":"DE",
    "sg:address":"Nikolaistr. 12",
    "sg:city":"Schleiz",
    "sg:phone":"+49 3663/428435",
    "sg:postcode":"07907",
    "sg:province":"Th\u00fcringen",
    "wof:name":"Andreas M\u00fcller",
    "wof:placetype":"venue"
},
  "geometry": {"coordinates":[11.8071098328,50.5791015625],"type":"Point"}
}