{
  "type": "Feature",
  "properties": {
    "iso:country":"DE",
    "sg:address":"Am Golfplatz 3",
    "sg:city":"Timmendorfer Strand",
    "sg:phone":"+49 4503/5152",
    "sg:postcode":"23669",
    "sg:province":"Schleswig-Holstein",
    "wof:name":"Ostsee Golf-treuhand- Gesellschaft Mbh",
    "wof:placetype":"venue"
},
  "geometry": {"coordinates":[10.754526,53.999996],"type":"Point"}
}