{
  "type": "Feature",
  "properties": {
    "iso:country":"DE",
    "sg:address":"Schubertstr. 1",
    "sg:city":"Zwickau",
    "sg:phone":"+49 375/301428",
    "sg:postcode":"08058",
    "sg:province":"Sachsen",
    "wof:name":"Ecoair",
    "wof:placetype":"venue"
},
  "geometry": {"coordinates":[12.485187,50.747795],"type":"Point"}
}