{
  "type": "Feature",
  "properties": {
    "iso:country":"DE",
    "sg:address":"Morangiser Str. 2",
    "sg:city":"Plaidt",
    "sg:phone":"+49 2632/953550",
    "sg:postcode":"56637",
    "sg:province":"Rheinland-Pfalz",
    "wof:name":"Bau Lampa Gmbh",
    "wof:placetype":"venue"
},
  "geometry": {"coordinates":[7.386876,50.392937],"type":"Point"}
}