{
  "type": "Feature",
  "properties": {
    "iso:country":"DE",
    "sg:address":"Trierer Str. 50-52",
    "sg:city":"Mechernich",
    "sg:postcode":"53894",
    "sg:province":"Nordrhein-Westfalen",
    "wof:name":"Inmodio Gmbh",
    "wof:placetype":"venue"
},
  "geometry": {"coordinates":[6.670662,50.572384],"type":"Point"}
}