{
  "type": "Feature",
  "properties": {
    "iso:country":"DE",
    "sg:address":"Am Eichengrund",
    "sg:city":"Lahstedt",
    "sg:phone":"+49 5174/1295",
    "sg:postcode":"31246",
    "sg:province":"Niedersachsen",
    "wof:name":"Mtv Gro\u00df Lafferde",
    "wof:placetype":"venue"
},
  "geometry": {"coordinates":[10.2169456482,52.244594574],"type":"Point"}
}