{
  "type": "Feature",
  "properties": {
    "iso:country":"DE",
    "sg:address":"Gebersdorfer Str. 195",
    "sg:city":"N\u00fcrnberg",
    "sg:phone":"+49 911/674643",
    "sg:postcode":"90449",
    "sg:province":"Bayern",
    "wof:name":"Erhard Hahn",
    "wof:placetype":"venue"
},
  "geometry": {"coordinates":[11.003663063,49.4300231934],"type":"Point"}
}