{
  "type": "Feature",
  "properties": {
    "iso:country":"DE",
    "sg:address":"Deiringser Weg 67",
    "sg:city":"Soest",
    "sg:phone":"+49 2921/63800",
    "sg:postcode":"59494",
    "sg:province":"Nordrhein-Westfalen",
    "wof:name":"Harald Blankenhahn",
    "wof:placetype":"venue"
},
  "geometry": {"coordinates":[8.0945558548,51.5600204468],"type":"Point"}
}