{
  "type": "Feature",
  "properties": {
    "iso:country":"DE",
    "sg:address":"Robert-Bosch-Str. 9",
    "sg:city":"Giessen",
    "sg:phone":"+49 4964/165073",
    "sg:postcode":"35398",
    "sg:province":"Hessen",
    "wof:name":"Paul Laufer Gmbh & Co Kg",
    "wof:placetype":"venue"
},
  "geometry": {"coordinates":[8.646301,50.581886],"type":"Point"}
}