{
  "type": "Feature",
  "properties": {
    "iso:country":"DE",
    "sg:address":"Ulmenweg 5",
    "sg:city":"Idstein",
    "sg:phone":"+49 6126/2526",
    "sg:postcode":"65510",
    "sg:province":"Hessen",
    "wof:name":"Willi Merkelbach",
    "wof:placetype":"venue"
},
  "geometry": {"coordinates":[8.263997,50.209641],"type":"Point"}
}