{
  "type": "Feature",
  "properties": {
    "iso:country":"DE",
    "sg:address":"Schwarzenmoorstr. 123",
    "sg:city":"Herford",
    "sg:postcode":"32049",
    "sg:province":"Nordrhein-Westfalen",
    "wof:name":"Markant Markt",
    "wof:placetype":"venue"
},
  "geometry": {"coordinates":[8.704167366,52.1289749146],"type":"Point"}
}