{
  "type": "Feature",
  "properties": {
    "iso:country":"DE",
    "sg:address":"Adolph-Roemer-Str. 16",
    "sg:city":"Clausthal-Zellerfeld",
    "sg:phone":"+49 5323/1681",
    "sg:postcode":"38678",
    "sg:province":"Niedersachsen",
    "wof:name":"Ursula Glock-menger Rechtsanw\u00e4ltin Und Notarin",
    "wof:placetype":"venue"
},
  "geometry": {"coordinates":[10.3353071213,51.805934906],"type":"Point"}
}