{
  "type": "Feature",
  "properties": {
    "iso:country":"DE",
    "sg:address":"Johannisstr 66",
    "sg:city":"L\u00f6\u00dfnitz",
    "sg:phone":"+49 3771/55640",
    "sg:postcode":"08294",
    "sg:province":"Sachsen",
    "wof:name":"Fahrzeugzubeh\u00f6r Gmbh",
    "wof:placetype":"venue"
},
  "geometry": {"coordinates":[12.735783,50.627525],"type":"Point"}
}