{
  "type": "Feature",
  "properties": {
    "iso:country":"DE",
    "sg:address":"Bockumer Weg 280",
    "sg:city":"Hamm",
    "sg:phone":"+49 2381/64856",
    "sg:postcode":"59065",
    "sg:province":"Nordrhein-Westfalen",
    "wof:name":"Gastst\u00e4tte Heinz Hagedorn",
    "wof:placetype":"venue"
},
  "geometry": {"coordinates":[7.7784538269,51.689239502],"type":"Point"}
}