{
  "type": "Feature",
  "properties": {
    "iso:country":"DE",
    "sg:address":"Dorfstr. 51",
    "sg:city":"Bergen",
    "sg:phone":"+49 5054/484",
    "sg:postcode":"29303",
    "sg:province":"Niedersachsen",
    "wof:name":"Heinz Marwede",
    "wof:placetype":"venue"
},
  "geometry": {"coordinates":[10.059459,52.750389],"type":"Point"}
}