{
  "type": "Feature",
  "properties": {
    "iso:country":"DE",
    "sg:address":"Hauptstr. 42",
    "sg:city":"Ochsenfurt",
    "sg:postcode":"97199",
    "sg:province":"Bayern",
    "wof:name":"St\u00e4dtische Wohnungsges. Mbh",
    "wof:placetype":"venue"
},
  "geometry": {"coordinates":[10.0651903152,49.6642417908],"type":"Point"}
}