{
  "type": "Feature",
  "properties": {
    "iso:country":"DE",
    "sg:address":"Im Hagenkamp 4",
    "sg:city":"Emsdetten",
    "sg:phone":"+49 2572/6901",
    "sg:postcode":"48282",
    "sg:province":"Nordrhein-Westfalen",
    "wof:name":"Gastst\u00e4tte Schneider",
    "wof:placetype":"venue"
},
  "geometry": {"coordinates":[7.5365858078,52.1744689941],"type":"Point"}
}