{
  "type": "Feature",
  "properties": {
    "iso:country":"DE",
    "sg:address":"Osterholzer Dorfstr. 44",
    "sg:city":"Bremen",
    "sg:postcode":"28307",
    "sg:province":"Bremen",
    "wof:name":"Betty O. Vertriebs Gmbh",
    "wof:placetype":"venue"
},
  "geometry": {"coordinates":[8.9339065552,53.058013916],"type":"Point"}
}