{
  "type": "Feature",
  "properties": {
    "iso:country":"DE",
    "sg:address":"Jeinser Weg 18",
    "sg:city":"Sarstedt",
    "sg:phone":"+49 5066/2309",
    "sg:postcode":"31157",
    "sg:province":"Niedersachsen",
    "wof:name":"Helmut Winter Innenausbau",
    "wof:placetype":"venue"
},
  "geometry": {"coordinates":[9.832809,52.216457],"type":"Point"}
}