{
  "type": "Feature",
  "properties": {
    "iso:country":"DE",
    "sg:address":"Baumwaide 20",
    "sg:city":"Ilsfeld",
    "sg:phone":"+49 7062/90410",
    "sg:postcode":"74360",
    "sg:province":"Baden-W\u00fcrttemberg",
    "wof:name":"Klaus G\u00f6dicke Werkzeugmaschinen",
    "wof:placetype":"venue"
},
  "geometry": {"coordinates":[9.2819595337,49.0558509827],"type":"Point"}
}