{
  "type": "Feature",
  "properties": {
    "iso:country":"DE",
    "sg:address":"Birkenhof 54",
    "sg:city":"Flensburg",
    "sg:phone":"+49 461/311131",
    "sg:postcode":"24944",
    "sg:province":"Schleswig-Holstein",
    "wof:name":"Her-m\u00fc Inh. Jens Br\u00fcggen",
    "wof:placetype":"venue"
},
  "geometry": {"coordinates":[9.4792346954,54.8082199097],"type":"Point"}
}