{
  "type": "Feature",
  "properties": {
    "iso:country":"DE",
    "sg:address":"Liebfrauenstr. 1",
    "sg:city":"D\u00fcsseldorf",
    "sg:phone":"+49 211/761960",
    "sg:postcode":"40591",
    "sg:province":"Nordrhein-Westfalen",
    "wof:name":"Automaten Pinz",
    "wof:placetype":"venue"
},
  "geometry": {"coordinates":[6.8178358078,51.1889533997],"type":"Point"}
}