{
  "type": "Feature",
  "properties": {
    "iso:country":"DE",
    "sg:address":"Heideweg 5",
    "sg:city":"Ellwangen",
    "sg:phone":"+49 7961/7893",
    "sg:postcode":"73479",
    "sg:province":"Baden-W\u00fcrttemberg",
    "wof:name":"H. Lebschi Strick- Und Wirkwaren",
    "wof:placetype":"venue"
},
  "geometry": {"coordinates":[10.1066713333,48.9764518738],"type":"Point"}
}