{
  "type": "Feature",
  "properties": {
    "iso:country":"DE",
    "sg:address":"Hochstr. 70",
    "sg:city":"T\u00f6nisvorst",
    "sg:phone":"+49 2151/700895",
    "sg:postcode":"47918",
    "sg:province":"Nordrhein-Westfalen",
    "wof:name":"Victoria Versicherungen",
    "wof:placetype":"venue"
},
  "geometry": {"coordinates":[6.4914498329,51.3223800659],"type":"Point"}
}