{
  "type": "Feature",
  "properties": {
    "iso:country":"DE",
    "sg:address":"Humboldtstr. 7",
    "sg:city":"Radebeul",
    "sg:phone":"+49 351/839120",
    "sg:postcode":"01445",
    "sg:province":"Sachsen",
    "wof:name":"Juhrig Und Merta Ingenieurgesellschaft Gmbh",
    "wof:placetype":"venue"
},
  "geometry": {"coordinates":[13.6470756531,51.112071991],"type":"Point"}
}