{
  "type": "Feature",
  "properties": {
    "iso:country":"DE",
    "sg:address":"Watzmannstr. 4",
    "sg:city":"M\u00fcnchen",
    "sg:postcode":"81541",
    "sg:province":"Bayern",
    "wof:name":"Gewerbehaus Filmproduktion Gmbh",
    "wof:placetype":"venue"
},
  "geometry": {"coordinates":[11.5831718445,48.1178283691],"type":"Point"}
}