{
  "type": "Feature",
  "properties": {
    "iso:country":"DE",
    "sg:address":"Karlstr. 3",
    "sg:city":"Friedrichshafen",
    "sg:postcode":"88045",
    "sg:province":"Baden-W\u00fcrttemberg",
    "wof:name":"Helmut Erhard Augenoptikermeister E. K.",
    "wof:placetype":"venue"
},
  "geometry": {"coordinates":[9.4773836136,47.6517601013],"type":"Point"}
}