{
  "type": "Feature",
  "properties": {
    "iso:country":"DE",
    "sg:address":"Hahnstr. 72",
    "sg:city":"Frankfurt",
    "sg:postcode":"60528",
    "sg:province":"Hessen",
    "wof:name":"Masternet Gmbh",
    "wof:placetype":"venue"
},
  "geometry": {"coordinates":[8.63401,50.079098],"type":"Point"}
}