{
  "type": "Feature",
  "properties": {
    "iso:country":"DE",
    "sg:address":"Freudenst\u00e4dter Str. 42",
    "sg:city":"Bad Wildbad",
    "sg:phone":"+49 7055/1772",
    "sg:postcode":"75323",
    "sg:province":"Baden-W\u00fcrttemberg",
    "wof:name":"Gr\u00fcner Baum",
    "wof:placetype":"venue"
},
  "geometry": {"coordinates":[8.5232572556,48.6637420654],"type":"Point"}
}