{
  "type": "Feature",
  "properties": {
    "iso:country":"DE",
    "sg:address":"Im Feld 86",
    "sg:city":"Bocholt",
    "sg:phone":"+49 2871/8238",
    "sg:postcode":"46395",
    "sg:province":"Nordrhein-Westfalen",
    "wof:name":"Vollenbroich Textilien Gmbh",
    "wof:placetype":"venue"
},
  "geometry": {"coordinates":[6.633065,51.818466],"type":"Point"}
}