{
  "type": "Feature",
  "properties": {
    "iso:country":"DE",
    "sg:address":"Quellenring 23",
    "sg:city":"Bad Orb",
    "sg:phone":"+49 6052/3233",
    "sg:postcode":"63619",
    "sg:province":"Hessen",
    "wof:name":"Foto-sonntag",
    "wof:placetype":"venue"
},
  "geometry": {"coordinates":[9.3495340347,50.224571228],"type":"Point"}
}