{
  "type": "Feature",
  "properties": {
    "iso:country":"DE",
    "sg:address":"Holder\u00e4ckerstr. 13",
    "sg:city":"Stuttgart",
    "sg:phone":"+49 711/8872376",
    "sg:postcode":"70499",
    "sg:province":"Baden-W\u00fcrttemberg",
    "wof:name":"Karl Godel & S\u00f6hne Gmbh & Co.",
    "wof:placetype":"venue"
},
  "geometry": {"coordinates":[9.102094,48.822914],"type":"Point"}
}