{
  "type": "Feature",
  "properties": {
    "iso:country":"DE",
    "sg:address":"Im Leingarten 45",
    "sg:city":"Bad Oeynhausen",
    "sg:phone":"+49 5731/22368",
    "sg:postcode":"32549",
    "sg:province":"Nordrhein-Westfalen",
    "wof:name":"Werner Flaig Verwaltungs- Und Beteiligungs-gmbh",
    "wof:placetype":"venue"
},
  "geometry": {"coordinates":[8.788567,52.217697],"type":"Point"}
}