{
  "type": "Feature",
  "properties": {
    "iso:country":"DE",
    "sg:address":"Marktplatz 1",
    "sg:city":"Rott",
    "sg:phone":"+49 8039/1267",
    "sg:postcode":"83543",
    "sg:province":"Bayern",
    "wof:name":"Modehaus Schaber",
    "wof:placetype":"venue"
},
  "geometry": {"coordinates":[12.128738,47.981846],"type":"Point"}
}