{
  "type": "Feature",
  "properties": {
    "iso:country":"DE",
    "sg:address":"Radergasse 3",
    "sg:city":"Kirn",
    "sg:phone":"+49 6752/2345",
    "sg:postcode":"55606",
    "sg:province":"Rheinland-Pfalz",
    "wof:name":"Kuhn Und Dermann Architekten",
    "wof:placetype":"venue"
},
  "geometry": {"coordinates":[7.458705,49.786045],"type":"Point"}
}