{
  "type": "Feature",
  "properties": {
    "iso:country":"DE",
    "sg:address":"Karl-Marx-Str. 37",
    "sg:city":"Langendorf",
    "sg:phone":"+49 3443/232386",
    "sg:postcode":"06667",
    "sg:province":"Sachsen-Anhalt",
    "wof:name":"Lange & Zippe",
    "wof:placetype":"venue"
},
  "geometry": {"coordinates":[11.9648418427,51.1807441711],"type":"Point"}
}