{
  "type": "Feature",
  "properties": {
    "iso:country":"DE",
    "sg:address":"Rurtalstr. 60",
    "sg:city":"Heinsberg",
    "sg:phone":"+49 2453/2389",
    "sg:postcode":"52525",
    "sg:province":"Nordrhein-Westfalen",
    "wof:name":"Gerhard Bongartz",
    "wof:placetype":"venue"
},
  "geometry": {"coordinates":[6.1738901138,51.0407905579],"type":"Point"}
}