{
  "type": "Feature",
  "properties": {
    "iso:country":"DE",
    "sg:address":"Rappenfeldstr. 7",
    "sg:city":"Monheim",
    "sg:postcode":"86653",
    "sg:province":"Bayern",
    "wof:name":"Didago Gmbh",
    "wof:placetype":"venue"
},
  "geometry": {"coordinates":[10.8365097046,48.8448753357],"type":"Point"}
}