{
  "type": "Feature",
  "properties": {
    "iso:country":"DE",
    "sg:address":"Hegaustr. 12",
    "sg:city":"Orsingen-Nenzingen",
    "sg:phone":"+49 7774/7780",
    "sg:postcode":"78359",
    "sg:province":"Baden-W\u00fcrttemberg",
    "wof:name":"O. Kamenzin",
    "wof:placetype":"venue"
},
  "geometry": {"coordinates":[8.932634,47.833443],"type":"Point"}
}