{
  "type": "Feature",
  "properties": {
    "iso:country":"DE",
    "sg:address":"Weserstr. 4-6",
    "sg:city":"Hessisch Oldendorf",
    "sg:phone":"+49 5152/2043",
    "sg:postcode":"31840",
    "sg:province":"Niedersachsen",
    "wof:name":"Hans P\u00f6rtner Eisen Und R\u00f6hren",
    "wof:placetype":"venue"
},
  "geometry": {"coordinates":[9.241617,52.169315],"type":"Point"}
}