{
  "type": "Feature",
  "properties": {
    "iso:country":"DE",
    "sg:address":"Dr\u00f6\u00dfiger Str. 23",
    "sg:city":"Finsterwalde",
    "sg:postcode":"03238",
    "sg:province":"Brandenburg",
    "wof:name":"Integral Gmbh",
    "wof:placetype":"venue"
},
  "geometry": {"coordinates":[13.7110328674,51.6113395691],"type":"Point"}
}