{
  "type": "Feature",
  "properties": {
    "iso:country":"DE",
    "sg:address":"Hahler Str. 248",
    "sg:city":"Minden",
    "sg:phone":"+49 4957/129564",
    "sg:postcode":"32427",
    "sg:province":"Nordrhein-Westfalen",
    "wof:name":"Mantsch Medizintechnik Gmbh",
    "wof:placetype":"venue"
},
  "geometry": {"coordinates":[8.8722896576,52.2993202209],"type":"Point"}
}