{
  "type": "Feature",
  "properties": {
    "iso:country":"DE",
    "sg:address":"Drosselweg 14",
    "sg:city":"Balve",
    "sg:phone":"+49 2375/5685",
    "sg:postcode":"58802",
    "sg:province":"Nordrhein-Westfalen",
    "wof:name":"Krdmusic",
    "wof:placetype":"venue"
},
  "geometry": {"coordinates":[7.8656082153,51.3222045898],"type":"Point"}
}