{
  "type": "Feature",
  "properties": {
    "iso:country":"DE",
    "sg:address":"Kaiser-Wilhelm-Str. 7",
    "sg:city":"Starnberg",
    "sg:phone":"+49 8151/12239",
    "sg:postcode":"82319",
    "sg:province":"Bayern",
    "wof:name":"K\u00e4the Reimann Krankengymnastin",
    "wof:placetype":"venue"
},
  "geometry": {"coordinates":[11.345369,47.99892],"type":"Point"}
}