{
  "type": "Feature",
  "properties": {
    "iso:country":"DE",
    "sg:address":"Karlstr. 21",
    "sg:city":"Rostock",
    "sg:phone":"+49 381/4908860",
    "sg:postcode":"18055",
    "sg:province":"Mecklenburg-Vorpommern",
    "wof:name":"Andrasch & Partner Gmbh",
    "wof:placetype":"venue"
},
  "geometry": {"coordinates":[12.128093,54.082615],"type":"Point"}
}