{
  "type": "Feature",
  "properties": {
    "iso:country":"DE",
    "sg:address":"Siedlung 13",
    "sg:city":"Seebergen",
    "sg:phone":"+49 36256/20593",
    "sg:postcode":"99869",
    "sg:province":"Th\u00fcringen",
    "wof:name":"J. Baumann",
    "wof:placetype":"venue"
},
  "geometry": {"coordinates":[10.7901554108,50.9270744324],"type":"Point"}
}