{
  "type": "Feature",
  "properties": {
    "iso:country":"DE",
    "sg:address":"Dingdener Str. 85",
    "sg:city":"Bocholt",
    "sg:phone":"+49 2871/14250",
    "sg:postcode":"46395",
    "sg:province":"Nordrhein-Westfalen",
    "wof:name":"Antje Gerke",
    "wof:placetype":"venue"
},
  "geometry": {"coordinates":[6.6141791344,51.8209877014],"type":"Point"}
}