{
  "type": "Feature",
  "properties": {
    "iso:country":"DE",
    "sg:address":"Eichendorffstr. 47",
    "sg:city":"Gammertingen",
    "sg:phone":"+49 7574/1323",
    "sg:postcode":"72501",
    "sg:province":"Baden-W\u00fcrttemberg",
    "wof:name":"Lothar Wasel Rechtsanwalt",
    "wof:placetype":"venue"
},
  "geometry": {"coordinates":[9.228348732,48.2487487793],"type":"Point"}
}