{
  "type": "Feature",
  "properties": {
    "iso:country":"DE",
    "sg:address":"Gorbitz-Center",
    "sg:city":"Dresden",
    "sg:phone":"+49 351/4111716",
    "sg:postcode":"01169",
    "sg:province":"Sachsen",
    "wof:name":"Orthop\u00e4die Rehatechnik Dresden Gmbh",
    "wof:placetype":"venue"
},
  "geometry": {"coordinates":[13.6700296402,51.0389900208],"type":"Point"}
}