{
  "type": "Feature",
  "properties": {
    "iso:country":"DE",
    "sg:address":"Stammelestr. 1a",
    "sg:city":"Pei\u00dfenberg",
    "sg:phone":"+49 8803/60598",
    "sg:postcode":"82380",
    "sg:province":"Bayern",
    "wof:name":"Montana Flugsport Gmbh",
    "wof:placetype":"venue"
},
  "geometry": {"coordinates":[11.0699596405,47.8038673401],"type":"Point"}
}