{
  "type": "Feature",
  "properties": {
    "iso:country":"DE",
    "sg:address":"Magdeburger Ring 7",
    "sg:city":"Rotenburg",
    "sg:phone":"+49 4261/63700",
    "sg:postcode":"27356",
    "sg:province":"Niedersachsen",
    "wof:name":"W. Lehmann",
    "wof:placetype":"venue"
},
  "geometry": {"coordinates":[9.427179,53.116875],"type":"Point"}
}