{
  "type": "Feature",
  "properties": {
    "iso:country":"DE",
    "sg:address":"Franz-Schubert-Str. 2",
    "sg:city":"Niederwerrn",
    "sg:postcode":"97464",
    "sg:province":"Bayern",
    "wof:name":"Pfaff Gmbh",
    "wof:placetype":"venue"
},
  "geometry": {"coordinates":[10.1871576309,50.0617752075],"type":"Point"}
}