{
  "type": "Feature",
  "properties": {
    "iso:country":"DE",
    "sg:address":"Bergiusstr. 9",
    "sg:city":"Dormagen",
    "sg:phone":"+49 2133/6966",
    "sg:postcode":"41540",
    "sg:province":"Nordrhein-Westfalen",
    "wof:name":"Mario Scire Pasta Fresca San Gmbh",
    "wof:placetype":"venue"
},
  "geometry": {"coordinates":[6.827849865,51.0593070984],"type":"Point"}
}