{
  "type": "Feature",
  "properties": {
    "iso:country":"DE",
    "sg:address":"Haffstr. 10 c",
    "sg:city":"Dargen",
    "sg:phone":"+49 38376/20421",
    "sg:postcode":"17419",
    "sg:province":"Mecklenburg-Vorpommern",
    "wof:name":"Gasthaus Inh. N. Butz",
    "wof:placetype":"venue"
},
  "geometry": {"coordinates":[14.0644378662,53.8856010437],"type":"Point"}
}