{
  "type": "Feature",
  "properties": {
    "iso:country":"DE",
    "sg:address":"Karl-Liebknecht-Str. 92",
    "sg:city":"Leipzig",
    "sg:phone":"+49 341/3915268",
    "sg:postcode":"04275",
    "sg:province":"Sachsen",
    "wof:name":"K. Falana",
    "wof:placetype":"venue"
},
  "geometry": {"coordinates":[12.373143,51.318512],"type":"Point"}
}