{
  "type": "Feature",
  "properties": {
    "iso:country":"DE",
    "sg:address":"Karl-Marx-Siedlung 9",
    "sg:city":"Annah\u00fctte",
    "sg:phone":"+49 35754/1653",
    "sg:postcode":"01994",
    "sg:province":"Brandenburg",
    "wof:name":"Karl-heinz Jahn",
    "wof:placetype":"venue"
},
  "geometry": {"coordinates":[13.872643,51.560444],"type":"Point"}
}