{
  "type": "Feature",
  "properties": {
    "iso:country":"DE",
    "sg:address":"Kirchgasse 3",
    "sg:city":"Wachau",
    "sg:postcode":"01454",
    "sg:province":"Sachsen",
    "wof:name":"Gemeindeschwesterstation Seifersdorf",
    "wof:placetype":"venue"
},
  "geometry": {"coordinates":[13.879882,51.159657],"type":"Point"}
}