{
  "type": "Feature",
  "properties": {
    "iso:country":"DE",
    "sg:address":"Birkenstr. 7",
    "sg:city":"Ratingen",
    "sg:phone":"+49 2102/893316",
    "sg:postcode":"40885",
    "sg:province":"Nordrhein-Westfalen",
    "wof:name":"Schreinerei Schl\u00fcter & Kleinbeck Gmbh",
    "wof:placetype":"venue"
},
  "geometry": {"coordinates":[6.822407,51.33408],"type":"Point"}
}