{
  "type": "Feature",
  "properties": {
    "iso:country":"DE",
    "sg:address":"L\u00fcbbecker Str. 6 a",
    "sg:city":"Minden",
    "sg:phone":"+49 571/57970",
    "sg:postcode":"32429",
    "sg:province":"Nordrhein-Westfalen",
    "wof:name":"Grill-pavillon",
    "wof:placetype":"venue"
},
  "geometry": {"coordinates":[8.9015836716,52.2772102356],"type":"Point"}
}