{
  "type": "Feature",
  "properties": {
    "iso:country":"DE",
    "sg:address":"Frieth\u00f6fer Kamp 4a",
    "sg:city":"Billerbeck",
    "sg:phone":"+49 2543/7071",
    "sg:postcode":"48727",
    "sg:province":"Nordrhein-Westfalen",
    "wof:name":"Hubert Leuters Gmbh & Co. Kg",
    "wof:placetype":"venue"
},
  "geometry": {"coordinates":[7.2824268341,51.9689064026],"type":"Point"}
}