{
  "type": "Feature",
  "properties": {
    "iso:country":"DE",
    "sg:address":"Gymnasiumstr. 30",
    "sg:city":"Winnweiler",
    "sg:phone":"+49 6302/3003",
    "sg:postcode":"67722",
    "sg:province":"Rheinland-Pfalz",
    "wof:name":"G\u00fcnther Wilding Heiz\u00f6l-handlung",
    "wof:placetype":"venue"
},
  "geometry": {"coordinates":[7.8477458954,49.5667724609],"type":"Point"}
}