{
  "type": "Feature",
  "properties": {
    "iso:country":"DE",
    "sg:address":"Nordecker Weg 16",
    "sg:city":"Ebsdorfergrund",
    "sg:phone":"+49 6424/923073",
    "sg:postcode":"35085",
    "sg:province":"Hessen",
    "wof:name":"K. Wagner",
    "wof:placetype":"venue"
},
  "geometry": {"coordinates":[8.855572,50.724766],"type":"Point"}
}