{
  "type": "Feature",
  "properties": {
    "iso:country":"DE",
    "sg:address":"Dekan-Karl-Platz 1",
    "sg:city":"Mittenwald",
    "sg:phone":"+49 8823/4669",
    "sg:postcode":"82481",
    "sg:province":"Bayern",
    "wof:name":"Zur H\u00f6lle",
    "wof:placetype":"venue"
},
  "geometry": {"coordinates":[11.260589,47.43972],"type":"Point"}
}