{
  "type": "Feature",
  "properties": {
    "iso:country":"DE",
    "sg:address":"Sudeweg 53",
    "sg:city":"Bielefeld",
    "sg:phone":"+49 5205/4725",
    "sg:postcode":"33689",
    "sg:province":"Nordrhein-Westfalen",
    "wof:name":"K. Kirchhoff",
    "wof:placetype":"venue"
},
  "geometry": {"coordinates":[8.6033411026,51.9539222717],"type":"Point"}
}