{
  "type": "Feature",
  "properties": {
    "iso:country":"DE",
    "sg:address":"Breite Str. 36",
    "sg:city":"Ilsede",
    "sg:phone":"+49 5171/53903",
    "sg:postcode":"31241",
    "sg:province":"Niedersachsen",
    "wof:name":"Ludwig Pl\u00fcnnecke",
    "wof:placetype":"venue"
},
  "geometry": {"coordinates":[10.218065,52.264091],"type":"Point"}
}