{
  "type": "Feature",
  "properties": {
    "iso:country":"DE",
    "sg:address":"Kreuzstr. 34",
    "sg:city":"Bielefeld",
    "sg:phone":"+49 4971/7118670",
    "sg:postcode":"33602",
    "sg:province":"Nordrhein-Westfalen",
    "wof:name":"Prodigital Softwaresysteme Gmbh",
    "wof:placetype":"venue"
},
  "geometry": {"coordinates":[9.753074646,48.7882766724],"type":"Point"}
}