{
  "type": "Feature",
  "properties": {
    "iso:country":"DE",
    "sg:address":"Schmiedestr. 33",
    "sg:city":"Sprockh\u00f6vel",
    "sg:phone":"+49 202/452766",
    "sg:postcode":"45549",
    "sg:province":"Nordrhein-Westfalen",
    "wof:name":"Dirk Pohli",
    "wof:placetype":"venue"
},
  "geometry": {"coordinates":[7.250748,51.315578],"type":"Point"}
}