{
  "type": "Feature",
  "properties": {
    "iso:country":"DE",
    "sg:address":"Im Redder 76",
    "sg:city":"L\u00fcneburg",
    "sg:phone":"+49 4131/682362",
    "sg:postcode":"21339",
    "sg:province":"Niedersachsen",
    "wof:name":"Wir Personalsysteme Gmbh",
    "wof:placetype":"venue"
},
  "geometry": {"coordinates":[10.384327,53.272087],"type":"Point"}
}