{
  "type": "Feature",
  "properties": {
    "iso:country":"DE",
    "sg:address":"Gerlinger Str. 2",
    "sg:city":"Bannewitz",
    "sg:phone":"+49 351/4030145",
    "sg:postcode":"01728",
    "sg:province":"Sachsen",
    "wof:name":"Dietmar Putzger",
    "wof:placetype":"venue"
},
  "geometry": {"coordinates":[13.7201366425,50.9957008362],"type":"Point"}
}