{
  "type": "Feature",
  "properties": {
    "iso:country":"DE",
    "sg:address":"Industriestr. 8-14",
    "sg:city":"Oer-Erkenschwick",
    "sg:phone":"+49 2368/610",
    "sg:postcode":"45739",
    "sg:province":"Nordrhein-Westfalen",
    "wof:name":"Barfu\u00df Produktions- Und Betriebs Gmbh",
    "wof:placetype":"venue"
},
  "geometry": {"coordinates":[7.274505,51.635914],"type":"Point"}
}