{
  "type": "Feature",
  "properties": {
    "iso:country":"DE",
    "sg:address":"Vereinsstr. 26",
    "sg:city":"Brandenburg",
    "sg:phone":"+49 3381/227310",
    "sg:postcode":"14770",
    "sg:province":"Brandenburg",
    "wof:name":"A. Weidner",
    "wof:placetype":"venue"
},
  "geometry": {"coordinates":[12.543634,52.410206],"type":"Point"}
}