{
  "type": "Feature",
  "properties": {
    "iso:country":"DE",
    "sg:address":"Werdohler Str. 118",
    "sg:city":"L\u00fcdenscheid",
    "sg:phone":"+49 2351/85160",
    "sg:postcode":"58511",
    "sg:province":"Nordrhein-Westfalen",
    "wof:name":"Willy Born Nachf.",
    "wof:placetype":"venue"
},
  "geometry": {"coordinates":[7.641725,51.223076],"type":"Point"}
}