{
  "type": "Feature",
  "properties": {
    "iso:country":"DE",
    "sg:address":"Paul-Singer-Str. 23",
    "sg:city":"Bremen",
    "sg:phone":"+49 421/465225",
    "sg:postcode":"28329",
    "sg:province":"Bremen",
    "wof:name":"Erhard Apfelbaum Kunstmaler",
    "wof:placetype":"venue"
},
  "geometry": {"coordinates":[8.893403,53.086063],"type":"Point"}
}