{
  "type": "Feature",
  "properties": {
    "iso:country":"DE",
    "sg:address":"Johannisstr. 3",
    "sg:city":"Neum\u00fcnster",
    "sg:phone":"+49 4321/43056",
    "sg:postcode":"24534",
    "sg:province":"Schleswig-Holstein",
    "wof:name":"Harald Kring Und A. Wittig Steuerberater",
    "wof:placetype":"venue"
},
  "geometry": {"coordinates":[9.9814291,54.0766067505],"type":"Point"}
}