{
  "type": "Feature",
  "properties": {
    "iso:country":"DE",
    "sg:address":"Rudolf-Diesel-Str 43a",
    "sg:city":"Walldorf",
    "sg:phone":"+49 6227/4352",
    "sg:postcode":"69190",
    "sg:province":"Baden-W\u00fcrttemberg",
    "wof:name":"Bewi Lackentfernungs Gmbh",
    "wof:placetype":"venue"
},
  "geometry": {"coordinates":[8.646281,49.290707],"type":"Point"}
}