{
  "type": "Feature",
  "properties": {
    "iso:country":"DE",
    "sg:address":"Hiller Str. 25",
    "sg:city":"Hille",
    "sg:phone":"+49 5703/2257",
    "sg:postcode":"32479",
    "sg:province":"Nordrhein-Westfalen",
    "wof:name":"Haake & Sohn Gmbh & Co. Kg",
    "wof:placetype":"venue"
},
  "geometry": {"coordinates":[8.7377624512,52.3076095581],"type":"Point"}
}