{
  "type": "Feature",
  "properties": {
    "iso:country":"DE",
    "sg:address":"Gartenstr. 26",
    "sg:city":"Oberstdorf",
    "sg:phone":"+49 8322/5197",
    "sg:postcode":"87561",
    "sg:province":"Bayern",
    "wof:name":"Sanaconsult Treuhand Steuerberatungsges. Mbh",
    "wof:placetype":"venue"
},
  "geometry": {"coordinates":[10.283416748,47.4098892212],"type":"Point"}
}