{
  "type": "Feature",
  "properties": {
    "iso:country":"DE",
    "sg:address":"Angermunder Str. 36",
    "sg:city":"D\u00fcsseldorf",
    "sg:phone":"+49 211/74415",
    "sg:postcode":"40489",
    "sg:province":"Nordrhein-Westfalen",
    "wof:name":"Reiseservice Angermund",
    "wof:placetype":"venue"
},
  "geometry": {"coordinates":[6.7711901665,51.3235588074],"type":"Point"}
}