{
  "type": "Feature",
  "properties": {
    "iso:country":"DE",
    "sg:address":"Gruberstr. 1",
    "sg:city":"Gro\u00dfhabersdorf",
    "sg:phone":"+49 9105/377",
    "sg:postcode":"90613",
    "sg:province":"Bayern",
    "wof:name":"W. Schneider Ingenieur",
    "wof:placetype":"venue"
},
  "geometry": {"coordinates":[10.7860174179,49.4003486633],"type":"Point"}
}