{
  "type": "Feature",
  "properties": {
    "iso:country":"DE",
    "sg:address":"Am Rothbuck 4",
    "sg:city":"Rednitzhembach",
    "sg:phone":"+49 9122/78560",
    "sg:postcode":"91126",
    "sg:province":"Bayern",
    "wof:name":"Smg Sommer-montage- Gruppen Gmbh",
    "wof:placetype":"venue"
},
  "geometry": {"coordinates":[11.05695,49.309807],"type":"Point"}
}