{
  "type": "Feature",
  "properties": {
    "iso:country":"DE",
    "sg:address":"Herbrechtinger Str. 12",
    "sg:city":"Herbrechtingen",
    "sg:phone":"+49 7324/7171",
    "sg:postcode":"89542",
    "sg:province":"Baden-W\u00fcrttemberg",
    "wof:name":"Fritz Heizmann",
    "wof:placetype":"venue"
},
  "geometry": {"coordinates":[10.150245,48.631264],"type":"Point"}
}