{
  "type": "Feature",
  "properties": {
    "iso:country":"DE",
    "sg:address":"Mergelackerstr. 8",
    "sg:city":"Karlsruhe",
    "sg:phone":"+49 721/9415960",
    "sg:postcode":"76228",
    "sg:province":"Baden-W\u00fcrttemberg",
    "wof:name":"Hans Klenert",
    "wof:placetype":"venue"
},
  "geometry": {"coordinates":[8.4515142441,48.9760398865],"type":"Point"}
}