{
  "type": "Feature",
  "properties": {
    "iso:country":"DE",
    "sg:address":"Riedgasse 7",
    "sg:city":"Bad Waldsee",
    "sg:phone":"+49 7524/5821",
    "sg:postcode":"88339",
    "sg:province":"Baden-W\u00fcrttemberg",
    "wof:name":"G\u00fcnter Sauter",
    "wof:placetype":"venue"
},
  "geometry": {"coordinates":[9.7368373871,47.9227638245],"type":"Point"}
}