{
  "type": "Feature",
  "properties": {
    "iso:country":"DE",
    "sg:address":"Bahnhofstr. 60",
    "sg:city":"Freiberg",
    "sg:phone":"+49 3731/213570",
    "sg:postcode":"09599",
    "sg:province":"Sachsen",
    "wof:name":"Hesa Freiberg",
    "wof:placetype":"venue"
},
  "geometry": {"coordinates":[13.3440570831,50.9108047485],"type":"Point"}
}