{
  "type": "Feature",
  "properties": {
    "iso:country":"DE",
    "sg:address":"Weimarstr. 25",
    "sg:city":"Stuttgart",
    "sg:phone":"+49 711/66770",
    "sg:postcode":"70176",
    "sg:province":"Baden-W\u00fcrttemberg",
    "wof:name":"Landsiedlung Baden- W\u00fcrttemberg Gmbh",
    "wof:placetype":"venue"
},
  "geometry": {"coordinates":[9.1664419174,48.7758560181],"type":"Point"}
}