{
  "type": "Feature",
  "properties": {
    "iso:country":"DE",
    "sg:address":"Seedammweg 58",
    "sg:city":"Bad Homburg",
    "sg:phone":"+49 6172/41129",
    "sg:postcode":"61352",
    "sg:province":"Hessen",
    "wof:name":"Dr. Hans-j\u00fcrgen Banhardt Rechtsanwalt",
    "wof:placetype":"venue"
},
  "geometry": {"coordinates":[8.6385879517,50.228767395],"type":"Point"}
}