{
  "type": "Feature",
  "properties": {
    "iso:country":"DE",
    "sg:address":"Hauptstr. 23",
    "sg:city":"Gro\u00dfheubach",
    "sg:phone":"+49 9371/66594",
    "sg:postcode":"63920",
    "sg:province":"Bayern",
    "wof:name":"Christof Lebold",
    "wof:placetype":"venue"
},
  "geometry": {"coordinates":[9.2222719193,49.726852417],"type":"Point"}
}