{
  "type": "Feature",
  "properties": {
    "iso:country":"DE",
    "sg:address":"Uhlbergstr. 19",
    "sg:city":"Filderstadt",
    "sg:phone":"+49 711/773097",
    "sg:postcode":"70794",
    "sg:province":"Baden-W\u00fcrttemberg",
    "wof:name":"Chinarestaurant Dai Trung",
    "wof:placetype":"venue"
},
  "geometry": {"coordinates":[9.1959133148,48.6554641724],"type":"Point"}
}