{
  "type": "Feature",
  "properties": {
    "iso:country":"DE",
    "sg:address":"Brockenblick 5",
    "sg:city":"Sorge",
    "sg:phone":"+49 39457/3150",
    "sg:postcode":"38875",
    "sg:province":"Sachsen-Anhalt",
    "wof:name":"Detlef Tronnier",
    "wof:placetype":"venue"
},
  "geometry": {"coordinates":[10.7010345459,51.691822052],"type":"Point"}
}