{
  "type": "Feature",
  "properties": {
    "iso:country":"DE",
    "sg:address":"Bahnhofstr. 28",
    "sg:city":"Borsdorf",
    "sg:phone":"+49 34291/86589",
    "sg:postcode":"04451",
    "sg:province":"Sachsen",
    "wof:name":"Dieter Sauer",
    "wof:placetype":"venue"
},
  "geometry": {"coordinates":[12.5438766479,51.3468399048],"type":"Point"}
}