{
  "type": "Feature",
  "properties": {
    "iso:country":"DE",
    "sg:address":"Alt Saale 28",
    "sg:city":"Kirchhasel",
    "sg:phone":"+49 3672/43720",
    "sg:postcode":"07407",
    "sg:province":"Th\u00fcringen",
    "wof:name":"Leo",
    "wof:placetype":"venue"
},
  "geometry": {"coordinates":[11.388765,50.726673],"type":"Point"}
}