{
  "type": "Feature",
  "properties": {
    "iso:country":"DE",
    "sg:address":"Hirtscheider Str. 12",
    "sg:city":"Nistertal",
    "sg:phone":"+49 2661/98600",
    "sg:postcode":"57647",
    "sg:province":"Rheinland-Pfalz",
    "wof:name":"Autohaus Gerbrand Gmbh",
    "wof:placetype":"venue"
},
  "geometry": {"coordinates":[7.8967161179,50.6320762634],"type":"Point"}
}