{
  "type": "Feature",
  "properties": {
    "iso:country":"DE",
    "sg:address":"Engersche Str. 89",
    "sg:city":"Bielefeld",
    "sg:phone":"+49 521/81903",
    "sg:postcode":"33611",
    "sg:province":"Nordrhein-Westfalen",
    "wof:name":"Horst Greiner Inh. Georg Knopp E. K.",
    "wof:placetype":"venue"
},
  "geometry": {"coordinates":[8.5506010056,52.050617218],"type":"Point"}
}