{
  "type": "Feature",
  "properties": {
    "iso:country":"DE",
    "sg:address":"Hochstr. 96-100",
    "sg:city":"Krefeld",
    "sg:phone":"+49 2151/85630",
    "sg:postcode":"47798",
    "sg:province":"Nordrhein-Westfalen",
    "wof:name":"Greve Gmbh",
    "wof:placetype":"venue"
},
  "geometry": {"coordinates":[6.562484,51.331982],"type":"Point"}
}