{
  "type": "Feature",
  "properties": {
    "iso:country":"DE",
    "sg:address":"Kirchplatz 3",
    "sg:city":"Prem",
    "sg:phone":"+49 8862/7679",
    "sg:postcode":"86984",
    "sg:province":"Bayern",
    "wof:name":"Gottfried Und Helga Gro\u00df",
    "wof:placetype":"venue"
},
  "geometry": {"coordinates":[10.8029928207,47.6777992249],"type":"Point"}
}