{
  "type": "Feature",
  "properties": {
    "iso:country":"DE",
    "sg:address":"Waldstr. 7 a",
    "sg:city":"Gro\u00df-Gerau",
    "sg:phone":"+49 6152/83914",
    "sg:postcode":"64521",
    "sg:province":"Hessen",
    "wof:name":"K. Merz Bauschlosserei",
    "wof:placetype":"venue"
},
  "geometry": {"coordinates":[8.483699,49.927059],"type":"Point"}
}