{
  "type": "Feature",
  "properties": {
    "iso:country":"DE",
    "sg:address":"Trautenauer Str. 50",
    "sg:city":"W\u00fcrzburg",
    "sg:phone":"+49 931/72242",
    "sg:postcode":"97074",
    "sg:province":"Bayern",
    "wof:name":"Hans Ellmer Architekt",
    "wof:placetype":"venue"
},
  "geometry": {"coordinates":[9.955488,49.781425],"type":"Point"}
}