{
  "type": "Feature",
  "properties": {
    "iso:country":"DE",
    "sg:address":"M\u00fchlenwallstr. 35 a",
    "sg:city":"M\u00f6nchengladbach",
    "sg:phone":"+49 2161/570664",
    "sg:postcode":"41179",
    "sg:province":"Nordrhein-Westfalen",
    "wof:name":"Ulrike M\u00fcller Krankengymnastin",
    "wof:placetype":"venue"
},
  "geometry": {"coordinates":[6.359893,51.147797],"type":"Point"}
}