{
  "type": "Feature",
  "properties": {
    "iso:country":"DE",
    "sg:address":"Tonndorfer Hauptstr. 78",
    "sg:city":"Hamburg",
    "sg:phone":"+49 40/662275",
    "sg:postcode":"22045",
    "sg:province":"Hamburg",
    "wof:name":"Peter Warmuth",
    "wof:placetype":"venue"
},
  "geometry": {"coordinates":[10.124692,53.585896],"type":"Point"}
}