{
  "type": "Feature",
  "properties": {
    "iso:country":"DE",
    "sg:address":"Hansastr 2",
    "sg:city":"Ibbenb\u00fcren",
    "sg:phone":"+49 5451/969630",
    "sg:postcode":"49477",
    "sg:province":"Nordrhein-Westfalen",
    "wof:name":"Lampe Fliesen Gmbh",
    "wof:placetype":"venue"
},
  "geometry": {"coordinates":[7.7409191132,52.2740631104],"type":"Point"}
}