{
  "type": "Feature",
  "properties": {
    "iso:country":"DE",
    "sg:address":"In der Delle 27",
    "sg:city":"Hennef",
    "sg:postcode":"53773",
    "sg:province":"Nordrhein-Westfalen",
    "wof:name":"Behindertenwerkstatt",
    "wof:placetype":"venue"
},
  "geometry": {"coordinates":[7.359354,50.733322],"type":"Point"}
}