{
  "type": "Feature",
  "properties": {
    "iso:country":"DE",
    "sg:address":"Moordiek 51",
    "sg:city":"M\u00f6nkeberg",
    "sg:phone":"+49 431/23510",
    "sg:postcode":"24248",
    "sg:province":"Schleswig-Holstein",
    "wof:name":"K. B. Siebenrok Kunstmaler",
    "wof:placetype":"venue"
},
  "geometry": {"coordinates":[10.20861,54.34621],"type":"Point"}
}