{
  "type": "Feature",
  "properties": {
    "iso:country":"DE",
    "sg:address":"Gr\u00fcnw\u00e4lderstr. 1",
    "sg:city":"Freiburg",
    "sg:phone":"+49 761/22552",
    "sg:postcode":"79098",
    "sg:province":"Baden-W\u00fcrttemberg",
    "wof:name":"Restaurant Gro\u00dfer Meyerhof",
    "wof:placetype":"venue"
},
  "geometry": {"coordinates":[7.8496479988,47.9943733215],"type":"Point"}
}