{
  "type": "Feature",
  "properties": {
    "iso:country":"DE",
    "sg:address":"Finkenstieg 16",
    "sg:city":"Uelzen",
    "sg:phone":"+49 581/3897987",
    "sg:postcode":"29525",
    "sg:province":"Niedersachsen",
    "wof:name":"Helga Maria Iwohn E. Kfr.",
    "wof:placetype":"venue"
},
  "geometry": {"coordinates":[10.533819,52.967518],"type":"Point"}
}