{
  "type": "Feature",
  "properties": {
    "iso:country":"DE",
    "sg:address":"Hohenrodaer Str. 21 Krensitz",
    "sg:city":"Krostitz",
    "sg:postcode":"04509",
    "sg:province":"Sachsen",
    "wof:name":"H\u00fcbner Malerbetrieb Gmbh",
    "wof:placetype":"venue"
},
  "geometry": {"coordinates":[12.353431,51.51115],"type":"Point"}
}