{
  "type": "Feature",
  "properties": {
    "iso:country":"DE",
    "sg:address":"Karl-Liebknecht-Str. 209",
    "sg:city":"Glienicke",
    "sg:phone":"+49 33056/77341",
    "sg:postcode":"16548",
    "sg:province":"Brandenburg",
    "wof:name":"Birkenw\u00e4ldchen",
    "wof:placetype":"venue"
},
  "geometry": {"coordinates":[13.3131217957,52.6306152344],"type":"Point"}
}