{
  "type": "Feature",
  "properties": {
    "iso:country":"DE",
    "sg:address":"Karcherstr. 15",
    "sg:city":"Saarbr\u00fccken",
    "sg:phone":"+49 681/31411",
    "sg:postcode":"66111",
    "sg:province":"Saarland",
    "wof:name":"Vollwertrestaurant La Carotte",
    "wof:placetype":"venue"
},
  "geometry": {"coordinates":[6.9948859215,49.2392463684],"type":"Point"}
}