{
  "type": "Feature",
  "properties": {
    "iso:country":"DE",
    "sg:address":"Birresborner Str. 14",
    "sg:city":"M\u00fcrlenbach",
    "sg:phone":"+49 6594/1576",
    "sg:postcode":"54570",
    "sg:province":"Rheinland-Pfalz",
    "wof:name":"Hans-joachim Gr\u00f6hsges",
    "wof:placetype":"venue"
},
  "geometry": {"coordinates":[6.603607,50.153034],"type":"Point"}
}