{
  "type": "Feature",
  "properties": {
    "iso:country":"DE",
    "sg:address":"Liebknechtstr. 48",
    "sg:city":"Magdeburg",
    "sg:phone":"+49 391/5619480",
    "sg:postcode":"39108",
    "sg:province":"Sachsen-Anhalt",
    "wof:name":"G. Frontzek Immobilienmakler",
    "wof:placetype":"venue"
},
  "geometry": {"coordinates":[11.6092233658,52.1237297058],"type":"Point"}
}