{
  "type": "Feature",
  "properties": {
    "iso:country":"DE",
    "sg:address":"Hauptstr. 201",
    "sg:city":"Gro\u00dfhartmannsdorf",
    "sg:phone":"+49 37329/319",
    "sg:postcode":"09618",
    "sg:province":"Sachsen",
    "wof:name":"Werner Lebsuch",
    "wof:placetype":"venue"
},
  "geometry": {"coordinates":[13.321868,50.803082],"type":"Point"}
}