{
  "type": "Feature",
  "properties": {
    "iso:country":"DE",
    "sg:address":"Auengarten 6",
    "sg:city":"Hilgert",
    "sg:phone":"+49 2624/3947",
    "sg:postcode":"56206",
    "sg:province":"Rheinland-Pfalz",
    "wof:name":"Horst Bartels",
    "wof:placetype":"venue"
},
  "geometry": {"coordinates":[7.691522,50.455006],"type":"Point"}
}