{
  "type": "Feature",
  "properties": {
    "iso:country":"DE",
    "sg:address":"Springstr. 3",
    "sg:city":"Oberkirch",
    "sg:phone":"+49 7802/3174",
    "sg:postcode":"77704",
    "sg:province":"Baden-W\u00fcrttemberg",
    "wof:name":"A. Wiegert",
    "wof:placetype":"venue"
},
  "geometry": {"coordinates":[8.0646190643,48.5540542603],"type":"Point"}
}