{
  "type": "Feature",
  "properties": {
    "iso:country":"DE",
    "sg:address":"Hauptstr. 43",
    "sg:city":"Weichering",
    "sg:phone":"+49 8450/8853",
    "sg:postcode":"86706",
    "sg:province":"Bayern",
    "wof:name":"Rita Schmid",
    "wof:placetype":"venue"
},
  "geometry": {"coordinates":[11.3489637375,48.7022705078],"type":"Point"}
}