{
  "type": "Feature",
  "properties": {
    "iso:country":"DE",
    "sg:address":"L\u00e4ngenau 32",
    "sg:city":"Selb",
    "sg:phone":"+49 9287/4047",
    "sg:postcode":"95100",
    "sg:province":"Bayern",
    "wof:name":"Heinz Schwarzmeier",
    "wof:placetype":"venue"
},
  "geometry": {"coordinates":[12.1768102646,50.1745109558],"type":"Point"}
}