{
  "type": "Feature",
  "properties": {
    "iso:country":"DE",
    "sg:address":"K\u00f6tnerstr. 10",
    "sg:city":"Northeim",
    "sg:phone":"+49 5551/52081",
    "sg:postcode":"37154",
    "sg:province":"Niedersachsen",
    "wof:name":"Tischlerei Hellmi\u00df Gmbh",
    "wof:placetype":"venue"
},
  "geometry": {"coordinates":[9.931538,51.750931],"type":"Point"}
}