{
  "type": "Feature",
  "properties": {
    "iso:country":"DE",
    "sg:address":"Schwarze Breite",
    "sg:city":"Kaufungen",
    "sg:phone":"+49 561/511960",
    "sg:postcode":"34260",
    "sg:province":"Hessen",
    "wof:name":"Herkules Transportbeton Gmbh & Co. Kg",
    "wof:placetype":"venue"
},
  "geometry": {"coordinates":[9.5722417831,51.2850990295],"type":"Point"}
}