{
  "type": "Feature",
  "properties": {
    "iso:country":"DE",
    "sg:address":"Hauptstr. 40",
    "sg:city":"Merxheim",
    "sg:phone":"+49 6754/217",
    "sg:postcode":"55627",
    "sg:province":"Rheinland-Pfalz",
    "wof:name":"Peter Sk\u00e4r",
    "wof:placetype":"venue"
},
  "geometry": {"coordinates":[7.561296,49.794708],"type":"Point"}
}