{
  "type": "Feature",
  "properties": {
    "iso:country":"DE",
    "sg:address":"Herwarthstr. 81",
    "sg:city":"Essen",
    "sg:phone":"+49 201/2806888",
    "sg:postcode":"45138",
    "sg:province":"Nordrhein-Westfalen",
    "wof:name":"Grafit Werbeagentur Gmbh",
    "wof:placetype":"venue"
},
  "geometry": {"coordinates":[7.033958,51.446655],"type":"Point"}
}