{
  "type": "Feature",
  "properties": {
    "iso:country":"DE",
    "sg:address":"Sch\u00fctzenbaum 22",
    "sg:city":"K\u00f6nigheim",
    "sg:phone":"+49 9340/362",
    "sg:postcode":"97953",
    "sg:province":"Baden-W\u00fcrttemberg",
    "wof:name":"Ludwig Leimbach",
    "wof:placetype":"venue"
},
  "geometry": {"coordinates":[9.589057,49.591351],"type":"Point"}
}