{
  "type": "Feature",
  "properties": {
    "iso:country":"DE",
    "sg:address":"Hermannstra\u00dfe 2",
    "sg:city":"Hildesheim",
    "sg:phone":"+49 5121",
    "sg:postcode":"31137",
    "sg:province":"Niedersachsen",
    "wof:name":"Technische Software F\u00fcr Den Maschinenbau",
    "wof:placetype":"venue"
},
  "geometry": {"coordinates":[9.945515,52.162872],"type":"Point"}
}