{
  "type": "Feature",
  "properties": {
    "iso:country":"DE",
    "sg:address":"Neugablonzer Str. 5",
    "sg:city":"Kaufbeuren",
    "sg:phone":"+49 8341/74048",
    "sg:postcode":"87600",
    "sg:province":"Bayern",
    "wof:name":"Wirth & Cie. Beteiligungsgesellschaft Mbh",
    "wof:placetype":"venue"
},
  "geometry": {"coordinates":[10.6245231628,47.8821411133],"type":"Point"}
}