{
  "type": "Feature",
  "properties": {
    "iso:country":"DE",
    "sg:address":"K\u00f6lner Str. 186",
    "sg:city":"Neunkirchen",
    "sg:phone":"+49 2735/2517",
    "sg:postcode":"57290",
    "sg:province":"Nordrhein-Westfalen",
    "wof:name":"Double Six",
    "wof:placetype":"venue"
},
  "geometry": {"coordinates":[8.0014381409,50.7899894714],"type":"Point"}
}