{
  "type": "Feature",
  "properties": {
    "iso:country":"DE",
    "sg:address":"Industriestr.1",
    "sg:city":"Biedenkopf",
    "sg:phone":"+49 6461/5131",
    "sg:postcode":"35216",
    "sg:province":"Hessen",
    "wof:name":"Rossbach Gmbh",
    "wof:placetype":"venue"
},
  "geometry": {"coordinates":[8.5371246338,50.9038925171],"type":"Point"}
}