{
  "type": "Feature",
  "properties": {
    "iso:country":"DE",
    "sg:address":"Obere Bahnhofstr. 12",
    "sg:city":"Oberstdorf",
    "sg:phone":"+49 8322/2446",
    "sg:postcode":"87561",
    "sg:province":"Bayern",
    "wof:name":"Fremdenheim Josef Rief",
    "wof:placetype":"venue"
},
  "geometry": {"coordinates":[10.2791566849,47.4106903076],"type":"Point"}
}