{
  "type": "Feature",
  "properties": {
    "iso:country":"DE",
    "sg:address":"Buscher Str. 66",
    "sg:city":"Duisburg",
    "sg:phone":"+49 203/767920",
    "sg:postcode":"47269",
    "sg:province":"Nordrhein-Westfalen",
    "wof:name":"Augenoptik Hans Von Buttlar",
    "wof:placetype":"venue"
},
  "geometry": {"coordinates":[6.7708559036,51.3625831604],"type":"Point"}
}