{
  "type": "Feature",
  "properties": {
    "iso:country":"DE",
    "sg:address":"B\u00e4ckerstr. 3-5",
    "sg:city":"L\u00fcbeck",
    "sg:phone":"+49 451/790201",
    "sg:postcode":"23564",
    "sg:province":"Schleswig-Holstein",
    "wof:name":"Ev.-luth. Kirche In L\u00fcbeck Bibliothek",
    "wof:placetype":"venue"
},
  "geometry": {"coordinates":[10.6943664551,53.8593597412],"type":"Point"}
}