{
  "type": "Feature",
  "properties": {
    "iso:country":"DE",
    "sg:address":"Dammstr. 4 c",
    "sg:city":"Baiersdorf",
    "sg:phone":"+49 9133/4934",
    "sg:postcode":"91083",
    "sg:province":"Bayern",
    "wof:name":"Doris Ludwig Anlageberaterin",
    "wof:placetype":"venue"
},
  "geometry": {"coordinates":[11.0263118744,49.6552658081],"type":"Point"}
}