{
  "type": "Feature",
  "properties": {
    "iso:country":"DE",
    "sg:address":"Hanauer Str. 20",
    "sg:city":"W\u00f6llstadt",
    "sg:phone":"+49 6034/2344",
    "sg:postcode":"61206",
    "sg:province":"Hessen",
    "wof:name":"Hans Feuerbach",
    "wof:placetype":"venue"
},
  "geometry": {"coordinates":[8.7515859604,50.2971954346],"type":"Point"}
}