{
  "type": "Feature",
  "properties": {
    "iso:country":"DE",
    "sg:address":"Schulstr. 12",
    "sg:city":"Nabburg",
    "sg:phone":"+49 9433/8282",
    "sg:postcode":"92507",
    "sg:province":"Bayern",
    "wof:name":"Tsn Tennis- Und Squashpark Nabburg Gmbh",
    "wof:placetype":"venue"
},
  "geometry": {"coordinates":[12.1802463531,49.4517974854],"type":"Point"}
}