{
  "type": "Feature",
  "properties": {
    "iso:country":"DE",
    "sg:address":"Kieferstr. 25",
    "sg:city":"Dortmund",
    "sg:phone":"+49 231/773870",
    "sg:postcode":"44225",
    "sg:province":"Nordrhein-Westfalen",
    "wof:name":"Florida-gym Fitness-center Gmbh",
    "wof:placetype":"venue"
},
  "geometry": {"coordinates":[7.4325208664,51.4721984863],"type":"Point"}
}