{
  "type": "Feature",
  "properties": {
    "iso:country":"DE",
    "sg:address":"Chemnitzer Str 38a",
    "sg:city":"Hartmannsdorf",
    "sg:phone":"+49 3722/73160",
    "sg:postcode":"09232",
    "sg:province":"Sachsen",
    "wof:name":"Bonifer & Co Speditions-gmbh",
    "wof:placetype":"venue"
},
  "geometry": {"coordinates":[12.820022583,50.8795280457],"type":"Point"}
}