{
  "type": "Feature",
  "properties": {
    "iso:country":"DE",
    "sg:address":"Lindenstr. 5",
    "sg:city":"Aiglsbach",
    "sg:phone":"+49 8753/336",
    "sg:postcode":"84089",
    "sg:province":"Bayern",
    "wof:name":"Georg Friedl",
    "wof:placetype":"venue"
},
  "geometry": {"coordinates":[11.710468,48.692364],"type":"Point"}
}