{
  "type": "Feature",
  "properties": {
    "iso:country":"DE",
    "sg:address":"Rathausstr. 4",
    "sg:city":"Kirchseeon",
    "sg:phone":"+49 8091/9664",
    "sg:postcode":"85614",
    "sg:province":"Bayern",
    "wof:name":"Dr. Med. G\u00fcnter Wantke Arzt F\u00fcr Allgemeinmedizin",
    "wof:placetype":"venue"
},
  "geometry": {"coordinates":[11.8866224289,48.0746307373],"type":"Point"}
}