{
  "type": "Feature",
  "properties": {
    "iso:country":"DE",
    "sg:address":"Heisinger Str. 24",
    "sg:city":"Essen",
    "sg:phone":"+49 201/441468",
    "sg:postcode":"45134",
    "sg:province":"Nordrhein-Westfalen",
    "wof:name":"Pelzatelier H\u00f6lscher",
    "wof:placetype":"venue"
},
  "geometry": {"coordinates":[7.024545,51.417515],"type":"Point"}
}