{
  "type": "Feature",
  "properties": {
    "iso:country":"DE",
    "sg:address":"Sch\u00fctzenstr. 15",
    "sg:city":"Schlangen",
    "sg:phone":"+49 5252/82251",
    "sg:postcode":"33189",
    "sg:province":"Nordrhein-Westfalen",
    "wof:name":"H\u00f6ttinger Tennis Gmbh",
    "wof:placetype":"venue"
},
  "geometry": {"coordinates":[8.832294,51.803139],"type":"Point"}
}