{
  "type": "Feature",
  "properties": {
    "iso:country":"DE",
    "sg:address":"Rondenbarg 2",
    "sg:city":"Hamburg",
    "sg:phone":"+49 40/8533230",
    "sg:postcode":"22525",
    "sg:province":"Hamburg",
    "wof:name":"Jaguar House Kr\u00fcll Gmbh",
    "wof:placetype":"venue"
},
  "geometry": {"coordinates":[9.9263372421,53.5720977783],"type":"Point"}
}