{
  "type": "Feature",
  "properties": {
    "iso:country":"DE",
    "sg:address":"Kammerratsheide 49",
    "sg:city":"Bielefeld",
    "sg:phone":"+49 521/71030",
    "sg:postcode":"33609",
    "sg:province":"Nordrhein-Westfalen",
    "wof:name":"Hawo Werkstatt F\u00fcr Haus- Und Wohnelemente",
    "wof:placetype":"venue"
},
  "geometry": {"coordinates":[8.5818529129,52.0417976379],"type":"Point"}
}