{
  "type": "Feature",
  "properties": {
    "iso:country":"DE",
    "sg:address":"Ehrlicherstr. 28",
    "sg:city":"Hildesheim",
    "sg:phone":"+49 5121/57375",
    "sg:postcode":"31135",
    "sg:province":"Niedersachsen",
    "wof:name":"Der Friseur",
    "wof:placetype":"venue"
},
  "geometry": {"coordinates":[9.9724721909,52.1733207703],"type":"Point"}
}