{
  "type": "Feature",
  "properties": {
    "iso:country":"DE",
    "sg:address":"Rundling 10",
    "sg:city":"Klein Rogahn",
    "sg:phone":"+49 385/6470000",
    "sg:postcode":"19073",
    "sg:province":"Mecklenburg-Vorpommern",
    "wof:name":"Paul Wissel",
    "wof:placetype":"venue"
},
  "geometry": {"coordinates":[11.3474493027,53.6040115356],"type":"Point"}
}