{
  "type": "Feature",
  "properties": {
    "iso:country":"DE",
    "sg:address":"Sonnenb\u00fchlstr 78",
    "sg:city":"Konstanz",
    "sg:phone":"+49 170 4005465",
    "sg:postcode":"78464",
    "sg:province":"Baden-W\u00fcrttemberg",
    "wof:name":"Forum Choreographie Regie",
    "wof:placetype":"venue"
},
  "geometry": {"coordinates":[9.19366,47.678406],"type":"Point"}
}