{
  "type": "Feature",
  "properties": {
    "iso:country":"DE",
    "sg:address":"Hauptstr. 11",
    "sg:city":"Halvesbostel",
    "sg:phone":"+49 4169/919091",
    "sg:postcode":"21646",
    "sg:province":"Niedersachsen",
    "wof:name":"Gerhard Schmidt Gmbh",
    "wof:placetype":"venue"
},
  "geometry": {"coordinates":[9.6202411652,53.3612632751],"type":"Point"}
}