{
  "type": "Feature",
  "properties": {
    "iso:country":"DE",
    "sg:address":"Reichenbachstr. 3",
    "sg:city":"M\u00fcnchen",
    "sg:postcode":"80469",
    "sg:province":"Bayern",
    "wof:name":"Chiemgauer Hof Hotelbetriebsges. Mbh",
    "wof:placetype":"venue"
},
  "geometry": {"coordinates":[11.576546669,48.1340866089],"type":"Point"}
}