{
  "type": "Feature",
  "properties": {
    "iso:country":"DE",
    "sg:address":"Glacisstr. 24",
    "sg:city":"Dresden",
    "sg:phone":"+49 351/8292430",
    "sg:postcode":"01099",
    "sg:province":"Sachsen",
    "wof:name":"Wei\u00dfer Hirsch Immobilien- S\u00fcd Verwaltungs- Gmbh",
    "wof:placetype":"venue"
},
  "geometry": {"coordinates":[13.7508182526,51.060836792],"type":"Point"}
}