{
  "type": "Feature",
  "properties": {
    "iso:country":"DE",
    "sg:address":"Fischtorplatz 21",
    "sg:city":"Mainz",
    "sg:phone":"+49 6131/221725",
    "sg:postcode":"55116",
    "sg:province":"Rheinland-Pfalz",
    "wof:name":"Trias Steuerberatungsges. Mbh",
    "wof:placetype":"venue"
},
  "geometry": {"coordinates":[8.2778816223,50.0001335144],"type":"Point"}
}