{
  "type": "Feature",
  "properties": {
    "iso:country":"DE",
    "sg:address":"Vachaer Str. 2 a",
    "sg:city":"Philippsthal",
    "sg:phone":"+49 6620/469",
    "sg:postcode":"36269",
    "sg:province":"Hessen",
    "wof:name":"Hotel-restaurant Rh\u00f6nblick",
    "wof:placetype":"venue"
},
  "geometry": {"coordinates":[10.0068359375,50.8409347534],"type":"Point"}
}