{
  "type": "Feature",
  "properties": {
    "iso:country":"DE",
    "sg:address":"Munstermannskamp 1",
    "sg:city":"Lueneburg",
    "sg:classifiers":[
        {
            "category":"Professional",
            "subcategory":"Computer Services",
            "type":"Services"
        }
    ],
    "sg:postcode":"21335",
    "sg:tags":[
        "Linux",
        "Tutorial",
        "Howto"
    ],
    "sg:website":"http://www.howtoforge.com",
    "wof:name":"HowtoForge",
    "wof:placetype":"venue"
},
  "geometry": {"coordinates":[10.403998,53.23171],"type":"Point"}
}