{
  "type": "Feature",
  "properties": {
    "iso:country":"DE",
    "sg:address":"Stedinger Str. 126",
    "sg:city":"Oldenburg",
    "sg:phone":"+49 441/9736360",
    "sg:postcode":"26135",
    "sg:province":"Niedersachsen",
    "wof:name":"Rainer Stasch Architekt",
    "wof:placetype":"venue"
},
  "geometry": {"coordinates":[8.235067,53.137192],"type":"Point"}
}