{
  "type": "Feature",
  "properties": {
    "iso:country":"DE",
    "sg:address":"Wilhelmstr. 20",
    "sg:city":"K\u00f6ln",
    "sg:phone":"+49 2203/54502",
    "sg:postcode":"51143",
    "sg:province":"Nordrhein-Westfalen",
    "wof:name":"Dedi Phone",
    "wof:placetype":"venue"
},
  "geometry": {"coordinates":[7.0569000244,50.8851623535],"type":"Point"}
}