{
  "type": "Feature",
  "properties": {
    "iso:country":"DE",
    "sg:address":"Kn\u00fctgenstr. 4-6",
    "sg:city":"Siegburg",
    "sg:postcode":"53721",
    "sg:province":"Nordrhein-Westfalen",
    "wof:name":"Rolf H. Mode- Und Vertriebsgmbh",
    "wof:placetype":"venue"
},
  "geometry": {"coordinates":[7.2098531723,50.8059883118],"type":"Point"}
}