{
  "type": "Feature",
  "properties": {
    "iso:country":"DE",
    "sg:address":"Gernotstr. 23",
    "sg:city":"Bottrop",
    "sg:phone":"+49 2041/93888",
    "sg:postcode":"46240",
    "sg:province":"Nordrhein-Westfalen",
    "wof:name":"E. Pietrowsky Heilpraktiker",
    "wof:placetype":"venue"
},
  "geometry": {"coordinates":[6.9133858681,51.5419540405],"type":"Point"}
}