{
  "type": "Feature",
  "properties": {
    "iso:country":"DE",
    "sg:address":"Im Falkenhorst 8",
    "sg:city":"K\u00f6ln",
    "sg:phone":"+49 2203/35236",
    "sg:postcode":"51145",
    "sg:province":"Nordrhein-Westfalen",
    "wof:name":"Josef Elsen",
    "wof:placetype":"venue"
},
  "geometry": {"coordinates":[7.082019,50.887386],"type":"Point"}
}