{
  "type": "Feature",
  "properties": {
    "iso:country":"DE",
    "sg:address":"Nebengasse 8",
    "sg:city":"Neu-Ulm",
    "sg:phone":"+49 731/83500",
    "sg:postcode":"89231",
    "sg:province":"Bayern",
    "wof:name":"Georg Koch",
    "wof:placetype":"venue"
},
  "geometry": {"coordinates":[10.008765,48.365669],"type":"Point"}
}