{
  "type": "Feature",
  "properties": {
    "iso:country":"DE",
    "sg:address":"Ladiusstr. 31",
    "sg:city":"Berlin",
    "sg:phone":"+49 30/8153248",
    "sg:postcode":"14165",
    "sg:province":"Berlin",
    "wof:name":"S\u00fcd-apotheke E. Kfm. Ellen Junior",
    "wof:placetype":"venue"
},
  "geometry": {"coordinates":[13.262064,52.410789],"type":"Point"}
}