{
  "type": "Feature",
  "properties": {
    "iso:country":"DE",
    "sg:city":"Dannewerk",
    "sg:phone":"+49 4621/32141",
    "sg:postcode":"24867",
    "sg:province":"Schleswig-Holstein",
    "wof:name":"Hans-j\u00fcrgen Lehmann Architekt",
    "wof:placetype":"venue"
},
  "geometry": {"coordinates":[9.511279,54.487114],"type":"Point"}
}