{
  "type": "Feature",
  "properties": {
    "iso:country":"DE",
    "sg:address":"Promenadeplatz 12",
    "sg:city":"M\u00fcnchen",
    "sg:phone":"+49 89/2422660",
    "sg:postcode":"80333",
    "sg:province":"Bayern",
    "wof:name":"Abg Allgemeine Bautr\u00e4gerges. Mbh & Co. Kg",
    "wof:placetype":"venue"
},
  "geometry": {"coordinates":[11.5722408295,48.1400642395],"type":"Point"}
}