{
  "type": "Feature",
  "properties": {
    "iso:country":"DE",
    "sg:address":"Gelstern 2",
    "sg:city":"Schalksm\u00fchle",
    "sg:postcode":"58579",
    "sg:province":"Nordrhein-Westfalen",
    "wof:name":"3g Geistern Golf Gmbh & Co. Kg",
    "wof:placetype":"venue"
},
  "geometry": {"coordinates":[7.594930172,51.251537323],"type":"Point"}
}