{
  "type": "Feature",
  "properties": {
    "iso:country":"DE",
    "sg:address":"Koppentalstr. 10",
    "sg:city":"Stuttgart",
    "sg:postcode":"70192",
    "sg:province":"Baden-W\u00fcrttemberg",
    "wof:name":"Verein F\u00fcr Verbraucher- Schutz Und Information E. V.",
    "wof:placetype":"venue"
},
  "geometry": {"coordinates":[9.1659297943,48.7885475159],"type":"Point"}
}