{
  "type": "Feature",
  "properties": {
    "iso:country":"DE",
    "sg:address":"Hauptstr. 57",
    "sg:city":"Isernhagen",
    "sg:phone":"+49 5139/278222",
    "sg:postcode":"30916",
    "sg:province":"Niedersachsen",
    "wof:name":"M.a.s. Messe- Und Ausstellungsservice",
    "wof:placetype":"venue"
},
  "geometry": {"coordinates":[9.841079,52.470531],"type":"Point"}
}