{
  "type": "Feature",
  "properties": {
    "iso:country":"DE",
    "sg:address":"Bahnhofstr. 13",
    "sg:city":"Regenstauf",
    "sg:phone":"+49 9402/5090",
    "sg:postcode":"93128",
    "sg:province":"Bayern",
    "wof:name":"Sangerberger Heimatstube",
    "wof:placetype":"venue"
},
  "geometry": {"coordinates":[12.126518,49.122749],"type":"Point"}
}