{
  "type": "Feature",
  "properties": {
    "iso:country":"DE",
    "sg:address":"Steinhauerstr. 55",
    "sg:city":"Springe",
    "sg:phone":"+49 5045/982282",
    "sg:postcode":"31832",
    "sg:province":"Niedersachsen",
    "wof:name":"Lehnberg Immobilienmakler",
    "wof:placetype":"venue"
},
  "geometry": {"coordinates":[9.6236391068,52.2172622681],"type":"Point"}
}