{
  "type": "Feature",
  "properties": {
    "iso:country":"DE",
    "sg:address":"Nordring 53",
    "sg:city":"Rheda-Wiedenbr\u00fcck",
    "sg:phone":"+49 5242/401406",
    "sg:postcode":"33378",
    "sg:province":"Nordrhein-Westfalen",
    "wof:name":"Hamburg-mannheimer Ernst Seidel",
    "wof:placetype":"venue"
},
  "geometry": {"coordinates":[8.3086795807,51.8401107788],"type":"Point"}
}