{
  "type": "Feature",
  "properties": {
    "iso:country":"DE",
    "sg:address":"Enten\u00e4cker 33",
    "sg:city":"Bietigheim-Bissingen",
    "sg:phone":"+49 7142/31637",
    "sg:postcode":"74321",
    "sg:province":"Baden-W\u00fcrttemberg",
    "wof:name":"Action-sport Tauchsportcenter Gmbh",
    "wof:placetype":"venue"
},
  "geometry": {"coordinates":[9.094137,48.941696],"type":"Point"}
}