{
  "type": "Feature",
  "properties": {
    "iso:country":"DE",
    "sg:address":"In den Weiden 2",
    "sg:city":"Erfurt",
    "sg:phone":"+49 361/3731111",
    "sg:postcode":"99099",
    "sg:province":"Th\u00fcringen",
    "wof:name":"Imha Gegr. Dr. H. Seeber",
    "wof:placetype":"venue"
},
  "geometry": {"coordinates":[11.094971,50.948814],"type":"Point"}
}