{
  "type": "Feature",
  "properties": {
    "iso:country":"DE",
    "sg:address":"Rothweg 4",
    "sg:city":"Lollar",
    "sg:postcode":"35457",
    "sg:province":"Hessen",
    "wof:name":"Praktiker Bau- Und Heimwerkermarkt",
    "wof:placetype":"venue"
},
  "geometry": {"coordinates":[8.7029600143,50.6394844055],"type":"Point"}
}