{
  "type": "Feature",
  "properties": {
    "iso:country":"DE",
    "sg:address":"Weststr. 59",
    "sg:city":"Kamen",
    "sg:phone":"+49 2307/13829",
    "sg:postcode":"59174",
    "sg:province":"Nordrhein-Westfalen",
    "wof:name":"H. Kr\u00e4mer",
    "wof:placetype":"venue"
},
  "geometry": {"coordinates":[7.6605510712,51.5923423767],"type":"Point"}
}