{
  "type": "Feature",
  "properties": {
    "iso:country":"DE",
    "sg:address":"Am Bahnhof 7",
    "sg:city":"Bad D\u00fcrkheim",
    "sg:phone":"+49 6322/1093",
    "sg:postcode":"67098",
    "sg:province":"Rheinland-Pfalz",
    "wof:name":"Raiffeisen-warengenossenschaft Bad D\u00fcrkheim Eg",
    "wof:placetype":"venue"
},
  "geometry": {"coordinates":[8.173636,49.462082],"type":"Point"}
}