{
  "type": "Feature",
  "properties": {
    "iso:country":"DE",
    "sg:address":"Zweidlerweg 32",
    "sg:city":"Bamberg",
    "sg:phone":"+49 951/15664",
    "sg:postcode":"96050",
    "sg:province":"Bayern",
    "wof:name":"Christa Stuber",
    "wof:placetype":"venue"
},
  "geometry": {"coordinates":[10.91309,49.884911],"type":"Point"}
}