{
  "type": "Feature",
  "properties": {
    "iso:country":"DE",
    "sg:address":"Sonnenweg 5",
    "sg:city":"Hannover",
    "sg:phone":"+49 511/858499",
    "sg:postcode":"30171",
    "sg:province":"Niedersachsen",
    "wof:name":"Wolfgang Schmieder Schilder Und Lichtreklame",
    "wof:placetype":"venue"
},
  "geometry": {"coordinates":[9.756743,52.369511],"type":"Point"}
}