{
  "type": "Feature",
  "properties": {
    "iso:country":"DE",
    "sg:address":"Brunnenstr. 10",
    "sg:city":"Bad Schwalbach",
    "sg:phone":"+49 6124/2975",
    "sg:postcode":"65307",
    "sg:province":"Hessen",
    "wof:name":"Optik-giefer Inh. G\u00fcnter Giefer",
    "wof:placetype":"venue"
},
  "geometry": {"coordinates":[8.0693273544,50.1394309998],"type":"Point"}
}