{
  "type": "Feature",
  "properties": {
    "iso:country":"DE",
    "sg:address":"Goldene Aue",
    "sg:city":"Gotha",
    "sg:phone":"+49 3621/52477",
    "sg:postcode":"99867",
    "sg:province":"Th\u00fcringen",
    "wof:name":"E. Augustin",
    "wof:placetype":"venue"
},
  "geometry": {"coordinates":[10.67678,50.937706],"type":"Point"}
}