{
  "type": "Feature",
  "properties": {
    "iso:country":"DE",
    "sg:address":"H\u00e4mmerlingstr. 119",
    "sg:city":"Berlin",
    "sg:phone":"+49 30/6572329",
    "sg:postcode":"12555",
    "sg:province":"Berlin",
    "wof:name":"S & M-schwidder Gie\u00dferei- Und Schilder Gmbh",
    "wof:placetype":"venue"
},
  "geometry": {"coordinates":[13.574321,52.456516],"type":"Point"}
}