{
  "type": "Feature",
  "properties": {
    "iso:country":"DE",
    "sg:address":"Seifenstr. 1a",
    "sg:city":"Malter",
    "sg:phone":"+49 3504/612465",
    "sg:postcode":"01744",
    "sg:province":"Sachsen",
    "wof:name":"Siegmar",
    "wof:placetype":"venue"
},
  "geometry": {"coordinates":[13.6549367905,50.8967170715],"type":"Point"}
}