{
  "type": "Feature",
  "properties": {
    "iso:country":"DE",
    "sg:address":"Roseggerstr. 41",
    "sg:city":"Hamburg",
    "sg:phone":"+49 40/7637334",
    "sg:postcode":"21079",
    "sg:province":"Hamburg",
    "wof:name":"Restaurant Taverna Ithaki",
    "wof:placetype":"venue"
},
  "geometry": {"coordinates":[9.9954242706,53.4435424805],"type":"Point"}
}