{
  "type": "Feature",
  "properties": {
    "iso:country":"DE",
    "sg:address":"Karl-Marx-Str. 239",
    "sg:city":"Berlin",
    "sg:phone":"+49 30/6843543",
    "sg:postcode":"12055",
    "sg:province":"Berlin",
    "wof:name":"Dr. Med. Ralf Wagner",
    "wof:placetype":"venue"
},
  "geometry": {"coordinates":[13.4420585632,52.4679107666],"type":"Point"}
}