{
  "type": "Feature",
  "properties": {
    "iso:country":"DE",
    "sg:address":"Stettiner Str. 9",
    "sg:city":"Gro\u00dfostheim",
    "sg:phone":"+49 6026/1282",
    "sg:postcode":"63762",
    "sg:province":"Bayern",
    "wof:name":"Philadelphia Discothekenbetriebs-gmbh",
    "wof:placetype":"venue"
},
  "geometry": {"coordinates":[9.033445,49.929497],"type":"Point"}
}