{
  "type": "Feature",
  "properties": {
    "iso:country":"DE",
    "sg:address":"Kaiserstr. 12",
    "sg:city":"Rosenheim",
    "sg:phone":"+49 8031/34555",
    "sg:postcode":"83022",
    "sg:province":"Bayern",
    "wof:name":"Sternbr\u00e4u",
    "wof:placetype":"venue"
},
  "geometry": {"coordinates":[12.1285161972,47.8574409485],"type":"Point"}
}