{
  "type": "Feature",
  "properties": {
    "iso:country":"DE",
    "sg:address":"Am J\u00e4gerhaus 1",
    "sg:city":"Telgte",
    "sg:phone":"+49 2504/1878",
    "sg:postcode":"48291",
    "sg:province":"Nordrhein-Westfalen",
    "wof:name":"Tanzlokal Single",
    "wof:placetype":"venue"
},
  "geometry": {"coordinates":[7.7464537621,51.9806747437],"type":"Point"}
}