{
  "type": "Feature",
  "properties": {
    "iso:country":"DE",
    "sg:address":"Frankfurter Str. 52",
    "sg:city":"Schwelm",
    "sg:phone":"+49 2336/13600",
    "sg:postcode":"58332",
    "sg:province":"Nordrhein-Westfalen",
    "wof:name":"Uwe Fichthorn",
    "wof:placetype":"venue"
},
  "geometry": {"coordinates":[7.3057332039,51.2790756226],"type":"Point"}
}