{
  "type": "Feature",
  "properties": {
    "iso:country":"DE",
    "sg:address":"Hohenzollernstr. 25",
    "sg:city":"D\u00fcren",
    "sg:phone":"+49 2421/17082",
    "sg:postcode":"52351",
    "sg:province":"Nordrhein-Westfalen",
    "wof:name":"Blickfang Ohg",
    "wof:placetype":"venue"
},
  "geometry": {"coordinates":[6.4868469238,50.8018569946],"type":"Point"}
}