{
  "type": "Feature",
  "properties": {
    "iso:country":"DE",
    "sg:address":"Flotowstr. 63",
    "sg:city":"M\u00fcnchen",
    "sg:phone":"+49 89/5467280",
    "sg:postcode":"80686",
    "sg:province":"Bayern",
    "wof:name":"Hans Aulinger Steuerberater Rechtsanwalt",
    "wof:placetype":"venue"
},
  "geometry": {"coordinates":[11.5047588348,48.1300163269],"type":"Point"}
}