{
  "type": "Feature",
  "properties": {
    "iso:country":"DE",
    "sg:address":"Memminger Str. 65",
    "sg:city":"Kempten",
    "sg:phone":"+49 831/28995",
    "sg:postcode":"87439",
    "sg:province":"Bayern",
    "wof:name":"Rudolf Steinacher",
    "wof:placetype":"venue"
},
  "geometry": {"coordinates":[10.3100252151,47.7342071533],"type":"Point"}
}