{
  "type": "Feature",
  "properties": {
    "iso:country":"DE",
    "sg:address":"K\u00f6nig-Ludwig-Str. 30a",
    "sg:city":"Recklinghausen",
    "sg:phone":"+49 2361/371172",
    "sg:postcode":"45663",
    "sg:province":"Nordrhein-Westfalen",
    "wof:name":"Reiner Glebsattel",
    "wof:placetype":"venue"
},
  "geometry": {"coordinates":[7.217361927,51.5781745911],"type":"Point"}
}