{
  "type": "Feature",
  "properties": {
    "iso:country":"DE",
    "sg:address":"Seefelderschaart 44",
    "sg:city":"Stadland",
    "sg:postcode":"26937",
    "sg:province":"Niedersachsen",
    "wof:name":"Tandem Investitions- Und Beteiligungsgesellschaft F\u00fcr",
    "wof:placetype":"venue"
},
  "geometry": {"coordinates":[8.356833,53.462818],"type":"Point"}
}