{
  "type": "Feature",
  "properties": {
    "iso:country":"DE",
    "sg:address":"Friedhofstr. 4",
    "sg:city":"Worms",
    "sg:postcode":"67549",
    "sg:province":"Rheinland-Pfalz",
    "wof:name":"Gt - Bautr\u00e4ger Gmbh",
    "wof:placetype":"venue"
},
  "geometry": {"coordinates":[8.30805,49.641693],"type":"Point"}
}