{
  "type": "Feature",
  "properties": {
    "iso:country":"DE",
    "sg:address":"Lauterbacher Str. 9",
    "sg:city":"Birstein",
    "sg:phone":"+49 6054/478",
    "sg:postcode":"63633",
    "sg:province":"Hessen",
    "wof:name":"Wilhelm Krack",
    "wof:placetype":"venue"
},
  "geometry": {"coordinates":[9.307786,50.354427],"type":"Point"}
}