{
  "type": "Feature",
  "properties": {
    "iso:country":"DE",
    "sg:address":"Hinter den L\u00f6hern 2",
    "sg:city":"Fulda",
    "sg:phone":"+49 661/73470",
    "sg:postcode":"36037",
    "sg:province":"Hessen",
    "wof:name":"Y. Kavlak",
    "wof:placetype":"venue"
},
  "geometry": {"coordinates":[9.6729335785,50.5495033264],"type":"Point"}
}