{
  "type": "Feature",
  "properties": {
    "iso:country":"DE",
    "sg:address":"Kirchstr. 11",
    "sg:city":"St. Wendel",
    "sg:phone":"+49 6854/265",
    "sg:postcode":"66606",
    "sg:province":"Saarland",
    "wof:name":"A. Bommer Immobilienmakler",
    "wof:placetype":"venue"
},
  "geometry": {"coordinates":[7.171189785,49.4685440063],"type":"Point"}
}