{
  "type": "Feature",
  "properties": {
    "iso:country":"DE",
    "sg:address":"Torgauer Str. 12",
    "sg:city":"Herzberg",
    "sg:phone":"+49 3535/6045",
    "sg:postcode":"04916",
    "sg:province":"Brandenburg",
    "wof:name":"Manfred Bl\u00fcthgen",
    "wof:placetype":"venue"
},
  "geometry": {"coordinates":[13.2327222824,51.6916732788],"type":"Point"}
}