{
  "type": "Feature",
  "properties": {
    "iso:country":"DE",
    "sg:address":"August-L\u00f6sch-Str. 2",
    "sg:city":"Heidenheim",
    "sg:phone":"+49 7321/24869",
    "sg:postcode":"89522",
    "sg:province":"Baden-W\u00fcrttemberg",
    "wof:name":"Ottilie G\u00f6bel Steuerberater",
    "wof:placetype":"venue"
},
  "geometry": {"coordinates":[10.1522302628,48.6756095886],"type":"Point"}
}