{
  "type": "Feature",
  "properties": {
    "iso:country":"DE",
    "sg:address":"L\u00fcneburger Str. 45",
    "sg:city":"Bielefeld",
    "sg:phone":"+49 521/206381",
    "sg:postcode":"33719",
    "sg:province":"Nordrhein-Westfalen",
    "wof:name":"Werner Hanke",
    "wof:placetype":"venue"
},
  "geometry": {"coordinates":[8.608795,52.013401],"type":"Point"}
}