{
  "type": "Feature",
  "properties": {
    "iso:country":"DE",
    "sg:address":"Wendelinstr. 71",
    "sg:city":"K\u00f6ln",
    "sg:phone":"+49 221/4912485",
    "sg:postcode":"50933",
    "sg:province":"Nordrhein-Westfalen",
    "wof:name":"Seidelt & Kreutzer Gmbh & Co. Kg",
    "wof:placetype":"venue"
},
  "geometry": {"coordinates":[6.878935,50.9408],"type":"Point"}
}