{
  "type": "Feature",
  "properties": {
    "iso:country":"DE",
    "sg:address":"Judenberg 17",
    "sg:city":"Duggendorf",
    "sg:phone":"+49 9409/426",
    "sg:postcode":"93182",
    "sg:province":"Bayern",
    "wof:name":"Ludwig Frank",
    "wof:placetype":"venue"
},
  "geometry": {"coordinates":[11.963408,49.120453],"type":"Point"}
}