{
  "type": "Feature",
  "properties": {
    "iso:country":"DE",
    "sg:address":"Obere Kirchstr. 33",
    "sg:city":"Gerstetten",
    "sg:phone":"+49 7323/7209",
    "sg:postcode":"89547",
    "sg:province":"Baden-W\u00fcrttemberg",
    "wof:name":"Stern",
    "wof:placetype":"venue"
},
  "geometry": {"coordinates":[10.0275182724,48.620765686],"type":"Point"}
}