{
  "type": "Feature",
  "properties": {
    "iso:country":"DE",
    "sg:address":"Geyer G\u00e4\u00dfchen 3",
    "sg:city":"B\u00fcdingen",
    "sg:phone":"+49 6041/96110",
    "sg:postcode":"63654",
    "sg:province":"Hessen",
    "wof:name":"Cp Elektrobau Gmbh",
    "wof:placetype":"venue"
},
  "geometry": {"coordinates":[9.028889,50.288452],"type":"Point"}
}