{
  "type": "Feature",
  "properties": {
    "iso:country":"DE",
    "sg:address":"Am Rosenplatz 5",
    "sg:city":"Reinbek",
    "sg:phone":"+49 40/7227289",
    "sg:postcode":"21465",
    "sg:province":"Schleswig-Holstein",
    "wof:name":"J\u00fcrgen Und Karin Kiene Steuerbevollm\u00e4chtigte",
    "wof:placetype":"venue"
},
  "geometry": {"coordinates":[10.2508649826,53.5119171143],"type":"Point"}
}