{
  "type": "Feature",
  "properties": {
    "iso:country":"DE",
    "sg:address":"Sinsheimer Str. 1",
    "sg:city":"Mauer",
    "sg:phone":"+49 4962/261233",
    "sg:postcode":"69256",
    "sg:province":"Baden-W\u00fcrttemberg",
    "wof:name":"Bezirkssparkasse",
    "wof:placetype":"venue"
},
  "geometry": {"coordinates":[8.800357,49.339458],"type":"Point"}
}