{
  "type": "Feature",
  "properties": {
    "iso:country":"DE",
    "sg:address":"Lochhamer Str. 8a",
    "sg:city":"Planegg",
    "sg:phone":"+49 89/12391463",
    "sg:postcode":"82152",
    "sg:province":"Bayern",
    "wof:name":"Clausen & Partner Werbeagentur Gmbh",
    "wof:placetype":"venue"
},
  "geometry": {"coordinates":[11.4521341324,48.1107940674],"type":"Point"}
}