{
  "type": "Feature",
  "properties": {
    "iso:country":"DE",
    "sg:address":"M\u00f6slein 32",
    "sg:city":"Abenberg",
    "sg:phone":"+49 9873/97770",
    "sg:postcode":"91183",
    "sg:province":"Bayern",
    "wof:name":"Dengler Vertriebs- Und Entwicklungs Gmbh",
    "wof:placetype":"venue"
},
  "geometry": {"coordinates":[10.894372,49.221226],"type":"Point"}
}