{
  "type": "Feature",
  "properties": {
    "iso:country":"DE",
    "sg:address":"Waldstr. 61",
    "sg:city":"Karlsruhe",
    "sg:phone":"+49 721/9203916",
    "sg:postcode":"76133",
    "sg:province":"Baden-W\u00fcrttemberg",
    "wof:name":"Vision Brillen Und Contact- Linsen Am Ludwigsplatz Gmbh",
    "wof:placetype":"venue"
},
  "geometry": {"coordinates":[8.3956012726,49.0088500977],"type":"Point"}
}