{
  "type": "Feature",
  "properties": {
    "iso:country":"DE",
    "sg:address":"Schellingstr. 3",
    "sg:city":"Gera",
    "sg:phone":"+49 365/23560",
    "sg:postcode":"07548",
    "sg:province":"Th\u00fcringen",
    "wof:name":"Dorothea Steingr\u00fcber",
    "wof:placetype":"venue"
},
  "geometry": {"coordinates":[12.067934,50.885017],"type":"Point"}
}