{
  "type": "Feature",
  "properties": {
    "iso:country":"DE",
    "sg:address":"In der Lohe 42",
    "sg:city":"F\u00fcrth",
    "sg:phone":"+49 911/7908625",
    "sg:postcode":"90765",
    "sg:province":"Bayern",
    "wof:name":"Edgar Ordnung Ingenieur",
    "wof:placetype":"venue"
},
  "geometry": {"coordinates":[11.0017871857,49.4951171875],"type":"Point"}
}