{
  "type": "Feature",
  "properties": {
    "iso:country":"DE",
    "sg:address":"Bogengasse 4",
    "sg:city":"Veldenz",
    "sg:phone":"+49 6534/516",
    "sg:postcode":"54472",
    "sg:province":"Rheinland-Pfalz",
    "wof:name":"Helmut Steinhauer",
    "wof:placetype":"venue"
},
  "geometry": {"coordinates":[7.0223269463,49.8897018433],"type":"Point"}
}