{
  "type": "Feature",
  "properties": {
    "iso:country":"DE",
    "sg:address":"S\u00fcderstr. 8",
    "sg:city":"Meldorf",
    "sg:phone":"+49 4832/2370",
    "sg:postcode":"25704",
    "sg:province":"Schleswig-Holstein",
    "wof:name":"Dithmarscher Sattelkammer",
    "wof:placetype":"venue"
},
  "geometry": {"coordinates":[9.07153,54.089279],"type":"Point"}
}