{
  "type": "Feature",
  "properties": {
    "iso:country":"DE",
    "sg:address":"K\u00f6nigsberger Str. 5",
    "sg:city":"Ahlen",
    "sg:phone":"+49 2382/71479",
    "sg:postcode":"59229",
    "sg:province":"Nordrhein-Westfalen",
    "wof:name":"Dieter H. Petrick Elektroheizungen",
    "wof:placetype":"venue"
},
  "geometry": {"coordinates":[7.889376,51.752945],"type":"Point"}
}