{
  "type": "Feature",
  "properties": {
    "iso:country":"DE",
    "sg:address":"Frennetstr. 76",
    "sg:city":"Aachen",
    "sg:phone":"+49 2408/80901",
    "sg:postcode":"52076",
    "sg:province":"Nordrhein-Westfalen",
    "wof:name":"Rainer D\u00f6rter Architekt",
    "wof:placetype":"venue"
},
  "geometry": {"coordinates":[6.168933,50.688583],"type":"Point"}
}