{
  "type": "Feature",
  "properties": {
    "iso:country":"DE",
    "sg:address":"Richard-Wagner-Str. 21",
    "sg:city":"Elsenfeld",
    "sg:phone":"+49 6022/1054",
    "sg:postcode":"63820",
    "sg:province":"Bayern",
    "wof:name":"R. Bachmann",
    "wof:placetype":"venue"
},
  "geometry": {"coordinates":[9.1629991531,49.8496513367],"type":"Point"}
}