{
  "type": "Feature",
  "properties": {
    "iso:country":"DE",
    "sg:address":"R\u00f6ntgenstr. 18",
    "sg:city":"Reinbek",
    "sg:phone":"+49 40/2483580",
    "sg:postcode":"21465",
    "sg:province":"Schleswig-Holstein",
    "wof:name":"Gst Worldwide Logistics Gmbh",
    "wof:placetype":"venue"
},
  "geometry": {"coordinates":[10.2410888672,53.5287971497],"type":"Point"}
}