{
  "type": "Feature",
  "properties": {
    "iso:country":"DE",
    "sg:address":"Briloner Landstr. 18",
    "sg:city":"Korbach",
    "sg:phone":"+49 4956/312408",
    "sg:postcode":"34497",
    "sg:province":"Hessen",
    "wof:name":"Wein-spezialhaus Karl Weber",
    "wof:placetype":"venue"
},
  "geometry": {"coordinates":[8.867366,51.277054],"type":"Point"}
}