{
  "type": "Feature",
  "properties": {
    "iso:country":"DE",
    "sg:address":"Regensburger Str. 7",
    "sg:city":"Nittendorf",
    "sg:postcode":"93152",
    "sg:province":"Bayern",
    "wof:name":"Nittendorfer Tiefbau Gmbh",
    "wof:placetype":"venue"
},
  "geometry": {"coordinates":[11.9587163925,49.0279159546],"type":"Point"}
}