{
  "type": "Feature",
  "properties": {
    "iso:country":"DE",
    "sg:address":"F\u00fcrholzer Weg 21",
    "sg:city":"Neufahrn",
    "sg:phone":"+49 8165/958760",
    "sg:postcode":"85375",
    "sg:province":"Bayern",
    "wof:name":"Dirschl Maschinen- Und Apparatebau Gmbh",
    "wof:placetype":"venue"
},
  "geometry": {"coordinates":[11.657642,48.317127],"type":"Point"}
}