{
  "type": "Feature",
  "properties": {
    "iso:country":"DE",
    "sg:address":"Unterprombach Hs. Nr. 2",
    "sg:city":"Cham",
    "sg:postcode":"93413",
    "sg:province":"Bayern",
    "wof:name":"Erc Energie-recycling Landkreis Cham Gmbh",
    "wof:placetype":"venue"
},
  "geometry": {"coordinates":[12.6629552841,49.2205467224],"type":"Point"}
}