{
  "type": "Feature",
  "properties": {
    "iso:country":"DE",
    "sg:address":"Janahofer Str. 1",
    "sg:city":"Cham",
    "sg:postcode":"93413",
    "sg:province":"Bayern",
    "wof:name":"Cham Car Autovermietungs Gmbh",
    "wof:placetype":"venue"
},
  "geometry": {"coordinates":[12.66859,49.215923],"type":"Point"}
}