{
  "type": "Feature",
  "properties": {
    "iso:country":"DE",
    "sg:address":"Ludwigstr. 10",
    "sg:city":"Landau",
    "sg:phone":"+49 9951/8455",
    "sg:postcode":"94405",
    "sg:province":"Bayern",
    "wof:name":"Pizzeria Bella Napoli",
    "wof:placetype":"venue"
},
  "geometry": {"coordinates":[12.6916093826,48.6701622009],"type":"Point"}
}