{
  "type": "Feature",
  "properties": {
    "iso:country":"DE",
    "sg:address":"Achalmstr. 68",
    "sg:city":"Pfullingen",
    "sg:phone":"+49 7121/71045",
    "sg:postcode":"72793",
    "sg:province":"Baden-W\u00fcrttemberg",
    "wof:name":"Restaurant Zur Achalm",
    "wof:placetype":"venue"
},
  "geometry": {"coordinates":[9.2323303223,48.4710044861],"type":"Point"}
}