{
  "type": "Feature",
  "properties": {
    "iso:country":"DE",
    "sg:address":"Zum Industriehafen 20",
    "sg:city":"Minden",
    "sg:phone":"+49 571/39910",
    "sg:postcode":"32423",
    "sg:province":"Nordrhein-Westfalen",
    "wof:name":"Raiffeisen Central- Genossenschaft Nordwest Eg",
    "wof:placetype":"venue"
},
  "geometry": {"coordinates":[8.95655,52.302692],"type":"Point"}
}