{
  "type": "Feature",
  "properties": {
    "iso:country":"DE",
    "sg:address":"Hauptstr. 22",
    "sg:city":"Ellwangen",
    "sg:phone":"+49 4979/65676",
    "sg:postcode":"73479",
    "sg:province":"Baden-W\u00fcrttemberg",
    "wof:name":"Raiffeisenbank R\u00f6hlingen Eg",
    "wof:placetype":"venue"
},
  "geometry": {"coordinates":[10.215569,48.942131],"type":"Point"}
}