{
  "type": "Feature",
  "properties": {
    "iso:country":"DE",
    "sg:address":"Auf L\u00fclingskreuz 8",
    "sg:city":"Korbach",
    "sg:phone":"+49 5631/7773",
    "sg:postcode":"34497",
    "sg:province":"Hessen",
    "wof:name":"F. W. Sprenger",
    "wof:placetype":"venue"
},
  "geometry": {"coordinates":[8.879162,51.28326],"type":"Point"}
}