{
  "type": "Feature",
  "properties": {
    "iso:country":"DE",
    "sg:address":"Hauptstr. 102",
    "sg:city":"W\u00f6rth",
    "sg:phone":"+49 6340/919191",
    "sg:postcode":"76744",
    "sg:province":"Rheinland-Pfalz",
    "wof:name":"Ludwig Metz",
    "wof:placetype":"venue"
},
  "geometry": {"coordinates":[10.272725,49.030788],"type":"Point"}
}