{
  "type": "Feature",
  "properties": {
    "iso:country":"DE",
    "sg:address":"Bahnhofstr. 5",
    "sg:city":"Beckum",
    "sg:phone":"+49 2525/2200",
    "sg:postcode":"59269",
    "sg:province":"Nordrhein-Westfalen",
    "wof:name":"Hotel Bahnhof",
    "wof:placetype":"venue"
},
  "geometry": {"coordinates":[8.0230455399,51.8016662598],"type":"Point"}
}