{
  "type": "Feature",
  "properties": {
    "iso:country":"DE",
    "sg:address":"Blumenweg 12",
    "sg:city":"\u00dcbersee",
    "sg:postcode":"83236",
    "sg:province":"Bayern",
    "wof:name":"Arte Di Colori Gmbh",
    "wof:placetype":"venue"
},
  "geometry": {"coordinates":[12.48226,47.83606],"type":"Point"}
}