{
  "type": "Feature",
  "properties": {
    "iso:country":"DE",
    "sg:address":"K\u00f6lner Landstr. 360",
    "sg:city":"D\u00fcsseldorf",
    "sg:phone":"+49 211/792040",
    "sg:postcode":"40589",
    "sg:province":"Nordrhein-Westfalen",
    "wof:name":"Allianz Versicherung Bernd Hufnagel Und",
    "wof:placetype":"venue"
},
  "geometry": {"coordinates":[6.8060941696,51.1662101746],"type":"Point"}
}