{
  "type": "Feature",
  "properties": {
    "iso:country":"DE",
    "sg:address":"Marburger Str. 4",
    "sg:city":"Darmstadt",
    "sg:phone":"+49 6151/76401",
    "sg:postcode":"64289",
    "sg:province":"Hessen",
    "wof:name":"W. Sp\u00e4th",
    "wof:placetype":"venue"
},
  "geometry": {"coordinates":[8.65355,49.887794],"type":"Point"}
}