{
  "type": "Feature",
  "properties": {
    "iso:country":"DE",
    "sg:address":"Hubeweg 119",
    "sg:city":"Einbeck",
    "sg:phone":"+49 5561/93020",
    "sg:postcode":"37574",
    "sg:province":"Niedersachsen",
    "wof:name":"Hotel Hasenj\u00e4ger",
    "wof:placetype":"venue"
},
  "geometry": {"coordinates":[9.8736009598,51.8323478699],"type":"Point"}
}