{
  "type": "Feature",
  "properties": {
    "iso:country":"DE",
    "sg:address":"K\u00f6rnerstr. 68",
    "sg:city":"Hagen",
    "sg:phone":"+49 2331/25444",
    "sg:postcode":"58095",
    "sg:province":"Nordrhein-Westfalen",
    "wof:name":"Rolf K\u00f6be",
    "wof:placetype":"venue"
},
  "geometry": {"coordinates":[7.4682121277,51.3614273071],"type":"Point"}
}