{
  "type": "Feature",
  "properties": {
    "iso:country":"DE",
    "sg:address":"Murrhardter Stra\u00dfe 10",
    "sg:city":"Welzheim",
    "sg:phone":"+49 7182/6897",
    "sg:postcode":"73642",
    "sg:province":"Baden-W\u00fcrttemberg",
    "wof:name":"Radio-richter",
    "wof:placetype":"venue"
},
  "geometry": {"coordinates":[9.634704,48.878307],"type":"Point"}
}