{
  "type": "Feature",
  "properties": {
    "iso:country":"DE",
    "sg:address":"Forststr. 102a",
    "sg:city":"Stuttgart",
    "sg:phone":"+49 711/631973",
    "sg:postcode":"70193",
    "sg:province":"Baden-W\u00fcrttemberg",
    "wof:name":"E. Danner",
    "wof:placetype":"venue"
},
  "geometry": {"coordinates":[9.1555547714,48.7773704529],"type":"Point"}
}