{
  "type": "Feature",
  "properties": {
    "iso:country":"DE",
    "sg:address":"S\u00fcdring 3",
    "sg:city":"Landau",
    "sg:phone":"+49 6341/4099",
    "sg:postcode":"76829",
    "sg:province":"Rheinland-Pfalz",
    "wof:name":"Gerd Marx Und Christian Sterzing",
    "wof:placetype":"venue"
},
  "geometry": {"coordinates":[8.1106939316,49.1942749023],"type":"Point"}
}