{
  "type": "Feature",
  "properties": {
    "iso:country":"DE",
    "sg:address":"Osthofenstr. 6",
    "sg:city":"Soest",
    "sg:phone":"+49 2921/4530",
    "sg:postcode":"59494",
    "sg:province":"Nordrhein-Westfalen",
    "wof:name":"Rainer Garz Objekteinrichtungen",
    "wof:placetype":"venue"
},
  "geometry": {"coordinates":[8.110574,51.571758],"type":"Point"}
}