{
  "type": "Feature",
  "properties": {
    "iso:country":"DE",
    "sg:address":"Am Harburger Wege 1",
    "sg:city":"Jesteburg",
    "sg:phone":"+49 4183/5760",
    "sg:postcode":"21266",
    "sg:province":"Niedersachsen",
    "wof:name":"Hans-j\u00fcrgen Maschewski Verlagsvertreter",
    "wof:placetype":"venue"
},
  "geometry": {"coordinates":[9.967454,53.314816],"type":"Point"}
}