{
  "type": "Feature",
  "properties": {
    "iso:country":"DE",
    "sg:address":"Kirchstr. 4a",
    "sg:city":"Bad Vilbel",
    "sg:phone":"+49 6101/32828",
    "sg:postcode":"61118",
    "sg:province":"Hessen",
    "wof:name":"Alt Gronau",
    "wof:placetype":"venue"
},
  "geometry": {"coordinates":[8.7794275284,50.1941986084],"type":"Point"}
}