{
  "type": "Feature",
  "properties": {
    "iso:country":"DE",
    "sg:address":"Am Detershof 8",
    "sg:city":"Westerstede",
    "sg:phone":"+49 4488/72448",
    "sg:postcode":"26655",
    "sg:province":"Niedersachsen",
    "wof:name":"Burrichter & Wilms",
    "wof:placetype":"venue"
},
  "geometry": {"coordinates":[7.92455,53.24707],"type":"Point"}
}