{
  "type": "Feature",
  "properties": {
    "iso:country":"DE",
    "sg:address":"Schlo\u00dfplatz 1",
    "sg:city":"Trochtelfingen",
    "sg:phone":"+49 4971/241071",
    "sg:postcode":"72818",
    "sg:province":"Baden-W\u00fcrttemberg",
    "wof:name":"Kreissparkasse Reutlingen",
    "wof:placetype":"venue"
},
  "geometry": {"coordinates":[9.243392,48.307045],"type":"Point"}
}