{
  "type": "Feature",
  "properties": {
    "iso:country":"DE",
    "sg:address":"Bleckenweg 98",
    "sg:city":"Celle",
    "sg:phone":"+49 5141/83109",
    "sg:postcode":"29227",
    "sg:province":"Niedersachsen",
    "wof:name":"Ferdinand Roselieb Alt- Und Abfallstoffe",
    "wof:placetype":"venue"
},
  "geometry": {"coordinates":[10.12107,52.589931],"type":"Point"}
}