{
  "type": "Feature",
  "properties": {
    "iso:country":"DE",
    "sg:address":"Rangenbergstr. 20",
    "sg:city":"Reutlingen",
    "sg:phone":"+49 7121/46689",
    "sg:postcode":"72766",
    "sg:province":"Baden-W\u00fcrttemberg",
    "wof:name":"Gerd Straif",
    "wof:placetype":"venue"
},
  "geometry": {"coordinates":[9.234222,48.512066],"type":"Point"}
}