{
  "type": "Feature",
  "properties": {
    "iso:country":"DE",
    "sg:address":"Robert-Wirichs-Str 53",
    "sg:city":"Krefeld",
    "sg:phone":"+49 2151/83770",
    "sg:postcode":"47807",
    "sg:province":"Nordrhein-Westfalen",
    "wof:name":"Hans Ploenes Gmbh",
    "wof:placetype":"venue"
},
  "geometry": {"coordinates":[6.563705,51.312016],"type":"Point"}
}