{
  "type": "Feature",
  "properties": {
    "iso:country":"DE",
    "sg:address":"Sch\u00f6nbuchstr. 51",
    "sg:city":"Nagold",
    "sg:phone":"+49 7459/368",
    "sg:postcode":"72202",
    "sg:province":"Baden-W\u00fcrttemberg",
    "wof:name":"Wei\u00df & Nesch Gmbh",
    "wof:placetype":"venue"
},
  "geometry": {"coordinates":[8.7535171509,48.5160751343],"type":"Point"}
}