{
  "type": "Feature",
  "properties": {
    "iso:country":"DE",
    "sg:address":"Reyplatz 15",
    "sg:city":"Baesweiler",
    "sg:phone":"+49 2401/7367",
    "sg:postcode":"52499",
    "sg:province":"Nordrhein-Westfalen",
    "wof:name":"Dautzenberg",
    "wof:placetype":"venue"
},
  "geometry": {"coordinates":[6.1787791252,50.9107093811],"type":"Point"}
}