{
  "type": "Feature",
  "properties": {
    "iso:country":"DE",
    "sg:address":"Senefelderstr.",
    "sg:city":"Stuttgart",
    "sg:phone":"+49 711/624407",
    "sg:postcode":"70176",
    "sg:province":"Baden-W\u00fcrttemberg",
    "wof:name":"Libellus",
    "wof:placetype":"venue"
},
  "geometry": {"coordinates":[9.157193,48.780537],"type":"Point"}
}