{
  "type": "Feature",
  "properties": {
    "iso:country":"DE",
    "sg:address":"Regensburger Str. 55",
    "sg:city":"Teublitz",
    "sg:phone":"+49 9471/9302",
    "sg:postcode":"93158",
    "sg:province":"Bayern",
    "wof:name":"W. Gerhardinger",
    "wof:placetype":"venue"
},
  "geometry": {"coordinates":[12.085934639,49.2218475342],"type":"Point"}
}