{
  "type": "Feature",
  "properties": {
    "iso:country":"DE",
    "sg:address":"Wrangelstr. 83",
    "sg:city":"Berlin",
    "sg:phone":"+49 30/6113674",
    "sg:postcode":"10997",
    "sg:province":"Berlin",
    "wof:name":"Lehmann",
    "wof:placetype":"venue"
},
  "geometry": {"coordinates":[13.4418773651,52.4987602234],"type":"Point"}
}