{
  "type": "Feature",
  "properties": {
    "iso:country":"DE",
    "sg:address":"Alte Landstr. 16a",
    "sg:city":"Neuenburg",
    "sg:phone":"+49 7631/73412",
    "sg:postcode":"79395",
    "sg:province":"Baden-W\u00fcrttemberg",
    "wof:name":"Reimund Kipar Ingenieur",
    "wof:placetype":"venue"
},
  "geometry": {"coordinates":[7.5772361755,47.8425750732],"type":"Point"}
}