{
  "type": "Feature",
  "properties": {
    "iso:country":"DE",
    "sg:address":"Hertener Str. 62",
    "sg:city":"Gelsenkirchen",
    "sg:phone":"+49 209/788448",
    "sg:postcode":"45892",
    "sg:province":"Nordrhein-Westfalen",
    "wof:name":"A. Atadinc",
    "wof:placetype":"venue"
},
  "geometry": {"coordinates":[7.1064348221,51.5816917419],"type":"Point"}
}