{
  "type": "Feature",
  "properties": {
    "iso:country":"DE",
    "sg:address":"Dieselstr. 5",
    "sg:city":"Anr\u00f6chte",
    "sg:phone":"+49 4929/47247",
    "sg:postcode":"59609",
    "sg:province":"Nordrhein-Westfalen",
    "wof:name":"Fleischereinkauf Lippstadt Soestsauerland Eingetragene Genossenschaft Ag",
    "wof:placetype":"venue"
},
  "geometry": {"coordinates":[8.3094491959,51.5660171509],"type":"Point"}
}