{
  "type": "Feature",
  "properties": {
    "iso:country":"DE",
    "sg:address":"H\u00fclsbergstr. 153",
    "sg:city":"Marl",
    "sg:phone":"+49 2365/61561",
    "sg:postcode":"45772",
    "sg:province":"Nordrhein-Westfalen",
    "wof:name":"Westermann Verwaltungs-gmbh",
    "wof:placetype":"venue"
},
  "geometry": {"coordinates":[7.1550049782,51.6627235413],"type":"Point"}
}