{
  "type": "Feature",
  "properties": {
    "iso:country":"DE",
    "sg:address":"Von Eichendorfring 1",
    "sg:city":"Handorf",
    "sg:postcode":"31226",
    "sg:province":"Niedersachsen",
    "wof:name":"Bequemes Shopping Von Zu Hause",
    "wof:placetype":"venue"
},
  "geometry": {"coordinates":[10.215369,52.292622],"type":"Point"}
}