{
  "type": "Feature",
  "properties": {
    "iso:country":"DE",
    "sg:address":"Carnotstr. 7",
    "sg:city":"Berlin",
    "sg:phone":"+49 30/2830820",
    "sg:postcode":"10587",
    "sg:province":"Berlin",
    "wof:name":"Bgkk Architektur Und Generalplanung",
    "wof:placetype":"venue"
},
  "geometry": {"coordinates":[13.319355,52.522533],"type":"Point"}
}