{
  "type": "Feature",
  "properties": {
    "iso:country":"DE",
    "sg:address":"Rabenhof 74",
    "sg:city":"Bielefeld",
    "sg:phone":"+49 521/72728",
    "sg:postcode":"33609",
    "sg:province":"Nordrhein-Westfalen",
    "wof:name":"Apotheke Am Rabenhof",
    "wof:placetype":"venue"
},
  "geometry": {"coordinates":[8.595019,52.050869],"type":"Point"}
}