{
  "type": "Feature",
  "properties": {
    "iso:country":"DE",
    "sg:address":"N\u00fcrnberger Str. 11a",
    "sg:city":"Ro\u00dftal",
    "sg:phone":"+49 9127/579468",
    "sg:postcode":"90574",
    "sg:province":"Bayern",
    "wof:name":"Harald B\u00fcttner Rechtsanwalt",
    "wof:placetype":"venue"
},
  "geometry": {"coordinates":[10.8868122101,49.3981552124],"type":"Point"}
}