{
  "type": "Feature",
  "properties": {
    "iso:country":"DE",
    "sg:address":"Norderhofenden 2",
    "sg:city":"Flensburg",
    "sg:phone":"+49 461/23415",
    "sg:postcode":"24937",
    "sg:province":"Schleswig-Holstein",
    "wof:name":"Tanzlokal Sasa Monika R\u00fcnzel",
    "wof:placetype":"venue"
},
  "geometry": {"coordinates":[9.436304,54.787033],"type":"Point"}
}