{
  "type": "Feature",
  "properties": {
    "iso:country":"DE",
    "sg:address":"Breite Str. 23",
    "sg:city":"Aschersleben",
    "sg:phone":"+49 34741/8220",
    "sg:postcode":"06449",
    "sg:province":"Sachsen-Anhalt",
    "wof:name":"Agrargenossengeschaft Neu K\u00f6nigsaue Eg",
    "wof:placetype":"venue"
},
  "geometry": {"coordinates":[11.458854,51.75375],"type":"Point"}
}