{
  "type": "Feature",
  "properties": {
    "iso:country":"DE",
    "sg:address":"Eichenweg 1",
    "sg:city":"Berga",
    "sg:phone":"+49 34651/49890",
    "sg:postcode":"06536",
    "sg:province":"Sachsen-Anhalt",
    "wof:name":"Mgw Stra\u00dfen- Tiefbau- Und Pflasterarbeiten",
    "wof:placetype":"venue"
},
  "geometry": {"coordinates":[11.0184249878,51.4570808411],"type":"Point"}
}