{
  "type": "Feature",
  "properties": {
    "iso:country":"DE",
    "sg:address":"Druffeler Str. 201",
    "sg:city":"Rietberg",
    "sg:phone":"+49 5244/5210",
    "sg:postcode":"33397",
    "sg:province":"Nordrhein-Westfalen",
    "wof:name":"Hedwig Theising",
    "wof:placetype":"venue"
},
  "geometry": {"coordinates":[8.3951034546,51.8266105652],"type":"Point"}
}