{
  "type": "Feature",
  "properties": {
    "iso:country":"DE",
    "sg:address":"Auf dem Dahlacker 76",
    "sg:city":"Bochum",
    "sg:phone":"+49 234/853793",
    "sg:postcode":"44809",
    "sg:province":"Nordrhein-Westfalen",
    "wof:name":"Rainer Kruip Fahrdienst F\u00fcr Medizinisches Probengut Gmbh",
    "wof:placetype":"venue"
},
  "geometry": {"coordinates":[7.203975,51.505863],"type":"Point"}
}