{
  "type": "Feature",
  "properties": {
    "iso:country":"DE",
    "sg:address":"ADW 16",
    "sg:city":"Osterburg",
    "sg:phone":"+49 3937/895361",
    "sg:postcode":"39606",
    "sg:province":"Sachsen-Anhalt",
    "wof:name":"Marlies Panitz",
    "wof:placetype":"venue"
},
  "geometry": {"coordinates":[11.75236,52.791275],"type":"Point"}
}