{
  "type": "Feature",
  "properties": {
    "iso:country":"DE",
    "sg:address":"Adalbert-Stifter-Str. 19",
    "sg:city":"Kr\u00fcn",
    "sg:phone":"+49 8825/1305",
    "sg:postcode":"82494",
    "sg:province":"Bayern",
    "wof:name":"G\u00e4stehaus Johann Niederl",
    "wof:placetype":"venue"
},
  "geometry": {"coordinates":[11.2788467407,47.4992141724],"type":"Point"}
}