{
  "type": "Feature",
  "properties": {
    "iso:country":"DE",
    "sg:address":"Kreuzjochstr. 4 A",
    "sg:city":"M\u00fcnchen",
    "sg:phone":"+49 89/434856",
    "sg:postcode":"81825",
    "sg:province":"Bayern",
    "wof:name":"Acs Flugzeugvermietung Gmbh",
    "wof:placetype":"venue"
},
  "geometry": {"coordinates":[11.6448040009,48.1218261719],"type":"Point"}
}