{
  "type": "Feature",
  "properties": {
    "iso:country":"DE",
    "sg:address":"S\u00e4ggasse 12",
    "sg:city":"Bad T\u00f6lz",
    "sg:phone":"+49 8041/5562",
    "sg:postcode":"83646",
    "sg:province":"Bayern",
    "wof:name":"Impetex Handelsges. Mbh",
    "wof:placetype":"venue"
},
  "geometry": {"coordinates":[11.5586481094,47.7616081238],"type":"Point"}
}