{
  "type": "Feature",
  "properties": {
    "iso:country":"DE",
    "sg:address":"Haselbach 2",
    "sg:city":"Velden",
    "sg:phone":"+49 8742/470",
    "sg:postcode":"84149",
    "sg:province":"Bayern",
    "wof:name":"Georg Schmidhuber",
    "wof:placetype":"venue"
},
  "geometry": {"coordinates":[12.3086099625,48.3937568665],"type":"Point"}
}