{
  "type": "Feature",
  "properties": {
    "iso:country":"DE",
    "sg:address":"Bei der Klosterkirche 2",
    "sg:city":"Wismar",
    "sg:phone":"+49 3841/613202",
    "sg:postcode":"23966",
    "sg:province":"Mecklenburg-Vorpommern",
    "wof:name":"Klostercafe Inh. Rainer Manthei",
    "wof:placetype":"venue"
},
  "geometry": {"coordinates":[11.465783,53.889507],"type":"Point"}
}