{
  "type": "Feature",
  "properties": {
    "iso:country":"DE",
    "sg:address":"Kegelbahnstr. 3",
    "sg:city":"Reipoltskirchen",
    "sg:phone":"+49 6364/8000",
    "sg:postcode":"67753",
    "sg:province":"Rheinland-Pfalz",
    "wof:name":"M. Und U. Draeger",
    "wof:placetype":"venue"
},
  "geometry": {"coordinates":[7.663621,49.63419],"type":"Point"}
}