{
  "type": "Feature",
  "properties": {
    "iso:country":"DE",
    "sg:address":"Talstr. 12",
    "sg:city":"Ha\u00dffurt",
    "sg:phone":"+49 9521/3849",
    "sg:postcode":"97437",
    "sg:province":"Bayern",
    "wof:name":"Katholische Arbeiterbewegung Sylbach",
    "wof:placetype":"venue"
},
  "geometry": {"coordinates":[10.5232563019,50.0481033325],"type":"Point"}
}