{
  "type": "Feature",
  "properties": {
    "iso:country":"DE",
    "sg:address":"Hauptstr. 2",
    "sg:city":"Dohren",
    "sg:phone":"+49 5962/669",
    "sg:postcode":"49770",
    "sg:province":"Niedersachsen",
    "wof:name":"Gastst\u00e4tte B. Frericks",
    "wof:placetype":"venue"
},
  "geometry": {"coordinates":[7.5846037865,52.645450592],"type":"Point"}
}