{
  "type": "Feature",
  "properties": {
    "iso:country":"DE",
    "sg:address":"Silcherstr. 7",
    "sg:city":"Esslingen",
    "sg:phone":"+49 711/3167911",
    "sg:postcode":"73730",
    "sg:province":"Baden-W\u00fcrttemberg",
    "wof:name":"Ursula Wieland",
    "wof:placetype":"venue"
},
  "geometry": {"coordinates":[9.321849,48.735844],"type":"Point"}
}