{
  "type": "Feature",
  "properties": {
    "iso:country":"DE",
    "sg:address":"Detmolder Str. 556",
    "sg:city":"Bielefeld",
    "sg:phone":"+49 521/201195",
    "sg:postcode":"33699",
    "sg:province":"Nordrhein-Westfalen",
    "wof:name":"W. Kuhlmann Haus- Und K\u00fcchenger\u00e4te",
    "wof:placetype":"venue"
},
  "geometry": {"coordinates":[8.6046447754,51.9934654236],"type":"Point"}
}