{
  "type": "Feature",
  "properties": {
    "iso:country":"DE",
    "sg:address":"Waldmeisterstr. 4",
    "sg:city":"Gro\u00dfkarolinenfeld",
    "sg:phone":"+49 8031/50994",
    "sg:postcode":"83109",
    "sg:province":"Bayern",
    "wof:name":"John Barker Entertainment",
    "wof:placetype":"venue"
},
  "geometry": {"coordinates":[12.089624,47.887421],"type":"Point"}
}