{
  "type": "Feature",
  "properties": {
    "iso:country":"DE",
    "sg:address":"Bahnhofstr. 5",
    "sg:city":"Eiterfeld",
    "sg:phone":"+49 6672/7530",
    "sg:postcode":"36132",
    "sg:province":"Hessen",
    "wof:name":"Karl Bock",
    "wof:placetype":"venue"
},
  "geometry": {"coordinates":[9.798538,50.760994],"type":"Point"}
}