{
  "type": "Feature",
  "properties": {
    "iso:country":"DE",
    "sg:address":"Gr\u00f6nerstr. 48",
    "sg:city":"Ludwigsburg",
    "sg:phone":"+49 7141/97910",
    "sg:postcode":"71636",
    "sg:province":"Baden-W\u00fcrttemberg",
    "wof:name":"Mht Verwaltungs Gmbh",
    "wof:placetype":"venue"
},
  "geometry": {"coordinates":[9.165555954,48.8931121826],"type":"Point"}
}