{
  "type": "Feature",
  "properties": {
    "iso:country":"DE",
    "sg:address":"Otto-Hahn-Str. 7a",
    "sg:city":"Baesweiler",
    "sg:phone":"+49 2401/801386",
    "sg:postcode":"52499",
    "sg:province":"Nordrhein-Westfalen",
    "wof:name":"Preiswerter Bastelbedarf Bei Bastelcity",
    "wof:placetype":"venue"
},
  "geometry": {"coordinates":[6.188017,50.909939],"type":"Point"}
}