{
  "type": "Feature",
  "properties": {
    "iso:country":"DE",
    "sg:address":"Steinfelder Str. 43",
    "sg:city":"Lohne",
    "sg:phone":"+49 4442/1488",
    "sg:postcode":"49393",
    "sg:province":"Niedersachsen",
    "wof:name":"Theodor Thole",
    "wof:placetype":"venue"
},
  "geometry": {"coordinates":[8.22495,52.661289],"type":"Point"}
}