{
  "type": "Feature",
  "properties": {
    "iso:country":"DE",
    "sg:address":"Willemerstr. 11",
    "sg:city":"Frankfurt",
    "sg:phone":"+49 69/616437",
    "sg:postcode":"60594",
    "sg:province":"Hessen",
    "wof:name":"Apfelwein-dax",
    "wof:placetype":"venue"
},
  "geometry": {"coordinates":[8.6921062469,50.1044654846],"type":"Point"}
}