{
  "type": "Feature",
  "properties": {
    "iso:country":"DE",
    "sg:address":"Franz-Lenz-Str. 6",
    "sg:city":"Osnabr\u00fcck",
    "sg:phone":"+49 541/801353",
    "sg:postcode":"49084",
    "sg:province":"Niedersachsen",
    "wof:name":"Skv Vermittlungsgesellschaft F\u00fcr Kapitalanlagen-mbh",
    "wof:placetype":"venue"
},
  "geometry": {"coordinates":[8.0813083649,52.2765922546],"type":"Point"}
}