{
  "type": "Feature",
  "properties": {
    "iso:country":"DE",
    "sg:address":"Starenweg 94",
    "sg:city":"Braunschweig",
    "sg:phone":"+49 531/873938",
    "sg:postcode":"38122",
    "sg:province":"Niedersachsen",
    "wof:name":"Monika Liersch",
    "wof:placetype":"venue"
},
  "geometry": {"coordinates":[10.4801292419,52.2317352295],"type":"Point"}
}