{
  "type": "Feature",
  "properties": {
    "iso:country":"DE",
    "sg:address":"Schulstr. 10",
    "sg:city":"R\u00fcdenau",
    "sg:phone":"+49 9371/3275",
    "sg:postcode":"63924",
    "sg:province":"Bayern",
    "wof:name":"Gastst\u00e4tte Karl-h. Schneider",
    "wof:placetype":"venue"
},
  "geometry": {"coordinates":[9.1786680222,49.7129211426],"type":"Point"}
}