{
  "type": "Feature",
  "properties": {
    "iso:country":"DE",
    "sg:address":"Am Langen Lande 4",
    "sg:city":"Rehden",
    "sg:phone":"+49 5446/903113",
    "sg:postcode":"49453",
    "sg:province":"Niedersachsen",
    "wof:name":"L\u00fchrs Ger\u00e4tebau Gmbh",
    "wof:placetype":"venue"
},
  "geometry": {"coordinates":[8.502907,52.618626],"type":"Point"}
}