{
  "type": "Feature",
  "properties": {
    "iso:country":"DE",
    "sg:address":"Lindengasse 14",
    "sg:city":"Alheim",
    "sg:postcode":"36211",
    "sg:province":"Hessen",
    "wof:name":"Rulle Holzhandlung Maria Grip E. Kfr.",
    "wof:placetype":"venue"
},
  "geometry": {"coordinates":[9.6700201035,51.0239372253],"type":"Point"}
}