{
  "type": "Feature",
  "properties": {
    "iso:country":"DE",
    "sg:address":"Ortsstr. 3",
    "sg:city":"Tiefenbach",
    "sg:postcode":"84184",
    "sg:province":"Bayern",
    "wof:name":"H\u00e4ring Veranstaltungs Gmbh",
    "wof:placetype":"venue"
},
  "geometry": {"coordinates":[12.1308870316,48.5058288574],"type":"Point"}
}