{
  "type": "Feature",
  "properties": {
    "iso:country":"DE",
    "sg:address":"Hochwaldstr. 1",
    "sg:city":"Rottweil",
    "sg:phone":"+49 741/8971",
    "sg:postcode":"78628",
    "sg:province":"Baden-W\u00fcrttemberg",
    "wof:name":"Spanischer B\u00fcrgerverein Francisco Delgado",
    "wof:placetype":"venue"
},
  "geometry": {"coordinates":[8.5521583557,48.1971244812],"type":"Point"}
}