{
  "type": "Feature",
  "properties": {
    "iso:country":"DE",
    "sg:address":"Am Schneiderberg 2a",
    "sg:city":"Bodenwerder",
    "sg:phone":"+49 5533/2770",
    "sg:postcode":"37619",
    "sg:province":"Niedersachsen",
    "wof:name":"Roswitha Schumacher",
    "wof:placetype":"venue"
},
  "geometry": {"coordinates":[9.51932,51.969955],"type":"Point"}
}