{
  "type": "Feature",
  "properties": {
    "iso:country":"DE",
    "sg:address":"Stummstr. 19",
    "sg:city":"Neunkirchen",
    "sg:phone":"+49 6821/13836",
    "sg:postcode":"66538",
    "sg:province":"Saarland",
    "wof:name":"City-polster Handels Gmbh",
    "wof:placetype":"venue"
},
  "geometry": {"coordinates":[7.1752510071,49.3469924927],"type":"Point"}
}