{
  "type": "Feature",
  "properties": {
    "iso:country":"DE",
    "sg:address":"Rheinstr. 36",
    "sg:city":"Rastatt",
    "sg:phone":"+49 7222/26627",
    "sg:postcode":"76437",
    "sg:province":"Baden-W\u00fcrttemberg",
    "wof:name":"Kath. Pfarramt St. \u00c4gidius",
    "wof:placetype":"venue"
},
  "geometry": {"coordinates":[8.1546373367,48.8612098694],"type":"Point"}
}