{
  "type": "Feature",
  "properties": {
    "iso:country":"DE",
    "sg:address":"Molkereistr. 10",
    "sg:city":"Dortmund",
    "sg:phone":"+49 231/335032",
    "sg:postcode":"44359",
    "sg:province":"Nordrhein-Westfalen",
    "wof:name":"P. Seligmann",
    "wof:placetype":"venue"
},
  "geometry": {"coordinates":[7.376783,51.570705],"type":"Point"}
}