{
  "type": "Feature",
  "properties": {
    "iso:country":"DE",
    "sg:address":"Am Schacht 12",
    "sg:city":"G\u00f6llingen",
    "sg:phone":"+49 34671/78942",
    "sg:postcode":"06567",
    "sg:province":"Th\u00fcringen",
    "wof:name":"Dr.-ing. Fritz Hengelhaupt",
    "wof:placetype":"venue"
},
  "geometry": {"coordinates":[10.996408,51.33754],"type":"Point"}
}