{
  "type": "Feature",
  "properties": {
    "iso:country":"DE",
    "sg:address":"Friesenwall 35",
    "sg:city":"K\u00f6ln",
    "sg:phone":"+49 221/254548",
    "sg:postcode":"50672",
    "sg:province":"Nordrhein-Westfalen",
    "wof:name":"W. G. Herr Versteigerer",
    "wof:placetype":"venue"
},
  "geometry": {"coordinates":[6.940639019,50.9389190674],"type":"Point"}
}