{
  "type": "Feature",
  "properties": {
    "iso:country":"DE",
    "sg:address":"Daimlerstr. 12",
    "sg:city":"Malsch",
    "sg:postcode":"76316",
    "sg:province":"Baden-W\u00fcrttemberg",
    "wof:name":"Rvz Reha - Vertriebs- Zentrum Gmbh",
    "wof:placetype":"venue"
},
  "geometry": {"coordinates":[8.313162,48.891491],"type":"Point"}
}