{
  "type": "Feature",
  "properties": {
    "iso:country":"DE",
    "sg:address":"Kr\u00f6tenweg 53",
    "sg:city":"Stuttgart",
    "sg:phone":"+49 711/8600412",
    "sg:postcode":"70499",
    "sg:province":"Baden-W\u00fcrttemberg",
    "wof:name":"Seeger Edv Kg",
    "wof:placetype":"venue"
},
  "geometry": {"coordinates":[9.087609,48.803356],"type":"Point"}
}