{
  "type": "Feature",
  "properties": {
    "iso:country":"DE",
    "sg:address":"Sieltiefsweg 9",
    "sg:city":"Butjadingen",
    "sg:phone":"+49 4733/1002",
    "sg:postcode":"26969",
    "sg:province":"Niedersachsen",
    "wof:name":"Ev. Pfarramt Waddens",
    "wof:placetype":"venue"
},
  "geometry": {"coordinates":[8.4136734009,53.5316467285],"type":"Point"}
}