{
  "type": "Feature",
  "properties": {
    "iso:country":"DE",
    "sg:address":"Drehbahn 15-23",
    "sg:city":"Hamburg",
    "sg:phone":"+49 40/354626",
    "sg:postcode":"20354",
    "sg:province":"Hamburg",
    "wof:name":"A. Kistenbr\u00fcgger",
    "wof:placetype":"venue"
},
  "geometry": {"coordinates":[9.985706,53.556454],"type":"Point"}
}