{
  "type": "Feature",
  "properties": {
    "iso:country":"DE",
    "sg:address":"Am Trieb 1",
    "sg:city":"Sonnenb\u00fchl",
    "sg:phone":"+49 4979/75274",
    "sg:postcode":"72820",
    "sg:province":"Baden-W\u00fcrttemberg",
    "wof:name":"Wilhelm H\u00c4gele Kg",
    "wof:placetype":"venue"
},
  "geometry": {"coordinates":[9.8735876083,48.9277534485],"type":"Point"}
}