{
  "type": "Feature",
  "properties": {
    "iso:country":"DE",
    "sg:address":"Freudenst\u00e4dter Str. 60",
    "sg:city":"Seewald",
    "sg:phone":"+49 7447/2800",
    "sg:postcode":"72297",
    "sg:province":"Baden-W\u00fcrttemberg",
    "wof:name":"Hotel Oberwiesenhof",
    "wof:placetype":"venue"
},
  "geometry": {"coordinates":[8.41817379,48.5912513733],"type":"Point"}
}