{
  "type": "Feature",
  "properties": {
    "iso:country":"DE",
    "sg:address":"Von-Itter-Platz 7",
    "sg:city":"Krefeld",
    "sg:phone":"+49 2151/27560",
    "sg:postcode":"47798",
    "sg:province":"Nordrhein-Westfalen",
    "wof:name":"Katholisches Pfarramt Liebfrauen",
    "wof:placetype":"venue"
},
  "geometry": {"coordinates":[6.5565829277,51.3379554749],"type":"Point"}
}