{
  "type": "Feature",
  "properties": {
    "iso:country":"DE",
    "sg:address":"Nickweilerer Str.",
    "sg:city":"Nannhausen",
    "sg:phone":"+49 6761/5118",
    "sg:postcode":"55469",
    "sg:province":"Rheinland-Pfalz",
    "wof:name":"H. Augustin",
    "wof:placetype":"venue"
},
  "geometry": {"coordinates":[7.478243,49.974392],"type":"Point"}
}