{
  "type": "Feature",
  "properties": {
    "iso:country":"DE",
    "sg:address":"K\u00f6niginhofstr. 97",
    "sg:city":"Kassel",
    "sg:phone":"+49 561/507140",
    "sg:postcode":"34123",
    "sg:province":"Hessen",
    "wof:name":"Karl-heinz Backmeyer Gmbh & Co. Kg",
    "wof:placetype":"venue"
},
  "geometry": {"coordinates":[9.5257387161,51.3110542297],"type":"Point"}
}