{
  "type": "Feature",
  "properties": {
    "iso:country":"DE",
    "sg:address":"Schuhmarkt 1",
    "sg:city":"Parchim",
    "sg:phone":"+49 3871",
    "sg:postcode":"19370",
    "sg:province":"Mecklenburg-Vorpommern",
    "wof:name":"Die Stadt Parchim Im Internet",
    "wof:placetype":"venue"
},
  "geometry": {"coordinates":[11.848151,53.427299],"type":"Point"}
}