{
  "type": "Feature",
  "properties": {
    "iso:country":"DE",
    "sg:address":"Von-Alten-Str. 12",
    "sg:city":"Burgwedel",
    "sg:phone":"+49 5139/5734",
    "sg:postcode":"30938",
    "sg:province":"Niedersachsen",
    "wof:name":"Gisela Scholz",
    "wof:placetype":"venue"
},
  "geometry": {"coordinates":[9.859107,52.492878],"type":"Point"}
}