{
  "type": "Feature",
  "properties": {
    "iso:country":"DE",
    "sg:address":"Fritz-Reuter-Str. 12",
    "sg:city":"Prislich",
    "sg:phone":"+49 38756/22846",
    "sg:postcode":"19300",
    "sg:province":"Mecklenburg-Vorpommern",
    "wof:name":"Volker Harm",
    "wof:placetype":"venue"
},
  "geometry": {"coordinates":[11.622786,53.270214],"type":"Point"}
}