{
  "type": "Feature",
  "properties": {
    "iso:country":"DE",
    "sg:address":"Mainzer Str. 2",
    "sg:city":"Wackernheim",
    "sg:phone":"+49 6132/57010",
    "sg:postcode":"55263",
    "sg:province":"Rheinland-Pfalz",
    "wof:name":"Wackernheimer Hof",
    "wof:placetype":"venue"
},
  "geometry": {"coordinates":[8.1198892593,49.9783401489],"type":"Point"}
}