{
  "type": "Feature",
  "properties": {
    "iso:country":"DE",
    "sg:address":"Im Alten Berge 5-7",
    "sg:city":"Remscheid",
    "sg:phone":"+49 2191/62395",
    "sg:postcode":"42897",
    "sg:province":"Nordrhein-Westfalen",
    "wof:name":"Schlosserei Uwe Link",
    "wof:placetype":"venue"
},
  "geometry": {"coordinates":[7.25468,51.174641],"type":"Point"}
}