{
  "type": "Feature",
  "properties": {
    "iso:country":"DE",
    "sg:address":"Rendsburger Str. 59",
    "sg:city":"Neum\u00fcnster",
    "sg:phone":"+49 4321/14900",
    "sg:postcode":"24534",
    "sg:province":"Schleswig-Holstein",
    "wof:name":"Prasse Tanzschule",
    "wof:placetype":"venue"
},
  "geometry": {"coordinates":[9.9789171219,54.0816612244],"type":"Point"}
}