{
  "type": "Feature",
  "properties": {
    "iso:country":"DE",
    "sg:address":"An den Steinbr\u00fcchen 4",
    "sg:city":"Bautzen",
    "sg:phone":"+49 3591/23780",
    "sg:postcode":"02625",
    "sg:province":"Sachsen",
    "wof:name":"Anita Mieth",
    "wof:placetype":"venue"
},
  "geometry": {"coordinates":[14.4637422562,51.2021942139],"type":"Point"}
}