{
  "type": "Feature",
  "properties": {
    "iso:country":"DE",
    "sg:address":"Obersh\u00e4user Platz 1",
    "sg:city":"Meiningen",
    "sg:phone":"+49 3693/485259",
    "sg:postcode":"98617",
    "sg:province":"Th\u00fcringen",
    "wof:name":"Landratsamt Schmalkalden-meiningen",
    "wof:placetype":"venue"
},
  "geometry": {"coordinates":[10.4170341492,50.5928153992],"type":"Point"}
}