{
  "type": "Feature",
  "properties": {
    "iso:country":"DE",
    "sg:address":"Hospitalstr. 4",
    "sg:city":"Schneidlingen",
    "sg:postcode":"39435",
    "sg:province":"Sachsen-Anhalt",
    "wof:name":"Werkstatt Des Evangelischen Katharinenstiftes",
    "wof:placetype":"venue"
},
  "geometry": {"coordinates":[11.4258651733,51.9413108826],"type":"Point"}
}