{
  "type": "Feature",
  "properties": {
    "iso:country":"DE",
    "sg:address":"Paderborner Str. 28",
    "sg:city":"Altenbeken",
    "sg:phone":"+49 5255/930810",
    "sg:postcode":"33184",
    "sg:province":"Nordrhein-Westfalen",
    "wof:name":"Norbert Keuter",
    "wof:placetype":"venue"
},
  "geometry": {"coordinates":[8.9314069748,51.7176132202],"type":"Point"}
}