{
  "type": "Feature",
  "properties": {
    "iso:country":"DE",
    "sg:address":"Schillerstr. 15",
    "sg:city":"Limburgerhof",
    "sg:postcode":"67117",
    "sg:province":"Rheinland-Pfalz",
    "wof:name":"Life Und Living Geschenke-vertrieb Gmbh",
    "wof:placetype":"venue"
},
  "geometry": {"coordinates":[8.3860874176,49.4220504761],"type":"Point"}
}