{
  "type": "Feature",
  "properties": {
    "iso:country":"DE",
    "sg:address":"Bendelebener Str. 105 g",
    "sg:city":"Steinthaleben",
    "sg:phone":"+49 34671/50049",
    "sg:postcode":"06567",
    "sg:province":"Th\u00fcringen",
    "wof:name":"Peter Blumenschein",
    "wof:placetype":"venue"
},
  "geometry": {"coordinates":[11.089135,51.355812],"type":"Point"}
}