{
  "type": "Feature",
  "properties": {
    "iso:country":"DE",
    "sg:address":"Viktor-Scheffel-Str. 12",
    "sg:city":"Erfurt",
    "sg:postcode":"99096",
    "sg:province":"Th\u00fcringen",
    "wof:name":"Peter K\u00fchnel",
    "wof:placetype":"venue"
},
  "geometry": {"coordinates":[11.030261,50.961784],"type":"Point"}
}