{
  "type": "Feature",
  "properties": {
    "iso:country":"DE",
    "sg:address":"B\u00fcrgerstr. 34",
    "sg:city":"M\u00fcnchen",
    "sg:phone":"+49 89/980441",
    "sg:postcode":"81925",
    "sg:province":"Bayern",
    "wof:name":"T. V. M\u00fcffling - Ziegaus E. K.",
    "wof:placetype":"venue"
},
  "geometry": {"coordinates":[11.618438,48.164059],"type":"Point"}
}