{
  "type": "Feature",
  "properties": {
    "iso:country":"DE",
    "sg:address":"Moltkestr. 20",
    "sg:city":"Schwelm",
    "sg:phone":"+49 2336/82737",
    "sg:postcode":"58332",
    "sg:province":"Nordrhein-Westfalen",
    "wof:name":"M. Froudarakis",
    "wof:placetype":"venue"
},
  "geometry": {"coordinates":[7.296913147,51.2868995667],"type":"Point"}
}