{
  "type": "Feature",
  "properties": {
    "iso:country":"DE",
    "sg:address":"Marktplatz 3",
    "sg:city":"Hauenstein",
    "sg:phone":"+49 6392/7316",
    "sg:postcode":"76846",
    "sg:province":"Rheinland-Pfalz",
    "wof:name":"J. Becker",
    "wof:placetype":"venue"
},
  "geometry": {"coordinates":[7.854487,49.192329],"type":"Point"}
}