{
  "type": "Feature",
  "properties": {
    "iso:country":"DE",
    "sg:address":"Annastr. 20",
    "sg:city":"M\u00fclheim-K\u00e4rlich",
    "sg:phone":"+49 2630/2556",
    "sg:postcode":"56218",
    "sg:province":"Rheinland-Pfalz",
    "wof:name":"A. Baulig Drescherei",
    "wof:placetype":"venue"
},
  "geometry": {"coordinates":[7.501238,50.390366],"type":"Point"}
}