{
  "type": "Feature",
  "properties": {
    "iso:country":"DE",
    "sg:address":"Friedrichstr. 94",
    "sg:city":"Dortmund",
    "sg:phone":"+49 231/451109",
    "sg:postcode":"44137",
    "sg:province":"Nordrhein-Westfalen",
    "wof:name":"F\u00f6rdergesellschaft Westf\u00e4lische Dlrg Gmbh",
    "wof:placetype":"venue"
},
  "geometry": {"coordinates":[7.4538259506,51.5078430176],"type":"Point"}
}