{
  "type": "Feature",
  "properties": {
    "iso:country":"DE",
    "sg:address":"Bungertstr. 41",
    "sg:city":"Essen",
    "sg:phone":"+49 201/49891",
    "sg:postcode":"45239",
    "sg:province":"Nordrhein-Westfalen",
    "wof:name":"Paletten-service Brigitte M\u00f6nke",
    "wof:placetype":"venue"
},
  "geometry": {"coordinates":[7.003265,51.38728],"type":"Point"}
}