{
  "type": "Feature",
  "properties": {
    "iso:country":"DE",
    "sg:address":"Leberberg 10",
    "sg:city":"Wiesbaden",
    "sg:phone":"+49 4969/5963003",
    "sg:postcode":"65193",
    "sg:province":"Hessen",
    "wof:name":"Rwgk Communications Gmbh",
    "wof:placetype":"venue"
},
  "geometry": {"coordinates":[8.671415,50.123108],"type":"Point"}
}