{
  "type": "Feature",
  "properties": {
    "iso:country":"DE",
    "sg:address":"R\u00f6dernweg 4",
    "sg:city":"Rastatt",
    "sg:postcode":"76437",
    "sg:province":"Baden-W\u00fcrttemberg",
    "wof:name":"Pahl Baukonzepte Ag",
    "wof:placetype":"venue"
},
  "geometry": {"coordinates":[8.209129,48.868191],"type":"Point"}
}