{
  "type": "Feature",
  "properties": {
    "iso:country":"DE",
    "sg:address":"Am Kirchenpfad 2",
    "sg:city":"Welgesheim",
    "sg:phone":"+49 6701/646",
    "sg:postcode":"55576",
    "sg:province":"Rheinland-Pfalz",
    "wof:name":"Rudolf Geib",
    "wof:placetype":"venue"
},
  "geometry": {"coordinates":[7.962969,49.880344],"type":"Point"}
}