{
  "type": "Feature",
  "properties": {
    "iso:country":"DE",
    "sg:address":"Gymnasiumstra\u00dfe 33",
    "sg:city":"Heilbronn",
    "sg:phone":"+49 7131/888666",
    "sg:postcode":"74072",
    "sg:province":"Baden-W\u00fcrttemberg",
    "wof:name":"Fichter, Z\u00fcrn, Kniep Und Kollegen,",
    "wof:placetype":"venue"
},
  "geometry": {"coordinates":[9.223422,49.139984],"type":"Point"}
}