{
  "type": "Feature",
  "properties": {
    "iso:country":"DE",
    "sg:address":"Maximilianstr. 32",
    "sg:city":"Wunsiedel",
    "sg:phone":"+49 9232/6181",
    "sg:postcode":"95632",
    "sg:province":"Bayern",
    "wof:name":"Pfarramt Und Dekanat H. Schmeckenbecher",
    "wof:placetype":"venue"
},
  "geometry": {"coordinates":[12.0040616989,50.0381278992],"type":"Point"}
}