{
  "type": "Feature",
  "properties": {
    "iso:country":"DE",
    "sg:address":"Bunzlauer Str. 6",
    "sg:city":"Bielefeld",
    "sg:phone":"+49 521/200066",
    "sg:postcode":"33719",
    "sg:province":"Nordrhein-Westfalen",
    "wof:name":"Heku-bootsanh\u00e4nger",
    "wof:placetype":"venue"
},
  "geometry": {"coordinates":[8.598548,52.010162],"type":"Point"}
}