{
  "type": "Feature",
  "properties": {
    "iso:country":"DE",
    "sg:address":"Bahnstr. 49",
    "sg:city":"Egelsbach",
    "sg:phone":"+49 6103/49008",
    "sg:postcode":"63329",
    "sg:province":"Hessen",
    "wof:name":"Apotheke Am Bahnhof Gertrud Hertwig E. K.",
    "wof:placetype":"venue"
},
  "geometry": {"coordinates":[8.658345,49.967819],"type":"Point"}
}