{
  "type": "Feature",
  "properties": {
    "iso:country":"DE",
    "sg:address":"Ludwigstr. 2-4",
    "sg:city":"Aschaffenburg",
    "sg:phone":"+49 6021/22211",
    "sg:postcode":"63739",
    "sg:province":"Bayern",
    "wof:name":"Tanzstudio, Peter Van Ettinger",
    "wof:placetype":"venue"
},
  "geometry": {"coordinates":[9.144673,49.980167],"type":"Point"}
}