{
  "type": "Feature",
  "properties": {
    "iso:country":"DE",
    "sg:address":"Karl-Liebknecht-Str. 3",
    "sg:city":"G\u00f6\u00dfnitz",
    "sg:phone":"+49 34493/21617",
    "sg:postcode":"04639",
    "sg:province":"Th\u00fcringen",
    "wof:name":"Rudolf Teller",
    "wof:placetype":"venue"
},
  "geometry": {"coordinates":[12.431584,50.891308],"type":"Point"}
}