{
  "type": "Feature",
  "properties": {
    "iso:country":"DE",
    "sg:address":"Am Rosenberg 51-53",
    "sg:city":"Bremen",
    "sg:phone":"+49 421/459393",
    "sg:postcode":"28207",
    "sg:province":"Bremen",
    "wof:name":"Wiroba Gmbh",
    "wof:placetype":"venue"
},
  "geometry": {"coordinates":[8.873514,53.064426],"type":"Point"}
}