{
  "type": "Feature",
  "properties": {
    "iso:country":"DE",
    "sg:address":"Wackelsbeck 57-59",
    "sg:city":"M\u00fclheim",
    "sg:postcode":"45472",
    "sg:province":"Nordrhein-Westfalen",
    "wof:name":"Pr\u00fcmer Verm\u00f6gensverwaltungs Kg",
    "wof:placetype":"venue"
},
  "geometry": {"coordinates":[6.950336,51.441639],"type":"Point"}
}