{
  "type": "Feature",
  "properties": {
    "iso:country":"DE",
    "sg:address":"S\u00e4ggasse 10",
    "sg:city":"Waakirchen",
    "sg:postcode":"83666",
    "sg:province":"Bayern",
    "wof:name":"Proaktiv Holding Gmbh",
    "wof:placetype":"venue"
},
  "geometry": {"coordinates":[11.68392,47.796207],"type":"Point"}
}