{
  "type": "Feature",
  "properties": {
    "iso:country":"DE",
    "sg:address":"Heinrichstr. 30",
    "sg:city":"Hannover",
    "sg:phone":"+49 511/342223",
    "sg:postcode":"30175",
    "sg:province":"Niedersachsen",
    "wof:name":"Behrens Und Pinkvo\u00df Rechtsanw\u00e4lte Und Notar",
    "wof:placetype":"venue"
},
  "geometry": {"coordinates":[9.7530250549,52.3789596558],"type":"Point"}
}