{
  "type": "Feature",
  "properties": {
    "iso:country":"DE",
    "sg:address":"De-la-Paz-Str. 12 b",
    "sg:city":"M\u00fcnchen",
    "sg:phone":"+49 89/174174",
    "sg:postcode":"80639",
    "sg:province":"Bayern",
    "wof:name":"Karl H. Kraus",
    "wof:placetype":"venue"
},
  "geometry": {"coordinates":[11.5084190369,48.1489868164],"type":"Point"}
}