{
  "type": "Feature",
  "properties": {
    "iso:country":"DE",
    "sg:address":"K\u00f6nigskreuzstr. 51",
    "sg:city":"G\u00f6llheim",
    "sg:phone":"+49 6351/36315",
    "sg:postcode":"67307",
    "sg:province":"Rheinland-Pfalz",
    "wof:name":"Gabys Videothek",
    "wof:placetype":"venue"
},
  "geometry": {"coordinates":[8.0428905487,49.5912857056],"type":"Point"}
}