{
  "type": "Feature",
  "properties": {
    "iso:country":"DE",
    "sg:address":"Dorfbrunnen 5",
    "sg:city":"Nahrendorf",
    "sg:phone":"+49 5855/249",
    "sg:postcode":"21369",
    "sg:province":"Niedersachsen",
    "wof:name":"G. Schneider",
    "wof:placetype":"venue"
},
  "geometry": {"coordinates":[10.814294,53.175579],"type":"Point"}
}