{
  "type": "Feature",
  "properties": {
    "iso:country":"DE",
    "sg:address":"Hellweg 4",
    "sg:city":"Bochum",
    "sg:phone":"+49 234/683391",
    "sg:postcode":"44787",
    "sg:province":"Nordrhein-Westfalen",
    "wof:name":"Cafe Village",
    "wof:placetype":"venue"
},
  "geometry": {"coordinates":[7.220236,51.480259],"type":"Point"}
}