{
  "type": "Feature",
  "properties": {
    "iso:country":"DE",
    "sg:address":"Staufenstr. 30",
    "sg:city":"Traunstein",
    "sg:phone":"+49 861/60542",
    "sg:postcode":"83278",
    "sg:province":"Bayern",
    "wof:name":"Georg Scheiber",
    "wof:placetype":"venue"
},
  "geometry": {"coordinates":[12.623495,47.865009],"type":"Point"}
}