{
  "type": "Feature",
  "properties": {
    "iso:country":"DE",
    "sg:address":"Kliever Str. 19",
    "sg:city":"Anr\u00f6chte",
    "sg:phone":"+49 2947/89240",
    "sg:postcode":"59609",
    "sg:province":"Nordrhein-Westfalen",
    "wof:name":"W. Heither Bedachungs Gmbh",
    "wof:placetype":"venue"
},
  "geometry": {"coordinates":[8.323836,51.560619],"type":"Point"}
}