{
  "type": "Feature",
  "properties": {
    "iso:country":"DE",
    "sg:address":"Bergstr. 22",
    "sg:city":"Holle",
    "sg:phone":"+49 5062/1309",
    "sg:postcode":"31188",
    "sg:province":"Niedersachsen",
    "wof:name":"Ludwig Nagel",
    "wof:placetype":"venue"
},
  "geometry": {"coordinates":[10.1225261688,52.0919570923],"type":"Point"}
}