{
  "type": "Feature",
  "properties": {
    "iso:country":"DE",
    "sg:address":"Oberbeckerweg 34",
    "sg:city":"L\u00fcnen",
    "sg:phone":"+49 2306/370000",
    "sg:postcode":"44532",
    "sg:province":"Nordrhein-Westfalen",
    "wof:name":"Ralf Kaczmarek",
    "wof:placetype":"venue"
},
  "geometry": {"coordinates":[7.5237269402,51.5846099854],"type":"Point"}
}