{
  "type": "Feature",
  "properties": {
    "iso:country":"DE",
    "sg:address":"Helmholtzstr. 20",
    "sg:city":"Essen",
    "sg:phone":"+49 201/6461100",
    "sg:postcode":"45143",
    "sg:province":"Nordrhein-Westfalen",
    "wof:name":"Pizzeria Avanti",
    "wof:placetype":"venue"
},
  "geometry": {"coordinates":[6.9791932106,51.4581794739],"type":"Point"}
}