{
  "type": "Feature",
  "properties": {
    "iso:country":"DE",
    "sg:address":"Kirchstr. 4",
    "sg:city":"Ostrhauderfehn",
    "sg:phone":"+49 4952/5488",
    "sg:postcode":"26842",
    "sg:province":"Niedersachsen",
    "wof:name":"Ev. Pfarramt I Ostrhauderfehn",
    "wof:placetype":"venue"
},
  "geometry": {"coordinates":[7.6194849014,53.1393814087],"type":"Point"}
}