{
  "type": "Feature",
  "properties": {
    "iso:country":"DE",
    "sg:address":"Herkenser Str. 18",
    "sg:city":"Coppenbr\u00fcgge",
    "sg:phone":"+49 5156/1690",
    "sg:postcode":"31863",
    "sg:province":"Niedersachsen",
    "wof:name":"Rudolf D\u00f6rriesfeld",
    "wof:placetype":"venue"
},
  "geometry": {"coordinates":[9.479553,52.13237],"type":"Point"}
}