{
  "type": "Feature",
  "properties": {
    "iso:country":"DE",
    "sg:address":"Melonenstr. 68",
    "sg:city":"Stuttgart",
    "sg:phone":"+49 711/471506",
    "sg:postcode":"70619",
    "sg:province":"Baden-W\u00fcrttemberg",
    "wof:name":"Robert Kappes",
    "wof:placetype":"venue"
},
  "geometry": {"coordinates":[9.2176904678,48.7354240417],"type":"Point"}
}