{
  "type": "Feature",
  "properties": {
    "iso:country":"DE",
    "sg:address":"August-Bier-Str. 31",
    "sg:city":"Bonn",
    "sg:phone":"+49 228/914550",
    "sg:postcode":"53129",
    "sg:province":"Nordrhein-Westfalen",
    "wof:name":"Botschaft Der Slowakischen Republik",
    "wof:placetype":"venue"
},
  "geometry": {"coordinates":[7.1111178398,50.7192993164],"type":"Point"}
}