{
  "type": "Feature",
  "properties": {
    "iso:country":"DE",
    "sg:address":"Erfenschlager Str 165",
    "sg:city":"Chemnitz",
    "sg:phone":"+49 371/523860",
    "sg:postcode":"09125",
    "sg:province":"Sachsen",
    "wof:name":"Lks Luft- U. Klimaservice Christian Israel",
    "wof:placetype":"venue"
},
  "geometry": {"coordinates":[12.94815,50.79071],"type":"Point"}
}