{
  "type": "Feature",
  "properties": {
    "iso:country":"DE",
    "sg:address":"G\u00fcnthersburgallee 38",
    "sg:city":"Frankfurt",
    "sg:phone":"+49 69/441012",
    "sg:postcode":"60316",
    "sg:province":"Hessen",
    "wof:name":"W. Kauffmann-werbe Foto-studio Gmbh",
    "wof:placetype":"venue"
},
  "geometry": {"coordinates":[8.6953907013,50.1249389648],"type":"Point"}
}