{
  "type": "Feature",
  "properties": {
    "iso:country":"DE",
    "sg:address":"Sch\u00f6ngeisinger Str. 15",
    "sg:city":"F\u00fcrstenfeldbruck",
    "sg:phone":"+49 8141/20633",
    "sg:postcode":"82256",
    "sg:province":"Bayern",
    "wof:name":"Alfred Schnalke",
    "wof:placetype":"venue"
},
  "geometry": {"coordinates":[11.2534980774,48.1770935059],"type":"Point"}
}