{
  "type": "Feature",
  "properties": {
    "iso:country":"DE",
    "sg:address":"Hochstr. 102",
    "sg:city":"Wuppertal",
    "sg:phone":"+49 202/442984",
    "sg:postcode":"42105",
    "sg:province":"Nordrhein-Westfalen",
    "wof:name":"Giuseppe Iovini",
    "wof:placetype":"venue"
},
  "geometry": {"coordinates":[7.144157,51.26033],"type":"Point"}
}