{
  "type": "Feature",
  "properties": {
    "iso:country":"DE",
    "sg:address":"Marienstr. 4",
    "sg:city":"Rehau",
    "sg:postcode":"95111",
    "sg:province":"Bayern",
    "wof:name":"Wfc Vertriebs Gmbh",
    "wof:placetype":"venue"
},
  "geometry": {"coordinates":[12.03703022,50.2416496277],"type":"Point"}
}