{
  "type": "Feature",
  "properties": {
    "iso:country":"DE",
    "sg:address":"Karl-Ludwig-Str. 4",
    "sg:city":"Heidelberg",
    "sg:phone":"+49 6221/184867",
    "sg:postcode":"69117",
    "sg:province":"Baden-W\u00fcrttemberg",
    "wof:name":"Stefan Peichl",
    "wof:placetype":"venue"
},
  "geometry": {"coordinates":[8.7016553879,49.4107208252],"type":"Point"}
}