{
  "type": "Feature",
  "properties": {
    "iso:country":"DE",
    "sg:address":"Carl-Zeiss-Str. 39",
    "sg:city":"R\u00f6dermark",
    "sg:phone":"+49 6074/89230",
    "sg:postcode":"63322",
    "sg:province":"Hessen",
    "wof:name":"Freiha Kartensysteme Gmbh",
    "wof:placetype":"venue"
},
  "geometry": {"coordinates":[8.817382,49.966789],"type":"Point"}
}