{
  "type": "Feature",
  "properties": {
    "iso:country":"DE",
    "sg:address":"Grand Centre Ring 12/4",
    "sg:city":"H\u00fcgelsheim",
    "sg:phone":"+49 7229/181696",
    "sg:postcode":"76549",
    "sg:province":"Baden-W\u00fcrttemberg",
    "wof:name":"Willi Barhofer",
    "wof:placetype":"venue"
},
  "geometry": {"coordinates":[8.1081008911,48.7847938538],"type":"Point"}
}