{
  "type": "Feature",
  "properties": {
    "iso:country":"DE",
    "sg:address":"Ernst-Hugo-Weg 4",
    "sg:city":"Langenhagen",
    "sg:phone":"+49 511/778204",
    "sg:postcode":"30855",
    "sg:province":"Niedersachsen",
    "wof:name":"Eintracht Kr\u00e4henwinkel E. V.",
    "wof:placetype":"venue"
},
  "geometry": {"coordinates":[9.7390851974,52.4713668823],"type":"Point"}
}