{
  "type": "Feature",
  "properties": {
    "iso:country":"DE",
    "sg:address":"Von-Oelhafen-Str. 12",
    "sg:city":"N\u00fcrnberg",
    "sg:phone":"+49 911/343366",
    "sg:postcode":"90425",
    "sg:province":"Bayern",
    "wof:name":"Bernhard Forster",
    "wof:placetype":"venue"
},
  "geometry": {"coordinates":[11.0676279068,49.4724693298],"type":"Point"}
}