{
  "type": "Feature",
  "properties": {
    "iso:country":"DE",
    "sg:address":"Heppenheimer Str. 3",
    "sg:city":"F\u00fcrth",
    "sg:phone":"+49 6253/5006",
    "sg:postcode":"64658",
    "sg:province":"Hessen",
    "wof:name":"Katzenmeier Und Neureuther Rechtsanw\u00e4lte Und Notare",
    "wof:placetype":"venue"
},
  "geometry": {"coordinates":[8.7814674377,49.6504745483],"type":"Point"}
}