{
  "type": "Feature",
  "properties": {
    "iso:country":"DE",
    "sg:address":"Kreuzwiese 7",
    "sg:city":"Neu Anspach",
    "sg:phone":"+49 6081",
    "sg:postcode":"61267",
    "sg:province":"Hessen",
    "wof:name":"Software Zur Abrechnung Von Reisekosten Bbs",
    "wof:placetype":"venue"
},
  "geometry": {"coordinates":[8.503388,50.305401],"type":"Point"}
}