{
  "type": "Feature",
  "properties": {
    "iso:country":"DE",
    "sg:address":"Gewerbeallee 24",
    "sg:city":"M\u00fclheim",
    "sg:phone":"+49 208/53046",
    "sg:postcode":"45478",
    "sg:province":"Nordrhein-Westfalen",
    "wof:name":"Ahles-schemenau Dienst- Leistungs- Und Beratungs Gmbh",
    "wof:placetype":"venue"
},
  "geometry": {"coordinates":[6.8504052162,51.4324836731],"type":"Point"}
}