{
  "type": "Feature",
  "properties": {
    "iso:country":"DE",
    "sg:address":"Waldstr. 34",
    "sg:city":"Birkenheide",
    "sg:phone":"+49 6237/7868",
    "sg:postcode":"67134",
    "sg:province":"Rheinland-Pfalz",
    "wof:name":"Ev. Pfarramt Birkenheide",
    "wof:placetype":"venue"
},
  "geometry": {"coordinates":[8.2651643753,49.4821968079],"type":"Point"}
}