{
  "type": "Feature",
  "properties": {
    "iso:country":"DE",
    "sg:address":"Wachstr.16",
    "sg:city":"Bremen",
    "sg:phone":"+49 421/36841",
    "sg:postcode":"28195",
    "sg:province":"Bremen",
    "wof:name":"Kreditbank-bankverein Ag",
    "wof:placetype":"venue"
},
  "geometry": {"coordinates":[8.806164,53.07415],"type":"Point"}
}