{
  "type": "Feature",
  "properties": {
    "iso:country":"DE",
    "sg:address":"Wilhelm-Leuschner-Str. 53",
    "sg:city":"Papenburg",
    "sg:phone":"+49 4961/4216",
    "sg:postcode":"26871",
    "sg:province":"Niedersachsen",
    "wof:name":"Lothar Breymann",
    "wof:placetype":"venue"
},
  "geometry": {"coordinates":[7.3970050812,53.0863075256],"type":"Point"}
}