{
  "type": "Feature",
  "properties": {
    "iso:country":"DE",
    "sg:address":"Solitudestr. 35",
    "sg:city":"Ludwigsburg",
    "sg:phone":"+49 7141/903260",
    "sg:postcode":"71638",
    "sg:province":"Baden-W\u00fcrttemberg",
    "wof:name":"Cafe Zeitlos",
    "wof:placetype":"venue"
},
  "geometry": {"coordinates":[9.188742,48.891613],"type":"Point"}
}