{
  "type": "Feature",
  "properties": {
    "iso:country":"DE",
    "sg:address":"Hauptstr. 72",
    "sg:city":"E\u00dfweiler",
    "sg:phone":"+49 6304/8402",
    "sg:postcode":"67754",
    "sg:province":"Rheinland-Pfalz",
    "wof:name":"G\u00fcnter Dick",
    "wof:placetype":"venue"
},
  "geometry": {"coordinates":[7.5655698776,49.558013916],"type":"Point"}
}