{
  "type": "Feature",
  "properties": {
    "iso:country":"DE",
    "sg:address":"Augsburger Str. 3",
    "sg:city":"Schongau",
    "sg:postcode":"86956",
    "sg:province":"Bayern",
    "wof:name":"Hanke Bau Gmbh",
    "wof:placetype":"venue"
},
  "geometry": {"coordinates":[10.89467,47.815601],"type":"Point"}
}