{
  "type": "Feature",
  "properties": {
    "iso:country":"DE",
    "sg:address":"Lahder Str. 44",
    "sg:city":"Minden",
    "sg:postcode":"32423",
    "sg:province":"Nordrhein-Westfalen",
    "wof:name":"Christian Bredemeyer Gmbh",
    "wof:placetype":"venue"
},
  "geometry": {"coordinates":[8.935816,52.311234],"type":"Point"}
}