{
  "type": "Feature",
  "properties": {
    "iso:country":"DE",
    "sg:address":"Moorgasse 10",
    "sg:city":"Langg\u00f6ns",
    "sg:phone":"+49 6403/926200",
    "sg:postcode":"35428",
    "sg:province":"Hessen",
    "wof:name":"Stehpizzeria",
    "wof:placetype":"venue"
},
  "geometry": {"coordinates":[8.6619672775,50.4978027344],"type":"Point"}
}