{
  "type": "Feature",
  "properties": {
    "iso:country":"DE",
    "sg:address":"Am See 1",
    "sg:city":"Baar-Ebenhausen",
    "sg:phone":"+49 8453/30844",
    "sg:postcode":"85107",
    "sg:province":"Bayern",
    "wof:name":"Seehaus",
    "wof:placetype":"venue"
},
  "geometry": {"coordinates":[11.4732160568,48.6714172363],"type":"Point"}
}