{
  "type": "Feature",
  "properties": {
    "iso:country":"DE",
    "sg:address":"Sedelfeldberg 34",
    "sg:city":"Friedberg",
    "sg:phone":"+49 821/781182",
    "sg:postcode":"86316",
    "sg:province":"Bayern",
    "wof:name":"Brigitte M\u00fcller Rechtsanw\u00e4ltin",
    "wof:placetype":"venue"
},
  "geometry": {"coordinates":[10.9838018417,48.3909492493],"type":"Point"}
}