{
  "type": "Feature",
  "properties": {
    "iso:country":"DE",
    "sg:address":"K\u00f6nigsheimer Str. 19",
    "sg:city":"Renquishausen",
    "sg:phone":"+49 7429/2864",
    "sg:postcode":"78603",
    "sg:province":"Baden-W\u00fcrttemberg",
    "wof:name":"F. Stehle Chirug. Instrumente",
    "wof:placetype":"venue"
},
  "geometry": {"coordinates":[8.892037,48.083214],"type":"Point"}
}