{
  "type": "Feature",
  "properties": {
    "iso:country":"DE",
    "sg:address":"Zum Heilbach 15",
    "sg:city":"Bad Berleburg",
    "sg:phone":"+49 2759/94430",
    "sg:postcode":"57319",
    "sg:province":"Nordrhein-Westfalen",
    "wof:name":"Tks Helga Treude Inh. Ingrid Kohlert",
    "wof:placetype":"venue"
},
  "geometry": {"coordinates":[8.283254,51.051647],"type":"Point"}
}