{
  "type": "Feature",
  "properties": {
    "iso:country":"DE",
    "sg:address":"Rheingoldstr. 213",
    "sg:city":"Mannheim",
    "sg:phone":"+49 621/8620300",
    "sg:postcode":"68199",
    "sg:province":"Baden-W\u00fcrttemberg",
    "wof:name":"Restaurant Sudpf\u00e4nnchen",
    "wof:placetype":"venue"
},
  "geometry": {"coordinates":[8.4693956375,49.4499282837],"type":"Point"}
}