{
  "type": "Feature",
  "properties": {
    "iso:country":"DE",
    "sg:address":"Hessebergstr. 10",
    "sg:city":"Rosdorf",
    "sg:phone":"+49 5509/1553",
    "sg:postcode":"37124",
    "sg:province":"Niedersachsen",
    "wof:name":"Hans Krippahl",
    "wof:placetype":"venue"
},
  "geometry": {"coordinates":[9.887349,51.469475],"type":"Point"}
}