{
  "type": "Feature",
  "properties": {
    "iso:country":"DE",
    "sg:address":"Siedlungsweg 4",
    "sg:city":"Weyhe",
    "sg:phone":"+49 4203/6429",
    "sg:postcode":"28844",
    "sg:province":"Niedersachsen",
    "wof:name":"Josef Kittl",
    "wof:placetype":"venue"
},
  "geometry": {"coordinates":[8.845312,52.98185],"type":"Point"}
}