{
  "type": "Feature",
  "properties": {
    "iso:country":"DE",
    "sg:address":"Ringstr 1",
    "sg:city":"Borgentreich",
    "sg:phone":"+49 35341/2089",
    "sg:postcode":"34434",
    "sg:province":"Nordrhein-Westfalen",
    "wof:name":"Mitteldeutscher Orgelbau A. Voigt Gmbh",
    "wof:placetype":"venue"
},
  "geometry": {"coordinates":[13.4047298431,51.523399353],"type":"Point"}
}