{
  "type": "Feature",
  "properties": {
    "iso:country":"DE",
    "sg:address":"Im Paradies 2",
    "sg:city":"Memmingen",
    "sg:phone":"+49 8331/80589",
    "sg:postcode":"87700",
    "sg:province":"Bayern",
    "wof:name":"Hans Schuhmaier",
    "wof:placetype":"venue"
},
  "geometry": {"coordinates":[10.1791772842,48.0058822632],"type":"Point"}
}