{
  "type": "Feature",
  "properties": {
    "iso:country":"DE",
    "sg:address":"Marktstr. 2",
    "sg:city":"Buttst\u00e4dt",
    "sg:phone":"+49 36373/40423",
    "sg:postcode":"99628",
    "sg:province":"Th\u00fcringen",
    "wof:name":"Bettenservice Koch",
    "wof:placetype":"venue"
},
  "geometry": {"coordinates":[11.4171047211,51.1211624146],"type":"Point"}
}