{
  "type": "Feature",
  "properties": {
    "iso:country":"DE",
    "sg:address":"Ludwig-Sch\u00fc\u00dfler-Str. 7",
    "sg:city":"Lindenfels",
    "sg:postcode":"64678",
    "sg:province":"Hessen",
    "wof:name":"Lothar Schaller Verm\u00f6gens- Verwaltung Gmbh",
    "wof:placetype":"venue"
},
  "geometry": {"coordinates":[8.7530899048,49.7080001831],"type":"Point"}
}