{
  "type": "Feature",
  "properties": {
    "iso:country":"DE",
    "sg:address":"Herzogspitalstr. 8",
    "sg:city":"M\u00fcnchen",
    "sg:phone":"+49 89/2604013",
    "sg:postcode":"80331",
    "sg:province":"Bayern",
    "wof:name":"Gruppe Ingenieurbau M\u00fcnchen Verwaltungs- Gbr",
    "wof:placetype":"venue"
},
  "geometry": {"coordinates":[11.56834,48.137802],"type":"Point"}
}