{
  "type": "Feature",
  "properties": {
    "iso:country":"DE",
    "sg:address":"Untere Dorfstr. 90b",
    "sg:city":"Hartmannsdorf-Reichenau",
    "sg:postcode":"01762",
    "sg:province":"Sachsen",
    "wof:name":"C. Hennig",
    "wof:placetype":"venue"
},
  "geometry": {"coordinates":[13.567403,50.800251],"type":"Point"}
}