{
  "type": "Feature",
  "properties": {
    "iso:country":"DE",
    "sg:address":"Sch\u00f6nbornstr. 2",
    "sg:city":"Lichtenfels",
    "sg:phone":"+49 9571/6831",
    "sg:postcode":"96215",
    "sg:province":"Bayern",
    "wof:name":"Dr. G\u00fcnther Hauptmann Rechtsanwalt",
    "wof:placetype":"venue"
},
  "geometry": {"coordinates":[11.052936554,50.1552581787],"type":"Point"}
}