{
  "type": "Feature",
  "properties": {
    "iso:country":"DE",
    "sg:address":"Stettiner Str.7",
    "sg:city":"Nordstemmen",
    "sg:phone":"+49 5069",
    "sg:postcode":"31171",
    "sg:province":"Niedersachsen",
    "wof:name":"R\u00f6ssing",
    "wof:placetype":"venue"
},
  "geometry": {"coordinates":[9.814369,52.179417],"type":"Point"}
}