{
  "type": "Feature",
  "properties": {
    "iso:country":"DE",
    "sg:address":"H\u00fcgelstr. 73",
    "sg:city":"Velbert",
    "sg:phone":"+49 2053/5222",
    "sg:postcode":"42553",
    "sg:province":"Nordrhein-Westfalen",
    "wof:name":"Heinrich Oestreich",
    "wof:placetype":"venue"
},
  "geometry": {"coordinates":[7.0877161026,51.3003349304],"type":"Point"}
}