{
  "type": "Feature",
  "properties": {
    "iso:country":"DE",
    "sg:address":"Lange Str. 27",
    "sg:city":"Bad Salzuflen",
    "sg:phone":"+49 5222/59049",
    "sg:postcode":"32105",
    "sg:province":"Nordrhein-Westfalen",
    "wof:name":"Contact Immobilien-gmbh",
    "wof:placetype":"venue"
},
  "geometry": {"coordinates":[8.745571,52.083939],"type":"Point"}
}