{
  "type": "Feature",
  "properties": {
    "iso:country":"DE",
    "sg:address":"Sprottaer Landstr. 1",
    "sg:city":"Eilenburg",
    "sg:phone":"+49 3423/51290",
    "sg:postcode":"04838",
    "sg:province":"Sachsen",
    "wof:name":"Paul Begau",
    "wof:placetype":"venue"
},
  "geometry": {"coordinates":[12.666669,51.471737],"type":"Point"}
}