{
  "type": "Feature",
  "properties": {
    "iso:country":"DE",
    "sg:address":"Hansastr. 54",
    "sg:city":"Ronnenberg",
    "sg:phone":"+49 511/466353",
    "sg:postcode":"30952",
    "sg:province":"Niedersachsen",
    "wof:name":"Bergmannsch\u00e4nke",
    "wof:placetype":"venue"
},
  "geometry": {"coordinates":[9.6507797241,52.3455810547],"type":"Point"}
}