{
  "type": "Feature",
  "properties": {
    "iso:country":"DE",
    "sg:address":"Masurenweg 6",
    "sg:city":"Bielefeld",
    "sg:phone":"+49 521/202796",
    "sg:postcode":"33605",
    "sg:province":"Nordrhein-Westfalen",
    "wof:name":"Mbbl Dr. Bartling Gmbh",
    "wof:placetype":"venue"
},
  "geometry": {"coordinates":[8.590722084,51.9981765747],"type":"Point"}
}