{
  "type": "Feature",
  "properties": {
    "iso:country":"DE",
    "sg:address":"Dachstr. 48",
    "sg:city":"M\u00fcnchen",
    "sg:phone":"+49 89/831459",
    "sg:postcode":"81243",
    "sg:province":"Bayern",
    "wof:name":"Auguste Kreuzer",
    "wof:placetype":"venue"
},
  "geometry": {"coordinates":[11.442408,48.139606],"type":"Point"}
}