{
  "type": "Feature",
  "properties": {
    "iso:country":"DE",
    "sg:address":"Burgstr. 10",
    "sg:city":"Bingen",
    "sg:phone":"+49 6721/41111",
    "sg:postcode":"55411",
    "sg:province":"Rheinland-Pfalz",
    "wof:name":"Hubert Schmidt",
    "wof:placetype":"venue"
},
  "geometry": {"coordinates":[9.255797,48.112572],"type":"Point"}
}