{
  "type": "Feature",
  "properties": {
    "iso:country":"DE",
    "sg:address":"Hergersh\u00e4user Str. 30-32",
    "sg:city":"Babenhausen",
    "sg:postcode":"64832",
    "sg:province":"Hessen",
    "wof:name":"Tewa Gmbh & Co.",
    "wof:placetype":"venue"
},
  "geometry": {"coordinates":[8.926304,49.94862],"type":"Point"}
}