{
  "type": "Feature",
  "properties": {
    "iso:country":"DE",
    "sg:address":"Neue Str. 15",
    "sg:city":"Erlangen",
    "sg:phone":"+49 9131/204538",
    "sg:postcode":"91054",
    "sg:province":"Bayern",
    "wof:name":"Baggers",
    "wof:placetype":"venue"
},
  "geometry": {"coordinates":[11.0058765411,49.6014289856],"type":"Point"}
}