{
  "type": "Feature",
  "properties": {
    "iso:country":"DE",
    "sg:address":"Severinstr. 214 - 218",
    "sg:city":"K\u00f6ln",
    "sg:phone":"+49 221/2014115",
    "sg:postcode":"50676",
    "sg:province":"Nordrhein-Westfalen",
    "wof:name":"Genossenschafts-treuhand Gmbh",
    "wof:placetype":"venue"
},
  "geometry": {"coordinates":[6.9572110176,50.9303207397],"type":"Point"}
}