{
  "type": "Feature",
  "properties": {
    "iso:country":"DE",
    "sg:address":"Lange Wiese 11",
    "sg:city":"Crossen",
    "sg:phone":"+49 36693/4470",
    "sg:postcode":"07613",
    "sg:province":"Th\u00fcringen",
    "wof:name":"Tischlerei Buff Gmbh",
    "wof:placetype":"venue"
},
  "geometry": {"coordinates":[11.981196,50.967789],"type":"Point"}
}