{
  "type": "Feature",
  "properties": {
    "iso:country":"DE",
    "sg:address":"Luisenstr. 3",
    "sg:city":"Weinheim",
    "sg:phone":"+49 6201/67433",
    "sg:postcode":"69469",
    "sg:province":"Baden-W\u00fcrttemberg",
    "wof:name":"Reformhaus Und Naturkost Stein Gmbh",
    "wof:placetype":"venue"
},
  "geometry": {"coordinates":[8.6690788269,49.550617218],"type":"Point"}
}