{
  "type": "Feature",
  "properties": {
    "iso:country":"DE",
    "sg:address":"Niederwaldstr. 43",
    "sg:city":"Wiesbaden",
    "sg:phone":"+49 611/441081",
    "sg:postcode":"65197",
    "sg:province":"Hessen",
    "wof:name":"Ofen Kaus & Co.",
    "wof:placetype":"venue"
},
  "geometry": {"coordinates":[8.2261133194,50.0740623474],"type":"Point"}
}