{
  "type": "Feature",
  "properties": {
    "iso:country":"DE",
    "sg:address":"Frankfurter Str. 33",
    "sg:city":"K\u00f6ln",
    "sg:phone":"+49 221/612025",
    "sg:postcode":"51065",
    "sg:province":"Nordrhein-Westfalen",
    "wof:name":"Heinz Pfeifer Rechtsanwalt",
    "wof:placetype":"venue"
},
  "geometry": {"coordinates":[7.0069589615,50.9607086182],"type":"Point"}
}