{
  "type": "Feature",
  "properties": {
    "iso:country":"DE",
    "sg:address":"Storndorfer Str. 49",
    "sg:city":"Lautertal",
    "sg:phone":"+49 6630/295",
    "sg:postcode":"36369",
    "sg:province":"Hessen",
    "wof:name":"E. Hansel",
    "wof:placetype":"venue"
},
  "geometry": {"coordinates":[9.2535476685,50.6283874512],"type":"Point"}
}