{
  "type": "Feature",
  "properties": {
    "iso:country":"DE",
    "sg:address":"Bahnhofstr. 20",
    "sg:city":"H\u00fcckeswagen",
    "sg:phone":"+49 2192/2003",
    "sg:postcode":"42499",
    "sg:province":"Nordrhein-Westfalen",
    "wof:name":"Peschla Werkzeugmaschinen- Handel Gmbh",
    "wof:placetype":"venue"
},
  "geometry": {"coordinates":[7.342411,51.150822],"type":"Point"}
}