{
  "type": "Feature",
  "properties": {
    "iso:country":"DE",
    "sg:address":"Palmzeile 8b",
    "sg:city":"Berlin",
    "sg:phone":"+49 30/80402514",
    "sg:postcode":"14129",
    "sg:province":"Berlin",
    "wof:name":"Roger N\u00e4big Rechtsanwalt",
    "wof:placetype":"venue"
},
  "geometry": {"coordinates":[13.2084789276,52.4329795837],"type":"Point"}
}