{
  "type": "Feature",
  "properties": {
    "iso:country":"DE",
    "sg:address":"Niederstr. 2",
    "sg:city":"Krefeld",
    "sg:phone":"+49 2151/42708",
    "sg:postcode":"47829",
    "sg:province":"Nordrhein-Westfalen",
    "wof:name":"Blumen Wilhelmus Von Stiphout",
    "wof:placetype":"venue"
},
  "geometry": {"coordinates":[6.649598,51.354309],"type":"Point"}
}