{
  "type": "Feature",
  "properties": {
    "iso:country":"DE",
    "sg:address":"Forbacher Str. 11",
    "sg:city":"Berlin",
    "sg:phone":"+49 30/8112917",
    "sg:postcode":"14169",
    "sg:province":"Berlin",
    "wof:name":"Marva Immobilien",
    "wof:placetype":"venue"
},
  "geometry": {"coordinates":[13.2712049484,52.4409942627],"type":"Point"}
}