{
  "type": "Feature",
  "properties": {
    "iso:country":"DE",
    "sg:address":"Schleusenstr. 5",
    "sg:city":"Lippstadt",
    "sg:phone":"+49 2948/838",
    "sg:postcode":"59558",
    "sg:province":"Nordrhein-Westfalen",
    "wof:name":"Eugen Dahlhoff Architekt",
    "wof:placetype":"venue"
},
  "geometry": {"coordinates":[8.43336,51.690819],"type":"Point"}
}