{
  "type": "Feature",
  "properties": {
    "iso:country":"DE",
    "sg:address":"Rosenstr. 32",
    "sg:city":"L\u00e4gerdorf",
    "sg:phone":"+49 4828/205",
    "sg:postcode":"25566",
    "sg:province":"Schleswig-Holstein",
    "wof:name":"Wilhelm Clausen",
    "wof:placetype":"venue"
},
  "geometry": {"coordinates":[9.57289,53.886101],"type":"Point"}
}