{
  "type": "Feature",
  "properties": {
    "iso:country":"DE",
    "sg:address":"Hauptstr. 215",
    "sg:city":"Gorxheimertal",
    "sg:phone":"+49 6201/23011",
    "sg:postcode":"69517",
    "sg:province":"Hessen",
    "wof:name":"Br\u00fcckner & Partner Gmbh",
    "wof:placetype":"venue"
},
  "geometry": {"coordinates":[8.7281217575,49.5325393677],"type":"Point"}
}