{
  "type": "Feature",
  "properties": {
    "iso:country":"DE",
    "sg:address":"Am Stadtfeld 26",
    "sg:city":"Sch\u00f6nebeck",
    "sg:phone":"+49 3928/69310",
    "sg:postcode":"39218",
    "sg:province":"Sachsen-Anhalt",
    "wof:name":"Alten U. Behinderten Hilfsdienst",
    "wof:placetype":"venue"
},
  "geometry": {"coordinates":[11.724855,52.014915],"type":"Point"}
}