{
  "type": "Feature",
  "properties": {
    "iso:country":"DE",
    "sg:address":"Steigerweg 49",
    "sg:city":"Quierschied",
    "sg:phone":"+49 6897/62875",
    "sg:postcode":"66287",
    "sg:province":"Saarland",
    "wof:name":"Carl Hub",
    "wof:placetype":"venue"
},
  "geometry": {"coordinates":[7.048035,49.329929],"type":"Point"}
}