{
  "type": "Feature",
  "properties": {
    "iso:country":"DE",
    "sg:address":"Ahornweg 9",
    "sg:city":"Empfingen",
    "sg:postcode":"72186",
    "sg:province":"Baden-W\u00fcrttemberg",
    "wof:name":"Areal Immobilien Gmbh",
    "wof:placetype":"venue"
},
  "geometry": {"coordinates":[8.7159166336,48.3927574158],"type":"Point"}
}