{
  "type": "Feature",
  "properties": {
    "iso:country":"DE",
    "sg:address":"Hauptstr. 62",
    "sg:city":"Bedburg-Hau",
    "sg:phone":"+49 2824/92713",
    "sg:postcode":"47551",
    "sg:province":"Nordrhein-Westfalen",
    "wof:name":"Ernst Westerhoff",
    "wof:placetype":"venue"
},
  "geometry": {"coordinates":[6.220259,51.735394],"type":"Point"}
}