{
  "type": "Feature",
  "properties": {
    "iso:country":"DE",
    "sg:address":"Ramsbergstr. 21",
    "sg:city":"Augsburg",
    "sg:phone":"+49 821/402195",
    "sg:postcode":"86156",
    "sg:province":"Bayern",
    "wof:name":"Elfriede Obser",
    "wof:placetype":"venue"
},
  "geometry": {"coordinates":[10.8592300415,48.3797950745],"type":"Point"}
}