{
  "type": "Feature",
  "properties": {
    "iso:country":"DE",
    "sg:address":"K\u00f6nigsbronner Str. 99",
    "sg:city":"Steinheim",
    "sg:phone":"+49 7329/6314",
    "sg:postcode":"89555",
    "sg:province":"Baden-W\u00fcrttemberg",
    "wof:name":"Jakob F\u00e4hnle",
    "wof:placetype":"venue"
},
  "geometry": {"coordinates":[10.071623,48.694996],"type":"Point"}
}