{
  "type": "Feature",
  "properties": {
    "iso:country":"DE",
    "sg:address":"Haidbarg 4 D",
    "sg:city":"Buchholz",
    "sg:phone":"+49 4181/6775",
    "sg:postcode":"21244",
    "sg:province":"Niedersachsen",
    "wof:name":"Ulf-joachim Friese",
    "wof:placetype":"venue"
},
  "geometry": {"coordinates":[9.859173,53.330372],"type":"Point"}
}