{
  "type": "Feature",
  "properties": {
    "iso:country":"DE",
    "sg:address":"Am Dorfplatz 5 a",
    "sg:city":"Tangstedt",
    "sg:phone":"+49 4109/6108",
    "sg:postcode":"22889",
    "sg:province":"Schleswig-Holstein",
    "wof:name":"Programm-text U. Und D. Fetzer Ohg",
    "wof:placetype":"venue"
},
  "geometry": {"coordinates":[10.068369,53.746365],"type":"Point"}
}