{
  "type": "Feature",
  "properties": {
    "iso:country":"DE",
    "sg:address":"Dorfstr. 44 c",
    "sg:city":"Langenhessen",
    "sg:phone":"+49 3761/18120",
    "sg:postcode":"08439",
    "wof:name":"E. Winkle",
    "wof:placetype":"venue"
},
  "geometry": {"coordinates":[12.3747282028,50.7555122375],"type":"Point"}
}