{
  "type": "Feature",
  "properties": {
    "iso:country":"DE",
    "sg:address":"Bieselheider Weg 10 A",
    "sg:city":"Berlin",
    "sg:postcode":"13465",
    "sg:province":"Berlin",
    "wof:name":"Alberts Baugesellschaft Mbh",
    "wof:placetype":"venue"
},
  "geometry": {"coordinates":[13.305876,52.64082],"type":"Point"}
}