{
  "type": "Feature",
  "properties": {
    "iso:country":"DE",
    "sg:address":"Schillerplatz 21",
    "sg:city":"Potsdam",
    "sg:phone":"+49 331/974891",
    "sg:postcode":"14471",
    "sg:province":"Brandenburg",
    "wof:name":"B.-sabine Andert",
    "wof:placetype":"venue"
},
  "geometry": {"coordinates":[13.03751,52.392002],"type":"Point"}
}