{
  "type": "Feature",
  "properties": {
    "iso:country":"DE",
    "sg:address":"Matzenbergstr. 151-153",
    "sg:city":"Oberhausen",
    "sg:phone":"+49 208/676744",
    "sg:postcode":"46145",
    "sg:province":"Nordrhein-Westfalen",
    "wof:name":"Irmgard G\u00fcnther Freizeittechnik",
    "wof:placetype":"venue"
},
  "geometry": {"coordinates":[6.86745,51.547039],"type":"Point"}
}