{
  "type": "Feature",
  "properties": {
    "iso:country":"DE",
    "sg:address":"Luitpoldstr. 208",
    "sg:city":"Ludwigshafen",
    "sg:phone":"+49 621/692346",
    "sg:postcode":"67063",
    "sg:province":"Rheinland-Pfalz",
    "wof:name":"Birgit Und Bernhard Latos Masseure",
    "wof:placetype":"venue"
},
  "geometry": {"coordinates":[8.399301,49.49279],"type":"Point"}
}