{
  "type": "Feature",
  "properties": {
    "iso:country":"DE",
    "sg:address":"Dortmunder Str. 77",
    "sg:city":"Waltrop",
    "sg:phone":"+49 2309/921606",
    "sg:postcode":"45731",
    "sg:province":"Nordrhein-Westfalen",
    "wof:name":"Mbmedia Computersysteme E. K.",
    "wof:placetype":"venue"
},
  "geometry": {"coordinates":[7.405520916,51.6239891052],"type":"Point"}
}