{
  "type": "Feature",
  "properties": {
    "iso:country":"DE",
    "sg:address":"Alte Dorfstr. 4",
    "sg:city":"Vechta",
    "sg:phone":"+49 4447/85971",
    "sg:postcode":"49377",
    "sg:province":"Niedersachsen",
    "wof:name":"Wtv Grundst\u00fccksverwaltung Gmbh",
    "wof:placetype":"venue"
},
  "geometry": {"coordinates":[8.2445707321,52.7812805176],"type":"Point"}
}