{
  "type": "Feature",
  "properties": {
    "iso:country":"DE",
    "sg:address":"\u00c4hrenweg 5",
    "sg:city":"Bayreuth",
    "sg:phone":"+49 9209/9830",
    "sg:postcode":"95448",
    "sg:province":"Bayern",
    "wof:name":"Gr\u00e4ber & Partner Ingenieurb\u00fcro Gmbh",
    "wof:placetype":"venue"
},
  "geometry": {"coordinates":[11.6087198257,49.9083366394],"type":"Point"}
}