{
  "type": "Feature",
  "properties": {
    "iso:country":"DE",
    "sg:address":"K\u00f6nigsbr\u00fccker Landstr. 90",
    "sg:city":"Dresden",
    "sg:phone":"+49 351/4965686",
    "sg:postcode":"01109",
    "sg:province":"Sachsen",
    "wof:name":"Dicon Investitions- Consult Gmbh",
    "wof:placetype":"venue"
},
  "geometry": {"coordinates":[13.7896556854,51.1183662415],"type":"Point"}
}