{
  "type": "Feature",
  "properties": {
    "iso:country":"DE",
    "sg:address":"Ersr\u00f6der Str. 7",
    "sg:city":"Kn\u00fcllwald",
    "sg:phone":"+49 5685/376",
    "sg:postcode":"34593",
    "sg:province":"Hessen",
    "wof:name":"Adam Z\u00fclch & Sohn Beton-und Natursteinwerk",
    "wof:placetype":"venue"
},
  "geometry": {"coordinates":[9.538088,51.005482],"type":"Point"}
}