{
  "type": "Feature",
  "properties": {
    "iso:country":"DE",
    "sg:address":"Kolpingstr. 27",
    "sg:city":"Schwetzingen",
    "sg:postcode":"68723",
    "sg:province":"Baden-W\u00fcrttemberg",
    "wof:name":"R & K Kunststoffe Gmbh",
    "wof:placetype":"venue"
},
  "geometry": {"coordinates":[8.57158,49.37912],"type":"Point"}
}