{
  "type": "Feature",
  "properties": {
    "iso:country":"DE",
    "sg:address":"Paintweg 10",
    "sg:city":"Flo\u00df",
    "sg:phone":"+49 9603",
    "sg:postcode":"92685",
    "sg:province":"Bayern",
    "wof:name":"Sysmotronic Gmbh",
    "wof:placetype":"venue"
},
  "geometry": {"coordinates":[12.2721014023,49.7205123901],"type":"Point"}
}