{
  "type": "Feature",
  "properties": {
    "iso:country":"DE",
    "sg:address":"Tumringer Str. 263",
    "sg:city":"L\u00f6rrach",
    "sg:postcode":"79539",
    "sg:province":"Baden-W\u00fcrttemberg",
    "wof:name":"M. Ziegler Immobilien Gmbh",
    "wof:placetype":"venue"
},
  "geometry": {"coordinates":[7.6594471931,47.6189613342],"type":"Point"}
}