{
  "type": "Feature",
  "properties": {
    "iso:country":"DE",
    "sg:address":"Tucherstr. 4",
    "sg:city":"N\u00fcrnberg",
    "sg:phone":"+49 911/226525",
    "sg:postcode":"90403",
    "sg:province":"Bayern",
    "wof:name":"Oskar Sommer",
    "wof:placetype":"venue"
},
  "geometry": {"coordinates":[11.0797634125,49.4543075562],"type":"Point"}
}