{
  "type": "Feature",
  "properties": {
    "iso:country":"DE",
    "sg:address":"Lerchenauer Str. 158 POSTFACH 450528",
    "sg:city":"M\u00fcnchen",
    "sg:phone":"+49 89/3571550",
    "sg:postcode":"80905",
    "sg:province":"Bayern",
    "wof:name":"M. Saupe & Co. Gmbh",
    "wof:placetype":"venue"
},
  "geometry": {"coordinates":[11.5486459732,48.1922492981],"type":"Point"}
}