{
  "type": "Feature",
  "properties": {
    "iso:country":"DE",
    "sg:address":"Cramerstr. 13",
    "sg:city":"Delmenhorst",
    "sg:phone":"+49 4221/13814",
    "sg:postcode":"27749",
    "sg:province":"Niedersachsen",
    "wof:name":"W. Galle",
    "wof:placetype":"venue"
},
  "geometry": {"coordinates":[8.6348514557,53.0479850769],"type":"Point"}
}