{
  "type": "Feature",
  "properties": {
    "iso:country":"DE",
    "sg:address":"Bollensdorfer Weg 37",
    "sg:city":"Dahlwitz-Hoppegarten",
    "sg:postcode":"15366",
    "sg:province":"Brandenburg",
    "wof:name":"Ilona Lehnert",
    "wof:placetype":"venue"
},
  "geometry": {"coordinates":[13.688965,52.526894],"type":"Point"}
}