{
  "type": "Feature",
  "properties": {
    "iso:country":"DE",
    "sg:address":"Wormser Str. 3",
    "sg:city":"Gau-Odernheim",
    "sg:phone":"+49 6733/507",
    "sg:postcode":"55239",
    "sg:province":"Rheinland-Pfalz",
    "wof:name":"J. Weiskopf",
    "wof:placetype":"venue"
},
  "geometry": {"coordinates":[8.193712,49.7836],"type":"Point"}
}