{
  "type": "Feature",
  "properties": {
    "iso:country":"DE",
    "sg:address":"Von-Gra\u00df-Str. 2 d",
    "sg:city":"Pulheim",
    "sg:phone":"+49 2238/50834",
    "sg:postcode":"50259",
    "sg:province":"Nordrhein-Westfalen",
    "wof:name":"C. Zwenger-r\u00f6hrig",
    "wof:placetype":"venue"
},
  "geometry": {"coordinates":[6.786096096,50.979598999],"type":"Point"}
}