{
  "type": "Feature",
  "properties": {
    "iso:country":"DE",
    "sg:address":"Schleizer Str. 41",
    "sg:city":"Gera",
    "sg:phone":"+49 365/35491",
    "sg:postcode":"07549",
    "sg:province":"Th\u00fcringen",
    "wof:name":"Planen-b\u00f6ttcher",
    "wof:placetype":"venue"
},
  "geometry": {"coordinates":[12.06797,50.848637],"type":"Point"}
}