{
  "type": "Feature",
  "properties": {
    "iso:country":"DE",
    "sg:address":"Viktoriastr. 1",
    "sg:city":"M\u00fcnchen",
    "sg:phone":"+49 89/391222",
    "sg:postcode":"80803",
    "sg:province":"Bayern",
    "wof:name":"Ibv Immobilien Beratungs- Und Vertriebsgesellschaft Mbh",
    "wof:placetype":"venue"
},
  "geometry": {"coordinates":[11.5796451569,48.1622009277],"type":"Point"}
}