{
  "type": "Feature",
  "properties": {
    "iso:country":"DE",
    "sg:address":"Weimarer Str 27",
    "sg:city":"Murrhardt",
    "sg:phone":"+49 7192/20260",
    "sg:postcode":"71540",
    "sg:province":"Baden-W\u00fcrttemberg",
    "wof:name":"Sft Service Gmbh",
    "wof:placetype":"venue"
},
  "geometry": {"coordinates":[9.5577611923,48.9822731018],"type":"Point"}
}