{
  "type": "Feature",
  "properties": {
    "iso:country":"DE",
    "sg:address":"Marcobrunnerstr. 9",
    "sg:city":"Wiesbaden",
    "sg:phone":"+49 611/440266",
    "sg:postcode":"65197",
    "sg:province":"Hessen",
    "wof:name":"Klatsch",
    "wof:placetype":"venue"
},
  "geometry": {"coordinates":[8.226607,50.076855],"type":"Point"}
}