{
  "type": "Feature",
  "properties": {
    "iso:country":"DE",
    "sg:address":"Frankenstr. 145",
    "sg:city":"Essen",
    "sg:postcode":"45134",
    "sg:province":"Nordrhein-Westfalen",
    "wof:name":"Friedhelm Reermann",
    "wof:placetype":"venue"
},
  "geometry": {"coordinates":[7.0399341583,51.424785614],"type":"Point"}
}