{
  "type": "Feature",
  "properties": {
    "iso:country":"DE",
    "sg:address":"Im Krummen Ort 8 b",
    "sg:city":"Ottersberg",
    "sg:postcode":"28870",
    "sg:province":"Niedersachsen",
    "wof:name":"Puga Handels- Und Beteiligungs Gmbh",
    "wof:placetype":"venue"
},
  "geometry": {"coordinates":[9.056487,53.114666],"type":"Point"}
}