{
  "type": "Feature",
  "properties": {
    "iso:country":"DE",
    "sg:address":"Alpenrosenstr. 1",
    "sg:city":"Waakirchen",
    "sg:phone":"+49 8021/448",
    "sg:postcode":"83666",
    "sg:province":"Bayern",
    "wof:name":"Horst Babl Bauunternehmung Verwaltungs Gmbh",
    "wof:placetype":"venue"
},
  "geometry": {"coordinates":[11.6739263535,47.7751159668],"type":"Point"}
}