{
  "type": "Feature",
  "properties": {
    "iso:country":"DE",
    "sg:address":"Rilkestr. 15c",
    "sg:city":"Bovenden",
    "sg:phone":"+49 551/838393",
    "sg:postcode":"37120",
    "sg:province":"Niedersachsen",
    "wof:name":"Joachim Scheuermann Ingenieur",
    "wof:placetype":"venue"
},
  "geometry": {"coordinates":[9.9361114502,51.5961608887],"type":"Point"}
}