{
  "type": "Feature",
  "properties": {
    "iso:country":"DE",
    "sg:address":"Rolander Weg 78",
    "sg:city":"D\u00fcsseldorf",
    "sg:phone":"+49 211/6169110",
    "sg:postcode":"40629",
    "sg:province":"Nordrhein-Westfalen",
    "wof:name":"Mec - Marketing Gmbh",
    "wof:placetype":"venue"
},
  "geometry": {"coordinates":[6.8357849121,51.2536048889],"type":"Point"}
}