{
  "type": "Feature",
  "properties": {
    "iso:country":"DE",
    "sg:address":"Adenauerstr. 8",
    "sg:city":"Konstanz",
    "sg:phone":"+49 7531/44804",
    "sg:postcode":"78465",
    "sg:province":"Baden-W\u00fcrttemberg",
    "wof:name":"Jochen Raabe Ingenieur",
    "wof:placetype":"venue"
},
  "geometry": {"coordinates":[9.1697483063,47.7126350403],"type":"Point"}
}