{
  "type": "Feature",
  "properties": {
    "iso:country":"DE",
    "sg:address":"Dorfstr. 11",
    "sg:city":"Obersch\u00f6negg",
    "sg:phone":"+49 8333/3100",
    "sg:postcode":"87770",
    "sg:province":"Bayern",
    "wof:name":"Ernst Schwegler",
    "wof:placetype":"venue"
},
  "geometry": {"coordinates":[10.2737092972,48.1315841675],"type":"Point"}
}