{
  "type": "Feature",
  "properties": {
    "iso:country":"DE",
    "sg:address":"James-Franck-Ring 9",
    "sg:city":"Ulm",
    "sg:phone":"+49 731/954490",
    "sg:postcode":"89081",
    "sg:province":"Baden-W\u00fcrttemberg",
    "wof:name":"Merck Eurolab Gmbh",
    "wof:placetype":"venue"
},
  "geometry": {"coordinates":[9.956145,48.425426],"type":"Point"}
}