{
  "type": "Feature",
  "properties": {
    "iso:country":"DE",
    "sg:address":"Pulverberg 5",
    "sg:city":"Bremen",
    "sg:phone":"+49 421/641276",
    "sg:postcode":"28239",
    "sg:province":"Bremen",
    "wof:name":"Gehlhaar Dachsanierung Gmbh",
    "wof:placetype":"venue"
},
  "geometry": {"coordinates":[8.727017,53.135887],"type":"Point"}
}