{
  "type": "Feature",
  "properties": {
    "iso:country":"DE",
    "sg:address":"Dorfstr. 1",
    "sg:city":"Moringen",
    "sg:phone":"+49 5554/2392",
    "sg:postcode":"37186",
    "sg:province":"Niedersachsen",
    "wof:name":"Bernd Volger",
    "wof:placetype":"venue"
},
  "geometry": {"coordinates":[9.826594,51.706455],"type":"Point"}
}