{
  "type": "Feature",
  "properties": {
    "iso:country":"DE",
    "sg:address":"Heinrich-Hertz-Str. 8",
    "sg:city":"Donaueschingen",
    "sg:phone":"+49 771/2197",
    "sg:postcode":"78166",
    "sg:province":"Baden-W\u00fcrttemberg",
    "wof:name":"W. Meier Gmbh",
    "wof:placetype":"venue"
},
  "geometry": {"coordinates":[8.5060138702,47.9593200684],"type":"Point"}
}