{
  "type": "Feature",
  "properties": {
    "iso:country":"DE",
    "sg:address":"Westfalenstr. 120",
    "sg:city":"M\u00fcnster",
    "sg:phone":"+49 2501/80060",
    "sg:postcode":"48165",
    "sg:province":"Nordrhein-Westfalen",
    "wof:name":"Hollenhorst Handelsges. Mbh & Co. Kg",
    "wof:placetype":"venue"
},
  "geometry": {"coordinates":[7.632900238,51.9139595032],"type":"Point"}
}