{
  "type": "Feature",
  "properties": {
    "iso:country":"DE",
    "sg:address":"Schierholzstr. 41",
    "sg:city":"Hannover",
    "sg:phone":"+49 511/563256",
    "sg:postcode":"30655",
    "sg:province":"Niedersachsen",
    "wof:name":"R. Mosert",
    "wof:placetype":"venue"
},
  "geometry": {"coordinates":[9.8181018829,52.3997497559],"type":"Point"}
}