{
  "type": "Feature",
  "properties": {
    "iso:country":"DE",
    "sg:address":"Moltkestr. 7",
    "sg:city":"M\u00fchldorf",
    "sg:postcode":"84453",
    "sg:province":"Bayern",
    "wof:name":"Riemann Gmbh",
    "wof:placetype":"venue"
},
  "geometry": {"coordinates":[12.520508,48.246082],"type":"Point"}
}