{
  "type": "Feature",
  "properties": {
    "iso:country":"DE",
    "sg:address":"Weiher\u00e4cker 3",
    "sg:city":"Ubstadt-Weiher",
    "sg:phone":"+49 7253/32587",
    "sg:postcode":"76698",
    "sg:province":"Baden-W\u00fcrttemberg",
    "wof:name":"Karl-heinz Winter",
    "wof:placetype":"venue"
},
  "geometry": {"coordinates":[8.6738853455,49.1813201904],"type":"Point"}
}