{
  "type": "Feature",
  "properties": {
    "iso:country":"DE",
    "sg:address":"Tauentzienstr. 15",
    "sg:city":"Berlin",
    "sg:phone":"+49 30/2350920",
    "sg:postcode":"10789",
    "sg:province":"Berlin",
    "wof:name":"Rechtsanw\u00e4lte Viereck Und Partner",
    "wof:placetype":"venue"
},
  "geometry": {"coordinates":[13.3372602463,52.50365448],"type":"Point"}
}