{
  "type": "Feature",
  "properties": {
    "iso:country":"DE",
    "sg:address":"Steigertsweg",
    "sg:city":"Darmstadt",
    "sg:postcode":"64297",
    "sg:province":"Hessen",
    "wof:name":"Press Verwaltungs Gmbh",
    "wof:placetype":"venue"
},
  "geometry": {"coordinates":[8.6681137085,49.8286323547],"type":"Point"}
}