{
  "type": "Feature",
  "properties": {
    "iso:country":"DE",
    "sg:address":"Weissacher Str. 71",
    "sg:city":"Backnang",
    "sg:phone":"+49 7191/68331",
    "sg:postcode":"71522",
    "sg:province":"Baden-W\u00fcrttemberg",
    "wof:name":"Herbert Ebinger",
    "wof:placetype":"venue"
},
  "geometry": {"coordinates":[9.4461946487,48.9362716675],"type":"Point"}
}