{
  "type": "Feature",
  "properties": {
    "iso:country":"DE",
    "sg:address":"Plochinger Str. 25",
    "sg:city":"Deizisau",
    "sg:phone":"+49 7153/25616",
    "sg:postcode":"73779",
    "sg:province":"Baden-W\u00fcrttemberg",
    "wof:name":"Alois Und Renate Staffl",
    "wof:placetype":"venue"
},
  "geometry": {"coordinates":[9.390652,48.715111],"type":"Point"}
}