{
  "type": "Feature",
  "properties": {
    "iso:country":"DE",
    "sg:address":"Gutenbergstr. 11",
    "sg:city":"Treuchtlingen",
    "sg:phone":"+49 9142/3360",
    "sg:postcode":"91757",
    "sg:province":"Bayern",
    "wof:name":"Thielsch",
    "wof:placetype":"venue"
},
  "geometry": {"coordinates":[10.909191,48.954239],"type":"Point"}
}