{
  "type": "Feature",
  "properties": {
    "iso:country":"DE",
    "sg:address":"Am Karrenberg 10",
    "sg:city":"Neustadt",
    "sg:phone":"+49 3596/502183",
    "sg:postcode":"01844",
    "sg:province":"Sachsen",
    "wof:name":"Fg Fu\u00dfbodenger\u00e4te- Und Maschinenbau Gmbh",
    "wof:placetype":"venue"
},
  "geometry": {"coordinates":[14.183565,51.034164],"type":"Point"}
}