{
  "type": "Feature",
  "properties": {
    "iso:country":"DE",
    "sg:address":"Hauptstr. 6",
    "sg:city":"Kirchheimbolanden",
    "sg:phone":"+49 6352/3633",
    "sg:postcode":"67292",
    "sg:province":"Rheinland-Pfalz",
    "wof:name":"Heinrich Engemann",
    "wof:placetype":"venue"
},
  "geometry": {"coordinates":[7.9927330017,49.6736907959],"type":"Point"}
}