{
  "type": "Feature",
  "properties": {
    "iso:country":"DE",
    "sg:address":"Gartenstr. 11",
    "sg:city":"Br\u00fchl",
    "sg:phone":"+49 2232/42316",
    "sg:postcode":"50321",
    "sg:province":"Nordrhein-Westfalen",
    "wof:name":"Regina Krautwig Heilpraktikerin",
    "wof:placetype":"venue"
},
  "geometry": {"coordinates":[6.9068889618,50.8307151794],"type":"Point"}
}