{
  "type": "Feature",
  "properties": {
    "iso:country":"DE",
    "sg:address":"Eichhaldenstr 1",
    "sg:city":"Donzdorf",
    "sg:phone":"+49 7162/27165",
    "sg:postcode":"73072",
    "sg:province":"Baden-W\u00fcrttemberg",
    "wof:name":"Franz Hofele",
    "wof:placetype":"venue"
},
  "geometry": {"coordinates":[9.821121,48.712505],"type":"Point"}
}