{
  "type": "Feature",
  "properties": {
    "iso:country":"DE",
    "sg:address":"Thomas-Wimmer-Ring 11",
    "sg:city":"M\u00fcnchen",
    "sg:postcode":"80539",
    "sg:province":"Bayern",
    "wof:name":"Dr. Fleissner Verwaltungs- Gmbh & Co. Kg",
    "wof:placetype":"venue"
},
  "geometry": {"coordinates":[11.5836048126,48.1362419128],"type":"Point"}
}