{
  "type": "Feature",
  "properties": {
    "iso:country":"DE",
    "sg:address":"Schwarzaer Str. 12",
    "sg:city":"Rohr",
    "sg:phone":"+49 36844/40230",
    "sg:postcode":"98530",
    "sg:province":"Th\u00fcringen",
    "wof:name":"Dorothea Gloyna Rechtsanw\u00e4ltin",
    "wof:placetype":"venue"
},
  "geometry": {"coordinates":[10.5023441315,50.5783081055],"type":"Point"}
}