{
  "type": "Feature",
  "properties": {
    "iso:country":"DE",
    "sg:address":"Friedhofstr. 7",
    "sg:city":"Burgebrach",
    "sg:phone":"+49 9546/481",
    "sg:postcode":"96138",
    "sg:province":"Bayern",
    "wof:name":"Georg Heidenreich",
    "wof:placetype":"venue"
},
  "geometry": {"coordinates":[10.725516,49.845703],"type":"Point"}
}