{
  "type": "Feature",
  "properties": {
    "iso:country":"DE",
    "sg:address":"Martin-Luther-Str. 24",
    "sg:city":"G\u00f6ttingen",
    "sg:phone":"+49 551/372285",
    "sg:postcode":"37081",
    "sg:province":"Niedersachsen",
    "wof:name":"Fritz D. Kuhlen Immobilienmakler",
    "wof:placetype":"venue"
},
  "geometry": {"coordinates":[9.8939189911,51.5397415161],"type":"Point"}
}