{
  "type": "Feature",
  "properties": {
    "iso:country":"DE",
    "sg:address":"Gildehofstr. 1",
    "sg:city":"Essen",
    "sg:postcode":"45127",
    "sg:province":"Nordrhein-Westfalen",
    "wof:name":"Financert Gmbh",
    "wof:placetype":"venue"
},
  "geometry": {"coordinates":[7.0161738396,51.4542770386],"type":"Point"}
}