{
  "type": "Feature",
  "properties": {
    "iso:country":"DE",
    "sg:address":"Am Alten Rhein 83",
    "sg:city":"D\u00fcsseldorf",
    "sg:phone":"+49 211/714597",
    "sg:postcode":"40593",
    "sg:province":"Nordrhein-Westfalen",
    "wof:name":"Altes Fischerhaus",
    "wof:placetype":"venue"
},
  "geometry": {"coordinates":[6.8609628677,51.1496658325],"type":"Point"}
}