{
  "type": "Feature",
  "properties": {
    "iso:country":"DE",
    "sg:address":"Baumschulweg 1",
    "sg:city":"Willich",
    "sg:phone":"+49 2156/5079",
    "sg:postcode":"47877",
    "sg:province":"Nordrhein-Westfalen",
    "wof:name":"Willicher Baumschulen",
    "wof:placetype":"venue"
},
  "geometry": {"coordinates":[6.4960751534,51.2663459778],"type":"Point"}
}