{
  "type": "Feature",
  "properties": {
    "iso:country":"DE",
    "sg:address":"Kaiserstr. 78",
    "sg:city":"Moers",
    "sg:phone":"+49 2841/30272",
    "sg:postcode":"47441",
    "sg:province":"Nordrhein-Westfalen",
    "wof:name":"Wilfried Kannengie\u00dfer Finanzberater",
    "wof:placetype":"venue"
},
  "geometry": {"coordinates":[6.637524128,51.442440033],"type":"Point"}
}