{
  "type": "Feature",
  "properties": {
    "iso:country":"DE",
    "sg:address":"Hauptstr. 12",
    "sg:city":"Schwanfeld",
    "sg:phone":"+49 9384/99940",
    "sg:postcode":"97523",
    "sg:province":"Bayern",
    "wof:name":"Delta-offsetdruck",
    "wof:placetype":"venue"
},
  "geometry": {"coordinates":[10.137285,49.923645],"type":"Point"}
}