{
  "type": "Feature",
  "properties": {
    "iso:country":"DE",
    "sg:address":"Eichelgasse 40",
    "sg:city":"Wertheim",
    "sg:phone":"+49 9342/37766",
    "sg:postcode":"97877",
    "sg:province":"Baden-W\u00fcrttemberg",
    "wof:name":"Reinhold Horn",
    "wof:placetype":"venue"
},
  "geometry": {"coordinates":[9.5188694,49.7601089478],"type":"Point"}
}