{
  "type": "Feature",
  "properties": {
    "iso:country":"DE",
    "sg:address":"Rheing\u00f6nheimer Str. 21",
    "sg:city":"Altrip",
    "sg:phone":"+49 6236/2891",
    "sg:postcode":"67122",
    "sg:province":"Rheinland-Pfalz",
    "wof:name":"Joachim Kotter",
    "wof:placetype":"venue"
},
  "geometry": {"coordinates":[8.4961233139,49.4313621521],"type":"Point"}
}