{
  "type": "Feature",
  "properties": {
    "iso:country":"DE",
    "sg:address":"Kurt-Hebach-Str. 5",
    "sg:city":"Mainz-Kastel",
    "sg:postcode":"55252",
    "sg:province":"Hessen",
    "wof:name":"Hl Markt Warenhandelsges. Mbh",
    "wof:placetype":"venue"
},
  "geometry": {"coordinates":[8.2912101746,50.0202903748],"type":"Point"}
}