{
  "type": "Feature",
  "properties": {
    "iso:country":"DE",
    "sg:address":"Am Lindenberg 5",
    "sg:city":"Braunschweig",
    "sg:phone":"+49 531/360883",
    "sg:postcode":"38104",
    "sg:province":"Niedersachsen",
    "wof:name":"Arbeitsgemeinschaft F\u00fcr Vorschulerziehung",
    "wof:placetype":"venue"
},
  "geometry": {"coordinates":[10.6055192947,52.2772903442],"type":"Point"}
}