{
  "type": "Feature",
  "properties": {
    "iso:country":"DE",
    "sg:address":"Oberfeldweg 6",
    "sg:city":"Regensburg",
    "sg:phone":"+49 941/36114",
    "sg:postcode":"93049",
    "sg:province":"Bayern",
    "wof:name":"Edelgard Hertel",
    "wof:placetype":"venue"
},
  "geometry": {"coordinates":[12.0420198441,49.0151939392],"type":"Point"}
}