{
  "type": "Feature",
  "properties": {
    "iso:country":"DE",
    "sg:address":"Weiskopfstr. 6",
    "sg:city":"M\u00fcnchen",
    "sg:phone":"+49 89/407590",
    "sg:postcode":"81671",
    "sg:province":"Bayern",
    "wof:name":"Michael Geith",
    "wof:placetype":"venue"
},
  "geometry": {"coordinates":[11.6129360199,48.118019104],"type":"Point"}
}