{
  "type": "Feature",
  "properties": {
    "iso:country":"DE",
    "sg:address":"Neuer Markt 6",
    "sg:city":"Dassel",
    "sg:phone":"+49 5562/8914",
    "sg:postcode":"37586",
    "sg:province":"Niedersachsen",
    "wof:name":"Wilhelm Ahrens",
    "wof:placetype":"venue"
},
  "geometry": {"coordinates":[9.768687,51.813343],"type":"Point"}
}