{
  "type": "Feature",
  "properties": {
    "iso:country":"DE",
    "sg:address":"Schwarzenbergstr. 6",
    "sg:city":"Bad Aibling",
    "sg:phone":"+49 8061/491991",
    "sg:postcode":"83043",
    "sg:province":"Bayern",
    "wof:name":"Inet Edv Und Netzwerk Gmbh",
    "wof:placetype":"venue"
},
  "geometry": {"coordinates":[11.9970006943,47.8589668274],"type":"Point"}
}