{
  "type": "Feature",
  "properties": {
    "iso:country":"DE",
    "sg:address":"Waldd\u00f6rferstr. 10",
    "sg:city":"Hamburg",
    "sg:phone":"+49 40/686583",
    "sg:postcode":"22041",
    "sg:province":"Hamburg",
    "wof:name":"Helga Raczka",
    "wof:placetype":"venue"
},
  "geometry": {"coordinates":[10.0666589737,53.5793151855],"type":"Point"}
}