{
  "type": "Feature",
  "properties": {
    "iso:country":"DE",
    "sg:address":"Neue Hausener Str. 1",
    "sg:city":"Wipfratal",
    "sg:postcode":"99310",
    "sg:province":"Th\u00fcringen",
    "wof:name":"Tew Transporte Land- Und Forstwirtschaftlicher",
    "wof:placetype":"venue"
},
  "geometry": {"coordinates":[11.0089054108,50.8095932007],"type":"Point"}
}