{
  "type": "Feature",
  "properties": {
    "iso:country":"DE",
    "sg:address":"Gr\u00fcne Str. 11",
    "sg:city":"Lensahn",
    "sg:phone":"+49 4363/511",
    "sg:postcode":"23738",
    "sg:province":"Schleswig-Holstein",
    "wof:name":"Codan Vertrieb Gmbh & Co. Kg",
    "wof:placetype":"venue"
},
  "geometry": {"coordinates":[10.887738,54.219849],"type":"Point"}
}