{
  "type": "Feature",
  "properties": {
    "iso:country":"DE",
    "sg:address":"Geisenh\u00f6ll 16",
    "sg:city":"A\u00dflar",
    "sg:phone":"+49 6441/88001",
    "sg:postcode":"35614",
    "sg:province":"Hessen",
    "wof:name":"Pension A\u00dflar",
    "wof:placetype":"venue"
},
  "geometry": {"coordinates":[8.4515333176,50.5946807861],"type":"Point"}
}