{
  "type": "Feature",
  "properties": {
    "iso:country":"DE",
    "sg:address":"Parkweg 1",
    "sg:city":"Bramsche",
    "sg:phone":"+49 5461/4294",
    "sg:postcode":"49565",
    "sg:province":"Niedersachsen",
    "wof:name":"I. Tillar",
    "wof:placetype":"venue"
},
  "geometry": {"coordinates":[8.0028944016,52.3990516663],"type":"Point"}
}