{
  "type": "Feature",
  "properties": {
    "iso:country":"DE",
    "sg:address":"Sch\u00fctzenstr. 7",
    "sg:city":"K\u00fcps",
    "sg:phone":"+49 9264/540",
    "sg:postcode":"96328",
    "sg:province":"Bayern",
    "wof:name":"Irmtraud Bauer",
    "wof:placetype":"venue"
},
  "geometry": {"coordinates":[11.26105,50.21608],"type":"Point"}
}