{
  "type": "Feature",
  "properties": {
    "iso:country":"DE",
    "sg:address":"Kurgartenstr. 54",
    "sg:city":"F\u00fcrth",
    "sg:postcode":"90762",
    "sg:province":"Bayern",
    "wof:name":"Ipte German Holding Gmbh & Co. Kg",
    "wof:placetype":"venue"
},
  "geometry": {"coordinates":[11.01487,49.468376],"type":"Point"}
}