{
  "type": "Feature",
  "properties": {
    "iso:country":"DE",
    "sg:city":"Stuttgart",
    "sg:postcode":"76543",
    "sg:province":"Baden-W\u00fcrttemberg",
    "wof:name":"Private Homepage Einer Dominanten Lady",
    "wof:placetype":"venue"
},
  "geometry": {"coordinates":[-91.552673,34.498363],"type":"Point"}
}