{
  "type": "Feature",
  "properties": {
    "iso:country":"DE",
    "sg:address":"Sellgraben 2",
    "sg:city":"Hasselfelde",
    "sg:phone":"+49 39459/71524",
    "sg:postcode":"38899",
    "sg:province":"Sachsen-Anhalt",
    "wof:name":"Walter Brauner",
    "wof:placetype":"venue"
},
  "geometry": {"coordinates":[10.848298,51.689087],"type":"Point"}
}