{
  "type": "Feature",
  "properties": {
    "iso:country":"DE",
    "sg:city":"Sch\u00f6nberg",
    "sg:phone":"+49 4534/609",
    "sg:postcode":"22929",
    "sg:province":"Schleswig-Holstein",
    "wof:name":"M. Von Enckevort",
    "wof:placetype":"venue"
},
  "geometry": {"coordinates":[10.430837,53.679611],"type":"Point"}
}