{
  "type": "Feature",
  "properties": {
    "iso:country":"DE",
    "sg:address":"Siegfried-Marcus-Str 37",
    "sg:city":"Waren",
    "sg:phone":"+49 3991/6730680",
    "sg:postcode":"17192",
    "sg:province":"Mecklenburg-Vorpommern",
    "wof:name":"Pactec Gmbh",
    "wof:placetype":"venue"
},
  "geometry": {"coordinates":[12.78299,53.510941],"type":"Point"}
}