{
  "type": "Feature",
  "properties": {
    "iso:country":"DE",
    "sg:address":"Robert-Zapp-Str 6",
    "sg:city":"Ratingen",
    "sg:phone":"+49 2102/451211",
    "sg:postcode":"40880",
    "sg:province":"Nordrhein-Westfalen",
    "wof:name":"P\u00f6nsgen Ohg",
    "wof:placetype":"venue"
},
  "geometry": {"coordinates":[6.8254709244,51.3065643311],"type":"Point"}
}