{
  "type": "Feature",
  "properties": {
    "iso:country":"DE",
    "sg:address":"Waldburgstr. 20",
    "sg:city":"B\u00f6blingen",
    "sg:phone":"+49 7031/71760",
    "sg:postcode":"71032",
    "sg:province":"Baden-W\u00fcrttemberg",
    "wof:name":"Rainer Kr\u00e4mer Steuerberater Und",
    "wof:placetype":"venue"
},
  "geometry": {"coordinates":[9.0234498978,48.687412262],"type":"Point"}
}