{
  "type": "Feature",
  "properties": {
    "iso:country":"DE",
    "sg:address":"\u00dctermarkermitteldeich 20",
    "sg:city":"Pellworm",
    "sg:phone":"+49 4844/291",
    "sg:postcode":"25849",
    "sg:province":"Schleswig-Holstein",
    "wof:name":"Heinz Mextorf",
    "wof:placetype":"venue"
},
  "geometry": {"coordinates":[8.68229,54.530602],"type":"Point"}
}