{
  "type": "Feature",
  "properties": {
    "iso:country":"DE",
    "sg:address":"Rekener Str. 14",
    "sg:city":"Velen",
    "sg:phone":"+49 2863/3553",
    "sg:postcode":"46342",
    "sg:province":"Nordrhein-Westfalen",
    "wof:name":"Elektro-edeler Verwaltungs-gmbh",
    "wof:placetype":"venue"
},
  "geometry": {"coordinates":[6.98698,51.893784],"type":"Point"}
}