{
  "type": "Feature",
  "properties": {
    "iso:country":"DE",
    "sg:address":"Hochstand 14",
    "sg:city":"Hattingen",
    "sg:phone":"+49 2324/53700",
    "sg:postcode":"45525",
    "sg:province":"Nordrhein-Westfalen",
    "wof:name":"Dr. Phil. S. Blome-pamperin Heilpraktikerin",
    "wof:placetype":"venue"
},
  "geometry": {"coordinates":[7.1805019379,51.3855628967],"type":"Point"}
}