{
  "type": "Feature",
  "properties": {
    "iso:country":"DE",
    "sg:address":"Staufenstr. 16",
    "sg:city":"Kelsterbach",
    "sg:phone":"+49 6107/61673",
    "sg:postcode":"65451",
    "sg:province":"Hessen",
    "wof:name":"Alte Oberf\u00f6rsterei",
    "wof:placetype":"venue"
},
  "geometry": {"coordinates":[8.5299701691,50.0654411316],"type":"Point"}
}