{
  "type": "Feature",
  "properties": {
    "iso:country":"DE",
    "sg:address":"Dorfstr. 13",
    "sg:city":"Eckersdorf",
    "sg:phone":"+49 9279/239",
    "sg:postcode":"95488",
    "sg:province":"Bayern",
    "wof:name":"Wilhelm Weith",
    "wof:placetype":"venue"
},
  "geometry": {"coordinates":[11.470416069,49.9397392273],"type":"Point"}
}