{
  "type": "Feature",
  "properties": {
    "iso:country":"DE",
    "sg:address":"Am Bahnhof",
    "sg:city":"Radeburg",
    "sg:phone":"+49 35208/2252",
    "sg:postcode":"01471",
    "sg:province":"Sachsen",
    "wof:name":"Radeburg",
    "wof:placetype":"venue"
},
  "geometry": {"coordinates":[13.718606,51.168808],"type":"Point"}
}