{
  "type": "Feature",
  "properties": {
    "iso:country":"DE",
    "sg:address":"Schwalbenstr. 1",
    "sg:city":"Neu-Isenburg",
    "sg:phone":"+49 6102/756043",
    "sg:postcode":"63263",
    "sg:province":"Hessen",
    "wof:name":"Mtt Mentoring Technologie Transfer Gmbh",
    "wof:placetype":"venue"
},
  "geometry": {"coordinates":[8.754907,50.058083],"type":"Point"}
}