{
  "type": "Feature",
  "properties": {
    "iso:country":"DE",
    "sg:address":"Beekhalf 12B",
    "sg:city":"Gro\u00dfenaspe",
    "sg:phone":"+49 4327/242",
    "sg:postcode":"24623",
    "sg:province":"Schleswig-Holstein",
    "wof:name":"Manfred Ginckel",
    "wof:placetype":"venue"
},
  "geometry": {"coordinates":[9.9623336792,53.9759941101],"type":"Point"}
}