{
  "type": "Feature",
  "properties": {
    "iso:country":"DE",
    "sg:address":"Am Sandfeld 17a",
    "sg:city":"Karlsruhe",
    "sg:phone":"+49 721/783910",
    "sg:postcode":"76149",
    "sg:province":"Baden-W\u00fcrttemberg",
    "wof:name":"Aachener Bausparkasse Ag",
    "wof:placetype":"venue"
},
  "geometry": {"coordinates":[8.392135,49.042564],"type":"Point"}
}