{
  "type": "Feature",
  "properties": {
    "iso:country":"DE",
    "sg:address":"Schwartauer Landstr. 89",
    "sg:city":"L\u00fcbeck",
    "sg:phone":"+49 451/408790",
    "sg:postcode":"23554",
    "sg:province":"Schleswig-Holstein",
    "wof:name":"Franz Meyer's Sohn Gmbh & Co.",
    "wof:placetype":"venue"
},
  "geometry": {"coordinates":[10.689874649,53.8987998962],"type":"Point"}
}