{
  "type": "Feature",
  "properties": {
    "iso:country":"DE",
    "sg:address":"Auf der Vogelwiese 9",
    "sg:city":"M\u00fcnchen",
    "sg:phone":"+49 89/703366",
    "sg:postcode":"81375",
    "sg:province":"Bayern",
    "wof:name":"H. Stadler Steuerberater",
    "wof:placetype":"venue"
},
  "geometry": {"coordinates":[11.4766149521,48.1197738647],"type":"Point"}
}