{
  "type": "Feature",
  "properties": {
    "iso:country":"DE",
    "sg:address":"Eltenberg 54",
    "sg:city":"Brakel",
    "sg:phone":"+49 5648/261",
    "sg:postcode":"33034",
    "sg:province":"Nordrhein-Westfalen",
    "wof:name":"W & F Gmbh",
    "wof:placetype":"venue"
},
  "geometry": {"coordinates":[9.1500148773,51.6654548645],"type":"Point"}
}