{
  "type": "Feature",
  "properties": {
    "iso:country":"DE",
    "sg:address":"Bahnhofplatz 8",
    "sg:city":"Bad T\u00f6lz",
    "sg:phone":"+49 8041/74255",
    "sg:postcode":"83646",
    "sg:province":"Bayern",
    "wof:name":"Franz Stiebler Schilder Und Lichtreklame",
    "wof:placetype":"venue"
},
  "geometry": {"coordinates":[11.573721,47.760853],"type":"Point"}
}