{
  "type": "Feature",
  "properties": {
    "iso:country":"DE",
    "sg:address":"Robert-Bosch-Str. 4+5",
    "sg:city":"Markdorf",
    "sg:phone":"+49 4975/4495440",
    "sg:postcode":"88677",
    "sg:province":"Baden-W\u00fcrttemberg",
    "wof:name":"Maucher Formbau U Kunststofftechnik Gmbh & Co Kg",
    "wof:placetype":"venue"
},
  "geometry": {"coordinates":[9.4042987823,47.7089233398],"type":"Point"}
}