{
  "type": "Feature",
  "properties": {
    "iso:country":"DE",
    "sg:address":"Grenzstr. 14",
    "sg:city":"Chemnitz",
    "sg:phone":"+49 371/8201269",
    "sg:postcode":"09117",
    "sg:province":"Sachsen",
    "wof:name":"Dr. Med. Veronika T\u00f6pfer",
    "wof:placetype":"venue"
},
  "geometry": {"coordinates":[12.821719,50.828079],"type":"Point"}
}