{
  "type": "Feature",
  "properties": {
    "iso:country":"DE",
    "sg:address":"Bremer Str. 10 c",
    "sg:city":"Dresden",
    "sg:phone":"+49 351/48160",
    "sg:postcode":"01067",
    "sg:province":"Sachsen",
    "wof:name":"Hochtief Ag",
    "wof:placetype":"venue"
},
  "geometry": {"coordinates":[13.7099370956,51.0617218018],"type":"Point"}
}