{
  "type": "Feature",
  "properties": {
    "iso:country":"DE",
    "sg:address":"Hauptstr. 43",
    "sg:city":"Lilienthal",
    "sg:phone":"+49 4298/1066",
    "sg:postcode":"28865",
    "sg:province":"Niedersachsen",
    "wof:name":"Haus Am Jan-reiners-weg Gmbh",
    "wof:placetype":"venue"
},
  "geometry": {"coordinates":[8.906008,53.140533],"type":"Point"}
}