{
  "type": "Feature",
  "properties": {
    "iso:country":"DE",
    "sg:address":"Bl\u00fccher Stra\u00dfe 16",
    "sg:city":"Neuruppin",
    "sg:phone":"+49 3391/504078",
    "sg:postcode":"16816",
    "sg:province":"Brandenburg",
    "wof:name":"Immobilien In Neuruppin",
    "wof:placetype":"venue"
},
  "geometry": {"coordinates":[12.795912,52.921059],"type":"Point"}
}