{
  "type": "Feature",
  "properties": {
    "iso:country":"DE",
    "sg:address":"Hussenstr. 3",
    "sg:city":"Konstanz",
    "sg:phone":"+49 7531/23049",
    "sg:postcode":"78462",
    "sg:province":"Baden-W\u00fcrttemberg",
    "wof:name":"Grenzg\u00e4nger Information Gmbh",
    "wof:placetype":"venue"
},
  "geometry": {"coordinates":[9.17321,47.660461],"type":"Point"}
}