{
  "type": "Feature",
  "properties": {
    "iso:country":"DE",
    "sg:address":"Siegener Str. 19",
    "sg:city":"Kreuztal",
    "sg:phone":"+49 2732/4426",
    "sg:postcode":"57223",
    "sg:province":"Nordrhein-Westfalen",
    "wof:name":"H. Hesse",
    "wof:placetype":"venue"
},
  "geometry": {"coordinates":[7.993039,50.95797],"type":"Point"}
}