{
  "type": "Feature",
  "properties": {
    "iso:country":"DE",
    "sg:address":"Schneewiesenstr. 3",
    "sg:city":"Birkenfeld",
    "sg:phone":"+49 6782/5495",
    "sg:postcode":"55765",
    "sg:province":"Rheinland-Pfalz",
    "wof:name":"Hans J. Franzmann",
    "wof:placetype":"venue"
},
  "geometry": {"coordinates":[7.1677279472,49.6496963501],"type":"Point"}
}