{
  "type": "Feature",
  "properties": {
    "iso:country":"DE",
    "sg:address":"Paarmarktstr. 4",
    "sg:city":"Nieheim",
    "sg:phone":"+49 5274/8369",
    "sg:postcode":"33039",
    "sg:province":"Nordrhein-Westfalen",
    "wof:name":"G. Paulukat",
    "wof:placetype":"venue"
},
  "geometry": {"coordinates":[9.105753,51.803932],"type":"Point"}
}