{
  "type": "Feature",
  "properties": {
    "iso:country":"DE",
    "sg:address":"Tichelener Weg 5",
    "sg:city":"Geilenkirchen",
    "sg:phone":"+49 2451/72188",
    "sg:postcode":"52511",
    "sg:province":"Nordrhein-Westfalen",
    "wof:name":"Forward Gmbh",
    "wof:placetype":"venue"
},
  "geometry": {"coordinates":[6.1324591637,50.9648132324],"type":"Point"}
}