{
  "type": "Feature",
  "properties": {
    "iso:country":"DE",
    "sg:address":"Eifelstr. 16",
    "sg:city":"Bengel",
    "sg:phone":"+49 6532/2497",
    "sg:postcode":"54538",
    "sg:province":"Rheinland-Pfalz",
    "wof:name":"Andreas Schie",
    "wof:placetype":"venue"
},
  "geometry": {"coordinates":[7.0606489182,50.01587677],"type":"Point"}
}