{
  "type": "Feature",
  "properties": {
    "iso:country":"DE",
    "sg:address":"Schulhof 3",
    "sg:city":"Sigmaringen",
    "sg:postcode":"72488",
    "sg:province":"Baden-W\u00fcrttemberg",
    "wof:name":"Www-ckv-agentur.de",
    "wof:placetype":"venue"
},
  "geometry": {"coordinates":[9.216603,48.085407],"type":"Point"}
}