{
  "type": "Feature",
  "properties": {
    "iso:country":"DE",
    "sg:address":"K\u00f6nigsberger Str. 7",
    "sg:city":"Kleinwallstadt",
    "sg:phone":"+49 6022/24768",
    "sg:postcode":"63839",
    "sg:province":"Bayern",
    "wof:name":"K.-h. Und S. Scherger",
    "wof:placetype":"venue"
},
  "geometry": {"coordinates":[9.1704111099,49.8657341003],"type":"Point"}
}