{
  "type": "Feature",
  "properties": {
    "iso:country":"DE",
    "sg:address":"Papenstr. 57b",
    "sg:city":"Lemgo",
    "sg:phone":"+49 5261/927917",
    "sg:postcode":"32657",
    "sg:province":"Nordrhein-Westfalen",
    "wof:name":"W\u00f6hler Bau- Und Verwaltungs Gmbh",
    "wof:placetype":"venue"
},
  "geometry": {"coordinates":[8.905733,52.027664],"type":"Point"}
}