{
  "type": "Feature",
  "properties": {
    "iso:country":"DE",
    "sg:address":"Hermann-L\u00f6ns-Weg 11",
    "sg:city":"Wolpertswende",
    "sg:phone":"+49 7502/911536",
    "sg:postcode":"88284",
    "sg:province":"Baden-W\u00fcrttemberg",
    "wof:name":"Schmieder & Partner Vermittlungs Gmbh",
    "wof:placetype":"venue"
},
  "geometry": {"coordinates":[9.6395692825,47.8716163635],"type":"Point"}
}