{
  "type": "Feature",
  "properties": {
    "iso:country":"DE",
    "sg:address":"Me\u00dfkircher Str. 21",
    "sg:city":"Stockach",
    "sg:phone":"+49 7771/2526",
    "sg:postcode":"78333",
    "sg:province":"Baden-W\u00fcrttemberg",
    "wof:name":"Karl Schellhammer",
    "wof:placetype":"venue"
},
  "geometry": {"coordinates":[9.00519,47.855762],"type":"Point"}
}