{
  "type": "Feature",
  "properties": {
    "iso:country":"DE",
    "sg:address":"Abbachstr. 28",
    "sg:city":"M\u00fcnchen",
    "sg:phone":"+49 89/1413662",
    "sg:postcode":"80992",
    "sg:province":"Bayern",
    "wof:name":"Hans Schwenk",
    "wof:placetype":"venue"
},
  "geometry": {"coordinates":[11.5228824615,48.1806373596],"type":"Point"}
}