{
  "type": "Feature",
  "properties": {
    "iso:country":"DE",
    "sg:address":"Gr\u00fctzm\u00fchlenweg 45",
    "sg:city":"Hamburg",
    "sg:phone":"+49 40/5386414",
    "sg:postcode":"22339",
    "sg:province":"Hamburg",
    "wof:name":"Tanzforum Hamburg Ballettschule",
    "wof:placetype":"venue"
},
  "geometry": {"coordinates":[10.0362997055,53.644947052],"type":"Point"}
}