{
  "type": "Feature",
  "properties": {
    "iso:country":"DE",
    "sg:address":"Holunderweg 9",
    "sg:city":"Recklinghausen",
    "sg:phone":"+49 2361/480555",
    "sg:postcode":"45665",
    "sg:province":"Nordrhein-Westfalen",
    "wof:name":"Quellenberg Park Squash-center",
    "wof:placetype":"venue"
},
  "geometry": {"coordinates":[7.2278709412,51.6030044556],"type":"Point"}
}