{
  "type": "Feature",
  "properties": {
    "iso:country":"DE",
    "sg:address":"Markt 34",
    "sg:city":"Neuss",
    "sg:postcode":"41460",
    "sg:province":"Nordrhein-Westfalen",
    "wof:name":"Rheinisches Textilkontor Gmbh",
    "wof:placetype":"venue"
},
  "geometry": {"coordinates":[6.6940870285,51.1984405518],"type":"Point"}
}