{
  "type": "Feature",
  "properties": {
    "iso:country":"DE",
    "sg:address":"Paul-Hindemit-Strasse 6",
    "sg:city":"Grevenbroich",
    "sg:phone":"+49 2181/243188",
    "sg:postcode":"41517",
    "sg:province":"Nordrhein-Westfalen",
    "wof:name":"Immobilien-kreis Neuss",
    "wof:placetype":"venue"
},
  "geometry": {"coordinates":[6.6005659103,51.0339851379],"type":"Point"}
}