{
  "type": "Feature",
  "properties": {
    "iso:country":"DE",
    "sg:address":"Steinweg 1b",
    "sg:city":"Quedlinburg",
    "sg:phone":"+49 3946/2489",
    "sg:postcode":"06484",
    "sg:province":"Sachsen-Anhalt",
    "wof:name":"U. M\u00fcller",
    "wof:placetype":"venue"
},
  "geometry": {"coordinates":[11.146596,51.790291],"type":"Point"}
}