{
  "type": "Feature",
  "properties": {
    "iso:country":"DE",
    "sg:address":"Willy-Brandt-Str. 28",
    "sg:city":"Stuttgart",
    "sg:phone":"+49 711/2229760",
    "sg:postcode":"70173",
    "sg:province":"Baden-W\u00fcrttemberg",
    "wof:name":"Patentanw\u00e4lte Ruff Beier Und Partner",
    "wof:placetype":"venue"
},
  "geometry": {"coordinates":[9.1882505417,48.7831039429],"type":"Point"}
}