{
  "type": "Feature",
  "properties": {
    "iso:country":"DE",
    "sg:address":"Twietenkoppel 31",
    "sg:city":"Hamburg",
    "sg:phone":"+49 40/6045986",
    "sg:postcode":"22395",
    "sg:province":"Hamburg",
    "wof:name":"Holger Hack",
    "wof:placetype":"venue"
},
  "geometry": {"coordinates":[10.11713,53.67289],"type":"Point"}
}