{
  "type": "Feature",
  "properties": {
    "iso:country":"DE",
    "sg:address":"Markt 2",
    "sg:city":"Ahaus",
    "sg:phone":"+49 4925/612557",
    "sg:postcode":"48683",
    "sg:province":"Nordrhein-Westfalen",
    "wof:name":"Dirk Beckering",
    "wof:placetype":"venue"
},
  "geometry": {"coordinates":[7.005672,52.075722],"type":"Point"}
}