{
  "type": "Feature",
  "properties": {
    "iso:country":"DE",
    "sg:address":"Spitzkrugring 2",
    "sg:city":"Frankfurt",
    "sg:phone":"+49 335/6800621",
    "sg:postcode":"15234",
    "sg:province":"Brandenburg",
    "wof:name":"Horst Weichselbaum",
    "wof:placetype":"venue"
},
  "geometry": {"coordinates":[14.5274248123,52.3619804382],"type":"Point"}
}