{
  "type": "Feature",
  "properties": {
    "iso:country":"DE",
    "sg:address":"Droste-H\u00fclshoff-Str. 27",
    "sg:city":"Gelsenkirchen",
    "sg:phone":"+49 209/38222",
    "sg:postcode":"45894",
    "sg:province":"Nordrhein-Westfalen",
    "wof:name":"Eurofast Handelsgesellschaft F\u00fcr Verbindungselemente Mbh",
    "wof:placetype":"venue"
},
  "geometry": {"coordinates":[7.066806,51.577751],"type":"Point"}
}