{
  "type": "Feature",
  "properties": {
    "iso:country":"DE",
    "sg:address":"Danziger Stra\u00dfe 1",
    "sg:city":"Sonsbeck",
    "sg:phone":"+49 2838/91690",
    "sg:postcode":"47665",
    "sg:province":"Nordrhein-Westfalen",
    "wof:name":"Plastik Ventil Armaturen",
    "wof:placetype":"venue"
},
  "geometry": {"coordinates":[6.3831539154,51.6015396118],"type":"Point"}
}