{
  "type": "Feature",
  "properties": {
    "iso:country":"DE",
    "sg:address":"Stra\u00dfe der Volkssolidarit\u00e4t 25",
    "sg:city":"Sangerhausen",
    "sg:phone":"+49 3464/614211",
    "sg:postcode":"06526",
    "sg:province":"Sachsen-Anhalt",
    "wof:name":"Restaurant Pizza-eck",
    "wof:placetype":"venue"
},
  "geometry": {"coordinates":[11.2942800522,51.4636039734],"type":"Point"}
}