{
  "type": "Feature",
  "properties": {
    "iso:country":"DE",
    "sg:address":"Am Bahndamm 8",
    "sg:city":"Neustrelitz",
    "sg:phone":"+49 3981/28700",
    "sg:postcode":"17235",
    "sg:province":"Mecklenburg-Vorpommern",
    "wof:name":"Egn Baustoffmarkt Neustrelitz Gmbh & Co. Kg",
    "wof:placetype":"venue"
},
  "geometry": {"coordinates":[13.0672502518,53.3377990723],"type":"Point"}
}