{
  "type": "Feature",
  "properties": {
    "iso:country":"DE",
    "sg:address":"Soester Str. 38",
    "sg:city":"Werl",
    "sg:phone":"+49 2922/2474",
    "sg:postcode":"59457",
    "sg:province":"Nordrhein-Westfalen",
    "wof:name":"Hans Sch\u00fctte Bildhauer",
    "wof:placetype":"venue"
},
  "geometry": {"coordinates":[7.920332,51.549366],"type":"Point"}
}