{
  "type": "Feature",
  "properties": {
    "iso:country":"DE",
    "sg:address":"Hellkofener Str. 2",
    "sg:city":"Aufhausen",
    "sg:phone":"+49 9454/876",
    "sg:postcode":"93089",
    "sg:province":"Bayern",
    "wof:name":"Johann Wild",
    "wof:placetype":"venue"
},
  "geometry": {"coordinates":[12.265401,48.885822],"type":"Point"}
}