{
  "type": "Feature",
  "properties": {
    "iso:country":"DE",
    "sg:address":"Hauptstr. 52b",
    "sg:city":"Ebersbach",
    "sg:phone":"+49 3431/613881",
    "sg:postcode":"04720",
    "sg:province":"Sachsen",
    "wof:name":"Werner Gierich",
    "wof:placetype":"venue"
},
  "geometry": {"coordinates":[13.110075,51.098934],"type":"Point"}
}