{
  "type": "Feature",
  "properties": {
    "iso:country":"DE",
    "sg:address":"Maximilianstr. 100",
    "sg:city":"Pforzheim",
    "sg:phone":"+49 7231/454967",
    "sg:postcode":"75172",
    "sg:province":"Baden-W\u00fcrttemberg",
    "wof:name":"Friedrich Sch\u00e4fer",
    "wof:placetype":"venue"
},
  "geometry": {"coordinates":[8.6804056168,48.8927192688],"type":"Point"}
}