{
  "type": "Feature",
  "properties": {
    "iso:country":"DE",
    "sg:address":"Rotbornstr 10",
    "sg:city":"Oberursel",
    "sg:phone":"+49 6171/926660",
    "sg:postcode":"61440",
    "sg:province":"Hessen",
    "wof:name":"Ali Werbeagentur Alfred Liebe Absatzf\u00f6rderung Und Kommunikation Kg",
    "wof:placetype":"venue"
},
  "geometry": {"coordinates":[8.562818,50.206966],"type":"Point"}
}