{
  "type": "Feature",
  "properties": {
    "iso:country":"DE",
    "sg:address":"Bornhardtstr. 1",
    "sg:city":"Goslar",
    "sg:phone":"+49 5321/5560",
    "sg:postcode":"38644",
    "sg:province":"Niedersachsen",
    "wof:name":"Bollmeyer Verwaltungs Gmbh",
    "wof:placetype":"venue"
},
  "geometry": {"coordinates":[10.414715,51.92432],"type":"Point"}
}