{
  "type": "Feature",
  "properties": {
    "iso:country":"DE",
    "sg:address":"Karl-Arnold-Str. 14",
    "sg:city":"Korschenbroich",
    "sg:phone":"+49 2161/670680",
    "sg:postcode":"41352",
    "sg:province":"Nordrhein-Westfalen",
    "wof:name":"Alfred Vones Vakuum-verpackung",
    "wof:placetype":"venue"
},
  "geometry": {"coordinates":[6.557598114,51.1922035217],"type":"Point"}
}