{
  "type": "Feature",
  "properties": {
    "iso:country":"DE",
    "sg:address":"Im Spring",
    "sg:city":"Sundern",
    "sg:phone":"+49 2934/234",
    "sg:postcode":"59846",
    "sg:province":"Nordrhein-Westfalen",
    "wof:name":"Strassenbaustoffindustrie Hellefeld Wolfgang Hilgenroth",
    "wof:placetype":"venue"
},
  "geometry": {"coordinates":[7.9959797859,51.3177757263],"type":"Point"}
}