{
  "type": "Feature",
  "properties": {
    "iso:country":"DE",
    "sg:address":"Ohmtalstr. 14",
    "sg:city":"C\u00f6lbe",
    "sg:phone":"+49 6427/930422",
    "sg:postcode":"35091",
    "sg:province":"Hessen",
    "wof:name":"Lagler Logistic Gmbh",
    "wof:placetype":"venue"
},
  "geometry": {"coordinates":[8.8205900192,50.8535575867],"type":"Point"}
}