{
  "type": "Feature",
  "properties": {
    "iso:country":"DE",
    "sg:address":"Usambarastr. 12",
    "sg:city":"M\u00fcnchen",
    "sg:phone":"+49 89/4303131",
    "sg:postcode":"81827",
    "sg:province":"Bayern",
    "wof:name":"Zum Sande Gmbh",
    "wof:placetype":"venue"
},
  "geometry": {"coordinates":[11.703496,48.112297],"type":"Point"}
}