{
  "type": "Feature",
  "properties": {
    "iso:country":"DE",
    "sg:address":"Untergasse 26",
    "sg:city":"Fernwald",
    "sg:phone":"+49 6404/61342",
    "sg:postcode":"35463",
    "sg:province":"Hessen",
    "wof:name":"Verein F\u00fcr Humor Albach Hans-ludwig Balser",
    "wof:placetype":"venue"
},
  "geometry": {"coordinates":[8.796245575,50.5538444519],"type":"Point"}
}