{
  "type": "Feature",
  "properties": {
    "iso:country":"DE",
    "sg:address":"Charlottenstr. 65",
    "sg:city":"Berlin",
    "sg:phone":"+49 30/20397814",
    "sg:postcode":"10117",
    "sg:province":"Berlin",
    "wof:name":"American Language Academy Gmbh Private Sprachschule",
    "wof:placetype":"venue"
},
  "geometry": {"coordinates":[13.3915157318,52.5108985901],"type":"Point"}
}