{
  "type": "Feature",
  "properties": {
    "iso:country":"DE",
    "sg:address":"Friedensstr. 3",
    "sg:city":"Dassow",
    "sg:phone":"+49 38826/86230",
    "sg:postcode":"23942",
    "sg:province":"Mecklenburg-Vorpommern",
    "wof:name":"K.-w. Gussmann",
    "wof:placetype":"venue"
},
  "geometry": {"coordinates":[10.97729,53.908806],"type":"Point"}
}