{
  "type": "Feature",
  "properties": {
    "iso:country":"DE",
    "sg:address":"Kiefholzstr. 180",
    "sg:city":"Berlin",
    "sg:phone":"+49 30",
    "sg:postcode":"12437",
    "sg:province":"Berlin",
    "wof:name":"Gebhard Boenke Uhrmachermeister",
    "wof:placetype":"venue"
},
  "geometry": {"coordinates":[13.4858617783,52.4662437439],"type":"Point"}
}