{
  "type": "Feature",
  "properties": {
    "iso:country":"DE",
    "sg:address":"Armbruststr. 18",
    "sg:city":"Hamburg",
    "sg:phone":"+49 40/8503311",
    "sg:postcode":"20257",
    "sg:province":"Hamburg",
    "wof:name":"U. Weidner",
    "wof:placetype":"venue"
},
  "geometry": {"coordinates":[9.941307,53.574852],"type":"Point"}
}