{
  "type": "Feature",
  "properties": {
    "iso:country":"DE",
    "sg:address":"Hofstetterstr. 20",
    "sg:city":"Welden",
    "sg:postcode":"86465",
    "sg:province":"Bayern",
    "wof:name":"Herban Flugcharter- Gmbh",
    "wof:placetype":"venue"
},
  "geometry": {"coordinates":[10.66048,48.461308],"type":"Point"}
}