{
  "type": "Feature",
  "properties": {
    "iso:country":"DE",
    "sg:address":"Hauptstr. 29",
    "sg:city":"Hetzles",
    "sg:phone":"+49 9134/5317",
    "sg:postcode":"91077",
    "sg:province":"Bayern",
    "wof:name":"Elisabeth Sternecker Architekten",
    "wof:placetype":"venue"
},
  "geometry": {"coordinates":[11.128288,49.63504],"type":"Point"}
}