{
  "type": "Feature",
  "properties": {
    "iso:country":"DE",
    "sg:address":"Hahnenkleer Str. 14",
    "sg:city":"Langelsheim",
    "sg:phone":"+49 5325/54747",
    "sg:postcode":"38685",
    "sg:province":"Niedersachsen",
    "wof:name":"Harry M\u00fcnchberg Wissenschaftlicher",
    "wof:placetype":"venue"
},
  "geometry": {"coordinates":[10.2881669998,51.8679504395],"type":"Point"}
}