{
  "type": "Feature",
  "properties": {
    "iso:country":"DE",
    "sg:address":"Ansbacher Str 34::",
    "sg:city":"Bechhofen",
    "sg:phone":"+49 9822/8400",
    "sg:postcode":"91572",
    "sg:province":"Bayern",
    "wof:name":"Raiffeisenbank Bechhofen Eg",
    "wof:placetype":"venue"
},
  "geometry": {"coordinates":[10.552469,49.159756],"type":"Point"}
}