{
  "type": "Feature",
  "properties": {
    "iso:country":"DE",
    "sg:address":"T\u00f6sstr. 6",
    "sg:city":"Schramberg",
    "sg:phone":"+49 7422/240519",
    "sg:postcode":"78713",
    "sg:province":"Baden-W\u00fcrttemberg",
    "wof:name":"Fischer-hydraulik Gmbh",
    "wof:placetype":"venue"
},
  "geometry": {"coordinates":[8.383113,48.222984],"type":"Point"}
}