{
  "type": "Feature",
  "properties": {
    "iso:country":"DE",
    "sg:address":"Mozartstr. 4",
    "sg:city":"Plettenberg",
    "sg:phone":"+49 2391/14670",
    "sg:postcode":"58840",
    "sg:province":"Nordrhein-Westfalen",
    "wof:name":"R. Hoffmann",
    "wof:placetype":"venue"
},
  "geometry": {"coordinates":[7.866021,51.206783],"type":"Point"}
}