{
  "type": "Feature",
  "properties": {
    "iso:country":"DE",
    "sg:address":"Lutherstr. 87",
    "sg:city":"Chemnitz",
    "sg:phone":"+49 371/57050",
    "sg:postcode":"09126",
    "sg:province":"Sachsen",
    "wof:name":"S\u00e4chsische Schraubenwerke Gmbh",
    "wof:placetype":"venue"
},
  "geometry": {"coordinates":[12.925308,50.819809],"type":"Point"}
}