{
  "type": "Feature",
  "properties": {
    "iso:country":"DE",
    "sg:address":"Bernhardstr. 92",
    "sg:city":"Dresden",
    "sg:phone":"+49 351/4711470",
    "sg:postcode":"01187",
    "sg:province":"Sachsen",
    "wof:name":"Kerkmann & Berthel Gmbh",
    "wof:placetype":"venue"
},
  "geometry": {"coordinates":[13.7129611969,51.026889801],"type":"Point"}
}