{
  "type": "Feature",
  "properties": {
    "iso:country":"DE",
    "sg:address":"Lindenstr. 14",
    "sg:city":"Sulingen",
    "sg:phone":"+49 4271/2733",
    "sg:postcode":"27232",
    "sg:province":"Niedersachsen",
    "wof:name":"Restaurant Akropolis",
    "wof:placetype":"venue"
},
  "geometry": {"coordinates":[8.8009586334,52.6823387146],"type":"Point"}
}