{
  "type": "Feature",
  "properties": {
    "iso:country":"DE",
    "sg:address":"Kolpingstr.",
    "sg:city":"Glandorf",
    "sg:postcode":"49219",
    "sg:province":"Niedersachsen",
    "wof:name":"Kath.\u00f6ffentl. Bibliothek Glandorf",
    "wof:placetype":"venue"
},
  "geometry": {"coordinates":[8.00193,52.081146],"type":"Point"}
}