{
  "type": "Feature",
  "properties": {
    "iso:country":"DE",
    "sg:address":"Reisewitzer Str. 27",
    "sg:city":"Dresden",
    "sg:phone":"+49 351/4214023",
    "sg:postcode":"01159",
    "sg:province":"Sachsen",
    "wof:name":"Wild Gefl\u00fcgel Kaninchen, Hordan Dresden",
    "wof:placetype":"venue"
},
  "geometry": {"coordinates":[13.701408,51.041969],"type":"Point"}
}