{
  "type": "Feature",
  "properties": {
    "iso:country":"DE",
    "sg:address":"Tanner Str. 2",
    "sg:city":"Wittibreut",
    "sg:phone":"+49 8574/660",
    "sg:postcode":"84384",
    "sg:province":"Bayern",
    "wof:name":"Walter Bauer",
    "wof:placetype":"venue"
},
  "geometry": {"coordinates":[12.9871501923,48.329662323],"type":"Point"}
}