{
  "type": "Feature",
  "properties": {
    "iso:country":"DE",
    "sg:address":"Jean-Paul-Str. 12",
    "sg:city":"Selbitz",
    "sg:phone":"+49 9280/953597",
    "sg:postcode":"95152",
    "sg:province":"Bayern",
    "wof:name":"Sts Signal Technik Sprenger Gmbh",
    "wof:placetype":"venue"
},
  "geometry": {"coordinates":[11.747859,50.311607],"type":"Point"}
}