{
  "type": "Feature",
  "properties": {
    "iso:country":"DE",
    "sg:address":"Seestr. 15",
    "sg:city":"Genshagen",
    "sg:phone":"+49 3378/86280",
    "sg:postcode":"14974",
    "sg:province":"Brandenburg",
    "wof:name":"Vollwert Und Di\u00e4t Vertriebs- Gmbh",
    "wof:placetype":"venue"
},
  "geometry": {"coordinates":[13.3109025955,52.3116455078],"type":"Point"}
}