{
  "type": "Feature",
  "properties": {
    "iso:country":"DE",
    "sg:address":"Schmiedgasse 3",
    "sg:city":"Wolpertswende",
    "sg:phone":"+49 7502/611",
    "sg:postcode":"88284",
    "sg:province":"Baden-W\u00fcrttemberg",
    "wof:name":"A. Schill",
    "wof:placetype":"venue"
},
  "geometry": {"coordinates":[9.611553,47.895138],"type":"Point"}
}