{
  "type": "Feature",
  "properties": {
    "iso:country":"DE",
    "sg:address":"Wibboldweg 4",
    "sg:city":"Bielefeld",
    "sg:phone":"+49 521/81533",
    "sg:postcode":"33611",
    "sg:province":"Nordrhein-Westfalen",
    "wof:name":"Wilhelm Theenhausen",
    "wof:placetype":"venue"
},
  "geometry": {"coordinates":[8.553764,52.054497],"type":"Point"}
}