{
  "type": "Feature",
  "properties": {
    "iso:country":"DE",
    "sg:address":"Theaterstrasse 2",
    "sg:city":"W\u00fcrzburg",
    "sg:phone":"+49 931/571555",
    "sg:postcode":"97070",
    "sg:province":"Bayern",
    "wof:name":"Zeitzeichen - Mode Im Zeichen Der Zeit - W\u00fcrzburg",
    "wof:placetype":"venue"
},
  "geometry": {"coordinates":[9.93348,49.797226],"type":"Point"}
}