{
  "type": "Feature",
  "properties": {
    "iso:country":"DE",
    "sg:address":"Am Sonnenberg 8",
    "sg:city":"W\u00fcrzburg",
    "sg:phone":"+49 931/281818",
    "sg:postcode":"97078",
    "sg:province":"Bayern",
    "wof:name":"Finanzvermittlung Rothemel Und Zorn",
    "wof:placetype":"venue"
},
  "geometry": {"coordinates":[9.96438694,49.8253364563],"type":"Point"}
}