{
  "type": "Feature",
  "properties": {
    "iso:country":"DE",
    "sg:address":"R\u00fcttenscheider Str. 166",
    "sg:city":"Essen",
    "sg:phone":"+49 201/425656",
    "sg:postcode":"45131",
    "sg:province":"Nordrhein-Westfalen",
    "wof:name":"Pizzeria Palladio",
    "wof:placetype":"venue"
},
  "geometry": {"coordinates":[7.0030560493,51.4294586182],"type":"Point"}
}