{
  "type": "Feature",
  "properties": {
    "iso:country":"DE",
    "sg:address":"Kraut\u00e4ckerstr. 18",
    "sg:city":"Winkelhaid",
    "sg:phone":"+49 9187/41893",
    "sg:postcode":"90610",
    "sg:province":"Bayern",
    "wof:name":"Reinhard Schoch",
    "wof:placetype":"venue"
},
  "geometry": {"coordinates":[11.3078832626,49.3783416748],"type":"Point"}
}