{
  "type": "Feature",
  "properties": {
    "iso:country":"DE",
    "sg:address":"Untere Dorfstra\u00dfe 31",
    "sg:city":"Straubing",
    "sg:phone":"+49 9421",
    "sg:postcode":"94315",
    "sg:province":"Bayern",
    "wof:name":"Taxi Und Mietwagen In Der G\u00e4ubodenstadt Straubing",
    "wof:placetype":"venue"
},
  "geometry": {"coordinates":[12.582225,48.878525],"type":"Point"}
}