{
  "type": "Feature",
  "properties": {
    "iso:country":"DE",
    "sg:address":"Breite Str. 94",
    "sg:city":"Wernigerode",
    "sg:phone":"+49 3943/632088",
    "sg:postcode":"38855",
    "sg:province":"Sachsen-Anhalt",
    "wof:name":"Kupper-keller",
    "wof:placetype":"venue"
},
  "geometry": {"coordinates":[10.7918128967,51.8361930847],"type":"Point"}
}