{
  "type": "Feature",
  "properties": {
    "iso:country":"DE",
    "sg:address":"Zieglerstr. 12",
    "sg:city":"Duisburg",
    "sg:phone":"+49 203/305460",
    "sg:postcode":"47058",
    "sg:province":"Nordrhein-Westfalen",
    "wof:name":"Technika Ingenieurb\u00fcro F\u00fcr Bauwesen Gmbh",
    "wof:placetype":"venue"
},
  "geometry": {"coordinates":[6.7942547798,51.4345474243],"type":"Point"}
}