{
  "type": "Feature",
  "properties": {
    "iso:country":"DE",
    "sg:address":"Lichtenfelser Str. 49a",
    "sg:city":"Hallstadt",
    "sg:phone":"+49 951/73440",
    "sg:postcode":"96103",
    "sg:province":"Bayern",
    "wof:name":"Homann Lebensmittelwerke Gmbh & Co. Kg",
    "wof:placetype":"venue"
},
  "geometry": {"coordinates":[10.880859375,49.9310913086],"type":"Point"}
}