{
  "type": "Feature",
  "properties": {
    "iso:country":"DE",
    "sg:address":"Rheinstr. 41",
    "sg:city":"Mainz",
    "sg:phone":"+49 6131/224499",
    "sg:postcode":"55116",
    "sg:province":"Rheinland-Pfalz",
    "wof:name":"Fenestra Jalousie Markt",
    "wof:placetype":"venue"
},
  "geometry": {"coordinates":[8.276405,49.999821],"type":"Point"}
}