{
  "type": "Feature",
  "properties": {
    "iso:country":"DE",
    "sg:address":"Biberacher Str. 94",
    "sg:city":"Bad Waldsee",
    "sg:postcode":"88339",
    "sg:province":"Baden-W\u00fcrttemberg",
    "wof:name":"Meb Verlag Gmbh",
    "wof:placetype":"venue"
},
  "geometry": {"coordinates":[9.7578544617,47.9283676147],"type":"Point"}
}