{
  "type": "Feature",
  "properties": {
    "iso:country":"DE",
    "sg:address":"Sandstr. 1",
    "sg:city":"Neu-Ulm",
    "sg:phone":"+49 731/8040",
    "sg:postcode":"89231",
    "sg:province":"Bayern",
    "wof:name":"Kreiskrankenh\u00e4user Neu-ulm U, Illertissen Gmbh",
    "wof:placetype":"venue"
},
  "geometry": {"coordinates":[9.994352,48.3941],"type":"Point"}
}