{
  "type": "Feature",
  "properties": {
    "iso:country":"DE",
    "sg:address":"Merrillweg 9 a",
    "sg:city":"K\u00f6ln",
    "sg:phone":"+49 2236/69529",
    "sg:postcode":"50996",
    "sg:province":"Nordrhein-Westfalen",
    "wof:name":"G\u00fcnter Christophe Rechtsanwalt",
    "wof:placetype":"venue"
},
  "geometry": {"coordinates":[6.981842041,50.872127533],"type":"Point"}
}