{
  "type": "Feature",
  "properties": {
    "iso:country":"DE",
    "sg:city":"Edertal",
    "sg:phone":"+49 4956/234918",
    "sg:postcode":"34549",
    "sg:province":"Hessen",
    "wof:name":"Kreissparkasse Waldeck",
    "wof:placetype":"venue"
},
  "geometry": {"coordinates":[9.136078,51.16798],"type":"Point"}
}