{
  "type": "Feature",
  "properties": {
    "iso:country":"DE",
    "sg:address":"Gaustr. 4",
    "sg:city":"Friesenheim",
    "sg:phone":"+49 6737/1067",
    "sg:postcode":"55278",
    "sg:province":"Rheinland-Pfalz",
    "wof:name":"Volker Lang -grabmale-",
    "wof:placetype":"venue"
},
  "geometry": {"coordinates":[8.2572937012,49.837020874],"type":"Point"}
}