{
  "type": "Feature",
  "properties": {
    "iso:country":"DE",
    "sg:address":"Vorwerkstr. 6",
    "sg:city":"Ingolstadt",
    "sg:postcode":"85051",
    "sg:province":"Bayern",
    "wof:name":"Regio Wohn- Und Gewerbebau Gmbh",
    "wof:placetype":"venue"
},
  "geometry": {"coordinates":[11.439613,48.733315],"type":"Point"}
}