{
  "type": "Feature",
  "properties": {
    "iso:country":"DE",
    "sg:address":"Heribertstr. 34",
    "sg:city":"N\u00f6rvenich",
    "sg:phone":"+49 2426/1624",
    "sg:postcode":"52388",
    "sg:province":"Nordrhein-Westfalen",
    "wof:name":"Hermann Axer",
    "wof:placetype":"venue"
},
  "geometry": {"coordinates":[6.578145,50.811531],"type":"Point"}
}