{
  "type": "Feature",
  "properties": {
    "iso:country":"DE",
    "sg:address":"Gablonzer Str. 16",
    "sg:city":"Fichtelberg",
    "sg:phone":"+49 9272/9750",
    "sg:postcode":"95686",
    "sg:province":"Bayern",
    "wof:name":"C. Gerhardt",
    "wof:placetype":"venue"
},
  "geometry": {"coordinates":[11.8519525528,50.0012397766],"type":"Point"}
}