{
  "type": "Feature",
  "properties": {
    "iso:country":"DE",
    "sg:address":"Brainpold 1",
    "sg:city":"Bad Feilnbach",
    "sg:phone":"+49 8066/261",
    "sg:postcode":"83075",
    "sg:province":"Bayern",
    "wof:name":"Anton Sager",
    "wof:placetype":"venue"
},
  "geometry": {"coordinates":[11.996213,47.781986],"type":"Point"}
}