{
  "type": "Feature",
  "properties": {
    "iso:country":"DE",
    "sg:address":"Oppspring 8",
    "sg:city":"M\u00fclheim",
    "sg:phone":"+49 208/374236",
    "sg:postcode":"45470",
    "sg:province":"Nordrhein-Westfalen",
    "wof:name":"Alfred Wilbert",
    "wof:placetype":"venue"
},
  "geometry": {"coordinates":[6.900429,51.419079],"type":"Point"}
}