{
  "type": "Feature",
  "properties": {
    "iso:country":"DE",
    "sg:address":"Simmersdorfer Str. 1 a",
    "sg:city":"Gro\u00df Schacksdorf",
    "sg:phone":"+49 35695/7710",
    "sg:postcode":"03149",
    "sg:province":"Brandenburg",
    "wof:name":"Schneider & Co. Baustoff Und Mineral\u00f6lhandel Gmbh",
    "wof:placetype":"venue"
},
  "geometry": {"coordinates":[14.6237297058,51.6902084351],"type":"Point"}
}