{
  "type": "Feature",
  "properties": {
    "iso:country":"DE",
    "sg:address":"Sundgauallee 112",
    "sg:city":"Freiburg i. Br.",
    "sg:phone":"+49 761",
    "sg:postcode":"79110",
    "sg:province":"Baden-W\u00fcrttemberg",
    "wof:name":"Media Online",
    "wof:placetype":"venue"
},
  "geometry": {"coordinates":[7.8104038239,48.0115585327],"type":"Point"}
}