{
  "type": "Feature",
  "properties": {
    "iso:country":"DE",
    "sg:address":"Hospitalstr. 10",
    "sg:city":"Alzey",
    "sg:phone":"+49 6731/3585",
    "sg:postcode":"55232",
    "sg:province":"Rheinland-Pfalz",
    "wof:name":"Eiscafe Arosa",
    "wof:placetype":"venue"
},
  "geometry": {"coordinates":[8.112278,49.746994],"type":"Point"}
}