{
  "type": "Feature",
  "properties": {
    "iso:country":"DE",
    "sg:address":"Gabelsbergerstr. 2",
    "sg:city":"Kelsterbach",
    "sg:phone":"+49 6107/1731",
    "sg:postcode":"65451",
    "sg:province":"Hessen",
    "wof:name":"B. Zeller",
    "wof:placetype":"venue"
},
  "geometry": {"coordinates":[8.5267343521,50.0584449768],"type":"Point"}
}