{
  "type": "Feature",
  "properties": {
    "iso:country":"DE",
    "sg:address":"Gewerbepark 6",
    "sg:city":"Fehrbellin",
    "sg:phone":"+49 33932/9980",
    "sg:postcode":"16833",
    "sg:province":"Brandenburg",
    "wof:name":"Betonwerk Fehrbellin Gmbh & Co. Kg",
    "wof:placetype":"venue"
},
  "geometry": {"coordinates":[12.7865009308,52.7973175049],"type":"Point"}
}