{
  "type": "Feature",
  "properties": {
    "iso:country":"DE",
    "sg:address":"Bahnhofstr. 8",
    "sg:city":"Heuchelheim-Klingen",
    "sg:phone":"+49 6349/8693",
    "sg:postcode":"76831",
    "sg:province":"Rheinland-Pfalz",
    "wof:name":"H. Bollinger",
    "wof:placetype":"venue"
},
  "geometry": {"coordinates":[8.0574922562,49.1444816589],"type":"Point"}
}