{
  "type": "Feature",
  "properties": {
    "iso:country":"DE",
    "sg:address":"Auf dem Goern 7",
    "sg:city":"Bischofsheim",
    "sg:postcode":"65474",
    "sg:province":"Hessen",
    "wof:name":"Schlafender Hase Gmbh",
    "wof:placetype":"venue"
},
  "geometry": {"coordinates":[8.347748,49.986401],"type":"Point"}
}