{
  "type": "Feature",
  "properties": {
    "iso:country":"DE",
    "sg:address":"Neckarkatzenbacher Str. 1",
    "sg:city":"Aglasterhausen",
    "sg:phone":"+49 6262/1207",
    "sg:postcode":"74858",
    "sg:province":"Baden-W\u00fcrttemberg",
    "wof:name":"Philipp Lenz",
    "wof:placetype":"venue"
},
  "geometry": {"coordinates":[9.023021,49.366009],"type":"Point"}
}