{
  "type": "Feature",
  "properties": {
    "iso:country":"DE",
    "sg:address":"Alter Postweg 125",
    "sg:city":"Oldenburg",
    "sg:phone":"+49 441/46766",
    "sg:postcode":"26133",
    "sg:province":"Niedersachsen",
    "wof:name":"Sofort-reinigung",
    "wof:placetype":"venue"
},
  "geometry": {"coordinates":[8.228345,53.094994],"type":"Point"}
}