{
  "type": "Feature",
  "properties": {
    "iso:country":"DE",
    "sg:address":"Im Kirchfeld 16",
    "sg:city":"Leverkusen",
    "sg:phone":"+49 2171/56011",
    "sg:postcode":"51381",
    "sg:province":"Nordrhein-Westfalen",
    "wof:name":"Alfons Dobroschke Architekt",
    "wof:placetype":"venue"
},
  "geometry": {"coordinates":[7.056501,51.064053],"type":"Point"}
}