{
  "type": "Feature",
  "properties": {
    "iso:country":"DE",
    "sg:address":"Mahatma-Gandhi-Str. 44",
    "sg:city":"Stuttgart",
    "sg:phone":"+49 711/2573886",
    "sg:postcode":"70376",
    "sg:province":"Baden-W\u00fcrttemberg",
    "wof:name":"Gerhard Haist",
    "wof:placetype":"venue"
},
  "geometry": {"coordinates":[9.192505,48.818172],"type":"Point"}
}