{
  "type": "Feature",
  "properties": {
    "iso:country":"DE",
    "sg:address":"Breslauer Weg 6",
    "sg:city":"Waldkirch",
    "sg:phone":"+49 7681/8055",
    "sg:postcode":"79183",
    "sg:province":"Baden-W\u00fcrttemberg",
    "wof:name":"Bernd Weber",
    "wof:placetype":"venue"
},
  "geometry": {"coordinates":[7.9654607773,48.1031112671],"type":"Point"}
}