{
  "type": "Feature",
  "properties": {
    "iso:country":"DE",
    "sg:address":"Am Brucher H\u00e4uschen 78",
    "sg:city":"Wuppertal",
    "sg:phone":"+49 202/701041",
    "sg:postcode":"42109",
    "sg:province":"Nordrhein-Westfalen",
    "wof:name":"Alfons Hackmann",
    "wof:placetype":"venue"
},
  "geometry": {"coordinates":[7.1554341316,51.2809295654],"type":"Point"}
}