{
  "type": "Feature",
  "properties": {
    "iso:country":"DE",
    "sg:address":"Bahnhofstr. 66",
    "sg:city":"Bad Tennstedt",
    "sg:phone":"+49 36041/57115",
    "sg:postcode":"99955",
    "sg:province":"Th\u00fcringen",
    "wof:name":"Wilhelm Busch Inh. G\u00fcnther Busch",
    "wof:placetype":"venue"
},
  "geometry": {"coordinates":[10.8509836197,51.1515350342],"type":"Point"}
}