{
  "type": "Feature",
  "properties": {
    "iso:country":"DE",
    "sg:address":"Taunusstr. 15",
    "sg:city":"Schwalbach",
    "sg:phone":"+49 6196/81483",
    "sg:postcode":"65824",
    "sg:province":"Hessen",
    "wof:name":"W. Reichert",
    "wof:placetype":"venue"
},
  "geometry": {"coordinates":[8.534493,50.150562],"type":"Point"}
}