{
  "type": "Feature",
  "properties": {
    "iso:country":"DE",
    "sg:address":"Armlandstr. 2",
    "sg:city":"Gescher",
    "sg:phone":"+49 2542/3212",
    "sg:postcode":"48712",
    "sg:province":"Nordrhein-Westfalen",
    "wof:name":"Peacock Moden Gmbh",
    "wof:placetype":"venue"
},
  "geometry": {"coordinates":[7.004267,51.956055],"type":"Point"}
}