{
  "type": "Feature",
  "properties": {
    "iso:country":"DE",
    "sg:address":"Epplestr. 13",
    "sg:city":"Stuttgart",
    "sg:phone":"+49 711/760530",
    "sg:postcode":"70597",
    "sg:province":"Baden-W\u00fcrttemberg",
    "wof:name":"R. Reuer-gro\u00df",
    "wof:placetype":"venue"
},
  "geometry": {"coordinates":[9.17029953,48.7479782104],"type":"Point"}
}