{
  "type": "Feature",
  "properties": {
    "iso:country":"DE",
    "sg:address":"Breitenau 7",
    "sg:city":"Bergkirchen",
    "sg:postcode":"85232",
    "sg:province":"Bayern",
    "wof:name":"Nmb Digitale Werbeanlagen Gmbh",
    "wof:placetype":"venue"
},
  "geometry": {"coordinates":[11.403321,48.271408],"type":"Point"}
}