{
  "type": "Feature",
  "properties": {
    "iso:country":"DE",
    "sg:address":"Fuchsstr. 11",
    "sg:city":"H\u00fcrth",
    "sg:phone":"+49 2233/43310",
    "sg:postcode":"50354",
    "sg:province":"Nordrhein-Westfalen",
    "wof:name":"Johann Klemmer",
    "wof:placetype":"venue"
},
  "geometry": {"coordinates":[6.856953,50.868343],"type":"Point"}
}