{
  "type": "Feature",
  "properties": {
    "iso:country":"DE",
    "sg:address":"Bahnhofstr. 5",
    "sg:city":"Dingolfing",
    "sg:phone":"+49 8731/73567",
    "sg:postcode":"84130",
    "sg:province":"Bayern",
    "wof:name":"Hans Sch\u00fctz E. K.",
    "wof:placetype":"venue"
},
  "geometry": {"coordinates":[12.4950466156,48.6354484558],"type":"Point"}
}