{
  "type": "Feature",
  "properties": {
    "iso:country":"DE",
    "sg:address":"Landgrafenstr. 7",
    "sg:city":"Hessisch Lichtenau",
    "sg:phone":"+49 5602/2691",
    "sg:postcode":"37235",
    "sg:province":"Hessen",
    "wof:name":"Linge Und Nowak Rechtsanw\u00e4lte Und Notare",
    "wof:placetype":"venue"
},
  "geometry": {"coordinates":[9.7218112946,51.1980209351],"type":"Point"}
}