{
  "type": "Feature",
  "properties": {
    "iso:country":"DE",
    "sg:address":"Bocholter Str. 9",
    "sg:city":"Salzgitter",
    "sg:phone":"+49 5341/43172",
    "sg:postcode":"38226",
    "sg:province":"Niedersachsen",
    "wof:name":"Mens Shop Herrenausstatter",
    "wof:placetype":"venue"
},
  "geometry": {"coordinates":[10.3331851959,52.1532859802],"type":"Point"}
}