{
  "type": "Feature",
  "properties": {
    "iso:country":"DE",
    "sg:address":"Moselstr. 8",
    "sg:city":"Trittenheim",
    "sg:phone":"+49 6507/2561",
    "sg:postcode":"54349",
    "sg:province":"Rheinland-Pfalz",
    "wof:name":"L. Nilles-bollig Weinanbau",
    "wof:placetype":"venue"
},
  "geometry": {"coordinates":[6.9012460709,49.8227272034],"type":"Point"}
}