{
  "type": "Feature",
  "properties": {
    "iso:country":"DE",
    "sg:address":"Zum Alten Dessauer 1",
    "sg:city":"Kesselsdorf",
    "sg:phone":"+49 35204/29550",
    "sg:postcode":"01723",
    "sg:province":"Sachsen",
    "wof:name":"Metall- Und Elektroausbildung Ggmbh",
    "wof:placetype":"venue"
},
  "geometry": {"coordinates":[13.519213,51.029343],"type":"Point"}
}