{
  "type": "Feature",
  "properties": {
    "iso:country":"DE",
    "sg:address":"Max-Liebermann-Str. 21",
    "sg:city":"K\u00f6ngen",
    "sg:phone":"+49 7024/989804",
    "sg:postcode":"73257",
    "sg:province":"Baden-W\u00fcrttemberg",
    "wof:name":"I. Und W. Fingerle Makler",
    "wof:placetype":"venue"
},
  "geometry": {"coordinates":[9.3636703491,48.6884498596],"type":"Point"}
}