{
  "type": "Feature",
  "properties": {
    "iso:country":"DE",
    "sg:address":"Poststr. 46",
    "sg:city":"Rees",
    "sg:phone":"+49 2851/7204",
    "sg:postcode":"46459",
    "sg:province":"Nordrhein-Westfalen",
    "wof:name":"E. H\u00f6fer",
    "wof:placetype":"venue"
},
  "geometry": {"coordinates":[6.3929290771,51.7594642639],"type":"Point"}
}