{
  "type": "Feature",
  "properties": {
    "iso:country":"DE",
    "sg:address":"Nr. 95 c",
    "sg:city":"Niedersch\u00f6na",
    "sg:phone":"+49 35209/508",
    "sg:postcode":"09600",
    "sg:province":"Sachsen",
    "wof:name":"H. L\u00fctzner",
    "wof:placetype":"venue"
},
  "geometry": {"coordinates":[13.40069,50.87167],"type":"Point"}
}