{
  "type": "Feature",
  "properties": {
    "iso:country":"DE",
    "sg:address":"Dahlbachs Weg 8",
    "sg:city":"Neuwied",
    "sg:phone":"+49 2631/48187",
    "sg:postcode":"56566",
    "sg:province":"Rheinland-Pfalz",
    "wof:name":"Mevit Gmbh",
    "wof:placetype":"venue"
},
  "geometry": {"coordinates":[7.4902892113,50.4704780579],"type":"Point"}
}