{
  "type": "Feature",
  "properties": {
    "iso:country":"DE",
    "sg:address":"Starnberger Str. 15",
    "sg:city":"Sch\u00e4ftlarn",
    "sg:phone":"+49 8178/4014",
    "sg:postcode":"82069",
    "sg:province":"Bayern",
    "wof:name":"Kreissparkasse M\u00fcnchen",
    "wof:placetype":"venue"
},
  "geometry": {"coordinates":[11.42011,47.997051],"type":"Point"}
}