{
  "type": "Feature",
  "properties": {
    "iso:country":"DE",
    "sg:address":"Am Tiefen See 5-8",
    "sg:city":"Maulbronn",
    "sg:phone":"+49 7043/920703",
    "sg:postcode":"75433",
    "sg:province":"Baden-W\u00fcrttemberg",
    "wof:name":"Evt Eiberger & Pf\u00f6hler Gmbh",
    "wof:placetype":"venue"
},
  "geometry": {"coordinates":[8.818188,49.003918],"type":"Point"}
}