{
  "type": "Feature",
  "properties": {
    "iso:country":"DE",
    "sg:address":"Usedomstr 23",
    "sg:city":"Hamburg",
    "sg:phone":"+49 40/660690",
    "sg:postcode":"22047",
    "sg:province":"Hamburg",
    "wof:name":"Gather Druck & Vertrieb Gmbh",
    "wof:placetype":"venue"
},
  "geometry": {"coordinates":[10.1030397415,53.5884628296],"type":"Point"}
}