{
  "type": "Feature",
  "properties": {
    "iso:country":"DE",
    "sg:address":"Kirchplatz 20",
    "sg:city":"Merzig",
    "sg:phone":"+49 6861/5454",
    "sg:postcode":"66663",
    "sg:province":"Saarland",
    "wof:name":"Zur Sonne",
    "wof:placetype":"venue"
},
  "geometry": {"coordinates":[6.6412000656,49.4440917969],"type":"Point"}
}