{
  "type": "Feature",
  "properties": {
    "iso:country":"DE",
    "sg:address":"An den Pappeln 2 A",
    "sg:city":"Oberursel",
    "sg:phone":"+49 6171/983373",
    "sg:postcode":"61440",
    "sg:province":"Hessen",
    "wof:name":"Psz-mtn Projekt Gesellschaft F\u00fcr Baudienstleistungen Und",
    "wof:placetype":"venue"
},
  "geometry": {"coordinates":[8.580428,50.18544],"type":"Point"}
}