{
  "type": "Feature",
  "properties": {
    "iso:country":"DE",
    "sg:address":"Karlstr. 85",
    "sg:city":"Karlsruhe",
    "sg:phone":"+49 721/359375",
    "sg:postcode":"76137",
    "sg:province":"Baden-W\u00fcrttemberg",
    "wof:name":"Moda Forte",
    "wof:placetype":"venue"
},
  "geometry": {"coordinates":[8.394134,48.999268],"type":"Point"}
}