{
  "type": "Feature",
  "properties": {
    "iso:country":"DE",
    "sg:address":"Bachgasse 42",
    "sg:city":"Bensheim",
    "sg:phone":"+49 6251/72900",
    "sg:postcode":"64625",
    "sg:province":"Hessen",
    "wof:name":"Omnibusbetrieb D\u00fcrr Inh. Gebr. D\u00fcrr",
    "wof:placetype":"venue"
},
  "geometry": {"coordinates":[8.6276798248,49.7034606934],"type":"Point"}
}