{
  "type": "Feature",
  "properties": {
    "iso:country":"DE",
    "sg:address":"Dorfstr. 20",
    "sg:city":"Angerm\u00fcnde",
    "sg:phone":"+49 3331/24757",
    "sg:postcode":"16278",
    "sg:province":"Brandenburg",
    "wof:name":"Dobberzin Agrar Gmbh",
    "wof:placetype":"venue"
},
  "geometry": {"coordinates":[13.991131,52.970646],"type":"Point"}
}