{
  "type": "Feature",
  "properties": {
    "iso:country":"DE",
    "sg:address":"Wiesenstr. 14",
    "sg:city":"Abenberg",
    "sg:phone":"+49 9178/1687",
    "sg:postcode":"91183",
    "sg:province":"Bayern",
    "wof:name":"\u00d6ko Bettenbau Brummer",
    "wof:placetype":"venue"
},
  "geometry": {"coordinates":[10.958777,49.240749],"type":"Point"}
}