{
  "type": "Feature",
  "properties": {
    "iso:country":"DE",
    "sg:address":"Im Kronenwinkel 1",
    "sg:city":"Teningen",
    "sg:phone":"+49 7641/91910",
    "sg:postcode":"79331",
    "sg:province":"Baden-W\u00fcrttemberg",
    "wof:name":"Gewo Gmbh",
    "wof:placetype":"venue"
},
  "geometry": {"coordinates":[7.8103737831,48.1276245117],"type":"Point"}
}