{
  "type": "Feature",
  "properties": {
    "iso:country":"DE",
    "sg:address":"Hauptstr. 34",
    "sg:city":"Eppingen",
    "sg:phone":"+49 7262/7723",
    "sg:postcode":"75031",
    "sg:province":"Baden-W\u00fcrttemberg",
    "wof:name":"Akd Krankenpflegezentrum",
    "wof:placetype":"venue"
},
  "geometry": {"coordinates":[8.901221,49.098721],"type":"Point"}
}