{
  "type": "Feature",
  "properties": {
    "iso:country":"DE",
    "sg:address":"Ro\u00dfbrunnenstr. 3",
    "sg:city":"Butzbach",
    "sg:phone":"+49 6033/2377",
    "sg:postcode":"35510",
    "sg:province":"Hessen",
    "wof:name":"Capitol-theater",
    "wof:placetype":"venue"
},
  "geometry": {"coordinates":[8.670386,50.433422],"type":"Point"}
}