{
  "type": "Feature",
  "properties": {
    "iso:country":"DE",
    "sg:address":"Spitziger Berg",
    "sg:city":"Langenau",
    "sg:phone":"+49 7345/7489",
    "sg:postcode":"89129",
    "sg:province":"Baden-W\u00fcrttemberg",
    "wof:name":"Zweckverband Landeswasserversorgung",
    "wof:placetype":"venue"
},
  "geometry": {"coordinates":[10.168558,48.503258],"type":"Point"}
}