{
  "type": "Feature",
  "properties": {
    "iso:country":"DE",
    "sg:address":"Karlstr. 4",
    "sg:city":"A\u00dflar",
    "sg:phone":"+49 6441/81654",
    "sg:postcode":"35614",
    "sg:province":"Hessen",
    "wof:name":"Horst Dittmar Architekt",
    "wof:placetype":"venue"
},
  "geometry": {"coordinates":[8.463467,50.59277],"type":"Point"}
}