{
  "type": "Feature",
  "properties": {
    "iso:country":"DE",
    "sg:address":"Max-Planck-Str. 11a",
    "sg:city":"Bad Salzuflen",
    "sg:postcode":"32107",
    "sg:province":"Nordrhein-Westfalen",
    "wof:name":"Tonerzentrum Betzendahl Gmbh",
    "wof:placetype":"venue"
},
  "geometry": {"coordinates":[8.76125,52.039639],"type":"Point"}
}