{
  "type": "Feature",
  "properties": {
    "iso:country":"DE",
    "sg:address":"Spinnenbergstr. 7",
    "sg:city":"Albertshofen",
    "sg:phone":"+49 9321/31792",
    "sg:postcode":"97320",
    "sg:province":"Bayern",
    "wof:name":"K. Hofmann",
    "wof:placetype":"venue"
},
  "geometry": {"coordinates":[10.160248,49.767979],"type":"Point"}
}