{
  "type": "Feature",
  "properties": {
    "iso:country":"DE",
    "sg:address":"Sellerweg 11",
    "sg:city":"Warstein",
    "sg:phone":"+49 2902/71036",
    "sg:postcode":"59581",
    "sg:province":"Nordrhein-Westfalen",
    "wof:name":"Heinrich Wagener",
    "wof:placetype":"venue"
},
  "geometry": {"coordinates":[8.331628,51.482349],"type":"Point"}
}