{
  "type": "Feature",
  "properties": {
    "iso:country":"DE",
    "sg:address":"Adlerstr. 12",
    "sg:city":"M\u00f6gglingen",
    "sg:phone":"+49 7171/64266",
    "sg:postcode":"73563",
    "sg:province":"Baden-W\u00fcrttemberg",
    "wof:name":"Reinald Kellert Gmbh",
    "wof:placetype":"venue"
},
  "geometry": {"coordinates":[9.953811,48.824879],"type":"Point"}
}