{
  "type": "Feature",
  "properties": {
    "iso:country":"DE",
    "sg:address":"Kohlenbissener Grund 6",
    "sg:city":"Munster",
    "sg:phone":"+49 5192/2248",
    "sg:postcode":"29633",
    "sg:province":"Niedersachsen",
    "wof:name":"Hans Cohrs",
    "wof:placetype":"venue"
},
  "geometry": {"coordinates":[10.10916,52.9893],"type":"Point"}
}