{
  "type": "Feature",
  "properties": {
    "iso:country":"DE",
    "sg:address":"Schl\u00f6\u00dflestr. 1",
    "sg:city":"Erkheim",
    "sg:phone":"+49 8336/7221",
    "sg:postcode":"87746",
    "sg:province":"Bayern",
    "wof:name":"Martin Christa",
    "wof:placetype":"venue"
},
  "geometry": {"coordinates":[10.3389940262,48.0373916626],"type":"Point"}
}