{
  "type": "Feature",
  "properties": {
    "iso:country":"DE",
    "sg:address":"Lange Str. 58",
    "sg:city":"Z\u00f6rbig",
    "sg:phone":"+49 34956/39800",
    "sg:postcode":"06780",
    "sg:province":"Sachsen-Anhalt",
    "wof:name":"Rene B\u00f6hme Rechtsanwalt",
    "wof:placetype":"venue"
},
  "geometry": {"coordinates":[12.1168050766,51.6282501221],"type":"Point"}
}