{
  "type": "Feature",
  "properties": {
    "iso:country":"DE",
    "sg:address":"Stadionstr. 17",
    "sg:city":"Pegnitz",
    "sg:phone":"+49 9241/3828",
    "sg:postcode":"91257",
    "sg:province":"Bayern",
    "wof:name":"Erich Roder",
    "wof:placetype":"venue"
},
  "geometry": {"coordinates":[11.553134,49.753315],"type":"Point"}
}