{
  "type": "Feature",
  "properties": {
    "iso:country":"DE",
    "sg:address":"Panoramastr. 13",
    "sg:city":"Waldenburg",
    "sg:phone":"+49 7942/2631",
    "sg:postcode":"74638",
    "sg:province":"Baden-W\u00fcrttemberg",
    "wof:name":"Jetgraphics Handelsgesell- Schaft Gmbh",
    "wof:placetype":"venue"
},
  "geometry": {"coordinates":[9.6338911057,49.1833305359],"type":"Point"}
}