{
  "type": "Feature",
  "properties": {
    "iso:country":"DE",
    "sg:address":"Fahrenheitstr. 1",
    "sg:city":"Bremen",
    "sg:phone":"+49 421/2010500",
    "sg:postcode":"28359",
    "sg:province":"Bremen",
    "wof:name":"Scg Software Consulting Gmbh",
    "wof:placetype":"venue"
},
  "geometry": {"coordinates":[8.8477630615,53.1078605652],"type":"Point"}
}