{
  "type": "Feature",
  "properties": {
    "iso:country":"DE",
    "sg:address":"Hauptstr.",
    "sg:city":"Alt Zachun",
    "sg:phone":"+49 38859/5102",
    "sg:postcode":"19230",
    "sg:province":"Mecklenburg-Vorpommern",
    "wof:name":"Kl\u00f6ckner Fl\u00fcssiggaslager Alt Zachun Verwaltungs-",
    "wof:placetype":"venue"
},
  "geometry": {"coordinates":[11.33903,53.493752],"type":"Point"}
}