{
  "type": "Feature",
  "properties": {
    "iso:country":"DE",
    "sg:address":"Am Stahlberg 21",
    "sg:city":"Gummersbach",
    "sg:phone":"+49 2261/62139",
    "sg:postcode":"51647",
    "sg:province":"Nordrhein-Westfalen",
    "wof:name":"Karl-heinz Lenz Architekt",
    "wof:placetype":"venue"
},
  "geometry": {"coordinates":[7.530218,51.035992],"type":"Point"}
}