{
  "type": "Feature",
  "properties": {
    "iso:country":"DE",
    "sg:address":"Gro\u00dfe Pfarrgasse 6",
    "sg:city":"Hofgeismar",
    "sg:phone":"+49 5671/5524",
    "sg:postcode":"34369",
    "sg:province":"Hessen",
    "wof:name":"D. Wehrmann",
    "wof:placetype":"venue"
},
  "geometry": {"coordinates":[9.378235,51.496517],"type":"Point"}
}