{
  "type": "Feature",
  "properties": {
    "iso:country":"DE",
    "sg:address":"Dimhausen 27",
    "sg:city":"Bassum",
    "sg:phone":"+49 4241/2245",
    "sg:postcode":"27211",
    "sg:province":"Niedersachsen",
    "wof:name":"Fritz Poggenburg",
    "wof:placetype":"venue"
},
  "geometry": {"coordinates":[8.683016,52.882786],"type":"Point"}
}