{
  "type": "Feature",
  "properties": {
    "iso:country":"DE",
    "sg:address":"Hafenstr. 13",
    "sg:city":"Ostseebad Prerow",
    "sg:phone":"+49 38233/324",
    "sg:postcode":"18375",
    "sg:province":"Mecklenburg-Vorpommern",
    "wof:name":"Restaurant Zur Tankstelle Inh. J\u00f6rg Manzke",
    "wof:placetype":"venue"
},
  "geometry": {"coordinates":[12.5733308792,54.4465370178],"type":"Point"}
}