{
  "type": "Feature",
  "properties": {
    "iso:country":"DE",
    "sg:address":"Robert-Koch-Str. 7",
    "sg:city":"Bischweier",
    "sg:phone":"+49 7222/4528",
    "sg:postcode":"76476",
    "sg:province":"Baden-W\u00fcrttemberg",
    "wof:name":"Martin Keller Architekt",
    "wof:placetype":"venue"
},
  "geometry": {"coordinates":[8.279243,48.835434],"type":"Point"}
}