{
  "type": "Feature",
  "properties": {
    "iso:country":"DE",
    "sg:address":"Klemens-Wrede-Str. 14",
    "sg:city":"Menden",
    "sg:phone":"+49 2373/81479",
    "sg:postcode":"58710",
    "sg:province":"Nordrhein-Westfalen",
    "wof:name":"Gisbert Reich",
    "wof:placetype":"venue"
},
  "geometry": {"coordinates":[7.8421869278,51.4101066589],"type":"Point"}
}