{
  "type": "Feature",
  "properties": {
    "iso:country":"DE",
    "sg:address":"Bahnhofstr. 3",
    "sg:city":"Mehringen",
    "sg:phone":"+49 3473/814488",
    "sg:postcode":"06456",
    "sg:province":"Sachsen-Anhalt",
    "wof:name":"Fasselt Beteiligungsges. Mbh",
    "wof:placetype":"venue"
},
  "geometry": {"coordinates":[11.512219,51.723785],"type":"Point"}
}