{
  "type": "Feature",
  "properties": {
    "iso:country":"DE",
    "sg:address":"M\u00fchlenstr. 3",
    "sg:city":"Mirow",
    "sg:phone":"+49 39833/20273",
    "sg:postcode":"17252",
    "sg:province":"Mecklenburg-Vorpommern",
    "wof:name":"Karl Stolzenburg",
    "wof:placetype":"venue"
},
  "geometry": {"coordinates":[12.8119373322,53.274520874],"type":"Point"}
}