{
  "type": "Feature",
  "properties": {
    "iso:country":"DE",
    "sg:address":"Heinr-v-Kleist-Str. 8",
    "sg:city":"R\u00f6dermark",
    "sg:phone":"+49 6074/892555",
    "sg:postcode":"63322",
    "sg:province":"Hessen",
    "wof:name":"Werbung Design Grafik Im Rhein-main-gebiet",
    "wof:placetype":"venue"
},
  "geometry": {"coordinates":[8.82807,49.977612],"type":"Point"}
}