{
  "type": "Feature",
  "properties": {
    "iso:country":"DE",
    "sg:address":"Chiemseeweg 5",
    "sg:city":"Stuttgart",
    "sg:phone":"+49 711/532011",
    "sg:postcode":"70378",
    "sg:province":"Baden-W\u00fcrttemberg",
    "wof:name":"Josef Stetter",
    "wof:placetype":"venue"
},
  "geometry": {"coordinates":[9.227575,48.834248],"type":"Point"}
}