{
  "type": "Feature",
  "properties": {
    "iso:country":"DE",
    "sg:address":"Buchenhofstr. 22",
    "sg:city":"Kirchen",
    "sg:phone":"+49 2741/8930",
    "sg:postcode":"57548",
    "sg:province":"Rheinland-Pfalz",
    "wof:name":"B. Jung",
    "wof:placetype":"venue"
},
  "geometry": {"coordinates":[7.8555831909,50.8286895752],"type":"Point"}
}