{
  "type": "Feature",
  "properties": {
    "iso:country":"DE",
    "sg:address":"ESSO-Stra\u00dfe",
    "sg:city":"Ingolstadt",
    "sg:postcode":"85003",
    "sg:province":"Bayern",
    "wof:name":"Esso Bayern",
    "wof:placetype":"venue"
},
  "geometry": {"coordinates":[11.4253902435,48.7621383667],"type":"Point"}
}