{
  "type": "Feature",
  "properties": {
    "iso:country":"DE",
    "sg:address":"Postfach",
    "sg:city":"Schmallenberg",
    "sg:postcode":"57376",
    "sg:province":"Nordrhein-Westfalen",
    "wof:name":"Kino Schmallenberg",
    "wof:placetype":"venue"
},
  "geometry": {"coordinates":[8.28561,51.147789],"type":"Point"}
}