{
  "type": "Feature",
  "properties": {
    "iso:country":"DE",
    "sg:address":"M\u00fcnzgasse 10",
    "sg:city":"N\u00f6rdlingen",
    "sg:phone":"+49 9081/4206",
    "sg:postcode":"86720",
    "sg:province":"Bayern",
    "wof:name":"J\u00e4gerst\u00fcble",
    "wof:placetype":"venue"
},
  "geometry": {"coordinates":[10.4913492203,48.8496856689],"type":"Point"}
}