{
  "type": "Feature",
  "properties": {
    "iso:country":"DE",
    "sg:address":"Lyoner Str. 15",
    "sg:city":"Frankfurt",
    "sg:phone":"+49 69/66442301",
    "sg:postcode":"60528",
    "sg:province":"Hessen",
    "wof:name":"Carrier 1 Holding Gmbh",
    "wof:placetype":"venue"
},
  "geometry": {"coordinates":[8.627032,50.08197],"type":"Point"}
}