{
  "type": "Feature",
  "properties": {
    "iso:country":"DE",
    "sg:address":"Ziegelstr. 14",
    "sg:city":"Schwaikheim",
    "sg:phone":"+49 7195/52773",
    "sg:postcode":"71409",
    "sg:province":"Baden-W\u00fcrttemberg",
    "wof:name":"Hermann Und Ellen Lorenz",
    "wof:placetype":"venue"
},
  "geometry": {"coordinates":[9.3448028564,48.8789710999],"type":"Point"}
}