{
  "type": "Feature",
  "properties": {
    "iso:country":"DE",
    "sg:address":"Br\u00fcckenstr. 49",
    "sg:city":"M\u00f6nchengladbach",
    "sg:postcode":"41238",
    "sg:province":"Nordrhein-Westfalen",
    "wof:name":"C T A Cryotherm Apparate Gmbh",
    "wof:placetype":"venue"
},
  "geometry": {"coordinates":[6.459626,51.155231],"type":"Point"}
}