{
  "type": "Feature",
  "properties": {
    "iso:country":"DE",
    "sg:address":"Hanegge 2",
    "sg:city":"Oerlinghausen",
    "sg:phone":"+49 4952/024604",
    "sg:postcode":"33813",
    "sg:province":"Nordrhein-Westfalen",
    "wof:name":"Die Filterb\u00d6rse",
    "wof:placetype":"venue"
},
  "geometry": {"coordinates":[8.66646,51.96542],"type":"Point"}
}