{
  "type": "Feature",
  "properties": {
    "iso:country":"DE",
    "sg:address":"Hindenburgstr. 20",
    "sg:city":"Buchen",
    "sg:phone":"+49 6292/817",
    "sg:postcode":"74722",
    "sg:province":"Baden-W\u00fcrttemberg",
    "wof:name":"Helmut R\u00f6derer",
    "wof:placetype":"venue"
},
  "geometry": {"coordinates":[9.317181,49.477104],"type":"Point"}
}