{
  "type": "Feature",
  "properties": {
    "iso:country":"DE",
    "sg:address":"An den M\u00fchlen 2",
    "sg:city":"Bad Lauterberg",
    "sg:phone":"+49 5524/4844",
    "sg:postcode":"37431",
    "sg:province":"Niedersachsen",
    "wof:name":"Horst Albrecht Kg",
    "wof:placetype":"venue"
},
  "geometry": {"coordinates":[10.442747,51.609737],"type":"Point"}
}