{
  "type": "Feature",
  "properties": {
    "iso:country":"DE",
    "sg:address":"K\u00e4merstr. 29",
    "sg:city":"Kamen",
    "sg:phone":"+49 2307/10678",
    "sg:postcode":"59174",
    "sg:province":"Nordrhein-Westfalen",
    "wof:name":"J. Nies",
    "wof:placetype":"venue"
},
  "geometry": {"coordinates":[7.660294,51.593925],"type":"Point"}
}