{
  "type": "Feature",
  "properties": {
    "iso:country":"DE",
    "sg:address":"Schmelzer Str. 14",
    "sg:city":"V\u00f6lklingen",
    "sg:phone":"+49 6898/26203",
    "sg:postcode":"66333",
    "sg:province":"Saarland",
    "wof:name":"Roswitha Kohler",
    "wof:placetype":"venue"
},
  "geometry": {"coordinates":[6.8320741653,49.2697906494],"type":"Point"}
}