{
  "type": "Feature",
  "properties": {
    "iso:country":"DE",
    "sg:address":"Am Bahnhof 9",
    "sg:city":"Wadgassen",
    "sg:phone":"+49 6834/41882",
    "sg:postcode":"66787",
    "sg:province":"Saarland",
    "wof:name":"Manfred G\u00f6rgen",
    "wof:placetype":"venue"
},
  "geometry": {"coordinates":[6.799392,49.263607],"type":"Point"}
}