{
  "type": "Feature",
  "properties": {
    "iso:country":"DE",
    "sg:address":"Sebaldsbr\u00fccker Heerstr.",
    "sg:city":"Bremen",
    "sg:phone":"+49 421/454232",
    "sg:postcode":"28309",
    "sg:province":"Bremen",
    "wof:name":"W. Weber",
    "wof:placetype":"venue"
},
  "geometry": {"coordinates":[8.897344,53.059078],"type":"Point"}
}