{
  "type": "Feature",
  "properties": {
    "iso:country":"DE",
    "sg:address":"Lindentaler Str. 78",
    "sg:city":"Rudersberg",
    "sg:phone":"+49 7183/92710",
    "sg:postcode":"73635",
    "sg:province":"Baden-W\u00fcrttemberg",
    "wof:name":"Baier Verwaltungs Gmbh",
    "wof:placetype":"venue"
},
  "geometry": {"coordinates":[9.5189342499,48.873588562],"type":"Point"}
}