{
  "type": "Feature",
  "properties": {
    "iso:country":"DE",
    "sg:address":"Vilsendorfer Str. 263",
    "sg:city":"Bielefeld",
    "sg:phone":"+49 521/871000",
    "sg:postcode":"33739",
    "sg:province":"Nordrhein-Westfalen",
    "wof:name":"Kottenst\u00fcbchen",
    "wof:placetype":"venue"
},
  "geometry": {"coordinates":[8.5547533035,52.0718307495],"type":"Point"}
}