{
  "type": "Feature",
  "properties": {
    "iso:country":"DE",
    "sg:address":"Markt 1",
    "sg:city":"Braunsbedra",
    "sg:phone":"+49 34633/21085",
    "sg:postcode":"06242",
    "sg:province":"Sachsen-Anhalt",
    "wof:name":"Reiseagentur Kunze",
    "wof:placetype":"venue"
},
  "geometry": {"coordinates":[11.8851747513,51.2841186523],"type":"Point"}
}