{
  "type": "Feature",
  "properties": {
    "iso:country":"DE",
    "sg:address":"Franz-Haniel-Platz 6",
    "sg:city":"Duisburg",
    "sg:phone":"+49 203/7980156",
    "sg:postcode":"47119",
    "sg:province":"Nordrhein-Westfalen",
    "wof:name":"S & I Verm\u00f6gensverwaltung Gmbh",
    "wof:placetype":"venue"
},
  "geometry": {"coordinates":[6.7326140404,51.4515113831],"type":"Point"}
}