{
  "type": "Feature",
  "properties": {
    "iso:country":"DE",
    "sg:address":"Engelsholt 150",
    "sg:city":"M\u00f6nchengladbach",
    "sg:phone":"+49 2161/592509",
    "sg:postcode":"41069",
    "sg:province":"Nordrhein-Westfalen",
    "wof:name":"Thomas Wolters",
    "wof:placetype":"venue"
},
  "geometry": {"coordinates":[6.4058299065,51.1758537292],"type":"Point"}
}