{
  "type": "Feature",
  "properties": {
    "iso:country":"DE",
    "sg:address":"Am Stadtgraben 8",
    "sg:city":"Windsbach",
    "sg:phone":"+49 9871/252",
    "sg:postcode":"91575",
    "sg:province":"Bayern",
    "wof:name":"Hermann Huber",
    "wof:placetype":"venue"
},
  "geometry": {"coordinates":[10.8289985657,49.2468185425],"type":"Point"}
}