{
  "type": "Feature",
  "properties": {
    "iso:country":"DE",
    "sg:address":"Alte R\u00f6merstr. 47",
    "sg:city":"Wilhelmsfeld",
    "sg:phone":"+49 6220/1682",
    "sg:postcode":"69259",
    "sg:province":"Baden-W\u00fcrttemberg",
    "wof:name":"Karl Hornstein Elektroinstallation",
    "wof:placetype":"venue"
},
  "geometry": {"coordinates":[8.759268,49.475811],"type":"Point"}
}