{
  "type": "Feature",
  "properties": {
    "iso:country":"DE",
    "sg:address":"Mittenwalder Str. 82",
    "sg:city":"Kochel",
    "sg:phone":"+49 8851/861",
    "sg:postcode":"82431",
    "sg:province":"Bayern",
    "wof:name":"Hotel-restaurant Grauer B\u00e4r",
    "wof:placetype":"venue"
},
  "geometry": {"coordinates":[11.3589792252,47.6421203613],"type":"Point"}
}