{
  "type": "Feature",
  "properties": {
    "iso:country":"DE",
    "sg:address":"K\u00f6rnerstr. 3 +5",
    "sg:city":"Langenberg",
    "sg:phone":"+49 5248/232",
    "sg:postcode":"33449",
    "sg:province":"Nordrhein-Westfalen",
    "wof:name":"G\u00f6dde Holzbearbeitung Gmbh",
    "wof:placetype":"venue"
},
  "geometry": {"coordinates":[8.3199853897,51.775062561],"type":"Point"}
}