{
  "type": "Feature",
  "properties": {
    "iso:country":"DE",
    "sg:address":"Rurstr. 22",
    "sg:city":"Viersen",
    "sg:phone":"+49 2162/70838",
    "sg:postcode":"41749",
    "sg:province":"Nordrhein-Westfalen",
    "wof:name":"Seifenkistenverein Viersen 84 E. V.",
    "wof:placetype":"venue"
},
  "geometry": {"coordinates":[6.3901348114,51.2753257751],"type":"Point"}
}