{
  "type": "Feature",
  "properties": {
    "iso:country":"DE",
    "sg:address":"M\u00fchlenberger Weg 35",
    "sg:city":"Hamburg",
    "sg:phone":"+49 40/863702",
    "sg:postcode":"22587",
    "sg:province":"Hamburg",
    "wof:name":"Hambg. \u00d6ffentl. B\u00fccherhallen B\u00fccherhalle Blankensee",
    "wof:placetype":"venue"
},
  "geometry": {"coordinates":[9.816518,53.557613],"type":"Point"}
}