{
  "type": "Feature",
  "properties": {
    "iso:country":"DE",
    "sg:address":"Lindenberger Str. 12",
    "sg:city":"Ahrensfelde",
    "sg:phone":"+49 30/9329237",
    "sg:postcode":"16356",
    "sg:province":"Brandenburg",
    "wof:name":"Werner Richter",
    "wof:placetype":"venue"
},
  "geometry": {"coordinates":[13.569309,52.580952],"type":"Point"}
}