{
  "type": "Feature",
  "properties": {
    "iso:country":"DE",
    "sg:address":"Pfaffenhalder Weg 8",
    "sg:city":"Alzey",
    "sg:phone":"+49 6731/8049",
    "sg:postcode":"55232",
    "sg:province":"Rheinland-Pfalz",
    "wof:name":"Werner Frangel",
    "wof:placetype":"venue"
},
  "geometry": {"coordinates":[8.1542129517,49.7594299316],"type":"Point"}
}