{
  "type": "Feature",
  "properties": {
    "iso:country":"DE",
    "sg:address":"Nersumer Str. 7",
    "sg:city":"Neuenkirchen",
    "sg:phone":"+49 5193/3552",
    "sg:postcode":"29643",
    "sg:province":"Niedersachsen",
    "wof:name":"Alex Berndt",
    "wof:placetype":"venue"
},
  "geometry": {"coordinates":[9.663617,53.098881],"type":"Point"}
}