{
  "type": "Feature",
  "properties": {
    "iso:country":"DE",
    "sg:address":"Schwimmbadstr. 7 a",
    "sg:city":"Me\u00dfkirch",
    "sg:phone":"+49 7575/3408",
    "sg:postcode":"88605",
    "sg:province":"Baden-W\u00fcrttemberg",
    "wof:name":"Sahin",
    "wof:placetype":"venue"
},
  "geometry": {"coordinates":[9.122341156,47.9956321716],"type":"Point"}
}