{
  "type": "Feature",
  "properties": {
    "iso:country":"DE",
    "sg:address":"Querstr. 35",
    "sg:city":"Bitterfeld",
    "sg:phone":"+49 3493/22564",
    "sg:postcode":"06749",
    "sg:province":"Sachsen-Anhalt",
    "wof:name":"Wilfried Zeyda",
    "wof:placetype":"venue"
},
  "geometry": {"coordinates":[12.320204,51.627914],"type":"Point"}
}