{
  "type": "Feature",
  "properties": {
    "iso:country":"DE",
    "sg:address":"Hauptstr. 242",
    "sg:city":"Lindenberg",
    "sg:phone":"+49 6325/351",
    "sg:postcode":"67473",
    "sg:province":"Rheinland-Pfalz",
    "wof:name":"Media Pre Press Gmbh",
    "wof:placetype":"venue"
},
  "geometry": {"coordinates":[8.098346,49.389984],"type":"Point"}
}