{
  "type": "Feature",
  "properties": {
    "iso:country":"DE",
    "sg:address":"Wupperstr. 13",
    "sg:city":"Leverkusen",
    "sg:phone":"+49 214/22046",
    "sg:postcode":"51371",
    "sg:province":"Nordrhein-Westfalen",
    "wof:name":"Rheindorfer Grill",
    "wof:placetype":"venue"
},
  "geometry": {"coordinates":[6.9509248734,51.0506515503],"type":"Point"}
}