{
  "type": "Feature",
  "properties": {
    "iso:country":"DE",
    "sg:address":"Theodor-Storm-weg 9a",
    "sg:city":"St. Peter-Ording",
    "sg:phone":"+49 4863/4764802",
    "sg:postcode":"25826",
    "sg:province":"Schleswig-Holstein",
    "wof:name":"Lanhaus Am Kieferwald",
    "wof:placetype":"venue"
},
  "geometry": {"coordinates":[8.6524343491,54.2950820923],"type":"Point"}
}