{
  "type": "Feature",
  "properties": {
    "iso:country":"DE",
    "sg:address":"Waagestr. 9",
    "sg:city":"Bielefeld",
    "sg:phone":"+49 521/76802",
    "sg:postcode":"33729",
    "sg:province":"Nordrhein-Westfalen",
    "wof:name":"Hellemann & Co. Nachf.",
    "wof:placetype":"venue"
},
  "geometry": {"coordinates":[8.6031446457,52.0695762634],"type":"Point"}
}