{
  "type": "Feature",
  "properties": {
    "iso:country":"DE",
    "sg:address":"Oppauer Str. 63",
    "sg:city":"Ludwigshafen",
    "sg:phone":"+49 621/661009",
    "sg:postcode":"67069",
    "sg:province":"Rheinland-Pfalz",
    "wof:name":"Holz-fr\u00f6hlin Gmbh",
    "wof:placetype":"venue"
},
  "geometry": {"coordinates":[8.3929834366,49.529624939],"type":"Point"}
}