{
  "type": "Feature",
  "properties": {
    "iso:country":"DE",
    "sg:address":"Retschystr. 22",
    "sg:city":"Burgdorf",
    "sg:phone":"+49 5136/873487",
    "sg:postcode":"31303",
    "sg:province":"Niedersachsen",
    "wof:name":"Terramed Medizintechnik Gmbh",
    "wof:placetype":"venue"
},
  "geometry": {"coordinates":[10.0206632614,52.4347305298],"type":"Point"}
}