{
  "type": "Feature",
  "properties": {
    "iso:country":"DE",
    "sg:address":"Niederm\u00fcnchsdorf 16",
    "sg:city":"Osterhofen",
    "sg:postcode":"94486",
    "sg:province":"Bayern",
    "wof:name":"Sparmarkt Weigl",
    "wof:placetype":"venue"
},
  "geometry": {"coordinates":[13.0029563904,48.7193603516],"type":"Point"}
}