{
  "type": "Feature",
  "properties": {
    "iso:country":"DE",
    "sg:address":"Dieselstr. 8",
    "sg:city":"Emsb\u00fcren",
    "sg:phone":"+49 5903/7580",
    "sg:postcode":"48488",
    "sg:province":"Niedersachsen",
    "wof:name":"Ha-ga-tex Gmbh",
    "wof:placetype":"venue"
},
  "geometry": {"coordinates":[7.307775,52.380676],"type":"Point"}
}