{
  "type": "Feature",
  "properties": {
    "iso:country":"DE",
    "sg:address":"Gutenbergstr. 5",
    "sg:city":"Kaufbeuren",
    "sg:phone":"+49 8341/993033",
    "sg:postcode":"87600",
    "sg:province":"Bayern",
    "wof:name":"Volker Kraus",
    "wof:placetype":"venue"
},
  "geometry": {"coordinates":[10.6251392365,47.8813247681],"type":"Point"}
}