{
  "type": "Feature",
  "properties": {
    "iso:country":"DE",
    "sg:address":"In der Pfingstweide 1",
    "sg:city":"Ober-Ramstadt",
    "sg:phone":"+49 6154/52384",
    "sg:postcode":"64372",
    "sg:province":"Hessen",
    "wof:name":"Marcus Scherner",
    "wof:placetype":"venue"
},
  "geometry": {"coordinates":[8.7429571152,49.8380317688],"type":"Point"}
}