{
  "type": "Feature",
  "properties": {
    "iso:country":"DE",
    "sg:address":"Friedrich-Ebert-Str. 8",
    "sg:city":"Rastatt",
    "sg:phone":"+49 7222/32624",
    "sg:postcode":"76437",
    "sg:province":"Baden-W\u00fcrttemberg",
    "wof:name":"Karl-josef Fritz",
    "wof:placetype":"venue"
},
  "geometry": {"coordinates":[8.2079629898,48.8519287109],"type":"Point"}
}