{
  "type": "Feature",
  "properties": {
    "iso:country":"DE",
    "sg:address":"Schillerstr. 39",
    "sg:city":"Dessau",
    "sg:phone":"+49 340/2202020",
    "sg:postcode":"06844",
    "sg:province":"Sachsen-Anhalt",
    "wof:name":"Wemeta Werbeanlagenvertrieb Und Metallbauhandel Gmbh",
    "wof:placetype":"venue"
},
  "geometry": {"coordinates":[12.243977,51.846878],"type":"Point"}
}