{
  "type": "Feature",
  "properties": {
    "iso:country":"DE",
    "sg:address":"Heinrich-L\u00fcbke-Str. 26",
    "sg:city":"Bestwig",
    "sg:phone":"+49 2905/300",
    "sg:postcode":"59909",
    "sg:province":"Nordrhein-Westfalen",
    "wof:name":"Reiseb\u00fcro Bayram Inhaber Alfred Tusch E. K.",
    "wof:placetype":"venue"
},
  "geometry": {"coordinates":[8.402920723,51.3118553162],"type":"Point"}
}