{
  "type": "Feature",
  "properties": {
    "iso:country":"DE",
    "sg:address":"Sp\u00e4thstr. 16",
    "sg:city":"Kaiserslautern",
    "sg:phone":"+49 631/25108",
    "sg:postcode":"67655",
    "sg:province":"Rheinland-Pfalz",
    "wof:name":"Sontec Systemhaus F\u00fcr Hard- Und Software Gmbh",
    "wof:placetype":"venue"
},
  "geometry": {"coordinates":[7.754854,49.441681],"type":"Point"}
}