{
  "type": "Feature",
  "properties": {
    "iso:country":"DE",
    "sg:address":"Ahornweg 13",
    "sg:city":"Altensteig",
    "sg:phone":"+49 7453/7691",
    "sg:postcode":"72213",
    "sg:province":"Baden-W\u00fcrttemberg",
    "wof:name":"Hans-heinrich Looft Innenarchitekt",
    "wof:placetype":"venue"
},
  "geometry": {"coordinates":[8.612382,48.589939],"type":"Point"}
}