{
  "type": "Feature",
  "properties": {
    "iso:country":"DE",
    "sg:address":"Waldenserstr. 7-9",
    "sg:city":"M\u00fchlacker",
    "sg:phone":"+49 7041/937370",
    "sg:postcode":"75417",
    "sg:province":"Baden-W\u00fcrttemberg",
    "wof:name":"Maler Metzger Gmbh",
    "wof:placetype":"venue"
},
  "geometry": {"coordinates":[8.841367,48.943245],"type":"Point"}
}