{
  "type": "Feature",
  "properties": {
    "iso:country":"DE",
    "sg:address":"Hauptstr. 10",
    "sg:city":"Gersdorf",
    "sg:phone":"+49 37203/7587",
    "sg:postcode":"09355",
    "sg:province":"Sachsen",
    "wof:name":"Goldammer & Schneider Dachdecker Gmbh",
    "wof:placetype":"venue"
},
  "geometry": {"coordinates":[12.699002,50.780514],"type":"Point"}
}