{
  "type": "Feature",
  "properties": {
    "iso:country":"DE",
    "sg:address":"Am Holzkamp 38",
    "sg:city":"Kirchseelte",
    "sg:phone":"+49 4206/7029",
    "sg:postcode":"27243",
    "sg:province":"Niedersachsen",
    "wof:name":"Kurt M\u00f6ller Immobilienmakler",
    "wof:placetype":"venue"
},
  "geometry": {"coordinates":[8.6790714264,52.9631767273],"type":"Point"}
}