{
  "type": "Feature",
  "properties": {
    "iso:country":"DE",
    "sg:address":"Hauptstr. 9",
    "sg:city":"Wentorf",
    "sg:phone":"+49 40/7202360",
    "sg:postcode":"21465",
    "sg:province":"Schleswig-Holstein",
    "wof:name":"Neue Apotheke",
    "wof:placetype":"venue"
},
  "geometry": {"coordinates":[10.251503,53.511887],"type":"Point"}
}