{
  "type": "Feature",
  "properties": {
    "iso:country":"DE",
    "sg:address":"Weidweg 10",
    "sg:city":"Lampertheim",
    "sg:phone":"+49 6206/57474",
    "sg:postcode":"68623",
    "sg:province":"Hessen",
    "wof:name":"Restaurant Reiterstube",
    "wof:placetype":"venue"
},
  "geometry": {"coordinates":[8.4527778625,49.592376709],"type":"Point"}
}