{
  "type": "Feature",
  "properties": {
    "iso:country":"DE",
    "sg:address":"Friedrich-Ebert-Str. 50",
    "sg:city":"Hainburg",
    "sg:phone":"+49 6182/4994",
    "sg:postcode":"63512",
    "sg:province":"Hessen",
    "wof:name":"C\u00e4cilia Werner-klever",
    "wof:placetype":"venue"
},
  "geometry": {"coordinates":[8.967843,50.075584],"type":"Point"}
}