{
  "type": "Feature",
  "properties": {
    "iso:country":"DE",
    "sg:address":"Butzbacher Str. 4",
    "sg:city":"Frankfurt",
    "sg:phone":"+49 69/451727",
    "sg:postcode":"60389",
    "sg:province":"Hessen",
    "wof:name":"Konrad Fischer",
    "wof:placetype":"venue"
},
  "geometry": {"coordinates":[8.7005290985,50.1327819824],"type":"Point"}
}