{
  "type": "Feature",
  "properties": {
    "iso:country":"DE",
    "sg:address":"Gri\u00dfheimer Weg 13",
    "sg:city":"Heitersheim",
    "sg:phone":"+49 7634/1271",
    "sg:postcode":"79423",
    "sg:province":"Baden-W\u00fcrttemberg",
    "wof:name":"Johannes Klaucke",
    "wof:placetype":"venue"
},
  "geometry": {"coordinates":[7.648075,47.87458],"type":"Point"}
}