{
  "type": "Feature",
  "properties": {
    "iso:country":"DE",
    "sg:address":"Rochwitzer Weg 3 c",
    "sg:city":"Dresden",
    "sg:postcode":"01328",
    "sg:province":"Sachsen",
    "wof:name":"Tps Transfer-und Profilsysteme Gmbh",
    "wof:placetype":"venue"
},
  "geometry": {"coordinates":[13.85311,51.039799],"type":"Point"}
}