{
  "type": "Feature",
  "properties": {
    "iso:country":"DE",
    "sg:address":"Karl-Marx-Str. 6",
    "sg:city":"Walldorf",
    "sg:phone":"+49 3693/893852",
    "sg:postcode":"98639",
    "sg:province":"Th\u00fcringen",
    "wof:name":"J. Thomas",
    "wof:placetype":"venue"
},
  "geometry": {"coordinates":[10.388205,50.610714],"type":"Point"}
}