{
  "type": "Feature",
  "properties": {
    "iso:country":"DE",
    "sg:address":"Karl-H\u00e4rting-Str. 3",
    "sg:city":"Leipzig",
    "sg:postcode":"04318",
    "sg:province":"Sachsen",
    "wof:name":"Peter Gottschalk",
    "wof:placetype":"venue"
},
  "geometry": {"coordinates":[12.4319953918,51.3406448364],"type":"Point"}
}