{
  "type": "Feature",
  "properties": {
    "iso:country":"DE",
    "sg:address":"Ahornstr. 12",
    "sg:city":"Unna",
    "sg:phone":"+49 2303/82399",
    "sg:postcode":"59423",
    "sg:province":"Nordrhein-Westfalen",
    "wof:name":"U. H\u00f6ltermann",
    "wof:placetype":"venue"
},
  "geometry": {"coordinates":[7.678989,51.524464],"type":"Point"}
}