{
  "type": "Feature",
  "properties": {
    "iso:country":"DE",
    "sg:address":"Marler Platz",
    "sg:city":"Bitterfeld",
    "sg:phone":"+49 3493/21553",
    "sg:postcode":"06749",
    "sg:province":"Sachsen-Anhalt",
    "wof:name":"Hauptvertretung Allianz Mechtild Fa\u00dfhauer",
    "wof:placetype":"venue"
},
  "geometry": {"coordinates":[12.3249645233,51.6252250671],"type":"Point"}
}