{
  "type": "Feature",
  "properties": {
    "iso:country":"DE",
    "sg:address":"escherstrasse 27",
    "sg:city":"Hannover",
    "sg:phone":"+49 511/1690905",
    "sg:postcode":"30167",
    "sg:province":"Niedersachsen",
    "wof:name":"Russland Sex Zeigt Sexmodells Nackt U. Live",
    "wof:placetype":"venue"
},
  "geometry": {"coordinates":[9.725495,52.382545],"type":"Point"}
}