{
  "type": "Feature",
  "properties": {
    "iso:country":"DE",
    "sg:address":"Leonhardiweg 16",
    "sg:city":"Ruhstorf",
    "sg:phone":"+49 8531/3712",
    "sg:postcode":"94099",
    "sg:province":"Bayern",
    "wof:name":"Brieger Putz Gmbh",
    "wof:placetype":"venue"
},
  "geometry": {"coordinates":[13.342798233,48.4354438782],"type":"Point"}
}