{
  "type": "Feature",
  "properties": {
    "iso:country":"DE",
    "sg:address":"Klauser",
    "sg:city":"Oberg\u00fcnzburg",
    "sg:phone":"+49 8306/7168",
    "sg:postcode":"87634",
    "sg:province":"Bayern",
    "wof:name":"Michael Schmid",
    "wof:placetype":"venue"
},
  "geometry": {"coordinates":[10.41894,47.878139],"type":"Point"}
}