{
  "type": "Feature",
  "properties": {
    "iso:country":"DE",
    "sg:address":"Roscherstr. 17 - 21",
    "sg:city":"Leipzig",
    "sg:phone":"+49 341/589490",
    "sg:postcode":"04105",
    "sg:province":"Sachsen",
    "wof:name":"Kfz-sachverst\u00e4ndigen B\u00fcro L\u00fcbke & Wolter",
    "wof:placetype":"venue"
},
  "geometry": {"coordinates":[12.379445076,51.3533592224],"type":"Point"}
}