{
  "type": "Feature",
  "properties": {
    "iso:country":"DE",
    "sg:address":"Mannheimer Str. 73",
    "sg:city":"Frankfurt",
    "sg:postcode":"60327",
    "sg:province":"Hessen",
    "wof:name":"Condor Condor-charterfl\u00fcge Charter Online Fl\u00fcge",
    "wof:placetype":"venue"
},
  "geometry": {"coordinates":[8.662445,50.103062],"type":"Point"}
}