{
  "type": "Feature",
  "properties": {
    "iso:country":"DE",
    "sg:address":"Heeper Str. 133",
    "sg:city":"Bielefeld",
    "sg:phone":"+49 521/64283",
    "sg:postcode":"33607",
    "sg:province":"Nordrhein-Westfalen",
    "wof:name":"Zweirad W\u00f6hrmann",
    "wof:placetype":"venue"
},
  "geometry": {"coordinates":[8.558811,52.022617],"type":"Point"}
}