{
  "type": "Feature",
  "properties": {
    "iso:country":"DE",
    "sg:address":"Roermonder Str. 74",
    "sg:city":"D\u00fcren",
    "sg:phone":"+49 2421/84831",
    "sg:postcode":"52353",
    "sg:province":"Nordrhein-Westfalen",
    "wof:name":"Peter Feucht",
    "wof:placetype":"venue"
},
  "geometry": {"coordinates":[6.4261,50.840141],"type":"Point"}
}