{
  "type": "Feature",
  "properties": {
    "iso:country":"DE",
    "sg:address":"Berliner Str. 494",
    "sg:city":"G\u00fctersloh",
    "sg:phone":"+49 5241/67279",
    "sg:postcode":"33334",
    "sg:province":"Nordrhein-Westfalen",
    "wof:name":"Willi Lemoine Schausteller",
    "wof:placetype":"venue"
},
  "geometry": {"coordinates":[8.42142,51.938183],"type":"Point"}
}