{
  "type": "Feature",
  "properties": {
    "iso:country":"DE",
    "sg:address":"Herrenstr. 14-16",
    "sg:city":"Freiburg",
    "sg:phone":"+49 761/22490",
    "sg:postcode":"79098",
    "sg:province":"Baden-W\u00fcrttemberg",
    "wof:name":"Kunstspiegel-rusticana Gmbh",
    "wof:placetype":"venue"
},
  "geometry": {"coordinates":[7.854043,47.995785],"type":"Point"}
}