{
  "type": "Feature",
  "properties": {
    "iso:country":"DE",
    "sg:address":"Alt Prester 84",
    "sg:city":"Magdeburg",
    "sg:phone":"+49 391/818020",
    "sg:postcode":"39114",
    "sg:province":"Sachsen-Anhalt",
    "wof:name":"Darec Gmbh",
    "wof:placetype":"venue"
},
  "geometry": {"coordinates":[11.6746959686,52.1041221619],"type":"Point"}
}