{
  "type": "Feature",
  "properties": {
    "iso:country":"DE",
    "sg:address":"An der Miele 10",
    "sg:city":"Meldorf",
    "sg:phone":"+49 4832/95050",
    "sg:postcode":"25704",
    "sg:province":"Schleswig-Holstein",
    "wof:name":"Telefon-karten-journal",
    "wof:placetype":"venue"
},
  "geometry": {"coordinates":[9.0634098053,54.0955123901],"type":"Point"}
}