{
  "type": "Feature",
  "properties": {
    "iso:country":"DE",
    "sg:address":"Bahnhofstr 18",
    "sg:city":"Heiningen",
    "sg:phone":"+49 7161/943000",
    "sg:postcode":"73092",
    "sg:province":"Baden-W\u00fcrttemberg",
    "wof:name":"Hapex Werkzeugmaschinen Service Und Vertriebs Gmbh",
    "wof:placetype":"venue"
},
  "geometry": {"coordinates":[9.648733,48.656216],"type":"Point"}
}