{
  "type": "Feature",
  "properties": {
    "iso:country":"DE",
    "sg:address":"Blechhammerweg 50",
    "sg:city":"Kaiserslautern",
    "sg:phone":"+49 631/95517",
    "sg:postcode":"67659",
    "sg:province":"Rheinland-Pfalz",
    "wof:name":"Kaiserm\u00fchle",
    "wof:placetype":"venue"
},
  "geometry": {"coordinates":[7.7432971001,49.4566459656],"type":"Point"}
}