{
  "type": "Feature",
  "properties": {
    "iso:country":"DE",
    "sg:address":"Hauptstr. 150",
    "sg:city":"Gaggenau",
    "sg:phone":"+49 7225/3291",
    "sg:postcode":"76571",
    "sg:province":"Baden-W\u00fcrttemberg",
    "wof:name":"Krug Metzgerei Vieh- Und Fleischhandel Gmbh",
    "wof:placetype":"venue"
},
  "geometry": {"coordinates":[8.3268947601,48.7947921753],"type":"Point"}
}