{
  "type": "Feature",
  "properties": {
    "iso:country":"DE",
    "sg:address":"Aluminiumstr. 1",
    "sg:city":"Verl",
    "sg:phone":"+49 5241/86070",
    "sg:postcode":"33415",
    "sg:province":"Nordrhein-Westfalen",
    "wof:name":"N\u00fc\u00dfing Gmbh",
    "wof:placetype":"venue"
},
  "geometry": {"coordinates":[8.465494,51.877621],"type":"Point"}
}