{
  "type": "Feature",
  "properties": {
    "iso:country":"DE",
    "sg:address":"Hubertusstr. 6",
    "sg:city":"Alsdorf",
    "sg:phone":"+49 2404/86618",
    "sg:postcode":"52477",
    "sg:province":"Nordrhein-Westfalen",
    "wof:name":"Artemis",
    "wof:placetype":"venue"
},
  "geometry": {"coordinates":[6.1655597687,50.87525177],"type":"Point"}
}