{
  "type": "Feature",
  "properties": {
    "iso:country":"DE",
    "sg:address":"Im Dorf 46",
    "sg:city":"Wadgassen",
    "sg:phone":"+49 6834/41771",
    "sg:postcode":"66787",
    "sg:province":"Saarland",
    "wof:name":"Kurt Burgard",
    "wof:placetype":"venue"
},
  "geometry": {"coordinates":[6.809387,49.256081],"type":"Point"}
}