{
  "type": "Feature",
  "properties": {
    "iso:country":"DE",
    "sg:address":"Fr\u00fchlingstr. 37",
    "sg:city":"Freising",
    "sg:phone":"+49 8161/91590",
    "sg:postcode":"85354",
    "sg:province":"Bayern",
    "wof:name":"Tina",
    "wof:placetype":"venue"
},
  "geometry": {"coordinates":[11.73389,48.391087],"type":"Point"}
}