{
  "type": "Feature",
  "properties": {
    "iso:country":"DE",
    "sg:address":"S\u00f6llerstr. 15-17",
    "sg:city":"Lauenburg",
    "sg:phone":"+49 4153/3505",
    "sg:postcode":"21481",
    "sg:province":"Schleswig-Holstein",
    "wof:name":"Be Betonelemente Gmbh",
    "wof:placetype":"venue"
},
  "geometry": {"coordinates":[10.582983017,53.3698120117],"type":"Point"}
}