{
  "type": "Feature",
  "properties": {
    "iso:country":"DE",
    "sg:address":"Waldstr. 20",
    "sg:city":"Zwingenberg",
    "sg:phone":"+49 6263/8224",
    "sg:postcode":"69439",
    "sg:province":"Baden-W\u00fcrttemberg",
    "wof:name":"W. Schulz Ingenieur Gmbh",
    "wof:placetype":"venue"
},
  "geometry": {"coordinates":[9.0494775772,49.4127578735],"type":"Point"}
}