{
  "type": "Feature",
  "properties": {
    "iso:country":"DE",
    "sg:address":"Mainzer Landstr. 46",
    "sg:city":"Frankfurt",
    "sg:phone":"+49 69/2385210",
    "sg:postcode":"60325",
    "sg:province":"Hessen",
    "wof:name":"Gatx Leasing Services Gmbh & Co. Projekt Kappa Kg",
    "wof:placetype":"venue"
},
  "geometry": {"coordinates":[8.663898,50.110981],"type":"Point"}
}