{
  "type": "Feature",
  "properties": {
    "iso:country":"DE",
    "sg:address":"Hauptstr. 7",
    "sg:city":"Toppenstedt",
    "sg:postcode":"21442",
    "sg:province":"Niedersachsen",
    "wof:name":"Uwe Wix E. K.",
    "wof:placetype":"venue"
},
  "geometry": {"coordinates":[10.1164674759,53.2646560669],"type":"Point"}
}