{
  "type": "Feature",
  "properties": {
    "iso:country":"DE",
    "sg:address":"Taunusblick 18",
    "sg:city":"Usingen",
    "sg:phone":"+49 6081/3988",
    "sg:postcode":"61250",
    "sg:province":"Hessen",
    "wof:name":"Edith Zimmer",
    "wof:placetype":"venue"
},
  "geometry": {"coordinates":[8.5413074493,50.3611946106],"type":"Point"}
}