{
  "type": "Feature",
  "properties": {
    "iso:country":"DE",
    "sg:address":"Passauer Str. 88",
    "sg:city":"Winzer",
    "sg:phone":"+49 9901/2220",
    "sg:postcode":"94577",
    "sg:province":"Bayern",
    "wof:name":"Josef Einhellig",
    "wof:placetype":"venue"
},
  "geometry": {"coordinates":[13.0766172409,48.7227592468],"type":"Point"}
}