{
  "type": "Feature",
  "properties": {
    "iso:country":"DE",
    "sg:address":"Naumburger Str. 8",
    "sg:city":"Hermsdorf",
    "sg:phone":"+49 36601/40775",
    "sg:postcode":"07629",
    "sg:province":"Th\u00fcringen",
    "wof:name":"Athen",
    "wof:placetype":"venue"
},
  "geometry": {"coordinates":[11.8539056778,50.8995132446],"type":"Point"}
}