{
  "type": "Feature",
  "properties": {
    "iso:country":"DE",
    "sg:address":"Im Teich 48",
    "sg:city":"Nauheim",
    "sg:phone":"+49 6152/62826",
    "sg:postcode":"64569",
    "sg:province":"Hessen",
    "wof:name":"Apeg Wohnbau Gmbh",
    "wof:placetype":"venue"
},
  "geometry": {"coordinates":[8.464192,49.957161],"type":"Point"}
}