{
  "type": "Feature",
  "properties": {
    "iso:country":"DE",
    "sg:address":"Am Hallenbad 2",
    "sg:city":"Stadtallendorf",
    "sg:phone":"+49 6428/2572",
    "sg:postcode":"35260",
    "sg:province":"Hessen",
    "wof:name":"Sport- Und Freizeitbad",
    "wof:placetype":"venue"
},
  "geometry": {"coordinates":[9.0143051147,50.8278160095],"type":"Point"}
}