{
  "type": "Feature",
  "properties": {
    "iso:country":"DE",
    "sg:address":"Alt-Wittenau 62",
    "sg:city":"Berlin",
    "sg:phone":"+49 30/4111462",
    "sg:postcode":"13437",
    "sg:province":"Berlin",
    "wof:name":"Karin Baer",
    "wof:placetype":"venue"
},
  "geometry": {"coordinates":[13.324996,52.591942],"type":"Point"}
}