{
  "type": "Feature",
  "properties": {
    "iso:country":"DE",
    "sg:address":"Eulerstr.",
    "sg:city":"Ransbach-Baumbach",
    "sg:phone":"+49 2623/1202",
    "sg:postcode":"56235",
    "sg:province":"Rheinland-Pfalz",
    "wof:name":"Atelier F\u00fcr Modene Gestaltung Helmut Hartenfels",
    "wof:placetype":"venue"
},
  "geometry": {"coordinates":[7.7252511978,50.4611473083],"type":"Point"}
}