{
  "type": "Feature",
  "properties": {
    "iso:country":"DE",
    "sg:address":"Gl\u00fcckaufsegenstr. 82",
    "sg:city":"Dortmund",
    "sg:phone":"+49 231/402437",
    "sg:postcode":"44265",
    "sg:province":"Nordrhein-Westfalen",
    "wof:name":"Korbach - Gmbh",
    "wof:placetype":"venue"
},
  "geometry": {"coordinates":[7.4795861244,51.4755249023],"type":"Point"}
}