{
  "type": "Feature",
  "properties": {
    "iso:country":"DE",
    "sg:address":"Friedrichstr. 2a",
    "sg:city":"Sinsheim",
    "sg:phone":"+49 7261/2034",
    "sg:postcode":"74889",
    "sg:province":"Baden-W\u00fcrttemberg",
    "wof:name":"Vertrauens\u00e4rztlicher-dienst Der Lva Baden",
    "wof:placetype":"venue"
},
  "geometry": {"coordinates":[8.879486084,49.2523918152],"type":"Point"}
}