{
  "type": "Feature",
  "properties": {
    "iso:country":"DE",
    "sg:address":"Vikarstr. 29",
    "sg:city":"M\u00f6mbris",
    "sg:phone":"+49 6029/995900",
    "sg:postcode":"63776",
    "sg:province":"Bayern",
    "wof:name":"Bautr\u00e4ger Am Beilstein Gmbh",
    "wof:placetype":"venue"
},
  "geometry": {"coordinates":[9.1628799438,50.0452690125],"type":"Point"}
}