{
  "type": "Feature",
  "properties": {
    "iso:country":"DE",
    "sg:address":"Warsteiner Str. 6",
    "sg:city":"Meschede",
    "sg:phone":"+49 291/2305",
    "sg:postcode":"59872",
    "sg:province":"Nordrhein-Westfalen",
    "wof:name":"D. E\u00dfer",
    "wof:placetype":"venue"
},
  "geometry": {"coordinates":[8.2815084457,51.3495063782],"type":"Point"}
}