{
  "type": "Feature",
  "properties": {
    "iso:country":"DE",
    "sg:address":"Sofienstr. 9",
    "sg:city":"Rottenburg",
    "sg:phone":"+49 7472/98030",
    "sg:postcode":"72108",
    "sg:province":"Baden-W\u00fcrttemberg",
    "wof:name":"Novis Networking Gmbh",
    "wof:placetype":"venue"
},
  "geometry": {"coordinates":[8.9383840561,48.4785614014],"type":"Point"}
}