{
  "type": "Feature",
  "properties": {
    "iso:country":"DE",
    "sg:address":"Hochstr. 7",
    "sg:city":"Reichelsheim",
    "sg:postcode":"64385",
    "sg:province":"Hessen",
    "wof:name":"Tbg Gmbh & Co. Kg",
    "wof:placetype":"venue"
},
  "geometry": {"coordinates":[8.842608,49.709667],"type":"Point"}
}