{
  "type": "Feature",
  "properties": {
    "iso:country":"DE",
    "sg:address":"Zur Schafbr\u00fccke 51",
    "sg:city":"Wuppertal",
    "sg:phone":"+49 202/554299",
    "sg:postcode":"42283",
    "sg:province":"Nordrhein-Westfalen",
    "wof:name":"Ulrich H\u00fcttenberend",
    "wof:placetype":"venue"
},
  "geometry": {"coordinates":[7.1920051575,51.2718315125],"type":"Point"}
}