{
  "type": "Feature",
  "properties": {
    "iso:country":"DE",
    "sg:address":"Kieshecker Wg. 144",
    "sg:city":"D\u00fcsseldorf",
    "sg:phone":"+49 4969/9399790",
    "sg:postcode":"40468",
    "sg:province":"Nordrhein-Westfalen",
    "wof:name":"Pfitzner Rettungs- Ausr\u00dcstung Gmbh",
    "wof:placetype":"venue"
},
  "geometry": {"coordinates":[8.601479,50.096771],"type":"Point"}
}