{
  "type": "Feature",
  "properties": {
    "iso:country":"DE",
    "sg:address":"Sandweg 4",
    "sg:city":"Burkau",
    "sg:phone":"+49 35953/6363",
    "sg:postcode":"01906",
    "sg:province":"Sachsen",
    "wof:name":"Margarete Anders",
    "wof:placetype":"venue"
},
  "geometry": {"coordinates":[14.1939430237,51.1801528931],"type":"Point"}
}