{
  "type": "Feature",
  "properties": {
    "iso:country":"DE",
    "sg:address":"Schulstr. 5",
    "sg:city":"M\u00f6gglingen",
    "sg:postcode":"73563",
    "sg:province":"Baden-W\u00fcrttemberg",
    "wof:name":"Neudecker Montage Gmbh",
    "wof:placetype":"venue"
},
  "geometry": {"coordinates":[9.963061,48.822441],"type":"Point"}
}