{
  "type": "Feature",
  "properties": {
    "iso:country":"DE",
    "sg:address":"Heilbronner Str. 37",
    "sg:city":"Bad Friedrichshall",
    "sg:phone":"+49 7136/23763",
    "sg:postcode":"74177",
    "sg:province":"Baden-W\u00fcrttemberg",
    "wof:name":"Hartmut Schiffter",
    "wof:placetype":"venue"
},
  "geometry": {"coordinates":[9.2153711319,49.2186737061],"type":"Point"}
}