{
  "type": "Feature",
  "properties": {
    "iso:country":"DE",
    "sg:address":"Ayrerstr. 1",
    "sg:city":"Ingolstadt",
    "sg:postcode":"85055",
    "sg:province":"Bayern",
    "wof:name":"Lithoscript Gmbh",
    "wof:placetype":"venue"
},
  "geometry": {"coordinates":[11.4538974762,48.7689666748],"type":"Point"}
}