{
  "type": "Feature",
  "properties": {
    "iso:country":"DE",
    "sg:address":"M\u00fchlenstr. 30",
    "sg:city":"Wittenbergen",
    "sg:phone":"+49 4822/5807",
    "sg:postcode":"25548",
    "sg:province":"Schleswig-Holstein",
    "wof:name":"Manfred Kr\u00f6ger",
    "wof:placetype":"venue"
},
  "geometry": {"coordinates":[9.688768,53.933441],"type":"Point"}
}