{
  "type": "Feature",
  "properties": {
    "iso:country":"DE",
    "sg:address":"Hauptstr. 29",
    "sg:city":"Selsingen",
    "sg:phone":"+49 4284/348",
    "sg:postcode":"27446",
    "sg:province":"Niedersachsen",
    "wof:name":"Heinrich Vollmer",
    "wof:placetype":"venue"
},
  "geometry": {"coordinates":[9.214212,53.372749],"type":"Point"}
}