{
  "type": "Feature",
  "properties": {
    "iso:country":"DE",
    "sg:address":"Langenalber Str. 8",
    "sg:city":"Straubenhardt",
    "sg:phone":"+49 7082/2156",
    "sg:postcode":"75334",
    "sg:province":"Baden-W\u00fcrttemberg",
    "wof:name":"Ilse Kreis",
    "wof:placetype":"venue"
},
  "geometry": {"coordinates":[8.5307445526,48.8543624878],"type":"Point"}
}