{
  "type": "Feature",
  "properties": {
    "iso:country":"DE",
    "sg:address":"Schm\u00e4hgasse 26",
    "sg:city":"Ha\u00dfloch",
    "sg:phone":"+49 6324/1426",
    "sg:postcode":"67454",
    "sg:province":"Rheinland-Pfalz",
    "wof:name":"Klemens Seelos",
    "wof:placetype":"venue"
},
  "geometry": {"coordinates":[8.262944,49.357914],"type":"Point"}
}