{
  "type": "Feature",
  "properties": {
    "iso:country":"DE",
    "sg:address":"Fremersbergstr. 1",
    "sg:city":"Baden-Baden",
    "sg:phone":"+49 7221/31811",
    "sg:postcode":"76530",
    "sg:province":"Baden-W\u00fcrttemberg",
    "wof:name":"Redaktion Film 816 & Video Verlag F\u00fcr Technik Und",
    "wof:placetype":"venue"
},
  "geometry": {"coordinates":[8.2365913391,48.7548217773],"type":"Point"}
}