{
  "type": "Feature",
  "properties": {
    "iso:country":"DE",
    "sg:address":"Dorfstr.",
    "sg:city":"Kyritz",
    "sg:phone":"+49 33971/71504",
    "sg:postcode":"16866",
    "sg:province":"Brandenburg",
    "wof:name":"Ilona Gielnik",
    "wof:placetype":"venue"
},
  "geometry": {"coordinates":[12.3542346954,52.9771995544],"type":"Point"}
}