{
  "type": "Feature",
  "properties": {
    "iso:country":"DE",
    "sg:address":"Augustastr.21a",
    "sg:city":"Berlin",
    "sg:phone":"+49 30",
    "sg:postcode":"12203",
    "sg:province":"Berlin",
    "wof:name":"Planar",
    "wof:placetype":"venue"
},
  "geometry": {"coordinates":[13.301958,52.440407],"type":"Point"}
}