{
  "type": "Feature",
  "properties": {
    "iso:country":"DE",
    "sg:address":"Hauskampstr. 39",
    "sg:city":"M\u00fclheim",
    "sg:phone":"+49 208/840091",
    "sg:postcode":"45476",
    "sg:province":"Nordrhein-Westfalen",
    "wof:name":"Wollnitz Gmbh",
    "wof:placetype":"venue"
},
  "geometry": {"coordinates":[6.854691,51.447964],"type":"Point"}
}