{
  "type": "Feature",
  "properties": {
    "iso:country":"DE",
    "sg:address":"Oskar-Pletsch-Str. 3",
    "sg:city":"Dresden",
    "sg:postcode":"01324",
    "sg:province":"Sachsen",
    "wof:name":"Modell-agentur Loar",
    "wof:placetype":"venue"
},
  "geometry": {"coordinates":[13.8224277496,51.0598602295],"type":"Point"}
}