{
  "type": "Feature",
  "properties": {
    "iso:country":"DE",
    "sg:address":"Hauptstr. 223",
    "sg:city":"Briedel",
    "sg:phone":"+49 6542/4484",
    "sg:postcode":"56867",
    "sg:province":"Rheinland-Pfalz",
    "wof:name":"Josef Eigelshoven Weinanbau",
    "wof:placetype":"venue"
},
  "geometry": {"coordinates":[7.1461210251,50.028968811],"type":"Point"}
}