{
  "type": "Feature",
  "properties": {
    "iso:country":"DE",
    "sg:address":"Am Kirchberg 2",
    "sg:city":"Bad Salzdetfurth",
    "sg:phone":"+49 5064/382",
    "sg:postcode":"31162",
    "sg:province":"Niedersachsen",
    "wof:name":"Ev.-luth. Pfarramt Gem. Heinde",
    "wof:placetype":"venue"
},
  "geometry": {"coordinates":[10.0378398895,52.1001167297],"type":"Point"}
}