{
  "type": "Feature",
  "properties": {
    "iso:country":"DE",
    "sg:address":"Wettberger Str. 1",
    "sg:city":"Ronnenberg",
    "sg:phone":"+49 5109/2461",
    "sg:postcode":"30952",
    "sg:province":"Niedersachsen",
    "wof:name":"Friedrich Flachsbarth",
    "wof:placetype":"venue"
},
  "geometry": {"coordinates":[9.677364,52.305737],"type":"Point"}
}