{
  "type": "Feature",
  "properties": {
    "iso:country":"DE",
    "sg:address":"Am Lachengraben 1a",
    "sg:city":"Dreieich",
    "sg:phone":"+49 6103/86099",
    "sg:postcode":"63303",
    "sg:province":"Hessen",
    "wof:name":"Techni-science Ex-& Import Gmbh",
    "wof:placetype":"venue"
},
  "geometry": {"coordinates":[8.734965,50.000301],"type":"Point"}
}