{
  "type": "Feature",
  "properties": {
    "iso:country":"DE",
    "sg:address":"Friedrich-Engels-Str. 51",
    "sg:city":"Jena",
    "sg:phone":"+49 3641/396916",
    "sg:postcode":"07749",
    "sg:province":"Th\u00fcringen",
    "wof:name":"F. Sommerfeld",
    "wof:placetype":"venue"
},
  "geometry": {"coordinates":[11.5996017456,50.9233283997],"type":"Point"}
}