{
  "type": "Feature",
  "properties": {
    "iso:country":"DE",
    "sg:address":"Gierather Wald 20",
    "sg:city":"Bergisch Gladbach",
    "sg:phone":"+49 2202/57512",
    "sg:postcode":"51469",
    "sg:province":"Nordrhein-Westfalen",
    "wof:name":"Hein Immobilienmakler",
    "wof:placetype":"venue"
},
  "geometry": {"coordinates":[7.1023650169,50.976108551],"type":"Point"}
}