{
  "type": "Feature",
  "properties": {
    "iso:country":"DE",
    "sg:address":"Georgenh\u00e4user Str. 20",
    "sg:city":"Reinheim",
    "sg:phone":"+49 6162/50191",
    "sg:postcode":"64354",
    "sg:province":"Hessen",
    "wof:name":"Andrea Wilken",
    "wof:placetype":"venue"
},
  "geometry": {"coordinates":[8.7945766449,49.8440933228],"type":"Point"}
}