{
  "type": "Feature",
  "properties": {
    "iso:country":"DE",
    "sg:address":"Further Str",
    "sg:city":"Wendelstein",
    "sg:phone":"+49 9129/4548",
    "sg:postcode":"90530",
    "sg:province":"Bayern",
    "wof:name":"Optik Martin",
    "wof:placetype":"venue"
},
  "geometry": {"coordinates":[11.1448411942,49.3536376953],"type":"Point"}
}