{
  "type": "Feature",
  "properties": {
    "iso:country":"DE",
    "sg:address":"Werner-Hilpert-Str. 26",
    "sg:city":"Kassel",
    "sg:phone":"+49 561/107491",
    "sg:postcode":"34117",
    "sg:province":"Hessen",
    "wof:name":"Kabarcik",
    "wof:placetype":"venue"
},
  "geometry": {"coordinates":[9.4918403625,51.3181686401],"type":"Point"}
}