{
  "type": "Feature",
  "properties": {
    "iso:country":"DE",
    "sg:address":"Pfannenschmiedsgasse 4",
    "sg:city":"N\u00fcrnberg",
    "sg:phone":"+49 911/221953",
    "sg:postcode":"90402",
    "sg:province":"Bayern",
    "wof:name":"Costei Kaffee Und Tee Gmbh & Co.",
    "wof:placetype":"venue"
},
  "geometry": {"coordinates":[11.0775823593,49.450378418],"type":"Point"}
}