{
  "type": "Feature",
  "properties": {
    "iso:country":"DE",
    "sg:address":"Kreuzbergstr. 27",
    "sg:city":"Remscheid",
    "sg:phone":"+49 4921/9150430",
    "sg:postcode":"42899",
    "sg:province":"Nordrhein-Westfalen",
    "wof:name":"Richard M\u00dcller Kg",
    "wof:placetype":"venue"
},
  "geometry": {"coordinates":[7.23566,51.210464],"type":"Point"}
}