{
  "type": "Feature",
  "properties": {
    "iso:country":"DE",
    "sg:address":"Parkstr. 15",
    "sg:city":"M\u00fcnchen",
    "sg:phone":"+49 89/58998476",
    "sg:postcode":"80339",
    "sg:province":"Bayern",
    "wof:name":"Encanto Networks Gmbh",
    "wof:placetype":"venue"
},
  "geometry": {"coordinates":[11.5442495346,48.1365509033],"type":"Point"}
}