{
  "type": "Feature",
  "properties": {
    "iso:country":"DE",
    "sg:address":"Unter Mastein 5",
    "sg:city":"Schweich",
    "sg:postcode":"54338",
    "sg:province":"Rheinland-Pfalz",
    "wof:name":"Ts System Haus Gmbh",
    "wof:placetype":"venue"
},
  "geometry": {"coordinates":[6.748355,49.820583],"type":"Point"}
}