{
  "type": "Feature",
  "properties": {
    "iso:country":"DE",
    "sg:address":"Hauptstr. 162",
    "sg:city":"Schwarza",
    "sg:phone":"+49 36843/60293",
    "sg:postcode":"98547",
    "sg:province":"Th\u00fcringen",
    "wof:name":"Heinz Baumann",
    "wof:placetype":"venue"
},
  "geometry": {"coordinates":[10.524126,50.612713],"type":"Point"}
}