{
  "type": "Feature",
  "properties": {
    "iso:country":"DE",
    "sg:address":"Rh\u00f6ndorfer Stra\u00dfe 87",
    "sg:city":"Bad Honnef",
    "sg:phone":"+49 2224",
    "sg:postcode":"53604",
    "sg:province":"Nordrhein-Westfalen",
    "wof:name":"Baeko-bundeszentrale Eg",
    "wof:placetype":"venue"
},
  "geometry": {"coordinates":[7.2170162201,50.6543121338],"type":"Point"}
}