{
  "type": "Feature",
  "properties": {
    "iso:country":"DE",
    "sg:address":"Am alden Schmidt",
    "sg:city":"Kleve",
    "sg:postcode":"47533",
    "sg:province":"Nordrhein-Westfalen",
    "wof:name":"Angelsportverein Kleve",
    "wof:placetype":"venue"
},
  "geometry": {"coordinates":[6.1652140617,51.8048362732],"type":"Point"}
}