{
  "type": "Feature",
  "properties": {
    "iso:country":"DE",
    "sg:address":"Am Nachbarsberg 46",
    "sg:city":"Haan",
    "sg:phone":"+49 212/931875",
    "sg:postcode":"42781",
    "sg:province":"Nordrhein-Westfalen",
    "wof:name":"Horst Gr\u00fctzmacher Architekt",
    "wof:placetype":"venue"
},
  "geometry": {"coordinates":[7.023806,51.195377],"type":"Point"}
}