{
  "type": "Feature",
  "properties": {
    "iso:country":"DE",
    "sg:address":"Fleher Str. 256",
    "sg:city":"D\u00fcsseldorf",
    "sg:phone":"+49 211/153657",
    "sg:postcode":"40223",
    "sg:province":"Nordrhein-Westfalen",
    "wof:name":"M. Boumahdi",
    "wof:placetype":"venue"
},
  "geometry": {"coordinates":[6.770969,51.1912],"type":"Point"}
}