{
  "type": "Feature",
  "properties": {
    "iso:country":"DE",
    "sg:address":"Hertener Str. 35",
    "sg:city":"Recklinghausen",
    "sg:phone":"+49 2361/26029",
    "sg:postcode":"45657",
    "sg:province":"Nordrhein-Westfalen",
    "wof:name":"Dr. Grossjohann Und Schlemmer Rechtsanw\u00e4lte Und Notare",
    "wof:placetype":"venue"
},
  "geometry": {"coordinates":[7.1887412071,51.6106948853],"type":"Point"}
}