{
  "type": "Feature",
  "properties": {
    "iso:country":"DE",
    "sg:address":"Haschaberg",
    "sg:city":"Haschaberg",
    "sg:postcode":"93449",
    "sg:province":"Bayern",
    "wof:name":"A. Gschwendtner",
    "wof:placetype":"venue"
},
  "geometry": {"coordinates":[12.648524,49.340973],"type":"Point"}
}