{
  "type": "Feature",
  "properties": {
    "iso:country":"DE",
    "sg:address":"Urnagold 7",
    "sg:city":"Seewald",
    "sg:phone":"+49 7448/509",
    "sg:postcode":"72297",
    "sg:province":"Baden-W\u00fcrttemberg",
    "wof:name":"Hirsch",
    "wof:placetype":"venue"
},
  "geometry": {"coordinates":[8.4353218079,48.6018562317],"type":"Point"}
}