{
  "type": "Feature",
  "properties": {
    "iso:country":"DE",
    "sg:address":"Z\u00e4hringer Str 68",
    "sg:city":"Mannheim",
    "sg:phone":"+49 621/471216",
    "sg:postcode":"68239",
    "sg:province":"Baden-W\u00fcrttemberg",
    "wof:name":"Schmidt & Sohn Gmbh",
    "wof:placetype":"venue"
},
  "geometry": {"coordinates":[8.5582761765,49.4665985107],"type":"Point"}
}