{
  "type": "Feature",
  "properties": {
    "iso:country":"DE",
    "sg:address":"Dr.-Wilhelm-K\u00fclz-Str. 80",
    "sg:city":"Brand-Erbisdorf",
    "sg:phone":"+49 37322/81487",
    "sg:postcode":"09618",
    "sg:province":"Sachsen",
    "wof:name":"Frank Glei\u00dfner",
    "wof:placetype":"venue"
},
  "geometry": {"coordinates":[13.328593,50.87376],"type":"Point"}
}