{
  "type": "Feature",
  "properties": {
    "iso:country":"DE",
    "sg:address":"Borgfelder Deich 17b",
    "sg:city":"Bremen",
    "sg:postcode":"28357",
    "sg:province":"Bremen",
    "wof:name":"Keith Vince Golf Gmbh",
    "wof:placetype":"venue"
},
  "geometry": {"coordinates":[8.892757,53.131573],"type":"Point"}
}