{
  "type": "Feature",
  "properties": {
    "iso:country":"DE",
    "sg:address":"Hauptstr. 30",
    "sg:city":"Altenstadt",
    "sg:phone":"+49 4960/479890",
    "sg:postcode":"63674",
    "sg:province":"Hessen",
    "wof:name":"Osi Software Gmbh",
    "wof:placetype":"venue"
},
  "geometry": {"coordinates":[8.9416465759,50.2761268616],"type":"Point"}
}