{
  "type": "Feature",
  "properties": {
    "iso:country":"DE",
    "sg:address":"Hallstr. 25",
    "sg:city":"Stuttgart",
    "sg:phone":"+49 711/541112",
    "sg:postcode":"70376",
    "sg:province":"Baden-W\u00fcrttemberg",
    "wof:name":"Architektenb\u00fcro 4a",
    "wof:placetype":"venue"
},
  "geometry": {"coordinates":[9.209832,48.808037],"type":"Point"}
}