{
  "type": "Feature",
  "properties": {
    "iso:country":"DE",
    "sg:address":"Hardweg 10",
    "sg:city":"Donaueschingen",
    "sg:phone":"+49 7705/351",
    "sg:postcode":"78166",
    "sg:province":"Baden-W\u00fcrttemberg",
    "wof:name":"Erwin Sigg Datenverarbeitungsanlagen",
    "wof:placetype":"venue"
},
  "geometry": {"coordinates":[8.4199666977,47.9760398865],"type":"Point"}
}