{
  "type": "Feature",
  "properties": {
    "iso:country":"DE",
    "sg:address":"Ripener Weg 13",
    "sg:city":"Kiel",
    "sg:phone":"+49 431/522818",
    "sg:postcode":"24109",
    "sg:province":"Schleswig-Holstein",
    "wof:name":"Schlaraffia Kilia E. V. Roland Hagen",
    "wof:placetype":"venue"
},
  "geometry": {"coordinates":[10.0440540314,54.3131484985],"type":"Point"}
}