{
  "type": "Feature",
  "properties": {
    "iso:country":"DE",
    "sg:address":"Wolfersreuther Str. 32",
    "sg:city":"Waldershof",
    "sg:phone":"+49 9231/7303",
    "sg:postcode":"95679",
    "sg:province":"Bayern",
    "wof:name":"Friedrich Schaller Gmbh",
    "wof:placetype":"venue"
},
  "geometry": {"coordinates":[12.066184,49.974537],"type":"Point"}
}