{
  "type": "Feature",
  "properties": {
    "iso:country":"DE",
    "sg:address":"Egidienplatz 15",
    "sg:city":"N\u00fcrnberg",
    "sg:phone":"+49 911/227374",
    "sg:postcode":"90403",
    "sg:province":"Bayern",
    "wof:name":"Andreas R\u00e4bel",
    "wof:placetype":"venue"
},
  "geometry": {"coordinates":[11.080748558,49.4567298889],"type":"Point"}
}