{
  "type": "Feature",
  "properties": {
    "iso:country":"DE",
    "sg:address":"Frickenfelder Str. 8",
    "sg:city":"Gunzenhausen",
    "sg:phone":"+49 9831/4994",
    "sg:postcode":"91710",
    "sg:province":"Bayern",
    "wof:name":"Waldschenke",
    "wof:placetype":"venue"
},
  "geometry": {"coordinates":[10.7681722641,49.1180000305],"type":"Point"}
}