{
  "type": "Feature",
  "properties": {
    "iso:country":"DE",
    "sg:address":"Schrecksbacher Str. 17",
    "sg:city":"Schrecksbach",
    "sg:phone":"+49 6698/275",
    "sg:postcode":"34637",
    "sg:province":"Hessen",
    "wof:name":"Manfred Wiener",
    "wof:placetype":"venue"
},
  "geometry": {"coordinates":[9.286648,50.833981],"type":"Point"}
}