{
  "type": "Feature",
  "properties": {
    "iso:country":"DE",
    "sg:address":"Marktplatz 7",
    "sg:city":"Bad Lippspringe",
    "sg:phone":"+49 5252/932925",
    "sg:postcode":"33175",
    "sg:province":"Nordrhein-Westfalen",
    "wof:name":"Net-stream",
    "wof:placetype":"venue"
},
  "geometry": {"coordinates":[8.8200159073,51.7819328308],"type":"Point"}
}