{
  "type": "Feature",
  "properties": {
    "iso:country":"DE",
    "sg:address":"Thiersteiner Str. 15",
    "sg:city":"Hohenberg",
    "sg:phone":"+49 9233/713519",
    "sg:postcode":"95691",
    "sg:province":"Bayern",
    "wof:name":"Werner F\u00fcrbringer",
    "wof:placetype":"venue"
},
  "geometry": {"coordinates":[12.165892601,50.1068611145],"type":"Point"}
}