{
  "type": "Feature",
  "properties": {
    "iso:country":"DE",
    "sg:address":"Friesendorfer Str 4",
    "sg:city":"Ebersdorf",
    "sg:phone":"+49 9562/3830",
    "sg:postcode":"96237",
    "sg:province":"Bayern",
    "wof:name":"Crimpack Wellpappenwerk",
    "wof:placetype":"venue"
},
  "geometry": {"coordinates":[11.061693,50.22813],"type":"Point"}
}