{
  "type": "Feature",
  "properties": {
    "iso:country":"DE",
    "sg:address":"Honigloch 9",
    "sg:city":"Velbert",
    "sg:phone":"+49 2051/64494",
    "sg:postcode":"42549",
    "sg:province":"Nordrhein-Westfalen",
    "wof:name":"Wolfgang Schriewer Steuerberater",
    "wof:placetype":"venue"
},
  "geometry": {"coordinates":[7.035089016,51.3264350891],"type":"Point"}
}