{
  "type": "Feature",
  "properties": {
    "iso:country":"DE",
    "sg:address":"Goethestr. 22",
    "sg:city":"Filderstadt",
    "sg:phone":"+49 711/7778377",
    "sg:postcode":"70794",
    "sg:province":"Baden-W\u00fcrttemberg",
    "wof:name":"G. Decker",
    "wof:placetype":"venue"
},
  "geometry": {"coordinates":[9.1999263763,48.6561088562],"type":"Point"}
}