{
  "type": "Feature",
  "properties": {
    "iso:country":"DE",
    "sg:address":"Drosselstr. 34",
    "sg:city":"Essen",
    "sg:phone":"+49 201/470546",
    "sg:postcode":"45134",
    "sg:province":"Nordrhein-Westfalen",
    "wof:name":"Wingender",
    "wof:placetype":"venue"
},
  "geometry": {"coordinates":[7.029460907,51.4181365967],"type":"Point"}
}