{
  "type": "Feature",
  "properties": {
    "iso:country":"DE",
    "sg:address":"J\u00e4gerstr. 14",
    "sg:city":"Worbis",
    "sg:phone":"+49 36074/30050",
    "sg:postcode":"37339",
    "sg:province":"Th\u00fcringen",
    "wof:name":"Gerhard Wolter",
    "wof:placetype":"venue"
},
  "geometry": {"coordinates":[10.268205,51.47084],"type":"Point"}
}