{
  "type": "Feature",
  "properties": {
    "iso:country":"DE",
    "sg:address":"Ibrunnenstr. 12",
    "sg:city":"Lauchringen",
    "sg:phone":"+49 7741/913481",
    "sg:postcode":"79787",
    "sg:province":"Baden-W\u00fcrttemberg",
    "wof:name":"P. Faller",
    "wof:placetype":"venue"
},
  "geometry": {"coordinates":[8.293496,47.631145],"type":"Point"}
}