{
  "type": "Feature",
  "properties": {
    "iso:country":"DE",
    "sg:address":"Gro\u00dfe Fischergasse 4",
    "sg:city":"Nierstein",
    "sg:phone":"+49 6133/5628",
    "sg:postcode":"55283",
    "sg:province":"Rheinland-Pfalz",
    "wof:name":"Hotel-restaurant Zum Alten Vater Rhein",
    "wof:placetype":"venue"
},
  "geometry": {"coordinates":[8.342171669,49.8737220764],"type":"Point"}
}