{
  "type": "Feature",
  "properties": {
    "iso:country":"DE",
    "sg:address":"Hochstr. 7",
    "sg:city":"Taufkirchen",
    "sg:phone":"+49 89/6121159",
    "sg:postcode":"82024",
    "sg:province":"Bayern",
    "wof:name":"Wagm\u00fcller Verwaltungs Gmbh",
    "wof:placetype":"venue"
},
  "geometry": {"coordinates":[11.6212596893,48.0404090881],"type":"Point"}
}