{
  "type": "Feature",
  "properties": {
    "iso:country":"DE",
    "sg:address":"Schillerstr. 52",
    "sg:city":"Knittlingen",
    "sg:phone":"+49 7043/32513",
    "sg:postcode":"75438",
    "sg:province":"Baden-W\u00fcrttemberg",
    "wof:name":"Max Drodofsky",
    "wof:placetype":"venue"
},
  "geometry": {"coordinates":[8.7667160034,49.0172691345],"type":"Point"}
}