{
  "type": "Feature",
  "properties": {
    "iso:country":"DE",
    "sg:address":"Donauw\u00f6rther Str. 6",
    "sg:city":"Aichach",
    "sg:phone":"+49 8251/5960",
    "sg:postcode":"86551",
    "sg:province":"Bayern",
    "wof:name":"Sieglinde Brandmeir",
    "wof:placetype":"venue"
},
  "geometry": {"coordinates":[11.1330013275,48.4617385864],"type":"Point"}
}