{
  "type": "Feature",
  "properties": {
    "iso:country":"DE",
    "sg:address":"Innstr. 2",
    "sg:city":"Raubling",
    "sg:phone":"+49 8035/2431",
    "sg:postcode":"83064",
    "sg:province":"Bayern",
    "wof:name":"Hubert B\u00f6ck",
    "wof:placetype":"venue"
},
  "geometry": {"coordinates":[12.11008,47.786625],"type":"Point"}
}