{
  "type": "Feature",
  "properties": {
    "iso:country":"DE",
    "sg:address":"Am Illerkanal 18-10",
    "sg:city":"Neu-Ulm",
    "sg:phone":"+49 731/81513",
    "sg:postcode":"89231",
    "sg:province":"Bayern",
    "wof:name":"Dieter Schwarz Ingenieur",
    "wof:placetype":"venue"
},
  "geometry": {"coordinates":[9.9903268814,48.385383606],"type":"Point"}
}