{
  "type": "Feature",
  "properties": {
    "iso:country":"DE",
    "sg:address":"Kaiser-Ludwig-Platz 6",
    "sg:city":"M\u00fcnchen",
    "sg:phone":"+49 89/535340",
    "sg:postcode":"80336",
    "sg:province":"Bayern",
    "wof:name":"Multimedia Gmbh",
    "wof:placetype":"venue"
},
  "geometry": {"coordinates":[11.5553321838,48.1320571899],"type":"Point"}
}