{
  "type": "Feature",
  "properties": {
    "iso:country":"DE",
    "sg:address":"Hof\u00e4ckerstr. 23",
    "sg:city":"Wellendingen",
    "sg:phone":"+49 7426/2250",
    "sg:postcode":"78669",
    "sg:province":"Baden-W\u00fcrttemberg",
    "wof:name":"Vereinsgastst\u00e4tte Sportclub 1928 E. V.",
    "wof:placetype":"venue"
},
  "geometry": {"coordinates":[8.6956291199,48.1468772888],"type":"Point"}
}