{
  "type": "Feature",
  "properties": {
    "iso:country":"DE",
    "sg:address":"Alsstr. 192",
    "sg:city":"M\u00f6nchengladbach",
    "sg:phone":"+49 2161/181087",
    "sg:postcode":"41063",
    "sg:province":"Nordrhein-Westfalen",
    "wof:name":"Siegfried Fr\u00f6hlich",
    "wof:placetype":"venue"
},
  "geometry": {"coordinates":[6.4582657814,51.2083244324],"type":"Point"}
}