{
  "type": "Feature",
  "properties": {
    "iso:country":"DE",
    "sg:address":"St.-T\u00f6niser-Str. 27",
    "sg:city":"Kempen",
    "sg:phone":"+49 2152/4118",
    "sg:postcode":"47906",
    "sg:province":"Nordrhein-Westfalen",
    "wof:name":"Bisges Office & Object E. K.",
    "wof:placetype":"venue"
},
  "geometry": {"coordinates":[6.4256920815,51.3632926941],"type":"Point"}
}