{
  "type": "Feature",
  "properties": {
    "iso:country":"DE",
    "sg:address":"An der Untertrave 83",
    "sg:city":"L\u00fcbeck",
    "sg:phone":"+49 451/793838",
    "sg:postcode":"23552",
    "sg:province":"Schleswig-Holstein",
    "wof:name":"Uwe Albrecht Vom Fass",
    "wof:placetype":"venue"
},
  "geometry": {"coordinates":[10.6803436279,53.870174408],"type":"Point"}
}