{
  "type": "Feature",
  "properties": {
    "iso:country":"DE",
    "sg:address":"Postauer Str. 5",
    "sg:city":"W\u00f6rth",
    "sg:phone":"+49 8702/94120",
    "sg:postcode":"84109",
    "sg:province":"Bayern",
    "wof:name":"Petermaier Electric Gesell. F\u00fcr Elektrotechnik Und Elek-",
    "wof:placetype":"venue"
},
  "geometry": {"coordinates":[12.3383903503,48.6240653992],"type":"Point"}
}