{
  "type": "Feature",
  "properties": {
    "iso:country":"DE",
    "sg:address":"Karl-Marx-Str. 15",
    "sg:city":"M\u00fcncheberg",
    "sg:postcode":"15374",
    "sg:province":"Brandenburg",
    "wof:name":"Katholisches Pfarramt M\u00fcncheberg",
    "wof:placetype":"venue"
},
  "geometry": {"coordinates":[14.1310338974,52.504611969],"type":"Point"}
}