{
  "type": "Feature",
  "properties": {
    "iso:country":"DE",
    "sg:address":"Lug ins Land 7",
    "sg:city":"Wolnzach",
    "sg:phone":"+49 8442/1575",
    "sg:postcode":"85283",
    "sg:province":"Bayern",
    "wof:name":"Wohnungsbaugenossenschaft Wolnzach Eg",
    "wof:placetype":"venue"
},
  "geometry": {"coordinates":[11.6326084137,48.6057548523],"type":"Point"}
}