{
  "type": "Feature",
  "properties": {
    "iso:country":"DE",
    "sg:address":"Nagelstr. 1",
    "sg:city":"Essen",
    "sg:phone":"+49 201/321359",
    "sg:postcode":"45326",
    "sg:province":"Nordrhein-Westfalen",
    "wof:name":"Olympia Anastasiadou",
    "wof:placetype":"venue"
},
  "geometry": {"coordinates":[6.9973387718,51.4741592407],"type":"Point"}
}