{
  "type": "Feature",
  "properties": {
    "iso:country":"DE",
    "sg:address":"Lippst\u00e4dter Str. 28",
    "sg:city":"Erwitte",
    "sg:phone":"+49 2943/7100",
    "sg:postcode":"59597",
    "sg:province":"Nordrhein-Westfalen",
    "wof:name":"Franz - Josef K\u00fchnel",
    "wof:placetype":"venue"
},
  "geometry": {"coordinates":[8.3353672028,51.6172065735],"type":"Point"}
}