{
  "type": "Feature",
  "properties": {
    "iso:country":"DE",
    "sg:address":"Friedrichstr. 26",
    "sg:city":"Schwetzingen",
    "sg:phone":"+49 6202/15521",
    "sg:postcode":"68723",
    "sg:province":"Baden-W\u00fcrttemberg",
    "wof:name":"G. B\u00fchler Immobilienges. Mbh",
    "wof:placetype":"venue"
},
  "geometry": {"coordinates":[8.5747013092,49.3830718994],"type":"Point"}
}