{
  "type": "Feature",
  "properties": {
    "iso:country":"DE",
    "sg:address":"Von-Braun-Str. 8",
    "sg:city":"Vreden",
    "sg:postcode":"48691",
    "sg:province":"Nordrhein-Westfalen",
    "wof:name":"Repro-beteiligungsges. Mbh",
    "wof:placetype":"venue"
},
  "geometry": {"coordinates":[6.797791,52.018414],"type":"Point"}
}