{
  "type": "Feature",
  "properties": {
    "iso:country":"DE",
    "sg:address":"Rathausstr.",
    "sg:city":"B\u00fcttelborn",
    "sg:postcode":"64572",
    "sg:province":"Hessen",
    "wof:name":"Die Brille E. K.",
    "wof:placetype":"venue"
},
  "geometry": {"coordinates":[8.5125246048,49.9015960693],"type":"Point"}
}