{
  "type": "Feature",
  "properties": {
    "iso:country":"DE",
    "sg:address":"Max-Eyth-Str. 49",
    "sg:city":"Oberhausen",
    "sg:phone":"+49 208/658626",
    "sg:postcode":"46149",
    "sg:province":"Nordrhein-Westfalen",
    "wof:name":"B. Menzenbach Gmbh",
    "wof:placetype":"venue"
},
  "geometry": {"coordinates":[6.842248,51.49651],"type":"Point"}
}