{
  "type": "Feature",
  "properties": {
    "iso:country":"DE",
    "sg:address":"Langbehnstr. 8",
    "sg:city":"Hamburg",
    "sg:postcode":"22761",
    "sg:province":"Hamburg",
    "wof:name":"Panem Et Salis Gastronomie- Und Veranstaltungsservice E.k.",
    "wof:placetype":"venue"
},
  "geometry": {"coordinates":[9.916163,53.56673],"type":"Point"}
}