{
  "type": "Feature",
  "properties": {
    "iso:country":"DE",
    "sg:address":"Bahnhofstr. 2",
    "sg:city":"Holzwickede",
    "sg:phone":"+49 2301/13710",
    "sg:postcode":"59439",
    "sg:province":"Nordrhein-Westfalen",
    "wof:name":"Rose",
    "wof:placetype":"venue"
},
  "geometry": {"coordinates":[7.6182990074,51.5029830933],"type":"Point"}
}