{
  "type": "Feature",
  "properties": {
    "iso:country":"DE",
    "sg:address":"Herbststr. 5",
    "sg:city":"Schechen",
    "sg:phone":"+49 8031/83535",
    "sg:postcode":"83135",
    "sg:province":"Bayern",
    "wof:name":"Hubert Kohlweyer",
    "wof:placetype":"venue"
},
  "geometry": {"coordinates":[12.1223449707,47.8869667053],"type":"Point"}
}