{
  "type": "Feature",
  "properties": {
    "iso:country":"DE",
    "sg:address":"Stra\u00dfe der Einheit 19",
    "sg:city":"Oranienburg",
    "sg:phone":"+49 3301/801333",
    "sg:postcode":"16515",
    "sg:province":"Brandenburg",
    "wof:name":"Ralf Behrend",
    "wof:placetype":"venue"
},
  "geometry": {"coordinates":[13.255225,52.759071],"type":"Point"}
}