{
  "type": "Feature",
  "properties": {
    "iso:country":"DE",
    "sg:address":"Sch\u00fctzenstr. 2",
    "sg:city":"Konstanz",
    "sg:phone":"+49 7531/25217",
    "sg:postcode":"78462",
    "sg:province":"Baden-W\u00fcrttemberg",
    "wof:name":"Ev. Pfarramt Luthergemeinde",
    "wof:placetype":"venue"
},
  "geometry": {"coordinates":[9.1701002121,47.661441803],"type":"Point"}
}