{
  "type": "Feature",
  "properties": {
    "iso:country":"DE",
    "sg:address":"Kirchstr. 115",
    "sg:city":"Goch",
    "sg:phone":"+49 2823/4441",
    "sg:postcode":"47574",
    "sg:province":"Nordrhein-Westfalen",
    "wof:name":"Schwarzer Adler",
    "wof:placetype":"venue"
},
  "geometry": {"coordinates":[6.1902298927,51.7199707031],"type":"Point"}
}