{
  "type": "Feature",
  "properties": {
    "iso:country":"DE",
    "sg:address":"Im Matzenecken 19 a",
    "sg:city":"Tholey",
    "sg:phone":"+49 6853/5285",
    "sg:postcode":"66636",
    "sg:province":"Saarland",
    "wof:name":"Claus Ames Restaurator",
    "wof:placetype":"venue"
},
  "geometry": {"coordinates":[7.033751,49.483219],"type":"Point"}
}