{
  "type": "Feature",
  "properties": {
    "iso:country":"DE",
    "sg:address":"Eschersheimer Landstr. 140",
    "sg:city":"Frankfurt",
    "sg:phone":"+49 69/598164",
    "sg:postcode":"60322",
    "sg:province":"Hessen",
    "wof:name":"K & S Vertriebsservice Agentur F\u00fcr Handelsmarketing",
    "wof:placetype":"venue"
},
  "geometry": {"coordinates":[8.672704,50.129326],"type":"Point"}
}