{
  "type": "Feature",
  "properties": {
    "iso:country":"DE",
    "sg:address":"Sandeldamm 12",
    "sg:city":"Hanau",
    "sg:phone":"+49 6181/915510",
    "sg:postcode":"63450",
    "sg:province":"Hessen",
    "wof:name":"Deutsche Verm\u00f6gensberatung Ag",
    "wof:placetype":"venue"
},
  "geometry": {"coordinates":[8.9225845337,50.136013031],"type":"Point"}
}