{
  "type": "Feature",
  "properties": {
    "iso:country":"DE",
    "sg:address":"Neue Str. 16",
    "sg:city":"Algermissen",
    "sg:phone":"+49 5126/8242",
    "sg:postcode":"31191",
    "sg:province":"Niedersachsen",
    "wof:name":"Heinz Engelke",
    "wof:placetype":"venue"
},
  "geometry": {"coordinates":[9.970419,52.25478],"type":"Point"}
}