{
  "type": "Feature",
  "properties": {
    "iso:country":"DE",
    "sg:address":"Pillmannstr. 17",
    "sg:city":"Braunschweig",
    "sg:phone":"+49 531/210850",
    "sg:postcode":"38112",
    "sg:province":"Niedersachsen",
    "wof:name":"Hk Bau Heinz Kienemann Gmbh",
    "wof:placetype":"venue"
},
  "geometry": {"coordinates":[10.4724645615,52.3151092529],"type":"Point"}
}