{
  "type": "Feature",
  "properties": {
    "iso:country":"DE",
    "sg:address":"Auf dem Flidd 28",
    "sg:city":"Uetersen",
    "sg:phone":"+49 4122/2663",
    "sg:postcode":"25436",
    "sg:province":"Schleswig-Holstein",
    "wof:name":"Wolfgang Rochelt",
    "wof:placetype":"venue"
},
  "geometry": {"coordinates":[9.681871,53.692265],"type":"Point"}
}