{
  "type": "Feature",
  "properties": {
    "iso:country":"DE",
    "sg:address":"Calwer Str. 26",
    "sg:city":"Stuttgart",
    "sg:phone":"+49 711/296703",
    "sg:postcode":"70173",
    "sg:province":"Baden-W\u00fcrttemberg",
    "wof:name":"Angela Grashoff Gmbh",
    "wof:placetype":"venue"
},
  "geometry": {"coordinates":[9.17447,48.776852],"type":"Point"}
}