{
  "type": "Feature",
  "properties": {
    "iso:country":"DE",
    "sg:address":"Leonhardstr. 32",
    "sg:city":"Wolfersdorf",
    "sg:phone":"+49 8168/588",
    "sg:postcode":"85395",
    "sg:province":"Bayern",
    "wof:name":"Jakob Gr\u00fcnberger",
    "wof:placetype":"venue"
},
  "geometry": {"coordinates":[11.689918,48.479279],"type":"Point"}
}