{
  "type": "Feature",
  "properties": {
    "iso:country":"DE",
    "sg:address":"Wulf-Isebrand-Platz",
    "sg:city":"Heide",
    "sg:phone":"+49 481/6886164",
    "sg:postcode":"25746",
    "sg:province":"Schleswig-Holstein",
    "wof:name":"Buchverlag Boyens & Co.",
    "wof:placetype":"venue"
},
  "geometry": {"coordinates":[9.098183,54.194542],"type":"Point"}
}