{
  "type": "Feature",
  "properties": {
    "iso:country":"DE",
    "sg:address":"Zum Jagenstein 32",
    "sg:city":"Potsdam",
    "sg:postcode":"14478",
    "sg:province":"Brandenburg",
    "wof:name":"Kev K\u00fcchen- Und Elektro- Vertriebsges. In Potsdam Mbh",
    "wof:placetype":"venue"
},
  "geometry": {"coordinates":[13.0916643143,52.3655090332],"type":"Point"}
}