{
  "type": "Feature",
  "properties": {
    "iso:country":"DE",
    "sg:address":"Alte Dorfstr.",
    "sg:city":"Baumersroda",
    "sg:phone":"+49 34632/22633",
    "sg:postcode":"06632",
    "sg:province":"Sachsen-Anhalt",
    "wof:name":"U. Brennenstuhl",
    "wof:placetype":"venue"
},
  "geometry": {"coordinates":[11.7581348419,51.2615585327],"type":"Point"}
}