{
  "type": "Feature",
  "properties": {
    "iso:country":"DE",
    "sg:address":"Johannes- M\u00fcller-Str. 39A",
    "sg:city":"K\u00f6ln",
    "sg:phone":"+49 221",
    "sg:postcode":"50735",
    "sg:province":"Nordrhein-Westfalen",
    "wof:name":"Sportletter - Beratung & Service.",
    "wof:placetype":"venue"
},
  "geometry": {"coordinates":[6.970591,50.963718],"type":"Point"}
}