{
  "type": "Feature",
  "properties": {
    "iso:country":"DE",
    "sg:address":"Alt-Buch 59",
    "sg:city":"Berlin",
    "sg:phone":"+49 30/9413186",
    "sg:postcode":"13125",
    "sg:province":"Berlin",
    "wof:name":"Eiscafe Gabriele R\u00fchl",
    "wof:placetype":"venue"
},
  "geometry": {"coordinates":[13.502701,52.636562],"type":"Point"}
}