{
  "type": "Feature",
  "properties": {
    "iso:country":"DE",
    "sg:address":"Marktstr. 7",
    "sg:city":"Wiesmoor",
    "sg:phone":"+49 4944/1881",
    "sg:postcode":"26639",
    "sg:province":"Niedersachsen",
    "wof:name":"Reiseladen H\u00e4ger Gmbh",
    "wof:placetype":"venue"
},
  "geometry": {"coordinates":[7.7357411385,53.4137153625],"type":"Point"}
}