{
  "type": "Feature",
  "properties": {
    "iso:country":"DE",
    "sg:address":"M\u00fcnchener Str. 5",
    "sg:city":"Freilassing",
    "sg:phone":"+49 8654/9317",
    "sg:postcode":"83395",
    "sg:province":"Bayern",
    "wof:name":"Georg Haintz Steuerberater",
    "wof:placetype":"venue"
},
  "geometry": {"coordinates":[12.9812574387,47.8413391113],"type":"Point"}
}