{
  "type": "Feature",
  "properties": {
    "iso:country":"DE",
    "sg:address":"Mangfallstr. 27",
    "sg:city":"Rosenheim",
    "sg:phone":"+49 8031/63306",
    "sg:postcode":"83026",
    "sg:province":"Bayern",
    "wof:name":"Edeka Chiemgau Eg",
    "wof:placetype":"venue"
},
  "geometry": {"coordinates":[12.1123132706,47.8418121338],"type":"Point"}
}