{
  "type": "Feature",
  "properties": {
    "iso:country":"DE",
    "sg:address":"Mexikoring 37",
    "sg:city":"Hamburg",
    "sg:phone":"+49 40/6320180",
    "sg:postcode":"22297",
    "sg:province":"Hamburg",
    "wof:name":"Ferdinand Holzmann Verlag Gmbh",
    "wof:placetype":"venue"
},
  "geometry": {"coordinates":[10.0243501663,53.6043663025],"type":"Point"}
}