{
  "type": "Feature",
  "properties": {
    "iso:country":"DE",
    "sg:address":"Watmarkt 4",
    "sg:city":"Regensburg",
    "sg:phone":"+49 941/53297",
    "sg:postcode":"93047",
    "sg:province":"Bayern",
    "wof:name":"Restaurant Dampfnudel-uli",
    "wof:placetype":"venue"
},
  "geometry": {"coordinates":[12.0961809158,49.0198326111],"type":"Point"}
}