{
  "type": "Feature",
  "properties": {
    "iso:country":"DE",
    "sg:address":"Meisenweg 12",
    "sg:city":"Sankt Augustin",
    "sg:phone":"+49 2241/331312",
    "sg:postcode":"53757",
    "sg:province":"Nordrhein-Westfalen",
    "wof:name":"Dietlinde Schula Krankengymnastin",
    "wof:placetype":"venue"
},
  "geometry": {"coordinates":[7.211709,50.769936],"type":"Point"}
}