{
  "type": "Feature",
  "properties": {
    "iso:country":"DE",
    "sg:address":"Im Laukesgarten 15",
    "sg:city":"Weiterstadt",
    "sg:phone":"+49 6150/4155",
    "sg:postcode":"64331",
    "sg:province":"Hessen",
    "wof:name":"Erhard Wendler",
    "wof:placetype":"venue"
},
  "geometry": {"coordinates":[8.5974731445,49.9036178589],"type":"Point"}
}