{
  "type": "Feature",
  "properties": {
    "iso:country":"DE",
    "sg:address":"Platz der Vereinten Nationen 1",
    "sg:city":"Berlin",
    "sg:phone":"+49 30/4261287",
    "sg:postcode":"10249",
    "sg:province":"Berlin",
    "wof:name":"Tesch Und Tesch",
    "wof:placetype":"venue"
},
  "geometry": {"coordinates":[13.4304895401,52.5234603882],"type":"Point"}
}