{
  "type": "Feature",
  "properties": {
    "iso:country":"DE",
    "sg:address":"Obermauersbach",
    "sg:city":"Aichach",
    "sg:phone":"+49 8251/2184",
    "sg:postcode":"86551",
    "sg:province":"Bayern",
    "wof:name":"Adolf Pechter Ingenieur",
    "wof:placetype":"venue"
},
  "geometry": {"coordinates":[11.1292457581,48.4655723572],"type":"Point"}
}