{
  "type": "Feature",
  "properties": {
    "iso:country":"DE",
    "sg:address":"Wielandstr. 24",
    "sg:city":"Biberach",
    "sg:phone":"+49 7351/7017",
    "sg:postcode":"88400",
    "sg:province":"Baden-W\u00fcrttemberg",
    "wof:name":"Beratung F. Werdende M\u00fctter Diak. Bezirksstelle",
    "wof:placetype":"venue"
},
  "geometry": {"coordinates":[9.786322,48.100887],"type":"Point"}
}