{
  "type": "Feature",
  "properties": {
    "iso:country":"DE",
    "sg:address":"Haldenstr. 14",
    "sg:city":"Esslingen",
    "sg:phone":"+49 711/314324",
    "sg:postcode":"73730",
    "sg:province":"Baden-W\u00fcrttemberg",
    "wof:name":"Else Beck",
    "wof:placetype":"venue"
},
  "geometry": {"coordinates":[9.334694,48.733437],"type":"Point"}
}