{
  "type": "Feature",
  "properties": {
    "iso:country":"DE",
    "sg:address":"Brunnenweg 68",
    "sg:city":"Verden",
    "sg:phone":"+49 4231/64565",
    "sg:postcode":"27283",
    "sg:province":"Niedersachsen",
    "wof:name":"K\u00fcchenstudio",
    "wof:placetype":"venue"
},
  "geometry": {"coordinates":[9.2428007126,52.9297523499],"type":"Point"}
}