{
  "type": "Feature",
  "properties": {
    "iso:country":"DE",
    "sg:address":"Hauptstr. 27",
    "sg:city":"Oberhermsdorf",
    "sg:phone":"+49 351/6503088",
    "sg:postcode":"01737",
    "sg:province":"Sachsen",
    "wof:name":"Gl\u00fcck-auf",
    "wof:placetype":"venue"
},
  "geometry": {"coordinates":[13.5909996033,51.0202827454],"type":"Point"}
}