{
  "type": "Feature",
  "properties": {
    "iso:country":"DE",
    "sg:address":"Wittenburger Str. 37",
    "sg:city":"Schwerin",
    "sg:phone":"+49 385/562930",
    "sg:postcode":"19053",
    "sg:province":"Mecklenburg-Vorpommern",
    "wof:name":"Carl Joseph Senger Dachdecker-meisterbetrieb",
    "wof:placetype":"venue"
},
  "geometry": {"coordinates":[11.406897,53.628963],"type":"Point"}
}