{
  "type": "Feature",
  "properties": {
    "iso:country":"DE",
    "sg:address":"B\u00fcrgerplatz 20",
    "sg:city":"Garching",
    "sg:phone":"+49 89/3207642",
    "sg:postcode":"85748",
    "sg:province":"Bayern",
    "wof:name":"Kreissparkasse M\u00fcnchen",
    "wof:placetype":"venue"
},
  "geometry": {"coordinates":[-110.772728,32.215431],"type":"Point"}
}