{
  "type": "Feature",
  "properties": {
    "iso:country":"DE",
    "sg:address":"Trabener Str. 72 b",
    "sg:city":"Berlin",
    "sg:phone":"+49 30/8929738",
    "sg:postcode":"14193",
    "sg:province":"Berlin",
    "wof:name":"Peter Schwiertz Architekt",
    "wof:placetype":"venue"
},
  "geometry": {"coordinates":[13.277955,52.494308],"type":"Point"}
}