{
  "type": "Feature",
  "properties": {
    "iso:country":"DE",
    "sg:address":"Zollenreuter Str. 25",
    "sg:city":"Aulendorf",
    "sg:phone":"+49 7525/1467",
    "sg:postcode":"88326",
    "sg:province":"Baden-W\u00fcrttemberg",
    "wof:name":"Georg Siegel",
    "wof:placetype":"venue"
},
  "geometry": {"coordinates":[9.641549,47.950562],"type":"Point"}
}