{
  "type": "Feature",
  "properties": {
    "iso:country":"DE",
    "sg:address":"Carl-Hertel-Str. 8",
    "sg:city":"Chemnitz",
    "sg:phone":"+49 371/852294",
    "sg:postcode":"09116",
    "sg:province":"Sachsen",
    "wof:name":"Hirsch",
    "wof:placetype":"venue"
},
  "geometry": {"coordinates":[12.8721179962,50.8182258606],"type":"Point"}
}