{
  "type": "Feature",
  "properties": {
    "iso:country":"DE",
    "sg:address":"Breithof 33",
    "sg:city":"Duisburg",
    "sg:phone":"+49 203/765160",
    "sg:postcode":"47269",
    "sg:province":"Nordrhein-Westfalen",
    "wof:name":"Michael Andre",
    "wof:placetype":"venue"
},
  "geometry": {"coordinates":[6.7777838707,51.3744926453],"type":"Point"}
}