{
  "type": "Feature",
  "properties": {
    "iso:country":"DE",
    "sg:address":"Goethering 7",
    "sg:city":"Osnabr\u00fcck",
    "sg:phone":"+49 541/3311231",
    "sg:postcode":"49074",
    "sg:province":"Niedersachsen",
    "wof:name":"Akademie \u00dcberlingen Neue Medien Gmbh",
    "wof:placetype":"venue"
},
  "geometry": {"coordinates":[8.053082,52.275166],"type":"Point"}
}