{
  "type": "Feature",
  "properties": {
    "iso:country":"DE",
    "sg:address":"D\u00f6rpefeld 54",
    "sg:city":"Hannover",
    "sg:phone":"+49 511/748824",
    "sg:postcode":"30419",
    "sg:province":"Niedersachsen",
    "wof:name":"Figurama",
    "wof:placetype":"venue"
},
  "geometry": {"coordinates":[9.703098,52.421276],"type":"Point"}
}