{
  "type": "Feature",
  "properties": {
    "iso:country":"DE",
    "sg:address":"Zanderstr. 2",
    "sg:city":"Ulm",
    "sg:phone":"+49 731/35777",
    "sg:postcode":"89079",
    "sg:province":"Baden-W\u00fcrttemberg",
    "wof:name":"Musik Und Service J\u00fcrgen M\u00e4urer",
    "wof:placetype":"venue"
},
  "geometry": {"coordinates":[9.9432067871,48.3386535645],"type":"Point"}
}