{
  "type": "Feature",
  "properties": {
    "iso:country":"DE",
    "sg:address":"Steinstr. 79a",
    "sg:city":"M\u00fcnchen",
    "sg:phone":"+49 89/4801746",
    "sg:postcode":"81667",
    "sg:province":"Bayern",
    "wof:name":"Norbert Hofherr S\u00fcsswaren",
    "wof:placetype":"venue"
},
  "geometry": {"coordinates":[11.5949611664,48.1293983459],"type":"Point"}
}