{
  "type": "Feature",
  "properties": {
    "iso:country":"DE",
    "sg:address":"Hauptstr. 20a",
    "sg:city":"Heiligenhagen",
    "sg:phone":"+49 38295/70138",
    "sg:postcode":"18239",
    "sg:province":"Mecklenburg-Vorpommern",
    "wof:name":"N. Belitz",
    "wof:placetype":"venue"
},
  "geometry": {"coordinates":[11.9339609146,54.0073661804],"type":"Point"}
}