{
  "type": "Feature",
  "properties": {
    "iso:country":"DE",
    "sg:address":"Ortsstr. 2a",
    "sg:city":"Mannheim",
    "sg:phone":"+49 621/7141743",
    "sg:postcode":"68259",
    "sg:province":"Baden-W\u00fcrttemberg",
    "wof:name":"Peter Netzer Architekt",
    "wof:placetype":"venue"
},
  "geometry": {"coordinates":[8.575984,49.512012],"type":"Point"}
}