{
  "type": "Feature",
  "properties": {
    "iso:country":"DE",
    "sg:address":"Woldegker Str. 25",
    "sg:city":"Neubrandenburg",
    "sg:phone":"+49 395/581780",
    "sg:postcode":"17033",
    "sg:province":"Mecklenburg-Vorpommern",
    "wof:name":"Fiskal Steuerberatungsges. Treuhandges. Mbh",
    "wof:placetype":"venue"
},
  "geometry": {"coordinates":[13.2711782455,53.5586433411],"type":"Point"}
}