{
  "type": "Feature",
  "properties": {
    "iso:country":"DE",
    "sg:address":"Windstr. 10",
    "sg:city":"Sch\u00fcttorf",
    "sg:phone":"+49 5923/95080",
    "sg:postcode":"48465",
    "sg:province":"Niedersachsen",
    "wof:name":"Vechte-apotheke Inh. Ralf Borwitzky",
    "wof:placetype":"venue"
},
  "geometry": {"coordinates":[7.223744,52.322029],"type":"Point"}
}