{
  "type": "Feature",
  "properties": {
    "iso:country":"DE",
    "sg:address":"Maximilianstr. 6",
    "sg:city":"Starnberg",
    "sg:phone":"+49 8151/16118",
    "sg:postcode":"82319",
    "sg:province":"Bayern",
    "wof:name":"Hans-berthold Hertlein Heilpraktiker",
    "wof:placetype":"venue"
},
  "geometry": {"coordinates":[11.3439178467,47.9977149963],"type":"Point"}
}