{
  "type": "Feature",
  "properties": {
    "iso:country":"DE",
    "sg:address":"Sonnenallee 1",
    "sg:city":"Kirchheim",
    "sg:phone":"+49 89/460080",
    "sg:postcode":"85551",
    "sg:province":"Bayern",
    "wof:name":"Sun Microsystems Gmbh",
    "wof:placetype":"venue"
},
  "geometry": {"coordinates":[11.760264,48.157028],"type":"Point"}
}