{
  "type": "Feature",
  "properties": {
    "iso:country":"DE",
    "sg:address":"Erich-Ollenhauer-Str 302",
    "sg:city":"Wiesbaden",
    "sg:phone":"+49 611/420678",
    "sg:postcode":"65199",
    "sg:province":"Hessen",
    "wof:name":"Wolfgang Bozsa",
    "wof:placetype":"venue"
},
  "geometry": {"coordinates":[8.1958551407,50.071559906],"type":"Point"}
}