{
  "type": "Feature",
  "properties": {
    "iso:country":"DE",
    "sg:city":"Extertal",
    "sg:phone":"+49 4952/622045",
    "sg:postcode":"32699",
    "sg:province":"Nordrhein-Westfalen",
    "wof:name":"Sparkasse Lemgo",
    "wof:placetype":"venue"
},
  "geometry": {"coordinates":[9.126196,52.06778],"type":"Point"}
}