{
  "type": "Feature",
  "properties": {
    "iso:country":"DE",
    "sg:address":"Riemekestr. 22",
    "sg:city":"Paderborn",
    "sg:postcode":"33102",
    "sg:province":"Nordrhein-Westfalen",
    "wof:name":"Asiatechnic Mit Zusatz E. K.",
    "wof:placetype":"venue"
},
  "geometry": {"coordinates":[8.743092,51.716167],"type":"Point"}
}