{
  "type": "Feature",
  "properties": {
    "iso:country":"DE",
    "sg:address":"Gartenweg 5",
    "sg:city":"Altenm\u00fcnster",
    "sg:phone":"+49 8295/1045",
    "sg:postcode":"86450",
    "sg:province":"Bayern",
    "wof:name":"Albert Treu",
    "wof:placetype":"venue"
},
  "geometry": {"coordinates":[10.5885095596,48.4617004395],"type":"Point"}
}