{
  "type": "Feature",
  "properties": {
    "iso:country":"DE",
    "sg:address":"Gro\u00dfe Gallusstr. 1-7",
    "sg:city":"Frankfurt",
    "sg:phone":"+49 4969/2989100",
    "sg:postcode":"60311",
    "sg:province":"Hessen",
    "wof:name":"Aka Ausfuhrkredit-gmbh",
    "wof:placetype":"venue"
},
  "geometry": {"coordinates":[8.67602,50.112049],"type":"Point"}
}