{
  "type": "Feature",
  "properties": {
    "iso:country":"DE",
    "sg:address":"Am Parkfriedhof 50",
    "sg:city":"Essen",
    "sg:phone":"+49 201/281484",
    "sg:postcode":"45138",
    "sg:province":"Nordrhein-Westfalen",
    "wof:name":"Klaus Conrad",
    "wof:placetype":"venue"
},
  "geometry": {"coordinates":[7.045227,51.449234],"type":"Point"}
}