{
  "type": "Feature",
  "properties": {
    "iso:country":"DE",
    "sg:address":"Stadionstr. 95",
    "sg:city":"Grefrath",
    "sg:phone":"+49 2158/4340",
    "sg:postcode":"47929",
    "sg:province":"Nordrhein-Westfalen",
    "wof:name":"Fellmann Gmbh",
    "wof:placetype":"venue"
},
  "geometry": {"coordinates":[6.34364,51.343853],"type":"Point"}
}