{
  "type": "Feature",
  "properties": {
    "iso:country":"DE",
    "sg:address":"Klosterstr. 4",
    "sg:city":"Oberhausen",
    "sg:phone":"+49 208/667307",
    "sg:postcode":"46145",
    "sg:province":"Nordrhein-Westfalen",
    "wof:name":"A. Schmidt",
    "wof:placetype":"venue"
},
  "geometry": {"coordinates":[6.8483839035,51.5162963867],"type":"Point"}
}