{
  "type": "Feature",
  "properties": {
    "iso:country":"DE",
    "sg:address":"K\u00f6nig-Wilhelm-Str. 42",
    "sg:city":"Oberndorf",
    "sg:phone":"+49 7423/3376",
    "sg:postcode":"78727",
    "sg:province":"Baden-W\u00fcrttemberg",
    "wof:name":"Weber Gmbh \u00c4rztebedarf",
    "wof:placetype":"venue"
},
  "geometry": {"coordinates":[8.578556,48.298786],"type":"Point"}
}