{
  "type": "Feature",
  "properties": {
    "iso:country":"DE",
    "sg:address":"Maximilianstr. 29",
    "sg:city":"Regensburg",
    "sg:phone":"+49 941/594010",
    "sg:postcode":"93047",
    "sg:province":"Bayern",
    "wof:name":"Reiseb\u00fcro Jakob",
    "wof:placetype":"venue"
},
  "geometry": {"coordinates":[12.1002826691,49.0148391724],"type":"Point"}
}