{
  "type": "Feature",
  "properties": {
    "iso:country":"DE",
    "sg:address":"Am Kalkwerk 23-25",
    "sg:city":"Banteln",
    "sg:phone":"+49 5182/6011",
    "sg:postcode":"31029",
    "sg:province":"Niedersachsen",
    "wof:name":"Betonfertigteilwerk Unseburg Verwaltungs Gmbh",
    "wof:placetype":"venue"
},
  "geometry": {"coordinates":[9.744361,52.070972],"type":"Point"}
}