{
  "type": "Feature",
  "properties": {
    "iso:country":"DE",
    "sg:address":"Rathausstr. 20",
    "sg:city":"Eppelborn",
    "sg:phone":"+49 6881/7155",
    "sg:postcode":"66571",
    "sg:province":"Saarland",
    "wof:name":"G\u00fcnther Hauth",
    "wof:placetype":"venue"
},
  "geometry": {"coordinates":[6.964557,49.40556],"type":"Point"}
}