{
  "type": "Feature",
  "properties": {
    "iso:country":"DE",
    "sg:address":"Adorfer Str. 3",
    "sg:city":"Leubetha",
    "sg:phone":"+49 37423/2625",
    "sg:postcode":"08626",
    "sg:province":"Sachsen",
    "wof:name":"Willy Schreiner",
    "wof:placetype":"venue"
},
  "geometry": {"coordinates":[12.2405195236,50.3296813965],"type":"Point"}
}