{
  "type": "Feature",
  "properties": {
    "iso:country":"DE",
    "sg:address":"Flachter Str. 31",
    "sg:city":"Weissach",
    "sg:phone":"+49 7044/31358",
    "sg:postcode":"71287",
    "sg:province":"Baden-W\u00fcrttemberg",
    "wof:name":"Gasthof Zuberb\u00fchler",
    "wof:placetype":"venue"
},
  "geometry": {"coordinates":[8.9226865768,48.8459014893],"type":"Point"}
}