{
  "type": "Feature",
  "properties": {
    "iso:country":"DE",
    "sg:address":"Further Str. 24-26",
    "sg:city":"Neuss",
    "sg:phone":"+49 4921/315220",
    "sg:postcode":"41462",
    "sg:province":"Nordrhein-Westfalen",
    "wof:name":"Textron Verbindungstechnik Gmbh & Co. Ohg",
    "wof:placetype":"venue"
},
  "geometry": {"coordinates":[6.681379,51.204643],"type":"Point"}
}