{
  "type": "Feature",
  "properties": {
    "iso:country":"DE",
    "sg:address":"Mayener Str. 127",
    "sg:city":"Koblenz",
    "sg:phone":"+49 261/82906",
    "sg:postcode":"56070",
    "sg:province":"Rheinland-Pfalz",
    "wof:name":"Hotel Moselschl\u00f6\u00dfchen",
    "wof:placetype":"venue"
},
  "geometry": {"coordinates":[7.5802569389,50.3692245483],"type":"Point"}
}