{
  "type": "Feature",
  "properties": {
    "iso:country":"DE",
    "sg:address":"Katharinenstr. 15",
    "sg:city":"Leipzig",
    "sg:phone":"+49 341/9601201",
    "sg:postcode":"04109",
    "sg:province":"Sachsen",
    "wof:name":"Kehrmann Marktforschung Gmbh",
    "wof:placetype":"venue"
},
  "geometry": {"coordinates":[12.3747911453,51.3420028687],"type":"Point"}
}