{
  "type": "Feature",
  "properties": {
    "iso:country":"DE",
    "sg:address":"Kantorstr. 41",
    "sg:city":"Lage",
    "sg:phone":"+49 5232/61512",
    "sg:postcode":"32791",
    "sg:province":"Nordrhein-Westfalen",
    "wof:name":"Willi Pehle",
    "wof:placetype":"venue"
},
  "geometry": {"coordinates":[8.8537197113,51.9800491333],"type":"Point"}
}