{
  "type": "Feature",
  "properties": {
    "iso:country":"DE",
    "sg:address":"Bahnhofstr. 2",
    "sg:city":"M\u00fchltroff",
    "sg:phone":"+49 36645/283",
    "sg:postcode":"07919",
    "sg:province":"Th\u00fcringen",
    "wof:name":"Raiffeisenbank Plauen",
    "wof:placetype":"venue"
},
  "geometry": {"coordinates":[11.932109,50.540897],"type":"Point"}
}