{
  "type": "Feature",
  "properties": {
    "iso:country":"DE",
    "sg:address":"Siegmund-Hiepe-Str. 22",
    "sg:city":"Wetzlar",
    "sg:phone":"+49 6441/92380",
    "sg:postcode":"35578",
    "sg:province":"Hessen",
    "wof:name":"M\u00f6bel Georg Gmbh",
    "wof:placetype":"venue"
},
  "geometry": {"coordinates":[8.473984,50.551678],"type":"Point"}
}