{
  "type": "Feature",
  "properties": {
    "iso:country":"DE",
    "sg:address":"Schulstr. 7",
    "sg:city":"Hemmingen",
    "sg:phone":"+49 5101/12607",
    "sg:postcode":"30966",
    "sg:province":"Niedersachsen",
    "wof:name":"F\u00f6sten Kg",
    "wof:placetype":"venue"
},
  "geometry": {"coordinates":[9.712535,52.280838],"type":"Point"}
}