{
  "type": "Feature",
  "properties": {
    "iso:country":"DE",
    "sg:address":"Reuchlinstr. 9",
    "sg:city":"Wiesbaden",
    "sg:phone":"+49 611/840581",
    "sg:postcode":"65199",
    "sg:province":"Hessen",
    "wof:name":"Schembs Taxibetriebs- Gesellschaft Mbh",
    "wof:placetype":"venue"
},
  "geometry": {"coordinates":[8.2127599716,50.0630912781],"type":"Point"}
}