{
  "type": "Feature",
  "properties": {
    "iso:country":"DE",
    "sg:address":"Oststr. 23",
    "sg:city":"Oberstdorf",
    "sg:phone":"+49 8322/4943",
    "sg:postcode":"87561",
    "sg:province":"Bayern",
    "wof:name":"G\u00e4stehaus Konrad Vogler",
    "wof:placetype":"venue"
},
  "geometry": {"coordinates":[10.2829303741,47.4057006836],"type":"Point"}
}