{
  "type": "Feature",
  "properties": {
    "iso:country":"DE",
    "sg:address":"Hans-Breinlinger-Str. 7",
    "sg:city":"Konstanz",
    "sg:phone":"+49 7531/29806",
    "sg:postcode":"78462",
    "sg:province":"Baden-W\u00fcrttemberg",
    "wof:name":"Teppich-service Taifun Gmbh",
    "wof:placetype":"venue"
},
  "geometry": {"coordinates":[9.164107,47.666973],"type":"Point"}
}