{
  "type": "Feature",
  "properties": {
    "iso:country":"DE",
    "sg:address":"Dieselstr. 18",
    "sg:city":"F\u00fcrth",
    "sg:phone":"+49 911/793108",
    "sg:postcode":"90765",
    "sg:province":"Bayern",
    "wof:name":"Helmut Prell Steuerberater",
    "wof:placetype":"venue"
},
  "geometry": {"coordinates":[11.0049943924,49.4872741699],"type":"Point"}
}