{
  "type": "Feature",
  "properties": {
    "iso:country":"DE",
    "sg:address":"Leipziger Str. 28",
    "sg:city":"M\u00fchlau",
    "sg:phone":"+49 3722/95175",
    "sg:postcode":"09241",
    "sg:province":"Sachsen",
    "wof:name":"Reiner Sch\u00f6nfeld",
    "wof:placetype":"venue"
},
  "geometry": {"coordinates":[12.760445,50.900181],"type":"Point"}
}