{
  "type": "Feature",
  "properties": {
    "iso:country":"DE",
    "sg:address":"Schweizer Str. 40",
    "sg:city":"Frankfurt",
    "sg:postcode":"60594",
    "sg:province":"Hessen",
    "wof:name":"Lady Plus Damenmoden Gmbh",
    "wof:placetype":"venue"
},
  "geometry": {"coordinates":[8.679754,50.102776],"type":"Point"}
}