{
  "type": "Feature",
  "properties": {
    "iso:country":"DE",
    "sg:address":"Osttor 15",
    "sg:city":"Sendenhorst",
    "sg:phone":"+49 2526/1364",
    "sg:postcode":"48324",
    "sg:province":"Nordrhein-Westfalen",
    "wof:name":"A. Reutscher Hebamme",
    "wof:placetype":"venue"
},
  "geometry": {"coordinates":[7.83249,51.844208],"type":"Point"}
}