{
  "type": "Feature",
  "properties": {
    "iso:country":"DE",
    "sg:address":"Str. Des 13.Januar 20-24",
    "sg:city":"Saarbr\u00fccken",
    "sg:phone":"+49 4968/164626",
    "sg:postcode":"66121",
    "sg:province":"Saarland",
    "wof:name":"Gerstle B\u00c4dertechnik Gmbh",
    "wof:placetype":"venue"
},
  "geometry": {"coordinates":[7.015495,49.226379],"type":"Point"}
}