{
  "type": "Feature",
  "properties": {
    "iso:country":"DE",
    "sg:address":"Kirchstr. 60",
    "sg:city":"Schermbeck",
    "sg:phone":"+49 2853/2925",
    "sg:postcode":"46514",
    "sg:province":"Nordrhein-Westfalen",
    "wof:name":"Anneliese Krause",
    "wof:placetype":"venue"
},
  "geometry": {"coordinates":[6.7980699539,51.6764602661],"type":"Point"}
}