{
  "type": "Feature",
  "properties": {
    "iso:country":"DE",
    "sg:address":"Knechtstedtener Str. 21",
    "sg:city":"Pulheim",
    "sg:phone":"+49 2238/962561",
    "sg:postcode":"50259",
    "sg:province":"Nordrhein-Westfalen",
    "wof:name":"Ziss Gmbh",
    "wof:placetype":"venue"
},
  "geometry": {"coordinates":[6.817062,51.026604],"type":"Point"}
}