{
  "type": "Feature",
  "properties": {
    "iso:country":"DE",
    "sg:address":"Von-H\u00f6rde-Str. 26",
    "sg:city":"Geseke",
    "sg:phone":"+49 2942/3890",
    "sg:postcode":"59590",
    "sg:province":"Nordrhein-Westfalen",
    "wof:name":"Ulrich Schulz Architekt",
    "wof:placetype":"venue"
},
  "geometry": {"coordinates":[8.474322,51.635563],"type":"Point"}
}