{
  "type": "Feature",
  "properties": {
    "iso:country":"DE",
    "sg:address":"Frankfurter Str. 115",
    "sg:city":"Bad Vilbel",
    "sg:phone":"+49 6101/2543",
    "sg:postcode":"61118",
    "sg:province":"Hessen",
    "wof:name":"Rainer Wolf Agentur F\u00fcr Einrichtungs-",
    "wof:placetype":"venue"
},
  "geometry": {"coordinates":[8.737159,50.179466],"type":"Point"}
}