{
  "type": "Feature",
  "properties": {
    "iso:country":"DE",
    "sg:address":"Immenburgstr. 20",
    "sg:city":"Bonn",
    "sg:postcode":"53121",
    "sg:province":"Nordrhein-Westfalen",
    "wof:name":"Rheindata Gmbh",
    "wof:placetype":"venue"
},
  "geometry": {"coordinates":[7.079498,50.73431],"type":"Point"}
}