{
  "type": "Feature",
  "properties": {
    "iso:country":"DE",
    "sg:address":"Gluckstr. 33",
    "sg:city":"Osnabr\u00fcck",
    "sg:phone":"+49 541/62402",
    "sg:postcode":"49076",
    "sg:province":"Niedersachsen",
    "wof:name":"Alfred Vogel",
    "wof:placetype":"venue"
},
  "geometry": {"coordinates":[8.0117225647,52.2853965759],"type":"Point"}
}