{
  "type": "Feature",
  "properties": {
    "iso:country":"DE",
    "sg:address":"Nutzhorner Landstr. 50",
    "sg:city":"Ganderkesee",
    "sg:phone":"+49 4223/8558",
    "sg:postcode":"27777",
    "sg:province":"Niedersachsen",
    "wof:name":"Kathmann Gmbh & Co. Kg",
    "wof:placetype":"venue"
},
  "geometry": {"coordinates":[8.581159,53.091324],"type":"Point"}
}