{
  "type": "Feature",
  "properties": {
    "iso:country":"DE",
    "sg:address":"Raustetten 10",
    "sg:city":"Fremdingen",
    "sg:phone":"+49 9086/358",
    "sg:postcode":"86742",
    "sg:province":"Bayern",
    "wof:name":"Melchior Sandmaier",
    "wof:placetype":"venue"
},
  "geometry": {"coordinates":[10.435634613,48.9668464661],"type":"Point"}
}