{
  "type": "Feature",
  "properties": {
    "iso:country":"DE",
    "sg:address":"R\u00f6ckinghausener Str. 6",
    "sg:city":"Rheda-Wiedenbr\u00fcck",
    "sg:phone":"+49 5242/5319",
    "sg:postcode":"33378",
    "sg:province":"Nordrhein-Westfalen",
    "wof:name":"Heinz Flaskamp Landtechnisches Lohnunternehmen Gmbh",
    "wof:placetype":"venue"
},
  "geometry": {"coordinates":[8.3230037689,51.8181419373],"type":"Point"}
}