{
  "type": "Feature",
  "properties": {
    "iso:country":"DE",
    "sg:address":"Dorfstr. 4b",
    "sg:city":"Bruckberg",
    "sg:phone":"+49 8765/920400",
    "sg:postcode":"84079",
    "sg:province":"Bayern",
    "wof:name":"Sparmarkt",
    "wof:placetype":"venue"
},
  "geometry": {"coordinates":[11.9946832657,48.5235176086],"type":"Point"}
}