{
  "type": "Feature",
  "properties": {
    "iso:country":"DE",
    "sg:address":"Etivalstr. 50",
    "sg:city":"Pforzheim",
    "sg:phone":"+49 7231/927070",
    "sg:postcode":"75173",
    "sg:province":"Baden-W\u00fcrttemberg",
    "wof:name":"Hermann M\u00fcrle",
    "wof:placetype":"venue"
},
  "geometry": {"coordinates":[8.686417,48.879776],"type":"Point"}
}