{
  "type": "Feature",
  "properties": {
    "iso:country":"DE",
    "sg:address":"Otto-T\u00fcrpe-Str. 21",
    "sg:city":"Werdau",
    "sg:phone":"+49 4937/615371",
    "sg:postcode":"08412",
    "sg:province":"Sachsen",
    "wof:name":"Dieter Junghanns Fahrzeug- U Stahlbau",
    "wof:placetype":"venue"
},
  "geometry": {"coordinates":[12.3782587051,50.7198066711],"type":"Point"}
}