{
  "type": "Feature",
  "properties": {
    "iso:country":"DE",
    "sg:address":"Kindsbacher Str. 39 b",
    "sg:city":"Ramstein-Miesenbach",
    "sg:phone":"+49 6371/5381",
    "sg:postcode":"66877",
    "sg:province":"Rheinland-Pfalz",
    "wof:name":"Diner Box",
    "wof:placetype":"venue"
},
  "geometry": {"coordinates":[7.5628089905,49.4420013428],"type":"Point"}
}