{
  "type": "Feature",
  "properties": {
    "iso:country":"DE",
    "sg:address":"Schlo\u00dfplatz 6",
    "sg:city":"Schwetzingen",
    "sg:phone":"+49 6202/21021",
    "sg:postcode":"68723",
    "sg:province":"Baden-W\u00fcrttemberg",
    "wof:name":"Hermann M\u00fcller Kg",
    "wof:placetype":"venue"
},
  "geometry": {"coordinates":[8.573285,49.384258],"type":"Point"}
}