{
  "type": "Feature",
  "properties": {
    "iso:country":"DE",
    "sg:address":"M\u00fchlenstr.",
    "sg:city":"Korschenbroich",
    "sg:phone":"+49 2161/641031",
    "sg:postcode":"41352",
    "sg:province":"Nordrhein-Westfalen",
    "wof:name":"Dresen S\u00e4gewerk Und Holzhandlung Niederlassung",
    "wof:placetype":"venue"
},
  "geometry": {"coordinates":[6.511795,51.18996],"type":"Point"}
}