{
  "type": "Feature",
  "properties": {
    "iso:country":"DE",
    "sg:address":"Sparkassenstr. 7",
    "sg:city":"Bad K\u00f6nigshofen",
    "sg:phone":"+49 9761/1269",
    "sg:postcode":"97631",
    "sg:province":"Bayern",
    "wof:name":"Gernert Brennstoffhandel Gmbh",
    "wof:placetype":"venue"
},
  "geometry": {"coordinates":[10.4665145874,50.3011779785],"type":"Point"}
}