{
  "type": "Feature",
  "properties": {
    "iso:country":"DE",
    "sg:address":"Am Schnatwinkel 200",
    "sg:city":"Nienst\u00e4dt",
    "sg:postcode":"31688",
    "sg:province":"Niedersachsen",
    "wof:name":"C. Witte & Sohn Gmbh",
    "wof:placetype":"venue"
},
  "geometry": {"coordinates":[9.172294,52.299873],"type":"Point"}
}