{
  "type": "Feature",
  "properties": {
    "iso:country":"DE",
    "sg:address":"Brandweg 3",
    "sg:city":"Celle",
    "sg:phone":"+49 5141/32566",
    "sg:postcode":"29223",
    "sg:province":"Niedersachsen",
    "wof:name":"F. Meyer",
    "wof:placetype":"venue"
},
  "geometry": {"coordinates":[10.117037,52.641689],"type":"Point"}
}