{
  "type": "Feature",
  "properties": {
    "iso:country":"DE",
    "sg:address":"W\u00f6lper Str. 18",
    "sg:city":"Nienburg",
    "sg:phone":"+49 5021/3227",
    "sg:postcode":"31582",
    "sg:province":"Niedersachsen",
    "wof:name":"Bernhard Kindermann",
    "wof:placetype":"venue"
},
  "geometry": {"coordinates":[9.242796,52.665924],"type":"Point"}
}