{
  "type": "Feature",
  "properties": {
    "iso:country":"DE",
    "sg:address":"Ulmer Str. 22",
    "sg:city":"Augsburg",
    "sg:phone":"+49 821/241620",
    "sg:postcode":"86154",
    "sg:province":"Bayern",
    "wof:name":"Lorenz Spitzer Verwaltungs-gmbh",
    "wof:placetype":"venue"
},
  "geometry": {"coordinates":[10.876949,48.380707],"type":"Point"}
}