{
  "type": "Feature",
  "properties": {
    "iso:country":"DE",
    "sg:address":"Beulstr. 6",
    "sg:city":"Boden",
    "sg:phone":"+49 2602/8810",
    "sg:postcode":"56412",
    "sg:province":"Rheinland-Pfalz",
    "wof:name":"Gastst\u00e4tte Johann Stamm",
    "wof:placetype":"venue"
},
  "geometry": {"coordinates":[7.8591051102,50.4729995728],"type":"Point"}
}