{
  "type": "Feature",
  "properties": {
    "iso:country":"DE",
    "sg:address":"Buchweg 10a",
    "sg:city":"Lindenfels",
    "sg:phone":"+49 6255/2313",
    "sg:postcode":"64678",
    "sg:province":"Hessen",
    "wof:name":"Werner Reichel Marketing-consulting",
    "wof:placetype":"venue"
},
  "geometry": {"coordinates":[8.780164,49.690575],"type":"Point"}
}