{
  "type": "Feature",
  "properties": {
    "iso:country":"DE",
    "sg:address":"Kutschweg 7",
    "sg:city":"Nettersheim",
    "sg:phone":"+49 2484/95010",
    "sg:postcode":"53947",
    "sg:province":"Nordrhein-Westfalen",
    "wof:name":"Gedino Vertriebsgesellschaft F\u00fcr Elektronische Datenver-",
    "wof:placetype":"venue"
},
  "geometry": {"coordinates":[6.689987,50.524517],"type":"Point"}
}