{
  "type": "Feature",
  "properties": {
    "iso:country":"DE",
    "sg:address":"Dorfstr. 20",
    "sg:city":"Rietzel",
    "sg:phone":"+49 39223/497",
    "sg:postcode":"39291",
    "sg:province":"Sachsen-Anhalt",
    "wof:name":"Rolf B\u00f6cker",
    "wof:placetype":"venue"
},
  "geometry": {"coordinates":[12.015397,52.276688],"type":"Point"}
}