{
  "type": "Feature",
  "properties": {
    "iso:country":"DE",
    "sg:address":"Zweibr\u00fccker Str. 2",
    "sg:city":"Wallhalben",
    "sg:phone":"+49 6375/993742",
    "sg:postcode":"66917",
    "sg:province":"Rheinland-Pfalz",
    "wof:name":"Grumbeer-stubb Ludwigs Katz-haus",
    "wof:placetype":"venue"
},
  "geometry": {"coordinates":[7.5214300156,49.3164710999],"type":"Point"}
}