{
  "type": "Feature",
  "properties": {
    "iso:country":"DE",
    "sg:address":"Magdeburger Str. 11",
    "sg:city":"Genthin",
    "sg:phone":"+49 3933/803205",
    "sg:postcode":"39307",
    "sg:province":"Sachsen-Anhalt",
    "wof:name":"Bs Bauelemente Service- Gmbh",
    "wof:placetype":"venue"
},
  "geometry": {"coordinates":[12.152529,52.404217],"type":"Point"}
}