{
  "type": "Feature",
  "properties": {
    "iso:country":"DE",
    "sg:address":"Dieselstr 7",
    "sg:city":"Leverkusen",
    "sg:phone":"+49 2171/5080",
    "sg:postcode":"51381",
    "sg:province":"Nordrhein-Westfalen",
    "wof:name":"Foam Partner Reisgies Schaumstoffe Gmbh",
    "wof:placetype":"venue"
},
  "geometry": {"coordinates":[7.0145950317,51.0566291809],"type":"Point"}
}