{
  "type": "Feature",
  "properties": {
    "iso:country":"DE",
    "sg:address":"Hermannstr. 8",
    "sg:city":"Datteln",
    "sg:phone":"+49 2363/734305",
    "sg:postcode":"45711",
    "sg:province":"Nordrhein-Westfalen",
    "wof:name":"Heinrich Schulte",
    "wof:placetype":"venue"
},
  "geometry": {"coordinates":[7.3128700256,51.6278114319],"type":"Point"}
}