{
  "type": "Feature",
  "properties": {
    "iso:country":"DE",
    "sg:address":"Althof",
    "sg:city":"Biberach",
    "sg:phone":"+49 7351/71247",
    "sg:postcode":"88400",
    "sg:province":"Baden-W\u00fcrttemberg",
    "wof:name":"Standhardinger",
    "wof:placetype":"venue"
},
  "geometry": {"coordinates":[9.825665,48.111305],"type":"Point"}
}