{
  "type": "Feature",
  "properties": {
    "iso:country":"DE",
    "sg:address":"Bahnhofstr 6/3",
    "sg:city":"Aalen",
    "sg:phone":"+49 7361/69944",
    "sg:postcode":"73430",
    "sg:province":"Baden-W\u00fcrttemberg",
    "wof:name":"Lpc",
    "wof:placetype":"venue"
},
  "geometry": {"coordinates":[10.094809,48.838848],"type":"Point"}
}