{
  "type": "Feature",
  "properties": {
    "iso:country":"DE",
    "sg:address":"Ebernburgstr. 2 a",
    "sg:city":"Landau",
    "sg:phone":"+49 6341/30340",
    "sg:postcode":"76829",
    "sg:province":"Rheinland-Pfalz",
    "wof:name":"Ev. Pfarramt Wollmersheimer H\u00f6he",
    "wof:placetype":"venue"
},
  "geometry": {"coordinates":[8.0944051743,49.1917037964],"type":"Point"}
}