{
  "type": "Feature",
  "properties": {
    "iso:country":"DE",
    "sg:address":"Forststr. 44",
    "sg:city":"Duisburg",
    "sg:phone":"+49 203/773076",
    "sg:postcode":"47055",
    "sg:province":"Nordrhein-Westfalen",
    "wof:name":"J\u00fcrgen Stockhorst-laven",
    "wof:placetype":"venue"
},
  "geometry": {"coordinates":[6.7530698776,51.3953056335],"type":"Point"}
}