{
  "type": "Feature",
  "properties": {
    "iso:country":"DE",
    "sg:address":"Hainbuchenweg 1",
    "sg:city":"Landau",
    "sg:phone":"+49 9951/8437",
    "sg:postcode":"94405",
    "sg:province":"Bayern",
    "wof:name":"Alfons Endl",
    "wof:placetype":"venue"
},
  "geometry": {"coordinates":[12.6891517639,48.6855812073],"type":"Point"}
}