{
  "type": "Feature",
  "properties": {
    "iso:country":"DE",
    "sg:address":"Ittenbeuren 4e",
    "sg:city":"Ravensburg",
    "sg:phone":"+49 751/3528003",
    "sg:postcode":"88212",
    "sg:province":"Baden-W\u00fcrttemberg",
    "wof:name":"Masko - Der Spezialist F\u00fcr Fahnenpr\u00e4sentation",
    "wof:placetype":"venue"
},
  "geometry": {"coordinates":[9.6347112656,47.7562904358],"type":"Point"}
}