{
  "type": "Feature",
  "properties": {
    "iso:country":"DE",
    "sg:address":"Bonfelder Str. 24",
    "sg:city":"Heilbronn",
    "sg:phone":"+49 7066/7282",
    "sg:postcode":"74078",
    "sg:province":"Baden-W\u00fcrttemberg",
    "wof:name":"Ahlter Gmbh Kronenbrauerei",
    "wof:placetype":"venue"
},
  "geometry": {"coordinates":[9.1402015686,49.1953659058],"type":"Point"}
}