{
  "type": "Feature",
  "properties": {
    "iso:country":"DE",
    "sg:address":"Stockumer Str. 174",
    "sg:city":"Werne",
    "sg:postcode":"59368",
    "sg:province":"Nordrhein-Westfalen",
    "wof:name":"Kath. \u00f6ffentliche Bibliothek St. Konrad",
    "wof:placetype":"venue"
},
  "geometry": {"coordinates":[7.658016,51.663979],"type":"Point"}
}