{
  "type": "Feature",
  "properties": {
    "iso:country":"DE",
    "sg:address":"Fullener Str. 35 a",
    "sg:city":"Meppen",
    "sg:postcode":"49716",
    "sg:province":"Niedersachsen",
    "wof:name":"Bauunternehmen Niehoff Gmbh",
    "wof:placetype":"venue"
},
  "geometry": {"coordinates":[7.2656950951,52.6906700134],"type":"Point"}
}