{
  "type": "Feature",
  "properties": {
    "iso:country":"DE",
    "sg:address":"Wilhelm-L\u00f6bbe-Allee 2 a",
    "sg:city":"L\u00fcnen",
    "sg:postcode":"44534",
    "sg:province":"Nordrhein-Westfalen",
    "wof:name":"K & M Marken Vertriebs Verwaltungs- Gmbh",
    "wof:placetype":"venue"
},
  "geometry": {"coordinates":[7.5483789444,51.6261177063],"type":"Point"}
}