{
  "type": "Feature",
  "properties": {
    "iso:country":"DE",
    "sg:address":"Haselhofstr 29",
    "sg:city":"Erlangen",
    "sg:phone":"+49 9131/879312",
    "sg:postcode":"91058",
    "sg:province":"Bayern",
    "wof:name":"Gabo Anlagentechnik Und Proze\u00dfmanagement Gmbh",
    "wof:placetype":"venue"
},
  "geometry": {"coordinates":[11.018068,49.552204],"type":"Point"}
}