{
  "type": "Feature",
  "properties": {
    "iso:country":"DE",
    "sg:address":"Burgplatz 1",
    "sg:city":"Braunschweig",
    "sg:phone":"+49 531/15409",
    "sg:postcode":"38100",
    "sg:province":"Niedersachsen",
    "wof:name":"Bistro Im Landesmuseum",
    "wof:placetype":"venue"
},
  "geometry": {"coordinates":[10.5232095718,52.2647323608],"type":"Point"}
}