{
  "type": "Feature",
  "properties": {
    "iso:country":"DE",
    "sg:address":"Ottener Str. 23",
    "sg:city":"R\u00fcckholz",
    "sg:phone":"+49 8369/300",
    "sg:postcode":"87494",
    "sg:province":"Bayern",
    "wof:name":"Kaspar Straub",
    "wof:placetype":"venue"
},
  "geometry": {"coordinates":[10.546142,47.660007],"type":"Point"}
}