{
  "type": "Feature",
  "properties": {
    "iso:country":"DE",
    "sg:address":"Geschwister-Scholl-Str. 2",
    "sg:city":"Erlangen",
    "sg:phone":"+49 9131/301134",
    "sg:postcode":"91058",
    "sg:province":"Bayern",
    "wof:name":"\u00dcbelacker Und Kollegen Rechtsanw\u00e4lte",
    "wof:placetype":"venue"
},
  "geometry": {"coordinates":[10.9933595657,49.5768966675],"type":"Point"}
}