{
  "type": "Feature",
  "properties": {
    "iso:country":"DE",
    "sg:address":"Julius-Vogel-Str. 6",
    "sg:city":"Eislingen",
    "sg:phone":"+49 7161/990243",
    "sg:postcode":"73054",
    "sg:province":"Baden-W\u00fcrttemberg",
    "wof:name":"H. Wahl",
    "wof:placetype":"venue"
},
  "geometry": {"coordinates":[9.7071170807,48.7007675171],"type":"Point"}
}