{
  "type": "Feature",
  "properties": {
    "iso:country":"DE",
    "sg:address":"Wilsdruffer Str. 7",
    "sg:city":"Kesselsdorf",
    "sg:phone":"+49 35204/47187",
    "sg:postcode":"01723",
    "sg:province":"Sachsen",
    "wof:name":"Christine Beyer",
    "wof:placetype":"venue"
},
  "geometry": {"coordinates":[13.5870399475,51.033290863],"type":"Point"}
}