{
  "type": "Feature",
  "properties": {
    "iso:country":"DE",
    "sg:address":"Saseler Chaussee 191 A",
    "sg:city":"Hamburg",
    "sg:phone":"+49 40/6017930",
    "sg:postcode":"22393",
    "sg:province":"Hamburg",
    "wof:name":"Gerhard Buchmann Gmbh",
    "wof:placetype":"venue"
},
  "geometry": {"coordinates":[10.105475,53.651718],"type":"Point"}
}