{
  "type": "Feature",
  "properties": {
    "iso:country":"DE",
    "sg:address":"Rainstr.3",
    "sg:city":"Lahnau",
    "sg:phone":"+49 6441/96190",
    "sg:postcode":"35633",
    "sg:province":"Hessen",
    "wof:name":"Putzteufel Gmbh Lahnau",
    "wof:placetype":"venue"
},
  "geometry": {"coordinates":[8.543765,50.585724],"type":"Point"}
}