{
  "type": "Feature",
  "properties": {
    "iso:country":"DE",
    "sg:address":"Ehlingsh\u00e4user Str. 8",
    "sg:city":"Frankenau",
    "sg:phone":"+49 6455/8616",
    "sg:postcode":"35110",
    "sg:province":"Hessen",
    "wof:name":"Renate Thuma Rechtsanw\u00e4ltin",
    "wof:placetype":"venue"
},
  "geometry": {"coordinates":[8.9307861328,51.0919723511],"type":"Point"}
}