{
  "type": "Feature",
  "properties": {
    "iso:country":"DE",
    "sg:address":"Montenstr. 3",
    "sg:city":"M\u00fcnchen",
    "sg:phone":"+49 89/172257",
    "sg:postcode":"80639",
    "sg:province":"Bayern",
    "wof:name":"H.-w. Hulzburger Steuerberater",
    "wof:placetype":"venue"
},
  "geometry": {"coordinates":[11.5223226547,48.1570701599],"type":"Point"}
}