{
  "type": "Feature",
  "properties": {
    "iso:country":"DE",
    "sg:address":"Schneidhausen",
    "sg:city":"Kreuzau",
    "sg:phone":"+49 2422/540",
    "sg:postcode":"52372",
    "sg:province":"Nordrhein-Westfalen",
    "wof:name":"Hoesch Metall- Und Kunststoffwerk",
    "wof:placetype":"venue"
},
  "geometry": {"coordinates":[6.480786,50.752377],"type":"Point"}
}