{
  "type": "Feature",
  "properties": {
    "iso:country":"DE",
    "sg:address":"Am Alten Graben 4",
    "sg:city":"Michelstadt",
    "sg:phone":"+49 6061/3840",
    "sg:postcode":"64720",
    "sg:province":"Hessen",
    "wof:name":"Rolf Apitzsch",
    "wof:placetype":"venue"
},
  "geometry": {"coordinates":[9.0062732697,49.6668586731],"type":"Point"}
}