{
  "type": "Feature",
  "properties": {
    "iso:country":"DE",
    "sg:address":"Hauptstr. 50",
    "sg:city":"Calberlah",
    "sg:phone":"+49 5374/9757",
    "sg:postcode":"38547",
    "sg:province":"Niedersachsen",
    "wof:name":"Schuh U. Sport Salge Gmbh",
    "wof:placetype":"venue"
},
  "geometry": {"coordinates":[10.6259126663,52.4206619263],"type":"Point"}
}