{
  "type": "Feature",
  "properties": {
    "iso:country":"DE",
    "sg:address":"Erbachstr. 24",
    "sg:city":"Morbach",
    "sg:phone":"+49 6533/2227",
    "sg:postcode":"54497",
    "sg:province":"Rheinland-Pfalz",
    "wof:name":"Deho Verwaltungs Gmbh",
    "wof:placetype":"venue"
},
  "geometry": {"coordinates":[7.133885,49.807446],"type":"Point"}
}