{
  "type": "Feature",
  "properties": {
    "iso:country":"DE",
    "sg:address":"Am Bahnhof 299",
    "sg:city":"Lebus",
    "sg:phone":"+49 33604/284",
    "sg:postcode":"15326",
    "sg:province":"Brandenburg",
    "wof:name":"Geschw. Powelleit",
    "wof:placetype":"venue"
},
  "geometry": {"coordinates":[14.52716,52.427029],"type":"Point"}
}