{
  "type": "Feature",
  "properties": {
    "iso:country":"DE",
    "sg:address":"Im Gries 5",
    "sg:city":"Dittelbrunn",
    "sg:phone":"+49 9725/4925",
    "sg:postcode":"97456",
    "sg:province":"Bayern",
    "wof:name":"Hannelore Reinert-jansen Heilpraktikerin",
    "wof:placetype":"venue"
},
  "geometry": {"coordinates":[10.2060670853,50.094417572],"type":"Point"}
}