{
  "type": "Feature",
  "properties": {
    "iso:country":"DE",
    "sg:address":"Brunnenstr. 8",
    "sg:city":"Karlsruhe",
    "sg:phone":"+49 721/374532",
    "sg:postcode":"76131",
    "sg:province":"Baden-W\u00fcrttemberg",
    "wof:name":"Pension Klein Venedig",
    "wof:placetype":"venue"
},
  "geometry": {"coordinates":[8.4155292511,49.0087738037],"type":"Point"}
}