{
  "type": "Feature",
  "properties": {
    "iso:country":"DE",
    "sg:address":"Hinter der Kirche 204",
    "sg:city":"Bad Colberg-Heldburg",
    "sg:postcode":"98663",
    "sg:province":"Th\u00fcringen",
    "wof:name":"Schwarz Gmbh",
    "wof:placetype":"venue"
},
  "geometry": {"coordinates":[10.7232475281,50.2800521851],"type":"Point"}
}