{
  "type": "Feature",
  "properties": {
    "iso:country":"DE",
    "sg:address":"Overdyker Str. 31",
    "sg:city":"Bochum",
    "sg:phone":"+49 234/9520005",
    "sg:postcode":"44809",
    "sg:province":"Nordrhein-Westfalen",
    "wof:name":"Heinz-g\u00fcnter Lietz",
    "wof:placetype":"venue"
},
  "geometry": {"coordinates":[7.188680172,51.4927215576],"type":"Point"}
}