{
  "type": "Feature",
  "properties": {
    "iso:country":"DE",
    "sg:address":"Natorper Str. 14",
    "sg:city":"Holzwickede",
    "sg:phone":"+49 2301/2857",
    "sg:postcode":"59439",
    "sg:province":"Nordrhein-Westfalen",
    "wof:name":"Walter M\u00fcller",
    "wof:placetype":"venue"
},
  "geometry": {"coordinates":[7.61959,51.510494],"type":"Point"}
}