{
  "type": "Feature",
  "properties": {
    "iso:country":"DE",
    "sg:address":"Grimmaische Str. 16",
    "sg:city":"Borsdorf",
    "sg:postcode":"04451",
    "sg:province":"Sachsen",
    "wof:name":"Bauservice Muldental Gmbh",
    "wof:placetype":"venue"
},
  "geometry": {"coordinates":[12.538421,51.343166],"type":"Point"}
}