{
  "type": "Feature",
  "properties": {
    "iso:country":"DE",
    "sg:address":"Hohenstaufenstr. 56",
    "sg:city":"G\u00f6ppingen",
    "sg:phone":"+49 7161/69065",
    "sg:postcode":"73033",
    "sg:province":"Baden-W\u00fcrttemberg",
    "wof:name":"W. Gaa Steuerberater",
    "wof:placetype":"venue"
},
  "geometry": {"coordinates":[9.6692419052,48.7055931091],"type":"Point"}
}