{
  "type": "Feature",
  "properties": {
    "iso:country":"DE",
    "sg:address":"Friedrich-Rottra-Str. 64",
    "sg:city":"Efringen-Kirchen",
    "sg:phone":"+49 7628/9932",
    "sg:postcode":"79588",
    "sg:province":"Baden-W\u00fcrttemberg",
    "wof:name":"I. Walter",
    "wof:placetype":"venue"
},
  "geometry": {"coordinates":[7.568789,47.647697],"type":"Point"}
}