{
  "type": "Feature",
  "properties": {
    "iso:country":"DE",
    "sg:address":"Bocketaler Str. 24",
    "sg:city":"Ibbenb\u00fcren",
    "sg:phone":"+49 5451/8244",
    "sg:postcode":"49479",
    "sg:province":"Nordrhein-Westfalen",
    "wof:name":"Architekten Markmeyer & Borgel Partnerschaft",
    "wof:placetype":"venue"
},
  "geometry": {"coordinates":[7.7813801765,52.2577209473],"type":"Point"}
}