{
  "type": "Feature",
  "properties": {
    "iso:country":"DE",
    "sg:address":"Hauptstr. 42",
    "sg:city":"Denkingen",
    "sg:phone":"+49 7424/97080",
    "sg:postcode":"78588",
    "sg:province":"Baden-W\u00fcrttemberg",
    "wof:name":"Dr. Med. Alfred Schwarz",
    "wof:placetype":"venue"
},
  "geometry": {"coordinates":[8.7358646393,48.1085205078],"type":"Point"}
}