{
  "type": "Feature",
  "properties": {
    "iso:country":"DE",
    "sg:address":"Lindenstr. 1",
    "sg:city":"Haslach",
    "sg:phone":"+49 7832/5265",
    "sg:postcode":"77716",
    "sg:province":"Baden-W\u00fcrttemberg",
    "wof:name":"R. Moser",
    "wof:placetype":"venue"
},
  "geometry": {"coordinates":[8.110975,48.287071],"type":"Point"}
}