{
  "type": "Feature",
  "properties": {
    "iso:country":"DE",
    "sg:address":"Brunner-Bey-Str. 22",
    "sg:city":"Pfreimd",
    "sg:phone":"+49 9606/8458",
    "sg:postcode":"92536",
    "sg:province":"Bayern",
    "wof:name":"H. Und M. Bl\u00f6th",
    "wof:placetype":"venue"
},
  "geometry": {"coordinates":[12.1831932068,49.4883346558],"type":"Point"}
}