{
  "type": "Feature",
  "properties": {
    "iso:country":"DE",
    "sg:address":"Otto-Findeisen-Str. 3",
    "sg:city":"Eibenstock",
    "sg:phone":"+49 37752/3191",
    "sg:postcode":"08309",
    "sg:province":"Sachsen",
    "wof:name":"Siegfried Funk",
    "wof:placetype":"venue"
},
  "geometry": {"coordinates":[12.601061821,50.4939041138],"type":"Point"}
}