{
  "type": "Feature",
  "properties": {
    "iso:country":"DE",
    "sg:address":"St\u00fcvestr. 15",
    "sg:city":"Essen",
    "sg:phone":"+49 201/765846",
    "sg:postcode":"45144",
    "sg:province":"Nordrhein-Westfalen",
    "wof:name":"Schachklub Holsterhausen",
    "wof:placetype":"venue"
},
  "geometry": {"coordinates":[6.9683451653,51.4526138306],"type":"Point"}
}