{
  "type": "Feature",
  "properties": {
    "iso:country":"DE",
    "sg:address":"Mothmecke 7",
    "sg:city":"Schmallenberg",
    "sg:phone":"+49 2974/6655",
    "sg:postcode":"57392",
    "sg:province":"Nordrhein-Westfalen",
    "wof:name":"Hermann Schl\u00fcter",
    "wof:placetype":"venue"
},
  "geometry": {"coordinates":[8.30936,51.191883],"type":"Point"}
}