{
  "type": "Feature",
  "properties": {
    "iso:country":"DE",
    "sg:address":"B\u00fcrgermeister-St\u00f6ckle-Str. 6",
    "sg:city":"Bad W\u00f6rishofen",
    "sg:phone":"+49 8247/7787",
    "sg:postcode":"86825",
    "sg:province":"Bayern",
    "wof:name":"Emma Schindler",
    "wof:placetype":"venue"
},
  "geometry": {"coordinates":[10.5911474228,48.0032310486],"type":"Point"}
}