{
  "type": "Feature",
  "properties": {
    "iso:country":"DE",
    "sg:address":"Assmannstr. 3",
    "sg:city":"Regensburg",
    "sg:postcode":"93049",
    "sg:province":"Bayern",
    "wof:name":"Schild Nickel & Partner Gmbh",
    "wof:placetype":"venue"
},
  "geometry": {"coordinates":[12.0594491959,49.0165634155],"type":"Point"}
}