{
  "type": "Feature",
  "properties": {
    "iso:country":"DE",
    "sg:address":"Alte Str. 62",
    "sg:city":"Schwanstetten",
    "sg:phone":"+49 9170/94490",
    "sg:postcode":"90596",
    "sg:province":"Bayern",
    "wof:name":"G\u00fcnther Pr\u00f6chel",
    "wof:placetype":"venue"
},
  "geometry": {"coordinates":[11.1212263107,49.2992210388],"type":"Point"}
}