{
  "type": "Feature",
  "properties": {
    "iso:country":"DE",
    "sg:address":"Schmidstr. 42",
    "sg:city":"Friedrichshafen",
    "sg:phone":"+49 7541/23735",
    "sg:postcode":"88045",
    "sg:province":"Baden-W\u00fcrttemberg",
    "wof:name":"Georg T\u00fcshans",
    "wof:placetype":"venue"
},
  "geometry": {"coordinates":[9.455861,47.655128],"type":"Point"}
}