{
  "type": "Feature",
  "properties": {
    "iso:country":"DE",
    "sg:address":"Federnseestr. 3",
    "sg:city":"Reutlingen",
    "sg:phone":"+49 7121/93500",
    "sg:postcode":"72764",
    "sg:province":"Baden-W\u00fcrttemberg",
    "wof:name":"Hypo-immobilien-service Gmbh",
    "wof:placetype":"venue"
},
  "geometry": {"coordinates":[9.2090320587,48.4933586121],"type":"Point"}
}