{
  "type": "Feature",
  "properties": {
    "iso:country":"DE",
    "sg:address":"Mozartstr. 111",
    "sg:city":"Wasserburg",
    "sg:phone":"+49 8071/925522",
    "sg:postcode":"83512",
    "sg:province":"Bayern",
    "wof:name":"Wood-line M\u00f6belvertriebs Gmbh",
    "wof:placetype":"venue"
},
  "geometry": {"coordinates":[12.214955,48.050663],"type":"Point"}
}