{
  "type": "Feature",
  "properties": {
    "iso:country":"DE",
    "sg:address":"Robert-Kratt-Str. 5",
    "sg:city":"M\u00f6nchweiler",
    "sg:phone":"+49 7721/71180",
    "sg:postcode":"78087",
    "sg:province":"Baden-W\u00fcrttemberg",
    "wof:name":"Rainer Lehmann",
    "wof:placetype":"venue"
},
  "geometry": {"coordinates":[8.426511,48.095619],"type":"Point"}
}