{
  "type": "Feature",
  "properties": {
    "iso:country":"DE",
    "sg:address":"Pappelallee 66",
    "sg:city":"Berlin",
    "sg:phone":"+49 30/4442180",
    "sg:postcode":"10437",
    "sg:province":"Berlin",
    "wof:name":"Klax E. V.",
    "wof:placetype":"venue"
},
  "geometry": {"coordinates":[13.4168119431,52.5454216003],"type":"Point"}
}