{
  "type": "Feature",
  "properties": {
    "iso:country":"DE",
    "sg:address":"Ostenallee 20",
    "sg:city":"Hamm",
    "sg:phone":"+49 2381/924280",
    "sg:postcode":"59063",
    "sg:province":"Nordrhein-Westfalen",
    "wof:name":"Leg Landesentwicklungsges. Nordrhein-westfalen Mbh",
    "wof:placetype":"venue"
},
  "geometry": {"coordinates":[7.829805851,51.6842193604],"type":"Point"}
}