{
  "type": "Feature",
  "properties": {
    "iso:country":"DE",
    "sg:address":"Windm\u00fchlenweg 4",
    "sg:city":"Schellerten",
    "sg:phone":"+49 5123/7638",
    "sg:postcode":"31174",
    "sg:province":"Niedersachsen",
    "wof:name":"Martin Wulf",
    "wof:placetype":"venue"
},
  "geometry": {"coordinates":[10.130497,52.175282],"type":"Point"}
}