{
  "type": "Feature",
  "properties": {
    "iso:country":"DE",
    "sg:address":"G\u00f6ppersdorfer Str. 64",
    "sg:city":"Burgst\u00e4dt",
    "sg:phone":"+49 3724/84812",
    "sg:postcode":"09217",
    "sg:province":"Sachsen",
    "wof:name":"R. Richter",
    "wof:placetype":"venue"
},
  "geometry": {"coordinates":[12.8025217056,50.9061164856],"type":"Point"}
}