{
  "type": "Feature",
  "properties": {
    "iso:country":"DE",
    "sg:address":"Hellweg 8 a",
    "sg:city":"Erwitte",
    "sg:phone":"+49 2943/3732",
    "sg:postcode":"59597",
    "sg:province":"Nordrhein-Westfalen",
    "wof:name":"Hanni G\u00f6bel",
    "wof:placetype":"venue"
},
  "geometry": {"coordinates":[8.337343,51.611996],"type":"Point"}
}