{
  "type": "Feature",
  "properties": {
    "iso:country":"DE",
    "sg:address":"St.Paulusstr. 2",
    "sg:city":"Balingen",
    "sg:postcode":"72336",
    "sg:province":"Baden-W\u00fcrttemberg",
    "wof:name":"Dpsg Frommern",
    "wof:placetype":"venue"
},
  "geometry": {"coordinates":[8.8748893738,48.2463150024],"type":"Point"}
}