{
  "type": "Feature",
  "properties": {
    "iso:country":"DE",
    "sg:address":"Lilienthalallee 40",
    "sg:city":"M\u00fcnchen",
    "sg:postcode":"80939",
    "sg:province":"Bayern",
    "wof:name":"Group 3 G Umts Holding Gmbh",
    "wof:placetype":"venue"
},
  "geometry": {"coordinates":[11.610454,48.197746],"type":"Point"}
}