{
  "type": "Feature",
  "properties": {
    "iso:country":"DE",
    "sg:address":"Leher Heerstr. 37",
    "sg:city":"Bremen",
    "sg:phone":"+49 421/239085",
    "sg:postcode":"28359",
    "sg:province":"Bremen",
    "wof:name":"Lloyd-dental Gmbh",
    "wof:placetype":"venue"
},
  "geometry": {"coordinates":[8.872816,53.100121],"type":"Point"}
}