{
  "type": "Feature",
  "properties": {
    "iso:country":"DE",
    "sg:address":"Vorderer Talweg 28",
    "sg:city":"Rottendorf",
    "sg:phone":"+49 9302/507",
    "sg:postcode":"97228",
    "sg:province":"Bayern",
    "wof:name":"Adolf Schlaghaufer",
    "wof:placetype":"venue"
},
  "geometry": {"coordinates":[10.021717,49.787174],"type":"Point"}
}