{
  "type": "Feature",
  "properties": {
    "iso:country":"DE",
    "sg:address":"Hochstr. 24",
    "sg:city":"Krefeld",
    "sg:phone":"+49 2151/69511",
    "sg:postcode":"47798",
    "sg:province":"Nordrhein-Westfalen",
    "wof:name":"G. Sch\u00e4tzlein",
    "wof:placetype":"venue"
},
  "geometry": {"coordinates":[6.5644950867,51.3286323547],"type":"Point"}
}