{
  "type": "Feature",
  "properties": {
    "iso:country":"DE",
    "sg:address":"An der Schinnenburg 4",
    "sg:city":"Ratingen",
    "sg:phone":"+49 2102/60687",
    "sg:postcode":"40883",
    "sg:province":"Nordrhein-Westfalen",
    "wof:name":"Heinz-e. Graffmann Rechtsanwalt",
    "wof:placetype":"venue"
},
  "geometry": {"coordinates":[6.9185848236,51.3313102722],"type":"Point"}
}