{
  "type": "Feature",
  "properties": {
    "iso:country":"DE",
    "sg:address":"Franz\u00f6sische Str. 27a",
    "sg:city":"Berlin",
    "sg:phone":"+49 30/2041523",
    "sg:postcode":"10117",
    "sg:province":"Berlin",
    "wof:name":"R. M\u00e4ngel Architekt",
    "wof:placetype":"venue"
},
  "geometry": {"coordinates":[13.39338,52.514877],"type":"Point"}
}