{
  "type": "Feature",
  "properties": {
    "iso:country":"DE",
    "sg:address":"M\u00fchlenstr. 2",
    "sg:city":"Merzenich",
    "sg:phone":"+49 2421/34548",
    "sg:postcode":"52399",
    "sg:province":"Nordrhein-Westfalen",
    "wof:name":"F. Reimer",
    "wof:placetype":"venue"
},
  "geometry": {"coordinates":[6.53682,50.821098],"type":"Point"}
}