{
  "type": "Feature",
  "properties": {
    "iso:country":"DE",
    "sg:address":"Piflaser Weg",
    "sg:city":"Landshut",
    "sg:phone":"+49 871/273366",
    "sg:postcode":"84034",
    "sg:province":"Bayern",
    "wof:name":"Helmut Wartner Landschaftsarchitekt",
    "wof:placetype":"venue"
},
  "geometry": {"coordinates":[12.159418,48.546108],"type":"Point"}
}