{
  "type": "Feature",
  "properties": {
    "iso:country":"DE",
    "sg:address":"Nordring 172",
    "sg:city":"Issum",
    "sg:phone":"+49 2835/3556",
    "sg:postcode":"47661",
    "sg:province":"Nordrhein-Westfalen",
    "wof:name":"Johannes Verheyen",
    "wof:placetype":"venue"
},
  "geometry": {"coordinates":[6.409218,51.541668],"type":"Point"}
}