{
  "type": "Feature",
  "properties": {
    "iso:country":"DE",
    "sg:address":"Schillerstr. 10",
    "sg:city":"Rebesgr\u00fcn",
    "sg:postcode":"08209",
    "sg:province":"Sachsen",
    "wof:name":"Evang.-luth. Kirche Rebesgr\u00fcn",
    "wof:placetype":"venue"
},
  "geometry": {"coordinates":[12.3707122803,50.5243339539],"type":"Point"}
}