{
  "type": "Feature",
  "properties": {
    "iso:country":"DE",
    "sg:address":"Burgholzstr. 62",
    "sg:city":"Dortmund",
    "sg:phone":"+49 231/8630549",
    "sg:postcode":"44145",
    "sg:province":"Nordrhein-Westfalen",
    "wof:name":"Hansa-tor",
    "wof:placetype":"venue"
},
  "geometry": {"coordinates":[7.4640469551,51.5290679932],"type":"Point"}
}