{
  "type": "Feature",
  "properties": {
    "iso:country":"DE",
    "sg:address":"Lohm\u00fchlenstr. 23",
    "sg:city":"Wirges",
    "sg:phone":"+49 2602/80645",
    "sg:postcode":"56422",
    "sg:province":"Rheinland-Pfalz",
    "wof:name":"Wiku Gesellschaft F\u00fcr Kunststoff- Und Anlagen-",
    "wof:placetype":"venue"
},
  "geometry": {"coordinates":[7.791976,50.476196],"type":"Point"}
}