{
  "type": "Feature",
  "properties": {
    "iso:country":"DE",
    "sg:address":"Wattmannstr. 40",
    "sg:city":"Kaarst",
    "sg:phone":"+49 2131/605001",
    "sg:postcode":"41564",
    "sg:province":"Nordrhein-Westfalen",
    "wof:name":"Team Druck Gmbh",
    "wof:placetype":"venue"
},
  "geometry": {"coordinates":[6.577064991,51.2150802612],"type":"Point"}
}