{
  "type": "Feature",
  "properties": {
    "iso:country":"DE",
    "sg:address":"Potsdamer Str. 16",
    "sg:city":"Brandenburg",
    "sg:postcode":"14776",
    "sg:province":"Brandenburg",
    "wof:name":"Ivb Ingenieurb\u00fcro F\u00fcr Vermessung Brandenburg Gmbh",
    "wof:placetype":"venue"
},
  "geometry": {"coordinates":[12.575261116,52.4058113098],"type":"Point"}
}