{
  "type": "Feature",
  "properties": {
    "iso:country":"DE",
    "sg:address":"Quellenstr. 35",
    "sg:city":"Remagen",
    "sg:phone":"+49 2642/980478",
    "sg:postcode":"53424",
    "sg:province":"Rheinland-Pfalz",
    "wof:name":"Stopfer Und Holzem",
    "wof:placetype":"venue"
},
  "geometry": {"coordinates":[7.272042,50.560371],"type":"Point"}
}