{
  "type": "Feature",
  "properties": {
    "iso:country":"DE",
    "sg:address":"Feldstr.",
    "sg:city":"Kierspe",
    "sg:postcode":"58566",
    "sg:province":"Nordrhein-Westfalen",
    "wof:name":"Willi Clever",
    "wof:placetype":"venue"
},
  "geometry": {"coordinates":[7.620661,51.129063],"type":"Point"}
}