{
  "type": "Feature",
  "properties": {
    "iso:country":"DE",
    "sg:address":"Wiesendamm 37",
    "sg:city":"Hamburg",
    "sg:phone":"+49 40/291727",
    "sg:postcode":"22305",
    "sg:province":"Hamburg",
    "wof:name":"Alstertal Malerei Gmbh",
    "wof:placetype":"venue"
},
  "geometry": {"coordinates":[10.039662,53.587067],"type":"Point"}
}