{
  "type": "Feature",
  "properties": {
    "iso:country":"DE",
    "sg:address":"Gustav-Adolf-Str. 9",
    "sg:city":"Berlin",
    "sg:phone":"+49 30/96202690",
    "sg:postcode":"13086",
    "sg:province":"Berlin",
    "wof:name":"Cornelius Jerecinski",
    "wof:placetype":"venue"
},
  "geometry": {"coordinates":[13.43271,52.552589],"type":"Point"}
}