{
  "type": "Feature",
  "properties": {
    "iso:country":"DE",
    "sg:address":"Hohlstr. 6",
    "sg:city":"Selters",
    "sg:phone":"+49 6483/7204",
    "sg:postcode":"65618",
    "sg:province":"Hessen",
    "wof:name":"H. Weichel",
    "wof:placetype":"venue"
},
  "geometry": {"coordinates":[8.263954,50.371597],"type":"Point"}
}