{
  "type": "Feature",
  "properties": {
    "iso:country":"DE",
    "sg:address":"Hauptstr. 12",
    "sg:city":"Hormersdorf",
    "sg:phone":"+49 3721/22378",
    "sg:postcode":"09395",
    "sg:province":"Sachsen",
    "wof:name":"Dauerbackwaren S\u00fc\u00dfwarenvertrieb",
    "wof:placetype":"venue"
},
  "geometry": {"coordinates":[12.8799200058,50.6833381653],"type":"Point"}
}