{
  "type": "Feature",
  "properties": {
    "iso:country":"DE",
    "sg:address":"Huttropstr. 61",
    "sg:city":"Essen",
    "sg:phone":"+49 201/250450",
    "sg:postcode":"45138",
    "sg:province":"Nordrhein-Westfalen",
    "wof:name":"Christine Dreyer",
    "wof:placetype":"venue"
},
  "geometry": {"coordinates":[7.0349488258,51.4437904358],"type":"Point"}
}