{
  "type": "Feature",
  "properties": {
    "iso:country":"DE",
    "sg:address":"Wasastr. 9",
    "sg:city":"Osnabr\u00fcck",
    "sg:phone":"+49 541/586066",
    "sg:postcode":"49082",
    "sg:province":"Niedersachsen",
    "wof:name":"Karl Freye",
    "wof:placetype":"venue"
},
  "geometry": {"coordinates":[8.0606832504,52.267124176],"type":"Point"}
}