{
  "type": "Feature",
  "properties": {
    "iso:country":"DE",
    "sg:address":"Schumanstr. 9",
    "sg:city":"W\u00fcrselen",
    "sg:phone":"+49 2405/41120",
    "sg:postcode":"52146",
    "sg:province":"Nordrhein-Westfalen",
    "wof:name":"M\u00f6bel Kings Gmbh",
    "wof:placetype":"venue"
},
  "geometry": {"coordinates":[6.152323,50.809353],"type":"Point"}
}