{
  "type": "Feature",
  "properties": {
    "iso:country":"DE",
    "sg:address":"Scheurlstr. 24",
    "sg:city":"N\u00fcrnberg",
    "sg:phone":"+49 911/945770",
    "sg:postcode":"90478",
    "sg:province":"Bayern",
    "wof:name":"Lichtzentrale Thurner Gmbh",
    "wof:placetype":"venue"
},
  "geometry": {"coordinates":[11.0885591507,49.4441833496],"type":"Point"}
}