{
  "type": "Feature",
  "properties": {
    "iso:country":"DE",
    "sg:address":"Jenaer Str 7",
    "sg:city":"M\u00f6nchengladbach",
    "sg:phone":"+49 2161/41358",
    "sg:postcode":"41065",
    "sg:province":"Nordrhein-Westfalen",
    "wof:name":"Herbert Laaser",
    "wof:placetype":"venue"
},
  "geometry": {"coordinates":[6.4444527626,51.1936302185],"type":"Point"}
}