{
  "type": "Feature",
  "properties": {
    "iso:country":"DE",
    "sg:address":"Memminger Str. 7",
    "sg:city":"Dietmannsried",
    "sg:phone":"+49 8374/6058",
    "sg:postcode":"87463",
    "sg:province":"Bayern",
    "wof:name":"Friedrich Dedler B\u00e4ckerei Gmbh",
    "wof:placetype":"venue"
},
  "geometry": {"coordinates":[10.289035,47.809395],"type":"Point"}
}