{
  "type": "Feature",
  "properties": {
    "iso:country":"DE",
    "sg:address":"Breslauer Str. 271",
    "sg:city":"Wolfsburg",
    "sg:phone":"+49 5361/35371",
    "sg:postcode":"38440",
    "sg:province":"Niedersachsen",
    "wof:name":"K. H. D\u00fcrr Tennislehrer",
    "wof:placetype":"venue"
},
  "geometry": {"coordinates":[10.7563896179,52.4083442688],"type":"Point"}
}