{
  "type": "Feature",
  "properties": {
    "iso:country":"DE",
    "sg:address":"Otto-von-Steinbeis-Str. 16",
    "sg:city":"Bruckm\u00fchl",
    "sg:phone":"+49 8062/70720",
    "sg:postcode":"83052",
    "sg:province":"Bayern",
    "wof:name":"Steinbeis Beratung Gmbh",
    "wof:placetype":"venue"
},
  "geometry": {"coordinates":[11.8985528946,47.8796615601],"type":"Point"}
}