{
  "type": "Feature",
  "properties": {
    "iso:country":"DE",
    "sg:address":"Salzstr. 60",
    "sg:city":"Heilbronn",
    "sg:phone":"+49 7131/94280",
    "sg:postcode":"74076",
    "sg:province":"Baden-W\u00fcrttemberg",
    "wof:name":"W. Und H. Frank",
    "wof:placetype":"venue"
},
  "geometry": {"coordinates":[9.2166919708,49.1557388306],"type":"Point"}
}