{
  "type": "Feature",
  "properties": {
    "iso:country":"DE",
    "sg:address":"Breite Str. 53",
    "sg:city":"Witten",
    "sg:phone":"+49 2302/56377",
    "sg:postcode":"58452",
    "sg:province":"Nordrhein-Westfalen",
    "wof:name":"H.-w. Golding",
    "wof:placetype":"venue"
},
  "geometry": {"coordinates":[7.330343,51.441425],"type":"Point"}
}