{
  "type": "Feature",
  "properties": {
    "iso:country":"DE",
    "sg:address":"Germaniastr. 199",
    "sg:city":"Essen",
    "sg:postcode":"45355",
    "sg:province":"Nordrhein-Westfalen",
    "wof:name":"Ways We Are Your Service E. K.",
    "wof:placetype":"venue"
},
  "geometry": {"coordinates":[6.959222,51.474621],"type":"Point"}
}