{
  "type": "Feature",
  "properties": {
    "iso:country":"DE",
    "sg:address":"Offenbacher Str. 19",
    "sg:city":"Herxheim",
    "sg:phone":"+49 7276/1201",
    "sg:postcode":"76863",
    "sg:province":"Rheinland-Pfalz",
    "wof:name":"Albert Rieder",
    "wof:placetype":"venue"
},
  "geometry": {"coordinates":[8.2084789276,49.1514625549],"type":"Point"}
}