{
  "type": "Feature",
  "properties": {
    "iso:country":"DE",
    "sg:address":"Ferndorfstr. 213",
    "sg:city":"Hilchenbach",
    "sg:phone":"+49 2733/4095",
    "sg:postcode":"57271",
    "sg:province":"Nordrhein-Westfalen",
    "wof:name":"Erich Menn",
    "wof:placetype":"venue"
},
  "geometry": {"coordinates":[8.14827,51.006615],"type":"Point"}
}