{
  "type": "Feature",
  "properties": {
    "iso:country":"DE",
    "sg:address":"Raiffeisenstr. 9",
    "sg:city":"Isen",
    "sg:phone":"+49 8083/9513",
    "sg:postcode":"84424",
    "sg:province":"Bayern",
    "wof:name":"H. E. Lechner",
    "wof:placetype":"venue"
},
  "geometry": {"coordinates":[12.0602197647,48.21276474],"type":"Point"}
}