{
  "type": "Feature",
  "properties": {
    "iso:country":"DE",
    "sg:address":"Hohe Klinge 1",
    "sg:city":"Calw",
    "sg:phone":"+49 7051/51319",
    "sg:postcode":"75365",
    "sg:province":"Baden-W\u00fcrttemberg",
    "wof:name":"Harald Mast Architekt",
    "wof:placetype":"venue"
},
  "geometry": {"coordinates":[8.740565,48.736469],"type":"Point"}
}