{
  "type": "Feature",
  "properties": {
    "iso:country":"DE",
    "sg:address":"Jahnstra\u00dfe 41 + 41a",
    "sg:city":"Ratingen",
    "sg:postcode":"40885",
    "sg:province":"Nordrhein-Westfalen",
    "wof:name":"Hotel Am Hallenbad",
    "wof:placetype":"venue"
},
  "geometry": {"coordinates":[6.8381061554,51.3319168091],"type":"Point"}
}