{
  "type": "Feature",
  "properties": {
    "iso:country":"DE",
    "sg:address":"Bahnhofstr. 41",
    "sg:city":"Berlin",
    "sg:postcode":"12555",
    "sg:province":"Berlin",
    "wof:name":"Gordon Jack Fashion Products Gmbh",
    "wof:placetype":"venue"
},
  "geometry": {"coordinates":[13.5775728226,52.4567756653],"type":"Point"}
}