{
  "type": "Feature",
  "properties": {
    "iso:country":"DE",
    "sg:city":"Alheim",
    "sg:phone":"+49 5664/7160",
    "sg:postcode":"36211",
    "sg:province":"Hessen",
    "wof:name":"Gerhard Siebold B\u00e4ckerei",
    "wof:placetype":"venue"
},
  "geometry": {"coordinates":[9.668355,51.024525],"type":"Point"}
}