{
  "type": "Feature",
  "properties": {
    "iso:country":"DE",
    "sg:address":"Wilhelmstr. 8",
    "sg:city":"Ehningen",
    "sg:phone":"+49 7034/8950",
    "sg:postcode":"71139",
    "sg:province":"Baden-W\u00fcrttemberg",
    "wof:name":"D. K\u00fchn",
    "wof:placetype":"venue"
},
  "geometry": {"coordinates":[8.943492,48.660706],"type":"Point"}
}