{
  "type": "Feature",
  "properties": {
    "iso:country":"DE",
    "sg:address":"Hohenstaufenring 39",
    "sg:city":"K\u00f6ln",
    "sg:phone":"+49 221/9210268",
    "sg:postcode":"50674",
    "sg:province":"Nordrhein-Westfalen",
    "wof:name":"Mediengestaltung Dix Siefer",
    "wof:placetype":"venue"
},
  "geometry": {"coordinates":[6.939999,50.931984],"type":"Point"}
}