{
  "type": "Feature",
  "properties": {
    "iso:country":"DE",
    "sg:address":"Buchenweg 6",
    "sg:city":"Lohmar",
    "sg:phone":"+49 2246/5718",
    "sg:postcode":"53797",
    "sg:province":"Nordrhein-Westfalen",
    "wof:name":"Siegfried Mei\u00dfner Und Helmut Philippi",
    "wof:placetype":"venue"
},
  "geometry": {"coordinates":[7.2335591316,50.8553276062],"type":"Point"}
}