{
  "type": "Feature",
  "properties": {
    "iso:country":"DE",
    "sg:address":"Sonnenstr. 8",
    "sg:city":"Solingen",
    "sg:phone":"+49 212/203079",
    "sg:postcode":"42655",
    "sg:province":"Nordrhein-Westfalen",
    "wof:name":"Werner Uedelhofen Rechtsanwalt",
    "wof:placetype":"venue"
},
  "geometry": {"coordinates":[7.0823631287,51.1742362976],"type":"Point"}
}