{
  "type": "Feature",
  "properties": {
    "iso:country":"DE",
    "sg:address":"Riedstr. 1",
    "sg:city":"Gernsheim",
    "sg:phone":"+49 6258/52814",
    "sg:postcode":"64579",
    "sg:province":"Hessen",
    "wof:name":"Parf\u00fcmerie Offeringa",
    "wof:placetype":"venue"
},
  "geometry": {"coordinates":[8.48523,49.751747],"type":"Point"}
}