{
  "type": "Feature",
  "properties": {
    "iso:country":"DE",
    "sg:address":"Autenstr. 4",
    "sg:city":"Ditzingen",
    "sg:phone":"+49 7156/39284",
    "sg:postcode":"71254",
    "sg:province":"Baden-W\u00fcrttemberg",
    "wof:name":"Dillenburger",
    "wof:placetype":"venue"
},
  "geometry": {"coordinates":[9.0629053116,48.8265724182],"type":"Point"}
}