{
  "type": "Feature",
  "properties": {
    "iso:country":"DE",
    "sg:address":"Rudolf-Breitscheid-Str. 109a",
    "sg:city":"Angerm\u00fcnde",
    "sg:phone":"+49 3331/21062",
    "sg:postcode":"16278",
    "sg:province":"Brandenburg",
    "wof:name":"Spielothek",
    "wof:placetype":"venue"
},
  "geometry": {"coordinates":[13.9811754227,53.0122756958],"type":"Point"}
}