{
  "type": "Feature",
  "properties": {
    "iso:country":"DE",
    "sg:address":"Theilerstr. 12",
    "sg:city":"Bamberg",
    "sg:phone":"+49 951/46766",
    "sg:postcode":"96052",
    "sg:province":"Bayern",
    "wof:name":"Hans-ulrich Derra Heilpraktiker",
    "wof:placetype":"venue"
},
  "geometry": {"coordinates":[10.9192142487,49.9122581482],"type":"Point"}
}