{
  "type": "Feature",
  "properties": {
    "iso:country":"DE",
    "sg:address":"Hofstr. 17",
    "sg:city":"Heiningen",
    "sg:phone":"+49 7161/45675",
    "sg:postcode":"73092",
    "sg:province":"Baden-W\u00fcrttemberg",
    "wof:name":"Erwin Hirschmann",
    "wof:placetype":"venue"
},
  "geometry": {"coordinates":[9.646796,48.661972],"type":"Point"}
}