{
  "type": "Feature",
  "properties": {
    "iso:country":"DE",
    "sg:address":"Am Klosterberg 3",
    "sg:city":"Triefenstein",
    "sg:phone":"+49 9395/8551",
    "sg:postcode":"97855",
    "sg:province":"Bayern",
    "wof:name":"J\u00fcrgen Kauer",
    "wof:placetype":"venue"
},
  "geometry": {"coordinates":[9.599125,49.807072],"type":"Point"}
}