{
  "type": "Feature",
  "properties": {
    "iso:country":"DE",
    "sg:address":"S\u00fcdlohne",
    "sg:city":"Lohne",
    "sg:phone":"+49 4442/2008",
    "sg:postcode":"49393",
    "sg:province":"Niedersachsen",
    "wof:name":"M. Donner",
    "wof:placetype":"venue"
},
  "geometry": {"coordinates":[8.2457790375,52.6393203735],"type":"Point"}
}