{
  "type": "Feature",
  "properties": {
    "iso:country":"DE",
    "sg:address":"Strackestr. 25",
    "sg:city":"Brilon",
    "sg:phone":"+49 2961/4535",
    "sg:postcode":"59929",
    "sg:province":"Nordrhein-Westfalen",
    "wof:name":"I. Hillebrand",
    "wof:placetype":"venue"
},
  "geometry": {"coordinates":[8.5643796921,51.3948287964],"type":"Point"}
}