{
  "type": "Feature",
  "properties": {
    "iso:country":"DE",
    "sg:address":"Erlenbachstr. 17",
    "sg:city":"Reutlingen",
    "sg:phone":"+49 7121/601050",
    "sg:postcode":"72768",
    "sg:province":"Baden-W\u00fcrttemberg",
    "wof:name":"Gottwald Raiser Ingenieur",
    "wof:placetype":"venue"
},
  "geometry": {"coordinates":[9.202805,48.533611],"type":"Point"}
}