{
  "type": "Feature",
  "properties": {
    "iso:country":"DE",
    "sg:address":"Seel\u00fcbber Weg 3",
    "sg:city":"Prenzlau",
    "sg:phone":"+49 3984/2895",
    "sg:postcode":"17291",
    "sg:province":"Brandenburg",
    "wof:name":"R. Scheffel",
    "wof:placetype":"venue"
},
  "geometry": {"coordinates":[13.8779029846,53.3045043945],"type":"Point"}
}