{
  "type": "Feature",
  "properties": {
    "iso:country":"DE",
    "sg:address":"Felix-Wankel-Ring 3",
    "sg:city":"Lenting",
    "sg:postcode":"85101",
    "sg:province":"Bayern",
    "wof:name":"Willi Kauf Gmbh",
    "wof:placetype":"venue"
},
  "geometry": {"coordinates":[11.4685230255,48.8094825745],"type":"Point"}
}