{
  "type": "Feature",
  "properties": {
    "iso:country":"DE",
    "sg:address":"Borghorster Weg 22",
    "sg:city":"Horstmar",
    "sg:phone":"+49 2558/1272",
    "sg:postcode":"48612",
    "sg:province":"Nordrhein-Westfalen",
    "wof:name":"C. Frieling",
    "wof:placetype":"venue"
},
  "geometry": {"coordinates":[7.3269,52.079227],"type":"Point"}
}