{
  "type": "Feature",
  "properties": {
    "iso:country":"DE",
    "sg:address":"Landsberger Str. 102",
    "sg:city":"M\u00fcnchen",
    "sg:phone":"+49 89/505564",
    "sg:postcode":"80339",
    "sg:province":"Bayern",
    "wof:name":"A. Tommaselli",
    "wof:placetype":"venue"
},
  "geometry": {"coordinates":[11.5366458893,48.1401062012],"type":"Point"}
}