{
  "type": "Feature",
  "properties": {
    "iso:country":"DE",
    "sg:address":"Edigheimer Str. 30",
    "sg:city":"Ludwigshafen",
    "sg:phone":"+49 621/651179",
    "sg:postcode":"67069",
    "sg:province":"Rheinland-Pfalz",
    "wof:name":"Albert Osieka",
    "wof:placetype":"venue"
},
  "geometry": {"coordinates":[8.4035072327,49.5219230652],"type":"Point"}
}