{
  "type": "Feature",
  "properties": {
    "iso:country":"DE",
    "sg:address":"Auf der Stelle 9",
    "sg:city":"Sindelfingen",
    "sg:phone":"+49 7031/805959",
    "sg:postcode":"71067",
    "sg:province":"Baden-W\u00fcrttemberg",
    "wof:name":"Peter Steinh\u00fclber",
    "wof:placetype":"venue"
},
  "geometry": {"coordinates":[9.013926,48.726196],"type":"Point"}
}