{
  "type": "Feature",
  "properties": {
    "iso:country":"DE",
    "sg:address":"Humperdinckstr. 35",
    "sg:city":"Leverkusen",
    "sg:phone":"+49 214/53306",
    "sg:postcode":"51375",
    "sg:province":"Nordrhein-Westfalen",
    "wof:name":"Eberhard Foest Architekt",
    "wof:placetype":"venue"
},
  "geometry": {"coordinates":[7.049231,51.026165],"type":"Point"}
}