{
  "type": "Feature",
  "properties": {
    "iso:country":"DE",
    "sg:address":"Altenessener Str.374",
    "sg:city":"Essen",
    "sg:postcode":"45326",
    "sg:province":"Nordrhein-Westfalen",
    "wof:name":"Dr-krueger-frauenarzt",
    "wof:placetype":"venue"
},
  "geometry": {"coordinates":[7.008375,51.496273],"type":"Point"}
}