{
  "type": "Feature",
  "properties": {
    "iso:country":"DE",
    "sg:address":"Neddenh\u00fcsen 16",
    "sg:city":"Ganderkesee",
    "sg:phone":"+49 4222/93020",
    "sg:postcode":"27777",
    "sg:province":"Niedersachsen",
    "wof:name":"Akzent-hotel",
    "wof:placetype":"venue"
},
  "geometry": {"coordinates":[8.5519094467,53.0290260315],"type":"Point"}
}