{
  "type": "Feature",
  "properties": {
    "iso:country":"DE",
    "sg:address":"Walsroder Str. 8",
    "sg:city":"Soltau",
    "sg:phone":"+49 5191/12555",
    "sg:postcode":"29614",
    "sg:province":"Niedersachsen",
    "wof:name":"Medicus-apotheke Inh. Andreas Hagedorn",
    "wof:placetype":"venue"
},
  "geometry": {"coordinates":[9.83597,52.983349],"type":"Point"}
}