{
  "type": "Feature",
  "properties": {
    "iso:country":"DE",
    "sg:address":"Hauptstr. 5",
    "sg:city":"Kirchheim",
    "sg:phone":"+49 36200/60374",
    "sg:postcode":"99334",
    "sg:province":"Th\u00fcringen",
    "wof:name":"Bodo Nu\u00dfmann",
    "wof:placetype":"venue"
},
  "geometry": {"coordinates":[11.023798,50.881363],"type":"Point"}
}