{
  "type": "Feature",
  "properties": {
    "iso:country":"DE",
    "sg:address":"Haselsteiner Str. 14",
    "sg:city":"N\u00fcsttal",
    "sg:phone":"+49 6684/356",
    "sg:postcode":"36167",
    "sg:province":"Hessen",
    "wof:name":"Albert Hahner",
    "wof:placetype":"venue"
},
  "geometry": {"coordinates":[9.8583860397,50.6469535828],"type":"Point"}
}