{
  "type": "Feature",
  "properties": {
    "iso:country":"DE",
    "sg:address":"Sofienstr. 8",
    "sg:city":"Offenburg",
    "sg:phone":"+49 781",
    "sg:postcode":"77654",
    "sg:province":"Baden-W\u00fcrttemberg",
    "wof:name":"Interparla Sprachzentrum",
    "wof:placetype":"venue"
},
  "geometry": {"coordinates":[7.949606,48.474133],"type":"Point"}
}