{
  "type": "Feature",
  "properties": {
    "iso:country":"DE",
    "sg:address":"Schlo\u00dfplatz 1",
    "sg:city":"B\u00fctzow",
    "sg:phone":"+49 38461/52875",
    "sg:postcode":"18246",
    "sg:province":"Mecklenburg-Vorpommern",
    "wof:name":"Victoria Versicherungen",
    "wof:placetype":"venue"
},
  "geometry": {"coordinates":[11.9794569016,53.8478126526],"type":"Point"}
}