{
  "type": "Feature",
  "properties": {
    "iso:country":"DE",
    "sg:address":"Christophallee 23-25",
    "sg:city":"Pforzheim",
    "sg:phone":"+49 7231/355076",
    "sg:postcode":"75177",
    "sg:province":"Baden-W\u00fcrttemberg",
    "wof:name":"Dieter St\u00fctz Gmbh",
    "wof:placetype":"venue"
},
  "geometry": {"coordinates":[8.7064790726,48.8967819214],"type":"Point"}
}