{
  "type": "Feature",
  "properties": {
    "iso:country":"DE",
    "sg:address":"Auf der Mersch 29",
    "sg:city":"Bad Lippspringe",
    "sg:phone":"+49 5252/51677",
    "sg:postcode":"33175",
    "sg:province":"Nordrhein-Westfalen",
    "wof:name":"Reinhard M\u00fcller",
    "wof:placetype":"venue"
},
  "geometry": {"coordinates":[8.812078476,51.7739028931],"type":"Point"}
}