{
  "type": "Feature",
  "properties": {
    "iso:country":"DE",
    "sg:address":"Lindenstr. 50",
    "sg:city":"Ha\u00dfloch",
    "sg:phone":"+49 6324/4047",
    "sg:postcode":"67454",
    "sg:province":"Rheinland-Pfalz",
    "wof:name":"Pfalzhotel",
    "wof:placetype":"venue"
},
  "geometry": {"coordinates":[8.2660913467,49.3560028076],"type":"Point"}
}