{
  "type": "Feature",
  "properties": {
    "iso:country":"DE",
    "sg:address":"Wilhelm-Leuschner-Str. 5",
    "sg:city":"Hofheim",
    "sg:phone":"+49 6192/8538",
    "sg:postcode":"65719",
    "sg:province":"Hessen",
    "wof:name":"Bernd Kuhn",
    "wof:placetype":"venue"
},
  "geometry": {"coordinates":[8.4459152222,50.0959968567],"type":"Point"}
}