{
  "type": "Feature",
  "properties": {
    "iso:country":"DE",
    "sg:address":"Bahnhofstr. 15",
    "sg:city":"Sendenhorst",
    "sg:phone":"+49 2535/1213",
    "sg:postcode":"48324",
    "sg:province":"Nordrhein-Westfalen",
    "wof:name":"Petzoldt",
    "wof:placetype":"venue"
},
  "geometry": {"coordinates":[7.73585,51.868999],"type":"Point"}
}