{
  "type": "Feature",
  "properties": {
    "iso:country":"DE",
    "sg:address":"Bornh\u00f6vedstr. 10-12",
    "sg:city":"Schwerin",
    "sg:postcode":"19055",
    "sg:province":"Mecklenburg-Vorpommern",
    "wof:name":"Numen Bau Gmbh",
    "wof:placetype":"venue"
},
  "geometry": {"coordinates":[11.422808,53.633572],"type":"Point"}
}