{
  "type": "Feature",
  "properties": {
    "iso:country":"DE",
    "sg:address":"Charles-Darwin-Ring 4",
    "sg:city":"Rostock",
    "sg:phone":"+49 381/2070210",
    "sg:postcode":"18059",
    "sg:province":"Mecklenburg-Vorpommern",
    "wof:name":"Hanseatische Bautenschutz Gmbh",
    "wof:placetype":"venue"
},
  "geometry": {"coordinates":[12.119559,54.061901],"type":"Point"}
}