{
  "type": "Feature",
  "properties": {
    "iso:country":"DE",
    "sg:address":"Elsbethstr. 34",
    "sg:city":"Leipzig",
    "sg:phone":"+49 341/5900670",
    "sg:postcode":"04155",
    "sg:province":"Sachsen",
    "wof:name":"Gbs-reisen Gmbh",
    "wof:placetype":"venue"
},
  "geometry": {"coordinates":[12.363404274,51.3638153076],"type":"Point"}
}