{
  "type": "Feature",
  "properties": {
    "iso:country":"DE",
    "sg:address":"Nibelungenstr. 17",
    "sg:city":"Gro\u00dfwallstadt",
    "sg:phone":"+49 6022/24606",
    "sg:postcode":"63868",
    "sg:province":"Bayern",
    "wof:name":"Reinhold Flittner",
    "wof:placetype":"venue"
},
  "geometry": {"coordinates":[9.1619253159,49.8846168518],"type":"Point"}
}