{
  "type": "Feature",
  "properties": {
    "iso:country":"DE",
    "sg:address":"Seegefelder Str. 128 d",
    "sg:city":"Berlin",
    "sg:phone":"+49 30/3722427",
    "sg:postcode":"13583",
    "sg:province":"Berlin",
    "wof:name":"Horst Hoffmann",
    "wof:placetype":"venue"
},
  "geometry": {"coordinates":[13.1802787781,52.5389060974],"type":"Point"}
}