{
  "type": "Feature",
  "properties": {
    "iso:country":"DE",
    "sg:address":"Kalkarer Str. 37",
    "sg:city":"Kleve",
    "sg:phone":"+49 2821/20610",
    "sg:postcode":"47533",
    "sg:province":"Nordrhein-Westfalen",
    "wof:name":"Josef Bloemen",
    "wof:placetype":"venue"
},
  "geometry": {"coordinates":[6.146867,51.785831],"type":"Point"}
}