{
  "type": "Feature",
  "properties": {
    "iso:country":"DE",
    "sg:address":"L\u00f6nsstr. 18",
    "sg:city":"Bad Rodach",
    "sg:phone":"+49 9564/1063",
    "sg:postcode":"96476",
    "sg:province":"Bayern",
    "wof:name":"Reiner Hochberger Architekt",
    "wof:placetype":"venue"
},
  "geometry": {"coordinates":[10.789954,50.341961],"type":"Point"}
}