{
  "type": "Feature",
  "properties": {
    "iso:country":"DE",
    "sg:address":"Melkberg 14",
    "sg:city":"L\u00fcneburg",
    "sg:phone":"+49 4131/62373",
    "sg:postcode":"21339",
    "sg:province":"Niedersachsen",
    "wof:name":"D. Klinzmann",
    "wof:placetype":"venue"
},
  "geometry": {"coordinates":[10.388008,53.273098],"type":"Point"}
}