{
  "type": "Feature",
  "properties": {
    "iso:country":"DE",
    "sg:address":"Paradiesbuck 13",
    "sg:city":"Malsburg-Marzell",
    "sg:phone":"+49 7626/7677",
    "sg:postcode":"79429",
    "sg:province":"Baden-W\u00fcrttemberg",
    "wof:name":"Ev. Pfarramt Malsburg",
    "wof:placetype":"venue"
},
  "geometry": {"coordinates":[7.7095241547,47.736240387],"type":"Point"}
}