{
  "type": "Feature",
  "properties": {
    "iso:country":"DE",
    "sg:address":"Schmiedstr. 14",
    "sg:city":"Ellwangen",
    "sg:phone":"+49 7961/2250",
    "sg:postcode":"73479",
    "sg:province":"Baden-W\u00fcrttemberg",
    "wof:name":"Otto Hauber",
    "wof:placetype":"venue"
},
  "geometry": {"coordinates":[10.130203,48.961674],"type":"Point"}
}