{
  "type": "Feature",
  "properties": {
    "iso:country":"DE",
    "sg:address":"Von-Stuben-Str. 14",
    "sg:city":"Oberg\u00fcnzburg",
    "sg:phone":"+49 8372/7510",
    "sg:postcode":"87634",
    "sg:province":"Bayern",
    "wof:name":"V. Michel Immobilienmakler",
    "wof:placetype":"venue"
},
  "geometry": {"coordinates":[10.4226331711,47.8534126282],"type":"Point"}
}