{
  "type": "Feature",
  "properties": {
    "iso:country":"DE",
    "sg:address":"Abtweilerstr. 31",
    "sg:city":"Lauschied",
    "sg:phone":"+49 6753/2797",
    "sg:postcode":"55568",
    "sg:province":"Rheinland-Pfalz",
    "wof:name":"Nowak Immobilienmakler",
    "wof:placetype":"venue"
},
  "geometry": {"coordinates":[7.6207900047,49.7428474426],"type":"Point"}
}