{
  "type": "Feature",
  "properties": {
    "iso:country":"DE",
    "sg:address":"Schlutterweg 68",
    "sg:city":"Delmenhorst",
    "sg:phone":"+49 4221/20970",
    "sg:postcode":"27755",
    "sg:province":"Niedersachsen",
    "wof:name":"Walter Hohnholt Tischlerei Bauelemente",
    "wof:placetype":"venue"
},
  "geometry": {"coordinates":[8.615597,53.031441],"type":"Point"}
}