{
  "type": "Feature",
  "properties": {
    "iso:country":"DE",
    "sg:address":"Herschberger Str. 4",
    "sg:city":"Saalstadt",
    "sg:phone":"+49 6375/367",
    "sg:postcode":"66919",
    "sg:province":"Rheinland-Pfalz",
    "wof:name":"Walter Stephan",
    "wof:placetype":"venue"
},
  "geometry": {"coordinates":[7.552859,49.322506],"type":"Point"}
}