{
  "type": "Feature",
  "properties": {
    "iso:country":"DE",
    "sg:address":"Luisenstr. 2",
    "sg:city":"Kuppenheim",
    "sg:phone":"+49 7222/47682",
    "sg:postcode":"76456",
    "sg:province":"Baden-W\u00fcrttemberg",
    "wof:name":"Stadt-apotheke Apothekerin Eva Ludwig E. Kfr.",
    "wof:placetype":"venue"
},
  "geometry": {"coordinates":[8.254963,48.830418],"type":"Point"}
}