{
  "type": "Feature",
  "properties": {
    "iso:country":"DE",
    "sg:address":"Temdestr. 4",
    "sg:city":"Detmold",
    "sg:phone":"+49 5231/65174",
    "sg:postcode":"32756",
    "sg:province":"Nordrhein-Westfalen",
    "wof:name":"Witra-wieneke Transport- Und F\u00f6rdertechnik",
    "wof:placetype":"venue"
},
  "geometry": {"coordinates":[8.866831,51.940552],"type":"Point"}
}