{
  "type": "Feature",
  "properties": {
    "iso:country":"DE",
    "sg:address":"Kreuzstr. 27",
    "sg:city":"Wuppertal",
    "sg:phone":"+49 202/523849",
    "sg:postcode":"42277",
    "sg:province":"Nordrhein-Westfalen",
    "wof:name":"Baugesch\u00e4ft Egon Korkowski Inh. Detlef Baum",
    "wof:placetype":"venue"
},
  "geometry": {"coordinates":[7.221035,51.286533],"type":"Point"}
}