{
  "type": "Feature",
  "properties": {
    "iso:country":"DE",
    "sg:address":"Hermannstr. 23",
    "sg:city":"Koblenz",
    "sg:phone":"+49 261/75969",
    "sg:postcode":"56076",
    "sg:province":"Rheinland-Pfalz",
    "wof:name":"Frank Reinhart M\u00fcller Architekt",
    "wof:placetype":"venue"
},
  "geometry": {"coordinates":[7.604336,50.344101],"type":"Point"}
}