{
  "type": "Feature",
  "properties": {
    "iso:country":"DE",
    "sg:address":"Br\u00fcckenstr. 7",
    "sg:city":"Kell",
    "sg:phone":"+49 6589/1041",
    "sg:postcode":"54427",
    "sg:province":"Rheinland-Pfalz",
    "wof:name":"Christoph Jungblut",
    "wof:placetype":"venue"
},
  "geometry": {"coordinates":[6.822054863,49.6346855164],"type":"Point"}
}