{
  "type": "Feature",
  "properties": {
    "iso:country":"DE",
    "sg:address":"In der Au 5",
    "sg:city":"Rottweil",
    "sg:phone":"+49 741/4720",
    "sg:postcode":"78628",
    "sg:province":"Baden-W\u00fcrttemberg",
    "wof:name":"Stadtwerke Rottweil",
    "wof:placetype":"venue"
},
  "geometry": {"coordinates":[8.633515,48.166897],"type":"Point"}
}