{
  "type": "Feature",
  "properties": {
    "iso:country":"DE",
    "sg:address":"Von-der-Tann-Str. 25",
    "sg:city":"Kiel",
    "sg:phone":"+49 431/7397710",
    "sg:postcode":"24114",
    "sg:province":"Schleswig-Holstein",
    "wof:name":"Thorsten Fahrahwarau",
    "wof:placetype":"venue"
},
  "geometry": {"coordinates":[10.1238098145,54.3153953552],"type":"Point"}
}