{
  "type": "Feature",
  "properties": {
    "iso:country":"DE",
    "sg:address":"Hessestr. 18",
    "sg:city":"N\u00fcrtingen",
    "sg:phone":"+49 7022/33250",
    "sg:postcode":"72622",
    "sg:province":"Baden-W\u00fcrttemberg",
    "wof:name":"D. Rothaug",
    "wof:placetype":"venue"
},
  "geometry": {"coordinates":[9.3327102661,48.624130249],"type":"Point"}
}