{
  "type": "Feature",
  "properties": {
    "iso:country":"DE",
    "sg:address":"Oberer Hornbachstaden 2",
    "sg:city":"Zweibr\u00fccken",
    "sg:phone":"+49 6332/12255",
    "sg:postcode":"66482",
    "sg:province":"Rheinland-Pfalz",
    "wof:name":"Dieter Ott",
    "wof:placetype":"venue"
},
  "geometry": {"coordinates":[7.357484,49.243725],"type":"Point"}
}