{
  "type": "Feature",
  "properties": {
    "iso:country":"DE",
    "sg:address":"Niederfeldstr. 13",
    "sg:city":"Bielefeld",
    "sg:phone":"+49 521/875856",
    "sg:postcode":"33611",
    "sg:province":"Nordrhein-Westfalen",
    "wof:name":"Heinr. Denker",
    "wof:placetype":"venue"
},
  "geometry": {"coordinates":[8.552315712,52.0539703369],"type":"Point"}
}