{
  "type": "Feature",
  "properties": {
    "iso:country":"DE",
    "sg:address":"Kronprinz-Rupprecht-Str. 1",
    "sg:city":"F\u00fcrstenfeldbruck",
    "sg:phone":"+49 8141/59558",
    "sg:postcode":"82256",
    "sg:province":"Bayern",
    "wof:name":"Karlheinz Graff Anlageberater",
    "wof:placetype":"venue"
},
  "geometry": {"coordinates":[11.2515258789,48.1869087219],"type":"Point"}
}