{
  "type": "Feature",
  "properties": {
    "iso:country":"DE",
    "sg:address":"Panoramastr. 46",
    "sg:city":"Bietigheim Bissingen",
    "sg:phone":"+49 7141/1485920",
    "sg:postcode":"74321",
    "sg:province":"Baden-W\u00fcrttemberg",
    "wof:name":"Kreissparkasse Ludwigsburg",
    "wof:placetype":"venue"
},
  "geometry": {"coordinates":[9.191875,48.894176],"type":"Point"}
}