{
  "type": "Feature",
  "properties": {
    "iso:country":"DE",
    "sg:address":"Bergmannstr. 19",
    "sg:city":"Leer",
    "sg:phone":"+49 491/4425",
    "sg:postcode":"26789",
    "sg:province":"Niedersachsen",
    "wof:name":"Jan Van Lessen Notar Und Rechtsanw\u00e4lte",
    "wof:placetype":"venue"
},
  "geometry": {"coordinates":[7.456193924,53.2315330505],"type":"Point"}
}