{
  "type": "Feature",
  "properties": {
    "iso:country":"DE",
    "sg:address":"Buchholzer Chaussee 1a",
    "sg:city":"F\u00fcrstenwalde",
    "sg:phone":"+49 3361/349968",
    "sg:postcode":"15517",
    "sg:province":"Brandenburg",
    "wof:name":"Flugplatz Betriebsgesellschaft F\u00fcrstenwalde Mbh",
    "wof:placetype":"venue"
},
  "geometry": {"coordinates":[14.0927753448,52.3935127258],"type":"Point"}
}