{
  "type": "Feature",
  "properties": {
    "iso:country":"DE",
    "sg:address":"K\u00f6nigstr. 25",
    "sg:city":"Germersheim",
    "sg:phone":"+49 4972/741061",
    "sg:postcode":"76726",
    "sg:province":"Rheinland-Pfalz",
    "wof:name":"S\u00fcdpf\u00e4lzer Volksbank Raiffeisenb.eg",
    "wof:placetype":"venue"
},
  "geometry": {"coordinates":[8.374246,49.217514],"type":"Point"}
}