{
  "type": "Feature",
  "properties": {
    "iso:country":"DE",
    "sg:address":"Fliederstr. 14",
    "sg:city":"Achberg",
    "sg:phone":"+49 8380/328",
    "sg:postcode":"88147",
    "sg:province":"Baden-W\u00fcrttemberg",
    "wof:name":"Lauber",
    "wof:placetype":"venue"
},
  "geometry": {"coordinates":[9.716756,47.615093],"type":"Point"}
}