{
  "type": "Feature",
  "properties": {
    "iso:country":"DE",
    "sg:address":"K\u00f6lner Str. 27",
    "sg:city":"Leverkusen",
    "sg:phone":"+49 2171/45509",
    "sg:postcode":"51379",
    "sg:province":"Nordrhein-Westfalen",
    "wof:name":"Goldkopf-parf\u00fcmerie Dr. Lennartz Gmbh",
    "wof:placetype":"venue"
},
  "geometry": {"coordinates":[7.003842,51.065887],"type":"Point"}
}