{
  "type": "Feature",
  "properties": {
    "iso:country":"DE",
    "sg:address":"Amtsweg 3",
    "sg:city":"Gronau",
    "sg:phone":"+49 2565/93420",
    "sg:postcode":"48599",
    "sg:province":"Nordrhein-Westfalen",
    "wof:name":"S\u00f6bbeke Und Kuhn Rechtsanw\u00e4ltinnen Und Notarin",
    "wof:placetype":"venue"
},
  "geometry": {"coordinates":[7.0416440964,52.1789894104],"type":"Point"}
}