{
  "type": "Feature",
  "properties": {
    "iso:country":"DE",
    "sg:address":"Stendaler Str. 68",
    "sg:city":"Berlin",
    "sg:phone":"+49 30/9981737",
    "sg:postcode":"12627",
    "sg:province":"Berlin",
    "wof:name":"Hoffmann",
    "wof:placetype":"venue"
},
  "geometry": {"coordinates":[13.6145000458,52.5371284485],"type":"Point"}
}