{
  "type": "Feature",
  "properties": {
    "iso:country":"DE",
    "sg:address":"Pfannenstiel 29",
    "sg:city":"Ravensburg",
    "sg:phone":"+49 751/36950",
    "sg:postcode":"88214",
    "sg:province":"Baden-W\u00fcrttemberg",
    "wof:name":"T\u00dcv S\u00fcdwest",
    "wof:placetype":"venue"
},
  "geometry": {"coordinates":[9.6038751602,47.7816162109],"type":"Point"}
}