{
  "type": "Feature",
  "properties": {
    "iso:country":"DE",
    "sg:address":"Hutfilterstr. 6-8",
    "sg:city":"Bremen",
    "sg:postcode":"28195",
    "sg:province":"Bremen",
    "wof:name":"Global-concept Beratungs- Marketing- Und Vertriebs Gmbh",
    "wof:placetype":"venue"
},
  "geometry": {"coordinates":[8.8022623062,53.0784645081],"type":"Point"}
}