{
  "type": "Feature",
  "properties": {
    "iso:country":"DE",
    "sg:address":"Weserstr. 27",
    "sg:city":"Verden",
    "sg:phone":"+49 4231/5500",
    "sg:postcode":"27283",
    "sg:province":"Niedersachsen",
    "wof:name":"Taxi-k\u00f6hler",
    "wof:placetype":"venue"
},
  "geometry": {"coordinates":[9.2251577377,52.9300422668],"type":"Point"}
}