{
  "type": "Feature",
  "properties": {
    "iso:country":"DE",
    "sg:address":"Koloniestr. 46",
    "sg:city":"Moormerland",
    "sg:phone":"+49 4954/4706",
    "sg:postcode":"26802",
    "sg:province":"Niedersachsen",
    "wof:name":"Karl Weber Seeschiffahrt-u.",
    "wof:placetype":"venue"
},
  "geometry": {"coordinates":[7.491907,53.29491],"type":"Point"}
}