{
  "type": "Feature",
  "properties": {
    "iso:country":"DE",
    "sg:address":"An der Chaussee 9",
    "sg:city":"Aitrach",
    "sg:postcode":"88319",
    "sg:province":"Baden-W\u00fcrttemberg",
    "wof:name":"Dr. Aypar Gmbh",
    "wof:placetype":"venue"
},
  "geometry": {"coordinates":[10.094116,47.929249],"type":"Point"}
}