{
  "type": "Feature",
  "properties": {
    "iso:country":"DE",
    "sg:address":"Neustr. 15",
    "sg:city":"Trier",
    "sg:phone":"+49 651/9941800",
    "sg:postcode":"54290",
    "sg:province":"Rheinland-Pfalz",
    "wof:name":"Restaurant Vadis",
    "wof:placetype":"venue"
},
  "geometry": {"coordinates":[6.6389169693,49.75258255],"type":"Point"}
}