{
  "type": "Feature",
  "properties": {
    "iso:country":"DE",
    "sg:address":"Am Kiesberg 3",
    "sg:city":"Pirna",
    "sg:phone":"+49 3501/523939",
    "sg:postcode":"01796",
    "sg:province":"Sachsen",
    "wof:name":"E. Kabus",
    "wof:placetype":"venue"
},
  "geometry": {"coordinates":[13.940864563,50.9819221497],"type":"Point"}
}