{
  "type": "Feature",
  "properties": {
    "iso:country":"DE",
    "sg:address":"Hauptstr. 4",
    "sg:city":"Ismaning",
    "sg:phone":"+49 89/9613555",
    "sg:postcode":"85737",
    "sg:province":"Bayern",
    "wof:name":"Baptista",
    "wof:placetype":"venue"
},
  "geometry": {"coordinates":[11.6740751266,48.2269248962],"type":"Point"}
}