{
  "type": "Feature",
  "properties": {
    "iso:country":"DE",
    "sg:address":"Erlenstr. 18",
    "sg:city":"Taufkirchen",
    "sg:phone":"+49 8084/1673",
    "sg:postcode":"84416",
    "sg:province":"Bayern",
    "wof:name":"J. Samhuber Gmbh",
    "wof:placetype":"venue"
},
  "geometry": {"coordinates":[12.1792201996,48.3422203064],"type":"Point"}
}