{
  "type": "Feature",
  "properties": {
    "iso:country":"DE",
    "sg:address":"Harkortstr. 14",
    "sg:city":"Sprockh\u00f6vel",
    "sg:phone":"+49 2339/12050",
    "sg:postcode":"45549",
    "sg:province":"Nordrhein-Westfalen",
    "wof:name":"Vpf-veredelungsgesellschaft Mbh F\u00fcr Papiere Und",
    "wof:placetype":"venue"
},
  "geometry": {"coordinates":[7.2809019089,51.3195152283],"type":"Point"}
}