{
  "type": "Feature",
  "properties": {
    "iso:country":"DE",
    "sg:address":"Zeppelinring 40",
    "sg:city":"Kiel",
    "sg:phone":"+49 431/684416",
    "sg:postcode":"24146",
    "sg:province":"Schleswig-Holstein",
    "wof:name":"Brug Gmbh",
    "wof:placetype":"venue"
},
  "geometry": {"coordinates":[10.2036867142,54.2825584412],"type":"Point"}
}