{
  "type": "Feature",
  "properties": {
    "iso:country":"DE",
    "sg:address":"Klarenstrecker Damm 7",
    "sg:city":"Stade",
    "sg:phone":"+49 4141/3755",
    "sg:postcode":"21684",
    "sg:province":"Niedersachsen",
    "wof:name":"Rieger Verwalt.-gmbh Bautenschutz U. Betonsanierung",
    "wof:placetype":"venue"
},
  "geometry": {"coordinates":[9.4929704666,53.5809440613],"type":"Point"}
}