{
  "type": "Feature",
  "properties": {
    "iso:country":"DE",
    "sg:address":"Gro\u00dfr\u00f6hrsdorfer Str. 18",
    "sg:city":"Dresden",
    "sg:phone":"+49 351/8809815",
    "sg:postcode":"01109",
    "sg:province":"Sachsen",
    "wof:name":"Lutz Eilers",
    "wof:placetype":"venue"
},
  "geometry": {"coordinates":[13.7276277542,51.1169548035],"type":"Point"}
}