{
  "type": "Feature",
  "properties": {
    "iso:country":"DE",
    "sg:address":"Steinfeld 10",
    "sg:city":"Ilfeld",
    "sg:phone":"+49 36331/46673",
    "sg:postcode":"99768",
    "sg:province":"Th\u00fcringen",
    "wof:name":"Land- Und Forst Wegebau Gmbh",
    "wof:placetype":"venue"
},
  "geometry": {"coordinates":[10.78327,51.574116],"type":"Point"}
}