{
  "type": "Feature",
  "properties": {
    "iso:country":"DE",
    "sg:address":"Bahnhofstr. 13",
    "sg:city":"Hilter",
    "sg:phone":"+49 5424/37400",
    "sg:postcode":"49176",
    "sg:province":"Niedersachsen",
    "wof:name":"Plastoform Gmbh",
    "wof:placetype":"venue"
},
  "geometry": {"coordinates":[8.1458797455,52.1392211914],"type":"Point"}
}