{
  "type": "Feature",
  "properties": {
    "iso:country":"DE",
    "sg:address":"Talstr. 20",
    "sg:city":"Schwarzenberg",
    "sg:phone":"+49 3774",
    "sg:postcode":"08340",
    "sg:province":"Sachsen",
    "wof:name":"Dds Stra\u00dfen- Und Tiefbau Gmbh",
    "wof:placetype":"venue"
},
  "geometry": {"coordinates":[12.76197,50.55685],"type":"Point"}
}