{
  "type": "Feature",
  "properties": {
    "iso:country":"DE",
    "sg:address":"Mittelstr. 3",
    "sg:city":"Nauen",
    "sg:phone":"+49 3321/454409",
    "sg:postcode":"14641",
    "sg:province":"Brandenburg",
    "wof:name":"Pizzeria-cafeteria Marko Polo",
    "wof:placetype":"venue"
},
  "geometry": {"coordinates":[12.8764009476,52.6055679321],"type":"Point"}
}