{
  "type": "Feature",
  "properties": {
    "iso:country":"DE",
    "sg:address":"Rotes Meer 12",
    "sg:city":"Z\u00f6rbig",
    "sg:phone":"+49 34956/20326",
    "sg:postcode":"06780",
    "sg:province":"Sachsen-Anhalt",
    "wof:name":"Zum Alten Bergmann Inh. J\u00f6rg Korus",
    "wof:placetype":"venue"
},
  "geometry": {"coordinates":[12.1156406403,51.6269798279],"type":"Point"}
}