{
  "type": "Feature",
  "properties": {
    "iso:country":"DE",
    "sg:address":"Luchstr. 11",
    "sg:city":"Fehrbellin",
    "sg:phone":"+49 33932/9850",
    "sg:postcode":"16833",
    "sg:province":"Brandenburg",
    "wof:name":"New Tex - Bauelemente Und Sonnenschutzanlagen Gmbh",
    "wof:placetype":"venue"
},
  "geometry": {"coordinates":[12.784814,52.816414],"type":"Point"}
}