{
  "type": "Feature",
  "properties": {
    "iso:country":"DE",
    "sg:address":"Eichenstr. 11",
    "sg:city":"Wuppertal",
    "sg:phone":"+49 202/556143",
    "sg:postcode":"42283",
    "sg:province":"Nordrhein-Westfalen",
    "wof:name":"F. J. Brandau Kunstmaler",
    "wof:placetype":"venue"
},
  "geometry": {"coordinates":[7.182443,51.269539],"type":"Point"}
}