{
  "type": "Feature",
  "properties": {
    "iso:country":"DE",
    "sg:address":"Adalbert-Stifter-Str. 36",
    "sg:city":"V\u00f6hringen",
    "sg:postcode":"89269",
    "sg:province":"Bayern",
    "wof:name":"Aldi Gmbh & Co. Kg",
    "wof:placetype":"venue"
},
  "geometry": {"coordinates":[10.0787572861,48.2908706665],"type":"Point"}
}