{
  "type": "Feature",
  "properties": {
    "iso:country":"DE",
    "sg:address":"Hohlweg 11",
    "sg:city":"Bad Soden",
    "sg:phone":"+49 6174/21162",
    "sg:postcode":"65812",
    "sg:province":"Hessen",
    "wof:name":"P. Gottschalk",
    "wof:placetype":"venue"
},
  "geometry": {"coordinates":[8.46648,50.157494],"type":"Point"}
}