{
  "type": "Feature",
  "properties": {
    "iso:country":"DE",
    "sg:address":"Talstr. 69 C",
    "sg:city":"Stuttgart",
    "sg:phone":"+49 711/282021",
    "sg:postcode":"70188",
    "sg:province":"Baden-W\u00fcrttemberg",
    "wof:name":"Bgg-christliche Medien Gmbh",
    "wof:placetype":"venue"
},
  "geometry": {"coordinates":[9.2149925232,48.7854995728],"type":"Point"}
}