{
  "type": "Feature",
  "properties": {
    "iso:country":"DE",
    "sg:address":"Otto-Brenner-Str. 17a",
    "sg:city":"Hannover",
    "sg:phone":"+49 511/1316501",
    "sg:postcode":"30159",
    "sg:province":"Niedersachsen",
    "wof:name":"Fix-druck Am Steintor Gmbh",
    "wof:placetype":"venue"
},
  "geometry": {"coordinates":[9.7280569077,52.3776321411],"type":"Point"}
}