{
  "type": "Feature",
  "properties": {
    "iso:country":"DE",
    "sg:address":"Alter Markt 48",
    "sg:city":"M\u00f6nchengladbach",
    "sg:phone":"+49 2161/21717",
    "sg:postcode":"41061",
    "sg:province":"Nordrhein-Westfalen",
    "wof:name":"Alma 48 Gastst\u00e4tten Gmbh",
    "wof:placetype":"venue"
},
  "geometry": {"coordinates":[6.4317140579,51.1946105957],"type":"Point"}
}