{
  "type": "Feature",
  "properties": {
    "iso:country":"DE",
    "sg:address":"Kirchstr. 1",
    "sg:city":"Sottrum",
    "sg:phone":"+49 4264/2933",
    "sg:postcode":"27367",
    "sg:province":"Niedersachsen",
    "wof:name":"Heinrich Fricke",
    "wof:placetype":"venue"
},
  "geometry": {"coordinates":[9.230208,53.1161],"type":"Point"}
}