{
  "type": "Feature",
  "properties": {
    "iso:country":"DE",
    "sg:address":"Winnberger Weg 2",
    "sg:city":"Deining",
    "sg:phone":"+49 9184/976",
    "sg:postcode":"92364",
    "sg:province":"Bayern",
    "wof:name":"Baugesch\u00e4ft Lukas Gmbh",
    "wof:placetype":"venue"
},
  "geometry": {"coordinates":[11.507093,49.231876],"type":"Point"}
}