{
  "type": "Feature",
  "properties": {
    "iso:country":"DE",
    "sg:address":"54451",
    "sg:city":"Irsch",
    "sg:postcode":"54451",
    "sg:province":"Rheinland-Pfalz",
    "wof:name":"Raiffeisenbank Irsch-greimerath-zerf Eg",
    "wof:placetype":"venue"
},
  "geometry": {"coordinates":[6.59314,49.603661],"type":"Point"}
}