{
  "type": "Feature",
  "properties": {
    "iso:country":"DE",
    "sg:address":"Gartenweg 2",
    "sg:city":"Brauneberg",
    "sg:postcode":"54472",
    "sg:province":"Rheinland-Pfalz",
    "wof:name":"H. Und H. Conrad Briefmarkenversand",
    "wof:placetype":"venue"
},
  "geometry": {"coordinates":[6.9893398285,49.9090194702],"type":"Point"}
}