{
  "type": "Feature",
  "properties": {
    "iso:country":"DE",
    "sg:address":"Hohe Str. 9",
    "sg:city":"Z\u00f6rbig",
    "sg:phone":"+49 34956/25122",
    "sg:postcode":"06780",
    "sg:province":"Sachsen-Anhalt",
    "wof:name":"Joachim Neubert",
    "wof:placetype":"venue"
},
  "geometry": {"coordinates":[12.1211309433,51.6278190613],"type":"Point"}
}