{
  "type": "Feature",
  "properties": {
    "iso:country":"DE",
    "sg:address":"Alte Hasel\u00fcnner Str. 8",
    "sg:city":"Lingen",
    "sg:phone":"+49 591/54141",
    "sg:postcode":"49808",
    "sg:province":"Niedersachsen",
    "wof:name":"Elternverein Restrisiko Emsland E. V.",
    "wof:placetype":"venue"
},
  "geometry": {"coordinates":[7.3242797852,52.5240745544],"type":"Point"}
}