{
  "type": "Feature",
  "properties": {
    "iso:country":"DE",
    "sg:address":"Werner-Seelenbinder-Str. 13",
    "sg:city":"Chemnitz",
    "sg:phone":"+49 371/429206",
    "sg:postcode":"09120",
    "sg:province":"Sachsen",
    "wof:name":"Saxonia Service- Und Verwaltungsges. Mbh",
    "wof:placetype":"venue"
},
  "geometry": {"coordinates":[12.924701,50.806179],"type":"Point"}
}