{
  "type": "Feature",
  "properties": {
    "iso:country":"DE",
    "sg:address":"Schullendamm 13",
    "sg:city":"Meppen",
    "sg:phone":"+49 5931/85200",
    "sg:postcode":"49716",
    "sg:province":"Niedersachsen",
    "wof:name":"J. Altmeppen",
    "wof:placetype":"venue"
},
  "geometry": {"coordinates":[7.2848801613,52.6935653687],"type":"Point"}
}