{
  "type": "Feature",
  "properties": {
    "iso:country":"DE",
    "sg:address":"Markenweg 35",
    "sg:city":"Neuwied",
    "sg:phone":"+49 2622/80751",
    "sg:postcode":"56566",
    "sg:province":"Rheinland-Pfalz",
    "wof:name":"Fries",
    "wof:placetype":"venue"
},
  "geometry": {"coordinates":[7.5395460129,50.4544181824],"type":"Point"}
}