{
  "type": "Feature",
  "properties": {
    "iso:country":"DE",
    "sg:address":"Am Brink 2",
    "sg:city":"Extertal",
    "sg:phone":"+49 5262/701",
    "sg:postcode":"32699",
    "sg:province":"Nordrhein-Westfalen",
    "wof:name":"Heinz-peter Meier",
    "wof:placetype":"venue"
},
  "geometry": {"coordinates":[9.089789,52.105721],"type":"Point"}
}