{
  "type": "Feature",
  "properties": {
    "iso:country":"DE",
    "sg:address":"Odenthaler Str. 2",
    "sg:city":"K\u00fcrten",
    "sg:phone":"+49 2207/6491",
    "sg:postcode":"51515",
    "sg:province":"Nordrhein-Westfalen",
    "wof:name":"Altenheim Armerding",
    "wof:placetype":"venue"
},
  "geometry": {"coordinates":[7.206576,51.038876],"type":"Point"}
}