{
  "type": "Feature",
  "properties": {
    "iso:country":"DE",
    "sg:address":"Am Eisernen Kreuz 23",
    "sg:city":"Nideggen",
    "sg:phone":"+49 2427/901444",
    "sg:postcode":"52385",
    "sg:province":"Nordrhein-Westfalen",
    "wof:name":"Ms Prokon Gmbh",
    "wof:placetype":"venue"
},
  "geometry": {"coordinates":[6.4887261391,50.692817688],"type":"Point"}
}