{
  "type": "Feature",
  "properties": {
    "iso:country":"DE",
    "sg:address":"Hauptstr. 65",
    "sg:city":"Stolzenau",
    "sg:phone":"+49 5765/1602",
    "sg:postcode":"31592",
    "sg:province":"Niedersachsen",
    "wof:name":"Wilhelm M\u00fcller",
    "wof:placetype":"venue"
},
  "geometry": {"coordinates":[8.975826,52.50032],"type":"Point"}
}