{
  "type": "Feature",
  "properties": {
    "iso:country":"DE",
    "sg:address":"Hauptstr. 86",
    "sg:city":"Neustadt",
    "sg:phone":"+49 6321/30910",
    "sg:postcode":"67433",
    "sg:province":"Rheinland-Pfalz",
    "wof:name":"Mayer Gmbh",
    "wof:placetype":"venue"
},
  "geometry": {"coordinates":[8.1370201111,49.3536338806],"type":"Point"}
}