{
  "type": "Feature",
  "properties": {
    "iso:country":"DE",
    "sg:address":"Krumme Str. 5",
    "sg:city":"Hedersleben",
    "sg:phone":"+49 39481/81606",
    "sg:postcode":"06458",
    "sg:province":"Sachsen-Anhalt",
    "wof:name":"H. Taft",
    "wof:placetype":"venue"
},
  "geometry": {"coordinates":[11.2458143234,51.8646392822],"type":"Point"}
}