{
  "type": "Feature",
  "properties": {
    "iso:country":"DE",
    "sg:address":"Robert-Koch-Str. 1",
    "sg:city":"Landshut",
    "sg:phone":"+49 871/6980",
    "sg:postcode":"84034",
    "sg:province":"Bayern",
    "wof:name":"Krankenhausvollapotheke Des St\u00e4dt. Krankenhauses",
    "wof:placetype":"venue"
},
  "geometry": {"coordinates":[12.137593,48.538113],"type":"Point"}
}