{
  "type": "Feature",
  "properties": {
    "iso:country":"DE",
    "sg:address":"Neustr. 8",
    "sg:city":"Euskirchen",
    "sg:phone":"+49 2251/72911",
    "sg:postcode":"53879",
    "sg:province":"Nordrhein-Westfalen",
    "wof:name":"Dm-drogerie Markt Gmbh & Co. Kg",
    "wof:placetype":"venue"
},
  "geometry": {"coordinates":[6.78876,50.660789],"type":"Point"}
}