{
  "type": "Feature",
  "properties": {
    "iso:country":"DE",
    "sg:address":"Zorger Str 2",
    "sg:city":"Walkenried",
    "sg:phone":"+49 5525/96700",
    "sg:postcode":"37445",
    "sg:province":"Niedersachsen",
    "wof:name":"Paul Will & Co Kg",
    "wof:placetype":"venue"
},
  "geometry": {"coordinates":[10.6190242767,51.5942802429],"type":"Point"}
}