{
  "type": "Feature",
  "properties": {
    "iso:country":"DE",
    "sg:address":"Am H\u00e4nisgraben 50",
    "sg:city":"Dieburg",
    "sg:phone":"+49 6071/980625",
    "sg:postcode":"64807",
    "sg:province":"Hessen",
    "wof:name":"Wis Wareninformations - Service Gmbh",
    "wof:placetype":"venue"
},
  "geometry": {"coordinates":[8.846297,49.890999],"type":"Point"}
}