{
  "type": "Feature",
  "properties": {
    "iso:country":"DE",
    "sg:address":"St.-Wolfgang-Str. 3",
    "sg:city":"Rauenberg",
    "sg:phone":"+49 7253/21100",
    "sg:postcode":"69231",
    "sg:province":"Baden-W\u00fcrttemberg",
    "wof:name":"Kath. Pfarramt St. Wolfgang",
    "wof:placetype":"venue"
},
  "geometry": {"coordinates":[8.6792230606,49.2543983459],"type":"Point"}
}