{
  "type": "Feature",
  "properties": {
    "iso:country":"DE",
    "sg:address":"Ostpreu\u00dfenstr. 13",
    "sg:city":"Frankfurt",
    "sg:phone":"+49 6109/31198",
    "sg:postcode":"60388",
    "sg:province":"Hessen",
    "wof:name":"Hofmann U. Agiannidis",
    "wof:placetype":"venue"
},
  "geometry": {"coordinates":[8.7591524124,50.1463241577],"type":"Point"}
}