{
  "type": "Feature",
  "properties": {
    "iso:country":"DE",
    "sg:address":"Sonnenallee 159",
    "sg:city":"Berlin",
    "sg:phone":"+49 30/6814431",
    "sg:postcode":"12059",
    "sg:province":"Berlin",
    "wof:name":"Schreibwaren B. Volk",
    "wof:placetype":"venue"
},
  "geometry": {"coordinates":[13.4471673965,52.4784736633],"type":"Point"}
}