{
  "type": "Feature",
  "properties": {
    "iso:country":"DE",
    "sg:address":"Siedlung 28",
    "sg:city":"Dippoldiswalde",
    "sg:phone":"+49 3504/614155",
    "sg:postcode":"01744",
    "sg:province":"Sachsen",
    "wof:name":"Frank Albertus",
    "wof:placetype":"venue"
},
  "geometry": {"coordinates":[13.670047,50.881092],"type":"Point"}
}