{
  "type": "Feature",
  "properties": {
    "iso:country":"DE",
    "sg:address":"Woldegker Str. 35",
    "sg:city":"Neubrandenburg",
    "sg:phone":"+49 395/7070107",
    "sg:postcode":"17036",
    "sg:province":"Mecklenburg-Vorpommern",
    "wof:name":"Tap Transportlogistik Gmbh",
    "wof:placetype":"venue"
},
  "geometry": {"coordinates":[13.3012609482,53.5570640564],"type":"Point"}
}