{
  "type": "Feature",
  "properties": {
    "iso:country":"DE",
    "sg:address":"Hohenhewenstr. 103",
    "sg:city":"Singen",
    "sg:postcode":"78224",
    "sg:province":"Baden-W\u00fcrttemberg",
    "wof:name":"In-line Kommunikations- + Marketing Gmbh",
    "wof:placetype":"venue"
},
  "geometry": {"coordinates":[8.8391609192,47.7733688354],"type":"Point"}
}