{
  "type": "Feature",
  "properties": {
    "iso:country":"DE",
    "sg:address":"IndustrieStra\u00dfe 2",
    "sg:city":"Altendorf",
    "sg:postcode":"96146",
    "sg:province":"Bayern",
    "wof:name":"Koester Gmbh & Co. Kg",
    "wof:placetype":"venue"
},
  "geometry": {"coordinates":[11.0151395798,49.796207428],"type":"Point"}
}