{
  "type": "Feature",
  "properties": {
    "iso:country":"DE",
    "sg:address":"Burgstr. 20",
    "sg:city":"Einbeck",
    "sg:phone":"+49 5565/1444",
    "sg:postcode":"37574",
    "sg:province":"Niedersachsen",
    "wof:name":"Imbi\u00df Brutzelstube",
    "wof:placetype":"venue"
},
  "geometry": {"coordinates":[9.8073949814,51.8707084656],"type":"Point"}
}