{
  "type": "Feature",
  "properties": {
    "iso:country":"DE",
    "sg:address":"Schwalbenweg 19",
    "sg:city":"Aachen",
    "sg:phone":"+49 241/573013",
    "sg:postcode":"52078",
    "sg:province":"Nordrhein-Westfalen",
    "wof:name":"Bc Rhemania 08 Aachen-rothe-erde E. V.",
    "wof:placetype":"venue"
},
  "geometry": {"coordinates":[6.1341481209,50.7686729431],"type":"Point"}
}