{
  "type": "Feature",
  "properties": {
    "iso:country":"DE",
    "sg:address":"Schwarzachstr. 14",
    "sg:city":"Ertingen",
    "sg:phone":"+49 7371/95000",
    "sg:postcode":"88521",
    "sg:province":"Baden-W\u00fcrttemberg",
    "wof:name":"Fensterle Beton- Und Fertigteilwerk Gmbh",
    "wof:placetype":"venue"
},
  "geometry": {"coordinates":[9.462677002,48.0891075134],"type":"Point"}
}