{
  "type": "Feature",
  "properties": {
    "iso:country":"DE",
    "sg:address":"Hauptstr. 33",
    "sg:city":"Aitrach",
    "sg:phone":"+49 7565/5815",
    "sg:postcode":"88319",
    "sg:province":"Baden-W\u00fcrttemberg",
    "wof:name":"Horst-dieter Preiss Masseur",
    "wof:placetype":"venue"
},
  "geometry": {"coordinates":[10.08862,47.939976],"type":"Point"}
}