{
  "type": "Feature",
  "properties": {
    "iso:country":"DE",
    "sg:address":"Hohentannenstr. 23",
    "sg:city":"Gschwend",
    "sg:phone":"+49 7972/5370",
    "sg:postcode":"74417",
    "sg:province":"Baden-W\u00fcrttemberg",
    "wof:name":"A. Kunz",
    "wof:placetype":"venue"
},
  "geometry": {"coordinates":[9.7851076126,48.9417953491],"type":"Point"}
}