{
  "type": "Feature",
  "properties": {
    "iso:country":"DE",
    "sg:address":"K\u00f6nigsteiner Str. 3",
    "sg:city":"Neuhaus",
    "sg:phone":"+49 9156/200",
    "sg:postcode":"91284",
    "sg:province":"Bayern",
    "wof:name":"Georg Stange Architekt",
    "wof:placetype":"venue"
},
  "geometry": {"coordinates":[11.560144,49.630356],"type":"Point"}
}