{
  "type": "Feature",
  "properties": {
    "iso:country":"DE",
    "sg:address":"Sponeckplatz 2",
    "sg:city":"M\u00fcnchen",
    "sg:phone":"+49 89/8634277",
    "sg:postcode":"81245",
    "sg:province":"Bayern",
    "wof:name":"Dr. H. Vaupel Tierarzt",
    "wof:placetype":"venue"
},
  "geometry": {"coordinates":[11.433134079,48.1562156677],"type":"Point"}
}