{
  "type": "Feature",
  "properties": {
    "iso:country":"DE",
    "sg:address":"Dorfstr. 32",
    "sg:city":"Bobeck",
    "sg:phone":"+49 36692/22587",
    "sg:postcode":"07646",
    "sg:province":"Th\u00fcringen",
    "wof:name":"Rudi Zeise",
    "wof:placetype":"venue"
},
  "geometry": {"coordinates":[11.7925491333,50.9031524658],"type":"Point"}
}