{
  "type": "Feature",
  "properties": {
    "iso:country":"DE",
    "sg:address":"Cuxhavener Str. 226",
    "sg:city":"Hamburg",
    "sg:phone":"+49 40/7016172",
    "sg:postcode":"21149",
    "sg:province":"Hamburg",
    "wof:name":"Herbert Lepel",
    "wof:placetype":"venue"
},
  "geometry": {"coordinates":[9.8750610352,53.4720344543],"type":"Point"}
}