{
  "type": "Feature",
  "properties": {
    "iso:country":"DE",
    "sg:address":"Butschstr. 6-1",
    "sg:city":"Trossingen",
    "sg:phone":"+49 7425/1506",
    "sg:postcode":"78647",
    "sg:province":"Baden-W\u00fcrttemberg",
    "wof:name":"A. Schopferer",
    "wof:placetype":"venue"
},
  "geometry": {"coordinates":[8.638158,48.077869],"type":"Point"}
}