{
  "type": "Feature",
  "properties": {
    "iso:country":"DE",
    "sg:address":"Lerchenweg 41",
    "sg:city":"Chemnitz",
    "sg:phone":"+49 371/821427",
    "sg:postcode":"09123",
    "sg:province":"Sachsen",
    "wof:name":"Gunter-ulrich Wolfram Immobilienmakler",
    "wof:placetype":"venue"
},
  "geometry": {"coordinates":[12.9384651184,50.7627906799],"type":"Point"}
}