{
  "type": "Feature",
  "properties": {
    "iso:country":"DE",
    "sg:address":"Vor dem Steintor 54",
    "sg:city":"Bremen",
    "sg:phone":"+49 421/78073",
    "sg:postcode":"28203",
    "sg:province":"Bremen",
    "wof:name":"Yildirim Reisen",
    "wof:placetype":"venue"
},
  "geometry": {"coordinates":[8.8262367249,53.0730133057],"type":"Point"}
}