{
  "type": "Feature",
  "properties": {
    "iso:country":"DE",
    "sg:address":"L\u00fctticher Str. 3 a",
    "sg:city":"Aachen",
    "sg:phone":"+49 241/72277",
    "sg:postcode":"52064",
    "sg:province":"Nordrhein-Westfalen",
    "wof:name":"Heinrich Kohnen",
    "wof:placetype":"venue"
},
  "geometry": {"coordinates":[6.073979,50.768726],"type":"Point"}
}