{
  "type": "Feature",
  "properties": {
    "iso:country":"DE",
    "sg:address":"Winthirstr. 31",
    "sg:city":"M\u00fcnchen",
    "sg:phone":"+49 89/132214",
    "sg:postcode":"80639",
    "sg:province":"Bayern",
    "wof:name":"A. Roeckenschuss Kg",
    "wof:placetype":"venue"
},
  "geometry": {"coordinates":[11.527386,48.157009],"type":"Point"}
}