{
  "type": "Feature",
  "properties": {
    "iso:country":"DE",
    "sg:address":"Auf den Bl\u00f6cken 1",
    "sg:city":"L\u00fcneburg",
    "sg:postcode":"21337",
    "sg:province":"Niedersachsen",
    "wof:name":"Bahr Baumarkt",
    "wof:placetype":"venue"
},
  "geometry": {"coordinates":[10.4426784515,53.2438316345],"type":"Point"}
}