{
  "type": "Feature",
  "properties": {
    "iso:country":"DE",
    "sg:address":"Hauptstr. 22",
    "sg:city":"Doberlug-Kirchhain",
    "sg:phone":"+49 35322/2641",
    "sg:postcode":"03253",
    "sg:province":"Brandenburg",
    "wof:name":"Karl Wolff Inh. Rudolf Pansow",
    "wof:placetype":"venue"
},
  "geometry": {"coordinates":[13.5510749817,51.6110649109],"type":"Point"}
}