{
  "type": "Feature",
  "properties": {
    "iso:country":"DE",
    "sg:address":"K\u00f6nigsberger Str. 24",
    "sg:city":"Delbr\u00fcck",
    "sg:phone":"+49 5250/7862",
    "sg:postcode":"33129",
    "sg:province":"Nordrhein-Westfalen",
    "wof:name":"Willi Brautmeier",
    "wof:placetype":"venue"
},
  "geometry": {"coordinates":[8.55804,51.757065],"type":"Point"}
}