{
  "type": "Feature",
  "properties": {
    "iso:country":"DE",
    "sg:address":"Abgunst 6",
    "sg:city":"Bad Grund",
    "sg:phone":"+49 5327/1224",
    "sg:postcode":"37539",
    "sg:province":"Niedersachsen",
    "wof:name":"G\u00e4stehaus Haus Paland",
    "wof:placetype":"venue"
},
  "geometry": {"coordinates":[10.2326517105,51.8051338196],"type":"Point"}
}