{
  "type": "Feature",
  "properties": {
    "iso:country":"DE",
    "sg:address":"Gr\u00e4wingheide 8",
    "sg:city":"Dorsten",
    "sg:phone":"+49 2362/24246",
    "sg:postcode":"46282",
    "sg:province":"Nordrhein-Westfalen",
    "wof:name":"Josef Erwig",
    "wof:placetype":"venue"
},
  "geometry": {"coordinates":[7.011158,51.637096],"type":"Point"}
}