{
  "type": "Feature",
  "properties": {
    "iso:country":"DE",
    "sg:address":"Riedwasen 3",
    "sg:city":"Aldingen",
    "sg:phone":"+49 4974/2497040",
    "sg:postcode":"78554",
    "sg:province":"Baden-W\u00fcrttemberg",
    "wof:name":"Fritz Auber Gmbh",
    "wof:placetype":"venue"
},
  "geometry": {"coordinates":[8.7109222412,48.0912818909],"type":"Point"}
}