{
  "type": "Feature",
  "properties": {
    "iso:country":"DE",
    "sg:address":"Ostackerweg 43",
    "sg:city":"Duisburg",
    "sg:phone":"+49 203/460392",
    "sg:postcode":"47139",
    "sg:province":"Nordrhein-Westfalen",
    "wof:name":"Praxis Dr. Med. Breimann Und Doese",
    "wof:placetype":"venue"
},
  "geometry": {"coordinates":[6.7459402084,51.4822883606],"type":"Point"}
}