{
  "type": "Feature",
  "properties": {
    "iso:country":"DE",
    "sg:address":"Schafhof 34",
    "sg:city":"Muggensturm",
    "sg:phone":"+49 7222/51551",
    "sg:postcode":"76461",
    "sg:province":"Baden-W\u00fcrttemberg",
    "wof:name":"Edmund M\u00fcller",
    "wof:placetype":"venue"
},
  "geometry": {"coordinates":[8.2747631073,48.8683204651],"type":"Point"}
}