{
  "type": "Feature",
  "properties": {
    "iso:country":"DE",
    "sg:address":"Am Graben 2",
    "sg:city":"Wunstorf",
    "sg:phone":"+49 5033/1422",
    "sg:postcode":"31515",
    "sg:province":"Niedersachsen",
    "wof:name":"Pension Gastst\u00e4tte Alter Krug",
    "wof:placetype":"venue"
},
  "geometry": {"coordinates":[9.3535041809,52.4531669617],"type":"Point"}
}