{
  "type": "Feature",
  "properties": {
    "iso:country":"DE",
    "sg:address":"Talstr. 58 a",
    "sg:city":"M\u00fclheim",
    "sg:phone":"+49 208/71591",
    "sg:postcode":"45475",
    "sg:province":"Nordrhein-Westfalen",
    "wof:name":"Hans-richard Spitza",
    "wof:placetype":"venue"
},
  "geometry": {"coordinates":[6.9019618034,51.463684082],"type":"Point"}
}