{
  "type": "Feature",
  "properties": {
    "iso:country":"DE",
    "sg:address":"Lindenstr.",
    "sg:city":"Itzehoe",
    "sg:phone":"+49 4821/75546",
    "sg:postcode":"25524",
    "sg:province":"Schleswig-Holstein",
    "wof:name":"Adler-apotheke Martin Bolle",
    "wof:placetype":"venue"
},
  "geometry": {"coordinates":[9.48498,53.933025],"type":"Point"}
}