{
  "type": "Feature",
  "properties": {
    "iso:country":"DE",
    "sg:address":"Hinterbr\u00fcnst 2",
    "sg:city":"Georgenberg",
    "sg:phone":"+49 9658/324",
    "sg:postcode":"92697",
    "sg:province":"Bayern",
    "wof:name":"Hans P\u00f6llinger",
    "wof:placetype":"venue"
},
  "geometry": {"coordinates":[12.4393196106,49.6989135742],"type":"Point"}
}