{
  "type": "Feature",
  "properties": {
    "iso:country":"DE",
    "sg:address":"Taubenweg 17",
    "sg:city":"Schotten",
    "sg:phone":"+49 6044/96260",
    "sg:postcode":"63679",
    "sg:province":"Hessen",
    "wof:name":"Volker Witamwas Gmbh",
    "wof:placetype":"venue"
},
  "geometry": {"coordinates":[9.119992,50.497143],"type":"Point"}
}