{
  "type": "Feature",
  "properties": {
    "iso:country":"DE",
    "sg:address":"Ferdinandstr. 1",
    "sg:city":"Rostock",
    "sg:phone":"+49 381/455830",
    "sg:postcode":"18055",
    "sg:province":"Mecklenburg-Vorpommern",
    "wof:name":"Dental-technik Gmbh Rostock Zentrum",
    "wof:placetype":"venue"
},
  "geometry": {"coordinates":[12.142493248,54.0821838379],"type":"Point"}
}