{
  "type": "Feature",
  "properties": {
    "iso:country":"DE",
    "sg:address":"Bahnhofstr. 11",
    "sg:city":"Singen",
    "sg:phone":"+49 7731/68146",
    "sg:postcode":"78224",
    "sg:province":"Baden-W\u00fcrttemberg",
    "wof:name":"M. Karaca",
    "wof:placetype":"venue"
},
  "geometry": {"coordinates":[8.8377609253,47.7579574585],"type":"Point"}
}