{
  "type": "Feature",
  "properties": {
    "iso:country":"DE",
    "sg:address":"Hauptstr. 49",
    "sg:city":"Oldenburg",
    "sg:phone":"+49 441/506494",
    "sg:postcode":"26122",
    "sg:province":"Niedersachsen",
    "wof:name":"Eversten-apotheke",
    "wof:placetype":"venue"
},
  "geometry": {"coordinates":[8.196782,53.133049],"type":"Point"}
}