{
  "type": "Feature",
  "properties": {
    "iso:country":"DE",
    "sg:address":"Beiersdorfer Str. 23",
    "sg:city":"Grimma",
    "sg:phone":"+49 3437/917400",
    "sg:postcode":"04668",
    "sg:province":"Sachsen",
    "wof:name":"Waltraud Franke",
    "wof:placetype":"venue"
},
  "geometry": {"coordinates":[12.7203807831,51.2406845093],"type":"Point"}
}