{
  "type": "Feature",
  "properties": {
    "iso:country":"DE",
    "sg:address":"Rabenstein 15",
    "sg:city":"Lichtenfels",
    "sg:phone":"+49 9571/8585",
    "sg:postcode":"96215",
    "sg:province":"Bayern",
    "wof:name":"Ev. Luth. Pfarramt",
    "wof:placetype":"venue"
},
  "geometry": {"coordinates":[11.0757637024,50.1639022827],"type":"Point"}
}