{
  "type": "Feature",
  "properties": {
    "iso:country":"DE",
    "sg:address":"Hofackerstr. 5",
    "sg:city":"Schwaig",
    "sg:phone":"+49 911/9588960",
    "sg:postcode":"90571",
    "sg:province":"Bayern",
    "wof:name":"Redaktion Simmelsdorf Verlag Seifert & Wiedemann",
    "wof:placetype":"venue"
},
  "geometry": {"coordinates":[11.2002258301,49.4729423523],"type":"Point"}
}