{
  "type": "Feature",
  "properties": {
    "iso:country":"DE",
    "sg:address":"Hauptstr. 48",
    "sg:city":"Luckau",
    "sg:phone":"+49 3544/3018",
    "sg:postcode":"15926",
    "sg:province":"Brandenburg",
    "wof:name":"Stadtschenke",
    "wof:placetype":"venue"
},
  "geometry": {"coordinates":[13.7135334015,51.8525810242],"type":"Point"}
}