{
  "type": "Feature",
  "properties": {
    "iso:country":"DE",
    "sg:address":"Am Waldrand 30",
    "sg:city":"Wassenberg",
    "sg:phone":"+49 2432/3483",
    "sg:postcode":"41849",
    "sg:province":"Nordrhein-Westfalen",
    "wof:name":"Theo J\u00fctten Obstanbau",
    "wof:placetype":"venue"
},
  "geometry": {"coordinates":[6.1747941971,51.1077156067],"type":"Point"}
}