{
  "type": "Feature",
  "properties": {
    "iso:country":"DE",
    "sg:address":"Schneewei\u00dfstr. 8",
    "sg:city":"Crailsheim",
    "sg:phone":"+49 7951/24139",
    "sg:postcode":"74564",
    "sg:province":"Baden-W\u00fcrttemberg",
    "wof:name":"H. J\u00f6kel",
    "wof:placetype":"venue"
},
  "geometry": {"coordinates":[10.0609846115,49.1288223267],"type":"Point"}
}