{
  "type": "Feature",
  "properties": {
    "iso:country":"DE",
    "sg:address":"Seestr. 64",
    "sg:city":"Berlin",
    "sg:phone":"+49 30/4564046",
    "sg:postcode":"13347",
    "sg:province":"Berlin",
    "wof:name":"Rex-tier-freund",
    "wof:placetype":"venue"
},
  "geometry": {"coordinates":[13.359384,52.553905],"type":"Point"}
}