{
  "type": "Feature",
  "properties": {
    "iso:country":"DE",
    "sg:address":"Langestr. 24",
    "sg:city":"B\u00fctzow",
    "sg:phone":"+49 38461/2577",
    "sg:postcode":"18246",
    "sg:province":"Mecklenburg-Vorpommern",
    "wof:name":"Fritz B\u00f6ckenhauer",
    "wof:placetype":"venue"
},
  "geometry": {"coordinates":[11.9840393066,53.8479881287],"type":"Point"}
}