{
  "type": "Feature",
  "properties": {
    "iso:country":"DE",
    "sg:address":"Robert-Blum-Str. 45",
    "sg:city":"Annaberg-Buchholz",
    "sg:phone":"+49 3733/22872",
    "sg:postcode":"09456",
    "sg:province":"Sachsen",
    "wof:name":"Gerhard Glowalla",
    "wof:placetype":"venue"
},
  "geometry": {"coordinates":[13.013347,50.569626],"type":"Point"}
}