{
  "type": "Feature",
  "properties": {
    "iso:country":"DE",
    "sg:address":"Ansbacher Str. 54",
    "sg:city":"Berlin",
    "sg:phone":"+49 30/2182135",
    "sg:postcode":"10777",
    "sg:province":"Berlin",
    "wof:name":"Fuks Immobilien Gmbh & Co. Kg",
    "wof:placetype":"venue"
},
  "geometry": {"coordinates":[13.3395843506,52.4978523254],"type":"Point"}
}