{
  "type": "Feature",
  "properties": {
    "iso:country":"DE",
    "sg:address":"Bauhausplatz 2",
    "sg:city":"Dessau",
    "sg:phone":"+49 340/2204638",
    "sg:postcode":"06846",
    "sg:province":"Sachsen-Anhalt",
    "wof:name":"Hans-georg Richter",
    "wof:placetype":"venue"
},
  "geometry": {"coordinates":[12.2265481949,51.8387069702],"type":"Point"}
}