{
  "type": "Feature",
  "properties": {
    "iso:country":"DE",
    "sg:address":"Fechterweg 13",
    "sg:city":"Bielefeld",
    "sg:phone":"+49 521/401434",
    "sg:postcode":"33659",
    "sg:province":"Nordrhein-Westfalen",
    "wof:name":"Dieter Schwieger",
    "wof:placetype":"venue"
},
  "geometry": {"coordinates":[8.516863,51.967762],"type":"Point"}
}