{
  "type": "Feature",
  "properties": {
    "iso:country":"DE",
    "sg:address":"Hoheluftchaussee 118",
    "sg:city":"Hamburg",
    "sg:postcode":"20253",
    "sg:province":"Hamburg",
    "wof:name":"Tiede Gastronomie Gmbh",
    "wof:placetype":"venue"
},
  "geometry": {"coordinates":[9.9695205688,53.5847892761],"type":"Point"}
}