{
  "type": "Feature",
  "properties": {
    "iso:country":"DE",
    "sg:address":"Sch\u00f6nbergstr. 16",
    "sg:city":"Ebringen",
    "sg:phone":"+49 7664/6309",
    "sg:postcode":"79285",
    "sg:province":"Baden-W\u00fcrttemberg",
    "wof:name":"Theo Kuhn Fachgesch\u00e4ft F\u00fcr Raumausstattung Gmbh",
    "wof:placetype":"venue"
},
  "geometry": {"coordinates":[7.771229,47.95742],"type":"Point"}
}