{
  "type": "Feature",
  "properties": {
    "iso:country":"DE",
    "sg:address":"Obere Gasse 3",
    "sg:city":"Erlangen",
    "sg:postcode":"91056",
    "sg:province":"Bayern",
    "wof:name":"Gehr Verwaltungsges. Mbh",
    "wof:placetype":"venue"
},
  "geometry": {"coordinates":[10.9592523575,49.5886383057],"type":"Point"}
}