{
  "type": "Feature",
  "properties": {
    "iso:country":"DE",
    "sg:address":"Wilhelm-Soehnle-Str. 2",
    "sg:city":"Murrhardt",
    "sg:phone":"+49 7192/281",
    "sg:postcode":"71540",
    "sg:province":"Baden-W\u00fcrttemberg",
    "wof:name":"Soehnle-waagen Verwaltungs- Gmbh",
    "wof:placetype":"venue"
},
  "geometry": {"coordinates":[9.555644989,48.9872131348],"type":"Point"}
}