{
  "type": "Feature",
  "properties": {
    "iso:country":"DE",
    "sg:address":"Stettiner Str. 2",
    "sg:city":"Bassum",
    "sg:phone":"+49 4241/2707",
    "sg:postcode":"27211",
    "sg:province":"Niedersachsen",
    "wof:name":"Gef Bau Gmbh",
    "wof:placetype":"venue"
},
  "geometry": {"coordinates":[8.7301549911,52.8577346802],"type":"Point"}
}