{
  "type": "Feature",
  "properties": {
    "iso:country":"DE",
    "sg:address":"Schlo\u00dfstr. 8",
    "sg:city":"Coswig",
    "sg:phone":"+49 34903/62204",
    "sg:postcode":"06869",
    "sg:province":"Sachsen-Anhalt",
    "wof:name":"Joachim Dorn",
    "wof:placetype":"venue"
},
  "geometry": {"coordinates":[12.458387,51.882927],"type":"Point"}
}