{
  "type": "Feature",
  "properties": {
    "iso:country":"DE",
    "sg:address":"Ph\u00f6bener Str. 89",
    "sg:city":"Werder",
    "sg:phone":"+49 3327/40427",
    "sg:postcode":"14542",
    "sg:province":"Brandenburg",
    "wof:name":"Rolf Lidzba",
    "wof:placetype":"venue"
},
  "geometry": {"coordinates":[12.920625,52.395233],"type":"Point"}
}