{
  "type": "Feature",
  "properties": {
    "iso:country":"DE",
    "sg:address":"Lenchen-Kunow-Weg 16",
    "sg:city":"Hannover",
    "sg:postcode":"30657",
    "sg:province":"Niedersachsen",
    "wof:name":"M\u00e4hler & Klaus Gmbh",
    "wof:placetype":"venue"
},
  "geometry": {"coordinates":[9.793421,52.421997],"type":"Point"}
}