{
  "type": "Feature",
  "properties": {
    "iso:country":"DE",
    "sg:address":"Langgasse 13",
    "sg:city":"Hattersheim",
    "sg:phone":"+49 6190/4572",
    "sg:postcode":"65795",
    "sg:province":"Hessen",
    "wof:name":"B\u00e4ckerei T\u00e4ffner Gmbh",
    "wof:placetype":"venue"
},
  "geometry": {"coordinates":[8.4992656708,50.051864624],"type":"Point"}
}