{
  "type": "Feature",
  "properties": {
    "iso:country":"DE",
    "sg:address":"Amberger Str. 2a",
    "sg:city":"Pilsach",
    "sg:phone":"+49 9181",
    "sg:postcode":"92367",
    "sg:province":"Bayern",
    "wof:name":"Fischer Automobile",
    "wof:placetype":"venue"
},
  "geometry": {"coordinates":[11.5077772141,49.3193397522],"type":"Point"}
}