{
  "type": "Feature",
  "properties": {
    "iso:country":"DE",
    "sg:address":"Gehsener Str. 41",
    "sg:city":"Berlin",
    "sg:phone":"+49 30/6529619",
    "sg:postcode":"12555",
    "sg:province":"Berlin",
    "wof:name":"Rudi Amelang",
    "wof:placetype":"venue"
},
  "geometry": {"coordinates":[13.5772457123,52.4660758972],"type":"Point"}
}