{
  "type": "Feature",
  "properties": {
    "iso:country":"DE",
    "sg:address":"Durlacher Str. 10a",
    "sg:city":"Karlsruhe",
    "sg:phone":"+49 721/482650",
    "sg:postcode":"76229",
    "sg:province":"Baden-W\u00fcrttemberg",
    "wof:name":"Volker Kek Ingenieur",
    "wof:placetype":"venue"
},
  "geometry": {"coordinates":[8.4930076599,49.0141983032],"type":"Point"}
}