{
  "type": "Feature",
  "properties": {
    "iso:country":"DE",
    "sg:address":"Marienburger Str. 26",
    "sg:city":"Bielefeld",
    "sg:postcode":"33605",
    "sg:province":"Nordrhein-Westfalen",
    "wof:name":"Hcb Handel Controlling Beratung Gmbh",
    "wof:placetype":"venue"
},
  "geometry": {"coordinates":[8.593334,52.004765],"type":"Point"}
}