{
  "type": "Feature",
  "properties": {
    "iso:country":"DE",
    "sg:address":"V\u00f6lklinger Str. 3",
    "sg:city":"D\u00fcsseldorf",
    "sg:phone":"+49 211/3032670",
    "sg:postcode":"40219",
    "sg:province":"Nordrhein-Westfalen",
    "wof:name":"Twenty 4 You Ohg",
    "wof:placetype":"venue"
},
  "geometry": {"coordinates":[6.759006,51.211342],"type":"Point"}
}