{
  "type": "Feature",
  "properties": {
    "iso:country":"DE",
    "sg:address":"Moorberg 2",
    "sg:city":"Langwedel",
    "sg:phone":"+49 4232/7905",
    "sg:postcode":"27299",
    "sg:province":"Niedersachsen",
    "wof:name":"Kurt Bornkamp",
    "wof:placetype":"venue"
},
  "geometry": {"coordinates":[9.190628,52.980083],"type":"Point"}
}