{
  "type": "Feature",
  "properties": {
    "iso:country":"DE",
    "sg:address":"Idenbrockplatz 14",
    "sg:city":"M\u00fcnster",
    "sg:phone":"+49 251/214310",
    "sg:postcode":"48159",
    "sg:province":"Nordrhein-Westfalen",
    "wof:name":"S. Deitmer",
    "wof:placetype":"venue"
},
  "geometry": {"coordinates":[7.6035699844,51.9947967529],"type":"Point"}
}