{
  "type": "Feature",
  "properties": {
    "iso:country":"DE",
    "sg:address":"Neuer Markt",
    "sg:city":"Ettlingen",
    "sg:phone":"+49 7243/54390",
    "sg:postcode":"76275",
    "sg:province":"Baden-W\u00fcrttemberg",
    "wof:name":"Durm F\u00fcr M\u00e4nner Gmbh",
    "wof:placetype":"venue"
},
  "geometry": {"coordinates":[8.4061203003,48.9417762756],"type":"Point"}
}