{
  "type": "Feature",
  "properties": {
    "iso:country":"DE",
    "sg:address":"Kaiserallee 25b",
    "sg:city":"Karlsruhe",
    "sg:phone":"+49 721/845380",
    "sg:postcode":"76133",
    "sg:province":"Baden-W\u00fcrttemberg",
    "wof:name":"Henk Und Gurock",
    "wof:placetype":"venue"
},
  "geometry": {"coordinates":[8.3809890747,49.0104103088],"type":"Point"}
}