{
  "type": "Feature",
  "properties": {
    "iso:country":"DE",
    "sg:address":"Georg-Benda-Str. 7",
    "sg:city":"F\u00fcrth",
    "sg:phone":"+49 911/7849081",
    "sg:postcode":"90763",
    "sg:province":"Bayern",
    "wof:name":"Bosch Dienst Fuchs Gmbh",
    "wof:placetype":"venue"
},
  "geometry": {"coordinates":[10.9948129654,49.4463043213],"type":"Point"}
}