{
  "type": "Feature",
  "properties": {
    "iso:country":"DE",
    "sg:address":"Sektkellereistr 5",
    "sg:city":"Freyburg",
    "sg:phone":"+49 6722/4040",
    "sg:postcode":"06632",
    "sg:province":"Sachsen-Anhalt",
    "wof:name":"R\u00fcdesheimer Weinkellerei Gmbh",
    "wof:placetype":"venue"
},
  "geometry": {"coordinates":[7.9327998161,49.9804458618],"type":"Point"}
}