{
  "type": "Feature",
  "properties": {
    "iso:country":"DE",
    "sg:address":"Engelbertstr. 63",
    "sg:city":"K\u00f6ln",
    "sg:phone":"+49 221/2404170",
    "sg:postcode":"50674",
    "sg:province":"Nordrhein-Westfalen",
    "wof:name":"Bamboo Club",
    "wof:placetype":"venue"
},
  "geometry": {"coordinates":[6.937727,50.93494],"type":"Point"}
}