{
  "type": "Feature",
  "properties": {
    "iso:country":"DE",
    "sg:address":"Steinweg 6",
    "sg:city":"R\u00f6mhild",
    "sg:phone":"+49 36948/20446",
    "sg:postcode":"98631",
    "sg:province":"Th\u00fcringen",
    "wof:name":"G\u00fcnter Lux",
    "wof:placetype":"venue"
},
  "geometry": {"coordinates":[10.5385074615,50.3943481445],"type":"Point"}
}