{
  "type": "Feature",
  "properties": {
    "iso:country":"DE",
    "sg:address":"Schmolkamp 10",
    "sg:city":"Eicklingen",
    "sg:phone":"+49 5144/4206",
    "sg:postcode":"29358",
    "sg:province":"Niedersachsen",
    "wof:name":"Ford Autohaus Wilke",
    "wof:placetype":"venue"
},
  "geometry": {"coordinates":[10.1871385574,52.5439109802],"type":"Point"}
}