{
  "type": "Feature",
  "properties": {
    "iso:country":"DE",
    "sg:address":"Opladener Str. 174",
    "sg:city":"Langenfeld",
    "sg:phone":"+49 2173/15441",
    "sg:postcode":"40764",
    "sg:province":"Nordrhein-Westfalen",
    "wof:name":"Gerd Buchheim",
    "wof:placetype":"venue"
},
  "geometry": {"coordinates":[6.977921,51.082237],"type":"Point"}
}