{
  "type": "Feature",
  "properties": {
    "iso:country":"DE",
    "sg:address":"Zur Lessingschule 12",
    "sg:city":"Freital",
    "sg:phone":"+49 351/6491114",
    "sg:postcode":"01705",
    "sg:province":"Sachsen",
    "wof:name":"Harald Hanak",
    "wof:placetype":"venue"
},
  "geometry": {"coordinates":[13.6603145599,51.0111579895],"type":"Point"}
}