{
  "type": "Feature",
  "properties": {
    "iso:country":"DE",
    "sg:address":"Haferbachstr. 45",
    "sg:city":"Lage",
    "sg:phone":"+49 5232/71160",
    "sg:postcode":"32791",
    "sg:province":"Nordrhein-Westfalen",
    "wof:name":"Hotel Landgasthaus Niemann",
    "wof:placetype":"venue"
},
  "geometry": {"coordinates":[8.7333402634,51.9776611328],"type":"Point"}
}