{
  "type": "Feature",
  "properties": {
    "iso:country":"DE",
    "sg:address":"August-Bebel-Str. 16",
    "sg:city":"Havelberg",
    "sg:phone":"+49 39387/8378",
    "sg:postcode":"39539",
    "sg:province":"Sachsen-Anhalt",
    "wof:name":"Wolfgang Fischer",
    "wof:placetype":"venue"
},
  "geometry": {"coordinates":[12.083497,52.828236],"type":"Point"}
}