{
  "type": "Feature",
  "properties": {
    "iso:country":"DE",
    "sg:address":"Parsifalstr. 4-6",
    "sg:city":"N\u00fcrnberg",
    "sg:phone":"+49 911/4780635",
    "sg:postcode":"90461",
    "sg:province":"Bayern",
    "wof:name":"Hawog Haus- Und Wohnungs- Verwaltungsgesellschaft Mbh",
    "wof:placetype":"venue"
},
  "geometry": {"coordinates":[11.1011190414,49.4382972717],"type":"Point"}
}