{
  "type": "Feature",
  "properties": {
    "iso:country":"DE",
    "sg:address":"Am Lustberg 14",
    "sg:city":"Hamburg",
    "sg:phone":"+49 40/697110",
    "sg:postcode":"22335",
    "sg:province":"Hamburg",
    "wof:name":"Rationell Wohnungsbau- Gesellschaft Mbh",
    "wof:placetype":"venue"
},
  "geometry": {"coordinates":[10.0133609772,53.6248779297],"type":"Point"}
}