{
  "type": "Feature",
  "properties": {
    "iso:country":"DE",
    "sg:address":"Rockel 72",
    "sg:city":"Rosendahl",
    "sg:phone":"+49 2545/507",
    "sg:postcode":"48720",
    "sg:province":"Nordrhein-Westfalen",
    "wof:name":"Karl Hemsing",
    "wof:placetype":"venue"
},
  "geometry": {"coordinates":[7.281795,52.05204],"type":"Point"}
}