{
  "type": "Feature",
  "properties": {
    "iso:country":"DE",
    "sg:address":"Forststr. 4",
    "sg:city":"Bad F\u00fcssing",
    "sg:phone":"+49 8537/358",
    "sg:postcode":"94072",
    "sg:province":"Bayern",
    "wof:name":"Hermann Buchinger",
    "wof:placetype":"venue"
},
  "geometry": {"coordinates":[13.270507,48.319294],"type":"Point"}
}