{
  "type": "Feature",
  "properties": {
    "iso:country":"DE",
    "sg:address":"Rothsteinslache 16",
    "sg:city":"Falkenberg",
    "sg:phone":"+49 35365/2835",
    "sg:postcode":"04895",
    "sg:province":"Brandenburg",
    "wof:name":"Ingenieur-b\u00fcro Voigt Gmbh",
    "wof:placetype":"venue"
},
  "geometry": {"coordinates":[13.2504081726,51.5847167969],"type":"Point"}
}