{
  "type": "Feature",
  "properties": {
    "iso:country":"DE",
    "sg:address":"L\u00fcbecker Landstr. 50",
    "sg:city":"Eutin",
    "sg:phone":"+49 4521/5230",
    "sg:postcode":"23701",
    "sg:province":"Schleswig-Holstein",
    "wof:name":"Gerd Huppelsberg",
    "wof:placetype":"venue"
},
  "geometry": {"coordinates":[10.635961,54.121578],"type":"Point"}
}