{
  "type": "Feature",
  "properties": {
    "iso:country":"DE",
    "sg:address":"Friedrich-Ebert-Str. 15",
    "sg:city":"G\u00fctersloh",
    "sg:phone":"+49 5241/12048",
    "sg:postcode":"33330",
    "sg:province":"Nordrhein-Westfalen",
    "wof:name":"Hornberg Gmbh Fleisch Und Wurstwaren",
    "wof:placetype":"venue"
},
  "geometry": {"coordinates":[8.3793945312,51.9127922058],"type":"Point"}
}