{
  "type": "Feature",
  "properties": {
    "iso:country":"DE",
    "sg:address":"Am Blauen Stein 7",
    "sg:city":"Darmstadt",
    "sg:phone":"+49 6151/313387",
    "sg:postcode":"64295",
    "sg:province":"Hessen",
    "wof:name":"Arnold Gmbh",
    "wof:placetype":"venue"
},
  "geometry": {"coordinates":[8.632867,49.856014],"type":"Point"}
}