{
  "type": "Feature",
  "properties": {
    "iso:country":"DE",
    "sg:address":"Braunstr. 4",
    "sg:city":"Hannover",
    "sg:phone":"+49 511/14682",
    "sg:postcode":"30169",
    "sg:province":"Niedersachsen",
    "wof:name":"Paul Scheerle",
    "wof:placetype":"venue"
},
  "geometry": {"coordinates":[9.7225151062,52.3730545044],"type":"Point"}
}