{
  "type": "Feature",
  "properties": {
    "iso:country":"DE",
    "sg:address":"Parkallee 48",
    "sg:city":"Bremen",
    "sg:phone":"+49 421/34050",
    "sg:postcode":"28209",
    "sg:province":"Bremen",
    "wof:name":"Siemer & M\u00fcller Gmbh & Co. Kg",
    "wof:placetype":"venue"
},
  "geometry": {"coordinates":[8.8242282867,53.0841407776],"type":"Point"}
}