{
  "type": "Feature",
  "properties": {
    "iso:country":"DE",
    "sg:address":"Schalweg 26",
    "sg:city":"Haltern",
    "sg:phone":"+49 2364/6382",
    "sg:postcode":"45721",
    "sg:province":"Nordrhein-Westfalen",
    "wof:name":"Manfred Prang",
    "wof:placetype":"venue"
},
  "geometry": {"coordinates":[7.2254958153,51.7724609375],"type":"Point"}
}