{
  "type": "Feature",
  "properties": {
    "iso:country":"DE",
    "sg:address":"Dingdener Str. 22",
    "sg:city":"Bocholt",
    "sg:postcode":"46395",
    "sg:province":"Nordrhein-Westfalen",
    "wof:name":"Praktiker Bau- Und Heimwerkermarkt",
    "wof:placetype":"venue"
},
  "geometry": {"coordinates":[6.6142430305,51.8232421875],"type":"Point"}
}