{
  "type": "Feature",
  "properties": {
    "iso:country":"DE",
    "sg:address":"Illbachstr. 3",
    "sg:city":"Marpingen",
    "sg:phone":"+49 6827/564",
    "sg:postcode":"66646",
    "sg:province":"Saarland",
    "wof:name":"Hans Recktenwald",
    "wof:placetype":"venue"
},
  "geometry": {"coordinates":[7.0801768303,49.4272613525],"type":"Point"}
}