{
  "type": "Feature",
  "properties": {
    "iso:country":"DE",
    "sg:address":"Hilbringer Str. 3",
    "sg:city":"Merzig",
    "sg:phone":"+49 6861/5001",
    "sg:postcode":"66663",
    "sg:province":"Saarland",
    "wof:name":"Wolfgang Richter-kirsch",
    "wof:placetype":"venue"
},
  "geometry": {"coordinates":[6.613574,49.445457],"type":"Point"}
}