{
  "type": "Feature",
  "properties": {
    "iso:country":"DE",
    "sg:address":"Am Schornacker 17",
    "sg:city":"Wesel",
    "sg:phone":"+49 281/82244",
    "sg:postcode":"46485",
    "sg:province":"Nordrhein-Westfalen",
    "wof:name":"Empire-plaza Freizeitzentrum Betriebs Gmbh",
    "wof:placetype":"venue"
},
  "geometry": {"coordinates":[6.705455,51.662907],"type":"Point"}
}