{
  "type": "Feature",
  "properties": {
    "iso:country":"DE",
    "sg:address":"Franz-Kobinger-Str. 5",
    "sg:city":"Augsburg",
    "sg:postcode":"86157",
    "sg:province":"Bayern",
    "wof:name":"Sea Breeze Travel Gmbh",
    "wof:placetype":"venue"
},
  "geometry": {"coordinates":[10.8723449707,48.3622207642],"type":"Point"}
}