{
  "type": "Feature",
  "properties": {
    "iso:country":"DE",
    "sg:address":"Bruchdorfer Str. 30",
    "sg:city":"Bleckede",
    "sg:phone":"+49 5853/310",
    "sg:postcode":"21354",
    "sg:province":"Niedersachsen",
    "wof:name":"Mutter Gr\u00fcn Campingplatz",
    "wof:placetype":"venue"
},
  "geometry": {"coordinates":[10.84925,53.23653],"type":"Point"}
}