{
  "type": "Feature",
  "properties": {
    "iso:country":"DE",
    "sg:address":"Daiserstrasse 24",
    "sg:city":"M\u00fcnchen",
    "sg:phone":"+49 89",
    "sg:postcode":"81371",
    "sg:province":"Bayern",
    "wof:name":"M\u00fcnchner-gazetten-verlag Jochen Nibbe",
    "wof:placetype":"venue"
},
  "geometry": {"coordinates":[11.543654,48.11974],"type":"Point"}
}