{
  "type": "Feature",
  "properties": {
    "iso:country":"DE",
    "sg:address":"Gartenstr. 16 a",
    "sg:city":"Dargun",
    "sg:phone":"+49 39959/20321",
    "sg:postcode":"17159",
    "sg:province":"Mecklenburg-Vorpommern",
    "wof:name":"M. Hinderlich",
    "wof:placetype":"venue"
},
  "geometry": {"coordinates":[12.854944,53.897865],"type":"Point"}
}