{
  "type": "Feature",
  "properties": {
    "iso:country":"DE",
    "sg:address":"Lindenweg 17",
    "sg:city":"Moritz",
    "sg:phone":"+49 39247/280",
    "sg:postcode":"39264",
    "sg:province":"Sachsen-Anhalt",
    "wof:name":"E. Bettge",
    "wof:placetype":"venue"
},
  "geometry": {"coordinates":[12.026768,51.996231],"type":"Point"}
}