{
  "type": "Feature",
  "properties": {
    "iso:country":"DE",
    "sg:address":"Frommhagenstr. 30",
    "sg:city":"Stendal",
    "sg:phone":"+49 3931/716116",
    "sg:postcode":"39576",
    "sg:province":"Sachsen-Anhalt",
    "wof:name":"Betreuungsverein Drk Stendal E. V.",
    "wof:placetype":"venue"
},
  "geometry": {"coordinates":[11.855363,52.60218],"type":"Point"}
}