{
  "type": "Feature",
  "properties": {
    "iso:country":"DE",
    "sg:address":"Schwabenheimer Str. 25",
    "sg:city":"Mannheim",
    "sg:phone":"+49 621/891497",
    "sg:postcode":"68219",
    "sg:province":"Baden-W\u00fcrttemberg",
    "wof:name":"Ev. Pfarramt Vers\u00f6hnungsgemeinde",
    "wof:placetype":"venue"
},
  "geometry": {"coordinates":[8.529800415,49.4345283508],"type":"Point"}
}