{
  "type": "Feature",
  "properties": {
    "iso:country":"DE",
    "sg:address":"Kanalstr. 49",
    "sg:city":"M\u00fcnster",
    "sg:phone":"+49 251/25513",
    "sg:postcode":"48147",
    "sg:province":"Nordrhein-Westfalen",
    "wof:name":"Restaurant Hong Bin",
    "wof:placetype":"venue"
},
  "geometry": {"coordinates":[7.6335000992,51.9786300659],"type":"Point"}
}