{
  "type": "Feature",
  "properties": {
    "iso:country":"DE",
    "sg:address":"Wandersmannstr. 46",
    "sg:city":"Wiesbaden",
    "sg:phone":"+49 611/711407",
    "sg:postcode":"65205",
    "sg:province":"Hessen",
    "wof:name":"Horst Christ",
    "wof:placetype":"venue"
},
  "geometry": {"coordinates":[8.30617,50.05558],"type":"Point"}
}