{
  "type": "Feature",
  "properties": {
    "iso:country":"DE",
    "sg:address":"Hardenbergstr. 9-11",
    "sg:city":"Kiel",
    "sg:phone":"+49 431/804965",
    "sg:postcode":"24105",
    "sg:province":"Schleswig-Holstein",
    "wof:name":"Centre Culturel Francais De Kiel",
    "wof:placetype":"venue"
},
  "geometry": {"coordinates":[10.1350631714,54.3423805237],"type":"Point"}
}