{
  "type": "Feature",
  "properties": {
    "iso:country":"DE",
    "sg:address":"Fr\u00f6ndenberger Str. 101-107",
    "sg:city":"Menden",
    "sg:phone":"+49 2373/9250",
    "sg:postcode":"58706",
    "sg:province":"Nordrhein-Westfalen",
    "wof:name":"B. Steinbach Kg",
    "wof:placetype":"venue"
},
  "geometry": {"coordinates":[7.7793288231,51.4506721497],"type":"Point"}
}