{
  "type": "Feature",
  "properties": {
    "iso:country":"DE",
    "sg:address":"Hanauer Str. 66",
    "sg:city":"Aschaffenburg",
    "sg:phone":"+49 6021/21460",
    "sg:postcode":"63739",
    "sg:province":"Bayern",
    "wof:name":"Wohnhaus Kr\u00f6gula Gmbh",
    "wof:placetype":"venue"
},
  "geometry": {"coordinates":[9.131648,49.98045],"type":"Point"}
}