{
  "type": "Feature",
  "properties": {
    "iso:country":"DE",
    "sg:address":"Marienstr. 27",
    "sg:city":"Sch\u00f6ningen",
    "sg:phone":"+49 5352/8804",
    "sg:postcode":"38364",
    "sg:province":"Niedersachsen",
    "wof:name":"Ulrich Schumann",
    "wof:placetype":"venue"
},
  "geometry": {"coordinates":[10.9664335251,52.1318130493],"type":"Point"}
}