{
  "type": "Feature",
  "properties": {
    "iso:country":"DE",
    "sg:address":"Blumenstr. 5",
    "sg:city":"Grabenstetten",
    "sg:phone":"+49 7382/1062",
    "sg:postcode":"72582",
    "sg:province":"Baden-W\u00fcrttemberg",
    "wof:name":"Bauabdichtungs- Gmbh",
    "wof:placetype":"venue"
},
  "geometry": {"coordinates":[9.4658994675,48.5220718384],"type":"Point"}
}