{
  "type": "Feature",
  "properties": {
    "iso:country":"DE",
    "sg:address":"Lilienthaler Heerstr. 63",
    "sg:city":"Bremen",
    "sg:phone":"+49 421/253541",
    "sg:postcode":"28357",
    "sg:province":"Bremen",
    "wof:name":"Ellinor Ritschewald Heilpraktikerin",
    "wof:placetype":"venue"
},
  "geometry": {"coordinates":[8.8828392029,53.1036186218],"type":"Point"}
}