{
  "type": "Feature",
  "properties": {
    "iso:country":"DE",
    "sg:address":"Burger Str. 22",
    "sg:city":"St. Michaelisdonn",
    "sg:postcode":"25693",
    "sg:province":"Schleswig-Holstein",
    "wof:name":"Aldi Gmbh & Co. Kg",
    "wof:placetype":"venue"
},
  "geometry": {"coordinates":[9.1183185577,53.993686676],"type":"Point"}
}