{
  "type": "Feature",
  "properties": {
    "iso:country":"DE",
    "sg:address":"Rathausmarkt 5",
    "sg:city":"Hamburg",
    "sg:phone":"+49 40/3096040",
    "sg:postcode":"20095",
    "sg:province":"Hamburg",
    "wof:name":"Today Fund Management Deutschland Gmbh",
    "wof:placetype":"venue"
},
  "geometry": {"coordinates":[9.99360466,53.5513038635],"type":"Point"}
}