{
  "type": "Feature",
  "properties": {
    "iso:country":"DE",
    "sg:address":"Bargauer Str. 32",
    "sg:city":"Heubach",
    "sg:phone":"+49 7173/6234",
    "sg:postcode":"73540",
    "sg:province":"Baden-W\u00fcrttemberg",
    "wof:name":"Gubu Lebensmittel- Betriebe Gmbh & Co. Kg",
    "wof:placetype":"venue"
},
  "geometry": {"coordinates":[9.9219112396,48.795009613],"type":"Point"}
}