{
  "type": "Feature",
  "properties": {
    "iso:country":"DE",
    "sg:address":"Gro\u00dfmannstr. 86",
    "sg:city":"Hamburg",
    "sg:phone":"+49 40/781616",
    "sg:postcode":"20539",
    "sg:province":"Hamburg",
    "wof:name":"E. Friedrichs & S\u00f6hne Armaturen Gmbh",
    "wof:placetype":"venue"
},
  "geometry": {"coordinates":[10.052148819,53.5396003723],"type":"Point"}
}