{
  "type": "Feature",
  "properties": {
    "iso:country":"DE",
    "sg:address":"Klenzestr. 50",
    "sg:city":"M\u00fcnchen",
    "sg:phone":"+49 89/2011505",
    "sg:postcode":"80469",
    "sg:province":"Bayern",
    "wof:name":"Hans-roderich Doerfler",
    "wof:placetype":"venue"
},
  "geometry": {"coordinates":[11.5714063644,48.1290130615],"type":"Point"}
}