{
  "type": "Feature",
  "properties": {
    "iso:country":"DE",
    "sg:address":"Hag\u00e4cker 10",
    "sg:city":"Allmendingen",
    "sg:postcode":"89604",
    "sg:province":"Baden-W\u00fcrttemberg",
    "wof:name":"Tauer Forst Gmbh",
    "wof:placetype":"venue"
},
  "geometry": {"coordinates":[9.6693487167,48.352771759],"type":"Point"}
}