{
  "type": "Feature",
  "properties": {
    "iso:country":"DE",
    "sg:address":"Langenbernsdorfer Str. 1",
    "sg:city":"Leubnitz",
    "sg:phone":"+49 3761/75216",
    "sg:postcode":"08412",
    "sg:province":"Sachsen",
    "wof:name":"Wolf Geb\u00e4ude- Und Textilreinigungs Gmbh",
    "wof:placetype":"venue"
},
  "geometry": {"coordinates":[12.37106,50.731152],"type":"Point"}
}