{
  "type": "Feature",
  "properties": {
    "iso:country":"DE",
    "sg:address":"Gerhart-Hauptmann-Str. 37",
    "sg:city":"Bopfingen",
    "sg:phone":"+49 7362/4289",
    "sg:postcode":"73441",
    "sg:province":"Baden-W\u00fcrttemberg",
    "wof:name":"Rudi Liebh\u00e4user",
    "wof:placetype":"venue"
},
  "geometry": {"coordinates":[10.3472661972,48.8519668579],"type":"Point"}
}