{
  "type": "Feature",
  "properties": {
    "iso:country":"DE",
    "sg:address":"Dollenschlucht 14",
    "sg:city":"Meschede",
    "sg:phone":"+49 291/59955",
    "sg:postcode":"59872",
    "sg:province":"Nordrhein-Westfalen",
    "wof:name":"Bernd Sch\u00fcttler",
    "wof:placetype":"venue"
},
  "geometry": {"coordinates":[8.3341369629,51.3671073914],"type":"Point"}
}