{
  "type": "Feature",
  "properties": {
    "iso:country":"DE",
    "sg:address":"Lanterdingerstr. 1 c",
    "sg:city":"M\u00fchldorf",
    "sg:phone":"+49 8631/8427",
    "sg:postcode":"84453",
    "sg:province":"Bayern",
    "wof:name":"Karl-heinz Resch",
    "wof:placetype":"venue"
},
  "geometry": {"coordinates":[12.5204772949,48.2666511536],"type":"Point"}
}