{
  "type": "Feature",
  "properties": {
    "iso:country":"DE",
    "sg:address":"Marktplatz 1",
    "sg:city":"Lohr",
    "sg:phone":"+49 9352/9011",
    "sg:postcode":"97816",
    "sg:province":"Bayern",
    "wof:name":"St\u00e4dtisches Wasserwerk",
    "wof:placetype":"venue"
},
  "geometry": {"coordinates":[9.5741071701,49.9947471619],"type":"Point"}
}