{
  "type": "Feature",
  "properties": {
    "iso:country":"DE",
    "sg:address":"Marienplatz 11",
    "sg:city":"Gro\u00dfmehring",
    "sg:phone":"+49 8407/237",
    "sg:postcode":"85098",
    "sg:province":"Bayern",
    "wof:name":"Karl Grauvogl",
    "wof:placetype":"venue"
},
  "geometry": {"coordinates":[11.53425,48.765308],"type":"Point"}
}