{
  "type": "Feature",
  "properties": {
    "iso:country":"DE",
    "sg:address":"Marktstr. 37",
    "sg:city":"Wegscheid",
    "sg:phone":"+49 8592/261",
    "sg:postcode":"94110",
    "sg:province":"Bayern",
    "wof:name":"Josef Irl",
    "wof:placetype":"venue"
},
  "geometry": {"coordinates":[13.79048,48.601543],"type":"Point"}
}