{
  "type": "Feature",
  "properties": {
    "iso:country":"DE",
    "sg:address":"D\u00f6belner Str. 24",
    "sg:city":"Nossen",
    "sg:phone":"+49 35242/67731",
    "sg:postcode":"01683",
    "sg:province":"Sachsen",
    "wof:name":"B\u00c4ckereimaschinen Und Anlagenbau Nossen",
    "wof:placetype":"venue"
},
  "geometry": {"coordinates":[13.288575,51.063137],"type":"Point"}
}