{
  "type": "Feature",
  "properties": {
    "iso:country":"DE",
    "sg:address":"Frankfurter Str. 82",
    "sg:city":"L\u00fcbben",
    "sg:phone":"+49 3546/27240",
    "sg:postcode":"15907",
    "sg:province":"Brandenburg",
    "wof:name":"Autow\u00e4sche E. Liebsch Gmbh",
    "wof:placetype":"venue"
},
  "geometry": {"coordinates":[13.91976,51.94997],"type":"Point"}
}