{
  "type": "Feature",
  "properties": {
    "iso:country":"DE",
    "sg:address":"Ottilienbergweg 1",
    "sg:city":"Schorndorf",
    "sg:phone":"+49 7181/935350",
    "sg:postcode":"73614",
    "sg:province":"Baden-W\u00fcrttemberg",
    "wof:name":"Wolfgang Sieg Ingenieur",
    "wof:placetype":"venue"
},
  "geometry": {"coordinates":[9.5273351669,48.7952003479],"type":"Point"}
}