{
  "type": "Feature",
  "properties": {
    "iso:country":"DE",
    "sg:address":"Friedrichsplatz 1-3",
    "sg:city":"Karlsruhe",
    "sg:postcode":"76133",
    "sg:province":"Baden-W\u00fcrttemberg",
    "wof:name":"Emil-wachter-stiftung",
    "wof:placetype":"venue"
},
  "geometry": {"coordinates":[8.4007577896,49.0087013245],"type":"Point"}
}