{
  "type": "Feature",
  "properties": {
    "iso:country":"DE",
    "sg:address":"Gro\u00dfseelheimer Str. 26",
    "sg:city":"Marburg",
    "sg:phone":"+49 6421/42801",
    "sg:postcode":"35039",
    "sg:province":"Hessen",
    "wof:name":"Newice Deutschland Gmbh",
    "wof:placetype":"venue"
},
  "geometry": {"coordinates":[8.7754383087,50.7979621887],"type":"Point"}
}