{
  "type": "Feature",
  "properties": {
    "iso:country":"DE",
    "sg:address":"Saatwinkler Damm 42",
    "sg:city":"Berlin",
    "sg:postcode":"13627",
    "sg:province":"Berlin",
    "wof:name":"Wohnanlage Leipzig Dr. Neuling Gmbh & Co. Kg",
    "wof:placetype":"venue"
},
  "geometry": {"coordinates":[13.318341,52.546352],"type":"Point"}
}