{
  "type": "Feature",
  "properties": {
    "iso:country":"DE",
    "sg:address":"Ziethenstr. 13a",
    "sg:city":"Hamburg",
    "sg:phone":"+49 40/6565607",
    "sg:postcode":"22041",
    "sg:province":"Hamburg",
    "wof:name":"Media Und Promotion Werbeagentur Und Verlag",
    "wof:placetype":"venue"
},
  "geometry": {"coordinates":[10.0986366272,53.5761680603],"type":"Point"}
}