{
  "type": "Feature",
  "properties": {
    "iso:country":"DE",
    "sg:address":"Am Hehsel 40",
    "sg:city":"Hamburg",
    "sg:phone":"+49 40/5389940",
    "sg:postcode":"22339",
    "sg:province":"Hamburg",
    "wof:name":"Cas Concepts And Solutions Ag",
    "wof:placetype":"venue"
},
  "geometry": {"coordinates":[10.0580759048,53.6462554932],"type":"Point"}
}