{
  "type": "Feature",
  "properties": {
    "iso:country":"DE",
    "sg:address":"Lobensteiner Str. 49",
    "sg:city":"Nordhalben",
    "sg:phone":"+49 9267/1716",
    "sg:postcode":"96365",
    "sg:province":"Bayern",
    "wof:name":"M. G\u00f6ring",
    "wof:placetype":"venue"
},
  "geometry": {"coordinates":[11.5067329407,50.3773612976],"type":"Point"}
}