{
  "type": "Feature",
  "properties": {
    "iso:country":"DE",
    "sg:address":"Dieselstr. 10",
    "sg:city":"Peine",
    "sg:postcode":"31228",
    "sg:province":"Niedersachsen",
    "wof:name":"Praktiker Bau- Und Heimwerkermarkt",
    "wof:placetype":"venue"
},
  "geometry": {"coordinates":[10.2454662323,52.3382720947],"type":"Point"}
}