{
  "type": "Feature",
  "properties": {
    "iso:country":"DE",
    "sg:address":"Im Albsgarten 3",
    "sg:city":"Rauschenberg",
    "sg:phone":"+49 6427/2818",
    "sg:postcode":"35282",
    "sg:province":"Hessen",
    "wof:name":"K. Klein Ingenieur",
    "wof:placetype":"venue"
},
  "geometry": {"coordinates":[8.852435112,50.9204139709],"type":"Point"}
}