{
  "type": "Feature",
  "properties": {
    "iso:country":"DE",
    "sg:address":"Hornschuchallee 6-8",
    "sg:city":"Forchheim",
    "sg:phone":"+49 9191/2392",
    "sg:postcode":"91301",
    "sg:province":"Bayern",
    "wof:name":"Franz G\u00fcrtler's Buchdruckerei Gmbh",
    "wof:placetype":"venue"
},
  "geometry": {"coordinates":[11.058897,49.720615],"type":"Point"}
}