{
  "type": "Feature",
  "properties": {
    "iso:country":"DE",
    "sg:address":"Sportfeldstr. 13",
    "sg:city":"Siegsdorf",
    "sg:phone":"+49 8662/2386",
    "sg:postcode":"83313",
    "sg:province":"Bayern",
    "wof:name":"Gertrud Vetter",
    "wof:placetype":"venue"
},
  "geometry": {"coordinates":[12.64448,47.825748],"type":"Point"}
}