{
  "type": "Feature",
  "properties": {
    "iso:country":"DE",
    "sg:address":"Wienburgstrasse 16",
    "sg:city":"M\u00fcnster",
    "sg:postcode":"48147",
    "sg:province":"Nordrhein-Westfalen",
    "wof:name":"Supervisionspraxis",
    "wof:placetype":"venue"
},
  "geometry": {"coordinates":[7.623494,51.973785],"type":"Point"}
}