{
  "type": "Feature",
  "properties": {
    "iso:country":"DE",
    "sg:address":"Nibelungenring 62-64",
    "sg:city":"Worms",
    "sg:postcode":"67547",
    "sg:province":"Rheinland-Pfalz",
    "wof:name":"K\u00e4uffer Haustechnik Gmbh",
    "wof:placetype":"venue"
},
  "geometry": {"coordinates":[8.370981,49.63694],"type":"Point"}
}