{
  "type": "Feature",
  "properties": {
    "iso:country":"DE",
    "sg:address":"Laaberstr. 2",
    "sg:city":"Dingolfing",
    "sg:phone":"+49 8731/7030",
    "sg:postcode":"84130",
    "sg:province":"Bayern",
    "wof:name":"W\u00e4lischmiller Druck Und Verlags Gmbh",
    "wof:placetype":"venue"
},
  "geometry": {"coordinates":[12.488243103,48.638458252],"type":"Point"}
}