{
  "type": "Feature",
  "properties": {
    "iso:country":"DE",
    "sg:address":"Pappelstr. 34",
    "sg:city":"Hagen",
    "sg:phone":"+49 2331/64746",
    "sg:postcode":"58099",
    "sg:province":"Nordrhein-Westfalen",
    "wof:name":"Ch. Melzer Masseurin",
    "wof:placetype":"venue"
},
  "geometry": {"coordinates":[7.480156,51.390903],"type":"Point"}
}