{
  "type": "Feature",
  "properties": {
    "iso:country":"DE",
    "sg:address":"Eckendorfer Str. 41",
    "sg:city":"Bielefeld",
    "sg:postcode":"33609",
    "sg:province":"Nordrhein-Westfalen",
    "wof:name":"Kowatsch Maschinenbau Gmbh",
    "wof:placetype":"venue"
},
  "geometry": {"coordinates":[8.55733,52.033546],"type":"Point"}
}