{
  "type": "Feature",
  "properties": {
    "iso:country":"DE",
    "sg:address":"Wasserhohl 1",
    "sg:city":"Bad D\u00fcrkheim",
    "sg:postcode":"67098",
    "sg:province":"Rheinland-Pfalz",
    "wof:name":"Omp Immobilien",
    "wof:placetype":"venue"
},
  "geometry": {"coordinates":[8.171462059,49.4612388611],"type":"Point"}
}