{
  "type": "Feature",
  "properties": {
    "iso:country":"DE",
    "sg:address":"Beethovenstr. 24",
    "sg:city":"Recklinghausen",
    "sg:phone":"+49 2361/29659",
    "sg:postcode":"45657",
    "sg:province":"Nordrhein-Westfalen",
    "wof:name":"Hedwig J\u00f6hren Steuerberaterin",
    "wof:placetype":"venue"
},
  "geometry": {"coordinates":[7.1977372169,51.624042511],"type":"Point"}
}