{
  "type": "Feature",
  "properties": {
    "iso:country":"DE",
    "sg:address":"Drei-Mohren-Str. 2",
    "sg:city":"Regensburg",
    "sg:phone":"+49 941/53962",
    "sg:postcode":"93047",
    "sg:province":"Bayern",
    "wof:name":"Blumen-erika",
    "wof:placetype":"venue"
},
  "geometry": {"coordinates":[12.090173,49.019596],"type":"Point"}
}