{
  "type": "Feature",
  "properties": {
    "iso:country":"DE",
    "sg:address":"J\u00fclicher Str. 4",
    "sg:city":"Berlin",
    "sg:phone":"+49 30/4936223",
    "sg:postcode":"13357",
    "sg:province":"Berlin",
    "wof:name":"Bauernstube",
    "wof:placetype":"venue"
},
  "geometry": {"coordinates":[13.3918609619,52.5534591675],"type":"Point"}
}