{
  "type": "Feature",
  "properties": {
    "iso:country":"DE",
    "sg:address":"Martin-Luther-Str. 2",
    "sg:city":"Altenburg",
    "sg:phone":"+49 3447",
    "sg:postcode":"04600",
    "sg:province":"Th\u00fcringen",
    "wof:name":"Landkreis Leipziger Land",
    "wof:placetype":"venue"
},
  "geometry": {"coordinates":[12.4298744202,50.9881973267],"type":"Point"}
}