{
  "type": "Feature",
  "properties": {
    "iso:country":"DE",
    "sg:address":"Dresselsteg",
    "sg:city":"Berlin",
    "sg:phone":"+49 30/32602710",
    "sg:postcode":"14057",
    "sg:province":"Berlin",
    "wof:name":"Odysseus Projektentwicklungs Gmbh",
    "wof:placetype":"venue"
},
  "geometry": {"coordinates":[13.284131,52.508781],"type":"Point"}
}