{
  "type": "Feature",
  "properties": {
    "iso:country":"DE",
    "sg:address":"Wilhelm-Schussen-Str. 9",
    "sg:city":"Bad Schussenried",
    "sg:postcode":"88427",
    "sg:province":"Baden-W\u00fcrttemberg",
    "wof:name":"B\u00e4ckerei Usenbenz Gmbh",
    "wof:placetype":"venue"
},
  "geometry": {"coordinates":[9.657974,48.003853],"type":"Point"}
}