{
  "type": "Feature",
  "properties": {
    "iso:country":"DE",
    "sg:address":"Schlachthofstr. 4",
    "sg:city":"Bautzen",
    "sg:phone":"+49 3591/531550",
    "sg:postcode":"02625",
    "sg:province":"Sachsen",
    "wof:name":"Gewerbezentrum Bautzen Eg",
    "wof:placetype":"venue"
},
  "geometry": {"coordinates":[14.436688,51.170628],"type":"Point"}
}