{
  "type": "Feature",
  "properties": {
    "iso:country":"DE",
    "sg:address":"Hohle Str. 5",
    "sg:city":"Br\u00fcggen",
    "sg:phone":"+49 5182/2415",
    "sg:postcode":"31033",
    "sg:province":"Niedersachsen",
    "wof:name":"Herbert Plate",
    "wof:placetype":"venue"
},
  "geometry": {"coordinates":[9.779645,52.041485],"type":"Point"}
}