{
  "type": "Feature",
  "properties": {
    "iso:country":"DE",
    "sg:address":"Marienberger Str. 42",
    "sg:city":"Wolkenstein",
    "sg:phone":"+49 37369/9548",
    "sg:postcode":"09429",
    "sg:province":"Sachsen",
    "wof:name":"Dach Gmbh Scheiter",
    "wof:placetype":"venue"
},
  "geometry": {"coordinates":[13.072325,50.655544],"type":"Point"}
}