{
  "type": "Feature",
  "properties": {
    "iso:country":"DE",
    "sg:address":"Stadionstr. 5 a",
    "sg:city":"Rheinau",
    "sg:phone":"+49 7844/1357",
    "sg:postcode":"77866",
    "sg:province":"Baden-W\u00fcrttemberg",
    "wof:name":"Werner Kern",
    "wof:placetype":"venue"
},
  "geometry": {"coordinates":[7.9390702248,48.6629142761],"type":"Point"}
}