{
  "type": "Feature",
  "properties": {
    "iso:country":"DE",
    "sg:address":"Auf dem Winkel 34",
    "sg:city":"Bad Zwischenahn",
    "sg:phone":"+49 4403/93810",
    "sg:postcode":"26160",
    "sg:province":"Niedersachsen",
    "wof:name":"Joachim Pschak Steuerberater",
    "wof:placetype":"venue"
},
  "geometry": {"coordinates":[8.0156173706,53.1817550659],"type":"Point"}
}