{
  "type": "Feature",
  "properties": {
    "iso:country":"DE",
    "sg:address":"Wiesengrund 4",
    "sg:city":"K\u00fchren-Burkartshain",
    "sg:phone":"+49 34261/61895",
    "sg:postcode":"04808",
    "sg:province":"Sachsen",
    "wof:name":"Alexander Weinhold",
    "wof:placetype":"venue"
},
  "geometry": {"coordinates":[12.7918653488,51.3923568726],"type":"Point"}
}