{
  "type": "Feature",
  "properties": {
    "iso:country":"DE",
    "sg:address":"Vogelsand 56",
    "sg:city":"Cuxhaven",
    "sg:phone":"+49 4721/47992",
    "sg:postcode":"27476",
    "sg:province":"Niedersachsen",
    "wof:name":"Independent Marine Consultants & Surveyors Germany Gmbh",
    "wof:placetype":"venue"
},
  "geometry": {"coordinates":[8.6688346863,53.8866996765],"type":"Point"}
}