{
  "type": "Feature",
  "properties": {
    "iso:country":"DE",
    "sg:address":"Amselweg 46",
    "sg:city":"Gerlingen",
    "sg:phone":"+49 7156/43160",
    "sg:postcode":"70839",
    "sg:province":"Baden-W\u00fcrttemberg",
    "wof:name":"Jenbacher Werke- Vertriebsges. Mbh",
    "wof:placetype":"venue"
},
  "geometry": {"coordinates":[9.06005,48.787708],"type":"Point"}
}