{
  "type": "Feature",
  "properties": {
    "iso:country":"DE",
    "sg:address":"Sulzbacher Str. 6",
    "sg:city":"Hahnbach",
    "sg:phone":"+49 9664/1042",
    "sg:postcode":"92256",
    "sg:province":"Bayern",
    "wof:name":"Sony-play",
    "wof:placetype":"venue"
},
  "geometry": {"coordinates":[11.7965736389,49.5321731567],"type":"Point"}
}