{
  "type": "Feature",
  "properties": {
    "iso:country":"DE",
    "sg:address":"Lauensteiner Str. 13",
    "sg:city":"Ludwigsstadt",
    "sg:phone":"+49 9263/258",
    "sg:postcode":"96337",
    "sg:province":"Bayern",
    "wof:name":"Heinrich Bergner",
    "wof:placetype":"venue"
},
  "geometry": {"coordinates":[11.387884,50.486244],"type":"Point"}
}