{
  "type": "Feature",
  "properties": {
    "iso:country":"DE",
    "sg:address":"Fernblick 3",
    "sg:city":"Essen",
    "sg:postcode":"45259",
    "sg:province":"Nordrhein-Westfalen",
    "wof:name":"M2o Handel Gmbh",
    "wof:placetype":"venue"
},
  "geometry": {"coordinates":[7.0584249496,51.4086265564],"type":"Point"}
}