{
  "type": "Feature",
  "properties": {
    "iso:country":"DE",
    "sg:address":"Hailerstrasse 13",
    "sg:city":"Karlsbad-Auerbach",
    "sg:phone":"+49 7202/7205",
    "sg:postcode":"76307",
    "sg:province":"Baden-W\u00fcrttemberg",
    "wof:name":"Elvira Schmuck Gerhard Heinzelmann",
    "wof:placetype":"venue"
},
  "geometry": {"coordinates":[8.5298643112,48.9110069275],"type":"Point"}
}