{
  "type": "Feature",
  "properties": {
    "iso:country":"DE",
    "sg:address":"Andersenstr. 15",
    "sg:city":"Karlsruhe",
    "sg:postcode":"76199",
    "sg:province":"Baden-W\u00fcrttemberg",
    "wof:name":"Christliche Lebensberatung",
    "wof:placetype":"venue"
},
  "geometry": {"coordinates":[8.419301,48.9697],"type":"Point"}
}