{
  "type": "Feature",
  "properties": {
    "iso:country":"DE",
    "sg:address":"Buschkoppel 5",
    "sg:city":"Bornh\u00f6ved",
    "sg:phone":"+49 4323/6473",
    "sg:postcode":"24619",
    "sg:province":"Schleswig-Holstein",
    "wof:name":"Manfred Schr\u00f6der",
    "wof:placetype":"venue"
},
  "geometry": {"coordinates":[10.237111,54.065784],"type":"Point"}
}