{
  "type": "Feature",
  "properties": {
    "iso:country":"DE",
    "sg:address":"Holdersbach 11",
    "sg:city":"Rottweil",
    "sg:phone":"+49 741/13442",
    "sg:postcode":"78628",
    "sg:province":"Baden-W\u00fcrttemberg",
    "wof:name":"Initiative Dritte Welt E. V. Gottfried Gestrich-g\u00e4rtner",
    "wof:placetype":"venue"
},
  "geometry": {"coordinates":[8.6370019913,48.1539077759],"type":"Point"}
}