{
  "type": "Feature",
  "properties": {
    "iso:country":"DE",
    "sg:address":"Dannergasse 13",
    "sg:city":"Schallstadt",
    "sg:phone":"+49 7664/7597",
    "sg:postcode":"79227",
    "sg:province":"Baden-W\u00fcrttemberg",
    "wof:name":"J\u00f6rg Hanser",
    "wof:placetype":"venue"
},
  "geometry": {"coordinates":[7.7464280128,47.956577301],"type":"Point"}
}