{
  "type": "Feature",
  "properties": {
    "iso:country":"DE",
    "sg:address":"Lechfelderstr 18",
    "sg:city":"Graben",
    "sg:phone":"+49 8232/74036",
    "sg:postcode":"86836",
    "sg:province":"Bayern",
    "wof:name":"Raiffeisenbank Schwabm\u00fcnchen Eg",
    "wof:placetype":"venue"
},
  "geometry": {"coordinates":[10.823693,48.188362],"type":"Point"}
}