{
  "type": "Feature",
  "properties": {
    "iso:country":"DE",
    "sg:address":"Altentr\u00fcdingen 34",
    "sg:city":"Wassertr\u00fcdingen",
    "sg:phone":"+49 9832/1779",
    "sg:postcode":"91717",
    "sg:province":"Bayern",
    "wof:name":"Emma Ebert",
    "wof:placetype":"venue"
},
  "geometry": {"coordinates":[10.6206798553,49.0620689392],"type":"Point"}
}