{
  "type": "Feature",
  "properties": {
    "iso:country":"DE",
    "sg:address":"Bunsenstr. 22",
    "sg:city":"B\u00f6blingen",
    "sg:phone":"+49 7031/21600",
    "sg:postcode":"71032",
    "sg:province":"Baden-W\u00fcrttemberg",
    "wof:name":"Willi Hug",
    "wof:placetype":"venue"
},
  "geometry": {"coordinates":[9.0187854767,48.6892471313],"type":"Point"}
}