{
  "type": "Feature",
  "properties": {
    "iso:country":"DE",
    "sg:address":"Schattbucher Str 11",
    "sg:city":"Amtzell",
    "sg:phone":"+49 7520/96610",
    "sg:postcode":"88279",
    "sg:province":"Baden-W\u00fcrttemberg",
    "wof:name":"Hans-j\u00fcrgen Schnell Anlagenbau",
    "wof:placetype":"venue"
},
  "geometry": {"coordinates":[9.754859,47.696377],"type":"Point"}
}