{
  "type": "Feature",
  "properties": {
    "iso:country":"DE",
    "sg:address":"Katrepeler Landstr. 19",
    "sg:city":"Bremen",
    "sg:phone":"+49 421/270289",
    "sg:postcode":"28357",
    "sg:province":"Bremen",
    "wof:name":"Fritz Patzer",
    "wof:placetype":"venue"
},
  "geometry": {"coordinates":[8.91769,53.121861],"type":"Point"}
}