{
  "type": "Feature",
  "properties": {
    "iso:country":"DE",
    "sg:address":"Paffrather Str. 132",
    "sg:city":"Bergisch Gladbach",
    "sg:phone":"+49 2202/21393",
    "sg:postcode":"51465",
    "sg:province":"Nordrhein-Westfalen",
    "wof:name":"H. Riedel",
    "wof:placetype":"venue"
},
  "geometry": {"coordinates":[7.1181907654,50.9946746826],"type":"Point"}
}