{
  "type": "Feature",
  "properties": {
    "iso:country":"DE",
    "sg:address":"Offenbacher Landstr. 185",
    "sg:city":"Frankfurt",
    "sg:phone":"+49 69/628721",
    "sg:postcode":"60599",
    "sg:province":"Hessen",
    "wof:name":"Dr. Christiane Hoffmann Rechtsanw\u00e4ltin",
    "wof:placetype":"venue"
},
  "geometry": {"coordinates":[8.7051362991,50.0991477966],"type":"Point"}
}