{
  "type": "Feature",
  "properties": {
    "iso:country":"DE",
    "sg:address":"Schwarzenb\u00f6rner Str. 17",
    "sg:city":"Frielendorf",
    "sg:phone":"+49 6691/50448",
    "sg:postcode":"34621",
    "sg:province":"Hessen",
    "wof:name":"G\u00e4stehaus W. Krebs",
    "wof:placetype":"venue"
},
  "geometry": {"coordinates":[9.3023052216,50.9182701111],"type":"Point"}
}