{
  "type": "Feature",
  "properties": {
    "iso:country":"DE",
    "sg:address":"Lohweg 2",
    "sg:city":"Sengenthal",
    "sg:phone":"+49 9181/4060",
    "sg:postcode":"92369",
    "sg:province":"Bayern",
    "wof:name":"Iksys Gesellschaft F\u00fcr Innova- Tive Kommunikationssysteme",
    "wof:placetype":"venue"
},
  "geometry": {"coordinates":[11.421614,49.229176],"type":"Point"}
}