{
  "type": "Feature",
  "properties": {
    "iso:country":"DE",
    "sg:address":"Amtsstr. 8",
    "sg:city":"Zarrentin",
    "sg:phone":"+49 38851/25769",
    "sg:postcode":"19246",
    "sg:province":"Mecklenburg-Vorpommern",
    "wof:name":"Restaurant Bier Linden",
    "wof:placetype":"venue"
},
  "geometry": {"coordinates":[10.9169301987,53.5533676147],"type":"Point"}
}