{
  "type": "Feature",
  "properties": {
    "iso:country":"DE",
    "sg:address":"Robert-Bosch-Str. 2",
    "sg:city":"Mendig",
    "sg:postcode":"56743",
    "sg:province":"Rheinland-Pfalz",
    "wof:name":"Haller Gmbh",
    "wof:placetype":"venue"
},
  "geometry": {"coordinates":[7.296834,50.367027],"type":"Point"}
}