{
  "type": "Feature",
  "properties": {
    "iso:country":"DE",
    "sg:address":"Hunsr\u00fcckstr. 2",
    "sg:city":"Losheim",
    "sg:phone":"+49 6872/5344",
    "sg:postcode":"66679",
    "sg:province":"Saarland",
    "wof:name":"Restaurante-pizzeria Capri",
    "wof:placetype":"venue"
},
  "geometry": {"coordinates":[6.7409558296,49.5110282898],"type":"Point"}
}