{
  "type": "Feature",
  "properties": {
    "iso:country":"DE",
    "sg:address":"Klugstr. 84",
    "sg:city":"M\u00fcnchen",
    "sg:phone":"+49 89/156786",
    "sg:postcode":"80638",
    "sg:province":"Bayern",
    "wof:name":"Friedrich Steigenberger Architekten",
    "wof:placetype":"venue"
},
  "geometry": {"coordinates":[11.527682,48.163673],"type":"Point"}
}