{
  "type": "Feature",
  "properties": {
    "iso:country":"DE",
    "sg:address":"Louis-Seegelken-Str. 28",
    "sg:city":"Bremen",
    "sg:phone":"+49 421/631385",
    "sg:postcode":"28717",
    "sg:province":"Bremen",
    "wof:name":"K. Arfmann Lebensmittel",
    "wof:placetype":"venue"
},
  "geometry": {"coordinates":[8.6884937286,53.1709213257],"type":"Point"}
}