{
  "type": "Feature",
  "properties": {
    "iso:country":"DE",
    "sg:address":"Bierstr. 18",
    "sg:city":"Saarlouis",
    "sg:phone":"+49 6831/40363",
    "sg:postcode":"66740",
    "sg:province":"Saarland",
    "wof:name":"Office",
    "wof:placetype":"venue"
},
  "geometry": {"coordinates":[6.7503700256,49.3137741089],"type":"Point"}
}