{
  "type": "Feature",
  "properties": {
    "iso:country":"DE",
    "sg:address":"Lange Str. 9",
    "sg:city":"Zeven",
    "sg:phone":"+49 4281/950695",
    "sg:postcode":"27404",
    "sg:province":"Niedersachsen",
    "wof:name":"Foto-krauskopf Gmbh & Co. Kg",
    "wof:placetype":"venue"
},
  "geometry": {"coordinates":[9.278588295,53.2942237854],"type":"Point"}
}