{
  "type": "Feature",
  "properties": {
    "iso:country":"DE",
    "sg:address":"Bergstr. 12",
    "sg:city":"H\u00f6hr-Grenzhausen",
    "sg:phone":"+49 2624/94090",
    "sg:postcode":"56203",
    "sg:province":"Rheinland-Pfalz",
    "wof:name":"Sozialstation Ahz Der Johanniter",
    "wof:placetype":"venue"
},
  "geometry": {"coordinates":[7.676069,50.432232],"type":"Point"}
}