{
  "type": "Feature",
  "properties": {
    "iso:country":"DE",
    "sg:address":"Dieskaustr. 259",
    "sg:city":"Leipzig",
    "sg:phone":"+49 341/4251670",
    "sg:postcode":"04249",
    "sg:province":"Sachsen",
    "wof:name":"Dirk Le\u00dfner",
    "wof:placetype":"venue"
},
  "geometry": {"coordinates":[12.3240242004,51.295791626],"type":"Point"}
}