{
  "type": "Feature",
  "properties": {
    "iso:country":"DE",
    "sg:address":"Klopstockstr. 50::",
    "sg:city":"Dresden",
    "sg:phone":"+49 4935/1423070",
    "sg:postcode":"01157",
    "sg:province":"Sachsen",
    "wof:name":"Disko Leasing Dresden Gmbh",
    "wof:placetype":"venue"
},
  "geometry": {"coordinates":[13.690007,51.049801],"type":"Point"}
}