{
  "type": "Feature",
  "properties": {
    "iso:country":"DE",
    "sg:address":"Gartenstr. 26",
    "sg:city":"Pirna",
    "sg:phone":"+49 3501/447438",
    "sg:postcode":"01796",
    "sg:province":"Sachsen",
    "wof:name":"Bestattungshaus W. Billing Gmbh",
    "wof:placetype":"venue"
},
  "geometry": {"coordinates":[13.933324,50.96207],"type":"Point"}
}