{
  "type": "Feature",
  "properties": {
    "iso:country":"DE",
    "sg:address":"Enztalstr. 13a",
    "sg:city":"Mettendorf",
    "sg:phone":"+49 6522/93020",
    "sg:postcode":"54675",
    "sg:province":"Rheinland-Pfalz",
    "wof:name":"Provinzial Versicherungsanstalten",
    "wof:placetype":"venue"
},
  "geometry": {"coordinates":[6.3324260712,49.9455833435],"type":"Point"}
}