{
  "type": "Feature",
  "properties": {
    "iso:country":"DE",
    "sg:address":"R.-Luxemburg Strasse 20",
    "sg:city":"Schwarzheide",
    "sg:phone":"+49 35752/77277",
    "sg:postcode":"01987",
    "sg:province":"Brandenburg",
    "wof:name":"Bmi Webdesign Schwarzheide",
    "wof:placetype":"venue"
},
  "geometry": {"coordinates":[13.8562316895,51.478515625],"type":"Point"}
}