{
  "type": "Feature",
  "properties": {
    "iso:country":"DE",
    "sg:address":"Pfarrstr. 13",
    "sg:city":"Eppishausen",
    "sg:postcode":"87745",
    "sg:province":"Bayern",
    "wof:name":"Kath. \u00f6ffentl. B\u00fccherei Haselbach",
    "wof:placetype":"venue"
},
  "geometry": {"coordinates":[10.510489,48.201591],"type":"Point"}
}