{
  "type": "Feature",
  "properties": {
    "iso:country":"DE",
    "sg:address":"Hornstr. 6",
    "sg:city":"Regensburg",
    "sg:phone":"+49 941/76300",
    "sg:postcode":"93053",
    "sg:province":"Bayern",
    "wof:name":"A. Str\u00f6bl",
    "wof:placetype":"venue"
},
  "geometry": {"coordinates":[12.114413,49.005955],"type":"Point"}
}