{
  "type": "Feature",
  "properties": {
    "iso:country":"DE",
    "sg:address":"Rosenstr. 6",
    "sg:city":"Heimsheim",
    "sg:phone":"+49 7033/390519",
    "sg:postcode":"71296",
    "sg:province":"Baden-W\u00fcrttemberg",
    "wof:name":"Magra Gmbh",
    "wof:placetype":"venue"
},
  "geometry": {"coordinates":[8.865678,48.809216],"type":"Point"}
}