{
  "type": "Feature",
  "properties": {
    "iso:country":"DE",
    "sg:address":"Birkenhain 1",
    "sg:city":"Wettringen",
    "sg:phone":"+49 5973/2110",
    "sg:postcode":"48493",
    "sg:province":"Nordrhein-Westfalen",
    "wof:name":"H. B\u00e4umer",
    "wof:placetype":"venue"
},
  "geometry": {"coordinates":[7.3289680481,52.27684021],"type":"Point"}
}