{
  "type": "Feature",
  "properties": {
    "iso:country":"DE",
    "sg:address":"Sch\u00f6nbergstr. 64",
    "sg:city":"Dresden",
    "sg:phone":"+49 351/2816520",
    "sg:postcode":"01239",
    "sg:province":"Sachsen",
    "wof:name":"Ulrike R\u00fcger Rechtsanw\u00e4ltin",
    "wof:placetype":"venue"
},
  "geometry": {"coordinates":[13.7850847244,51.0017204285],"type":"Point"}
}