{
  "type": "Feature",
  "properties": {
    "iso:country":"DE",
    "sg:address":"Sch\u00f6nberger Str. 6",
    "sg:city":"Sch\u00f6nberg",
    "sg:phone":"+49 8554/2936",
    "sg:postcode":"94513",
    "sg:province":"Bayern",
    "wof:name":"Schlo\u00dfwirt",
    "wof:placetype":"venue"
},
  "geometry": {"coordinates":[13.3572244644,48.8208389282],"type":"Point"}
}