{
  "type": "Feature",
  "properties": {
    "iso:country":"DE",
    "sg:address":"Hochstr. 62",
    "sg:city":"Gelsenkirchen",
    "sg:phone":"+49 209/30091",
    "sg:postcode":"45894",
    "sg:province":"Nordrhein-Westfalen",
    "wof:name":"Heinrich Wimmers",
    "wof:placetype":"venue"
},
  "geometry": {"coordinates":[7.0503849983,51.5801696777],"type":"Point"}
}