{
  "type": "Feature",
  "properties": {
    "iso:country":"DE",
    "sg:address":"Erich-K\u00e4stner-Str. 28",
    "sg:city":"Menden",
    "sg:phone":"+49 2373/81064",
    "sg:postcode":"58710",
    "sg:province":"Nordrhein-Westfalen",
    "wof:name":"Teunhof Gmbh",
    "wof:placetype":"venue"
},
  "geometry": {"coordinates":[7.8355197906,51.4194908142],"type":"Point"}
}