{
  "type": "Feature",
  "properties": {
    "iso:country":"DE",
    "sg:address":"Altenbach 9",
    "sg:city":"Thierhaupten",
    "sg:postcode":"86672",
    "sg:province":"Bayern",
    "wof:name":"Karl Meitinger",
    "wof:placetype":"venue"
},
  "geometry": {"coordinates":[10.9106826782,48.5638427734],"type":"Point"}
}