{
  "type": "Feature",
  "properties": {
    "iso:country":"DE",
    "sg:address":"Heimen 91 1-2",
    "sg:city":"Opfenbach",
    "sg:postcode":"88145",
    "sg:province":"Bayern",
    "wof:name":"Eko Gmbh",
    "wof:placetype":"venue"
},
  "geometry": {"coordinates":[9.8300247192,47.6492538452],"type":"Point"}
}