{
  "type": "Feature",
  "properties": {
    "iso:country":"DE",
    "sg:address":"St.-Stefan-Str. 51",
    "sg:city":"Aichach",
    "sg:phone":"+49 8251/819820",
    "sg:postcode":"86551",
    "sg:province":"Bayern",
    "wof:name":"Anton Siessmair Verwaltungs Gmbh",
    "wof:placetype":"venue"
},
  "geometry": {"coordinates":[11.0977859497,48.4177093506],"type":"Point"}
}