{
  "type": "Feature",
  "properties": {
    "iso:country":"DE",
    "sg:address":"Dorfstr. 6",
    "sg:city":"Marienheide",
    "sg:phone":"+49 2264/8455",
    "sg:postcode":"51709",
    "sg:province":"Nordrhein-Westfalen",
    "wof:name":"Willi Velbecker",
    "wof:placetype":"venue"
},
  "geometry": {"coordinates":[7.5014648438,51.0555267334],"type":"Point"}
}