{
  "type": "Feature",
  "properties": {
    "iso:country":"DE",
    "sg:address":"Seeburgstr. 39",
    "sg:city":"Berg",
    "sg:phone":"+49 8151/5410",
    "sg:postcode":"82335",
    "sg:province":"Bayern",
    "wof:name":"F. Petznik",
    "wof:placetype":"venue"
},
  "geometry": {"coordinates":[11.3381967545,47.9334144592],"type":"Point"}
}