{
  "type": "Feature",
  "properties": {
    "iso:country":"DE",
    "sg:address":"Schwarzwaldstr. 20",
    "sg:city":"St. Ingbert",
    "sg:phone":"+49 6894/52181",
    "sg:postcode":"66386",
    "sg:province":"Saarland",
    "wof:name":"Alwin Zimmermann",
    "wof:placetype":"venue"
},
  "geometry": {"coordinates":[7.1534981728,49.2786331177],"type":"Point"}
}