{
  "type": "Feature",
  "properties": {
    "iso:country":"DE",
    "sg:address":"\u00d6lkofer Str. 8",
    "sg:city":"Hohentengen",
    "sg:phone":"+49 7572/3214",
    "sg:postcode":"88367",
    "sg:province":"Baden-W\u00fcrttemberg",
    "wof:name":"Hans Rauch",
    "wof:placetype":"venue"
},
  "geometry": {"coordinates":[9.389373,48.035427],"type":"Point"}
}