{
  "type": "Feature",
  "properties": {
    "iso:country":"DE",
    "sg:address":"Kreyerner Str. 39",
    "sg:city":"Mei\u00dfen",
    "sg:phone":"+49 3521/738325",
    "sg:postcode":"01662",
    "sg:province":"Sachsen",
    "wof:name":"Hoffmann Motors Gmbh",
    "wof:placetype":"venue"
},
  "geometry": {"coordinates":[13.5101356506,51.1537322998],"type":"Point"}
}