{
  "type": "Feature",
  "properties": {
    "iso:country":"DE",
    "sg:address":"Gro\u00dfenhainer Str. 2",
    "sg:city":"Hirschfeld",
    "sg:phone":"+49 35343/61440",
    "sg:postcode":"04932",
    "sg:province":"Brandenburg",
    "wof:name":"Hirschfelder Stra\u00dfen- Und Tiefbau Gmbh",
    "wof:placetype":"venue"
},
  "geometry": {"coordinates":[13.6162128448,51.3867492676],"type":"Point"}
}