{
  "type": "Feature",
  "properties": {
    "iso:country":"DE",
    "sg:address":"Reichenhaller Str. 8",
    "sg:city":"M\u00fcnchen",
    "sg:phone":"+49 89/6225302",
    "sg:postcode":"81547",
    "sg:province":"Bayern",
    "wof:name":"Adria Verm\u00f6gensverwaltung Erich Ross Gmbh & Co. Kg",
    "wof:placetype":"venue"
},
  "geometry": {"coordinates":[11.572470665,48.1087150574],"type":"Point"}
}