{
  "type": "Feature",
  "properties": {
    "iso:country":"DE",
    "sg:address":"Ro\u00dfweide",
    "sg:city":"M\u00f6nchengladbach",
    "sg:phone":"+49 2166/57309",
    "sg:postcode":"41189",
    "sg:province":"Nordrhein-Westfalen",
    "wof:name":"Wickrather Hof",
    "wof:placetype":"venue"
},
  "geometry": {"coordinates":[6.4190378189,51.1327018738],"type":"Point"}
}