{
  "type": "Feature",
  "properties": {
    "iso:country":"DE",
    "sg:address":"Thomasstr. 9",
    "sg:city":"Darmstadt",
    "sg:phone":"+49 6151/595858",
    "sg:postcode":"64297",
    "sg:province":"Hessen",
    "wof:name":"Borger",
    "wof:placetype":"venue"
},
  "geometry": {"coordinates":[8.645209,49.821121],"type":"Point"}
}