{
  "type": "Feature",
  "properties": {
    "iso:country":"DE",
    "sg:address":"Hauptstr. 9",
    "sg:city":"Kehl",
    "sg:phone":"+49 7851/644",
    "sg:postcode":"77694",
    "sg:province":"Baden-W\u00fcrttemberg",
    "wof:name":"Internationales Reiseb\u00fcro Hugger & Reinwald",
    "wof:placetype":"venue"
},
  "geometry": {"coordinates":[7.8070731163,48.5749855042],"type":"Point"}
}