{
  "type": "Feature",
  "properties": {
    "iso:country":"DE",
    "sg:address":"Laurentiusberg 17",
    "sg:city":"Saarburg",
    "sg:phone":"+49 6581/2380",
    "sg:postcode":"54439",
    "sg:province":"Rheinland-Pfalz",
    "wof:name":"Walter Lauter",
    "wof:placetype":"venue"
},
  "geometry": {"coordinates":[6.5517988205,49.6075363159],"type":"Point"}
}