{
  "type": "Feature",
  "properties": {
    "iso:country":"DE",
    "sg:address":"Fronhofstr. 30",
    "sg:city":"W\u00fcrselen",
    "sg:phone":"+49 2405/48471",
    "sg:postcode":"52146",
    "sg:province":"Nordrhein-Westfalen",
    "wof:name":"Wefa-brot Gmbh",
    "wof:placetype":"venue"
},
  "geometry": {"coordinates":[6.18009,50.839401],"type":"Point"}
}