{
  "type": "Feature",
  "properties": {
    "iso:country":"DE",
    "sg:address":"Dreizehnmorgenweg 54",
    "sg:city":"Bonn",
    "sg:phone":"+49 228/9590035",
    "sg:postcode":"53175",
    "sg:province":"Nordrhein-Westfalen",
    "wof:name":"Hardt & Partner Marketing Gmbh",
    "wof:placetype":"venue"
},
  "geometry": {"coordinates":[7.1318860054,50.7038040161],"type":"Point"}
}