{
  "type": "Feature",
  "properties": {
    "iso:country":"DE",
    "sg:address":"Franz-Xaver-Stenzel-Str. 5",
    "sg:city":"Elzach",
    "sg:phone":"+49 7682/8802",
    "sg:postcode":"79215",
    "sg:province":"Baden-W\u00fcrttemberg",
    "wof:name":"Irene H\u00e4\u00dfler",
    "wof:placetype":"venue"
},
  "geometry": {"coordinates":[8.067588,48.173065],"type":"Point"}
}