{
  "type": "Feature",
  "properties": {
    "iso:country":"DE",
    "sg:address":"Bremer Str. 60",
    "sg:city":"M\u00fclheim",
    "sg:phone":"+49 208/422890",
    "sg:postcode":"45481",
    "sg:province":"Nordrhein-Westfalen",
    "wof:name":"Helmut Scheede Ingenieur",
    "wof:placetype":"venue"
},
  "geometry": {"coordinates":[6.8644161224,51.4124679565],"type":"Point"}
}