{
  "type": "Feature",
  "properties": {
    "iso:country":"DE",
    "sg:address":"Ausbau 1-2",
    "sg:city":"Wriezen",
    "sg:phone":"+49 33456/71686",
    "sg:postcode":"16269",
    "sg:province":"Brandenburg",
    "wof:name":"Stp Schulzendorfertierprodukte Gmbh",
    "wof:placetype":"venue"
},
  "geometry": {"coordinates":[14.109538,52.688488],"type":"Point"}
}