{
  "type": "Feature",
  "properties": {
    "iso:country":"DE",
    "sg:address":"Trierer Str. 10",
    "sg:city":"Bausendorf",
    "sg:phone":"+49 6532/4673",
    "sg:postcode":"54538",
    "sg:province":"Rheinland-Pfalz",
    "wof:name":"Trossen",
    "wof:placetype":"venue"
},
  "geometry": {"coordinates":[6.9952640533,50.0129966736],"type":"Point"}
}