{
  "type": "Feature",
  "properties": {
    "iso:country":"DE",
    "sg:address":"Schauinslandstr. 6",
    "sg:city":"Bad Krozingen",
    "sg:phone":"+49 7633/4915",
    "sg:postcode":"79189",
    "sg:province":"Baden-W\u00fcrttemberg",
    "wof:name":"Eugenie Reber Klaus Neugebauer",
    "wof:placetype":"venue"
},
  "geometry": {"coordinates":[7.7034158707,47.9149551392],"type":"Point"}
}