{
  "type": "Feature",
  "properties": {
    "iso:country":"DE",
    "sg:address":"Geschwister-Scholl-Str. 9",
    "sg:city":"M\u00fchlberg",
    "sg:phone":"+49 36256/20258",
    "sg:postcode":"99869",
    "sg:province":"Th\u00fcringen",
    "wof:name":"Kathrin Sch\u00f6nwaldt",
    "wof:placetype":"venue"
},
  "geometry": {"coordinates":[10.8257551193,50.8684654236],"type":"Point"}
}