{
  "type": "Feature",
  "properties": {
    "iso:country":"DE",
    "sg:address":"W\u00fcrzburger Str. 20",
    "sg:city":"Bremen",
    "sg:phone":"+49 421/370643",
    "sg:postcode":"28215",
    "sg:province":"Bremen",
    "wof:name":"Hans M\u00fcller",
    "wof:placetype":"venue"
},
  "geometry": {"coordinates":[8.800486,53.09222],"type":"Point"}
}