{
  "type": "Feature",
  "properties": {
    "iso:country":"DE",
    "sg:address":"Kiefernweg 14",
    "sg:city":"Gro\u00dfenkneten",
    "sg:postcode":"26197",
    "sg:province":"Niedersachsen",
    "wof:name":"Textilhaus Jestel Gmbh",
    "wof:placetype":"venue"
},
  "geometry": {"coordinates":[8.2488527298,52.9421310425],"type":"Point"}
}