{
  "type": "Feature",
  "properties": {
    "iso:country":"DE",
    "sg:address":"Am Hardtanger 10",
    "sg:city":"F\u00fcrstenfeldbruck",
    "sg:phone":"+49 8141/4030",
    "sg:postcode":"82256",
    "sg:province":"Bayern",
    "wof:name":"Schleifring Und Apparatebau Gmbh",
    "wof:placetype":"venue"
},
  "geometry": {"coordinates":[11.2514076233,48.1951179504],"type":"Point"}
}