{
  "type": "Feature",
  "properties": {
    "iso:country":"DE",
    "sg:address":"Vogelsangstr. 4",
    "sg:city":"Reutlingen",
    "sg:phone":"+49 7121/321534",
    "sg:postcode":"72770",
    "sg:province":"Baden-W\u00fcrttemberg",
    "wof:name":"Horst Wilke Ingenieur",
    "wof:placetype":"venue"
},
  "geometry": {"coordinates":[9.1823549271,48.5027885437],"type":"Point"}
}