{
  "type": "Feature",
  "properties": {
    "iso:country":"DE",
    "sg:address":"Oberstetten 20",
    "sg:city":"Niederstetten",
    "sg:phone":"+49 7932/163",
    "sg:postcode":"97996",
    "sg:province":"Baden-W\u00fcrttemberg",
    "wof:name":"Georg Schmidt",
    "wof:placetype":"venue"
},
  "geometry": {"coordinates":[9.9207439423,49.3960571289],"type":"Point"}
}