{
  "type": "Feature",
  "properties": {
    "iso:country":"DE",
    "sg:address":"M\u00fcnsterstr 2-4::",
    "sg:city":"\u00dcberlingen",
    "sg:postcode":"88662",
    "sg:province":"Baden-W\u00fcrttemberg",
    "wof:name":"Sparkasse \u00dcberlingen",
    "wof:placetype":"venue"
},
  "geometry": {"coordinates":[9.161491,47.766735],"type":"Point"}
}