{
  "type": "Feature",
  "properties": {
    "iso:country":"DE",
    "sg:address":"Dorfstr. 10",
    "sg:city":"Battin",
    "sg:phone":"+49 3537/212788",
    "sg:postcode":"06917",
    "sg:province":"Sachsen-Anhalt",
    "wof:name":"J. Komrovski",
    "wof:placetype":"venue"
},
  "geometry": {"coordinates":[12.9052944183,51.7673530579],"type":"Point"}
}