{
  "type": "Feature",
  "properties": {
    "iso:country":"DE",
    "sg:address":"Badstr. 22",
    "sg:city":"Venusberg",
    "sg:phone":"+49 3725/77198",
    "sg:postcode":"09430",
    "sg:province":"Sachsen",
    "wof:name":"Freibad Venusberg",
    "wof:placetype":"venue"
},
  "geometry": {"coordinates":[13.0148649216,50.6953887939],"type":"Point"}
}