{
  "type": "Feature",
  "properties": {
    "iso:country":"DE",
    "sg:address":"Hammoor 1",
    "sg:city":"Espelkamp",
    "sg:phone":"+49 5743/1857",
    "sg:postcode":"32339",
    "sg:province":"Nordrhein-Westfalen",
    "wof:name":"Gustav Schumacher",
    "wof:placetype":"venue"
},
  "geometry": {"coordinates":[8.546955,52.356182],"type":"Point"}
}