{
  "type": "Feature",
  "properties": {
    "iso:country":"DE",
    "sg:address":"Am Nikolaustor 8",
    "sg:city":"W\u00fcrzburg",
    "sg:phone":"+49 931/62667",
    "sg:postcode":"97084",
    "sg:province":"Bayern",
    "wof:name":"Giemaulschenke",
    "wof:placetype":"venue"
},
  "geometry": {"coordinates":[9.9473581314,49.7660140991],"type":"Point"}
}