{
  "type": "Feature",
  "properties": {
    "iso:country":"DE",
    "sg:address":"Br\u00fcderstr. 4",
    "sg:city":"Gevelsberg",
    "sg:phone":"+49 2332/13760",
    "sg:postcode":"58285",
    "sg:province":"Nordrhein-Westfalen",
    "wof:name":"G. Schulz Steuerberater",
    "wof:placetype":"venue"
},
  "geometry": {"coordinates":[7.3439478874,51.3201255798],"type":"Point"}
}