{
  "type": "Feature",
  "properties": {
    "iso:country":"DE",
    "sg:address":"Eichenbirkig 10-11",
    "sg:city":"Waischenfeld",
    "sg:phone":"+49 9202/1416",
    "sg:postcode":"91344",
    "sg:province":"Bayern",
    "wof:name":"Ulrich Sterndorff",
    "wof:placetype":"venue"
},
  "geometry": {"coordinates":[11.33946,49.820225],"type":"Point"}
}