{
  "type": "Feature",
  "properties": {
    "iso:country":"DE",
    "sg:address":"Huhnsgasse 32",
    "sg:city":"K\u00f6ln",
    "sg:phone":"+49 221/232263",
    "sg:postcode":"50676",
    "sg:province":"Nordrhein-Westfalen",
    "wof:name":"R. Vielhaber",
    "wof:placetype":"venue"
},
  "geometry": {"coordinates":[6.943365,50.930962],"type":"Point"}
}