{
  "type": "Feature",
  "properties": {
    "iso:country":"DE",
    "sg:address":"D\u00fcsseldorfer Str. 46",
    "sg:city":"M\u00fclheim",
    "sg:phone":"+49 208/487247",
    "sg:postcode":"45481",
    "sg:province":"Nordrhein-Westfalen",
    "wof:name":"Hermann Birkhoff Inh. Renate Zboron-huennekes",
    "wof:placetype":"venue"
},
  "geometry": {"coordinates":[6.876006,51.404449],"type":"Point"}
}