{
  "type": "Feature",
  "properties": {
    "iso:country":"DE",
    "sg:address":"Burghaldenweg 62-64",
    "sg:city":"Stuttgart",
    "sg:phone":"+49 711/815453",
    "sg:postcode":"70469",
    "sg:province":"Baden-W\u00fcrttemberg",
    "wof:name":"S & S Werksvertretungen Gmbh",
    "wof:placetype":"venue"
},
  "geometry": {"coordinates":[9.1666097641,48.8081130981],"type":"Point"}
}