{
  "type": "Feature",
  "properties": {
    "iso:country":"DE",
    "sg:address":"Im Etter 8",
    "sg:city":"Freiburg",
    "sg:phone":"+49 761/65383",
    "sg:postcode":"79117",
    "sg:province":"Baden-W\u00fcrttemberg",
    "wof:name":"Silke Laubis Krankengymnastin",
    "wof:placetype":"venue"
},
  "geometry": {"coordinates":[7.907967,47.986931],"type":"Point"}
}