{
  "type": "Feature",
  "properties": {
    "iso:country":"DE",
    "sg:address":"Schlo\u00dfberg 31",
    "sg:city":"Sch\u00f6nberg",
    "sg:phone":"+49 8554/1711",
    "sg:postcode":"94513",
    "sg:province":"Bayern",
    "wof:name":"Gefl\u00fcgelzuchtverein Peter Ludwig",
    "wof:placetype":"venue"
},
  "geometry": {"coordinates":[13.3256464005,48.83801651],"type":"Point"}
}