{
  "type": "Feature",
  "properties": {
    "iso:country":"DE",
    "sg:address":"K\u00f6nigskamp 29",
    "sg:city":"Sylt-Ost",
    "sg:phone":"+49 4651/3821",
    "sg:postcode":"25980",
    "sg:province":"Schleswig-Holstein",
    "wof:name":"A. Kraut",
    "wof:placetype":"venue"
},
  "geometry": {"coordinates":[8.321214,54.902485],"type":"Point"}
}