{
  "type": "Feature",
  "properties": {
    "iso:country":"DE",
    "sg:address":"Tippelstr. 117",
    "sg:city":"Hattingen",
    "sg:phone":"+49 2324/41657",
    "sg:postcode":"45529",
    "sg:province":"Nordrhein-Westfalen",
    "wof:name":"Willi Holbeck",
    "wof:placetype":"venue"
},
  "geometry": {"coordinates":[7.127318,51.38681],"type":"Point"}
}