{
  "type": "Feature",
  "properties": {
    "iso:country":"DE",
    "sg:address":"Au\u00dferlandholz 234",
    "sg:city":"Legau",
    "sg:phone":"+49 8330/93344",
    "sg:postcode":"87764",
    "sg:province":"Bayern",
    "wof:name":"Altronik Josef Albrecht Gmbh",
    "wof:placetype":"venue"
},
  "geometry": {"coordinates":[10.1350917816,47.8290748596],"type":"Point"}
}