{
  "type": "Feature",
  "properties": {
    "iso:country":"DE",
    "sg:address":"Hammatalstr. 1",
    "sg:city":"Sondershausen",
    "sg:phone":"+49 3632/703188",
    "sg:postcode":"99706",
    "sg:province":"Th\u00fcringen",
    "wof:name":"Gastst\u00e4tte Stille Liebe",
    "wof:placetype":"venue"
},
  "geometry": {"coordinates":[10.8602151871,51.3837547302],"type":"Point"}
}