{
  "type": "Feature",
  "properties": {
    "iso:country":"DE",
    "sg:address":"R\u00fcsterstr. 24",
    "sg:city":"Frankfurt",
    "sg:phone":"+49 69/725801",
    "sg:postcode":"60325",
    "sg:province":"Hessen",
    "wof:name":"Gregor Wettannahme",
    "wof:placetype":"venue"
},
  "geometry": {"coordinates":[8.662847,50.113213],"type":"Point"}
}