{
  "type": "Feature",
  "properties": {
    "iso:country":"DE",
    "sg:address":"Fabrikweg 4",
    "sg:city":"Fl\u00f6ha",
    "sg:phone":"+49 3726/712356",
    "sg:postcode":"09557",
    "sg:province":"Sachsen",
    "wof:name":"Fliesen Oswald Gmbh",
    "wof:placetype":"venue"
},
  "geometry": {"coordinates":[13.0825214386,50.8607749939],"type":"Point"}
}