{
  "type": "Feature",
  "properties": {
    "iso:country":"DE",
    "sg:address":"F\u00fcnfhausen 57",
    "sg:city":"Buseck",
    "sg:phone":"+49 6408/4242",
    "sg:postcode":"35418",
    "sg:province":"Hessen",
    "wof:name":"Mode-idee 5000 - Einkaufen Bei Freunden Gmbh",
    "wof:placetype":"venue"
},
  "geometry": {"coordinates":[8.8277683258,50.6325683594],"type":"Point"}
}