{
  "type": "Feature",
  "properties": {
    "iso:country":"DE",
    "sg:address":"Pfarrgasse 8",
    "sg:city":"Aschaffenburg",
    "sg:phone":"+49 6021/219759",
    "sg:postcode":"63739",
    "sg:province":"Bayern",
    "wof:name":"Armin Dressel",
    "wof:placetype":"venue"
},
  "geometry": {"coordinates":[9.14353,49.973961],"type":"Point"}
}