{
  "type": "Feature",
  "properties": {
    "iso:country":"DE",
    "sg:address":"Obere Dorfstr. 26",
    "sg:city":"Kranzberg",
    "sg:phone":"+49 8166/7857",
    "sg:postcode":"85402",
    "sg:province":"Bayern",
    "wof:name":"A. Rauschecker",
    "wof:placetype":"venue"
},
  "geometry": {"coordinates":[11.6155576706,48.4057998657],"type":"Point"}
}