{
  "type": "Feature",
  "properties": {
    "iso:country":"DE",
    "sg:address":"Jahnstr. 5",
    "sg:city":"Stadthagen",
    "sg:postcode":"31655",
    "sg:province":"Niedersachsen",
    "wof:name":"Extra",
    "wof:placetype":"venue"
},
  "geometry": {"coordinates":[9.1927070618,52.3201141357],"type":"Point"}
}