{
  "type": "Feature",
  "properties": {
    "iso:country":"DE",
    "sg:address":"F\u00f6rster-Schr\u00f6dter-Str. 30",
    "sg:city":"Koserow",
    "sg:phone":"+49 38375/2620",
    "sg:postcode":"17459",
    "sg:province":"Mecklenburg-Vorpommern",
    "wof:name":"Hotel Restaurant Wald Und Meer",
    "wof:placetype":"venue"
},
  "geometry": {"coordinates":[14.007900238,54.0549697876],"type":"Point"}
}