{
  "type": "Feature",
  "properties": {
    "iso:country":"DE",
    "sg:address":"Heinrich-Lanz-Str. 2 b",
    "sg:city":"Beindersheim",
    "sg:phone":"+49 6233/737284",
    "sg:postcode":"67259",
    "sg:province":"Rheinland-Pfalz",
    "wof:name":"G. Eck",
    "wof:placetype":"venue"
},
  "geometry": {"coordinates":[8.325835228,49.5581817627],"type":"Point"}
}