{
  "type": "Feature",
  "properties": {
    "iso:country":"DE",
    "sg:address":"Hornenbergstr. 49",
    "sg:city":"Lauf",
    "sg:phone":"+49 7841/3395",
    "sg:postcode":"77886",
    "sg:province":"Baden-W\u00fcrttemberg",
    "wof:name":"Willi Karcher",
    "wof:placetype":"venue"
},
  "geometry": {"coordinates":[8.1395597458,48.6342086792],"type":"Point"}
}