{
  "type": "Feature",
  "properties": {
    "iso:country":"DE",
    "sg:address":"Breitensteinstr. 55",
    "sg:city":"Stephanskirchen",
    "sg:phone":"+49 8031/71500",
    "sg:postcode":"83071",
    "sg:province":"Bayern",
    "wof:name":"Schreiber Verwaltungs Gmbh",
    "wof:placetype":"venue"
},
  "geometry": {"coordinates":[12.1560220718,47.8542404175],"type":"Point"}
}