{
  "type": "Feature",
  "properties": {
    "iso:country":"DE",
    "sg:address":"Haffstr. 10",
    "sg:city":"Te\u00dfmannsdorf",
    "sg:phone":"+49 38294/12582",
    "sg:postcode":"18233",
    "sg:province":"Mecklenburg-Vorpommern",
    "wof:name":"Malermeister M. Puffpaff Gmbh",
    "wof:placetype":"venue"
},
  "geometry": {"coordinates":[11.6128864288,54.0561180115],"type":"Point"}
}