{
  "type": "Feature",
  "properties": {
    "iso:country":"DE",
    "sg:address":"Pulverstr. 26",
    "sg:city":"Bochum",
    "sg:phone":"+49 2327/55932",
    "sg:postcode":"44869",
    "sg:province":"Nordrhein-Westfalen",
    "wof:name":"J\u00fcrgen Stolz",
    "wof:placetype":"venue"
},
  "geometry": {"coordinates":[7.143341,51.457935],"type":"Point"}
}