{
  "type": "Feature",
  "properties": {
    "iso:country":"DE",
    "sg:address":"Am Gleis 3",
    "sg:city":"Oranienburg",
    "sg:postcode":"16515",
    "sg:province":"Brandenburg",
    "wof:name":"Gleitschliff Zentrum Oranienburg E. Kfm.",
    "wof:placetype":"venue"
},
  "geometry": {"coordinates":[13.2668390274,52.7760467529],"type":"Point"}
}