{
  "type": "Feature",
  "properties": {
    "iso:country":"DE",
    "sg:address":"Kylische Str. 28",
    "sg:city":"Sangerhausen",
    "sg:phone":"+49 3464/570136",
    "sg:postcode":"06526",
    "sg:province":"Sachsen-Anhalt",
    "wof:name":"Reise Welt",
    "wof:placetype":"venue"
},
  "geometry": {"coordinates":[11.2964754105,51.473361969],"type":"Point"}
}