{
  "type": "Feature",
  "properties": {
    "iso:country":"DE",
    "sg:address":"Bargteheider Str. 134",
    "sg:city":"Hamburg",
    "sg:phone":"+49 40/6771909",
    "sg:postcode":"22143",
    "sg:province":"Hamburg",
    "wof:name":"Alt-rahlstedter Landhaus Gebr. Nicolaisen Gmbh",
    "wof:placetype":"venue"
},
  "geometry": {"coordinates":[10.1518268585,53.6093826294],"type":"Point"}
}