{
  "type": "Feature",
  "properties": {
    "iso:country":"DE",
    "sg:address":"Am Bahnhof 5",
    "sg:city":"Kalefeld",
    "sg:phone":"+49 5553/99250",
    "sg:postcode":"37589",
    "sg:province":"Niedersachsen",
    "wof:name":"M\u00f6belwerkst\u00e4tten Sorge Gmbh",
    "wof:placetype":"venue"
},
  "geometry": {"coordinates":[10.061996,51.787846],"type":"Point"}
}