{
  "type": "Feature",
  "properties": {
    "iso:country":"DE",
    "sg:address":"Wasenstr. 15",
    "sg:city":"G\u00f6ppingen",
    "sg:phone":"+49 7161/42412",
    "sg:postcode":"73035",
    "sg:province":"Baden-W\u00fcrttemberg",
    "wof:name":"Hotel-pension Fausel Inh. Dieter Und Karin Fausel",
    "wof:placetype":"venue"
},
  "geometry": {"coordinates":[9.6337471008,48.6886253357],"type":"Point"}
}