{
  "type": "Feature",
  "properties": {
    "iso:country":"DE",
    "sg:address":"Silvertstr. 1",
    "sg:city":"Marl",
    "sg:phone":"+49 2365/26169",
    "sg:postcode":"45772",
    "sg:province":"Nordrhein-Westfalen",
    "wof:name":"D. Kania",
    "wof:placetype":"venue"
},
  "geometry": {"coordinates":[7.1261439323,51.6761703491],"type":"Point"}
}