{
  "type": "Feature",
  "properties": {
    "iso:country":"DE",
    "sg:address":"F\u00fcrstenwall 99",
    "sg:city":"D\u00fcsseldorf",
    "sg:postcode":"40217",
    "sg:province":"Nordrhein-Westfalen",
    "wof:name":"Institut F\u00fcr Ergotherapie Gmbh & Co. Kg",
    "wof:placetype":"venue"
},
  "geometry": {"coordinates":[6.7741289139,51.2138786316],"type":"Point"}
}