{
  "type": "Feature",
  "properties": {
    "iso:country":"DE",
    "sg:address":"Bruchgarten 27",
    "sg:city":"Paderborn",
    "sg:phone":"+49 5251/9441",
    "sg:postcode":"33106",
    "sg:province":"Nordrhein-Westfalen",
    "wof:name":"Kabau Kabelbau Gmbh",
    "wof:placetype":"venue"
},
  "geometry": {"coordinates":[8.69042,51.690399],"type":"Point"}
}