{
  "type": "Feature",
  "properties": {
    "iso:country":"DE",
    "sg:address":"Bahnhofstr 2",
    "sg:city":"Friedrichshafen",
    "sg:phone":"+49 9741/91050",
    "sg:postcode":"88048",
    "sg:province":"Baden-W\u00fcrttemberg",
    "wof:name":"Torbau Bad Br\u00fcckenau Gmbh",
    "wof:placetype":"venue"
},
  "geometry": {"coordinates":[9.789742,50.289619],"type":"Point"}
}