{
  "type": "Feature",
  "properties": {
    "iso:country":"DE",
    "sg:address":"Bahnhofstr. 48-50",
    "sg:city":"Wittingen",
    "sg:phone":"+49 5831/7700",
    "sg:postcode":"29378",
    "sg:province":"Niedersachsen",
    "wof:name":"China-restaurant Cin Lin",
    "wof:placetype":"venue"
},
  "geometry": {"coordinates":[10.7271947861,52.7287254333],"type":"Point"}
}