{
  "type": "Feature",
  "properties": {
    "iso:country":"DE",
    "sg:address":"Bahnhofstr. 7",
    "sg:city":"Ladenburg",
    "sg:phone":"+49 6203/180900",
    "sg:postcode":"68526",
    "sg:province":"Baden-W\u00fcrttemberg",
    "wof:name":"B. Kappis",
    "wof:placetype":"venue"
},
  "geometry": {"coordinates":[8.602764,49.472332],"type":"Point"}
}