{
  "type": "Feature",
  "properties": {
    "iso:country":"DE",
    "sg:address":"Zeppelinstr. 10",
    "sg:city":"M\u00fcnchen",
    "sg:postcode":"81541",
    "sg:province":"Bayern",
    "wof:name":"Instanova S\u00fcd Gmbh",
    "wof:placetype":"venue"
},
  "geometry": {"coordinates":[11.5811729431,48.1262207031],"type":"Point"}
}