{
  "type": "Feature",
  "properties": {
    "iso:country":"DE",
    "sg:address":"Moorkaten",
    "sg:city":"Kaltenkirchen",
    "sg:phone":"+49 4191/7841",
    "sg:postcode":"24568",
    "sg:province":"Schleswig-Holstein",
    "wof:name":"Holztrocknungs- Und Impr\u00e4g- Nierwerk Moorkaten",
    "wof:placetype":"venue"
},
  "geometry": {"coordinates":[9.9148550034,53.8224449158],"type":"Point"}
}