{
  "type": "Feature",
  "properties": {
    "iso:country":"DE",
    "sg:address":"Blumgasse 38",
    "sg:city":"Monschau",
    "sg:phone":"+49 2472/5319",
    "sg:postcode":"52156",
    "sg:province":"Nordrhein-Westfalen",
    "wof:name":"K. Stollenwerk",
    "wof:placetype":"venue"
},
  "geometry": {"coordinates":[6.255420208,50.5967102051],"type":"Point"}
}