{
  "type": "Feature",
  "properties": {
    "iso:country":"DE",
    "sg:address":"Azorenstr. 19",
    "sg:city":"Bielefeld",
    "sg:phone":"+49 521/762452",
    "sg:postcode":"33729",
    "sg:province":"Nordrhein-Westfalen",
    "wof:name":"W. Schweppe",
    "wof:placetype":"venue"
},
  "geometry": {"coordinates":[8.61881,52.062916],"type":"Point"}
}