{
  "type": "Feature",
  "properties": {
    "iso:country":"DE",
    "sg:address":"Konrad-Adenauer-Allee 53",
    "sg:city":"Augsburg",
    "sg:phone":"+49 821/3494460",
    "sg:postcode":"86150",
    "sg:province":"Bayern",
    "wof:name":"Germania Steuerberatungs Gmbh",
    "wof:placetype":"venue"
},
  "geometry": {"coordinates":[10.8974580765,48.3610992432],"type":"Point"}
}