{
  "type": "Feature",
  "properties": {
    "iso:country":"DE",
    "sg:address":"Lembergstr 46",
    "sg:city":"Reutlingen",
    "sg:phone":"+49 7121/144980",
    "sg:postcode":"72766",
    "sg:province":"Baden-W\u00fcrttemberg",
    "wof:name":"Hsb Automation Gmbh",
    "wof:placetype":"venue"
},
  "geometry": {"coordinates":[9.21746,48.515869],"type":"Point"}
}