{
  "type": "Feature",
  "properties": {
    "iso:country":"DE",
    "sg:address":"Berliner Str. 11",
    "sg:city":"Merzig",
    "sg:phone":"+49 6861/5442",
    "sg:postcode":"66663",
    "sg:province":"Saarland",
    "wof:name":"H. Und E. Kettenhofen",
    "wof:placetype":"venue"
},
  "geometry": {"coordinates":[6.618598938,49.4319000244],"type":"Point"}
}