{
  "type": "Feature",
  "properties": {
    "iso:country":"DE",
    "sg:address":"Wei\u00dfer Weg 13",
    "sg:city":"C\u00f6lbe",
    "sg:phone":"+49 6427/92080",
    "sg:postcode":"35091",
    "sg:province":"Hessen",
    "wof:name":"Ingeborg Fischbach Steuerbevollm\u00e4chtigte",
    "wof:placetype":"venue"
},
  "geometry": {"coordinates":[8.8336696625,50.886554718],"type":"Point"}
}