{
  "type": "Feature",
  "properties": {
    "iso:country":"DE",
    "sg:address":"Zum Bahnhof 10",
    "sg:city":"Schwerin",
    "sg:phone":"+49 385/564692",
    "sg:postcode":"19055",
    "sg:province":"Mecklenburg-Vorpommern",
    "wof:name":"Frank Bergmann",
    "wof:placetype":"venue"
},
  "geometry": {"coordinates":[11.4094400406,53.6336555481],"type":"Point"}
}