{
  "type": "Feature",
  "properties": {
    "iso:country":"DE",
    "sg:address":"Am K\u00fcnstlerhaus 32",
    "sg:city":"Karlsruhe",
    "sg:phone":"+49 721/9334040",
    "sg:postcode":"76131",
    "sg:province":"Baden-W\u00fcrttemberg",
    "wof:name":"Prof. Martin Einsele Architekt Bda",
    "wof:placetype":"venue"
},
  "geometry": {"coordinates":[8.413466,49.007957],"type":"Point"}
}