{
  "type": "Feature",
  "properties": {
    "iso:country":"DE",
    "sg:address":"D\u00fcrener Str. 62a",
    "sg:city":"Eschweiler",
    "sg:phone":"+49 2403/29706",
    "sg:postcode":"52249",
    "sg:province":"Nordrhein-Westfalen",
    "wof:name":"Restaurant Haus Lersch",
    "wof:placetype":"venue"
},
  "geometry": {"coordinates":[6.2714858055,50.8192329407],"type":"Point"}
}