{
  "type": "Feature",
  "properties": {
    "iso:country":"DE",
    "sg:address":"Lersnerstr. 29",
    "sg:city":"Frankfurt",
    "sg:phone":"+49 69/591531",
    "sg:postcode":"60322",
    "sg:province":"Hessen",
    "wof:name":"Rainer Diekerhoff",
    "wof:placetype":"venue"
},
  "geometry": {"coordinates":[8.679371,50.123547],"type":"Point"}
}