{
  "type": "Feature",
  "properties": {
    "iso:country":"DE",
    "sg:address":"Lemgoer Str 48",
    "sg:city":"Kalletal",
    "sg:phone":"+49 5264/363",
    "sg:postcode":"32689",
    "sg:province":"Nordrhein-Westfalen",
    "wof:name":"Sandmann Gmbh",
    "wof:placetype":"venue"
},
  "geometry": {"coordinates":[8.9412755966,52.1042060852],"type":"Point"}
}