{
  "type": "Feature",
  "properties": {
    "iso:country":"DE",
    "sg:address":"K\u00fcrnbacher Str. 7",
    "sg:city":"Oberderdingen",
    "sg:postcode":"75038",
    "sg:province":"Baden-W\u00fcrttemberg",
    "wof:name":"Pjetri Gmbh",
    "wof:placetype":"venue"
},
  "geometry": {"coordinates":[8.791029,49.087791],"type":"Point"}
}