{
  "type": "Feature",
  "properties": {
    "iso:country":"DE",
    "sg:address":"Sch\u00fctzenweg 12",
    "sg:city":"Bad K\u00f6nigshofen",
    "sg:phone":"+49 9761/2070",
    "sg:postcode":"97631",
    "sg:province":"Bayern",
    "wof:name":"Holger Kerner",
    "wof:placetype":"venue"
},
  "geometry": {"coordinates":[10.467965126,50.2945899963],"type":"Point"}
}