{
  "type": "Feature",
  "properties": {
    "iso:country":"DE",
    "sg:address":"Sch\u00f6naustr. 3",
    "sg:city":"D\u00fcsseldorf",
    "sg:phone":"+49 211/297184",
    "sg:postcode":"40625",
    "sg:province":"Nordrhein-Westfalen",
    "wof:name":"Beauty Hair Design",
    "wof:placetype":"venue"
},
  "geometry": {"coordinates":[6.8609070778,51.2343597412],"type":"Point"}
}