{
  "type": "Feature",
  "properties": {
    "iso:country":"DE",
    "sg:address":"Bellermannstr. 96",
    "sg:city":"Berlin",
    "sg:phone":"+49 30/4947328",
    "sg:postcode":"13357",
    "sg:province":"Berlin",
    "wof:name":"Geyriye G\u00fcl",
    "wof:placetype":"venue"
},
  "geometry": {"coordinates":[13.3848323822,52.5545845032],"type":"Point"}
}