{
  "type": "Feature",
  "properties": {
    "iso:country":"DE",
    "sg:address":"Fasanenstr. 30",
    "sg:city":"Dornstadt",
    "sg:phone":"+49 7304/919077",
    "sg:postcode":"89160",
    "sg:province":"Baden-W\u00fcrttemberg",
    "wof:name":"Rentenberater Reiner Nittmann",
    "wof:placetype":"venue"
},
  "geometry": {"coordinates":[9.912772,48.458019],"type":"Point"}
}