{
  "type": "Feature",
  "properties": {
    "iso:country":"DE",
    "sg:address":"Lessingstr. 55",
    "sg:city":"Karlsruhe",
    "sg:phone":"+49 721/858191",
    "sg:postcode":"76135",
    "sg:province":"Baden-W\u00fcrttemberg",
    "wof:name":"Germaine Muly",
    "wof:placetype":"venue"
},
  "geometry": {"coordinates":[8.3847494125,49.0044708252],"type":"Point"}
}