{
  "type": "Feature",
  "properties": {
    "iso:country":"DE",
    "sg:address":"Wiekhorner Heuweg 8",
    "sg:city":"Delmenhorst",
    "sg:phone":"+49 4221/82021",
    "sg:postcode":"27753",
    "sg:province":"Niedersachsen",
    "wof:name":"Dr. Otto Schubert Tierarzt",
    "wof:placetype":"venue"
},
  "geometry": {"coordinates":[8.6104335785,53.0452728271],"type":"Point"}
}