{
  "type": "Feature",
  "properties": {
    "iso:country":"DE",
    "sg:address":"Sch\u00e4lg\u00e4rten 13",
    "sg:city":"Pohlheim",
    "sg:phone":"+49 6004/786",
    "sg:postcode":"35415",
    "sg:province":"Hessen",
    "wof:name":"Heinz P\u00f6tzl",
    "wof:placetype":"venue"
},
  "geometry": {"coordinates":[8.7218408585,50.4910888672],"type":"Point"}
}