{
  "type": "Feature",
  "properties": {
    "iso:country":"DE",
    "sg:address":"Vor dem Bundeberg 2",
    "sg:city":"Dautphetal",
    "sg:phone":"+49 6466/315",
    "sg:postcode":"35232",
    "sg:province":"Hessen",
    "wof:name":"L. Aue",
    "wof:placetype":"venue"
},
  "geometry": {"coordinates":[8.604227066,50.8735389709],"type":"Point"}
}