{
  "type": "Feature",
  "properties": {
    "iso:country":"DE",
    "sg:address":"Rudolf-Diesel-Str 10",
    "sg:city":"Buxtehude",
    "sg:phone":"+49 4161/50270",
    "sg:postcode":"21614",
    "sg:province":"Niedersachsen",
    "wof:name":"Whirlpool Import Gmbh",
    "wof:placetype":"venue"
},
  "geometry": {"coordinates":[9.7038154602,53.4612922668],"type":"Point"}
}