{
  "type": "Feature",
  "properties": {
    "iso:country":"DE",
    "sg:address":"Merkurstr. 30",
    "sg:city":"Solingen",
    "sg:phone":"+49 212/334398",
    "sg:postcode":"42699",
    "sg:province":"Nordrhein-Westfalen",
    "wof:name":"G\u00fcnter Hermes",
    "wof:placetype":"venue"
},
  "geometry": {"coordinates":[7.015388,51.160202],"type":"Point"}
}