{
  "type": "Feature",
  "properties": {
    "iso:country":"DE",
    "sg:address":"Karlstr. 41-43",
    "sg:city":"Karlsruhe",
    "sg:phone":"+49 721/913730",
    "sg:postcode":"76133",
    "sg:province":"Baden-W\u00fcrttemberg",
    "wof:name":"Reif Exquisit Moden Inh. B. Reif",
    "wof:placetype":"venue"
},
  "geometry": {"coordinates":[8.394966,49.006599],"type":"Point"}
}