{
  "type": "Feature",
  "properties": {
    "iso:country":"DE",
    "sg:address":"Robbenplate 22",
    "sg:city":"Wangerland",
    "sg:postcode":"26434",
    "sg:province":"Niedersachsen",
    "wof:name":"Vermietungs- Und Immobilienservice",
    "wof:placetype":"venue"
},
  "geometry": {"coordinates":[8.0335035324,53.6339073181],"type":"Point"}
}