{
  "type": "Feature",
  "properties": {
    "iso:country":"DE",
    "sg:address":"Bierstadter Str. 23",
    "sg:city":"Wiesbaden",
    "sg:postcode":"65189",
    "sg:province":"Hessen",
    "wof:name":"Atalea Grundst\u00fccks- Verwaltungs Gmbh & Co.",
    "wof:placetype":"venue"
},
  "geometry": {"coordinates":[8.252934,50.081409],"type":"Point"}
}