{
  "type": "Feature",
  "properties": {
    "iso:country":"DE",
    "sg:address":"Bahnhofstr. 14",
    "sg:city":"Werl",
    "sg:phone":"+49 2922/3338",
    "sg:postcode":"59457",
    "sg:province":"Nordrhein-Westfalen",
    "wof:name":"Wwk Versicherungen Uwe Constantin E. K.",
    "wof:placetype":"venue"
},
  "geometry": {"coordinates":[7.9119348526,51.5568161011],"type":"Point"}
}