{
  "type": "Feature",
  "properties": {
    "iso:country":"DE",
    "sg:address":"Landschreibergasse 2",
    "sg:city":"Lahnau",
    "sg:postcode":"35633",
    "sg:province":"Hessen",
    "wof:name":"Agel Handels Gmbh",
    "wof:placetype":"venue"
},
  "geometry": {"coordinates":[8.5882444382,50.5771179199],"type":"Point"}
}