{
  "type": "Feature",
  "properties": {
    "iso:country":"DE",
    "sg:address":"Ernst-Th\u00e4lmann-Str. 162",
    "sg:city":"Beilrode",
    "sg:phone":"+49 3421/711276",
    "sg:postcode":"04886",
    "sg:province":"Sachsen",
    "wof:name":"Dr. Frank Seifert Tierarzt",
    "wof:placetype":"venue"
},
  "geometry": {"coordinates":[13.0753917694,51.5621948242],"type":"Point"}
}