{
  "type": "Feature",
  "properties": {
    "iso:country":"DE",
    "sg:address":"Behlstr. 23",
    "sg:city":"Geisenheim",
    "sg:phone":"+49 6722/8759",
    "sg:postcode":"65366",
    "sg:province":"Hessen",
    "wof:name":"H. Und E. Schmitt Steinmetze",
    "wof:placetype":"venue"
},
  "geometry": {"coordinates":[7.9660620689,49.9864845276],"type":"Point"}
}