{
  "type": "Feature",
  "properties": {
    "iso:country":"DE",
    "sg:address":"Amtmannsweg 20",
    "sg:city":"Harpstedt",
    "sg:phone":"+49 4244/8882",
    "sg:postcode":"27243",
    "sg:province":"Niedersachsen",
    "wof:name":"Inn-gastro Einrichtungs Gmbh",
    "wof:placetype":"venue"
},
  "geometry": {"coordinates":[8.597028,52.912453],"type":"Point"}
}