{
  "type": "Feature",
  "properties": {
    "iso:country":"DE",
    "sg:address":"Dr.-von-Pichler-Platz 2",
    "sg:city":"Passau",
    "sg:phone":"+49 851/7648",
    "sg:postcode":"94036",
    "sg:province":"Bayern",
    "wof:name":"Kath. Pfarramt St. Josef",
    "wof:placetype":"venue"
},
  "geometry": {"coordinates":[13.4182338715,48.5703544617],"type":"Point"}
}