{
  "type": "Feature",
  "properties": {
    "iso:country":"DE",
    "sg:address":"B\u00f6hmerwaldstr. 31",
    "sg:city":"Altdorf",
    "sg:phone":"+49 871/33333",
    "sg:postcode":"84032",
    "sg:province":"Bayern",
    "wof:name":"Gks Gesundheits- Und Karatestudio",
    "wof:placetype":"venue"
},
  "geometry": {"coordinates":[12.1101045609,48.5533790588],"type":"Point"}
}