{
  "type": "Feature",
  "properties": {
    "iso:country":"DE",
    "sg:address":"Loher Str. 115",
    "sg:city":"Ennepetal",
    "sg:phone":"+49 2333/81008",
    "sg:postcode":"58256",
    "sg:province":"Nordrhein-Westfalen",
    "wof:name":"Fritz Beier",
    "wof:placetype":"venue"
},
  "geometry": {"coordinates":[7.381222,51.30373],"type":"Point"}
}