{
  "type": "Feature",
  "properties": {
    "iso:country":"DE",
    "sg:address":"Tr\u00f6ndlinring 7",
    "sg:city":"Leipzig",
    "sg:postcode":"04105",
    "sg:province":"Sachsen",
    "wof:name":"Ev. Reformierte Kirche",
    "wof:placetype":"venue"
},
  "geometry": {"coordinates":[12.3734235764,51.3445396423],"type":"Point"}
}