{
  "type": "Feature",
  "properties": {
    "iso:country":"DE",
    "sg:address":"Neufelder Weg 7",
    "sg:city":"Schiffdorf",
    "sg:phone":"+49 471/984820",
    "sg:postcode":"27619",
    "sg:province":"Niedersachsen",
    "wof:name":"Siemer & M\u00fcller Gmbh & Co. Kg",
    "wof:placetype":"venue"
},
  "geometry": {"coordinates":[8.629739,53.583309],"type":"Point"}
}