{
  "type": "Feature",
  "properties": {
    "iso:country":"DE",
    "sg:address":"Holzgasse 11",
    "sg:city":"Alfter",
    "sg:phone":"+49 2222/934410",
    "sg:postcode":"53347",
    "sg:province":"Nordrhein-Westfalen",
    "wof:name":"A. Teich",
    "wof:placetype":"venue"
},
  "geometry": {"coordinates":[7.011743,50.736698],"type":"Point"}
}