{
  "type": "Feature",
  "properties": {
    "iso:country":"DE",
    "sg:address":"Karl-Lange-Str. 53",
    "sg:city":"Bochum",
    "sg:phone":"+49 234/500535",
    "sg:postcode":"44791",
    "sg:province":"Nordrhein-Westfalen",
    "wof:name":"Ktb-plast Kunststoff Gmbh",
    "wof:placetype":"venue"
},
  "geometry": {"coordinates":[7.243821,51.485672],"type":"Point"}
}