{
  "type": "Feature",
  "properties": {
    "iso:country":"DE",
    "sg:address":"Eickelstr. 17",
    "sg:city":"Rheda",
    "sg:phone":"+49 4952/4255107",
    "sg:postcode":"33378",
    "sg:province":"Nordrhein-Westfalen",
    "wof:name":"Cb Credit-bank Gmbh",
    "wof:placetype":"venue"
},
  "geometry": {"coordinates":[8.321408,51.836765],"type":"Point"}
}