{
  "type": "Feature",
  "properties": {
    "iso:country":"DE",
    "sg:address":"Bonner Str. 20",
    "sg:city":"Wesseling",
    "sg:phone":"+49 2236/81377",
    "sg:postcode":"50389",
    "sg:province":"Nordrhein-Westfalen",
    "wof:name":"Da Franco",
    "wof:placetype":"venue"
},
  "geometry": {"coordinates":[6.9833569527,50.8251152039],"type":"Point"}
}