{
  "type": "Feature",
  "properties": {
    "iso:country":"DE",
    "sg:address":"Westphalenweg 50a",
    "sg:city":"Paderborn",
    "sg:phone":"+49 5252/96610",
    "sg:postcode":"33104",
    "sg:province":"Nordrhein-Westfalen",
    "wof:name":"Pama Partner Marketing F\u00fcr Warenvertrieb Gmbh & Co. Kg",
    "wof:placetype":"venue"
},
  "geometry": {"coordinates":[8.748695,51.757942],"type":"Point"}
}