{
  "type": "Feature",
  "properties": {
    "iso:country":"DE",
    "sg:address":"Haart 224",
    "sg:city":"Neum\u00fcnster",
    "sg:phone":"+49 4321/70910",
    "sg:postcode":"24539",
    "sg:province":"Schleswig-Holstein",
    "wof:name":"Famila-handelsmarkt Neum\u00fcnster Gmbh & Co. Kg",
    "wof:placetype":"venue"
},
  "geometry": {"coordinates":[10.01146698,54.0602912903],"type":"Point"}
}