{
  "type": "Feature",
  "properties": {
    "iso:country":"DE",
    "sg:address":"Forsterstr. 14",
    "sg:city":"Kastl",
    "sg:phone":"+49 8671/6045",
    "sg:postcode":"84556",
    "sg:province":"Bayern",
    "wof:name":"Henriette Maki Garten- Und",
    "wof:placetype":"venue"
},
  "geometry": {"coordinates":[12.700214,48.197315],"type":"Point"}
}