{
  "type": "Feature",
  "properties": {
    "iso:country":"DE",
    "sg:address":"Spandlberg 4",
    "sg:city":"Neukirchen",
    "sg:phone":"+49 9947/645",
    "sg:postcode":"93453",
    "sg:province":"Bayern",
    "wof:name":"Josef Dengscherz",
    "wof:placetype":"venue"
},
  "geometry": {"coordinates":[13.00039,49.267479],"type":"Point"}
}