{
  "type": "Feature",
  "properties": {
    "iso:country":"DE",
    "sg:address":"Obere Str. 8",
    "sg:city":"Nordstemmen",
    "sg:phone":"+49 5069/96326",
    "sg:postcode":"31171",
    "sg:province":"Niedersachsen",
    "wof:name":"Wulf Warnecke",
    "wof:placetype":"venue"
},
  "geometry": {"coordinates":[9.77934,52.161968],"type":"Point"}
}