{
  "type": "Feature",
  "properties": {
    "iso:country":"DE",
    "sg:address":"B\u00f6singer Str. 6",
    "sg:city":"B\u00f6singen",
    "sg:phone":"+49 7404/7387",
    "sg:postcode":"78662",
    "sg:province":"Baden-W\u00fcrttemberg",
    "wof:name":"Anton M\u00fcller",
    "wof:placetype":"venue"
},
  "geometry": {"coordinates":[8.579573,48.224983],"type":"Point"}
}