{
  "type": "Feature",
  "properties": {
    "iso:country":"DE",
    "sg:address":"D\u00fcsseldorfer Str. 53",
    "sg:city":"K\u00f6ln",
    "sg:postcode":"51063",
    "sg:province":"Nordrhein-Westfalen",
    "wof:name":"B.kollek & Partner",
    "wof:placetype":"venue"
},
  "geometry": {"coordinates":[7.002529,50.972897],"type":"Point"}
}