{
  "type": "Feature",
  "properties": {
    "iso:country":"DE",
    "sg:address":"Yorckstr. 7a",
    "sg:city":"Remscheid",
    "sg:phone":"+49 2191/952001",
    "sg:postcode":"42899",
    "sg:province":"Nordrhein-Westfalen",
    "wof:name":"Lohmann Gmbh",
    "wof:placetype":"venue"
},
  "geometry": {"coordinates":[7.2339010239,51.2113494873],"type":"Point"}
}