{
  "type": "Feature",
  "properties": {
    "iso:country":"DE",
    "sg:address":"M\u00fchlheimer Str. 24",
    "sg:city":"Tuttlingen",
    "sg:phone":"+49 7461/3646",
    "sg:postcode":"78532",
    "sg:province":"Baden-W\u00fcrttemberg",
    "wof:name":"Josef Katz",
    "wof:placetype":"venue"
},
  "geometry": {"coordinates":[8.8579702377,48.0048866272],"type":"Point"}
}