{
  "type": "Feature",
  "properties": {
    "iso:country":"DE",
    "sg:address":"Maerkische Str.16-20",
    "sg:city":"Dortmund",
    "sg:phone":"+49 231/8280233",
    "sg:postcode":"44135",
    "sg:province":"Nordrhein-Westfalen",
    "wof:name":"Discothek Ballhaus",
    "wof:placetype":"venue"
},
  "geometry": {"coordinates":[7.4695801735,51.5085601807],"type":"Point"}
}