{
  "type": "Feature",
  "properties": {
    "iso:country":"DE",
    "sg:address":"Goethestr. 6",
    "sg:city":"Wei\u00dfenfels",
    "sg:phone":"+49 3443/209820",
    "sg:postcode":"06667",
    "sg:province":"Sachsen-Anhalt",
    "wof:name":"E. Svetelsky",
    "wof:placetype":"venue"
},
  "geometry": {"coordinates":[11.9681482315,51.2094230652],"type":"Point"}
}