{
  "type": "Feature",
  "properties": {
    "iso:country":"DE",
    "sg:address":"Akilindastr. 56",
    "sg:city":"Gr\u00e4felfing",
    "sg:postcode":"82166",
    "sg:province":"Bayern",
    "wof:name":"Ga Project Gmbh",
    "wof:placetype":"venue"
},
  "geometry": {"coordinates":[11.4158010483,48.1170539856],"type":"Point"}
}