{
  "type": "Feature",
  "properties": {
    "iso:country":"DE",
    "sg:address":"Planetenring 38",
    "sg:city":"Garbsen",
    "sg:phone":"+49 5137/78518",
    "sg:postcode":"30823",
    "sg:province":"Niedersachsen",
    "wof:name":"Kl\u00f6nstuben Im Hallenbad",
    "wof:placetype":"venue"
},
  "geometry": {"coordinates":[9.6068201065,52.4164085388],"type":"Point"}
}