{
  "type": "Feature",
  "properties": {
    "iso:country":"DE",
    "sg:address":"Fontanestr. 9",
    "sg:city":"Engstingen",
    "sg:phone":"+49 7129/7646",
    "sg:postcode":"72829",
    "sg:province":"Baden-W\u00fcrttemberg",
    "wof:name":"Shd Spiel Und Holz Design Gmbh",
    "wof:placetype":"venue"
},
  "geometry": {"coordinates":[9.2861289978,48.3835296631],"type":"Point"}
}