{
  "type": "Feature",
  "properties": {
    "iso:country":"DE",
    "sg:address":"Essener Str. 96",
    "sg:city":"Bottrop",
    "sg:phone":"+49 2041/66099",
    "sg:postcode":"46236",
    "sg:province":"Nordrhein-Westfalen",
    "wof:name":"Pizzeria Etna",
    "wof:placetype":"venue"
},
  "geometry": {"coordinates":[6.9336352348,51.5135002136],"type":"Point"}
}