{
  "type": "Feature",
  "properties": {
    "iso:country":"DE",
    "sg:address":"Realschulstr. 11",
    "sg:city":"Gro\u00df-Umstadt",
    "sg:phone":"+49 6078/4326",
    "sg:postcode":"64823",
    "sg:province":"Hessen",
    "wof:name":"Alexander-apotheke",
    "wof:placetype":"venue"
},
  "geometry": {"coordinates":[8.925933,49.868862],"type":"Point"}
}