{
  "type": "Feature",
  "properties": {
    "iso:country":"DE",
    "sg:address":"Wiesenstr. 20 b",
    "sg:city":"Sch\u00f6nheide",
    "sg:phone":"+49 37755/3116",
    "sg:postcode":"08304",
    "sg:province":"Sachsen",
    "wof:name":"J. Seidel",
    "wof:placetype":"venue"
},
  "geometry": {"coordinates":[12.514208,50.499378],"type":"Point"}
}