{
  "type": "Feature",
  "properties": {
    "iso:country":"DE",
    "sg:address":"Benzstr. 15",
    "sg:city":"Attendorn",
    "sg:phone":"+49 2722/53619",
    "sg:postcode":"57439",
    "sg:province":"Nordrhein-Westfalen",
    "wof:name":"Pizzeria Ennest",
    "wof:placetype":"venue"
},
  "geometry": {"coordinates":[7.9182910919,51.1416282654],"type":"Point"}
}