{
  "type": "Feature",
  "properties": {
    "iso:country":"DE",
    "sg:address":"Rehstieg 7",
    "sg:city":"Elmshorn",
    "sg:phone":"+49 4121/1241",
    "sg:postcode":"25335",
    "sg:province":"Schleswig-Holstein",
    "wof:name":"Andrea Thomsen",
    "wof:placetype":"venue"
},
  "geometry": {"coordinates":[9.639380455,53.7628479004],"type":"Point"}
}