{
  "type": "Feature",
  "properties": {
    "iso:country":"DE",
    "sg:address":"Dr.-Lauter-Str. 5",
    "sg:city":"Memmingen",
    "sg:postcode":"87700",
    "sg:province":"Bayern",
    "wof:name":"Systemgastronomie Seidemann Gmbh",
    "wof:placetype":"venue"
},
  "geometry": {"coordinates":[10.1586265564,47.9956283569],"type":"Point"}
}