{
  "type": "Feature",
  "properties": {
    "iso:country":"DE",
    "sg:address":"Kahlertstr. 102",
    "sg:city":"G\u00fctersloh",
    "sg:phone":"+49 5241/340628",
    "sg:postcode":"33330",
    "sg:province":"Nordrhein-Westfalen",
    "wof:name":"Hoppenheit",
    "wof:placetype":"venue"
},
  "geometry": {"coordinates":[8.385736,51.919598],"type":"Point"}
}