{
  "type": "Feature",
  "properties": {
    "iso:country":"DE",
    "sg:address":"F\u00f6lderichstr. 64",
    "sg:city":"Berlin",
    "sg:phone":"+49 30/3315275",
    "sg:postcode":"13595",
    "sg:province":"Berlin",
    "wof:name":"Armin Feldt Metall- Und Akustikbau Gmbh",
    "wof:placetype":"venue"
},
  "geometry": {"coordinates":[13.195016,52.523773],"type":"Point"}
}