{
  "type": "Feature",
  "properties": {
    "iso:country":"DE",
    "sg:address":"Industriestr.",
    "sg:city":"Bad Krozingen",
    "sg:phone":"+49 7633/3135",
    "sg:postcode":"79189",
    "sg:province":"Baden-W\u00fcrttemberg",
    "wof:name":"Farbhandel Sch\u00f6ne",
    "wof:placetype":"venue"
},
  "geometry": {"coordinates":[7.705735,47.92157],"type":"Point"}
}