{
  "type": "Feature",
  "properties": {
    "iso:country":"DE",
    "sg:address":"Spreeweg 1",
    "sg:city":"Berlin",
    "sg:phone":"+49 30/20000",
    "sg:postcode":"10557",
    "sg:province":"Berlin",
    "wof:name":"Bundespr\u00e4sidialamt",
    "wof:placetype":"venue"
},
  "geometry": {"coordinates":[13.35467,52.517246],"type":"Point"}
}