{
  "type": "Feature",
  "properties": {
    "iso:country":"DE",
    "sg:address":"Hauptstr. 89",
    "sg:city":"Tangstedt",
    "sg:phone":"+49 4109/9249",
    "sg:postcode":"22889",
    "sg:province":"Schleswig-Holstein",
    "wof:name":"Hans-j\u00fcrgen Rathje",
    "wof:placetype":"venue"
},
  "geometry": {"coordinates":[10.0861,53.733326],"type":"Point"}
}