{
  "type": "Feature",
  "properties": {
    "iso:country":"DE",
    "sg:address":"An der Marienkirche 14",
    "sg:city":"Salzgitter",
    "sg:phone":"+49 5341/7580",
    "sg:postcode":"38229",
    "sg:province":"Niedersachsen",
    "wof:name":"Hermann Voges",
    "wof:placetype":"venue"
},
  "geometry": {"coordinates":[10.370992,52.08836],"type":"Point"}
}