{
  "type": "Feature",
  "properties": {
    "iso:country":"DE",
    "sg:address":"Parkstr. 3",
    "sg:city":"Grunewald",
    "sg:phone":"+49 39883/261",
    "sg:postcode":"17268",
    "sg:province":"Brandenburg",
    "wof:name":"Bodo Pittack",
    "wof:placetype":"venue"
},
  "geometry": {"coordinates":[13.528618,52.99313],"type":"Point"}
}