{
  "type": "Feature",
  "properties": {
    "iso:country":"DE",
    "sg:address":"Tegelweg 202 a",
    "sg:city":"Hamburg",
    "sg:phone":"+49 40/6434308",
    "sg:postcode":"22159",
    "sg:province":"Hamburg",
    "wof:name":"Karl-heinz Sch\u00fctt",
    "wof:placetype":"venue"
},
  "geometry": {"coordinates":[10.102081,53.608585],"type":"Point"}
}