{
  "type": "Feature",
  "properties": {
    "iso:country":"DE",
    "sg:address":"Postfach 1112",
    "sg:city":"Homberg",
    "sg:phone":"+49 5681",
    "sg:postcode":"34576",
    "sg:province":"Hessen",
    "wof:name":"Ilgradio\u00b4s Internationales Rundfunk Internet Verzeichniss",
    "wof:placetype":"venue"
},
  "geometry": {"coordinates":[9.406095,51.03376],"type":"Point"}
}