{
  "type": "Feature",
  "properties": {
    "iso:country":"DE",
    "sg:address":"Nordstr. 12",
    "sg:city":"Neugersdorf",
    "sg:phone":"+49 3586/7850",
    "sg:postcode":"02727",
    "sg:province":"Sachsen",
    "wof:name":"Stadtwerke Oberland Gmbh",
    "wof:placetype":"venue"
},
  "geometry": {"coordinates":[14.612022,50.987305],"type":"Point"}
}