{
  "type": "Feature",
  "properties": {
    "iso:country":"DE",
    "sg:address":"Waldstr. 46",
    "sg:city":"Saarbr\u00fccken",
    "sg:phone":"+49 681/752051",
    "sg:postcode":"66113",
    "sg:province":"Saarland",
    "wof:name":"Wr Graphics Gmbh",
    "wof:placetype":"venue"
},
  "geometry": {"coordinates":[6.962175,49.246593],"type":"Point"}
}