{
  "type": "Feature",
  "properties": {
    "iso:country":"DE",
    "sg:address":"Braunschweiger Str. 1",
    "sg:city":"Brome",
    "sg:phone":"+49 5833/1623",
    "sg:postcode":"38465",
    "sg:province":"Niedersachsen",
    "wof:name":"Gasthaus Schmidt",
    "wof:placetype":"venue"
},
  "geometry": {"coordinates":[10.9420824051,52.6013221741],"type":"Point"}
}