{
  "type": "Feature",
  "properties": {
    "iso:country":"DE",
    "sg:address":"B\u00f6lschestr. 80",
    "sg:city":"Berlin",
    "sg:phone":"+49 30/6418865",
    "sg:postcode":"12587",
    "sg:province":"Berlin",
    "wof:name":"Wohlthatsche Buchhandlung Gmbh",
    "wof:placetype":"venue"
},
  "geometry": {"coordinates":[13.6250658035,52.4553489685],"type":"Point"}
}