{
  "type": "Feature",
  "properties": {
    "iso:country":"DE",
    "sg:address":"Unterbastorf 6a",
    "sg:city":"Bastorf",
    "sg:phone":"+49 38293/13744",
    "sg:postcode":"18230",
    "sg:province":"Mecklenburg-Vorpommern",
    "wof:name":"Pension Zur Pause",
    "wof:placetype":"venue"
},
  "geometry": {"coordinates":[11.6140651703,54.1058616638],"type":"Point"}
}