{
  "type": "Feature",
  "properties": {
    "iso:country":"DE",
    "sg:address":"Lange Gasse 24",
    "sg:city":"Zw\u00f6nitz",
    "sg:phone":"+49 37754/2347",
    "sg:postcode":"08297",
    "sg:province":"Sachsen",
    "wof:name":"Hermann Maier",
    "wof:placetype":"venue"
},
  "geometry": {"coordinates":[12.809633,50.630505],"type":"Point"}
}