{
  "type": "Feature",
  "properties": {
    "iso:country":"DE",
    "sg:address":"Lindenstr. 28",
    "sg:city":"Koblenz",
    "sg:phone":"+49 261/41456",
    "sg:postcode":"56073",
    "sg:province":"Rheinland-Pfalz",
    "wof:name":"Apotheke In Der Goldgrube",
    "wof:placetype":"venue"
},
  "geometry": {"coordinates":[7.583116,50.354256],"type":"Point"}
}