{
  "type": "Feature",
  "properties": {
    "iso:country":"DE",
    "sg:address":"Homsstr. 15",
    "sg:city":"Seevetal",
    "sg:phone":"+49 700 5258 5258",
    "sg:postcode":"21220",
    "sg:province":"Niedersachsen",
    "wof:name":"Win Tech It Gmbh",
    "wof:placetype":"venue"
},
  "geometry": {"coordinates":[10.046205,53.392132],"type":"Point"}
}