{
  "type": "Feature",
  "properties": {
    "iso:country":"DE",
    "sg:address":"Kurt-Schumacher-Str. 34",
    "sg:city":"Hannover",
    "sg:phone":"+49 511/1316666",
    "sg:postcode":"30159",
    "sg:province":"Niedersachsen",
    "wof:name":"Hubensack Beteiligungsges. Mbh & Co. Verwaltungs- Kg",
    "wof:placetype":"venue"
},
  "geometry": {"coordinates":[9.733231,52.376938],"type":"Point"}
}