{
  "type": "Feature",
  "properties": {
    "iso:country":"DE",
    "sg:address":"Beckenweiherallee 2",
    "sg:city":"Ansbach",
    "sg:phone":"+49 981/9774236",
    "sg:postcode":"91522",
    "sg:province":"Bayern",
    "wof:name":"Penther",
    "wof:placetype":"venue"
},
  "geometry": {"coordinates":[10.584568,49.297298],"type":"Point"}
}