{
  "type": "Feature",
  "properties": {
    "iso:country":"DE",
    "sg:address":"Am Offenbrunn 28",
    "sg:city":"Heideck",
    "sg:phone":"+49 9177",
    "sg:postcode":"91180",
    "sg:province":"Bayern",
    "wof:name":"Prchal-grafik",
    "wof:placetype":"venue"
},
  "geometry": {"coordinates":[11.114402,49.134369],"type":"Point"}
}