{
  "type": "Feature",
  "properties": {
    "iso:country":"DE",
    "sg:address":"Perchtinger Str. 10",
    "sg:city":"M\u00fcnchen",
    "sg:phone":"+49 89/7488490",
    "sg:postcode":"81379",
    "sg:province":"Bayern",
    "wof:name":"Martin Krisam",
    "wof:placetype":"venue"
},
  "geometry": {"coordinates":[11.511126,48.095928],"type":"Point"}
}