{
  "type": "Feature",
  "properties": {
    "iso:country":"DE",
    "sg:address":"Klemensstr. 31",
    "sg:city":"Meitingen",
    "sg:phone":"+49 8271/2775",
    "sg:postcode":"86405",
    "sg:province":"Bayern",
    "wof:name":"Erwin M\u00fcller",
    "wof:placetype":"venue"
},
  "geometry": {"coordinates":[10.851183,48.528667],"type":"Point"}
}