{
  "type": "Feature",
  "properties": {
    "iso:country":"DE",
    "sg:address":"Ludwig-Jahn-Str. 12",
    "sg:city":"Alzey",
    "sg:phone":"+49 6731/8448",
    "sg:postcode":"55232",
    "sg:province":"Rheinland-Pfalz",
    "wof:name":"Anton Hegedisch",
    "wof:placetype":"venue"
},
  "geometry": {"coordinates":[8.10698,49.739685],"type":"Point"}
}