{
  "type": "Feature",
  "properties": {
    "iso:country":"DE",
    "sg:address":"Thomas-Mann-Platz 1",
    "sg:city":"Chemnitz",
    "sg:postcode":"09130",
    "sg:province":"Sachsen",
    "wof:name":"Deutsche Telekom T-punkt",
    "wof:placetype":"venue"
},
  "geometry": {"coordinates":[12.9371900558,50.8454055786],"type":"Point"}
}