{
  "type": "Feature",
  "properties": {
    "iso:country":"DE",
    "sg:address":"Dresdner Str. 63",
    "sg:city":"Leipzig",
    "sg:phone":"+49 341/6888342",
    "sg:postcode":"04317",
    "sg:province":"Sachsen",
    "wof:name":"Reudnitzer Reisen Gmbh",
    "wof:placetype":"venue"
},
  "geometry": {"coordinates":[12.4046001434,51.3383674622],"type":"Point"}
}