{
  "type": "Feature",
  "properties": {
    "iso:country":"DE",
    "sg:address":"Sch\u00f6ngeisinger Str. 2a",
    "sg:city":"F\u00fcrstenfeldbruck",
    "sg:phone":"+49 8141/18064",
    "sg:postcode":"82256",
    "sg:province":"Bayern",
    "wof:name":"Abr-amtliches Bayerisches Reiseb\u00fcro",
    "wof:placetype":"venue"
},
  "geometry": {"coordinates":[11.2550811768,48.1778297424],"type":"Point"}
}