{
  "type": "Feature",
  "properties": {
    "iso:country":"DE",
    "sg:address":"Am Elbdeich 15a",
    "sg:city":"M\u00fcggendorf",
    "sg:phone":"+49 38794/30822",
    "sg:postcode":"19322",
    "sg:province":"Brandenburg",
    "wof:name":"Eden",
    "wof:placetype":"venue"
},
  "geometry": {"coordinates":[11.6525278091,53.0089073181],"type":"Point"}
}