{
  "type": "Feature",
  "properties": {
    "iso:country":"DE",
    "sg:address":"Siemensstr 12",
    "sg:city":"Landsberg",
    "sg:phone":"+49 8191/965596",
    "sg:postcode":"86899",
    "sg:province":"Bayern",
    "wof:name":"Comed\u00ae Informationsmanagement Gmbh",
    "wof:placetype":"venue"
},
  "geometry": {"coordinates":[10.8528528214,48.0626106262],"type":"Point"}
}