{
  "type": "Feature",
  "properties": {
    "iso:country":"DE",
    "sg:address":"Pirminiusstr. 52",
    "sg:city":"Blieskastel",
    "sg:phone":"+49 6842/507558",
    "sg:postcode":"66440",
    "sg:province":"Saarland",
    "wof:name":"Wolfgang Fischer",
    "wof:placetype":"venue"
},
  "geometry": {"coordinates":[7.2548189163,49.2521820068],"type":"Point"}
}