{
  "type": "Feature",
  "properties": {
    "iso:country":"DE",
    "sg:address":"Westring 79",
    "sg:city":"Schwalbach",
    "sg:phone":"+49 6196/81385",
    "sg:postcode":"65824",
    "sg:province":"Hessen",
    "wof:name":"Dr. Hans-martin Kellner Tierarzt",
    "wof:placetype":"venue"
},
  "geometry": {"coordinates":[8.5184211731,50.1567993164],"type":"Point"}
}