{
  "type": "Feature",
  "properties": {
    "iso:country":"DE",
    "sg:address":"Waldbr\u00f6ler Str. 65",
    "sg:city":"Morsbach",
    "sg:phone":"+49 2294/90462",
    "sg:postcode":"51597",
    "sg:province":"Nordrhein-Westfalen",
    "wof:name":"Wolfgang Siefener Heilpraktiker",
    "wof:placetype":"venue"
},
  "geometry": {"coordinates":[7.725965023,50.8693771362],"type":"Point"}
}