{
  "type": "Feature",
  "properties": {
    "iso:country":"DE",
    "sg:address":"Badstr.",
    "sg:city":"Lichtenau",
    "sg:phone":"+49 9827/861",
    "sg:postcode":"91586",
    "sg:province":"Bayern",
    "wof:name":"Freibad",
    "wof:placetype":"venue"
},
  "geometry": {"coordinates":[10.6816320419,49.2719955444],"type":"Point"}
}