{
  "type": "Feature",
  "properties": {
    "iso:country":"DE",
    "sg:address":"Brohltalstr. 96",
    "sg:city":"Niederzissen",
    "sg:phone":"+49 2636/6022",
    "sg:postcode":"56651",
    "sg:province":"Rheinland-Pfalz",
    "wof:name":"Brohltal-apotheke Michael Hitzel E. Kfm.",
    "wof:placetype":"venue"
},
  "geometry": {"coordinates":[7.220763,50.459808],"type":"Point"}
}