{
  "type": "Feature",
  "properties": {
    "iso:country":"DE",
    "sg:address":"Friedrich-Lange-Str. 1",
    "sg:city":"Essen",
    "sg:phone":"+49 201/663365",
    "sg:postcode":"45356",
    "sg:province":"Nordrhein-Westfalen",
    "wof:name":"Ev. Pfarramt Bergeborbeck-vogelheim",
    "wof:placetype":"venue"
},
  "geometry": {"coordinates":[6.9792838097,51.4766082764],"type":"Point"}
}