{
  "type": "Feature",
  "properties": {
    "iso:country":"DE",
    "sg:address":"Buxheimer Str. 116",
    "sg:city":"Memmingen",
    "sg:phone":"+49 8331/97730",
    "sg:postcode":"87700",
    "sg:province":"Bayern",
    "wof:name":"Hermann Kutter Landschaftsbau & Sportplatzbau Gmbh",
    "wof:placetype":"venue"
},
  "geometry": {"coordinates":[10.153506,47.992405],"type":"Point"}
}