{
  "type": "Feature",
  "properties": {
    "iso:country":"DE",
    "sg:address":"Hauptstr. 37",
    "sg:city":"Reken",
    "sg:phone":"+49 2864/1297",
    "sg:postcode":"48734",
    "sg:province":"Nordrhein-Westfalen",
    "wof:name":"G\u00fcnter Niewerth",
    "wof:placetype":"venue"
},
  "geometry": {"coordinates":[7.040561,51.831898],"type":"Point"}
}