{
  "type": "Feature",
  "properties": {
    "iso:country":"DE",
    "sg:address":"H\u00f6her Weg 42",
    "sg:city":"L\u00fcdenscheid",
    "sg:phone":"+49 2351/458733",
    "sg:postcode":"58511",
    "sg:province":"Nordrhein-Westfalen",
    "wof:name":"Dr. Gert Bremecker Tierarzt",
    "wof:placetype":"venue"
},
  "geometry": {"coordinates":[7.6444301605,51.2054214478],"type":"Point"}
}