{
  "type": "Feature",
  "properties": {
    "iso:country":"DE",
    "sg:address":"M\u00fchlenstr. 9",
    "sg:city":"Friedersdorf",
    "sg:phone":"+49 33767/80278",
    "sg:postcode":"15754",
    "sg:province":"Brandenburg",
    "wof:name":"Friedack - Friedersdorfer Ackerbau Und Tierzucht-",
    "wof:placetype":"venue"
},
  "geometry": {"coordinates":[13.788066,52.298527],"type":"Point"}
}