{
  "type": "Feature",
  "properties": {
    "iso:country":"DE",
    "sg:address":"Heggenstr. 3",
    "sg:city":"Melle",
    "sg:phone":"+49 5429/410",
    "sg:postcode":"49326",
    "sg:province":"Niedersachsen",
    "wof:name":"Bernhard Theiling",
    "wof:placetype":"venue"
},
  "geometry": {"coordinates":[8.262432,52.15955],"type":"Point"}
}