{
  "type": "Feature",
  "properties": {
    "iso:country":"DE",
    "sg:address":"Frerener Str. 36",
    "sg:city":"Lingen",
    "sg:phone":"+49 591/2145",
    "sg:postcode":"49809",
    "sg:province":"Niedersachsen",
    "wof:name":"H. Reiter",
    "wof:placetype":"venue"
},
  "geometry": {"coordinates":[7.343357,52.518337],"type":"Point"}
}