{
  "type": "Feature",
  "properties": {
    "iso:country":"DE",
    "sg:address":"Schillerstr. 6",
    "sg:city":"\u00dcberherrn",
    "sg:phone":"+49 6836/2974",
    "sg:postcode":"66802",
    "sg:province":"Saarland",
    "wof:name":"Wohnstadtcafe Portz Gmbh",
    "wof:placetype":"venue"
},
  "geometry": {"coordinates":[6.706169,49.238705],"type":"Point"}
}