{
  "type": "Feature",
  "properties": {
    "iso:country":"DE",
    "sg:address":"Albstr. 53",
    "sg:city":"Burladingen",
    "sg:phone":"+49 7475/8472",
    "sg:postcode":"72393",
    "sg:province":"Baden-W\u00fcrttemberg",
    "wof:name":"Sebastian Hauser",
    "wof:placetype":"venue"
},
  "geometry": {"coordinates":[9.1186237335,48.2919807434],"type":"Point"}
}