{
  "type": "Feature",
  "properties": {
    "iso:country":"DE",
    "sg:address":"Kyffh\u00e4userstr. 60",
    "sg:city":"Wuppertal",
    "sg:phone":"+49 202/710223",
    "sg:postcode":"42115",
    "sg:province":"Nordrhein-Westfalen",
    "wof:name":"N\u00fctzenberger H\u00f6he",
    "wof:placetype":"venue"
},
  "geometry": {"coordinates":[7.116232872,51.2515907288],"type":"Point"}
}