{
  "type": "Feature",
  "properties": {
    "iso:country":"DE",
    "sg:address":"Kastanienstr 7",
    "sg:city":"Lichtenstein",
    "sg:phone":"+49 37204/590",
    "sg:postcode":"09350",
    "sg:province":"Sachsen",
    "wof:name":"Geberit Lichtenstein Gmbh",
    "wof:placetype":"venue"
},
  "geometry": {"coordinates":[12.6347703934,50.754108429],"type":"Point"}
}