{
  "type": "Feature",
  "properties": {
    "iso:country":"DE",
    "sg:address":"Kursiefer Weg 12",
    "sg:city":"Leverkusen",
    "sg:phone":"+49 214/8505628",
    "sg:postcode":"51375",
    "sg:province":"Nordrhein-Westfalen",
    "wof:name":"R. Richter",
    "wof:placetype":"venue"
},
  "geometry": {"coordinates":[7.0787220001,51.0324935913],"type":"Point"}
}