{
  "type": "Feature",
  "properties": {
    "iso:country":"DE",
    "sg:address":"Hauptstr. 89",
    "sg:city":"Tegernheim",
    "sg:phone":"+49 9403/2536",
    "sg:postcode":"93105",
    "sg:province":"Bayern",
    "wof:name":"Martha Zahnweh Drogerie",
    "wof:placetype":"venue"
},
  "geometry": {"coordinates":[12.17219,49.024567],"type":"Point"}
}