{
  "type": "Feature",
  "properties": {
    "iso:country":"DE",
    "sg:address":"Reepschl\u00e4gerstr. 10b",
    "sg:city":"L\u00fcbeck",
    "sg:phone":"+49 451/8999401",
    "sg:postcode":"23556",
    "sg:province":"Schleswig-Holstein",
    "wof:name":"Flexschlauch Produktions Gmbh",
    "wof:placetype":"venue"
},
  "geometry": {"coordinates":[10.615794,53.863262],"type":"Point"}
}