{
  "type": "Feature",
  "properties": {
    "iso:country":"DE",
    "sg:address":"Auf dem Gleichen 6",
    "sg:city":"Haan",
    "sg:phone":"+49 212/9344610",
    "sg:postcode":"42781",
    "sg:province":"Nordrhein-Westfalen",
    "wof:name":"Fides Hausbau Gmbh",
    "wof:placetype":"venue"
},
  "geometry": {"coordinates":[7.023665,51.194397],"type":"Point"}
}