{
  "type": "Feature",
  "properties": {
    "iso:country":"DE",
    "sg:city":"N\u00fcrnberg",
    "sg:postcode":"90478",
    "sg:province":"Bayern",
    "wof:name":"Gluecklich Leben",
    "wof:placetype":"venue"
},
  "geometry": {"coordinates":[11.10362,49.437752],"type":"Point"}
}