{
  "type": "Feature",
  "properties": {
    "iso:country":"DE",
    "sg:address":"Sch\u00f6nholzer Str. 9",
    "sg:city":"Berlin",
    "sg:phone":"+49 30/4856990",
    "sg:postcode":"13187",
    "sg:province":"Berlin",
    "wof:name":"Elcovek B\u00fcrotechnik Ingenieurbetrieb Gmbh",
    "wof:placetype":"venue"
},
  "geometry": {"coordinates":[13.399233,52.570183],"type":"Point"}
}