{
  "type": "Feature",
  "properties": {
    "iso:country":"DE",
    "sg:address":"Hauptstr. 37",
    "sg:city":"Gundelfingen",
    "sg:phone":"+49 9073/7217",
    "sg:postcode":"89423",
    "sg:province":"Bayern",
    "wof:name":"Karl Hinterst\u00f6sser Inh. Robert Schmid",
    "wof:placetype":"venue"
},
  "geometry": {"coordinates":[10.3664140701,48.5527038574],"type":"Point"}
}