{
  "type": "Feature",
  "properties": {
    "iso:country":"DE",
    "sg:address":"Bachwiesenweg 41",
    "sg:city":"Bruckm\u00fchl",
    "sg:phone":"+49 8062/6583",
    "sg:postcode":"83052",
    "sg:province":"Bayern",
    "wof:name":"Sportverein Bruckm\u00fchl E. V.",
    "wof:placetype":"venue"
},
  "geometry": {"coordinates":[11.9171199799,47.8710708618],"type":"Point"}
}