{
  "type": "Feature",
  "properties": {
    "iso:country":"DE",
    "sg:address":"Stadelbachstr. 21",
    "sg:city":"Tiefenbronn",
    "sg:phone":"+49 7234/7678",
    "sg:postcode":"75233",
    "sg:province":"Baden-W\u00fcrttemberg",
    "wof:name":"K. P. Lorson Steuerberater",
    "wof:placetype":"venue"
},
  "geometry": {"coordinates":[8.8210048676,48.8102607727],"type":"Point"}
}