{
  "type": "Feature",
  "properties": {
    "iso:country":"DE",
    "sg:address":"Auf das Loh 6",
    "sg:city":"Hainburg",
    "sg:phone":"+49 6182/4313",
    "sg:postcode":"63512",
    "sg:province":"Hessen",
    "wof:name":"Blum\u00f6r Gmbh",
    "wof:placetype":"venue"
},
  "geometry": {"coordinates":[8.9312229156,50.0766067505],"type":"Point"}
}