{
  "type": "Feature",
  "properties": {
    "iso:country":"DE",
    "sg:address":"Hagenbacher Str. 5 a",
    "sg:city":"Berg",
    "sg:postcode":"76768",
    "sg:province":"Rheinland-Pfalz",
    "wof:name":"Monti-takeaway Gmbh",
    "wof:placetype":"venue"
},
  "geometry": {"coordinates":[8.1831130981,48.9786720276],"type":"Point"}
}