{
  "type": "Feature",
  "properties": {
    "iso:country":"DE",
    "sg:address":"Steind\u00f6rfel 8a",
    "sg:city":"Hochkirch",
    "sg:phone":"+49 35939/80073",
    "sg:postcode":"02627",
    "sg:province":"Sachsen",
    "wof:name":"Kloss Keramik",
    "wof:placetype":"venue"
},
  "geometry": {"coordinates":[14.5441713333,51.1552658081],"type":"Point"}
}