{
  "type": "Feature",
  "properties": {
    "iso:country":"DE",
    "sg:address":"Deining",
    "sg:city":"Deining",
    "sg:phone":"+49 9184/985",
    "sg:postcode":"92364",
    "sg:province":"Bayern",
    "wof:name":"Raiffeisenbank Parsberg Eg",
    "wof:placetype":"venue"
},
  "geometry": {"coordinates":[11.539553,49.223656],"type":"Point"}
}