{
  "type": "Feature",
  "properties": {
    "iso:country":"DE",
    "sg:address":"Leienstr. 13",
    "sg:city":"Monheim",
    "sg:phone":"+49 2173/65753",
    "sg:postcode":"40789",
    "sg:province":"Nordrhein-Westfalen",
    "wof:name":"M. Starosielec",
    "wof:placetype":"venue"
},
  "geometry": {"coordinates":[6.8865399361,51.1172523499],"type":"Point"}
}