{
  "type": "Feature",
  "properties": {
    "iso:country":"DE",
    "sg:address":"G\u00e4ns\u00e4ckerstr. 54",
    "sg:city":"Calw",
    "sg:phone":"+49 7051/79200",
    "sg:postcode":"75365",
    "sg:province":"Baden-W\u00fcrttemberg",
    "wof:name":"Steuerberatung Treuhand- Revisions- Und Beratungs-gmbh",
    "wof:placetype":"venue"
},
  "geometry": {"coordinates":[8.7711429596,48.6976699829],"type":"Point"}
}