{
  "type": "Feature",
  "properties": {
    "iso:country":"DE",
    "sg:address":"Sachsenbergstr. 3",
    "sg:city":"K\u00f6ln",
    "sg:postcode":"51063",
    "sg:province":"Nordrhein-Westfalen",
    "wof:name":"Treibgut Personenbef\u00f6rderung Und Veranstaltungen Gmbh",
    "wof:placetype":"venue"
},
  "geometry": {"coordinates":[6.9806060791,50.9510383606],"type":"Point"}
}