{
  "type": "Feature",
  "properties": {
    "iso:country":"DE",
    "sg:address":"Unterortstr. 36",
    "sg:city":"Eschborn",
    "sg:phone":"+49 6196/45751",
    "sg:postcode":"65760",
    "sg:province":"Hessen",
    "wof:name":"Aerocontact Gmbh",
    "wof:placetype":"venue"
},
  "geometry": {"coordinates":[8.5711698532,50.1415748596],"type":"Point"}
}