{
  "type": "Feature",
  "properties": {
    "iso:country":"DE",
    "sg:address":"Weidweg 7",
    "sg:city":"Freiburg",
    "sg:phone":"+49 761/81517",
    "sg:postcode":"79110",
    "sg:province":"Baden-W\u00fcrttemberg",
    "wof:name":"H. Eckerle",
    "wof:placetype":"venue"
},
  "geometry": {"coordinates":[7.8224620819,48.0150756836],"type":"Point"}
}