{
  "type": "Feature",
  "properties": {
    "iso:country":"DE",
    "sg:address":"Regensburger Str. 26",
    "sg:city":"Schwandorf",
    "sg:phone":"+49 9431/56270",
    "sg:postcode":"92421",
    "sg:province":"Bayern",
    "wof:name":"Friedel",
    "wof:placetype":"venue"
},
  "geometry": {"coordinates":[12.105099,49.319725],"type":"Point"}
}