{
  "type": "Feature",
  "properties": {
    "iso:country":"DE",
    "sg:address":"Woringer Str. 6",
    "sg:city":"Memmingen",
    "sg:phone":"+49 8331/86147",
    "sg:postcode":"87700",
    "sg:province":"Bayern",
    "wof:name":"G\u00fcnther",
    "wof:placetype":"venue"
},
  "geometry": {"coordinates":[10.1840305328,47.9713020325],"type":"Point"}
}