{
  "type": "Feature",
  "properties": {
    "iso:country":"DE",
    "sg:address":"Schulgasse 6",
    "sg:city":"Wasungen",
    "sg:phone":"+49 36940/50294",
    "sg:postcode":"98634",
    "sg:province":"Th\u00fcringen",
    "wof:name":"Kero Bau- Und Baustoffhandel Gmbh",
    "wof:placetype":"venue"
},
  "geometry": {"coordinates":[10.3702192307,50.6634216309],"type":"Point"}
}