{
  "type": "Feature",
  "properties": {
    "iso:country":"DE",
    "sg:address":"M\u00fchlengrube 38",
    "sg:city":"Wismar",
    "sg:phone":"+49 3841/28000",
    "sg:postcode":"23966",
    "sg:province":"Mecklenburg-Vorpommern",
    "wof:name":"Bartholl Versicherungs- Vermittlung Gmbh",
    "wof:placetype":"venue"
},
  "geometry": {"coordinates":[11.468082428,53.895614624],"type":"Point"}
}