{
  "type": "Feature",
  "properties": {
    "iso:country":"DE",
    "sg:address":"Hofmarkstr. 21",
    "sg:city":"Sankt Wolfgang",
    "sg:phone":"+49 8085/281",
    "sg:postcode":"84427",
    "sg:province":"Bayern",
    "wof:name":"Paula Hofinger",
    "wof:placetype":"venue"
},
  "geometry": {"coordinates":[12.1353397369,48.2222518921],"type":"Point"}
}