{
  "type": "Feature",
  "properties": {
    "iso:country":"DE",
    "sg:address":"POSTFACH 4::",
    "sg:city":"Sta\u00dffurt",
    "sg:phone":"+49 4939/2580260",
    "sg:postcode":"39401",
    "sg:province":"Sachsen-Anhalt",
    "wof:name":"Kreissparkasse Aschersleben- Stassfurt",
    "wof:placetype":"venue"
},
  "geometry": {"coordinates":[11.58834,51.85305],"type":"Point"}
}