{
  "type": "Feature",
  "properties": {
    "iso:country":"DE",
    "sg:address":"Dallweg 7",
    "sg:city":"Halle",
    "sg:phone":"+49 5201/9541",
    "sg:postcode":"33790",
    "sg:province":"Nordrhein-Westfalen",
    "wof:name":"Alfred K\u00f6lkebeck",
    "wof:placetype":"venue"
},
  "geometry": {"coordinates":[8.283649,52.005245],"type":"Point"}
}