{
  "type": "Feature",
  "properties": {
    "iso:country":"DE",
    "sg:address":"Hauptstr. 40",
    "sg:city":"Reichshof",
    "sg:phone":"+49 2265/371",
    "sg:postcode":"51580",
    "sg:province":"Nordrhein-Westfalen",
    "wof:name":"Heinz T\u00f6pler Elektroinstallation",
    "wof:placetype":"venue"
},
  "geometry": {"coordinates":[7.694062,50.987282],"type":"Point"}
}