{
  "type": "Feature",
  "properties": {
    "iso:country":"DE",
    "sg:address":"Auf dem Wilcher 5",
    "sg:city":"Breitenbach",
    "sg:phone":"+49 6386/5757",
    "sg:postcode":"66916",
    "sg:province":"Rheinland-Pfalz",
    "wof:name":"G. Kopp",
    "wof:placetype":"venue"
},
  "geometry": {"coordinates":[7.2650570869,49.4317359924],"type":"Point"}
}