{
  "type": "Feature",
  "properties": {
    "iso:country":"DE",
    "sg:address":"Mauermattenstr. 10",
    "sg:city":"Buggingen",
    "sg:phone":"+49 7634/2735",
    "sg:postcode":"79426",
    "sg:province":"Baden-W\u00fcrttemberg",
    "wof:name":"Georg Sauer \u00c4rztebedarf",
    "wof:placetype":"venue"
},
  "geometry": {"coordinates":[7.636285,47.862167],"type":"Point"}
}