{
  "type": "Feature",
  "properties": {
    "iso:country":"DE",
    "sg:address":"Haeg 47",
    "sg:city":"Haeg-Ehrsberg",
    "sg:phone":"+49 7625/924005",
    "sg:postcode":"79685",
    "sg:province":"Baden-W\u00fcrttemberg",
    "wof:name":"Die Homepage Der Baeckerei Schelb In Haeg",
    "wof:placetype":"venue"
},
  "geometry": {"coordinates":[7.919768,47.734741],"type":"Point"}
}