{
  "type": "Feature",
  "properties": {
    "iso:country":"DE",
    "sg:address":"Deutscher Ring 44",
    "sg:city":"Wuppertal",
    "sg:phone":"+49 202/749988",
    "sg:postcode":"42327",
    "sg:province":"Nordrhein-Westfalen",
    "wof:name":"Induk Gmbh",
    "wof:placetype":"venue"
},
  "geometry": {"coordinates":[7.097409,51.24736],"type":"Point"}
}