{
  "type": "Feature",
  "properties": {
    "iso:country":"DE",
    "sg:address":"Herzog-Georg-Str. 6",
    "sg:city":"Altom\u00fcnster",
    "sg:postcode":"85250",
    "sg:province":"Bayern",
    "wof:name":"Mairs Backstube Ohg",
    "wof:placetype":"venue"
},
  "geometry": {"coordinates":[11.255966,48.388195],"type":"Point"}
}