{
  "type": "Feature",
  "properties": {
    "iso:country":"DE",
    "sg:address":"Buckower Damm 189",
    "sg:city":"Berlin",
    "sg:postcode":"12349",
    "sg:province":"Berlin",
    "wof:name":"Aldi Gmbh & Co. Kg",
    "wof:placetype":"venue"
},
  "geometry": {"coordinates":[13.4353990555,52.4265670776],"type":"Point"}
}