{
  "type": "Feature",
  "properties": {
    "iso:country":"DE",
    "sg:address":"Sch\u00f6nbuchstr. 44",
    "sg:city":"Aichtal",
    "sg:phone":"+49 7127/57990",
    "sg:postcode":"72631",
    "sg:province":"Baden-W\u00fcrttemberg",
    "wof:name":"Tennis-club Neuenhaus E. V.",
    "wof:placetype":"venue"
},
  "geometry": {"coordinates":[9.2029256821,48.6207466125],"type":"Point"}
}