{
  "type": "Feature",
  "properties": {
    "iso:country":"DE",
    "sg:address":"Sollingstr. 62",
    "sg:city":"Dassel",
    "sg:phone":"+49 5562/1543",
    "sg:postcode":"37586",
    "sg:province":"Niedersachsen",
    "wof:name":"G\u00e4rtner",
    "wof:placetype":"venue"
},
  "geometry": {"coordinates":[9.61433,51.811119],"type":"Point"}
}