{
  "type": "Feature",
  "properties": {
    "iso:country":"DE",
    "sg:address":"Warendorpstr. 35",
    "sg:city":"L\u00fcbeck",
    "sg:phone":"+49 451/477478",
    "sg:postcode":"23554",
    "sg:province":"Schleswig-Holstein",
    "wof:name":"Warnow Immobilien- Und Bautr\u00e4ger Gmbh",
    "wof:placetype":"venue"
},
  "geometry": {"coordinates":[10.676414,53.876732],"type":"Point"}
}