{
  "type": "Feature",
  "properties": {
    "iso:country":"DE",
    "sg:address":"Auenstr. 3",
    "sg:city":"Schweinfurt",
    "sg:phone":"+49 9721/185041",
    "sg:postcode":"97421",
    "sg:province":"Bayern",
    "wof:name":"Elektro J. Orth",
    "wof:placetype":"venue"
},
  "geometry": {"coordinates":[10.2240447998,50.0491752625],"type":"Point"}
}