{
  "type": "Feature",
  "properties": {
    "iso:country":"DE",
    "sg:address":"Sondersh\u00e4user Str. 102",
    "sg:city":"Nohra",
    "sg:phone":"+49 36334/50537",
    "sg:postcode":"99735",
    "sg:province":"Th\u00fcringen",
    "wof:name":"Atlas Copco Mct Gmbh",
    "wof:placetype":"venue"
},
  "geometry": {"coordinates":[10.69723,51.433266],"type":"Point"}
}