{
  "type": "Feature",
  "properties": {
    "iso:country":"DE",
    "sg:address":"Ochtendunger Str. 9",
    "sg:city":"Saffig",
    "sg:phone":"+49 2625/6657",
    "sg:postcode":"56648",
    "sg:province":"Rheinland-Pfalz",
    "wof:name":"Ricco Heimtier Gmbh",
    "wof:placetype":"venue"
},
  "geometry": {"coordinates":[7.414785862,50.3788261414],"type":"Point"}
}