{
  "type": "Feature",
  "properties": {
    "iso:country":"DE",
    "sg:address":"Bertolt-Brecht-Allee 24",
    "sg:city":"Dresden",
    "sg:phone":"+49 351/64160",
    "sg:postcode":"01309",
    "sg:province":"Sachsen",
    "wof:name":"Dv-com Edith Gretzschel",
    "wof:placetype":"venue"
},
  "geometry": {"coordinates":[13.780499,51.041748],"type":"Point"}
}