{
  "type": "Feature",
  "properties": {
    "iso:country":"DE",
    "sg:address":"Burgweilerstr 13",
    "sg:city":"Pfrungen",
    "sg:phone":"+49 7558/244",
    "sg:postcode":"88271",
    "sg:province":"Baden-W\u00fcrttemberg",
    "wof:name":"Kneer Torf- Und Erdenwerke",
    "wof:placetype":"venue"
},
  "geometry": {"coordinates":[9.396357,47.874027],"type":"Point"}
}