{
  "type": "Feature",
  "properties": {
    "iso:country":"DE",
    "sg:address":"Kurf\u00fcrstenstr. 75",
    "sg:city":"Berlin",
    "sg:postcode":"10787",
    "sg:province":"Berlin",
    "wof:name":"Hot Carwash Autowaschanlagen Gmbh",
    "wof:placetype":"venue"
},
  "geometry": {"coordinates":[13.3485927582,52.5036468506],"type":"Point"}
}