{
  "type": "Feature",
  "properties": {
    "iso:country":"DE",
    "sg:address":"Mittelkanal Rechts 92",
    "sg:city":"Papenburg",
    "sg:phone":"+49 4961/97840",
    "sg:postcode":"26871",
    "sg:province":"Niedersachsen",
    "wof:name":"Bestattungen Hubert Siemer E. K.",
    "wof:placetype":"venue"
},
  "geometry": {"coordinates":[7.437114,53.079254],"type":"Point"}
}