{
  "type": "Feature",
  "properties": {
    "iso:country":"DE",
    "sg:address":"Am Lindenanger 4",
    "sg:city":"Forchheim",
    "sg:phone":"+49 9191/13352",
    "sg:postcode":"91301",
    "sg:province":"Bayern",
    "wof:name":"Friedr. H\u00fcbschmann",
    "wof:placetype":"venue"
},
  "geometry": {"coordinates":[11.059222,49.72443],"type":"Point"}
}