{
  "type": "Feature",
  "properties": {
    "iso:country":"DE",
    "sg:address":"H\u00f6ger Damm 16",
    "sg:city":"Essen",
    "sg:phone":"+49 5434/2601",
    "sg:postcode":"49632",
    "sg:province":"Niedersachsen",
    "wof:name":"Heinrich Nietfeld",
    "wof:placetype":"venue"
},
  "geometry": {"coordinates":[7.928951,52.753231],"type":"Point"}
}