{
  "type": "Feature",
  "properties": {
    "iso:country":"DE",
    "sg:address":"Ratsm\u00fchlendamm 9",
    "sg:city":"Hamburg",
    "sg:phone":"+49 40/50053680",
    "sg:postcode":"22335",
    "sg:province":"Hamburg",
    "wof:name":"Csf Computer Service Fuhlsb\u00fcttel Gmbh",
    "wof:placetype":"venue"
},
  "geometry": {"coordinates":[10.0277738571,53.6258888245],"type":"Point"}
}