{
  "type": "Feature",
  "properties": {
    "iso:country":"DE",
    "sg:address":"Mergenthalerallee 10-",
    "sg:city":"Eschborn",
    "sg:phone":"+49 6196/9960",
    "sg:postcode":"65760",
    "sg:province":"Hessen",
    "wof:name":"Arthur Andersen Wirtschaftspr\u00fcfungsges.",
    "wof:placetype":"venue"
},
  "geometry": {"coordinates":[8.5674753189,50.133518219],"type":"Point"}
}