{
  "type": "Feature",
  "properties": {
    "iso:country":"DE",
    "sg:address":"Birkenbergstr. 20-22",
    "sg:city":"Leverkusen",
    "sg:phone":"+49 2171/44440",
    "sg:postcode":"51379",
    "sg:province":"Nordrhein-Westfalen",
    "wof:name":"Blumenparadies Horst Bausch",
    "wof:placetype":"venue"
},
  "geometry": {"coordinates":[7.001671,51.065571],"type":"Point"}
}