{
  "type": "Feature",
  "properties": {
    "iso:country":"DE",
    "sg:address":"Im Faas 1",
    "sg:city":"W\u00fcschheim",
    "sg:phone":"+49 6762/9110",
    "sg:postcode":"55471",
    "sg:province":"Rheinland-Pfalz",
    "wof:name":"Rwe Umwelt Rheinland- Pfalz Nord Gmbh",
    "wof:placetype":"venue"
},
  "geometry": {"coordinates":[7.380111,50.014172],"type":"Point"}
}