{
  "type": "Feature",
  "properties": {
    "iso:country":"DE",
    "sg:address":"Allee 1",
    "sg:city":"Holzwickede",
    "sg:phone":"+49 2301/2257",
    "sg:postcode":"59439",
    "sg:province":"Nordrhein-Westfalen",
    "wof:name":"Helga Pflug",
    "wof:placetype":"venue"
},
  "geometry": {"coordinates":[7.618103981,51.5028419495],"type":"Point"}
}