{
  "type": "Feature",
  "properties": {
    "iso:country":"DE",
    "sg:address":"Am Leihdenberg 4",
    "sg:city":"Kleinjena",
    "sg:phone":"+49 3445/208417",
    "sg:postcode":"06618",
    "sg:province":"Sachsen-Anhalt",
    "wof:name":"Karl-heinz Broderius",
    "wof:placetype":"venue"
},
  "geometry": {"coordinates":[11.8205280304,51.1440734863],"type":"Point"}
}