{
  "type": "Feature",
  "properties": {
    "iso:country":"DE",
    "sg:address":"Massendorfer Str. 8",
    "sg:city":"Spalt",
    "sg:phone":"+49 9175/78866",
    "sg:postcode":"91174",
    "sg:province":"Bayern",
    "wof:name":"Rudolf Kittsteiner",
    "wof:placetype":"venue"
},
  "geometry": {"coordinates":[10.926401,49.18111],"type":"Point"}
}