{
  "type": "Feature",
  "properties": {
    "iso:country":"DE",
    "sg:address":"Sch\u00fctzenstr. 189",
    "sg:city":"Neuburg",
    "sg:phone":"+49 8431/645963",
    "sg:postcode":"86633",
    "sg:province":"Bayern",
    "wof:name":"Cafe Unico",
    "wof:placetype":"venue"
},
  "geometry": {"coordinates":[11.184602,48.735207],"type":"Point"}
}