{
  "type": "Feature",
  "properties": {
    "iso:country":"DE",
    "sg:address":"Dorfstr. 35",
    "sg:city":"Kotelow",
    "sg:phone":"+49 39607/20228",
    "sg:postcode":"17099",
    "sg:province":"Mecklenburg-Vorpommern",
    "wof:name":"Koeppen",
    "wof:placetype":"venue"
},
  "geometry": {"coordinates":[13.4523200989,53.6041755676],"type":"Point"}
}