{
  "type": "Feature",
  "properties": {
    "iso:country":"DE",
    "sg:address":"Fichtenstr. 18",
    "sg:city":"Schwedeneck",
    "sg:phone":"+49 4308/414",
    "sg:postcode":"24229",
    "sg:province":"Schleswig-Holstein",
    "wof:name":"Lothar Schakinnis Architekt",
    "wof:placetype":"venue"
},
  "geometry": {"coordinates":[10.121449,54.476315],"type":"Point"}
}