{
  "type": "Feature",
  "properties": {
    "iso:country":"DE",
    "sg:address":"Rosenaustr. 36",
    "sg:city":"Augsburg",
    "sg:phone":"+49 821/516226",
    "sg:postcode":"86150",
    "sg:province":"Bayern",
    "wof:name":"H. Prechter Kunstmaler",
    "wof:placetype":"venue"
},
  "geometry": {"coordinates":[10.882405,48.364632],"type":"Point"}
}