{
  "type": "Feature",
  "properties": {
    "iso:country":"DE",
    "sg:address":"Lucienv\u00f6rder Allee 1",
    "sg:city":"Hildesheim",
    "sg:phone":"+49 5121/35575",
    "sg:postcode":"31139",
    "sg:province":"Niedersachsen",
    "wof:name":"Badeanstalt Johanniswiese",
    "wof:placetype":"venue"
},
  "geometry": {"coordinates":[9.9451541901,52.1429481506],"type":"Point"}
}