{
  "type": "Feature",
  "properties": {
    "iso:country":"DE",
    "sg:address":"Piusallee 8",
    "sg:city":"M\u00fcnster",
    "sg:phone":"+49 251/484880",
    "sg:postcode":"48147",
    "sg:province":"Nordrhein-Westfalen",
    "wof:name":"Baumeister Und Partner",
    "wof:placetype":"venue"
},
  "geometry": {"coordinates":[7.6370940208,51.9628295898],"type":"Point"}
}