{
  "type": "Feature",
  "properties": {
    "iso:country":"DE",
    "sg:address":"Etzelstr. 13",
    "sg:city":"Stutensee",
    "sg:phone":"+49 7244/96037",
    "sg:postcode":"76297",
    "sg:province":"Baden-W\u00fcrttemberg",
    "wof:name":"Eltos Kuhn Gmbh",
    "wof:placetype":"venue"
},
  "geometry": {"coordinates":[8.47184,49.070698],"type":"Point"}
}