{
  "type": "Feature",
  "properties": {
    "iso:country":"DE",
    "sg:address":"Schulthei\u00dfstr. 30",
    "sg:city":"Bonn",
    "sg:phone":"+49 228/466053",
    "sg:postcode":"53225",
    "sg:province":"Nordrhein-Westfalen",
    "wof:name":"Orthonova Sieglinde Hessenm\u00fcller",
    "wof:placetype":"venue"
},
  "geometry": {"coordinates":[7.13063,50.752003],"type":"Point"}
}