{
  "type": "Feature",
  "properties": {
    "iso:country":"DE",
    "sg:address":"H\u00fcttenweg",
    "sg:city":"Ilsede",
    "sg:phone":"+49 5344/7074",
    "sg:postcode":"31241",
    "sg:province":"Niedersachsen",
    "wof:name":"Filcon Gmbh",
    "wof:placetype":"venue"
},
  "geometry": {"coordinates":[10.218715,52.264301],"type":"Point"}
}