{
  "type": "Feature",
  "properties": {
    "iso:country":"DE",
    "sg:address":"Kniprodestr. 60",
    "sg:city":"Berlin",
    "sg:postcode":"10407",
    "sg:province":"Berlin",
    "wof:name":"Baureparaturen Gmbh Prenzlauer Berg",
    "wof:placetype":"venue"
},
  "geometry": {"coordinates":[13.4552755356,52.5406799316],"type":"Point"}
}