{
  "type": "Feature",
  "properties": {
    "iso:country":"DE",
    "sg:address":"Bergstr. 7",
    "sg:city":"Winkelbach",
    "sg:phone":"+49 2680/378",
    "sg:postcode":"57644",
    "sg:province":"Rheinland-Pfalz",
    "wof:name":"Alfred Deimling",
    "wof:placetype":"venue"
},
  "geometry": {"coordinates":[7.731051,50.642815],"type":"Point"}
}