{
  "type": "Feature",
  "properties": {
    "iso:country":"DE",
    "sg:address":"Rheinbacher Str. 36",
    "sg:city":"Meckenheim",
    "sg:phone":"+49 2225/6234",
    "sg:postcode":"53340",
    "sg:province":"Nordrhein-Westfalen",
    "wof:name":"Hans-peter Wi\u00dfkirchen",
    "wof:placetype":"venue"
},
  "geometry": {"coordinates":[7.0045151711,50.5951347351],"type":"Point"}
}