{
  "type": "Feature",
  "properties": {
    "iso:country":"DE",
    "sg:address":"Richard-Wagner-Stra\u00dfe 22",
    "sg:city":"V\u00f6lklingen",
    "sg:phone":"+49 6898",
    "sg:postcode":"66333",
    "sg:province":"Saarland",
    "wof:name":"Compac - Exklusive Quarzb\u00f6den Gmbh",
    "wof:placetype":"venue"
},
  "geometry": {"coordinates":[6.8632178307,49.25522995],"type":"Point"}
}