{
  "type": "Feature",
  "properties": {
    "iso:country":"DE",
    "sg:address":"Angerstr 18",
    "sg:city":"Halle",
    "sg:phone":"+49 345/5220431",
    "sg:postcode":"06118",
    "sg:province":"Sachsen-Anhalt",
    "wof:name":"Gebauer Lagertechnik Gmbh",
    "wof:placetype":"venue"
},
  "geometry": {"coordinates":[11.959487,51.526703],"type":"Point"}
}