{
  "type": "Feature",
  "properties": {
    "iso:country":"DE",
    "sg:address":"M\u00fcnchenerstr. 9",
    "sg:city":"Gro\u00df-Gerau",
    "sg:phone":"+49 6158",
    "sg:postcode":"64521",
    "sg:province":"Hessen",
    "wof:name":"Form Acryl Funktion Und Design In Acrylglas",
    "wof:placetype":"venue"
},
  "geometry": {"coordinates":[8.481933,49.922211],"type":"Point"}
}