{
  "type": "Feature",
  "properties": {
    "iso:country":"DE",
    "sg:address":"Rudolf-Diesel-Str. 4",
    "sg:city":"Asbach-B\u00e4umenheim",
    "sg:phone":"+49 906/9770",
    "sg:postcode":"86663",
    "sg:province":"Bayern",
    "wof:name":"Squash Oase Gmbh",
    "wof:placetype":"venue"
},
  "geometry": {"coordinates":[10.811786,48.669811],"type":"Point"}
}