{
  "type": "Feature",
  "properties": {
    "iso:country":"DE",
    "sg:address":"Ahornweg 5",
    "sg:city":"Kreuzwertheim",
    "sg:phone":"+49 9342/3345",
    "sg:postcode":"97892",
    "sg:province":"Bayern",
    "wof:name":"Schuck Bau Thomas Schuck E. K.",
    "wof:placetype":"venue"
},
  "geometry": {"coordinates":[9.531936,49.77462],"type":"Point"}
}