{
  "type": "Feature",
  "properties": {
    "iso:country":"DE",
    "sg:address":"Sommerhaldenstr. 25",
    "sg:city":"Alth\u00fctte",
    "sg:phone":"+49 7183/42543",
    "sg:postcode":"71566",
    "sg:province":"Baden-W\u00fcrttemberg",
    "wof:name":"T. D\u00f6rflinger Heilpraktiker",
    "wof:placetype":"venue"
},
  "geometry": {"coordinates":[9.5700292587,48.9116134644],"type":"Point"}
}