{
  "type": "Feature",
  "properties": {
    "iso:country":"DE",
    "sg:address":"Eckernf\u00f6rder Chaussee 9-11",
    "sg:city":"Gettorf",
    "sg:phone":"+49 4346/413595",
    "sg:postcode":"24214",
    "sg:province":"Schleswig-Holstein",
    "wof:name":"Irmak Ramazan Telekommunikation",
    "wof:placetype":"venue"
},
  "geometry": {"coordinates":[9.9776573181,54.4121704102],"type":"Point"}
}