{
  "type": "Feature",
  "properties": {
    "iso:country":"DE",
    "sg:address":"Gerhard-Hansen-Str. 24",
    "sg:city":"Sulzbach-Laufen",
    "sg:phone":"+49 7976/98760",
    "sg:postcode":"74429",
    "sg:province":"Baden-W\u00fcrttemberg",
    "wof:name":"Willi Bauer",
    "wof:placetype":"venue"
},
  "geometry": {"coordinates":[9.8600378036,48.9452514648],"type":"Point"}
}