{
  "type": "Feature",
  "properties": {
    "iso:country":"DE",
    "sg:address":"Friedensstr. 61",
    "sg:city":"Hanau",
    "sg:phone":"+49 6181/259270",
    "sg:postcode":"63454",
    "sg:province":"Hessen",
    "wof:name":"Siegmund Urff Architekt",
    "wof:placetype":"venue"
},
  "geometry": {"coordinates":[8.890071,50.136181],"type":"Point"}
}