{
  "type": "Feature",
  "properties": {
    "iso:country":"DE",
    "sg:address":"Bei der B\u00f6rne 6",
    "sg:city":"Stade",
    "sg:phone":"+49 4141/44114",
    "sg:postcode":"21682",
    "sg:province":"Niedersachsen",
    "wof:name":"Holst",
    "wof:placetype":"venue"
},
  "geometry": {"coordinates":[9.474414,53.601925],"type":"Point"}
}