{
  "type": "Feature",
  "properties": {
    "iso:country":"DE",
    "sg:address":"Petersilienstr. 10",
    "sg:city":"Goslar",
    "sg:phone":"+49 5321/24903",
    "sg:postcode":"38640",
    "sg:province":"Niedersachsen",
    "wof:name":"Arno Rausch",
    "wof:placetype":"venue"
},
  "geometry": {"coordinates":[10.428730011,51.9088783264],"type":"Point"}
}