{
  "type": "Feature",
  "properties": {
    "iso:country":"DE",
    "sg:address":"Dorfstr. 82",
    "sg:city":"Weil am Rhein",
    "sg:phone":"+49 7621/62228",
    "sg:postcode":"79576",
    "sg:province":"Baden-W\u00fcrttemberg",
    "wof:name":"Ochsen",
    "wof:placetype":"venue"
},
  "geometry": {"coordinates":[7.6376271248,47.6257743835],"type":"Point"}
}