{
  "type": "Feature",
  "properties": {
    "iso:country":"DE",
    "sg:address":"Friedensstr. 3 a",
    "sg:city":"Oschatz",
    "sg:phone":"+49 3435/622425",
    "sg:postcode":"04758",
    "sg:province":"Sachsen",
    "wof:name":"Rolladenservice Christian Sch\u00f6ne Gmbh",
    "wof:placetype":"venue"
},
  "geometry": {"coordinates":[13.104551,51.305176],"type":"Point"}
}