{
  "type": "Feature",
  "properties": {
    "iso:country":"DE",
    "sg:address":"Morsestr. 9 a",
    "sg:city":"K\u00f6ln",
    "sg:phone":"+49 221/9703200",
    "sg:postcode":"50769",
    "sg:province":"Nordrhein-Westfalen",
    "wof:name":"Kurth Kunststoffindustrie- Und Und Rohrleitungsbau Gmbh",
    "wof:placetype":"venue"
},
  "geometry": {"coordinates":[6.924727,51.038155],"type":"Point"}
}