{
  "type": "Feature",
  "properties": {
    "iso:country":"DE",
    "sg:address":"Waldweg 13",
    "sg:city":"Malter",
    "sg:phone":"+49 3504/614246",
    "sg:postcode":"01744",
    "sg:province":"Sachsen",
    "wof:name":"H. Scharfe",
    "wof:placetype":"venue"
},
  "geometry": {"coordinates":[13.6549367905,50.8967170715],"type":"Point"}
}