{
  "type": "Feature",
  "properties": {
    "iso:country":"DE",
    "sg:address":"Sternstr. 52",
    "sg:city":"Bonn",
    "sg:phone":"+49 228/652430",
    "sg:postcode":"53111",
    "sg:province":"Nordrhein-Westfalen",
    "wof:name":"Ledermoden Sackewitz",
    "wof:placetype":"venue"
},
  "geometry": {"coordinates":[7.099278,50.735897],"type":"Point"}
}