{
  "type": "Feature",
  "properties": {
    "iso:country":"DE",
    "sg:address":"Altm\u00fchlweg 8",
    "sg:city":"Leutershausen",
    "sg:phone":"+49 9803/460",
    "sg:postcode":"91578",
    "sg:province":"Bayern",
    "wof:name":"Willi Krau\u00df",
    "wof:placetype":"venue"
},
  "geometry": {"coordinates":[10.3757820129,49.3384437561],"type":"Point"}
}