{
  "type": "Feature",
  "properties": {
    "iso:country":"DE",
    "sg:address":"Rechtenbacher Str. 1",
    "sg:city":"H\u00fcttenberg",
    "sg:phone":"+49 6403/4776",
    "sg:postcode":"35625",
    "sg:province":"Hessen",
    "wof:name":"Willi Dern",
    "wof:placetype":"venue"
},
  "geometry": {"coordinates":[8.625814,50.517857],"type":"Point"}
}