{
  "type": "Feature",
  "properties": {
    "iso:country":"DE",
    "sg:address":"Levetzowstr. 16",
    "sg:city":"Berlin",
    "sg:phone":"+49 30/3995842",
    "sg:postcode":"10555",
    "sg:province":"Berlin",
    "wof:name":"Schreibwaren B. Volk",
    "wof:placetype":"venue"
},
  "geometry": {"coordinates":[13.3368501663,52.5203819275],"type":"Point"}
}