{
  "type": "Feature",
  "properties": {
    "iso:country":"DE",
    "sg:address":"Weher Str. 7",
    "sg:city":"Rahden",
    "sg:phone":"+49 5771/97310",
    "sg:postcode":"32369",
    "sg:province":"Nordrhein-Westfalen",
    "wof:name":"Red. Diepholzer Kreisblatt",
    "wof:placetype":"venue"
},
  "geometry": {"coordinates":[8.6176595688,52.4336013794],"type":"Point"}
}