{
  "type": "Feature",
  "properties": {
    "iso:country":"DE",
    "sg:address":"Buchenweg 49",
    "sg:city":"Baden-Baden",
    "sg:phone":"+49 7221/65485",
    "sg:postcode":"76532",
    "sg:province":"Baden-W\u00fcrttemberg",
    "wof:name":"Kade Vertriebs Gmbh",
    "wof:placetype":"venue"
},
  "geometry": {"coordinates":[8.2282781601,48.7890472412],"type":"Point"}
}