{
  "type": "Feature",
  "properties": {
    "iso:country":"DE",
    "sg:address":"Bachemer Str. 412",
    "sg:city":"K\u00f6ln",
    "sg:phone":"+49 221/4302772",
    "sg:postcode":"50935",
    "sg:province":"Nordrhein-Westfalen",
    "wof:name":"Bzc Edv-beratungs Gmbh",
    "wof:placetype":"venue"
},
  "geometry": {"coordinates":[6.8970341682,50.9212226868],"type":"Point"}
}