{
  "type": "Feature",
  "properties": {
    "iso:country":"DE",
    "sg:address":"Teilbachstr. 1",
    "sg:city":"Wertheim",
    "sg:phone":"+49 9342/6673",
    "sg:postcode":"97877",
    "sg:province":"Baden-W\u00fcrttemberg",
    "wof:name":"Ev. Pfarramt",
    "wof:placetype":"venue"
},
  "geometry": {"coordinates":[9.4941902161,49.7307701111],"type":"Point"}
}