{
  "type": "Feature",
  "properties": {
    "iso:country":"DE",
    "sg:address":"Robert-Koch-Str. 31",
    "sg:city":"Alsdorf",
    "sg:phone":"+49 2404/20139",
    "sg:postcode":"52477",
    "sg:province":"Nordrhein-Westfalen",
    "wof:name":"Heinz Ruppert",
    "wof:placetype":"venue"
},
  "geometry": {"coordinates":[6.1595001221,50.8768386841],"type":"Point"}
}