{
  "type": "Feature",
  "properties": {
    "iso:country":"DE",
    "sg:address":"Saalbahnhofstr. 12a",
    "sg:city":"Jena",
    "sg:phone":"+49 3641/22825",
    "sg:postcode":"07743",
    "sg:province":"Th\u00fcringen",
    "wof:name":"Ofen-, Kamin- Und Fliesenbau Jena Gmbh",
    "wof:placetype":"venue"
},
  "geometry": {"coordinates":[11.5899925232,50.9323768616],"type":"Point"}
}