{
  "type": "Feature",
  "properties": {
    "iso:country":"DE",
    "sg:city":"Katzow",
    "sg:postcode":"17509",
    "sg:province":"Mecklenburg-Vorpommern",
    "wof:name":"Gemeindeschwesterstation Katzow",
    "wof:placetype":"venue"
},
  "geometry": {"coordinates":[13.674716,54.048954],"type":"Point"}
}