{
  "type": "Feature",
  "properties": {
    "iso:country":"DE",
    "sg:address":"Hauptstr. 33",
    "sg:city":"Emmingen-Liptingen",
    "sg:phone":"+49 7465/830",
    "sg:postcode":"78576",
    "sg:province":"Baden-W\u00fcrttemberg",
    "wof:name":"Bernd Gnir\u00df",
    "wof:placetype":"venue"
},
  "geometry": {"coordinates":[8.8514814377,47.930431366],"type":"Point"}
}