{
  "type": "Feature",
  "properties": {
    "iso:country":"DE",
    "sg:address":"Alt Salbke 96",
    "sg:city":"Magdeburg",
    "sg:phone":"+49 391/4020219",
    "sg:postcode":"39122",
    "sg:province":"Sachsen-Anhalt",
    "wof:name":"Klosterhof-apotheke Inh. Armin Herold",
    "wof:placetype":"venue"
},
  "geometry": {"coordinates":[11.66671,52.079708],"type":"Point"}
}