{
  "type": "Feature",
  "properties": {
    "iso:country":"DE",
    "sg:address":"Sch\u00fctzeberger Str. 49",
    "sg:city":"Wolfhagen",
    "sg:phone":"+49 5692/2241",
    "sg:postcode":"34466",
    "sg:province":"Hessen",
    "wof:name":"Cafe L\u00f6wenstein Inh. Philipp L\u00f6wenstein",
    "wof:placetype":"venue"
},
  "geometry": {"coordinates":[9.169439,51.326595],"type":"Point"}
}