{
  "type": "Feature",
  "properties": {
    "iso:country":"DE",
    "sg:address":"Rathausstr. 12",
    "sg:city":"Kleinaitingen",
    "sg:phone":"+49 8203/6274",
    "sg:postcode":"86507",
    "sg:province":"Bayern",
    "wof:name":"Gr\u00fcnig",
    "wof:placetype":"venue"
},
  "geometry": {"coordinates":[10.844761,48.217079],"type":"Point"}
}