{
  "type": "Feature",
  "properties": {
    "iso:country":"DE",
    "sg:address":"Poppenb\u00fctteler Weg 197",
    "sg:city":"Hamburg",
    "sg:phone":"+49 40/6067250",
    "sg:postcode":"22399",
    "sg:province":"Hamburg",
    "wof:name":"Awo Pflegen Und Betreuen Sozialstation Poppenb\u00fcttel",
    "wof:placetype":"venue"
},
  "geometry": {"coordinates":[10.084794,53.658943],"type":"Point"}
}