{
  "type": "Feature",
  "properties": {
    "iso:country":"DE",
    "sg:address":"Rotbuschweg 1",
    "sg:city":"Sundern",
    "sg:phone":"+49 2933/3570",
    "sg:postcode":"59846",
    "sg:province":"Nordrhein-Westfalen",
    "wof:name":"Manuel Sanchez-cobos",
    "wof:placetype":"venue"
},
  "geometry": {"coordinates":[8.004818,51.324036],"type":"Point"}
}