{
  "type": "Feature",
  "properties": {
    "iso:country":"DE",
    "sg:address":"Hauer Grenzweg 25",
    "sg:city":"Bedburg-Hau",
    "sg:phone":"+49 2821/40290",
    "sg:postcode":"47551",
    "sg:province":"Nordrhein-Westfalen",
    "wof:name":"Karl-heinz Janssen",
    "wof:placetype":"venue"
},
  "geometry": {"coordinates":[6.162674,51.745907],"type":"Point"}
}