{
  "type": "Feature",
  "properties": {
    "iso:country":"DE",
    "sg:address":"Diestedder Str.39",
    "sg:city":"Wadersloh",
    "sg:phone":"+49 2523",
    "sg:postcode":"59329",
    "sg:province":"Nordrhein-Westfalen",
    "wof:name":"Gloria-werke, H.schulte-farnkenfeld Gmbh & Co.",
    "wof:placetype":"venue"
},
  "geometry": {"coordinates":[8.2327852249,51.7323074341],"type":"Point"}
}