{
  "type": "Feature",
  "properties": {
    "iso:country":"DE",
    "sg:address":"Gewerbehof 28",
    "sg:city":"Werne",
    "sg:phone":"+49 2389/8015",
    "sg:postcode":"59368",
    "sg:province":"Nordrhein-Westfalen",
    "wof:name":"Lbs Baumaschinen Vertriebs Gmbh",
    "wof:placetype":"venue"
},
  "geometry": {"coordinates":[7.606641,51.663136],"type":"Point"}
}