{
  "type": "Feature",
  "properties": {
    "iso:country":"DE",
    "sg:address":"Ulmer Str. 141",
    "sg:city":"Aalen",
    "sg:postcode":"73431",
    "sg:province":"Baden-W\u00fcrttemberg",
    "wof:name":"It & C Information Technology Und Communication Consulting",
    "wof:placetype":"venue"
},
  "geometry": {"coordinates":[10.1110401154,48.8292198181],"type":"Point"}
}