{
  "type": "Feature",
  "properties": {
    "iso:country":"DE",
    "sg:address":"Friedinger Str. 58",
    "sg:city":"Langenenslingen",
    "sg:phone":"+49 7376/397",
    "sg:postcode":"88515",
    "sg:province":"Baden-W\u00fcrttemberg",
    "wof:name":"Gairing Gmbh",
    "wof:placetype":"venue"
},
  "geometry": {"coordinates":[9.3780479431,48.1489028931],"type":"Point"}
}