{
  "type": "Feature",
  "properties": {
    "iso:country":"DE",
    "sg:address":"Hirtengasse 17",
    "sg:city":"Braunsbach",
    "sg:phone":"+49 7906/479",
    "sg:postcode":"74542",
    "sg:province":"Baden-W\u00fcrttemberg",
    "wof:name":"Fritz Etzel",
    "wof:placetype":"venue"
},
  "geometry": {"coordinates":[9.772169,49.222424],"type":"Point"}
}