{
  "type": "Feature",
  "properties": {
    "iso:country":"DE",
    "sg:address":"H\u00e4hnelstr. 9",
    "sg:city":"Berlin",
    "sg:phone":"+49 30/8520073",
    "sg:postcode":"12159",
    "sg:province":"Berlin",
    "wof:name":"Gellwitzki Und Sch\u00e4fer Rechtsanw\u00e4lte",
    "wof:placetype":"venue"
},
  "geometry": {"coordinates":[13.339258194,52.4754676819],"type":"Point"}
}