{
  "type": "Feature",
  "properties": {
    "iso:country":"DE",
    "sg:address":"Schwandlichstr. 2",
    "sg:city":"Neufra",
    "sg:phone":"+49 7574/2061",
    "sg:postcode":"72419",
    "sg:province":"Baden-W\u00fcrttemberg",
    "wof:name":"R. Scheppach",
    "wof:placetype":"venue"
},
  "geometry": {"coordinates":[9.121814,48.23872],"type":"Point"}
}