{
  "type": "Feature",
  "properties": {
    "iso:country":"DE",
    "sg:address":"Carlsh\u00fctte 6",
    "sg:city":"Dautphetal",
    "sg:phone":"+49 6466/1227",
    "sg:postcode":"35232",
    "sg:province":"Hessen",
    "wof:name":"Ullrich Metallbau Gmbh",
    "wof:placetype":"venue"
},
  "geometry": {"coordinates":[8.5867061615,50.8616333008],"type":"Point"}
}