{
  "type": "Feature",
  "properties": {
    "iso:country":"DE",
    "sg:address":"Remy-und-Geiser-Str. 1",
    "sg:city":"Altenfeld",
    "sg:phone":"+49 36781/4880",
    "sg:postcode":"98701",
    "sg:province":"Th\u00fcringen",
    "wof:name":"Remy & Geiser Gmbh",
    "wof:placetype":"venue"
},
  "geometry": {"coordinates":[10.976026535,50.5680847168],"type":"Point"}
}