{
  "type": "Feature",
  "properties": {
    "iso:country":"DE",
    "sg:address":"Charlottenstr. 45-51",
    "sg:city":"Reutlingen",
    "sg:phone":"+49 7121/489401",
    "sg:postcode":"72764",
    "sg:province":"Baden-W\u00fcrttemberg",
    "wof:name":"Rwt Anwaltskanzlei Gmbh",
    "wof:placetype":"venue"
},
  "geometry": {"coordinates":[9.2195997238,48.4947509766],"type":"Point"}
}