{
  "type": "Feature",
  "properties": {
    "iso:country":"DE",
    "sg:address":"Radickestr. 31",
    "sg:city":"Hamburg",
    "sg:phone":"+49 40/7633043",
    "sg:postcode":"21079",
    "sg:province":"Hamburg",
    "wof:name":"Dkr Altenwohnanlage Harburg",
    "wof:placetype":"venue"
},
  "geometry": {"coordinates":[10.000134,53.438679],"type":"Point"}
}