{
  "type": "Feature",
  "properties": {
    "iso:country":"DE",
    "sg:address":"Bienenweide 5",
    "sg:city":"Ahrensb\u00f6k",
    "sg:phone":"+49 4525/2581",
    "sg:postcode":"23623",
    "sg:province":"Schleswig-Holstein",
    "wof:name":"Eberhard Kolmsee",
    "wof:placetype":"venue"
},
  "geometry": {"coordinates":[10.5769815445,54.0130615234],"type":"Point"}
}