{
  "type": "Feature",
  "properties": {
    "iso:country":"DE",
    "sg:address":"Heinrich-Steinweg-Str. 17",
    "sg:city":"Langelsheim",
    "sg:postcode":"38685",
    "sg:province":"Niedersachsen",
    "wof:name":"Ccs-cook & Clean Service Gmbh",
    "wof:placetype":"venue"
},
  "geometry": {"coordinates":[10.318314,51.909092],"type":"Point"}
}