{
  "type": "Feature",
  "properties": {
    "iso:country":"DE",
    "sg:address":"Hilsbach 5",
    "sg:city":"Durbach",
    "sg:phone":"+49 781/43535",
    "sg:postcode":"77770",
    "sg:province":"Baden-W\u00fcrttemberg",
    "wof:name":"Werner Zimmermann",
    "wof:placetype":"venue"
},
  "geometry": {"coordinates":[8.012514,48.494686],"type":"Point"}
}