{
  "type": "Feature",
  "properties": {
    "iso:country":"DE",
    "sg:address":"Gnadauer Str. 4",
    "sg:city":"Gro\u00dfm\u00fchlingen",
    "sg:phone":"+49 39297/2710",
    "sg:postcode":"39221",
    "sg:province":"Sachsen-Anhalt",
    "wof:name":"Malerbetrieb Kersten Gmbh",
    "wof:placetype":"venue"
},
  "geometry": {"coordinates":[11.71145,51.956528],"type":"Point"}
}