{
  "type": "Feature",
  "properties": {
    "iso:country":"DE",
    "sg:address":"Nu\u00dfbergstr. 80",
    "sg:city":"Iserlohn",
    "sg:phone":"+49 2371/36880",
    "sg:postcode":"58638",
    "sg:province":"Nordrhein-Westfalen",
    "wof:name":"Herbert Lustinetz Wettannahme",
    "wof:placetype":"venue"
},
  "geometry": {"coordinates":[7.688975,51.387253],"type":"Point"}
}