{
  "type": "Feature",
  "properties": {
    "iso:country":"DE",
    "sg:address":"Wangerlandstr. 8",
    "sg:city":"Wiefelstede",
    "sg:phone":"+49 4402/60102",
    "sg:postcode":"26215",
    "sg:province":"Niedersachsen",
    "wof:name":"Fred Heinzelmann Ingenieur",
    "wof:placetype":"venue"
},
  "geometry": {"coordinates":[8.1145591736,53.2626876831],"type":"Point"}
}