{
  "type": "Feature",
  "properties": {
    "iso:country":"DE",
    "sg:address":"Beethovenstr. 19",
    "sg:city":"Karlstein",
    "sg:phone":"+49 6188/6657",
    "sg:postcode":"63791",
    "sg:province":"Bayern",
    "wof:name":"Taxi-he\u00dfberger",
    "wof:placetype":"venue"
},
  "geometry": {"coordinates":[9.016744,50.049809],"type":"Point"}
}