{
  "type": "Feature",
  "properties": {
    "iso:country":"DE",
    "sg:address":"Billstr. 181",
    "sg:city":"Hamburg",
    "sg:phone":"+49 40/787778",
    "sg:postcode":"20539",
    "sg:province":"Hamburg",
    "wof:name":"Ziems Stahlhandel Gmbh",
    "wof:placetype":"venue"
},
  "geometry": {"coordinates":[10.054371,53.537155],"type":"Point"}
}