{
  "type": "Feature",
  "properties": {
    "iso:country":"DE",
    "sg:address":"Radegaster Str. 10",
    "sg:city":"Dessau",
    "sg:phone":"+49 340/8822164",
    "sg:postcode":"06842",
    "sg:province":"Sachsen-Anhalt",
    "wof:name":"Evangelische Bibliothek",
    "wof:placetype":"venue"
},
  "geometry": {"coordinates":[12.240093,51.82407],"type":"Point"}
}