{
  "type": "Feature",
  "properties": {
    "iso:country":"DE",
    "sg:address":"Adickesallee 47",
    "sg:city":"Frankfurt",
    "sg:phone":"+49 69/550338",
    "sg:postcode":"60322",
    "sg:province":"Hessen",
    "wof:name":"Cm Institut",
    "wof:placetype":"venue"
},
  "geometry": {"coordinates":[8.6770544052,50.1321411133],"type":"Point"}
}