{
  "type": "Feature",
  "properties": {
    "iso:country":"DE",
    "sg:address":"Archivstr. 3-5",
    "sg:city":"Stade",
    "sg:phone":"+49 4141/922724",
    "sg:postcode":"21682",
    "sg:province":"Niedersachsen",
    "wof:name":"Archiv Der Ritterschaft Des Herzogt. Bremen U. D. Landsch.",
    "wof:placetype":"venue"
},
  "geometry": {"coordinates":[9.478029,53.599125],"type":"Point"}
}