{
  "type": "Feature",
  "properties": {
    "iso:country":"DE",
    "sg:address":"Hauptstr. 89",
    "sg:city":"Pulheim",
    "sg:phone":"+49 2238/2214",
    "sg:postcode":"50259",
    "sg:province":"Nordrhein-Westfalen",
    "wof:name":"Gastst\u00e4tte G. Sauerland",
    "wof:placetype":"venue"
},
  "geometry": {"coordinates":[6.7595920563,51.0198440552],"type":"Point"}
}