{
  "type": "Feature",
  "properties": {
    "iso:country":"DE",
    "sg:address":"Bienenweg 6",
    "sg:city":"Erlangen",
    "sg:phone":"+49 9131/65294",
    "sg:postcode":"91058",
    "sg:province":"Bayern",
    "wof:name":"Dietmar Helf Masseur",
    "wof:placetype":"venue"
},
  "geometry": {"coordinates":[10.992526,49.565826],"type":"Point"}
}