{
  "type": "Feature",
  "properties": {
    "iso:country":"DE",
    "sg:address":"Wagnerstr. 7",
    "sg:city":"Pohlheim",
    "sg:phone":"+49 6404/4511",
    "sg:postcode":"35415",
    "sg:province":"Hessen",
    "wof:name":"Ire",
    "wof:placetype":"venue"
},
  "geometry": {"coordinates":[8.7518606186,50.5355796814],"type":"Point"}
}