{
  "type": "Feature",
  "properties": {
    "iso:country":"DE",
    "sg:address":"Grenzweg 29",
    "sg:city":"Eibau",
    "sg:phone":"+49 3586/310525",
    "sg:postcode":"02739",
    "sg:province":"Sachsen",
    "wof:name":"E. R\u00f6ttig",
    "wof:placetype":"venue"
},
  "geometry": {"coordinates":[14.6337995529,50.9986305237],"type":"Point"}
}