{
  "type": "Feature",
  "properties": {
    "iso:country":"DE",
    "sg:address":"Br\u00fcderstr. 48",
    "sg:city":"Soest",
    "sg:phone":"+49 2921/15546",
    "sg:postcode":"59494",
    "sg:province":"Nordrhein-Westfalen",
    "wof:name":"Albert Engbers Gmbh",
    "wof:placetype":"venue"
},
  "geometry": {"coordinates":[8.103356,51.575699],"type":"Point"}
}