{
  "type": "Feature",
  "properties": {
    "iso:country":"DE",
    "sg:address":"Im Grund 14",
    "sg:city":"Saal",
    "sg:phone":"+49 9441/177990",
    "sg:postcode":"93342",
    "sg:province":"Bayern",
    "wof:name":"Pepper Designergy",
    "wof:placetype":"venue"
},
  "geometry": {"coordinates":[11.93999,48.90279],"type":"Point"}
}