{
  "type": "Feature",
  "properties": {
    "iso:country":"DE",
    "sg:address":"M\u00fchlenstr. 57",
    "sg:city":"L\u00fcdinghausen",
    "sg:phone":"+49 2591/3708",
    "sg:postcode":"59348",
    "sg:province":"Nordrhein-Westfalen",
    "wof:name":"Helmut Letsch Steuerberater",
    "wof:placetype":"venue"
},
  "geometry": {"coordinates":[7.4504909515,51.7710494995],"type":"Point"}
}