{
  "type": "Feature",
  "properties": {
    "iso:country":"DE",
    "sg:address":"\u00dcber dem Hainberg 23",
    "sg:city":"Weilburg",
    "sg:phone":"+49 6471/30951",
    "sg:postcode":"35781",
    "sg:province":"Hessen",
    "wof:name":"Susanne Weil",
    "wof:placetype":"venue"
},
  "geometry": {"coordinates":[8.2594,50.485962],"type":"Point"}
}