{
  "type": "Feature",
  "properties": {
    "iso:country":"DE",
    "sg:address":"Rudolf-Diesel-Str. 9",
    "sg:city":"H\u00f6hr-Grenzhausen",
    "sg:phone":"+49 2624/2470",
    "sg:postcode":"56203",
    "sg:province":"Rheinland-Pfalz",
    "wof:name":"Blumen-priebe",
    "wof:placetype":"venue"
},
  "geometry": {"coordinates":[7.673954,50.440571],"type":"Point"}
}