{
  "type": "Feature",
  "properties": {
    "iso:country":"DE",
    "sg:address":"Haydnstr. 8",
    "sg:city":"Krefeld",
    "sg:phone":"+49 2151/591784",
    "sg:postcode":"47800",
    "sg:province":"Nordrhein-Westfalen",
    "wof:name":"Dr. Peter Pokorny Rechtsanwalt",
    "wof:placetype":"venue"
},
  "geometry": {"coordinates":[6.5861778259,51.3434677124],"type":"Point"}
}