{
  "type": "Feature",
  "properties": {
    "iso:country":"DE",
    "sg:address":"Kleine K\u00f6nigstr. 11",
    "sg:city":"Stuttgart",
    "sg:phone":"+49 711/2991592",
    "sg:postcode":"70178",
    "sg:province":"Baden-W\u00fcrttemberg",
    "wof:name":"Japanisches Restaurant",
    "wof:placetype":"venue"
},
  "geometry": {"coordinates":[9.1739635468,48.7731437683],"type":"Point"}
}