{
  "type": "Feature",
  "properties": {
    "iso:country":"DE",
    "sg:address":"K\u00f6nigst\u00e4dter Str. 34",
    "sg:city":"Nauheim",
    "sg:phone":"+49 6152/61523",
    "sg:postcode":"64569",
    "sg:province":"Hessen",
    "wof:name":"Hildegard Schwenger",
    "wof:placetype":"venue"
},
  "geometry": {"coordinates":[8.451284,49.946636],"type":"Point"}
}