{
  "type": "Feature",
  "properties": {
    "iso:country":"DE",
    "sg:address":"Karl-Liebknecht-Str. 5",
    "sg:city":"Potsdam",
    "sg:phone":"+49 331/7405128",
    "sg:postcode":"14482",
    "sg:province":"Brandenburg",
    "wof:name":"Bahnhof Apotheke Babelsberg Stephan K\u00e4rgell",
    "wof:placetype":"venue"
},
  "geometry": {"coordinates":[13.091617,52.391773],"type":"Point"}
}