{
  "type": "Feature",
  "properties": {
    "iso:country":"DE",
    "sg:address":"Lauterbacher Str. 4",
    "sg:city":"Florstadt",
    "sg:phone":"+49 6041/300",
    "sg:postcode":"61197",
    "sg:province":"Hessen",
    "wof:name":"H. Knoll",
    "wof:placetype":"venue"
},
  "geometry": {"coordinates":[8.943903,50.332462],"type":"Point"}
}