{
  "type": "Feature",
  "properties": {
    "iso:country":"DE",
    "sg:address":"Otto-Schmirgal-Str. 1",
    "sg:city":"Berlin",
    "sg:phone":"+49 30/32709271",
    "sg:postcode":"10319",
    "sg:province":"Berlin",
    "wof:name":"M.a.r.v.i.n. Sportswear Gmbh",
    "wof:placetype":"venue"
},
  "geometry": {"coordinates":[13.522789,52.497456],"type":"Point"}
}