{
  "type": "Feature",
  "properties": {
    "iso:country":"DE",
    "sg:address":"Spichraer Str. 1",
    "sg:city":"Eisenach",
    "sg:phone":"+49 36928/90253",
    "sg:postcode":"99817",
    "sg:province":"Th\u00fcringen",
    "wof:name":"G. Busch",
    "wof:placetype":"venue"
},
  "geometry": {"coordinates":[10.230498,51.009293],"type":"Point"}
}