{
  "type": "Feature",
  "properties": {
    "iso:country":"DE",
    "sg:address":"Papenwisch 9",
    "sg:city":"Gro\u00dfhansdorf",
    "sg:phone":"+49 4102/61697",
    "sg:postcode":"22927",
    "sg:province":"Schleswig-Holstein",
    "wof:name":"Redaktion German Maritime Industry Journal",
    "wof:placetype":"venue"
},
  "geometry": {"coordinates":[10.2824668884,53.6506729126],"type":"Point"}
}