{
  "type": "Feature",
  "properties": {
    "iso:country":"DE",
    "sg:address":"Kleinliebringer Str. 13",
    "sg:city":"Gro\u00dfliebringen",
    "sg:phone":"+49 3629/802271",
    "sg:postcode":"99326",
    "sg:province":"Th\u00fcringen",
    "wof:name":"Gasthaus Zur Tulpe",
    "wof:placetype":"venue"
},
  "geometry": {"coordinates":[11.1245098114,50.7514381409],"type":"Point"}
}