{
  "type": "Feature",
  "properties": {
    "iso:country":"DE",
    "sg:address":"Hauptstr. 10",
    "sg:city":"L\u00f6ningen",
    "sg:phone":"+49 5432/2860",
    "sg:postcode":"49624",
    "sg:province":"Niedersachsen",
    "wof:name":"Katholisches Pfarramt Mari\u00e4 Himmelfahrt",
    "wof:placetype":"venue"
},
  "geometry": {"coordinates":[7.7206201553,52.7957687378],"type":"Point"}
}