{
  "type": "Feature",
  "properties": {
    "iso:country":"DE",
    "sg:address":"Am Becker 12",
    "sg:city":"Sprockh\u00f6vel",
    "sg:phone":"+49 2324/97350",
    "sg:postcode":"45549",
    "sg:province":"Nordrhein-Westfalen",
    "wof:name":"Egbert Buchwald Ingenieur",
    "wof:placetype":"venue"
},
  "geometry": {"coordinates":[7.2541937828,51.3779067993],"type":"Point"}
}