{
  "type": "Feature",
  "properties": {
    "iso:country":"DE",
    "sg:address":"Lindenstr. 23",
    "sg:city":"Bad Saulgau",
    "sg:phone":"+49 7581/7496",
    "sg:postcode":"88348",
    "sg:province":"Baden-W\u00fcrttemberg",
    "wof:name":"H. Heim",
    "wof:placetype":"venue"
},
  "geometry": {"coordinates":[9.496251,48.016048],"type":"Point"}
}