{
  "type": "Feature",
  "properties": {
    "iso:country":"DE",
    "sg:address":"Zum Gipsberg 21",
    "sg:city":"Merzig",
    "sg:phone":"+49 6861/793444",
    "sg:postcode":"66663",
    "sg:province":"Saarland",
    "wof:name":"Kerstin Hansen Rechtsanw\u00e4ltin",
    "wof:placetype":"venue"
},
  "geometry": {"coordinates":[6.6574158669,49.4462928772],"type":"Point"}
}