{
  "type": "Feature",
  "properties": {
    "iso:country":"DE",
    "sg:address":"Kleiner Markt",
    "sg:city":"Saarlouis",
    "sg:phone":"+49 6831/43044",
    "sg:postcode":"66740",
    "sg:province":"Saarland",
    "wof:name":"Mc Donalds",
    "wof:placetype":"venue"
},
  "geometry": {"coordinates":[6.7533388138,49.3135757446],"type":"Point"}
}