{
  "type": "Feature",
  "properties": {
    "iso:country":"DE",
    "sg:address":"Hauptstr. 102",
    "sg:city":"Bergisch Gladbach",
    "sg:phone":"+49 2202/51721",
    "sg:postcode":"51465",
    "sg:province":"Nordrhein-Westfalen",
    "wof:name":"Karl Heinrich Kellershohn Inh. Markus M\u00fcller",
    "wof:placetype":"venue"
},
  "geometry": {"coordinates":[7.123131,50.988701],"type":"Point"}
}