{
  "type": "Feature",
  "properties": {
    "iso:country":"DE",
    "sg:address":"Burgstr. 14",
    "sg:city":"Salzwedel",
    "sg:phone":"+49 3901/26116",
    "sg:postcode":"29410",
    "sg:province":"Sachsen-Anhalt",
    "wof:name":"Jeans-schapp Gmbh",
    "wof:placetype":"venue"
},
  "geometry": {"coordinates":[11.152418,52.852318],"type":"Point"}
}