{
  "type": "Feature",
  "properties": {
    "iso:country":"DE",
    "sg:address":"Oertelstr. 2a",
    "sg:city":"D\u00fcsseldorf",
    "sg:phone":"+49 211/334022",
    "sg:postcode":"40225",
    "sg:province":"Nordrhein-Westfalen",
    "wof:name":"Aquila Markenvertriebs- Gmbh & Co. Kg",
    "wof:placetype":"venue"
},
  "geometry": {"coordinates":[6.7898950577,51.2011222839],"type":"Point"}
}