{
  "type": "Feature",
  "properties": {
    "iso:country":"DE",
    "sg:address":"Raiffeisenstr. 6",
    "sg:city":"Heddesheim",
    "sg:phone":"+49 4962/034751",
    "sg:postcode":"68542",
    "sg:province":"Baden-W\u00fcrttemberg",
    "wof:name":"Graf Gmbh",
    "wof:placetype":"venue"
},
  "geometry": {"coordinates":[8.6280908585,49.5050735474],"type":"Point"}
}