{
  "type": "Feature",
  "properties": {
    "iso:country":"DE",
    "sg:address":"Dischinger Str. 4",
    "sg:city":"Fleinheim",
    "sg:phone":"+49 4973/276370",
    "sg:postcode":"89564",
    "sg:province":"Baden-W\u00fcrttemberg",
    "wof:name":"Kreissparkasse Heidenheim",
    "wof:placetype":"venue"
},
  "geometry": {"coordinates":[10.297579,48.706963],"type":"Point"}
}