{
  "type": "Feature",
  "properties": {
    "iso:country":"DE",
    "sg:address":"Ostermeiersfeld 10",
    "sg:city":"H\u00fcllhorst",
    "sg:phone":"+49 5741/310730",
    "sg:postcode":"32609",
    "sg:province":"Nordrhein-Westfalen",
    "wof:name":"A. Und A. Dahm",
    "wof:placetype":"venue"
},
  "geometry": {"coordinates":[8.628780365,52.2795295715],"type":"Point"}
}