{
  "type": "Feature",
  "properties": {
    "iso:country":"DE",
    "sg:address":"Betmauerstr. 15",
    "sg:city":"Reutlingen",
    "sg:phone":"+49 7121/66621",
    "sg:postcode":"72768",
    "sg:province":"Baden-W\u00fcrttemberg",
    "wof:name":"Legel Bau Gmbh",
    "wof:placetype":"venue"
},
  "geometry": {"coordinates":[9.198211,48.55024],"type":"Point"}
}