{
  "type": "Feature",
  "properties": {
    "iso:country":"DE",
    "sg:address":"Neuenk\u00e4mpen 35",
    "sg:city":"Lindern",
    "sg:phone":"+49 5957/1442",
    "sg:postcode":"49699",
    "sg:province":"Niedersachsen",
    "wof:name":"Franz Horstmann",
    "wof:placetype":"venue"
},
  "geometry": {"coordinates":[7.791553,52.857563],"type":"Point"}
}