{
  "type": "Feature",
  "properties": {
    "iso:country":"DE",
    "sg:address":"Uhlandstr 60",
    "sg:city":"Pfullingen",
    "sg:phone":"+49 7121/99439560",
    "sg:postcode":"72793",
    "sg:province":"Baden-W\u00fcrttemberg",
    "wof:name":"Hailfinger & Kiefer Gmbh Umformtechnik",
    "wof:placetype":"venue"
},
  "geometry": {"coordinates":[9.224517,48.473682],"type":"Point"}
}