{
  "type": "Feature",
  "properties": {
    "iso:country":"DE",
    "sg:address":"Karl-Marx-Str. 25",
    "sg:city":"Eisenh\u00fcttenstadt",
    "sg:phone":"+49 3364/44891",
    "sg:postcode":"15890",
    "sg:province":"Brandenburg",
    "wof:name":"Ingeborg Trautmann",
    "wof:placetype":"venue"
},
  "geometry": {"coordinates":[14.63565,52.146381],"type":"Point"}
}