{
  "type": "Feature",
  "properties": {
    "iso:country":"DE",
    "sg:address":"Brunnenstra\u00dfe 2a",
    "sg:city":"Reit im Winkl",
    "sg:phone":"+49 172 8216552",
    "sg:postcode":"83242",
    "sg:province":"Bayern",
    "wof:name":"Zwei Bayrische Konditoren Im Internet",
    "wof:placetype":"venue"
},
  "geometry": {"coordinates":[12.469625473,47.6768379211],"type":"Point"}
}