{
  "type": "Feature",
  "properties": {
    "iso:country":"DE",
    "sg:address":"Schwarzwaldstr. 101",
    "sg:city":"Waldkirch",
    "sg:phone":"+49 7681/9806",
    "sg:postcode":"79183",
    "sg:province":"Baden-W\u00fcrttemberg",
    "wof:name":"Georg Schwehr",
    "wof:placetype":"venue"
},
  "geometry": {"coordinates":[7.9228301048,48.0801315308],"type":"Point"}
}