{
  "type": "Feature",
  "properties": {
    "iso:country":"DE",
    "sg:address":"M\u00fchlstr. 20",
    "sg:city":"Riedenburg",
    "sg:phone":"+49 9442/1254",
    "sg:postcode":"93339",
    "sg:province":"Bayern",
    "wof:name":"Andreas Kettner",
    "wof:placetype":"venue"
},
  "geometry": {"coordinates":[11.6836442947,48.9610519409],"type":"Point"}
}