{
  "type": "Feature",
  "properties": {
    "iso:country":"DE",
    "sg:address":"Falkstr. 92",
    "sg:city":"Frankfurt",
    "sg:phone":"+49 69/772180",
    "sg:postcode":"60487",
    "sg:province":"Hessen",
    "wof:name":"Adler",
    "wof:placetype":"venue"
},
  "geometry": {"coordinates":[8.6442098618,50.1256599426],"type":"Point"}
}