{
  "type": "Feature",
  "properties": {
    "iso:country":"DE",
    "sg:address":"Rheinstr. 8",
    "sg:city":"Lindlar",
    "sg:postcode":"51789",
    "sg:province":"Nordrhein-Westfalen",
    "wof:name":"Hermann Josef Schnepper Gmbh",
    "wof:placetype":"venue"
},
  "geometry": {"coordinates":[7.3680038452,51.0191307068],"type":"Point"}
}