{
  "type": "Feature",
  "properties": {
    "iso:country":"DE",
    "sg:address":"Dorfstr. 3",
    "sg:city":"D\u00f6tlingen",
    "sg:phone":"+49 4432/94850",
    "sg:postcode":"27801",
    "sg:province":"Niedersachsen",
    "wof:name":"Johannes Kuhlmann",
    "wof:placetype":"venue"
},
  "geometry": {"coordinates":[8.383886,52.935314],"type":"Point"}
}