{
  "type": "Feature",
  "properties": {
    "iso:country":"DE",
    "sg:address":"Dorfstr. 16",
    "sg:city":"Gaildorf",
    "sg:phone":"+49 7971/7777",
    "sg:postcode":"74405",
    "sg:province":"Baden-W\u00fcrttemberg",
    "wof:name":"Schuster Gmbh",
    "wof:placetype":"venue"
},
  "geometry": {"coordinates":[9.782844,48.995529],"type":"Point"}
}