{
  "type": "Feature",
  "properties": {
    "iso:country":"DE",
    "sg:address":"Unteranger 41",
    "sg:city":"Kochel",
    "sg:phone":"+49 8851/465",
    "sg:postcode":"82431",
    "sg:province":"Bayern",
    "wof:name":"Elektro-service Fischer Gmbh",
    "wof:placetype":"venue"
},
  "geometry": {"coordinates":[11.37396,47.661896],"type":"Point"}
}