{
  "type": "Feature",
  "properties": {
    "iso:country":"DE",
    "sg:address":"Max-Planck-Str. 61",
    "sg:city":"B\u00fcnde",
    "sg:phone":"+49 5223/188886",
    "sg:postcode":"32257",
    "sg:province":"Nordrhein-Westfalen",
    "wof:name":"Weissenhorn Immobilien",
    "wof:placetype":"venue"
},
  "geometry": {"coordinates":[8.6085395813,52.1901512146],"type":"Point"}
}