{
  "type": "Feature",
  "properties": {
    "iso:country":"DE",
    "sg:address":"Hoffmannallee 28",
    "sg:city":"Kleve",
    "sg:phone":"+49 2821/27124",
    "sg:postcode":"47533",
    "sg:province":"Nordrhein-Westfalen",
    "wof:name":"A. Kok",
    "wof:placetype":"venue"
},
  "geometry": {"coordinates":[6.1282849312,51.7808418274],"type":"Point"}
}