{
  "type": "Feature",
  "properties": {
    "iso:country":"DE",
    "sg:address":"Marktstr. 6",
    "sg:city":"Oer-Erkenschwick",
    "sg:phone":"+49 2368/58712",
    "sg:postcode":"45739",
    "sg:province":"Nordrhein-Westfalen",
    "wof:name":"August Vonnahme Ingenieur",
    "wof:placetype":"venue"
},
  "geometry": {"coordinates":[7.2619700432,51.6396789551],"type":"Point"}
}