{
  "type": "Feature",
  "properties": {
    "iso:country":"DE",
    "sg:address":"An der H\u00fchle 1",
    "sg:city":"Pfaffenhofen",
    "sg:phone":"+49 7302/784",
    "sg:postcode":"89284",
    "sg:province":"Bayern",
    "wof:name":"B. Und K. Fleischer",
    "wof:placetype":"venue"
},
  "geometry": {"coordinates":[10.157856,48.364414],"type":"Point"}
}