{
  "type": "Feature",
  "properties": {
    "iso:country":"DE",
    "sg:address":"Max-Eyth-Str 12",
    "sg:city":"Hochdorf",
    "sg:phone":"+49 7153/51249",
    "sg:postcode":"73269",
    "sg:province":"Baden-W\u00fcrttemberg",
    "wof:name":"Reiser Gmbh",
    "wof:placetype":"venue"
},
  "geometry": {"coordinates":[9.4754247665,48.6907997131],"type":"Point"}
}