{
  "type": "Feature",
  "properties": {
    "iso:country":"DE",
    "sg:address":"Sulzer Str. 28",
    "sg:city":"Schopfloch",
    "sg:phone":"+49 7443/4449",
    "sg:postcode":"72296",
    "sg:province":"Baden-W\u00fcrttemberg",
    "wof:name":"T. G\u00fcnther",
    "wof:placetype":"venue"
},
  "geometry": {"coordinates":[8.5542678833,48.4236907959],"type":"Point"}
}