{
  "type": "Feature",
  "properties": {
    "iso:country":"DE",
    "sg:address":"M\u00fchlenweg 2",
    "sg:city":"Hanerau-Hademarschen",
    "sg:phone":"+49 4872/440",
    "sg:postcode":"25557",
    "sg:province":"Schleswig-Holstein",
    "wof:name":"Lennart Medin Bauunternehmen Gmbh",
    "wof:placetype":"venue"
},
  "geometry": {"coordinates":[9.418539,54.125172],"type":"Point"}
}