{
  "type": "Feature",
  "properties": {
    "iso:country":"DE",
    "sg:address":"Strohdeich 3",
    "sg:city":"Kollmar",
    "sg:phone":"+49 4128/305",
    "sg:postcode":"25377",
    "sg:province":"Schleswig-Holstein",
    "wof:name":"Norbert Cassens",
    "wof:placetype":"venue"
},
  "geometry": {"coordinates":[9.474975,53.755028],"type":"Point"}
}