{
  "type": "Feature",
  "properties": {
    "iso:country":"DE",
    "sg:address":"Kirchhof 20",
    "sg:city":"Werne",
    "sg:phone":"+49 2389/2656",
    "sg:postcode":"59368",
    "sg:province":"Nordrhein-Westfalen",
    "wof:name":"Puk Upn Balken",
    "wof:placetype":"venue"
},
  "geometry": {"coordinates":[7.6355409622,51.663028717],"type":"Point"}
}