{
  "type": "Feature",
  "properties": {
    "iso:country":"DE",
    "sg:address":"Willy-Brandt-Str. 7",
    "sg:city":"Gaggenau",
    "sg:phone":"+49 7225/72643",
    "sg:postcode":"76571",
    "sg:province":"Baden-W\u00fcrttemberg",
    "wof:name":"B. De Jonge Ingenieur",
    "wof:placetype":"venue"
},
  "geometry": {"coordinates":[8.3183412552,48.8079071045],"type":"Point"}
}