{
  "type": "Feature",
  "properties": {
    "iso:country":"DE",
    "sg:address":"Friedrich-Harkort-Str. 35",
    "sg:city":"Oelde",
    "sg:phone":"+49 2522/3782",
    "sg:postcode":"59302",
    "sg:province":"Nordrhein-Westfalen",
    "wof:name":"H. Feldmann",
    "wof:placetype":"venue"
},
  "geometry": {"coordinates":[8.138952,51.835358],"type":"Point"}
}