{
  "type": "Feature",
  "properties": {
    "iso:country":"DE",
    "sg:address":"L\u00fclsdorfer Str. 46",
    "sg:city":"Troisdorf",
    "sg:phone":"+49 2241/951210",
    "sg:postcode":"53842",
    "sg:province":"Nordrhein-Westfalen",
    "wof:name":"K\u00fcra Acrylglas- Und Kunststoffverarbeitung Gmbh",
    "wof:placetype":"venue"
},
  "geometry": {"coordinates":[7.107099,50.826389],"type":"Point"}
}