{
  "type": "Feature",
  "properties": {
    "iso:country":"DE",
    "sg:address":"Lei\u00dfnerstr. 67",
    "sg:city":"Plauen",
    "sg:phone":"+49 3741/223030",
    "sg:postcode":"08525",
    "sg:province":"Sachsen",
    "wof:name":"Igs Strunz Ingenieurges. F\u00fcr Bauwesen Gmbh",
    "wof:placetype":"venue"
},
  "geometry": {"coordinates":[12.1443080902,50.504737854],"type":"Point"}
}