{
  "type": "Feature",
  "properties": {
    "iso:country":"DE",
    "sg:address":"Warnetalstr. 7",
    "sg:city":"Alfeld",
    "sg:phone":"+49 5181/5896",
    "sg:postcode":"31061",
    "sg:province":"Niedersachsen",
    "wof:name":"August Wulfes",
    "wof:placetype":"venue"
},
  "geometry": {"coordinates":[9.847061,51.994122],"type":"Point"}
}