{
  "type": "Feature",
  "properties": {
    "iso:country":"DE",
    "sg:address":"K\u00fcppelsm\u00fchle",
    "sg:city":"Bad Orb",
    "sg:postcode":"63619",
    "sg:province":"Hessen",
    "wof:name":"Kurklinik M\u00fchlenhof-k\u00fcppelsm\u00fchle",
    "wof:placetype":"venue"
},
  "geometry": {"coordinates":[9.3593568802,50.2131195068],"type":"Point"}
}