{
  "type": "Feature",
  "properties": {
    "iso:country":"DE",
    "sg:address":"F\u00f6rderstedter Str. 5c",
    "sg:city":"Sta\u00dffurt",
    "sg:phone":"+49 3925/930070",
    "sg:postcode":"39418",
    "sg:province":"Sachsen-Anhalt",
    "wof:name":"Gr\u00dcnes Centrum Sta\u00dffurt",
    "wof:placetype":"venue"
},
  "geometry": {"coordinates":[11.594369,51.861462],"type":"Point"}
}