{
  "type": "Feature",
  "properties": {
    "iso:country":"DE",
    "sg:address":"Schlehenkamp 4",
    "sg:city":"Kiel",
    "sg:postcode":"24146",
    "sg:province":"Schleswig-Holstein",
    "wof:name":"H\u00f6ft & S\u00f6hne Gmbh",
    "wof:placetype":"venue"
},
  "geometry": {"coordinates":[10.173146,54.294689],"type":"Point"}
}