{
  "type": "Feature",
  "properties": {
    "iso:country":"DE",
    "sg:address":"Johann Liesenberger Strasse 11",
    "sg:city":"Niederschach",
    "sg:phone":"+49 7728",
    "sg:postcode":"78078",
    "sg:province":"Baden-W\u00fcrttemberg",
    "wof:name":"Eurotriade Gmbh",
    "wof:placetype":"venue"
},
  "geometry": {"coordinates":[8.527345,48.131298],"type":"Point"}
}