{
  "type": "Feature",
  "properties": {
    "iso:country":"DE",
    "sg:address":"Eisenbahnstr. 4",
    "sg:city":"B\u00fchl",
    "sg:phone":"+49 7223/20800",
    "sg:postcode":"77815",
    "sg:province":"Baden-W\u00fcrttemberg",
    "wof:name":"Gerhard Heilpraktiker",
    "wof:placetype":"venue"
},
  "geometry": {"coordinates":[8.13585186,48.6958808899],"type":"Point"}
}