{
  "type": "Feature",
  "properties": {
    "iso:country":"DE",
    "sg:address":"Schulplatz 4",
    "sg:city":"Kirchberg i. Wald",
    "sg:phone":"+49 9927/8207",
    "sg:postcode":"94259",
    "sg:province":"Bayern",
    "wof:name":"Bernd Schulz",
    "wof:placetype":"venue"
},
  "geometry": {"coordinates":[13.137208,48.905792],"type":"Point"}
}