{
  "type": "Feature",
  "properties": {
    "iso:country":"DE",
    "sg:address":"Brockauer Str. 7",
    "sg:city":"Brockau",
    "sg:phone":"+49 3765/64390",
    "sg:postcode":"08491",
    "sg:province":"Sachsen",
    "wof:name":"Gabriele Sch\u00f6nicke",
    "wof:placetype":"venue"
},
  "geometry": {"coordinates":[12.2438707352,50.6010475159],"type":"Point"}
}