{
  "type": "Feature",
  "properties": {
    "iso:country":"DE",
    "sg:address":"Gertigstr. 46",
    "sg:city":"Hamburg",
    "sg:phone":"+49 40/2794446",
    "sg:postcode":"22303",
    "sg:province":"Hamburg",
    "wof:name":"D. Wexel",
    "wof:placetype":"venue"
},
  "geometry": {"coordinates":[10.0167474747,53.5823287964],"type":"Point"}
}