{
  "type": "Feature",
  "properties": {
    "iso:country":"DE",
    "sg:address":"Stellinger Weg 39",
    "sg:city":"Hamburg",
    "sg:phone":"+49 40/497278",
    "sg:postcode":"20255",
    "sg:province":"Hamburg",
    "wof:name":"G. Bertram",
    "wof:placetype":"venue"
},
  "geometry": {"coordinates":[9.9481010437,53.5798492432],"type":"Point"}
}