{
  "type": "Feature",
  "properties": {
    "iso:country":"DE",
    "sg:address":"Friedhofstr. 1",
    "sg:city":"M\u00fcllheim",
    "sg:phone":"+49 7631/12554",
    "sg:postcode":"79379",
    "sg:province":"Baden-W\u00fcrttemberg",
    "wof:name":"Treffpunkt Bei Brigitte",
    "wof:placetype":"venue"
},
  "geometry": {"coordinates":[7.621090889,47.8095588684],"type":"Point"}
}