{
  "type": "Feature",
  "properties": {
    "iso:country":"DE",
    "sg:address":"Mei\u00dfener Str. 30",
    "sg:city":"Lohmar",
    "sg:phone":"+49 2206/1855",
    "sg:postcode":"53797",
    "sg:province":"Nordrhein-Westfalen",
    "wof:name":"A. Conrads",
    "wof:placetype":"venue"
},
  "geometry": {"coordinates":[7.2642698288,50.9081420898],"type":"Point"}
}