{
  "type": "Feature",
  "properties": {
    "iso:country":"DE",
    "sg:address":"Bessemerstr. 80",
    "sg:city":"Bochum",
    "sg:phone":"+49 234/91180",
    "sg:postcode":"44793",
    "sg:province":"Nordrhein-Westfalen",
    "wof:name":"Bochumer Eisenh\u00fctte Heintzmann Gmbh & Co.",
    "wof:placetype":"venue"
},
  "geometry": {"coordinates":[7.2076,51.474281],"type":"Point"}
}