{
  "type": "Feature",
  "properties": {
    "iso:country":"DE",
    "sg:address":"Lennestr. 12",
    "sg:city":"Schmallenberg",
    "sg:phone":"+49 2975/546",
    "sg:postcode":"57392",
    "sg:province":"Nordrhein-Westfalen",
    "wof:name":"Paul Feldmann",
    "wof:placetype":"venue"
},
  "geometry": {"coordinates":[8.380729,51.168129],"type":"Point"}
}