{
  "type": "Feature",
  "properties": {
    "iso:country":"DE",
    "sg:address":"Hiltenspergerstr. 81",
    "sg:city":"M\u00fcnchen",
    "sg:phone":"+49 89/303207",
    "sg:postcode":"80796",
    "sg:province":"Bayern",
    "wof:name":"Dr. Med. Elmar Kampmann Arzt F\u00fcr Allgemeinmedizin",
    "wof:placetype":"venue"
},
  "geometry": {"coordinates":[11.5661067963,48.1648712158],"type":"Point"}
}