{
  "type": "Feature",
  "properties": {
    "iso:country":"DE",
    "sg:address":"Kolberger Str. 1",
    "sg:city":"Bad Hersfeld",
    "sg:phone":"+49 6621/62321",
    "sg:postcode":"36251",
    "sg:province":"Hessen",
    "wof:name":"Restaurant Steakhaus",
    "wof:placetype":"venue"
},
  "geometry": {"coordinates":[9.7381715775,50.8634567261],"type":"Point"}
}