{
  "type": "Feature",
  "properties": {
    "iso:country":"DE",
    "sg:address":"Bahnhofstr. 64-66",
    "sg:city":"Falkensee",
    "sg:phone":"+49 3322/22217",
    "sg:postcode":"14612",
    "sg:province":"Brandenburg",
    "wof:name":"H\u00f6rger\u00e4teakustik Czeszak Gmbh",
    "wof:placetype":"venue"
},
  "geometry": {"coordinates":[13.093253,52.561279],"type":"Point"}
}