{
  "type": "Feature",
  "properties": {
    "iso:country":"DE",
    "sg:address":"Mannheimer Str. 212",
    "sg:city":"Bad Kreuznach",
    "sg:phone":"+49 671/26990",
    "sg:postcode":"55543",
    "sg:province":"Rheinland-Pfalz",
    "wof:name":"J\u00fcrgen Wermke",
    "wof:placetype":"venue"
},
  "geometry": {"coordinates":[7.8652768135,49.8395462036],"type":"Point"}
}