{
  "type": "Feature",
  "properties": {
    "iso:country":"DE",
    "sg:address":"S\u00fcdring 6",
    "sg:city":"Visselh\u00f6vede",
    "sg:phone":"+49 4262/957012",
    "sg:postcode":"27374",
    "sg:province":"Niedersachsen",
    "wof:name":"Speedy Finanzbuchhaltung Nicole Teuteberg",
    "wof:placetype":"venue"
},
  "geometry": {"coordinates":[9.5743103027,52.9790153503],"type":"Point"}
}