{
  "type": "Feature",
  "properties": {
    "iso:country":"DE",
    "sg:address":"Z\u00f6llerstr. 20",
    "sg:city":"Plauen",
    "sg:phone":"+49 3741/527288",
    "sg:postcode":"08525",
    "sg:province":"Sachsen",
    "wof:name":"Bewa-stepp Dagmar Tasch",
    "wof:placetype":"venue"
},
  "geometry": {"coordinates":[12.0934553146,50.5237503052],"type":"Point"}
}