{
  "type": "Feature",
  "properties": {
    "iso:country":"DE",
    "sg:address":"Garstedter Weg 244",
    "sg:city":"Hamburg",
    "sg:phone":"+49 40/5514712",
    "sg:postcode":"22455",
    "sg:province":"Hamburg",
    "wof:name":"R. Heidenreich",
    "wof:placetype":"venue"
},
  "geometry": {"coordinates":[9.968206,53.636574],"type":"Point"}
}