{
  "type": "Feature",
  "properties": {
    "iso:country":"DE",
    "sg:address":"Klausenerplatz 11",
    "sg:city":"Berlin",
    "sg:phone":"+49 30/32601718",
    "sg:postcode":"14059",
    "sg:province":"Berlin",
    "wof:name":"Wolfgang Zimmermann Architektur- Gmbh",
    "wof:placetype":"venue"
},
  "geometry": {"coordinates":[13.29151,52.517696],"type":"Point"}
}