{
  "type": "Feature",
  "properties": {
    "iso:country":"DE",
    "sg:address":"Kaiser-Friedrich-Ring 10",
    "sg:city":"Saarlouis",
    "sg:phone":"+49 6831/123322",
    "sg:postcode":"66740",
    "sg:province":"Saarland",
    "wof:name":"Hekomed Sanit\u00e4tshaus Gmbh",
    "wof:placetype":"venue"
},
  "geometry": {"coordinates":[6.752649,49.312695],"type":"Point"}
}