{
  "type": "Feature",
  "properties": {
    "iso:country":"DE",
    "sg:address":"Torgauer Str. 114",
    "sg:city":"Leipzig",
    "sg:phone":"+49 341/2373295",
    "sg:postcode":"04347",
    "sg:province":"Sachsen",
    "wof:name":"Richard Herbig Kg",
    "wof:placetype":"venue"
},
  "geometry": {"coordinates":[12.434759,51.355614],"type":"Point"}
}