{
  "type": "Feature",
  "properties": {
    "iso:country":"DE",
    "sg:address":"M\u00f6llhoven 89",
    "sg:city":"Essen",
    "sg:phone":"+49 201/690001",
    "sg:postcode":"45357",
    "sg:province":"Nordrhein-Westfalen",
    "wof:name":"Dr. Freischlad Gmbh",
    "wof:placetype":"venue"
},
  "geometry": {"coordinates":[6.9351248741,51.4739303589],"type":"Point"}
}