{
  "type": "Feature",
  "properties": {
    "iso:country":"DE",
    "sg:address":"Bergerr\u00fccken 9",
    "sg:city":"Unterw\u00f6ssen",
    "sg:phone":"+49 8640/8645",
    "sg:postcode":"83246",
    "sg:province":"Bayern",
    "wof:name":"Ludwig Bl\u00f6sl",
    "wof:placetype":"venue"
},
  "geometry": {"coordinates":[12.479095,47.706738],"type":"Point"}
}