{
  "type": "Feature",
  "properties": {
    "iso:country":"DE",
    "sg:address":"Ahrensfelder Weg 1",
    "sg:city":"Gro\u00dfhansdorf",
    "sg:phone":"+49 4102/61178",
    "sg:postcode":"22927",
    "sg:province":"Schleswig-Holstein",
    "wof:name":"Waldd\u00f6rfer-apotheke",
    "wof:placetype":"venue"
},
  "geometry": {"coordinates":[10.26025,53.652142],"type":"Point"}
}