{
  "type": "Feature",
  "properties": {
    "iso:country":"DE",
    "sg:address":"Vollerding 8",
    "sg:city":"Tiefenbach",
    "sg:phone":"+49 8546",
    "sg:postcode":"94113",
    "sg:province":"Bayern",
    "wof:name":"Mobilstrom-maier",
    "wof:placetype":"venue"
},
  "geometry": {"coordinates":[13.362619,48.624176],"type":"Point"}
}