{
  "type": "Feature",
  "properties": {
    "iso:country":"DE",
    "sg:address":"Kningelbach 16",
    "sg:city":"Siegburg",
    "sg:phone":"+49 2241/381997",
    "sg:postcode":"53721",
    "sg:province":"Nordrhein-Westfalen",
    "wof:name":"Gerhard Stenz Ing. Grad.architekt",
    "wof:placetype":"venue"
},
  "geometry": {"coordinates":[7.258823,50.806805],"type":"Point"}
}