{
  "type": "Feature",
  "properties": {
    "iso:country":"DE",
    "sg:address":"Software-Center 5",
    "sg:city":"Marburg",
    "sg:phone":"+49 6421/12061",
    "sg:postcode":"35037",
    "sg:province":"Hessen",
    "wof:name":"Sofa Gmbh",
    "wof:placetype":"venue"
},
  "geometry": {"coordinates":[8.7691707611,50.8024177551],"type":"Point"}
}