{
  "type": "Feature",
  "properties": {
    "iso:country":"DE",
    "sg:address":"Lilienthalstr. 25",
    "sg:city":"Hallbergmoos",
    "sg:postcode":"85399",
    "sg:province":"Bayern",
    "wof:name":"Company Veranstaltungs Gmbh",
    "wof:placetype":"venue"
},
  "geometry": {"coordinates":[11.7314271927,48.3326797485],"type":"Point"}
}