{
  "type": "Feature",
  "properties": {
    "iso:country":"DE",
    "sg:address":"Hans-Vogel-Str. 59",
    "sg:city":"F\u00fcrth",
    "sg:phone":"+49 911/791040",
    "sg:postcode":"90765",
    "sg:province":"Bayern",
    "wof:name":"Kenngott Treppen",
    "wof:placetype":"venue"
},
  "geometry": {"coordinates":[11.0096673965,49.4805831909],"type":"Point"}
}