{
  "type": "Feature",
  "properties": {
    "iso:country":"DE",
    "sg:address":"Am Swistbach 15",
    "sg:city":"Meckenheim",
    "sg:postcode":"53121",
    "sg:province":"Nordrhein-Westfalen",
    "wof:name":"Reisen, Korsika Und Das Rainbow-tours Camp",
    "wof:placetype":"venue"
},
  "geometry": {"coordinates":[-88.533058,42.725151],"type":"Point"}
}