{
  "type": "Feature",
  "properties": {
    "iso:country":"DE",
    "sg:address":"Landwehr 12",
    "sg:city":"Neustadt",
    "sg:phone":"+49 4950/3267349",
    "sg:postcode":"31535",
    "sg:province":"Niedersachsen",
    "wof:name":"Kreissparkasse",
    "wof:placetype":"venue"
},
  "geometry": {"coordinates":[11.577553,53.382069],"type":"Point"}
}