{
  "type": "Feature",
  "properties": {
    "iso:country":"DE",
    "sg:address":"Ernst-Th\u00e4lmann-Str. 24",
    "sg:city":"Storkow",
    "sg:phone":"+49 33678/3479",
    "sg:postcode":"15859",
    "sg:province":"Brandenburg",
    "wof:name":"A. Koch",
    "wof:placetype":"venue"
},
  "geometry": {"coordinates":[13.9223651886,52.253490448],"type":"Point"}
}