{
  "type": "Feature",
  "properties": {
    "iso:country":"DE",
    "sg:address":"Feichthofstr. 183",
    "sg:city":"M\u00fcnchen",
    "sg:phone":"+49 89/881582",
    "sg:postcode":"81247",
    "sg:province":"Bayern",
    "wof:name":"Dr. Jakob Strobl Rechtsanwalt",
    "wof:placetype":"venue"
},
  "geometry": {"coordinates":[11.4618062973,48.1580352783],"type":"Point"}
}