{
  "type": "Feature",
  "properties": {
    "iso:country":"DE",
    "sg:address":"Mercatorstr. 26",
    "sg:city":"Frankfurt",
    "sg:phone":"+49 69/447200",
    "sg:postcode":"60316",
    "sg:province":"Hessen",
    "wof:name":"Exil Gastst\u00e4ttenbetriebs Gmbh",
    "wof:placetype":"venue"
},
  "geometry": {"coordinates":[8.6897172928,50.1202545166],"type":"Point"}
}