{
  "type": "Feature",
  "properties": {
    "iso:country":"DE",
    "sg:address":"Merveldtstr. 107",
    "sg:city":"Recklinghausen",
    "sg:phone":"+49 2361/657524",
    "sg:postcode":"45663",
    "sg:province":"Nordrhein-Westfalen",
    "wof:name":"P. Papatziamos",
    "wof:placetype":"venue"
},
  "geometry": {"coordinates":[7.2476959229,51.5785102844],"type":"Point"}
}