{
  "type": "Feature",
  "properties": {
    "iso:country":"DE",
    "sg:address":"Friedrichsstr. 10",
    "sg:city":"Alpirsbach",
    "sg:phone":"+49 7444/91070",
    "sg:postcode":"72275",
    "sg:province":"Baden-W\u00fcrttemberg",
    "wof:name":"Waldemar Link",
    "wof:placetype":"venue"
},
  "geometry": {"coordinates":[8.4631099701,48.3284034729],"type":"Point"}
}