{
  "type": "Feature",
  "properties": {
    "iso:country":"DE",
    "sg:address":"Schulstr. 4",
    "sg:city":"G\u00f6rlitz",
    "sg:phone":"+49 3581/417970",
    "sg:postcode":"02826",
    "sg:province":"Sachsen",
    "wof:name":"Bullin Und Wei\u00dfbach Rechtsanw\u00e4lte",
    "wof:placetype":"venue"
},
  "geometry": {"coordinates":[14.9820251465,51.1491889954],"type":"Point"}
}