{
  "type": "Feature",
  "properties": {
    "iso:country":"DE",
    "sg:address":"Am Westkai 25",
    "sg:city":"Stuttgart",
    "sg:phone":"+49 711/9189460",
    "sg:postcode":"70327",
    "sg:province":"Baden-W\u00fcrttemberg",
    "wof:name":"Tan Internationale Spedition Gmbh",
    "wof:placetype":"venue"
},
  "geometry": {"coordinates":[9.254792,48.764954],"type":"Point"}
}