{
  "type": "Feature",
  "properties": {
    "iso:country":"DE",
    "sg:address":"Leopoldstr. 30",
    "sg:city":"M\u00fcnchen",
    "sg:phone":"+49 89/31598484",
    "sg:postcode":"80802",
    "sg:province":"Bayern",
    "wof:name":"Plakativ Gmbh",
    "wof:placetype":"venue"
},
  "geometry": {"coordinates":[11.5839071274,48.1556816101],"type":"Point"}
}