{
  "type": "Feature",
  "properties": {
    "iso:country":"DE",
    "sg:address":"Carl-Zeiss-Str. 20",
    "sg:city":"Rheine",
    "sg:postcode":"48432",
    "sg:province":"Nordrhein-Westfalen",
    "wof:name":"Pl\u00fcth Baugesellschaft Mbh",
    "wof:placetype":"venue"
},
  "geometry": {"coordinates":[7.485818,52.286831],"type":"Point"}
}