{
  "type": "Feature",
  "properties": {
    "iso:country":"DE",
    "sg:address":"Urbanstr. 41",
    "sg:city":"Plochingen",
    "sg:phone":"+49 7153/22643",
    "sg:postcode":"73207",
    "sg:province":"Baden-W\u00fcrttemberg",
    "wof:name":"Pizzeria Don Camillo",
    "wof:placetype":"venue"
},
  "geometry": {"coordinates":[9.4171762466,48.7140693665],"type":"Point"}
}