{
  "type": "Feature",
  "properties": {
    "iso:country":"DE",
    "sg:address":"Wilhelm-Kraut-Str. 17",
    "sg:city":"Balingen",
    "sg:phone":"+49 7433/381910",
    "sg:postcode":"72336",
    "sg:province":"Baden-W\u00fcrttemberg",
    "wof:name":"Kneiple",
    "wof:placetype":"venue"
},
  "geometry": {"coordinates":[8.8511619568,48.2700042725],"type":"Point"}
}