{
  "type": "Feature",
  "properties": {
    "iso:country":"DE",
    "sg:address":"Limminghofer Str. 13",
    "sg:city":"Solingen",
    "sg:phone":"+49 212/2331082",
    "sg:postcode":"42699",
    "sg:province":"Nordrhein-Westfalen",
    "wof:name":"Ltu Gmbh & Co. Kg",
    "wof:placetype":"venue"
},
  "geometry": {"coordinates":[7.040364,51.170879],"type":"Point"}
}