{
  "type": "Feature",
  "properties": {
    "iso:country":"DE",
    "sg:address":"Neue Waldstr. 24",
    "sg:city":"Winsen",
    "sg:phone":"+49 5146/92174",
    "sg:postcode":"29308",
    "sg:province":"Niedersachsen",
    "wof:name":"R. Engelke Ingenieur",
    "wof:placetype":"venue"
},
  "geometry": {"coordinates":[9.7609119415,52.6793937683],"type":"Point"}
}