{
  "type": "Feature",
  "properties": {
    "iso:country":"DE",
    "sg:address":"Ermischstr. 3",
    "sg:city":"Dresden",
    "sg:phone":"+49 351/4954918",
    "sg:postcode":"01067",
    "sg:province":"Sachsen",
    "wof:name":"Wilfried Engelmann Patentanwalt",
    "wof:placetype":"venue"
},
  "geometry": {"coordinates":[13.7280864716,51.051574707],"type":"Point"}
}