{
  "type": "Feature",
  "properties": {
    "iso:country":"DE",
    "sg:address":"Fritz-Erler-Str. 44",
    "sg:city":"D\u00fcren",
    "sg:phone":"+49 2421/941434",
    "sg:postcode":"52349",
    "sg:province":"Nordrhein-Westfalen",
    "wof:name":"Weyerstra\u00df Regenerative Energien Gmbh",
    "wof:placetype":"venue"
},
  "geometry": {"coordinates":[6.473094,50.806938],"type":"Point"}
}