{
  "type": "Feature",
  "properties": {
    "iso:country":"DE",
    "sg:address":"Breslauer Str. 24",
    "sg:city":"W\u00fcrzburg",
    "sg:phone":"+49 931/71232",
    "sg:postcode":"97072",
    "sg:province":"Bayern",
    "wof:name":"Katholisches Pfarramt St. Andreas",
    "wof:placetype":"venue"
},
  "geometry": {"coordinates":[9.9339990616,49.7765655518],"type":"Point"}
}