{
  "type": "Feature",
  "properties": {
    "iso:country":"DE",
    "sg:address":"Pinkertweg 4",
    "sg:city":"Hamburg",
    "sg:phone":"+49 40/7320601",
    "sg:postcode":"22113",
    "sg:province":"Schleswig-Holstein",
    "wof:name":"Ernst Kastning Drogenm\u00fchle Gmbh",
    "wof:placetype":"venue"
},
  "geometry": {"coordinates":[10.0835161209,53.5272789001],"type":"Point"}
}