{
  "type": "Feature",
  "properties": {
    "iso:country":"DE",
    "sg:address":"Kierberger Str. 119",
    "sg:city":"Br\u00fchl",
    "sg:phone":"+49 2232/25061",
    "sg:postcode":"50321",
    "sg:province":"Nordrhein-Westfalen",
    "wof:name":"S. Stettner",
    "wof:placetype":"venue"
},
  "geometry": {"coordinates":[6.891629,50.838741],"type":"Point"}
}