{
  "type": "Feature",
  "properties": {
    "iso:country":"DE",
    "sg:address":"Jersbeker Str. 29 a",
    "sg:city":"Bargteheide",
    "sg:phone":"+49 4532/24532",
    "sg:postcode":"22941",
    "sg:province":"Schleswig-Holstein",
    "wof:name":"U. Und U. Jabs",
    "wof:placetype":"venue"
},
  "geometry": {"coordinates":[10.254254,53.730427],"type":"Point"}
}