{
  "type": "Feature",
  "properties": {
    "iso:country":"DE",
    "sg:address":"Alemannenstr. 71",
    "sg:city":"Baden-Baden",
    "sg:phone":"+49 7221/53808",
    "sg:postcode":"76532",
    "sg:province":"Baden-W\u00fcrttemberg",
    "wof:name":"Mario Seitz",
    "wof:placetype":"venue"
},
  "geometry": {"coordinates":[8.2109537125,48.7830505371],"type":"Point"}
}