{
  "type": "Feature",
  "properties": {
    "iso:country":"DE",
    "sg:address":"Birkenbusch 45",
    "sg:city":"Sankt Augustin",
    "sg:phone":"+49 2241/332367",
    "sg:postcode":"53757",
    "sg:province":"Nordrhein-Westfalen",
    "wof:name":"Virtueller Semesterapparat Philosophie",
    "wof:placetype":"venue"
},
  "geometry": {"coordinates":[7.207192,50.773102],"type":"Point"}
}