{
  "type": "Feature",
  "properties": {
    "iso:country":"DE",
    "sg:address":"Frankfurter Landstr. 9",
    "sg:city":"M\u00f6rfelden-Walldorf",
    "sg:phone":"+49 6105/951403",
    "sg:postcode":"64546",
    "sg:province":"Hessen",
    "wof:name":"Associates Of Cape Cod Gmbh",
    "wof:placetype":"venue"
},
  "geometry": {"coordinates":[8.59287,50.004799],"type":"Point"}
}