{
  "type": "Feature",
  "properties": {
    "iso:country":"DE",
    "sg:address":"Kurze Str. 10",
    "sg:city":"Heidenheim",
    "sg:phone":"+49 7321/21068",
    "sg:postcode":"89522",
    "sg:province":"Baden-W\u00fcrttemberg",
    "wof:name":"Metzger-einkauf Eg",
    "wof:placetype":"venue"
},
  "geometry": {"coordinates":[10.1515,48.67564],"type":"Point"}
}