{
  "type": "Feature",
  "properties": {
    "iso:country":"DE",
    "sg:address":"Rathausplatz 15",
    "sg:city":"Flensburg",
    "sg:postcode":"24937",
    "sg:province":"Schleswig-Holstein",
    "wof:name":"Olikom Inlinekommunikations- Dienste Gmbh",
    "wof:placetype":"venue"
},
  "geometry": {"coordinates":[9.43517,54.780914],"type":"Point"}
}