{
  "type": "Feature",
  "properties": {
    "iso:country":"DE",
    "sg:address":"Br\u00f6nninghauser Str. 42",
    "sg:city":"Bielefeld",
    "sg:postcode":"33729",
    "sg:province":"Nordrhein-Westfalen",
    "wof:name":"Linke Beteiligungs Kg",
    "wof:placetype":"venue"
},
  "geometry": {"coordinates":[8.63549,52.045311],"type":"Point"}
}