{
  "type": "Feature",
  "properties": {
    "iso:country":"DE",
    "sg:address":"Auf der H\u00fctte 6",
    "sg:city":"Winterberg",
    "sg:phone":"+49 2985/8878",
    "sg:postcode":"59955",
    "sg:province":"Nordrhein-Westfalen",
    "wof:name":"U. Und R. Langer",
    "wof:placetype":"venue"
},
  "geometry": {"coordinates":[8.528619,51.254135],"type":"Point"}
}