{
  "type": "Feature",
  "properties": {
    "iso:country":"DE",
    "sg:address":"Karl-Marx-Str. 12",
    "sg:city":"M\u00f6hlau",
    "sg:phone":"+49 34953/70420",
    "sg:postcode":"06791",
    "sg:province":"Sachsen-Anhalt",
    "wof:name":"Fs Fliesenbau Gmbh",
    "wof:placetype":"venue"
},
  "geometry": {"coordinates":[12.3553686142,51.71925354],"type":"Point"}
}