{
  "type": "Feature",
  "properties": {
    "iso:country":"DE",
    "sg:address":"Deutsch-Ordens-Str. 22",
    "sg:city":"Westhausen",
    "sg:phone":"+49 7363/961111",
    "sg:postcode":"73463",
    "sg:province":"Baden-W\u00fcrttemberg",
    "wof:name":"Hans Fischer",
    "wof:placetype":"venue"
},
  "geometry": {"coordinates":[10.1875333786,48.8817672729],"type":"Point"}
}