{
  "type": "Feature",
  "properties": {
    "iso:country":"DE",
    "sg:address":"Lindweilerweg 110",
    "sg:city":"K\u00f6ln",
    "sg:phone":"+49 221/5995700",
    "sg:postcode":"50739",
    "sg:province":"Nordrhein-Westfalen",
    "wof:name":"Dieter Maierthaler",
    "wof:placetype":"venue"
},
  "geometry": {"coordinates":[6.897585,50.997276],"type":"Point"}
}