{
  "type": "Feature",
  "properties": {
    "iso:country":"DE",
    "sg:address":"Castroper Str. 89",
    "sg:city":"Bochum",
    "sg:phone":"+49 234/503198",
    "sg:postcode":"44791",
    "sg:province":"Nordrhein-Westfalen",
    "wof:name":"Lautwein Und Ritzenhoff",
    "wof:placetype":"venue"
},
  "geometry": {"coordinates":[7.2304520607,51.4865722656],"type":"Point"}
}