{
  "type": "Feature",
  "properties": {
    "iso:country":"DE",
    "sg:address":"Die\u00dfener Str. 46",
    "sg:city":"Utting",
    "sg:phone":"+49 8806/1255",
    "sg:postcode":"86919",
    "sg:province":"Bayern",
    "wof:name":"Kraupner & Wiedemann Gbr",
    "wof:placetype":"venue"
},
  "geometry": {"coordinates":[11.080192,48.020077],"type":"Point"}
}