{
  "type": "Feature",
  "properties": {
    "iso:country":"DE",
    "sg:address":"Alte Kreisstr. 13",
    "sg:city":"Vechelde",
    "sg:phone":"+49 5300/1832",
    "sg:postcode":"38159",
    "sg:province":"Niedersachsen",
    "wof:name":"Friedrich Brandes",
    "wof:placetype":"venue"
},
  "geometry": {"coordinates":[10.408942,52.238491],"type":"Point"}
}