{
  "type": "Feature",
  "properties": {
    "iso:country":"DE",
    "sg:address":"Gifhorner Str. 8",
    "sg:city":"Wesendorf",
    "sg:phone":"+49 5376/9922",
    "sg:postcode":"29392",
    "sg:province":"Niedersachsen",
    "wof:name":"Albersmeier",
    "wof:placetype":"venue"
},
  "geometry": {"coordinates":[10.5336027145,52.5915679932],"type":"Point"}
}