{
  "type": "Feature",
  "properties": {
    "iso:country":"DE",
    "sg:address":"Beim Wallratsroth 13",
    "sg:city":"Neunkirchen",
    "sg:phone":"+49 6821/3838",
    "sg:postcode":"66539",
    "sg:province":"Saarland",
    "wof:name":"Gutssch\u00e4nke",
    "wof:placetype":"venue"
},
  "geometry": {"coordinates":[7.2154960632,49.3216629028],"type":"Point"}
}