{
  "type": "Feature",
  "properties": {
    "iso:country":"DE",
    "sg:address":"Flottmannstr. 90",
    "sg:city":"Herne",
    "sg:phone":"+49 2323/40338",
    "sg:postcode":"44625",
    "sg:province":"Nordrhein-Westfalen",
    "wof:name":"Wilhelm Billeke",
    "wof:placetype":"venue"
},
  "geometry": {"coordinates":[7.225624,51.523102],"type":"Point"}
}