{
  "type": "Feature",
  "properties": {
    "iso:country":"DE",
    "sg:address":"Am Zollstock 24",
    "sg:city":"Gie\u00dfen",
    "sg:phone":"+49 641/21999",
    "sg:postcode":"35392",
    "sg:province":"Hessen",
    "wof:name":"Wilhelm Falter Architekt",
    "wof:placetype":"venue"
},
  "geometry": {"coordinates":[8.659932,50.569279],"type":"Point"}
}