{
  "type": "Feature",
  "properties": {
    "iso:country":"DE",
    "sg:address":"Horkheimer Str. 40",
    "sg:city":"Heilbronn",
    "sg:phone":"+49 7131/257653",
    "sg:postcode":"74081",
    "sg:province":"Baden-W\u00fcrttemberg",
    "wof:name":"I. Serr",
    "wof:placetype":"venue"
},
  "geometry": {"coordinates":[9.186696,49.1194],"type":"Point"}
}