{
  "type": "Feature",
  "properties": {
    "iso:country":"DE",
    "sg:address":"Lange Str. 94",
    "sg:city":"Brieselang",
    "sg:phone":"+49 33232/41231",
    "sg:postcode":"14656",
    "sg:province":"Brandenburg",
    "wof:name":"M. Preu\u00df",
    "wof:placetype":"venue"
},
  "geometry": {"coordinates":[12.9972696304,52.5973472595],"type":"Point"}
}