{
  "type": "Feature",
  "properties": {
    "iso:country":"DE",
    "sg:address":"Lange Str. 14",
    "sg:city":"Herzberg",
    "sg:phone":"+49 3535/5222",
    "sg:postcode":"04916",
    "sg:province":"Brandenburg",
    "wof:name":"R. Thiele",
    "wof:placetype":"venue"
},
  "geometry": {"coordinates":[13.2311344147,51.7279434204],"type":"Point"}
}