{
  "type": "Feature",
  "properties": {
    "iso:country":"DE",
    "sg:address":"Pfarrweg 2",
    "sg:city":"Wernberg-K\u00f6blitz",
    "sg:phone":"+49 9604/2269",
    "sg:postcode":"92533",
    "sg:province":"Bayern",
    "wof:name":"Kath. Pfarramt St. Anna",
    "wof:placetype":"venue"
},
  "geometry": {"coordinates":[12.1636991501,49.5409736633],"type":"Point"}
}