{
  "type": "Feature",
  "properties": {
    "iso:country":"DE",
    "sg:address":"Juri-Gagarin-Ring 1",
    "sg:city":"Neubrandenburg",
    "sg:phone":"+49 395/7792143",
    "sg:postcode":"17036",
    "sg:province":"Mecklenburg-Vorpommern",
    "wof:name":"Lindetal-apotheke Inh. Karin Lauinger E. Kfr.",
    "wof:placetype":"venue"
},
  "geometry": {"coordinates":[13.293466,53.555908],"type":"Point"}
}