{
  "type": "Feature",
  "properties": {
    "iso:country":"DE",
    "sg:address":"Hauptstr. 20",
    "sg:city":"Hoppst\u00e4dten-Weiersbach",
    "sg:phone":"+49 6782/2115",
    "sg:postcode":"55768",
    "sg:province":"Rheinland-Pfalz",
    "wof:name":"Rudolf Seibert",
    "wof:placetype":"venue"
},
  "geometry": {"coordinates":[7.195448,49.616905],"type":"Point"}
}