{
  "type": "Feature",
  "properties": {
    "iso:country":"DE",
    "sg:address":"Gernotstr 18",
    "sg:city":"Dortmund",
    "sg:phone":"+49 231/44940",
    "sg:postcode":"44319",
    "sg:province":"Nordrhein-Westfalen",
    "wof:name":"Erwin Huchtemeier Gmbh & Co Kg",
    "wof:placetype":"venue"
},
  "geometry": {"coordinates":[7.6232180595,51.5304145813],"type":"Point"}
}