{
  "type": "Feature",
  "properties": {
    "iso:country":"DE",
    "sg:address":"Rhinstr. 4",
    "sg:city":"Rheinsberg",
    "sg:phone":"+49 33931/2424",
    "sg:postcode":"16831",
    "sg:province":"Brandenburg",
    "wof:name":"Vier Jahreszeiten",
    "wof:placetype":"venue"
},
  "geometry": {"coordinates":[12.8941230774,53.097114563],"type":"Point"}
}