{
  "type": "Feature",
  "properties": {
    "iso:country":"DE",
    "sg:address":"Pr\u00fch\u00dfstr. 31",
    "sg:city":"Berlin",
    "sg:phone":"+49 30/7064922",
    "sg:postcode":"12105",
    "sg:province":"Berlin",
    "wof:name":"Musikkneipe Shadow Volley",
    "wof:placetype":"venue"
},
  "geometry": {"coordinates":[13.3835296631,52.4432525635],"type":"Point"}
}