{
  "type": "Feature",
  "properties": {
    "iso:country":"DE",
    "sg:address":"Tangstedter Weg 57a",
    "sg:city":"Hamburg",
    "sg:phone":"+49 40/6072749",
    "sg:postcode":"22397",
    "sg:province":"Hamburg",
    "wof:name":"P. Klatte",
    "wof:placetype":"venue"
},
  "geometry": {"coordinates":[10.104113,53.711956],"type":"Point"}
}