{
  "type": "Feature",
  "properties": {
    "iso:country":"DE",
    "sg:address":"Nordstr. 19-23",
    "sg:city":"Bocholt",
    "sg:phone":"+49 2871/184912",
    "sg:postcode":"46399",
    "sg:province":"Nordrhein-Westfalen",
    "wof:name":"Johann B. Fisser Gmbh & Co. Kg",
    "wof:placetype":"venue"
},
  "geometry": {"coordinates":[6.6149687767,51.8398628235],"type":"Point"}
}