{
  "type": "Feature",
  "properties": {
    "iso:country":"DE",
    "sg:address":"Mindener Str. 4",
    "sg:city":"K\u00f6ln",
    "sg:phone":"+49 221/9810390",
    "sg:postcode":"50679",
    "sg:province":"Nordrhein-Westfalen",
    "wof:name":"Inter Rent Europcar Autovermietung Gmbh",
    "wof:placetype":"venue"
},
  "geometry": {"coordinates":[6.971812,50.938061],"type":"Point"}
}