{
  "type": "Feature",
  "properties": {
    "iso:country":"DE",
    "sg:address":"Starenweg 15",
    "sg:city":"Neuss",
    "sg:phone":"+49 2131/465368",
    "sg:postcode":"41466",
    "sg:province":"Nordrhein-Westfalen",
    "wof:name":"Hans Langen",
    "wof:placetype":"venue"
},
  "geometry": {"coordinates":[6.6823649406,51.1648674011],"type":"Point"}
}