{
  "type": "Feature",
  "properties": {
    "iso:country":"DE",
    "sg:address":"Beimoorstr. 29",
    "sg:city":"Hamburg",
    "sg:postcode":"22081",
    "sg:province":"Hamburg",
    "wof:name":"Ostasien Service Dr. Boesken & Partner Gmbh",
    "wof:placetype":"venue"
},
  "geometry": {"coordinates":[10.044532,53.580097],"type":"Point"}
}