{
  "type": "Feature",
  "properties": {
    "iso:country":"DE",
    "sg:address":"Girmes-Kreuz-Str. 63",
    "sg:city":"Kaarst",
    "sg:phone":"+49 2131/880900",
    "sg:postcode":"41564",
    "sg:province":"Nordrhein-Westfalen",
    "wof:name":"Herlitschka Busreisen",
    "wof:placetype":"venue"
},
  "geometry": {"coordinates":[6.6304140091,51.2198753357],"type":"Point"}
}