{
  "type": "Feature",
  "properties": {
    "iso:country":"DE",
    "sg:address":"Industriestr 10",
    "sg:city":"K\u00fcrten",
    "sg:phone":"+49 2268/92800",
    "sg:postcode":"51515",
    "sg:province":"Nordrhein-Westfalen",
    "wof:name":"Bam Beh\u00e4lter-apparate- Und Maschinenbau Gmbh & Co Kg",
    "wof:placetype":"venue"
},
  "geometry": {"coordinates":[7.25998,51.03651],"type":"Point"}
}