{
  "type": "Feature",
  "properties": {
    "iso:country":"DE",
    "sg:address":"Rischenkrug 1",
    "sg:city":"Rosdorf",
    "sg:phone":"+49 5502/1857",
    "sg:postcode":"37124",
    "sg:province":"Niedersachsen",
    "wof:name":"Albert Obermann",
    "wof:placetype":"venue"
},
  "geometry": {"coordinates":[9.8130025864,51.5155944824],"type":"Point"}
}