{
  "type": "Feature",
  "properties": {
    "iso:country":"DE",
    "sg:address":"Im Feld",
    "sg:city":"Alpen",
    "sg:phone":"+49 2802/2373",
    "sg:postcode":"46519",
    "sg:province":"Nordrhein-Westfalen",
    "wof:name":"Heinrich Van Leuck",
    "wof:placetype":"venue"
},
  "geometry": {"coordinates":[6.472445,51.615356],"type":"Point"}
}