{
  "type": "Feature",
  "properties": {
    "iso:country":"DE",
    "sg:address":"Daimlerstr. 29",
    "sg:city":"B\u00fcnde",
    "sg:phone":"+49 5223/69080",
    "sg:postcode":"32257",
    "sg:province":"Nordrhein-Westfalen",
    "wof:name":"Flair Polsterm\u00f6bel Vertriebsges. Mbh & Co. Kg",
    "wof:placetype":"venue"
},
  "geometry": {"coordinates":[8.5318603516,52.2008895874],"type":"Point"}
}