{
  "type": "Feature",
  "properties": {
    "iso:country":"DE",
    "sg:address":"Bahnhofstr. 40",
    "sg:city":"Eutin",
    "sg:phone":"+49 4521/3110",
    "sg:postcode":"23701",
    "sg:province":"Schleswig-Holstein",
    "wof:name":"Planungsgruppe Ost-holstein Architekten",
    "wof:placetype":"venue"
},
  "geometry": {"coordinates":[10.609273,54.136894],"type":"Point"}
}