{
  "type": "Feature",
  "properties": {
    "iso:country":"DE",
    "sg:address":"Max-Winterhalter-Ring 41",
    "sg:city":"Mannheim",
    "sg:postcode":"68307",
    "sg:province":"Baden-W\u00fcrttemberg",
    "wof:name":"Tourtec Musik- Veranstaltungen Gmbh",
    "wof:placetype":"venue"
},
  "geometry": {"coordinates":[8.477126,49.550678],"type":"Point"}
}