{
  "type": "Feature",
  "properties": {
    "iso:country":"DE",
    "sg:address":"Ostpreu\u00dfenweg 3",
    "sg:city":"Hohenfelde",
    "sg:phone":"+49 4385/241",
    "sg:postcode":"24257",
    "sg:province":"Schleswig-Holstein",
    "wof:name":"Erwin Perkuhn",
    "wof:placetype":"venue"
},
  "geometry": {"coordinates":[10.514335,54.379467],"type":"Point"}
}