{
  "type": "Feature",
  "properties": {
    "iso:country":"DE",
    "sg:address":"Ringstr. 10",
    "sg:city":"L\u00f6rrach",
    "sg:phone":"+49 4976/2151119",
    "sg:postcode":"79541",
    "sg:province":"Baden-W\u00fcrttemberg",
    "wof:name":"Elektro R\u00dctten Gmbh",
    "wof:placetype":"venue"
},
  "geometry": {"coordinates":[7.694262,47.633949],"type":"Point"}
}