{
  "type": "Feature",
  "properties": {
    "iso:country":"DE",
    "sg:address":"Rotdornstr. 10",
    "sg:city":"Westoverledingen",
    "sg:phone":"+49 4955/7600",
    "sg:postcode":"26810",
    "sg:province":"Niedersachsen",
    "wof:name":"G\u00fcnter Hoffmann",
    "wof:placetype":"venue"
},
  "geometry": {"coordinates":[7.463533,53.119633],"type":"Point"}
}