{
  "type": "Feature",
  "properties": {
    "iso:country":"DE",
    "sg:address":"Friedrich-Naumann-Str. 9a",
    "sg:city":"Ludwigshafen",
    "sg:phone":"+49 621/6297350",
    "sg:postcode":"67071",
    "sg:province":"Rheinland-Pfalz",
    "wof:name":"Old Daddy",
    "wof:placetype":"venue"
},
  "geometry": {"coordinates":[8.3597488403,49.4942016602],"type":"Point"}
}