{
  "type": "Feature",
  "properties": {
    "iso:country":"DE",
    "sg:address":"Christian-Messner-Str. 13",
    "sg:city":"Trossingen",
    "sg:phone":"+49 7425/27084",
    "sg:postcode":"78647",
    "sg:province":"Baden-W\u00fcrttemberg",
    "wof:name":"M\u00fcllers Bettenland-babynest Inh. Ester Alesi",
    "wof:placetype":"venue"
},
  "geometry": {"coordinates":[8.629983902,48.0723342896],"type":"Point"}
}