{
  "type": "Feature",
  "properties": {
    "iso:country":"DE",
    "sg:address":"Sperberweg 5",
    "sg:city":"Weissach",
    "sg:phone":"+49 7044/33397",
    "sg:postcode":"71287",
    "sg:province":"Baden-W\u00fcrttemberg",
    "wof:name":"A. P. Elektronik Gmbh",
    "wof:placetype":"venue"
},
  "geometry": {"coordinates":[8.9268035889,48.8506660461],"type":"Point"}
}