{
  "type": "Feature",
  "properties": {
    "iso:country":"DE",
    "sg:address":"Alt-Blankenburg 25",
    "sg:city":"Berlin",
    "sg:phone":"+49 30/4743298",
    "sg:postcode":"13129",
    "sg:province":"Berlin",
    "wof:name":"Werkzeugschleiferei Schaube",
    "wof:placetype":"venue"
},
  "geometry": {"coordinates":[13.4547424316,52.5934371948],"type":"Point"}
}