{
  "type": "Feature",
  "properties": {
    "iso:country":"DE",
    "sg:address":"Bahnhofstr. 26",
    "sg:city":"Sohland",
    "sg:postcode":"02689",
    "sg:province":"Sachsen",
    "wof:name":"Wohnbau Sohland Gmbh",
    "wof:placetype":"venue"
},
  "geometry": {"coordinates":[14.4280700684,51.0465583801],"type":"Point"}
}