{
  "type": "Feature",
  "properties": {
    "iso:country":"DE",
    "sg:address":"Bielefelder Str. 215",
    "sg:city":"Verl",
    "sg:phone":"+49 5246/6690",
    "sg:postcode":"33415",
    "sg:province":"Nordrhein-Westfalen",
    "wof:name":"Herbert Piepenbrock Ingenieur",
    "wof:placetype":"venue"
},
  "geometry": {"coordinates":[8.4936294556,51.9063262939],"type":"Point"}
}