{
  "type": "Feature",
  "properties": {
    "iso:country":"DE",
    "sg:address":"Dreieichstr. 10",
    "sg:city":"M\u00f6rfelden-Walldorf",
    "sg:postcode":"64546",
    "sg:province":"Hessen",
    "wof:name":"Born Videotheken Betriebsges. Kg",
    "wof:placetype":"venue"
},
  "geometry": {"coordinates":[8.582597,49.983547],"type":"Point"}
}