{
  "type": "Feature",
  "properties": {
    "iso:country":"DE",
    "sg:address":"Hechtweg 6",
    "sg:city":"Erlangen",
    "sg:phone":"+49 9131/45361",
    "sg:postcode":"91056",
    "sg:province":"Bayern",
    "wof:name":"Fink Werbeagentur Gmbh",
    "wof:placetype":"venue"
},
  "geometry": {"coordinates":[10.9348773956,49.6020622253],"type":"Point"}
}