{
  "type": "Feature",
  "properties": {
    "iso:country":"DE",
    "sg:address":"Ernst-Th\u00e4lmann-Str. 4",
    "sg:city":"Osterburg",
    "sg:phone":"+49 3937/84551",
    "sg:postcode":"39606",
    "sg:province":"Sachsen-Anhalt",
    "wof:name":"R. Fromm",
    "wof:placetype":"venue"
},
  "geometry": {"coordinates":[11.7548475266,52.7866287231],"type":"Point"}
}