{
  "type": "Feature",
  "properties": {
    "iso:country":"DE",
    "sg:address":"Meschwitzstr 9-11",
    "sg:city":"Dresden",
    "sg:phone":"+49 351/8266640",
    "sg:postcode":"01099",
    "sg:province":"Sachsen",
    "wof:name":"Schroth",
    "wof:placetype":"venue"
},
  "geometry": {"coordinates":[13.765569,51.084106],"type":"Point"}
}