{
  "type": "Feature",
  "properties": {
    "iso:country":"DE",
    "sg:address":"T\u00f6nisheider Str. 20",
    "sg:city":"W\u00fclfrath",
    "sg:phone":"+49 2058/4132",
    "sg:postcode":"42489",
    "sg:province":"Nordrhein-Westfalen",
    "wof:name":"Sch\u00f6ller Gmbh",
    "wof:placetype":"venue"
},
  "geometry": {"coordinates":[7.043672,51.287247],"type":"Point"}
}