{
  "type": "Feature",
  "properties": {
    "iso:country":"DE",
    "sg:address":"Kieferstr. 27",
    "sg:city":"Dortmund",
    "sg:phone":"+49 231/711530",
    "sg:postcode":"44225",
    "sg:province":"Nordrhein-Westfalen",
    "wof:name":"Hovemann Betriebs Gmbh",
    "wof:placetype":"venue"
},
  "geometry": {"coordinates":[7.4324421883,51.4718742371],"type":"Point"}
}