{
  "type": "Feature",
  "properties": {
    "iso:country":"DE",
    "sg:address":"Jahnstr. 23",
    "sg:city":"Zwickau",
    "sg:phone":"+49 375/213547",
    "sg:postcode":"08058",
    "sg:province":"Sachsen",
    "wof:name":"Frank Christer",
    "wof:placetype":"venue"
},
  "geometry": {"coordinates":[12.477401,50.736553],"type":"Point"}
}