{
  "type": "Feature",
  "properties": {
    "iso:country":"DE",
    "sg:address":"Ingolst\u00e4dter Str. 76",
    "sg:city":"K\u00f6nigsmoos",
    "sg:phone":"+49 8454/2878",
    "sg:postcode":"86669",
    "sg:province":"Bayern",
    "wof:name":"Ernst Br\u00fcderle",
    "wof:placetype":"venue"
},
  "geometry": {"coordinates":[11.240896,48.670033],"type":"Point"}
}