{
  "type": "Feature",
  "properties": {
    "iso:country":"DE",
    "sg:address":"Deichstr. 31",
    "sg:city":"Hoya",
    "sg:phone":"+49 4251/7200",
    "sg:postcode":"27318",
    "sg:province":"Niedersachsen",
    "wof:name":"Taxi-jacob E. K.",
    "wof:placetype":"venue"
},
  "geometry": {"coordinates":[9.1443319321,52.8085632324],"type":"Point"}
}