{
  "type": "Feature",
  "properties": {
    "iso:country":"DE",
    "sg:address":"Benzer Str 8",
    "sg:city":"Malente",
    "sg:phone":"+49 4523/99110",
    "sg:postcode":"23714",
    "sg:province":"Schleswig-Holstein",
    "wof:name":"Sallingboe Kunstgewerbe Gmbh",
    "wof:placetype":"venue"
},
  "geometry": {"coordinates":[10.6472902298,54.201210022],"type":"Point"}
}