{
  "type": "Feature",
  "properties": {
    "iso:country":"DE",
    "sg:address":"Oesterweger Str. 14",
    "sg:city":"Versmold",
    "sg:phone":"+49 5423/49030",
    "sg:postcode":"33775",
    "sg:province":"Nordrhein-Westfalen",
    "wof:name":"Kibler",
    "wof:placetype":"venue"
},
  "geometry": {"coordinates":[8.22786,52.026226],"type":"Point"}
}