{
  "type": "Feature",
  "properties": {
    "iso:country":"DE",
    "sg:address":"Ellrichsh\u00e4user Str. 9",
    "sg:city":"Satteldorf",
    "sg:phone":"+49 7951/7880",
    "sg:postcode":"74589",
    "sg:province":"Baden-W\u00fcrttemberg",
    "wof:name":"Fritz Wieland",
    "wof:placetype":"venue"
},
  "geometry": {"coordinates":[10.0862998962,49.1701316833],"type":"Point"}
}