{
  "type": "Feature",
  "properties": {
    "iso:country":"DE",
    "sg:address":"Am K\u00f6nigsbusch 35",
    "sg:city":"Langerwehe",
    "sg:phone":"+49 2423/3222",
    "sg:postcode":"52379",
    "sg:province":"Nordrhein-Westfalen",
    "wof:name":"Birgit Knorr Krankengymnastin",
    "wof:placetype":"venue"
},
  "geometry": {"coordinates":[6.367562,50.812683],"type":"Point"}
}