{
  "type": "Feature",
  "properties": {
    "iso:country":"DE",
    "sg:address":"Hauptstr. 17",
    "sg:city":"Biedenkopf",
    "sg:phone":"+49 6461/8653",
    "sg:postcode":"35216",
    "sg:province":"Hessen",
    "wof:name":"Zur Stadtsch\u00e4nke",
    "wof:placetype":"venue"
},
  "geometry": {"coordinates":[8.4684877396,50.9138031006],"type":"Point"}
}