{
  "type": "Feature",
  "properties": {
    "iso:country":"DE",
    "sg:address":"Handwerkerweg 2",
    "sg:city":"Preetz",
    "sg:phone":"+49 4342/84406",
    "sg:postcode":"24211",
    "sg:province":"Schleswig-Holstein",
    "wof:name":"Thate Gedr\u00fcckte Pr\u00e4zision Inh. H. Weimann",
    "wof:placetype":"venue"
},
  "geometry": {"coordinates":[10.282623291,54.235912323],"type":"Point"}
}