{
  "type": "Feature",
  "properties": {
    "iso:country":"DE",
    "sg:address":"Senkingstr. 27",
    "sg:city":"Hildesheim",
    "sg:phone":"+49 5121/516787",
    "sg:postcode":"31137",
    "sg:province":"Niedersachsen",
    "wof:name":"Sch\u00f6ler & Micke Gmbh",
    "wof:placetype":"venue"
},
  "geometry": {"coordinates":[9.941638,52.157837],"type":"Point"}
}