{
  "type": "Feature",
  "properties": {
    "iso:country":"DE",
    "sg:address":"Hohenesch 68",
    "sg:city":"Hamburg",
    "sg:phone":"+49 40/3906941",
    "sg:postcode":"22765",
    "sg:province":"Hamburg",
    "wof:name":"B\u00c4ng Siebdruckerei",
    "wof:placetype":"venue"
},
  "geometry": {"coordinates":[9.9316253662,53.5540733337],"type":"Point"}
}