{
  "type": "Feature",
  "properties": {
    "iso:country":"DE",
    "sg:address":"Sonnenstr. 1",
    "sg:city":"Gie\u00dfen",
    "sg:phone":"+49 641/31968",
    "sg:postcode":"35390",
    "sg:province":"Hessen",
    "wof:name":"Solid Gmbh",
    "wof:placetype":"venue"
},
  "geometry": {"coordinates":[8.676777,50.586411],"type":"Point"}
}