{
  "type": "Feature",
  "properties": {
    "iso:country":"DE",
    "sg:address":"Hauptstr. 17",
    "sg:city":"Kleinrinderfeld",
    "sg:phone":"+49 9366/1560",
    "sg:postcode":"97271",
    "sg:province":"Bayern",
    "wof:name":"Gerhard Borst",
    "wof:placetype":"venue"
},
  "geometry": {"coordinates":[9.844465,49.698601],"type":"Point"}
}