{
  "type": "Feature",
  "properties": {
    "iso:country":"DE",
    "sg:address":"Gartenstr. 4",
    "sg:city":"Ebensfeld",
    "sg:postcode":"96250",
    "sg:province":"Bayern",
    "wof:name":"Bernd Ackermann Ergotherapiepraxis",
    "wof:placetype":"venue"
},
  "geometry": {"coordinates":[10.959404,50.063061],"type":"Point"}
}