{
  "type": "Feature",
  "properties": {
    "iso:country":"DE",
    "sg:address":"Leopoldstr. 5",
    "sg:city":"M\u00fcnchen",
    "sg:phone":"+49 89/21803622",
    "sg:postcode":"80802",
    "sg:province":"Bayern",
    "wof:name":"Institut F\u00fcr Vergleichende Tropenmedizin Und Para-",
    "wof:placetype":"venue"
},
  "geometry": {"coordinates":[11.5826148987,48.1538047791],"type":"Point"}
}