{
  "type": "Feature",
  "properties": {
    "iso:country":"DE",
    "sg:address":"Lindenhofstr. 7",
    "sg:city":"Bergen",
    "sg:phone":"+49 8662/8302",
    "sg:postcode":"83346",
    "sg:province":"Bayern",
    "wof:name":"Bergener Wintersport- Veranstaltungs-gmbh",
    "wof:placetype":"venue"
},
  "geometry": {"coordinates":[12.59173,47.798664],"type":"Point"}
}