{
  "type": "Feature",
  "properties": {
    "iso:country":"DE",
    "sg:address":"Sudetenstr. 5",
    "sg:city":"Glauburg",
    "sg:phone":"+49 6041/1396",
    "sg:postcode":"63695",
    "sg:province":"Hessen",
    "wof:name":"J. Neeb Leasing",
    "wof:placetype":"venue"
},
  "geometry": {"coordinates":[9.0131168365,50.3263130188],"type":"Point"}
}