{
  "type": "Feature",
  "properties": {
    "iso:country":"DE",
    "sg:address":"Memelstr.",
    "sg:city":"Erlangen",
    "sg:phone":"+49 9131/39187",
    "sg:postcode":"91052",
    "sg:province":"Bayern",
    "wof:name":"Modeatelier S. Niersberger",
    "wof:placetype":"venue"
},
  "geometry": {"coordinates":[11.0103149414,49.5841255188],"type":"Point"}
}