{
  "type": "Feature",
  "properties": {
    "iso:country":"DE",
    "sg:address":"Hofer Str. 3",
    "sg:city":"Rehau",
    "sg:phone":"+49 9283/1515",
    "sg:postcode":"95111",
    "sg:province":"Bayern",
    "wof:name":"Georg Rank",
    "wof:placetype":"venue"
},
  "geometry": {"coordinates":[12.0311250687,50.2510910034],"type":"Point"}
}