{
  "type": "Feature",
  "properties": {
    "iso:country":"DE",
    "sg:address":"Altholzstr. 1",
    "sg:city":"Deggendorf",
    "sg:phone":"+49 991/6181",
    "sg:postcode":"94469",
    "sg:province":"Bayern",
    "wof:name":"Walter Kufner",
    "wof:placetype":"venue"
},
  "geometry": {"coordinates":[12.944664,48.812641],"type":"Point"}
}