{
  "type": "Feature",
  "properties": {
    "iso:country":"DE",
    "sg:address":"Hauptstr. 11-13",
    "sg:city":"Neuenhaus",
    "sg:postcode":"49828",
    "sg:province":"Niedersachsen",
    "wof:name":"Aktiv-markt",
    "wof:placetype":"venue"
},
  "geometry": {"coordinates":[6.9625349045,52.4972305298],"type":"Point"}
}