{
  "type": "Feature",
  "properties": {
    "iso:country":"DE",
    "sg:address":"Pennricher Str. 28",
    "sg:city":"Dresden",
    "sg:phone":"+49 351/4216761",
    "sg:postcode":"01157",
    "sg:province":"Sachsen",
    "wof:name":"M. Brilka",
    "wof:placetype":"venue"
},
  "geometry": {"coordinates":[13.6916618347,51.0492324829],"type":"Point"}
}