{
  "type": "Feature",
  "properties": {
    "iso:country":"DE",
    "sg:address":"R\u00fcssenbacher Str.",
    "sg:city":"Ebermannstadt",
    "sg:postcode":"91320",
    "sg:province":"Bayern",
    "wof:name":"Geiger Maschinenbau Gmbh",
    "wof:placetype":"venue"
},
  "geometry": {"coordinates":[11.162426,49.769611],"type":"Point"}
}