{
  "type": "Feature",
  "properties": {
    "iso:country":"DE",
    "sg:address":"Kart\u00e4userstr. 14",
    "sg:city":"Freiburg",
    "sg:phone":"+49 761/33519",
    "sg:postcode":"79102",
    "sg:province":"Baden-W\u00fcrttemberg",
    "wof:name":"Amin",
    "wof:placetype":"venue"
},
  "geometry": {"coordinates":[7.8560991287,47.9916725159],"type":"Point"}
}