{
  "type": "Feature",
  "properties": {
    "iso:country":"DE",
    "sg:address":"Mengstr. 4",
    "sg:city":"L\u00fcbeck",
    "sg:phone":"+49 451/1224192",
    "sg:postcode":"23552",
    "sg:province":"Schleswig-Holstein",
    "wof:name":"Kulturstiftung Hansestadt L\u00fcbeck",
    "wof:placetype":"venue"
},
  "geometry": {"coordinates":[10.6859779358,53.8683013916],"type":"Point"}
}