{
  "type": "Feature",
  "properties": {
    "iso:country":"DE",
    "sg:address":"Rheinallee 45",
    "sg:city":"Bonn",
    "sg:phone":"+49 228/358355",
    "sg:postcode":"53173",
    "sg:province":"Nordrhein-Westfalen",
    "wof:name":"Botschaft Der Republik Kongo",
    "wof:placetype":"venue"
},
  "geometry": {"coordinates":[7.1658978462,50.6889190674],"type":"Point"}
}