{
  "type": "Feature",
  "properties": {
    "iso:country":"DE",
    "sg:address":"Blumenau 173",
    "sg:city":"Hamburg",
    "sg:phone":"+49 40/2003040",
    "sg:postcode":"22089",
    "sg:province":"Hamburg",
    "wof:name":"Beate Streckert",
    "wof:placetype":"venue"
},
  "geometry": {"coordinates":[10.0439376831,53.570476532],"type":"Point"}
}