{
  "type": "Feature",
  "properties": {
    "iso:country":"DE",
    "sg:address":"Finnentroper Str. 39",
    "sg:city":"Attendorn",
    "sg:phone":"+49 2722/3042",
    "sg:postcode":"57439",
    "sg:province":"Nordrhein-Westfalen",
    "wof:name":"Hotel Himmelreich",
    "wof:placetype":"venue"
},
  "geometry": {"coordinates":[7.9147791862,51.1249923706],"type":"Point"}
}