{
  "type": "Feature",
  "properties": {
    "iso:country":"DE",
    "sg:address":"Tauchaer Str. 260",
    "sg:city":"Leipzig",
    "sg:phone":"+49 341/9214834",
    "sg:postcode":"04349",
    "sg:province":"Sachsen",
    "wof:name":"Wiesen-apotheke Inh. Isa Schneider",
    "wof:placetype":"venue"
},
  "geometry": {"coordinates":[12.450014,51.383244],"type":"Point"}
}