{
  "type": "Feature",
  "properties": {
    "iso:country":"DE",
    "sg:address":"Dorfstr. 24",
    "sg:city":"Pl\u00f6\u00dfberg",
    "sg:phone":"+49 9636/91144",
    "sg:postcode":"95703",
    "sg:province":"Bayern",
    "wof:name":"Alu Tech Gmbh",
    "wof:placetype":"venue"
},
  "geometry": {"coordinates":[12.290974,49.793793],"type":"Point"}
}