{
  "type": "Feature",
  "properties": {
    "iso:country":"DE",
    "sg:address":"Schlo\u00dfstr. 83",
    "sg:city":"Frankfurt",
    "sg:phone":"+49 69/772323",
    "sg:postcode":"60486",
    "sg:province":"Hessen",
    "wof:name":"Karin Hoyer",
    "wof:placetype":"venue"
},
  "geometry": {"coordinates":[8.6450004578,50.1181945801],"type":"Point"}
}