{
  "type": "Feature",
  "properties": {
    "iso:country":"DE",
    "sg:address":"Frankenbacher Str. 31",
    "sg:city":"Heilbronn",
    "sg:phone":"+49 7131/21043",
    "sg:postcode":"74078",
    "sg:province":"Baden-W\u00fcrttemberg",
    "wof:name":"Sonjas Fruchtk\u00f6rble",
    "wof:placetype":"venue"
},
  "geometry": {"coordinates":[9.2004528046,49.1688194275],"type":"Point"}
}