{
  "type": "Feature",
  "properties": {
    "iso:country":"DE",
    "sg:address":"Fichtenweg 2",
    "sg:city":"Drachselsried",
    "sg:phone":"+49 9945/1006",
    "sg:postcode":"94256",
    "sg:province":"Bayern",
    "wof:name":"Pension Siegfried Gra\u00dfl",
    "wof:placetype":"venue"
},
  "geometry": {"coordinates":[13.009472847,49.1088180542],"type":"Point"}
}