{
  "type": "Feature",
  "properties": {
    "iso:country":"DE",
    "sg:address":"Weimarer Str. 8",
    "sg:city":"St. Wendel",
    "sg:phone":"+49 6851/3091",
    "sg:postcode":"66606",
    "sg:province":"Saarland",
    "wof:name":"Schuster & Sohn Gmbh Esso Vertretung",
    "wof:placetype":"venue"
},
  "geometry": {"coordinates":[7.14412117,49.462020874],"type":"Point"}
}