{
  "type": "Feature",
  "properties": {
    "iso:country":"DE",
    "sg:address":"Von-der-Mark-Str. 65",
    "sg:city":"Duisburg",
    "sg:phone":"+49 203/445648",
    "sg:postcode":"47137",
    "sg:province":"Nordrhein-Westfalen",
    "wof:name":"Beerdigungsinstitut Ute Kaiser-musebrink",
    "wof:placetype":"venue"
},
  "geometry": {"coordinates":[6.774497,51.467255],"type":"Point"}
}