{
  "type": "Feature",
  "properties": {
    "iso:country":"DE",
    "sg:address":"Dammweg 6",
    "sg:city":"Verl",
    "sg:phone":"+49 5244/1614",
    "sg:postcode":"33415",
    "sg:province":"Nordrhein-Westfalen",
    "wof:name":"Christian Schlingmann",
    "wof:placetype":"venue"
},
  "geometry": {"coordinates":[8.504401,51.843876],"type":"Point"}
}