{
  "type": "Feature",
  "properties": {
    "iso:country":"DE",
    "sg:address":"John-F.-Kennedy-Str. 29-1",
    "sg:city":"Heilbronn",
    "sg:phone":"+49 7131/402745",
    "sg:postcode":"74074",
    "sg:province":"Baden-W\u00fcrttemberg",
    "wof:name":"Herbert Klomann",
    "wof:placetype":"venue"
},
  "geometry": {"coordinates":[9.2216348648,49.1241188049],"type":"Point"}
}