{
  "type": "Feature",
  "properties": {
    "iso:country":"DE",
    "sg:address":"Benzstr. 2",
    "sg:city":"L\u00fcbeck",
    "sg:phone":"+49 451/601212",
    "sg:postcode":"23566",
    "sg:province":"Schleswig-Holstein",
    "wof:name":"Kath. Pfarramt Liebfrauen",
    "wof:placetype":"venue"
},
  "geometry": {"coordinates":[10.7374973297,53.853679657],"type":"Point"}
}