{
  "type": "Feature",
  "properties": {
    "iso:country":"DE",
    "sg:address":"Eichsfelder Stra\u00dfe 99",
    "sg:city":"Hannover",
    "sg:phone":"+49 4951/1790160",
    "sg:postcode":"30419",
    "sg:province":"Niedersachsen",
    "wof:name":"Hotel Andrea",
    "wof:placetype":"venue"
},
  "geometry": {"coordinates":[9.663998,52.409523],"type":"Point"}
}