{
  "type": "Feature",
  "properties": {
    "iso:country":"DE",
    "sg:address":"J\u00f6llenbecker 100",
    "sg:city":"Bielefeld",
    "sg:phone":"+49 4952/128920",
    "sg:postcode":"33613",
    "sg:province":"Nordrhein-Westfalen",
    "wof:name":"Twistel Gmbh",
    "wof:placetype":"venue"
},
  "geometry": {"coordinates":[8.5241193771,52.0348510742],"type":"Point"}
}