{
  "type": "Feature",
  "properties": {
    "iso:country":"DE",
    "sg:address":"Weidenweg 61",
    "sg:city":"Duisburg",
    "sg:phone":"+49 203/310127",
    "sg:postcode":"47059",
    "sg:province":"Nordrhein-Westfalen",
    "wof:name":"Heinrich Loesken",
    "wof:placetype":"venue"
},
  "geometry": {"coordinates":[6.749350071,51.4375],"type":"Point"}
}