{
  "type": "Feature",
  "properties": {
    "iso:country":"DE",
    "sg:address":"Graf-Goltstein-Str. 6",
    "sg:city":"Geilenkirchen",
    "sg:phone":"+49 2451/68246",
    "sg:postcode":"52511",
    "sg:province":"Nordrhein-Westfalen",
    "wof:name":"Karl Josef Lamersdorf Gmbh",
    "wof:placetype":"venue"
},
  "geometry": {"coordinates":[6.1308588982,50.9649162292],"type":"Point"}
}