{
  "type": "Feature",
  "properties": {
    "iso:country":"DE",
    "sg:address":"Speicherstr. 10",
    "sg:city":"Bernburg",
    "sg:phone":"+49 3471/22159",
    "sg:postcode":"06406",
    "sg:province":"Sachsen-Anhalt",
    "wof:name":"Tabel & Hanusa Gbr",
    "wof:placetype":"venue"
},
  "geometry": {"coordinates":[11.73456,51.793259],"type":"Point"}
}