{
  "type": "Feature",
  "properties": {
    "iso:country":"DE",
    "sg:address":"Augustastr. 21",
    "sg:city":"Herten",
    "sg:phone":"+49 2366/38500",
    "sg:postcode":"45699",
    "sg:province":"Nordrhein-Westfalen",
    "wof:name":"U. Roch",
    "wof:placetype":"venue"
},
  "geometry": {"coordinates":[7.1531667709,51.5795631409],"type":"Point"}
}