{
  "type": "Feature",
  "properties": {
    "iso:country":"DE",
    "sg:address":"Rungestrasse 22-24",
    "sg:city":"Berlin",
    "sg:classifiers":[
        {
            "category":"Professional",
            "subcategory":"Computer Services",
            "type":"Services"
        }
    ],
    "sg:postcode":"10179",
    "sg:tags":[
        "web-application",
        "web-development",
        "software",
        "germany",
        "europe",
        "silverlight",
        "python",
        "ajax",
        "php",
        "ruby",
        "javascript",
        "wpf",
        "berlin"
    ],
    "sg:website":"http://www.puremedia-online.de",
    "wof:name":"puremedia",
    "wof:placetype":"venue"
},
  "geometry": {"coordinates":[13.4192693,52.5122701],"type":"Point"}
}