{
  "type": "Feature",
  "properties": {
    "iso:country":"DE",
    "sg:address":"H\u00f6perfeld 5",
    "sg:city":"Hamburg",
    "sg:phone":"+49 40/7240668",
    "sg:postcode":"21033",
    "sg:province":"Hamburg",
    "wof:name":"J. Grabbe",
    "wof:placetype":"venue"
},
  "geometry": {"coordinates":[10.2046489716,53.4943962097],"type":"Point"}
}