{
  "type": "Feature",
  "properties": {
    "iso:country":"DE",
    "sg:address":"Johannesplatz 3",
    "sg:city":"J\u00fclich",
    "sg:phone":"+49 2463/905980",
    "sg:postcode":"52428",
    "sg:province":"Nordrhein-Westfalen",
    "wof:name":"Bauunternehmung Ingo Becker Gmbh",
    "wof:placetype":"venue"
},
  "geometry": {"coordinates":[6.43083,50.958874],"type":"Point"}
}