{
  "type": "Feature",
  "properties": {
    "iso:country":"DE",
    "sg:address":"Springstr. 18",
    "sg:city":"Geislingen",
    "sg:postcode":"73312",
    "sg:province":"Baden-W\u00fcrttemberg",
    "wof:name":"Eugen Ruff Gmbh",
    "wof:placetype":"venue"
},
  "geometry": {"coordinates":[9.827898,48.626125],"type":"Point"}
}