{
  "type": "Feature",
  "properties": {
    "iso:country":"DE",
    "sg:address":"Dreik\u00f6nigstr. 14",
    "sg:city":"Freiburg",
    "sg:phone":"+49 761/7070934",
    "sg:postcode":"79102",
    "sg:province":"Baden-W\u00fcrttemberg",
    "wof:name":"Synerges Synergetische Gesundheitsf\u00f6rderung Kg",
    "wof:placetype":"venue"
},
  "geometry": {"coordinates":[7.857028,47.988636],"type":"Point"}
}