{
  "type": "Feature",
  "properties": {
    "iso:country":"DE",
    "sg:address":"Johann-Wichern-Str. 2",
    "sg:city":"Geseke",
    "sg:phone":"+49 2942/1235",
    "sg:postcode":"59590",
    "sg:province":"Nordrhein-Westfalen",
    "wof:name":"A. Sanders",
    "wof:placetype":"venue"
},
  "geometry": {"coordinates":[8.496755,51.641479],"type":"Point"}
}