{
  "type": "Feature",
  "properties": {
    "iso:country":"DE",
    "sg:address":"Kirchstr. 12",
    "sg:city":"Vilsbiburg",
    "sg:phone":"+49 8741/4175",
    "sg:postcode":"84137",
    "sg:province":"Bayern",
    "wof:name":"Dieter Trespe Masseur",
    "wof:placetype":"venue"
},
  "geometry": {"coordinates":[12.357793,48.452236],"type":"Point"}
}