{
  "type": "Feature",
  "properties": {
    "iso:country":"DE",
    "sg:address":"Hauptstr. 110",
    "sg:city":"Neubiberg",
    "sg:phone":"+49 89/6011213",
    "sg:postcode":"85579",
    "sg:province":"Bayern",
    "wof:name":"Carl Weigang",
    "wof:placetype":"venue"
},
  "geometry": {"coordinates":[11.6823310852,48.074092865],"type":"Point"}
}