{
  "type": "Feature",
  "properties": {
    "iso:country":"DE",
    "sg:address":"Libellenweg 7",
    "sg:city":"Osnabr\u00fcck",
    "sg:phone":"+49 541/441453",
    "sg:postcode":"49078",
    "sg:province":"Niedersachsen",
    "wof:name":"Willy Mehlmann Masseur",
    "wof:placetype":"venue"
},
  "geometry": {"coordinates":[7.990638,52.256969],"type":"Point"}
}