{
  "type": "Feature",
  "properties": {
    "iso:country":"DE",
    "sg:address":"Domstr. 11",
    "sg:city":"Greifswald",
    "sg:phone":"+49 3834/862503",
    "sg:postcode":"17489",
    "sg:province":"Mecklenburg-Vorpommern",
    "wof:name":"Victor-schultze-institut",
    "wof:placetype":"venue"
},
  "geometry": {"coordinates":[13.374873,54.094936],"type":"Point"}
}