{
  "type": "Feature",
  "properties": {
    "iso:country":"DE",
    "sg:address":"W\u00fcrzburger Stra\u00dfe",
    "sg:city":"Estenfeld",
    "sg:phone":"+49 9305",
    "sg:postcode":"97230",
    "sg:province":"Bayern",
    "wof:name":"Tennisclub Estenfeld",
    "wof:placetype":"venue"
},
  "geometry": {"coordinates":[10.004775,49.830875],"type":"Point"}
}