{
  "type": "Feature",
  "properties": {
    "iso:country":"DE",
    "sg:address":"Neusser Landstr. 9",
    "sg:city":"K\u00f6ln",
    "sg:phone":"+49 221/701471",
    "sg:postcode":"50769",
    "sg:province":"Nordrhein-Westfalen",
    "wof:name":"Edda Frehn Heilpraktikerin",
    "wof:placetype":"venue"
},
  "geometry": {"coordinates":[6.9036960602,51.0349235535],"type":"Point"}
}