{
  "type": "Feature",
  "properties": {
    "iso:country":"DE",
    "sg:address":"Grabfeldstr. 33",
    "sg:city":"Mellrichstadt",
    "sg:phone":"+49 9776/1881",
    "sg:postcode":"97638",
    "sg:province":"Bayern",
    "wof:name":"Eugen Diesel",
    "wof:placetype":"venue"
},
  "geometry": {"coordinates":[10.37973,50.417458],"type":"Point"}
}