{
  "type": "Feature",
  "properties": {
    "iso:country":"DE",
    "sg:address":"Klagenfurter Ring 100",
    "sg:city":"Wiesbaden",
    "sg:phone":"+49 611/85239",
    "sg:postcode":"65187",
    "sg:province":"Hessen",
    "wof:name":"Rudolf Hausmann",
    "wof:placetype":"venue"
},
  "geometry": {"coordinates":[8.2181806564,50.0588493347],"type":"Point"}
}