{
  "type": "Feature",
  "properties": {
    "iso:country":"DE",
    "sg:address":"Oberdorfer Str. 14",
    "sg:city":"Mittelstetten",
    "sg:phone":"+49 8202/8009",
    "sg:postcode":"82293",
    "sg:province":"Bayern",
    "wof:name":"J. Britzelmair Mech. Werkst\u00e4tte",
    "wof:placetype":"venue"
},
  "geometry": {"coordinates":[11.09359,48.254829],"type":"Point"}
}