{
  "type": "Feature",
  "properties": {
    "iso:country":"DE",
    "sg:address":"Sch\u00fctzenhof 71",
    "sg:city":"Meppen",
    "sg:phone":"+49 5931/7061",
    "sg:postcode":"49716",
    "sg:province":"Niedersachsen",
    "wof:name":"August Schonhoff Gbr",
    "wof:placetype":"venue"
},
  "geometry": {"coordinates":[7.28397,52.70649],"type":"Point"}
}