{
  "type": "Feature",
  "properties": {
    "iso:country":"DE",
    "sg:address":"Cunnersdorfer Str. 24",
    "sg:city":"Leipzig",
    "sg:phone":"+49 341/2610453",
    "sg:postcode":"04318",
    "sg:province":"Sachsen",
    "wof:name":"Sartory Gmbh",
    "wof:placetype":"venue"
},
  "geometry": {"coordinates":[12.42998,51.341698],"type":"Point"}
}