{
  "type": "Feature",
  "properties": {
    "iso:country":"DE",
    "sg:address":"Saarstr. 99",
    "sg:city":"Trier",
    "sg:phone":"+49 651/35355",
    "sg:postcode":"54290",
    "sg:province":"Rheinland-Pfalz",
    "wof:name":"Eiscafe San Marco",
    "wof:placetype":"venue"
},
  "geometry": {"coordinates":[6.634681,49.744282],"type":"Point"}
}