{
  "type": "Feature",
  "properties": {
    "iso:country":"DE",
    "sg:address":"Rosenstr. 123",
    "sg:city":"Mannheim",
    "sg:phone":"+49 621/8620364",
    "sg:postcode":"68199",
    "sg:province":"Baden-W\u00fcrttemberg",
    "wof:name":"Petra Kaetel",
    "wof:placetype":"venue"
},
  "geometry": {"coordinates":[8.48521,49.452408],"type":"Point"}
}