{
  "type": "Feature",
  "properties": {
    "iso:country":"DE",
    "sg:address":"Am Berg 2",
    "sg:city":"Bad Birnbach",
    "sg:phone":"+49 8563/3960",
    "sg:postcode":"84364",
    "sg:province":"Bayern",
    "wof:name":"Gasthof Wirt Am Berg",
    "wof:placetype":"venue"
},
  "geometry": {"coordinates":[13.0932016373,48.4436798096],"type":"Point"}
}