{
  "type": "Feature",
  "properties": {
    "iso:country":"DE",
    "sg:address":"Glockengie\u00dferwall 17",
    "sg:city":"Hamburg",
    "sg:postcode":"20095",
    "sg:province":"Hamburg",
    "wof:name":"Hdm Bau Gmbh",
    "wof:placetype":"venue"
},
  "geometry": {"coordinates":[10.002571,53.554375],"type":"Point"}
}