{
  "type": "Feature",
  "properties": {
    "iso:country":"DE",
    "sg:address":"Bischof-Vicelin-Damm 8",
    "sg:city":"Bosau",
    "sg:phone":"+49 4527/530",
    "sg:postcode":"23715",
    "sg:province":"Schleswig-Holstein",
    "wof:name":"M\u00f6ller-holzbau Gmbh",
    "wof:placetype":"venue"
},
  "geometry": {"coordinates":[10.4284448624,54.1053543091],"type":"Point"}
}