{
  "type": "Feature",
  "properties": {
    "iso:country":"DE",
    "sg:address":"Rurwiesenstr. 27",
    "sg:city":"J\u00fclich",
    "sg:postcode":"52428",
    "sg:province":"Nordrhein-Westfalen",
    "wof:name":"B\u00fcrgerinitiative M\u00fcll Broich Gundi Jumpertz-steffke",
    "wof:placetype":"venue"
},
  "geometry": {"coordinates":[6.3304018974,50.9504356384],"type":"Point"}
}