{
  "type": "Feature",
  "properties": {
    "iso:country":"DE",
    "sg:address":"Heidemannstrasse 220",
    "sg:city":"M\u00fcnchen",
    "sg:postcode":"80939",
    "sg:province":"Bayern",
    "wof:name":"Autobusoberbayern",
    "wof:placetype":"venue"
},
  "geometry": {"coordinates":[11.614865303,48.198841095],"type":"Point"}
}