{
  "type": "Feature",
  "properties": {
    "iso:country":"DE",
    "sg:address":"Mainzer Str. 46",
    "sg:city":"Heidesheim",
    "sg:phone":"+49 6132/59071",
    "sg:postcode":"55262",
    "sg:province":"Rheinland-Pfalz",
    "wof:name":"F. Arnold",
    "wof:placetype":"venue"
},
  "geometry": {"coordinates":[8.1174955368,49.99609375],"type":"Point"}
}