{
  "type": "Feature",
  "properties": {
    "iso:country":"DE",
    "sg:address":"Dragonerstr. 29",
    "sg:city":"Oberhausen",
    "sg:phone":"+49 208/643250",
    "sg:postcode":"46149",
    "sg:province":"Nordrhein-Westfalen",
    "wof:name":"W. Mager",
    "wof:placetype":"venue"
},
  "geometry": {"coordinates":[6.8491997719,51.5297431946],"type":"Point"}
}