{
  "type": "Feature",
  "properties": {
    "iso:country":"DE",
    "sg:address":"Richard-Wagner-Str. 3",
    "sg:city":"Ingolstadt",
    "sg:phone":"+49 841/482345",
    "sg:postcode":"85057",
    "sg:province":"Bayern",
    "wof:name":"Herbert Przibylla",
    "wof:placetype":"venue"
},
  "geometry": {"coordinates":[11.416096,48.774857],"type":"Point"}
}