{
  "type": "Feature",
  "properties": {
    "iso:country":"DE",
    "sg:address":"Taunusblick 1",
    "sg:city":"Lahnstein",
    "sg:phone":"+49 2621/91700",
    "sg:postcode":"56112",
    "sg:province":"Rheinland-Pfalz",
    "wof:name":"Emu-verlags- Und Vertriebs Gmbh",
    "wof:placetype":"venue"
},
  "geometry": {"coordinates":[7.6452589035,50.3001022339],"type":"Point"}
}