{
  "type": "Feature",
  "properties": {
    "iso:country":"DE",
    "sg:address":"Westf\u00e4lische Str 251",
    "sg:city":"Dortmund",
    "sg:phone":"+49 231/25060",
    "sg:postcode":"44309",
    "sg:province":"Nordrhein-Westfalen",
    "wof:name":"Tremonis Gmbh",
    "wof:placetype":"venue"
},
  "geometry": {"coordinates":[7.564319,51.522442],"type":"Point"}
}