{
  "type": "Feature",
  "properties": {
    "iso:country":"DE",
    "sg:address":"Alter Steinweg 1",
    "sg:city":"Hamburg",
    "sg:phone":"+49 40/330001",
    "sg:postcode":"20459",
    "sg:province":"Hamburg",
    "wof:name":"Marcus Dirks Und Christian Holst",
    "wof:placetype":"venue"
},
  "geometry": {"coordinates":[9.9838094711,53.550113678],"type":"Point"}
}