{
  "type": "Feature",
  "properties": {
    "iso:country":"DE",
    "sg:address":"M\u00fchlweg 109",
    "sg:city":"Mainz",
    "sg:phone":"+49 6131/366633",
    "sg:postcode":"55128",
    "sg:province":"Rheinland-Pfalz",
    "wof:name":"Asb Baubetreuungs Gmbh",
    "wof:placetype":"venue"
},
  "geometry": {"coordinates":[8.254385,49.985722],"type":"Point"}
}