{
  "type": "Feature",
  "properties": {
    "iso:country":"DE",
    "sg:address":"Kranichstr. 21",
    "sg:city":"Duisburg",
    "sg:phone":"+49 203/7380512",
    "sg:postcode":"47055",
    "sg:province":"Nordrhein-Westfalen",
    "wof:name":"Awo Duisburg E. V.",
    "wof:placetype":"venue"
},
  "geometry": {"coordinates":[6.765616,51.402302],"type":"Point"}
}