{
  "type": "Feature",
  "properties": {
    "iso:country":"DE",
    "sg:address":"Eckertswehr 11",
    "sg:city":"Kreuztal",
    "sg:postcode":"57223",
    "sg:province":"Nordrhein-Westfalen",
    "wof:name":"Homero Consult Gmbh",
    "wof:placetype":"venue"
},
  "geometry": {"coordinates":[8.0398702621,50.9639778137],"type":"Point"}
}