{
  "type": "Feature",
  "properties": {
    "iso:country":"DE",
    "sg:address":"Fliederstr. 10",
    "sg:city":"Hanau",
    "sg:phone":"+49 6181/60261",
    "sg:postcode":"63456",
    "sg:province":"Hessen",
    "wof:name":"Hermann Theisinger Steuerberater",
    "wof:placetype":"venue"
},
  "geometry": {"coordinates":[8.9257125854,50.0968513489],"type":"Point"}
}