{
  "type": "Feature",
  "properties": {
    "iso:country":"DE",
    "sg:address":"Lappiner Platz",
    "sg:city":"Berlin",
    "sg:postcode":"12683",
    "sg:province":"Berlin",
    "wof:name":"Willkommen Beim Tc Berolina Biesdorf E.v. !",
    "wof:placetype":"venue"
},
  "geometry": {"coordinates":[13.55241,52.517666],"type":"Point"}
}