{
  "type": "Feature",
  "properties": {
    "iso:country":"DE",
    "sg:address":"Auf dem Wiesberg",
    "sg:city":"R\u00fcdesheim",
    "sg:postcode":"55593",
    "sg:province":"Rheinland-Pfalz",
    "wof:name":"Weingut R\u00fcdesheimer Hof Bernd B\u00e4der",
    "wof:placetype":"venue"
},
  "geometry": {"coordinates":[7.8184571266,49.8454208374],"type":"Point"}
}