{
  "type": "Feature",
  "properties": {
    "iso:country":"DE",
    "sg:address":"H\u00f6lzleweg 4",
    "sg:city":"Bad Saulgau",
    "sg:phone":"+49 7581/6187",
    "sg:postcode":"88348",
    "sg:province":"Baden-W\u00fcrttemberg",
    "wof:name":"Josef M\u00fctz",
    "wof:placetype":"venue"
},
  "geometry": {"coordinates":[9.548762,48.002232],"type":"Point"}
}