{
  "type": "Feature",
  "properties": {
    "iso:country":"DE",
    "sg:address":"Obernauer Str. 8b",
    "sg:city":"Aschaffenburg",
    "sg:phone":"+49 6021/13384",
    "sg:postcode":"63739",
    "sg:province":"Bayern",
    "wof:name":"B. Und E. Nussbaum Finanzberater",
    "wof:placetype":"venue"
},
  "geometry": {"coordinates":[9.1419286728,49.9683418274],"type":"Point"}
}