{
  "type": "Feature",
  "properties": {
    "iso:country":"DE",
    "sg:address":"L\u00fctzschenaer Str. 1",
    "sg:city":"B\u00f6hlitz-Ehrenberg",
    "sg:phone":"+49 341/4426859",
    "sg:postcode":"04430",
    "wof:name":"A. Winter",
    "wof:placetype":"venue"
},
  "geometry": {"coordinates":[12.2709321976,51.3619995117],"type":"Point"}
}