{
  "type": "Feature",
  "properties": {
    "iso:country":"DE",
    "sg:address":"Zum Kreuz 12",
    "sg:city":"Nidda",
    "sg:phone":"+49 6043/3134",
    "sg:postcode":"63667",
    "sg:province":"Hessen",
    "wof:name":"Adolf Hannig",
    "wof:placetype":"venue"
},
  "geometry": {"coordinates":[8.969823,50.404137],"type":"Point"}
}