{
  "type": "Feature",
  "properties": {
    "iso:country":"DE",
    "sg:address":"Rathausplatz 4",
    "sg:city":"Hattingen",
    "sg:phone":"+49 2324/22985",
    "sg:postcode":"45525",
    "sg:province":"Nordrhein-Westfalen",
    "wof:name":"Egon Baske",
    "wof:placetype":"venue"
},
  "geometry": {"coordinates":[7.185251,51.40033],"type":"Point"}
}