{
  "type": "Feature",
  "properties": {
    "iso:country":"DE",
    "sg:address":"W\u00f6hrdstr. 12",
    "sg:city":"Regensburg",
    "sg:phone":"+49 941/54231",
    "sg:postcode":"93059",
    "sg:province":"Bayern",
    "wof:name":"Masters Tv-hifi Kern",
    "wof:placetype":"venue"
},
  "geometry": {"coordinates":[12.1021461487,49.0215110779],"type":"Point"}
}