{
  "type": "Feature",
  "properties": {
    "iso:country":"DE",
    "sg:address":"Ludwig-Uhland-Str. 29",
    "sg:city":"Wolfhagen",
    "sg:phone":"+49 5692/2888",
    "sg:postcode":"34466",
    "sg:province":"Hessen",
    "wof:name":"Dr. Helmut Staub Tierarzt",
    "wof:placetype":"venue"
},
  "geometry": {"coordinates":[9.1794786453,51.3187561035],"type":"Point"}
}