{
  "type": "Feature",
  "properties": {
    "iso:country":"DE",
    "sg:address":"M\u00fcllroser Str. 7",
    "sg:city":"Eisenh\u00fcttenstadt",
    "sg:phone":"+49 3364/46739",
    "sg:postcode":"15890",
    "sg:province":"Brandenburg",
    "wof:name":"Renate Hoffmann",
    "wof:placetype":"venue"
},
  "geometry": {"coordinates":[14.6084918976,52.1557846069],"type":"Point"}
}