{
  "type": "Feature",
  "properties": {
    "iso:country":"DE",
    "sg:address":"Denkmalstr. 2",
    "sg:city":"Jemgum",
    "sg:phone":"+49 4958/475",
    "sg:postcode":"26844",
    "sg:province":"Niedersachsen",
    "wof:name":"Eberhardt Gottwald",
    "wof:placetype":"venue"
},
  "geometry": {"coordinates":[7.3730449677,53.2838821411],"type":"Point"}
}