{
  "type": "Feature",
  "properties": {
    "iso:country":"DE",
    "sg:address":"Alte Salzstr. 10",
    "sg:city":"Schnakenbek",
    "sg:postcode":"21481",
    "sg:province":"Schleswig-Holstein",
    "wof:name":"Gonsch Gmbh",
    "wof:placetype":"venue"
},
  "geometry": {"coordinates":[10.500164032,53.3854942322],"type":"Point"}
}