{
  "type": "Feature",
  "properties": {
    "iso:country":"DE",
    "sg:address":"Brunnenweg 2",
    "sg:city":"Mosbach",
    "sg:phone":"+49 6261/2193",
    "sg:postcode":"74821",
    "sg:province":"Baden-W\u00fcrttemberg",
    "wof:name":"Albert Flicker Elektroinstallation",
    "wof:placetype":"venue"
},
  "geometry": {"coordinates":[9.13773,49.399639],"type":"Point"}
}