{
  "type": "Feature",
  "properties": {
    "iso:country":"DE",
    "sg:address":"Filder Str. 77",
    "sg:city":"Moers",
    "sg:phone":"+49 2841/26556",
    "sg:postcode":"47441",
    "sg:province":"Nordrhein-Westfalen",
    "wof:name":"Waltraud Otto Steuerberaterin",
    "wof:placetype":"venue"
},
  "geometry": {"coordinates":[6.6261467934,51.4443359375],"type":"Point"}
}