{
  "type": "Feature",
  "properties": {
    "iso:country":"DE",
    "sg:address":"Waldbachtal 8",
    "sg:city":"M\u00fclheim",
    "sg:phone":"+49 208/56025",
    "sg:postcode":"45481",
    "sg:province":"Nordrhein-Westfalen",
    "wof:name":"Pmb Uli Baus Modevertriebsges. Mbh",
    "wof:placetype":"venue"
},
  "geometry": {"coordinates":[6.8492598534,51.4033088684],"type":"Point"}
}