{
  "type": "Feature",
  "properties": {
    "iso:country":"DE",
    "sg:address":"Parkstr. 14",
    "sg:city":"Schmitten",
    "sg:phone":"+49 6084/2836",
    "sg:postcode":"61389",
    "sg:province":"Hessen",
    "wof:name":"Max Mieger",
    "wof:placetype":"venue"
},
  "geometry": {"coordinates":[8.4409198761,50.2720184326],"type":"Point"}
}