{
  "type": "Feature",
  "properties": {
    "iso:country":"DE",
    "sg:address":"Waltershofer Str. 11 -15",
    "sg:city":"Gottenheim",
    "sg:phone":"+49 7665/969690",
    "sg:postcode":"79288",
    "sg:province":"Baden-W\u00fcrttemberg",
    "wof:name":"H. Meier Gmbh",
    "wof:placetype":"venue"
},
  "geometry": {"coordinates":[7.7273302078,48.0499801636],"type":"Point"}
}