{
  "type": "Feature",
  "properties": {
    "iso:country":"DE",
    "sg:address":"Dobelweg 1",
    "sg:city":"Blumberg",
    "sg:phone":"+49 7702/1392",
    "sg:postcode":"78176",
    "sg:province":"Baden-W\u00fcrttemberg",
    "wof:name":"Rudolf Hewer",
    "wof:placetype":"venue"
},
  "geometry": {"coordinates":[8.5269136429,47.8429222107],"type":"Point"}
}