{
  "type": "Feature",
  "properties": {
    "iso:country":"DE",
    "sg:address":"Friedlandstr. 54",
    "sg:city":"Amberg",
    "sg:phone":"+49 9621/21620",
    "sg:postcode":"92224",
    "sg:province":"Bayern",
    "wof:name":"Verena Thumm Rechtsanw\u00e4ltin",
    "wof:placetype":"venue"
},
  "geometry": {"coordinates":[11.888551712,49.4498443604],"type":"Point"}
}