{
  "type": "Feature",
  "properties": {
    "iso:country":"DE",
    "sg:address":"Schillerstr. 39",
    "sg:city":"Coswig",
    "sg:phone":"+49 3523/68242",
    "sg:postcode":"01640",
    "sg:province":"Sachsen",
    "wof:name":"Stefan Und H.-l. B\u00f6hme",
    "wof:placetype":"venue"
},
  "geometry": {"coordinates":[13.5780601501,51.1330451965],"type":"Point"}
}