{
  "type": "Feature",
  "properties": {
    "iso:country":"DE",
    "sg:address":"Papenhuder Str. 32",
    "sg:city":"Hamburg",
    "sg:phone":"+49 40/2270939",
    "sg:postcode":"22087",
    "sg:province":"Hamburg",
    "wof:name":"R & J B\u00fcrogestaltung Gmbh",
    "wof:placetype":"venue"
},
  "geometry": {"coordinates":[10.0192422867,53.5670661926],"type":"Point"}
}