{
  "type": "Feature",
  "properties": {
    "iso:country":"DE",
    "sg:address":"Sachsenstr. 1",
    "sg:city":"Neuwied",
    "sg:phone":"+49 2631/52469",
    "sg:postcode":"56567",
    "sg:province":"Rheinland-Pfalz",
    "wof:name":"M. Vetter",
    "wof:placetype":"venue"
},
  "geometry": {"coordinates":[7.4881272316,50.4612350464],"type":"Point"}
}