{
  "type": "Feature",
  "properties": {
    "iso:country":"DE",
    "sg:address":"Lisztstr. 7",
    "sg:city":"Bayreuth",
    "sg:phone":"+49 921/66104",
    "sg:postcode":"95444",
    "sg:province":"Bayern",
    "wof:name":"Egon Hofmann Architekt",
    "wof:placetype":"venue"
},
  "geometry": {"coordinates":[11.58421,49.939953],"type":"Point"}
}