{
  "type": "Feature",
  "properties": {
    "iso:country":"DE",
    "sg:address":"Albertstr. 20",
    "sg:city":"Markneukirchen",
    "sg:phone":"+49 37422/3579",
    "sg:postcode":"08258",
    "sg:province":"Sachsen",
    "wof:name":"Harald Kohlmann",
    "wof:placetype":"venue"
},
  "geometry": {"coordinates":[12.3252220154,50.3124732971],"type":"Point"}
}