{
  "type": "Feature",
  "properties": {
    "iso:country":"DE",
    "sg:address":"Marktplatz 12",
    "sg:city":"Lam",
    "sg:postcode":"93462",
    "sg:province":"Bayern",
    "wof:name":"Krankenpflegeverband Lamer Winkel",
    "wof:placetype":"venue"
},
  "geometry": {"coordinates":[13.049469,49.197472],"type":"Point"}
}