{
  "type": "Feature",
  "properties": {
    "iso:country":"DE",
    "sg:address":"Im Granetal 19",
    "sg:city":"Langelsheim",
    "sg:phone":"+49 5326/86639",
    "sg:postcode":"38685",
    "sg:province":"Niedersachsen",
    "wof:name":"Gr\u00e4tz",
    "wof:placetype":"venue"
},
  "geometry": {"coordinates":[10.380414,51.913509],"type":"Point"}
}