{
  "type": "Feature",
  "properties": {
    "iso:country":"DE",
    "sg:address":"Bremer Str. 99",
    "sg:city":"Stuhr",
    "sg:phone":"+49 421/870054",
    "sg:postcode":"28816",
    "sg:province":"Niedersachsen",
    "wof:name":"Mercator Druck Verlag Gmbh & Co. Kg",
    "wof:placetype":"venue"
},
  "geometry": {"coordinates":[8.786793,52.996838],"type":"Point"}
}