{
  "type": "Feature",
  "properties": {
    "iso:country":"DE",
    "sg:address":"Hauptstr. 31",
    "sg:city":"Ruhpolding",
    "sg:phone":"+49 8663/9878",
    "sg:postcode":"83324",
    "sg:province":"Bayern",
    "wof:name":"Unternbergbahn Gmbh",
    "wof:placetype":"venue"
},
  "geometry": {"coordinates":[12.6446943283,47.7643432617],"type":"Point"}
}