{
  "type": "Feature",
  "properties": {
    "iso:country":"DE",
    "sg:address":"St. Florianstr. 5",
    "sg:city":"Steinfeld",
    "sg:phone":"+49 5492/1289",
    "sg:postcode":"49439",
    "sg:province":"Niedersachsen",
    "wof:name":"Rolfsen Bau Gmbh",
    "wof:placetype":"venue"
},
  "geometry": {"coordinates":[8.198542,52.585812],"type":"Point"}
}