{
  "type": "Feature",
  "properties": {
    "iso:country":"DE",
    "sg:address":"Lutterh\u00e4user Stra\u00dfe 4",
    "sg:city":"Moringen",
    "sg:phone":"+49 5554/9959161",
    "sg:postcode":"37186",
    "sg:province":"Niedersachsen",
    "wof:name":"P-concept Ihr Netzwerkpartner",
    "wof:placetype":"venue"
},
  "geometry": {"coordinates":[9.870934,51.702965],"type":"Point"}
}