{
  "type": "Feature",
  "properties": {
    "iso:country":"DE",
    "sg:address":"Poststr. 40",
    "sg:city":"B\u00f6blingen",
    "sg:phone":"+49 7031/234887",
    "sg:postcode":"71032",
    "sg:province":"Baden-W\u00fcrttemberg",
    "wof:name":"G\u00fcnter B\u00e4chle",
    "wof:placetype":"venue"
},
  "geometry": {"coordinates":[9.0140972137,48.6842842102],"type":"Point"}
}