{
  "type": "Feature",
  "properties": {
    "iso:country":"DE",
    "sg:address":"Hauptstr. 20",
    "sg:city":"Luhe-Wildenau",
    "sg:phone":"+49 9607/1414",
    "sg:postcode":"92706",
    "sg:province":"Bayern",
    "wof:name":"Georg Schmidt",
    "wof:placetype":"venue"
},
  "geometry": {"coordinates":[12.1231203079,49.5975227356],"type":"Point"}
}