{
  "type": "Feature",
  "properties": {
    "iso:country":"DE",
    "sg:address":"Hauptstr. 3",
    "sg:city":"Harschbach",
    "sg:phone":"+49 2684/4261",
    "sg:postcode":"56307",
    "sg:province":"Rheinland-Pfalz",
    "wof:name":"R\u00fcdiger Noll",
    "wof:placetype":"venue"
},
  "geometry": {"coordinates":[7.589948,50.573738],"type":"Point"}
}