{
  "type": "Feature",
  "properties": {
    "iso:country":"DE",
    "sg:address":"Brinkstr. 4",
    "sg:city":"Petershagen",
    "sg:phone":"+49 5707/727",
    "sg:postcode":"32469",
    "sg:province":"Nordrhein-Westfalen",
    "wof:name":"Karo As Alt- Und Abfallstoffe",
    "wof:placetype":"venue"
},
  "geometry": {"coordinates":[8.970885,52.417526],"type":"Point"}
}