{
  "type": "Feature",
  "properties": {
    "iso:country":"DE",
    "sg:address":"Zum Hagelkreuz 22",
    "sg:city":"Eschweiler",
    "sg:phone":"+49 2403/9910",
    "sg:postcode":"52249",
    "sg:province":"Nordrhein-Westfalen",
    "wof:name":"Mva Weisweiler Verwaltungs-gmbh",
    "wof:placetype":"venue"
},
  "geometry": {"coordinates":[6.3017401695,50.845451355],"type":"Point"}
}