{
  "type": "Feature",
  "properties": {
    "iso:country":"DE",
    "sg:address":"Kaiser-Wilhelm-Str. 60",
    "sg:city":"Ludwigshafen",
    "sg:phone":"+49 621/515051",
    "sg:postcode":"67059",
    "sg:province":"Rheinland-Pfalz",
    "wof:name":"Barth H\u00fcbner Lelle Ingenieur Gmbh",
    "wof:placetype":"venue"
},
  "geometry": {"coordinates":[8.4427947998,49.4787902832],"type":"Point"}
}