{
  "type": "Feature",
  "properties": {
    "iso:country":"DE",
    "sg:address":"Karolingerstr. 72",
    "sg:city":"Andernach",
    "sg:phone":"+49 2632/43470",
    "sg:postcode":"56626",
    "sg:province":"Rheinland-Pfalz",
    "wof:name":"Theodor Loef Ohg",
    "wof:placetype":"venue"
},
  "geometry": {"coordinates":[7.411536,50.436703],"type":"Point"}
}