{
  "type": "Feature",
  "properties": {
    "iso:country":"DE",
    "sg:address":"Tungerloh-Pr\u00f6bsting 10",
    "sg:city":"Gescher",
    "sg:phone":"+49 2542/98260",
    "sg:postcode":"48712",
    "sg:province":"Nordrhein-Westfalen",
    "wof:name":"Sis Gmbh",
    "wof:placetype":"venue"
},
  "geometry": {"coordinates":[7.041052,51.938992],"type":"Point"}
}