{
  "type": "Feature",
  "properties": {
    "iso:country":"DE",
    "sg:address":"Uhlandstr. 6 a",
    "sg:city":"Hamburg",
    "sg:phone":"+49 40/2200899",
    "sg:postcode":"22087",
    "sg:province":"Hamburg",
    "wof:name":"Deko-service Stender Kg",
    "wof:placetype":"venue"
},
  "geometry": {"coordinates":[10.025336,53.565048],"type":"Point"}
}