{
  "type": "Feature",
  "properties": {
    "iso:country":"DE",
    "sg:address":"Kohlbergstr. 16",
    "sg:city":"Bonn",
    "sg:phone":"+49 228/9483500",
    "sg:postcode":"53229",
    "sg:province":"Nordrhein-Westfalen",
    "wof:name":"Fff Unit Ges. F\u00fcr Konzept Und Produktion In Film Funk Und",
    "wof:placetype":"venue"
},
  "geometry": {"coordinates":[7.1926307678,50.7409133911],"type":"Point"}
}