{
  "type": "Feature",
  "properties": {
    "iso:country":"DE",
    "sg:address":"Luxemburger Str. 15",
    "sg:city":"Erftstadt",
    "sg:phone":"+49 2235/74784",
    "sg:postcode":"50374",
    "sg:province":"Nordrhein-Westfalen",
    "wof:name":"Haus Dominik",
    "wof:placetype":"venue"
},
  "geometry": {"coordinates":[6.7263698578,50.7691307068],"type":"Point"}
}