{
  "type": "Feature",
  "properties": {
    "iso:country":"DE",
    "sg:address":"Am Heyerberg 1",
    "sg:city":"Koblenz",
    "sg:phone":"+49 261/4030876",
    "sg:postcode":"56072",
    "sg:province":"Rheinland-Pfalz",
    "wof:name":"Fr\u00f6hlich Geb\u00e4ude- Management Gmbh",
    "wof:placetype":"venue"
},
  "geometry": {"coordinates":[7.547038,50.345467],"type":"Point"}
}