{
  "type": "Feature",
  "properties": {
    "iso:country":"DE",
    "sg:address":"Karolinenstr. 17",
    "sg:city":"F\u00fcrth",
    "sg:phone":"+49 911/773832",
    "sg:postcode":"90763",
    "sg:province":"Bayern",
    "wof:name":"Kinderwagen-hammer",
    "wof:placetype":"venue"
},
  "geometry": {"coordinates":[10.9867887497,49.4701843262],"type":"Point"}
}