{
  "type": "Feature",
  "properties": {
    "iso:country":"DE",
    "sg:address":"Alsenstr. 41",
    "sg:city":"L\u00fcnen",
    "sg:phone":"+49 2306/4527",
    "sg:postcode":"44532",
    "sg:province":"Nordrhein-Westfalen",
    "wof:name":"Weiss Architektengruppe L\u00fcnen",
    "wof:placetype":"venue"
},
  "geometry": {"coordinates":[7.535983,51.587364],"type":"Point"}
}