{
  "type": "Feature",
  "properties": {
    "iso:country":"DE",
    "sg:address":"Schutterstr. 20",
    "sg:city":"Neuried",
    "sg:phone":"+49 7807/759",
    "sg:postcode":"77743",
    "sg:province":"Baden-W\u00fcrttemberg",
    "wof:name":"Ortenauer Gmbh",
    "wof:placetype":"venue"
},
  "geometry": {"coordinates":[7.8380098343,48.4704742432],"type":"Point"}
}