{
  "type": "Feature",
  "properties": {
    "iso:country":"DE",
    "sg:address":"Eisenbahnstr. 12a",
    "sg:city":"Dreieich",
    "sg:phone":"+49 6103/61830",
    "sg:postcode":"63303",
    "sg:province":"Hessen",
    "wof:name":"D. Cordier",
    "wof:placetype":"venue"
},
  "geometry": {"coordinates":[8.693775,50.0173],"type":"Point"}
}