{
  "type": "Feature",
  "properties": {
    "iso:country":"DE",
    "sg:address":"Postfach 1270",
    "sg:city":"Bad Bevensen",
    "sg:phone":"+49 5821/7014",
    "sg:postcode":"29543",
    "sg:province":"Niedersachsen",
    "wof:name":"B\u00fcnde Parkettverleger",
    "wof:placetype":"venue"
},
  "geometry": {"coordinates":[10.5905036926,53.0792922974],"type":"Point"}
}