{
  "type": "Feature",
  "properties": {
    "iso:country":"DE",
    "sg:address":"Am Lehmteich 4",
    "sg:city":"Oelsnitz",
    "sg:phone":"+49 4937/4214600",
    "sg:postcode":"08606",
    "sg:province":"Sachsen",
    "wof:name":"Tul-tec Gmbh Isdn 460-0",
    "wof:placetype":"venue"
},
  "geometry": {"coordinates":[12.1913614273,50.4344749451],"type":"Point"}
}