{
  "type": "Feature",
  "properties": {
    "iso:country":"DE",
    "sg:address":"Kanalstr. 48",
    "sg:city":"Fulda",
    "sg:phone":"+49 661/73725",
    "sg:postcode":"36037",
    "sg:province":"Hessen",
    "wof:name":"H. Rauscher",
    "wof:placetype":"venue"
},
  "geometry": {"coordinates":[9.675578,50.549873],"type":"Point"}
}