{
  "type": "Feature",
  "properties": {
    "iso:country":"DE",
    "sg:address":"Bornweg 1",
    "sg:city":"Dassendorf",
    "sg:postcode":"21521",
    "sg:province":"Schleswig-Holstein",
    "wof:name":"Dosen-matz",
    "wof:placetype":"venue"
},
  "geometry": {"coordinates":[10.3507919312,53.4940414429],"type":"Point"}
}