{
  "type": "Feature",
  "properties": {
    "iso:country":"DE",
    "sg:address":"M\u00fcller-Breslau-Str. 28",
    "sg:city":"Essen",
    "sg:phone":"+49 201/266633",
    "sg:postcode":"45130",
    "sg:province":"Nordrhein-Westfalen",
    "wof:name":"Ewald & Fischer Gmbh",
    "wof:placetype":"venue"
},
  "geometry": {"coordinates":[7.017108,51.434761],"type":"Point"}
}