{
  "type": "Feature",
  "properties": {
    "iso:country":"DE",
    "sg:address":"Bahnhofstr. 24",
    "sg:city":"Garmisch-Partenkirchen",
    "sg:phone":"+49 8821/2254",
    "sg:postcode":"82467",
    "sg:province":"Bayern",
    "wof:name":"Restaurant El-greco",
    "wof:placetype":"venue"
},
  "geometry": {"coordinates":[11.0996341705,47.4919967651],"type":"Point"}
}