{
  "type": "Feature",
  "properties": {
    "iso:country":"DE",
    "sg:address":"Eckernf\u00f6rder Str. 259",
    "sg:city":"Kronshagen",
    "sg:phone":"+49 431/5459504",
    "sg:postcode":"24119",
    "sg:province":"Schleswig-Holstein",
    "wof:name":"K\u00f6rner Verlag Gmbh",
    "wof:placetype":"venue"
},
  "geometry": {"coordinates":[10.1021366119,54.3408737183],"type":"Point"}
}