{
  "type": "Feature",
  "properties": {
    "iso:country":"DE",
    "sg:address":"Weg beim J\u00e4ger 218",
    "sg:city":"Hamburg",
    "sg:phone":"+49 40/363641",
    "sg:postcode":"22335",
    "sg:province":"Hamburg",
    "wof:name":"L.w.t. Interworld Transport Gmbh",
    "wof:placetype":"venue"
},
  "geometry": {"coordinates":[10.0086450577,53.6232261658],"type":"Point"}
}