{
  "type": "Feature",
  "properties": {
    "iso:country":"DE",
    "sg:address":"Gr\u00f6ppersgasse 2",
    "sg:city":"K\u00f6ln",
    "sg:phone":"+49 221/865295",
    "sg:postcode":"51107",
    "sg:province":"Nordrhein-Westfalen",
    "wof:name":"D. Senerath Masseur",
    "wof:placetype":"venue"
},
  "geometry": {"coordinates":[7.089702,50.922634],"type":"Point"}
}