{
  "type": "Feature",
  "properties": {
    "iso:country":"DE",
    "sg:address":"Nachtigallenweg 5",
    "sg:city":"Brandis",
    "sg:phone":"+49 34292/73644",
    "sg:postcode":"04821",
    "sg:province":"Sachsen",
    "wof:name":"K. Barthel",
    "wof:placetype":"venue"
},
  "geometry": {"coordinates":[12.59827,51.320141],"type":"Point"}
}