{
  "type": "Feature",
  "properties": {
    "iso:country":"DE",
    "sg:address":"Weinbergstr. 11",
    "sg:city":"Kamenz",
    "sg:phone":"+49 35783/04355",
    "sg:postcode":"01917",
    "sg:province":"Sachsen",
    "wof:name":"Hans Demski",
    "wof:placetype":"venue"
},
  "geometry": {"coordinates":[14.093837738,51.2759094238],"type":"Point"}
}