{
  "type": "Feature",
  "properties": {
    "iso:country":"DE",
    "sg:address":"Stiftstr. 19",
    "sg:city":"Laubach",
    "sg:postcode":"35321",
    "sg:province":"Hessen",
    "wof:name":"Laubacher Stift Service Gmbh",
    "wof:placetype":"venue"
},
  "geometry": {"coordinates":[8.9943599701,50.542339325],"type":"Point"}
}