{
  "type": "Feature",
  "properties": {
    "iso:country":"DE",
    "sg:address":"Ooser Karlstr. 14",
    "sg:city":"Baden-Baden",
    "sg:phone":"+49 7221/17015",
    "sg:postcode":"76532",
    "sg:province":"Baden-W\u00fcrttemberg",
    "wof:name":"W. Mu\u00dfler",
    "wof:placetype":"venue"
},
  "geometry": {"coordinates":[8.191023,48.788094],"type":"Point"}
}