{
  "type": "Feature",
  "properties": {
    "iso:country":"DE",
    "sg:address":"Richard-Wagner-Str. 56",
    "sg:city":"Bayreuth",
    "sg:phone":"+49 921/64789",
    "sg:postcode":"95444",
    "sg:province":"Bayern",
    "wof:name":"Haushaltswaren Und Geschenkartikel",
    "wof:placetype":"venue"
},
  "geometry": {"coordinates":[11.5846290588,49.940700531],"type":"Point"}
}