{
  "type": "Feature",
  "properties": {
    "iso:country":"DE",
    "sg:address":"Alleestr. 28",
    "sg:city":"Remscheid",
    "sg:phone":"+49 2191/24821",
    "sg:postcode":"42853",
    "sg:province":"Nordrhein-Westfalen",
    "wof:name":"Metropol 14",
    "wof:placetype":"venue"
},
  "geometry": {"coordinates":[7.192059,51.180447],"type":"Point"}
}