{
  "type": "Feature",
  "properties": {
    "iso:country":"DE",
    "sg:address":"Poststr. 24",
    "sg:city":"Ochsenhausen",
    "sg:phone":"+49 7352/1242",
    "sg:postcode":"88416",
    "sg:province":"Baden-W\u00fcrttemberg",
    "wof:name":"Pizzeria-restaurant Zur Alten Post",
    "wof:placetype":"venue"
},
  "geometry": {"coordinates":[9.9520292282,48.0720901489],"type":"Point"}
}