{
  "type": "Feature",
  "properties": {
    "iso:country":"DE",
    "sg:address":"Kaiserstr. 83",
    "sg:city":"Friedberg",
    "sg:phone":"+49 6031/692448",
    "sg:postcode":"61169",
    "sg:province":"Hessen",
    "wof:name":"Hydrophil Dosiertechnik Gmbh",
    "wof:placetype":"venue"
},
  "geometry": {"coordinates":[8.7535,50.336987],"type":"Point"}
}