{
  "type": "Feature",
  "properties": {
    "iso:country":"DE",
    "sg:address":"Industriestr. 14",
    "sg:city":"F\u00fcrth",
    "sg:postcode":"90765",
    "sg:province":"Bayern",
    "wof:name":"Helmut Hufer Kg",
    "wof:placetype":"venue"
},
  "geometry": {"coordinates":[11.0021629333,49.5115585327],"type":"Point"}
}