{
  "type": "Feature",
  "properties": {
    "iso:country":"DE",
    "sg:address":"Andreas-Hofer-Str. 41",
    "sg:city":"Meckenbeuren",
    "sg:phone":"+49 7542/2796",
    "sg:postcode":"88074",
    "sg:province":"Baden-W\u00fcrttemberg",
    "wof:name":"Max Keckeisen",
    "wof:placetype":"venue"
},
  "geometry": {"coordinates":[9.549271,47.705399],"type":"Point"}
}