{
  "type": "Feature",
  "properties": {
    "iso:country":"DE",
    "sg:address":"Grabenstr. 2",
    "sg:city":"Bad Lauterberg",
    "sg:phone":"+49 5524/3507",
    "sg:postcode":"37431",
    "sg:province":"Niedersachsen",
    "wof:name":"Helmut Dreymann",
    "wof:placetype":"venue"
},
  "geometry": {"coordinates":[10.4166269302,51.6217727661],"type":"Point"}
}