{
  "type": "Feature",
  "properties": {
    "iso:country":"DE",
    "sg:address":"M\u00fcnchner Stra\u00dfe 18",
    "sg:city":"Holzkirchen",
    "sg:phone":"+49 8024/6290",
    "sg:postcode":"83607",
    "sg:province":"Bayern",
    "wof:name":"Restaurant Oberland",
    "wof:placetype":"venue"
},
  "geometry": {"coordinates":[11.6997051239,47.8797531128],"type":"Point"}
}