{
  "type": "Feature",
  "properties": {
    "iso:country":"DE",
    "sg:address":"Schulerstr. 20",
    "sg:city":"Pforzheim",
    "sg:phone":"+49 7231/75131",
    "sg:postcode":"75180",
    "sg:province":"Baden-W\u00fcrttemberg",
    "wof:name":"Hans Rupp",
    "wof:placetype":"venue"
},
  "geometry": {"coordinates":[8.6679439545,48.856880188],"type":"Point"}
}