{
  "type": "Feature",
  "properties": {
    "iso:country":"DE",
    "sg:city":"Mering",
    "sg:phone":"+49 8233/9481",
    "sg:postcode":"86415",
    "sg:province":"Bayern",
    "wof:name":"Meditation Und Bewegung",
    "wof:placetype":"venue"
},
  "geometry": {"coordinates":[10.986428,48.26688],"type":"Point"}
}