{
  "type": "Feature",
  "properties": {
    "iso:country":"DE",
    "sg:address":"Herkenkrug 13",
    "sg:city":"Hamburg",
    "sg:phone":"+49 40/6010981",
    "sg:postcode":"22359",
    "sg:province":"Hamburg",
    "wof:name":"Erich Moll Anlageberater",
    "wof:placetype":"venue"
},
  "geometry": {"coordinates":[10.1819286346,53.6441726685],"type":"Point"}
}