{
  "type": "Feature",
  "properties": {
    "iso:country":"DE",
    "sg:address":"Tj\u00fccher Kolken 5",
    "sg:city":"Ihrhove",
    "sg:phone":"+49 4955/923500",
    "sg:postcode":"26810",
    "sg:province":"Niedersachsen",
    "wof:name":"Lamptronic International Gmbh & Co Kg",
    "wof:placetype":"venue"
},
  "geometry": {"coordinates":[7.448928,53.163536],"type":"Point"}
}