{
  "type": "Feature",
  "properties": {
    "iso:country":"DE",
    "sg:address":"Velener Str. 17",
    "sg:city":"Heiden",
    "sg:phone":"+49 2867/97171",
    "sg:postcode":"46359",
    "sg:province":"Nordrhein-Westfalen",
    "wof:name":"Nienhoff Und Schulte-repel Augenoptiker",
    "wof:placetype":"venue"
},
  "geometry": {"coordinates":[6.9325489998,51.8278121948],"type":"Point"}
}