{
  "type": "Feature",
  "properties": {
    "iso:country":"DE",
    "sg:address":"Erfurter Str.",
    "sg:city":"Kranichfeld",
    "sg:phone":"+49 36450/42276",
    "sg:postcode":"99448",
    "sg:province":"Th\u00fcringen",
    "wof:name":"Freibad",
    "wof:placetype":"venue"
},
  "geometry": {"coordinates":[11.2058238983,50.8593597412],"type":"Point"}
}