{
  "type": "Feature",
  "properties": {
    "iso:country":"DE",
    "sg:address":"Oberhausener Str 8",
    "sg:city":"Wilnsdorf",
    "sg:phone":"+49 2739/8700321",
    "sg:postcode":"57234",
    "sg:province":"Nordrhein-Westfalen",
    "wof:name":"Ap & T Automation, Pressen & Werkzeuge Vertriebs-gmbh",
    "wof:placetype":"venue"
},
  "geometry": {"coordinates":[8.106935,50.818027],"type":"Point"}
}