{
  "type": "Feature",
  "properties": {
    "iso:country":"DE",
    "sg:address":"Heimerdinger Str. 13/1",
    "sg:city":"Ditzingen",
    "sg:phone":"+49 7156/31180",
    "sg:postcode":"71254",
    "sg:province":"Baden-W\u00fcrttemberg",
    "wof:name":"Ev. Pfarramt",
    "wof:placetype":"venue"
},
  "geometry": {"coordinates":[9.0369520187,48.8376312256],"type":"Point"}
}