{
  "type": "Feature",
  "properties": {
    "iso:country":"DE",
    "sg:address":"Bachstr. 15a",
    "sg:city":"Ibbenb\u00fcren",
    "sg:postcode":"49477",
    "sg:province":"Nordrhein-Westfalen",
    "wof:name":"Hermann Engbrink",
    "wof:placetype":"venue"
},
  "geometry": {"coordinates":[7.7133188248,52.2725448608],"type":"Point"}
}