{
  "type": "Feature",
  "properties": {
    "iso:country":"DE",
    "sg:address":"Rosenheimer Str. 14",
    "sg:city":"Brannenburg",
    "sg:phone":"+49 8034/8654",
    "sg:postcode":"83098",
    "sg:province":"Bayern",
    "wof:name":"Christian Hauser",
    "wof:placetype":"venue"
},
  "geometry": {"coordinates":[12.107566,47.735115],"type":"Point"}
}