{
  "type": "Feature",
  "properties": {
    "iso:country":"DE",
    "sg:address":"Lange Str. 55",
    "sg:city":"Cloppenburg",
    "sg:phone":"+49 4471/6326",
    "sg:postcode":"49661",
    "sg:province":"Niedersachsen",
    "wof:name":"August Kruck",
    "wof:placetype":"venue"
},
  "geometry": {"coordinates":[8.0385246277,52.8444099426],"type":"Point"}
}