{
  "type": "Feature",
  "properties": {
    "iso:country":"DE",
    "sg:address":"Sanders Weg 69",
    "sg:city":"Stade",
    "sg:phone":"+49 4141/62906",
    "sg:postcode":"21680",
    "sg:province":"Niedersachsen",
    "wof:name":"Ev. Pfarramt Ii Johannis-gemeinde",
    "wof:placetype":"venue"
},
  "geometry": {"coordinates":[9.4666261673,53.5857658386],"type":"Point"}
}