{
  "type": "Feature",
  "properties": {
    "iso:country":"DE",
    "sg:address":"M\u00fchlenhof 5-9",
    "sg:city":"Hilden",
    "sg:phone":"+49 2103/89000",
    "sg:postcode":"40721",
    "sg:province":"Nordrhein-Westfalen",
    "wof:name":"Bf-bau Gmbh",
    "wof:placetype":"venue"
},
  "geometry": {"coordinates":[6.9421730042,51.1702270508],"type":"Point"}
}