{
  "type": "Feature",
  "properties": {
    "iso:country":"DE",
    "sg:address":"Vor den B\u00fcschen",
    "sg:city":"Marl",
    "sg:postcode":"45770",
    "sg:province":"Nordrhein-Westfalen",
    "wof:name":"Jostmeyer Gmbh",
    "wof:placetype":"venue"
},
  "geometry": {"coordinates":[7.16378,51.667641],"type":"Point"}
}