{
  "type": "Feature",
  "properties": {
    "iso:country":"DE",
    "sg:address":"Finkenbergweg 9",
    "sg:city":"Sebnitz",
    "sg:phone":"+49 35971/56385",
    "sg:postcode":"01855",
    "sg:province":"Sachsen",
    "wof:name":"G\u00fcnter Pflicke",
    "wof:placetype":"venue"
},
  "geometry": {"coordinates":[14.2736902237,50.9789237976],"type":"Point"}
}