{
  "type": "Feature",
  "properties": {
    "iso:country":"DE",
    "sg:address":"Gro\u00dfenschwand 31",
    "sg:city":"T\u00e4nnesberg",
    "sg:phone":"+49 9655/1554",
    "sg:postcode":"92723",
    "sg:province":"Bayern",
    "wof:name":"J. Liebl Mineral\u00f6l",
    "wof:placetype":"venue"
},
  "geometry": {"coordinates":[12.300696373,49.5456924438],"type":"Point"}
}