{
  "type": "Feature",
  "properties": {
    "iso:country":"DE",
    "sg:address":"Waidweg 8",
    "sg:city":"Bad Langensalza",
    "sg:postcode":"99947",
    "sg:province":"Th\u00fcringen",
    "wof:name":"Otto Maier",
    "wof:placetype":"venue"
},
  "geometry": {"coordinates":[10.6409158707,51.1109199524],"type":"Point"}
}