{
  "type": "Feature",
  "properties": {
    "iso:country":"DE",
    "sg:address":"Buchheimer Str. 53-55",
    "sg:city":"K\u00f6ln",
    "sg:phone":"+49 221/614335",
    "sg:postcode":"51063",
    "sg:province":"Nordrhein-Westfalen",
    "wof:name":"I. Schoaei",
    "wof:placetype":"venue"
},
  "geometry": {"coordinates":[7.0034170151,50.9626159668],"type":"Point"}
}