{
  "type": "Feature",
  "properties": {
    "iso:country":"DE",
    "sg:address":"Mittlere Kanalstr. 1",
    "sg:city":"N\u00fcrnberg",
    "sg:phone":"+49 911/267117",
    "sg:postcode":"90429",
    "sg:province":"Bayern",
    "wof:name":"Marga Kaib",
    "wof:placetype":"venue"
},
  "geometry": {"coordinates":[11.0579710007,49.4496841431],"type":"Point"}
}