{
  "type": "Feature",
  "properties": {
    "iso:country":"DE",
    "sg:address":"Siemensstr. 9a",
    "sg:city":"Ottobrunn",
    "sg:phone":"+49 89/6092084",
    "sg:postcode":"85521",
    "sg:province":"Bayern",
    "wof:name":"Caesar Collection Gmbh",
    "wof:placetype":"venue"
},
  "geometry": {"coordinates":[11.6510972977,48.0656814575],"type":"Point"}
}