{
  "type": "Feature",
  "properties": {
    "iso:country":"DE",
    "sg:address":"Eichenstr. 5",
    "sg:city":"Pfakofen",
    "sg:phone":"+49 9401/880299",
    "sg:postcode":"93101",
    "sg:province":"Bayern",
    "wof:name":"Atk Linde, Technischer Kundendienst",
    "wof:placetype":"venue"
},
  "geometry": {"coordinates":[12.220226,48.858582],"type":"Point"}
}