{
  "type": "Feature",
  "properties": {
    "iso:country":"DE",
    "sg:address":"Bahnhofstr 33",
    "sg:city":"Aschheim",
    "sg:phone":"+49 89/9455420",
    "sg:postcode":"85609",
    "sg:province":"Bayern",
    "wof:name":"R. Grossmann Gmbh",
    "wof:placetype":"venue"
},
  "geometry": {"coordinates":[11.680566,48.14476],"type":"Point"}
}