{
  "type": "Feature",
  "properties": {
    "iso:country":"DE",
    "sg:address":"Ludwig-Richter-Allee 18",
    "sg:city":"Radebeul",
    "sg:phone":"+49 351/8303729",
    "sg:postcode":"01445",
    "sg:province":"Sachsen",
    "wof:name":"Klaus Und H. R\u00fcdiger Steuerberater",
    "wof:placetype":"venue"
},
  "geometry": {"coordinates":[13.627986908,51.1112937927],"type":"Point"}
}