{
  "type": "Feature",
  "properties": {
    "iso:country":"DE",
    "sg:address":"Mainzer Stra\u00dfe 143",
    "sg:city":"Marbach",
    "sg:phone":"+49 4971/445987",
    "sg:postcode":"71672",
    "sg:province":"Baden-W\u00fcrttemberg",
    "wof:name":"Mediterranean Music School",
    "wof:placetype":"venue"
},
  "geometry": {"coordinates":[9.2536706924,48.9288101196],"type":"Point"}
}