{
  "type": "Feature",
  "properties": {
    "iso:country":"DE",
    "sg:address":"Hauptstr. 24",
    "sg:city":"Lorup",
    "sg:phone":"+49 4959/541207",
    "sg:postcode":"26901",
    "sg:province":"Niedersachsen",
    "wof:name":"Kreissparkasse Aschendorf-h\u00fcmm",
    "wof:placetype":"venue"
},
  "geometry": {"coordinates":[7.640172,52.925331],"type":"Point"}
}