{
  "type": "Feature",
  "properties": {
    "iso:country":"DE",
    "sg:address":"Osterfeldstr. 86 Haus D",
    "sg:city":"Ismaning",
    "sg:phone":"+49 89/206060",
    "sg:postcode":"85737",
    "sg:province":"Bayern",
    "wof:name":"Cross Worlds Software Gmbh",
    "wof:placetype":"venue"
},
  "geometry": {"coordinates":[11.6762800217,48.2272644043],"type":"Point"}
}