{
  "type": "Feature",
  "properties": {
    "iso:country":"DE",
    "sg:address":"Brabanter Str. 31",
    "sg:city":"Kassel",
    "sg:phone":"+49 561/39000",
    "sg:postcode":"34131",
    "sg:province":"Hessen",
    "wof:name":"G\u00fcnter Meyer Steuerbevollm\u00e4chtigter",
    "wof:placetype":"venue"
},
  "geometry": {"coordinates":[9.4208126068,51.309047699],"type":"Point"}
}