{
  "type": "Feature",
  "properties": {
    "iso:country":"DE",
    "sg:address":"Bayernstr. 20",
    "sg:city":"Regenstauf",
    "sg:postcode":"93128",
    "sg:province":"Bayern",
    "wof:name":"Reisberg Stuben",
    "wof:placetype":"venue"
},
  "geometry": {"coordinates":[12.1335000992,49.1154098511],"type":"Point"}
}