{
  "type": "Feature",
  "properties": {
    "iso:country":"DE",
    "sg:address":"Eichenweg 6",
    "sg:city":"Bad Zwischenahn",
    "sg:phone":"+49 4486/1213",
    "sg:postcode":"26160",
    "sg:province":"Niedersachsen",
    "wof:name":"Erwin Saul Inh. Frank Saul",
    "wof:placetype":"venue"
},
  "geometry": {"coordinates":[8.121919632,53.1415672302],"type":"Point"}
}