{
  "type": "Feature",
  "properties": {
    "iso:country":"DE",
    "sg:address":"Jahnstr. 6",
    "sg:city":"Kandel",
    "sg:phone":"+49 7275/2026",
    "sg:postcode":"76870",
    "sg:province":"Rheinland-Pfalz",
    "wof:name":"Manfred Bechberger Und Thomas Fl\u00f6rsch",
    "wof:placetype":"venue"
},
  "geometry": {"coordinates":[8.1971969604,49.0774879456],"type":"Point"}
}