{
  "type": "Feature",
  "properties": {
    "iso:country":"DE",
    "sg:address":"Schwabstr. 2",
    "sg:city":"Stuttgart",
    "sg:phone":"+49 711/616913",
    "sg:postcode":"70197",
    "sg:province":"Baden-W\u00fcrttemberg",
    "wof:name":"Manfred Breitsprecher",
    "wof:placetype":"venue"
},
  "geometry": {"coordinates":[9.1597,48.768269],"type":"Point"}
}