{
  "type": "Feature",
  "properties": {
    "iso:country":"DE",
    "sg:address":"Wilhelmstr. 10",
    "sg:city":"M\u00fcnchen",
    "sg:phone":"+49 89/3815860",
    "sg:postcode":"80801",
    "sg:province":"Bayern",
    "wof:name":"Hc Grundst\u00fccks Gmbh & Co. Untere Jakobermauer Kg",
    "wof:placetype":"venue"
},
  "geometry": {"coordinates":[11.5833206177,48.1599617004],"type":"Point"}
}