{
  "type": "Feature",
  "properties": {
    "iso:country":"DE",
    "sg:address":"Hochstr. 31",
    "sg:city":"T\u00f6nisvorst",
    "sg:phone":"+49 2151/790118",
    "sg:postcode":"47918",
    "sg:province":"Nordrhein-Westfalen",
    "wof:name":"Hans Troekes",
    "wof:placetype":"venue"
},
  "geometry": {"coordinates":[6.493444,51.321659],"type":"Point"}
}