{
  "type": "Feature",
  "properties": {
    "iso:country":"DE",
    "sg:address":"Ludwigsplatz 25",
    "sg:city":"N\u00fcrnberg",
    "sg:phone":"+49 911/24910",
    "sg:postcode":"90403",
    "sg:province":"Bayern",
    "wof:name":"C & A",
    "wof:placetype":"venue"
},
  "geometry": {"coordinates":[11.070406,49.450275],"type":"Point"}
}