{
  "type": "Feature",
  "properties": {
    "iso:country":"DE",
    "sg:address":"R\u00f6wekamps Damm 13 A",
    "sg:city":"Badbergen",
    "sg:phone":"+49 5431/2520",
    "sg:postcode":"49635",
    "sg:province":"Niedersachsen",
    "wof:name":"Ernst Gerberding",
    "wof:placetype":"venue"
},
  "geometry": {"coordinates":[7.89443,52.660488],"type":"Point"}
}