{
  "type": "Feature",
  "properties": {
    "iso:country":"DE",
    "sg:address":"Kursdorfer Str. 102",
    "sg:city":"Schkeuditz",
    "sg:phone":"+49 34204/64773",
    "sg:postcode":"04435",
    "sg:province":"Sachsen",
    "wof:name":"Ingeborg Schl\u00fcter",
    "wof:placetype":"venue"
},
  "geometry": {"coordinates":[12.2209482193,51.4061088562],"type":"Point"}
}