{
  "type": "Feature",
  "properties": {
    "iso:country":"DE",
    "sg:address":"Germaniastr. 18",
    "sg:city":"Berlin",
    "sg:postcode":"12099",
    "sg:province":"Berlin",
    "wof:name":"Seniorenresidenz Germaniabogen Schlangenbad Gmbh",
    "wof:placetype":"venue"
},
  "geometry": {"coordinates":[13.3973779678,52.4650764465],"type":"Point"}
}