{
  "type": "Feature",
  "properties": {
    "iso:country":"DE",
    "sg:address":"Gro\u00dfenheide 4",
    "sg:city":"Stemwede",
    "sg:phone":"+49 5745/2231",
    "sg:postcode":"32351",
    "sg:province":"Nordrhein-Westfalen",
    "wof:name":"Friedrich Menke",
    "wof:placetype":"venue"
},
  "geometry": {"coordinates":[8.482625,52.392345],"type":"Point"}
}