{
  "type": "Feature",
  "properties": {
    "iso:country":"DE",
    "sg:address":"Hauptstr. 53",
    "sg:city":"Rehlingen-Siersburg",
    "sg:phone":"+49 6835/2664",
    "sg:postcode":"66780",
    "sg:province":"Saarland",
    "wof:name":"Restaurant Alt Siersburg",
    "wof:placetype":"venue"
},
  "geometry": {"coordinates":[6.6650071144,49.3632316589],"type":"Point"}
}