{
  "type": "Feature",
  "properties": {
    "iso:country":"DE",
    "sg:address":"Silcherweg 6",
    "sg:city":"Pfinztal",
    "sg:phone":"+49 7240/1001",
    "sg:postcode":"76327",
    "sg:province":"Baden-W\u00fcrttemberg",
    "wof:name":"Mark Schnerr Rechtsanwalt",
    "wof:placetype":"venue"
},
  "geometry": {"coordinates":[8.5484981537,48.9883918762],"type":"Point"}
}