{
  "type": "Feature",
  "properties": {
    "iso:country":"DE",
    "sg:address":"Hauptstr. 71",
    "sg:city":"Havixbeck",
    "sg:phone":"+49 2507/4287",
    "sg:postcode":"48329",
    "sg:province":"Nordrhein-Westfalen",
    "wof:name":"Foto Aktuell-vertrieb Sabine Th\u00fcs Gmbh",
    "wof:placetype":"venue"
},
  "geometry": {"coordinates":[7.4130830765,51.9745330811],"type":"Point"}
}