{
  "type": "Feature",
  "properties": {
    "iso:country":"DE",
    "sg:address":"Weitlstr. 73",
    "sg:city":"M\u00fcnchen",
    "sg:phone":"+49 89/3131269",
    "sg:postcode":"80935",
    "sg:province":"Bayern",
    "wof:name":"Siegfried Fischer Architekt",
    "wof:placetype":"venue"
},
  "geometry": {"coordinates":[11.557202,48.208221],"type":"Point"}
}