{
  "type": "Feature",
  "properties": {
    "iso:country":"DE",
    "sg:address":"Sebastian-Bach-Str. 34",
    "sg:city":"Leipzig",
    "sg:postcode":"04109",
    "sg:province":"Sachsen",
    "wof:name":"Elektra",
    "wof:placetype":"venue"
},
  "geometry": {"coordinates":[12.3558225632,51.3345947266],"type":"Point"}
}