{
  "type": "Feature",
  "properties": {
    "iso:country":"DE",
    "sg:address":"Alt-Engelbostel 21",
    "sg:city":"Langenhagen",
    "sg:phone":"+49 511/782852",
    "sg:postcode":"30855",
    "sg:province":"Niedersachsen",
    "wof:name":"Heinrich Bruns",
    "wof:placetype":"venue"
},
  "geometry": {"coordinates":[9.64995,52.446812],"type":"Point"}
}