{
  "type": "Feature",
  "properties": {
    "iso:country":"DE",
    "sg:address":"Hechtg\u00e4\u00dfle 3",
    "sg:city":"Bahlingen",
    "sg:phone":"+49 7663/1748",
    "sg:postcode":"79353",
    "sg:province":"Baden-W\u00fcrttemberg",
    "wof:name":"Karl B\u00fcrkin",
    "wof:placetype":"venue"
},
  "geometry": {"coordinates":[7.73816,48.123646],"type":"Point"}
}