{
  "type": "Feature",
  "properties": {
    "iso:country":"DE",
    "sg:address":"Adelungstr. 17",
    "sg:city":"Darmstadt",
    "sg:postcode":"64283",
    "sg:province":"Hessen",
    "wof:name":"Bvg Immobilien Gmbh",
    "wof:placetype":"venue"
},
  "geometry": {"coordinates":[8.647897,49.870911],"type":"Point"}
}