{
  "type": "Feature",
  "properties": {
    "iso:country":"DE",
    "sg:address":"Bahnhofstr. 5",
    "sg:city":"Neuhausen",
    "sg:phone":"+49 37361/45615",
    "sg:postcode":"09544",
    "sg:province":"Sachsen",
    "wof:name":"Probierst\u00fcbl",
    "wof:placetype":"venue"
},
  "geometry": {"coordinates":[13.465511322,50.6745681763],"type":"Point"}
}