{
  "type": "Feature",
  "properties": {
    "iso:country":"DE",
    "sg:address":"M\u00f6ster Str. 23",
    "sg:city":"Dessau",
    "sg:phone":"+49 340/8581890",
    "sg:postcode":"06849",
    "sg:province":"Sachsen-Anhalt",
    "wof:name":"Walter Schnelle",
    "wof:placetype":"venue"
},
  "geometry": {"coordinates":[12.256799,51.793377],"type":"Point"}
}