{
  "type": "Feature",
  "properties": {
    "iso:country":"DE",
    "sg:address":"Kohfurth 7",
    "sg:city":"Norderstedt",
    "sg:phone":"+49 40/5232511",
    "sg:postcode":"22850",
    "sg:province":"Schleswig-Holstein",
    "wof:name":"Detlef Berghahn",
    "wof:placetype":"venue"
},
  "geometry": {"coordinates":[9.983866,53.687977],"type":"Point"}
}