{
  "type": "Feature",
  "properties": {
    "iso:country":"DE",
    "sg:address":"Landstr. 12",
    "sg:city":"Kreuztal",
    "sg:phone":"+49 2732/1836",
    "sg:postcode":"57223",
    "sg:province":"Nordrhein-Westfalen",
    "wof:name":"Mehlvertrieb Siegerland Gmbh",
    "wof:placetype":"venue"
},
  "geometry": {"coordinates":[7.981958,50.958405],"type":"Point"}
}