{
  "type": "Feature",
  "properties": {
    "iso:country":"DE",
    "sg:address":"Buchener Str. 41",
    "sg:city":"Walld\u00fcrn",
    "sg:phone":"+49 6282/1200",
    "sg:postcode":"74731",
    "sg:province":"Baden-W\u00fcrttemberg",
    "wof:name":"Autohaus Wild Gmbh",
    "wof:placetype":"venue"
},
  "geometry": {"coordinates":[9.3629484177,49.5670013428],"type":"Point"}
}