{
  "type": "Feature",
  "properties": {
    "iso:country":"DE",
    "sg:address":"Ohlendorfer Str. 78",
    "sg:city":"Hildesheim",
    "sg:phone":"+49 5121/516812",
    "sg:postcode":"31137",
    "sg:province":"Niedersachsen",
    "wof:name":"Br\u00fcckenst\u00fcbchen",
    "wof:placetype":"venue"
},
  "geometry": {"coordinates":[9.9175596237,52.1620407104],"type":"Point"}
}