{
  "type": "Feature",
  "properties": {
    "iso:country":"DE",
    "sg:address":"Hahnenfu\u00dfweg 5",
    "sg:city":"Stutensee",
    "sg:phone":"+49 7249/951600",
    "sg:postcode":"76297",
    "sg:province":"Baden-W\u00fcrttemberg",
    "wof:name":"Bauunternehmen Fetzner Gmbh",
    "wof:placetype":"venue"
},
  "geometry": {"coordinates":[8.503187,49.118824],"type":"Point"}
}