{
  "type": "Feature",
  "properties": {
    "iso:country":"DE",
    "sg:address":"Kotterheidberg 5",
    "sg:city":"Solingen",
    "sg:phone":"+49 212/815973",
    "sg:postcode":"42655",
    "sg:province":"Nordrhein-Westfalen",
    "wof:name":"Werner Staubes",
    "wof:placetype":"venue"
},
  "geometry": {"coordinates":[7.069042,51.167099],"type":"Point"}
}