{
  "type": "Feature",
  "properties": {
    "iso:country":"DE",
    "sg:address":"Hauptstr. 155 a",
    "sg:city":"Friedelsheim",
    "sg:phone":"+49 6322/68378",
    "sg:postcode":"67159",
    "sg:province":"Rheinland-Pfalz",
    "wof:name":"J. Und C. Umstadt",
    "wof:placetype":"venue"
},
  "geometry": {"coordinates":[8.230474,49.447811],"type":"Point"}
}