{
  "type": "Feature",
  "properties": {
    "iso:country":"DE",
    "sg:address":"Malerstr. 52a",
    "sg:city":"Bremen",
    "sg:phone":"+49 421/445566",
    "sg:postcode":"28207",
    "sg:province":"Bremen",
    "wof:name":"Rolf Schw\u00e4n",
    "wof:placetype":"venue"
},
  "geometry": {"coordinates":[8.871118,53.065655],"type":"Point"}
}