{
  "type": "Feature",
  "properties": {
    "iso:country":"DE",
    "sg:address":"Luitpoldstr. 54",
    "sg:city":"Erlangen",
    "sg:phone":"+49 9131/25326",
    "sg:postcode":"91052",
    "sg:province":"Bayern",
    "wof:name":"M\u00fcnchner Kindl",
    "wof:placetype":"venue"
},
  "geometry": {"coordinates":[11.0200386047,49.5969848633],"type":"Point"}
}