{
  "type": "Feature",
  "properties": {
    "iso:country":"DE",
    "sg:address":"Ledererstr 11",
    "sg:city":"Gauting",
    "sg:phone":"+49 89/8502655",
    "sg:postcode":"82131",
    "sg:province":"Bayern",
    "wof:name":"Benson Gmbh",
    "wof:placetype":"venue"
},
  "geometry": {"coordinates":[11.3852071762,48.0678672791],"type":"Point"}
}