{
  "type": "Feature",
  "properties": {
    "iso:country":"DE",
    "sg:address":"Heribertweg 18",
    "sg:city":"Solingen",
    "sg:phone":"+49 212/812632",
    "sg:postcode":"42657",
    "sg:province":"Nordrhein-Westfalen",
    "wof:name":"Rolf Und Christa Reininghaus Architekten",
    "wof:placetype":"venue"
},
  "geometry": {"coordinates":[7.067586,51.135803],"type":"Point"}
}