{
  "type": "Feature",
  "properties": {
    "iso:country":"DE",
    "sg:address":"Kirchenweg 20",
    "sg:city":"Molfsee",
    "sg:phone":"+49 431/65966",
    "sg:postcode":"24113",
    "sg:province":"Schleswig-Holstein",
    "wof:name":"Ev. Pfarramt Schulensee",
    "wof:placetype":"venue"
},
  "geometry": {"coordinates":[10.0803108215,54.2854652405],"type":"Point"}
}