{
  "type": "Feature",
  "properties": {
    "iso:country":"DE",
    "sg:address":"Birnthon 2a",
    "sg:city":"N\u00fcrnberg",
    "sg:phone":"+49 9128/8104",
    "sg:postcode":"90475",
    "sg:province":"Bayern",
    "wof:name":"Western Club N\u00fcrnberg E. V.",
    "wof:placetype":"venue"
},
  "geometry": {"coordinates":[11.2618751526,49.4120674133],"type":"Point"}
}