{
  "type": "Feature",
  "properties": {
    "iso:country":"DE",
    "sg:address":"Altenaer Str. 72",
    "sg:city":"L\u00fcdenscheid",
    "sg:phone":"+49 2351/20320",
    "sg:postcode":"58507",
    "sg:province":"Nordrhein-Westfalen",
    "wof:name":"Eberhard Vielhaber Gmbh & Co.",
    "wof:placetype":"venue"
},
  "geometry": {"coordinates":[7.632397,51.221382],"type":"Point"}
}