{
  "type": "Feature",
  "properties": {
    "iso:country":"DE",
    "sg:address":"Hauptstr. 6",
    "sg:city":"Gelsenkirchen",
    "sg:phone":"+49 209/22090",
    "sg:postcode":"45879",
    "sg:province":"Nordrhein-Westfalen",
    "wof:name":"Wettb\u00fcro Dirk Riese",
    "wof:placetype":"venue"
},
  "geometry": {"coordinates":[7.09544,51.511063],"type":"Point"}
}