{
  "type": "Feature",
  "properties": {
    "iso:country":"DE",
    "sg:address":"P\u00f6mmelter Str. 7",
    "sg:city":"Sch\u00f6nebeck",
    "sg:postcode":"39218",
    "sg:province":"Sachsen-Anhalt",
    "wof:name":"Sch\u00fc\u00dfler Gmbh",
    "wof:placetype":"venue"
},
  "geometry": {"coordinates":[11.7645893097,52.0149345398],"type":"Point"}
}