{
  "type": "Feature",
  "properties": {
    "iso:country":"DE",
    "sg:address":"Adrian Stoop Str. 50",
    "sg:city":"Bad Wiessee",
    "sg:phone":"+49 8022/863140",
    "sg:postcode":"83707",
    "sg:province":"Bayern",
    "wof:name":"Eventt Sport Und Catering Am Tegernsee",
    "wof:placetype":"venue"
},
  "geometry": {"coordinates":[11.724926,47.719471],"type":"Point"}
}