{
  "type": "Feature",
  "properties": {
    "iso:country":"DE",
    "sg:address":"Oberer Ehmschen 93",
    "sg:city":"Rellingen",
    "sg:postcode":"25462",
    "sg:province":"Schleswig-Holstein",
    "wof:name":"Leather & Cars Christopher Heinemann",
    "wof:placetype":"venue"
},
  "geometry": {"coordinates":[9.8150520325,53.6542205811],"type":"Point"}
}