{
  "type": "Feature",
  "properties": {
    "iso:country":"DE",
    "sg:address":"M\u00fcnchener Str. 34",
    "sg:city":"Pfaffenhofen",
    "sg:phone":"+49 8441/3986",
    "sg:postcode":"85276",
    "sg:province":"Bayern",
    "wof:name":"Anton B\u00f6swirth Bahnhof-drogerie",
    "wof:placetype":"venue"
},
  "geometry": {"coordinates":[11.510829,48.526264],"type":"Point"}
}