{
  "type": "Feature",
  "properties": {
    "iso:country":"DE",
    "sg:address":"Auf Dem Zimmermann 7-9",
    "sg:city":"Niedereschach",
    "sg:phone":"+49 4977/2892790",
    "sg:postcode":"78078",
    "sg:province":"Baden-W\u00fcrttemberg",
    "wof:name":"Touratech Ag",
    "wof:placetype":"venue"
},
  "geometry": {"coordinates":[8.5309839249,48.1262626648],"type":"Point"}
}