{
  "type": "Feature",
  "properties": {
    "iso:country":"DE",
    "sg:address":"Kleiner Anger 27",
    "sg:city":"Karlsruhe",
    "sg:postcode":"76189",
    "sg:province":"Baden-W\u00fcrttemberg",
    "wof:name":"Sportstudio Galaxy",
    "wof:placetype":"venue"
},
  "geometry": {"coordinates":[8.3331804276,48.9953536987],"type":"Point"}
}