{
  "type": "Feature",
  "properties": {
    "iso:country":"DE",
    "sg:address":"Bahnhofstr. 69",
    "sg:city":"Effelder",
    "sg:postcode":"96528",
    "sg:province":"Th\u00fcringen",
    "wof:name":"Baumontageservice-fach- Handels-gmbh",
    "wof:placetype":"venue"
},
  "geometry": {"coordinates":[11.07574,50.379662],"type":"Point"}
}