{
  "type": "Feature",
  "properties": {
    "iso:country":"DE",
    "sg:address":"Burgsteinstr. 37",
    "sg:city":"Geroldsgr\u00fcn",
    "sg:phone":"+49 9288/229",
    "sg:postcode":"95179",
    "sg:province":"Bayern",
    "wof:name":"Helmut Menger",
    "wof:placetype":"venue"
},
  "geometry": {"coordinates":[11.591193,50.335464],"type":"Point"}
}