{
  "type": "Feature",
  "properties": {
    "iso:country":"DE",
    "sg:address":"K\u00f6rsestr. 6A",
    "sg:city":"Stadthagen",
    "sg:postcode":"31655",
    "sg:province":"Niedersachsen",
    "wof:name":"M. Roy",
    "wof:placetype":"venue"
},
  "geometry": {"coordinates":[9.192766,52.307034],"type":"Point"}
}