{
  "type": "Feature",
  "properties": {
    "iso:country":"DE",
    "sg:address":"Gelbinger Gasse 79",
    "sg:city":"Schw\u00e4bisch Hall",
    "sg:phone":"+49 791/71549",
    "sg:postcode":"74523",
    "sg:province":"Baden-W\u00fcrttemberg",
    "wof:name":"Pizzeria Pulcinella",
    "wof:placetype":"venue"
},
  "geometry": {"coordinates":[9.7358236313,49.1154747009],"type":"Point"}
}