{
  "type": "Feature",
  "properties": {
    "iso:country":"DE",
    "sg:address":"Kurt-Weill-Str. 1",
    "sg:city":"Dessau",
    "sg:phone":"+49 340/215548",
    "sg:postcode":"06844",
    "sg:province":"Sachsen-Anhalt",
    "wof:name":"Siegfried George",
    "wof:placetype":"venue"
},
  "geometry": {"coordinates":[12.2450294495,51.8409576416],"type":"Point"}
}