{
  "type": "Feature",
  "properties": {
    "iso:country":"DE",
    "sg:address":"M\u00fcmlingtalstr. 32",
    "sg:city":"Beerfelden",
    "sg:phone":"+49 6068/3434",
    "sg:postcode":"64743",
    "sg:province":"Hessen",
    "wof:name":"Restaurant Pfeiffer",
    "wof:placetype":"venue"
},
  "geometry": {"coordinates":[8.9782371521,49.5708618164],"type":"Point"}
}