{
  "type": "Feature",
  "properties": {
    "iso:country":"DE",
    "sg:address":"Zeppelinstr. 14",
    "sg:city":"Haan",
    "sg:phone":"+49 212/933895",
    "sg:postcode":"42781",
    "sg:province":"Nordrhein-Westfalen",
    "wof:name":"J\u00fcrgen Budde Rechtsanwalt",
    "wof:placetype":"venue"
},
  "geometry": {"coordinates":[7.0004048347,51.1910324097],"type":"Point"}
}