{
  "type": "Feature",
  "properties": {
    "iso:country":"DE",
    "sg:address":"Lieberoser Str. 46",
    "sg:city":"L\u00fcbben",
    "sg:phone":"+49 3546/4059",
    "sg:postcode":"15907",
    "sg:province":"Brandenburg",
    "wof:name":"Bbs Computersysteme Gmbh",
    "wof:placetype":"venue"
},
  "geometry": {"coordinates":[13.9215049744,51.9412956238],"type":"Point"}
}