{
  "type": "Feature",
  "properties": {
    "iso:country":"DE",
    "sg:address":"Georgenstr. 51",
    "sg:city":"Stendal",
    "sg:postcode":"39576",
    "sg:province":"Sachsen-Anhalt",
    "wof:name":"Karin Wiechmann",
    "wof:placetype":"venue"
},
  "geometry": {"coordinates":[11.84601,52.61301],"type":"Point"}
}