{
  "type": "Feature",
  "properties": {
    "iso:country":"DE",
    "sg:address":"Gutenbergstr. 33",
    "sg:city":"Spaichingen",
    "sg:phone":"+49 7424/4362",
    "sg:postcode":"78549",
    "sg:province":"Baden-W\u00fcrttemberg",
    "wof:name":"R\u00fcnzler-technik Gmbh",
    "wof:placetype":"venue"
},
  "geometry": {"coordinates":[8.730648,48.069176],"type":"Point"}
}