{
  "type": "Feature",
  "properties": {
    "iso:country":"DE",
    "sg:address":"Im Breitspiel 5",
    "sg:city":"Heidelberg",
    "sg:postcode":"69126",
    "sg:province":"Baden-W\u00fcrttemberg",
    "wof:name":"Rnc Consulting Gmbh",
    "wof:placetype":"venue"
},
  "geometry": {"coordinates":[8.6868314743,49.3649673462],"type":"Point"}
}