{
  "type": "Feature",
  "properties": {
    "iso:country":"DE",
    "sg:address":"Kohlh\u00f6kerstr. 46",
    "sg:city":"Bremen",
    "sg:postcode":"28203",
    "sg:province":"Bremen",
    "wof:name":"William R. P. Schulz Elektrogrosshandel",
    "wof:placetype":"venue"
},
  "geometry": {"coordinates":[8.8161392212,53.0756645203],"type":"Point"}
}