{
  "type": "Feature",
  "properties": {
    "iso:country":"DE",
    "sg:address":"Margaretenh\u00fctte 42",
    "sg:city":"Gie\u00dfen",
    "sg:phone":"+49 641/9718103",
    "sg:postcode":"35398",
    "sg:province":"Hessen",
    "wof:name":"Bilderrahmenfabrik Kolmer",
    "wof:placetype":"venue"
},
  "geometry": {"coordinates":[8.655019,50.574219],"type":"Point"}
}