{
  "type": "Feature",
  "properties": {
    "iso:country":"DE",
    "sg:address":"Teichrosenpfad 13",
    "sg:city":"Berlin",
    "sg:phone":"+49 30/7035086",
    "sg:postcode":"12347",
    "sg:province":"Berlin",
    "wof:name":"A & V Ges. F\u00fcr Absatzwerbung Und Verkaufsf\u00f6rderung Mbh",
    "wof:placetype":"venue"
},
  "geometry": {"coordinates":[13.4164934158,52.4438285828],"type":"Point"}
}