{
  "type": "Feature",
  "properties": {
    "iso:country":"DE",
    "sg:address":"Rohrbachstr. 35",
    "sg:city":"Wiedenzhausen",
    "sg:phone":"+49 8134/92430",
    "sg:postcode":"85259",
    "sg:province":"Bayern",
    "wof:name":"Klaus Fieber",
    "wof:placetype":"venue"
},
  "geometry": {"coordinates":[11.2383031845,48.3008842468],"type":"Point"}
}