{
  "type": "Feature",
  "properties": {
    "iso:country":"DE",
    "sg:address":"Gro\u00dfe Bahnstr. 101",
    "sg:city":"Hamburg",
    "sg:postcode":"22769",
    "sg:province":"Hamburg",
    "wof:name":"Nmv Service Gmbh",
    "wof:placetype":"venue"
},
  "geometry": {"coordinates":[9.934601,53.570286],"type":"Point"}
}