{
  "type": "Feature",
  "properties": {
    "iso:country":"DE",
    "sg:address":"Querschlag 18",
    "sg:city":"Bochum",
    "sg:phone":"+49 234/73392",
    "sg:postcode":"44799",
    "sg:province":"Nordrhein-Westfalen",
    "wof:name":"Restaurant Georgskrug",
    "wof:placetype":"venue"
},
  "geometry": {"coordinates":[7.2319221497,51.4553108215],"type":"Point"}
}