{
  "type": "Feature",
  "properties": {
    "iso:country":"DE",
    "sg:address":"Kaiserstr. 52",
    "sg:city":"Langenfeld",
    "sg:phone":"+49 2173/70179",
    "sg:postcode":"40764",
    "sg:province":"Nordrhein-Westfalen",
    "wof:name":"F. Und H. Noack",
    "wof:placetype":"venue"
},
  "geometry": {"coordinates":[6.94496,51.131413],"type":"Point"}
}