{
  "type": "Feature",
  "properties": {
    "iso:country":"DE",
    "sg:address":"D\u00fcneberger Str. 73 I",
    "sg:city":"Geesthacht",
    "sg:phone":"+49 4152/83216",
    "sg:postcode":"21502",
    "sg:province":"Schleswig-Holstein",
    "wof:name":"E. Glogasa",
    "wof:placetype":"venue"
},
  "geometry": {"coordinates":[10.374250412,53.4302940369],"type":"Point"}
}