{
  "type": "Feature",
  "properties": {
    "iso:country":"DE",
    "sg:address":"Ederstr. 32",
    "sg:city":"Hatzfeld",
    "sg:phone":"+49 6452/8289",
    "sg:postcode":"35116",
    "sg:province":"Hessen",
    "wof:name":"Landhaus Feisel",
    "wof:placetype":"venue"
},
  "geometry": {"coordinates":[8.5865316391,51.0114097595],"type":"Point"}
}