{
  "type": "Feature",
  "properties": {
    "iso:country":"DE",
    "sg:address":"St.-Anna-Str. 10",
    "sg:city":"M\u00fcnchen",
    "sg:phone":"+49 89/225533",
    "sg:postcode":"80538",
    "sg:province":"Bayern",
    "wof:name":"Hotel Opera",
    "wof:placetype":"venue"
},
  "geometry": {"coordinates":[11.5871515274,48.1389007568],"type":"Point"}
}