{
  "type": "Feature",
  "properties": {
    "iso:country":"DE",
    "sg:address":"Schneidhainer Str. 33",
    "sg:city":"K\u00f6nigstein",
    "sg:phone":"+49 6174/92750",
    "sg:postcode":"61462",
    "sg:province":"Hessen",
    "wof:name":"Rotec Handels Gmbh",
    "wof:placetype":"venue"
},
  "geometry": {"coordinates":[8.467792,50.175682],"type":"Point"}
}