{
  "type": "Feature",
  "properties": {
    "iso:country":"DE",
    "sg:address":"Markt 11",
    "sg:city":"Naumburg",
    "sg:phone":"+49 3445/205577",
    "sg:postcode":"06618",
    "sg:province":"Sachsen-Anhalt",
    "wof:name":"Carolus Magnus Inh. Ralf Kannegie\u00dfler",
    "wof:placetype":"venue"
},
  "geometry": {"coordinates":[11.8101806641,51.1529006958],"type":"Point"}
}