{
  "type": "Feature",
  "properties": {
    "iso:country":"DE",
    "sg:address":"M\u00fcnchener Str. 66",
    "sg:city":"Rosenheim",
    "sg:postcode":"83022",
    "sg:province":"Bayern",
    "wof:name":"Erzgebirgische Volksbank Aue (sachsen) Eg",
    "wof:placetype":"venue"
},
  "geometry": {"coordinates":[12.697393,50.588596],"type":"Point"}
}