{
  "type": "Feature",
  "properties": {
    "iso:country":"DE",
    "sg:address":"Rollgasse 1",
    "sg:city":"N\u00fcsttal",
    "sg:phone":"+49 6684/239",
    "sg:postcode":"36167",
    "sg:province":"Hessen",
    "wof:name":"G\u00e4stehaus Elmar Uth",
    "wof:placetype":"venue"
},
  "geometry": {"coordinates":[9.9010391235,50.6213989258],"type":"Point"}
}