{
  "type": "Feature",
  "properties": {
    "iso:country":"DE",
    "sg:address":"Neustr. 82",
    "sg:city":"Trier",
    "sg:phone":"+49 651/42389",
    "sg:postcode":"54290",
    "sg:province":"Rheinland-Pfalz",
    "wof:name":"August Loch",
    "wof:placetype":"venue"
},
  "geometry": {"coordinates":[6.638010025,49.7521057129],"type":"Point"}
}