{
  "type": "Feature",
  "properties": {
    "iso:country":"DE",
    "sg:address":"Berliner Str. 157",
    "sg:city":"Berlin",
    "sg:phone":"+49 30/8544001",
    "sg:postcode":"10715",
    "sg:province":"Berlin",
    "wof:name":"Klaus-peter Maslowski Malermeister Inh.",
    "wof:placetype":"venue"
},
  "geometry": {"coordinates":[13.332728,52.487373],"type":"Point"}
}