{
  "type": "Feature",
  "properties": {
    "iso:country":"DE",
    "sg:address":"Kirchenstr. 3",
    "sg:city":"Rimpar",
    "sg:phone":"+49 9365/5113",
    "sg:postcode":"97222",
    "sg:province":"Bayern",
    "wof:name":"J. Werner",
    "wof:placetype":"venue"
},
  "geometry": {"coordinates":[9.9554958344,49.8563690186],"type":"Point"}
}