{
  "type": "Feature",
  "properties": {
    "iso:country":"DE",
    "sg:address":"Badweg 4",
    "sg:city":"Waldkirch",
    "sg:phone":"+49 7681/9771",
    "sg:postcode":"79183",
    "sg:province":"Baden-W\u00fcrttemberg",
    "wof:name":"Rolf Ringwald",
    "wof:placetype":"venue"
},
  "geometry": {"coordinates":[7.9207878113,48.0796966553],"type":"Point"}
}