{
  "type": "Feature",
  "properties": {
    "iso:country":"DE",
    "sg:address":"An der Mehlwaage 2",
    "sg:city":"Freiburg",
    "sg:phone":"+49 761/3805220",
    "sg:postcode":"79098",
    "sg:province":"Baden-W\u00fcrttemberg",
    "wof:name":"A. Rechtsanwalt R\u00fcdiger Stark",
    "wof:placetype":"venue"
},
  "geometry": {"coordinates":[7.848531,47.992905],"type":"Point"}
}