{
  "type": "Feature",
  "properties": {
    "iso:country":"DE",
    "sg:address":"M\u00fcnchener Str 20",
    "sg:city":"Feldkirchen-Westerham",
    "sg:phone":"+49 8063/200330",
    "sg:postcode":"83620",
    "sg:province":"Bayern",
    "wof:name":"Solarpartner Gmbh",
    "wof:placetype":"venue"
},
  "geometry": {"coordinates":[11.8398189545,47.9102554321],"type":"Point"}
}