{
  "type": "Feature",
  "properties": {
    "iso:country":"DE",
    "sg:address":"Bahnhofstr. 11",
    "sg:city":"Olsberg",
    "sg:phone":"+49 2962/2388",
    "sg:postcode":"59939",
    "sg:province":"Nordrhein-Westfalen",
    "wof:name":"Hildegard Vorderw\u00fclbecke",
    "wof:placetype":"venue"
},
  "geometry": {"coordinates":[8.489661,51.354454],"type":"Point"}
}