{
  "type": "Feature",
  "properties": {
    "iso:country":"DE",
    "sg:address":"Sonnenbichlweg 5",
    "sg:city":"Starnberg",
    "sg:phone":"+49 8151/918563",
    "sg:postcode":"82319",
    "sg:province":"Bayern",
    "wof:name":"Gz Hausverwaltungs Gmbh",
    "wof:placetype":"venue"
},
  "geometry": {"coordinates":[11.3200998306,48.0074424744],"type":"Point"}
}