{
  "type": "Feature",
  "properties": {
    "iso:country":"DE",
    "sg:address":"Wilhelm-Tell-Str. 72",
    "sg:city":"Hannover",
    "sg:phone":"+49 511/584452",
    "sg:postcode":"30629",
    "sg:province":"Niedersachsen",
    "wof:name":"Horst Schmalz",
    "wof:placetype":"venue"
},
  "geometry": {"coordinates":[9.8344297409,52.3930702209],"type":"Point"}
}