{
  "type": "Feature",
  "properties": {
    "iso:country":"DE",
    "sg:address":"Neust\u00e4dter Str. 13",
    "sg:city":"Cottbus",
    "sg:phone":"+49 355/78340",
    "sg:postcode":"03046",
    "sg:province":"Brandenburg",
    "wof:name":"Bilfinger Berger Ag",
    "wof:placetype":"venue"
},
  "geometry": {"coordinates":[14.3354320526,51.7593955994],"type":"Point"}
}