{
  "type": "Feature",
  "properties": {
    "iso:country":"DE",
    "sg:address":"Hubstr. 13",
    "sg:city":"Kandel",
    "sg:phone":"+49 7275/3546",
    "sg:postcode":"76870",
    "sg:province":"Rheinland-Pfalz",
    "wof:name":"W. Dahl",
    "wof:placetype":"venue"
},
  "geometry": {"coordinates":[8.1853313446,49.080657959],"type":"Point"}
}