{
  "type": "Feature",
  "properties": {
    "iso:country":"DE",
    "sg:address":"Bahnhofstr. 13",
    "sg:city":"Bruchhausen-Vilsen",
    "sg:phone":"+49 4252/1824",
    "sg:postcode":"27305",
    "sg:province":"Niedersachsen",
    "wof:name":"Wolrad Peimann E. K.",
    "wof:placetype":"venue"
},
  "geometry": {"coordinates":[8.98734,52.82658],"type":"Point"}
}