{
  "type": "Feature",
  "properties": {
    "iso:country":"DE",
    "sg:address":"Hergenrotherstra\u00dfe 3",
    "sg:city":"Westerburg",
    "sg:phone":"+49 2663",
    "sg:postcode":"56457",
    "sg:province":"Rheinland-Pfalz",
    "wof:name":"Louis Kl\u00f6ckner Schilderfabrik",
    "wof:placetype":"venue"
},
  "geometry": {"coordinates":[7.974409,50.572723],"type":"Point"}
}