{
  "type": "Feature",
  "properties": {
    "iso:country":"DE",
    "sg:address":"Fellendsweg 12",
    "sg:city":"Bremen",
    "sg:phone":"+49 421/831962",
    "sg:postcode":"28279",
    "sg:province":"Bremen",
    "wof:name":"E. H. Witt",
    "wof:placetype":"venue"
},
  "geometry": {"coordinates":[8.8394012451,53.0517311096],"type":"Point"}
}