{
  "type": "Feature",
  "properties": {
    "iso:country":"DE",
    "sg:address":"N\u00fcrnberger Str. 90",
    "sg:city":"Erlangen",
    "sg:phone":"+49 9131/34044",
    "sg:postcode":"91052",
    "sg:province":"Bayern",
    "wof:name":"Fmp Autovermiet-gmbh",
    "wof:placetype":"venue"
},
  "geometry": {"coordinates":[11.007823,49.5868],"type":"Point"}
}