{
  "type": "Feature",
  "properties": {
    "iso:country":"DE",
    "sg:address":"Auf den L\u00fcppen",
    "sg:city":"Herborn",
    "sg:phone":"+49 2772/54506",
    "sg:postcode":"35745",
    "sg:province":"Hessen",
    "wof:name":"Lewe Pr\u00e4zisionswerkzeuge Gmbh",
    "wof:placetype":"venue"
},
  "geometry": {"coordinates":[8.28013,50.67181],"type":"Point"}
}