{
  "type": "Feature",
  "properties": {
    "iso:country":"DE",
    "sg:address":"Tanzhausstr. 1",
    "sg:city":"Kronberg",
    "sg:phone":"+49 6173/640518",
    "sg:postcode":"61476",
    "sg:province":"Hessen",
    "wof:name":"Uwe Opper",
    "wof:placetype":"venue"
},
  "geometry": {"coordinates":[8.508573,50.180012],"type":"Point"}
}