{
  "type": "Feature",
  "properties": {
    "iso:country":"DE",
    "sg:address":"Schneeberger Str. 34a",
    "sg:city":"L\u00f6\u00dfnitz",
    "sg:phone":"+49 3771/35470",
    "sg:postcode":"08294",
    "sg:province":"Sachsen",
    "wof:name":"Helmut Georgi",
    "wof:placetype":"venue"
},
  "geometry": {"coordinates":[12.7253789902,50.6201019287],"type":"Point"}
}