{
  "type": "Feature",
  "properties": {
    "iso:country":"DE",
    "sg:address":"Tannenweg 3",
    "sg:city":"Schirmitz",
    "sg:phone":"+49 961/5991",
    "sg:postcode":"92718",
    "sg:province":"Bayern",
    "wof:name":"Sigrun Abrill",
    "wof:placetype":"venue"
},
  "geometry": {"coordinates":[12.171176,49.650265],"type":"Point"}
}