{
  "type": "Feature",
  "properties": {
    "iso:country":"DE",
    "sg:address":"Brucknerstr. 18",
    "sg:city":"Recklinghausen",
    "sg:postcode":"45657",
    "sg:province":"Nordrhein-Westfalen",
    "wof:name":"Magneto E. K.",
    "wof:placetype":"venue"
},
  "geometry": {"coordinates":[7.196682,51.62368],"type":"Point"}
}