{
  "type": "Feature",
  "properties": {
    "iso:country":"DE",
    "sg:address":"Industriestr. 4",
    "sg:city":"Himmelkron",
    "sg:phone":"+49 9227/818",
    "sg:postcode":"95502",
    "sg:province":"Bayern",
    "wof:name":"Frenzelit-werke Gmbh & Co.",
    "wof:placetype":"venue"
},
  "geometry": {"coordinates":[11.6037397385,50.0683403015],"type":"Point"}
}