{
  "type": "Feature",
  "properties": {
    "iso:country":"DE",
    "sg:address":"Markt 25",
    "sg:city":"Leisnig",
    "sg:phone":"+49 34321/14717",
    "sg:postcode":"04703",
    "sg:province":"Sachsen",
    "wof:name":"Reiseb\u00fcro H\u00f6rich & Stenzel",
    "wof:placetype":"venue"
},
  "geometry": {"coordinates":[12.9270038605,51.1600608826],"type":"Point"}
}