{
  "type": "Feature",
  "properties": {
    "iso:country":"DE",
    "sg:address":"Karlstr. 20",
    "sg:city":"Biebertal",
    "sg:phone":"+49 6409/81070",
    "sg:postcode":"35444",
    "sg:province":"Hessen",
    "wof:name":"Kehm Kerl Und Remy Gbr Garten- Und",
    "wof:placetype":"venue"
},
  "geometry": {"coordinates":[8.610545,50.613792],"type":"Point"}
}