{
  "type": "Feature",
  "properties": {
    "iso:country":"DE",
    "sg:address":"Sonnenstr. 22",
    "sg:city":"Hindelang",
    "sg:phone":"+49 8324/98010",
    "sg:postcode":"87541",
    "sg:province":"Bayern",
    "wof:name":"Hotel Berghof",
    "wof:placetype":"venue"
},
  "geometry": {"coordinates":[10.4223613739,47.5442504883],"type":"Point"}
}