{
  "type": "Feature",
  "properties": {
    "iso:country":"DE",
    "sg:address":"Maseler Dorfstr. 27",
    "sg:city":"Sprakensehl",
    "sg:phone":"+49 5837/554",
    "sg:postcode":"29365",
    "sg:province":"Niedersachsen",
    "wof:name":"W. Niebuhr",
    "wof:placetype":"venue"
},
  "geometry": {"coordinates":[10.5151147842,52.7524337769],"type":"Point"}
}