{
  "type": "Feature",
  "properties": {
    "iso:country":"DE",
    "sg:address":"Wittenauer Str. 10-16",
    "sg:city":"Berlin",
    "sg:postcode":"13435",
    "sg:province":"Berlin",
    "wof:name":"Hans Laatzig Automobile Gmbh",
    "wof:placetype":"venue"
},
  "geometry": {"coordinates":[13.33303,52.603031],"type":"Point"}
}