{
  "type": "Feature",
  "properties": {
    "iso:country":"DE",
    "sg:address":"Hauptstr. 18",
    "sg:city":"Mainaschaff",
    "sg:phone":"+49 6021/73539",
    "sg:postcode":"63814",
    "sg:province":"Bayern",
    "wof:name":"Karl Wei\u00dfkopf & Sohn Inh. Rainer Wei\u00dfkopf",
    "wof:placetype":"venue"
},
  "geometry": {"coordinates":[9.0861940384,49.9774932861],"type":"Point"}
}