{
  "type": "Feature",
  "properties": {
    "iso:country":"DE",
    "sg:address":"L\u00fcttemicke 2",
    "sg:city":"Drolshagen",
    "sg:phone":"+49 2761/969023",
    "sg:postcode":"57489",
    "sg:province":"Nordrhein-Westfalen",
    "wof:name":"Kon Gesellschaft F\u00fcr Datenverarbeitung Mbh",
    "wof:placetype":"venue"
},
  "geometry": {"coordinates":[7.819583,51.059471],"type":"Point"}
}