{
  "type": "Feature",
  "properties": {
    "iso:country":"DE",
    "sg:address":"Oranienburger Str. 141",
    "sg:city":"Berlin",
    "sg:phone":"+49 30/4039060",
    "sg:postcode":"13437",
    "sg:province":"Berlin",
    "wof:name":"Zenker-hausbau Gmbh & Co. Kg Ges. F. Marketing U. Vertrieb",
    "wof:placetype":"venue"
},
  "geometry": {"coordinates":[13.3258781433,52.6051864624],"type":"Point"}
}