{
  "type": "Feature",
  "properties": {
    "iso:country":"DE",
    "sg:address":"Auf Sprung 15",
    "sg:city":"Trier",
    "sg:phone":"+49 651/52105",
    "sg:postcode":"54292",
    "sg:province":"Rheinland-Pfalz",
    "wof:name":"J\u00fcrgen Schollendorf Rechtsanwalt",
    "wof:placetype":"venue"
},
  "geometry": {"coordinates":[6.7104120255,49.7896003723],"type":"Point"}
}