{
  "type": "Feature",
  "properties": {
    "iso:country":"DE",
    "sg:address":"Iserlohner Str. 99",
    "sg:city":"Hagen",
    "sg:phone":"+49 2334/56594",
    "sg:postcode":"58119",
    "sg:province":"Nordrhein-Westfalen",
    "wof:name":"Restaurant Haus Nordhoff",
    "wof:placetype":"venue"
},
  "geometry": {"coordinates":[7.5734348297,51.3605537415],"type":"Point"}
}