{
  "type": "Feature",
  "properties": {
    "iso:country":"DE",
    "sg:address":"Geleitsstr. 36",
    "sg:city":"Offenbach",
    "sg:phone":"+49 69/813569",
    "sg:postcode":"63065",
    "sg:province":"Hessen",
    "wof:name":"Deko Shop",
    "wof:placetype":"venue"
},
  "geometry": {"coordinates":[8.7609291077,50.1028175354],"type":"Point"}
}