{
  "type": "Feature",
  "properties": {
    "iso:country":"DE",
    "sg:address":"B\u00fcrgermeister-Herb-Str. 2",
    "sg:city":"Gengenbach",
    "sg:phone":"+49 7803/2515",
    "sg:postcode":"77723",
    "sg:province":"Baden-W\u00fcrttemberg",
    "wof:name":"Ziva Zimmermann Verwaltungs-gmbh",
    "wof:placetype":"venue"
},
  "geometry": {"coordinates":[8.017991066,48.3991203308],"type":"Point"}
}