{
  "type": "Feature",
  "properties": {
    "iso:country":"DE",
    "sg:address":"Averhoffstr. 4",
    "sg:city":"Hamburg",
    "sg:phone":"+49 40/2200099",
    "sg:postcode":"22085",
    "sg:province":"Hamburg",
    "wof:name":"Bernhard Wolff Gmbh",
    "wof:placetype":"venue"
},
  "geometry": {"coordinates":[10.017587,53.570564],"type":"Point"}
}