{
  "type": "Feature",
  "properties": {
    "iso:country":"DE",
    "sg:address":"K\u00e4the-Kollwitz-Str. 65",
    "sg:city":"Leipzig",
    "sg:phone":"+49 341/9833457",
    "sg:postcode":"04109",
    "sg:province":"Sachsen",
    "wof:name":"Weskamp & Partner Rechtsanw\u00e4lte",
    "wof:placetype":"venue"
},
  "geometry": {"coordinates":[12.3611898422,51.3381958008],"type":"Point"}
}