{
  "type": "Feature",
  "properties": {
    "iso:country":"DE",
    "sg:address":"Genslerstr. 33",
    "sg:city":"Berlin",
    "sg:phone":"+49 30/9715111",
    "sg:postcode":"13055",
    "sg:province":"Berlin",
    "wof:name":"China Restaurant Peking City",
    "wof:placetype":"venue"
},
  "geometry": {"coordinates":[13.4974536896,52.5359306335],"type":"Point"}
}