{
  "type": "Feature",
  "properties": {
    "iso:country":"DE",
    "sg:address":"Turnerheimstr. 43",
    "sg:city":"N\u00fcrnberg",
    "sg:phone":"+49 911/662172",
    "sg:postcode":"90441",
    "sg:province":"Bayern",
    "wof:name":"Friedrich Sporer",
    "wof:placetype":"venue"
},
  "geometry": {"coordinates":[11.046969,49.426128],"type":"Point"}
}