{
  "type": "Feature",
  "properties": {
    "iso:country":"DE",
    "sg:address":"Doggerbankweg 19",
    "sg:city":"Hamburg",
    "sg:phone":"+49 40/7425361",
    "sg:postcode":"21129",
    "sg:province":"Hamburg",
    "wof:name":"Walter Stehr",
    "wof:placetype":"venue"
},
  "geometry": {"coordinates":[9.872455,53.536209],"type":"Point"}
}