{
  "type": "Feature",
  "properties": {
    "iso:country":"DE",
    "sg:address":"Hohenzollernstr. 14",
    "sg:city":"Berlin",
    "sg:phone":"+49 30/806800",
    "sg:postcode":"14109",
    "sg:province":"Berlin",
    "wof:name":"Wannseeheim F.jugendarbeit Berlin E.v.",
    "wof:placetype":"venue"
},
  "geometry": {"coordinates":[13.1527853012,52.4127883911],"type":"Point"}
}