{
  "type": "Feature",
  "properties": {
    "iso:country":"DE",
    "sg:address":"Martin-Bauer-Weg 9",
    "sg:city":"Mammendorf",
    "sg:phone":"+49 8145/237",
    "sg:postcode":"82291",
    "sg:province":"Bayern",
    "wof:name":"K. Eggert Landmaschinenhdl. Und",
    "wof:placetype":"venue"
},
  "geometry": {"coordinates":[11.17482,48.216068],"type":"Point"}
}