{
  "type": "Feature",
  "properties": {
    "iso:country":"DE",
    "sg:address":"Bernsdorfer Str. 179",
    "sg:city":"Chemnitz",
    "sg:postcode":"09126",
    "sg:province":"Sachsen",
    "wof:name":"Prisma Bauelemente Handelsvertretung Gmbh",
    "wof:placetype":"venue"
},
  "geometry": {"coordinates":[12.9429101944,50.8081893921],"type":"Point"}
}