{
  "type": "Feature",
  "properties": {
    "iso:country":"DE",
    "sg:address":"Telegrafstr. 16",
    "sg:city":"Troisdorf",
    "sg:phone":"+49 2241/43003",
    "sg:postcode":"53842",
    "sg:province":"Nordrhein-Westfalen",
    "wof:name":"Telegraf-lokal",
    "wof:placetype":"venue"
},
  "geometry": {"coordinates":[7.1277871132,50.8259811401],"type":"Point"}
}