{
  "type": "Feature",
  "properties": {
    "iso:country":"DE",
    "sg:address":"Karl-Schneider-Str. 8",
    "sg:city":"Gladbeck",
    "sg:phone":"+49 2043/478055",
    "sg:postcode":"45966",
    "sg:province":"Nordrhein-Westfalen",
    "wof:name":"Drexler Immobilien Und Handels Kg",
    "wof:placetype":"venue"
},
  "geometry": {"coordinates":[6.968822,51.572552],"type":"Point"}
}