{
  "type": "Feature",
  "properties": {
    "iso:country":"DE",
    "sg:address":"Schulstr. 10",
    "sg:city":"Walldorf",
    "sg:phone":"+49 3693/803686",
    "sg:postcode":"98639",
    "sg:province":"Th\u00fcringen",
    "wof:name":"J\u00fcrgen M\u00fcller Ingenieur",
    "wof:placetype":"venue"
},
  "geometry": {"coordinates":[10.3868980408,50.6112556458],"type":"Point"}
}