{
  "type": "Feature",
  "properties": {
    "iso:country":"DE",
    "sg:address":"Alicestr. 11",
    "sg:city":"Alsfeld",
    "sg:phone":"+49 6631/4137",
    "sg:postcode":"36304",
    "sg:province":"Hessen",
    "wof:name":"Tutti-frutti Christoph Hartmann",
    "wof:placetype":"venue"
},
  "geometry": {"coordinates":[9.2669944763,50.7515830994],"type":"Point"}
}