{
  "type": "Feature",
  "properties": {
    "iso:country":"DE",
    "sg:address":"Schrannenstr. 18",
    "sg:city":"Ingolstadt",
    "sg:phone":"+49 841/34292",
    "sg:postcode":"85049",
    "sg:province":"Bayern",
    "wof:name":"Fotostudio Adlhoch Inh. Gabriele Bienert E. K.",
    "wof:placetype":"venue"
},
  "geometry": {"coordinates":[11.4248723984,48.7652435303],"type":"Point"}
}