{
  "type": "Feature",
  "properties": {
    "iso:country":"DE",
    "sg:address":"Talsbachstr. 14 A",
    "sg:city":"Siegen",
    "sg:phone":"+49 4927/1382035",
    "sg:postcode":"57080",
    "sg:province":"Nordrhein-Westfalen",
    "wof:name":"Steiner Gmbh",
    "wof:placetype":"venue"
},
  "geometry": {"coordinates":[7.998088,50.832397],"type":"Point"}
}