{
  "type": "Feature",
  "properties": {
    "iso:country":"DE",
    "sg:address":"Mittelstr. 11-15",
    "sg:city":"Neum\u00fcnster",
    "sg:phone":"+49 4321/40990",
    "sg:postcode":"24534",
    "sg:province":"Schleswig-Holstein",
    "wof:name":"Liekfeldt Druck Gmbh",
    "wof:placetype":"venue"
},
  "geometry": {"coordinates":[9.982103,54.077602],"type":"Point"}
}