{
  "type": "Feature",
  "properties": {
    "iso:country":"DE",
    "sg:address":"Adolfsallee 39",
    "sg:city":"Wiesbaden",
    "sg:phone":"+49 611/305054",
    "sg:postcode":"65185",
    "sg:province":"Hessen",
    "wof:name":"Interessengemeinschaft Der Apotheker Hessen-nassau E. V.",
    "wof:placetype":"venue"
},
  "geometry": {"coordinates":[8.2399682999,50.0728569031],"type":"Point"}
}