{
  "type": "Feature",
  "properties": {
    "iso:country":"DE",
    "sg:address":"Gellertstr. 2",
    "sg:city":"Karlsruhe",
    "sg:postcode":"76185",
    "sg:province":"Baden-W\u00fcrttemberg",
    "wof:name":"Hopp Autovermietung",
    "wof:placetype":"venue"
},
  "geometry": {"coordinates":[8.373528,49.009705],"type":"Point"}
}