{
  "type": "Feature",
  "properties": {
    "iso:country":"DE",
    "sg:address":"Sch\u00f6nheider Str. 7",
    "sg:city":"Steinberg",
    "sg:phone":"+49 37462/3234",
    "sg:postcode":"08237",
    "sg:province":"Sachsen",
    "wof:name":"Tischlerei Bauer Gmbh",
    "wof:placetype":"venue"
},
  "geometry": {"coordinates":[12.511102,50.532768],"type":"Point"}
}