{
  "type": "Feature",
  "properties": {
    "iso:country":"DE",
    "sg:address":"Hauptstr. 5",
    "sg:city":"Kraftisried",
    "sg:phone":"+49 8377/1646",
    "sg:postcode":"87647",
    "sg:province":"Bayern",
    "wof:name":"Berghorn",
    "wof:placetype":"venue"
},
  "geometry": {"coordinates":[10.4726285934,47.7785797119],"type":"Point"}
}