{
  "type": "Feature",
  "properties": {
    "iso:country":"DE",
    "sg:address":"Flurstr. 120",
    "sg:city":"Gelsenkirchen",
    "sg:phone":"+49 209/581236",
    "sg:postcode":"45899",
    "sg:province":"Nordrhein-Westfalen",
    "wof:name":"Roland Krause Ingenieur Und Architekt",
    "wof:placetype":"venue"
},
  "geometry": {"coordinates":[7.0493,51.551311],"type":"Point"}
}