{
  "type": "Feature",
  "properties": {
    "iso:country":"DE",
    "sg:address":"Ernst-Schneller-Str. 77",
    "sg:city":"St. Egidien",
    "sg:phone":"+49 3723/411215",
    "sg:postcode":"09356",
    "sg:province":"Sachsen",
    "wof:name":"M. Stiehler",
    "wof:placetype":"venue"
},
  "geometry": {"coordinates":[12.6251,50.799683],"type":"Point"}
}