{
  "type": "Feature",
  "properties": {
    "iso:country":"DE",
    "sg:address":"Bernburger Str. 10/12",
    "sg:city":"Sta\u00dffurt",
    "sg:postcode":"39418",
    "sg:province":"Sachsen-Anhalt",
    "wof:name":"Repo Markt Rest- Und Sonderposten Gmbh",
    "wof:placetype":"venue"
},
  "geometry": {"coordinates":[11.594447,51.84597],"type":"Point"}
}