{
  "type": "Feature",
  "properties": {
    "iso:country":"DE",
    "sg:address":"Neumann-Reichardt-Stra\u00dfe 27-33",
    "sg:city":"Hamburg",
    "sg:phone":"+49 40",
    "sg:postcode":"22041",
    "sg:province":"Hamburg",
    "wof:name":"Bildungsforum Hamburg",
    "wof:placetype":"venue"
},
  "geometry": {"coordinates":[10.06602,53.571709],"type":"Point"}
}