{
  "type": "Feature",
  "properties": {
    "iso:country":"DE",
    "sg:address":"Kurstr. 26",
    "sg:city":"Brandenburg",
    "sg:phone":"+49 3381/25000",
    "sg:postcode":"14776",
    "sg:province":"Brandenburg",
    "wof:name":"Igk Ingenieurgesellschaft F\u00fcr Kommunales Bauen Mbh",
    "wof:placetype":"venue"
},
  "geometry": {"coordinates":[12.5581655502,52.4071426392],"type":"Point"}
}