{
  "type": "Feature",
  "properties": {
    "iso:country":"DE",
    "sg:address":"Alt-Mahlsdorf",
    "sg:city":"Berlin",
    "sg:phone":"+49 30/20276112",
    "sg:postcode":"12623",
    "sg:province":"Berlin",
    "wof:name":"Elf Oil Ag",
    "wof:placetype":"venue"
},
  "geometry": {"coordinates":[13.6189613342,52.5044059753],"type":"Point"}
}