{
  "type": "Feature",
  "properties": {
    "iso:country":"DE",
    "sg:address":"Hartmannsbach 7",
    "sg:city":"Bad Gottleuba",
    "sg:phone":"+49 35023/62767",
    "sg:postcode":"01816",
    "sg:province":"Sachsen",
    "wof:name":"Werner Fiedler",
    "wof:placetype":"venue"
},
  "geometry": {"coordinates":[13.927123,50.843922],"type":"Point"}
}