{
  "type": "Feature",
  "properties": {
    "iso:country":"DE",
    "sg:address":"Heinestr. 28",
    "sg:city":"Bocholt",
    "sg:phone":"+49 2871/180419",
    "sg:postcode":"46397",
    "sg:province":"Nordrhein-Westfalen",
    "wof:name":"R & M Radstaak Gmbh",
    "wof:placetype":"venue"
},
  "geometry": {"coordinates":[6.6440858841,51.8310279846],"type":"Point"}
}