{
  "type": "Feature",
  "properties": {
    "iso:country":"DE",
    "sg:address":"Hochstr. 47",
    "sg:city":"Frankfurt",
    "sg:phone":"+49 69/280151",
    "sg:postcode":"60313",
    "sg:province":"Hessen",
    "wof:name":"Sigrid Nolte-schefold Rechtsanw\u00e4ltin",
    "wof:placetype":"venue"
},
  "geometry": {"coordinates":[8.6736936569,50.115436554],"type":"Point"}
}