{
  "type": "Feature",
  "properties": {
    "iso:country":"DE",
    "sg:address":"Moorstr. 71",
    "sg:city":"Steinwenden",
    "sg:phone":"+49 6371/50637",
    "sg:postcode":"66879",
    "sg:province":"Rheinland-Pfalz",
    "wof:name":"Dr. Gerhard Kuhn Rechtsanwalt",
    "wof:placetype":"venue"
},
  "geometry": {"coordinates":[7.5246930122,49.4551582336],"type":"Point"}
}