{
  "type": "Feature",
  "properties": {
    "iso:country":"DE",
    "sg:address":"Hohe Str. 1",
    "sg:city":"Prettin",
    "sg:phone":"+49 35386/22649",
    "sg:postcode":"06922",
    "sg:province":"Sachsen-Anhalt",
    "wof:name":"S. Schmidt",
    "wof:placetype":"venue"
},
  "geometry": {"coordinates":[12.9230804443,51.66147995],"type":"Point"}
}