{
  "type": "Feature",
  "properties": {
    "iso:country":"DE",
    "sg:address":"Siemensstr. 19",
    "sg:city":"Unterschlei\u00dfheim",
    "sg:phone":"+49 89/3178470",
    "sg:postcode":"85716",
    "sg:province":"Bayern",
    "wof:name":"Keller & Kalmbach Beteiligungs-gmbh",
    "wof:placetype":"venue"
},
  "geometry": {"coordinates":[11.571094,48.287697],"type":"Point"}
}