{
  "type": "Feature",
  "properties": {
    "iso:country":"DE",
    "sg:address":"Gartenstr. 18",
    "sg:city":"Neustadt",
    "sg:phone":"+49 6692/6382",
    "sg:postcode":"35279",
    "sg:province":"Hessen",
    "wof:name":"Willi Ruhl Feuerwehrbedarf",
    "wof:placetype":"venue"
},
  "geometry": {"coordinates":[9.116447,50.849613],"type":"Point"}
}