{
  "type": "Feature",
  "properties": {
    "iso:country":"DE",
    "sg:address":"Zwotaer Str. 59",
    "sg:city":"Klingenthal",
    "sg:phone":"+49 37467/6430",
    "sg:postcode":"08248",
    "sg:province":"Sachsen",
    "wof:name":"Holzbau Klingenthal Gmbh & Co. Kg",
    "wof:placetype":"venue"
},
  "geometry": {"coordinates":[12.454752,50.357513],"type":"Point"}
}