{
  "type": "Feature",
  "properties": {
    "iso:country":"DE",
    "sg:address":"Graf-Recke-Str. 82",
    "sg:city":"D\u00fcsseldorf",
    "sg:postcode":"40239",
    "sg:province":"Nordrhein-Westfalen",
    "wof:name":"Stiftung Herzog Engelbert Charles Und Herzogin Mathildis",
    "wof:placetype":"venue"
},
  "geometry": {"coordinates":[6.8104348183,51.2418251038],"type":"Point"}
}