{
  "type": "Feature",
  "properties": {
    "iso:country":"DE",
    "sg:address":"Lupinenweg 14",
    "sg:city":"F\u00fcrth",
    "sg:phone":"+49 911/751319",
    "sg:postcode":"90768",
    "sg:province":"Bayern",
    "wof:name":"Luise Herget",
    "wof:placetype":"venue"
},
  "geometry": {"coordinates":[10.9337749481,49.4905891418],"type":"Point"}
}