{
  "type": "Feature",
  "properties": {
    "iso:country":"DE",
    "sg:address":"Birkenstr. 75",
    "sg:city":"Rastede",
    "sg:phone":"+49 4483/1288",
    "sg:postcode":"26180",
    "sg:province":"Niedersachsen",
    "wof:name":"Johann Westerholt",
    "wof:placetype":"venue"
},
  "geometry": {"coordinates":[8.28396,53.227032],"type":"Point"}
}