{
  "type": "Feature",
  "properties": {
    "iso:country":"DE",
    "sg:address":"Industriestr. 1",
    "sg:city":"Waldesch",
    "sg:phone":"+49 2628/987035",
    "sg:postcode":"56323",
    "sg:province":"Rheinland-Pfalz",
    "wof:name":"Bhg Bauservice- Grund- Und Tiefbau Gmbh",
    "wof:placetype":"venue"
},
  "geometry": {"coordinates":[7.5500450134,50.279712677],"type":"Point"}
}