{
  "type": "Feature",
  "properties": {
    "iso:country":"DE",
    "sg:address":"Lange Str. 100",
    "sg:city":"Steinhagen",
    "sg:phone":"+49 5204/3639",
    "sg:postcode":"33803",
    "sg:province":"Nordrhein-Westfalen",
    "wof:name":"G. Femmer",
    "wof:placetype":"venue"
},
  "geometry": {"coordinates":[8.4502,52.001202],"type":"Point"}
}