{
  "type": "Feature",
  "properties": {
    "iso:country":"DE",
    "sg:address":"Drostenweg 3 b",
    "sg:city":"Hage",
    "sg:phone":"+49 4931/984921",
    "sg:postcode":"26524",
    "sg:province":"Niedersachsen",
    "wof:name":"Tkf Gmbh & Co. Kg",
    "wof:placetype":"venue"
},
  "geometry": {"coordinates":[7.2870788574,53.6040306091],"type":"Point"}
}