{
  "type": "Feature",
  "properties": {
    "iso:country":"DE",
    "sg:address":"Burgwedeler Str. 25",
    "sg:city":"Isernhagen",
    "sg:postcode":"30916",
    "sg:province":"Niedersachsen",
    "wof:name":"Ganzheitliches Gesundheits- Centrum Kronsberg Kg",
    "wof:placetype":"venue"
},
  "geometry": {"coordinates":[9.789195,52.459351],"type":"Point"}
}