{
  "type": "Feature",
  "properties": {
    "iso:country":"DE",
    "sg:address":"Anna-Karbe-Str.16",
    "sg:city":"Gramzow",
    "sg:phone":"+49 39861/70510",
    "sg:postcode":"17291",
    "sg:province":"Brandenburg",
    "wof:name":"Agrargen. Eg",
    "wof:placetype":"venue"
},
  "geometry": {"coordinates":[14.0131702423,53.2132606506],"type":"Point"}
}