{
  "type": "Feature",
  "properties": {
    "iso:country":"DE",
    "sg:address":"Untere Burghalde 22",
    "sg:city":"Leonberg",
    "sg:phone":"+49 7152/75188",
    "sg:postcode":"71229",
    "sg:province":"Baden-W\u00fcrttemberg",
    "wof:name":"Alexander Sukatsch",
    "wof:placetype":"venue"
},
  "geometry": {"coordinates":[9.0204000473,48.8009376526],"type":"Point"}
}