{
  "type": "Feature",
  "properties": {
    "iso:country":"DE",
    "sg:address":"Brettener Str. 33 c",
    "sg:city":"Pforzheim",
    "sg:phone":"+49 7231/358693",
    "sg:postcode":"75177",
    "sg:province":"Baden-W\u00fcrttemberg",
    "wof:name":"Paul Augenstein",
    "wof:placetype":"venue"
},
  "geometry": {"coordinates":[8.7098960876,48.9006576538],"type":"Point"}
}