{
  "type": "Feature",
  "properties": {
    "iso:country":"DE",
    "sg:address":"Prinz-Eugen-Str. 20",
    "sg:city":"Villingen-Schwenningen",
    "sg:phone":"+49 7721/86347",
    "sg:postcode":"78048",
    "sg:province":"Baden-W\u00fcrttemberg",
    "wof:name":"Redaktion Forum Digital Kienzle Computersystem",
    "wof:placetype":"venue"
},
  "geometry": {"coordinates":[8.4539213181,48.0652618408],"type":"Point"}
}