{
  "type": "Feature",
  "properties": {
    "iso:country":"DE",
    "sg:address":"Im Schollengarten 5",
    "sg:city":"Bruchsal",
    "sg:phone":"+49 7257/1303",
    "sg:postcode":"76646",
    "sg:province":"Baden-W\u00fcrttemberg",
    "wof:name":"Hermann Schmitt Bau Gmbh",
    "wof:placetype":"venue"
},
  "geometry": {"coordinates":[8.5595340729,49.0948982239],"type":"Point"}
}