{
  "type": "Feature",
  "properties": {
    "iso:country":"DE",
    "sg:address":"R\u00f6merweg 1",
    "sg:city":"Dirlewang",
    "sg:phone":"+49 170 9367142",
    "sg:postcode":"87742",
    "sg:province":"Bayern",
    "wof:name":"Stefan Welzel Rechtsanwalt",
    "wof:placetype":"venue"
},
  "geometry": {"coordinates":[10.4976940155,48.0029373169],"type":"Point"}
}