{
  "type": "Feature",
  "properties": {
    "iso:country":"DE",
    "sg:address":"Mittelgasse 4",
    "sg:city":"Pfungstadt",
    "sg:phone":"+49 6157/3598",
    "sg:postcode":"64319",
    "sg:province":"Hessen",
    "wof:name":"Heinrich Nungesser",
    "wof:placetype":"venue"
},
  "geometry": {"coordinates":[8.597650528,49.8014717102],"type":"Point"}
}