{
  "type": "Feature",
  "properties": {
    "iso:country":"DE",
    "sg:address":"Junkersstr. 35/36",
    "sg:city":"Dessau",
    "sg:postcode":"06847",
    "sg:province":"Sachsen-Anhalt",
    "wof:name":"Gas- Und Elektroger\u00e4te Gmbh",
    "wof:placetype":"venue"
},
  "geometry": {"coordinates":[12.2115850449,51.8267593384],"type":"Point"}
}