{
  "type": "Feature",
  "properties": {
    "iso:country":"DE",
    "sg:address":"Lettenstr. 22",
    "sg:city":"Donzdorf",
    "sg:phone":"+49 7162/23907",
    "sg:postcode":"73072",
    "sg:province":"Baden-W\u00fcrttemberg",
    "wof:name":"Kaufmann & Partner Gmbh",
    "wof:placetype":"venue"
},
  "geometry": {"coordinates":[9.799627,48.709366],"type":"Point"}
}