{
  "type": "Feature",
  "properties": {
    "iso:country":"DE",
    "sg:address":"Bessunger Str. 131",
    "sg:city":"Griesheim",
    "sg:phone":"+49 6155/2393",
    "sg:postcode":"64347",
    "sg:province":"Hessen",
    "wof:name":"J. San-segundo",
    "wof:placetype":"venue"
},
  "geometry": {"coordinates":[8.5719041824,49.8585243225],"type":"Point"}
}