{
  "type": "Feature",
  "properties": {
    "iso:country":"DE",
    "sg:address":"Panoramaweg 29",
    "sg:city":"Schwaigern",
    "sg:phone":"+49 7138/6089",
    "sg:postcode":"74193",
    "sg:province":"Baden-W\u00fcrttemberg",
    "wof:name":"Christoph Templin",
    "wof:placetype":"venue"
},
  "geometry": {"coordinates":[8.985582,49.108742],"type":"Point"}
}