{
  "type": "Feature",
  "properties": {
    "iso:country":"DE",
    "sg:address":"Favoriteg\u00e4rten 55 b",
    "sg:city":"Ludwigsburg",
    "sg:phone":"+49 7141/904788",
    "sg:postcode":"71634",
    "sg:province":"Baden-W\u00fcrttemberg",
    "wof:name":"G. Ingelfinger",
    "wof:placetype":"venue"
},
  "geometry": {"coordinates":[9.1882390976,48.9032745361],"type":"Point"}
}