{
  "type": "Feature",
  "properties": {
    "iso:country":"DE",
    "sg:address":"Parkstr. 3",
    "sg:city":"Hofheim",
    "sg:phone":"+49 6198/8784",
    "sg:postcode":"65719",
    "sg:province":"Hessen",
    "wof:name":"Wildsachsenhalle Mehrzweckhalle",
    "wof:placetype":"venue"
},
  "geometry": {"coordinates":[8.362191,50.117489],"type":"Point"}
}