{
  "type": "Feature",
  "properties": {
    "iso:country":"DE",
    "sg:address":"Fischerhagen 46",
    "sg:city":"Petershagen",
    "sg:phone":"+49 5768/1297",
    "sg:postcode":"32469",
    "sg:province":"Nordrhein-Westfalen",
    "wof:name":"Heinz Hagemann",
    "wof:placetype":"venue"
},
  "geometry": {"coordinates":[9.050058,52.465618],"type":"Point"}
}