{
  "type": "Feature",
  "properties": {
    "iso:country":"DE",
    "sg:address":"Itterstr. 1",
    "sg:city":"Eberbach",
    "sg:phone":"+49 6271/71079",
    "sg:postcode":"69412",
    "sg:province":"Baden-W\u00fcrttemberg",
    "wof:name":"A & S Mediateam Werbeagentur Gmbh",
    "wof:placetype":"venue"
},
  "geometry": {"coordinates":[8.9831943512,49.4650650024],"type":"Point"}
}