{
  "type": "Feature",
  "properties": {
    "iso:country":"DE",
    "sg:address":"Siedlung 10",
    "sg:city":"Jesberg",
    "sg:phone":"+49 6695/1241",
    "sg:postcode":"34632",
    "sg:province":"Hessen",
    "wof:name":"Heinrich Kr\u00f6schel",
    "wof:placetype":"venue"
},
  "geometry": {"coordinates":[9.153409,50.99501],"type":"Point"}
}