{
  "type": "Feature",
  "properties": {
    "iso:country":"DE",
    "sg:address":"Radeweller Str. 10",
    "sg:city":"Halle",
    "sg:phone":"+49 345/7766002",
    "sg:postcode":"06132",
    "sg:province":"Sachsen-Anhalt",
    "wof:name":"M. Dittmann",
    "wof:placetype":"venue"
},
  "geometry": {"coordinates":[11.997446,51.424103],"type":"Point"}
}