{
  "type": "Feature",
  "properties": {
    "iso:country":"DE",
    "sg:address":"Oelder Str. 34",
    "sg:city":"Beckum",
    "sg:phone":"+49 2521/6011",
    "sg:postcode":"59269",
    "sg:province":"Nordrhein-Westfalen",
    "wof:name":"Moorfeld & Scheiperpeter Ohg",
    "wof:placetype":"venue"
},
  "geometry": {"coordinates":[8.04545784,51.7618789673],"type":"Point"}
}