{
  "type": "Feature",
  "properties": {
    "iso:country":"DE",
    "sg:address":"W\u00fcrzburger Str. 7 - 11",
    "sg:city":"Bad Orb",
    "sg:phone":"+49 6052/870",
    "sg:postcode":"63619",
    "sg:province":"Hessen",
    "wof:name":"Spessart-klinik Bad Orb Dienstleistungsges. Mbh",
    "wof:placetype":"venue"
},
  "geometry": {"coordinates":[9.349856,50.226978],"type":"Point"}
}