{
  "type": "Feature",
  "properties": {
    "iso:country":"DE",
    "sg:address":"Burhaver Str. 267",
    "sg:city":"Nordenham",
    "sg:phone":"+49 4731/39418",
    "sg:postcode":"26954",
    "sg:province":"Niedersachsen",
    "wof:name":"Holger Jan\u00dfen",
    "wof:placetype":"venue"
},
  "geometry": {"coordinates":[8.4693698883,53.5328788757],"type":"Point"}
}