{
  "type": "Feature",
  "properties": {
    "iso:country":"DE",
    "sg:address":"Liebigweg 8",
    "sg:city":"Neufahrn",
    "sg:phone":"+49 8165/61433",
    "sg:postcode":"85375",
    "sg:province":"Bayern",
    "wof:name":"E. Engel",
    "wof:placetype":"venue"
},
  "geometry": {"coordinates":[11.6713790894,48.3103942871],"type":"Point"}
}