{
  "type": "Feature",
  "properties": {
    "iso:country":"DE",
    "sg:address":"Marktplatz 8",
    "sg:city":"Amorbach",
    "sg:phone":"+49 9373/902565",
    "sg:postcode":"63916",
    "sg:province":"Bayern",
    "wof:name":"Karl Schirm",
    "wof:placetype":"venue"
},
  "geometry": {"coordinates":[9.219585,49.645157],"type":"Point"}
}