{
  "type": "Feature",
  "properties": {
    "iso:country":"DE",
    "sg:address":"Schillerstr. 1",
    "sg:city":"Johanngeorgenstadt",
    "sg:phone":"+49 3773/2164",
    "sg:postcode":"08349",
    "sg:province":"Sachsen",
    "wof:name":"Poly Profil",
    "wof:placetype":"venue"
},
  "geometry": {"coordinates":[12.715087,50.43243],"type":"Point"}
}