{
  "type": "Feature",
  "properties": {
    "iso:country":"DE",
    "sg:address":"Staatsbahnhofstr. 2 A",
    "sg:city":"Wiesloch",
    "sg:postcode":"69168",
    "sg:province":"Baden-W\u00fcrttemberg",
    "wof:name":"Holzbau Berger & Heitzler Gmbh",
    "wof:placetype":"venue"
},
  "geometry": {"coordinates":[8.6664485931,49.2916755676],"type":"Point"}
}