{
  "type": "Feature",
  "properties": {
    "iso:country":"DE",
    "sg:address":"Hinter dem Hainzaun 5",
    "sg:city":"Neu-Anspach",
    "sg:phone":"+49 6081/41880",
    "sg:postcode":"61267",
    "sg:province":"Hessen",
    "wof:name":"Siegfried Lohnstein",
    "wof:placetype":"venue"
},
  "geometry": {"coordinates":[8.488212,50.300976],"type":"Point"}
}