{
  "type": "Feature",
  "properties": {
    "iso:country":"DE",
    "sg:address":"Schulstr. 32",
    "sg:city":"Wilthen",
    "sg:phone":"+49 3592/31624",
    "sg:postcode":"02681",
    "sg:province":"Sachsen",
    "wof:name":"Hannelore Renner",
    "wof:placetype":"venue"
},
  "geometry": {"coordinates":[14.3951263428,51.0990715027],"type":"Point"}
}