{
  "type": "Feature",
  "properties": {
    "iso:country":"DE",
    "sg:address":"Rimbachstr. 4",
    "sg:city":"Suhl",
    "sg:phone":"+49 3681/724055",
    "sg:postcode":"98527",
    "sg:province":"Th\u00fcringen",
    "wof:name":"First-reiseb\u00fcro Gmbh",
    "wof:placetype":"venue"
},
  "geometry": {"coordinates":[10.6937322617,50.6093521118],"type":"Point"}
}