{
  "type": "Feature",
  "properties": {
    "iso:country":"DE",
    "sg:address":"Kirschenstr. 32",
    "sg:city":"Viernheim",
    "sg:phone":"+49 6204/2714",
    "sg:postcode":"68519",
    "sg:province":"Hessen",
    "wof:name":"Arthur Lutz",
    "wof:placetype":"venue"
},
  "geometry": {"coordinates":[8.574459,49.54377],"type":"Point"}
}