{
  "type": "Feature",
  "properties": {
    "iso:country":"DE",
    "sg:address":"Schillerstr. 60",
    "sg:city":"Zeuthen",
    "sg:phone":"+49 33762/92415",
    "sg:postcode":"15738",
    "sg:province":"Brandenburg",
    "wof:name":"Baugrund Berlin Bohrgesellschaft Mbh",
    "wof:placetype":"venue"
},
  "geometry": {"coordinates":[13.624987,52.362049],"type":"Point"}
}