{
  "type": "Feature",
  "properties": {
    "iso:country":"DE",
    "sg:address":"L\u00f6bdergraben 32",
    "sg:city":"Jena",
    "sg:postcode":"07743",
    "sg:province":"Th\u00fcringen",
    "wof:name":"Bnm-ges. F\u00fcr Die Bearbeitung Neuer Materialien Und",
    "wof:placetype":"venue"
},
  "geometry": {"coordinates":[11.587596,50.926804],"type":"Point"}
}