{
  "type": "Feature",
  "properties": {
    "iso:country":"DE",
    "sg:address":"Bahnhofplatz 3",
    "sg:city":"Rheinfelden",
    "sg:phone":"+49 7623/20559",
    "sg:postcode":"79618",
    "sg:province":"Baden-W\u00fcrttemberg",
    "wof:name":"R\u00f6mer-apotheke Hildegard Fischer",
    "wof:placetype":"venue"
},
  "geometry": {"coordinates":[7.732826,47.556366],"type":"Point"}
}