{
  "type": "Feature",
  "properties": {
    "iso:country":"DE",
    "sg:address":"Blumenweg 28",
    "sg:city":"Wei\u00dfenstadt",
    "sg:phone":"+49 9253/446",
    "sg:postcode":"95163",
    "sg:province":"Bayern",
    "wof:name":"Gerhard Hager Versicherungsmakler Gmbh",
    "wof:placetype":"venue"
},
  "geometry": {"coordinates":[11.8846540451,50.1071510315],"type":"Point"}
}