{
  "type": "Feature",
  "properties": {
    "iso:country":"DE",
    "sg:address":"Weiher-Passage 3",
    "sg:city":"Wiehl",
    "sg:phone":"+49 2262/91129",
    "sg:postcode":"51674",
    "sg:province":"Nordrhein-Westfalen",
    "wof:name":"U. Giurukidu",
    "wof:placetype":"venue"
},
  "geometry": {"coordinates":[7.547281,50.949715],"type":"Point"}
}