{
  "type": "Feature",
  "properties": {
    "iso:country":"DE",
    "sg:address":"Nordenheideweg 8",
    "sg:city":"Hamm",
    "sg:phone":"+49 2381/671528",
    "sg:postcode":"59065",
    "sg:province":"Nordrhein-Westfalen",
    "wof:name":"D. Hecker",
    "wof:placetype":"venue"
},
  "geometry": {"coordinates":[7.8000998497,51.6905059814],"type":"Point"}
}