{
  "type": "Feature",
  "properties": {
    "iso:country":"DE",
    "sg:address":"Pitterer Siedlung 16",
    "sg:city":"Offenberg",
    "sg:phone":"+49 9905/247",
    "sg:postcode":"94560",
    "sg:province":"Bayern",
    "wof:name":"R. Stiglmeier",
    "wof:placetype":"venue"
},
  "geometry": {"coordinates":[12.8976602554,48.8810424805],"type":"Point"}
}