{
  "type": "Feature",
  "properties": {
    "iso:country":"DE",
    "sg:address":"Paumgartnerstr. 20",
    "sg:city":"N\u00fcrnberg",
    "sg:phone":"+49 911/267303",
    "sg:postcode":"90429",
    "sg:province":"Bayern",
    "wof:name":"Dieter Augustin",
    "wof:placetype":"venue"
},
  "geometry": {"coordinates":[11.0481395721,49.4513511658],"type":"Point"}
}