{
  "type": "Feature",
  "properties": {
    "iso:country":"DE",
    "sg:address":"Kirchstr. 26",
    "sg:city":"N\u00fcrtingen",
    "sg:phone":"+49 7022/35170",
    "sg:postcode":"72622",
    "sg:province":"Baden-W\u00fcrttemberg",
    "wof:name":"Dieter Schwarz",
    "wof:placetype":"venue"
},
  "geometry": {"coordinates":[9.3402891159,48.626121521],"type":"Point"}
}