{
  "type": "Feature",
  "properties": {
    "iso:country":"DE",
    "sg:address":"Max-von-Laue-Str. 36",
    "sg:city":"W\u00fcrzburg",
    "sg:phone":"+49 931/970680",
    "sg:postcode":"97080",
    "sg:province":"Bayern",
    "wof:name":"Offsetreproduktion Held Gmbh",
    "wof:placetype":"venue"
},
  "geometry": {"coordinates":[9.885601,49.814976],"type":"Point"}
}