{
  "type": "Feature",
  "properties": {
    "iso:country":"DE",
    "sg:address":"Am Kirschgarten 9",
    "sg:city":"Neustadt",
    "sg:phone":"+49 6321/481237",
    "sg:postcode":"67434",
    "sg:province":"Rheinland-Pfalz",
    "wof:name":"Eugen Anton Steuerberater",
    "wof:placetype":"venue"
},
  "geometry": {"coordinates":[8.1290531158,49.327041626],"type":"Point"}
}