{
  "type": "Feature",
  "properties": {
    "iso:country":"DE",
    "sg:address":"Graflinger Str. 222",
    "sg:city":"Deggendorf",
    "sg:phone":"+49 991/29610",
    "sg:postcode":"94469",
    "sg:province":"Bayern",
    "wof:name":"Eiberweiser Service Gmbh",
    "wof:placetype":"venue"
},
  "geometry": {"coordinates":[12.9622411728,48.8562698364],"type":"Point"}
}