{
  "type": "Feature",
  "properties": {
    "iso:country":"DE",
    "sg:address":"Bahnhofstr.",
    "sg:city":"M\u00fchlacker",
    "sg:postcode":"75417",
    "sg:province":"Baden-W\u00fcrttemberg",
    "wof:name":"Wohnpark Goldshalde In M\u00fchlacker",
    "wof:placetype":"venue"
},
  "geometry": {"coordinates":[8.84025,48.948975],"type":"Point"}
}