{
  "type": "Feature",
  "properties": {
    "iso:country":"DE",
    "sg:address":"Zellertalstr. 5",
    "sg:city":"Worms",
    "sg:phone":"+49 6247/5412",
    "sg:postcode":"67551",
    "sg:province":"Rheinland-Pfalz",
    "wof:name":"Rewe Markt",
    "wof:placetype":"venue"
},
  "geometry": {"coordinates":[8.2694702148,49.6326789856],"type":"Point"}
}