{
  "type": "Feature",
  "properties": {
    "iso:country":"DE",
    "sg:address":"Tiefer Weg 2",
    "sg:city":"Kreiensen",
    "sg:phone":"+49 5563/1608",
    "sg:postcode":"37547",
    "sg:province":"Niedersachsen",
    "wof:name":"Dieter Schillig",
    "wof:placetype":"venue"
},
  "geometry": {"coordinates":[9.926965,51.892361],"type":"Point"}
}