{
  "type": "Feature",
  "properties": {
    "iso:country":"DE",
    "sg:address":"Kirchstr. 35",
    "sg:city":"Remseck",
    "sg:phone":"+49 7146/893050",
    "sg:postcode":"71686",
    "sg:province":"Baden-W\u00fcrttemberg",
    "wof:name":"Kleeblatt",
    "wof:placetype":"venue"
},
  "geometry": {"coordinates":[9.253555,48.865734],"type":"Point"}
}