{
  "type": "Feature",
  "properties": {
    "iso:country":"DE",
    "sg:address":"An der Leite 1",
    "sg:city":"Jena",
    "sg:phone":"+49 3641/638560",
    "sg:postcode":"07749",
    "sg:province":"Th\u00fcringen",
    "wof:name":"Timing-systems",
    "wof:placetype":"venue"
},
  "geometry": {"coordinates":[11.599375,50.928654],"type":"Point"}
}