{
  "type": "Feature",
  "properties": {
    "iso:country":"DE",
    "sg:address":"Altenhofer Weg 50",
    "sg:city":"Wetter",
    "sg:phone":"+49 5734/91090",
    "sg:postcode":"58300",
    "sg:province":"Nordrhein-Westfalen",
    "wof:name":"Spedition Gebr. Schr\u00f6der Gmbh",
    "wof:placetype":"venue"
},
  "geometry": {"coordinates":[8.7420969009,52.2385635376],"type":"Point"}
}