{
  "type": "Feature",
  "properties": {
    "iso:country":"DE",
    "sg:address":"Portitzer Allee 4",
    "sg:city":"Leipzig",
    "sg:phone":"+49 341/2508300",
    "sg:postcode":"04329",
    "sg:province":"Sachsen",
    "wof:name":"Raab Karcher Baustoffe",
    "wof:placetype":"venue"
},
  "geometry": {"coordinates":[12.4624872208,51.3655548096],"type":"Point"}
}