{
  "type": "Feature",
  "properties": {
    "iso:country":"DE",
    "sg:address":"Paulinenstr. 68",
    "sg:city":"Detmold",
    "sg:phone":"+49 5231/29197",
    "sg:postcode":"32756",
    "sg:province":"Nordrhein-Westfalen",
    "wof:name":"Roswitha Schad",
    "wof:placetype":"venue"
},
  "geometry": {"coordinates":[8.875888,51.941383],"type":"Point"}
}