{
  "type": "Feature",
  "properties": {
    "iso:country":"DE",
    "sg:address":"Bodenstedtstr. 1",
    "sg:city":"Peine",
    "sg:phone":"+49 5171/17301",
    "sg:postcode":"31224",
    "sg:province":"Niedersachsen",
    "wof:name":"Heinrich Ebermann",
    "wof:placetype":"venue"
},
  "geometry": {"coordinates":[10.2293119431,52.3220825195],"type":"Point"}
}