{
  "type": "Feature",
  "properties": {
    "iso:country":"DE",
    "sg:address":"Bahnhofstr. 37",
    "sg:city":"Hettstedt",
    "sg:phone":"+49 3476/813088",
    "sg:postcode":"06333",
    "sg:province":"Sachsen-Anhalt",
    "wof:name":"Reinhard Schulz",
    "wof:placetype":"venue"
},
  "geometry": {"coordinates":[11.510081,51.637878],"type":"Point"}
}