{
  "type": "Feature",
  "properties": {
    "iso:country":"DE",
    "sg:address":"Hochgerichtstr. 33",
    "sg:city":"Dornstetten",
    "sg:phone":"+49 4974/4396330",
    "sg:postcode":"72280",
    "sg:province":"Baden-W\u00fcrttemberg",
    "wof:name":"Klaeger Spritzguss Gmbh & Co. Kg",
    "wof:placetype":"venue"
},
  "geometry": {"coordinates":[8.4890642166,48.4752731323],"type":"Point"}
}