{
  "type": "Feature",
  "properties": {
    "iso:country":"DE",
    "sg:address":"Hainerter Str. 4",
    "sg:city":"Knetzgau",
    "sg:phone":"+49 9529/922317",
    "sg:postcode":"97478",
    "sg:province":"Bayern",
    "wof:name":"Schwimmbad",
    "wof:placetype":"venue"
},
  "geometry": {"coordinates":[10.5481004715,49.9931335449],"type":"Point"}
}