{
  "type": "Feature",
  "properties": {
    "iso:country":"DE",
    "sg:address":"Sch\u00fctzenstr. 127",
    "sg:city":"Ochtrup",
    "sg:phone":"+49 2553/3043",
    "sg:postcode":"48607",
    "sg:province":"Nordrhein-Westfalen",
    "wof:name":"M. Schebera",
    "wof:placetype":"venue"
},
  "geometry": {"coordinates":[7.208371,52.203167],"type":"Point"}
}