{
  "type": "Feature",
  "properties": {
    "iso:country":"DE",
    "sg:address":"Sachsenfeld 2",
    "sg:city":"Hamburg",
    "sg:phone":"+49 40/23650001",
    "sg:postcode":"20097",
    "sg:province":"Hamburg",
    "wof:name":"Aachener Und M\u00fcnchener Lebensversicherung Ag",
    "wof:placetype":"venue"
},
  "geometry": {"coordinates":[10.0225830078,53.5449447632],"type":"Point"}
}