{
  "type": "Feature",
  "properties": {
    "iso:country":"DE",
    "sg:address":"Gartenstr. 8",
    "sg:city":"Bad Feilnbach",
    "sg:phone":"+49 8066/701",
    "sg:postcode":"83075",
    "sg:province":"Bayern",
    "wof:name":"Volksb\u00fccherei",
    "wof:placetype":"venue"
},
  "geometry": {"coordinates":[12.006273,47.772488],"type":"Point"}
}