{
  "type": "Feature",
  "properties": {
    "iso:country":"DE",
    "sg:address":"Norderende 6",
    "sg:city":"Bordelum",
    "sg:phone":"+49 4671/930418",
    "sg:postcode":"25852",
    "sg:province":"Schleswig-Holstein",
    "wof:name":"Volker Brauer",
    "wof:placetype":"venue"
},
  "geometry": {"coordinates":[8.9411973953,54.6332015991],"type":"Point"}
}