{
  "type": "Feature",
  "properties": {
    "iso:country":"DE",
    "sg:address":"Lorenz-Sandler-Str. 10",
    "sg:city":"Kulmbach",
    "sg:phone":"+49 9221/87410",
    "sg:postcode":"95326",
    "sg:province":"Bayern",
    "wof:name":"Dr. Med. Uwe Kirsten Arzt F\u00fcr Allgemeinmedizin",
    "wof:placetype":"venue"
},
  "geometry": {"coordinates":[11.4467039108,50.1173553467],"type":"Point"}
}