{
  "type": "Feature",
  "properties": {
    "iso:country":"DE",
    "sg:address":"Porta-Nigra-Platz",
    "sg:city":"Trier",
    "sg:phone":"+49 651/48042",
    "sg:postcode":"54292",
    "sg:province":"Rheinland-Pfalz",
    "wof:name":"Altstadthotel",
    "wof:placetype":"venue"
},
  "geometry": {"coordinates":[6.6439170837,49.7602043152],"type":"Point"}
}