{
  "type": "Feature",
  "properties": {
    "iso:country":"DE",
    "sg:address":"Am Surck 3",
    "sg:city":"Dortmund",
    "sg:phone":"+49 231/711233",
    "sg:postcode":"44225",
    "sg:province":"Nordrhein-Westfalen",
    "wof:name":"Albert Kukuk",
    "wof:placetype":"venue"
},
  "geometry": {"coordinates":[7.436247,51.482262],"type":"Point"}
}