{
  "type": "Feature",
  "properties": {
    "iso:country":"DE",
    "sg:address":"Friedrich-Engels-Str. 68",
    "sg:city":"Wildau",
    "sg:phone":"+49 3375/501251",
    "sg:postcode":"15745",
    "sg:province":"Brandenburg",
    "wof:name":"Elektrodienst Simroth",
    "wof:placetype":"venue"
},
  "geometry": {"coordinates":[13.6380252838,52.3264846802],"type":"Point"}
}