{
  "type": "Feature",
  "properties": {
    "iso:country":"DE",
    "sg:address":"Eichenstr. 116",
    "sg:city":"Hilden",
    "sg:phone":"+49 2103/360060",
    "sg:postcode":"40721",
    "sg:province":"Nordrhein-Westfalen",
    "wof:name":"Thomas Peckhaus",
    "wof:placetype":"venue"
},
  "geometry": {"coordinates":[6.9071121216,51.1638069153],"type":"Point"}
}