{
  "type": "Feature",
  "properties": {
    "iso:country":"DE",
    "sg:address":"August-Bebel-Str. 51",
    "sg:city":"Zschorlau",
    "sg:phone":"+49 3771/458125",
    "sg:postcode":"08321",
    "sg:province":"Sachsen",
    "wof:name":"Manfred Dittrich",
    "wof:placetype":"venue"
},
  "geometry": {"coordinates":[12.6484937668,50.5675888062],"type":"Point"}
}