{
  "type": "Feature",
  "properties": {
    "iso:country":"DE",
    "sg:address":"Fuldastr. 4",
    "sg:city":"Baunatal",
    "sg:phone":"+49 5665/8150",
    "sg:postcode":"34225",
    "sg:province":"Hessen",
    "wof:name":"Garten-center Gr\u00fcnwald Gmbh & Co. Kg",
    "wof:placetype":"venue"
},
  "geometry": {"coordinates":[9.431011,51.227898],"type":"Point"}
}