{
  "type": "Feature",
  "properties": {
    "iso:country":"DE",
    "sg:address":"Walkerdamm 1",
    "sg:city":"Kiel",
    "sg:phone":"+49 431/66330",
    "sg:postcode":"24103",
    "sg:province":"Schleswig-Holstein",
    "wof:name":"Bhw Bausparkasse Ag",
    "wof:placetype":"venue"
},
  "geometry": {"coordinates":[10.130917,54.318928],"type":"Point"}
}