{
  "type": "Feature",
  "properties": {
    "iso:country":"DE",
    "sg:address":"Havelberger Str. 18",
    "sg:city":"Berlin",
    "sg:phone":"+49 30/3953508",
    "sg:postcode":"10559",
    "sg:province":"Berlin",
    "wof:name":"Biberbau Parkett- Und Bodenlegerei Gmbh",
    "wof:placetype":"venue"
},
  "geometry": {"coordinates":[13.3469009399,52.5343780518],"type":"Point"}
}