{
  "type": "Feature",
  "properties": {
    "iso:country":"DE",
    "sg:address":"Hauptstr. 1",
    "sg:city":"Apfelst\u00e4dt",
    "sg:phone":"+49 36202/90205",
    "sg:postcode":"99192",
    "sg:province":"Th\u00fcringen",
    "wof:name":"Restaurant Im Schlo\u00df Molsdorf",
    "wof:placetype":"venue"
},
  "geometry": {"coordinates":[10.8837127686,50.9006729126],"type":"Point"}
}