{
  "type": "Feature",
  "properties": {
    "iso:country":"DE",
    "sg:address":"\u00c4hrenweg 8",
    "sg:city":"Bayreuth",
    "sg:phone":"+49 9209/305",
    "sg:postcode":"95448",
    "sg:province":"Bayern",
    "wof:name":"Hans Bauernfeind",
    "wof:placetype":"venue"
},
  "geometry": {"coordinates":[11.609263,49.908375],"type":"Point"}
}