{
  "type": "Feature",
  "properties": {
    "iso:country":"DE",
    "sg:address":"Blankenburger Str. 25",
    "sg:city":"Magdeburg",
    "sg:phone":"+49 391/6200166",
    "sg:postcode":"39118",
    "sg:province":"Sachsen-Anhalt",
    "wof:name":"Pension Dirk Lorenz",
    "wof:placetype":"venue"
},
  "geometry": {"coordinates":[11.5981140137,52.1010017395],"type":"Point"}
}