{
  "type": "Feature",
  "properties": {
    "iso:country":"DE",
    "sg:address":"Fridtjof-Nansen-Str. 2",
    "sg:city":"Traunreut",
    "sg:phone":"+49 8669/901209",
    "sg:postcode":"83301",
    "sg:province":"Bayern",
    "wof:name":"Optik Trieb",
    "wof:placetype":"venue"
},
  "geometry": {"coordinates":[12.5936803818,47.9615974426],"type":"Point"}
}