{
  "type": "Feature",
  "properties": {
    "iso:country":"DE",
    "sg:address":"Rudolf-Breitscheid-Str. 22a",
    "sg:city":"Zwickau",
    "sg:phone":"+49 375/784902",
    "sg:postcode":"08062",
    "sg:province":"Sachsen",
    "wof:name":"Helmut Liebsch",
    "wof:placetype":"venue"
},
  "geometry": {"coordinates":[12.469629,50.69138],"type":"Point"}
}