{
  "type": "Feature",
  "properties": {
    "iso:country":"DE",
    "sg:address":"Erzbach 4",
    "sg:city":"Biberach",
    "sg:phone":"+49 7835/7114",
    "sg:postcode":"77781",
    "sg:province":"Baden-W\u00fcrttemberg",
    "wof:name":"G\u00fcnter Lerch",
    "wof:placetype":"venue"
},
  "geometry": {"coordinates":[8.00922,48.345226],"type":"Point"}
}