{
  "type": "Feature",
  "properties": {
    "iso:country":"DE",
    "sg:address":"Zum Wiesengrund 7",
    "sg:city":"Machern",
    "sg:postcode":"04827",
    "sg:province":"Sachsen",
    "wof:name":"Uwf Beratungs- & Managementges. Mbh",
    "wof:placetype":"venue"
},
  "geometry": {"coordinates":[12.6405878067,51.354888916],"type":"Point"}
}