{
  "type": "Feature",
  "properties": {
    "iso:country":"DE",
    "sg:address":"Edisonstr. 44",
    "sg:city":"Berlin",
    "sg:phone":"+49 30/5358861",
    "sg:postcode":"12459",
    "sg:province":"Berlin",
    "wof:name":"Harald Grothe",
    "wof:placetype":"venue"
},
  "geometry": {"coordinates":[13.51311,52.465897],"type":"Point"}
}