{
  "type": "Feature",
  "properties": {
    "iso:country":"DE",
    "sg:address":"Moosacher Str. 32b",
    "sg:city":"M\u00fcnchen",
    "sg:phone":"+49 89/32714412",
    "sg:postcode":"80809",
    "sg:province":"Bayern",
    "wof:name":"Schilcher Transporte Gmbh",
    "wof:placetype":"venue"
},
  "geometry": {"coordinates":[11.5567531586,48.1867866516],"type":"Point"}
}