{
  "type": "Feature",
  "properties": {
    "iso:country":"DE",
    "sg:address":"Holzweg 69",
    "sg:city":"Aurich",
    "sg:phone":"+49 4941/18522",
    "sg:postcode":"26605",
    "sg:province":"Niedersachsen",
    "wof:name":"Johannes Henkel",
    "wof:placetype":"venue"
},
  "geometry": {"coordinates":[7.551491,53.496517],"type":"Point"}
}