{
  "type": "Feature",
  "properties": {
    "iso:country":"DE",
    "sg:address":"Kapellenstr. 40",
    "sg:city":"Mandelbachtal",
    "sg:phone":"+49 6893/986707",
    "sg:postcode":"66399",
    "sg:province":"Saarland",
    "wof:name":"Berthold Vogelgesang",
    "wof:placetype":"venue"
},
  "geometry": {"coordinates":[7.14383,49.195274],"type":"Point"}
}