{
  "type": "Feature",
  "properties": {
    "iso:country":"DE",
    "sg:address":"Altensteiger Str. 9",
    "sg:city":"Simmersfeld",
    "sg:phone":"+49 7484/357",
    "sg:postcode":"72226",
    "sg:province":"Baden-W\u00fcrttemberg",
    "wof:name":"Hirsch",
    "wof:placetype":"venue"
},
  "geometry": {"coordinates":[8.5183877945,48.6212005615],"type":"Point"}
}