{
  "type": "Feature",
  "properties": {
    "iso:country":"DE",
    "sg:address":"Friedrich-Ebert-Str. 2",
    "sg:city":"Laudenbach",
    "sg:phone":"+49 6201/75257",
    "sg:postcode":"69514",
    "sg:province":"Baden-W\u00fcrttemberg",
    "wof:name":"Katholisches Pfarramt St. Bartholom\u00e4us",
    "wof:placetype":"venue"
},
  "geometry": {"coordinates":[8.6512641907,49.6113891602],"type":"Point"}
}