{
  "type": "Feature",
  "properties": {
    "iso:country":"DE",
    "sg:address":"Hauptstr. 21",
    "sg:city":"Bad Windsheim",
    "sg:phone":"+49 9841/1796",
    "sg:postcode":"91438",
    "sg:province":"Bayern",
    "wof:name":"Leonhard Wust",
    "wof:placetype":"venue"
},
  "geometry": {"coordinates":[10.434338,49.479046],"type":"Point"}
}