{
  "type": "Feature",
  "properties": {
    "iso:country":"DE",
    "sg:address":"Vor der Pforte 17",
    "sg:city":"Dreieich",
    "sg:phone":"+49 6103/88287",
    "sg:postcode":"63303",
    "sg:province":"Hessen",
    "wof:name":"P. Waschek",
    "wof:placetype":"venue"
},
  "geometry": {"coordinates":[8.735619545,50.0008010864],"type":"Point"}
}