{
  "type": "Feature",
  "properties": {
    "iso:country":"DE",
    "sg:address":"Klausengarten 6",
    "sg:city":"W\u00f6llstein",
    "sg:phone":"+49 6703/1354",
    "sg:postcode":"55597",
    "sg:province":"Rheinland-Pfalz",
    "wof:name":"Heinrich Singer",
    "wof:placetype":"venue"
},
  "geometry": {"coordinates":[7.9568538666,49.8137626648],"type":"Point"}
}