{
  "type": "Feature",
  "properties": {
    "iso:country":"DE",
    "sg:address":"Beim Elbkurhaus 13",
    "sg:city":"Hamburg",
    "sg:postcode":"22587",
    "sg:province":"Hamburg",
    "wof:name":"Alkraha Gmbh",
    "wof:placetype":"venue"
},
  "geometry": {"coordinates":[9.8218870163,53.5545082092],"type":"Point"}
}