{
  "type": "Feature",
  "properties": {
    "iso:country":"DE",
    "sg:address":"Werner-Siemens-Str. 64",
    "sg:city":"Pforzheim",
    "sg:postcode":"75173",
    "sg:province":"Baden-W\u00fcrttemberg",
    "wof:name":"Extratours - Gruppenreisen Mit Dem Auto",
    "wof:placetype":"venue"
},
  "geometry": {"coordinates":[8.6814022064,48.88646698],"type":"Point"}
}