{
  "type": "Feature",
  "properties": {
    "iso:country":"DE",
    "sg:address":"Wilhelmstra\u00dfe 61",
    "sg:city":"Aachen",
    "sg:postcode":"52070",
    "sg:province":"Nordrhein-Westfalen",
    "wof:name":"Anwaltskanzlei Friedhoff, Mauer & Pampfer",
    "wof:placetype":"venue"
},
  "geometry": {"coordinates":[6.095882,50.771744],"type":"Point"}
}