{
  "type": "Feature",
  "properties": {
    "iso:country":"DE",
    "sg:address":"Haingrabengasse 2",
    "sg:city":"M\u00fchlheim",
    "sg:postcode":"63165",
    "sg:province":"Hessen",
    "wof:name":"D. K\u00fchn Hebamme",
    "wof:placetype":"venue"
},
  "geometry": {"coordinates":[8.830444,50.124939],"type":"Point"}
}