{
  "type": "Feature",
  "properties": {
    "iso:country":"DE",
    "sg:address":"Ignaz-Sch\u00f6n-Str. 11",
    "sg:city":"Schweinfurt",
    "sg:phone":"+49 9721/9405",
    "sg:postcode":"97421",
    "sg:province":"Bayern",
    "wof:name":"Bibliothek Der Fachhochschule W\u00fcrzburg",
    "wof:placetype":"venue"
},
  "geometry": {"coordinates":[10.209431,50.04549],"type":"Point"}
}