{
  "type": "Feature",
  "properties": {
    "iso:country":"DE",
    "sg:address":"Lindenstr. 49",
    "sg:city":"H\u00fcffenhardt",
    "sg:phone":"+49 6268/339",
    "sg:postcode":"74928",
    "sg:province":"Baden-W\u00fcrttemberg",
    "wof:name":"Berthold Labitzke",
    "wof:placetype":"venue"
},
  "geometry": {"coordinates":[9.060137,49.316151],"type":"Point"}
}