{
  "type": "Feature",
  "properties": {
    "iso:country":"DE",
    "sg:address":"Entenstrich 2",
    "sg:city":"Mannheim",
    "sg:phone":"+49 621/476922",
    "sg:postcode":"68229",
    "sg:province":"Baden-W\u00fcrttemberg",
    "wof:name":"Werner Rothermel",
    "wof:placetype":"venue"
},
  "geometry": {"coordinates":[8.570138,49.429028],"type":"Point"}
}