{
  "type": "Feature",
  "properties": {
    "iso:country":"DE",
    "sg:address":"G\u00f6rlitzer Str. 14",
    "sg:city":"Lohsa",
    "sg:postcode":"02999",
    "sg:province":"Sachsen",
    "wof:name":"Deutsche Verm\u00f6gensberatung",
    "wof:placetype":"venue"
},
  "geometry": {"coordinates":[14.4067869186,51.3831062317],"type":"Point"}
}