{
  "type": "Feature",
  "properties": {
    "iso:country":"DE",
    "sg:address":"In der Scheib",
    "sg:city":"Pfalzfeld",
    "sg:postcode":"56291",
    "sg:province":"Rheinland-Pfalz",
    "wof:name":"Heinrich Frey Gmbh",
    "wof:placetype":"venue"
},
  "geometry": {"coordinates":[7.5997171402,50.1164283752],"type":"Point"}
}