{
  "type": "Feature",
  "properties": {
    "iso:country":"DE",
    "sg:address":"Weinhof 8",
    "sg:city":"Ulm",
    "sg:phone":"+49 731/63570",
    "sg:postcode":"89073",
    "sg:province":"Baden-W\u00fcrttemberg",
    "wof:name":"Willi Gienger",
    "wof:placetype":"venue"
},
  "geometry": {"coordinates":[9.98923,48.396561],"type":"Point"}
}