{
  "type": "Feature",
  "properties": {
    "iso:country":"DE",
    "sg:address":"Ziegelgasse 6",
    "sg:city":"Neunkirchen",
    "sg:phone":"+49 9378/1558",
    "sg:postcode":"63930",
    "sg:province":"Bayern",
    "wof:name":"U. Horn",
    "wof:placetype":"venue"
},
  "geometry": {"coordinates":[9.402062,49.708481],"type":"Point"}
}