{
  "type": "Feature",
  "properties": {
    "iso:country":"DE",
    "sg:address":"Markt 1",
    "sg:city":"L\u00fcdinghausen",
    "sg:phone":"+49 2591/5465",
    "sg:postcode":"59348",
    "sg:province":"Nordrhein-Westfalen",
    "wof:name":"Blumenst\u00fcbchen",
    "wof:placetype":"venue"
},
  "geometry": {"coordinates":[7.44492,51.771645],"type":"Point"}
}