{
  "type": "Feature",
  "properties": {
    "iso:country":"DE",
    "sg:address":"Friedberger Landstr. 293",
    "sg:city":"Frankfurt",
    "sg:phone":"+49 69/9591130",
    "sg:postcode":"60389",
    "sg:province":"Hessen",
    "wof:name":"N. R. L\u00f6ffler Gmbh",
    "wof:placetype":"venue"
},
  "geometry": {"coordinates":[8.6971931458,50.1378135681],"type":"Point"}
}