{
  "type": "Feature",
  "properties": {
    "iso:country":"DE",
    "sg:address":"Duisburger Str. 103",
    "sg:city":"Dinslaken",
    "sg:phone":"+49 2064/414510",
    "sg:postcode":"46535",
    "sg:province":"Nordrhein-Westfalen",
    "wof:name":"Verein F\u00fcr Vormundschaften Im Diakon. Werk D. Kirchenkreises",
    "wof:placetype":"venue"
},
  "geometry": {"coordinates":[6.7321162224,51.557598114],"type":"Point"}
}