{
  "type": "Feature",
  "properties": {
    "iso:country":"DE",
    "sg:address":"Menzinger Str. 123",
    "sg:city":"M\u00fcnchen",
    "sg:phone":"+49 89/89161941",
    "sg:postcode":"80997",
    "sg:province":"Bayern",
    "wof:name":"Menzinger Hof",
    "wof:placetype":"venue"
},
  "geometry": {"coordinates":[11.4806289673,48.1715698242],"type":"Point"}
}