{
  "type": "Feature",
  "properties": {
    "iso:country":"DE",
    "sg:address":"Cadolzburger Str. 6",
    "sg:city":"Herzogenaurach",
    "sg:phone":"+49 9132/78080",
    "sg:postcode":"91074",
    "sg:province":"Bayern",
    "wof:name":"Frank Dassler Sport Conzept Gmbh",
    "wof:placetype":"venue"
},
  "geometry": {"coordinates":[10.8784599304,49.5656814575],"type":"Point"}
}