{
  "type": "Feature",
  "properties": {
    "iso:country":"DE",
    "sg:address":"Hauptstr. 6",
    "sg:city":"Schweinfurt",
    "sg:phone":"+49 9721/82559",
    "sg:postcode":"97424",
    "sg:province":"Bayern",
    "wof:name":"G\u00fcndermann & Schmitt",
    "wof:placetype":"venue"
},
  "geometry": {"coordinates":[10.204213,50.028584],"type":"Point"}
}