{
  "type": "Feature",
  "properties": {
    "iso:country":"DE",
    "sg:address":"Mozartstr. 20",
    "sg:city":"L\u00fcbbecke",
    "sg:phone":"+49 5741/8232",
    "sg:postcode":"32312",
    "sg:province":"Nordrhein-Westfalen",
    "wof:name":"Ev. Pfarramt L\u00fcbbecke",
    "wof:placetype":"venue"
},
  "geometry": {"coordinates":[8.606010437,52.3108520508],"type":"Point"}
}