{
  "type": "Feature",
  "properties": {
    "iso:country":"DE",
    "sg:address":"Noerballe 5",
    "sg:city":"Felsted",
    "sg:postcode":"06340",
    "wof:name":"Waldkindergarten Feldstedt",
    "wof:placetype":"venue"
},
  "geometry": {"coordinates":[9.497378,54.980171],"type":"Point"}
}