{
  "type": "Feature",
  "properties": {
    "iso:country":"DE",
    "sg:address":"Laufamholzstr. 114",
    "sg:city":"N\u00fcrnberg",
    "sg:phone":"+49 911/5460561",
    "sg:postcode":"90482",
    "sg:province":"Bayern",
    "wof:name":"Campus-sports Und Reha Gmbh",
    "wof:placetype":"venue"
},
  "geometry": {"coordinates":[11.1463117599,49.4637260437],"type":"Point"}
}