{
  "type": "Feature",
  "properties": {
    "iso:country":"DE",
    "sg:address":"Vogelweide 10",
    "sg:city":"Koblenz",
    "sg:phone":"+49 261/69531",
    "sg:postcode":"56077",
    "sg:province":"Rheinland-Pfalz",
    "wof:name":"Kurt Dietz",
    "wof:placetype":"venue"
},
  "geometry": {"coordinates":[7.6459898949,50.3659133911],"type":"Point"}
}