{
  "type": "Feature",
  "properties": {
    "iso:country":"DE",
    "sg:address":"St.-Veit-Str. 8",
    "sg:city":"M\u00fcnchen",
    "sg:phone":"+49 89/4363567",
    "sg:postcode":"81673",
    "sg:province":"Bayern",
    "wof:name":"Schneider",
    "wof:placetype":"venue"
},
  "geometry": {"coordinates":[11.645973,48.128891],"type":"Point"}
}