{
  "type": "Feature",
  "properties": {
    "iso:country":"DE",
    "sg:address":"Kleiststr. 81",
    "sg:city":"Dinslaken",
    "sg:phone":"+49 2064/56851",
    "sg:postcode":"46539",
    "sg:province":"Nordrhein-Westfalen",
    "wof:name":"P. Fortmann",
    "wof:placetype":"venue"
},
  "geometry": {"coordinates":[6.753094,51.566605],"type":"Point"}
}