{
  "type": "Feature",
  "properties": {
    "iso:country":"DE",
    "sg:address":"Krummhardter Str. 62",
    "sg:city":"Aichwald",
    "sg:phone":"+49 711/363536",
    "sg:postcode":"73773",
    "sg:province":"Baden-W\u00fcrttemberg",
    "wof:name":"Schurwaldhalle",
    "wof:placetype":"venue"
},
  "geometry": {"coordinates":[9.380397,48.759342],"type":"Point"}
}