{
  "type": "Feature",
  "properties": {
    "iso:country":"DE",
    "sg:address":"Ober der Steinhohle 14",
    "sg:city":"Sulzbach",
    "sg:phone":"+49 6028/4899",
    "sg:postcode":"63834",
    "sg:province":"Bayern",
    "wof:name":"Bernhard Seitz",
    "wof:placetype":"venue"
},
  "geometry": {"coordinates":[9.151497,49.913586],"type":"Point"}
}