{
  "type": "Feature",
  "properties": {
    "iso:country":"DE",
    "sg:address":"Am Busch 9",
    "sg:city":"Castrop-Rauxel",
    "sg:phone":"+49 2305",
    "sg:postcode":"44581",
    "sg:province":"Nordrhein-Westfalen",
    "wof:name":"Vielleicht Mehr Als Heisse Luft",
    "wof:placetype":"venue"
},
  "geometry": {"coordinates":[7.321521,51.588203],"type":"Point"}
}