{
  "type": "Feature",
  "properties": {
    "iso:country":"DE",
    "sg:address":"Steintorwall 13",
    "sg:city":"Herford",
    "sg:postcode":"32052",
    "sg:province":"Nordrhein-Westfalen",
    "wof:name":"Hiebo Gmbh",
    "wof:placetype":"venue"
},
  "geometry": {"coordinates":[8.668265,52.117401],"type":"Point"}
}