{
  "type": "Feature",
  "properties": {
    "iso:country":"DE",
    "sg:address":"Hauskampstr. 32",
    "sg:city":"Gescher",
    "sg:phone":"+49 2542/1245",
    "sg:postcode":"48712",
    "sg:province":"Nordrhein-Westfalen",
    "wof:name":"Von Der Beck",
    "wof:placetype":"venue"
},
  "geometry": {"coordinates":[7.0107851028,51.9563217163],"type":"Point"}
}