{
  "type": "Feature",
  "properties": {
    "iso:country":"DE",
    "sg:address":"Ochsenwerder Elbdeich 249",
    "sg:city":"Hamburg",
    "sg:phone":"+49 40/7373209",
    "sg:postcode":"21037",
    "sg:province":"Hamburg",
    "wof:name":"G\u00fcnter Meyer",
    "wof:placetype":"venue"
},
  "geometry": {"coordinates":[10.106117,53.447506],"type":"Point"}
}