{
  "type": "Feature",
  "properties": {
    "iso:country":"DE",
    "sg:address":"Dillenburger Str 75",
    "sg:city":"K\u00f6ln",
    "sg:phone":"+49 221/33730210",
    "sg:postcode":"51105",
    "sg:province":"Nordrhein-Westfalen",
    "wof:name":"Econia Solutions Gmbh",
    "wof:placetype":"venue"
},
  "geometry": {"coordinates":[6.9994001389,50.9354515076],"type":"Point"}
}