{
  "type": "Feature",
  "properties": {
    "iso:country":"DE",
    "sg:address":"Am B\u00fcchsensch\u00fctz 15",
    "sg:city":"Hattingen",
    "sg:phone":"+49 2324/96030",
    "sg:postcode":"45527",
    "sg:province":"Nordrhein-Westfalen",
    "wof:name":"Diergardt Zum K\u00fchlen Grunde Gmbh",
    "wof:placetype":"venue"
},
  "geometry": {"coordinates":[7.204100132,51.4050521851],"type":"Point"}
}