{
  "type": "Feature",
  "properties": {
    "iso:country":"DE",
    "sg:address":"Im alten Museum",
    "sg:city":"Rinteln",
    "sg:postcode":"31737",
    "sg:province":"Niedersachsen",
    "wof:name":"Modehaus Sasse",
    "wof:placetype":"venue"
},
  "geometry": {"coordinates":[9.08679,52.189331],"type":"Point"}
}