{
  "type": "Feature",
  "properties": {
    "iso:country":"DE",
    "sg:address":"Klein Schweinebr\u00fcck 8",
    "sg:city":"Zetel",
    "sg:phone":"+49 4453/3490",
    "sg:postcode":"26340",
    "sg:province":"Niedersachsen",
    "wof:name":"Heinz Skeries",
    "wof:placetype":"venue"
},
  "geometry": {"coordinates":[7.97371,53.408279],"type":"Point"}
}