{
  "type": "Feature",
  "properties": {
    "iso:country":"DE",
    "sg:address":"Peinerweg 43",
    "sg:city":"Pinneberg",
    "sg:phone":"+49 4101/54510",
    "sg:postcode":"25421",
    "sg:province":"Schleswig-Holstein",
    "wof:name":"Erwin Kosanke Heizungsbau Gmbh",
    "wof:placetype":"venue"
},
  "geometry": {"coordinates":[9.7844743729,53.6646728516],"type":"Point"}
}