{
  "type": "Feature",
  "properties": {
    "iso:country":"DE",
    "sg:address":"Rathaus",
    "sg:city":"Witzenhausen",
    "sg:phone":"+49 5542/50855",
    "sg:postcode":"37213",
    "sg:province":"Hessen",
    "wof:name":"Stadtarchiv Stadtverwaltung",
    "wof:placetype":"venue"
},
  "geometry": {"coordinates":[9.8535,51.34227],"type":"Point"}
}