{
  "type": "Feature",
  "properties": {
    "iso:country":"DE",
    "sg:address":"St\u00f6ckachstr. 31",
    "sg:city":"Eisingen",
    "sg:phone":"+49 9306/2911",
    "sg:postcode":"97249",
    "sg:province":"Bayern",
    "wof:name":"Franz Heim Omnibusunternehmen Gmbh",
    "wof:placetype":"venue"
},
  "geometry": {"coordinates":[9.8336057663,49.7579231262],"type":"Point"}
}