{
  "type": "Feature",
  "properties": {
    "iso:country":"DE",
    "sg:address":"Hahnenstr. 27",
    "sg:city":"Pforzheim",
    "sg:phone":"+49 7231/451481",
    "sg:postcode":"75179",
    "sg:province":"Baden-W\u00fcrttemberg",
    "wof:name":"J. Harms",
    "wof:placetype":"venue"
},
  "geometry": {"coordinates":[8.661936,48.889748],"type":"Point"}
}