{
  "type": "Feature",
  "properties": {
    "iso:country":"DE",
    "sg:address":"D\u00e4nzergasse 8",
    "sg:city":"Regensburg",
    "sg:phone":"+49 941/82012",
    "sg:postcode":"93047",
    "sg:province":"Bayern",
    "wof:name":"Umspannwerk Windkraft Auf Der H\u00f6te",
    "wof:placetype":"venue"
},
  "geometry": {"coordinates":[12.091673,49.01804],"type":"Point"}
}