{
  "type": "Feature",
  "properties": {
    "iso:country":"DE",
    "sg:address":"Clara-Bartram-Weg 4",
    "sg:city":"Pinneberg",
    "sg:phone":"+49 4101/512515",
    "sg:postcode":"25421",
    "sg:province":"Schleswig-Holstein",
    "wof:name":"Mediteam",
    "wof:placetype":"venue"
},
  "geometry": {"coordinates":[9.797904,53.664303],"type":"Point"}
}