{
  "type": "Feature",
  "properties": {
    "iso:country":"DE",
    "sg:address":"F\u00f6hrenweg 14",
    "sg:city":"Karlsfeld",
    "sg:phone":"+49 8131/92382",
    "sg:postcode":"85757",
    "sg:province":"Bayern",
    "wof:name":"Eleonore Walter",
    "wof:placetype":"venue"
},
  "geometry": {"coordinates":[11.4566478729,48.2104682922],"type":"Point"}
}