{
  "type": "Feature",
  "properties": {
    "iso:country":"DE",
    "sg:address":"Schlagbreite 48",
    "sg:city":"Dessau",
    "sg:phone":"+49 340/541170",
    "sg:postcode":"06842",
    "sg:province":"Sachsen-Anhalt",
    "wof:name":"Berzau Gmbh",
    "wof:placetype":"venue"
},
  "geometry": {"coordinates":[12.2198753357,51.81798172],"type":"Point"}
}