{
  "type": "Feature",
  "properties": {
    "iso:country":"DE",
    "sg:address":"Saarlandstr. 2",
    "sg:city":"Pullach",
    "sg:postcode":"82049",
    "sg:province":"Bayern",
    "wof:name":"Ahv Verm\u00f6gensverwaltung Gmbh",
    "wof:placetype":"venue"
},
  "geometry": {"coordinates":[11.518933,48.065132],"type":"Point"}
}