{
  "type": "Feature",
  "properties": {
    "iso:country":"DE",
    "sg:address":"Stuttgarter Str. 28/1",
    "sg:city":"Lauffen",
    "sg:postcode":"74348",
    "sg:province":"Baden-W\u00fcrttemberg",
    "wof:name":"Iduna Nova",
    "wof:placetype":"venue"
},
  "geometry": {"coordinates":[9.1549863815,49.0736465454],"type":"Point"}
}