{
  "type": "Feature",
  "properties": {
    "iso:country":"DE",
    "sg:address":"Oberwendelsheim 17",
    "sg:city":"Wendelsheim",
    "sg:phone":"+49 6734/590",
    "sg:postcode":"55234",
    "sg:province":"Rheinland-Pfalz",
    "wof:name":"Ludwig Und Erich Klippel",
    "wof:placetype":"venue"
},
  "geometry": {"coordinates":[7.987967,49.763798],"type":"Point"}
}