{
  "type": "Feature",
  "properties": {
    "iso:country":"DE",
    "sg:address":"Mozartstr. 1",
    "sg:city":"Ebern",
    "sg:phone":"+49 9531/5367",
    "sg:postcode":"96106",
    "sg:province":"Bayern",
    "wof:name":"C. R\u00fcpplein",
    "wof:placetype":"venue"
},
  "geometry": {"coordinates":[10.799744606,50.0974731445],"type":"Point"}
}