{
  "type": "Feature",
  "properties": {
    "iso:country":"DE",
    "sg:address":"Eberhartstr. 5",
    "sg:city":"Geislingen",
    "sg:phone":"+49 7428/37002",
    "sg:postcode":"72351",
    "sg:province":"Baden-W\u00fcrttemberg",
    "wof:name":"Doris Braun",
    "wof:placetype":"venue"
},
  "geometry": {"coordinates":[8.758143,48.306957],"type":"Point"}
}