{
  "type": "Feature",
  "properties": {
    "iso:country":"DE",
    "sg:address":"Frankfurter Str. 54",
    "sg:city":"Kelkheim",
    "sg:phone":"+49 6195/3870",
    "sg:postcode":"65779",
    "sg:province":"Hessen",
    "wof:name":"Forte",
    "wof:placetype":"venue"
},
  "geometry": {"coordinates":[8.45265,50.13282],"type":"Point"}
}