{
  "type": "Feature",
  "properties": {
    "iso:country":"DE",
    "sg:address":"Medienallee 7",
    "sg:city":"Unterf\u00f6hring",
    "sg:postcode":"85767",
    "sg:province":"Bayern",
    "wof:name":"Prosieben Media Ag",
    "wof:placetype":"venue"
},
  "geometry": {"coordinates":[11.649182,48.191193],"type":"Point"}
}