{
  "type": "Feature",
  "properties": {
    "iso:country":"DE",
    "sg:address":"Talstr. 6",
    "sg:city":"Markdorf",
    "sg:phone":"+49 7544/5849",
    "sg:postcode":"88677",
    "sg:province":"Baden-W\u00fcrttemberg",
    "wof:name":"Egle",
    "wof:placetype":"venue"
},
  "geometry": {"coordinates":[9.3839216232,47.7225646973],"type":"Point"}
}