{
  "type": "Feature",
  "properties": {
    "iso:country":"DE",
    "sg:address":"Hufnagelstr. 19-21",
    "sg:city":"Frankfurt",
    "sg:phone":"+49 4969/9731070",
    "sg:postcode":"60326",
    "sg:province":"Hessen",
    "wof:name":"K & W Offsetdruck Gmbh",
    "wof:placetype":"venue"
},
  "geometry": {"coordinates":[8.6428489685,50.1040878296],"type":"Point"}
}