{
  "type": "Feature",
  "properties": {
    "iso:country":"DE",
    "sg:address":"Jacobstr. 11",
    "sg:city":"Leipzig",
    "sg:phone":"+49 341/984060",
    "sg:postcode":"04105",
    "sg:province":"Sachsen",
    "wof:name":"Gfl Gesellschaft F\u00fcr Finanzierungsberatung Und",
    "wof:placetype":"venue"
},
  "geometry": {"coordinates":[12.3680429459,51.3450660706],"type":"Point"}
}