{
  "type": "Feature",
  "properties": {
    "iso:country":"DE",
    "sg:address":"Gewerbepark 13",
    "sg:city":"Altom\u00fcnster",
    "sg:phone":"+49 8254/99760",
    "sg:postcode":"85250",
    "sg:province":"Bayern",
    "wof:name":"Tbs Montageservice Gmbh",
    "wof:placetype":"venue"
},
  "geometry": {"coordinates":[11.259936,48.37849],"type":"Point"}
}