{
  "type": "Feature",
  "properties": {
    "iso:country":"DE",
    "sg:address":"Im Wiesengrund 16",
    "sg:city":"Sulzheim/bei W\u00f6rrstadt",
    "sg:phone":"+49 6732",
    "sg:postcode":"55286",
    "sg:province":"Rheinland-Pfalz",
    "wof:name":"Tauchertreff Dekokammer",
    "wof:placetype":"venue"
},
  "geometry": {"coordinates":[8.0992145538,49.8423461914],"type":"Point"}
}