{
  "type": "Feature",
  "properties": {
    "iso:country":"DE",
    "sg:address":"Siemensstr. 5",
    "sg:city":"Konstanz",
    "sg:phone":"+49 7531/56120",
    "sg:postcode":"78467",
    "sg:province":"Baden-W\u00fcrttemberg",
    "wof:name":"Kunststoff- Und Kautschuk- Technik Van Husen Gmbh",
    "wof:placetype":"venue"
},
  "geometry": {"coordinates":[9.148779,47.673893],"type":"Point"}
}