{
  "type": "Feature",
  "properties": {
    "iso:country":"DE",
    "sg:address":"Au\u00dfenliegend 10",
    "sg:city":"Butzbach",
    "sg:phone":"+49 6033/96120",
    "sg:postcode":"35510",
    "sg:province":"Hessen",
    "wof:name":"Kalksandsteinwerk Griedel Verwaltungsges. Mbh",
    "wof:placetype":"venue"
},
  "geometry": {"coordinates":[8.671438,50.435814],"type":"Point"}
}