{
  "type": "Feature",
  "properties": {
    "iso:country":"DE",
    "sg:address":"Marktplatz 10",
    "sg:city":"Georgensgm\u00fcnd",
    "sg:phone":"+49 9172/68113",
    "sg:postcode":"91166",
    "sg:province":"Bayern",
    "wof:name":"Wolfgang B\u00f6hm Architekt",
    "wof:placetype":"venue"
},
  "geometry": {"coordinates":[11.014415,49.187958],"type":"Point"}
}