{
  "type": "Feature",
  "properties": {
    "iso:country":"DE",
    "sg:address":"Mainzer Str. 60",
    "sg:city":"Kaiserslautern",
    "sg:phone":"+49 631/48282",
    "sg:postcode":"67657",
    "sg:province":"Rheinland-Pfalz",
    "wof:name":"Bbv Heizungs-l\u00fcftungs- Klimatechnik Gmbh",
    "wof:placetype":"venue"
},
  "geometry": {"coordinates":[7.7848558426,49.4511528015],"type":"Point"}
}