{
  "type": "Feature",
  "properties": {
    "iso:country":"DE",
    "sg:address":"Burgstr. 33",
    "sg:city":"B\u00fcren",
    "sg:phone":"+49 2951/6475",
    "sg:postcode":"33142",
    "sg:province":"Nordrhein-Westfalen",
    "wof:name":"Feindt Ohg",
    "wof:placetype":"venue"
},
  "geometry": {"coordinates":[8.5588693619,51.5519447327],"type":"Point"}
}