{
  "type": "Feature",
  "properties": {
    "iso:country":"DE",
    "sg:address":"Forsterweg 4",
    "sg:city":"Garmisch-Partenkirchen",
    "sg:phone":"+49 8821/55493",
    "sg:postcode":"82467",
    "sg:province":"Bayern",
    "wof:name":"Peter Hartl Architekt",
    "wof:placetype":"venue"
},
  "geometry": {"coordinates":[11.107956,47.496868],"type":"Point"}
}