{
  "type": "Feature",
  "properties": {
    "iso:country":"DE",
    "sg:address":"Stehlings 16",
    "sg:city":"Monschau",
    "sg:phone":"+49 2472/2274",
    "sg:postcode":"52156",
    "sg:province":"Nordrhein-Westfalen",
    "wof:name":"Rur-caf\u00e9",
    "wof:placetype":"venue"
},
  "geometry": {"coordinates":[6.241787,50.555386],"type":"Point"}
}