{
  "type": "Feature",
  "properties": {
    "iso:country":"DE",
    "sg:address":"Eichendorffstr. 116",
    "sg:city":"Stadtlohn",
    "sg:phone":"+49 2563/8285",
    "sg:postcode":"48703",
    "sg:province":"Nordrhein-Westfalen",
    "wof:name":"D\u00fccker Gmbh Landwirtschaftliches Lohn-",
    "wof:placetype":"venue"
},
  "geometry": {"coordinates":[6.857043,51.996269],"type":"Point"}
}