{
  "type": "Feature",
  "properties": {
    "iso:country":"DE",
    "sg:address":"Fichtenstr. 2",
    "sg:city":"Unterf\u00f6hring",
    "sg:postcode":"85774",
    "sg:province":"Bayern",
    "wof:name":"Decon Gesch\u00e4ftsf\u00fchrungs- Gmbh",
    "wof:placetype":"venue"
},
  "geometry": {"coordinates":[11.64951,48.197903],"type":"Point"}
}