{
  "type": "Feature",
  "properties": {
    "iso:country":"DE",
    "sg:address":"Friedrich-Ebert-Str. 53",
    "sg:city":"Frankfurt",
    "sg:postcode":"15234",
    "sg:province":"Brandenburg",
    "wof:name":"Kreuzkirchengemeinde",
    "wof:placetype":"venue"
},
  "geometry": {"coordinates":[14.4757051468,52.371635437],"type":"Point"}
}