{
  "type": "Feature",
  "properties": {
    "iso:country":"DE",
    "sg:address":"Falkensteinstr. 16",
    "sg:city":"Kassel",
    "sg:phone":"+49 561/42154",
    "sg:postcode":"34132",
    "sg:province":"Hessen",
    "wof:name":"K. Almeroth",
    "wof:placetype":"venue"
},
  "geometry": {"coordinates":[9.45068,51.273949],"type":"Point"}
}