{
  "type": "Feature",
  "properties": {
    "iso:country":"DE",
    "sg:address":"K\u00fcster-Meyer-Platz 1",
    "sg:city":"Detmold",
    "sg:phone":"+49 5231/39662",
    "sg:postcode":"32756",
    "sg:province":"Nordrhein-Westfalen",
    "wof:name":"Klaus Runte",
    "wof:placetype":"venue"
},
  "geometry": {"coordinates":[8.882849,51.934399],"type":"Point"}
}