{
  "type": "Feature",
  "properties": {
    "iso:country":"DE",
    "sg:address":"Zittauer Str. 24",
    "sg:city":"Wilthen",
    "sg:postcode":"02681",
    "sg:province":"Sachsen",
    "wof:name":"W. Ewald",
    "wof:placetype":"venue"
},
  "geometry": {"coordinates":[14.39516,51.097263],"type":"Point"}
}