{
  "type": "Feature",
  "properties": {
    "iso:country":"DE",
    "sg:address":"S\u00fcdermarkt 8",
    "sg:city":"Flensburg",
    "sg:phone":"+49 461/17217",
    "sg:postcode":"24937",
    "sg:province":"Schleswig-Holstein",
    "wof:name":"Christoph Konopacki Rechtsanwalt Und Notar",
    "wof:placetype":"venue"
},
  "geometry": {"coordinates":[9.4363098145,54.7824440002],"type":"Point"}
}