{
  "type": "Feature",
  "properties": {
    "iso:country":"DE",
    "sg:address":"Hollestr. 7 b",
    "sg:city":"Essen",
    "sg:postcode":"45127",
    "sg:province":"Nordrhein-Westfalen",
    "wof:name":"Rwe Telliance Tele- Kommunikation Verwaltungs Gmbh",
    "wof:placetype":"venue"
},
  "geometry": {"coordinates":[7.0191040039,51.4535636902],"type":"Point"}
}