{
  "type": "Feature",
  "properties": {
    "iso:country":"DE",
    "sg:address":"Coppie Str. 1e",
    "sg:city":"Eberswalde",
    "sg:phone":"+49 3334",
    "sg:postcode":"16227",
    "sg:province":"Brandenburg",
    "wof:name":"Forth Elektroanlagen Gmbh & Co.ingenieur Kg",
    "wof:placetype":"venue"
},
  "geometry": {"coordinates":[13.769597,52.845802],"type":"Point"}
}