{
  "type": "Feature",
  "properties": {
    "iso:country":"DE",
    "sg:address":"Geschwister-Scholl-Str. 3",
    "sg:city":"Salzm\u00fcnde",
    "sg:phone":"+49 34609/29021",
    "sg:postcode":"06198",
    "sg:province":"Sachsen-Anhalt",
    "wof:name":"T. Ziegenhardt",
    "wof:placetype":"venue"
},
  "geometry": {"coordinates":[11.8504037857,51.5266952515],"type":"Point"}
}