{
  "type": "Feature",
  "properties": {
    "iso:country":"DE",
    "sg:address":"Hauptstr 7",
    "sg:city":"Balgheim",
    "sg:phone":"+49 7424/502017",
    "sg:postcode":"78582",
    "sg:province":"Baden-W\u00fcrttemberg",
    "wof:name":"Schuchter & Herzog",
    "wof:placetype":"venue"
},
  "geometry": {"coordinates":[8.763044,48.066563],"type":"Point"}
}