{
  "type": "Feature",
  "properties": {
    "iso:country":"DE",
    "sg:address":"Amthausstr. 20",
    "sg:city":"Karlsruhe",
    "sg:phone":"+49 721/406088",
    "sg:postcode":"76227",
    "sg:province":"Baden-W\u00fcrttemberg",
    "wof:name":"Rundschau Reisen",
    "wof:placetype":"venue"
},
  "geometry": {"coordinates":[8.4706878662,48.9977264404],"type":"Point"}
}