{
  "type": "Feature",
  "properties": {
    "iso:country":"DE",
    "sg:address":"Tevesstr. 2",
    "sg:city":"Blumberg",
    "sg:phone":"+49 7702/805",
    "sg:postcode":"78176",
    "sg:province":"Baden-W\u00fcrttemberg",
    "wof:name":"Neukauf",
    "wof:placetype":"venue"
},
  "geometry": {"coordinates":[8.5406007767,47.8368530273],"type":"Point"}
}