{
  "type": "Feature",
  "properties": {
    "iso:country":"DE",
    "sg:address":"Frankfurter Str. 37",
    "sg:city":"W\u00fcrzburg",
    "sg:phone":"+49 931/43234",
    "sg:postcode":"97082",
    "sg:province":"Bayern",
    "wof:name":"Hartmann Haus Und Grund Gmbh",
    "wof:placetype":"venue"
},
  "geometry": {"coordinates":[9.911274,49.794186],"type":"Point"}
}