{
  "type": "Feature",
  "properties": {
    "iso:country":"DE",
    "sg:address":"Metzinger Str. 41",
    "sg:city":"N\u00fcrtingen",
    "sg:phone":"+49 7022/32195",
    "sg:postcode":"72622",
    "sg:province":"Baden-W\u00fcrttemberg",
    "wof:name":"Tauchcenter N\u00fcrtingen Gbr",
    "wof:placetype":"venue"
},
  "geometry": {"coordinates":[9.33224,48.623791],"type":"Point"}
}