{
  "type": "Feature",
  "properties": {
    "iso:country":"DE",
    "sg:address":"Strombachstr. 4",
    "sg:city":"Gummersbach",
    "sg:phone":"+49 2261/73604",
    "sg:postcode":"51645",
    "sg:province":"Nordrhein-Westfalen",
    "wof:name":"Beas Bierst\u00fcbchen",
    "wof:placetype":"venue"
},
  "geometry": {"coordinates":[7.549448967,50.9880180359],"type":"Point"}
}