{
  "type": "Feature",
  "properties": {
    "iso:country":"DE",
    "sg:address":"Holter Str.",
    "sg:city":"Hilter",
    "sg:postcode":"49176",
    "sg:province":"Niedersachsen",
    "wof:name":"Walter Nielsson Gmbh & Co. Kg",
    "wof:placetype":"venue"
},
  "geometry": {"coordinates":[8.2041912079,52.2003822327],"type":"Point"}
}