{
  "type": "Feature",
  "properties": {
    "iso:country":"DE",
    "sg:address":"Rathausplatz 3",
    "sg:city":"Abtsgm\u00fcnd",
    "sg:postcode":"73453",
    "sg:province":"Baden-W\u00fcrttemberg",
    "wof:name":"R\u00f6waplan Ag",
    "wof:placetype":"venue"
},
  "geometry": {"coordinates":[10.0047664642,48.8937911987],"type":"Point"}
}