{
  "type": "Feature",
  "properties": {
    "iso:country":"DE",
    "sg:address":"Reichenstr. 14",
    "sg:city":"Otterndorf",
    "sg:phone":"+49 4751/91590",
    "sg:postcode":"21762",
    "sg:province":"Niedersachsen",
    "wof:name":"Compass Immobilien-marketing",
    "wof:placetype":"venue"
},
  "geometry": {"coordinates":[8.9000492096,53.8078269958],"type":"Point"}
}