{
  "type": "Feature",
  "properties": {
    "iso:country":"DE",
    "sg:address":"Frauengraben 32",
    "sg:city":"Ulm",
    "sg:phone":"+49 731/64668",
    "sg:postcode":"89073",
    "sg:province":"Baden-W\u00fcrttemberg",
    "wof:name":"Karl Spengler Gmbh",
    "wof:placetype":"venue"
},
  "geometry": {"coordinates":[9.9965229034,48.4012069702],"type":"Point"}
}