{
  "type": "Feature",
  "properties": {
    "iso:country":"DE",
    "sg:address":"Rittnertstr. 15",
    "sg:city":"Pfinztal",
    "sg:phone":"+49 7240/1433",
    "sg:postcode":"76327",
    "sg:province":"Baden-W\u00fcrttemberg",
    "wof:name":"H. Endres Grabdenkm\u00e4ler",
    "wof:placetype":"venue"
},
  "geometry": {"coordinates":[8.5414438248,48.9861297607],"type":"Point"}
}