{
  "type": "Feature",
  "properties": {
    "iso:country":"DE",
    "sg:address":"Admiral-Spee-Str. 8",
    "sg:city":"M\u00fcnster",
    "sg:phone":"+49 251/33768",
    "sg:postcode":"48145",
    "sg:province":"Nordrhein-Westfalen",
    "wof:name":"Filou Verein Zur F\u00f6rderung Einer Partnerschaftl. Eltern-",
    "wof:placetype":"venue"
},
  "geometry": {"coordinates":[7.6595759392,51.9669685364],"type":"Point"}
}