{
  "type": "Feature",
  "properties": {
    "iso:country":"DE",
    "sg:address":"Edelmannshofer Str. 26",
    "sg:city":"Jagsthausen",
    "sg:phone":"+49 7943/2431",
    "sg:postcode":"74249",
    "sg:province":"Baden-W\u00fcrttemberg",
    "wof:name":"Erich Fromm",
    "wof:placetype":"venue"
},
  "geometry": {"coordinates":[9.475196,49.313053],"type":"Point"}
}