{
  "type": "Feature",
  "properties": {
    "iso:country":"DE",
    "sg:address":"Laustergasse 7",
    "sg:city":"Neustadt",
    "sg:phone":"+49 6321/30058",
    "sg:postcode":"67433",
    "sg:province":"Rheinland-Pfalz",
    "wof:name":"Gerd O. Westenweller Rechtsanwalt",
    "wof:placetype":"venue"
},
  "geometry": {"coordinates":[8.1390047073,49.3532905579],"type":"Point"}
}