{
  "type": "Feature",
  "properties": {
    "iso:country":"DE",
    "sg:address":"Bohlweg 33",
    "sg:city":"Salzgitter",
    "sg:phone":"+49 5341/38179",
    "sg:postcode":"38259",
    "sg:province":"Niedersachsen",
    "wof:name":"Erika Klug",
    "wof:placetype":"venue"
},
  "geometry": {"coordinates":[10.374341011,52.0463752747],"type":"Point"}
}