{
  "type": "Feature",
  "properties": {
    "iso:country":"DE",
    "sg:address":"Markt",
    "sg:city":"Lunzenau",
    "sg:postcode":"09328",
    "sg:province":"Sachsen",
    "wof:name":"Kohlehandel Chemnitz Gmbh",
    "wof:placetype":"venue"
},
  "geometry": {"coordinates":[12.755899,50.962166],"type":"Point"}
}