{
  "type": "Feature",
  "properties": {
    "iso:country":"DE",
    "sg:address":"Oberdorfstr. 97",
    "sg:city":"Hamm",
    "sg:phone":"+49 6246/1847",
    "sg:postcode":"67580",
    "sg:province":"Rheinland-Pfalz",
    "wof:name":"W.m. Holz",
    "wof:placetype":"venue"
},
  "geometry": {"coordinates":[8.4202728271,49.7305107117],"type":"Point"}
}