{
  "type": "Feature",
  "properties": {
    "iso:country":"DE",
    "sg:address":"Gambrinusstr. 12",
    "sg:city":"Dresden",
    "sg:phone":"+49 351/4941217",
    "sg:postcode":"01159",
    "sg:province":"Sachsen",
    "wof:name":"M. Homfeldt",
    "wof:placetype":"venue"
},
  "geometry": {"coordinates":[13.7091588974,51.0500907898],"type":"Point"}
}