{
  "type": "Feature",
  "properties": {
    "iso:country":"DE",
    "sg:address":"Gr\u00fcnestr. 75",
    "sg:city":"Plettenberg",
    "sg:phone":"+49 2391/3033",
    "sg:postcode":"58840",
    "sg:province":"Nordrhein-Westfalen",
    "wof:name":"Dieter Kessler",
    "wof:placetype":"venue"
},
  "geometry": {"coordinates":[7.8858251572,51.2097740173],"type":"Point"}
}