{
  "type": "Feature",
  "properties": {
    "iso:country":"DE",
    "sg:address":"Ambelwiesenstr. 18",
    "sg:city":"Eschelbronn",
    "sg:phone":"+49 6226/970262",
    "sg:postcode":"74927",
    "sg:province":"Baden-W\u00fcrttemberg",
    "wof:name":"Manfred W. Grimm",
    "wof:placetype":"venue"
},
  "geometry": {"coordinates":[8.8735523224,49.3185195923],"type":"Point"}
}