{
  "type": "Feature",
  "properties": {
    "iso:country":"DE",
    "sg:address":"Berliner Str. 7",
    "sg:city":"Bad K\u00f6nig",
    "sg:phone":"+49 6063/57512",
    "sg:postcode":"64732",
    "sg:province":"Hessen",
    "wof:name":"B. Klimpel",
    "wof:placetype":"venue"
},
  "geometry": {"coordinates":[9.0039453506,49.7502975464],"type":"Point"}
}