{
  "type": "Feature",
  "properties": {
    "iso:country":"DE",
    "sg:address":"Giesbert-Bergerhoff-Str. 1",
    "sg:city":"Osnabr\u00fcck",
    "sg:phone":"+49 541/122061",
    "sg:postcode":"49076",
    "sg:province":"Niedersachsen",
    "wof:name":"Ecco Werbeagentur Gmbh",
    "wof:placetype":"venue"
},
  "geometry": {"coordinates":[7.9451189041,52.2829971313],"type":"Point"}
}