{
  "type": "Feature",
  "properties": {
    "iso:country":"DE",
    "sg:address":"Neustr. 10",
    "sg:city":"Weiterstadt",
    "sg:phone":"+49 6150/52752",
    "sg:postcode":"64331",
    "sg:province":"Hessen",
    "wof:name":"Walter Storck",
    "wof:placetype":"venue"
},
  "geometry": {"coordinates":[8.578426,49.927433],"type":"Point"}
}