{
  "type": "Feature",
  "properties": {
    "iso:country":"DE",
    "sg:address":"H\u00fcchelner Str. 154",
    "sg:city":"Frechen",
    "sg:phone":"+49 2234/955050",
    "sg:postcode":"50226",
    "sg:province":"Nordrhein-Westfalen",
    "wof:name":"Hotel Olympia Garni",
    "wof:placetype":"venue"
},
  "geometry": {"coordinates":[6.8123397827,50.9166107178],"type":"Point"}
}