{
  "type": "Feature",
  "properties": {
    "iso:country":"DE",
    "sg:address":"Turnhallenweg 9",
    "sg:city":"Lengefeld",
    "sg:phone":"+49 37367/8870",
    "sg:postcode":"09514",
    "sg:province":"Sachsen",
    "wof:name":"Wolfgang Fiedler",
    "wof:placetype":"venue"
},
  "geometry": {"coordinates":[13.2564563751,50.7601203918],"type":"Point"}
}