{
  "type": "Feature",
  "properties": {
    "iso:country":"DE",
    "sg:address":"Zinsbachstr. 38",
    "sg:city":"Pfalzgrafenweiler",
    "sg:phone":"+49 7445/2403",
    "sg:postcode":"72285",
    "sg:province":"Baden-W\u00fcrttemberg",
    "wof:name":"R. Gau\u00df",
    "wof:placetype":"venue"
},
  "geometry": {"coordinates":[8.4987783432,48.533870697],"type":"Point"}
}