{
  "type": "Feature",
  "properties": {
    "iso:country":"DE",
    "sg:address":"Am Rapohl 8",
    "sg:city":"K\u00f6ln",
    "sg:phone":"+49 2234/77048",
    "sg:postcode":"50859",
    "sg:province":"Nordrhein-Westfalen",
    "wof:name":"Krause Krolikowski & Co. Gmbh",
    "wof:placetype":"venue"
},
  "geometry": {"coordinates":[6.8226571083,50.9376296997],"type":"Point"}
}