{
  "type": "Feature",
  "properties": {
    "iso:country":"DE",
    "sg:address":"Sandweg 7",
    "sg:city":"Leinfelden-Echterdingen",
    "sg:phone":"+49 711/753702",
    "sg:postcode":"70771",
    "sg:province":"Baden-W\u00fcrttemberg",
    "wof:name":"Dr. Peter Schweickhardt Rechtsanwalt",
    "wof:placetype":"venue"
},
  "geometry": {"coordinates":[9.1378364563,48.6901054382],"type":"Point"}
}