{
  "type": "Feature",
  "properties": {
    "iso:country":"DE",
    "sg:address":"Molsdorfer Str. 9",
    "sg:city":"Erfurt",
    "sg:phone":"+49 361/7968337",
    "sg:postcode":"99094",
    "sg:province":"Th\u00fcringen",
    "wof:name":"Michael Bohn",
    "wof:placetype":"venue"
},
  "geometry": {"coordinates":[10.987777,50.919968],"type":"Point"}
}