{
  "type": "Feature",
  "properties": {
    "iso:country":"DE",
    "sg:address":"Seewiesenredder 23",
    "sg:city":"Kiel",
    "sg:phone":"+49 431/717300",
    "sg:postcode":"24145",
    "sg:province":"Schleswig-Holstein",
    "wof:name":"Kuhl",
    "wof:placetype":"venue"
},
  "geometry": {"coordinates":[10.14363,54.264381],"type":"Point"}
}