{
  "type": "Feature",
  "properties": {
    "iso:country":"DE",
    "sg:address":"Marktstr. 197",
    "sg:city":"Krefeld",
    "sg:phone":"+49 2151/774290",
    "sg:postcode":"47798",
    "sg:province":"Nordrhein-Westfalen",
    "wof:name":"Akropolis Grill",
    "wof:placetype":"venue"
},
  "geometry": {"coordinates":[6.5511250496,51.3279953003],"type":"Point"}
}