{
  "type": "Feature",
  "properties": {
    "iso:country":"DE",
    "sg:address":"Martin-Luther-Str. 31",
    "sg:city":"Gerolzhofen",
    "sg:phone":"+49 9382/97790",
    "sg:postcode":"97447",
    "sg:province":"Bayern",
    "wof:name":"Ratio Steuerberatungs-gmbh",
    "wof:placetype":"venue"
},
  "geometry": {"coordinates":[10.3440179825,49.8953704834],"type":"Point"}
}