{
  "type": "Feature",
  "properties": {
    "iso:country":"DE",
    "sg:address":"Alte Neust\u00e4dtleiner Str. 2",
    "sg:city":"Dinkelsb\u00fchl",
    "sg:phone":"+49 9851/2238",
    "sg:postcode":"91550",
    "sg:province":"Bayern",
    "wof:name":"Ralf Sch\u00e4fer",
    "wof:placetype":"venue"
},
  "geometry": {"coordinates":[10.330202,49.066196],"type":"Point"}
}