{
  "type": "Feature",
  "properties": {
    "iso:country":"DE",
    "sg:address":"Goldbacher Str. 77",
    "sg:city":"Aschaffenburg",
    "sg:phone":"+49 6021/410781",
    "sg:postcode":"63741",
    "sg:province":"Bayern",
    "wof:name":"Amod-gl\u00fcckwunschkartenverlag Inh. Thomas G. Rupprecht E. K.",
    "wof:placetype":"venue"
},
  "geometry": {"coordinates":[9.1642379761,49.9861030579],"type":"Point"}
}