{
  "type": "Feature",
  "properties": {
    "iso:country":"DE",
    "sg:address":"Bahnhofstr. 32",
    "sg:city":"Bielefeld",
    "sg:phone":"+49 521/62836",
    "sg:postcode":"33602",
    "sg:province":"Nordrhein-Westfalen",
    "wof:name":"Vazzola-eiscafe",
    "wof:placetype":"venue"
},
  "geometry": {"coordinates":[8.531696,52.026524],"type":"Point"}
}