{
  "type": "Feature",
  "properties": {
    "iso:country":"DE",
    "sg:address":"Adenauerstr. 22",
    "sg:city":"Puchheim",
    "sg:phone":"+49 89/804466",
    "sg:postcode":"82178",
    "sg:province":"Bayern",
    "wof:name":"Flora-apotheke Inh. Dr. Eva Mandel E. K.",
    "wof:placetype":"venue"
},
  "geometry": {"coordinates":[11.35465,48.168865],"type":"Point"}
}