{
  "type": "Feature",
  "properties": {
    "iso:country":"DE",
    "sg:address":"Harthweg 27",
    "sg:city":"Chemnitz",
    "sg:phone":"+49 371",
    "sg:postcode":"09116",
    "sg:province":"Sachsen",
    "wof:name":"Eigenheimprojekte",
    "wof:placetype":"venue"
},
  "geometry": {"coordinates":[12.879744,50.825367],"type":"Point"}
}