{
  "type": "Feature",
  "properties": {
    "iso:country":"DE",
    "sg:address":"Lenzener Str. 15",
    "sg:city":"D\u00f6mitz",
    "sg:phone":"+49 38758/20002",
    "sg:postcode":"19303",
    "sg:province":"Mecklenburg-Vorpommern",
    "wof:name":"Glb Gartenbau- Landschafts- Arbeiten Und Baumpflege Gmbh",
    "wof:placetype":"venue"
},
  "geometry": {"coordinates":[11.294371,53.130787],"type":"Point"}
}