{
  "type": "Feature",
  "properties": {
    "iso:country":"DE",
    "sg:address":"Lerchenweg 6",
    "sg:city":"Bubenreuth",
    "sg:phone":"+49 9131/21561",
    "sg:postcode":"91088",
    "sg:province":"Bayern",
    "wof:name":"Karl Ulbricht Ingenieur",
    "wof:placetype":"venue"
},
  "geometry": {"coordinates":[11.0177154541,49.6295013428],"type":"Point"}
}