{
  "type": "Feature",
  "properties": {
    "iso:country":"DE",
    "sg:address":"Neckarstr. 10",
    "sg:city":"Neckartailfingen",
    "sg:phone":"+49 7127/938917",
    "sg:postcode":"72666",
    "sg:province":"Baden-W\u00fcrttemberg",
    "wof:name":"Hobbyring, Robo Dr. Kussmaul Gmbh",
    "wof:placetype":"venue"
},
  "geometry": {"coordinates":[9.2704534531,48.6140975952],"type":"Point"}
}