{
  "type": "Feature",
  "properties": {
    "iso:country":"DE",
    "sg:address":"Wilhelmstr. 64",
    "sg:city":"Remscheid",
    "sg:phone":"+49 2191/76114",
    "sg:postcode":"42853",
    "sg:province":"Nordrhein-Westfalen",
    "wof:name":"G\u00fcnter Manne Masseur",
    "wof:placetype":"venue"
},
  "geometry": {"coordinates":[7.176033,51.185867],"type":"Point"}
}