{
  "type": "Feature",
  "properties": {
    "iso:country":"DE",
    "sg:address":"Heiglhofstr. 8",
    "sg:city":"M\u00fcnchen",
    "sg:phone":"+49 89/716081",
    "sg:postcode":"81377",
    "sg:province":"Bayern",
    "wof:name":"Karl D\u00d6rfel Reproduktionsgesellschaft Mbh",
    "wof:placetype":"venue"
},
  "geometry": {"coordinates":[11.4784755707,48.113910675],"type":"Point"}
}