{
  "type": "Feature",
  "properties": {
    "iso:country":"DE",
    "sg:address":"Overhagener Str. 96",
    "sg:city":"Lippstadt",
    "sg:phone":"+49 2941/10089",
    "sg:postcode":"59557",
    "sg:province":"Nordrhein-Westfalen",
    "wof:name":"Grill Athen",
    "wof:placetype":"venue"
},
  "geometry": {"coordinates":[8.3354597092,51.661151886],"type":"Point"}
}