{
  "type": "Feature",
  "properties": {
    "iso:country":"DE",
    "sg:address":"Forstweg 30",
    "sg:city":"Oranienburg",
    "sg:phone":"+49 3301/802764",
    "sg:postcode":"16515",
    "sg:province":"Brandenburg",
    "wof:name":"Peter Pilke",
    "wof:placetype":"venue"
},
  "geometry": {"coordinates":[13.26057,52.736099],"type":"Point"}
}