{
  "type": "Feature",
  "properties": {
    "iso:country":"DE",
    "sg:address":"Auf der Kier 11",
    "sg:city":"Aachen",
    "sg:phone":"+49 241/5266",
    "sg:postcode":"52076",
    "sg:province":"Nordrhein-Westfalen",
    "wof:name":"D. Boshof",
    "wof:placetype":"venue"
},
  "geometry": {"coordinates":[6.1777358055,50.7023506165],"type":"Point"}
}