{
  "type": "Feature",
  "properties": {
    "iso:country":"DE",
    "sg:address":"Frankfurter Str. 6",
    "sg:city":"Borken",
    "sg:phone":"+49 5682/2595",
    "sg:postcode":"34582",
    "sg:province":"Hessen",
    "wof:name":"G\u00fcnther Gimbel",
    "wof:placetype":"venue"
},
  "geometry": {"coordinates":[9.215815,51.06414],"type":"Point"}
}