{
  "type": "Feature",
  "properties": {
    "iso:country":"DE",
    "sg:address":"Lehmdener Str. 48",
    "sg:city":"Damme",
    "sg:phone":"+49 5491/7626",
    "sg:postcode":"49401",
    "sg:province":"Niedersachsen",
    "wof:name":"Langenteiler Sportboden Beteiligungs Gmbh",
    "wof:placetype":"venue"
},
  "geometry": {"coordinates":[8.288729,52.561344],"type":"Point"}
}