{
  "type": "Feature",
  "properties": {
    "iso:country":"DE",
    "sg:address":"Im Bruchkamp 6",
    "sg:city":"Wesel",
    "sg:phone":"+49 281/53148",
    "sg:postcode":"46485",
    "sg:province":"Nordrhein-Westfalen",
    "wof:name":"Josef Olland",
    "wof:placetype":"venue"
},
  "geometry": {"coordinates":[6.687416,51.670612],"type":"Point"}
}