{
  "type": "Feature",
  "properties": {
    "iso:country":"DE",
    "sg:address":"Am Berg",
    "sg:city":"Kurort Oberwiesenthal",
    "sg:phone":"+49 37348/7319",
    "sg:postcode":"09484",
    "sg:province":"Sachsen",
    "wof:name":"Himmelsleiter",
    "wof:placetype":"venue"
},
  "geometry": {"coordinates":[12.9894275665,50.4309692383],"type":"Point"}
}