{
  "type": "Feature",
  "properties": {
    "iso:country":"DE",
    "sg:address":"M\u00fchlweg 11",
    "sg:city":"Markt Rettenbach",
    "sg:phone":"+49 8392/216",
    "sg:postcode":"87733",
    "sg:province":"Bayern",
    "wof:name":"Georg Grambihler",
    "wof:placetype":"venue"
},
  "geometry": {"coordinates":[10.3893642426,47.946182251],"type":"Point"}
}