{
  "type": "Feature",
  "properties": {
    "iso:country":"DE",
    "sg:address":"Theresienstr. 6",
    "sg:city":"Dinslaken",
    "sg:phone":"+49 2064/55010",
    "sg:postcode":"46537",
    "sg:province":"Nordrhein-Westfalen",
    "wof:name":"Kath. Pfarramt St. Jakobus",
    "wof:placetype":"venue"
},
  "geometry": {"coordinates":[6.7458181381,51.5736579895],"type":"Point"}
}