{
  "type": "Feature",
  "properties": {
    "iso:country":"DE",
    "sg:address":"Neugasse 4",
    "sg:city":"Bad Soden",
    "sg:phone":"+49 6196/25717",
    "sg:postcode":"65812",
    "sg:province":"Hessen",
    "wof:name":"Thea Tec B\u00fchnentechnische Anlagen Gmbh",
    "wof:placetype":"venue"
},
  "geometry": {"coordinates":[8.4999265671,50.1417655945],"type":"Point"}
}