{
  "type": "Feature",
  "properties": {
    "iso:country":"DE",
    "sg:address":"Sonthofener Str. 11",
    "sg:city":"Burgberg",
    "sg:phone":"+49 8321/67370",
    "sg:postcode":"87545",
    "sg:province":"Bayern",
    "wof:name":"Hannes Gerzer Steuerberater",
    "wof:placetype":"venue"
},
  "geometry": {"coordinates":[10.2858476639,47.536529541],"type":"Point"}
}