{
  "type": "Feature",
  "properties": {
    "iso:country":"DE",
    "sg:address":"Erlanger Str. 20",
    "sg:city":"F\u00fcrth",
    "sg:phone":"+49 911/7905314",
    "sg:postcode":"90765",
    "sg:province":"Bayern",
    "wof:name":"Heinz Wei\u00dfmann",
    "wof:placetype":"venue"
},
  "geometry": {"coordinates":[10.995986,49.479958],"type":"Point"}
}