{
  "type": "Feature",
  "properties": {
    "iso:country":"DE",
    "sg:address":"Lewitzblick 8",
    "sg:city":"Spornitz",
    "sg:phone":"+49 38726/20312",
    "sg:postcode":"19372",
    "sg:province":"Mecklenburg-Vorpommern",
    "wof:name":"Arnulf Oeser Fsp Gmbh & Co. Kg",
    "wof:placetype":"venue"
},
  "geometry": {"coordinates":[11.7126703262,53.4091758728],"type":"Point"}
}