{
  "type": "Feature",
  "properties": {
    "iso:country":"DE",
    "sg:address":"Einsteinstr. 13",
    "sg:city":"Dreieich",
    "sg:phone":"+49 6103/59350",
    "sg:postcode":"63303",
    "sg:province":"Hessen",
    "wof:name":"Blanchin Textil Gmbh",
    "wof:placetype":"venue"
},
  "geometry": {"coordinates":[8.7099781036,50.0302734375],"type":"Point"}
}