{
  "type": "Feature",
  "properties": {
    "iso:country":"DE",
    "sg:address":"B\u00fcrklinstr. 4",
    "sg:city":"Karlsruhe",
    "sg:phone":"+49 721/812226",
    "sg:postcode":"76137",
    "sg:province":"Baden-W\u00fcrttemberg",
    "wof:name":"Peter Willborn Architekt",
    "wof:placetype":"venue"
},
  "geometry": {"coordinates":[8.389057,49.000641],"type":"Point"}
}