{
  "type": "Feature",
  "properties": {
    "iso:country":"DE",
    "sg:address":"Zeppelinstr. 10",
    "sg:city":"V\u00f6hringen",
    "sg:phone":"+49 7454/96220",
    "sg:postcode":"72189",
    "sg:province":"Baden-W\u00fcrttemberg",
    "wof:name":"H\u00e4berlin Gmbh",
    "wof:placetype":"venue"
},
  "geometry": {"coordinates":[8.6688995361,48.3398895264],"type":"Point"}
}