{
  "type": "Feature",
  "properties": {
    "iso:country":"DE",
    "sg:address":"Grabenstr. 2",
    "sg:city":"Hemsbach",
    "sg:phone":"+49 6201/71146",
    "sg:postcode":"69502",
    "sg:province":"Baden-W\u00fcrttemberg",
    "wof:name":"H. A. Ehret",
    "wof:placetype":"venue"
},
  "geometry": {"coordinates":[8.6521759033,49.5909080505],"type":"Point"}
}