{
  "type": "Feature",
  "properties": {
    "iso:country":"DE",
    "sg:address":"Bundesstrasse 48e",
    "sg:city":"Hamburg",
    "sg:phone":"+49 40/41350413",
    "sg:postcode":"20148",
    "sg:province":"Hamburg",
    "wof:name":"Ecotropica",
    "wof:placetype":"venue"
},
  "geometry": {"coordinates":[9.978208,53.566845],"type":"Point"}
}