{
  "type": "Feature",
  "properties": {
    "iso:country":"DE",
    "sg:address":"Bismarckstr. 21",
    "sg:city":"Elmshorn",
    "sg:phone":"+49 4121/26710",
    "sg:postcode":"25335",
    "sg:province":"Schleswig-Holstein",
    "wof:name":"Landeszentralbank In Der Freien U. Hansest. Hamburg In",
    "wof:placetype":"venue"
},
  "geometry": {"coordinates":[9.6518888474,53.7572364807],"type":"Point"}
}