{
  "type": "Feature",
  "properties": {
    "iso:country":"DE",
    "sg:address":"Briesener Str. 19",
    "sg:city":"Alt Madlitz",
    "sg:phone":"+49 33607/219",
    "sg:postcode":"15518",
    "sg:province":"Brandenburg",
    "wof:name":"Mw Agrarbetrieb Gmbh & Co. Kg",
    "wof:placetype":"venue"
},
  "geometry": {"coordinates":[14.164855,52.401516],"type":"Point"}
}