{
  "type": "Feature",
  "properties": {
    "iso:country":"DE",
    "sg:address":"Hutweide 57",
    "sg:city":"B\u00e4renstein",
    "sg:phone":"+49 37347/1236",
    "sg:postcode":"09471",
    "sg:province":"Sachsen",
    "wof:name":"G\u00e4stehaus Hutweide",
    "wof:placetype":"venue"
},
  "geometry": {"coordinates":[13.0189666748,50.4859657288],"type":"Point"}
}