{
  "type": "Feature",
  "properties": {
    "iso:country":"DE",
    "sg:address":"Rahmenstr. 11",
    "sg:city":"Iserlohn",
    "sg:postcode":"58638",
    "sg:province":"Nordrhein-Westfalen",
    "wof:name":"Charel-moden",
    "wof:placetype":"venue"
},
  "geometry": {"coordinates":[7.690483,51.374138],"type":"Point"}
}