{
  "type": "Feature",
  "properties": {
    "iso:country":"DE",
    "sg:address":"Wallbacher Str. 1-3",
    "sg:city":"Walldorf",
    "sg:postcode":"98639",
    "sg:province":"Th\u00fcringen",
    "wof:name":"Inter-baumaschinenhandel Gmbh",
    "wof:placetype":"venue"
},
  "geometry": {"coordinates":[10.390584,50.618839],"type":"Point"}
}