{
  "type": "Feature",
  "properties": {
    "iso:country":"DE",
    "sg:address":"Mechenharder Str. 127",
    "sg:city":"Erlenbach",
    "sg:phone":"+49 9372/5149",
    "sg:postcode":"63906",
    "sg:province":"Bayern",
    "wof:name":"W. Sch\u00fcrger",
    "wof:placetype":"venue"
},
  "geometry": {"coordinates":[9.1901712418,49.7961883545],"type":"Point"}
}