{
  "type": "Feature",
  "properties": {
    "iso:country":"DE",
    "sg:address":"Ernsth\u00f6fer Str. 34",
    "sg:city":"Seeheim-Jugenheim",
    "sg:postcode":"64342",
    "sg:province":"Hessen",
    "wof:name":"Sigrid Und Peter Pl\u00f6\u00dfer",
    "wof:placetype":"venue"
},
  "geometry": {"coordinates":[8.6910400391,49.7653999329],"type":"Point"}
}