{
  "type": "Feature",
  "properties": {
    "iso:country":"DE",
    "sg:address":"Schwarzwaldstr. 17",
    "sg:city":"Schopfheim",
    "sg:phone":"+49 7622/7215",
    "sg:postcode":"79650",
    "sg:province":"Baden-W\u00fcrttemberg",
    "wof:name":"Jakob Freund",
    "wof:placetype":"venue"
},
  "geometry": {"coordinates":[7.8222851753,47.6466636658],"type":"Point"}
}