{
  "type": "Feature",
  "properties": {
    "iso:country":"DE",
    "sg:address":"Ferndorfstr. 178",
    "sg:city":"Hilchenbach",
    "sg:phone":"+49 2733/4588",
    "sg:postcode":"57271",
    "sg:province":"Nordrhein-Westfalen",
    "wof:name":"Ernst Sch\u00e4fer",
    "wof:placetype":"venue"
},
  "geometry": {"coordinates":[8.146924,51.006237],"type":"Point"}
}