{
  "type": "Feature",
  "properties": {
    "iso:country":"DE",
    "sg:address":"Heerstr. 2",
    "sg:city":"Drolshagen",
    "sg:phone":"+49 2763/7481",
    "sg:postcode":"57489",
    "sg:province":"Nordrhein-Westfalen",
    "wof:name":"Siegfried Neu Steuerberater Und",
    "wof:placetype":"venue"
},
  "geometry": {"coordinates":[7.7391810417,51.0627250671],"type":"Point"}
}