{
  "type": "Feature",
  "properties": {
    "iso:country":"DE",
    "sg:address":"Sch\u00fctzenstr. 56",
    "sg:city":"D\u00fcsseldorf",
    "sg:phone":"+49 211/357783",
    "sg:postcode":"40211",
    "sg:province":"Nordrhein-Westfalen",
    "wof:name":"Johanneskirchengemeinde D\u00fcsseldorf",
    "wof:placetype":"venue"
},
  "geometry": {"coordinates":[6.795126,51.226673],"type":"Point"}
}