{
  "type": "Feature",
  "properties": {
    "iso:country":"DE",
    "sg:address":"Im Bienengarten 5",
    "sg:city":"Mayen",
    "sg:phone":"+49 4926/516111",
    "sg:postcode":"56727",
    "sg:province":"Rheinland-Pfalz",
    "wof:name":"Kerstin Klee",
    "wof:placetype":"venue"
},
  "geometry": {"coordinates":[7.231605,50.295204],"type":"Point"}
}