{
  "type": "Feature",
  "properties": {
    "iso:country":"DE",
    "sg:address":"Am Hulsberg 59",
    "sg:city":"Bremen",
    "sg:phone":"+49 421/492636",
    "sg:postcode":"28205",
    "sg:province":"Bremen",
    "wof:name":"A. B\u00f6litz",
    "wof:placetype":"venue"
},
  "geometry": {"coordinates":[8.8469371796,53.0714607239],"type":"Point"}
}