{
  "type": "Feature",
  "properties": {
    "iso:country":"DE",
    "sg:address":"Am S\u00fclterberg 9",
    "sg:city":"Lehrte",
    "sg:phone":"+49 5132/2457",
    "sg:postcode":"31275",
    "sg:province":"Niedersachsen",
    "wof:name":"Julius Borchers",
    "wof:placetype":"venue"
},
  "geometry": {"coordinates":[9.956271,52.361103],"type":"Point"}
}