{
  "type": "Feature",
  "properties": {
    "iso:country":"DE",
    "sg:address":"Am Saaldamm 9",
    "sg:city":"Rudolstadt",
    "sg:phone":"+49 3672/43590",
    "sg:postcode":"07407",
    "sg:province":"Th\u00fcringen",
    "wof:name":"Architektur- Und Ingenieurb\u00fcro Gmbh",
    "wof:placetype":"venue"
},
  "geometry": {"coordinates":[11.33951,50.718544],"type":"Point"}
}