{
  "type": "Feature",
  "properties": {
    "iso:country":"DE",
    "sg:address":"Mariabergstr. 16",
    "sg:city":"Wiggensbach",
    "sg:phone":"+49 8370/1891",
    "sg:postcode":"87487",
    "sg:province":"Bayern",
    "wof:name":"Franziska Stabik Masseur",
    "wof:placetype":"venue"
},
  "geometry": {"coordinates":[10.257108,47.725811],"type":"Point"}
}