{
  "type": "Feature",
  "properties": {
    "iso:country":"DE",
    "sg:address":"Hauptstr. 36",
    "sg:city":"B\u00f6blingen",
    "sg:phone":"+49 7034/649901",
    "sg:postcode":"71034",
    "sg:province":"Baden-W\u00fcrttemberg",
    "wof:name":"B. Timm Anlageberater",
    "wof:placetype":"venue"
},
  "geometry": {"coordinates":[8.9483642578,48.692035675],"type":"Point"}
}