{
  "type": "Feature",
  "properties": {
    "iso:country":"DE",
    "sg:address":"Neue Str. 10",
    "sg:city":"Breidenbach",
    "sg:phone":"+49 6465/913060",
    "sg:postcode":"35236",
    "sg:province":"Hessen",
    "wof:name":"Konstruktionsb\u00fcro Kfc Gmbh",
    "wof:placetype":"venue"
},
  "geometry": {"coordinates":[8.4542703629,50.8862495422],"type":"Point"}
}