{
  "type": "Feature",
  "properties": {
    "iso:country":"DE",
    "sg:address":"Hinterbach 131",
    "sg:city":"Rattelsdorf",
    "sg:postcode":"96179",
    "sg:province":"Bayern",
    "wof:name":"Uhl & S\u00fcppel",
    "wof:placetype":"venue"
},
  "geometry": {"coordinates":[10.86201,50.060406],"type":"Point"}
}