{
  "type": "Feature",
  "properties": {
    "iso:country":"DE",
    "sg:address":"Horkaer Str. 180",
    "sg:city":"Rothenburg",
    "sg:postcode":"02929",
    "sg:province":"Sachsen",
    "wof:name":"Rothenburger Service Und Vertrieb Landtechnik Und",
    "wof:placetype":"venue"
},
  "geometry": {"coordinates":[14.95113,51.34444],"type":"Point"}
}