{
  "type": "Feature",
  "properties": {
    "iso:country":"DE",
    "sg:address":"Adelberger Str. 2",
    "sg:city":"Uhingen",
    "sg:phone":"+49 7161/32895",
    "sg:postcode":"73066",
    "sg:province":"Baden-W\u00fcrttemberg",
    "wof:name":"Fritz Veil",
    "wof:placetype":"venue"
},
  "geometry": {"coordinates":[9.584371,48.720257],"type":"Point"}
}