{
  "type": "Feature",
  "properties": {
    "iso:country":"DE",
    "sg:address":"Messings Garten 4",
    "sg:city":"Essen",
    "sg:phone":"+49 201/706011",
    "sg:postcode":"45147",
    "sg:province":"Nordrhein-Westfalen",
    "wof:name":"Familien- Und Krankenpflege E. V.",
    "wof:placetype":"venue"
},
  "geometry": {"coordinates":[6.973419,51.441353],"type":"Point"}
}