{
  "type": "Feature",
  "properties": {
    "iso:country":"DE",
    "sg:address":"Gr\u00f6benrieder Str. 21",
    "sg:city":"Dachau",
    "sg:phone":"+49 8131/56810",
    "sg:postcode":"85221",
    "sg:province":"Bayern",
    "wof:name":"Asv Dachau Werbe Gmbh",
    "wof:placetype":"venue"
},
  "geometry": {"coordinates":[11.4352750778,48.2447319031],"type":"Point"}
}