{
  "type": "Feature",
  "properties": {
    "iso:country":"DE",
    "sg:address":"Saydaer Str. 18",
    "sg:city":"Heidersdorf",
    "sg:phone":"+49 4937/3614640",
    "sg:postcode":"09526",
    "sg:province":"Sachsen",
    "wof:name":"Heidersdorfer Produktions & Vertriebs Gmbh",
    "wof:placetype":"venue"
},
  "geometry": {"coordinates":[13.419757,50.670269],"type":"Point"}
}