{
  "type": "Feature",
  "properties": {
    "iso:country":"DE",
    "sg:address":"Neue Str. 40",
    "sg:city":"Pinneberg",
    "sg:phone":"+49 4101/32061",
    "sg:postcode":"25421",
    "sg:province":"Schleswig-Holstein",
    "wof:name":"Decocolor Vertriebs- Gesellschaft Mbh",
    "wof:placetype":"venue"
},
  "geometry": {"coordinates":[9.8191566467,53.6417961121],"type":"Point"}
}