{
  "type": "Feature",
  "properties": {
    "iso:country":"DE",
    "sg:address":"B\u00fcnder Str. 1",
    "sg:city":"Bielefeld",
    "sg:phone":"+49 521/896176",
    "sg:postcode":"33613",
    "sg:province":"Nordrhein-Westfalen",
    "wof:name":"Rolf B\u00fcscher Reproduktionsanstalt",
    "wof:placetype":"venue"
},
  "geometry": {"coordinates":[8.532267,52.039101],"type":"Point"}
}