{
  "type": "Feature",
  "properties": {
    "iso:country":"DE",
    "sg:address":"Bismarckstr. 60",
    "sg:city":"D\u00fcsseldorf",
    "sg:phone":"+49 211/357249",
    "sg:postcode":"40210",
    "sg:province":"Nordrhein-Westfalen",
    "wof:name":"Holger K\u00e4mpfe",
    "wof:placetype":"venue"
},
  "geometry": {"coordinates":[6.7868537903,51.2219924927],"type":"Point"}
}