{
  "type": "Feature",
  "properties": {
    "iso:country":"DE",
    "sg:address":"Schuraer Str.",
    "sg:city":"Spaichingen",
    "sg:phone":"+49 7424/3665",
    "sg:postcode":"78549",
    "sg:province":"Baden-W\u00fcrttemberg",
    "wof:name":"Freibad",
    "wof:placetype":"venue"
},
  "geometry": {"coordinates":[8.7256546021,48.0713806152],"type":"Point"}
}