{
  "type": "Feature",
  "properties": {
    "iso:country":"DE",
    "sg:address":"Gerichtsstr. 18",
    "sg:city":"Bottrop",
    "sg:phone":"+49 2041/22014",
    "sg:postcode":"46236",
    "sg:province":"Nordrhein-Westfalen",
    "wof:name":"Volkmar Erwig Rechtsanwalt",
    "wof:placetype":"venue"
},
  "geometry": {"coordinates":[6.9267988205,51.5255088806],"type":"Point"}
}