{
  "type": "Feature",
  "properties": {
    "iso:country":"DE",
    "sg:address":"Winterbergstr. 96",
    "sg:city":"Dresden",
    "sg:phone":"+49 351/212500",
    "sg:postcode":"01237",
    "sg:province":"Sachsen",
    "wof:name":"An Der Rennbahn Inh. Ursula Bolz",
    "wof:placetype":"venue"
},
  "geometry": {"coordinates":[13.7961406708,51.0244941711],"type":"Point"}
}