{
  "type": "Feature",
  "properties": {
    "iso:country":"DE",
    "sg:address":"Hoogeweg 134a",
    "sg:city":"Kevelaer",
    "sg:phone":"+49 2832/93210",
    "sg:postcode":"47623",
    "sg:province":"Nordrhein-Westfalen",
    "wof:name":"Manu Tech Gmbh",
    "wof:placetype":"venue"
},
  "geometry": {"coordinates":[6.259868145,51.5819892883],"type":"Point"}
}