{
  "type": "Feature",
  "properties": {
    "iso:country":"DE",
    "sg:address":"Hohenzollerndamm 3",
    "sg:city":"Berlin",
    "sg:postcode":"10717",
    "sg:province":"Berlin",
    "wof:name":"Inter Select Verm\u00f6gens- Verwaltung Gmbh",
    "wof:placetype":"venue"
},
  "geometry": {"coordinates":[13.3291702271,52.4953956604],"type":"Point"}
}