{
  "type": "Feature",
  "properties": {
    "iso:country":"DE",
    "sg:address":"Huglfinger Str. 31",
    "sg:city":"Polling",
    "sg:phone":"+49 881/61543",
    "sg:postcode":"82398",
    "sg:province":"Bayern",
    "wof:name":"Apsis Andreas Und Peter Solymosi",
    "wof:placetype":"venue"
},
  "geometry": {"coordinates":[11.124987,47.808926],"type":"Point"}
}