{
  "type": "Feature",
  "properties": {
    "iso:country":"DE",
    "sg:address":"Gl\u00fcck-Auf-Str. 3",
    "sg:city":"Freital",
    "sg:phone":"+49 351/6502906",
    "sg:postcode":"01705",
    "sg:province":"Sachsen",
    "wof:name":"Stern-apotheke Wolfgang Lorenz",
    "wof:placetype":"venue"
},
  "geometry": {"coordinates":[13.68211,51.004086],"type":"Point"}
}