{
  "type": "Feature",
  "properties": {
    "iso:country":"DE",
    "sg:address":"Weinbrennerstr. 30",
    "sg:city":"Karlsruhe",
    "sg:phone":"+49 721/842464",
    "sg:postcode":"76135",
    "sg:province":"Baden-W\u00fcrttemberg",
    "wof:name":"Carisma",
    "wof:placetype":"venue"
},
  "geometry": {"coordinates":[8.3745422363,49.0067176819],"type":"Point"}
}