{
  "type": "Feature",
  "properties": {
    "iso:country":"DE",
    "sg:address":"Dhr\u00f6nchen 1",
    "sg:city":"Trittenheim",
    "sg:phone":"+49 6507/4229",
    "sg:postcode":"54349",
    "sg:province":"Rheinland-Pfalz",
    "wof:name":"Stefan Ritz",
    "wof:placetype":"venue"
},
  "geometry": {"coordinates":[6.9171328545,49.8161773682],"type":"Point"}
}