{
  "type": "Feature",
  "properties": {
    "iso:country":"DE",
    "sg:address":"Rathausplatz 1",
    "sg:city":"Heroldsbach",
    "sg:phone":"+49 9190/597",
    "sg:postcode":"91336",
    "sg:province":"Bayern",
    "wof:name":"Raiffeisenbank Heroldsbach Eg",
    "wof:placetype":"venue"
},
  "geometry": {"coordinates":[10.998955,49.692852],"type":"Point"}
}