{
  "type": "Feature",
  "properties": {
    "iso:country":"DE",
    "sg:address":"Hauptstr. 62",
    "sg:city":"Neunkirchen",
    "sg:phone":"+49 6262/6261",
    "sg:postcode":"74867",
    "sg:province":"Baden-W\u00fcrttemberg",
    "wof:name":"Adam Kleim",
    "wof:placetype":"venue"
},
  "geometry": {"coordinates":[9.010143,49.38773],"type":"Point"}
}