{
  "type": "Feature",
  "properties": {
    "iso:country":"DE",
    "sg:address":"Habbr\u00fcgger Weg 23",
    "sg:city":"Ganderkesee",
    "sg:phone":"+49 4222/79332",
    "sg:postcode":"27777",
    "sg:province":"Niedersachsen",
    "wof:name":"Bierst\u00fcbchen",
    "wof:placetype":"venue"
},
  "geometry": {"coordinates":[8.5339269638,53.0371780396],"type":"Point"}
}