{
  "type": "Feature",
  "properties": {
    "iso:country":"DE",
    "sg:address":"Raiffeisenstr. 68",
    "sg:city":"Unterschlei\u00dfheim",
    "sg:phone":"+49 89/3175594",
    "sg:postcode":"85716",
    "sg:province":"Bayern",
    "wof:name":"Norbert Werner Rechtsanwalt",
    "wof:placetype":"venue"
},
  "geometry": {"coordinates":[11.5729446411,48.2753791809],"type":"Point"}
}