{
  "type": "Feature",
  "properties": {
    "iso:country":"DE",
    "sg:address":"Steinkirchener Str. 1a",
    "sg:city":"Dachau",
    "sg:phone":"+49 8131/72439",
    "sg:postcode":"85221",
    "sg:province":"Bayern",
    "wof:name":"R. Hornung",
    "wof:placetype":"venue"
},
  "geometry": {"coordinates":[11.435287,48.263969],"type":"Point"}
}