{
  "type": "Feature",
  "properties": {
    "iso:country":"DE",
    "sg:address":"Hofgasse 8",
    "sg:city":"F\u00fcrstenzell",
    "sg:phone":"+49 8502/3144",
    "sg:postcode":"94081",
    "sg:province":"Bayern",
    "wof:name":"Ratsweinst\u00fcberl",
    "wof:placetype":"venue"
},
  "geometry": {"coordinates":[13.318116188,48.5218582153],"type":"Point"}
}