{
  "type": "Feature",
  "properties": {
    "iso:country":"DE",
    "sg:address":"Am Wittenborn 70",
    "sg:city":"Hann. M\u00fcnden",
    "sg:phone":"+49 5541/31071",
    "sg:postcode":"34346",
    "sg:province":"Niedersachsen",
    "wof:name":"Thomas Volkmer Architekt",
    "wof:placetype":"venue"
},
  "geometry": {"coordinates":[9.666585,51.401131],"type":"Point"}
}