{
  "type": "Feature",
  "properties": {
    "iso:country":"DE",
    "sg:address":"Edisonstr. 6",
    "sg:city":"Unterschlei\u00dfheim",
    "sg:phone":"+49 89/3740590",
    "sg:postcode":"85716",
    "sg:province":"Bayern",
    "wof:name":"Ibykus Ag Zweigndl. Unterschlei\u00dfheim",
    "wof:placetype":"venue"
},
  "geometry": {"coordinates":[11.5689630508,48.2860946655],"type":"Point"}
}