{
  "type": "Feature",
  "properties": {
    "iso:country":"DE",
    "sg:address":"Wilhelm-Wessel-Str. 9",
    "sg:city":"Iserlohn",
    "sg:phone":"+49 2371/68718",
    "sg:postcode":"58636",
    "sg:province":"Nordrhein-Westfalen",
    "wof:name":"M. Nordmann-malkmus Rechtsanwalt",
    "wof:placetype":"venue"
},
  "geometry": {"coordinates":[7.7330198288,51.3733596802],"type":"Point"}
}