{
  "type": "Feature",
  "properties": {
    "iso:country":"DE",
    "sg:address":"Steinstr. 2",
    "sg:city":"\u00d6tigheim",
    "sg:phone":"+49 7222/23674",
    "sg:postcode":"76470",
    "sg:province":"Baden-W\u00fcrttemberg",
    "wof:name":"Anton K\u00fchn",
    "wof:placetype":"venue"
},
  "geometry": {"coordinates":[8.232523,48.890701],"type":"Point"}
}