{
  "type": "Feature",
  "properties": {
    "iso:country":"DE",
    "sg:address":"Rosgartenstr. 9",
    "sg:city":"Konstanz",
    "sg:phone":"+49 7531/24700",
    "sg:postcode":"78462",
    "sg:province":"Baden-W\u00fcrttemberg",
    "wof:name":"Cafe Rosgarten",
    "wof:placetype":"venue"
},
  "geometry": {"coordinates":[9.1748847961,47.659828186],"type":"Point"}
}