{
  "type": "Feature",
  "properties": {
    "iso:country":"DE",
    "sg:address":"Dreishofstr. 12",
    "sg:city":"Unna",
    "sg:phone":"+49 2303/22740",
    "sg:postcode":"59425",
    "sg:province":"Nordrhein-Westfalen",
    "wof:name":"Wbk Weierke Beton- Und Korrosionsschutz Gmbh",
    "wof:placetype":"venue"
},
  "geometry": {"coordinates":[7.7229142189,51.5431671143],"type":"Point"}
}