{
  "type": "Feature",
  "properties": {
    "iso:country":"DE",
    "sg:address":"Thietorstr. 2",
    "sg:city":"Hameln",
    "sg:phone":"+49 5151/41840",
    "sg:postcode":"31785",
    "sg:province":"Niedersachsen",
    "wof:name":"Foto-oehlmann",
    "wof:placetype":"venue"
},
  "geometry": {"coordinates":[9.3551559448,52.106098175],"type":"Point"}
}