{
  "type": "Feature",
  "properties": {
    "iso:country":"DE",
    "sg:address":"Herscheider Landstr. 49",
    "sg:city":"L\u00fcdenscheid",
    "sg:phone":"+49 2351/458761",
    "sg:postcode":"58511",
    "sg:province":"Nordrhein-Westfalen",
    "wof:name":"Pizzeria Grill Zur H\u00f6h",
    "wof:placetype":"venue"
},
  "geometry": {"coordinates":[7.6508541107,51.2099266052],"type":"Point"}
}