{
  "type": "Feature",
  "properties": {
    "iso:country":"DE",
    "sg:address":"Benzstr. 2",
    "sg:city":"Landshut",
    "sg:phone":"+49 871/73420",
    "sg:postcode":"84030",
    "sg:province":"Bayern",
    "wof:name":"Textilia Hermann H\u00d6nnl Kg",
    "wof:placetype":"venue"
},
  "geometry": {"coordinates":[12.153198,48.552647],"type":"Point"}
}