{
  "type": "Feature",
  "properties": {
    "iso:country":"DE",
    "sg:address":"Blessenberg 35",
    "sg:city":"Eutin",
    "sg:phone":"+49 4521/2040",
    "sg:postcode":"23701",
    "sg:province":"Schleswig-Holstein",
    "wof:name":"Dr. Lutz Werner Tierarzt",
    "wof:placetype":"venue"
},
  "geometry": {"coordinates":[10.6132249832,54.1588668823],"type":"Point"}
}