{
  "type": "Feature",
  "properties": {
    "iso:country":"DE",
    "sg:address":"Berggartenstra\u00dfe 19",
    "sg:city":"Dresden",
    "sg:phone":"+49 351/3103030",
    "sg:postcode":"01277",
    "sg:province":"Sachsen",
    "wof:name":"Super-tele Tv 1.dresdner Telefon- Und Kabel-tv Gesellschaft",
    "wof:placetype":"venue"
},
  "geometry": {"coordinates":[13.809006,51.047623],"type":"Point"}
}