{
  "type": "Feature",
  "properties": {
    "iso:country":"DE",
    "sg:address":"Silcherstr. 33",
    "sg:city":"Deizisau",
    "sg:phone":"+49 7153/898660",
    "sg:postcode":"73779",
    "sg:province":"Baden-W\u00fcrttemberg",
    "wof:name":"D. M. Kr\u00fcger Steuerberater",
    "wof:placetype":"venue"
},
  "geometry": {"coordinates":[9.3858509064,48.7147026062],"type":"Point"}
}