{
  "type": "Feature",
  "properties": {
    "iso:country":"DE",
    "sg:address":"Straelener Weg 27",
    "sg:city":"Viersen",
    "sg:phone":"+49 2162/56173",
    "sg:postcode":"41751",
    "sg:province":"Nordrhein-Westfalen",
    "wof:name":"Thomas Schneppendahl Rechtsanwalt",
    "wof:placetype":"venue"
},
  "geometry": {"coordinates":[6.3339099884,51.2641487122],"type":"Point"}
}