{
  "type": "Feature",
  "properties": {
    "iso:country":"DE",
    "sg:address":"Leipziger Str. 100",
    "sg:city":"Leipzig",
    "sg:phone":"+49 341/2522240",
    "sg:postcode":"04178",
    "sg:province":"Sachsen",
    "wof:name":"C. Stehr",
    "wof:placetype":"venue"
},
  "geometry": {"coordinates":[12.289193,51.360062],"type":"Point"}
}