{
  "type": "Feature",
  "properties": {
    "iso:country":"DE",
    "sg:address":"D\u00f6rflaser Hauptstr. 41",
    "sg:city":"Marktredwitz",
    "sg:phone":"+49 9231/2292",
    "sg:postcode":"95615",
    "sg:province":"Bayern",
    "wof:name":"Vereinsgastst\u00e4tte Turnverein D\u00f6rflas E. V.",
    "wof:placetype":"venue"
},
  "geometry": {"coordinates":[12.0863399506,49.9954185486],"type":"Point"}
}