{
  "type": "Feature",
  "properties": {
    "iso:country":"DE",
    "sg:address":"Landsberger Str. 24",
    "sg:city":"P\u00fcrgen",
    "sg:phone":"+49 8196/252",
    "sg:postcode":"86932",
    "sg:province":"Bayern",
    "wof:name":"Ritzau Kg",
    "wof:placetype":"venue"
},
  "geometry": {"coordinates":[10.9174585342,48.0282440186],"type":"Point"}
}