{
  "type": "Feature",
  "properties": {
    "iso:country":"DE",
    "sg:address":"Gottschedstr. 4",
    "sg:city":"Berlin",
    "sg:phone":"+49 30/4627822",
    "sg:postcode":"13357",
    "sg:province":"Berlin",
    "wof:name":"Andrea Hund-tasan",
    "wof:placetype":"venue"
},
  "geometry": {"coordinates":[13.369519,52.5504],"type":"Point"}
}