{
  "type": "Feature",
  "properties": {
    "iso:country":"DE",
    "sg:address":"Trixweg 18",
    "sg:city":"Neukirchen-Vluyn",
    "sg:phone":"+49 2845/2413",
    "sg:postcode":"47506",
    "sg:province":"Nordrhein-Westfalen",
    "wof:name":"Peter Hasenrahm",
    "wof:placetype":"venue"
},
  "geometry": {"coordinates":[6.556714,51.427303],"type":"Point"}
}