{
  "type": "Feature",
  "properties": {
    "iso:country":"DE",
    "sg:address":"Tirolerstr. 2",
    "sg:city":"Bonndorf",
    "sg:phone":"+49 7653/9136",
    "sg:postcode":"79848",
    "sg:province":"Baden-W\u00fcrttemberg",
    "wof:name":"Lothar B\u00f6hler",
    "wof:placetype":"venue"
},
  "geometry": {"coordinates":[8.2641057968,47.8494567871],"type":"Point"}
}