{
  "type": "Feature",
  "properties": {
    "iso:country":"DE",
    "sg:address":"Rosenstr. 15",
    "sg:city":"Sulzberg",
    "sg:phone":"+49 831/561520",
    "sg:postcode":"87477",
    "sg:province":"Bayern",
    "wof:name":"Schropp Gmbh",
    "wof:placetype":"venue"
},
  "geometry": {"coordinates":[10.3265657425,47.6894683838],"type":"Point"}
}