{
  "type": "Feature",
  "properties": {
    "iso:country":"DE",
    "sg:address":"Marienstr. 8",
    "sg:city":"Marktredwitz",
    "sg:phone":"+49 9231/661361",
    "sg:postcode":"95615",
    "sg:province":"Bayern",
    "wof:name":"Gastst\u00e4tte Brotzeitst\u00fcberl",
    "wof:placetype":"venue"
},
  "geometry": {"coordinates":[12.0951452255,50.0058860779],"type":"Point"}
}