{
  "type": "Feature",
  "properties": {
    "iso:country":"DE",
    "sg:address":"M\u00fchlenteichstr. 35",
    "sg:city":"Varel",
    "sg:phone":"+49 4944/515758",
    "sg:postcode":"26316",
    "sg:province":"Niedersachsen",
    "wof:name":"Hugo Gert-schl\u00dchr Gmbh & Co.",
    "wof:placetype":"venue"
},
  "geometry": {"coordinates":[8.0900402069,53.3769493103],"type":"Point"}
}