{
  "type": "Feature",
  "properties": {
    "iso:country":"DE",
    "sg:address":"Waldweg 18",
    "sg:city":"Donaustauf",
    "sg:phone":"+49 9403/1626",
    "sg:postcode":"93093",
    "sg:province":"Bayern",
    "wof:name":"Max Fisch",
    "wof:placetype":"venue"
},
  "geometry": {"coordinates":[12.245226,49.028854],"type":"Point"}
}