{
  "type": "Feature",
  "properties": {
    "iso:country":"DE",
    "sg:address":"Im L\u00f6hfeld 19",
    "sg:city":"Lindlar",
    "sg:phone":"+49 2266/7067",
    "sg:postcode":"51789",
    "sg:province":"Nordrhein-Westfalen",
    "wof:name":"Gr\u00fcnhage Ohg",
    "wof:placetype":"venue"
},
  "geometry": {"coordinates":[7.4291911125,51.0492362976],"type":"Point"}
}