{
  "type": "Feature",
  "properties": {
    "iso:country":"DE",
    "sg:address":"Bahnhofstr. 10",
    "sg:city":"Gro\u00dfengottern",
    "sg:phone":"+49 36022/96333",
    "sg:postcode":"99991",
    "sg:province":"Th\u00fcringen",
    "wof:name":"Georg R\u00fcmpler",
    "wof:placetype":"venue"
},
  "geometry": {"coordinates":[10.562346,51.145607],"type":"Point"}
}