{
  "type": "Feature",
  "properties": {
    "iso:country":"DE",
    "sg:address":"Schmiechastr. 84",
    "sg:city":"Albstadt",
    "sg:phone":"+49 7431/2220",
    "sg:postcode":"72458",
    "sg:province":"Baden-W\u00fcrttemberg",
    "wof:name":"Diebold & Streich",
    "wof:placetype":"venue"
},
  "geometry": {"coordinates":[9.0282,48.222149],"type":"Point"}
}