{
  "type": "Feature",
  "properties": {
    "iso:country":"DE",
    "sg:city":"Neulehe",
    "sg:phone":"+49 4968/269",
    "sg:postcode":"26909",
    "sg:province":"Niedersachsen",
    "wof:name":"Walburga Bruns",
    "wof:placetype":"venue"
},
  "geometry": {"coordinates":[7.413795,53.004662],"type":"Point"}
}