{
  "type": "Feature",
  "properties": {
    "iso:country":"DE",
    "sg:address":"Keplerstr. 75",
    "sg:city":"M\u00f6nchengladbach",
    "sg:phone":"+49 2166/41172",
    "sg:postcode":"41236",
    "sg:province":"Nordrhein-Westfalen",
    "wof:name":"Katholisches Pfarramt St. Josef",
    "wof:placetype":"venue"
},
  "geometry": {"coordinates":[6.4518680573,51.1619682312],"type":"Point"}
}