{
  "type": "Feature",
  "properties": {
    "iso:country":"DE",
    "sg:address":"Vidumstr. 1",
    "sg:city":"Westerkappeln",
    "sg:phone":"+49 5404/96180",
    "sg:postcode":"49492",
    "sg:province":"Nordrhein-Westfalen",
    "wof:name":"Schulte-derne Gmbh",
    "wof:placetype":"venue"
},
  "geometry": {"coordinates":[7.886578083,52.3132247925],"type":"Point"}
}