{
  "type": "Feature",
  "properties": {
    "iso:country":"DE",
    "sg:address":"Eschenweg 4",
    "sg:city":"Eberswalde",
    "sg:phone":"+49 3334/235420",
    "sg:postcode":"16225",
    "sg:province":"Brandenburg",
    "wof:name":"G. Milbradt",
    "wof:placetype":"venue"
},
  "geometry": {"coordinates":[13.821477,52.847244],"type":"Point"}
}