{
  "type": "Feature",
  "properties": {
    "iso:country":"DE",
    "sg:address":"Neschwitzer Str. 31",
    "sg:city":"Kamenz",
    "sg:phone":"+49 35783/00200",
    "sg:postcode":"01917",
    "sg:province":"Sachsen",
    "wof:name":"Erholung",
    "wof:placetype":"venue"
},
  "geometry": {"coordinates":[14.104684,51.274258],"type":"Point"}
}