{
  "type": "Feature",
  "properties": {
    "iso:country":"DE",
    "sg:address":"Berliner Str. 3",
    "sg:city":"Berlin",
    "sg:postcode":"14169",
    "sg:province":"Berlin",
    "wof:name":"Claudia Schulz Steuerberaterin",
    "wof:placetype":"venue"
},
  "geometry": {"coordinates":[13.2617750168,52.4351615906],"type":"Point"}
}