{
  "type": "Feature",
  "properties": {
    "iso:country":"DE",
    "sg:address":"Lerchenweg 10",
    "sg:city":"Vollersode",
    "sg:phone":"+49 4793/8355",
    "sg:postcode":"27729",
    "sg:province":"Niedersachsen",
    "wof:name":"Devk Versicherungen",
    "wof:placetype":"venue"
},
  "geometry": {"coordinates":[8.868806839,53.32447052],"type":"Point"}
}