{
  "type": "Feature",
  "properties": {
    "iso:country":"DE",
    "sg:address":"Haselquanten 2",
    "sg:city":"Hunderdorf",
    "sg:phone":"+49 9961/509",
    "sg:postcode":"94336",
    "sg:province":"Bayern",
    "wof:name":"Holzbearbeitungsbetrieb Hornberger Gmbh",
    "wof:placetype":"venue"
},
  "geometry": {"coordinates":[12.739692688,48.954158783],"type":"Point"}
}