{
  "type": "Feature",
  "properties": {
    "iso:country":"DE",
    "sg:address":"Lachnerstr. 1 e",
    "sg:city":"Hamburg",
    "sg:postcode":"22083",
    "sg:province":"Hamburg",
    "wof:name":"Feinschild Gmbh",
    "wof:placetype":"venue"
},
  "geometry": {"coordinates":[10.032559,53.574188],"type":"Point"}
}