{
  "type": "Feature",
  "properties": {
    "iso:country":"DE",
    "sg:address":"Kamener Str. 160",
    "sg:city":"Hamm",
    "sg:phone":"+49 2381/400578",
    "sg:postcode":"59077",
    "sg:province":"Nordrhein-Westfalen",
    "wof:name":"W. Hegemann",
    "wof:placetype":"venue"
},
  "geometry": {"coordinates":[7.752456,51.642563],"type":"Point"}
}