{
  "type": "Feature",
  "properties": {
    "iso:country":"DE",
    "sg:address":"Sportheimstr. 2",
    "sg:city":"Ried",
    "sg:phone":"+49 8233/6278",
    "sg:postcode":"86510",
    "sg:province":"Bayern",
    "wof:name":"Josef Straucher",
    "wof:placetype":"venue"
},
  "geometry": {"coordinates":[11.047934,48.291122],"type":"Point"}
}