{
  "type": "Feature",
  "properties": {
    "iso:country":"DE",
    "sg:address":"Purchhauserstr. 5",
    "sg:city":"Lenting",
    "sg:phone":"+49 8456/1212",
    "sg:postcode":"85101",
    "sg:province":"Bayern",
    "wof:name":"V. Und B. Schupfer",
    "wof:placetype":"venue"
},
  "geometry": {"coordinates":[11.456728,48.812279],"type":"Point"}
}