{
  "type": "Feature",
  "properties": {
    "iso:country":"DE",
    "sg:address":"Mettendorfer Weg 24",
    "sg:city":"Greding",
    "sg:phone":"+49 8463/606160",
    "sg:postcode":"91171",
    "sg:province":"Bayern",
    "wof:name":"Steintek Gmbh",
    "wof:placetype":"venue"
},
  "geometry": {"coordinates":[11.3622341156,49.0420074463],"type":"Point"}
}