{
  "type": "Feature",
  "properties": {
    "iso:country":"DE",
    "sg:address":"Pestalozzistr. 58",
    "sg:city":"D\u00fcsseldorf",
    "sg:phone":"+49 211/501434",
    "sg:postcode":"40549",
    "sg:province":"Nordrhein-Westfalen",
    "wof:name":"Franz Meyer",
    "wof:placetype":"venue"
},
  "geometry": {"coordinates":[6.719449,51.230076],"type":"Point"}
}