{
  "type": "Feature",
  "properties": {
    "iso:country":"DE",
    "sg:address":"Lerchenweg 34",
    "sg:city":"Bodnegg",
    "sg:postcode":"88285",
    "sg:province":"Baden-W\u00fcrttemberg",
    "wof:name":"G\u00fcnter Heine Verwaltungs Gmbh",
    "wof:placetype":"venue"
},
  "geometry": {"coordinates":[9.6903800964,47.7065696716],"type":"Point"}
}