{
  "type": "Feature",
  "properties": {
    "iso:country":"DE",
    "sg:address":"Rottweiler Str. 29",
    "sg:city":"Villingen-Schwenningen",
    "sg:phone":"+49 7720/5535",
    "sg:postcode":"78056",
    "sg:province":"Baden-W\u00fcrttemberg",
    "wof:name":"Wolfgang M\u00fcller",
    "wof:placetype":"venue"
},
  "geometry": {"coordinates":[8.5460357666,48.0642776489],"type":"Point"}
}