{
  "type": "Feature",
  "properties": {
    "iso:country":"DE",
    "sg:address":"Beethovenstr. 22",
    "sg:city":"Bad F\u00fcssing",
    "sg:postcode":"94072",
    "sg:province":"Bayern",
    "wof:name":"Kaisers Drugstore",
    "wof:placetype":"venue"
},
  "geometry": {"coordinates":[13.316402,48.35043],"type":"Point"}
}