{
  "type": "Feature",
  "properties": {
    "iso:country":"DE",
    "sg:address":"Merianstr. 13-15",
    "sg:city":"Freiburg",
    "sg:phone":"+49 761/282730",
    "sg:postcode":"79098",
    "sg:province":"Baden-W\u00fcrttemberg",
    "wof:name":"R & V Allgemeine Versicherung Ag",
    "wof:placetype":"venue"
},
  "geometry": {"coordinates":[7.8498148918,47.9974479675],"type":"Point"}
}