{
  "type": "Feature",
  "properties": {
    "iso:country":"DE",
    "sg:address":"Neustr. 35 A",
    "sg:city":"Emmendingen",
    "sg:postcode":"79312",
    "sg:province":"Baden-W\u00fcrttemberg",
    "wof:name":"Schlachthaus Verwaltungs Gmbh",
    "wof:placetype":"venue"
},
  "geometry": {"coordinates":[7.839404,48.12302],"type":"Point"}
}