{
  "type": "Feature",
  "properties": {
    "iso:country":"DE",
    "sg:address":"Mariendorfer Damm 408",
    "sg:city":"Berlin",
    "sg:phone":"+49 30/7412625",
    "sg:postcode":"12107",
    "sg:province":"Berlin",
    "wof:name":"J\u00f6rg H\u00f6land",
    "wof:placetype":"venue"
},
  "geometry": {"coordinates":[13.3985786438,52.4184875488],"type":"Point"}
}