{
  "type": "Feature",
  "properties": {
    "iso:country":"DE",
    "sg:address":"Kirchstr. 44",
    "sg:city":"Arnsberg",
    "sg:phone":"+49 2937/81095",
    "sg:postcode":"59823",
    "sg:province":"Nordrhein-Westfalen",
    "wof:name":"Wilhelm Blome",
    "wof:placetype":"venue"
},
  "geometry": {"coordinates":[8.1359539032,51.3944740295],"type":"Point"}
}