{
  "type": "Feature",
  "properties": {
    "iso:country":"DE",
    "sg:address":"Turnerstr. 27",
    "sg:city":"Bielefeld",
    "sg:phone":"+49 521/965450",
    "sg:postcode":"33602",
    "sg:province":"Nordrhein-Westfalen",
    "wof:name":"Werbung > Planet Weco",
    "wof:placetype":"venue"
},
  "geometry": {"coordinates":[8.537101,52.019882],"type":"Point"}
}