{
  "type": "Feature",
  "properties": {
    "iso:country":"DE",
    "sg:address":"Ahrstr. 2a",
    "sg:city":"Meckenheim",
    "sg:phone":"+49 2225/14672",
    "sg:postcode":"53340",
    "sg:province":"Nordrhein-Westfalen",
    "wof:name":"Richard Frey",
    "wof:placetype":"venue"
},
  "geometry": {"coordinates":[7.01574,50.591339],"type":"Point"}
}