{
  "type": "Feature",
  "properties": {
    "iso:country":"DE",
    "sg:address":"Am Berger Spielhaus 1",
    "sg:city":"Frankfurt",
    "sg:phone":"+49 6109/23273",
    "sg:postcode":"60388",
    "sg:province":"Hessen",
    "wof:name":"Stadtsch\u00e4nke",
    "wof:placetype":"venue"
},
  "geometry": {"coordinates":[8.753739357,50.1553649902],"type":"Point"}
}