{
  "type": "Feature",
  "properties": {
    "iso:country":"DE",
    "sg:address":"Neidenburger Allee 11",
    "sg:city":"Berlin",
    "sg:phone":"+49 30/3022939",
    "sg:postcode":"14055",
    "sg:province":"Berlin",
    "wof:name":"Dr. Eberhard Schmidt Tierarzt",
    "wof:placetype":"venue"
},
  "geometry": {"coordinates":[13.2589912415,52.5046920776],"type":"Point"}
}