{
  "type": "Feature",
  "properties": {
    "iso:country":"DE",
    "sg:address":"Fredersdorfer Str. 10",
    "sg:city":"Berlin",
    "sg:phone":"+49 30/2936306",
    "sg:postcode":"10243",
    "sg:province":"Berlin",
    "wof:name":"Kurb\u00fcro Dr. Tschacher Ges. F\u00fcr Die Vermittlung Beratung Und",
    "wof:placetype":"venue"
},
  "geometry": {"coordinates":[13.4424161911,52.5142059326],"type":"Point"}
}