{
  "type": "Feature",
  "properties": {
    "iso:country":"DE",
    "sg:address":"Gro\u00dfe Sankt Ilsenstr. 22",
    "sg:city":"Salzwedel",
    "sg:phone":"+49 3901/81167",
    "sg:postcode":"29410",
    "sg:province":"Sachsen-Anhalt",
    "wof:name":"Emc Gmbh",
    "wof:placetype":"venue"
},
  "geometry": {"coordinates":[11.1562833786,52.8514785767],"type":"Point"}
}