{
  "type": "Feature",
  "properties": {
    "iso:country":"DE",
    "sg:address":"Kirschenallee 2",
    "sg:city":"Neustrelitz",
    "sg:phone":"+49 3981/445420",
    "sg:postcode":"17235",
    "sg:province":"Mecklenburg-Vorpommern",
    "wof:name":"Karin Wiedemann Rechtsanw\u00e4ltin",
    "wof:placetype":"venue"
},
  "geometry": {"coordinates":[13.0749111176,53.3563156128],"type":"Point"}
}