{
  "type": "Feature",
  "properties": {
    "iso:country":"DE",
    "sg:address":"Bayreuther Str. 21",
    "sg:city":"N\u00fcrnberg",
    "sg:phone":"+49 911/550069",
    "sg:postcode":"90409",
    "sg:province":"Bayern",
    "wof:name":"Fortuna-apotheke Ingrid Tollk\u00fchn E. K.",
    "wof:placetype":"venue"
},
  "geometry": {"coordinates":[11.09145,49.460461],"type":"Point"}
}