{
  "type": "Feature",
  "properties": {
    "iso:country":"DE",
    "sg:address":"Babinger Str. 2",
    "sg:city":"Velden",
    "sg:phone":"+49 8742/96010",
    "sg:postcode":"84149",
    "sg:province":"Bayern",
    "wof:name":"Bay Wa Ag",
    "wof:placetype":"venue"
},
  "geometry": {"coordinates":[12.248405,48.364525],"type":"Point"}
}