{
  "type": "Feature",
  "properties": {
    "iso:country":"DE",
    "sg:address":"Vollersweg 30",
    "sg:city":"Ganderkesee",
    "sg:phone":"+49 4223/585",
    "sg:postcode":"27777",
    "sg:province":"Niedersachsen",
    "wof:name":"He\u00dfe Rolladenbau",
    "wof:placetype":"venue"
},
  "geometry": {"coordinates":[8.53925,53.104614],"type":"Point"}
}