{
  "type": "Feature",
  "properties": {
    "iso:country":"DE",
    "sg:address":"Ratzeburger Allee 2a",
    "sg:city":"L\u00fcbeck",
    "sg:phone":"+49 451/796697",
    "sg:postcode":"23564",
    "sg:province":"Schleswig-Holstein",
    "wof:name":"H. D\u00fcrkop",
    "wof:placetype":"venue"
},
  "geometry": {"coordinates":[10.691976,53.858036],"type":"Point"}
}