{
  "type": "Feature",
  "properties": {
    "iso:country":"DE",
    "sg:address":"Schlo\u00dfstr. 21",
    "sg:city":"Radeberg",
    "sg:phone":"+49 3528/442477",
    "sg:postcode":"01454",
    "sg:province":"Sachsen",
    "wof:name":"H\u00fctterm\u00fchle",
    "wof:placetype":"venue"
},
  "geometry": {"coordinates":[13.9258098602,51.1194000244],"type":"Point"}
}