{
  "type": "Feature",
  "properties": {
    "iso:country":"DE",
    "sg:address":"S\u00e4gem\u00fchlenstr. 17",
    "sg:city":"Unterl\u00fc\u00df",
    "sg:phone":"+49 4958/27248",
    "sg:postcode":"29345",
    "sg:province":"Niedersachsen",
    "wof:name":"Rudolf & Otto Schimek",
    "wof:placetype":"venue"
},
  "geometry": {"coordinates":[10.2955169678,52.8318862915],"type":"Point"}
}