{
  "type": "Feature",
  "properties": {
    "iso:country":"DE",
    "sg:address":"Op de Veih 123",
    "sg:city":"Bochum",
    "sg:phone":"+49 2327/71672",
    "sg:postcode":"44869",
    "sg:province":"Nordrhein-Westfalen",
    "wof:name":"Krug Zum Gr\u00fcnen Kranz",
    "wof:placetype":"venue"
},
  "geometry": {"coordinates":[7.153441906,51.4561882019],"type":"Point"}
}