{
  "type": "Feature",
  "properties": {
    "iso:country":"DE",
    "sg:address":"Stra\u00dfe des Friedens 27",
    "sg:city":"Menteroda",
    "sg:phone":"+49 36029/82448",
    "sg:postcode":"99996",
    "sg:province":"Th\u00fcringen",
    "wof:name":"Wohnungsbaugenossenschaft Meteroda Eg",
    "wof:placetype":"venue"
},
  "geometry": {"coordinates":[10.562444,51.309967],"type":"Point"}
}