{
  "type": "Feature",
  "properties": {
    "iso:country":"DE",
    "sg:address":"Beckengasse 3",
    "sg:city":"Zwiefalten",
    "sg:phone":"+49 7373/1216",
    "sg:postcode":"88529",
    "sg:province":"Baden-W\u00fcrttemberg",
    "wof:name":"Ernst Fuchsloch",
    "wof:placetype":"venue"
},
  "geometry": {"coordinates":[9.48156,48.253929],"type":"Point"}
}