{
  "type": "Feature",
  "properties": {
    "iso:country":"DE",
    "sg:address":"Ilmstr. 6",
    "sg:city":"Jena",
    "sg:phone":"+49 4936/4145440",
    "sg:postcode":"07743",
    "sg:province":"Th\u00fcringen",
    "wof:name":"Fega Elektro Gro\u00dfhandels Gmbh",
    "wof:placetype":"venue"
},
  "geometry": {"coordinates":[11.609094,50.946934],"type":"Point"}
}