{
  "type": "Feature",
  "properties": {
    "iso:country":"DE",
    "sg:address":"Hohenbirker Str. 8-12",
    "sg:city":"Remscheid",
    "sg:phone":"+49 4921/9188510",
    "sg:postcode":"42855",
    "sg:province":"Nordrhein-Westfalen",
    "wof:name":"Koll & Cie Gmbh & Co Kg",
    "wof:placetype":"venue"
},
  "geometry": {"coordinates":[7.1654291153,51.1981315613],"type":"Point"}
}