{
  "type": "Feature",
  "properties": {
    "iso:country":"DE",
    "sg:address":"Bismarckstr. 12",
    "sg:city":"K\u00f6ln",
    "sg:phone":"+49 221/5906554",
    "sg:postcode":"50672",
    "sg:province":"Nordrhein-Westfalen",
    "wof:name":"Gebr Entsorgungs- Und Beratungsges. F. D. Deutsche",
    "wof:placetype":"venue"
},
  "geometry": {"coordinates":[6.939139843,50.9426269531],"type":"Point"}
}