{
  "type": "Feature",
  "properties": {
    "iso:country":"DE",
    "sg:address":"Cervinusstr. 36",
    "sg:city":"Laubach",
    "sg:phone":"+49 6405/950380",
    "sg:postcode":"35321",
    "sg:province":"Hessen",
    "wof:name":"Nicole Querl-grupe Ergotherapiepraxis",
    "wof:placetype":"venue"
},
  "geometry": {"coordinates":[8.951517,50.54612],"type":"Point"}
}