{
  "type": "Feature",
  "properties": {
    "iso:country":"DE",
    "sg:address":"Glash\u00fcttenplatz 2",
    "sg:city":"Sprockh\u00f6vel",
    "sg:phone":"+49 2339/2182",
    "sg:postcode":"45549",
    "sg:province":"Nordrhein-Westfalen",
    "wof:name":"Masannek Zimmerei Und Holzbau Gmbh",
    "wof:placetype":"venue"
},
  "geometry": {"coordinates":[7.2752809525,51.3332252502],"type":"Point"}
}