{
  "type": "Feature",
  "properties": {
    "iso:country":"DE",
    "sg:address":"Johannes-Scheiffele-Str. 11",
    "sg:city":"Dillingen",
    "sg:phone":"+49 9071/588960",
    "sg:postcode":"89407",
    "sg:province":"Bayern",
    "wof:name":"Katers Electrocenter Dillingen Gmbh",
    "wof:placetype":"venue"
},
  "geometry": {"coordinates":[10.4758243561,48.5782241821],"type":"Point"}
}