{
  "type": "Feature",
  "properties": {
    "iso:country":"DE",
    "sg:address":"Frankenfelder Chaussee",
    "sg:city":"Luckenwalde",
    "sg:phone":"+49 3371/620037",
    "sg:postcode":"14943",
    "sg:province":"Brandenburg",
    "wof:name":"Schlemmerland Schnellgastronomie Gmbh",
    "wof:placetype":"venue"
},
  "geometry": {"coordinates":[13.1390447617,52.0984458923],"type":"Point"}
}