{
  "type": "Feature",
  "properties": {
    "iso:country":"DE",
    "sg:address":"Lerchenweg 5",
    "sg:city":"Waldmohr",
    "sg:phone":"+49 6373/3643",
    "sg:postcode":"66914",
    "sg:province":"Rheinland-Pfalz",
    "wof:name":"G. Friedle",
    "wof:placetype":"venue"
},
  "geometry": {"coordinates":[7.333794117,49.3911819458],"type":"Point"}
}