{
  "type": "Feature",
  "properties": {
    "iso:country":"DE",
    "sg:address":"Redtenbacherstr. 5",
    "sg:city":"Pforzheim",
    "sg:phone":"+49 7231/565055",
    "sg:postcode":"75177",
    "sg:province":"Baden-W\u00fcrttemberg",
    "wof:name":"Gustav Ramminger",
    "wof:placetype":"venue"
},
  "geometry": {"coordinates":[8.710256,48.899132],"type":"Point"}
}