{
  "type": "Feature",
  "properties": {
    "iso:country":"DE",
    "sg:address":"Am Josbach 1",
    "sg:city":"Eppstein",
    "sg:phone":"+49 6198/2247",
    "sg:postcode":"65817",
    "sg:province":"Hessen",
    "wof:name":"Baudekoration G\u00f6ttnauer Gmbh",
    "wof:placetype":"venue"
},
  "geometry": {"coordinates":[8.350436,50.15419],"type":"Point"}
}