{
  "type": "Feature",
  "properties": {
    "iso:country":"DE",
    "sg:address":"Langengasse 3",
    "sg:city":"Sulzfeld",
    "sg:phone":"+49 9321/7545",
    "sg:postcode":"97320",
    "sg:province":"Bayern",
    "wof:name":"Weinstube Michelskeller",
    "wof:placetype":"venue"
},
  "geometry": {"coordinates":[10.1323823929,49.708278656],"type":"Point"}
}