{
  "type": "Feature",
  "properties": {
    "iso:country":"DE",
    "sg:address":"Friedrich-Ebert-Str. 104",
    "sg:city":"Wuppertal",
    "sg:phone":"+49 202/306180",
    "sg:postcode":"42117",
    "sg:province":"Nordrhein-Westfalen",
    "wof:name":"Reinhard H\u00f6sterey",
    "wof:placetype":"venue"
},
  "geometry": {"coordinates":[7.132283,51.253059],"type":"Point"}
}