{
  "type": "Feature",
  "properties": {
    "iso:country":"DE",
    "sg:address":"Ulrichsstr. 24",
    "sg:city":"Grafrath",
    "sg:phone":"+49 8144/7524",
    "sg:postcode":"82284",
    "sg:province":"Bayern",
    "wof:name":"Siegfried Christner",
    "wof:placetype":"venue"
},
  "geometry": {"coordinates":[11.1584968567,48.1246795654],"type":"Point"}
}