{
  "type": "Feature",
  "properties": {
    "iso:country":"DE",
    "sg:address":"Heppendorfer Str. 21",
    "sg:city":"Elsdorf",
    "sg:phone":"+49 2274/3328",
    "sg:postcode":"50189",
    "sg:province":"Nordrhein-Westfalen",
    "wof:name":"Kath. Pfarramt St. Michael",
    "wof:placetype":"venue"
},
  "geometry": {"coordinates":[6.5912499428,50.9260635376],"type":"Point"}
}