{
  "type": "Feature",
  "properties": {
    "iso:country":"DE",
    "sg:address":"Kastell 17",
    "sg:city":"Moers",
    "sg:postcode":"47441",
    "sg:province":"Nordrhein-Westfalen",
    "wof:name":"Ristorante Leonardo Gmbh",
    "wof:placetype":"venue"
},
  "geometry": {"coordinates":[6.6256599426,51.4493789673],"type":"Point"}
}