{
  "type": "Feature",
  "properties": {
    "iso:country":"DE",
    "sg:address":"Bergwaldstr. 25",
    "sg:city":"Nagold",
    "sg:phone":"+49 7452/65131",
    "sg:postcode":"72202",
    "sg:province":"Baden-W\u00fcrttemberg",
    "wof:name":"Rolf Kalmbach Architekt",
    "wof:placetype":"venue"
},
  "geometry": {"coordinates":[8.740435,48.587505],"type":"Point"}
}