{
  "type": "Feature",
  "properties": {
    "iso:country":"DE",
    "sg:address":"H.-H.-Meier-Allee 32",
    "sg:city":"Bremen",
    "sg:phone":"+49 421/219457",
    "sg:postcode":"28213",
    "sg:province":"Bremen",
    "wof:name":"K\u00e4sekiste",
    "wof:placetype":"venue"
},
  "geometry": {"coordinates":[8.8447980881,53.0908851624],"type":"Point"}
}