{
  "type": "Feature",
  "properties": {
    "iso:country":"DE",
    "sg:address":"Postgartenstr. 3",
    "sg:city":"Schwandorf",
    "sg:phone":"+49 9431/2568",
    "sg:postcode":"92421",
    "sg:province":"Bayern",
    "wof:name":"Rudolf Peschel Kg",
    "wof:placetype":"venue"
},
  "geometry": {"coordinates":[12.107475,49.327377],"type":"Point"}
}