{
  "type": "Feature",
  "properties": {
    "iso:country":"DE",
    "sg:address":"Henriettenstr. 3",
    "sg:city":"Minden",
    "sg:phone":"+49 571/32339",
    "sg:postcode":"32423",
    "sg:province":"Nordrhein-Westfalen",
    "wof:name":"Christian-herbert Kirchner Architekt",
    "wof:placetype":"venue"
},
  "geometry": {"coordinates":[8.954044,52.293354],"type":"Point"}
}