{
  "type": "Feature",
  "properties": {
    "iso:country":"DE",
    "sg:address":"Karlstr. 70",
    "sg:city":"Gerstetten",
    "sg:phone":"+49 4973/236380",
    "sg:postcode":"89547",
    "sg:province":"Baden-W\u00fcrttemberg",
    "wof:name":"Em-ge Sportgeraete Gmbh & Co. Kg",
    "wof:placetype":"venue"
},
  "geometry": {"coordinates":[10.0289068222,48.6244430542],"type":"Point"}
}