{
  "type": "Feature",
  "properties": {
    "iso:country":"DE",
    "sg:address":"Abt-Bernhard-Str. 1",
    "sg:city":"Marienfeld",
    "sg:phone":"+49 5247/80035",
    "sg:postcode":"33428",
    "sg:province":"Nordrhein-Westfalen",
    "wof:name":"Sauna-park",
    "wof:placetype":"venue"
},
  "geometry": {"coordinates":[8.265817,51.948669],"type":"Point"}
}