{
  "type": "Feature",
  "properties": {
    "iso:country":"DE",
    "sg:address":"Moltkestr. 100",
    "sg:city":"D\u00fcsseldorf",
    "sg:phone":"+49 211/463825",
    "sg:postcode":"40479",
    "sg:province":"Nordrhein-Westfalen",
    "wof:name":"L. Bachhuber Bildhauerei",
    "wof:placetype":"venue"
},
  "geometry": {"coordinates":[6.79091,51.23753],"type":"Point"}
}