{
  "type": "Feature",
  "properties": {
    "iso:country":"DE",
    "sg:address":"Vaihinger Str. 9",
    "sg:city":"Ludwigsburg",
    "sg:phone":"+49 7141/36441",
    "sg:postcode":"71634",
    "sg:province":"Baden-W\u00fcrttemberg",
    "wof:name":"D. Ullrich Immobilienmakler",
    "wof:placetype":"venue"
},
  "geometry": {"coordinates":[9.1741123199,48.9044303894],"type":"Point"}
}