{
  "type": "Feature",
  "properties": {
    "iso:country":"DE",
    "sg:address":"Kipperstr. 44",
    "sg:city":"Hagen",
    "sg:postcode":"58135",
    "sg:province":"Nordrhein-Westfalen",
    "wof:name":"Erfolgreich Mit Iconnectstar",
    "wof:placetype":"venue"
},
  "geometry": {"coordinates":[7.402778,51.336666],"type":"Point"}
}