{
  "type": "Feature",
  "properties": {
    "iso:country":"DE",
    "sg:address":"Perkam 20",
    "sg:city":"Perkam",
    "sg:phone":"+49 9423/363",
    "sg:postcode":"94368",
    "sg:province":"Bayern",
    "wof:name":"Kath. Pfarramt Mari\u00e4 Himmelfahrt",
    "wof:placetype":"venue"
},
  "geometry": {"coordinates":[12.4401226044,48.8541107178],"type":"Point"}
}