{
  "type": "Feature",
  "properties": {
    "iso:country":"DE",
    "sg:address":"Freiheitstr. 19",
    "sg:city":"Singen",
    "sg:phone":"+49 7731/9520",
    "sg:postcode":"78224",
    "sg:province":"Baden-W\u00fcrttemberg",
    "wof:name":"C & A",
    "wof:placetype":"venue"
},
  "geometry": {"coordinates":[8.8375759125,47.7628059387],"type":"Point"}
}