{
  "type": "Feature",
  "properties": {
    "iso:country":"DE",
    "sg:address":"Waldstr. 38",
    "sg:city":"Rebesgr\u00fcn",
    "sg:phone":"+49 3744/211647",
    "sg:postcode":"08209",
    "sg:province":"Sachsen",
    "wof:name":"Jens Langner",
    "wof:placetype":"venue"
},
  "geometry": {"coordinates":[12.36024,50.523129],"type":"Point"}
}