{
  "type": "Feature",
  "properties": {
    "iso:country":"DE",
    "sg:address":"B\u00f6tzowstr. 17",
    "sg:city":"Berlin",
    "sg:phone":"+49 30/42857662",
    "sg:postcode":"10407",
    "sg:province":"Berlin",
    "wof:name":"Profil Haus Und Grund Verwaltungsgesellschaft Mbh",
    "wof:placetype":"venue"
},
  "geometry": {"coordinates":[13.4325704575,52.5306930542],"type":"Point"}
}