{
  "type": "Feature",
  "properties": {
    "iso:country":"DE",
    "sg:address":"Erfurter Tor 125",
    "sg:city":"T\u00f6ttelst\u00e4dt",
    "sg:phone":"+49 36208/686",
    "sg:postcode":"99100",
    "sg:province":"Th\u00fcringen",
    "wof:name":"Agrar T\u00f6ttelst\u00e4dt Gmbh",
    "wof:placetype":"venue"
},
  "geometry": {"coordinates":[10.8859138489,51.0067329407],"type":"Point"}
}