{
  "type": "Feature",
  "properties": {
    "iso:country":"DE",
    "sg:address":"An der Beeke 6",
    "sg:city":"Elze",
    "sg:phone":"+49 5068/3708",
    "sg:postcode":"31008",
    "sg:province":"Niedersachsen",
    "wof:name":"Werner Burose",
    "wof:placetype":"venue"
},
  "geometry": {"coordinates":[9.723907,52.1385],"type":"Point"}
}