{
  "type": "Feature",
  "properties": {
    "iso:country":"DE",
    "sg:address":"Friedrichstr. 16",
    "sg:city":"Ingersheim",
    "sg:phone":"+49 7142/54241",
    "sg:postcode":"74379",
    "sg:province":"Baden-W\u00fcrttemberg",
    "wof:name":"Barbara Aymar",
    "wof:placetype":"venue"
},
  "geometry": {"coordinates":[9.177365303,48.9603347778],"type":"Point"}
}