{
  "type": "Feature",
  "properties": {
    "iso:country":"DE",
    "sg:address":"Longericher Str. 179",
    "sg:city":"K\u00f6ln",
    "sg:phone":"+49 221/174745",
    "sg:postcode":"50739",
    "sg:province":"Nordrhein-Westfalen",
    "wof:name":"Elmo Tiefbau Gmbh",
    "wof:placetype":"venue"
},
  "geometry": {"coordinates":[6.925011158,50.9785766602],"type":"Point"}
}