{
  "type": "Feature",
  "properties": {
    "iso:country":"DE",
    "sg:address":"Horchstrasse 2",
    "sg:city":"Zwickau",
    "sg:phone":"+49 375/279990",
    "sg:postcode":"08058",
    "sg:province":"Sachsen",
    "wof:name":"Callcenter-zwickau",
    "wof:placetype":"venue"
},
  "geometry": {"coordinates":[12.481401,50.732418],"type":"Point"}
}