{
  "type": "Feature",
  "properties": {
    "iso:country":"DE",
    "sg:address":"Von-Arenberg-Str. 13",
    "sg:city":"S\u00f6gel",
    "sg:postcode":"49751",
    "sg:province":"Niedersachsen",
    "wof:name":"Mbbf Windpark Wulfen Verwaltungs- Und",
    "wof:placetype":"venue"
},
  "geometry": {"coordinates":[7.514379,52.849258],"type":"Point"}
}