{
  "type": "Feature",
  "properties": {
    "iso:country":"DE",
    "sg:address":"Krechtinger Str. 29",
    "sg:city":"Rhede",
    "sg:phone":"+49 2872/3033",
    "sg:postcode":"46414",
    "sg:province":"Nordrhein-Westfalen",
    "wof:name":"Schulte Klinkerhandel Gmbh",
    "wof:placetype":"venue"
},
  "geometry": {"coordinates":[6.6994290352,51.8322372437],"type":"Point"}
}