{
  "type": "Feature",
  "properties": {
    "iso:country":"DE",
    "sg:address":"Am Eichenhain 6",
    "sg:city":"Soltendieck",
    "sg:phone":"+49 5874/261",
    "sg:postcode":"29594",
    "sg:province":"Niedersachsen",
    "wof:name":"Peter Fehlhaber",
    "wof:placetype":"venue"
},
  "geometry": {"coordinates":[10.802102,52.880409],"type":"Point"}
}