{
  "type": "Feature",
  "properties": {
    "iso:country":"DE",
    "sg:address":"Allee 76",
    "sg:city":"Ballenstedt",
    "sg:phone":"+49 39483/357",
    "sg:postcode":"06493",
    "sg:province":"Sachsen-Anhalt",
    "wof:name":"Mathias Bormann",
    "wof:placetype":"venue"
},
  "geometry": {"coordinates":[11.233774,51.720791],"type":"Point"}
}