{
  "type": "Feature",
  "properties": {
    "iso:country":"DE",
    "sg:address":"B\u00fchlstr. 13",
    "sg:city":"Durlangen",
    "sg:phone":"+49 7176/6209",
    "sg:postcode":"73568",
    "sg:province":"Baden-W\u00fcrttemberg",
    "wof:name":"P. Und E. Ertle",
    "wof:placetype":"venue"
},
  "geometry": {"coordinates":[9.792589,48.853794],"type":"Point"}
}