{
  "type": "Feature",
  "properties": {
    "iso:country":"DE",
    "sg:address":"Robert-Bosch-Str. 19",
    "sg:city":"Altlu\u00dfheim",
    "sg:phone":"+49 4962/0539520",
    "sg:postcode":"68804",
    "sg:province":"Baden-W\u00fcrttemberg",
    "wof:name":"Werner Burkard Gmbh",
    "wof:placetype":"venue"
},
  "geometry": {"coordinates":[8.509487,49.291298],"type":"Point"}
}