{
  "type": "Feature",
  "properties": {
    "iso:country":"DE",
    "sg:address":"Wagenfeldstr. 35",
    "sg:city":"Drensteinfurt",
    "sg:phone":"+49 2508/202",
    "sg:postcode":"48317",
    "sg:province":"Nordrhein-Westfalen",
    "wof:name":"Heinrich T\u00f6ns",
    "wof:placetype":"venue"
},
  "geometry": {"coordinates":[7.7404298782,51.79737854],"type":"Point"}
}