{
  "type": "Feature",
  "properties": {
    "iso:country":"DE",
    "sg:address":"Vorbach 5",
    "sg:city":"Vorbach",
    "sg:phone":"+49 9205/203",
    "sg:postcode":"95519",
    "sg:province":"Bayern",
    "wof:name":"H. Schmid",
    "wof:placetype":"venue"
},
  "geometry": {"coordinates":[11.7422847748,49.8216400146],"type":"Point"}
}