{
  "type": "Feature",
  "properties": {
    "iso:country":"DE",
    "sg:address":"Rosenweg 2",
    "sg:city":"Melle",
    "sg:phone":"+49 5422/2332",
    "sg:postcode":"49324",
    "sg:province":"Niedersachsen",
    "wof:name":"Armin Peters Ingenieur",
    "wof:placetype":"venue"
},
  "geometry": {"coordinates":[8.3406133652,52.2008628845],"type":"Point"}
}