{
  "type": "Feature",
  "properties": {
    "iso:country":"DE",
    "sg:address":"Bahnhofstr. 23",
    "sg:city":"Bad K\u00f6nig",
    "sg:phone":"+49 6063/57332",
    "sg:postcode":"64732",
    "sg:province":"Hessen",
    "wof:name":"Johanna Gaydoul",
    "wof:placetype":"venue"
},
  "geometry": {"coordinates":[9.003667,49.740707],"type":"Point"}
}