{
  "type": "Feature",
  "properties": {
    "iso:country":"DE",
    "sg:address":"Sofienstr. 3",
    "sg:city":"Langen",
    "sg:phone":"+49 6103/52716",
    "sg:postcode":"63225",
    "sg:province":"Hessen",
    "wof:name":"Zeltverleih Und Partyservice Walther Gmbh",
    "wof:placetype":"venue"
},
  "geometry": {"coordinates":[8.665463,49.991974],"type":"Point"}
}