{
  "type": "Feature",
  "properties": {
    "iso:country":"DE",
    "sg:address":"Hauptstr 40",
    "sg:city":"Brandenburg",
    "sg:phone":"+49 3381/272250",
    "sg:postcode":"14776",
    "sg:province":"Brandenburg",
    "wof:name":"Volksbank & Raiffeisenbank Eg",
    "wof:placetype":"venue"
},
  "geometry": {"coordinates":[12.559679,52.410065],"type":"Point"}
}