{
  "type": "Feature",
  "properties": {
    "iso:country":"DE",
    "sg:address":"Heinrich-Schlusnus-Str. 3",
    "sg:city":"Braubach",
    "sg:phone":"+49 2627/240",
    "sg:postcode":"56338",
    "sg:province":"Rheinland-Pfalz",
    "wof:name":"Hotel Rheintal",
    "wof:placetype":"venue"
},
  "geometry": {"coordinates":[7.6427302361,50.2754898071],"type":"Point"}
}