{
  "type": "Feature",
  "properties": {
    "iso:country":"DE",
    "sg:address":"Wesel 3a",
    "sg:city":"Lingen",
    "sg:postcode":"49811",
    "sg:province":"Niedersachsen",
    "wof:name":"Luca Verlag",
    "wof:placetype":"venue"
},
  "geometry": {"coordinates":[7.3751997948,52.5268135071],"type":"Point"}
}