{
  "type": "Feature",
  "properties": {
    "iso:country":"DE",
    "sg:address":"Karl-Benz-Str. 31-33",
    "sg:city":"Frankfurt",
    "sg:phone":"+49 69/425090",
    "sg:postcode":"60386",
    "sg:province":"Hessen",
    "wof:name":"Habermann Kommunikation Gmbh",
    "wof:placetype":"venue"
},
  "geometry": {"coordinates":[8.7566986084,50.1192436218],"type":"Point"}
}