{
  "type": "Feature",
  "properties": {
    "iso:country":"DE",
    "sg:address":"Hofstallstr. 6-8",
    "sg:city":"W\u00fcrzburg",
    "sg:phone":"+49 931/72701",
    "sg:postcode":"97070",
    "sg:province":"Bayern",
    "wof:name":"Berthold Hummel Komponist",
    "wof:placetype":"venue"
},
  "geometry": {"coordinates":[9.9407682419,49.7949714661],"type":"Point"}
}