{
  "type": "Feature",
  "properties": {
    "iso:country":"DE",
    "sg:address":"D\u00fcrmentinger Str. 13",
    "sg:city":"D\u00fcrmentingen",
    "sg:phone":"+49 7371/6701",
    "sg:postcode":"88525",
    "sg:province":"Baden-W\u00fcrttemberg",
    "wof:name":"Willi Schmid",
    "wof:placetype":"venue"
},
  "geometry": {"coordinates":[9.5131244659,48.1303672791],"type":"Point"}
}