{
  "type": "Feature",
  "properties": {
    "iso:country":"DE",
    "sg:address":"H\u00fcgelweg 7",
    "sg:city":"Altena",
    "sg:phone":"+49 2352/51515",
    "sg:postcode":"58762",
    "sg:province":"Nordrhein-Westfalen",
    "wof:name":"Jochen Haas Kameramann",
    "wof:placetype":"venue"
},
  "geometry": {"coordinates":[7.6749558449,51.2774238586],"type":"Point"}
}