{
  "type": "Feature",
  "properties": {
    "iso:country":"DE",
    "sg:address":"Schottm\u00fcllerstr. 35",
    "sg:city":"Hamburg",
    "sg:phone":"+49 40/474480",
    "sg:postcode":"20251",
    "sg:province":"Hamburg",
    "wof:name":"R\u00fcdiger Tarp Antiquit\u00e4ten",
    "wof:placetype":"venue"
},
  "geometry": {"coordinates":[9.986506,53.592384],"type":"Point"}
}