{
  "type": "Feature",
  "properties": {
    "iso:country":"DE",
    "sg:address":"M\u00fcnchener Str. 100",
    "sg:city":"Essen",
    "sg:phone":"+49 201/749800",
    "sg:postcode":"45145",
    "sg:province":"Nordrhein-Westfalen",
    "wof:name":"Vdh Systemtechnik Gmbh",
    "wof:placetype":"venue"
},
  "geometry": {"coordinates":[6.989575,51.44751],"type":"Point"}
}