{
  "type": "Feature",
  "properties": {
    "iso:country":"DE",
    "sg:address":"R\u00f6merweg 98",
    "sg:city":"Niedereschach",
    "sg:phone":"+49 7725/919973",
    "sg:postcode":"78078",
    "sg:province":"Baden-W\u00fcrttemberg",
    "wof:name":"Bernhard Stern Gmbh",
    "wof:placetype":"venue"
},
  "geometry": {"coordinates":[8.4883575439,48.1570510864],"type":"Point"}
}