{
  "type": "Feature",
  "properties": {
    "iso:country":"DE",
    "sg:address":"Elisabethstr. 1",
    "sg:city":"Mannheim",
    "sg:phone":"+49 621/419920",
    "sg:postcode":"68165",
    "sg:province":"Baden-W\u00fcrttemberg",
    "wof:name":"S.h.i.-stahlhandels Gmbh",
    "wof:placetype":"venue"
},
  "geometry": {"coordinates":[8.478225,49.484055],"type":"Point"}
}