{
  "type": "Feature",
  "properties": {
    "iso:country":"DE",
    "sg:address":"Oberdorfstr. 2",
    "sg:city":"Rimsting",
    "sg:postcode":"83253",
    "sg:province":"Bayern",
    "wof:name":"Ludwigs-apotheke E. K.",
    "wof:placetype":"venue"
},
  "geometry": {"coordinates":[12.336512,47.87973],"type":"Point"}
}