{
  "type": "Feature",
  "properties": {
    "iso:country":"DE",
    "sg:address":"Pariser Str. 83",
    "sg:city":"W\u00f6rrstadt",
    "sg:phone":"+49 6732/960636",
    "sg:postcode":"55286",
    "sg:province":"Rheinland-Pfalz",
    "wof:name":"Tengelmann",
    "wof:placetype":"venue"
},
  "geometry": {"coordinates":[8.1148195267,49.8369865417],"type":"Point"}
}