{
  "type": "Feature",
  "properties": {
    "iso:country":"DE",
    "sg:address":"Schwanenhaus 61",
    "sg:city":"Nettetal",
    "sg:postcode":"41334",
    "sg:province":"Nordrhein-Westfalen",
    "wof:name":"Klings Dekoration Import Export Gmbh",
    "wof:placetype":"venue"
},
  "geometry": {"coordinates":[6.192144,51.34026],"type":"Point"}
}