{
  "type": "Feature",
  "properties": {
    "iso:country":"DE",
    "sg:city":"Pressath",
    "sg:postcode":"92690",
    "sg:province":"Bayern",
    "wof:name":"Gebr. Grabowski Gmbh & Co. Kg",
    "wof:placetype":"venue"
},
  "geometry": {"coordinates":[11.942215,49.762787],"type":"Point"}
}