{
  "type": "Feature",
  "properties": {
    "iso:country":"DE",
    "sg:address":"Heimgarten 5",
    "sg:city":"Drebach",
    "sg:phone":"+49 37341/54735",
    "sg:postcode":"09430",
    "sg:province":"Sachsen",
    "wof:name":"Uwe R\u00fcmmler",
    "wof:placetype":"venue"
},
  "geometry": {"coordinates":[13.015281,50.688316],"type":"Point"}
}