{
  "type": "Feature",
  "properties": {
    "iso:country":"DE",
    "sg:address":"Hindenburgstr. 4",
    "sg:city":"Bad Nenndorf",
    "sg:phone":"+49 5723/3578",
    "sg:postcode":"31542",
    "sg:province":"Niedersachsen",
    "wof:name":"G\u00e4stehaus Haus Charlotte",
    "wof:placetype":"venue"
},
  "geometry": {"coordinates":[9.3733301163,52.3378486633],"type":"Point"}
}