{
  "type": "Feature",
  "properties": {
    "iso:country":"DE",
    "sg:address":"Kanalstr. 5",
    "sg:city":"Eisenach",
    "sg:postcode":"99817",
    "sg:province":"Th\u00fcringen",
    "wof:name":"Robert Bosch",
    "wof:placetype":"venue"
},
  "geometry": {"coordinates":[10.313119,51.003078],"type":"Point"}
}