{
  "type": "Feature",
  "properties": {
    "iso:country":"DE",
    "sg:address":"Schwalenberger Str. 41",
    "sg:city":"Schieder-Schwalenberg",
    "sg:phone":"+49 5282/248",
    "sg:postcode":"32816",
    "sg:province":"Nordrhein-Westfalen",
    "wof:name":"Hotel R\u00f6merschanze Anita Schr\u00f6der E. K.",
    "wof:placetype":"venue"
},
  "geometry": {"coordinates":[9.1563720703,51.909450531],"type":"Point"}
}