{
  "type": "Feature",
  "properties": {
    "iso:country":"DE",
    "sg:address":"Campestr. 27",
    "sg:city":"Braunschweig",
    "sg:phone":"+49 531/72846",
    "sg:postcode":"38102",
    "sg:province":"Niedersachsen",
    "wof:name":"Sigma Gmbh",
    "wof:placetype":"venue"
},
  "geometry": {"coordinates":[10.5292711258,52.2552757263],"type":"Point"}
}