{
  "type": "Feature",
  "properties": {
    "iso:country":"DE",
    "sg:address":"Baldurstr",
    "sg:city":"K\u00f6ln",
    "sg:phone":"+49 221/860000",
    "sg:postcode":"51107",
    "sg:province":"Nordrhein-Westfalen",
    "wof:name":"Wohnsiedlung G\u00f6ttersiedlung K\u00f6ln -rath K\u00f6nigsforst",
    "wof:placetype":"venue"
},
  "geometry": {"coordinates":[7.0983,50.927071],"type":"Point"}
}