{
  "type": "Feature",
  "properties": {
    "iso:country":"DE",
    "sg:address":"Eichendorffstr. 35",
    "sg:city":"Neckarsteinach",
    "sg:phone":"+49 6229/28304",
    "sg:postcode":"69239",
    "sg:province":"Hessen",
    "wof:name":"Tdc Technical Design & Consulting Gmbh",
    "wof:placetype":"venue"
},
  "geometry": {"coordinates":[8.8518190384,49.4017524719],"type":"Point"}
}