{
  "type": "Feature",
  "properties": {
    "iso:country":"DE",
    "sg:address":"M\u00fcnchener Str. 68",
    "sg:city":"Rosenheim",
    "sg:phone":"+49 8031/13986",
    "sg:postcode":"83022",
    "sg:province":"Bayern",
    "wof:name":"Pension Seiffert",
    "wof:placetype":"venue"
},
  "geometry": {"coordinates":[12.1184663773,47.8527259827],"type":"Point"}
}