{
  "type": "Feature",
  "properties": {
    "iso:country":"DE",
    "sg:address":"Illerstr. 60",
    "sg:city":"Braunschweig",
    "sg:phone":"+49 531/842223",
    "sg:postcode":"38120",
    "sg:province":"Niedersachsen",
    "wof:name":"Hans Rinnewitz",
    "wof:placetype":"venue"
},
  "geometry": {"coordinates":[10.4805908203,52.2418441772],"type":"Point"}
}