{
  "type": "Feature",
  "properties": {
    "iso:country":"DE",
    "sg:address":"Im Brunnenfeld 6",
    "sg:city":"Umkirch",
    "sg:phone":"+49 7665/94600",
    "sg:postcode":"79224",
    "sg:province":"Baden-W\u00fcrttemberg",
    "wof:name":"Ladenbau Koch Gmbh",
    "wof:placetype":"venue"
},
  "geometry": {"coordinates":[7.7636427879,48.0411987305],"type":"Point"}
}