{
  "type": "Feature",
  "properties": {
    "iso:country":"DE",
    "sg:address":"Casinostr. 3",
    "sg:city":"Koblenz",
    "sg:phone":"+49 261/15229",
    "sg:postcode":"56068",
    "sg:province":"Rheinland-Pfalz",
    "wof:name":"Im Wurstkessel",
    "wof:placetype":"venue"
},
  "geometry": {"coordinates":[7.5976991653,50.3590965271],"type":"Point"}
}