{
  "type": "Feature",
  "properties": {
    "iso:country":"DE",
    "sg:address":"Am Feldberg 67",
    "sg:city":"H\u00f6xter",
    "sg:phone":"+49 5531/3591",
    "sg:postcode":"37671",
    "sg:province":"Nordrhein-Westfalen",
    "wof:name":"Gebr. Reker Kieswerke Gmbh & Co. Kg",
    "wof:placetype":"venue"
},
  "geometry": {"coordinates":[9.4178962708,51.8365974426],"type":"Point"}
}