{
  "type": "Feature",
  "properties": {
    "iso:country":"DE",
    "sg:address":"Brunnanger 37",
    "sg:city":"Nabburg",
    "sg:phone":"+49 9433/401",
    "sg:postcode":"92507",
    "sg:province":"Bayern",
    "wof:name":"Theo Seitz",
    "wof:placetype":"venue"
},
  "geometry": {"coordinates":[12.176032,49.456261],"type":"Point"}
}