{
  "type": "Feature",
  "properties": {
    "iso:country":"DE",
    "sg:address":"Stra\u00dfburger Str. 2 a",
    "sg:city":"Oldenburg",
    "sg:phone":"+49 441/882099",
    "sg:postcode":"26123",
    "sg:province":"Niedersachsen",
    "wof:name":"Apotheke Am Europaplatz",
    "wof:placetype":"venue"
},
  "geometry": {"coordinates":[8.224671,53.147972],"type":"Point"}
}