{
  "type": "Feature",
  "properties": {
    "iso:country":"DE",
    "sg:address":"Ruppenmanklitz 20",
    "sg:city":"Weiler-Simmerberg",
    "sg:phone":"+49 8381/2403",
    "sg:postcode":"88171",
    "sg:province":"Bayern",
    "wof:name":"Gastst\u00e4tte Erich Fehr",
    "wof:placetype":"venue"
},
  "geometry": {"coordinates":[9.8980541229,47.5976715088],"type":"Point"}
}