{
  "type": "Feature",
  "properties": {
    "iso:country":"DE",
    "sg:address":"Amselweg 10",
    "sg:city":"Viersen",
    "sg:phone":"+49 2162/80855",
    "sg:postcode":"41749",
    "sg:province":"Nordrhein-Westfalen",
    "wof:name":"Ernst Kamp",
    "wof:placetype":"venue"
},
  "geometry": {"coordinates":[6.37173,51.284756],"type":"Point"}
}