{
  "type": "Feature",
  "properties": {
    "iso:country":"DE",
    "sg:address":"Grabenstr. 117",
    "sg:city":"Essen",
    "sg:phone":"+49 201/296622",
    "sg:postcode":"45141",
    "sg:province":"Nordrhein-Westfalen",
    "wof:name":"Michael Hinzke",
    "wof:placetype":"venue"
},
  "geometry": {"coordinates":[7.0263738632,51.4719047546],"type":"Point"}
}