{
  "type": "Feature",
  "properties": {
    "iso:country":"DE",
    "sg:address":"Talstr. 1",
    "sg:city":"Seelitz",
    "sg:phone":"+49 3737/42441",
    "sg:postcode":"09306",
    "sg:province":"Sachsen",
    "wof:name":"Agro Trocknung D\u00f6hlen Gmbh",
    "wof:placetype":"venue"
},
  "geometry": {"coordinates":[12.833872,51.050354],"type":"Point"}
}