{
  "type": "Feature",
  "properties": {
    "iso:country":"DE",
    "sg:address":"Kallstadter Str. 9",
    "sg:city":"Ludwigshafen",
    "sg:phone":"+49 621/5042747",
    "sg:postcode":"67067",
    "sg:province":"Rheinland-Pfalz",
    "wof:name":"St\u00e4dt. Seniorenwohnheim",
    "wof:placetype":"venue"
},
  "geometry": {"coordinates":[8.401007,49.466942],"type":"Point"}
}