{
  "type": "Feature",
  "properties": {
    "iso:country":"DE",
    "sg:address":"Lindenhardt 4",
    "sg:city":"Olpe",
    "sg:phone":"+49 2761/62001",
    "sg:postcode":"57462",
    "sg:province":"Nordrhein-Westfalen",
    "wof:name":"Ulrich Hengstebeck",
    "wof:placetype":"venue"
},
  "geometry": {"coordinates":[7.8577108383,51.0340805054],"type":"Point"}
}