{
  "type": "Feature",
  "properties": {
    "iso:country":"DE",
    "sg:address":"Bogenstr. 1",
    "sg:city":"Schwabach",
    "sg:phone":"+49 9122/3966",
    "sg:postcode":"91126",
    "sg:province":"Bayern",
    "wof:name":"E. Handschu Elektroinstallation",
    "wof:placetype":"venue"
},
  "geometry": {"coordinates":[11.016936,49.326988],"type":"Point"}
}