{
  "type": "Feature",
  "properties": {
    "iso:country":"DE",
    "sg:address":"Wilhelmstr. 26",
    "sg:city":"Plettenberg",
    "sg:phone":"+49 2391/2210",
    "sg:postcode":"58840",
    "sg:province":"Nordrhein-Westfalen",
    "wof:name":"H.-j. Arnold U. U. Nahrgang",
    "wof:placetype":"venue"
},
  "geometry": {"coordinates":[7.873218,51.214931],"type":"Point"}
}