{
  "type": "Feature",
  "properties": {
    "iso:country":"DE",
    "sg:address":"Bahnstr. 71",
    "sg:city":"Willich",
    "sg:phone":"+49 2154/2453",
    "sg:postcode":"47877",
    "sg:province":"Nordrhein-Westfalen",
    "wof:name":"C. Strehlau",
    "wof:placetype":"venue"
},
  "geometry": {"coordinates":[6.543037,51.266327],"type":"Point"}
}