{
  "type": "Feature",
  "properties": {
    "iso:country":"DE",
    "sg:address":"Hauptstr. 15",
    "sg:city":"Br\u00fcggen",
    "sg:phone":"+49 5182/1305",
    "sg:postcode":"31033",
    "sg:province":"Niedersachsen",
    "wof:name":"Zur Post",
    "wof:placetype":"venue"
},
  "geometry": {"coordinates":[9.7774181366,52.0417327881],"type":"Point"}
}