{
  "type": "Feature",
  "properties": {
    "iso:country":"DE",
    "sg:address":"Bertha-von-Suttner-Str. 4",
    "sg:city":"Offenburg",
    "sg:phone":"+49 781/92970",
    "sg:postcode":"77654",
    "sg:province":"Baden-W\u00fcrttemberg",
    "wof:name":"Ads Allgemeine Deutsche Steuerberatungsges. Mbh",
    "wof:placetype":"venue"
},
  "geometry": {"coordinates":[7.956840992,48.4801483154],"type":"Point"}
}