{
  "type": "Feature",
  "properties": {
    "iso:country":"DE",
    "sg:address":"S\u00fcdliche Ringstr. 98",
    "sg:city":"Langen",
    "sg:phone":"+49 6103/25635",
    "sg:postcode":"63225",
    "sg:province":"Hessen",
    "wof:name":"H. S. G\u00fcnther",
    "wof:placetype":"venue"
},
  "geometry": {"coordinates":[8.670047,49.985497],"type":"Point"}
}