{
  "type": "Feature",
  "properties": {
    "iso:country":"DE",
    "sg:address":"Salinger Feld 36",
    "sg:city":"Witten",
    "sg:phone":"+49 2302/801918",
    "sg:postcode":"58454",
    "sg:province":"Nordrhein-Westfalen",
    "wof:name":"Zellmann & Heimer Ohg",
    "wof:placetype":"venue"
},
  "geometry": {"coordinates":[7.382185,51.455166],"type":"Point"}
}