{
  "type": "Feature",
  "properties": {
    "iso:country":"DE",
    "sg:address":"N\u00e4gelistr. 13",
    "sg:city":"K\u00f6ln",
    "sg:phone":"+49 221/765220",
    "sg:postcode":"50733",
    "sg:province":"Nordrhein-Westfalen",
    "wof:name":"Helmut Paland",
    "wof:placetype":"venue"
},
  "geometry": {"coordinates":[6.9668741226,50.9610061646],"type":"Point"}
}