{
  "type": "Feature",
  "properties": {
    "iso:country":"DE",
    "sg:address":"H\u00fcttenstr. 20",
    "sg:city":"Blankenheim",
    "sg:phone":"+49 2697/7434",
    "sg:postcode":"53945",
    "sg:province":"Nordrhein-Westfalen",
    "wof:name":"P. Op Den Kelder",
    "wof:placetype":"venue"
},
  "geometry": {"coordinates":[6.7356,50.388245],"type":"Point"}
}