{
  "type": "Feature",
  "properties": {
    "iso:country":"DE",
    "sg:address":"Bahnhofstr. 1",
    "sg:city":"Gem\u00fcnden",
    "sg:phone":"+49 6765/960073",
    "sg:postcode":"55490",
    "sg:province":"Rheinland-Pfalz",
    "wof:name":"Wolfgang Neum\u00fcller Masseur",
    "wof:placetype":"venue"
},
  "geometry": {"coordinates":[7.4829,49.896858],"type":"Point"}
}