{
  "type": "Feature",
  "properties": {
    "iso:country":"DE",
    "sg:address":"Germersheimer Str. 11 1/3",
    "sg:city":"Augsburg",
    "sg:phone":"+49 821/523100",
    "sg:postcode":"86157",
    "sg:province":"Bayern",
    "wof:name":"Augusta Import Gmbh",
    "wof:placetype":"venue"
},
  "geometry": {"coordinates":[10.8744564056,48.3691444397],"type":"Point"}
}