{
  "type": "Feature",
  "properties": {
    "iso:country":"DE",
    "sg:address":"Schwalbengasse 56",
    "sg:city":"Wald-Michelbach",
    "sg:phone":"+49 6207/3491",
    "sg:postcode":"69483",
    "sg:province":"Hessen",
    "wof:name":"B. Kara",
    "wof:placetype":"venue"
},
  "geometry": {"coordinates":[8.8247966766,49.570766449],"type":"Point"}
}