{
  "type": "Feature",
  "properties": {
    "iso:country":"DE",
    "sg:address":"Rilkeweg 4 a",
    "sg:city":"Velbert",
    "sg:phone":"+49 2053/83472",
    "sg:postcode":"42553",
    "sg:province":"Nordrhein-Westfalen",
    "wof:name":"Gast & K\u00f6hler Alpha Service Inh. Renate Gast",
    "wof:placetype":"venue"
},
  "geometry": {"coordinates":[7.058574,51.308796],"type":"Point"}
}