{
  "type": "Feature",
  "properties": {
    "iso:country":"DE",
    "sg:city":"J\u00f6rdenstorf",
    "sg:postcode":"17168",
    "sg:province":"Mecklenburg-Vorpommern",
    "wof:name":"Bibliothek",
    "wof:placetype":"venue"
},
  "geometry": {"coordinates":[12.614354,53.878071],"type":"Point"}
}