{
  "type": "Feature",
  "properties": {
    "iso:country":"DE",
    "sg:address":"Ro\u00dfmarkt 4",
    "sg:city":"Memmingen",
    "sg:phone":"+49 8331/497893",
    "sg:postcode":"87700",
    "sg:province":"Bayern",
    "wof:name":"Alois Sch\u00fctz",
    "wof:placetype":"venue"
},
  "geometry": {"coordinates":[10.18023,47.984554],"type":"Point"}
}