{
  "type": "Feature",
  "properties": {
    "iso:country":"DE",
    "sg:address":"Wabestr. 12",
    "sg:city":"Braunschweig",
    "sg:phone":"+49 531/343973",
    "sg:postcode":"38106",
    "sg:province":"Niedersachsen",
    "wof:name":"Fred Mohr",
    "wof:placetype":"venue"
},
  "geometry": {"coordinates":[10.5426130295,52.2728996277],"type":"Point"}
}