{
  "type": "Feature",
  "properties": {
    "iso:country":"DE",
    "sg:address":"Knappheide 1",
    "sg:city":"Bahrenborstel",
    "sg:phone":"+49 4273/8113",
    "sg:postcode":"27245",
    "sg:province":"Niedersachsen",
    "wof:name":"Heinrich Plenge",
    "wof:placetype":"venue"
},
  "geometry": {"coordinates":[8.800176,52.561306],"type":"Point"}
}