{
  "type": "Feature",
  "properties": {
    "iso:country":"DE",
    "sg:address":"Waldstr. 5",
    "sg:city":"Lauchr\u00f6den",
    "sg:postcode":"99819",
    "sg:province":"Th\u00fcringen",
    "wof:name":"D. K\u00f6nig",
    "wof:placetype":"venue"
},
  "geometry": {"coordinates":[10.153193,50.99155],"type":"Point"}
}