{
  "type": "Feature",
  "properties": {
    "iso:country":"DE",
    "sg:address":"Am Bahnhof 20",
    "sg:city":"Sinsheim",
    "sg:phone":"+49 7261/64537",
    "sg:postcode":"74889",
    "sg:province":"Baden-W\u00fcrttemberg",
    "wof:name":"M\u00fchltal-restaurant",
    "wof:placetype":"venue"
},
  "geometry": {"coordinates":[8.9222326279,49.2148323059],"type":"Point"}
}