{
  "type": "Feature",
  "properties": {
    "iso:country":"DE",
    "sg:address":"Industriestr. 15",
    "sg:city":"Landau",
    "sg:postcode":"76829",
    "sg:province":"Rheinland-Pfalz",
    "wof:name":"Ess Embedded Systems Solutions Gmbh",
    "wof:placetype":"venue"
},
  "geometry": {"coordinates":[8.1209411621,49.1997032166],"type":"Point"}
}