{
  "type": "Feature",
  "properties": {
    "iso:country":"DE",
    "sg:address":"Ramertsweg 52",
    "sg:city":"M\u00fcnster",
    "sg:phone":"+49 251/864345",
    "sg:postcode":"48161",
    "sg:province":"Nordrhein-Westfalen",
    "wof:name":"Johannes M\u00fchlenbeck",
    "wof:placetype":"venue"
},
  "geometry": {"coordinates":[7.56659,51.956638],"type":"Point"}
}