{
  "type": "Feature",
  "properties": {
    "iso:country":"DE",
    "sg:address":"Emil-Rittershaus-Str. 1",
    "sg:city":"Remscheid",
    "sg:phone":"+49 2191/780830",
    "sg:postcode":"42853",
    "sg:province":"Nordrhein-Westfalen",
    "wof:name":"Tiffany",
    "wof:placetype":"venue"
},
  "geometry": {"coordinates":[7.175590992,51.1822471619],"type":"Point"}
}