{
  "type": "Feature",
  "properties": {
    "iso:country":"DE",
    "sg:address":"Bommersheimer Str. 87",
    "sg:city":"Oberursel",
    "sg:phone":"+49 6171/631470",
    "sg:postcode":"61440",
    "sg:province":"Hessen",
    "wof:name":"Reimund Krammich",
    "wof:placetype":"venue"
},
  "geometry": {"coordinates":[8.599002,50.198017],"type":"Point"}
}