{
  "type": "Feature",
  "properties": {
    "iso:country":"DE",
    "sg:address":"Lemsahler Bargweg 10",
    "sg:city":"Hamburg",
    "sg:phone":"+49 40/6083332",
    "sg:postcode":"22397",
    "sg:province":"Hamburg",
    "wof:name":"Thomas Plum Restaurator",
    "wof:placetype":"venue"
},
  "geometry": {"coordinates":[10.1063432693,53.679019928],"type":"Point"}
}