{
  "type": "Feature",
  "properties": {
    "iso:country":"DE",
    "sg:address":"Urbanstr. 67",
    "sg:city":"Esslingen",
    "sg:phone":"+49 711/35122433",
    "sg:postcode":"73728",
    "sg:province":"Baden-W\u00fcrttemberg",
    "wof:name":"Bestattungsinstitut Der Stadt Esslingen",
    "wof:placetype":"venue"
},
  "geometry": {"coordinates":[9.320351,48.739441],"type":"Point"}
}