{
  "type": "Feature",
  "properties": {
    "iso:country":"DE",
    "sg:address":"Auf der Bornau",
    "sg:city":"Brey",
    "sg:phone":"+49 2628/1228",
    "sg:postcode":"56321",
    "sg:province":"Rheinland-Pfalz",
    "wof:name":"Event-trucking",
    "wof:placetype":"venue"
},
  "geometry": {"coordinates":[7.627486,50.275013],"type":"Point"}
}