{
  "type": "Feature",
  "properties": {
    "iso:country":"DE",
    "sg:address":"Vollweidstr. 9",
    "sg:city":"Saarbr\u00fccken",
    "sg:postcode":"66115",
    "sg:province":"Saarland",
    "wof:name":"Ingenium Engineering Ag",
    "wof:placetype":"venue"
},
  "geometry": {"coordinates":[6.9536547661,49.2417182922],"type":"Point"}
}