{
  "type": "Feature",
  "properties": {
    "iso:country":"DE",
    "sg:address":"Gewerbestr. 8 A",
    "sg:city":"Dieburg",
    "sg:phone":"+49 6071/985710",
    "sg:postcode":"64807",
    "sg:province":"Hessen",
    "wof:name":"Mr. Schutztechnik Kabinenbau Gmbh",
    "wof:placetype":"venue"
},
  "geometry": {"coordinates":[8.85336,49.908268],"type":"Point"}
}