{
  "type": "Feature",
  "properties": {
    "iso:country":"DE",
    "sg:address":"K\u00f6llns Acker 2",
    "sg:city":"Hamburg",
    "sg:phone":"+49 40/8805869",
    "sg:postcode":"22523",
    "sg:province":"Hamburg",
    "wof:name":"Manfred Thordsen",
    "wof:placetype":"venue"
},
  "geometry": {"coordinates":[9.893741,53.620594],"type":"Point"}
}