{
  "type": "Feature",
  "properties": {
    "iso:country":"DE",
    "sg:address":"Seevering 73",
    "sg:city":"Neu Wulmstorf",
    "sg:phone":"+49 40/7000544",
    "sg:postcode":"21629",
    "sg:province":"Niedersachsen",
    "wof:name":"W. Lacker",
    "wof:placetype":"venue"
},
  "geometry": {"coordinates":[9.794464,53.46999],"type":"Point"}
}