{
  "type": "Feature",
  "properties": {
    "iso:country":"DE",
    "sg:address":"Kuchengrund 18",
    "sg:city":"Backnang",
    "sg:phone":"+49 7191/95720",
    "sg:postcode":"71522",
    "sg:province":"Baden-W\u00fcrttemberg",
    "wof:name":"Elpo Gmbh Luft- Und Trocknungstechnik",
    "wof:placetype":"venue"
},
  "geometry": {"coordinates":[9.443525,48.928726],"type":"Point"}
}