{
  "type": "Feature",
  "properties": {
    "iso:country":"DE",
    "sg:address":"Chemnitzer Str. 47",
    "sg:city":"R\u00f6hrsdorf",
    "sg:phone":"+49 3722/502734",
    "sg:postcode":"09247",
    "sg:province":"Sachsen",
    "wof:name":"Herbert K\u00fcnzel",
    "wof:placetype":"venue"
},
  "geometry": {"coordinates":[12.840514,50.861012],"type":"Point"}
}