{
  "type": "Feature",
  "properties": {
    "iso:country":"DE",
    "sg:address":"Umgehungsstr. 29",
    "sg:city":"Marburg",
    "sg:phone":"+49 6421/41228",
    "sg:postcode":"35043",
    "sg:province":"Hessen",
    "wof:name":"W. Kaletsch",
    "wof:placetype":"venue"
},
  "geometry": {"coordinates":[8.7640247345,50.7738037109],"type":"Point"}
}