{
  "type": "Feature",
  "properties": {
    "iso:country":"DE",
    "sg:address":"Hauptstr. 32",
    "sg:city":"Zwickau",
    "sg:phone":"+49 375/281132",
    "sg:postcode":"08056",
    "sg:province":"Sachsen",
    "wof:name":"Blume 2000 Blumenhandels Gmbh & Co. Kg",
    "wof:placetype":"venue"
},
  "geometry": {"coordinates":[12.496586,50.719589],"type":"Point"}
}