{
  "type": "Feature",
  "properties": {
    "iso:country":"DE",
    "sg:address":"Heerstra\u00dfe 70",
    "sg:city":"Frankfurt/Main",
    "sg:phone":"+49 69/9766060",
    "sg:postcode":"60488",
    "sg:province":"Hessen",
    "wof:name":"Servomat Miosga Gmbh",
    "wof:placetype":"venue"
},
  "geometry": {"coordinates":[8.614341,50.147785],"type":"Point"}
}