{
  "type": "Feature",
  "properties": {
    "iso:country":"DE",
    "sg:city":"Biburg",
    "sg:phone":"+49 9443/5306",
    "sg:postcode":"93354",
    "sg:province":"Bayern",
    "wof:name":"Anton Winkler",
    "wof:placetype":"venue"
},
  "geometry": {"coordinates":[11.855531,48.790581],"type":"Point"}
}