{
  "type": "Feature",
  "properties": {
    "iso:country":"DE",
    "sg:address":"Bahnhofstr. 17",
    "sg:city":"Lechbruck",
    "sg:postcode":"86983",
    "sg:province":"Bayern",
    "wof:name":"Zink Anlagen- Und Energie- Technik Gmbh",
    "wof:placetype":"venue"
},
  "geometry": {"coordinates":[10.793718,47.69788],"type":"Point"}
}