{
  "type": "Feature",
  "properties": {
    "iso:country":"DE",
    "sg:address":"Zunftstr. 12",
    "sg:city":"Kehl",
    "sg:phone":"+49 7854/1783",
    "sg:postcode":"77694",
    "sg:province":"Baden-W\u00fcrttemberg",
    "wof:name":"R. Krieg",
    "wof:placetype":"venue"
},
  "geometry": {"coordinates":[7.831763,48.519081],"type":"Point"}
}