{
  "type": "Feature",
  "properties": {
    "iso:country":"DE",
    "sg:address":"Lange Reihe 54",
    "sg:city":"Hamburg",
    "sg:phone":"+49 40/245860",
    "sg:postcode":"20099",
    "sg:province":"Hamburg",
    "wof:name":"Hotel Benecke",
    "wof:placetype":"venue"
},
  "geometry": {"coordinates":[10.0107898712,53.5569076538],"type":"Point"}
}