{
  "type": "Feature",
  "properties": {
    "iso:country":"DE",
    "sg:address":"Pl\u00f6ck 56a",
    "sg:city":"Heidelberg",
    "sg:phone":"+49 6221/183449",
    "sg:postcode":"69117",
    "sg:province":"Baden-W\u00fcrttemberg",
    "wof:name":"Christian Dehner",
    "wof:placetype":"venue"
},
  "geometry": {"coordinates":[8.703785,49.409355],"type":"Point"}
}