{
  "type": "Feature",
  "properties": {
    "iso:country":"DE",
    "sg:address":"Yorckstr. 48 a",
    "sg:city":"Delmenhorst",
    "sg:phone":"+49 4221/24747",
    "sg:postcode":"27755",
    "sg:province":"Niedersachsen",
    "wof:name":"Artur Schr\u00f6der Zimmereibetrieb Gmbh",
    "wof:placetype":"venue"
},
  "geometry": {"coordinates":[8.6213378906,53.0219917297],"type":"Point"}
}