{
  "type": "Feature",
  "properties": {
    "iso:country":"DE",
    "sg:address":"Kaulbachstr. 28",
    "sg:city":"M\u00fcnchen",
    "sg:postcode":"80539",
    "sg:province":"Bayern",
    "wof:name":"Bunte-suche.de -- Die Farbenfrohe Suchmaschine",
    "wof:placetype":"venue"
},
  "geometry": {"coordinates":[11.58391,48.149189],"type":"Point"}
}