{
  "type": "Feature",
  "properties": {
    "iso:country":"DE",
    "sg:address":"Oberhof 16",
    "sg:city":"Wei\u00dfensberg",
    "sg:phone":"+49 8382/975720",
    "sg:postcode":"88138",
    "sg:province":"Bayern",
    "wof:name":"Bernd Kleeis",
    "wof:placetype":"venue"
},
  "geometry": {"coordinates":[9.725678,47.573643],"type":"Point"}
}