{
  "type": "Feature",
  "properties": {
    "iso:country":"DE",
    "sg:address":"Osterholder Allee 8-10",
    "sg:city":"Pinneberg",
    "sg:postcode":"25421",
    "sg:province":"Schleswig-Holstein",
    "wof:name":"Dorrit Sporsen",
    "wof:placetype":"venue"
},
  "geometry": {"coordinates":[9.7986183167,53.6519126892],"type":"Point"}
}