{
  "type": "Feature",
  "properties": {
    "iso:country":"DE",
    "sg:address":"Am Fuchsloch 2",
    "sg:city":"Linz",
    "sg:phone":"+49 2644/6600",
    "sg:postcode":"53545",
    "sg:province":"Rheinland-Pfalz",
    "wof:name":"Arnulf Speckmann Ingenieur",
    "wof:placetype":"venue"
},
  "geometry": {"coordinates":[7.2848148346,50.5728569031],"type":"Point"}
}