{
  "type": "Feature",
  "properties": {
    "iso:country":"DE",
    "sg:address":"Friedrichstr. 1",
    "sg:city":"Geeste",
    "sg:phone":"+49 5907/282",
    "sg:postcode":"49744",
    "sg:province":"Niedersachsen",
    "wof:name":"Franz Konermann",
    "wof:placetype":"venue"
},
  "geometry": {"coordinates":[7.2759389877,52.6015548706],"type":"Point"}
}