{
  "type": "Feature",
  "properties": {
    "iso:country":"DE",
    "sg:address":"Tulpenstr. 3",
    "sg:city":"L\u00fctzelbach",
    "sg:phone":"+49 6165/912094",
    "sg:postcode":"64750",
    "sg:province":"Hessen",
    "wof:name":"Fritz Hiller",
    "wof:placetype":"venue"
},
  "geometry": {"coordinates":[9.0816354752,49.7842636108],"type":"Point"}
}