{
  "type": "Feature",
  "properties": {
    "iso:country":"DE",
    "sg:address":"Pampower Str. 3",
    "sg:city":"Stralendorf",
    "sg:phone":"+49 3869/7412",
    "sg:postcode":"19073",
    "sg:province":"Mecklenburg-Vorpommern",
    "wof:name":"Mario Petzold",
    "wof:placetype":"venue"
},
  "geometry": {"coordinates":[11.3106327057,53.5746841431],"type":"Point"}
}