{
  "type": "Feature",
  "properties": {
    "iso:country":"DE",
    "sg:address":"L\u00e4ndenstr. 4",
    "sg:city":"Riedenburg",
    "sg:phone":"+49 9442/455",
    "sg:postcode":"93339",
    "sg:province":"Bayern",
    "wof:name":"M. Perras Jun.",
    "wof:placetype":"venue"
},
  "geometry": {"coordinates":[11.691852,48.982487],"type":"Point"}
}