{
  "type": "Feature",
  "properties": {
    "iso:country":"DE",
    "sg:address":"Am Landgericht 12",
    "sg:city":"Hallstadt",
    "sg:phone":"+49 951/9710801",
    "sg:postcode":"96103",
    "sg:province":"Bayern",
    "wof:name":"Pcs Transportlogistik",
    "wof:placetype":"venue"
},
  "geometry": {"coordinates":[10.8815345764,49.9239997864],"type":"Point"}
}