{
  "type": "Feature",
  "properties": {
    "iso:country":"DE",
    "sg:address":"Colonnaden 104",
    "sg:city":"Hamburg",
    "sg:phone":"+49 40/3589918",
    "sg:postcode":"20354",
    "sg:province":"Hamburg",
    "wof:name":"Niels Kreye Rechtsanwalt",
    "wof:placetype":"venue"
},
  "geometry": {"coordinates":[9.9901590347,53.5577507019],"type":"Point"}
}