{
  "type": "Feature",
  "properties": {
    "iso:country":"DE",
    "sg:address":"Marienstr. 38",
    "sg:city":"Karlsruhe",
    "sg:postcode":"76137",
    "sg:province":"Baden-W\u00fcrttemberg",
    "wof:name":"Wolf Verwaltungs- Gmbh",
    "wof:placetype":"venue"
},
  "geometry": {"coordinates":[8.4078788757,49.0019073486],"type":"Point"}
}