{
  "type": "Feature",
  "properties": {
    "iso:country":"DE",
    "sg:address":"K\u00f6lnstr. 438",
    "sg:city":"Bonn",
    "sg:phone":"+49 228/679169",
    "sg:postcode":"53117",
    "sg:province":"Nordrhein-Westfalen",
    "wof:name":"Pizzeria Mastangelo",
    "wof:placetype":"venue"
},
  "geometry": {"coordinates":[7.0757231712,50.7517814636],"type":"Point"}
}