{
  "type": "Feature",
  "properties": {
    "iso:country":"DE",
    "sg:address":"M\u00fchlenstr. 12",
    "sg:city":"Wendeburg",
    "sg:postcode":"38176",
    "sg:province":"Niedersachsen",
    "wof:name":"Katholische Kirchengemeinde",
    "wof:placetype":"venue"
},
  "geometry": {"coordinates":[10.3809814453,52.327167511],"type":"Point"}
}