{
  "type": "Feature",
  "properties": {
    "iso:country":"DE",
    "sg:address":"Remsaer Str. 20 b",
    "sg:city":"Altenburg",
    "sg:phone":"+49 3447/834308",
    "sg:postcode":"04600",
    "sg:province":"Th\u00fcringen",
    "wof:name":"Bau- Und Malerfach- Gro\u00dfhandel Gmbh",
    "wof:placetype":"venue"
},
  "geometry": {"coordinates":[12.4639062881,51.0023956299],"type":"Point"}
}