{
  "type": "Feature",
  "properties": {
    "iso:country":"DE",
    "sg:address":"Verdener Landstr. 162",
    "sg:city":"Nienburg",
    "sg:phone":"+49 5021/912450",
    "sg:postcode":"31582",
    "sg:province":"Niedersachsen",
    "wof:name":"Signal Iduna Versicherung Wolfgang Kr\u00fcger",
    "wof:placetype":"venue"
},
  "geometry": {"coordinates":[9.223236084,52.6657142639],"type":"Point"}
}