{
  "type": "Feature",
  "properties": {
    "iso:country":"DE",
    "sg:address":"Brinkstr. 6",
    "sg:city":"Loxstedt",
    "sg:phone":"+49 4744/5427",
    "sg:postcode":"27612",
    "sg:province":"Niedersachsen",
    "wof:name":"A. B\u00f6hme",
    "wof:placetype":"venue"
},
  "geometry": {"coordinates":[8.5990610123,53.4496803284],"type":"Point"}
}