{
  "type": "Feature",
  "properties": {
    "iso:country":"DE",
    "sg:address":"Brunhildstr. 5",
    "sg:city":"Helmbrechts",
    "sg:phone":"+49 9252/6244",
    "sg:postcode":"95233",
    "sg:province":"Bayern",
    "wof:name":"Gluth Textilwaren",
    "wof:placetype":"venue"
},
  "geometry": {"coordinates":[11.7286043167,50.2348098755],"type":"Point"}
}