{
  "type": "Feature",
  "properties": {
    "iso:country":"DE",
    "sg:address":"Am Alten Brunnen 1",
    "sg:city":"Marloffstein",
    "sg:phone":"+49 9131/53650",
    "sg:postcode":"91080",
    "sg:province":"Bayern",
    "wof:name":"Hotel Alter Brunnen",
    "wof:placetype":"venue"
},
  "geometry": {"coordinates":[11.0629148483,49.6170387268],"type":"Point"}
}