{
  "type": "Feature",
  "properties": {
    "iso:country":"DE",
    "sg:address":"Jellinghausen 124",
    "sg:city":"Ennepetal",
    "sg:phone":"+49 2333/3648",
    "sg:postcode":"58256",
    "sg:province":"Nordrhein-Westfalen",
    "wof:name":"Gatst\u00e4tte H. Natrop",
    "wof:placetype":"venue"
},
  "geometry": {"coordinates":[7.3764839172,51.3146247864],"type":"Point"}
}