{
  "type": "Feature",
  "properties": {
    "iso:country":"DE",
    "sg:address":"Lyoner Str. 24",
    "sg:city":"Frankfurt",
    "sg:phone":"+49 69/153060",
    "sg:postcode":"60528",
    "sg:province":"Hessen",
    "wof:name":"At & T Communications Services Deutschland Gmbh",
    "wof:placetype":"venue"
},
  "geometry": {"coordinates":[8.623642,50.081272],"type":"Point"}
}