{
  "type": "Feature",
  "properties": {
    "iso:country":"DE",
    "sg:address":"Waldstr. 1",
    "sg:city":"Dahnsdorf",
    "sg:phone":"+49 33843/6280",
    "sg:postcode":"14806",
    "sg:province":"Brandenburg",
    "wof:name":"Bloemer Und Nolting Steuerberater",
    "wof:placetype":"venue"
},
  "geometry": {"coordinates":[12.5896177292,52.1435317993],"type":"Point"}
}