{
  "type": "Feature",
  "properties": {
    "iso:country":"DE",
    "sg:address":"H\u00f6lzleinsm\u00fchle 6",
    "sg:city":"Bayreuth",
    "sg:phone":"+49 921/726430",
    "sg:postcode":"95448",
    "sg:province":"Bayern",
    "wof:name":"Muvi Service & Promotion Gmbh",
    "wof:placetype":"venue"
},
  "geometry": {"coordinates":[11.606696,49.953709],"type":"Point"}
}