{
  "type": "Feature",
  "properties": {
    "iso:country":"DE",
    "sg:address":"Am Kanonengraben 3a",
    "sg:city":"M\u00fcnster",
    "sg:phone":"+49 251/526844",
    "sg:postcode":"48151",
    "sg:province":"Nordrhein-Westfalen",
    "wof:name":"Fitness Body Fitness",
    "wof:placetype":"venue"
},
  "geometry": {"coordinates":[7.6202979088,51.9558296204],"type":"Point"}
}