{
  "type": "Feature",
  "properties": {
    "iso:country":"DE",
    "sg:address":"Bahnhofstr. 1",
    "sg:city":"W\u00fcnsdorf",
    "sg:phone":"+49 33702/66511",
    "sg:postcode":"15838",
    "sg:province":"Brandenburg",
    "wof:name":"Horst Sablowski",
    "wof:placetype":"venue"
},
  "geometry": {"coordinates":[13.40193,52.168114],"type":"Point"}
}