{
  "type": "Feature",
  "properties": {
    "iso:country":"DE",
    "sg:address":"Iggensbacher Str. 45",
    "sg:city":"Sch\u00f6llnach",
    "sg:phone":"+49 9903/495",
    "sg:postcode":"94508",
    "sg:province":"Bayern",
    "wof:name":"Ludwig Vierthaler",
    "wof:placetype":"venue"
},
  "geometry": {"coordinates":[13.171165,48.751545],"type":"Point"}
}