{
  "type": "Feature",
  "properties": {
    "iso:country":"DE",
    "sg:address":"Riedweg 9",
    "sg:city":"Bad Homburg",
    "sg:phone":"+49 6172/451451",
    "sg:postcode":"61352",
    "sg:province":"Hessen",
    "wof:name":"Winfried Obst",
    "wof:placetype":"venue"
},
  "geometry": {"coordinates":[8.6751098633,50.2254905701],"type":"Point"}
}