{
  "type": "Feature",
  "properties": {
    "iso:country":"DE",
    "sg:address":"Zwickauer Str. 31",
    "sg:city":"Crimmitschau",
    "sg:phone":"+49 3762/2044",
    "sg:postcode":"08451",
    "sg:province":"Sachsen",
    "wof:name":"Dura Stahl- Und Montagebau Gmbh",
    "wof:placetype":"venue"
},
  "geometry": {"coordinates":[12.3917589188,50.8100700378],"type":"Point"}
}