{
  "type": "Feature",
  "properties": {
    "iso:country":"DE",
    "sg:address":"Stephanplatz 6",
    "sg:city":"Krefeld",
    "sg:phone":"+49 2151/606004",
    "sg:postcode":"47799",
    "sg:province":"Nordrhein-Westfalen",
    "wof:name":"Pflegedienst Accuro Peter Hambloch",
    "wof:placetype":"venue"
},
  "geometry": {"coordinates":[6.570283,51.329811],"type":"Point"}
}