{
  "type": "Feature",
  "properties": {
    "iso:country":"DE",
    "sg:address":"Horstmannsweg 1",
    "sg:city":"Moers",
    "sg:phone":"+49 2841/73053",
    "sg:postcode":"47445",
    "sg:province":"Nordrhein-Westfalen",
    "wof:name":"Axel Neuwirth",
    "wof:placetype":"venue"
},
  "geometry": {"coordinates":[6.6008358002,51.4743843079],"type":"Point"}
}