{
  "type": "Feature",
  "properties": {
    "iso:country":"DE",
    "sg:address":"Stahlbrunnstr. 16",
    "sg:city":"Bissingen",
    "sg:phone":"+49 7023/2879",
    "sg:postcode":"73266",
    "sg:province":"Baden-W\u00fcrttemberg",
    "wof:name":"Karl Weissinger Gmbh",
    "wof:placetype":"venue"
},
  "geometry": {"coordinates":[9.4915180206,48.6076812744],"type":"Point"}
}