{
  "type": "Feature",
  "properties": {
    "iso:country":"DE",
    "sg:address":"Kleyer Weg 34",
    "sg:city":"Dortmund",
    "sg:phone":"+49 231/650707",
    "sg:postcode":"44149",
    "sg:province":"Nordrhein-Westfalen",
    "wof:name":"Rolf K. F. Heinrichs Architekt",
    "wof:placetype":"venue"
},
  "geometry": {"coordinates":[7.3645,51.492352],"type":"Point"}
}