{
  "type": "Feature",
  "properties": {
    "iso:country":"DE",
    "sg:address":"Provinzstr. 88",
    "sg:city":"Berlin",
    "sg:phone":"+49 30/4923087",
    "sg:postcode":"13409",
    "sg:province":"Berlin",
    "wof:name":"Hollys Sportladen H. Seidel",
    "wof:placetype":"venue"
},
  "geometry": {"coordinates":[13.379117,52.56953],"type":"Point"}
}