{
  "type": "Feature",
  "properties": {
    "iso:country":"DE",
    "sg:address":"Zwickauer Str. 61",
    "sg:city":"Meerane",
    "sg:phone":"+49 3764/4477",
    "sg:postcode":"08393",
    "sg:province":"Sachsen",
    "wof:name":"J\u00f6rg H\u00fcfner",
    "wof:placetype":"venue"
},
  "geometry": {"coordinates":[12.4681282043,50.8423194885],"type":"Point"}
}