{
  "type": "Feature",
  "properties": {
    "iso:country":"DE",
    "sg:address":"Eschstr. 1",
    "sg:city":"S\u00fcdlohn",
    "sg:phone":"+49 2862/7276",
    "sg:postcode":"46354",
    "sg:province":"Nordrhein-Westfalen",
    "wof:name":"Hotel Haus L\u00f6velt",
    "wof:placetype":"venue"
},
  "geometry": {"coordinates":[6.8680291176,51.945350647],"type":"Point"}
}