{
  "type": "Feature",
  "properties": {
    "iso:country":"DE",
    "sg:address":"Fiedelerstr. 25",
    "sg:city":"Hannover",
    "sg:phone":"+49 511/835776",
    "sg:postcode":"30519",
    "sg:province":"Niedersachsen",
    "wof:name":"Restaurant Ariston",
    "wof:placetype":"venue"
},
  "geometry": {"coordinates":[9.7637271881,52.3390808105],"type":"Point"}
}