{
  "type": "Feature",
  "properties": {
    "iso:country":"DE",
    "sg:address":"Eichendorffstr. 14",
    "sg:city":"Leingarten",
    "sg:postcode":"74211",
    "sg:province":"Baden-W\u00fcrttemberg",
    "wof:name":"Redaktion Ibe Informationen Und Berichte",
    "wof:placetype":"venue"
},
  "geometry": {"coordinates":[9.0975255966,49.147895813],"type":"Point"}
}