{
  "type": "Feature",
  "properties": {
    "iso:country":"DE",
    "sg:address":"Landsberger Str. 11",
    "sg:city":"Augsburg",
    "sg:phone":"+49 821/808570",
    "sg:postcode":"86179",
    "sg:province":"Bayern",
    "wof:name":"Rudi P\u00f6lsterl Ohg",
    "wof:placetype":"venue"
},
  "geometry": {"coordinates":[10.908616066,48.3150062561],"type":"Point"}
}