{
  "type": "Feature",
  "properties": {
    "iso:country":"DE",
    "sg:address":"Holzstr. 37",
    "sg:city":"D\u00fcren",
    "sg:phone":"+49 2421/42724",
    "sg:postcode":"52349",
    "sg:province":"Nordrhein-Westfalen",
    "wof:name":"Karl-heinz Langen",
    "wof:placetype":"venue"
},
  "geometry": {"coordinates":[6.474907,50.801601],"type":"Point"}
}