{
  "type": "Feature",
  "properties": {
    "iso:country":"DE",
    "sg:address":"Teuchatz",
    "sg:city":"Heiligenstadt",
    "sg:phone":"+49 9505/1702",
    "sg:postcode":"91332",
    "sg:province":"Bayern",
    "wof:name":"Georg Neuner",
    "wof:placetype":"venue"
},
  "geometry": {"coordinates":[11.0909852982,49.8708648682],"type":"Point"}
}