{
  "type": "Feature",
  "properties": {
    "iso:country":"DE",
    "sg:address":"Bahnhofstr. 5",
    "sg:city":"Bindlach",
    "sg:phone":"+49 9208/271",
    "sg:postcode":"95463",
    "sg:province":"Bayern",
    "wof:name":"B\u00e4ren-apotheke",
    "wof:placetype":"venue"
},
  "geometry": {"coordinates":[11.610234,49.980553],"type":"Point"}
}