{
  "type": "Feature",
  "properties": {
    "iso:country":"DE",
    "sg:address":"Frankensteinstr. 23",
    "sg:city":"Arnstein",
    "sg:phone":"+49 9363/1763",
    "sg:postcode":"97450",
    "sg:province":"Bayern",
    "wof:name":"Robert Lichtlein",
    "wof:placetype":"venue"
},
  "geometry": {"coordinates":[9.957859993,49.9790115356],"type":"Point"}
}