{
  "type": "Feature",
  "properties": {
    "iso:country":"DE",
    "sg:address":"Zeiler Str. 3",
    "sg:city":"Ha\u00dffurt",
    "sg:phone":"+49 9521/9500098",
    "sg:postcode":"97437",
    "sg:province":"Bayern",
    "wof:name":"Andre Kamphausen Rechtsanwalt",
    "wof:placetype":"venue"
},
  "geometry": {"coordinates":[10.5139513016,50.0326461792],"type":"Point"}
}