{
  "type": "Feature",
  "properties": {
    "iso:country":"DE",
    "sg:address":"Neust\u00e4dter Str. 186",
    "sg:city":"P\u00f6\u00dfneck",
    "sg:phone":"+49 3647/412678",
    "sg:postcode":"07381",
    "sg:province":"Th\u00fcringen",
    "wof:name":"G. Meinhardt",
    "wof:placetype":"venue"
},
  "geometry": {"coordinates":[11.61681,50.70155],"type":"Point"}
}