{
  "type": "Feature",
  "properties": {
    "iso:country":"DE",
    "sg:address":"Am Ziegelfeld 12",
    "sg:city":"Nentershausen",
    "sg:phone":"+49 6627/681",
    "sg:postcode":"36214",
    "sg:province":"Hessen",
    "wof:name":"R. Tarant Garten- Und Landschafts-",
    "wof:placetype":"venue"
},
  "geometry": {"coordinates":[9.929527,51.0158],"type":"Point"}
}