{
  "type": "Feature",
  "properties": {
    "iso:country":"DE",
    "sg:address":"Lange Str. 79",
    "sg:city":"Sulingen",
    "sg:phone":"+49 4271/2248",
    "sg:postcode":"27232",
    "sg:province":"Niedersachsen",
    "wof:name":"Hotel Meier-riehl",
    "wof:placetype":"venue"
},
  "geometry": {"coordinates":[8.7963457108,52.6812744141],"type":"Point"}
}