{
  "type": "Feature",
  "properties": {
    "iso:country":"DE",
    "sg:address":"Am Hecklehamm",
    "sg:city":"H\u00fcgelsheim",
    "sg:postcode":"76549",
    "sg:province":"Baden-W\u00fcrttemberg",
    "wof:name":"Markant",
    "wof:placetype":"venue"
},
  "geometry": {"coordinates":[8.1149454117,48.800617218],"type":"Point"}
}