{
  "type": "Feature",
  "properties": {
    "iso:country":"DE",
    "sg:address":"Fr.-Ebert-Str.14",
    "sg:city":"Altenburg",
    "sg:phone":"+49 3447/551838",
    "sg:postcode":"04600",
    "sg:province":"Th\u00fcringen",
    "wof:name":"Altenburger Skatschule Gmbh",
    "wof:placetype":"venue"
},
  "geometry": {"coordinates":[12.435251236,50.9884605408],"type":"Point"}
}