{
  "type": "Feature",
  "properties": {
    "iso:country":"DE",
    "sg:address":"Georgstr. 54",
    "sg:city":"Hannover",
    "sg:phone":"+49 511/3681003",
    "sg:postcode":"30159",
    "sg:province":"Niedersachsen",
    "wof:name":"American Express International Inc.",
    "wof:placetype":"venue"
},
  "geometry": {"coordinates":[9.740901947,52.3714981079],"type":"Point"}
}