{
  "type": "Feature",
  "properties": {
    "iso:country":"DE",
    "sg:address":"Kollower Str 40c",
    "sg:city":"Schwarzenbek",
    "sg:phone":"+49 4151/6544",
    "sg:postcode":"21493",
    "sg:province":"Schleswig-Holstein",
    "wof:name":"Thomas Baeck",
    "wof:placetype":"venue"
},
  "geometry": {"coordinates":[10.47404,53.497437],"type":"Point"}
}