{
  "type": "Feature",
  "properties": {
    "iso:country":"DE",
    "sg:address":"Wericastr. 10",
    "sg:city":"Witten",
    "sg:phone":"+49 2302/77003",
    "sg:postcode":"58456",
    "sg:province":"Nordrhein-Westfalen",
    "wof:name":"K. Und L. Kessenbrock",
    "wof:placetype":"venue"
},
  "geometry": {"coordinates":[7.2852168083,51.4234199524],"type":"Point"}
}