{
  "type": "Feature",
  "properties": {
    "iso:country":"DE",
    "sg:address":"Hammelstalstr. 44",
    "sg:city":"Bad D\u00fcrkheim",
    "sg:phone":"+49 6322/989097",
    "sg:postcode":"67098",
    "sg:province":"Rheinland-Pfalz",
    "wof:name":"H. Harm Immobilienmakler",
    "wof:placetype":"venue"
},
  "geometry": {"coordinates":[8.1473703384,49.4521789551],"type":"Point"}
}