{
  "type": "Feature",
  "properties": {
    "iso:country":"DE",
    "sg:address":"Max-Reger-Str. 2a",
    "sg:city":"Weiden",
    "sg:phone":"+49 961/482120",
    "sg:postcode":"92637",
    "sg:province":"Bayern",
    "wof:name":"J\u00fcrgen Schr\u00f6ter Steuerberater",
    "wof:placetype":"venue"
},
  "geometry": {"coordinates":[12.15873909,49.6748657227],"type":"Point"}
}