{
  "type": "Feature",
  "properties": {
    "iso:country":"DE",
    "sg:address":"Bahnhofstr. 16A",
    "sg:city":"S\u00fcderbrarup",
    "sg:phone":"+49 4641/1801",
    "sg:postcode":"24392",
    "sg:province":"Schleswig-Holstein",
    "wof:name":"Gerlinde Jorga Hardwarehandel",
    "wof:placetype":"venue"
},
  "geometry": {"coordinates":[9.772149086,54.6370582581],"type":"Point"}
}