{
  "type": "Feature",
  "properties": {
    "iso:country":"DE",
    "sg:address":"Gundhelmer Str. 11",
    "sg:city":"Schl\u00fcchtern",
    "sg:phone":"+49 6661/4574",
    "sg:postcode":"36381",
    "sg:province":"Hessen",
    "wof:name":"H. Dorn Garten- Und",
    "wof:placetype":"venue"
},
  "geometry": {"coordinates":[9.557038,50.359364],"type":"Point"}
}