{
  "type": "Feature",
  "properties": {
    "iso:country":"DE",
    "sg:city":"Gerbrunn",
    "sg:postcode":"97218",
    "sg:province":"Bayern",
    "wof:name":"Gela \u00b484 E. V.",
    "wof:placetype":"venue"
},
  "geometry": {"coordinates":[9.983605,49.778069],"type":"Point"}
}