{
  "type": "Feature",
  "properties": {
    "iso:country":"DE",
    "sg:address":"Arminiusstr 67",
    "sg:city":"Gera",
    "sg:phone":"+49 365/737670",
    "sg:postcode":"07548",
    "sg:province":"Th\u00fcringen",
    "wof:name":"Ost-consult Gesellschaft F\u00fcr Generalplanung, Umweltschutz Und Unternehmensberatung Mbh",
    "wof:placetype":"venue"
},
  "geometry": {"coordinates":[12.065647,50.862415],"type":"Point"}
}