{
  "type": "Feature",
  "properties": {
    "iso:country":"DE",
    "sg:address":"Lemgoer Str. 63",
    "sg:city":"Lemgo",
    "sg:phone":"+49 5261/89008",
    "sg:postcode":"32657",
    "sg:province":"Nordrhein-Westfalen",
    "wof:name":"Wilh. Kaufmann",
    "wof:placetype":"venue"
},
  "geometry": {"coordinates":[8.913755,52.018482],"type":"Point"}
}