{
  "type": "Feature",
  "properties": {
    "iso:country":"DE",
    "sg:address":"Hauptstr. 3",
    "sg:city":"B\u00f6hlen",
    "sg:phone":"+49 34386/41344",
    "sg:postcode":"04668",
    "sg:province":"Sachsen",
    "wof:name":"K. Schmieder",
    "wof:placetype":"venue"
},
  "geometry": {"coordinates":[12.73623,51.219872],"type":"Point"}
}