{
  "type": "Feature",
  "properties": {
    "iso:country":"DE",
    "sg:address":"Apelsteinallee 22",
    "sg:city":"Wachau",
    "sg:phone":"+49 34297/76300",
    "sg:postcode":"04416",
    "sg:province":"Sachsen",
    "wof:name":"Ams Mess-, Steuer- U. Automatisierungservice Gmbh",
    "wof:placetype":"venue"
},
  "geometry": {"coordinates":[12.381605,51.272709],"type":"Point"}
}