{
  "type": "Feature",
  "properties": {
    "iso:country":"DE",
    "sg:address":"Fritz-Reuter-Str. 12",
    "sg:city":"Rehna",
    "sg:phone":"+49 38872/56335",
    "sg:postcode":"19217",
    "sg:province":"Mecklenburg-Vorpommern",
    "wof:name":"Wilfried Janetzke",
    "wof:placetype":"venue"
},
  "geometry": {"coordinates":[11.048182,53.777977],"type":"Point"}
}