{
  "type": "Feature",
  "properties": {
    "iso:country":"DE",
    "sg:address":"Repkowstr. 2",
    "sg:city":"Magdeburg",
    "sg:postcode":"39122",
    "sg:province":"Sachsen-Anhalt",
    "wof:name":"Katholisches Pfarramt St. Joh. Baptist",
    "wof:placetype":"venue"
},
  "geometry": {"coordinates":[11.6711244583,52.073890686],"type":"Point"}
}