{
  "type": "Feature",
  "properties": {
    "iso:country":"DE",
    "sg:address":"Winkelser Str. 4",
    "sg:city":"Bad Kissingen",
    "sg:phone":"+49 971/71760",
    "sg:postcode":"97688",
    "sg:province":"Bayern",
    "wof:name":"H\u00e4ckner Bosch-dienst Gmbh",
    "wof:placetype":"venue"
},
  "geometry": {"coordinates":[10.0917129517,50.2029953003],"type":"Point"}
}