{
  "type": "Feature",
  "properties": {
    "iso:country":"DE",
    "sg:address":"Poststr. 6",
    "sg:city":"Bad Saulgau",
    "sg:phone":"+49 7581/8751",
    "sg:postcode":"88348",
    "sg:province":"Baden-W\u00fcrttemberg",
    "wof:name":"Bambi-theater",
    "wof:placetype":"venue"
},
  "geometry": {"coordinates":[9.500849,48.015209],"type":"Point"}
}