{
  "type": "Feature",
  "properties": {
    "iso:country":"DE",
    "sg:address":"Max-Planck-Str. 5",
    "sg:city":"Wernigerode",
    "sg:phone":"+49 3943/56677",
    "sg:postcode":"38855",
    "sg:province":"Sachsen-Anhalt",
    "wof:name":"Klingenberger Gmbh",
    "wof:placetype":"venue"
},
  "geometry": {"coordinates":[10.80961,51.849972],"type":"Point"}
}