{
  "type": "Feature",
  "properties": {
    "iso:country":"DE",
    "sg:address":"Wenigerath 9",
    "sg:city":"Morbach",
    "sg:phone":"+49 6533/9589931",
    "sg:postcode":"54497",
    "sg:province":"Rheinland-Pfalz",
    "wof:name":"Tierheilpraxis F\u00fcr Energetische Therapien",
    "wof:placetype":"venue"
},
  "geometry": {"coordinates":[7.1372,49.827679],"type":"Point"}
}