{
  "type": "Feature",
  "properties": {
    "iso:country":"DE",
    "sg:address":"Borsigstr. 8",
    "sg:city":"L\u00fcbbecke",
    "sg:phone":"+49 5741/297031",
    "sg:postcode":"32312",
    "sg:province":"Nordrhein-Westfalen",
    "wof:name":"Werner Blase Gmbh & Co. Kg",
    "wof:placetype":"venue"
},
  "geometry": {"coordinates":[8.62003,52.324188],"type":"Point"}
}