{
  "type": "Feature",
  "properties": {
    "iso:country":"DE",
    "sg:address":"Erlanger Str. 39",
    "sg:city":"F\u00fcrth",
    "sg:phone":"+49 911/7906694",
    "sg:postcode":"90765",
    "sg:province":"Bayern",
    "wof:name":"Ernst Olbert",
    "wof:placetype":"venue"
},
  "geometry": {"coordinates":[10.9974479675,49.4807281494],"type":"Point"}
}