{
  "type": "Feature",
  "properties": {
    "iso:country":"DE",
    "sg:address":"Dieselstr. 2",
    "sg:city":"Meckesheim",
    "sg:phone":"+49 6226/5122",
    "sg:postcode":"74909",
    "sg:province":"Baden-W\u00fcrttemberg",
    "wof:name":"Mtm-metall Technic Mechanic Gmbh",
    "wof:placetype":"venue"
},
  "geometry": {"coordinates":[8.8054485321,49.3257789612],"type":"Point"}
}