{
  "type": "Feature",
  "properties": {
    "iso:country":"DE",
    "sg:address":"K\u00f6lner Str. 40",
    "sg:city":"Leverkusen",
    "sg:phone":"+49 2171/2141",
    "sg:postcode":"51379",
    "sg:province":"Nordrhein-Westfalen",
    "wof:name":"Siegmund Walczyk",
    "wof:placetype":"venue"
},
  "geometry": {"coordinates":[7.0034451485,51.0648460388],"type":"Point"}
}