{
  "type": "Feature",
  "properties": {
    "iso:country":"DE",
    "sg:address":"Am Borsigturm 9",
    "sg:city":"Berlin",
    "sg:phone":"+49 30/8827664",
    "sg:postcode":"13507",
    "sg:province":"Berlin",
    "wof:name":"Robert Schumacher Rechtsanwalt",
    "wof:placetype":"venue"
},
  "geometry": {"coordinates":[13.2861728668,52.5835952759],"type":"Point"}
}