{
  "type": "Feature",
  "properties": {
    "iso:country":"DE",
    "sg:address":"Lilienstr. 20",
    "sg:city":"Velbert",
    "sg:phone":"+49 2053/3808",
    "sg:postcode":"42553",
    "sg:province":"Nordrhein-Westfalen",
    "wof:name":"Max Wendland",
    "wof:placetype":"venue"
},
  "geometry": {"coordinates":[7.0964708328,51.2981109619],"type":"Point"}
}