{
  "type": "Feature",
  "properties": {
    "iso:country":"DE",
    "sg:address":"m\u00fchlenstr. 20",
    "sg:city":"neuss",
    "sg:phone":"+49 2131",
    "sg:postcode":"41460",
    "sg:province":"Nordrhein-Westfalen",
    "wof:name":"Galerie Bilderetage Kll\u00f6den",
    "wof:placetype":"venue"
},
  "geometry": {"coordinates":[6.6962752342,51.1948394775],"type":"Point"}
}