{
  "type": "Feature",
  "properties": {
    "iso:country":"DE",
    "sg:address":"Wagrainstr. 8",
    "sg:city":"Gro\u00dfbottwar",
    "sg:phone":"+49 7148/8425",
    "sg:postcode":"71723",
    "sg:province":"Baden-W\u00fcrttemberg",
    "wof:name":"Willi Philipps",
    "wof:placetype":"venue"
},
  "geometry": {"coordinates":[9.294,48.997112],"type":"Point"}
}