{
  "type": "Feature",
  "properties": {
    "iso:country":"DE",
    "sg:address":"Von-Stephan-Str. 14",
    "sg:city":"Babenhausen",
    "sg:phone":"+49 6073/4122",
    "sg:postcode":"64832",
    "sg:province":"Hessen",
    "wof:name":"Hartl Software- Entwicklungs Gmbh",
    "wof:placetype":"venue"
},
  "geometry": {"coordinates":[8.9577703476,49.9665870667],"type":"Point"}
}