{
  "type": "Feature",
  "properties": {
    "iso:country":"DE",
    "sg:address":"Hangarsteinstr. 49",
    "sg:city":"Kassel",
    "sg:phone":"+49 561/88877",
    "sg:postcode":"34130",
    "sg:province":"Hessen",
    "wof:name":"Helmut Peter",
    "wof:placetype":"venue"
},
  "geometry": {"coordinates":[9.452476,51.326153],"type":"Point"}
}