{
  "type": "Feature",
  "properties": {
    "iso:country":"DE",
    "sg:address":"M\u00f6rzheimer Hauptstr. 34",
    "sg:city":"Landau",
    "sg:phone":"+49 6341/34331",
    "sg:postcode":"76829",
    "sg:province":"Rheinland-Pfalz",
    "wof:name":"Gastst\u00e4tte Zum Goldenen L\u00f6wen",
    "wof:placetype":"venue"
},
  "geometry": {"coordinates":[8.0747919083,49.1681747437],"type":"Point"}
}