{
  "type": "Feature",
  "properties": {
    "iso:country":"DE",
    "sg:address":"M\u00fchlenstrasse 34a",
    "sg:city":"Gro\u00df Wittensee",
    "sg:phone":"+49 4356/315",
    "sg:postcode":"24361",
    "sg:province":"Schleswig-Holstein",
    "wof:name":"Mass Gmbh Malereibetrieb",
    "wof:placetype":"venue"
},
  "geometry": {"coordinates":[9.766866,54.407452],"type":"Point"}
}