{
  "type": "Feature",
  "properties": {
    "iso:country":"DE",
    "sg:address":"Lindenstr. 9",
    "sg:city":"Iffezheim",
    "sg:phone":"+49 7229/2358",
    "sg:postcode":"76473",
    "sg:province":"Baden-W\u00fcrttemberg",
    "wof:name":"W. Leuchtner",
    "wof:placetype":"venue"
},
  "geometry": {"coordinates":[8.139879,48.824055],"type":"Point"}
}