{
  "type": "Feature",
  "properties": {
    "iso:country":"DE",
    "sg:address":"W\u00fcstinger Ring",
    "sg:city":"Hude",
    "sg:phone":"+49 4484/364",
    "sg:postcode":"27798",
    "sg:province":"Niedersachsen",
    "wof:name":"G\u00fcnter Sch\u00fctte",
    "wof:placetype":"venue"
},
  "geometry": {"coordinates":[8.33351,53.11985],"type":"Point"}
}