{
  "type": "Feature",
  "properties": {
    "iso:country":"DE",
    "sg:address":"Ahornring 8",
    "sg:city":"Roggentin",
    "sg:phone":"+49 38204",
    "sg:postcode":"18184",
    "sg:province":"Mecklenburg-Vorpommern",
    "wof:name":"Happy-toys",
    "wof:placetype":"venue"
},
  "geometry": {"coordinates":[12.2183008194,54.0762023926],"type":"Point"}
}