{
  "type": "Feature",
  "properties": {
    "iso:country":"DE",
    "sg:address":"Hauptstr. 95",
    "sg:city":"Kreuzau",
    "sg:phone":"+49 2422/8041",
    "sg:postcode":"52372",
    "sg:province":"Nordrhein-Westfalen",
    "wof:name":"Kreuzauer Reiseb\u00fcro Gmbh",
    "wof:placetype":"venue"
},
  "geometry": {"coordinates":[6.4928498268,50.7453765869],"type":"Point"}
}