{
  "type": "Feature",
  "properties": {
    "iso:country":"DE",
    "sg:address":"Steinsfurter Str. 33",
    "sg:city":"Sinsheim",
    "sg:phone":"+49 7261/2608",
    "sg:postcode":"74889",
    "sg:province":"Baden-W\u00fcrttemberg",
    "wof:name":"J. M\u00fcller",
    "wof:placetype":"venue"
},
  "geometry": {"coordinates":[8.906179,49.24255],"type":"Point"}
}