{
  "type": "Feature",
  "properties": {
    "iso:country":"DE",
    "sg:address":"B\u00e4ckerwiese 1",
    "sg:city":"Duderstadt",
    "sg:phone":"+49 5527/2826",
    "sg:postcode":"37115",
    "sg:province":"Niedersachsen",
    "wof:name":"August Becker",
    "wof:placetype":"venue"
},
  "geometry": {"coordinates":[10.224954,51.519245],"type":"Point"}
}