{
  "type": "Feature",
  "properties": {
    "iso:country":"DE",
    "sg:address":"Rosmarinweg 7",
    "sg:city":"Bad Zwischenahn",
    "sg:phone":"+49 4403/1033",
    "sg:postcode":"26160",
    "sg:province":"Niedersachsen",
    "wof:name":"Hotel Am Torfteich",
    "wof:placetype":"venue"
},
  "geometry": {"coordinates":[8.0190763474,53.1783943176],"type":"Point"}
}