{
  "type": "Feature",
  "properties": {
    "iso:country":"DE",
    "sg:address":"Rittershausstr. 65",
    "sg:city":"Dortmund",
    "sg:phone":"+49 231/148241",
    "sg:postcode":"44137",
    "sg:province":"Nordrhein-Westfalen",
    "wof:name":"Kamp Beteiligungs Gmbh",
    "wof:placetype":"venue"
},
  "geometry": {"coordinates":[7.450173,51.50782],"type":"Point"}
}