{
  "type": "Feature",
  "properties": {
    "iso:country":"DE",
    "sg:address":"Heyestr. 99",
    "sg:city":"D\u00fcsseldorf",
    "sg:phone":"+49 211/28080",
    "sg:postcode":"40625",
    "sg:province":"Nordrhein-Westfalen",
    "wof:name":"Rheinischer Gemeindeunfall- Versicherungsverband",
    "wof:placetype":"venue"
},
  "geometry": {"coordinates":[6.8625531197,51.2260475159],"type":"Point"}
}