{
  "type": "Feature",
  "properties": {
    "iso:country":"DE",
    "sg:address":"Auenweg 22",
    "sg:city":"Meuschau",
    "sg:phone":"+49 3461/219005",
    "sg:postcode":"06217",
    "sg:province":"Sachsen-Anhalt",
    "wof:name":"M. F\u00f6rster",
    "wof:placetype":"venue"
},
  "geometry": {"coordinates":[11.9790410995,51.3501472473],"type":"Point"}
}