{
  "type": "Feature",
  "properties": {
    "iso:country":"DE",
    "sg:address":"Am Natruper Holz 60",
    "sg:city":"Osnabr\u00fcck",
    "sg:phone":"+49 541/65180",
    "sg:postcode":"49090",
    "sg:province":"Niedersachsen",
    "wof:name":"Hermann Bruns",
    "wof:placetype":"venue"
},
  "geometry": {"coordinates":[8.0091648102,52.2890548706],"type":"Point"}
}