{
  "type": "Feature",
  "properties": {
    "iso:country":"DE",
    "sg:address":"Wagnerstr. 44a",
    "sg:city":"L\u00fcdenscheid",
    "sg:phone":"+49 2351/60535",
    "sg:postcode":"58509",
    "sg:province":"Nordrhein-Westfalen",
    "wof:name":"Julius Gosdzinski",
    "wof:placetype":"venue"
},
  "geometry": {"coordinates":[7.5974397659,51.221118927],"type":"Point"}
}