{
  "type": "Feature",
  "properties": {
    "iso:country":"DE",
    "sg:address":"Burg-Windeck-Str. 2",
    "sg:city":"B\u00fchl",
    "sg:postcode":"77815",
    "sg:province":"Baden-W\u00fcrttemberg",
    "wof:name":"Zachmann Ingenieur Consult Gmbh",
    "wof:placetype":"venue"
},
  "geometry": {"coordinates":[8.1366786957,48.6937637329],"type":"Point"}
}