{
  "type": "Feature",
  "properties": {
    "iso:country":"DE",
    "sg:address":"K\u00f6thener Str. 27",
    "sg:city":"Halle",
    "sg:phone":"+49 345/5234180",
    "sg:postcode":"06118",
    "sg:province":"Sachsen-Anhalt",
    "wof:name":"Stoll",
    "wof:placetype":"venue"
},
  "geometry": {"coordinates":[11.956386,51.523926],"type":"Point"}
}