{
  "type": "Feature",
  "properties": {
    "iso:country":"DE",
    "sg:address":"Alte Poststr. 21",
    "sg:city":"Freising",
    "sg:phone":"+49 8161/938110",
    "sg:postcode":"85356",
    "sg:province":"Bayern",
    "wof:name":"Erwin Maurer Gmbh",
    "wof:placetype":"venue"
},
  "geometry": {"coordinates":[11.751391,48.404911],"type":"Point"}
}