{
  "type": "Feature",
  "properties": {
    "iso:country":"DE",
    "sg:address":"Hauptstr. 27",
    "sg:city":"Wendlingen",
    "sg:phone":"+49 7024/7132",
    "sg:postcode":"73240",
    "sg:province":"Baden-W\u00fcrttemberg",
    "wof:name":"A. Grossmann Kohlenhandlung",
    "wof:placetype":"venue"
},
  "geometry": {"coordinates":[9.37413,48.667294],"type":"Point"}
}