{
  "type": "Feature",
  "properties": {
    "iso:country":"DE",
    "sg:address":"Bergstr. 19",
    "sg:city":"Eckernf\u00f6rde",
    "sg:phone":"+49 4351/81173",
    "sg:postcode":"24340",
    "sg:province":"Schleswig-Holstein",
    "wof:name":"Lindenhof",
    "wof:placetype":"venue"
},
  "geometry": {"coordinates":[9.839466095,54.4773254395],"type":"Point"}
}