{
  "type": "Feature",
  "properties": {
    "iso:country":"DE",
    "sg:address":"Wei\u00dfenberger Str. 12",
    "sg:city":"Dresden",
    "sg:phone":"+49 351/2686914",
    "sg:postcode":"01324",
    "sg:province":"Sachsen",
    "wof:name":"Roswitha Oehme-heintze",
    "wof:placetype":"venue"
},
  "geometry": {"coordinates":[13.846326,51.063133],"type":"Point"}
}