{
  "type": "Feature",
  "properties": {
    "iso:country":"DE",
    "sg:address":"Stra\u00dfe Nach Trebnitz 12",
    "sg:city":"Teuchern",
    "sg:phone":"+49 4934/4436133",
    "sg:postcode":"06682",
    "sg:province":"Sachsen-Anhalt",
    "wof:name":"Osterland Landwirtschafts Gmbh",
    "wof:placetype":"venue"
},
  "geometry": {"coordinates":[12.03081,51.11528],"type":"Point"}
}