{
  "type": "Feature",
  "properties": {
    "iso:country":"DE",
    "sg:address":"Luitpoldstr. 53",
    "sg:city":"Ottobeuren",
    "sg:phone":"+49 8332/212",
    "sg:postcode":"87724",
    "sg:province":"Bayern",
    "wof:name":"E. Brosig",
    "wof:placetype":"venue"
},
  "geometry": {"coordinates":[10.298866,47.938335],"type":"Point"}
}