{
  "type": "Feature",
  "properties": {
    "iso:country":"DE",
    "sg:address":"Heinrich-Pieper-Str. 1c",
    "sg:city":"Goslar",
    "sg:phone":"+49 5321/21522",
    "sg:postcode":"38640",
    "sg:province":"Niedersachsen",
    "wof:name":"Junge Medien Niedersachsen E. V.",
    "wof:placetype":"venue"
},
  "geometry": {"coordinates":[10.4262075424,51.9190292358],"type":"Point"}
}