{
  "type": "Feature",
  "properties": {
    "iso:country":"DE",
    "sg:address":"R\u00f6ckumstr. 138",
    "sg:city":"Bonn",
    "sg:postcode":"53121",
    "sg:province":"Nordrhein-Westfalen",
    "wof:name":"Terra Internet-farm Gmbh",
    "wof:placetype":"venue"
},
  "geometry": {"coordinates":[7.07219,50.71999],"type":"Point"}
}