{
  "type": "Feature",
  "properties": {
    "iso:country":"DE",
    "sg:address":"Landsberger Str. 317",
    "sg:city":"M\u00fcnchen",
    "sg:phone":"+49 89/564610",
    "sg:postcode":"80687",
    "sg:province":"Bayern",
    "wof:name":"Cleopatra",
    "wof:placetype":"venue"
},
  "geometry": {"coordinates":[11.4977483749,48.1433830261],"type":"Point"}
}