{
  "type": "Feature",
  "properties": {
    "iso:country":"DE",
    "sg:address":"Wipperf\u00fcrther Str. 140",
    "sg:city":"K\u00fcrten",
    "sg:phone":"+49 2207/7390",
    "sg:postcode":"51515",
    "sg:province":"Nordrhein-Westfalen",
    "wof:name":"P. Sch\u00e4tzm\u00fcller",
    "wof:placetype":"venue"
},
  "geometry": {"coordinates":[7.2226901054,51.0119514465],"type":"Point"}
}