{
  "type": "Feature",
  "properties": {
    "iso:country":"DE",
    "sg:address":"Hauptstr. 19a",
    "sg:city":"Mahlberg",
    "sg:phone":"+49 7822/3334",
    "sg:postcode":"77972",
    "sg:province":"Baden-W\u00fcrttemberg",
    "wof:name":"Schaub",
    "wof:placetype":"venue"
},
  "geometry": {"coordinates":[7.7994999886,48.2788124084],"type":"Point"}
}