{
  "type": "Feature",
  "properties": {
    "iso:country":"DE",
    "sg:address":"Will\u00f6perstr. 2",
    "sg:city":"Hamburg",
    "sg:phone":"+49 40/6939377",
    "sg:postcode":"22047",
    "sg:province":"Hamburg",
    "wof:name":"D. Und O. Muss",
    "wof:placetype":"venue"
},
  "geometry": {"coordinates":[10.10166,53.58326],"type":"Point"}
}