{
  "type": "Feature",
  "properties": {
    "iso:country":"DE",
    "sg:address":"Klettenberg 44",
    "sg:city":"Kitzingen",
    "sg:phone":"+49 9321/937211",
    "sg:postcode":"97318",
    "sg:province":"Bayern",
    "wof:name":"Stt Sch\u00fc\u00dfler Transformatoren-technik Gmbh & Co Kg",
    "wof:placetype":"venue"
},
  "geometry": {"coordinates":[10.191296,49.726524],"type":"Point"}
}