{
  "type": "Feature",
  "properties": {
    "iso:country":"DE",
    "sg:address":"Wei\u00dfenburger Str. 10",
    "sg:city":"M\u00fcnchen",
    "sg:phone":"+49 89/238070",
    "sg:postcode":"81667",
    "sg:province":"Bayern",
    "wof:name":"M\u00f6ssbauer Gmbh",
    "wof:placetype":"venue"
},
  "geometry": {"coordinates":[11.595454216,48.1284790039],"type":"Point"}
}