{
  "type": "Feature",
  "properties": {
    "iso:country":"DE",
    "sg:address":"Traut\u00e4ckerstr. 11",
    "sg:city":"Stuttgart",
    "sg:postcode":"70567",
    "sg:province":"Baden-W\u00fcrttemberg",
    "wof:name":"Gib Gesellschaft F\u00fcr Immobilien - Und",
    "wof:placetype":"venue"
},
  "geometry": {"coordinates":[9.1603679657,48.7256584167],"type":"Point"}
}