{
  "type": "Feature",
  "properties": {
    "iso:country":"DE",
    "sg:address":"Br\u00fcckenstr. 75",
    "sg:city":"Erftstadt",
    "sg:phone":"+49 2235/67541",
    "sg:postcode":"50374",
    "sg:province":"Nordrhein-Westfalen",
    "wof:name":"M. May Verm\u00f6gens- Verwaltungs- Gmbh",
    "wof:placetype":"venue"
},
  "geometry": {"coordinates":[6.7674460411,50.8210334778],"type":"Point"}
}