{
  "type": "Feature",
  "properties": {
    "iso:country":"DE",
    "sg:address":"Im Br\u00fchl 3",
    "sg:city":"Konz",
    "sg:phone":"+49 6501/15565",
    "sg:postcode":"54329",
    "sg:province":"Rheinland-Pfalz",
    "wof:name":"Martin Schmitt",
    "wof:placetype":"venue"
},
  "geometry": {"coordinates":[6.632226944,49.6625785828],"type":"Point"}
}