{
  "type": "Feature",
  "properties": {
    "iso:country":"DE",
    "sg:address":"Schlo\u00dfstra\u00dfe 76",
    "sg:city":"Bergisch Gladbach",
    "sg:phone":"+49 2204",
    "sg:postcode":"51429",
    "sg:province":"Nordrhein-Westfalen",
    "wof:name":"Magnetrol International Gmbh",
    "wof:placetype":"venue"
},
  "geometry": {"coordinates":[7.1604099274,50.9654464722],"type":"Point"}
}