{
  "type": "Feature",
  "properties": {
    "iso:country":"DE",
    "sg:address":"Mainstr. 101",
    "sg:city":"Breuberg",
    "sg:phone":"+49 6165/6135",
    "sg:postcode":"64747",
    "sg:province":"Hessen",
    "wof:name":"Erwin Sauerwein",
    "wof:placetype":"venue"
},
  "geometry": {"coordinates":[9.043489,49.835129],"type":"Point"}
}