{
  "type": "Feature",
  "properties": {
    "iso:country":"DE",
    "sg:address":"Sofienstr. 1",
    "sg:city":"T\u00fcbingen",
    "sg:phone":"+49 7071/410804",
    "sg:postcode":"72070",
    "sg:province":"Baden-W\u00fcrttemberg",
    "wof:name":"Heinrich Funk",
    "wof:placetype":"venue"
},
  "geometry": {"coordinates":[9.047497,48.521233],"type":"Point"}
}