{
  "type": "Feature",
  "properties": {
    "iso:country":"DE",
    "sg:address":"Alte Poststr. 20",
    "sg:city":"N\u00fcmbrecht",
    "sg:phone":"+49 2293/4542",
    "sg:postcode":"51588",
    "sg:province":"Nordrhein-Westfalen",
    "wof:name":"Molly",
    "wof:placetype":"venue"
},
  "geometry": {"coordinates":[7.543027,50.902905],"type":"Point"}
}