{
  "type": "Feature",
  "properties": {
    "iso:country":"DE",
    "sg:address":"Jakobstr. 9",
    "sg:city":"Aachen",
    "sg:phone":"+49 241/22562",
    "sg:postcode":"52064",
    "sg:province":"Nordrhein-Westfalen",
    "wof:name":"St. Pauls-apotheke",
    "wof:placetype":"venue"
},
  "geometry": {"coordinates":[6.0802,50.774731],"type":"Point"}
}