{
  "type": "Feature",
  "properties": {
    "iso:country":"DE",
    "sg:address":"Osterfeldstr. 1 a",
    "sg:city":"Porta Westfalica",
    "sg:phone":"+49 571/52551",
    "sg:postcode":"32457",
    "sg:province":"Nordrhein-Westfalen",
    "wof:name":"M\u00f6bel-gestelle Buchheister Gmbh",
    "wof:placetype":"venue"
},
  "geometry": {"coordinates":[8.9100608826,52.2536735535],"type":"Point"}
}