{
  "type": "Feature",
  "properties": {
    "iso:country":"DE",
    "sg:address":"Hermann-Hesse-Str. 106",
    "sg:city":"Mainz",
    "sg:phone":"+49 6131/72454",
    "sg:postcode":"55127",
    "sg:province":"Rheinland-Pfalz",
    "wof:name":"H. Und W. Riemann",
    "wof:placetype":"venue"
},
  "geometry": {"coordinates":[8.1945314407,49.9559898376],"type":"Point"}
}