{
  "type": "Feature",
  "properties": {
    "iso:country":"DE",
    "sg:address":"Am Bahndamm 1",
    "sg:city":"Nettetal",
    "sg:phone":"+49 2153/9507830",
    "sg:postcode":"41334",
    "sg:province":"Nordrhein-Westfalen",
    "wof:name":"3d-zerspanungstechnik Gmbh",
    "wof:placetype":"venue"
},
  "geometry": {"coordinates":[6.25794,51.288132],"type":"Point"}
}