{
  "type": "Feature",
  "properties": {
    "iso:country":"DE",
    "sg:address":"Kippelbachstr. 1",
    "sg:city":"Gersfeld",
    "sg:phone":"+49 6654/8785",
    "sg:postcode":"36129",
    "sg:province":"Hessen",
    "wof:name":"Wahl",
    "wof:placetype":"venue"
},
  "geometry": {"coordinates":[9.921354,50.448933],"type":"Point"}
}