{
  "type": "Feature",
  "properties": {
    "iso:country":"DE",
    "sg:address":"Wilmskamp 15",
    "sg:city":"M\u00f6nchengladbach",
    "sg:phone":"+49 2161/966060",
    "sg:postcode":"41069",
    "sg:province":"Nordrhein-Westfalen",
    "wof:name":"A Lifestyle Handels- Und Unterhaltungs Gmbh",
    "wof:placetype":"venue"
},
  "geometry": {"coordinates":[6.3996858597,51.1739883423],"type":"Point"}
}