{
  "type": "Feature",
  "properties": {
    "iso:country":"DE",
    "sg:address":"Imperialstr. 32",
    "sg:city":"B\u00fcnde",
    "sg:phone":"+49 5223/6754",
    "sg:postcode":"32257",
    "sg:province":"Nordrhein-Westfalen",
    "wof:name":"Reisedienst Elsetal Heinz Hemminghaus Gmbh & Co.",
    "wof:placetype":"venue"
},
  "geometry": {"coordinates":[8.5164136887,52.1956748962],"type":"Point"}
}