{
  "type": "Feature",
  "properties": {
    "iso:country":"DE",
    "sg:address":"Gro\u00dfer Kuhlenweg 76 b",
    "sg:city":"Oldenburg",
    "sg:phone":"+49 441/31379",
    "sg:postcode":"26125",
    "sg:province":"Niedersachsen",
    "wof:name":"Rudolf Nolte Dipl.-ingenieur",
    "wof:placetype":"venue"
},
  "geometry": {"coordinates":[8.2371788025,53.1635360718],"type":"Point"}
}