{
  "type": "Feature",
  "properties": {
    "iso:country":"DE",
    "sg:address":"Meseberger Str. 30",
    "sg:city":"Wolmirstedt",
    "sg:phone":"+49 39201/22254",
    "sg:postcode":"39326",
    "sg:province":"Sachsen-Anhalt",
    "wof:name":"G. Schulze",
    "wof:placetype":"venue"
},
  "geometry": {"coordinates":[11.61564,52.249767],"type":"Point"}
}