{
  "type": "Feature",
  "properties": {
    "iso:country":"DE",
    "sg:address":"Berliner Str. 36",
    "sg:city":"Meerbusch",
    "sg:phone":"+49 2150/4306",
    "sg:postcode":"40668",
    "sg:province":"Nordrhein-Westfalen",
    "wof:name":"Franz-peter Becker",
    "wof:placetype":"venue"
},
  "geometry": {"coordinates":[6.68638,51.308079],"type":"Point"}
}