{
  "type": "Feature",
  "properties": {
    "iso:country":"DE",
    "sg:address":"Siedlung 17",
    "sg:city":"Sch\u00f6neck",
    "sg:phone":"+49 30/54431625",
    "sg:postcode":"08261",
    "sg:province":"Sachsen",
    "wof:name":"Rasche Transporte Radojkow & Scherzer Gbr",
    "wof:placetype":"venue"
},
  "geometry": {"coordinates":[12.2959623337,50.3947715759],"type":"Point"}
}