{
  "type": "Feature",
  "properties": {
    "iso:country":"DE",
    "sg:address":"Gunneby 63",
    "sg:city":"Ulsnis",
    "sg:phone":"+49 4641/8369",
    "sg:postcode":"24897",
    "sg:province":"Schleswig-Holstein",
    "wof:name":"Hans-heinrich Hansen",
    "wof:placetype":"venue"
},
  "geometry": {"coordinates":[9.7787,54.58374],"type":"Point"}
}