{
  "type": "Feature",
  "properties": {
    "iso:country":"DE",
    "sg:address":"Industriestr. 8",
    "sg:city":"Dormagen",
    "sg:phone":"+49 2133/70638",
    "sg:postcode":"41542",
    "sg:province":"Nordrhein-Westfalen",
    "wof:name":"Friedhelm Kemper",
    "wof:placetype":"venue"
},
  "geometry": {"coordinates":[6.787265,51.129776],"type":"Point"}
}