{
  "type": "Feature",
  "properties": {
    "iso:country":"DE",
    "sg:address":"Wirtembergstr. 59",
    "sg:city":"Fellbach",
    "sg:phone":"+49 711/5160420",
    "sg:postcode":"70736",
    "sg:province":"Baden-W\u00fcrttemberg",
    "wof:name":"Karl-heinz L\u00f6sch",
    "wof:placetype":"venue"
},
  "geometry": {"coordinates":[9.262202,48.832294],"type":"Point"}
}