{
  "type": "Feature",
  "properties": {
    "iso:country":"DE",
    "sg:address":"Spanische Allee 138",
    "sg:city":"Berlin",
    "sg:phone":"+49 30/8031111",
    "sg:postcode":"14129",
    "sg:province":"Berlin",
    "wof:name":"Tex Pack Handels-und Service Gmbh",
    "wof:placetype":"venue"
},
  "geometry": {"coordinates":[13.197258,52.434788],"type":"Point"}
}