{
  "type": "Feature",
  "properties": {
    "iso:country":"DE",
    "sg:address":"Auf dem H\u00fcgel 41",
    "sg:city":"Salzgitter",
    "sg:phone":"+49 5341/34135",
    "sg:postcode":"38259",
    "sg:province":"Niedersachsen",
    "wof:name":"Mini Car Dragon Gmbh",
    "wof:placetype":"venue"
},
  "geometry": {"coordinates":[10.3755979538,52.0696640015],"type":"Point"}
}