{
  "type": "Feature",
  "properties": {
    "iso:country":"DE",
    "sg:address":"Glandorfer Damm 40",
    "sg:city":"Lienen",
    "sg:phone":"+49 5484/321",
    "sg:postcode":"49536",
    "sg:province":"Nordrhein-Westfalen",
    "wof:name":"N. Vahrenhorst",
    "wof:placetype":"venue"
},
  "geometry": {"coordinates":[7.9141049385,52.112575531],"type":"Point"}
}