{
  "type": "Feature",
  "properties": {
    "iso:country":"DE",
    "sg:address":"Bruchhagen 13",
    "sg:city":"Steyerberg",
    "sg:phone":"+49 5764/809",
    "sg:postcode":"31595",
    "sg:province":"Niedersachsen",
    "wof:name":"Ewald Oldenburg",
    "wof:placetype":"venue"
},
  "geometry": {"coordinates":[8.976207,52.547462],"type":"Point"}
}