{
  "type": "Feature",
  "properties": {
    "iso:country":"DE",
    "sg:address":"Citypassage 5",
    "sg:city":"Pfungstadt",
    "sg:postcode":"64319",
    "sg:province":"Hessen",
    "wof:name":"Frosch",
    "wof:placetype":"venue"
},
  "geometry": {"coordinates":[8.6005916595,49.8039550781],"type":"Point"}
}