{
  "type": "Feature",
  "properties": {
    "iso:country":"DE",
    "sg:address":"Weinstr. 11",
    "sg:city":"Pfaffenweiler",
    "sg:phone":"+49 7664/97020",
    "sg:postcode":"79292",
    "sg:province":"Baden-W\u00fcrttemberg",
    "wof:name":"Gebhardt Ehrath Steuerberater",
    "wof:placetype":"venue"
},
  "geometry": {"coordinates":[7.7556247711,47.9411277771],"type":"Point"}
}