{
  "type": "Feature",
  "properties": {
    "iso:country":"DE",
    "sg:address":"Sandstr. 39",
    "sg:city":"Ratingen",
    "sg:phone":"+49 2102/448316",
    "sg:postcode":"40878",
    "sg:province":"Nordrhein-Westfalen",
    "wof:name":"T\u00dcv Rheinland",
    "wof:placetype":"venue"
},
  "geometry": {"coordinates":[6.8371009827,51.2944526672],"type":"Point"}
}