{
  "type": "Feature",
  "properties": {
    "iso:country":"DE",
    "sg:address":"K\u00fcppersstr. 7",
    "sg:city":"Bad Kreuznach",
    "sg:phone":"+49 671/61483",
    "sg:postcode":"55543",
    "sg:province":"Rheinland-Pfalz",
    "wof:name":"F. Und U. Eichenauer Kunstmaler",
    "wof:placetype":"venue"
},
  "geometry": {"coordinates":[7.858355,49.828369],"type":"Point"}
}