{
  "type": "Feature",
  "properties": {
    "iso:country":"DE",
    "sg:address":"Amtsstr. 30",
    "sg:city":"Bielefeld",
    "sg:postcode":"33739",
    "sg:province":"Nordrhein-Westfalen",
    "wof:name":"Kleindienst Autowaschtechnik",
    "wof:placetype":"venue"
},
  "geometry": {"coordinates":[8.518052,52.095844],"type":"Point"}
}