{
  "type": "Feature",
  "properties": {
    "iso:country":"DE",
    "sg:address":"Zietenstr. 8",
    "sg:city":"Berlin",
    "sg:phone":"+49 30/7729037",
    "sg:postcode":"12249",
    "sg:province":"Berlin",
    "wof:name":"Staedtler Reinigungsservice Gmbh",
    "wof:placetype":"venue"
},
  "geometry": {"coordinates":[13.336888,52.429981],"type":"Point"}
}