{
  "type": "Feature",
  "properties": {
    "iso:country":"DE",
    "sg:address":"Kalkumer Str. 106",
    "sg:city":"D\u00fcsseldorf",
    "sg:postcode":"40468",
    "sg:province":"Nordrhein-Westfalen",
    "wof:name":"Professional Travel Service Gmbh",
    "wof:placetype":"venue"
},
  "geometry": {"coordinates":[6.7743220329,51.2697792053],"type":"Point"}
}