{
  "type": "Feature",
  "properties": {
    "iso:country":"DE",
    "sg:address":"Lerchenstr. 134",
    "sg:city":"Osnabr\u00fcck",
    "sg:phone":"+49 541/62028",
    "sg:postcode":"49088",
    "sg:province":"Niedersachsen",
    "wof:name":"Brietzke Schleif- Technik Gmbh",
    "wof:placetype":"venue"
},
  "geometry": {"coordinates":[8.0572795868,52.2999458313],"type":"Point"}
}