{
  "type": "Feature",
  "properties": {
    "iso:country":"DE",
    "sg:address":"Friedrichstr. 7",
    "sg:city":"Kellinghusen",
    "sg:phone":"+49 4822/5123",
    "sg:postcode":"25548",
    "sg:province":"Schleswig-Holstein",
    "wof:name":"Carsten Eickstaedt",
    "wof:placetype":"venue"
},
  "geometry": {"coordinates":[9.7285346985,53.9470863342],"type":"Point"}
}