{
  "type": "Feature",
  "properties": {
    "iso:country":"DE",
    "sg:address":"Regentenstr. 175",
    "sg:city":"M\u00f6nchengladbach",
    "sg:phone":"+49 2161/13147",
    "sg:postcode":"41061",
    "sg:province":"Nordrhein-Westfalen",
    "wof:name":"Jannis",
    "wof:placetype":"venue"
},
  "geometry": {"coordinates":[6.4453539848,51.2027130127],"type":"Point"}
}