{
  "type": "Feature",
  "properties": {
    "iso:country":"DE",
    "sg:address":"Industriestr. 12",
    "sg:city":"Sta\u00dffurt",
    "sg:phone":"+49 3925/324129",
    "sg:postcode":"39418",
    "sg:province":"Sachsen-Anhalt",
    "wof:name":"Salzland Bau Gmbh",
    "wof:placetype":"venue"
},
  "geometry": {"coordinates":[11.5910959244,51.8446655273],"type":"Point"}
}