{
  "type": "Feature",
  "properties": {
    "iso:country":"DE",
    "sg:address":"Reutener Str.",
    "sg:city":"Mittelbiberach",
    "sg:phone":"+49 7351/23613",
    "sg:postcode":"88441",
    "sg:province":"Baden-W\u00fcrttemberg",
    "wof:name":"Kath. Pfarramt St. Nikolaus",
    "wof:placetype":"venue"
},
  "geometry": {"coordinates":[9.7484350204,48.0848083496],"type":"Point"}
}