{
  "type": "Feature",
  "properties": {
    "iso:country":"DE",
    "sg:address":"Kemsstr. 24",
    "sg:city":"Bad Krozingen",
    "sg:phone":"+49 7633/2149",
    "sg:postcode":"79189",
    "sg:province":"Baden-W\u00fcrttemberg",
    "wof:name":"Karl-heinz Hauser",
    "wof:placetype":"venue"
},
  "geometry": {"coordinates":[7.706746,47.907913],"type":"Point"}
}