{
  "type": "Feature",
  "properties": {
    "iso:country":"DE",
    "sg:address":"Delsener Heide 14",
    "sg:city":"Telgte",
    "sg:phone":"+49 2504/4240",
    "sg:postcode":"48291",
    "sg:province":"Nordrhein-Westfalen",
    "wof:name":"Bernhard Kortenbrede",
    "wof:placetype":"venue"
},
  "geometry": {"coordinates":[7.792551,51.964897],"type":"Point"}
}