{
  "type": "Feature",
  "properties": {
    "iso:country":"DE",
    "sg:city":"Rottenacker",
    "sg:phone":"+49 4973/932596",
    "sg:postcode":"89616",
    "sg:province":"Baden-W\u00fcrttemberg",
    "wof:name":"Sparkasse",
    "wof:placetype":"venue"
},
  "geometry": {"coordinates":[9.687475,48.232746],"type":"Point"}
}