{
  "type": "Feature",
  "properties": {
    "iso:country":"DE",
    "sg:address":"Bahnhofstr. 11",
    "sg:city":"Eschershausen",
    "sg:phone":"+49 5534/99230",
    "sg:postcode":"37632",
    "sg:province":"Niedersachsen",
    "wof:name":"Hils-apotheke",
    "wof:placetype":"venue"
},
  "geometry": {"coordinates":[9.64215,51.926479],"type":"Point"}
}