{
  "type": "Feature",
  "properties": {
    "iso:country":"DE",
    "sg:address":"Aspenweg 3",
    "sg:city":"Erbach",
    "sg:phone":"+49 7305/919080",
    "sg:postcode":"89155",
    "sg:province":"Baden-W\u00fcrttemberg",
    "wof:name":"Walker",
    "wof:placetype":"venue"
},
  "geometry": {"coordinates":[9.905662,48.297218],"type":"Point"}
}