{
  "type": "Feature",
  "properties": {
    "iso:country":"DE",
    "sg:address":"Von-Pl\u00fcschow Str. 14",
    "sg:city":"Manching",
    "sg:phone":"+49 8459/550",
    "sg:postcode":"85077",
    "sg:province":"Bayern",
    "wof:name":"Sparkasse Ingolstadt",
    "wof:placetype":"venue"
},
  "geometry": {"coordinates":[11.475059,48.718449],"type":"Point"}
}