{
  "type": "Feature",
  "properties": {
    "iso:country":"DE",
    "sg:address":"Siedlerstr. 9",
    "sg:city":"Unterf\u00f6hring",
    "sg:phone":"+49 4936/4812190",
    "sg:postcode":"85774",
    "sg:province":"Bayern",
    "wof:name":"Em Kunststofftechnik Gmbh",
    "wof:placetype":"venue"
},
  "geometry": {"coordinates":[11.777062,50.74218],"type":"Point"}
}