{
  "type": "Feature",
  "properties": {
    "iso:country":"DE",
    "sg:address":"Donnerschweer Str. 82",
    "sg:city":"Oldenburg",
    "sg:phone":"+49 441/9849949",
    "sg:postcode":"26123",
    "sg:province":"Niedersachsen",
    "wof:name":"Viola Sklarski Immobilienmaklerin",
    "wof:placetype":"venue"
},
  "geometry": {"coordinates":[8.2227916718,53.1476593018],"type":"Point"}
}