{
  "type": "Feature",
  "properties": {
    "iso:country":"DE",
    "sg:address":"Adalbertstr. 5",
    "sg:city":"Frankfurt",
    "sg:phone":"+49 69/7075680",
    "sg:postcode":"60486",
    "sg:province":"Hessen",
    "wof:name":"Stefan Weinreich Gmbh",
    "wof:placetype":"venue"
},
  "geometry": {"coordinates":[8.649251,50.119919],"type":"Point"}
}