{
  "type": "Feature",
  "properties": {
    "iso:country":"DE",
    "sg:address":"Am Hang 6",
    "sg:city":"Gifhorn",
    "sg:phone":"+49 5371/4251",
    "sg:postcode":"38518",
    "sg:province":"Niedersachsen",
    "wof:name":"Rosemarie Leisge Heilpraktikerin",
    "wof:placetype":"venue"
},
  "geometry": {"coordinates":[10.5386629105,52.4872894287],"type":"Point"}
}