{
  "type": "Feature",
  "properties": {
    "iso:country":"DE",
    "sg:address":"Stollen 10",
    "sg:city":"Remscheid",
    "sg:phone":"+49 2191/22048",
    "sg:postcode":"42899",
    "sg:province":"Nordrhein-Westfalen",
    "wof:name":"Hermann Fr\u00f6hlich Gmbh & Co. Kg",
    "wof:placetype":"venue"
},
  "geometry": {"coordinates":[7.2156920433,51.2051200867],"type":"Point"}
}