{
  "type": "Feature",
  "properties": {
    "iso:country":"DE",
    "sg:address":"Hofheimer Str. 10",
    "sg:city":"Hattersheim",
    "sg:phone":"+49 69/4691624",
    "sg:postcode":"65795",
    "sg:province":"Hessen",
    "wof:name":"Medaillon",
    "wof:placetype":"venue"
},
  "geometry": {"coordinates":[8.4814510345,50.0709571838],"type":"Point"}
}