{
  "type": "Feature",
  "properties": {
    "iso:country":"DE",
    "sg:address":"Olvenstedter Scheid 71",
    "sg:city":"Magdeburg",
    "sg:phone":"+49 391/7225347",
    "sg:postcode":"39130",
    "sg:province":"Sachsen-Anhalt",
    "wof:name":"K. Breda Immobilienmakler",
    "wof:placetype":"venue"
},
  "geometry": {"coordinates":[11.5888328552,52.1498069763],"type":"Point"}
}