{
  "type": "Feature",
  "properties": {
    "iso:country":"DE",
    "sg:address":"St.-B\u00e4uml-Str. 1",
    "sg:city":"Thalmassing",
    "sg:phone":"+49 9453/550",
    "sg:postcode":"93107",
    "sg:province":"Bayern",
    "wof:name":"Johann Ipfelkofer",
    "wof:placetype":"venue"
},
  "geometry": {"coordinates":[12.135144,48.916447],"type":"Point"}
}