{
  "type": "Feature",
  "properties": {
    "iso:country":"DE",
    "sg:address":"Wilhelm-Hauff-Str. 15",
    "sg:city":"K\u00f6nigsbronn",
    "sg:phone":"+49 7328/4528",
    "sg:postcode":"89551",
    "sg:province":"Baden-W\u00fcrttemberg",
    "wof:name":"Elfriede Fischer",
    "wof:placetype":"venue"
},
  "geometry": {"coordinates":[10.1134605408,48.7447357178],"type":"Point"}
}