{
  "type": "Feature",
  "properties": {
    "iso:country":"DE",
    "sg:address":"Martin-Reinhard-Str. 6",
    "sg:city":"Bad K\u00f6nigshofen",
    "sg:phone":"+49 9761/2087",
    "sg:postcode":"97631",
    "sg:province":"Bayern",
    "wof:name":"Karl Schuck",
    "wof:placetype":"venue"
},
  "geometry": {"coordinates":[10.4686822891,50.2995414734],"type":"Point"}
}