{
  "type": "Feature",
  "properties": {
    "iso:country":"DE",
    "sg:address":"Hag\u00e4ckerstr. 8",
    "sg:city":"Ostfildern",
    "sg:phone":"+49 711/4560060",
    "sg:postcode":"73760",
    "sg:province":"Baden-W\u00fcrttemberg",
    "wof:name":"Druckerei E.+ H. M\u00dcller Gmbh",
    "wof:placetype":"venue"
},
  "geometry": {"coordinates":[9.2266187668,48.7221298218],"type":"Point"}
}