{
  "type": "Feature",
  "properties": {
    "iso:country":"DE",
    "sg:address":"Industriestr. 11",
    "sg:city":"Neuenhaus",
    "sg:phone":"+49 5941/8464",
    "sg:postcode":"49828",
    "sg:province":"Niedersachsen",
    "wof:name":"Alfred Albers",
    "wof:placetype":"venue"
},
  "geometry": {"coordinates":[6.982404,52.512466],"type":"Point"}
}