{
  "type": "Feature",
  "properties": {
    "iso:country":"DE",
    "sg:address":"Unter Kleeburg 4",
    "sg:city":"Trier",
    "sg:phone":"+49 651/22262",
    "sg:postcode":"54296",
    "sg:province":"Rheinland-Pfalz",
    "wof:name":"Karl Heinz Welter Steuerberater",
    "wof:placetype":"venue"
},
  "geometry": {"coordinates":[6.6788191795,49.7467575073],"type":"Point"}
}