{
  "type": "Feature",
  "properties": {
    "iso:country":"DE",
    "sg:address":"Uferallee 23",
    "sg:city":"Bernkastel-Kues",
    "sg:phone":"+49 6531/3211",
    "sg:postcode":"54470",
    "sg:province":"Rheinland-Pfalz",
    "wof:name":"Karl Schmitz",
    "wof:placetype":"venue"
},
  "geometry": {"coordinates":[7.0482950211,49.9404144287],"type":"Point"}
}