{
  "type": "Feature",
  "properties": {
    "iso:country":"DE",
    "sg:address":"Wilhelmstr. 27",
    "sg:city":"Winterlingen",
    "sg:phone":"+49 7434/278890",
    "sg:postcode":"72474",
    "sg:province":"Baden-W\u00fcrttemberg",
    "wof:name":"Gerhard Risch Ingenieur",
    "wof:placetype":"venue"
},
  "geometry": {"coordinates":[9.1129322052,48.1777381897],"type":"Point"}
}