{
  "type": "Feature",
  "properties": {
    "iso:country":"DE",
    "sg:address":"Ophofstr. 2",
    "sg:city":"Gelsenkirchen",
    "sg:phone":"+49 209/3809300",
    "sg:postcode":"45894",
    "sg:province":"Nordrhein-Westfalen",
    "wof:name":"Michael Asmuth Rechtsanwalt",
    "wof:placetype":"venue"
},
  "geometry": {"coordinates":[7.0537018776,51.5785255432],"type":"Point"}
}