{
  "type": "Feature",
  "properties": {
    "iso:country":"DE",
    "sg:address":"S\u00fcdfeldstr. 7",
    "sg:city":"Hannover",
    "sg:phone":"+49 511/21260",
    "sg:postcode":"30453",
    "sg:province":"Niedersachsen",
    "wof:name":"Ditha Elektro- Fachgro\u00dfhandelshaus Gmbh",
    "wof:placetype":"venue"
},
  "geometry": {"coordinates":[9.6834001541,52.3679885864],"type":"Point"}
}