{
  "type": "Feature",
  "properties": {
    "iso:country":"DE",
    "sg:address":"Heideweg 7",
    "sg:city":"Duisburg",
    "sg:phone":"+49 2066/13819",
    "sg:postcode":"47198",
    "sg:province":"Nordrhein-Westfalen",
    "wof:name":"U. Bongards Immobilienmakler",
    "wof:placetype":"venue"
},
  "geometry": {"coordinates":[6.690071106,51.4597358704],"type":"Point"}
}