{
  "type": "Feature",
  "properties": {
    "iso:country":"DE",
    "sg:address":"Hochstr. 25",
    "sg:city":"Gelsenkirchen",
    "sg:phone":"+49 209/395110",
    "sg:postcode":"45894",
    "sg:province":"Nordrhein-Westfalen",
    "wof:name":"Hildegard Sikorski",
    "wof:placetype":"venue"
},
  "geometry": {"coordinates":[7.053039,51.579456],"type":"Point"}
}