{
  "type": "Feature",
  "properties": {
    "iso:country":"DE",
    "sg:address":"Friesdorfer Str. 121",
    "sg:city":"Bonn",
    "sg:phone":"+49 228/3869490",
    "sg:postcode":"53175",
    "sg:province":"Nordrhein-Westfalen",
    "wof:name":"Extra",
    "wof:placetype":"venue"
},
  "geometry": {"coordinates":[7.1453018188,50.6891975403],"type":"Point"}
}