{
  "type": "Feature",
  "properties": {
    "iso:country":"DE",
    "sg:address":"Estebr\u00fcgger Str. 7",
    "sg:city":"Buxtehude",
    "sg:phone":"+49 4161/2203",
    "sg:postcode":"21614",
    "sg:province":"Niedersachsen",
    "wof:name":"Architekturb\u00fcro Ghaschghaee & Schubert Buxtehude",
    "wof:placetype":"venue"
},
  "geometry": {"coordinates":[9.7008428574,53.4795913696],"type":"Point"}
}