{
  "type": "Feature",
  "properties": {
    "iso:country":"DE",
    "sg:address":"Wilhelmstr. 109",
    "sg:city":"Reutlingen",
    "sg:phone":"+49 7121/346235",
    "sg:postcode":"72764",
    "sg:province":"Baden-W\u00fcrttemberg",
    "wof:name":"Martin Rilling",
    "wof:placetype":"venue"
},
  "geometry": {"coordinates":[9.2139101028,48.4907722473],"type":"Point"}
}