{
  "type": "Feature",
  "properties": {
    "iso:country":"DE",
    "sg:address":"K\u00f6rnerstr. 9",
    "sg:city":"Bad Schwartau",
    "sg:phone":"+49 451/2801831",
    "sg:postcode":"23611",
    "sg:province":"Schleswig-Holstein",
    "wof:name":"Gabriele Und Stefan Ramien Rechtsanw\u00e4lte",
    "wof:placetype":"venue"
},
  "geometry": {"coordinates":[10.6877508163,53.9092178345],"type":"Point"}
}