{
  "type": "Feature",
  "properties": {
    "iso:country":"DE",
    "sg:address":"Schlo\u00dfplatz",
    "sg:city":"Karlsruhe",
    "sg:phone":"+49 721/6081",
    "sg:postcode":"76131",
    "sg:province":"Baden-W\u00fcrttemberg",
    "wof:name":"Institut F. Philosophie",
    "wof:placetype":"venue"
},
  "geometry": {"coordinates":[8.4010763168,49.0116996765],"type":"Point"}
}