{
  "type": "Feature",
  "properties": {
    "iso:country":"DE",
    "sg:address":"Kuhberg 23",
    "sg:city":"Neum\u00fcnster",
    "sg:phone":"+49 431/46129",
    "sg:postcode":"24534",
    "sg:province":"Schleswig-Holstein",
    "wof:name":"Goldschmiede Sch\u00fctt",
    "wof:placetype":"venue"
},
  "geometry": {"coordinates":[9.9831457138,54.0750808716],"type":"Point"}
}