{
  "type": "Feature",
  "properties": {
    "iso:country":"DE",
    "sg:address":"Krugerpfad 1",
    "sg:city":"Nettetal",
    "sg:phone":"+49 2153/89988",
    "sg:postcode":"41334",
    "sg:province":"Nordrhein-Westfalen",
    "wof:name":"H.j.g\u00f6rgens Verlagsvertretungen",
    "wof:placetype":"venue"
},
  "geometry": {"coordinates":[6.2858891487,51.3319282532],"type":"Point"}
}