{
  "type": "Feature",
  "properties": {
    "iso:country":"DE",
    "sg:address":"Havelberger Str. 50",
    "sg:city":"Breddin",
    "sg:phone":"+49 33972/40503",
    "sg:postcode":"16845",
    "sg:province":"Brandenburg",
    "wof:name":"Charlotte Fritz",
    "wof:placetype":"venue"
},
  "geometry": {"coordinates":[12.2205429077,52.88230896],"type":"Point"}
}