{
  "type": "Feature",
  "properties": {
    "iso:country":"DE",
    "sg:address":"Altenburger Str. 31",
    "sg:city":"Ronneburg",
    "sg:phone":"+49 36602/35082",
    "sg:postcode":"07580",
    "sg:province":"Th\u00fcringen",
    "wof:name":"Manfred Bauer",
    "wof:placetype":"venue"
},
  "geometry": {"coordinates":[12.186288,50.863564],"type":"Point"}
}