{
  "type": "Feature",
  "properties": {
    "iso:country":"DE",
    "sg:address":"P\u00fctjerweg 11",
    "sg:city":"Buchholz",
    "sg:phone":"+49 4181/98611",
    "sg:postcode":"21244",
    "sg:province":"Niedersachsen",
    "wof:name":"R. Michel Hebamme",
    "wof:placetype":"venue"
},
  "geometry": {"coordinates":[9.842718,53.329132],"type":"Point"}
}