{
  "type": "Feature",
  "properties": {
    "iso:country":"DE",
    "sg:address":"Falltorstr. 13-15",
    "sg:city":"Bergisch Gladbach",
    "sg:phone":"+49 2204/54751",
    "sg:postcode":"51429",
    "sg:province":"Nordrhein-Westfalen",
    "wof:name":"Wzv Verwaltungs- Gmbh",
    "wof:placetype":"venue"
},
  "geometry": {"coordinates":[7.1562,50.964409],"type":"Point"}
}