{
  "type": "Feature",
  "properties": {
    "iso:country":"DE",
    "sg:address":"Castroper Str. 107",
    "sg:city":"Bochum",
    "sg:phone":"+49 234/501734",
    "sg:postcode":"44791",
    "sg:province":"Nordrhein-Westfalen",
    "wof:name":"Partyservice Leske",
    "wof:placetype":"venue"
},
  "geometry": {"coordinates":[7.23155,51.487244],"type":"Point"}
}