{
  "type": "Feature",
  "properties": {
    "iso:country":"DE",
    "sg:address":"Hildesheimer Str. 140",
    "sg:city":"Hannover",
    "sg:phone":"+49 511/56358330",
    "sg:postcode":"30173",
    "sg:province":"Niedersachsen",
    "wof:name":"Alfa Verm\u00f6gensplanung Gmbh",
    "wof:placetype":"venue"
},
  "geometry": {"coordinates":[9.7562036514,52.3521156311],"type":"Point"}
}