{
  "type": "Feature",
  "properties": {
    "iso:country":"DE",
    "sg:address":"Am Piperfenn 16",
    "sg:city":"Brandenburg",
    "sg:postcode":"14776",
    "sg:province":"Brandenburg",
    "wof:name":"Sauer Hydraulik Gmbh",
    "wof:placetype":"venue"
},
  "geometry": {"coordinates":[12.596991539,52.3803787231],"type":"Point"}
}