{
  "type": "Feature",
  "properties": {
    "iso:country":"DE",
    "sg:address":"Schmiedestr. 3",
    "sg:city":"Gielde",
    "sg:phone":"+49 5339/415",
    "sg:postcode":"38315",
    "sg:province":"Niedersachsen",
    "wof:name":"Georg Und Christa Thiele",
    "wof:placetype":"venue"
},
  "geometry": {"coordinates":[10.49292,52.035191],"type":"Point"}
}