{
  "type": "Feature",
  "properties": {
    "iso:country":"DE",
    "sg:address":"Hirsch-Gereuth-Str. 32",
    "sg:city":"M\u00fcnchen",
    "sg:phone":"+49 89/784028",
    "sg:postcode":"81369",
    "sg:province":"Bayern",
    "wof:name":"Dr. Tino Krebs Und Partner",
    "wof:placetype":"venue"
},
  "geometry": {"coordinates":[11.5291013718,48.1070098877],"type":"Point"}
}