{
  "type": "Feature",
  "properties": {
    "iso:country":"DE",
    "sg:address":"Auf dem Berg 3",
    "sg:city":"Cavertitz",
    "sg:phone":"+49 35264/90480",
    "sg:postcode":"04758",
    "sg:province":"Sachsen",
    "wof:name":"Import Landtechnik Gmbh",
    "wof:placetype":"venue"
},
  "geometry": {"coordinates":[13.183728,51.392265],"type":"Point"}
}