{
  "type": "Feature",
  "properties": {
    "iso:country":"DE",
    "sg:address":"Salzstr. 36",
    "sg:city":"Gommern",
    "sg:phone":"+49 39200/51579",
    "sg:postcode":"39245",
    "sg:province":"Sachsen-Anhalt",
    "wof:name":"G\u00fcnter Hagendorf",
    "wof:placetype":"venue"
},
  "geometry": {"coordinates":[11.817454,52.067493],"type":"Point"}
}