{
  "type": "Feature",
  "properties": {
    "iso:country":"DE",
    "sg:address":"Sch\u00fctzenhof 61",
    "sg:city":"Meppen",
    "sg:phone":"+49 5931/93960",
    "sg:postcode":"49716",
    "sg:province":"Niedersachsen",
    "wof:name":"Lana Kur M\u00f6belhandels Gmbh",
    "wof:placetype":"venue"
},
  "geometry": {"coordinates":[7.2845759392,52.7042350769],"type":"Point"}
}