{
  "type": "Feature",
  "properties": {
    "iso:country":"DE",
    "sg:address":"Schlo\u00dfstr. 14b",
    "sg:city":"Gr\u00fcnwald",
    "sg:postcode":"82031",
    "sg:province":"Bayern",
    "wof:name":"Mk Spezial Gmbh",
    "wof:placetype":"venue"
},
  "geometry": {"coordinates":[11.5238380432,48.0413665771],"type":"Point"}
}