{
  "type": "Feature",
  "properties": {
    "iso:country":"DE",
    "sg:address":"Dietershaner Str. 4",
    "sg:city":"Fulda",
    "sg:phone":"+49 661/65990",
    "sg:postcode":"36039",
    "sg:province":"Hessen",
    "wof:name":"Tilly Hohmann Stahl- Und Schneidwaren",
    "wof:placetype":"venue"
},
  "geometry": {"coordinates":[9.7051696777,50.6001396179],"type":"Point"}
}