{
  "type": "Feature",
  "properties": {
    "iso:country":"DE",
    "sg:address":"Ebertstr. 70",
    "sg:city":"Oberhausen",
    "sg:phone":"+49 208/26051",
    "sg:postcode":"46045",
    "sg:province":"Nordrhein-Westfalen",
    "wof:name":"Theater Oberhausen",
    "wof:placetype":"venue"
},
  "geometry": {"coordinates":[6.8604822159,51.4761581421],"type":"Point"}
}