{
  "type": "Feature",
  "properties": {
    "iso:country":"DE",
    "sg:address":"Recklingh\u00e4user Str. 22",
    "sg:city":"Dorsten",
    "sg:phone":"+49 2362/23308",
    "sg:postcode":"46282",
    "sg:province":"Nordrhein-Westfalen",
    "wof:name":"Datscha Inh. Dora Fr\u00fchauf",
    "wof:placetype":"venue"
},
  "geometry": {"coordinates":[6.9669151306,51.6602058411],"type":"Point"}
}