{
  "type": "Feature",
  "properties": {
    "iso:country":"DE",
    "sg:address":"66 rue de Ag\u00e9ratums",
    "sg:city":"le Tampon Ile de la R\u00e9union",
    "sg:postcode":"97430",
    "wof:name":"Net-planet,h\u00e9bergement,cr\u00e9ation,design,tutorial,schttp://www.net",
    "wof:placetype":"venue"
},
  "geometry": {"coordinates":[0.059402,44.335709],"type":"Point"}
}