{
  "type": "Feature",
  "properties": {
    "iso:country":"DE",
    "sg:address":"Neue Weinsteige 44",
    "sg:city":"Stuttgart",
    "sg:phone":"+49 711/648640",
    "sg:postcode":"70180",
    "sg:province":"Baden-W\u00fcrttemberg",
    "wof:name":"Verlag S\u00fcdwestdeutscher Einzelhandel Gmbh",
    "wof:placetype":"venue"
},
  "geometry": {"coordinates":[9.1797103882,48.7646789551],"type":"Point"}
}