{
  "type": "Feature",
  "properties": {
    "iso:country":"DE",
    "sg:address":"Gensunger Str. 5",
    "sg:city":"Felsberg",
    "sg:phone":"+49 5662/2033",
    "sg:postcode":"34587",
    "sg:province":"Hessen",
    "wof:name":"Helmut G\u00f6bel",
    "wof:placetype":"venue"
},
  "geometry": {"coordinates":[9.465688,51.116364],"type":"Point"}
}