{
  "type": "Feature",
  "properties": {
    "iso:country":"DE",
    "sg:address":"Gaustr. 6",
    "sg:city":"Dolgesheim",
    "sg:postcode":"55278",
    "sg:province":"Rheinland-Pfalz",
    "wof:name":"Gunter Starck",
    "wof:placetype":"venue"
},
  "geometry": {"coordinates":[8.2596769333,49.795879364],"type":"Point"}
}