{
  "type": "Feature",
  "properties": {
    "iso:country":"DE",
    "sg:address":"Hauptstr. 37",
    "sg:city":"Surwold",
    "sg:phone":"+49 4965/990011",
    "sg:postcode":"26903",
    "sg:province":"Niedersachsen",
    "wof:name":"Korte & Co. Sch\u00fcttguthandel Und Transport Gmbh",
    "wof:placetype":"venue"
},
  "geometry": {"coordinates":[7.5107340813,52.98387146],"type":"Point"}
}