{
  "type": "Feature",
  "properties": {
    "iso:country":"DE",
    "sg:address":"Auf dem B\u00fclt 40",
    "sg:city":"Twist",
    "sg:phone":"+49 5936/6116",
    "sg:postcode":"49767",
    "sg:province":"Niedersachsen",
    "wof:name":"H. Backers",
    "wof:placetype":"venue"
},
  "geometry": {"coordinates":[7.0608758926,52.6411705017],"type":"Point"}
}