{
  "type": "Feature",
  "properties": {
    "iso:country":"DE",
    "sg:address":"Freiherr-vom-Stein-Promenade",
    "sg:city":"Oschatz",
    "sg:phone":"+49 3435/929412",
    "sg:postcode":"04758",
    "sg:province":"Sachsen",
    "wof:name":"Kay Achtelik Rechtsanwalt",
    "wof:placetype":"venue"
},
  "geometry": {"coordinates":[13.1097278595,51.2946510315],"type":"Point"}
}