{
  "type": "Feature",
  "properties": {
    "iso:country":"DE",
    "sg:address":"Brink 7",
    "sg:city":"Spelle",
    "sg:phone":"+49 5977/93790",
    "sg:postcode":"48480",
    "sg:province":"Niedersachsen",
    "wof:name":"Schwimmhalle",
    "wof:placetype":"venue"
},
  "geometry": {"coordinates":[7.470580101,52.370098114],"type":"Point"}
}