{
  "type": "Feature",
  "properties": {
    "iso:country":"DE",
    "sg:address":"Wasenstr. 99",
    "sg:city":"Urbach",
    "sg:phone":"+49 7181/98850",
    "sg:postcode":"73660",
    "sg:province":"Baden-W\u00fcrttemberg",
    "wof:name":"Helmut Holzwarth Gmbh & Co. Kg",
    "wof:placetype":"venue"
},
  "geometry": {"coordinates":[9.5589151382,48.8087921143],"type":"Point"}
}