{
  "type": "Feature",
  "properties": {
    "iso:country":"DE",
    "sg:address":"Grundstr.3",
    "sg:city":"Hamburg",
    "sg:phone":"+49 40",
    "sg:postcode":"20257",
    "sg:province":"Hamburg",
    "wof:name":"Taxi-stadtf\u00fchrer-hamburg",
    "wof:placetype":"venue"
},
  "geometry": {"coordinates":[9.944423,53.577194],"type":"Point"}
}