{
  "type": "Feature",
  "properties": {
    "iso:country":"DE",
    "sg:address":"Ochsh\u00e4user Str. 40",
    "sg:city":"Kassel",
    "sg:phone":"+49 561/512670",
    "sg:postcode":"34123",
    "sg:province":"Hessen",
    "wof:name":"Kath. Pfarramt St. Andreas",
    "wof:placetype":"venue"
},
  "geometry": {"coordinates":[9.5364017487,51.2925033569],"type":"Point"}
}