{
  "type": "Feature",
  "properties": {
    "iso:country":"DE",
    "sg:address":"Hansestr. 18",
    "sg:city":"Stade",
    "sg:postcode":"21682",
    "sg:province":"Niedersachsen",
    "wof:name":"Stader Versorgungs- Und B\u00e4dergesellschaft Mbh",
    "wof:placetype":"venue"
},
  "geometry": {"coordinates":[9.477459,53.60519],"type":"Point"}
}