{
  "type": "Feature",
  "properties": {
    "iso:country":"DE",
    "sg:address":"Kayhstr. 5",
    "sg:city":"Bietigheim-Bissingen",
    "sg:phone":"+49 7142/41035",
    "sg:postcode":"74321",
    "sg:province":"Baden-W\u00fcrttemberg",
    "wof:name":"Makadamwerk Schwaben Gmbh",
    "wof:placetype":"venue"
},
  "geometry": {"coordinates":[9.1108217239,48.9481582642],"type":"Point"}
}