{
  "type": "Feature",
  "properties": {
    "iso:country":"DE",
    "sg:address":"In Gerderhahn 61a",
    "sg:city":"Erkelenz",
    "sg:phone":"+49 2431/5322",
    "sg:postcode":"41812",
    "sg:province":"Nordrhein-Westfalen",
    "wof:name":"Wilfried Jakobs",
    "wof:placetype":"venue"
},
  "geometry": {"coordinates":[6.239599,51.100163],"type":"Point"}
}