{
  "type": "Feature",
  "properties": {
    "iso:country":"DE",
    "sg:address":"Alte H\u00f6fe 1",
    "sg:city":"Gartow",
    "sg:phone":"+49 5846/9809033",
    "sg:postcode":"29471",
    "sg:province":"Niedersachsen",
    "wof:name":"Pension Sonnenhof",
    "wof:placetype":"venue"
},
  "geometry": {"coordinates":[11.4918174744,53.0108680725],"type":"Point"}
}