{
  "type": "Feature",
  "properties": {
    "iso:country":"DE",
    "sg:address":"Hauptstr. 52",
    "sg:city":"Dautphetal",
    "sg:phone":"+49 6466/7465",
    "sg:postcode":"35232",
    "sg:province":"Hessen",
    "wof:name":"Karl Henkel",
    "wof:placetype":"venue"
},
  "geometry": {"coordinates":[8.540048,50.858086],"type":"Point"}
}