{
  "type": "Feature",
  "properties": {
    "iso:country":"DE",
    "sg:address":"Bahnhofstr. 14",
    "sg:city":"Amberg",
    "sg:phone":"+49 9621/24105",
    "sg:postcode":"92224",
    "sg:province":"Bayern",
    "wof:name":"Optik Matt Augenoptik",
    "wof:placetype":"venue"
},
  "geometry": {"coordinates":[11.8608798981,49.4462623596],"type":"Point"}
}