{
  "type": "Feature",
  "properties": {
    "iso:country":"DE",
    "sg:address":"Ahlfeld 2",
    "sg:city":"Hamburg",
    "sg:phone":"+49 40/5521248",
    "sg:postcode":"22415",
    "sg:province":"Hamburg",
    "wof:name":"Hansa Langenhorn Immobilien Vermittlungsges. Mbh",
    "wof:placetype":"venue"
},
  "geometry": {"coordinates":[10.0194664001,53.6415176392],"type":"Point"}
}