{
  "type": "Feature",
  "properties": {
    "iso:country":"DE",
    "sg:address":"Tilburger Str. 22",
    "sg:city":"Viersen",
    "sg:phone":"+49 2162/41895",
    "sg:postcode":"41751",
    "sg:province":"Nordrhein-Westfalen",
    "wof:name":"Auto Schmitz Gmbh",
    "wof:placetype":"venue"
},
  "geometry": {"coordinates":[6.334727,51.255585],"type":"Point"}
}