{
  "type": "Feature",
  "properties": {
    "iso:country":"DE",
    "sg:address":"Emilienstr. 48",
    "sg:city":"Chemnitz",
    "sg:phone":"+49 371/419786",
    "sg:postcode":"09131",
    "sg:province":"Sachsen",
    "wof:name":"Vereinigte Haftpflicht Versicherung",
    "wof:placetype":"venue"
},
  "geometry": {"coordinates":[12.937207222,50.8512916565],"type":"Point"}
}