{
  "type": "Feature",
  "properties": {
    "iso:country":"DE",
    "sg:address":"Deisterstr. 39",
    "sg:city":"Hannover",
    "sg:phone":"+49 511/453209",
    "sg:postcode":"30449",
    "sg:province":"Niedersachsen",
    "wof:name":"M. B\u00e4hre",
    "wof:placetype":"venue"
},
  "geometry": {"coordinates":[9.7183885574,52.364780426],"type":"Point"}
}