{
  "type": "Feature",
  "properties": {
    "iso:country":"DE",
    "sg:address":"Bahnweg 1",
    "sg:city":"Sch\u00f6ntal",
    "sg:phone":"+49 7943/941650",
    "sg:postcode":"74214",
    "sg:province":"Baden-W\u00fcrttemberg",
    "wof:name":"Ralf Oppermann & Partner Beteiligungs Gmbh",
    "wof:placetype":"venue"
},
  "geometry": {"coordinates":[9.5596876144,49.3442001343],"type":"Point"}
}