{
  "type": "Feature",
  "properties": {
    "iso:country":"DE",
    "sg:address":"Gewerbering 8",
    "sg:city":"Hohenstein-Ernstthal",
    "sg:phone":"+49 3723/499170",
    "sg:postcode":"09337",
    "sg:province":"Sachsen",
    "wof:name":"Wirtschaftsjournal Sachsen Gmbh",
    "wof:placetype":"venue"
},
  "geometry": {"coordinates":[12.7559146881,50.8023414612],"type":"Point"}
}