{
  "type": "Feature",
  "properties": {
    "iso:country":"DE",
    "sg:address":"Eschenheimer Tor 2",
    "sg:city":"Frankfurt",
    "sg:phone":"+49 69/21931",
    "sg:postcode":"60318",
    "sg:province":"Hessen",
    "wof:name":"Beratungsstelle Pflanzenschutz",
    "wof:placetype":"venue"
},
  "geometry": {"coordinates":[8.679871,50.11726],"type":"Point"}
}