{
  "type": "Feature",
  "properties": {
    "iso:country":"DE",
    "sg:address":"Kurhausstr. 1",
    "sg:city":"Bad Segeberg",
    "sg:postcode":"23795",
    "sg:province":"Schleswig-Holstein",
    "wof:name":"Segm\u00fcller-caldera Grundst\u00fccksverwaltungsgesellschaft B\u00fcrgerlichen Rechts",
    "wof:placetype":"venue"
},
  "geometry": {"coordinates":[11.57752,48.13641],"type":"Point"}
}