{
  "type": "Feature",
  "properties": {
    "iso:country":"DE",
    "sg:address":"Papenhuder Str. 38",
    "sg:city":"Hamburg",
    "sg:phone":"+49 40/223638",
    "sg:postcode":"22087",
    "sg:province":"Hamburg",
    "wof:name":"Brigitte Petersen Heilpraktikerin",
    "wof:placetype":"venue"
},
  "geometry": {"coordinates":[10.0190725327,53.5673866272],"type":"Point"}
}