{
  "type": "Feature",
  "properties": {
    "iso:country":"DE",
    "sg:address":"Dr.-Martin-Luther-Str. 9",
    "sg:city":"Regensburg",
    "sg:phone":"+49 941/560681",
    "sg:postcode":"93047",
    "sg:province":"Bayern",
    "wof:name":"Lauterbach-zilch",
    "wof:placetype":"venue"
},
  "geometry": {"coordinates":[12.1020545959,49.016582489],"type":"Point"}
}