{
  "type": "Feature",
  "properties": {
    "iso:country":"DE",
    "sg:address":"Frankfurter Str. 17",
    "sg:city":"Unkel",
    "sg:phone":"+49 2224/73560",
    "sg:postcode":"53572",
    "sg:province":"Rheinland-Pfalz",
    "wof:name":"H. Dommermuth",
    "wof:placetype":"venue"
},
  "geometry": {"coordinates":[7.2155599594,50.5987281799],"type":"Point"}
}