{
  "type": "Feature",
  "properties": {
    "iso:country":"DE",
    "sg:address":"Kaiserstr. 37",
    "sg:city":"Rastatt",
    "sg:phone":"+49 7222/3840",
    "sg:postcode":"76437",
    "sg:province":"Baden-W\u00fcrttemberg",
    "wof:name":"Grundst\u00fccksgesellschaft Der Sparkasse Rastatt-gernsbach",
    "wof:placetype":"venue"
},
  "geometry": {"coordinates":[8.2020483017,48.8577308655],"type":"Point"}
}