{
  "type": "Feature",
  "properties": {
    "iso:country":"DE",
    "sg:address":"Landgrafenstr. 63",
    "sg:city":"Dortmund",
    "sg:phone":"+49 231/123820",
    "sg:postcode":"44139",
    "sg:province":"Nordrhein-Westfalen",
    "wof:name":"J. Strunk",
    "wof:placetype":"venue"
},
  "geometry": {"coordinates":[7.469668,51.503311],"type":"Point"}
}