{
  "type": "Feature",
  "properties": {
    "iso:country":"DE",
    "sg:address":"Carl-Zeiss-Str. 16",
    "sg:city":"Hemmingen",
    "sg:phone":"+49 511/414420",
    "sg:postcode":"30966",
    "sg:province":"Niedersachsen",
    "wof:name":"Isolab Gmbh",
    "wof:placetype":"venue"
},
  "geometry": {"coordinates":[9.7258405685,52.32056427],"type":"Point"}
}