{
  "type": "Feature",
  "properties": {
    "iso:country":"DE",
    "sg:address":"Westende 4",
    "sg:city":"Georgsdorf",
    "sg:phone":"+49 5946/531",
    "sg:postcode":"49828",
    "sg:province":"Niedersachsen",
    "wof:name":"J. Schnieders",
    "wof:placetype":"venue"
},
  "geometry": {"coordinates":[7.0676488876,52.5693817139],"type":"Point"}
}