{
  "type": "Feature",
  "properties": {
    "iso:country":"DE",
    "sg:address":"Neckarstr. 6",
    "sg:city":"M\u00fclheim",
    "sg:phone":"+49 208/56021",
    "sg:postcode":"45478",
    "sg:province":"Nordrhein-Westfalen",
    "wof:name":"Linder Gardinen Gmbh",
    "wof:placetype":"venue"
},
  "geometry": {"coordinates":[6.8568878174,51.4327201843],"type":"Point"}
}