{
  "type": "Feature",
  "properties": {
    "iso:country":"DE",
    "sg:address":"Adolf-Sautter-Str. 4",
    "sg:city":"Pforzheim",
    "sg:phone":"+49 7231/79233",
    "sg:postcode":"75181",
    "sg:province":"Baden-W\u00fcrttemberg",
    "wof:name":"C.a.c.h.e.t. Schmuck Gmbh",
    "wof:placetype":"venue"
},
  "geometry": {"coordinates":[8.735523,48.855961],"type":"Point"}
}