{
  "type": "Feature",
  "properties": {
    "iso:country":"DE",
    "sg:address":"Nunzenrieder Str. 9",
    "sg:city":"Oberviechtach",
    "sg:phone":"+49 9671/91630",
    "sg:postcode":"92526",
    "sg:province":"Bayern",
    "wof:name":"Druckerei Forstner Gmbh",
    "wof:placetype":"venue"
},
  "geometry": {"coordinates":[12.420323,49.457958],"type":"Point"}
}