{
  "type": "Feature",
  "properties": {
    "iso:country":"DE",
    "sg:address":"Dorfstr. 30",
    "sg:city":"Klein Meckelsen",
    "sg:phone":"+49 4282/1374",
    "sg:postcode":"27419",
    "sg:province":"Niedersachsen",
    "wof:name":"Kurt Burfeind",
    "wof:placetype":"venue"
},
  "geometry": {"coordinates":[9.454344,53.306469],"type":"Point"}
}