{
  "type": "Feature",
  "properties": {
    "iso:country":"DE",
    "sg:address":"Helmsweg 8",
    "sg:city":"Seevetal",
    "sg:phone":"+49 4105/14190",
    "sg:postcode":"21218",
    "sg:province":"Niedersachsen",
    "wof:name":"Sost Gmbh",
    "wof:placetype":"venue"
},
  "geometry": {"coordinates":[9.9771242142,53.4028739929],"type":"Point"}
}