{
  "type": "Feature",
  "properties": {
    "iso:country":"DE",
    "sg:address":"Neust\u00e4dter Str. 19",
    "sg:city":"Titisee-Neustadt",
    "sg:phone":"+49 7651/8147",
    "sg:postcode":"79822",
    "sg:province":"Baden-W\u00fcrttemberg",
    "wof:name":"Richard Kleiser",
    "wof:placetype":"venue"
},
  "geometry": {"coordinates":[8.15094,47.902805],"type":"Point"}
}