{
  "type": "Feature",
  "properties": {
    "iso:country":"DE",
    "sg:address":"Mittelstr. 8",
    "sg:city":"Uetze",
    "sg:phone":"+49 5147/72277",
    "sg:postcode":"31311",
    "sg:province":"Niedersachsen",
    "wof:name":"Vag-armaturen Gmbh",
    "wof:placetype":"venue"
},
  "geometry": {"coordinates":[10.201772,52.460526],"type":"Point"}
}