{
  "type": "Feature",
  "properties": {
    "iso:country":"DE",
    "sg:address":"Roermonder Str. 407",
    "sg:city":"Aachen",
    "sg:phone":"+49 241/176503",
    "sg:postcode":"52072",
    "sg:province":"Nordrhein-Westfalen",
    "wof:name":"Friedrich Mallmann Architekt",
    "wof:placetype":"venue"
},
  "geometry": {"coordinates":[6.0667,50.791698],"type":"Point"}
}