{
  "type": "Feature",
  "properties": {
    "iso:country":"DE",
    "sg:address":"An der Kanalbr\u00fccke 6",
    "sg:city":"Potsdam",
    "sg:phone":"+49 331/2759210",
    "sg:postcode":"14469",
    "sg:province":"Brandenburg",
    "wof:name":"Wei\u00dfe Flotte Potsdam Gmbh",
    "wof:placetype":"venue"
},
  "geometry": {"coordinates":[12.975374,52.451469],"type":"Point"}
}