{
  "type": "Feature",
  "properties": {
    "iso:country":"DE",
    "sg:address":"Jaspisstein 19",
    "sg:city":"Hof",
    "sg:phone":"+49 9281/40763",
    "sg:postcode":"95028",
    "sg:province":"Bayern",
    "wof:name":"Weihenstephan",
    "wof:placetype":"venue"
},
  "geometry": {"coordinates":[11.9245033264,50.3161201477],"type":"Point"}
}