{
  "type": "Feature",
  "properties": {
    "iso:country":"DE",
    "sg:address":"Vormarkt 21",
    "sg:city":"Trostberg",
    "sg:phone":"+49 8621/979088",
    "sg:postcode":"83308",
    "sg:province":"Bayern",
    "wof:name":"Christoph Bunk Rechtsanwalt",
    "wof:placetype":"venue"
},
  "geometry": {"coordinates":[12.5506839752,48.0271835327],"type":"Point"}
}