{
  "type": "Feature",
  "properties": {
    "iso:country":"DE",
    "sg:address":"Industriestr. 7",
    "sg:city":"Beverungen",
    "sg:phone":"+49 4952/7335780",
    "sg:postcode":"37688",
    "sg:province":"Nordrhein-Westfalen",
    "wof:name":"K\u00dcbler Galerie Gmbh",
    "wof:placetype":"venue"
},
  "geometry": {"coordinates":[9.3789901733,51.6746902466],"type":"Point"}
}