{
  "type": "Feature",
  "properties": {
    "iso:country":"DE",
    "sg:address":"Fuchsm\u00fchlenweg 7",
    "sg:city":"Freiberg",
    "sg:phone":"+49 3731/34849",
    "sg:postcode":"09599",
    "sg:province":"Sachsen",
    "wof:name":"Nightshift",
    "wof:placetype":"venue"
},
  "geometry": {"coordinates":[13.360117,50.927181],"type":"Point"}
}