{
  "type": "Feature",
  "properties": {
    "iso:country":"DE",
    "sg:address":"Engelhardtstr. 32",
    "sg:city":"Schwanstetten",
    "sg:postcode":"90596",
    "sg:province":"Bayern",
    "wof:name":"Automaten Werner",
    "wof:placetype":"venue"
},
  "geometry": {"coordinates":[11.1283016205,49.3166465759],"type":"Point"}
}