{
  "type": "Feature",
  "properties": {
    "iso:country":"DE",
    "sg:address":"Brunowstr. 52",
    "sg:city":"Berlin",
    "sg:phone":"+49 30/4338082",
    "sg:postcode":"13507",
    "sg:province":"Berlin",
    "wof:name":"Bik-bau Gmbh",
    "wof:placetype":"venue"
},
  "geometry": {"coordinates":[13.285084,52.587589],"type":"Point"}
}