{
  "type": "Feature",
  "properties": {
    "iso:country":"DE",
    "sg:address":"Pfarrstr. 5",
    "sg:city":"Oberstdorf",
    "sg:phone":"+49 8322/7541",
    "sg:postcode":"87561",
    "sg:province":"Bayern",
    "wof:name":"S Chalet Landhausmoden Arno Mysak",
    "wof:placetype":"venue"
},
  "geometry": {"coordinates":[10.2791252136,47.4081764221],"type":"Point"}
}