{
  "type": "Feature",
  "properties": {
    "iso:country":"DE",
    "sg:address":"D\u00fcnstr. 20",
    "sg:city":"Heilbad Heiligenstadt",
    "sg:postcode":"37308",
    "sg:province":"Th\u00fcringen",
    "wof:name":"Wa Me Umwelttechnik Gmbh & Co. Kg",
    "wof:placetype":"venue"
},
  "geometry": {"coordinates":[10.1512899399,51.3758010864],"type":"Point"}
}