{
  "type": "Feature",
  "properties": {
    "iso:country":"DE",
    "sg:address":"Haaggasse 1",
    "sg:city":"T\u00fcbingen",
    "sg:phone":"+49 7071/26155",
    "sg:postcode":"72070",
    "sg:province":"Baden-W\u00fcrttemberg",
    "wof:name":"Peter Danner Architekt",
    "wof:placetype":"venue"
},
  "geometry": {"coordinates":[9.053303,48.52013],"type":"Point"}
}