{
  "type": "Feature",
  "properties": {
    "iso:country":"DE",
    "sg:address":"Ludwigsplatz 1",
    "sg:city":"Edenkoben",
    "sg:phone":"+49 6323/980982",
    "sg:postcode":"67480",
    "sg:province":"Rheinland-Pfalz",
    "wof:name":"Heike Rost-axer",
    "wof:placetype":"venue"
},
  "geometry": {"coordinates":[8.1273479462,49.2816429138],"type":"Point"}
}