{
  "type": "Feature",
  "properties": {
    "iso:country":"DE",
    "sg:address":"Hauptstr. 16",
    "sg:city":"Carlsfeld",
    "sg:phone":"+49 37752/4084",
    "sg:postcode":"08325",
    "wof:name":"Sybille Hahn",
    "wof:placetype":"venue"
},
  "geometry": {"coordinates":[12.591991,50.433777],"type":"Point"}
}