{
  "type": "Feature",
  "properties": {
    "iso:country":"DE",
    "sg:address":"Seppenhofer Str. 7",
    "sg:city":"L\u00f6ffingen",
    "sg:phone":"+49 7654/80281",
    "sg:postcode":"79843",
    "sg:province":"Baden-W\u00fcrttemberg",
    "wof:name":"Altersheim St. Martin",
    "wof:placetype":"venue"
},
  "geometry": {"coordinates":[8.345408,47.881683],"type":"Point"}
}