{
  "type": "Feature",
  "properties": {
    "iso:country":"DE",
    "sg:address":"Rudolf-Breitscheid-Str 52",
    "sg:city":"Aue",
    "sg:phone":"+49 3771/552042",
    "sg:postcode":"08280",
    "sg:province":"Sachsen",
    "wof:name":"Erzschlag",
    "wof:placetype":"venue"
},
  "geometry": {"coordinates":[12.7104444504,50.5852546692],"type":"Point"}
}