{
  "type": "Feature",
  "properties": {
    "iso:country":"DE",
    "sg:address":"Widilostr. 2",
    "sg:city":"Hofheim",
    "sg:phone":"+49 6198/500726",
    "sg:postcode":"65719",
    "sg:province":"Hessen",
    "wof:name":"Hmc Handel Marketing Consult Gmbh",
    "wof:placetype":"venue"
},
  "geometry": {"coordinates":[8.3617630005,50.1185035706],"type":"Point"}
}