{
  "type": "Feature",
  "properties": {
    "iso:country":"DE",
    "sg:address":"Kilianstr. 65 A",
    "sg:city":"Paderborn",
    "sg:phone":"+49 5251/22540",
    "sg:postcode":"33098",
    "sg:province":"Nordrhein-Westfalen",
    "wof:name":"Adm Institut F\u00fcr Management- Und",
    "wof:placetype":"venue"
},
  "geometry": {"coordinates":[8.7564611435,51.7100448608],"type":"Point"}
}