{
  "type": "Feature",
  "properties": {
    "iso:country":"DE",
    "sg:address":"K\u00fcpperssteg 1",
    "sg:city":"Geldern",
    "sg:phone":"+49 2831/6071",
    "sg:postcode":"47608",
    "sg:province":"Nordrhein-Westfalen",
    "wof:name":"Arians Ohg",
    "wof:placetype":"venue"
},
  "geometry": {"coordinates":[6.2438597679,51.496761322],"type":"Point"}
}