{
  "type": "Feature",
  "properties": {
    "iso:country":"DE",
    "sg:address":"Schlachthofstr. 4",
    "sg:city":"Schleusingen",
    "sg:phone":"+49 36841/48231",
    "sg:postcode":"98553",
    "sg:province":"Th\u00fcringen",
    "wof:name":"Lobal Ohg",
    "wof:placetype":"venue"
},
  "geometry": {"coordinates":[10.740739,50.507389],"type":"Point"}
}