{
  "type": "Feature",
  "properties": {
    "iso:country":"DE",
    "sg:address":"Ramskamp 41",
    "sg:city":"Elmshorn",
    "sg:phone":"+49 4121/73427",
    "sg:postcode":"25337",
    "sg:province":"Schleswig-Holstein",
    "wof:name":"H. Gerson",
    "wof:placetype":"venue"
},
  "geometry": {"coordinates":[9.6880102158,53.7422485352],"type":"Point"}
}