{
  "type": "Feature",
  "properties": {
    "iso:country":"DE",
    "sg:address":"Lebacher Str. 9",
    "sg:city":"Tholey",
    "sg:phone":"+49 6853/6330",
    "sg:postcode":"66636",
    "sg:province":"Saarland",
    "wof:name":"Alt Sotzweiler Inh. Willi Mandernach",
    "wof:placetype":"venue"
},
  "geometry": {"coordinates":[6.99669981,49.4628753662],"type":"Point"}
}