{
  "type": "Feature",
  "properties": {
    "iso:country":"DE",
    "sg:address":"K\u00f6nig-Wilhelm-Str. 36",
    "sg:city":"Ulm",
    "sg:phone":"+49 731/984690",
    "sg:postcode":"89073",
    "sg:province":"Baden-W\u00fcrttemberg",
    "wof:name":"Gerhard Gr\u00f6ner Architekt",
    "wof:placetype":"venue"
},
  "geometry": {"coordinates":[10.00026,48.405888],"type":"Point"}
}