{
  "type": "Feature",
  "properties": {
    "iso:country":"DE",
    "sg:address":"Weidenring 2 e",
    "sg:city":"Neu Wulmstorf",
    "sg:phone":"+49 40/7001058",
    "sg:postcode":"21629",
    "sg:province":"Niedersachsen",
    "wof:name":"Sat-technik-swirin In Neu Wulmstorf, Online-shop",
    "wof:placetype":"venue"
},
  "geometry": {"coordinates":[9.792125,53.46801],"type":"Point"}
}