{
  "type": "Feature",
  "properties": {
    "iso:country":"DE",
    "sg:address":"Hardweg 6",
    "sg:city":"Klettgau",
    "sg:phone":"+49 7742/92340",
    "sg:postcode":"79771",
    "sg:province":"Baden-W\u00fcrttemberg",
    "wof:name":"Sozialstation Klettgau-rheintal E. V.",
    "wof:placetype":"venue"
},
  "geometry": {"coordinates":[8.413584,47.627586],"type":"Point"}
}