{
  "type": "Feature",
  "properties": {
    "iso:country":"DE",
    "sg:address":"M\u00fchlenstr. 19b",
    "sg:city":"Koblenz",
    "sg:phone":"+49 261/24446",
    "sg:postcode":"56072",
    "sg:province":"Rheinland-Pfalz",
    "wof:name":"Theo Elben Architekt",
    "wof:placetype":"venue"
},
  "geometry": {"coordinates":[7.524899,50.370541],"type":"Point"}
}