{
  "type": "Feature",
  "properties": {
    "iso:country":"DE",
    "sg:address":"Finkenweg 2",
    "sg:city":"Schwaikheim",
    "sg:postcode":"71409",
    "sg:province":"Baden-W\u00fcrttemberg",
    "wof:name":"Weckerle Gmbh",
    "wof:placetype":"venue"
},
  "geometry": {"coordinates":[9.35819,48.871449],"type":"Point"}
}