{
  "type": "Feature",
  "properties": {
    "iso:country":"DE",
    "sg:address":"Wachtelgarten 4 a",
    "sg:city":"Lippstadt",
    "sg:phone":"+49 2941/5002",
    "sg:postcode":"59557",
    "sg:province":"Nordrhein-Westfalen",
    "wof:name":"K Und S Planbau Bautr\u00e4ger Gmbh",
    "wof:placetype":"venue"
},
  "geometry": {"coordinates":[8.330182,51.670326],"type":"Point"}
}