{
  "type": "Feature",
  "properties": {
    "iso:country":"DE",
    "sg:address":"W\u00f6rpeweg 29",
    "sg:city":"Tarmstedt",
    "sg:phone":"+49 4283/488",
    "sg:postcode":"27412",
    "sg:province":"Niedersachsen",
    "wof:name":"Erich Seifert",
    "wof:placetype":"venue"
},
  "geometry": {"coordinates":[9.0896091461,53.2219963074],"type":"Point"}
}