{
  "type": "Feature",
  "properties": {
    "iso:country":"DE",
    "sg:address":"Wingertsweg 8",
    "sg:city":"Linsengericht",
    "sg:phone":"+49 6051/71688",
    "sg:postcode":"63589",
    "sg:province":"Hessen",
    "wof:name":"Folker Staedel",
    "wof:placetype":"venue"
},
  "geometry": {"coordinates":[9.2395715714,50.1829414368],"type":"Point"}
}