{
  "type": "Feature",
  "properties": {
    "iso:country":"DE",
    "sg:address":"Nienburger Damm 6",
    "sg:city":"Nienburg",
    "sg:phone":"+49 5021/62605",
    "sg:postcode":"31582",
    "sg:province":"Niedersachsen",
    "wof:name":"Heino Germann Gmbh",
    "wof:placetype":"venue"
},
  "geometry": {"coordinates":[9.239147,52.623131],"type":"Point"}
}