{
  "type": "Feature",
  "properties": {
    "iso:country":"DE",
    "sg:address":"Bismarckstr. 22",
    "sg:city":"M\u00f6nchengladbach",
    "sg:phone":"+49 2161/20274",
    "sg:postcode":"41061",
    "sg:province":"Nordrhein-Westfalen",
    "wof:name":"Hall Tabakwaren E. K.",
    "wof:placetype":"venue"
},
  "geometry": {"coordinates":[6.4427819252,51.1956367493],"type":"Point"}
}