{
  "type": "Feature",
  "properties": {
    "iso:country":"DE",
    "sg:address":"Windthorststr. 1/2",
    "sg:city":"Oschersleben",
    "sg:postcode":"39387",
    "sg:province":"Sachsen-Anhalt",
    "wof:name":"Eab Elektro Anlagenbau Elgos Oschersleben Gmbh",
    "wof:placetype":"venue"
},
  "geometry": {"coordinates":[11.22444,52.031548],"type":"Point"}
}