{
  "type": "Feature",
  "properties": {
    "iso:country":"DE",
    "sg:address":"Erikastr. 18",
    "sg:city":"Baldham",
    "sg:phone":"+49 8106/6244",
    "sg:postcode":"85598",
    "sg:province":"Bayern",
    "wof:name":"Norbert Kobsa Architekt",
    "wof:placetype":"venue"
},
  "geometry": {"coordinates":[11.805101,48.098194],"type":"Point"}
}