{
  "type": "Feature",
  "properties": {
    "iso:country":"DE",
    "sg:address":"Auf der D\u00f6nche 19",
    "sg:city":"Kassel",
    "sg:phone":"+49 561/408145",
    "sg:postcode":"34132",
    "sg:province":"Hessen",
    "wof:name":"Restaurant Zur Sonnenblume",
    "wof:placetype":"venue"
},
  "geometry": {"coordinates":[9.4312229156,51.2858963013],"type":"Point"}
}