{
  "type": "Feature",
  "properties": {
    "iso:country":"DE",
    "sg:address":"Kirchstr. 4",
    "sg:city":"Gehrden",
    "sg:phone":"+49 5137/2366",
    "sg:postcode":"30989",
    "sg:province":"Niedersachsen",
    "wof:name":"Ev. Luth. Pfarramt Gem. Lenthe Nord",
    "wof:placetype":"venue"
},
  "geometry": {"coordinates":[9.6012678146,52.3133049011],"type":"Point"}
}