{
  "type": "Feature",
  "properties": {
    "iso:country":"DE",
    "sg:address":"Hauptstr. 28",
    "sg:city":"Kenzingen",
    "sg:phone":"+49 7644/91080",
    "sg:postcode":"79341",
    "sg:province":"Baden-W\u00fcrttemberg",
    "wof:name":"Ruder Dtp & Sprachen Gmbh",
    "wof:placetype":"venue"
},
  "geometry": {"coordinates":[7.768522,48.191788],"type":"Point"}
}