{
  "type": "Feature",
  "properties": {
    "iso:country":"DE",
    "sg:address":"Wendelinusstr. 9a",
    "sg:city":"Koblenz",
    "sg:phone":"+49 261/72641",
    "sg:postcode":"56076",
    "sg:province":"Rheinland-Pfalz",
    "wof:name":"Rich. Schiedel Ingenieur",
    "wof:placetype":"venue"
},
  "geometry": {"coordinates":[7.6052541733,50.3472633362],"type":"Point"}
}