{
  "type": "Feature",
  "properties": {
    "iso:country":"DE",
    "sg:address":"Dorfstr. 24",
    "sg:city":"K\u00f6nigheim",
    "sg:phone":"+49 9340/262",
    "sg:postcode":"97953",
    "sg:province":"Baden-W\u00fcrttemberg",
    "wof:name":"Erhard Scherer",
    "wof:placetype":"venue"
},
  "geometry": {"coordinates":[9.526219,49.580864],"type":"Point"}
}