{
  "type": "Feature",
  "properties": {
    "iso:country":"DE",
    "sg:address":"Malchiner Str. 9",
    "sg:city":"Stavenhagen",
    "sg:phone":"+49 39954/21351",
    "sg:postcode":"17153",
    "sg:province":"Mecklenburg-Vorpommern",
    "wof:name":"Querfeldein Co Thomas Zahn",
    "wof:placetype":"venue"
},
  "geometry": {"coordinates":[12.9704303741,53.7102355957],"type":"Point"}
}