{
  "type": "Feature",
  "properties": {
    "iso:country":"DE",
    "sg:address":"Kaiserstr. 54",
    "sg:city":"Wadgassen",
    "sg:phone":"+49 6834/41630",
    "sg:postcode":"66787",
    "sg:province":"Saarland",
    "wof:name":"Pizzeria Roma Express",
    "wof:placetype":"venue"
},
  "geometry": {"coordinates":[6.8240790367,49.2634124756],"type":"Point"}
}