{
  "type": "Feature",
  "properties": {
    "iso:country":"DE",
    "sg:address":"Boltentorstr. 25",
    "sg:city":"Emden",
    "sg:phone":"+49 4921/21762",
    "sg:postcode":"26721",
    "sg:province":"Niedersachsen",
    "wof:name":"Alex Stepiuk",
    "wof:placetype":"venue"
},
  "geometry": {"coordinates":[7.202329,53.371361],"type":"Point"}
}