{
  "type": "Feature",
  "properties": {
    "iso:country":"DE",
    "sg:address":"Heidestr 12",
    "sg:city":"Magdeburg",
    "sg:phone":"+49 391/624370",
    "sg:postcode":"39112",
    "sg:province":"Sachsen-Anhalt",
    "wof:name":"Wiede - Haustechnik",
    "wof:placetype":"venue"
},
  "geometry": {"coordinates":[11.602346,52.108547],"type":"Point"}
}