{
  "type": "Feature",
  "properties": {
    "iso:country":"DE",
    "sg:address":"Arp-Schnitger-Stieg 10-12",
    "sg:city":"Hamburg",
    "sg:phone":"+49 40/7459320",
    "sg:postcode":"21129",
    "sg:province":"Hamburg",
    "wof:name":"Apotheke In Neuenfelde Klaus Reiche",
    "wof:placetype":"venue"
},
  "geometry": {"coordinates":[9.81127,53.5168],"type":"Point"}
}