{
  "type": "Feature",
  "properties": {
    "iso:country":"DE",
    "sg:address":"Hunnenplatz 5",
    "sg:city":"Regensburg",
    "sg:phone":"+49 941/57235",
    "sg:postcode":"93047",
    "sg:province":"Bayern",
    "wof:name":"Gloria-gas",
    "wof:placetype":"venue"
},
  "geometry": {"coordinates":[12.1022987366,49.0199928284],"type":"Point"}
}