{
  "type": "Feature",
  "properties": {
    "iso:country":"DE",
    "sg:address":"Pfalzgrafenweiler Str. 29",
    "sg:city":"Pfalzgrafenweiler",
    "sg:phone":"+49 7445/2418",
    "sg:postcode":"72285",
    "sg:province":"Baden-W\u00fcrttemberg",
    "wof:name":"Friedrich Koch",
    "wof:placetype":"venue"
},
  "geometry": {"coordinates":[8.594543,48.535583],"type":"Point"}
}