{
  "type": "Feature",
  "properties": {
    "iso:country":"DE",
    "sg:address":"Grubenweg 19",
    "sg:city":"Lengede",
    "sg:phone":"+49 5344/5005",
    "sg:postcode":"38268",
    "sg:province":"Niedersachsen",
    "wof:name":"Peter Zauers Metallbau Gmbh",
    "wof:placetype":"venue"
},
  "geometry": {"coordinates":[10.324482,52.200619],"type":"Point"}
}