{
  "type": "Feature",
  "properties": {
    "iso:country":"DE",
    "sg:address":"Kaiserstr. 23",
    "sg:city":"Wadgassen",
    "sg:phone":"+49 6834/46506",
    "sg:postcode":"66787",
    "sg:province":"Saarland",
    "wof:name":"Joachim Sartorius",
    "wof:placetype":"venue"
},
  "geometry": {"coordinates":[6.8233699799,49.2630882263],"type":"Point"}
}