{
  "type": "Feature",
  "properties": {
    "iso:country":"DE",
    "sg:address":"Starkenburger Str. 16",
    "sg:city":"Raunheim",
    "sg:phone":"+49 6142/9429940",
    "sg:postcode":"65479",
    "sg:province":"Hessen",
    "wof:name":"Kauzner Und Draudt Rechtsanw\u00e4lte",
    "wof:placetype":"venue"
},
  "geometry": {"coordinates":[8.4509773254,50.0116348267],"type":"Point"}
}