{
  "type": "Feature",
  "properties": {
    "iso:country":"DE",
    "sg:address":"B\u00e4renbergweg 8",
    "sg:city":"G\u00f6ggingen",
    "sg:phone":"+49 7175/6561",
    "sg:postcode":"73571",
    "sg:province":"Baden-W\u00fcrttemberg",
    "wof:name":"S. Hanselmann",
    "wof:placetype":"venue"
},
  "geometry": {"coordinates":[9.882293,48.857761],"type":"Point"}
}