{
  "type": "Feature",
  "properties": {
    "iso:country":"DE",
    "sg:address":"Altewiekring 19 c",
    "sg:city":"Braunschweig",
    "sg:phone":"+49 531/71798",
    "sg:postcode":"38102",
    "sg:province":"Niedersachsen",
    "wof:name":"Martha Fauter",
    "wof:placetype":"venue"
},
  "geometry": {"coordinates":[10.5428209305,52.2625656128],"type":"Point"}
}