{
  "type": "Feature",
  "properties": {
    "iso:country":"DE",
    "sg:address":"Krefelder Str. 6",
    "sg:city":"Erkelenz",
    "sg:phone":"+49 2431/3063",
    "sg:postcode":"41812",
    "sg:province":"Nordrhein-Westfalen",
    "wof:name":"U. Schmaler",
    "wof:placetype":"venue"
},
  "geometry": {"coordinates":[6.317715168,51.0789489746],"type":"Point"}
}