{
  "type": "Feature",
  "properties": {
    "iso:country":"DE",
    "sg:address":"General-Woyna-Str. 1 a",
    "sg:city":"Berlin",
    "sg:phone":"+49 30/4122656",
    "sg:postcode":"13403",
    "sg:province":"Berlin",
    "wof:name":"Jakow Kerem",
    "wof:placetype":"venue"
},
  "geometry": {"coordinates":[13.315038681,52.5675849915],"type":"Point"}
}