{
  "type": "Feature",
  "properties": {
    "iso:country":"DE",
    "sg:address":"Auf Wei\u00dfmauer 4",
    "sg:city":"Gondorf",
    "sg:postcode":"54647",
    "sg:province":"Rheinland-Pfalz",
    "wof:name":"Adolf Beck",
    "wof:placetype":"venue"
},
  "geometry": {"coordinates":[6.6217708588,49.9688606262],"type":"Point"}
}