{
  "type": "Feature",
  "properties": {
    "iso:country":"DE",
    "sg:address":"Saarbr\u00fccker Str. 72",
    "sg:city":"Saarbr\u00fccken",
    "sg:phone":"+49 681/872134",
    "sg:postcode":"66130",
    "sg:province":"Saarland",
    "wof:name":"Kath. Pfarramt St. Marien",
    "wof:placetype":"venue"
},
  "geometry": {"coordinates":[7.0258040428,49.2074966431],"type":"Point"}
}