{
  "type": "Feature",
  "properties": {
    "iso:country":"DE",
    "sg:address":"Ringstr. 2",
    "sg:city":"Niesky",
    "sg:phone":"+49 3588/200548",
    "sg:postcode":"02906",
    "sg:province":"Sachsen",
    "wof:name":"Karl Irmer Rechtsanwalt",
    "wof:placetype":"venue"
},
  "geometry": {"coordinates":[14.8243312836,51.2912101746],"type":"Point"}
}