{
  "type": "Feature",
  "properties": {
    "iso:country":"DE",
    "sg:address":"Pezoldstr. 5",
    "sg:city":"G\u00f6\u00dfweinstein",
    "sg:phone":"+49 9242/98765",
    "sg:postcode":"91327",
    "sg:province":"Bayern",
    "wof:name":"Hotel Gasthof Stern Bernd Vogl",
    "wof:placetype":"venue"
},
  "geometry": {"coordinates":[11.3363294601,49.7694358826],"type":"Point"}
}