{
  "type": "Feature",
  "properties": {
    "iso:country":"DE",
    "sg:address":"Br\u00fcckhofstr. 3",
    "sg:city":"Frankfurt",
    "sg:phone":"+49 69/294414",
    "sg:postcode":"60311",
    "sg:province":"Hessen",
    "wof:name":"Otto Rolvien",
    "wof:placetype":"venue"
},
  "geometry": {"coordinates":[8.6888198853,50.1102714539],"type":"Point"}
}