{
  "type": "Feature",
  "properties": {
    "iso:country":"DE",
    "sg:address":"Burgstallerstr. 15",
    "sg:city":"Gmund",
    "sg:phone":"+49 8022/74642",
    "sg:postcode":"83703",
    "sg:province":"Bayern",
    "wof:name":"Dr. V. S\u00fcssmann Rechtsanwalt",
    "wof:placetype":"venue"
},
  "geometry": {"coordinates":[11.7384977341,47.7375488281],"type":"Point"}
}