{
  "type": "Feature",
  "properties": {
    "iso:country":"DE",
    "sg:address":"Boschstr. 15",
    "sg:city":"Hamburg",
    "sg:phone":"+49 40/8991774",
    "sg:postcode":"22761",
    "sg:province":"Hamburg",
    "wof:name":"Stadt-land Genossenschaft Eg",
    "wof:placetype":"venue"
},
  "geometry": {"coordinates":[9.914416,53.567101],"type":"Point"}
}