{
  "type": "Feature",
  "properties": {
    "iso:country":"DE",
    "sg:address":"Wermelskirchener Str. 27",
    "sg:city":"Remscheid",
    "sg:postcode":"42859",
    "sg:province":"Nordrhein-Westfalen",
    "wof:name":"Brawe Brand- Und Werkschutz Gmbh",
    "wof:placetype":"venue"
},
  "geometry": {"coordinates":[7.1975002289,51.1588401794],"type":"Point"}
}