{
  "type": "Feature",
  "properties": {
    "iso:country":"DE",
    "sg:address":"Havelplatz 3",
    "sg:city":"Hennigsdorf",
    "sg:phone":"+49 3302/810885",
    "sg:postcode":"16761",
    "sg:province":"Brandenburg",
    "wof:name":"Steakhouse Il Molino",
    "wof:placetype":"venue"
},
  "geometry": {"coordinates":[13.1999959946,52.6368713379],"type":"Point"}
}