{
  "type": "Feature",
  "properties": {
    "iso:country":"DE",
    "sg:address":"Anrather Str. 31",
    "sg:city":"Krefeld",
    "sg:phone":"+49 2151/303408",
    "sg:postcode":"47807",
    "sg:province":"Nordrhein-Westfalen",
    "wof:name":"Hermann Hannappel & Sohn",
    "wof:placetype":"venue"
},
  "geometry": {"coordinates":[6.586263,51.304245],"type":"Point"}
}