{
  "type": "Feature",
  "properties": {
    "iso:country":"DE",
    "sg:address":"Neugasse 16",
    "sg:city":"Butzbach",
    "sg:phone":"+49 6033/64969",
    "sg:postcode":"35510",
    "sg:province":"Hessen",
    "wof:name":"Pizza Sheriff",
    "wof:placetype":"venue"
},
  "geometry": {"coordinates":[8.6704044342,50.4342041016],"type":"Point"}
}