{
  "type": "Feature",
  "properties": {
    "iso:country":"DE",
    "sg:address":"Am Kielortplatz 132",
    "sg:city":"Norderstedt",
    "sg:postcode":"22850",
    "sg:province":"Schleswig-Holstein",
    "wof:name":"Aldi Gmbh & Co. Kg",
    "wof:placetype":"venue"
},
  "geometry": {"coordinates":[10.0104122162,53.6822509766],"type":"Point"}
}