{
  "type": "Feature",
  "properties": {
    "iso:country":"DE",
    "sg:address":"Patthorster Str. 115",
    "sg:city":"Steinhagen",
    "sg:phone":"+49 5204/3773",
    "sg:postcode":"33803",
    "sg:province":"Nordrhein-Westfalen",
    "wof:name":"Ulrich Beckmann Gmbh",
    "wof:placetype":"venue"
},
  "geometry": {"coordinates":[8.3731,52.009411],"type":"Point"}
}