{
  "type": "Feature",
  "properties": {
    "iso:country":"DE",
    "sg:address":"St.-Nepomuk-Str. 11",
    "sg:city":"Gerbrunn",
    "sg:phone":"+49 931/708001",
    "sg:postcode":"97218",
    "sg:province":"Bayern",
    "wof:name":"Katholisches Pfarramt St. Nikolaus",
    "wof:placetype":"venue"
},
  "geometry": {"coordinates":[9.9816522598,49.7779006958],"type":"Point"}
}