{
  "type": "Feature",
  "properties": {
    "iso:country":"DE",
    "sg:address":"Friesenheimer Weg 16",
    "sg:city":"Lahr",
    "sg:phone":"+49 7821/22101",
    "sg:postcode":"77933",
    "sg:province":"Baden-W\u00fcrttemberg",
    "wof:name":"Mondial Gmbh",
    "wof:placetype":"venue"
},
  "geometry": {"coordinates":[7.875977993,48.3483200073],"type":"Point"}
}