{
  "type": "Feature",
  "properties": {
    "iso:country":"DE",
    "sg:address":"Br\u00fcggerfelder Str. 8",
    "sg:city":"Gevelsberg",
    "sg:phone":"+49 2332/1570",
    "sg:postcode":"58285",
    "sg:province":"Nordrhein-Westfalen",
    "wof:name":"Burtex Chemie Gmbh",
    "wof:placetype":"venue"
},
  "geometry": {"coordinates":[7.340403,51.317589],"type":"Point"}
}