{
  "type": "Feature",
  "properties": {
    "iso:country":"DE",
    "sg:address":"Meister-Gerhard-Str. 10",
    "sg:city":"K\u00f6ln",
    "sg:phone":"+49 221/211610",
    "sg:postcode":"50674",
    "sg:province":"Nordrhein-Westfalen",
    "wof:name":"Italienische Beratungsstelle",
    "wof:placetype":"venue"
},
  "geometry": {"coordinates":[6.936449,50.929874],"type":"Point"}
}