{
  "type": "Feature",
  "properties": {
    "iso:country":"DE",
    "sg:address":"Hauptstr. 41",
    "sg:city":"Amtsberg",
    "sg:phone":"+49 3725/22774",
    "sg:postcode":"09439",
    "sg:province":"Sachsen",
    "wof:name":"Eckhard Arnold",
    "wof:placetype":"venue"
},
  "geometry": {"coordinates":[13.00916,50.734699],"type":"Point"}
}