{
  "type": "Feature",
  "properties": {
    "iso:country":"DE",
    "sg:address":"Gro\u00df-Ziethener Chaussee 126",
    "sg:city":"Berlin",
    "sg:phone":"+49 30/6634959",
    "sg:postcode":"12355",
    "sg:province":"Berlin",
    "wof:name":"Rufena Transport Und Handels Gmbh",
    "wof:placetype":"venue"
},
  "geometry": {"coordinates":[13.478346,52.410217],"type":"Point"}
}