{
  "type": "Feature",
  "properties": {
    "iso:country":"DE",
    "sg:address":"Am Schulhof 3",
    "sg:city":"Karlstadt",
    "sg:phone":"+49 9360/474",
    "sg:postcode":"97753",
    "sg:province":"Bayern",
    "wof:name":"Katholisches Pfarramt Erzengel Michael",
    "wof:placetype":"venue"
},
  "geometry": {"coordinates":[9.8499765396,49.9722442627],"type":"Point"}
}