{
  "type": "Feature",
  "properties": {
    "iso:country":"DE",
    "sg:address":"Mengelr\u00f6der Weg 78",
    "sg:city":"Heilbad Heiligenstadt",
    "sg:postcode":"37308",
    "sg:province":"Th\u00fcringen",
    "wof:name":"Fritz Elberg Gmbh",
    "wof:placetype":"venue"
},
  "geometry": {"coordinates":[10.1217699051,51.3842010498],"type":"Point"}
}