{
  "type": "Feature",
  "properties": {
    "iso:country":"DE",
    "sg:address":"Friedrich-Wilhelm-Str. 27",
    "sg:city":"W\u00e4chtersbach",
    "sg:phone":"+49 6053/3721",
    "sg:postcode":"63607",
    "sg:province":"Hessen",
    "wof:name":"Tannen-apotheke Inh. Ursula Cress",
    "wof:placetype":"venue"
},
  "geometry": {"coordinates":[9.28785,50.255066],"type":"Point"}
}