{
  "type": "Feature",
  "properties": {
    "iso:country":"DE",
    "sg:address":"Heinrich-Lersch-Str. 13",
    "sg:city":"Hilden",
    "sg:postcode":"40721",
    "sg:province":"Nordrhein-Westfalen",
    "wof:name":"Tfm F\u00fcgner Kunststoff Und Metallbau Fertigungs- Und",
    "wof:placetype":"venue"
},
  "geometry": {"coordinates":[6.923755,51.178242],"type":"Point"}
}