{
  "type": "Feature",
  "properties": {
    "iso:country":"DE",
    "sg:address":"Salinstr. 1",
    "sg:city":"Rosenheim",
    "sg:phone":"+49 8031/396677",
    "sg:postcode":"83022",
    "sg:province":"Bayern",
    "wof:name":"Restaurant Pastavino",
    "wof:placetype":"venue"
},
  "geometry": {"coordinates":[12.123339653,47.8529510498],"type":"Point"}
}