{
  "type": "Feature",
  "properties": {
    "iso:country":"DE",
    "sg:address":"Bergedorfer Str. 68",
    "sg:city":"Hamburg",
    "sg:postcode":"21033",
    "sg:province":"Hamburg",
    "wof:name":"M\u00f6ller Automobile Ag",
    "wof:placetype":"venue"
},
  "geometry": {"coordinates":[10.1795597076,53.5073776245],"type":"Point"}
}