{
  "type": "Feature",
  "properties": {
    "iso:country":"DE",
    "sg:address":"Hauptstr.2",
    "sg:city":"Zaisenhausen",
    "sg:phone":"+49 7258",
    "sg:postcode":"75038",
    "sg:province":"Baden-W\u00fcrttemberg",
    "wof:name":"Straehle Galvanikbetrieb Zaisenhausen Bretten Internetforum",
    "wof:placetype":"venue"
},
  "geometry": {"coordinates":[-96.98327636720001,32.875038147],"type":"Point"}
}