{
  "type": "Feature",
  "properties": {
    "iso:country":"DE",
    "sg:address":"Buchbergstr 9",
    "sg:city":"Alzenau",
    "sg:phone":"+49 6023/999641",
    "sg:postcode":"63755",
    "sg:province":"Bayern",
    "wof:name":"Cuiod Tec Gmbh",
    "wof:placetype":"venue"
},
  "geometry": {"coordinates":[9.111771,50.116604],"type":"Point"}
}