{
  "type": "Feature",
  "properties": {
    "iso:country":"DE",
    "sg:address":"Saalburgallee 6",
    "sg:city":"Frankfurt",
    "sg:phone":"+49 69/94414406",
    "sg:postcode":"60385",
    "sg:province":"Hessen",
    "wof:name":"Honesta Unternehmensberatung Gmbh",
    "wof:placetype":"venue"
},
  "geometry": {"coordinates":[8.7106332779,50.1251373291],"type":"Point"}
}