{
  "type": "Feature",
  "properties": {
    "iso:country":"DE",
    "sg:address":"Th\u00f6rnicher Str. 20",
    "sg:city":"Detzem",
    "sg:phone":"+49 6507/3498",
    "sg:postcode":"54340",
    "sg:province":"Rheinland-Pfalz",
    "wof:name":"Franz-josef Liewen",
    "wof:placetype":"venue"
},
  "geometry": {"coordinates":[6.8429298401,49.825088501],"type":"Point"}
}