{
  "type": "Feature",
  "properties": {
    "iso:country":"DE",
    "sg:address":"Max-Eyth-Str. 14",
    "sg:city":"Illerrieden",
    "sg:phone":"+49 7306/7820",
    "sg:postcode":"89186",
    "sg:province":"Baden-W\u00fcrttemberg",
    "wof:name":"Kvt Koenig Verbindungstechnik Gmbh",
    "wof:placetype":"venue"
},
  "geometry": {"coordinates":[10.0564203262,48.2737388611],"type":"Point"}
}