{
  "type": "Feature",
  "properties": {
    "iso:country":"DE",
    "sg:address":"Filsstr. 8",
    "sg:city":"Asperg",
    "sg:phone":"+49 7141/681770",
    "sg:postcode":"71679",
    "sg:province":"Baden-W\u00fcrttemberg",
    "wof:name":"Zeisberger & Co",
    "wof:placetype":"venue"
},
  "geometry": {"coordinates":[9.1509933472,48.8990364075],"type":"Point"}
}