{
  "type": "Feature",
  "properties": {
    "iso:country":"DE",
    "sg:address":"Holzerweg 5",
    "sg:city":"Dortmund",
    "sg:phone":"+599 332332",
    "sg:postcode":"44287",
    "sg:province":"Nordrhein-Westfalen",
    "wof:name":"Webcomm - Internet Communities",
    "wof:placetype":"venue"
},
  "geometry": {"coordinates":[7.551908,51.505882],"type":"Point"}
}