{
  "type": "Feature",
  "properties": {
    "iso:country":"DE",
    "sg:address":"Stedingerstr. 42",
    "sg:city":"Stuttgart",
    "sg:phone":"+49 711/886040",
    "sg:postcode":"70499",
    "sg:province":"Baden-W\u00fcrttemberg",
    "wof:name":"M\u00fcrlepartner",
    "wof:placetype":"venue"
},
  "geometry": {"coordinates":[9.1179094315,48.8150444031],"type":"Point"}
}