{
  "type": "Feature",
  "properties": {
    "iso:country":"DE",
    "sg:address":"Falkenhagener Str. 40",
    "sg:city":"Falkensee",
    "sg:phone":"+49 3322/216394",
    "sg:postcode":"14612",
    "sg:province":"Brandenburg",
    "wof:name":"M\u00fcller Holz- Und Bautenschutz Gmbh",
    "wof:placetype":"venue"
},
  "geometry": {"coordinates":[13.097731,52.568352],"type":"Point"}
}