{
  "type": "Feature",
  "properties": {
    "iso:country":"DE",
    "sg:address":"Reutersgarten 4",
    "sg:city":"Lampertheim",
    "sg:phone":"+49 6206/2812",
    "sg:postcode":"68623",
    "sg:province":"Hessen",
    "wof:name":"Hans Gunkel Ingenieur",
    "wof:placetype":"venue"
},
  "geometry": {"coordinates":[8.4563617706,49.5928192139],"type":"Point"}
}