{
  "type": "Feature",
  "properties": {
    "iso:country":"DE",
    "sg:address":"Hauptstr. 47",
    "sg:city":"Gehlberg",
    "sg:phone":"+49 36845/50207",
    "sg:postcode":"98559",
    "sg:province":"Th\u00fcringen",
    "wof:name":"Zur Linde",
    "wof:placetype":"venue"
},
  "geometry": {"coordinates":[10.7908821106,50.67786026],"type":"Point"}
}