{
  "type": "Feature",
  "properties": {
    "iso:country":"DE",
    "sg:address":"Postfach 2252",
    "sg:city":"Nettetal",
    "sg:phone":"+49 2153/6887",
    "sg:postcode":"41309",
    "sg:province":"Nordrhein-Westfalen",
    "wof:name":"Mfb Gmbh",
    "wof:placetype":"venue"
},
  "geometry": {"coordinates":[6.275780201,51.3081283569],"type":"Point"}
}