{
  "type": "Feature",
  "properties": {
    "iso:country":"DE",
    "sg:address":"Alte Salzstr. 3",
    "sg:city":"Hamm",
    "sg:phone":"+49 2385/8711",
    "sg:postcode":"59069",
    "sg:province":"Nordrhein-Westfalen",
    "wof:name":"Imatex Import Und Export Handels Gmbh",
    "wof:placetype":"venue"
},
  "geometry": {"coordinates":[7.855565,51.630459],"type":"Point"}
}