{
  "type": "Feature",
  "properties": {
    "iso:country":"DE",
    "sg:address":"Hohe Str. 1",
    "sg:city":"Itzehoe",
    "sg:phone":"+49 4821/62424",
    "sg:postcode":"25524",
    "sg:province":"Schleswig-Holstein",
    "wof:name":"G. Krause Ingenieur",
    "wof:placetype":"venue"
},
  "geometry": {"coordinates":[9.5205831528,53.9228096008],"type":"Point"}
}