{
  "type": "Feature",
  "properties": {
    "iso:country":"DE",
    "sg:address":"Steppach 24",
    "sg:city":"Pommersfelden",
    "sg:phone":"+49 9548/265",
    "sg:postcode":"96178",
    "sg:province":"Bayern",
    "wof:name":"G. Holler",
    "wof:placetype":"venue"
},
  "geometry": {"coordinates":[10.80244,49.77335],"type":"Point"}
}