{
  "type": "Feature",
  "properties": {
    "iso:country":"DE",
    "sg:address":"Esbachgraben 11",
    "sg:city":"Bindlach",
    "sg:phone":"+49 921/7857439",
    "sg:postcode":"95463",
    "sg:province":"Bayern",
    "wof:name":"Wts Internationale Jumbo-transporte Gmbh",
    "wof:placetype":"venue"
},
  "geometry": {"coordinates":[11.6178693771,49.973400116],"type":"Point"}
}