{
  "type": "Feature",
  "properties": {
    "iso:country":"DE",
    "sg:address":"Schlieperstr. 80",
    "sg:city":"Berlin",
    "sg:phone":"+49 30/4338273",
    "sg:postcode":"13507",
    "sg:province":"Berlin",
    "wof:name":"Budde Eck",
    "wof:placetype":"venue"
},
  "geometry": {"coordinates":[13.288942337,52.5870246887],"type":"Point"}
}