{
  "type": "Feature",
  "properties": {
    "iso:country":"DE",
    "sg:address":"Auguste-Viktoria-Allee 67 a",
    "sg:city":"Berlin",
    "sg:phone":"+49 30/4126418",
    "sg:postcode":"13403",
    "sg:province":"Berlin",
    "wof:name":"Restaurant Zum Krug",
    "wof:placetype":"venue"
},
  "geometry": {"coordinates":[13.3157749176,52.5709609985],"type":"Point"}
}