{
  "type": "Feature",
  "properties": {
    "iso:country":"DE",
    "sg:address":"Dernburgstr. 4",
    "sg:city":"Berlin",
    "sg:postcode":"14057",
    "sg:province":"Berlin",
    "wof:name":"Gray Matter Gmbh",
    "wof:placetype":"venue"
},
  "geometry": {"coordinates":[13.289532,52.503109],"type":"Point"}
}