{
  "type": "Feature",
  "properties": {
    "iso:country":"DE",
    "sg:address":"Fliederweg 9",
    "sg:city":"Rheine",
    "sg:postcode":"48431",
    "sg:province":"Nordrhein-Westfalen",
    "wof:name":"Net@once Ohg",
    "wof:placetype":"venue"
},
  "geometry": {"coordinates":[7.417391777,52.2643547058],"type":"Point"}
}