{
  "type": "Feature",
  "properties": {
    "iso:country":"DE",
    "sg:address":"Professor-Stock-Str. 12",
    "sg:city":"Pfaffenhofen",
    "sg:phone":"+49 8441/2945",
    "sg:postcode":"85276",
    "sg:province":"Bayern",
    "wof:name":"Hildegard V\u00f6lker",
    "wof:placetype":"venue"
},
  "geometry": {"coordinates":[11.5123519897,48.5284767151],"type":"Point"}
}