{
  "type": "Feature",
  "properties": {
    "iso:country":"DE",
    "sg:address":"Staulinie 14-17",
    "sg:city":"Oldenburg",
    "sg:phone":"+49 441/92540371",
    "sg:postcode":"26122",
    "sg:province":"Niedersachsen",
    "wof:name":"Asw Aqua System Wassertechnik Gmbh",
    "wof:placetype":"venue"
},
  "geometry": {"coordinates":[8.21143,53.13868],"type":"Point"}
}