{
  "type": "Feature",
  "properties": {
    "iso:country":"DE",
    "sg:address":"Ubierstr. 1",
    "sg:city":"Br\u00fchl",
    "sg:phone":"+49 2232/25227",
    "sg:postcode":"50321",
    "sg:province":"Nordrhein-Westfalen",
    "wof:name":"Brunhilde Berg Masseurin",
    "wof:placetype":"venue"
},
  "geometry": {"coordinates":[6.893094,50.826469],"type":"Point"}
}