{
  "type": "Feature",
  "properties": {
    "iso:country":"DE",
    "sg:address":"Schlo\u00dfstr. 107",
    "sg:city":"Olching",
    "sg:phone":"+49 8142/12715",
    "sg:postcode":"82140",
    "sg:province":"Bayern",
    "wof:name":"Mathias Widmann",
    "wof:placetype":"venue"
},
  "geometry": {"coordinates":[11.315941,48.209702],"type":"Point"}
}