{
  "type": "Feature",
  "properties": {
    "iso:country":"DE",
    "sg:address":"An der Lausur 2",
    "sg:city":"Gro\u00dfsch\u00f6nau",
    "sg:phone":"+49 35841/35525",
    "sg:postcode":"02779",
    "sg:province":"Sachsen",
    "wof:name":"Ronald Bergmann",
    "wof:placetype":"venue"
},
  "geometry": {"coordinates":[14.6637592316,50.8958625793],"type":"Point"}
}