{
  "type": "Feature",
  "properties": {
    "iso:country":"DE",
    "sg:address":"Honsbacher Str. 12",
    "sg:city":"Lohmar",
    "sg:phone":"+49 2206/81154",
    "sg:postcode":"53797",
    "sg:province":"Nordrhein-Westfalen",
    "wof:name":"Honsbacher M\u00fchle Gastronomie- Und Veranstaltungs Gmbh",
    "wof:placetype":"venue"
},
  "geometry": {"coordinates":[7.2718682289,50.9022598267],"type":"Point"}
}