{
  "type": "Feature",
  "properties": {
    "iso:country":"DE",
    "sg:address":"Hauptstr. 16",
    "sg:city":"D\u00f6rentrup",
    "sg:phone":"+49 5265/8989",
    "sg:postcode":"32694",
    "sg:province":"Nordrhein-Westfalen",
    "wof:name":"Wilhelm Ellermeier Inh. W. Ellermeier",
    "wof:placetype":"venue"
},
  "geometry": {"coordinates":[9.0053100586,52.0341796875],"type":"Point"}
}