{
  "type": "Feature",
  "properties": {
    "iso:country":"DE",
    "sg:address":"L\u00f6wenstr. 4",
    "sg:city":"Lindenberg",
    "sg:phone":"+49 8381/2350",
    "sg:postcode":"88161",
    "sg:province":"Bayern",
    "wof:name":"Franz Ritter",
    "wof:placetype":"venue"
},
  "geometry": {"coordinates":[9.8875980377,47.6007804871],"type":"Point"}
}