{
  "type": "Feature",
  "properties": {
    "iso:country":"DE",
    "sg:address":"Wandsbeker Stieg 19",
    "sg:city":"Hamburg",
    "sg:phone":"+49 40/2502075",
    "sg:postcode":"22087",
    "sg:province":"Hamburg",
    "wof:name":"Tfh Handels- Gesellschaft Mbh",
    "wof:placetype":"venue"
},
  "geometry": {"coordinates":[10.0269460678,53.5606193542],"type":"Point"}
}