{
  "type": "Feature",
  "properties": {
    "iso:country":"DE",
    "sg:address":"Ernestinenstr. 4",
    "sg:city":"Lichtenstein",
    "sg:phone":"+49 37204/3668",
    "sg:postcode":"09350",
    "sg:province":"Sachsen",
    "wof:name":"Ullrich Michael Ingenieur",
    "wof:placetype":"venue"
},
  "geometry": {"coordinates":[12.6269979477,50.7634048462],"type":"Point"}
}