{
  "type": "Feature",
  "properties": {
    "iso:country":"DE",
    "sg:address":"Franzenstr. 3",
    "sg:city":"Witten",
    "sg:postcode":"58452",
    "sg:province":"Nordrhein-Westfalen",
    "wof:name":"Emil Boormann Eisenwaren",
    "wof:placetype":"venue"
},
  "geometry": {"coordinates":[7.3404688835,51.4327697754],"type":"Point"}
}