{
  "type": "Feature",
  "properties": {
    "iso:country":"DE",
    "sg:address":"Wintersberg",
    "sg:city":"Gr\u00f6mitz",
    "sg:phone":"+49 4366/501",
    "sg:postcode":"23743",
    "sg:province":"Schleswig-Holstein",
    "wof:name":"Gustav Schlapkohl",
    "wof:placetype":"venue"
},
  "geometry": {"coordinates":[11.000388,54.197857],"type":"Point"}
}