{
  "type": "Feature",
  "properties": {
    "iso:country":"DE",
    "sg:address":"Bahnhofstr. 9",
    "sg:city":"Andernach",
    "sg:phone":"+49 2632/949253",
    "sg:postcode":"56626",
    "sg:province":"Rheinland-Pfalz",
    "wof:name":"K\u00f6nig",
    "wof:placetype":"venue"
},
  "geometry": {"coordinates":[7.4004950523,50.4388008118],"type":"Point"}
}