{
  "type": "Feature",
  "properties": {
    "iso:country":"DE",
    "sg:address":"Langewanneweg 219",
    "sg:city":"Hamm",
    "sg:phone":"+49 2381/58080",
    "sg:postcode":"59069",
    "sg:province":"Nordrhein-Westfalen",
    "wof:name":"Kleine Gmbh & Co. Kg",
    "wof:placetype":"venue"
},
  "geometry": {"coordinates":[7.821152,51.655369],"type":"Point"}
}