{
  "type": "Feature",
  "properties": {
    "iso:country":"DE",
    "sg:address":"Baseler Str. 15",
    "sg:city":"Frankfurt",
    "sg:phone":"+49 69/253959",
    "sg:postcode":"60329",
    "sg:province":"Hessen",
    "wof:name":"Pizzeria Italia",
    "wof:placetype":"venue"
},
  "geometry": {"coordinates":[8.6643800735,50.1042022705],"type":"Point"}
}