{
  "type": "Feature",
  "properties": {
    "iso:country":"DE",
    "sg:address":"B\u00f6rsenstr. 117",
    "sg:city":"Solingen",
    "sg:phone":"+49 212/809996",
    "sg:postcode":"42657",
    "sg:province":"Nordrhein-Westfalen",
    "wof:name":"Widderter Schmette",
    "wof:placetype":"venue"
},
  "geometry": {"coordinates":[7.0697932243,51.1399116516],"type":"Point"}
}