{
  "type": "Feature",
  "properties": {
    "iso:country":"DE",
    "sg:address":"Am Bahnhof",
    "sg:city":"Burgkunstadt",
    "sg:phone":"+49 9572/1410",
    "sg:postcode":"96224",
    "sg:province":"Bayern",
    "wof:name":"Deutsche Bahn Ag",
    "wof:placetype":"venue"
},
  "geometry": {"coordinates":[11.2434415817,50.1377258301],"type":"Point"}
}