{
  "type": "Feature",
  "properties": {
    "iso:country":"DE",
    "sg:address":"Bardenberger Str. 46",
    "sg:city":"W\u00fcrselen",
    "sg:phone":"+49 2405/82562",
    "sg:postcode":"52146",
    "sg:province":"Nordrhein-Westfalen",
    "wof:name":"Friedrich Gruissem",
    "wof:placetype":"venue"
},
  "geometry": {"coordinates":[6.121556,50.833862],"type":"Point"}
}