{
  "type": "Feature",
  "properties": {
    "iso:country":"DE",
    "sg:address":"Wirmerstr. 33",
    "sg:city":"Bochum",
    "sg:phone":"+49 234/350120",
    "sg:postcode":"44803",
    "sg:province":"Nordrhein-Westfalen",
    "wof:name":"K. H. Abshoff Architekt",
    "wof:placetype":"venue"
},
  "geometry": {"coordinates":[7.243456,51.479691],"type":"Point"}
}