{
  "type": "Feature",
  "properties": {
    "iso:country":"DE",
    "sg:address":"Hauptstr. 3",
    "sg:city":"Laubsdorf",
    "sg:phone":"+49 35605/384",
    "sg:postcode":"03058",
    "sg:province":"Brandenburg",
    "wof:name":"Erika Kr\u00fcger",
    "wof:placetype":"venue"
},
  "geometry": {"coordinates":[14.428969,51.68594],"type":"Point"}
}