{
  "type": "Feature",
  "properties": {
    "iso:country":"DE",
    "sg:address":"Ostendorf 60",
    "sg:city":"Horstmar",
    "sg:postcode":"48612",
    "sg:province":"Nordrhein-Westfalen",
    "wof:name":"Windpark Sch\u00f6ppinger Berg Verwaltungsgesellschaft Mbh",
    "wof:placetype":"venue"
},
  "geometry": {"coordinates":[7.3014240265,52.1097335815],"type":"Point"}
}