{
  "type": "Feature",
  "properties": {
    "iso:country":"DE",
    "sg:address":"Flensburger Str. 166",
    "sg:city":"Schleswig",
    "sg:phone":"+49 4621/25044",
    "sg:postcode":"24837",
    "sg:province":"Schleswig-Holstein",
    "wof:name":"Flemming Dental Gmbh & Co. Kg",
    "wof:placetype":"venue"
},
  "geometry": {"coordinates":[9.5319929123,54.5291671753],"type":"Point"}
}