{
  "type": "Feature",
  "properties": {
    "iso:country":"DE",
    "sg:address":"Schulstr. 8",
    "sg:city":"Rheda-Wiedenbr\u00fcck",
    "sg:phone":"+49 5242/377410",
    "sg:postcode":"33378",
    "sg:province":"Nordrhein-Westfalen",
    "wof:name":"Reinhard Schnettler",
    "wof:placetype":"venue"
},
  "geometry": {"coordinates":[8.3038959503,51.8313064575],"type":"Point"}
}