{
  "type": "Feature",
  "properties": {
    "iso:country":"DE",
    "sg:address":"Riedstr. 3/2",
    "sg:city":"Ludwigsburg",
    "sg:postcode":"71634",
    "sg:province":"Baden-W\u00fcrttemberg",
    "wof:name":"Center Tools Software Gmbh",
    "wof:placetype":"venue"
},
  "geometry": {"coordinates":[9.1664638519,48.9075202942],"type":"Point"}
}