{
  "type": "Feature",
  "properties": {
    "iso:country":"DE",
    "sg:address":"Esteweg",
    "sg:city":"Hollenstedt",
    "sg:phone":"+49 4165/21430",
    "sg:postcode":"21279",
    "sg:province":"Niedersachsen",
    "wof:name":"Autobahnrastst\u00e4tte Hollenstedt Nord",
    "wof:placetype":"venue"
},
  "geometry": {"coordinates":[9.7142753601,53.3860588074],"type":"Point"}
}