{
  "type": "Feature",
  "properties": {
    "iso:country":"DE",
    "sg:address":"Residenzplatz 1",
    "sg:city":"Passau",
    "sg:phone":"+49 851/2927",
    "sg:postcode":"94032",
    "sg:province":"Bayern",
    "wof:name":"Altstadtgrill",
    "wof:placetype":"venue"
},
  "geometry": {"coordinates":[13.467622757,48.5742607117],"type":"Point"}
}