{
  "type": "Feature",
  "properties": {
    "iso:country":"DE",
    "sg:address":"M\u00f6nchstr. 24",
    "sg:city":"Marsberg",
    "sg:phone":"+49 2992/65000",
    "sg:postcode":"34431",
    "sg:province":"Nordrhein-Westfalen",
    "wof:name":"Tegethoff Inh. K. Dornow",
    "wof:placetype":"venue"
},
  "geometry": {"coordinates":[8.856302,51.465992],"type":"Point"}
}