{
  "type": "Feature",
  "properties": {
    "iso:country":"DE",
    "sg:address":"Am Ostenberg 7",
    "sg:city":"Stemwede",
    "sg:phone":"+49 5773/496",
    "sg:postcode":"32351",
    "sg:province":"Nordrhein-Westfalen",
    "wof:name":"H. H\u00f6gemeier",
    "wof:placetype":"venue"
},
  "geometry": {"coordinates":[8.480239,52.453709],"type":"Point"}
}