{
  "type": "Feature",
  "properties": {
    "iso:country":"DE",
    "sg:address":"An den Nahewiesen 5",
    "sg:city":"Langenlonsheim",
    "sg:phone":"+49 6704/93300",
    "sg:postcode":"55450",
    "sg:province":"Rheinland-Pfalz",
    "wof:name":"Novocork Korken- Vertriebsgesellschaft Mbh",
    "wof:placetype":"venue"
},
  "geometry": {"coordinates":[7.9016480446,49.9019470215],"type":"Point"}
}