{
  "type": "Feature",
  "properties": {
    "iso:country":"DE",
    "sg:address":"Buchenweg 8",
    "sg:city":"Ellerau",
    "sg:phone":"+49 4106/71514",
    "sg:postcode":"25479",
    "sg:province":"Schleswig-Holstein",
    "wof:name":"Anselm K\u00fchnel Heilpraktiker",
    "wof:placetype":"venue"
},
  "geometry": {"coordinates":[9.9392623901,53.7591323853],"type":"Point"}
}