{
  "type": "Feature",
  "properties": {
    "iso:country":"DE",
    "sg:address":"Am Schwimmbad",
    "sg:city":"Bad Neuenahr-Ahrweiler",
    "sg:phone":"+49 2641/34718",
    "sg:postcode":"53474",
    "sg:province":"Rheinland-Pfalz",
    "wof:name":"Freibad Ahrweiler",
    "wof:placetype":"venue"
},
  "geometry": {"coordinates":[7.1006741524,50.5378608704],"type":"Point"}
}