{
  "type": "Feature",
  "properties": {
    "iso:country":"DE",
    "sg:address":"Auf dem Bohnenkamp 95",
    "sg:city":"Bremen",
    "sg:phone":"+49 421/529472",
    "sg:postcode":"28197",
    "sg:province":"Bremen",
    "wof:name":"Kramer Beteiligungs- Gmbh",
    "wof:placetype":"venue"
},
  "geometry": {"coordinates":[8.762705,53.084393],"type":"Point"}
}