{
  "type": "Feature",
  "properties": {
    "iso:country":"DE",
    "sg:address":"Werniger\u00f6der Str. 21",
    "sg:city":"Halberstadt",
    "sg:phone":"+49 3941/600051",
    "sg:postcode":"38820",
    "sg:province":"Sachsen-Anhalt",
    "wof:name":"Freckmann & Wessel Gmbh",
    "wof:placetype":"venue"
},
  "geometry": {"coordinates":[11.038646698,51.8902740479],"type":"Point"}
}