{
  "type": "Feature",
  "properties": {
    "iso:country":"DE",
    "sg:address":"Thomas-Mann-Str. 9",
    "sg:city":"Stuttgart",
    "sg:phone":"+49 711/855985",
    "sg:postcode":"70469",
    "sg:province":"Baden-W\u00fcrttemberg",
    "wof:name":"Karin Feldmer Masseur",
    "wof:placetype":"venue"
},
  "geometry": {"coordinates":[9.146548,48.80703],"type":"Point"}
}