{
  "type": "Feature",
  "properties": {
    "iso:country":"DE",
    "sg:address":"Dr.-Enders-Str.57a",
    "sg:city":"Hof",
    "sg:phone":"+49 9281/67488",
    "sg:postcode":"95030",
    "sg:province":"Bayern",
    "wof:name":"Rekkenze Brass",
    "wof:placetype":"venue"
},
  "geometry": {"coordinates":[11.8970947266,50.3207130432],"type":"Point"}
}