{
  "type": "Feature",
  "properties": {
    "iso:country":"DE",
    "sg:address":"Hauptstr. 57",
    "sg:city":"Oberkirch",
    "sg:phone":"+49 7802/4314",
    "sg:postcode":"77704",
    "sg:province":"Baden-W\u00fcrttemberg",
    "wof:name":"Greifen-apotheke",
    "wof:placetype":"venue"
},
  "geometry": {"coordinates":[8.078494,48.531082],"type":"Point"}
}