{
  "type": "Feature",
  "properties": {
    "iso:country":"DE",
    "sg:address":"Wolbecker Str. 4",
    "sg:city":"Telgte",
    "sg:phone":"+49 2504/5580",
    "sg:postcode":"48291",
    "sg:province":"Nordrhein-Westfalen",
    "wof:name":"In Form Damen Fitness-center",
    "wof:placetype":"venue"
},
  "geometry": {"coordinates":[7.7855629921,51.9805717468],"type":"Point"}
}