{
  "type": "Feature",
  "properties": {
    "iso:country":"DE",
    "sg:address":"Silvanerweg 8 a",
    "sg:city":"Konstanz",
    "sg:phone":"+49 7531/55802",
    "sg:postcode":"78464",
    "sg:province":"Baden-W\u00fcrttemberg",
    "wof:name":"Reiner Rembs",
    "wof:placetype":"venue"
},
  "geometry": {"coordinates":[9.1902103424,47.6773529053],"type":"Point"}
}