{
  "type": "Feature",
  "properties": {
    "iso:country":"DE",
    "sg:address":"Dorfstr. 2",
    "sg:city":"Wulfsen",
    "sg:phone":"+49 4173/8461",
    "sg:postcode":"21445",
    "sg:province":"Niedersachsen",
    "wof:name":"August Menke",
    "wof:placetype":"venue"
},
  "geometry": {"coordinates":[10.1472110748,53.3065032959],"type":"Point"}
}