{
  "type": "Feature",
  "properties": {
    "iso:country":"DE",
    "sg:address":"Kopernikusstr. 10",
    "sg:city":"Bad Oeynhausen",
    "sg:phone":"+49 5731/30620",
    "sg:postcode":"32549",
    "sg:province":"Nordrhein-Westfalen",
    "wof:name":"Ludger Ahling Finanzberater",
    "wof:placetype":"venue"
},
  "geometry": {"coordinates":[8.7864236832,52.2167739868],"type":"Point"}
}