{
  "type": "Feature",
  "properties": {
    "iso:country":"DE",
    "sg:address":"Am Weingartsgraben 43",
    "sg:city":"H\u00f6chstadt",
    "sg:phone":"+49 9193/63570",
    "sg:postcode":"91315",
    "sg:province":"Bayern",
    "wof:name":"Hans J\u00fcrgen Kahler Ingenieur",
    "wof:placetype":"venue"
},
  "geometry": {"coordinates":[10.8019895554,49.7157325745],"type":"Point"}
}