{
  "type": "Feature",
  "properties": {
    "iso:country":"DE",
    "sg:address":"Gr\u00fcner Weg 1",
    "sg:city":"Beverungen",
    "sg:phone":"+49 5273/9010",
    "sg:postcode":"37688",
    "sg:province":"Nordrhein-Westfalen",
    "wof:name":"Herlag Kinderwagenfabrik Gmbh",
    "wof:placetype":"venue"
},
  "geometry": {"coordinates":[9.376304,51.672592],"type":"Point"}
}