{
  "type": "Feature",
  "properties": {
    "iso:country":"DE",
    "sg:address":"Untere Dorfstr. 4",
    "sg:city":"Duingen",
    "sg:phone":"+49 5186/483",
    "sg:postcode":"31089",
    "sg:province":"Niedersachsen",
    "wof:name":"Renate Nehrig",
    "wof:placetype":"venue"
},
  "geometry": {"coordinates":[9.6514101028,51.9919548035],"type":"Point"}
}