{
  "type": "Feature",
  "properties": {
    "iso:country":"DE",
    "sg:address":"Geschwister-Scholl-Str. 4",
    "sg:city":"Bad Aibling",
    "sg:phone":"+49 8061/2616",
    "sg:postcode":"83043",
    "sg:province":"Bayern",
    "wof:name":"Dr.med. Wolfgang Kessler Arzt F\u00fcr Allgemeinmedizin",
    "wof:placetype":"venue"
},
  "geometry": {"coordinates":[12.0059900284,47.8588066101],"type":"Point"}
}