{
  "type": "Feature",
  "properties": {
    "iso:country":"DE",
    "sg:address":"Sch\u00f6nhauser Stra\u00dfe 33",
    "sg:city":"Berlin",
    "sg:phone":"+49 49030",
    "sg:postcode":"13158",
    "sg:province":"Berlin",
    "wof:name":"A.& R. Winkler - Scherengitter, Rolll\u00e4den Und Markisen - Ber",
    "wof:placetype":"venue"
},
  "geometry": {"coordinates":[13.3975543976,52.5932426453],"type":"Point"}
}