{
  "type": "Feature",
  "properties": {
    "iso:country":"DE",
    "sg:address":"Hauptstr. 25",
    "sg:city":"Mietingen",
    "sg:postcode":"88487",
    "sg:province":"Baden-W\u00fcrttemberg",
    "wof:name":"Werner Eble Beteiligungs Gmbh",
    "wof:placetype":"venue"
},
  "geometry": {"coordinates":[9.900123,48.182007],"type":"Point"}
}