{
  "type": "Feature",
  "properties": {
    "iso:country":"DE",
    "sg:address":"Marktplatz 7",
    "sg:city":"Bischofsheim",
    "sg:phone":"+49 9772/234",
    "sg:postcode":"97653",
    "sg:province":"Bayern",
    "wof:name":"Hieronymus L\u00f6hrlein",
    "wof:placetype":"venue"
},
  "geometry": {"coordinates":[10.0076503754,50.4009017944],"type":"Point"}
}