{
  "type": "Feature",
  "properties": {
    "iso:country":"DE",
    "sg:address":"August-Bebel-Str. 19",
    "sg:city":"Zwickau",
    "sg:phone":"+49 375/370140",
    "sg:postcode":"08058",
    "sg:province":"Sachsen",
    "wof:name":"A. Wolfram Immobilienmakler",
    "wof:placetype":"venue"
},
  "geometry": {"coordinates":[12.4858427048,50.7279777527],"type":"Point"}
}