{
  "type": "Feature",
  "properties": {
    "iso:country":"DE",
    "sg:address":"Richard-Wagner-Str. 4",
    "sg:city":"Waldmohr",
    "sg:phone":"+49 6373/893330",
    "sg:postcode":"66914",
    "sg:province":"Rheinland-Pfalz",
    "wof:name":"J\u00fcrgen Schmitt Steuerbevollm\u00e4chtigter",
    "wof:placetype":"venue"
},
  "geometry": {"coordinates":[7.3292012215,49.3904571533],"type":"Point"}
}