{
  "type": "Feature",
  "properties": {
    "iso:country":"DE",
    "sg:address":"Karlstr. 14",
    "sg:city":"Stendal",
    "sg:phone":"+49 3931/216284",
    "sg:postcode":"39576",
    "sg:province":"Sachsen-Anhalt",
    "wof:name":"Anita Konrad",
    "wof:placetype":"venue"
},
  "geometry": {"coordinates":[11.8618717194,52.602268219],"type":"Point"}
}