{
  "type": "Feature",
  "properties": {
    "iso:country":"DE",
    "sg:address":"Kirchenweg 24",
    "sg:city":"Wang",
    "sg:phone":"+49 8764/8446",
    "sg:postcode":"85368",
    "sg:province":"Bayern",
    "wof:name":"Flugschule Cumulus E. K. Inh. Robert Ramm",
    "wof:placetype":"venue"
},
  "geometry": {"coordinates":[11.869951,48.497341],"type":"Point"}
}