{
  "type": "Feature",
  "properties": {
    "iso:country":"DE",
    "sg:address":"Friedenstr. 38",
    "sg:city":"Kronberg",
    "sg:postcode":"61476",
    "sg:province":"Hessen",
    "wof:name":"Alvarez & Partner",
    "wof:placetype":"venue"
},
  "geometry": {"coordinates":[8.542851,50.179459],"type":"Point"}
}