{
  "type": "Feature",
  "properties": {
    "iso:country":"DE",
    "sg:address":"Bahnhofstr. 9",
    "sg:city":"Sottrum",
    "sg:phone":"+49 4264/435",
    "sg:postcode":"27367",
    "sg:province":"Niedersachsen",
    "wof:name":"Karl-heinz R\u00f6hl",
    "wof:placetype":"venue"
},
  "geometry": {"coordinates":[9.23801,53.113552],"type":"Point"}
}