{
  "type": "Feature",
  "properties": {
    "iso:country":"DE",
    "sg:address":"Leyenweg 3",
    "sg:city":"Neunkirchen-Seelscheid",
    "sg:phone":"+49 2247/1800",
    "sg:postcode":"53819",
    "sg:province":"Nordrhein-Westfalen",
    "wof:name":"Udo Hartmann",
    "wof:placetype":"venue"
},
  "geometry": {"coordinates":[7.3504281044,50.821231842],"type":"Point"}
}