{
  "type": "Feature",
  "properties": {
    "iso:country":"DE",
    "sg:address":"Alois-Burger-Str. 2",
    "sg:city":"Ichenhausen",
    "sg:phone":"+49 8223/776",
    "sg:postcode":"89335",
    "sg:province":"Bayern",
    "wof:name":"Josef Schaffer Bauschlosserei",
    "wof:placetype":"venue"
},
  "geometry": {"coordinates":[10.30967,48.38961],"type":"Point"}
}