{
  "type": "Feature",
  "properties": {
    "iso:country":"DE",
    "sg:address":"Geraer Str. 3",
    "sg:city":"Ronneburg",
    "sg:phone":"+49 36602/22230",
    "sg:postcode":"07580",
    "sg:province":"Th\u00fcringen",
    "wof:name":"F\u00fcrstenhof",
    "wof:placetype":"venue"
},
  "geometry": {"coordinates":[12.1796636581,50.8655014038],"type":"Point"}
}