{
  "type": "Feature",
  "properties": {
    "iso:country":"DE",
    "sg:address":"Z\u00e4hringer Str. 21",
    "sg:city":"Freiburg",
    "sg:phone":"+49 761/52637",
    "sg:postcode":"79108",
    "sg:province":"Baden-W\u00fcrttemberg",
    "wof:name":"Lothar Friedrich",
    "wof:placetype":"venue"
},
  "geometry": {"coordinates":[7.855325222,48.0144577026],"type":"Point"}
}