{
  "type": "Feature",
  "properties": {
    "iso:country":"DE",
    "sg:address":"Fasanenweg 7 D",
    "sg:city":"Kelsterbach",
    "sg:postcode":"65451",
    "sg:province":"Hessen",
    "wof:name":"Adler Cargo Handling Gmbh",
    "wof:placetype":"venue"
},
  "geometry": {"coordinates":[8.541021347,50.0497703552],"type":"Point"}
}