{
  "type": "Feature",
  "properties": {
    "iso:country":"DE",
    "sg:address":"Enzianweg 1",
    "sg:city":"Kempten",
    "sg:phone":"+49 831/83326",
    "sg:postcode":"87439",
    "sg:province":"Bayern",
    "wof:name":"Wilhelm F. Ceelen Rechtsanwalt",
    "wof:placetype":"venue"
},
  "geometry": {"coordinates":[10.2992925644,47.7211647034],"type":"Point"}
}