{
  "type": "Feature",
  "properties": {
    "iso:country":"DE",
    "sg:address":"Hansaring 28::",
    "sg:city":"K\u00f6ln",
    "sg:phone":"+49 4922/1132243",
    "sg:postcode":"50670",
    "sg:province":"Nordrhein-Westfalen",
    "wof:name":"Rova Gesellschaft F\u00dcr Finanzierungsvermittlung Und Aussenhandels Mbh",
    "wof:placetype":"venue"
},
  "geometry": {"coordinates":[6.945608,50.94622],"type":"Point"}
}