{
  "type": "Feature",
  "properties": {
    "iso:country":"DE",
    "sg:address":"Im Schafl\u00e4ger 30",
    "sg:city":"Viernheim",
    "sg:phone":"+49 6204/4226",
    "sg:postcode":"68519",
    "sg:province":"Hessen",
    "wof:name":"Dr. Klaus M\u00fcller Tierarzt",
    "wof:placetype":"venue"
},
  "geometry": {"coordinates":[8.5630931854,49.5471534729],"type":"Point"}
}