{
  "type": "Feature",
  "properties": {
    "iso:country":"DE",
    "sg:address":"Goethestr. 1 a",
    "sg:city":"Oberkotzau",
    "sg:phone":"+49 9286/96296",
    "sg:postcode":"95145",
    "sg:province":"Bayern",
    "wof:name":"Reinhard Gr\u00fcner",
    "wof:placetype":"venue"
},
  "geometry": {"coordinates":[11.9238519669,50.2641716003],"type":"Point"}
}