{
  "type": "Feature",
  "properties": {
    "iso:country":"DE",
    "sg:address":"Mittenzweistr. 7",
    "sg:city":"Zwickau",
    "sg:phone":"+49 375/281616",
    "sg:postcode":"08056",
    "sg:province":"Sachsen",
    "wof:name":"Olaf Beyersdorf",
    "wof:placetype":"venue"
},
  "geometry": {"coordinates":[12.4862346649,50.7129974365],"type":"Point"}
}