{
  "type": "Feature",
  "properties": {
    "iso:country":"DE",
    "sg:address":"Lehengraben 4",
    "sg:city":"Bindlach",
    "sg:phone":"+49 9208/8516",
    "sg:postcode":"95463",
    "sg:province":"Bayern",
    "wof:name":"Como M\u00f6belzentrum Gmbh & Co. Kg",
    "wof:placetype":"venue"
},
  "geometry": {"coordinates":[11.613023,49.9767],"type":"Point"}
}