{
  "type": "Feature",
  "properties": {
    "iso:country":"DE",
    "sg:address":"Am Spaltmannsfeld 15",
    "sg:city":"Wesel",
    "sg:phone":"+49 281/953388",
    "sg:postcode":"46485",
    "sg:province":"Nordrhein-Westfalen",
    "wof:name":"M. M\u00fcnnich",
    "wof:placetype":"venue"
},
  "geometry": {"coordinates":[6.646513,51.662197],"type":"Point"}
}