{
  "type": "Feature",
  "properties": {
    "iso:country":"DE",
    "sg:address":"Rul\u00e4nderstr. 2",
    "sg:city":"Schliengen",
    "sg:phone":"+49 7635/81160",
    "sg:postcode":"79418",
    "sg:province":"Baden-W\u00fcrttemberg",
    "wof:name":"Ritter & Schwald Baumaschinen Gmbh",
    "wof:placetype":"venue"
},
  "geometry": {"coordinates":[7.575438,47.762207],"type":"Point"}
}