{
  "type": "Feature",
  "properties": {
    "iso:country":"DE",
    "sg:address":"Taunusstr.",
    "sg:city":"Wiesbaden",
    "sg:postcode":"65193",
    "sg:province":"Hessen",
    "wof:name":"Bu-he Billiard Sportst\u00e4tten Betriebs-gmbh",
    "wof:placetype":"venue"
},
  "geometry": {"coordinates":[8.244205,50.08609],"type":"Point"}
}