{
  "type": "Feature",
  "properties": {
    "iso:country":"DE",
    "sg:address":"Alt Rensefeld 49",
    "sg:city":"Bad Schwartau",
    "sg:phone":"+49 451/2920001",
    "sg:postcode":"23611",
    "sg:province":"Schleswig-Holstein",
    "wof:name":"As Gmbh",
    "wof:placetype":"venue"
},
  "geometry": {"coordinates":[10.675174,53.920414],"type":"Point"}
}