{
  "type": "Feature",
  "properties": {
    "iso:country":"DE",
    "sg:address":"dorfstr.8",
    "sg:city":"K\u00f6ln",
    "sg:postcode":"50500",
    "sg:province":"Nordrhein-Westfalen",
    "wof:name":"Kessls Internetportal",
    "wof:placetype":"venue"
},
  "geometry": {"coordinates":[13.345984,53.759258],"type":"Point"}
}