{
  "type": "Feature",
  "properties": {
    "iso:country":"DE",
    "sg:address":"Steinlein 29",
    "sg:city":"W\u00fcrzburg",
    "sg:phone":"+49 931/2879161",
    "sg:postcode":"97078",
    "sg:province":"Bayern",
    "wof:name":"Wisco Computerservice E. Kfm.",
    "wof:placetype":"venue"
},
  "geometry": {"coordinates":[9.9554977417,49.8136863708],"type":"Point"}
}