{
  "type": "Feature",
  "properties": {
    "iso:country":"DE",
    "sg:address":"Alte Torkelbergstr. 12 a",
    "sg:city":"Konstanz",
    "sg:phone":"+49 7531/45972",
    "sg:postcode":"78465",
    "sg:province":"Baden-W\u00fcrttemberg",
    "wof:name":"Ernst Munz Bauschlosserei",
    "wof:placetype":"venue"
},
  "geometry": {"coordinates":[9.170132,47.711788],"type":"Point"}
}