{
  "type": "Feature",
  "properties": {
    "iso:country":"DE",
    "sg:address":"Hauptstr. 20",
    "sg:city":"Garmisch-Partenkirchen",
    "sg:phone":"+49 8821/55832",
    "sg:postcode":"82467",
    "sg:province":"Bayern",
    "wof:name":"Autoverleih Werdenfels Horst Josef Koschwanez",
    "wof:placetype":"venue"
},
  "geometry": {"coordinates":[11.1013479233,47.5003013611],"type":"Point"}
}