{
  "type": "Feature",
  "properties": {
    "iso:country":"DE",
    "sg:address":"Gartenstr.",
    "sg:city":"M\u00fclsen",
    "sg:phone":"+49 37601/3130",
    "sg:postcode":"08132",
    "sg:province":"Sachsen",
    "wof:name":"Hbm Hausbau Gmbh",
    "wof:placetype":"venue"
},
  "geometry": {"coordinates":[12.579784,50.736183],"type":"Point"}
}