{
  "type": "Feature",
  "properties": {
    "iso:country":"DE",
    "sg:address":"Unterdorfstr. 14",
    "sg:city":"K\u00f6ngen",
    "sg:phone":"+49 7024/866030",
    "sg:postcode":"73257",
    "sg:province":"Baden-W\u00fcrttemberg",
    "wof:name":"Handy Land G\u00fcz",
    "wof:placetype":"venue"
},
  "geometry": {"coordinates":[9.3633184433,48.6840858459],"type":"Point"}
}