{
  "type": "Feature",
  "properties": {
    "iso:country":"DE",
    "sg:address":"Marktplatz 5",
    "sg:city":"Neuerburg",
    "sg:phone":"+49 6564/2217",
    "sg:postcode":"54673",
    "sg:province":"Rheinland-Pfalz",
    "wof:name":"Gerd Weihrauch",
    "wof:placetype":"venue"
},
  "geometry": {"coordinates":[6.2945451736,50.010307312],"type":"Point"}
}