{
  "type": "Feature",
  "properties": {
    "iso:country":"DE",
    "sg:address":"Blumenstr. 38",
    "sg:city":"Offenbach",
    "sg:phone":"+49 69/83836000",
    "sg:postcode":"63069",
    "sg:province":"Hessen",
    "wof:name":"Holorib Deutschland Gmbh",
    "wof:placetype":"venue"
},
  "geometry": {"coordinates":[8.747054,50.09111],"type":"Point"}
}