{
  "type": "Feature",
  "properties": {
    "iso:country":"DE",
    "sg:address":"Dorotheenstr. 19",
    "sg:city":"M\u00fcnster",
    "sg:phone":"+49 251/64460",
    "sg:postcode":"48145",
    "sg:province":"Nordrhein-Westfalen",
    "wof:name":"G. Rahm Versicherungsvertreter",
    "wof:placetype":"venue"
},
  "geometry": {"coordinates":[7.6428871155,51.9576797485],"type":"Point"}
}