{
  "type": "Feature",
  "properties": {
    "iso:country":"DE",
    "sg:address":"Gau\u00dfstr 11",
    "sg:city":"Karlsfeld",
    "sg:phone":"+49 8131/59560",
    "sg:postcode":"85757",
    "sg:province":"Bayern",
    "wof:name":"Thorlabs Gmbh",
    "wof:placetype":"venue"
},
  "geometry": {"coordinates":[11.480924,48.222324],"type":"Point"}
}