{
  "type": "Feature",
  "properties": {
    "iso:country":"DE",
    "sg:address":"Semmelstr. 51",
    "sg:city":"W\u00fcrzburg",
    "sg:phone":"+49 931/57987",
    "sg:postcode":"97070",
    "sg:province":"Bayern",
    "wof:name":"T. Karg",
    "wof:placetype":"venue"
},
  "geometry": {"coordinates":[9.9376497269,49.7975692749],"type":"Point"}
}