{
  "type": "Feature",
  "properties": {
    "iso:country":"DE",
    "sg:address":"Hammerweg 104",
    "sg:city":"Weiden",
    "sg:phone":"+49 961/35124",
    "sg:postcode":"92637",
    "sg:province":"Bayern",
    "wof:name":"H. Stilp",
    "wof:placetype":"venue"
},
  "geometry": {"coordinates":[12.171007,49.694412],"type":"Point"}
}