{
  "type": "Feature",
  "properties": {
    "iso:country":"DE",
    "sg:address":"Otto-Nagel-Str. 1",
    "sg:city":"Bautzen",
    "sg:phone":"+49 3591/23116",
    "sg:postcode":"02625",
    "sg:province":"Sachsen",
    "wof:name":"Solarienfachhandel Johannes M\u00fcller",
    "wof:placetype":"venue"
},
  "geometry": {"coordinates":[14.44798,51.192661],"type":"Point"}
}