{
  "type": "Feature",
  "properties": {
    "iso:country":"DE",
    "sg:address":"An den M\u00e4rkten 1-5",
    "sg:city":"Rheinbach",
    "sg:phone":"+49 2226/800828",
    "sg:postcode":"53359",
    "sg:province":"Nordrhein-Westfalen",
    "wof:name":"Obi Bau- Und Heimwerkermarkt",
    "wof:placetype":"venue"
},
  "geometry": {"coordinates":[6.9635620117,50.6229667664],"type":"Point"}
}