{
  "type": "Feature",
  "properties": {
    "iso:country":"DE",
    "sg:address":"K\u00f6lner Str. 62",
    "sg:city":"Wermelskirchen",
    "sg:phone":"+49 2196/6160",
    "sg:postcode":"42929",
    "sg:province":"Nordrhein-Westfalen",
    "wof:name":"Eiscafe Venezia",
    "wof:placetype":"venue"
},
  "geometry": {"coordinates":[7.212813,51.138687],"type":"Point"}
}