{
  "type": "Feature",
  "properties": {
    "iso:country":"DE",
    "sg:address":"Magdeburger Str. 3",
    "sg:city":"Springe",
    "sg:phone":"+49 5041/4026",
    "sg:postcode":"31832",
    "sg:province":"Niedersachsen",
    "wof:name":"Brandt Und Brandt Rechtsanw\u00e4lte Und Notare",
    "wof:placetype":"venue"
},
  "geometry": {"coordinates":[9.5481624603,52.213470459],"type":"Point"}
}