{
  "type": "Feature",
  "properties": {
    "iso:country":"DE",
    "sg:address":"F\u00fcrstenberger Str. 21",
    "sg:city":"Eisenh\u00fcttenstadt",
    "sg:phone":"+49 3364/71038",
    "sg:postcode":"15890",
    "sg:province":"Brandenburg",
    "wof:name":"Treff 7",
    "wof:placetype":"venue"
},
  "geometry": {"coordinates":[14.6639623642,52.1424064636],"type":"Point"}
}