{
  "type": "Feature",
  "properties": {
    "iso:country":"DE",
    "sg:address":"Klingenberger Str 2",
    "sg:city":"Brackenheim",
    "sg:phone":"+49 7135/1760",
    "sg:postcode":"74336",
    "sg:province":"Baden-W\u00fcrttemberg",
    "wof:name":"Febra-kunststoffe Gmbh",
    "wof:placetype":"venue"
},
  "geometry": {"coordinates":[9.083669,49.091068],"type":"Point"}
}