{
  "type": "Feature",
  "properties": {
    "iso:country":"DE",
    "sg:address":"M\u00fcllerstr. 20",
    "sg:city":"Peiting",
    "sg:phone":"+49 8861/59031",
    "sg:postcode":"86971",
    "sg:province":"Bayern",
    "wof:name":"Welz Gmbh",
    "wof:placetype":"venue"
},
  "geometry": {"coordinates":[10.924498,47.798939],"type":"Point"}
}