{
  "type": "Feature",
  "properties": {
    "iso:country":"DE",
    "sg:address":"Wei\u00dfenburger Str. 40",
    "sg:city":"Landau",
    "sg:phone":"+49 6341/31538",
    "sg:postcode":"76829",
    "sg:province":"Rheinland-Pfalz",
    "wof:name":"Carl Meder Kg",
    "wof:placetype":"venue"
},
  "geometry": {"coordinates":[8.115316391,49.193561554],"type":"Point"}
}