{
  "type": "Feature",
  "properties": {
    "iso:country":"DE",
    "sg:address":"Heimbacher M\u00fchle",
    "sg:city":"M\u00f6mbris",
    "sg:phone":"+49 6029/1386",
    "sg:postcode":"63776",
    "sg:province":"Bayern",
    "wof:name":"Gottlieb Stadtm\u00fcller",
    "wof:placetype":"venue"
},
  "geometry": {"coordinates":[9.1563978195,50.0509681702],"type":"Point"}
}