{
  "type": "Feature",
  "properties": {
    "iso:country":"DE",
    "sg:address":"Pestalozzistr.",
    "sg:city":"Waldheim",
    "sg:phone":"+49 34327/92825",
    "sg:postcode":"04736",
    "sg:province":"Sachsen",
    "wof:name":"Kowa Handelsgenossenschaft D\u00f6beln Eg",
    "wof:placetype":"venue"
},
  "geometry": {"coordinates":[13.0098924637,51.0735588074],"type":"Point"}
}