{
  "type": "Feature",
  "properties": {
    "iso:country":"DE",
    "sg:address":"Darmst\u00e4dter Str. 11",
    "sg:city":"Dietzenbach",
    "sg:phone":"+49 6074/41742",
    "sg:postcode":"63128",
    "sg:province":"Hessen",
    "wof:name":"Heimatmuseum",
    "wof:placetype":"venue"
},
  "geometry": {"coordinates":[8.776962,50.009842],"type":"Point"}
}