{
  "type": "Feature",
  "properties": {
    "iso:country":"DE",
    "sg:address":"Mainstr. 17",
    "sg:city":"Bergrheinfeld",
    "sg:phone":"+49 9721/90201",
    "sg:postcode":"97493",
    "sg:province":"Bayern",
    "wof:name":"Karg Gmbh",
    "wof:placetype":"venue"
},
  "geometry": {"coordinates":[10.1832313538,50.0057945251],"type":"Point"}
}