{
  "type": "Feature",
  "properties": {
    "iso:country":"DE",
    "sg:address":"Kantstr. 4 / 1",
    "sg:city":"Frickenhausen",
    "sg:postcode":"72636",
    "sg:province":"Baden-W\u00fcrttemberg",
    "wof:name":"It-service Gmbh",
    "wof:placetype":"venue"
},
  "geometry": {"coordinates":[9.3497772217,48.5923080444],"type":"Point"}
}