{
  "type": "Feature",
  "properties": {
    "iso:country":"DE",
    "sg:address":"Blocksbergstr. 52",
    "sg:city":"Pirmasens",
    "sg:phone":"+49 6331/70647",
    "sg:postcode":"66955",
    "sg:province":"Rheinland-Pfalz",
    "wof:name":"Haag",
    "wof:placetype":"venue"
},
  "geometry": {"coordinates":[7.600459,49.192318],"type":"Point"}
}