{
  "type": "Feature",
  "properties": {
    "iso:country":"DE",
    "sg:address":"Werner-von-Siemens-Str. 16",
    "sg:city":"Gehrden",
    "sg:postcode":"30989",
    "sg:province":"Niedersachsen",
    "wof:name":"Bianca Richter",
    "wof:placetype":"venue"
},
  "geometry": {"coordinates":[9.61164,52.355541],"type":"Point"}
}