{
  "type": "Feature",
  "properties": {
    "iso:country":"DE",
    "sg:address":"Konsulstr. 60",
    "sg:city":"G\u00f6rlitz",
    "sg:phone":"+49 3581/313902",
    "sg:postcode":"02826",
    "sg:province":"Sachsen",
    "wof:name":"Stumm & Perez Gbr",
    "wof:placetype":"venue"
},
  "geometry": {"coordinates":[14.987794,51.149998],"type":"Point"}
}