{
  "type": "Feature",
  "properties": {
    "iso:country":"DE",
    "sg:address":"Cradefelder Str. 48",
    "sg:city":"Leipzig",
    "sg:phone":"+49 341/9217084",
    "sg:postcode":"04349",
    "sg:province":"Sachsen",
    "wof:name":"Otto Sommer Steuerbevollm\u00e4chtigter",
    "wof:placetype":"venue"
},
  "geometry": {"coordinates":[12.4645290375,51.3878326416],"type":"Point"}
}