{
  "type": "Feature",
  "properties": {
    "iso:country":"DE",
    "sg:address":"Frankfurter Str. 591",
    "sg:city":"K\u00f6ln",
    "sg:phone":"+49 2203/932163",
    "sg:postcode":"51145",
    "sg:province":"Nordrhein-Westfalen",
    "wof:name":"M. Schwarz",
    "wof:placetype":"venue"
},
  "geometry": {"coordinates":[7.0833501816,50.8721199036],"type":"Point"}
}