{
  "type": "Feature",
  "properties": {
    "iso:country":"DE",
    "sg:address":"Maybachstr. 2",
    "sg:city":"M\u00f6glingen",
    "sg:phone":"+49 7141/241301",
    "sg:postcode":"71696",
    "sg:province":"Baden-W\u00fcrttemberg",
    "wof:name":"Tengelmann-markt",
    "wof:placetype":"venue"
},
  "geometry": {"coordinates":[9.1413049698,48.8908081055],"type":"Point"}
}