{
  "type": "Feature",
  "properties": {
    "iso:country":"DE",
    "sg:address":"Am Tonschuppen 4",
    "sg:city":"Alfter",
    "sg:phone":"+49 228/6420080",
    "sg:postcode":"53347",
    "sg:province":"Nordrhein-Westfalen",
    "wof:name":"Koch Bau- Und M\u00f6bel- Schreinerei Gmbh",
    "wof:placetype":"venue"
},
  "geometry": {"coordinates":[7.020712,50.683895],"type":"Point"}
}