{
  "type": "Feature",
  "properties": {
    "iso:country":"DE",
    "sg:address":"Koksstr. 45",
    "sg:city":"Bochum",
    "sg:postcode":"44879",
    "sg:province":"Nordrhein-Westfalen",
    "wof:name":"Hydramech Gmbh",
    "wof:placetype":"venue"
},
  "geometry": {"coordinates":[7.169789,51.434216],"type":"Point"}
}