{
  "type": "Feature",
  "properties": {
    "iso:country":"DE",
    "sg:address":"Holzhauser Str. 35",
    "sg:city":"Stuttgart",
    "sg:phone":"+49 711/734190",
    "sg:postcode":"70563",
    "sg:province":"Baden-W\u00fcrttemberg",
    "wof:name":"Effinger Wohntextilien Gmbh",
    "wof:placetype":"venue"
},
  "geometry": {"coordinates":[9.1026601791,48.7351913452],"type":"Point"}
}