{
  "type": "Feature",
  "properties": {
    "iso:country":"DE",
    "sg:address":"Daimlerstr. 14",
    "sg:city":"Burbach",
    "sg:phone":"+49 2736/4120",
    "sg:postcode":"57299",
    "sg:province":"Nordrhein-Westfalen",
    "wof:name":"Rittal-schaltschrank- System-bau Gmbh",
    "wof:placetype":"venue"
},
  "geometry": {"coordinates":[8.097578,50.751465],"type":"Point"}
}