{
  "type": "Feature",
  "properties": {
    "iso:country":"DE",
    "sg:address":"Dorfstr. 20",
    "sg:city":"Pantelitz",
    "sg:phone":"+49 38321/235",
    "sg:postcode":"18442",
    "sg:province":"Mecklenburg-Vorpommern",
    "wof:name":"Rainer Herold",
    "wof:placetype":"venue"
},
  "geometry": {"coordinates":[12.982514,54.290539],"type":"Point"}
}