{
  "type": "Feature",
  "properties": {
    "iso:country":"DE",
    "sg:address":"Orffstr. 37-37b",
    "sg:city":"Neuwied",
    "sg:postcode":"56566",
    "sg:province":"Rheinland-Pfalz",
    "wof:name":"Lebenshilfe F\u00f6rderzentrum Neuwied-andernach Ggmbh",
    "wof:placetype":"venue"
},
  "geometry": {"coordinates":[7.5437340736,50.4302978516],"type":"Point"}
}