{
  "type": "Feature",
  "properties": {
    "iso:country":"DE",
    "sg:address":"Einsteinstr. 73a",
    "sg:city":"Neubrandenburg",
    "sg:phone":"+49 395/7072620",
    "sg:postcode":"17036",
    "sg:province":"Mecklenburg-Vorpommern",
    "wof:name":"Eiscafe Tina",
    "wof:placetype":"venue"
},
  "geometry": {"coordinates":[13.29952,53.55125],"type":"Point"}
}