{
  "type": "Feature",
  "properties": {
    "iso:country":"DE",
    "sg:address":"Untere M\u00fchlengasse 7",
    "sg:city":"Niederzissen",
    "sg:postcode":"56651",
    "sg:province":"Rheinland-Pfalz",
    "wof:name":"Internetshoping Internetshopping Onlineshopping",
    "wof:placetype":"venue"
},
  "geometry": {"coordinates":[7.218774,50.458717],"type":"Point"}
}