{
  "type": "Feature",
  "properties": {
    "iso:country":"DE",
    "sg:address":"Wriezener Str. 87",
    "sg:city":"Bad Freienwalde",
    "sg:phone":"+49 3344/31588",
    "sg:postcode":"16259",
    "sg:province":"Brandenburg",
    "wof:name":"J. Sobirey",
    "wof:placetype":"venue"
},
  "geometry": {"coordinates":[14.0390844345,52.7818412781],"type":"Point"}
}