{
  "type": "Feature",
  "properties": {
    "iso:country":"DE",
    "sg:address":"Weststr. 6f",
    "sg:city":"Brandis",
    "sg:phone":"+49 34292/74464",
    "sg:postcode":"04821",
    "sg:province":"Sachsen",
    "wof:name":"Angela Karrow",
    "wof:placetype":"venue"
},
  "geometry": {"coordinates":[12.60235,51.32959],"type":"Point"}
}