{
  "type": "Feature",
  "properties": {
    "iso:country":"DE",
    "sg:address":"Herderstr. 11",
    "sg:city":"Bremen",
    "sg:phone":"+49 421/78707",
    "sg:postcode":"28203",
    "sg:province":"Bremen",
    "wof:name":"Rhizom-modell Soziale \u00d6kologie E. V.",
    "wof:placetype":"venue"
},
  "geometry": {"coordinates":[8.8268032074,53.0756149292],"type":"Point"}
}