{
  "type": "Feature",
  "properties": {
    "iso:country":"DE",
    "sg:address":"Gablenzstr. 5",
    "sg:city":"Kiel",
    "sg:phone":"+49 431/665554",
    "sg:postcode":"24114",
    "sg:province":"Schleswig-Holstein",
    "wof:name":"In Sound Professional Music Equipment Gmbh",
    "wof:placetype":"venue"
},
  "geometry": {"coordinates":[10.1285028458,54.3111572266],"type":"Point"}
}