{
  "type": "Feature",
  "properties": {
    "iso:country":"DE",
    "sg:address":"Hauptstr. 1",
    "sg:city":"Waldkirch",
    "sg:phone":"+49 7681/22247",
    "sg:postcode":"79183",
    "sg:province":"Baden-W\u00fcrttemberg",
    "wof:name":"Entennest",
    "wof:placetype":"venue"
},
  "geometry": {"coordinates":[7.9705629349,48.1002502441],"type":"Point"}
}