{
  "type": "Feature",
  "properties": {
    "iso:country":"DE",
    "sg:address":"Worringer Str. 86",
    "sg:city":"D\u00fcsseldorf",
    "sg:phone":"+49 211/358487",
    "sg:postcode":"40211",
    "sg:province":"Nordrhein-Westfalen",
    "wof:name":"F. Tuxhorn",
    "wof:placetype":"venue"
},
  "geometry": {"coordinates":[6.7963671684,51.2249717712],"type":"Point"}
}