{
  "type": "Feature",
  "properties": {
    "iso:country":"DE",
    "sg:address":"Richthofenstr. 4a",
    "sg:city":"Germersheim",
    "sg:phone":"+49 7274/2418",
    "sg:postcode":"76726",
    "sg:province":"Rheinland-Pfalz",
    "wof:name":"Heinz Steiner Ingenieur",
    "wof:placetype":"venue"
},
  "geometry": {"coordinates":[8.3651323318,49.2187576294],"type":"Point"}
}