{
  "type": "Feature",
  "properties": {
    "iso:country":"DE",
    "sg:address":"Wertherberg 19",
    "sg:city":"Werther",
    "sg:phone":"+49 5203/7594",
    "sg:postcode":"33824",
    "sg:province":"Nordrhein-Westfalen",
    "wof:name":"Heinz Eschweiler Restaurator",
    "wof:placetype":"venue"
},
  "geometry": {"coordinates":[8.3978300095,52.0681152344],"type":"Point"}
}