{
  "type": "Feature",
  "properties": {
    "iso:country":"DE",
    "sg:address":"Bredenbeck 1",
    "sg:city":"Senden",
    "sg:postcode":"48308",
    "sg:province":"Nordrhein-Westfalen",
    "wof:name":"Josef Schulze M\u00f6nking Immobilien Verwaltungsges.",
    "wof:placetype":"venue"
},
  "geometry": {"coordinates":[7.4850621223,51.8803520203],"type":"Point"}
}