{
  "type": "Feature",
  "properties": {
    "iso:country":"DE",
    "sg:address":"Wengen 15",
    "sg:city":"Oberstaufen",
    "sg:phone":"+49 8386/961683",
    "sg:postcode":"87534",
    "sg:province":"Bayern",
    "wof:name":"S & L Schneider & Lingenhel Ohg",
    "wof:placetype":"venue"
},
  "geometry": {"coordinates":[10.045218,47.556034],"type":"Point"}
}