{
  "type": "Feature",
  "properties": {
    "iso:country":"DE",
    "sg:address":"Wilhelmstr. 25",
    "sg:city":"Winningen",
    "sg:phone":"+49 2606/200019",
    "sg:postcode":"56333",
    "sg:province":"Rheinland-Pfalz",
    "wof:name":"Friedhelm Hautt Weinanbau",
    "wof:placetype":"venue"
},
  "geometry": {"coordinates":[7.5152611732,50.3128395081],"type":"Point"}
}