{
  "type": "Feature",
  "properties": {
    "iso:country":"DE",
    "sg:address":"Heide 10",
    "sg:city":"Zerbst",
    "sg:phone":"+49 3923/2598",
    "sg:postcode":"39261",
    "sg:province":"Sachsen-Anhalt",
    "wof:name":"F. Lindig",
    "wof:placetype":"venue"
},
  "geometry": {"coordinates":[12.0880384445,51.9703216553],"type":"Point"}
}