{
  "type": "Feature",
  "properties": {
    "iso:country":"DE",
    "sg:address":"Hafendecke 4",
    "sg:city":"Selb",
    "sg:phone":"+49 9287/2308",
    "sg:postcode":"95100",
    "sg:province":"Bayern",
    "wof:name":"Zebalith-max Zeidelhack",
    "wof:placetype":"venue"
},
  "geometry": {"coordinates":[12.1485309601,50.1682128906],"type":"Point"}
}