{
  "type": "Feature",
  "properties": {
    "iso:country":"DE",
    "sg:address":"Seeweg 30a",
    "sg:city":"H\u00f6chberg",
    "sg:phone":"+49 931/400072",
    "sg:postcode":"97204",
    "sg:province":"Bayern",
    "wof:name":"Karin Schuler",
    "wof:placetype":"venue"
},
  "geometry": {"coordinates":[9.886619,49.787891],"type":"Point"}
}