{
  "type": "Feature",
  "properties": {
    "iso:country":"DE",
    "sg:address":"Kaiser-Friedrich-Str. 29",
    "sg:city":"Berlin",
    "sg:phone":"+49 30/3410399",
    "sg:postcode":"10585",
    "sg:province":"Berlin",
    "wof:name":"Tabakwaren-zeitschriften Ingrid Gluska",
    "wof:placetype":"venue"
},
  "geometry": {"coordinates":[13.3011455536,52.5118103027],"type":"Point"}
}