{
  "type": "Feature",
  "properties": {
    "iso:country":"DE",
    "sg:address":"\u00d6sterbergstr. 3",
    "sg:city":"T\u00fcbingen",
    "sg:postcode":"72074",
    "sg:province":"Baden-W\u00fcrttemberg",
    "wof:name":"Uni-anatomisches Institut",
    "wof:placetype":"venue"
},
  "geometry": {"coordinates":[9.0585803986,48.5208473206],"type":"Point"}
}