{
  "type": "Feature",
  "properties": {
    "iso:country":"DE",
    "sg:address":"Hauptstr. 13",
    "sg:city":"Erndtebr\u00fcck",
    "sg:phone":"+49 2753/4301",
    "sg:postcode":"57339",
    "sg:province":"Nordrhein-Westfalen",
    "wof:name":"G. Dreisbach",
    "wof:placetype":"venue"
},
  "geometry": {"coordinates":[8.300158,50.995968],"type":"Point"}
}