{
  "type": "Feature",
  "properties": {
    "iso:country":"DE",
    "sg:address":"Ortsstr. 4",
    "sg:city":"K\u00f6tz",
    "sg:phone":"+49 8221/5113",
    "sg:postcode":"89359",
    "sg:province":"Bayern",
    "wof:name":"Gastst\u00e4tte Karl Zwerger",
    "wof:placetype":"venue"
},
  "geometry": {"coordinates":[10.2742500305,48.4069824219],"type":"Point"}
}