{
  "type": "Feature",
  "properties": {
    "iso:country":"DE",
    "sg:address":"Triftstr. 9",
    "sg:city":"M\u00fcnchen",
    "sg:phone":"+49 89/221886",
    "sg:postcode":"80538",
    "sg:province":"Bayern",
    "wof:name":"M. N. Hack",
    "wof:placetype":"venue"
},
  "geometry": {"coordinates":[11.588507,48.140659],"type":"Point"}
}