{
  "type": "Feature",
  "properties": {
    "iso:country":"DE",
    "sg:address":"Pariser Str. 7",
    "sg:city":"M\u00fcnchen",
    "sg:phone":"+49 89/4485347",
    "sg:postcode":"81669",
    "sg:province":"Bayern",
    "wof:name":"M. Hartwig Architekt",
    "wof:placetype":"venue"
},
  "geometry": {"coordinates":[11.596587,48.126579],"type":"Point"}
}