{
  "type": "Feature",
  "properties": {
    "iso:country":"DE",
    "sg:address":"Damaschkestr. 55",
    "sg:city":"Erlangen",
    "sg:phone":"+49 9131/450501",
    "sg:postcode":"91056",
    "sg:province":"Bayern",
    "wof:name":"M. Und H. Kuschel Architekten",
    "wof:placetype":"venue"
},
  "geometry": {"coordinates":[10.979033,49.594006],"type":"Point"}
}