{
  "type": "Feature",
  "properties": {
    "iso:country":"DE",
    "sg:address":"Ohlm\u00fcllerstr. 16",
    "sg:city":"M\u00fcnchen",
    "sg:phone":"+49 89/653542",
    "sg:postcode":"81541",
    "sg:province":"Bayern",
    "wof:name":"Mariahilf-apotheke",
    "wof:placetype":"venue"
},
  "geometry": {"coordinates":[11.579781,48.125183],"type":"Point"}
}