{
  "type": "Feature",
  "properties": {
    "iso:country":"DE",
    "sg:address":"Am Alten Stadtbad 13",
    "sg:city":"Sch\u00f6nebeck",
    "sg:phone":"+49 3928/68272",
    "sg:postcode":"39218",
    "sg:province":"Sachsen-Anhalt",
    "wof:name":"Biging-motorger\u00e4te",
    "wof:placetype":"venue"
},
  "geometry": {"coordinates":[11.726249,52.002907],"type":"Point"}
}