{
  "type": "Feature",
  "properties": {
    "iso:country":"DE",
    "sg:address":"Kinzigstr. 59",
    "sg:city":"Kehl",
    "sg:phone":"+49 7851/73292",
    "sg:postcode":"77694",
    "sg:province":"Baden-W\u00fcrttemberg",
    "wof:name":"Thomas Brockhaus Architekt",
    "wof:placetype":"venue"
},
  "geometry": {"coordinates":[7.814239,48.573845],"type":"Point"}
}