{
  "type": "Feature",
  "properties": {
    "iso:country":"DE",
    "sg:address":"Reeser Landstr. 15",
    "sg:city":"Wesel",
    "sg:phone":"+49 281/22372",
    "sg:postcode":"46483",
    "sg:province":"Nordrhein-Westfalen",
    "wof:name":"Aral Ag",
    "wof:placetype":"venue"
},
  "geometry": {"coordinates":[6.609744072,51.6633224487],"type":"Point"}
}