{
  "type": "Feature",
  "properties": {
    "iso:country":"DE",
    "sg:address":"M\u00fchlenstr. 65",
    "sg:city":"Melle",
    "sg:phone":"+49 5422/2589",
    "sg:postcode":"49324",
    "sg:province":"Niedersachsen",
    "wof:name":"Gerhard Heller",
    "wof:placetype":"venue"
},
  "geometry": {"coordinates":[8.3421440125,52.2072486877],"type":"Point"}
}