{
  "type": "Feature",
  "properties": {
    "iso:country":"DE",
    "sg:address":"Janahof",
    "sg:city":"Cham",
    "sg:phone":"+49 9971/32886",
    "sg:postcode":"93413",
    "sg:province":"Bayern",
    "wof:name":"American Store",
    "wof:placetype":"venue"
},
  "geometry": {"coordinates":[12.66343,49.201729],"type":"Point"}
}