{
  "type": "Feature",
  "properties": {
    "iso:country":"DE",
    "sg:address":"Ziegelei",
    "sg:city":"Ohlweiler",
    "sg:phone":"+49 6761/3549",
    "sg:postcode":"55469",
    "sg:province":"Rheinland-Pfalz",
    "wof:name":"R. M\u00fchl & W. Didt",
    "wof:placetype":"venue"
},
  "geometry": {"coordinates":[7.4931049347,49.9704437256],"type":"Point"}
}