{
  "type": "Feature",
  "properties": {
    "iso:country":"DE",
    "sg:address":"Edisonstr. 2",
    "sg:city":"Viernheim",
    "sg:phone":"+49 6204/79245",
    "sg:postcode":"68519",
    "sg:province":"Hessen",
    "wof:name":"Walther Pradel",
    "wof:placetype":"venue"
},
  "geometry": {"coordinates":[8.59294,49.549526],"type":"Point"}
}