{
  "type": "Feature",
  "properties": {
    "iso:country":"DE",
    "sg:address":"Kapellenweg 6",
    "sg:city":"St. Peter",
    "sg:phone":"+49 7660/920162",
    "sg:postcode":"79271",
    "sg:province":"Baden-W\u00fcrttemberg",
    "wof:name":"Dr.med. W. Thies Arzt F\u00fcr Allgemeinmedizin",
    "wof:placetype":"venue"
},
  "geometry": {"coordinates":[8.0367765427,48.0185928345],"type":"Point"}
}