{
  "type": "Feature",
  "properties": {
    "iso:country":"DE",
    "sg:address":"Luckower Str. 1",
    "sg:city":"Eggesin",
    "sg:phone":"+49 39779/20344",
    "sg:postcode":"17367",
    "sg:province":"Mecklenburg-Vorpommern",
    "wof:name":"Ursula Wegner",
    "wof:placetype":"venue"
},
  "geometry": {"coordinates":[14.087558,53.688679],"type":"Point"}
}