{
  "type": "Feature",
  "properties": {
    "iso:country":"DE",
    "sg:address":"Sendnicher Str. 20",
    "sg:city":"Koblenz",
    "sg:phone":"+49 261/23884",
    "sg:postcode":"56072",
    "sg:province":"Rheinland-Pfalz",
    "wof:name":"Walter Schmitz",
    "wof:placetype":"venue"
},
  "geometry": {"coordinates":[7.515102,50.369358],"type":"Point"}
}