{
  "type": "Feature",
  "properties": {
    "iso:country":"DE",
    "sg:address":"Schindackerweg 1",
    "sg:city":"Hindelang",
    "sg:phone":"+49 8324/365",
    "sg:postcode":"87541",
    "sg:province":"Bayern",
    "wof:name":"Hotel-cafe Sonnenbichl",
    "wof:placetype":"venue"
},
  "geometry": {"coordinates":[10.376953125,47.5078010559],"type":"Point"}
}