{
  "type": "Feature",
  "properties": {
    "iso:country":"DE",
    "sg:address":"Schulstr. 23",
    "sg:city":"Bawinkel",
    "sg:phone":"+49 5963/339",
    "sg:postcode":"49844",
    "sg:province":"Niedersachsen",
    "wof:name":"Meemann Gmbh & Co.",
    "wof:placetype":"venue"
},
  "geometry": {"coordinates":[7.413758,52.599628],"type":"Point"}
}