{
  "type": "Feature",
  "properties": {
    "iso:country":"DE",
    "sg:address":"Basler Str. 59",
    "sg:city":"Freiburg",
    "sg:phone":"+49 7664/59936",
    "sg:postcode":"79100",
    "sg:province":"Baden-W\u00fcrttemberg",
    "wof:name":"Global-test Vertriebsges. Mbh",
    "wof:placetype":"venue"
},
  "geometry": {"coordinates":[7.8383970261,47.987071991],"type":"Point"}
}