{
  "type": "Feature",
  "properties": {
    "iso:country":"DE",
    "sg:address":"Betzenm\u00fchle 3",
    "sg:city":"Pl\u00f6\u00dfberg",
    "sg:phone":"+49 9636/92090",
    "sg:postcode":"95703",
    "sg:province":"Bayern",
    "wof:name":"Ludwig Ziegler Inh. Wilhelm Ziegler",
    "wof:placetype":"venue"
},
  "geometry": {"coordinates":[12.3266525269,49.8164024353],"type":"Point"}
}