{
  "type": "Feature",
  "properties": {
    "iso:country":"DE",
    "sg:address":"Bottroper Str. 44",
    "sg:city":"Bottrop",
    "sg:phone":"+49 2045/3596",
    "sg:postcode":"46244",
    "sg:province":"Nordrhein-Westfalen",
    "wof:name":"H. Schl\u00fcter",
    "wof:placetype":"venue"
},
  "geometry": {"coordinates":[6.9134640694,51.5882644653],"type":"Point"}
}