{
  "type": "Feature",
  "properties": {
    "iso:country":"DE",
    "sg:address":"Syldaer Weg 5",
    "sg:city":"Alterode",
    "sg:phone":"+49 34742/340",
    "sg:postcode":"06543",
    "sg:province":"Sachsen-Anhalt",
    "wof:name":"K. Ballhorn",
    "wof:placetype":"venue"
},
  "geometry": {"coordinates":[11.3874464035,51.6763114929],"type":"Point"}
}