{
  "type": "Feature",
  "properties": {
    "iso:country":"DE",
    "sg:address":"Deutz-M\u00fclheimer Str. 352",
    "sg:city":"K\u00f6ln",
    "sg:phone":"+49 221/614334",
    "sg:postcode":"51063",
    "sg:province":"Nordrhein-Westfalen",
    "wof:name":"Johann Pohl",
    "wof:placetype":"venue"
},
  "geometry": {"coordinates":[6.997812,50.962364],"type":"Point"}
}