{
  "type": "Feature",
  "properties": {
    "iso:country":"DE",
    "sg:address":"Von-Frerichs-Str. 24",
    "sg:city":"Aurich",
    "sg:phone":"+49 4941/5802",
    "sg:postcode":"26603",
    "sg:province":"Niedersachsen",
    "wof:name":"Joh. Vaillant Gmbh & Co.",
    "wof:placetype":"venue"
},
  "geometry": {"coordinates":[7.4881658554,53.4720039368],"type":"Point"}
}