{
  "type": "Feature",
  "properties": {
    "iso:country":"DE",
    "sg:address":"Kopstr.59",
    "sg:city":"Sankt Augustin",
    "sg:postcode":"53757",
    "sg:province":"Nordrhein-Westfalen",
    "wof:name":"South Park Clothing And Merchandise",
    "wof:placetype":"venue"
},
  "geometry": {"coordinates":[7.188175,50.776085],"type":"Point"}
}