{
  "type": "Feature",
  "properties": {
    "iso:country":"DE",
    "sg:address":"Brinkstr. 7",
    "sg:city":"Dielmissen",
    "sg:phone":"+49 5534/2850",
    "sg:postcode":"37633",
    "sg:province":"Niedersachsen",
    "wof:name":"August-wilhelm Wedekind",
    "wof:placetype":"venue"
},
  "geometry": {"coordinates":[9.61123,51.970333],"type":"Point"}
}