{
  "type": "Feature",
  "properties": {
    "iso:country":"DE",
    "sg:address":"Rubinger Str. 13",
    "sg:city":"Oberstdorf",
    "sg:phone":"+49 8322/3446",
    "sg:postcode":"87561",
    "sg:province":"Bayern",
    "wof:name":"G\u00e4stehaus Walter Benkler",
    "wof:placetype":"venue"
},
  "geometry": {"coordinates":[10.2764587402,47.4236831665],"type":"Point"}
}