{
  "type": "Feature",
  "properties": {
    "iso:country":"DE",
    "sg:address":"Meisenweg 19",
    "sg:city":"Dormagen",
    "sg:phone":"+49 2133/80943",
    "sg:postcode":"41540",
    "sg:province":"Nordrhein-Westfalen",
    "wof:name":"Klaus Becker Ingenieur",
    "wof:placetype":"venue"
},
  "geometry": {"coordinates":[6.7880001068,51.0761489868],"type":"Point"}
}