{
  "type": "Feature",
  "properties": {
    "iso:country":"DE",
    "sg:address":"Waldstr. 60",
    "sg:city":"Leipzig",
    "sg:phone":"+49 341/9800895",
    "sg:postcode":"04105",
    "sg:province":"Sachsen",
    "wof:name":"R. Keil Architekt",
    "wof:placetype":"venue"
},
  "geometry": {"coordinates":[12.356805,51.346653],"type":"Point"}
}