{
  "type": "Feature",
  "properties": {
    "iso:country":"DE",
    "sg:address":"Haddamsh\u00e4user Str. 44",
    "sg:city":"Marburg",
    "sg:phone":"+49 6421/31525",
    "sg:postcode":"35041",
    "sg:province":"Hessen",
    "wof:name":"Bernd Koch Massagepraxis",
    "wof:placetype":"venue"
},
  "geometry": {"coordinates":[8.698816,50.780361],"type":"Point"}
}