{
  "type": "Feature",
  "properties": {
    "iso:country":"DE",
    "sg:address":"Goyatzer Str. 1",
    "sg:city":"Cottbus",
    "sg:phone":"+49 355/873113",
    "sg:postcode":"03044",
    "sg:province":"Brandenburg",
    "wof:name":"Elvira S\u00fc\u00dfmuth",
    "wof:placetype":"venue"
},
  "geometry": {"coordinates":[14.3248109818,51.774772644],"type":"Point"}
}