{
  "type": "Feature",
  "properties": {
    "iso:country":"DE",
    "sg:address":"Bodestr. 19",
    "sg:city":"Hamburg",
    "sg:phone":"+49 40/7303730",
    "sg:postcode":"21031",
    "sg:province":"Hamburg",
    "wof:name":"Ludwig Pfeiffer Inh. Carsten Steenw\u00e4rder",
    "wof:placetype":"venue"
},
  "geometry": {"coordinates":[10.1811714172,53.5095825195],"type":"Point"}
}