{
  "type": "Feature",
  "properties": {
    "iso:country":"DE",
    "sg:address":"Gerlachsheimer Str. 13",
    "sg:city":"Gr\u00fcnsfeld",
    "sg:phone":"+49 9346/1018",
    "sg:postcode":"97947",
    "sg:province":"Baden-W\u00fcrttemberg",
    "wof:name":"Hilarius Muthig Werbegeschenk-hdl.",
    "wof:placetype":"venue"
},
  "geometry": {"coordinates":[9.746591568,49.6041297913],"type":"Point"}
}