{
  "type": "Feature",
  "properties": {
    "iso:country":"DE",
    "sg:address":"Sorenfeldring 27",
    "sg:city":"Hamburg",
    "sg:phone":"+49 40/6037456",
    "sg:postcode":"22359",
    "sg:province":"Hamburg",
    "wof:name":"Beltana Trading E. K.",
    "wof:placetype":"venue"
},
  "geometry": {"coordinates":[10.1714305878,53.6559562683],"type":"Point"}
}