{
  "type": "Feature",
  "properties": {
    "iso:country":"DE",
    "sg:address":"Gemarkenstr. 12",
    "sg:city":"K\u00f6ln",
    "sg:phone":"+49 221/683456",
    "sg:postcode":"51069",
    "sg:province":"Nordrhein-Westfalen",
    "wof:name":"Hans-bernd Schiefer Architekt",
    "wof:placetype":"venue"
},
  "geometry": {"coordinates":[7.078781,50.972969],"type":"Point"}
}