{
  "type": "Feature",
  "properties": {
    "iso:country":"DE",
    "sg:address":"Kapellenweg 36",
    "sg:city":"Titisee-Neustadt",
    "sg:phone":"+49 7651/8569",
    "sg:postcode":"79822",
    "sg:province":"Baden-W\u00fcrttemberg",
    "wof:name":"Hoepfner Gmbh",
    "wof:placetype":"venue"
},
  "geometry": {"coordinates":[8.1493597031,47.9025421143],"type":"Point"}
}