{
  "type": "Feature",
  "properties": {
    "iso:country":"DE",
    "sg:address":"Strothheide 21",
    "sg:city":"Verl",
    "sg:phone":"+49 5246/6527",
    "sg:postcode":"33415",
    "sg:province":"Nordrhein-Westfalen",
    "wof:name":"H.-d. Puhl",
    "wof:placetype":"venue"
},
  "geometry": {"coordinates":[8.48602,51.874039],"type":"Point"}
}