{
  "type": "Feature",
  "properties": {
    "iso:country":"DE",
    "sg:address":"Bohnenkamp 6",
    "sg:city":"Bad Harzburg",
    "sg:postcode":"38667",
    "sg:province":"Niedersachsen",
    "wof:name":"Wulf Garten Landschaften Gmbh",
    "wof:placetype":"venue"
},
  "geometry": {"coordinates":[10.5408973694,51.9132232666],"type":"Point"}
}