{
  "type": "Feature",
  "properties": {
    "iso:country":"DE",
    "sg:address":"Hauptstr. 25",
    "sg:city":"Greimersburg",
    "sg:phone":"+49 2671/7754",
    "sg:postcode":"56814",
    "sg:province":"Rheinland-Pfalz",
    "wof:name":"Herbert Esper",
    "wof:placetype":"venue"
},
  "geometry": {"coordinates":[7.1411190033,50.185043335],"type":"Point"}
}