{
  "type": "Feature",
  "properties": {
    "iso:country":"DE",
    "sg:address":"Lange Str. 40",
    "sg:city":"Iserlohn",
    "sg:phone":"+49 2371/29173",
    "sg:postcode":"58636",
    "sg:province":"Nordrhein-Westfalen",
    "wof:name":"Klaus Weber Werkzeuge",
    "wof:placetype":"venue"
},
  "geometry": {"coordinates":[7.702904,51.378307],"type":"Point"}
}