{
  "type": "Feature",
  "properties": {
    "iso:country":"DE",
    "sg:address":"Eppendorfer Weg 58",
    "sg:city":"Hamburg",
    "sg:phone":"+49 40/405701",
    "sg:postcode":"20259",
    "sg:province":"Hamburg",
    "wof:name":"Robert Jochens & Sohn",
    "wof:placetype":"venue"
},
  "geometry": {"coordinates":[9.959623,53.572384],"type":"Point"}
}