{
  "type": "Feature",
  "properties": {
    "iso:country":"DE",
    "sg:address":"Bahnhofstr. 47",
    "sg:city":"Rennerod",
    "sg:phone":"+49 2664/999672",
    "sg:postcode":"56477",
    "sg:province":"Rheinland-Pfalz",
    "wof:name":"Nurischad Reisen Gmbh",
    "wof:placetype":"venue"
},
  "geometry": {"coordinates":[8.0703735352,50.617351532],"type":"Point"}
}