{
  "type": "Feature",
  "properties": {
    "iso:country":"DE",
    "sg:address":"Tannenhof",
    "sg:city":"Neustrelitz",
    "sg:postcode":"17235",
    "sg:province":"Mecklenburg-Vorpommern",
    "wof:name":"Handel- Und Leistungszentrum Axel Michen",
    "wof:placetype":"venue"
},
  "geometry": {"coordinates":[13.0415048599,53.3807067871],"type":"Point"}
}