{
  "type": "Feature",
  "properties": {
    "iso:country":"DE",
    "sg:address":"R\u00f6merkanal 64",
    "sg:city":"Rheinbach",
    "sg:phone":"+49 2226/92250",
    "sg:postcode":"53359",
    "sg:province":"Nordrhein-Westfalen",
    "wof:name":"Autohaus Grohmann - Renault Vertragsh\u00e4ndler",
    "wof:placetype":"venue"
},
  "geometry": {"coordinates":[6.9618220329,50.6281852722],"type":"Point"}
}