{
  "type": "Feature",
  "properties": {
    "iso:country":"DE",
    "sg:address":"Hemmerlestra\u00dfe 3",
    "sg:city":"Memmingen",
    "sg:phone":"+49 8331/94480",
    "sg:postcode":"87700",
    "sg:province":"Bayern",
    "wof:name":"Alois M\u00fcller Gmbh",
    "wof:placetype":"venue"
},
  "geometry": {"coordinates":[10.1838102341,47.9956169128],"type":"Point"}
}