{
  "type": "Feature",
  "properties": {
    "iso:country":"DE",
    "sg:address":"Akazienstr. 30",
    "sg:city":"Wustermark",
    "sg:postcode":"14641",
    "sg:province":"Brandenburg",
    "wof:name":"B & K Wustermark Gmbh",
    "wof:placetype":"venue"
},
  "geometry": {"coordinates":[12.933061,52.544239],"type":"Point"}
}