{
  "type": "Feature",
  "properties": {
    "iso:country":"DE",
    "sg:address":"Sch\u00f6nw\u00e4lder Str. 11",
    "sg:city":"Schonach",
    "sg:phone":"+49 7722/4772",
    "sg:postcode":"78136",
    "sg:province":"Baden-W\u00fcrttemberg",
    "wof:name":"Pension Rita Und Dieter Nock",
    "wof:placetype":"venue"
},
  "geometry": {"coordinates":[8.240445137,48.147644043],"type":"Point"}
}