{
  "type": "Feature",
  "properties": {
    "iso:country":"DE",
    "sg:address":"Karltor 2",
    "sg:city":"D\u00fcsseldorf",
    "sg:phone":"+49 211/8284643",
    "sg:postcode":"40213",
    "sg:province":"Nordrhein-Westfalen",
    "wof:name":"Upg Dr. Flender Gmbh",
    "wof:placetype":"venue"
},
  "geometry": {"coordinates":[6.775735,51.227871],"type":"Point"}
}