{
  "type": "Feature",
  "properties": {
    "iso:country":"DE",
    "sg:address":"Rastenhofer Str. 9",
    "sg:city":"Neustadt",
    "sg:phone":"+49 9602/1785",
    "sg:postcode":"92660",
    "sg:province":"Bayern",
    "wof:name":"Wolfgang Fleischmann",
    "wof:placetype":"venue"
},
  "geometry": {"coordinates":[12.184998,49.733707],"type":"Point"}
}