{
  "type": "Feature",
  "properties": {
    "iso:country":"DE",
    "sg:address":"Hauptstr 33",
    "sg:city":"P\u00fcchau",
    "sg:phone":"+49 3425/89720",
    "sg:postcode":"04828",
    "sg:province":"Sachsen",
    "wof:name":"Est Spezialtechnik Gmbh",
    "wof:placetype":"venue"
},
  "geometry": {"coordinates":[12.647089,51.400696],"type":"Point"}
}