{
  "type": "Feature",
  "properties": {
    "iso:country":"DE",
    "sg:address":"Bodelschwinghstr. 5",
    "sg:city":"Beeskow",
    "sg:phone":"+49 3366/20530",
    "sg:postcode":"15848",
    "sg:province":"Brandenburg",
    "wof:name":"Hgs Haushaltger\u00e4teservice Gmbh",
    "wof:placetype":"venue"
},
  "geometry": {"coordinates":[14.247879982,52.1711654663],"type":"Point"}
}