{
  "type": "Feature",
  "properties": {
    "iso:country":"DE",
    "sg:address":"Am Strothebach 2",
    "sg:city":"Bissendorf",
    "sg:phone":"+49 5402/6190",
    "sg:postcode":"49143",
    "sg:province":"Niedersachsen",
    "wof:name":"Technopool Schwimmbad- Technologie Gmbh",
    "wof:placetype":"venue"
},
  "geometry": {"coordinates":[8.13666,52.258141],"type":"Point"}
}