{
  "type": "Feature",
  "properties": {
    "iso:country":"DE",
    "sg:address":"Halberst\u00e4dter Str. 2a",
    "sg:city":"Wolfenb\u00fcttel",
    "sg:postcode":"38300",
    "sg:province":"Niedersachsen",
    "wof:name":"Neubauer Verwaltungs-gmbh",
    "wof:placetype":"venue"
},
  "geometry": {"coordinates":[10.553863,52.151119],"type":"Point"}
}