{
  "type": "Feature",
  "properties": {
    "iso:country":"DE",
    "sg:address":"Mainaustr. 32",
    "sg:city":"W\u00fcrzburg",
    "sg:phone":"+49 931/42535",
    "sg:postcode":"97082",
    "sg:province":"Bayern",
    "wof:name":"Vereinsgastst\u00e4tte W\u00fcrzburger Fu\u00dfballverein E. V.",
    "wof:placetype":"venue"
},
  "geometry": {"coordinates":[9.9105224609,49.8021240234],"type":"Point"}
}