{
  "type": "Feature",
  "properties": {
    "iso:country":"DE",
    "sg:address":"Riehe 6",
    "sg:city":"Ganderkesee",
    "sg:postcode":"27777",
    "sg:province":"Niedersachsen",
    "wof:name":"Max Sigma Gmbh",
    "wof:placetype":"venue"
},
  "geometry": {"coordinates":[8.5306529999,52.9746704102],"type":"Point"}
}