{
  "type": "Feature",
  "properties": {
    "iso:country":"DE",
    "sg:address":"Winterhuder Weg 18",
    "sg:city":"Hamburg",
    "sg:phone":"+49 40/223381",
    "sg:postcode":"22085",
    "sg:province":"Hamburg",
    "wof:name":"Uwe Rosenkranz",
    "wof:placetype":"venue"
},
  "geometry": {"coordinates":[10.0256576538,53.5716934204],"type":"Point"}
}