{
  "type": "Feature",
  "properties": {
    "iso:country":"DE",
    "sg:address":"Georg-Winkler-Str. 7a",
    "sg:city":"M\u00fcnchen",
    "sg:phone":"+49 89/31215707",
    "sg:postcode":"80995",
    "sg:province":"Bayern",
    "wof:name":"Edv-beratung M\u00fcnchen Martin Steinherr",
    "wof:placetype":"venue"
},
  "geometry": {"coordinates":[11.5382423401,48.2154083252],"type":"Point"}
}