{
  "type": "Feature",
  "properties": {
    "iso:country":"DE",
    "sg:address":"Hellestr 40",
    "sg:city":"Hemer",
    "sg:phone":"+49 2372/860940",
    "sg:postcode":"58675",
    "sg:province":"Nordrhein-Westfalen",
    "wof:name":"Gebr\u00fcder Vom Braucke Gmbh & Co Kg",
    "wof:placetype":"venue"
},
  "geometry": {"coordinates":[7.7456102371,51.3553009033],"type":"Point"}
}