{
  "type": "Feature",
  "properties": {
    "iso:country":"DE",
    "sg:address":"Greffener Str. 25",
    "sg:city":"Sassenberg",
    "sg:phone":"+49 2583/1552",
    "sg:postcode":"48336",
    "sg:province":"Nordrhein-Westfalen",
    "wof:name":"F. Kunstleve",
    "wof:placetype":"venue"
},
  "geometry": {"coordinates":[8.0658378601,51.9807090759],"type":"Point"}
}