{
  "type": "Feature",
  "properties": {
    "iso:country":"DE",
    "sg:address":"Ostwall 3",
    "sg:city":"Dortmund",
    "sg:phone":"+49 231/522066",
    "sg:postcode":"44135",
    "sg:province":"Nordrhein-Westfalen",
    "wof:name":"R. Gebauer Und M. Kwetina Rechtsanw\u00e4lte",
    "wof:placetype":"venue"
},
  "geometry": {"coordinates":[7.472299099,51.5138511658],"type":"Point"}
}