{
  "type": "Feature",
  "properties": {
    "iso:country":"DE",
    "sg:address":"Ringstr. 15",
    "sg:city":"Girkenroth",
    "sg:phone":"+49 6435/2822",
    "sg:postcode":"56459",
    "sg:province":"Rheinland-Pfalz",
    "wof:name":"Pension Ursula Weimer",
    "wof:placetype":"venue"
},
  "geometry": {"coordinates":[7.9686689377,50.5196495056],"type":"Point"}
}