{
  "type": "Feature",
  "properties": {
    "iso:country":"DE",
    "sg:address":"Ebertstr. 13",
    "sg:city":"Landshut",
    "sg:postcode":"84032",
    "sg:province":"Bayern",
    "wof:name":"Colledo.com Handels Gmbh",
    "wof:placetype":"venue"
},
  "geometry": {"coordinates":[12.1363153458,48.5502281189],"type":"Point"}
}