{
  "type": "Feature",
  "properties": {
    "iso:country":"DE",
    "sg:address":"Kolbergerstr. 1",
    "sg:city":"M\u00fcnchen",
    "sg:phone":"+49 89/983414",
    "sg:postcode":"81679",
    "sg:province":"Bayern",
    "wof:name":"Anko Handels Gmbh",
    "wof:placetype":"venue"
},
  "geometry": {"coordinates":[11.6038618088,48.1504211426],"type":"Point"}
}