{
  "type": "Feature",
  "properties": {
    "iso:country":"DE",
    "sg:address":"S\u00fcdfeld 88",
    "sg:city":"Kamen",
    "sg:phone":"+49 2307/43971",
    "sg:postcode":"59174",
    "sg:province":"Nordrhein-Westfalen",
    "wof:name":"Praxis Dr. Med. Eickerling Und Dr. Med. Jansen",
    "wof:placetype":"venue"
},
  "geometry": {"coordinates":[7.7190499306,51.578212738],"type":"Point"}
}