{
  "type": "Feature",
  "properties": {
    "iso:country":"DE",
    "sg:address":"Pirmasenser Str. 13",
    "sg:city":"Kaiserslautern",
    "sg:phone":"+49 631/696585",
    "sg:postcode":"67655",
    "sg:province":"Rheinland-Pfalz",
    "wof:name":"Profi Shop",
    "wof:placetype":"venue"
},
  "geometry": {"coordinates":[7.7672457695,49.4414825439],"type":"Point"}
}