{
  "type": "Feature",
  "properties": {
    "iso:country":"DE",
    "sg:address":"Carl-Zuckmayer-Platz 3",
    "sg:city":"Nackenheim",
    "sg:phone":"+49 6135/92990",
    "sg:postcode":"55299",
    "sg:province":"Rheinland-Pfalz",
    "wof:name":"Hotel St. Gereon",
    "wof:placetype":"venue"
},
  "geometry": {"coordinates":[8.3418064117,49.9151954651],"type":"Point"}
}