{
  "type": "Feature",
  "properties": {
    "iso:country":"DE",
    "sg:address":"Im Langetal",
    "sg:city":"Jena",
    "sg:phone":"+49 3641/447775",
    "sg:postcode":"07743",
    "sg:province":"Th\u00fcringen",
    "wof:name":"Kleingartenanlage",
    "wof:placetype":"venue"
},
  "geometry": {"coordinates":[11.5539083481,50.9337654114],"type":"Point"}
}