{
  "type": "Feature",
  "properties": {
    "iso:country":"DE",
    "sg:address":"Rengsh\u00e4user Str. 19",
    "sg:city":"Kn\u00fcllwald",
    "sg:phone":"+49 5685/651",
    "sg:postcode":"34593",
    "sg:province":"Hessen",
    "wof:name":"Karl Jakob",
    "wof:placetype":"venue"
},
  "geometry": {"coordinates":[9.526061,51.03857],"type":"Point"}
}