{
  "type": "Feature",
  "properties": {
    "iso:country":"DE",
    "sg:address":"Kirchplatz 6",
    "sg:city":"K\u00f6nigsee",
    "sg:postcode":"07426",
    "sg:province":"Th\u00fcringen",
    "wof:name":"Uf Technologie Gmbh",
    "wof:placetype":"venue"
},
  "geometry": {"coordinates":[11.096143,50.662083],"type":"Point"}
}