{
  "type": "Feature",
  "properties": {
    "iso:country":"DE",
    "sg:address":"Bachtalstr. 216",
    "sg:city":"Schwalbach",
    "sg:phone":"+49 6834/55313",
    "sg:postcode":"66773",
    "sg:province":"Saarland",
    "wof:name":"Hotel M\u00fchlental Gmbh",
    "wof:placetype":"venue"
},
  "geometry": {"coordinates":[6.8415389061,49.2954101562],"type":"Point"}
}