{
  "type": "Feature",
  "properties": {
    "iso:country":"DE",
    "sg:address":"Heldener Str. 17",
    "sg:city":"Attendorn",
    "sg:phone":"+49 2722/4323",
    "sg:postcode":"57439",
    "sg:province":"Nordrhein-Westfalen",
    "wof:name":"Deutsche Bp Gmbh",
    "wof:placetype":"venue"
},
  "geometry": {"coordinates":[7.9139308929,51.1225280762],"type":"Point"}
}