{
  "type": "Feature",
  "properties": {
    "iso:country":"DE",
    "sg:address":"Siemensstr. 7",
    "sg:city":"Herzebrock-Clarholz",
    "sg:phone":"+49 5245/3597",
    "sg:postcode":"33442",
    "sg:province":"Nordrhein-Westfalen",
    "wof:name":"G. Mokinski & Sohn Kg",
    "wof:placetype":"venue"
},
  "geometry": {"coordinates":[8.215269,51.886799],"type":"Point"}
}