{
  "type": "Feature",
  "properties": {
    "iso:country":"DE",
    "sg:address":"Konradstr. 9",
    "sg:city":"W\u00fcrzburg",
    "sg:phone":"+49 931/355000",
    "sg:postcode":"97072",
    "sg:province":"Bayern",
    "wof:name":"Tiebautechn. B\u00fcro K\u00f6hl W\u00fcrzburg Gmbh",
    "wof:placetype":"venue"
},
  "geometry": {"coordinates":[9.9486780167,49.7928543091],"type":"Point"}
}