{
  "type": "Feature",
  "properties": {
    "iso:country":"DE",
    "sg:address":"Wilhelm-K\u00fclz-Str. 18",
    "sg:city":"K\u00f6rner",
    "sg:phone":"+49 36025/50253",
    "sg:postcode":"99998",
    "sg:province":"Th\u00fcringen",
    "wof:name":"Landwirtschaft K\u00f6rner Gmbh & Co. Betriebs Kg",
    "wof:placetype":"venue"
},
  "geometry": {"coordinates":[10.592899,51.231457],"type":"Point"}
}