{
  "type": "Feature",
  "properties": {
    "iso:country":"DE",
    "sg:address":"Obergath 126",
    "sg:city":"Krefeld",
    "sg:phone":"+49 2151/31950",
    "sg:postcode":"47805",
    "sg:province":"Nordrhein-Westfalen",
    "wof:name":"Wtk W\u00e4rmetechnik Service Gmbh",
    "wof:placetype":"venue"
},
  "geometry": {"coordinates":[6.566243,51.314018],"type":"Point"}
}