{
  "type": "Feature",
  "properties": {
    "iso:country":"DE",
    "sg:address":"Ludwigstr. 6",
    "sg:city":"Pei\u00dfenberg",
    "sg:phone":"+49 8803/2764",
    "sg:postcode":"82380",
    "sg:province":"Bayern",
    "wof:name":"Manfred Achleitner",
    "wof:placetype":"venue"
},
  "geometry": {"coordinates":[11.076433,47.803318],"type":"Point"}
}