{
  "type": "Feature",
  "properties": {
    "iso:country":"DE",
    "sg:address":"Am Plan 8",
    "sg:city":"Koblenz",
    "sg:phone":"+49 261/33178",
    "sg:postcode":"56068",
    "sg:province":"Rheinland-Pfalz",
    "wof:name":"Nick Mode Gmbh",
    "wof:placetype":"venue"
},
  "geometry": {"coordinates":[7.594668,50.360168],"type":"Point"}
}