{
  "type": "Feature",
  "properties": {
    "iso:country":"DE",
    "sg:address":"Bottroper-Str. 20",
    "sg:city":"Essen",
    "sg:phone":"+49 201",
    "sg:postcode":"45141",
    "sg:province":"Nordrhein-Westfalen",
    "wof:name":"Gastgeber Brandenburg",
    "wof:placetype":"venue"
},
  "geometry": {"coordinates":[6.994712,51.470772],"type":"Point"}
}