{
  "type": "Feature",
  "properties": {
    "iso:country":"DE",
    "sg:address":"Schillerstr. 8",
    "sg:city":"Rostock",
    "sg:phone":"+49 381/724088",
    "sg:postcode":"18055",
    "sg:province":"Mecklenburg-Vorpommern",
    "wof:name":"Helmuth Rathsack Finanzberater",
    "wof:placetype":"venue"
},
  "geometry": {"coordinates":[12.1387605667,54.0764884949],"type":"Point"}
}