{
  "type": "Feature",
  "properties": {
    "iso:country":"DE",
    "sg:address":"Schlo\u00dfstr. 2",
    "sg:city":"Neu Zauche",
    "sg:phone":"+49 35475/336",
    "sg:postcode":"15913",
    "sg:province":"Brandenburg",
    "wof:name":"Manfred Nakonzer",
    "wof:placetype":"venue"
},
  "geometry": {"coordinates":[14.0885429382,51.9273262024],"type":"Point"}
}