{
  "type": "Feature",
  "properties": {
    "iso:country":"DE",
    "sg:address":"Curtiusstr. 4",
    "sg:city":"Berlin",
    "sg:phone":"+49 30/8332107",
    "sg:postcode":"12205",
    "sg:province":"Berlin",
    "wof:name":"Curtius-apotheke",
    "wof:placetype":"venue"
},
  "geometry": {"coordinates":[13.296025,52.442894],"type":"Point"}
}