{
  "type": "Feature",
  "properties": {
    "iso:country":"DE",
    "sg:address":"Gewerberg. 19",
    "sg:city":"Lohne",
    "sg:phone":"+49 4944/4293230",
    "sg:postcode":"49393",
    "sg:province":"Niedersachsen",
    "wof:name":"Dettmer Verpackungen Gmbh",
    "wof:placetype":"venue"
},
  "geometry": {"coordinates":[8.2249498367,52.6612892151],"type":"Point"}
}