{
  "type": "Feature",
  "properties": {
    "iso:country":"DE",
    "sg:address":"Gelderstr. 11",
    "sg:city":"Rheinberg",
    "sg:phone":"+49 2843/2336",
    "sg:postcode":"47495",
    "sg:province":"Nordrhein-Westfalen",
    "wof:name":"Thomas Seidl",
    "wof:placetype":"venue"
},
  "geometry": {"coordinates":[6.601749897,51.5448646545],"type":"Point"}
}