{
  "type": "Feature",
  "properties": {
    "iso:country":"DE",
    "sg:address":"Emsingsweg 1",
    "sg:city":"Bocholt",
    "sg:phone":"+49 4928/7144493",
    "sg:postcode":"46399",
    "sg:province":"Nordrhein-Westfalen",
    "wof:name":"Klemens Hoven",
    "wof:placetype":"venue"
},
  "geometry": {"coordinates":[6.529603,51.872913],"type":"Point"}
}