{
  "type": "Feature",
  "properties": {
    "iso:country":"DE",
    "sg:address":"Graf-Bernadotte-Platz 5",
    "sg:city":"Kassel",
    "sg:phone":"+49 561/31071",
    "sg:postcode":"34119",
    "sg:province":"Hessen",
    "wof:name":"Bundessozialgericht Bibliothek",
    "wof:placetype":"venue"
},
  "geometry": {"coordinates":[9.450145,51.314686],"type":"Point"}
}