{
  "type": "Feature",
  "properties": {
    "iso:country":"DE",
    "sg:address":"Kelterstr. 34",
    "sg:city":"Dettingen",
    "sg:phone":"+49 7021/81089",
    "sg:postcode":"73265",
    "sg:province":"Baden-W\u00fcrttemberg",
    "wof:name":"Kurbad Dettingen",
    "wof:placetype":"venue"
},
  "geometry": {"coordinates":[9.450402,48.621429],"type":"Point"}
}