{
  "type": "Feature",
  "properties": {
    "iso:country":"DE",
    "sg:address":"Ulrichstr. 64",
    "sg:city":"Icking",
    "sg:phone":"+49 8178/3302",
    "sg:postcode":"82057",
    "sg:province":"Bayern",
    "wof:name":"Klaus Doldinger",
    "wof:placetype":"venue"
},
  "geometry": {"coordinates":[11.4357805252,47.9614486694],"type":"Point"}
}