{
  "type": "Feature",
  "properties": {
    "iso:country":"DE",
    "sg:address":"Gerhart-Hauptmann-Str. 6",
    "sg:city":"Oberderdingen",
    "sg:phone":"+49 7045/671",
    "sg:postcode":"75038",
    "sg:province":"Baden-W\u00fcrttemberg",
    "wof:name":"Kreiter Gmbh",
    "wof:placetype":"venue"
},
  "geometry": {"coordinates":[8.795812,49.065762],"type":"Point"}
}