{
  "type": "Feature",
  "properties": {
    "iso:country":"DE",
    "sg:address":"Obere M\u00fchlenstr. 10 a",
    "sg:city":"Templin",
    "sg:phone":"+49 3987/3476",
    "sg:postcode":"17268",
    "sg:province":"Brandenburg",
    "wof:name":"J\u00fcrgen Wei\u00dfmann",
    "wof:placetype":"venue"
},
  "geometry": {"coordinates":[13.504986,53.118095],"type":"Point"}
}