{
  "type": "Feature",
  "properties": {
    "iso:country":"DE",
    "sg:address":"Rotteroder Str. 48",
    "sg:city":"Steinbach-Hallenberg",
    "sg:phone":"+49 36847/42265",
    "sg:postcode":"98587",
    "sg:province":"Th\u00fcringen",
    "wof:name":"H & B Elektroger\u00e4temontagen Gmbh",
    "wof:placetype":"venue"
},
  "geometry": {"coordinates":[10.563262,50.707996],"type":"Point"}
}