{
  "type": "Feature",
  "properties": {
    "iso:country":"DE",
    "sg:address":"Eglinger Str. 11",
    "sg:city":"Prittriching",
    "sg:phone":"+49 8206/529",
    "sg:postcode":"86931",
    "sg:province":"Bayern",
    "wof:name":"Kaspar Kriegenhofer",
    "wof:placetype":"venue"
},
  "geometry": {"coordinates":[10.931139,48.2034],"type":"Point"}
}