{
  "type": "Feature",
  "properties": {
    "iso:country":"DE",
    "sg:address":"Bahnhofstrasse 48",
    "sg:city":"Deggendorf",
    "sg:phone":"+49 991/6186",
    "sg:postcode":"94469",
    "sg:province":"Bayern",
    "wof:name":"Ferienfahrschule A. Stern",
    "wof:placetype":"venue"
},
  "geometry": {"coordinates":[12.95655,48.835155],"type":"Point"}
}