{
  "type": "Feature",
  "properties": {
    "iso:country":"DE",
    "sg:address":"Halmersreihe 8",
    "sg:city":"Sundern",
    "sg:phone":"+49 2393/375",
    "sg:postcode":"59846",
    "sg:province":"Nordrhein-Westfalen",
    "wof:name":"Hahn",
    "wof:placetype":"venue"
},
  "geometry": {"coordinates":[7.9526848793,51.2836875916],"type":"Point"}
}