{
  "type": "Feature",
  "properties": {
    "iso:country":"DE",
    "sg:address":"Frankfurter Str. 75::",
    "sg:city":"Kronberg",
    "sg:phone":"+49 4961/7395860",
    "sg:postcode":"61476",
    "sg:province":"Hessen",
    "wof:name":"Merca Leasing- U. Verwaltungs- Gmbh & Co. Kg",
    "wof:placetype":"venue"
},
  "geometry": {"coordinates":[8.523654,50.174194],"type":"Point"}
}