{
  "type": "Feature",
  "properties": {
    "iso:country":"DE",
    "sg:address":"In der Lohrenbeck 30b",
    "sg:city":"Wuppertal",
    "sg:phone":"+49 202/712340",
    "sg:postcode":"42115",
    "sg:province":"Nordrhein-Westfalen",
    "wof:name":"Reiner Tr\u00f6tschel",
    "wof:placetype":"venue"
},
  "geometry": {"coordinates":[7.095267,51.258423],"type":"Point"}
}