{
  "type": "Feature",
  "properties": {
    "iso:country":"DE",
    "sg:address":"Dorfstr. 50",
    "sg:city":"Jesberg",
    "sg:phone":"+49 6695/825",
    "sg:postcode":"34632",
    "sg:province":"Hessen",
    "wof:name":"Helmut Zinn",
    "wof:placetype":"venue"
},
  "geometry": {"coordinates":[9.145396,50.973389],"type":"Point"}
}