{
  "type": "Feature",
  "properties": {
    "iso:country":"DE",
    "sg:address":"Steinbeeke 10",
    "sg:city":"Auetal",
    "sg:phone":"+49 5752/890",
    "sg:postcode":"31749",
    "sg:province":"Niedersachsen",
    "wof:name":"Friedrich Westermann",
    "wof:placetype":"venue"
},
  "geometry": {"coordinates":[9.233699,52.235588],"type":"Point"}
}