{
  "type": "Feature",
  "properties": {
    "iso:country":"DE",
    "sg:address":"Strandweg 12",
    "sg:city":"Rostock",
    "sg:phone":"+49 381/51201",
    "sg:postcode":"18119",
    "sg:province":"Mecklenburg-Vorpommern",
    "wof:name":"Hotelbetriebsf\u00fchrungs Gmbh Rostock",
    "wof:placetype":"venue"
},
  "geometry": {"coordinates":[12.0688352585,54.1776275635],"type":"Point"}
}