{
  "type": "Feature",
  "properties": {
    "iso:country":"DE",
    "sg:address":"Sch\u00fctzenstr. 7",
    "sg:city":"M\u00fchltroff",
    "sg:phone":"+49 36645/21967",
    "sg:postcode":"07919",
    "sg:province":"Th\u00fcringen",
    "wof:name":"Ehrhardt & Kuhn Gmbh",
    "wof:placetype":"venue"
},
  "geometry": {"coordinates":[11.926281929,50.5384483337],"type":"Point"}
}