{
  "type": "Feature",
  "properties": {
    "iso:country":"DE",
    "sg:address":"Kalscheurener Str. 92",
    "sg:city":"H\u00fcrth",
    "sg:phone":"+49 4922/3369990",
    "sg:postcode":"50354",
    "sg:province":"Nordrhein-Westfalen",
    "wof:name":"Steris Gmbh",
    "wof:placetype":"venue"
},
  "geometry": {"coordinates":[6.90633,50.888409],"type":"Point"}
}