{
  "type": "Feature",
  "properties": {
    "iso:country":"DE",
    "sg:address":"Klosterstr. 11",
    "sg:city":"Rinteln",
    "sg:phone":"+49 180 1 2555148",
    "sg:postcode":"31737",
    "sg:province":"Niedersachsen",
    "wof:name":"Sparkasse Schaumburg",
    "wof:placetype":"venue"
},
  "geometry": {"coordinates":[9.079452,52.186466],"type":"Point"}
}