{
  "type": "Feature",
  "properties": {
    "iso:country":"DE",
    "sg:address":"Borsigstr. 16",
    "sg:city":"Wiesbaden",
    "sg:phone":"+49 6122/999911",
    "sg:postcode":"65205",
    "sg:province":"Hessen",
    "wof:name":"Plus Finanzservice- Gmbh",
    "wof:placetype":"venue"
},
  "geometry": {"coordinates":[8.3349323273,50.0573272705],"type":"Point"}
}