{
  "type": "Feature",
  "properties": {
    "iso:country":"DE",
    "sg:address":"Knooper Weg 10",
    "sg:city":"Kiel",
    "sg:phone":"+49 431/92272",
    "sg:postcode":"24103",
    "sg:province":"Schleswig-Holstein",
    "wof:name":"Joachim Hinrichsen",
    "wof:placetype":"venue"
},
  "geometry": {"coordinates":[10.127198,54.323044],"type":"Point"}
}