{
  "type": "Feature",
  "properties": {
    "iso:country":"DE",
    "sg:address":"Hauptstr. 106",
    "sg:city":"Freigericht",
    "sg:phone":"+49 6055/1216",
    "sg:postcode":"63579",
    "sg:province":"Hessen",
    "wof:name":"Wep Wagner Engineering Und Production Gmbh",
    "wof:placetype":"venue"
},
  "geometry": {"coordinates":[9.1436805725,50.1398200989],"type":"Point"}
}