{
  "type": "Feature",
  "properties": {
    "iso:country":"DE",
    "sg:address":"Kirchstr. 15",
    "sg:city":"Hagen",
    "sg:phone":"+49 2331/60961",
    "sg:postcode":"58099",
    "sg:province":"Nordrhein-Westfalen",
    "wof:name":"Eiscafe Gianfranco Collato",
    "wof:placetype":"venue"
},
  "geometry": {"coordinates":[7.471612,51.395683],"type":"Point"}
}