{
  "type": "Feature",
  "properties": {
    "iso:country":"DE",
    "sg:address":"Nordpromenade 1 A",
    "sg:city":"Schafst\u00e4dt",
    "sg:phone":"+49 34636/60597",
    "sg:postcode":"06255",
    "sg:province":"Sachsen-Anhalt",
    "wof:name":"Norma Gmbh & Co. Kg",
    "wof:placetype":"venue"
},
  "geometry": {"coordinates":[11.767039299,51.3828048706],"type":"Point"}
}