{
  "type": "Feature",
  "properties": {
    "iso:country":"DE",
    "sg:address":"Industriestr. 5",
    "sg:city":"Heideck",
    "sg:phone":"+49 9177/1601",
    "sg:postcode":"91180",
    "sg:province":"Bayern",
    "wof:name":"Franz Pollak Gmbh",
    "wof:placetype":"venue"
},
  "geometry": {"coordinates":[11.1190958023,49.1314277649],"type":"Point"}
}