{
  "type": "Feature",
  "properties": {
    "iso:country":"DE",
    "sg:address":"G\u00f6gginger Mauer 23-25",
    "sg:city":"Augsburg",
    "sg:phone":"+49 821/36813",
    "sg:postcode":"86150",
    "sg:province":"Bayern",
    "wof:name":"Karl-heinz Englet Gmbh",
    "wof:placetype":"venue"
},
  "geometry": {"coordinates":[10.8982038498,48.3606643677],"type":"Point"}
}