{
  "type": "Feature",
  "properties": {
    "iso:country":"DE",
    "sg:address":"Pflugweg 35",
    "sg:city":"Solingen",
    "sg:phone":"+49 212/248360",
    "sg:postcode":"42655",
    "sg:province":"Nordrhein-Westfalen",
    "wof:name":"Porysek Maschinen- Und Anlagenbau Gmbh",
    "wof:placetype":"venue"
},
  "geometry": {"coordinates":[7.043463,51.155666],"type":"Point"}
}