{
  "type": "Feature",
  "properties": {
    "iso:country":"DE",
    "sg:address":"Hauptstr. 27",
    "sg:city":"Kriebitzsch",
    "sg:phone":"+49 3448/410143",
    "sg:postcode":"04617",
    "sg:province":"Th\u00fcringen",
    "wof:name":"M\u00fchle",
    "wof:placetype":"venue"
},
  "geometry": {"coordinates":[12.336517,51.027954],"type":"Point"}
}