{
  "type": "Feature",
  "properties": {
    "iso:country":"DE",
    "sg:address":"Leipziger Str. 175",
    "sg:city":"Frankfurt",
    "sg:phone":"+49 335/542320",
    "sg:postcode":"15232",
    "sg:province":"Brandenburg",
    "wof:name":"Zerna K\u00f6pper & Partner Ingenieurgesellschaft",
    "wof:placetype":"venue"
},
  "geometry": {"coordinates":[14.5366830826,52.335105896],"type":"Point"}
}