{
  "type": "Feature",
  "properties": {
    "iso:country":"DE",
    "sg:address":"Markt 10",
    "sg:city":"Leipzig",
    "sg:phone":"+49 34298",
    "sg:postcode":"04425",
    "sg:province":"Sachsen",
    "wof:name":"Firma A.trautmann",
    "wof:placetype":"venue"
},
  "geometry": {"coordinates":[12.50041,51.381001],"type":"Point"}
}