{
  "type": "Feature",
  "properties": {
    "iso:country":"DE",
    "sg:address":"Hafenstr. 25",
    "sg:city":"Petershagen",
    "sg:postcode":"32469",
    "sg:province":"Nordrhein-Westfalen",
    "wof:name":"Uwe Czisielski",
    "wof:placetype":"venue"
},
  "geometry": {"coordinates":[8.968324,52.38039],"type":"Point"}
}