{
  "type": "Feature",
  "properties": {
    "iso:country":"DE",
    "sg:address":"Wallstr. 13",
    "sg:city":"Oldenburg",
    "sg:phone":"+49 441/13128",
    "sg:postcode":"26122",
    "sg:province":"Niedersachsen",
    "wof:name":"Restaurant Le Journal",
    "wof:placetype":"venue"
},
  "geometry": {"coordinates":[8.2099866867,53.1420211792],"type":"Point"}
}