{
  "type": "Feature",
  "properties": {
    "iso:country":"DE",
    "sg:address":"Ringstr. 14",
    "sg:city":"Gemmingen",
    "sg:phone":"+49 7267/467",
    "sg:postcode":"75050",
    "sg:province":"Baden-W\u00fcrttemberg",
    "wof:name":"Erna Richter",
    "wof:placetype":"venue"
},
  "geometry": {"coordinates":[8.9713869095,49.146156311],"type":"Point"}
}