{
  "type": "Feature",
  "properties": {
    "iso:country":"DE",
    "sg:address":"Gundelsheimer Str. 32",
    "sg:city":"Bad Rappenau",
    "sg:phone":"+49 7264/5522",
    "sg:postcode":"74906",
    "sg:province":"Baden-W\u00fcrttemberg",
    "wof:name":"Willi Fink",
    "wof:placetype":"venue"
},
  "geometry": {"coordinates":[9.15001297,49.2612419128],"type":"Point"}
}