{
  "type": "Feature",
  "properties": {
    "iso:country":"DE",
    "sg:address":"Kuppinger Str. 14",
    "sg:city":"Herrenberg",
    "sg:phone":"+49 7032/31670",
    "sg:postcode":"71083",
    "sg:province":"Baden-W\u00fcrttemberg",
    "wof:name":"Restaurant Linde",
    "wof:placetype":"venue"
},
  "geometry": {"coordinates":[8.8572731018,48.607624054],"type":"Point"}
}