{
  "type": "Feature",
  "properties": {
    "iso:country":"DE",
    "sg:address":"D\u00fcsterntwiete 29",
    "sg:city":"Norderstedt",
    "sg:phone":"+49 40/5232412",
    "sg:postcode":"22850",
    "sg:province":"Schleswig-Holstein",
    "wof:name":"Horst Raben",
    "wof:placetype":"venue"
},
  "geometry": {"coordinates":[9.976319313,53.684677124],"type":"Point"}
}