{
  "type": "Feature",
  "properties": {
    "iso:country":"DE",
    "sg:address":"Kurparkstr. 31",
    "sg:city":"Bad Orb",
    "sg:phone":"+49 6052/80030",
    "sg:postcode":"63619",
    "sg:province":"Hessen",
    "wof:name":"Haus Margarethenhof Inh. Manfred Stock",
    "wof:placetype":"venue"
},
  "geometry": {"coordinates":[9.3555603027,50.2182312012],"type":"Point"}
}