{
  "type": "Feature",
  "properties": {
    "iso:country":"DE",
    "sg:address":"Lintiger Str. 24",
    "sg:city":"Lintig",
    "sg:phone":"+49 4745/209",
    "sg:postcode":"27624",
    "sg:province":"Niedersachsen",
    "wof:name":"Gastst\u00e4tte H. George",
    "wof:placetype":"venue"
},
  "geometry": {"coordinates":[8.8823108673,53.6037788391],"type":"Point"}
}