{
  "type": "Feature",
  "properties": {
    "iso:country":"DE",
    "sg:address":"Ewaldstr. 5-7",
    "sg:city":"Remscheid",
    "sg:phone":"+49 2191/388356",
    "sg:postcode":"42859",
    "sg:province":"Nordrhein-Westfalen",
    "wof:name":"Prodimex Produktions- Und Handelsges. Mbh",
    "wof:placetype":"venue"
},
  "geometry": {"coordinates":[7.205274,51.17395],"type":"Point"}
}