{
  "type": "Feature",
  "properties": {
    "iso:country":"DE",
    "sg:address":"Dorfstr. 16",
    "sg:city":"Wienhausen",
    "sg:phone":"+49 5149/98030",
    "sg:postcode":"29342",
    "sg:province":"Niedersachsen",
    "wof:name":"Landhotel Klosterhof",
    "wof:placetype":"venue"
},
  "geometry": {"coordinates":[10.1979150772,52.5858573914],"type":"Point"}
}