{
  "type": "Feature",
  "properties": {
    "iso:country":"DE",
    "sg:address":"An der Halde 18a",
    "sg:city":"Germaringen",
    "sg:phone":"+49 8344",
    "sg:postcode":"87656",
    "sg:province":"Bayern",
    "wof:name":"Cad B\u00fcro Twp",
    "wof:placetype":"venue"
},
  "geometry": {"coordinates":[10.6795034409,47.9409828186],"type":"Point"}
}