{
  "type": "Feature",
  "properties": {
    "iso:country":"DE",
    "sg:address":"Grenzweg 4",
    "sg:city":"Eibau",
    "sg:phone":"+49 3586/310528",
    "sg:postcode":"02739",
    "sg:province":"Sachsen",
    "wof:name":"G. Paul",
    "wof:placetype":"venue"
},
  "geometry": {"coordinates":[14.65036,50.988892],"type":"Point"}
}