{
  "type": "Feature",
  "properties": {
    "iso:country":"DE",
    "sg:address":"Hauptstr. 24",
    "sg:city":"Erlangen",
    "sg:phone":"+49 9131/21162",
    "sg:postcode":"91054",
    "sg:province":"Bayern",
    "wof:name":"Optik Amberg",
    "wof:placetype":"venue"
},
  "geometry": {"coordinates":[11.0042629242,49.5970191956],"type":"Point"}
}