{
  "type": "Feature",
  "properties": {
    "iso:country":"DE",
    "sg:address":"Gro\u00dfe Str. 45",
    "sg:city":"Rotenburg",
    "sg:phone":"+49 4261/4591",
    "sg:postcode":"27356",
    "sg:province":"Niedersachsen",
    "wof:name":"L\u00f6wen-apotheke Inh. Hassan Hakkaki E. K.",
    "wof:placetype":"venue"
},
  "geometry": {"coordinates":[9.404578,53.110683],"type":"Point"}
}