{
  "type": "Feature",
  "properties": {
    "iso:country":"DE",
    "sg:address":"Dagobertsweg 4",
    "sg:city":"Landau",
    "sg:phone":"+49 6341/62248",
    "sg:postcode":"76829",
    "sg:province":"Rheinland-Pfalz",
    "wof:name":"Elisabeth Kyas Architekten",
    "wof:placetype":"venue"
},
  "geometry": {"coordinates":[8.087195,49.211891],"type":"Point"}
}