{
  "type": "Feature",
  "properties": {
    "iso:country":"DE",
    "sg:address":"Geisenhausenerstr. 7",
    "sg:city":"M\u00fcnchen",
    "sg:phone":"+49 89/78760",
    "sg:postcode":"81379",
    "sg:province":"Bayern",
    "wof:name":"Kl\u00dcber Lubrication M\u00dcnchen Kg",
    "wof:placetype":"venue"
},
  "geometry": {"coordinates":[11.519653,48.097973],"type":"Point"}
}