{
  "type": "Feature",
  "properties": {
    "iso:country":"DE",
    "sg:address":"Herner Str. 68",
    "sg:city":"Recklinghausen",
    "sg:phone":"+49 2361/23624",
    "sg:postcode":"45657",
    "sg:province":"Nordrhein-Westfalen",
    "wof:name":"Textilreinigung Kuhlmann Gmbh",
    "wof:placetype":"venue"
},
  "geometry": {"coordinates":[7.2006897926,51.6033973694],"type":"Point"}
}