{
  "type": "Feature",
  "properties": {
    "iso:country":"DE",
    "sg:address":"B\u00fcrener Str. 12",
    "sg:city":"B\u00fcren",
    "sg:phone":"+49 2951/70495",
    "sg:postcode":"33142",
    "sg:province":"Nordrhein-Westfalen",
    "wof:name":"Losch Haust\u00fcrenstudio",
    "wof:placetype":"venue"
},
  "geometry": {"coordinates":[8.516592,51.581192],"type":"Point"}
}