{
  "type": "Feature",
  "properties": {
    "iso:country":"DE",
    "sg:address":"Zum Binnenfeld 10",
    "sg:city":"Vreden",
    "sg:phone":"+49 2564/4042",
    "sg:postcode":"48691",
    "sg:province":"Nordrhein-Westfalen",
    "wof:name":"Agnes Resing Hebamme",
    "wof:placetype":"venue"
},
  "geometry": {"coordinates":[6.807872,52.034237],"type":"Point"}
}