{
  "type": "Feature",
  "properties": {
    "iso:country":"DE",
    "sg:address":"Am Eichw\u00e4ldchen 49",
    "sg:city":"Leidersbach",
    "sg:phone":"+49 6028/996536",
    "sg:postcode":"63849",
    "sg:province":"Bayern",
    "wof:name":"M. G\u00f6bel Elektroinstallation",
    "wof:placetype":"venue"
},
  "geometry": {"coordinates":[9.242769,49.896965],"type":"Point"}
}