{
  "type": "Feature",
  "properties": {
    "iso:country":"DE",
    "sg:address":"Goldsternstr. 55",
    "sg:city":"Leipzig",
    "sg:phone":"+49 341/2511592",
    "sg:postcode":"04329",
    "sg:province":"Sachsen",
    "wof:name":"Joachim M\u00fcller Patentanwalt",
    "wof:placetype":"venue"
},
  "geometry": {"coordinates":[12.4597263336,51.3571548462],"type":"Point"}
}