{
  "type": "Feature",
  "properties": {
    "iso:country":"DE",
    "sg:address":"Wotanstr. 65",
    "sg:city":"Mannheim",
    "sg:phone":"+49 621/753692",
    "sg:postcode":"68305",
    "sg:province":"Baden-W\u00fcrttemberg",
    "wof:name":"Walter Braun Steuerberater Und",
    "wof:placetype":"venue"
},
  "geometry": {"coordinates":[8.5000915527,49.5266876221],"type":"Point"}
}