{
  "type": "Feature",
  "properties": {
    "iso:country":"DE",
    "sg:address":"Hohfuhrstr. 34",
    "sg:city":"L\u00fcdenscheid",
    "sg:phone":"+49 2351/25001",
    "sg:postcode":"58509",
    "sg:province":"Nordrhein-Westfalen",
    "wof:name":"Kirchenkreis L\u00fcdenscheid",
    "wof:placetype":"venue"
},
  "geometry": {"coordinates":[7.6261281967,51.2130088806],"type":"Point"}
}