{
  "type": "Feature",
  "properties": {
    "iso:country":"DE",
    "sg:address":"Konrad-Adenauer-Allee 1",
    "sg:city":"Nidderau",
    "sg:phone":"+49 6187/22133",
    "sg:postcode":"61130",
    "sg:province":"Hessen",
    "wof:name":"Aral Ag",
    "wof:placetype":"venue"
},
  "geometry": {"coordinates":[8.8633499146,50.2334671021],"type":"Point"}
}