{
  "type": "Feature",
  "properties": {
    "iso:country":"DE",
    "sg:address":"Hauptstr. 147",
    "sg:city":"Gro\u00dfschirma",
    "sg:phone":"+49 37328/7115",
    "sg:postcode":"09603",
    "sg:province":"Sachsen",
    "wof:name":"M. Teuchert",
    "wof:placetype":"venue"
},
  "geometry": {"coordinates":[13.270233,50.965668],"type":"Point"}
}