{
  "type": "Feature",
  "properties": {
    "iso:country":"DE",
    "sg:address":"Friedrich-Naumann-Platz 10",
    "sg:city":"F\u00fcrstenwalde",
    "sg:phone":"+49 3361/307679",
    "sg:postcode":"15517",
    "sg:province":"Brandenburg",
    "wof:name":"Arka Immobilien Und Hausverwaltung Gmbh",
    "wof:placetype":"venue"
},
  "geometry": {"coordinates":[14.064146,52.348011],"type":"Point"}
}