{
  "type": "Feature",
  "properties": {
    "iso:country":"DE",
    "sg:address":"Graslitzer Str. 30",
    "sg:city":"Geretsried",
    "sg:phone":"+49 8171/6829",
    "sg:postcode":"82538",
    "sg:province":"Bayern",
    "wof:name":"Kolbenheyer-archiv Bibliothek",
    "wof:placetype":"venue"
},
  "geometry": {"coordinates":[11.463115,47.876171],"type":"Point"}
}