{
  "type": "Feature",
  "properties": {
    "iso:country":"DE",
    "sg:address":"Hauptstr. 48",
    "sg:city":"Gerolfingen",
    "sg:phone":"+49 9854/380",
    "sg:postcode":"91726",
    "sg:province":"Bayern",
    "wof:name":"Friedrich R\u00f6tter",
    "wof:placetype":"venue"
},
  "geometry": {"coordinates":[10.505699,49.054466],"type":"Point"}
}