{
  "type": "Feature",
  "properties": {
    "iso:country":"DE",
    "sg:address":"Am Pfuhl 11",
    "sg:city":"Berlin",
    "sg:phone":"+49 30/7734875",
    "sg:postcode":"12209",
    "sg:province":"Berlin",
    "wof:name":"M. A. Stockhausen Finanzberater",
    "wof:placetype":"venue"
},
  "geometry": {"coordinates":[13.3246898651,52.4202156067],"type":"Point"}
}