{
  "type": "Feature",
  "properties": {
    "iso:country":"DE",
    "sg:address":"Senefelderstr 17",
    "sg:city":"R\u00f6dermark",
    "sg:phone":"+49 6074/85220",
    "sg:postcode":"63322",
    "sg:province":"Hessen",
    "wof:name":"Sinotec Sicherheitssysteme Gmbh",
    "wof:placetype":"venue"
},
  "geometry": {"coordinates":[8.8260259628,49.9697990417],"type":"Point"}
}