{
  "type": "Feature",
  "properties": {
    "iso:country":"DE",
    "sg:address":"Tauentzienstr. 20",
    "sg:city":"Berlin",
    "sg:postcode":"10789",
    "sg:province":"Berlin",
    "wof:name":"Hildebrand",
    "wof:placetype":"venue"
},
  "geometry": {"coordinates":[13.3401041031,52.5025444031],"type":"Point"}
}