{
  "type": "Feature",
  "properties": {
    "iso:country":"DE",
    "sg:address":"Marktberg 18",
    "sg:city":"Prenzlau",
    "sg:phone":"+49 3984/801329",
    "sg:postcode":"17291",
    "sg:province":"Brandenburg",
    "wof:name":"Irmeli Paetsch",
    "wof:placetype":"venue"
},
  "geometry": {"coordinates":[13.8580284119,53.3134231567],"type":"Point"}
}