{
  "type": "Feature",
  "properties": {
    "iso:country":"DE",
    "sg:address":"Eisenbahnstr. 68",
    "sg:city":"Freiburg",
    "sg:phone":"+49 761/36543",
    "sg:postcode":"79098",
    "sg:province":"Baden-W\u00fcrttemberg",
    "wof:name":"Im Iduna Haus",
    "wof:placetype":"venue"
},
  "geometry": {"coordinates":[7.842924118,47.9973487854],"type":"Point"}
}