{
  "type": "Feature",
  "properties": {
    "iso:country":"DE",
    "sg:address":"Goldsternstr. 8",
    "sg:city":"Hamm",
    "sg:phone":"+49 2381/673187",
    "sg:postcode":"59073",
    "sg:province":"Nordrhein-Westfalen",
    "wof:name":"Siegmund Cichon",
    "wof:placetype":"venue"
},
  "geometry": {"coordinates":[7.819103,51.717335],"type":"Point"}
}