{
  "type": "Feature",
  "properties": {
    "iso:country":"DE",
    "sg:address":"Augustusburger Str. 41",
    "sg:city":"Oederan",
    "sg:postcode":"09569",
    "sg:province":"Sachsen",
    "wof:name":"Zimmerrei Und Holzbau Rothe Gmbh",
    "wof:placetype":"venue"
},
  "geometry": {"coordinates":[13.1657552719,50.858833313],"type":"Point"}
}