{
  "type": "Feature",
  "properties": {
    "iso:country":"DE",
    "sg:address":"Matthias-Zimmermann-Str. 14",
    "sg:city":"Simmerath",
    "sg:phone":"+49 2473/6530",
    "sg:postcode":"52152",
    "sg:province":"Nordrhein-Westfalen",
    "wof:name":"Christian T\u00e4chl",
    "wof:placetype":"venue"
},
  "geometry": {"coordinates":[6.309519,50.609425],"type":"Point"}
}