{
  "type": "Feature",
  "properties": {
    "iso:country":"DE",
    "sg:address":"Schreinerweg 5",
    "sg:city":"Lindlar",
    "sg:phone":"+49 2266/3798",
    "sg:postcode":"51789",
    "sg:province":"Nordrhein-Westfalen",
    "wof:name":"F\u00f6rster Sondermaschinen Gmbh",
    "wof:placetype":"venue"
},
  "geometry": {"coordinates":[7.4125890732,51.026599884],"type":"Point"}
}