{
  "type": "Feature",
  "properties": {
    "iso:country":"DE",
    "sg:address":"Kupfergrubenweg 3",
    "sg:city":"Feilitzsch",
    "sg:phone":"+49 9295/555",
    "sg:postcode":"95183",
    "sg:province":"Bayern",
    "wof:name":"W. Stadlinger & Rauh Inh. Gerhard Rauh",
    "wof:placetype":"venue"
},
  "geometry": {"coordinates":[11.9334363937,50.3885421753],"type":"Point"}
}