{
  "type": "Feature",
  "properties": {
    "iso:country":"DE",
    "sg:address":"Simmisgasse 2",
    "sg:city":"Laupheim",
    "sg:phone":"+49 7392/10746",
    "sg:postcode":"88471",
    "sg:province":"Baden-W\u00fcrttemberg",
    "wof:name":"Akropolis Grill",
    "wof:placetype":"venue"
},
  "geometry": {"coordinates":[9.8770847321,48.2294769287],"type":"Point"}
}