{
  "type": "Feature",
  "properties": {
    "iso:country":"DE",
    "sg:address":"Im Langgewann 85",
    "sg:city":"Weinheim",
    "sg:phone":"+49 6201/53649",
    "sg:postcode":"69469",
    "sg:province":"Baden-W\u00fcrttemberg",
    "wof:name":"Esw Finanzberatung Und -vermittlung Gmbh",
    "wof:placetype":"venue"
},
  "geometry": {"coordinates":[8.6631555557,49.5367851257],"type":"Point"}
}