{
  "type": "Feature",
  "properties": {
    "iso:country":"DE",
    "sg:address":"Hattinger Str. 24",
    "sg:city":"Sprockh\u00f6vel",
    "sg:phone":"+49 2324/73495",
    "sg:postcode":"45549",
    "sg:province":"Nordrhein-Westfalen",
    "wof:name":"Karl Friehe Gmbh",
    "wof:placetype":"venue"
},
  "geometry": {"coordinates":[7.2472457886,51.3716773987],"type":"Point"}
}