{
  "type": "Feature",
  "properties": {
    "iso:country":"DE",
    "sg:address":"Max-Planck-Str. 1",
    "sg:city":"Wurmlingen",
    "sg:phone":"+49 7461/72072",
    "sg:postcode":"78573",
    "sg:province":"Baden-W\u00fcrttemberg",
    "wof:name":"Hauschel & Sohn Gmbh",
    "wof:placetype":"venue"
},
  "geometry": {"coordinates":[8.7775249481,47.9992408752],"type":"Point"}
}