{
  "type": "Feature",
  "properties": {
    "iso:country":"DE",
    "sg:address":"Kirchplatz 5",
    "sg:city":"Weyhe",
    "sg:phone":"+49 4203/6448",
    "sg:postcode":"28844",
    "sg:province":"Niedersachsen",
    "wof:name":"Ev. Pfarramt Weyhe",
    "wof:placetype":"venue"
},
  "geometry": {"coordinates":[8.8777856827,52.9946022034],"type":"Point"}
}