{
  "type": "Feature",
  "properties": {
    "iso:country":"DE",
    "sg:address":"Heidelberger Landstr. 77 a",
    "sg:city":"Darmstadt",
    "sg:phone":"+49 6151/52782",
    "sg:postcode":"64297",
    "sg:province":"Hessen",
    "wof:name":"Bernd Heesen",
    "wof:placetype":"venue"
},
  "geometry": {"coordinates":[8.6449604034,49.8339500427],"type":"Point"}
}