{
  "type": "Feature",
  "properties": {
    "iso:country":"DE",
    "sg:address":"Friedenstr. 39",
    "sg:city":"W\u00fcrzburg",
    "sg:phone":"+49 931/12215",
    "sg:postcode":"97072",
    "sg:province":"Bayern",
    "wof:name":"Hvk Gesellschaft F\u00fcr Verm\u00f6gensverwaltung Mbh",
    "wof:placetype":"venue"
},
  "geometry": {"coordinates":[9.9389314651,49.7853546143],"type":"Point"}
}