{
  "type": "Feature",
  "properties": {
    "iso:country":"DE",
    "sg:address":"Oberstr. 4951",
    "sg:city":"R\u00fcdesheim am Rhein",
    "sg:phone":"+49 6722/2547",
    "sg:postcode":"65385",
    "sg:province":"Hessen",
    "wof:name":"Julius Trapp & Co. Gmbh",
    "wof:placetype":"venue"
},
  "geometry": {"coordinates":[7.9249300957,49.9808387756],"type":"Point"}
}