{
  "type": "Feature",
  "properties": {
    "iso:country":"DE",
    "sg:address":"Lange Str. 27",
    "sg:city":"Emstek",
    "sg:phone":"+49 4473/6400",
    "sg:postcode":"49685",
    "sg:province":"Niedersachsen",
    "wof:name":"Nikis Dreil\u00e4nder Spezialit\u00e4ten",
    "wof:placetype":"venue"
},
  "geometry": {"coordinates":[8.1614704132,52.8333320618],"type":"Point"}
}