{
  "type": "Feature",
  "properties": {
    "iso:country":"DE",
    "sg:address":"Volbehrstr. 24",
    "sg:city":"N\u00fcrnberg",
    "sg:phone":"+49 911/511555",
    "sg:postcode":"90491",
    "sg:province":"Bayern",
    "wof:name":"Tampico Trading Hartmut C. Hentschel Gmbh",
    "wof:placetype":"venue"
},
  "geometry": {"coordinates":[11.1243124008,49.4757118225],"type":"Point"}
}