{
  "type": "Feature",
  "properties": {
    "iso:country":"DE",
    "sg:address":"Kurf\u00fcrstendamm 218",
    "sg:city":"Berlin",
    "sg:phone":"+49 30/8823271",
    "sg:postcode":"10719",
    "sg:province":"Berlin",
    "wof:name":"China-restaurant Ho Lin Wah",
    "wof:placetype":"venue"
},
  "geometry": {"coordinates":[13.3280553818,52.502872467],"type":"Point"}
}