{
  "type": "Feature",
  "properties": {
    "iso:country":"DE",
    "sg:address":"Ringstr. 80",
    "sg:city":"Kamp-Lintfort",
    "sg:phone":"+49 2842/5858",
    "sg:postcode":"47475",
    "sg:province":"Nordrhein-Westfalen",
    "wof:name":"H. H\u00fcsken",
    "wof:placetype":"venue"
},
  "geometry": {"coordinates":[6.543251,51.502338],"type":"Point"}
}