{
  "type": "Feature",
  "properties": {
    "iso:country":"DE",
    "sg:address":"Am Alten Rathaus 12",
    "sg:city":"Mudau",
    "sg:phone":"+49 6284/95377",
    "sg:postcode":"69427",
    "sg:province":"Baden-W\u00fcrttemberg",
    "wof:name":"H. Jungh\u00e4nel",
    "wof:placetype":"venue"
},
  "geometry": {"coordinates":[9.2048921585,49.5342140198],"type":"Point"}
}