{
  "type": "Feature",
  "properties": {
    "iso:country":"DE",
    "sg:address":"Gutenbergstr. 31",
    "sg:city":"Lilienthal",
    "sg:postcode":"28865",
    "sg:province":"Niedersachsen",
    "wof:name":"Kastens & Knauer Gmbh",
    "wof:placetype":"venue"
},
  "geometry": {"coordinates":[8.902437,53.155548],"type":"Point"}
}