{
  "type": "Feature",
  "properties": {
    "iso:country":"DE",
    "sg:address":"Ahornstr. 14",
    "sg:city":"Baienfurt",
    "sg:phone":"+49 751/41953",
    "sg:postcode":"88255",
    "sg:province":"Baden-W\u00fcrttemberg",
    "wof:name":"I. Stotz Heissmangel",
    "wof:placetype":"venue"
},
  "geometry": {"coordinates":[9.6443634033,47.8251991272],"type":"Point"}
}