{
  "type": "Feature",
  "properties": {
    "iso:country":"DE",
    "sg:address":"K\u00f6nigsberger Str. 4s",
    "sg:city":"Frankfurt",
    "sg:phone":"+49 69/7958501",
    "sg:postcode":"60487",
    "sg:province":"Hessen",
    "wof:name":"Multiprint Georg Grandpierre Graf.betriebe F.mehrfarbigen",
    "wof:placetype":"venue"
},
  "geometry": {"coordinates":[8.6280441284,50.1289100647],"type":"Point"}
}