{
  "type": "Feature",
  "properties": {
    "iso:country":"DE",
    "sg:address":"Klingenderstr. 18 a",
    "sg:city":"Paderborn",
    "sg:phone":"+49 5251/15740",
    "sg:postcode":"33100",
    "sg:province":"Nordrhein-Westfalen",
    "wof:name":"Dr. Volker Bastert Steuerberater",
    "wof:placetype":"venue"
},
  "geometry": {"coordinates":[8.7765026093,51.7293891907],"type":"Point"}
}