{
  "type": "Feature",
  "properties": {
    "iso:country":"DE",
    "sg:address":"Orkener Str. 41",
    "sg:city":"Grevenbroich",
    "sg:phone":"+49 2181/68989",
    "sg:postcode":"41515",
    "sg:province":"Nordrhein-Westfalen",
    "wof:name":"Hubert Wi\u00dfdorf",
    "wof:placetype":"venue"
},
  "geometry": {"coordinates":[6.5818219185,51.0945167542],"type":"Point"}
}