{
  "type": "Feature",
  "properties": {
    "iso:country":"DE",
    "sg:address":"Mettinger Str. 26",
    "sg:city":"Esslingen",
    "sg:phone":"+49 711/3517933",
    "sg:postcode":"73728",
    "sg:province":"Baden-W\u00fcrttemberg",
    "wof:name":"D. Seebe",
    "wof:placetype":"venue"
},
  "geometry": {"coordinates":[9.2977733612,48.7433815002],"type":"Point"}
}