{
  "type": "Feature",
  "properties": {
    "iso:country":"DE",
    "sg:address":"Poststr. 3",
    "sg:city":"Meerane",
    "sg:phone":"+49 3764/2275",
    "sg:postcode":"08393",
    "sg:province":"Sachsen",
    "wof:name":"Friedrich",
    "wof:placetype":"venue"
},
  "geometry": {"coordinates":[12.462351799,50.8514213562],"type":"Point"}
}