{
  "type": "Feature",
  "properties": {
    "iso:country":"DE",
    "sg:address":"Adelsreuter Str. 21",
    "sg:city":"Ravensburg",
    "sg:phone":"+49 751/93342",
    "sg:postcode":"88213",
    "sg:province":"Baden-W\u00fcrttemberg",
    "wof:name":"Wolfram Klein",
    "wof:placetype":"venue"
},
  "geometry": {"coordinates":[9.5404548645,47.7580871582],"type":"Point"}
}