{
  "type": "Feature",
  "properties": {
    "iso:country":"DE",
    "sg:address":"Johann-Breidenassel-Str. 10",
    "sg:city":"Lindlar",
    "sg:phone":"+49 2206/2713",
    "sg:postcode":"51789",
    "sg:province":"Nordrhein-Westfalen",
    "wof:name":"Geselligkeitsverein Der Dorfgemeinschaft Hohkeppel",
    "wof:placetype":"venue"
},
  "geometry": {"coordinates":[7.3072099686,50.9803199768],"type":"Point"}
}