{
  "type": "Feature",
  "properties": {
    "iso:country":"DE",
    "sg:address":"Schlo\u00dfstrasse 2",
    "sg:city":"Isselburg",
    "sg:postcode":"46419",
    "sg:province":"Nordrhein-Westfalen",
    "wof:name":"Mwd-net",
    "wof:placetype":"venue"
},
  "geometry": {"coordinates":[6.4268321991,51.8460006714],"type":"Point"}
}