{
  "type": "Feature",
  "properties": {
    "iso:country":"DE",
    "sg:address":"Lessingstr. 1",
    "sg:city":"M\u00fcnchen",
    "sg:phone":"+49 89/530044",
    "sg:postcode":"80336",
    "sg:province":"Bayern",
    "wof:name":"Jugendaufbauwerk Bayern",
    "wof:placetype":"venue"
},
  "geometry": {"coordinates":[11.5577278137,48.1331253052],"type":"Point"}
}