{
  "type": "Feature",
  "properties": {
    "iso:country":"DE",
    "sg:address":"Tillystr. 8",
    "sg:city":"Hannover",
    "sg:phone":"+49 511/5463239",
    "sg:postcode":"30459",
    "sg:province":"Niedersachsen",
    "wof:name":"Acryl Shop Bernadette Zettelmann",
    "wof:placetype":"venue"
},
  "geometry": {"coordinates":[9.718761,52.339317],"type":"Point"}
}