{
  "type": "Feature",
  "properties": {
    "iso:country":"DE",
    "sg:address":"Herberichstr. 39 b",
    "sg:city":"Koblenz",
    "sg:phone":"+49 261/83666",
    "sg:postcode":"56070",
    "sg:province":"Rheinland-Pfalz",
    "wof:name":"Peter W. Krumscheid",
    "wof:placetype":"venue"
},
  "geometry": {"coordinates":[7.605481,50.375053],"type":"Point"}
}