{
  "type": "Feature",
  "properties": {
    "iso:country":"DE",
    "sg:address":"Schulstr. 11",
    "sg:city":"Kirchenlamitz",
    "sg:phone":"+49 9285/1281",
    "sg:postcode":"95158",
    "sg:province":"Bayern",
    "wof:name":"Sparkasse Fichtelgebirge",
    "wof:placetype":"venue"
},
  "geometry": {"coordinates":[11.94973,50.153481],"type":"Point"}
}