{
  "type": "Feature",
  "properties": {
    "iso:country":"DE",
    "sg:address":"Umgehungsstrasse",
    "sg:city":"Dillingen",
    "sg:phone":"+49 6831/74060",
    "sg:postcode":"66763",
    "sg:province":"Saarland",
    "wof:name":"Fertigbeton Saar Gmbh & Co. Kg",
    "wof:placetype":"venue"
},
  "geometry": {"coordinates":[6.71863,49.35815],"type":"Point"}
}