{
  "type": "Feature",
  "properties": {
    "iso:country":"DE",
    "sg:address":"Bachstr. 1",
    "sg:city":"Berlin",
    "sg:postcode":"10555",
    "sg:province":"Berlin",
    "wof:name":"Redaktion Die Diakonie- Schwester",
    "wof:placetype":"venue"
},
  "geometry": {"coordinates":[13.3393039703,52.5186729431],"type":"Point"}
}