{
  "type": "Feature",
  "properties": {
    "iso:country":"DE",
    "sg:address":"Sanger Dyck 7",
    "sg:city":"Straelen",
    "sg:phone":"+49 2834/8697",
    "sg:postcode":"47638",
    "sg:province":"Nordrhein-Westfalen",
    "wof:name":"Goutherm Maschinenbau Gmbh",
    "wof:placetype":"venue"
},
  "geometry": {"coordinates":[6.270996,51.431572],"type":"Point"}
}