{
  "type": "Feature",
  "properties": {
    "iso:country":"DE",
    "sg:address":"Diedrich-Wilkens-Str. 27",
    "sg:city":"Bremen",
    "sg:phone":"+49 421/450170",
    "sg:postcode":"28309",
    "sg:province":"Bremen",
    "wof:name":"Karl Osterhorn Gmbh",
    "wof:placetype":"venue"
},
  "geometry": {"coordinates":[8.8890352249,53.0577163696],"type":"Point"}
}