{
  "type": "Feature",
  "properties": {
    "iso:country":"DE",
    "sg:address":"Becksteiner Str. 24",
    "sg:city":"Lauda-K\u00f6nigshofen",
    "sg:phone":"+49 9343/7440",
    "sg:postcode":"97922",
    "sg:province":"Baden-W\u00fcrttemberg",
    "wof:name":"Buchner Und Dosch",
    "wof:placetype":"venue"
},
  "geometry": {"coordinates":[9.702249527,49.5659141541],"type":"Point"}
}