{
  "type": "Feature",
  "properties": {
    "iso:country":"DE",
    "sg:address":"Im Tiefenbach 9",
    "sg:city":"Saarbr\u00fccken",
    "sg:phone":"+49 6893/986651",
    "sg:postcode":"66130",
    "sg:province":"Saarland",
    "wof:name":"Gunter Fette Rechtsanwalt",
    "wof:placetype":"venue"
},
  "geometry": {"coordinates":[7.0637598038,49.1938095093],"type":"Point"}
}