{
  "type": "Feature",
  "properties": {
    "iso:country":"DE",
    "sg:address":"Planstr. 6",
    "sg:city":"Bad Harzburg",
    "sg:phone":"+49 5322/81101",
    "sg:postcode":"38667",
    "sg:province":"Niedersachsen",
    "wof:name":"Hermann Beer",
    "wof:placetype":"venue"
},
  "geometry": {"coordinates":[10.5210819244,51.9097099304],"type":"Point"}
}