{
  "type": "Feature",
  "properties": {
    "iso:country":"DE",
    "sg:address":"Aussiger Str. 4 a",
    "sg:city":"Regensburg",
    "sg:postcode":"93057",
    "sg:province":"Bayern",
    "wof:name":"Nuclearmontaj S. A. Ag Zw. Ndl. Regensburg",
    "wof:placetype":"venue"
},
  "geometry": {"coordinates":[12.123803,49.040993],"type":"Point"}
}