{
  "type": "Feature",
  "properties": {
    "iso:country":"DE",
    "sg:address":"Gr\u00fcnfeldstr. 18",
    "sg:city":"Rosenheim",
    "sg:phone":"+49 8031/67800",
    "sg:postcode":"83026",
    "sg:province":"Bayern",
    "wof:name":"M. \u00dcbler Steuerberater",
    "wof:placetype":"venue"
},
  "geometry": {"coordinates":[12.1129837036,47.8289451599],"type":"Point"}
}