{
  "type": "Feature",
  "properties": {
    "iso:country":"DE",
    "sg:address":"Friedhofstr. 150",
    "sg:city":"M\u00fclheim",
    "sg:phone":"+49 208/52237",
    "sg:postcode":"45478",
    "sg:province":"Nordrhein-Westfalen",
    "wof:name":"Friedrich-karl Ufermann",
    "wof:placetype":"venue"
},
  "geometry": {"coordinates":[6.8352608681,51.4198112488],"type":"Point"}
}