{
  "type": "Feature",
  "properties": {
    "iso:country":"DE",
    "sg:address":"Lohhof 5",
    "sg:city":"Tiefenbach",
    "sg:phone":"+49 8509/91080",
    "sg:postcode":"94113",
    "sg:province":"Bayern",
    "wof:name":"Autosportclub Tiefenbach E.v.",
    "wof:placetype":"venue"
},
  "geometry": {"coordinates":[13.410911,48.637665],"type":"Point"}
}