{
  "type": "Feature",
  "properties": {
    "iso:country":"DE",
    "sg:address":"Am Breiten Rain 18",
    "sg:city":"Memmelsdorf",
    "sg:phone":"+49 951/406660",
    "sg:postcode":"96117",
    "sg:province":"Bayern",
    "wof:name":"Spiel Media Verlag Gmbh",
    "wof:placetype":"venue"
},
  "geometry": {"coordinates":[10.957690239,49.9306716919],"type":"Point"}
}