{
  "type": "Feature",
  "properties": {
    "iso:country":"DE",
    "sg:address":"Kaiserstr. 69",
    "sg:city":"Waldbr\u00f6l",
    "sg:phone":"+49 2291/830",
    "sg:postcode":"51545",
    "sg:province":"Nordrhein-Westfalen",
    "wof:name":"Kreissparkasse",
    "wof:placetype":"venue"
},
  "geometry": {"coordinates":[7.62219,50.878571],"type":"Point"}
}