{
  "type": "Feature",
  "properties": {
    "iso:country":"DE",
    "sg:address":"Sredzkistr. 47",
    "sg:city":"Berlin",
    "sg:phone":"+49 30/4410793",
    "sg:postcode":"10435",
    "sg:province":"Berlin",
    "wof:name":"Prof. K. Heuer Dr. S. Friedl\u00e4nder",
    "wof:placetype":"venue"
},
  "geometry": {"coordinates":[13.4193553925,52.5383682251],"type":"Point"}
}