{
  "type": "Feature",
  "properties": {
    "iso:country":"DE",
    "sg:address":"Heckenrosenweg 8",
    "sg:city":"Pfedelbach",
    "sg:phone":"+49 7941/98228",
    "sg:postcode":"74629",
    "sg:province":"Baden-W\u00fcrttemberg",
    "wof:name":"Industrievertretungen Hurrle E. K.",
    "wof:placetype":"venue"
},
  "geometry": {"coordinates":[9.4897432327,49.1803588867],"type":"Point"}
}