{
  "type": "Feature",
  "properties": {
    "iso:country":"DE",
    "sg:address":"Obermauerstr. 1",
    "sg:city":"Duisburg",
    "sg:phone":"+49 203/20935",
    "sg:postcode":"47051",
    "sg:province":"Nordrhein-Westfalen",
    "wof:name":"China Restaurant Wuhan",
    "wof:placetype":"venue"
},
  "geometry": {"coordinates":[6.7642807961,51.4340133667],"type":"Point"}
}