{
  "type": "Feature",
  "properties": {
    "iso:country":"DE",
    "sg:address":"Rotenackerweg 12",
    "sg:city":"Bad Rappenau",
    "sg:phone":"+49 7266/794",
    "sg:postcode":"74906",
    "sg:province":"Baden-W\u00fcrttemberg",
    "wof:name":"Werner Gruber Ingenieur",
    "wof:placetype":"venue"
},
  "geometry": {"coordinates":[8.9996109009,49.2296981812],"type":"Point"}
}