{
  "type": "Feature",
  "properties": {
    "iso:country":"DE",
    "sg:address":"Gottfried-K\u00f6lwel-Platz 5",
    "sg:city":"Beratzhausen",
    "sg:phone":"+49 9493/94030",
    "sg:postcode":"93176",
    "sg:province":"Bayern",
    "wof:name":"Elektro Thaler Karl Thaler Gmbh & Co. Kg",
    "wof:placetype":"venue"
},
  "geometry": {"coordinates":[11.8058156967,49.0971641541],"type":"Point"}
}