{
  "type": "Feature",
  "properties": {
    "iso:country":"DE",
    "sg:address":"Riedweg 2-4",
    "sg:city":"Br\u00e4unlingen",
    "sg:postcode":"78199",
    "sg:province":"Baden-W\u00fcrttemberg",
    "wof:name":"Fesenmeyer - M\u00fchle Inh. Gerhard Fesenmeyer",
    "wof:placetype":"venue"
},
  "geometry": {"coordinates":[8.4504852295,47.9272880554],"type":"Point"}
}