{
  "type": "Feature",
  "properties": {
    "iso:country":"DE",
    "sg:address":"Am Alten Kaninsberg 16",
    "sg:city":"W\u00fcrselen",
    "sg:phone":"+49 2405/60060",
    "sg:postcode":"52146",
    "sg:province":"Nordrhein-Westfalen",
    "wof:name":"I-center Elektrogro\u00dfhandel Gmbh & Co.",
    "wof:placetype":"venue"
},
  "geometry": {"coordinates":[6.1396298409,50.8091049194],"type":"Point"}
}