{
  "type": "Feature",
  "properties": {
    "iso:country":"DE",
    "sg:address":"Buxtehuder Str. 43",
    "sg:city":"Jork",
    "sg:postcode":"21635",
    "sg:province":"Niedersachsen",
    "wof:name":"Computer Und Graphik Services Dipl.-ing. Joachim Schmitt-",
    "wof:placetype":"venue"
},
  "geometry": {"coordinates":[9.7279109955,53.5032806396],"type":"Point"}
}