{
  "type": "Feature",
  "properties": {
    "iso:country":"DE",
    "sg:address":"Lise-Meitner-Str. 20",
    "sg:city":"Flensburg",
    "sg:phone":"+49 4946/190420",
    "sg:postcode":"24941",
    "sg:province":"Schleswig-Holstein",
    "wof:name":"Otto J\u00d6rgensen & Sohn Gmbh",
    "wof:placetype":"venue"
},
  "geometry": {"coordinates":[9.440276,54.760696],"type":"Point"}
}