{
  "type": "Feature",
  "properties": {
    "iso:country":"DE",
    "sg:address":"Dierdorfer Str. 1",
    "sg:city":"Gro\u00dfmaischeid",
    "sg:phone":"+49 2689/5264",
    "sg:postcode":"56276",
    "sg:province":"Rheinland-Pfalz",
    "wof:name":"Franz-josef Kern",
    "wof:placetype":"venue"
},
  "geometry": {"coordinates":[7.633835,50.505177],"type":"Point"}
}