{
  "type": "Feature",
  "properties": {
    "iso:country":"DE",
    "sg:address":"N\u00fctzer Weg 7",
    "sg:city":"Lentf\u00f6hrden",
    "sg:phone":"+49 4192/2831",
    "sg:postcode":"24632",
    "sg:province":"Schleswig-Holstein",
    "wof:name":"Heinz Pfeiffer",
    "wof:placetype":"venue"
},
  "geometry": {"coordinates":[9.890823,53.871708],"type":"Point"}
}