{
  "type": "Feature",
  "properties": {
    "iso:country":"DE",
    "sg:address":"Gartenstr. 5",
    "sg:city":"Bad Klosterlausnitz",
    "sg:phone":"+49 36601/83055",
    "sg:postcode":"07639",
    "sg:province":"Th\u00fcringen",
    "wof:name":"Pension Gertrud Sachse",
    "wof:placetype":"venue"
},
  "geometry": {"coordinates":[11.8675069809,50.9195365906],"type":"Point"}
}