{
  "type": "Feature",
  "properties": {
    "iso:country":"DE",
    "sg:address":"Sperbergasse 3",
    "sg:city":"Friedrichshafen",
    "sg:phone":"+49 7541/31817",
    "sg:postcode":"88046",
    "sg:province":"Baden-W\u00fcrttemberg",
    "wof:name":"Werne Gmbh",
    "wof:placetype":"venue"
},
  "geometry": {"coordinates":[9.4951019287,47.6585502625],"type":"Point"}
}