{
  "type": "Feature",
  "properties": {
    "iso:country":"DE",
    "sg:address":"Diemershaldenstr. 17",
    "sg:city":"Stuttgart",
    "sg:phone":"+49 711/245561",
    "sg:postcode":"70184",
    "sg:province":"Baden-W\u00fcrttemberg",
    "wof:name":"Wohnbau Eckert Kg",
    "wof:placetype":"venue"
},
  "geometry": {"coordinates":[9.190867,48.776985],"type":"Point"}
}