{
  "type": "Feature",
  "properties": {
    "iso:country":"DE",
    "sg:address":"Siedlungsstr. 2",
    "sg:city":"Vohburg",
    "sg:phone":"+49 8457/1256",
    "sg:postcode":"85088",
    "sg:province":"Bayern",
    "wof:name":"Hans Reith",
    "wof:placetype":"venue"
},
  "geometry": {"coordinates":[11.6179456711,48.7623023987],"type":"Point"}
}