{
  "type": "Feature",
  "properties": {
    "iso:country":"DE",
    "sg:address":"Lindenstr. 33",
    "sg:city":"Bad Essen",
    "sg:phone":"+49 5472/6514",
    "sg:postcode":"49152",
    "sg:province":"Niedersachsen",
    "wof:name":"Blumen- Und Fr\u00fcchtehaus Fritz Honermeyer",
    "wof:placetype":"venue"
},
  "geometry": {"coordinates":[8.3419303894,52.3198661804],"type":"Point"}
}