{
  "type": "Feature",
  "properties": {
    "iso:country":"DE",
    "sg:address":"Hasenbergstrasse 113",
    "sg:city":"Stuttgart",
    "sg:phone":"+49 711/6363461",
    "sg:postcode":"70176",
    "sg:province":"Baden-W\u00fcrttemberg",
    "wof:name":"Mb Design-edition",
    "wof:placetype":"venue"
},
  "geometry": {"coordinates":[9.1559848785,48.7780570984],"type":"Point"}
}