{
  "type": "Feature",
  "properties": {
    "iso:country":"DE",
    "sg:address":"Uhlandstr. 12",
    "sg:city":"Aichhalden",
    "sg:phone":"+49 7422/50050",
    "sg:postcode":"78733",
    "sg:province":"Baden-W\u00fcrttemberg",
    "wof:name":"Linke & Partner",
    "wof:placetype":"venue"
},
  "geometry": {"coordinates":[8.3965368271,48.2721366882],"type":"Point"}
}