{
  "type": "Feature",
  "properties": {
    "iso:country":"DE",
    "sg:address":"M\u00fcnchener Str. 9",
    "sg:city":"Gro\u00df-Gerau",
    "sg:postcode":"64521",
    "sg:province":"Hessen",
    "wof:name":"G\u00fcnter Kollross Gmbh",
    "wof:placetype":"venue"
},
  "geometry": {"coordinates":[8.488948,49.935837],"type":"Point"}
}