{
  "type": "Feature",
  "properties": {
    "iso:country":"DE",
    "sg:address":"Mittelh\u00e4user Str 42",
    "sg:city":"Erfurt",
    "sg:phone":"+49 361/7924641",
    "sg:postcode":"99091",
    "sg:province":"Th\u00fcringen",
    "wof:name":"Sbe Sondermaschinenbau Erfurt Gmbh",
    "wof:placetype":"venue"
},
  "geometry": {"coordinates":[11.006376,51.031921],"type":"Point"}
}