{
  "type": "Feature",
  "properties": {
    "iso:country":"DE",
    "sg:address":"Mathildenstr. 67",
    "sg:city":"Einhausen",
    "sg:phone":"+49 6251/57536",
    "sg:postcode":"64683",
    "sg:province":"Hessen",
    "wof:name":"Hans-peter Flori",
    "wof:placetype":"venue"
},
  "geometry": {"coordinates":[8.5511636734,49.6706047058],"type":"Point"}
}