{
  "type": "Feature",
  "properties": {
    "iso:country":"DE",
    "sg:address":"Mittelstr. 29",
    "sg:city":"Kamen",
    "sg:phone":"+49 2307/40362",
    "sg:postcode":"59174",
    "sg:province":"Nordrhein-Westfalen",
    "wof:name":"Artur Trowe",
    "wof:placetype":"venue"
},
  "geometry": {"coordinates":[7.7098650932,51.5791702271],"type":"Point"}
}