{
  "type": "Feature",
  "properties": {
    "iso:country":"DE",
    "sg:address":"Schlachthofstr. 2-8",
    "sg:city":"Zwickau",
    "sg:phone":"+49 375/3320",
    "sg:postcode":"08058",
    "sg:province":"Sachsen",
    "wof:name":"Zsh Zwickauer System- Und Haustechnik Gmbh",
    "wof:placetype":"venue"
},
  "geometry": {"coordinates":[12.48352,50.735512],"type":"Point"}
}