{
  "type": "Feature",
  "properties": {
    "iso:country":"DE",
    "sg:address":"Neufchateaustr. 2",
    "sg:city":"Hamm",
    "sg:phone":"+49 2381/24265",
    "sg:postcode":"59077",
    "sg:province":"Nordrhein-Westfalen",
    "wof:name":"Anna Filbrich",
    "wof:placetype":"venue"
},
  "geometry": {"coordinates":[7.7439060211,51.661491394],"type":"Point"}
}