{
  "type": "Feature",
  "properties": {
    "iso:country":"DE",
    "sg:address":"Fu\u00dfbergstr. 23",
    "sg:city":"Gauting",
    "sg:phone":"+49 89/8507525",
    "sg:postcode":"82131",
    "sg:province":"Bayern",
    "wof:name":"Martin Zeil Rechtsanwalt",
    "wof:placetype":"venue"
},
  "geometry": {"coordinates":[11.3891773224,48.0716629028],"type":"Point"}
}