{
  "type": "Feature",
  "properties": {
    "iso:country":"DE",
    "sg:address":"Untergasse 18",
    "sg:city":"Marburg",
    "sg:phone":"+49 6421/25654",
    "sg:postcode":"35037",
    "sg:province":"Hessen",
    "wof:name":"Rustica",
    "wof:placetype":"venue"
},
  "geometry": {"coordinates":[8.770904541,50.8075523376],"type":"Point"}
}