{
  "type": "Feature",
  "properties": {
    "iso:country":"DE",
    "sg:address":"Martin-Kirchner-Str. 42",
    "sg:city":"Mainz",
    "sg:phone":"+49 6131/330033",
    "sg:postcode":"55128",
    "sg:province":"Rheinland-Pfalz",
    "wof:name":"Dr. Med. Kristine Reck \u00c4rztin F\u00fcr Allgemeinmedizin",
    "wof:placetype":"venue"
},
  "geometry": {"coordinates":[8.2377195358,49.9826507568],"type":"Point"}
}