{
  "type": "Feature",
  "properties": {
    "iso:country":"DE",
    "sg:address":"Zum Lachenw\u00e4ldle 7",
    "sg:city":"Pforzheim",
    "sg:phone":"+49 7231/441104",
    "sg:postcode":"75179",
    "sg:province":"Baden-W\u00fcrttemberg",
    "wof:name":"Ernst Wamsler",
    "wof:placetype":"venue"
},
  "geometry": {"coordinates":[8.6571483612,48.884853363],"type":"Point"}
}