{
  "type": "Feature",
  "properties": {
    "iso:country":"DE",
    "sg:address":"Flamweg 100",
    "sg:city":"Elmshorn",
    "sg:phone":"+49 4121/21627",
    "sg:postcode":"25335",
    "sg:province":"Schleswig-Holstein",
    "wof:name":"Flamweg-grill",
    "wof:placetype":"venue"
},
  "geometry": {"coordinates":[9.6457738876,53.7582015991],"type":"Point"}
}