{
  "type": "Feature",
  "properties": {
    "iso:country":"DE",
    "sg:address":"Ahornstr. 87",
    "sg:city":"Ergolding",
    "sg:phone":"+49 871/12427",
    "sg:postcode":"84030",
    "sg:province":"Bayern",
    "wof:name":"M & F Trocken- Und Innenausbau Gmbh",
    "wof:placetype":"venue"
},
  "geometry": {"coordinates":[12.166062,48.566704],"type":"Point"}
}