{
  "type": "Feature",
  "properties": {
    "iso:country":"DE",
    "sg:address":"Peilsteiner Str. 7",
    "sg:city":"Neukirchen",
    "sg:phone":"+49 9663/95040",
    "sg:postcode":"92259",
    "sg:province":"Bayern",
    "wof:name":"B\u00e4r",
    "wof:placetype":"venue"
},
  "geometry": {"coordinates":[11.630936,49.529453],"type":"Point"}
}