{
  "type": "Feature",
  "properties": {
    "iso:country":"DE",
    "sg:address":"Burgstr. 17",
    "sg:city":"Bad Mergentheim",
    "sg:phone":"+49 7931/52064",
    "sg:postcode":"97980",
    "sg:province":"Baden-W\u00fcrttemberg",
    "wof:name":"Vbw Gesellschaft F\u00fcr Schl\u00fcsselfertiges Bauen Gmbh",
    "wof:placetype":"venue"
},
  "geometry": {"coordinates":[9.774545,49.49107],"type":"Point"}
}