{
  "type": "Feature",
  "properties": {
    "iso:country":"DE",
    "sg:address":"Hein-K\u00f6llisch-Platz 4",
    "sg:city":"Hamburg",
    "sg:phone":"+49 40/310318",
    "sg:postcode":"20359",
    "sg:province":"Hamburg",
    "wof:name":"Werner Geyer",
    "wof:placetype":"venue"
},
  "geometry": {"coordinates":[9.956988,53.547298],"type":"Point"}
}