{
  "type": "Feature",
  "properties": {
    "iso:country":"DE",
    "sg:address":"Hauptstr. 21",
    "sg:city":"R\u00e4bke",
    "sg:postcode":"38375",
    "sg:province":"Niedersachsen",
    "wof:name":"Marcus Uter Bau Gmbh",
    "wof:placetype":"venue"
},
  "geometry": {"coordinates":[10.8769493103,52.1953582764],"type":"Point"}
}