{
  "type": "Feature",
  "properties": {
    "iso:country":"DE",
    "sg:address":"D\u00fcppelstr 5b",
    "sg:city":"Vallendar",
    "sg:postcode":"56179",
    "sg:province":"Rheinland-Pfalz",
    "wof:name":"Willkommen Beim Landratskandidat Prof. Dr. Ruedige",
    "wof:placetype":"venue"
},
  "geometry": {"coordinates":[7.61961,50.39505],"type":"Point"}
}