{
  "type": "Feature",
  "properties": {
    "iso:country":"DE",
    "sg:address":"Ravensberger Str. 45",
    "sg:city":"Werther",
    "sg:phone":"+49 5203/88648",
    "sg:postcode":"33824",
    "sg:province":"Nordrhein-Westfalen",
    "wof:name":"H. Massmann Ohg Inh. Schmedtmann & Fillies",
    "wof:placetype":"venue"
},
  "geometry": {"coordinates":[8.4174556732,52.0752906799],"type":"Point"}
}