{
  "type": "Feature",
  "properties": {
    "iso:country":"DE",
    "sg:address":"Westerburger Weg 24",
    "sg:city":"Wardenburg",
    "sg:phone":"+49 4407/1875",
    "sg:postcode":"26203",
    "sg:province":"Niedersachsen",
    "wof:name":"Jochen Hoppe Bauunternehmen Gmbh",
    "wof:placetype":"venue"
},
  "geometry": {"coordinates":[8.208567,53.048141],"type":"Point"}
}