{
  "type": "Feature",
  "properties": {
    "iso:country":"DE",
    "sg:address":"Quellenweg 2",
    "sg:city":"K\u00f6nigswinter",
    "sg:phone":"+49 2223/24665",
    "sg:postcode":"53639",
    "sg:province":"Nordrhein-Westfalen",
    "wof:name":"Knut Lehrke Garten- Und",
    "wof:placetype":"venue"
},
  "geometry": {"coordinates":[7.254456,50.674252],"type":"Point"}
}