{
  "type": "Feature",
  "properties": {
    "iso:country":"DE",
    "sg:address":"Wallstr. 48",
    "sg:city":"Aurich",
    "sg:phone":"+49 4941/2029",
    "sg:postcode":"26603",
    "sg:province":"Niedersachsen",
    "wof:name":"Heinrich Heyen",
    "wof:placetype":"venue"
},
  "geometry": {"coordinates":[7.484871,53.471363],"type":"Point"}
}