{
  "type": "Feature",
  "properties": {
    "iso:country":"DE",
    "sg:address":"Erich-Weinert-Str. 37",
    "sg:city":"Guben",
    "sg:phone":"+49 3561/67753",
    "sg:postcode":"03172",
    "sg:province":"Brandenburg",
    "wof:name":"Allianz Versicherungs Ag",
    "wof:placetype":"venue"
},
  "geometry": {"coordinates":[14.6997966766,51.9458732605],"type":"Point"}
}