{
  "type": "Feature",
  "properties": {
    "iso:country":"DE",
    "sg:address":"Wilhelmstr. 74",
    "sg:city":"B\u00fcnde",
    "sg:phone":"+49 5223/5525",
    "sg:postcode":"32257",
    "sg:province":"Nordrhein-Westfalen",
    "wof:name":"Der Handytreff - Handys Und Handyzubeh\u00f6r",
    "wof:placetype":"venue"
},
  "geometry": {"coordinates":[8.5660209656,52.1993103027],"type":"Point"}
}