{
  "type": "Feature",
  "properties": {
    "iso:country":"DE",
    "sg:address":"Hauptstr. 43",
    "sg:city":"Illingen",
    "sg:phone":"+49 6825/2579",
    "sg:postcode":"66557",
    "sg:province":"Saarland",
    "wof:name":"Paul Vogel",
    "wof:placetype":"venue"
},
  "geometry": {"coordinates":[7.0513520241,49.3770027161],"type":"Point"}
}