{
  "type": "Feature",
  "properties": {
    "iso:country":"DE",
    "sg:address":"St.-Ulrich-Str. 10",
    "sg:city":"Konzell",
    "sg:phone":"+49 9963/412",
    "sg:postcode":"94357",
    "sg:province":"Bayern",
    "wof:name":"Brigitte Nusko",
    "wof:placetype":"venue"
},
  "geometry": {"coordinates":[12.70965,49.071857],"type":"Point"}
}