{
  "type": "Feature",
  "properties": {
    "iso:country":"DE",
    "sg:address":"Meister-Erwin-Stra\u00dfe 57",
    "sg:city":"Baden-Baden",
    "sg:postcode":"76534",
    "sg:province":"Baden-W\u00fcrttemberg",
    "wof:name":"Schroembgens Industrievertretung Cdh",
    "wof:placetype":"venue"
},
  "geometry": {"coordinates":[8.1728658676,48.7275352478],"type":"Point"}
}