{
  "type": "Feature",
  "properties": {
    "iso:country":"DE",
    "sg:address":"Krahnstr. 17-18",
    "sg:city":"Osnabr\u00fcck",
    "sg:phone":"+49 541/338350",
    "sg:postcode":"49074",
    "sg:province":"Niedersachsen",
    "wof:name":"Atlantic Travel Service Verwaltungsges. Mbh",
    "wof:placetype":"venue"
},
  "geometry": {"coordinates":[8.042575,52.276119],"type":"Point"}
}