{
  "type": "Feature",
  "properties": {
    "iso:country":"DE",
    "sg:address":"Udenh\u00e4user Str. 19",
    "sg:city":"Grebenstein",
    "sg:phone":"+49 5674/1327",
    "sg:postcode":"34393",
    "sg:province":"Hessen",
    "wof:name":"Mannshausen Schmiede Landmaschinen Gmbh",
    "wof:placetype":"venue"
},
  "geometry": {"coordinates":[9.418202,51.445389],"type":"Point"}
}