{
  "type": "Feature",
  "properties": {
    "iso:country":"DE",
    "sg:address":"Hauptstr. 17",
    "sg:city":"Burgsinn",
    "sg:phone":"+49 9356/2686",
    "sg:postcode":"97775",
    "sg:province":"Bayern",
    "wof:name":"Zissler Cafe",
    "wof:placetype":"venue"
},
  "geometry": {"coordinates":[9.649837,50.147774],"type":"Point"}
}