{
  "type": "Feature",
  "properties": {
    "iso:country":"DE",
    "sg:address":"R\u00fcbenstr. 44",
    "sg:city":"Wuppertal",
    "sg:phone":"+49 202/625044",
    "sg:postcode":"42289",
    "sg:province":"Nordrhein-Westfalen",
    "wof:name":"Hans Peter Schenk",
    "wof:placetype":"venue"
},
  "geometry": {"coordinates":[7.226911068,51.269821167],"type":"Point"}
}