{
  "type": "Feature",
  "properties": {
    "iso:country":"DE",
    "sg:address":"Stadl 4",
    "sg:city":"Nittenau",
    "sg:phone":"+49 9436/8341",
    "sg:postcode":"93149",
    "sg:province":"Bayern",
    "wof:name":"Georg Lanzl",
    "wof:placetype":"venue"
},
  "geometry": {"coordinates":[12.2709226608,49.2271995544],"type":"Point"}
}