{
  "type": "Feature",
  "properties": {
    "iso:country":"DE",
    "sg:address":"Hauptstr. 175",
    "sg:city":"Heiligenhaus",
    "sg:phone":"+49 2056/5563",
    "sg:postcode":"42579",
    "sg:province":"Nordrhein-Westfalen",
    "wof:name":"Atlas Reisen Gmbh",
    "wof:placetype":"venue"
},
  "geometry": {"coordinates":[6.9696121216,51.3262786865],"type":"Point"}
}