{
  "type": "Feature",
  "properties": {
    "iso:country":"DE",
    "sg:address":"D\u00fclkener Str. 71",
    "sg:city":"Viersen",
    "sg:postcode":"41747",
    "sg:province":"Nordrhein-Westfalen",
    "wof:name":"B & S Immobilien Ohg",
    "wof:placetype":"venue"
},
  "geometry": {"coordinates":[6.3803019524,51.2579841614],"type":"Point"}
}