{
  "type": "Feature",
  "properties": {
    "iso:country":"DE",
    "sg:address":"Verbindungsweg",
    "sg:city":"Bad Marienberg",
    "sg:phone":"+49 2661/1666",
    "sg:postcode":"56470",
    "sg:province":"Rheinland-Pfalz",
    "wof:name":"Wildpark Bad Marienberg Kurverwaltung",
    "wof:placetype":"venue"
},
  "geometry": {"coordinates":[7.9621148109,50.6451911926],"type":"Point"}
}