{
  "type": "Feature",
  "properties": {
    "iso:country":"DE",
    "sg:address":"M\u00fcnchener Str. 21",
    "sg:city":"Forstinning",
    "sg:phone":"+49 8121/48012",
    "sg:postcode":"85661",
    "sg:province":"Bayern",
    "wof:name":"Ludwig Greska",
    "wof:placetype":"venue"
},
  "geometry": {"coordinates":[11.909637,48.165592],"type":"Point"}
}