{
  "type": "Feature",
  "properties": {
    "iso:country":"DE",
    "sg:address":"Pochelstr. 37",
    "sg:city":"Bad D\u00fcrkheim",
    "sg:phone":"+49 6322/63206",
    "sg:postcode":"67098",
    "sg:province":"Rheinland-Pfalz",
    "wof:name":"Erhard Hanewald Weinanbau",
    "wof:placetype":"venue"
},
  "geometry": {"coordinates":[8.1531152725,49.4943351746],"type":"Point"}
}