{
  "type": "Feature",
  "properties": {
    "iso:country":"DE",
    "sg:address":"Taunusstr. 51",
    "sg:city":"M\u00fcnchen",
    "sg:phone":"+49 89/3599350",
    "sg:postcode":"80807",
    "sg:province":"Bayern",
    "wof:name":"Gebr. Wirkes",
    "wof:placetype":"venue"
},
  "geometry": {"coordinates":[11.5813713074,48.1880340576],"type":"Point"}
}