{
  "type": "Feature",
  "properties": {
    "iso:country":"DE",
    "sg:address":"R\u00f6delheimer Landstr. 60",
    "sg:city":"Frankfurt",
    "sg:phone":"+49 69/705077",
    "sg:postcode":"60487",
    "sg:province":"Hessen",
    "wof:name":"Artisan B\u00fcro-hotel Gmbh",
    "wof:placetype":"venue"
},
  "geometry": {"coordinates":[8.6289796829,50.1220397949],"type":"Point"}
}