{
  "type": "Feature",
  "properties": {
    "iso:country":"DE",
    "sg:address":"Vetschauer Str. 9 401",
    "sg:city":"Dresden",
    "sg:phone":"+49 351/2817732",
    "sg:postcode":"01237",
    "sg:province":"Sachsen",
    "wof:name":"Dr. Uwe Bankwitz",
    "wof:placetype":"venue"
},
  "geometry": {"coordinates":[13.795971,51.010239],"type":"Point"}
}