{
  "type": "Feature",
  "properties": {
    "iso:country":"DE",
    "sg:address":"Hintergasse 27",
    "sg:city":"Pfungstadt",
    "sg:phone":"+49 6157",
    "sg:postcode":"64319",
    "sg:province":"Hessen",
    "wof:name":"Ingenieurb\u00fcro Kautz -wir Senken Ihre Energiekosten",
    "wof:placetype":"venue"
},
  "geometry": {"coordinates":[8.56191,49.81155],"type":"Point"}
}