{
  "type": "Feature",
  "properties": {
    "iso:country":"DE",
    "sg:address":"Ernst-Th\u00e4lmann-Str. 20",
    "sg:city":"M\u00fccheln",
    "sg:phone":"+49 34632/22416",
    "sg:postcode":"06249",
    "sg:province":"Sachsen-Anhalt",
    "wof:name":"Prei\u00dfer & S\u00f6hne",
    "wof:placetype":"venue"
},
  "geometry": {"coordinates":[11.808962,51.302948],"type":"Point"}
}