{
  "type": "Feature",
  "properties": {
    "iso:country":"DE",
    "sg:address":"Harkortstr. 10",
    "sg:city":"Leipzig",
    "sg:phone":"+49 341/9605301",
    "sg:postcode":"04107",
    "sg:province":"Sachsen",
    "wof:name":"Dr. Gertraud Stieler Rechtsanw\u00e4ltin",
    "wof:placetype":"venue"
},
  "geometry": {"coordinates":[12.3711557388,51.3319244385],"type":"Point"}
}