{
  "type": "Feature",
  "properties": {
    "iso:country":"DE",
    "sg:address":"Im Baumgarten 9",
    "sg:city":"Dettingen",
    "sg:phone":"+49 7021/82536",
    "sg:postcode":"73265",
    "sg:province":"Baden-W\u00fcrttemberg",
    "wof:name":"Hard- Und Software Telekommunikation Itz",
    "wof:placetype":"venue"
},
  "geometry": {"coordinates":[9.4462270737,48.6179161072],"type":"Point"}
}