{
  "type": "Feature",
  "properties": {
    "iso:country":"DE",
    "sg:address":"Kettelerstr. 4",
    "sg:city":"Schwandorf",
    "sg:postcode":"92421",
    "sg:province":"Bayern",
    "wof:name":"Sp Selbstbaupartner Bausysteme Gmbh",
    "wof:placetype":"venue"
},
  "geometry": {"coordinates":[12.098671,49.328796],"type":"Point"}
}