{
  "type": "Feature",
  "properties": {
    "iso:country":"DE",
    "sg:address":"M\u00fchlenstr. 8",
    "sg:city":"Waldau",
    "sg:phone":"+49 36878/61384",
    "sg:postcode":"98667",
    "sg:province":"Th\u00fcringen",
    "wof:name":"Walter Schmidt",
    "wof:placetype":"venue"
},
  "geometry": {"coordinates":[10.822359,50.500797],"type":"Point"}
}