{
  "type": "Feature",
  "properties": {
    "iso:country":"DE",
    "sg:address":"Kolpingstr. 26",
    "sg:city":"Esslingen",
    "sg:phone":"+49 711/372127",
    "sg:postcode":"73732",
    "sg:province":"Baden-W\u00fcrttemberg",
    "wof:name":"Clau\u00df Gartenbedarf Gottfried Clau\u00df",
    "wof:placetype":"venue"
},
  "geometry": {"coordinates":[9.311729,48.755074],"type":"Point"}
}