{
  "type": "Feature",
  "properties": {
    "iso:country":"DE",
    "sg:address":"Eisfelder Str. 22",
    "sg:city":"Hildburghausen",
    "sg:phone":"+49 3685/7272",
    "sg:postcode":"98646",
    "sg:province":"Th\u00fcringen",
    "wof:name":"Ingenieurb\u00fcro Dworrak Und Gatzer",
    "wof:placetype":"venue"
},
  "geometry": {"coordinates":[10.7353248596,50.4241027832],"type":"Point"}
}