{
  "type": "Feature",
  "properties": {
    "iso:country":"DE",
    "sg:address":"Backhausstr. 19",
    "sg:city":"Kemmenau",
    "sg:phone":"+49 2603/2670",
    "sg:postcode":"56132",
    "sg:province":"Rheinland-Pfalz",
    "wof:name":"Peter Bestmann",
    "wof:placetype":"venue"
},
  "geometry": {"coordinates":[7.7515377998,50.3478393555],"type":"Point"}
}