{
  "type": "Feature",
  "properties": {
    "iso:country":"DE",
    "sg:address":"Bernwardstr. 37",
    "sg:city":"Hannover",
    "sg:phone":"+49 511/8436824",
    "sg:postcode":"30519",
    "sg:province":"Niedersachsen",
    "wof:name":"Vereinslokal Gr\u00e4ser",
    "wof:placetype":"venue"
},
  "geometry": {"coordinates":[9.760635376,52.3393096924],"type":"Point"}
}