{
  "type": "Feature",
  "properties": {
    "iso:country":"DE",
    "sg:address":"B\u00fccken 6",
    "sg:city":"Hohenlockstedt",
    "sg:phone":"+49 4826/2857",
    "sg:postcode":"25551",
    "sg:province":"Schleswig-Holstein",
    "wof:name":"Willi Haack",
    "wof:placetype":"venue"
},
  "geometry": {"coordinates":[9.598263,53.973724],"type":"Point"}
}