{
  "type": "Feature",
  "properties": {
    "iso:country":"DE",
    "sg:address":"Monschauer Str. 2",
    "sg:city":"Nideggen",
    "sg:phone":"+49 2474/487",
    "sg:postcode":"52385",
    "sg:province":"Nordrhein-Westfalen",
    "wof:name":"Kreissparkasse D\u00fcren",
    "wof:placetype":"venue"
},
  "geometry": {"coordinates":[6.39875,50.658211],"type":"Point"}
}