{
  "type": "Feature",
  "properties": {
    "iso:country":"DE",
    "sg:address":"Bahnhofstr. 9",
    "sg:city":"Sinzig",
    "sg:phone":"+49 2642/41200",
    "sg:postcode":"53489",
    "sg:province":"Rheinland-Pfalz",
    "wof:name":"Brunnen-apotheke",
    "wof:placetype":"venue"
},
  "geometry": {"coordinates":[7.217896,50.556438],"type":"Point"}
}