{
  "type": "Feature",
  "properties": {
    "iso:country":"DE",
    "sg:address":"Am Flie\u00df 40",
    "sg:city":"Eschweiler",
    "sg:phone":"+49 2403/53400",
    "sg:postcode":"52249",
    "sg:province":"Nordrhein-Westfalen",
    "wof:name":"K\u00fclzer",
    "wof:placetype":"venue"
},
  "geometry": {"coordinates":[6.2782239914,50.832660675],"type":"Point"}
}