{
  "type": "Feature",
  "properties": {
    "iso:country":"DE",
    "sg:address":"Otto-Hue-Str. 40",
    "sg:city":"Frechen",
    "sg:phone":"+49 2234/59433",
    "sg:postcode":"50226",
    "sg:province":"Nordrhein-Westfalen",
    "wof:name":"Josef Schaaf Heilpraktiker",
    "wof:placetype":"venue"
},
  "geometry": {"coordinates":[6.8210320473,50.9041061401],"type":"Point"}
}