{
  "type": "Feature",
  "properties": {
    "iso:country":"DE",
    "sg:address":"Heisterbacher Str. 92",
    "sg:city":"K\u00f6nigswinter",
    "sg:phone":"+49 2223/70050",
    "sg:postcode":"53639",
    "sg:province":"Nordrhein-Westfalen",
    "wof:name":"Neuhaus Consulting Gmbh",
    "wof:placetype":"venue"
},
  "geometry": {"coordinates":[7.186357975,50.6963272095],"type":"Point"}
}