{
  "type": "Feature",
  "properties": {
    "iso:country":"DE",
    "sg:address":"Heuweg 24",
    "sg:city":"Bad W\u00fcnnenberg",
    "sg:phone":"+49 2953/274",
    "sg:postcode":"33181",
    "sg:province":"Nordrhein-Westfalen",
    "wof:name":"Heinz J\u00fcrgens",
    "wof:placetype":"venue"
},
  "geometry": {"coordinates":[8.69436,51.51828],"type":"Point"}
}