{
  "type": "Feature",
  "properties": {
    "iso:country":"DE",
    "sg:address":"Am Ower 4",
    "sg:city":"Friesenhagen",
    "sg:phone":"+49 2294/8714",
    "sg:postcode":"51598",
    "sg:province":"Rheinland-Pfalz",
    "wof:name":"Karla-margitta Heuel Steuerberaterin",
    "wof:placetype":"venue"
},
  "geometry": {"coordinates":[7.7857851982,50.8800697327],"type":"Point"}
}