{
  "type": "Feature",
  "properties": {
    "iso:country":"DE",
    "sg:address":"Gewerbegebiet 1",
    "sg:city":"Rhede",
    "sg:phone":"+49 4964/91800",
    "sg:postcode":"26899",
    "sg:province":"Niedersachsen",
    "wof:name":"Burghard Brak Gmbh",
    "wof:placetype":"venue"
},
  "geometry": {"coordinates":[7.27083,53.05946],"type":"Point"}
}