{
  "type": "Feature",
  "properties": {
    "iso:country":"DE",
    "sg:address":"Hauptstr. 5",
    "sg:city":"Bad Waldsee",
    "sg:phone":"+49 7524/8721",
    "sg:postcode":"88339",
    "sg:province":"Baden-W\u00fcrttemberg",
    "wof:name":"Joker",
    "wof:placetype":"venue"
},
  "geometry": {"coordinates":[9.7556056976,47.9199523926],"type":"Point"}
}