{
  "type": "Feature",
  "properties": {
    "iso:country":"DE",
    "sg:address":"Alte Landstr. 79",
    "sg:city":"Linkenheim-Hochstetten",
    "sg:phone":"+49 7247/6014",
    "sg:postcode":"76351",
    "sg:province":"Baden-W\u00fcrttemberg",
    "wof:name":"O. B\u00f6ser",
    "wof:placetype":"venue"
},
  "geometry": {"coordinates":[8.418258,49.131214],"type":"Point"}
}