{
  "type": "Feature",
  "properties": {
    "iso:country":"DE",
    "sg:address":"Im Walsumer Esch 16",
    "sg:city":"Ankum",
    "sg:phone":"+49 5462/420",
    "sg:postcode":"49577",
    "sg:province":"Niedersachsen",
    "wof:name":"Reinhold Koddenberg Inh. Ulrich Koddenberg",
    "wof:placetype":"venue"
},
  "geometry": {"coordinates":[7.8882632256,52.5442962646],"type":"Point"}
}