{
  "type": "Feature",
  "properties": {
    "iso:country":"DE",
    "sg:address":"Galvanistr 1",
    "sg:city":"Hermsdorf",
    "sg:phone":"+49 36601/5720",
    "sg:postcode":"07629",
    "sg:province":"Th\u00fcringen",
    "wof:name":"Pieper Oberfl\u00e4chentechnik Hermsdorf Gmbh",
    "wof:placetype":"venue"
},
  "geometry": {"coordinates":[11.850532,50.89386],"type":"Point"}
}