{
  "type": "Feature",
  "properties": {
    "iso:country":"DE",
    "sg:address":"Stengertsweg 10",
    "sg:city":"Aschaffenburg",
    "sg:phone":"+49 6021/69496",
    "sg:postcode":"63743",
    "sg:province":"Bayern",
    "wof:name":"Sauna Am Stengerts",
    "wof:placetype":"venue"
},
  "geometry": {"coordinates":[9.206228,49.94545],"type":"Point"}
}