{
  "type": "Feature",
  "properties": {
    "iso:country":"DE",
    "sg:address":"Karl-May-Str. 2",
    "sg:city":"Metzingen",
    "sg:phone":"+49 7123/21631",
    "sg:postcode":"72555",
    "sg:province":"Baden-W\u00fcrttemberg",
    "wof:name":"G\u00fcnter Salzer",
    "wof:placetype":"venue"
},
  "geometry": {"coordinates":[9.30299,48.530674],"type":"Point"}
}