{
  "type": "Feature",
  "properties": {
    "iso:country":"DE",
    "sg:address":"Wolpersreuth 6",
    "sg:city":"Mainleus",
    "sg:phone":"+49 9229/7437",
    "sg:postcode":"95336",
    "sg:province":"Bayern",
    "wof:name":"Heinz Keim",
    "wof:placetype":"venue"
},
  "geometry": {"coordinates":[11.3657302856,50.0911216736],"type":"Point"}
}