{
  "type": "Feature",
  "properties": {
    "iso:country":"DE",
    "sg:address":"Schwanitzstr. 1",
    "sg:city":"Ilmenau",
    "sg:phone":"+49 3677/2130",
    "sg:postcode":"98693",
    "sg:province":"Th\u00fcringen",
    "wof:name":"Mittelth\u00fcringer Druck",
    "wof:placetype":"venue"
},
  "geometry": {"coordinates":[10.9150791168,50.684879303],"type":"Point"}
}