{
  "type": "Feature",
  "properties": {
    "iso:country":"DE",
    "sg:address":"Hauptstr. 17",
    "sg:city":"Berlstedt",
    "sg:phone":"+49 36452/71202",
    "sg:postcode":"99439",
    "sg:province":"Th\u00fcringen",
    "wof:name":"Anette Reinhardt",
    "wof:placetype":"venue"
},
  "geometry": {"coordinates":[11.2438735962,51.06224823],"type":"Point"}
}