{
  "type": "Feature",
  "properties": {
    "iso:country":"DE",
    "sg:address":"Br\u00fcckenstr. 5",
    "sg:city":"Uelzen",
    "sg:phone":"+49 581/3891788",
    "sg:postcode":"29525",
    "sg:province":"Niedersachsen",
    "wof:name":"Phones Corner",
    "wof:placetype":"venue"
},
  "geometry": {"coordinates":[10.5631847382,52.9664649963],"type":"Point"}
}