{
  "type": "Feature",
  "properties": {
    "iso:country":"DE",
    "sg:address":"Bremer Str. 60",
    "sg:city":"Buchholz",
    "sg:postcode":"21244",
    "sg:province":"Niedersachsen",
    "wof:name":"Alkohol Selbsthilfegruppen Adressen",
    "wof:placetype":"venue"
},
  "geometry": {"coordinates":[9.864188,53.325459],"type":"Point"}
}