{
  "type": "Feature",
  "properties": {
    "iso:country":"DE",
    "sg:address":"Mat-Gr\u00fcnewald-Str 23",
    "sg:city":"Freiburg",
    "sg:phone":"+49 761/7079166",
    "sg:postcode":"79100",
    "sg:province":"Baden-W\u00fcrttemberg",
    "wof:name":"Citron-weber Und Weber Rechtsanw\u00e4lte",
    "wof:placetype":"venue"
},
  "geometry": {"coordinates":[7.8475699425,47.9839096069],"type":"Point"}
}