{
  "type": "Feature",
  "properties": {
    "iso:country":"DE",
    "sg:address":"Gottlieb-Dunkel-Str 25",
    "sg:city":"Berlin",
    "sg:phone":"+49 30/7009090",
    "sg:postcode":"12099",
    "sg:province":"Berlin",
    "wof:name":"Metallwerk Oetinger Berlin-tempelhof Gmbh",
    "wof:placetype":"venue"
},
  "geometry": {"coordinates":[13.40935,52.454952],"type":"Point"}
}