{
  "type": "Feature",
  "properties": {
    "iso:country":"DE",
    "sg:address":"Weinstr. 33",
    "sg:city":"Bad Bergzabern",
    "sg:phone":"+49 6343/4798",
    "sg:postcode":"76887",
    "sg:province":"Rheinland-Pfalz",
    "wof:name":"Kur-apotheke Christine Tretter E. K.",
    "wof:placetype":"venue"
},
  "geometry": {"coordinates":[7.99388,49.100182],"type":"Point"}
}