{
  "type": "Feature",
  "properties": {
    "iso:country":"DE",
    "sg:address":"Am Oberen Hart 1",
    "sg:city":"Germaringen",
    "sg:phone":"+49 8341/64978",
    "sg:postcode":"87656",
    "sg:province":"Bayern",
    "wof:name":"A. Reggel Gmbh",
    "wof:placetype":"venue"
},
  "geometry": {"coordinates":[10.675853,47.924797],"type":"Point"}
}