{
  "type": "Feature",
  "properties": {
    "iso:country":"DE",
    "sg:address":"Allee 16",
    "sg:city":"Fritzlar",
    "sg:phone":"+49 5622/3004",
    "sg:postcode":"34560",
    "sg:province":"Hessen",
    "wof:name":"Hagebaumarkt Stegner Gmbh & Co. Kg",
    "wof:placetype":"venue"
},
  "geometry": {"coordinates":[9.2705955505,51.1333236694],"type":"Point"}
}