{
  "type": "Feature",
  "properties": {
    "iso:country":"DE",
    "sg:address":"Pothoff 15",
    "sg:city":"Osterholz-Scharmbeck",
    "sg:phone":"+49 4791/7503",
    "sg:postcode":"27711",
    "sg:province":"Niedersachsen",
    "wof:name":"Joh. Werkmeister",
    "wof:placetype":"venue"
},
  "geometry": {"coordinates":[8.756286,53.223072],"type":"Point"}
}