{
  "type": "Feature",
  "properties": {
    "iso:country":"DE",
    "sg:address":"Friedrichstr. 9",
    "sg:city":"Hof",
    "sg:postcode":"95028",
    "sg:province":"Bayern",
    "wof:name":"Hartmann & Krau\u00df Gro\u00dfparksysteme-vertriebsges.",
    "wof:placetype":"venue"
},
  "geometry": {"coordinates":[11.9144268036,50.3141479492],"type":"Point"}
}