{
  "type": "Feature",
  "properties": {
    "iso:country":"DE",
    "sg:address":"Wei\u00dfenhofstrasse 4",
    "sg:city":"Erlenbach",
    "sg:phone":"+49 7132/2901",
    "sg:postcode":"74235",
    "sg:province":"Baden-W\u00fcrttemberg",
    "wof:name":"Weingut Klaus Haberkern",
    "wof:placetype":"venue"
},
  "geometry": {"coordinates":[9.269389,49.169743],"type":"Point"}
}