{
  "type": "Feature",
  "properties": {
    "iso:country":"DE",
    "sg:address":"L\u00f6wensteiner Str. 6",
    "sg:city":"Ludwigsburg",
    "sg:phone":"+49 7141/51900",
    "sg:postcode":"71642",
    "sg:province":"Baden-W\u00fcrttemberg",
    "wof:name":"Margarete Braun Steuerbevollm\u00e4chtigte",
    "wof:placetype":"venue"
},
  "geometry": {"coordinates":[9.2041501999,48.9104347229],"type":"Point"}
}