{
  "type": "Feature",
  "properties": {
    "iso:country":"DE",
    "sg:address":"Bayreuther Str. 11",
    "sg:city":"Erlangen",
    "sg:phone":"+49 9131/22776",
    "sg:postcode":"91054",
    "sg:province":"Bayern",
    "wof:name":"Ev. Luth. Pfarramt",
    "wof:placetype":"venue"
},
  "geometry": {"coordinates":[11.0042047501,49.6044120789],"type":"Point"}
}