{
  "type": "Feature",
  "properties": {
    "iso:country":"DE",
    "sg:address":"Sertoriusring 23",
    "sg:city":"Mainz",
    "sg:phone":"+49 6131/478266",
    "sg:postcode":"55126",
    "sg:province":"Rheinland-Pfalz",
    "wof:name":"H. Dastig",
    "wof:placetype":"venue"
},
  "geometry": {"coordinates":[8.1760168076,49.9955978394],"type":"Point"}
}