{
  "type": "Feature",
  "properties": {
    "iso:country":"DE",
    "sg:address":"Marktplatz 1",
    "sg:city":"Pfeffenhausen",
    "sg:phone":"+49 8782/275",
    "sg:postcode":"84076",
    "sg:province":"Bayern",
    "wof:name":"Brauerei Reder",
    "wof:placetype":"venue"
},
  "geometry": {"coordinates":[11.965147,48.665642],"type":"Point"}
}