{
  "type": "Feature",
  "properties": {
    "iso:country":"DE",
    "sg:address":"Br\u00fcckenstr. 9",
    "sg:city":"Traben-Trarbach",
    "sg:phone":"+49 6541/1609",
    "sg:postcode":"56841",
    "sg:province":"Rheinland-Pfalz",
    "wof:name":"Matthias P\u00f6lcher",
    "wof:placetype":"venue"
},
  "geometry": {"coordinates":[7.113245,49.948486],"type":"Point"}
}