{
  "type": "Feature",
  "properties": {
    "iso:country":"DE",
    "sg:address":"Kreisental 21",
    "sg:city":"Epfenbach",
    "sg:phone":"+49 7263/5325",
    "sg:postcode":"74925",
    "sg:province":"Baden-W\u00fcrttemberg",
    "wof:name":"Konrad Hafner",
    "wof:placetype":"venue"
},
  "geometry": {"coordinates":[8.90814,49.339874],"type":"Point"}
}