{
  "type": "Feature",
  "properties": {
    "iso:country":"DE",
    "sg:address":"Saargem\u00fcnder Str. 53",
    "sg:city":"Saarbr\u00fccken",
    "sg:phone":"+49 681/881407",
    "sg:postcode":"66130",
    "sg:province":"Saarland",
    "wof:name":"S. Gro\u00dfklos",
    "wof:placetype":"venue"
},
  "geometry": {"coordinates":[7.028758,49.20834],"type":"Point"}
}