{
  "type": "Feature",
  "properties": {
    "iso:country":"DE",
    "sg:address":"Willinghusener Landstr. 11 b",
    "sg:city":"Barsb\u00fcttel",
    "sg:phone":"+49 40/6703588",
    "sg:postcode":"22885",
    "sg:province":"Schleswig-Holstein",
    "wof:name":"Imbi\u00df Kai Schwarten",
    "wof:placetype":"venue"
},
  "geometry": {"coordinates":[10.173699379,53.5689735413],"type":"Point"}
}