{
  "type": "Feature",
  "properties": {
    "iso:country":"DE",
    "sg:address":"Germaniastr. 17",
    "sg:city":"D\u00fcsseldorf",
    "sg:phone":"+49 211/308201",
    "sg:postcode":"40223",
    "sg:province":"Nordrhein-Westfalen",
    "wof:name":"Fischer-stahlbau",
    "wof:placetype":"venue"
},
  "geometry": {"coordinates":[6.762047,51.20726],"type":"Point"}
}