{
  "type": "Feature",
  "properties": {
    "iso:country":"DE",
    "sg:address":"Jahnstr. 18",
    "sg:city":"Eppertshausen",
    "sg:phone":"+49 6071/31881",
    "sg:postcode":"64859",
    "sg:province":"Hessen",
    "wof:name":"Atm Kropf Gmbh",
    "wof:placetype":"venue"
},
  "geometry": {"coordinates":[8.8422603607,49.9440841675],"type":"Point"}
}