{
  "type": "Feature",
  "properties": {
    "iso:country":"DE",
    "sg:address":"Teichstr. 2",
    "sg:city":"Gro\u00dfenbrode",
    "sg:phone":"+49 4367/227",
    "sg:postcode":"23775",
    "sg:province":"Schleswig-Holstein",
    "wof:name":"Pension P. Lobe",
    "wof:placetype":"venue"
},
  "geometry": {"coordinates":[11.0863571167,54.3742599487],"type":"Point"}
}