{
  "type": "Feature",
  "properties": {
    "iso:country":"DE",
    "sg:address":"Gutenbergstr. 4",
    "sg:city":"D\u00fclmen",
    "sg:phone":"+49 2594/7479",
    "sg:postcode":"48249",
    "sg:province":"Nordrhein-Westfalen",
    "wof:name":"Otto B\u00f6deker Heilpraktiker",
    "wof:placetype":"venue"
},
  "geometry": {"coordinates":[7.2804589272,51.8400382996],"type":"Point"}
}