{
  "type": "Feature",
  "properties": {
    "iso:country":"DE",
    "sg:address":"Kiefernweg 3A",
    "sg:city":"Erlenbach",
    "sg:phone":"+49 9372/944242",
    "sg:postcode":"63906",
    "sg:province":"Bayern",
    "wof:name":"Klaus Kl\u00fchspies Ingenieur Und Architekt",
    "wof:placetype":"venue"
},
  "geometry": {"coordinates":[9.162049,49.812744],"type":"Point"}
}