{
  "type": "Feature",
  "properties": {
    "iso:country":"DE",
    "sg:address":"Jagowstr 20",
    "sg:city":"Berlin",
    "sg:phone":"+49 30/3353866",
    "sg:postcode":"13585",
    "sg:province":"Berlin",
    "wof:name":"Fuhl & Hornung Nachfolger Ek",
    "wof:placetype":"venue"
},
  "geometry": {"coordinates":[13.2060184479,52.5471038818],"type":"Point"}
}