{
  "type": "Feature",
  "properties": {
    "iso:country":"DE",
    "sg:address":"H\u00f6lsersundern 9",
    "sg:city":"Bad Salzuflen",
    "sg:phone":"+49 5232/64505",
    "sg:postcode":"32108",
    "sg:province":"Nordrhein-Westfalen",
    "wof:name":"D. Stille Gmbh & Co. Kg",
    "wof:placetype":"venue"
},
  "geometry": {"coordinates":[8.7809896469,52.0323600769],"type":"Point"}
}