{
  "type": "Feature",
  "properties": {
    "iso:country":"DE",
    "sg:address":"Dieselstr 6-8",
    "sg:city":"Leinfelden-Echterdingen",
    "sg:phone":"+49 711/902180",
    "sg:postcode":"70771",
    "sg:province":"Baden-W\u00fcrttemberg",
    "wof:name":"Typopress Druckerei Gmbh",
    "wof:placetype":"venue"
},
  "geometry": {"coordinates":[9.1654396057,48.6956596375],"type":"Point"}
}