{
  "type": "Feature",
  "properties": {
    "iso:country":"DE",
    "sg:address":"Am Gorzberg 10",
    "sg:city":"Greifswald",
    "sg:postcode":"17489",
    "sg:province":"Mecklenburg-Vorpommern",
    "wof:name":"Thema Einrichtungen Manfred Thei\u00dfen Gmbh & Co. Kg",
    "wof:placetype":"venue"
},
  "geometry": {"coordinates":[13.3949508667,54.0756874084],"type":"Point"}
}