{
  "type": "Feature",
  "properties": {
    "iso:country":"DE",
    "sg:address":"Jenseitsstr. 10",
    "sg:city":"Bergheim",
    "sg:phone":"+49 2271/92791",
    "sg:postcode":"50127",
    "sg:province":"Nordrhein-Westfalen",
    "wof:name":"Redaktion Deutscher Versand Einkaufsf\u00fchrer",
    "wof:placetype":"venue"
},
  "geometry": {"coordinates":[6.6987051964,50.9371681213],"type":"Point"}
}