{
  "type": "Feature",
  "properties": {
    "iso:country":"DE",
    "sg:address":"Mainzer Str. 3",
    "sg:city":"Wolfsheim",
    "sg:phone":"+49 6701/7205",
    "sg:postcode":"55578",
    "sg:province":"Rheinland-Pfalz",
    "wof:name":"Heinrich Bieser",
    "wof:placetype":"venue"
},
  "geometry": {"coordinates":[8.0421218872,49.8730430603],"type":"Point"}
}