{
  "type": "Feature",
  "properties": {
    "iso:country":"DE",
    "sg:address":"Gummersbacher Str. 9a",
    "sg:city":"Gummersbach",
    "sg:phone":"+49 2261/21029",
    "sg:postcode":"51645",
    "sg:province":"Nordrhein-Westfalen",
    "wof:name":"Teco",
    "wof:placetype":"venue"
},
  "geometry": {"coordinates":[7.5718398094,51.0091018677],"type":"Point"}
}