{
  "type": "Feature",
  "properties": {
    "iso:country":"DE",
    "sg:address":"Hauptstr 72",
    "sg:city":"Heidelberg",
    "sg:phone":"+49 6221/20869",
    "sg:postcode":"69117",
    "sg:province":"Baden-W\u00fcrttemberg",
    "wof:name":"Lehmanns",
    "wof:placetype":"venue"
},
  "geometry": {"coordinates":[8.6993627548,49.4106025696],"type":"Point"}
}