{
  "type": "Feature",
  "properties": {
    "iso:country":"DE",
    "sg:address":"Wittmunder Str. 71",
    "sg:city":"Wiesmoor",
    "sg:phone":"+49 4944/2028",
    "sg:postcode":"26639",
    "sg:province":"Niedersachsen",
    "wof:name":"M. Jacobs",
    "wof:placetype":"venue"
},
  "geometry": {"coordinates":[7.7289118767,53.4238357544],"type":"Point"}
}