{
  "type": "Feature",
  "properties": {
    "iso:country":"DE",
    "sg:address":"Alte Dorfstr. 22",
    "sg:city":"Sylt-Ost",
    "sg:phone":"+49 4651/935080",
    "sg:postcode":"25980",
    "sg:province":"Schleswig-Holstein",
    "wof:name":"Haus Jacobsen",
    "wof:placetype":"venue"
},
  "geometry": {"coordinates":[8.3459472656,54.8985671997],"type":"Point"}
}