{
  "type": "Feature",
  "properties": {
    "iso:country":"DE",
    "sg:city":"Frickenhausen am Main",
    "sg:phone":"+49 9331/2635",
    "sg:postcode":"97252",
    "sg:province":"Bayern",
    "wof:name":"Sparkasse Ochsenfurt",
    "wof:placetype":"venue"
},
  "geometry": {"coordinates":[10.09401,49.670666],"type":"Point"}
}