{
  "type": "Feature",
  "properties": {
    "iso:country":"DE",
    "sg:address":"Tro\u00dfweg 1",
    "sg:city":"Mannheim",
    "sg:phone":"+49 621/408667",
    "sg:postcode":"68163",
    "sg:province":"Baden-W\u00fcrttemberg",
    "wof:name":"Britta Hollich",
    "wof:placetype":"venue"
},
  "geometry": {"coordinates":[8.5004491806,49.4675140381],"type":"Point"}
}