{
  "type": "Feature",
  "properties": {
    "iso:country":"DE",
    "sg:address":"Marktplatz 4",
    "sg:city":"Bad Saulgau",
    "sg:phone":"+49 7581/3716",
    "sg:postcode":"88348",
    "sg:province":"Baden-W\u00fcrttemberg",
    "wof:name":"Buck Gmbh",
    "wof:placetype":"venue"
},
  "geometry": {"coordinates":[9.4993467331,48.0174064636],"type":"Point"}
}