{
  "type": "Feature",
  "properties": {
    "iso:country":"DE",
    "sg:address":"Kirchenhang 21",
    "sg:city":"Hamburg",
    "sg:phone":"+49 40/7906122",
    "sg:postcode":"21073",
    "sg:province":"Hamburg",
    "wof:name":"Ev. Pfarramt I Luther-gemeinde",
    "wof:placetype":"venue"
},
  "geometry": {"coordinates":[9.9588165283,53.4549713135],"type":"Point"}
}