{
  "type": "Feature",
  "properties": {
    "iso:country":"DE",
    "sg:address":"Hohenzollernstr. 30",
    "sg:city":"M\u00fcnchen",
    "sg:phone":"+49 89/342147",
    "sg:postcode":"80801",
    "sg:province":"Bayern",
    "wof:name":"Hbg Gmbh",
    "wof:placetype":"venue"
},
  "geometry": {"coordinates":[11.58168,48.159981],"type":"Point"}
}