{
  "type": "Feature",
  "properties": {
    "iso:country":"DE",
    "sg:address":"Josef-Sedlmayr-Str. 5",
    "sg:city":"Maisach",
    "sg:phone":"+49 8141/94188",
    "sg:postcode":"82216",
    "sg:province":"Bayern",
    "wof:name":"Herbert Krank Steuerberater",
    "wof:placetype":"venue"
},
  "geometry": {"coordinates":[11.254658699,48.2173347473],"type":"Point"}
}