{
  "type": "Feature",
  "properties": {
    "iso:country":"DE",
    "sg:address":"Bl\u00fcmnerstr. 37",
    "sg:city":"Leipzig",
    "sg:phone":"+49 341/4770123",
    "sg:postcode":"04229",
    "sg:province":"Sachsen",
    "wof:name":"Cityinfo 2000 Delitzsch",
    "wof:placetype":"venue"
},
  "geometry": {"coordinates":[12.340569,51.320034],"type":"Point"}
}