{
  "type": "Feature",
  "properties": {
    "iso:country":"DE",
    "sg:address":"Schlachthausstr. 59",
    "sg:city":"G\u00fcnzburg",
    "sg:phone":"+49 8221/9090",
    "sg:postcode":"89312",
    "sg:province":"Bayern",
    "wof:name":"Deutsche Post Ag",
    "wof:placetype":"venue"
},
  "geometry": {"coordinates":[10.2767219543,48.4589080811],"type":"Point"}
}