{
  "type": "Feature",
  "properties": {
    "iso:country":"DE",
    "sg:address":"N\u00fcrtinger Str. 34-1",
    "sg:city":"Neuffen",
    "sg:phone":"+49 7025/5020",
    "sg:postcode":"72639",
    "sg:province":"Baden-W\u00fcrttemberg",
    "wof:name":"Lm-meisterteam Renovierungs Gmbh",
    "wof:placetype":"venue"
},
  "geometry": {"coordinates":[9.372837,48.557518],"type":"Point"}
}