{
  "type": "Feature",
  "properties": {
    "iso:country":"DE",
    "sg:address":"H\u00fcbenthal 2",
    "sg:city":"Sontra",
    "sg:phone":"+49 5653/5326",
    "sg:postcode":"36205",
    "sg:province":"Hessen",
    "wof:name":"Karl Rehm",
    "wof:placetype":"venue"
},
  "geometry": {"coordinates":[9.894864,51.070633],"type":"Point"}
}