{
  "type": "Feature",
  "properties": {
    "iso:country":"DE",
    "sg:address":"Wilhelm-Busch-Str. 66",
    "sg:city":"Erfurt",
    "sg:phone":"+49 361/3453810",
    "sg:postcode":"99099",
    "sg:province":"Th\u00fcringen",
    "wof:name":"Speedikon Service Cad Dienstleistungs Gmbh",
    "wof:placetype":"venue"
},
  "geometry": {"coordinates":[11.0456809998,50.9703216553],"type":"Point"}
}