{
  "type": "Feature",
  "properties": {
    "iso:country":"DE",
    "sg:address":"Nedderfeld 15-17",
    "sg:city":"Hamburg",
    "sg:phone":"+49 40/5535939",
    "sg:postcode":"22529",
    "sg:province":"Hamburg",
    "wof:name":"Heinz Pelka",
    "wof:placetype":"venue"
},
  "geometry": {"coordinates":[9.966513,53.603619],"type":"Point"}
}