{
  "type": "Feature",
  "properties": {
    "iso:country":"DE",
    "sg:city":"Bordelum",
    "sg:postcode":"25852",
    "sg:province":"Schleswig-Holstein",
    "wof:name":"Arnd Jansohn Gmbh",
    "wof:placetype":"venue"
},
  "geometry": {"coordinates":[8.92497,54.63599],"type":"Point"}
}