{
  "type": "Feature",
  "properties": {
    "iso:country":"DE",
    "sg:address":"Spitalgasse 7",
    "sg:city":"Bad S\u00e4ckingen",
    "sg:postcode":"79713",
    "sg:province":"Baden-W\u00fcrttemberg",
    "wof:name":"Business Computer Service Gmbh",
    "wof:placetype":"venue"
},
  "geometry": {"coordinates":[7.948137,47.552372],"type":"Point"}
}