{
  "type": "Feature",
  "properties": {
    "iso:country":"DE",
    "sg:address":"Geschwister-Scholl-Str. 5",
    "sg:city":"Jena",
    "sg:phone":"+49 3641/443954",
    "sg:postcode":"07749",
    "sg:province":"Th\u00fcringen",
    "wof:name":"Etzoldt Bau Gmbh",
    "wof:placetype":"venue"
},
  "geometry": {"coordinates":[11.599081,50.929592],"type":"Point"}
}