{
  "type": "Feature",
  "properties": {
    "iso:country":"DE",
    "sg:address":"Europastr. 11",
    "sg:city":"N\u00fcrtingen",
    "sg:phone":"+49 7022/35511",
    "sg:postcode":"72622",
    "sg:province":"Baden-W\u00fcrttemberg",
    "wof:name":"Dr. Med. Rudolf Handschuh",
    "wof:placetype":"venue"
},
  "geometry": {"coordinates":[9.3394517899,48.6281700134],"type":"Point"}
}