{
  "type": "Feature",
  "properties": {
    "iso:country":"DE",
    "sg:address":"Albert-Schweitzer-Str. 17",
    "sg:city":"H\u00fcrth",
    "sg:phone":"+49 2233/966063",
    "sg:postcode":"50354",
    "sg:province":"Nordrhein-Westfalen",
    "wof:name":"A. T\u00f6pfer Rechtsanwalt",
    "wof:placetype":"venue"
},
  "geometry": {"coordinates":[6.8891429901,50.8925895691],"type":"Point"}
}