{
  "type": "Feature",
  "properties": {
    "iso:country":"DE",
    "sg:address":"Elisabethstr. 40",
    "sg:city":"Stendal",
    "sg:phone":"+49 3931/415027",
    "sg:postcode":"39576",
    "sg:province":"Sachsen-Anhalt",
    "wof:name":"Neumann Stelle",
    "wof:placetype":"venue"
},
  "geometry": {"coordinates":[11.851724,52.610737],"type":"Point"}
}