{
  "type": "Feature",
  "properties": {
    "iso:country":"DE",
    "sg:address":"Am Sulberg 6",
    "sg:city":"Duderstadt",
    "sg:phone":"+49 5527/5046",
    "sg:postcode":"37115",
    "sg:province":"Niedersachsen",
    "wof:name":"Hotel Kurmainzer-eck",
    "wof:placetype":"venue"
},
  "geometry": {"coordinates":[10.2503900528,51.5178108215],"type":"Point"}
}