{
  "type": "Feature",
  "properties": {
    "iso:country":"DE",
    "sg:address":"Rodenkirchener Str 200",
    "sg:city":"Wesseling",
    "sg:phone":"+49 2236",
    "sg:postcode":"50389",
    "sg:province":"Nordrhein-Westfalen",
    "wof:name":"K&f Keramik & Fliesen Gmbh",
    "wof:placetype":"venue"
},
  "geometry": {"coordinates":[6.9598660469,50.8286209106],"type":"Point"}
}