{
  "type": "Feature",
  "properties": {
    "iso:country":"DE",
    "sg:address":"Im Kerberich 32",
    "sg:city":"Odenthal",
    "sg:phone":"+49 2174/40373",
    "sg:postcode":"51519",
    "sg:province":"Nordrhein-Westfalen",
    "wof:name":"Brigitte Rentmeister",
    "wof:placetype":"venue"
},
  "geometry": {"coordinates":[7.127933,51.05999],"type":"Point"}
}