{
  "type": "Feature",
  "properties": {
    "iso:country":"DE",
    "sg:address":"Sch\u00fctzenstr. 2",
    "sg:city":"Adorf",
    "sg:postcode":"08626",
    "sg:province":"Sachsen",
    "wof:name":"S. Dorst",
    "wof:placetype":"venue"
},
  "geometry": {"coordinates":[12.2195,50.322208],"type":"Point"}
}