{
  "type": "Feature",
  "properties": {
    "iso:country":"DE",
    "sg:address":"Ingersheimer Str. 12",
    "sg:city":"Stuttgart",
    "sg:postcode":"70499",
    "sg:province":"Baden-W\u00fcrttemberg",
    "wof:name":"Fitness Forum Ohg",
    "wof:placetype":"venue"
},
  "geometry": {"coordinates":[9.094874382,48.8223876953],"type":"Point"}
}