{
  "type": "Feature",
  "properties": {
    "iso:country":"DE",
    "sg:address":"Waldluststr. 79",
    "sg:city":"N\u00fcrnberg",
    "sg:phone":"+49 911/405000",
    "sg:postcode":"90480",
    "sg:province":"Bayern",
    "wof:name":"Wohnungsunternehmen N\u00fcrnberg-ost Eg",
    "wof:placetype":"venue"
},
  "geometry": {"coordinates":[11.1222200394,49.4404258728],"type":"Point"}
}