{
  "type": "Feature",
  "properties": {
    "iso:country":"DE",
    "sg:address":"Sch\u00fctzenstr. 102",
    "sg:city":"Hamburg",
    "sg:phone":"+49 40/8511380",
    "sg:postcode":"22761",
    "sg:province":"Hamburg",
    "wof:name":"Harrys Fliesenmarkt Gmbh",
    "wof:placetype":"venue"
},
  "geometry": {"coordinates":[9.92933,53.567917],"type":"Point"}
}