{
  "type": "Feature",
  "properties": {
    "iso:country":"DE",
    "sg:address":"Am Bergfried 28 A",
    "sg:city":"Langen",
    "sg:phone":"+49 6103/53588",
    "sg:postcode":"63225",
    "sg:province":"Hessen",
    "wof:name":"Cornelia Haager Rechtsanw\u00e4ltin",
    "wof:placetype":"venue"
},
  "geometry": {"coordinates":[8.6873512268,49.9804954529],"type":"Point"}
}