{
  "type": "Feature",
  "properties": {
    "iso:country":"DE",
    "sg:address":"Leverner Str. 45",
    "sg:city":"Bohmte",
    "sg:phone":"+49 5471/4408",
    "sg:postcode":"49163",
    "sg:province":"Niedersachsen",
    "wof:name":"Heinz Schnier",
    "wof:placetype":"venue"
},
  "geometry": {"coordinates":[8.34977,52.375607],"type":"Point"}
}