{
  "type": "Feature",
  "properties": {
    "iso:country":"DE",
    "sg:address":"Zollrain 9",
    "sg:city":"Halle",
    "sg:phone":"+49 345/695080",
    "sg:postcode":"06124",
    "sg:province":"Sachsen-Anhalt",
    "wof:name":"Kobold Apotheke Dr. Kristin L\u00fcdecke",
    "wof:placetype":"venue"
},
  "geometry": {"coordinates":[11.92247,51.474522],"type":"Point"}
}