{
  "type": "Feature",
  "properties": {
    "iso:country":"DE",
    "sg:address":"Fasangartenstr. 131",
    "sg:city":"M\u00fcnchen",
    "sg:phone":"+49 89/69340071",
    "sg:postcode":"81549",
    "sg:province":"Bayern",
    "wof:name":"Pallauf Treuhand Gmbh",
    "wof:placetype":"venue"
},
  "geometry": {"coordinates":[11.6060771942,48.0882110596],"type":"Point"}
}