{
  "type": "Feature",
  "properties": {
    "iso:country":"DE",
    "sg:address":"Wasserwerk 11",
    "sg:city":"B\u00fcrstadt",
    "sg:phone":"+49 6206/6666",
    "sg:postcode":"68642",
    "sg:province":"Hessen",
    "wof:name":"Brigitte Daiker-neumann Rechtsanw\u00e4ltin Und Notarin",
    "wof:placetype":"venue"
},
  "geometry": {"coordinates":[8.4741754532,49.6426124573],"type":"Point"}
}