{
  "type": "Feature",
  "properties": {
    "iso:country":"DE",
    "sg:address":"Stegwiesen 10",
    "sg:city":"Stockach",
    "sg:phone":"+49 7771/61048",
    "sg:postcode":"78333",
    "sg:province":"Baden-W\u00fcrttemberg",
    "wof:name":"Hermann Meister",
    "wof:placetype":"venue"
},
  "geometry": {"coordinates":[9.00463,47.85516],"type":"Point"}
}