{
  "type": "Feature",
  "properties": {
    "iso:country":"DE",
    "sg:address":"Robert-Koch-Str. 60",
    "sg:city":"Burghausen",
    "sg:phone":"+49 8677/65288",
    "sg:postcode":"84489",
    "sg:province":"Bayern",
    "wof:name":"Hl-markt",
    "wof:placetype":"venue"
},
  "geometry": {"coordinates":[12.8258562088,48.1706314087],"type":"Point"}
}