{
  "type": "Feature",
  "properties": {
    "iso:country":"DE",
    "sg:address":"M\u00f6nckebergstr. 27",
    "sg:city":"Hamburg",
    "sg:phone":"+49 40/3080080",
    "sg:postcode":"20095",
    "sg:province":"Hamburg",
    "wof:name":"Dr. Ancker Dr. R\u00f6h Und Dr. Vogel",
    "wof:placetype":"venue"
},
  "geometry": {"coordinates":[9.9953775406,53.5504493713],"type":"Point"}
}