{
  "type": "Feature",
  "properties": {
    "iso:country":"DE",
    "sg:address":"Leimbacher Str. 49",
    "sg:city":"Bad Salzungen",
    "sg:phone":"+49 3695/603469",
    "sg:postcode":"36433",
    "sg:province":"Th\u00fcringen",
    "wof:name":"Wolfgang Kr\u00fcgel",
    "wof:placetype":"venue"
},
  "geometry": {"coordinates":[10.2276573181,50.8118476868],"type":"Point"}
}