{
  "type": "Feature",
  "properties": {
    "iso:country":"DE",
    "sg:address":"Neuer Weg 27",
    "sg:city":"Werther",
    "sg:phone":"+49 3631/600825",
    "sg:postcode":"99735",
    "sg:province":"Th\u00fcringen",
    "wof:name":"Robert Becke",
    "wof:placetype":"venue"
},
  "geometry": {"coordinates":[10.7407684326,51.4850120544],"type":"Point"}
}