{
  "type": "Feature",
  "properties": {
    "iso:country":"DE",
    "sg:address":"Haarenstr. 53",
    "sg:city":"Oldenburg",
    "sg:phone":"+49 441/15400",
    "sg:postcode":"26122",
    "sg:province":"Niedersachsen",
    "wof:name":"H. Oltmann",
    "wof:placetype":"venue"
},
  "geometry": {"coordinates":[8.2120304108,53.140499115],"type":"Point"}
}