{
  "type": "Feature",
  "properties": {
    "iso:country":"DE",
    "sg:address":"Milchhalle Hauptbahnhof",
    "sg:city":"N\u00fcrnberg",
    "sg:phone":"+49 911/241002",
    "sg:postcode":"90443",
    "sg:province":"Bayern",
    "wof:name":"Wiener Feinb\u00e4ckerei Heberer Gmbh",
    "wof:placetype":"venue"
},
  "geometry": {"coordinates":[11.07034,49.437832],"type":"Point"}
}