{
  "type": "Feature",
  "properties": {
    "iso:country":"DE",
    "sg:address":"Kirchbichl 6",
    "sg:city":"Grainau",
    "sg:phone":"+49 8821/8805",
    "sg:postcode":"82491",
    "sg:province":"Bayern",
    "wof:name":"Kath. \u00d6ffentliche Bibliothek Kath. Pfarramt",
    "wof:placetype":"venue"
},
  "geometry": {"coordinates":[11.024593,47.470825],"type":"Point"}
}