{
  "type": "Feature",
  "properties": {
    "iso:country":"DE",
    "sg:address":"Bachstr. 44",
    "sg:city":"Alsheim",
    "sg:phone":"+49 6249/5168",
    "sg:postcode":"67577",
    "sg:province":"Rheinland-Pfalz",
    "wof:name":"Leonhard Lauth",
    "wof:placetype":"venue"
},
  "geometry": {"coordinates":[8.3401832581,49.7644767761],"type":"Point"}
}