{
  "type": "Feature",
  "properties": {
    "iso:country":"DE",
    "sg:address":"Luitfriedstr. 17 a",
    "sg:city":"M\u00fcnchen",
    "sg:phone":"+49 89/3134461",
    "sg:postcode":"80995",
    "sg:province":"Bayern",
    "wof:name":"Karin Parker Fotostudio",
    "wof:placetype":"venue"
},
  "geometry": {"coordinates":[11.5396976471,48.2123260498],"type":"Point"}
}