{
  "type": "Feature",
  "properties": {
    "iso:country":"DE",
    "sg:address":"K\u00f6nigsberger Str. 30a",
    "sg:city":"Ratzeburg",
    "sg:phone":"+49 4541/6449",
    "sg:postcode":"23909",
    "sg:province":"Schleswig-Holstein",
    "wof:name":"Modern Sports",
    "wof:placetype":"venue"
},
  "geometry": {"coordinates":[10.792677,53.688293],"type":"Point"}
}