{
  "type": "Feature",
  "properties": {
    "iso:country":"DE",
    "sg:address":"Beinsteiner Str. 165",
    "sg:city":"Waiblingen",
    "sg:phone":"+49 7151/31519",
    "sg:postcode":"71334",
    "sg:province":"Baden-W\u00fcrttemberg",
    "wof:name":"Willy Lenz Felsenberg",
    "wof:placetype":"venue"
},
  "geometry": {"coordinates":[9.335559,48.825836],"type":"Point"}
}