{
  "type": "Feature",
  "properties": {
    "iso:country":"DE",
    "sg:address":"Rathausstr. 40",
    "sg:city":"Markkleeberg",
    "sg:phone":"+49 341/3581919",
    "sg:postcode":"04416",
    "sg:province":"Sachsen",
    "wof:name":"Bestattungen Dunker Gmbh",
    "wof:placetype":"venue"
},
  "geometry": {"coordinates":[12.367853,51.279385],"type":"Point"}
}