{
  "type": "Feature",
  "properties": {
    "iso:country":"DE",
    "sg:address":"Christian-R\u00f6tzel-Allee 23",
    "sg:city":"Nettetal",
    "sg:phone":"+49 2153/72072",
    "sg:postcode":"41334",
    "sg:province":"Nordrhein-Westfalen",
    "wof:name":"Petrol-tank Mineral\u00f6l-handels Gmbh",
    "wof:placetype":"venue"
},
  "geometry": {"coordinates":[6.2395739555,51.2947158813],"type":"Point"}
}