{
  "type": "Feature",
  "properties": {
    "iso:country":"DE",
    "sg:address":"Robert-Schuman-Strasse 10",
    "sg:city":"Bocholt",
    "sg:phone":"+49 2871/40728",
    "sg:postcode":"46399",
    "sg:province":"Nordrhein-Westfalen",
    "wof:name":"Willkommen Bei Fro-sign",
    "wof:placetype":"venue"
},
  "geometry": {"coordinates":[6.614361,51.847504],"type":"Point"}
}