{
  "type": "Feature",
  "properties": {
    "iso:country":"DE",
    "sg:address":"Mainzer Str. 5",
    "sg:city":"Oberdiebach",
    "sg:postcode":"55413",
    "sg:province":"Rheinland-Pfalz",
    "wof:name":"Konzepte Und Systeme Bautr\u00e4ger-immobilien Gmbh",
    "wof:placetype":"venue"
},
  "geometry": {"coordinates":[7.78847,50.042671],"type":"Point"}
}