{
  "type": "Feature",
  "properties": {
    "iso:country":"DE",
    "sg:address":"Christine-Englerth-Str. 5",
    "sg:city":"Recklinghausen",
    "sg:phone":"+49 2361/88569",
    "sg:postcode":"45665",
    "sg:province":"Nordrhein-Westfalen",
    "wof:name":"J. Debelak E. K.",
    "wof:placetype":"venue"
},
  "geometry": {"coordinates":[7.24683,51.60561],"type":"Point"}
}