{
  "type": "Feature",
  "properties": {
    "iso:country":"DE",
    "sg:address":"Weidenstr. 7",
    "sg:city":"Ravensburg",
    "sg:phone":"+49 751/25932",
    "sg:postcode":"88212",
    "sg:province":"Baden-W\u00fcrttemberg",
    "wof:name":"Willy M\u00fcller",
    "wof:placetype":"venue"
},
  "geometry": {"coordinates":[9.619071,47.790798],"type":"Point"}
}