{
  "type": "Feature",
  "properties": {
    "iso:country":"DE",
    "sg:address":"Cassellastr. 30 -32",
    "sg:city":"Frankfurt",
    "sg:phone":"+49 69/618003",
    "sg:postcode":"60386",
    "sg:province":"Hessen",
    "wof:name":"Arcus Architekt",
    "wof:placetype":"venue"
},
  "geometry": {"coordinates":[8.758024,50.131489],"type":"Point"}
}