{
  "type": "Feature",
  "properties": {
    "iso:country":"DE",
    "sg:address":"Baustr. 19",
    "sg:city":"Wolgast",
    "sg:phone":"+49 3836/203298",
    "sg:postcode":"17438",
    "sg:province":"Mecklenburg-Vorpommern",
    "wof:name":"Reisecenter Delphini Gmbh",
    "wof:placetype":"venue"
},
  "geometry": {"coordinates":[13.7642650604,54.0564308167],"type":"Point"}
}