{
  "type": "Feature",
  "properties": {
    "iso:country":"DE",
    "sg:address":"Lemsdorfer Weg 3",
    "sg:city":"Magdeburg",
    "sg:phone":"+49 391/5613324",
    "sg:postcode":"39112",
    "sg:province":"Sachsen-Anhalt",
    "wof:name":"J. Heppner Immobilienmakler",
    "wof:placetype":"venue"
},
  "geometry": {"coordinates":[11.6034145355,52.1109199524],"type":"Point"}
}