{
  "type": "Feature",
  "properties": {
    "iso:country":"DE",
    "sg:address":"Neustadtring 47 a",
    "sg:city":"Braunschweig",
    "sg:phone":"+49 531/577886",
    "sg:postcode":"38114",
    "sg:province":"Niedersachsen",
    "wof:name":"Blumen-wolf Am Ring Kg",
    "wof:placetype":"venue"
},
  "geometry": {"coordinates":[10.50489,52.271824],"type":"Point"}
}