{
  "type": "Feature",
  "properties": {
    "iso:country":"DE",
    "sg:address":"Wilhelmsaue 9",
    "sg:city":"Berlin",
    "sg:phone":"+49 30/8737584",
    "sg:postcode":"10715",
    "sg:province":"Berlin",
    "wof:name":"Aka-autoglasscheiben- Service Gmbh",
    "wof:placetype":"venue"
},
  "geometry": {"coordinates":[13.3276386261,52.4853172302],"type":"Point"}
}