{
  "type": "Feature",
  "properties": {
    "iso:country":"DE",
    "sg:address":"Allmend 22",
    "sg:city":"Schenkenzell",
    "sg:phone":"+49 7836/349",
    "sg:postcode":"77773",
    "sg:province":"Baden-W\u00fcrttemberg",
    "wof:name":"Johannes Haas Spedition Inh. Christoph Haas",
    "wof:placetype":"venue"
},
  "geometry": {"coordinates":[8.3685092926,48.3059577942],"type":"Point"}
}