{
  "type": "Feature",
  "properties": {
    "iso:country":"DE",
    "sg:address":"Seestr. 26",
    "sg:city":"Drolshagen",
    "sg:phone":"+49 2763/91580",
    "sg:postcode":"57489",
    "sg:province":"Nordrhein-Westfalen",
    "wof:name":"A. Bieker Ingenieur",
    "wof:placetype":"venue"
},
  "geometry": {"coordinates":[7.7935261726,51.0701332092],"type":"Point"}
}