{
  "type": "Feature",
  "properties": {
    "iso:country":"DE",
    "sg:address":"Laufenstr. 40",
    "sg:city":"Monschau",
    "sg:phone":"+49 2472/3590",
    "sg:postcode":"52156",
    "sg:province":"Nordrhein-Westfalen",
    "wof:name":"Restaurant Zur Post",
    "wof:placetype":"venue"
},
  "geometry": {"coordinates":[6.2402391434,50.5555076599],"type":"Point"}
}