{
  "type": "Feature",
  "properties": {
    "iso:country":"DE",
    "sg:address":"Regnitzstr. 18 b",
    "sg:city":"Bamberg",
    "sg:postcode":"96052",
    "sg:province":"Bayern",
    "wof:name":"Elflein Logistik Gmbh",
    "wof:placetype":"venue"
},
  "geometry": {"coordinates":[10.8688077927,49.9065742493],"type":"Point"}
}