{
  "type": "Feature",
  "properties": {
    "iso:country":"DE",
    "sg:address":"Allee 2-4",
    "sg:city":"Roth",
    "sg:phone":"+49 9171/970322",
    "sg:postcode":"91154",
    "sg:province":"Bayern",
    "wof:name":"Redaktion Roth- Hiltpoltsteiner Volkszeitung",
    "wof:placetype":"venue"
},
  "geometry": {"coordinates":[11.093120575,49.2455329895],"type":"Point"}
}