{
  "type": "Feature",
  "properties": {
    "iso:country":"DE",
    "sg:address":"Scharfstr. 1",
    "sg:city":"Mainburg",
    "sg:phone":"+49 8751/4136",
    "sg:postcode":"84048",
    "sg:province":"Bayern",
    "wof:name":"Arturs Chaplin",
    "wof:placetype":"venue"
},
  "geometry": {"coordinates":[11.7874088287,48.6414146423],"type":"Point"}
}