{
  "type": "Feature",
  "properties": {
    "iso:country":"DE",
    "sg:address":"Hermannsh\u00f6he 46a",
    "sg:city":"Bochum",
    "sg:phone":"+49 234/37238",
    "sg:postcode":"44789",
    "sg:province":"Nordrhein-Westfalen",
    "wof:name":"Sco Filter Gmbh",
    "wof:placetype":"venue"
},
  "geometry": {"coordinates":[7.22270298,51.476524353],"type":"Point"}
}