{
  "type": "Feature",
  "properties": {
    "iso:country":"DE",
    "sg:address":"Marktplatz 19",
    "sg:city":"Greding",
    "sg:phone":"+49 8463/224",
    "sg:postcode":"91171",
    "sg:province":"Bayern",
    "wof:name":"J. B\u00f6sl Lagerhaus",
    "wof:placetype":"venue"
},
  "geometry": {"coordinates":[11.353799,49.045971],"type":"Point"}
}