{
  "type": "Feature",
  "properties": {
    "iso:country":"DE",
    "sg:address":"M\u00fchlweg 15",
    "sg:city":"Pegnitz",
    "sg:phone":"+49 9241",
    "sg:postcode":"91257",
    "sg:province":"Bayern",
    "wof:name":"Orthop\u00e4dische Praxis Dr. Med. Thomas Stumptner",
    "wof:placetype":"venue"
},
  "geometry": {"coordinates":[11.544017,49.751476],"type":"Point"}
}