{
  "type": "Feature",
  "properties": {
    "iso:country":"DE",
    "sg:address":"Steinweg 5",
    "sg:city":"Rednitzhembach",
    "sg:phone":"+49 9122/62800",
    "sg:postcode":"91126",
    "sg:province":"Bayern",
    "wof:name":"Planungsb\u00fcro F\u00fcr E-technik Stefan Beck",
    "wof:placetype":"venue"
},
  "geometry": {"coordinates":[11.0711593628,49.2972946167],"type":"Point"}
}