{
  "type": "Feature",
  "properties": {
    "iso:country":"DE",
    "sg:address":"Hauptstr. 34",
    "sg:city":"Karlstadt",
    "sg:phone":"+49 9353/8471",
    "sg:postcode":"97753",
    "sg:province":"Bayern",
    "wof:name":"Alt Franken",
    "wof:placetype":"venue"
},
  "geometry": {"coordinates":[9.7640857697,49.9619789124],"type":"Point"}
}