{
  "type": "Feature",
  "properties": {
    "iso:country":"DE",
    "sg:address":"Asternstr. 14",
    "sg:city":"Lenting",
    "sg:phone":"+49 8456/912200",
    "sg:postcode":"85101",
    "sg:province":"Bayern",
    "wof:name":"Innenausbau Gmbh Martin Meyer",
    "wof:placetype":"venue"
},
  "geometry": {"coordinates":[11.453254,48.805042],"type":"Point"}
}