{
  "type": "Feature",
  "properties": {
    "iso:country":"DE",
    "sg:address":"Friesenstr. 2",
    "sg:city":"Papenburg",
    "sg:postcode":"26871",
    "sg:province":"Niedersachsen",
    "wof:name":"Bunte & Bunte Gmbh",
    "wof:placetype":"venue"
},
  "geometry": {"coordinates":[7.3905229568,53.0910339355],"type":"Point"}
}