{
  "type": "Feature",
  "properties": {
    "iso:country":"DE",
    "sg:address":"Nu\u00dfbaumstr. 77",
    "sg:city":"Solingen",
    "sg:phone":"+49 212/60584",
    "sg:postcode":"42699",
    "sg:province":"Nordrhein-Westfalen",
    "wof:name":"J. Buchm\u00fcller Architekt",
    "wof:placetype":"venue"
},
  "geometry": {"coordinates":[7.00674,51.143578],"type":"Point"}
}