{
  "type": "Feature",
  "properties": {
    "iso:country":"DE",
    "sg:address":"Lehnschulzenstr. 22",
    "sg:city":"Finowfurt",
    "sg:phone":"+49 3335/7235",
    "sg:postcode":"16244",
    "sg:province":"Brandenburg",
    "wof:name":"Hans-joachim Grothe Ingenieur",
    "wof:placetype":"venue"
},
  "geometry": {"coordinates":[13.6749229431,52.8481483459],"type":"Point"}
}