{
  "type": "Feature",
  "properties": {
    "iso:country":"DE",
    "sg:address":"Bundesstr. 52",
    "sg:city":"Hattstedt",
    "sg:postcode":"25856",
    "sg:province":"Schleswig-Holstein",
    "wof:name":"Der Friesenb\u00e4cker Mariechen Kock",
    "wof:placetype":"venue"
},
  "geometry": {"coordinates":[9.023364,54.529694],"type":"Point"}
}