{
  "type": "Feature",
  "properties": {
    "iso:country":"DE",
    "sg:address":"Neue Str. 12",
    "sg:city":"Gro\u00dfkugel",
    "sg:phone":"+49 34605/20049",
    "sg:postcode":"06184",
    "sg:province":"Sachsen-Anhalt",
    "wof:name":"Christine Wendt",
    "wof:placetype":"venue"
},
  "geometry": {"coordinates":[12.147898674,51.4145011902],"type":"Point"}
}