{
  "type": "Feature",
  "properties": {
    "iso:country":"DE",
    "sg:address":"Tiefentalstr. 8",
    "sg:city":"Karlsruhe",
    "sg:phone":"+49 721/473454",
    "sg:postcode":"76228",
    "sg:province":"Baden-W\u00fcrttemberg",
    "wof:name":"P. Boritsch",
    "wof:placetype":"venue"
},
  "geometry": {"coordinates":[8.463252,48.982071],"type":"Point"}
}