{
  "type": "Feature",
  "properties": {
    "iso:country":"DE",
    "sg:address":"Liedberger Str. 5",
    "sg:city":"Korschenbroich",
    "sg:phone":"+49 2161/642188",
    "sg:postcode":"41352",
    "sg:province":"Nordrhein-Westfalen",
    "wof:name":"Willi Frommen",
    "wof:placetype":"venue"
},
  "geometry": {"coordinates":[6.531051,51.183182],"type":"Point"}
}