{
  "type": "Feature",
  "properties": {
    "iso:country":"DE",
    "sg:address":"Zossener Str. 46",
    "sg:city":"Sperenberg",
    "sg:phone":"+49 33703/7359",
    "sg:postcode":"15838",
    "sg:province":"Brandenburg",
    "wof:name":"Heinz Schade",
    "wof:placetype":"venue"
},
  "geometry": {"coordinates":[13.364971,52.143307],"type":"Point"}
}