{
  "type": "Feature",
  "properties": {
    "iso:country":"DE",
    "sg:address":"Bahnhofstr. 98 a",
    "sg:city":"Herten",
    "sg:phone":"+49 209/611098",
    "sg:postcode":"45701",
    "sg:province":"Nordrhein-Westfalen",
    "wof:name":"Mariola Gryczycha Praxis F\u00fcr Krankengymnastik",
    "wof:placetype":"venue"
},
  "geometry": {"coordinates":[7.085295,51.606091],"type":"Point"}
}