{
  "type": "Feature",
  "properties": {
    "iso:country":"DE",
    "sg:address":"Otto-Sch\u00e4ffler-Str. 44",
    "sg:city":"Bretzfeld",
    "sg:phone":"+49 7946/2215",
    "sg:postcode":"74626",
    "sg:province":"Baden-W\u00fcrttemberg",
    "wof:name":"Weingut Traube Mai",
    "wof:placetype":"venue"
},
  "geometry": {"coordinates":[9.4640636444,49.1408462524],"type":"Point"}
}