{
  "type": "Feature",
  "properties": {
    "iso:country":"DE",
    "sg:address":"Singerhoffstr. 2",
    "sg:city":"Dortmund",
    "sg:phone":"+49 231/779671",
    "sg:postcode":"44225",
    "sg:province":"Nordrhein-Westfalen",
    "wof:name":"Don Camillo & Peppone",
    "wof:placetype":"venue"
},
  "geometry": {"coordinates":[7.4369301796,51.4753379822],"type":"Point"}
}