{
  "type": "Feature",
  "properties": {
    "iso:country":"DE",
    "sg:address":"Haroldstr. 34",
    "sg:city":"D\u00fcsseldorf",
    "sg:phone":"+49 211/134150",
    "sg:postcode":"40213",
    "sg:province":"Nordrhein-Westfalen",
    "wof:name":"H. Grothe",
    "wof:placetype":"venue"
},
  "geometry": {"coordinates":[6.7750120163,51.2192153931],"type":"Point"}
}