{
  "type": "Feature",
  "properties": {
    "iso:country":"DE",
    "sg:address":"Gollnowstr. 20",
    "sg:city":"Sta\u00dffurt",
    "sg:phone":"+49 3925/382227",
    "sg:postcode":"39418",
    "sg:province":"Sachsen-Anhalt",
    "wof:name":"Wolfgang Koch",
    "wof:placetype":"venue"
},
  "geometry": {"coordinates":[11.586753,51.849171],"type":"Point"}
}