{
  "type": "Feature",
  "properties": {
    "iso:country":"DE",
    "sg:address":"Kleinr\u00fcckerswalder Str. 3",
    "sg:city":"Annaberg-Buchholz",
    "sg:phone":"+49 3733/22533",
    "sg:postcode":"09456",
    "sg:province":"Sachsen",
    "wof:name":"M. Tappert",
    "wof:placetype":"venue"
},
  "geometry": {"coordinates":[13.0078191757,50.576133728],"type":"Point"}
}