{
  "type": "Feature",
  "properties": {
    "iso:country":"DE",
    "sg:address":"Burbankstr. 28",
    "sg:city":"Bonn",
    "sg:phone":"+49 228/482192",
    "sg:postcode":"53229",
    "sg:province":"Nordrhein-Westfalen",
    "wof:name":"Verlag Claus Divossen",
    "wof:placetype":"venue"
},
  "geometry": {"coordinates":[7.1454458237,50.7584915161],"type":"Point"}
}