{
  "type": "Feature",
  "properties": {
    "iso:country":"DE",
    "sg:city":"H\u00fcrth",
    "sg:postcode":"50354",
    "sg:province":"Nordrhein-Westfalen",
    "wof:name":"Rote Ohren",
    "wof:placetype":"venue"
},
  "geometry": {"coordinates":[6.879661,50.880096],"type":"Point"}
}