{
  "type": "Feature",
  "properties": {
    "iso:country":"DE",
    "sg:address":"Lange Reihe 21",
    "sg:city":"Kiel",
    "sg:phone":"+49 431/93635",
    "sg:postcode":"24103",
    "sg:province":"Schleswig-Holstein",
    "wof:name":"Erika Mross King George",
    "wof:placetype":"venue"
},
  "geometry": {"coordinates":[10.1323108673,54.3193054199],"type":"Point"}
}