{
  "type": "Feature",
  "properties": {
    "iso:country":"DE",
    "sg:address":"Albrechtstr. 11",
    "sg:city":"Hannover",
    "sg:phone":"+49 511/562176",
    "sg:postcode":"30627",
    "sg:province":"Niedersachsen",
    "wof:name":"Erich Siebert",
    "wof:placetype":"venue"
},
  "geometry": {"coordinates":[9.8324298859,52.3815803528],"type":"Point"}
}