{
  "type": "Feature",
  "properties": {
    "iso:country":"DE",
    "sg:address":"Ernst-Th\u00e4lmann-Allee 38",
    "sg:city":"Moritzburg",
    "sg:postcode":"01468",
    "sg:province":"Sachsen",
    "wof:name":"Evangelisches Pfarramt",
    "wof:placetype":"venue"
},
  "geometry": {"coordinates":[13.679889679,51.1426086426],"type":"Point"}
}