{
  "type": "Feature",
  "properties": {
    "iso:country":"DE",
    "sg:address":"Strandpromenade 44",
    "sg:city":"Ostseebad Binz",
    "sg:phone":"+49 38393/40170",
    "sg:postcode":"18609",
    "sg:province":"Mecklenburg-Vorpommern",
    "wof:name":"Eiscafe Adriana",
    "wof:placetype":"venue"
},
  "geometry": {"coordinates":[13.60758,54.405674],"type":"Point"}
}