{
  "type": "Feature",
  "properties": {
    "iso:country":"DE",
    "sg:address":"Hauptstr. 47",
    "sg:city":"Friedrichsbrunn",
    "sg:phone":"+49 39487/71271",
    "sg:postcode":"06507",
    "sg:province":"Sachsen-Anhalt",
    "wof:name":"Walter Kranert",
    "wof:placetype":"venue"
},
  "geometry": {"coordinates":[11.0345630646,51.6873817444],"type":"Point"}
}