{
  "type": "Feature",
  "properties": {
    "iso:country":"DE",
    "sg:address":"Jakobistr. 15",
    "sg:city":"Hannover",
    "sg:postcode":"30163",
    "sg:province":"Niedersachsen",
    "wof:name":"Knop Gmbh",
    "wof:placetype":"venue"
},
  "geometry": {"coordinates":[9.746633,52.389496],"type":"Point"}
}