{
  "type": "Feature",
  "properties": {
    "iso:country":"DE",
    "sg:address":"Neckarstr. 198",
    "sg:city":"Stuttgart",
    "sg:phone":"+49 711/2622864",
    "sg:postcode":"70190",
    "sg:province":"Baden-W\u00fcrttemberg",
    "wof:name":"Bernd Sch\u00f6ck",
    "wof:placetype":"venue"
},
  "geometry": {"coordinates":[9.199807,48.791534],"type":"Point"}
}