{
  "type": "Feature",
  "properties": {
    "iso:country":"DE",
    "sg:address":"Hechendorfer Str. 142",
    "sg:city":"Herrsching",
    "sg:phone":"+49 8152/2220",
    "sg:postcode":"82211",
    "sg:province":"Bayern",
    "wof:name":"Diatec Medizintechnik Vertriebs Gmbh",
    "wof:placetype":"venue"
},
  "geometry": {"coordinates":[11.17102,48.001781],"type":"Point"}
}