{
  "type": "Feature",
  "properties": {
    "iso:country":"DE",
    "sg:address":"Bahnhofstr. 27",
    "sg:city":"Bodelshausen",
    "sg:phone":"+49 4974/7171008",
    "sg:postcode":"72411",
    "sg:province":"Baden-W\u00fcrttemberg",
    "wof:name":"Volksbank M\u00f6ssingen Eg",
    "wof:placetype":"venue"
},
  "geometry": {"coordinates":[8.97332,48.393005],"type":"Point"}
}