{
  "type": "Feature",
  "properties": {
    "iso:country":"DE",
    "sg:address":"J\u00fcterboger Str. 20",
    "sg:city":"M\u00fcgeln",
    "sg:phone":"+49 35384/20504",
    "sg:postcode":"06928",
    "sg:province":"Sachsen-Anhalt",
    "wof:name":"F. Luczak",
    "wof:placetype":"venue"
},
  "geometry": {"coordinates":[13.0248966217,51.8560829163],"type":"Point"}
}