{
  "type": "Feature",
  "properties": {
    "iso:country":"DE",
    "sg:address":"Kreuzlingerforststrasse 31",
    "sg:city":"Gauting",
    "sg:phone":"+49 89/8501875",
    "sg:postcode":"82131",
    "sg:province":"Bayern",
    "wof:name":"Haller-meurer Ersatzteilvertrieb & Ersatzger\u00e4te",
    "wof:placetype":"venue"
},
  "geometry": {"coordinates":[11.378611,48.079193],"type":"Point"}
}