{
  "type": "Feature",
  "properties": {
    "iso:country":"DE",
    "sg:address":"Hemmerhof 121",
    "sg:city":"Essen",
    "sg:phone":"+49 201/583934",
    "sg:postcode":"45277",
    "sg:province":"Nordrhein-Westfalen",
    "wof:name":"Erwin A. Von Bergen Rechtsanwalt",
    "wof:placetype":"venue"
},
  "geometry": {"coordinates":[7.0799307823,51.4155044556],"type":"Point"}
}