{
  "type": "Feature",
  "properties": {
    "iso:country":"DE",
    "sg:address":"Stauseestr. 21",
    "sg:city":"Dingolfing",
    "sg:phone":"+49 8731/37770",
    "sg:postcode":"84130",
    "sg:province":"Bayern",
    "wof:name":"Apelb\u00f6ck Ingenieurb\u00fcro Gmbh",
    "wof:placetype":"venue"
},
  "geometry": {"coordinates":[12.4819364548,48.6396369934],"type":"Point"}
}