{
  "type": "Feature",
  "properties": {
    "iso:country":"DE",
    "sg:address":"Fritz-Weber-Str. 12",
    "sg:city":"Heidenau",
    "sg:phone":"+49 3529/523278",
    "sg:postcode":"01809",
    "sg:province":"Sachsen",
    "wof:name":"Heinz Schmidt",
    "wof:placetype":"venue"
},
  "geometry": {"coordinates":[13.863089,50.977879],"type":"Point"}
}