{
  "type": "Feature",
  "properties": {
    "iso:country":"DE",
    "sg:address":"Am Hellenberg 26",
    "sg:city":"Niederzissen",
    "sg:postcode":"56651",
    "sg:province":"Rheinland-Pfalz",
    "wof:name":"Schr\u00f6der Verwaltungsges. Mbh",
    "wof:placetype":"venue"
},
  "geometry": {"coordinates":[7.2123799324,50.4575500488],"type":"Point"}
}