{
  "type": "Feature",
  "properties": {
    "iso:country":"DE",
    "sg:address":"Westmarkstr. 35",
    "sg:city":"Oberhausen",
    "sg:phone":"+49 208/854033",
    "sg:postcode":"46149",
    "sg:province":"Nordrhein-Westfalen",
    "wof:name":"Hundeschule Pelzer - Oberhuasen/rheinland",
    "wof:placetype":"venue"
},
  "geometry": {"coordinates":[6.827562,51.491871],"type":"Point"}
}