{
  "type": "Feature",
  "properties": {
    "iso:country":"DE",
    "sg:address":"Bahnhofstr. 23",
    "sg:city":"Nordgermersleben",
    "sg:phone":"+49 39062/413",
    "sg:postcode":"39343",
    "sg:province":"Sachsen-Anhalt",
    "wof:name":"Beer Baumarkt Gmbh",
    "wof:placetype":"venue"
},
  "geometry": {"coordinates":[11.330471,52.209599],"type":"Point"}
}