{
  "type": "Feature",
  "properties": {
    "iso:country":"DE",
    "sg:address":"S\u00fcdstr. 10",
    "sg:city":"Kehl",
    "sg:phone":"+49 7851/483136",
    "sg:postcode":"77694",
    "sg:province":"Baden-W\u00fcrttemberg",
    "wof:name":"Hk Asbestsanierung Und Entsorgungstechnik Gmbh",
    "wof:placetype":"venue"
},
  "geometry": {"coordinates":[7.8095140457,48.5821647644],"type":"Point"}
}