{
  "type": "Feature",
  "properties": {
    "iso:country":"DE",
    "sg:address":"Gr\u00f6belweg 16b",
    "sg:city":"Osnabr\u00fcck",
    "sg:phone":"+49 541/596203",
    "sg:postcode":"49082",
    "sg:province":"Niedersachsen",
    "wof:name":"M. Jong",
    "wof:placetype":"venue"
},
  "geometry": {"coordinates":[8.02411,52.236343],"type":"Point"}
}