{
  "type": "Feature",
  "properties": {
    "iso:country":"DE",
    "sg:address":"Krumme Steig 37",
    "sg:city":"Pirmasens",
    "sg:phone":"+49 6331/99052",
    "sg:postcode":"66953",
    "sg:province":"Rheinland-Pfalz",
    "wof:name":"Kbb - Brandschutzanlagen Gmbh",
    "wof:placetype":"venue"
},
  "geometry": {"coordinates":[7.62659,49.21336],"type":"Point"}
}