{
  "type": "Feature",
  "properties": {
    "iso:country":"DE",
    "sg:address":"Nordheimer Str. 14",
    "sg:city":"Ostheim",
    "sg:postcode":"97645",
    "sg:province":"Bayern",
    "wof:name":"Terragetik Gmbh & Co. Innovations Kg",
    "wof:placetype":"venue"
},
  "geometry": {"coordinates":[10.2199211121,50.4603347778],"type":"Point"}
}