{
  "type": "Feature",
  "properties": {
    "iso:country":"DE",
    "sg:address":"W\u00fcrdinghauser Str. 39",
    "sg:city":"Kirchhundem",
    "sg:phone":"+49 2723/3384",
    "sg:postcode":"57399",
    "sg:province":"Nordrhein-Westfalen",
    "wof:name":"G. Beckmann",
    "wof:placetype":"venue"
},
  "geometry": {"coordinates":[8.1231708527,51.0843505859],"type":"Point"}
}