{
  "type": "Feature",
  "properties": {
    "iso:country":"DE",
    "sg:address":"Bremer Tor 9",
    "sg:city":"Visbek",
    "sg:phone":"+49 4445/402",
    "sg:postcode":"49429",
    "sg:province":"Niedersachsen",
    "wof:name":"Theodor Kluth Inh. J\u00fcrgen Kluth",
    "wof:placetype":"venue"
},
  "geometry": {"coordinates":[8.3138656616,52.8384399414],"type":"Point"}
}