{
  "type": "Feature",
  "properties": {
    "iso:country":"DE",
    "sg:address":"Auf dem Meere 47",
    "sg:city":"L\u00fcneburg",
    "sg:phone":"+49 4131/24200",
    "sg:postcode":"21335",
    "sg:province":"Niedersachsen",
    "wof:name":"Geb Bautr\u00e4ger- Und Entwicklungs- Gmbh",
    "wof:placetype":"venue"
},
  "geometry": {"coordinates":[10.41414,53.247585],"type":"Point"}
}