{
  "type": "Feature",
  "properties": {
    "iso:country":"DE",
    "sg:address":"Ferdinand-Lassalle-Str. 40",
    "sg:city":"Reutlingen",
    "sg:phone":"+49 7121/54076",
    "sg:postcode":"72770",
    "sg:province":"Baden-W\u00fcrttemberg",
    "wof:name":"Panakeia Handel Und Untersuchungen Gmbh",
    "wof:placetype":"venue"
},
  "geometry": {"coordinates":[9.1519241333,48.4906349182],"type":"Point"}
}