{
  "type": "Feature",
  "properties": {
    "iso:country":"DE",
    "sg:address":"Goetheweg 17",
    "sg:city":"M\u00fchlhausen",
    "sg:phone":"+49 36018/12416",
    "sg:postcode":"99974",
    "sg:province":"Th\u00fcringen",
    "wof:name":"Wiesel & Partner",
    "wof:placetype":"venue"
},
  "geometry": {"coordinates":[10.4565057755,51.2026863098],"type":"Point"}
}