{
  "type": "Feature",
  "properties": {
    "iso:country":"DE",
    "sg:address":"Graf-Stauffenberg-Str. 21",
    "sg:city":"Alzey",
    "sg:phone":"+49 6731/1681",
    "sg:postcode":"55232",
    "sg:province":"Rheinland-Pfalz",
    "wof:name":"Elimor Import- Und Export- Handels Gmbh",
    "wof:placetype":"venue"
},
  "geometry": {"coordinates":[8.1147241592,49.7434463501],"type":"Point"}
}