{
  "type": "Feature",
  "properties": {
    "iso:country":"DE",
    "sg:address":"Straubinger Str. 42",
    "sg:city":"Abensberg",
    "sg:phone":"+49 9443/5919",
    "sg:postcode":"93326",
    "sg:province":"Bayern",
    "wof:name":"Asmo",
    "wof:placetype":"venue"
},
  "geometry": {"coordinates":[11.8587713242,48.8109207153],"type":"Point"}
}