{
  "type": "Feature",
  "properties": {
    "iso:country":"DE",
    "sg:address":"Friedrichshulder Weg 163",
    "sg:city":"Halstenbek",
    "sg:phone":"+49 4101/45051",
    "sg:postcode":"25469",
    "sg:province":"Schleswig-Holstein",
    "wof:name":"Hubert Mayer",
    "wof:placetype":"venue"
},
  "geometry": {"coordinates":[9.832757,53.618019],"type":"Point"}
}