{
  "type": "Feature",
  "properties": {
    "iso:country":"DE",
    "sg:address":"Potsdamer Str. 100",
    "sg:city":"Berlin",
    "sg:phone":"+49 30/2640327",
    "sg:postcode":"10785",
    "sg:province":"Berlin",
    "wof:name":"Parsec Gesellschaft F\u00fcr Softwareentwicklung Und",
    "wof:placetype":"venue"
},
  "geometry": {"coordinates":[13.3643522263,52.5018424988],"type":"Point"}
}