{
  "type": "Feature",
  "properties": {
    "iso:country":"DE",
    "sg:address":"Windischbucher Str. 22",
    "sg:city":"Krautheim",
    "sg:phone":"+49 6294/753",
    "sg:postcode":"74238",
    "sg:province":"Baden-W\u00fcrttemberg",
    "wof:name":"Kurt Sigmann",
    "wof:placetype":"venue"
},
  "geometry": {"coordinates":[9.612289,49.414944],"type":"Point"}
}