{
  "type": "Feature",
  "properties": {
    "iso:country":"DE",
    "sg:address":"Am Bahnhof 5",
    "sg:city":"Quadensch\u00f6nfeld",
    "sg:postcode":"17237",
    "sg:province":"Mecklenburg-Vorpommern",
    "wof:name":"Landgasthof \u00b4st.moritz\u00b4",
    "wof:placetype":"venue"
},
  "geometry": {"coordinates":[13.2614555359,53.4172782898],"type":"Point"}
}