{
  "type": "Feature",
  "properties": {
    "iso:country":"DE",
    "sg:address":"Pappelallee 1",
    "sg:city":"Greifswald",
    "sg:phone":"+49 3834/872570",
    "sg:postcode":"17489",
    "sg:province":"Mecklenburg-Vorpommern",
    "wof:name":"Medizinisches Fachhaus Hansen & Enderlein Gmbh",
    "wof:placetype":"venue"
},
  "geometry": {"coordinates":[13.4137878418,54.088218689],"type":"Point"}
}