{
  "type": "Feature",
  "properties": {
    "iso:country":"DE",
    "sg:address":"Burgstr. 1",
    "sg:city":"Kronburg",
    "sg:phone":"+49 8394/1671",
    "sg:postcode":"87758",
    "sg:province":"Bayern",
    "wof:name":"Archiv Der Freiherren Von Vequel-westernach",
    "wof:placetype":"venue"
},
  "geometry": {"coordinates":[10.161132,47.904377],"type":"Point"}
}