{
  "type": "Feature",
  "properties": {
    "iso:country":"DE",
    "sg:address":"Hauptstr. 32",
    "sg:city":"Schopfloch",
    "sg:phone":"+49 7443/3955",
    "sg:postcode":"72296",
    "sg:province":"Baden-W\u00fcrttemberg",
    "wof:name":"Apotheke Am B\u00fchl",
    "wof:placetype":"venue"
},
  "geometry": {"coordinates":[8.551538,48.453945],"type":"Point"}
}