{
  "type": "Feature",
  "properties": {
    "iso:country":"DE",
    "sg:address":"Ebbingen 39",
    "sg:city":"Walsrode",
    "sg:postcode":"29664",
    "sg:province":"Niedersachsen",
    "wof:name":"Scarf Verwalgungsges. Mbh",
    "wof:placetype":"venue"
},
  "geometry": {"coordinates":[9.5721330643,52.9079933167],"type":"Point"}
}