{
  "type": "Feature",
  "properties": {
    "iso:country":"DE",
    "sg:address":"Hartlaubstr. 35",
    "sg:city":"Bremen",
    "sg:phone":"+49 421/251897",
    "sg:postcode":"28355",
    "sg:province":"Bremen",
    "wof:name":"Heinz K\u00f6nig Gmbh",
    "wof:placetype":"venue"
},
  "geometry": {"coordinates":[8.9158420563,53.0904045105],"type":"Point"}
}