{
  "type": "Feature",
  "properties": {
    "iso:country":"DE",
    "sg:address":"Frankfurter Str. 41",
    "sg:city":"Heilbronn",
    "sg:phone":"+49 7131/68603",
    "sg:postcode":"74072",
    "sg:province":"Baden-W\u00fcrttemberg",
    "wof:name":"Pascham 1",
    "wof:placetype":"venue"
},
  "geometry": {"coordinates":[9.2089166641,49.1409034729],"type":"Point"}
}