{
  "type": "Feature",
  "properties": {
    "iso:country":"DE",
    "sg:address":"B\u00f6blinger Str. 19",
    "sg:city":"Holzgerlingen",
    "sg:phone":"+49 7031/602431",
    "sg:postcode":"71088",
    "sg:province":"Baden-W\u00fcrttemberg",
    "wof:name":"Karl Nestele Mech. Werkstatt",
    "wof:placetype":"venue"
},
  "geometry": {"coordinates":[9.011434,48.640747],"type":"Point"}
}