{
  "type": "Feature",
  "properties": {
    "iso:country":"DE",
    "sg:address":"Bahnhofstr. 3A",
    "sg:city":"Burgdorf",
    "sg:phone":"+49 5136/7561",
    "sg:postcode":"31303",
    "sg:province":"Niedersachsen",
    "wof:name":"Hoffmeister Glasbau Gmbh",
    "wof:placetype":"venue"
},
  "geometry": {"coordinates":[10.0037965775,52.4468154907],"type":"Point"}
}