{
  "type": "Feature",
  "properties": {
    "iso:country":"DE",
    "sg:address":"Ringstr. 36",
    "sg:city":"Ansbach",
    "sg:phone":"+49 981/94302",
    "sg:postcode":"91522",
    "sg:province":"Bayern",
    "wof:name":"Ernst Eschenbacher",
    "wof:placetype":"venue"
},
  "geometry": {"coordinates":[10.588675,49.301754],"type":"Point"}
}