{
  "type": "Feature",
  "properties": {
    "iso:country":"DE",
    "sg:address":"Rheinblickstr. 112",
    "sg:city":"Rheinbreitbach",
    "sg:phone":"+49 2224/73802",
    "sg:postcode":"53619",
    "sg:province":"Rheinland-Pfalz",
    "wof:name":"Friedrich-karl Monte Architekt",
    "wof:placetype":"venue"
},
  "geometry": {"coordinates":[7.237771,50.619217],"type":"Point"}
}