{
  "type": "Feature",
  "properties": {
    "iso:country":"DE",
    "sg:address":"Bahnhofstr. 19",
    "sg:city":"Kusel",
    "sg:phone":"+49 6381/40974",
    "sg:postcode":"66869",
    "sg:province":"Rheinland-Pfalz",
    "wof:name":"Mecklenburgische",
    "wof:placetype":"venue"
},
  "geometry": {"coordinates":[7.4034790993,49.5382575989],"type":"Point"}
}