{
  "type": "Feature",
  "properties": {
    "iso:country":"DE",
    "sg:address":"Br\u00fcckenstr. 6",
    "sg:city":"K\u00e4mpfelbach",
    "sg:phone":"+49 7231/984777",
    "sg:postcode":"75236",
    "sg:province":"Baden-W\u00fcrttemberg",
    "wof:name":"Manfred Frei",
    "wof:placetype":"venue"
},
  "geometry": {"coordinates":[8.6343832016,48.9328231812],"type":"Point"}
}