{
  "type": "Feature",
  "properties": {
    "iso:country":"DE",
    "sg:address":"Rosenthalerstr.62",
    "sg:city":"Berlin",
    "sg:phone":"+49 30",
    "sg:postcode":"10119",
    "sg:province":"Berlin",
    "wof:name":"M\u00fcllers Haarb\u00fcro",
    "wof:placetype":"venue"
},
  "geometry": {"coordinates":[13.403351,52.52776],"type":"Point"}
}