{
  "type": "Feature",
  "properties": {
    "iso:country":"DE",
    "sg:address":"Brunnenplatz 9",
    "sg:city":"Eppelborn",
    "sg:phone":"+49 6881/961620",
    "sg:postcode":"66571",
    "sg:province":"Saarland",
    "wof:name":"Hartsteinwerk Gihl Gmbh",
    "wof:placetype":"venue"
},
  "geometry": {"coordinates":[6.9510941505,49.4134292603],"type":"Point"}
}