{
  "type": "Feature",
  "properties": {
    "iso:country":"DE",
    "sg:address":"K\u00f6lner Str. 63",
    "sg:city":"Burscheid",
    "sg:phone":"+49 2174/2408",
    "sg:postcode":"51399",
    "sg:province":"Nordrhein-Westfalen",
    "wof:name":"G. Longerich",
    "wof:placetype":"venue"
},
  "geometry": {"coordinates":[7.1584768295,51.1042098999],"type":"Point"}
}