{
  "type": "Feature",
  "properties": {
    "iso:country":"DE",
    "sg:address":"Hauptstr. 46",
    "sg:city":"Nufringen",
    "sg:phone":"+49 7032/83747",
    "sg:postcode":"71154",
    "sg:province":"Baden-W\u00fcrttemberg",
    "wof:name":"Pub",
    "wof:placetype":"venue"
},
  "geometry": {"coordinates":[8.893017,48.623177],"type":"Point"}
}