{
  "type": "Feature",
  "properties": {
    "iso:country":"DE",
    "sg:address":"Hauptstr. 39",
    "sg:city":"Selsingen",
    "sg:phone":"+49 4284/1666",
    "sg:postcode":"27446",
    "sg:province":"Niedersachsen",
    "wof:name":"Heiner Morgenstern Rechtsanwalt",
    "wof:placetype":"venue"
},
  "geometry": {"coordinates":[9.2148141861,53.3715591431],"type":"Point"}
}