{
  "type": "Feature",
  "properties": {
    "iso:country":"DE",
    "sg:address":"Spessartstr. 2 a",
    "sg:city":"Biebergem\u00fcnd",
    "sg:phone":"+49 6050/911660",
    "sg:postcode":"63599",
    "sg:province":"Hessen",
    "wof:name":"Josef Prasch Kg",
    "wof:placetype":"venue"
},
  "geometry": {"coordinates":[9.2735776901,50.211807251],"type":"Point"}
}