{
  "type": "Feature",
  "properties": {
    "iso:country":"DE",
    "sg:address":"Humboldtstr. 16",
    "sg:city":"N\u00fcrnberg",
    "sg:postcode":"90443",
    "sg:province":"Bayern",
    "wof:name":"Cmi Immobilienhandel Gmbh",
    "wof:placetype":"venue"
},
  "geometry": {"coordinates":[11.0698032379,49.4368743896],"type":"Point"}
}