{
  "type": "Feature",
  "properties": {
    "iso:country":"DE",
    "sg:address":"Gr\u00fcnewaldstr. 30",
    "sg:city":"Mainz",
    "sg:phone":"+49 6131/7535",
    "sg:postcode":"55127",
    "sg:province":"Rheinland-Pfalz",
    "wof:name":"Jochen Gr\u00fcn Ingenieur",
    "wof:placetype":"venue"
},
  "geometry": {"coordinates":[8.1908664703,49.9648399353],"type":"Point"}
}