{
  "type": "Feature",
  "properties": {
    "iso:country":"DE",
    "sg:address":"Heinersdorfer Str. 4",
    "sg:city":"Schwedt",
    "sg:phone":"+49 3332/22925",
    "sg:postcode":"16303",
    "sg:province":"Brandenburg",
    "wof:name":"Otto Wendt",
    "wof:placetype":"venue"
},
  "geometry": {"coordinates":[14.28317,53.054428],"type":"Point"}
}