{
  "type": "Feature",
  "properties": {
    "iso:country":"DE",
    "sg:address":"Bonner Str. 10",
    "sg:city":"Remagen",
    "sg:postcode":"53424",
    "sg:province":"Rheinland-Pfalz",
    "wof:name":"Alcove Deutschland Gmbh",
    "wof:placetype":"venue"
},
  "geometry": {"coordinates":[7.2082948685,50.6228904724],"type":"Point"}
}