{
  "type": "Feature",
  "properties": {
    "iso:country":"DE",
    "sg:address":"Munscheider Str. 91",
    "sg:city":"Bochum",
    "sg:phone":"+49 2327/76866",
    "sg:postcode":"44869",
    "sg:province":"Nordrhein-Westfalen",
    "wof:name":"Behrens & Co.",
    "wof:placetype":"venue"
},
  "geometry": {"coordinates":[7.1714658737,51.4441871643],"type":"Point"}
}