{
  "type": "Feature",
  "properties": {
    "iso:country":"DE",
    "sg:address":"Nord-West-Ring 35",
    "sg:city":"Augustdorf",
    "sg:phone":"+49 5237/96960",
    "sg:postcode":"32832",
    "sg:province":"Nordrhein-Westfalen",
    "wof:name":"Ferrum-edelstahl-h\u00e4rterei Gmbh",
    "wof:placetype":"venue"
},
  "geometry": {"coordinates":[8.7082576752,51.9063072205],"type":"Point"}
}