{
  "type": "Feature",
  "properties": {
    "iso:country":"DE",
    "sg:address":"Rosenheimer Str. 4",
    "sg:city":"M\u00fcnchen",
    "sg:phone":"+49 89/484409",
    "sg:postcode":"81669",
    "sg:province":"Bayern",
    "wof:name":"Jam",
    "wof:placetype":"venue"
},
  "geometry": {"coordinates":[11.5882415771,48.1313705444],"type":"Point"}
}