{
  "type": "Feature",
  "properties": {
    "iso:country":"DE",
    "sg:address":"Werkstr 5",
    "sg:city":"B\u00f6hlen",
    "sg:phone":"+49 34206/6420",
    "sg:postcode":"04564",
    "sg:province":"Sachsen",
    "wof:name":"Bartec Benke Gmbh",
    "wof:placetype":"venue"
},
  "geometry": {"coordinates":[12.38119,51.201859],"type":"Point"}
}