{
  "type": "Feature",
  "properties": {
    "iso:country":"DE",
    "sg:address":"Falkstr. 38",
    "sg:city":"Frankfurt",
    "sg:phone":"+49 69/704111",
    "sg:postcode":"60487",
    "sg:province":"Hessen",
    "wof:name":"Le Marocain",
    "wof:placetype":"venue"
},
  "geometry": {"coordinates":[8.6484136581,50.1232337952],"type":"Point"}
}