{
  "type": "Feature",
  "properties": {
    "iso:country":"DE",
    "sg:address":"Lappacher Weg 28",
    "sg:city":"H\u00f6chstadt",
    "sg:phone":"+49 9193/1355",
    "sg:postcode":"91315",
    "sg:province":"Bayern",
    "wof:name":"Wilhelm Waller",
    "wof:placetype":"venue"
},
  "geometry": {"coordinates":[10.7991132736,49.6936073303],"type":"Point"}
}