{
  "type": "Feature",
  "properties": {
    "iso:country":"DE",
    "sg:address":"Kirner Str. 90 a",
    "sg:city":"Kirn",
    "sg:phone":"+49 6752/6846",
    "sg:postcode":"55606",
    "sg:province":"Rheinland-Pfalz",
    "wof:name":"Kiss Kreuznacher Initiative Schafft Stellen Ggmbh",
    "wof:placetype":"venue"
},
  "geometry": {"coordinates":[7.4611048698,49.7851600647],"type":"Point"}
}