{
  "type": "Feature",
  "properties": {
    "iso:country":"DE",
    "sg:address":"K\u00f6venig",
    "sg:city":"Kr\u00f6v",
    "sg:phone":"+49 6541/6802",
    "sg:postcode":"54536",
    "sg:province":"Rheinland-Pfalz",
    "wof:name":"Rudolf M\u00fcllers",
    "wof:placetype":"venue"
},
  "geometry": {"coordinates":[7.0802521706,49.9767494202],"type":"Point"}
}