{
  "type": "Feature",
  "properties": {
    "iso:country":"DE",
    "sg:address":"L\u00f6derburger Str. 22",
    "sg:city":"Sta\u00dffurt",
    "sg:phone":"+49 3925/930358",
    "sg:postcode":"39418",
    "sg:province":"Sachsen-Anhalt",
    "wof:name":"Gruetzmacher Ohg",
    "wof:placetype":"venue"
},
  "geometry": {"coordinates":[11.575921,51.858395],"type":"Point"}
}