{
  "type": "Feature",
  "properties": {
    "iso:country":"DE",
    "sg:address":"Im Eichwald 11",
    "sg:city":"Dornburg",
    "sg:phone":"+49 6436/7426",
    "sg:postcode":"65599",
    "sg:province":"Hessen",
    "wof:name":"Dieter Bill Architekt",
    "wof:placetype":"venue"
},
  "geometry": {"coordinates":[8.0291461945,50.5122718811],"type":"Point"}
}