{
  "type": "Feature",
  "properties": {
    "iso:country":"DE",
    "sg:address":"Steinstr. 5",
    "sg:city":"Lampertheim",
    "sg:phone":"+49 6206/910240",
    "sg:postcode":"68623",
    "sg:province":"Hessen",
    "wof:name":"Richard Hinz",
    "wof:placetype":"venue"
},
  "geometry": {"coordinates":[8.4746084213,49.5984840393],"type":"Point"}
}