{
  "type": "Feature",
  "properties": {
    "iso:country":"DE",
    "sg:address":"Backoffenstr. 6",
    "sg:city":"Aschaffenburg",
    "sg:phone":"+49 6021/930901",
    "sg:postcode":"63739",
    "sg:province":"Bayern",
    "wof:name":"Ursula Schleicher",
    "wof:placetype":"venue"
},
  "geometry": {"coordinates":[9.173187,49.972771],"type":"Point"}
}