{
  "type": "Feature",
  "properties": {
    "iso:country":"DE",
    "sg:address":"Professor-G\u00e4rtner-Str. 4",
    "sg:city":"Ochtrup",
    "sg:phone":"+49 2553/7328",
    "sg:postcode":"48607",
    "sg:province":"Nordrhein-Westfalen",
    "wof:name":"Stadtarchiv",
    "wof:placetype":"venue"
},
  "geometry": {"coordinates":[7.184747,52.20853],"type":"Point"}
}