{
  "type": "Feature",
  "properties": {
    "iso:country":"DE",
    "sg:address":"Schulstr. 1",
    "sg:city":"Gro\u00dfwechsungen",
    "sg:phone":"+49 36335/313",
    "sg:postcode":"99735",
    "sg:province":"Th\u00fcringen",
    "wof:name":"Ev. Kirche Grosswechsungen",
    "wof:placetype":"venue"
},
  "geometry": {"coordinates":[10.6893749237,51.4925613403],"type":"Point"}
}