{
  "type": "Feature",
  "properties": {
    "iso:country":"DE",
    "sg:address":"Junkersstr 4",
    "sg:city":"Viernheim",
    "sg:phone":"+49 6204/76754",
    "sg:postcode":"68519",
    "sg:province":"Hessen",
    "wof:name":"Faltermann Gmbh",
    "wof:placetype":"venue"
},
  "geometry": {"coordinates":[8.591533,49.545616],"type":"Point"}
}