{
  "type": "Feature",
  "properties": {
    "iso:country":"DE",
    "sg:address":"Schlo\u00dfwiese 37",
    "sg:city":"Essen",
    "sg:phone":"+49 201/671646",
    "sg:postcode":"45355",
    "sg:province":"Nordrhein-Westfalen",
    "wof:name":"Helmut Berger Architekt",
    "wof:placetype":"venue"
},
  "geometry": {"coordinates":[6.934899,51.467197],"type":"Point"}
}