{
  "type": "Feature",
  "properties": {
    "iso:country":"DE",
    "sg:address":"Potsdamer Allee 11",
    "sg:city":"Stahnsdorf",
    "sg:phone":"+49 3329/62034",
    "sg:postcode":"14532",
    "sg:province":"Brandenburg",
    "wof:name":"Hans K\u00fchnapfel",
    "wof:placetype":"venue"
},
  "geometry": {"coordinates":[13.2121210098,52.3926811218],"type":"Point"}
}