{
  "type": "Feature",
  "properties": {
    "iso:country":"DE",
    "sg:address":"Burgstr. 6",
    "sg:city":"Freiberg",
    "sg:phone":"+49 3731/39790",
    "sg:postcode":"09599",
    "sg:province":"Sachsen",
    "wof:name":"Hansj\u00f6rg H\u00fchnel Rechtsanwalt",
    "wof:placetype":"venue"
},
  "geometry": {"coordinates":[13.34379673,50.9173583984],"type":"Point"}
}