{
  "type": "Feature",
  "properties": {
    "iso:country":"DE",
    "sg:address":"Hengdorfer Str. 5",
    "sg:city":"Rohr",
    "sg:phone":"+49 9122/81701",
    "sg:postcode":"91189",
    "sg:province":"Bayern",
    "wof:name":"Hans R\u00fchl",
    "wof:placetype":"venue"
},
  "geometry": {"coordinates":[10.950323,49.3699],"type":"Point"}
}