{
  "type": "Feature",
  "properties": {
    "iso:country":"DE",
    "sg:address":"Wittelsbacherring 35",
    "sg:city":"Vilshofen",
    "sg:phone":"+49 8541/8431",
    "sg:postcode":"94474",
    "sg:province":"Bayern",
    "wof:name":"G. Unertl Und R. Lepschy Rechtsanw\u00e4lte",
    "wof:placetype":"venue"
},
  "geometry": {"coordinates":[13.1946763992,48.593547821],"type":"Point"}
}