{
  "type": "Feature",
  "properties": {
    "iso:country":"DE",
    "sg:address":"Hauptstr. 26",
    "sg:city":"Walldorf",
    "sg:phone":"+49 6227/82040",
    "sg:postcode":"69190",
    "sg:province":"Baden-W\u00fcrttemberg",
    "wof:name":"Hotel Zum Wei\u00dfen R\u00f6ssel",
    "wof:placetype":"venue"
},
  "geometry": {"coordinates":[8.6396741867,49.3021736145],"type":"Point"}
}