{
  "type": "Feature",
  "properties": {
    "iso:country":"DE",
    "sg:address":"K\u00e4hnermatt 1/2",
    "sg:city":"Lahr",
    "sg:phone":"+49 7821/906540",
    "sg:postcode":"77933",
    "sg:province":"Baden-W\u00fcrttemberg",
    "wof:name":"Fs-etiketten Gmbh",
    "wof:placetype":"venue"
},
  "geometry": {"coordinates":[7.8633871078,48.3099861145],"type":"Point"}
}