{
  "type": "Feature",
  "properties": {
    "iso:country":"DE",
    "sg:address":"Wiesengrundweg 3",
    "sg:city":"Aystetten",
    "sg:phone":"+49 821/4862806",
    "sg:postcode":"86482",
    "sg:province":"Bayern",
    "wof:name":"Buka-bau Gmbh",
    "wof:placetype":"venue"
},
  "geometry": {"coordinates":[10.7730436325,48.4065437317],"type":"Point"}
}