{
  "type": "Feature",
  "properties": {
    "iso:country":"DE",
    "sg:address":"Crailsheimstr. 3",
    "sg:city":"Traunstein",
    "sg:postcode":"83278",
    "sg:province":"Bayern",
    "wof:name":"Michael Borstner",
    "wof:placetype":"venue"
},
  "geometry": {"coordinates":[12.642217,47.86816],"type":"Point"}
}