{
  "type": "Feature",
  "properties": {
    "iso:country":"DE",
    "sg:address":"Kyllburger Str. 7 a",
    "sg:city":"Meisburg",
    "sg:phone":"+49 6599/961075",
    "sg:postcode":"54570",
    "sg:province":"Rheinland-Pfalz",
    "wof:name":"Norbert Schmitt",
    "wof:placetype":"venue"
},
  "geometry": {"coordinates":[6.6869430542,50.1090812683],"type":"Point"}
}