{
  "type": "Feature",
  "properties": {
    "iso:country":"DE",
    "sg:address":"Am Pfaffensteig 23",
    "sg:city":"Schwabach",
    "sg:phone":"+49 911/6324838",
    "sg:postcode":"91126",
    "sg:province":"Bayern",
    "wof:name":"E. Polster",
    "wof:placetype":"venue"
},
  "geometry": {"coordinates":[11.010524,49.35638],"type":"Point"}
}