{
  "type": "Feature",
  "properties": {
    "iso:country":"DE",
    "sg:address":"Henrichenburger Str. 55",
    "sg:city":"Recklinghausen",
    "sg:phone":"+49 2361/98980",
    "sg:postcode":"45665",
    "sg:province":"Nordrhein-Westfalen",
    "wof:name":"Seniorenzentrum Suderwich",
    "wof:placetype":"venue"
},
  "geometry": {"coordinates":[7.28055,51.60157],"type":"Point"}
}