{
  "type": "Feature",
  "properties": {
    "iso:country":"DE",
    "sg:address":"Wildbachweg 11",
    "sg:city":"Freiburg",
    "sg:postcode":"79117",
    "sg:province":"Baden-W\u00fcrttemberg",
    "wof:name":"Thomae Wohnbesitz-anteile Immobilienfonds 10 Potsdam",
    "wof:placetype":"venue"
},
  "geometry": {"coordinates":[7.9226870537,47.9910507202],"type":"Point"}
}