{
  "type": "Feature",
  "properties": {
    "iso:country":"DE",
    "sg:address":"Wagenstieg 6",
    "sg:city":"G\u00f6ttingen",
    "sg:phone":"+49 551/35121",
    "sg:postcode":"37077",
    "sg:province":"Niedersachsen",
    "wof:name":"Zastrau Gmbh",
    "wof:placetype":"venue"
},
  "geometry": {"coordinates":[9.928319,51.561859],"type":"Point"}
}