{
  "type": "Feature",
  "properties": {
    "iso:country":"DE",
    "sg:address":"Wilhelm - Pieck- Str. 27",
    "sg:city":"Suhl",
    "sg:phone":"+49 3681/79580",
    "sg:postcode":"98527",
    "sg:province":"Th\u00fcringen",
    "wof:name":"Bayerische Hypotheken- U. Wechsel-, Bank Ag",
    "wof:placetype":"venue"
},
  "geometry": {"coordinates":[10.702352,50.610859],"type":"Point"}
}