{
  "type": "Feature",
  "properties": {
    "iso:country":"DE",
    "sg:address":"Reitmorstr. 12",
    "sg:city":"M\u00fcnchen",
    "sg:phone":"+49 89/222433",
    "sg:postcode":"80538",
    "sg:province":"Bayern",
    "wof:name":"Pension Maximilian",
    "wof:placetype":"venue"
},
  "geometry": {"coordinates":[11.5927124023,48.139919281],"type":"Point"}
}