{
  "type": "Feature",
  "properties": {
    "iso:country":"DE",
    "sg:address":"Hochstr. 38",
    "sg:city":"Willich",
    "sg:phone":"+49 2154/80871",
    "sg:postcode":"47877",
    "sg:province":"Nordrhein-Westfalen",
    "wof:name":"Hans Winkelhag",
    "wof:placetype":"venue"
},
  "geometry": {"coordinates":[6.536053,51.242554],"type":"Point"}
}