{
  "type": "Feature",
  "properties": {
    "iso:country":"DE",
    "sg:address":"Hauptstr. 3",
    "sg:city":"Pinnau",
    "sg:phone":"+49 38845/40494",
    "sg:postcode":"19273",
    "sg:province":"Mecklenburg-Vorpommern",
    "wof:name":"T\u00fcrenwerke Warnke Gmbh & Co. Kg",
    "wof:placetype":"venue"
},
  "geometry": {"coordinates":[10.928685,53.286045],"type":"Point"}
}