{
  "type": "Feature",
  "properties": {
    "iso:country":"DE",
    "sg:address":"Mittelgasse 7",
    "sg:city":"Ruppertsberg",
    "sg:postcode":"67152",
    "sg:province":"Rheinland-Pfalz",
    "wof:name":"Kath. \u00f6ffentl. B\u00fccherei St. Martinus",
    "wof:placetype":"venue"
},
  "geometry": {"coordinates":[8.196278,49.400322],"type":"Point"}
}