{
  "type": "Feature",
  "properties": {
    "iso:country":"DE",
    "sg:address":"Burgstr. 26",
    "sg:city":"Cottbus",
    "sg:phone":"+49 355/24445",
    "sg:postcode":"03046",
    "sg:province":"Brandenburg",
    "wof:name":"Ralf Emrich",
    "wof:placetype":"venue"
},
  "geometry": {"coordinates":[14.3340358734,51.7580184937],"type":"Point"}
}