{
  "type": "Feature",
  "properties": {
    "iso:country":"DE",
    "sg:address":"Quellenstr. 74",
    "sg:city":"Gro\u00dfwallstadt",
    "sg:phone":"+49 6022/66370",
    "sg:postcode":"63868",
    "sg:province":"Bayern",
    "wof:name":"G\u00fcnther M\u00fcller",
    "wof:placetype":"venue"
},
  "geometry": {"coordinates":[9.15409,49.8848],"type":"Point"}
}