{
  "type": "Feature",
  "properties": {
    "iso:country":"DE",
    "sg:address":"Hauptstr. 10",
    "sg:city":"Bubenreuth",
    "sg:phone":"+49 9131/22568",
    "sg:postcode":"91088",
    "sg:province":"Bayern",
    "wof:name":"H. Klier",
    "wof:placetype":"venue"
},
  "geometry": {"coordinates":[11.0168895721,49.6273460388],"type":"Point"}
}