{
  "type": "Feature",
  "properties": {
    "iso:country":"DE",
    "sg:address":"Werftstr. 1a",
    "sg:city":"Marienwerder",
    "sg:postcode":"16348",
    "sg:province":"Brandenburg",
    "wof:name":"Strema Bautr\u00e4ger Gmbh",
    "wof:placetype":"venue"
},
  "geometry": {"coordinates":[13.605353,52.848801],"type":"Point"}
}