{
  "type": "Feature",
  "properties": {
    "iso:country":"DE",
    "sg:address":"Alte Gladbacherstra\u00dfe 286",
    "sg:city":"Krefeld",
    "sg:phone":"+49 2151/367272",
    "sg:postcode":"47804",
    "sg:province":"Nordrhein-Westfalen",
    "wof:name":"Angelger\u00e4te - Www.anglermeister.de",
    "wof:placetype":"venue"
},
  "geometry": {"coordinates":[6.5380411148,51.3145904541],"type":"Point"}
}