{
  "type": "Feature",
  "properties": {
    "iso:country":"DE",
    "sg:address":"B\u00f6ttgerstr. 1a",
    "sg:city":"Hamburg",
    "sg:postcode":"20148",
    "sg:province":"Hamburg",
    "wof:name":"Enserv Euroquip Energy Industry Equipment Sales",
    "wof:placetype":"venue"
},
  "geometry": {"coordinates":[9.99584,53.568565],"type":"Point"}
}