{
  "type": "Feature",
  "properties": {
    "iso:country":"DE",
    "sg:address":"Dieselstr 87",
    "sg:city":"M\u00f6nchengladbach",
    "sg:phone":"+49 2166/5066",
    "sg:postcode":"41189",
    "sg:province":"Nordrhein-Westfalen",
    "wof:name":"Schm\u00f6lling Gmbh",
    "wof:placetype":"venue"
},
  "geometry": {"coordinates":[6.40891,51.145512],"type":"Point"}
}