{
  "type": "Feature",
  "properties": {
    "iso:country":"DE",
    "sg:address":"Gutenbergstr. 29",
    "sg:city":"Fellbach",
    "sg:phone":"+49 711/9519290",
    "sg:postcode":"70736",
    "sg:province":"Baden-W\u00fcrttemberg",
    "wof:name":"Knorr-bremse Systeme F\u00fcr Nutzfahrzeuge Gmbh",
    "wof:placetype":"venue"
},
  "geometry": {"coordinates":[9.2583618164,48.8292160034],"type":"Point"}
}