{
  "type": "Feature",
  "properties": {
    "iso:country":"DE",
    "sg:address":"Eichenallee 21",
    "sg:city":"Leegebruch",
    "sg:phone":"+49 3304/250848",
    "sg:postcode":"16767",
    "sg:province":"Brandenburg",
    "wof:name":"Detlef Reichenberger Ingenieur",
    "wof:placetype":"venue"
},
  "geometry": {"coordinates":[13.1941900253,52.7235298157],"type":"Point"}
}