{
  "type": "Feature",
  "properties": {
    "iso:country":"DE",
    "sg:address":"Lindenstr. 98",
    "sg:city":"Kellinghusen",
    "sg:postcode":"25548",
    "sg:province":"Schleswig-Holstein",
    "wof:name":"Hans Windecker Kg",
    "wof:placetype":"venue"
},
  "geometry": {"coordinates":[9.7207241058,53.9579772949],"type":"Point"}
}