{
  "type": "Feature",
  "properties": {
    "iso:country":"DE",
    "sg:address":"Jonsdorfer Str. 3",
    "sg:city":"Kurort Oybin",
    "sg:phone":"+49 35844/70245",
    "sg:postcode":"02797",
    "sg:province":"Sachsen",
    "wof:name":"Forsthaus Hain",
    "wof:placetype":"venue"
},
  "geometry": {"coordinates":[14.7260847092,50.8342399597],"type":"Point"}
}