{
  "type": "Feature",
  "properties": {
    "iso:country":"DE",
    "sg:address":"Gottesackerstr. 6",
    "sg:city":"Immenstadt",
    "sg:phone":"+49 8323/52229",
    "sg:postcode":"87509",
    "sg:province":"Bayern",
    "wof:name":"Peter Melchin",
    "wof:placetype":"venue"
},
  "geometry": {"coordinates":[10.21728,47.557758],"type":"Point"}
}