{
  "type": "Feature",
  "properties": {
    "iso:country":"DE",
    "sg:address":"Engelssiepen 3",
    "sg:city":"Essen",
    "sg:phone":"+49 201/481086",
    "sg:postcode":"45257",
    "sg:province":"Nordrhein-Westfalen",
    "wof:name":"Helmut Grossheimann Ingenieur",
    "wof:placetype":"venue"
},
  "geometry": {"coordinates":[7.0949578285,51.3973274231],"type":"Point"}
}