{
  "type": "Feature",
  "properties": {
    "iso:country":"DE",
    "sg:address":"Hauptstr. 21",
    "sg:city":"Andernach",
    "sg:phone":"+49 2632/491131",
    "sg:postcode":"56626",
    "sg:province":"Rheinland-Pfalz",
    "wof:name":"Ada Immobilien Und Wohnbetreuungs-gmbh",
    "wof:placetype":"venue"
},
  "geometry": {"coordinates":[7.3601927757,50.4547767639],"type":"Point"}
}