{
  "type": "Feature",
  "properties": {
    "iso:country":"DE",
    "sg:address":"Am Koppelberg 28",
    "sg:city":"Steimbke",
    "sg:phone":"+49 5026/90260",
    "sg:postcode":"31634",
    "sg:province":"Niedersachsen",
    "wof:name":"Agt Aktiengesellschaft F\u00fcr Telekommunikation",
    "wof:placetype":"venue"
},
  "geometry": {"coordinates":[9.4016675949,52.6577033997],"type":"Point"}
}