{
  "type": "Feature",
  "properties": {
    "iso:country":"DE",
    "sg:address":"Birkenallee 6",
    "sg:city":"Gro\u00df Kummerfeld",
    "sg:phone":"+49 4393/1235",
    "sg:postcode":"24626",
    "sg:province":"Schleswig-Holstein",
    "wof:name":"Harms Baugesch\u00e4ft Gmbh",
    "wof:placetype":"venue"
},
  "geometry": {"coordinates":[10.07076,54.04763],"type":"Point"}
}