{
  "type": "Feature",
  "properties": {
    "iso:country":"DE",
    "sg:address":"Kloster 26",
    "sg:city":"Malchow",
    "sg:postcode":"17213",
    "sg:province":"Mecklenburg-Vorpommern",
    "wof:name":"Evangelisch-lutherische Kirche",
    "wof:placetype":"venue"
},
  "geometry": {"coordinates":[12.4326782227,53.4715385437],"type":"Point"}
}