{
  "type": "Feature",
  "properties": {
    "iso:country":"DE",
    "sg:address":"Dietrichstr. 5",
    "sg:city":"Garbsen",
    "sg:phone":"+49 5131/92158",
    "sg:postcode":"30827",
    "sg:province":"Niedersachsen",
    "wof:name":"Bernd Schulz Zimmerei Und Holzbau Gmbh",
    "wof:placetype":"venue"
},
  "geometry": {"coordinates":[9.594751358,52.4384422302],"type":"Point"}
}