{
  "type": "Feature",
  "properties": {
    "iso:country":"DE",
    "sg:address":"Pferdemarkt 10",
    "sg:city":"Stade",
    "sg:phone":"+49 4141/44066",
    "sg:postcode":"21682",
    "sg:province":"Niedersachsen",
    "wof:name":"Reiseb\u00fcro Stade Gmbh",
    "wof:placetype":"venue"
},
  "geometry": {"coordinates":[9.4754533768,53.5997810364],"type":"Point"}
}