{
  "type": "Feature",
  "properties": {
    "iso:country":"DE",
    "sg:address":"Beuggenerstr.7",
    "sg:city":"Rheinfelden",
    "sg:phone":"+49 7623",
    "sg:postcode":"79618",
    "sg:province":"Baden-W\u00fcrttemberg",
    "wof:name":"Humanpower Repr\u00e4sentanz Thomas Waldmeier",
    "wof:placetype":"venue"
},
  "geometry": {"coordinates":[7.776822,47.574341],"type":"Point"}
}