{
  "type": "Feature",
  "properties": {
    "iso:country":"DE",
    "sg:address":"Ginsterweg 66",
    "sg:city":"Bad Wildbad",
    "sg:phone":"+49 7081/8118",
    "sg:postcode":"75323",
    "sg:province":"Baden-W\u00fcrttemberg",
    "wof:name":"Horst Klaiber",
    "wof:placetype":"venue"
},
  "geometry": {"coordinates":[8.523946,48.701466],"type":"Point"}
}