{
  "type": "Feature",
  "properties": {
    "iso:country":"DE",
    "sg:address":"Feuerdornstr. 172",
    "sg:city":"Hamm",
    "sg:phone":"+49 2381/889537",
    "sg:postcode":"59071",
    "sg:province":"Nordrhein-Westfalen",
    "wof:name":"Rainer Wilms Rechtsanwalt",
    "wof:placetype":"venue"
},
  "geometry": {"coordinates":[7.8746337891,51.6813201904],"type":"Point"}
}