{
  "type": "Feature",
  "properties": {
    "iso:country":"DE",
    "sg:address":"Hauptstr. 32",
    "sg:city":"Bad Nenndorf",
    "sg:phone":"+49 5723/5511",
    "sg:postcode":"31542",
    "sg:province":"Niedersachsen",
    "wof:name":"Bayern Stadl",
    "wof:placetype":"venue"
},
  "geometry": {"coordinates":[9.3802585602,52.3369674683],"type":"Point"}
}