{
  "type": "Feature",
  "properties": {
    "iso:country":"DE",
    "sg:address":"Fuggerstr. 7",
    "sg:city":"Korschenbroich",
    "sg:phone":"+49 2161/998440",
    "sg:postcode":"41352",
    "sg:province":"Nordrhein-Westfalen",
    "wof:name":"Return Gmbh",
    "wof:placetype":"venue"
},
  "geometry": {"coordinates":[6.5407590866,51.1980819702],"type":"Point"}
}