{
  "type": "Feature",
  "properties": {
    "iso:country":"DE",
    "sg:address":"Gerner Str. 27",
    "sg:city":"M\u00fcnchen",
    "sg:phone":"+49 89/15930015",
    "sg:postcode":"80638",
    "sg:province":"Bayern",
    "wof:name":"Kommik-gmbh",
    "wof:placetype":"venue"
},
  "geometry": {"coordinates":[11.523434639,48.1616516113],"type":"Point"}
}