{
  "type": "Feature",
  "properties": {
    "iso:country":"DE",
    "sg:address":"Herderstr 7",
    "sg:city":"Remscheid",
    "sg:phone":"+49 2191/80790",
    "sg:postcode":"42853",
    "sg:province":"Nordrhein-Westfalen",
    "wof:name":"E. C. Emmerich Gmbh & Co Kg",
    "wof:placetype":"venue"
},
  "geometry": {"coordinates":[7.1693639755,51.189868927],"type":"Point"}
}