{
  "type": "Feature",
  "properties": {
    "iso:country":"DE",
    "sg:address":"Marienwerder Str. 31",
    "sg:city":"Eberswalde",
    "sg:phone":"+49 3334/236161",
    "sg:postcode":"16225",
    "sg:province":"Brandenburg",
    "wof:name":"Dirk Zieger Notar",
    "wof:placetype":"venue"
},
  "geometry": {"coordinates":[13.7825965881,52.8362960815],"type":"Point"}
}