{
  "type": "Feature",
  "properties": {
    "iso:country":"DE",
    "sg:address":"Holmingfelder Str. 3",
    "sg:city":"Havetoft",
    "sg:phone":"+49 4603/1564",
    "sg:postcode":"24873",
    "sg:province":"Schleswig-Holstein",
    "wof:name":"Zimmerei Michael Sch\u00f6nk Gmbh & Co. Kg",
    "wof:placetype":"venue"
},
  "geometry": {"coordinates":[9.4968881607,54.6591453552],"type":"Point"}
}