{
  "type": "Feature",
  "properties": {
    "iso:country":"DE",
    "sg:address":"An der B\u00e4renleite 7",
    "sg:city":"P\u00f6\u00dfneck",
    "sg:phone":"+49 3647/412477",
    "sg:postcode":"07381",
    "sg:province":"Th\u00fcringen",
    "wof:name":"Siegfried Kr\u00f6kel",
    "wof:placetype":"venue"
},
  "geometry": {"coordinates":[11.59349,50.699432],"type":"Point"}
}