{
  "type": "Feature",
  "properties": {
    "iso:country":"DE",
    "sg:address":"Kreuztaler Str. 7",
    "sg:city":"Netphen",
    "sg:phone":"+49 271/772350",
    "sg:postcode":"57250",
    "sg:province":"Nordrhein-Westfalen",
    "wof:name":"Petersen Service Gmbh",
    "wof:placetype":"venue"
},
  "geometry": {"coordinates":[8.0605230331,50.9169120789],"type":"Point"}
}