{
  "type": "Feature",
  "properties": {
    "iso:country":"DE",
    "sg:address":"Adalbert-Stifter-Str. 70",
    "sg:city":"Stuttgart",
    "sg:phone":"+49 711/842157",
    "sg:postcode":"70437",
    "sg:province":"Baden-W\u00fcrttemberg",
    "wof:name":"Hermann Roller Architekt",
    "wof:placetype":"venue"
},
  "geometry": {"coordinates":[9.206338,48.836891],"type":"Point"}
}