{
  "type": "Feature",
  "properties": {
    "iso:country":"DE",
    "sg:address":"Heinz-Luhnen-Str. 2a",
    "sg:city":"Viersen",
    "sg:phone":"+49 2162/51022",
    "sg:postcode":"41751",
    "sg:province":"Nordrhein-Westfalen",
    "wof:name":"Kurt Niethen Inh. Horst Niethen",
    "wof:placetype":"venue"
},
  "geometry": {"coordinates":[6.3363890648,51.2540779114],"type":"Point"}
}