{
  "type": "Feature",
  "properties": {
    "iso:country":"DE",
    "sg:address":"Isestr. 1",
    "sg:city":"Hamburg",
    "sg:phone":"+49 40/4202972",
    "sg:postcode":"20144",
    "sg:province":"Hamburg",
    "wof:name":"Werner Schl\u00f6tcke",
    "wof:placetype":"venue"
},
  "geometry": {"coordinates":[9.976668,53.578247],"type":"Point"}
}