{
  "type": "Feature",
  "properties": {
    "iso:country":"DE",
    "sg:address":"Bauernstr. 20",
    "sg:city":"Lehrte",
    "sg:phone":"+49 5175/1514",
    "sg:postcode":"31275",
    "sg:province":"Niedersachsen",
    "wof:name":"Brunhilde Heineke",
    "wof:placetype":"venue"
},
  "geometry": {"coordinates":[10.063577652,52.3947715759],"type":"Point"}
}