{
  "type": "Feature",
  "properties": {
    "iso:country":"DE",
    "sg:address":"St.-J\u00f6ris-Str. 25",
    "sg:city":"Alsdorf",
    "sg:phone":"+49 2404/61817",
    "sg:postcode":"52477",
    "sg:province":"Nordrhein-Westfalen",
    "wof:name":"Heinz Spiertz",
    "wof:placetype":"venue"
},
  "geometry": {"coordinates":[6.203532,50.851841],"type":"Point"}
}