{
  "type": "Feature",
  "properties": {
    "iso:country":"DE",
    "sg:address":"Im Tiefen Winkel 28",
    "sg:city":"Menden",
    "sg:phone":"+49 2373/10028",
    "sg:postcode":"58706",
    "sg:province":"Nordrhein-Westfalen",
    "wof:name":"Textilagentur Meincken Gmbh",
    "wof:placetype":"venue"
},
  "geometry": {"coordinates":[7.8040399551,51.4437637329],"type":"Point"}
}