{
  "type": "Feature",
  "properties": {
    "iso:country":"DE",
    "sg:address":"Am Hagelkreuz 20",
    "sg:city":"Krefeld",
    "sg:phone":"+49 2151/731397",
    "sg:postcode":"47839",
    "sg:province":"Nordrhein-Westfalen",
    "wof:name":"M. Horsten",
    "wof:placetype":"venue"
},
  "geometry": {"coordinates":[6.5077838898,51.3834609985],"type":"Point"}
}