{
  "type": "Feature",
  "properties": {
    "iso:country":"DE",
    "sg:address":"Felsenstr. 1",
    "sg:city":"Burgthann",
    "sg:postcode":"90559",
    "sg:province":"Bayern",
    "wof:name":"Cash Flow Finanz- Und Wirtschaftsberatung Gmbh",
    "wof:placetype":"venue"
},
  "geometry": {"coordinates":[11.3083467484,49.3439254761],"type":"Point"}
}