{
  "type": "Feature",
  "properties": {
    "iso:country":"DE",
    "sg:address":"Frh-v-Lichtenstern-Str 17",
    "sg:city":"Flo\u00df",
    "sg:phone":"+49 9603/705",
    "sg:postcode":"92685",
    "sg:province":"Bayern",
    "wof:name":"Ernst Lindner",
    "wof:placetype":"venue"
},
  "geometry": {"coordinates":[12.27659,49.723808],"type":"Point"}
}