{
  "type": "Feature",
  "properties": {
    "iso:country":"DE",
    "sg:address":"Fl\u00fcggestr. 26",
    "sg:city":"Hannover",
    "sg:postcode":"30161",
    "sg:province":"Niedersachsen",
    "wof:name":"Vamos-bildung Und Reisen E. V.",
    "wof:placetype":"venue"
},
  "geometry": {"coordinates":[9.7495250702,52.3836555481],"type":"Point"}
}