{
  "type": "Feature",
  "properties": {
    "iso:country":"DE",
    "sg:address":"Mitteldamm 3",
    "sg:city":"Minden",
    "sg:phone":"+49 571/5085683",
    "sg:postcode":"32429",
    "sg:province":"Nordrhein-Westfalen",
    "wof:name":"Tigo Gesellschaft F\u00fcr G\u00fctertransport Mbh",
    "wof:placetype":"venue"
},
  "geometry": {"coordinates":[8.885783,52.286892],"type":"Point"}
}