{
  "type": "Feature",
  "properties": {
    "iso:country":"DE",
    "sg:address":"Weinberg 32",
    "sg:city":"Herrsching",
    "sg:phone":"+49 8152/8971",
    "sg:postcode":"82211",
    "sg:province":"Bayern",
    "wof:name":"Dipl.ing. Georg Reil Architekt",
    "wof:placetype":"venue"
},
  "geometry": {"coordinates":[11.184407,48.005829],"type":"Point"}
}