{
  "type": "Feature",
  "properties": {
    "iso:country":"DE",
    "sg:address":"Eichenstr. 6",
    "sg:city":"Schechen",
    "sg:phone":"+49 8031/28460",
    "sg:postcode":"83135",
    "sg:province":"Bayern",
    "wof:name":"Dieter Mauritz",
    "wof:placetype":"venue"
},
  "geometry": {"coordinates":[12.1206016541,47.8932304382],"type":"Point"}
}