{
  "type": "Feature",
  "properties": {
    "iso:country":"DE",
    "sg:address":"S\u00fcderhausen 3",
    "sg:city":"Wangerland",
    "sg:phone":"+49 4463/489",
    "sg:postcode":"26434",
    "sg:province":"Niedersachsen",
    "wof:name":"Karl Heissenb\u00fcttel",
    "wof:placetype":"venue"
},
  "geometry": {"coordinates":[7.922779,53.650078],"type":"Point"}
}