{
  "type": "Feature",
  "properties": {
    "iso:country":"DE",
    "sg:address":"Seestr. 13/ 1",
    "sg:city":"Weissach",
    "sg:phone":"+49 7152/42530",
    "sg:postcode":"71287",
    "sg:province":"Baden-W\u00fcrttemberg",
    "wof:name":"Roland Iseli Steuerberater",
    "wof:placetype":"venue"
},
  "geometry": {"coordinates":[8.9098577499,48.8306274414],"type":"Point"}
}