{
  "type": "Feature",
  "properties": {
    "iso:country":"DE",
    "sg:address":"Gaertnerstr. 2",
    "sg:city":"Aschaffenburg",
    "sg:phone":"+49 4960/2138490",
    "sg:postcode":"63739",
    "sg:province":"Bayern",
    "wof:name":"Witreu Wirtschaftsberatungs- Und Treuhandges. Mbh",
    "wof:placetype":"venue"
},
  "geometry": {"coordinates":[9.136605,49.978596],"type":"Point"}
}