{
  "type": "Feature",
  "properties": {
    "iso:country":"DE",
    "sg:address":"Lothringer Str. 28",
    "sg:city":"Wiesbaden",
    "sg:phone":"+49 611/406868",
    "sg:postcode":"65195",
    "sg:province":"Hessen",
    "wof:name":"Hans-joachim Janotta",
    "wof:placetype":"venue"
},
  "geometry": {"coordinates":[8.221979,50.081848],"type":"Point"}
}