{
  "type": "Feature",
  "properties": {
    "iso:country":"DE",
    "sg:address":"Papierm\u00fchlstr. 20",
    "sg:city":"Leipzig",
    "sg:phone":"+49 341/8621431",
    "sg:postcode":"04299",
    "sg:province":"Sachsen",
    "wof:name":"Manfred Rattey",
    "wof:placetype":"venue"
},
  "geometry": {"coordinates":[12.417216301,51.3234596252],"type":"Point"}
}