{
  "type": "Feature",
  "properties": {
    "iso:country":"DE",
    "sg:address":"Vereinsstr. 50",
    "sg:city":"Krefeld",
    "sg:phone":"+49 2151/27941",
    "sg:postcode":"47799",
    "sg:province":"Nordrhein-Westfalen",
    "wof:name":"J. Dallner",
    "wof:placetype":"venue"
},
  "geometry": {"coordinates":[6.574692,51.33073],"type":"Point"}
}