{
  "type": "Feature",
  "properties": {
    "iso:country":"DE",
    "sg:city":"Bevern",
    "sg:phone":"+49 4123/2223",
    "sg:postcode":"25355",
    "sg:province":"Schleswig-Holstein",
    "wof:name":"Hinrich Seeth",
    "wof:placetype":"venue"
},
  "geometry": {"coordinates":[9.771524,53.756283],"type":"Point"}
}