{
  "type": "Feature",
  "properties": {
    "iso:country":"DE",
    "sg:address":"Westfalendamm 293",
    "sg:city":"Dortmund",
    "sg:phone":"+49 231/431363",
    "sg:postcode":"44141",
    "sg:province":"Nordrhein-Westfalen",
    "wof:name":"Beate H}ls Heilpraktikerin",
    "wof:placetype":"venue"
},
  "geometry": {"coordinates":[7.5144901276,51.5037384033],"type":"Point"}
}