{
  "type": "Feature",
  "properties": {
    "iso:country":"DE",
    "sg:address":"Adenauerstr. 5",
    "sg:city":"Waldkirch",
    "sg:phone":"+49 7681/6878",
    "sg:postcode":"79183",
    "sg:province":"Baden-W\u00fcrttemberg",
    "wof:name":"P. Eisenmann",
    "wof:placetype":"venue"
},
  "geometry": {"coordinates":[7.9581079483,48.0931434631],"type":"Point"}
}