{
  "type": "Feature",
  "properties": {
    "iso:country":"DE",
    "sg:address":"Am Viehmarktplatz 2",
    "sg:city":"Apen",
    "sg:phone":"+49 4489/5154",
    "sg:postcode":"26689",
    "sg:province":"Niedersachsen",
    "wof:name":"Restaurant Saloniki",
    "wof:placetype":"venue"
},
  "geometry": {"coordinates":[7.8022060394,53.2187843323],"type":"Point"}
}