{
  "type": "Feature",
  "properties": {
    "iso:country":"DE",
    "sg:address":"Rixdorfer Str. 117",
    "sg:city":"Berlin",
    "sg:phone":"+49 30/7032077",
    "sg:postcode":"12109",
    "sg:province":"Berlin",
    "wof:name":"Olms-apotheke",
    "wof:placetype":"venue"
},
  "geometry": {"coordinates":[13.400104,52.444527],"type":"Point"}
}