{
  "type": "Feature",
  "properties": {
    "iso:country":"DE",
    "sg:address":"Clarenberg 30",
    "sg:city":"Dortmund",
    "sg:phone":"+49 231/412253",
    "sg:postcode":"44263",
    "sg:province":"Nordrhein-Westfalen",
    "wof:name":"Heiner Blomeyer Architekt",
    "wof:placetype":"venue"
},
  "geometry": {"coordinates":[7.504696,51.482212],"type":"Point"}
}