{
  "type": "Feature",
  "properties": {
    "iso:country":"DE",
    "sg:address":"Platter Str. 87",
    "sg:city":"Taunusstein",
    "sg:phone":"+49 6128/84802",
    "sg:postcode":"65232",
    "sg:province":"Hessen",
    "wof:name":"Thai Garden",
    "wof:placetype":"venue"
},
  "geometry": {"coordinates":[8.1411848068,50.1399650574],"type":"Point"}
}