{
  "type": "Feature",
  "properties": {
    "iso:country":"DE",
    "sg:address":"Max-Lang-Str. 62",
    "sg:city":"Leinfelden-Echterdingen",
    "sg:phone":"+49 4971/1752075",
    "sg:postcode":"70771",
    "sg:province":"Baden-W\u00fcrttemberg",
    "wof:name":"Rieker Druckveredelung Gmbh & Co Kg",
    "wof:placetype":"venue"
},
  "geometry": {"coordinates":[9.1428356171,48.701789856],"type":"Point"}
}