{
  "type": "Feature",
  "properties": {
    "iso:country":"DE",
    "sg:address":"Raiffeisenstr. 8",
    "sg:city":"Krummh\u00f6rn",
    "sg:phone":"+49 4923/990288",
    "sg:postcode":"26736",
    "sg:province":"Niedersachsen",
    "wof:name":"Galaxy Inh. Gerd Dr\u00f6st",
    "wof:placetype":"venue"
},
  "geometry": {"coordinates":[7.1024951935,53.4280776978],"type":"Point"}
}