{
  "type": "Feature",
  "properties": {
    "iso:country":"DE",
    "sg:address":"Am Rittbrook 4",
    "sg:city":"L\u00fcbeck",
    "sg:phone":"+49 451/621242",
    "sg:postcode":"23566",
    "sg:province":"Schleswig-Holstein",
    "wof:name":"Lothar Otte",
    "wof:placetype":"venue"
},
  "geometry": {"coordinates":[10.7275018692,53.8737297058],"type":"Point"}
}