{
  "type": "Feature",
  "properties": {
    "iso:country":"DE",
    "sg:address":"Deutz-M\u00fclheimer Str. 326",
    "sg:city":"K\u00f6ln",
    "sg:phone":"+49 221/613593",
    "sg:postcode":"51063",
    "sg:province":"Nordrhein-Westfalen",
    "wof:name":"Br\u00fcckeneck",
    "wof:placetype":"venue"
},
  "geometry": {"coordinates":[6.9971151352,50.9612503052],"type":"Point"}
}