{
  "type": "Feature",
  "properties": {
    "iso:country":"DE",
    "sg:address":"Mittelstr. 2",
    "sg:city":"Gro\u00df-Gerau",
    "sg:phone":"+49 6152/2689",
    "sg:postcode":"64521",
    "sg:province":"Hessen",
    "wof:name":"Spalt Und M\u00fchlhans Rechtsanwalt Und Notar",
    "wof:placetype":"venue"
},
  "geometry": {"coordinates":[8.4873027802,49.9189910889],"type":"Point"}
}