{
  "type": "Feature",
  "properties": {
    "iso:country":"DE",
    "sg:address":"M\u00fcnchhof 3 c",
    "sg:city":"Ostrau",
    "sg:phone":"+49 34324/24668",
    "sg:postcode":"04749",
    "sg:province":"Sachsen",
    "wof:name":"Rat Rohr- Und Anlagentechnik Gmbh",
    "wof:placetype":"venue"
},
  "geometry": {"coordinates":[13.1196498871,51.198059082],"type":"Point"}
}