{
  "type": "Feature",
  "properties": {
    "iso:country":"DE",
    "sg:address":"Kaiser-Friedrich-Str. 5",
    "sg:city":"Berlin",
    "sg:phone":"+49 30/3421676",
    "sg:postcode":"10585",
    "sg:province":"Berlin",
    "wof:name":"Medienwerkstatt Wissenschaft Berlin Ev",
    "wof:placetype":"venue"
},
  "geometry": {"coordinates":[13.2999668121,52.5179634094],"type":"Point"}
}