{
  "type": "Feature",
  "properties": {
    "iso:country":"DE",
    "sg:address":"Olpe 45",
    "sg:city":"Dortmund",
    "sg:phone":"+49 231/515127",
    "sg:postcode":"44135",
    "sg:province":"Nordrhein-Westfalen",
    "wof:name":"Gregor Miczka",
    "wof:placetype":"venue"
},
  "geometry": {"coordinates":[7.4719781876,51.5124664307],"type":"Point"}
}