{
  "type": "Feature",
  "properties": {
    "iso:country":"DE",
    "sg:address":"Schwertstr. 35",
    "sg:city":"Solingen",
    "sg:phone":"+49 4921/2222600",
    "sg:postcode":"42651",
    "sg:province":"Nordrhein-Westfalen",
    "wof:name":"Bub Druckguss Gmbh",
    "wof:placetype":"venue"
},
  "geometry": {"coordinates":[7.0912771225,51.1701316833],"type":"Point"}
}