{
  "type": "Feature",
  "properties": {
    "iso:country":"DE",
    "sg:address":"Eichriede 4",
    "sg:city":"Wunstorf",
    "sg:phone":"+49 5031",
    "sg:postcode":"31515",
    "sg:province":"Niedersachsen",
    "wof:name":"A.r.niepel-ingenieurb\u00fcro F\u00fcr Umweltschutz & Energieberatung",
    "wof:placetype":"venue"
},
  "geometry": {"coordinates":[9.463043,52.415817],"type":"Point"}
}