{
  "type": "Feature",
  "properties": {
    "iso:country":"DE",
    "sg:address":"Igelweg 12",
    "sg:city":"Castrop-Rauxel",
    "sg:postcode":"44577",
    "sg:province":"Nordrhein-Westfalen",
    "wof:name":"Herbert Weidner",
    "wof:placetype":"venue"
},
  "geometry": {"coordinates":[7.3571748734,51.5271453857],"type":"Point"}
}