{
  "type": "Feature",
  "properties": {
    "iso:country":"DE",
    "sg:address":"Kirchplatz 5",
    "sg:city":"Hausen",
    "sg:phone":"+49 9448/1366",
    "sg:postcode":"93345",
    "sg:province":"Bayern",
    "wof:name":"Gastst\u00e4tte Alfons Fischer",
    "wof:placetype":"venue"
},
  "geometry": {"coordinates":[11.9603261948,48.8370246887],"type":"Point"}
}