{
  "type": "Feature",
  "properties": {
    "iso:country":"DE",
    "sg:address":"Kirchgasse 23",
    "sg:city":"Wiesbaden",
    "sg:phone":"+49 611/379132",
    "sg:postcode":"65185",
    "sg:province":"Hessen",
    "wof:name":"H & M Gmbh",
    "wof:placetype":"venue"
},
  "geometry": {"coordinates":[8.238274,50.079651],"type":"Point"}
}