{
  "type": "Feature",
  "properties": {
    "iso:country":"DE",
    "sg:address":"Schulstr. 23",
    "sg:city":"Gefrees",
    "sg:phone":"+49 9254/8283",
    "sg:postcode":"95482",
    "sg:province":"Bayern",
    "wof:name":"Volkshaus",
    "wof:placetype":"venue"
},
  "geometry": {"coordinates":[11.7393131256,50.0961456299],"type":"Point"}
}