{
  "type": "Feature",
  "properties": {
    "iso:country":"DE",
    "sg:address":"Burgwallbacher Str.",
    "sg:city":"Sch\u00f6nau",
    "sg:phone":"+49 9775/779",
    "sg:postcode":"97659",
    "sg:province":"Bayern",
    "wof:name":"Reinhold Und Ursula Pfeuffer",
    "wof:placetype":"venue"
},
  "geometry": {"coordinates":[10.1032104492,50.3813209534],"type":"Point"}
}