{
  "type": "Feature",
  "properties": {
    "iso:country":"DE",
    "sg:address":"Ruhpoldinger Str. 11",
    "sg:city":"M\u00fcnchen",
    "sg:phone":"+49 89/4801451",
    "sg:postcode":"81825",
    "sg:province":"Bayern",
    "wof:name":"Bavaria-brotzeit-service Gmbh",
    "wof:placetype":"venue"
},
  "geometry": {"coordinates":[11.650944,48.123882],"type":"Point"}
}