{
  "type": "Feature",
  "properties": {
    "iso:country":"DE",
    "sg:address":"Moltkeplatz 47",
    "sg:city":"Essen",
    "sg:phone":"+49 201/268594",
    "sg:postcode":"45138",
    "sg:province":"Nordrhein-Westfalen",
    "wof:name":"Spm Consulting U. Trading Gmbh",
    "wof:placetype":"venue"
},
  "geometry": {"coordinates":[7.0246891975,51.4445114136],"type":"Point"}
}