{
  "type": "Feature",
  "properties": {
    "iso:country":"DE",
    "sg:address":"Schauinslandstr. 44",
    "sg:city":"Freiburg",
    "sg:phone":"+49 761/29494",
    "sg:postcode":"79100",
    "sg:province":"Baden-W\u00fcrttemberg",
    "wof:name":"Dr. Med. Gudrun St\u00fcber",
    "wof:placetype":"venue"
},
  "geometry": {"coordinates":[7.8638191223,47.9559173584],"type":"Point"}
}