{
  "type": "Feature",
  "properties": {
    "iso:country":"DE",
    "sg:address":"Unterer Markt 39",
    "sg:city":"Weiden",
    "sg:phone":"+49 961/43987",
    "sg:postcode":"92637",
    "sg:province":"Bayern",
    "wof:name":"Karl-heinz Hermann",
    "wof:placetype":"venue"
},
  "geometry": {"coordinates":[12.165398,49.676762],"type":"Point"}
}