{
  "type": "Feature",
  "properties": {
    "iso:country":"DE",
    "sg:address":"Hermann-Friesen-Str. 6",
    "sg:city":"Hofheim",
    "sg:phone":"+49 6192/26076",
    "sg:postcode":"65719",
    "sg:province":"Hessen",
    "wof:name":"V. Popadic",
    "wof:placetype":"venue"
},
  "geometry": {"coordinates":[8.4531345367,50.090587616],"type":"Point"}
}