{
  "type": "Feature",
  "properties": {
    "iso:country":"DE",
    "sg:address":"Dornestr. 81",
    "sg:city":"L\u00fcbeck",
    "sg:phone":"+49 451/861568",
    "sg:postcode":"23558",
    "sg:province":"Schleswig-Holstein",
    "wof:name":"H. J\u00fcrs",
    "wof:placetype":"venue"
},
  "geometry": {"coordinates":[10.6656370163,53.8576622009],"type":"Point"}
}