{
  "type": "Feature",
  "properties": {
    "iso:country":"DE",
    "sg:address":"Gustav-Radbruch-Str. 25",
    "sg:city":"Bremen",
    "sg:phone":"+49 421/1696064",
    "sg:postcode":"28329",
    "sg:province":"Bremen",
    "wof:name":"Nova International Trading Gmbh",
    "wof:placetype":"venue"
},
  "geometry": {"coordinates":[8.898991,53.084229],"type":"Point"}
}