{
  "type": "Feature",
  "properties": {
    "iso:country":"DE",
    "sg:address":"Wullener Feld 51",
    "sg:city":"Witten",
    "sg:phone":"+49 2302/60561",
    "sg:postcode":"58454",
    "sg:province":"Nordrhein-Westfalen",
    "wof:name":"Siegward Klabunde",
    "wof:placetype":"venue"
},
  "geometry": {"coordinates":[7.363937,51.457527],"type":"Point"}
}