{
  "type": "Feature",
  "properties": {
    "iso:country":"DE",
    "sg:address":"Parkstr.",
    "sg:city":"Habichtswald",
    "sg:phone":"+49 5606/9562",
    "sg:postcode":"34317",
    "sg:province":"Hessen",
    "wof:name":"Dea Tankstelle",
    "wof:placetype":"venue"
},
  "geometry": {"coordinates":[9.3175573349,51.3268280029],"type":"Point"}
}