{
  "type": "Feature",
  "properties": {
    "iso:country":"DE",
    "sg:address":"Prendener Str. 30",
    "sg:city":"Klosterfelde",
    "sg:phone":"+49 33396/520",
    "sg:postcode":"16348",
    "sg:province":"Brandenburg",
    "wof:name":"G. K\u00e4mke",
    "wof:placetype":"venue"
},
  "geometry": {"coordinates":[13.4937238693,52.7939224243],"type":"Point"}
}