{
  "type": "Feature",
  "properties": {
    "iso:country":"DE",
    "sg:address":"Haroldstrasse 14",
    "sg:city":"D\u00fcsseldorf",
    "sg:phone":"+49 211/864060",
    "sg:postcode":"40213",
    "sg:province":"Nordrhein-Westfalen",
    "wof:name":"Deutscher Marketing-verband",
    "wof:placetype":"venue"
},
  "geometry": {"coordinates":[6.771628,51.219135],"type":"Point"}
}