{
  "type": "Feature",
  "properties": {
    "iso:country":"DE",
    "sg:address":"Hermannplatz 9",
    "sg:city":"Berlin",
    "sg:phone":"+49 30/6235959",
    "sg:postcode":"10967",
    "sg:province":"Berlin",
    "wof:name":"W. Finkelmann",
    "wof:placetype":"venue"
},
  "geometry": {"coordinates":[13.4255094528,52.4874343872],"type":"Point"}
}