{
  "type": "Feature",
  "properties": {
    "iso:country":"DE",
    "sg:address":"Hammer Str. 154",
    "sg:city":"Hamm",
    "sg:phone":"+49 2381/973060",
    "sg:postcode":"59075",
    "sg:province":"Nordrhein-Westfalen",
    "wof:name":"Projektgesellschaft Radbod Mbh",
    "wof:placetype":"venue"
},
  "geometry": {"coordinates":[7.743367,51.626266],"type":"Point"}
}