{
  "type": "Feature",
  "properties": {
    "iso:country":"DE",
    "sg:address":"Am Hopfengarten 18",
    "sg:city":"Ro\u00dftal",
    "sg:phone":"+49 9127/57418",
    "sg:postcode":"90574",
    "sg:province":"Bayern",
    "wof:name":"Erich Koal",
    "wof:placetype":"venue"
},
  "geometry": {"coordinates":[10.877298,49.39846],"type":"Point"}
}