{
  "type": "Feature",
  "properties": {
    "iso:country":"DE",
    "sg:address":"Industriestr. 50",
    "sg:city":"Haiger",
    "sg:phone":"+49 2773/3031",
    "sg:postcode":"35708",
    "sg:province":"Hessen",
    "wof:name":"Systemlagertechnik Haiger Gmbh",
    "wof:placetype":"venue"
},
  "geometry": {"coordinates":[8.221609,50.740215],"type":"Point"}
}