{
  "type": "Feature",
  "properties": {
    "iso:country":"DE",
    "sg:address":"Holsteiner Str. 13",
    "sg:city":"Ludwigsburg",
    "sg:phone":"+49 7141/290846",
    "sg:postcode":"71640",
    "sg:province":"Baden-W\u00fcrttemberg",
    "wof:name":"B. Werner",
    "wof:placetype":"venue"
},
  "geometry": {"coordinates":[9.222219,48.892738],"type":"Point"}
}