{
  "type": "Feature",
  "properties": {
    "iso:country":"DE",
    "sg:address":"Claffheim 10b",
    "sg:city":"Ansbach",
    "sg:phone":"+49 9805/7797",
    "sg:postcode":"91522",
    "sg:province":"Bayern",
    "wof:name":"Mapo Baubetreuungs Gmbh",
    "wof:placetype":"venue"
},
  "geometry": {"coordinates":[10.5900201797,49.2533378601],"type":"Point"}
}