{
  "type": "Feature",
  "properties": {
    "iso:country":"DE",
    "sg:address":"Steinstr. 21",
    "sg:city":"Esens",
    "sg:phone":"+49 4971/3876",
    "sg:postcode":"26427",
    "sg:province":"Niedersachsen",
    "wof:name":"Sporthaus Duo-schuh Dunker & Oelrichs",
    "wof:placetype":"venue"
},
  "geometry": {"coordinates":[7.6132149696,53.6453666687],"type":"Point"}
}