{
  "type": "Feature",
  "properties": {
    "iso:country":"DE",
    "sg:address":"Fabrikstr. 8",
    "sg:city":"Nossen",
    "sg:phone":"+49 35242/4150",
    "sg:postcode":"01683",
    "sg:province":"Sachsen",
    "wof:name":"Cedo Papierprodukte Gmbh",
    "wof:placetype":"venue"
},
  "geometry": {"coordinates":[13.2942895889,51.0629959106],"type":"Point"}
}