{
  "type": "Feature",
  "properties": {
    "iso:country":"DE",
    "sg:address":"Lindenstr. 41",
    "sg:city":"Bramsche",
    "sg:phone":"+49 5461/8880",
    "sg:postcode":"49565",
    "sg:province":"Niedersachsen",
    "wof:name":"Bramscher Buchbinder Betriebe Beteiligungsges. Mbh",
    "wof:placetype":"venue"
},
  "geometry": {"coordinates":[7.97541,52.415077],"type":"Point"}
}