{
  "type": "Feature",
  "properties": {
    "iso:country":"DE",
    "sg:address":"Molkenmarkt 1-3",
    "sg:city":"Berlin",
    "sg:phone":"+49 30/2478013",
    "sg:postcode":"10179",
    "sg:province":"Berlin",
    "wof:name":"Konrad-adenauer-stiftung E. V. Schwerinisches Palais",
    "wof:placetype":"venue"
},
  "geometry": {"coordinates":[13.4087200165,52.5160560608],"type":"Point"}
}