{
  "type": "Feature",
  "properties": {
    "iso:country":"DE",
    "sg:address":"Opladener Str. 92",
    "sg:city":"Leverkusen",
    "sg:phone":"+49 214/52993",
    "sg:postcode":"51375",
    "sg:province":"Nordrhein-Westfalen",
    "wof:name":"Johann Burtscheidt",
    "wof:placetype":"venue"
},
  "geometry": {"coordinates":[7.0430808067,51.0409393311],"type":"Point"}
}