{
  "type": "Feature",
  "properties": {
    "iso:country":"DE",
    "sg:address":"Rathenaustr. 17",
    "sg:city":"Eppelheim",
    "sg:phone":"+49 6221/763182",
    "sg:postcode":"69214",
    "sg:province":"Baden-W\u00fcrttemberg",
    "wof:name":"Christian Wache",
    "wof:placetype":"venue"
},
  "geometry": {"coordinates":[8.62988,49.391899],"type":"Point"}
}