{
  "type": "Feature",
  "properties": {
    "iso:country":"DE",
    "sg:address":"Meisenbachhof 1",
    "sg:city":"Illingen",
    "sg:phone":"+49 7043/2222",
    "sg:postcode":"75428",
    "sg:province":"Baden-W\u00fcrttemberg",
    "wof:name":"Werner Gienger",
    "wof:placetype":"venue"
},
  "geometry": {"coordinates":[8.887427,49.004265],"type":"Point"}
}