{
  "type": "Feature",
  "properties": {
    "iso:country":"DE",
    "sg:address":"Schlo\u00dfstr. 24",
    "sg:city":"Mainstockheim",
    "sg:phone":"+49 9321/6688",
    "sg:postcode":"97320",
    "sg:province":"Bayern",
    "wof:name":"Hans Zepter",
    "wof:placetype":"venue"
},
  "geometry": {"coordinates":[10.151124,49.776981],"type":"Point"}
}