{
  "type": "Feature",
  "properties": {
    "iso:country":"DE",
    "sg:address":"D\u00f6llingerstr 17",
    "sg:city":"M\u00fcnchen",
    "sg:phone":"+49 89/7482370",
    "sg:postcode":"80639",
    "sg:province":"Bayern",
    "wof:name":"Wps World-patentservice Gmbh",
    "wof:placetype":"venue"
},
  "geometry": {"coordinates":[11.5145149231,48.1551589966],"type":"Point"}
}