{
  "type": "Feature",
  "properties": {
    "iso:country":"DE",
    "sg:address":"Hauptstr. 71",
    "sg:city":"Wittorf",
    "sg:phone":"+49 4133/7418",
    "sg:postcode":"21357",
    "sg:province":"Niedersachsen",
    "wof:name":"Reinhold Wegner",
    "wof:placetype":"venue"
},
  "geometry": {"coordinates":[10.3601560593,53.3281288147],"type":"Point"}
}