{
  "type": "Feature",
  "properties": {
    "iso:country":"DE",
    "sg:address":"Rotstr. 5",
    "sg:city":"Stimpfach",
    "sg:phone":"+49 7967/483",
    "sg:postcode":"74597",
    "sg:province":"Baden-W\u00fcrttemberg",
    "wof:name":"Kath. Pfarramt St. Georg",
    "wof:placetype":"venue"
},
  "geometry": {"coordinates":[10.093626976,49.0621490479],"type":"Point"}
}