{
  "type": "Feature",
  "properties": {
    "iso:country":"DE",
    "sg:address":"Molkereistr 35",
    "sg:city":"Garbsen",
    "sg:phone":"+49 5131/45980",
    "sg:postcode":"30826",
    "sg:province":"Niedersachsen",
    "wof:name":"Haase Logistik Gmbh",
    "wof:placetype":"venue"
},
  "geometry": {"coordinates":[9.5703001022,52.4485588074],"type":"Point"}
}