{
  "type": "Feature",
  "properties": {
    "iso:country":"DE",
    "sg:address":"Marktplatz 11",
    "sg:city":"Bad Kissingen",
    "sg:phone":"+49 971/2100",
    "sg:postcode":"97688",
    "sg:province":"Bayern",
    "wof:name":"Ludewig In Der Brunnengasse",
    "wof:placetype":"venue"
},
  "geometry": {"coordinates":[10.0766305923,50.1998901367],"type":"Point"}
}