{
  "type": "Feature",
  "properties": {
    "iso:country":"DE",
    "sg:address":"Wilmersstr 6",
    "sg:city":"Emsdetten",
    "sg:phone":"+49 2572/951868",
    "sg:postcode":"48282",
    "sg:province":"Nordrhein-Westfalen",
    "wof:name":"Diwa Promotionsysteme Gmbh",
    "wof:placetype":"venue"
},
  "geometry": {"coordinates":[7.559172,52.159359],"type":"Point"}
}