{
  "type": "Feature",
  "properties": {
    "iso:country":"DE",
    "sg:address":"Rheinstr. 27",
    "sg:city":"Offenburg",
    "sg:phone":"+49 781/74117",
    "sg:postcode":"77652",
    "sg:province":"Baden-W\u00fcrttemberg",
    "wof:name":"Armbruster Und Eidel Ingenieure",
    "wof:placetype":"venue"
},
  "geometry": {"coordinates":[7.9393839836,48.4794006348],"type":"Point"}
}