{
  "type": "Feature",
  "properties": {
    "iso:country":"DE",
    "sg:address":"Birkenstr. 5",
    "sg:city":"Willst\u00e4tt",
    "sg:phone":"+49 7854/7300",
    "sg:postcode":"77731",
    "sg:province":"Baden-W\u00fcrttemberg",
    "wof:name":"Pizzeria R\u00f6mertopf",
    "wof:placetype":"venue"
},
  "geometry": {"coordinates":[7.8587870598,48.5305747986],"type":"Point"}
}