{
  "type": "Feature",
  "properties": {
    "iso:country":"DE",
    "sg:address":"Werdohler Str 15",
    "sg:city":"L\u00fcdenscheid",
    "sg:phone":"+49 2351/23023",
    "sg:postcode":"58511",
    "sg:province":"Nordrhein-Westfalen",
    "wof:name":"Lebos Druckstore",
    "wof:placetype":"venue"
},
  "geometry": {"coordinates":[7.6365199089,51.2166671753],"type":"Point"}
}