{
  "type": "Feature",
  "properties": {
    "iso:country":"DE",
    "sg:address":"Waldstr. 34",
    "sg:city":"Albstadt",
    "sg:phone":"+49 7435/1219",
    "sg:postcode":"72459",
    "sg:province":"Baden-W\u00fcrttemberg",
    "wof:name":"Charpie Ledermoden Gmbh",
    "wof:placetype":"venue"
},
  "geometry": {"coordinates":[8.9278039932,48.2196846008],"type":"Point"}
}