{
  "type": "Feature",
  "properties": {
    "iso:country":"DE",
    "sg:address":"An der Deisinger Mauer 12",
    "sg:city":"N\u00f6rdlingen",
    "sg:phone":"+49 9081/25653",
    "sg:postcode":"86720",
    "sg:province":"Bayern",
    "wof:name":"G. Frank",
    "wof:placetype":"venue"
},
  "geometry": {"coordinates":[10.4940910339,48.852180481],"type":"Point"}
}