{
  "type": "Feature",
  "properties": {
    "iso:country":"DE",
    "sg:address":"Kirchstr.",
    "sg:city":"Diemelsee",
    "sg:phone":"+49 5633/5499",
    "sg:postcode":"34519",
    "sg:province":"Hessen",
    "wof:name":"Rudolf Pack Jun.",
    "wof:placetype":"venue"
},
  "geometry": {"coordinates":[8.730703,51.36335],"type":"Point"}
}