{
  "type": "Feature",
  "properties": {
    "iso:country":"DE",
    "sg:address":"Flodelingsweg 3",
    "sg:city":"Bonn",
    "sg:phone":"+49 228/624483",
    "sg:postcode":"53121",
    "sg:province":"Nordrhein-Westfalen",
    "wof:name":"F. J. Lepper",
    "wof:placetype":"venue"
},
  "geometry": {"coordinates":[7.0784511566,50.7228317261],"type":"Point"}
}