{
  "type": "Feature",
  "properties": {
    "iso:country":"DE",
    "sg:address":"Glambecker Weg 22",
    "sg:city":"Berlin",
    "sg:phone":"+49 30/4045074",
    "sg:postcode":"13467",
    "sg:province":"Berlin",
    "wof:name":"R. Glitsch Und W. Zimmermann Architekten",
    "wof:placetype":"venue"
},
  "geometry": {"coordinates":[13.2910165787,52.6237983704],"type":"Point"}
}