{
  "type": "Feature",
  "properties": {
    "iso:country":"DE",
    "sg:address":"Hummelwiesenweg 42",
    "sg:city":"Stuttgart",
    "sg:phone":"+49 711/6873433",
    "sg:postcode":"70569",
    "sg:province":"Baden-W\u00fcrttemberg",
    "wof:name":"Ursula Dietze Steuerberaterin",
    "wof:placetype":"venue"
},
  "geometry": {"coordinates":[9.1381807327,48.7414855957],"type":"Point"}
}