{
  "type": "Feature",
  "properties": {
    "iso:country":"DE",
    "sg:address":"Alte Bundesstr. 50",
    "sg:city":"Waiblingen",
    "sg:phone":"+49 7151/5030",
    "sg:postcode":"71332",
    "sg:province":"Baden-W\u00fcrttemberg",
    "wof:name":"Robert Bosch Gmbh",
    "wof:placetype":"venue"
},
  "geometry": {"coordinates":[9.314866066,48.8222160339],"type":"Point"}
}