{
  "type": "Feature",
  "properties": {
    "iso:country":"DE",
    "sg:address":"Alemannenweg 11",
    "sg:city":"Rainau",
    "sg:postcode":"73492",
    "sg:province":"Baden-W\u00fcrttemberg",
    "wof:name":"Binitek Gmbh",
    "wof:placetype":"venue"
},
  "geometry": {"coordinates":[10.1321105957,48.910446167],"type":"Point"}
}