{
  "type": "Feature",
  "properties": {
    "iso:country":"DE",
    "sg:address":"Furschweilerstr. 45",
    "sg:city":"Namborn",
    "sg:phone":"+49 6857/6233",
    "sg:postcode":"66640",
    "sg:province":"Saarland",
    "wof:name":"Johannes Haab Gmbh",
    "wof:placetype":"venue"
},
  "geometry": {"coordinates":[7.1651740074,49.5146026611],"type":"Point"}
}