{
  "type": "Feature",
  "properties": {
    "iso:country":"DE",
    "sg:address":"Parkstr. 1",
    "sg:city":"Oschatz",
    "sg:phone":"+49 3435/929571",
    "sg:postcode":"04758",
    "sg:province":"Sachsen",
    "wof:name":"Deutsches Rotes Kreuz Kreisverband Oschatz E. V.",
    "wof:placetype":"venue"
},
  "geometry": {"coordinates":[13.1135530472,51.2927322388],"type":"Point"}
}