{
  "type": "Feature",
  "properties": {
    "iso:country":"DE",
    "sg:address":"Lemsahler Weg 23",
    "sg:city":"Norderstedt",
    "sg:phone":"+49 40/5295800",
    "sg:postcode":"22851",
    "sg:province":"Schleswig-Holstein",
    "wof:name":"Dp Maritim Spares Service Gmbh",
    "wof:placetype":"venue"
},
  "geometry": {"coordinates":[10.052033,53.684204],"type":"Point"}
}