{
  "type": "Feature",
  "properties": {
    "iso:country":"DE",
    "sg:address":"Bahnhofstr. 62",
    "sg:city":"Twistringen",
    "sg:phone":"+49 4243/3958",
    "sg:postcode":"27239",
    "sg:province":"Niedersachsen",
    "wof:name":"Peter Blome",
    "wof:placetype":"venue"
},
  "geometry": {"coordinates":[8.6442165375,52.7950439453],"type":"Point"}
}