{
  "type": "Feature",
  "properties": {
    "iso:country":"DE",
    "sg:address":"M\u00fchlenweg 28",
    "sg:city":"Borchen",
    "sg:phone":"+49 5251/138880",
    "sg:postcode":"33178",
    "sg:province":"Nordrhein-Westfalen",
    "wof:name":"Bota Taxi E. Glowienka Und",
    "wof:placetype":"venue"
},
  "geometry": {"coordinates":[8.7354,51.660938],"type":"Point"}
}