{
  "type": "Feature",
  "properties": {
    "iso:country":"DE",
    "sg:address":"Haufeld 11",
    "sg:city":"Siegburg",
    "sg:phone":"+49 2241/64267",
    "sg:postcode":"53721",
    "sg:province":"Nordrhein-Westfalen",
    "wof:name":"G. Rossbach",
    "wof:placetype":"venue"
},
  "geometry": {"coordinates":[7.200775,50.797745],"type":"Point"}
}