{
  "type": "Feature",
  "properties": {
    "iso:country":"DE",
    "sg:address":"Mielberg 5",
    "sg:city":"Kropp",
    "sg:phone":"+49 4624/2941",
    "sg:postcode":"24848",
    "sg:province":"Schleswig-Holstein",
    "wof:name":"E. Kohl",
    "wof:placetype":"venue"
},
  "geometry": {"coordinates":[9.52044,54.438839],"type":"Point"}
}