{
  "type": "Feature",
  "properties": {
    "iso:country":"DE",
    "sg:address":"Haferkamp 26",
    "sg:city":"Hamburg",
    "sg:postcode":"22081",
    "sg:province":"Hamburg",
    "wof:name":"Tub Ton Und Boden Gmbh",
    "wof:placetype":"venue"
},
  "geometry": {"coordinates":[10.0462999344,53.5813598633],"type":"Point"}
}