{
  "type": "Feature",
  "properties": {
    "iso:country":"DE",
    "sg:address":"Weydingerstr. 18",
    "sg:city":"Berlin",
    "sg:phone":"+49 30/2423332",
    "sg:postcode":"10178",
    "sg:province":"Berlin",
    "wof:name":"Ingrid Bahr \u00c4rztin F\u00fcr Allgemeinmedizin",
    "wof:placetype":"venue"
},
  "geometry": {"coordinates":[13.4139785767,52.5268173218],"type":"Point"}
}