{
  "type": "Feature",
  "properties": {
    "iso:country":"DE",
    "sg:address":"Landecker Str. 10",
    "sg:city":"Emmendingen",
    "sg:phone":"+49 7641/570672",
    "sg:postcode":"79312",
    "sg:province":"Baden-W\u00fcrttemberg",
    "wof:name":"Thomas Voigt",
    "wof:placetype":"venue"
},
  "geometry": {"coordinates":[7.834782,48.137413],"type":"Point"}
}