{
  "type": "Feature",
  "properties": {
    "iso:country":"DE",
    "sg:address":"Fohlenweide 18",
    "sg:city":"Barntrup",
    "sg:phone":"+49 5263/8602",
    "sg:postcode":"32683",
    "sg:province":"Nordrhein-Westfalen",
    "wof:name":"Profilform M\u00f6belteile Gmbh",
    "wof:placetype":"venue"
},
  "geometry": {"coordinates":[9.105538,51.996181],"type":"Point"}
}