{
  "type": "Feature",
  "properties": {
    "iso:country":"DE",
    "sg:address":"Th\u00f6rener Str. 39 A",
    "sg:city":"Winsen",
    "sg:phone":"+49 5146/929200",
    "sg:postcode":"29308",
    "sg:province":"Niedersachsen",
    "wof:name":"Wilfried Poets",
    "wof:placetype":"venue"
},
  "geometry": {"coordinates":[9.7575645447,52.6774482727],"type":"Point"}
}