{
  "type": "Feature",
  "properties": {
    "iso:country":"DE",
    "sg:address":"Am Weiher 5",
    "sg:city":"Hamburg",
    "sg:phone":"+49 40/402952",
    "sg:postcode":"20255",
    "sg:province":"Hamburg",
    "wof:name":"Katrin Speidel Heilpraktikerin",
    "wof:placetype":"venue"
},
  "geometry": {"coordinates":[9.9596948624,53.576675415],"type":"Point"}
}