{
  "type": "Feature",
  "properties": {
    "iso:country":"DE",
    "sg:address":"Dieselstr 38",
    "sg:city":"Leingarten",
    "sg:phone":"+49 7131/902100",
    "sg:postcode":"74211",
    "sg:province":"Baden-W\u00fcrttemberg",
    "wof:name":"Sanit-chemie Reinigungsmittel- Und Ger\u00e4te Gmbh",
    "wof:placetype":"venue"
},
  "geometry": {"coordinates":[9.1252117157,49.1466789246],"type":"Point"}
}