{
  "type": "Feature",
  "properties": {
    "iso:country":"DE",
    "sg:address":"Hauptstr. 76",
    "sg:city":"Steinmauern",
    "sg:phone":"+49 7222/22798",
    "sg:postcode":"76479",
    "sg:province":"Baden-W\u00fcrttemberg",
    "wof:name":"Rudi Zoller",
    "wof:placetype":"venue"
},
  "geometry": {"coordinates":[8.1998853683,48.9003295898],"type":"Point"}
}