{
  "type": "Feature",
  "properties": {
    "iso:country":"DE",
    "sg:address":"Wasserburger Str. 4",
    "sg:city":"Haag",
    "sg:phone":"+49 8072/692",
    "sg:postcode":"83527",
    "sg:province":"Bayern",
    "wof:name":"A. Knittberger",
    "wof:placetype":"venue"
},
  "geometry": {"coordinates":[12.1856021881,48.1608734131],"type":"Point"}
}