{
  "type": "Feature",
  "properties": {
    "iso:country":"DE",
    "sg:address":"Rainer Str. 39",
    "sg:city":"Tuntenhausen",
    "sg:phone":"+49 8067/540",
    "sg:postcode":"83104",
    "sg:province":"Bayern",
    "wof:name":"Alois Kalteis",
    "wof:placetype":"venue"
},
  "geometry": {"coordinates":[12.043216,47.948368],"type":"Point"}
}