{
  "type": "Feature",
  "properties": {
    "iso:country":"DE",
    "sg:address":"Schillerstr. 21",
    "sg:city":"Hof",
    "sg:phone":"+49 9281/1798",
    "sg:postcode":"95028",
    "sg:province":"Bayern",
    "wof:name":"Immobilien Eg Raiffeisen Im Landkreis",
    "wof:placetype":"venue"
},
  "geometry": {"coordinates":[11.91335392,50.3152732849],"type":"Point"}
}