{
  "type": "Feature",
  "properties": {
    "iso:country":"DE",
    "sg:address":"Heidestr. 113 b",
    "sg:city":"Schwerte",
    "sg:phone":"+49 2304/41936",
    "sg:postcode":"58239",
    "sg:province":"Nordrhein-Westfalen",
    "wof:name":"F\u00f6rderverein Der Kinderg\u00e4rten Der Evang. Kirchengemeinde",
    "wof:placetype":"venue"
},
  "geometry": {"coordinates":[7.5786151886,51.4654464722],"type":"Point"}
}