{
  "type": "Feature",
  "properties": {
    "iso:country":"DE",
    "sg:address":"Teutonenstr. 101",
    "sg:city":"L\u00fcdenscheid",
    "sg:phone":"+49 2351/3355",
    "sg:postcode":"58509",
    "sg:province":"Nordrhein-Westfalen",
    "wof:name":"Dieter Funke Rechtsanwalt Und Notar",
    "wof:placetype":"venue"
},
  "geometry": {"coordinates":[7.600481987,51.213180542],"type":"Point"}
}