{
  "type": "Feature",
  "properties": {
    "iso:country":"DE",
    "sg:address":"Am Fliegerhorst 2",
    "sg:city":"Gro\u00dfostheim",
    "sg:phone":"+49 6026/990420",
    "sg:postcode":"63762",
    "sg:province":"Bayern",
    "wof:name":"Ips Intelligent Pelletizing Solutions",
    "wof:placetype":"venue"
},
  "geometry": {"coordinates":[9.030999,49.937355],"type":"Point"}
}