{
  "type": "Feature",
  "properties": {
    "iso:country":"DE",
    "sg:address":"Marktplatz 11",
    "sg:city":"Heilbronn",
    "sg:phone":"+49 7131/86580",
    "sg:postcode":"74072",
    "sg:province":"Baden-W\u00fcrttemberg",
    "wof:name":"Tresen Am Markt",
    "wof:placetype":"venue"
},
  "geometry": {"coordinates":[9.2192554474,49.1423149109],"type":"Point"}
}