{
  "type": "Feature",
  "properties": {
    "iso:country":"DE",
    "sg:address":"Amtsstr. 6",
    "sg:city":"Elze",
    "sg:phone":"+49 5068/8420",
    "sg:postcode":"31008",
    "sg:province":"Niedersachsen",
    "wof:name":"Sportlertreff",
    "wof:placetype":"venue"
},
  "geometry": {"coordinates":[9.7394351959,52.1151237488],"type":"Point"}
}