{
  "type": "Feature",
  "properties": {
    "iso:country":"DE",
    "sg:address":"Bahnhofstr. 19",
    "sg:city":"Bienenb\u00fcttel",
    "sg:phone":"+49 5823/333",
    "sg:postcode":"29553",
    "sg:province":"Niedersachsen",
    "wof:name":"Moden Gewald Inh. Hans- Joachim Gewald",
    "wof:placetype":"venue"
},
  "geometry": {"coordinates":[10.487406,53.141834],"type":"Point"}
}