{
  "type": "Feature",
  "properties": {
    "iso:country":"DE",
    "sg:address":"Bischof-Neuh\u00e4usler-Str. 39",
    "sg:city":"Erdweg",
    "sg:phone":"+49 8135/8884",
    "sg:postcode":"85253",
    "sg:province":"Bayern",
    "wof:name":"Robert Und Brigitte Birner",
    "wof:placetype":"venue"
},
  "geometry": {"coordinates":[11.305903,48.343372],"type":"Point"}
}