{
  "type": "Feature",
  "properties": {
    "iso:country":"DE",
    "sg:address":"Hauptstr. 51",
    "sg:city":"Baek",
    "sg:postcode":"19348",
    "sg:province":"Brandenburg",
    "wof:name":"Rita Jordan Lvm-versicherungsb\u00fcro",
    "wof:placetype":"venue"
},
  "geometry": {"coordinates":[11.9196596146,53.1635169983],"type":"Point"}
}