{
  "type": "Feature",
  "properties": {
    "iso:country":"DE",
    "sg:address":"Dorfbroicher Str. 51-53",
    "sg:city":"M\u00f6nchengladbach",
    "sg:phone":"+49 2166/94890",
    "sg:postcode":"41236",
    "sg:province":"Nordrhein-Westfalen",
    "wof:name":"B. Lennartz Und J. Eggen",
    "wof:placetype":"venue"
},
  "geometry": {"coordinates":[6.4525671005,51.1669082642],"type":"Point"}
}