{
  "type": "Feature",
  "properties": {
    "iso:country":"DE",
    "sg:address":"Eggerscheidter Str. 12",
    "sg:city":"Ratingen",
    "sg:phone":"+49 2102/68574",
    "sg:postcode":"40883",
    "sg:province":"Nordrhein-Westfalen",
    "wof:name":"Haus Boltenburg",
    "wof:placetype":"venue"
},
  "geometry": {"coordinates":[6.9081931114,51.3295974731],"type":"Point"}
}