{
  "type": "Feature",
  "properties": {
    "iso:country":"DE",
    "sg:address":"J\u00e4gersruh 12",
    "sg:city":"Braunschweig",
    "sg:phone":"+49 531/62170",
    "sg:postcode":"38126",
    "sg:province":"Niedersachsen",
    "wof:name":"Klaus Harder",
    "wof:placetype":"venue"
},
  "geometry": {"coordinates":[10.55024,52.224751],"type":"Point"}
}