{
  "type": "Feature",
  "properties": {
    "iso:country":"DE",
    "sg:address":"Bruchweg 9",
    "sg:city":"Malsfeld",
    "sg:postcode":"34323",
    "sg:province":"Hessen",
    "wof:name":"Tech Industrieleistung Gmbh",
    "wof:placetype":"venue"
},
  "geometry": {"coordinates":[9.53821,51.092098],"type":"Point"}
}