{
  "type": "Feature",
  "properties": {
    "iso:country":"DE",
    "sg:address":"Kienhorststr 53",
    "sg:city":"Berlin",
    "sg:phone":"+49 30/4100040",
    "sg:postcode":"13403",
    "sg:province":"Berlin",
    "wof:name":"Universal-kugellager-fabrik Gmbh",
    "wof:placetype":"venue"
},
  "geometry": {"coordinates":[13.329355,52.573463],"type":"Point"}
}