{
  "type": "Feature",
  "properties": {
    "iso:country":"DE",
    "sg:address":"Industriestr. 2a",
    "sg:city":"Heinsberg",
    "sg:phone":"+49 2452/23363",
    "sg:postcode":"52525",
    "sg:province":"Nordrhein-Westfalen",
    "wof:name":"Mc Donalds",
    "wof:placetype":"venue"
},
  "geometry": {"coordinates":[6.1011281013,51.0654945374],"type":"Point"}
}