{
  "type": "Feature",
  "properties": {
    "iso:country":"DE",
    "sg:address":"Hanauer Landstrasse 67",
    "sg:city":"Karlsteim am Main",
    "sg:phone":"+49 6188/95030",
    "sg:postcode":"63786",
    "wof:name":"Eucor Gmbh",
    "wof:placetype":"venue"
},
  "geometry": {"coordinates":[-76.06028000000001,42.195438],"type":"Point"}
}