{
  "type": "Feature",
  "properties": {
    "iso:country":"DE",
    "sg:address":"Wischhofsweg 38",
    "sg:city":"Hamburg",
    "sg:postcode":"22523",
    "sg:province":"Hamburg",
    "wof:name":"Bernd Otto",
    "wof:placetype":"venue"
},
  "geometry": {"coordinates":[9.903604,53.6036],"type":"Point"}
}