{
  "type": "Feature",
  "properties": {
    "iso:country":"DE",
    "sg:address":"Thujastr. 17",
    "sg:city":"Schorndorf",
    "sg:phone":"+49 7181/3634",
    "sg:postcode":"73614",
    "sg:province":"Baden-W\u00fcrttemberg",
    "wof:name":"Sf Ober- Unterberken E. V. J\u00fcrgen Geiger",
    "wof:placetype":"venue"
},
  "geometry": {"coordinates":[9.5574016571,48.7789077759],"type":"Point"}
}