{
  "type": "Feature",
  "properties": {
    "iso:country":"DE",
    "sg:address":"Triftstr. 2-8",
    "sg:city":"Berlin",
    "sg:phone":"+49 8651/6080",
    "sg:postcode":"13127",
    "sg:province":"Berlin",
    "wof:name":"Buergerbraeu Bad Reichenhall August Roehm & Soehne Kg",
    "wof:placetype":"venue"
},
  "geometry": {"coordinates":[12.875589,47.722115],"type":"Point"}
}