{
  "type": "Feature",
  "properties": {
    "iso:country":"DE",
    "sg:address":"Reichenbachstr. 13",
    "sg:city":"M\u00fcnchen",
    "sg:phone":"+49 89/2311660",
    "sg:postcode":"80469",
    "sg:province":"Bayern",
    "wof:name":"Hotel Restaurant Deutsche Eiche",
    "wof:placetype":"venue"
},
  "geometry": {"coordinates":[11.576382637,48.1327667236],"type":"Point"}
}