{
  "type": "Feature",
  "properties": {
    "iso:country":"DE",
    "sg:address":"Richtweg 81",
    "sg:city":"Wendelstein",
    "sg:phone":"+49 9129/281818",
    "sg:postcode":"90530",
    "sg:province":"Bayern",
    "wof:name":"Ksl Kosmetik-servicelabor Gmbh & Co Kg",
    "wof:placetype":"venue"
},
  "geometry": {"coordinates":[11.168993,49.351982],"type":"Point"}
}