{
  "type": "Feature",
  "properties": {
    "iso:country":"DE",
    "sg:address":"Falkenstr. 18",
    "sg:city":"Bad Liebenzell",
    "sg:phone":"+49 7052/2713",
    "sg:postcode":"75378",
    "sg:province":"Baden-W\u00fcrttemberg",
    "wof:name":"Johannes M\u00fcller",
    "wof:placetype":"venue"
},
  "geometry": {"coordinates":[8.7992506027,48.7584762573],"type":"Point"}
}