{
  "type": "Feature",
  "properties": {
    "iso:country":"DE",
    "sg:address":"Wehrm\u00fchlenweg 23",
    "sg:city":"Zielitz",
    "sg:phone":"+49 39208/23116",
    "sg:postcode":"39326",
    "sg:province":"Sachsen-Anhalt",
    "wof:name":"Eiscafe Venezia",
    "wof:placetype":"venue"
},
  "geometry": {"coordinates":[11.676384,52.294392],"type":"Point"}
}