{
  "type": "Feature",
  "properties": {
    "iso:country":"DE",
    "sg:address":"Hochst\u00e4dter Landstr. 21",
    "sg:city":"Hanau",
    "sg:postcode":"63454",
    "sg:province":"Hessen",
    "wof:name":"Sgb Stoll Beteiligungs Gmbh",
    "wof:placetype":"venue"
},
  "geometry": {"coordinates":[8.8889,50.143982],"type":"Point"}
}