{
  "type": "Feature",
  "properties": {
    "iso:country":"DE",
    "sg:address":"W\u00f6rthstr. 12",
    "sg:city":"Hof",
    "sg:phone":"+49 9281/84113",
    "sg:postcode":"95028",
    "sg:province":"Bayern",
    "wof:name":"Versandbuchhandlung Karl Oettler E. K.",
    "wof:placetype":"venue"
},
  "geometry": {"coordinates":[11.9175071716,50.3132514954],"type":"Point"}
}