{
  "type": "Feature",
  "properties": {
    "iso:country":"DE",
    "sg:address":"Jahnstr. 200",
    "sg:city":"Eibau",
    "sg:phone":"+49 3586/702516",
    "sg:postcode":"02739",
    "sg:province":"Sachsen",
    "wof:name":"Kottmarbergbaude",
    "wof:placetype":"venue"
},
  "geometry": {"coordinates":[14.6440048218,50.9955711365],"type":"Point"}
}