{
  "type": "Feature",
  "properties": {
    "iso:country":"DE",
    "sg:address":"Marienfelder Allee 75",
    "sg:city":"Berlin",
    "sg:phone":"+49 30/72320635",
    "sg:postcode":"12277",
    "sg:province":"Berlin",
    "wof:name":"Ursus-apotheke",
    "wof:placetype":"venue"
},
  "geometry": {"coordinates":[13.368308,52.419308],"type":"Point"}
}