{
  "type": "Feature",
  "properties": {
    "iso:country":"DE",
    "sg:address":"Am Gut 3",
    "sg:city":"Sch\u00f6nwalde",
    "sg:phone":"+49 3322/22105",
    "sg:postcode":"14621",
    "sg:province":"Brandenburg",
    "wof:name":"Mobile Rohrschwei\u00dferei Sobotta Gmbh",
    "wof:placetype":"venue"
},
  "geometry": {"coordinates":[13.127159,52.622353],"type":"Point"}
}