{
  "type": "Feature",
  "properties": {
    "iso:country":"DE",
    "sg:address":"Im Vogelsang 7",
    "sg:city":"Erpel",
    "sg:phone":"+49 2644/5050",
    "sg:postcode":"53579",
    "sg:province":"Rheinland-Pfalz",
    "wof:name":"Heinz Und Elfriede Fuchs",
    "wof:placetype":"venue"
},
  "geometry": {"coordinates":[7.2410049438,50.5932235718],"type":"Point"}
}