{
  "type": "Feature",
  "properties": {
    "iso:country":"DE",
    "sg:city":"G\u00f6ttingen",
    "sg:postcode":"37075",
    "sg:province":"Niedersachsen",
    "wof:name":"Gaygarden.de",
    "wof:placetype":"venue"
},
  "geometry": {"coordinates":[9.984562,51.5406],"type":"Point"}
}