{
  "type": "Feature",
  "properties": {
    "iso:country":"DE",
    "sg:address":"Bismarckstr. 10",
    "sg:city":"Heilbronn",
    "sg:phone":"+49 7131/81299",
    "sg:postcode":"74072",
    "sg:province":"Baden-W\u00fcrttemberg",
    "wof:name":"Robert-mayer-volks-und Schul- Sternwarte Heilbronn E. V.",
    "wof:placetype":"venue"
},
  "geometry": {"coordinates":[9.2264823914,49.1399803162],"type":"Point"}
}