{
  "type": "Feature",
  "properties": {
    "iso:country":"DE",
    "sg:address":"Heidenheimer Str. 133",
    "sg:city":"Heidenheim",
    "sg:phone":"+49 7321/61004",
    "sg:postcode":"89520",
    "sg:province":"Baden-W\u00fcrttemberg",
    "wof:name":"Gnaier Gmbh",
    "wof:placetype":"venue"
},
  "geometry": {"coordinates":[10.160027,48.699047],"type":"Point"}
}