{
  "type": "Feature",
  "properties": {
    "iso:country":"DE",
    "sg:address":"Kraupaer Str. 2",
    "sg:city":"Elsterwerda",
    "sg:phone":"+49 3533/3250",
    "sg:postcode":"04910",
    "sg:province":"Brandenburg",
    "wof:name":"Rudolf Rost",
    "wof:placetype":"venue"
},
  "geometry": {"coordinates":[13.50403,51.473228],"type":"Point"}
}