{
  "type": "Feature",
  "properties": {
    "iso:country":"DE",
    "sg:address":"Dohrweg 57",
    "sg:city":"M\u00f6nchengladbach",
    "sg:phone":"+49 2161/603468",
    "sg:postcode":"41066",
    "sg:province":"Nordrhein-Westfalen",
    "wof:name":"Berthold Pardon",
    "wof:placetype":"venue"
},
  "geometry": {"coordinates":[6.47472,51.212517],"type":"Point"}
}