{
  "type": "Feature",
  "properties": {
    "iso:country":"DE",
    "sg:address":"Rieder Str. 65",
    "sg:city":"Herrsching",
    "sg:phone":"+49 8152/6735",
    "sg:postcode":"82211",
    "sg:province":"Bayern",
    "wof:name":"Klaus Keller Heilpraktiker",
    "wof:placetype":"venue"
},
  "geometry": {"coordinates":[11.1710195541,48.0017814636],"type":"Point"}
}