{
  "type": "Feature",
  "properties": {
    "iso:country":"DE",
    "sg:address":"Eferdinger Str. 7",
    "sg:city":"Leipzig",
    "sg:phone":"+49 341/9214002",
    "sg:postcode":"04349",
    "sg:province":"Sachsen",
    "wof:name":"W. Heim",
    "wof:placetype":"venue"
},
  "geometry": {"coordinates":[12.4648618698,51.3816223145],"type":"Point"}
}