{
  "type": "Feature",
  "properties": {
    "iso:country":"DE",
    "sg:address":"Klarastr. 10",
    "sg:city":"Bochum",
    "sg:phone":"+49 234/66101",
    "sg:postcode":"44793",
    "sg:province":"Nordrhein-Westfalen",
    "wof:name":"Hotel City-west",
    "wof:placetype":"venue"
},
  "geometry": {"coordinates":[7.2056789398,51.4780082703],"type":"Point"}
}