{
  "type": "Feature",
  "properties": {
    "iso:country":"DE",
    "sg:address":"Lindenstr. 2",
    "sg:city":"Reutlingen",
    "sg:phone":"+49 7121/321493",
    "sg:postcode":"72764",
    "sg:province":"Baden-W\u00fcrttemberg",
    "wof:name":"K.-u. Schmidt Immobilienmakler",
    "wof:placetype":"venue"
},
  "geometry": {"coordinates":[9.214392662,48.4902687073],"type":"Point"}
}