{
  "type": "Feature",
  "properties": {
    "iso:country":"DE",
    "sg:address":"An der Kotsche 17",
    "sg:city":"Leipzig",
    "sg:phone":"+49 341/9415461",
    "sg:postcode":"04207",
    "sg:province":"Sachsen",
    "wof:name":"R\u00fcdiger Hemp Anlageberater",
    "wof:placetype":"venue"
},
  "geometry": {"coordinates":[12.2680597305,51.30884552],"type":"Point"}
}