{
  "type": "Feature",
  "properties": {
    "iso:country":"DE",
    "sg:address":"An der Leuchtenburg 3",
    "sg:city":"Bad Essen",
    "sg:postcode":"49152",
    "sg:province":"Niedersachsen",
    "wof:name":"Holle & Dunker Buchbinderei- Maschinen Gesellschaft Mbh",
    "wof:placetype":"venue"
},
  "geometry": {"coordinates":[8.359537,52.319016],"type":"Point"}
}