{
  "type": "Feature",
  "properties": {
    "iso:country":"DE",
    "sg:address":"Ostseite",
    "sg:city":"H\u00fcnxe",
    "sg:phone":"+49 2858/92020",
    "sg:postcode":"46569",
    "sg:province":"Nordrhein-Westfalen",
    "wof:name":"Autobahntankstelle H\u00fcnxe Ost",
    "wof:placetype":"venue"
},
  "geometry": {"coordinates":[6.7657299042,51.641998291],"type":"Point"}
}