{
  "type": "Feature",
  "properties": {
    "iso:country":"DE",
    "sg:address":"Parkstr. 17",
    "sg:city":"Ehlscheid",
    "sg:phone":"+49 2634/8543",
    "sg:postcode":"56581",
    "sg:province":"Rheinland-Pfalz",
    "wof:name":"Framkes Park-hotel",
    "wof:placetype":"venue"
},
  "geometry": {"coordinates":[7.4692811966,50.5167388916],"type":"Point"}
}