{
  "type": "Feature",
  "properties": {
    "iso:country":"DE",
    "sg:address":"Im Bruchfeld 17",
    "sg:city":"Hattingen",
    "sg:phone":"+49 2324/50090",
    "sg:postcode":"45525",
    "sg:province":"Nordrhein-Westfalen",
    "wof:name":"Hattinger Wohnst\u00e4tten- Genossenschaft Eg",
    "wof:placetype":"venue"
},
  "geometry": {"coordinates":[7.1795401573,51.3964271545],"type":"Point"}
}