{
  "type": "Feature",
  "properties": {
    "iso:country":"DE",
    "sg:address":"Halskestr. 44",
    "sg:city":"Hamburg",
    "sg:phone":"+49 40/784041",
    "sg:postcode":"22113",
    "sg:province":"Schleswig-Holstein",
    "wof:name":"Walter Voss & Co. Schiffahrts Gmbh & Co. Kg",
    "wof:placetype":"venue"
},
  "geometry": {"coordinates":[10.0827980042,53.5210838318],"type":"Point"}
}