{
  "type": "Feature",
  "properties": {
    "iso:country":"DE",
    "sg:address":"Lindenstr. 40",
    "sg:city":"Burgst\u00e4dt",
    "sg:phone":"+49 3724/3865",
    "sg:postcode":"09217",
    "sg:province":"Sachsen",
    "wof:name":"Jens Herrmann",
    "wof:placetype":"venue"
},
  "geometry": {"coordinates":[12.8162050247,50.9232139587],"type":"Point"}
}