{
  "type": "Feature",
  "properties": {
    "iso:country":"DE",
    "sg:address":"Eiermarkt 10",
    "sg:city":"Kesten",
    "sg:phone":"+49 6535/321",
    "sg:postcode":"54518",
    "sg:province":"Rheinland-Pfalz",
    "wof:name":"Franz-josef J\u00fcngling-bockstanz",
    "wof:placetype":"venue"
},
  "geometry": {"coordinates":[6.9554271698,49.9017944336],"type":"Point"}
}