{
  "type": "Feature",
  "properties": {
    "iso:country":"DE",
    "sg:address":"Jochbergstr. 1",
    "sg:city":"Wolfratshausen",
    "sg:phone":"+49 8171/21082",
    "sg:postcode":"82515",
    "sg:province":"Bayern",
    "wof:name":"Harald L\u00f6ssl",
    "wof:placetype":"venue"
},
  "geometry": {"coordinates":[11.4240159988,47.9063987732],"type":"Point"}
}