{
  "type": "Feature",
  "properties": {
    "iso:country":"DE",
    "sg:address":"Hochkamp 7",
    "sg:city":"Haverlah",
    "sg:phone":"+49 5341/33006",
    "sg:postcode":"38275",
    "sg:province":"Niedersachsen",
    "wof:name":"Hannelore Sch\u00f6nfeld",
    "wof:placetype":"venue"
},
  "geometry": {"coordinates":[10.3284912109,52.05103302],"type":"Point"}
}