{
  "type": "Feature",
  "properties": {
    "iso:country":"DE",
    "sg:address":"Horner Landstr. 173",
    "sg:city":"Hamburg",
    "sg:postcode":"22111",
    "sg:province":"Hamburg",
    "wof:name":"Ben Gipsputz Gmbh",
    "wof:placetype":"venue"
},
  "geometry": {"coordinates":[10.079136,53.550236],"type":"Point"}
}