{
  "type": "Feature",
  "properties": {
    "iso:country":"DE",
    "sg:address":"Zillertalstra\u00dfe 55",
    "sg:city":"Berlin",
    "sg:phone":"+49 30/47306064",
    "sg:postcode":"13187",
    "sg:province":"Berlin",
    "wof:name":"Web-public Internetdienstleistungen Iund Service",
    "wof:placetype":"venue"
},
  "geometry": {"coordinates":[13.410626,52.560406],"type":"Point"}
}