{
  "type": "Feature",
  "properties": {
    "iso:country":"DE",
    "sg:address":"Kohlenstr. 15",
    "sg:city":"Wuppertal",
    "sg:phone":"+49 202/602853",
    "sg:postcode":"42389",
    "sg:province":"Nordrhein-Westfalen",
    "wof:name":"Margarethe Maurer",
    "wof:placetype":"venue"
},
  "geometry": {"coordinates":[7.243803978,51.275970459],"type":"Point"}
}