{
  "type": "Feature",
  "properties": {
    "iso:country":"DE",
    "sg:address":"Nikolastr. 25",
    "sg:city":"Landshut",
    "sg:phone":"+49 871/64556",
    "sg:postcode":"84034",
    "sg:province":"Bayern",
    "wof:name":"Nikola",
    "wof:placetype":"venue"
},
  "geometry": {"coordinates":[12.142456,48.543076],"type":"Point"}
}