{
  "type": "Feature",
  "properties": {
    "iso:country":"DE",
    "sg:address":"Versuchsfeld Neuhof",
    "sg:city":"Parchim",
    "sg:postcode":"19370",
    "sg:province":"Mecklenburg-Vorpommern",
    "wof:name":"Zentralstelle F\u00fcr Sortenwesen",
    "wof:placetype":"venue"
},
  "geometry": {"coordinates":[11.854283,53.426849],"type":"Point"}
}