{
  "type": "Feature",
  "properties": {
    "iso:country":"DE",
    "sg:address":"Gasstr. 37c",
    "sg:city":"Solingen",
    "sg:phone":"+49 212/800888",
    "sg:postcode":"42657",
    "sg:province":"Nordrhein-Westfalen",
    "wof:name":"Dachdecker Kl\u00f6mpges Gmbh",
    "wof:placetype":"venue"
},
  "geometry": {"coordinates":[7.08113,51.159466],"type":"Point"}
}