{
  "type": "Feature",
  "properties": {
    "iso:country":"DE",
    "sg:address":"Dorfstr. 86",
    "sg:city":"Nordholz",
    "sg:phone":"+49 4741/1351",
    "sg:postcode":"27637",
    "sg:province":"Niedersachsen",
    "wof:name":"Ralf Redelfs",
    "wof:placetype":"venue"
},
  "geometry": {"coordinates":[8.58795,53.76902],"type":"Point"}
}