{
  "type": "Feature",
  "properties": {
    "iso:country":"DE",
    "sg:address":"Breslauer Str. 23",
    "sg:city":"Ellwangen",
    "sg:phone":"+49 7961/53635",
    "sg:postcode":"73479",
    "sg:province":"Baden-W\u00fcrttemberg",
    "wof:name":"Martin Lang Architekt",
    "wof:placetype":"venue"
},
  "geometry": {"coordinates":[10.116549,48.97139],"type":"Point"}
}