{
  "type": "Feature",
  "properties": {
    "iso:country":"DE",
    "sg:address":"Schakengasse 7",
    "sg:city":"Bitburg",
    "sg:phone":"+49 6561/1011",
    "sg:postcode":"54634",
    "sg:province":"Rheinland-Pfalz",
    "wof:name":"Reiseb\u00fcro Grete Schmitz",
    "wof:placetype":"venue"
},
  "geometry": {"coordinates":[6.5239310265,49.9740180969],"type":"Point"}
}