{
  "type": "Feature",
  "properties": {
    "iso:country":"DE",
    "sg:address":"Langer Weg 9b",
    "sg:city":"Lobenstein",
    "sg:phone":"+49 36651/87455",
    "sg:postcode":"07356",
    "sg:province":"Th\u00fcringen",
    "wof:name":"Carsten Schr\u00f6der",
    "wof:placetype":"venue"
},
  "geometry": {"coordinates":[11.650554657,50.4501991272],"type":"Point"}
}