{
  "type": "Feature",
  "properties": {
    "iso:country":"DE",
    "sg:address":"Winterkastener Weg 10",
    "sg:city":"Lindenfels",
    "sg:phone":"+49 6254/833",
    "sg:postcode":"64678",
    "sg:province":"Hessen",
    "wof:name":"Hotel Buchenhof",
    "wof:placetype":"venue"
},
  "geometry": {"coordinates":[8.7570390701,49.7059516907],"type":"Point"}
}