{
  "type": "Feature",
  "properties": {
    "iso:country":"DE",
    "sg:address":"Oberer Weg 19",
    "sg:city":"Freiburg",
    "sg:phone":"+49 7664/4454",
    "sg:postcode":"79112",
    "sg:province":"Baden-W\u00fcrttemberg",
    "wof:name":"Ernst Hofs\u00e4\u00df",
    "wof:placetype":"venue"
},
  "geometry": {"coordinates":[7.718888,48.003513],"type":"Point"}
}