{
  "type": "Feature",
  "properties": {
    "iso:country":"DE",
    "sg:address":"Friedrich-Engels-Allee 120",
    "sg:city":"Falkensee",
    "sg:phone":"+49 3322/203877",
    "sg:postcode":"14612",
    "sg:province":"Brandenburg",
    "wof:name":"Guido Te\u00dfmer",
    "wof:placetype":"venue"
},
  "geometry": {"coordinates":[13.0627,52.575909],"type":"Point"}
}