{
  "type": "Feature",
  "properties": {
    "iso:country":"DE",
    "sg:address":"Grashofstr. 45",
    "sg:city":"Hagen",
    "sg:phone":"+49 2331/207593",
    "sg:postcode":"58095",
    "sg:province":"Nordrhein-Westfalen",
    "wof:name":"Jugendb\u00fccherei",
    "wof:placetype":"venue"
},
  "geometry": {"coordinates":[7.47125,51.359905],"type":"Point"}
}