{
  "type": "Feature",
  "properties": {
    "iso:country":"DE",
    "sg:address":"Zimmermannstr. 10",
    "sg:city":"Berlin",
    "sg:phone":"+49 30/7916735",
    "sg:postcode":"12163",
    "sg:province":"Berlin",
    "wof:name":"Ursula B\u00f6hm Gmbh",
    "wof:placetype":"venue"
},
  "geometry": {"coordinates":[13.3215856552,52.4600257874],"type":"Point"}
}