{
  "type": "Feature",
  "properties": {
    "iso:country":"DE",
    "sg:address":"Industriestr. 4",
    "sg:city":"D\u00f6rpen",
    "sg:phone":"+49 4963/4030",
    "sg:postcode":"26892",
    "sg:province":"Niedersachsen",
    "wof:name":"Nortrans Speditionsges. Mbh",
    "wof:placetype":"venue"
},
  "geometry": {"coordinates":[7.36142,52.969662],"type":"Point"}
}