{
  "type": "Feature",
  "properties": {
    "iso:country":"DE",
    "sg:address":"Hauptstr. 31",
    "sg:city":"Brombachtal",
    "sg:phone":"+49 4960/631463",
    "sg:postcode":"64753",
    "sg:province":"Hessen",
    "wof:name":"Sparkasse Odenwaldkreis",
    "wof:placetype":"venue"
},
  "geometry": {"coordinates":[8.959009,49.730701],"type":"Point"}
}