{
  "type": "Feature",
  "properties": {
    "iso:country":"DE",
    "sg:address":"Friedrichstr. 47",
    "sg:city":"Wittlich",
    "sg:phone":"+49 6571/96660",
    "sg:postcode":"54516",
    "sg:province":"Rheinland-Pfalz",
    "wof:name":"Kf Elektroservice Gmbh",
    "wof:placetype":"venue"
},
  "geometry": {"coordinates":[6.9013972282,49.9886245728],"type":"Point"}
}