{
  "type": "Feature",
  "properties": {
    "iso:country":"DE",
    "sg:address":"Kornstr. 18",
    "sg:city":"Lorch",
    "sg:postcode":"73547",
    "sg:province":"Baden-W\u00fcrttemberg",
    "wof:name":"Anjo Hydraulische Steuerungen",
    "wof:placetype":"venue"
},
  "geometry": {"coordinates":[9.693039,48.784321],"type":"Point"}
}