{
  "type": "Feature",
  "properties": {
    "iso:country":"DE",
    "sg:address":"Friedrichstr. 1 a",
    "sg:city":"H\u00f6xter",
    "sg:phone":"+49 5271/8250",
    "sg:postcode":"37671",
    "sg:province":"Nordrhein-Westfalen",
    "wof:name":"Christel Andree-melms",
    "wof:placetype":"venue"
},
  "geometry": {"coordinates":[9.3826541901,51.7796936035],"type":"Point"}
}