{
  "type": "Feature",
  "properties": {
    "iso:country":"DE",
    "sg:address":"Ottostr. 3 a",
    "sg:city":"Heusenstamm",
    "sg:phone":"+49 6104/92092",
    "sg:postcode":"63150",
    "sg:province":"Hessen",
    "wof:name":"Peter Hofmann",
    "wof:placetype":"venue"
},
  "geometry": {"coordinates":[8.7989273071,50.0481109619],"type":"Point"}
}