{
  "type": "Feature",
  "properties": {
    "iso:country":"DE",
    "sg:address":"Bruchstr. 38",
    "sg:city":"Ratingen",
    "sg:phone":"+49 2102/83719",
    "sg:postcode":"40882",
    "sg:province":"Nordrhein-Westfalen",
    "wof:name":"Eco Systemberatung Gmbh",
    "wof:placetype":"venue"
},
  "geometry": {"coordinates":[6.8746562004,51.3000831604],"type":"Point"}
}