{
  "type": "Feature",
  "properties": {
    "iso:country":"DE",
    "sg:address":"Elmenhorster Str. 41/1",
    "sg:city":"Wittenhagen",
    "sg:postcode":"18510",
    "sg:province":"Mecklenburg-Vorpommern",
    "wof:name":"Haustechnik Gmbh Norbert Golke",
    "wof:placetype":"venue"
},
  "geometry": {"coordinates":[13.077149,54.18438],"type":"Point"}
}