{
  "type": "Feature",
  "properties": {
    "iso:country":"DE",
    "sg:address":"Lochhamer Str. 15",
    "sg:city":"Planegg",
    "sg:phone":"+49 89/8996860",
    "sg:postcode":"82152",
    "sg:province":"Bayern",
    "wof:name":"Schmolz Und Zimmermann Steuerberater Und",
    "wof:placetype":"venue"
},
  "geometry": {"coordinates":[11.4517383575,48.1109008789],"type":"Point"}
}