{
  "type": "Feature",
  "properties": {
    "iso:country":"DE",
    "sg:address":"Am Wei\u00dfen Stein 23",
    "sg:city":"Frankfurt",
    "sg:phone":"+49 69/525582",
    "sg:postcode":"60431",
    "sg:province":"Hessen",
    "wof:name":"Kurt St\u00e4dter",
    "wof:placetype":"venue"
},
  "geometry": {"coordinates":[8.6547374725,50.1570777893],"type":"Point"}
}