{
  "type": "Feature",
  "properties": {
    "iso:country":"DE",
    "sg:address":"Schillerstr. 18",
    "sg:city":"Tauberbischofsheim",
    "sg:phone":"+49 9341/2029",
    "sg:postcode":"97941",
    "sg:province":"Baden-W\u00fcrttemberg",
    "wof:name":"Hans Schl\u00f6tterlein",
    "wof:placetype":"venue"
},
  "geometry": {"coordinates":[9.6752595901,49.6256523132],"type":"Point"}
}