{
  "type": "Feature",
  "properties": {
    "iso:country":"DE",
    "sg:address":"Stra\u00dfe 76 19",
    "sg:city":"Berlin",
    "sg:postcode":"13127",
    "sg:province":"Berlin",
    "wof:name":"Fubotex Fu\u00dfboden- Und Trockenbautechnik Gmbh",
    "wof:placetype":"venue"
},
  "geometry": {"coordinates":[13.439718,52.610207],"type":"Point"}
}