{
  "type": "Feature",
  "properties": {
    "iso:country":"DE",
    "sg:address":"M\u00fchlbacher Str. 3",
    "sg:city":"K\u00fchren-Burkartshain",
    "sg:phone":"+49 3425/813362",
    "sg:postcode":"04808",
    "sg:province":"Sachsen",
    "wof:name":"Junge Gleis- Weichen- Und Tiefbau Gmbh",
    "wof:placetype":"venue"
},
  "geometry": {"coordinates":[12.791865,51.392357],"type":"Point"}
}