{
  "type": "Feature",
  "properties": {
    "iso:country":"DE",
    "sg:address":"Hugsweierer Kirchstr. 40",
    "sg:city":"Lahr",
    "sg:phone":"+49 7821/43303",
    "sg:postcode":"77933",
    "sg:province":"Baden-W\u00fcrttemberg",
    "wof:name":"Erich Ernst",
    "wof:placetype":"venue"
},
  "geometry": {"coordinates":[7.837391,48.363758],"type":"Point"}
}