{
  "type": "Feature",
  "properties": {
    "iso:country":"DE",
    "sg:address":"Lohrengelweg 11b",
    "sg:city":"Ro\u00dflau",
    "sg:phone":"+49 34901/83057",
    "sg:postcode":"06862",
    "sg:province":"Sachsen-Anhalt",
    "wof:name":"M. Guddel",
    "wof:placetype":"venue"
},
  "geometry": {"coordinates":[12.2372,51.89991],"type":"Point"}
}