{
  "type": "Feature",
  "properties": {
    "iso:country":"DE",
    "sg:address":"Karolingerstr.",
    "sg:city":"Kr\u00f6v",
    "sg:phone":"+49 6541/6291",
    "sg:postcode":"54536",
    "sg:province":"Rheinland-Pfalz",
    "wof:name":"J. Schnitzius-m\u00fcllers Ohg",
    "wof:placetype":"venue"
},
  "geometry": {"coordinates":[7.0864920616,49.9791107178],"type":"Point"}
}