{
  "type": "Feature",
  "properties": {
    "iso:country":"DE",
    "sg:address":"Am Herrschaftswald 97 a",
    "sg:city":"Mannheim",
    "sg:phone":"+49 621/746356",
    "sg:postcode":"68305",
    "sg:province":"Baden-W\u00fcrttemberg",
    "wof:name":"Norbert Reisert",
    "wof:placetype":"venue"
},
  "geometry": {"coordinates":[8.506775856,49.534740448],"type":"Point"}
}