{
  "type": "Feature",
  "properties": {
    "iso:country":"DE",
    "sg:address":"Petersbergstr. 16",
    "sg:city":"Unkel",
    "sg:phone":"+49 2224/4163",
    "sg:postcode":"53572",
    "sg:province":"Rheinland-Pfalz",
    "wof:name":"Gesell. F\u00fcr Eigentumswohnungs- Bau Und Einfamilienh\u00e4user Mbh",
    "wof:placetype":"venue"
},
  "geometry": {"coordinates":[7.2273278236,50.6075210571],"type":"Point"}
}