{
  "type": "Feature",
  "properties": {
    "iso:country":"DE",
    "sg:address":"Crimmitschauer Str. 17",
    "sg:city":"Ponitz",
    "sg:phone":"+49 3764/3046",
    "sg:postcode":"04639",
    "sg:province":"Th\u00fcringen",
    "wof:name":"Peter Grundmann",
    "wof:placetype":"venue"
},
  "geometry": {"coordinates":[12.423235,50.853687],"type":"Point"}
}