{
  "type": "Feature",
  "properties": {
    "iso:country":"DE",
    "sg:address":"Oppauer Str. 21",
    "sg:city":"Mannheim",
    "sg:phone":"+49 621/742656",
    "sg:postcode":"68305",
    "sg:province":"Baden-W\u00fcrttemberg",
    "wof:name":"Hajduk Hirsch",
    "wof:placetype":"venue"
},
  "geometry": {"coordinates":[8.4778299332,49.5275001526],"type":"Point"}
}