{
  "type": "Feature",
  "properties": {
    "iso:country":"DE",
    "sg:address":"Berliner Str. 134",
    "sg:city":"Salzgitter",
    "sg:phone":"+49 5341/65001",
    "sg:postcode":"38226",
    "sg:province":"Niedersachsen",
    "wof:name":"Autoverleih Bismark Gmbh",
    "wof:placetype":"venue"
},
  "geometry": {"coordinates":[10.336093,52.159187],"type":"Point"}
}