{
  "type": "Feature",
  "properties": {
    "iso:country":"DE",
    "sg:address":"Schmidtstedter Str. 29 a",
    "sg:city":"Erfurt",
    "sg:phone":"+49 361/565800",
    "sg:postcode":"99084",
    "sg:province":"Th\u00fcringen",
    "wof:name":"Westphalen Und Kollegen Rechtsanw\u00e4lte",
    "wof:placetype":"venue"
},
  "geometry": {"coordinates":[11.038022995,50.9741859436],"type":"Point"}
}