{
  "type": "Feature",
  "properties": {
    "iso:country":"DE",
    "sg:address":"Puschkinstr. 99",
    "sg:city":"Eilenburg",
    "sg:phone":"+49 3423/605039",
    "sg:postcode":"04838",
    "sg:province":"Sachsen",
    "wof:name":"Angelika Bannier",
    "wof:placetype":"venue"
},
  "geometry": {"coordinates":[12.6553010941,51.4670333862],"type":"Point"}
}