{
  "type": "Feature",
  "properties": {
    "iso:country":"DE",
    "sg:address":"Kellershaustr. 28",
    "sg:city":"Aachen",
    "sg:phone":"+49 4924/1928440",
    "sg:postcode":"52078",
    "sg:province":"Nordrhein-Westfalen",
    "wof:name":"August Heinrigs Druck & Verpackung Gmbh & Co. Kg",
    "wof:placetype":"venue"
},
  "geometry": {"coordinates":[6.1610980034,50.7676277161],"type":"Point"}
}