{
  "type": "Feature",
  "properties": {
    "iso:country":"DE",
    "sg:address":"Rheinstr. 88",
    "sg:city":"M\u00fcnster-Sarmsheim",
    "sg:phone":"+49 6721/994099",
    "sg:postcode":"55424",
    "sg:province":"Rheinland-Pfalz",
    "wof:name":"Norbert Kossmann",
    "wof:placetype":"venue"
},
  "geometry": {"coordinates":[7.8961901665,49.942237854],"type":"Point"}
}