{
  "type": "Feature",
  "properties": {
    "iso:country":"DE",
    "sg:address":"Hauptstr. 106",
    "sg:city":"H\u00fcllhorst",
    "sg:postcode":"32609",
    "sg:province":"Nordrhein-Westfalen",
    "wof:name":"It Civic Lederwaren Gmbh",
    "wof:placetype":"venue"
},
  "geometry": {"coordinates":[8.6665029526,52.2836112976],"type":"Point"}
}