{
  "type": "Feature",
  "properties": {
    "iso:country":"DE",
    "sg:address":"B\u00f6hmerstr. 23",
    "sg:city":"Meerane",
    "sg:phone":"+49 3764/2985",
    "sg:postcode":"08393",
    "sg:province":"Sachsen",
    "wof:name":"H.j. Gr\u00f6ger Nachf.",
    "wof:placetype":"venue"
},
  "geometry": {"coordinates":[12.474082,50.848709],"type":"Point"}
}