{
  "type": "Feature",
  "properties": {
    "iso:country":"DE",
    "sg:address":"Talstr. 2",
    "sg:city":"Emmingen-Liptingen",
    "sg:phone":"+49 7465/1244",
    "sg:postcode":"78576",
    "sg:province":"Baden-W\u00fcrttemberg",
    "wof:name":"Reinhard Bailer",
    "wof:placetype":"venue"
},
  "geometry": {"coordinates":[8.8543834686,47.9306488037],"type":"Point"}
}