{
  "type": "Feature",
  "properties": {
    "iso:country":"DE",
    "sg:address":"Gr\u00fcnberger Str. 4",
    "sg:city":"Dresden",
    "sg:phone":"+49 351/8801800",
    "sg:postcode":"01108",
    "sg:province":"Sachsen",
    "wof:name":"Steffen M\u00fcller Gastronomie- Ausstattungen E. K.",
    "wof:placetype":"venue"
},
  "geometry": {"coordinates":[13.810601,51.153801],"type":"Point"}
}