{
  "type": "Feature",
  "properties": {
    "iso:country":"DE",
    "sg:address":"Zum Aap 34",
    "sg:city":"Dorsten",
    "sg:postcode":"46284",
    "sg:province":"Nordrhein-Westfalen",
    "wof:name":"Michael Spangenberg",
    "wof:placetype":"venue"
},
  "geometry": {"coordinates":[6.9376549721,51.6762771606],"type":"Point"}
}