{
  "type": "Feature",
  "properties": {
    "iso:country":"DE",
    "sg:address":"Mirkstr. 10",
    "sg:city":"Bottrop",
    "sg:phone":"+49 2041/73680",
    "sg:postcode":"46238",
    "sg:province":"Nordrhein-Westfalen",
    "wof:name":"Unterberg Gmbh",
    "wof:placetype":"venue"
},
  "geometry": {"coordinates":[6.9528141022,51.53358078],"type":"Point"}
}