{
  "type": "Feature",
  "properties": {
    "iso:country":"DE",
    "sg:address":"Im Borngarten 19",
    "sg:city":"Waldbrunn",
    "sg:phone":"+49 6436/4386",
    "sg:postcode":"65620",
    "sg:province":"Hessen",
    "wof:name":"Pension Haus Waldesruh",
    "wof:placetype":"venue"
},
  "geometry": {"coordinates":[8.0984239578,50.5067596436],"type":"Point"}
}