{
  "type": "Feature",
  "properties": {
    "iso:country":"DE",
    "sg:address":"Kiefernweg 5",
    "sg:city":"Bad Oeynhausen",
    "sg:phone":"+49 5731/52323",
    "sg:postcode":"32549",
    "sg:province":"Nordrhein-Westfalen",
    "wof:name":"B. M\u00fcller Versandgesch\u00e4ft",
    "wof:placetype":"venue"
},
  "geometry": {"coordinates":[8.7915410995,52.2245178223],"type":"Point"}
}