{
  "type": "Feature",
  "properties": {
    "iso:country":"DE",
    "sg:address":"Oberbachstr. 61",
    "sg:city":"Holzminden",
    "sg:phone":"+49 5531/7561",
    "sg:postcode":"37603",
    "sg:province":"Niedersachsen",
    "wof:name":"H. Sackmann H\u00fcte",
    "wof:placetype":"venue"
},
  "geometry": {"coordinates":[9.4495630264,51.8280181885],"type":"Point"}
}