{
  "type": "Feature",
  "properties": {
    "iso:country":"DE",
    "sg:address":"Gopplasgr\u00fcner Str. 45",
    "sg:city":"Erlbach",
    "sg:phone":"+49 37422/6329",
    "sg:postcode":"08265",
    "sg:province":"Sachsen",
    "wof:name":"M. Bernt",
    "wof:placetype":"venue"
},
  "geometry": {"coordinates":[12.37536,50.314678],"type":"Point"}
}