{
  "type": "Feature",
  "properties": {
    "iso:country":"DE",
    "sg:address":"August-Bebel-Str. 225",
    "sg:city":"Bielefeld",
    "sg:phone":"+49 521/964120",
    "sg:postcode":"33602",
    "sg:province":"Nordrhein-Westfalen",
    "wof:name":"Dr. Holger Rostek Und Christoph Von Haugwitz",
    "wof:placetype":"venue"
},
  "geometry": {"coordinates":[8.5369148254,52.0130233765],"type":"Point"}
}