{
  "type": "Feature",
  "properties": {
    "iso:country":"DE",
    "sg:address":"Hauptstr. 91",
    "sg:city":"Ebersbach",
    "sg:postcode":"02730",
    "sg:province":"Sachsen",
    "wof:name":"Evangelisches Pfarramt Ebersbach",
    "wof:placetype":"venue"
},
  "geometry": {"coordinates":[14.5964269638,51.0091896057],"type":"Point"}
}