{
  "type": "Feature",
  "properties": {
    "iso:country":"DE",
    "sg:address":"Waldeyerstr. 12-14",
    "sg:city":"M\u00fcnster",
    "sg:postcode":"48149",
    "sg:province":"Nordrhein-Westfalen",
    "wof:name":"Angestellten-b\u00fccherei Des Kath. Klinikenpfarramtes",
    "wof:placetype":"venue"
},
  "geometry": {"coordinates":[7.600217,51.959297],"type":"Point"}
}