{
  "type": "Feature",
  "properties": {
    "iso:country":"DE",
    "sg:address":"Frankenthaler Str. 14",
    "sg:city":"Bobenheim-Roxheim",
    "sg:phone":"+49 6239/1249",
    "sg:postcode":"67240",
    "sg:province":"Rheinland-Pfalz",
    "wof:name":"G\u00fcnther Ottmann Gmbh",
    "wof:placetype":"venue"
},
  "geometry": {"coordinates":[8.355371,49.586929],"type":"Point"}
}