{
  "type": "Feature",
  "properties": {
    "iso:country":"DE",
    "sg:address":"Am Kanal 22",
    "sg:city":"Ladbergen",
    "sg:phone":"+49 5485/1508",
    "sg:postcode":"49549",
    "sg:province":"Nordrhein-Westfalen",
    "wof:name":"Ewald Fiegenbaum",
    "wof:placetype":"venue"
},
  "geometry": {"coordinates":[7.715656,52.151928],"type":"Point"}
}