{
  "type": "Feature",
  "properties": {
    "iso:country":"DE",
    "sg:address":"Maienstr. 9 Kottweil",
    "sg:city":"Berglen",
    "sg:phone":"+49 7181/977570",
    "sg:postcode":"71663",
    "sg:province":"Baden-W\u00fcrttemberg",
    "wof:name":"Ernst Heck + Soehne Bauunternehmen, Gmbh",
    "wof:placetype":"venue"
},
  "geometry": {"coordinates":[-91.457527,33.225182],"type":"Point"}
}