{
  "type": "Feature",
  "properties": {
    "iso:country":"DE",
    "sg:address":"Mei\u00dfener Str. 14",
    "sg:city":"Essen",
    "sg:phone":"+49 201/733044",
    "sg:postcode":"45145",
    "sg:province":"Nordrhein-Westfalen",
    "wof:name":"Helmut K\u00f6lscheidt Masseur",
    "wof:placetype":"venue"
},
  "geometry": {"coordinates":[6.975305,51.444599],"type":"Point"}
}