{
  "type": "Feature",
  "properties": {
    "iso:country":"DE",
    "sg:address":"Die Ritterwiesen 17",
    "sg:city":"Liederbach",
    "sg:phone":"+49 6196/21757",
    "sg:postcode":"65835",
    "sg:province":"Hessen",
    "wof:name":"J\u00fcrgen Schl\u00fcter",
    "wof:placetype":"venue"
},
  "geometry": {"coordinates":[8.481306,50.127041],"type":"Point"}
}