{
  "type": "Feature",
  "properties": {
    "iso:country":"DE",
    "sg:address":"Hasselbusch 44",
    "sg:city":"Henstedt-Ulzburg",
    "sg:phone":"+49 4193/94582",
    "sg:postcode":"24558",
    "sg:province":"Schleswig-Holstein",
    "wof:name":"Ktg Textil-import Gmbh",
    "wof:placetype":"venue"
},
  "geometry": {"coordinates":[10.0072622299,53.7947158813],"type":"Point"}
}