{
  "type": "Feature",
  "properties": {
    "iso:country":"DE",
    "sg:address":"Rottmannsiepe 9",
    "sg:city":"Gelsenkirchen",
    "sg:phone":"+49 209/370377",
    "sg:postcode":"45894",
    "sg:province":"Nordrhein-Westfalen",
    "wof:name":"Harpers Bazar Textil Handels Gmbh & Co. Kg",
    "wof:placetype":"venue"
},
  "geometry": {"coordinates":[7.052403,51.578213],"type":"Point"}
}