{
  "type": "Feature",
  "properties": {
    "iso:country":"DE",
    "sg:address":"Oststr. 14",
    "sg:city":"Uelsen",
    "sg:phone":"+49 5942/712",
    "sg:postcode":"49843",
    "sg:province":"Niedersachsen",
    "wof:name":"W. Elsmann",
    "wof:placetype":"venue"
},
  "geometry": {"coordinates":[6.8950791359,52.4920349121],"type":"Point"}
}