{
  "type": "Feature",
  "properties": {
    "iso:country":"DE",
    "sg:address":"Ilmenauer Str. 7",
    "sg:city":"St\u00fctzerbach",
    "sg:phone":"+49 36784/50238",
    "sg:postcode":"98714",
    "sg:province":"Th\u00fcringen",
    "wof:name":"Egon Witzmann",
    "wof:placetype":"venue"
},
  "geometry": {"coordinates":[10.8504199982,50.6493911743],"type":"Point"}
}