{
  "type": "Feature",
  "properties": {
    "iso:country":"DE",
    "sg:address":"Bundesstr. 27",
    "sg:city":"Versmold",
    "sg:phone":"+49 5423/2567",
    "sg:postcode":"33775",
    "sg:province":"Nordrhein-Westfalen",
    "wof:name":"Kottemann & Wolf Gmbh",
    "wof:placetype":"venue"
},
  "geometry": {"coordinates":[8.234045,52.074036],"type":"Point"}
}