{
  "type": "Feature",
  "properties": {
    "iso:country":"DE",
    "sg:address":"Oberstr. 22",
    "sg:city":"Langenscheid",
    "sg:phone":"+49 6439/467",
    "sg:postcode":"65558",
    "sg:province":"Rheinland-Pfalz",
    "wof:name":"Margot Kr\u00fcger Masseurin",
    "wof:placetype":"venue"
},
  "geometry": {"coordinates":[7.950633,50.355412],"type":"Point"}
}