{
  "type": "Feature",
  "properties": {
    "iso:country":"DE",
    "sg:address":"Polarweg 1 B",
    "sg:city":"Hamburg",
    "sg:phone":"+49 40/6784242",
    "sg:postcode":"22145",
    "sg:province":"Hamburg",
    "wof:name":"Dr. Polensky Kg",
    "wof:placetype":"venue"
},
  "geometry": {"coordinates":[10.1496629715,53.6281166077],"type":"Point"}
}