{
  "type": "Feature",
  "properties": {
    "iso:country":"DE",
    "sg:address":"Kaplan-Mertens-Weg 6",
    "sg:city":"Oberhausen",
    "sg:postcode":"46147",
    "sg:province":"Nordrhein-Westfalen",
    "wof:name":"Kath. \u00f6ffentliche Bibliothek St. Joseph",
    "wof:placetype":"venue"
},
  "geometry": {"coordinates":[6.821099,51.54023],"type":"Point"}
}