{
  "type": "Feature",
  "properties": {
    "iso:country":"DE",
    "sg:address":"Ahornstr. 8-9",
    "sg:city":"Finowfurt",
    "sg:phone":"+49 3335/7198",
    "sg:postcode":"16244",
    "sg:province":"Brandenburg",
    "wof:name":"Ebbecke & Berger Trockenbau Gmbh",
    "wof:placetype":"venue"
},
  "geometry": {"coordinates":[13.690463,52.842278],"type":"Point"}
}