{
  "type": "Feature",
  "properties": {
    "iso:country":"DE",
    "sg:address":"Gothaer Weg 49",
    "sg:city":"D\u00fcsseldorf",
    "sg:phone":"+49 211/275137",
    "sg:postcode":"40627",
    "sg:province":"Nordrhein-Westfalen",
    "wof:name":"Hauke R\u00f6ssler",
    "wof:placetype":"venue"
},
  "geometry": {"coordinates":[6.8545250893,51.2177047729],"type":"Point"}
}