{
  "type": "Feature",
  "properties": {
    "iso:country":"DE",
    "sg:address":"Frankfurter Str. 110",
    "sg:city":"Seligenstadt",
    "sg:postcode":"63500",
    "sg:province":"Hessen",
    "wof:name":"Am Eurocargo Gmbh",
    "wof:placetype":"venue"
},
  "geometry": {"coordinates":[8.9595918655,50.0454788208],"type":"Point"}
}