{
  "type": "Feature",
  "properties": {
    "iso:country":"DE",
    "sg:address":"An der Senke 18",
    "sg:city":"Reken",
    "sg:phone":"+49 2864/881587",
    "sg:postcode":"48734",
    "sg:province":"Nordrhein-Westfalen",
    "wof:name":"Webs @nd Sites",
    "wof:placetype":"venue"
},
  "geometry": {"coordinates":[7.0394902229,51.8286895752],"type":"Point"}
}