{
  "type": "Feature",
  "properties": {
    "iso:country":"DE",
    "sg:address":"Pohlgasse 7",
    "sg:city":"Troisdorf",
    "sg:phone":"+49 228/451935",
    "sg:postcode":"53844",
    "sg:province":"Nordrhein-Westfalen",
    "wof:name":"Hans Schmitz",
    "wof:placetype":"venue"
},
  "geometry": {"coordinates":[7.092063,50.776012],"type":"Point"}
}