{
  "type": "Feature",
  "properties": {
    "iso:country":"DE",
    "sg:address":"Tittmoninger Str. 19",
    "sg:city":"Laufen",
    "sg:phone":"+49 8682/89840",
    "sg:postcode":"83410",
    "sg:province":"Bayern",
    "wof:name":"Hotel-restaurant Traunsteiner Hof",
    "wof:placetype":"venue"
},
  "geometry": {"coordinates":[12.9331245422,47.9368476868],"type":"Point"}
}