{
  "type": "Feature",
  "properties": {
    "iso:country":"DE",
    "sg:address":"Hauptstr. 17",
    "sg:city":"Priestewitz",
    "sg:phone":"+49 35249/71473",
    "sg:postcode":"01561",
    "sg:province":"Sachsen",
    "wof:name":"S. Fischer",
    "wof:placetype":"venue"
},
  "geometry": {"coordinates":[13.5435571671,51.2344856262],"type":"Point"}
}