{
  "type": "Feature",
  "properties": {
    "iso:country":"DE",
    "sg:address":"Rathelbeckstr. 273",
    "sg:city":"D\u00fcsseldorf",
    "sg:phone":"+49 211/202034",
    "sg:postcode":"40627",
    "sg:province":"Nordrhein-Westfalen",
    "wof:name":"Janssen Computer + Software Gmbh",
    "wof:placetype":"venue"
},
  "geometry": {"coordinates":[6.8812999725,51.2086715698],"type":"Point"}
}