{
  "type": "Feature",
  "properties": {
    "iso:country":"DE",
    "sg:address":"Friedrichshafener Str. 79",
    "sg:city":"Eriskirch",
    "sg:phone":"+49 7541/8431",
    "sg:postcode":"88097",
    "sg:province":"Baden-W\u00fcrttemberg",
    "wof:name":"Kaisers Tengelmann Ag",
    "wof:placetype":"venue"
},
  "geometry": {"coordinates":[9.5238103867,47.6345710754],"type":"Point"}
}