{
  "type": "Feature",
  "properties": {
    "iso:country":"DE",
    "sg:address":"Robert-Bosch-Str. 30",
    "sg:city":"Dreieich",
    "sg:phone":"+49 6103/311437",
    "sg:postcode":"63303",
    "sg:province":"Hessen",
    "wof:name":"Landgraf Gmbh",
    "wof:placetype":"venue"
},
  "geometry": {"coordinates":[8.7042417526,50.0321617126],"type":"Point"}
}