{
  "type": "Feature",
  "properties": {
    "iso:country":"DE",
    "sg:address":"Mindener Str. 55",
    "sg:city":"H\u00fcllhorst",
    "sg:phone":"+49 5744/921134",
    "sg:postcode":"32609",
    "sg:province":"Nordrhein-Westfalen",
    "wof:name":"D. Sielermann",
    "wof:placetype":"venue"
},
  "geometry": {"coordinates":[8.718455,52.274029],"type":"Point"}
}