{
  "type": "Feature",
  "properties": {
    "iso:country":"DE",
    "sg:address":"Stauden 2",
    "sg:city":"Haag",
    "sg:phone":"+49 8072/1331",
    "sg:postcode":"83527",
    "sg:province":"Bayern",
    "wof:name":"Franz Maier",
    "wof:placetype":"venue"
},
  "geometry": {"coordinates":[12.123295784,48.1697769165],"type":"Point"}
}