{
  "type": "Feature",
  "properties": {
    "iso:country":"DE",
    "sg:address":"Siedlung West 87",
    "sg:city":"Brandis",
    "sg:phone":"+49 34292/78264",
    "sg:postcode":"04821",
    "sg:province":"Sachsen",
    "wof:name":"Sander Gmbh",
    "wof:placetype":"venue"
},
  "geometry": {"coordinates":[12.5957098007,51.3275299072],"type":"Point"}
}