{
  "type": "Feature",
  "properties": {
    "iso:country":"DE",
    "sg:address":"Geratsberger Str. 5",
    "sg:city":"Dingolfing",
    "sg:phone":"+49 8731/71265",
    "sg:postcode":"84130",
    "sg:province":"Bayern",
    "wof:name":"Krei\u00dfl Malerbetrieb-farben- Haus Tapetenstudio E. K.",
    "wof:placetype":"venue"
},
  "geometry": {"coordinates":[12.495983,48.639725],"type":"Point"}
}