{
  "type": "Feature",
  "properties": {
    "iso:country":"DE",
    "sg:address":"Lange Str. 39",
    "sg:city":"Cloppenburg",
    "sg:phone":"+49 4471/88030",
    "sg:postcode":"49661",
    "sg:province":"Niedersachsen",
    "wof:name":"Commerzbank Ag",
    "wof:placetype":"venue"
},
  "geometry": {"coordinates":[8.039774,52.844749],"type":"Point"}
}