{
  "type": "Feature",
  "properties": {
    "iso:country":"DE",
    "sg:address":"Filzengraben 33",
    "sg:city":"Kerpen",
    "sg:phone":"+49 2237/53969",
    "sg:postcode":"50171",
    "sg:province":"Nordrhein-Westfalen",
    "wof:name":"Jean Rindermann Innenarchitekt",
    "wof:placetype":"venue"
},
  "geometry": {"coordinates":[6.69004,50.870575],"type":"Point"}
}