{
  "type": "Feature",
  "properties": {
    "iso:country":"DE",
    "sg:address":"Am Hohenwiesenweg 1",
    "sg:city":"Schotten",
    "sg:phone":"+49 6044/2631",
    "sg:postcode":"63679",
    "sg:province":"Hessen",
    "wof:name":"Naturpark Hoher Vogelsberg",
    "wof:placetype":"venue"
},
  "geometry": {"coordinates":[9.1194629669,50.4995765686],"type":"Point"}
}