{
  "type": "Feature",
  "properties": {
    "iso:country":"DE",
    "sg:address":"Marie-Curie-Str. 24",
    "sg:city":"Frankfurt",
    "sg:phone":"+49 69/9511670",
    "sg:postcode":"60439",
    "sg:province":"Hessen",
    "wof:name":"Imbau Industrielles Bauen Gmbh",
    "wof:placetype":"venue"
},
  "geometry": {"coordinates":[8.6368255615,50.1710395813],"type":"Point"}
}