{
  "type": "Feature",
  "properties": {
    "iso:country":"DE",
    "sg:address":"Bauernwinkel 1a",
    "sg:city":"Amesdorf",
    "sg:phone":"+49 39262/211",
    "sg:postcode":"39439",
    "sg:province":"Sachsen-Anhalt",
    "wof:name":"Agrar-genossenschaft Amesdorf Eg",
    "wof:placetype":"venue"
},
  "geometry": {"coordinates":[11.6000041962,51.7816467285],"type":"Point"}
}