{
  "type": "Feature",
  "properties": {
    "iso:country":"DE",
    "sg:address":"Schulze-Delitzsch-Str. 7a",
    "sg:city":"Burgwedel",
    "sg:phone":"+49 5139/4914",
    "sg:postcode":"30938",
    "sg:province":"Niedersachsen",
    "wof:name":"Klaus-dietrich Schr\u00f6der Ingenieur",
    "wof:placetype":"venue"
},
  "geometry": {"coordinates":[9.8337726593,52.4962882996],"type":"Point"}
}