{
  "type": "Feature",
  "properties": {
    "iso:country":"DE",
    "sg:address":"Fontanestr. 10",
    "sg:city":"Strausberg",
    "sg:phone":"+49 3341/311946",
    "sg:postcode":"15344",
    "sg:province":"Brandenburg",
    "wof:name":"Klaas Immobilien Gmbh",
    "wof:placetype":"venue"
},
  "geometry": {"coordinates":[13.8672561646,52.5657844543],"type":"Point"}
}