{
  "type": "Feature",
  "properties": {
    "iso:country":"DE",
    "sg:address":"Dorfstr. 4",
    "sg:city":"Waldkirchen",
    "sg:postcode":"09437",
    "sg:province":"Sachsen",
    "wof:name":"H. Wagner",
    "wof:placetype":"venue"
},
  "geometry": {"coordinates":[13.1208095551,50.7655220032],"type":"Point"}
}