{
  "type": "Feature",
  "properties": {
    "iso:country":"DE",
    "sg:address":"Diemannskirchen 23",
    "sg:city":"Geisenhausen",
    "sg:phone":"+49 8743/1097",
    "sg:postcode":"84144",
    "sg:province":"Bayern",
    "wof:name":"Landgasthof Vitus Schwaiger",
    "wof:placetype":"venue"
},
  "geometry": {"coordinates":[12.3041248322,48.485660553],"type":"Point"}
}