{
  "type": "Feature",
  "properties": {
    "iso:country":"DE",
    "sg:address":"Hauptstr. 58",
    "sg:city":"Mickhausen",
    "sg:phone":"+49 8204/757",
    "sg:postcode":"86866",
    "sg:province":"Bayern",
    "wof:name":"Stauden Schreiner Holzbau Gmbh",
    "wof:placetype":"venue"
},
  "geometry": {"coordinates":[10.637863,48.235611],"type":"Point"}
}