{
  "type": "Feature",
  "properties": {
    "iso:country":"DE",
    "sg:address":"Gro\u00dfe M\u00fchlenwallstr. 36",
    "sg:city":"Aurich",
    "sg:phone":"+49 4941/62655",
    "sg:postcode":"26603",
    "sg:province":"Niedersachsen",
    "wof:name":"Tiffany",
    "wof:placetype":"venue"
},
  "geometry": {"coordinates":[7.4861431122,53.4678421021],"type":"Point"}
}