{
  "type": "Feature",
  "properties": {
    "iso:country":"DE",
    "sg:address":"Hauptstr. 63",
    "sg:city":"Donzdorf",
    "sg:phone":"+49 4971/6220080",
    "sg:postcode":"73072",
    "sg:province":"Baden-W\u00fcrttemberg",
    "wof:name":"Kreissparkasse G\u00f6ppingen",
    "wof:placetype":"venue"
},
  "geometry": {"coordinates":[9.80949,48.686668],"type":"Point"}
}