{
  "type": "Feature",
  "properties": {
    "iso:country":"DE",
    "sg:address":"Scheidertalstr. 22",
    "sg:city":"Aarbergen",
    "sg:phone":"+49 6120/281",
    "sg:postcode":"65326",
    "sg:province":"Hessen",
    "wof:name":"Prv-gesellschaft F\u00fcr Verm\u00f6gensverwaltung Immo-",
    "wof:placetype":"venue"
},
  "geometry": {"coordinates":[8.075821,50.243191],"type":"Point"}
}