{
  "type": "Feature",
  "properties": {
    "iso:country":"DE",
    "sg:address":"Waldstr. 9",
    "sg:city":"M\u00f6rfelden-Walldorf",
    "sg:phone":"+49 6105/5264",
    "sg:postcode":"64546",
    "sg:province":"Hessen",
    "wof:name":"Adolf Cezanne",
    "wof:placetype":"venue"
},
  "geometry": {"coordinates":[8.57954,50.002872],"type":"Point"}
}