{
  "type": "Feature",
  "properties": {
    "iso:country":"DE",
    "sg:address":"Bahnhofstr. 16",
    "sg:city":"Gro\u00dfenl\u00fcder",
    "sg:phone":"+49 6648/7259",
    "sg:postcode":"36137",
    "sg:province":"Hessen",
    "wof:name":"Friedrich Hahn",
    "wof:placetype":"venue"
},
  "geometry": {"coordinates":[9.543442,50.589237],"type":"Point"}
}