{
  "type": "Feature",
  "properties": {
    "iso:country":"DE",
    "sg:address":"Druckerstr. 55",
    "sg:city":"M\u00f6nchengladbach",
    "sg:phone":"+49 2166/915141",
    "sg:postcode":"41238",
    "sg:province":"Nordrhein-Westfalen",
    "wof:name":"Hans Kaluba",
    "wof:placetype":"venue"
},
  "geometry": {"coordinates":[6.4618592262,51.1686134338],"type":"Point"}
}