{
  "type": "Feature",
  "properties": {
    "iso:country":"DE",
    "sg:address":"Im Hauen 103",
    "sg:city":"Pinneberg",
    "sg:phone":"+49 4101/74784",
    "sg:postcode":"25421",
    "sg:province":"Schleswig-Holstein",
    "wof:name":"Arno Lange Steuerberater",
    "wof:placetype":"venue"
},
  "geometry": {"coordinates":[9.7772321701,53.6817016602],"type":"Point"}
}