{
  "type": "Feature",
  "properties": {
    "iso:country":"DE",
    "sg:address":"Allmannsdorf 3",
    "sg:city":"Pleinfeld",
    "sg:phone":"+49 9144/926460",
    "sg:postcode":"91785",
    "sg:province":"Bayern",
    "wof:name":"Landgasthaus Hocheder Inh. J\u00fcrgen Tr\u00f6ster",
    "wof:placetype":"venue"
},
  "geometry": {"coordinates":[10.9649019241,49.1359825134],"type":"Point"}
}