{
  "type": "Feature",
  "properties": {
    "iso:country":"DE",
    "sg:address":"Zum Hallenbad 15",
    "sg:city":"Lebach",
    "sg:phone":"+49 6881/4223",
    "sg:postcode":"66822",
    "sg:province":"Saarland",
    "wof:name":"Rudolf Georg",
    "wof:placetype":"venue"
},
  "geometry": {"coordinates":[6.9042110443,49.4132080078],"type":"Point"}
}