{
  "type": "Feature",
  "properties": {
    "iso:country":"DE",
    "sg:address":"Zeil 51",
    "sg:city":"Frankfurt",
    "sg:phone":"+49 69/288691",
    "sg:postcode":"60313",
    "sg:province":"Hessen",
    "wof:name":"Baader Textil- Handels Beteiligungs Gmbh",
    "wof:placetype":"venue"
},
  "geometry": {"coordinates":[8.687485,50.114559],"type":"Point"}
}