{
  "type": "Feature",
  "properties": {
    "iso:country":"DE",
    "sg:address":"Schmiedegasse 36",
    "sg:city":"Bornheim",
    "sg:phone":"+49 2227/880",
    "sg:postcode":"53332",
    "sg:province":"Nordrhein-Westfalen",
    "wof:name":"Hotel-restaurant Zum Dorfbrunnen",
    "wof:placetype":"venue"
},
  "geometry": {"coordinates":[6.9509048462,50.7628822327],"type":"Point"}
}