{
  "type": "Feature",
  "properties": {
    "iso:country":"DE",
    "sg:address":"Am Sandbach 55",
    "sg:city":"Haan",
    "sg:phone":"+49 212/96569",
    "sg:postcode":"42781",
    "sg:province":"Nordrhein-Westfalen",
    "wof:name":"Hartmut Eicker Ingenieur",
    "wof:placetype":"venue"
},
  "geometry": {"coordinates":[6.9831609726,51.189743042],"type":"Point"}
}