{
  "type": "Feature",
  "properties": {
    "iso:country":"DE",
    "sg:address":"Dollartstr. 4",
    "sg:city":"Emden",
    "sg:phone":"+49 4921/21923",
    "sg:postcode":"26723",
    "sg:province":"Niedersachsen",
    "wof:name":"B. Und H. Hentschel Inh. J\u00fcrren Kreft E. K.",
    "wof:placetype":"venue"
},
  "geometry": {"coordinates":[7.1947450638,53.3561668396],"type":"Point"}
}