{
  "type": "Feature",
  "properties": {
    "iso:country":"DE",
    "sg:address":"Zwickauer Str. 73",
    "sg:city":"Leipzig",
    "sg:phone":"+49 341/8780210",
    "sg:postcode":"04277",
    "sg:province":"Sachsen",
    "wof:name":"Werner Riedel Architekt",
    "wof:placetype":"venue"
},
  "geometry": {"coordinates":[12.396684,51.30862],"type":"Point"}
}