{
  "type": "Feature",
  "properties": {
    "iso:country":"DE",
    "sg:address":"Laurenzstr. 57",
    "sg:city":"Ochtrup",
    "sg:phone":"+49 2553/3626",
    "sg:postcode":"48607",
    "sg:province":"Nordrhein-Westfalen",
    "wof:name":"Theodor Holling Fina-tankstelle",
    "wof:placetype":"venue"
},
  "geometry": {"coordinates":[7.1951899529,52.2103347778],"type":"Point"}
}