{
  "type": "Feature",
  "properties": {
    "iso:country":"DE",
    "sg:address":"Am Ruhrpark",
    "sg:city":"Bochum",
    "sg:postcode":"44805",
    "sg:province":"Nordrhein-Westfalen",
    "wof:name":"Aldi Gmbh & Co. Kg",
    "wof:placetype":"venue"
},
  "geometry": {"coordinates":[7.2893438339,51.4985656738],"type":"Point"}
}