{
  "type": "Feature",
  "properties": {
    "iso:country":"DE",
    "sg:address":"Endenicher Str. 315",
    "sg:city":"Bonn",
    "sg:phone":"+49 228/614554",
    "sg:postcode":"53121",
    "sg:province":"Nordrhein-Westfalen",
    "wof:name":"Delicado-grill",
    "wof:placetype":"venue"
},
  "geometry": {"coordinates":[7.0729570389,50.7271652222],"type":"Point"}
}