{
  "type": "Feature",
  "properties": {
    "iso:country":"DE",
    "sg:address":"Hagenau",
    "sg:city":"Ainring",
    "sg:phone":"+49 8654/8216",
    "sg:postcode":"83404",
    "sg:province":"Bayern",
    "wof:name":"Roman Steinbacher",
    "wof:placetype":"venue"
},
  "geometry": {"coordinates":[12.9531202316,47.7983398438],"type":"Point"}
}