{
  "type": "Feature",
  "properties": {
    "iso:country":"DE",
    "sg:address":"Hauptstr. 1",
    "sg:city":"St\u00fchlingen",
    "sg:phone":"+49 7744/715",
    "sg:postcode":"79780",
    "sg:province":"Baden-W\u00fcrttemberg",
    "wof:name":"A. Duttlinger",
    "wof:placetype":"venue"
},
  "geometry": {"coordinates":[8.4485301971,47.7457695007],"type":"Point"}
}