{
  "type": "Feature",
  "properties": {
    "iso:country":"DE",
    "sg:address":"Trappenweg 11c",
    "sg:city":"Falkensee",
    "sg:phone":"+49 3322/22815",
    "sg:postcode":"14612",
    "sg:province":"Brandenburg",
    "wof:name":"Norman Ascot",
    "wof:placetype":"venue"
},
  "geometry": {"coordinates":[13.06407547,52.5607414246],"type":"Point"}
}