{
  "type": "Feature",
  "properties": {
    "iso:country":"DE",
    "sg:address":"Nizzatal 4",
    "sg:city":"Velbert",
    "sg:phone":"+49 2052/961240",
    "sg:postcode":"42555",
    "sg:province":"Nordrhein-Westfalen",
    "wof:name":"Nizza Bad",
    "wof:placetype":"venue"
},
  "geometry": {"coordinates":[7.135643959,51.3434143066],"type":"Point"}
}