{
  "type": "Feature",
  "properties": {
    "iso:country":"DE",
    "sg:address":"Am Gstadthof 7",
    "sg:city":"Teisnach",
    "sg:phone":"+49 9923/2065",
    "sg:postcode":"94244",
    "sg:province":"Bayern",
    "wof:name":"Dr. Med. Sigisbert Molz Arzt F\u00fcr Allgemeinmedizin",
    "wof:placetype":"venue"
},
  "geometry": {"coordinates":[12.9930782318,49.0394287109],"type":"Point"}
}