{
  "type": "Feature",
  "properties": {
    "iso:country":"DE",
    "sg:address":"Schreckenbachstr. 16",
    "sg:city":"Berlin",
    "sg:postcode":"13156",
    "sg:province":"Berlin",
    "wof:name":"Elektromontage Nordlicht Gmbh",
    "wof:placetype":"venue"
},
  "geometry": {"coordinates":[13.398039,52.589355],"type":"Point"}
}