{
  "type": "Feature",
  "properties": {
    "iso:country":"DE",
    "sg:address":"Mayenfischstr. 20",
    "sg:city":"Konstanz",
    "sg:phone":"+49 7531/16463",
    "sg:postcode":"78462",
    "sg:province":"Baden-W\u00fcrttemberg",
    "wof:name":"U. Knoll Und T. Grieshaber Knoll",
    "wof:placetype":"venue"
},
  "geometry": {"coordinates":[9.16426754,47.6642303467],"type":"Point"}
}