{
  "type": "Feature",
  "properties": {
    "iso:country":"DE",
    "sg:address":"Sch\u00f6tmarsche Str. 20",
    "sg:city":"Leopoldsh\u00f6he",
    "sg:postcode":"33818",
    "sg:province":"Nordrhein-Westfalen",
    "wof:name":"Bekleidungswerkst\u00e4tte Linneweber Gmbh",
    "wof:placetype":"venue"
},
  "geometry": {"coordinates":[8.7012176514,52.0128822327],"type":"Point"}
}