{
  "type": "Feature",
  "properties": {
    "iso:country":"DE",
    "sg:address":"Gr\u00fcner Weg 2",
    "sg:city":"Eschwege",
    "sg:postcode":"37269",
    "sg:province":"Hessen",
    "wof:name":"Jantz Beteiligungsges. Mbh",
    "wof:placetype":"venue"
},
  "geometry": {"coordinates":[10.060053,51.18372],"type":"Point"}
}