{
  "type": "Feature",
  "properties": {
    "iso:country":"DE",
    "sg:address":"Salzstr. 13",
    "sg:city":"Gera",
    "sg:phone":"+49 365/7101185",
    "sg:postcode":"07551",
    "sg:province":"Th\u00fcringen",
    "wof:name":"Christian Wild",
    "wof:placetype":"venue"
},
  "geometry": {"coordinates":[12.080809,50.841064],"type":"Point"}
}