{
  "type": "Feature",
  "properties": {
    "iso:country":"DE",
    "sg:address":"Wapelstr. 29",
    "sg:city":"Rietberg",
    "sg:phone":"+49 5244/5668",
    "sg:postcode":"33397",
    "sg:province":"Nordrhein-Westfalen",
    "wof:name":"Hubert Ellendorff",
    "wof:placetype":"venue"
},
  "geometry": {"coordinates":[8.408636,51.84169],"type":"Point"}
}