{
  "type": "Feature",
  "properties": {
    "iso:country":"DE",
    "sg:address":"Garde-du-Corps-Str. 7",
    "sg:city":"Kassel",
    "sg:phone":"+49 561/776216",
    "sg:postcode":"34117",
    "sg:province":"Hessen",
    "wof:name":"Schwanenapotheke Ohg",
    "wof:placetype":"venue"
},
  "geometry": {"coordinates":[9.490423,51.313103],"type":"Point"}
}