{
  "type": "Feature",
  "properties": {
    "iso:country":"DE",
    "sg:address":"Geranienstr. 10",
    "sg:city":"Leinfelden-Echterdingen",
    "sg:phone":"+49 711/753375",
    "sg:postcode":"70771",
    "sg:province":"Baden-W\u00fcrttemberg",
    "wof:name":"Walter Schimpf Kunstmaler",
    "wof:placetype":"venue"
},
  "geometry": {"coordinates":[9.141254,48.695343],"type":"Point"}
}