{
  "type": "Feature",
  "properties": {
    "iso:country":"DE",
    "sg:address":"Im Trieb 40",
    "sg:city":"Ulm",
    "sg:phone":"+49 731/45140",
    "sg:postcode":"89079",
    "sg:province":"Baden-W\u00fcrttemberg",
    "wof:name":"R. Brandl",
    "wof:placetype":"venue"
},
  "geometry": {"coordinates":[9.9789571762,48.3553314209],"type":"Point"}
}