{
  "type": "Feature",
  "properties": {
    "iso:country":"DE",
    "sg:address":"Dom-Pedro-Str. 17",
    "sg:city":"M\u00fcnchen",
    "sg:phone":"+49 89/180061",
    "sg:postcode":"80637",
    "sg:province":"Bayern",
    "wof:name":"Bau Und Boden Gmbh & Co. Immobilien Kg",
    "wof:placetype":"venue"
},
  "geometry": {"coordinates":[11.5422353745,48.159488678],"type":"Point"}
}