{
  "type": "Feature",
  "properties": {
    "iso:country":"DE",
    "sg:address":"Hirschweg 15",
    "sg:city":"Lohr",
    "sg:postcode":"97816",
    "sg:province":"Bayern",
    "wof:name":"Sps Finanzierungs- Und Unternehmensberatungsges. Mbh",
    "wof:placetype":"venue"
},
  "geometry": {"coordinates":[9.573756218,50.0031890869],"type":"Point"}
}