{
  "type": "Feature",
  "properties": {
    "iso:country":"DE",
    "sg:address":"Poolstr. 32",
    "sg:city":"Hamburg",
    "sg:postcode":"20355",
    "sg:province":"Hamburg",
    "wof:name":"E. Ruffer Gmbh",
    "wof:placetype":"venue"
},
  "geometry": {"coordinates":[9.979641,53.554508],"type":"Point"}
}