{
  "type": "Feature",
  "properties": {
    "iso:country":"DE",
    "sg:address":"Obere Vorstadtstr. 4",
    "sg:city":"Walld\u00fcrn",
    "sg:phone":"+49 6282/7407",
    "sg:postcode":"74731",
    "sg:province":"Baden-W\u00fcrttemberg",
    "wof:name":"Foto Sommer",
    "wof:placetype":"venue"
},
  "geometry": {"coordinates":[9.3686609268,49.582359314],"type":"Point"}
}