{
  "type": "Feature",
  "properties": {
    "iso:country":"DE",
    "sg:city":"Ansbach",
    "sg:phone":"+49 981/2196",
    "sg:postcode":"91522",
    "sg:province":"Bayern",
    "wof:name":"Aqualit-quellsteine Bonsai- Und Lavabrunnen-centrum Gmbh",
    "wof:placetype":"venue"
},
  "geometry": {"coordinates":[10.572037,49.300686],"type":"Point"}
}