{
  "type": "Feature",
  "properties": {
    "iso:country":"DE",
    "sg:address":"Bert-Brecht-Str. 26",
    "sg:city":"Eching",
    "sg:postcode":"85386",
    "sg:province":"Bayern",
    "wof:name":"Lx Agency E. K.",
    "wof:placetype":"venue"
},
  "geometry": {"coordinates":[11.6231489182,48.3042030334],"type":"Point"}
}