{
  "type": "Feature",
  "properties": {
    "iso:country":"DE",
    "sg:address":"Salzstr. 6",
    "sg:city":"R\u00f6merstein",
    "sg:phone":"+49 7382/5491",
    "sg:postcode":"72587",
    "sg:province":"Baden-W\u00fcrttemberg",
    "wof:name":"Monashee Blockhaus",
    "wof:placetype":"venue"
},
  "geometry": {"coordinates":[9.5556373596,48.4828872681],"type":"Point"}
}