{
  "type": "Feature",
  "properties": {
    "iso:country":"DE",
    "sg:address":"Dorfstr. 6",
    "sg:city":"Alt Duvenstedt",
    "sg:phone":"+49 4338/325",
    "sg:postcode":"24791",
    "sg:province":"Schleswig-Holstein",
    "wof:name":"Hans-j\u00fcrgen Pahl",
    "wof:placetype":"venue"
},
  "geometry": {"coordinates":[9.6435861588,54.358379364],"type":"Point"}
}