{
  "type": "Feature",
  "properties": {
    "iso:country":"DE",
    "sg:address":"Im Spektefeld 32",
    "sg:city":"Berlin",
    "sg:phone":"+49 30/37401170",
    "sg:postcode":"13589",
    "sg:province":"Berlin",
    "wof:name":"Kaisers Kaffee-gesch\u00e4ft",
    "wof:placetype":"venue"
},
  "geometry": {"coordinates":[13.1566553116,52.5491294861],"type":"Point"}
}