{
  "type": "Feature",
  "properties": {
    "iso:country":"DE",
    "sg:address":"Brunnenstr. 25",
    "sg:city":"Pforzheim",
    "sg:phone":"+49 7231/467903",
    "sg:postcode":"75172",
    "sg:province":"Baden-W\u00fcrttemberg",
    "wof:name":"Bei Lore",
    "wof:placetype":"venue"
},
  "geometry": {"coordinates":[8.6720228195,48.889339447],"type":"Point"}
}