{
  "type": "Feature",
  "properties": {
    "iso:country":"DE",
    "sg:address":"Am Wallgraben 100",
    "sg:city":"Stuttgart",
    "sg:phone":"+49 711/78105",
    "sg:postcode":"70565",
    "sg:province":"Baden-W\u00fcrttemberg",
    "wof:name":"Dv-d Systempartner Gmbh",
    "wof:placetype":"venue"
},
  "geometry": {"coordinates":[9.1231565475,48.7259941101],"type":"Point"}
}