{
  "type": "Feature",
  "properties": {
    "iso:country":"DE",
    "sg:address":"Riedersteinweg 1",
    "sg:city":"Bad Wiessee",
    "sg:phone":"+49 8022/82187",
    "sg:postcode":"83707",
    "sg:province":"Bayern",
    "wof:name":"G\u00e4stehaus Bergsee",
    "wof:placetype":"venue"
},
  "geometry": {"coordinates":[11.7262372971,47.7166023254],"type":"Point"}
}