{
  "type": "Feature",
  "properties": {
    "iso:country":"DE",
    "sg:address":"Breite 7",
    "sg:city":"Kalletal",
    "sg:phone":"+49 5733/3661",
    "sg:postcode":"32689",
    "sg:province":"Nordrhein-Westfalen",
    "wof:name":"Friedrich-wilhelm Husemann",
    "wof:placetype":"venue"
},
  "geometry": {"coordinates":[8.9372768402,52.1796455383],"type":"Point"}
}