{
  "type": "Feature",
  "properties": {
    "iso:country":"DE",
    "sg:address":"Ellenbacher Str. 7",
    "sg:city":"F\u00fcrth",
    "sg:phone":"+49 6253/1619",
    "sg:postcode":"64658",
    "sg:province":"Hessen",
    "wof:name":"R.-i. Stemmle",
    "wof:placetype":"venue"
},
  "geometry": {"coordinates":[8.777955,49.650471],"type":"Point"}
}