{
  "type": "Feature",
  "properties": {
    "iso:country":"DE",
    "sg:address":"Erlochweg 2",
    "sg:city":"Babenhausen",
    "sg:phone":"+49 6073/63280",
    "sg:postcode":"64832",
    "sg:province":"Hessen",
    "wof:name":"Michael Daniel",
    "wof:placetype":"venue"
},
  "geometry": {"coordinates":[8.9414873123,49.9623146057],"type":"Point"}
}