{
  "type": "Feature",
  "properties": {
    "iso:country":"DE",
    "sg:address":"K\u00fcckhovener Str. 3a",
    "sg:city":"Erkelenz",
    "sg:phone":"+49 2435/653562",
    "sg:postcode":"41812",
    "sg:province":"Nordrhein-Westfalen",
    "wof:name":"G.-w. Kahlke Finanzberater",
    "wof:placetype":"venue"
},
  "geometry": {"coordinates":[6.3498492241,51.0394744873],"type":"Point"}
}