{
  "type": "Feature",
  "properties": {
    "iso:country":"DE",
    "sg:address":"Gr\u00fcnhufer Bogen 11 -14",
    "sg:city":"Stralsund",
    "sg:phone":"+49 3831/37640",
    "sg:postcode":"18437",
    "sg:province":"Mecklenburg-Vorpommern",
    "wof:name":"Strelapark Einkaufszentrum Verwaltungs Gmbh",
    "wof:placetype":"venue"
},
  "geometry": {"coordinates":[13.0489807129,54.3201026917],"type":"Point"}
}