{
  "type": "Feature",
  "properties": {
    "iso:country":"DE",
    "sg:address":"Ringstr. 1",
    "sg:city":"Sebnitz",
    "sg:phone":"+49 35971/53401",
    "sg:postcode":"01855",
    "sg:province":"Sachsen",
    "wof:name":"Birgit Grosser",
    "wof:placetype":"venue"
},
  "geometry": {"coordinates":[14.2668743134,50.9768943787],"type":"Point"}
}