{
  "type": "Feature",
  "properties": {
    "iso:country":"DE",
    "sg:city":"Kirchendemenreuth",
    "sg:postcode":"92665",
    "sg:province":"Bayern",
    "wof:name":"Islandpferde Reiter- Und Zuechterverein Oberpfalz Nord E.v.",
    "wof:placetype":"venue"
},
  "geometry": {"coordinates":[12.093077,49.777115],"type":"Point"}
}