{
  "type": "Feature",
  "properties": {
    "iso:country":"DE",
    "sg:address":"Hangstr. 18",
    "sg:city":"Gefrees",
    "sg:phone":"+49 9254/7415",
    "sg:postcode":"95482",
    "sg:province":"Bayern",
    "wof:name":"J. Benker",
    "wof:placetype":"venue"
},
  "geometry": {"coordinates":[11.7299394608,50.0879402161],"type":"Point"}
}