{
  "type": "Feature",
  "properties": {
    "iso:country":"DE",
    "sg:address":"Hinterm Horstberg 21",
    "sg:city":"Harmstorf",
    "sg:postcode":"21228",
    "sg:province":"Niedersachsen",
    "wof:name":"Post & Baginski Ohg",
    "wof:placetype":"venue"
},
  "geometry": {"coordinates":[9.9833402634,53.3447799683],"type":"Point"}
}