{
  "type": "Feature",
  "properties": {
    "iso:country":"DE",
    "sg:address":"Am Seewald 17",
    "sg:city":"Friedrichshafen",
    "sg:phone":"+49 7541/21160",
    "sg:postcode":"88046",
    "sg:province":"Baden-W\u00fcrttemberg",
    "wof:name":"P. Rieser",
    "wof:placetype":"venue"
},
  "geometry": {"coordinates":[9.504456,47.660126],"type":"Point"}
}