{
  "type": "Feature",
  "properties": {
    "iso:country":"DE",
    "sg:address":"Hintern Br\u00fcdern 1",
    "sg:city":"Braunschweig",
    "sg:phone":"+49 531/67851",
    "sg:postcode":"38100",
    "sg:province":"Niedersachsen",
    "wof:name":"Avak Versicherungs- Vermittlungs Gmbh",
    "wof:placetype":"venue"
},
  "geometry": {"coordinates":[10.5198383331,52.2656097412],"type":"Point"}
}