{
  "type": "Feature",
  "properties": {
    "iso:country":"DE",
    "sg:address":"Ludwigstr. 6 b",
    "sg:city":"Starnberg",
    "sg:phone":"+49 8151/2215",
    "sg:postcode":"82319",
    "sg:province":"Bayern",
    "wof:name":"Marlene Gatterer Reiseb\u00fcro",
    "wof:placetype":"venue"
},
  "geometry": {"coordinates":[11.3447036743,47.9985466003],"type":"Point"}
}