{
  "type": "Feature",
  "properties": {
    "iso:country":"DE",
    "sg:address":"St\u00f6rnhof",
    "sg:city":"Wiesenttal",
    "sg:phone":"+49 9196/261",
    "sg:postcode":"91346",
    "sg:province":"Bayern",
    "wof:name":"Konrad Hofmann",
    "wof:placetype":"venue"
},
  "geometry": {"coordinates":[11.21459198,49.8280334473],"type":"Point"}
}