{
  "type": "Feature",
  "properties": {
    "iso:country":"DE",
    "sg:address":"Bahnofstrasse 32",
    "sg:city":"Flacht",
    "sg:phone":"+49 4964/3295120",
    "sg:postcode":"65558",
    "sg:province":"Rheinland-Pfalz",
    "wof:name":"Rolf Greiner Bio Chemica Vertriebsges.",
    "wof:placetype":"venue"
},
  "geometry": {"coordinates":[8.05254,50.344219],"type":"Point"}
}