{
  "type": "Feature",
  "properties": {
    "iso:country":"DE",
    "sg:address":"Industriestr. 11-13",
    "sg:city":"Eltmann",
    "sg:phone":"+49 9522/7260",
    "sg:postcode":"97483",
    "sg:province":"Bayern",
    "wof:name":"G\u00fcnther Gleussner",
    "wof:placetype":"venue"
},
  "geometry": {"coordinates":[10.6685838699,49.9808273315],"type":"Point"}
}