{
  "type": "Feature",
  "properties": {
    "iso:country":"DE",
    "sg:address":"Malkeser Str. 18",
    "sg:city":"Fulda",
    "sg:phone":"+49 661/241765",
    "sg:postcode":"36041",
    "sg:province":"Hessen",
    "wof:name":"Trausch Verwaltungs- Gmbh",
    "wof:placetype":"venue"
},
  "geometry": {"coordinates":[9.5846376419,50.5551719666],"type":"Point"}
}