{
  "type": "Feature",
  "properties": {
    "iso:country":"DE",
    "sg:address":"Hauptstr. 5 a",
    "sg:city":"Neckargerach",
    "sg:phone":"+49 6263/8271",
    "sg:postcode":"69437",
    "sg:province":"Baden-W\u00fcrttemberg",
    "wof:name":"Friedrich Sch\u00e4fer",
    "wof:placetype":"venue"
},
  "geometry": {"coordinates":[9.069004,49.40097],"type":"Point"}
}