{
  "type": "Feature",
  "properties": {
    "iso:country":"DE",
    "sg:address":"Wilder-Mann-Str. 47",
    "sg:city":"Dresden",
    "sg:phone":"+49 351/429010",
    "sg:postcode":"01129",
    "sg:province":"Sachsen",
    "wof:name":"Intec Geb\u00e4udemanagement Gmbh",
    "wof:placetype":"venue"
},
  "geometry": {"coordinates":[13.7176675797,51.0950508118],"type":"Point"}
}