{
  "type": "Feature",
  "properties": {
    "iso:country":"DE",
    "sg:address":"Justus-Liebig-Str. 1",
    "sg:city":"Mainz",
    "sg:phone":"+49 6131/592021",
    "sg:postcode":"55129",
    "sg:province":"Rheinland-Pfalz",
    "wof:name":"Lavahum Ges. F. Baustoffe Im Garten- Und Landschaftsb. Mbh",
    "wof:placetype":"venue"
},
  "geometry": {"coordinates":[8.266114,49.96917],"type":"Point"}
}