{
  "type": "Feature",
  "properties": {
    "iso:country":"DE",
    "sg:address":"Am Triesch 30",
    "sg:city":"Frielendorf",
    "sg:phone":"+49 5684/7749",
    "sg:postcode":"34621",
    "sg:province":"Hessen",
    "wof:name":"Freibad Frielendorf Gemeinde",
    "wof:placetype":"venue"
},
  "geometry": {"coordinates":[9.3279037476,50.9701652527],"type":"Point"}
}