{
  "type": "Feature",
  "properties": {
    "iso:country":"DE",
    "sg:address":"Fichtenstr. 15",
    "sg:city":"Brunnthal",
    "sg:phone":"+49 8104/9860",
    "sg:postcode":"85649",
    "sg:province":"Bayern",
    "wof:name":"Josef Weiss Plastic Gmbh",
    "wof:placetype":"venue"
},
  "geometry": {"coordinates":[11.705093,47.985607],"type":"Point"}
}