{
  "type": "Feature",
  "properties": {
    "iso:country":"DE",
    "sg:address":"Birlenbacher Str. 13",
    "sg:city":"Fachingen",
    "sg:phone":"+49 6432/989985",
    "sg:postcode":"65626",
    "sg:province":"Rheinland-Pfalz",
    "wof:name":"G. Schwarz Immobilienmakler",
    "wof:placetype":"venue"
},
  "geometry": {"coordinates":[7.996201992,50.3612174988],"type":"Point"}
}