{
  "type": "Feature",
  "properties": {
    "iso:country":"DE",
    "sg:address":"Schildfarnweg 10a",
    "sg:city":"Stuttgart",
    "sg:postcode":"70619",
    "sg:province":"Baden-W\u00fcrttemberg",
    "wof:name":"Contitec Maschinenbau Gmbh",
    "wof:placetype":"venue"
},
  "geometry": {"coordinates":[9.243139,48.751247],"type":"Point"}
}