{
  "type": "Feature",
  "properties": {
    "iso:country":"DE",
    "sg:address":"Schmelzh\u00fcttenstr. 15",
    "sg:city":"Gera",
    "sg:phone":"+49 365/8001091",
    "sg:postcode":"07545",
    "sg:province":"Th\u00fcringen",
    "wof:name":"Lorenz & Co. Fenster- Und Raum-design Ohg",
    "wof:placetype":"venue"
},
  "geometry": {"coordinates":[12.080696,50.872543],"type":"Point"}
}