{
  "type": "Feature",
  "properties": {
    "iso:country":"DE",
    "sg:address":"Heidemannstr. 101",
    "sg:city":"K\u00f6ln",
    "sg:phone":"+49 221/5503242",
    "sg:postcode":"50825",
    "sg:province":"Nordrhein-Westfalen",
    "wof:name":"Schiffer-schlag-rosenbaum Zahntechnisches",
    "wof:placetype":"venue"
},
  "geometry": {"coordinates":[6.9196848869,50.9613494873],"type":"Point"}
}