{
  "type": "Feature",
  "properties": {
    "iso:country":"DE",
    "sg:address":"Villering",
    "sg:city":"H\u00fcrth",
    "sg:postcode":"50354",
    "sg:province":"Nordrhein-Westfalen",
    "wof:name":"Autobahnrastst\u00e4tte Ville West",
    "wof:placetype":"venue"
},
  "geometry": {"coordinates":[6.8720049858,50.8814811707],"type":"Point"}
}