{
  "type": "Feature",
  "properties": {
    "iso:country":"DE",
    "sg:address":"Friedrich-Herschel-Str. 3",
    "sg:city":"M\u00fcnchen",
    "sg:phone":"+49 89/988893",
    "sg:postcode":"81679",
    "sg:province":"Bayern",
    "wof:name":"Werner Janda Fotograf",
    "wof:placetype":"venue"
},
  "geometry": {"coordinates":[11.6027421951,48.1433677673],"type":"Point"}
}