{
  "type": "Feature",
  "properties": {
    "iso:country":"DE",
    "sg:address":"Wohldstr. 8",
    "sg:city":"Quakenbr\u00fcck",
    "sg:phone":"+49 5431/94130",
    "sg:postcode":"49610",
    "sg:province":"Niedersachsen",
    "wof:name":"Wirtschaftsbund Gmbh",
    "wof:placetype":"venue"
},
  "geometry": {"coordinates":[7.9624648094,52.6806182861],"type":"Point"}
}