{
  "type": "Feature",
  "properties": {
    "iso:country":"DE",
    "sg:address":"Bergstr. 31",
    "sg:city":"Dresden",
    "sg:phone":"+49 351/3105553",
    "sg:postcode":"01069",
    "sg:province":"Sachsen",
    "wof:name":"Gebit Edv- Unternehmens- Beratung Gmbh",
    "wof:placetype":"venue"
},
  "geometry": {"coordinates":[13.7296981812,51.0348358154],"type":"Point"}
}