{
  "type": "Feature",
  "properties": {
    "iso:country":"DE",
    "sg:address":"Michelangelostr. 1",
    "sg:city":"Dresden",
    "sg:phone":"+49 351/4370820",
    "sg:postcode":"01217",
    "sg:province":"Sachsen",
    "wof:name":"Gesop Ggmbh",
    "wof:placetype":"venue"
},
  "geometry": {"coordinates":[13.744568,51.02261],"type":"Point"}
}