{
  "type": "Feature",
  "properties": {
    "iso:country":"DE",
    "sg:address":"Kr\u00e4merbank 11",
    "sg:city":"Dortmund",
    "sg:phone":"+49 231/750516",
    "sg:postcode":"44227",
    "sg:province":"Nordrhein-Westfalen",
    "wof:name":"I. Pochanke",
    "wof:placetype":"venue"
},
  "geometry": {"coordinates":[7.423306942,51.472366333],"type":"Point"}
}