{
  "type": "Feature",
  "properties": {
    "iso:country":"DE",
    "sg:address":"Hauptstr. 14",
    "sg:city":"Kirchheim",
    "sg:phone":"+49 89/9915650",
    "sg:postcode":"85551",
    "sg:province":"Bayern",
    "wof:name":"Hotel Eschenhof",
    "wof:placetype":"venue"
},
  "geometry": {"coordinates":[9.5755319595,50.8365135193],"type":"Point"}
}