{
  "type": "Feature",
  "properties": {
    "iso:country":"DE",
    "sg:address":"Selterser Str. 23",
    "sg:city":"Weilburg",
    "sg:phone":"+49 6471/7279",
    "sg:postcode":"35781",
    "sg:province":"Hessen",
    "wof:name":"Heinz Ketter",
    "wof:placetype":"venue"
},
  "geometry": {"coordinates":[8.270489,50.498444],"type":"Point"}
}