{
  "type": "Feature",
  "properties": {
    "iso:country":"DE",
    "sg:address":"Berliner Damm 2c",
    "sg:city":"Ellerau",
    "sg:phone":"+49 4106/74471",
    "sg:postcode":"25479",
    "sg:province":"Schleswig-Holstein",
    "wof:name":"G. Riedemann",
    "wof:placetype":"venue"
},
  "geometry": {"coordinates":[9.918779,53.74992],"type":"Point"}
}