{
  "type": "Feature",
  "properties": {
    "iso:country":"DE",
    "sg:address":"Krummenort",
    "sg:city":"Alt Duvenstedt",
    "sg:postcode":"24791",
    "sg:province":"Schleswig-Holstein",
    "wof:name":"R. Bertram",
    "wof:placetype":"venue"
},
  "geometry": {"coordinates":[9.579925,54.348686],"type":"Point"}
}