{
  "type": "Feature",
  "properties": {
    "iso:country":"DE",
    "sg:address":"Lindenstr. 2",
    "sg:city":"Pfaffenhofen",
    "sg:phone":"+49 7046/911030",
    "sg:postcode":"74397",
    "sg:province":"Baden-W\u00fcrttemberg",
    "wof:name":"Ulrich Schl\u00f6sser Marktaus- Stattung Und Promotion Gmbh",
    "wof:placetype":"venue"
},
  "geometry": {"coordinates":[8.9495754242,49.0578384399],"type":"Point"}
}