{
  "type": "Feature",
  "properties": {
    "iso:country":"DE",
    "sg:address":"Bergweg 5",
    "sg:city":"Alfdorf",
    "sg:phone":"+49 7171/74209",
    "sg:postcode":"73553",
    "sg:province":"Baden-W\u00fcrttemberg",
    "wof:name":"H. Seybold Versicherungsvertreter",
    "wof:placetype":"venue"
},
  "geometry": {"coordinates":[9.7580528259,48.8444633484],"type":"Point"}
}