{
  "type": "Feature",
  "properties": {
    "iso:country":"DE",
    "sg:address":"Westerwaldstr. 6",
    "sg:city":"Sankt Augustin",
    "sg:phone":"+49 2241/34070",
    "sg:postcode":"53757",
    "sg:province":"Nordrhein-Westfalen",
    "wof:name":"Bundesverband Des Schornsteinfegerhandwerks",
    "wof:placetype":"venue"
},
  "geometry": {"coordinates":[7.1729068756,50.7576942444],"type":"Point"}
}