{
  "type": "Feature",
  "properties": {
    "iso:country":"DE",
    "sg:address":"Regierungsplatz 567",
    "sg:city":"Landshut",
    "sg:phone":"+49 871/23106",
    "sg:postcode":"84028",
    "sg:province":"Bayern",
    "wof:name":"Zirngibl",
    "wof:placetype":"venue"
},
  "geometry": {"coordinates":[12.1557579041,48.5367393494],"type":"Point"}
}