{
  "type": "Feature",
  "properties": {
    "iso:country":"DE",
    "sg:address":"Westring 431",
    "sg:city":"Kiel",
    "sg:phone":"+49 431/88180",
    "sg:postcode":"24118",
    "sg:province":"Schleswig-Holstein",
    "wof:name":"Hagenuk Automotive Gmbh",
    "wof:placetype":"venue"
},
  "geometry": {"coordinates":[10.1260671616,54.3407745361],"type":"Point"}
}