{
  "type": "Feature",
  "properties": {
    "iso:country":"DE",
    "sg:address":"Cosimastr. 4",
    "sg:city":"M\u00fcnchen",
    "sg:phone":"+49 89/911564",
    "sg:postcode":"81927",
    "sg:province":"Bayern",
    "wof:name":"Cosima Apotheke Inh. Johanna Schaller E. K.",
    "wof:placetype":"venue"
},
  "geometry": {"coordinates":[11.629961,48.154713],"type":"Point"}
}