{
  "type": "Feature",
  "properties": {
    "iso:country":"DE",
    "sg:address":"Minkelsches Feld 41",
    "sg:city":"Hamminkeln",
    "sg:phone":"+49 2852",
    "sg:postcode":"46499",
    "sg:province":"Nordrhein-Westfalen",
    "wof:name":"Automobile-huebers",
    "wof:placetype":"venue"
},
  "geometry": {"coordinates":[6.5869131088,51.734413147],"type":"Point"}
}