{
  "type": "Feature",
  "properties": {
    "iso:country":"DE",
    "sg:address":"Max-Hamerich-Str 2a",
    "sg:city":"Stockelsdorf",
    "sg:phone":"+49 451/4988240",
    "sg:postcode":"23617",
    "sg:province":"Schleswig-Holstein",
    "wof:name":"Sun Protect Michael Matthias",
    "wof:placetype":"venue"
},
  "geometry": {"coordinates":[10.6410741806,53.8840942383],"type":"Point"}
}