{
  "type": "Feature",
  "properties": {
    "iso:country":"DE",
    "sg:address":"Obernh\u00e4user Str. 27",
    "sg:city":"Birkenfeld",
    "sg:phone":"+49 7082/414833",
    "sg:postcode":"75217",
    "sg:province":"Baden-W\u00fcrttemberg",
    "wof:name":"I & B Haustechnik Gmbh",
    "wof:placetype":"venue"
},
  "geometry": {"coordinates":[8.5932188034,48.870174408],"type":"Point"}
}