{
  "type": "Feature",
  "properties": {
    "iso:country":"DE",
    "sg:address":"Hansastra\u00dfe 2",
    "sg:city":"Schwabach",
    "sg:postcode":"91126",
    "sg:province":"Bayern",
    "wof:name":"Deuerlein Gmbh",
    "wof:placetype":"venue"
},
  "geometry": {"coordinates":[11.0582113266,49.3212547302],"type":"Point"}
}