{
  "type": "Feature",
  "properties": {
    "iso:country":"DE",
    "sg:address":"Hospitalstr. 11",
    "sg:city":"Limburg",
    "sg:phone":"+49 6431/27994",
    "sg:postcode":"65549",
    "sg:province":"Hessen",
    "wof:name":"Siegfried Schauenburg Zahnarzt",
    "wof:placetype":"venue"
},
  "geometry": {"coordinates":[8.0626096725,50.3864707947],"type":"Point"}
}