{
  "type": "Feature",
  "properties": {
    "iso:country":"DE",
    "sg:address":"Schwaighofstr. 97",
    "sg:city":"Tegernsee",
    "sg:phone":"+49 8022/26207",
    "sg:postcode":"83684",
    "sg:province":"Bayern",
    "wof:name":"Mathias B\u00f6hnke Gmbh",
    "wof:placetype":"venue"
},
  "geometry": {"coordinates":[11.771884,47.693871],"type":"Point"}
}