{
  "type": "Feature",
  "properties": {
    "iso:country":"DE",
    "sg:address":"Trierer Str. 28",
    "sg:city":"Zerf",
    "sg:phone":"+49 6587/288",
    "sg:postcode":"54314",
    "sg:province":"Rheinland-Pfalz",
    "wof:name":"Paul Merz",
    "wof:placetype":"venue"
},
  "geometry": {"coordinates":[6.689808,49.60107],"type":"Point"}
}