{
  "type": "Feature",
  "properties": {
    "iso:country":"DE",
    "sg:address":"Seiferstetterstr. 15",
    "sg:city":"Landsberg",
    "sg:phone":"+49 8191/46303",
    "sg:postcode":"86899",
    "sg:province":"Bayern",
    "wof:name":"Stahl",
    "wof:placetype":"venue"
},
  "geometry": {"coordinates":[10.8829336166,48.0083274841],"type":"Point"}
}