{
  "type": "Feature",
  "properties": {
    "iso:country":"DE",
    "sg:address":"Hubertusweg 18",
    "sg:city":"Stuttgart",
    "sg:phone":"+49 711/861022",
    "sg:postcode":"70499",
    "sg:province":"Baden-W\u00fcrttemberg",
    "wof:name":"Erwin Zwicker",
    "wof:placetype":"venue"
},
  "geometry": {"coordinates":[9.108694,48.806152],"type":"Point"}
}