{
  "type": "Feature",
  "properties": {
    "iso:country":"DE",
    "sg:address":"Hattinger Str. 198",
    "sg:city":"Schwelm",
    "sg:phone":"+49 2339/2651",
    "sg:postcode":"58332",
    "sg:province":"Nordrhein-Westfalen",
    "wof:name":"Max Baumann",
    "wof:placetype":"venue"
},
  "geometry": {"coordinates":[7.279812,51.311745],"type":"Point"}
}