{
  "type": "Feature",
  "properties": {
    "iso:country":"DE",
    "sg:address":"Theta 1",
    "sg:city":"Bindlach",
    "sg:phone":"+49 9208/8452",
    "sg:postcode":"95463",
    "sg:province":"Bayern",
    "wof:name":"Bruno Depser Omnibusbetrieb",
    "wof:placetype":"venue"
},
  "geometry": {"coordinates":[11.548579216,49.9888000488],"type":"Point"}
}