{
  "type": "Feature",
  "properties": {
    "iso:country":"DE",
    "sg:address":"Metzgerstr. 18",
    "sg:city":"Reutlingen",
    "sg:phone":"+49 7121/334269",
    "sg:postcode":"72764",
    "sg:province":"Baden-W\u00fcrttemberg",
    "wof:name":"Restaurant China-thai-wok",
    "wof:placetype":"venue"
},
  "geometry": {"coordinates":[9.2110729218,48.4937362671],"type":"Point"}
}