{
  "type": "Feature",
  "properties": {
    "iso:country":"DE",
    "sg:address":"Philipp-Reis-Str. 1 - 3",
    "sg:city":"K\u00fcnzell",
    "sg:phone":"+49 661/934220",
    "sg:postcode":"36093",
    "sg:province":"Hessen",
    "wof:name":"Prodhag Kg Inh. E. Bodenr\u00fcder",
    "wof:placetype":"venue"
},
  "geometry": {"coordinates":[9.7177877426,50.5353660583],"type":"Point"}
}