{
  "type": "Feature",
  "properties": {
    "iso:country":"DE",
    "sg:address":"K\u00fcchengartenweg 8",
    "sg:city":"Butzbach",
    "sg:phone":"+49 6033/9880",
    "sg:postcode":"35510",
    "sg:province":"Hessen",
    "wof:name":"Druckerei Und Verlag Otto Lembeck Kg",
    "wof:placetype":"venue"
},
  "geometry": {"coordinates":[8.6737909317,50.435634613],"type":"Point"}
}