{
  "type": "Feature",
  "properties": {
    "iso:country":"DE",
    "sg:address":"Schlo\u00dfstr. 15 D",
    "sg:city":"L\u00f6rrach",
    "sg:phone":"+49 7621/56838",
    "sg:postcode":"79541",
    "sg:province":"Baden-W\u00fcrttemberg",
    "wof:name":"Beate Greven",
    "wof:placetype":"venue"
},
  "geometry": {"coordinates":[7.6796159744,47.6381263733],"type":"Point"}
}