{
  "type": "Feature",
  "properties": {
    "iso:country":"DE",
    "sg:address":"Landshuter Str. 33",
    "sg:city":"Regensburg",
    "sg:phone":"+49 941/7082140",
    "sg:postcode":"93053",
    "sg:province":"Bayern",
    "wof:name":"Universa Lebensversicherung Ag",
    "wof:placetype":"venue"
},
  "geometry": {"coordinates":[12.1104927063,49.0114936829],"type":"Point"}
}