{
  "type": "Feature",
  "properties": {
    "iso:country":"DE",
    "sg:address":"L\u00fcbecker Str. 104",
    "sg:city":"Magdeburg",
    "sg:postcode":"39124",
    "sg:province":"Sachsen-Anhalt",
    "wof:name":"Verwaltungsges. Magdeburg Crucigerstra\u00dfe 24 Mbh",
    "wof:placetype":"venue"
},
  "geometry": {"coordinates":[11.635933876,52.158744812],"type":"Point"}
}