{
  "type": "Feature",
  "properties": {
    "iso:country":"DE",
    "sg:address":"Im Brander Feld 2",
    "sg:city":"Aachen",
    "sg:phone":"+49 241/563613",
    "sg:postcode":"52078",
    "sg:province":"Nordrhein-Westfalen",
    "wof:name":"Blumen Sch\u00e4fer Gmbh",
    "wof:placetype":"venue"
},
  "geometry": {"coordinates":[6.158597,50.74514],"type":"Point"}
}