{
  "type": "Feature",
  "properties": {
    "iso:country":"DE",
    "sg:address":"Pentruper Str. 39",
    "sg:city":"Greven",
    "sg:phone":"+49 2571/40896",
    "sg:postcode":"48268",
    "sg:province":"Nordrhein-Westfalen",
    "wof:name":"Suwelack Kg",
    "wof:placetype":"venue"
},
  "geometry": {"coordinates":[7.642223835,52.1400032043],"type":"Point"}
}