{
  "type": "Feature",
  "properties": {
    "iso:country":"DE",
    "sg:address":"Peiner Str. 151-155",
    "sg:city":"Salzgitter",
    "sg:phone":"+49 4953/4186770",
    "sg:postcode":"38229",
    "sg:province":"Niedersachsen",
    "wof:name":"Magna International Stanztechnik Gmbh",
    "wof:placetype":"venue"
},
  "geometry": {"coordinates":[10.3531141281,52.1633148193],"type":"Point"}
}