{
  "type": "Feature",
  "properties": {
    "iso:country":"DE",
    "sg:address":"Hauptstr. 19",
    "sg:city":"Steffenberg",
    "sg:phone":"+49 6464/7315",
    "sg:postcode":"35239",
    "sg:province":"Hessen",
    "wof:name":"Heini B\u00e4cker",
    "wof:placetype":"venue"
},
  "geometry": {"coordinates":[8.425693,50.838058],"type":"Point"}
}