{
  "type": "Feature",
  "properties": {
    "iso:country":"DE",
    "sg:address":"Gro\u00dfe Fischergasse 21",
    "sg:city":"Nierstein",
    "sg:phone":"+49 6133/5505",
    "sg:postcode":"55283",
    "sg:province":"Rheinland-Pfalz",
    "wof:name":"Raiffeisen",
    "wof:placetype":"venue"
},
  "geometry": {"coordinates":[8.340403,49.873383],"type":"Point"}
}