{
  "type": "Feature",
  "properties": {
    "iso:country":"DE",
    "sg:address":"Hansastr. 235",
    "sg:city":"Berlin",
    "sg:phone":"+49 30/9626262",
    "sg:postcode":"13051",
    "sg:province":"Berlin",
    "wof:name":"Trans-bwg- Gmbh",
    "wof:placetype":"venue"
},
  "geometry": {"coordinates":[13.4976062775,52.5608673096],"type":"Point"}
}