{
  "type": "Feature",
  "properties": {
    "iso:country":"DE",
    "sg:address":"Dresdner Str. 13",
    "sg:city":"Freital",
    "sg:phone":"+49 2191/31100",
    "sg:postcode":"01705",
    "sg:province":"Sachsen",
    "wof:name":"Hanns-d. Berger Architekt",
    "wof:placetype":"venue"
},
  "geometry": {"coordinates":[13.659266,51.029152],"type":"Point"}
}