{
  "type": "Feature",
  "properties": {
    "iso:country":"DE",
    "sg:address":"Eifelstr. 12",
    "sg:city":"K\u00f6ln",
    "sg:phone":"+49 221/315282",
    "sg:postcode":"50677",
    "sg:province":"Nordrhein-Westfalen",
    "wof:name":"Western Wave Line",
    "wof:placetype":"venue"
},
  "geometry": {"coordinates":[6.945435,50.925278],"type":"Point"}
}