{
  "type": "Feature",
  "properties": {
    "iso:country":"DE",
    "sg:address":"Kemnade 11",
    "sg:city":"Gevelsberg",
    "sg:phone":"+49 2332/55800",
    "sg:postcode":"58285",
    "sg:province":"Nordrhein-Westfalen",
    "wof:name":"Albert Hillringhaus Kg",
    "wof:placetype":"venue"
},
  "geometry": {"coordinates":[7.3298177719,51.3628616333],"type":"Point"}
}