{
  "type": "Feature",
  "properties": {
    "iso:country":"DE",
    "sg:address":"Prisdorfer Str. 6",
    "sg:city":"Berlin",
    "sg:phone":"+49 30/3663540",
    "sg:postcode":"13581",
    "sg:province":"Berlin",
    "wof:name":"Fred Scheunert",
    "wof:placetype":"venue"
},
  "geometry": {"coordinates":[13.165292,52.5341],"type":"Point"}
}