{
  "type": "Feature",
  "properties": {
    "iso:country":"DE",
    "sg:address":"Rosa-Luxemburg-Ring",
    "sg:city":"Dranske",
    "sg:phone":"+49 38391/8464",
    "sg:postcode":"18556",
    "sg:province":"Mecklenburg-Vorpommern",
    "wof:name":"Imbi\u00df R. Rosner",
    "wof:placetype":"venue"
},
  "geometry": {"coordinates":[13.230966568,54.6329193115],"type":"Point"}
}