{
  "type": "Feature",
  "properties": {
    "iso:country":"DE",
    "sg:address":"Aroser Allee 81",
    "sg:city":"Berlin",
    "sg:phone":"+49 30/4551172",
    "sg:postcode":"13407",
    "sg:province":"Berlin",
    "wof:name":"L & P Verwaltungs Und Beteiligungs Gmbh",
    "wof:placetype":"venue"
},
  "geometry": {"coordinates":[13.35264,52.563766],"type":"Point"}
}