{
  "type": "Feature",
  "properties": {
    "iso:country":"DE",
    "sg:address":"Ansbacher Str. 2",
    "sg:city":"Zirndorf",
    "sg:postcode":"90513",
    "sg:province":"Bayern",
    "wof:name":"Speedster Versandhandel",
    "wof:placetype":"venue"
},
  "geometry": {"coordinates":[10.9207191467,49.427986145],"type":"Point"}
}