{
  "type": "Feature",
  "properties": {
    "iso:country":"DE",
    "sg:address":"Bergstr. 1",
    "sg:city":"Vorderweidenthal",
    "sg:phone":"+49 6398/363",
    "sg:postcode":"76889",
    "sg:province":"Rheinland-Pfalz",
    "wof:name":"E. Ettel & Sohn Bauschlosserei",
    "wof:placetype":"venue"
},
  "geometry": {"coordinates":[7.8795499802,49.1274642944],"type":"Point"}
}