{
  "type": "Feature",
  "properties": {
    "iso:country":"DE",
    "sg:address":"Schulstr. 26",
    "sg:city":"Bad Emstal",
    "sg:phone":"+49 5624/6900",
    "sg:postcode":"34308",
    "sg:province":"Hessen",
    "wof:name":"Udo F\u00f6lsch Steuerbevollm\u00e4chtigter",
    "wof:placetype":"venue"
},
  "geometry": {"coordinates":[9.259847641,51.2471237183],"type":"Point"}
}