{
  "type": "Feature",
  "properties": {
    "iso:country":"DE",
    "sg:address":"Graudenzer Linie 51",
    "sg:city":"Mannheim",
    "sg:phone":"+49 621/773114",
    "sg:postcode":"68307",
    "sg:province":"Baden-W\u00fcrttemberg",
    "wof:name":"Kurt Rieth",
    "wof:placetype":"venue"
},
  "geometry": {"coordinates":[8.4739837646,49.539100647],"type":"Point"}
}