{
  "type": "Feature",
  "properties": {
    "iso:country":"DE",
    "sg:address":"Im Haag 2",
    "sg:city":"Losheim",
    "sg:phone":"+49 6872/4188",
    "sg:postcode":"66679",
    "sg:province":"Saarland",
    "wof:name":"R. Sch\u00e4fer",
    "wof:placetype":"venue"
},
  "geometry": {"coordinates":[6.752461,49.509129],"type":"Point"}
}