{
  "type": "Feature",
  "properties": {
    "iso:country":"DE",
    "sg:address":"K\u00f6nigsreihe 53",
    "sg:city":"Hamburg",
    "sg:postcode":"22041",
    "sg:province":"Hamburg",
    "wof:name":"Schnabel Media E. Kfr.",
    "wof:placetype":"venue"
},
  "geometry": {"coordinates":[10.065507,53.574699],"type":"Point"}
}