{
  "type": "Feature",
  "properties": {
    "iso:country":"DE",
    "sg:address":"Ziegelfeldstr. 24",
    "sg:city":"M\u00f6gglingen",
    "sg:phone":"+49 7174/295",
    "sg:postcode":"73563",
    "sg:province":"Baden-W\u00fcrttemberg",
    "wof:name":"K\u00fchn-plast Gesellschaft Mbh",
    "wof:placetype":"venue"
},
  "geometry": {"coordinates":[9.968176,48.82201],"type":"Point"}
}