{
  "type": "Feature",
  "properties": {
    "iso:country":"DE",
    "sg:address":"Alte Poststr. 6",
    "sg:city":"Dornum",
    "sg:phone":"+49 4933/428",
    "sg:postcode":"26553",
    "sg:province":"Niedersachsen",
    "wof:name":"Sparkasse Norden",
    "wof:placetype":"venue"
},
  "geometry": {"coordinates":[7.430485,53.646946],"type":"Point"}
}