{
  "type": "Feature",
  "properties": {
    "iso:country":"DE",
    "sg:address":"Gerstau 19",
    "sg:city":"Remscheid",
    "sg:phone":"+49 2191/81548",
    "sg:postcode":"42857",
    "sg:province":"Nordrhein-Westfalen",
    "wof:name":"Heinz-g\u00fcnter Simon",
    "wof:placetype":"venue"
},
  "geometry": {"coordinates":[7.15814,51.199921],"type":"Point"}
}