{
  "type": "Feature",
  "properties": {
    "iso:country":"DE",
    "sg:address":"Burgdorfer Str. 19-21",
    "sg:city":"Lehrte",
    "sg:phone":"+49 5132/4015",
    "sg:postcode":"31275",
    "sg:province":"Niedersachsen",
    "wof:name":"Praxis Dr. Med. Mansouri",
    "wof:placetype":"venue"
},
  "geometry": {"coordinates":[9.9758329391,52.3776817322],"type":"Point"}
}