{
  "type": "Feature",
  "properties": {
    "iso:country":"DE",
    "sg:address":"Wiebach 26",
    "sg:city":"Paderborn",
    "sg:postcode":"33100",
    "sg:province":"Nordrhein-Westfalen",
    "wof:name":"L\u00f6dige Internationale Beteiligungen Gmbh",
    "wof:placetype":"venue"
},
  "geometry": {"coordinates":[8.841483,51.749603],"type":"Point"}
}