{
  "type": "Feature",
  "properties": {
    "iso:country":"DE",
    "sg:address":"Gehsbergweg 5",
    "sg:city":"K\u00f6tzting",
    "sg:phone":"+49 9941/8416",
    "sg:postcode":"93444",
    "sg:province":"Bayern",
    "wof:name":"Hermann Costa",
    "wof:placetype":"venue"
},
  "geometry": {"coordinates":[12.8448228836,49.1721801758],"type":"Point"}
}