{
  "type": "Feature",
  "properties": {
    "iso:country":"DE",
    "sg:address":"M\u00fchlenstr. 27",
    "sg:city":"Bremen",
    "sg:phone":"+49 421/6009384",
    "sg:postcode":"28779",
    "sg:province":"Bremen",
    "wof:name":"Cactus Modehandel Gmbh",
    "wof:placetype":"venue"
},
  "geometry": {"coordinates":[8.572231,53.183804],"type":"Point"}
}