{
  "type": "Feature",
  "properties": {
    "iso:country":"DE",
    "sg:address":"Gr\u00fcnwalder Str. 106",
    "sg:city":"M\u00fcnchen",
    "sg:phone":"+49 89/4802921",
    "sg:postcode":"81547",
    "sg:province":"Bayern",
    "wof:name":"Heinzen",
    "wof:placetype":"venue"
},
  "geometry": {"coordinates":[11.56711483,48.1017951965],"type":"Point"}
}