{
  "type": "Feature",
  "properties": {
    "iso:country":"DE",
    "sg:address":"Hohenzollernring 88",
    "sg:city":"K\u00f6ln",
    "sg:phone":"+49 221/9130266",
    "sg:postcode":"50672",
    "sg:province":"Nordrhein-Westfalen",
    "wof:name":"Engler Edelhoff Und Horsten Rechtsanw\u00e4lte",
    "wof:placetype":"venue"
},
  "geometry": {"coordinates":[6.9405341148,50.9419631958],"type":"Point"}
}