{
  "type": "Feature",
  "properties": {
    "iso:country":"DE",
    "sg:address":"Lange Str. 80",
    "sg:city":"M\u00fcnsingen",
    "sg:phone":"+49 7383/539",
    "sg:postcode":"72525",
    "sg:province":"Baden-W\u00fcrttemberg",
    "wof:name":"Rauscher Berufsbekleidung Gmbh",
    "wof:placetype":"venue"
},
  "geometry": {"coordinates":[9.499268,48.375111],"type":"Point"}
}