{
  "type": "Feature",
  "properties": {
    "iso:country":"DE",
    "sg:address":"T\u00fcbinger Str. 8",
    "sg:city":"Kusterdingen",
    "sg:phone":"+49 7071/31900",
    "sg:postcode":"72127",
    "sg:province":"Baden-W\u00fcrttemberg",
    "wof:name":"Pizzeria Aetna",
    "wof:placetype":"venue"
},
  "geometry": {"coordinates":[9.120891571,48.5199317932],"type":"Point"}
}