{
  "type": "Feature",
  "properties": {
    "iso:country":"DE",
    "sg:address":"Neukirchener Str. 26",
    "sg:city":"Neuss",
    "sg:phone":"+49 2137/7171",
    "sg:postcode":"41470",
    "sg:province":"Nordrhein-Westfalen",
    "wof:name":"J\u00fcrgen Frank Masseur",
    "wof:placetype":"venue"
},
  "geometry": {"coordinates":[6.727572,51.125458],"type":"Point"}
}