{
  "type": "Feature",
  "properties": {
    "iso:country":"DE",
    "sg:address":"Sontumer Str. 71",
    "sg:city":"Velbert",
    "sg:phone":"+49 2051/2060",
    "sg:postcode":"42551",
    "sg:province":"Nordrhein-Westfalen",
    "wof:name":"R. Woeste Gmbh & Co. Kg",
    "wof:placetype":"venue"
},
  "geometry": {"coordinates":[7.057298,51.330688],"type":"Point"}
}