{
  "type": "Feature",
  "properties": {
    "iso:country":"DE",
    "sg:address":"Sophienstr. 1",
    "sg:city":"Kirchlinteln",
    "sg:phone":"+49 4231/64369",
    "sg:postcode":"27308",
    "sg:province":"Niedersachsen",
    "wof:name":"Johannes Meyer",
    "wof:placetype":"venue"
},
  "geometry": {"coordinates":[9.299035,52.896935],"type":"Point"}
}