{
  "type": "Feature",
  "properties": {
    "iso:country":"DE",
    "sg:address":"Hauptstr. 56",
    "sg:city":"Werlte",
    "sg:postcode":"49757",
    "sg:province":"Niedersachsen",
    "wof:name":"Diy-fachmarkt Fritz Finke Gmbh & Co. Kg",
    "wof:placetype":"venue"
},
  "geometry": {"coordinates":[7.6820311546,52.8511390686],"type":"Point"}
}