{
  "type": "Feature",
  "properties": {
    "iso:country":"DE",
    "sg:address":"Ortsstr. 31",
    "sg:city":"Pfakofen",
    "sg:phone":"+49 9451/3066",
    "sg:postcode":"93101",
    "sg:province":"Bayern",
    "wof:name":"Josef Und Robert Zink Gmbh",
    "wof:placetype":"venue"
},
  "geometry": {"coordinates":[12.22639,48.858177],"type":"Point"}
}