{
  "type": "Feature",
  "properties": {
    "iso:country":"DE",
    "sg:address":"Stationenweg 3",
    "sg:city":"M\u00fcnstermaifeld",
    "sg:phone":"+49 2605/583",
    "sg:postcode":"56294",
    "sg:province":"Rheinland-Pfalz",
    "wof:name":"G. M\u00fcller",
    "wof:placetype":"venue"
},
  "geometry": {"coordinates":[7.36085,50.249405],"type":"Point"}
}