{
  "type": "Feature",
  "properties": {
    "iso:country":"DE",
    "sg:address":"Burg Sooneck",
    "sg:city":"Niederheimbach",
    "sg:phone":"+49 6743/6487",
    "sg:postcode":"55413",
    "sg:province":"Rheinland-Pfalz",
    "wof:name":"Burgschenke",
    "wof:placetype":"venue"
},
  "geometry": {"coordinates":[7.8245501518,50.0197715759],"type":"Point"}
}