{
  "type": "Feature",
  "properties": {
    "iso:country":"DE",
    "sg:address":"Parkstr 6",
    "sg:city":"Spenge",
    "sg:phone":"+49 5225/9719",
    "sg:postcode":"32139",
    "sg:province":"Nordrhein-Westfalen",
    "wof:name":"Atzler Industrieservice Gmbh",
    "wof:placetype":"venue"
},
  "geometry": {"coordinates":[8.477857,52.116737],"type":"Point"}
}