{
  "type": "Feature",
  "properties": {
    "iso:country":"DE",
    "sg:address":"Am Scheffelsberg 2a",
    "sg:city":"Gr\u00fcnhainichen",
    "sg:phone":"+49 37294/7248",
    "sg:postcode":"09579",
    "sg:province":"Sachsen",
    "wof:name":"Lieberknecht & B\u00f6hme Gmbh",
    "wof:placetype":"venue"
},
  "geometry": {"coordinates":[13.152978,50.763241],"type":"Point"}
}