{
  "type": "Feature",
  "properties": {
    "iso:country":"DE",
    "sg:address":"Heidem\u00fchlweg 23E",
    "sg:city":"Dresden",
    "sg:postcode":"01324",
    "sg:province":"Sachsen",
    "wof:name":"Bst Bautenschutz-und Sanier- Ungstechnik Erich K\u00fchfu\u00df Gmbh",
    "wof:placetype":"venue"
},
  "geometry": {"coordinates":[13.855442,51.063889],"type":"Point"}
}