{
  "type": "Feature",
  "properties": {
    "iso:country":"DE",
    "sg:address":"Hellerhofstr. 2-4",
    "sg:city":"Frankfurt",
    "sg:postcode":"60327",
    "sg:province":"Hessen",
    "wof:name":"F.a.z. Radio Beteiligungs Gmbh & Co. Kg",
    "wof:placetype":"venue"
},
  "geometry": {"coordinates":[8.64718,50.104584],"type":"Point"}
}