{
  "type": "Feature",
  "properties": {
    "iso:country":"DE",
    "sg:address":"Hofmarkstr. 9",
    "sg:city":"M\u00fcnchen",
    "sg:phone":"+49 89/6704820",
    "sg:postcode":"81737",
    "sg:province":"Bayern",
    "wof:name":"Kurbad Altperlach",
    "wof:placetype":"venue"
},
  "geometry": {"coordinates":[11.630621,48.102947],"type":"Point"}
}