{
  "type": "Feature",
  "properties": {
    "iso:country":"DE",
    "sg:address":"Tostedter Str. 1",
    "sg:city":"Hollenstedt",
    "sg:phone":"+49 4165/8661",
    "sg:postcode":"21279",
    "sg:province":"Niedersachsen",
    "wof:name":"Aral-tankstelle",
    "wof:placetype":"venue"
},
  "geometry": {"coordinates":[9.7113647461,53.3651580811],"type":"Point"}
}