{
  "type": "Feature",
  "properties": {
    "iso:country":"DE",
    "sg:address":"Siegfriedstr. 45",
    "sg:city":"Bad Oeynhausen",
    "sg:phone":"+49 5731/9034",
    "sg:postcode":"32547",
    "sg:province":"Nordrhein-Westfalen",
    "wof:name":"K\u00f6rtner Verwaltungs Gmbh",
    "wof:placetype":"venue"
},
  "geometry": {"coordinates":[8.8089590073,52.1925811768],"type":"Point"}
}