{
  "type": "Feature",
  "properties": {
    "iso:country":"DE",
    "sg:address":"Hans-B\u00f6ckler-Str. 12-16",
    "sg:city":"Bochum",
    "sg:phone":"+49 234/687080",
    "sg:postcode":"44787",
    "sg:province":"Nordrhein-Westfalen",
    "wof:name":"Redaktion Ruhr-nachrichten Zeitung F\u00fcr Bochum Und",
    "wof:placetype":"venue"
},
  "geometry": {"coordinates":[7.215944767,51.4830627441],"type":"Point"}
}