{
  "type": "Feature",
  "properties": {
    "iso:country":"DE",
    "sg:address":"Blankeneser Hauptstr. 138",
    "sg:city":"Hamburg",
    "sg:phone":"+49 40/863498",
    "sg:postcode":"22587",
    "sg:province":"Hamburg",
    "wof:name":"Undine Baum Tanz- Und Ballettschule",
    "wof:placetype":"venue"
},
  "geometry": {"coordinates":[9.8087854385,53.5584945679],"type":"Point"}
}