{
  "type": "Feature",
  "properties": {
    "iso:country":"DE",
    "sg:address":"Maria-Hilf-Weg 10",
    "sg:city":"Greding",
    "sg:phone":"+49 8463/1207",
    "sg:postcode":"91171",
    "sg:province":"Bayern",
    "wof:name":"Taxi Schnabel",
    "wof:placetype":"venue"
},
  "geometry": {"coordinates":[11.3527746201,49.0479736328],"type":"Point"}
}