{
  "type": "Feature",
  "properties": {
    "iso:country":"DE",
    "sg:address":"Kolpingstr. 8",
    "sg:city":"Borgentreich",
    "sg:phone":"+49 5645/9122",
    "sg:postcode":"34434",
    "sg:province":"Nordrhein-Westfalen",
    "wof:name":"Anton Scherf",
    "wof:placetype":"venue"
},
  "geometry": {"coordinates":[9.239030838,51.6121101379],"type":"Point"}
}