{
  "type": "Feature",
  "properties": {
    "iso:country":"DE",
    "sg:address":"Schlo\u00dfberg 16",
    "sg:city":"Riedlingen",
    "sg:phone":"+49 7371/6657",
    "sg:postcode":"88499",
    "sg:province":"Baden-W\u00fcrttemberg",
    "wof:name":"Joachim Schuberth",
    "wof:placetype":"venue"
},
  "geometry": {"coordinates":[9.4757375717,48.1268348694],"type":"Point"}
}