{
  "type": "Feature",
  "properties": {
    "iso:country":"DE",
    "sg:address":"Sandberg 36",
    "sg:city":"Halle",
    "sg:phone":"+49 345/6874015",
    "sg:postcode":"06126",
    "sg:province":"Sachsen-Anhalt",
    "wof:name":"Ger\u00fcstbau Wilhelm Gmbh",
    "wof:placetype":"venue"
},
  "geometry": {"coordinates":[11.8877048492,51.4817390442],"type":"Point"}
}