{
  "type": "Feature",
  "properties": {
    "iso:country":"DE",
    "sg:address":"Schwanh\u00e4user Str. 2",
    "sg:city":"Sulzdorf",
    "sg:postcode":"97528",
    "sg:province":"Bayern",
    "wof:name":"3 K B\u00fcrom\u00f6bel-vertriebs Gmbh",
    "wof:placetype":"venue"
},
  "geometry": {"coordinates":[10.5703191757,50.238319397],"type":"Point"}
}