{
  "type": "Feature",
  "properties": {
    "iso:country":"DE",
    "sg:address":"St\u00e4udach 119",
    "sg:city":"T\u00fcbingen",
    "sg:phone":"+49 7071/87193",
    "sg:postcode":"72074",
    "sg:province":"Baden-W\u00fcrttemberg",
    "wof:name":"E. D\u00fcrr Hebamme",
    "wof:placetype":"venue"
},
  "geometry": {"coordinates":[9.090284,48.532806],"type":"Point"}
}