{
  "type": "Feature",
  "properties": {
    "iso:country":"DE",
    "sg:address":"Pestalozzistr. 34",
    "sg:city":"Nordhorn",
    "sg:phone":"+49 5921/34699",
    "sg:postcode":"48527",
    "sg:province":"Niedersachsen",
    "wof:name":"R. Sledz Versicherungsvertreter",
    "wof:placetype":"venue"
},
  "geometry": {"coordinates":[7.0564799309,52.4504585266],"type":"Point"}
}