{
  "type": "Feature",
  "properties": {
    "iso:country":"DE",
    "sg:address":"Teuditzer Str. 45",
    "sg:city":"Tollwitz",
    "sg:phone":"+49 3462/83693",
    "sg:postcode":"06231",
    "sg:province":"Sachsen-Anhalt",
    "wof:name":"Gasthof Zur Linde",
    "wof:placetype":"venue"
},
  "geometry": {"coordinates":[12.1001739502,51.2818107605],"type":"Point"}
}