{
  "type": "Feature",
  "properties": {
    "iso:country":"DE",
    "sg:address":"Zum Pfingstanger 3",
    "sg:city":"Bad M\u00fcnder",
    "sg:phone":"+49 5042/51424",
    "sg:postcode":"31848",
    "sg:province":"Niedersachsen",
    "wof:name":"Heinz Schaper",
    "wof:placetype":"venue"
},
  "geometry": {"coordinates":[9.439261,52.15839],"type":"Point"}
}