{
  "type": "Feature",
  "properties": {
    "iso:country":"DE",
    "sg:address":"R\u00f6derweg 10",
    "sg:city":"Taunusstein",
    "sg:phone":"+49 6128/91650",
    "sg:postcode":"65232",
    "sg:province":"Hessen",
    "wof:name":"Steinhardt Gmbh",
    "wof:placetype":"venue"
},
  "geometry": {"coordinates":[8.15188694,50.1369667053],"type":"Point"}
}