{
  "type": "Feature",
  "properties": {
    "iso:country":"DE",
    "sg:address":"Strutweg 20",
    "sg:city":"Bischofsheim",
    "sg:phone":"+49 9772/1269",
    "sg:postcode":"97653",
    "sg:province":"Bayern",
    "wof:name":"Pension Edith R\u00e4der",
    "wof:placetype":"venue"
},
  "geometry": {"coordinates":[10.0289001465,50.398311615],"type":"Point"}
}