{
  "type": "Feature",
  "properties": {
    "iso:country":"DE",
    "sg:address":"M\u00fchlstr. 11",
    "sg:city":"Goldbach",
    "sg:phone":"+49 6021/570979",
    "sg:postcode":"63773",
    "sg:province":"Bayern",
    "wof:name":"Karl-heinz Bank Ingenieur",
    "wof:placetype":"venue"
},
  "geometry": {"coordinates":[9.1854286194,49.9967880249],"type":"Point"}
}