{
  "type": "Feature",
  "properties": {
    "iso:country":"DE",
    "sg:address":"Kilianstr. 6",
    "sg:city":"Wendelstein",
    "sg:phone":"+49 9129/26528",
    "sg:postcode":"90530",
    "sg:province":"Bayern",
    "wof:name":"Heinz Beck Steuerberater",
    "wof:placetype":"venue"
},
  "geometry": {"coordinates":[11.1663579941,49.365322113],"type":"Point"}
}