{
  "type": "Feature",
  "properties": {
    "iso:country":"DE",
    "sg:address":"Bellingerstr. 4",
    "sg:city":"Fulda",
    "sg:phone":"+49 661/94340",
    "sg:postcode":"36043",
    "sg:province":"Hessen",
    "wof:name":"M\u00fcwa Handels Gmbh",
    "wof:placetype":"venue"
},
  "geometry": {"coordinates":[9.6830921173,50.5332565308],"type":"Point"}
}