{
  "type": "Feature",
  "properties": {
    "iso:country":"DE",
    "sg:address":"Amtshausstr. 7",
    "sg:city":"R\u00f6dinghausen",
    "sg:phone":"+49 5746/920236",
    "sg:postcode":"32289",
    "sg:province":"Nordrhein-Westfalen",
    "wof:name":"Manfred Kr\u00e4mer",
    "wof:placetype":"venue"
},
  "geometry": {"coordinates":[8.479529,52.251183],"type":"Point"}
}