{
  "type": "Feature",
  "properties": {
    "iso:country":"DE",
    "sg:address":"Kulmbacher Str. 29",
    "sg:city":"Kronach",
    "sg:phone":"+49 9261/62640",
    "sg:postcode":"96317",
    "sg:province":"Bayern",
    "wof:name":"Hans Karst Kg",
    "wof:placetype":"venue"
},
  "geometry": {"coordinates":[11.324493,50.234058],"type":"Point"}
}