{
  "type": "Feature",
  "properties": {
    "iso:country":"DE",
    "sg:address":"Ennsstr. 19",
    "sg:city":"Krefeld",
    "sg:phone":"+49 2151/543047",
    "sg:postcode":"47809",
    "sg:province":"Nordrhein-Westfalen",
    "wof:name":"Baurent Baumaschinen Miet-service Gmbh",
    "wof:placetype":"venue"
},
  "geometry": {"coordinates":[6.602118,51.320267],"type":"Point"}
}