{
  "type": "Feature",
  "properties": {
    "iso:country":"DE",
    "sg:address":"S\u00fclztalplatz 1",
    "sg:city":"R\u00f6srath",
    "sg:phone":"+49 2205/92330",
    "sg:postcode":"51503",
    "sg:province":"Nordrhein-Westfalen",
    "wof:name":"Dr. Ulrich Theodor Wiemann Rechtsanwalt",
    "wof:placetype":"venue"
},
  "geometry": {"coordinates":[7.1826400757,50.8957328796],"type":"Point"}
}