{
  "type": "Feature",
  "properties": {
    "iso:country":"DE",
    "sg:address":"Koebkeweg 24",
    "sg:city":"Herrsching",
    "sg:postcode":"82211",
    "sg:province":"Bayern",
    "wof:name":"Id-riva Tours Gmbh",
    "wof:placetype":"venue"
},
  "geometry": {"coordinates":[11.1703243256,48.0011978149],"type":"Point"}
}