{
  "type": "Feature",
  "properties": {
    "iso:country":"DE",
    "sg:address":"Harpelsteinstr. 1",
    "sg:city":"Neumagen-Dhron",
    "sg:phone":"+49 6507/4313",
    "sg:postcode":"54347",
    "sg:province":"Rheinland-Pfalz",
    "wof:name":"Gasthaus Zum Harpelstein",
    "wof:placetype":"venue"
},
  "geometry": {"coordinates":[6.9407248497,49.8267097473],"type":"Point"}
}