{
  "type": "Feature",
  "properties": {
    "iso:country":"DE",
    "sg:address":"Corneliusstr. 18",
    "sg:city":"Frankfurt",
    "sg:phone":"+49 69/9074580",
    "sg:postcode":"60325",
    "sg:province":"Hessen",
    "wof:name":"Wellensiek Hagebusch Und Wahl Rechtsanw\u00e4lte",
    "wof:placetype":"venue"
},
  "geometry": {"coordinates":[8.6583099365,50.1170310974],"type":"Point"}
}