{
  "type": "Feature",
  "properties": {
    "iso:country":"DE",
    "sg:address":"Bismarckstr. 1",
    "sg:city":"D\u00fcren",
    "sg:phone":"+49 2421/13122",
    "sg:postcode":"52351",
    "sg:province":"Nordrhein-Westfalen",
    "wof:name":"Josefine Niederau",
    "wof:placetype":"venue"
},
  "geometry": {"coordinates":[6.486554,50.805954],"type":"Point"}
}