{
  "type": "Feature",
  "properties": {
    "iso:country":"DE",
    "sg:address":"Metzstr. 19",
    "sg:city":"Kiel",
    "sg:phone":"+49 431/17239",
    "sg:postcode":"24116",
    "sg:province":"Schleswig-Holstein",
    "wof:name":"B. Weber Masseur",
    "wof:placetype":"venue"
},
  "geometry": {"coordinates":[10.118113,54.326118],"type":"Point"}
}