{
  "type": "Feature",
  "properties": {
    "iso:country":"DE",
    "sg:address":"Br\u00fchlstr. 19",
    "sg:city":"Esslingen",
    "sg:phone":"+49 711/3450665",
    "sg:postcode":"73734",
    "sg:province":"Baden-W\u00fcrttemberg",
    "wof:name":"Mis Micro Infusions Systeme Gmbh",
    "wof:placetype":"venue"
},
  "geometry": {"coordinates":[9.3165607452,48.7203445435],"type":"Point"}
}