{
  "type": "Feature",
  "properties": {
    "iso:country":"DE",
    "sg:address":"Bachstr. 2",
    "sg:city":"Offenbach",
    "sg:phone":"+49 69/851631",
    "sg:postcode":"63071",
    "sg:province":"Hessen",
    "wof:name":"Hermann Nuber",
    "wof:placetype":"venue"
},
  "geometry": {"coordinates":[8.7726106644,50.1005401611],"type":"Point"}
}