{
  "type": "Feature",
  "properties": {
    "iso:country":"DE",
    "sg:address":"Mainzer Str. 85",
    "sg:city":"Remagen",
    "sg:phone":"+49 2228/369",
    "sg:postcode":"53424",
    "sg:province":"Rheinland-Pfalz",
    "wof:name":"Ferd. Braun Personenschiffahrts Agt.",
    "wof:placetype":"venue"
},
  "geometry": {"coordinates":[7.206191,50.642307],"type":"Point"}
}