{
  "type": "Feature",
  "properties": {
    "iso:country":"DE",
    "sg:address":"Weingartenstr. 24",
    "sg:city":"M\u00f6rfelden-Walldorf",
    "sg:phone":"+49 6105/277707",
    "sg:postcode":"64546",
    "sg:province":"Hessen",
    "wof:name":"Vollmond",
    "wof:placetype":"venue"
},
  "geometry": {"coordinates":[8.569190979,49.9774894714],"type":"Point"}
}