{
  "type": "Feature",
  "properties": {
    "iso:country":"DE",
    "sg:address":"Annenstr. 3",
    "sg:city":"Cuxhaven",
    "sg:phone":"+49 4721/554651",
    "sg:postcode":"27472",
    "sg:province":"Niedersachsen",
    "wof:name":"Schwarz-b\u00fcrotechnik Inh. G\u00fcnter Jung",
    "wof:placetype":"venue"
},
  "geometry": {"coordinates":[8.7016954422,53.8678817749],"type":"Point"}
}