{
  "type": "Feature",
  "properties": {
    "iso:country":"DE",
    "sg:address":"Blauwiesenweg 85",
    "sg:city":"Frankfurt",
    "sg:phone":"+49 69/499738",
    "sg:postcode":"60439",
    "sg:province":"Hessen",
    "wof:name":"Marino Arufe",
    "wof:placetype":"venue"
},
  "geometry": {"coordinates":[8.641131,50.165607],"type":"Point"}
}