{
  "type": "Feature",
  "properties": {
    "iso:country":"DE",
    "sg:address":"Steinm\u00fchle 6 1-2",
    "sg:city":"Tiefenbach",
    "sg:postcode":"93464",
    "sg:province":"Bayern",
    "wof:name":"Bioheizwerk R\u00f6tz Gmbh",
    "wof:placetype":"venue"
},
  "geometry": {"coordinates":[12.583512,49.437645],"type":"Point"}
}