{
  "type": "Feature",
  "properties": {
    "iso:country":"DE",
    "sg:address":"Gartenstr. 26",
    "sg:city":"Hiddenhausen",
    "sg:phone":"+49 5223/83422",
    "sg:postcode":"32120",
    "sg:province":"Nordrhein-Westfalen",
    "wof:name":"Elise Petring",
    "wof:placetype":"venue"
},
  "geometry": {"coordinates":[8.6205625534,52.1623077393],"type":"Point"}
}