{
  "type": "Feature",
  "properties": {
    "iso:country":"DE",
    "sg:address":"Kirchplatz 16",
    "sg:city":"Rosendahl",
    "sg:phone":"+49 2566/4248",
    "sg:postcode":"48720",
    "sg:province":"Nordrhein-Westfalen",
    "wof:name":"St. Nikolaus-apotheke",
    "wof:placetype":"venue"
},
  "geometry": {"coordinates":[7.133224,52.006447],"type":"Point"}
}