{
  "type": "Feature",
  "properties": {
    "iso:country":"DE",
    "sg:address":"Torgauer Str. 17",
    "sg:city":"Dommitzsch",
    "sg:phone":"+49 34223/40268",
    "sg:postcode":"04880",
    "sg:province":"Sachsen",
    "wof:name":"Martin Richter",
    "wof:placetype":"venue"
},
  "geometry": {"coordinates":[12.885797,51.637676],"type":"Point"}
}