{
  "type": "Feature",
  "properties": {
    "iso:country":"DE",
    "sg:address":"Bottroper Str. 20",
    "sg:city":"Essen",
    "sg:postcode":"45141",
    "sg:province":"Nordrhein-Westfalen",
    "wof:name":"Dialog Gesellschaft F\u00fcr Direktmarketing Mbh",
    "wof:placetype":"venue"
},
  "geometry": {"coordinates":[6.9947118759,51.4707717896],"type":"Point"}
}