{
  "type": "Feature",
  "properties": {
    "iso:country":"DE",
    "sg:address":"Weizenkamp 1",
    "sg:city":"Sottrum",
    "sg:phone":"+49 4264/2821",
    "sg:postcode":"27367",
    "sg:province":"Niedersachsen",
    "wof:name":"Ocka Niemann Rechtsanw\u00e4ltin",
    "wof:placetype":"venue"
},
  "geometry": {"coordinates":[9.2303676605,53.1065483093],"type":"Point"}
}