{
  "type": "Feature",
  "properties": {
    "iso:country":"DE",
    "sg:address":"Hubertusstr. 37",
    "sg:city":"Wesseling",
    "sg:phone":"+49 2236/42417",
    "sg:postcode":"50389",
    "sg:province":"Nordrhein-Westfalen",
    "wof:name":"Heinz Brenig Kg",
    "wof:placetype":"venue"
},
  "geometry": {"coordinates":[6.9709358215,50.8221244812],"type":"Point"}
}