{
  "type": "Feature",
  "properties": {
    "iso:country":"DE",
    "sg:city":"Koblenz",
    "sg:postcode":"56070",
    "sg:province":"Rheinland-Pfalz",
    "wof:name":"Debeka Versicherungen Und Bausparen",
    "wof:placetype":"venue"
},
  "geometry": {"coordinates":[7.548229,50.380749],"type":"Point"}
}