{
  "type": "Feature",
  "properties": {
    "iso:country":"DE",
    "sg:address":"Weberstr. 1",
    "sg:city":"Nordhausen",
    "sg:phone":"+49 3631/982932",
    "sg:postcode":"99734",
    "sg:province":"Th\u00fcringen",
    "wof:name":"Werner-optik Gmbh",
    "wof:placetype":"venue"
},
  "geometry": {"coordinates":[10.7947044373,51.5015716553],"type":"Point"}
}