{
  "type": "Feature",
  "properties": {
    "iso:country":"DE",
    "sg:address":"Hauptstr. 46",
    "sg:city":"Gersfeld",
    "sg:phone":"+49 6656/392",
    "sg:postcode":"36129",
    "sg:province":"Hessen",
    "wof:name":"Albert Simon",
    "wof:placetype":"venue"
},
  "geometry": {"coordinates":[9.814155,50.450256],"type":"Point"}
}