{
  "type": "Feature",
  "properties": {
    "iso:country":"DE",
    "sg:address":"M\u00fchlendamm 23",
    "sg:city":"Flensburg",
    "sg:phone":"+49 461/13071",
    "sg:postcode":"24937",
    "sg:province":"Schleswig-Holstein",
    "wof:name":"Dns Transport Und Spedition Gmbh Beteiligungsgesellschaft",
    "wof:placetype":"venue"
},
  "geometry": {"coordinates":[9.4391489029,54.7768669128],"type":"Point"}
}