{
  "type": "Feature",
  "properties": {
    "iso:country":"DE",
    "sg:address":"Hauptstr. 33",
    "sg:city":"Gro\u00dfmaischeid",
    "sg:phone":"+49 2689/5223",
    "sg:postcode":"56276",
    "sg:province":"Rheinland-Pfalz",
    "wof:name":"W. Schultheis",
    "wof:placetype":"venue"
},
  "geometry": {"coordinates":[7.636334,50.503174],"type":"Point"}
}