{
  "type": "Feature",
  "properties": {
    "iso:country":"DE",
    "sg:address":"D\u00fcrkheimer Str. 30",
    "sg:city":"Ludwigshafen",
    "sg:phone":"+49 621/676513",
    "sg:postcode":"67071",
    "sg:province":"Rheinland-Pfalz",
    "wof:name":"Ritter-apotheke",
    "wof:placetype":"venue"
},
  "geometry": {"coordinates":[8.370789,49.492764],"type":"Point"}
}