{
  "type": "Feature",
  "properties": {
    "iso:country":"DE",
    "sg:address":"Marktstr. 32",
    "sg:city":"B\u00fccken",
    "sg:phone":"+49 4251/2770",
    "sg:postcode":"27333",
    "sg:province":"Niedersachsen",
    "wof:name":"Harry Kehlenbeck",
    "wof:placetype":"venue"
},
  "geometry": {"coordinates":[9.129263,52.780132],"type":"Point"}
}