{
  "type": "Feature",
  "properties": {
    "iso:country":"DE",
    "sg:address":"Unterulsham",
    "sg:city":"Eggst\u00e4tt",
    "sg:phone":"+49 8056/352",
    "sg:postcode":"83125",
    "sg:province":"Bayern",
    "wof:name":"Valentin Rohrm\u00fcller",
    "wof:placetype":"venue"
},
  "geometry": {"coordinates":[12.3610696793,47.9379501343],"type":"Point"}
}