{
  "type": "Feature",
  "properties": {
    "iso:country":"DE",
    "sg:address":"Alexander-Puschkin-Str. 9",
    "sg:city":"G\u00f6\u00dfnitz",
    "sg:phone":"+49 34493/30236",
    "sg:postcode":"04639",
    "sg:province":"Th\u00fcringen",
    "wof:name":"I. Sch\u00f6nig",
    "wof:placetype":"venue"
},
  "geometry": {"coordinates":[12.4265727997,50.8890342712],"type":"Point"}
}