{
  "type": "Feature",
  "properties": {
    "iso:country":"DE",
    "sg:address":"Heimeranstr. 2",
    "sg:city":"M\u00fcnchen",
    "sg:phone":"+49 89/51099011",
    "sg:postcode":"80339",
    "sg:province":"Bayern",
    "wof:name":"B & B Stahl-rohr-industriepro- Dukte Vertriebs Gmbh",
    "wof:placetype":"venue"
},
  "geometry": {"coordinates":[11.544955,48.134476],"type":"Point"}
}