{
  "type": "Feature",
  "properties": {
    "iso:country":"DE",
    "sg:address":"Kirchstr. 10",
    "sg:city":"Rhede",
    "sg:phone":"+49 2872/6037",
    "sg:postcode":"46414",
    "sg:province":"Nordrhein-Westfalen",
    "wof:name":"Ristorante Italia",
    "wof:placetype":"venue"
},
  "geometry": {"coordinates":[6.6963229179,51.8409156799],"type":"Point"}
}