{
  "type": "Feature",
  "properties": {
    "iso:country":"DE",
    "sg:address":"Neue Kasseler Str. 54",
    "sg:city":"Marburg",
    "sg:phone":"+49 6421/65325",
    "sg:postcode":"35039",
    "sg:province":"Hessen",
    "wof:name":"Art Design",
    "wof:placetype":"venue"
},
  "geometry": {"coordinates":[8.771033,50.828465],"type":"Point"}
}