{
  "type": "Feature",
  "properties": {
    "iso:country":"DE",
    "sg:address":"Hohe Tannen 55",
    "sg:city":"Cloppenburg",
    "sg:phone":"+49 4471/2073",
    "sg:postcode":"49661",
    "sg:province":"Niedersachsen",
    "wof:name":"Franz Grote",
    "wof:placetype":"venue"
},
  "geometry": {"coordinates":[8.082415,52.840904],"type":"Point"}
}