{
  "type": "Feature",
  "properties": {
    "iso:country":"DE",
    "sg:address":"Kurf\u00fcrst-Dietrich-Str. 6",
    "sg:city":"Montabaur",
    "sg:phone":"+49 2602/5834",
    "sg:postcode":"56410",
    "sg:province":"Rheinland-Pfalz",
    "wof:name":"Johann-alexander Mrugowski Innenarchitekt",
    "wof:placetype":"venue"
},
  "geometry": {"coordinates":[7.815563,50.437012],"type":"Point"}
}