{
  "type": "Feature",
  "properties": {
    "iso:country":"DE",
    "sg:address":"Gro\u00dfe Str. 98",
    "sg:city":"D\u00f6rverden",
    "sg:phone":"+49 4234/1324",
    "sg:postcode":"27313",
    "sg:province":"Niedersachsen",
    "wof:name":"Gerd M\u00f6cker",
    "wof:placetype":"venue"
},
  "geometry": {"coordinates":[9.2309370041,52.8488044739],"type":"Point"}
}