{
  "type": "Feature",
  "properties": {
    "iso:country":"DE",
    "sg:address":"Eyller Str. 99",
    "sg:city":"Kamp-Lintfort",
    "sg:phone":"+49 2842/96685",
    "sg:postcode":"47475",
    "sg:province":"Nordrhein-Westfalen",
    "wof:name":"Studio Volker Wulff",
    "wof:placetype":"venue"
},
  "geometry": {"coordinates":[6.532336235,51.4957733154],"type":"Point"}
}