{
  "type": "Feature",
  "properties": {
    "iso:country":"DE",
    "sg:address":"Georg-Hacker-Weg 1",
    "sg:city":"Hof",
    "sg:phone":"+49 9281/67007",
    "sg:postcode":"95030",
    "sg:province":"Bayern",
    "wof:name":"Uwe H. Pittelkow",
    "wof:placetype":"venue"
},
  "geometry": {"coordinates":[11.897445,50.33046],"type":"Point"}
}