{
  "type": "Feature",
  "properties": {
    "iso:country":"DE",
    "sg:address":"Reinsehlener Weg 17",
    "sg:city":"Schneverdingen",
    "sg:phone":"+49 5193/7787",
    "sg:postcode":"29640",
    "sg:province":"Niedersachsen",
    "wof:name":"Wilfried Wesseloh",
    "wof:placetype":"venue"
},
  "geometry": {"coordinates":[9.768724,53.14769],"type":"Point"}
}