{
  "type": "Feature",
  "properties": {
    "iso:country":"DE",
    "sg:address":"Waxensteinstr. 19",
    "sg:city":"Garmisch-Partenkirchen",
    "sg:postcode":"82467",
    "sg:province":"Bayern",
    "wof:name":"Vogel Grundst\u00fccks- Verwaltung Gmbh & Co. Kg",
    "wof:placetype":"venue"
},
  "geometry": {"coordinates":[11.0804643631,47.4851226807],"type":"Point"}
}