{
  "type": "Feature",
  "properties": {
    "iso:country":"DE",
    "sg:address":"Ludwigstr. 56",
    "sg:city":"N\u00fcrnberg",
    "sg:phone":"+49 911/226319",
    "sg:postcode":"90402",
    "sg:province":"Bayern",
    "wof:name":"Optik Drexler",
    "wof:placetype":"venue"
},
  "geometry": {"coordinates":[11.0680704117,49.4491157532],"type":"Point"}
}