{
  "type": "Feature",
  "properties": {
    "iso:country":"DE",
    "sg:address":"Balduinstr. 50",
    "sg:city":"St. Wendel",
    "sg:phone":"+49 6851/2347",
    "sg:postcode":"66606",
    "sg:province":"Saarland",
    "wof:name":"G\u00fcnther Born",
    "wof:placetype":"venue"
},
  "geometry": {"coordinates":[7.172548,49.467533],"type":"Point"}
}