{
  "type": "Feature",
  "properties": {
    "iso:country":"DE",
    "sg:address":"Simmelberger Weg 44",
    "sg:city":"Heroldsberg",
    "sg:phone":"+49 911/5180234",
    "sg:postcode":"90562",
    "sg:province":"Bayern",
    "wof:name":"Kaspar Hoog",
    "wof:placetype":"venue"
},
  "geometry": {"coordinates":[11.1624221802,49.5282325745],"type":"Point"}
}