{
  "type": "Feature",
  "properties": {
    "iso:country":"DE",
    "sg:address":"Conrad-Clau\u00df-Str. 20",
    "sg:city":"Hohenstein-Ernstthal",
    "sg:phone":"+49 3723/42046",
    "sg:postcode":"09337",
    "sg:province":"Sachsen",
    "wof:name":"Feri-w\u00e4sche Gmbh",
    "wof:placetype":"venue"
},
  "geometry": {"coordinates":[12.703373909,50.8001556396],"type":"Point"}
}