{
  "type": "Feature",
  "properties": {
    "iso:country":"DE",
    "sg:address":"Grunewaldstr. 99",
    "sg:city":"M\u00f6nchengladbach",
    "sg:phone":"+49 2161/664562",
    "sg:postcode":"41066",
    "sg:province":"Nordrhein-Westfalen",
    "wof:name":"Neuwerker Hof",
    "wof:placetype":"venue"
},
  "geometry": {"coordinates":[6.478000164,51.2325820923],"type":"Point"}
}