{
  "type": "Feature",
  "properties": {
    "iso:country":"DE",
    "sg:address":"Hauptstr. 123",
    "sg:city":"Moormerland",
    "sg:phone":"+49 4954/6724",
    "sg:postcode":"26802",
    "sg:province":"Niedersachsen",
    "wof:name":"Thea Meyer",
    "wof:placetype":"venue"
},
  "geometry": {"coordinates":[7.4840450287,53.2891998291],"type":"Point"}
}