{
  "type": "Feature",
  "properties": {
    "iso:country":"DE",
    "sg:address":"Vier Eichen 8",
    "sg:city":"Kupferzell",
    "sg:postcode":"74635",
    "sg:province":"Baden-W\u00fcrttemberg",
    "wof:name":"Neckermann Reisen",
    "wof:placetype":"venue"
},
  "geometry": {"coordinates":[9.6933670044,49.1790390015],"type":"Point"}
}