{
  "type": "Feature",
  "properties": {
    "iso:country":"DE",
    "sg:address":"Nordring 34",
    "sg:city":"Eilenburg",
    "sg:phone":"+49 3423/68250",
    "sg:postcode":"04838",
    "sg:province":"Sachsen",
    "wof:name":"Wohnungsgenossenschaft Eg",
    "wof:placetype":"venue"
},
  "geometry": {"coordinates":[12.6297550201,51.4605674744],"type":"Point"}
}