{
  "type": "Feature",
  "properties": {
    "iso:country":"DE",
    "sg:address":"Kasparstr. 22",
    "sg:city":"Bingen",
    "sg:phone":"+49 6721/12375",
    "sg:postcode":"55411",
    "sg:province":"Rheinland-Pfalz",
    "wof:name":"Langheinrich Und B\u00f6hme",
    "wof:placetype":"venue"
},
  "geometry": {"coordinates":[7.9411020279,49.9646148682],"type":"Point"}
}