{
  "type": "Feature",
  "properties": {
    "iso:country":"DE",
    "sg:address":"Heinrich-Seidel-Str. 17",
    "sg:city":"Berlin",
    "sg:phone":"+49 30/7965252",
    "sg:postcode":"12167",
    "sg:province":"Berlin",
    "wof:name":"Gr\u00fcnwald Immobilien",
    "wof:placetype":"venue"
},
  "geometry": {"coordinates":[13.3433389664,52.4491615295],"type":"Point"}
}