{
  "type": "Feature",
  "properties": {
    "iso:country":"DE",
    "sg:address":"Feldweg 6",
    "sg:city":"Gallinchen",
    "sg:phone":"+49 355/534658",
    "sg:postcode":"03058",
    "sg:province":"Brandenburg",
    "wof:name":"Juergen Dittmann",
    "wof:placetype":"venue"
},
  "geometry": {"coordinates":[14.3518,51.709965],"type":"Point"}
}