{
  "type": "Feature",
  "properties": {
    "iso:country":"DE",
    "sg:address":"Sophienstr. 56",
    "sg:city":"Karlsruhe",
    "sg:phone":"+49 721/27364",
    "sg:postcode":"76133",
    "sg:province":"Baden-W\u00fcrttemberg",
    "wof:name":"C. Portabales Malerfachbetrieb Gmbh",
    "wof:placetype":"venue"
},
  "geometry": {"coordinates":[8.388126,49.007725],"type":"Point"}
}