{
  "type": "Feature",
  "properties": {
    "iso:country":"DE",
    "sg:address":"Allee 49",
    "sg:city":"Heilbronn",
    "sg:phone":"+49 7131/627463",
    "sg:postcode":"74072",
    "sg:province":"Baden-W\u00fcrttemberg",
    "wof:name":"Apotheke Am Theater",
    "wof:placetype":"venue"
},
  "geometry": {"coordinates":[9.222564,49.143974],"type":"Point"}
}