{
  "type": "Feature",
  "properties": {
    "iso:country":"DE",
    "sg:address":"D\u00e4nnendiek 1",
    "sg:city":"Rhede",
    "sg:postcode":"46414",
    "sg:province":"Nordrhein-Westfalen",
    "wof:name":"Angelshop Rhede Gmbh",
    "wof:placetype":"venue"
},
  "geometry": {"coordinates":[6.6996431351,51.8335800171],"type":"Point"}
}