{
  "type": "Feature",
  "properties": {
    "iso:country":"DE",
    "sg:address":"Eichendorffweg 2",
    "sg:city":"H\u00fcckeswagen",
    "sg:phone":"+49 2192/5685",
    "sg:postcode":"42499",
    "sg:province":"Nordrhein-Westfalen",
    "wof:name":"W. Und C. Neuhaus",
    "wof:placetype":"venue"
},
  "geometry": {"coordinates":[7.342076,51.142662],"type":"Point"}
}