{
  "type": "Feature",
  "properties": {
    "iso:country":"DE",
    "sg:address":"Hausen 9",
    "sg:city":"Kirchheim",
    "sg:phone":"+49 89/9902290",
    "sg:postcode":"85551",
    "sg:province":"Bayern",
    "wof:name":"Hiltmair Gmbh & Co. Kg",
    "wof:placetype":"venue"
},
  "geometry": {"coordinates":[11.7425413132,48.1761016846],"type":"Point"}
}