{
  "type": "Feature",
  "properties": {
    "iso:country":"DE",
    "sg:address":"Hauptstr. 21",
    "sg:city":"Sch\u00f6nwald",
    "sg:phone":"+49 7722/4548",
    "sg:postcode":"78141",
    "sg:province":"Baden-W\u00fcrttemberg",
    "wof:name":"Dr. Lemmer Touristik Gmbh",
    "wof:placetype":"venue"
},
  "geometry": {"coordinates":[13.4394359589,52.675579071],"type":"Point"}
}