{
  "type": "Feature",
  "properties": {
    "iso:country":"DE",
    "sg:address":"Neue Str. 5",
    "sg:city":"Immenhausen",
    "sg:phone":"+49 5673/6202",
    "sg:postcode":"34376",
    "sg:province":"Hessen",
    "wof:name":"Dive Away",
    "wof:placetype":"venue"
},
  "geometry": {"coordinates":[9.480275,51.428104],"type":"Point"}
}