{
  "type": "Feature",
  "properties": {
    "iso:country":"DE",
    "sg:address":"Hauptstr. 91",
    "sg:city":"Mengen",
    "sg:phone":"+49 7572/9789",
    "sg:postcode":"88512",
    "sg:province":"Baden-W\u00fcrttemberg",
    "wof:name":"Wolfgang Beller",
    "wof:placetype":"venue"
},
  "geometry": {"coordinates":[9.329446,48.04858],"type":"Point"}
}