{
  "type": "Feature",
  "properties": {
    "iso:country":"DE",
    "sg:address":"Berliner Str. 64 b",
    "sg:city":"Hohen Neuendorf",
    "sg:postcode":"16540",
    "sg:province":"Brandenburg",
    "wof:name":"Ipeg Immoblien-projekt-ent- Wicklungsgesellschaft Mbh",
    "wof:placetype":"venue"
},
  "geometry": {"coordinates":[13.284403801,52.6641311646],"type":"Point"}
}