{
  "type": "Feature",
  "properties": {
    "iso:country":"DE",
    "sg:address":"Am Thomaskreuzchen 44",
    "sg:city":"Sankt Augustin",
    "sg:phone":"+49 2241/338272",
    "sg:postcode":"53757",
    "sg:province":"Nordrhein-Westfalen",
    "wof:name":"Karin Scharfenberg Heilpraktikerin",
    "wof:placetype":"venue"
},
  "geometry": {"coordinates":[7.1941008568,50.7698516846],"type":"Point"}
}