{
  "type": "Feature",
  "properties": {
    "iso:country":"DE",
    "sg:address":"Dachsweg 35",
    "sg:city":"Jesteburg",
    "sg:phone":"+49 4183/5975",
    "sg:postcode":"21266",
    "sg:province":"Niedersachsen",
    "wof:name":"Dieter Brunck Ingenieur",
    "wof:placetype":"venue"
},
  "geometry": {"coordinates":[9.9650373459,53.30991745],"type":"Point"}
}