{
  "type": "Feature",
  "properties": {
    "iso:country":"DE",
    "sg:address":"F-Wilh-v-Steuben-Str 104",
    "sg:city":"Frankfurt",
    "sg:phone":"+49 69/786999",
    "sg:postcode":"60488",
    "sg:province":"Hessen",
    "wof:name":"Arnold & Stolzenberg Gmbh",
    "wof:placetype":"venue"
},
  "geometry": {"coordinates":[8.621143,50.149487],"type":"Point"}
}