{
  "type": "Feature",
  "properties": {
    "iso:country":"DE",
    "sg:address":"Im Gro\u00dfen Ahl 52",
    "sg:city":"Offenbach",
    "sg:phone":"+49 69/861215",
    "sg:postcode":"63075",
    "sg:province":"Hessen",
    "wof:name":"\u00c4gid Menges",
    "wof:placetype":"venue"
},
  "geometry": {"coordinates":[8.797883,50.109177],"type":"Point"}
}