{
  "type": "Feature",
  "properties": {
    "iso:country":"DE",
    "sg:address":"Ringgasse 13",
    "sg:city":"Vohenstrau\u00df",
    "sg:phone":"+49 9651/2208",
    "sg:postcode":"92648",
    "sg:province":"Bayern",
    "wof:name":"Fuchs",
    "wof:placetype":"venue"
},
  "geometry": {"coordinates":[12.342188,49.625179],"type":"Point"}
}