{
  "type": "Feature",
  "properties": {
    "iso:country":"DE",
    "sg:address":"Lerchesbergring 1",
    "sg:city":"Frankfurt",
    "sg:phone":"+49 69/683177",
    "sg:postcode":"60598",
    "sg:province":"Hessen",
    "wof:name":"G\u00fcnter Schanz",
    "wof:placetype":"venue"
},
  "geometry": {"coordinates":[8.6849727631,50.0849342346],"type":"Point"}
}