{
  "type": "Feature",
  "properties": {
    "iso:country":"DE",
    "sg:address":"Lohtorstr. 27",
    "sg:city":"Heilbronn",
    "sg:phone":"+49 4971/3162220",
    "sg:postcode":"74072",
    "sg:province":"Baden-W\u00fcrttemberg",
    "wof:name":"Bfg Bank",
    "wof:placetype":"venue"
},
  "geometry": {"coordinates":[9.219268,49.14328],"type":"Point"}
}