{
  "type": "Feature",
  "properties": {
    "iso:country":"DE",
    "sg:address":"Hammerstr. 7",
    "sg:city":"Mettmann",
    "sg:phone":"+49 2104/28519",
    "sg:postcode":"40822",
    "sg:province":"Nordrhein-Westfalen",
    "wof:name":"Ellen Juffernbruch",
    "wof:placetype":"venue"
},
  "geometry": {"coordinates":[6.9780650139,51.2550048828],"type":"Point"}
}