{
  "type": "Feature",
  "properties": {
    "iso:country":"DE",
    "sg:address":"Herrfurthstr. 8",
    "sg:city":"Merseburg",
    "sg:phone":"+49 4934/6173230",
    "sg:postcode":"06217",
    "sg:province":"Sachsen-Anhalt",
    "wof:name":"Wilhelm Pesch Gmbh & Co.kg",
    "wof:placetype":"venue"
},
  "geometry": {"coordinates":[11.9753932953,51.374420166],"type":"Point"}
}