{
  "type": "Feature",
  "properties": {
    "iso:country":"DE",
    "sg:address":"Reilsheimer Str. 32/1",
    "sg:city":"Bammental",
    "sg:phone":"+49 6223/46286",
    "sg:postcode":"69245",
    "sg:province":"Baden-W\u00fcrttemberg",
    "wof:name":"Klaus Und Helga Heinzmann",
    "wof:placetype":"venue"
},
  "geometry": {"coordinates":[8.7754802704,49.3515815735],"type":"Point"}
}