{
  "type": "Feature",
  "properties": {
    "iso:country":"DE",
    "sg:address":"Klein Feldhus 46",
    "sg:city":"Rastede",
    "sg:phone":"+49 4402/83334",
    "sg:postcode":"26180",
    "sg:province":"Niedersachsen",
    "wof:name":"Gurol Gmbh",
    "wof:placetype":"venue"
},
  "geometry": {"coordinates":[8.2247514725,53.2145309448],"type":"Point"}
}