{
  "type": "Feature",
  "properties": {
    "iso:country":"DE",
    "sg:address":"Vogtswg. 18",
    "sg:city":"Marne",
    "sg:phone":"+49 4948/5191110",
    "sg:postcode":"25709",
    "sg:province":"Schleswig-Holstein",
    "wof:name":"Dithmarscher K\u00c4ltetechnik Gmbh",
    "wof:placetype":"venue"
},
  "geometry": {"coordinates":[9.00447,53.958656],"type":"Point"}
}