{
  "type": "Feature",
  "properties": {
    "iso:country":"DE",
    "sg:address":"Bahlinger Str. 18",
    "sg:city":"Eichstetten",
    "sg:phone":"+49 7663/94640",
    "sg:postcode":"79356",
    "sg:province":"Baden-W\u00fcrttemberg",
    "wof:name":"Manfred Leithold",
    "wof:placetype":"venue"
},
  "geometry": {"coordinates":[7.72887,48.09343],"type":"Point"}
}