{
  "type": "Feature",
  "properties": {
    "iso:country":"DE",
    "sg:address":"Markt 21",
    "sg:city":"R\u00fcdesheim am Rhein",
    "sg:phone":"+49 6722/47868",
    "sg:postcode":"65385",
    "sg:province":"Hessen",
    "wof:name":"D. Feuerstein",
    "wof:placetype":"venue"
},
  "geometry": {"coordinates":[7.9227662086,49.979057312],"type":"Point"}
}