{
  "type": "Feature",
  "properties": {
    "iso:country":"DE",
    "sg:address":"Sanderstr. 5",
    "sg:city":"W\u00fcrzburg",
    "sg:phone":"+49 931/53807",
    "sg:postcode":"97070",
    "sg:province":"Bayern",
    "wof:name":"Heimbaugenossenschaft Unterfranken Eg",
    "wof:placetype":"venue"
},
  "geometry": {"coordinates":[9.9303894043,49.7894363403],"type":"Point"}
}