{
  "type": "Feature",
  "properties": {
    "iso:country":"DE",
    "sg:address":"Gr\u00fcber Str. 21",
    "sg:city":"Ansbach",
    "sg:phone":"+49 981/86947",
    "sg:postcode":"91522",
    "sg:province":"Bayern",
    "wof:name":"Johanna Meierh\u00f6fer",
    "wof:placetype":"venue"
},
  "geometry": {"coordinates":[10.5860586166,49.3103523254],"type":"Point"}
}