{
  "type": "Feature",
  "properties": {
    "iso:country":"DE",
    "sg:address":"Arnulfstr. 279",
    "sg:city":"M\u00fcnchen",
    "sg:postcode":"80639",
    "sg:province":"Bayern",
    "wof:name":"J\u00f6rg Thomas Minneken E. K. -unternehmen Arnulfstra\u00dfe-",
    "wof:placetype":"venue"
},
  "geometry": {"coordinates":[11.514669,48.152378],"type":"Point"}
}