{
  "type": "Feature",
  "properties": {
    "iso:country":"DE",
    "sg:address":"Hamburger Str. 27",
    "sg:city":"Leezen",
    "sg:phone":"+49 4552/248",
    "sg:postcode":"23816",
    "sg:province":"Schleswig-Holstein",
    "wof:name":"Walter B\u00f6lk",
    "wof:placetype":"venue"
},
  "geometry": {"coordinates":[10.252512,53.867001],"type":"Point"}
}