{
  "type": "Feature",
  "properties": {
    "iso:country":"DE",
    "sg:address":"Stolpseestr. 3",
    "sg:city":"Himmelpfort",
    "sg:phone":"+49 33089/41310",
    "sg:postcode":"16798",
    "sg:province":"Brandenburg",
    "wof:name":"J. Reinhardt Immobilienmakler",
    "wof:placetype":"venue"
},
  "geometry": {"coordinates":[13.2324113846,53.1759033203],"type":"Point"}
}