{
  "type": "Feature",
  "properties": {
    "iso:country":"DE",
    "sg:address":"Buchenstr. 1",
    "sg:city":"Frankfurt",
    "sg:phone":"+49 69/393553",
    "sg:postcode":"65933",
    "sg:province":"Hessen",
    "wof:name":"Vlatka Jurcevic Massagepraxis",
    "wof:placetype":"venue"
},
  "geometry": {"coordinates":[8.606976,50.095772],"type":"Point"}
}