{
  "type": "Feature",
  "properties": {
    "iso:country":"DE",
    "sg:address":"Baumannstr. 4",
    "sg:city":"Arnstadt",
    "sg:phone":"+49 3628/43049",
    "sg:postcode":"99310",
    "sg:province":"Th\u00fcringen",
    "wof:name":"Arnst\u00e4dter Bierschwemme",
    "wof:placetype":"venue"
},
  "geometry": {"coordinates":[10.9484443665,50.8391990662],"type":"Point"}
}