{
  "type": "Feature",
  "properties": {
    "iso:country":"DE",
    "sg:address":"Berliner Str. 30",
    "sg:city":"Rottenburg",
    "sg:phone":"+49 7472/25154",
    "sg:postcode":"72108",
    "sg:province":"Baden-W\u00fcrttemberg",
    "wof:name":"Christoph Lang",
    "wof:placetype":"venue"
},
  "geometry": {"coordinates":[8.9258117676,48.4776649475],"type":"Point"}
}