{
  "type": "Feature",
  "properties": {
    "iso:country":"DE",
    "sg:address":"Stuttgarter Str. 17",
    "sg:city":"Vaihingen",
    "sg:phone":"+49 7042/17549",
    "sg:postcode":"71665",
    "sg:province":"Baden-W\u00fcrttemberg",
    "wof:name":"Ute Heininger",
    "wof:placetype":"venue"
},
  "geometry": {"coordinates":[8.958601,48.931343],"type":"Point"}
}