{
  "type": "Feature",
  "properties": {
    "iso:country":"DE",
    "sg:address":"Pfaffenstr. 1b",
    "sg:city":"Osnabr\u00fcck",
    "sg:phone":"+49 541/25354",
    "sg:postcode":"49074",
    "sg:province":"Niedersachsen",
    "wof:name":"Mayer Gastronomiebetriebe Osnabr\u00fcck Beteiligungs Gmbh",
    "wof:placetype":"venue"
},
  "geometry": {"coordinates":[8.05341,52.269859],"type":"Point"}
}