{
  "type": "Feature",
  "properties": {
    "iso:country":"DE",
    "sg:address":"Hamburger Str. 123-127",
    "sg:city":"Heide",
    "sg:phone":"+49 481/3022",
    "sg:postcode":"25746",
    "sg:province":"Schleswig-Holstein",
    "wof:name":"Werner Leinweber Kg",
    "wof:placetype":"venue"
},
  "geometry": {"coordinates":[9.1169252396,54.1975784302],"type":"Point"}
}