{
  "type": "Feature",
  "properties": {
    "iso:country":"DE",
    "sg:address":"Schulstr. 30",
    "sg:city":"Bretleben",
    "sg:postcode":"06556",
    "sg:province":"Th\u00fcringen",
    "wof:name":"Wasserversorgung Und Abwasserbehandlung Halle Gmbh",
    "wof:placetype":"venue"
},
  "geometry": {"coordinates":[11.2284736633,51.3340301514],"type":"Point"}
}