{
  "type": "Feature",
  "properties": {
    "iso:country":"DE",
    "sg:address":"Lennestr. 17",
    "sg:city":"Werdohl",
    "sg:phone":"+49 2392/3030",
    "sg:postcode":"58791",
    "sg:province":"Nordrhein-Westfalen",
    "wof:name":"Bernd Nickel Tankstellen Gmbh",
    "wof:placetype":"venue"
},
  "geometry": {"coordinates":[7.7571320534,51.2570037842],"type":"Point"}
}