{
  "type": "Feature",
  "properties": {
    "iso:country":"DE",
    "sg:address":"Wilhelmstr. 40",
    "sg:city":"Badenweiler",
    "sg:phone":"+49 7632/82040",
    "sg:postcode":"79410",
    "sg:province":"Baden-W\u00fcrttemberg",
    "wof:name":"Hotel Badenweiler Hof",
    "wof:placetype":"venue"
},
  "geometry": {"coordinates":[7.6780648232,47.8015785217],"type":"Point"}
}