{
  "type": "Feature",
  "properties": {
    "iso:country":"DE",
    "sg:address":"Ulmenstr. 299",
    "sg:city":"D\u00fcsseldorf",
    "sg:phone":"+49 211/410547",
    "sg:postcode":"40468",
    "sg:province":"Nordrhein-Westfalen",
    "wof:name":"Cosy-wasch Autoservice-betriebe Gmbh",
    "wof:placetype":"venue"
},
  "geometry": {"coordinates":[6.776898,51.261292],"type":"Point"}
}