{
  "type": "Feature",
  "properties": {
    "iso:country":"DE",
    "sg:address":"Alter Kirchenweg 2",
    "sg:city":"Husum",
    "sg:phone":"+49 4841/4870",
    "sg:postcode":"25813",
    "sg:province":"Schleswig-Holstein",
    "wof:name":"Ev. Pfarramt Albert-schweizer-haus",
    "wof:placetype":"venue"
},
  "geometry": {"coordinates":[9.0562620163,54.468547821],"type":"Point"}
}