{
  "type": "Feature",
  "properties": {
    "iso:country":"DE",
    "sg:address":"M\u00fchlenstr. 5",
    "sg:city":"Sittensen",
    "sg:phone":"+49 4282/1439",
    "sg:postcode":"27419",
    "sg:province":"Niedersachsen",
    "wof:name":"Gastst\u00e4tte Fr.-w. Behrens",
    "wof:placetype":"venue"
},
  "geometry": {"coordinates":[9.506570816,53.2768363953],"type":"Point"}
}