{
  "type": "Feature",
  "properties": {
    "iso:country":"DE",
    "sg:address":"Marktgasse 12",
    "sg:city":"Mei\u00dfen",
    "sg:phone":"+49 3521/452567",
    "sg:postcode":"01662",
    "sg:province":"Sachsen",
    "wof:name":"Monika Fu\u00dfy Rechtsanw\u00e4ltin",
    "wof:placetype":"venue"
},
  "geometry": {"coordinates":[13.4716243744,51.1625556946],"type":"Point"}
}