{
  "type": "Feature",
  "properties": {
    "iso:country":"DE",
    "sg:address":"Sch\u00e4ftersheimer Str. 49",
    "sg:city":"Weikersheim",
    "sg:postcode":"97990",
    "sg:province":"Baden-W\u00fcrttemberg",
    "wof:name":"Michel Metalltechnik Gmbh",
    "wof:placetype":"venue"
},
  "geometry": {"coordinates":[9.9018497467,49.4887695312],"type":"Point"}
}