{
  "type": "Feature",
  "properties": {
    "iso:country":"DE",
    "sg:city":"Raubling",
    "sg:phone":"+49 8035/1001",
    "sg:postcode":"83064",
    "sg:province":"Bayern",
    "wof:name":"Raiffeisenbank Rosenheim Eg",
    "wof:placetype":"venue"
},
  "geometry": {"coordinates":[12.109181,47.787838],"type":"Point"}
}