{
  "type": "Feature",
  "properties": {
    "iso:country":"DE",
    "sg:address":"M\u00fchlenweg 3-4",
    "sg:city":"Brunsb\u00fcttel",
    "sg:phone":"+49 4858/569",
    "sg:postcode":"25541",
    "sg:province":"Schleswig-Holstein",
    "wof:name":"Kaefer Isoliertechnik Gmbh & Co. Kg",
    "wof:placetype":"venue"
},
  "geometry": {"coordinates":[9.108305,53.895954],"type":"Point"}
}