{
  "type": "Feature",
  "properties": {
    "iso:country":"DE",
    "sg:address":"Altheimer Str. 76",
    "sg:city":"Essenbach",
    "sg:phone":"+49 8703/1301",
    "sg:postcode":"84051",
    "sg:province":"Bayern",
    "wof:name":"Katholisches Pfarramt St. Peter",
    "wof:placetype":"venue"
},
  "geometry": {"coordinates":[12.2122688293,48.6062583923],"type":"Point"}
}