{
  "type": "Feature",
  "properties": {
    "iso:country":"DE",
    "sg:address":"Bahnhofstr. 26",
    "sg:city":"Augsburg",
    "sg:phone":"+49 821/343990",
    "sg:postcode":"86150",
    "sg:province":"Bayern",
    "wof:name":"Gss Gesellschaft F\u00fcr Service Und Sicherheit Im \u00d6pnv Mbh",
    "wof:placetype":"venue"
},
  "geometry": {"coordinates":[10.8883,48.366093],"type":"Point"}
}