{
  "type": "Feature",
  "properties": {
    "iso:country":"DE",
    "sg:address":"Obere Vorstadt 18",
    "sg:city":"Auerbach",
    "sg:phone":"+49 9643/916404",
    "sg:postcode":"91275",
    "sg:province":"Bayern",
    "wof:name":"Akropolis Restaurant",
    "wof:placetype":"venue"
},
  "geometry": {"coordinates":[11.6323108673,49.6905441284],"type":"Point"}
}