{
  "type": "Feature",
  "properties": {
    "iso:country":"DE",
    "sg:address":"Senefelderstr. 50a",
    "sg:city":"Stuttgart",
    "sg:phone":"+49 711/618857",
    "sg:postcode":"70176",
    "sg:province":"Baden-W\u00fcrttemberg",
    "wof:name":"Martin Raible Anlageberater",
    "wof:placetype":"venue"
},
  "geometry": {"coordinates":[9.1616630554,48.7745094299],"type":"Point"}
}