{
  "type": "Feature",
  "properties": {
    "iso:country":"DE",
    "sg:address":"Hengstwaldstr. 9a",
    "sg:city":"Puettlingen",
    "sg:phone":"+49 700 3593 2337",
    "sg:postcode":"66346",
    "sg:province":"Saarland",
    "wof:name":"Perfectwww.de - Dresen, Gruen Und Martin Gbr",
    "wof:placetype":"venue"
},
  "geometry": {"coordinates":[6.899188,49.280651],"type":"Point"}
}