{
  "type": "Feature",
  "properties": {
    "iso:country":"DE",
    "sg:address":"K\u00f6lner Str. 59",
    "sg:city":"D\u00fcsseldorf",
    "sg:phone":"+49 211/1649996",
    "sg:postcode":"40211",
    "sg:province":"Nordrhein-Westfalen",
    "wof:name":"Absolut",
    "wof:placetype":"venue"
},
  "geometry": {"coordinates":[6.795188,51.22477],"type":"Point"}
}