{
  "type": "Feature",
  "properties": {
    "iso:country":"DE",
    "sg:address":"Siemensstr. 5",
    "sg:city":"Meppen",
    "sg:phone":"+49 5931/89861",
    "sg:postcode":"49716",
    "sg:province":"Niedersachsen",
    "wof:name":"Etcom Gesellschaft F\u00fcr Daten- Techn. Unternehmensberatung",
    "wof:placetype":"venue"
},
  "geometry": {"coordinates":[7.290596,52.660328],"type":"Point"}
}