{
  "type": "Feature",
  "properties": {
    "iso:country":"DE",
    "sg:address":"Flemmingstr. 14",
    "sg:city":"Crossen",
    "sg:phone":"+49 36693/22508",
    "sg:postcode":"07613",
    "sg:province":"Th\u00fcringen",
    "wof:name":"Konsumgenossenschaft Ostth\u00fcringen Eg",
    "wof:placetype":"venue"
},
  "geometry": {"coordinates":[11.9771709442,50.9757728577],"type":"Point"}
}