{
  "type": "Feature",
  "properties": {
    "iso:country":"DE",
    "sg:address":"Dubliner Str. 35",
    "sg:city":"W\u00fcrzburg",
    "sg:phone":"+49 931/69710",
    "sg:postcode":"97084",
    "sg:province":"Bayern",
    "wof:name":"Siegfried Herrmann Gmbh",
    "wof:placetype":"venue"
},
  "geometry": {"coordinates":[9.9515695572,49.7518348694],"type":"Point"}
}