{
  "type": "Feature",
  "properties": {
    "iso:country":"DE",
    "sg:address":"Willy-Brandt-Allee 5",
    "sg:city":"Hannover",
    "sg:phone":"+49 511/9807700",
    "sg:postcode":"30169",
    "sg:province":"Niedersachsen",
    "wof:name":"Nieders\u00e4chsischer Landesverein F\u00fcr Urgeschichte E. V.",
    "wof:placetype":"venue"
},
  "geometry": {"coordinates":[9.739954,52.365505],"type":"Point"}
}