{
  "type": "Feature",
  "properties": {
    "iso:country":"DE",
    "sg:address":"Falterweg 4",
    "sg:city":"Langenfeld",
    "sg:phone":"+49 2173/12210",
    "sg:postcode":"40764",
    "sg:province":"Nordrhein-Westfalen",
    "wof:name":"Ernst Piepereit",
    "wof:placetype":"venue"
},
  "geometry": {"coordinates":[6.979391098,51.0858840942],"type":"Point"}
}