{
  "type": "Feature",
  "properties": {
    "iso:country":"DE",
    "sg:address":"Pr\u00e4lat-Schofer-Str. 1",
    "sg:city":"Ettenheim",
    "sg:phone":"+49 7822/4489610",
    "sg:postcode":"77955",
    "sg:province":"Baden-W\u00fcrttemberg",
    "wof:name":"Fernw\u00e4rme Ettenheim Gmbh",
    "wof:placetype":"venue"
},
  "geometry": {"coordinates":[7.825971,48.25351],"type":"Point"}
}