{
  "type": "Feature",
  "properties": {
    "iso:country":"DE",
    "sg:address":"Bahnhofstr. 21",
    "sg:city":"Gro\u00df-Umstadt",
    "sg:phone":"+49 6078/5665",
    "sg:postcode":"64823",
    "sg:province":"Hessen",
    "wof:name":"Sturmfels",
    "wof:placetype":"venue"
},
  "geometry": {"coordinates":[8.9484024048,49.8890419006],"type":"Point"}
}