{
  "type": "Feature",
  "properties": {
    "iso:country":"DE",
    "sg:address":"Derken 17",
    "sg:city":"Wuppertal",
    "sg:phone":"+49 202/733074",
    "sg:postcode":"42327",
    "sg:province":"Nordrhein-Westfalen",
    "wof:name":"T. Heuke & H. Schmidt",
    "wof:placetype":"venue"
},
  "geometry": {"coordinates":[7.0463199615,51.2280578613],"type":"Point"}
}