{
  "type": "Feature",
  "properties": {
    "iso:country":"DE",
    "sg:address":"C\u00e4cilienstr. 3",
    "sg:city":"Dresden",
    "sg:phone":"+49 351/4424505",
    "sg:postcode":"01219",
    "sg:province":"Sachsen",
    "wof:name":"Volker Von Vogel Rechtsanwalt",
    "wof:placetype":"venue"
},
  "geometry": {"coordinates":[13.7683506012,51.0240898132],"type":"Point"}
}