{
  "type": "Feature",
  "properties": {
    "iso:country":"DE",
    "sg:address":"Melkenweg 57",
    "sg:city":"Bad H\u00f6nningen",
    "sg:phone":"+49 2635/3430",
    "sg:postcode":"53557",
    "sg:province":"Rheinland-Pfalz",
    "wof:name":"Rudolf Weiler",
    "wof:placetype":"venue"
},
  "geometry": {"coordinates":[7.317275,50.514626],"type":"Point"}
}