{
  "type": "Feature",
  "properties": {
    "iso:country":"DE",
    "sg:address":"Albertstr. 7",
    "sg:city":"Thale",
    "sg:postcode":"06502",
    "sg:province":"Sachsen-Anhalt",
    "wof:name":"Troba Gmbh",
    "wof:placetype":"venue"
},
  "geometry": {"coordinates":[11.039645,51.748833],"type":"Point"}
}