{
  "type": "Feature",
  "properties": {
    "iso:country":"DE",
    "sg:address":"Oelkinghauser Str 18",
    "sg:city":"Ennepetal",
    "sg:phone":"+49 2333/98950",
    "sg:postcode":"58256",
    "sg:province":"Nordrhein-Westfalen",
    "wof:name":"St\u00f6rring Satz & Druck Gmbh",
    "wof:placetype":"venue"
},
  "geometry": {"coordinates":[7.325669,51.284958],"type":"Point"}
}