{
  "type": "Feature",
  "properties": {
    "iso:country":"DE",
    "sg:address":"Herkentrup 7",
    "sg:city":"Havixbeck",
    "sg:phone":"+49 2507/9404",
    "sg:postcode":"48329",
    "sg:province":"Nordrhein-Westfalen",
    "wof:name":"Heinrich Weiligmann",
    "wof:placetype":"venue"
},
  "geometry": {"coordinates":[7.454636,51.977924],"type":"Point"}
}