{
  "type": "Feature",
  "properties": {
    "iso:country":"DE",
    "sg:address":"Gro\u00df-Ziethener Str. 68",
    "sg:city":"Berlin",
    "sg:phone":"+49 30/7659290",
    "sg:postcode":"12309",
    "sg:province":"Berlin",
    "wof:name":"Herzog Elektro-anlagen Gmbh",
    "wof:placetype":"venue"
},
  "geometry": {"coordinates":[13.415804,52.394459],"type":"Point"}
}