{
  "type": "Feature",
  "properties": {
    "iso:country":"DE",
    "sg:address":"Vor dem Obertor 2a",
    "sg:city":"Kindelbr\u00fcck",
    "sg:phone":"+49 36375/50407",
    "sg:postcode":"99638",
    "sg:province":"Th\u00fcringen",
    "wof:name":"P. Rausch",
    "wof:placetype":"venue"
},
  "geometry": {"coordinates":[11.087027,51.262321],"type":"Point"}
}