{
  "type": "Feature",
  "properties": {
    "iso:country":"DE",
    "sg:address":"Stephanstr. 46",
    "sg:city":"Bonn",
    "sg:phone":"+49 228/9108441",
    "sg:postcode":"53129",
    "sg:province":"Nordrhein-Westfalen",
    "wof:name":"C. A. M. Stra\u00dfen Und Tiefbau Gmbh",
    "wof:placetype":"venue"
},
  "geometry": {"coordinates":[7.11642313,50.7042427063],"type":"Point"}
}