{
  "type": "Feature",
  "properties": {
    "iso:country":"DE",
    "sg:address":"Wahlstr. 11",
    "sg:city":"Amberg",
    "sg:phone":"+49 9621/33946",
    "sg:postcode":"92224",
    "sg:province":"Bayern",
    "wof:name":"A. Und M. Mayer",
    "wof:placetype":"venue"
},
  "geometry": {"coordinates":[11.8465061188,49.4474029541],"type":"Point"}
}