{
  "type": "Feature",
  "properties": {
    "iso:country":"DE",
    "sg:address":"Leibnizstr. 10",
    "sg:city":"Wolfenb\u00fcttel",
    "sg:postcode":"38300",
    "sg:province":"Niedersachsen",
    "wof:name":"Renta Gmbh Verwaltungsges.",
    "wof:placetype":"venue"
},
  "geometry": {"coordinates":[10.532111,52.164783],"type":"Point"}
}