{
  "type": "Feature",
  "properties": {
    "iso:country":"DE",
    "sg:address":"Schulstr. 6",
    "sg:city":"Mehring",
    "sg:phone":"+49 6502/3967",
    "sg:postcode":"54346",
    "sg:province":"Rheinland-Pfalz",
    "wof:name":"Albert Scholtes Weinanbau",
    "wof:placetype":"venue"
},
  "geometry": {"coordinates":[6.8249249458,49.7962722778],"type":"Point"}
}