{
  "type": "Feature",
  "properties": {
    "iso:country":"DE",
    "sg:address":"Cubanzestr. 5",
    "sg:city":"K\u00fchlungsborn",
    "sg:phone":"+49 38293/17353",
    "sg:postcode":"18225",
    "sg:province":"Mecklenburg-Vorpommern",
    "wof:name":"Hermann Bugar",
    "wof:placetype":"venue"
},
  "geometry": {"coordinates":[11.7540845871,54.1419868469],"type":"Point"}
}