{
  "type": "Feature",
  "properties": {
    "iso:country":"DE",
    "sg:address":"Am Stadtwald 66",
    "sg:city":"Erlenbach",
    "sg:phone":"+49 9372/4440",
    "sg:postcode":"63906",
    "sg:province":"Bayern",
    "wof:name":"Wenzel Bauer Chefkoch",
    "wof:placetype":"venue"
},
  "geometry": {"coordinates":[9.1596069336,49.8045654297],"type":"Point"}
}