{
  "type": "Feature",
  "properties": {
    "iso:country":"DE",
    "sg:address":"Mittelstr. 107",
    "sg:city":"Mannheim",
    "sg:phone":"+49 621/314389",
    "sg:postcode":"68169",
    "sg:province":"Baden-W\u00fcrttemberg",
    "wof:name":"M. Bay",
    "wof:placetype":"venue"
},
  "geometry": {"coordinates":[8.4632329941,49.5014190674],"type":"Point"}
}