{
  "type": "Feature",
  "properties": {
    "iso:country":"DE",
    "sg:address":"Eberhardstr. 20",
    "sg:city":"Friedrichshafen",
    "sg:phone":"+49 7541/72935",
    "sg:postcode":"88046",
    "sg:province":"Baden-W\u00fcrttemberg",
    "wof:name":"Schlo\u00dfbr\u00e4ust\u00fcble",
    "wof:placetype":"venue"
},
  "geometry": {"coordinates":[9.4934892654,47.6529693604],"type":"Point"}
}