{
  "type": "Feature",
  "properties": {
    "iso:country":"DE",
    "sg:address":"Gutenbergstr. 4 d",
    "sg:city":"Erlangen",
    "sg:phone":"+49 9131/65394",
    "sg:postcode":"91058",
    "sg:province":"Bayern",
    "wof:name":"L. Vettermann",
    "wof:placetype":"venue"
},
  "geometry": {"coordinates":[11.00392,49.565788],"type":"Point"}
}