{
  "type": "Feature",
  "properties": {
    "iso:country":"DE",
    "sg:address":"Aschaffstr. 7",
    "sg:city":"Goldbach",
    "sg:phone":"+49 6021/59910",
    "sg:postcode":"63773",
    "sg:province":"Bayern",
    "wof:name":"M. Werner Gmbh",
    "wof:placetype":"venue"
},
  "geometry": {"coordinates":[9.192042,49.998577],"type":"Point"}
}