{
  "type": "Feature",
  "properties": {
    "iso:country":"DE",
    "sg:address":"Bahnhofstr. 31",
    "sg:city":"Betzdorf",
    "sg:phone":"+49 2741/971141",
    "sg:postcode":"57518",
    "sg:province":"Rheinland-Pfalz",
    "wof:name":"Wolfgang Boquoi-kipping",
    "wof:placetype":"venue"
},
  "geometry": {"coordinates":[7.8726000786,50.7883682251],"type":"Point"}
}