{
  "type": "Feature",
  "properties": {
    "iso:country":"DE",
    "sg:address":"Am H\u00f6fchen 7 a",
    "sg:city":"Kaiserslautern",
    "sg:phone":"+49 631/77708",
    "sg:postcode":"67659",
    "sg:province":"Rheinland-Pfalz",
    "wof:name":"C. Schlemmer",
    "wof:placetype":"venue"
},
  "geometry": {"coordinates":[7.766256,49.468685],"type":"Point"}
}