{
  "type": "Feature",
  "properties": {
    "iso:country":"DE",
    "sg:address":"Helmstedter Str. 58 c",
    "sg:city":"Braunschweig",
    "sg:phone":"+49 531/273820",
    "sg:postcode":"38126",
    "sg:province":"Niedersachsen",
    "wof:name":"Aerosol Service Gmbh",
    "wof:placetype":"venue"
},
  "geometry": {"coordinates":[10.593654,52.24984],"type":"Point"}
}