{
  "type": "Feature",
  "properties": {
    "iso:country":"DE",
    "sg:address":"Gottfrieding",
    "sg:city":"Gottfrieding",
    "sg:phone":"+49 8731/6426",
    "sg:postcode":"84177",
    "sg:province":"Bayern",
    "wof:name":"Raiffeisenbank Mamming-hocking Eg",
    "wof:placetype":"venue"
},
  "geometry": {"coordinates":[12.535955,48.638805],"type":"Point"}
}