{
  "type": "Feature",
  "properties": {
    "iso:country":"DE",
    "sg:address":"Schmiedstra\u00dfe 5",
    "sg:city":"Singen",
    "sg:phone":"+49 7731/83840",
    "sg:postcode":"78224",
    "sg:province":"Baden-W\u00fcrttemberg",
    "wof:name":"Whb Gmbh Singen",
    "wof:placetype":"venue"
},
  "geometry": {"coordinates":[8.86762,47.757111],"type":"Point"}
}