{
  "type": "Feature",
  "properties": {
    "iso:country":"DE",
    "sg:address":"Ortsstr. 75",
    "sg:city":"Schlegel",
    "sg:phone":"+49 36642/22621",
    "sg:postcode":"07366",
    "sg:province":"Th\u00fcringen",
    "wof:name":"Hilmar Korn",
    "wof:placetype":"venue"
},
  "geometry": {"coordinates":[11.621733,50.404995],"type":"Point"}
}