{
  "type": "Feature",
  "properties": {
    "iso:country":"DE",
    "sg:address":"Jahnstr. 10",
    "sg:city":"Rathenow",
    "sg:postcode":"14712",
    "sg:province":"Brandenburg",
    "wof:name":"Deutsche Verm\u00f6gensberatung Ag",
    "wof:placetype":"venue"
},
  "geometry": {"coordinates":[12.3490743637,52.6108551025],"type":"Point"}
}