{
  "type": "Feature",
  "properties": {
    "iso:country":"DE",
    "sg:address":"Steinfelder Str. 3",
    "sg:city":"Damme",
    "sg:phone":"+49 5491/4101",
    "sg:postcode":"49401",
    "sg:province":"Niedersachsen",
    "wof:name":"Maria Wellmann Krankengymnastin",
    "wof:placetype":"venue"
},
  "geometry": {"coordinates":[8.201091,52.524017],"type":"Point"}
}