{
  "type": "Feature",
  "properties": {
    "iso:country":"DE",
    "sg:address":"Petersplatz 8",
    "sg:city":"M\u00fcnchen",
    "sg:phone":"+49 89/264469",
    "sg:postcode":"80331",
    "sg:province":"Bayern",
    "wof:name":"Bernis Nudelbrett",
    "wof:placetype":"venue"
},
  "geometry": {"coordinates":[11.5760993958,48.1360206604],"type":"Point"}
}