{
  "type": "Feature",
  "properties": {
    "iso:country":"DE",
    "sg:address":"N\u00fctzenberger Str. 6",
    "sg:city":"Wuppertal",
    "sg:phone":"+49 202/301872",
    "sg:postcode":"42115",
    "sg:province":"Nordrhein-Westfalen",
    "wof:name":"Wolfgang Sennlaub",
    "wof:placetype":"venue"
},
  "geometry": {"coordinates":[7.1312460899,51.2540512085],"type":"Point"}
}