{
  "type": "Feature",
  "properties": {
    "iso:country":"DE",
    "sg:address":"Westerhaar 17",
    "sg:city":"Wickede",
    "sg:phone":"+49 2377/919010",
    "sg:postcode":"58739",
    "sg:province":"Nordrhein-Westfalen",
    "wof:name":"Sat Semer Anlagen Technik Gmbh",
    "wof:placetype":"venue"
},
  "geometry": {"coordinates":[7.873286,51.508018],"type":"Point"}
}