{
  "type": "Feature",
  "properties": {
    "iso:country":"DE",
    "sg:address":"Erich-Weinert-Str. 24",
    "sg:city":"Hoyerswerda",
    "sg:phone":"+49 3571/409541",
    "sg:postcode":"02977",
    "sg:province":"Sachsen",
    "wof:name":"Bernd Kirchh\u00fcbel",
    "wof:placetype":"venue"
},
  "geometry": {"coordinates":[14.2712469101,51.4394950867],"type":"Point"}
}