{
  "type": "Feature",
  "properties": {
    "iso:country":"DE",
    "sg:address":"G\u00fcntherstr. 6",
    "sg:city":"Andernach",
    "sg:phone":"+49 2632/43602",
    "sg:postcode":"56626",
    "sg:province":"Rheinland-Pfalz",
    "wof:name":"Emine Sevinc",
    "wof:placetype":"venue"
},
  "geometry": {"coordinates":[7.4011998177,50.4370613098],"type":"Point"}
}