{
  "type": "Feature",
  "properties": {
    "iso:country":"DE",
    "sg:address":"Schwanseestr. 83",
    "sg:city":"M\u00fcnchen",
    "sg:phone":"+49 89/6903657",
    "sg:postcode":"81549",
    "sg:province":"Bayern",
    "wof:name":"Friedrich Rutz",
    "wof:placetype":"venue"
},
  "geometry": {"coordinates":[11.597586,48.103035],"type":"Point"}
}