{
  "type": "Feature",
  "properties": {
    "iso:country":"DE",
    "sg:address":"Kochelseestr. 11",
    "sg:city":"M\u00fcnchen",
    "sg:phone":"+49 89/7463330",
    "sg:postcode":"81371",
    "sg:province":"Bayern",
    "wof:name":"Antonio Calzoni",
    "wof:placetype":"venue"
},
  "geometry": {"coordinates":[11.5524806976,48.118434906],"type":"Point"}
}