{
  "type": "Feature",
  "properties": {
    "iso:country":"DE",
    "sg:address":"Ostlandstr. 2",
    "sg:city":"F\u00fcrstenau",
    "sg:phone":"+49 5901/2790",
    "sg:postcode":"49584",
    "sg:province":"Niedersachsen",
    "wof:name":"Willi Glasmeyer Bildhauer",
    "wof:placetype":"venue"
},
  "geometry": {"coordinates":[7.685371,52.515411],"type":"Point"}
}