{
  "type": "Feature",
  "properties": {
    "iso:country":"DE",
    "sg:address":"Hospitalstr. 6-8",
    "sg:city":"Billerbeck",
    "sg:phone":"+49 2543/23020",
    "sg:postcode":"48727",
    "sg:province":"Nordrhein-Westfalen",
    "wof:name":"Stiftung St. Ludgerus",
    "wof:placetype":"venue"
},
  "geometry": {"coordinates":[7.2897181511,51.9744720459],"type":"Point"}
}