{
  "type": "Feature",
  "properties": {
    "iso:country":"DE",
    "sg:address":"Diebrocker Str. 2",
    "sg:city":"Herford",
    "sg:phone":"+49 5221/4272",
    "sg:postcode":"32051",
    "sg:province":"Nordrhein-Westfalen",
    "wof:name":"B 7",
    "wof:placetype":"venue"
},
  "geometry": {"coordinates":[8.6611318588,52.1179199219],"type":"Point"}
}