{
  "type": "Feature",
  "properties": {
    "iso:country":"DE",
    "sg:address":"K\u00f6nigsheide 59",
    "sg:city":"L\u00fcnen",
    "sg:phone":"+49 231/872617",
    "sg:postcode":"44536",
    "sg:province":"Nordrhein-Westfalen",
    "wof:name":"El Greco",
    "wof:placetype":"venue"
},
  "geometry": {"coordinates":[7.4464797974,51.5970993042],"type":"Point"}
}