{
  "type": "Feature",
  "properties": {
    "iso:country":"DE",
    "sg:address":"Bachstr. 4",
    "sg:city":"Bahlingen",
    "sg:phone":"+49 7663/5751",
    "sg:postcode":"79353",
    "sg:province":"Baden-W\u00fcrttemberg",
    "wof:name":"Albert Sommer",
    "wof:placetype":"venue"
},
  "geometry": {"coordinates":[7.7388,48.123035],"type":"Point"}
}