{
  "type": "Feature",
  "properties": {
    "iso:country":"DE",
    "sg:address":"Zeller Str. 7",
    "sg:city":"Holzmaden",
    "sg:phone":"+49 7023/909540",
    "sg:postcode":"73271",
    "sg:province":"Baden-W\u00fcrttemberg",
    "wof:name":"Bleher Gmbh",
    "wof:placetype":"venue"
},
  "geometry": {"coordinates":[9.5285711288,48.6380195618],"type":"Point"}
}