{
  "type": "Feature",
  "properties": {
    "iso:country":"DE",
    "sg:address":"K\u00f6thener Str 8",
    "sg:city":"Landsberg",
    "sg:phone":"+49 34602/21806",
    "sg:postcode":"06188",
    "sg:province":"Sachsen-Anhalt",
    "wof:name":"Imontec Elektrotechnik Landsberg Gmbh",
    "wof:placetype":"venue"
},
  "geometry": {"coordinates":[12.157632,51.53093],"type":"Point"}
}