{
  "type": "Feature",
  "properties": {
    "iso:country":"DE",
    "sg:address":"Atterstr. 86",
    "sg:city":"Osnabr\u00fcck",
    "sg:phone":"+49 541/123567",
    "sg:postcode":"49090",
    "sg:province":"Niedersachsen",
    "wof:name":"Kroka-m\u00f6bel Inh. Karin Klausing",
    "wof:placetype":"venue"
},
  "geometry": {"coordinates":[8.005351,52.299541],"type":"Point"}
}