{
  "type": "Feature",
  "properties": {
    "iso:country":"DE",
    "sg:address":"Itzgrund 20",
    "sg:city":"Neudrossenfeld",
    "sg:phone":"+49 9203/314",
    "sg:postcode":"95512",
    "sg:province":"Bayern",
    "wof:name":"Joachim Heinz Architekt",
    "wof:placetype":"venue"
},
  "geometry": {"coordinates":[11.496449,50.015636],"type":"Point"}
}