{
  "type": "Feature",
  "properties": {
    "iso:country":"DE",
    "sg:address":"Wendelinusstr. 65",
    "sg:city":"Eschweiler",
    "sg:phone":"+49 2403/37269",
    "sg:postcode":"52249",
    "sg:province":"Nordrhein-Westfalen",
    "wof:name":"Wolfgang Felkel Heizung Sanitaer",
    "wof:placetype":"venue"
},
  "geometry": {"coordinates":[6.2890329361,50.7924575806],"type":"Point"}
}