{
  "type": "Feature",
  "properties": {
    "iso:country":"DE",
    "sg:address":"Hallesche Str. 50",
    "sg:city":"Bernburg",
    "sg:phone":"+49 3471/624282",
    "sg:postcode":"06406",
    "sg:province":"Sachsen-Anhalt",
    "wof:name":"Kirsten Wieduwilt",
    "wof:placetype":"venue"
},
  "geometry": {"coordinates":[11.740599,51.790092],"type":"Point"}
}