{
  "type": "Feature",
  "properties": {
    "iso:country":"DE",
    "sg:address":"Friedrich-Linke-Str. 1",
    "sg:city":"Hirschfelde",
    "sg:postcode":"02788",
    "sg:province":"Sachsen",
    "wof:name":"Peter Neugebauer",
    "wof:placetype":"venue"
},
  "geometry": {"coordinates":[14.88591,50.943218],"type":"Point"}
}