{
  "type": "Feature",
  "properties": {
    "iso:country":"DE",
    "sg:address":"Am See",
    "sg:city":"H\u00f6chst",
    "sg:phone":"+49 6163/7080",
    "sg:postcode":"64739",
    "sg:province":"Hessen",
    "wof:name":"Gemeindearchiv",
    "wof:placetype":"venue"
},
  "geometry": {"coordinates":[8.997854,49.801506],"type":"Point"}
}