{
  "type": "Feature",
  "properties": {
    "iso:country":"DE",
    "sg:address":"Hedderichstr. 47",
    "sg:city":"Frankfurt",
    "sg:phone":"+49 69/623065",
    "sg:postcode":"60594",
    "sg:province":"Hessen",
    "wof:name":"Peter Powalla",
    "wof:placetype":"venue"
},
  "geometry": {"coordinates":[8.6866769791,50.100315094],"type":"Point"}
}