{
  "type": "Feature",
  "properties": {
    "iso:country":"DE",
    "sg:city":"Alfdorf",
    "sg:postcode":"73553",
    "sg:province":"Baden-W\u00fcrttemberg",
    "wof:name":"Baybo-bau Gmbh",
    "wof:placetype":"venue"
},
  "geometry": {"coordinates":[9.719763,48.843151],"type":"Point"}
}