{
  "type": "Feature",
  "properties": {
    "iso:country":"DE",
    "sg:address":"Walsroder Weg 18",
    "sg:city":"D\u00fcsseldorf",
    "sg:phone":"+49 211/411425",
    "sg:postcode":"40468",
    "sg:province":"Nordrhein-Westfalen",
    "wof:name":"Slide-o-mix K\u00f6nigs Gmbh",
    "wof:placetype":"venue"
},
  "geometry": {"coordinates":[6.7847628593,51.268913269],"type":"Point"}
}