{
  "type": "Feature",
  "properties": {
    "iso:country":"DE",
    "sg:address":"Von-Th\u00fcrheim-Str. 69",
    "sg:city":"Wei\u00dfenhorn",
    "sg:phone":"+49 7309/425887",
    "sg:postcode":"89264",
    "sg:province":"Bayern",
    "wof:name":"Josef Weltle Jun. E. K. Inhaber J\u00fcrgen Angerer",
    "wof:placetype":"venue"
},
  "geometry": {"coordinates":[10.2147264481,48.318572998],"type":"Point"}
}