{
  "type": "Feature",
  "properties": {
    "iso:country":"DE",
    "sg:address":"Tonnaer Str. 35",
    "sg:city":"Bad Langensalza",
    "sg:phone":"+49 3603/842658",
    "sg:postcode":"99947",
    "sg:province":"Th\u00fcringen",
    "wof:name":"Rudolf Birkhan",
    "wof:placetype":"venue"
},
  "geometry": {"coordinates":[10.659255,51.105179],"type":"Point"}
}