{
  "type": "Feature",
  "properties": {
    "iso:country":"DE",
    "sg:address":"Gartenstr. 3",
    "sg:city":"Satteldorf",
    "sg:phone":"+49 7951/5940",
    "sg:postcode":"74589",
    "sg:province":"Baden-W\u00fcrttemberg",
    "wof:name":"Wohnbau-sch\u00e4ufele Gmbh",
    "wof:placetype":"venue"
},
  "geometry": {"coordinates":[10.081234,49.16967],"type":"Point"}
}