{
  "type": "Feature",
  "properties": {
    "iso:country":"DE",
    "sg:address":"Aisinger Str. 82",
    "sg:city":"Rosenheim",
    "sg:phone":"+49 8031/66482",
    "sg:postcode":"83026",
    "sg:province":"Bayern",
    "wof:name":"Dario Gro\u00df- Und Einzelhandel Teppichboden Gmbh",
    "wof:placetype":"venue"
},
  "geometry": {"coordinates":[12.1127414703,47.8341407776],"type":"Point"}
}