{
  "type": "Feature",
  "properties": {
    "iso:country":"DE",
    "sg:address":"Joseph-Haydn-Str. 14",
    "sg:city":"Waldkraiburg",
    "sg:phone":"+49 8638/3690",
    "sg:postcode":"84478",
    "sg:province":"Bayern",
    "wof:name":"Georg Duschl Baubetreuungs-gmbh",
    "wof:placetype":"venue"
},
  "geometry": {"coordinates":[12.4171419144,48.2069892883],"type":"Point"}
}