{
  "type": "Feature",
  "properties": {
    "iso:country":"DE",
    "sg:address":"R\u00f6\u00dflegasse 6",
    "sg:city":"Friesenheim",
    "sg:phone":"+49 7821/67324",
    "sg:postcode":"77948",
    "sg:province":"Baden-W\u00fcrttemberg",
    "wof:name":"Klaus Schubnell Steuerberater",
    "wof:placetype":"venue"
},
  "geometry": {"coordinates":[7.8756561279,48.3728370667],"type":"Point"}
}