{
  "type": "Feature",
  "properties": {
    "iso:country":"DE",
    "sg:address":"Mahdenstr. 11",
    "sg:city":"Kirchentellinsfurt",
    "sg:phone":"+49 7121/909280",
    "sg:postcode":"72138",
    "sg:province":"Baden-W\u00fcrttemberg",
    "wof:name":"Sch\u00fcschke Gmbh & Co. Kg",
    "wof:placetype":"venue"
},
  "geometry": {"coordinates":[9.16913,48.541553],"type":"Point"}
}