{
  "type": "Feature",
  "properties": {
    "iso:country":"DE",
    "sg:address":"Winkel 13",
    "sg:city":"Geeste",
    "sg:phone":"+49 5937/970663",
    "sg:postcode":"49744",
    "sg:province":"Niedersachsen",
    "wof:name":"Der Vgl K\u00fcnstlertreff",
    "wof:placetype":"venue"
},
  "geometry": {"coordinates":[7.206774,52.563293],"type":"Point"}
}