{
  "type": "Feature",
  "properties": {
    "iso:country":"DE",
    "sg:address":"riemenstr. 564",
    "sg:city":"vs-schwenningen",
    "sg:phone":"+49 8130/95",
    "sg:postcode":"78054",
    "sg:province":"Baden-W\u00fcrttemberg",
    "wof:name":"Sexvideos Erotikvideos Erotik Sex Videos",
    "wof:placetype":"venue"
},
  "geometry": {"coordinates":[-98.690697,29.325199],"type":"Point"}
}