{
  "type": "Feature",
  "properties": {
    "iso:country":"DE",
    "sg:address":"Borsigkehre 11",
    "sg:city":"Quickborn",
    "sg:phone":"+49 4106/761340",
    "sg:postcode":"25451",
    "sg:province":"Schleswig-Holstein",
    "wof:name":"Archiv-zentrale-nord Gmbh",
    "wof:placetype":"venue"
},
  "geometry": {"coordinates":[9.93568,53.74625],"type":"Point"}
}