{
  "type": "Feature",
  "properties": {
    "iso:country":"DE",
    "sg:address":"Richard-Wagner-Str. 90",
    "sg:city":"Geretsried",
    "sg:phone":"+49 8171/5453",
    "sg:postcode":"82538",
    "sg:province":"Bayern",
    "wof:name":"Rudi Radler Aral Tankstelle",
    "wof:placetype":"venue"
},
  "geometry": {"coordinates":[11.4767599106,47.8496360779],"type":"Point"}
}