{
  "type": "Feature",
  "properties": {
    "iso:country":"DE",
    "sg:address":"Heubnerstr. 7",
    "sg:city":"Lutherstadt Wittenberg",
    "sg:phone":"+49 3491/401805",
    "sg:postcode":"06886",
    "sg:province":"Sachsen-Anhalt",
    "wof:name":"M. Kettenbeil",
    "wof:placetype":"venue"
},
  "geometry": {"coordinates":[12.6521749496,51.8690834045],"type":"Point"}
}