{
  "type": "Feature",
  "properties": {
    "iso:country":"DE",
    "sg:address":"Neuer Weg 6",
    "sg:city":"Dahlem",
    "sg:phone":"+49 6557/361",
    "sg:postcode":"53949",
    "sg:province":"Nordrhein-Westfalen",
    "wof:name":"P. K\u00f6ller",
    "wof:placetype":"venue"
},
  "geometry": {"coordinates":[6.476753,50.360241],"type":"Point"}
}