{
  "type": "Feature",
  "properties": {
    "iso:country":"DE",
    "sg:address":"Neuer Wall 75",
    "sg:city":"Hamburg",
    "sg:postcode":"20354",
    "sg:province":"Hamburg",
    "wof:name":"Finnigan Mat Gmbh",
    "wof:placetype":"venue"
},
  "geometry": {"coordinates":[9.98686,53.549919],"type":"Point"}
}