{
  "type": "Feature",
  "properties": {
    "iso:country":"DE",
    "sg:address":"Hammerst\u00e4ttle 2",
    "sg:city":"Horb",
    "sg:phone":"+49 7482/1373",
    "sg:postcode":"72160",
    "sg:province":"Baden-W\u00fcrttemberg",
    "wof:name":"Berthold Hinger K\u00fcchenvertriebs Gmbh",
    "wof:placetype":"venue"
},
  "geometry": {"coordinates":[8.634557,48.416752],"type":"Point"}
}