{
  "type": "Feature",
  "properties": {
    "iso:country":"DE",
    "sg:address":"Bahngel\u00e4nde 11a",
    "sg:city":"Hersbruck",
    "sg:phone":"+49 9151/81870",
    "sg:postcode":"91217",
    "sg:province":"Bayern",
    "wof:name":"Hans Hirschmann Mineral\u00f6l-handelsges. Mbh",
    "wof:placetype":"venue"
},
  "geometry": {"coordinates":[11.420073,49.508877],"type":"Point"}
}