{
  "type": "Feature",
  "properties": {
    "iso:country":"DE",
    "sg:address":"Kolberger Platz 4",
    "sg:city":"Berlin",
    "sg:phone":"+49 30/8261574",
    "sg:postcode":"14199",
    "sg:province":"Berlin",
    "wof:name":"Karin Grunwald",
    "wof:placetype":"venue"
},
  "geometry": {"coordinates":[13.2901563644,52.4770698547],"type":"Point"}
}