{
  "type": "Feature",
  "properties": {
    "iso:country":"DE",
    "sg:address":"Eisenacher Str. 1",
    "sg:city":"Philippsthal",
    "sg:phone":"+49 6620/919000",
    "sg:postcode":"36269",
    "sg:province":"Hessen",
    "wof:name":"Peter Heurich Gmbh",
    "wof:placetype":"venue"
},
  "geometry": {"coordinates":[9.954811,50.854576],"type":"Point"}
}