{
  "type": "Feature",
  "properties": {
    "iso:country":"DE",
    "sg:address":"Herrenstr. 3a",
    "sg:city":"Freinsheim",
    "sg:phone":"+49 6353/2784",
    "sg:postcode":"67251",
    "sg:province":"Rheinland-Pfalz",
    "wof:name":"Petra Altherr",
    "wof:placetype":"venue"
},
  "geometry": {"coordinates":[8.2131729126,49.50730896],"type":"Point"}
}