{
  "type": "Feature",
  "properties": {
    "iso:country":"DE",
    "sg:address":"Sch\u00fctzenrain 15",
    "sg:city":"Friedberg",
    "sg:phone":"+49 6031/4488",
    "sg:postcode":"61169",
    "sg:province":"Hessen",
    "wof:name":"Psycho-soz. Beratungs- U. Behandlungsstelle Des",
    "wof:placetype":"venue"
},
  "geometry": {"coordinates":[8.755918,50.332031],"type":"Point"}
}