{
  "type": "Feature",
  "properties": {
    "iso:country":"DE",
    "sg:address":"Waldstr. 20 a",
    "sg:city":"Altenstadt",
    "sg:phone":"+49 6047/4843",
    "sg:postcode":"63674",
    "sg:province":"Hessen",
    "wof:name":"Becker Und Ga\u00dfmann",
    "wof:placetype":"venue"
},
  "geometry": {"coordinates":[8.9628982544,50.267414093],"type":"Point"}
}