{
  "type": "Feature",
  "properties": {
    "iso:country":"DE",
    "sg:address":"Altonaer Str. 390c",
    "sg:city":"Halstenbek",
    "sg:phone":"+49 4101/34349",
    "sg:postcode":"25469",
    "sg:province":"Schleswig-Holstein",
    "wof:name":"Herbert Borchert",
    "wof:placetype":"venue"
},
  "geometry": {"coordinates":[9.87321,53.626839],"type":"Point"}
}