{
  "type": "Feature",
  "properties": {
    "iso:country":"DE",
    "sg:address":"Ruhlander Str. 23",
    "sg:city":"Schwarzheide",
    "sg:phone":"+49 35752/8640",
    "sg:postcode":"01987",
    "sg:province":"Brandenburg",
    "wof:name":"Wolfgang Hofmann Und Kerstin Herzog",
    "wof:placetype":"venue"
},
  "geometry": {"coordinates":[13.8430128098,51.4827651978],"type":"Point"}
}