{
  "type": "Feature",
  "properties": {
    "iso:country":"DE",
    "sg:address":"Bl\u00fccherstr. 7",
    "sg:city":"Bonn",
    "sg:phone":"+49 228/219978",
    "sg:postcode":"53115",
    "sg:province":"Nordrhein-Westfalen",
    "wof:name":"R. Schweitzer Architekten",
    "wof:placetype":"venue"
},
  "geometry": {"coordinates":[7.094462,50.721741],"type":"Point"}
}