{
  "type": "Feature",
  "properties": {
    "iso:country":"DE",
    "sg:address":"Holm 39",
    "sg:city":"Flensburg",
    "sg:phone":"+49 461/21666",
    "sg:postcode":"24937",
    "sg:province":"Schleswig-Holstein",
    "wof:name":"Milano Lederwaren Inh. Detlev Meissner",
    "wof:placetype":"venue"
},
  "geometry": {"coordinates":[9.43588,54.784225],"type":"Point"}
}