{
  "type": "Feature",
  "properties": {
    "iso:country":"DE",
    "sg:address":"Adebarweg 30",
    "sg:city":"Hamburg",
    "sg:postcode":"22559",
    "sg:province":"Hamburg",
    "wof:name":"Eberswalder Holz- Veredelung Gmbh",
    "wof:placetype":"venue"
},
  "geometry": {"coordinates":[9.7439565659,53.5835227966],"type":"Point"}
}