{
  "type": "Feature",
  "properties": {
    "iso:country":"DE",
    "sg:address":"Osterstr. 80",
    "sg:city":"Hamburg",
    "sg:phone":"+49 40/73679088",
    "sg:postcode":"20259",
    "sg:province":"Hamburg",
    "wof:name":"Krishna Enterprises Import- Export Inh. Kuppu Swami Suresh",
    "wof:placetype":"venue"
},
  "geometry": {"coordinates":[9.9545669556,53.5757064819],"type":"Point"}
}