{
  "type": "Feature",
  "properties": {
    "iso:country":"DE",
    "sg:address":"Lindenstr. 27",
    "sg:city":"Thallwitz",
    "sg:phone":"+49 34263/41647",
    "sg:postcode":"04808",
    "sg:province":"Sachsen",
    "wof:name":"Siegfried Walter",
    "wof:placetype":"venue"
},
  "geometry": {"coordinates":[12.782959,51.45578],"type":"Point"}
}