{
  "type": "Feature",
  "properties": {
    "iso:country":"DE",
    "sg:address":"Lohm\u00fchlenstr. 1",
    "sg:city":"Hamburg",
    "sg:phone":"+49 40/4505520",
    "sg:postcode":"20099",
    "sg:province":"Hamburg",
    "wof:name":"Weber Immobilienmakler",
    "wof:placetype":"venue"
},
  "geometry": {"coordinates":[10.0141658783,53.5608673096],"type":"Point"}
}