{
  "type": "Feature",
  "properties": {
    "iso:country":"DE",
    "sg:address":"Im Weidig 14",
    "sg:city":"M\u00fcnnerstadt",
    "sg:phone":"+49 9733/9217",
    "sg:postcode":"97702",
    "sg:province":"Bayern",
    "wof:name":"O. Brodesser",
    "wof:placetype":"venue"
},
  "geometry": {"coordinates":[10.1511468887,50.2599105835],"type":"Point"}
}