{
  "type": "Feature",
  "properties": {
    "iso:country":"DE",
    "sg:address":"Eckertswehr 16",
    "sg:city":"Kreuztal",
    "sg:phone":"+49 2732/582030",
    "sg:postcode":"57223",
    "sg:province":"Nordrhein-Westfalen",
    "wof:name":"Klaus M\u00fcller Heilpraktiker",
    "wof:placetype":"venue"
},
  "geometry": {"coordinates":[8.0416669846,50.9640197754],"type":"Point"}
}