{
  "type": "Feature",
  "properties": {
    "iso:country":"DE",
    "sg:address":"Obere Muldenstr. 111",
    "sg:city":"Glauchau",
    "sg:phone":"+49 3763/12137",
    "sg:postcode":"08371",
    "sg:province":"Sachsen",
    "wof:name":"J\u00fcrgen G\u00fcnther",
    "wof:placetype":"venue"
},
  "geometry": {"coordinates":[12.5390396118,50.8269195557],"type":"Point"}
}