{
  "type": "Feature",
  "properties": {
    "iso:country":"DE",
    "sg:address":"Obernstr. 14",
    "sg:city":"Bremen",
    "sg:phone":"+49 421/335610",
    "sg:postcode":"28195",
    "sg:province":"Bremen",
    "wof:name":"Hanseatische Leasing Gmbh",
    "wof:placetype":"venue"
},
  "geometry": {"coordinates":[8.806061,53.076717],"type":"Point"}
}