{
  "type": "Feature",
  "properties": {
    "iso:country":"DE",
    "sg:address":"Kirchstr. 56",
    "sg:city":"Waldfeucht",
    "sg:phone":"+49 2455/612",
    "sg:postcode":"52525",
    "sg:province":"Nordrhein-Westfalen",
    "wof:name":"Heinz Goertz",
    "wof:placetype":"venue"
},
  "geometry": {"coordinates":[5.991239,51.054424],"type":"Point"}
}