{
  "type": "Feature",
  "properties": {
    "iso:country":"DE",
    "sg:address":"Am Kirchplatz 17",
    "sg:city":"Gl\u00fcckstadt",
    "sg:phone":"+49 4124/2621",
    "sg:postcode":"25348",
    "sg:province":"Schleswig-Holstein",
    "wof:name":"Max Berg",
    "wof:placetype":"venue"
},
  "geometry": {"coordinates":[9.425106,53.787807],"type":"Point"}
}