{
  "type": "Feature",
  "properties": {
    "iso:country":"DE",
    "sg:address":"Hauptstr. 77",
    "sg:city":"Fr\u00f6ndenberg",
    "sg:phone":"+49 2378/910035",
    "sg:postcode":"58730",
    "sg:province":"Nordrhein-Westfalen",
    "wof:name":"Elektro Hering Gmbh",
    "wof:placetype":"venue"
},
  "geometry": {"coordinates":[7.694861,51.478237],"type":"Point"}
}