{
  "type": "Feature",
  "properties": {
    "iso:country":"DE",
    "sg:address":"Rhododendronstr. 55",
    "sg:city":"Wiesmoor",
    "sg:phone":"+49 4944/35724",
    "sg:postcode":"26639",
    "sg:province":"Niedersachsen",
    "wof:name":"Iris Blumenzauber",
    "wof:placetype":"venue"
},
  "geometry": {"coordinates":[7.73624,53.382648],"type":"Point"}
}