{
  "type": "Feature",
  "properties": {
    "iso:country":"DE",
    "sg:address":"Westbahnhofstr. 22a",
    "sg:city":"Mayen",
    "sg:phone":"+49 2651/76264",
    "sg:postcode":"56727",
    "sg:province":"Rheinland-Pfalz",
    "wof:name":"Studio-doris",
    "wof:placetype":"venue"
},
  "geometry": {"coordinates":[7.216023922,50.3283119202],"type":"Point"}
}