{
  "type": "Feature",
  "properties": {
    "iso:country":"DE",
    "sg:address":"Am Eichenwald 15",
    "sg:city":"Lichtenstein",
    "sg:postcode":"09350",
    "sg:province":"Sachsen",
    "wof:name":"Druckservice Albrecht Schirmer",
    "wof:placetype":"venue"
},
  "geometry": {"coordinates":[12.6347703934,50.754108429],"type":"Point"}
}