{
  "type": "Feature",
  "properties": {
    "iso:country":"DE",
    "sg:address":"Deichreihe 3",
    "sg:city":"Haseldorf",
    "sg:phone":"+49 4129/253",
    "sg:postcode":"25489",
    "sg:province":"Schleswig-Holstein",
    "wof:name":"Hans-joachim Schuldt",
    "wof:placetype":"venue"
},
  "geometry": {"coordinates":[9.5893449783,53.6383018494],"type":"Point"}
}