{
  "type": "Feature",
  "properties": {
    "iso:country":"DE",
    "sg:address":"Marienstr. 32 a",
    "sg:city":"Fulda",
    "sg:phone":"+49 661/75654",
    "sg:postcode":"36039",
    "sg:province":"Hessen",
    "wof:name":"Oskar Wehner Steuerbevollm\u00e4chtigter",
    "wof:placetype":"venue"
},
  "geometry": {"coordinates":[9.6642456055,50.5619392395],"type":"Point"}
}