{
  "type": "Feature",
  "properties": {
    "iso:country":"DE",
    "sg:address":"Jabeler Chaussee 1",
    "sg:city":"Wittstock",
    "sg:postcode":"16909",
    "sg:province":"Brandenburg",
    "wof:name":"Agro- Handels- Beteiligungs- Und Verwaltungs Gmbh",
    "wof:placetype":"venue"
},
  "geometry": {"coordinates":[12.46336,53.160923],"type":"Point"}
}