{
  "type": "Feature",
  "properties": {
    "iso:country":"DE",
    "sg:address":"Rudolf-Breitscheid-Str. 7",
    "sg:city":"Bremen",
    "sg:phone":"+49 421/602330",
    "sg:postcode":"28779",
    "sg:province":"Bremen",
    "wof:name":"K. N\u00f6ding",
    "wof:placetype":"venue"
},
  "geometry": {"coordinates":[8.578325,53.18589],"type":"Point"}
}