{
  "type": "Feature",
  "properties": {
    "iso:country":"DE",
    "sg:address":"Hans-B\u00f6ckler-Allee 13b",
    "sg:city":"Aachen",
    "sg:phone":"+49 241/870066",
    "sg:postcode":"52074",
    "sg:province":"Nordrhein-Westfalen",
    "wof:name":"C. Schumann",
    "wof:placetype":"venue"
},
  "geometry": {"coordinates":[6.034072,50.773823],"type":"Point"}
}