{
  "type": "Feature",
  "properties": {
    "iso:country":"DE",
    "sg:address":"Klingenweg 14",
    "sg:city":"Wertheim",
    "sg:phone":"+49 9342/6219",
    "sg:postcode":"97877",
    "sg:province":"Baden-W\u00fcrttemberg",
    "wof:name":"H. Sadowski Drescherei",
    "wof:placetype":"venue"
},
  "geometry": {"coordinates":[9.4556,49.739944],"type":"Point"}
}