{
  "type": "Feature",
  "properties": {
    "iso:country":"DE",
    "sg:address":"Paulinenstr. 9",
    "sg:city":"Blankenhain",
    "sg:phone":"+49 36459/40704",
    "sg:postcode":"99444",
    "sg:province":"Th\u00fcringen",
    "wof:name":"Frisch Back Gmbh",
    "wof:placetype":"venue"
},
  "geometry": {"coordinates":[11.345216,50.857044],"type":"Point"}
}