{
  "type": "Feature",
  "properties": {
    "iso:country":"DE",
    "sg:address":"Rotenh\u00e4user Str. 30",
    "sg:city":"Hamburg",
    "sg:phone":"+49 40/757005",
    "sg:postcode":"21109",
    "sg:province":"Hamburg",
    "wof:name":"Heidi Compahn",
    "wof:placetype":"venue"
},
  "geometry": {"coordinates":[10.00005,53.50592],"type":"Point"}
}