{
  "type": "Feature",
  "properties": {
    "iso:country":"DE",
    "sg:address":"Waldstr. 15",
    "sg:city":"Ostseebad Prerow",
    "sg:postcode":"18375",
    "sg:province":"Mecklenburg-Vorpommern",
    "wof:name":"Dar\u00dflichtspiele",
    "wof:placetype":"venue"
},
  "geometry": {"coordinates":[12.568381,54.447422],"type":"Point"}
}