{
  "type": "Feature",
  "properties": {
    "iso:country":"DE",
    "sg:address":"Glienicker Weg 125-127",
    "sg:city":"Berlin",
    "sg:phone":"+49 30/67070",
    "sg:postcode":"12489",
    "sg:province":"Berlin",
    "wof:name":"Berlin-chemie Ag",
    "wof:placetype":"venue"
},
  "geometry": {"coordinates":[13.5567712784,52.4339065552],"type":"Point"}
}