{
  "type": "Feature",
  "properties": {
    "iso:country":"DE",
    "sg:address":"Am Markt 22",
    "sg:city":"Eppelborn",
    "sg:phone":"+49 6881/8501",
    "sg:postcode":"66571",
    "sg:province":"Saarland",
    "wof:name":"Aktiv Sportstudio",
    "wof:placetype":"venue"
},
  "geometry": {"coordinates":[6.9686288834,49.4082374573],"type":"Point"}
}