{
  "type": "Feature",
  "properties": {
    "iso:country":"DE",
    "sg:address":"Rheinstr. 6",
    "sg:city":"Kleve",
    "sg:phone":"+49 2821/92215",
    "sg:postcode":"47533",
    "sg:province":"Nordrhein-Westfalen",
    "wof:name":"Johannes Van Koeverden",
    "wof:placetype":"venue"
},
  "geometry": {"coordinates":[6.166483,51.823765],"type":"Point"}
}