{
  "type": "Feature",
  "properties": {
    "iso:country":"DE",
    "sg:address":"Neue Str. 17 a",
    "sg:city":"Markt Erlbach",
    "sg:phone":"+49 9106/92760",
    "sg:postcode":"91459",
    "sg:province":"Bayern",
    "wof:name":"Heffner & M\u00fcller Wohn- Und Gewerbebau Gmbh",
    "wof:placetype":"venue"
},
  "geometry": {"coordinates":[10.655602,49.492275],"type":"Point"}
}