{
  "type": "Feature",
  "properties": {
    "iso:country":"DE",
    "sg:address":"Dorf-G\u00fcller-Str. 49",
    "sg:city":"Pohlheim",
    "sg:phone":"+49 6404/1386",
    "sg:postcode":"35415",
    "sg:province":"Hessen",
    "wof:name":"Elena Zakel",
    "wof:placetype":"venue"
},
  "geometry": {"coordinates":[8.7536706924,50.5331497192],"type":"Point"}
}