{
  "type": "Feature",
  "properties": {
    "iso:country":"DE",
    "sg:address":"Gebr-Batscheider-Str 4",
    "sg:city":"Oberhaching",
    "sg:phone":"+49 89/6130470",
    "sg:postcode":"82041",
    "sg:province":"Bayern",
    "wof:name":"Rk-betreuungsgesellschaft Mbh",
    "wof:placetype":"venue"
},
  "geometry": {"coordinates":[11.585994,48.023506],"type":"Point"}
}