{
  "type": "Feature",
  "properties": {
    "iso:country":"DE",
    "sg:address":"Br\u00fcckenstr. 10",
    "sg:city":"Ha\u00dffurt",
    "sg:phone":"+49 9521/1541",
    "sg:postcode":"97437",
    "sg:province":"Bayern",
    "wof:name":"Heinrich J\u00fcngling",
    "wof:placetype":"venue"
},
  "geometry": {"coordinates":[10.506724,50.030891],"type":"Point"}
}