{
  "type": "Feature",
  "properties": {
    "iso:country":"DE",
    "sg:address":"Hauptstr. 521",
    "sg:city":"Saterland",
    "sg:phone":"+49 4498/7283",
    "sg:postcode":"26683",
    "sg:province":"Niedersachsen",
    "wof:name":"Rudolf Schulte",
    "wof:placetype":"venue"
},
  "geometry": {"coordinates":[7.6710939407,53.1042747498],"type":"Point"}
}