{
  "type": "Feature",
  "properties": {
    "iso:country":"DE",
    "sg:address":"Westring 75",
    "sg:city":"Mainz",
    "sg:phone":"+49 6131/684676",
    "sg:postcode":"55120",
    "sg:province":"Rheinland-Pfalz",
    "wof:name":"Heinz Pr\u00fcstel Kunstmaler",
    "wof:placetype":"venue"
},
  "geometry": {"coordinates":[8.216722,50.014133],"type":"Point"}
}