{
  "type": "Feature",
  "properties": {
    "iso:country":"DE",
    "sg:address":"Alte Hauptstra\u00dfe 15",
    "sg:city":"Stolpen",
    "sg:phone":"+49 35973/28340",
    "sg:postcode":"01833",
    "sg:province":"Sachsen",
    "wof:name":"Tierservice.com Info-center & Online-shop F\u00fcr Tierfreunde",
    "wof:placetype":"venue"
},
  "geometry": {"coordinates":[14.065990448,51.0611457825],"type":"Point"}
}