{
  "type": "Feature",
  "properties": {
    "iso:country":"DE",
    "sg:address":"Marktstr. 90",
    "sg:city":"Remagen",
    "sg:phone":"+49 2642/23194",
    "sg:postcode":"53424",
    "sg:province":"Rheinland-Pfalz",
    "wof:name":"Klaus Klute",
    "wof:placetype":"venue"
},
  "geometry": {"coordinates":[7.2293720245,50.5791931152],"type":"Point"}
}