{
  "type": "Feature",
  "properties": {
    "iso:country":"DE",
    "sg:address":"Hansestr. 19",
    "sg:city":"Bentwisch",
    "sg:phone":"+49 381/6867980",
    "sg:postcode":"18182",
    "sg:province":"Mecklenburg-Vorpommern",
    "wof:name":"Nat\u00fcrlich Stein Gmbh",
    "wof:placetype":"venue"
},
  "geometry": {"coordinates":[12.1833324432,54.1170501709],"type":"Point"}
}