{
  "type": "Feature",
  "properties": {
    "iso:country":"DE",
    "sg:address":"M\u00fchlstr. 11",
    "sg:city":"Klingenberg",
    "sg:phone":"+49 9372/2605",
    "sg:postcode":"63911",
    "sg:province":"Bayern",
    "wof:name":"Paul Neuberger",
    "wof:placetype":"venue"
},
  "geometry": {"coordinates":[9.1911993027,49.7649536133],"type":"Point"}
}