{
  "type": "Feature",
  "properties": {
    "iso:country":"DE",
    "sg:address":"Mittelweg 8A",
    "sg:city":"Schwante",
    "sg:postcode":"16727",
    "sg:province":"Brandenburg",
    "wof:name":"Sfbe Gmbh",
    "wof:placetype":"venue"
},
  "geometry": {"coordinates":[13.073321,52.722065],"type":"Point"}
}