{
  "type": "Feature",
  "properties": {
    "iso:country":"DE",
    "sg:address":"Weinmarkt 7",
    "sg:city":"Dinkelsb\u00fchl",
    "sg:phone":"+49 9851/2020",
    "sg:postcode":"91550",
    "sg:province":"Bayern",
    "wof:name":"Restaurant Zum Reichsadler",
    "wof:placetype":"venue"
},
  "geometry": {"coordinates":[10.3187084198,49.069770813],"type":"Point"}
}