{
  "type": "Feature",
  "properties": {
    "iso:country":"DE",
    "sg:address":"Dachsweg 2",
    "sg:city":"Langen",
    "sg:phone":"+49 4743/5891",
    "sg:postcode":"27607",
    "sg:province":"Niedersachsen",
    "wof:name":"Harry Naused",
    "wof:placetype":"venue"
},
  "geometry": {"coordinates":[8.586526,53.598457],"type":"Point"}
}