{
  "type": "Feature",
  "properties": {
    "iso:country":"DE",
    "sg:address":"Mittelstr. 5",
    "sg:city":"Laupheim",
    "sg:phone":"+49 7392/3827",
    "sg:postcode":"88471",
    "sg:province":"Baden-W\u00fcrttemberg",
    "wof:name":"Geber Intertabaco Gmbh",
    "wof:placetype":"venue"
},
  "geometry": {"coordinates":[9.8834276199,48.2294616699],"type":"Point"}
}