{
  "type": "Feature",
  "properties": {
    "iso:country":"DE",
    "sg:address":"Zur Lauterhecke 24",
    "sg:city":"Sailauf",
    "sg:postcode":"63877",
    "sg:province":"Bayern",
    "wof:name":"Kristen Informations Und Software Services Gmbh",
    "wof:placetype":"venue"
},
  "geometry": {"coordinates":[9.2660751343,50.0250740051],"type":"Point"}
}