{
  "type": "Feature",
  "properties": {
    "iso:country":"DE",
    "sg:address":"Landstra\u00dfe 19",
    "sg:city":"Schenkenzell",
    "sg:phone":"+49 7836",
    "sg:postcode":"77773",
    "sg:province":"Baden-W\u00fcrttemberg",
    "wof:name":"Dr. Martina Dieterle - M\u00fcnzen Und Antike Kunst",
    "wof:placetype":"venue"
},
  "geometry": {"coordinates":[8.374192,48.312714],"type":"Point"}
}