{
  "type": "Feature",
  "properties": {
    "iso:country":"DE",
    "sg:address":"Kirchstr. 1",
    "sg:city":"Riedlingen",
    "sg:postcode":"88499",
    "sg:province":"Baden-W\u00fcrttemberg",
    "wof:name":"Kath. \u00d6ffentliche Bibliothek",
    "wof:placetype":"venue"
},
  "geometry": {"coordinates":[9.475851,48.154255],"type":"Point"}
}