{
  "type": "Feature",
  "properties": {
    "iso:country":"DE",
    "sg:address":"Gut Schoellerhof",
    "sg:city":"Merzenich",
    "sg:phone":"+49 2275",
    "sg:postcode":"52399",
    "sg:province":"Nordrhein-Westfalen",
    "wof:name":"Nfs Nachfolge- Und Strukturberatung",
    "wof:placetype":"venue"
},
  "geometry": {"coordinates":[6.5930352211,50.833782196],"type":"Point"}
}