{
  "type": "Feature",
  "properties": {
    "iso:country":"DE",
    "sg:address":"Boimstorfer Str. 1",
    "sg:city":"Lehre",
    "sg:phone":"+49 5308/6363",
    "sg:postcode":"38165",
    "sg:province":"Niedersachsen",
    "wof:name":"Hildegard Piehl",
    "wof:placetype":"venue"
},
  "geometry": {"coordinates":[10.668234,52.326637],"type":"Point"}
}