{
  "type": "Feature",
  "properties": {
    "iso:country":"DE",
    "sg:address":"Seckenheimer Hauptstr. 159",
    "sg:city":"Mannheim",
    "sg:phone":"+49 621/48080",
    "sg:postcode":"68239",
    "sg:province":"Baden-W\u00fcrttemberg",
    "wof:name":"L\u00f6wen-seckenheim Hotelbetriebs Gmbh & Co. Kg",
    "wof:placetype":"venue"
},
  "geometry": {"coordinates":[8.5598430634,49.4686355591],"type":"Point"}
}