{
  "type": "Feature",
  "properties": {
    "iso:country":"DE",
    "sg:address":"Forst 10",
    "sg:city":"Wassenberg",
    "sg:phone":"+49 2432/20905",
    "sg:postcode":"41849",
    "sg:province":"Nordrhein-Westfalen",
    "wof:name":"Hans Rauh",
    "wof:placetype":"venue"
},
  "geometry": {"coordinates":[6.13082,51.098072],"type":"Point"}
}