{
  "type": "Feature",
  "properties": {
    "iso:country":"DE",
    "sg:address":"Eberhardstr. 21",
    "sg:city":"Grafenau",
    "sg:phone":"+49 7033/42061",
    "sg:postcode":"71120",
    "sg:province":"Baden-W\u00fcrttemberg",
    "wof:name":"Hans-ulrich Holzhausen Dentallabor Gmbh",
    "wof:placetype":"venue"
},
  "geometry": {"coordinates":[8.909865,48.713196],"type":"Point"}
}