{
  "type": "Feature",
  "properties": {
    "iso:country":"DE",
    "sg:address":"Karolinenstr. 21",
    "sg:city":"Porta Westfalica",
    "sg:phone":"+49 5751/8591",
    "sg:postcode":"32457",
    "sg:province":"Nordrhein-Westfalen",
    "wof:name":"S. Diekmann Steuerbevollm\u00e4chtigter",
    "wof:placetype":"venue"
},
  "geometry": {"coordinates":[9.0004711151,52.2031784058],"type":"Point"}
}