{
  "type": "Feature",
  "properties": {
    "iso:country":"DE",
    "sg:address":"Stader Elbstr. 25",
    "sg:city":"Stade",
    "sg:phone":"+49 4941/4195450",
    "sg:postcode":"21683",
    "sg:province":"Niedersachsen",
    "wof:name":"Air Liquide Gmbh",
    "wof:placetype":"venue"
},
  "geometry": {"coordinates":[9.497905,53.620609],"type":"Point"}
}