{
  "type": "Feature",
  "properties": {
    "iso:country":"DE",
    "sg:address":"Talstr. 30",
    "sg:city":"Malsch",
    "sg:phone":"+49 7246/1245",
    "sg:postcode":"76316",
    "sg:province":"Baden-W\u00fcrttemberg",
    "wof:name":"B\u00fccherei Waldprechtsweier",
    "wof:placetype":"venue"
},
  "geometry": {"coordinates":[8.331255,48.860386],"type":"Point"}
}