{
  "type": "Feature",
  "properties": {
    "iso:country":"DE",
    "sg:address":"Scheiderh\u00f6her Str. 79",
    "sg:city":"Lohmar",
    "sg:phone":"+49 2246/5427",
    "sg:postcode":"53797",
    "sg:province":"Nordrhein-Westfalen",
    "wof:name":"J\u00fcrgen Wirwahn",
    "wof:placetype":"venue"
},
  "geometry": {"coordinates":[7.2263059616,50.8740882874],"type":"Point"}
}