{
  "type": "Feature",
  "properties": {
    "iso:country":"DE",
    "sg:address":"Talstr. 7",
    "sg:city":"Winterbach",
    "sg:phone":"+49 4971/8143777",
    "sg:postcode":"73650",
    "sg:province":"Baden-W\u00fcrttemberg",
    "wof:name":"H.u.m. Finkbeiner Gbr.",
    "wof:placetype":"venue"
},
  "geometry": {"coordinates":[9.476186,48.805054],"type":"Point"}
}