{
  "type": "Feature",
  "properties": {
    "iso:country":"DE",
    "sg:address":"Schauinslandstr. 2",
    "sg:city":"Ettlingen",
    "sg:phone":"+49 7243/597213",
    "sg:postcode":"76275",
    "sg:province":"Baden-W\u00fcrttemberg",
    "wof:name":"Leo Stahl Ingenieur",
    "wof:placetype":"venue"
},
  "geometry": {"coordinates":[8.3941707611,48.925327301],"type":"Point"}
}