{
  "type": "Feature",
  "properties": {
    "iso:country":"DE",
    "sg:address":"Universit\u00e4tsstr. 2",
    "sg:city":"Essen",
    "sg:phone":"+49 201/1832159",
    "sg:postcode":"45141",
    "sg:province":"Nordrhein-Westfalen",
    "wof:name":"Ag Sekundarstufe",
    "wof:placetype":"venue"
},
  "geometry": {"coordinates":[7.008802,51.463581],"type":"Point"}
}