{
  "type": "Feature",
  "properties": {
    "iso:country":"DE",
    "sg:address":"Forstenrieder Allee 59",
    "sg:city":"M\u00fcnchen",
    "sg:phone":"+49 89/7455410",
    "sg:postcode":"81476",
    "sg:province":"Bayern",
    "wof:name":"Herrmann Und Partner Patentanw\u00e4lte",
    "wof:placetype":"venue"
},
  "geometry": {"coordinates":[11.4980649948,48.0942306519],"type":"Point"}
}