{
  "type": "Feature",
  "properties": {
    "iso:country":"DE",
    "sg:address":"Am Pagenkamp 5",
    "sg:city":"Bad Rothenfelde",
    "sg:phone":"+49 5424/1084",
    "sg:postcode":"49214",
    "sg:province":"Niedersachsen",
    "wof:name":"Nana-fashion",
    "wof:placetype":"venue"
},
  "geometry": {"coordinates":[8.163413,52.102276],"type":"Point"}
}