{
  "type": "Feature",
  "properties": {
    "iso:country":"DE",
    "sg:address":"Prinz-Ludwig-Str. 29",
    "sg:city":"Waldsassen",
    "sg:phone":"+49 9632/915030",
    "sg:postcode":"95652",
    "sg:province":"Bayern",
    "wof:name":"E & H Formtechnik Entwicklung Gmbh",
    "wof:placetype":"venue"
},
  "geometry": {"coordinates":[12.301782608,50.0031852722],"type":"Point"}
}