{
  "type": "Feature",
  "properties": {
    "iso:country":"DE",
    "sg:address":"Poststr. 40",
    "sg:city":"Meerbusch",
    "sg:phone":"+49 2132/4077",
    "sg:postcode":"40667",
    "sg:province":"Nordrhein-Westfalen",
    "wof:name":"Alfred Ulrich",
    "wof:placetype":"venue"
},
  "geometry": {"coordinates":[6.6976561546,51.2503585815],"type":"Point"}
}