{
  "type": "Feature",
  "properties": {
    "iso:country":"DE",
    "sg:address":"Dammchaussee 6",
    "sg:city":"Bad Doberan",
    "sg:phone":"+49 38203/63123",
    "sg:postcode":"18209",
    "sg:province":"Mecklenburg-Vorpommern",
    "wof:name":"Paul-friedrich Gaede",
    "wof:placetype":"venue"
},
  "geometry": {"coordinates":[11.904565,54.110535],"type":"Point"}
}