{
  "type": "Feature",
  "properties": {
    "iso:country":"DE",
    "sg:address":"Ballindamm 3",
    "sg:city":"Hamburg",
    "sg:phone":"+49 40/3097440",
    "sg:postcode":"20095",
    "sg:province":"Hamburg",
    "wof:name":"Eisenf\u00fchr Speiser & Partner Patentanw\u00e4lte Rechtsanw\u00e4lte",
    "wof:placetype":"venue"
},
  "geometry": {"coordinates":[10.0005207062,53.5551643372],"type":"Point"}
}