{
  "type": "Feature",
  "properties": {
    "iso:country":"DE",
    "sg:address":"Lindenstr. 12",
    "sg:city":"Melle",
    "sg:postcode":"49324",
    "sg:province":"Niedersachsen",
    "wof:name":"S U. D. Satz Und Druckservice Gmbh",
    "wof:placetype":"venue"
},
  "geometry": {"coordinates":[8.318486,52.197784],"type":"Point"}
}