{
  "type": "Feature",
  "properties": {
    "iso:country":"DE",
    "sg:address":"Im Meerfeld 91",
    "sg:city":"Moers",
    "sg:phone":"+49 2841/70014",
    "sg:postcode":"47445",
    "sg:province":"Nordrhein-Westfalen",
    "wof:name":"Dsm Rohrummantelung Montage Gmbh",
    "wof:placetype":"venue"
},
  "geometry": {"coordinates":[6.6069498062,51.4769363403],"type":"Point"}
}