{
  "type": "Feature",
  "properties": {
    "iso:country":"DE",
    "sg:address":"Saargem\u00fcnder Str. 157-159",
    "sg:city":"Saarbr\u00fccken",
    "sg:phone":"+49 681/3004497",
    "sg:postcode":"66119",
    "sg:province":"Saarland",
    "wof:name":"Bank Eins Saar Eg",
    "wof:placetype":"venue"
},
  "geometry": {"coordinates":[7.0162038803,49.2175292969],"type":"Point"}
}