{
  "type": "Feature",
  "properties": {
    "iso:country":"DE",
    "sg:address":"Ru\u00dflandweg 16",
    "sg:city":"Friedeburg",
    "sg:phone":"+49 4465/94600",
    "sg:postcode":"26446",
    "sg:province":"Niedersachsen",
    "wof:name":"Ostfriesische Marken- Spirituosen",
    "wof:placetype":"venue"
},
  "geometry": {"coordinates":[7.8198747635,53.4521064758],"type":"Point"}
}