{
  "type": "Feature",
  "properties": {
    "iso:country":"DE",
    "sg:address":"Julienstr. 10",
    "sg:city":"Hamburg",
    "sg:phone":"+49 40/8997080",
    "sg:postcode":"22761",
    "sg:province":"Hamburg",
    "wof:name":"Lorenz K\u00f6ster Immobilienmakler",
    "wof:placetype":"venue"
},
  "geometry": {"coordinates":[9.8955230713,53.5664329529],"type":"Point"}
}