{
  "type": "Feature",
  "properties": {
    "iso:country":"DE",
    "sg:address":"Seltersweg 14",
    "sg:city":"Gie\u00dfen",
    "sg:phone":"+49 641/72467",
    "sg:postcode":"35390",
    "sg:province":"Hessen",
    "wof:name":"Nordsee Gmbh",
    "wof:placetype":"venue"
},
  "geometry": {"coordinates":[8.6735458374,50.5844268799],"type":"Point"}
}