{
  "type": "Feature",
  "properties": {
    "iso:country":"DE",
    "sg:address":"Rellinger Str. 23",
    "sg:city":"Hamburg",
    "sg:phone":"+49 40/8514070",
    "sg:postcode":"20257",
    "sg:province":"Hamburg",
    "wof:name":"Praxis Dobbratz",
    "wof:placetype":"venue"
},
  "geometry": {"coordinates":[9.9418344498,53.5746612549],"type":"Point"}
}