{
  "type": "Feature",
  "properties": {
    "iso:country":"DE",
    "sg:address":"D\u00fcesbergweg 124",
    "sg:city":"M\u00fcnster",
    "sg:phone":"+49 251/9760",
    "sg:postcode":"48153",
    "sg:province":"Nordrhein-Westfalen",
    "wof:name":"Kath. Krankenhausbibliothek Clemenshospital",
    "wof:placetype":"venue"
},
  "geometry": {"coordinates":[7.615763,51.932735],"type":"Point"}
}