{
  "type": "Feature",
  "properties": {
    "iso:country":"DE",
    "sg:address":"Korbacher Str. 73",
    "sg:city":"Brilon",
    "sg:phone":"+49 2961/2875",
    "sg:postcode":"59929",
    "sg:province":"Nordrhein-Westfalen",
    "wof:name":"Lindenhof",
    "wof:placetype":"venue"
},
  "geometry": {"coordinates":[8.5779161453,51.337272644],"type":"Point"}
}