{
  "type": "Feature",
  "properties": {
    "iso:country":"DE",
    "sg:address":"Gr\u00fcnwalder Str. 157",
    "sg:city":"M\u00fcnchen",
    "sg:phone":"+49 89/645352",
    "sg:postcode":"81545",
    "sg:province":"Bayern",
    "wof:name":"Erwin Lochmann Gmbh",
    "wof:placetype":"venue"
},
  "geometry": {"coordinates":[11.564765,48.097893],"type":"Point"}
}