{
  "type": "Feature",
  "properties": {
    "iso:country":"DE",
    "sg:address":"Unterer Sand 8",
    "sg:city":"Passau",
    "sg:phone":"+49 851/34407",
    "sg:postcode":"94032",
    "sg:province":"Bayern",
    "wof:name":"Goldenes Schiff",
    "wof:placetype":"venue"
},
  "geometry": {"coordinates":[13.4628763199,48.5734863281],"type":"Point"}
}