{
  "type": "Feature",
  "properties": {
    "iso:country":"DE",
    "sg:address":"Seestr. 5",
    "sg:city":"Radolfzell",
    "sg:phone":"+49 7732/54666",
    "sg:postcode":"78315",
    "sg:province":"Baden-W\u00fcrttemberg",
    "wof:name":"Udo Biller",
    "wof:placetype":"venue"
},
  "geometry": {"coordinates":[8.970927,47.736416],"type":"Point"}
}