{
  "type": "Feature",
  "properties": {
    "iso:country":"DE",
    "sg:address":"B\u00fchnenberg 45",
    "sg:city":"Schermbeck",
    "sg:postcode":"46514",
    "sg:province":"Nordrhein-Westfalen",
    "wof:name":"S-consult Gmbh",
    "wof:placetype":"venue"
},
  "geometry": {"coordinates":[6.8809480667,51.6384773254],"type":"Point"}
}