{
  "type": "Feature",
  "properties": {
    "iso:country":"DE",
    "sg:address":"Stephanienstr. 8",
    "sg:city":"Karlsruhe",
    "sg:phone":"+49 721/20914",
    "sg:postcode":"76133",
    "sg:province":"Baden-W\u00fcrttemberg",
    "wof:name":"Lilo Schnurbusch Heilpraktikerin",
    "wof:placetype":"venue"
},
  "geometry": {"coordinates":[8.3976173401,49.012676239],"type":"Point"}
}