{
  "type": "Feature",
  "properties": {
    "iso:country":"DE",
    "sg:address":"Indestr. 14",
    "sg:city":"Inden",
    "sg:phone":"+49 2465/300558",
    "sg:postcode":"52459",
    "sg:province":"Nordrhein-Westfalen",
    "wof:name":"Herrmann Ultraschall-technik Gmbh & Co.kg",
    "wof:placetype":"venue"
},
  "geometry": {"coordinates":[6.353618,50.847202],"type":"Point"}
}