{
  "type": "Feature",
  "properties": {
    "iso:country":"DE",
    "sg:address":"Hauptstr. 29",
    "sg:city":"Friesenheim",
    "sg:phone":"+49 6737/8543",
    "sg:postcode":"55278",
    "sg:province":"Rheinland-Pfalz",
    "wof:name":"Horst Henrici",
    "wof:placetype":"venue"
},
  "geometry": {"coordinates":[8.2552862167,49.8357696533],"type":"Point"}
}