{
  "type": "Feature",
  "properties": {
    "iso:country":"DE",
    "sg:address":"Kavarinerstr. 45",
    "sg:city":"Kleve",
    "sg:phone":"+49 2821/23776",
    "sg:postcode":"47533",
    "sg:province":"Nordrhein-Westfalen",
    "wof:name":"Heicks Beteiligungs- Gmbh",
    "wof:placetype":"venue"
},
  "geometry": {"coordinates":[6.13747,51.790428],"type":"Point"}
}