{
  "type": "Feature",
  "properties": {
    "iso:country":"DE",
    "sg:city":"Pfarrkirchen",
    "sg:phone":"+49 8561/8950",
    "sg:postcode":"84347",
    "sg:province":"Bayern",
    "wof:name":"Gelateria La Fenice",
    "wof:placetype":"venue"
},
  "geometry": {"coordinates":[12.939037,48.432175],"type":"Point"}
}