{
  "type": "Feature",
  "properties": {
    "iso:country":"DE",
    "sg:address":"Kirchgasse 1",
    "sg:city":"Gaienhofen-Horn",
    "sg:phone":"+49 7735/93380",
    "sg:postcode":"78343",
    "sg:province":"Baden-W\u00fcrttemberg",
    "wof:name":"Gasthof Hirschen",
    "wof:placetype":"venue"
},
  "geometry": {"coordinates":[8.9943437576,47.6961898804],"type":"Point"}
}