{
  "type": "Feature",
  "properties": {
    "iso:country":"DE",
    "sg:address":"Zusestr 1",
    "sg:city":"Itzehoe",
    "sg:phone":"+49 4821/6090",
    "sg:postcode":"25524",
    "sg:province":"Schleswig-Holstein",
    "wof:name":"Inefa Kunststoffe Gmbh",
    "wof:placetype":"venue"
},
  "geometry": {"coordinates":[9.4844522476,53.9528961182],"type":"Point"}
}