{
  "type": "Feature",
  "properties": {
    "iso:country":"DE",
    "sg:address":"Schlesier Str. 11",
    "sg:city":"N\u00f6rdlingen",
    "sg:phone":"+49 9081/6377",
    "sg:postcode":"86720",
    "sg:province":"Bayern",
    "wof:name":"R. Ulrich",
    "wof:placetype":"venue"
},
  "geometry": {"coordinates":[10.507389,48.84729],"type":"Point"}
}