{
  "type": "Feature",
  "properties": {
    "iso:country":"DE",
    "sg:address":"Kastanienweg 3",
    "sg:city":"M\u00fchltroff",
    "sg:phone":"+49 36645/22474",
    "sg:postcode":"07919",
    "sg:province":"Th\u00fcringen",
    "wof:name":"Klaus Behr",
    "wof:placetype":"venue"
},
  "geometry": {"coordinates":[11.929676,50.543812],"type":"Point"}
}