{
  "type": "Feature",
  "properties": {
    "iso:country":"DE",
    "sg:address":"Tautenburger Str. 36a",
    "sg:city":"Berlin",
    "sg:phone":"+49 30/7112339",
    "sg:postcode":"12249",
    "sg:province":"Berlin",
    "wof:name":"Rolf Haase Steuerberater",
    "wof:placetype":"venue"
},
  "geometry": {"coordinates":[13.3496789932,52.4211807251],"type":"Point"}
}