{
  "type": "Feature",
  "properties": {
    "iso:country":"DE",
    "sg:address":"Karlsbaderstrasse 9",
    "sg:city":"Berlin",
    "sg:phone":"+49 30/8262728",
    "sg:postcode":"14193",
    "sg:province":"Berlin",
    "wof:name":"Die Fitnessbar Im Achb",
    "wof:placetype":"venue"
},
  "geometry": {"coordinates":[13.2828531265,52.4820861816],"type":"Point"}
}