{
  "type": "Feature",
  "properties": {
    "iso:country":"DE",
    "sg:address":"Dr.-Hans-Wolf-Str.36",
    "sg:city":"Schwerin",
    "sg:phone":"+49 385/5509970",
    "sg:postcode":"19055",
    "sg:province":"Mecklenburg-Vorpommern",
    "wof:name":"World For Internet And Communication",
    "wof:placetype":"venue"
},
  "geometry": {"coordinates":[11.409657,53.644871],"type":"Point"}
}