{
  "type": "Feature",
  "properties": {
    "iso:country":"DE",
    "sg:address":"Ostdeutsche Str. 6",
    "sg:city":"Plochingen",
    "sg:postcode":"73207",
    "sg:province":"Baden-W\u00fcrttemberg",
    "wof:name":"Elio Industriebetreuung Gmbh",
    "wof:placetype":"venue"
},
  "geometry": {"coordinates":[9.429301,48.719318],"type":"Point"}
}