{
  "type": "Feature",
  "properties": {
    "iso:country":"DE",
    "sg:address":"Forster Weg 48",
    "sg:city":"Wassenberg",
    "sg:phone":"+49 2432/4061",
    "sg:postcode":"41849",
    "sg:province":"Nordrhein-Westfalen",
    "wof:name":"Gebr. Kremers Gmbh & Co. Kg",
    "wof:placetype":"venue"
},
  "geometry": {"coordinates":[6.1395959854,51.1003112793],"type":"Point"}
}