{
  "type": "Feature",
  "properties": {
    "iso:country":"DE",
    "sg:address":"Augustenstr. 115",
    "sg:city":"M\u00fcnchen",
    "sg:postcode":"80798",
    "sg:province":"Bayern",
    "wof:name":"Aurea Classica Goldschmuck Gmbh",
    "wof:placetype":"venue"
},
  "geometry": {"coordinates":[11.5661211014,48.1543159485],"type":"Point"}
}