{
  "type": "Feature",
  "properties": {
    "iso:country":"DE",
    "sg:address":"Bahnhofstr. 17",
    "sg:city":"Murnau",
    "sg:phone":"+49 8841/99211",
    "sg:postcode":"82418",
    "sg:province":"Bayern",
    "wof:name":"R\u00f6merbad",
    "wof:placetype":"venue"
},
  "geometry": {"coordinates":[11.19797,47.679787],"type":"Point"}
}