{
  "type": "Feature",
  "properties": {
    "iso:country":"DE",
    "sg:address":"Esmarchstr. 62",
    "sg:city":"Kiel",
    "sg:phone":"+49 431/802032",
    "sg:postcode":"24105",
    "sg:province":"Schleswig-Holstein",
    "wof:name":"Nagel Und Hecht-nagel Architekten",
    "wof:placetype":"venue"
},
  "geometry": {"coordinates":[10.135789,54.341656],"type":"Point"}
}