{
  "type": "Feature",
  "properties": {
    "iso:country":"DE",
    "sg:address":"Kurt-Schumacher-Str. 39",
    "sg:city":"Leipzig",
    "sg:phone":"+49 341/2118426",
    "sg:postcode":"04105",
    "sg:province":"Sachsen",
    "wof:name":"Procon Gbr",
    "wof:placetype":"venue"
},
  "geometry": {"coordinates":[12.37778,51.348831],"type":"Point"}
}