{
  "type": "Feature",
  "properties": {
    "iso:country":"DE",
    "sg:address":"Haasstr 6",
    "sg:city":"Darmstadt",
    "sg:phone":"+49 6151/366860",
    "sg:postcode":"64293",
    "sg:province":"Hessen",
    "wof:name":"Riese Und M\u00fcller Gmbh",
    "wof:placetype":"venue"
},
  "geometry": {"coordinates":[8.620269,49.885826],"type":"Point"}
}