{
  "type": "Feature",
  "properties": {
    "iso:country":"DE",
    "sg:address":"Hauptstr. 33",
    "sg:city":"Bestwig",
    "sg:phone":"+49 2904/97980",
    "sg:postcode":"59909",
    "sg:province":"Nordrhein-Westfalen",
    "wof:name":"K\u00e4lte- Und Klimatechnik Ulrich Vorderw\u00fclbecke Gmbh",
    "wof:placetype":"venue"
},
  "geometry": {"coordinates":[8.4183244705,51.3597564697],"type":"Point"}
}