{
  "type": "Feature",
  "properties": {
    "iso:country":"DE",
    "sg:address":"Am Rinnentor 12",
    "sg:city":"Bensheim",
    "sg:phone":"+49 6251/61458",
    "sg:postcode":"64625",
    "sg:province":"Hessen",
    "wof:name":"Kollerer Gmbh",
    "wof:placetype":"venue"
},
  "geometry": {"coordinates":[8.6214523315,49.6799736023],"type":"Point"}
}