{
  "type": "Feature",
  "properties": {
    "iso:country":"DE",
    "sg:address":"Fischauktionsstr. 21",
    "sg:city":"Bremerhaven",
    "sg:phone":"+49 471/75009",
    "sg:postcode":"27572",
    "sg:province":"Bremen",
    "wof:name":"Westfalia",
    "wof:placetype":"venue"
},
  "geometry": {"coordinates":[8.577375412,53.5190162659],"type":"Point"}
}