{
  "type": "Feature",
  "properties": {
    "iso:country":"DE",
    "sg:address":"Am Richtenberg 9",
    "sg:city":"Essen",
    "sg:phone":"+49 201/761272",
    "sg:postcode":"45145",
    "sg:province":"Nordrhein-Westfalen",
    "wof:name":"Josef Grave",
    "wof:placetype":"venue"
},
  "geometry": {"coordinates":[6.95409,51.447708],"type":"Point"}
}