{
  "type": "Feature",
  "properties": {
    "iso:country":"DE",
    "sg:address":"Christophstr. 46",
    "sg:city":"Leinfelden-Echterdingen",
    "sg:phone":"+49 711/792756",
    "sg:postcode":"70771",
    "sg:province":"Baden-W\u00fcrttemberg",
    "wof:name":"Helmut Fritz",
    "wof:placetype":"venue"
},
  "geometry": {"coordinates":[9.1676082611,48.6846351624],"type":"Point"}
}