{
  "type": "Feature",
  "properties": {
    "iso:country":"DE",
    "sg:address":"Danziger Str. 47",
    "sg:city":"Pfaffenhofen",
    "sg:phone":"+49 8441/5850",
    "sg:postcode":"85276",
    "sg:province":"Bayern",
    "wof:name":"Peter Fuchs Augenoptiker",
    "wof:placetype":"venue"
},
  "geometry": {"coordinates":[11.4864711761,48.5318183899],"type":"Point"}
}