{
  "type": "Feature",
  "properties": {
    "iso:country":"DE",
    "sg:address":"Weseler Str. 113",
    "sg:city":"Duisburg",
    "sg:phone":"+49 203/990960",
    "sg:postcode":"47169",
    "sg:province":"Nordrhein-Westfalen",
    "wof:name":"Cmart Compumedia Gmbh & Co. Kg",
    "wof:placetype":"venue"
},
  "geometry": {"coordinates":[6.7495260239,51.5068817139],"type":"Point"}
}