{
  "type": "Feature",
  "properties": {
    "iso:country":"DE",
    "sg:address":"Welsleber Str. 4",
    "sg:city":"Sch\u00f6nebeck",
    "sg:phone":"+49 3928/65482",
    "sg:postcode":"39218",
    "sg:province":"Sachsen-Anhalt",
    "wof:name":"C. Else",
    "wof:placetype":"venue"
},
  "geometry": {"coordinates":[11.7261390686,52.0203971863],"type":"Point"}
}