{
  "type": "Feature",
  "properties": {
    "iso:country":"DE",
    "sg:address":"Postfach 1403",
    "sg:city":"Seligenstadt",
    "sg:postcode":"63490",
    "sg:province":"Hessen",
    "wof:name":"Esoterik, Amulette, Talismane Und Feng-shui.",
    "wof:placetype":"venue"
},
  "geometry": {"coordinates":[8.97555,50.043369],"type":"Point"}
}