{
  "type": "Feature",
  "properties": {
    "iso:country":"DE",
    "sg:address":"Neue Gr\u00fcnstr. 19",
    "sg:city":"Berlin",
    "sg:phone":"+49 30/2786755",
    "sg:postcode":"10179",
    "sg:province":"Berlin",
    "wof:name":"Diakonie- Treuhandgesellschaft Mbh",
    "wof:placetype":"venue"
},
  "geometry": {"coordinates":[13.4059753418,52.5107421875],"type":"Point"}
}