{
  "type": "Feature",
  "properties": {
    "iso:country":"DE",
    "sg:address":"Friedrich-Karl-Str. 9",
    "sg:city":"Berlin",
    "sg:phone":"+49 30/7522016",
    "sg:postcode":"12103",
    "sg:province":"Berlin",
    "wof:name":"Schild Reiseb\u00fcro",
    "wof:placetype":"venue"
},
  "geometry": {"coordinates":[13.3820381165,52.4557647705],"type":"Point"}
}