{
  "type": "Feature",
  "properties": {
    "iso:country":"DE",
    "sg:address":"Margarete-Bieber-Weg 6",
    "sg:city":"Gie\u00dfen",
    "sg:phone":"+49 641/33620",
    "sg:postcode":"35396",
    "sg:province":"Hessen",
    "wof:name":"Wolfgang Fremuth",
    "wof:placetype":"venue"
},
  "geometry": {"coordinates":[8.677232,50.603802],"type":"Point"}
}