{
  "type": "Feature",
  "properties": {
    "iso:country":"DE",
    "sg:address":"Wunsiedler Str. 7",
    "sg:city":"Hof",
    "sg:postcode":"95032",
    "sg:province":"Bayern",
    "wof:name":"Sioux Graphic Gmbh",
    "wof:placetype":"venue"
},
  "geometry": {"coordinates":[11.9193096161,50.3049278259],"type":"Point"}
}