{
  "type": "Feature",
  "properties": {
    "iso:country":"DE",
    "sg:address":"Lerchenrain 2",
    "sg:city":"Wollbach",
    "sg:phone":"+49 9773/1431",
    "sg:postcode":"97618",
    "sg:province":"Bayern",
    "wof:name":"Reinhart",
    "wof:placetype":"venue"
},
  "geometry": {"coordinates":[10.221773,50.361012],"type":"Point"}
}