{
  "type": "Feature",
  "properties": {
    "iso:country":"DE",
    "sg:address":"Herforder Str. 47",
    "sg:city":"Bad Salzuflen",
    "sg:phone":"+49 5222/40558",
    "sg:postcode":"32105",
    "sg:province":"Nordrhein-Westfalen",
    "wof:name":"Heinz Meise",
    "wof:placetype":"venue"
},
  "geometry": {"coordinates":[8.7363929749,52.0870704651],"type":"Point"}
}