{
  "type": "Feature",
  "properties": {
    "iso:country":"DE",
    "sg:address":"Gewerbegebiet Herste",
    "sg:city":"Bad Driburg",
    "sg:phone":"+49 5253/5201",
    "sg:postcode":"33014",
    "sg:province":"Nordrhein-Westfalen",
    "wof:name":"Christa Fehring",
    "wof:placetype":"venue"
},
  "geometry": {"coordinates":[9.075961113,51.7139854431],"type":"Point"}
}