{
  "type": "Feature",
  "properties": {
    "iso:country":"DE",
    "sg:address":"Dortmunder Str 12",
    "sg:city":"Schwetzingen",
    "sg:phone":"+49 3491/6380",
    "sg:postcode":"68723",
    "sg:province":"Baden-W\u00fcrttemberg",
    "wof:name":"Sig Combibloc Gmbh",
    "wof:placetype":"venue"
},
  "geometry": {"coordinates":[12.5676546097,51.8850631714],"type":"Point"}
}