{
  "type": "Feature",
  "properties": {
    "iso:country":"DE",
    "sg:address":"Am Papenholz 5",
    "sg:city":"Braunschweig",
    "sg:phone":"+49 531/360421",
    "sg:postcode":"38104",
    "sg:province":"Niedersachsen",
    "wof:name":"Bernhard Storm Architekt",
    "wof:placetype":"venue"
},
  "geometry": {"coordinates":[10.581983,52.289692],"type":"Point"}
}