{
  "type": "Feature",
  "properties": {
    "iso:country":"DE",
    "sg:address":"Triniusstr. 15",
    "sg:city":"Arnstadt",
    "sg:phone":"+49 3628/41503",
    "sg:postcode":"99310",
    "sg:province":"Th\u00fcringen",
    "wof:name":"Gerhard Gutheil",
    "wof:placetype":"venue"
},
  "geometry": {"coordinates":[10.936072,50.835701],"type":"Point"}
}