{
  "type": "Feature",
  "properties": {
    "iso:country":"DE",
    "sg:address":"Bei der Kirche 22",
    "sg:city":"Hanstedt",
    "sg:phone":"+49 4184/7504",
    "sg:postcode":"21271",
    "sg:province":"Niedersachsen",
    "wof:name":"Ingeborg St\u00f6ckicht",
    "wof:placetype":"venue"
},
  "geometry": {"coordinates":[10.013704,53.257351],"type":"Point"}
}