{
  "type": "Feature",
  "properties": {
    "iso:country":"DE",
    "sg:address":"Siedlung 13",
    "sg:city":"Haina",
    "sg:phone":"+49 6455/1248",
    "sg:postcode":"35114",
    "sg:province":"Hessen",
    "wof:name":"M\u00f6llers Fr\u00fchst\u00fccksdienst",
    "wof:placetype":"venue"
},
  "geometry": {"coordinates":[8.97693,51.062519],"type":"Point"}
}