{
  "type": "Feature",
  "properties": {
    "iso:country":"DE",
    "sg:address":"Gutenbergstr 26",
    "sg:city":"Giesen",
    "sg:phone":"+49 5121/60050",
    "sg:postcode":"31180",
    "sg:province":"Niedersachsen",
    "wof:name":"Sander",
    "wof:placetype":"venue"
},
  "geometry": {"coordinates":[9.870398,52.16048],"type":"Point"}
}