{
  "type": "Feature",
  "properties": {
    "iso:country":"DE",
    "sg:address":"Am Kirchplatz 8",
    "sg:city":"Feldafing",
    "sg:phone":"+49 8157/90543",
    "sg:postcode":"82340",
    "sg:province":"Bayern",
    "wof:name":"Kaisers Tengelmann Ag",
    "wof:placetype":"venue"
},
  "geometry": {"coordinates":[11.2971534729,47.9505081177],"type":"Point"}
}