{
  "type": "Feature",
  "properties": {
    "iso:country":"DE",
    "sg:address":"B\u00e4ckergasse 20",
    "sg:city":"Rosbach",
    "sg:phone":"+49 6003/91710",
    "sg:postcode":"61191",
    "sg:province":"Hessen",
    "wof:name":"Versicherungs-dienst Schreiter Vds E. K.",
    "wof:placetype":"venue"
},
  "geometry": {"coordinates":[8.7062559128,50.3007659912],"type":"Point"}
}