{
  "type": "Feature",
  "properties": {
    "iso:country":"DE",
    "sg:address":"Ochsenzoller Str. 102",
    "sg:city":"Norderstedt",
    "sg:phone":"+49 40/5236650",
    "sg:postcode":"22848",
    "sg:province":"Schleswig-Holstein",
    "wof:name":"Taverne Savvas",
    "wof:placetype":"venue"
},
  "geometry": {"coordinates":[9.9801912308,53.6815681458],"type":"Point"}
}