{
  "type": "Feature",
  "properties": {
    "iso:country":"DE",
    "sg:address":"Bahnhofstr. 40",
    "sg:city":"Quakenbr\u00fcck",
    "sg:phone":"+49 5431/6646",
    "sg:postcode":"49610",
    "sg:province":"Niedersachsen",
    "wof:name":"Restaurant Le Bistro",
    "wof:placetype":"venue"
},
  "geometry": {"coordinates":[7.9500150681,52.6737480164],"type":"Point"}
}