{
  "type": "Feature",
  "properties": {
    "iso:country":"DE",
    "sg:address":"Bliesgaustr. 59 A",
    "sg:city":"Blieskastel",
    "sg:phone":"+49 4968/4251522",
    "sg:postcode":"66440",
    "sg:province":"Saarland",
    "wof:name":"Electronic Knoerr Gmbh",
    "wof:placetype":"venue"
},
  "geometry": {"coordinates":[7.259815,49.243069],"type":"Point"}
}