{
  "type": "Feature",
  "properties": {
    "iso:country":"DE",
    "sg:address":"Glockenstr. 1",
    "sg:city":"Bad Salzuflen",
    "sg:phone":"+49 5222/73956",
    "sg:postcode":"32107",
    "sg:province":"Nordrhein-Westfalen",
    "wof:name":"Glocken-apotheke Inh. Marianne Freygang",
    "wof:placetype":"venue"
},
  "geometry": {"coordinates":[8.682272,52.062946],"type":"Point"}
}