{
  "type": "Feature",
  "properties": {
    "iso:country":"DE",
    "sg:address":"Montfortstr. 14",
    "sg:city":"Tettnang",
    "sg:phone":"+49 7542/93770",
    "sg:postcode":"88069",
    "sg:province":"Baden-W\u00fcrttemberg",
    "wof:name":"G. G\u00f6\u00dfl",
    "wof:placetype":"venue"
},
  "geometry": {"coordinates":[9.5871219635,47.6711997986],"type":"Point"}
}