{
  "type": "Feature",
  "properties": {
    "iso:country":"DE",
    "sg:address":"Ludwigstr. 79",
    "sg:city":"Hof",
    "sg:phone":"+49 9281/15015",
    "sg:postcode":"95028",
    "sg:province":"Bayern",
    "wof:name":"City Reiseb\u00fcro Gmbh",
    "wof:placetype":"venue"
},
  "geometry": {"coordinates":[11.917391777,50.3195571899],"type":"Point"}
}