{
  "type": "Feature",
  "properties": {
    "iso:country":"DE",
    "sg:address":"Hauptstr. 39",
    "sg:city":"W\u00fcrselen",
    "sg:phone":"+49 2405/73225",
    "sg:postcode":"52146",
    "sg:province":"Nordrhein-Westfalen",
    "wof:name":"Heike Havertz Und Kirsten Groh",
    "wof:placetype":"venue"
},
  "geometry": {"coordinates":[6.15356,50.815048],"type":"Point"}
}