{
  "type": "Feature",
  "properties": {
    "iso:country":"DE",
    "sg:address":"Ruppertsberger Str. 13",
    "sg:city":"Meckenheim",
    "sg:phone":"+49 6326/202",
    "sg:postcode":"67149",
    "sg:province":"Rheinland-Pfalz",
    "wof:name":"Kurt Wagner Architekt",
    "wof:placetype":"venue"
},
  "geometry": {"coordinates":[8.239407,49.406044],"type":"Point"}
}