{
  "type": "Feature",
  "properties": {
    "iso:country":"DE",
    "sg:address":"Uentropstr. 9",
    "sg:city":"Schmallenberg",
    "sg:phone":"+49 2972/960618",
    "sg:postcode":"57392",
    "sg:province":"Nordrhein-Westfalen",
    "wof:name":"Sternberg Dreh- Und Fr\u00e4stechnik Gmbh",
    "wof:placetype":"venue"
},
  "geometry": {"coordinates":[8.2213802338,51.1330718994],"type":"Point"}
}