{
  "type": "Feature",
  "properties": {
    "iso:country":"DE",
    "sg:address":"Mainzer Str. 22",
    "sg:city":"Ingelheim",
    "sg:phone":"+49 6132/2446",
    "sg:postcode":"55218",
    "sg:province":"Rheinland-Pfalz",
    "wof:name":"Hermann Schweikhard",
    "wof:placetype":"venue"
},
  "geometry": {"coordinates":[8.065857,49.975819],"type":"Point"}
}