{
  "type": "Feature",
  "properties": {
    "iso:country":"DE",
    "sg:address":"Karl-Brunnengr\u00e4ber-Str. 3a",
    "sg:city":"L\u00fctzelbach",
    "sg:phone":"+49 9372/4683",
    "sg:postcode":"64750",
    "sg:province":"Hessen",
    "wof:name":"Waldhaus Diana",
    "wof:placetype":"venue"
},
  "geometry": {"coordinates":[9.1225748062,49.7916145325],"type":"Point"}
}