{
  "type": "Feature",
  "properties": {
    "iso:country":"DE",
    "sg:address":"Bahnhofstr. 86",
    "sg:city":"Eichwalde",
    "sg:phone":"+49 30/6757154",
    "sg:postcode":"15732",
    "sg:province":"Brandenburg",
    "wof:name":"Udo Gerrath",
    "wof:placetype":"venue"
},
  "geometry": {"coordinates":[13.6163654327,52.3727455139],"type":"Point"}
}