{
  "type": "Feature",
  "properties": {
    "iso:country":"DE",
    "sg:address":"Truderinger Str. 300",
    "sg:city":"M\u00fcnchen",
    "sg:phone":"+49 89/421002",
    "sg:postcode":"81825",
    "sg:province":"Bayern",
    "wof:name":"Theodor Imberg Gmbh & Co. Kg",
    "wof:placetype":"venue"
},
  "geometry": {"coordinates":[11.6687602997,48.1224250793],"type":"Point"}
}