{
  "type": "Feature",
  "properties": {
    "iso:country":"DE",
    "sg:address":"D\u00f6lziger Str. 49",
    "sg:city":"Markranst\u00e4dt",
    "sg:phone":"+49 341/9411223",
    "sg:postcode":"04420",
    "sg:province":"Sachsen",
    "wof:name":"Helmut Vo\u00df",
    "wof:placetype":"venue"
},
  "geometry": {"coordinates":[12.232674,51.338261],"type":"Point"}
}