{
  "type": "Feature",
  "properties": {
    "iso:country":"DE",
    "sg:address":"Kaiser-Max-Str. 31",
    "sg:city":"Kaufbeuren",
    "sg:phone":"+49 8341/2724",
    "sg:postcode":"87600",
    "sg:province":"Bayern",
    "wof:name":"Gastst\u00e4tte Zum L\u00f6wen",
    "wof:placetype":"venue"
},
  "geometry": {"coordinates":[10.6200866699,47.8792114258],"type":"Point"}
}