{
  "type": "Feature",
  "properties": {
    "iso:country":"DE",
    "sg:address":"M\u00fchlenstr. 10",
    "sg:city":"Rethem",
    "sg:phone":"+49 5165/2375",
    "sg:postcode":"27336",
    "sg:province":"Niedersachsen",
    "wof:name":"C.c. Johannsen Inh. Hans-j\u00fcrgen Rabe",
    "wof:placetype":"venue"
},
  "geometry": {"coordinates":[9.3809480667,52.7861213684],"type":"Point"}
}