{
  "type": "Feature",
  "properties": {
    "iso:country":"DE",
    "sg:address":"Hans-Mielich-Str. 8",
    "sg:city":"Ingolstadt",
    "sg:phone":"+49 841/66482",
    "sg:postcode":"85053",
    "sg:province":"Bayern",
    "wof:name":"Karl Hefner",
    "wof:placetype":"venue"
},
  "geometry": {"coordinates":[11.44344,48.741734],"type":"Point"}
}