{
  "type": "Feature",
  "properties": {
    "iso:country":"DE",
    "sg:address":"Georg-Schumann-Str. 313",
    "sg:city":"Leipzig",
    "sg:phone":"+49 341/9014011",
    "sg:postcode":"04159",
    "sg:province":"Sachsen",
    "wof:name":"Peter Krull",
    "wof:placetype":"venue"
},
  "geometry": {"coordinates":[12.3300514221,51.372215271],"type":"Point"}
}