{
  "type": "Feature",
  "properties": {
    "iso:country":"DE",
    "sg:address":"Ostendstr. 4",
    "sg:city":"Stockstadt",
    "sg:phone":"+49 6027/401936",
    "sg:postcode":"63811",
    "sg:province":"Bayern",
    "wof:name":"Ing. J\u00fcrgen Horn Kunststoffverarbeitung Gmbh",
    "wof:placetype":"venue"
},
  "geometry": {"coordinates":[9.086592,49.962662],"type":"Point"}
}