{
  "type": "Feature",
  "properties": {
    "iso:country":"DE",
    "sg:address":"Kleiner Zimmerhof 12",
    "sg:city":"Wolfenb\u00fcttel",
    "sg:phone":"+49 5331/2830",
    "sg:postcode":"38300",
    "sg:province":"Niedersachsen",
    "wof:name":"Ingrid Schell Masseurin",
    "wof:placetype":"venue"
},
  "geometry": {"coordinates":[10.533605,52.163521],"type":"Point"}
}