{
  "type": "Feature",
  "properties": {
    "iso:country":"DE",
    "sg:address":"Fautenbruchstr. 49",
    "sg:city":"Karlsruhe",
    "sg:phone":"+49 721/9338280",
    "sg:postcode":"76137",
    "sg:province":"Baden-W\u00fcrttemberg",
    "wof:name":"Transact Gmbh",
    "wof:placetype":"venue"
},
  "geometry": {"coordinates":[8.4072561264,48.992931366],"type":"Point"}
}