{
  "type": "Feature",
  "properties": {
    "iso:country":"DE",
    "sg:address":"Frankfurter Str. 38",
    "sg:city":"Bad Rothenfelde",
    "sg:phone":"+49 5424/1772",
    "sg:postcode":"49214",
    "sg:province":"Niedersachsen",
    "wof:name":"Paul Menke",
    "wof:placetype":"venue"
},
  "geometry": {"coordinates":[8.1628246307,52.1052436829],"type":"Point"}
}