{
  "type": "Feature",
  "properties": {
    "iso:country":"DE",
    "sg:address":"Holzgartenstr. 38",
    "sg:city":"N\u00fcrnberg",
    "sg:phone":"+49 911/468061",
    "sg:postcode":"90461",
    "sg:province":"Bayern",
    "wof:name":"Rosskath Textilmaschinen Gmbh",
    "wof:placetype":"venue"
},
  "geometry": {"coordinates":[11.096327,49.437866],"type":"Point"}
}