{
  "type": "Feature",
  "properties": {
    "iso:country":"DE",
    "sg:address":"Boschstr. 1",
    "sg:city":"Haren",
    "sg:phone":"+49 5932/72080",
    "sg:postcode":"49733",
    "sg:province":"Niedersachsen",
    "wof:name":"Autohaus Josef Geers Gmbh",
    "wof:placetype":"venue"
},
  "geometry": {"coordinates":[7.214563,52.7971],"type":"Point"}
}