{
  "type": "Feature",
  "properties": {
    "iso:country":"DE",
    "sg:address":"Berenbosteler Str. 74",
    "sg:city":"Garbsen",
    "sg:phone":"+49 5137/875552",
    "sg:postcode":"30823",
    "sg:province":"Niedersachsen",
    "wof:name":"Milena Zaccarino",
    "wof:placetype":"venue"
},
  "geometry": {"coordinates":[9.5921621323,52.4216079712],"type":"Point"}
}