{
  "type": "Feature",
  "properties": {
    "iso:country":"DE",
    "sg:address":"R\u00f6merrast 8",
    "sg:city":"Hamminkeln",
    "sg:phone":"+49 2852/2373",
    "sg:postcode":"46499",
    "sg:province":"Nordrhein-Westfalen",
    "wof:name":"Werner Arntzen",
    "wof:placetype":"venue"
},
  "geometry": {"coordinates":[6.583319,51.76017],"type":"Point"}
}