{
  "type": "Feature",
  "properties": {
    "iso:country":"DE",
    "sg:address":"Landsberger Str. 392",
    "sg:city":"M\u00fcnchen",
    "sg:phone":"+49 89/5461600",
    "sg:postcode":"81241",
    "sg:province":"Bayern",
    "wof:name":"Bp Direkt Gmbh",
    "wof:placetype":"venue"
},
  "geometry": {"coordinates":[11.484227,48.145073],"type":"Point"}
}