{
  "type": "Feature",
  "properties": {
    "iso:country":"DE",
    "sg:address":"D\u00fcrener Str. 227",
    "sg:city":"K\u00f6ln",
    "sg:phone":"+49 221/408515",
    "sg:postcode":"50931",
    "sg:province":"Nordrhein-Westfalen",
    "wof:name":"Peter Hirsch",
    "wof:placetype":"venue"
},
  "geometry": {"coordinates":[6.912033,50.929192],"type":"Point"}
}