{
  "type": "Feature",
  "properties": {
    "iso:country":"DE",
    "sg:address":"Clara-Zetkin-Str. 27",
    "sg:city":"Potsdam",
    "sg:postcode":"14471",
    "sg:province":"Brandenburg",
    "wof:name":"M. Schwinzer",
    "wof:placetype":"venue"
},
  "geometry": {"coordinates":[13.0376358032,52.3952293396],"type":"Point"}
}