{
  "type": "Feature",
  "properties": {
    "iso:country":"DE",
    "sg:address":"Kirchstr. 5",
    "sg:city":"Rotenhain",
    "sg:phone":"+49 2661/8257",
    "sg:postcode":"56459",
    "sg:province":"Rheinland-Pfalz",
    "wof:name":"E. Hanz",
    "wof:placetype":"venue"
},
  "geometry": {"coordinates":[7.88174,50.599648],"type":"Point"}
}