{
  "type": "Feature",
  "properties": {
    "iso:country":"DE",
    "sg:address":"Carl-Leverkus-Str. 19",
    "sg:city":"Odenthal",
    "sg:phone":"+49 2202/78625",
    "sg:postcode":"51519",
    "sg:province":"Nordrhein-Westfalen",
    "wof:name":"Adolf Eichborn",
    "wof:placetype":"venue"
},
  "geometry": {"coordinates":[7.1143121719,51.0347175598],"type":"Point"}
}