{
  "type": "Feature",
  "properties": {
    "iso:country":"DE",
    "sg:address":"Herzberger Str. 11",
    "sg:city":"Schlieben",
    "sg:phone":"+49 35361/80069",
    "sg:postcode":"04936",
    "sg:province":"Brandenburg",
    "wof:name":"Handy-salon",
    "wof:placetype":"venue"
},
  "geometry": {"coordinates":[13.381449,51.721668],"type":"Point"}
}