{
  "type": "Feature",
  "properties": {
    "iso:country":"DE",
    "sg:address":"Hilgerstr. 5",
    "sg:city":"M\u00fcnchen",
    "sg:phone":"+49 89/3117082",
    "sg:postcode":"80937",
    "sg:province":"Bayern",
    "wof:name":"Max Reindl",
    "wof:placetype":"venue"
},
  "geometry": {"coordinates":[11.5740995407,48.2000045776],"type":"Point"}
}