{
  "type": "Feature",
  "properties": {
    "iso:country":"DE",
    "sg:address":"L\u00f6chgauer Str. 13",
    "sg:city":"Bietigheim-Bissingen",
    "sg:phone":"+49 7142/44223",
    "sg:postcode":"74321",
    "sg:province":"Baden-W\u00fcrttemberg",
    "wof:name":"Roland W. Vollmer Ingenieur",
    "wof:placetype":"venue"
},
  "geometry": {"coordinates":[9.1274709702,48.9606704712],"type":"Point"}
}