{
  "type": "Feature",
  "properties": {
    "iso:country":"DE",
    "sg:address":"Mercedesstr. 1",
    "sg:city":"Mainz",
    "sg:phone":"+49 6131/983330",
    "sg:postcode":"55128",
    "sg:province":"Rheinland-Pfalz",
    "wof:name":"Carmax Autovermietung",
    "wof:placetype":"venue"
},
  "geometry": {"coordinates":[8.233405,49.966385],"type":"Point"}
}