{
  "type": "Feature",
  "properties": {
    "iso:country":"DE",
    "sg:address":"Eschersheimer Landstr. 81",
    "sg:city":"Frankfurt",
    "sg:phone":"+49 69/559777",
    "sg:postcode":"60322",
    "sg:province":"Hessen",
    "wof:name":"Air-taxi-frankfurt Gmbh",
    "wof:placetype":"venue"
},
  "geometry": {"coordinates":[8.675198,50.123814],"type":"Point"}
}