{
  "type": "Feature",
  "properties": {
    "iso:country":"DE",
    "sg:address":"Marktplatz 13",
    "sg:city":"Reisbach",
    "sg:phone":"+49 8734/343",
    "sg:postcode":"94419",
    "sg:province":"Bayern",
    "wof:name":"R. Schr\u00f6der",
    "wof:placetype":"venue"
},
  "geometry": {"coordinates":[12.627442,48.572716],"type":"Point"}
}