{
  "type": "Feature",
  "properties": {
    "iso:country":"DE",
    "sg:address":"Steinweg 30",
    "sg:city":"Naumburg",
    "sg:phone":"+49 3445/202545",
    "sg:postcode":"06618",
    "sg:province":"Sachsen-Anhalt",
    "wof:name":"Hackerbr\u00e4u",
    "wof:placetype":"venue"
},
  "geometry": {"coordinates":[11.8063354492,51.1534576416],"type":"Point"}
}