{
  "type": "Feature",
  "properties": {
    "iso:country":"DE",
    "sg:address":"Thadd\u00e4usstr. 64",
    "sg:city":"Verl",
    "sg:phone":"+49 5246/3660",
    "sg:postcode":"33415",
    "sg:province":"Nordrhein-Westfalen",
    "wof:name":"H. Thiesbrummel",
    "wof:placetype":"venue"
},
  "geometry": {"coordinates":[8.466666,51.890221],"type":"Point"}
}