{
  "type": "Feature",
  "properties": {
    "iso:country":"DE",
    "sg:address":"Am Tierpark 1",
    "sg:city":"Ueckerm\u00fcnde",
    "sg:phone":"+49 39771/22971",
    "sg:postcode":"17373",
    "sg:province":"Mecklenburg-Vorpommern",
    "wof:name":"Hans-ulrich Klotz",
    "wof:placetype":"venue"
},
  "geometry": {"coordinates":[14.035519,53.73378],"type":"Point"}
}