{
  "type": "Feature",
  "properties": {
    "iso:country":"DE",
    "sg:address":"Sack 5-11",
    "sg:city":"Braunschweig",
    "sg:postcode":"38100",
    "sg:province":"Niedersachsen",
    "wof:name":"Heutelbeck Gmbh & Co. Kg",
    "wof:placetype":"venue"
},
  "geometry": {"coordinates":[10.5214090347,52.264503479],"type":"Point"}
}