{
  "type": "Feature",
  "properties": {
    "iso:country":"DE",
    "sg:address":"Hauptstr. 27",
    "sg:city":"Weihmichl",
    "sg:phone":"+49 8704/367",
    "sg:postcode":"84107",
    "sg:province":"Bayern",
    "wof:name":"Gasthof M. Schreiner",
    "wof:placetype":"venue"
},
  "geometry": {"coordinates":[12.0431375504,48.6046524048],"type":"Point"}
}