{
  "type": "Feature",
  "properties": {
    "iso:country":"DE",
    "sg:address":"Krahnendonk 12 a und b",
    "sg:city":"M\u00f6nchengladbach",
    "sg:postcode":"41066",
    "sg:province":"Nordrhein-Westfalen",
    "wof:name":"Helmuth Hauth Warenautomaten Gmbh & Co. Kg",
    "wof:placetype":"venue"
},
  "geometry": {"coordinates":[6.468765,51.223869],"type":"Point"}
}