{
  "type": "Feature",
  "properties": {
    "iso:country":"DE",
    "sg:address":"Kellerstr. 2",
    "sg:city":"Stadtoldendorf",
    "sg:phone":"+49 5532/4201",
    "sg:postcode":"37627",
    "sg:province":"Niedersachsen",
    "wof:name":"Wilhelm Arste",
    "wof:placetype":"venue"
},
  "geometry": {"coordinates":[9.6244001389,51.8837585449],"type":"Point"}
}