{
  "type": "Feature",
  "properties": {
    "iso:country":"DE",
    "sg:address":"Dorfstr. 38",
    "sg:city":"Alsdorf",
    "sg:phone":"+49 2404/25405",
    "sg:postcode":"52477",
    "sg:province":"Nordrhein-Westfalen",
    "wof:name":"Wolfgang Lamm",
    "wof:placetype":"venue"
},
  "geometry": {"coordinates":[6.160247,50.85886],"type":"Point"}
}