{
  "type": "Feature",
  "properties": {
    "iso:country":"DE",
    "sg:address":"Dittelsdorfer Str 2",
    "sg:city":"Zittau",
    "sg:phone":"+49 3583/77750",
    "sg:postcode":"02763",
    "sg:province":"Sachsen",
    "wof:name":"Tillig Modellbahnen Gmbh & Co Kg",
    "wof:placetype":"venue"
},
  "geometry": {"coordinates":[14.8365163803,50.9090385437],"type":"Point"}
}