{
  "type": "Feature",
  "properties": {
    "iso:country":"DE",
    "sg:address":"Candidplatz 13",
    "sg:city":"M\u00fcnchen",
    "sg:phone":"+49 89/62509703",
    "sg:postcode":"81543",
    "sg:province":"Bayern",
    "wof:name":"K & V Management Consulting Group Gmbh",
    "wof:placetype":"venue"
},
  "geometry": {"coordinates":[11.5701990128,48.1114692688],"type":"Point"}
}