{
  "type": "Feature",
  "properties": {
    "iso:country":"DE",
    "sg:address":"Langemarckstr. 24",
    "sg:city":"Essen",
    "sg:phone":"+49 201/29995",
    "sg:postcode":"45141",
    "sg:province":"Nordrhein-Westfalen",
    "wof:name":"Hermann Sprenger Gmbh",
    "wof:placetype":"venue"
},
  "geometry": {"coordinates":[7.0508828163,51.4710502625],"type":"Point"}
}