{
  "type": "Feature",
  "properties": {
    "iso:country":"DE",
    "sg:address":"Waldweg 45",
    "sg:city":"H\u00fcnxe",
    "sg:phone":"+49 2064/30301",
    "sg:postcode":"46569",
    "sg:province":"Nordrhein-Westfalen",
    "wof:name":"Kath. Pfarramt St. Albertus Magnus",
    "wof:placetype":"venue"
},
  "geometry": {"coordinates":[6.7393198013,51.601108551],"type":"Point"}
}