{
  "type": "Feature",
  "properties": {
    "iso:country":"DE",
    "sg:address":"Rheinstr 19",
    "sg:city":"Stadtallendorf",
    "sg:phone":"+49 6428/70502",
    "sg:postcode":"35260",
    "sg:province":"Hessen",
    "wof:name":"Kap Beteiligungs-ag",
    "wof:placetype":"venue"
},
  "geometry": {"coordinates":[9.0013875961,50.8233261108],"type":"Point"}
}