{
  "type": "Feature",
  "properties": {
    "iso:country":"DE",
    "sg:address":"B\u00e4ckergasse 1",
    "sg:city":"Viechtach",
    "sg:phone":"+49 9942/902002",
    "sg:postcode":"94234",
    "sg:province":"Bayern",
    "wof:name":"Nkd City-kauf",
    "wof:placetype":"venue"
},
  "geometry": {"coordinates":[12.886067,49.080875],"type":"Point"}
}