{
  "type": "Feature",
  "properties": {
    "iso:country":"DE",
    "sg:address":"Siemensstr. 2",
    "sg:city":"Lichtenstein",
    "sg:postcode":"72805",
    "sg:province":"Baden-W\u00fcrttemberg",
    "wof:name":"Litex Lichtensteiner Textil Gmbh",
    "wof:placetype":"venue"
},
  "geometry": {"coordinates":[9.2535495758,48.4422225952],"type":"Point"}
}