{
  "type": "Feature",
  "properties": {
    "iso:country":"DE",
    "sg:address":"Starkenburger Str. 23",
    "sg:city":"Gernsheim",
    "sg:phone":"+49 6258/51714",
    "sg:postcode":"64579",
    "sg:province":"Hessen",
    "wof:name":"Klaus-peter Roth Kg",
    "wof:placetype":"venue"
},
  "geometry": {"coordinates":[8.4991436005,49.7591552734],"type":"Point"}
}