{
  "type": "Feature",
  "properties": {
    "iso:country":"DE",
    "sg:address":"Friedrichsplatz 19 - 20",
    "sg:city":"Kassel",
    "sg:phone":"+49 561/91870",
    "sg:postcode":"34117",
    "sg:province":"Hessen",
    "wof:name":"Leffers Ag",
    "wof:placetype":"venue"
},
  "geometry": {"coordinates":[9.490396,51.312099],"type":"Point"}
}