{
  "type": "Feature",
  "properties": {
    "iso:country":"DE",
    "sg:address":"Albert-Schweitzer-Str. 13",
    "sg:city":"Magdeburg",
    "sg:phone":"+49 391/2533015",
    "sg:postcode":"39126",
    "sg:province":"Sachsen-Anhalt",
    "wof:name":"Harald Trzewik",
    "wof:placetype":"venue"
},
  "geometry": {"coordinates":[11.629665,52.172825],"type":"Point"}
}