{
  "type": "Feature",
  "properties": {
    "iso:country":"DE",
    "sg:address":"Ingolst\u00e4dter Str. 18",
    "sg:city":"Neumarkt",
    "sg:phone":"+49 9181/2390",
    "sg:postcode":"92318",
    "sg:province":"Bayern",
    "wof:name":"Stadtwerke Neumarkt",
    "wof:placetype":"venue"
},
  "geometry": {"coordinates":[11.460472,49.272106],"type":"Point"}
}