{
  "type": "Feature",
  "properties": {
    "iso:country":"DE",
    "sg:address":"Turmstr. 15",
    "sg:city":"Winnenden",
    "sg:phone":"+49 7195/3161",
    "sg:postcode":"71364",
    "sg:province":"Baden-W\u00fcrttemberg",
    "wof:name":"Hans-dieter Lorenz Rechtsanwalt",
    "wof:placetype":"venue"
},
  "geometry": {"coordinates":[9.3979053497,48.8769454956],"type":"Point"}
}