{
  "type": "Feature",
  "properties": {
    "iso:country":"DE",
    "sg:address":"Starnberger Str. 25",
    "sg:city":"Gauting",
    "sg:phone":"+49 89/8507878",
    "sg:postcode":"82131",
    "sg:province":"Bayern",
    "wof:name":"Gudrun Misch-rohrmoser Praxis F\u00fcr Krankengymnastik",
    "wof:placetype":"venue"
},
  "geometry": {"coordinates":[11.377733,48.06374],"type":"Point"}
}