{
  "type": "Feature",
  "properties": {
    "iso:country":"DE",
    "sg:address":"Donaustr. 19",
    "sg:city":"Kelheim",
    "sg:phone":"+49 9441/3380",
    "sg:postcode":"93309",
    "sg:province":"Bayern",
    "wof:name":"Andreas Aman",
    "wof:placetype":"venue"
},
  "geometry": {"coordinates":[11.8716430664,48.9172554016],"type":"Point"}
}