{
  "type": "Feature",
  "properties": {
    "iso:country":"DE",
    "sg:address":"Wilhelmstr. 9",
    "sg:city":"Alfeld",
    "sg:phone":"+49 5181/5357",
    "sg:postcode":"31061",
    "sg:province":"Niedersachsen",
    "wof:name":"A. Bartels",
    "wof:placetype":"venue"
},
  "geometry": {"coordinates":[9.837807,51.96368],"type":"Point"}
}