{
  "type": "Feature",
  "properties": {
    "iso:country":"DE",
    "sg:address":"Herzogenauracher Str. 3",
    "sg:city":"F\u00fcrth",
    "sg:phone":"+49 911/976840",
    "sg:postcode":"90768",
    "sg:province":"Bayern",
    "wof:name":"Brauerei Dorn Gmbh",
    "wof:placetype":"venue"
},
  "geometry": {"coordinates":[10.966571,49.527458],"type":"Point"}
}