{
  "type": "Feature",
  "properties": {
    "iso:country":"DE",
    "sg:address":"Schwalbenring 20",
    "sg:city":"Metzingen",
    "sg:phone":"+49 7123/971070",
    "sg:postcode":"72555",
    "sg:province":"Baden-W\u00fcrttemberg",
    "wof:name":"Gardilux Garten- Ausstattung Gmbh",
    "wof:placetype":"venue"
},
  "geometry": {"coordinates":[9.308352,48.521664],"type":"Point"}
}