{
  "type": "Feature",
  "properties": {
    "iso:country":"DE",
    "sg:address":"Am Ziegelgraben 14",
    "sg:city":"Schorndorf",
    "sg:postcode":"73614",
    "sg:province":"Baden-W\u00fcrttemberg",
    "wof:name":"Schatz Grundst\u00fccksges. Gmbh & Co. Kg",
    "wof:placetype":"venue"
},
  "geometry": {"coordinates":[9.5158815384,48.8010139465],"type":"Point"}
}