{
  "type": "Feature",
  "properties": {
    "iso:country":"DE",
    "sg:address":"Teichstr. 6",
    "sg:city":"Wittenborn",
    "sg:phone":"+49 4554/905656",
    "sg:postcode":"23829",
    "sg:province":"Schleswig-Holstein",
    "wof:name":"Immobilien Agentur Sarau Gmbh",
    "wof:placetype":"venue"
},
  "geometry": {"coordinates":[10.2255315781,53.9205131531],"type":"Point"}
}