{
  "type": "Feature",
  "properties": {
    "iso:country":"DE",
    "sg:address":"Kirchstr. 14",
    "sg:city":"Beuron",
    "sg:phone":"+49 7579/844",
    "sg:postcode":"88631",
    "sg:province":"Baden-W\u00fcrttemberg",
    "wof:name":"M. Aky\u00fcrek",
    "wof:placetype":"venue"
},
  "geometry": {"coordinates":[9.037415,48.083439],"type":"Point"}
}