{
  "type": "Feature",
  "properties": {
    "iso:country":"DE",
    "sg:address":"Mayener-Strasse",
    "sg:city":"Langenfeld",
    "sg:phone":"+49 2655",
    "sg:postcode":"56729",
    "sg:province":"Rheinland-Pfalz",
    "wof:name":"Willkommen Beim Hotel-anker In Der Eifel",
    "wof:placetype":"venue"
},
  "geometry": {"coordinates":[7.095877,50.376102],"type":"Point"}
}