{
  "type": "Feature",
  "properties": {
    "iso:country":"DE",
    "sg:address":"Aachener Str. 48",
    "sg:city":"Rheinbach",
    "sg:phone":"+49 2226/10345",
    "sg:postcode":"53359",
    "sg:province":"Nordrhein-Westfalen",
    "wof:name":"Karl Schurz",
    "wof:placetype":"venue"
},
  "geometry": {"coordinates":[6.938485,50.635696],"type":"Point"}
}