{
  "type": "Feature",
  "properties": {
    "iso:country":"DE",
    "sg:address":"K\u00f6lner Str. 94",
    "sg:city":"J\u00fcchen",
    "sg:phone":"+49 2165/911112",
    "sg:postcode":"41363",
    "sg:province":"Nordrhein-Westfalen",
    "wof:name":"Tanzlokal Bolero",
    "wof:placetype":"venue"
},
  "geometry": {"coordinates":[6.5146417618,51.0968742371],"type":"Point"}
}