{
  "type": "Feature",
  "properties": {
    "iso:country":"DE",
    "sg:address":"Waldstr. 26",
    "sg:city":"Hennigsdorf",
    "sg:phone":"+49 3302/234541",
    "sg:postcode":"16761",
    "sg:province":"Brandenburg",
    "wof:name":"Werner Berndt",
    "wof:placetype":"venue"
},
  "geometry": {"coordinates":[13.1966295242,52.6444320679],"type":"Point"}
}