{
  "type": "Feature",
  "properties": {
    "iso:country":"DE",
    "sg:address":"Herolder Str. 3A",
    "sg:city":"Thum",
    "sg:phone":"+49 37297/4225",
    "sg:postcode":"09419",
    "sg:province":"Sachsen",
    "wof:name":"Finanz- Und Versicherungs- Kontor Thum",
    "wof:placetype":"venue"
},
  "geometry": {"coordinates":[12.9744195938,50.6784934998],"type":"Point"}
}