{
  "type": "Feature",
  "properties": {
    "iso:country":"DE",
    "sg:address":"Germanstr. 28/1",
    "sg:city":"Villingen-Schwenningen",
    "sg:postcode":"78048",
    "sg:province":"Baden-W\u00fcrttemberg",
    "wof:name":"H. K. Kapital Gmbh & Co. Kg",
    "wof:placetype":"venue"
},
  "geometry": {"coordinates":[8.4317102432,48.074131012],"type":"Point"}
}