{
  "type": "Feature",
  "properties": {
    "iso:country":"DE",
    "sg:address":"Goethestr. 27",
    "sg:city":"M\u00fclheim-K\u00e4rlich",
    "sg:phone":"+49 2630/4160",
    "sg:postcode":"56218",
    "sg:province":"Rheinland-Pfalz",
    "wof:name":"Hans Hommer",
    "wof:placetype":"venue"
},
  "geometry": {"coordinates":[7.5074567795,50.3986778259],"type":"Point"}
}