{
  "type": "Feature",
  "properties": {
    "iso:country":"DE",
    "sg:address":"Bergzaberner Str. 45",
    "sg:city":"Karlsruhe",
    "sg:phone":"+49 721/7569281",
    "sg:postcode":"76187",
    "sg:province":"Baden-W\u00fcrttemberg",
    "wof:name":"Ibrahim Aladdin Ingenieur",
    "wof:placetype":"venue"
},
  "geometry": {"coordinates":[8.3708667755,49.0372810364],"type":"Point"}
}