{
  "type": "Feature",
  "properties": {
    "iso:country":"DE",
    "sg:address":"Helmholtzstr. 5",
    "sg:city":"Allmersbach",
    "sg:phone":"+49 7191/51734",
    "sg:postcode":"71573",
    "sg:province":"Baden-W\u00fcrttemberg",
    "wof:name":"Gerhard Diessner Werkzeuge",
    "wof:placetype":"venue"
},
  "geometry": {"coordinates":[9.46377,48.903107],"type":"Point"}
}