{
  "type": "Feature",
  "properties": {
    "iso:country":"DE",
    "sg:address":"Sch\u00fctzenhof 67",
    "sg:city":"Meppen",
    "sg:phone":"+49 5931/3008",
    "sg:postcode":"49716",
    "sg:province":"Niedersachsen",
    "wof:name":"Esso Mineral\u00f6l Grossh.",
    "wof:placetype":"venue"
},
  "geometry": {"coordinates":[7.2842588425,52.7056007385],"type":"Point"}
}