{
  "type": "Feature",
  "properties": {
    "iso:country":"DE",
    "sg:address":"Marktstr. 71",
    "sg:city":"Stuttgart",
    "sg:phone":"+49 711/564788",
    "sg:postcode":"70372",
    "sg:province":"Baden-W\u00fcrttemberg",
    "wof:name":"Stadtmudeum Bad Cannstatt",
    "wof:placetype":"venue"
},
  "geometry": {"coordinates":[9.213192,48.805672],"type":"Point"}
}