{
  "type": "Feature",
  "properties": {
    "iso:country":"DE",
    "sg:address":"Rugenbarg 250",
    "sg:city":"Hamburg",
    "sg:postcode":"22549",
    "sg:province":"Hamburg",
    "wof:name":"Hermann Kerckhoff Gmbh",
    "wof:placetype":"venue"
},
  "geometry": {"coordinates":[9.8722982407,53.5860939026],"type":"Point"}
}