{
  "type": "Feature",
  "properties": {
    "iso:country":"DE",
    "sg:address":"W\u00f6lmsdorfer Weg 5",
    "sg:city":"Niederg\u00f6rsdorf",
    "sg:phone":"+49 33741/6950",
    "sg:postcode":"14913",
    "sg:province":"Brandenburg",
    "wof:name":"Taw Technischer Anlagenbau F\u00fcr Wasserwirtschaft Gmbh & Co. Kg",
    "wof:placetype":"venue"
},
  "geometry": {"coordinates":[12.977471,51.975677],"type":"Point"}
}