{
  "type": "Feature",
  "properties": {
    "iso:country":"DE",
    "sg:address":"Am Klosteracker 19",
    "sg:city":"Ballrechten-Dottingen",
    "sg:phone":"+49 7634/69735",
    "sg:postcode":"79282",
    "sg:province":"Baden-W\u00fcrttemberg",
    "wof:name":"Medien Design Studio Thomas Scherer",
    "wof:placetype":"venue"
},
  "geometry": {"coordinates":[7.694215,47.859009],"type":"Point"}
}