{
  "type": "Feature",
  "properties": {
    "iso:country":"DE",
    "sg:address":"W\u00fcrmm\u00fchle 1",
    "sg:city":"Dachau",
    "sg:phone":"+49 8131/15546",
    "sg:postcode":"85221",
    "sg:province":"Bayern",
    "wof:name":"Simon Kraus Gmbh Kunst- M\u00fchle Dachau W\u00fcrmm\u00fchle",
    "wof:placetype":"venue"
},
  "geometry": {"coordinates":[11.46402,48.279339],"type":"Point"}
}