{
  "type": "Feature",
  "properties": {
    "iso:country":"DE",
    "sg:address":"Prinzregentenstr. 45",
    "sg:city":"Rodalben",
    "sg:phone":"+49 6331/17249",
    "sg:postcode":"66976",
    "sg:province":"Rheinland-Pfalz",
    "wof:name":"Brigitte Kutschmann Steuerberaterin",
    "wof:placetype":"venue"
},
  "geometry": {"coordinates":[7.6381587982,49.239151001],"type":"Point"}
}