{
  "type": "Feature",
  "properties": {
    "iso:country":"DE",
    "sg:address":"Ammergaustr. 43",
    "sg:city":"Oldenburg",
    "sg:postcode":"26123",
    "sg:province":"Niedersachsen",
    "wof:name":"M & G It Gmbh & Co. Kg",
    "wof:placetype":"venue"
},
  "geometry": {"coordinates":[8.229511261,53.1621322632],"type":"Point"}
}