{
  "type": "Feature",
  "properties": {
    "iso:country":"DE",
    "sg:address":"Bismarckstr. 18",
    "sg:city":"Eschweiler",
    "sg:phone":"+49 2403/23281",
    "sg:postcode":"52249",
    "sg:province":"Nordrhein-Westfalen",
    "wof:name":"Gebr. Hompesch",
    "wof:placetype":"venue"
},
  "geometry": {"coordinates":[6.262632,50.815643],"type":"Point"}
}