{
  "type": "Feature",
  "properties": {
    "iso:country":"DE",
    "sg:address":"Fischergasse 19",
    "sg:city":"Aschaffenburg",
    "sg:phone":"+49 6021/30990",
    "sg:postcode":"63739",
    "sg:province":"Bayern",
    "wof:name":"Dieter Beham Architekt",
    "wof:placetype":"venue"
},
  "geometry": {"coordinates":[9.143045,49.970776],"type":"Point"}
}