{
  "type": "Feature",
  "properties": {
    "iso:country":"DE",
    "sg:address":"Wacholderweg 13",
    "sg:city":"Elmshorn",
    "sg:phone":"+49 4121/94804",
    "sg:postcode":"25336",
    "sg:province":"Schleswig-Holstein",
    "wof:name":"Ursula Pfeiffer Steuerberaterin",
    "wof:placetype":"venue"
},
  "geometry": {"coordinates":[9.6595001221,53.7300071716],"type":"Point"}
}