{
  "type": "Feature",
  "properties": {
    "iso:country":"DE",
    "sg:address":"Rote Str. 36",
    "sg:city":"Flensburg",
    "sg:phone":"+49 461/17333",
    "sg:postcode":"24937",
    "sg:province":"Schleswig-Holstein",
    "wof:name":"Hotel Am Rathaus Gmbh",
    "wof:placetype":"venue"
},
  "geometry": {"coordinates":[9.4356765747,54.7813606262],"type":"Point"}
}