{
  "type": "Feature",
  "properties": {
    "iso:country":"DE",
    "sg:address":"Waltersteig 1",
    "sg:city":"Eurasburg",
    "sg:phone":"+49 8179/1020",
    "sg:postcode":"82547",
    "sg:province":"Bayern",
    "wof:name":"Vollrad Ritter Von Poschinger",
    "wof:placetype":"venue"
},
  "geometry": {"coordinates":[11.4296197891,47.8434638977],"type":"Point"}
}