{
  "type": "Feature",
  "properties": {
    "iso:country":"DE",
    "sg:address":"Heinrich-P\u00fcts-Str. 35",
    "sg:city":"Rheda-Wiedenbr\u00fcck",
    "sg:phone":"+49 5242/36237",
    "sg:postcode":"33378",
    "sg:province":"Nordrhein-Westfalen",
    "wof:name":"Erich Lappe",
    "wof:placetype":"venue"
},
  "geometry": {"coordinates":[8.3068389893,51.8307380676],"type":"Point"}
}