{
  "type": "Feature",
  "properties": {
    "iso:country":"DE",
    "sg:address":"Klaas M\u00fchle",
    "sg:city":"Herborn",
    "sg:phone":"+49 2772/55119",
    "sg:postcode":"35745",
    "sg:province":"Hessen",
    "wof:name":"R. Klaas Maschinen",
    "wof:placetype":"venue"
},
  "geometry": {"coordinates":[8.258533,50.65934],"type":"Point"}
}