{
  "type": "Feature",
  "properties": {
    "iso:country":"DE",
    "sg:address":"St.-Georg-Str. 58",
    "sg:city":"Rostock",
    "sg:phone":"+49 381/2423260",
    "sg:postcode":"18055",
    "sg:province":"Mecklenburg-Vorpommern",
    "wof:name":"Bauma Gmbh",
    "wof:placetype":"venue"
},
  "geometry": {"coordinates":[12.127525,54.083237],"type":"Point"}
}