{
  "type": "Feature",
  "properties": {
    "iso:country":"DE",
    "sg:address":"Im Hasseldamm 21",
    "sg:city":"Korschenbroich",
    "sg:phone":"+49 2161/99880",
    "sg:postcode":"41352",
    "sg:province":"Nordrhein-Westfalen",
    "wof:name":"Asem Industrieberatung Und Vermittlung Gmbh",
    "wof:placetype":"venue"
},
  "geometry": {"coordinates":[6.546227932,51.2158317566],"type":"Point"}
}