{
  "type": "Feature",
  "properties": {
    "iso:country":"DE",
    "sg:address":"Moritzburger Str. 74",
    "sg:city":"Coswig",
    "sg:phone":"+49 3523/63817",
    "sg:postcode":"01640",
    "sg:province":"Sachsen",
    "wof:name":"Constanze Reinhold",
    "wof:placetype":"venue"
},
  "geometry": {"coordinates":[13.5896949768,51.1383171082],"type":"Point"}
}