{
  "type": "Feature",
  "properties": {
    "iso:country":"DE",
    "sg:address":"Schulstr. 19",
    "sg:city":"Lindenberg",
    "sg:postcode":"15864",
    "sg:province":"Brandenburg",
    "wof:name":"Lhe Bauplanungs Und Betreuungs Gmbh",
    "wof:placetype":"venue"
},
  "geometry": {"coordinates":[14.121693,52.206581],"type":"Point"}
}