{
  "type": "Feature",
  "properties": {
    "iso:country":"DE",
    "sg:address":"Lederstr. 28",
    "sg:city":"Hamburg",
    "sg:postcode":"22525",
    "sg:province":"Hamburg",
    "wof:name":"Ibk Gesellschaft F\u00fcr Engineering Software Und",
    "wof:placetype":"venue"
},
  "geometry": {"coordinates":[9.9092407227,53.5899887085],"type":"Point"}
}