{
  "type": "Feature",
  "properties": {
    "iso:country":"DE",
    "sg:address":"Schwarzenbach 14",
    "sg:city":"Sch\u00f6nwald",
    "sg:phone":"+49 7722/5182",
    "sg:postcode":"78141",
    "sg:province":"Baden-W\u00fcrttemberg",
    "wof:name":"Naturfreundehaus K\u00fcferh\u00e4usle",
    "wof:placetype":"venue"
},
  "geometry": {"coordinates":[8.1971082687,48.1183280945],"type":"Point"}
}