{
  "type": "Feature",
  "properties": {
    "iso:country":"DE",
    "sg:address":"Augsburger Str. 25",
    "sg:city":"N\u00f6rdlingen",
    "sg:phone":"+49 9081/88015",
    "sg:postcode":"86720",
    "sg:province":"Bayern",
    "wof:name":"K\u00fcchenstudio Deffner",
    "wof:placetype":"venue"
},
  "geometry": {"coordinates":[10.4970769882,48.8467674255],"type":"Point"}
}