{
  "type": "Feature",
  "properties": {
    "iso:country":"DE",
    "sg:address":"Luisenstr. 9",
    "sg:city":"Bad D\u00fcrrheim",
    "sg:phone":"+49 7726/6660",
    "sg:postcode":"78073",
    "sg:province":"Baden-W\u00fcrttemberg",
    "wof:name":"Urban-brigitte- Und Johannes Goll-stiftung",
    "wof:placetype":"venue"
},
  "geometry": {"coordinates":[8.5325689316,48.0176887512],"type":"Point"}
}