{
  "type": "Feature",
  "properties": {
    "iso:country":"DE",
    "sg:address":"Gemsenstr. 2",
    "sg:city":"Kaarst",
    "sg:phone":"+49 2131/62928",
    "sg:postcode":"41564",
    "sg:province":"Nordrhein-Westfalen",
    "wof:name":"Josef Stamm",
    "wof:placetype":"venue"
},
  "geometry": {"coordinates":[6.5955848694,51.2307128906],"type":"Point"}
}