{
  "type": "Feature",
  "properties": {
    "iso:country":"DE",
    "sg:address":"Vattmannstr. 2",
    "sg:city":"Paderborn",
    "sg:phone":"+49 5251/55717",
    "sg:postcode":"33100",
    "sg:province":"Nordrhein-Westfalen",
    "wof:name":"Soldenhoff-fotowerbung Gmbh",
    "wof:placetype":"venue"
},
  "geometry": {"coordinates":[8.7965326309,51.7256813049],"type":"Point"}
}