{
  "type": "Feature",
  "properties": {
    "iso:country":"DE",
    "sg:address":"Bahnhofstr. 5",
    "sg:city":"Z\u00f6blitz",
    "sg:phone":"+49 37363/7312",
    "sg:postcode":"09517",
    "sg:province":"Sachsen",
    "wof:name":"P. Zenker",
    "wof:placetype":"venue"
},
  "geometry": {"coordinates":[13.229439,50.658649],"type":"Point"}
}