{
  "type": "Feature",
  "properties": {
    "iso:country":"DE",
    "sg:address":"Kochwiesenstrasse 41",
    "sg:city":"Koeln",
    "sg:postcode":"51067",
    "sg:province":"Nordrhein-Westfalen",
    "wof:name":"Precious Stone Synthetic, Edelsteine Syntherisch.",
    "wof:placetype":"venue"
},
  "geometry": {"coordinates":[7.050963,50.965473],"type":"Point"}
}