{
  "type": "Feature",
  "properties": {
    "iso:country":"DE",
    "sg:address":"Reutlinger Str. 18",
    "sg:city":"Metzingen",
    "sg:phone":"+49 7123/14916",
    "sg:postcode":"72555",
    "sg:province":"Baden-W\u00fcrttemberg",
    "wof:name":"Gerhard Schmid Steuerberater",
    "wof:placetype":"venue"
},
  "geometry": {"coordinates":[9.2833251953,48.5383987427],"type":"Point"}
}