{
  "type": "Feature",
  "properties": {
    "iso:country":"DE",
    "sg:address":"Am Steig 14",
    "sg:city":"Rottenburg-Hailfingen",
    "sg:phone":"+49 721",
    "sg:postcode":"72108",
    "sg:province":"Baden-W\u00fcrttemberg",
    "wof:name":"Privatschulungen Und Softwareentwichlung Psuse",
    "wof:placetype":"venue"
},
  "geometry": {"coordinates":[8.865599,48.52536],"type":"Point"}
}