{
  "type": "Feature",
  "properties": {
    "iso:country":"DE",
    "sg:address":"Kaiser-Wilhelm-Platz 1",
    "sg:city":"Essen",
    "sg:phone":"+49 201/517242",
    "sg:postcode":"45276",
    "sg:province":"Nordrhein-Westfalen",
    "wof:name":"Barbie",
    "wof:placetype":"venue"
},
  "geometry": {"coordinates":[7.0772547722,51.4480133057],"type":"Point"}
}