{
  "type": "Feature",
  "properties": {
    "iso:country":"DE",
    "sg:address":"G\u00e4nsestr. 6-8",
    "sg:city":"Warendorf",
    "sg:postcode":"48231",
    "sg:province":"Nordrhein-Westfalen",
    "wof:name":"Olympic Filmtheaterbetriebe Heinz Riech & Sohn",
    "wof:placetype":"venue"
},
  "geometry": {"coordinates":[7.9674940109,51.9230766296],"type":"Point"}
}