{
  "type": "Feature",
  "properties": {
    "iso:country":"DE",
    "sg:address":"Georg-Fischer-Str 40a",
    "sg:city":"Singen",
    "sg:phone":"+49 7731/68110",
    "sg:postcode":"78224",
    "sg:province":"Baden-W\u00fcrttemberg",
    "wof:name":"Maytec Me\u00df- Und Regeltechnik Gmbh",
    "wof:placetype":"venue"
},
  "geometry": {"coordinates":[8.8504104614,47.7528572083],"type":"Point"}
}