{
  "type": "Feature",
  "properties": {
    "iso:country":"DE",
    "sg:address":"Eicken 3",
    "sg:city":"Kierspe",
    "sg:phone":"+49 2359/2187",
    "sg:postcode":"58566",
    "sg:province":"Nordrhein-Westfalen",
    "wof:name":"Manfred Rosenthal",
    "wof:placetype":"venue"
},
  "geometry": {"coordinates":[7.579048,51.130184],"type":"Point"}
}