{
  "type": "Feature",
  "properties": {
    "iso:country":"DE",
    "sg:address":"Bergstr. 9",
    "sg:city":"Zierenberg",
    "sg:phone":"+49 5606/56826",
    "sg:postcode":"34289",
    "sg:province":"Hessen",
    "wof:name":"Manfred Pape",
    "wof:placetype":"venue"
},
  "geometry": {"coordinates":[9.275637,51.321125],"type":"Point"}
}