{
  "type": "Feature",
  "properties": {
    "iso:country":"DE",
    "sg:address":"Weiersh\u00e4user Str. 26",
    "sg:city":"Weimar",
    "sg:phone":"+49 6421/78848",
    "sg:postcode":"35096",
    "sg:province":"Hessen",
    "wof:name":"Gastst\u00e4tte Konrad Beimborn",
    "wof:placetype":"venue"
},
  "geometry": {"coordinates":[8.6645450592,50.7851829529],"type":"Point"}
}