{
  "type": "Feature",
  "properties": {
    "iso:country":"DE",
    "sg:address":"Kupferstr. 12",
    "sg:city":"Kall",
    "sg:phone":"+49 2441/775055",
    "sg:postcode":"53925",
    "sg:province":"Nordrhein-Westfalen",
    "wof:name":"Schmitz Ml Warenhandels Gmbh",
    "wof:placetype":"venue"
},
  "geometry": {"coordinates":[6.5641589165,50.5419197083],"type":"Point"}
}