{
  "type": "Feature",
  "properties": {
    "iso:country":"DE",
    "sg:address":"B\u00fclthausen 27",
    "sg:city":"Mettmann",
    "sg:phone":"+49 2104/54486",
    "sg:postcode":"40822",
    "sg:province":"Nordrhein-Westfalen",
    "wof:name":"Ernst Terjung",
    "wof:placetype":"venue"
},
  "geometry": {"coordinates":[6.973518,51.279057],"type":"Point"}
}