{
  "type": "Feature",
  "properties": {
    "iso:country":"DE",
    "sg:address":"Babenbergerring 36 a",
    "sg:city":"Bamberg",
    "sg:phone":"+49 951/952340",
    "sg:postcode":"96049",
    "sg:province":"Bayern",
    "wof:name":"Reiseb\u00fcro Dirks Inh. Rita Dirks",
    "wof:placetype":"venue"
},
  "geometry": {"coordinates":[10.8743877411,49.8764190674],"type":"Point"}
}