{
  "type": "Feature",
  "properties": {
    "iso:country":"DE",
    "sg:address":"Georg-Kae\u00df-Str. 20",
    "sg:city":"Bad Schussenried",
    "sg:phone":"+49 7583/1690",
    "sg:postcode":"88427",
    "sg:province":"Baden-W\u00fcrttemberg",
    "wof:name":"Harald Widmann Steuerberater",
    "wof:placetype":"venue"
},
  "geometry": {"coordinates":[9.6564702988,48.0042610168],"type":"Point"}
}