{
  "type": "Feature",
  "properties": {
    "iso:country":"DE",
    "sg:address":"Kippdorfstr. 29",
    "sg:city":"Remscheid",
    "sg:phone":"+49 2191/76446",
    "sg:postcode":"42857",
    "sg:province":"Nordrhein-Westfalen",
    "wof:name":"Anna Kesting",
    "wof:placetype":"venue"
},
  "geometry": {"coordinates":[7.1781439781,51.1751213074],"type":"Point"}
}