{
  "type": "Feature",
  "properties": {
    "iso:country":"DE",
    "sg:address":"Auf dem Rausch 3",
    "sg:city":"Konz",
    "sg:postcode":"54329",
    "sg:province":"Rheinland-Pfalz",
    "wof:name":"Klaus Forber",
    "wof:placetype":"venue"
},
  "geometry": {"coordinates":[6.607589,49.683193],"type":"Point"}
}