{
  "type": "Feature",
  "properties": {
    "iso:country":"DE",
    "sg:address":"Louis-Leitz-Str. 1",
    "sg:city":"Bremen",
    "sg:postcode":"28355",
    "sg:province":"Bremen",
    "wof:name":"Lbv Launspach Beratungs- Und Vertriebsgesellschaft Mbh",
    "wof:placetype":"venue"
},
  "geometry": {"coordinates":[8.910309,53.083359],"type":"Point"}
}