{
  "type": "Feature",
  "properties": {
    "iso:country":"DE",
    "sg:address":"Postfach 120",
    "sg:city":"Tuttlingen",
    "sg:phone":"+49 7461/700215",
    "sg:postcode":"78502",
    "sg:province":"Baden-W\u00fcrttemberg",
    "wof:name":"Stiftung Der Kreissparkasse Tuttlingen Z. F\u00f6rd. Innovat.",
    "wof:placetype":"venue"
},
  "geometry": {"coordinates":[8.7995796204,47.9894104004],"type":"Point"}
}