{
  "type": "Feature",
  "properties": {
    "iso:country":"DE",
    "sg:address":"Mauerstr. 19",
    "sg:city":"Aachen",
    "sg:phone":"+49 6561/940540",
    "sg:postcode":"52064",
    "sg:province":"Nordrhein-Westfalen",
    "wof:name":"Itb Elektrohandels Gmbh",
    "wof:placetype":"venue"
},
  "geometry": {"coordinates":[6.0745630264,50.7743263245],"type":"Point"}
}