{
  "type": "Feature",
  "properties": {
    "iso:country":"DE",
    "sg:address":"Malchinerstr.22",
    "sg:city":"Stavenhagen",
    "sg:phone":"+49 39954/30758",
    "sg:postcode":"17153",
    "sg:province":"Mecklenburg-Vorpommern",
    "wof:name":"Generalvertretung Der Devk",
    "wof:placetype":"venue"
},
  "geometry": {"coordinates":[12.9704303741,53.7102355957],"type":"Point"}
}