{
  "type": "Feature",
  "properties": {
    "iso:country":"DE",
    "sg:address":"Kirchstr. 3",
    "sg:city":"Seevetal",
    "sg:phone":"+49 4105/54777",
    "sg:postcode":"21218",
    "sg:province":"Niedersachsen",
    "wof:name":"Carola Werner Masseurin",
    "wof:placetype":"venue"
},
  "geometry": {"coordinates":[9.979251,53.384686],"type":"Point"}
}