{
  "type": "Feature",
  "properties": {
    "iso:country":"DE",
    "sg:address":"Dorfstr. 22",
    "sg:city":"Bassum",
    "sg:phone":"+49 4241/2397",
    "sg:postcode":"27211",
    "sg:province":"Niedersachsen",
    "wof:name":"Bernd Lampe",
    "wof:placetype":"venue"
},
  "geometry": {"coordinates":[8.7859010696,52.8721466064],"type":"Point"}
}