{
  "type": "Feature",
  "properties": {
    "iso:country":"DE",
    "sg:address":"Warnitzer Str. 5",
    "sg:city":"Berlin",
    "sg:phone":"+49 30/9285939",
    "sg:postcode":"13057",
    "sg:province":"Berlin",
    "wof:name":"Norbert Filla",
    "wof:placetype":"venue"
},
  "geometry": {"coordinates":[13.520593,52.566284],"type":"Point"}
}