{
  "type": "Feature",
  "properties": {
    "iso:country":"DE",
    "sg:address":"Alte Mainzer Str.",
    "sg:city":"Oberwesel",
    "sg:phone":"+49 6744/8103",
    "sg:postcode":"55430",
    "sg:province":"Rheinland-Pfalz",
    "wof:name":"Werner Brager",
    "wof:placetype":"venue"
},
  "geometry": {"coordinates":[7.742451,50.095829],"type":"Point"}
}