{
  "type": "Feature",
  "properties": {
    "iso:country":"DE",
    "sg:address":"Dorfstr. 33a",
    "sg:city":"Oberammergau",
    "sg:phone":"+49 8822/259",
    "sg:postcode":"82487",
    "sg:province":"Bayern",
    "wof:name":"Cafe Italia",
    "wof:placetype":"venue"
},
  "geometry": {"coordinates":[11.064403,47.597237],"type":"Point"}
}