{
  "type": "Feature",
  "properties": {
    "iso:country":"DE",
    "sg:address":"Am Langen Weiher 21",
    "sg:city":"D\u00fcsseldorf",
    "sg:phone":"+49 211/791789",
    "sg:postcode":"40589",
    "sg:province":"Nordrhein-Westfalen",
    "wof:name":"Katholisches Pfarramt St. Joseph",
    "wof:placetype":"venue"
},
  "geometry": {"coordinates":[6.8336510658,51.1770820618],"type":"Point"}
}