{
  "type": "Feature",
  "properties": {
    "iso:country":"DE",
    "sg:address":"Gustav-Hertz-Str. 16",
    "sg:city":"Kamen",
    "sg:phone":"+49 2307/32813",
    "sg:postcode":"59174",
    "sg:province":"Nordrhein-Westfalen",
    "wof:name":"R. Wyborny",
    "wof:placetype":"venue"
},
  "geometry": {"coordinates":[7.606106,51.573441],"type":"Point"}
}