{
  "type": "Feature",
  "properties": {
    "iso:country":"DE",
    "sg:address":"Nach den Kiefern 24",
    "sg:city":"Plauen",
    "sg:phone":"+49 3741/131966",
    "sg:postcode":"08523",
    "sg:province":"Sachsen",
    "wof:name":"Matthias Fritsche",
    "wof:placetype":"venue"
},
  "geometry": {"coordinates":[12.0984268188,50.4870185852],"type":"Point"}
}