{
  "type": "Feature",
  "properties": {
    "iso:country":"DE",
    "sg:address":"Theisbr\u00fcgger Str. 12",
    "sg:city":"Drochtersen",
    "sg:phone":"+49 4143/280",
    "sg:postcode":"21706",
    "sg:province":"Niedersachsen",
    "wof:name":"Heinz Von Allw\u00f6rden",
    "wof:placetype":"venue"
},
  "geometry": {"coordinates":[9.341652,53.70676],"type":"Point"}
}