{
  "type": "Feature",
  "properties": {
    "iso:country":"DE",
    "sg:address":"Eislebener Weg 4",
    "sg:city":"Mannheim",
    "sg:phone":"+49 621/705889",
    "sg:postcode":"68309",
    "sg:province":"Baden-W\u00fcrttemberg",
    "wof:name":"Wal Baubetreuung Beteiligungs Gmbh",
    "wof:placetype":"venue"
},
  "geometry": {"coordinates":[8.550755,49.508549],"type":"Point"}
}