{
  "type": "Feature",
  "properties": {
    "iso:country":"DE",
    "sg:address":"Otto-R\u00f6hm-Str. 90 A",
    "sg:city":"Darmstadt",
    "sg:phone":"+49 6151/891113",
    "sg:postcode":"64293",
    "sg:province":"Hessen",
    "wof:name":"Lachs-r\u00c4ucherei M. Eberhard",
    "wof:placetype":"venue"
},
  "geometry": {"coordinates":[8.633697,49.888981],"type":"Point"}
}