{
  "type": "Feature",
  "properties": {
    "iso:country":"DE",
    "sg:address":"Rotenhofstr. 14",
    "sg:city":"Saarbr\u00fccken",
    "sg:phone":"+49 681/397552",
    "sg:postcode":"66111",
    "sg:province":"Saarland",
    "wof:name":"Elke Exclusiv Elke Bender",
    "wof:placetype":"venue"
},
  "geometry": {"coordinates":[6.9939107895,49.2365837097],"type":"Point"}
}