{
  "type": "Feature",
  "properties": {
    "iso:country":"DE",
    "sg:address":"Marktstr. 110",
    "sg:city":"Oberhausen",
    "sg:phone":"+49 208/21773",
    "sg:postcode":"46045",
    "sg:province":"Nordrhein-Westfalen",
    "wof:name":"Sporthaus G\u00fcnther Inh. Karl-heinz Cramer",
    "wof:placetype":"venue"
},
  "geometry": {"coordinates":[6.856923,51.46883],"type":"Point"}
}