{
  "type": "Feature",
  "properties": {
    "iso:country":"DE",
    "sg:address":"Trierer Str 317",
    "sg:city":"Koblenz",
    "sg:phone":"+49 261/280004",
    "sg:postcode":"56068",
    "sg:province":"Rheinland-Pfalz",
    "wof:name":"Sparkasse Koblenz",
    "wof:placetype":"venue"
},
  "geometry": {"coordinates":[7.592795,50.360794],"type":"Point"}
}