{
  "type": "Feature",
  "properties": {
    "iso:country":"DE",
    "sg:address":"L\u00fcttinghofstr. 62 a",
    "sg:city":"Gelsenkirchen",
    "sg:phone":"+49 209/67338",
    "sg:postcode":"45896",
    "sg:province":"Nordrhein-Westfalen",
    "wof:name":"Eurotex Sonnenschutzsysteme E. K.",
    "wof:placetype":"venue"
},
  "geometry": {"coordinates":[7.042183,51.610737],"type":"Point"}
}