{
  "type": "Feature",
  "properties": {
    "iso:country":"DE",
    "sg:address":"Wendenstr 4::",
    "sg:city":"Hamburg",
    "sg:postcode":"20097",
    "sg:province":"Hamburg",
    "wof:name":"Herms Bank Kg Ik",
    "wof:placetype":"venue"
},
  "geometry": {"coordinates":[10.024784,53.546623],"type":"Point"}
}