{
  "type": "Feature",
  "properties": {
    "iso:country":"DE",
    "sg:address":"Nachtigallenweg 23",
    "sg:city":"M\u00f6nchengladbach",
    "sg:phone":"+49 2161/602238",
    "sg:postcode":"41065",
    "sg:province":"Nordrhein-Westfalen",
    "wof:name":"Lothar Wiese",
    "wof:placetype":"venue"
},
  "geometry": {"coordinates":[6.4862651825,51.1997566223],"type":"Point"}
}