{
  "type": "Feature",
  "properties": {
    "iso:country":"DE",
    "sg:address":"Zwickauer Str. 6",
    "sg:city":"Koblenz",
    "sg:phone":"+49 261/53746",
    "sg:postcode":"56075",
    "sg:province":"Rheinland-Pfalz",
    "wof:name":"R. Tillmann Heilpraktiker",
    "wof:placetype":"venue"
},
  "geometry": {"coordinates":[7.5657958984,50.3358879089],"type":"Point"}
}