{
  "type": "Feature",
  "properties": {
    "iso:country":"DE",
    "sg:address":"Planken P 6",
    "sg:city":"Mannheim",
    "sg:phone":"+49 621/127440",
    "sg:postcode":"68161",
    "sg:province":"Baden-W\u00fcrttemberg",
    "wof:name":"Claus Baum Touristic",
    "wof:placetype":"venue"
},
  "geometry": {"coordinates":[8.4710960388,49.4856987],"type":"Point"}
}