{
  "type": "Feature",
  "properties": {
    "iso:country":"DE",
    "sg:address":"Nienborger Damm 32",
    "sg:city":"Ochtrup",
    "sg:phone":"+49 4925/5393850",
    "sg:postcode":"48607",
    "sg:province":"Nordrhein-Westfalen",
    "wof:name":"Albers Tiefbau Gmbh",
    "wof:placetype":"venue"
},
  "geometry": {"coordinates":[7.184436,52.200985],"type":"Point"}
}