{
  "type": "Feature",
  "properties": {
    "iso:country":"DE",
    "sg:address":"Gerhart-Hauptmann-Str 30",
    "sg:city":"Dossenheim",
    "sg:phone":"+49 6221/64630",
    "sg:postcode":"69221",
    "sg:province":"Baden-W\u00fcrttemberg",
    "wof:name":"Heidelberg Engineering Optische Me\u00dfsysteme Gmbh",
    "wof:placetype":"venue"
},
  "geometry": {"coordinates":[8.666847229,49.4428863525],"type":"Point"}
}