{
  "type": "Feature",
  "properties": {
    "iso:country":"DE",
    "sg:address":"Am Stadtarchiv 1",
    "sg:city":"Neuss",
    "sg:phone":"+49 2131/271833",
    "sg:postcode":"41460",
    "sg:province":"Nordrhein-Westfalen",
    "wof:name":"Richard Jungbluth Rechtsanwalt",
    "wof:placetype":"venue"
},
  "geometry": {"coordinates":[6.6986379623,51.1949539185],"type":"Point"}
}