{
  "type": "Feature",
  "properties": {
    "iso:country":"DE",
    "sg:address":"Zwickauer Str. 220",
    "sg:city":"Chemnitz",
    "sg:phone":"+49 371/852218",
    "sg:postcode":"09116",
    "sg:province":"Sachsen",
    "wof:name":"Gunther Riedel",
    "wof:placetype":"venue"
},
  "geometry": {"coordinates":[12.8802995682,50.8206558228],"type":"Point"}
}