{
  "type": "Feature",
  "properties": {
    "iso:country":"DE",
    "sg:address":"Br\u00fcckenstr. 5",
    "sg:city":"Ha\u00dffurt",
    "sg:phone":"+49 9521/1397",
    "sg:postcode":"97437",
    "sg:province":"Bayern",
    "wof:name":"Josef Heurung & Co.",
    "wof:placetype":"venue"
},
  "geometry": {"coordinates":[10.507021904,50.0310974121],"type":"Point"}
}