{
  "type": "Feature",
  "properties": {
    "iso:country":"DE",
    "sg:address":"Saarner Str. 34",
    "sg:city":"Duisburg",
    "sg:phone":"+49 203/761112",
    "sg:postcode":"47269",
    "sg:province":"Nordrhein-Westfalen",
    "wof:name":"U. Hilbig Mode- Und Bekleidungshaus",
    "wof:placetype":"venue"
},
  "geometry": {"coordinates":[6.7826800346,51.3653678894],"type":"Point"}
}