{
  "type": "Feature",
  "properties": {
    "iso:country":"DE",
    "sg:address":"Berliner Str.",
    "sg:city":"Kleve",
    "sg:phone":"+49 2821/47249",
    "sg:postcode":"47533",
    "sg:province":"Nordrhein-Westfalen",
    "wof:name":"Berliner Grillst\u00fcbchen",
    "wof:placetype":"venue"
},
  "geometry": {"coordinates":[6.1134409904,51.7719306946],"type":"Point"}
}