{
  "type": "Feature",
  "properties": {
    "iso:country":"DE",
    "sg:address":"Ludwigsburger Str. 18",
    "sg:city":"Tamm",
    "sg:phone":"+49 7141/602432",
    "sg:postcode":"71732",
    "sg:province":"Baden-W\u00fcrttemberg",
    "wof:name":"Josef Einsle",
    "wof:placetype":"venue"
},
  "geometry": {"coordinates":[9.1327838898,48.9210891724],"type":"Point"}
}