{
  "type": "Feature",
  "properties": {
    "iso:country":"DE",
    "sg:address":"Am Maifeld 5",
    "sg:city":"Werl",
    "sg:phone":"+49 2922/8090",
    "sg:postcode":"59457",
    "sg:province":"Nordrhein-Westfalen",
    "wof:name":"Westdeutscher Baubedarf Gmbh",
    "wof:placetype":"venue"
},
  "geometry": {"coordinates":[7.8902201653,51.5690231323],"type":"Point"}
}