{
  "type": "Feature",
  "properties": {
    "iso:country":"DE",
    "sg:address":"Kl\u00f6ppelweg 4",
    "sg:city":"Dortmund",
    "sg:postcode":"44141",
    "sg:province":"Nordrhein-Westfalen",
    "wof:name":"Zim Zentrum F\u00fcr Inter- Nationales Management",
    "wof:placetype":"venue"
},
  "geometry": {"coordinates":[7.4968900681,51.5076332092],"type":"Point"}
}