{
  "type": "Feature",
  "properties": {
    "iso:country":"DE",
    "sg:address":"Rautenstrauchstr. 55",
    "sg:city":"Hamm",
    "sg:phone":"+49 2381/71990",
    "sg:postcode":"59075",
    "sg:province":"Nordrhein-Westfalen",
    "wof:name":"R. Lemik",
    "wof:placetype":"venue"
},
  "geometry": {"coordinates":[7.7597589493,51.694519043],"type":"Point"}
}