{
  "type": "Feature",
  "properties": {
    "iso:country":"DE",
    "sg:address":"Uhlstr. 58",
    "sg:city":"Br\u00fchl",
    "sg:phone":"+49 2232/942597",
    "sg:postcode":"50321",
    "sg:province":"Nordrhein-Westfalen",
    "wof:name":"Berta Van Baal Inh. Inge Zimmermann",
    "wof:placetype":"venue"
},
  "geometry": {"coordinates":[6.90331,50.82679],"type":"Point"}
}