{
  "type": "Feature",
  "properties": {
    "iso:country":"DE",
    "sg:address":"Freifrau-von-Moreau-Str. 18",
    "sg:city":"Schrobenhausen",
    "sg:phone":"+49 8252/2248",
    "sg:postcode":"86529",
    "sg:province":"Bayern",
    "wof:name":"Johann Menzinger",
    "wof:placetype":"venue"
},
  "geometry": {"coordinates":[11.246,48.569626],"type":"Point"}
}