{
  "type": "Feature",
  "properties": {
    "iso:country":"DE",
    "sg:address":"Berliner Str. 19",
    "sg:city":"Bad M\u00fcnster-Ebernburg",
    "sg:phone":"+49 6708/1507",
    "sg:postcode":"55583",
    "sg:province":"Rheinland-Pfalz",
    "wof:name":"Traude D\u00f6rr",
    "wof:placetype":"venue"
},
  "geometry": {"coordinates":[7.848183,49.812847],"type":"Point"}
}