{
  "type": "Feature",
  "properties": {
    "iso:country":"DE",
    "sg:address":"Baldestr. 16",
    "sg:city":"M\u00fcnchen",
    "sg:postcode":"80469",
    "sg:province":"Bayern",
    "wof:name":"M\u00fchl Rinkes Partnerschaft Architekt-dipl. Ing.",
    "wof:placetype":"venue"
},
  "geometry": {"coordinates":[11.5667943954,48.1239929199],"type":"Point"}
}