{
  "type": "Feature",
  "properties": {
    "iso:country":"DE",
    "sg:address":"Gabelsbergerstr. 43",
    "sg:city":"Ingolstadt",
    "sg:phone":"+49 841/46460",
    "sg:postcode":"85057",
    "sg:province":"Bayern",
    "wof:name":"F. Straub Und H. Pfeiffer",
    "wof:placetype":"venue"
},
  "geometry": {"coordinates":[11.410386,48.772755],"type":"Point"}
}