{
  "type": "Feature",
  "properties": {
    "iso:country":"DE",
    "sg:address":"Ludwig-Uhland-Str. 31",
    "sg:city":"Neu Wulmstorf",
    "sg:phone":"+49 40/7006633",
    "sg:postcode":"21629",
    "sg:province":"Niedersachsen",
    "wof:name":"Gerhard Detjen",
    "wof:placetype":"venue"
},
  "geometry": {"coordinates":[9.790559,53.466465],"type":"Point"}
}