{
  "type": "Feature",
  "properties": {
    "iso:country":"DE",
    "sg:address":"S\u00fcdring 31",
    "sg:city":"Bitburg",
    "sg:phone":"+49 6561/5552",
    "sg:postcode":"54634",
    "sg:province":"Rheinland-Pfalz",
    "wof:name":"G\u00fcnter Birkel",
    "wof:placetype":"venue"
},
  "geometry": {"coordinates":[6.5307350159,49.9579467773],"type":"Point"}
}