{
  "type": "Feature",
  "properties": {
    "iso:country":"DE",
    "sg:address":"Konrad-Adenauer-Str.",
    "sg:city":"Geilenkirchen",
    "sg:phone":"+49 2451/68415",
    "sg:postcode":"52511",
    "sg:province":"Nordrhein-Westfalen",
    "wof:name":"Restaurant Steakhouse Mujo",
    "wof:placetype":"venue"
},
  "geometry": {"coordinates":[6.1250491142,50.96301651],"type":"Point"}
}