{
  "type": "Feature",
  "properties": {
    "iso:country":"DE",
    "sg:address":"Osterende 32",
    "sg:city":"Wiesmoor",
    "sg:phone":"+49 4946/1285",
    "sg:postcode":"26639",
    "sg:province":"Niedersachsen",
    "wof:name":"Gerhard Simmering",
    "wof:placetype":"venue"
},
  "geometry": {"coordinates":[7.692279,53.369465],"type":"Point"}
}