{
  "type": "Feature",
  "properties": {
    "iso:country":"DE",
    "sg:address":"Unterreuten 51",
    "sg:city":"Eisenberg",
    "sg:phone":"+49 8363/91120",
    "sg:postcode":"87637",
    "sg:province":"Bayern",
    "wof:name":"G\u00e4stehaus Magnushof",
    "wof:placetype":"venue"
},
  "geometry": {"coordinates":[10.6072874069,47.6541557312],"type":"Point"}
}