{
  "type": "Feature",
  "properties": {
    "iso:country":"DE",
    "sg:address":"Dechant-Spr\u00fcnken-Str. 49B",
    "sg:city":"Emmerich",
    "sg:phone":"+49 2822/97140",
    "sg:postcode":"46446",
    "sg:province":"Nordrhein-Westfalen",
    "wof:name":"Promatec Konstruktion Und",
    "wof:placetype":"venue"
},
  "geometry": {"coordinates":[6.264071,51.84193],"type":"Point"}
}