{
  "type": "Feature",
  "properties": {
    "iso:country":"DE",
    "sg:address":"Donaliesstr. 45",
    "sg:city":"Zeitz",
    "sg:phone":"+49 3441/250810",
    "sg:postcode":"06712",
    "sg:province":"Sachsen-Anhalt",
    "wof:name":"N. & N.",
    "wof:placetype":"venue"
},
  "geometry": {"coordinates":[12.1329336166,51.0587692261],"type":"Point"}
}