{
  "type": "Feature",
  "properties": {
    "iso:country":"DE",
    "sg:address":"Schlesienstr. 23",
    "sg:city":"Dillingen",
    "sg:phone":"+49 9071/2210",
    "sg:postcode":"89407",
    "sg:province":"Bayern",
    "wof:name":"Stein- Und Bildhauerei Linder Gmbh",
    "wof:placetype":"venue"
},
  "geometry": {"coordinates":[10.499666214,48.5867347717],"type":"Point"}
}