{
  "type": "Feature",
  "properties": {
    "iso:country":"DE",
    "sg:address":"R\u00f6derweg 3",
    "sg:city":"Karben",
    "sg:phone":"+49 6039/7620",
    "sg:postcode":"61184",
    "sg:province":"Hessen",
    "wof:name":"K. H. Sennefelder Steuerberater",
    "wof:placetype":"venue"
},
  "geometry": {"coordinates":[8.7734699249,50.2397270203],"type":"Point"}
}