{
  "type": "Feature",
  "properties": {
    "iso:country":"DE",
    "sg:address":"Wilhelmstr. 2",
    "sg:city":"G\u00e4rtringen",
    "sg:phone":"+49 7034/26019",
    "sg:postcode":"71116",
    "sg:province":"Baden-W\u00fcrttemberg",
    "wof:name":"Alte-apotheke-g\u00e4rtringen Werner Mayer",
    "wof:placetype":"venue"
},
  "geometry": {"coordinates":[8.902116,48.642288],"type":"Point"}
}