{
  "type": "Feature",
  "properties": {
    "iso:country":"DE",
    "sg:address":"Ostpreu\u00dfenstr. 8",
    "sg:city":"Burgau",
    "sg:phone":"+49 8222/9900",
    "sg:postcode":"89331",
    "sg:province":"Bayern",
    "wof:name":"Ernst Klimmer Gmbh",
    "wof:placetype":"venue"
},
  "geometry": {"coordinates":[10.422328949,48.4288101196],"type":"Point"}
}