{
  "type": "Feature",
  "properties": {
    "iso:country":"DE",
    "sg:address":"Dominikus-Zimmermann-Str. 2",
    "sg:city":"G\u00fcnzburg",
    "sg:phone":"+49 8221/32020",
    "sg:postcode":"89312",
    "sg:province":"Bayern",
    "wof:name":"Sanit\u00e4tshaus R. Hilscher",
    "wof:placetype":"venue"
},
  "geometry": {"coordinates":[10.2771949768,48.4558563232],"type":"Point"}
}