{
  "type": "Feature",
  "properties": {
    "iso:country":"DE",
    "sg:address":"Sannetalstr.4",
    "sg:city":"Metzingen",
    "sg:phone":"+49 7123/21611",
    "sg:postcode":"72555",
    "sg:province":"Baden-W\u00fcrttemberg",
    "wof:name":"Spritzgussa Plastics",
    "wof:placetype":"venue"
},
  "geometry": {"coordinates":[9.2781019211,48.5396156311],"type":"Point"}
}