{
  "type": "Feature",
  "properties": {
    "iso:country":"DE",
    "sg:address":"Waldbadstr. 20-22",
    "sg:city":"Steinhagen",
    "sg:phone":"+49 5204/920240",
    "sg:postcode":"33803",
    "sg:province":"Nordrhein-Westfalen",
    "wof:name":"Aqua Systeme Sch\u00e4fer & Diekmann Verwaltungs-gmbh",
    "wof:placetype":"venue"
},
  "geometry": {"coordinates":[8.424953,52.018227],"type":"Point"}
}