{
  "type": "Feature",
  "properties": {
    "iso:country":"DE",
    "sg:address":"Anklamer Str.",
    "sg:city":"Greifswald",
    "sg:phone":"+49 3834/820396",
    "sg:postcode":"17489",
    "sg:province":"Mecklenburg-Vorpommern",
    "wof:name":"H. Kaapke",
    "wof:placetype":"venue"
},
  "geometry": {"coordinates":[13.4012899399,54.0874710083],"type":"Point"}
}