{
  "type": "Feature",
  "properties": {
    "iso:country":"DE",
    "sg:address":"Heckenh\u00fcgel 2",
    "sg:city":"Windischholzhausen",
    "sg:phone":"+49 361/416563",
    "sg:postcode":"99102",
    "sg:province":"Th\u00fcringen",
    "wof:name":"F. H\u00e4ndel",
    "wof:placetype":"venue"
},
  "geometry": {"coordinates":[11.0953788757,50.9466781616],"type":"Point"}
}