{
  "type": "Feature",
  "properties": {
    "iso:country":"DE",
    "sg:address":"G\u00fcrtelstr. 2",
    "sg:city":"Berlin",
    "sg:postcode":"13088",
    "sg:province":"Berlin",
    "wof:name":"Dr. Med. Kr\u00f6ckel",
    "wof:placetype":"venue"
},
  "geometry": {"coordinates":[13.448732,52.546871],"type":"Point"}
}