{
  "type": "Feature",
  "properties": {
    "iso:country":"DE",
    "sg:address":"Dianastr. 38",
    "sg:city":"Potsdam",
    "sg:postcode":"14482",
    "sg:province":"Brandenburg",
    "wof:name":"Angelika Jakop",
    "wof:placetype":"venue"
},
  "geometry": {"coordinates":[13.12369,52.386562],"type":"Point"}
}