{
  "type": "Feature",
  "properties": {
    "iso:country":"DE",
    "sg:address":"Wolfsgasse 4",
    "sg:city":"Emskirchen",
    "sg:phone":"+49 9104/709",
    "sg:postcode":"91448",
    "sg:province":"Bayern",
    "wof:name":"Metzgerei Friedrich Kerschbaum",
    "wof:placetype":"venue"
},
  "geometry": {"coordinates":[10.7167682648,49.550075531],"type":"Point"}
}