{
  "type": "Feature",
  "properties": {
    "iso:country":"DE",
    "sg:address":"Karl-Theodor Stra\u00dfe 66",
    "sg:city":"M\u00fcnchen",
    "sg:phone":"+49 89/30635890",
    "sg:postcode":"80803",
    "sg:province":"Bayern",
    "wof:name":"Syslab.com",
    "wof:placetype":"venue"
},
  "geometry": {"coordinates":[11.5769252777,48.1669845581],"type":"Point"}
}