{
  "type": "Feature",
  "properties": {
    "iso:country":"DE",
    "sg:address":"Urselbachstr. 24",
    "sg:city":"Oberursel",
    "sg:phone":"+49 6171/73406",
    "sg:postcode":"61440",
    "sg:province":"Hessen",
    "wof:name":"Kath. Pfarramt St. Crutzen",
    "wof:placetype":"venue"
},
  "geometry": {"coordinates":[8.5972251892,50.180141449],"type":"Point"}
}