{
  "type": "Feature",
  "properties": {
    "iso:country":"DE",
    "sg:address":"Berliner Str. 227",
    "sg:city":"Wiesbaden",
    "sg:phone":"+49 611/761254",
    "sg:postcode":"65205",
    "sg:province":"Hessen",
    "wof:name":"W. Roth",
    "wof:placetype":"venue"
},
  "geometry": {"coordinates":[8.29283,50.057213],"type":"Point"}
}