{
  "type": "Feature",
  "properties": {
    "iso:country":"DE",
    "sg:address":"Fischerhuder Str. 62",
    "sg:city":"Bremen",
    "sg:phone":"+49 421/617478",
    "sg:postcode":"28237",
    "sg:province":"Bremen",
    "wof:name":"Isotec Isoliertechnik Gmbh",
    "wof:placetype":"venue"
},
  "geometry": {"coordinates":[8.76519,53.11412],"type":"Point"}
}