{
  "type": "Feature",
  "properties": {
    "iso:country":"DE",
    "sg:address":"Wehlgraben 5",
    "sg:city":"Ebersburg",
    "sg:phone":"+49 6656/919994",
    "sg:postcode":"36157",
    "sg:province":"Hessen",
    "wof:name":"Otto Schramm Masseur",
    "wof:placetype":"venue"
},
  "geometry": {"coordinates":[9.807101,50.481884],"type":"Point"}
}