{
  "type": "Feature",
  "properties": {
    "iso:country":"DE",
    "sg:address":"Nordring 5",
    "sg:city":"Iffezheim",
    "sg:phone":"+49 7229/30470",
    "sg:postcode":"76473",
    "sg:province":"Baden-W\u00fcrttemberg",
    "wof:name":"A. Und Th. Schneider Gmbh",
    "wof:placetype":"venue"
},
  "geometry": {"coordinates":[8.1594991684,48.8196487427],"type":"Point"}
}