{
  "type": "Feature",
  "properties": {
    "iso:country":"DE",
    "sg:address":"Exerzierplatzstr. 9-11",
    "sg:city":"Pirmasens",
    "sg:phone":"+49 6331/63329",
    "sg:postcode":"66953",
    "sg:province":"Rheinland-Pfalz",
    "wof:name":"Landgrafen-apotheke Annemarie Hublitz",
    "wof:placetype":"venue"
},
  "geometry": {"coordinates":[7.604078,49.202377],"type":"Point"}
}