{
  "type": "Feature",
  "properties": {
    "iso:country":"DE",
    "sg:address":"Schw\u00fcrbitzer Str. 17",
    "sg:city":"Michelau",
    "sg:phone":"+49 9574/650548",
    "sg:postcode":"96247",
    "sg:province":"Bayern",
    "wof:name":"W. Ender",
    "wof:placetype":"venue"
},
  "geometry": {"coordinates":[11.1255941391,50.1749649048],"type":"Point"}
}