{
  "type": "Feature",
  "properties": {
    "iso:country":"DE",
    "sg:address":"Nauheimer Str. 51",
    "sg:city":"Stuttgart",
    "sg:phone":"+49 711/560023",
    "sg:postcode":"70372",
    "sg:province":"Baden-W\u00fcrttemberg",
    "wof:name":"Hans-rehn-stiftung",
    "wof:placetype":"venue"
},
  "geometry": {"coordinates":[9.222181,48.80629],"type":"Point"}
}