{
  "type": "Feature",
  "properties": {
    "iso:country":"DE",
    "sg:address":"An den Ellern 6",
    "sg:city":"Bergheim",
    "sg:phone":"+49 2271/41833",
    "sg:postcode":"50126",
    "sg:province":"Nordrhein-Westfalen",
    "wof:name":"Anton Broich",
    "wof:placetype":"venue"
},
  "geometry": {"coordinates":[6.612128,50.962177],"type":"Point"}
}