{
  "type": "Feature",
  "properties": {
    "iso:country":"DE",
    "sg:address":"H\u00f6henstr. 16",
    "sg:city":"Fellbach",
    "sg:phone":"+49 711/5789966",
    "sg:postcode":"70736",
    "sg:province":"Baden-W\u00fcrttemberg",
    "wof:name":"P & K Energietechnik Gmbh",
    "wof:placetype":"venue"
},
  "geometry": {"coordinates":[9.2600135803,48.8153114319],"type":"Point"}
}