{
  "type": "Feature",
  "properties": {
    "iso:country":"DE",
    "sg:address":"W\u00fcrzburger Str. 5",
    "sg:city":"Zellingen",
    "sg:phone":"+49 9364/9905",
    "sg:postcode":"97225",
    "sg:province":"Bayern",
    "wof:name":"Siegfried Goldstein",
    "wof:placetype":"venue"
},
  "geometry": {"coordinates":[9.8171033859,49.8972206116],"type":"Point"}
}