{
  "type": "Feature",
  "properties": {
    "iso:country":"DE",
    "sg:address":"Hauptstr 3",
    "sg:city":"Nentershausen",
    "sg:phone":"+49 6627/915330",
    "sg:postcode":"36214",
    "sg:province":"Hessen",
    "wof:name":"Wicke Industrieberatung",
    "wof:placetype":"venue"
},
  "geometry": {"coordinates":[9.909168,51.024162],"type":"Point"}
}