{
  "type": "Feature",
  "properties": {
    "iso:country":"DE",
    "sg:address":"Gl\u00e4tteweg 2",
    "sg:city":"Bovenden-G\u00f6ttingen",
    "sg:phone":"+49 5594",
    "sg:postcode":"37120",
    "sg:province":"Niedersachsen",
    "wof:name":"Andiamo-kommunikation",
    "wof:placetype":"venue"
},
  "geometry": {"coordinates":[9.94588,51.600208],"type":"Point"}
}