{
  "type": "Feature",
  "properties": {
    "iso:country":"DE",
    "sg:address":"An der Landwehr 38",
    "sg:city":"Iserlohn",
    "sg:phone":"+49 2371/774952",
    "sg:postcode":"58636",
    "sg:province":"Nordrhein-Westfalen",
    "wof:name":"Dataservice Crew Forum",
    "wof:placetype":"venue"
},
  "geometry": {"coordinates":[7.714986,51.368778],"type":"Point"}
}