{
  "type": "Feature",
  "properties": {
    "iso:country":"DE",
    "sg:address":"Lessingstr. 12",
    "sg:city":"M\u00fcnchen",
    "sg:phone":"+49 89/5443450",
    "sg:postcode":"80336",
    "sg:province":"Bayern",
    "wof:name":"Srt-s\u00fcdbayerische Revisions- Und Treuhandges. Mbh",
    "wof:placetype":"venue"
},
  "geometry": {"coordinates":[11.5566139221,48.1342849731],"type":"Point"}
}