{
  "type": "Feature",
  "properties": {
    "iso:country":"DE",
    "sg:address":"Koblenzer Str. 16",
    "sg:city":"Kaisersesch",
    "sg:phone":"+49 2653/99050",
    "sg:postcode":"56759",
    "sg:province":"Rheinland-Pfalz",
    "wof:name":"Rewe-center R-kauf M\u00e4rkte Gmbh & Co. Kg",
    "wof:placetype":"venue"
},
  "geometry": {"coordinates":[7.1441049576,50.2336387634],"type":"Point"}
}