{
  "type": "Feature",
  "properties": {
    "iso:country":"DE",
    "sg:address":"Rederscheider Stra\u00dfe 25",
    "sg:city":"Windhagen",
    "sg:phone":"+49 2645",
    "sg:postcode":"53578",
    "sg:province":"Rheinland-Pfalz",
    "wof:name":"Studenynet - Studeny Beratungsgesellschaft",
    "wof:placetype":"venue"
},
  "geometry": {"coordinates":[7.326529026,50.6363677979],"type":"Point"}
}