{
  "type": "Feature",
  "properties": {
    "iso:country":"DE",
    "sg:address":"Zieglerstr 16",
    "sg:city":"H\u00f6velhof",
    "sg:phone":"+49 6227/51088",
    "sg:postcode":"33161",
    "sg:province":"Nordrhein-Westfalen",
    "wof:name":"Wissmeier",
    "wof:placetype":"venue"
},
  "geometry": {"coordinates":[8.6080350876,49.2592887878],"type":"Point"}
}