{
  "type": "Feature",
  "properties": {
    "iso:country":"DE",
    "sg:address":"Friedensstr. 12",
    "sg:city":"Bedburg",
    "sg:phone":"+49 2272/82045",
    "sg:postcode":"50181",
    "sg:province":"Nordrhein-Westfalen",
    "wof:name":"Gsm Gesellschaft F\u00fcr Schweissmaterialien Mbh",
    "wof:placetype":"venue"
},
  "geometry": {"coordinates":[6.633083,51.006275],"type":"Point"}
}