{
  "type": "Feature",
  "properties": {
    "iso:country":"DE",
    "sg:address":"Schanzstr. 16",
    "sg:city":"Friedrichshafen",
    "sg:phone":"+49 7541/32329",
    "sg:postcode":"88045",
    "sg:province":"Baden-W\u00fcrttemberg",
    "wof:name":"I. Isemann",
    "wof:placetype":"venue"
},
  "geometry": {"coordinates":[9.479555,47.651409],"type":"Point"}
}