{
  "type": "Feature",
  "properties": {
    "iso:country":"DE",
    "sg:address":"Victor-Mezger-Str. 15",
    "sg:city":"\u00dcberlingen",
    "sg:phone":"+49 7551/62723",
    "sg:postcode":"88662",
    "sg:province":"Baden-W\u00fcrttemberg",
    "wof:name":"H. Schr\u00f6der Architekt",
    "wof:placetype":"venue"
},
  "geometry": {"coordinates":[9.178257,47.76741],"type":"Point"}
}