{
  "type": "Feature",
  "properties": {
    "iso:country":"DE",
    "sg:address":"Marktstr. 1",
    "sg:city":"Reichertshofen",
    "sg:phone":"+49 8453/338666",
    "sg:postcode":"85084",
    "sg:province":"Bayern",
    "wof:name":"Taverne Saloniki",
    "wof:placetype":"venue"
},
  "geometry": {"coordinates":[11.4669237137,48.6577072144],"type":"Point"}
}