{
  "type": "Feature",
  "properties": {
    "iso:country":"DE",
    "sg:address":"Sch\u00f6nberger Weg 6-10",
    "sg:city":"Frankfurt",
    "sg:phone":"+49 69/9766080",
    "sg:postcode":"60488",
    "sg:province":"Hessen",
    "wof:name":"Elt Electronic Lift Thoma Gmbh",
    "wof:placetype":"venue"
},
  "geometry": {"coordinates":[8.6147251129,50.148651123],"type":"Point"}
}