{
  "type": "Feature",
  "properties": {
    "iso:country":"DE",
    "sg:address":"Am Hartenberg",
    "sg:city":"Niederahr",
    "sg:postcode":"56414",
    "sg:province":"Rheinland-Pfalz",
    "wof:name":"Kath. \u00d6ffentliche Bibliothek",
    "wof:placetype":"venue"
},
  "geometry": {"coordinates":[7.861892,50.493469],"type":"Point"}
}