{
  "type": "Feature",
  "properties": {
    "iso:country":"DE",
    "sg:address":"Rathausstr. 65 a",
    "sg:city":"Wissen",
    "sg:phone":"+49 2742/2244",
    "sg:postcode":"57537",
    "sg:province":"Rheinland-Pfalz",
    "wof:name":"Hotel B\u00fcrgergesellschaft",
    "wof:placetype":"venue"
},
  "geometry": {"coordinates":[7.7363061905,50.781627655],"type":"Point"}
}