{
  "type": "Feature",
  "properties": {
    "iso:country":"DE",
    "sg:address":"Willenk\u00e4mper Str. 2",
    "sg:city":"Staffhorst",
    "sg:phone":"+49 4272/1627",
    "sg:postcode":"27254",
    "sg:province":"Niedersachsen",
    "wof:name":"H. Denker",
    "wof:placetype":"venue"
},
  "geometry": {"coordinates":[8.9873504639,52.7243461609],"type":"Point"}
}