{
  "type": "Feature",
  "properties": {
    "iso:country":"DE",
    "sg:address":"Radaustr. 43 c",
    "sg:city":"Augsburg",
    "sg:phone":"+49 821/91390",
    "sg:postcode":"86199",
    "sg:province":"Bayern",
    "wof:name":"Para-star 2000 Inh. Gerhilde Schubert",
    "wof:placetype":"venue"
},
  "geometry": {"coordinates":[10.85988,48.334354],"type":"Point"}
}