{
  "type": "Feature",
  "properties": {
    "iso:country":"DE",
    "sg:address":"Friedrich-Ebert-Str. 88",
    "sg:city":"Potsdam",
    "sg:phone":"+49 331/2708419",
    "sg:postcode":"14467",
    "sg:province":"Brandenburg",
    "wof:name":"Beumer Ohg",
    "wof:placetype":"venue"
},
  "geometry": {"coordinates":[13.057584,52.402401],"type":"Point"}
}