{
  "type": "Feature",
  "properties": {
    "iso:country":"DE",
    "sg:address":"Daimlerstr. 32 /1",
    "sg:city":"Gosheim",
    "sg:phone":"+49 7426/1222",
    "sg:postcode":"78559",
    "sg:province":"Baden-W\u00fcrttemberg",
    "wof:name":"Adolf Hermle Gmbh",
    "wof:placetype":"venue"
},
  "geometry": {"coordinates":[8.756873,48.137619],"type":"Point"}
}