{
  "type": "Feature",
  "properties": {
    "iso:country":"DE",
    "sg:address":"Ringstr. 27",
    "sg:city":"Steinau",
    "sg:phone":"+49 6663/919692",
    "sg:postcode":"36396",
    "sg:province":"Hessen",
    "wof:name":"Alexius Bestattungen Inh. B. Alexius",
    "wof:placetype":"venue"
},
  "geometry": {"coordinates":[9.465968,50.311363],"type":"Point"}
}