{
  "type": "Feature",
  "properties": {
    "iso:country":"DE",
    "sg:address":"J\u00e4gerstr. 1",
    "sg:city":"Stegen",
    "sg:phone":"+49 4976/6161060",
    "sg:postcode":"79252",
    "sg:province":"Baden-W\u00fcrttemberg",
    "wof:name":"Sparkasse Hochschwarzwald",
    "wof:placetype":"venue"
},
  "geometry": {"coordinates":[7.964238,47.98196],"type":"Point"}
}