{
  "type": "Feature",
  "properties": {
    "iso:country":"DE",
    "sg:address":"Echternstr. 9",
    "sg:city":"Braunschweig",
    "sg:phone":"+49 531/44738",
    "sg:postcode":"38100",
    "sg:province":"Niedersachsen",
    "wof:name":"Werner R\u00fcgge Architekt",
    "wof:placetype":"venue"
},
  "geometry": {"coordinates":[10.514341,52.260208],"type":"Point"}
}