{
  "type": "Feature",
  "properties": {
    "iso:country":"DE",
    "sg:address":"Peter-Kl\u00f6ckner-Str. 3",
    "sg:city":"Koblenz",
    "sg:phone":"+49 261/46059",
    "sg:postcode":"56073",
    "sg:province":"Rheinland-Pfalz",
    "wof:name":"Bwz Elektrodienst Beaujean Weiss Zell Gmbh",
    "wof:placetype":"venue"
},
  "geometry": {"coordinates":[7.571692,50.36375],"type":"Point"}
}