{
  "type": "Feature",
  "properties": {
    "iso:country":"DE",
    "sg:address":"Paulusstr. 16",
    "sg:city":"Herzogenrath",
    "sg:phone":"+49 2407/3326",
    "sg:postcode":"52134",
    "sg:province":"Nordrhein-Westfalen",
    "wof:name":"H. Scholl Elektromeisterbetrieb",
    "wof:placetype":"venue"
},
  "geometry": {"coordinates":[6.08694,50.833363],"type":"Point"}
}