{
  "type": "Feature",
  "properties": {
    "iso:country":"DE",
    "sg:address":"Baumannstr. 25",
    "sg:city":"Oberstdorf",
    "sg:phone":"+49 8322/2483",
    "sg:postcode":"87561",
    "sg:province":"Bayern",
    "wof:name":"Eugen L\u00e4ndle",
    "wof:placetype":"venue"
},
  "geometry": {"coordinates":[10.271264,47.411552],"type":"Point"}
}