{
  "type": "Feature",
  "properties": {
    "iso:country":"DE",
    "sg:address":"Pfarrgasse 11",
    "sg:city":"Oettingen",
    "sg:phone":"+49 9082/2109",
    "sg:postcode":"86732",
    "sg:province":"Bayern",
    "wof:name":"Ernst Haygis B\u00f6ttcherei",
    "wof:placetype":"venue"
},
  "geometry": {"coordinates":[10.605213,48.953358],"type":"Point"}
}