{
  "type": "Feature",
  "properties": {
    "iso:country":"DE",
    "sg:address":"Hauptkanal Rechts 105",
    "sg:city":"Papenburg",
    "sg:phone":"+49 4961/942315",
    "sg:postcode":"26871",
    "sg:province":"Niedersachsen",
    "wof:name":"Restaurant Fehnstube",
    "wof:placetype":"venue"
},
  "geometry": {"coordinates":[7.4040818214,53.0762672424],"type":"Point"}
}