{
  "type": "Feature",
  "properties": {
    "iso:country":"DE",
    "sg:address":"Legienstr. 8 a",
    "sg:city":"Hamburg",
    "sg:postcode":"22111",
    "sg:province":"Hamburg",
    "wof:name":"Karl Kneisner Gmbh",
    "wof:placetype":"venue"
},
  "geometry": {"coordinates":[10.0970287323,53.5432128906],"type":"Point"}
}