{
  "type": "Feature",
  "properties": {
    "iso:country":"DE",
    "sg:address":"Ansbacher Str. 15-19",
    "sg:city":"Burgoberbach",
    "sg:phone":"+49 9805/1531",
    "sg:postcode":"91595",
    "sg:province":"Bayern",
    "wof:name":"Fritz Appel",
    "wof:placetype":"venue"
},
  "geometry": {"coordinates":[10.59224,49.238888],"type":"Point"}
}