{
  "type": "Feature",
  "properties": {
    "iso:country":"DE",
    "sg:address":"Beim \u00d6lsteg 7",
    "sg:city":"Bad Mergentheim",
    "sg:phone":"+49 7931/52264",
    "sg:postcode":"97980",
    "sg:province":"Baden-W\u00fcrttemberg",
    "wof:name":"Wolfram Rost",
    "wof:placetype":"venue"
},
  "geometry": {"coordinates":[9.7676830292,49.4957313538],"type":"Point"}
}