{
  "type": "Feature",
  "properties": {
    "iso:country":"DE",
    "sg:address":"Schemmen 1",
    "sg:city":"Marienheide",
    "sg:phone":"+49 2261/21850",
    "sg:postcode":"51709",
    "sg:province":"Nordrhein-Westfalen",
    "wof:name":"Combi",
    "wof:placetype":"venue"
},
  "geometry": {"coordinates":[7.5597610474,51.0669708252],"type":"Point"}
}