{
  "type": "Feature",
  "properties": {
    "iso:country":"DE",
    "sg:address":"K\u00f6llner Str. 30",
    "sg:city":"Riegelsberg",
    "sg:phone":"+49 6806/44404",
    "sg:postcode":"66292",
    "sg:province":"Saarland",
    "wof:name":"M. Gansemer",
    "wof:placetype":"venue"
},
  "geometry": {"coordinates":[6.9251160622,49.29662323],"type":"Point"}
}