{
  "type": "Feature",
  "properties": {
    "iso:country":"DE",
    "sg:address":"Questiner Weg 3-9",
    "sg:city":"Grevesm\u00fchlen",
    "sg:phone":"+49 3881/2454",
    "sg:postcode":"23936",
    "sg:province":"Mecklenburg-Vorpommern",
    "wof:name":"Heinz Bruhn",
    "wof:placetype":"venue"
},
  "geometry": {"coordinates":[11.1784124374,53.8606910706],"type":"Point"}
}