{
  "type": "Feature",
  "properties": {
    "iso:country":"DE",
    "sg:address":"Neue Str. 97-99",
    "sg:city":"Ulm",
    "sg:phone":"+49 731/60715",
    "sg:postcode":"89073",
    "sg:province":"Baden-W\u00fcrttemberg",
    "wof:name":"Dieter Schnarrenberger Ingenieur",
    "wof:placetype":"venue"
},
  "geometry": {"coordinates":[9.9878110886,48.3971862793],"type":"Point"}
}