{
  "type": "Feature",
  "properties": {
    "iso:country":"DE",
    "sg:address":"Willi-Bleicher-Str. 1",
    "sg:city":"G\u00f6ppingen",
    "sg:phone":"+49 7161/964540",
    "sg:postcode":"73033",
    "sg:province":"Baden-W\u00fcrttemberg",
    "wof:name":"G. Kr\u00f6ner",
    "wof:placetype":"venue"
},
  "geometry": {"coordinates":[9.6476411819,48.7030601501],"type":"Point"}
}