{
  "type": "Feature",
  "properties": {
    "iso:country":"DE",
    "sg:address":"Strunkeicher Str.",
    "sg:city":"Puderbach",
    "sg:phone":"+49 2684/3504",
    "sg:postcode":"56305",
    "sg:province":"Rheinland-Pfalz",
    "wof:name":"Friedrich Noll Gmbh",
    "wof:placetype":"venue"
},
  "geometry": {"coordinates":[7.6029438972,50.6077461243],"type":"Point"}
}