{
  "type": "Feature",
  "properties": {
    "iso:country":"DE",
    "sg:address":"In der Aue 1",
    "sg:city":"Gr\u00fcndau",
    "sg:phone":"+49 6051/924461",
    "sg:postcode":"63584",
    "sg:province":"Hessen",
    "wof:name":"Rhino Gmbh",
    "wof:placetype":"venue"
},
  "geometry": {"coordinates":[9.1363868713,50.2041854858],"type":"Point"}
}