{
  "type": "Feature",
  "properties": {
    "iso:country":"DE",
    "sg:address":"Heimst\u00e4ttenweg 20",
    "sg:city":"N\u00fcrtingen",
    "sg:phone":"+49 7022/33602",
    "sg:postcode":"72622",
    "sg:province":"Baden-W\u00fcrttemberg",
    "wof:name":"Richard Holder",
    "wof:placetype":"venue"
},
  "geometry": {"coordinates":[9.360365,48.624851],"type":"Point"}
}