{
  "type": "Feature",
  "properties": {
    "iso:country":"DE",
    "sg:address":"Hinter der Wand 72",
    "sg:city":"Schielo",
    "sg:phone":"+49 39484/8111",
    "sg:postcode":"06493",
    "sg:province":"Sachsen-Anhalt",
    "wof:name":"Gerda Winkler",
    "wof:placetype":"venue"
},
  "geometry": {"coordinates":[11.217483,51.619389],"type":"Point"}
}