{
  "type": "Feature",
  "properties": {
    "iso:country":"DE",
    "sg:address":"M\u00f6nckebergstr. 5",
    "sg:city":"Hamburg",
    "sg:phone":"+49 40/338481",
    "sg:postcode":"20095",
    "sg:province":"Hamburg",
    "wof:name":"Weiss & Wulffsohn Contact-linsen",
    "wof:placetype":"venue"
},
  "geometry": {"coordinates":[10.003465,53.551338],"type":"Point"}
}