{
  "type": "Feature",
  "properties": {
    "iso:country":"DE",
    "sg:address":"Rendsburger Str. 30",
    "sg:city":"Fockbek",
    "sg:phone":"+49 4331/61065",
    "sg:postcode":"24787",
    "sg:province":"Schleswig-Holstein",
    "wof:name":"Wilfried Kaminski Rechtsanwalt Und Notar",
    "wof:placetype":"venue"
},
  "geometry": {"coordinates":[9.6058540344,54.3080940247],"type":"Point"}
}