{
  "type": "Feature",
  "properties": {
    "iso:country":"DE",
    "sg:address":"Almweg 21",
    "sg:city":"Baierbrunn",
    "sg:phone":"+49 89/7932673",
    "sg:postcode":"82065",
    "sg:province":"Bayern",
    "wof:name":"R. Von Opolski Ingenieur",
    "wof:placetype":"venue"
},
  "geometry": {"coordinates":[11.4782066345,48.0198440552],"type":"Point"}
}