{
  "type": "Feature",
  "properties": {
    "iso:country":"DE",
    "sg:address":"Holzbergweg 25",
    "sg:city":"Schorndorf",
    "sg:phone":"+49 7181/76637",
    "sg:postcode":"73614",
    "sg:province":"Baden-W\u00fcrttemberg",
    "wof:name":"Krankenpflegeverein Hans-martin Golder",
    "wof:placetype":"venue"
},
  "geometry": {"coordinates":[9.523270607,48.8175125122],"type":"Point"}
}