{
  "type": "Feature",
  "properties": {
    "iso:country":"DE",
    "sg:address":"F\u00e4hnrichst\u00fcttem 5",
    "sg:city":"Wipperf\u00fcrth",
    "sg:phone":"+49 2267/880220",
    "sg:postcode":"51688",
    "sg:province":"Nordrhein-Westfalen",
    "wof:name":"F\u00e4hnrich-plastic Gmbh & Co. Kg",
    "wof:placetype":"venue"
},
  "geometry": {"coordinates":[7.414824,51.08477],"type":"Point"}
}