{
  "type": "Feature",
  "properties": {
    "iso:country":"DE",
    "sg:address":"Hauptstr. 36",
    "sg:city":"Nidderau",
    "sg:postcode":"61130",
    "sg:province":"Hessen",
    "wof:name":"Agriculture Gmbh",
    "wof:placetype":"venue"
},
  "geometry": {"coordinates":[8.86515,50.267361],"type":"Point"}
}