{
  "type": "Feature",
  "properties": {
    "iso:country":"DE",
    "sg:address":"Kirchbergstr. 6",
    "sg:city":"Ried",
    "sg:phone":"+49 8233/8197",
    "sg:postcode":"86510",
    "sg:province":"Bayern",
    "wof:name":"E & F Erhard & Falkenstein Gro\u00dfk\u00fcchen Einrichtungs-gmbh",
    "wof:placetype":"venue"
},
  "geometry": {"coordinates":[11.051261,48.282681],"type":"Point"}
}