{
  "type": "Feature",
  "properties": {
    "iso:country":"DE",
    "sg:address":"Sturmiusstr. 4",
    "sg:city":"Fulda",
    "sg:phone":"+49 661/72211",
    "sg:postcode":"36037",
    "sg:province":"Hessen",
    "wof:name":"Yadollah Djafari Krankengymnast",
    "wof:placetype":"venue"
},
  "geometry": {"coordinates":[9.680684,50.554111],"type":"Point"}
}