{
  "type": "Feature",
  "properties": {
    "iso:country":"DE",
    "sg:address":"Hospitalgasse 7-11",
    "sg:city":"Schw\u00e4bisch Gm\u00fcnd",
    "sg:phone":"+49 7171/37337",
    "sg:postcode":"73525",
    "sg:province":"Baden-W\u00fcrttemberg",
    "wof:name":"Farben-center Gebr. H\u00f6rner Gmbh & Co.",
    "wof:placetype":"venue"
},
  "geometry": {"coordinates":[9.7971057892,48.8021507263],"type":"Point"}
}