{
  "type": "Feature",
  "properties": {
    "iso:country":"DE",
    "sg:address":"Schulstr. 3",
    "sg:city":"Reil",
    "sg:phone":"+49 6542/21849",
    "sg:postcode":"56861",
    "sg:province":"Rheinland-Pfalz",
    "wof:name":"Reinhard Barzen",
    "wof:placetype":"venue"
},
  "geometry": {"coordinates":[7.1145801544,50.024394989],"type":"Point"}
}