{
  "type": "Feature",
  "properties": {
    "iso:country":"DE",
    "sg:address":"Wanderuper Str. 21",
    "sg:city":"Tarp",
    "sg:phone":"+49 4638/8900",
    "sg:postcode":"24963",
    "sg:province":"Schleswig-Holstein",
    "wof:name":"Dsc Dansk Senior-center Tarp Gmbh & Co. Kg",
    "wof:placetype":"venue"
},
  "geometry": {"coordinates":[9.390797,54.668995],"type":"Point"}
}