{
  "type": "Feature",
  "properties": {
    "iso:country":"DE",
    "sg:address":"Hauptstr. 9",
    "sg:city":"\u00d6hningen",
    "sg:phone":"+49 7735/2178",
    "sg:postcode":"78337",
    "sg:province":"Baden-W\u00fcrttemberg",
    "wof:name":"Karl Singer",
    "wof:placetype":"venue"
},
  "geometry": {"coordinates":[8.9272966385,47.6607894897],"type":"Point"}
}