{
  "type": "Feature",
  "properties": {
    "iso:country":"DE",
    "sg:address":"Zenettistr. 10",
    "sg:city":"M\u00fcnchen",
    "sg:phone":"+49 89/7469702",
    "sg:postcode":"80337",
    "sg:province":"Bayern",
    "wof:name":"Fleischmarkt M\u00fcnchen Bau- Und Vermietungs Gmbh",
    "wof:placetype":"venue"
},
  "geometry": {"coordinates":[11.557906,48.123566],"type":"Point"}
}