{
  "type": "Feature",
  "properties": {
    "iso:country":"DE",
    "sg:address":"Blumenstr. 34",
    "sg:city":"Saarbr\u00fccken",
    "sg:phone":"+49 681/373781",
    "sg:postcode":"66111",
    "sg:province":"Saarland",
    "wof:name":"M. Lenzen",
    "wof:placetype":"venue"
},
  "geometry": {"coordinates":[7.000725,49.23687],"type":"Point"}
}