{
  "type": "Feature",
  "properties": {
    "iso:country":"DE",
    "sg:address":"Im Grund 23",
    "sg:city":"D\u00fcsseldorf",
    "sg:phone":"+49 211/133777",
    "sg:postcode":"40474",
    "sg:province":"Nordrhein-Westfalen",
    "wof:name":"J. Von Roebel",
    "wof:placetype":"venue"
},
  "geometry": {"coordinates":[6.7378759384,51.2834663391],"type":"Point"}
}