{
  "type": "Feature",
  "properties": {
    "iso:country":"DE",
    "sg:address":"Maasstr. 15",
    "sg:city":"Essen",
    "sg:phone":"+49 201/8405264",
    "sg:postcode":"45239",
    "sg:province":"Nordrhein-Westfalen",
    "wof:name":"Ulrich Geis Gmbh Handelsagentur",
    "wof:placetype":"venue"
},
  "geometry": {"coordinates":[7.032804966,51.3938179016],"type":"Point"}
}