{
  "type": "Feature",
  "properties": {
    "iso:country":"DE",
    "sg:address":"Harzstr. 10",
    "sg:city":"Seesen",
    "sg:phone":"+49 5381/710",
    "sg:postcode":"38723",
    "sg:province":"Niedersachsen",
    "wof:name":"Archiv Der Sonnen-bassermann- Werke Siegburg & Pf\u00f6rtner",
    "wof:placetype":"venue"
},
  "geometry": {"coordinates":[10.180343,51.889671],"type":"Point"}
}