{
  "type": "Feature",
  "properties": {
    "iso:country":"DE",
    "sg:address":"Am Sch\u00e4nzel 26",
    "sg:city":"Neckargem\u00fcnd",
    "sg:phone":"+49 6223/73866",
    "sg:postcode":"69151",
    "sg:province":"Baden-W\u00fcrttemberg",
    "wof:name":"Arnd Wolf Rechtsanwalt",
    "wof:placetype":"venue"
},
  "geometry": {"coordinates":[8.8448896408,49.3915328979],"type":"Point"}
}