{
  "type": "Feature",
  "properties": {
    "iso:country":"DE",
    "sg:address":"Hauptstr. 69a",
    "sg:city":"Waldkirch",
    "sg:phone":"+49 7681/3228",
    "sg:postcode":"79183",
    "sg:province":"Baden-W\u00fcrttemberg",
    "wof:name":"Beate Ganz",
    "wof:placetype":"venue"
},
  "geometry": {"coordinates":[7.972303,48.105892],"type":"Point"}
}