{
  "type": "Feature",
  "properties": {
    "iso:country":"DE",
    "sg:address":"Willibaldplatz 5",
    "sg:city":"M\u00fcnchen",
    "sg:phone":"+49 89/5804055",
    "sg:postcode":"80687",
    "sg:province":"Bayern",
    "wof:name":"Magnus-apotheke",
    "wof:placetype":"venue"
},
  "geometry": {"coordinates":[11.488953,48.141064],"type":"Point"}
}