{
  "type": "Feature",
  "properties": {
    "iso:country":"DE",
    "sg:address":"Dorfplatz 2",
    "sg:city":"Feldkirchen-Westerham",
    "sg:phone":"+49 8063/807540",
    "sg:postcode":"83620",
    "sg:province":"Bayern",
    "wof:name":"Onyx Holzhaus Gmbh",
    "wof:placetype":"venue"
},
  "geometry": {"coordinates":[11.9025583267,47.9220962524],"type":"Point"}
}