{
  "type": "Feature",
  "properties": {
    "iso:country":"DE",
    "sg:address":"Waldstr. 18",
    "sg:city":"Wahlstedt",
    "sg:postcode":"23812",
    "sg:province":"Schleswig-Holstein",
    "wof:name":"Beeck Malereifachbetrieb Gmbh",
    "wof:placetype":"venue"
},
  "geometry": {"coordinates":[10.209274,53.951588],"type":"Point"}
}