{
  "type": "Feature",
  "properties": {
    "iso:country":"DE",
    "sg:address":"Speyerer Str. 10",
    "sg:city":"Edesheim",
    "sg:phone":"+49 6323/3503",
    "sg:postcode":"67483",
    "sg:province":"Rheinland-Pfalz",
    "wof:name":"Franziskus Apotheke Kurt Von Nida E. K.",
    "wof:placetype":"venue"
},
  "geometry": {"coordinates":[8.135748,49.264236],"type":"Point"}
}