{
  "type": "Feature",
  "properties": {
    "iso:country":"DE",
    "sg:address":"Wendl-Dietrich-Str. 2",
    "sg:city":"M\u00fcnchen",
    "sg:phone":"+49 89/13016260",
    "sg:postcode":"80634",
    "sg:province":"Bayern",
    "wof:name":"Kranich-apotheke",
    "wof:placetype":"venue"
},
  "geometry": {"coordinates":[11.531931,48.152882],"type":"Point"}
}