{
  "type": "Feature",
  "properties": {
    "iso:country":"DE",
    "sg:address":"Salinstr. 1",
    "sg:city":"Rosenheim",
    "sg:postcode":"83022",
    "sg:province":"Bayern",
    "wof:name":"Tm Depotmanagement Gmbh",
    "wof:placetype":"venue"
},
  "geometry": {"coordinates":[12.12334,47.852951],"type":"Point"}
}