{
  "type": "Feature",
  "properties": {
    "iso:country":"DE",
    "sg:address":"Fischstr. 8",
    "sg:city":"G\u00f6ppingen",
    "sg:phone":"+49 7161/73200",
    "sg:postcode":"73033",
    "sg:province":"Baden-W\u00fcrttemberg",
    "wof:name":"K. Schindler",
    "wof:placetype":"venue"
},
  "geometry": {"coordinates":[9.648303,48.703049],"type":"Point"}
}