{
  "type": "Feature",
  "properties": {
    "iso:country":"DE",
    "sg:address":"Marktstr. 25",
    "sg:city":"Wiesbaden",
    "sg:phone":"+49 611/301812",
    "sg:postcode":"65183",
    "sg:province":"Hessen",
    "wof:name":"R\u00f6ver System Gmbh",
    "wof:placetype":"venue"
},
  "geometry": {"coordinates":[8.239507,50.082726],"type":"Point"}
}