{
  "type": "Feature",
  "properties": {
    "iso:country":"DE",
    "sg:address":"Loschwitzer Weg 4",
    "sg:city":"Berlin",
    "sg:phone":"+49 30/3631816",
    "sg:postcode":"13593",
    "sg:province":"Berlin",
    "wof:name":"Pizzeria Due-volpi",
    "wof:placetype":"venue"
},
  "geometry": {"coordinates":[13.1614112854,52.5217285156],"type":"Point"}
}