{
  "type": "Feature",
  "properties": {
    "iso:country":"DE",
    "sg:address":"Langenhausen 24",
    "sg:city":"Gnarrenburg",
    "sg:phone":"+49 4763/7240",
    "sg:postcode":"27442",
    "sg:province":"Niedersachsen",
    "wof:name":"Hans K\u00fcck",
    "wof:placetype":"venue"
},
  "geometry": {"coordinates":[9.0432,53.41106],"type":"Point"}
}