{
  "type": "Feature",
  "properties": {
    "iso:country":"DE",
    "sg:address":"Rautenstr. 8",
    "sg:city":"Nordhausen",
    "sg:phone":"+49 3631/436940",
    "sg:postcode":"99734",
    "sg:province":"Th\u00fcringen",
    "wof:name":"D2 Shop Herfag Nordhausen",
    "wof:placetype":"venue"
},
  "geometry": {"coordinates":[10.7946987152,51.5007781982],"type":"Point"}
}