{
  "type": "Feature",
  "properties": {
    "iso:country":"DE",
    "sg:address":"Leppestr. 7",
    "sg:city":"Engelskirchen",
    "sg:phone":"+49 2263/1477",
    "sg:postcode":"51766",
    "sg:province":"Nordrhein-Westfalen",
    "wof:name":"Wolfgang Griesel Rechtsanwalt",
    "wof:placetype":"venue"
},
  "geometry": {"coordinates":[7.4104709625,50.9881095886],"type":"Point"}
}