{
  "type": "Feature",
  "properties": {
    "iso:country":"DE",
    "sg:address":"Gro\u00dfe Bleichen 21",
    "sg:city":"Hamburg",
    "sg:phone":"+49 40/2002026",
    "sg:postcode":"20354",
    "sg:province":"Hamburg",
    "wof:name":"Shirt Company Handels- Gesellschaft Mbh",
    "wof:placetype":"venue"
},
  "geometry": {"coordinates":[9.9894914627,53.5528068542],"type":"Point"}
}