{
  "type": "Feature",
  "properties": {
    "iso:country":"DE",
    "sg:address":"Lindenstr. 6",
    "sg:city":"Euerbach",
    "sg:postcode":"97502",
    "sg:province":"Bayern",
    "wof:name":"R. Markert",
    "wof:placetype":"venue"
},
  "geometry": {"coordinates":[10.0977754593,50.0606193542],"type":"Point"}
}