{
  "type": "Feature",
  "properties": {
    "iso:country":"DE",
    "sg:address":"Ostkirchstr 1",
    "sg:city":"Dortmund",
    "sg:phone":"+49 231/488461",
    "sg:postcode":"44269",
    "sg:province":"Nordrhein-Westfalen",
    "wof:name":"E. Sabelstr\u00f6m",
    "wof:placetype":"venue"
},
  "geometry": {"coordinates":[7.5359902382,51.478061676],"type":"Point"}
}