{
  "type": "Feature",
  "properties": {
    "iso:country":"DE",
    "sg:address":"Paul-Hindemith-Stra\u00dfe 14",
    "sg:city":"Neubrandenburg",
    "sg:phone":"+49 4964/65",
    "sg:postcode":"17033",
    "sg:province":"Mecklenburg-Vorpommern",
    "wof:name":"Islandpferdezucht-gestuet Schlossberg-hof Kvistir",
    "wof:placetype":"venue"
},
  "geometry": {"coordinates":[13.228141,53.549255],"type":"Point"}
}