{
  "type": "Feature",
  "properties": {
    "iso:country":"DE",
    "sg:address":"Pfarranger 2-6",
    "sg:city":"Salzgitter",
    "sg:phone":"+49 5341/2022",
    "sg:postcode":"38229",
    "sg:province":"Niedersachsen",
    "wof:name":"Pfotenhauer",
    "wof:placetype":"venue"
},
  "geometry": {"coordinates":[10.4188299179,52.1213874817],"type":"Point"}
}