{
  "type": "Feature",
  "properties": {
    "iso:country":"DE",
    "sg:address":"Wenkenstr. 51",
    "sg:city":"Bad Salzuflen",
    "sg:phone":"+49 5222/16406",
    "sg:postcode":"32105",
    "sg:province":"Nordrhein-Westfalen",
    "wof:name":"F. Baus",
    "wof:placetype":"venue"
},
  "geometry": {"coordinates":[8.7524290085,52.0867347717],"type":"Point"}
}