{
  "type": "Feature",
  "properties": {
    "iso:country":"DE",
    "sg:address":"Poststr. 25",
    "sg:city":"M\u00fcncheberg",
    "sg:phone":"+49 33432/457",
    "sg:postcode":"15374",
    "sg:province":"Brandenburg",
    "wof:name":"Martina Aschenbach",
    "wof:placetype":"venue"
},
  "geometry": {"coordinates":[14.137509,52.502754],"type":"Point"}
}