{
  "type": "Feature",
  "properties": {
    "iso:country":"DE",
    "sg:address":"Amtsstr. 3",
    "sg:city":"Rodenberg",
    "sg:phone":"+49 4957/233051",
    "sg:postcode":"31552",
    "sg:province":"Niedersachsen",
    "wof:name":"Volksbank",
    "wof:placetype":"venue"
},
  "geometry": {"coordinates":[9.355957,52.31242],"type":"Point"}
}