{
  "type": "Feature",
  "properties": {
    "iso:country":"DE",
    "sg:address":"Berrenrather Str. 361",
    "sg:city":"H\u00fcrth",
    "sg:phone":"+49 2233/965966",
    "sg:postcode":"50354",
    "sg:province":"Nordrhein-Westfalen",
    "wof:name":"Hehner Transport Gmbh",
    "wof:placetype":"venue"
},
  "geometry": {"coordinates":[6.8851299286,50.894908905],"type":"Point"}
}