{
  "type": "Feature",
  "properties": {
    "iso:country":"DE",
    "sg:address":"Rixstr. 6",
    "sg:city":"Pinneberg",
    "sg:postcode":"25421",
    "sg:province":"Schleswig-Holstein",
    "wof:name":"Balu Gesellschaft F\u00fcr Objekt- Und Geb\u00e4udeentwicklung Mbh",
    "wof:placetype":"venue"
},
  "geometry": {"coordinates":[9.7873573303,53.6492614746],"type":"Point"}
}