{
  "type": "Feature",
  "properties": {
    "iso:country":"DE",
    "sg:address":"Regentenstr. 14",
    "sg:city":"K\u00f6ln",
    "sg:phone":"+49 221/612972",
    "sg:postcode":"51063",
    "sg:province":"Nordrhein-Westfalen",
    "wof:name":"G. Niewisch",
    "wof:placetype":"venue"
},
  "geometry": {"coordinates":[7.002678,50.964039],"type":"Point"}
}