{
  "type": "Feature",
  "properties": {
    "iso:country":"DE",
    "sg:address":"Hornh\u00e4user Str. 72",
    "sg:city":"Oschersleben",
    "sg:phone":"+49 3949/2221",
    "sg:postcode":"39387",
    "sg:province":"Sachsen-Anhalt",
    "wof:name":"K. Kaiser",
    "wof:placetype":"venue"
},
  "geometry": {"coordinates":[11.219866,52.028187],"type":"Point"}
}