{
  "type": "Feature",
  "properties": {
    "iso:country":"DE",
    "sg:address":"Naumburger Str. 55",
    "sg:city":"Leipzig",
    "sg:phone":"+49 341/4806553",
    "sg:postcode":"04229",
    "sg:province":"Sachsen",
    "wof:name":"D. Erdmann",
    "wof:placetype":"venue"
},
  "geometry": {"coordinates":[12.324769,51.326859],"type":"Point"}
}