{
  "type": "Feature",
  "properties": {
    "iso:country":"DE",
    "sg:address":"Kirchberg 17",
    "sg:city":"Arnstein",
    "sg:phone":"+49 9363/365",
    "sg:postcode":"97450",
    "sg:province":"Bayern",
    "wof:name":"Psa Technologie E. K.",
    "wof:placetype":"venue"
},
  "geometry": {"coordinates":[9.9693183899,49.9782905579],"type":"Point"}
}