{
  "type": "Feature",
  "properties": {
    "iso:country":"DE",
    "sg:address":"Franz-Hartl-Str. 8",
    "sg:city":"Regensburg",
    "sg:phone":"+49 941/702417",
    "sg:postcode":"93053",
    "sg:province":"Bayern",
    "wof:name":"Mc Donalds",
    "wof:placetype":"venue"
},
  "geometry": {"coordinates":[12.110118866,48.993434906],"type":"Point"}
}