{
  "type": "Feature",
  "properties": {
    "iso:country":"DE",
    "sg:address":"Bohlweg 41",
    "sg:city":"Wildemann",
    "sg:phone":"+49 5323/6174",
    "sg:postcode":"38709",
    "sg:province":"Niedersachsen",
    "wof:name":"Manfred Eisfeld",
    "wof:placetype":"venue"
},
  "geometry": {"coordinates":[10.2838811874,51.8257255554],"type":"Point"}
}