{
  "type": "Feature",
  "properties": {
    "iso:country":"DE",
    "sg:address":"Biener Str. 39",
    "sg:city":"Lingen",
    "sg:phone":"+49 591/64662",
    "sg:postcode":"49808",
    "sg:province":"Niedersachsen",
    "wof:name":"Handelsagentur Driever Gmbh",
    "wof:placetype":"venue"
},
  "geometry": {"coordinates":[7.3158597946,52.5215492249],"type":"Point"}
}