{
  "type": "Feature",
  "properties": {
    "iso:country":"DE",
    "sg:address":"Bergstr. 6",
    "sg:city":"Zweibr\u00fccken",
    "sg:phone":"+49 6332/73456",
    "sg:postcode":"66482",
    "sg:province":"Rheinland-Pfalz",
    "wof:name":"Lisa",
    "wof:placetype":"venue"
},
  "geometry": {"coordinates":[7.365016,49.245682],"type":"Point"}
}