{
  "type": "Feature",
  "properties": {
    "iso:country":"DE",
    "sg:address":"Nombericher Str. 26",
    "sg:city":"Duisburg",
    "sg:phone":"+49 203/447255",
    "sg:postcode":"47137",
    "sg:province":"Nordrhein-Westfalen",
    "wof:name":"Pizzeria Bei Stefano",
    "wof:placetype":"venue"
},
  "geometry": {"coordinates":[6.7603259087,51.47032547],"type":"Point"}
}