{
  "type": "Feature",
  "properties": {
    "iso:country":"DE",
    "sg:address":"Osterwaldstr. 149",
    "sg:city":"M\u00fcnchen",
    "sg:phone":"+49 89/3689243",
    "sg:postcode":"80805",
    "sg:province":"Bayern",
    "wof:name":"H\u00f6ss Maschinenbau Kg",
    "wof:placetype":"venue"
},
  "geometry": {"coordinates":[11.608089,48.176075],"type":"Point"}
}