{
  "type": "Feature",
  "properties": {
    "iso:country":"DE",
    "sg:address":"Langenfelde 11",
    "sg:city":"Bad Schwartau",
    "sg:phone":"+49 451/21048",
    "sg:postcode":"23611",
    "sg:province":"Schleswig-Holstein",
    "wof:name":"Druckerei Timmermann Ohg",
    "wof:placetype":"venue"
},
  "geometry": {"coordinates":[10.66742,53.918251],"type":"Point"}
}