{
  "type": "Feature",
  "properties": {
    "iso:country":"DE",
    "sg:address":"Alte Ziegelei 3",
    "sg:city":"Aglasterhausen",
    "sg:phone":"+49 6262/4246",
    "sg:postcode":"74858",
    "sg:province":"Baden-W\u00fcrttemberg",
    "wof:name":"K. Sch\u00f6n",
    "wof:placetype":"venue"
},
  "geometry": {"coordinates":[8.9866,49.355629],"type":"Point"}
}