{
  "type": "Feature",
  "properties": {
    "iso:country":"DE",
    "sg:address":"Nietzschestr. 16",
    "sg:city":"Mannheim",
    "sg:phone":"+49 621/416256",
    "sg:postcode":"68165",
    "sg:province":"Baden-W\u00fcrttemberg",
    "wof:name":"Dietmar Ewald Architekt",
    "wof:placetype":"venue"
},
  "geometry": {"coordinates":[8.486738,49.480618],"type":"Point"}
}