{
  "type": "Feature",
  "properties": {
    "iso:country":"DE",
    "sg:address":"Zeppelinstr. 8",
    "sg:city":"Geldern",
    "sg:phone":"+49 2831/12051",
    "sg:postcode":"47608",
    "sg:province":"Nordrhein-Westfalen",
    "wof:name":"Bsab Elektronik Strulik & Bosch Gmbh",
    "wof:placetype":"venue"
},
  "geometry": {"coordinates":[6.3444261551,51.5246391296],"type":"Point"}
}