{
  "type": "Feature",
  "properties": {
    "iso:country":"DE",
    "sg:address":"Dorfplatz 1",
    "sg:city":"Schmidgaden",
    "sg:phone":"+49 9438/207",
    "sg:postcode":"92546",
    "sg:province":"Bayern",
    "wof:name":"Gastst\u00e4tte Josef Pr\u00f6ls",
    "wof:placetype":"venue"
},
  "geometry": {"coordinates":[12.0543270111,49.4342689514],"type":"Point"}
}