{
  "type": "Feature",
  "properties": {
    "iso:country":"DE",
    "sg:address":"Holsteiner Chaussee 319 A",
    "sg:city":"Hamburg",
    "sg:postcode":"22457",
    "sg:province":"Hamburg",
    "wof:name":"Agr Deko Service",
    "wof:placetype":"venue"
},
  "geometry": {"coordinates":[9.91035,53.638908],"type":"Point"}
}