{
  "type": "Feature",
  "properties": {
    "iso:country":"DE",
    "sg:address":"Woldemarstr. 4",
    "sg:city":"Detmold",
    "sg:phone":"+49 5231/33343",
    "sg:postcode":"32756",
    "sg:province":"Nordrhein-Westfalen",
    "wof:name":"Heike Mergel",
    "wof:placetype":"venue"
},
  "geometry": {"coordinates":[8.882859,51.936424],"type":"Point"}
}