{
  "type": "Feature",
  "properties": {
    "iso:country":"DE",
    "sg:address":"Pariser Str. 8",
    "sg:city":"Kaiserslautern",
    "sg:phone":"+49 631/72277",
    "sg:postcode":"67655",
    "sg:province":"Rheinland-Pfalz",
    "wof:name":"Dieter Und Ellen Sturm",
    "wof:placetype":"venue"
},
  "geometry": {"coordinates":[7.7647151947,49.4444847107],"type":"Point"}
}