{
  "type": "Feature",
  "properties": {
    "iso:country":"DE",
    "sg:address":"Siegburger Str. 229",
    "sg:city":"K\u00f6ln",
    "sg:phone":"+49 221/82700",
    "sg:postcode":"50679",
    "sg:province":"Nordrhein-Westfalen",
    "wof:name":"Strabag Projekt- Entwicklung Gmbh",
    "wof:placetype":"venue"
},
  "geometry": {"coordinates":[6.9804840088,50.9234313965],"type":"Point"}
}