{
  "type": "Feature",
  "properties": {
    "iso:country":"DE",
    "sg:address":"Am Berg 1",
    "sg:city":"Ro\u00dfbach",
    "sg:phone":"+49 2638/4530",
    "sg:postcode":"53547",
    "sg:province":"Rheinland-Pfalz",
    "wof:name":"Hans-peter Kr\u00f6ll Architekt",
    "wof:placetype":"venue"
},
  "geometry": {"coordinates":[7.41799,50.576599],"type":"Point"}
}