{
  "type": "Feature",
  "properties": {
    "iso:country":"DE",
    "sg:address":"Stolberger Str. 351-353",
    "sg:city":"K\u00f6ln",
    "sg:phone":"+49 221/49071",
    "sg:postcode":"50933",
    "sg:province":"Nordrhein-Westfalen",
    "wof:name":"B\u00d6ttcher Grundbesitz Verwaltung Gmbh & Co. Kg",
    "wof:placetype":"venue"
},
  "geometry": {"coordinates":[6.8878979683,50.9423179626],"type":"Point"}
}