{
  "type": "Feature",
  "properties": {
    "iso:country":"DE",
    "sg:address":"Auf der Heide 9",
    "sg:city":"Erwitte",
    "sg:postcode":"59597",
    "sg:province":"Nordrhein-Westfalen",
    "wof:name":"Zellmer Natursteine Joachim Zellmer E. K.",
    "wof:placetype":"venue"
},
  "geometry": {"coordinates":[8.3158721924,51.6072692871],"type":"Point"}
}