{
  "type": "Feature",
  "properties": {
    "iso:country":"DE",
    "sg:address":"Allersberger Str. 147",
    "sg:city":"N\u00fcrnberg",
    "sg:phone":"+49 911/467275",
    "sg:postcode":"90461",
    "sg:province":"Bayern",
    "wof:name":"Dieter Horrer",
    "wof:placetype":"venue"
},
  "geometry": {"coordinates":[11.093177,49.435375],"type":"Point"}
}