{
  "type": "Feature",
  "properties": {
    "iso:country":"DE",
    "sg:address":"Parumer Weg 35",
    "sg:city":"G\u00fcstrow",
    "sg:phone":"+49 3843/69400",
    "sg:postcode":"18273",
    "sg:province":"Mecklenburg-Vorpommern",
    "wof:name":"Omnibusverkehrsgesellschaft G\u00fcstrow Mbh",
    "wof:placetype":"venue"
},
  "geometry": {"coordinates":[12.1519775391,53.8019752502],"type":"Point"}
}