{
  "type": "Feature",
  "properties": {
    "iso:country":"DE",
    "sg:address":"Marktstr. 12",
    "sg:city":"Wei\u00dfensee",
    "sg:phone":"+49 36374/20328",
    "sg:postcode":"99631",
    "sg:province":"Th\u00fcringen",
    "wof:name":"J. Embrecht",
    "wof:placetype":"venue"
},
  "geometry": {"coordinates":[11.0649633408,51.2000999451],"type":"Point"}
}