{
  "type": "Feature",
  "properties": {
    "iso:country":"DE",
    "sg:address":"Schwojerstr. 33",
    "sg:city":"Olching",
    "sg:phone":"+49 8142/30010",
    "sg:postcode":"82140",
    "sg:province":"Bayern",
    "wof:name":"Franz Wesinger Architekt",
    "wof:placetype":"venue"
},
  "geometry": {"coordinates":[11.330308,48.204258],"type":"Point"}
}