{
  "type": "Feature",
  "properties": {
    "iso:country":"DE",
    "sg:address":"Postfach 119::",
    "sg:city":"Stadtroda",
    "sg:postcode":"07646",
    "sg:province":"Th\u00fcringen",
    "wof:name":"Kreissparkasse Stadtroda",
    "wof:placetype":"venue"
},
  "geometry": {"coordinates":[11.72737,50.857979],"type":"Point"}
}