{
  "type": "Feature",
  "properties": {
    "iso:country":"DE",
    "sg:address":"Bergstr. 2",
    "sg:city":"Drolshagen",
    "sg:phone":"+49 4927/6193450",
    "sg:postcode":"57489",
    "sg:province":"Nordrhein-Westfalen",
    "wof:name":"August Kadagies Gmbh & Co Kg",
    "wof:placetype":"venue"
},
  "geometry": {"coordinates":[7.80414,51.037472],"type":"Point"}
}