{
  "type": "Feature",
  "properties": {
    "iso:country":"DE",
    "sg:address":"Am Sande 7",
    "sg:city":"Buxtehude",
    "sg:postcode":"21614",
    "sg:province":"Niedersachsen",
    "wof:name":"Bsb Brandschutz Systembau Buxtehude Gmbh",
    "wof:placetype":"venue"
},
  "geometry": {"coordinates":[9.645298,53.478012],"type":"Point"}
}