{
  "type": "Feature",
  "properties": {
    "iso:country":"DE",
    "sg:address":"Heymelstr. 3",
    "sg:city":"Bremen",
    "sg:phone":"+49 421/236402",
    "sg:postcode":"28359",
    "sg:province":"Bremen",
    "wof:name":"Verein Der Feunde Zonta E. V. Petra Schottelius",
    "wof:placetype":"venue"
},
  "geometry": {"coordinates":[8.8639812469,53.094367981],"type":"Point"}
}