{
  "type": "Feature",
  "properties": {
    "iso:country":"DE",
    "sg:address":"Am Dorfweiher 8",
    "sg:city":"Waldbr\u00f6l",
    "sg:phone":"+49 2291/2137",
    "sg:postcode":"51545",
    "sg:province":"Nordrhein-Westfalen",
    "wof:name":"Horst Demmer Heilpraktiker",
    "wof:placetype":"venue"
},
  "geometry": {"coordinates":[7.6555681229,50.8930664062],"type":"Point"}
}