{
  "type": "Feature",
  "properties": {
    "iso:country":"DE",
    "sg:address":"Siedlung 2",
    "sg:city":"Gr\u00e4fendorf",
    "sg:phone":"+49 33746/72745",
    "sg:postcode":"14913",
    "sg:province":"Brandenburg",
    "wof:name":"B. Jorkschat",
    "wof:placetype":"venue"
},
  "geometry": {"coordinates":[13.191032,51.9109],"type":"Point"}
}