{
  "type": "Feature",
  "properties": {
    "iso:country":"DE",
    "sg:address":"Raiffeisenstr. 2",
    "sg:city":"Forstinning",
    "sg:phone":"+49 8121/46997",
    "sg:postcode":"85661",
    "sg:province":"Bayern",
    "wof:name":"Stefan Denser Rechtsanwalt",
    "wof:placetype":"venue"
},
  "geometry": {"coordinates":[11.9098320007,48.1695365906],"type":"Point"}
}