{
  "type": "Feature",
  "properties": {
    "iso:country":"DE",
    "sg:address":"Implerstr. 34",
    "sg:city":"M\u00fcnchen",
    "sg:phone":"+49 89/74688630",
    "sg:postcode":"81371",
    "sg:province":"Bayern",
    "wof:name":"Mischa Mihajlovic",
    "wof:placetype":"venue"
},
  "geometry": {"coordinates":[11.5480899811,48.1199302673],"type":"Point"}
}