{
  "type": "Feature",
  "properties": {
    "iso:country":"DE",
    "sg:address":"Hohenleuchtestr. 9",
    "sg:city":"Holzwickede",
    "sg:phone":"+49 2301/2531",
    "sg:postcode":"59439",
    "sg:province":"Nordrhein-Westfalen",
    "wof:name":"K.-h. Helms",
    "wof:placetype":"venue"
},
  "geometry": {"coordinates":[7.6110610962,51.498500824],"type":"Point"}
}