{
  "type": "Feature",
  "properties": {
    "iso:country":"DE",
    "sg:address":"Bauseweinallee 63",
    "sg:city":"M\u00fcnchen",
    "sg:phone":"+49 89/8116016",
    "sg:postcode":"81247",
    "sg:province":"Bayern",
    "wof:name":"Team Collection",
    "wof:placetype":"venue"
},
  "geometry": {"coordinates":[11.4738721848,48.1718673706],"type":"Point"}
}