{
  "type": "Feature",
  "properties": {
    "iso:country":"DE",
    "sg:address":"Querstr. 1",
    "sg:city":"Berlin",
    "sg:postcode":"14163",
    "sg:province":"Berlin",
    "wof:name":"C. Schwabe & Co. Kg",
    "wof:placetype":"venue"
},
  "geometry": {"coordinates":[13.248834,52.437321],"type":"Point"}
}