{
  "type": "Feature",
  "properties": {
    "iso:country":"DE",
    "sg:address":"Heierstr. 43",
    "sg:city":"Viersen",
    "sg:phone":"+49 2162/16166",
    "sg:postcode":"41747",
    "sg:province":"Nordrhein-Westfalen",
    "wof:name":"Klaus Hurdalek Heilpraktiker",
    "wof:placetype":"venue"
},
  "geometry": {"coordinates":[6.3890748024,51.251914978],"type":"Point"}
}