{
  "type": "Feature",
  "properties": {
    "iso:country":"DE",
    "sg:address":"Rh\u00f6nstr. 34",
    "sg:city":"Langenselbold",
    "sg:phone":"+49 6184/3865",
    "sg:postcode":"63505",
    "sg:province":"Hessen",
    "wof:name":"Dressler Lehrmittel Gmbh",
    "wof:placetype":"venue"
},
  "geometry": {"coordinates":[9.0490112305,50.1793327332],"type":"Point"}
}