{
  "type": "Feature",
  "properties": {
    "iso:country":"DE",
    "sg:address":"Schlesische Str. 26",
    "sg:city":"Berlin",
    "sg:phone":"+49 30",
    "sg:postcode":"10997",
    "sg:province":"Berlin",
    "wof:name":"Das Sockenhaus - Der G\u00fcnstige Onlineshop",
    "wof:placetype":"venue"
},
  "geometry": {"coordinates":[13.4482545853,52.4978370667],"type":"Point"}
}