{
  "type": "Feature",
  "properties": {
    "iso:country":"DE",
    "sg:address":"Hahnenstr. 35",
    "sg:city":"Elsdorf",
    "sg:phone":"+49 2274/5252",
    "sg:postcode":"50189",
    "sg:province":"Nordrhein-Westfalen",
    "wof:name":"Elisabeth Fa\u00dfbender",
    "wof:placetype":"venue"
},
  "geometry": {"coordinates":[6.5456848145,50.9662322998],"type":"Point"}
}