{
  "type": "Feature",
  "properties": {
    "iso:country":"DE",
    "sg:address":"Stresemannstr. 46",
    "sg:city":"Bremerhaven",
    "sg:postcode":"27570",
    "sg:province":"Bremen",
    "wof:name":"Energiekontor Griechenland Epanosifi Gmbh & Co.",
    "wof:placetype":"venue"
},
  "geometry": {"coordinates":[8.594394,53.548107],"type":"Point"}
}