{
  "type": "Feature",
  "properties": {
    "iso:country":"DE",
    "sg:address":"Alemannenstr. 14",
    "sg:city":"Geisingen",
    "sg:phone":"+49 7704/6937",
    "sg:postcode":"78187",
    "sg:province":"Baden-W\u00fcrttemberg",
    "wof:name":"F. Boll",
    "wof:placetype":"venue"
},
  "geometry": {"coordinates":[8.617767334,47.9122200012],"type":"Point"}
}