{
  "type": "Feature",
  "properties": {
    "iso:country":"DE",
    "sg:address":"Jakobstr. 44",
    "sg:city":"N\u00fcrnberg",
    "sg:phone":"+49 911/221656",
    "sg:postcode":"90402",
    "sg:province":"Bayern",
    "wof:name":"L\u00f6hlein & Seitz Gmbh",
    "wof:placetype":"venue"
},
  "geometry": {"coordinates":[11.0717086792,49.4491729736],"type":"Point"}
}