{
  "type": "Feature",
  "properties": {
    "iso:country":"DE",
    "sg:address":"Milkdelle 6",
    "sg:city":"Essen",
    "sg:phone":"+49 201/865220",
    "sg:postcode":"45149",
    "sg:province":"Nordrhein-Westfalen",
    "wof:name":"Mc Immobilien Verwaltungs Gmbh & Co.",
    "wof:placetype":"venue"
},
  "geometry": {"coordinates":[6.9686980247,51.4222984314],"type":"Point"}
}