{
  "type": "Feature",
  "properties": {
    "iso:country":"DE",
    "sg:address":"Friedrich-August-Str. 9",
    "sg:city":"Birkenfeld",
    "sg:phone":"+49 6782/5825",
    "sg:postcode":"55765",
    "sg:province":"Rheinland-Pfalz",
    "wof:name":"Peter Thiel",
    "wof:placetype":"venue"
},
  "geometry": {"coordinates":[7.165202,49.647533],"type":"Point"}
}