{
  "type": "Feature",
  "properties": {
    "iso:country":"DE",
    "sg:address":"Paderborner Str. 2",
    "sg:city":"Berlin",
    "sg:phone":"+49 30/8966880",
    "sg:postcode":"10709",
    "sg:province":"Berlin",
    "wof:name":"Rechtsanw\u00e4lte K\u00fchnel Und Partner",
    "wof:placetype":"venue"
},
  "geometry": {"coordinates":[13.3068799973,52.497177124],"type":"Point"}
}