{
  "type": "Feature",
  "properties": {
    "iso:country":"DE",
    "sg:address":"Sonnborner Str. 118",
    "sg:city":"Wuppertal",
    "sg:phone":"+49 202/740437",
    "sg:postcode":"42327",
    "sg:province":"Nordrhein-Westfalen",
    "wof:name":"W. Schmidt Augenoptiker",
    "wof:placetype":"venue"
},
  "geometry": {"coordinates":[7.0990438461,51.2384872437],"type":"Point"}
}