{
  "type": "Feature",
  "properties": {
    "iso:country":"DE",
    "sg:address":"Damaschkestr.",
    "sg:city":"Wolfen",
    "sg:postcode":"06766",
    "sg:province":"Sachsen-Anhalt",
    "wof:name":"Videokonferenztechnik",
    "wof:placetype":"venue"
},
  "geometry": {"coordinates":[12.26125,51.661915],"type":"Point"}
}