{
  "type": "Feature",
  "properties": {
    "iso:country":"DE",
    "sg:address":"Spandauer Str. 27",
    "sg:city":"Berlin",
    "sg:phone":"+49 30/2427261",
    "sg:postcode":"10178",
    "sg:province":"Berlin",
    "wof:name":"Nikolaus Struck",
    "wof:placetype":"venue"
},
  "geometry": {"coordinates":[13.408478,52.517231],"type":"Point"}
}