{
  "type": "Feature",
  "properties": {
    "iso:country":"DE",
    "sg:address":"Von-Essen-Str. 36",
    "sg:city":"Hamburg",
    "sg:phone":"+49 40/294416",
    "sg:postcode":"22081",
    "sg:province":"Hamburg",
    "wof:name":"Miklos Meszaros Damenfriseur",
    "wof:placetype":"venue"
},
  "geometry": {"coordinates":[10.044291,53.572937],"type":"Point"}
}