{
  "type": "Feature",
  "properties": {
    "iso:country":"DE",
    "sg:address":"Sand 13",
    "sg:city":"T\u00fcbingen",
    "sg:postcode":"72076",
    "sg:province":"Baden-W\u00fcrttemberg",
    "wof:name":"Insuma Gmbh",
    "wof:placetype":"venue"
},
  "geometry": {"coordinates":[9.0717458725,48.5339355469],"type":"Point"}
}