{
  "type": "Feature",
  "properties": {
    "iso:country":"DE",
    "sg:address":"Am Waldspitz 29",
    "sg:city":"M\u00fcnchen",
    "sg:phone":"+49 89/7003051",
    "sg:postcode":"81375",
    "sg:province":"Bayern",
    "wof:name":"D. Popoff Verlagsvertreter",
    "wof:placetype":"venue"
},
  "geometry": {"coordinates":[11.468203,48.115566],"type":"Point"}
}