{
  "type": "Feature",
  "properties": {
    "iso:country":"DE",
    "sg:address":"Torenstr. 12",
    "sg:city":"Meersburg",
    "sg:phone":"+49 7532/7575",
    "sg:postcode":"88709",
    "sg:province":"Baden-W\u00fcrttemberg",
    "wof:name":"Sybille Marcinowski Krankengymnastin",
    "wof:placetype":"venue"
},
  "geometry": {"coordinates":[9.285997,47.697617],"type":"Point"}
}