{
  "type": "Feature",
  "properties": {
    "iso:country":"DE",
    "sg:address":"Kirchstr. 12",
    "sg:city":"Stockstadt",
    "sg:postcode":"64589",
    "sg:province":"Hessen",
    "wof:name":"Volksb\u00fccherei",
    "wof:placetype":"venue"
},
  "geometry": {"coordinates":[8.468287,49.809105],"type":"Point"}
}