{
  "type": "Feature",
  "properties": {
    "iso:country":"DE",
    "sg:address":"Aidenbacher Str. 4",
    "sg:city":"Egglham",
    "sg:phone":"+49 8543/729",
    "sg:postcode":"84385",
    "sg:province":"Bayern",
    "wof:name":"H. Immerfall",
    "wof:placetype":"venue"
},
  "geometry": {"coordinates":[13.0574617386,48.5322608948],"type":"Point"}
}