{
  "type": "Feature",
  "properties": {
    "iso:country":"DE",
    "sg:address":"Wilhelmstr. 49",
    "sg:city":"Diez",
    "sg:phone":"+49 6432/2697",
    "sg:postcode":"65582",
    "sg:province":"Rheinland-Pfalz",
    "wof:name":"Berkes",
    "wof:placetype":"venue"
},
  "geometry": {"coordinates":[8.0129957199,50.3710174561],"type":"Point"}
}