{
  "type": "Feature",
  "properties": {
    "iso:country":"DE",
    "sg:address":"Karstr. 19 a",
    "sg:city":"M\u00f6nchengladbach",
    "sg:postcode":"41068",
    "sg:province":"Nordrhein-Westfalen",
    "wof:name":"Getech Ges. F\u00fcr Innovative Elektrotechnik Mbh",
    "wof:placetype":"venue"
},
  "geometry": {"coordinates":[6.413670063,51.1872177124],"type":"Point"}
}