{
  "type": "Feature",
  "properties": {
    "iso:country":"DE",
    "sg:address":"Br\u00fchlstr. 16",
    "sg:city":"Aalen",
    "sg:phone":"+49 7361/62086",
    "sg:postcode":"73430",
    "sg:province":"Baden-W\u00fcrttemberg",
    "wof:name":"Obel Und Britsch Rechtsanw\u00e4lte",
    "wof:placetype":"venue"
},
  "geometry": {"coordinates":[10.0884847641,48.8369598389],"type":"Point"}
}