{
  "type": "Feature",
  "properties": {
    "iso:country":"DE",
    "sg:address":"Poxstall",
    "sg:city":"Ebermannstadt",
    "sg:phone":"+49 9194/1883",
    "sg:postcode":"91320",
    "sg:province":"Bayern",
    "wof:name":"J. Schriefer",
    "wof:placetype":"venue"
},
  "geometry": {"coordinates":[11.1365823746,49.7717514038],"type":"Point"}
}