{
  "type": "Feature",
  "properties": {
    "iso:country":"DE",
    "sg:address":"G\u00f6rlitzer Str. 15",
    "sg:city":"Rothenburg",
    "sg:phone":"+49 35891/35151",
    "sg:postcode":"02929",
    "sg:province":"Sachsen",
    "wof:name":"E. Frenzel",
    "wof:placetype":"venue"
},
  "geometry": {"coordinates":[14.9705467224,51.3328971863],"type":"Point"}
}