{
  "type": "Feature",
  "properties": {
    "iso:country":"DE",
    "sg:address":"Hohenfeldstr. 18",
    "sg:city":"Bad Camberg",
    "sg:phone":"+49 6434/7008",
    "sg:postcode":"65520",
    "sg:province":"Hessen",
    "wof:name":"Heinz Stillger Architekt",
    "wof:placetype":"venue"
},
  "geometry": {"coordinates":[8.277013,50.296597],"type":"Point"}
}