{
  "type": "Feature",
  "properties": {
    "iso:country":"DE",
    "sg:address":"Lindwurmstr. 72",
    "sg:city":"M\u00fcnchen",
    "sg:phone":"+49 89/7473540",
    "sg:postcode":"80337",
    "sg:province":"Bayern",
    "wof:name":"D. Und E. Eilebrecht",
    "wof:placetype":"venue"
},
  "geometry": {"coordinates":[11.5515613556,48.1262588501],"type":"Point"}
}