{
  "type": "Feature",
  "properties": {
    "iso:country":"DE",
    "sg:address":"Gradebergstr. 6",
    "sg:city":"\u00dcberlingen",
    "sg:phone":"+49 7551/4196",
    "sg:postcode":"88662",
    "sg:province":"Baden-W\u00fcrttemberg",
    "wof:name":"Martin Miller",
    "wof:placetype":"venue"
},
  "geometry": {"coordinates":[9.1626234055,47.7666625977],"type":"Point"}
}