{
  "type": "Feature",
  "properties": {
    "iso:country":"DE",
    "sg:address":"Am Heldenhain 9",
    "sg:city":"Diepholz",
    "sg:postcode":"49356",
    "sg:province":"Niedersachsen",
    "wof:name":"Tasche Ohg",
    "wof:placetype":"venue"
},
  "geometry": {"coordinates":[8.37083,52.613483],"type":"Point"}
}