{
  "type": "Feature",
  "properties": {
    "iso:country":"DE",
    "sg:address":"Stadtplatz 9",
    "sg:city":"Windischeschenbach",
    "sg:phone":"+49 9681/2882",
    "sg:postcode":"92670",
    "sg:province":"Bayern",
    "wof:name":"Norma Lebensmittelfilial- Betrieb Gmbh & Co. Kg",
    "wof:placetype":"venue"
},
  "geometry": {"coordinates":[12.1546363831,49.8031539917],"type":"Point"}
}