{
  "type": "Feature",
  "properties": {
    "iso:country":"DE",
    "sg:address":"Ulmer Str 2",
    "sg:city":"Laatzen",
    "sg:phone":"+49 511/5909150",
    "sg:postcode":"30880",
    "sg:province":"Niedersachsen",
    "wof:name":"Earth Tech Kl\u00e4rtechnik Gmbh",
    "wof:placetype":"venue"
},
  "geometry": {"coordinates":[9.7915391922,52.322971344],"type":"Point"}
}