{
  "type": "Feature",
  "properties": {
    "iso:country":"DE",
    "sg:address":"Hauptstr. 44",
    "sg:city":"Rammenau",
    "sg:phone":"+49 3594/3603",
    "sg:postcode":"01877",
    "sg:province":"Sachsen",
    "wof:name":"K. Bach",
    "wof:placetype":"venue"
},
  "geometry": {"coordinates":[14.1386871338,51.1540603638],"type":"Point"}
}