{
  "type": "Feature",
  "properties": {
    "iso:country":"DE",
    "sg:address":"Bischofsholer Damm 15",
    "sg:city":"Hannover",
    "sg:phone":"+49 511/8566",
    "sg:postcode":"30173",
    "sg:province":"Niedersachsen",
    "wof:name":"Veterin\u00e4rmedizinhistorisches Museum Tier\u00e4rztlicher",
    "wof:placetype":"venue"
},
  "geometry": {"coordinates":[9.766177,52.367493],"type":"Point"}
}