{
  "type": "Feature",
  "properties": {
    "iso:country":"DE",
    "sg:address":"Wehrstr 2",
    "sg:city":"Schwindegg",
    "sg:phone":"+49 8082/93560",
    "sg:postcode":"84419",
    "sg:province":"Bayern",
    "wof:name":"Kaspareth Gmbh",
    "wof:placetype":"venue"
},
  "geometry": {"coordinates":[12.2641677856,48.2748069763],"type":"Point"}
}