{
  "type": "Feature",
  "properties": {
    "iso:country":"DE",
    "sg:address":"Talstr. 73",
    "sg:city":"Bad Liebenzell",
    "sg:phone":"+49 7084/7947",
    "sg:postcode":"75378",
    "sg:province":"Baden-W\u00fcrttemberg",
    "wof:name":"Hans Fuchs",
    "wof:placetype":"venue"
},
  "geometry": {"coordinates":[8.682981,48.768627],"type":"Point"}
}