{
  "type": "Feature",
  "properties": {
    "iso:country":"DE",
    "sg:address":"Gai\u00dfacher Str. 30",
    "sg:city":"Lenggries",
    "sg:phone":"+49 8042/1300",
    "sg:postcode":"83661",
    "sg:province":"Bayern",
    "wof:name":"G\u00e4stehaus Maria Drexler",
    "wof:placetype":"venue"
},
  "geometry": {"coordinates":[11.5747270584,47.6861495972],"type":"Point"}
}