{
  "type": "Feature",
  "properties": {
    "iso:country":"DE",
    "sg:address":"Gewerberg. 5",
    "sg:city":"Holzkirchen",
    "sg:phone":"+49 8024/90680",
    "sg:postcode":"83607",
    "sg:province":"Bayern",
    "wof:name":"Heinze Kg",
    "wof:placetype":"venue"
},
  "geometry": {"coordinates":[11.7166252136,47.8801727295],"type":"Point"}
}