{
  "type": "Feature",
  "properties": {
    "iso:country":"DE",
    "sg:address":"Franz-Mehring-Str. 15",
    "sg:city":"Schwerin",
    "sg:phone":"+49 385/715445",
    "sg:postcode":"19053",
    "sg:province":"Mecklenburg-Vorpommern",
    "wof:name":"H. Brauer",
    "wof:placetype":"venue"
},
  "geometry": {"coordinates":[11.4064178467,53.6323852539],"type":"Point"}
}