{
  "type": "Feature",
  "properties": {
    "iso:country":"DE",
    "sg:address":"Gewerbestr. 16",
    "sg:city":"Freiburg",
    "sg:phone":"+49 7664/910768",
    "sg:postcode":"79112",
    "sg:province":"Baden-W\u00fcrttemberg",
    "wof:name":"G\u00fcnes Dienstleistungs- Gmbh",
    "wof:placetype":"venue"
},
  "geometry": {"coordinates":[7.71851,47.997128],"type":"Point"}
}