{
  "type": "Feature",
  "properties": {
    "iso:country":"DE",
    "sg:address":"Finkenweg 12",
    "sg:city":"Neitersen",
    "sg:postcode":"57638",
    "sg:province":"Rheinland-Pfalz",
    "wof:name":"Keramische Wohn- Gestaltung Fritz Gmbh",
    "wof:placetype":"venue"
},
  "geometry": {"coordinates":[7.5951581001,50.6686477661],"type":"Point"}
}