{
  "type": "Feature",
  "properties": {
    "iso:country":"DE",
    "sg:address":"Pfarrer-Fein-Str. 2",
    "sg:city":"Montabaur",
    "sg:phone":"+49 2602/12701",
    "sg:postcode":"56410",
    "sg:province":"Rheinland-Pfalz",
    "wof:name":"Karl-heinz Decker",
    "wof:placetype":"venue"
},
  "geometry": {"coordinates":[7.7952551842,50.4423561096],"type":"Point"}
}