{
  "type": "Feature",
  "properties": {
    "iso:country":"DE",
    "sg:address":"Dudenh\u00f6fer Str. 18",
    "sg:city":"Rodgau",
    "sg:phone":"+49 6106/3348",
    "sg:postcode":"63110",
    "sg:province":"Hessen",
    "wof:name":"Gebr. Simon",
    "wof:placetype":"venue"
},
  "geometry": {"coordinates":[8.886329,50.023052],"type":"Point"}
}