{
  "type": "Feature",
  "properties": {
    "iso:country":"DE",
    "sg:address":"Rupprechtstegen",
    "sg:city":"Hartenstein",
    "sg:phone":"+49 9152/530",
    "sg:postcode":"91235",
    "sg:province":"Bayern",
    "wof:name":"Tarzan",
    "wof:placetype":"venue"
},
  "geometry": {"coordinates":[11.482219696,49.599899292],"type":"Point"}
}