{
  "type": "Feature",
  "properties": {
    "iso:country":"DE",
    "sg:address":"Uferstr. 92",
    "sg:city":"Gr\u00f6mitz",
    "sg:phone":"+49 4562/1273",
    "sg:postcode":"23743",
    "sg:province":"Schleswig-Holstein",
    "wof:name":"Sager",
    "wof:placetype":"venue"
},
  "geometry": {"coordinates":[10.9512500763,54.1398582458],"type":"Point"}
}