{
  "type": "Feature",
  "properties": {
    "iso:country":"DE",
    "sg:address":"Eichbuscher Ring 15",
    "sg:city":"Dresden",
    "sg:phone":"+49 351/2689015",
    "sg:postcode":"01328",
    "sg:province":"Sachsen",
    "wof:name":"Ralf Woidt",
    "wof:placetype":"venue"
},
  "geometry": {"coordinates":[13.8750953674,51.0326957703],"type":"Point"}
}