{
  "type": "Feature",
  "properties": {
    "iso:country":"DE",
    "sg:address":"Holzschuherring 40",
    "sg:city":"Erlangen",
    "sg:phone":"+49 9131/601111",
    "sg:postcode":"91058",
    "sg:province":"Bayern",
    "wof:name":"Freizeitzentrum St. Kunigund Inh. Josef Huber",
    "wof:placetype":"venue"
},
  "geometry": {"coordinates":[10.9897460938,49.5474281311],"type":"Point"}
}