{
  "type": "Feature",
  "properties": {
    "iso:country":"DE",
    "sg:address":"Am Holl\u00e4nder 1",
    "sg:city":"Finsterwalde",
    "sg:phone":"+49 3531/73046",
    "sg:postcode":"03238",
    "sg:province":"Brandenburg",
    "wof:name":"Sons Babychic Gmbh",
    "wof:placetype":"venue"
},
  "geometry": {"coordinates":[13.70835,51.639912],"type":"Point"}
}