{
  "type": "Feature",
  "properties": {
    "iso:country":"DE",
    "sg:address":"Bl\u00fccherstr. 4",
    "sg:city":"Berlin",
    "sg:phone":"+49 30/7122266",
    "sg:postcode":"12207",
    "sg:province":"Berlin",
    "wof:name":"Werner M\u00f6bius & Sohn Ohg",
    "wof:placetype":"venue"
},
  "geometry": {"coordinates":[13.309702,52.415577],"type":"Point"}
}