{
  "type": "Feature",
  "properties": {
    "iso:country":"DE",
    "sg:address":"Hagedornstr. 12",
    "sg:city":"Halle",
    "sg:phone":"+49 5201/665266",
    "sg:postcode":"33790",
    "sg:province":"Nordrhein-Westfalen",
    "wof:name":"Blaschke Kg Maschinen",
    "wof:placetype":"venue"
},
  "geometry": {"coordinates":[8.362457,52.065792],"type":"Point"}
}