{
  "type": "Feature",
  "properties": {
    "iso:country":"DE",
    "sg:address":"K\u00f6bler Weg 53",
    "sg:city":"Hammersbach",
    "sg:phone":"+49 6185/1410",
    "sg:postcode":"63546",
    "sg:province":"Hessen",
    "wof:name":"Rudolf Reinhardt",
    "wof:placetype":"venue"
},
  "geometry": {"coordinates":[8.99824,50.22934],"type":"Point"}
}