{
  "type": "Feature",
  "properties": {
    "iso:country":"DE",
    "sg:address":"Am M\u00fchlenborn 34",
    "sg:city":"Lebach",
    "sg:phone":"+49 6881/51212",
    "sg:postcode":"66822",
    "sg:province":"Saarland",
    "wof:name":"Carmen Dann Immobilienmaklerin",
    "wof:placetype":"venue"
},
  "geometry": {"coordinates":[6.9207048416,49.4175758362],"type":"Point"}
}