{
  "type": "Feature",
  "properties": {
    "iso:country":"DE",
    "sg:address":"Heutingsheimer Str. 50",
    "sg:city":"Stuttgart",
    "sg:phone":"+49 711/825013",
    "sg:postcode":"70439",
    "sg:province":"Baden-W\u00fcrttemberg",
    "wof:name":"Richard Heist Immobilienmakler",
    "wof:placetype":"venue"
},
  "geometry": {"coordinates":[9.1640844345,48.8428230286],"type":"Point"}
}