{
  "type": "Feature",
  "properties": {
    "iso:country":"DE",
    "sg:address":"Rathausstr. 71",
    "sg:city":"Viernheim",
    "sg:phone":"+49 6204/2206",
    "sg:postcode":"68519",
    "sg:province":"Hessen",
    "wof:name":"Textilhaus Karl Borrom\u00e4us Winkler",
    "wof:placetype":"venue"
},
  "geometry": {"coordinates":[8.5760631561,49.5352783203],"type":"Point"}
}