{
  "type": "Feature",
  "properties": {
    "iso:country":"DE",
    "sg:address":"Lange Str. 99",
    "sg:city":"Herbrechtingen",
    "sg:phone":"+49 7324/3060",
    "sg:postcode":"89542",
    "sg:province":"Baden-W\u00fcrttemberg",
    "wof:name":"Avia Tankstelle",
    "wof:placetype":"venue"
},
  "geometry": {"coordinates":[10.1816358566,48.618938446],"type":"Point"}
}