{
  "type": "Feature",
  "properties": {
    "iso:country":"DE",
    "sg:address":"Alt Frohse 42",
    "sg:city":"Sch\u00f6nebeck",
    "sg:phone":"+49 3928/400111",
    "sg:postcode":"39218",
    "sg:province":"Sachsen-Anhalt",
    "wof:name":"Martin Bauer",
    "wof:placetype":"venue"
},
  "geometry": {"coordinates":[11.714582,52.033035],"type":"Point"}
}