{
  "type": "Feature",
  "properties": {
    "iso:country":"DE",
    "sg:address":"Osterstr. 1",
    "sg:city":"H\u00fcllhorst",
    "sg:phone":"+49 5744/1339",
    "sg:postcode":"32609",
    "sg:province":"Nordrhein-Westfalen",
    "wof:name":"Amts-apotheke",
    "wof:placetype":"venue"
},
  "geometry": {"coordinates":[8.670707,52.27425],"type":"Point"}
}