{
  "type": "Feature",
  "properties": {
    "iso:country":"DE",
    "sg:address":"Bergstr. 5",
    "sg:city":"Zella-Mehlis",
    "sg:phone":"+49 3682/41864",
    "sg:postcode":"98544",
    "sg:province":"Th\u00fcringen",
    "wof:name":"Thomas Franke Architekt",
    "wof:placetype":"venue"
},
  "geometry": {"coordinates":[10.675425,50.653458],"type":"Point"}
}