{
  "type": "Feature",
  "properties": {
    "iso:country":"DE",
    "sg:address":"Reinhardstr. 66a",
    "sg:city":"Aachen",
    "sg:phone":"+49 241/9529542",
    "sg:postcode":"52078",
    "sg:province":"Nordrhein-Westfalen",
    "wof:name":"Birkhild Jaspert-g\u00e4rtner Rechtsanw\u00e4ltin",
    "wof:placetype":"venue"
},
  "geometry": {"coordinates":[6.13793993,50.7666549683],"type":"Point"}
}