{
  "type": "Feature",
  "properties": {
    "iso:country":"DE",
    "sg:address":"Germaniastr. 13",
    "sg:city":"Lehrte",
    "sg:phone":"+49 4951/3254912",
    "sg:postcode":"31275",
    "sg:province":"Niedersachsen",
    "wof:name":"Giuseppe Donadei",
    "wof:placetype":"venue"
},
  "geometry": {"coordinates":[9.9871969223,52.3730354309],"type":"Point"}
}