{
  "type": "Feature",
  "properties": {
    "iso:country":"DE",
    "sg:address":"Jasminweg 12",
    "sg:city":"Bochum",
    "sg:phone":"+49 2327/75014",
    "sg:postcode":"44869",
    "sg:province":"Nordrhein-Westfalen",
    "wof:name":"Greenteam Panda-b\u00e4ren -verein Gegen Umweltkriminalit\u00e4t-",
    "wof:placetype":"venue"
},
  "geometry": {"coordinates":[7.1482667923,51.4573860168],"type":"Point"}
}