{
  "type": "Feature",
  "properties": {
    "iso:country":"DE",
    "sg:address":"Schallerstr. 2",
    "sg:city":"Meiningen",
    "sg:phone":"+49 3693/3039",
    "sg:postcode":"98617",
    "sg:province":"Th\u00fcringen",
    "wof:name":"Volker Havekost Transportunternehmen",
    "wof:placetype":"venue"
},
  "geometry": {"coordinates":[10.422517,50.562981],"type":"Point"}
}