{
  "type": "Feature",
  "properties": {
    "iso:country":"DE",
    "sg:address":"Gewerbeallee 11",
    "sg:city":"Crivitz",
    "sg:phone":"+49 3863/54020",
    "sg:postcode":"19089",
    "sg:province":"Mecklenburg-Vorpommern",
    "wof:name":"Hellmann Worldwide Logistics Gmbh & Co Kg",
    "wof:placetype":"venue"
},
  "geometry": {"coordinates":[11.66656,53.564301],"type":"Point"}
}