{
  "type": "Feature",
  "properties": {
    "iso:country":"DE",
    "sg:address":"Aubing-Ost-Str. 79a",
    "sg:city":"M\u00fcnchen",
    "sg:phone":"+49 89/8634476",
    "sg:postcode":"81245",
    "sg:province":"Bayern",
    "wof:name":"Dieter Sedlacek",
    "wof:placetype":"venue"
},
  "geometry": {"coordinates":[11.4291801453,48.157787323],"type":"Point"}
}