{
  "type": "Feature",
  "properties": {
    "iso:country":"DE",
    "sg:address":"Marktplatz 5",
    "sg:city":"L\u00f6rrach",
    "sg:phone":"+49 7621/40040",
    "sg:postcode":"79539",
    "sg:province":"Baden-W\u00fcrttemberg",
    "wof:name":"Victoria",
    "wof:placetype":"venue"
},
  "geometry": {"coordinates":[7.6608147621,47.6116943359],"type":"Point"}
}