{
  "type": "Feature",
  "properties": {
    "iso:country":"DE",
    "sg:address":"Lange Str. 16",
    "sg:city":"Grimma",
    "sg:phone":"+49 3437/910137",
    "sg:postcode":"04668",
    "sg:province":"Sachsen",
    "wof:name":"G\u00f6schen-apotheke E. Kfr.",
    "wof:placetype":"venue"
},
  "geometry": {"coordinates":[12.726564,51.23344],"type":"Point"}
}