{
  "type": "Feature",
  "properties": {
    "iso:country":"DE",
    "sg:address":"Beul 4",
    "sg:city":"Werdohl",
    "sg:phone":"+49 2392/91890",
    "sg:postcode":"58791",
    "sg:province":"Nordrhein-Westfalen",
    "wof:name":"Seniorenheim Forsthaus",
    "wof:placetype":"venue"
},
  "geometry": {"coordinates":[7.745439,51.248417],"type":"Point"}
}