{
  "type": "Feature",
  "properties": {
    "iso:country":"DE",
    "sg:address":"Japanweg 16",
    "sg:city":"Bleicherode",
    "sg:phone":"+49 36338/64040",
    "sg:postcode":"99752",
    "sg:province":"Th\u00fcringen",
    "wof:name":"Gabriele Engelke",
    "wof:placetype":"venue"
},
  "geometry": {"coordinates":[10.559516,51.44516],"type":"Point"}
}