{
  "type": "Feature",
  "properties": {
    "iso:country":"DE",
    "sg:address":"Kirchwerder Landweg 380",
    "sg:city":"Hamburg",
    "sg:postcode":"21037",
    "sg:province":"Hamburg",
    "wof:name":"Solar Construction Nord Gmbh",
    "wof:placetype":"venue"
},
  "geometry": {"coordinates":[10.155049,53.429787],"type":"Point"}
}