{
  "type": "Feature",
  "properties": {
    "iso:country":"DE",
    "sg:address":"Zum Betzenberg 2",
    "sg:city":"Kaiserslautern",
    "sg:phone":"+49 631/17600",
    "sg:postcode":"67663",
    "sg:province":"Rheinland-Pfalz",
    "wof:name":"Vs Play-land Spielhallen Betriebs Gmbh",
    "wof:placetype":"venue"
},
  "geometry": {"coordinates":[7.771784,49.435394],"type":"Point"}
}