{
  "type": "Feature",
  "properties": {
    "iso:country":"DE",
    "sg:address":"Am L\u00f6wenberg 5",
    "sg:city":"Leupoldsgr\u00fcn",
    "sg:phone":"+49 9292/349",
    "sg:postcode":"95191",
    "sg:province":"Bayern",
    "wof:name":"H. Fischer",
    "wof:placetype":"venue"
},
  "geometry": {"coordinates":[11.7944154739,50.2872238159],"type":"Point"}
}