{
  "type": "Feature",
  "properties": {
    "iso:country":"DE",
    "sg:address":"Junkerstr. 84",
    "sg:city":"B\u00fcsingen",
    "sg:phone":"+49 4977/342320",
    "sg:postcode":"78266",
    "sg:province":"Baden-W\u00fcrttemberg",
    "wof:name":"Bezirkssparkasse Gottmadingen",
    "wof:placetype":"venue"
},
  "geometry": {"coordinates":[8.687595,47.696247],"type":"Point"}
}