{
  "type": "Feature",
  "properties": {
    "iso:country":"DE",
    "sg:address":"Heckenweg 27",
    "sg:city":"Castrop-Rauxel",
    "sg:phone":"+49 2367/302",
    "sg:postcode":"44577",
    "sg:province":"Nordrhein-Westfalen",
    "wof:name":"Alois Namyslo Bauschlosserei",
    "wof:placetype":"venue"
},
  "geometry": {"coordinates":[7.312201,51.608349],"type":"Point"}
}