{
  "type": "Feature",
  "properties": {
    "iso:country":"DE",
    "sg:address":"Volkmaroder Str. 16",
    "sg:city":"Braunschweig",
    "sg:postcode":"38104",
    "sg:province":"Niedersachsen",
    "wof:name":"Artbau Gmbh",
    "wof:placetype":"venue"
},
  "geometry": {"coordinates":[10.573445,52.288078],"type":"Point"}
}