{
  "type": "Feature",
  "properties": {
    "iso:country":"DE",
    "sg:address":"Mittenwalder Str. 3",
    "sg:city":"Wallgau",
    "sg:phone":"+49 8825/2021",
    "sg:postcode":"82499",
    "sg:province":"Bayern",
    "wof:name":"Hotel Garni Zunterer",
    "wof:placetype":"venue"
},
  "geometry": {"coordinates":[11.2821130753,47.5205497742],"type":"Point"}
}