{
  "type": "Feature",
  "properties": {
    "iso:country":"DE",
    "sg:address":"Dachinger Str. 7",
    "sg:city":"Moosthenning",
    "sg:phone":"+49 8731/9645",
    "sg:postcode":"84164",
    "sg:province":"Bayern",
    "wof:name":"Josef Kaindl",
    "wof:placetype":"venue"
},
  "geometry": {"coordinates":[12.5321359634,48.7063140869],"type":"Point"}
}