{
  "type": "Feature",
  "properties": {
    "iso:country":"DE",
    "sg:address":"Asternweg 11",
    "sg:city":"Bochum",
    "sg:phone":"+49 2327",
    "sg:postcode":"44869",
    "sg:province":"Nordrhein-Westfalen",
    "wof:name":"Industriebedarf A. Zimmermann",
    "wof:placetype":"venue"
},
  "geometry": {"coordinates":[7.162755,51.443382],"type":"Point"}
}