{
  "type": "Feature",
  "properties": {
    "iso:country":"DE",
    "sg:address":"Am Bahnhof 3",
    "sg:city":"Balve",
    "sg:phone":"+49 2375/91930",
    "sg:postcode":"58802",
    "sg:province":"Nordrhein-Westfalen",
    "wof:name":"Kalkwerk Gr\u00fcbeck Kg Heinrich Thorwesten",
    "wof:placetype":"venue"
},
  "geometry": {"coordinates":[7.862844,51.332134],"type":"Point"}
}