{
  "type": "Feature",
  "properties": {
    "iso:country":"DE",
    "sg:address":"Molkereistr. 1",
    "sg:city":"Nattheim",
    "sg:phone":"+49 7321/71807",
    "sg:postcode":"89564",
    "sg:province":"Baden-W\u00fcrttemberg",
    "wof:name":"Sozialstation",
    "wof:placetype":"venue"
},
  "geometry": {"coordinates":[10.240765,48.700249],"type":"Point"}
}