{
  "type": "Feature",
  "properties": {
    "iso:country":"DE",
    "sg:address":"Gardelegener Str. 40",
    "sg:city":"Salzwedel",
    "sg:phone":"+49 3901/423396",
    "sg:postcode":"29410",
    "sg:province":"Sachsen-Anhalt",
    "wof:name":"Uwe Walther",
    "wof:placetype":"venue"
},
  "geometry": {"coordinates":[11.164438,52.840549],"type":"Point"}
}