{
  "type": "Feature",
  "properties": {
    "iso:country":"DE",
    "sg:address":"Langewanneweg 145",
    "sg:city":"Hamm",
    "sg:phone":"+49 2381/51520",
    "sg:postcode":"59063",
    "sg:province":"Nordrhein-Westfalen",
    "wof:name":"Roadblock Promotion",
    "wof:placetype":"venue"
},
  "geometry": {"coordinates":[7.8222589493,51.6623382568],"type":"Point"}
}