{
  "type": "Feature",
  "properties": {
    "iso:country":"DE",
    "sg:address":"S\u00fcdring 92",
    "sg:city":"Stadtlohn",
    "sg:phone":"+49 2563/3431",
    "sg:postcode":"48703",
    "sg:province":"Nordrhein-Westfalen",
    "wof:name":"Wilhelm Tenbrink Gmbh",
    "wof:placetype":"venue"
},
  "geometry": {"coordinates":[6.91426,51.987835],"type":"Point"}
}