{
  "type": "Feature",
  "properties": {
    "iso:country":"DE",
    "sg:address":"Schmiedstr. 59",
    "sg:city":"Herzogenrath",
    "sg:phone":"+49 2406/3169",
    "sg:postcode":"52134",
    "sg:province":"Nordrhein-Westfalen",
    "wof:name":"Golden Sword",
    "wof:placetype":"venue"
},
  "geometry": {"coordinates":[6.113432,50.851257],"type":"Point"}
}