{
  "type": "Feature",
  "properties": {
    "iso:country":"DE",
    "sg:address":"Zum Erlenbusch 2",
    "sg:city":"M\u00fcnster",
    "sg:phone":"+49 251/615765",
    "sg:postcode":"48167",
    "sg:province":"Nordrhein-Westfalen",
    "wof:name":"Reinhold Dr\u00fcgem\u00f6ller",
    "wof:placetype":"venue"
},
  "geometry": {"coordinates":[7.6741070747,51.9258384705],"type":"Point"}
}