{
  "type": "Feature",
  "properties": {
    "iso:country":"DE",
    "sg:address":"An der Ilse 16",
    "sg:city":"Osterwieck",
    "sg:phone":"+49 39421/73591",
    "sg:postcode":"38835",
    "sg:province":"Sachsen-Anhalt",
    "wof:name":"I. Marek",
    "wof:placetype":"venue"
},
  "geometry": {"coordinates":[10.7149372101,51.9660072327],"type":"Point"}
}