{
  "type": "Feature",
  "properties": {
    "iso:country":"DE",
    "sg:address":"Bahnhofstr. 43",
    "sg:city":"Bodenmais",
    "sg:phone":"+49 9924/479",
    "sg:postcode":"94249",
    "sg:province":"Bayern",
    "wof:name":"Cafe Wilderstuben",
    "wof:placetype":"venue"
},
  "geometry": {"coordinates":[13.103165,49.069252],"type":"Point"}
}