{
  "type": "Feature",
  "properties": {
    "iso:country":"DE",
    "sg:address":"Schneidem\u00fchler Str. 18",
    "sg:city":"Hohenlockstedt",
    "sg:phone":"+49 4826/976",
    "sg:postcode":"25551",
    "sg:province":"Schleswig-Holstein",
    "wof:name":"Dr. Dietrich Jacobs Tierarzt",
    "wof:placetype":"venue"
},
  "geometry": {"coordinates":[9.6186590195,53.9726753235],"type":"Point"}
}