{
  "type": "Feature",
  "properties": {
    "iso:country":"DE",
    "sg:address":"Sodentalstr. 148",
    "sg:city":"Sulzbach",
    "sg:phone":"+49 6028/1351",
    "sg:postcode":"63834",
    "sg:province":"Bayern",
    "wof:name":"Ellmar Schmitt",
    "wof:placetype":"venue"
},
  "geometry": {"coordinates":[9.219991,49.927395],"type":"Point"}
}