{
  "type": "Feature",
  "properties": {
    "iso:country":"DE",
    "sg:address":"Zum Kn\u00f6ll 18",
    "sg:city":"Gnutz",
    "sg:phone":"+49 4392/1691",
    "sg:postcode":"24622",
    "sg:province":"Schleswig-Holstein",
    "wof:name":"Hans Rohwedder",
    "wof:placetype":"venue"
},
  "geometry": {"coordinates":[9.824611,54.138508],"type":"Point"}
}