{
  "type": "Feature",
  "properties": {
    "iso:country":"DE",
    "sg:address":"Ehrenfriedstr. 16",
    "sg:city":"Vellberg",
    "sg:phone":"+49 7907/7187",
    "sg:postcode":"74541",
    "sg:province":"Baden-W\u00fcrttemberg",
    "wof:name":"E. Freisinger Steuerberaterin",
    "wof:placetype":"venue"
},
  "geometry": {"coordinates":[9.8731546402,49.0828704834],"type":"Point"}
}