{
  "type": "Feature",
  "properties": {
    "iso:country":"DE",
    "sg:address":"Im Ziegelfeld 14",
    "sg:city":"W\u00f6rth",
    "sg:phone":"+49 6340/919052",
    "sg:postcode":"76744",
    "sg:province":"Rheinland-Pfalz",
    "wof:name":"Kegel Industrievertretungen Gmbh",
    "wof:placetype":"venue"
},
  "geometry": {"coordinates":[8.0699548721,49.0640830994],"type":"Point"}
}