{
  "type": "Feature",
  "properties": {
    "iso:country":"DE",
    "sg:address":"Dohne 72",
    "sg:city":"M\u00fclheim",
    "sg:phone":"+49 208/381797",
    "sg:postcode":"45468",
    "sg:province":"Nordrhein-Westfalen",
    "wof:name":"M. Kiefel Ingenieur",
    "wof:placetype":"venue"
},
  "geometry": {"coordinates":[6.8771381378,51.416267395],"type":"Point"}
}