{
  "type": "Feature",
  "properties": {
    "iso:country":"DE",
    "sg:address":"Marienburger Str. 71",
    "sg:city":"Hildesheim",
    "sg:phone":"+49 5121/867578",
    "sg:postcode":"31141",
    "sg:province":"Niedersachsen",
    "wof:name":"Gr\u00fcnkern Naturkost",
    "wof:placetype":"venue"
},
  "geometry": {"coordinates":[9.9650068283,52.139087677],"type":"Point"}
}