{
  "type": "Feature",
  "properties": {
    "iso:country":"DE",
    "sg:address":"Hellenweg 13",
    "sg:city":"Fritzlar",
    "sg:phone":"+49 5622/2291",
    "sg:postcode":"34560",
    "sg:province":"Hessen",
    "wof:name":"H. Clobes",
    "wof:placetype":"venue"
},
  "geometry": {"coordinates":[9.27022,51.136658],"type":"Point"}
}