{
  "type": "Feature",
  "properties": {
    "iso:country":"DE",
    "sg:address":"Martinstr. 2",
    "sg:city":"Duisburg",
    "sg:phone":"+49 2065/21875",
    "sg:postcode":"47228",
    "sg:province":"Nordrhein-Westfalen",
    "wof:name":"Georg Wirth",
    "wof:placetype":"venue"
},
  "geometry": {"coordinates":[6.7006959915,51.4045524597],"type":"Point"}
}