{
  "type": "Feature",
  "properties": {
    "iso:country":"DE",
    "sg:address":"Bischof-Hermann-Str. 3",
    "sg:city":"Heek",
    "sg:phone":"+49 2568/1075",
    "sg:postcode":"48619",
    "sg:province":"Nordrhein-Westfalen",
    "wof:name":"Felix B\u00f6cker",
    "wof:placetype":"venue"
},
  "geometry": {"coordinates":[7.1049442291,52.1319961548],"type":"Point"}
}