{
  "type": "Feature",
  "properties": {
    "iso:country":"DE",
    "sg:address":"Pfalzblick 2",
    "sg:city":"Traisen",
    "sg:phone":"+49 671/31339",
    "sg:postcode":"55595",
    "sg:province":"Rheinland-Pfalz",
    "wof:name":"P. Leibig \u00dcbersetzungsb\u00fcro",
    "wof:placetype":"venue"
},
  "geometry": {"coordinates":[7.81689,49.818901],"type":"Point"}
}