{
  "type": "Feature",
  "properties": {
    "iso:country":"DE",
    "sg:address":"Pforzheimer Str. 186",
    "sg:city":"Ettlingen",
    "sg:phone":"+49 7243/57840",
    "sg:postcode":"76275",
    "sg:province":"Baden-W\u00fcrttemberg",
    "wof:name":"Printz Gmbh",
    "wof:placetype":"venue"
},
  "geometry": {"coordinates":[8.4475870132,48.931224823],"type":"Point"}
}