{
  "type": "Feature",
  "properties": {
    "iso:country":"DE",
    "sg:address":"Schmittmannstr. 45",
    "sg:city":"Dernau",
    "sg:phone":"+49 2643/1588",
    "sg:postcode":"53507",
    "sg:province":"Rheinland-Pfalz",
    "wof:name":"Helmut Fisang",
    "wof:placetype":"venue"
},
  "geometry": {"coordinates":[7.0490608215,50.5349502563],"type":"Point"}
}