{
  "type": "Feature",
  "properties": {
    "iso:country":"DE",
    "sg:address":"Burgstr. 60",
    "sg:city":"Halle",
    "sg:phone":"+49 345/5232620",
    "sg:postcode":"06114",
    "sg:province":"Sachsen-Anhalt",
    "wof:name":"Berndt Schmidt",
    "wof:placetype":"venue"
},
  "geometry": {"coordinates":[11.954669,51.499931],"type":"Point"}
}