{
  "type": "Feature",
  "properties": {
    "iso:country":"DE",
    "sg:address":"Lichtenhaidestr. 3c",
    "sg:city":"Bamberg",
    "sg:phone":"+49 951/96260",
    "sg:postcode":"96052",
    "sg:province":"Bayern",
    "wof:name":"B\u00f6hnlein Gmbh",
    "wof:placetype":"venue"
},
  "geometry": {"coordinates":[10.88265,49.903999],"type":"Point"}
}