{
  "type": "Feature",
  "properties": {
    "iso:country":"DE",
    "sg:address":"Am Vo\u00dfberg 21",
    "sg:city":"Oldenburg",
    "sg:phone":"+49 4361/7004",
    "sg:postcode":"23758",
    "sg:province":"Schleswig-Holstein",
    "wof:name":"Feldhoff-druck Gmbh",
    "wof:placetype":"venue"
},
  "geometry": {"coordinates":[-85.206238,39.339813],"type":"Point"}
}