{
  "type": "Feature",
  "properties": {
    "iso:country":"DE",
    "sg:address":"R\u00f6merstr. 22",
    "sg:city":"Zwickau",
    "sg:phone":"+49 375/241417",
    "sg:postcode":"08056",
    "sg:province":"Sachsen",
    "wof:name":"Mca Immobilien Gmbh",
    "wof:placetype":"venue"
},
  "geometry": {"coordinates":[12.4932117462,50.7226371765],"type":"Point"}
}