{
  "type": "Feature",
  "properties": {
    "iso:country":"DE",
    "sg:address":"Grosse Str. 90-92",
    "sg:city":"Osnabr\u00fcck",
    "sg:phone":"+49 4954/124174",
    "sg:postcode":"49074",
    "sg:province":"Niedersachsen",
    "wof:name":"Noris Bank Gmbh",
    "wof:placetype":"venue"
},
  "geometry": {"coordinates":[8.04808,52.273277],"type":"Point"}
}