{
  "type": "Feature",
  "properties": {
    "iso:country":"DE",
    "sg:address":"Im Thal 1",
    "sg:city":"Penzberg",
    "sg:phone":"+49 8856/935326",
    "sg:postcode":"82377",
    "sg:province":"Bayern",
    "wof:name":"Duo-dental Gmbh",
    "wof:placetype":"venue"
},
  "geometry": {"coordinates":[11.377578,47.756088],"type":"Point"}
}