{
  "type": "Feature",
  "properties": {
    "iso:country":"DE",
    "sg:address":"Uthmannstr. 15",
    "sg:city":"Zwickau",
    "sg:phone":"+49 375/785644",
    "sg:postcode":"08064",
    "sg:province":"Sachsen",
    "wof:name":"Gerd Noll",
    "wof:placetype":"venue"
},
  "geometry": {"coordinates":[12.4788017273,50.6758003235],"type":"Point"}
}