{
  "type": "Feature",
  "properties": {
    "iso:country":"DE",
    "sg:address":"Bochumer Str. 30",
    "sg:city":"Essen",
    "sg:phone":"+49 201/519301",
    "sg:postcode":"45276",
    "sg:province":"Nordrhein-Westfalen",
    "wof:name":"U. Fluck",
    "wof:placetype":"venue"
},
  "geometry": {"coordinates":[7.077959,51.446152],"type":"Point"}
}