{
  "type": "Feature",
  "properties": {
    "iso:country":"DE",
    "sg:address":"Von-Axen-Str. 8",
    "sg:city":"Hamburg",
    "sg:postcode":"22083",
    "sg:province":"Hamburg",
    "wof:name":"Hindenburg-online Shop",
    "wof:placetype":"venue"
},
  "geometry": {"coordinates":[10.024943,53.580166],"type":"Point"}
}