{
  "type": "Feature",
  "properties": {
    "iso:country":"DE",
    "sg:address":"Pfaffenhofener Str. 5",
    "sg:city":"Schrobenhausen",
    "sg:phone":"+49 8252/2445",
    "sg:postcode":"86529",
    "sg:province":"Bayern",
    "wof:name":"Lindenkeller",
    "wof:placetype":"venue"
},
  "geometry": {"coordinates":[11.2714281082,48.5551185608],"type":"Point"}
}