{
  "type": "Feature",
  "properties": {
    "iso:country":"DE",
    "sg:address":"Koogstr. 3",
    "sg:city":"Brunsb\u00fcttel",
    "sg:phone":"+49 4852/6464",
    "sg:postcode":"25541",
    "sg:province":"Schleswig-Holstein",
    "wof:name":"Gothaer Versicherungsbank Vvag",
    "wof:placetype":"venue"
},
  "geometry": {"coordinates":[9.1291761398,53.8979225159],"type":"Point"}
}