{
  "type": "Feature",
  "properties": {
    "iso:country":"DE",
    "sg:address":"Am Sportplatz 5",
    "sg:city":"Vienenburg",
    "sg:phone":"+49 5324/3307",
    "sg:postcode":"38690",
    "sg:province":"Niedersachsen",
    "wof:name":"Wilhelm Hartge",
    "wof:placetype":"venue"
},
  "geometry": {"coordinates":[10.598161,51.928219],"type":"Point"}
}