{
  "type": "Feature",
  "properties": {
    "iso:country":"DE",
    "sg:address":"Viehofer Str. 62",
    "sg:city":"Essen",
    "sg:phone":"+49 201/223651",
    "sg:postcode":"45127",
    "sg:province":"Nordrhein-Westfalen",
    "wof:name":"Leuchten-kaiser August Kaiser",
    "wof:placetype":"venue"
},
  "geometry": {"coordinates":[7.013937,51.460529],"type":"Point"}
}