{
  "type": "Feature",
  "properties": {
    "iso:country":"DE",
    "sg:address":"Untere Str. 10",
    "sg:city":"F\u00fcrth",
    "sg:postcode":"90768",
    "sg:province":"Bayern",
    "wof:name":"Maag Verwaltungs- Und Beteiligungs-gmbh",
    "wof:placetype":"venue"
},
  "geometry": {"coordinates":[10.9767999649,49.4623260498],"type":"Point"}
}