{
  "type": "Feature",
  "properties": {
    "iso:country":"DE",
    "sg:address":"Braunschweiger Str. 19",
    "sg:city":"Schw\u00fclper",
    "sg:phone":"+49 5303/4173",
    "sg:postcode":"38179",
    "sg:province":"Niedersachsen",
    "wof:name":"Karl Hoyer",
    "wof:placetype":"venue"
},
  "geometry": {"coordinates":[10.436473,52.350502],"type":"Point"}
}