{
  "type": "Feature",
  "properties": {
    "iso:country":"DE",
    "sg:address":"Waldstr. 32",
    "sg:city":"Stutensee",
    "sg:phone":"+49 721/683258",
    "sg:postcode":"76297",
    "sg:province":"Baden-W\u00fcrttemberg",
    "wof:name":"Kosmetik F\u00fcr Sie Und Ihn",
    "wof:placetype":"venue"
},
  "geometry": {"coordinates":[8.465249,49.047436],"type":"Point"}
}