{
  "type": "Feature",
  "properties": {
    "iso:country":"DE",
    "sg:address":"Wallstr. 20",
    "sg:city":"M\u00fclheim",
    "sg:phone":"+49 208/470107",
    "sg:postcode":"45468",
    "sg:province":"Nordrhein-Westfalen",
    "wof:name":"Mengede Verm\u00f6gens- Verwaltungs-gmbh",
    "wof:placetype":"venue"
},
  "geometry": {"coordinates":[6.8799328804,51.4284477234],"type":"Point"}
}