{
  "type": "Feature",
  "properties": {
    "iso:country":"DE",
    "sg:address":"Sterkenhofweg 9",
    "sg:city":"Krefeld",
    "sg:phone":"+49 2151/396205",
    "sg:postcode":"47807",
    "sg:province":"Nordrhein-Westfalen",
    "wof:name":"Schmelzer Gmbh",
    "wof:placetype":"venue"
},
  "geometry": {"coordinates":[6.564291954,51.3015670776],"type":"Point"}
}