{
  "type": "Feature",
  "properties": {
    "iso:country":"DE",
    "sg:address":"Nr. 43a",
    "sg:city":"Gro\u00dfobringen",
    "sg:postcode":"99439",
    "sg:province":"Th\u00fcringen",
    "wof:name":"H. Barthel",
    "wof:placetype":"venue"
},
  "geometry": {"coordinates":[11.24356,51.062061],"type":"Point"}
}