{
  "type": "Feature",
  "properties": {
    "iso:country":"DE",
    "sg:address":"Alte Schulstr. 1",
    "sg:city":"Bad Nauheim",
    "sg:phone":"+49 6032/86001",
    "sg:postcode":"61231",
    "sg:province":"Hessen",
    "wof:name":"Rosenmudeum Steinfurth",
    "wof:placetype":"venue"
},
  "geometry": {"coordinates":[8.747077,50.400227],"type":"Point"}
}