{
  "type": "Feature",
  "properties": {
    "iso:country":"DE",
    "sg:address":"Osterburgstr. 21",
    "sg:city":"Rinteln",
    "sg:phone":"+49 5152/2696",
    "sg:postcode":"31737",
    "sg:province":"Niedersachsen",
    "wof:name":"Pension H. Bredemeier",
    "wof:placetype":"venue"
},
  "geometry": {"coordinates":[9.1706609726,52.2045402527],"type":"Point"}
}