{
  "type": "Feature",
  "properties": {
    "iso:country":"DE",
    "sg:address":"Daimler-Str. 18",
    "sg:city":"Elmshorn",
    "sg:phone":"+49 4941/2145720",
    "sg:postcode":"25335",
    "sg:province":"Schleswig-Holstein",
    "wof:name":"Hygan Chemie & Service Gmbh & Co Kg",
    "wof:placetype":"venue"
},
  "geometry": {"coordinates":[9.690595,53.743916],"type":"Point"}
}