{
  "type": "Feature",
  "properties": {
    "iso:country":"DE",
    "sg:address":"Dr.-Wirtz-Str. 27",
    "sg:city":"Much",
    "sg:phone":"+49 2245/8601",
    "sg:postcode":"53804",
    "sg:province":"Nordrhein-Westfalen",
    "wof:name":"Auditec Gesellschaft F\u00fcr Pr\u00fcf- Und Me\u00dftechnik Gmbh",
    "wof:placetype":"venue"
},
  "geometry": {"coordinates":[7.4062671661,50.9090766907],"type":"Point"}
}