{
  "type": "Feature",
  "properties": {
    "iso:country":"DE",
    "sg:address":"Oberbruchstr. 212",
    "sg:city":"Krefeld",
    "sg:phone":"+49 2151/301553",
    "sg:postcode":"47807",
    "sg:province":"Nordrhein-Westfalen",
    "wof:name":"Heinrich Hannen",
    "wof:placetype":"venue"
},
  "geometry": {"coordinates":[6.595681,51.310616],"type":"Point"}
}