{
  "type": "Feature",
  "properties": {
    "iso:country":"DE",
    "sg:address":"Scheffelstr. 4 a",
    "sg:city":"Ettlingen",
    "sg:phone":"+49 7243/30650",
    "sg:postcode":"76275",
    "sg:province":"Baden-W\u00fcrttemberg",
    "wof:name":"Terra Viva-reisen Gmbh",
    "wof:placetype":"venue"
},
  "geometry": {"coordinates":[8.4075336456,48.943813324],"type":"Point"}
}