{
  "type": "Feature",
  "properties": {
    "iso:country":"DE",
    "sg:address":"Ossenpa\u00df 6",
    "sg:city":"Kevelaer",
    "sg:phone":"+49 2832/4456",
    "sg:postcode":"47623",
    "sg:province":"Nordrhein-Westfalen",
    "wof:name":"Otto Tenh\u00e4f Kg",
    "wof:placetype":"venue"
},
  "geometry": {"coordinates":[6.261718,51.584312],"type":"Point"}
}