{
  "type": "Feature",
  "properties": {
    "iso:country":"DE",
    "sg:address":"Hahnweg 75",
    "sg:city":"Coburg",
    "sg:phone":"+49 9561/94421",
    "sg:postcode":"96450",
    "sg:province":"Bayern",
    "wof:name":"Die Kartoffel",
    "wof:placetype":"venue"
},
  "geometry": {"coordinates":[10.974656105,50.268081665],"type":"Point"}
}