{
  "type": "Feature",
  "properties": {
    "iso:country":"DE",
    "sg:address":"Marktplatz 21",
    "sg:city":"T\u00e4nnesberg",
    "sg:phone":"+49 9655/317",
    "sg:postcode":"92723",
    "sg:province":"Bayern",
    "wof:name":"Felsenkeller",
    "wof:placetype":"venue"
},
  "geometry": {"coordinates":[12.3257112503,49.5318260193],"type":"Point"}
}