{
  "type": "Feature",
  "properties": {
    "iso:country":"DE",
    "sg:address":"72070",
    "sg:city":"T\u00fcbingen",
    "sg:phone":"+49 7071/78516",
    "sg:postcode":"72070",
    "sg:province":"Baden-W\u00fcrttemberg",
    "wof:name":"Http://www.stempel-online-bestellen.de",
    "wof:placetype":"venue"
},
  "geometry": {"coordinates":[9.0112695694,48.5205192566],"type":"Point"}
}