{
  "type": "Feature",
  "properties": {
    "iso:country":"DE",
    "sg:address":"Burgwartstr. 146",
    "sg:city":"Freital",
    "sg:postcode":"01705",
    "sg:province":"Sachsen",
    "wof:name":"M. Wansner",
    "wof:placetype":"venue"
},
  "geometry": {"coordinates":[13.643148,51.018997],"type":"Point"}
}