{
  "type": "Feature",
  "properties": {
    "iso:country":"DE",
    "sg:address":"Bartelbergweg 1",
    "sg:city":"Kaufbeuren",
    "sg:postcode":"87600",
    "sg:province":"Bayern",
    "wof:name":"Dogurt Neuheitenbertriebs Gmbh",
    "wof:placetype":"venue"
},
  "geometry": {"coordinates":[10.627381,47.905506],"type":"Point"}
}