{
  "type": "Feature",
  "properties": {
    "iso:country":"DE",
    "sg:address":"Mittelh\u00e4user Str 76",
    "sg:city":"Erfurt",
    "sg:phone":"+49 361/734923",
    "sg:postcode":"99089",
    "sg:province":"Th\u00fcringen",
    "wof:name":"R&r Druck Gbr",
    "wof:placetype":"venue"
},
  "geometry": {"coordinates":[11.0196075439,51.0071105957],"type":"Point"}
}