{
  "type": "Feature",
  "properties": {
    "iso:country":"DE",
    "sg:address":"Leipziger Str. 36",
    "sg:city":"Waldkappel",
    "sg:phone":"+49 5656/4023",
    "sg:postcode":"37284",
    "sg:province":"Hessen",
    "wof:name":"Michaela Karges Architektin",
    "wof:placetype":"venue"
},
  "geometry": {"coordinates":[9.8769,51.143951],"type":"Point"}
}