{
  "type": "Feature",
  "properties": {
    "iso:country":"DE",
    "sg:address":"Hauptstr. 12",
    "sg:city":"Kroppen",
    "sg:phone":"+49 35755/51194",
    "sg:postcode":"01945",
    "sg:province":"Brandenburg",
    "wof:name":"Klaus H\u00f6hnel",
    "wof:placetype":"venue"
},
  "geometry": {"coordinates":[13.7927742004,51.3841133118],"type":"Point"}
}