{
  "type": "Feature",
  "properties": {
    "iso:country":"DE",
    "sg:address":"Billbrookdeich 184",
    "sg:city":"Hamburg",
    "sg:phone":"+49 40/7314201",
    "sg:postcode":"22113",
    "sg:province":"Schleswig-Holstein",
    "wof:name":"Ring Transport H. J. Huntscha",
    "wof:placetype":"venue"
},
  "geometry": {"coordinates":[10.1027040482,53.5350646973],"type":"Point"}
}