{
  "type": "Feature",
  "properties": {
    "iso:country":"DE",
    "sg:address":"Bahnhofplatz 1",
    "sg:city":"Dachau",
    "sg:phone":"+49 8131/72613",
    "sg:postcode":"85221",
    "sg:province":"Bayern",
    "wof:name":"Deutsche Bahn Ag",
    "wof:placetype":"venue"
},
  "geometry": {"coordinates":[11.4437227249,48.2548980713],"type":"Point"}
}