{
  "type": "Feature",
  "properties": {
    "iso:country":"DE",
    "sg:address":"Lindenweg 7",
    "sg:city":"Sehnde",
    "sg:phone":"+49 5138/608280",
    "sg:postcode":"31319",
    "sg:province":"Niedersachsen",
    "wof:name":"J. Rahe Tief- Und Rohrleitungsbau",
    "wof:placetype":"venue"
},
  "geometry": {"coordinates":[9.972530365,52.3104362488],"type":"Point"}
}