{
  "type": "Feature",
  "properties": {
    "iso:country":"DE",
    "sg:address":"Bussardweg 13",
    "sg:city":"Herbrechtingen",
    "sg:phone":"+49 7324/3267",
    "sg:postcode":"89542",
    "sg:province":"Baden-W\u00fcrttemberg",
    "wof:name":"Karl Maier Architekt",
    "wof:placetype":"venue"
},
  "geometry": {"coordinates":[10.175451,48.624916],"type":"Point"}
}