{
  "type": "Feature",
  "properties": {
    "iso:country":"DE",
    "sg:address":"Roetenweg 5",
    "sg:city":"Seevetal",
    "sg:phone":"+49 4105/3274",
    "sg:postcode":"21217",
    "sg:province":"Niedersachsen",
    "wof:name":"Hillmann Erschlie\u00dfungsbau",
    "wof:placetype":"venue"
},
  "geometry": {"coordinates":[10.0199508667,53.4055938721],"type":"Point"}
}