{
  "type": "Feature",
  "properties": {
    "iso:country":"DE",
    "sg:address":"Sperbersloher Str. 52",
    "sg:city":"Schwanstetten",
    "sg:phone":"+49 9170/94930",
    "sg:postcode":"90596",
    "sg:province":"Bayern",
    "wof:name":"Versicherungsvermittlung Wilfried Schilling",
    "wof:placetype":"venue"
},
  "geometry": {"coordinates":[11.1246519089,49.3113670349],"type":"Point"}
}