{
  "type": "Feature",
  "properties": {
    "iso:country":"DE",
    "sg:address":"Am M\u00fcckenst\u00fcck 7",
    "sg:city":"Kehrig",
    "sg:phone":"+49 2651/3738",
    "sg:postcode":"56729",
    "sg:province":"Rheinland-Pfalz",
    "wof:name":"Fuhrmann Gmbh",
    "wof:placetype":"venue"
},
  "geometry": {"coordinates":[7.22002,50.280025],"type":"Point"}
}