{
  "type": "Feature",
  "properties": {
    "iso:country":"DE",
    "sg:address":"Lauterbach",
    "sg:city":"Buttenwiesen",
    "sg:phone":"+49 8274/1224",
    "sg:postcode":"86647",
    "sg:province":"Bayern",
    "wof:name":"M. Und S. Hillenbrand",
    "wof:placetype":"venue"
},
  "geometry": {"coordinates":[10.7467403412,48.6234512329],"type":"Point"}
}