{
  "type": "Feature",
  "properties": {
    "iso:country":"DE",
    "sg:address":"Markt 4",
    "sg:city":"Stolpen",
    "sg:phone":"+49 35973/24188",
    "sg:postcode":"01833",
    "sg:province":"Sachsen",
    "wof:name":"A. W. I. Gastst\u00e4ttenbetriebs- Und Verwaltungs Gmbh",
    "wof:placetype":"venue"
},
  "geometry": {"coordinates":[14.0831298828,51.0495986938],"type":"Point"}
}