{
  "type": "Feature",
  "properties": {
    "iso:country":"DE",
    "sg:address":"Kirchhellener Str. 1",
    "sg:city":"Schermbeck",
    "sg:phone":"+49 2362/41132",
    "sg:postcode":"46514",
    "sg:province":"Nordrhein-Westfalen",
    "wof:name":"Landhaus Spickermann",
    "wof:placetype":"venue"
},
  "geometry": {"coordinates":[6.8961172104,51.6444396973],"type":"Point"}
}