{
  "type": "Feature",
  "properties": {
    "iso:country":"DE",
    "sg:address":"Bert-Brecht-Str. 38",
    "sg:city":"Achern",
    "sg:phone":"+49 7841/668220",
    "sg:postcode":"77855",
    "sg:province":"Baden-W\u00fcrttemberg",
    "wof:name":"S\u00fcma Gmbh",
    "wof:placetype":"venue"
},
  "geometry": {"coordinates":[8.0852718353,48.6315879822],"type":"Point"}
}