{
  "type": "Feature",
  "properties": {
    "iso:country":"DE",
    "sg:address":"Neuweselstr. 39",
    "sg:city":"Essen",
    "sg:phone":"+49 201/682330",
    "sg:postcode":"45355",
    "sg:province":"Nordrhein-Westfalen",
    "wof:name":"Hans-peter Dracke",
    "wof:placetype":"venue"
},
  "geometry": {"coordinates":[6.93809,51.471184],"type":"Point"}
}