{
  "type": "Feature",
  "properties": {
    "iso:country":"DE",
    "sg:address":"Heintgesweg 31",
    "sg:city":"M\u00f6nchengladbach",
    "sg:phone":"+49 2166/31200",
    "sg:postcode":"41239",
    "sg:province":"Nordrhein-Westfalen",
    "wof:name":"Kaiser Industrie Elektronik Gmbh",
    "wof:placetype":"venue"
},
  "geometry": {"coordinates":[6.4226841927,51.1645011902],"type":"Point"}
}