{
  "type": "Feature",
  "properties": {
    "iso:country":"DE",
    "sg:address":"Karlsruher Str. 2",
    "sg:city":"Ketsch",
    "sg:postcode":"68775",
    "sg:province":"Baden-W\u00fcrttemberg",
    "wof:name":"Born Gmbh",
    "wof:placetype":"venue"
},
  "geometry": {"coordinates":[8.53482,49.3605],"type":"Point"}
}