{
  "type": "Feature",
  "properties": {
    "iso:country":"DE",
    "sg:address":"Obere Dorfstr. 72",
    "sg:city":"Henfst\u00e4dt",
    "sg:phone":"+49 36873/67420",
    "sg:postcode":"98660",
    "sg:province":"Th\u00fcringen",
    "wof:name":"Hotel Siegfried Vollmar",
    "wof:placetype":"venue"
},
  "geometry": {"coordinates":[10.5862216949,50.5153388977],"type":"Point"}
}