{
  "type": "Feature",
  "properties": {
    "iso:country":"DE",
    "sg:address":"Matthias-Claudius-Weg 3 d",
    "sg:city":"Bad Segeberg",
    "sg:phone":"+49 4551/91744",
    "sg:postcode":"23795",
    "sg:province":"Schleswig-Holstein",
    "wof:name":"Karin Rieper Heilpraktikerin",
    "wof:placetype":"venue"
},
  "geometry": {"coordinates":[10.2956552505,53.9316673279],"type":"Point"}
}