{
  "type": "Feature",
  "properties": {
    "iso:country":"DE",
    "sg:address":"Alliger Weg",
    "sg:city":"Kruft",
    "sg:phone":"+49 2652/92840",
    "sg:postcode":"56642",
    "sg:province":"Rheinland-Pfalz",
    "wof:name":"Jungbluth Baumaschinen Gmbh",
    "wof:placetype":"venue"
},
  "geometry": {"coordinates":[7.331776,50.389153],"type":"Point"}
}