{
  "type": "Feature",
  "properties": {
    "iso:country":"DE",
    "sg:address":"Asbacher Str.",
    "sg:city":"Eitorf",
    "sg:phone":"+49 2243/80697",
    "sg:postcode":"53783",
    "sg:province":"Nordrhein-Westfalen",
    "wof:name":"Galerie Icontro",
    "wof:placetype":"venue"
},
  "geometry": {"coordinates":[7.44781,50.767078],"type":"Point"}
}