{
  "type": "Feature",
  "properties": {
    "iso:country":"DE",
    "sg:address":"Bl\u00fccherstr. 5E",
    "sg:city":"Berlin",
    "sg:phone":"+49 30",
    "sg:postcode":"12207",
    "sg:province":"Berlin",
    "wof:name":"G\u00fcnther Immobilien",
    "wof:placetype":"venue"
},
  "geometry": {"coordinates":[13.3095541,52.4153442383],"type":"Point"}
}