{
  "type": "Feature",
  "properties": {
    "iso:country":"DE",
    "sg:address":"Am Bierb\u00e4umchen 7 a",
    "sg:city":"Welver",
    "sg:phone":"+49 2384/3391",
    "sg:postcode":"59514",
    "sg:province":"Nordrhein-Westfalen",
    "wof:name":"Schmalenbach Und Sohn Abfallverwertungs Gmbh",
    "wof:placetype":"venue"
},
  "geometry": {"coordinates":[7.929827,51.606129],"type":"Point"}
}