{
  "type": "Feature",
  "properties": {
    "iso:country":"DE",
    "sg:address":"Regensburger Str. 6",
    "sg:city":"Berlin",
    "sg:phone":"+49 30/2118262",
    "sg:postcode":"10777",
    "sg:province":"Berlin",
    "wof:name":"Soft Kontor Raschke Gmbh",
    "wof:placetype":"venue"
},
  "geometry": {"coordinates":[13.3381462097,52.4960250854],"type":"Point"}
}