{
  "type": "Feature",
  "properties": {
    "iso:country":"DE",
    "sg:address":"Hattenheimer Str. 9b",
    "sg:city":"Ingelheim",
    "sg:phone":"+49 6132/86476",
    "sg:postcode":"55218",
    "sg:province":"Rheinland-Pfalz",
    "wof:name":"Akademie Modernes Management D. Kropshofer E. K.",
    "wof:placetype":"venue"
},
  "geometry": {"coordinates":[8.055425,49.974766],"type":"Point"}
}