{
  "type": "Feature",
  "properties": {
    "iso:country":"DE",
    "sg:address":"Wolkensteiner Str. 8a",
    "sg:city":"Lengefeld",
    "sg:phone":"+49 37367/2897",
    "sg:postcode":"09514",
    "sg:province":"Sachsen",
    "wof:name":"Waldbau Tilo Budde Gmbh",
    "wof:placetype":"venue"
},
  "geometry": {"coordinates":[13.1905622482,50.7184295654],"type":"Point"}
}