{
  "type": "Feature",
  "properties": {
    "iso:country":"DE",
    "sg:address":"Pascalstr. 26",
    "sg:city":"Aachen",
    "sg:postcode":"52076",
    "sg:province":"Nordrhein-Westfalen",
    "wof:name":"Hehl Datentechnik Ag",
    "wof:placetype":"venue"
},
  "geometry": {"coordinates":[6.1443128586,50.7133407593],"type":"Point"}
}