{
  "type": "Feature",
  "properties": {
    "iso:country":"DE",
    "sg:address":"In den Wulferten 2",
    "sg:city":"Welver",
    "sg:phone":"+49 2384/5542",
    "sg:postcode":"59514",
    "sg:province":"Nordrhein-Westfalen",
    "wof:name":"Urlaub In G\u00f6rgen \u00b4s Ferienhaus In Norden-norddeich",
    "wof:placetype":"venue"
},
  "geometry": {"coordinates":[7.949368,51.62249],"type":"Point"}
}