{
  "type": "Feature",
  "properties": {
    "iso:country":"DE",
    "sg:address":"Nienstedt 25",
    "sg:city":"Bassum",
    "sg:phone":"+49 4245/312",
    "sg:postcode":"27211",
    "sg:province":"Niedersachsen",
    "wof:name":"I. Feldermann",
    "wof:placetype":"venue"
},
  "geometry": {"coordinates":[8.769577,52.790207],"type":"Point"}
}