{
  "type": "Feature",
  "properties": {
    "iso:country":"DE",
    "sg:address":"Stedter Weg 13",
    "sg:city":"Bad Homburg",
    "sg:postcode":"61350",
    "sg:province":"Hessen",
    "wof:name":"Gp Klimatechnik Gmbh",
    "wof:placetype":"venue"
},
  "geometry": {"coordinates":[8.6048259735,50.2397422791],"type":"Point"}
}