{
  "type": "Feature",
  "properties": {
    "iso:country":"DE",
    "sg:address":"Reiterweg 1",
    "sg:city":"Ganderkesee",
    "sg:phone":"+49 4223/3012",
    "sg:postcode":"27777",
    "sg:province":"Niedersachsen",
    "wof:name":"Zur Tr\u00e4nke Elfriede Kropp",
    "wof:placetype":"venue"
},
  "geometry": {"coordinates":[8.5086803436,53.1042480469],"type":"Point"}
}