{
  "type": "Feature",
  "properties": {
    "iso:country":"DE",
    "sg:address":"Blenderweg 11",
    "sg:city":"Wiggensbach",
    "sg:phone":"+49 8370/97448",
    "sg:postcode":"87487",
    "sg:province":"Bayern",
    "wof:name":"Christl & Seeler Consulting Gmbh",
    "wof:placetype":"venue"
},
  "geometry": {"coordinates":[10.230689,47.743416],"type":"Point"}
}