{
  "type": "Feature",
  "properties": {
    "iso:country":"DE",
    "sg:address":"Schulstr. 1",
    "sg:city":"Beverstedt",
    "sg:phone":"+49 4747/872922",
    "sg:postcode":"27616",
    "sg:province":"Niedersachsen",
    "wof:name":"Elke Faubel Ergotherapeutsche Praxis",
    "wof:placetype":"venue"
},
  "geometry": {"coordinates":[8.817909,53.435509],"type":"Point"}
}