{
  "type": "Feature",
  "properties": {
    "iso:country":"DE",
    "sg:address":"Oetingerstr. 19",
    "sg:city":"G\u00f6ppingen",
    "sg:phone":"+49 7161/23775",
    "sg:postcode":"73033",
    "sg:province":"Baden-W\u00fcrttemberg",
    "wof:name":"Ev. Pfarramt Reuschkirche",
    "wof:placetype":"venue"
},
  "geometry": {"coordinates":[9.6433334351,48.7104530334],"type":"Point"}
}