{
  "type": "Feature",
  "properties": {
    "iso:country":"DE",
    "sg:address":"Melanchthonstr. 9",
    "sg:city":"Pfalzgrafenweiler",
    "sg:phone":"+49 7445/2558",
    "sg:postcode":"72285",
    "sg:province":"Baden-W\u00fcrttemberg",
    "wof:name":"Fritz Lamparter",
    "wof:placetype":"venue"
},
  "geometry": {"coordinates":[8.570636,48.527676],"type":"Point"}
}