{
  "type": "Feature",
  "properties": {
    "iso:country":"DE",
    "sg:address":"Ketschengasse 5",
    "sg:city":"Coburg",
    "sg:phone":"+49 9561/90886",
    "sg:postcode":"96450",
    "sg:province":"Bayern",
    "wof:name":"Bayerischer Squashcenter Betreiberverband",
    "wof:placetype":"venue"
},
  "geometry": {"coordinates":[10.9648799896,50.2577133179],"type":"Point"}
}