{
  "type": "Feature",
  "properties": {
    "iso:country":"DE",
    "sg:address":"Musestieg 2",
    "sg:city":"Thale",
    "sg:phone":"+49 3947/2818",
    "sg:postcode":"06502",
    "sg:province":"Sachsen-Anhalt",
    "wof:name":"Prof. Willi Neubert",
    "wof:placetype":"venue"
},
  "geometry": {"coordinates":[11.045795,51.752911],"type":"Point"}
}