{
  "type": "Feature",
  "properties": {
    "iso:country":"DE",
    "sg:address":"Bilsteiner Str. 18",
    "sg:city":"Olpe",
    "sg:postcode":"57462",
    "sg:province":"Nordrhein-Westfalen",
    "wof:name":"Mas Gmbh",
    "wof:placetype":"venue"
},
  "geometry": {"coordinates":[7.858353138,51.0361442566],"type":"Point"}
}