{
  "type": "Feature",
  "properties": {
    "iso:country":"DE",
    "sg:address":"Hahnheimer Str. 17",
    "sg:city":"Wolfsheim",
    "sg:postcode":"55578",
    "sg:province":"Rheinland-Pfalz",
    "wof:name":"Helmut Hangen",
    "wof:placetype":"venue"
},
  "geometry": {"coordinates":[8.0430164337,49.8725700378],"type":"Point"}
}