{
  "type": "Feature",
  "properties": {
    "iso:country":"DE",
    "sg:address":"Dorfstr. 37",
    "sg:city":"Krugau",
    "sg:phone":"+49 35471/497",
    "sg:postcode":"15913",
    "sg:province":"Brandenburg",
    "wof:name":"R. Dillan",
    "wof:placetype":"venue"
},
  "geometry": {"coordinates":[13.9841423035,52.0270309448],"type":"Point"}
}