{
  "type": "Feature",
  "properties": {
    "iso:country":"DE",
    "sg:address":"Halfenweg 26",
    "sg:city":"Mettlach",
    "sg:phone":"+49 6864/7815",
    "sg:postcode":"66693",
    "sg:province":"Saarland",
    "wof:name":"Michael Margraf",
    "wof:placetype":"venue"
},
  "geometry": {"coordinates":[6.6047568321,49.5155296326],"type":"Point"}
}