{
  "type": "Feature",
  "properties": {
    "iso:country":"DE",
    "sg:address":"Teutonenstr. 4",
    "sg:city":"Vechta",
    "sg:phone":"+49 4441/84351",
    "sg:postcode":"49377",
    "sg:province":"Niedersachsen",
    "wof:name":"Itworks - Software F\u00fcr Den T\u00e4glichen Bedarf",
    "wof:placetype":"venue"
},
  "geometry": {"coordinates":[8.280301,52.715481],"type":"Point"}
}