{
  "type": "Feature",
  "properties": {
    "iso:country":"DE",
    "sg:address":"Donaustr. 42",
    "sg:city":"Hanau",
    "sg:phone":"+49 6181/13465",
    "sg:postcode":"63452",
    "sg:province":"Hessen",
    "wof:name":"Richard Heckl",
    "wof:placetype":"venue"
},
  "geometry": {"coordinates":[8.9370002747,50.152431488],"type":"Point"}
}