{
  "type": "Feature",
  "properties": {
    "iso:country":"DE",
    "sg:address":"Oschitzer Str. 13",
    "sg:city":"Schleiz",
    "sg:phone":"+49 3663/423191",
    "sg:postcode":"07907",
    "sg:province":"Th\u00fcringen",
    "wof:name":"Berata Gmbh",
    "wof:placetype":"venue"
},
  "geometry": {"coordinates":[11.8037939072,50.5756340027],"type":"Point"}
}