{
  "type": "Feature",
  "properties": {
    "iso:country":"DE",
    "sg:address":"Sauerlandstra\u00dfe 7",
    "sg:city":"Gelsenkirchen",
    "sg:phone":"+49 209/397429",
    "sg:postcode":"45889",
    "sg:province":"Nordrhein-Westfalen",
    "wof:name":"Firma Schulnerberatung Marion Bruder",
    "wof:placetype":"venue"
},
  "geometry": {"coordinates":[7.105367,51.538944],"type":"Point"}
}