{
  "type": "Feature",
  "properties": {
    "iso:country":"DE",
    "sg:address":"Kleiner Kielort 6-8",
    "sg:city":"Hamburg",
    "sg:postcode":"20144",
    "sg:province":"Hamburg",
    "wof:name":"Dormoolen Fachlabor F\u00fcr Fotografie Gmbh & Co. Kg",
    "wof:placetype":"venue"
},
  "geometry": {"coordinates":[9.9760742188,53.5716247559],"type":"Point"}
}