{
  "type": "Feature",
  "properties": {
    "iso:country":"DE",
    "sg:address":"Niedergasse 88",
    "sg:city":"Stolberg",
    "sg:phone":"+49 34654/92002",
    "sg:postcode":"06547",
    "sg:province":"Sachsen-Anhalt",
    "wof:name":"I. Krischok",
    "wof:placetype":"venue"
},
  "geometry": {"coordinates":[10.957228,51.569294],"type":"Point"}
}