{
  "type": "Feature",
  "properties": {
    "iso:country":"DE",
    "sg:address":"Essener Str. 27",
    "sg:city":"Wilnsdorf",
    "sg:phone":"+49 2739/89750",
    "sg:postcode":"57234",
    "sg:province":"Nordrhein-Westfalen",
    "wof:name":"Gip Gmbh",
    "wof:placetype":"venue"
},
  "geometry": {"coordinates":[8.079346,50.82341],"type":"Point"}
}