{
  "type": "Feature",
  "properties": {
    "iso:country":"DE",
    "sg:address":"Bahnhofstr. 17",
    "sg:city":"Edemissen",
    "sg:phone":"+49 5372/1313",
    "sg:postcode":"31234",
    "sg:province":"Niedersachsen",
    "wof:name":"A. Bunk",
    "wof:placetype":"venue"
},
  "geometry": {"coordinates":[10.2766036987,52.4392051697],"type":"Point"}
}