{
  "type": "Feature",
  "properties": {
    "iso:country":"DE",
    "sg:address":"Sachsenh\u00e4user Landwehrweg 78",
    "sg:city":"Frankfurt",
    "sg:phone":"+49 69/681778",
    "sg:postcode":"60599",
    "sg:province":"Hessen",
    "wof:name":"Dr. Tilo Strickstock Rechtsanwalt",
    "wof:placetype":"venue"
},
  "geometry": {"coordinates":[8.7020740509,50.0892410278],"type":"Point"}
}