{
  "type": "Feature",
  "properties": {
    "iso:country":"DE",
    "sg:address":"An Der Lieth 14",
    "sg:city":"Osterholz-Scharmbeck",
    "sg:phone":"+49 4947/9196160",
    "sg:postcode":"27711",
    "sg:province":"Niedersachsen",
    "wof:name":"Kvt Kurlbaum Gmbh & Co. Kg",
    "wof:placetype":"venue"
},
  "geometry": {"coordinates":[8.778661,53.239239],"type":"Point"}
}