{
  "type": "Feature",
  "properties": {
    "iso:country":"DE",
    "sg:address":"Otto-Hahn-Str. 12",
    "sg:city":"Trittau",
    "sg:phone":"+49 4154/79330",
    "sg:postcode":"22946",
    "sg:province":"Schleswig-Holstein",
    "wof:name":"Holzhandlung Evermann & Sohn Kg",
    "wof:placetype":"venue"
},
  "geometry": {"coordinates":[10.3918581009,53.6230583191],"type":"Point"}
}