{
  "type": "Feature",
  "properties": {
    "iso:country":"DE",
    "sg:address":"B\u00e4ckerstr. 9",
    "sg:city":"Norderney",
    "sg:phone":"+49 4932/81698",
    "sg:postcode":"26548",
    "sg:province":"Niedersachsen",
    "wof:name":"Norderneyer Biergarten",
    "wof:placetype":"venue"
},
  "geometry": {"coordinates":[7.1452097893,53.7061500549],"type":"Point"}
}