{
  "type": "Feature",
  "properties": {
    "iso:country":"DE",
    "sg:address":"Steeg 12",
    "sg:city":"R\u00f6srath",
    "sg:phone":"+49 2205/4338",
    "sg:postcode":"51503",
    "sg:province":"Nordrhein-Westfalen",
    "wof:name":"Karl-heinz Scherschel",
    "wof:placetype":"venue"
},
  "geometry": {"coordinates":[7.1917161942,50.8840789795],"type":"Point"}
}