{
  "type": "Feature",
  "properties": {
    "iso:country":"DE",
    "sg:address":"Wendelsteinstr. 5",
    "sg:city":"Burgkirchen",
    "sg:phone":"+49 8679/1823",
    "sg:postcode":"84508",
    "sg:province":"Bayern",
    "wof:name":"Peter Ecker",
    "wof:placetype":"venue"
},
  "geometry": {"coordinates":[12.733312,48.157543],"type":"Point"}
}