{
  "type": "Feature",
  "properties": {
    "iso:country":"DE",
    "sg:address":"Hinter Kronshorst 4",
    "sg:city":"Espelkamp",
    "sg:phone":"+49 5743/920153",
    "sg:postcode":"32339",
    "sg:province":"Nordrhein-Westfalen",
    "wof:name":"A.t.m. Schmiedetechnik Gmbh",
    "wof:placetype":"venue"
},
  "geometry": {"coordinates":[8.6801147461,52.351726532],"type":"Point"}
}