{
  "type": "Feature",
  "properties": {
    "iso:country":"DE",
    "sg:address":"Landshuter Str. 35a",
    "sg:city":"Regensburg",
    "sg:phone":"+49 941/75407",
    "sg:postcode":"93053",
    "sg:province":"Bayern",
    "wof:name":"E. Ach",
    "wof:placetype":"venue"
},
  "geometry": {"coordinates":[12.1107969284,49.0111236572],"type":"Point"}
}