{
  "type": "Feature",
  "properties": {
    "iso:country":"DE",
    "sg:address":"Am Roten Schl\u00f6\u00dfle 14",
    "sg:city":"Memmingerberg",
    "sg:phone":"+49 8331/89459",
    "sg:postcode":"87766",
    "sg:province":"Bayern",
    "wof:name":"Josef Goder Reprografie",
    "wof:placetype":"venue"
},
  "geometry": {"coordinates":[10.2080879211,47.9909744263],"type":"Point"}
}