{
  "type": "Feature",
  "properties": {
    "iso:country":"DE",
    "sg:address":"Karlstr. 18",
    "sg:city":"Falkenberg",
    "sg:phone":"+49 35365/2235",
    "sg:postcode":"04895",
    "sg:province":"Brandenburg",
    "wof:name":"G\u00fcnter Barth",
    "wof:placetype":"venue"
},
  "geometry": {"coordinates":[13.2413902283,51.5867347717],"type":"Point"}
}