{
  "type": "Feature",
  "properties": {
    "iso:country":"DE",
    "sg:address":"Kaarster Str. 25",
    "sg:city":"Kaarst",
    "sg:phone":"+49 2131/604671",
    "sg:postcode":"41564",
    "sg:province":"Nordrhein-Westfalen",
    "wof:name":"Thoma Elektroanlagen Gmbh",
    "wof:placetype":"venue"
},
  "geometry": {"coordinates":[6.6067671776,51.2201385498],"type":"Point"}
}