{
  "type": "Feature",
  "properties": {
    "iso:country":"DE",
    "sg:address":"Gartenstr. 1 a",
    "sg:city":"B\u00fctzow",
    "sg:phone":"+49 38461/3278",
    "sg:postcode":"18246",
    "sg:province":"Mecklenburg-Vorpommern",
    "wof:name":"Warnow Klause",
    "wof:placetype":"venue"
},
  "geometry": {"coordinates":[11.9694232941,53.8349494934],"type":"Point"}
}