{
  "type": "Feature",
  "properties": {
    "iso:country":"DE",
    "sg:address":"Fuchsbergstr. 1",
    "sg:city":"Dresden",
    "sg:phone":"+49 351/8908477",
    "sg:postcode":"01108",
    "sg:province":"Sachsen",
    "wof:name":"Ines Und Roland B\u00e4rich",
    "wof:placetype":"venue"
},
  "geometry": {"coordinates":[13.795835,51.13451],"type":"Point"}
}