{
  "type": "Feature",
  "properties": {
    "iso:country":"DE",
    "sg:address":"Schlesienstr 2",
    "sg:city":"Sachsenhagen",
    "sg:phone":"+49 5725/8956",
    "sg:postcode":"31553",
    "sg:province":"Niedersachsen",
    "wof:name":"M. Weiche",
    "wof:placetype":"venue"
},
  "geometry": {"coordinates":[9.2689399719,52.3978652954],"type":"Point"}
}