{
  "type": "Feature",
  "properties": {
    "iso:country":"DE",
    "sg:address":"Neuenb\u00fcrger Str. 2",
    "sg:city":"Dobel",
    "sg:phone":"+49 7083/3191",
    "sg:postcode":"75335",
    "sg:province":"Baden-W\u00fcrttemberg",
    "wof:name":"Panorama-apotheke",
    "wof:placetype":"venue"
},
  "geometry": {"coordinates":[8.494317,48.797272],"type":"Point"}
}