{
  "type": "Feature",
  "properties": {
    "iso:country":"DE",
    "sg:address":"Unten im Felde 29",
    "sg:city":"Dortmund",
    "sg:phone":"+49 231/692316",
    "sg:postcode":"44388",
    "sg:province":"Nordrhein-Westfalen",
    "wof:name":"Elisabeth Ziebarth",
    "wof:placetype":"venue"
},
  "geometry": {"coordinates":[7.3199720383,51.5109443665],"type":"Point"}
}