{
  "type": "Feature",
  "properties": {
    "iso:country":"DE",
    "sg:address":"Am Breilingsweg 24",
    "sg:city":"Kronau",
    "sg:phone":"+49 7253/33822",
    "sg:postcode":"76709",
    "sg:province":"Baden-W\u00fcrttemberg",
    "wof:name":"Michael Breuer",
    "wof:placetype":"venue"
},
  "geometry": {"coordinates":[8.625375,49.214245],"type":"Point"}
}