{
  "type": "Feature",
  "properties": {
    "iso:country":"DE",
    "sg:address":"Dorfstr. 13",
    "sg:city":"H\u00f6now",
    "sg:postcode":"15366",
    "sg:province":"Brandenburg",
    "wof:name":"Pitta - Pieces Handelsgesellschaft Mbh",
    "wof:placetype":"venue"
},
  "geometry": {"coordinates":[13.638063,52.547283],"type":"Point"}
}