{
  "type": "Feature",
  "properties": {
    "iso:country":"DE",
    "sg:address":"Schulstr. 8",
    "sg:city":"Weinsheim",
    "sg:phone":"+49 6758/1538",
    "sg:postcode":"55595",
    "sg:province":"Rheinland-Pfalz",
    "wof:name":"G. Und H. Zimmermann",
    "wof:placetype":"venue"
},
  "geometry": {"coordinates":[7.76846,49.836445],"type":"Point"}
}