{
  "type": "Feature",
  "properties": {
    "iso:country":"DE",
    "sg:address":"Dresdener Str. 28",
    "sg:city":"Heiligenroth",
    "sg:phone":"+49 2602/90111",
    "sg:postcode":"56412",
    "sg:province":"Rheinland-Pfalz",
    "wof:name":"Christiane Leyendecker",
    "wof:placetype":"venue"
},
  "geometry": {"coordinates":[7.8647251129,50.4450912476],"type":"Point"}
}