{
  "type": "Feature",
  "properties": {
    "iso:country":"DE",
    "sg:address":"Roderburgm\u00fchle 13",
    "sg:city":"Stolberg",
    "sg:phone":"+49 2402/23311",
    "sg:postcode":"52222",
    "sg:province":"Nordrhein-Westfalen",
    "wof:name":"Sharr Turist Gmbh",
    "wof:placetype":"venue"
},
  "geometry": {"coordinates":[6.222468853,50.7770576477],"type":"Point"}
}