{
  "type": "Feature",
  "properties": {
    "iso:country":"DE",
    "sg:address":"Eichenweg 1",
    "sg:city":"Obernburg",
    "sg:phone":"+49 6022/5700",
    "sg:postcode":"63785",
    "sg:province":"Bayern",
    "wof:name":"Eichen-apotheke",
    "wof:placetype":"venue"
},
  "geometry": {"coordinates":[9.118048,49.836311],"type":"Point"}
}