{
  "type": "Feature",
  "properties": {
    "iso:country":"DE",
    "sg:address":"Flughafen",
    "sg:city":"Sch\u00f6nefeld",
    "sg:postcode":"12529",
    "sg:province":"Brandenburg",
    "wof:name":"Condor Flugdienst Gmbh",
    "wof:placetype":"venue"
},
  "geometry": {"coordinates":[13.517975,52.391628],"type":"Point"}
}