{
  "type": "Feature",
  "properties": {
    "iso:country":"DE",
    "sg:address":"Wei\u00dfenh\u00f6her Str. 73",
    "sg:city":"Berlin",
    "sg:phone":"+49 30/5147963",
    "sg:postcode":"12683",
    "sg:province":"Berlin",
    "wof:name":"Etk Gmbh",
    "wof:placetype":"venue"
},
  "geometry": {"coordinates":[13.554325,52.507584],"type":"Point"}
}