{
  "type": "Feature",
  "properties": {
    "iso:country":"DE",
    "sg:address":"Dorfstr. 21",
    "sg:city":"Westfehmarn",
    "sg:phone":"+49 4372/8070",
    "sg:postcode":"23769",
    "sg:province":"Schleswig-Holstein",
    "wof:name":"Atlas Treuhandges. Mbh",
    "wof:placetype":"venue"
},
  "geometry": {"coordinates":[11.0995397568,54.439781189],"type":"Point"}
}