{
  "type": "Feature",
  "properties": {
    "iso:country":"DE",
    "sg:address":"Lindenstr. 10",
    "sg:city":"Weifa",
    "sg:postcode":"01904",
    "sg:province":"Sachsen",
    "wof:name":"Christa Zosel",
    "wof:placetype":"venue"
},
  "geometry": {"coordinates":[14.360793,51.074886],"type":"Point"}
}