{
  "type": "Feature",
  "properties": {
    "iso:country":"DE",
    "sg:address":"Hegaustr. 5",
    "sg:city":"Bodman-Ludwigshafen",
    "sg:phone":"+49 7773/5305",
    "sg:postcode":"78351",
    "sg:province":"Baden-W\u00fcrttemberg",
    "wof:name":"Maria Stoffel-schwarz Steuerbevollm\u00e4chtigte",
    "wof:placetype":"venue"
},
  "geometry": {"coordinates":[9.0592746735,47.8215370178],"type":"Point"}
}