{
  "type": "Feature",
  "properties": {
    "iso:country":"DE",
    "sg:address":"Belziger Str. 34",
    "sg:city":"Berlin",
    "sg:postcode":"10823",
    "sg:province":"Berlin",
    "wof:name":"Actors-service Com Mediadata Gmbh",
    "wof:placetype":"venue"
},
  "geometry": {"coordinates":[13.351983,52.486694],"type":"Point"}
}