{
  "type": "Feature",
  "properties": {
    "iso:country":"DE",
    "sg:address":"Hellenbergstr. 60",
    "sg:city":"Rommerskirchen",
    "sg:phone":"+49 2182/7770",
    "sg:postcode":"41569",
    "sg:province":"Nordrhein-Westfalen",
    "wof:name":"Peter Glasmacher",
    "wof:placetype":"venue"
},
  "geometry": {"coordinates":[6.677501,51.099068],"type":"Point"}
}