{
  "type": "Feature",
  "properties": {
    "iso:country":"DE",
    "sg:address":"Carl-Hesse-Str. 35",
    "sg:city":"Verden",
    "sg:phone":"+49 4231/61019",
    "sg:postcode":"27283",
    "sg:province":"Niedersachsen",
    "wof:name":"Herbert Ringel",
    "wof:placetype":"venue"
},
  "geometry": {"coordinates":[9.2600393295,52.9241294861],"type":"Point"}
}