{
  "type": "Feature",
  "properties": {
    "iso:country":"DE",
    "sg:address":"Sch\u00f6nfelder Weg 42",
    "sg:city":"Solingen",
    "sg:phone":"+49 212/66713",
    "sg:postcode":"42699",
    "sg:province":"Nordrhein-Westfalen",
    "wof:name":"Heinz Tabbert Steuerberater",
    "wof:placetype":"venue"
},
  "geometry": {"coordinates":[7.0116848946,51.1440467834],"type":"Point"}
}