{
  "type": "Feature",
  "properties": {
    "iso:country":"DE",
    "sg:address":"Schertlestr. 2",
    "sg:city":"Villingen-Schwenningen",
    "sg:phone":"+49 7721/804273",
    "sg:postcode":"78050",
    "sg:province":"Baden-W\u00fcrttemberg",
    "wof:name":"Mauchsche Stiftung",
    "wof:placetype":"venue"
},
  "geometry": {"coordinates":[8.437836647,48.060798645],"type":"Point"}
}