{
  "type": "Feature",
  "properties": {
    "iso:country":"DE",
    "sg:address":"Kurhessenstr. 42",
    "sg:city":"Frankfurt",
    "sg:phone":"+49 69/529489",
    "sg:postcode":"60431",
    "sg:province":"Hessen",
    "wof:name":"Dr. M.p. Henninger Rechtsanwalt",
    "wof:placetype":"venue"
},
  "geometry": {"coordinates":[8.6569242477,50.1520881653],"type":"Point"}
}