{
  "type": "Feature",
  "properties": {
    "iso:country":"DE",
    "sg:address":"Wernher-von-Braun-Str 1-3",
    "sg:city":"Walsrode",
    "sg:phone":"+49 5161/98200",
    "sg:postcode":"29664",
    "sg:province":"Niedersachsen",
    "wof:name":"Schr\u00f6der Druck & Design Gmbh",
    "wof:placetype":"venue"
},
  "geometry": {"coordinates":[9.6177082062,52.8656997681],"type":"Point"}
}