{
  "type": "Feature",
  "properties": {
    "iso:country":"DE",
    "sg:address":"Hauptstr. 36",
    "sg:city":"Saarbr\u00fccken",
    "sg:phone":"+49 6898/39483",
    "sg:postcode":"66127",
    "sg:province":"Saarland",
    "wof:name":"J. Scheid",
    "wof:placetype":"venue"
},
  "geometry": {"coordinates":[6.895295,49.231342],"type":"Point"}
}