{
  "type": "Feature",
  "properties": {
    "iso:country":"DE",
    "sg:address":"Eugen-Bolz-Str. 94",
    "sg:city":"Ulm",
    "sg:phone":"+49 731/266634",
    "sg:postcode":"89075",
    "sg:province":"Baden-W\u00fcrttemberg",
    "wof:name":"Richard Simon",
    "wof:placetype":"venue"
},
  "geometry": {"coordinates":[10.0064725876,48.4202575684],"type":"Point"}
}