{
  "type": "Feature",
  "properties": {
    "iso:country":"DE",
    "sg:address":"Karl-Meister-Str. 6",
    "sg:city":"Taunusstein",
    "sg:phone":"+49 6128/8321",
    "sg:postcode":"65232",
    "sg:province":"Hessen",
    "wof:name":"G\u00fcnter Plomitzer",
    "wof:placetype":"venue"
},
  "geometry": {"coordinates":[8.1887521744,50.1491661072],"type":"Point"}
}