{
  "type": "Feature",
  "properties": {
    "iso:country":"DE",
    "sg:address":"Vo\u00dfkuhle 6",
    "sg:city":"Herdecke",
    "sg:phone":"+49 2335/3041",
    "sg:postcode":"58313",
    "sg:province":"Nordrhein-Westfalen",
    "wof:name":"E. Schoska Altenheim",
    "wof:placetype":"venue"
},
  "geometry": {"coordinates":[7.371187,51.395863],"type":"Point"}
}