{
  "type": "Feature",
  "properties": {
    "iso:country":"DE",
    "sg:address":"Hiddeser Str. 135",
    "sg:city":"Detmold",
    "sg:phone":"+49 5231/87231",
    "sg:postcode":"32760",
    "sg:province":"Nordrhein-Westfalen",
    "wof:name":"Eduard Vogt Kartoffelgro\u00dfhdlg. Inh. Matthias Erfkamp",
    "wof:placetype":"venue"
},
  "geometry": {"coordinates":[8.834944725,51.9327659607],"type":"Point"}
}