{
  "type": "Feature",
  "properties": {
    "iso:country":"DE",
    "sg:address":"Heimst\u00e4ttenstr. 1",
    "sg:city":"Seelze",
    "sg:phone":"+49 5137/937102",
    "sg:postcode":"30926",
    "sg:province":"Niedersachsen",
    "wof:name":"Thomas Warnat - Der Fliegende Hausmeister",
    "wof:placetype":"venue"
},
  "geometry": {"coordinates":[9.59276,52.393826],"type":"Point"}
}