{
  "type": "Feature",
  "properties": {
    "iso:country":"DE",
    "sg:address":"Mosacherweg 23",
    "sg:city":"Amberg",
    "sg:phone":"+49 9621/81279",
    "sg:postcode":"92224",
    "sg:province":"Bayern",
    "wof:name":"Fr\u00fcchte-l\u00f6hmer Inh. Anneliese Bernard",
    "wof:placetype":"venue"
},
  "geometry": {"coordinates":[11.8814430237,49.4414367676],"type":"Point"}
}