{
  "type": "Feature",
  "properties": {
    "iso:country":"DE",
    "sg:address":"Schumannstr. 8",
    "sg:city":"Chemnitz",
    "sg:phone":"+49 371/2801545",
    "sg:postcode":"09120",
    "sg:province":"Sachsen",
    "wof:name":"Eberhard J\u00e4hler",
    "wof:placetype":"venue"
},
  "geometry": {"coordinates":[12.904077,50.814182],"type":"Point"}
}