{
  "type": "Feature",
  "properties": {
    "iso:country":"DE",
    "sg:address":"Auf der Horst 1",
    "sg:city":"Osterholz-Scharmbeck",
    "sg:phone":"+49 4791/2592",
    "sg:postcode":"27711",
    "sg:province":"Niedersachsen",
    "wof:name":"Jan Jahnke",
    "wof:placetype":"venue"
},
  "geometry": {"coordinates":[8.8188724518,53.234172821],"type":"Point"}
}