{
  "type": "Feature",
  "properties": {
    "iso:country":"DE",
    "sg:address":"Justus-von-Liebig-Str. 19",
    "sg:city":"Neustadt",
    "sg:phone":"+49 5032/61011",
    "sg:postcode":"31535",
    "sg:province":"Niedersachsen",
    "wof:name":"Pallak Gmbh",
    "wof:placetype":"venue"
},
  "geometry": {"coordinates":[9.4772825241,52.5085754395],"type":"Point"}
}