{
  "type": "Feature",
  "properties": {
    "iso:country":"DE",
    "sg:address":"Freibachstr. 8",
    "sg:city":"Neukirchen",
    "sg:phone":"+49 9947/312",
    "sg:postcode":"93453",
    "sg:province":"Bayern",
    "wof:name":"Josef Weber",
    "wof:placetype":"venue"
},
  "geometry": {"coordinates":[12.971049,49.256531],"type":"Point"}
}