{
  "type": "Feature",
  "properties": {
    "iso:country":"DE",
    "sg:address":"Am Markt",
    "sg:city":"Insel Poel",
    "sg:phone":"+49 38425/352",
    "sg:postcode":"23999",
    "sg:province":"Mecklenburg-Vorpommern",
    "wof:name":"Am Markt",
    "wof:placetype":"venue"
},
  "geometry": {"coordinates":[11.4396696091,53.9976234436],"type":"Point"}
}