{
  "type": "Feature",
  "properties": {
    "iso:country":"DE",
    "sg:address":"Schleifweg 6",
    "sg:city":"Altusried",
    "sg:phone":"+49 8373/7002",
    "sg:postcode":"87452",
    "sg:province":"Bayern",
    "wof:name":"S. R\u00f6ck",
    "wof:placetype":"venue"
},
  "geometry": {"coordinates":[10.2089824677,47.809387207],"type":"Point"}
}