{
  "type": "Feature",
  "properties": {
    "iso:country":"DE",
    "sg:address":"Fichtenweg 10",
    "sg:city":"Bechenheim",
    "sg:phone":"+49 6736/582",
    "sg:postcode":"55234",
    "sg:province":"Rheinland-Pfalz",
    "wof:name":"Hans-walter Und Angela Sauer",
    "wof:placetype":"venue"
},
  "geometry": {"coordinates":[8.0037183762,49.7262001038],"type":"Point"}
}