{
  "type": "Feature",
  "properties": {
    "iso:country":"DE",
    "sg:address":"Hauptstr. 39",
    "sg:city":"Westerstetten",
    "sg:phone":"+49 7348/5873",
    "sg:postcode":"89198",
    "sg:province":"Baden-W\u00fcrttemberg",
    "wof:name":"G. Groner",
    "wof:placetype":"venue"
},
  "geometry": {"coordinates":[9.9527721405,48.5192909241],"type":"Point"}
}