{
  "type": "Feature",
  "properties": {
    "iso:country":"DE",
    "sg:address":"Langenfelder Str. 6",
    "sg:city":"K\u00f6then",
    "sg:phone":"+49 3496/505790",
    "sg:postcode":"06366",
    "sg:province":"Sachsen-Anhalt",
    "wof:name":"Azk Fahrzeughandel Gmbh",
    "wof:placetype":"venue"
},
  "geometry": {"coordinates":[11.9476079941,51.7450256348],"type":"Point"}
}