{
  "type": "Feature",
  "properties": {
    "iso:country":"DE",
    "sg:address":"Parkweg 2",
    "sg:city":"Albstadt",
    "sg:phone":"+49 7431/100",
    "sg:postcode":"72458",
    "sg:province":"Baden-W\u00fcrttemberg",
    "wof:name":"Groz-beckert Kg",
    "wof:placetype":"venue"
},
  "geometry": {"coordinates":[9.02531,48.209286],"type":"Point"}
}