{
  "type": "Feature",
  "properties": {
    "iso:country":"DE",
    "sg:address":"Sandstr. 3 a",
    "sg:city":"Viernheim",
    "sg:phone":"+49 6204/76381",
    "sg:postcode":"68519",
    "sg:province":"Hessen",
    "wof:name":"M. Tekath Immobilienmakler",
    "wof:placetype":"venue"
},
  "geometry": {"coordinates":[8.5741033554,49.5307159424],"type":"Point"}
}