{
  "type": "Feature",
  "properties": {
    "iso:country":"DE",
    "sg:address":"Haferkuhle 1",
    "sg:city":"Uchte",
    "sg:phone":"+49 5763/96100",
    "sg:postcode":"31600",
    "sg:province":"Niedersachsen",
    "wof:name":"Preco",
    "wof:placetype":"venue"
},
  "geometry": {"coordinates":[8.8968572617,52.4805603027],"type":"Point"}
}