{
  "type": "Feature",
  "properties": {
    "iso:country":"DE",
    "sg:address":"Coerdestr. 3b",
    "sg:city":"M\u00fcnster",
    "sg:phone":"+49 251/270171",
    "sg:postcode":"48147",
    "sg:province":"Nordrhein-Westfalen",
    "wof:name":"Axel Von Der Dunk",
    "wof:placetype":"venue"
},
  "geometry": {"coordinates":[7.6276640892,51.9685440063],"type":"Point"}
}