{
  "type": "Feature",
  "properties": {
    "iso:country":"DE",
    "sg:address":"Bruckstr. 26",
    "sg:city":"Dingolfing",
    "sg:phone":"+49 8731/3716",
    "sg:postcode":"84130",
    "sg:province":"Bayern",
    "wof:name":"Homberg- Ernst Zahnweh E. K.",
    "wof:placetype":"venue"
},
  "geometry": {"coordinates":[12.4962720871,48.6297607422],"type":"Point"}
}