{
  "type": "Feature",
  "properties": {
    "iso:country":"DE",
    "sg:address":"Friedrich-Ebert-Str. 15",
    "sg:city":"Reutlingen",
    "sg:phone":"+49 7121/270336",
    "sg:postcode":"72762",
    "sg:province":"Baden-W\u00fcrttemberg",
    "wof:name":"Ev. Freikirchl. Pfarramt",
    "wof:placetype":"venue"
},
  "geometry": {"coordinates":[9.2096948624,48.488658905],"type":"Point"}
}