{
  "type": "Feature",
  "properties": {
    "iso:country":"DE",
    "sg:address":"Kreuzstr. 3",
    "sg:city":"Wermelskirchen",
    "sg:phone":"+49 2196/6333",
    "sg:postcode":"42929",
    "sg:province":"Nordrhein-Westfalen",
    "wof:name":"Gerhard Hundt Gmbh",
    "wof:placetype":"venue"
},
  "geometry": {"coordinates":[7.2181940079,51.1435317993],"type":"Point"}
}