{
  "type": "Feature",
  "properties": {
    "iso:country":"DE",
    "sg:address":"Wiclefstr. 63",
    "sg:city":"Berlin",
    "sg:phone":"+49 30/3964067",
    "sg:postcode":"10551",
    "sg:province":"Berlin",
    "wof:name":"Lampenputzer",
    "wof:placetype":"venue"
},
  "geometry": {"coordinates":[13.3381357193,52.5300865173],"type":"Point"}
}