{
  "type": "Feature",
  "properties": {
    "iso:country":"DE",
    "sg:address":"Rohlfsstr. 15",
    "sg:city":"Dresden",
    "sg:phone":"+49 351/4724110",
    "sg:postcode":"01069",
    "sg:province":"Sachsen",
    "wof:name":"Christian Thoma Architekt",
    "wof:placetype":"venue"
},
  "geometry": {"coordinates":[13.73829,51.03212],"type":"Point"}
}