{
  "type": "Feature",
  "properties": {
    "iso:country":"DE",
    "sg:address":"Ferdinandstr. 45",
    "sg:city":"Paderborn",
    "sg:phone":"+49 5251/34710",
    "sg:postcode":"33102",
    "sg:province":"Nordrhein-Westfalen",
    "wof:name":"Wolfgang M\u00fcller",
    "wof:placetype":"venue"
},
  "geometry": {"coordinates":[8.7428398132,51.7189292908],"type":"Point"}
}