{
  "type": "Feature",
  "properties": {
    "iso:country":"DE",
    "sg:address":"M\u00fcncheh\u00e4ger Str. 1",
    "sg:city":"Rehburg-Loccum",
    "sg:phone":"+49 5766/228",
    "sg:postcode":"31547",
    "sg:province":"Niedersachsen",
    "wof:name":"Textilhaus Heinrich B\u00f6ger Inh. Sieglinde B\u00f6ger E. K.",
    "wof:placetype":"venue"
},
  "geometry": {"coordinates":[9.153289,52.45401],"type":"Point"}
}