{
  "type": "Feature",
  "properties": {
    "iso:country":"DE",
    "sg:address":"Kurze Str. 2",
    "sg:city":"Wuppertal",
    "sg:phone":"+49 202/602782",
    "sg:postcode":"42389",
    "sg:province":"Nordrhein-Westfalen",
    "wof:name":"Mennen\u00f6h",
    "wof:placetype":"venue"
},
  "geometry": {"coordinates":[7.244965,51.27499],"type":"Point"}
}