{
  "type": "Feature",
  "properties": {
    "iso:country":"DE",
    "sg:address":"Karlsruher Str. 55",
    "sg:city":"Rheinstetten",
    "sg:phone":"+49 721/510526",
    "sg:postcode":"76287",
    "sg:province":"Baden-W\u00fcrttemberg",
    "wof:name":"Ev. Pfarramt Gem. Forchheim",
    "wof:placetype":"venue"
},
  "geometry": {"coordinates":[8.3181009293,48.979259491],"type":"Point"}
}