{
  "type": "Feature",
  "properties": {
    "iso:country":"DE",
    "sg:address":"Sinstorfer Kirchweg 22",
    "sg:city":"Hamburg",
    "sg:postcode":"21077",
    "sg:province":"Hamburg",
    "wof:name":"Vermarktung, Bannerwerbung, Adserver, Advertising",
    "wof:placetype":"venue"
},
  "geometry": {"coordinates":[9.97411,53.424282],"type":"Point"}
}