{
  "type": "Feature",
  "properties": {
    "iso:country":"DE",
    "sg:address":"Jahnstr. 21",
    "sg:city":"Dorfen",
    "sg:phone":"+49 8081/3126",
    "sg:postcode":"84405",
    "sg:province":"Bayern",
    "wof:name":"Wolfgang Strobl",
    "wof:placetype":"venue"
},
  "geometry": {"coordinates":[12.1548585892,48.2712860107],"type":"Point"}
}