{
  "type": "Feature",
  "properties": {
    "iso:country":"DE",
    "sg:address":"Teichstr. 14",
    "sg:city":"Velbert",
    "sg:phone":"+49 2051/254073",
    "sg:postcode":"42551",
    "sg:province":"Nordrhein-Westfalen",
    "wof:name":"K. J\u00fclicher Beteiligungs- Gmbh",
    "wof:placetype":"venue"
},
  "geometry": {"coordinates":[7.056527,51.32568],"type":"Point"}
}