{
  "type": "Feature",
  "properties": {
    "iso:country":"DE",
    "sg:address":"In der Dodesheide 39",
    "sg:city":"Osnabr\u00fcck",
    "sg:phone":"+49 541/188483",
    "sg:postcode":"49088",
    "sg:province":"Niedersachsen",
    "wof:name":"Galenus-apotheke",
    "wof:placetype":"venue"
},
  "geometry": {"coordinates":[8.064049,52.3027],"type":"Point"}
}