{
  "type": "Feature",
  "properties": {
    "iso:country":"DE",
    "sg:address":"Gerhart-Hauptmann-Str. 28",
    "sg:city":"B\u00fcckeburg",
    "sg:phone":"+49 5722/5577",
    "sg:postcode":"31675",
    "sg:province":"Niedersachsen",
    "wof:name":"Pension Am Harrl",
    "wof:placetype":"venue"
},
  "geometry": {"coordinates":[9.0615034103,52.2486495972],"type":"Point"}
}