{
  "type": "Feature",
  "properties": {
    "iso:country":"DE",
    "sg:address":"Am Geeren 8",
    "sg:city":"Detmold",
    "sg:phone":"+49 5231/89393",
    "sg:postcode":"32760",
    "sg:province":"Nordrhein-Westfalen",
    "wof:name":"Tanz Studio M\u00e4cker Wilhelm M\u00e4cker",
    "wof:placetype":"venue"
},
  "geometry": {"coordinates":[8.8446855545,51.9237976074],"type":"Point"}
}