{
  "type": "Feature",
  "properties": {
    "iso:country":"DE",
    "sg:address":"Kleingem\u00fcnder Str. 42",
    "sg:city":"Heidelberg",
    "sg:phone":"+49 6221/802280",
    "sg:postcode":"69118",
    "sg:province":"Baden-W\u00fcrttemberg",
    "wof:name":"Hans-j\u00f6rg Hennig",
    "wof:placetype":"venue"
},
  "geometry": {"coordinates":[8.772359848,49.4151000977],"type":"Point"}
}