{
  "type": "Feature",
  "properties": {
    "iso:country":"DE",
    "sg:address":"Herrnstr. 3",
    "sg:city":"W\u00fcrzburg",
    "sg:phone":"+49 931/355720",
    "sg:postcode":"97070",
    "sg:province":"Bayern",
    "wof:name":"Signal Unfallversicherung Ag",
    "wof:placetype":"venue"
},
  "geometry": {"coordinates":[9.9324092865,49.7946281433],"type":"Point"}
}