{
  "type": "Feature",
  "properties": {
    "iso:country":"DE",
    "sg:address":"Steinhauser Weg 7",
    "sg:city":"Aalen",
    "sg:phone":"+49 7366/4840",
    "sg:postcode":"73434",
    "sg:province":"Baden-W\u00fcrttemberg",
    "wof:name":"Manfred Haug",
    "wof:placetype":"venue"
},
  "geometry": {"coordinates":[10.0352697372,48.871383667],"type":"Point"}
}