{
  "type": "Feature",
  "properties": {
    "iso:country":"DE",
    "sg:address":"Hansestr. 3",
    "sg:city":"L\u00fcbeck",
    "sg:phone":"+49 451/88090",
    "sg:postcode":"23558",
    "sg:province":"Schleswig-Holstein",
    "wof:name":"Hotel Excelsior",
    "wof:placetype":"venue"
},
  "geometry": {"coordinates":[10.6723432541,53.8659858704],"type":"Point"}
}