{
  "type": "Feature",
  "properties": {
    "iso:country":"DE",
    "sg:address":"K\u00f6sters Gang 15",
    "sg:city":"Dinklage",
    "sg:phone":"+49 4443/4646",
    "sg:postcode":"49413",
    "sg:province":"Niedersachsen",
    "wof:name":"Driversche Apotheke",
    "wof:placetype":"venue"
},
  "geometry": {"coordinates":[8.121404,52.659027],"type":"Point"}
}