{
  "type": "Feature",
  "properties": {
    "iso:country":"DE",
    "sg:address":"Loickstr 7d",
    "sg:city":"Mittenwalde",
    "sg:phone":"+49 33764/20328",
    "sg:postcode":"15749",
    "sg:province":"Brandenburg",
    "wof:name":"M\u00e4rkische Agrargenossenschaft Eg",
    "wof:placetype":"venue"
},
  "geometry": {"coordinates":[13.531460762,52.2640647888],"type":"Point"}
}