{
  "type": "Feature",
  "properties": {
    "iso:country":"DE",
    "sg:address":"Stader Str. 99-101",
    "sg:city":"Hemmoor",
    "sg:phone":"+49 4771/2822",
    "sg:postcode":"21745",
    "sg:province":"Niedersachsen",
    "wof:name":"Ewald Kr\u00f6ncke",
    "wof:placetype":"venue"
},
  "geometry": {"coordinates":[9.171994,53.687176],"type":"Point"}
}