{
  "type": "Feature",
  "properties": {
    "iso:country":"DE",
    "sg:address":"Pfarrer-Maier-Str. 30",
    "sg:city":"B\u00f6bingen",
    "sg:phone":"+49 7173/4537",
    "sg:postcode":"73560",
    "sg:province":"Baden-W\u00fcrttemberg",
    "wof:name":"Bernhard U. Maria Krone Praxis F\u00fcr Krankengymnastik",
    "wof:placetype":"venue"
},
  "geometry": {"coordinates":[9.927188,48.813148],"type":"Point"}
}