{
  "type": "Feature",
  "properties": {
    "iso:country":"DE",
    "sg:address":"R\u00f6ntgenstr. 7",
    "sg:city":"Schwarzenbek",
    "sg:postcode":"21493",
    "sg:province":"Schleswig-Holstein",
    "wof:name":"Marmor- Und Granit Verlege Gmbh",
    "wof:placetype":"venue"
},
  "geometry": {"coordinates":[10.5049171448,53.5062599182],"type":"Point"}
}