{
  "type": "Feature",
  "properties": {
    "iso:country":"DE",
    "sg:address":"Bahnhofstr.",
    "sg:city":"Moschheim",
    "sg:phone":"+49 2602/81833",
    "sg:postcode":"56424",
    "sg:province":"Rheinland-Pfalz",
    "wof:name":"Pfeifer",
    "wof:placetype":"venue"
},
  "geometry": {"coordinates":[7.840760231,50.4815406799],"type":"Point"}
}