{
  "type": "Feature",
  "properties": {
    "iso:country":"DE",
    "sg:address":"Postfach 1120",
    "sg:city":"Freudenberg",
    "sg:phone":"+49 2734/4362",
    "sg:postcode":"57251",
    "sg:province":"Baden-W\u00fcrttemberg",
    "wof:name":"Stadtverwaltung Stadtb\u00fccherei",
    "wof:placetype":"venue"
},
  "geometry": {"coordinates":[7.875825,50.896782],"type":"Point"}
}