{
  "type": "Feature",
  "properties": {
    "iso:country":"DE",
    "sg:address":"S\u00fcdstr. 7",
    "sg:city":"Genderkingen",
    "sg:phone":"+49 9090/90277",
    "sg:postcode":"86682",
    "sg:province":"Bayern",
    "wof:name":"Prs Gmbh",
    "wof:placetype":"venue"
},
  "geometry": {"coordinates":[10.8734312057,48.6994132996],"type":"Point"}
}