{
  "type": "Feature",
  "properties": {
    "iso:country":"DE",
    "sg:address":"Jahnstr. 41",
    "sg:city":"Horn-Bad Meinberg",
    "sg:phone":"+49 5234/5855",
    "sg:postcode":"32805",
    "sg:province":"Nordrhein-Westfalen",
    "wof:name":"Gemballa",
    "wof:placetype":"venue"
},
  "geometry": {"coordinates":[8.933002,51.866268],"type":"Point"}
}