{
  "type": "Feature",
  "properties": {
    "iso:country":"DE",
    "sg:address":"Gleisenhofer Str. 21",
    "sg:city":"Neunkirchen",
    "sg:phone":"+49 9192/8548",
    "sg:postcode":"91077",
    "sg:province":"Bayern",
    "wof:name":"Restaurant Berggastst\u00e4tte Hass",
    "wof:placetype":"venue"
},
  "geometry": {"coordinates":[11.1310253143,49.6129798889],"type":"Point"}
}