{
  "type": "Feature",
  "properties": {
    "iso:country":"DE",
    "sg:address":"Neustadt 464",
    "sg:city":"Landshut",
    "sg:phone":"+49 871/923440",
    "sg:postcode":"84028",
    "sg:province":"Bayern",
    "wof:name":"Hella Opel Feine Damenmoden Gmbh",
    "wof:placetype":"venue"
},
  "geometry": {"coordinates":[12.153708,48.535545],"type":"Point"}
}