{
  "type": "Feature",
  "properties": {
    "iso:country":"DE",
    "sg:address":"Trebeweg 14",
    "sg:city":"Dresden",
    "sg:phone":"+49 351/269920",
    "sg:postcode":"01324",
    "sg:province":"Sachsen",
    "wof:name":"R. Gr\u00fctzner Steuerberater",
    "wof:placetype":"venue"
},
  "geometry": {"coordinates":[13.8614501953,51.053855896],"type":"Point"}
}