{
  "type": "Feature",
  "properties": {
    "iso:country":"DE",
    "sg:address":"Marthastr. 6",
    "sg:city":"K\u00f6ln",
    "sg:phone":"+49 221/6893070",
    "sg:postcode":"51069",
    "sg:province":"Nordrhein-Westfalen",
    "wof:name":"Frank Schmidt Steuerberater",
    "wof:placetype":"venue"
},
  "geometry": {"coordinates":[7.0694518089,50.9778633118],"type":"Point"}
}