{
  "type": "Feature",
  "properties": {
    "iso:country":"DE",
    "sg:address":"Weisestr. 49",
    "sg:city":"Berlin",
    "sg:postcode":"12049",
    "sg:province":"Berlin",
    "wof:name":"Filigrana Gmbh",
    "wof:placetype":"venue"
},
  "geometry": {"coordinates":[13.424388,52.476761],"type":"Point"}
}