{
  "type": "Feature",
  "properties": {
    "iso:country":"DE",
    "sg:address":"Bahnhofplatz 1",
    "sg:city":"F\u00fcrth",
    "sg:phone":"+49 911/773022",
    "sg:postcode":"90762",
    "sg:province":"Bayern",
    "wof:name":"Henrich & Partner Gmbh",
    "wof:placetype":"venue"
},
  "geometry": {"coordinates":[10.9899587631,49.4710845947],"type":"Point"}
}