{
  "type": "Feature",
  "properties": {
    "iso:country":"DE",
    "sg:address":"Gro\u00dfer Winkelsheidermoorweg 40",
    "sg:city":"Varel",
    "sg:phone":"+49 4451/4663",
    "sg:postcode":"26316",
    "sg:province":"Niedersachsen",
    "wof:name":"W. Fehners",
    "wof:placetype":"venue"
},
  "geometry": {"coordinates":[8.097253,53.406433],"type":"Point"}
}