{
  "type": "Feature",
  "properties": {
    "iso:country":"DE",
    "sg:address":"Heideg\u00e4rten 5",
    "sg:city":"Bielefeld",
    "sg:phone":"+49 521/81460",
    "sg:postcode":"33611",
    "sg:province":"Nordrhein-Westfalen",
    "wof:name":"Gustav Dr\u00f6ge",
    "wof:placetype":"venue"
},
  "geometry": {"coordinates":[8.546611,52.052299],"type":"Point"}
}