{
  "type": "Feature",
  "properties": {
    "iso:country":"DE",
    "sg:address":"F\u00fcnfhausen 50",
    "sg:city":"Worpswede",
    "sg:phone":"+49 4794/334",
    "sg:postcode":"27726",
    "sg:province":"Niedersachsen",
    "wof:name":"Gastst\u00e4tte Hildegard Bruse",
    "wof:placetype":"venue"
},
  "geometry": {"coordinates":[8.9892902374,53.277130127],"type":"Point"}
}