{
  "type": "Feature",
  "properties": {
    "iso:country":"DE",
    "sg:address":"Steintorwall 3",
    "sg:city":"Braunschweig",
    "sg:phone":"+49 531/4704861",
    "sg:postcode":"38100",
    "sg:province":"Niedersachsen",
    "wof:name":"Die Br\u00fccke",
    "wof:placetype":"venue"
},
  "geometry": {"coordinates":[10.533773,52.262325],"type":"Point"}
}