{
  "type": "Feature",
  "properties": {
    "iso:country":"DE",
    "sg:address":"Harenberger Meile 24d",
    "sg:city":"Seelze",
    "sg:phone":"+49 5137/4871",
    "sg:postcode":"30926",
    "sg:province":"Niedersachsen",
    "wof:name":"Gerhard Saborowski Gmbh",
    "wof:placetype":"venue"
},
  "geometry": {"coordinates":[9.618241,52.378098],"type":"Point"}
}