{
  "type": "Feature",
  "properties": {
    "iso:country":"DE",
    "sg:address":"Wasserstr. 9",
    "sg:city":"Hoym",
    "sg:phone":"+49 34741/474",
    "sg:postcode":"06467",
    "sg:province":"Sachsen-Anhalt",
    "wof:name":"Albrecht",
    "wof:placetype":"venue"
},
  "geometry": {"coordinates":[11.3138713837,51.7855529785],"type":"Point"}
}