{
  "type": "Feature",
  "properties": {
    "iso:country":"DE",
    "sg:address":"Haydnstr. 7",
    "sg:city":"Hockenheim",
    "sg:phone":"+49 6205/4530",
    "sg:postcode":"68766",
    "sg:province":"Baden-W\u00fcrttemberg",
    "wof:name":"Henry Lorenz",
    "wof:placetype":"venue"
},
  "geometry": {"coordinates":[8.540706,49.314407],"type":"Point"}
}