{
  "type": "Feature",
  "properties": {
    "iso:country":"DE",
    "sg:address":"H\u00fchnerkamp 11 a",
    "sg:city":"Achim",
    "sg:phone":"+49 4202/82228",
    "sg:postcode":"28832",
    "sg:province":"Niedersachsen",
    "wof:name":"Heinrich Martens Jun.",
    "wof:placetype":"venue"
},
  "geometry": {"coordinates":[9.030648,53.033997],"type":"Point"}
}