{
  "type": "Feature",
  "properties": {
    "iso:country":"DE",
    "sg:address":"Walter-Rohloff-Str. 1",
    "sg:city":"Ichtershausen",
    "sg:phone":"+49 3628/603536",
    "sg:postcode":"99334",
    "sg:province":"Th\u00fcringen",
    "wof:name":"M. Hoyme",
    "wof:placetype":"venue"
},
  "geometry": {"coordinates":[10.968537,50.876965],"type":"Point"}
}