{
  "type": "Feature",
  "properties": {
    "iso:country":"DE",
    "sg:address":"Ostwall 37",
    "sg:city":"Dortmund",
    "sg:phone":"+49 231/528583",
    "sg:postcode":"44135",
    "sg:province":"Nordrhein-Westfalen",
    "wof:name":"Victorian Pub",
    "wof:placetype":"venue"
},
  "geometry": {"coordinates":[7.4707660675,51.5111122131],"type":"Point"}
}