{
  "type": "Feature",
  "properties": {
    "iso:country":"DE",
    "sg:address":"Schongauer Str. 116",
    "sg:city":"Pei\u00dfenberg",
    "sg:phone":"+49 8803/2768",
    "sg:postcode":"82380",
    "sg:province":"Bayern",
    "wof:name":"Ludwig B\u00f6sl",
    "wof:placetype":"venue"
},
  "geometry": {"coordinates":[11.052748,47.785942],"type":"Point"}
}