{
  "type": "Feature",
  "properties": {
    "iso:country":"DE",
    "sg:address":"Bruchweg 11",
    "sg:city":"Heinade",
    "sg:phone":"+49 5564/2751",
    "sg:postcode":"37627",
    "sg:province":"Niedersachsen",
    "wof:name":"R. Sommerfeld",
    "wof:placetype":"venue"
},
  "geometry": {"coordinates":[9.6417808533,51.8246765137],"type":"Point"}
}