{
  "type": "Feature",
  "properties": {
    "iso:country":"DE",
    "sg:address":"Albwerkstr. 8",
    "sg:city":"Geislingen",
    "sg:phone":"+49 7331/61253",
    "sg:postcode":"73312",
    "sg:province":"Baden-W\u00fcrttemberg",
    "wof:name":"Adolf Brucker Architekt",
    "wof:placetype":"venue"
},
  "geometry": {"coordinates":[9.83475,48.624229],"type":"Point"}
}