{
  "type": "Feature",
  "properties": {
    "iso:country":"DE",
    "sg:address":"F\u00e4hrstr. 35",
    "sg:city":"Eisenh\u00fcttenstadt",
    "sg:phone":"+49 3364/40760",
    "sg:postcode":"15890",
    "sg:province":"Brandenburg",
    "wof:name":"Kaufland Warenhandel Ost Gmbh & Co. Kg",
    "wof:placetype":"venue"
},
  "geometry": {"coordinates":[14.6448154449,52.1457824707],"type":"Point"}
}