{
  "type": "Feature",
  "properties": {
    "iso:country":"DE",
    "sg:address":"August-Bebel-Str. 62",
    "sg:city":"Blankenfelde",
    "sg:phone":"+49 3379/372666",
    "sg:postcode":"15827",
    "sg:province":"Brandenburg",
    "wof:name":"Bernhard Klein",
    "wof:placetype":"venue"
},
  "geometry": {"coordinates":[13.4012699127,52.3374671936],"type":"Point"}
}