{
  "type": "Feature",
  "properties": {
    "iso:country":"DE",
    "sg:address":"Zollernstr. 11",
    "sg:city":"Augsburg",
    "sg:phone":"+49 821/413541",
    "sg:postcode":"86154",
    "sg:province":"Bayern",
    "wof:name":"Helmut Mayer",
    "wof:placetype":"venue"
},
  "geometry": {"coordinates":[10.876536,48.383862],"type":"Point"}
}