{
  "type": "Feature",
  "properties": {
    "iso:country":"DE",
    "sg:address":"Kelterberg 5",
    "sg:city":"Stuttgart",
    "sg:postcode":"70563",
    "sg:province":"Baden-W\u00fcrttemberg",
    "wof:name":"Verein Griechischer Eltern Und Erziehungsberechtigter",
    "wof:placetype":"venue"
},
  "geometry": {"coordinates":[9.1081590652,48.7318878174],"type":"Point"}
}