{
  "type": "Feature",
  "properties": {
    "iso:country":"DE",
    "sg:address":"Jahnstr. 7",
    "sg:city":"Schornsheim",
    "sg:phone":"+49 6732/65313",
    "sg:postcode":"55288",
    "sg:province":"Rheinland-Pfalz",
    "wof:name":"Horst Schermer",
    "wof:placetype":"venue"
},
  "geometry": {"coordinates":[8.1716394424,49.8462409973],"type":"Point"}
}