{
  "type": "Feature",
  "properties": {
    "iso:country":"DE",
    "sg:address":"Bei der Wimpfener Br\u00fccke",
    "sg:city":"Bad Friedrichshall",
    "sg:phone":"+49 7136/95450",
    "sg:postcode":"74177",
    "sg:province":"Baden-W\u00fcrttemberg",
    "wof:name":"Clemens Erath Gmbh & Co.",
    "wof:placetype":"venue"
},
  "geometry": {"coordinates":[9.193453,49.23563],"type":"Point"}
}