{
  "type": "Feature",
  "properties": {
    "iso:country":"DE",
    "sg:address":"Von-Droste-H\u00fclshoff-Str 7",
    "sg:city":"Ahlen",
    "sg:phone":"+49 7136/7760",
    "sg:postcode":"59227",
    "sg:province":"Nordrhein-Westfalen",
    "wof:name":"Crysopal Tiffany Glastechnik Gmbh",
    "wof:placetype":"venue"
},
  "geometry": {"coordinates":[9.1951313019,49.2322807312],"type":"Point"}
}