{
  "type": "Feature",
  "properties": {
    "iso:country":"DE",
    "sg:address":"Heilbronner Str. 3",
    "sg:city":"G\u00f6ppingen",
    "sg:phone":"+49 7161/963880",
    "sg:postcode":"73037",
    "sg:province":"Baden-W\u00fcrttemberg",
    "wof:name":"Elektro-heldele Gmbh",
    "wof:placetype":"venue"
},
  "geometry": {"coordinates":[9.682261,48.693729],"type":"Point"}
}