{
  "type": "Feature",
  "properties": {
    "iso:country":"DE",
    "sg:address":"Glockenstr. 83 Bergheim",
    "sg:city":"Troisdorf",
    "sg:phone":"+49 4922/8450064",
    "sg:postcode":"53844",
    "sg:province":"Nordrhein-Westfalen",
    "wof:name":"Klaus Hee\u00df Reisen U. Transporte Gmbh",
    "wof:placetype":"venue"
},
  "geometry": {"coordinates":[7.1246800423,50.8001213074],"type":"Point"}
}