{
  "type": "Feature",
  "properties": {
    "iso:country":"DE",
    "sg:address":"Sandhauser Str. 8 d",
    "sg:city":"Berlin",
    "sg:phone":"+49 30/4319926",
    "sg:postcode":"13505",
    "sg:province":"Berlin",
    "wof:name":"Michael Swoboda",
    "wof:placetype":"venue"
},
  "geometry": {"coordinates":[13.2266139984,52.5867500305],"type":"Point"}
}