{
  "type": "Feature",
  "properties": {
    "iso:country":"DE",
    "sg:address":"Oberlinden 9",
    "sg:city":"Freiburg",
    "sg:phone":"+49 761/34743",
    "sg:postcode":"79098",
    "sg:province":"Baden-W\u00fcrttemberg",
    "wof:name":"H. M\u00fcller",
    "wof:placetype":"venue"
},
  "geometry": {"coordinates":[7.854141,47.993374],"type":"Point"}
}