{
  "type": "Feature",
  "properties": {
    "iso:country":"DE",
    "sg:address":"Korbacherstr. 15",
    "sg:city":"Wiesentheid",
    "sg:phone":"+49 9383/97320",
    "sg:postcode":"97353",
    "sg:province":"Bayern",
    "wof:name":"Dahlmann-sinningsystemtechnik Gmbh",
    "wof:placetype":"venue"
},
  "geometry": {"coordinates":[10.343458,49.786427],"type":"Point"}
}