{
  "type": "Feature",
  "properties": {
    "iso:country":"DE",
    "sg:address":"Hannoversche Str. 110",
    "sg:city":"Nienburg",
    "sg:phone":"+49 5021/91810",
    "sg:postcode":"31582",
    "sg:province":"Niedersachsen",
    "wof:name":"Nienburger M\u00f6belfabrik Gmbh",
    "wof:placetype":"venue"
},
  "geometry": {"coordinates":[9.2262620926,52.6264801025],"type":"Point"}
}