{
  "type": "Feature",
  "properties": {
    "iso:country":"DE",
    "sg:address":"Neutor 24",
    "sg:city":"Borken",
    "sg:postcode":"46325",
    "sg:province":"Nordrhein-Westfalen",
    "wof:name":"Spielomat Borken Handels-gmbh",
    "wof:placetype":"venue"
},
  "geometry": {"coordinates":[6.8568310738,51.8428192139],"type":"Point"}
}