{
  "type": "Feature",
  "properties": {
    "iso:country":"DE",
    "sg:address":"Riedebachweg 22",
    "sg:city":"Winsen",
    "sg:phone":"+49 4171/71186",
    "sg:postcode":"21423",
    "sg:province":"Niedersachsen",
    "wof:name":"Torsten Schemat",
    "wof:placetype":"venue"
},
  "geometry": {"coordinates":[10.2128362656,53.3450508118],"type":"Point"}
}