{
  "type": "Feature",
  "properties": {
    "iso:country":"DE",
    "sg:address":"Oberer Bangert 2",
    "sg:city":"Bolanden",
    "sg:postcode":"67295",
    "sg:province":"Rheinland-Pfalz",
    "wof:name":"Masel Medizinhandel Gmbh",
    "wof:placetype":"venue"
},
  "geometry": {"coordinates":[8.0073900223,49.638923645],"type":"Point"}
}