{
  "type": "Feature",
  "properties": {
    "iso:country":"DE",
    "sg:address":"Fernpa\u00dfstr. 2",
    "sg:city":"M\u00fcnchen",
    "sg:phone":"+49 89/49002980",
    "sg:postcode":"81373",
    "sg:province":"Bayern",
    "wof:name":"Gebes Reinigungsservice Dienstleistungen Gmbh",
    "wof:placetype":"venue"
},
  "geometry": {"coordinates":[11.523307,48.115543],"type":"Point"}
}