{
  "type": "Feature",
  "properties": {
    "iso:country":"DE",
    "sg:address":"Anger 10",
    "sg:city":"Erfurt",
    "sg:phone":"+49 361/5669830",
    "sg:postcode":"99084",
    "sg:province":"Th\u00fcringen",
    "wof:name":"Nur Touristik",
    "wof:placetype":"venue"
},
  "geometry": {"coordinates":[11.0349702835,50.9764442444],"type":"Point"}
}