{
  "type": "Feature",
  "properties": {
    "iso:country":"DE",
    "sg:address":"Dunantstr. 125",
    "sg:city":"Kempen",
    "sg:phone":"+49 2152/1079",
    "sg:postcode":"47906",
    "sg:province":"Nordrhein-Westfalen",
    "wof:name":"Kurt Aretz Rechtsanwalt",
    "wof:placetype":"venue"
},
  "geometry": {"coordinates":[6.4053587914,51.3750724792],"type":"Point"}
}