{
  "type": "Feature",
  "properties": {
    "iso:country":"DE",
    "sg:address":"Herrenstr. 8",
    "sg:city":"Burgst\u00e4dt",
    "sg:phone":"+49 3724/2919",
    "sg:postcode":"09217",
    "sg:province":"Sachsen",
    "wof:name":"M. Ludewig",
    "wof:placetype":"venue"
},
  "geometry": {"coordinates":[12.8043193817,50.9201965332],"type":"Point"}
}