{
  "type": "Feature",
  "properties": {
    "iso:country":"DE",
    "sg:address":"Quergasse 4",
    "sg:city":"B\u00f6sdorf",
    "sg:postcode":"39359",
    "sg:province":"Sachsen-Anhalt",
    "wof:name":"Prometa Gmbh",
    "wof:placetype":"venue"
},
  "geometry": {"coordinates":[11.0730581284,52.4141273499],"type":"Point"}
}