{
  "type": "Feature",
  "properties": {
    "iso:country":"DE",
    "sg:address":"Kesselsdorfer Str. 60",
    "sg:city":"Dresden",
    "sg:phone":"+49 351/4121453",
    "sg:postcode":"01159",
    "sg:province":"Sachsen",
    "wof:name":"Gunter M\u00fcller",
    "wof:placetype":"venue"
},
  "geometry": {"coordinates":[13.6920900345,51.0429573059],"type":"Point"}
}