{
  "type": "Feature",
  "properties": {
    "iso:country":"DE",
    "sg:address":"Wimmerstr. 15",
    "sg:city":"M\u00fcnchen",
    "sg:phone":"+49 89/915054",
    "sg:postcode":"81927",
    "sg:province":"Bayern",
    "wof:name":"Nathan Kalmanovicz Ingenieur",
    "wof:placetype":"venue"
},
  "geometry": {"coordinates":[11.6316642761,48.1527290344],"type":"Point"}
}