{
  "type": "Feature",
  "properties": {
    "iso:country":"DE",
    "sg:address":"Poststr. 59",
    "sg:city":"Bad Berleburg",
    "sg:phone":"+49 2751/92620",
    "sg:postcode":"57319",
    "sg:province":"Nordrhein-Westfalen",
    "wof:name":"Schlabach Beteiligungs- Gmbh",
    "wof:placetype":"venue"
},
  "geometry": {"coordinates":[8.393724,51.055134],"type":"Point"}
}